"type";"unit_name";"on_building";"total_supply";"supply"
"Unit";"Overlord";"Larva";13;0
"Building";"Extractor";NA;17;0
"Unit";"Overlord";"Larva";21;0
"Building";"SpawningPool";NA;17;0
"Building";"Hatchery";NA;17;0
"Unit";"Zergling";"Larva";22;1
"Unit";"Zergling";"Larva";22;1
"Unit";"Zergling";"Larva";25;1
"Unit";"Zergling";"Larva";25;1
"Unit";"Queen";"Hatchery";22;2
"Unit";"Queen";"Hatchery";23;2
"Unit";"Overlord";"Larva";37;0
"Unit";"Queen";"Hatchery";35;2
"Unit";"Zergling";"Larva";37;1
"Unit";"Zergling";"Larva";37;1
"Unit";"Zergling";"Larva";39;1
"Unit";"Zergling";"Larva";39;1
"Unit";"Overlord";"Larva";39;0
"Building";"Hatchery";NA;31;0
"Building";"CreepTumorQueen";NA;51;0
"Building";"RoachWarren";NA;41;0
"Building";"CreepTumorQueen";NA;51;0
"Building";"Extractor";NA;51;0
"Building";"Extractor";NA;51;0
"Unit";"Overlord";"Larva";58;0
"Unit";"Queen";"Hatchery";51;2
"Unit";"Overlord";"Larva";58;0
"Unit";"Overlord";"Larva";58;0
"Unit";"Overlord";"Larva";58;0
"Building";"CreepTumorQueen";NA;63;0
"Unit";"Overlord";"Larva";63;0
"Unit";"Roach";"Larva";67;2
"Building";"CreepTumor";NA;72;0
"Building";"CreepTumor";NA;72;0
"Unit";"Overlord";"Larva";70;0
"Unit";"Roach";"Larva";71;2
"Unit";"Roach";"Larva";71;2
"Unit";"Roach";"Larva";72;2
"Unit";"Roach";"Larva";72;2
"Unit";"Roach";"Larva";72;2
"Unit";"Roach";"Larva";72;2
"Unit";"Roach";"Larva";78;2
"Building";"CreepTumor";NA;82;0
"Unit";"Roach";"Larva";78;2
"Unit";"Roach";"Larva";78;2
"Building";"Extractor";NA;78;0
"Building";"CreepTumor";NA;86;0
"Unit";"Roach";"Larva";82;2
"Unit";"Roach";"Larva";82;2
"Unit";"Zergling";"Larva";88;1
"Unit";"Zergling";"Larva";88;1
"Unit";"Roach";"Larva";88;2
"Unit";"Roach";"Larva";88;2
"Unit";"Roach";"Larva";88;2
"Unit";"Roach";"Larva";88;2
"Unit";"Roach";"Larva";88;2
"Unit";"Roach";"Larva";88;2
"Unit";"Overlord";"Larva";98;0
"Unit";"Overlord";"Larva";98;0
"Unit";"Overlord";"Larva";98;0
"Unit";"Roach";"Larva";112;2
"Unit";"Roach";"Larva";112;2
"Unit";"Roach";"Larva";112;2
"Unit";"Roach";"Larva";112;2
"Unit";"Roach";"Larva";112;2
"Unit";"Roach";"Larva";112;2
"Unit";"Roach";"Larva";112;2
"Unit";"Roach";"Larva";112;2
"Unit";"Roach";"Larva";112;2
"Upgrade";"GlialReconstitution";"RoachWarren";88;0
"Unit";"Roach";"Larva";112;2
"Unit";"Overlord";"Larva";130;0
"Unit";"Queen";"Hatchery";112;2
"Unit";"Overlord";"Larva";139;0
"Unit";"Overlord";"Larva";139;0
"Unit";"Overlord";"Larva";139;0
"Unit";"Overlord";"Larva";139;0
"Building";"EvolutionChamber";NA;139;0
"Building";"Extractor";NA;143;0
"Unit";"Zergling";"Larva";146;1
"Unit";"Zergling";"Larva";146;1
"Unit";"Zergling";"Larva";146;1
"Unit";"Zergling";"Larva";146;1
"Unit";"Zergling";"Larva";146;1
"Unit";"Zergling";"Larva";146;1
"Unit";"Zergling";"Larva";146;1
"Unit";"Zergling";"Larva";146;1
"Unit";"Zergling";"Larva";146;1
"Unit";"Zergling";"Larva";146;1
"Unit";"Zergling";"Larva";146;1
"Unit";"Zergling";"Larva";146;1
"Unit";"Roach";"Larva";146;2
"Unit";"Roach";"Larva";146;2
"Unit";"Roach";"Larva";146;2
"Unit";"Roach";"Larva";146;2
"Unit";"Roach";"Larva";146;2
"Unit";"Overlord";"Larva";146;0
"Unit";"Overlord";"Larva";146;0
"Unit";"Queen";"Hatchery";143;2
"Unit";"Roach";"Larva";146;2
"Unit";"Roach";"Larva";146;2
"Unit";"Roach";"Larva";146;2
"Unit";"Roach";"Larva";146;2
"Unit";"Overlord";"Larva";168;0
"Unit";"Overlord";"Larva";168;0
"Unit";"Overlord";"Larva";168;0
"Unit";"Roach";"Larva";178;2
"Unit";"Roach";"Larva";178;2
"Unit";"Roach";"Larva";178;2
"Unit";"Roach";"Larva";178;2
"Unit";"Roach";"Larva";178;2
"Unit";"Roach";"Larva";178;2
"Unit";"Roach";"Larva";178;2
"Unit";"Roach";"Larva";178;2
"Unit";"Roach";"Larva";178;2
"Unit";"Roach";"Larva";178;2
"Unit";"Roach";"Larva";178;2
"Unit";"Roach";"Larva";178;2
"Building";"Hatchery";NA;146;0
"Unit";"Roach";"Larva";202;2
"Unit";"Roach";"Larva";202;2
"Unit";"Roach";"Larva";202;2
"Unit";"Roach";"Larva";202;2
"Unit";"Roach";"Larva";202;2
"Unit";"Roach";"Larva";202;2
"Unit";"Roach";"Larva";202;2
"Unit";"Roach";"Larva";202;2
"Unit";"Roach";"Larva";202;2
"Unit";"Roach";"Larva";202;2
"Unit";"Roach";"Larva";202;2
"Unit";"Roach";"Larva";202;2
"Unit";"Roach";"Larva";202;2
"Unit";"Roach";"Larva";202;2
"Unit";"Roach";"Larva";202;2
"Unit";"Roach";"Larva";202;2
"Unit";"Roach";"Larva";202;2
"Unit";"Roach";"Larva";236;2
"Unit";"Roach";"Larva";236;2
"Unit";"Roach";"Larva";236;2
"Unit";"Roach";"Larva";236;2
"Unit";"Roach";"Larva";236;2
"Unit";"Roach";"Larva";236;2
"Unit";"Roach";"Larva";236;2
"Unit";"Roach";"Larva";236;2
"Unit";"Roach";"Larva";236;2
"Unit";"Roach";"Larva";236;2
"Unit";"Roach";"Larva";238;2
"Unit";"Roach";"Larva";240;2
"Unit";"Roach";"Larva";240;2
"Unit";"Roach";"Larva";244;2
"Unit";"Roach";"Larva";244;2
"Unit";"Roach";"Larva";248;2
"Unit";"Roach";"Larva";254;2
"Unit";"Roach";"Larva";254;2
"Unit";"Roach";"Larva";254;2
"Unit";"Roach";"Larva";254;2
"Unit";"Roach";"Larva";254;2
"Unit";"Roach";"Larva";254;2
"Unit";"Roach";"Larva";254;2
"Unit";"Roach";"Larva";268;2
"Unit";"Roach";"Larva";268;2
"Unit";"Roach";"Larva";268;2
"Unit";"Roach";"Larva";268;2
"Unit";"Roach";"Larva";268;2
"Unit";"Roach";"Larva";268;2
"Unit";"Roach";"Larva";268;2
"Unit";"Roach";"Larva";282;2
"Unit";"Roach";"Larva";282;2
"Unit";"Roach";"Larva";282;2
"Unit";"Roach";"Larva";282;2
"Unit";"Roach";"Larva";282;2
"Unit";"Roach";"Larva";296;2
"Unit";"Roach";"Larva";298;2
"Unit";"Roach";"Larva";298;2
"Unit";"Roach";"Larva";298;2
"Unit";"Roach";"Larva";298;2
"Unit";"Roach";"Larva";298;2
"Unit";"Roach";"Larva";306;2
"Unit";"Roach";"Larva";306;2
"Unit";"Roach";"Larva";306;2
"Unit";"Roach";"Larva";306;2
"Unit";"Roach";"Larva";306;2
"Unit";"Roach";"Larva";306;2
"Unit";"Roach";"Larva";306;2
"Unit";"Roach";"Larva";306;2
