"type";"unit_name";"on_building";"total_supply_lag";"supply"
"Unit";"Overlord";"Larva";13;0
"Building";"Hatchery";NA;16;0
"Building";"Extractor";NA;19;0
"Building";"SpawningPool";NA;19;0
"Unit";"Overlord";"Larva";23;0
"Unit";"Queen";"Hatchery";23;2
"Unit";"Queen";"Hatchery";25;2
"Unit";"Zergling";"Larva";27;1
"Unit";"Zergling";"Larva";28;1
"Unit";"Zergling";"Larva";29;1
"Unit";"Zergling";"Larva";30;1
"Building";"Hatchery";NA;36;0
"Building";"CreepTumorQueen";NA;36;0
"Unit";"Queen";"Hatchery";36;2
"Unit";"Overlord";"Larva";39;0
"Building";"CreepTumor";NA;42;0
"Building";"CreepTumorQueen";NA;47;0
"Unit";"Overlord";"Larva";47;0
"Unit";"Queen";"Hatchery";47;2
"Unit";"Overlord";"Larva";50;0
"Building";"CreepTumorQueen";NA;55;0
"Building";"CreepTumor";NA;55;0
"Building";"CreepTumor";NA;55;0
"Unit";"Overlord";"Larva";57;0
"Building";"SporeCrawler";NA;60;0
"Building";"Extractor";NA;60;0
"Building";"SporeCrawler";NA;62;0
"Unit";"Zergling";"Larva";62;1
"Unit";"Zergling";"Larva";63;1
"Building";"Extractor";NA;64;0
"Unit";"Overlord";"Larva";64;0
"Unit";"Zergling";"Larva";64;1
"Unit";"Zergling";"Larva";65;1
"Unit";"Zergling";"Larva";66;1
"Unit";"Zergling";"Larva";67;1
"Unit";"Zergling";"Larva";68;1
"Unit";"Zergling";"Larva";69;1
"Unit";"Zergling";"Larva";70;1
"Unit";"Zergling";"Larva";71;1
"Unit";"Overlord";"Larva";72;0
"Building";"Extractor";NA;72;0
"Building";"CreepTumor";NA;76;0
"Building";"CreepTumorQueen";NA;76;0
"Building";"CreepTumor";NA;76;0
"Building";"HydraliskDen";NA;81;0
"Unit";"Overlord";"Larva";81;0
"Unit";"Overlord";"Larva";82;0
"Unit";"Overlord";"Larva";86;0
"Unit";"Hydralisk";"Larva";86;2
"Unit";"Hydralisk";"Larva";88;2
"Unit";"Hydralisk";"Larva";90;2
"Unit";"Hydralisk";"Larva";92;2
"Unit";"Hydralisk";"Larva";94;2
"Unit";"Hydralisk";"Larva";96;2
"Unit";"Hydralisk";"Larva";98;2
"Unit";"Hydralisk";"Larva";100;2
"Unit";"Hydralisk";"Larva";102;2
"Unit";"Hydralisk";"Larva";104;2
"Unit";"Hydralisk";"Larva";106;2
"Building";"CreepTumor";NA;108;0
"Unit";"Hydralisk";"Larva";108;2
"Building";"CreepTumor";NA;110;0
"Unit";"Zergling";"Larva";110;1
"Unit";"Zergling";"Larva";111;1
"Unit";"Zergling";"Larva";112;1
"Unit";"Zergling";"Larva";113;1
"Unit";"Zergling";"Larva";114;1
"Unit";"Zergling";"Larva";115;1
"Unit";"Zergling";"Larva";116;1
"Unit";"Zergling";"Larva";117;1
"Unit";"Zergling";"Larva";118;1
"Unit";"Zergling";"Larva";119;1
"Unit";"Zergling";"Larva";120;1
"Unit";"Zergling";"Larva";121;1
"Building";"CreepTumor";NA;122;0
"Unit";"Overlord";"Larva";122;0
"Unit";"Hydralisk";"Larva";122;2
"Unit";"Hydralisk";"Larva";124;2
"Unit";"Hydralisk";"Larva";126;2
"Unit";"Hydralisk";"Larva";128;2
"Unit";"Zergling";"Larva";130;1
"Unit";"Zergling";"Larva";131;1
"Unit";"Zergling";"Larva";132;1
"Unit";"Zergling";"Larva";133;1
"Unit";"Zergling";"Larva";134;1
"Unit";"Zergling";"Larva";135;1
"Unit";"Hydralisk";"Larva";136;2
"Unit";"Zergling";"Larva";138;1
"Unit";"Zergling";"Larva";139;1
"Unit";"Zergling";"Larva";140;1
"Unit";"Zergling";"Larva";141;1
"Unit";"Zergling";"Larva";142;1
"Unit";"Zergling";"Larva";143;1
"Unit";"Zergling";"Larva";144;1
"Unit";"Zergling";"Larva";145;1
"Unit";"Hydralisk";"Larva";146;2
"Unit";"Overlord";"Larva";148;0
"Unit";"Hydralisk";"Larva";148;2
"Unit";"Zergling";"Larva";150;1
"Unit";"Zergling";"Larva";151;1
"Unit";"Overlord";"Larva";152;0
"Unit";"Hydralisk";"Larva";152;2
"Unit";"Hydralisk";"Larva";154;2
"Unit";"Hydralisk";"Larva";156;2
"Unit";"Hydralisk";"Larva";158;2
"Unit";"Hydralisk";"Larva";160;2
"Unit";"Hydralisk";"Larva";162;2
"Unit";"Hydralisk";"Larva";164;2
"Unit";"Zergling";"Larva";166;1
"Unit";"Zergling";"Larva";167;1
"Unit";"Zergling";"Larva";168;1
"Unit";"Zergling";"Larva";169;1
"Unit";"Zergling";"Larva";170;1
"Unit";"Zergling";"Larva";171;1
"Unit";"Zergling";"Larva";172;1
"Unit";"Zergling";"Larva";173;1
"Unit";"Zergling";"Larva";174;1
"Unit";"Zergling";"Larva";175;1
"Unit";"Zergling";"Larva";176;1
"Unit";"Zergling";"Larva";177;1
"Unit";"Zergling";"Larva";178;1
"Unit";"Zergling";"Larva";179;1
"Unit";"Zergling";"Larva";180;1
"Unit";"Zergling";"Larva";181;1
"Unit";"Zergling";"Larva";182;1
"Unit";"Zergling";"Larva";183;1
"Unit";"Zergling";"Larva";184;1
"Unit";"Zergling";"Larva";185;1
"Unit";"Zergling";"Larva";186;1
"Unit";"Zergling";"Larva";187;1
"Unit";"Zergling";"Larva";188;1
"Unit";"Zergling";"Larva";189;1
"Unit";"Zergling";"Larva";190;1
"Unit";"Zergling";"Larva";191;1
"Unit";"Overlord";"Larva";192;0
"Unit";"Overlord";"Larva";192;0
"Unit";"Overlord";"Larva";192;0
"Unit";"Zergling";"Larva";192;1
"Unit";"Zergling";"Larva";193;1
"Unit";"Zergling";"Larva";194;1
"Unit";"Zergling";"Larva";195;1
"Unit";"Zergling";"Larva";196;1
"Unit";"Zergling";"Larva";197;1
"Unit";"Zergling";"Larva";198;1
"Unit";"Zergling";"Larva";199;1
"Unit";"Zergling";"Larva";200;1
"Unit";"Zergling";"Larva";201;1
"Unit";"Zergling";"Larva";202;1
"Unit";"Zergling";"Larva";203;1
"Unit";"Zergling";"Larva";204;1
"Unit";"Zergling";"Larva";205;1
"Unit";"Zergling";"Larva";206;1
"Unit";"Zergling";"Larva";207;1
"Unit";"Zergling";"Larva";208;1
"Unit";"Zergling";"Larva";209;1
"Unit";"Zergling";"Larva";210;1
"Unit";"Zergling";"Larva";211;1
"Unit";"Zergling";"Larva";212;1
"Unit";"Zergling";"Larva";213;1
"Unit";"Zergling";"Larva";214;1
"Unit";"Zergling";"Larva";215;1
"Unit";"Zergling";"Larva";216;1
"Unit";"Zergling";"Larva";217;1
"Unit";"Zergling";"Larva";218;1
"Unit";"Zergling";"Larva";219;1
"Unit";"Zergling";"Larva";220;1
"Unit";"Zergling";"Larva";221;1
"Unit";"Zergling";"Larva";222;1
"Unit";"Zergling";"Larva";223;1
"Unit";"Zergling";"Larva";224;1
"Unit";"Zergling";"Larva";225;1
"Unit";"Hydralisk";"Larva";226;2
"Unit";"Hydralisk";"Larva";228;2
"Unit";"Hydralisk";"Larva";230;2
"Unit";"Hydralisk";"Larva";232;2
"Unit";"Hydralisk";"Larva";234;2
"Unit";"Hydralisk";"Larva";236;2
"Unit";"Hydralisk";"Larva";238;2
"Unit";"Hydralisk";"Larva";240;2
"Unit";"Zergling";"Larva";242;1
"Unit";"Zergling";"Larva";243;1
"Unit";"Zergling";"Larva";244;1
"Unit";"Zergling";"Larva";245;1
"Unit";"Zergling";"Larva";246;1
"Unit";"Zergling";"Larva";247;1
"Upgrade";"SprayZerg";NA;248;0
"Upgrade";"SprayZerg";NA;248;0
"Upgrade";"SprayZerg";NA;248;0
"Upgrade";"zerglingmovementspeed";NA;248;0
"Upgrade";"SprayZerg";NA;248;0
"Upgrade";"EvolveMuscularAugments";NA;248;0
