"type";"unit_name";"on_building";"total_supply_lag";"supply"
"Unit";"Overlord";"Larva";13;0
"Building";"Hatchery";NA;16;0
"Building";"Extractor";NA;19;0
"Building";"SpawningPool";NA;19;0
"Unit";"Overlord";"Larva";23;0
"Unit";"Queen";"Hatchery";23;2
"Unit";"Queen";"Hatchery";25;2
"Unit";"Zergling";"Larva";27;1
"Unit";"Zergling";"Larva";28;1
"Unit";"Zergling";"Larva";29;1
"Unit";"Zergling";"Larva";30;1
"Building";"Hatchery";NA;37;0
"Building";"CreepTumorQueen";NA;37;0
"Unit";"Queen";"Hatchery";37;2
"Unit";"Overlord";"Larva";39;0
"Unit";"Zergling";"Larva";39;1
"Unit";"Zergling";"Larva";40;1
"Unit";"Zergling";"Larva";41;1
"Unit";"Zergling";"Larva";42;1
"Unit";"Overlord";"Larva";43;0
"Building";"SporeCrawler";NA;51;0
"Building";"SporeCrawler";NA;52;0
"Unit";"Queen";"Hatchery";52;2
"Building";"CreepTumor";NA;56;0
"Building";"CreepTumorQueen";NA;59;0
"Unit";"Overlord";"Larva";66;0
"Building";"SporeCrawler";NA;66;0
"Building";"CreepTumor";NA;67;0
"Unit";"Overlord";"Larva";67;0
"Unit";"Queen";"Hatchery";67;2
"Building";"RoachWarren";NA;70;0
"Building";"CreepTumor";NA;72;0
"Building";"Extractor";NA;77;0
"Building";"Extractor";NA;77;0
"Unit";"Zergling";"Larva";79;1
"Unit";"Zergling";"Larva";80;1
"Unit";"Zergling";"Larva";81;1
"Unit";"Zergling";"Larva";82;1
"Unit";"Zergling";"Larva";83;1
"Unit";"Zergling";"Larva";84;1
"Unit";"Zergling";"Larva";85;1
"Unit";"Zergling";"Larva";86;1
"Unit";"Zergling";"Larva";87;1
"Unit";"Zergling";"Larva";88;1
"Unit";"Zergling";"Larva";89;1
"Unit";"Zergling";"Larva";90;1
"Building";"CreepTumor";NA;91;0
"Unit";"Zergling";"Larva";91;1
"Unit";"Zergling";"Larva";92;1
"Unit";"Zergling";"Larva";93;1
"Unit";"Zergling";"Larva";94;1
"Unit";"Overlord";"Larva";95;0
"Unit";"Overlord";"Larva";101;0
"Building";"CreepTumor";NA;104;0
"Unit";"Overlord";"Larva";106;0
"Unit";"Roach";"Larva";106;2
"Building";"CreepTumorQueen";NA;108;0
"Unit";"Roach";"Larva";108;2
"Unit";"Roach";"Larva";110;2
"Unit";"Roach";"Larva";112;2
"Unit";"Roach";"Larva";114;2
"Unit";"Roach";"Larva";116;2
"Unit";"Overlord";"Larva";118;0
"Upgrade";"GlialReconstitution";"RoachWarren";118;0
"Unit";"Roach";"Larva";118;2
"Unit";"Roach";"Larva";120;2
"Unit";"Roach";"Larva";122;2
"Unit";"Overlord";"Larva";124;0
"Unit";"Roach";"Larva";124;2
"Unit";"Roach";"Larva";126;2
"Unit";"Roach";"Larva";128;2
"Unit";"Roach";"Larva";130;2
"Unit";"Roach";"Larva";132;2
"Unit";"Overlord";"Larva";134;0
"Building";"EvolutionChamber";NA;134;0
"Building";"CreepTumor";NA;135;0
"Building";"CreepTumor";NA;135;0
"Unit";"Overlord";"Larva";135;0
"Building";"Extractor";NA;145;0
"Building";"InfestationPit";NA;145;0
"Unit";"Overlord";"Larva";145;0
"Building";"CreepTumor";NA;148;0
"Unit";"Overlord";"Larva";148;0
"Unit";"Overlord";"Larva";150;0
"Unit";"Overlord";"Larva";150;0
"Building";"Extractor";NA;156;0
"Building";"Extractor";NA;156;0
"Building";"CreepTumorQueen";NA;156;0
"Building";"CreepTumor";NA;156;0
"Unit";"Overlord";"Larva";156;0
"Unit";"Roach";"Larva";156;2
"Unit";"Roach";"Larva";158;2
"Unit";"Roach";"Larva";160;2
"Unit";"Roach";"Larva";162;2
"Unit";"Roach";"Larva";164;2
"Building";"CreepTumorQueen";NA;166;0
"Building";"Hatchery";NA;166;0
"Building";"CreepTumorQueen";NA;171;0
"Unit";"Overlord";"Larva";171;0
"Building";"CreepTumor";NA;171;0
"Building";"CreepTumor";NA;171;0
"Unit";"Overlord";"Larva";171;0
"Unit";"Overlord";"Larva";171;0
"Unit";"Overlord";"Larva";171;0
"Unit";"Overlord";"Larva";171;0
"Unit";"Overlord";"Larva";171;0
"Unit";"Roach";"Larva";171;2
"Unit";"Roach";"Larva";173;2
"Unit";"Roach";"Larva";175;2
"Unit";"Roach";"Larva";177;2
"Unit";"Roach";"Larva";179;2
"Unit";"Roach";"Larva";181;2
"Unit";"Roach";"Larva";183;2
"Unit";"Roach";"Larva";185;2
"Unit";"Roach";"Larva";187;2
"Unit";"Roach";"Larva";189;2
"Unit";"Roach";"Larva";191;2
"Unit";"Roach";"Larva";193;2
"Unit";"Roach";"Larva";195;2
"Unit";"Roach";"Larva";197;2
"Unit";"Roach";"Larva";199;2
"Unit";"Roach";"Larva";201;2
"Unit";"Roach";"Larva";203;2
"Unit";"Roach";"Larva";205;2
"Unit";"Roach";"Larva";207;2
"Unit";"Roach";"Larva";209;2
"Unit";"Roach";"Larva";211;2
"Unit";"Roach";"Larva";213;2
"Unit";"Roach";"Larva";215;2
"Unit";"Roach";"Larva";217;2
"Unit";"Roach";"Larva";219;2
"Unit";"Roach";"Larva";221;2
"Unit";"Roach";"Larva";223;2
"Unit";"Roach";"Larva";225;2
"Unit";"Roach";"Larva";227;2
"Unit";"Roach";"Larva";229;2
"Unit";"Roach";"Larva";231;2
"Unit";"Roach";"Larva";233;2
"Unit";"Roach";"Larva";235;2
"Unit";"Roach";"Larva";237;2
"Unit";"Roach";"Larva";239;2
"Unit";"Roach";"Larva";241;2
"Unit";"Roach";"Larva";243;2
"Unit";"Roach";"Larva";245;2
"Unit";"Roach";"Larva";247;2
"Unit";"Roach";"Larva";249;2
"Unit";"Roach";"Larva";251;2
"Unit";"Roach";"Larva";253;2
"Unit";"Roach";"Larva";255;2
"Unit";"Roach";"Larva";257;2
"Unit";"Roach";"Larva";259;2
"Unit";"Roach";"Larva";261;2
"Unit";"Roach";"Larva";263;2
"Unit";"Roach";"Larva";265;2
"Unit";"Roach";"Larva";267;2
"Unit";"Roach";"Larva";269;2
"Unit";"Roach";"Larva";271;2
"Unit";"Roach";"Larva";273;2
"Unit";"Roach";"Larva";275;2
"Unit";"Roach";"Larva";277;2
"Unit";"Roach";"Larva";279;2
"Unit";"Roach";"Larva";281;2
"Unit";"Roach";"Larva";283;2
"Unit";"Roach";"Larva";285;2
"Unit";"Roach";"Larva";287;2
"Unit";"Roach";"Larva";289;2
"Unit";"Roach";"Larva";291;2
"Unit";"Roach";"Larva";293;2
"Unit";"Roach";"Larva";295;2
"Unit";"Roach";"Larva";297;2
"Unit";"Roach";"Larva";299;2
"Unit";"Roach";"Larva";301;2
"Unit";"Roach";"Larva";303;2
"Unit";"Roach";"Larva";305;2
"Unit";"Roach";"Larva";307;2
"Unit";"Roach";"Larva";309;2
"Unit";"Roach";"Larva";311;2
"Unit";"Roach";"Larva";313;2
"Unit";"Roach";"Larva";315;2
"Unit";"Roach";"Larva";317;2
"Unit";"Roach";"Larva";319;2
"Unit";"Roach";"Larva";321;2
"Unit";"Roach";"Larva";323;2
"Upgrade";"SprayZerg";NA;325;0
"Upgrade";"SprayZerg";NA;325;0
"Upgrade";"SprayZerg";NA;325;0
"Upgrade";"zerglingmovementspeed";NA;325;0
"Upgrade";"SprayZerg";NA;325;0
"Upgrade";"SprayZerg";NA;325;0
"Upgrade";"SprayZerg";NA;325;0
"Upgrade";"ZergMissileWeaponsLevel1";NA;325;0
