"type";"unit_name";"on_building";"total_supply";"supply"
"Unit";"Overlord";"Larva";13;0
"Building";"Extractor";NA;24;0
"Unit";"Overlord";"Larva";25;0
"Building";"Hatchery";NA;21;0
"Building";"SpawningPool";NA;24;0
"Unit";"Zergling";"Larva";26;1
"Unit";"Zergling";"Larva";26;1
"Unit";"Zergling";"Larva";26;1
"Unit";"Zergling";"Larva";26;1
"Unit";"Zergling";"Larva";26;1
"Unit";"Zergling";"Larva";26;1
"Unit";"Zergling";"Larva";26;1
"Unit";"Zergling";"Larva";26;1
"Unit";"Zergling";"Larva";26;1
"Unit";"Zergling";"Larva";26;1
"Unit";"Zergling";"Larva";26;1
"Unit";"Zergling";"Larva";26;1
"Unit";"Zergling";"Larva";26;1
"Unit";"Zergling";"Larva";26;1
"Unit";"Queen";"Hatchery";26;2
"Unit";"Queen";"Hatchery";26;2
"Building";"RoachWarren";NA;26;0
"Unit";"Overlord";"Larva";50;0
"Unit";"Overlord";"Larva";50;0
"Unit";"Overlord";"Larva";50;0
"Unit";"Roach";"Larva";50;2
"Unit";"Roach";"Larva";50;2
"Unit";"Roach";"Larva";50;2
"Unit";"Roach";"Larva";50;2
"Unit";"Roach";"Larva";50;2
"Unit";"Roach";"Larva";50;2
"Unit";"Roach";"Larva";50;2
"Unit";"Roach";"Larva";50;2
"Unit";"Zergling";"Larva";50;1
"Unit";"Zergling";"Larva";50;1
"Unit";"Zergling";"Larva";60;1
"Unit";"Zergling";"Larva";60;1
"Building";"Hatchery";NA;46;0
"Unit";"Zergling";"Larva";64;1
"Unit";"Zergling";"Larva";64;1
"Unit";"Zergling";"Larva";64;1
"Unit";"Zergling";"Larva";64;1
"Unit";"Zergling";"Larva";64;1
"Unit";"Zergling";"Larva";64;1
"Unit";"Overlord";"Larva";66;0
"Unit";"Overlord";"Larva";68;0
"Unit";"Overlord";"Larva";68;0
"Unit";"Queen";"Hatchery";76;2
"Building";"EvolutionChamber";NA;93;0
"Building";"Extractor";NA;105;0
"Building";"Extractor";NA;105;0
"Unit";"Overlord";"Larva";109;0
"Unit";"Overlord";"Larva";112;0
"Building";"Extractor";NA;113;0
"Building";"Extractor";NA;113;0
"Unit";"Overlord";"Larva";116;0
"Building";"Extractor";NA;116;0
"Unit";"Zergling";"Larva";116;1
"Unit";"Zergling";"Larva";116;1
"Unit";"Zergling";"Larva";116;1
"Unit";"Zergling";"Larva";116;1
"Unit";"Zergling";"Larva";116;1
"Unit";"Zergling";"Larva";116;1
"Unit";"Zergling";"Larva";116;1
"Unit";"Zergling";"Larva";116;1
"Unit";"Zergling";"Larva";116;1
"Unit";"Zergling";"Larva";116;1
"Unit";"Zergling";"Larva";116;1
"Unit";"Zergling";"Larva";116;1
"Unit";"Zergling";"Larva";116;1
"Unit";"Zergling";"Larva";116;1
"Unit";"Zergling";"Larva";116;1
"Unit";"Zergling";"Larva";116;1
"Unit";"Zergling";"Larva";116;1
"Unit";"Zergling";"Larva";116;1
"Unit";"Zergling";"Larva";116;1
"Unit";"Zergling";"Larva";116;1
"Unit";"Zergling";"Larva";116;1
"Unit";"Zergling";"Larva";116;1
"Building";"HydraliskDen";NA;116;0
"Building";"SporeCrawler";NA;143;0
"Unit";"Queen";"Hatchery";143;2
"Unit";"Queen";"Hatchery";143;2
"Unit";"Queen";"Hatchery";143;2
"Unit";"Hydralisk";"Larva";143;2
"Unit";"Hydralisk";"Larva";143;2
"Unit";"Hydralisk";"Larva";143;2
"Unit";"Hydralisk";"Larva";143;2
"Unit";"Hydralisk";"Larva";143;2
"Upgrade";"ZergMissileWeaponsLevel1";"EvolutionChamber";116;0
"Unit";"Hydralisk";"Larva";143;2
"Unit";"Hydralisk";"Larva";143;2
"Unit";"Hydralisk";"Larva";143;2
"Upgrade";"GlialReconstitution";"RoachWarren";143;0
"Building";"Hatchery";NA;116;0
"Building";"Hatchery";NA;121;0
"Unit";"Overlord";"Larva";173;0
"Unit";"Overlord";"Larva";183;0
"Unit";"Overlord";"Larva";183;0
"Unit";"Overlord";"Larva";183;0
"Unit";"Hydralisk";"Larva";181;2
"Unit";"Hydralisk";"Larva";182;2
"Unit";"Hydralisk";"Larva";183;2
"Unit";"Overlord";"Larva";183;0
"Unit";"Overlord";"Larva";183;0
"Unit";"Hydralisk";"Larva";183;2
"Upgrade";"EvolveGroovedSpines";"HydraliskDen";172;0
"Unit";"Hydralisk";"Larva";183;2
"Unit";"Overlord";"Larva";183;0
"Unit";"Hydralisk";"Larva";183;2
"Unit";"Hydralisk";"Larva";183;2
"Unit";"Overlord";"Larva";183;0
"Unit";"Hydralisk";"Larva";189;2
"Unit";"Hydralisk";"Larva";189;2
"Unit";"Hydralisk";"Larva";189;2
"Unit";"Hydralisk";"Larva";191;2
"Unit";"Hydralisk";"Larva";193;2
"Unit";"Roach";"Larva";195;2
"Unit";"Roach";"Larva";197;2
"Unit";"Roach";"Larva";197;2
"Unit";"Roach";"Larva";199;2
"Unit";"Roach";"Larva";199;2
"Unit";"Roach";"Larva";199;2
"Unit";"Roach";"Larva";199;2
"Unit";"Roach";"Larva";199;2
"Unit";"Roach";"Larva";199;2
"Unit";"Roach";"Larva";199;2
"Unit";"Roach";"Larva";199;2
"Unit";"Overlord";"Larva";205;0
"Building";"Extractor";NA;215;0
"Building";"Extractor";NA;215;0
"Unit";"Roach";"Larva";215;2
"Unit";"Roach";"Larva";215;2
"Unit";"Roach";"Larva";215;2
"Unit";"Overlord";"Larva";215;0
"Unit";"Roach";"Larva";234;2
"Unit";"Roach";"Larva";235;2
"Unit";"Roach";"Larva";235;2
"Unit";"Roach";"Larva";237;2
"Unit";"Roach";"Larva";237;2
"Unit";"Roach";"Larva";237;2
"Unit";"Roach";"Larva";237;2
"Unit";"Roach";"Larva";237;2
"Unit";"Roach";"Larva";237;2
"Upgrade";"EvolveMuscularAugments";"HydraliskDen";199;0
"Upgrade";"ZergMissileWeaponsLevel2";"EvolutionChamber";183;0
"Unit";"Roach";"Larva";261;2
"Unit";"Roach";"Larva";261;2
"Unit";"Roach";"Larva";261;2
"Unit";"Roach";"Larva";261;2
"Unit";"Roach";"Larva";261;2
"Unit";"Roach";"Larva";261;2
"Unit";"Roach";"Larva";261;2
"Unit";"Roach";"Larva";261;2
"Unit";"Queen";"Hatchery";247;2
"Building";"InfestationPit";NA;261;0
"Building";"CreepTumorQueen";NA;279;0
"Unit";"Overlord";"Larva";279;0
"Unit";"Overlord";"Larva";279;0
"Unit";"Overlord";"Larva";279;0
"Unit";"Overlord";"Larva";279;0
"Unit";"Overlord";"Larva";279;0
"Unit";"Overlord";"Larva";279;0
"Unit";"Hydralisk";"Larva";279;2
