"type";"unit_name";"on_building";"total_supply";"supply"
"Unit";"Overlord";"Larva";13;0
"Building";"Extractor";NA;18;0
"Unit";"Overlord";"Larva";21;0
"Building";"SpawningPool";NA;19;0
"Building";"Hatchery";NA;17;0
"Unit";"Zergling";"Larva";22;1
"Unit";"Zergling";"Larva";22;1
"Unit";"Zergling";"Larva";22;1
"Unit";"Zergling";"Larva";22;1
"Unit";"Queen";"Hatchery";22;2
"Unit";"Queen";"Hatchery";22;2
"Building";"CreepTumorQueen";NA;35;0
"Unit";"Overlord";"Larva";35;0
"Unit";"Queen";"Hatchery";35;2
"Building";"CreepTumorQueen";NA;37;0
"Building";"CreepTumor";NA;37;0
"Unit";"Overlord";"Larva";37;0
"Building";"Hatchery";NA;32;0
"Unit";"Overlord";"Larva";42;0
"Unit";"Overlord";"Larva";42;0
"Building";"CreepTumor";NA;47;0
"Unit";"Queen";"Hatchery";42;2
"Building";"SporeCrawler";NA;48;0
"Building";"SporeCrawler";NA;48;0
"Building";"CreepTumorQueen";NA;53;0
"Building";"CreepTumor";NA;53;0
"Building";"Extractor";NA;50;0
"Building";"Extractor";NA;50;0
"Unit";"Overlord";"Larva";58;0
"Building";"RoachWarren";NA;50;0
"Building";"CreepTumor";NA;63;0
"Building";"CreepTumor";NA;66;0
"Building";"CreepTumorQueen";NA;69;0
"Building";"CreepTumor";NA;67;0
"Unit";"Roach";"Larva";70;2
"Unit";"Roach";"Larva";70;2
"Unit";"Roach";"Larva";70;2
"Unit";"Roach";"Larva";70;2
"Unit";"Roach";"Larva";70;2
"Unit";"Roach";"Larva";70;2
"Unit";"Roach";"Larva";70;2
"Unit";"Overlord";"Larva";70;0
"Unit";"Overlord";"Larva";70;0
"Unit";"Roach";"Larva";70;2
"Building";"CreepTumor";NA;70;0
"Unit";"Zergling";"Larva";72;1
"Unit";"Zergling";"Larva";72;1
"Unit";"Zergling";"Larva";84;1
"Unit";"Zergling";"Larva";84;1
"Unit";"Zergling";"Larva";84;1
"Unit";"Zergling";"Larva";84;1
"Unit";"Zergling";"Larva";84;1
"Unit";"Zergling";"Larva";84;1
"Unit";"Zergling";"Larva";84;1
"Unit";"Zergling";"Larva";84;1
"Unit";"Zergling";"Larva";84;1
"Unit";"Zergling";"Larva";84;1
"Unit";"Zergling";"Larva";84;1
"Unit";"Zergling";"Larva";84;1
"Unit";"Zergling";"Larva";84;1
"Unit";"Zergling";"Larva";84;1
"Building";"CreepTumor";NA;84;0
"Building";"CreepTumorQueen";NA;84;0
"Building";"EvolutionChamber";NA;72;0
"Upgrade";"GlialReconstitution";"RoachWarren";86;0
"Building";"Extractor";NA;118;0
"Unit";"Overlord";"Larva";118;0
"Unit";"Overlord";"Larva";118;0
"Building";"CreepTumor";NA;121;0
"Building";"CreepTumor";NA;121;0
"Building";"SporeCrawler";NA;118;0
"Building";"CreepTumor";NA;122;0
"Building";"CreepTumor";NA;124;0
"Building";"Extractor";NA;122;0
"Unit";"Roach";"Larva";124;2
"Unit";"Roach";"Larva";124;2
"Unit";"Roach";"Larva";124;2
"Unit";"Roach";"Larva";124;2
"Unit";"Roach";"Larva";124;2
"Unit";"Roach";"Larva";124;2
"Unit";"Roach";"Larva";124;2
"Unit";"Roach";"Larva";124;2
"Unit";"Overlord";"Larva";124;0
"Unit";"Overlord";"Larva";124;0
"Unit";"Overlord";"Larva";124;0
"Building";"CreepTumor";NA;125;0
"Building";"HydraliskDen";NA;124;0
"Building";"CreepTumor";NA;125;0
"Building";"CreepTumor";NA;125;0
"Building";"CreepTumor";NA;141;0
"Unit";"Zergling";"Larva";141;1
"Unit";"Zergling";"Larva";141;1
"Unit";"Zergling";"Larva";141;1
"Unit";"Zergling";"Larva";141;1
"Unit";"Zergling";"Larva";141;1
"Unit";"Zergling";"Larva";141;1
"Unit";"Zergling";"Larva";141;1
"Unit";"Zergling";"Larva";141;1
"Unit";"Zergling";"Larva";141;1
"Unit";"Zergling";"Larva";141;1
"Unit";"Zergling";"Larva";141;1
"Unit";"Zergling";"Larva";141;1
"Unit";"Zergling";"Larva";141;1
"Unit";"Zergling";"Larva";141;1
"Unit";"Zergling";"Larva";141;1
"Unit";"Zergling";"Larva";141;1
"Unit";"Zergling";"Larva";141;1
"Unit";"Zergling";"Larva";141;1
"Building";"Extractor";NA;141;0
"Building";"CreepTumor";NA;165;0
"Building";"Hatchery";NA;124;0
"Building";"Hatchery";NA;124;0
"Upgrade";"ZergMissileWeaponsLevel1";"EvolutionChamber";124;0
"Unit";"Overlord";"Larva";165;0
"Unit";"Overlord";"Larva";165;0
"Unit";"Overlord";"Larva";165;0
"Unit";"Overlord";"Larva";165;0
"Upgrade";"EvolveGroovedSpines";"HydraliskDen";165;0
"Building";"InfestationPit";NA;165;0
"Unit";"Overlord";"Larva";188;0
"Building";"Extractor";NA;188;0
"Building";"Extractor";NA;188;0
"Building";"CreepTumor";NA;196;0
"Building";"CreepTumor";NA;196;0
"Unit";"Hydralisk";"Larva";191;2
"Unit";"Hydralisk";"Larva";196;2
"Unit";"Hydralisk";"Larva";196;2
"Unit";"Hydralisk";"Larva";196;2
"Unit";"Hydralisk";"Larva";196;2
"Unit";"Hydralisk";"Larva";196;2
"Unit";"Hydralisk";"Larva";196;2
"Unit";"Hydralisk";"Larva";196;2
"Building";"CreepTumor";NA;197;0
"Building";"CreepTumor";NA;197;0
"Building";"SporeCrawler";NA;196;0
"Unit";"Hydralisk";"Larva";197;2
"Unit";"Hydralisk";"Larva";197;2
"Unit";"Hydralisk";"Larva";197;2
"Unit";"Hydralisk";"Larva";197;2
"Building";"LurkerDenMP";NA;172;0
"Building";"SpineCrawler";NA;196;0
"Building";"SpineCrawler";NA;197;0
"Building";"SpineCrawler";NA;197;0
"Building";"SpineCrawler";NA;197;0
"Unit";"Hydralisk";"Larva";213;2
"Unit";"Hydralisk";"Larva";213;2
"Unit";"Hydralisk";"Larva";213;2
"Unit";"Hydralisk";"Larva";213;2
"Unit";"Hydralisk";"Larva";213;2
"Unit";"Hydralisk";"Larva";213;2
"Building";"CreepTumor";NA;221;0
"Unit";"Overlord";"Larva";221;0
"Unit";"Overlord";"Larva";221;0
"Unit";"Overlord";"Larva";221;0
"Upgrade";"EvolveMuscularAugments";"HydraliskDen";196;0
"Building";"Spire";NA;188;0
"Unit";"Hydralisk";"Larva";221;2
"Unit";"Hydralisk";"Larva";221;2
"Unit";"Hydralisk";"Larva";221;2
"Unit";"Hydralisk";"Larva";221;2
"Unit";"Hydralisk";"Larva";221;2
"Unit";"Hydralisk";"Larva";221;2
"Building";"CreepTumorQueen";NA;233;0
"Building";"CreepTumorQueen";NA;233;0
"Building";"CreepTumorQueen";NA;233;0
"Unit";"Overlord";"Larva";233;0
"Unit";"Overlord";"Larva";233;0
"Unit";"Overlord";"Larva";233;0
"Building";"Hatchery";NA;213;0
"Unit";"Roach";"Larva";245;2
"Unit";"Roach";"Larva";245;2
"Unit";"Roach";"Larva";245;2
"Unit";"Roach";"Larva";245;2
"Unit";"Roach";"Larva";245;2
"Unit";"Hydralisk";"Larva";245;2
"Unit";"Hydralisk";"Larva";245;2
"Unit";"Hydralisk";"Larva";245;2
"Unit";"Hydralisk";"Larva";245;2
"Unit";"Roach";"Larva";245;2
"Unit";"Roach";"Larva";245;2
"Unit";"Roach";"Larva";245;2
"Unit";"Roach";"Larva";249;2
"Unit";"Roach";"Larva";251;2
"Unit";"Roach";"Larva";253;2
"Unit";"Hydralisk";"Larva";245;2
"Unit";"Hydralisk";"Larva";245;2
"Unit";"Hydralisk";"Larva";245;2
"Unit";"Hydralisk";"Larva";249;2
"Unit";"Hydralisk";"Larva";251;2
