"type";"unit_name";"on_building";"total_supply";"supply"
"Building";"Extractor";NA;13;0
"Unit";"Overlord";"Larva";15;0
"Building";"SpawningPool";NA;13;0
"Unit";"Zergling";"Larva";16;1
"Unit";"Zergling";"Larva";16;1
"Unit";"Zergling";"Larva";16;1
"Unit";"Zergling";"Larva";16;1
"Unit";"Zergling";"Larva";16;1
"Unit";"Zergling";"Larva";16;1
"Unit";"Queen";"Hatchery";16;2
"Unit";"Overlord";"Larva";25;0
"Building";"Hatchery";NA;26;0
"Unit";"Overlord";"Larva";35;0
"Building";"CreepTumorQueen";NA;36;0
"Unit";"Queen";"Hatchery";34;2
"Unit";"Zergling";"Larva";39;1
"Unit";"Zergling";"Larva";39;1
"Unit";"Zergling";"Larva";39;1
"Unit";"Zergling";"Larva";39;1
"Unit";"Overlord";"Larva";43;0
"Building";"Hatchery";NA;34;0
"Building";"CreepTumor";NA;51;0
"Unit";"Zergling";"Larva";51;1
"Unit";"Zergling";"Larva";51;1
"Unit";"Zergling";"Larva";51;1
"Unit";"Zergling";"Larva";51;1
"Unit";"Queen";"Hatchery";51;2
"Unit";"Zergling";"Larva";61;1
"Unit";"Zergling";"Larva";61;1
"Unit";"Zergling";"Larva";61;1
"Unit";"Zergling";"Larva";61;1
"Building";"CreepTumor";NA;61;0
"Unit";"Overlord";"Larva";61;0
"Unit";"Queen";"Hatchery";53;2
"Unit";"Zergling";"Larva";65;1
"Unit";"Zergling";"Larva";65;1
"Unit";"Zergling";"Larva";65;1
"Unit";"Zergling";"Larva";65;1
"Building";"Extractor";NA;70;0
"Building";"CreepTumorQueen";NA;79;0
"Building";"Extractor";NA;72;0
"Building";"Extractor";NA;79;0
"Building";"Extractor";NA;83;0
"Building";"Extractor";NA;83;0
"Building";"CreepTumorQueen";NA;89;0
"Unit";"Overlord";"Larva";83;0
"Building";"CreepTumor";NA;89;0
"Unit";"Overlord";"Larva";83;0
"Unit";"Overlord";"Larva";83;0
"Building";"CreepTumor";NA;91;0
"Unit";"Overlord";"Larva";89;0
"Building";"RoachWarren";NA;83;0
"Building";"CreepTumorQueen";NA;106;0
"Building";"Spire";NA;79;0
"Unit";"Overlord";"Larva";104;0
"Unit";"Overlord";"Larva";104;0
"Unit";"Roach";"Larva";104;2
"Unit";"Roach";"Larva";104;2
"Unit";"Roach";"Larva";106;2
"Unit";"Roach";"Larva";106;2
"Building";"CreepTumor";NA;106;0
"Building";"CreepTumor";NA;106;0
"Unit";"Overlord";"Larva";106;0
"Building";"CreepTumor";NA;110;0
"Unit";"Mutalisk";"Larva";114;2
"Unit";"Mutalisk";"Larva";114;2
"Unit";"Mutalisk";"Larva";114;2
"Unit";"Mutalisk";"Larva";114;2
"Unit";"Mutalisk";"Larva";114;2
"Unit";"Mutalisk";"Larva";114;2
"Building";"CreepTumor";NA;114;0
"Unit";"Mutalisk";"Larva";114;2
"Unit";"Mutalisk";"Larva";114;2
"Unit";"Mutalisk";"Larva";114;2
"Building";"CreepTumor";NA;118;0
"Building";"CreepTumor";NA;124;0
"Building";"CreepTumorQueen";NA;124;0
"Building";"EvolutionChamber";NA;114;0
"Unit";"Roach";"Larva";126;2
"Upgrade";"GlialReconstitution";"RoachWarren";114;0
"Building";"Hatchery";NA;110;0
"Building";"CreepTumor";NA;136;0
"Building";"CreepTumorQueen";NA;146;0
"Building";"CreepTumor";NA;137;0
"Unit";"Roach";"Larva";136;2
"Unit";"Roach";"Larva";136;2
"Building";"CreepTumor";NA;147;0
"Building";"CreepTumor";NA;148;0
"Unit";"Overlord";"Larva";147;0
"Building";"HydraliskDen";NA;136;0
"Unit";"Overlord";"Larva";148;0
"Building";"Extractor";NA;148;0
"Unit";"Overlord";"Larva";148;0
"Unit";"Overlord";"Larva";148;0
"Unit";"Roach";"Larva";148;2
"Unit";"Roach";"Larva";148;2
"Building";"Extractor";NA;148;0
"Unit";"Queen";"Hatchery";148;2
"Unit";"Mutalisk";"Larva";154;2
"Unit";"Mutalisk";"Larva";154;2
"Unit";"Mutalisk";"Larva";154;2
"Unit";"Mutalisk";"Larva";154;2
"Unit";"Mutalisk";"Larva";154;2
"Unit";"Mutalisk";"Larva";154;2
"Unit";"Mutalisk";"Larva";154;2
"Unit";"Roach";"Larva";158;2
"Unit";"Roach";"Larva";158;2
"Unit";"Roach";"Larva";158;2
"Unit";"Roach";"Larva";158;2
"Unit";"Roach";"Larva";158;2
"Unit";"Roach";"Larva";158;2
"Unit";"Roach";"Larva";158;2
"Unit";"Roach";"Larva";158;2
"Building";"CreepTumorQueen";NA;160;0
"Building";"CreepTumor";NA;160;0
"Building";"CreepTumorQueen";NA;174;0
"Unit";"Zergling";"Larva";160;1
"Unit";"Zergling";"Larva";160;1
"Unit";"Zergling";"Larva";160;1
"Unit";"Zergling";"Larva";160;1
"Unit";"Overlord";"Larva";174;0
"Unit";"Overlord";"Larva";192;0
"Unit";"Hydralisk";"Larva";192;2
"Building";"Hatchery";NA;152;0
"Unit";"Hydralisk";"Larva";196;2
"Unit";"Hydralisk";"Larva";196;2
"Unit";"Hydralisk";"Larva";196;2
"Unit";"Hydralisk";"Larva";196;2
"Unit";"Hydralisk";"Larva";196;2
"Unit";"Hydralisk";"Larva";196;2
"Unit";"Hydralisk";"Larva";196;2
"Unit";"Hydralisk";"Larva";196;2
"Unit";"Hydralisk";"Larva";196;2
"Unit";"Hydralisk";"Larva";196;2
"Unit";"Hydralisk";"Larva";196;2
"Unit";"Overlord";"Larva";198;0
"Unit";"Overlord";"Larva";198;0
"Upgrade";"ZergMissileWeaponsLevel1";"EvolutionChamber";154;0
"Unit";"Hydralisk";"Larva";198;2
"Unit";"Hydralisk";"Larva";198;2
"Unit";"Hydralisk";"Larva";198;2
"Upgrade";"EvolveGroovedSpines";"HydraliskDen";196;0
"Unit";"Roach";"Larva";226;2
"Unit";"Roach";"Larva";226;2
"Unit";"Roach";"Larva";226;2
"Unit";"Roach";"Larva";226;2
"Unit";"Roach";"Larva";226;2
"Unit";"Roach";"Larva";226;2
"Unit";"Roach";"Larva";226;2
