"type";"unit_name";"on_building";"total_supply_lag";"supply"
"Unit";"Overlord";"Larva";13;0
"Building";"Hatchery";NA;16;0
"Building";"Extractor";NA;19;0
"Building";"SpawningPool";NA;19;0
"Unit";"Queen";"Hatchery";22;2
"Unit";"Queen";"Hatchery";24;2
"Unit";"Zergling";"Larva";26;1
"Unit";"Zergling";"Larva";27;1
"Unit";"Overlord";"Larva";32;0
"Unit";"Overlord";"Larva";32;0
"Unit";"Queen";"Hatchery";32;2
"Unit";"Queen";"Hatchery";34;2
"Unit";"Zergling";"Larva";38;1
"Unit";"Zergling";"Larva";39;1
"Unit";"Zergling";"Larva";40;1
"Unit";"Zergling";"Larva";41;1
"Unit";"Overlord";"Larva";50;0
"Unit";"Overlord";"Larva";50;0
"Building";"CreepTumorQueen";NA;50;0
"Building";"CreepTumorQueen";NA;50;0
"Building";"Hatchery";NA;55;0
"Building";"Extractor";NA;57;0
"Building";"Extractor";NA;58;0
"Building";"CreepTumor";NA;62;0
"Building";"CreepTumor";NA;62;0
"Unit";"Overlord";"Larva";62;0
"Building";"EvolutionChamber";NA;62;0
"Building";"HydraliskDen";NA;70;0
"Unit";"Overlord";"Larva";71;0
"Building";"CreepTumor";NA;71;0
"Building";"CreepTumor";NA;71;0
"Unit";"Zergling";"Larva";71;1
"Unit";"Zergling";"Larva";72;1
"Unit";"Zergling";"Larva";73;1
"Unit";"Zergling";"Larva";74;1
"Unit";"Zergling";"Larva";75;1
"Unit";"Zergling";"Larva";76;1
"Unit";"Overlord";"Larva";77;0
"Unit";"Zergling";"Larva";77;1
"Unit";"Zergling";"Larva";78;1
"Unit";"Zergling";"Larva";79;1
"Unit";"Zergling";"Larva";80;1
"Building";"Extractor";NA;81;0
"Unit";"Hydralisk";"Larva";81;2
"Unit";"Hydralisk";"Larva";83;2
"Unit";"Hydralisk";"Larva";85;2
"Building";"CreepTumor";NA;87;0
"Unit";"Hydralisk";"Larva";87;2
"Unit";"Zergling";"Larva";89;1
"Unit";"Zergling";"Larva";90;1
"Unit";"Zergling";"Larva";91;1
"Unit";"Zergling";"Larva";92;1
"Unit";"Zergling";"Larva";93;1
"Unit";"Zergling";"Larva";94;1
"Unit";"Zergling";"Larva";95;1
"Unit";"Zergling";"Larva";96;1
"Unit";"Zergling";"Larva";97;1
"Unit";"Zergling";"Larva";98;1
"Unit";"Zergling";"Larva";99;1
"Unit";"Zergling";"Larva";100;1
"Unit";"Zergling";"Larva";101;1
"Unit";"Zergling";"Larva";102;1
"Unit";"Zergling";"Larva";103;1
"Unit";"Zergling";"Larva";104;1
"Unit";"Zergling";"Larva";105;1
"Unit";"Zergling";"Larva";106;1
"Unit";"Zergling";"Larva";107;1
"Unit";"Zergling";"Larva";108;1
"Unit";"Zergling";"Larva";109;1
"Unit";"Zergling";"Larva";110;1
"Unit";"Zergling";"Larva";111;1
"Unit";"Zergling";"Larva";112;1
"Unit";"Hydralisk";"Larva";115;2
"Building";"CreepTumor";NA;117;0
"Building";"CreepTumor";NA;117;0
"Unit";"Overlord";"Larva";117;0
"Unit";"Overlord";"Larva";117;0
"Unit";"Overlord";"Larva";117;0
"Unit";"Overlord";"Larva";117;0
"Unit";"Overlord";"Larva";117;0
"Building";"CreepTumor";NA;123;0
"Unit";"Hydralisk";"Larva";123;2
"Unit";"Hydralisk";"Larva";125;2
"Unit";"Hydralisk";"Larva";127;2
"Unit";"Hydralisk";"Larva";129;2
"Unit";"Hydralisk";"Larva";131;2
"Building";"CreepTumor";NA;135;0
"Unit";"Hydralisk";"Larva";135;2
"Unit";"Hydralisk";"Larva";137;2
"Unit";"Hydralisk";"Larva";139;2
"Unit";"Hydralisk";"Larva";141;2
"Building";"Spire";NA;145;0
"Building";"CreepTumorQueen";NA;145;0
"Unit";"Hydralisk";"Larva";145;2
"Unit";"Hydralisk";"Larva";147;2
"Building";"CreepTumor";NA;149;0
"Unit";"Hydralisk";"Larva";149;2
"Unit";"Hydralisk";"Larva";151;2
"Unit";"Hydralisk";"Larva";153;2
"Unit";"Hydralisk";"Larva";155;2
"Unit";"Zergling";"Larva";157;1
"Unit";"Zergling";"Larva";158;1
"Unit";"Overlord";"Larva";159;0
"Unit";"Overlord";"Larva";159;0
"Unit";"Overlord";"Larva";159;0
"Unit";"Zergling";"Larva";159;1
"Unit";"Zergling";"Larva";160;1
"Unit";"Zergling";"Larva";161;1
"Unit";"Zergling";"Larva";162;1
"Unit";"Zergling";"Larva";163;1
"Unit";"Zergling";"Larva";164;1
"Unit";"Hydralisk";"Larva";165;2
"Unit";"Hydralisk";"Larva";167;2
"Unit";"Hydralisk";"Larva";169;2
"Unit";"Hydralisk";"Larva";171;2
"Unit";"Hydralisk";"Larva";173;2
"Unit";"Zergling";"Larva";175;1
"Unit";"Zergling";"Larva";176;1
"Unit";"Zergling";"Larva";177;1
"Unit";"Zergling";"Larva";178;1
"Unit";"Zergling";"Larva";179;1
"Unit";"Zergling";"Larva";180;1
"Unit";"Zergling";"Larva";181;1
"Unit";"Zergling";"Larva";182;1
"Unit";"Zergling";"Larva";183;1
"Unit";"Zergling";"Larva";184;1
"Unit";"Zergling";"Larva";185;1
"Unit";"Zergling";"Larva";186;1
"Unit";"Zergling";"Larva";187;1
"Unit";"Zergling";"Larva";188;1
"Unit";"Zergling";"Larva";189;1
"Unit";"Zergling";"Larva";190;1
"Unit";"Zergling";"Larva";191;1
"Unit";"Zergling";"Larva";192;1
"Unit";"Hydralisk";"Larva";193;2
"Unit";"Hydralisk";"Larva";195;2
"Unit";"Hydralisk";"Larva";197;2
"Unit";"Hydralisk";"Larva";199;2
"Unit";"Hydralisk";"Larva";201;2
"Building";"CreepTumor";NA;203;0
"Unit";"Zergling";"Larva";203;1
"Unit";"Zergling";"Larva";204;1
"Unit";"Zergling";"Larva";205;1
"Unit";"Zergling";"Larva";206;1
"Unit";"Zergling";"Larva";207;1
"Unit";"Zergling";"Larva";208;1
"Unit";"Zergling";"Larva";209;1
"Unit";"Zergling";"Larva";210;1
"Unit";"Zergling";"Larva";211;1
"Unit";"Zergling";"Larva";212;1
"Building";"CreepTumor";NA;213;0
"Unit";"Zergling";"Larva";213;1
"Unit";"Zergling";"Larva";214;1
"Unit";"Zergling";"Larva";215;1
"Unit";"Zergling";"Larva";216;1
"Unit";"Hydralisk";"Larva";217;2
"Unit";"Hydralisk";"Larva";219;2
"Unit";"Zergling";"Larva";221;1
"Unit";"Zergling";"Larva";222;1
"Unit";"Zergling";"Larva";223;1
"Unit";"Zergling";"Larva";224;1
"Unit";"Zergling";"Larva";225;1
"Unit";"Zergling";"Larva";226;1
"Unit";"Zergling";"Larva";227;1
"Unit";"Zergling";"Larva";228;1
"Unit";"Hydralisk";"Larva";233;2
"Unit";"Zergling";"Larva";235;1
"Unit";"Zergling";"Larva";236;1
"Unit";"Zergling";"Larva";237;1
"Unit";"Zergling";"Larva";238;1
"Unit";"Zergling";"Larva";239;1
"Unit";"Zergling";"Larva";240;1
"Building";"CreepTumor";NA;241;0
"Upgrade";"SprayZerg";NA;241;0
"Upgrade";"SprayZerg";NA;241;0
"Upgrade";"zerglingmovementspeed";NA;241;0
"Upgrade";"SprayZerg";NA;241;0
"Upgrade";"SprayZerg";NA;241;0
"Upgrade";"EvolveMuscularAugments";NA;241;0
"Upgrade";"ZergMissileWeaponsLevel1";NA;241;0
"Upgrade";"SprayZerg";NA;241;0
