"type";"unit_name";"on_building";"total_supply";"supply"
"Unit";"Overlord";"Larva";12;0
"Building";"Extractor";NA;18;0
"Building";"SpawningPool";NA;18;0
"Building";"Hatchery";NA;16;0
"Unit";"Overlord";"Larva";23;0
"Unit";"Zergling";"Larva";23;1
"Unit";"Zergling";"Larva";23;1
"Unit";"Zergling";"Larva";23;1
"Unit";"Zergling";"Larva";23;1
"Unit";"Queen";"Hatchery";23;2
"Unit";"Queen";"Hatchery";23;2
"Building";"CreepTumorQueen";NA;33;0
"Unit";"Queen";"Hatchery";33;2
"Unit";"Overlord";"Larva";37;0
"Building";"CreepTumor";NA;37;0
"Building";"CreepTumorQueen";NA;39;0
"Building";"Hatchery";NA;33;0
"Unit";"Queen";"Hatchery";39;2
"Building";"SporeCrawler";NA;48;0
"Unit";"Overlord";"Larva";48;0
"Building";"SporeCrawler";NA;48;0
"Building";"CreepTumorQueen";NA;52;0
"Building";"CreepTumor";NA;52;0
"Building";"CreepTumor";NA;52;0
"Building";"SporeCrawler";NA;53;0
"Building";"CreepTumorQueen";NA;63;0
"Building";"CreepTumor";NA;63;0
"Building";"CreepTumor";NA;63;0
"Building";"Extractor";NA;58;0
"Building";"RoachWarren";NA;58;0
"Unit";"Queen";"Hatchery";58;2
"Unit";"Overlord";"Larva";65;0
"Unit";"Overlord";"Larva";65;0
"Unit";"Overlord";"Larva";65;0
"Unit";"Overlord";"Larva";65;0
"Building";"CreepTumor";NA;69;0
"Unit";"Roach";"Larva";69;2
"Unit";"Roach";"Larva";69;2
"Unit";"Roach";"Larva";69;2
"Unit";"Roach";"Larva";69;2
"Unit";"Roach";"Larva";69;2
"Unit";"Roach";"Larva";69;2
"Unit";"Roach";"Larva";69;2
"Building";"EvolutionChamber";NA;69;0
"Building";"EvolutionChamber";NA;69;0
"Unit";"Overlord";"Larva";69;0
"Building";"CreepTumor";NA;70;0
"Building";"CreepTumor";NA;70;0
"Unit";"Roach";"Larva";70;2
"Unit";"Roach";"Larva";70;2
"Unit";"Roach";"Larva";70;2
"Unit";"Overlord";"Larva";71;0
"Unit";"Overlord";"Larva";85;0
"Building";"Extractor";NA;85;0
"Building";"Extractor";NA;85;0
"Building";"CreepTumor";NA;91;0
"Unit";"Overlord";"Larva";91;0
"Unit";"Overlord";"Larva";97;0
"Building";"CreepTumor";NA;105;0
"Building";"CreepTumor";NA;105;0
"Building";"CreepTumor";NA;107;0
"Building";"CreepTumorQueen";NA;109;0
"Building";"Extractor";NA;107;0
"Building";"Extractor";NA;107;0
"Building";"HydraliskDen";NA;107;0
"Building";"CreepTumor";NA;121;0
"Building";"SpineCrawler";NA;107;0
"Unit";"Overlord";"Larva";121;0
"Upgrade";"GlialReconstitution";"RoachWarren";105;0
"Building";"CreepTumorQueen";NA;121;0
"Building";"SpineCrawler";NA;107;0
"Building";"CreepTumorQueen";NA;121;0
"Unit";"Overlord";"Larva";121;0
"Unit";"Zergling";"Larva";121;1
"Unit";"Zergling";"Larva";121;1
"Unit";"Overlord";"Larva";121;0
"Unit";"Zergling";"Larva";121;1
"Unit";"Zergling";"Larva";121;1
"Unit";"Zergling";"Larva";121;1
"Unit";"Zergling";"Larva";121;1
"Unit";"Zergling";"Larva";121;1
"Unit";"Zergling";"Larva";121;1
"Unit";"Overlord";"Larva";121;0
"Unit";"Overlord";"Larva";121;0
"Building";"CreepTumor";NA;129;0
"Unit";"Overlord";"Larva";129;0
"Unit";"Overlord";"Larva";129;0
"Building";"Hatchery";NA;109;0
"Building";"CreepTumor";NA;135;0
"Building";"CreepTumor";NA;135;0
"Building";"Extractor";NA;129;0
"Building";"Extractor";NA;129;0
"Unit";"Overlord";"Larva";135;0
"Unit";"Overlord";"Larva";135;0
"Building";"SporeCrawler";NA;135;0
"Unit";"Hydralisk";"Larva";134;2
"Unit";"Hydralisk";"Larva";135;2
"Unit";"Hydralisk";"Larva";135;2
"Unit";"Hydralisk";"Larva";135;2
"Unit";"Hydralisk";"Larva";135;2
"Unit";"Hydralisk";"Larva";135;2
"Unit";"Hydralisk";"Larva";135;2
"Unit";"Hydralisk";"Larva";135;2
"Unit";"Zergling";"Larva";136;1
"Unit";"Zergling";"Larva";136;1
"Unit";"Zergling";"Larva";136;1
"Unit";"Zergling";"Larva";136;1
"Unit";"Zergling";"Larva";136;1
"Unit";"Zergling";"Larva";136;1
"Building";"SpineCrawler";NA;129;0
"Unit";"Overlord";"Larva";136;0
"Upgrade";"ZergMissileWeaponsLevel1";"EvolutionChamber";121;0
"Upgrade";"ZergGroundArmorsLevel1";"EvolutionChamber";121;0
"Upgrade";"EvolveMuscularAugments";"HydraliskDen";135;0
"Building";"CreepTumor";NA;161;0
"Building";"CreepTumor";NA;164;0
"Building";"CreepTumor";NA;164;0
"Building";"CreepTumor";NA;164;0
"Building";"LurkerDenMP";NA;129;0
"Building";"CreepTumorQueen";NA;164;0
"Building";"CreepTumorQueen";NA;164;0
"Building";"CreepTumorQueen";NA;164;0
"Unit";"Hydralisk";"Larva";161;2
"Unit";"Hydralisk";"Larva";161;2
"Unit";"Hydralisk";"Larva";161;2
"Unit";"Hydralisk";"Larva";161;2
"Unit";"Hydralisk";"Larva";161;2
"Unit";"Hydralisk";"Larva";161;2
"Unit";"Hydralisk";"Larva";161;2
"Unit";"Hydralisk";"Larva";161;2
"Unit";"Hydralisk";"Larva";161;2
"Unit";"Overlord";"Larva";164;0
"Building";"CreepTumor";NA;164;0
"Unit";"Overlord";"Larva";182;0
"Unit";"Overlord";"Larva";182;0
"Unit";"Overlord";"Larva";182;0
"Building";"CreepTumorQueen";NA;182;0
"Building";"CreepTumor";NA;182;0
"Building";"CreepTumor";NA;182;0
"Building";"CreepTumor";NA;182;0
"Building";"CreepTumor";NA;182;0
"Building";"CreepTumorQueen";NA;182;0
"Building";"CreepTumor";NA;182;0
"Building";"CreepTumorQueen";NA;182;0
"Building";"CreepTumorQueen";NA;182;0
"Building";"CreepTumor";NA;185;0
"Building";"CreepTumor";NA;185;0
"Unit";"Overlord";"Larva";185;0
"Building";"Hatchery";NA;164;0
"Unit";"Zergling";"Larva";185;1
"Unit";"Zergling";"Larva";185;1
"Unit";"Zergling";"Larva";185;1
"Unit";"Zergling";"Larva";185;1
"Unit";"Zergling";"Larva";185;1
"Unit";"Zergling";"Larva";185;1
"Unit";"Zergling";"Larva";185;1
"Unit";"Zergling";"Larva";185;1
"Unit";"Zergling";"Larva";185;1
"Unit";"Zergling";"Larva";185;1
"Unit";"Zergling";"Larva";185;1
"Unit";"Zergling";"Larva";185;1
"Unit";"Zergling";"Larva";185;1
"Unit";"Zergling";"Larva";185;1
"Unit";"Zergling";"Larva";185;1
"Unit";"Zergling";"Larva";185;1
"Unit";"Zergling";"Larva";185;1
"Unit";"Zergling";"Larva";185;1
"Unit";"Zergling";"Larva";185;1
"Unit";"Zergling";"Larva";185;1
"Unit";"Zergling";"Larva";185;1
"Unit";"Zergling";"Larva";185;1
"Unit";"Zergling";"Larva";185;1
"Unit";"Zergling";"Larva";185;1
"Unit";"Zergling";"Larva";185;1
"Unit";"Zergling";"Larva";185;1
"Unit";"Zergling";"Larva";185;1
"Unit";"Zergling";"Larva";185;1
"Unit";"Zergling";"Larva";185;1
"Unit";"Zergling";"Larva";185;1
"Unit";"Zergling";"Larva";185;1
"Unit";"Zergling";"Larva";185;1
"Unit";"Zergling";"Larva";185;1
"Unit";"Zergling";"Larva";185;1
"Unit";"Zergling";"Larva";185;1
"Unit";"Zergling";"Larva";185;1
"Building";"CreepTumor";NA;185;0
"Building";"CreepTumor";NA;185;0
"Building";"CreepTumor";NA;185;0
"Building";"CreepTumor";NA;185;0
"Building";"CreepTumor";NA;185;0
"Building";"CreepTumor";NA;185;0
"Building";"CreepTumor";NA;185;0
"Building";"CreepTumor";NA;185;0
"Building";"CreepTumor";NA;185;0
"Unit";"Hydralisk";"Larva";185;2
"Unit";"Hydralisk";"Larva";185;2
"Unit";"Hydralisk";"Larva";185;2
"Unit";"Hydralisk";"Larva";185;2
"Unit";"Hydralisk";"Larva";185;2
"Unit";"Hydralisk";"Larva";185;2
"Building";"CreepTumor";NA;185;0
"Building";"CreepTumor";NA;185;0
"Upgrade";"EvolveGroovedSpines";"HydraliskDen";182;0
"Building";"Extractor";NA;185;0
"Building";"BanelingNest";NA;185;0
"Building";"Hatchery";NA;182;0
"Building";"InfestationPit";NA;221;0
"Building";"SpineCrawler";NA;221;0
"Upgrade";"ZergMissileWeaponsLevel2";"EvolutionChamber";166;0
"Upgrade";"ZergGroundArmorsLevel2";"EvolutionChamber";180;0
"Building";"SpineCrawler";NA;233;0
"Unit";"Hydralisk";"Larva";237;2
"Unit";"Hydralisk";"Larva";237;2
"Unit";"Hydralisk";"Larva";237;2
"Unit";"Hydralisk";"Larva";237;2
"Unit";"Hydralisk";"Larva";237;2
"Unit";"Hydralisk";"Larva";237;2
"Unit";"Hydralisk";"Larva";237;2
"Unit";"Hydralisk";"Larva";237;2
"Unit";"Hydralisk";"Larva";237;2
"Unit";"Hydralisk";"Larva";237;2
"Unit";"Hydralisk";"Larva";237;2
"Unit";"Hydralisk";"Larva";237;2
"Unit";"Hydralisk";"Larva";237;2
"Upgrade";"Burrow";"Hatchery";233;0
"Unit";"Zergling";"Larva";237;1
"Unit";"Zergling";"Larva";237;1
"Unit";"Zergling";"Larva";237;1
"Unit";"Zergling";"Larva";237;1
"Unit";"Hydralisk";"Larva";237;2
"Unit";"Hydralisk";"Larva";237;2
"Unit";"Hydralisk";"Larva";237;2
"Unit";"Hydralisk";"Larva";237;2
"Unit";"Hydralisk";"Larva";237;2
"Building";"Spire";NA;221;0
"Unit";"Zergling";"Larva";263;1
"Unit";"Zergling";"Larva";263;1
"Unit";"Zergling";"Larva";263;1
"Unit";"Zergling";"Larva";263;1
"Unit";"Zergling";"Larva";263;1
"Unit";"Zergling";"Larva";263;1
"Unit";"Zergling";"Larva";263;1
"Unit";"Zergling";"Larva";263;1
"Unit";"Zergling";"Larva";263;1
"Unit";"Zergling";"Larva";263;1
"Unit";"Zergling";"Larva";263;1
"Unit";"Zergling";"Larva";263;1
"Unit";"Hydralisk";"Larva";263;2
"Unit";"Zergling";"Larva";277;1
"Unit";"Zergling";"Larva";277;1
"Unit";"Zergling";"Larva";277;1
"Unit";"Zergling";"Larva";277;1
"Unit";"Hydralisk";"Larva";277;2
"Unit";"Hydralisk";"Larva";277;2
"Unit";"Overlord";"Larva";298;0
"Unit";"Overlord";"Larva";302;0
"Unit";"Zergling";"Larva";302;1
"Unit";"Zergling";"Larva";302;1
"Unit";"Zergling";"Larva";302;1
"Unit";"Zergling";"Larva";302;1
"Unit";"Zergling";"Larva";302;1
"Unit";"Zergling";"Larva";302;1
"Unit";"Zergling";"Larva";302;1
"Unit";"Zergling";"Larva";302;1
"Unit";"Zergling";"Larva";302;1
"Unit";"Zergling";"Larva";302;1
"Unit";"Zergling";"Larva";302;1
"Unit";"Zergling";"Larva";302;1
"Unit";"Zergling";"Larva";302;1
"Unit";"Zergling";"Larva";302;1
"Unit";"Zergling";"Larva";302;1
"Unit";"Zergling";"Larva";302;1
"Unit";"Zergling";"Larva";302;1
"Unit";"Zergling";"Larva";302;1
"Unit";"Zergling";"Larva";302;1
"Unit";"Zergling";"Larva";302;1
"Unit";"Zergling";"Larva";302;1
"Unit";"Zergling";"Larva";302;1
"Unit";"Zergling";"Larva";302;1
"Unit";"Zergling";"Larva";302;1
"Unit";"Zergling";"Larva";302;1
"Unit";"Zergling";"Larva";302;1
"Unit";"Zergling";"Larva";302;1
"Unit";"Zergling";"Larva";302;1
"Unit";"Hydralisk";"Larva";302;2
"Unit";"Hydralisk";"Larva";302;2
"Unit";"Hydralisk";"Larva";302;2
"Unit";"Hydralisk";"Larva";302;2
"Unit";"Hydralisk";"Larva";302;2
"Unit";"Hydralisk";"Larva";302;2
"Unit";"Hydralisk";"Larva";302;2
"Unit";"Hydralisk";"Larva";302;2
"Unit";"Hydralisk";"Larva";302;2
"Unit";"Hydralisk";"Larva";302;2
"Unit";"Hydralisk";"Larva";302;2
"Unit";"Hydralisk";"Larva";302;2
"Unit";"Hydralisk";"Larva";302;2
"Building";"CreepTumor";NA;304;0
"Building";"CreepTumor";NA;304;0
"Building";"CreepTumor";NA;304;0
"Building";"CreepTumor";NA;304;0
"Unit";"Overlord";"Larva";304;0
"Unit";"Baneling";"Zergling";358;0
"Unit";"Baneling";"Zergling";358;0
"Unit";"Baneling";"Zergling";358;0
"Unit";"Baneling";"Zergling";358;0
"Unit";"Baneling";"Zergling";358;0
"Unit";"Baneling";"Zergling";358;0
"Unit";"Baneling";"Zergling";358;0
"Unit";"Baneling";"Zergling";358;0
"Unit";"Baneling";"Zergling";358;0
"Unit";"Baneling";"Zergling";358;0
"Unit";"Baneling";"Zergling";358;0
"Unit";"Baneling";"Zergling";358;0
"Unit";"Baneling";"Zergling";358;0
"Unit";"Baneling";"Zergling";358;0
"Unit";"Baneling";"Zergling";358;0
"Unit";"Corruptor";"Larva";358;2
"Unit";"Corruptor";"Larva";358;2
"Unit";"Corruptor";"Larva";358;2
"Unit";"Corruptor";"Larva";358;2
"Unit";"Corruptor";"Larva";358;2
"Unit";"Corruptor";"Larva";358;2
