"type";"unit_name";"on_building";"total_supply";"supply"
"Unit";"Overlord";"Larva";12;0
"Building";"Extractor";NA;18;0
"Building";"Hatchery";NA;17;0
"Building";"SpawningPool";NA;19;0
"Unit";"Overlord";"Larva";22;0
"Unit";"Zergling";"Larva";23;1
"Unit";"Zergling";"Larva";23;1
"Unit";"Queen";"Hatchery";23;2
"Unit";"Queen";"Hatchery";23;2
"Building";"CreepTumorQueen";NA;35;0
"Unit";"Zergling";"Larva";35;1
"Unit";"Zergling";"Larva";35;1
"Unit";"Zergling";"Larva";35;1
"Unit";"Zergling";"Larva";35;1
"Unit";"Queen";"Hatchery";32;2
"Unit";"Overlord";"Larva";35;0
"Building";"CreepTumor";NA;41;0
"Building";"CreepTumorQueen";NA;43;0
"Unit";"Overlord";"Larva";43;0
"Building";"Hatchery";NA;30;0
"Unit";"Queen";"Hatchery";43;2
"Unit";"Zergling";"Larva";49;1
"Unit";"Zergling";"Larva";49;1
"Unit";"Zergling";"Larva";49;1
"Unit";"Zergling";"Larva";49;1
"Unit";"Zergling";"Larva";49;1
"Unit";"Zergling";"Larva";49;1
"Unit";"Zergling";"Larva";49;1
"Unit";"Zergling";"Larva";49;1
"Unit";"Zergling";"Larva";49;1
"Unit";"Zergling";"Larva";49;1
"Unit";"Zergling";"Larva";49;1
"Unit";"Zergling";"Larva";49;1
"Unit";"Zergling";"Larva";49;1
"Unit";"Zergling";"Larva";49;1
"Building";"CreepTumorQueen";NA;49;0
"Building";"SporeCrawler";NA;49;0
"Building";"SporeCrawler";NA;49;0
"Building";"CreepTumor";NA;49;0
"Building";"CreepTumor";NA;49;0
"Building";"SporeCrawler";NA;72;0
"Building";"CreepTumor";NA;74;0
"Building";"CreepTumorQueen";NA;75;0
"Building";"CreepTumor";NA;74;0
"Building";"CreepTumor";NA;75;0
"Building";"EvolutionChamber";NA;72;0
"Unit";"Overlord";"Larva";84;0
"Building";"CreepTumor";NA;84;0
"Unit";"Overlord";"Larva";84;0
"Building";"CreepTumor";NA;84;0
"Building";"CreepTumor";NA;84;0
"Unit";"Overlord";"Larva";84;0
"Unit";"Overlord";"Larva";84;0
"Building";"Extractor";NA;84;0
"Building";"Extractor";NA;84;0
"Unit";"Overlord";"Larva";93;0
"Building";"CreepTumor";NA;93;0
"Building";"CreepTumor";NA;93;0
"Building";"CreepTumor";NA;93;0
"Unit";"Overlord";"Larva";93;0
"Unit";"Overlord";"Larva";93;0
"Building";"BanelingNest";NA;93;0
"Building";"Hatchery";NA;84;0
"Unit";"Zergling";"Larva";103;1
"Unit";"Zergling";"Larva";103;1
"Unit";"Zergling";"Larva";103;1
"Unit";"Zergling";"Larva";103;1
"Unit";"Zergling";"Larva";103;1
"Unit";"Zergling";"Larva";103;1
"Unit";"Zergling";"Larva";103;1
"Unit";"Zergling";"Larva";103;1
"Unit";"Zergling";"Larva";103;1
"Unit";"Zergling";"Larva";103;1
"Building";"CreepTumor";NA;109;0
"Unit";"Overlord";"Larva";109;0
"Unit";"Zergling";"Larva";109;1
"Unit";"Zergling";"Larva";109;1
"Unit";"Zergling";"Larva";109;1
"Unit";"Zergling";"Larva";109;1
"Unit";"Zergling";"Larva";109;1
"Unit";"Zergling";"Larva";109;1
"Unit";"Zergling";"Larva";109;1
"Unit";"Zergling";"Larva";109;1
"Unit";"Zergling";"Larva";109;1
"Unit";"Zergling";"Larva";109;1
"Building";"HydraliskDen";NA;109;0
"Unit";"Zergling";"Larva";119;1
"Unit";"Zergling";"Larva";119;1
"Unit";"Zergling";"Larva";119;1
"Unit";"Zergling";"Larva";119;1
"Unit";"Zergling";"Larva";119;1
"Unit";"Zergling";"Larva";119;1
"Building";"CreepTumor";NA;119;0
"Upgrade";"ZergMeleeWeaponsLevel1";"EvolutionChamber";93;0
"Building";"CreepTumorQueen";NA;135;0
"Building";"Extractor";NA;119;0
"Building";"CreepTumorQueen";NA;137;0
"Building";"CreepTumorQueen";NA;137;0
"Building";"CreepTumorQueen";NA;137;0
"Building";"Extractor";NA;137;0
"Building";"Extractor";NA;137;0
"Building";"CreepTumorQueen";NA;143;0
"Building";"CreepTumorQueen";NA;143;0
"Building";"Hatchery";NA;103;0
"Unit";"Queen";"Hatchery";137;2
"Unit";"Overlord";"Larva";147;0
"Unit";"Overlord";"Larva";147;0
"Building";"CreepTumor";NA;149;0
"Building";"CreepTumor";NA;149;0
"Building";"CreepTumor";NA;149;0
"Building";"CreepTumor";NA;149;0
"Unit";"Overlord";"Larva";161;0
"Unit";"Overlord";"Larva";161;0
"Unit";"Overlord";"Larva";161;0
"Unit";"Overlord";"Larva";161;0
"Unit";"Overlord";"Larva";161;0
"Unit";"Overlord";"Larva";161;0
"Unit";"Overlord";"Larva";161;0
"Unit";"Hydralisk";"Larva";149;2
"Building";"CreepTumor";NA;161;0
"Building";"CreepTumor";NA;161;0
"Building";"CreepTumor";NA;161;0
"Building";"CreepTumor";NA;161;0
"Upgrade";"EvolveGroovedSpines";"HydraliskDen";147;0
"Unit";"Hydralisk";"Larva";161;2
"Unit";"Hydralisk";"Larva";161;2
"Unit";"Hydralisk";"Larva";161;2
"Unit";"Hydralisk";"Larva";161;2
"Unit";"Hydralisk";"Larva";161;2
"Unit";"Hydralisk";"Larva";161;2
"Unit";"Hydralisk";"Larva";163;2
"Unit";"Hydralisk";"Larva";163;2
"Unit";"Hydralisk";"Larva";163;2
"Unit";"Zergling";"Larva";175;1
"Unit";"Zergling";"Larva";175;1
"Unit";"Zergling";"Larva";175;1
"Unit";"Zergling";"Larva";175;1
"Unit";"Zergling";"Larva";175;1
"Unit";"Zergling";"Larva";175;1
"Unit";"Zergling";"Larva";175;1
"Unit";"Zergling";"Larva";175;1
"Unit";"Zergling";"Larva";175;1
"Unit";"Zergling";"Larva";175;1
"Unit";"Zergling";"Larva";175;1
"Unit";"Zergling";"Larva";175;1
"Unit";"Zergling";"Larva";175;1
"Unit";"Zergling";"Larva";175;1
"Unit";"Zergling";"Larva";175;1
"Unit";"Zergling";"Larva";175;1
"Unit";"Zergling";"Larva";175;1
"Unit";"Zergling";"Larva";175;1
"Unit";"Zergling";"Larva";175;1
"Unit";"Zergling";"Larva";175;1
"Unit";"Zergling";"Larva";175;1
"Unit";"Zergling";"Larva";175;1
"Unit";"Zergling";"Larva";175;1
"Unit";"Zergling";"Larva";175;1
"Unit";"Zergling";"Larva";175;1
"Unit";"Zergling";"Larva";175;1
"Unit";"Zergling";"Larva";175;1
"Unit";"Zergling";"Larva";175;1
"Unit";"Hydralisk";"Larva";175;2
"Unit";"Hydralisk";"Larva";175;2
"Unit";"Zergling";"Larva";179;1
"Unit";"Zergling";"Larva";179;1
"Unit";"Zergling";"Larva";179;1
"Unit";"Zergling";"Larva";179;1
"Unit";"Zergling";"Larva";181;1
"Unit";"Zergling";"Larva";181;1
"Unit";"Zergling";"Larva";181;1
"Unit";"Zergling";"Larva";181;1
"Unit";"Zergling";"Larva";181;1
"Unit";"Zergling";"Larva";181;1
"Unit";"Zergling";"Larva";181;1
"Unit";"Zergling";"Larva";181;1
"Unit";"Zergling";"Larva";181;1
"Unit";"Zergling";"Larva";181;1
"Unit";"Hydralisk";"Larva";215;2
"Unit";"Hydralisk";"Larva";217;2
"Unit";"Hydralisk";"Larva";217;2
"Unit";"Hydralisk";"Larva";217;2
"Unit";"Hydralisk";"Larva";217;2
"Unit";"Hydralisk";"Larva";217;2
"Unit";"Hydralisk";"Larva";227;2
"Unit";"Hydralisk";"Larva";227;2
"Upgrade";"ZergMeleeWeaponsLevel2";"EvolutionChamber";161;0
"Upgrade";"EvolveMuscularAugments";"HydraliskDen";181;0
"Building";"CreepTumor";NA;239;0
"Building";"CreepTumor";NA;239;0
"Unit";"Hydralisk";"Larva";227;2
"Building";"EvolutionChamber";NA;241;0
"Unit";"Zergling";"Larva";261;1
"Unit";"Zergling";"Larva";261;1
"Unit";"Zergling";"Larva";261;1
"Unit";"Zergling";"Larva";261;1
"Unit";"Zergling";"Larva";261;1
"Unit";"Zergling";"Larva";261;1
"Unit";"Zergling";"Larva";261;1
"Unit";"Zergling";"Larva";261;1
"Unit";"Zergling";"Larva";261;1
"Unit";"Zergling";"Larva";261;1
"Unit";"Zergling";"Larva";261;1
"Unit";"Zergling";"Larva";261;1
"Unit";"Zergling";"Larva";261;1
"Unit";"Zergling";"Larva";261;1
"Unit";"Zergling";"Larva";261;1
"Unit";"Zergling";"Larva";261;1
"Unit";"Zergling";"Larva";261;1
"Unit";"Zergling";"Larva";261;1
"Unit";"Zergling";"Larva";261;1
"Unit";"Zergling";"Larva";261;1
"Unit";"Hydralisk";"Larva";261;2
"Unit";"Hydralisk";"Larva";261;2
"Unit";"Zergling";"Larva";261;1
"Unit";"Zergling";"Larva";261;1
"Unit";"Zergling";"Larva";261;1
"Unit";"Zergling";"Larva";261;1
"Unit";"Zergling";"Larva";261;1
"Unit";"Zergling";"Larva";261;1
"Building";"InfestationPit";NA;261;0
"Unit";"Queen";"Hatchery";261;2
"Unit";"Zergling";"Larva";291;1
"Unit";"Zergling";"Larva";291;1
"Unit";"Zergling";"Larva";291;1
"Unit";"Zergling";"Larva";291;1
"Unit";"Zergling";"Larva";291;1
"Unit";"Zergling";"Larva";291;1
"Unit";"Zergling";"Larva";291;1
"Unit";"Zergling";"Larva";291;1
"Unit";"Zergling";"Larva";291;1
"Unit";"Zergling";"Larva";291;1
"Unit";"Zergling";"Larva";291;1
"Unit";"Zergling";"Larva";291;1
"Unit";"Hydralisk";"Larva";291;2
"Unit";"Hydralisk";"Larva";291;2
"Unit";"Hydralisk";"Larva";291;2
"Unit";"Hydralisk";"Larva";291;2
"Unit";"Hydralisk";"Larva";291;2
"Unit";"Hydralisk";"Larva";291;2
"Unit";"Baneling";"Zergling";293;0
"Unit";"Baneling";"Zergling";293;0
"Unit";"Baneling";"Zergling";293;0
"Unit";"Baneling";"Zergling";293;0
"Unit";"Baneling";"Zergling";293;0
"Unit";"Baneling";"Zergling";293;0
"Unit";"Baneling";"Zergling";293;0
"Unit";"Baneling";"Zergling";293;0
"Unit";"Baneling";"Zergling";293;0
"Unit";"Baneling";"Zergling";293;0
"Unit";"Baneling";"Zergling";293;0
"Unit";"Baneling";"Zergling";293;0
"Unit";"Baneling";"Zergling";293;0
"Unit";"Baneling";"Zergling";293;0
"Unit";"Baneling";"Zergling";293;0
"Unit";"Baneling";"Zergling";293;0
"Building";"SpineCrawler";NA;291;0
"Unit";"Zergling";"Larva";295;1
"Unit";"Zergling";"Larva";295;1
"Building";"SpineCrawler";NA;291;0
"Unit";"Overlord";"Larva";305;0
"Unit";"Overlord";"Larva";305;0
"Building";"CreepTumor";NA;317;0
"Unit";"Zergling";"Larva";317;1
"Unit";"Zergling";"Larva";317;1
"Unit";"Zergling";"Larva";317;1
"Unit";"Zergling";"Larva";317;1
"Unit";"Zergling";"Larva";317;1
"Unit";"Zergling";"Larva";317;1
"Unit";"Zergling";"Larva";317;1
"Unit";"Zergling";"Larva";317;1
"Unit";"Overlord";"Larva";317;0
"Unit";"Overlord";"Larva";317;0
"Unit";"Zergling";"Larva";319;1
"Unit";"Zergling";"Larva";319;1
"Unit";"Zergling";"Larva";319;1
"Unit";"Zergling";"Larva";319;1
"Unit";"Zergling";"Larva";319;1
"Unit";"Zergling";"Larva";319;1
"Unit";"Zergling";"Larva";319;1
"Unit";"Zergling";"Larva";319;1
"Unit";"Zergling";"Larva";319;1
"Unit";"Zergling";"Larva";319;1
"Unit";"Zergling";"Larva";319;1
"Unit";"Zergling";"Larva";319;1
"Unit";"Zergling";"Larva";319;1
"Unit";"Zergling";"Larva";319;1
"Unit";"Zergling";"Larva";319;1
"Unit";"Zergling";"Larva";319;1
"Unit";"Zergling";"Larva";319;1
"Unit";"Zergling";"Larva";319;1
"Unit";"Zergling";"Larva";319;1
"Unit";"Zergling";"Larva";319;1
"Unit";"Zergling";"Larva";319;1
"Unit";"Zergling";"Larva";319;1
"Unit";"Zergling";"Larva";319;1
"Unit";"Zergling";"Larva";319;1
"Unit";"Zergling";"Larva";319;1
"Unit";"Zergling";"Larva";319;1
"Unit";"Zergling";"Larva";319;1
"Unit";"Zergling";"Larva";319;1
"Unit";"Zergling";"Larva";319;1
"Unit";"Zergling";"Larva";319;1
"Unit";"Zergling";"Larva";319;1
"Unit";"Zergling";"Larva";319;1
"Unit";"Zergling";"Larva";327;1
"Unit";"Zergling";"Larva";327;1
"Unit";"Zergling";"Larva";327;1
"Unit";"Zergling";"Larva";327;1
"Upgrade";"ZergMissileWeaponsLevel1";"EvolutionChamber";287;0
"Unit";"Zergling";"Larva";327;1
"Unit";"Zergling";"Larva";327;1
"Unit";"Zergling";"Larva";327;1
"Unit";"Zergling";"Larva";327;1
"Unit";"Zergling";"Larva";327;1
"Unit";"Zergling";"Larva";327;1
"Unit";"Zergling";"Larva";327;1
"Unit";"Zergling";"Larva";327;1
"Unit";"Zergling";"Larva";359;1
"Unit";"Zergling";"Larva";359;1
"Unit";"Zergling";"Larva";359;1
"Unit";"Zergling";"Larva";359;1
"Unit";"Zergling";"Larva";359;1
"Unit";"Zergling";"Larva";359;1
"Unit";"Zergling";"Larva";359;1
"Unit";"Zergling";"Larva";359;1
"Unit";"Zergling";"Larva";359;1
"Unit";"Zergling";"Larva";359;1
"Unit";"Zergling";"Larva";359;1
"Unit";"Zergling";"Larva";359;1
"Unit";"Zergling";"Larva";359;1
"Unit";"Zergling";"Larva";359;1
"Unit";"Zergling";"Larva";359;1
"Unit";"Zergling";"Larva";359;1
"Unit";"Zergling";"Larva";359;1
"Unit";"Zergling";"Larva";359;1
"Building";"Hatchery";NA;293;0
"Unit";"Queen";"Hatchery";327;2
"Unit";"Zergling";"Larva";389;1
"Unit";"Zergling";"Larva";389;1
"Unit";"Zergling";"Larva";389;1
"Unit";"Zergling";"Larva";389;1
"Unit";"Zergling";"Larva";389;1
"Unit";"Zergling";"Larva";389;1
"Unit";"Zergling";"Larva";389;1
"Unit";"Zergling";"Larva";389;1
"Unit";"Zergling";"Larva";389;1
"Unit";"Zergling";"Larva";389;1
"Unit";"Zergling";"Larva";389;1
"Unit";"Zergling";"Larva";389;1
"Unit";"Zergling";"Larva";389;1
"Unit";"Zergling";"Larva";389;1
"Unit";"Zergling";"Larva";389;1
"Unit";"Zergling";"Larva";389;1
"Unit";"Zergling";"Larva";389;1
"Unit";"Zergling";"Larva";389;1
"Unit";"Zergling";"Larva";398;1
"Unit";"Zergling";"Larva";398;1
"Unit";"Zergling";"Larva";398;1
"Unit";"Zergling";"Larva";398;1
"Upgrade";"ZergGroundArmorsLevel1";"EvolutionChamber";319;0
"Unit";"Zergling";"Larva";408;1
"Unit";"Zergling";"Larva";408;1
"Unit";"Zergling";"Larva";408;1
"Unit";"Zergling";"Larva";408;1
"Unit";"Zergling";"Larva";408;1
"Unit";"Zergling";"Larva";408;1
"Unit";"Zergling";"Larva";408;1
"Unit";"Zergling";"Larva";408;1
"Unit";"Queen";"Hatchery";398;2
"Unit";"Queen";"Hatchery";398;2
"Unit";"Hydralisk";"Larva";418;2
"Unit";"Hydralisk";"Larva";418;2
"Unit";"Hydralisk";"Larva";418;2
"Unit";"Hydralisk";"Larva";418;2
"Unit";"Hydralisk";"Larva";418;2
"Unit";"Hydralisk";"Larva";418;2
"Unit";"Hydralisk";"Larva";418;2
"Unit";"Hydralisk";"Larva";420;2
"Building";"Extractor";NA;428;0
"Unit";"Zergling";"Larva";428;1
"Unit";"Zergling";"Larva";428;1
"Unit";"Zergling";"Larva";428;1
"Unit";"Zergling";"Larva";428;1
"Unit";"Zergling";"Larva";428;1
"Unit";"Zergling";"Larva";428;1
"Building";"Extractor";NA;428;0
"Unit";"Hydralisk";"Larva";428;2
"Unit";"Hydralisk";"Larva";428;2
"Unit";"Hydralisk";"Larva";428;2
"Unit";"Hydralisk";"Larva";428;2
"Unit";"Hydralisk";"Larva";428;2
"Unit";"Baneling";"Zergling";450;0
"Unit";"Zergling";"Larva";448;1
"Unit";"Zergling";"Larva";448;1
"Unit";"Zergling";"Larva";448;1
"Unit";"Zergling";"Larva";448;1
"Unit";"Baneling";"Zergling";454;0
"Unit";"Baneling";"Zergling";454;0
"Unit";"Baneling";"Zergling";454;0
"Unit";"Zergling";"Larva";448;1
"Unit";"Zergling";"Larva";448;1
"Unit";"Zergling";"Larva";448;1
"Unit";"Zergling";"Larva";448;1
"Unit";"Zergling";"Larva";448;1
"Unit";"Zergling";"Larva";448;1
"Unit";"Zergling";"Larva";448;1
"Unit";"Zergling";"Larva";448;1
"Unit";"Baneling";"Zergling";454;0
"Unit";"Baneling";"Zergling";454;0
"Unit";"Zergling";"Larva";448;1
"Unit";"Zergling";"Larva";448;1
"Unit";"Zergling";"Larva";448;1
"Unit";"Zergling";"Larva";448;1
"Unit";"Baneling";"Zergling";454;0
"Unit";"Baneling";"Zergling";454;0
"Unit";"Baneling";"Zergling";454;0
"Unit";"Baneling";"Zergling";454;0
"Unit";"Baneling";"Zergling";454;0
"Unit";"Baneling";"Zergling";454;0
"Unit";"Baneling";"Zergling";454;0
"Unit";"Baneling";"Zergling";454;0
"Unit";"Baneling";"Zergling";454;0
"Unit";"Baneling";"Zergling";454;0
"Unit";"Baneling";"Zergling";454;0
"Unit";"Baneling";"Zergling";454;0
"Unit";"Baneling";"Zergling";454;0
"Unit";"Baneling";"Zergling";454;0
"Unit";"Baneling";"Zergling";454;0
"Unit";"Baneling";"Zergling";454;0
"Unit";"Queen";"Hatchery";432;2
"Unit";"Queen";"Hatchery";432;2
"Unit";"Queen";"Hatchery";432;2
"Building";"Hatchery";NA;428;0
"Building";"SpineCrawler";NA;480;0
"Building";"SpineCrawler";NA;486;0
"Building";"SpineCrawler";NA;486;0
"Building";"Hatchery";NA;444;0
"Building";"CreepTumor";NA;498;0
"Building";"CreepTumor";NA;498;0
"Unit";"Overlord";"Larva";498;0
"Building";"CreepTumor";NA;498;0
"Building";"CreepTumorQueen";NA;498;0
"Unit";"Zergling";"Larva";498;1
"Unit";"Zergling";"Larva";498;1
"Building";"CreepTumorQueen";NA;498;0
"Building";"SpineCrawler";NA;498;0
"Building";"SpineCrawler";NA;498;0
"Upgrade";"ZergMissileWeaponsLevel2";"EvolutionChamber";464;0
"Upgrade";"ZergGroundArmorsLevel2";"EvolutionChamber";464;0
"Unit";"Zergling";"Larva";500;1
"Unit";"Zergling";"Larva";500;1
"Unit";"Zergling";"Larva";500;1
"Unit";"Zergling";"Larva";500;1
"Unit";"Zergling";"Larva";500;1
"Unit";"Zergling";"Larva";500;1
"Unit";"Zergling";"Larva";500;1
"Unit";"Zergling";"Larva";500;1
"Unit";"Zergling";"Larva";500;1
"Unit";"Zergling";"Larva";500;1
"Unit";"Zergling";"Larva";500;1
"Unit";"Zergling";"Larva";500;1
"Unit";"Zergling";"Larva";500;1
"Unit";"Zergling";"Larva";500;1
"Unit";"Zergling";"Larva";500;1
"Unit";"Zergling";"Larva";500;1
"Unit";"Zergling";"Larva";500;1
"Unit";"Zergling";"Larva";500;1
"Unit";"Zergling";"Larva";500;1
"Unit";"Zergling";"Larva";500;1
"Unit";"Zergling";"Larva";500;1
"Unit";"Zergling";"Larva";500;1
"Unit";"Zergling";"Larva";500;1
"Unit";"Zergling";"Larva";500;1
"Unit";"Zergling";"Larva";500;1
"Unit";"Zergling";"Larva";500;1
"Unit";"Zergling";"Larva";500;1
"Unit";"Zergling";"Larva";500;1
"Unit";"Zergling";"Larva";500;1
"Unit";"Zergling";"Larva";500;1
"Unit";"Zergling";"Larva";500;1
"Unit";"Zergling";"Larva";500;1
"Unit";"Zergling";"Larva";500;1
"Unit";"Zergling";"Larva";500;1
"Unit";"Zergling";"Larva";500;1
"Unit";"Zergling";"Larva";500;1
"Unit";"Zergling";"Larva";500;1
"Unit";"Zergling";"Larva";500;1
"Unit";"Zergling";"Larva";500;1
"Unit";"Zergling";"Larva";500;1
"Unit";"Zergling";"Larva";500;1
"Unit";"Zergling";"Larva";500;1
"Unit";"Zergling";"Larva";500;1
"Unit";"Zergling";"Larva";500;1
"Unit";"Zergling";"Larva";500;1
"Unit";"Zergling";"Larva";500;1
"Unit";"Zergling";"Larva";500;1
"Unit";"Zergling";"Larva";500;1
"Unit";"Zergling";"Larva";500;1
"Unit";"Zergling";"Larva";500;1
"Unit";"Zergling";"Larva";500;1
"Unit";"Zergling";"Larva";500;1
"Building";"Spire";NA;498;0
"Unit";"Zergling";"Larva";501;1
"Unit";"Zergling";"Larva";501;1
"Unit";"Zergling";"Larva";501;1
"Unit";"Zergling";"Larva";501;1
"Unit";"Zergling";"Larva";501;1
"Unit";"Zergling";"Larva";501;1
"Unit";"Zergling";"Larva";501;1
"Unit";"Zergling";"Larva";501;1
"Unit";"Zergling";"Larva";501;1
"Unit";"Zergling";"Larva";501;1
"Unit";"Zergling";"Larva";563;1
"Unit";"Zergling";"Larva";563;1
"Unit";"Zergling";"Larva";563;1
"Unit";"Zergling";"Larva";563;1
"Unit";"Zergling";"Larva";563;1
"Unit";"Zergling";"Larva";563;1
"Unit";"Zergling";"Larva";563;1
"Unit";"Zergling";"Larva";563;1
"Unit";"Zergling";"Larva";563;1
"Unit";"Zergling";"Larva";563;1
"Unit";"Zergling";"Larva";563;1
"Unit";"Zergling";"Larva";563;1
"Unit";"Zergling";"Larva";563;1
"Unit";"Zergling";"Larva";563;1
"Unit";"Zergling";"Larva";563;1
"Unit";"Zergling";"Larva";563;1
"Unit";"Zergling";"Larva";563;1
"Unit";"Zergling";"Larva";563;1
"Unit";"Zergling";"Larva";563;1
"Unit";"Zergling";"Larva";563;1
"Unit";"Zergling";"Larva";563;1
"Unit";"Zergling";"Larva";563;1
"Unit";"Zergling";"Larva";563;1
"Unit";"Zergling";"Larva";563;1
"Unit";"Zergling";"Larva";563;1
"Unit";"Zergling";"Larva";563;1
"Unit";"Zergling";"Larva";563;1
"Unit";"Zergling";"Larva";563;1
"Unit";"Zergling";"Larva";563;1
"Unit";"Zergling";"Larva";563;1
"Unit";"Zergling";"Larva";563;1
"Unit";"Zergling";"Larva";563;1
"Unit";"Zergling";"Larva";563;1
"Unit";"Zergling";"Larva";563;1
"Unit";"Zergling";"Larva";563;1
"Unit";"Zergling";"Larva";563;1
"Unit";"Zergling";"Larva";563;1
"Unit";"Zergling";"Larva";563;1
"Unit";"Zergling";"Larva";563;1
"Unit";"Zergling";"Larva";563;1
"Unit";"Zergling";"Larva";563;1
"Unit";"Zergling";"Larva";563;1
"Unit";"Zergling";"Larva";563;1
"Unit";"Zergling";"Larva";563;1
"Building";"Spire";NA;498;0
"Unit";"Zergling";"Larva";563;1
"Unit";"Zergling";"Larva";563;1
"Unit";"Zergling";"Larva";563;1
"Unit";"Zergling";"Larva";563;1
"Unit";"Zergling";"Larva";563;1
"Unit";"Zergling";"Larva";563;1
"Unit";"Zergling";"Larva";563;1
"Unit";"Zergling";"Larva";563;1
"Unit";"Zergling";"Larva";563;1
"Unit";"Zergling";"Larva";563;1
"Unit";"Zergling";"Larva";563;1
"Unit";"Zergling";"Larva";563;1
"Unit";"Zergling";"Larva";563;1
"Unit";"Zergling";"Larva";563;1
"Unit";"Zergling";"Larva";563;1
"Unit";"Zergling";"Larva";563;1
"Unit";"Zergling";"Larva";563;1
"Unit";"Zergling";"Larva";563;1
"Unit";"Zergling";"Larva";563;1
"Unit";"Zergling";"Larva";563;1
"Unit";"Zergling";"Larva";563;1
"Unit";"Zergling";"Larva";563;1
"Unit";"Zergling";"Larva";563;1
"Unit";"Zergling";"Larva";563;1
"Unit";"Zergling";"Larva";563;1
"Unit";"Zergling";"Larva";563;1
"Unit";"Zergling";"Larva";563;1
"Unit";"Zergling";"Larva";563;1
"Unit";"Zergling";"Larva";563;1
"Unit";"Zergling";"Larva";563;1
"Building";"CreepTumorQueen";NA;607;0
"Building";"CreepTumorQueen";NA;637;0
"Unit";"Zergling";"Larva";637;1
"Unit";"Zergling";"Larva";637;1
"Unit";"Zergling";"Larva";637;1
"Unit";"Zergling";"Larva";637;1
"Unit";"Zergling";"Larva";637;1
"Unit";"Zergling";"Larva";637;1
"Unit";"Zergling";"Larva";637;1
"Unit";"Zergling";"Larva";637;1
"Unit";"Zergling";"Larva";637;1
"Unit";"Zergling";"Larva";637;1
"Unit";"Zergling";"Larva";637;1
"Unit";"Zergling";"Larva";637;1
"Unit";"Zergling";"Larva";637;1
"Unit";"Zergling";"Larva";637;1
"Unit";"Zergling";"Larva";637;1
"Unit";"Zergling";"Larva";637;1
"Unit";"Zergling";"Larva";637;1
"Unit";"Zergling";"Larva";637;1
"Unit";"Zergling";"Larva";637;1
"Unit";"Zergling";"Larva";637;1
"Unit";"Zergling";"Larva";637;1
"Unit";"Zergling";"Larva";637;1
"Unit";"Zergling";"Larva";637;1
"Unit";"Zergling";"Larva";637;1
"Unit";"Zergling";"Larva";637;1
"Unit";"Zergling";"Larva";637;1
"Unit";"Zergling";"Larva";637;1
"Unit";"Zergling";"Larva";637;1
"Unit";"Zergling";"Larva";637;1
"Unit";"Zergling";"Larva";637;1
"Unit";"Zergling";"Larva";637;1
"Unit";"Zergling";"Larva";637;1
"Unit";"Zergling";"Larva";637;1
"Unit";"Zergling";"Larva";637;1
"Unit";"Zergling";"Larva";637;1
"Unit";"Zergling";"Larva";637;1
"Unit";"Baneling";"Zergling";637;0
"Unit";"Baneling";"Zergling";637;0
"Unit";"Baneling";"Zergling";637;0
"Unit";"Baneling";"Zergling";637;0
"Unit";"Baneling";"Zergling";637;0
"Unit";"Baneling";"Zergling";637;0
"Unit";"Baneling";"Zergling";637;0
"Unit";"Baneling";"Zergling";637;0
"Unit";"Baneling";"Zergling";637;0
"Unit";"Baneling";"Zergling";637;0
"Unit";"Baneling";"Zergling";637;0
"Unit";"Baneling";"Zergling";637;0
"Unit";"Baneling";"Zergling";637;0
"Unit";"Baneling";"Zergling";637;0
"Unit";"Baneling";"Zergling";637;0
"Unit";"Baneling";"Zergling";637;0
"Unit";"Baneling";"Zergling";637;0
"Unit";"Baneling";"Zergling";637;0
"Unit";"Baneling";"Zergling";637;0
"Unit";"Baneling";"Zergling";637;0
"Unit";"Baneling";"Zergling";637;0
"Unit";"Baneling";"Zergling";637;0
"Unit";"Baneling";"Zergling";637;0
"Building";"Spire";NA;553;0
"Unit";"Zergling";"Larva";637;1
"Unit";"Zergling";"Larva";637;1
