"type";"unit_name";"on_building";"total_supply";"supply"
"Unit";"Overlord";"Larva";14;0
"Building";"SpawningPool";NA;12;0
"Unit";"Zergling";"Larva";15;1
"Unit";"Zergling";"Larva";15;1
"Unit";"Zergling";"Larva";15;1
"Unit";"Zergling";"Larva";15;1
"Unit";"Zergling";"Larva";15;1
"Unit";"Zergling";"Larva";15;1
"Unit";"Zergling";"Larva";15;1
"Unit";"Zergling";"Larva";15;1
"Unit";"Overlord";"Larva";23;0
"Unit";"Queen";"Hatchery";21;2
"Building";"Hatchery";NA;21;0
"Unit";"Queen";"Hatchery";27;2
"Unit";"Overlord";"Larva";35;0
"Unit";"Zergling";"Larva";39;1
"Unit";"Zergling";"Larva";39;1
"Unit";"Zergling";"Larva";39;1
"Unit";"Zergling";"Larva";39;1
"Building";"Hatchery";NA;29;0
"Unit";"Queen";"Hatchery";39;2
"Unit";"Overlord";"Larva";40;0
"Unit";"Zergling";"Larva";48;1
"Unit";"Zergling";"Larva";48;1
"Unit";"Zergling";"Larva";48;1
"Unit";"Zergling";"Larva";48;1
"Unit";"Overlord";"Larva";50;0
"Building";"CreepTumorQueen";NA;53;0
"Building";"Extractor";NA;57;0
"Building";"Extractor";NA;57;0
"Building";"CreepTumor";NA;67;0
"Unit";"Overlord";"Larva";67;0
"Unit";"Overlord";"Larva";67;0
"Building";"Extractor";NA;67;0
"Building";"SporeCrawler";NA;70;0
"Building";"SporeCrawler";NA;70;0
"Building";"CreepTumor";NA;73;0
"Building";"SporeCrawler";NA;72;0
"Building";"RoachWarren";NA;69;0
"Unit";"Queen";"Hatchery";72;2
"Unit";"Zergling";"Larva";80;1
"Unit";"Zergling";"Larva";80;1
"Unit";"Zergling";"Larva";80;1
"Unit";"Zergling";"Larva";80;1
"Unit";"Zergling";"Larva";80;1
"Unit";"Zergling";"Larva";80;1
"Building";"CreepTumor";NA;81;0
"Unit";"Roach";"Larva";81;2
"Unit";"Roach";"Larva";81;2
"Building";"CreepTumorQueen";NA;87;0
"Unit";"Roach";"Larva";87;2
"Unit";"Roach";"Larva";87;2
"Unit";"Overlord";"Larva";87;0
"Unit";"Overlord";"Larva";87;0
"Unit";"Roach";"Larva";97;2
"Unit";"Roach";"Larva";97;2
"Unit";"Roach";"Larva";97;2
"Building";"EvolutionChamber";NA;93;0
"Unit";"Roach";"Larva";101;2
"Unit";"Zergling";"Larva";101;1
"Unit";"Zergling";"Larva";101;1
"Unit";"Zergling";"Larva";101;1
"Unit";"Zergling";"Larva";101;1
"Unit";"Zergling";"Larva";101;1
"Unit";"Zergling";"Larva";101;1
"Unit";"Zergling";"Larva";101;1
"Unit";"Zergling";"Larva";101;1
"Unit";"Zergling";"Larva";101;1
"Unit";"Zergling";"Larva";101;1
"Unit";"Zergling";"Larva";101;1
"Unit";"Zergling";"Larva";101;1
"Unit";"Zergling";"Larva";101;1
"Unit";"Zergling";"Larva";101;1
"Building";"CreepTumorQueen";NA;130;0
"Building";"CreepTumor";NA;130;0
"Unit";"Overlord";"Larva";130;0
"Building";"CreepTumor";NA;136;0
"Building";"Extractor";NA;130;0
"Building";"CreepTumorQueen";NA;136;0
"Unit";"Overlord";"Larva";136;0
"Building";"HydraliskDen";NA;136;0
"Unit";"Zergling";"Larva";141;1
"Unit";"Zergling";"Larva";141;1
"Unit";"Overlord";"Larva";141;0
"Unit";"Overlord";"Larva";141;0
"Unit";"Zergling";"Larva";141;1
"Unit";"Zergling";"Larva";141;1
"Unit";"Zergling";"Larva";141;1
"Unit";"Zergling";"Larva";141;1
"Unit";"Zergling";"Larva";141;1
"Unit";"Zergling";"Larva";141;1
"Unit";"Zergling";"Larva";141;1
"Unit";"Zergling";"Larva";141;1
"Unit";"Zergling";"Larva";141;1
"Unit";"Zergling";"Larva";141;1
"Unit";"Zergling";"Larva";141;1
"Unit";"Zergling";"Larva";141;1
"Unit";"Zergling";"Larva";141;1
"Unit";"Zergling";"Larva";141;1
"Unit";"Zergling";"Larva";141;1
"Unit";"Zergling";"Larva";141;1
"Building";"CreepTumor";NA;142;0
"Building";"CreepTumor";NA;160;0
"Building";"CreepTumor";NA;160;0
"Building";"CreepTumorQueen";NA;161;0
"Building";"BanelingNest";NA;141;0
"Unit";"Hydralisk";"Larva";142;2
"Unit";"Hydralisk";"Larva";142;2
"Unit";"Hydralisk";"Larva";142;2
"Unit";"Hydralisk";"Larva";142;2
"Building";"Extractor";NA;142;0
"Building";"CreepTumor";NA;162;0
"Unit";"Overlord";"Larva";162;0
"Unit";"Overlord";"Larva";162;0
"Building";"Extractor";NA;162;0
"Unit";"Hydralisk";"Larva";162;2
"Unit";"Hydralisk";"Larva";162;2
"Building";"CreepTumor";NA;172;0
"Building";"EvolutionChamber";NA;162;0
"Unit";"Hydralisk";"Larva";170;2
"Unit";"Hydralisk";"Larva";170;2
"Building";"CreepTumor";NA;173;0
"Building";"CreepTumor";NA;173;0
"Unit";"Hydralisk";"Larva";172;2
"Building";"Hatchery";NA;141;0
"Upgrade";"ZergMeleeWeaponsLevel1";"EvolutionChamber";141;0
"Unit";"Overlord";"Larva";175;0
"Unit";"Hydralisk";"Larva";173;2
"Unit";"Hydralisk";"Larva";173;2
"Building";"CreepTumor";NA;188;0
"Unit";"Zergling";"Larva";181;1
"Unit";"Zergling";"Larva";181;1
"Upgrade";"EvolveGroovedSpines";"HydraliskDen";162;0
"Unit";"Hydralisk";"Larva";181;2
"Unit";"Hydralisk";"Larva";181;2
"Unit";"Hydralisk";"Larva";181;2
"Building";"CreepTumor";NA;192;0
"Unit";"Zergling";"Larva";192;1
"Unit";"Zergling";"Larva";192;1
"Unit";"Zergling";"Larva";192;1
"Unit";"Zergling";"Larva";192;1
"Unit";"Zergling";"Larva";192;1
"Unit";"Zergling";"Larva";192;1
"Unit";"Zergling";"Larva";192;1
"Unit";"Zergling";"Larva";192;1
"Unit";"Zergling";"Larva";192;1
"Unit";"Zergling";"Larva";192;1
"Unit";"Zergling";"Larva";192;1
"Unit";"Zergling";"Larva";192;1
"Unit";"Hydralisk";"Larva";188;2
"Unit";"Hydralisk";"Larva";188;2
"Building";"Extractor";NA;200;0
"Unit";"Overlord";"Larva";212;0
"Unit";"Overlord";"Larva";212;0
"Building";"CreepTumor";NA;219;0
"Building";"CreepTumor";NA;219;0
"Unit";"Zergling";"Larva";218;1
"Unit";"Zergling";"Larva";218;1
"Building";"CreepTumor";NA;219;0
"Unit";"Zergling";"Larva";219;1
"Unit";"Zergling";"Larva";219;1
"Unit";"Zergling";"Larva";219;1
"Unit";"Zergling";"Larva";219;1
"Unit";"Zergling";"Larva";219;1
"Unit";"Zergling";"Larva";219;1
"Unit";"Hydralisk";"Larva";212;2
"Unit";"Hydralisk";"Larva";212;2
"Unit";"Hydralisk";"Larva";212;2
"Unit";"Hydralisk";"Larva";212;2
"Unit";"Baneling";"Zergling";219;0
"Unit";"Baneling";"Zergling";219;0
"Unit";"Baneling";"Zergling";219;0
"Unit";"Baneling";"Zergling";219;0
"Unit";"Baneling";"Zergling";219;0
"Unit";"Baneling";"Zergling";219;0
"Unit";"Baneling";"Zergling";219;0
"Unit";"Baneling";"Zergling";219;0
"Unit";"Baneling";"Zergling";219;0
"Unit";"Baneling";"Zergling";219;0
"Unit";"Baneling";"Zergling";219;0
"Unit";"Overlord";"Larva";235;0
"Unit";"Overlord";"Larva";235;0
"Unit";"Hydralisk";"Larva";235;2
"Unit";"Hydralisk";"Larva";235;2
"Unit";"Hydralisk";"Larva";235;2
"Unit";"Hydralisk";"Larva";235;2
"Upgrade";"EvolveMuscularAugments";"HydraliskDen";219;0
"Unit";"Baneling";"Zergling";235;0
"Unit";"Baneling";"Zergling";235;0
"Unit";"Baneling";"Zergling";235;0
"Unit";"Baneling";"Zergling";235;0
"Unit";"Baneling";"Zergling";235;0
"Unit";"Baneling";"Zergling";235;0
"Unit";"Baneling";"Zergling";235;0
"Unit";"Baneling";"Zergling";235;0
"Unit";"Zergling";"Larva";235;1
"Unit";"Zergling";"Larva";235;1
"Unit";"Zergling";"Larva";235;1
"Unit";"Zergling";"Larva";235;1
"Unit";"Zergling";"Larva";235;1
"Unit";"Zergling";"Larva";235;1
"Unit";"Zergling";"Larva";235;1
"Unit";"Zergling";"Larva";235;1
"Unit";"Zergling";"Larva";235;1
"Unit";"Zergling";"Larva";235;1
"Unit";"Zergling";"Larva";235;1
"Unit";"Zergling";"Larva";235;1
"Unit";"Zergling";"Larva";235;1
"Unit";"Zergling";"Larva";235;1
"Unit";"Zergling";"Larva";235;1
"Unit";"Zergling";"Larva";235;1
"Unit";"Zergling";"Larva";235;1
"Unit";"Zergling";"Larva";235;1
"Unit";"Zergling";"Larva";235;1
"Unit";"Zergling";"Larva";235;1
"Unit";"Zergling";"Larva";235;1
"Unit";"Zergling";"Larva";235;1
"Unit";"Zergling";"Larva";235;1
"Unit";"Zergling";"Larva";235;1
"Unit";"Zergling";"Larva";235;1
"Unit";"Zergling";"Larva";235;1
"Unit";"Zergling";"Larva";235;1
"Unit";"Zergling";"Larva";235;1
"Unit";"Baneling";"Zergling";235;0
"Unit";"Baneling";"Zergling";235;0
"Unit";"Baneling";"Zergling";235;0
"Unit";"Baneling";"Zergling";235;0
"Unit";"Baneling";"Zergling";277;0
"Unit";"Baneling";"Zergling";277;0
"Unit";"Baneling";"Zergling";277;0
"Unit";"Baneling";"Zergling";277;0
"Unit";"Baneling";"Zergling";277;0
"Unit";"Baneling";"Zergling";277;0
"Unit";"Baneling";"Zergling";277;0
"Unit";"Baneling";"Zergling";277;0
"Unit";"Baneling";"Zergling";277;0
"Unit";"Baneling";"Zergling";277;0
"Unit";"Baneling";"Zergling";277;0
"Unit";"Baneling";"Zergling";277;0
"Unit";"Baneling";"Zergling";277;0
"Unit";"Baneling";"Zergling";277;0
"Unit";"Baneling";"Zergling";277;0
"Unit";"Zergling";"Larva";277;1
"Unit";"Zergling";"Larva";277;1
"Unit";"Zergling";"Larva";277;1
"Unit";"Zergling";"Larva";277;1
"Unit";"Hydralisk";"Larva";277;2
"Unit";"Hydralisk";"Larva";277;2
"Upgrade";"ZergMeleeWeaponsLevel2";"EvolutionChamber";235;0
