"type";"unit_name";"on_building";"total_supply";"supply"
"Unit";"Overlord";"Larva";14;0
"Building";"SpawningPool";NA;12;0
"Unit";"Zergling";"Larva";15;1
"Unit";"Zergling";"Larva";15;1
"Unit";"Zergling";"Larva";15;1
"Unit";"Zergling";"Larva";15;1
"Unit";"Zergling";"Larva";15;1
"Unit";"Zergling";"Larva";15;1
"Unit";"Zergling";"Larva";15;1
"Unit";"Zergling";"Larva";15;1
"Unit";"Zergling";"Larva";23;1
"Unit";"Zergling";"Larva";23;1
"Unit";"Zergling";"Larva";23;1
"Unit";"Zergling";"Larva";23;1
"Unit";"Overlord";"Larva";23;0
"Unit";"Queen";"Hatchery";21;2
"Building";"Hatchery";NA;21;0
"Unit";"Queen";"Hatchery";29;2
"Unit";"Overlord";"Larva";42;0
"Unit";"Overlord";"Larva";42;0
"Unit";"Queen";"Hatchery";40;2
"Building";"Extractor";NA;42;0
"Unit";"Overlord";"Larva";42;0
"Building";"Hatchery";NA;35;0
"Building";"CreepTumorQueen";NA;47;0
"Unit";"Queen";"Hatchery";42;2
"Building";"CreepTumor";NA;55;0
"Building";"CreepTumorQueen";NA;55;0
"Building";"Extractor";NA;52;0
"Building";"SporeCrawler";NA;55;0
"Unit";"Queen";"Hatchery";50;2
"Unit";"Overlord";"Larva";57;0
"Building";"CreepTumor";NA;67;0
"Building";"CreepTumorQueen";NA;67;0
"Unit";"Overlord";"Larva";67;0
"Building";"CreepTumorQueen";NA;71;0
"Building";"SporeCrawler";NA;67;0
"Building";"BanelingNest";NA;71;0
"Building";"CreepTumor";NA;82;0
"Building";"CreepTumor";NA;82;0
"Unit";"Zergling";"Larva";82;1
"Unit";"Zergling";"Larva";82;1
"Unit";"Zergling";"Larva";82;1
"Unit";"Zergling";"Larva";82;1
"Unit";"Zergling";"Larva";82;1
"Unit";"Zergling";"Larva";82;1
"Unit";"Zergling";"Larva";82;1
"Unit";"Zergling";"Larva";82;1
"Unit";"Zergling";"Larva";82;1
"Unit";"Zergling";"Larva";82;1
"Unit";"Zergling";"Larva";82;1
"Unit";"Zergling";"Larva";82;1
"Unit";"Zergling";"Larva";82;1
"Unit";"Zergling";"Larva";82;1
"Unit";"Zergling";"Larva";82;1
"Unit";"Zergling";"Larva";82;1
"Unit";"Overlord";"Larva";82;0
"Unit";"Overlord";"Larva";82;0
"Building";"CreepTumorQueen";NA;82;0
"Unit";"Overlord";"Larva";82;0
"Unit";"Overlord";"Larva";82;0
"Building";"CreepTumorQueen";NA;98;0
"Unit";"Zergling";"Larva";98;1
"Unit";"Zergling";"Larva";98;1
"Unit";"Zergling";"Larva";98;1
"Unit";"Zergling";"Larva";98;1
"Unit";"Zergling";"Larva";98;1
"Unit";"Zergling";"Larva";98;1
"Unit";"Zergling";"Larva";98;1
"Unit";"Zergling";"Larva";98;1
"Unit";"Zergling";"Larva";98;1
"Unit";"Zergling";"Larva";98;1
"Unit";"Zergling";"Larva";98;1
"Unit";"Zergling";"Larva";98;1
"Unit";"Zergling";"Larva";98;1
"Unit";"Zergling";"Larva";98;1
"Unit";"Zergling";"Larva";98;1
"Unit";"Zergling";"Larva";98;1
"Unit";"Zergling";"Larva";98;1
"Unit";"Zergling";"Larva";98;1
"Building";"CreepTumor";NA;98;0
"Building";"CreepTumor";NA;98;0
"Unit";"Zergling";"Larva";98;1
"Unit";"Zergling";"Larva";98;1
"Unit";"Zergling";"Larva";98;1
"Unit";"Zergling";"Larva";98;1
"Unit";"Zergling";"Larva";98;1
"Unit";"Zergling";"Larva";98;1
"Unit";"Zergling";"Larva";98;1
"Unit";"Zergling";"Larva";98;1
"Unit";"Zergling";"Larva";98;1
"Unit";"Zergling";"Larva";98;1
"Unit";"Zergling";"Larva";98;1
"Unit";"Zergling";"Larva";98;1
"Unit";"Zergling";"Larva";98;1
"Unit";"Zergling";"Larva";98;1
"Unit";"Zergling";"Larva";98;1
"Unit";"Zergling";"Larva";98;1
"Building";"CreepTumorQueen";NA;116;0
"Unit";"Zergling";"Larva";116;1
"Unit";"Zergling";"Larva";116;1
"Unit";"Zergling";"Larva";116;1
"Unit";"Zergling";"Larva";116;1
"Unit";"Baneling";"Zergling";128;0
"Unit";"Baneling";"Zergling";128;0
"Unit";"Baneling";"Zergling";128;0
"Unit";"Baneling";"Zergling";128;0
"Unit";"Baneling";"Zergling";128;0
"Unit";"Baneling";"Zergling";128;0
"Unit";"Baneling";"Zergling";128;0
"Unit";"Baneling";"Zergling";128;0
"Building";"EvolutionChamber";NA;116;0
"Unit";"Zergling";"Larva";132;1
"Unit";"Zergling";"Larva";132;1
"Unit";"Zergling";"Larva";132;1
"Unit";"Zergling";"Larva";132;1
"Unit";"Zergling";"Larva";132;1
"Unit";"Zergling";"Larva";132;1
"Unit";"Zergling";"Larva";132;1
"Unit";"Zergling";"Larva";132;1
"Unit";"Zergling";"Larva";132;1
"Unit";"Zergling";"Larva";132;1
"Unit";"Zergling";"Larva";132;1
"Unit";"Zergling";"Larva";132;1
"Unit";"Zergling";"Larva";132;1
"Unit";"Zergling";"Larva";132;1
"Unit";"Zergling";"Larva";132;1
"Unit";"Zergling";"Larva";132;1
"Unit";"Zergling";"Larva";132;1
"Unit";"Zergling";"Larva";132;1
"Unit";"Zergling";"Larva";132;1
"Unit";"Zergling";"Larva";132;1
"Building";"CreepTumorQueen";NA;136;0
"Building";"CreepTumor";NA;136;0
"Building";"CreepTumor";NA;136;0
"Building";"HydraliskDen";NA;128;0
"Building";"Extractor";NA;136;0
"Building";"Extractor";NA;136;0
"Building";"CreepTumor";NA;167;0
"Building";"Hatchery";NA;98;0
"Building";"CreepTumor";NA;167;0
"Building";"CreepTumor";NA;167;0
"Building";"Extractor";NA;167;0
"Building";"Extractor";NA;167;0
"Building";"CreepTumor";NA;173;0
"Building";"CreepTumor";NA;173;0
"Building";"CreepTumor";NA;173;0
"Building";"EvolutionChamber";NA;169;0
"Building";"Spire";NA;161;0
"Unit";"Zergling";"Larva";191;1
"Unit";"Zergling";"Larva";191;1
"Unit";"Zergling";"Larva";191;1
"Unit";"Zergling";"Larva";191;1
"Unit";"Zergling";"Larva";191;1
"Unit";"Zergling";"Larva";191;1
"Building";"SporeCrawler";NA;191;0
"Unit";"Overlord";"Larva";191;0
"Unit";"Overlord";"Larva";191;0
"Unit";"Overlord";"Larva";191;0
"Unit";"Overlord";"Larva";191;0
"Unit";"Overlord";"Larva";191;0
"Building";"SporeCrawler";NA;191;0
"Building";"SporeCrawler";NA;191;0
"Building";"Extractor";NA;191;0
"Building";"Extractor";NA;191;0
"Building";"CreepTumor";NA;193;0
"Building";"CreepTumor";NA;193;0
"Building";"CreepTumor";NA;197;0
"Building";"CreepTumorQueen";NA;197;0
"Building";"CreepTumorQueen";NA;201;0
"Building";"CreepTumor";NA;201;0
"Building";"CreepTumor";NA;201;0
"Unit";"Baneling";"Zergling";201;0
"Unit";"Baneling";"Zergling";201;0
"Unit";"Baneling";"Zergling";201;0
"Unit";"Baneling";"Zergling";201;0
"Unit";"Baneling";"Zergling";201;0
"Unit";"Baneling";"Zergling";201;0
"Unit";"Baneling";"Zergling";201;0
"Unit";"Baneling";"Zergling";201;0
"Unit";"Baneling";"Zergling";201;0
"Unit";"Zergling";"Larva";201;1
"Unit";"Zergling";"Larva";201;1
"Unit";"Zergling";"Larva";201;1
"Unit";"Zergling";"Larva";201;1
"Unit";"Zergling";"Larva";201;1
"Unit";"Zergling";"Larva";201;1
"Unit";"Zergling";"Larva";201;1
"Unit";"Zergling";"Larva";201;1
"Unit";"Zergling";"Larva";201;1
"Unit";"Zergling";"Larva";201;1
"Unit";"Zergling";"Larva";201;1
"Unit";"Zergling";"Larva";201;1
"Unit";"Zergling";"Larva";201;1
"Unit";"Zergling";"Larva";201;1
"Unit";"Zergling";"Larva";201;1
"Unit";"Zergling";"Larva";201;1
"Unit";"Zergling";"Larva";201;1
"Unit";"Zergling";"Larva";201;1
"Unit";"Zergling";"Larva";201;1
"Unit";"Zergling";"Larva";201;1
"Unit";"Zergling";"Larva";201;1
"Unit";"Zergling";"Larva";201;1
"Unit";"Zergling";"Larva";202;1
"Unit";"Zergling";"Larva";202;1
"Unit";"Zergling";"Larva";202;1
"Unit";"Zergling";"Larva";202;1
"Unit";"Zergling";"Larva";202;1
"Unit";"Zergling";"Larva";202;1
"Unit";"Zergling";"Larva";202;1
"Unit";"Zergling";"Larva";202;1
"Unit";"Zergling";"Larva";203;1
"Unit";"Zergling";"Larva";203;1
"Upgrade";"ZergGroundArmorsLevel1";"EvolutionChamber";179;0
"Building";"Hatchery";NA;191;0
"Building";"InfestationPit";NA;204;0
"Building";"CreepTumor";NA;239;0
"Building";"CreepTumor";NA;239;0
"Unit";"Corruptor";"Larva";239;2
"Unit";"Corruptor";"Larva";239;2
"Unit";"Corruptor";"Larva";239;2
"Unit";"Corruptor";"Larva";239;2
"Unit";"Corruptor";"Larva";239;2
"Unit";"Corruptor";"Larva";239;2
"Unit";"Corruptor";"Larva";239;2
"Building";"Hatchery";NA;197;0
"Building";"CreepTumor";NA;239;0
"Building";"CreepTumor";NA;239;0
"Building";"CreepTumor";NA;239;0
"Building";"CreepTumor";NA;239;0
"Building";"CreepTumor";NA;239;0
"Unit";"Corruptor";"Larva";239;2
"Unit";"Corruptor";"Larva";239;2
"Unit";"Corruptor";"Larva";239;2
"Unit";"Corruptor";"Larva";239;2
"Upgrade";"ZergMeleeWeaponsLevel1";"EvolutionChamber";197;0
"Building";"CreepTumorQueen";NA;253;0
"Building";"CreepTumorQueen";NA;253;0
"Building";"Hatchery";NA;201;0
"Building";"CreepTumor";NA;253;0
"Building";"CreepTumor";NA;253;0
"Unit";"Zergling";"Larva";253;1
"Unit";"Zergling";"Larva";253;1
"Unit";"Zergling";"Larva";253;1
"Unit";"Zergling";"Larva";253;1
"Unit";"Zergling";"Larva";253;1
"Unit";"Zergling";"Larva";253;1
"Unit";"Zergling";"Larva";253;1
"Unit";"Zergling";"Larva";253;1
"Unit";"Zergling";"Larva";253;1
"Unit";"Zergling";"Larva";253;1
"Unit";"Zergling";"Larva";253;1
"Unit";"Zergling";"Larva";253;1
"Unit";"Zergling";"Larva";253;1
"Unit";"Zergling";"Larva";253;1
"Unit";"Zergling";"Larva";253;1
"Unit";"Zergling";"Larva";253;1
"Unit";"Corruptor";"Larva";253;2
"Unit";"Corruptor";"Larva";253;2
"Building";"Extractor";NA;266;0
"Building";"Extractor";NA;266;0
"Building";"CreepTumorQueen";NA;289;0
"Unit";"Baneling";"Zergling";292;0
"Unit";"Baneling";"Zergling";292;0
"Unit";"Baneling";"Zergling";292;0
"Unit";"Baneling";"Zergling";292;0
"Unit";"Baneling";"Zergling";292;0
"Unit";"Baneling";"Zergling";292;0
"Unit";"Baneling";"Zergling";292;0
"Unit";"Baneling";"Zergling";292;0
"Building";"CreepTumor";NA;292;0
"Building";"CreepTumor";NA;292;0
"Building";"CreepTumor";NA;292;0
"Building";"CreepTumor";NA;292;0
"Building";"CreepTumor";NA;292;0
"Building";"CreepTumor";NA;292;0
"Building";"CreepTumor";NA;292;0
"Unit";"Zergling";"Larva";292;1
"Unit";"Zergling";"Larva";292;1
"Unit";"Zergling";"Larva";292;1
"Unit";"Zergling";"Larva";292;1
"Unit";"Zergling";"Larva";292;1
"Unit";"Zergling";"Larva";292;1
"Unit";"Zergling";"Larva";292;1
"Unit";"Zergling";"Larva";292;1
"Unit";"Zergling";"Larva";292;1
"Unit";"Zergling";"Larva";292;1
"Unit";"Zergling";"Larva";292;1
"Unit";"Zergling";"Larva";292;1
"Unit";"Zergling";"Larva";292;1
"Unit";"Zergling";"Larva";292;1
"Unit";"Zergling";"Larva";292;1
"Unit";"Zergling";"Larva";292;1
"Unit";"Zergling";"Larva";292;1
"Unit";"Zergling";"Larva";292;1
"Unit";"Corruptor";"Larva";289;2
"Unit";"Corruptor";"Larva";289;2
"Unit";"Corruptor";"Larva";289;2
"Unit";"Corruptor";"Larva";289;2
"Building";"CreepTumorQueen";NA;292;0
"Unit";"Overlord";"Larva";292;0
"Unit";"Overlord";"Larva";294;0
"Unit";"Overlord";"Larva";294;0
"Unit";"Overlord";"Larva";294;0
"Unit";"Overlord";"Larva";294;0
"Building";"CreepTumor";NA;318;0
"Unit";"Zergling";"Larva";318;1
"Unit";"Zergling";"Larva";318;1
"Unit";"Zergling";"Larva";318;1
"Unit";"Zergling";"Larva";318;1
"Unit";"Zergling";"Larva";318;1
"Unit";"Zergling";"Larva";318;1
"Unit";"Zergling";"Larva";318;1
"Unit";"Zergling";"Larva";318;1
"Unit";"Zergling";"Larva";318;1
"Unit";"Zergling";"Larva";318;1
"Unit";"Zergling";"Larva";318;1
"Unit";"Zergling";"Larva";318;1
"Unit";"Zergling";"Larva";318;1
"Unit";"Zergling";"Larva";318;1
"Building";"CreepTumor";NA;318;0
"Unit";"Zergling";"Larva";318;1
"Unit";"Zergling";"Larva";318;1
"Unit";"Zergling";"Larva";318;1
"Unit";"Zergling";"Larva";318;1
"Unit";"Zergling";"Larva";318;1
"Unit";"Zergling";"Larva";318;1
"Unit";"Corruptor";"Larva";318;2
"Unit";"Corruptor";"Larva";318;2
"Unit";"Corruptor";"Larva";318;2
"Unit";"Corruptor";"Larva";318;2
"Unit";"Corruptor";"Larva";318;2
"Unit";"Corruptor";"Larva";318;2
"Unit";"Corruptor";"Larva";318;2
"Unit";"Zergling";"Larva";318;1
"Unit";"Zergling";"Larva";318;1
"Unit";"Zergling";"Larva";318;1
"Unit";"Zergling";"Larva";318;1
"Unit";"Zergling";"Larva";318;1
"Unit";"Zergling";"Larva";318;1
"Unit";"Zergling";"Larva";318;1
"Unit";"Zergling";"Larva";318;1
"Unit";"Zergling";"Larva";318;1
"Unit";"Zergling";"Larva";318;1
"Building";"CreepTumor";NA;338;0
"Building";"CreepTumor";NA;338;0
"Building";"CreepTumor";NA;338;0
"Unit";"Baneling";"Zergling";352;0
"Unit";"Baneling";"Zergling";352;0
"Unit";"Baneling";"Zergling";352;0
"Unit";"Baneling";"Zergling";354;0
"Unit";"Baneling";"Zergling";354;0
"Unit";"Baneling";"Zergling";354;0
"Unit";"Baneling";"Zergling";354;0
"Unit";"Baneling";"Zergling";362;0
"Building";"CreepTumorQueen";NA;362;0
"Upgrade";"EvolveMuscularAugments";"HydraliskDen";318;0
"Upgrade";"ZergMeleeWeaponsLevel2";"EvolutionChamber";292;0
"Unit";"Corruptor";"Larva";362;2
"Unit";"Corruptor";"Larva";362;2
"Unit";"Corruptor";"Larva";362;2
"Unit";"Corruptor";"Larva";362;2
"Building";"CreepTumor";NA;362;0
"Building";"CreepTumor";NA;362;0
"Building";"CreepTumorQueen";NA;362;0
"Building";"CreepTumor";NA;362;0
"Unit";"Zergling";"Larva";362;1
"Unit";"Zergling";"Larva";362;1
"Unit";"Zergling";"Larva";362;1
"Unit";"Zergling";"Larva";362;1
"Unit";"Zergling";"Larva";362;1
"Unit";"Zergling";"Larva";362;1
"Unit";"Zergling";"Larva";362;1
"Unit";"Zergling";"Larva";362;1
"Unit";"Zergling";"Larva";362;1
"Unit";"Zergling";"Larva";362;1
"Unit";"Zergling";"Larva";362;1
"Unit";"Zergling";"Larva";362;1
"Unit";"Zergling";"Larva";362;1
"Unit";"Zergling";"Larva";362;1
"Unit";"Zergling";"Larva";362;1
"Unit";"Zergling";"Larva";362;1
"Unit";"Zergling";"Larva";362;1
"Unit";"Zergling";"Larva";362;1
"Unit";"Zergling";"Larva";362;1
"Unit";"Zergling";"Larva";362;1
"Unit";"Zergling";"Larva";362;1
"Unit";"Zergling";"Larva";362;1
"Unit";"Zergling";"Larva";362;1
"Unit";"Zergling";"Larva";362;1
"Unit";"Zergling";"Larva";362;1
"Unit";"Zergling";"Larva";362;1
"Unit";"Zergling";"Larva";362;1
"Unit";"Zergling";"Larva";362;1
"Unit";"Zergling";"Larva";362;1
"Unit";"Zergling";"Larva";362;1
"Upgrade";"ZergMissileWeaponsLevel1";"EvolutionChamber";318;0
"Unit";"Corruptor";"Larva";362;2
"Unit";"Corruptor";"Larva";362;2
"Unit";"Corruptor";"Larva";362;2
"Unit";"Corruptor";"Larva";362;2
"Unit";"Baneling";"Zergling";370;0
"Unit";"Baneling";"Zergling";370;0
"Unit";"Baneling";"Zergling";370;0
"Unit";"Baneling";"Zergling";370;0
"Unit";"Baneling";"Zergling";370;0
"Unit";"Baneling";"Zergling";370;0
"Unit";"Baneling";"Zergling";370;0
"Unit";"Baneling";"Zergling";370;0
"Unit";"Baneling";"Zergling";370;0
"Unit";"Baneling";"Zergling";370;0
"Unit";"Baneling";"Zergling";370;0
"Building";"Extractor";NA;370;0
"Building";"Extractor";NA;370;0
"Building";"CreepTumor";NA;400;0
"Unit";"Zergling";"Larva";400;1
"Unit";"Zergling";"Larva";400;1
"Unit";"Zergling";"Larva";400;1
"Unit";"Zergling";"Larva";400;1
"Unit";"Zergling";"Larva";400;1
"Unit";"Zergling";"Larva";400;1
"Unit";"Zergling";"Larva";400;1
"Unit";"Zergling";"Larva";400;1
"Unit";"Zergling";"Larva";400;1
"Unit";"Zergling";"Larva";400;1
"Unit";"Zergling";"Larva";400;1
"Unit";"Zergling";"Larva";400;1
"Unit";"Zergling";"Larva";400;1
"Unit";"Zergling";"Larva";400;1
"Unit";"Zergling";"Larva";400;1
"Unit";"Zergling";"Larva";400;1
"Unit";"Baneling";"Zergling";400;0
"Unit";"Baneling";"Zergling";400;0
"Unit";"Baneling";"Zergling";400;0
"Unit";"Zergling";"Larva";400;1
"Unit";"Zergling";"Larva";400;1
"Unit";"Baneling";"Zergling";400;0
"Unit";"Baneling";"Zergling";400;0
"Unit";"Baneling";"Zergling";400;0
"Unit";"Baneling";"Zergling";400;0
"Upgrade";"EvolveGroovedSpines";"HydraliskDen";362;0
"Building";"UltraliskCavern";NA;370;0
