"type";"unit_name";"on_building";"total_supply";"supply"
"Unit";"Overlord";"Larva";13;0
"Building";"Extractor";NA;17;0
"Building";"SpawningPool";NA;19;0
"Building";"Hatchery";NA;17;0
"Unit";"Zergling";"Larva";23;1
"Unit";"Zergling";"Larva";23;1
"Unit";"Zergling";"Larva";23;1
"Unit";"Zergling";"Larva";23;1
"Unit";"Queen";"Hatchery";23;2
"Unit";"Queen";"Hatchery";23;2
"Unit";"Overlord";"Larva";29;0
"Unit";"Queen";"Hatchery";33;2
"Unit";"Overlord";"Larva";37;0
"Unit";"Zergling";"Larva";37;1
"Unit";"Zergling";"Larva";37;1
"Building";"CreepTumorQueen";NA;41;0
"Unit";"Zergling";"Larva";41;1
"Unit";"Zergling";"Larva";41;1
"Unit";"Zergling";"Larva";43;1
"Unit";"Zergling";"Larva";43;1
"Building";"Hatchery";NA;31;0
"Unit";"Overlord";"Larva";43;0
"Unit";"Queen";"Hatchery";41;2
"Building";"RoachWarren";NA;41;0
"Building";"SporeCrawler";NA;47;0
"Building";"CreepTumorQueen";NA;49;0
"Building";"SporeCrawler";NA;49;0
"Unit";"Zergling";"Larva";62;1
"Unit";"Zergling";"Larva";62;1
"Unit";"Zergling";"Larva";62;1
"Unit";"Zergling";"Larva";62;1
"Unit";"Zergling";"Larva";62;1
"Unit";"Zergling";"Larva";62;1
"Unit";"Zergling";"Larva";62;1
"Unit";"Zergling";"Larva";62;1
"Unit";"Zergling";"Larva";62;1
"Unit";"Zergling";"Larva";62;1
"Unit";"Zergling";"Larva";62;1
"Unit";"Zergling";"Larva";62;1
"Unit";"Zergling";"Larva";62;1
"Unit";"Zergling";"Larva";62;1
"Building";"SporeCrawler";NA;62;0
"Unit";"Overlord";"Larva";62;0
"Building";"Extractor";NA;62;0
"Building";"Extractor";NA;76;0
"Building";"EvolutionChamber";NA;76;0
"Building";"EvolutionChamber";NA;76;0
"Building";"Extractor";NA;82;0
"Unit";"Overlord";"Larva";89;0
"Unit";"Overlord";"Larva";89;0
"Unit";"Roach";"Larva";97;2
"Unit";"Roach";"Larva";97;2
"Unit";"Roach";"Larva";97;2
"Unit";"Roach";"Larva";97;2
"Unit";"Roach";"Larva";97;2
"Unit";"Roach";"Larva";97;2
"Unit";"Roach";"Larva";97;2
"Unit";"Roach";"Larva";97;2
"Building";"CreepTumor";NA;111;0
"Unit";"Overlord";"Larva";97;0
"Unit";"Overlord";"Larva";97;0
"Unit";"Overlord";"Larva";97;0
"Unit";"Overlord";"Larva";97;0
"Unit";"Overlord";"Larva";113;0
"Building";"CreepTumor";NA;113;0
"Building";"CreepTumorQueen";NA;113;0
"Upgrade";"GlialReconstitution";"RoachWarren";97;0
"Building";"CreepTumorQueen";NA;113;0
"Building";"CreepTumorQueen";NA;113;0
"Building";"CreepTumorQueen";NA;113;0
"Building";"CreepTumorQueen";NA;113;0
"Building";"Extractor";NA;113;0
"Building";"HydraliskDen";NA;113;0
"Building";"Extractor";NA;113;0
"Unit";"Overlord";"Larva";117;0
"Unit";"Overlord";"Larva";118;0
"Unit";"Roach";"Larva";127;2
"Unit";"Roach";"Larva";127;2
"Unit";"Roach";"Larva";127;2
"Unit";"Roach";"Larva";127;2
"Unit";"Roach";"Larva";127;2
"Unit";"Roach";"Larva";127;2
"Unit";"Roach";"Larva";127;2
"Unit";"Roach";"Larva";127;2
"Unit";"Roach";"Larva";127;2
"Upgrade";"ZergMissileWeaponsLevel1";"EvolutionChamber";97;0
"Upgrade";"ZergGroundArmorsLevel1";"EvolutionChamber";97;0
"Building";"CreepTumorQueen";NA;145;0
"Building";"CreepTumor";NA;145;0
"Building";"CreepTumor";NA;145;0
"Building";"CreepTumor";NA;146;0
"Building";"CreepTumor";NA;149;0
"Building";"CreepTumor";NA;149;0
"Building";"CreepTumor";NA;149;0
"Building";"CreepTumorQueen";NA;149;0
"Building";"CreepTumor";NA;149;0
"Unit";"Overlord";"Larva";149;0
"Unit";"Overlord";"Larva";149;0
"Unit";"Overlord";"Larva";149;0
"Unit";"Overlord";"Larva";149;0
"Building";"CreepTumor";NA;149;0
"Unit";"Hydralisk";"Larva";149;2
"Building";"CreepTumor";NA;149;0
"Unit";"Hydralisk";"Larva";149;2
"Unit";"Hydralisk";"Larva";149;2
"Building";"CreepTumor";NA;149;0
"Unit";"Hydralisk";"Larva";149;2
"Building";"CreepTumor";NA;149;0
"Building";"CreepTumor";NA;149;0
"Building";"CreepTumor";NA;149;0
"Building";"CreepTumor";NA;149;0
"Building";"CreepTumorQueen";NA;157;0
"Upgrade";"EvolveGroovedSpines";"HydraliskDen";149;0
"Unit";"Hydralisk";"Larva";149;2
"Unit";"Hydralisk";"Larva";149;2
"Unit";"Hydralisk";"Larva";149;2
"Unit";"Hydralisk";"Larva";149;2
"Unit";"Hydralisk";"Larva";149;2
"Unit";"Hydralisk";"Larva";149;2
"Unit";"Hydralisk";"Larva";149;2
"Unit";"Hydralisk";"Larva";149;2
"Building";"CreepTumor";NA;157;0
"Building";"Hatchery";NA;145;0
"Building";"CreepTumor";NA;173;0
"Building";"CreepTumor";NA;173;0
"Building";"CreepTumor";NA;173;0
"Building";"CreepTumor";NA;173;0
"Building";"CreepTumor";NA;173;0
"Building";"CreepTumor";NA;173;0
"Building";"CreepTumor";NA;173;0
"Unit";"Hydralisk";"Larva";173;2
"Unit";"Hydralisk";"Larva";173;2
"Unit";"Hydralisk";"Larva";173;2
"Unit";"Hydralisk";"Larva";173;2
"Unit";"Hydralisk";"Larva";173;2
"Unit";"Hydralisk";"Larva";173;2
"Unit";"Hydralisk";"Larva";173;2
"Unit";"Hydralisk";"Larva";173;2
"Unit";"Hydralisk";"Larva";173;2
"Unit";"Hydralisk";"Larva";173;2
"Unit";"Hydralisk";"Larva";173;2
"Unit";"Hydralisk";"Larva";173;2
"Unit";"Hydralisk";"Larva";173;2
"Building";"CreepTumor";NA;173;0
"Building";"CreepTumor";NA;173;0
"Unit";"Overlord";"Larva";173;0
"Unit";"Overlord";"Larva";173;0
"Unit";"Overlord";"Larva";173;0
"Unit";"Overlord";"Larva";173;0
"Building";"CreepTumor";NA;206;0
"Building";"CreepTumor";NA;206;0
"Building";"CreepTumor";NA;206;0
"Unit";"Overlord";"Larva";206;0
"Unit";"Overlord";"Larva";206;0
"Building";"CreepTumor";NA;206;0
"Upgrade";"EvolveMuscularAugments";"HydraliskDen";173;0
"Unit";"Roach";"Larva";206;2
"Unit";"Roach";"Larva";206;2
"Unit";"Roach";"Larva";206;2
"Unit";"Roach";"Larva";206;2
"Unit";"Roach";"Larva";206;2
"Unit";"Roach";"Larva";206;2
"Unit";"Roach";"Larva";206;2
"Unit";"Roach";"Larva";206;2
"Unit";"Roach";"Larva";206;2
"Unit";"Roach";"Larva";206;2
"Building";"CreepTumor";NA;226;0
"Upgrade";"ZergMissileWeaponsLevel2";"EvolutionChamber";157;0
"Building";"CreepTumor";NA;226;0
"Upgrade";"ZergGroundArmorsLevel2";"EvolutionChamber";157;0
"Building";"Extractor";NA;226;0
"Unit";"Hydralisk";"Larva";226;2
"Unit";"Hydralisk";"Larva";226;2
"Unit";"Hydralisk";"Larva";226;2
"Unit";"Hydralisk";"Larva";226;2
"Unit";"Hydralisk";"Larva";226;2
"Unit";"Hydralisk";"Larva";226;2
"Unit";"Hydralisk";"Larva";226;2
"Unit";"Hydralisk";"Larva";226;2
"Unit";"Hydralisk";"Larva";226;2
"Unit";"Hydralisk";"Larva";226;2
"Unit";"Hydralisk";"Larva";226;2
"Building";"Extractor";NA;226;0
"Unit";"Hydralisk";"Larva";226;2
"Unit";"Roach";"Larva";226;2
"Unit";"Roach";"Larva";226;2
"Unit";"Roach";"Larva";226;2
"Unit";"Roach";"Larva";226;2
"Building";"CreepTumor";NA;226;0
"Building";"CreepTumor";NA;261;0
"Building";"CreepTumor";NA;261;0
"Building";"LurkerDenMP";NA;206;0
"Unit";"Roach";"Larva";261;2
"Unit";"Roach";"Larva";261;2
"Unit";"Roach";"Larva";261;2
"Unit";"Roach";"Larva";261;2
"Unit";"Roach";"Larva";261;2
"Unit";"Roach";"Larva";261;2
"Unit";"Roach";"Larva";261;2
"Unit";"Roach";"Larva";261;2
"Unit";"Roach";"Larva";277;2
"Unit";"Roach";"Larva";277;2
"Unit";"Roach";"Larva";277;2
"Unit";"Roach";"Larva";277;2
"Unit";"Roach";"Larva";277;2
"Unit";"Roach";"Larva";277;2
"Unit";"Roach";"Larva";277;2
"Unit";"Roach";"Larva";277;2
"Unit";"Roach";"Larva";277;2
"Unit";"Roach";"Larva";277;2
"Unit";"Roach";"Larva";277;2
"Building";"CreepTumor";NA;277;0
"Building";"CreepTumor";NA;277;0
"Building";"CreepTumor";NA;277;0
"Building";"Spire";NA;226;0
"Unit";"Hydralisk";"Larva";299;2
"Unit";"Hydralisk";"Larva";299;2
"Unit";"Hydralisk";"Larva";299;2
"Unit";"Hydralisk";"Larva";299;2
"Building";"InfestationPit";NA;299;0
"Unit";"Hydralisk";"Larva";299;2
"Unit";"Hydralisk";"Larva";299;2
"Unit";"Hydralisk";"Larva";299;2
"Unit";"Hydralisk";"Larva";299;2
"Unit";"Hydralisk";"Larva";299;2
"Unit";"Hydralisk";"Larva";299;2
"Unit";"Hydralisk";"Larva";299;2
"Unit";"Hydralisk";"Larva";299;2
"Unit";"Hydralisk";"Larva";299;2
"Unit";"Hydralisk";"Larva";299;2
"Unit";"Hydralisk";"Larva";299;2
"Unit";"Hydralisk";"Larva";307;2
"Unit";"Hydralisk";"Larva";307;2
"Unit";"Hydralisk";"Larva";307;2
"Unit";"Hydralisk";"Larva";307;2
"Unit";"Hydralisk";"Larva";307;2
"Unit";"Hydralisk";"Larva";307;2
"Unit";"Zergling";"Larva";323;1
"Unit";"Zergling";"Larva";323;1
"Unit";"Zergling";"Larva";329;1
"Unit";"Zergling";"Larva";329;1
"Unit";"Zergling";"Larva";329;1
"Unit";"Zergling";"Larva";329;1
"Unit";"Zergling";"Larva";329;1
"Unit";"Zergling";"Larva";329;1
"Unit";"Zergling";"Larva";329;1
"Unit";"Zergling";"Larva";329;1
"Unit";"Zergling";"Larva";329;1
"Unit";"Zergling";"Larva";329;1
"Unit";"Zergling";"Larva";329;1
"Unit";"Zergling";"Larva";329;1
"Unit";"Zergling";"Larva";329;1
"Unit";"Zergling";"Larva";329;1
"Unit";"Zergling";"Larva";329;1
"Unit";"Zergling";"Larva";329;1
"Unit";"Zergling";"Larva";329;1
"Unit";"Zergling";"Larva";329;1
"Unit";"Hydralisk";"Larva";341;2
"Unit";"Hydralisk";"Larva";341;2
"Unit";"Hydralisk";"Larva";341;2
"Unit";"Hydralisk";"Larva";341;2
"Unit";"Hydralisk";"Larva";341;2
"Unit";"Hydralisk";"Larva";341;2
"Unit";"Zergling";"Larva";361;1
"Unit";"Zergling";"Larva";361;1
"Unit";"Zergling";"Larva";361;1
"Unit";"Zergling";"Larva";361;1
"Unit";"Zergling";"Larva";361;1
"Unit";"Zergling";"Larva";361;1
"Unit";"Zergling";"Larva";361;1
"Unit";"Zergling";"Larva";361;1
"Unit";"Zergling";"Larva";361;1
"Unit";"Zergling";"Larva";361;1
"Unit";"Zergling";"Larva";361;1
"Unit";"Zergling";"Larva";361;1
"Building";"CreepTumor";NA;361;0
"Building";"CreepTumor";NA;361;0
"Building";"CreepTumor";NA;385;0
"Building";"CreepTumor";NA;385;0
"Unit";"Hydralisk";"Larva";373;2
"Unit";"Hydralisk";"Larva";373;2
"Unit";"Hydralisk";"Larva";373;2
"Unit";"Hydralisk";"Larva";385;2
"Unit";"Hydralisk";"Larva";385;2
"Unit";"Hydralisk";"Larva";385;2
"Unit";"Hydralisk";"Larva";385;2
"Unit";"Hydralisk";"Larva";385;2
"Unit";"Zergling";"Larva";401;1
"Unit";"Zergling";"Larva";401;1
"Unit";"Zergling";"Larva";401;1
"Unit";"Zergling";"Larva";401;1
"Unit";"Zergling";"Larva";401;1
"Unit";"Zergling";"Larva";401;1
"Unit";"Zergling";"Larva";401;1
"Unit";"Zergling";"Larva";401;1
"Unit";"Zergling";"Larva";401;1
"Unit";"Zergling";"Larva";401;1
"Unit";"Zergling";"Larva";401;1
"Unit";"Zergling";"Larva";401;1
"Unit";"Zergling";"Larva";401;1
"Unit";"Zergling";"Larva";401;1
"Unit";"Zergling";"Larva";401;1
"Unit";"Zergling";"Larva";401;1
"Unit";"Zergling";"Larva";401;1
"Unit";"Zergling";"Larva";401;1
"Unit";"Zergling";"Larva";401;1
"Unit";"Zergling";"Larva";401;1
"Unit";"Zergling";"Larva";401;1
"Unit";"Zergling";"Larva";401;1
"Unit";"Zergling";"Larva";401;1
"Unit";"Zergling";"Larva";401;1
"Unit";"Hydralisk";"Larva";401;2
"Unit";"Hydralisk";"Larva";401;2
"Unit";"Hydralisk";"Larva";401;2
"Unit";"Hydralisk";"Larva";401;2
"Unit";"Hydralisk";"Larva";401;2
"Unit";"Hydralisk";"Larva";401;2
"Unit";"Hydralisk";"Larva";401;2
"Unit";"Hydralisk";"Larva";401;2
"Unit";"Hydralisk";"Larva";401;2
"Unit";"Hydralisk";"Larva";401;2
"Building";"Hatchery";NA;385;0
"Unit";"Zergling";"Larva";425;1
"Unit";"Zergling";"Larva";425;1
"Unit";"Zergling";"Larva";425;1
"Unit";"Zergling";"Larva";425;1
"Unit";"Zergling";"Larva";425;1
"Unit";"Zergling";"Larva";425;1
"Unit";"Zergling";"Larva";425;1
"Unit";"Zergling";"Larva";425;1
"Unit";"Zergling";"Larva";425;1
"Unit";"Zergling";"Larva";425;1
"Unit";"Zergling";"Larva";425;1
"Unit";"Zergling";"Larva";425;1
"Unit";"Zergling";"Larva";425;1
"Unit";"Zergling";"Larva";425;1
"Unit";"Zergling";"Larva";425;1
"Unit";"Zergling";"Larva";425;1
"Unit";"Zergling";"Larva";425;1
"Unit";"Zergling";"Larva";425;1
"Unit";"Zergling";"Larva";463;1
"Unit";"Zergling";"Larva";463;1
"Unit";"Zergling";"Larva";463;1
"Unit";"Zergling";"Larva";463;1
"Unit";"Zergling";"Larva";463;1
"Unit";"Zergling";"Larva";463;1
"Unit";"Zergling";"Larva";463;1
"Unit";"Zergling";"Larva";463;1
"Unit";"Zergling";"Larva";463;1
"Unit";"Zergling";"Larva";463;1
"Unit";"Zergling";"Larva";463;1
"Unit";"Zergling";"Larva";463;1
"Unit";"Zergling";"Larva";463;1
"Unit";"Zergling";"Larva";463;1
"Unit";"Zergling";"Larva";463;1
"Unit";"Zergling";"Larva";463;1
"Unit";"Zergling";"Larva";463;1
"Unit";"Zergling";"Larva";463;1
"Unit";"Zergling";"Larva";463;1
"Unit";"Zergling";"Larva";463;1
"Unit";"Zergling";"Larva";463;1
"Unit";"Zergling";"Larva";463;1
"Unit";"Zergling";"Larva";463;1
"Unit";"Zergling";"Larva";463;1
"Unit";"Zergling";"Larva";463;1
"Unit";"Zergling";"Larva";463;1
"Unit";"Zergling";"Larva";463;1
"Unit";"Zergling";"Larva";463;1
"Unit";"Zergling";"Larva";463;1
"Unit";"Zergling";"Larva";463;1
"Unit";"Zergling";"Larva";463;1
"Unit";"Zergling";"Larva";463;1
"Unit";"Zergling";"Larva";463;1
"Unit";"Zergling";"Larva";463;1
"Unit";"Zergling";"Larva";463;1
"Unit";"Zergling";"Larva";463;1
"Unit";"Zergling";"Larva";463;1
"Unit";"Zergling";"Larva";463;1
"Unit";"Zergling";"Larva";463;1
"Unit";"Zergling";"Larva";463;1
"Unit";"Zergling";"Larva";463;1
"Unit";"Zergling";"Larva";463;1
"Unit";"Zergling";"Larva";463;1
"Unit";"Zergling";"Larva";463;1
"Unit";"Zergling";"Larva";463;1
"Unit";"Zergling";"Larva";463;1
"Unit";"Zergling";"Larva";463;1
"Unit";"Zergling";"Larva";463;1
"Unit";"Zergling";"Larva";463;1
"Unit";"Zergling";"Larva";463;1
"Unit";"Zergling";"Larva";463;1
"Unit";"Zergling";"Larva";463;1
"Unit";"Zergling";"Larva";463;1
"Unit";"Zergling";"Larva";463;1
"Unit";"Zergling";"Larva";463;1
"Unit";"Zergling";"Larva";463;1
"Upgrade";"ZergMeleeWeaponsLevel1";"EvolutionChamber";463;0
"Building";"BanelingNest";NA;519;0
"Unit";"Baneling";"Zergling";519;0
"Unit";"Baneling";"Zergling";519;0
"Unit";"Baneling";"Zergling";519;0
"Unit";"Baneling";"Zergling";519;0
"Unit";"Baneling";"Zergling";519;0
"Unit";"Baneling";"Zergling";519;0
"Unit";"Baneling";"Zergling";519;0
"Unit";"Baneling";"Zergling";519;0
"Unit";"Baneling";"Zergling";519;0
"Unit";"Baneling";"Zergling";519;0
"Unit";"Baneling";"Zergling";519;0
"Unit";"Baneling";"Zergling";519;0
"Unit";"Baneling";"Zergling";519;0
"Unit";"Baneling";"Zergling";519;0
"Unit";"Baneling";"Zergling";519;0
"Unit";"Baneling";"Zergling";519;0
"Unit";"Baneling";"Zergling";519;0
"Unit";"Baneling";"Zergling";519;0
"Unit";"Baneling";"Zergling";519;0
"Unit";"Baneling";"Zergling";519;0
"Unit";"Baneling";"Zergling";519;0
"Unit";"Baneling";"Zergling";519;0
"Unit";"Baneling";"Zergling";519;0
"Unit";"Baneling";"Zergling";519;0
"Unit";"Baneling";"Zergling";519;0
"Unit";"Baneling";"Zergling";519;0
"Unit";"Baneling";"Zergling";519;0
"Unit";"Baneling";"Zergling";519;0
"Unit";"Baneling";"Zergling";519;0
"Unit";"Baneling";"Zergling";519;0
"Unit";"Baneling";"Zergling";519;0
"Unit";"Baneling";"Zergling";519;0
"Unit";"Baneling";"Zergling";519;0
"Unit";"Baneling";"Zergling";519;0
"Unit";"Baneling";"Zergling";519;0
"Unit";"Baneling";"Zergling";519;0
"Unit";"Baneling";"Zergling";519;0
"Unit";"Baneling";"Zergling";519;0
"Unit";"Baneling";"Zergling";519;0
"Unit";"Baneling";"Zergling";519;0
"Unit";"Baneling";"Zergling";519;0
"Unit";"Baneling";"Zergling";519;0
"Unit";"Baneling";"Zergling";519;0
"Unit";"Baneling";"Zergling";519;0
"Unit";"Baneling";"Zergling";519;0
"Unit";"Baneling";"Zergling";519;0
"Unit";"Baneling";"Zergling";519;0
"Unit";"Baneling";"Zergling";519;0
"Unit";"Baneling";"Zergling";519;0
"Unit";"Baneling";"Zergling";519;0
"Unit";"Baneling";"Zergling";519;0
"Unit";"Baneling";"Zergling";519;0
"Unit";"Baneling";"Zergling";519;0
"Unit";"Baneling";"Zergling";519;0
"Unit";"Baneling";"Zergling";519;0
"Unit";"Baneling";"Zergling";519;0
"Unit";"Baneling";"Zergling";519;0
"Unit";"Baneling";"Zergling";519;0
"Upgrade";"ZergGroundArmorsLevel3";"EvolutionChamber";463;0
