"type";"unit_name";"on_building";"total_supply";"supply"
"Unit";"Overlord";"Larva";12;0
"Building";"Extractor";NA;16;0
"Building";"SpawningPool";NA;17;0
"Unit";"Overlord";"Larva";21;0
"Unit";"Zergling";"Larva";21;1
"Unit";"Zergling";"Larva";21;1
"Unit";"Zergling";"Larva";21;1
"Unit";"Zergling";"Larva";21;1
"Unit";"Queen";"Hatchery";21;2
"Building";"Hatchery";NA;21;0
"Unit";"Queen";"Hatchery";25;2
"Unit";"Overlord";"Larva";29;0
"Building";"EvolutionChamber";NA;29;0
"Unit";"Queen";"Hatchery";30;2
"Unit";"Zergling";"Larva";37;1
"Unit";"Zergling";"Larva";37;1
"Building";"Extractor";NA;37;0
"Building";"CreepTumorQueen";NA;43;0
"Building";"SporeCrawler";NA;43;0
"Building";"CreepTumor";NA;49;0
"Unit";"Overlord";"Larva";49;0
"Unit";"Overlord";"Larva";52;0
"Building";"SporeCrawler";NA;53;0
"Building";"CreepTumor";NA;55;0
"Unit";"Overlord";"Larva";55;0
"Unit";"Overlord";"Larva";55;0
"Upgrade";"ZergMeleeWeaponsLevel1";"EvolutionChamber";43;0
"Building";"CreepTumorQueen";NA;58;0
"Unit";"Overlord";"Larva";55;0
"Unit";"Overlord";"Larva";55;0
"Building";"Hatchery";NA;49;0
"Building";"CreepTumor";NA;61;0
"Unit";"Zergling";"Larva";61;1
"Unit";"Zergling";"Larva";61;1
"Unit";"Zergling";"Larva";61;1
"Unit";"Zergling";"Larva";61;1
"Building";"CreepTumor";NA;62;0
"Building";"Extractor";NA;62;0
"Building";"Extractor";NA;62;0
"Building";"HydraliskDen";NA;61;0
"Unit";"Zergling";"Larva";73;1
"Unit";"Zergling";"Larva";73;1
"Building";"CreepTumor";NA;77;0
"Building";"CreepTumor";NA;77;0
"Unit";"Hydralisk";"Larva";75;2
"Unit";"Hydralisk";"Larva";75;2
"Unit";"Hydralisk";"Larva";77;2
"Unit";"Hydralisk";"Larva";77;2
"Building";"BanelingNest";NA;74;0
"Building";"Extractor";NA;92;0
"Unit";"Zergling";"Larva";96;1
"Unit";"Zergling";"Larva";96;1
"Unit";"Zergling";"Larva";96;1
"Unit";"Zergling";"Larva";96;1
"Unit";"Zergling";"Larva";96;1
"Unit";"Zergling";"Larva";96;1
"Unit";"Zergling";"Larva";96;1
"Unit";"Zergling";"Larva";96;1
"Unit";"Hydralisk";"Larva";96;2
"Unit";"Hydralisk";"Larva";96;2
"Unit";"Hydralisk";"Larva";96;2
"Upgrade";"EvolveMuscularAugments";"HydraliskDen";80;0
"Upgrade";"ZergMissileWeaponsLevel1";"EvolutionChamber";73;0
"Building";"SporeCrawler";NA;97;0
"Unit";"Overlord";"Larva";111;0
"Unit";"Overlord";"Larva";111;0
"Unit";"Overlord";"Larva";111;0
"Unit";"Overlord";"Larva";111;0
"Building";"CreepTumor";NA;122;0
"Building";"CreepTumor";NA;122;0
"Building";"LurkerDenMP";NA;91;0
"Unit";"Queen";"Hatchery";111;2
"Unit";"Hydralisk";"Larva";122;2
"Unit";"Hydralisk";"Larva";122;2
"Unit";"Hydralisk";"Larva";122;2
"Building";"CreepTumor";NA;124;0
"Building";"CreepTumor";NA;124;0
"Upgrade";"EvolveGroovedSpines";"HydraliskDen";111;0
"Unit";"Hydralisk";"Larva";122;2
"Unit";"Hydralisk";"Larva";122;2
"Unit";"Hydralisk";"Larva";122;2
"Unit";"Hydralisk";"Larva";122;2
"Unit";"Hydralisk";"Larva";122;2
"Unit";"Overlord";"Larva";130;0
"Unit";"Overlord";"Larva";130;0
"Unit";"Baneling";"Zergling";143;0
"Unit";"Baneling";"Zergling";143;0
"Unit";"Baneling";"Zergling";143;0
"Unit";"Zergling";"Larva";143;1
"Unit";"Zergling";"Larva";143;1
"Unit";"Zergling";"Larva";143;1
"Unit";"Zergling";"Larva";143;1
"Unit";"Zergling";"Larva";143;1
"Unit";"Zergling";"Larva";143;1
"Unit";"Zergling";"Larva";143;1
"Unit";"Zergling";"Larva";143;1
"Unit";"Zergling";"Larva";143;1
"Unit";"Zergling";"Larva";143;1
"Unit";"Hydralisk";"Larva";143;2
"Unit";"Hydralisk";"Larva";143;2
"Unit";"Hydralisk";"Larva";143;2
"Unit";"Zergling";"Larva";143;1
"Unit";"Zergling";"Larva";143;1
"Unit";"Zergling";"Larva";143;1
"Unit";"Zergling";"Larva";143;1
"Unit";"Zergling";"Larva";143;1
"Unit";"Zergling";"Larva";143;1
"Unit";"Hydralisk";"Larva";143;2
"Unit";"Hydralisk";"Larva";143;2
"Unit";"Hydralisk";"Larva";143;2
"Unit";"Zergling";"Larva";159;1
"Unit";"Zergling";"Larva";159;1
"Unit";"Zergling";"Larva";159;1
"Unit";"Zergling";"Larva";159;1
"Building";"Extractor";NA;159;0
"Building";"CreepTumor";NA;168;0
"Building";"CreepTumor";NA;168;0
"Unit";"Overlord";"Larva";168;0
"Unit";"Overlord";"Larva";174;0
"Unit";"Overlord";"Larva";174;0
"Building";"Extractor";NA;178;0
"Building";"Extractor";NA;178;0
"Unit";"Zergling";"Larva";180;1
"Unit";"Zergling";"Larva";180;1
"Unit";"Zergling";"Larva";180;1
"Unit";"Zergling";"Larva";180;1
"Unit";"Zergling";"Larva";180;1
"Unit";"Zergling";"Larva";180;1
"Building";"Hatchery";NA;143;0
"Unit";"Zergling";"Larva";180;1
"Unit";"Zergling";"Larva";180;1
"Upgrade";"ZergMissileWeaponsLevel2";"EvolutionChamber";130;0
"Building";"CreepTumor";NA;180;0
"Unit";"Hydralisk";"Larva";180;2
"Unit";"Hydralisk";"Larva";180;2
"Unit";"Hydralisk";"Larva";180;2
"Unit";"Hydralisk";"Larva";180;2
"Unit";"Hydralisk";"Larva";180;2
"Unit";"Hydralisk";"Larva";180;2
"Unit";"Hydralisk";"Larva";180;2
"Building";"InfestationPit";NA;180;0
"Unit";"Overlord";"Larva";202;0
"Unit";"Overlord";"Larva";202;0
"Unit";"Overlord";"Larva";202;0
"Unit";"Zergling";"Larva";205;1
"Unit";"Zergling";"Larva";205;1
"Unit";"Zergling";"Larva";205;1
"Unit";"Zergling";"Larva";205;1
"Building";"Spire";NA;202;0
"Unit";"Zergling";"Larva";205;1
"Unit";"Zergling";"Larva";205;1
"Unit";"Zergling";"Larva";205;1
"Unit";"Zergling";"Larva";205;1
"Unit";"Zergling";"Larva";205;1
"Unit";"Zergling";"Larva";205;1
"Building";"Hatchery";NA;202;0
"Unit";"Corruptor";"Larva";218;2
"Unit";"Corruptor";"Larva";218;2
"Unit";"Corruptor";"Larva";218;2
"Unit";"Corruptor";"Larva";218;2
"Unit";"Corruptor";"Larva";218;2
"Unit";"Corruptor";"Larva";218;2
"Unit";"Corruptor";"Larva";218;2
"Unit";"Corruptor";"Larva";218;2
"Unit";"Corruptor";"Larva";218;2
"Unit";"Corruptor";"Larva";218;2
"Unit";"Baneling";"Zergling";224;0
"Unit";"Baneling";"Zergling";224;0
"Unit";"Baneling";"Zergling";224;0
"Unit";"Baneling";"Zergling";224;0
"Unit";"Zergling";"Larva";224;1
"Unit";"Zergling";"Larva";224;1
"Unit";"Zergling";"Larva";224;1
"Unit";"Zergling";"Larva";224;1
"Unit";"Zergling";"Larva";224;1
"Unit";"Zergling";"Larva";224;1
"Unit";"Zergling";"Larva";224;1
"Unit";"Zergling";"Larva";224;1
"Unit";"Zergling";"Larva";224;1
"Unit";"Zergling";"Larva";224;1
"Unit";"Corruptor";"Larva";224;2
"Unit";"Corruptor";"Larva";224;2
"Unit";"Corruptor";"Larva";224;2
"Unit";"Overlord";"Larva";244;0
"Building";"Extractor";NA;244;0
"Building";"CreepTumor";NA;255;0
"Building";"Extractor";NA;244;0
"Building";"CreepTumor";NA;255;0
"Unit";"Corruptor";"Larva";261;2
"Unit";"Corruptor";"Larva";261;2
"Unit";"Corruptor";"Larva";261;2
"Unit";"Corruptor";"Larva";261;2
"Unit";"Corruptor";"Larva";261;2
"Building";"CreepTumor";NA;271;0
"Unit";"Overlord";"Larva";271;0
"Unit";"Overlord";"Larva";271;0
"Unit";"Overlord";"Larva";271;0
"Unit";"Overlord";"Larva";271;0
"Unit";"Overlord";"Larva";271;0
"Unit";"Hydralisk";"Larva";271;2
"Unit";"Hydralisk";"Larva";271;2
"Unit";"Hydralisk";"Larva";271;2
"Upgrade";"ZergMissileWeaponsLevel3";"EvolutionChamber";261;0
"Unit";"Zergling";"Larva";277;1
"Unit";"Zergling";"Larva";277;1
"Unit";"Zergling";"Larva";277;1
"Unit";"Zergling";"Larva";277;1
"Unit";"Zergling";"Larva";277;1
"Unit";"Zergling";"Larva";277;1
"Unit";"Corruptor";"Larva";277;2
"Unit";"Corruptor";"Larva";277;2
"Unit";"Corruptor";"Larva";277;2
"Unit";"Corruptor";"Larva";277;2
"Unit";"Corruptor";"Larva";277;2
"Unit";"Corruptor";"Larva";277;2
"Unit";"Corruptor";"Larva";277;2
"Unit";"Corruptor";"Larva";277;2
"Unit";"Corruptor";"Larva";277;2
"Unit";"Corruptor";"Larva";277;2
"Unit";"Corruptor";"Larva";277;2
"Unit";"Corruptor";"Larva";277;2
"Unit";"Corruptor";"Larva";277;2
"Unit";"Corruptor";"Larva";277;2
"Unit";"Corruptor";"Larva";277;2
"Unit";"Corruptor";"Larva";277;2
"Unit";"Corruptor";"Larva";277;2
"Building";"CreepTumor";NA;283;0
"Building";"Hatchery";NA;271;0
"Building";"Extractor";NA;317;0
"Building";"Extractor";NA;317;0
"Unit";"Corruptor";"Larva";320;2
"Unit";"Corruptor";"Larva";320;2
"Unit";"Corruptor";"Larva";320;2
"Unit";"Corruptor";"Larva";320;2
