"type";"unit_name";"on_building";"total_supply";"supply"
"Unit";"Overlord";"Larva";12;0
"Building";"Extractor";NA;17;0
"Building";"SpawningPool";NA;19;0
"Unit";"Overlord";"Larva";22;0
"Building";"Hatchery";NA;17;0
"Unit";"Zergling";"Larva";22;1
"Unit";"Zergling";"Larva";22;1
"Unit";"Zergling";"Larva";22;1
"Unit";"Zergling";"Larva";22;1
"Unit";"Queen";"Hatchery";22;2
"Unit";"Queen";"Hatchery";22;2
"Unit";"Overlord";"Larva";36;0
"Unit";"Queen";"Hatchery";35;2
"Building";"CreepTumorQueen";NA;40;0
"Unit";"Overlord";"Larva";39;0
"Building";"Hatchery";NA;29;0
"Unit";"Overlord";"Larva";50;0
"Building";"SporeCrawler";NA;50;0
"Building";"SporeCrawler";NA;50;0
"Building";"CreepTumor";NA;52;0
"Unit";"Overlord";"Larva";50;0
"Building";"CreepTumorQueen";NA;59;0
"Unit";"Queen";"Hatchery";50;2
"Building";"SporeCrawler";NA;59;0
"Building";"Extractor";NA;59;0
"Building";"Extractor";NA;59;0
"Building";"EvolutionChamber";NA;59;0
"Building";"RoachWarren";NA;59;0
"Building";"CreepTumor";NA;75;0
"Building";"CreepTumorQueen";NA;75;0
"Unit";"Overlord";"Larva";75;0
"Unit";"Overlord";"Larva";80;0
"Building";"Extractor";NA;80;0
"Building";"CreepTumor";NA;81;0
"Building";"CreepTumorQueen";NA;84;0
"Building";"HydraliskDen";NA;80;0
"Building";"CreepTumor";NA;84;0
"Unit";"Overlord";"Larva";86;0
"Unit";"Overlord";"Larva";86;0
"Unit";"Overlord";"Larva";92;0
"Building";"BanelingNest";NA;80;0
"Building";"Extractor";NA;92;0
"Building";"Extractor";NA;92;0
"Unit";"Hydralisk";"Larva";92;2
"Unit";"Hydralisk";"Larva";92;2
"Unit";"Hydralisk";"Larva";92;2
"Unit";"Hydralisk";"Larva";92;2
"Unit";"Hydralisk";"Larva";92;2
"Building";"CreepTumor";NA;98;0
"Building";"CreepTumor";NA;98;0
"Unit";"Overlord";"Larva";98;0
"Unit";"Overlord";"Larva";98;0
"Unit";"Overlord";"Larva";98;0
"Building";"Hatchery";NA;80;0
"Unit";"Zergling";"Larva";108;1
"Unit";"Zergling";"Larva";108;1
"Unit";"Zergling";"Larva";108;1
"Unit";"Zergling";"Larva";108;1
"Unit";"Zergling";"Larva";108;1
"Unit";"Zergling";"Larva";108;1
"Unit";"Zergling";"Larva";108;1
"Unit";"Zergling";"Larva";108;1
"Unit";"Zergling";"Larva";108;1
"Unit";"Zergling";"Larva";108;1
"Unit";"Zergling";"Larva";108;1
"Unit";"Zergling";"Larva";108;1
"Unit";"Baneling";"Zergling";108;0
"Unit";"Baneling";"Zergling";108;0
"Unit";"Hydralisk";"Larva";98;2
"Unit";"Hydralisk";"Larva";98;2
"Unit";"Hydralisk";"Larva";98;2
"Unit";"Roach";"Larva";108;2
"Unit";"Roach";"Larva";108;2
"Building";"EvolutionChamber";NA;108;0
"Unit";"Baneling";"Zergling";120;0
"Unit";"Baneling";"Zergling";120;0
"Unit";"Baneling";"Zergling";120;0
"Unit";"Baneling";"Zergling";120;0
"Unit";"Baneling";"Zergling";120;0
"Unit";"Baneling";"Zergling";120;0
"Unit";"Roach";"Larva";108;2
"Unit";"Roach";"Larva";108;2
"Unit";"Roach";"Larva";108;2
"Unit";"Zergling";"Larva";122;1
"Unit";"Zergling";"Larva";122;1
"Unit";"Zergling";"Larva";122;1
"Unit";"Zergling";"Larva";122;1
"Unit";"Zergling";"Larva";124;1
"Unit";"Zergling";"Larva";124;1
"Unit";"Roach";"Larva";126;2
"Unit";"Roach";"Larva";126;2
"Unit";"Roach";"Larva";126;2
"Upgrade";"EvolveGroovedSpines";"HydraliskDen";98;0
"Upgrade";"ZergMissileWeaponsLevel1";"EvolutionChamber";92;0
"Building";"CreepTumorQueen";NA;148;0
"Building";"LurkerDenMP";NA;98;0
"Building";"CreepTumorQueen";NA;148;0
"Unit";"Queen";"Hatchery";142;2
"Unit";"Queen";"Hatchery";142;2
"Unit";"Queen";"Hatchery";142;2
"Unit";"Hydralisk";"Larva";148;2
"Unit";"Hydralisk";"Larva";148;2
"Unit";"Hydralisk";"Larva";148;2
"Unit";"Hydralisk";"Larva";148;2
"Unit";"Hydralisk";"Larva";148;2
"Unit";"Hydralisk";"Larva";148;2
"Building";"CreepTumor";NA;154;0
"Unit";"Queen";"Hatchery";148;2
"Building";"CreepTumorQueen";NA;161;0
"Building";"CreepTumor";NA;161;0
"Unit";"Overlord";"Larva";161;0
"Unit";"Overlord";"Larva";161;0
"Unit";"Overlord";"Larva";161;0
"Building";"Extractor";NA;173;0
"Unit";"Hydralisk";"Larva";175;2
"Unit";"Hydralisk";"Larva";175;2
"Unit";"Hydralisk";"Larva";175;2
"Unit";"Hydralisk";"Larva";175;2
"Building";"CreepTumor";NA;176;0
"Building";"CreepTumor";NA;182;0
"Upgrade";"EvolveMuscularAugments";"HydraliskDen";154;0
"Building";"CreepTumorQueen";NA;189;0
"Building";"CreepTumor";NA;187;0
"Building";"Extractor";NA;176;0
"Unit";"Overlord";"Larva";192;0
"Unit";"Overlord";"Larva";192;0
"Unit";"Overlord";"Larva";192;0
"Unit";"Overlord";"Larva";192;0
"Building";"CreepTumor";NA;192;0
"Unit";"Hydralisk";"Larva";192;2
"Unit";"Hydralisk";"Larva";192;2
"Unit";"Hydralisk";"Larva";192;2
"Unit";"Hydralisk";"Larva";192;2
"Unit";"Hydralisk";"Larva";192;2
"Unit";"Hydralisk";"Larva";192;2
"Unit";"Hydralisk";"Larva";192;2
"Building";"CreepTumor";NA;192;0
"Unit";"Overlord";"Larva";192;0
"Unit";"Overlord";"Larva";192;0
"Building";"CreepTumor";NA;192;0
"Building";"CreepTumor";NA;192;0
"Building";"CreepTumorQueen";NA;192;0
"Upgrade";"ZergMeleeWeaponsLevel1";"EvolutionChamber";173;0
"Building";"InfestationPit";NA;192;0
"Unit";"Hydralisk";"Larva";192;2
"Unit";"Hydralisk";"Larva";192;2
"Unit";"Hydralisk";"Larva";192;2
"Unit";"Hydralisk";"Larva";192;2
"Unit";"Hydralisk";"Larva";192;2
"Unit";"Hydralisk";"Larva";192;2
"Unit";"Hydralisk";"Larva";192;2
"Unit";"Hydralisk";"Larva";192;2
"Unit";"Hydralisk";"Larva";192;2
"Unit";"Hydralisk";"Larva";192;2
"Unit";"Hydralisk";"Larva";192;2
"Building";"Hatchery";NA;189;0
"Upgrade";"ZergMissileWeaponsLevel2";"EvolutionChamber";175;0
"Building";"Extractor";NA;209;0
"Building";"Extractor";NA;210;0
"Unit";"Zergling";"Larva";233;1
"Unit";"Zergling";"Larva";233;1
"Unit";"Zergling";"Larva";233;1
"Unit";"Zergling";"Larva";233;1
"Unit";"Zergling";"Larva";233;1
"Unit";"Zergling";"Larva";233;1
"Unit";"Zergling";"Larva";233;1
"Unit";"Zergling";"Larva";233;1
"Unit";"Zergling";"Larva";233;1
"Unit";"Zergling";"Larva";233;1
"Unit";"Zergling";"Larva";233;1
"Unit";"Zergling";"Larva";233;1
"Unit";"Zergling";"Larva";233;1
"Unit";"Zergling";"Larva";233;1
"Unit";"Zergling";"Larva";233;1
"Unit";"Zergling";"Larva";233;1
"Unit";"Zergling";"Larva";233;1
"Unit";"Zergling";"Larva";233;1
"Unit";"Zergling";"Larva";233;1
"Unit";"Zergling";"Larva";233;1
"Unit";"Zergling";"Larva";233;1
"Unit";"Zergling";"Larva";233;1
"Unit";"Zergling";"Larva";233;1
"Unit";"Zergling";"Larva";233;1
"Unit";"Zergling";"Larva";233;1
"Unit";"Zergling";"Larva";233;1
"Unit";"Zergling";"Larva";233;1
"Unit";"Zergling";"Larva";233;1
"Unit";"Zergling";"Larva";233;1
"Unit";"Zergling";"Larva";233;1
"Unit";"Zergling";"Larva";233;1
"Unit";"Zergling";"Larva";233;1
"Building";"Spire";NA;206;0
"Building";"SporeCrawler";NA;265;0
"Unit";"Baneling";"Zergling";274;0
"Unit";"Baneling";"Zergling";274;0
"Unit";"Baneling";"Zergling";274;0
"Unit";"Baneling";"Zergling";274;0
"Unit";"Baneling";"Zergling";274;0
"Unit";"Baneling";"Zergling";274;0
"Unit";"Baneling";"Zergling";274;0
"Unit";"Baneling";"Zergling";274;0
"Unit";"Baneling";"Zergling";274;0
"Unit";"Baneling";"Zergling";274;0
"Unit";"Corruptor";"Larva";274;2
"Unit";"Corruptor";"Larva";274;2
"Unit";"Corruptor";"Larva";274;2
"Unit";"Corruptor";"Larva";274;2
"Building";"SpineCrawler";NA;274;0
"Building";"SpineCrawler";NA;278;0
"Building";"SpineCrawler";NA;278;0
"Building";"SpineCrawler";NA;278;0
"Building";"SpineCrawler";NA;278;0
"Building";"SpineCrawler";NA;278;0
"Upgrade";"ZergMeleeWeaponsLevel2";"EvolutionChamber";270;0
"Unit";"Zergling";"Larva";282;1
"Unit";"Zergling";"Larva";282;1
"Unit";"Zergling";"Larva";282;1
"Unit";"Zergling";"Larva";282;1
"Unit";"Zergling";"Larva";282;1
"Unit";"Zergling";"Larva";282;1
"Unit";"Zergling";"Larva";282;1
"Unit";"Zergling";"Larva";282;1
"Unit";"Zergling";"Larva";282;1
"Unit";"Zergling";"Larva";282;1
"Unit";"Zergling";"Larva";282;1
"Unit";"Zergling";"Larva";282;1
"Unit";"Zergling";"Larva";282;1
"Unit";"Zergling";"Larva";282;1
"Unit";"Zergling";"Larva";282;1
"Unit";"Zergling";"Larva";282;1
"Unit";"Zergling";"Larva";282;1
"Unit";"Zergling";"Larva";282;1
"Unit";"Zergling";"Larva";282;1
"Unit";"Zergling";"Larva";282;1
"Unit";"Zergling";"Larva";282;1
"Unit";"Zergling";"Larva";282;1
"Unit";"Zergling";"Larva";282;1
"Unit";"Zergling";"Larva";282;1
"Unit";"Zergling";"Larva";282;1
"Unit";"Zergling";"Larva";282;1
"Unit";"Zergling";"Larva";282;1
"Unit";"Zergling";"Larva";282;1
"Unit";"Zergling";"Larva";282;1
"Unit";"Zergling";"Larva";282;1
"Unit";"Zergling";"Larva";282;1
"Unit";"Zergling";"Larva";282;1
"Unit";"Zergling";"Larva";282;1
"Unit";"Zergling";"Larva";282;1
"Unit";"Zergling";"Larva";282;1
"Unit";"Zergling";"Larva";282;1
"Unit";"Zergling";"Larva";282;1
"Unit";"Zergling";"Larva";282;1
"Unit";"Zergling";"Larva";282;1
"Unit";"Zergling";"Larva";282;1
"Unit";"Zergling";"Larva";282;1
"Unit";"Zergling";"Larva";282;1
"Unit";"Zergling";"Larva";282;1
"Unit";"Zergling";"Larva";282;1
"Unit";"Zergling";"Larva";282;1
"Unit";"Zergling";"Larva";282;1
"Unit";"Zergling";"Larva";282;1
"Unit";"Zergling";"Larva";282;1
"Unit";"Zergling";"Larva";282;1
"Unit";"Zergling";"Larva";282;1
"Unit";"Zergling";"Larva";282;1
"Unit";"Zergling";"Larva";282;1
"Unit";"Zergling";"Larva";282;1
"Unit";"Zergling";"Larva";282;1
"Unit";"Zergling";"Larva";282;1
"Unit";"Zergling";"Larva";282;1
"Unit";"Zergling";"Larva";282;1
"Unit";"Zergling";"Larva";282;1
"Unit";"Corruptor";"Larva";282;2
"Unit";"Corruptor";"Larva";282;2
"Unit";"Corruptor";"Larva";282;2
"Building";"SporeCrawler";NA;340;0
"Unit";"Corruptor";"Larva";340;2
"Unit";"Corruptor";"Larva";340;2
"Unit";"Corruptor";"Larva";340;2
"Unit";"Corruptor";"Larva";340;2
"Unit";"Corruptor";"Larva";340;2
"Unit";"Corruptor";"Larva";346;2
"Unit";"Corruptor";"Larva";346;2
"Unit";"Overlord";"Larva";356;0
"Unit";"Overlord";"Larva";356;0
"Unit";"Baneling";"Zergling";360;0
"Unit";"Baneling";"Zergling";360;0
"Unit";"Baneling";"Zergling";360;0
"Unit";"Baneling";"Zergling";360;0
"Unit";"Baneling";"Zergling";360;0
"Unit";"Baneling";"Zergling";360;0
"Unit";"Baneling";"Zergling";360;0
"Building";"Hatchery";NA;340;0
"Unit";"Hydralisk";"Larva";360;2
"Unit";"Hydralisk";"Larva";360;2
"Unit";"Hydralisk";"Larva";360;2
"Unit";"Hydralisk";"Larva";360;2
"Unit";"Hydralisk";"Larva";360;2
"Unit";"Hydralisk";"Larva";360;2
"Unit";"Hydralisk";"Larva";360;2
"Unit";"Hydralisk";"Larva";360;2
"Unit";"Zergling";"Larva";360;1
"Unit";"Zergling";"Larva";360;1
"Unit";"Zergling";"Larva";360;1
"Unit";"Zergling";"Larva";360;1
"Unit";"Zergling";"Larva";360;1
"Unit";"Zergling";"Larva";360;1
"Unit";"Zergling";"Larva";360;1
"Unit";"Zergling";"Larva";360;1
"Unit";"Zergling";"Larva";360;1
"Unit";"Zergling";"Larva";360;1
"Unit";"Zergling";"Larva";360;1
"Unit";"Zergling";"Larva";360;1
"Unit";"Zergling";"Larva";360;1
"Unit";"Zergling";"Larva";360;1
"Building";"Extractor";NA;376;0
"Building";"Extractor";NA;376;0
"Building";"Hatchery";NA;356;0
"Unit";"Corruptor";"Larva";390;2
"Unit";"Corruptor";"Larva";390;2
"Unit";"Corruptor";"Larva";390;2
"Unit";"Corruptor";"Larva";390;2
"Unit";"Corruptor";"Larva";390;2
"Unit";"Corruptor";"Larva";390;2
"Unit";"Hydralisk";"Larva";408;2
"Unit";"Hydralisk";"Larva";408;2
"Unit";"Zergling";"Larva";408;1
"Unit";"Zergling";"Larva";408;1
"Unit";"Zergling";"Larva";408;1
"Unit";"Zergling";"Larva";408;1
"Unit";"Zergling";"Larva";408;1
"Unit";"Zergling";"Larva";408;1
"Unit";"Zergling";"Larva";408;1
"Unit";"Zergling";"Larva";408;1
"Unit";"Zergling";"Larva";408;1
"Unit";"Zergling";"Larva";408;1
"Unit";"Zergling";"Larva";408;1
"Unit";"Zergling";"Larva";408;1
"Unit";"Zergling";"Larva";408;1
"Unit";"Zergling";"Larva";408;1
"Unit";"Zergling";"Larva";408;1
"Unit";"Zergling";"Larva";408;1
"Unit";"Hydralisk";"Larva";408;2
"Unit";"Zergling";"Larva";428;1
"Unit";"Zergling";"Larva";428;1
"Unit";"Hydralisk";"Larva";428;2
"Unit";"Hydralisk";"Larva";428;2
"Unit";"Hydralisk";"Larva";428;2
"Unit";"Hydralisk";"Larva";428;2
"Unit";"Hydralisk";"Larva";428;2
