"type";"unit_name";"on_building";"total_supply";"supply"
"Unit";"Overlord";"Larva";13;0
"Building";"Extractor";NA;17;0
"Unit";"Overlord";"Larva";21;0
"Building";"SpawningPool";NA;19;0
"Building";"Hatchery";NA;17;0
"Unit";"Queen";"Hatchery";22;2
"Unit";"Queen";"Hatchery";23;2
"Unit";"Zergling";"Larva";27;1
"Unit";"Zergling";"Larva";27;1
"Unit";"Zergling";"Larva";27;1
"Unit";"Zergling";"Larva";27;1
"Unit";"Overlord";"Larva";31;0
"Unit";"Overlord";"Larva";37;0
"Unit";"Zergling";"Larva";38;1
"Unit";"Zergling";"Larva";38;1
"Unit";"Zergling";"Larva";39;1
"Unit";"Zergling";"Larva";39;1
"Building";"Hatchery";NA;27;0
"Building";"Extractor";NA;44;0
"Building";"RoachWarren";NA;46;0
"Building";"EvolutionChamber";NA;52;0
"Unit";"Queen";"Hatchery";52;2
"Unit";"Queen";"Hatchery";52;2
"Building";"CreepTumorQueen";NA;69;0
"Unit";"Overlord";"Larva";69;0
"Unit";"Overlord";"Larva";69;0
"Unit";"Overlord";"Larva";69;0
"Building";"Extractor";NA;69;0
"Unit";"Queen";"Hatchery";69;2
"Unit";"Overlord";"Larva";69;0
"Unit";"Overlord";"Larva";69;0
"Building";"Extractor";NA;69;0
"Unit";"Queen";"Hatchery";69;2
"Building";"CreepTumorQueen";NA;84;0
"Building";"CreepTumorQueen";NA;84;0
"Building";"CreepTumorQueen";NA;84;0
"Building";"HydraliskDen";NA;84;0
"Unit";"Overlord";"Larva";84;0
"Building";"Extractor";NA;84;0
"Building";"Extractor";NA;84;0
"Building";"InfestationPit";NA;91;0
"Upgrade";"ZergMissileWeaponsLevel1";"EvolutionChamber";69;0
"Unit";"Roach";"Larva";101;2
"Unit";"Roach";"Larva";101;2
"Unit";"Roach";"Larva";101;2
"Unit";"Roach";"Larva";101;2
"Unit";"Roach";"Larva";101;2
"Unit";"Roach";"Larva";101;2
"Unit";"Roach";"Larva";101;2
"Unit";"Roach";"Larva";101;2
"Unit";"Roach";"Larva";101;2
"Unit";"Roach";"Larva";101;2
"Unit";"Roach";"Larva";101;2
"Unit";"Roach";"Larva";101;2
"Unit";"Roach";"Larva";101;2
"Unit";"Overlord";"Larva";101;0
"Upgrade";"GlialReconstitution";"RoachWarren";84;0
"Unit";"Overlord";"Larva";101;0
"Unit";"Overlord";"Larva";101;0
"Unit";"Overlord";"Larva";101;0
"Building";"CreepTumor";NA;127;0
"Building";"CreepTumor";NA;127;0
"Building";"CreepTumor";NA;127;0
"Building";"CreepTumorQueen";NA;127;0
"Unit";"Overlord";"Larva";101;0
"Unit";"Overlord";"Larva";103;0
"Building";"CreepTumorQueen";NA;127;0
"Building";"CreepTumorQueen";NA;127;0
"Upgrade";"EvolveGroovedSpines";"HydraliskDen";101;0
"Building";"CreepTumorQueen";NA;127;0
"Building";"CreepTumorQueen";NA;127;0
"Building";"CreepTumorQueen";NA;127;0
"Building";"LurkerDenMP";NA;91;0
"Unit";"Overlord";"Larva";127;0
"Building";"Hatchery";NA;101;0
"Unit";"Hydralisk";"Larva";127;2
"Unit";"Hydralisk";"Larva";127;2
"Unit";"Hydralisk";"Larva";127;2
"Unit";"Hydralisk";"Larva";127;2
"Unit";"Hydralisk";"Larva";127;2
"Unit";"Hydralisk";"Larva";127;2
"Unit";"Hydralisk";"Larva";127;2
"Unit";"Hydralisk";"Larva";127;2
"Building";"CreepTumor";NA;127;0
"Building";"CreepTumor";NA;127;0
"Building";"CreepTumorQueen";NA;146;0
"Building";"CreepTumor";NA;129;0
"Building";"CreepTumor";NA;130;0
"Building";"CreepTumor";NA;133;0
"Building";"CreepTumorQueen";NA;149;0
"Building";"CreepTumor";NA;149;0
"Building";"CreepTumor";NA;149;0
"Building";"CreepTumorQueen";NA;149;0
"Building";"CreepTumor";NA;149;0
"Unit";"Hydralisk";"Larva";127;2
"Unit";"Hydralisk";"Larva";127;2
"Unit";"Hydralisk";"Larva";127;2
"Unit";"Hydralisk";"Larva";127;2
"Unit";"Hydralisk";"Larva";127;2
"Building";"Extractor";NA;127;0
"Building";"CreepTumor";NA;149;0
"Unit";"Hydralisk";"Larva";127;2
"Building";"Extractor";NA;129;0
"Unit";"Roach";"Larva";149;2
"Unit";"Overlord";"Larva";155;0
"Unit";"Overlord";"Larva";159;0
"Unit";"Roach";"Larva";149;2
"Unit";"Roach";"Larva";149;2
"Unit";"Overlord";"Larva";159;0
"Unit";"Roach";"Larva";149;2
"Unit";"Roach";"Larva";149;2
"Unit";"Roach";"Larva";149;2
"Unit";"Roach";"Larva";149;2
"Unit";"Overlord";"Larva";159;0
"Unit";"Overlord";"Larva";159;0
"Unit";"Overlord";"Larva";159;0
"Building";"CreepTumor";NA;161;0
"Building";"CreepTumor";NA;161;0
"Building";"CreepTumor";NA;161;0
"Building";"CreepTumor";NA;161;0
"Building";"CreepTumor";NA;161;0
"Building";"CreepTumor";NA;161;0
"Building";"CreepTumorQueen";NA;161;0
"Building";"CreepTumorQueen";NA;161;0
"Building";"CreepTumor";NA;161;0
"Building";"CreepTumor";NA;161;0
"Upgrade";"EvolveMuscularAugments";"HydraliskDen";127;0
"Upgrade";"ZergMissileWeaponsLevel2";"EvolutionChamber";127;0
"Unit";"Roach";"Larva";175;2
"Unit";"Roach";"Larva";175;2
"Unit";"Roach";"Larva";175;2
"Building";"CreepTumor";NA;175;0
"Building";"CreepTumor";NA;175;0
"Building";"CreepTumor";NA;175;0
"Building";"CreepTumor";NA;175;0
"Building";"CreepTumor";NA;175;0
"Unit";"Hydralisk";"Larva";175;2
"Building";"CreepTumor";NA;175;0
"Building";"CreepTumor";NA;175;0
"Building";"CreepTumor";NA;175;0
"Unit";"Hydralisk";"Larva";175;2
"Unit";"Hydralisk";"Larva";175;2
"Unit";"Hydralisk";"Larva";175;2
"Unit";"Hydralisk";"Larva";175;2
"Unit";"Hydralisk";"Larva";175;2
"Unit";"Hydralisk";"Larva";175;2
"Unit";"Hydralisk";"Larva";175;2
"Unit";"Roach";"Larva";175;2
"Unit";"Hydralisk";"Larva";175;2
"Unit";"Hydralisk";"Larva";175;2
"Unit";"Hydralisk";"Larva";175;2
"Unit";"Hydralisk";"Larva";175;2
"Unit";"Hydralisk";"Larva";175;2
"Unit";"Hydralisk";"Larva";175;2
"Unit";"Hydralisk";"Larva";175;2
"Unit";"Hydralisk";"Larva";175;2
"Unit";"Hydralisk";"Larva";175;2
"Unit";"Hydralisk";"Larva";175;2
"Unit";"Hydralisk";"Larva";175;2
"Unit";"Roach";"Larva";175;2
"Building";"SporeCrawler";NA;175;0
"Building";"SporeCrawler";NA;175;0
"Building";"CreepTumor";NA;223;0
"Building";"SporeCrawler";NA;221;0
"Building";"CreepTumor";NA;223;0
"Building";"CreepTumor";NA;223;0
"Building";"CreepTumor";NA;223;0
"Building";"CreepTumor";NA;223;0
"Building";"CreepTumor";NA;223;0
"Building";"CreepTumor";NA;223;0
"Building";"SporeCrawler";NA;223;0
"Building";"SpineCrawler";NA;175;0
"Building";"SpineCrawler";NA;175;0
"Building";"SpineCrawler";NA;181;0
"Building";"SpineCrawler";NA;221;0
"Building";"SpineCrawler";NA;223;0
"Building";"SpineCrawler";NA;223;0
"Building";"SpineCrawler";NA;223;0
"Unit";"Roach";"Larva";223;2
"Unit";"Roach";"Larva";223;2
"Unit";"Roach";"Larva";223;2
"Unit";"Roach";"Larva";223;2
"Unit";"Roach";"Larva";223;2
"Unit";"Roach";"Larva";223;2
"Unit";"Roach";"Larva";223;2
"Unit";"Roach";"Larva";223;2
"Unit";"Roach";"Larva";223;2
"Unit";"Hydralisk";"Larva";241;2
"Unit";"Hydralisk";"Larva";241;2
"Unit";"Hydralisk";"Larva";241;2
"Unit";"Hydralisk";"Larva";241;2
"Unit";"Hydralisk";"Larva";241;2
"Unit";"Hydralisk";"Larva";241;2
"Unit";"Hydralisk";"Larva";241;2
"Unit";"Roach";"Larva";241;2
"Unit";"Roach";"Larva";241;2
"Unit";"Roach";"Larva";241;2
"Unit";"Roach";"Larva";241;2
"Building";"CreepTumor";NA;267;0
"Building";"CreepTumor";NA;267;0
"Building";"CreepTumor";NA;267;0
"Building";"CreepTumor";NA;267;0
"Building";"CreepTumor";NA;267;0
"Building";"CreepTumor";NA;267;0
"Building";"CreepTumor";NA;267;0
"Building";"CreepTumor";NA;267;0
"Building";"CreepTumor";NA;267;0
"Unit";"Hydralisk";"Larva";267;2
"Unit";"Hydralisk";"Larva";267;2
"Unit";"Hydralisk";"Larva";267;2
"Unit";"Hydralisk";"Larva";267;2
"Unit";"Hydralisk";"Larva";267;2
"Unit";"Hydralisk";"Larva";267;2
"Unit";"Hydralisk";"Larva";267;2
"Unit";"Hydralisk";"Larva";267;2
"Unit";"Hydralisk";"Larva";267;2
"Unit";"Hydralisk";"Larva";267;2
"Unit";"Hydralisk";"Larva";267;2
