"type";"unit_name";"on_building";"total_supply";"supply"
"Unit";"Overlord";"Larva";13;0
"Building";"Extractor";NA;19;0
"Building";"Hatchery";NA;16;0
"Building";"SpawningPool";NA;19;0
"Unit";"Overlord";"Larva";22;0
"Unit";"Queen";"Hatchery";23;2
"Unit";"Queen";"Hatchery";23;2
"Unit";"Overlord";"Larva";32;0
"Unit";"Zergling";"Larva";35;1
"Unit";"Zergling";"Larva";35;1
"Unit";"Zergling";"Larva";35;1
"Unit";"Zergling";"Larva";35;1
"Building";"CreepTumorQueen";NA;36;0
"Unit";"Overlord";"Larva";38;0
"Unit";"Queen";"Hatchery";36;2
"Unit";"Overlord";"Larva";40;0
"Building";"Hatchery";NA;27;0
"Building";"SporeCrawler";NA;44;0
"Building";"CreepTumorQueen";NA;50;0
"Building";"CreepTumor";NA;51;0
"Unit";"Overlord";"Larva";51;0
"Unit";"Overlord";"Larva";51;0
"Unit";"Queen";"Hatchery";49;2
"Unit";"Zergling";"Larva";57;1
"Unit";"Zergling";"Larva";57;1
"Unit";"Queen";"Hatchery";49;2
"Building";"CreepTumor";NA;57;0
"Unit";"Overlord";"Larva";59;0
"Building";"CreepTumorQueen";NA;68;0
"Building";"CreepTumor";NA;70;0
"Building";"Extractor";NA;74;0
"Building";"Extractor";NA;74;0
"Building";"CreepTumor";NA;79;0
"Building";"Extractor";NA;78;0
"Building";"Extractor";NA;78;0
"Building";"CreepTumorQueen";NA;88;0
"Building";"CreepTumor";NA;88;0
"Building";"EvolutionChamber";NA;79;0
"Unit";"Overlord";"Larva";88;0
"Unit";"Overlord";"Larva";88;0
"Building";"CreepTumorQueen";NA;88;0
"Building";"CreepTumor";NA;88;0
"Building";"HydraliskDen";NA;88;0
"Unit";"Overlord";"Larva";88;0
"Unit";"Overlord";"Larva";88;0
"Unit";"Overlord";"Larva";88;0
"Unit";"Overlord";"Larva";88;0
"Unit";"Overlord";"Larva";88;0
"Unit";"Overlord";"Larva";88;0
"Unit";"Hydralisk";"Larva";88;2
"Unit";"Hydralisk";"Larva";88;2
"Unit";"Hydralisk";"Larva";88;2
"Unit";"Hydralisk";"Larva";88;2
"Unit";"Hydralisk";"Larva";88;2
"Unit";"Hydralisk";"Larva";88;2
"Unit";"Hydralisk";"Larva";88;2
"Unit";"Hydralisk";"Larva";88;2
"Building";"CreepTumor";NA;88;0
"Building";"CreepTumor";NA;88;0
"Building";"CreepTumor";NA;88;0
"Building";"CreepTumor";NA;88;0
"Unit";"Hydralisk";"Larva";88;2
"Unit";"Hydralisk";"Larva";88;2
"Unit";"Queen";"Hatchery";88;2
"Unit";"Hydralisk";"Larva";88;2
"Unit";"Hydralisk";"Larva";88;2
"Unit";"Hydralisk";"Larva";88;2
"Unit";"Hydralisk";"Larva";104;2
"Unit";"Overlord";"Larva";110;0
"Unit";"Overlord";"Larva";110;0
"Unit";"Overlord";"Larva";110;0
"Unit";"Hydralisk";"Larva";110;2
"Unit";"Hydralisk";"Larva";110;2
"Building";"CreepTumor";NA;118;0
"Building";"CreepTumor";NA;118;0
"Unit";"Overlord";"Larva";118;0
"Unit";"Overlord";"Larva";118;0
"Unit";"Hydralisk";"Larva";118;2
"Unit";"Hydralisk";"Larva";118;2
"Unit";"Hydralisk";"Larva";118;2
"Unit";"Hydralisk";"Larva";118;2
"Unit";"Queen";"Hatchery";116;2
"Unit";"Queen";"Hatchery";116;2
"Unit";"Overlord";"Larva";122;0
"Unit";"Hydralisk";"Larva";122;2
"Unit";"Hydralisk";"Larva";122;2
"Unit";"Hydralisk";"Larva";122;2
"Building";"CreepTumor";NA;130;0
"Building";"CreepTumor";NA;130;0
"Upgrade";"EvolveGroovedSpines";"HydraliskDen";116;0
"Unit";"Hydralisk";"Larva";122;2
"Unit";"Hydralisk";"Larva";122;2
"Unit";"Zergling";"Larva";130;1
"Unit";"Zergling";"Larva";130;1
"Unit";"Zergling";"Larva";130;1
"Unit";"Zergling";"Larva";130;1
"Unit";"Zergling";"Larva";130;1
"Unit";"Zergling";"Larva";130;1
"Unit";"Zergling";"Larva";130;1
"Unit";"Zergling";"Larva";130;1
"Unit";"Zergling";"Larva";130;1
"Unit";"Zergling";"Larva";130;1
"Unit";"Zergling";"Larva";130;1
"Unit";"Zergling";"Larva";130;1
"Unit";"Zergling";"Larva";130;1
"Unit";"Zergling";"Larva";130;1
"Unit";"Zergling";"Larva";130;1
"Unit";"Zergling";"Larva";130;1
"Unit";"Hydralisk";"Larva";122;2
"Upgrade";"ZergMissileWeaponsLevel1";"EvolutionChamber";88;0
"Unit";"Queen";"Hatchery";122;2
"Unit";"Zergling";"Larva";140;1
"Unit";"Zergling";"Larva";140;1
"Unit";"Zergling";"Larva";140;1
"Unit";"Zergling";"Larva";140;1
"Unit";"Zergling";"Larva";140;1
"Unit";"Zergling";"Larva";140;1
"Unit";"Zergling";"Larva";140;1
"Unit";"Zergling";"Larva";140;1
"Unit";"Zergling";"Larva";140;1
"Unit";"Zergling";"Larva";140;1
"Unit";"Zergling";"Larva";140;1
"Unit";"Zergling";"Larva";140;1
"Unit";"Zergling";"Larva";140;1
"Unit";"Zergling";"Larva";140;1
"Unit";"Zergling";"Larva";144;1
"Unit";"Zergling";"Larva";144;1
"Unit";"Zergling";"Larva";144;1
"Unit";"Zergling";"Larva";144;1
"Unit";"Zergling";"Larva";144;1
"Unit";"Zergling";"Larva";144;1
"Unit";"Hydralisk";"Larva";162;2
"Unit";"Hydralisk";"Larva";162;2
"Unit";"Hydralisk";"Larva";162;2
"Unit";"Hydralisk";"Larva";190;2
"Unit";"Hydralisk";"Larva";190;2
"Unit";"Hydralisk";"Larva";190;2
"Unit";"Hydralisk";"Larva";190;2
"Unit";"Hydralisk";"Larva";190;2
"Unit";"Hydralisk";"Larva";190;2
"Unit";"Hydralisk";"Larva";190;2
"Unit";"Zergling";"Larva";190;1
"Unit";"Zergling";"Larva";190;1
"Unit";"Hydralisk";"Larva";190;2
"Unit";"Hydralisk";"Larva";190;2
"Unit";"Hydralisk";"Larva";190;2
"Unit";"Hydralisk";"Larva";210;2
"Unit";"Hydralisk";"Larva";210;2
"Unit";"Hydralisk";"Larva";210;2
"Unit";"Hydralisk";"Larva";210;2
"Unit";"Hydralisk";"Larva";212;2
"Unit";"Hydralisk";"Larva";212;2
"Unit";"Hydralisk";"Larva";212;2
"Unit";"Hydralisk";"Larva";212;2
"Unit";"Hydralisk";"Larva";212;2
"Unit";"Hydralisk";"Larva";212;2
"Unit";"Hydralisk";"Larva";220;2
"Unit";"Hydralisk";"Larva";220;2
"Unit";"Hydralisk";"Larva";220;2
"Upgrade";"EvolveMuscularAugments";"HydraliskDen";212;0
"Unit";"Hydralisk";"Larva";232;2
"Unit";"Zergling";"Larva";234;1
"Unit";"Zergling";"Larva";234;1
"Unit";"Zergling";"Larva";238;1
"Unit";"Zergling";"Larva";238;1
"Unit";"Zergling";"Larva";238;1
"Unit";"Zergling";"Larva";238;1
"Unit";"Zergling";"Larva";238;1
"Unit";"Zergling";"Larva";238;1
"Unit";"Zergling";"Larva";238;1
"Unit";"Zergling";"Larva";238;1
"Unit";"Zergling";"Larva";238;1
"Unit";"Zergling";"Larva";238;1
"Building";"Extractor";NA;232;0
"Unit";"Hydralisk";"Larva";232;2
"Unit";"Hydralisk";"Larva";232;2
"Unit";"Hydralisk";"Larva";232;2
"Unit";"Hydralisk";"Larva";232;2
"Building";"CreepTumor";NA;238;0
"Building";"CreepTumor";NA;238;0
"Unit";"Hydralisk";"Larva";238;2
"Unit";"Queen";"Hatchery";232;2
"Unit";"Queen";"Hatchery";232;2
"Unit";"Hydralisk";"Larva";238;2
"Unit";"Hydralisk";"Larva";238;2
"Unit";"Hydralisk";"Larva";238;2
"Unit";"Hydralisk";"Larva";252;2
"Unit";"Hydralisk";"Larva";260;2
"Building";"CreepTumorQueen";NA;266;0
"Unit";"Hydralisk";"Larva";260;2
"Unit";"Overlord";"Larva";262;0
"Unit";"Overlord";"Larva";262;0
"Unit";"Overlord";"Larva";262;0
"Unit";"Hydralisk";"Larva";262;2
"Unit";"Hydralisk";"Larva";262;2
"Building";"CreepTumor";NA;272;0
"Building";"CreepTumor";NA;274;0
"Unit";"Queen";"Hatchery";260;2
"Unit";"Hydralisk";"Larva";274;2
"Unit";"Hydralisk";"Larva";274;2
"Unit";"Hydralisk";"Larva";274;2
"Unit";"Hydralisk";"Larva";274;2
"Unit";"Hydralisk";"Larva";274;2
"Unit";"Queen";"Hatchery";262;2
"Unit";"Queen";"Hatchery";264;2
"Unit";"Hydralisk";"Larva";282;2
"Unit";"Hydralisk";"Larva";282;2
"Unit";"Hydralisk";"Larva";282;2
"Unit";"Hydralisk";"Larva";282;2
"Building";"Hatchery";NA;238;0
"Building";"CreepTumor";NA;298;0
"Unit";"Hydralisk";"Larva";284;2
"Unit";"Hydralisk";"Larva";284;2
"Building";"CreepTumor";NA;298;0
"Unit";"Queen";"Hatchery";282;2
"Unit";"Zergling";"Larva";312;1
"Unit";"Zergling";"Larva";312;1
"Unit";"Zergling";"Larva";312;1
"Unit";"Zergling";"Larva";312;1
"Unit";"Queen";"Hatchery";294;2
"Unit";"Hydralisk";"Larva";306;2
"Unit";"Hydralisk";"Larva";306;2
"Unit";"Hydralisk";"Larva";306;2
"Unit";"Hydralisk";"Larva";330;2
"Unit";"Hydralisk";"Larva";330;2
"Unit";"Hydralisk";"Larva";330;2
"Unit";"Hydralisk";"Larva";330;2
"Unit";"Hydralisk";"Larva";330;2
"Unit";"Hydralisk";"Larva";330;2
"Unit";"Hydralisk";"Larva";330;2
