"type";"unit_name";"on_building";"total_supply";"supply"
"Unit";"Overlord";"Larva";13;0
"Building";"Extractor";NA;18;0
"Unit";"Overlord";"Larva";21;0
"Building";"SpawningPool";NA;19;0
"Building";"Hatchery";NA;17;0
"Unit";"Zergling";"Larva";22;1
"Unit";"Zergling";"Larva";22;1
"Unit";"Queen";"Hatchery";22;2
"Unit";"Queen";"Hatchery";23;2
"Unit";"Zergling";"Larva";30;1
"Unit";"Zergling";"Larva";30;1
"Unit";"Zergling";"Larva";30;1
"Unit";"Zergling";"Larva";30;1
"Unit";"Overlord";"Larva";34;0
"Unit";"Overlord";"Larva";39;0
"Building";"Hatchery";NA;28;0
"Building";"SporeCrawler";NA;49;0
"Unit";"Queen";"Hatchery";43;2
"Unit";"Queen";"Hatchery";43;2
"Building";"SporeCrawler";NA;49;0
"Building";"CreepTumorQueen";NA;58;0
"Unit";"Queen";"Hatchery";49;2
"Unit";"Overlord";"Larva";58;0
"Unit";"Overlord";"Larva";58;0
"Building";"Extractor";NA;58;0
"Unit";"Zergling";"Larva";58;1
"Unit";"Zergling";"Larva";58;1
"Unit";"Zergling";"Larva";58;1
"Unit";"Zergling";"Larva";58;1
"Building";"RoachWarren";NA;58;0
"Building";"CreepTumorQueen";NA;70;0
"Building";"Extractor";NA;71;0
"Unit";"Overlord";"Larva";71;0
"Unit";"Overlord";"Larva";71;0
"Building";"CreepTumorQueen";NA;79;0
"Building";"CreepTumorQueen";NA;79;0
"Building";"CreepTumor";NA;79;0
"Building";"CreepTumor";NA;79;0
"Building";"CreepTumorQueen";NA;79;0
"Unit";"Overlord";"Larva";79;0
"Unit";"Roach";"Larva";79;2
"Unit";"Roach";"Larva";79;2
"Building";"CreepTumor";NA;88;0
"Building";"CreepTumor";NA;88;0
"Unit";"Roach";"Larva";88;2
"Building";"CreepTumor";NA;88;0
"Unit";"Roach";"Larva";88;2
"Unit";"Roach";"Larva";88;2
"Building";"CreepTumor";NA;88;0
"Unit";"Roach";"Larva";88;2
"Unit";"Overlord";"Larva";88;0
"Building";"CreepTumorQueen";NA;92;0
"Building";"CreepTumorQueen";NA;92;0
"Unit";"Roach";"Larva";92;2
"Unit";"Roach";"Larva";92;2
"Unit";"Roach";"Larva";92;2
"Building";"SporeCrawler";NA;92;0
"Unit";"Roach";"Larva";92;2
"Unit";"Roach";"Larva";92;2
"Unit";"Overlord";"Larva";100;0
"Unit";"Overlord";"Larva";100;0
"Unit";"Roach";"Larva";100;2
"Unit";"Roach";"Larva";100;2
"Unit";"Roach";"Larva";100;2
"Building";"EvolutionChamber";NA;100;0
"Unit";"Overlord";"Larva";110;0
"Unit";"Overlord";"Larva";110;0
"Unit";"Roach";"Larva";110;2
"Unit";"Roach";"Larva";110;2
"Unit";"Overlord";"Larva";112;0
"Unit";"Overlord";"Larva";116;0
"Unit";"Roach";"Larva";116;2
"Unit";"Roach";"Larva";116;2
"Unit";"Roach";"Larva";116;2
"Unit";"Roach";"Larva";116;2
"Unit";"Roach";"Larva";120;2
"Unit";"Roach";"Larva";120;2
"Unit";"Roach";"Larva";120;2
"Unit";"Roach";"Larva";120;2
"Unit";"Roach";"Larva";128;2
"Unit";"Roach";"Larva";128;2
"Unit";"Roach";"Larva";128;2
"Unit";"Roach";"Larva";136;2
"Unit";"Roach";"Larva";136;2
"Unit";"Roach";"Larva";136;2
"Unit";"Roach";"Larva";136;2
"Building";"CreepTumor";NA;154;0
"Building";"CreepTumor";NA;154;0
"Building";"CreepTumor";NA;154;0
"Building";"CreepTumor";NA;154;0
"Building";"CreepTumorQueen";NA;161;0
"Building";"CreepTumorQueen";NA;161;0
"Building";"CreepTumorQueen";NA;161;0
"Building";"CreepTumorQueen";NA;161;0
"Unit";"Overlord";"Larva";161;0
"Unit";"Roach";"Larva";165;2
"Unit";"Roach";"Larva";165;2
"Unit";"Roach";"Larva";173;2
"Unit";"Roach";"Larva";173;2
"Unit";"Roach";"Larva";173;2
"Unit";"Roach";"Larva";173;2
"Unit";"Roach";"Larva";173;2
"Unit";"Roach";"Larva";173;2
"Unit";"Roach";"Larva";177;2
"Unit";"Roach";"Larva";177;2
"Unit";"Roach";"Larva";177;2
"Unit";"Roach";"Larva";177;2
"Unit";"Roach";"Larva";177;2
"Unit";"Roach";"Larva";177;2
"Unit";"Roach";"Larva";179;2
"Unit";"Roach";"Larva";189;2
"Unit";"Roach";"Larva";189;2
"Unit";"Roach";"Larva";189;2
"Unit";"Roach";"Larva";189;2
"Building";"CreepTumor";NA;203;0
"Building";"CreepTumor";NA;203;0
"Building";"CreepTumor";NA;203;0
"Building";"CreepTumor";NA;203;0
"Building";"Extractor";NA;203;0
"Building";"CreepTumor";NA;211;0
"Building";"CreepTumor";NA;211;0
"Building";"CreepTumor";NA;211;0
"Building";"CreepTumor";NA;211;0
"Building";"CreepTumorQueen";NA;211;0
"Building";"CreepTumorQueen";NA;211;0
"Building";"CreepTumorQueen";NA;211;0
"Building";"Extractor";NA;211;0
"Unit";"Roach";"Larva";211;2
"Unit";"Roach";"Larva";211;2
"Unit";"Roach";"Larva";211;2
"Unit";"Roach";"Larva";211;2
"Unit";"Roach";"Larva";211;2
"Unit";"Roach";"Larva";211;2
"Unit";"Roach";"Larva";211;2
"Unit";"Roach";"Larva";211;2
"Unit";"Roach";"Larva";211;2
"Unit";"Roach";"Larva";211;2
"Unit";"Roach";"Larva";211;2
"Building";"CreepTumor";NA;211;0
"Building";"CreepTumor";NA;211;0
"Building";"Extractor";NA;211;0
"Upgrade";"GlialReconstitution";"RoachWarren";211;0
"Building";"HydraliskDen";NA;233;0
"Unit";"Roach";"Larva";233;2
"Unit";"Roach";"Larva";233;2
"Unit";"Roach";"Larva";233;2
"Unit";"Roach";"Larva";233;2
"Unit";"Roach";"Larva";233;2
"Unit";"Roach";"Larva";233;2
"Unit";"Roach";"Larva";233;2
"Unit";"Roach";"Larva";233;2
"Unit";"Roach";"Larva";233;2
"Unit";"Roach";"Larva";233;2
"Unit";"Roach";"Larva";233;2
"Unit";"Roach";"Larva";233;2
"Unit";"Roach";"Larva";233;2
"Unit";"Roach";"Larva";233;2
"Unit";"Roach";"Larva";233;2
"Unit";"Roach";"Larva";233;2
"Unit";"Roach";"Larva";233;2
"Unit";"Roach";"Larva";233;2
"Upgrade";"ZergMissileWeaponsLevel1";"EvolutionChamber";211;0
"Building";"CreepTumor";NA;269;0
"Building";"CreepTumor";NA;269;0
"Building";"CreepTumor";NA;269;0
"Unit";"Hydralisk";"Larva";269;2
"Building";"CreepTumor";NA;269;0
"Unit";"Hydralisk";"Larva";269;2
"Unit";"Hydralisk";"Larva";269;2
"Unit";"Hydralisk";"Larva";269;2
"Unit";"Hydralisk";"Larva";269;2
"Unit";"Hydralisk";"Larva";269;2
"Unit";"Hydralisk";"Larva";269;2
"Unit";"Hydralisk";"Larva";269;2
"Unit";"Hydralisk";"Larva";269;2
"Unit";"Hydralisk";"Larva";269;2
"Unit";"Hydralisk";"Larva";269;2
"Unit";"Hydralisk";"Larva";269;2
"Building";"CreepTumor";NA;269;0
"Building";"CreepTumor";NA;269;0
"Building";"CreepTumor";NA;269;0
"Building";"CreepTumor";NA;269;0
"Building";"CreepTumor";NA;269;0
"Building";"CreepTumor";NA;269;0
"Building";"CreepTumor";NA;269;0
"Building";"CreepTumorQueen";NA;293;0
"Building";"CreepTumorQueen";NA;293;0
"Unit";"Overlord";"Larva";293;0
"Unit";"Overlord";"Larva";299;0
"Unit";"Overlord";"Larva";299;0
"Unit";"Overlord";"Larva";299;0
"Unit";"Overlord";"Larva";299;0
"Building";"CreepTumor";NA;299;0
"Building";"CreepTumor";NA;299;0
"Building";"CreepTumor";NA;299;0
"Building";"CreepTumor";NA;306;0
"Building";"CreepTumor";NA;306;0
"Building";"CreepTumor";NA;306;0
"Building";"CreepTumor";NA;306;0
"Building";"CreepTumor";NA;306;0
"Building";"CreepTumor";NA;306;0
"Building";"CreepTumor";NA;306;0
"Building";"CreepTumorQueen";NA;306;0
"Building";"CreepTumor";NA;306;0
"Building";"CreepTumorQueen";NA;306;0
"Building";"CreepTumorQueen";NA;306;0
"Building";"Hatchery";NA;269;0
"Upgrade";"EvolveGroovedSpines";"HydraliskDen";299;0
"Building";"InfestationPit";NA;306;0
"Building";"CreepTumor";NA;306;0
"Building";"CreepTumor";NA;306;0
"Building";"CreepTumor";NA;306;0
"Building";"CreepTumor";NA;306;0
"Unit";"Hydralisk";"Larva";306;2
"Unit";"Hydralisk";"Larva";306;2
"Unit";"Hydralisk";"Larva";306;2
"Unit";"Hydralisk";"Larva";306;2
"Unit";"Hydralisk";"Larva";306;2
"Unit";"Hydralisk";"Larva";306;2
"Unit";"Hydralisk";"Larva";306;2
"Unit";"Hydralisk";"Larva";306;2
"Unit";"Hydralisk";"Larva";306;2
"Unit";"Hydralisk";"Larva";306;2
"Unit";"Roach";"Larva";306;2
"Unit";"Roach";"Larva";306;2
"Unit";"Roach";"Larva";306;2
"Unit";"Roach";"Larva";306;2
"Unit";"Roach";"Larva";306;2
"Unit";"Roach";"Larva";306;2
"Unit";"Roach";"Larva";306;2
"Unit";"Roach";"Larva";306;2
"Unit";"Roach";"Larva";326;2
"Unit";"Roach";"Larva";326;2
"Unit";"Roach";"Larva";326;2
"Unit";"Roach";"Larva";326;2
"Unit";"Roach";"Larva";326;2
"Upgrade";"ZergMissileWeaponsLevel2";"EvolutionChamber";306;0
