"type";"unit_name";"on_building";"total_supply";"supply"
"Unit";"Overlord";"Larva";13;0
"Building";"Extractor";NA;18;0
"Unit";"Overlord";"Larva";21;0
"Building";"SpawningPool";NA;19;0
"Building";"Hatchery";NA;17;0
"Unit";"Zergling";"Larva";22;1
"Unit";"Zergling";"Larva";22;1
"Unit";"Queen";"Hatchery";22;2
"Unit";"Queen";"Hatchery";22;2
"Unit";"Overlord";"Larva";34;0
"Unit";"Queen";"Hatchery";34;2
"Building";"CreepTumorQueen";NA;36;0
"Unit";"Zergling";"Larva";36;1
"Unit";"Zergling";"Larva";36;1
"Unit";"Zergling";"Larva";36;1
"Unit";"Zergling";"Larva";36;1
"Building";"CreepTumorQueen";NA;39;0
"Unit";"Overlord";"Larva";39;0
"Building";"Hatchery";NA;34;0
"Building";"CreepTumor";NA;49;0
"Building";"RoachWarren";NA;48;0
"Building";"Extractor";NA;52;0
"Unit";"Overlord";"Larva";59;0
"Unit";"Overlord";"Larva";59;0
"Building";"SporeCrawler";NA;59;0
"Unit";"Queen";"Hatchery";52;2
"Building";"SporeCrawler";NA;59;0
"Building";"CreepTumor";NA;62;0
"Building";"CreepTumor";NA;62;0
"Building";"SporeCrawler";NA;62;0
"Building";"CreepTumorQueen";NA;64;0
"Building";"CreepTumorQueen";NA;64;0
"Unit";"Overlord";"Larva";75;0
"Unit";"Overlord";"Larva";75;0
"Unit";"Overlord";"Larva";75;0
"Building";"CreepTumor";NA;75;0
"Building";"CreepTumor";NA;77;0
"Building";"CreepTumor";NA;77;0
"Building";"CreepTumor";NA;77;0
"Building";"CreepTumorQueen";NA;77;0
"Unit";"Overlord";"Larva";77;0
"Unit";"Roach";"Larva";77;2
"Unit";"Roach";"Larva";77;2
"Unit";"Roach";"Larva";77;2
"Unit";"Roach";"Larva";77;2
"Unit";"Roach";"Larva";77;2
"Unit";"Roach";"Larva";77;2
"Unit";"Roach";"Larva";77;2
"Unit";"Roach";"Larva";77;2
"Unit";"Roach";"Larva";77;2
"Unit";"Roach";"Larva";77;2
"Unit";"Roach";"Larva";77;2
"Building";"CreepTumor";NA;77;0
"Unit";"Roach";"Larva";77;2
"Building";"CreepTumor";NA;87;0
"Building";"CreepTumor";NA;87;0
"Building";"CreepTumor";NA;87;0
"Building";"CreepTumorQueen";NA;93;0
"Unit";"Roach";"Larva";87;2
"Unit";"Roach";"Larva";87;2
"Unit";"Roach";"Larva";87;2
"Unit";"Roach";"Larva";87;2
"Unit";"Roach";"Larva";87;2
"Unit";"Overlord";"Larva";111;0
"Unit";"Overlord";"Larva";111;0
"Unit";"Overlord";"Larva";111;0
"Unit";"Overlord";"Larva";111;0
"Unit";"Roach";"Larva";111;2
"Building";"SpineCrawler";NA;101;0
"Building";"SpineCrawler";NA;101;0
"Building";"SpineCrawler";NA;101;0
"Unit";"Zergling";"Larva";113;1
"Unit";"Zergling";"Larva";113;1
"Unit";"Zergling";"Larva";113;1
"Unit";"Zergling";"Larva";113;1
"Unit";"Zergling";"Larva";113;1
"Unit";"Zergling";"Larva";113;1
"Unit";"Roach";"Larva";113;2
"Unit";"Roach";"Larva";113;2
"Unit";"Roach";"Larva";113;2
"Unit";"Roach";"Larva";113;2
"Unit";"Roach";"Larva";113;2
"Unit";"Roach";"Larva";113;2
"Unit";"Roach";"Larva";113;2
"Unit";"Roach";"Larva";113;2
"Unit";"Queen";"Hatchery";113;2
"Upgrade";"GlialReconstitution";"RoachWarren";111;0
"Unit";"Zergling";"Larva";135;1
"Unit";"Zergling";"Larva";135;1
"Unit";"Zergling";"Larva";135;1
"Unit";"Zergling";"Larva";135;1
"Unit";"Zergling";"Larva";135;1
"Unit";"Zergling";"Larva";135;1
"Unit";"Zergling";"Larva";135;1
"Unit";"Zergling";"Larva";135;1
"Unit";"Zergling";"Larva";135;1
"Unit";"Zergling";"Larva";135;1
"Unit";"Zergling";"Larva";135;1
"Unit";"Zergling";"Larva";135;1
"Unit";"Roach";"Larva";135;2
"Unit";"Roach";"Larva";135;2
"Unit";"Roach";"Larva";135;2
"Unit";"Roach";"Larva";135;2
"Unit";"Roach";"Larva";135;2
"Unit";"Overlord";"Larva";137;0
"Unit";"Overlord";"Larva";137;0
"Unit";"Overlord";"Larva";137;0
"Unit";"Queen";"Hatchery";159;2
"Unit";"Queen";"Hatchery";159;2
"Building";"Extractor";NA;159;0
"Building";"Extractor";NA;159;0
"Building";"CreepTumor";NA;175;0
"Building";"CreepTumor";NA;175;0
"Building";"HydraliskDen";NA;159;0
"Building";"CreepTumor";NA;175;0
"Building";"CreepTumor";NA;175;0
"Building";"CreepTumor";NA;175;0
"Building";"CreepTumor";NA;175;0
"Building";"SpineCrawler";NA;175;0
"Building";"SpineCrawler";NA;175;0
"Unit";"Roach";"Larva";183;2
"Unit";"Roach";"Larva";183;2
"Unit";"Roach";"Larva";183;2
"Unit";"Roach";"Larva";183;2
"Unit";"Roach";"Larva";183;2
"Unit";"Roach";"Larva";183;2
"Building";"CreepTumor";NA;183;0
"Building";"CreepTumor";NA;183;0
"Building";"CreepTumor";NA;195;0
"Building";"CreepTumor";NA;195;0
"Building";"CreepTumor";NA;195;0
"Building";"CreepTumor";NA;195;0
"Building";"Extractor";NA;183;0
"Building";"Extractor";NA;183;0
"Building";"CreepTumor";NA;200;0
"Building";"CreepTumor";NA;200;0
"Building";"EvolutionChamber";NA;200;0
"Building";"EvolutionChamber";NA;200;0
"Upgrade";"EvolveGroovedSpines";"HydraliskDen";183;0
"Building";"CreepTumor";NA;209;0
"Building";"CreepTumor";NA;209;0
"Building";"CreepTumor";NA;209;0
"Building";"CreepTumor";NA;209;0
"Unit";"Hydralisk";"Larva";209;2
"Unit";"Hydralisk";"Larva";209;2
"Unit";"Hydralisk";"Larva";209;2
"Unit";"Hydralisk";"Larva";209;2
"Unit";"Hydralisk";"Larva";209;2
"Unit";"Hydralisk";"Larva";209;2
"Unit";"Hydralisk";"Larva";209;2
"Building";"CreepTumor";NA;209;0
"Building";"Hatchery";NA;200;0
"Building";"LurkerDenMP";NA;200;0
"Building";"Hatchery";NA;209;0
"Upgrade";"EvolveMuscularAugments";"HydraliskDen";209;0
"Building";"SporeCrawler";NA;238;0
"Building";"SporeCrawler";NA;238;0
"Building";"SporeCrawler";NA;238;0
"Building";"Extractor";NA;238;0
"Building";"Extractor";NA;238;0
"Building";"SporeCrawler";NA;238;0
"Building";"SporeCrawler";NA;238;0
"Unit";"Hydralisk";"Larva";238;2
"Unit";"Hydralisk";"Larva";238;2
"Unit";"Hydralisk";"Larva";238;2
"Unit";"Hydralisk";"Larva";238;2
"Unit";"Hydralisk";"Larva";238;2
"Building";"InfestationPit";NA;238;0
"Upgrade";"ZergMissileWeaponsLevel1";"EvolutionChamber";223;0
"Upgrade";"ZergGroundArmorsLevel1";"EvolutionChamber";223;0
"Building";"Hatchery";NA;236;0
"Building";"SporeCrawler";NA;256;0
"Unit";"Overlord";"Larva";256;0
"Unit";"Overlord";"Larva";256;0
"Unit";"Overlord";"Larva";256;0
"Unit";"Overlord";"Larva";256;0
"Unit";"Overlord";"Larva";256;0
"Unit";"Overlord";"Larva";256;0
"Unit";"Queen";"Hatchery";256;2
"Building";"SporeCrawler";NA;276;0
"Building";"SporeCrawler";NA;276;0
"Unit";"Hydralisk";"Larva";280;2
"Unit";"Hydralisk";"Larva";280;2
"Unit";"Hydralisk";"Larva";280;2
"Unit";"Hydralisk";"Larva";280;2
"Unit";"Hydralisk";"Larva";280;2
"Unit";"Hydralisk";"Larva";280;2
"Unit";"Hydralisk";"Larva";280;2
"Unit";"Hydralisk";"Larva";281;2
"Building";"Spire";NA;256;0
"Building";"Spire";NA;256;0
"Building";"SpineCrawler";NA;276;0
"Building";"SpineCrawler";NA;276;0
"Building";"SpineCrawler";NA;276;0
"Building";"SpineCrawler";NA;281;0
"Building";"SpineCrawler";NA;281;0
"Building";"SpineCrawler";NA;281;0
"Building";"SpineCrawler";NA;281;0
"Building";"SpineCrawler";NA;281;0
"Building";"SpineCrawler";NA;281;0
"Building";"SporeCrawler";NA;300;0
"Building";"Extractor";NA;300;0
"Building";"SporeCrawler";NA;300;0
"Building";"Extractor";NA;300;0
"Building";"SporeCrawler";NA;300;0
"Unit";"Queen";"Hatchery";300;2
"Upgrade";"ZergMissileWeaponsLevel2";"EvolutionChamber";281;0
"Upgrade";"ZergGroundArmorsLevel2";"EvolutionChamber";281;0
"Building";"SpineCrawler";NA;309;0
"Building";"SpineCrawler";NA;309;0
"Building";"SpineCrawler";NA;309;0
"Building";"SpineCrawler";NA;309;0
"Building";"SpineCrawler";NA;309;0
"Building";"SpineCrawler";NA;309;0
"Building";"SpineCrawler";NA;309;0
"Building";"SpineCrawler";NA;309;0
"Unit";"Corruptor";"Larva";322;2
"Unit";"Corruptor";"Larva";322;2
"Unit";"Corruptor";"Larva";322;2
"Unit";"Corruptor";"Larva";322;2
"Unit";"Corruptor";"Larva";322;2
"Unit";"Corruptor";"Larva";322;2
"Unit";"Corruptor";"Larva";322;2
"Building";"SporeCrawler";NA;336;0
"Building";"SpineCrawler";NA;336;0
"Building";"SpineCrawler";NA;336;0
"Building";"SpineCrawler";NA;336;0
"Building";"SpineCrawler";NA;336;0
"Building";"SpineCrawler";NA;336;0
"Unit";"Hydralisk";"Larva";349;2
"Unit";"Hydralisk";"Larva";349;2
"Unit";"Hydralisk";"Larva";349;2
"Unit";"Hydralisk";"Larva";349;2
"Unit";"Hydralisk";"Larva";349;2
"Unit";"Hydralisk";"Larva";349;2
"Unit";"Hydralisk";"Larva";349;2
"Unit";"Hydralisk";"Larva";349;2
"Unit";"Hydralisk";"Larva";349;2
"Unit";"Hydralisk";"Larva";349;2
"Unit";"Hydralisk";"Larva";349;2
"Unit";"Hydralisk";"Larva";349;2
"Unit";"Hydralisk";"Larva";349;2
"Building";"Hatchery";NA;363;0
"Upgrade";"ZergMissileWeaponsLevel3";"EvolutionChamber";349;0
"Upgrade";"ZergGroundArmorsLevel3";"EvolutionChamber";349;0
"Unit";"Roach";"Larva";375;2
"Unit";"Roach";"Larva";375;2
"Unit";"Roach";"Larva";375;2
"Unit";"Roach";"Larva";375;2
"Unit";"Roach";"Larva";375;2
"Unit";"Roach";"Larva";375;2
"Unit";"Roach";"Larva";375;2
"Unit";"Hydralisk";"Larva";375;2
