"type";"unit_name";"on_building";"total_supply";"supply"
"Unit";"Overlord";"Larva";13;0
"Building";"Extractor";NA;17;0
"Unit";"Overlord";"Larva";21;0
"Building";"SpawningPool";NA;19;0
"Building";"Hatchery";NA;17;0
"Unit";"Queen";"Hatchery";23;2
"Unit";"Queen";"Hatchery";23;2
"Unit";"Overlord";"Larva";34;0
"Unit";"Overlord";"Larva";34;0
"Unit";"Zergling";"Larva";36;1
"Unit";"Zergling";"Larva";36;1
"Unit";"Zergling";"Larva";36;1
"Unit";"Zergling";"Larva";36;1
"Building";"Extractor";NA;44;0
"Unit";"Queen";"Hatchery";37;2
"Unit";"Queen";"Hatchery";37;2
"Building";"Hatchery";NA;29;0
"Building";"CreepTumorQueen";NA;54;0
"Building";"CreepTumorQueen";NA;54;0
"Unit";"Overlord";"Larva";54;0
"Unit";"Overlord";"Larva";54;0
"Building";"EvolutionChamber";NA;54;0
"Unit";"Overlord";"Larva";59;0
"Unit";"Overlord";"Larva";59;0
"Unit";"Queen";"Hatchery";54;2
"Building";"RoachWarren";NA;54;0
"Building";"Extractor";NA;64;0
"Building";"SporeCrawler";NA;64;0
"Building";"SporeCrawler";NA;66;0
"Building";"SporeCrawler";NA;66;0
"Building";"HydraliskDen";NA;80;0
"Building";"Extractor";NA;88;0
"Building";"Extractor";NA;88;0
"Building";"Extractor";NA;88;0
"Unit";"Overlord";"Larva";88;0
"Building";"CreepTumor";NA;89;0
"Unit";"Overlord";"Larva";88;0
"Unit";"Overlord";"Larva";88;0
"Unit";"Overlord";"Larva";88;0
"Building";"CreepTumorQueen";NA;97;0
"Unit";"Overlord";"Larva";100;0
"Unit";"Overlord";"Larva";100;0
"Unit";"Overlord";"Larva";100;0
"Unit";"Overlord";"Larva";100;0
"Building";"CreepTumorQueen";NA;100;0
"Upgrade";"ZergMissileWeaponsLevel1";"EvolutionChamber";77;0
"Unit";"Hydralisk";"Larva";100;2
"Unit";"Hydralisk";"Larva";100;2
"Unit";"Hydralisk";"Larva";100;2
"Unit";"Hydralisk";"Larva";100;2
"Unit";"Hydralisk";"Larva";100;2
"Unit";"Hydralisk";"Larva";100;2
"Unit";"Hydralisk";"Larva";100;2
"Unit";"Hydralisk";"Larva";100;2
"Unit";"Hydralisk";"Larva";100;2
"Building";"CreepTumor";NA;123;0
"Building";"CreepTumorQueen";NA;123;0
"Building";"CreepTumorQueen";NA;124;0
"Upgrade";"EvolveGroovedSpines";"HydraliskDen";100;0
"Upgrade";"GlialReconstitution";"RoachWarren";100;0
"Building";"InfestationPit";NA;100;0
"Building";"CreepTumor";NA;126;0
"Building";"CreepTumor";NA;126;0
"Building";"CreepTumor";NA;126;0
"Building";"CreepTumor";NA;126;0
"Building";"CreepTumor";NA;126;0
"Building";"CreepTumorQueen";NA;126;0
"Unit";"Roach";"Larva";126;2
"Building";"CreepTumorQueen";NA;126;0
"Unit";"Roach";"Larva";126;2
"Unit";"Roach";"Larva";126;2
"Unit";"Roach";"Larva";126;2
"Unit";"Roach";"Larva";126;2
"Unit";"Roach";"Larva";126;2
"Unit";"Roach";"Larva";126;2
"Unit";"Roach";"Larva";126;2
"Unit";"Roach";"Larva";126;2
"Unit";"Roach";"Larva";126;2
"Unit";"Roach";"Larva";126;2
"Unit";"Roach";"Larva";126;2
"Building";"CreepTumorQueen";NA;126;0
"Building";"CreepTumorQueen";NA;126;0
"Building";"Hatchery";NA;100;0
"Unit";"Overlord";"Larva";128;0
"Unit";"Overlord";"Larva";128;0
"Unit";"Overlord";"Larva";134;0
"Unit";"Overlord";"Larva";144;0
"Unit";"Overlord";"Larva";150;0
"Building";"CreepTumor";NA;150;0
"Building";"CreepTumor";NA;150;0
"Building";"CreepTumor";NA;150;0
"Building";"CreepTumor";NA;150;0
"Building";"CreepTumor";NA;150;0
"Building";"CreepTumor";NA;150;0
"Building";"CreepTumor";NA;150;0
"Building";"Extractor";NA;150;0
"Building";"CreepTumorQueen";NA;150;0
"Unit";"Overlord";"Larva";150;0
"Building";"CreepTumorQueen";NA;157;0
"Building";"Extractor";NA;150;0
"Building";"CreepTumor";NA;150;0
"Building";"CreepTumorQueen";NA;157;0
"Building";"CreepTumor";NA;157;0
"Building";"CreepTumor";NA;157;0
"Building";"LurkerDenMP";NA;100;0
"Unit";"Hydralisk";"Larva";157;2
"Unit";"Hydralisk";"Larva";157;2
"Unit";"Hydralisk";"Larva";157;2
"Unit";"Hydralisk";"Larva";157;2
"Unit";"Hydralisk";"Larva";157;2
"Unit";"Hydralisk";"Larva";157;2
"Unit";"Hydralisk";"Larva";157;2
"Unit";"Hydralisk";"Larva";157;2
"Unit";"Hydralisk";"Larva";157;2
"Building";"SporeCrawler";NA;157;0
"Building";"CreepTumor";NA;157;0
"Building";"CreepTumor";NA;157;0
"Building";"CreepTumor";NA;157;0
"Building";"CreepTumor";NA;157;0
"Building";"CreepTumor";NA;175;0
"Building";"CreepTumor";NA;175;0
"Building";"CreepTumor";NA;175;0
"Building";"CreepTumor";NA;175;0
"Building";"CreepTumorQueen";NA;175;0
"Building";"CreepTumor";NA;175;0
"Building";"CreepTumor";NA;175;0
"Building";"CreepTumor";NA;175;0
"Upgrade";"EvolveMuscularAugments";"HydraliskDen";150;0
"Unit";"Hydralisk";"Larva";175;2
"Unit";"Hydralisk";"Larva";175;2
"Unit";"Hydralisk";"Larva";175;2
"Unit";"Hydralisk";"Larva";175;2
"Unit";"Hydralisk";"Larva";175;2
"Unit";"Hydralisk";"Larva";175;2
"Unit";"Hydralisk";"Larva";175;2
"Unit";"Hydralisk";"Larva";175;2
"Unit";"Hydralisk";"Larva";175;2
"Unit";"Hydralisk";"Larva";175;2
"Unit";"Hydralisk";"Larva";175;2
"Unit";"Hydralisk";"Larva";175;2
"Unit";"Hydralisk";"Larva";175;2
"Unit";"Roach";"Larva";175;2
"Unit";"Roach";"Larva";175;2
"Unit";"Roach";"Larva";175;2
"Unit";"Roach";"Larva";175;2
"Unit";"Roach";"Larva";175;2
"Unit";"Roach";"Larva";175;2
"Upgrade";"ZergMissileWeaponsLevel2";"EvolutionChamber";126;0
"Unit";"Roach";"Larva";175;2
"Unit";"Roach";"Larva";175;2
"Unit";"Roach";"Larva";175;2
"Unit";"Roach";"Larva";175;2
"Unit";"Roach";"Larva";175;2
"Unit";"Hydralisk";"Larva";201;2
"Unit";"Hydralisk";"Larva";201;2
"Unit";"Hydralisk";"Larva";201;2
"Unit";"Hydralisk";"Larva";211;2
"Unit";"Hydralisk";"Larva";213;2
"Building";"CreepTumor";NA;239;0
"Building";"CreepTumor";NA;239;0
"Building";"CreepTumor";NA;239;0
"Building";"CreepTumor";NA;239;0
"Unit";"Roach";"Larva";233;2
"Unit";"Roach";"Larva";233;2
"Unit";"Roach";"Larva";233;2
"Unit";"Roach";"Larva";233;2
"Building";"CreepTumor";NA;239;0
"Unit";"Roach";"Larva";233;2
"Unit";"Queen";"Hatchery";233;2
"Building";"CreepTumorQueen";NA;239;0
"Building";"CreepTumorQueen";NA;239;0
"Building";"CreepTumorQueen";NA;249;0
"Building";"CreepTumorQueen";NA;251;0
"Unit";"Hydralisk";"Larva";249;2
"Unit";"Hydralisk";"Larva";249;2
"Unit";"Hydralisk";"Larva";249;2
"Unit";"Hydralisk";"Larva";249;2
"Unit";"Hydralisk";"Larva";249;2
"Unit";"Hydralisk";"Larva";249;2
"Unit";"Hydralisk";"Larva";249;2
"Unit";"Hydralisk";"Larva";249;2
"Unit";"Hydralisk";"Larva";251;2
"Building";"CreepTumor";NA;251;0
"Building";"CreepTumor";NA;251;0
"Building";"CreepTumor";NA;251;0
"Building";"CreepTumor";NA;251;0
"Unit";"Overlord";"Larva";251;0
"Unit";"Overlord";"Larva";251;0
"Unit";"Overlord";"Larva";251;0
"Upgrade";"ZergMissileWeaponsLevel3";"EvolutionChamber";233;0
"Unit";"Roach";"Larva";284;2
"Unit";"Roach";"Larva";284;2
"Unit";"Roach";"Larva";284;2
"Unit";"Roach";"Larva";284;2
"Unit";"Roach";"Larva";284;2
"Unit";"Roach";"Larva";284;2
"Unit";"Roach";"Larva";284;2
"Unit";"Roach";"Larva";284;2
"Unit";"Roach";"Larva";284;2
"Unit";"Roach";"Larva";284;2
"Unit";"Roach";"Larva";284;2
"Unit";"Roach";"Larva";284;2
"Unit";"Roach";"Larva";284;2
"Unit";"Roach";"Larva";284;2
"Unit";"Roach";"Larva";284;2
"Unit";"Roach";"Larva";284;2
"Unit";"Roach";"Larva";284;2
"Unit";"Roach";"Larva";284;2
"Unit";"Roach";"Larva";284;2
"Unit";"Hydralisk";"Larva";284;2
"Unit";"Hydralisk";"Larva";284;2
"Unit";"Hydralisk";"Larva";284;2
"Unit";"Hydralisk";"Larva";284;2
"Unit";"Hydralisk";"Larva";284;2
"Unit";"Hydralisk";"Larva";284;2
"Unit";"Hydralisk";"Larva";284;2
"Unit";"Hydralisk";"Larva";284;2
"Unit";"Hydralisk";"Larva";284;2
"Unit";"Hydralisk";"Larva";284;2
"Unit";"Hydralisk";"Larva";284;2
"Unit";"Hydralisk";"Larva";284;2
"Unit";"Hydralisk";"Larva";284;2
"Building";"Hatchery";NA;283;0
"Unit";"Hydralisk";"Larva";348;2
"Unit";"Hydralisk";"Larva";348;2
"Unit";"Hydralisk";"Larva";348;2
"Unit";"Hydralisk";"Larva";348;2
"Unit";"Hydralisk";"Larva";348;2
"Unit";"Hydralisk";"Larva";348;2
"Unit";"Hydralisk";"Larva";348;2
"Unit";"Hydralisk";"Larva";348;2
"Unit";"Hydralisk";"Larva";348;2
"Unit";"Hydralisk";"Larva";348;2
"Unit";"Hydralisk";"Larva";348;2
"Unit";"Hydralisk";"Larva";348;2
"Unit";"Hydralisk";"Larva";348;2
"Building";"Spire";NA;284;0
"Building";"CreepTumor";NA;374;0
"Building";"CreepTumor";NA;374;0
"Building";"CreepTumor";NA;374;0
"Unit";"Hydralisk";"Larva";348;2
"Unit";"Hydralisk";"Larva";348;2
"Building";"CreepTumor";NA;374;0
"Building";"CreepTumor";NA;374;0
"Building";"CreepTumor";NA;374;0
"Building";"CreepTumor";NA;374;0
"Building";"CreepTumor";NA;374;0
"Building";"CreepTumor";NA;374;0
"Unit";"Roach";"Larva";378;2
"Unit";"Roach";"Larva";378;2
"Unit";"Roach";"Larva";378;2
"Unit";"Roach";"Larva";378;2
"Unit";"Roach";"Larva";378;2
"Unit";"Roach";"Larva";378;2
"Unit";"Roach";"Larva";378;2
"Unit";"Roach";"Larva";378;2
"Unit";"Hydralisk";"Larva";394;2
"Unit";"Hydralisk";"Larva";394;2
"Unit";"Hydralisk";"Larva";394;2
"Unit";"Hydralisk";"Larva";394;2
"Unit";"Hydralisk";"Larva";394;2
"Unit";"Hydralisk";"Larva";394;2
"Unit";"Hydralisk";"Larva";394;2
"Unit";"Hydralisk";"Larva";394;2
"Unit";"Hydralisk";"Larva";394;2
"Unit";"Hydralisk";"Larva";394;2
"Unit";"Hydralisk";"Larva";394;2
"Unit";"Hydralisk";"Larva";394;2
"Unit";"Hydralisk";"Larva";394;2
"Unit";"Hydralisk";"Larva";394;2
"Unit";"Hydralisk";"Larva";394;2
"Unit";"Hydralisk";"Larva";394;2
"Unit";"Hydralisk";"Larva";394;2
"Unit";"Hydralisk";"Larva";394;2
"Unit";"Hydralisk";"Larva";394;2
"Unit";"Hydralisk";"Larva";394;2
