"type";"unit_name";"on_building";"total_supply";"supply"
"Unit";"Overlord";"Larva";13;0
"Building";"Extractor";NA;18;0
"Unit";"Overlord";"Larva";21;0
"Building";"SpawningPool";NA;19;0
"Building";"Hatchery";NA;17;0
"Unit";"Zergling";"Larva";22;1
"Unit";"Zergling";"Larva";22;1
"Unit";"Queen";"Hatchery";22;2
"Unit";"Queen";"Hatchery";22;2
"Unit";"Zergling";"Larva";28;1
"Unit";"Zergling";"Larva";28;1
"Building";"CreepTumorQueen";NA;34;0
"Unit";"Overlord";"Larva";34;0
"Unit";"Zergling";"Larva";36;1
"Unit";"Zergling";"Larva";36;1
"Unit";"Queen";"Hatchery";34;2
"Unit";"Overlord";"Larva";36;0
"Building";"CreepTumor";NA;41;0
"Building";"CreepTumorQueen";NA;47;0
"Unit";"Overlord";"Larva";47;0
"Building";"Hatchery";NA;31;0
"Unit";"Overlord";"Larva";50;0
"Building";"CreepTumor";NA;50;0
"Building";"CreepTumor";NA;50;0
"Unit";"Queen";"Hatchery";49;2
"Building";"SporeCrawler";NA;50;0
"Building";"SporeCrawler";NA;50;0
"Building";"SporeCrawler";NA;50;0
"Building";"CreepTumorQueen";NA;57;0
"Building";"Extractor";NA;57;0
"Building";"Extractor";NA;57;0
"Building";"CreepTumor";NA;61;0
"Building";"CreepTumor";NA;61;0
"Building";"CreepTumor";NA;73;0
"Unit";"Overlord";"Larva";70;0
"Unit";"Overlord";"Larva";72;0
"Building";"CreepTumorQueen";NA;75;0
"Building";"Extractor";NA;75;0
"Building";"CreepTumor";NA;75;0
"Unit";"Zergling";"Larva";75;1
"Unit";"Zergling";"Larva";75;1
"Unit";"Zergling";"Larva";75;1
"Unit";"Zergling";"Larva";75;1
"Unit";"Zergling";"Larva";75;1
"Unit";"Zergling";"Larva";75;1
"Unit";"Zergling";"Larva";75;1
"Unit";"Zergling";"Larva";75;1
"Unit";"Zergling";"Larva";75;1
"Unit";"Zergling";"Larva";75;1
"Building";"CreepTumor";NA;75;0
"Unit";"Zergling";"Larva";75;1
"Unit";"Zergling";"Larva";75;1
"Unit";"Zergling";"Larva";75;1
"Unit";"Zergling";"Larva";75;1
"Building";"HydraliskDen";NA;75;0
"Unit";"Overlord";"Larva";76;0
"Unit";"Overlord";"Larva";78;0
"Building";"CreepTumorQueen";NA;91;0
"Unit";"Overlord";"Larva";81;0
"Unit";"Hydralisk";"Larva";95;2
"Unit";"Hydralisk";"Larva";95;2
"Unit";"Hydralisk";"Larva";95;2
"Unit";"Hydralisk";"Larva";95;2
"Unit";"Hydralisk";"Larva";95;2
"Unit";"Hydralisk";"Larva";95;2
"Unit";"Hydralisk";"Larva";95;2
"Unit";"Hydralisk";"Larva";95;2
"Unit";"Hydralisk";"Larva";95;2
"Unit";"Hydralisk";"Larva";95;2
"Unit";"Hydralisk";"Larva";95;2
"Unit";"Hydralisk";"Larva";95;2
"Unit";"Zergling";"Larva";95;1
"Unit";"Zergling";"Larva";95;1
"Unit";"Zergling";"Larva";95;1
"Unit";"Zergling";"Larva";95;1
"Unit";"Zergling";"Larva";95;1
"Unit";"Zergling";"Larva";95;1
"Unit";"Zergling";"Larva";95;1
"Unit";"Zergling";"Larva";95;1
"Building";"CreepTumor";NA;127;0
"Building";"CreepTumor";NA;127;0
"Building";"CreepTumor";NA;127;0
"Unit";"Overlord";"Larva";117;0
"Building";"CreepTumor";NA;127;0
"Building";"CreepTumor";NA;127;0
"Building";"CreepTumorQueen";NA;136;0
"Building";"Extractor";NA;136;0
"Building";"Extractor";NA;136;0
"Unit";"Overlord";"Larva";136;0
"Unit";"Overlord";"Larva";136;0
"Building";"EvolutionChamber";NA;136;0
"Building";"CreepTumor";NA;138;0
"Building";"CreepTumor";NA;140;0
"Unit";"Zergling";"Larva";141;1
"Unit";"Zergling";"Larva";141;1
"Unit";"Zergling";"Larva";142;1
"Unit";"Zergling";"Larva";142;1
"Unit";"Zergling";"Larva";142;1
"Unit";"Zergling";"Larva";142;1
"Unit";"Zergling";"Larva";142;1
"Unit";"Zergling";"Larva";142;1
"Unit";"Zergling";"Larva";142;1
"Unit";"Zergling";"Larva";142;1
"Unit";"Zergling";"Larva";142;1
"Unit";"Zergling";"Larva";142;1
"Unit";"Zergling";"Larva";142;1
"Unit";"Zergling";"Larva";142;1
"Unit";"Zergling";"Larva";142;1
"Unit";"Zergling";"Larva";142;1
"Unit";"Zergling";"Larva";142;1
"Unit";"Zergling";"Larva";142;1
"Building";"CreepTumor";NA;142;0
"Building";"CreepTumor";NA;142;0
"Building";"CreepTumor";NA;142;0
"Building";"CreepTumor";NA;142;0
"Unit";"Zergling";"Larva";142;1
"Unit";"Zergling";"Larva";142;1
"Unit";"Zergling";"Larva";142;1
"Unit";"Zergling";"Larva";142;1
"Upgrade";"EvolveMuscularAugments";"HydraliskDen";136;0
"Unit";"Overlord";"Larva";142;0
"Building";"CreepTumorQueen";NA;164;0
"Building";"CreepTumor";NA;164;0
"Unit";"Hydralisk";"Larva";162;2
"Building";"CreepTumor";NA;164;0
"Unit";"Hydralisk";"Larva";164;2
"Unit";"Hydralisk";"Larva";164;2
"Unit";"Hydralisk";"Larva";164;2
"Unit";"Hydralisk";"Larva";164;2
"Unit";"Hydralisk";"Larva";164;2
"Unit";"Hydralisk";"Larva";164;2
"Unit";"Hydralisk";"Larva";164;2
"Unit";"Hydralisk";"Larva";164;2
"Unit";"Hydralisk";"Larva";164;2
"Building";"CreepTumor";NA;164;0
"Unit";"Hydralisk";"Larva";164;2
"Unit";"Hydralisk";"Larva";164;2
"Unit";"Hydralisk";"Larva";164;2
"Building";"CreepTumor";NA;164;0
"Unit";"Hydralisk";"Larva";164;2
"Unit";"Overlord";"Larva";164;0
"Unit";"Hydralisk";"Larva";164;2
"Building";"InfestationPit";NA;164;0
"Unit";"Hydralisk";"Larva";164;2
"Unit";"Hydralisk";"Larva";182;2
"Unit";"Hydralisk";"Larva";182;2
"Unit";"Hydralisk";"Larva";182;2
"Unit";"Hydralisk";"Larva";182;2
"Building";"CreepTumorQueen";NA;196;0
"Unit";"Hydralisk";"Larva";190;2
"Building";"CreepTumor";NA;196;0
"Building";"CreepTumor";NA;196;0
"Building";"CreepTumor";NA;198;0
"Building";"CreepTumor";NA;198;0
"Building";"CreepTumor";NA;198;0
"Building";"CreepTumor";NA;198;0
"Building";"CreepTumor";NA;198;0
"Unit";"Zergling";"Larva";198;1
"Unit";"Zergling";"Larva";198;1
"Unit";"Zergling";"Larva";198;1
"Unit";"Zergling";"Larva";198;1
"Unit";"Zergling";"Larva";198;1
"Unit";"Zergling";"Larva";198;1
"Unit";"Zergling";"Larva";198;1
"Unit";"Zergling";"Larva";198;1
"Unit";"Zergling";"Larva";198;1
"Unit";"Zergling";"Larva";198;1
"Unit";"Zergling";"Larva";198;1
"Unit";"Zergling";"Larva";198;1
"Unit";"Zergling";"Larva";198;1
"Unit";"Zergling";"Larva";198;1
"Unit";"Hydralisk";"Larva";196;2
"Unit";"Hydralisk";"Larva";196;2
"Upgrade";"EvolveGroovedSpines";"HydraliskDen";182;0
"Unit";"Overlord";"Larva";206;0
"Building";"CreepTumor";NA;224;0
"Building";"CreepTumor";NA;224;0
"Building";"Hatchery";NA;164;0
"Unit";"Hydralisk";"Larva";206;2
"Unit";"Hydralisk";"Larva";206;2
"Unit";"Hydralisk";"Larva";206;2
"Unit";"Hydralisk";"Larva";206;2
"Unit";"Overlord";"Larva";224;0
"Unit";"Overlord";"Larva";224;0
"Unit";"Overlord";"Larva";224;0
"Unit";"Overlord";"Larva";224;0
"Upgrade";"ZergMissileWeaponsLevel1";"EvolutionChamber";164;0
"Unit";"Zergling";"Larva";225;1
"Unit";"Zergling";"Larva";225;1
"Unit";"Zergling";"Larva";225;1
"Unit";"Zergling";"Larva";225;1
"Unit";"Zergling";"Larva";225;1
"Unit";"Zergling";"Larva";225;1
"Unit";"Zergling";"Larva";225;1
"Unit";"Zergling";"Larva";225;1
"Unit";"Zergling";"Larva";225;1
"Unit";"Zergling";"Larva";225;1
"Unit";"Zergling";"Larva";225;1
"Unit";"Zergling";"Larva";225;1
"Unit";"Zergling";"Larva";225;1
"Unit";"Zergling";"Larva";225;1
"Building";"Extractor";NA;225;0
"Building";"Extractor";NA;225;0
