"type";"unit_name";"on_building";"total_supply";"supply"
"Unit";"Overlord";"Larva";12;0
"Building";"SpawningPool";NA;18;0
"Building";"Hatchery";NA;17;0
"Unit";"Zergling";"Larva";21;1
"Unit";"Zergling";"Larva";21;1
"Unit";"Zergling";"Larva";21;1
"Unit";"Zergling";"Larva";21;1
"Unit";"Zergling";"Larva";21;1
"Unit";"Zergling";"Larva";21;1
"Unit";"Zergling";"Larva";21;1
"Unit";"Zergling";"Larva";21;1
"Unit";"Queen";"Hatchery";21;2
"Unit";"Overlord";"Larva";27;0
"Unit";"Queen";"Hatchery";21;2
"Unit";"Zergling";"Larva";27;1
"Unit";"Zergling";"Larva";27;1
"Unit";"Zergling";"Larva";27;1
"Unit";"Zergling";"Larva";27;1
"Building";"Hatchery";NA;21;0
"Unit";"Zergling";"Larva";37;1
"Unit";"Zergling";"Larva";37;1
"Unit";"Zergling";"Larva";37;1
"Unit";"Zergling";"Larva";37;1
"Unit";"Zergling";"Larva";37;1
"Unit";"Zergling";"Larva";37;1
"Unit";"Zergling";"Larva";37;1
"Unit";"Zergling";"Larva";37;1
"Unit";"Zergling";"Larva";37;1
"Unit";"Zergling";"Larva";37;1
"Unit";"Zergling";"Larva";37;1
"Unit";"Zergling";"Larva";37;1
"Unit";"Zergling";"Larva";49;1
"Unit";"Zergling";"Larva";49;1
"Unit";"Zergling";"Larva";49;1
"Unit";"Zergling";"Larva";49;1
"Unit";"Zergling";"Larva";49;1
"Unit";"Zergling";"Larva";49;1
"Unit";"Zergling";"Larva";49;1
"Unit";"Zergling";"Larva";49;1
"Unit";"Queen";"Hatchery";37;2
"Unit";"Zergling";"Larva";58;1
"Unit";"Zergling";"Larva";58;1
"Unit";"Zergling";"Larva";58;1
"Unit";"Zergling";"Larva";58;1
"Unit";"Zergling";"Larva";58;1
"Unit";"Zergling";"Larva";58;1
"Building";"CreepTumorQueen";NA;60;0
"Unit";"Zergling";"Larva";60;1
"Unit";"Zergling";"Larva";60;1
"Unit";"Zergling";"Larva";60;1
"Unit";"Zergling";"Larva";60;1
"Unit";"Zergling";"Larva";60;1
"Unit";"Zergling";"Larva";60;1
"Unit";"Zergling";"Larva";60;1
"Unit";"Zergling";"Larva";60;1
"Building";"SpineCrawler";NA;58;0
"Building";"CreepTumor";NA;74;0
"Unit";"Zergling";"Larva";74;1
"Unit";"Zergling";"Larva";74;1
"Unit";"Zergling";"Larva";74;1
"Unit";"Zergling";"Larva";74;1
"Unit";"Zergling";"Larva";74;1
"Unit";"Zergling";"Larva";74;1
"Unit";"Zergling";"Larva";74;1
"Unit";"Zergling";"Larva";74;1
"Building";"CreepTumorQueen";NA;74;0
"Unit";"Zergling";"Larva";74;1
"Unit";"Zergling";"Larva";74;1
"Unit";"Zergling";"Larva";74;1
"Unit";"Zergling";"Larva";74;1
"Unit";"Queen";"Hatchery";74;2
"Building";"SporeCrawler";NA;82;0
"Unit";"Zergling";"Larva";82;1
"Unit";"Zergling";"Larva";82;1
"Unit";"Queen";"Hatchery";88;2
"Building";"SporeCrawler";NA;94;0
"Unit";"Overlord";"Larva";97;0
"Unit";"Overlord";"Larva";97;0
"Building";"CreepTumor";NA;97;0
"Building";"SporeCrawler";NA;97;0
"Building";"SporeCrawler";NA;97;0
"Building";"CreepTumor";NA;99;0
"Building";"CreepTumorQueen";NA;99;0
"Building";"CreepTumorQueen";NA;99;0
"Unit";"Queen";"Hatchery";99;2
"Unit";"Queen";"Hatchery";99;2
"Building";"SporeCrawler";NA;114;0
"Unit";"Overlord";"Larva";114;0
"Unit";"Overlord";"Larva";114;0
"Building";"CreepTumorQueen";NA;114;0
"Building";"CreepTumor";NA;115;0
"Unit";"Queen";"Hatchery";114;2
"Building";"CreepTumor";NA;115;0
"Unit";"Queen";"Hatchery";114;2
"Building";"CreepTumor";NA;115;0
"Building";"Extractor";NA;121;0
"Building";"Extractor";NA;121;0
"Building";"CreepTumor";NA;127;0
"Building";"CreepTumorQueen";NA;128;0
"Building";"Extractor";NA;127;0
"Building";"EvolutionChamber";NA;128;0
"Unit";"Overlord";"Larva";135;0
"Unit";"Overlord";"Larva";135;0
"Unit";"Overlord";"Larva";135;0
"Building";"EvolutionChamber";NA;131;0
"Building";"CreepTumor";NA;137;0
"Building";"CreepTumor";NA;137;0
"Building";"CreepTumorQueen";NA;137;0
"Building";"CreepTumor";NA;137;0
"Building";"CreepTumor";NA;137;0
"Building";"Hatchery";NA;125;0
"Unit";"Queen";"Hatchery";131;2
"Building";"CreepTumor";NA;137;0
"Building";"Hatchery";NA;128;0
"Building";"CreepTumor";NA;139;0
"Building";"CreepTumor";NA;139;0
"Building";"CreepTumor";NA;139;0
"Building";"SporeCrawler";NA;139;0
"Unit";"Zergling";"Larva";139;1
"Unit";"Zergling";"Larva";139;1
"Unit";"Zergling";"Larva";139;1
"Unit";"Zergling";"Larva";139;1
"Unit";"Zergling";"Larva";139;1
"Unit";"Zergling";"Larva";139;1
"Unit";"Zergling";"Larva";139;1
"Unit";"Zergling";"Larva";139;1
"Unit";"Zergling";"Larva";139;1
"Unit";"Zergling";"Larva";139;1
"Unit";"Zergling";"Larva";139;1
"Unit";"Zergling";"Larva";139;1
"Unit";"Zergling";"Larva";139;1
"Unit";"Zergling";"Larva";139;1
"Unit";"Zergling";"Larva";139;1
"Unit";"Zergling";"Larva";139;1
"Unit";"Zergling";"Larva";139;1
"Unit";"Zergling";"Larva";139;1
"Unit";"Zergling";"Larva";139;1
"Unit";"Zergling";"Larva";139;1
"Unit";"Zergling";"Larva";139;1
"Unit";"Zergling";"Larva";139;1
"Unit";"Queen";"Hatchery";139;2
"Unit";"Queen";"Hatchery";139;2
"Building";"CreepTumorQueen";NA;139;0
"Unit";"Queen";"Hatchery";139;2
"Building";"CreepTumor";NA;139;0
"Building";"CreepTumor";NA;145;0
"Building";"CreepTumor";NA;155;0
"Unit";"Zergling";"Larva";139;1
"Unit";"Zergling";"Larva";139;1
"Unit";"Zergling";"Larva";139;1
"Unit";"Zergling";"Larva";139;1
"Unit";"Zergling";"Larva";139;1
"Unit";"Zergling";"Larva";139;1
"Unit";"Zergling";"Larva";139;1
"Unit";"Zergling";"Larva";139;1
"Unit";"Zergling";"Larva";139;1
"Unit";"Zergling";"Larva";139;1
"Unit";"Zergling";"Larva";139;1
"Unit";"Zergling";"Larva";139;1
"Building";"CreepTumor";NA;167;0
"Unit";"Zergling";"Larva";167;1
"Unit";"Zergling";"Larva";167;1
"Unit";"Zergling";"Larva";167;1
"Unit";"Zergling";"Larva";167;1
"Unit";"Zergling";"Larva";167;1
"Unit";"Zergling";"Larva";167;1
"Unit";"Zergling";"Larva";167;1
"Unit";"Zergling";"Larva";167;1
"Unit";"Zergling";"Larva";167;1
"Unit";"Zergling";"Larva";167;1
"Unit";"Zergling";"Larva";167;1
"Unit";"Zergling";"Larva";167;1
"Unit";"Zergling";"Larva";179;1
"Unit";"Zergling";"Larva";179;1
"Unit";"Zergling";"Larva";179;1
"Unit";"Zergling";"Larva";179;1
"Upgrade";"ZergMissileWeaponsLevel1";"EvolutionChamber";139;0
"Unit";"Queen";"Hatchery";167;2
"Unit";"Queen";"Hatchery";167;2
"Unit";"Zergling";"Larva";195;1
"Unit";"Zergling";"Larva";195;1
"Unit";"Zergling";"Larva";195;1
"Unit";"Zergling";"Larva";195;1
"Unit";"Zergling";"Larva";195;1
"Unit";"Zergling";"Larva";195;1
"Unit";"Zergling";"Larva";195;1
"Unit";"Zergling";"Larva";195;1
"Unit";"Zergling";"Larva";195;1
"Unit";"Zergling";"Larva";195;1
"Upgrade";"ZergMeleeWeaponsLevel1";"EvolutionChamber";139;0
"Unit";"Overlord";"Larva";199;0
"Unit";"Overlord";"Larva";199;0
"Unit";"Overlord";"Larva";199;0
"Unit";"Overlord";"Larva";199;0
"Unit";"Zergling";"Larva";209;1
"Unit";"Zergling";"Larva";209;1
"Unit";"Zergling";"Larva";209;1
"Unit";"Zergling";"Larva";209;1
"Unit";"Zergling";"Larva";209;1
"Unit";"Zergling";"Larva";209;1
"Unit";"Zergling";"Larva";209;1
"Unit";"Zergling";"Larva";209;1
"Unit";"Zergling";"Larva";209;1
"Unit";"Zergling";"Larva";209;1
"Unit";"Zergling";"Larva";209;1
"Unit";"Zergling";"Larva";209;1
"Unit";"Zergling";"Larva";209;1
"Unit";"Zergling";"Larva";209;1
"Unit";"Zergling";"Larva";209;1
"Unit";"Zergling";"Larva";209;1
"Unit";"Zergling";"Larva";209;1
"Unit";"Zergling";"Larva";209;1
"Unit";"Zergling";"Larva";209;1
"Unit";"Zergling";"Larva";209;1
"Unit";"Zergling";"Larva";209;1
"Unit";"Zergling";"Larva";209;1
