"type";"unit_name";"on_building";"total_supply";"supply"
"Unit";"Overlord";"Larva";12;0
"Building";"SpawningPool";NA;19;0
"Building";"Hatchery";NA;16;0
"Unit";"Zergling";"Larva";22;1
"Unit";"Zergling";"Larva";22;1
"Unit";"Zergling";"Larva";22;1
"Unit";"Zergling";"Larva";22;1
"Unit";"Zergling";"Larva";22;1
"Unit";"Zergling";"Larva";22;1
"Building";"SpineCrawler";NA;22;0
"Building";"SpineCrawler";NA;22;0
"Building";"SpineCrawler";NA;22;0
"Unit";"Zergling";"Larva";22;1
"Unit";"Zergling";"Larva";22;1
"Unit";"Queen";"Hatchery";22;2
"Building";"SpineCrawler";NA;22;0
"Unit";"Zergling";"Larva";22;1
"Unit";"Zergling";"Larva";22;1
"Unit";"Queen";"Hatchery";22;2
"Unit";"Zergling";"Larva";28;1
"Unit";"Zergling";"Larva";28;1
"Unit";"Zergling";"Larva";39;1
"Unit";"Zergling";"Larva";39;1
"Unit";"Zergling";"Larva";39;1
"Unit";"Zergling";"Larva";39;1
"Unit";"Zergling";"Larva";39;1
"Unit";"Zergling";"Larva";39;1
"Unit";"Zergling";"Larva";39;1
"Unit";"Zergling";"Larva";39;1
"Unit";"Zergling";"Larva";39;1
"Unit";"Zergling";"Larva";39;1
"Unit";"Zergling";"Larva";39;1
"Unit";"Zergling";"Larva";39;1
"Unit";"Zergling";"Larva";49;1
"Unit";"Zergling";"Larva";49;1
"Unit";"Zergling";"Larva";49;1
"Unit";"Zergling";"Larva";49;1
"Building";"CreepTumorQueen";NA;51;0
"Unit";"Overlord";"Larva";55;0
"Unit";"Overlord";"Larva";55;0
"Building";"CreepTumor";NA;55;0
"Building";"CreepTumorQueen";NA;58;0
"Building";"CreepTumorQueen";NA;58;0
"Building";"Hatchery";NA;55;0
"Unit";"Zergling";"Larva";60;1
"Unit";"Zergling";"Larva";60;1
"Unit";"Queen";"Hatchery";59;2
"Unit";"Zergling";"Larva";60;1
"Unit";"Zergling";"Larva";60;1
"Unit";"Zergling";"Larva";60;1
"Unit";"Zergling";"Larva";60;1
"Building";"SpineCrawler";NA;60;0
"Unit";"Queen";"Hatchery";64;2
"Building";"CreepTumor";NA;75;0
"Building";"CreepTumor";NA;75;0
"Building";"CreepTumor";NA;75;0
"Unit";"Queen";"Hatchery";72;2
"Building";"RoachWarren";NA;73;0
"Building";"CreepTumorQueen";NA;86;0
"Unit";"Overlord";"Larva";86;0
"Building";"Extractor";NA;86;0
"Building";"Extractor";NA;86;0
"Building";"CreepTumor";NA;86;0
"Building";"CreepTumor";NA;86;0
"Building";"CreepTumor";NA;86;0
"Unit";"Overlord";"Larva";86;0
"Unit";"Overlord";"Larva";86;0
"Unit";"Overlord";"Larva";86;0
"Unit";"Overlord";"Larva";86;0
"Unit";"Queen";"Hatchery";86;2
"Unit";"Zergling";"Larva";86;1
"Unit";"Zergling";"Larva";86;1
"Unit";"Zergling";"Larva";86;1
"Unit";"Zergling";"Larva";86;1
"Unit";"Zergling";"Larva";86;1
"Unit";"Zergling";"Larva";86;1
"Unit";"Zergling";"Larva";86;1
"Unit";"Zergling";"Larva";86;1
"Unit";"Zergling";"Larva";86;1
"Unit";"Zergling";"Larva";86;1
"Unit";"Roach";"Larva";98;2
"Unit";"Roach";"Larva";98;2
"Unit";"Roach";"Larva";98;2
"Unit";"Roach";"Larva";98;2
"Unit";"Roach";"Larva";98;2
"Unit";"Roach";"Larva";98;2
"Unit";"Roach";"Larva";98;2
"Unit";"Roach";"Larva";98;2
"Unit";"Zergling";"Larva";106;1
"Unit";"Zergling";"Larva";106;1
"Unit";"Zergling";"Larva";106;1
"Unit";"Zergling";"Larva";106;1
"Unit";"Zergling";"Larva";106;1
"Unit";"Zergling";"Larva";106;1
"Unit";"Zergling";"Larva";106;1
"Unit";"Zergling";"Larva";106;1
"Unit";"Roach";"Larva";106;2
"Unit";"Roach";"Larva";106;2
"Unit";"Roach";"Larva";106;2
"Unit";"Zergling";"Larva";106;1
"Unit";"Zergling";"Larva";106;1
"Unit";"Zergling";"Larva";122;1
"Unit";"Zergling";"Larva";122;1
"Unit";"Zergling";"Larva";122;1
"Unit";"Zergling";"Larva";122;1
"Unit";"Roach";"Larva";130;2
"Unit";"Roach";"Larva";130;2
"Unit";"Queen";"Hatchery";122;2
"Unit";"Queen";"Hatchery";122;2
"Unit";"Overlord";"Larva";134;0
"Unit";"Overlord";"Larva";134;0
"Unit";"Roach";"Larva";136;2
"Unit";"Roach";"Larva";136;2
"Unit";"Roach";"Larva";142;2
"Unit";"Zergling";"Larva";142;1
"Unit";"Zergling";"Larva";142;1
"Unit";"Zergling";"Larva";146;1
"Unit";"Zergling";"Larva";146;1
"Unit";"Zergling";"Larva";146;1
"Unit";"Zergling";"Larva";146;1
"Unit";"Roach";"Larva";150;2
"Building";"Extractor";NA;150;0
"Unit";"Queen";"Hatchery";146;2
"Unit";"Queen";"Hatchery";146;2
"Unit";"Roach";"Larva";154;2
"Unit";"Roach";"Larva";154;2
"Unit";"Roach";"Larva";154;2
"Unit";"Roach";"Larva";154;2
"Unit";"Roach";"Larva";154;2
"Unit";"Roach";"Larva";154;2
"Unit";"Roach";"Larva";172;2
"Unit";"Roach";"Larva";172;2
"Unit";"Roach";"Larva";172;2
"Building";"CreepTumorQueen";NA;172;0
"Building";"CreepTumorQueen";NA;172;0
"Building";"CreepTumor";NA;178;0
"Building";"CreepTumor";NA;178;0
"Building";"Extractor";NA;172;0
"Building";"CreepTumor";NA;182;0
"Building";"CreepTumorQueen";NA;182;0
"Unit";"Overlord";"Larva";182;0
"Unit";"Overlord";"Larva";182;0
"Unit";"Overlord";"Larva";182;0
"Unit";"Overlord";"Larva";182;0
"Building";"CreepTumor";NA;185;0
"Unit";"Overlord";"Larva";185;0
"Unit";"Overlord";"Larva";185;0
"Building";"CreepTumor";NA;185;0
"Building";"CreepTumor";NA;185;0
"Building";"CreepTumorQueen";NA;185;0
"Building";"CreepTumor";NA;185;0
"Building";"CreepTumorQueen";NA;185;0
"Building";"EvolutionChamber";NA;185;0
"Building";"SporeCrawler";NA;185;0
"Building";"SporeCrawler";NA;185;0
"Building";"CreepTumorQueen";NA;188;0
"Building";"CreepTumor";NA;188;0
"Building";"CreepTumor";NA;188;0
"Building";"CreepTumor";NA;188;0
"Building";"CreepTumorQueen";NA;191;0
"Building";"HydraliskDen";NA;191;0
"Building";"CreepTumor";NA;193;0
"Building";"Hatchery";NA;185;0
"Building";"CreepTumor";NA;195;0
"Building";"CreepTumor";NA;195;0
"Building";"CreepTumor";NA;195;0
"Building";"CreepTumor";NA;195;0
"Building";"CreepTumorQueen";NA;196;0
"Building";"CreepTumor";NA;196;0
"Building";"CreepTumorQueen";NA;196;0
"Building";"CreepTumor";NA;196;0
"Building";"CreepTumor";NA;196;0
"Unit";"Hydralisk";"Larva";196;2
"Unit";"Hydralisk";"Larva";196;2
"Unit";"Hydralisk";"Larva";196;2
"Building";"CreepTumor";NA;204;0
"Unit";"Overlord";"Larva";204;0
"Upgrade";"GlialReconstitution";"RoachWarren";195;0
"Building";"CreepTumor";NA;204;0
"Building";"CreepTumor";NA;204;0
"Building";"CreepTumor";NA;204;0
"Building";"CreepTumor";NA;204;0
"Unit";"Hydralisk";"Larva";204;2
"Unit";"Hydralisk";"Larva";204;2
"Unit";"Hydralisk";"Larva";204;2
"Building";"CreepTumor";NA;204;0
"Building";"CreepTumor";NA;204;0
"Building";"CreepTumorQueen";NA;210;0
"Building";"CreepTumor";NA;210;0
"Upgrade";"EvolveGroovedSpines";"HydraliskDen";196;0
"Upgrade";"ZergMissileWeaponsLevel1";"EvolutionChamber";195;0
"Building";"CreepTumor";NA;210;0
"Unit";"Hydralisk";"Larva";210;2
"Unit";"Hydralisk";"Larva";210;2
"Unit";"Hydralisk";"Larva";210;2
"Unit";"Hydralisk";"Larva";210;2
"Unit";"Hydralisk";"Larva";210;2
"Unit";"Hydralisk";"Larva";210;2
"Unit";"Overlord";"Larva";210;0
"Unit";"Overlord";"Larva";210;0
