"type";"unit_name";"on_building";"total_supply";"supply"
"Unit";"Overlord";"Larva";12;0
"Building";"Extractor";NA;17;0
"Unit";"Overlord";"Larva";21;0
"Building";"Hatchery";NA;16;0
"Building";"SpawningPool";NA;19;0
"Unit";"Zergling";"Larva";23;1
"Unit";"Zergling";"Larva";23;1
"Unit";"Zergling";"Larva";23;1
"Unit";"Zergling";"Larva";23;1
"Unit";"Queen";"Hatchery";23;2
"Unit";"Queen";"Hatchery";23;2
"Building";"CreepTumorQueen";NA;35;0
"Unit";"Overlord";"Larva";36;0
"Unit";"Overlord";"Larva";39;0
"Building";"CreepTumorQueen";NA;40;0
"Building";"CreepTumor";NA;40;0
"Unit";"Queen";"Hatchery";37;2
"Building";"Hatchery";NA;31;0
"Building";"CreepTumor";NA;50;0
"Building";"CreepTumorQueen";NA;50;0
"Building";"SporeCrawler";NA;50;0
"Building";"SporeCrawler";NA;50;0
"Unit";"Zergling";"Larva";51;1
"Unit";"Zergling";"Larva";51;1
"Unit";"Zergling";"Larva";51;1
"Unit";"Zergling";"Larva";51;1
"Unit";"Zergling";"Larva";51;1
"Unit";"Zergling";"Larva";51;1
"Unit";"Zergling";"Larva";51;1
"Unit";"Zergling";"Larva";51;1
"Unit";"Zergling";"Larva";51;1
"Unit";"Zergling";"Larva";51;1
"Unit";"Zergling";"Larva";51;1
"Unit";"Zergling";"Larva";51;1
"Building";"SporeCrawler";NA;52;0
"Unit";"Overlord";"Larva";52;0
"Building";"CreepTumor";NA;60;0
"Building";"CreepTumor";NA;66;0
"Building";"CreepTumorQueen";NA;66;0
"Unit";"Zergling";"Larva";66;1
"Unit";"Zergling";"Larva";66;1
"Unit";"Zergling";"Larva";66;1
"Unit";"Zergling";"Larva";66;1
"Unit";"Zergling";"Larva";66;1
"Unit";"Zergling";"Larva";66;1
"Unit";"Zergling";"Larva";66;1
"Unit";"Zergling";"Larva";66;1
"Unit";"Zergling";"Larva";66;1
"Unit";"Zergling";"Larva";66;1
"Unit";"Zergling";"Larva";66;1
"Unit";"Zergling";"Larva";66;1
"Unit";"Zergling";"Larva";66;1
"Unit";"Zergling";"Larva";66;1
"Unit";"Queen";"Hatchery";52;2
"Building";"Extractor";NA;66;0
"Building";"Extractor";NA;66;0
"Unit";"Overlord";"Larva";84;0
"Unit";"Overlord";"Larva";84;0
"Building";"CreepTumor";NA;86;0
"Building";"EvolutionChamber";NA;66;0
"Building";"CreepTumorQueen";NA;86;0
"Building";"CreepTumor";NA;86;0
"Building";"CreepTumor";NA;86;0
"Unit";"Overlord";"Larva";86;0
"Unit";"Overlord";"Larva";86;0
"Building";"BanelingNest";NA;80;0
"Unit";"Overlord";"Larva";86;0
"Unit";"Overlord";"Larva";86;0
"Building";"CreepTumor";NA;95;0
"Building";"CreepTumorQueen";NA;100;0
"Building";"HydraliskDen";NA;95;0
"Building";"CreepTumorQueen";NA;107;0
"Building";"CreepTumor";NA;107;0
"Building";"CreepTumor";NA;107;0
"Building";"CreepTumor";NA;108;0
"Unit";"Zergling";"Larva";108;1
"Unit";"Zergling";"Larva";108;1
"Unit";"Zergling";"Larva";108;1
"Unit";"Zergling";"Larva";108;1
"Unit";"Zergling";"Larva";108;1
"Unit";"Zergling";"Larva";108;1
"Unit";"Zergling";"Larva";108;1
"Unit";"Zergling";"Larva";108;1
"Unit";"Zergling";"Larva";108;1
"Unit";"Zergling";"Larva";108;1
"Unit";"Zergling";"Larva";108;1
"Unit";"Zergling";"Larva";108;1
"Unit";"Zergling";"Larva";108;1
"Unit";"Zergling";"Larva";108;1
"Unit";"Zergling";"Larva";108;1
"Unit";"Zergling";"Larva";108;1
"Unit";"Zergling";"Larva";108;1
"Unit";"Zergling";"Larva";108;1
"Unit";"Zergling";"Larva";108;1
"Unit";"Zergling";"Larva";108;1
"Building";"CreepTumor";NA;108;0
"Building";"CreepTumor";NA;108;0
"Building";"Extractor";NA;108;0
"Building";"Extractor";NA;128;0
"Building";"CreepTumorQueen";NA;131;0
"Unit";"Overlord";"Larva";131;0
"Unit";"Overlord";"Larva";131;0
"Unit";"Overlord";"Larva";131;0
"Unit";"Hydralisk";"Larva";131;2
"Unit";"Hydralisk";"Larva";131;2
"Unit";"Hydralisk";"Larva";131;2
"Unit";"Hydralisk";"Larva";131;2
"Building";"Extractor";NA;131;0
"Building";"CreepTumor";NA;131;0
"Building";"CreepTumor";NA;139;0
"Building";"CreepTumor";NA;139;0
"Upgrade";"ZergMissileWeaponsLevel1";"EvolutionChamber";100;0
"Unit";"Hydralisk";"Larva";131;2
"Unit";"Hydralisk";"Larva";131;2
"Unit";"Hydralisk";"Larva";131;2
"Upgrade";"EvolveGroovedSpines";"HydraliskDen";128;0
"Unit";"Zergling";"Larva";139;1
"Unit";"Zergling";"Larva";139;1
"Unit";"Zergling";"Larva";139;1
"Unit";"Zergling";"Larva";139;1
"Unit";"Zergling";"Larva";139;1
"Unit";"Zergling";"Larva";139;1
"Unit";"Zergling";"Larva";139;1
"Unit";"Zergling";"Larva";139;1
"Unit";"Zergling";"Larva";139;1
"Unit";"Zergling";"Larva";139;1
"Unit";"Zergling";"Larva";139;1
"Unit";"Zergling";"Larva";139;1
"Unit";"Zergling";"Larva";139;1
"Unit";"Zergling";"Larva";139;1
"Unit";"Zergling";"Larva";139;1
"Unit";"Zergling";"Larva";139;1
"Unit";"Hydralisk";"Larva";139;2
"Unit";"Hydralisk";"Larva";139;2
"Unit";"Hydralisk";"Larva";139;2
"Unit";"Baneling";"Zergling";145;0
"Unit";"Baneling";"Zergling";145;0
"Unit";"Baneling";"Zergling";145;0
"Unit";"Baneling";"Zergling";145;0
"Building";"CreepTumor";NA;161;0
"Building";"CreepTumor";NA;170;0
"Building";"CreepTumor";NA;170;0
"Building";"CreepTumorQueen";NA;170;0
"Building";"CreepTumor";NA;170;0
"Building";"Hatchery";NA;131;0
"Building";"CreepTumor";NA;170;0
"Unit";"Zergling";"Larva";162;1
"Unit";"Zergling";"Larva";162;1
"Building";"CreepTumorQueen";NA;170;0
"Building";"CreepTumor";NA;170;0
"Unit";"Zergling";"Larva";162;1
"Unit";"Zergling";"Larva";162;1
"Unit";"Baneling";"Zergling";170;0
"Unit";"Baneling";"Zergling";170;0
"Unit";"Baneling";"Zergling";170;0
"Unit";"Baneling";"Zergling";170;0
"Unit";"Baneling";"Zergling";170;0
"Unit";"Baneling";"Zergling";170;0
"Unit";"Baneling";"Zergling";170;0
"Unit";"Baneling";"Zergling";170;0
"Unit";"Baneling";"Zergling";170;0
"Building";"SporeCrawler";NA;170;0
"Unit";"Hydralisk";"Larva";162;2
"Building";"SporeCrawler";NA;170;0
"Unit";"Hydralisk";"Larva";176;2
"Unit";"Hydralisk";"Larva";176;2
"Unit";"Hydralisk";"Larva";176;2
"Unit";"Zergling";"Larva";182;1
"Unit";"Zergling";"Larva";182;1
"Unit";"Zergling";"Larva";182;1
"Unit";"Zergling";"Larva";182;1
"Unit";"Zergling";"Larva";182;1
"Unit";"Zergling";"Larva";182;1
"Unit";"Zergling";"Larva";182;1
"Unit";"Zergling";"Larva";182;1
"Unit";"Zergling";"Larva";182;1
"Unit";"Zergling";"Larva";182;1
"Unit";"Zergling";"Larva";182;1
"Unit";"Zergling";"Larva";182;1
"Unit";"Zergling";"Larva";182;1
"Unit";"Zergling";"Larva";182;1
"Unit";"Hydralisk";"Larva";182;2
"Unit";"Hydralisk";"Larva";182;2
"Upgrade";"EvolveMuscularAugments";"HydraliskDen";172;0
"Unit";"Zergling";"Larva";212;1
"Unit";"Zergling";"Larva";212;1
"Unit";"Zergling";"Larva";212;1
"Unit";"Zergling";"Larva";212;1
"Unit";"Zergling";"Larva";212;1
"Unit";"Zergling";"Larva";212;1
"Unit";"Zergling";"Larva";212;1
"Unit";"Zergling";"Larva";212;1
"Unit";"Baneling";"Zergling";215;0
"Unit";"Baneling";"Zergling";215;0
"Unit";"Baneling";"Zergling";215;0
"Unit";"Baneling";"Zergling";215;0
"Unit";"Baneling";"Zergling";215;0
"Unit";"Baneling";"Zergling";215;0
"Unit";"Baneling";"Zergling";215;0
"Unit";"Baneling";"Zergling";215;0
"Unit";"Baneling";"Zergling";215;0
"Unit";"Baneling";"Zergling";215;0
"Unit";"Baneling";"Zergling";215;0
"Unit";"Baneling";"Zergling";215;0
"Unit";"Baneling";"Zergling";215;0
"Unit";"Baneling";"Zergling";215;0
"Unit";"Hydralisk";"Larva";223;2
"Unit";"Queen";"Hatchery";223;2
"Upgrade";"ZergMissileWeaponsLevel2";"EvolutionChamber";182;0
"Unit";"Zergling";"Larva";229;1
"Unit";"Zergling";"Larva";229;1
"Unit";"Hydralisk";"Larva";229;2
"Unit";"Zergling";"Larva";229;1
"Unit";"Zergling";"Larva";229;1
"Unit";"Zergling";"Larva";229;1
"Unit";"Zergling";"Larva";229;1
"Unit";"Hydralisk";"Larva";229;2
"Unit";"Hydralisk";"Larva";229;2
"Unit";"Hydralisk";"Larva";229;2
"Unit";"Hydralisk";"Larva";229;2
"Unit";"Hydralisk";"Larva";229;2
"Unit";"Hydralisk";"Larva";229;2
"Unit";"Hydralisk";"Larva";229;2
"Unit";"Hydralisk";"Larva";229;2
"Unit";"Hydralisk";"Larva";229;2
"Unit";"Hydralisk";"Larva";229;2
"Unit";"Zergling";"Larva";231;1
"Unit";"Zergling";"Larva";231;1
"Unit";"Zergling";"Larva";231;1
"Unit";"Zergling";"Larva";231;1
"Unit";"Zergling";"Larva";231;1
"Unit";"Zergling";"Larva";231;1
"Unit";"Zergling";"Larva";231;1
"Unit";"Zergling";"Larva";231;1
"Unit";"Baneling";"Zergling";259;0
"Unit";"Baneling";"Zergling";259;0
"Unit";"Baneling";"Zergling";259;0
"Unit";"Baneling";"Zergling";259;0
"Unit";"Baneling";"Zergling";259;0
"Unit";"Queen";"Hatchery";231;2
"Building";"CreepTumor";NA;271;0
"Unit";"Baneling";"Zergling";271;0
"Unit";"Baneling";"Zergling";271;0
"Unit";"Baneling";"Zergling";271;0
"Unit";"Queen";"Hatchery";231;2
"Unit";"Baneling";"Zergling";271;0
"Building";"CreepTumor";NA;271;0
"Building";"CreepTumor";NA;271;0
"Building";"CreepTumor";NA;274;0
"Building";"CreepTumorQueen";NA;282;0
"Building";"CreepTumorQueen";NA;282;0
"Building";"CreepTumorQueen";NA;282;0
"Building";"CreepTumorQueen";NA;289;0
"Building";"CreepTumorQueen";NA;291;0
"Unit";"Hydralisk";"Larva";292;2
"Unit";"Hydralisk";"Larva";292;2
"Unit";"Zergling";"Larva";292;1
"Unit";"Zergling";"Larva";292;1
"Unit";"Zergling";"Larva";292;1
"Unit";"Zergling";"Larva";292;1
"Unit";"Zergling";"Larva";292;1
"Unit";"Zergling";"Larva";292;1
"Unit";"Zergling";"Larva";292;1
"Unit";"Zergling";"Larva";292;1
"Unit";"Zergling";"Larva";292;1
"Unit";"Zergling";"Larva";292;1
"Unit";"Zergling";"Larva";292;1
"Unit";"Zergling";"Larva";292;1
"Unit";"Zergling";"Larva";292;1
"Unit";"Zergling";"Larva";292;1
"Unit";"Zergling";"Larva";292;1
"Unit";"Zergling";"Larva";292;1
"Unit";"Hydralisk";"Larva";292;2
"Unit";"Hydralisk";"Larva";292;2
"Building";"Extractor";NA;292;0
"Building";"Extractor";NA;292;0
"Unit";"Zergling";"Larva";296;1
"Unit";"Zergling";"Larva";296;1
"Unit";"Zergling";"Larva";296;1
"Unit";"Zergling";"Larva";296;1
"Building";"LurkerDenMP";NA;259;0
"Unit";"Baneling";"Zergling";312;0
"Unit";"Hydralisk";"Larva";296;2
"Unit";"Baneling";"Zergling";312;0
"Unit";"Hydralisk";"Larva";296;2
"Unit";"Hydralisk";"Larva";296;2
"Unit";"Hydralisk";"Larva";296;2
"Unit";"Hydralisk";"Larva";296;2
"Unit";"Hydralisk";"Larva";296;2
"Unit";"Hydralisk";"Larva";296;2
"Unit";"Baneling";"Zergling";312;0
"Unit";"Baneling";"Zergling";312;0
"Unit";"Baneling";"Zergling";312;0
"Unit";"Baneling";"Zergling";312;0
"Unit";"Baneling";"Zergling";312;0
"Unit";"Baneling";"Zergling";312;0
"Building";"Hatchery";NA;277;0
"Building";"CreepTumor";NA;320;0
"Building";"CreepTumor";NA;320;0
"Building";"CreepTumor";NA;320;0
"Building";"CreepTumor";NA;320;0
"Unit";"Zergling";"Larva";320;1
"Unit";"Zergling";"Larva";320;1
"Unit";"Zergling";"Larva";322;1
"Unit";"Zergling";"Larva";322;1
"Unit";"Overlord";"Larva";334;0
"Unit";"Overlord";"Larva";334;0
"Unit";"Overlord";"Larva";334;0
"Unit";"Overlord";"Larva";334;0
"Building";"CreepTumor";NA;334;0
"Upgrade";"ZergMeleeWeaponsLevel1";"EvolutionChamber";282;0
"Building";"CreepTumor";NA;334;0
"Building";"CreepTumor";NA;334;0
"Building";"CreepTumor";NA;334;0
"Building";"CreepTumor";NA;334;0
"Building";"CreepTumor";NA;334;0
"Building";"CreepTumor";NA;334;0
"Building";"CreepTumorQueen";NA;338;0
"Building";"CreepTumorQueen";NA;338;0
"Building";"CreepTumor";NA;338;0
"Building";"CreepTumor";NA;338;0
"Building";"CreepTumor";NA;338;0
"Building";"CreepTumorQueen";NA;338;0
"Unit";"Zergling";"Larva";338;1
"Unit";"Zergling";"Larva";338;1
"Unit";"Zergling";"Larva";338;1
"Unit";"Zergling";"Larva";338;1
"Unit";"Zergling";"Larva";338;1
"Unit";"Zergling";"Larva";338;1
"Unit";"Zergling";"Larva";338;1
"Unit";"Zergling";"Larva";338;1
"Unit";"Zergling";"Larva";338;1
"Unit";"Zergling";"Larva";338;1
"Unit";"Zergling";"Larva";338;1
"Unit";"Zergling";"Larva";338;1
"Unit";"Zergling";"Larva";338;1
"Unit";"Zergling";"Larva";338;1
"Unit";"Zergling";"Larva";338;1
"Unit";"Zergling";"Larva";338;1
"Unit";"Zergling";"Larva";338;1
"Unit";"Zergling";"Larva";338;1
"Unit";"Zergling";"Larva";338;1
"Unit";"Zergling";"Larva";338;1
"Unit";"Zergling";"Larva";338;1
"Unit";"Zergling";"Larva";338;1
"Unit";"Zergling";"Larva";338;1
"Unit";"Zergling";"Larva";338;1
"Unit";"Zergling";"Larva";338;1
"Unit";"Zergling";"Larva";338;1
"Unit";"Zergling";"Larva";338;1
"Unit";"Zergling";"Larva";338;1
"Unit";"Zergling";"Larva";338;1
"Unit";"Zergling";"Larva";338;1
"Unit";"Zergling";"Larva";338;1
"Unit";"Zergling";"Larva";338;1
"Unit";"Zergling";"Larva";338;1
"Unit";"Zergling";"Larva";338;1
"Unit";"Zergling";"Larva";338;1
"Unit";"Zergling";"Larva";338;1
"Building";"CreepTumor";NA;338;0
"Building";"CreepTumor";NA;338;0
"Unit";"Zergling";"Larva";338;1
"Unit";"Zergling";"Larva";338;1
"Unit";"Zergling";"Larva";338;1
"Unit";"Zergling";"Larva";338;1
"Unit";"Zergling";"Larva";338;1
"Unit";"Zergling";"Larva";338;1
"Unit";"Zergling";"Larva";338;1
"Unit";"Zergling";"Larva";338;1
"Unit";"Zergling";"Larva";338;1
"Unit";"Zergling";"Larva";338;1
"Unit";"Zergling";"Larva";338;1
"Unit";"Zergling";"Larva";338;1
"Unit";"Zergling";"Larva";338;1
"Unit";"Zergling";"Larva";338;1
"Building";"SporeCrawler";NA;338;0
"Unit";"Hydralisk";"Larva";374;2
"Unit";"Hydralisk";"Larva";374;2
"Unit";"Hydralisk";"Larva";374;2
"Unit";"Hydralisk";"Larva";374;2
"Unit";"Queen";"Hatchery";338;2
"Unit";"Overlord";"Larva";389;0
"Unit";"Overlord";"Larva";389;0
"Unit";"Overlord";"Larva";389;0
"Unit";"Overlord";"Larva";389;0
"Building";"CreepTumor";NA;399;0
"Building";"CreepTumor";NA;399;0
"Building";"InfestationPit";NA;389;0
"Unit";"Hydralisk";"Larva";399;2
"Unit";"Hydralisk";"Larva";399;2
"Unit";"Hydralisk";"Larva";399;2
"Unit";"Hydralisk";"Larva";399;2
"Unit";"Hydralisk";"Larva";399;2
"Unit";"Hydralisk";"Larva";399;2
"Unit";"Hydralisk";"Larva";399;2
"Unit";"Hydralisk";"Larva";399;2
"Unit";"Hydralisk";"Larva";399;2
"Building";"CreepTumor";NA;399;0
"Building";"CreepTumor";NA;399;0
"Building";"CreepTumor";NA;399;0
"Building";"CreepTumor";NA;399;0
"Building";"CreepTumor";NA;399;0
"Building";"CreepTumorQueen";NA;399;0
"Building";"CreepTumorQueen";NA;399;0
"Unit";"Hydralisk";"Larva";399;2
"Unit";"Hydralisk";"Larva";399;2
"Unit";"Hydralisk";"Larva";399;2
"Unit";"Hydralisk";"Larva";399;2
"Unit";"Zergling";"Larva";399;1
"Unit";"Zergling";"Larva";399;1
"Unit";"Zergling";"Larva";399;1
"Unit";"Zergling";"Larva";399;1
"Unit";"Zergling";"Larva";399;1
"Unit";"Zergling";"Larva";399;1
"Unit";"Zergling";"Larva";399;1
"Unit";"Zergling";"Larva";399;1
"Unit";"Zergling";"Larva";399;1
"Unit";"Zergling";"Larva";399;1
"Unit";"Zergling";"Larva";399;1
"Unit";"Zergling";"Larva";399;1
"Unit";"Zergling";"Larva";399;1
"Unit";"Zergling";"Larva";399;1
"Unit";"Zergling";"Larva";399;1
"Unit";"Zergling";"Larva";399;1
"Unit";"Zergling";"Larva";399;1
"Unit";"Zergling";"Larva";399;1
"Unit";"Zergling";"Larva";401;1
"Unit";"Zergling";"Larva";401;1
"Unit";"Zergling";"Larva";401;1
"Unit";"Zergling";"Larva";401;1
"Unit";"Zergling";"Larva";401;1
"Unit";"Zergling";"Larva";401;1
"Unit";"Hydralisk";"Larva";417;2
"Unit";"Hydralisk";"Larva";417;2
"Building";"Spire";NA;389;0
"Upgrade";"ZergGroundArmorsLevel1";"EvolutionChamber";389;0
"Unit";"Hydralisk";"Larva";451;2
"Unit";"Hydralisk";"Larva";451;2
"Unit";"Hydralisk";"Larva";451;2
"Unit";"Hydralisk";"Larva";451;2
"Unit";"Hydralisk";"Larva";451;2
"Unit";"Hydralisk";"Larva";451;2
"Unit";"Zergling";"Larva";455;1
"Unit";"Zergling";"Larva";455;1
"Unit";"Zergling";"Larva";455;1
"Unit";"Zergling";"Larva";455;1
"Unit";"Zergling";"Larva";455;1
"Unit";"Zergling";"Larva";455;1
"Unit";"Zergling";"Larva";455;1
"Unit";"Zergling";"Larva";455;1
"Unit";"Overlord";"Larva";455;0
"Building";"CreepTumor";NA;455;0
"Building";"CreepTumor";NA;455;0
"Unit";"Hydralisk";"Larva";455;2
"Unit";"Hydralisk";"Larva";455;2
"Unit";"Zergling";"Larva";455;1
"Unit";"Zergling";"Larva";455;1
"Unit";"Zergling";"Larva";455;1
"Unit";"Zergling";"Larva";455;1
"Unit";"Hydralisk";"Larva";455;2
"Unit";"Hydralisk";"Larva";455;2
"Unit";"Overlord";"Larva";475;0
"Unit";"Hydralisk";"Larva";487;2
"Unit";"Hydralisk";"Larva";487;2
"Unit";"Hydralisk";"Larva";487;2
"Unit";"Hydralisk";"Larva";487;2
"Unit";"Hydralisk";"Larva";487;2
"Unit";"Hydralisk";"Larva";487;2
"Unit";"Hydralisk";"Larva";487;2
"Unit";"Zergling";"Larva";487;1
"Unit";"Zergling";"Larva";487;1
"Unit";"Zergling";"Larva";487;1
"Unit";"Zergling";"Larva";487;1
"Unit";"Zergling";"Larva";487;1
"Unit";"Zergling";"Larva";487;1
"Unit";"Zergling";"Larva";487;1
"Unit";"Zergling";"Larva";487;1
"Unit";"Zergling";"Larva";487;1
"Unit";"Zergling";"Larva";487;1
"Unit";"Zergling";"Larva";487;1
"Unit";"Zergling";"Larva";487;1
"Unit";"Zergling";"Larva";487;1
"Unit";"Zergling";"Larva";487;1
"Unit";"Zergling";"Larva";487;1
"Unit";"Zergling";"Larva";487;1
"Unit";"Zergling";"Larva";487;1
"Unit";"Zergling";"Larva";487;1
"Unit";"Hydralisk";"Larva";487;2
"Unit";"Zergling";"Larva";487;1
"Unit";"Zergling";"Larva";487;1
"Unit";"Zergling";"Larva";487;1
"Unit";"Zergling";"Larva";487;1
"Unit";"Zergling";"Larva";487;1
"Unit";"Zergling";"Larva";487;1
"Unit";"Zergling";"Larva";487;1
"Unit";"Zergling";"Larva";487;1
"Unit";"Hydralisk";"Larva";487;2
"Unit";"Hydralisk";"Larva";487;2
"Unit";"Hydralisk";"Larva";487;2
"Unit";"Hydralisk";"Larva";487;2
"Unit";"Hydralisk";"Larva";489;2
"Unit";"Zergling";"Larva";529;1
"Unit";"Zergling";"Larva";529;1
"Unit";"Zergling";"Larva";529;1
"Unit";"Zergling";"Larva";529;1
"Unit";"Zergling";"Larva";529;1
"Unit";"Zergling";"Larva";529;1
"Unit";"Zergling";"Larva";529;1
"Unit";"Zergling";"Larva";529;1
"Unit";"Zergling";"Larva";529;1
"Unit";"Zergling";"Larva";529;1
"Unit";"Zergling";"Larva";529;1
"Unit";"Zergling";"Larva";529;1
"Unit";"Zergling";"Larva";529;1
"Unit";"Zergling";"Larva";529;1
"Unit";"Zergling";"Larva";529;1
"Unit";"Zergling";"Larva";529;1
"Unit";"Zergling";"Larva";529;1
"Unit";"Zergling";"Larva";529;1
"Unit";"Zergling";"Larva";529;1
"Unit";"Zergling";"Larva";529;1
"Unit";"Zergling";"Larva";529;1
"Unit";"Zergling";"Larva";529;1
"Unit";"Zergling";"Larva";529;1
"Unit";"Zergling";"Larva";529;1
"Unit";"Hydralisk";"Larva";529;2
"Unit";"Hydralisk";"Larva";529;2
"Unit";"Hydralisk";"Larva";529;2
"Unit";"Hydralisk";"Larva";539;2
"Unit";"Hydralisk";"Larva";539;2
"Unit";"Hydralisk";"Larva";539;2
"Unit";"Hydralisk";"Larva";563;2
"Unit";"Hydralisk";"Larva";563;2
"Unit";"Zergling";"Larva";565;1
"Unit";"Zergling";"Larva";565;1
"Unit";"Zergling";"Larva";567;1
"Unit";"Zergling";"Larva";567;1
"Unit";"Hydralisk";"Larva";563;2
"Unit";"Hydralisk";"Larva";563;2
"Building";"CreepTumor";NA;569;0
"Unit";"Hydralisk";"Larva";563;2
"Building";"CreepTumor";NA;569;0
"Unit";"Hydralisk";"Larva";563;2
"Unit";"Hydralisk";"Larva";563;2
"Unit";"Zergling";"Larva";575;1
"Unit";"Zergling";"Larva";575;1
"Unit";"Zergling";"Larva";575;1
"Unit";"Zergling";"Larva";575;1
"Unit";"Hydralisk";"Larva";567;2
"Unit";"Hydralisk";"Larva";569;2
"Unit";"Hydralisk";"Larva";569;2
"Unit";"Hydralisk";"Larva";579;2
"Unit";"Hydralisk";"Larva";579;2
"Unit";"Hydralisk";"Larva";587;2
"Unit";"Hydralisk";"Larva";587;2
"Unit";"Hydralisk";"Larva";589;2
"Unit";"Hydralisk";"Larva";593;2
"Unit";"Hydralisk";"Larva";599;2
"Unit";"Hydralisk";"Larva";599;2
"Unit";"Zergling";"Larva";603;1
"Unit";"Zergling";"Larva";603;1
"Unit";"Hydralisk";"Larva";603;2
"Unit";"Hydralisk";"Larva";603;2
"Unit";"Zergling";"Larva";613;1
"Unit";"Zergling";"Larva";613;1
"Unit";"Zergling";"Larva";613;1
"Unit";"Zergling";"Larva";613;1
"Unit";"Zergling";"Larva";613;1
"Unit";"Zergling";"Larva";613;1
"Unit";"Baneling";"Zergling";615;0
"Unit";"Baneling";"Zergling";615;0
"Unit";"Baneling";"Zergling";615;0
"Unit";"Baneling";"Zergling";615;0
"Unit";"Baneling";"Zergling";615;0
"Unit";"Baneling";"Zergling";615;0
"Unit";"Baneling";"Zergling";615;0
"Unit";"Baneling";"Zergling";615;0
"Unit";"Hydralisk";"Larva";613;2
"Unit";"Hydralisk";"Larva";613;2
