"type";"unit_name";"on_building";"total_supply_lag";"supply"
"Unit";"Overlord";"Larva";13;0
"Building";"Hatchery";NA;16;0
"Building";"SpawningPool";NA;18;0
"Unit";"Overlord";"Larva";22;0
"Building";"Extractor";NA;22;0
"Unit";"Queen";"Hatchery";22;2
"Unit";"Zergling";"Larva";24;1
"Unit";"Zergling";"Larva";25;1
"Unit";"Queen";"Hatchery";27;2
"Building";"Hatchery";NA;34;0
"Unit";"Overlord";"Larva";34;0
"Unit";"Queen";"Hatchery";34;2
"Unit";"Zergling";"Larva";39;1
"Unit";"Zergling";"Larva";40;1
"Unit";"Zergling";"Larva";41;1
"Unit";"Zergling";"Larva";42;1
"Unit";"Zergling";"Larva";43;1
"Unit";"Zergling";"Larva";44;1
"Building";"CreepTumorQueen";NA;45;0
"Unit";"Overlord";"Larva";50;0
"Unit";"Overlord";"Larva";51;0
"Building";"SporeCrawler";NA;52;0
"Building";"SporeCrawler";NA;52;0
"Building";"CreepTumor";NA;53;0
"Building";"SporeCrawler";NA;53;0
"Building";"CreepTumorQueen";NA;54;0
"Unit";"Overlord";"Larva";59;0
"Building";"Extractor";NA;61;0
"Unit";"Overlord";"Larva";61;0
"Building";"CreepTumor";NA;63;0
"Building";"CreepTumor";NA;63;0
"Building";"Extractor";NA;63;0
"Building";"Extractor";NA;64;0
"Unit";"Overlord";"Larva";69;0
"Building";"CreepTumor";NA;75;0
"Building";"CreepTumor";NA;75;0
"Unit";"Zergling";"Larva";75;1
"Unit";"Zergling";"Larva";76;1
"Unit";"Zergling";"Larva";77;1
"Unit";"Zergling";"Larva";78;1
"Unit";"Zergling";"Larva";79;1
"Unit";"Zergling";"Larva";80;1
"Unit";"Zergling";"Larva";81;1
"Unit";"Zergling";"Larva";82;1
"Unit";"Zergling";"Larva";84;1
"Unit";"Zergling";"Larva";85;1
"Unit";"Zergling";"Larva";86;1
"Unit";"Zergling";"Larva";87;1
"Unit";"Zergling";"Larva";88;1
"Unit";"Zergling";"Larva";89;1
"Unit";"Overlord";"Larva";90;0
"Building";"HydraliskDen";NA;90;0
"Building";"CreepTumor";NA;94;0
"Building";"CreepTumor";NA;94;0
"Unit";"Zergling";"Larva";94;1
"Unit";"Zergling";"Larva";95;1
"Unit";"Zergling";"Larva";96;1
"Unit";"Zergling";"Larva";97;1
"Unit";"Zergling";"Larva";98;1
"Unit";"Zergling";"Larva";99;1
"Unit";"Overlord";"Larva";100;0
"Unit";"Zergling";"Larva";100;1
"Unit";"Zergling";"Larva";101;1
"Unit";"Overlord";"Larva";102;0
"Unit";"Zergling";"Larva";102;1
"Unit";"Zergling";"Larva";103;1
"Unit";"Zergling";"Larva";104;1
"Unit";"Zergling";"Larva";105;1
"Unit";"Overlord";"Larva";106;0
"Unit";"Hydralisk";"Larva";106;2
"Unit";"Hydralisk";"Larva";108;2
"Unit";"Hydralisk";"Larva";110;2
"Unit";"Hydralisk";"Larva";112;2
"Unit";"Hydralisk";"Larva";114;2
"Building";"CreepTumor";NA;116;0
"Building";"CreepTumor";NA;116;0
"Unit";"Hydralisk";"Larva";116;2
"Unit";"Hydralisk";"Larva";118;2
"Unit";"Hydralisk";"Larva";120;2
"Unit";"Zergling";"Larva";122;1
"Unit";"Zergling";"Larva";123;1
"Unit";"Hydralisk";"Larva";124;2
"Unit";"Zergling";"Larva";126;1
"Unit";"Zergling";"Larva";127;1
"Unit";"Hydralisk";"Larva";128;2
"Unit";"Hydralisk";"Larva";130;2
"Unit";"Hydralisk";"Larva";132;2
"Unit";"Zergling";"Larva";134;1
"Unit";"Zergling";"Larva";135;1
"Unit";"Zergling";"Larva";136;1
"Unit";"Zergling";"Larva";137;1
"Unit";"Hydralisk";"Larva";138;2
"Unit";"Hydralisk";"Larva";140;2
"Building";"CreepTumor";NA;142;0
"Building";"CreepTumor";NA;142;0
"Unit";"Hydralisk";"Larva";142;2
"Unit";"Zergling";"Larva";144;1
"Unit";"Zergling";"Larva";145;1
"Unit";"Overlord";"Larva";146;0
"Unit";"Hydralisk";"Larva";146;2
"Unit";"Zergling";"Larva";148;1
"Unit";"Zergling";"Larva";149;1
"Unit";"Overlord";"Larva";150;0
"Unit";"Overlord";"Larva";150;0
"Unit";"Zergling";"Larva";150;1
"Unit";"Zergling";"Larva";151;1
"Unit";"Overlord";"Larva";152;0
"Unit";"Zergling";"Larva";152;1
"Unit";"Zergling";"Larva";153;1
"Unit";"Zergling";"Larva";154;1
"Unit";"Zergling";"Larva";155;1
"Unit";"Zergling";"Larva";156;1
"Unit";"Zergling";"Larva";157;1
"Unit";"Hydralisk";"Larva";158;2
"Unit";"Zergling";"Larva";160;1
"Unit";"Zergling";"Larva";161;1
"Unit";"Zergling";"Larva";162;1
"Unit";"Zergling";"Larva";163;1
"Unit";"Zergling";"Larva";164;1
"Unit";"Zergling";"Larva";165;1
"Unit";"Zergling";"Larva";166;1
"Unit";"Zergling";"Larva";167;1
"Unit";"Hydralisk";"Larva";168;2
"Unit";"Hydralisk";"Larva";170;2
"Unit";"Hydralisk";"Larva";172;2
"Building";"CreepTumor";NA;174;0
"Building";"CreepTumor";NA;174;0
"Unit";"Hydralisk";"Larva";174;2
"Unit";"Hydralisk";"Larva";176;2
"Unit";"Hydralisk";"Larva";178;2
"Unit";"Zergling";"Larva";180;1
"Unit";"Zergling";"Larva";181;1
"Unit";"Zergling";"Larva";182;1
"Unit";"Zergling";"Larva";183;1
"Unit";"Hydralisk";"Larva";184;2
"Unit";"Zergling";"Larva";186;1
"Unit";"Zergling";"Larva";187;1
"Unit";"Zergling";"Larva";188;1
"Unit";"Zergling";"Larva";189;1
"Unit";"Zergling";"Larva";190;1
"Unit";"Zergling";"Larva";191;1
"Unit";"Zergling";"Larva";192;1
"Unit";"Zergling";"Larva";193;1
"Unit";"Zergling";"Larva";194;1
"Unit";"Zergling";"Larva";195;1
"Unit";"Zergling";"Larva";196;1
"Unit";"Zergling";"Larva";197;1
"Unit";"Zergling";"Larva";198;1
"Unit";"Zergling";"Larva";199;1
"Unit";"Zergling";"Larva";200;1
"Unit";"Zergling";"Larva";201;1
"Unit";"Zergling";"Larva";202;1
"Unit";"Zergling";"Larva";203;1
"Upgrade";"SprayZerg";NA;204;0
"Upgrade";"SprayZerg";NA;204;0
"Upgrade";"SprayZerg";NA;204;0
"Upgrade";"SprayZerg";NA;204;0
"Upgrade";"zerglingmovementspeed";NA;204;0
"Upgrade";"EvolveMuscularAugments";NA;204;0
