"type";"unit_name";"on_building";"total_supply";"supply"
"Unit";"Overlord";"Larva";13;0
"Building";"Extractor";NA;18;0
"Building";"SpawningPool";NA;19;0
"Building";"Hatchery";NA;16;0
"Unit";"Overlord";"Larva";22;0
"Unit";"Zergling";"Larva";23;1
"Unit";"Zergling";"Larva";23;1
"Unit";"Zergling";"Larva";23;1
"Unit";"Zergling";"Larva";23;1
"Unit";"Queen";"Hatchery";23;2
"Unit";"Queen";"Hatchery";23;2
"Unit";"Overlord";"Larva";35;0
"Building";"CreepTumorQueen";NA;40;0
"Unit";"Overlord";"Larva";38;0
"Unit";"Queen";"Hatchery";38;2
"Building";"Hatchery";NA;29;0
"Building";"EvolutionChamber";NA;44;0
"Unit";"Overlord";"Larva";47;0
"Unit";"Overlord";"Larva";49;0
"Building";"CreepTumorQueen";NA;50;0
"Building";"CreepTumor";NA;50;0
"Unit";"Queen";"Hatchery";44;2
"Unit";"Overlord";"Larva";51;0
"Unit";"Queen";"Hatchery";50;2
"Unit";"Zergling";"Larva";53;1
"Unit";"Zergling";"Larva";53;1
"Unit";"Zergling";"Larva";53;1
"Unit";"Zergling";"Larva";53;1
"Unit";"Zergling";"Larva";53;1
"Unit";"Zergling";"Larva";53;1
"Building";"CreepTumorQueen";NA;55;0
"Building";"CreepTumorQueen";NA;61;0
"Building";"SporeCrawler";NA;55;0
"Unit";"Overlord";"Larva";77;0
"Unit";"Overlord";"Larva";77;0
"Building";"CreepTumor";NA;79;0
"Building";"Extractor";NA;77;0
"Building";"Extractor";NA;79;0
"Unit";"Overlord";"Larva";82;0
"Unit";"Overlord";"Larva";82;0
"Building";"Extractor";NA;79;0
"Building";"Extractor";NA;79;0
"Building";"CreepTumor";NA;91;0
"Unit";"Zergling";"Larva";91;1
"Unit";"Zergling";"Larva";91;1
"Unit";"Zergling";"Larva";91;1
"Unit";"Zergling";"Larva";91;1
"Unit";"Zergling";"Larva";91;1
"Unit";"Zergling";"Larva";91;1
"Unit";"Zergling";"Larva";91;1
"Unit";"Zergling";"Larva";91;1
"Unit";"Zergling";"Larva";91;1
"Unit";"Zergling";"Larva";91;1
"Unit";"Zergling";"Larva";91;1
"Unit";"Zergling";"Larva";91;1
"Unit";"Zergling";"Larva";91;1
"Unit";"Zergling";"Larva";91;1
"Unit";"Zergling";"Larva";96;1
"Unit";"Zergling";"Larva";96;1
"Upgrade";"ZergMeleeWeaponsLevel1";"EvolutionChamber";68;0
"Unit";"Zergling";"Larva";96;1
"Unit";"Zergling";"Larva";96;1
"Unit";"Zergling";"Larva";96;1
"Unit";"Zergling";"Larva";96;1
"Unit";"Zergling";"Larva";97;1
"Unit";"Zergling";"Larva";97;1
"Unit";"Zergling";"Larva";97;1
"Unit";"Zergling";"Larva";97;1
"Unit";"Zergling";"Larva";117;1
"Unit";"Zergling";"Larva";117;1
"Unit";"Zergling";"Larva";117;1
"Unit";"Zergling";"Larva";117;1
"Unit";"Overlord";"Larva";117;0
"Unit";"Overlord";"Larva";117;0
"Unit";"Overlord";"Larva";117;0
"Building";"Extractor";NA;117;0
"Building";"HydraliskDen";NA;111;0
"Building";"BanelingNest";NA;96;0
"Building";"CreepTumor";NA;124;0
"Unit";"Overlord";"Larva";124;0
"Unit";"Overlord";"Larva";124;0
"Unit";"Overlord";"Larva";124;0
"Building";"CreepTumor";NA;128;0
"Building";"CreepTumor";NA;128;0
"Building";"CreepTumor";NA;128;0
"Building";"Hatchery";NA;89;0
"Building";"CreepTumor";NA;130;0
"Building";"CreepTumor";NA;130;0
"Unit";"Hydralisk";"Larva";130;2
"Unit";"Hydralisk";"Larva";130;2
"Unit";"Hydralisk";"Larva";130;2
"Unit";"Hydralisk";"Larva";130;2
"Unit";"Hydralisk";"Larva";130;2
"Unit";"Hydralisk";"Larva";130;2
"Unit";"Hydralisk";"Larva";130;2
"Unit";"Hydralisk";"Larva";130;2
"Unit";"Hydralisk";"Larva";130;2
"Unit";"Hydralisk";"Larva";130;2
"Unit";"Hydralisk";"Larva";130;2
"Building";"CreepTumor";NA;130;0
"Building";"CreepTumorQueen";NA;130;0
"Unit";"Hydralisk";"Larva";130;2
"Unit";"Hydralisk";"Larva";130;2
"Unit";"Hydralisk";"Larva";130;2
"Unit";"Hydralisk";"Larva";130;2
"Unit";"Hydralisk";"Larva";130;2
"Unit";"Hydralisk";"Larva";130;2
"Unit";"Hydralisk";"Larva";130;2
"Unit";"Hydralisk";"Larva";130;2
"Unit";"Hydralisk";"Larva";130;2
"Building";"CreepTumorQueen";NA;153;0
"Unit";"Hydralisk";"Larva";153;2
"Unit";"Hydralisk";"Larva";153;2
"Unit";"Hydralisk";"Larva";153;2
"Unit";"Hydralisk";"Larva";153;2
"Unit";"Zergling";"Larva";153;1
"Unit";"Zergling";"Larva";153;1
"Building";"CreepTumor";NA;175;0
"Building";"CreepTumor";NA;175;0
"Building";"CreepTumor";NA;175;0
"Building";"CreepTumor";NA;175;0
"Unit";"Hydralisk";"Larva";153;2
"Unit";"Hydralisk";"Larva";153;2
"Unit";"Hydralisk";"Larva";153;2
"Upgrade";"ZergMissileWeaponsLevel1";"EvolutionChamber";129;0
"Upgrade";"EvolveGroovedSpines";"HydraliskDen";130;0
"Unit";"Hydralisk";"Larva";175;2
"Unit";"Overlord";"Larva";175;0
"Unit";"Overlord";"Larva";175;0
"Unit";"Hydralisk";"Larva";175;2
"Unit";"Overlord";"Larva";175;0
"Unit";"Hydralisk";"Larva";175;2
"Unit";"Zergling";"Larva";185;1
"Unit";"Zergling";"Larva";185;1
"Unit";"Zergling";"Larva";185;1
"Unit";"Zergling";"Larva";185;1
"Unit";"Zergling";"Larva";185;1
"Unit";"Zergling";"Larva";185;1
"Unit";"Zergling";"Larva";185;1
"Unit";"Zergling";"Larva";185;1
"Unit";"Zergling";"Larva";185;1
"Unit";"Zergling";"Larva";185;1
"Unit";"Zergling";"Larva";185;1
"Unit";"Zergling";"Larva";185;1
"Unit";"Zergling";"Larva";185;1
"Unit";"Zergling";"Larva";185;1
"Building";"CreepTumor";NA;197;0
"Building";"CreepTumor";NA;197;0
"Building";"CreepTumorQueen";NA;211;0
"Unit";"Hydralisk";"Larva";197;2
"Unit";"Hydralisk";"Larva";197;2
"Unit";"Hydralisk";"Larva";197;2
"Unit";"Hydralisk";"Larva";197;2
"Unit";"Zergling";"Larva";211;1
"Unit";"Zergling";"Larva";211;1
"Building";"CreepTumorQueen";NA;211;0
"Unit";"Zergling";"Larva";211;1
"Unit";"Zergling";"Larva";211;1
"Unit";"Zergling";"Larva";211;1
"Unit";"Zergling";"Larva";211;1
"Unit";"Zergling";"Larva";211;1
"Unit";"Zergling";"Larva";211;1
"Unit";"Zergling";"Larva";211;1
"Unit";"Zergling";"Larva";211;1
"Unit";"Zergling";"Larva";211;1
"Unit";"Zergling";"Larva";211;1
"Unit";"Zergling";"Larva";211;1
"Unit";"Zergling";"Larva";211;1
"Unit";"Zergling";"Larva";211;1
"Unit";"Zergling";"Larva";211;1
"Unit";"Zergling";"Larva";211;1
"Unit";"Zergling";"Larva";211;1
"Building";"CreepTumorQueen";NA;211;0
"Building";"CreepTumorQueen";NA;211;0
"Unit";"Overlord";"Larva";211;0
"Unit";"Overlord";"Larva";211;0
"Unit";"Overlord";"Larva";211;0
"Unit";"Overlord";"Larva";237;0
"Unit";"Overlord";"Larva";237;0
"Unit";"Hydralisk";"Larva";211;2
"Unit";"Hydralisk";"Larva";211;2
"Unit";"Hydralisk";"Larva";211;2
"Unit";"Baneling";"Zergling";243;0
"Unit";"Hydralisk";"Larva";237;2
"Unit";"Baneling";"Zergling";243;0
"Unit";"Baneling";"Zergling";243;0
"Unit";"Hydralisk";"Larva";237;2
"Unit";"Hydralisk";"Larva";237;2
"Unit";"Hydralisk";"Larva";237;2
"Unit";"Hydralisk";"Larva";237;2
"Unit";"Hydralisk";"Larva";237;2
"Unit";"Baneling";"Zergling";243;0
"Unit";"Zergling";"Larva";243;1
"Unit";"Zergling";"Larva";243;1
"Unit";"Zergling";"Larva";243;1
"Unit";"Zergling";"Larva";243;1
"Unit";"Zergling";"Larva";243;1
"Unit";"Zergling";"Larva";243;1
"Unit";"Zergling";"Larva";243;1
"Unit";"Zergling";"Larva";243;1
"Unit";"Zergling";"Larva";243;1
"Unit";"Zergling";"Larva";243;1
"Unit";"Zergling";"Larva";243;1
"Unit";"Zergling";"Larva";243;1
"Unit";"Zergling";"Larva";243;1
"Unit";"Zergling";"Larva";243;1
"Unit";"Zergling";"Larva";243;1
"Unit";"Zergling";"Larva";243;1
"Unit";"Zergling";"Larva";243;1
"Unit";"Zergling";"Larva";243;1
"Unit";"Baneling";"Zergling";243;0
"Unit";"Baneling";"Zergling";243;0
"Unit";"Baneling";"Zergling";243;0
"Unit";"Baneling";"Zergling";243;0
"Unit";"Baneling";"Zergling";243;0
"Unit";"Baneling";"Zergling";243;0
"Unit";"Baneling";"Zergling";243;0
"Unit";"Baneling";"Zergling";243;0
"Unit";"Baneling";"Zergling";243;0
"Unit";"Baneling";"Zergling";243;0
"Upgrade";"EvolveMuscularAugments";"HydraliskDen";211;0
"Unit";"Zergling";"Larva";243;1
"Unit";"Zergling";"Larva";243;1
"Unit";"Zergling";"Larva";243;1
"Unit";"Zergling";"Larva";243;1
"Unit";"Zergling";"Larva";243;1
"Unit";"Zergling";"Larva";243;1
"Unit";"Zergling";"Larva";243;1
"Unit";"Zergling";"Larva";243;1
"Unit";"Zergling";"Larva";243;1
"Unit";"Zergling";"Larva";243;1
"Unit";"Zergling";"Larva";243;1
"Unit";"Zergling";"Larva";243;1
"Building";"CreepTumor";NA;273;0
"Building";"CreepTumor";NA;273;0
"Building";"CreepTumor";NA;273;0
"Building";"CreepTumor";NA;273;0
"Building";"CreepTumor";NA;273;0
"Unit";"Zergling";"Larva";273;1
"Unit";"Zergling";"Larva";273;1
"Unit";"Zergling";"Larva";273;1
"Unit";"Zergling";"Larva";273;1
"Unit";"Zergling";"Larva";273;1
"Unit";"Zergling";"Larva";273;1
"Unit";"Zergling";"Larva";273;1
"Unit";"Zergling";"Larva";273;1
"Unit";"Baneling";"Zergling";273;0
"Unit";"Baneling";"Zergling";273;0
"Unit";"Baneling";"Zergling";273;0
"Unit";"Baneling";"Zergling";273;0
"Unit";"Baneling";"Zergling";273;0
"Unit";"Baneling";"Zergling";273;0
"Unit";"Baneling";"Zergling";273;0
"Unit";"Baneling";"Zergling";273;0
"Unit";"Baneling";"Zergling";273;0
"Unit";"Baneling";"Zergling";273;0
"Unit";"Baneling";"Zergling";273;0
"Unit";"Baneling";"Zergling";273;0
"Unit";"Baneling";"Zergling";273;0
"Unit";"Baneling";"Zergling";273;0
"Unit";"Baneling";"Zergling";273;0
"Unit";"Zergling";"Larva";285;1
"Unit";"Zergling";"Larva";285;1
"Unit";"Zergling";"Larva";293;1
"Unit";"Zergling";"Larva";293;1
"Unit";"Zergling";"Larva";293;1
"Unit";"Zergling";"Larva";293;1
"Unit";"Zergling";"Larva";293;1
"Unit";"Zergling";"Larva";293;1
"Unit";"Zergling";"Larva";293;1
"Unit";"Zergling";"Larva";293;1
"Unit";"Zergling";"Larva";293;1
"Unit";"Zergling";"Larva";293;1
"Unit";"Zergling";"Larva";293;1
"Unit";"Zergling";"Larva";293;1
"Unit";"Zergling";"Larva";293;1
"Unit";"Zergling";"Larva";293;1
"Unit";"Zergling";"Larva";293;1
"Unit";"Zergling";"Larva";293;1
"Unit";"Zergling";"Larva";293;1
"Unit";"Zergling";"Larva";293;1
"Unit";"Zergling";"Larva";293;1
"Unit";"Zergling";"Larva";293;1
"Unit";"Zergling";"Larva";293;1
"Unit";"Zergling";"Larva";293;1
"Unit";"Zergling";"Larva";293;1
"Unit";"Zergling";"Larva";293;1
"Unit";"Zergling";"Larva";293;1
"Unit";"Zergling";"Larva";293;1
"Unit";"Zergling";"Larva";293;1
"Unit";"Zergling";"Larva";293;1
"Unit";"Zergling";"Larva";293;1
"Unit";"Zergling";"Larva";293;1
"Unit";"Zergling";"Larva";293;1
"Unit";"Zergling";"Larva";293;1
"Unit";"Zergling";"Larva";293;1
"Unit";"Zergling";"Larva";293;1
"Unit";"Zergling";"Larva";293;1
"Unit";"Zergling";"Larva";293;1
