"type";"unit_name";"on_building";"total_supply";"supply"
"Unit";"Overlord";"Larva";13;0
"Building";"Extractor";NA;17;0
"Unit";"Overlord";"Larva";21;0
"Building";"SpawningPool";NA;19;0
"Building";"Hatchery";NA;17;0
"Unit";"Zergling";"Larva";23;1
"Unit";"Zergling";"Larva";23;1
"Unit";"Zergling";"Larva";23;1
"Unit";"Zergling";"Larva";23;1
"Unit";"Queen";"Hatchery";23;2
"Unit";"Queen";"Hatchery";23;2
"Unit";"Overlord";"Larva";37;0
"Unit";"Overlord";"Larva";38;0
"Building";"CreepTumorQueen";NA;39;0
"Unit";"Overlord";"Larva";39;0
"Unit";"Queen";"Hatchery";38;2
"Building";"SporeCrawler";NA;40;0
"Unit";"Overlord";"Larva";44;0
"Building";"CreepTumor";NA;48;0
"Building";"SporeCrawler";NA;44;0
"Building";"Hatchery";NA;35;0
"Building";"EvolutionChamber";NA;48;0
"Unit";"Zergling";"Larva";49;1
"Unit";"Zergling";"Larva";49;1
"Unit";"Zergling";"Larva";49;1
"Unit";"Zergling";"Larva";49;1
"Unit";"Zergling";"Larva";49;1
"Unit";"Zergling";"Larva";49;1
"Unit";"Zergling";"Larva";49;1
"Unit";"Zergling";"Larva";49;1
"Unit";"Zergling";"Larva";49;1
"Unit";"Zergling";"Larva";49;1
"Building";"CreepTumor";NA;51;0
"Unit";"Overlord";"Larva";51;0
"Unit";"Zergling";"Larva";62;1
"Unit";"Zergling";"Larva";62;1
"Unit";"Zergling";"Larva";62;1
"Unit";"Zergling";"Larva";62;1
"Unit";"Zergling";"Larva";62;1
"Unit";"Zergling";"Larva";62;1
"Unit";"Zergling";"Larva";62;1
"Unit";"Zergling";"Larva";62;1
"Unit";"Queen";"Hatchery";52;2
"Building";"CreepTumor";NA;90;0
"Unit";"Overlord";"Larva";88;0
"Unit";"Overlord";"Larva";88;0
"Unit";"Overlord";"Larva";88;0
"Unit";"Overlord";"Larva";88;0
"Building";"Extractor";NA;88;0
"Building";"Extractor";NA;88;0
"Building";"CreepTumorQueen";NA;93;0
"Building";"CreepTumorQueen";NA;93;0
"Unit";"Zergling";"Larva";93;1
"Unit";"Zergling";"Larva";93;1
"Unit";"Zergling";"Larva";93;1
"Unit";"Zergling";"Larva";93;1
"Unit";"Zergling";"Larva";93;1
"Unit";"Zergling";"Larva";93;1
"Unit";"Zergling";"Larva";93;1
"Unit";"Zergling";"Larva";93;1
"Unit";"Zergling";"Larva";93;1
"Unit";"Zergling";"Larva";93;1
"Unit";"Zergling";"Larva";93;1
"Unit";"Zergling";"Larva";93;1
"Unit";"Zergling";"Larva";93;1
"Unit";"Zergling";"Larva";93;1
"Unit";"Zergling";"Larva";93;1
"Unit";"Zergling";"Larva";93;1
"Unit";"Zergling";"Larva";93;1
"Unit";"Zergling";"Larva";93;1
"Unit";"Zergling";"Larva";93;1
"Unit";"Zergling";"Larva";93;1
"Unit";"Zergling";"Larva";93;1
"Unit";"Zergling";"Larva";93;1
"Unit";"Zergling";"Larva";93;1
"Unit";"Zergling";"Larva";93;1
"Building";"BanelingNest";NA;90;0
"Building";"CreepTumor";NA;93;0
"Building";"CreepTumor";NA;93;0
"Building";"CreepTumor";NA;93;0
"Upgrade";"ZergMeleeWeaponsLevel1";"EvolutionChamber";76;0
"Unit";"Overlord";"Larva";101;0
"Building";"Extractor";NA;118;0
"Unit";"Overlord";"Larva";121;0
"Building";"HydraliskDen";NA;127;0
"Building";"CreepTumor";NA;130;0
"Building";"CreepTumor";NA;130;0
"Unit";"Overlord";"Larva";130;0
"Unit";"Overlord";"Larva";130;0
"Unit";"Overlord";"Larva";130;0
"Unit";"Hydralisk";"Larva";130;2
"Unit";"Hydralisk";"Larva";130;2
"Unit";"Hydralisk";"Larva";130;2
"Unit";"Hydralisk";"Larva";130;2
"Unit";"Hydralisk";"Larva";130;2
"Unit";"Hydralisk";"Larva";130;2
"Unit";"Hydralisk";"Larva";130;2
"Unit";"Hydralisk";"Larva";130;2
"Building";"CreepTumor";NA;130;0
"Unit";"Hydralisk";"Larva";130;2
"Unit";"Overlord";"Larva";130;0
"Unit";"Overlord";"Larva";130;0
"Building";"Extractor";NA;130;0
"Building";"Extractor";NA;130;0
"Unit";"Zergling";"Larva";146;1
"Unit";"Zergling";"Larva";146;1
"Unit";"Zergling";"Larva";146;1
"Unit";"Zergling";"Larva";146;1
"Unit";"Zergling";"Larva";146;1
"Unit";"Zergling";"Larva";146;1
"Unit";"Hydralisk";"Larva";130;2
"Unit";"Hydralisk";"Larva";130;2
"Building";"CreepTumorQueen";NA;157;0
"Unit";"Hydralisk";"Larva";157;2
"Building";"CreepTumor";NA;167;0
"Unit";"Zergling";"Larva";167;1
"Unit";"Zergling";"Larva";167;1
"Unit";"Zergling";"Larva";167;1
"Unit";"Zergling";"Larva";167;1
"Unit";"Zergling";"Larva";167;1
"Unit";"Zergling";"Larva";167;1
"Unit";"Zergling";"Larva";167;1
"Unit";"Zergling";"Larva";167;1
"Unit";"Zergling";"Larva";167;1
"Unit";"Zergling";"Larva";167;1
"Unit";"Zergling";"Larva";167;1
"Unit";"Zergling";"Larva";167;1
"Unit";"Zergling";"Larva";167;1
"Unit";"Zergling";"Larva";167;1
"Unit";"Hydralisk";"Larva";167;2
"Unit";"Hydralisk";"Larva";167;2
"Unit";"Hydralisk";"Larva";167;2
"Building";"CreepTumor";NA;169;0
"Unit";"Overlord";"Larva";167;0
"Building";"Hatchery";NA;130;0
"Unit";"Zergling";"Larva";169;1
"Unit";"Zergling";"Larva";169;1
"Unit";"Zergling";"Larva";169;1
"Unit";"Zergling";"Larva";169;1
"Unit";"Zergling";"Larva";169;1
"Unit";"Zergling";"Larva";169;1
"Unit";"Zergling";"Larva";169;1
"Unit";"Zergling";"Larva";169;1
"Unit";"Zergling";"Larva";169;1
"Unit";"Zergling";"Larva";169;1
"Unit";"Zergling";"Larva";169;1
"Unit";"Zergling";"Larva";169;1
"Building";"CreepTumor";NA;189;0
"Building";"CreepTumor";NA;189;0
"Upgrade";"EvolveGroovedSpines";"HydraliskDen";157;0
"Unit";"Zergling";"Larva";189;1
"Unit";"Zergling";"Larva";189;1
"Unit";"Hydralisk";"Larva";189;2
"Unit";"Hydralisk";"Larva";189;2
"Unit";"Hydralisk";"Larva";189;2
"Unit";"Hydralisk";"Larva";201;2
"Unit";"Hydralisk";"Larva";201;2
"Unit";"Hydralisk";"Larva";201;2
"Unit";"Hydralisk";"Larva";201;2
"Unit";"Hydralisk";"Larva";201;2
"Unit";"Hydralisk";"Larva";201;2
"Building";"CreepTumor";NA;203;0
"Unit";"Zergling";"Larva";209;1
"Unit";"Zergling";"Larva";209;1
"Unit";"Zergling";"Larva";209;1
"Unit";"Zergling";"Larva";209;1
"Unit";"Zergling";"Larva";209;1
"Unit";"Zergling";"Larva";209;1
"Upgrade";"ZergMeleeWeaponsLevel2";"EvolutionChamber";146;0
"Unit";"Zergling";"Larva";235;1
"Unit";"Zergling";"Larva";235;1
"Unit";"Zergling";"Larva";235;1
"Unit";"Zergling";"Larva";235;1
"Unit";"Zergling";"Larva";235;1
"Unit";"Zergling";"Larva";235;1
"Unit";"Zergling";"Larva";235;1
"Unit";"Zergling";"Larva";235;1
"Unit";"Zergling";"Larva";235;1
"Unit";"Zergling";"Larva";235;1
"Unit";"Hydralisk";"Larva";229;2
"Unit";"Hydralisk";"Larva";229;2
"Unit";"Hydralisk";"Larva";229;2
"Unit";"Hydralisk";"Larva";229;2
"Unit";"Hydralisk";"Larva";229;2
"Building";"CreepTumor";NA;235;0
"Unit";"Hydralisk";"Larva";229;2
"Unit";"Hydralisk";"Larva";229;2
"Unit";"Zergling";"Larva";235;1
"Unit";"Zergling";"Larva";235;1
"Unit";"Zergling";"Larva";235;1
"Unit";"Zergling";"Larva";235;1
"Unit";"Zergling";"Larva";235;1
"Unit";"Zergling";"Larva";235;1
"Unit";"Zergling";"Larva";235;1
"Unit";"Zergling";"Larva";235;1
"Unit";"Zergling";"Larva";235;1
"Unit";"Zergling";"Larva";235;1
"Unit";"Zergling";"Larva";235;1
"Unit";"Zergling";"Larva";235;1
"Building";"CreepTumor";NA;245;0
"Unit";"Baneling";"Zergling";235;0
"Unit";"Baneling";"Zergling";235;0
"Unit";"Baneling";"Zergling";235;0
"Unit";"Baneling";"Zergling";235;0
"Unit";"Baneling";"Zergling";235;0
"Unit";"Baneling";"Zergling";235;0
"Unit";"Baneling";"Zergling";235;0
"Unit";"Baneling";"Zergling";235;0
"Unit";"Baneling";"Zergling";235;0
"Unit";"Baneling";"Zergling";235;0
"Unit";"Baneling";"Zergling";235;0
"Unit";"Baneling";"Zergling";235;0
"Upgrade";"EvolveMuscularAugments";"HydraliskDen";226;0
"Unit";"Overlord";"Larva";259;0
"Unit";"Overlord";"Larva";259;0
"Unit";"Overlord";"Larva";259;0
"Building";"Extractor";NA;259;0
"Building";"Extractor";NA;259;0
"Unit";"Baneling";"Zergling";271;0
"Unit";"Baneling";"Zergling";271;0
"Unit";"Baneling";"Zergling";271;0
"Unit";"Baneling";"Zergling";271;0
"Unit";"Baneling";"Zergling";271;0
"Unit";"Baneling";"Zergling";271;0
"Unit";"Baneling";"Zergling";271;0
"Unit";"Baneling";"Zergling";271;0
"Unit";"Baneling";"Zergling";271;0
"Unit";"Overlord";"Larva";271;0
"Unit";"Overlord";"Larva";271;0
"Building";"CreepTumor";NA;276;0
"Building";"CreepTumor";NA;276;0
"Unit";"Zergling";"Larva";276;1
"Unit";"Zergling";"Larva";276;1
"Unit";"Zergling";"Larva";276;1
"Unit";"Zergling";"Larva";276;1
"Unit";"Zergling";"Larva";276;1
"Unit";"Zergling";"Larva";276;1
"Unit";"Zergling";"Larva";276;1
"Unit";"Zergling";"Larva";276;1
"Unit";"Zergling";"Larva";276;1
"Unit";"Zergling";"Larva";276;1
"Unit";"Zergling";"Larva";276;1
"Unit";"Zergling";"Larva";276;1
"Unit";"Zergling";"Larva";276;1
"Unit";"Zergling";"Larva";276;1
"Unit";"Zergling";"Larva";276;1
"Unit";"Zergling";"Larva";276;1
"Unit";"Zergling";"Larva";276;1
"Unit";"Zergling";"Larva";276;1
"Unit";"Zergling";"Larva";276;1
"Unit";"Zergling";"Larva";276;1
"Unit";"Zergling";"Larva";276;1
"Unit";"Zergling";"Larva";276;1
"Unit";"Zergling";"Larva";276;1
"Unit";"Zergling";"Larva";276;1
"Unit";"Zergling";"Larva";276;1
"Unit";"Zergling";"Larva";276;1
"Unit";"Zergling";"Larva";276;1
"Unit";"Zergling";"Larva";276;1
"Unit";"Zergling";"Larva";276;1
"Unit";"Zergling";"Larva";276;1
"Unit";"Zergling";"Larva";276;1
"Unit";"Zergling";"Larva";276;1
"Unit";"Zergling";"Larva";276;1
"Unit";"Zergling";"Larva";276;1
"Unit";"Hydralisk";"Larva";310;2
"Unit";"Hydralisk";"Larva";310;2
"Unit";"Hydralisk";"Larva";310;2
"Unit";"Hydralisk";"Larva";310;2
"Unit";"Hydralisk";"Larva";310;2
"Unit";"Hydralisk";"Larva";310;2
"Unit";"Hydralisk";"Larva";310;2
"Unit";"Hydralisk";"Larva";310;2
"Unit";"Hydralisk";"Larva";310;2
"Unit";"Hydralisk";"Larva";310;2
"Unit";"Hydralisk";"Larva";310;2
"Unit";"Hydralisk";"Larva";310;2
"Unit";"Hydralisk";"Larva";310;2
"Unit";"Hydralisk";"Larva";311;2
"Building";"InfestationPit";NA;310;0
"Unit";"Hydralisk";"Larva";323;2
"Unit";"Hydralisk";"Larva";323;2
"Unit";"Hydralisk";"Larva";323;2
"Unit";"Hydralisk";"Larva";323;2
"Upgrade";"ZergMissileWeaponsLevel1";"EvolutionChamber";276;0
"Unit";"Baneling";"Zergling";341;0
"Unit";"Baneling";"Zergling";341;0
"Unit";"Baneling";"Zergling";341;0
"Unit";"Baneling";"Zergling";341;0
"Unit";"Baneling";"Zergling";341;0
"Unit";"Baneling";"Zergling";341;0
"Unit";"Baneling";"Zergling";341;0
"Unit";"Baneling";"Zergling";341;0
"Unit";"Queen";"Hatchery";323;2
"Unit";"Zergling";"Larva";357;1
"Unit";"Zergling";"Larva";357;1
"Unit";"Zergling";"Larva";357;1
"Unit";"Zergling";"Larva";357;1
"Unit";"Zergling";"Larva";357;1
"Unit";"Zergling";"Larva";357;1
"Unit";"Zergling";"Larva";357;1
"Unit";"Zergling";"Larva";357;1
"Unit";"Zergling";"Larva";357;1
"Unit";"Zergling";"Larva";357;1
"Unit";"Zergling";"Larva";357;1
"Unit";"Zergling";"Larva";357;1
"Unit";"Zergling";"Larva";357;1
"Unit";"Zergling";"Larva";357;1
"Unit";"Zergling";"Larva";357;1
"Unit";"Zergling";"Larva";357;1
"Unit";"Zergling";"Larva";357;1
"Unit";"Zergling";"Larva";357;1
"Unit";"Zergling";"Larva";357;1
"Unit";"Zergling";"Larva";357;1
"Building";"Spire";NA;310;0
"Unit";"Zergling";"Larva";379;1
"Unit";"Zergling";"Larva";379;1
"Unit";"Zergling";"Larva";379;1
"Unit";"Zergling";"Larva";379;1
"Unit";"Zergling";"Larva";379;1
"Unit";"Zergling";"Larva";379;1
"Unit";"Zergling";"Larva";379;1
"Unit";"Zergling";"Larva";379;1
"Unit";"Zergling";"Larva";379;1
"Unit";"Zergling";"Larva";379;1
"Building";"Hatchery";NA;323;0
"Unit";"Mutalisk";"Larva";379;2
"Unit";"Mutalisk";"Larva";379;2
"Unit";"Mutalisk";"Larva";379;2
"Unit";"Mutalisk";"Larva";379;2
"Unit";"Mutalisk";"Larva";379;2
"Unit";"Mutalisk";"Larva";379;2
"Unit";"Zergling";"Larva";379;1
"Unit";"Zergling";"Larva";379;1
"Unit";"Zergling";"Larva";379;1
"Unit";"Zergling";"Larva";379;1
"Unit";"Mutalisk";"Larva";379;2
"Unit";"Zergling";"Larva";379;1
"Unit";"Zergling";"Larva";379;1
"Unit";"Zergling";"Larva";379;1
"Unit";"Zergling";"Larva";379;1
"Unit";"Baneling";"Zergling";389;0
"Unit";"Baneling";"Zergling";389;0
"Unit";"Baneling";"Zergling";389;0
"Unit";"Baneling";"Zergling";389;0
"Unit";"Baneling";"Zergling";389;0
"Unit";"Baneling";"Zergling";389;0
"Unit";"Baneling";"Zergling";389;0
"Unit";"Baneling";"Zergling";389;0
"Unit";"Baneling";"Zergling";389;0
"Unit";"Baneling";"Zergling";389;0
"Building";"Extractor";NA;389;0
"Building";"Extractor";NA;389;0
"Unit";"Baneling";"Zergling";403;0
"Unit";"Baneling";"Zergling";409;0
"Unit";"Baneling";"Zergling";411;0
"Unit";"Baneling";"Zergling";411;0
"Unit";"Baneling";"Zergling";411;0
"Unit";"Baneling";"Zergling";411;0
"Unit";"Baneling";"Zergling";411;0
"Unit";"Baneling";"Zergling";411;0
"Unit";"Baneling";"Zergling";413;0
"Unit";"Baneling";"Zergling";413;0
"Unit";"Baneling";"Zergling";413;0
"Unit";"Hydralisk";"Larva";413;2
"Unit";"Zergling";"Larva";413;1
"Unit";"Zergling";"Larva";413;1
"Unit";"Hydralisk";"Larva";413;2
"Unit";"Hydralisk";"Larva";413;2
"Unit";"Zergling";"Larva";413;1
"Unit";"Zergling";"Larva";413;1
"Unit";"Zergling";"Larva";413;1
"Unit";"Zergling";"Larva";413;1
"Unit";"Zergling";"Larva";413;1
"Unit";"Zergling";"Larva";413;1
"Unit";"Zergling";"Larva";413;1
"Unit";"Zergling";"Larva";413;1
"Unit";"Zergling";"Larva";413;1
"Unit";"Zergling";"Larva";413;1
"Unit";"Zergling";"Larva";413;1
"Unit";"Zergling";"Larva";413;1
"Unit";"Zergling";"Larva";413;1
"Unit";"Zergling";"Larva";413;1
"Unit";"Zergling";"Larva";413;1
"Unit";"Zergling";"Larva";413;1
"Unit";"Zergling";"Larva";413;1
"Unit";"Zergling";"Larva";413;1
"Unit";"Zergling";"Larva";413;1
"Unit";"Zergling";"Larva";413;1
"Unit";"Zergling";"Larva";413;1
"Unit";"Zergling";"Larva";413;1
"Building";"SpineCrawler";NA;419;0
"Building";"SpineCrawler";NA;419;0
"Unit";"Zergling";"Larva";449;1
"Unit";"Zergling";"Larva";449;1
"Unit";"Zergling";"Larva";449;1
"Unit";"Zergling";"Larva";449;1
"Unit";"Zergling";"Larva";449;1
"Unit";"Zergling";"Larva";449;1
"Unit";"Zergling";"Larva";449;1
"Unit";"Zergling";"Larva";449;1
"Unit";"Zergling";"Larva";449;1
"Unit";"Zergling";"Larva";449;1
"Unit";"Zergling";"Larva";449;1
"Unit";"Zergling";"Larva";449;1
"Unit";"Zergling";"Larva";449;1
"Unit";"Zergling";"Larva";449;1
"Unit";"Zergling";"Larva";449;1
"Unit";"Zergling";"Larva";449;1
"Unit";"Zergling";"Larva";449;1
"Unit";"Zergling";"Larva";449;1
"Unit";"Zergling";"Larva";449;1
"Unit";"Zergling";"Larva";449;1
"Unit";"Zergling";"Larva";449;1
"Unit";"Zergling";"Larva";449;1
"Unit";"Zergling";"Larva";449;1
"Unit";"Zergling";"Larva";449;1
"Unit";"Zergling";"Larva";449;1
"Unit";"Zergling";"Larva";449;1
"Unit";"Zergling";"Larva";449;1
"Unit";"Zergling";"Larva";449;1
"Unit";"Zergling";"Larva";449;1
"Unit";"Zergling";"Larva";449;1
"Unit";"Zergling";"Larva";449;1
"Unit";"Zergling";"Larva";449;1
"Unit";"Zergling";"Larva";449;1
"Unit";"Zergling";"Larva";449;1
"Unit";"Baneling";"Zergling";481;0
"Unit";"Baneling";"Zergling";481;0
"Unit";"Baneling";"Zergling";481;0
"Unit";"Baneling";"Zergling";481;0
"Unit";"Baneling";"Zergling";481;0
"Unit";"Baneling";"Zergling";481;0
"Unit";"Baneling";"Zergling";481;0
"Unit";"Baneling";"Zergling";481;0
"Unit";"Baneling";"Zergling";481;0
"Unit";"Baneling";"Zergling";481;0
"Unit";"Baneling";"Zergling";481;0
"Unit";"Baneling";"Zergling";481;0
"Unit";"Baneling";"Zergling";481;0
"Unit";"Baneling";"Zergling";481;0
"Unit";"Baneling";"Zergling";481;0
"Unit";"Baneling";"Zergling";481;0
"Unit";"Baneling";"Zergling";481;0
"Unit";"Baneling";"Zergling";481;0
"Unit";"Baneling";"Zergling";481;0
"Unit";"Baneling";"Zergling";481;0
"Unit";"Baneling";"Zergling";481;0
"Unit";"Baneling";"Zergling";481;0
"Unit";"Baneling";"Zergling";481;0
"Unit";"Baneling";"Zergling";481;0
"Unit";"Zergling";"Larva";481;1
"Unit";"Zergling";"Larva";481;1
"Unit";"Zergling";"Larva";483;1
"Unit";"Zergling";"Larva";483;1
"Unit";"Zergling";"Larva";483;1
"Unit";"Zergling";"Larva";483;1
"Unit";"Zergling";"Larva";483;1
"Unit";"Zergling";"Larva";483;1
"Unit";"Corruptor";"Larva";491;2
"Unit";"Corruptor";"Larva";491;2
"Unit";"Corruptor";"Larva";491;2
"Building";"Extractor";NA;502;0
"Building";"CreepTumor";NA;502;0
"Unit";"Corruptor";"Larva";502;2
"Unit";"Corruptor";"Larva";502;2
"Unit";"Corruptor";"Larva";502;2
"Unit";"Corruptor";"Larva";502;2
"Unit";"Corruptor";"Larva";502;2
"Unit";"Corruptor";"Larva";502;2
"Unit";"Overlord";"Larva";508;0
"Unit";"Overlord";"Larva";508;0
"Unit";"Corruptor";"Larva";502;2
"Unit";"Corruptor";"Larva";502;2
"Unit";"Corruptor";"Larva";502;2
"Unit";"Corruptor";"Larva";520;2
"Unit";"Corruptor";"Larva";520;2
"Building";"Hatchery";NA;502;0
"Unit";"Zergling";"Larva";526;1
"Unit";"Zergling";"Larva";526;1
"Unit";"Zergling";"Larva";526;1
"Unit";"Zergling";"Larva";526;1
"Unit";"Zergling";"Larva";526;1
"Unit";"Zergling";"Larva";526;1
"Unit";"Zergling";"Larva";526;1
"Unit";"Zergling";"Larva";526;1
"Unit";"Zergling";"Larva";526;1
"Unit";"Zergling";"Larva";526;1
"Unit";"Zergling";"Larva";526;1
"Unit";"Zergling";"Larva";526;1
"Unit";"Zergling";"Larva";526;1
"Unit";"Zergling";"Larva";526;1
"Unit";"Zergling";"Larva";526;1
"Unit";"Zergling";"Larva";526;1
"Unit";"Zergling";"Larva";526;1
"Unit";"Zergling";"Larva";526;1
"Unit";"Zergling";"Larva";526;1
"Unit";"Zergling";"Larva";526;1
"Unit";"Zergling";"Larva";526;1
"Unit";"Zergling";"Larva";526;1
"Unit";"Zergling";"Larva";526;1
"Unit";"Zergling";"Larva";526;1
"Unit";"Zergling";"Larva";526;1
"Unit";"Zergling";"Larva";526;1
"Unit";"Zergling";"Larva";526;1
"Unit";"Zergling";"Larva";526;1
"Unit";"Zergling";"Larva";526;1
"Unit";"Zergling";"Larva";526;1
"Unit";"Zergling";"Larva";526;1
"Unit";"Zergling";"Larva";526;1
"Unit";"Zergling";"Larva";526;1
"Unit";"Zergling";"Larva";526;1
"Building";"Hatchery";NA;502;0
"Building";"Hatchery";NA;502;0
"Unit";"Corruptor";"Larva";564;2
"Unit";"Corruptor";"Larva";564;2
"Unit";"Hydralisk";"Larva";564;2
"Unit";"Hydralisk";"Larva";564;2
"Unit";"Hydralisk";"Larva";564;2
"Unit";"Hydralisk";"Larva";564;2
"Unit";"Hydralisk";"Larva";564;2
"Upgrade";"ZergMeleeWeaponsLevel3";"EvolutionChamber";502;0
"Unit";"Corruptor";"Larva";564;2
"Unit";"Corruptor";"Larva";564;2
"Unit";"Hydralisk";"Larva";568;2
"Unit";"Hydralisk";"Larva";568;2
"Unit";"Hydralisk";"Larva";578;2
"Unit";"Hydralisk";"Larva";578;2
"Unit";"Hydralisk";"Larva";578;2
"Unit";"Hydralisk";"Larva";578;2
"Unit";"Zergling";"Larva";582;1
"Unit";"Zergling";"Larva";582;1
"Unit";"Zergling";"Larva";582;1
"Unit";"Zergling";"Larva";582;1
"Unit";"Hydralisk";"Larva";582;2
"Unit";"Hydralisk";"Larva";582;2
"Unit";"Hydralisk";"Larva";582;2
"Unit";"Hydralisk";"Larva";582;2
"Unit";"Hydralisk";"Larva";582;2
