"type";"unit_name";"on_building";"total_supply";"supply"
"Unit";"Overlord";"Larva";13;0
"Building";"Extractor";NA;16;0
"Building";"SpawningPool";NA;17;0
"Unit";"Zergling";"Larva";19;1
"Unit";"Zergling";"Larva";19;1
"Unit";"Zergling";"Larva";19;1
"Unit";"Zergling";"Larva";19;1
"Unit";"Zergling";"Larva";19;1
"Unit";"Zergling";"Larva";19;1
"Unit";"Queen";"Hatchery";19;2
"Building";"Hatchery";NA;19;0
"Unit";"Overlord";"Larva";29;0
"Unit";"Overlord";"Larva";29;0
"Building";"RoachWarren";NA;26;0
"Unit";"Roach";"Larva";29;2
"Unit";"Roach";"Larva";29;2
"Unit";"Roach";"Larva";29;2
"Unit";"Roach";"Larva";29;2
"Unit";"Zergling";"Larva";29;1
"Unit";"Zergling";"Larva";29;1
"Unit";"Zergling";"Larva";29;1
"Unit";"Zergling";"Larva";29;1
"Unit";"Zergling";"Larva";29;1
"Unit";"Zergling";"Larva";29;1
"Unit";"Zergling";"Larva";29;1
"Unit";"Zergling";"Larva";29;1
"Unit";"Roach";"Larva";29;2
"Unit";"Zergling";"Larva";37;1
"Unit";"Zergling";"Larva";37;1
"Unit";"Roach";"Larva";35;2
"Building";"CreepTumorQueen";NA;47;0
"Unit";"Overlord";"Larva";47;0
"Unit";"Zergling";"Larva";47;1
"Unit";"Zergling";"Larva";47;1
"Unit";"Zergling";"Larva";51;1
"Unit";"Zergling";"Larva";51;1
"Unit";"Zergling";"Larva";51;1
"Unit";"Zergling";"Larva";51;1
"Building";"CreepTumor";NA;53;0
"Unit";"Zergling";"Larva";53;1
"Unit";"Zergling";"Larva";53;1
"Unit";"Zergling";"Larva";53;1
"Unit";"Zergling";"Larva";53;1
"Unit";"Zergling";"Larva";53;1
"Unit";"Zergling";"Larva";53;1
"Unit";"Zergling";"Larva";53;1
"Unit";"Zergling";"Larva";53;1
"Unit";"Zergling";"Larva";53;1
"Unit";"Zergling";"Larva";53;1
"Unit";"Zergling";"Larva";67;1
"Unit";"Zergling";"Larva";67;1
"Unit";"Zergling";"Larva";67;1
"Unit";"Zergling";"Larva";67;1
"Unit";"Zergling";"Larva";67;1
"Unit";"Zergling";"Larva";67;1
"Unit";"Zergling";"Larva";67;1
"Unit";"Zergling";"Larva";67;1
"Unit";"Zergling";"Larva";67;1
"Unit";"Zergling";"Larva";67;1
"Unit";"Zergling";"Larva";67;1
"Unit";"Zergling";"Larva";67;1
"Unit";"Zergling";"Larva";67;1
"Unit";"Zergling";"Larva";67;1
"Unit";"Zergling";"Larva";77;1
"Unit";"Zergling";"Larva";77;1
"Unit";"Zergling";"Larva";77;1
"Unit";"Zergling";"Larva";77;1
"Unit";"Queen";"Hatchery";81;2
"Building";"SporeCrawler";NA;91;0
"Building";"SporeCrawler";NA;93;0
"Building";"CreepTumor";NA;95;0
"Building";"CreepTumorQueen";NA;100;0
"Building";"CreepTumor";NA;100;0
"Unit";"Queen";"Hatchery";100;2
"Building";"SporeCrawler";NA;100;0
"Unit";"Queen";"Hatchery";100;2
"Unit";"Overlord";"Larva";105;0
"Building";"CreepTumor";NA;109;0
"Unit";"Overlord";"Larva";109;0
"Building";"CreepTumor";NA;109;0
"Building";"CreepTumorQueen";NA;109;0
"Unit";"Queen";"Hatchery";109;2
"Building";"CreepTumorQueen";NA;116;0
"Building";"Hatchery";NA;105;0
"Building";"SporeCrawler";NA;118;0
"Building";"Extractor";NA;118;0
"Unit";"Queen";"Hatchery";116;2
"Building";"CreepTumor";NA;136;0
"Building";"CreepTumor";NA;136;0
"Building";"CreepTumor";NA;136;0
"Building";"Extractor";NA;126;0
"Unit";"Overlord";"Larva";136;0
"Building";"HydraliskDen";NA;126;0
"Unit";"Queen";"Hatchery";124;2
"Unit";"Overlord";"Larva";136;0
"Unit";"Overlord";"Larva";136;0
"Building";"CreepTumor";NA;141;0
"Building";"CreepTumor";NA;141;0
"Building";"CreepTumor";NA;141;0
"Building";"Extractor";NA;141;0
"Building";"Extractor";NA;141;0
"Building";"EvolutionChamber";NA;141;0
"Building";"EvolutionChamber";NA;141;0
"Unit";"Hydralisk";"Larva";141;2
"Building";"CreepTumorQueen";NA;147;0
"Unit";"Hydralisk";"Larva";141;2
"Building";"CreepTumor";NA;147;0
"Unit";"Queen";"Hatchery";136;2
"Unit";"Hydralisk";"Larva";141;2
"Unit";"Hydralisk";"Larva";141;2
"Unit";"Hydralisk";"Larva";141;2
"Unit";"Hydralisk";"Larva";141;2
"Unit";"Overlord";"Larva";147;0
"Upgrade";"GlialReconstitution";"RoachWarren";136;0
"Building";"CreepTumor";NA;162;0
"Building";"CreepTumor";NA;168;0
"Building";"CreepTumor";NA;168;0
"Unit";"Roach";"Larva";162;2
"Unit";"Roach";"Larva";162;2
"Unit";"Roach";"Larva";162;2
"Unit";"Roach";"Larva";162;2
"Building";"CreepTumorQueen";NA;168;0
"Upgrade";"EvolveMuscularAugments";"HydraliskDen";147;0
"Unit";"Overlord";"Larva";168;0
"Unit";"Overlord";"Larva";168;0
"Building";"CreepTumorQueen";NA;176;0
"Building";"CreepTumor";NA;176;0
"Building";"CreepTumorQueen";NA;176;0
"Unit";"Overlord";"Larva";176;0
"Unit";"Overlord";"Larva";176;0
"Unit";"Overlord";"Larva";176;0
"Unit";"Roach";"Larva";176;2
"Unit";"Roach";"Larva";176;2
"Unit";"Roach";"Larva";176;2
"Unit";"Roach";"Larva";176;2
"Unit";"Roach";"Larva";176;2
"Unit";"Roach";"Larva";176;2
"Unit";"Roach";"Larva";176;2
"Unit";"Roach";"Larva";176;2
"Building";"CreepTumor";NA;176;0
"Building";"CreepTumor";NA;176;0
"Building";"Extractor";NA;176;0
"Building";"CreepTumor";NA;192;0
"Building";"CreepTumor";NA;192;0
"Building";"CreepTumor";NA;192;0
"Building";"CreepTumorQueen";NA;192;0
"Unit";"Roach";"Larva";192;2
"Unit";"Roach";"Larva";192;2
"Unit";"Roach";"Larva";192;2
"Unit";"Roach";"Larva";192;2
"Unit";"Roach";"Larva";192;2
"Building";"CreepTumor";NA;192;0
"Building";"CreepTumor";NA;192;0
"Building";"CreepTumor";NA;198;0
"Building";"Hatchery";NA;168;0
"Unit";"Overlord";"Larva";198;0
"Unit";"Overlord";"Larva";198;0
"Upgrade";"ZergMissileWeaponsLevel1";"EvolutionChamber";168;0
"Building";"Extractor";NA;208;0
"Building";"Extractor";NA;208;0
"Upgrade";"EvolveGroovedSpines";"HydraliskDen";192;0
"Building";"CreepTumor";NA;208;0
"Building";"CreepTumor";NA;208;0
"Building";"CreepTumor";NA;208;0
"Building";"CreepTumor";NA;211;0
"Building";"CreepTumor";NA;214;0
"Building";"CreepTumor";NA;214;0
"Building";"CreepTumor";NA;217;0
"Building";"CreepTumor";NA;217;0
"Building";"CreepTumor";NA;217;0
"Unit";"Overlord";"Larva";217;0
"Unit";"Overlord";"Larva";217;0
"Unit";"Overlord";"Larva";217;0
"Building";"CreepTumorQueen";NA;217;0
"Building";"CreepTumorQueen";NA;220;0
"Building";"CreepTumor";NA;219;0
"Building";"Extractor";NA;217;0
"Building";"CreepTumor";NA;220;0
"Building";"CreepTumor";NA;220;0
"Building";"Extractor";NA;217;0
"Building";"CreepTumor";NA;223;0
"Building";"SporeCrawler";NA;220;0
"Building";"Spire";NA;208;0
"Building";"Spire";NA;208;0
"Building";"CreepTumorQueen";NA;226;0
"Building";"CreepTumor";NA;226;0
"Building";"CreepTumor";NA;226;0
"Building";"CreepTumorQueen";NA;226;0
"Building";"CreepTumorQueen";NA;226;0
"Building";"CreepTumor";NA;226;0
"Building";"CreepTumor";NA;226;0
"Building";"CreepTumor";NA;226;0
"Building";"Hatchery";NA;217;0
"Building";"CreepTumorQueen";NA;226;0
"Building";"CreepTumorQueen";NA;226;0
"Unit";"Corruptor";"Larva";226;2
"Unit";"Corruptor";"Larva";226;2
"Unit";"Corruptor";"Larva";226;2
"Unit";"Corruptor";"Larva";226;2
"Unit";"Corruptor";"Larva";226;2
"Unit";"Corruptor";"Larva";226;2
"Unit";"Corruptor";"Larva";226;2
"Unit";"Corruptor";"Larva";226;2
"Unit";"Corruptor";"Larva";226;2
"Unit";"Corruptor";"Larva";226;2
"Unit";"Corruptor";"Larva";226;2
"Building";"CreepTumorQueen";NA;226;0
"Building";"CreepTumorQueen";NA;226;0
"Building";"CreepTumor";NA;226;0
"Building";"CreepTumorQueen";NA;226;0
"Building";"CreepTumorQueen";NA;226;0
"Building";"CreepTumorQueen";NA;226;0
"Building";"CreepTumor";NA;226;0
"Building";"CreepTumorQueen";NA;226;0
"Building";"CreepTumorQueen";NA;226;0
"Building";"CreepTumorQueen";NA;248;0
"Building";"CreepTumor";NA;248;0
"Unit";"Corruptor";"Larva";226;2
"Building";"CreepTumorQueen";NA;248;0
"Unit";"Corruptor";"Larva";226;2
"Unit";"Corruptor";"Larva";226;2
"Building";"CreepTumorQueen";NA;248;0
"Building";"CreepTumor";NA;248;0
"Building";"CreepTumor";NA;248;0
"Building";"CreepTumor";NA;248;0
"Unit";"Corruptor";"Larva";226;2
"Unit";"Corruptor";"Larva";226;2
"Building";"CreepTumor";NA;254;0
"Building";"CreepTumor";NA;254;0
"Building";"CreepTumor";NA;254;0
"Building";"CreepTumor";NA;254;0
"Building";"CreepTumor";NA;254;0
"Building";"CreepTumorQueen";NA;254;0
"Unit";"Corruptor";"Larva";248;2
"Unit";"Corruptor";"Larva";248;2
"Building";"CreepTumorQueen";NA;256;0
"Building";"CreepTumorQueen";NA;258;0
"Building";"CreepTumorQueen";NA;258;0
"Building";"CreepTumorQueen";NA;258;0
"Building";"CreepTumorQueen";NA;258;0
"Building";"CreepTumorQueen";NA;258;0
"Building";"CreepTumorQueen";NA;258;0
"Building";"CreepTumorQueen";NA;262;0
"Building";"CreepTumorQueen";NA;262;0
"Building";"CreepTumorQueen";NA;262;0
"Building";"CreepTumorQueen";NA;262;0
"Building";"CreepTumorQueen";NA;262;0
"Building";"CreepTumorQueen";NA;262;0
"Unit";"Corruptor";"Larva";258;2
"Unit";"Corruptor";"Larva";258;2
"Unit";"Corruptor";"Larva";258;2
"Unit";"Corruptor";"Larva";258;2
"Unit";"Corruptor";"Larva";258;2
"Unit";"Corruptor";"Larva";258;2
"Building";"InfestationPit";NA;256;0
"Building";"CreepTumor";NA;262;0
"Building";"CreepTumor";NA;262;0
"Building";"CreepTumor";NA;262;0
"Building";"CreepTumor";NA;262;0
"Building";"CreepTumor";NA;262;0
"Building";"CreepTumor";NA;262;0
"Unit";"Overlord";"Larva";262;0
"Building";"CreepTumor";NA;262;0
"Building";"CreepTumor";NA;262;0
"Unit";"Overlord";"Larva";262;0
"Unit";"Overlord";"Larva";262;0
"Building";"CreepTumor";NA;274;0
"Building";"CreepTumor";NA;274;0
"Unit";"Corruptor";"Larva";262;2
"Building";"CreepTumor";NA;274;0
"Building";"CreepTumor";NA;274;0
"Building";"CreepTumor";NA;274;0
"Building";"CreepTumor";NA;274;0
"Building";"CreepTumor";NA;274;0
"Building";"CreepTumor";NA;274;0
"Building";"Hatchery";NA;248;0
"Building";"Extractor";NA;274;0
"Building";"CreepTumorQueen";NA;276;0
"Building";"Extractor";NA;274;0
"Building";"CreepTumorQueen";NA;276;0
"Building";"CreepTumorQueen";NA;276;0
"Building";"CreepTumorQueen";NA;276;0
"Unit";"Corruptor";"Larva";276;2
"Unit";"Corruptor";"Larva";276;2
"Unit";"Corruptor";"Larva";276;2
"Unit";"Corruptor";"Larva";276;2
"Unit";"Corruptor";"Larva";276;2
"Unit";"Corruptor";"Larva";276;2
"Unit";"Corruptor";"Larva";276;2
"Unit";"Corruptor";"Larva";276;2
"Building";"CreepTumor";NA;276;0
"Building";"CreepTumor";NA;276;0
"Building";"CreepTumor";NA;276;0
"Building";"CreepTumor";NA;276;0
"Building";"CreepTumor";NA;276;0
"Building";"CreepTumor";NA;276;0
"Building";"CreepTumor";NA;276;0
"Building";"CreepTumor";NA;276;0
"Building";"CreepTumor";NA;276;0
"Building";"CreepTumor";NA;276;0
"Building";"CreepTumor";NA;276;0
"Unit";"Corruptor";"Larva";276;2
"Unit";"Corruptor";"Larva";276;2
"Unit";"Corruptor";"Larva";276;2
"Building";"CreepTumor";NA;296;0
"Building";"CreepTumor";NA;296;0
"Building";"CreepTumor";NA;296;0
