"type";"unit_name";"on_building";"total_supply";"supply"
"Unit";"Overlord";"Larva";13;0
"Building";"Extractor";NA;19;0
"Building";"SpawningPool";NA;19;0
"Unit";"Overlord";"Larva";22;0
"Building";"Hatchery";NA;17;0
"Unit";"Queen";"Hatchery";22;2
"Unit";"Queen";"Hatchery";25;2
"Unit";"Overlord";"Larva";32;0
"Building";"Hatchery";NA;23;0
"Building";"SporeCrawler";NA;37;0
"Unit";"Queen";"Hatchery";34;2
"Building";"SporeCrawler";NA;38;0
"Unit";"Zergling";"Larva";43;1
"Unit";"Zergling";"Larva";43;1
"Unit";"Zergling";"Larva";43;1
"Unit";"Zergling";"Larva";43;1
"Unit";"Zergling";"Larva";43;1
"Unit";"Zergling";"Larva";43;1
"Unit";"Zergling";"Larva";44;1
"Unit";"Zergling";"Larva";44;1
"Building";"CreepTumorQueen";NA;46;0
"Building";"Extractor";NA;46;0
"Building";"Extractor";NA;46;0
"Unit";"Overlord";"Larva";57;0
"Unit";"Overlord";"Larva";57;0
"Unit";"Overlord";"Larva";57;0
"Building";"RoachWarren";NA;46;0
"Unit";"Overlord";"Larva";57;0
"Unit";"Overlord";"Larva";57;0
"Building";"SporeCrawler";NA;57;0
"Building";"CreepTumor";NA;61;0
"Building";"CreepTumorQueen";NA;68;0
"Building";"Extractor";NA;63;0
"Building";"EvolutionChamber";NA;62;0
"Building";"HydraliskDen";NA;62;0
"Building";"CreepTumor";NA;72;0
"Building";"CreepTumor";NA;73;0
"Building";"Extractor";NA;82;0
"Building";"CreepTumor";NA;88;0
"Unit";"Hydralisk";"Larva";87;2
"Unit";"Hydralisk";"Larva";87;2
"Unit";"Hydralisk";"Larva";88;2
"Unit";"Hydralisk";"Larva";88;2
"Unit";"Overlord";"Larva";88;0
"Unit";"Overlord";"Larva";88;0
"Unit";"Overlord";"Larva";88;0
"Unit";"Overlord";"Larva";88;0
"Unit";"Overlord";"Larva";88;0
"Unit";"Hydralisk";"Larva";90;2
"Unit";"Hydralisk";"Larva";90;2
"Unit";"Hydralisk";"Larva";90;2
"Upgrade";"EvolveGroovedSpines";"HydraliskDen";83;0
"Building";"CreepTumor";NA;96;0
"Unit";"Hydralisk";"Larva";96;2
"Unit";"Hydralisk";"Larva";96;2
"Unit";"Hydralisk";"Larva";96;2
"Unit";"Hydralisk";"Larva";96;2
"Unit";"Hydralisk";"Larva";96;2
"Unit";"Hydralisk";"Larva";96;2
"Unit";"Hydralisk";"Larva";96;2
"Unit";"Hydralisk";"Larva";96;2
"Unit";"Hydralisk";"Larva";96;2
"Unit";"Overlord";"Larva";102;0
"Unit";"Hydralisk";"Larva";102;2
"Unit";"Hydralisk";"Larva";102;2
"Unit";"Hydralisk";"Larva";110;2
"Unit";"Hydralisk";"Larva";110;2
"Unit";"Hydralisk";"Larva";110;2
"Unit";"Hydralisk";"Larva";110;2
"Unit";"Overlord";"Larva";114;0
"Unit";"Hydralisk";"Larva";114;2
"Unit";"Hydralisk";"Larva";114;2
"Unit";"Zergling";"Larva";124;1
"Unit";"Zergling";"Larva";124;1
"Unit";"Zergling";"Larva";124;1
"Unit";"Zergling";"Larva";124;1
"Unit";"Zergling";"Larva";124;1
"Unit";"Zergling";"Larva";124;1
"Unit";"Zergling";"Larva";124;1
"Unit";"Zergling";"Larva";124;1
"Upgrade";"ZergMissileWeaponsLevel1";"EvolutionChamber";88;0
"Unit";"Hydralisk";"Larva";122;2
"Building";"CreepTumor";NA;132;0
"Unit";"Hydralisk";"Larva";128;2
"Unit";"Hydralisk";"Larva";128;2
"Unit";"Zergling";"Larva";136;1
"Unit";"Zergling";"Larva";136;1
"Unit";"Hydralisk";"Larva";134;2
"Unit";"Hydralisk";"Larva";136;2
"Unit";"Hydralisk";"Larva";136;2
"Unit";"Hydralisk";"Larva";136;2
"Unit";"Zergling";"Larva";146;1
"Unit";"Zergling";"Larva";146;1
"Unit";"Zergling";"Larva";146;1
"Unit";"Zergling";"Larva";146;1
"Unit";"Zergling";"Larva";146;1
"Unit";"Zergling";"Larva";146;1
"Unit";"Overlord";"Larva";146;0
"Unit";"Overlord";"Larva";146;0
"Upgrade";"EvolveMuscularAugments";"HydraliskDen";120;0
"Unit";"Hydralisk";"Larva";152;2
"Unit";"Hydralisk";"Larva";152;2
"Unit";"Hydralisk";"Larva";152;2
"Unit";"Hydralisk";"Larva";166;2
"Unit";"Hydralisk";"Larva";166;2
"Unit";"Hydralisk";"Larva";166;2
"Unit";"Zergling";"Larva";172;1
"Unit";"Zergling";"Larva";172;1
"Unit";"Zergling";"Larva";172;1
"Unit";"Zergling";"Larva";172;1
"Unit";"Zergling";"Larva";172;1
"Unit";"Zergling";"Larva";172;1
"Unit";"Zergling";"Larva";172;1
"Unit";"Zergling";"Larva";172;1
"Unit";"Zergling";"Larva";172;1
"Unit";"Zergling";"Larva";172;1
"Unit";"Zergling";"Larva";172;1
"Unit";"Zergling";"Larva";172;1
"Unit";"Zergling";"Larva";172;1
"Unit";"Zergling";"Larva";172;1
"Unit";"Zergling";"Larva";172;1
"Unit";"Zergling";"Larva";172;1
"Unit";"Zergling";"Larva";172;1
"Unit";"Zergling";"Larva";172;1
"Unit";"Zergling";"Larva";172;1
"Unit";"Zergling";"Larva";172;1
"Unit";"Hydralisk";"Larva";200;2
"Unit";"Hydralisk";"Larva";200;2
"Unit";"Hydralisk";"Larva";200;2
"Unit";"Hydralisk";"Larva";200;2
"Unit";"Zergling";"Larva";204;1
"Unit";"Zergling";"Larva";204;1
"Unit";"Zergling";"Larva";204;1
"Unit";"Zergling";"Larva";204;1
"Unit";"Zergling";"Larva";204;1
"Unit";"Zergling";"Larva";204;1
"Upgrade";"ZergMeleeWeaponsLevel1";"EvolutionChamber";166;0
"Building";"CreepTumor";NA;226;0
"Unit";"Hydralisk";"Larva";226;2
"Unit";"Hydralisk";"Larva";226;2
"Unit";"Hydralisk";"Larva";226;2
"Unit";"Hydralisk";"Larva";226;2
"Unit";"Hydralisk";"Larva";226;2
"Unit";"Hydralisk";"Larva";226;2
"Unit";"Hydralisk";"Larva";226;2
"Unit";"Hydralisk";"Larva";226;2
"Unit";"Hydralisk";"Larva";226;2
"Unit";"Hydralisk";"Larva";226;2
"Unit";"Hydralisk";"Larva";226;2
"Unit";"Hydralisk";"Larva";226;2
"Unit";"Hydralisk";"Larva";226;2
"Unit";"Hydralisk";"Larva";226;2
"Building";"CreepTumor";NA;234;0
"Building";"Hatchery";NA;226;0
"Upgrade";"GlialReconstitution";"RoachWarren";234;0
"Building";"CreepTumor";NA;264;0
"Unit";"Roach";"Larva";264;2
"Unit";"Roach";"Larva";264;2
"Unit";"Roach";"Larva";264;2
"Unit";"Roach";"Larva";264;2
"Unit";"Roach";"Larva";264;2
"Unit";"Roach";"Larva";264;2
"Unit";"Roach";"Larva";264;2
"Unit";"Roach";"Larva";264;2
"Unit";"Roach";"Larva";264;2
"Unit";"Roach";"Larva";264;2
"Unit";"Roach";"Larva";264;2
"Building";"Extractor";NA;264;0
"Unit";"Hydralisk";"Larva";264;2
"Unit";"Overlord";"Larva";264;0
"Unit";"Hydralisk";"Larva";264;2
"Unit";"Hydralisk";"Larva";264;2
"Unit";"Hydralisk";"Larva";264;2
"Unit";"Roach";"Larva";286;2
"Unit";"Roach";"Larva";286;2
"Unit";"Roach";"Larva";286;2
"Unit";"Overlord";"Larva";286;0
"Building";"CreepTumor";NA;286;0
"Building";"Hatchery";NA;254;0
"Unit";"Roach";"Larva";294;2
"Unit";"Roach";"Larva";294;2
"Unit";"Roach";"Larva";294;2
"Unit";"Roach";"Larva";294;2
"Unit";"Roach";"Larva";294;2
"Upgrade";"ZergMissileWeaponsLevel2";"EvolutionChamber";254;0
"Unit";"Roach";"Larva";300;2
"Unit";"Roach";"Larva";300;2
"Unit";"Roach";"Larva";300;2
"Unit";"Roach";"Larva";300;2
"Building";"CreepTumor";NA;310;0
"Unit";"Roach";"Larva";312;2
"Unit";"Roach";"Larva";318;2
"Building";"InfestationPit";NA;308;0
