"type";"unit_name";"on_building";"total_supply";"supply"
"Unit";"Overlord";"Larva";13;0
"Building";"Extractor";NA;19;0
"Unit";"Overlord";"Larva";22;0
"Building";"SpawningPool";NA;19;0
"Building";"Hatchery";NA;17;0
"Unit";"Zergling";"Larva";22;1
"Unit";"Zergling";"Larva";22;1
"Unit";"Zergling";"Larva";22;1
"Unit";"Zergling";"Larva";22;1
"Unit";"Queen";"Hatchery";22;2
"Unit";"Queen";"Hatchery";23;2
"Building";"CreepTumorQueen";NA;35;0
"Unit";"Overlord";"Larva";37;0
"Unit";"Queen";"Hatchery";33;2
"Building";"CreepTumorQueen";NA;42;0
"Building";"CreepTumor";NA;42;0
"Unit";"Overlord";"Larva";47;0
"Building";"SporeCrawler";NA;47;0
"Building";"SporeCrawler";NA;47;0
"Unit";"Queen";"Hatchery";41;2
"Unit";"Overlord";"Larva";47;0
"Building";"CreepTumorQueen";NA;50;0
"Building";"CreepTumor";NA;50;0
"Building";"CreepTumor";NA;53;0
"Building";"Extractor";NA;53;0
"Unit";"Zergling";"Larva";53;1
"Unit";"Zergling";"Larva";53;1
"Unit";"Zergling";"Larva";53;1
"Unit";"Zergling";"Larva";53;1
"Unit";"Zergling";"Larva";53;1
"Unit";"Zergling";"Larva";53;1
"Unit";"Zergling";"Larva";58;1
"Unit";"Zergling";"Larva";58;1
"Unit";"Zergling";"Larva";58;1
"Unit";"Zergling";"Larva";58;1
"Unit";"Zergling";"Larva";58;1
"Unit";"Zergling";"Larva";58;1
"Unit";"Zergling";"Larva";58;1
"Unit";"Zergling";"Larva";58;1
"Unit";"Queen";"Hatchery";53;2
"Building";"CreepTumor";NA;64;0
"Building";"CreepTumor";NA;64;0
"Unit";"Overlord";"Larva";58;0
"Building";"CreepTumor";NA;64;0
"Building";"RoachWarren";NA;53;0
"Building";"CreepTumorQueen";NA;64;0
"Building";"CreepTumorQueen";NA;72;0
"Building";"CreepTumorQueen";NA;72;0
"Building";"CreepTumorQueen";NA;72;0
"Building";"CreepTumor";NA;74;0
"Building";"CreepTumor";NA;74;0
"Building";"Hatchery";NA;50;0
"Building";"Extractor";NA;74;0
"Building";"Extractor";NA;74;0
"Building";"CreepTumor";NA;83;0
"Building";"CreepTumor";NA;83;0
"Building";"CreepTumor";NA;83;0
"Building";"CreepTumor";NA;83;0
"Building";"CreepTumorQueen";NA;83;0
"Building";"CreepTumorQueen";NA;88;0
"Building";"CreepTumorQueen";NA;88;0
"Building";"CreepTumor";NA;89;0
"Building";"CreepTumor";NA;89;0
"Unit";"Overlord";"Larva";88;0
"Unit";"Overlord";"Larva";88;0
"Building";"CreepTumorQueen";NA;89;0
"Unit";"Queen";"Hatchery";83;2
"Building";"CreepTumor";NA;89;0
"Building";"CreepTumorQueen";NA;89;0
"Unit";"Overlord";"Larva";89;0
"Building";"HydraliskDen";NA;88;0
"Unit";"Overlord";"Larva";95;0
"Unit";"Overlord";"Larva";95;0
"Building";"CreepTumor";NA;97;0
"Building";"CreepTumor";NA;97;0
"Building";"CreepTumor";NA;97;0
"Building";"CreepTumor";NA;98;0
"Building";"SpineCrawler";NA;89;0
"Building";"CreepTumor";NA;98;0
"Building";"EvolutionChamber";NA;95;0
"Building";"EvolutionChamber";NA;95;0
"Building";"CreepTumor";NA;100;0
"Building";"CreepTumor";NA;100;0
"Building";"CreepTumorQueen";NA;100;0
"Building";"CreepTumor";NA;100;0
"Building";"CreepTumor";NA;100;0
"Building";"CreepTumor";NA;100;0
"Building";"CreepTumorQueen";NA;100;0
"Unit";"Hydralisk";"Larva";98;2
"Unit";"Hydralisk";"Larva";98;2
"Unit";"Hydralisk";"Larva";98;2
"Unit";"Hydralisk";"Larva";98;2
"Unit";"Hydralisk";"Larva";98;2
"Unit";"Overlord";"Larva";100;0
"Unit";"Overlord";"Larva";100;0
"Building";"CreepTumor";NA;100;0
"Building";"CreepTumor";NA;100;0
"Building";"CreepTumor";NA;100;0
"Building";"CreepTumor";NA;100;0
"Building";"CreepTumor";NA;100;0
"Building";"CreepTumor";NA;100;0
"Building";"CreepTumor";NA;110;0
"Upgrade";"GlialReconstitution";"RoachWarren";93;0
"Building";"CreepTumor";NA;115;0
"Building";"CreepTumor";NA;115;0
"Building";"CreepTumorQueen";NA;115;0
"Unit";"Hydralisk";"Larva";115;2
"Unit";"Hydralisk";"Larva";115;2
"Unit";"Hydralisk";"Larva";115;2
"Unit";"Hydralisk";"Larva";115;2
"Unit";"Hydralisk";"Larva";115;2
"Unit";"Overlord";"Larva";115;0
"Unit";"Overlord";"Larva";115;0
"Unit";"Overlord";"Larva";115;0
"Building";"CreepTumor";NA;115;0
"Building";"Extractor";NA;115;0
"Building";"Extractor";NA;115;0
"Building";"CreepTumor";NA;115;0
"Building";"CreepTumor";NA;115;0
"Building";"CreepTumor";NA;115;0
"Upgrade";"EvolveMuscularAugments";"HydraliskDen";100;0
"Building";"CreepTumor";NA;118;0
"Building";"CreepTumor";NA;120;0
"Building";"CreepTumor";NA;120;0
"Unit";"Hydralisk";"Larva";115;2
"Unit";"Hydralisk";"Larva";115;2
"Building";"CreepTumor";NA;130;0
"Building";"CreepTumor";NA;130;0
"Building";"CreepTumor";NA;130;0
"Building";"CreepTumor";NA;130;0
"Building";"CreepTumor";NA;130;0
"Building";"CreepTumorQueen";NA;130;0
"Unit";"Overlord";"Larva";130;0
"Unit";"Hydralisk";"Larva";130;2
"Unit";"Hydralisk";"Larva";130;2
"Unit";"Hydralisk";"Larva";130;2
"Unit";"Roach";"Larva";130;2
"Unit";"Roach";"Larva";130;2
"Unit";"Roach";"Larva";130;2
"Unit";"Roach";"Larva";130;2
"Unit";"Roach";"Larva";130;2
"Unit";"Zergling";"Larva";134;1
"Unit";"Zergling";"Larva";134;1
"Unit";"Zergling";"Larva";134;1
"Unit";"Zergling";"Larva";134;1
"Building";"CreepTumor";NA;134;0
"Unit";"Zergling";"Larva";134;1
"Unit";"Zergling";"Larva";134;1
"Unit";"Zergling";"Larva";134;1
"Unit";"Zergling";"Larva";134;1
"Unit";"Zergling";"Larva";134;1
"Unit";"Zergling";"Larva";134;1
"Unit";"Zergling";"Larva";134;1
"Unit";"Zergling";"Larva";134;1
"Unit";"Zergling";"Larva";134;1
"Unit";"Zergling";"Larva";134;1
"Building";"CreepTumor";NA;140;0
"Building";"CreepTumor";NA;140;0
"Building";"CreepTumor";NA;140;0
"Building";"CreepTumorQueen";NA;150;0
"Building";"CreepTumorQueen";NA;164;0
"Building";"CreepTumor";NA;158;0
"Unit";"Hydralisk";"Larva";150;2
"Unit";"Hydralisk";"Larva";150;2
"Unit";"Hydralisk";"Larva";150;2
"Unit";"Overlord";"Larva";164;0
"Unit";"Overlord";"Larva";164;0
"Unit";"Hydralisk";"Larva";164;2
"Unit";"Hydralisk";"Larva";164;2
"Upgrade";"ZergMissileWeaponsLevel1";"EvolutionChamber";115;0
"Unit";"Hydralisk";"Larva";164;2
"Upgrade";"ZergGroundArmorsLevel1";"EvolutionChamber";115;0
"Unit";"Hydralisk";"Larva";164;2
"Unit";"Hydralisk";"Larva";164;2
"Unit";"Hydralisk";"Larva";164;2
"Unit";"Hydralisk";"Larva";164;2
"Unit";"Hydralisk";"Larva";164;2
"Unit";"Hydralisk";"Larva";164;2
"Upgrade";"EvolveGroovedSpines";"HydraliskDen";142;0
"Unit";"Zergling";"Larva";178;1
"Unit";"Zergling";"Larva";178;1
"Unit";"Zergling";"Larva";178;1
"Unit";"Zergling";"Larva";178;1
"Unit";"Zergling";"Larva";178;1
"Unit";"Zergling";"Larva";178;1
"Unit";"Zergling";"Larva";178;1
"Unit";"Zergling";"Larva";178;1
"Unit";"Zergling";"Larva";178;1
"Unit";"Zergling";"Larva";178;1
"Unit";"Hydralisk";"Larva";178;2
"Unit";"Hydralisk";"Larva";178;2
"Unit";"Hydralisk";"Larva";178;2
"Unit";"Hydralisk";"Larva";178;2
"Unit";"Hydralisk";"Larva";178;2
"Unit";"Hydralisk";"Larva";178;2
"Unit";"Hydralisk";"Larva";188;2
"Unit";"Hydralisk";"Larva";188;2
"Building";"CreepTumor";NA;212;0
"Building";"CreepTumor";NA;212;0
"Unit";"Hydralisk";"Larva";200;2
"Unit";"Roach";"Larva";212;2
"Unit";"Roach";"Larva";212;2
"Building";"CreepTumor";NA;216;0
"Unit";"Roach";"Larva";212;2
"Unit";"Roach";"Larva";212;2
"Building";"CreepTumor";NA;223;0
"Building";"CreepTumor";NA;223;0
"Building";"CreepTumor";NA;223;0
"Unit";"Zergling";"Larva";218;1
"Unit";"Zergling";"Larva";218;1
"Unit";"Zergling";"Larva";218;1
"Unit";"Zergling";"Larva";218;1
"Unit";"Zergling";"Larva";218;1
"Unit";"Zergling";"Larva";218;1
"Unit";"Hydralisk";"Larva";216;2
"Unit";"Hydralisk";"Larva";216;2
"Unit";"Hydralisk";"Larva";216;2
"Unit";"Hydralisk";"Larva";216;2
"Unit";"Hydralisk";"Larva";216;2
"Unit";"Hydralisk";"Larva";216;2
"Unit";"Overlord";"Larva";223;0
"Unit";"Overlord";"Larva";223;0
"Building";"Extractor";NA;223;0
"Building";"Extractor";NA;227;0
"Unit";"Overlord";"Larva";245;0
"Building";"CreepTumor";NA;245;0
"Unit";"Overlord";"Larva";245;0
"Unit";"Roach";"Larva";245;2
"Unit";"Roach";"Larva";245;2
"Unit";"Roach";"Larva";245;2
"Unit";"Roach";"Larva";245;2
"Unit";"Roach";"Larva";245;2
"Unit";"Roach";"Larva";245;2
"Unit";"Hydralisk";"Larva";245;2
"Unit";"Hydralisk";"Larva";245;2
"Unit";"Hydralisk";"Larva";245;2
"Unit";"Hydralisk";"Larva";245;2
"Unit";"Hydralisk";"Larva";245;2
"Building";"CreepTumor";NA;245;0
"Building";"CreepTumor";NA;245;0
"Unit";"Overlord";"Larva";245;0
"Building";"CreepTumor";NA;247;0
"Building";"CreepTumor";NA;257;0
"Building";"CreepTumor";NA;257;0
"Building";"CreepTumor";NA;267;0
"Building";"Hatchery";NA;223;0
"Building";"LurkerDenMP";NA;216;0
"Unit";"Overlord";"Larva";267;0
"Building";"CreepTumor";NA;267;0
"Building";"CreepTumor";NA;267;0
"Building";"CreepTumor";NA;267;0
"Building";"CreepTumor";NA;267;0
"Building";"CreepTumor";NA;267;0
"Unit";"Overlord";"Larva";267;0
"Unit";"Zergling";"Larva";267;1
"Unit";"Zergling";"Larva";267;1
"Unit";"Zergling";"Larva";267;1
"Unit";"Zergling";"Larva";267;1
"Unit";"Zergling";"Larva";267;1
"Unit";"Zergling";"Larva";267;1
"Unit";"Zergling";"Larva";267;1
"Unit";"Zergling";"Larva";267;1
"Unit";"Zergling";"Larva";267;1
"Unit";"Zergling";"Larva";267;1
"Unit";"Zergling";"Larva";267;1
"Unit";"Zergling";"Larva";267;1
"Unit";"Zergling";"Larva";267;1
"Unit";"Zergling";"Larva";267;1
"Unit";"Zergling";"Larva";267;1
"Unit";"Zergling";"Larva";267;1
"Unit";"Zergling";"Larva";267;1
"Unit";"Zergling";"Larva";267;1
"Unit";"Zergling";"Larva";267;1
"Unit";"Zergling";"Larva";267;1
"Unit";"Zergling";"Larva";267;1
"Unit";"Zergling";"Larva";267;1
"Unit";"Zergling";"Larva";267;1
"Unit";"Zergling";"Larva";267;1
"Unit";"Zergling";"Larva";267;1
"Unit";"Zergling";"Larva";267;1
"Unit";"Zergling";"Larva";267;1
"Unit";"Zergling";"Larva";267;1
"Unit";"Zergling";"Larva";267;1
"Unit";"Zergling";"Larva";267;1
"Unit";"Zergling";"Larva";267;1
"Unit";"Zergling";"Larva";267;1
"Unit";"Hydralisk";"Larva";267;2
"Unit";"Hydralisk";"Larva";267;2
"Unit";"Overlord";"Larva";314;0
"Unit";"Queen";"Hatchery";267;2
"Unit";"Queen";"Hatchery";299;2
"Upgrade";"ZergMissileWeaponsLevel2";"EvolutionChamber";267;0
"Building";"SpineCrawler";NA;314;0
"Building";"SporeCrawler";NA;321;0
"Building";"CreepTumorQueen";NA;325;0
"Building";"SporeCrawler";NA;325;0
"Building";"CreepTumor";NA;325;0
"Unit";"Queen";"Hatchery";323;2
"Unit";"Overlord";"Larva";325;0
"Building";"InfestationPit";NA;325;0
"Building";"SpineCrawler";NA;325;0
"Unit";"Overlord";"Larva";325;0
"Building";"CreepTumor";NA;326;0
"Building";"CreepTumor";NA;328;0
"Building";"CreepTumor";NA;328;0
"Building";"CreepTumor";NA;328;0
"Building";"SpineCrawler";NA;325;0
"Unit";"Queen";"Hatchery";326;2
"Unit";"Hydralisk";"Larva";328;2
"Unit";"Hydralisk";"Larva";328;2
"Unit";"Hydralisk";"Larva";328;2
"Unit";"Hydralisk";"Larva";328;2
"Unit";"Hydralisk";"Larva";328;2
"Unit";"Hydralisk";"Larva";328;2
"Unit";"Hydralisk";"Larva";328;2
"Unit";"Hydralisk";"Larva";328;2
"Unit";"Hydralisk";"Larva";328;2
"Unit";"Hydralisk";"Larva";328;2
"Unit";"Hydralisk";"Larva";328;2
"Unit";"Hydralisk";"Larva";328;2
"Unit";"Hydralisk";"Larva";328;2
"Unit";"Hydralisk";"Larva";328;2
"Unit";"Hydralisk";"Larva";328;2
"Unit";"Hydralisk";"Larva";328;2
"Unit";"Hydralisk";"Larva";328;2
"Unit";"Hydralisk";"Larva";328;2
"Unit";"Hydralisk";"Larva";328;2
"Unit";"Hydralisk";"Larva";340;2
"Unit";"Hydralisk";"Larva";340;2
"Unit";"Hydralisk";"Larva";340;2
"Unit";"Hydralisk";"Larva";340;2
"Unit";"Hydralisk";"Larva";340;2
"Unit";"Hydralisk";"Larva";340;2
"Unit";"Hydralisk";"Larva";340;2
"Unit";"Hydralisk";"Larva";340;2
"Unit";"Hydralisk";"Larva";340;2
"Unit";"Hydralisk";"Larva";340;2
"Unit";"Hydralisk";"Larva";340;2
"Unit";"Hydralisk";"Larva";340;2
"Unit";"Hydralisk";"Larva";340;2
"Unit";"Hydralisk";"Larva";340;2
"Unit";"Roach";"Larva";368;2
"Unit";"Roach";"Larva";368;2
"Unit";"Roach";"Larva";368;2
"Unit";"Roach";"Larva";368;2
"Unit";"Roach";"Larva";368;2
"Unit";"Roach";"Larva";368;2
"Unit";"Roach";"Larva";368;2
"Unit";"Hydralisk";"Larva";368;2
