"type";"unit_name";"on_building";"total_supply";"supply"
"Unit";"Overlord";"Larva";12;0
"Building";"SpawningPool";NA;19;0
"Building";"Hatchery";NA;16;0
"Unit";"Overlord";"Larva";24;0
"Unit";"Queen";"Hatchery";23;2
"Unit";"Queen";"Hatchery";23;2
"Building";"Hatchery";NA;21;0
"Unit";"Zergling";"Larva";34;1
"Unit";"Zergling";"Larva";34;1
"Unit";"Queen";"Hatchery";26;2
"Building";"Extractor";NA;35;0
"Building";"Extractor";NA;35;0
"Unit";"Queen";"Hatchery";35;2
"Unit";"Overlord";"Larva";48;0
"Unit";"Overlord";"Larva";48;0
"Unit";"Overlord";"Larva";48;0
"Unit";"Overlord";"Larva";48;0
"Unit";"Overlord";"Larva";48;0
"Building";"Extractor";NA;48;0
"Building";"Extractor";NA;48;0
"Unit";"Overlord";"Larva";48;0
"Unit";"Overlord";"Larva";48;0
"Building";"CreepTumorQueen";NA;48;0
"Building";"RoachWarren";NA;48;0
"Unit";"Queen";"Hatchery";48;2
"Building";"CreepTumorQueen";NA;57;0
"Building";"CreepTumor";NA;57;0
"Unit";"Roach";"Larva";57;2
"Unit";"Roach";"Larva";57;2
"Unit";"Roach";"Larva";57;2
"Unit";"Roach";"Larva";57;2
"Building";"CreepTumorQueen";NA;59;0
"Building";"CreepTumorQueen";NA;59;0
"Building";"CreepTumor";NA;70;0
"Unit";"Overlord";"Larva";59;0
"Building";"CreepTumor";NA;70;0
"Unit";"Roach";"Larva";61;2
"Unit";"Zergling";"Larva";72;1
"Unit";"Zergling";"Larva";72;1
"Unit";"Zergling";"Larva";72;1
"Unit";"Zergling";"Larva";72;1
"Unit";"Roach";"Larva";72;2
"Unit";"Roach";"Larva";72;2
"Unit";"Roach";"Larva";72;2
"Building";"CreepTumorQueen";NA;74;0
"Building";"CreepTumor";NA;74;0
"Building";"CreepTumor";NA;74;0
"Unit";"Roach";"Larva";74;2
"Unit";"Roach";"Larva";74;2
"Unit";"Roach";"Larva";74;2
"Unit";"Roach";"Larva";84;2
"Unit";"Roach";"Larva";84;2
"Unit";"Roach";"Larva";84;2
"Unit";"Overlord";"Larva";84;0
"Building";"CreepTumor";NA;90;0
"Building";"CreepTumor";NA;90;0
"Unit";"Overlord";"Larva";90;0
"Unit";"Roach";"Larva";96;2
"Unit";"Roach";"Larva";96;2
"Unit";"Roach";"Larva";96;2
"Unit";"Roach";"Larva";96;2
"Unit";"Roach";"Larva";96;2
"Unit";"Roach";"Larva";96;2
"Unit";"Roach";"Larva";96;2
"Unit";"Overlord";"Larva";96;0
"Building";"CreepTumor";NA;96;0
"Upgrade";"GlialReconstitution";"RoachWarren";84;0
"Unit";"Overlord";"Larva";96;0
"Unit";"Overlord";"Larva";96;0
"Building";"CreepTumorQueen";NA;110;0
"Unit";"Roach";"Larva";110;2
"Unit";"Roach";"Larva";110;2
"Unit";"Roach";"Larva";110;2
"Unit";"Roach";"Larva";110;2
"Unit";"Overlord";"Larva";110;0
"Unit";"Overlord";"Larva";110;0
"Unit";"Overlord";"Larva";110;0
"Building";"CreepTumorQueen";NA;118;0
"Building";"CreepTumorQueen";NA;118;0
"Building";"CreepTumorQueen";NA;118;0
"Building";"CreepTumor";NA;118;0
"Building";"CreepTumor";NA;118;0
"Unit";"Roach";"Larva";110;2
"Building";"CreepTumor";NA;118;0
"Unit";"Roach";"Larva";110;2
"Unit";"Roach";"Larva";110;2
"Unit";"Roach";"Larva";110;2
"Unit";"Roach";"Larva";110;2
"Unit";"Roach";"Larva";110;2
"Unit";"Roach";"Larva";110;2
"Unit";"Overlord";"Larva";118;0
"Unit";"Overlord";"Larva";118;0
"Unit";"Roach";"Larva";118;2
"Unit";"Roach";"Larva";118;2
"Building";"CreepTumorQueen";NA;132;0
"Building";"CreepTumorQueen";NA;132;0
"Building";"CreepTumorQueen";NA;132;0
"Unit";"Roach";"Larva";132;2
"Unit";"Roach";"Larva";132;2
"Unit";"Roach";"Larva";132;2
"Unit";"Roach";"Larva";132;2
"Unit";"Roach";"Larva";132;2
"Building";"EvolutionChamber";NA;132;0
"Building";"CreepTumor";NA;136;0
"Unit";"Roach";"Larva";136;2
"Unit";"Roach";"Larva";136;2
"Unit";"Roach";"Larva";136;2
"Unit";"Roach";"Larva";136;2
"Unit";"Roach";"Larva";136;2
"Building";"CreepTumor";NA;146;0
"Building";"CreepTumor";NA;146;0
"Building";"CreepTumor";NA;146;0
"Building";"CreepTumor";NA;146;0
"Building";"CreepTumor";NA;146;0
"Unit";"Roach";"Larva";146;2
"Unit";"Roach";"Larva";146;2
"Unit";"Roach";"Larva";146;2
"Building";"CreepTumor";NA;162;0
"Building";"CreepTumor";NA;162;0
"Building";"CreepTumor";NA;162;0
"Unit";"Overlord";"Larva";162;0
"Building";"HydraliskDen";NA;156;0
"Building";"SporeCrawler";NA;156;0
"Building";"CreepTumor";NA;164;0
"Building";"CreepTumor";NA;164;0
"Building";"CreepTumor";NA;164;0
"Building";"CreepTumorQueen";NA;164;0
"Building";"CreepTumorQueen";NA;164;0
"Building";"CreepTumor";NA;164;0
"Building";"CreepTumor";NA;164;0
"Building";"CreepTumor";NA;164;0
"Building";"CreepTumor";NA;164;0
"Unit";"Hydralisk";"Larva";164;2
"Unit";"Hydralisk";"Larva";164;2
"Unit";"Hydralisk";"Larva";164;2
"Unit";"Hydralisk";"Larva";164;2
"Unit";"Hydralisk";"Larva";164;2
"Unit";"Hydralisk";"Larva";164;2
"Unit";"Hydralisk";"Larva";164;2
"Unit";"Hydralisk";"Larva";164;2
"Unit";"Hydralisk";"Larva";164;2
"Unit";"Hydralisk";"Larva";164;2
"Unit";"Hydralisk";"Larva";164;2
"Unit";"Hydralisk";"Larva";164;2
