"type";"unit_name";"on_building";"total_supply";"supply"
"Unit";"Overlord";"Larva";12;0
"Building";"Extractor";NA;18;0
"Building";"SpawningPool";NA;19;0
"Building";"Hatchery";NA;16;0
"Unit";"Overlord";"Larva";22;0
"Unit";"Zergling";"Larva";22;1
"Unit";"Zergling";"Larva";22;1
"Unit";"Queen";"Hatchery";22;2
"Unit";"Queen";"Hatchery";22;2
"Unit";"Zergling";"Larva";34;1
"Unit";"Zergling";"Larva";34;1
"Unit";"Zergling";"Larva";34;1
"Unit";"Zergling";"Larva";34;1
"Unit";"Overlord";"Larva";34;0
"Unit";"Overlord";"Larva";38;0
"Unit";"Queen";"Hatchery";34;2
"Unit";"Zergling";"Larva";41;1
"Unit";"Zergling";"Larva";41;1
"Unit";"Zergling";"Larva";41;1
"Unit";"Zergling";"Larva";41;1
"Unit";"Zergling";"Larva";41;1
"Unit";"Zergling";"Larva";41;1
"Unit";"Zergling";"Larva";41;1
"Unit";"Zergling";"Larva";41;1
"Unit";"Zergling";"Larva";41;1
"Unit";"Zergling";"Larva";41;1
"Unit";"Zergling";"Larva";41;1
"Unit";"Zergling";"Larva";41;1
"Building";"CreepTumorQueen";NA;45;0
"Building";"SporeCrawler";NA;43;0
"Building";"SporeCrawler";NA;45;0
"Building";"Hatchery";NA;34;0
"Unit";"Overlord";"Larva";62;0
"Building";"CreepTumor";NA;65;0
"Unit";"Overlord";"Larva";62;0
"Unit";"Queen";"Hatchery";58;2
"Unit";"Overlord";"Larva";65;0
"Building";"SporeCrawler";NA;65;0
"Building";"CreepTumorQueen";NA;72;0
"Unit";"Overlord";"Larva";72;0
"Building";"Extractor";NA;73;0
"Building";"EvolutionChamber";NA;75;0
"Unit";"Overlord";"Larva";77;0
"Unit";"Overlord";"Larva";83;0
"Unit";"Overlord";"Larva";83;0
"Unit";"Overlord";"Larva";87;0
"Unit";"Overlord";"Larva";88;0
"Unit";"Overlord";"Larva";88;0
"Unit";"Zergling";"Larva";88;1
"Unit";"Zergling";"Larva";88;1
"Unit";"Zergling";"Larva";88;1
"Unit";"Zergling";"Larva";88;1
"Unit";"Overlord";"Larva";88;0
"Unit";"Zergling";"Larva";88;1
"Unit";"Zergling";"Larva";88;1
"Unit";"Zergling";"Larva";88;1
"Unit";"Zergling";"Larva";88;1
"Unit";"Zergling";"Larva";88;1
"Unit";"Zergling";"Larva";88;1
"Unit";"Zergling";"Larva";88;1
"Unit";"Zergling";"Larva";88;1
"Unit";"Zergling";"Larva";88;1
"Unit";"Zergling";"Larva";88;1
"Unit";"Zergling";"Larva";88;1
"Unit";"Zergling";"Larva";88;1
"Building";"RoachWarren";NA;88;0
"Building";"CreepTumor";NA;104;0
"Unit";"Overlord";"Larva";104;0
"Building";"CreepTumor";NA;111;0
"Building";"CreepTumorQueen";NA;111;0
"Building";"CreepTumorQueen";NA;112;0
"Unit";"Roach";"Larva";120;2
"Building";"CreepTumorQueen";NA;121;0
"Unit";"Roach";"Larva";120;2
"Unit";"Roach";"Larva";120;2
"Unit";"Roach";"Larva";120;2
"Unit";"Roach";"Larva";120;2
"Unit";"Roach";"Larva";120;2
"Building";"CreepTumor";NA;121;0
"Building";"CreepTumor";NA;121;0
"Building";"CreepTumor";NA;121;0
"Building";"CreepTumorQueen";NA;121;0
"Building";"Extractor";NA;121;0
"Building";"Extractor";NA;121;0
"Unit";"Roach";"Larva";121;2
"Unit";"Roach";"Larva";121;2
"Unit";"Roach";"Larva";121;2
"Unit";"Overlord";"Larva";123;0
"Unit";"Overlord";"Larva";123;0
"Unit";"Overlord";"Larva";133;0
"Unit";"Roach";"Larva";133;2
"Unit";"Roach";"Larva";133;2
"Unit";"Roach";"Larva";133;2
"Unit";"Zergling";"Larva";143;1
"Unit";"Zergling";"Larva";143;1
"Unit";"Zergling";"Larva";143;1
"Unit";"Zergling";"Larva";143;1
"Unit";"Zergling";"Larva";143;1
"Unit";"Zergling";"Larva";143;1
"Unit";"Zergling";"Larva";143;1
"Unit";"Zergling";"Larva";143;1
"Unit";"Zergling";"Larva";143;1
"Unit";"Zergling";"Larva";143;1
"Building";"Hatchery";NA;114;0
"Building";"CreepTumor";NA;145;0
"Unit";"Roach";"Larva";143;2
"Unit";"Roach";"Larva";143;2
"Unit";"Roach";"Larva";143;2
"Building";"CreepTumor";NA;145;0
"Building";"CreepTumorQueen";NA;145;0
"Unit";"Zergling";"Larva";149;1
"Unit";"Zergling";"Larva";149;1
"Unit";"Zergling";"Larva";149;1
"Unit";"Zergling";"Larva";149;1
"Unit";"Zergling";"Larva";149;1
"Unit";"Zergling";"Larva";149;1
"Upgrade";"ZergMissileWeaponsLevel1";"EvolutionChamber";115;0
"Building";"Extractor";NA;155;0
"Upgrade";"GlialReconstitution";"RoachWarren";133;0
"Building";"HydraliskDen";NA;145;0
"Building";"SporeCrawler";NA;167;0
"Unit";"Roach";"Larva";181;2
"Unit";"Overlord";"Larva";186;0
"Unit";"Overlord";"Larva";186;0
"Unit";"Overlord";"Larva";186;0
"Building";"SpineCrawler";NA;173;0
"Unit";"Overlord";"Larva";186;0
"Unit";"Zergling";"Larva";188;1
"Unit";"Zergling";"Larva";188;1
"Unit";"Zergling";"Larva";188;1
"Unit";"Zergling";"Larva";188;1
"Unit";"Zergling";"Larva";188;1
"Unit";"Zergling";"Larva";188;1
"Unit";"Zergling";"Larva";188;1
"Unit";"Zergling";"Larva";188;1
"Unit";"Zergling";"Larva";188;1
"Unit";"Zergling";"Larva";188;1
"Unit";"Zergling";"Larva";188;1
"Unit";"Zergling";"Larva";188;1
"Unit";"Zergling";"Larva";188;1
"Unit";"Zergling";"Larva";188;1
"Unit";"Zergling";"Larva";188;1
"Unit";"Zergling";"Larva";188;1
"Unit";"Zergling";"Larva";188;1
"Unit";"Zergling";"Larva";188;1
"Unit";"Zergling";"Larva";188;1
"Unit";"Zergling";"Larva";188;1
"Unit";"Zergling";"Larva";188;1
"Unit";"Zergling";"Larva";188;1
"Unit";"Zergling";"Larva";188;1
"Unit";"Zergling";"Larva";188;1
"Unit";"Zergling";"Larva";188;1
"Unit";"Zergling";"Larva";188;1
"Unit";"Zergling";"Larva";188;1
"Unit";"Zergling";"Larva";188;1
"Unit";"Hydralisk";"Larva";188;2
"Unit";"Hydralisk";"Larva";188;2
"Unit";"Hydralisk";"Larva";188;2
"Unit";"Roach";"Larva";188;2
"Unit";"Roach";"Larva";188;2
"Unit";"Roach";"Larva";188;2
"Unit";"Roach";"Larva";188;2
"Unit";"Roach";"Larva";222;2
"Building";"Extractor";NA;222;0
"Building";"Extractor";NA;222;0
"Upgrade";"EvolveGroovedSpines";"HydraliskDen";188;0
"Unit";"Hydralisk";"Larva";222;2
"Unit";"Hydralisk";"Larva";224;2
"Unit";"Hydralisk";"Larva";225;2
"Building";"CreepTumor";NA;240;0
"Building";"CreepTumor";NA;240;0
"Unit";"Hydralisk";"Larva";237;2
"Building";"CreepTumor";NA;240;0
"Unit";"Queen";"Hatchery";222;2
"Building";"SpineCrawler";NA;228;0
"Building";"SpineCrawler";NA;228;0
"Unit";"Hydralisk";"Larva";239;2
"Building";"InfestationPit";NA;237;0
"Building";"SpineCrawler";NA;237;0
"Building";"SpineCrawler";NA;237;0
"Unit";"Hydralisk";"Larva";246;2
"Unit";"Hydralisk";"Larva";246;2
"Unit";"Hydralisk";"Larva";246;2
"Building";"CreepTumorQueen";NA;260;0
"Building";"CreepTumorQueen";NA;260;0
"Unit";"Hydralisk";"Larva";253;2
"Unit";"Hydralisk";"Larva";254;2
"Unit";"Zergling";"Larva";260;1
"Unit";"Zergling";"Larva";260;1
"Unit";"Zergling";"Larva";260;1
"Unit";"Zergling";"Larva";260;1
"Unit";"Zergling";"Larva";260;1
"Unit";"Zergling";"Larva";260;1
"Unit";"Zergling";"Larva";260;1
"Unit";"Zergling";"Larva";260;1
"Unit";"Zergling";"Larva";260;1
"Unit";"Zergling";"Larva";260;1
"Unit";"Hydralisk";"Larva";260;2
"Unit";"Hydralisk";"Larva";260;2
"Unit";"Roach";"Larva";266;2
"Unit";"Roach";"Larva";266;2
"Unit";"Roach";"Larva";266;2
"Building";"CreepTumor";NA;271;0
"Building";"CreepTumor";NA;271;0
"Unit";"Roach";"Larva";266;2
"Unit";"Roach";"Larva";266;2
"Building";"CreepTumor";NA;271;0
"Unit";"Roach";"Larva";266;2
"Upgrade";"ZergMissileWeaponsLevel2";"EvolutionChamber";188;0
"Unit";"Hydralisk";"Larva";281;2
"Unit";"Hydralisk";"Larva";281;2
"Unit";"Hydralisk";"Larva";281;2
"Building";"Hatchery";NA;240;0
"Unit";"Roach";"Larva";297;2
"Unit";"Overlord";"Larva";297;0
"Unit";"Overlord";"Larva";297;0
"Unit";"Overlord";"Larva";297;0
"Unit";"Zergling";"Larva";297;1
"Unit";"Zergling";"Larva";297;1
"Unit";"Zergling";"Larva";297;1
"Unit";"Zergling";"Larva";297;1
"Unit";"Zergling";"Larva";297;1
"Unit";"Zergling";"Larva";297;1
"Unit";"Zergling";"Larva";297;1
"Unit";"Zergling";"Larva";297;1
"Unit";"Zergling";"Larva";297;1
"Unit";"Zergling";"Larva";297;1
"Unit";"Zergling";"Larva";297;1
"Unit";"Zergling";"Larva";297;1
"Unit";"Hydralisk";"Larva";297;2
"Unit";"Hydralisk";"Larva";297;2
"Building";"Extractor";NA;303;0
"Building";"CreepTumor";NA;321;0
"Building";"CreepTumor";NA;321;0
"Building";"CreepTumor";NA;321;0
"Unit";"Hydralisk";"Larva";303;2
"Unit";"Hydralisk";"Larva";303;2
"Unit";"Hydralisk";"Larva";303;2
"Unit";"Hydralisk";"Larva";309;2
"Unit";"Hydralisk";"Larva";311;2
"Unit";"Hydralisk";"Larva";313;2
"Unit";"Hydralisk";"Larva";315;2
"Unit";"Roach";"Larva";321;2
"Unit";"Roach";"Larva";321;2
"Unit";"Roach";"Larva";321;2
"Unit";"Roach";"Larva";321;2
"Unit";"Roach";"Larva";321;2
"Unit";"Hydralisk";"Larva";321;2
"Unit";"Hydralisk";"Larva";321;2
"Unit";"Hydralisk";"Larva";321;2
"Unit";"Hydralisk";"Larva";345;2
"Unit";"Hydralisk";"Larva";348;2
"Unit";"Hydralisk";"Larva";348;2
"Unit";"Hydralisk";"Larva";354;2
"Unit";"Hydralisk";"Larva";354;2
"Building";"SpineCrawler";NA;354;0
"Building";"SpineCrawler";NA;354;0
"Building";"SpineCrawler";NA;354;0
"Unit";"Hydralisk";"Larva";360;2
"Unit";"Hydralisk";"Larva";360;2
"Unit";"Roach";"Larva";360;2
"Unit";"Roach";"Larva";360;2
"Unit";"Roach";"Larva";360;2
"Unit";"Roach";"Larva";360;2
"Unit";"Roach";"Larva";360;2
"Unit";"Zergling";"Larva";360;1
"Unit";"Zergling";"Larva";360;1
"Unit";"Roach";"Larva";368;2
"Unit";"Roach";"Larva";368;2
"Unit";"Roach";"Larva";368;2
"Unit";"Overlord";"Larva";380;0
"Unit";"Overlord";"Larva";380;0
"Unit";"Overlord";"Larva";380;0
"Unit";"Hydralisk";"Larva";380;2
"Unit";"Hydralisk";"Larva";380;2
"Unit";"Hydralisk";"Larva";390;2
"Unit";"Hydralisk";"Larva";390;2
"Unit";"Hydralisk";"Larva";390;2
"Unit";"Hydralisk";"Larva";390;2
"Unit";"Hydralisk";"Larva";390;2
"Unit";"Hydralisk";"Larva";390;2
"Unit";"Hydralisk";"Larva";390;2
"Unit";"Hydralisk";"Larva";390;2
"Unit";"Hydralisk";"Larva";390;2
"Unit";"Hydralisk";"Larva";390;2
"Upgrade";"EvolveMuscularAugments";"HydraliskDen";380;0
"Building";"Spire";NA;364;0
"Unit";"Hydralisk";"Larva";390;2
"Unit";"Hydralisk";"Larva";390;2
"Unit";"Hydralisk";"Larva";390;2
"Unit";"Hydralisk";"Larva";390;2
"Unit";"Hydralisk";"Larva";390;2
"Unit";"Hydralisk";"Larva";390;2
"Unit";"Hydralisk";"Larva";390;2
"Unit";"Hydralisk";"Larva";390;2
"Unit";"Roach";"Larva";390;2
"Unit";"Roach";"Larva";390;2
"Unit";"Roach";"Larva";390;2
"Unit";"Roach";"Larva";396;2
"Unit";"Roach";"Larva";398;2
"Unit";"Roach";"Larva";400;2
"Unit";"Roach";"Larva";410;2
"Unit";"Hydralisk";"Larva";426;2
"Unit";"Hydralisk";"Larva";438;2
"Unit";"Hydralisk";"Larva";438;2
"Unit";"Hydralisk";"Larva";438;2
"Unit";"Hydralisk";"Larva";438;2
"Unit";"Hydralisk";"Larva";438;2
"Unit";"Hydralisk";"Larva";438;2
"Unit";"Hydralisk";"Larva";438;2
"Unit";"Hydralisk";"Larva";438;2
"Unit";"Hydralisk";"Larva";438;2
"Unit";"Roach";"Larva";440;2
"Unit";"Roach";"Larva";440;2
"Unit";"Hydralisk";"Larva";440;2
"Unit";"Roach";"Larva";442;2
"Unit";"Roach";"Larva";442;2
"Unit";"Roach";"Larva";442;2
"Unit";"Hydralisk";"Larva";440;2
"Unit";"Hydralisk";"Larva";440;2
"Unit";"Hydralisk";"Larva";440;2
"Unit";"Hydralisk";"Larva";440;2
"Unit";"Hydralisk";"Larva";440;2
"Unit";"Roach";"Larva";457;2
"Unit";"Zergling";"Larva";471;1
"Unit";"Zergling";"Larva";471;1
"Unit";"Zergling";"Larva";471;1
"Unit";"Zergling";"Larva";471;1
"Unit";"Zergling";"Larva";471;1
"Unit";"Zergling";"Larva";471;1
"Unit";"Zergling";"Larva";471;1
"Unit";"Zergling";"Larva";471;1
"Unit";"Queen";"Hatchery";449;2
"Unit";"Roach";"Larva";487;2
"Unit";"Roach";"Larva";487;2
"Unit";"Hydralisk";"Larva";475;2
"Unit";"Hydralisk";"Larva";479;2
"Unit";"Hydralisk";"Larva";481;2
"Unit";"Hydralisk";"Larva";489;2
"Unit";"Hydralisk";"Larva";489;2
"Building";"Hatchery";NA;438;0
"Unit";"Corruptor";"Larva";489;2
"Unit";"Roach";"Larva";497;2
"Unit";"Roach";"Larva";497;2
"Unit";"Corruptor";"Larva";489;2
"Unit";"Corruptor";"Larva";489;2
"Building";"Extractor";NA;503;0
"Unit";"Corruptor";"Larva";497;2
"Unit";"Corruptor";"Larva";497;2
"Building";"Extractor";NA;509;0
"Unit";"Corruptor";"Larva";513;2
"Unit";"Corruptor";"Larva";513;2
"Unit";"Corruptor";"Larva";513;2
"Unit";"Overlord";"Larva";527;0
"Building";"CreepTumorQueen";NA;533;0
"Unit";"Corruptor";"Larva";527;2
"Building";"CreepTumorQueen";NA;535;0
"Unit";"Zergling";"Larva";535;1
"Unit";"Zergling";"Larva";535;1
"Unit";"Zergling";"Larva";535;1
"Unit";"Zergling";"Larva";535;1
"Unit";"Zergling";"Larva";535;1
"Unit";"Zergling";"Larva";535;1
"Unit";"Zergling";"Larva";535;1
"Unit";"Zergling";"Larva";535;1
"Unit";"Zergling";"Larva";535;1
"Unit";"Zergling";"Larva";535;1
"Unit";"Zergling";"Larva";535;1
"Unit";"Zergling";"Larva";535;1
"Unit";"Hydralisk";"Larva";547;2
"Unit";"Hydralisk";"Larva";547;2
"Unit";"Hydralisk";"Larva";547;2
"Unit";"Hydralisk";"Larva";547;2
"Unit";"Hydralisk";"Larva";547;2
"Unit";"Hydralisk";"Larva";548;2
"Unit";"Hydralisk";"Larva";548;2
"Unit";"Hydralisk";"Larva";548;2
"Unit";"Hydralisk";"Larva";548;2
"Unit";"Hydralisk";"Larva";548;2
"Unit";"Hydralisk";"Larva";548;2
"Building";"Extractor";NA;558;0
"Unit";"Corruptor";"Larva";564;2
"Unit";"Corruptor";"Larva";564;2
"Unit";"Corruptor";"Larva";564;2
"Building";"LurkerDenMP";NA;535;0
"Unit";"Corruptor";"Larva";576;2
"Unit";"Zergling";"Larva";582;1
"Unit";"Zergling";"Larva";582;1
"Unit";"Zergling";"Larva";582;1
"Unit";"Zergling";"Larva";582;1
"Unit";"Zergling";"Larva";582;1
"Unit";"Zergling";"Larva";582;1
"Unit";"Zergling";"Larva";582;1
"Unit";"Zergling";"Larva";582;1
"Unit";"Zergling";"Larva";582;1
"Unit";"Zergling";"Larva";582;1
"Unit";"Zergling";"Larva";582;1
"Unit";"Zergling";"Larva";582;1
"Unit";"Zergling";"Larva";582;1
"Unit";"Zergling";"Larva";582;1
"Unit";"Zergling";"Larva";582;1
"Unit";"Zergling";"Larva";582;1
"Unit";"Zergling";"Larva";582;1
"Unit";"Zergling";"Larva";582;1
"Unit";"Hydralisk";"Larva";578;2
"Unit";"Hydralisk";"Larva";580;2
"Unit";"Hydralisk";"Larva";582;2
"Unit";"Hydralisk";"Larva";582;2
"Unit";"Hydralisk";"Larva";582;2
"Unit";"Hydralisk";"Larva";582;2
"Unit";"Hydralisk";"Larva";582;2
"Unit";"Hydralisk";"Larva";582;2
"Unit";"Hydralisk";"Larva";582;2
"Unit";"Hydralisk";"Larva";582;2
"Unit";"Zergling";"Larva";582;1
"Unit";"Zergling";"Larva";582;1
"Unit";"Zergling";"Larva";582;1
"Unit";"Zergling";"Larva";582;1
"Unit";"Zergling";"Larva";582;1
"Unit";"Zergling";"Larva";582;1
"Unit";"Roach";"Larva";584;2
"Unit";"Roach";"Larva";584;2
"Unit";"Roach";"Larva";584;2
"Unit";"Roach";"Larva";584;2
"Unit";"Roach";"Larva";584;2
"Unit";"Hydralisk";"Larva";608;2
"Unit";"Hydralisk";"Larva";608;2
"Unit";"Hydralisk";"Larva";622;2
"Unit";"Hydralisk";"Larva";622;2
"Unit";"Zergling";"Larva";628;1
"Unit";"Zergling";"Larva";628;1
"Unit";"Zergling";"Larva";628;1
"Unit";"Zergling";"Larva";628;1
"Unit";"Overlord";"Larva";638;0
"Unit";"Overlord";"Larva";638;0
"Unit";"Overlord";"Larva";638;0
"Unit";"Overlord";"Larva";638;0
"Upgrade";"ZergMissileWeaponsLevel3";"EvolutionChamber";552;0
"Unit";"Overlord";"Larva";650;0
"Unit";"Zergling";"Larva";652;1
"Unit";"Zergling";"Larva";652;1
"Unit";"Zergling";"Larva";652;1
"Unit";"Zergling";"Larva";652;1
"Unit";"Zergling";"Larva";652;1
"Unit";"Zergling";"Larva";652;1
"Unit";"Zergling";"Larva";652;1
"Unit";"Zergling";"Larva";652;1
"Unit";"Zergling";"Larva";652;1
"Unit";"Zergling";"Larva";652;1
"Unit";"Zergling";"Larva";652;1
"Unit";"Zergling";"Larva";652;1
"Unit";"Hydralisk";"Larva";652;2
"Unit";"Hydralisk";"Larva";652;2
"Unit";"Hydralisk";"Larva";652;2
"Unit";"Hydralisk";"Larva";652;2
"Unit";"Hydralisk";"Larva";652;2
"Unit";"Hydralisk";"Larva";652;2
