"type";"unit_name";"on_building";"total_supply";"supply"
"Unit";"Overlord";"Larva";13;0
"Building";"Extractor";NA;18;0
"Building";"SpawningPool";NA;18;0
"Building";"Hatchery";NA;17;0
"Unit";"Overlord";"Larva";23;0
"Unit";"Zergling";"Larva";23;1
"Unit";"Zergling";"Larva";23;1
"Unit";"Zergling";"Larva";23;1
"Unit";"Zergling";"Larva";23;1
"Unit";"Queen";"Hatchery";22;2
"Unit";"Zergling";"Larva";23;1
"Unit";"Zergling";"Larva";23;1
"Unit";"Zergling";"Larva";23;1
"Unit";"Zergling";"Larva";23;1
"Unit";"Queen";"Hatchery";23;2
"Unit";"Zergling";"Larva";30;1
"Unit";"Zergling";"Larva";30;1
"Unit";"Zergling";"Larva";30;1
"Unit";"Zergling";"Larva";30;1
"Unit";"Overlord";"Larva";34;0
"Unit";"Zergling";"Larva";45;1
"Unit";"Zergling";"Larva";45;1
"Unit";"Zergling";"Larva";45;1
"Unit";"Zergling";"Larva";45;1
"Unit";"Zergling";"Larva";45;1
"Unit";"Zergling";"Larva";45;1
"Unit";"Zergling";"Larva";45;1
"Unit";"Zergling";"Larva";45;1
"Unit";"Zergling";"Larva";45;1
"Unit";"Zergling";"Larva";45;1
"Unit";"Zergling";"Larva";45;1
"Unit";"Zergling";"Larva";45;1
"Unit";"Zergling";"Larva";45;1
"Unit";"Zergling";"Larva";45;1
"Building";"Hatchery";NA;30;0
"Unit";"Zergling";"Larva";45;1
"Unit";"Zergling";"Larva";45;1
"Unit";"Zergling";"Larva";45;1
"Unit";"Zergling";"Larva";45;1
"Unit";"Zergling";"Larva";45;1
"Unit";"Zergling";"Larva";45;1
"Unit";"Zergling";"Larva";45;1
"Unit";"Zergling";"Larva";45;1
"Building";"SporeCrawler";NA;59;0
"Building";"SporeCrawler";NA;67;0
"Unit";"Zergling";"Larva";70;1
"Unit";"Zergling";"Larva";70;1
"Unit";"Zergling";"Larva";70;1
"Unit";"Zergling";"Larva";70;1
"Unit";"Zergling";"Larva";70;1
"Unit";"Zergling";"Larva";70;1
"Unit";"Zergling";"Larva";70;1
"Unit";"Zergling";"Larva";70;1
"Unit";"Queen";"Hatchery";67;2
"Unit";"Queen";"Hatchery";67;2
"Unit";"Overlord";"Larva";78;0
"Unit";"Overlord";"Larva";78;0
"Building";"Extractor";NA;78;0
"Unit";"Zergling";"Larva";82;1
"Unit";"Zergling";"Larva";82;1
"Building";"SporeCrawler";NA;107;0
"Building";"CreepTumorQueen";NA;107;0
"Building";"CreepTumorQueen";NA;107;0
"Building";"CreepTumorQueen";NA;107;0
"Building";"Extractor";NA;107;0
"Unit";"Overlord";"Larva";107;0
"Unit";"Overlord";"Larva";107;0
"Unit";"Zergling";"Larva";110;1
"Unit";"Zergling";"Larva";110;1
"Unit";"Zergling";"Larva";110;1
"Unit";"Zergling";"Larva";110;1
"Unit";"Zergling";"Larva";110;1
"Unit";"Zergling";"Larva";110;1
"Unit";"Zergling";"Larva";110;1
"Unit";"Zergling";"Larva";110;1
"Unit";"Zergling";"Larva";110;1
"Unit";"Zergling";"Larva";110;1
"Unit";"Zergling";"Larva";110;1
"Unit";"Zergling";"Larva";110;1
"Unit";"Zergling";"Larva";110;1
"Unit";"Zergling";"Larva";110;1
"Unit";"Zergling";"Larva";110;1
"Unit";"Zergling";"Larva";110;1
"Building";"EvolutionChamber";NA;110;0
"Building";"EvolutionChamber";NA;110;0
"Unit";"Zergling";"Larva";113;1
"Unit";"Zergling";"Larva";113;1
"Unit";"Zergling";"Larva";113;1
"Unit";"Zergling";"Larva";113;1
"Unit";"Zergling";"Larva";113;1
"Unit";"Zergling";"Larva";113;1
"Unit";"Zergling";"Larva";113;1
"Unit";"Zergling";"Larva";113;1
"Unit";"Zergling";"Larva";113;1
"Unit";"Zergling";"Larva";113;1
"Unit";"Zergling";"Larva";129;1
"Unit";"Zergling";"Larva";129;1
"Unit";"Zergling";"Larva";129;1
"Unit";"Zergling";"Larva";129;1
"Unit";"Zergling";"Larva";129;1
"Unit";"Zergling";"Larva";129;1
"Unit";"Queen";"Hatchery";113;2
"Unit";"Queen";"Hatchery";113;2
"Unit";"Zergling";"Larva";137;1
"Unit";"Zergling";"Larva";137;1
"Unit";"Zergling";"Larva";139;1
"Unit";"Zergling";"Larva";139;1
"Unit";"Zergling";"Larva";139;1
"Unit";"Zergling";"Larva";139;1
"Unit";"Zergling";"Larva";139;1
"Unit";"Zergling";"Larva";139;1
"Unit";"Zergling";"Larva";139;1
"Unit";"Zergling";"Larva";139;1
"Unit";"Zergling";"Larva";139;1
"Unit";"Zergling";"Larva";139;1
"Building";"RoachWarren";NA;113;0
"Unit";"Zergling";"Larva";145;1
"Unit";"Zergling";"Larva";145;1
"Unit";"Zergling";"Larva";145;1
"Unit";"Zergling";"Larva";145;1
"Unit";"Zergling";"Larva";145;1
"Unit";"Zergling";"Larva";145;1
"Unit";"Zergling";"Larva";145;1
"Unit";"Zergling";"Larva";145;1
"Unit";"Overlord";"Larva";161;0
"Unit";"Overlord";"Larva";161;0
"Unit";"Overlord";"Larva";161;0
"Unit";"Overlord";"Larva";161;0
"Unit";"Queen";"Hatchery";145;2
"Unit";"Zergling";"Larva";169;1
"Unit";"Zergling";"Larva";169;1
"Unit";"Zergling";"Larva";169;1
"Unit";"Zergling";"Larva";169;1
"Building";"Extractor";NA;169;0
"Unit";"Zergling";"Larva";169;1
"Unit";"Zergling";"Larva";169;1
"Unit";"Zergling";"Larva";169;1
"Unit";"Zergling";"Larva";169;1
"Unit";"Zergling";"Larva";169;1
"Unit";"Zergling";"Larva";169;1
"Unit";"Zergling";"Larva";169;1
"Unit";"Zergling";"Larva";169;1
"Unit";"Zergling";"Larva";169;1
"Unit";"Zergling";"Larva";169;1
"Unit";"Zergling";"Larva";169;1
"Unit";"Zergling";"Larva";169;1
"Unit";"Zergling";"Larva";169;1
"Unit";"Zergling";"Larva";169;1
"Unit";"Zergling";"Larva";169;1
"Unit";"Zergling";"Larva";169;1
"Unit";"Zergling";"Larva";169;1
"Unit";"Zergling";"Larva";169;1
"Unit";"Zergling";"Larva";169;1
"Unit";"Zergling";"Larva";169;1
"Unit";"Zergling";"Larva";169;1
"Unit";"Zergling";"Larva";169;1
"Unit";"Zergling";"Larva";169;1
"Unit";"Zergling";"Larva";169;1
"Unit";"Zergling";"Larva";169;1
"Unit";"Zergling";"Larva";169;1
"Unit";"Zergling";"Larva";169;1
"Unit";"Zergling";"Larva";169;1
"Unit";"Zergling";"Larva";169;1
"Unit";"Zergling";"Larva";169;1
"Unit";"Zergling";"Larva";169;1
"Unit";"Zergling";"Larva";169;1
"Unit";"Zergling";"Larva";169;1
"Unit";"Zergling";"Larva";169;1
"Unit";"Zergling";"Larva";175;1
"Unit";"Zergling";"Larva";175;1
"Upgrade";"GlialReconstitution";"RoachWarren";169;0
"Building";"Spire";NA;169;0
"Building";"CreepTumor";NA;214;0
"Building";"CreepTumorQueen";NA;215;0
"Building";"Extractor";NA;214;0
"Building";"CreepTumorQueen";NA;223;0
"Building";"Extractor";NA;214;0
"Unit";"Overlord";"Larva";214;0
"Unit";"Overlord";"Larva";214;0
"Unit";"Overlord";"Larva";214;0
"Building";"CreepTumorQueen";NA;223;0
"Building";"CreepTumorQueen";NA;223;0
"Building";"CreepTumorQueen";NA;223;0
"Unit";"Zergling";"Larva";223;1
"Unit";"Zergling";"Larva";223;1
"Unit";"Zergling";"Larva";223;1
"Unit";"Zergling";"Larva";223;1
"Unit";"Zergling";"Larva";223;1
"Unit";"Zergling";"Larva";223;1
"Unit";"Zergling";"Larva";223;1
"Unit";"Zergling";"Larva";223;1
"Unit";"Zergling";"Larva";223;1
"Unit";"Zergling";"Larva";223;1
"Unit";"Zergling";"Larva";223;1
"Unit";"Zergling";"Larva";223;1
"Unit";"Zergling";"Larva";223;1
"Unit";"Zergling";"Larva";223;1
"Unit";"Zergling";"Larva";223;1
"Unit";"Zergling";"Larva";223;1
"Unit";"Zergling";"Larva";223;1
"Unit";"Zergling";"Larva";223;1
"Unit";"Zergling";"Larva";223;1
"Unit";"Zergling";"Larva";223;1
"Unit";"Zergling";"Larva";223;1
"Unit";"Zergling";"Larva";223;1
"Upgrade";"ZergMeleeWeaponsLevel1";"EvolutionChamber";175;0
"Upgrade";"ZergGroundArmorsLevel1";"EvolutionChamber";175;0
"Building";"CreepTumor";NA;246;0
"Building";"CreepTumor";NA;246;0
"Building";"CreepTumor";NA;246;0
"Building";"Extractor";NA;246;0
"Building";"Extractor";NA;246;0
"Building";"CreepTumorQueen";NA;250;0
"Building";"Hatchery";NA;223;0
"Unit";"Mutalisk";"Larva";250;2
"Unit";"Mutalisk";"Larva";250;2
"Unit";"Mutalisk";"Larva";250;2
"Unit";"Mutalisk";"Larva";250;2
"Unit";"Mutalisk";"Larva";256;2
"Unit";"Mutalisk";"Larva";256;2
"Unit";"Mutalisk";"Larva";256;2
"Unit";"Mutalisk";"Larva";256;2
"Unit";"Mutalisk";"Larva";256;2
"Unit";"Mutalisk";"Larva";256;2
"Unit";"Zergling";"Larva";256;1
"Unit";"Zergling";"Larva";256;1
"Unit";"Zergling";"Larva";256;1
"Unit";"Zergling";"Larva";256;1
"Unit";"Zergling";"Larva";256;1
"Unit";"Zergling";"Larva";256;1
"Unit";"Zergling";"Larva";256;1
"Unit";"Zergling";"Larva";256;1
"Unit";"Zergling";"Larva";256;1
"Unit";"Zergling";"Larva";256;1
"Unit";"Zergling";"Larva";256;1
"Unit";"Zergling";"Larva";256;1
"Unit";"Zergling";"Larva";256;1
"Unit";"Zergling";"Larva";256;1
"Unit";"Mutalisk";"Larva";256;2
"Unit";"Mutalisk";"Larva";256;2
"Unit";"Overlord";"Larva";264;0
"Unit";"Overlord";"Larva";264;0
"Unit";"Overlord";"Larva";264;0
"Building";"CreepTumor";NA;290;0
"Building";"CreepTumor";NA;290;0
"Building";"CreepTumor";NA;290;0
"Building";"CreepTumor";NA;290;0
"Building";"CreepTumor";NA;294;0
"Building";"CreepTumor";NA;294;0
"Building";"CreepTumor";NA;294;0
"Building";"CreepTumorQueen";NA;294;0
"Building";"CreepTumorQueen";NA;298;0
"Building";"CreepTumorQueen";NA;302;0
"Unit";"Mutalisk";"Larva";294;2
"Unit";"Mutalisk";"Larva";294;2
"Unit";"Mutalisk";"Larva";294;2
"Unit";"Mutalisk";"Larva";294;2
"Unit";"Mutalisk";"Larva";294;2
"Unit";"Zergling";"Larva";302;1
"Unit";"Zergling";"Larva";302;1
"Unit";"Zergling";"Larva";302;1
"Unit";"Zergling";"Larva";302;1
"Unit";"Zergling";"Larva";302;1
"Unit";"Zergling";"Larva";302;1
"Unit";"Zergling";"Larva";302;1
"Unit";"Zergling";"Larva";302;1
"Unit";"Zergling";"Larva";302;1
"Unit";"Zergling";"Larva";302;1
"Unit";"Zergling";"Larva";302;1
"Unit";"Zergling";"Larva";302;1
"Unit";"Zergling";"Larva";302;1
"Unit";"Zergling";"Larva";302;1
"Unit";"Zergling";"Larva";302;1
"Unit";"Zergling";"Larva";302;1
"Unit";"Zergling";"Larva";302;1
"Unit";"Zergling";"Larva";302;1
"Unit";"Zergling";"Larva";302;1
"Unit";"Zergling";"Larva";302;1
"Unit";"Zergling";"Larva";302;1
"Unit";"Zergling";"Larva";302;1
"Unit";"Zergling";"Larva";302;1
"Unit";"Zergling";"Larva";302;1
"Unit";"Zergling";"Larva";302;1
"Unit";"Zergling";"Larva";302;1
"Building";"Hatchery";NA;290;0
"Upgrade";"ZergMeleeWeaponsLevel2";"EvolutionChamber";270;0
"Upgrade";"ZergGroundArmorsLevel2";"EvolutionChamber";274;0
"Unit";"Mutalisk";"Larva";338;2
"Unit";"Mutalisk";"Larva";338;2
"Unit";"Mutalisk";"Larva";338;2
"Unit";"Mutalisk";"Larva";338;2
"Unit";"Mutalisk";"Larva";338;2
"Unit";"Mutalisk";"Larva";338;2
"Unit";"Mutalisk";"Larva";338;2
"Unit";"Mutalisk";"Larva";338;2
"Unit";"Mutalisk";"Larva";338;2
"Unit";"Mutalisk";"Larva";338;2
"Unit";"Mutalisk";"Larva";338;2
"Unit";"Mutalisk";"Larva";338;2
"Unit";"Mutalisk";"Larva";338;2
"Building";"CreepTumor";NA;338;0
"Building";"CreepTumor";NA;338;0
"Building";"CreepTumor";NA;338;0
"Building";"CreepTumor";NA;338;0
"Building";"CreepTumorQueen";NA;364;0
"Building";"CreepTumorQueen";NA;364;0
"Building";"CreepTumorQueen";NA;364;0
"Unit";"Overlord";"Larva";364;0
"Unit";"Overlord";"Larva";364;0
"Unit";"Overlord";"Larva";364;0
"Unit";"Overlord";"Larva";364;0
"Unit";"Overlord";"Larva";364;0
"Unit";"Mutalisk";"Larva";364;2
"Unit";"Mutalisk";"Larva";364;2
"Unit";"Mutalisk";"Larva";364;2
"Unit";"Zergling";"Larva";364;1
"Unit";"Zergling";"Larva";364;1
"Unit";"Zergling";"Larva";364;1
"Unit";"Zergling";"Larva";364;1
"Unit";"Zergling";"Larva";370;1
"Unit";"Zergling";"Larva";370;1
"Unit";"Zergling";"Larva";370;1
"Unit";"Zergling";"Larva";370;1
"Unit";"Zergling";"Larva";370;1
"Unit";"Zergling";"Larva";370;1
"Unit";"Zergling";"Larva";370;1
"Unit";"Zergling";"Larva";370;1
"Unit";"Zergling";"Larva";370;1
"Unit";"Zergling";"Larva";370;1
"Unit";"Zergling";"Larva";370;1
"Unit";"Zergling";"Larva";370;1
"Unit";"Zergling";"Larva";370;1
"Unit";"Zergling";"Larva";370;1
"Unit";"Zergling";"Larva";370;1
"Unit";"Zergling";"Larva";370;1
"Unit";"Zergling";"Larva";370;1
"Unit";"Zergling";"Larva";370;1
"Unit";"Zergling";"Larva";370;1
"Unit";"Zergling";"Larva";370;1
"Unit";"Zergling";"Larva";370;1
"Unit";"Zergling";"Larva";370;1
"Unit";"Zergling";"Larva";370;1
"Unit";"Zergling";"Larva";370;1
"Unit";"Zergling";"Larva";370;1
"Unit";"Zergling";"Larva";370;1
"Unit";"Zergling";"Larva";370;1
"Unit";"Zergling";"Larva";370;1
"Unit";"Zergling";"Larva";370;1
"Unit";"Zergling";"Larva";370;1
"Unit";"Zergling";"Larva";370;1
"Unit";"Zergling";"Larva";370;1
"Unit";"Zergling";"Larva";370;1
"Unit";"Zergling";"Larva";370;1
"Unit";"Zergling";"Larva";370;1
"Unit";"Zergling";"Larva";370;1
"Unit";"Zergling";"Larva";370;1
"Unit";"Zergling";"Larva";370;1
"Unit";"Zergling";"Larva";370;1
"Unit";"Zergling";"Larva";370;1
"Unit";"Zergling";"Larva";370;1
"Unit";"Zergling";"Larva";370;1
"Building";"InfestationPit";NA;364;0
"Building";"CreepTumor";NA;372;0
"Building";"CreepTumorQueen";NA;374;0
"Building";"CreepTumor";NA;374;0
"Building";"CreepTumor";NA;374;0
"Building";"CreepTumor";NA;374;0
