"type";"unit_name";"on_building";"total_supply";"supply"
"Unit";"Overlord";"Larva";12;0
"Building";"Extractor";NA;19;0
"Unit";"Overlord";"Larva";21;0
"Building";"SpawningPool";NA;19;0
"Building";"Hatchery";NA;17;0
"Unit";"Queen";"Hatchery";22;2
"Unit";"Queen";"Hatchery";23;2
"Unit";"Overlord";"Larva";32;0
"Unit";"Queen";"Hatchery";32;2
"Building";"CreepTumorQueen";NA;37;0
"Unit";"Overlord";"Larva";35;0
"Unit";"Zergling";"Larva";40;1
"Unit";"Zergling";"Larva";40;1
"Unit";"Zergling";"Larva";45;1
"Unit";"Zergling";"Larva";45;1
"Building";"Hatchery";NA;27;0
"Building";"CreepTumor";NA;47;0
"Unit";"Overlord";"Larva";47;0
"Unit";"Overlord";"Larva";47;0
"Building";"CreepTumorQueen";NA;51;0
"Building";"EvolutionChamber";NA;49;0
"Unit";"Overlord";"Larva";51;0
"Building";"SporeCrawler";NA;51;0
"Building";"SporeCrawler";NA;52;0
"Unit";"Queen";"Hatchery";51;2
"Building";"CreepTumorQueen";NA;62;0
"Building";"SporeCrawler";NA;60;0
"Building";"CreepTumor";NA;64;0
"Building";"CreepTumor";NA;64;0
"Unit";"Overlord";"Larva";65;0
"Building";"CreepTumor";NA;75;0
"Building";"Extractor";NA;70;0
"Building";"Extractor";NA;70;0
"Building";"Extractor";NA;70;0
"Building";"CreepTumorQueen";NA;78;0
"Building";"Extractor";NA;70;0
"Building";"Extractor";NA;71;0
"Unit";"Overlord";"Larva";78;0
"Building";"CreepTumor";NA;86;0
"Unit";"Zergling";"Larva";88;1
"Unit";"Zergling";"Larva";88;1
"Unit";"Zergling";"Larva";88;1
"Unit";"Zergling";"Larva";88;1
"Unit";"Zergling";"Larva";95;1
"Unit";"Zergling";"Larva";95;1
"Unit";"Zergling";"Larva";95;1
"Unit";"Zergling";"Larva";95;1
"Unit";"Zergling";"Larva";95;1
"Unit";"Zergling";"Larva";95;1
"Building";"CreepTumor";NA;99;0
"Building";"CreepTumorQueen";NA;99;0
"Building";"CreepTumor";NA;99;0
"Building";"BanelingNest";NA;84;0
"Upgrade";"ZergMeleeWeaponsLevel1";"EvolutionChamber";75;0
"Building";"HydraliskDen";NA;95;0
"Unit";"Overlord";"Larva";105;0
"Unit";"Overlord";"Larva";105;0
"Unit";"Overlord";"Larva";105;0
"Unit";"Overlord";"Larva";105;0
"Unit";"Overlord";"Larva";105;0
"Unit";"Zergling";"Larva";105;1
"Unit";"Zergling";"Larva";105;1
"Unit";"Zergling";"Larva";105;1
"Unit";"Zergling";"Larva";105;1
"Unit";"Zergling";"Larva";105;1
"Unit";"Zergling";"Larva";105;1
"Unit";"Zergling";"Larva";105;1
"Unit";"Zergling";"Larva";105;1
"Unit";"Zergling";"Larva";105;1
"Unit";"Zergling";"Larva";105;1
"Unit";"Zergling";"Larva";105;1
"Unit";"Zergling";"Larva";105;1
"Unit";"Overlord";"Larva";117;0
"Building";"EvolutionChamber";NA;105;0
"Building";"CreepTumor";NA;117;0
"Unit";"Hydralisk";"Larva";117;2
"Unit";"Hydralisk";"Larva";117;2
"Unit";"Hydralisk";"Larva";117;2
"Unit";"Hydralisk";"Larva";117;2
"Unit";"Hydralisk";"Larva";117;2
"Unit";"Hydralisk";"Larva";117;2
"Unit";"Hydralisk";"Larva";117;2
"Unit";"Hydralisk";"Larva";117;2
"Building";"CreepTumor";NA;117;0
"Building";"CreepTumorQueen";NA;117;0
"Building";"CreepTumor";NA;117;0
"Unit";"Hydralisk";"Larva";117;2
"Unit";"Hydralisk";"Larva";117;2
"Unit";"Hydralisk";"Larva";117;2
"Unit";"Hydralisk";"Larva";117;2
"Unit";"Hydralisk";"Larva";117;2
"Building";"Hatchery";NA;99;0
"Building";"CreepTumorQueen";NA;150;0
"Building";"CreepTumor";NA;151;0
"Building";"CreepTumorQueen";NA;152;0
"Building";"CreepTumor";NA;151;0
"Unit";"Hydralisk";"Larva";151;2
"Unit";"Hydralisk";"Larva";151;2
"Upgrade";"EvolveGroovedSpines";"HydraliskDen";117;0
"Unit";"Hydralisk";"Larva";157;2
"Unit";"Hydralisk";"Larva";158;2
"Unit";"Hydralisk";"Larva";158;2
"Unit";"Hydralisk";"Larva";158;2
"Unit";"Hydralisk";"Larva";158;2
"Unit";"Hydralisk";"Larva";158;2
"Building";"Extractor";NA;162;0
"Building";"Extractor";NA;162;0
"Unit";"Overlord";"Larva";178;0
"Unit";"Overlord";"Larva";178;0
"Unit";"Overlord";"Larva";178;0
"Unit";"Overlord";"Larva";178;0
"Building";"CreepTumor";NA;178;0
"Building";"CreepTumor";NA;178;0
"Building";"CreepTumor";NA;178;0
"Building";"CreepTumorQueen";NA;178;0
"Upgrade";"ZergMissileWeaponsLevel1";"EvolutionChamber";134;0
"Unit";"Overlord";"Larva";178;0
"Unit";"Overlord";"Larva";178;0
"Unit";"Overlord";"Larva";181;0
"Unit";"Overlord";"Larva";181;0
"Unit";"Overlord";"Larva";181;0
"Unit";"Overlord";"Larva";181;0
"Unit";"Overlord";"Larva";181;0
"Building";"Spire";NA;162;0
"Upgrade";"EvolveMuscularAugments";"HydraliskDen";178;0
"Unit";"Hydralisk";"Larva";181;2
"Unit";"Hydralisk";"Larva";181;2
"Unit";"Hydralisk";"Larva";181;2
"Unit";"Hydralisk";"Larva";181;2
"Unit";"Hydralisk";"Larva";181;2
"Unit";"Hydralisk";"Larva";181;2
"Unit";"Hydralisk";"Larva";181;2
"Unit";"Hydralisk";"Larva";181;2
"Upgrade";"ZergGroundArmorsLevel1";"EvolutionChamber";157;0
"Building";"CreepTumor";NA;181;0
"Building";"CreepTumor";NA;181;0
"Unit";"Zergling";"Larva";181;1
"Unit";"Zergling";"Larva";181;1
"Unit";"Zergling";"Larva";181;1
"Unit";"Zergling";"Larva";181;1
"Unit";"Zergling";"Larva";181;1
"Unit";"Zergling";"Larva";181;1
"Unit";"Zergling";"Larva";181;1
"Unit";"Zergling";"Larva";181;1
"Unit";"Zergling";"Larva";181;1
"Unit";"Zergling";"Larva";181;1
"Unit";"Zergling";"Larva";181;1
"Unit";"Zergling";"Larva";181;1
"Unit";"Zergling";"Larva";181;1
"Unit";"Zergling";"Larva";181;1
"Unit";"Zergling";"Larva";181;1
"Unit";"Zergling";"Larva";181;1
"Unit";"Zergling";"Larva";181;1
"Unit";"Zergling";"Larva";181;1
"Unit";"Zergling";"Larva";181;1
"Unit";"Zergling";"Larva";181;1
"Unit";"Zergling";"Larva";181;1
"Unit";"Zergling";"Larva";181;1
"Unit";"Zergling";"Larva";181;1
"Unit";"Zergling";"Larva";181;1
"Unit";"Zergling";"Larva";181;1
"Unit";"Zergling";"Larva";181;1
"Building";"CreepTumor";NA;181;0
"Building";"Hatchery";NA;162;0
"Building";"CreepTumor";NA;181;0
"Building";"CreepTumor";NA;181;0
"Building";"CreepTumorQueen";NA;223;0
"Building";"CreepTumorQueen";NA;223;0
"Unit";"Corruptor";"Larva";197;2
"Unit";"Corruptor";"Larva";197;2
"Unit";"Corruptor";"Larva";197;2
"Unit";"Corruptor";"Larva";197;2
"Unit";"Zergling";"Larva";223;1
"Unit";"Zergling";"Larva";223;1
"Unit";"Zergling";"Larva";223;1
"Unit";"Zergling";"Larva";223;1
"Unit";"Zergling";"Larva";223;1
"Unit";"Zergling";"Larva";223;1
"Unit";"Zergling";"Larva";223;1
"Unit";"Zergling";"Larva";223;1
"Unit";"Zergling";"Larva";223;1
"Unit";"Zergling";"Larva";223;1
"Unit";"Zergling";"Larva";223;1
"Unit";"Zergling";"Larva";223;1
"Unit";"Zergling";"Larva";223;1
"Unit";"Zergling";"Larva";223;1
"Unit";"Zergling";"Larva";223;1
"Unit";"Zergling";"Larva";223;1
"Unit";"Zergling";"Larva";223;1
"Unit";"Zergling";"Larva";223;1
"Unit";"Corruptor";"Larva";223;2
"Unit";"Corruptor";"Larva";223;2
"Unit";"Corruptor";"Larva";223;2
"Unit";"Corruptor";"Larva";223;2
"Unit";"Corruptor";"Larva";223;2
"Building";"CreepTumor";NA;259;0
"Unit";"Corruptor";"Larva";233;2
"Unit";"Corruptor";"Larva";237;2
"Unit";"Zergling";"Larva";263;1
"Unit";"Zergling";"Larva";263;1
"Unit";"Zergling";"Larva";263;1
"Unit";"Zergling";"Larva";263;1
"Unit";"Zergling";"Larva";263;1
"Unit";"Zergling";"Larva";263;1
"Unit";"Zergling";"Larva";263;1
"Unit";"Zergling";"Larva";263;1
"Unit";"Zergling";"Larva";263;1
"Unit";"Zergling";"Larva";263;1
"Unit";"Zergling";"Larva";263;1
"Unit";"Zergling";"Larva";263;1
"Unit";"Zergling";"Larva";263;1
"Unit";"Zergling";"Larva";263;1
"Unit";"Zergling";"Larva";263;1
"Unit";"Zergling";"Larva";263;1
"Unit";"Zergling";"Larva";263;1
"Unit";"Zergling";"Larva";263;1
"Unit";"Zergling";"Larva";263;1
"Unit";"Zergling";"Larva";263;1
"Unit";"Zergling";"Larva";263;1
"Unit";"Zergling";"Larva";263;1
"Unit";"Zergling";"Larva";263;1
"Unit";"Zergling";"Larva";263;1
"Unit";"Zergling";"Larva";263;1
"Unit";"Zergling";"Larva";263;1
"Unit";"Zergling";"Larva";263;1
"Unit";"Zergling";"Larva";263;1
"Unit";"Zergling";"Larva";263;1
"Unit";"Zergling";"Larva";263;1
"Unit";"Zergling";"Larva";263;1
"Unit";"Zergling";"Larva";263;1
"Unit";"Zergling";"Larva";263;1
"Unit";"Zergling";"Larva";263;1
"Unit";"Zergling";"Larva";263;1
"Unit";"Zergling";"Larva";263;1
"Unit";"Zergling";"Larva";263;1
"Unit";"Zergling";"Larva";263;1
"Unit";"Zergling";"Larva";263;1
"Unit";"Zergling";"Larva";263;1
"Unit";"Baneling";"Zergling";263;0
"Unit";"Baneling";"Zergling";263;0
"Unit";"Baneling";"Zergling";263;0
"Unit";"Baneling";"Zergling";263;0
"Unit";"Baneling";"Zergling";263;0
"Unit";"Baneling";"Zergling";263;0
"Unit";"Baneling";"Zergling";263;0
"Unit";"Baneling";"Zergling";263;0
"Unit";"Baneling";"Zergling";263;0
"Unit";"Baneling";"Zergling";263;0
"Unit";"Baneling";"Zergling";263;0
"Unit";"Baneling";"Zergling";263;0
"Unit";"Baneling";"Zergling";263;0
"Unit";"Baneling";"Zergling";263;0
"Unit";"Baneling";"Zergling";263;0
"Unit";"Baneling";"Zergling";263;0
"Unit";"Baneling";"Zergling";263;0
"Unit";"Baneling";"Zergling";263;0
"Upgrade";"ZergMissileWeaponsLevel2";"EvolutionChamber";223;0
"Unit";"Hydralisk";"Larva";303;2
"Unit";"Hydralisk";"Larva";303;2
"Unit";"Hydralisk";"Larva";303;2
"Unit";"Hydralisk";"Larva";303;2
"Unit";"Hydralisk";"Larva";303;2
"Building";"InfestationPit";NA;303;0
"Unit";"Baneling";"Zergling";313;0
"Unit";"Baneling";"Zergling";313;0
"Unit";"Baneling";"Zergling";313;0
"Unit";"Baneling";"Zergling";313;0
"Unit";"Baneling";"Zergling";313;0
"Unit";"Baneling";"Zergling";313;0
"Unit";"Baneling";"Zergling";313;0
"Unit";"Baneling";"Zergling";313;0
"Unit";"Baneling";"Zergling";313;0
"Unit";"Baneling";"Zergling";313;0
"Unit";"Baneling";"Zergling";313;0
"Unit";"Baneling";"Zergling";313;0
"Unit";"Baneling";"Zergling";313;0
"Unit";"Baneling";"Zergling";313;0
"Unit";"Baneling";"Zergling";313;0
"Unit";"Baneling";"Zergling";313;0
"Unit";"Baneling";"Zergling";313;0
"Unit";"Baneling";"Zergling";313;0
"Unit";"Baneling";"Zergling";313;0
"Unit";"Corruptor";"Larva";313;2
"Upgrade";"ZergGroundArmorsLevel2";"EvolutionChamber";259;0
"Unit";"Corruptor";"Larva";313;2
"Unit";"Corruptor";"Larva";313;2
"Unit";"Corruptor";"Larva";313;2
"Unit";"Corruptor";"Larva";313;2
"Unit";"Corruptor";"Larva";313;2
"Unit";"Corruptor";"Larva";313;2
"Unit";"Corruptor";"Larva";313;2
"Unit";"Corruptor";"Larva";313;2
"Building";"CreepTumor";NA;331;0
"Building";"CreepTumor";NA;331;0
"Building";"CreepTumor";NA;331;0
"Unit";"Hydralisk";"Larva";344;2
"Unit";"Hydralisk";"Larva";344;2
"Unit";"Hydralisk";"Larva";344;2
"Unit";"Hydralisk";"Larva";344;2
"Unit";"Hydralisk";"Larva";344;2
"Unit";"Hydralisk";"Larva";344;2
"Unit";"Hydralisk";"Larva";344;2
"Unit";"Hydralisk";"Larva";344;2
"Unit";"Zergling";"Larva";344;1
"Unit";"Zergling";"Larva";344;1
"Unit";"Zergling";"Larva";344;1
"Unit";"Zergling";"Larva";344;1
"Unit";"Zergling";"Larva";344;1
"Unit";"Zergling";"Larva";344;1
"Unit";"Zergling";"Larva";344;1
"Unit";"Zergling";"Larva";344;1
"Unit";"Zergling";"Larva";344;1
"Unit";"Zergling";"Larva";344;1
"Unit";"Zergling";"Larva";344;1
"Unit";"Zergling";"Larva";344;1
"Unit";"Zergling";"Larva";344;1
"Unit";"Zergling";"Larva";344;1
"Building";"Extractor";NA;360;0
"Building";"Extractor";NA;360;0
"Unit";"Zergling";"Larva";360;1
"Unit";"Zergling";"Larva";360;1
"Unit";"Zergling";"Larva";360;1
"Unit";"Zergling";"Larva";360;1
"Unit";"Zergling";"Larva";360;1
"Unit";"Zergling";"Larva";360;1
"Unit";"Zergling";"Larva";360;1
"Unit";"Zergling";"Larva";360;1
"Unit";"Hydralisk";"Larva";382;2
"Unit";"Hydralisk";"Larva";382;2
"Unit";"Hydralisk";"Larva";382;2
"Unit";"Hydralisk";"Larva";382;2
"Unit";"Hydralisk";"Larva";382;2
"Unit";"Hydralisk";"Larva";382;2
"Unit";"Hydralisk";"Larva";382;2
"Unit";"Hydralisk";"Larva";382;2
"Unit";"Hydralisk";"Larva";382;2
"Unit";"Hydralisk";"Larva";382;2
"Unit";"Hydralisk";"Larva";382;2
"Unit";"Hydralisk";"Larva";382;2
"Unit";"Hydralisk";"Larva";382;2
"Unit";"Hydralisk";"Larva";382;2
"Unit";"Hydralisk";"Larva";382;2
"Unit";"Hydralisk";"Larva";382;2
"Unit";"Hydralisk";"Larva";382;2
"Unit";"Hydralisk";"Larva";382;2
"Unit";"Hydralisk";"Larva";382;2
"Unit";"Hydralisk";"Larva";382;2
"Unit";"Hydralisk";"Larva";382;2
"Unit";"Hydralisk";"Larva";382;2
"Unit";"Hydralisk";"Larva";382;2
"Unit";"Hydralisk";"Larva";382;2
"Unit";"Hydralisk";"Larva";382;2
"Unit";"Hydralisk";"Larva";382;2
"Unit";"Zergling";"Larva";434;1
"Unit";"Zergling";"Larva";434;1
"Unit";"Zergling";"Larva";434;1
"Unit";"Zergling";"Larva";434;1
"Unit";"Zergling";"Larva";434;1
"Unit";"Zergling";"Larva";434;1
"Unit";"Zergling";"Larva";434;1
"Unit";"Zergling";"Larva";434;1
"Unit";"Zergling";"Larva";434;1
"Unit";"Zergling";"Larva";434;1
"Unit";"Zergling";"Larva";434;1
"Unit";"Zergling";"Larva";434;1
"Unit";"Zergling";"Larva";434;1
"Unit";"Zergling";"Larva";434;1
"Unit";"Zergling";"Larva";434;1
"Unit";"Zergling";"Larva";434;1
"Unit";"Zergling";"Larva";434;1
"Unit";"Zergling";"Larva";434;1
"Unit";"Zergling";"Larva";434;1
"Unit";"Zergling";"Larva";434;1
"Unit";"Zergling";"Larva";434;1
"Unit";"Zergling";"Larva";434;1
"Unit";"Corruptor";"Larva";422;2
"Unit";"Corruptor";"Larva";422;2
"Unit";"Corruptor";"Larva";422;2
"Unit";"Corruptor";"Larva";422;2
"Unit";"Corruptor";"Larva";422;2
"Unit";"Corruptor";"Larva";422;2
"Unit";"Corruptor";"Larva";422;2
"Unit";"Hydralisk";"Larva";458;2
"Unit";"Hydralisk";"Larva";468;2
"Unit";"Hydralisk";"Larva";470;2
"Unit";"Hydralisk";"Larva";470;2
"Unit";"Hydralisk";"Larva";470;2
"Unit";"Hydralisk";"Larva";470;2
"Unit";"Hydralisk";"Larva";470;2
"Unit";"Hydralisk";"Larva";470;2
"Unit";"Hydralisk";"Larva";470;2
"Unit";"Hydralisk";"Larva";470;2
"Unit";"Hydralisk";"Larva";470;2
"Unit";"Hydralisk";"Larva";470;2
"Unit";"Hydralisk";"Larva";470;2
"Unit";"Hydralisk";"Larva";470;2
"Unit";"Hydralisk";"Larva";470;2
"Unit";"Hydralisk";"Larva";470;2
"Unit";"Hydralisk";"Larva";472;2
"Unit";"Hydralisk";"Larva";478;2
"Unit";"Hydralisk";"Larva";478;2
"Unit";"Hydralisk";"Larva";480;2
"Unit";"Hydralisk";"Larva";480;2
"Unit";"Hydralisk";"Larva";482;2
"Unit";"Hydralisk";"Larva";486;2
"Unit";"Hydralisk";"Larva";486;2
"Building";"Hatchery";NA;434;0
"Upgrade";"ZergMissileWeaponsLevel3";"EvolutionChamber";382;0
"Upgrade";"ZergGroundArmorsLevel3";"EvolutionChamber";382;0
"Unit";"Hydralisk";"Larva";508;2
"Unit";"Hydralisk";"Larva";518;2
"Unit";"Hydralisk";"Larva";518;2
"Unit";"Hydralisk";"Larva";518;2
"Unit";"Hydralisk";"Larva";518;2
"Unit";"Hydralisk";"Larva";518;2
"Unit";"Hydralisk";"Larva";518;2
"Unit";"Hydralisk";"Larva";518;2
"Unit";"Hydralisk";"Larva";518;2
"Unit";"Hydralisk";"Larva";518;2
"Unit";"Hydralisk";"Larva";518;2
"Unit";"Hydralisk";"Larva";518;2
"Unit";"Hydralisk";"Larva";518;2
"Unit";"Hydralisk";"Larva";518;2
"Unit";"Hydralisk";"Larva";518;2
"Unit";"Hydralisk";"Larva";518;2
"Unit";"Hydralisk";"Larva";518;2
"Unit";"Hydralisk";"Larva";518;2
"Building";"Extractor";NA;530;0
"Building";"Extractor";NA;530;0
"Unit";"Zergling";"Larva";540;1
"Unit";"Zergling";"Larva";540;1
"Unit";"Zergling";"Larva";542;1
"Unit";"Zergling";"Larva";542;1
"Unit";"Zergling";"Larva";542;1
"Unit";"Zergling";"Larva";542;1
"Unit";"Zergling";"Larva";544;1
"Unit";"Zergling";"Larva";544;1
"Unit";"Zergling";"Larva";544;1
"Unit";"Zergling";"Larva";544;1
"Unit";"Zergling";"Larva";544;1
"Unit";"Zergling";"Larva";544;1
"Unit";"Zergling";"Larva";544;1
"Unit";"Zergling";"Larva";544;1
"Unit";"Zergling";"Larva";544;1
"Unit";"Zergling";"Larva";544;1
"Unit";"Overlord";"Larva";560;0
"Unit";"Overlord";"Larva";560;0
"Unit";"Overlord";"Larva";560;0
"Unit";"Hydralisk";"Larva";576;2
"Unit";"Hydralisk";"Larva";576;2
"Unit";"Hydralisk";"Larva";576;2
"Unit";"Hydralisk";"Larva";576;2
"Unit";"Hydralisk";"Larva";576;2
"Unit";"Hydralisk";"Larva";576;2
"Unit";"Hydralisk";"Larva";576;2
"Unit";"Hydralisk";"Larva";576;2
"Unit";"Hydralisk";"Larva";576;2
"Unit";"Hydralisk";"Larva";576;2
"Unit";"Hydralisk";"Larva";576;2
"Unit";"Hydralisk";"Larva";576;2
"Unit";"Hydralisk";"Larva";576;2
"Unit";"Hydralisk";"Larva";576;2
"Building";"Hatchery";NA;530;0
"Unit";"Zergling";"Larva";592;1
"Unit";"Zergling";"Larva";592;1
"Unit";"Zergling";"Larva";592;1
"Unit";"Zergling";"Larva";592;1
"Unit";"Zergling";"Larva";592;1
"Unit";"Zergling";"Larva";592;1
"Unit";"Zergling";"Larva";592;1
"Unit";"Zergling";"Larva";592;1
"Unit";"Zergling";"Larva";592;1
"Unit";"Zergling";"Larva";592;1
"Unit";"Hydralisk";"Larva";604;2
"Unit";"Hydralisk";"Larva";604;2
"Unit";"Hydralisk";"Larva";604;2
"Unit";"Hydralisk";"Larva";604;2
"Unit";"Hydralisk";"Larva";604;2
"Unit";"Hydralisk";"Larva";604;2
"Unit";"Hydralisk";"Larva";604;2
"Unit";"Hydralisk";"Larva";604;2
"Unit";"Hydralisk";"Larva";604;2
"Unit";"Hydralisk";"Larva";604;2
"Unit";"Hydralisk";"Larva";604;2
"Unit";"Hydralisk";"Larva";604;2
"Unit";"Hydralisk";"Larva";604;2
"Unit";"Hydralisk";"Larva";604;2
"Unit";"Hydralisk";"Larva";604;2
"Unit";"Hydralisk";"Larva";604;2
"Unit";"Hydralisk";"Larva";604;2
"Unit";"Hydralisk";"Larva";604;2
"Unit";"Zergling";"Larva";614;1
"Unit";"Zergling";"Larva";614;1
"Unit";"Zergling";"Larva";614;1
"Unit";"Zergling";"Larva";614;1
"Unit";"Zergling";"Larva";614;1
"Unit";"Zergling";"Larva";614;1
"Unit";"Zergling";"Larva";614;1
"Unit";"Zergling";"Larva";614;1
"Unit";"Zergling";"Larva";614;1
"Unit";"Zergling";"Larva";614;1
"Unit";"Zergling";"Larva";614;1
"Unit";"Zergling";"Larva";614;1
"Unit";"Zergling";"Larva";614;1
"Unit";"Zergling";"Larva";614;1
"Unit";"Zergling";"Larva";614;1
"Unit";"Zergling";"Larva";614;1
"Unit";"Zergling";"Larva";614;1
"Unit";"Zergling";"Larva";614;1
"Unit";"Zergling";"Larva";614;1
"Unit";"Zergling";"Larva";614;1
"Unit";"Zergling";"Larva";614;1
"Unit";"Zergling";"Larva";614;1
"Unit";"Hydralisk";"Larva";650;2
"Unit";"Hydralisk";"Larva";650;2
"Building";"Hatchery";NA;592;0
"Unit";"Hydralisk";"Larva";672;2
"Unit";"Hydralisk";"Larva";676;2
"Unit";"Hydralisk";"Larva";676;2
"Unit";"Hydralisk";"Larva";676;2
"Unit";"Hydralisk";"Larva";676;2
"Unit";"Hydralisk";"Larva";676;2
"Unit";"Hydralisk";"Larva";676;2
"Unit";"Hydralisk";"Larva";676;2
"Unit";"Hydralisk";"Larva";676;2
"Unit";"Hydralisk";"Larva";676;2
"Unit";"Hydralisk";"Larva";676;2
"Unit";"Hydralisk";"Larva";676;2
"Unit";"Hydralisk";"Larva";676;2
"Unit";"Hydralisk";"Larva";676;2
"Unit";"Hydralisk";"Larva";676;2
"Unit";"Hydralisk";"Larva";676;2
"Unit";"Hydralisk";"Larva";676;2
"Unit";"Hydralisk";"Larva";682;2
"Unit";"Hydralisk";"Larva";682;2
"Unit";"Hydralisk";"Larva";682;2
"Unit";"Hydralisk";"Larva";682;2
"Unit";"Hydralisk";"Larva";682;2
"Unit";"Hydralisk";"Larva";682;2
"Unit";"Hydralisk";"Larva";682;2
"Unit";"Hydralisk";"Larva";682;2
"Unit";"Hydralisk";"Larva";682;2
"Unit";"Hydralisk";"Larva";682;2
"Unit";"Hydralisk";"Larva";682;2
"Unit";"Hydralisk";"Larva";682;2
"Unit";"Hydralisk";"Larva";682;2
"Unit";"Hydralisk";"Larva";682;2
"Unit";"Hydralisk";"Larva";682;2
"Unit";"Hydralisk";"Larva";682;2
"Building";"UltraliskCavern";NA;678;0
"Unit";"Hydralisk";"Larva";710;2
"Unit";"Hydralisk";"Larva";710;2
"Unit";"Hydralisk";"Larva";710;2
"Unit";"Hydralisk";"Larva";710;2
"Unit";"Hydralisk";"Larva";710;2
"Unit";"Hydralisk";"Larva";710;2
"Unit";"Hydralisk";"Larva";710;2
"Unit";"Hydralisk";"Larva";710;2
"Unit";"Hydralisk";"Larva";710;2
"Unit";"Hydralisk";"Larva";760;2
"Unit";"Hydralisk";"Larva";760;2
"Unit";"Hydralisk";"Larva";760;2
"Unit";"Hydralisk";"Larva";760;2
"Unit";"Hydralisk";"Larva";760;2
"Unit";"Hydralisk";"Larva";760;2
"Unit";"Hydralisk";"Larva";760;2
"Unit";"Hydralisk";"Larva";760;2
"Unit";"Hydralisk";"Larva";760;2
"Unit";"Hydralisk";"Larva";760;2
"Unit";"Overlord";"Larva";760;0
"Unit";"Overlord";"Larva";760;0
"Unit";"Overlord";"Larva";760;0
"Unit";"Overlord";"Larva";760;0
"Unit";"Hydralisk";"Larva";780;2
"Unit";"Hydralisk";"Larva";780;2
"Unit";"Hydralisk";"Larva";780;2
"Unit";"Hydralisk";"Larva";780;2
"Unit";"Hydralisk";"Larva";780;2
"Unit";"Hydralisk";"Larva";780;2
"Unit";"Hydralisk";"Larva";780;2
"Unit";"Hydralisk";"Larva";780;2
"Unit";"Hydralisk";"Larva";780;2
"Upgrade";"ChitinousPlating";"UltraliskCavern";760;0
"Building";"Hatchery";NA;760;0
"Unit";"Hydralisk";"Larva";804;2
"Unit";"Hydralisk";"Larva";804;2
"Unit";"Hydralisk";"Larva";804;2
"Unit";"Hydralisk";"Larva";804;2
"Unit";"Hydralisk";"Larva";804;2
"Unit";"Hydralisk";"Larva";804;2
"Unit";"Hydralisk";"Larva";804;2
"Unit";"Ultralisk";"Larva";780;6
"Unit";"Ultralisk";"Larva";780;6
"Unit";"Ultralisk";"Larva";780;6
"Unit";"Hydralisk";"Larva";836;2
"Unit";"Hydralisk";"Larva";836;2
"Unit";"Hydralisk";"Larva";836;2
"Unit";"Hydralisk";"Larva";836;2
"Unit";"Hydralisk";"Larva";836;2
"Unit";"Hydralisk";"Larva";836;2
"Unit";"Hydralisk";"Larva";838;2
"Unit";"Hydralisk";"Larva";848;2
"Building";"Hatchery";NA;804;0
"Unit";"Hydralisk";"Larva";848;2
"Unit";"Hydralisk";"Larva";848;2
"Unit";"Hydralisk";"Larva";848;2
"Unit";"Hydralisk";"Larva";848;2
"Unit";"Zergling";"Larva";852;1
"Unit";"Zergling";"Larva";852;1
"Unit";"Zergling";"Larva";852;1
"Unit";"Zergling";"Larva";852;1
"Unit";"Zergling";"Larva";852;1
"Unit";"Zergling";"Larva";852;1
"Unit";"Zergling";"Larva";852;1
"Unit";"Zergling";"Larva";852;1
"Unit";"Zergling";"Larva";852;1
"Unit";"Zergling";"Larva";852;1
"Unit";"Zergling";"Larva";852;1
"Unit";"Zergling";"Larva";852;1
"Unit";"Zergling";"Larva";852;1
"Unit";"Zergling";"Larva";852;1
"Unit";"Zergling";"Larva";852;1
"Unit";"Zergling";"Larva";852;1
"Unit";"Zergling";"Larva";852;1
"Unit";"Zergling";"Larva";852;1
"Unit";"Zergling";"Larva";852;1
"Unit";"Zergling";"Larva";852;1
"Unit";"Zergling";"Larva";852;1
"Unit";"Zergling";"Larva";852;1
"Unit";"Zergling";"Larva";852;1
"Unit";"Zergling";"Larva";852;1
"Unit";"Zergling";"Larva";852;1
"Unit";"Zergling";"Larva";852;1
"Unit";"Zergling";"Larva";852;1
"Unit";"Zergling";"Larva";852;1
"Unit";"Zergling";"Larva";852;1
"Unit";"Zergling";"Larva";852;1
"Unit";"Zergling";"Larva";852;1
"Unit";"Zergling";"Larva";852;1
"Unit";"Zergling";"Larva";852;1
"Unit";"Zergling";"Larva";852;1
"Unit";"Zergling";"Larva";852;1
"Unit";"Zergling";"Larva";852;1
"Unit";"Zergling";"Larva";852;1
"Unit";"Zergling";"Larva";852;1
"Unit";"Zergling";"Larva";852;1
"Unit";"Zergling";"Larva";852;1
"Unit";"Zergling";"Larva";852;1
"Unit";"Zergling";"Larva";852;1
"Unit";"Zergling";"Larva";852;1
"Unit";"Zergling";"Larva";852;1
"Unit";"Zergling";"Larva";852;1
"Unit";"Zergling";"Larva";852;1
"Unit";"Zergling";"Larva";852;1
"Unit";"Zergling";"Larva";852;1
"Unit";"Zergling";"Larva";852;1
"Unit";"Zergling";"Larva";852;1
"Unit";"Zergling";"Larva";852;1
"Unit";"Zergling";"Larva";852;1
"Unit";"Zergling";"Larva";852;1
"Unit";"Zergling";"Larva";852;1
"Unit";"Zergling";"Larva";852;1
"Unit";"Zergling";"Larva";852;1
"Unit";"Zergling";"Larva";860;1
"Unit";"Zergling";"Larva";860;1
"Unit";"Zergling";"Larva";860;1
"Unit";"Zergling";"Larva";860;1
"Unit";"Zergling";"Larva";860;1
"Unit";"Zergling";"Larva";860;1
"Unit";"Zergling";"Larva";860;1
"Unit";"Zergling";"Larva";860;1
"Unit";"Zergling";"Larva";860;1
"Unit";"Zergling";"Larva";860;1
"Upgrade";"ZergMeleeWeaponsLevel2";"EvolutionChamber";836;0
"Building";"Hatchery";NA;848;0
"Unit";"Zergling";"Larva";926;1
"Unit";"Zergling";"Larva";926;1
"Unit";"Zergling";"Larva";926;1
"Unit";"Zergling";"Larva";926;1
"Unit";"Zergling";"Larva";926;1
"Unit";"Zergling";"Larva";926;1
"Unit";"Zergling";"Larva";926;1
"Unit";"Zergling";"Larva";926;1
"Unit";"Zergling";"Larva";926;1
"Unit";"Zergling";"Larva";926;1
"Unit";"Zergling";"Larva";926;1
"Unit";"Zergling";"Larva";926;1
"Unit";"Zergling";"Larva";926;1
"Unit";"Zergling";"Larva";926;1
"Unit";"Zergling";"Larva";926;1
"Unit";"Zergling";"Larva";926;1
"Unit";"Hydralisk";"Larva";926;2
"Unit";"Hydralisk";"Larva";926;2
"Unit";"Zergling";"Larva";942;1
"Unit";"Zergling";"Larva";942;1
"Unit";"Zergling";"Larva";942;1
"Unit";"Zergling";"Larva";942;1
"Unit";"Zergling";"Larva";942;1
"Unit";"Zergling";"Larva";942;1
"Unit";"Zergling";"Larva";942;1
"Unit";"Zergling";"Larva";942;1
"Unit";"Zergling";"Larva";942;1
"Unit";"Zergling";"Larva";942;1
"Unit";"Zergling";"Larva";942;1
"Unit";"Zergling";"Larva";942;1
"Building";"Extractor";NA;946;0
"Building";"Extractor";NA;946;0
"Building";"Extractor";NA;946;0
"Building";"Extractor";NA;946;0
"Building";"Hatchery";NA;912;0
"Building";"Extractor";NA;964;0
"Building";"Extractor";NA;964;0
"Building";"SpawningPool";NA;963;0
"Unit";"Overlord";"Larva";973;0
"Unit";"Overlord";"Larva";973;0
"Unit";"Overlord";"Larva";973;0
"Unit";"Overlord";"Larva";973;0
"Unit";"Overlord";"Larva";973;0
"Unit";"Overlord";"Larva";973;0
"Unit";"Overlord";"Larva";973;0
"Unit";"Overlord";"Larva";973;0
"Unit";"Overlord";"Larva";973;0
"Unit";"Overlord";"Larva";973;0
"Unit";"Overlord";"Larva";973;0
"Unit";"Overlord";"Larva";973;0
"Building";"Extractor";NA;982;0
"Building";"Extractor";NA;982;0
"Building";"BanelingNest";NA;973;0
"Building";"Hatchery";NA;973;0
"Building";"Hatchery";NA;973;0
"Building";"HydraliskDen";NA;982;0
