"type";"unit_name";"on_building";"total_supply";"supply"
"Unit";"Overlord";"Larva";13;0
"Building";"Extractor";NA;17;0
"Unit";"Overlord";"Larva";21;0
"Building";"SpawningPool";NA;19;0
"Building";"Hatchery";NA;17;0
"Unit";"Zergling";"Larva";23;1
"Unit";"Zergling";"Larva";23;1
"Unit";"Zergling";"Larva";23;1
"Unit";"Zergling";"Larva";23;1
"Unit";"Queen";"Hatchery";23;2
"Unit";"Queen";"Hatchery";23;2
"Unit";"Overlord";"Larva";36;0
"Unit";"Zergling";"Larva";38;1
"Unit";"Zergling";"Larva";38;1
"Unit";"Zergling";"Larva";38;1
"Unit";"Zergling";"Larva";38;1
"Unit";"Overlord";"Larva";38;0
"Building";"Hatchery";NA;36;0
"Unit";"Queen";"Hatchery";41;2
"Building";"Extractor";NA;48;0
"Building";"Extractor";NA;48;0
"Building";"SporeCrawler";NA;53;0
"Building";"CreepTumorQueen";NA;55;0
"Building";"SporeCrawler";NA;53;0
"Building";"CreepTumorQueen";NA;55;0
"Unit";"Queen";"Hatchery";55;2
"Building";"CreepTumor";NA;65;0
"Unit";"Overlord";"Larva";66;0
"Unit";"Overlord";"Larva";66;0
"Building";"CreepTumorQueen";NA;68;0
"Building";"EvolutionChamber";NA;68;0
"Building";"EvolutionChamber";NA;68;0
"Unit";"Overlord";"Larva";68;0
"Unit";"Overlord";"Larva";68;0
"Building";"CreepTumorQueen";NA;68;0
"Building";"CreepTumor";NA;68;0
"Building";"HydraliskDen";NA;68;0
"Building";"CreepTumor";NA;73;0
"Building";"CreepTumorQueen";NA;74;0
"Building";"CreepTumor";NA;74;0
"Unit";"Queen";"Hatchery";68;2
"Unit";"Queen";"Hatchery";68;2
"Building";"Extractor";NA;74;0
"Building";"SporeCrawler";NA;74;0
"Building";"CreepTumor";NA;90;0
"Building";"CreepTumorQueen";NA;90;0
"Unit";"Overlord";"Larva";90;0
"Unit";"Overlord";"Larva";90;0
"Building";"CreepTumor";NA;90;0
"Building";"CreepTumorQueen";NA;90;0
"Building";"CreepTumorQueen";NA;90;0
"Building";"CreepTumor";NA;90;0
"Building";"CreepTumor";NA;90;0
"Building";"Extractor";NA;90;0
"Building";"Extractor";NA;90;0
"Building";"CreepTumorQueen";NA;95;0
"Building";"CreepTumor";NA;99;0
"Unit";"Hydralisk";"Larva";95;2
"Unit";"Hydralisk";"Larva";95;2
"Unit";"Hydralisk";"Larva";95;2
"Unit";"Hydralisk";"Larva";95;2
"Building";"CreepTumor";NA;99;0
"Building";"CreepTumor";NA;99;0
"Building";"CreepTumor";NA;99;0
"Building";"CreepTumor";NA;99;0
"Building";"CreepTumorQueen";NA;99;0
"Upgrade";"EvolveGroovedSpines";"HydraliskDen";90;0
"Building";"CreepTumor";NA;101;0
"Building";"CreepTumorQueen";NA;104;0
"Building";"CreepTumor";NA;104;0
"Building";"CreepTumorQueen";NA;112;0
"Building";"SporeCrawler";NA;99;0
"Building";"CreepTumor";NA;104;0
"Building";"LurkerDenMP";NA;83;0
"Unit";"Overlord";"Larva";112;0
"Unit";"Overlord";"Larva";112;0
"Unit";"Hydralisk";"Larva";112;2
"Unit";"Hydralisk";"Larva";112;2
"Unit";"Hydralisk";"Larva";112;2
"Unit";"Hydralisk";"Larva";112;2
"Building";"CreepTumor";NA;112;0
"Building";"CreepTumor";NA;112;0
"Building";"CreepTumor";NA;112;0
"Building";"CreepTumorQueen";NA;114;0
"Building";"CreepTumorQueen";NA;120;0
"Building";"CreepTumor";NA;112;0
"Building";"CreepTumor";NA;120;0
"Building";"CreepTumor";NA;120;0
"Upgrade";"Burrow";"Hatchery";99;0
"Building";"CreepTumor";NA;120;0
"Unit";"Hydralisk";"Larva";120;2
"Unit";"Hydralisk";"Larva";120;2
"Unit";"Hydralisk";"Larva";120;2
"Building";"CreepTumor";NA;120;0
"Unit";"Hydralisk";"Larva";120;2
"Unit";"Hydralisk";"Larva";120;2
"Unit";"Hydralisk";"Larva";120;2
"Building";"CreepTumor";NA;126;0
"Unit";"Overlord";"Larva";120;0
"Unit";"Overlord";"Larva";120;0
"Unit";"Overlord";"Larva";120;0
"Unit";"Overlord";"Larva";120;0
"Unit";"Overlord";"Larva";120;0
"Unit";"Overlord";"Larva";120;0
"Unit";"Overlord";"Larva";120;0
"Upgrade";"EvolveMuscularAugments";"HydraliskDen";112;0
"Unit";"Hydralisk";"Larva";120;2
"Unit";"Hydralisk";"Larva";120;2
"Unit";"Hydralisk";"Larva";120;2
"Unit";"Hydralisk";"Larva";120;2
"Building";"CreepTumorQueen";NA;132;0
"Building";"CreepTumor";NA;132;0
"Building";"CreepTumorQueen";NA;132;0
"Building";"CreepTumor";NA;132;0
"Upgrade";"ZergMissileWeaponsLevel1";"EvolutionChamber";112;0
"Upgrade";"ZergGroundArmorsLevel1";"EvolutionChamber";112;0
"Building";"CreepTumor";NA;132;0
"Building";"Hatchery";NA;112;0
"Building";"CreepTumor";NA;138;0
"Building";"CreepTumor";NA;140;0
"Building";"CreepTumor";NA;140;0
"Building";"CreepTumor";NA;141;0
"Building";"CreepTumor";NA;141;0
"Building";"CreepTumor";NA;141;0
"Building";"CreepTumor";NA;141;0
"Building";"CreepTumor";NA;141;0
"Unit";"Overlord";"Larva";141;0
"Unit";"Overlord";"Larva";141;0
"Unit";"Zergling";"Larva";141;1
"Unit";"Zergling";"Larva";141;1
"Unit";"Zergling";"Larva";141;1
"Unit";"Zergling";"Larva";141;1
"Unit";"Zergling";"Larva";141;1
"Unit";"Zergling";"Larva";141;1
"Unit";"Zergling";"Larva";141;1
"Unit";"Zergling";"Larva";141;1
"Building";"CreepTumor";NA;146;0
"Unit";"Zergling";"Larva";146;1
"Unit";"Zergling";"Larva";146;1
"Unit";"Zergling";"Larva";146;1
"Unit";"Zergling";"Larva";146;1
"Unit";"Hydralisk";"Larva";146;2
"Unit";"Hydralisk";"Larva";146;2
"Unit";"Hydralisk";"Larva";146;2
"Unit";"Hydralisk";"Larva";146;2
"Unit";"Hydralisk";"Larva";146;2
"Building";"Extractor";NA;154;0
"Building";"Extractor";NA;154;0
"Building";"SpineCrawler";NA;146;0
"Building";"SpineCrawler";NA;146;0
"Building";"Spire";NA;126;0
"Building";"SpineCrawler";NA;146;0
"Building";"CreepTumor";NA;175;0
"Unit";"Hydralisk";"Larva";162;2
"Unit";"Hydralisk";"Larva";163;2
"Unit";"Hydralisk";"Larva";163;2
"Building";"SpineCrawler";NA;154;0
"Building";"SpineCrawler";NA;154;0
"Building";"SpineCrawler";NA;154;0
"Building";"CreepTumor";NA;175;0
"Building";"CreepTumor";NA;175;0
"Building";"CreepTumor";NA;181;0
"Building";"CreepTumor";NA;181;0
"Building";"SporeCrawler";NA;175;0
"Unit";"Zergling";"Larva";181;1
"Unit";"Zergling";"Larva";181;1
"Unit";"Zergling";"Larva";181;1
"Unit";"Zergling";"Larva";181;1
"Unit";"Zergling";"Larva";181;1
"Unit";"Zergling";"Larva";181;1
"Unit";"Zergling";"Larva";181;1
"Unit";"Zergling";"Larva";181;1
"Unit";"Zergling";"Larva";181;1
"Unit";"Zergling";"Larva";181;1
"Unit";"Zergling";"Larva";181;1
"Unit";"Zergling";"Larva";181;1
"Unit";"Zergling";"Larva";181;1
"Unit";"Zergling";"Larva";181;1
"Unit";"Zergling";"Larva";181;1
"Unit";"Zergling";"Larva";181;1
"Unit";"Zergling";"Larva";181;1
"Unit";"Zergling";"Larva";181;1
"Unit";"Zergling";"Larva";181;1
"Unit";"Zergling";"Larva";181;1
"Building";"CreepTumor";NA;181;0
"Building";"CreepTumor";NA;181;0
"Unit";"Mutalisk";"Larva";183;2
"Unit";"Mutalisk";"Larva";183;2
"Unit";"Mutalisk";"Larva";187;2
"Unit";"Mutalisk";"Larva";187;2
"Unit";"Mutalisk";"Larva";191;2
"Unit";"Mutalisk";"Larva";195;2
"Unit";"Mutalisk";"Larva";195;2
"Unit";"Mutalisk";"Larva";197;2
"Unit";"Mutalisk";"Larva";197;2
"Unit";"Mutalisk";"Larva";201;2
"Building";"CreepTumor";NA;201;0
"Building";"CreepTumor";NA;201;0
"Unit";"Overlord";"Larva";201;0
"Unit";"Overlord";"Larva";201;0
"Unit";"Mutalisk";"Larva";224;2
"Unit";"Mutalisk";"Larva";224;2
"Unit";"Mutalisk";"Larva";224;2
"Unit";"Mutalisk";"Larva";224;2
"Building";"CreepTumor";NA;224;0
"Building";"CreepTumor";NA;224;0
"Unit";"Mutalisk";"Larva";235;2
"Unit";"Mutalisk";"Larva";235;2
"Unit";"Mutalisk";"Larva";235;2
"Unit";"Mutalisk";"Larva";235;2
"Unit";"Zergling";"Larva";235;1
"Unit";"Zergling";"Larva";235;1
"Unit";"Mutalisk";"Larva";235;2
"Unit";"Mutalisk";"Larva";235;2
"Unit";"Mutalisk";"Larva";243;2
"Building";"BanelingNest";NA;235;0
"Unit";"Baneling";"Zergling";251;0
"Unit";"Baneling";"Zergling";251;0
"Unit";"Baneling";"Zergling";251;0
"Unit";"Baneling";"Zergling";251;0
"Unit";"Baneling";"Zergling";251;0
"Unit";"Baneling";"Zergling";251;0
"Unit";"Baneling";"Zergling";251;0
"Unit";"Baneling";"Zergling";251;0
"Unit";"Baneling";"Zergling";251;0
"Unit";"Mutalisk";"Larva";251;2
"Unit";"Mutalisk";"Larva";251;2
"Unit";"Mutalisk";"Larva";251;2
"Unit";"Baneling";"Zergling";251;0
"Unit";"Baneling";"Zergling";251;0
"Unit";"Baneling";"Zergling";251;0
"Unit";"Baneling";"Zergling";251;0
"Unit";"Baneling";"Zergling";251;0
"Unit";"Baneling";"Zergling";251;0
"Unit";"Baneling";"Zergling";251;0
"Unit";"Baneling";"Zergling";251;0
"Unit";"Baneling";"Zergling";251;0
"Upgrade";"ZergMissileWeaponsLevel2";"EvolutionChamber";224;0
"Building";"CreepTumor";NA;257;0
"Building";"CreepTumor";NA;257;0
"Building";"CreepTumor";NA;257;0
"Building";"SpineCrawler";NA;251;0
"Building";"SpineCrawler";NA;251;0
"Building";"SpineCrawler";NA;251;0
"Unit";"Mutalisk";"Larva";257;2
"Unit";"Mutalisk";"Larva";257;2
"Unit";"Mutalisk";"Larva";257;2
"Unit";"Mutalisk";"Larva";257;2
"Building";"CreepTumorQueen";NA;265;0
"Building";"CreepTumorQueen";NA;265;0
"Building";"CreepTumorQueen";NA;265;0
"Building";"CreepTumorQueen";NA;265;0
"Building";"CreepTumor";NA;265;0
"Building";"CreepTumor";NA;265;0
"Building";"SporeCrawler";NA;265;0
"Building";"SporeCrawler";NA;265;0
"Unit";"Zergling";"Larva";265;1
"Unit";"Zergling";"Larva";265;1
"Unit";"Zergling";"Larva";265;1
"Unit";"Zergling";"Larva";265;1
"Unit";"Zergling";"Larva";265;1
"Unit";"Zergling";"Larva";265;1
"Unit";"Zergling";"Larva";265;1
"Unit";"Zergling";"Larva";265;1
"Unit";"Zergling";"Larva";265;1
"Unit";"Zergling";"Larva";265;1
"Unit";"Zergling";"Larva";265;1
"Unit";"Zergling";"Larva";265;1
"Unit";"Zergling";"Larva";265;1
"Unit";"Zergling";"Larva";265;1
"Unit";"Zergling";"Larva";265;1
"Unit";"Zergling";"Larva";265;1
"Unit";"Zergling";"Larva";265;1
"Unit";"Zergling";"Larva";265;1
"Unit";"Zergling";"Larva";265;1
"Unit";"Zergling";"Larva";265;1
"Building";"InfestationPit";NA;265;0
"Building";"SporeCrawler";NA;265;0
