"type";"unit_name";"on_building";"total_supply_lag";"supply"
"Unit";"Overlord";"Larva";13;0
"Building";"Hatchery";NA;19;0
"Building";"Extractor";NA;19;0
"Building";"SpawningPool";NA;20;0
"Unit";"Overlord";"Larva";22;0
"Unit";"Zergling";"Larva";23;1
"Unit";"Zergling";"Larva";24;1
"Unit";"Queen";"Hatchery";25;2
"Unit";"Queen";"Hatchery";27;2
"Unit";"Zergling";"Larva";29;1
"Unit";"Zergling";"Larva";30;1
"Building";"Hatchery";NA;34;0
"Unit";"Zergling";"Larva";34;1
"Unit";"Zergling";"Larva";35;1
"Unit";"Zergling";"Larva";36;1
"Unit";"Zergling";"Larva";37;1
"Unit";"Overlord";"Larva";39;0
"Unit";"Queen";"Hatchery";39;2
"Unit";"Zergling";"Larva";45;1
"Unit";"Zergling";"Larva";46;1
"Building";"CreepTumorQueen";NA;47;0
"Unit";"Overlord";"Larva";49;0
"Unit";"Overlord";"Larva";52;0
"Unit";"Overlord";"Larva";52;0
"Building";"SporeCrawler";NA;52;0
"Unit";"Queen";"Hatchery";52;2
"Building";"SporeCrawler";NA;54;0
"Unit";"Zergling";"Larva";54;1
"Unit";"Zergling";"Larva";55;1
"Building";"CreepTumor";NA;57;0
"Unit";"Queen";"Hatchery";62;2
"Building";"SporeCrawler";NA;64;0
"Unit";"Overlord";"Larva";66;0
"Unit";"Overlord";"Larva";69;0
"Building";"CreepTumorQueen";NA;71;0
"Building";"CreepTumorQueen";NA;78;0
"Unit";"Queen";"Hatchery";78;2
"Building";"CreepTumor";NA;80;0
"Building";"RoachWarren";NA;81;0
"Building";"CreepTumor";NA;81;0
"Unit";"Overlord";"Larva";81;0
"Unit";"Zergling";"Larva";81;1
"Unit";"Zergling";"Larva";82;1
"Building";"CreepTumorQueen";NA;83;0
"Unit";"Zergling";"Larva";83;1
"Unit";"Zergling";"Larva";84;1
"Unit";"Zergling";"Larva";85;1
"Unit";"Zergling";"Larva";86;1
"Unit";"Zergling";"Larva";87;1
"Unit";"Zergling";"Larva";88;1
"Unit";"Zergling";"Larva";89;1
"Unit";"Zergling";"Larva";90;1
"Building";"CreepTumorQueen";NA;91;0
"Building";"Extractor";NA;91;0
"Building";"CreepTumor";NA;91;0
"Building";"Extractor";NA;91;0
"Unit";"Zergling";"Larva";91;1
"Unit";"Zergling";"Larva";92;1
"Unit";"Zergling";"Larva";93;1
"Unit";"Zergling";"Larva";94;1
"Unit";"Zergling";"Larva";95;1
"Unit";"Zergling";"Larva";96;1
"Unit";"Queen";"Hatchery";101;2
"Unit";"Zergling";"Larva";103;1
"Unit";"Zergling";"Larva";104;1
"Unit";"Overlord";"Larva";108;0
"Unit";"Overlord";"Larva";108;0
"Unit";"Overlord";"Larva";108;0
"Building";"CreepTumor";NA;108;0
"Building";"CreepTumor";NA;108;0
"Building";"CreepTumor";NA;108;0
"Unit";"Roach";"Larva";108;2
"Unit";"Roach";"Larva";110;2
"Unit";"Roach";"Larva";112;2
"Unit";"Roach";"Larva";114;2
"Unit";"Roach";"Larva";116;2
"Building";"CreepTumor";NA;118;0
"Unit";"Overlord";"Larva";118;0
"Unit";"Overlord";"Larva";118;0
"Building";"CreepTumorQueen";NA;118;0
"Unit";"Roach";"Larva";118;2
"Unit";"Roach";"Larva";120;2
"Unit";"Roach";"Larva";122;2
"Unit";"Roach";"Larva";124;2
"Building";"EvolutionChamber";NA;126;0
"Building";"Extractor";NA;130;0
"Building";"CreepTumor";NA;130;0
"Building";"Extractor";NA;130;0
"Building";"CreepTumor";NA;130;0
"Building";"HydraliskDen";NA;130;0
"Building";"CreepTumor";NA;130;0
"Building";"CreepTumor";NA;130;0
"Unit";"Overlord";"Larva";132;0
"Upgrade";"GlialReconstitution";"RoachWarren";132;0
"Unit";"Overlord";"Larva";136;0
"Building";"CreepTumor";NA;144;0
"Building";"CreepTumor";NA;144;0
"Building";"CreepTumor";NA;144;0
"Building";"CreepTumor";NA;144;0
"Unit";"Hydralisk";"Larva";144;2
"Unit";"Overlord";"Larva";146;0
"Unit";"Overlord";"Larva";146;0
"Unit";"Overlord";"Larva";146;0
"Building";"CreepTumorQueen";NA;146;0
"Building";"CreepTumorQueen";NA;146;0
"Building";"CreepTumorQueen";NA;146;0
"Building";"Hatchery";NA;146;0
"Unit";"Hydralisk";"Larva";146;2
"Unit";"Hydralisk";"Larva";148;2
"Unit";"Hydralisk";"Larva";150;2
"Unit";"Hydralisk";"Larva";152;2
"Building";"CreepTumorQueen";NA;154;0
"Building";"CreepTumorQueen";NA;154;0
"Building";"CreepTumorQueen";NA;154;0
"Building";"CreepTumorQueen";NA;154;0
"Unit";"Hydralisk";"Larva";154;2
"Unit";"Hydralisk";"Larva";156;2
"Unit";"Overlord";"Larva";158;0
"Building";"Extractor";NA;162;0
"Unit";"Hydralisk";"Larva";162;2
"Building";"CreepTumor";NA;164;0
"Building";"CreepTumor";NA;164;0
"Building";"CreepTumor";NA;164;0
"Unit";"Hydralisk";"Larva";164;2
"Building";"SpineCrawler";NA;166;0
"Building";"CreepTumor";NA;166;0
"Building";"CreepTumor";NA;166;0
"Building";"CreepTumor";NA;166;0
"Building";"LurkerDenMP";NA;166;0
"Unit";"Hydralisk";"Larva";166;2
"Unit";"Roach";"Larva";168;2
"Unit";"Roach";"Larva";170;2
"Unit";"Roach";"Larva";172;2
"Unit";"Roach";"Larva";174;2
"Unit";"Overlord";"Larva";176;0
"Unit";"Roach";"Larva";176;2
"Unit";"Roach";"Larva";178;2
"Unit";"Roach";"Larva";180;2
"Unit";"Roach";"Larva";182;2
"Unit";"Roach";"Larva";184;2
"Unit";"Roach";"Larva";186;2
"Building";"CreepTumor";NA;188;0
"Building";"CreepTumor";NA;188;0
"Unit";"Overlord";"Larva";188;0
"Unit";"Roach";"Larva";188;2
"Unit";"Roach";"Larva";190;2
"Unit";"Roach";"Larva";192;2
"Unit";"Roach";"Larva";194;2
"Unit";"Roach";"Larva";196;2
"Unit";"Roach";"Larva";198;2
"Unit";"Roach";"Larva";200;2
"Unit";"Roach";"Larva";202;2
"Unit";"Roach";"Larva";204;2
"Unit";"Roach";"Larva";206;2
"Building";"CreepTumorQueen";NA;208;0
"Building";"CreepTumorQueen";NA;208;0
"Building";"CreepTumorQueen";NA;208;0
"Unit";"Roach";"Larva";208;2
"Unit";"Roach";"Larva";210;2
"Unit";"Roach";"Larva";212;2
"Unit";"Roach";"Larva";214;2
"Unit";"Roach";"Larva";216;2
"Unit";"Roach";"Larva";218;2
"Unit";"Roach";"Larva";220;2
"Building";"CreepTumor";NA;222;0
"Building";"CreepTumor";NA;222;0
"Unit";"Hydralisk";"Larva";222;2
"Unit";"Roach";"Larva";224;2
"Unit";"Zergling";"Larva";226;1
"Unit";"Zergling";"Larva";227;1
"Unit";"Zergling";"Larva";228;1
"Unit";"Zergling";"Larva";229;1
"Unit";"Zergling";"Larva";230;1
"Unit";"Zergling";"Larva";231;1
"Unit";"Roach";"Larva";232;2
"Unit";"Zergling";"Larva";234;1
"Unit";"Zergling";"Larva";235;1
"Unit";"Zergling";"Larva";236;1
"Unit";"Zergling";"Larva";237;1
"Building";"CreepTumor";NA;238;0
"Building";"CreepTumor";NA;238;0
"Building";"CreepTumor";NA;238;0
"Building";"CreepTumor";NA;238;0
"Unit";"Roach";"Larva";238;2
"Building";"CreepTumor";NA;240;0
"Building";"CreepTumor";NA;240;0
"Unit";"Overlord";"Larva";240;0
"Unit";"Overlord";"Larva";240;0
"Unit";"Zergling";"Larva";240;1
"Unit";"Zergling";"Larva";241;1
"Unit";"Zergling";"Larva";242;1
"Unit";"Zergling";"Larva";243;1
"Unit";"Zergling";"Larva";244;1
"Unit";"Zergling";"Larva";245;1
"Unit";"Zergling";"Larva";246;1
"Unit";"Zergling";"Larva";247;1
"Unit";"Overlord";"Larva";248;0
"Unit";"Zergling";"Larva";248;1
"Unit";"Zergling";"Larva";249;1
"Unit";"Overlord";"Larva";250;0
"Unit";"Roach";"Larva";250;2
"Unit";"Zergling";"Larva";252;1
"Unit";"Zergling";"Larva";253;1
"Unit";"Zergling";"Larva";254;1
"Unit";"Zergling";"Larva";255;1
"Unit";"Zergling";"Larva";256;1
"Unit";"Zergling";"Larva";257;1
"Unit";"Zergling";"Larva";258;1
"Unit";"Zergling";"Larva";259;1
"Unit";"Zergling";"Larva";260;1
"Unit";"Zergling";"Larva";261;1
"Unit";"Zergling";"Larva";262;1
"Unit";"Zergling";"Larva";263;1
"Unit";"Zergling";"Larva";264;1
"Unit";"Zergling";"Larva";265;1
"Unit";"Zergling";"Larva";266;1
"Unit";"Zergling";"Larva";267;1
"Unit";"Zergling";"Larva";268;1
"Unit";"Zergling";"Larva";269;1
"Unit";"Hydralisk";"Larva";270;2
"Unit";"Hydralisk";"Larva";272;2
"Unit";"Zergling";"Larva";274;1
"Unit";"Zergling";"Larva";275;1
"Unit";"Roach";"Larva";276;2
"Unit";"Zergling";"Larva";278;1
"Unit";"Zergling";"Larva";279;1
"Unit";"Zergling";"Larva";280;1
"Unit";"Zergling";"Larva";281;1
"Unit";"Roach";"Larva";282;2
"Unit";"Zergling";"Larva";284;1
"Unit";"Zergling";"Larva";285;1
"Unit";"Zergling";"Larva";286;1
"Unit";"Zergling";"Larva";287;1
"Unit";"Zergling";"Larva";288;1
"Unit";"Zergling";"Larva";289;1
"Unit";"Hydralisk";"Larva";290;2
"Unit";"Hydralisk";"Larva";292;2
"Unit";"Hydralisk";"Larva";294;2
"Unit";"Hydralisk";"Larva";296;2
"Unit";"Hydralisk";"Larva";298;2
"Unit";"Hydralisk";"Larva";300;2
"Unit";"Hydralisk";"Larva";302;2
"Unit";"Zergling";"Larva";304;1
"Unit";"Zergling";"Larva";305;1
"Unit";"Zergling";"Larva";306;1
"Unit";"Zergling";"Larva";307;1
"Unit";"Zergling";"Larva";308;1
"Unit";"Zergling";"Larva";309;1
"Unit";"Hydralisk";"Larva";310;2
"Unit";"Zergling";"Larva";312;1
"Unit";"Zergling";"Larva";313;1
"Unit";"Hydralisk";"Larva";314;2
"Unit";"Hydralisk";"Larva";316;2
"Unit";"Hydralisk";"Larva";318;2
"Unit";"Hydralisk";"Larva";320;2
"Building";"CreepTumor";NA;322;0
"Building";"CreepTumor";NA;322;0
"Building";"Extractor";NA;328;0
"Unit";"Roach";"Larva";328;2
"Building";"Extractor";NA;330;0
"Building";"InfestationPit";NA;333;0
"Unit";"Roach";"Larva";333;2
"Unit";"Roach";"Larva";335;2
"Unit";"Roach";"Larva";337;2
"Unit";"Zergling";"Larva";339;1
"Unit";"Zergling";"Larva";340;1
"Unit";"Roach";"Larva";341;2
"Unit";"Zergling";"Larva";343;1
"Unit";"Zergling";"Larva";344;1
"Unit";"Roach";"Larva";345;2
"Unit";"Zergling";"Larva";347;1
"Unit";"Zergling";"Larva";348;1
"Unit";"Hydralisk";"Larva";349;2
"Unit";"Hydralisk";"Larva";351;2
"Unit";"Hydralisk";"Larva";353;2
"Unit";"Hydralisk";"Larva";355;2
"Unit";"Hydralisk";"Larva";357;2
"Unit";"Hydralisk";"Larva";359;2
"Unit";"Zergling";"Larva";361;1
"Unit";"Zergling";"Larva";362;1
"Unit";"Zergling";"Larva";363;1
"Unit";"Zergling";"Larva";364;1
"Unit";"Zergling";"Larva";365;1
"Unit";"Zergling";"Larva";366;1
"Unit";"Hydralisk";"Larva";367;2
"Building";"CreepTumor";NA;370;0
"Building";"CreepTumor";NA;370;0
"Unit";"Hydralisk";"Larva";370;2
"Unit";"Zergling";"Larva";372;1
"Unit";"Zergling";"Larva";373;1
"Unit";"Zergling";"Larva";374;1
"Unit";"Zergling";"Larva";375;1
"Unit";"Zergling";"Larva";376;1
"Unit";"Zergling";"Larva";377;1
"Unit";"Zergling";"Larva";378;1
"Unit";"Zergling";"Larva";379;1
"Unit";"Zergling";"Larva";380;1
"Unit";"Zergling";"Larva";381;1
"Unit";"Zergling";"Larva";382;1
"Unit";"Zergling";"Larva";383;1
"Unit";"Zergling";"Larva";384;1
"Unit";"Zergling";"Larva";385;1
"Unit";"Zergling";"Larva";386;1
"Unit";"Zergling";"Larva";387;1
"Building";"CreepTumor";NA;388;0
"Building";"CreepTumor";NA;388;0
"Unit";"Zergling";"Larva";388;1
"Unit";"Zergling";"Larva";389;1
"Unit";"Zergling";"Larva";390;1
"Unit";"Zergling";"Larva";391;1
"Building";"CreepTumor";NA;392;0
"Unit";"Zergling";"Larva";392;1
"Unit";"Zergling";"Larva";393;1
"Unit";"Zergling";"Larva";394;1
"Unit";"Zergling";"Larva";395;1
"Unit";"Zergling";"Larva";396;1
"Unit";"Zergling";"Larva";397;1
"Unit";"Zergling";"Larva";398;1
"Unit";"Zergling";"Larva";399;1
"Unit";"Zergling";"Larva";400;1
"Unit";"Zergling";"Larva";401;1
"Building";"Hatchery";NA;402;0
"Unit";"Zergling";"Larva";402;1
"Unit";"Zergling";"Larva";403;1
"Unit";"Zergling";"Larva";404;1
"Unit";"Zergling";"Larva";405;1
"Unit";"Zergling";"Larva";406;1
"Unit";"Zergling";"Larva";407;1
"Unit";"Zergling";"Larva";408;1
"Unit";"Zergling";"Larva";409;1
"Unit";"Zergling";"Larva";410;1
"Unit";"Zergling";"Larva";411;1
"Building";"EvolutionChamber";NA;415;0
"Unit";"Zergling";"Larva";416;1
"Unit";"Zergling";"Larva";417;1
"Unit";"Zergling";"Larva";418;1
"Unit";"Zergling";"Larva";419;1
"Unit";"Zergling";"Larva";420;1
"Unit";"Zergling";"Larva";421;1
"Unit";"Zergling";"Larva";422;1
"Unit";"Zergling";"Larva";423;1
"Unit";"Zergling";"Larva";424;1
"Unit";"Zergling";"Larva";425;1
"Unit";"Zergling";"Larva";426;1
"Unit";"Zergling";"Larva";427;1
"Unit";"Zergling";"Larva";428;1
"Unit";"Zergling";"Larva";429;1
"Unit";"Zergling";"Larva";430;1
"Unit";"Zergling";"Larva";431;1
"Unit";"Zergling";"Larva";432;1
"Unit";"Zergling";"Larva";433;1
"Unit";"Zergling";"Larva";434;1
"Unit";"Zergling";"Larva";435;1
"Unit";"Hydralisk";"Larva";436;2
"Unit";"Zergling";"Larva";438;1
"Unit";"Zergling";"Larva";439;1
"Unit";"Hydralisk";"Larva";440;2
"Unit";"Hydralisk";"Larva";449;2
"Unit";"Hydralisk";"Larva";451;2
"Unit";"Hydralisk";"Larva";453;2
"Unit";"Hydralisk";"Larva";455;2
"Unit";"Hydralisk";"Larva";457;2
"Unit";"Hydralisk";"Larva";459;2
"Unit";"Hydralisk";"Larva";461;2
"Unit";"Hydralisk";"Larva";463;2
"Building";"CreepTumor";NA;465;0
"Building";"CreepTumor";NA;465;0
"Unit";"Hydralisk";"Larva";465;2
"Unit";"Hydralisk";"Larva";467;2
"Unit";"Hydralisk";"Larva";469;2
"Unit";"Hydralisk";"Larva";471;2
"Unit";"Hydralisk";"Larva";473;2
"Unit";"Hydralisk";"Larva";475;2
"Unit";"Roach";"Larva";477;2
"Unit";"Roach";"Larva";479;2
"Unit";"Roach";"Larva";481;2
"Unit";"Zergling";"Larva";483;1
"Unit";"Zergling";"Larva";484;1
"Unit";"Zergling";"Larva";485;1
"Unit";"Zergling";"Larva";486;1
"Unit";"Roach";"Larva";487;2
"Unit";"Zergling";"Larva";489;1
"Unit";"Zergling";"Larva";490;1
"Unit";"Zergling";"Larva";491;1
"Unit";"Zergling";"Larva";492;1
"Unit";"Zergling";"Larva";493;1
"Unit";"Zergling";"Larva";494;1
"Building";"CreepTumor";NA;495;0
"Unit";"Roach";"Larva";495;2
"Unit";"Hydralisk";"Larva";497;2
"Unit";"Hydralisk";"Larva";499;2
"Unit";"Hydralisk";"Larva";501;2
"Unit";"Roach";"Larva";503;2
"Unit";"Roach";"Larva";505;2
"Unit";"Roach";"Larva";507;2
"Unit";"Roach";"Larva";509;2
"Unit";"Roach";"Larva";511;2
"Unit";"Zergling";"Larva";513;1
"Unit";"Zergling";"Larva";514;1
"Unit";"Hydralisk";"Larva";515;2
"Unit";"Hydralisk";"Larva";517;2
"Unit";"Zergling";"Larva";519;1
"Unit";"Zergling";"Larva";520;1
"Unit";"Zergling";"Larva";521;1
"Unit";"Zergling";"Larva";522;1
"Unit";"Zergling";"Larva";523;1
"Unit";"Zergling";"Larva";524;1
"Unit";"Zergling";"Larva";525;1
"Unit";"Zergling";"Larva";526;1
"Unit";"Zergling";"Larva";527;1
"Unit";"Zergling";"Larva";528;1
"Unit";"Zergling";"Larva";529;1
"Unit";"Zergling";"Larva";530;1
"Unit";"Zergling";"Larva";531;1
"Unit";"Zergling";"Larva";532;1
"Unit";"Zergling";"Larva";533;1
"Unit";"Zergling";"Larva";534;1
"Unit";"Roach";"Larva";535;2
"Unit";"Zergling";"Larva";537;1
"Unit";"Zergling";"Larva";538;1
"Unit";"Zergling";"Larva";539;1
"Unit";"Zergling";"Larva";540;1
"Unit";"Zergling";"Larva";541;1
"Unit";"Zergling";"Larva";542;1
"Unit";"Zergling";"Larva";543;1
"Unit";"Zergling";"Larva";544;1
"Unit";"Zergling";"Larva";545;1
"Unit";"Zergling";"Larva";546;1
"Unit";"Zergling";"Larva";547;1
"Unit";"Zergling";"Larva";548;1
"Unit";"Zergling";"Larva";549;1
"Unit";"Zergling";"Larva";550;1
"Unit";"Roach";"Larva";551;2
"Unit";"Zergling";"Larva";553;1
"Unit";"Zergling";"Larva";554;1
"Unit";"Zergling";"Larva";555;1
"Unit";"Zergling";"Larva";556;1
"Unit";"Roach";"Larva";557;2
"Unit";"Zergling";"Larva";559;1
"Unit";"Zergling";"Larva";560;1
"Unit";"Roach";"Larva";561;2
"Unit";"Zergling";"Larva";563;1
"Unit";"Zergling";"Larva";564;1
"Unit";"Zergling";"Larva";565;1
"Unit";"Zergling";"Larva";566;1
"Unit";"Hydralisk";"Larva";567;2
"Unit";"Hydralisk";"Larva";569;2
"Unit";"Zergling";"Larva";571;1
"Unit";"Zergling";"Larva";572;1
"Unit";"Zergling";"Larva";573;1
"Unit";"Zergling";"Larva";574;1
"Unit";"Zergling";"Larva";575;1
"Unit";"Zergling";"Larva";576;1
"Unit";"Zergling";"Larva";577;1
"Unit";"Zergling";"Larva";578;1
"Unit";"Hydralisk";"Larva";579;2
"Unit";"Hydralisk";"Larva";581;2
"Unit";"Hydralisk";"Larva";583;2
"Unit";"Hydralisk";"Larva";585;2
"Unit";"Hydralisk";"Larva";587;2
"Unit";"Hydralisk";"Larva";589;2
"Unit";"Zergling";"Larva";591;1
"Unit";"Zergling";"Larva";592;1
"Building";"Spire";NA;602;0
"Unit";"Hydralisk";"Larva";602;2
"Unit";"Roach";"Larva";604;2
"Unit";"Roach";"Larva";606;2
"Building";"CreepTumor";NA;608;0
"Building";"CreepTumor";NA;608;0
"Unit";"Roach";"Larva";608;2
"Unit";"Hydralisk";"Larva";610;2
"Unit";"Roach";"Larva";612;2
"Building";"SpineCrawler";NA;614;0
"Building";"CreepTumor";NA;614;0
"Unit";"Roach";"Larva";614;2
"Unit";"Hydralisk";"Larva";616;2
"Building";"SpineCrawler";NA;618;0
"Building";"CreepTumor";NA;618;0
"Unit";"Roach";"Larva";618;2
"Unit";"Roach";"Larva";620;2
"Unit";"Roach";"Larva";622;2
"Unit";"Roach";"Larva";624;2
"Unit";"Hydralisk";"Larva";626;2
"Unit";"Zergling";"Larva";628;1
"Unit";"Zergling";"Larva";629;1
"Unit";"Zergling";"Larva";630;1
"Unit";"Zergling";"Larva";631;1
"Unit";"Zergling";"Larva";632;1
"Unit";"Zergling";"Larva";633;1
"Unit";"Zergling";"Larva";634;1
"Unit";"Zergling";"Larva";635;1
"Unit";"Zergling";"Larva";636;1
"Unit";"Zergling";"Larva";637;1
"Unit";"Hydralisk";"Larva";638;2
"Unit";"Zergling";"Larva";640;1
"Unit";"Zergling";"Larva";641;1
"Unit";"Zergling";"Larva";642;1
"Unit";"Zergling";"Larva";643;1
"Unit";"Zergling";"Larva";644;1
"Unit";"Zergling";"Larva";645;1
"Unit";"Zergling";"Larva";646;1
"Unit";"Zergling";"Larva";647;1
"Unit";"Zergling";"Larva";648;1
"Unit";"Zergling";"Larva";649;1
"Unit";"Zergling";"Larva";650;1
"Unit";"Zergling";"Larva";651;1
"Unit";"Zergling";"Larva";652;1
"Unit";"Zergling";"Larva";653;1
"Unit";"Zergling";"Larva";654;1
"Unit";"Zergling";"Larva";655;1
"Unit";"Zergling";"Larva";656;1
"Unit";"Zergling";"Larva";657;1
"Unit";"Zergling";"Larva";658;1
"Unit";"Zergling";"Larva";659;1
"Unit";"Zergling";"Larva";660;1
"Unit";"Zergling";"Larva";661;1
"Unit";"Zergling";"Larva";663;1
"Unit";"Zergling";"Larva";664;1
"Unit";"Zergling";"Larva";665;1
"Unit";"Zergling";"Larva";666;1
"Upgrade";"SprayZerg";NA;667;0
"Upgrade";"SprayZerg";NA;667;0
"Upgrade";"SprayZerg";NA;667;0
"Upgrade";"zerglingmovementspeed";NA;667;0
"Upgrade";"SprayZerg";NA;667;0
"Upgrade";"SprayZerg";NA;667;0
"Upgrade";"EvolveGroovedSpines";NA;667;0
"Upgrade";"SprayZerg";NA;667;0
"Upgrade";"ZergMissileWeaponsLevel1";NA;667;0
"Upgrade";"EvolveMuscularAugments";NA;667;0
"Upgrade";"ZergMissileWeaponsLevel2";NA;667;0
"Upgrade";"SprayZerg";NA;667;0
"Upgrade";"SprayZerg";NA;667;0
"Upgrade";"ZergGroundArmorsLevel1";NA;667;0
"Upgrade";"DiggingClaws";NA;667;0
"Upgrade";"ZergMeleeWeaponsLevel1";NA;667;0
