"type";"unit_name";"on_building";"total_supply";"supply"
"Unit";"Overlord";"Larva";13;0
"Building";"Extractor";NA;19;0
"Building";"SpawningPool";NA;19;0
"Building";"Hatchery";NA;17;0
"Unit";"Overlord";"Larva";23;0
"Unit";"Queen";"Hatchery";23;2
"Building";"Hatchery";NA;22;0
"Unit";"Overlord";"Larva";33;0
"Unit";"Queen";"Hatchery";29;2
"Unit";"Zergling";"Larva";35;1
"Unit";"Zergling";"Larva";35;1
"Unit";"Zergling";"Larva";35;1
"Unit";"Zergling";"Larva";35;1
"Unit";"Zergling";"Larva";37;1
"Unit";"Zergling";"Larva";37;1
"Unit";"Zergling";"Larva";37;1
"Unit";"Zergling";"Larva";37;1
"Unit";"Zergling";"Larva";39;1
"Unit";"Zergling";"Larva";39;1
"Unit";"Queen";"Hatchery";34;2
"Unit";"Overlord";"Larva";56;0
"Unit";"Overlord";"Larva";58;0
"Unit";"Overlord";"Larva";58;0
"Building";"Extractor";NA;58;0
"Building";"Extractor";NA;58;0
"Unit";"Zergling";"Larva";62;1
"Unit";"Zergling";"Larva";62;1
"Unit";"Zergling";"Larva";62;1
"Unit";"Zergling";"Larva";62;1
"Unit";"Zergling";"Larva";62;1
"Unit";"Zergling";"Larva";62;1
"Unit";"Zergling";"Larva";62;1
"Unit";"Zergling";"Larva";62;1
"Unit";"Zergling";"Larva";62;1
"Unit";"Zergling";"Larva";62;1
"Unit";"Overlord";"Larva";64;0
"Building";"RoachWarren";NA;67;0
"Building";"SporeCrawler";NA;77;0
"Building";"EvolutionChamber";NA;77;0
"Unit";"Overlord";"Larva";91;0
"Building";"SporeCrawler";NA;91;0
"Unit";"Overlord";"Larva";91;0
"Unit";"Overlord";"Larva";91;0
"Building";"SporeCrawler";NA;91;0
"Unit";"Roach";"Larva";91;2
"Unit";"Roach";"Larva";91;2
"Unit";"Roach";"Larva";91;2
"Unit";"Roach";"Larva";94;2
"Unit";"Roach";"Larva";94;2
"Unit";"Roach";"Larva";94;2
"Unit";"Roach";"Larva";94;2
"Unit";"Roach";"Larva";94;2
"Unit";"Overlord";"Larva";94;0
"Unit";"Roach";"Larva";96;2
"Unit";"Roach";"Larva";100;2
"Unit";"Roach";"Larva";110;2
"Unit";"Roach";"Larva";110;2
"Building";"Extractor";NA;110;0
"Unit";"Roach";"Larva";114;2
"Unit";"Roach";"Larva";114;2
"Unit";"Roach";"Larva";114;2
"Unit";"Roach";"Larva";114;2
"Upgrade";"GlialReconstitution";"RoachWarren";94;0
"Unit";"Overlord";"Larva";120;0
"Unit";"Roach";"Larva";128;2
"Unit";"Roach";"Larva";128;2
"Unit";"Roach";"Larva";128;2
"Unit";"Roach";"Larva";128;2
"Unit";"Roach";"Larva";128;2
"Unit";"Roach";"Larva";128;2
"Unit";"Overlord";"Larva";128;0
"Unit";"Overlord";"Larva";128;0
"Unit";"Overlord";"Larva";128;0
"Unit";"Roach";"Larva";128;2
"Unit";"Queen";"Hatchery";128;2
"Unit";"Queen";"Hatchery";128;2
"Unit";"Queen";"Hatchery";140;2
"Unit";"Roach";"Larva";153;2
"Unit";"Roach";"Larva";153;2
"Unit";"Roach";"Larva";153;2
"Unit";"Roach";"Larva";153;2
"Unit";"Roach";"Larva";153;2
"Upgrade";"ZergMissileWeaponsLevel1";"EvolutionChamber";120;0
"Building";"Hatchery";NA;128;0
"Unit";"Roach";"Larva";169;2
"Unit";"Roach";"Larva";169;2
"Unit";"Roach";"Larva";169;2
"Unit";"Roach";"Larva";169;2
"Unit";"Roach";"Larva";169;2
"Unit";"Roach";"Larva";169;2
"Unit";"Roach";"Larva";169;2
"Unit";"Roach";"Larva";169;2
"Unit";"Roach";"Larva";169;2
"Unit";"Roach";"Larva";169;2
"Unit";"Roach";"Larva";169;2
"Unit";"Roach";"Larva";169;2
"Unit";"Roach";"Larva";169;2
"Unit";"Roach";"Larva";169;2
"Unit";"Roach";"Larva";169;2
"Unit";"Roach";"Larva";169;2
"Unit";"Roach";"Larva";169;2
"Unit";"Roach";"Larva";171;2
"Unit";"Roach";"Larva";175;2
"Unit";"Roach";"Larva";181;2
"Unit";"Roach";"Larva";189;2
"Unit";"Roach";"Larva";189;2
"Unit";"Roach";"Larva";189;2
"Unit";"Overlord";"Larva";189;0
"Unit";"Overlord";"Larva";189;0
"Unit";"Overlord";"Larva";189;0
"Unit";"Overlord";"Larva";215;0
"Unit";"Overlord";"Larva";215;0
"Unit";"Overlord";"Larva";215;0
"Building";"Extractor";NA;215;0
"Building";"Extractor";NA;215;0
"Unit";"Roach";"Larva";215;2
"Unit";"Roach";"Larva";215;2
"Unit";"Roach";"Larva";215;2
"Unit";"Roach";"Larva";215;2
"Unit";"Roach";"Larva";215;2
"Unit";"Roach";"Larva";215;2
"Unit";"Roach";"Larva";215;2
"Unit";"Roach";"Larva";215;2
"Unit";"Roach";"Larva";215;2
"Unit";"Roach";"Larva";215;2
"Unit";"Roach";"Larva";215;2
"Unit";"Roach";"Larva";215;2
"Unit";"Roach";"Larva";215;2
"Unit";"Roach";"Larva";215;2
"Unit";"Roach";"Larva";215;2
"Unit";"Roach";"Larva";215;2
"Unit";"Roach";"Larva";215;2
"Unit";"Roach";"Larva";215;2
"Unit";"Roach";"Larva";215;2
"Building";"CreepTumorQueen";NA;243;0
"Building";"CreepTumorQueen";NA;256;0
"Building";"CreepTumorQueen";NA;259;0
"Building";"CreepTumorQueen";NA;259;0
"Building";"CreepTumorQueen";NA;263;0
"Building";"CreepTumorQueen";NA;263;0
"Building";"InfestationPit";NA;243;0
"Building";"Extractor";NA;261;0
"Building";"Hatchery";NA;215;0
"Unit";"Overlord";"Larva";263;0
"Building";"Extractor";NA;263;0
"Building";"Extractor";NA;263;0
"Building";"Extractor";NA;263;0
"Unit";"Roach";"Larva";263;2
"Unit";"Roach";"Larva";263;2
"Unit";"Roach";"Larva";263;2
"Unit";"Roach";"Larva";263;2
"Unit";"Roach";"Larva";263;2
"Unit";"Roach";"Larva";263;2
"Unit";"Roach";"Larva";263;2
"Building";"SporeCrawler";NA;263;0
"Upgrade";"ZergMissileWeaponsLevel2";"EvolutionChamber";215;0
"Unit";"Roach";"Larva";274;2
"Unit";"Roach";"Larva";274;2
"Unit";"Roach";"Larva";274;2
"Unit";"Roach";"Larva";274;2
"Unit";"Roach";"Larva";274;2
"Unit";"Roach";"Larva";274;2
"Unit";"Roach";"Larva";274;2
"Unit";"Roach";"Larva";274;2
"Building";"SpineCrawler";NA;264;0
"Building";"SpineCrawler";NA;266;0
"Upgrade";"Burrow";"Hatchery";263;0
"Upgrade";"TunnelingClaws";"RoachWarren";263;0
"Unit";"Overlord";"Larva";304;0
"Unit";"Overlord";"Larva";304;0
