"type";"unit_name";"on_building";"total_supply";"supply"
"Unit";"Overlord";"Larva";13;0
"Building";"Extractor";NA;17;0
"Unit";"Overlord";"Larva";21;0
"Building";"SpawningPool";NA;19;0
"Building";"Hatchery";NA;17;0
"Unit";"Zergling";"Larva";22;1
"Unit";"Zergling";"Larva";22;1
"Unit";"Zergling";"Larva";22;1
"Unit";"Zergling";"Larva";22;1
"Unit";"Queen";"Hatchery";22;2
"Unit";"Queen";"Hatchery";22;2
"Unit";"Zergling";"Larva";35;1
"Unit";"Zergling";"Larva";35;1
"Unit";"Zergling";"Larva";35;1
"Unit";"Zergling";"Larva";35;1
"Unit";"Zergling";"Larva";35;1
"Unit";"Zergling";"Larva";35;1
"Unit";"Zergling";"Larva";35;1
"Unit";"Zergling";"Larva";35;1
"Unit";"Overlord";"Larva";35;0
"Unit";"Overlord";"Larva";52;0
"Building";"Hatchery";NA;35;0
"Unit";"Queen";"Hatchery";52;2
"Building";"SporeCrawler";NA;54;0
"Building";"SporeCrawler";NA;54;0
"Building";"RoachWarren";NA;54;0
"Building";"CreepTumorQueen";NA;61;0
"Unit";"Queen";"Hatchery";54;2
"Building";"SporeCrawler";NA;61;0
"Building";"CreepTumorQueen";NA;73;0
"Building";"CreepTumor";NA;73;0
"Unit";"Overlord";"Larva";73;0
"Unit";"Overlord";"Larva";73;0
"Unit";"Overlord";"Larva";73;0
"Unit";"Overlord";"Larva";73;0
"Unit";"Overlord";"Larva";73;0
"Unit";"Roach";"Larva";73;2
"Unit";"Roach";"Larva";73;2
"Unit";"Roach";"Larva";73;2
"Unit";"Roach";"Larva";73;2
"Unit";"Roach";"Larva";73;2
"Unit";"Roach";"Larva";73;2
"Unit";"Roach";"Larva";73;2
"Unit";"Roach";"Larva";73;2
"Unit";"Roach";"Larva";73;2
"Unit";"Roach";"Larva";73;2
"Unit";"Roach";"Larva";73;2
"Building";"CreepTumor";NA;73;0
"Building";"CreepTumorQueen";NA;73;0
"Building";"CreepTumor";NA;73;0
"Unit";"Overlord";"Larva";73;0
"Unit";"Overlord";"Larva";73;0
"Unit";"Overlord";"Larva";73;0
"Building";"Extractor";NA;93;0
"Unit";"Overlord";"Larva";98;0
"Unit";"Overlord";"Larva";98;0
"Unit";"Overlord";"Larva";98;0
"Unit";"Overlord";"Larva";98;0
"Building";"CreepTumorQueen";NA;100;0
"Building";"CreepTumor";NA;98;0
"Building";"CreepTumor";NA;100;0
"Building";"CreepTumor";NA;100;0
"Unit";"Overlord";"Larva";106;0
"Unit";"Overlord";"Larva";106;0
"Unit";"Overlord";"Larva";106;0
"Unit";"Roach";"Larva";106;2
"Unit";"Roach";"Larva";106;2
"Unit";"Roach";"Larva";106;2
"Unit";"Roach";"Larva";106;2
"Unit";"Roach";"Larva";106;2
"Building";"Extractor";NA;106;0
"Building";"Extractor";NA;106;0
"Unit";"Roach";"Larva";119;2
"Unit";"Roach";"Larva";119;2
"Unit";"Roach";"Larva";119;2
"Upgrade";"GlialReconstitution";"RoachWarren";106;0
"Unit";"Zergling";"Larva";124;1
"Unit";"Zergling";"Larva";124;1
"Unit";"Zergling";"Larva";124;1
"Unit";"Zergling";"Larva";124;1
"Unit";"Zergling";"Larva";124;1
"Unit";"Zergling";"Larva";124;1
"Unit";"Zergling";"Larva";124;1
"Unit";"Zergling";"Larva";124;1
"Unit";"Zergling";"Larva";124;1
"Unit";"Zergling";"Larva";124;1
"Unit";"Zergling";"Larva";124;1
"Unit";"Zergling";"Larva";124;1
"Unit";"Zergling";"Larva";124;1
"Unit";"Zergling";"Larva";124;1
"Building";"EvolutionChamber";NA;124;0
"Building";"CreepTumor";NA;132;0
"Building";"HydraliskDen";NA;124;0
"Building";"CreepTumor";NA;132;0
"Building";"CreepTumorQueen";NA;132;0
"Building";"CreepTumorQueen";NA;148;0
"Building";"CreepTumor";NA;148;0
"Building";"CreepTumor";NA;148;0
"Building";"Extractor";NA;148;0
"Building";"Extractor";NA;148;0
"Building";"SpineCrawler";NA;130;0
"Building";"SpineCrawler";NA;130;0
"Unit";"Roach";"Larva";152;2
"Unit";"Roach";"Larva";152;2
"Unit";"Roach";"Larva";152;2
"Unit";"Roach";"Larva";152;2
"Unit";"Roach";"Larva";152;2
"Unit";"Roach";"Larva";152;2
"Unit";"Roach";"Larva";152;2
"Unit";"Roach";"Larva";152;2
"Unit";"Roach";"Larva";152;2
"Unit";"Roach";"Larva";152;2
"Unit";"Roach";"Larva";152;2
"Unit";"Roach";"Larva";152;2
"Unit";"Roach";"Larva";152;2
"Building";"Hatchery";NA;124;0
"Building";"CreepTumor";NA;170;0
"Building";"CreepTumor";NA;178;0
"Building";"CreepTumor";NA;178;0
"Building";"CreepTumor";NA;182;0
"Building";"CreepTumor";NA;182;0
"Building";"CreepTumorQueen";NA;182;0
"Unit";"Hydralisk";"Larva";182;2
"Unit";"Hydralisk";"Larva";182;2
"Unit";"Hydralisk";"Larva";182;2
"Unit";"Hydralisk";"Larva";182;2
"Unit";"Hydralisk";"Larva";182;2
"Building";"CreepTumor";NA;188;0
"Building";"CreepTumor";NA;188;0
"Unit";"Queen";"Hatchery";182;2
"Building";"CreepTumor";NA;188;0
"Building";"CreepTumor";NA;188;0
"Building";"CreepTumor";NA;188;0
"Building";"CreepTumor";NA;198;0
"Building";"CreepTumorQueen";NA;209;0
"Building";"Extractor";NA;209;0
"Building";"Extractor";NA;211;0
"Upgrade";"EvolveGroovedSpines";"HydraliskDen";182;0
"Building";"SporeCrawler";NA;211;0
"Unit";"Hydralisk";"Larva";211;2
"Unit";"Hydralisk";"Larva";211;2
"Unit";"Hydralisk";"Larva";211;2
"Unit";"Hydralisk";"Larva";211;2
"Unit";"Hydralisk";"Larva";211;2
"Unit";"Hydralisk";"Larva";211;2
"Unit";"Hydralisk";"Larva";211;2
"Unit";"Hydralisk";"Larva";211;2
"Unit";"Hydralisk";"Larva";211;2
"Building";"SpineCrawler";NA;211;0
"Building";"SpineCrawler";NA;211;0
"Unit";"Zergling";"Larva";214;1
"Unit";"Zergling";"Larva";214;1
"Unit";"Zergling";"Larva";214;1
"Unit";"Zergling";"Larva";214;1
"Unit";"Zergling";"Larva";214;1
"Unit";"Zergling";"Larva";214;1
"Unit";"Zergling";"Larva";214;1
"Unit";"Zergling";"Larva";214;1
"Unit";"Zergling";"Larva";214;1
"Unit";"Zergling";"Larva";214;1
"Unit";"Overlord";"Larva";214;0
"Unit";"Overlord";"Larva";214;0
"Unit";"Overlord";"Larva";214;0
"Building";"CreepTumor";NA;234;0
"Building";"CreepTumor";NA;234;0
"Building";"CreepTumor";NA;234;0
"Building";"SpineCrawler";NA;211;0
"Building";"CreepTumor";NA;234;0
"Building";"SpineCrawler";NA;211;0
"Building";"CreepTumor";NA;234;0
"Building";"CreepTumorQueen";NA;244;0
"Building";"CreepTumorQueen";NA;244;0
"Upgrade";"ZergMissileWeaponsLevel1";"EvolutionChamber";188;0
"Building";"LurkerDenMP";NA;182;0
"Unit";"Hydralisk";"Larva";244;2
"Unit";"Hydralisk";"Larva";244;2
"Unit";"Hydralisk";"Larva";244;2
"Unit";"Hydralisk";"Larva";244;2
"Unit";"Hydralisk";"Larva";244;2
"Unit";"Hydralisk";"Larva";244;2
"Unit";"Hydralisk";"Larva";244;2
"Unit";"Hydralisk";"Larva";244;2
"Unit";"Hydralisk";"Larva";244;2
"Unit";"Hydralisk";"Larva";244;2
"Upgrade";"EvolveMuscularAugments";"HydraliskDen";234;0
"Unit";"Zergling";"Larva";264;1
"Unit";"Zergling";"Larva";264;1
"Unit";"Zergling";"Larva";264;1
"Unit";"Zergling";"Larva";264;1
"Unit";"Overlord";"Larva";264;0
"Unit";"Overlord";"Larva";264;0
"Building";"InfestationPit";NA;246;0
"Unit";"Zergling";"Larva";268;1
"Unit";"Zergling";"Larva";268;1
"Unit";"Zergling";"Larva";268;1
"Unit";"Zergling";"Larva";268;1
"Unit";"Zergling";"Larva";268;1
"Unit";"Zergling";"Larva";268;1
"Unit";"Zergling";"Larva";268;1
"Unit";"Zergling";"Larva";268;1
"Unit";"Zergling";"Larva";268;1
"Unit";"Zergling";"Larva";268;1
"Unit";"Zergling";"Larva";268;1
"Unit";"Zergling";"Larva";268;1
"Unit";"Zergling";"Larva";268;1
"Unit";"Zergling";"Larva";268;1
"Unit";"Zergling";"Larva";268;1
"Unit";"Zergling";"Larva";268;1
"Unit";"Zergling";"Larva";268;1
"Unit";"Zergling";"Larva";268;1
"Unit";"Zergling";"Larva";268;1
"Unit";"Zergling";"Larva";268;1
"Unit";"Hydralisk";"Larva";268;2
"Unit";"Hydralisk";"Larva";268;2
"Unit";"Hydralisk";"Larva";268;2
"Unit";"Hydralisk";"Larva";268;2
"Unit";"Hydralisk";"Larva";268;2
"Unit";"Hydralisk";"Larva";268;2
"Unit";"Hydralisk";"Larva";268;2
"Unit";"Hydralisk";"Larva";268;2
"Building";"Spire";NA;244;0
"Unit";"Hydralisk";"Larva";268;2
"Unit";"Hydralisk";"Larva";268;2
"Unit";"Hydralisk";"Larva";268;2
"Upgrade";"ZergMissileWeaponsLevel2";"EvolutionChamber";268;0
"Unit";"Mutalisk";"Larva";310;2
"Unit";"Mutalisk";"Larva";310;2
"Unit";"Mutalisk";"Larva";310;2
"Unit";"Mutalisk";"Larva";310;2
"Unit";"Mutalisk";"Larva";310;2
"Unit";"Mutalisk";"Larva";310;2
"Unit";"Mutalisk";"Larva";310;2
"Unit";"Mutalisk";"Larva";310;2
"Unit";"Mutalisk";"Larva";310;2
"Unit";"Mutalisk";"Larva";310;2
"Unit";"Mutalisk";"Larva";310;2
"Unit";"Mutalisk";"Larva";310;2
"Unit";"Mutalisk";"Larva";310;2
"Unit";"Mutalisk";"Larva";310;2
"Unit";"Mutalisk";"Larva";310;2
"Unit";"Mutalisk";"Larva";310;2
"Unit";"Mutalisk";"Larva";310;2
"Unit";"Mutalisk";"Larva";336;2
"Unit";"Mutalisk";"Larva";336;2
"Unit";"Mutalisk";"Larva";336;2
"Unit";"Mutalisk";"Larva";336;2
"Unit";"Mutalisk";"Larva";352;2
"Unit";"Mutalisk";"Larva";352;2
"Unit";"Mutalisk";"Larva";352;2
"Unit";"Mutalisk";"Larva";352;2
"Unit";"Mutalisk";"Larva";352;2
"Unit";"Mutalisk";"Larva";352;2
"Unit";"Mutalisk";"Larva";352;2
"Unit";"Mutalisk";"Larva";352;2
"Unit";"Mutalisk";"Larva";352;2
"Unit";"Mutalisk";"Larva";352;2
"Building";"Spire";NA;352;0
"Unit";"Hydralisk";"Larva";352;2
"Unit";"Hydralisk";"Larva";352;2
"Unit";"Hydralisk";"Larva";352;2
"Unit";"Hydralisk";"Larva";352;2
"Building";"SporeCrawler";NA;372;0
"Building";"SporeCrawler";NA;372;0
"Building";"Hatchery";NA;352;0
"Building";"SpineCrawler";NA;352;0
"Building";"SpineCrawler";NA;352;0
"Building";"SpineCrawler";NA;352;0
"Building";"SpineCrawler";NA;352;0
"Building";"SpineCrawler";NA;366;0
"Building";"SporeCrawler";NA;380;0
"Building";"SporeCrawler";NA;380;0
"Building";"SporeCrawler";NA;380;0
"Unit";"Overlord";"Larva";380;0
"Unit";"Overlord";"Larva";380;0
"Unit";"Overlord";"Larva";380;0
"Unit";"Overlord";"Larva";380;0
"Unit";"Overlord";"Larva";380;0
"Unit";"Overlord";"Larva";380;0
"Unit";"Overlord";"Larva";380;0
"Unit";"Overlord";"Larva";380;0
