"type";"unit_name";"on_building";"total_supply";"supply"
"Unit";"Overlord";"Larva";13;0
"Building";"Extractor";NA;18;0
"Building";"SpawningPool";NA;18;0
"Building";"Hatchery";NA;16;0
"Unit";"Zergling";"Larva";23;1
"Unit";"Zergling";"Larva";23;1
"Unit";"Queen";"Hatchery";23;2
"Unit";"Overlord";"Larva";25;0
"Unit";"Zergling";"Larva";27;1
"Unit";"Zergling";"Larva";27;1
"Building";"Hatchery";NA;22;0
"Unit";"Overlord";"Larva";32;0
"Unit";"Queen";"Hatchery";31;2
"Building";"CreepTumorQueen";NA;37;0
"Unit";"Queen";"Hatchery";36;2
"Unit";"Overlord";"Larva";42;0
"Unit";"Zergling";"Larva";44;1
"Unit";"Zergling";"Larva";44;1
"Unit";"Overlord";"Larva";44;0
"Building";"CreepTumor";NA;51;0
"Unit";"Overlord";"Larva";53;0
"Building";"Extractor";NA;54;0
"Unit";"Queen";"Hatchery";51;2
"Building";"CreepTumor";NA;60;0
"Building";"CreepTumorQueen";NA;62;0
"Building";"Extractor";NA;60;0
"Building";"SporeCrawler";NA;66;0
"Unit";"Zergling";"Larva";69;1
"Unit";"Zergling";"Larva";69;1
"Unit";"Zergling";"Larva";69;1
"Unit";"Zergling";"Larva";69;1
"Unit";"Zergling";"Larva";69;1
"Unit";"Zergling";"Larva";69;1
"Unit";"Zergling";"Larva";69;1
"Unit";"Zergling";"Larva";69;1
"Building";"RoachWarren";NA;60;0
"Building";"CreepTumor";NA;75;0
"Unit";"Zergling";"Larva";75;1
"Unit";"Zergling";"Larva";75;1
"Building";"SporeCrawler";NA;72;0
"Building";"CreepTumor";NA;75;0
"Unit";"Zergling";"Larva";75;1
"Unit";"Zergling";"Larva";75;1
"Unit";"Zergling";"Larva";75;1
"Unit";"Zergling";"Larva";75;1
"Building";"CreepTumorQueen";NA;83;0
"Unit";"Overlord";"Larva";81;0
"Building";"SporeCrawler";NA;75;0
"Unit";"Roach";"Larva";83;2
"Unit";"Roach";"Larva";83;2
"Unit";"Roach";"Larva";83;2
"Unit";"Overlord";"Larva";89;0
"Unit";"Overlord";"Larva";89;0
"Unit";"Overlord";"Larva";89;0
"Unit";"Roach";"Larva";89;2
"Unit";"Roach";"Larva";89;2
"Unit";"Roach";"Larva";89;2
"Unit";"Roach";"Larva";89;2
"Unit";"Overlord";"Larva";95;0
"Unit";"Overlord";"Larva";95;0
"Building";"CreepTumor";NA;95;0
"Building";"Extractor";NA;95;0
"Unit";"Roach";"Larva";95;2
"Unit";"Roach";"Larva";95;2
"Unit";"Roach";"Larva";95;2
"Unit";"Roach";"Larva";95;2
"Unit";"Roach";"Larva";95;2
"Building";"CreepTumor";NA;103;0
"Unit";"Overlord";"Larva";103;0
"Building";"CreepTumor";NA;107;0
"Building";"CreepTumor";NA;113;0
"Building";"Extractor";NA;103;0
"Unit";"Overlord";"Larva";113;0
"Building";"CreepTumorQueen";NA;119;0
"Building";"EvolutionChamber";NA;103;0
"Building";"HydraliskDen";NA;103;0
"Upgrade";"GlialReconstitution";"RoachWarren";95;0
"Building";"CreepTumor";NA;124;0
"Building";"Extractor";NA;124;0
"Building";"CreepTumor";NA;134;0
"Building";"CreepTumor";NA;134;0
"Building";"CreepTumor";NA;134;0
"Building";"CreepTumor";NA;134;0
"Building";"CreepTumorQueen";NA;134;0
"Unit";"Roach";"Larva";134;2
"Unit";"Roach";"Larva";134;2
"Unit";"Roach";"Larva";134;2
"Unit";"Roach";"Larva";134;2
"Unit";"Roach";"Larva";134;2
"Building";"EvolutionChamber";NA;134;0
"Unit";"Overlord";"Larva";135;0
"Unit";"Hydralisk";"Larva";135;2
"Unit";"Hydralisk";"Larva";135;2
"Unit";"Hydralisk";"Larva";135;2
"Unit";"Hydralisk";"Larva";135;2
"Building";"CreepTumor";NA;146;0
"Building";"CreepTumor";NA;146;0
"Building";"CreepTumorQueen";NA;150;0
"Unit";"Hydralisk";"Larva";146;2
"Unit";"Hydralisk";"Larva";146;2
"Unit";"Hydralisk";"Larva";146;2
"Unit";"Hydralisk";"Larva";146;2
"Unit";"Hydralisk";"Larva";146;2
"Building";"BanelingNest";NA;135;0
"Unit";"Hydralisk";"Larva";146;2
"Upgrade";"EvolveMuscularAugments";"HydraliskDen";134;0
"Building";"CreepTumor";NA;160;0
"Unit";"Hydralisk";"Larva";154;2
"Unit";"Hydralisk";"Larva";154;2
"Unit";"Hydralisk";"Larva";154;2
"Unit";"Hydralisk";"Larva";154;2
"Unit";"Overlord";"Larva";160;0
"Unit";"Hydralisk";"Larva";154;2
"Building";"Hatchery";NA;134;0
"Building";"CreepTumor";NA;166;0
"Unit";"Overlord";"Larva";166;0
"Unit";"Zergling";"Larva";166;1
"Unit";"Zergling";"Larva";166;1
"Unit";"Zergling";"Larva";166;1
"Unit";"Zergling";"Larva";166;1
"Unit";"Zergling";"Larva";166;1
"Unit";"Zergling";"Larva";166;1
"Unit";"Zergling";"Larva";166;1
"Unit";"Zergling";"Larva";166;1
"Unit";"Overlord";"Larva";166;0
"Building";"CreepTumor";NA;167;0
"Building";"CreepTumor";NA;167;0
"Building";"CreepTumor";NA;173;0
"Unit";"Overlord";"Larva";177;0
"Building";"CreepTumorQueen";NA;185;0
"Unit";"Zergling";"Larva";185;1
"Unit";"Zergling";"Larva";185;1
"Unit";"Zergling";"Larva";186;1
"Unit";"Zergling";"Larva";186;1
"Building";"CreepTumorQueen";NA;197;0
"Upgrade";"ZergMeleeWeaponsLevel1";"EvolutionChamber";146;0
"Building";"CreepTumor";NA;197;0
"Building";"Extractor";NA;197;0
"Building";"Extractor";NA;197;0
"Building";"CreepTumor";NA;205;0
"Unit";"Zergling";"Larva";205;1
"Unit";"Zergling";"Larva";205;1
"Unit";"Zergling";"Larva";205;1
"Unit";"Zergling";"Larva";205;1
"Unit";"Zergling";"Larva";205;1
"Unit";"Zergling";"Larva";205;1
"Unit";"Zergling";"Larva";205;1
"Unit";"Zergling";"Larva";205;1
"Unit";"Zergling";"Larva";205;1
"Unit";"Zergling";"Larva";205;1
"Unit";"Zergling";"Larva";205;1
"Unit";"Zergling";"Larva";205;1
"Building";"CreepTumor";NA;205;0
"Building";"CreepTumor";NA;205;0
"Building";"CreepTumor";NA;205;0
"Unit";"Zergling";"Larva";205;1
"Unit";"Zergling";"Larva";205;1
"Unit";"Zergling";"Larva";205;1
"Unit";"Zergling";"Larva";205;1
"Unit";"Zergling";"Larva";205;1
"Unit";"Zergling";"Larva";205;1
"Unit";"Zergling";"Larva";205;1
"Unit";"Zergling";"Larva";205;1
"Unit";"Zergling";"Larva";205;1
"Unit";"Zergling";"Larva";205;1
"Unit";"Zergling";"Larva";205;1
"Unit";"Zergling";"Larva";205;1
"Unit";"Zergling";"Larva";205;1
"Unit";"Zergling";"Larva";205;1
"Unit";"Zergling";"Larva";217;1
"Unit";"Zergling";"Larva";217;1
"Unit";"Zergling";"Larva";217;1
"Unit";"Zergling";"Larva";217;1
"Unit";"Zergling";"Larva";217;1
"Unit";"Zergling";"Larva";217;1
"Unit";"Zergling";"Larva";217;1
"Unit";"Zergling";"Larva";217;1
"Unit";"Zergling";"Larva";217;1
"Unit";"Zergling";"Larva";217;1
"Unit";"Zergling";"Larva";217;1
"Unit";"Zergling";"Larva";217;1
"Unit";"Zergling";"Larva";217;1
"Unit";"Zergling";"Larva";217;1
"Unit";"Zergling";"Larva";217;1
"Unit";"Zergling";"Larva";217;1
"Unit";"Zergling";"Larva";217;1
"Unit";"Zergling";"Larva";217;1
"Unit";"Baneling";"Zergling";223;0
"Unit";"Baneling";"Zergling";223;0
"Unit";"Baneling";"Zergling";223;0
"Unit";"Baneling";"Zergling";223;0
"Unit";"Baneling";"Zergling";223;0
"Unit";"Baneling";"Zergling";223;0
"Unit";"Baneling";"Zergling";223;0
"Unit";"Baneling";"Zergling";223;0
"Unit";"Baneling";"Zergling";223;0
"Unit";"Baneling";"Zergling";223;0
"Unit";"Baneling";"Zergling";223;0
"Unit";"Baneling";"Zergling";223;0
"Upgrade";"ZergMissileWeaponsLevel1";"EvolutionChamber";185;0
"Upgrade";"EvolveGroovedSpines";"HydraliskDen";205;0
"Building";"SporeCrawler";NA;249;0
"Unit";"Overlord";"Larva";249;0
"Unit";"Overlord";"Larva";249;0
"Unit";"Zergling";"Larva";249;1
"Unit";"Zergling";"Larva";249;1
"Unit";"Zergling";"Larva";250;1
"Unit";"Zergling";"Larva";250;1
"Unit";"Zergling";"Larva";250;1
"Unit";"Zergling";"Larva";250;1
"Unit";"Zergling";"Larva";251;1
"Unit";"Zergling";"Larva";251;1
"Unit";"Zergling";"Larva";252;1
"Unit";"Zergling";"Larva";252;1
"Unit";"Zergling";"Larva";252;1
"Unit";"Zergling";"Larva";252;1
"Unit";"Zergling";"Larva";252;1
"Unit";"Zergling";"Larva";252;1
"Unit";"Zergling";"Larva";252;1
"Unit";"Zergling";"Larva";252;1
"Unit";"Baneling";"Zergling";252;0
"Unit";"Baneling";"Zergling";252;0
"Unit";"Baneling";"Zergling";252;0
"Unit";"Baneling";"Zergling";252;0
"Unit";"Baneling";"Zergling";252;0
"Unit";"Baneling";"Zergling";252;0
"Unit";"Baneling";"Zergling";252;0
"Unit";"Baneling";"Zergling";252;0
"Unit";"Baneling";"Zergling";252;0
"Unit";"Baneling";"Zergling";252;0
"Unit";"Baneling";"Zergling";252;0
"Unit";"Baneling";"Zergling";252;0
"Unit";"Baneling";"Zergling";252;0
"Unit";"Baneling";"Zergling";252;0
"Unit";"Baneling";"Zergling";252;0
"Unit";"Baneling";"Zergling";252;0
"Unit";"Baneling";"Zergling";252;0
"Building";"CreepTumor";NA;252;0
"Building";"CreepTumor";NA;252;0
"Building";"CreepTumor";NA;252;0
"Building";"Hatchery";NA;205;0
"Building";"SpineCrawler";NA;249;0
"Building";"InfestationPit";NA;249;0
"Unit";"Zergling";"Larva";252;1
"Unit";"Zergling";"Larva";252;1
"Unit";"Zergling";"Larva";254;1
"Unit";"Zergling";"Larva";254;1
"Unit";"Zergling";"Larva";254;1
"Unit";"Zergling";"Larva";254;1
"Unit";"Zergling";"Larva";254;1
"Unit";"Zergling";"Larva";254;1
"Unit";"Zergling";"Larva";254;1
"Unit";"Zergling";"Larva";254;1
"Unit";"Zergling";"Larva";254;1
"Unit";"Zergling";"Larva";254;1
"Unit";"Zergling";"Larva";258;1
"Unit";"Zergling";"Larva";258;1
"Unit";"Zergling";"Larva";258;1
"Unit";"Zergling";"Larva";258;1
"Unit";"Zergling";"Larva";260;1
"Unit";"Zergling";"Larva";260;1
"Unit";"Zergling";"Larva";260;1
"Unit";"Zergling";"Larva";260;1
"Unit";"Zergling";"Larva";264;1
"Unit";"Zergling";"Larva";264;1
"Unit";"Zergling";"Larva";268;1
"Unit";"Zergling";"Larva";268;1
"Unit";"Zergling";"Larva";268;1
"Unit";"Zergling";"Larva";268;1
"Unit";"Zergling";"Larva";268;1
"Unit";"Zergling";"Larva";268;1
"Unit";"Zergling";"Larva";270;1
"Unit";"Zergling";"Larva";270;1
"Unit";"Zergling";"Larva";270;1
"Unit";"Zergling";"Larva";270;1
"Unit";"Zergling";"Larva";270;1
"Unit";"Zergling";"Larva";270;1
"Unit";"Zergling";"Larva";270;1
"Unit";"Zergling";"Larva";270;1
"Unit";"Baneling";"Zergling";290;0
"Unit";"Baneling";"Zergling";290;0
"Unit";"Baneling";"Zergling";290;0
"Unit";"Baneling";"Zergling";290;0
"Unit";"Baneling";"Zergling";290;0
"Unit";"Baneling";"Zergling";290;0
"Unit";"Baneling";"Zergling";290;0
"Unit";"Baneling";"Zergling";290;0
"Unit";"Baneling";"Zergling";290;0
"Unit";"Baneling";"Zergling";290;0
"Unit";"Baneling";"Zergling";290;0
"Unit";"Baneling";"Zergling";290;0
"Unit";"Baneling";"Zergling";290;0
"Unit";"Baneling";"Zergling";290;0
"Unit";"Baneling";"Zergling";290;0
"Unit";"Baneling";"Zergling";290;0
"Unit";"Baneling";"Zergling";290;0
"Unit";"Baneling";"Zergling";290;0
"Building";"CreepTumor";NA;290;0
"Unit";"Zergling";"Larva";290;1
"Unit";"Zergling";"Larva";290;1
"Unit";"Zergling";"Larva";290;1
"Unit";"Zergling";"Larva";290;1
"Unit";"Zergling";"Larva";290;1
"Unit";"Zergling";"Larva";290;1
"Unit";"Zergling";"Larva";290;1
"Unit";"Zergling";"Larva";290;1
"Unit";"Zergling";"Larva";290;1
"Unit";"Zergling";"Larva";290;1
"Unit";"Zergling";"Larva";305;1
"Unit";"Zergling";"Larva";305;1
"Unit";"Zergling";"Larva";305;1
"Unit";"Zergling";"Larva";305;1
"Unit";"Zergling";"Larva";305;1
"Unit";"Zergling";"Larva";305;1
"Unit";"Zergling";"Larva";305;1
"Unit";"Zergling";"Larva";305;1
"Unit";"Zergling";"Larva";305;1
"Unit";"Zergling";"Larva";305;1
"Unit";"Zergling";"Larva";305;1
"Unit";"Zergling";"Larva";305;1
"Unit";"Zergling";"Larva";305;1
"Unit";"Zergling";"Larva";305;1
"Unit";"Zergling";"Larva";305;1
"Unit";"Zergling";"Larva";305;1
"Upgrade";"ZergMeleeWeaponsLevel2";"EvolutionChamber";231;0
"Unit";"Hydralisk";"Larva";315;2
"Unit";"Hydralisk";"Larva";315;2
"Unit";"Hydralisk";"Larva";315;2
"Unit";"Hydralisk";"Larva";315;2
"Unit";"Hydralisk";"Larva";315;2
"Unit";"Hydralisk";"Larva";315;2
"Unit";"Zergling";"Larva";331;1
"Unit";"Zergling";"Larva";331;1
"Unit";"Zergling";"Larva";331;1
"Unit";"Zergling";"Larva";331;1
"Unit";"Zergling";"Larva";331;1
"Unit";"Zergling";"Larva";331;1
"Unit";"Zergling";"Larva";331;1
"Unit";"Zergling";"Larva";331;1
"Unit";"Zergling";"Larva";331;1
"Unit";"Zergling";"Larva";331;1
"Unit";"Zergling";"Larva";331;1
"Unit";"Zergling";"Larva";331;1
"Unit";"Zergling";"Larva";331;1
"Unit";"Zergling";"Larva";331;1
"Unit";"Zergling";"Larva";331;1
"Unit";"Zergling";"Larva";331;1
"Unit";"Zergling";"Larva";331;1
"Unit";"Zergling";"Larva";331;1
"Unit";"Zergling";"Larva";331;1
"Unit";"Zergling";"Larva";331;1
"Unit";"Zergling";"Larva";331;1
"Unit";"Zergling";"Larva";331;1
"Unit";"Zergling";"Larva";331;1
"Unit";"Zergling";"Larva";331;1
"Unit";"Zergling";"Larva";331;1
"Unit";"Zergling";"Larva";331;1
"Unit";"Zergling";"Larva";331;1
"Unit";"Zergling";"Larva";331;1
"Unit";"Zergling";"Larva";331;1
"Unit";"Zergling";"Larva";331;1
"Building";"Spire";NA;290;0
"Building";"SporeCrawler";NA;343;0
"Building";"SpineCrawler";NA;343;0
"Unit";"Queen";"Hatchery";343;2
"Building";"SpineCrawler";NA;343;0
"Unit";"Corruptor";"Larva";373;2
"Unit";"Corruptor";"Larva";373;2
"Unit";"Corruptor";"Larva";373;2
"Unit";"Corruptor";"Larva";373;2
"Unit";"Corruptor";"Larva";373;2
"Unit";"Corruptor";"Larva";373;2
"Upgrade";"ZergMissileWeaponsLevel2";"EvolutionChamber";305;0
"Unit";"Overlord";"Larva";383;0
"Building";"CreepTumor";NA;387;0
"Unit";"Corruptor";"Larva";383;2
"Unit";"Corruptor";"Larva";383;2
"Unit";"Corruptor";"Larva";383;2
"Unit";"Corruptor";"Larva";383;2
"Unit";"Corruptor";"Larva";383;2
"Building";"Extractor";NA;387;0
"Unit";"Corruptor";"Larva";393;2
"Unit";"Corruptor";"Larva";393;2
"Unit";"Corruptor";"Larva";393;2
"Unit";"Corruptor";"Larva";393;2
"Unit";"Corruptor";"Larva";393;2
"Unit";"Overlord";"Larva";402;0
"Building";"SpineCrawler";NA;402;0
"Building";"SpineCrawler";NA;402;0
"Building";"Spire";NA;387;0
"Unit";"Corruptor";"Larva";402;2
"Unit";"Corruptor";"Larva";402;2
"Unit";"Corruptor";"Larva";402;2
"Unit";"Corruptor";"Larva";402;2
"Unit";"Hydralisk";"Larva";412;2
"Unit";"Hydralisk";"Larva";412;2
"Unit";"Hydralisk";"Larva";412;2
"Unit";"Hydralisk";"Larva";412;2
"Unit";"Hydralisk";"Larva";412;2
"Unit";"Hydralisk";"Larva";412;2
"Unit";"Hydralisk";"Larva";412;2
"Unit";"Hydralisk";"Larva";412;2
"Unit";"Hydralisk";"Larva";412;2
"Unit";"Hydralisk";"Larva";412;2
"Unit";"Hydralisk";"Larva";412;2
"Unit";"Hydralisk";"Larva";412;2
"Unit";"Hydralisk";"Larva";412;2
"Unit";"Hydralisk";"Larva";412;2
"Unit";"Hydralisk";"Larva";412;2
"Unit";"Hydralisk";"Larva";412;2
"Unit";"Zergling";"Larva";420;1
"Unit";"Zergling";"Larva";420;1
"Unit";"Zergling";"Larva";420;1
"Unit";"Zergling";"Larva";420;1
"Unit";"Zergling";"Larva";420;1
"Unit";"Zergling";"Larva";420;1
"Unit";"Zergling";"Larva";420;1
"Unit";"Zergling";"Larva";420;1
"Unit";"Zergling";"Larva";420;1
"Unit";"Zergling";"Larva";420;1
"Unit";"Zergling";"Larva";420;1
"Unit";"Zergling";"Larva";420;1
"Unit";"Zergling";"Larva";420;1
"Unit";"Zergling";"Larva";420;1
"Unit";"Zergling";"Larva";420;1
"Unit";"Zergling";"Larva";420;1
"Unit";"Zergling";"Larva";420;1
"Unit";"Zergling";"Larva";420;1
"Unit";"Zergling";"Larva";420;1
"Unit";"Zergling";"Larva";420;1
"Unit";"Zergling";"Larva";420;1
"Unit";"Zergling";"Larva";420;1
"Unit";"Zergling";"Larva";420;1
"Unit";"Zergling";"Larva";420;1
"Unit";"Zergling";"Larva";420;1
"Unit";"Zergling";"Larva";420;1
"Unit";"Zergling";"Larva";420;1
"Unit";"Zergling";"Larva";420;1
"Unit";"Zergling";"Larva";420;1
"Unit";"Zergling";"Larva";420;1
"Building";"CreepTumor";NA;482;0
"Unit";"Zergling";"Larva";485;1
"Unit";"Zergling";"Larva";485;1
"Unit";"Zergling";"Larva";485;1
"Unit";"Zergling";"Larva";485;1
"Unit";"Zergling";"Larva";485;1
"Unit";"Zergling";"Larva";485;1
"Unit";"Zergling";"Larva";485;1
"Unit";"Zergling";"Larva";485;1
"Unit";"Zergling";"Larva";485;1
"Unit";"Zergling";"Larva";485;1
"Unit";"Zergling";"Larva";485;1
"Unit";"Zergling";"Larva";485;1
"Unit";"Zergling";"Larva";485;1
"Unit";"Zergling";"Larva";485;1
"Unit";"Corruptor";"Larva";485;2
"Unit";"Corruptor";"Larva";485;2
"Unit";"Baneling";"Zergling";499;0
"Unit";"Baneling";"Zergling";499;0
"Unit";"Baneling";"Zergling";499;0
"Unit";"Baneling";"Zergling";499;0
"Unit";"Baneling";"Zergling";499;0
"Unit";"Corruptor";"Larva";499;2
"Unit";"Corruptor";"Larva";499;2
"Unit";"Corruptor";"Larva";499;2
"Unit";"Corruptor";"Larva";499;2
"Unit";"Corruptor";"Larva";503;2
"Unit";"Corruptor";"Larva";503;2
"Unit";"Corruptor";"Larva";503;2
"Unit";"Corruptor";"Larva";503;2
"Unit";"Corruptor";"Larva";503;2
"Unit";"Overlord";"Larva";511;0
"Building";"Extractor";NA;521;0
"Upgrade";"ZergGroundArmorsLevel1";"EvolutionChamber";499;0
"Unit";"Corruptor";"Larva";521;2
"Unit";"Corruptor";"Larva";521;2
"Unit";"Zergling";"Larva";521;1
"Unit";"Zergling";"Larva";521;1
"Unit";"Zergling";"Larva";521;1
"Unit";"Zergling";"Larva";521;1
"Unit";"Zergling";"Larva";521;1
"Unit";"Zergling";"Larva";521;1
"Unit";"Zergling";"Larva";521;1
"Unit";"Zergling";"Larva";521;1
"Unit";"Zergling";"Larva";521;1
"Unit";"Zergling";"Larva";521;1
"Unit";"Zergling";"Larva";521;1
"Unit";"Zergling";"Larva";521;1
"Unit";"Zergling";"Larva";521;1
"Unit";"Zergling";"Larva";521;1
"Unit";"Zergling";"Larva";521;1
"Unit";"Zergling";"Larva";521;1
"Unit";"Zergling";"Larva";521;1
"Unit";"Zergling";"Larva";521;1
"Unit";"Zergling";"Larva";521;1
"Unit";"Zergling";"Larva";521;1
"Unit";"Zergling";"Larva";521;1
"Unit";"Zergling";"Larva";521;1
"Unit";"Zergling";"Larva";521;1
"Unit";"Zergling";"Larva";521;1
"Unit";"Zergling";"Larva";521;1
"Unit";"Zergling";"Larva";521;1
"Unit";"Zergling";"Larva";521;1
"Unit";"Zergling";"Larva";521;1
"Unit";"Zergling";"Larva";521;1
"Unit";"Zergling";"Larva";521;1
"Unit";"Zergling";"Larva";521;1
"Unit";"Zergling";"Larva";521;1
"Unit";"Zergling";"Larva";521;1
"Unit";"Zergling";"Larva";521;1
"Unit";"Zergling";"Larva";521;1
"Unit";"Zergling";"Larva";521;1
"Unit";"Zergling";"Larva";521;1
"Unit";"Zergling";"Larva";521;1
"Unit";"Zergling";"Larva";521;1
"Unit";"Zergling";"Larva";521;1
"Unit";"Zergling";"Larva";521;1
"Unit";"Zergling";"Larva";521;1
"Unit";"Zergling";"Larva";521;1
"Unit";"Zergling";"Larva";521;1
"Unit";"Zergling";"Larva";521;1
"Unit";"Zergling";"Larva";521;1
"Unit";"Zergling";"Larva";521;1
"Unit";"Zergling";"Larva";521;1
"Unit";"Zergling";"Larva";521;1
"Unit";"Zergling";"Larva";521;1
"Unit";"Zergling";"Larva";521;1
"Unit";"Zergling";"Larva";521;1
"Unit";"Zergling";"Larva";521;1
"Unit";"Zergling";"Larva";521;1
"Unit";"Zergling";"Larva";521;1
"Unit";"Zergling";"Larva";521;1
"Unit";"Zergling";"Larva";521;1
"Unit";"Zergling";"Larva";521;1
"Unit";"Hydralisk";"Larva";521;2
"Unit";"Hydralisk";"Larva";521;2
"Unit";"Hydralisk";"Larva";521;2
"Unit";"Zergling";"Larva";583;1
"Unit";"Zergling";"Larva";583;1
"Unit";"Zergling";"Larva";583;1
"Unit";"Zergling";"Larva";583;1
"Unit";"Zergling";"Larva";583;1
"Unit";"Zergling";"Larva";583;1
"Unit";"Zergling";"Larva";583;1
"Unit";"Zergling";"Larva";583;1
"Unit";"Corruptor";"Larva";521;2
"Unit";"Corruptor";"Larva";521;2
"Unit";"Corruptor";"Larva";521;2
"Unit";"Corruptor";"Larva";521;2
"Unit";"Corruptor";"Larva";521;2
"Unit";"Hydralisk";"Larva";561;2
"Unit";"Hydralisk";"Larva";567;2
"Upgrade";"ZergMeleeWeaponsLevel3";"EvolutionChamber";499;0
"Unit";"Zergling";"Larva";611;1
"Unit";"Zergling";"Larva";611;1
"Unit";"Zergling";"Larva";611;1
"Unit";"Zergling";"Larva";611;1
"Unit";"Zergling";"Larva";611;1
"Unit";"Zergling";"Larva";611;1
"Unit";"Zergling";"Larva";611;1
"Unit";"Zergling";"Larva";611;1
"Unit";"Zergling";"Larva";611;1
"Unit";"Zergling";"Larva";611;1
"Unit";"Zergling";"Larva";611;1
"Unit";"Zergling";"Larva";611;1
"Unit";"Zergling";"Larva";611;1
"Unit";"Zergling";"Larva";611;1
"Unit";"Zergling";"Larva";611;1
"Unit";"Zergling";"Larva";611;1
"Unit";"Zergling";"Larva";611;1
"Unit";"Zergling";"Larva";611;1
"Unit";"Zergling";"Larva";611;1
"Unit";"Zergling";"Larva";611;1
"Unit";"Zergling";"Larva";611;1
"Unit";"Zergling";"Larva";611;1
"Unit";"Corruptor";"Larva";597;2
"Unit";"Corruptor";"Larva";597;2
"Unit";"Corruptor";"Larva";597;2
"Unit";"Corruptor";"Larva";597;2
"Unit";"Corruptor";"Larva";597;2
"Building";"CreepTumor";NA;643;0
"Unit";"Corruptor";"Larva";643;2
"Unit";"Corruptor";"Larva";643;2
"Unit";"Infestor";"Larva";643;2
"Unit";"Infestor";"Larva";643;2
"Unit";"Infestor";"Larva";643;2
"Unit";"Infestor";"Larva";643;2
"Unit";"Infestor";"Larva";643;2
"Unit";"Infestor";"Larva";643;2
"Unit";"Infestor";"Larva";643;2
"Unit";"Corruptor";"Larva";643;2
"Unit";"Corruptor";"Larva";643;2
"Building";"CreepTumor";NA;665;0
"Unit";"Corruptor";"Larva";661;2
"Unit";"Corruptor";"Larva";661;2
"Unit";"Corruptor";"Larva";661;2
"Unit";"Corruptor";"Larva";661;2
"Unit";"Corruptor";"Larva";665;2
"Unit";"Corruptor";"Larva";665;2
"Unit";"Corruptor";"Larva";665;2
"Unit";"Corruptor";"Larva";665;2
"Unit";"Zergling";"Larva";673;1
"Unit";"Zergling";"Larva";673;1
"Unit";"Zergling";"Larva";673;1
"Unit";"Zergling";"Larva";673;1
"Unit";"Zergling";"Larva";673;1
"Unit";"Zergling";"Larva";673;1
"Unit";"Zergling";"Larva";673;1
"Unit";"Zergling";"Larva";673;1
"Unit";"Zergling";"Larva";673;1
"Unit";"Zergling";"Larva";673;1
"Unit";"Zergling";"Larva";673;1
"Unit";"Zergling";"Larva";673;1
"Unit";"Zergling";"Larva";673;1
"Unit";"Zergling";"Larva";673;1
"Unit";"Zergling";"Larva";673;1
"Unit";"Zergling";"Larva";673;1
"Unit";"Zergling";"Larva";673;1
"Unit";"Zergling";"Larva";673;1
"Building";"Hatchery";NA;643;0
"Building";"CreepTumor";NA;704;0
"Unit";"Overlord";"Larva";704;0
"Unit";"Overlord";"Larva";704;0
"Unit";"Overlord";"Larva";704;0
"Unit";"Overlord";"Larva";704;0
"Unit";"Overlord";"Larva";704;0
"Unit";"Overlord";"Larva";704;0
"Upgrade";"NeuralParasite";"InfestationPit";665;0
"Unit";"Zergling";"Larva";704;1
"Unit";"Zergling";"Larva";704;1
"Unit";"Zergling";"Larva";704;1
"Unit";"Zergling";"Larva";704;1
"Unit";"Zergling";"Larva";704;1
"Unit";"Zergling";"Larva";704;1
"Unit";"Zergling";"Larva";704;1
"Unit";"Zergling";"Larva";704;1
"Unit";"Zergling";"Larva";704;1
"Unit";"Zergling";"Larva";704;1
"Unit";"Zergling";"Larva";704;1
"Unit";"Zergling";"Larva";704;1
"Unit";"Zergling";"Larva";704;1
"Unit";"Zergling";"Larva";704;1
"Unit";"Zergling";"Larva";704;1
"Unit";"Zergling";"Larva";704;1
"Unit";"Corruptor";"Larva";704;2
"Unit";"Zergling";"Larva";704;1
"Unit";"Zergling";"Larva";704;1
"Unit";"Corruptor";"Larva";704;2
"Unit";"Corruptor";"Larva";704;2
"Unit";"Corruptor";"Larva";704;2
"Unit";"Corruptor";"Larva";704;2
"Building";"Extractor";NA;704;0
"Building";"Extractor";NA;704;0
"Unit";"Corruptor";"Larva";704;2
"Unit";"Corruptor";"Larva";704;2
"Unit";"Corruptor";"Larva";704;2
"Unit";"Corruptor";"Larva";704;2
"Upgrade";"ZergGroundArmorsLevel2";"EvolutionChamber";704;0
"Unit";"Infestor";"Larva";740;2
"Unit";"Infestor";"Larva";740;2
"Unit";"Infestor";"Larva";740;2
"Unit";"Infestor";"Larva";740;2
"Building";"SporeCrawler";NA;740;0
"Building";"SpineCrawler";NA;740;0
"Building";"SpineCrawler";NA;740;0
"Building";"SpineCrawler";NA;740;0
"Unit";"Zergling";"Larva";740;1
"Unit";"Zergling";"Larva";740;1
"Unit";"Zergling";"Larva";740;1
"Unit";"Zergling";"Larva";740;1
"Unit";"Zergling";"Larva";740;1
"Unit";"Zergling";"Larva";740;1
"Unit";"Zergling";"Larva";740;1
"Unit";"Zergling";"Larva";740;1
"Unit";"Zergling";"Larva";740;1
"Unit";"Zergling";"Larva";740;1
"Unit";"Zergling";"Larva";740;1
"Unit";"Zergling";"Larva";740;1
"Unit";"Zergling";"Larva";740;1
"Unit";"Zergling";"Larva";740;1
"Unit";"Zergling";"Larva";740;1
"Unit";"Zergling";"Larva";740;1
"Unit";"Zergling";"Larva";740;1
"Unit";"Zergling";"Larva";740;1
"Unit";"Zergling";"Larva";740;1
"Unit";"Zergling";"Larva";740;1
"Unit";"Zergling";"Larva";740;1
"Unit";"Zergling";"Larva";740;1
"Unit";"Zergling";"Larva";740;1
"Unit";"Zergling";"Larva";740;1
"Unit";"Zergling";"Larva";740;1
"Unit";"Zergling";"Larva";740;1
"Unit";"Zergling";"Larva";740;1
"Unit";"Zergling";"Larva";740;1
"Building";"CreepTumorQueen";NA;748;0
"Building";"CreepTumor";NA;748;0
"Building";"CreepTumor";NA;748;0
"Building";"CreepTumorQueen";NA;748;0
"Building";"SpineCrawler";NA;740;0
"Building";"SpineCrawler";NA;740;0
"Building";"SpineCrawler";NA;740;0
"Building";"SpineCrawler";NA;740;0
"Building";"SpineCrawler";NA;740;0
"Unit";"Corruptor";"Larva";740;2
"Unit";"Infestor";"Larva";776;2
"Unit";"Infestor";"Larva";776;2
"Unit";"Infestor";"Larva";776;2
"Unit";"Infestor";"Larva";776;2
"Unit";"Infestor";"Larva";776;2
"Unit";"Infestor";"Larva";776;2
"Building";"Hatchery";NA;776;0
"Unit";"Zergling";"Larva";790;1
"Unit";"Zergling";"Larva";790;1
"Unit";"Zergling";"Larva";790;1
"Unit";"Zergling";"Larva";790;1
"Unit";"Zergling";"Larva";790;1
"Unit";"Zergling";"Larva";790;1
"Unit";"Zergling";"Larva";790;1
"Unit";"Zergling";"Larva";790;1
"Unit";"Zergling";"Larva";790;1
"Unit";"Zergling";"Larva";790;1
"Unit";"Zergling";"Larva";790;1
"Unit";"Zergling";"Larva";790;1
"Unit";"Zergling";"Larva";790;1
"Unit";"Zergling";"Larva";790;1
"Building";"CreepTumor";NA;790;0
"Unit";"Zergling";"Larva";790;1
"Unit";"Zergling";"Larva";790;1
"Unit";"Zergling";"Larva";790;1
"Unit";"Zergling";"Larva";790;1
"Unit";"Zergling";"Larva";790;1
"Unit";"Zergling";"Larva";790;1
"Unit";"Zergling";"Larva";790;1
"Unit";"Zergling";"Larva";790;1
"Unit";"Zergling";"Larva";790;1
"Unit";"Zergling";"Larva";790;1
"Unit";"Zergling";"Larva";790;1
"Unit";"Zergling";"Larva";790;1
"Unit";"Zergling";"Larva";790;1
"Unit";"Zergling";"Larva";790;1
"Unit";"Zergling";"Larva";790;1
"Unit";"Zergling";"Larva";790;1
"Unit";"Zergling";"Larva";804;1
"Unit";"Zergling";"Larva";804;1
"Unit";"Zergling";"Larva";804;1
"Unit";"Zergling";"Larva";804;1
"Unit";"Zergling";"Larva";806;1
"Unit";"Zergling";"Larva";806;1
"Unit";"Zergling";"Larva";806;1
"Unit";"Zergling";"Larva";806;1
"Building";"CreepTumor";NA;820;0
"Building";"CreepTumor";NA;828;0
"Building";"Hatchery";NA;790;0
"Building";"Extractor";NA;828;0
"Building";"Extractor";NA;828;0
"Unit";"Zergling";"Larva";828;1
"Unit";"Zergling";"Larva";828;1
"Unit";"Zergling";"Larva";828;1
"Unit";"Zergling";"Larva";828;1
"Unit";"Zergling";"Larva";828;1
"Unit";"Zergling";"Larva";828;1
"Unit";"Zergling";"Larva";828;1
"Unit";"Zergling";"Larva";828;1
"Unit";"Zergling";"Larva";828;1
"Unit";"Zergling";"Larva";828;1
"Unit";"Zergling";"Larva";828;1
"Unit";"Zergling";"Larva";828;1
"Unit";"Zergling";"Larva";828;1
"Unit";"Zergling";"Larva";828;1
"Unit";"Zergling";"Larva";828;1
"Unit";"Zergling";"Larva";828;1
"Unit";"Zergling";"Larva";828;1
"Unit";"Zergling";"Larva";828;1
"Unit";"Zergling";"Larva";828;1
"Unit";"Zergling";"Larva";828;1
"Unit";"Zergling";"Larva";828;1
"Unit";"Zergling";"Larva";828;1
"Unit";"Zergling";"Larva";828;1
"Unit";"Zergling";"Larva";828;1
"Unit";"Zergling";"Larva";828;1
"Unit";"Zergling";"Larva";828;1
"Unit";"Zergling";"Larva";828;1
"Unit";"Zergling";"Larva";828;1
"Unit";"Zergling";"Larva";828;1
"Unit";"Zergling";"Larva";828;1
"Unit";"Zergling";"Larva";828;1
"Unit";"Zergling";"Larva";828;1
"Unit";"Zergling";"Larva";828;1
"Unit";"Zergling";"Larva";828;1
"Unit";"Zergling";"Larva";828;1
"Unit";"Zergling";"Larva";828;1
"Unit";"Zergling";"Larva";828;1
"Unit";"Zergling";"Larva";828;1
"Unit";"Zergling";"Larva";828;1
"Unit";"Zergling";"Larva";828;1
"Unit";"Zergling";"Larva";828;1
"Unit";"Zergling";"Larva";828;1
"Building";"Extractor";NA;870;0
"Building";"Extractor";NA;870;0
"Unit";"Zergling";"Larva";870;1
"Unit";"Zergling";"Larva";870;1
"Unit";"Zergling";"Larva";870;1
"Unit";"Zergling";"Larva";870;1
"Unit";"Zergling";"Larva";870;1
"Unit";"Zergling";"Larva";870;1
"Unit";"Zergling";"Larva";870;1
"Unit";"Zergling";"Larva";870;1
"Unit";"Zergling";"Larva";870;1
"Unit";"Zergling";"Larva";870;1
"Unit";"Zergling";"Larva";870;1
"Unit";"Zergling";"Larva";870;1
"Unit";"Zergling";"Larva";870;1
"Unit";"Zergling";"Larva";870;1
"Unit";"Zergling";"Larva";870;1
"Unit";"Zergling";"Larva";870;1
"Unit";"Zergling";"Larva";870;1
"Unit";"Zergling";"Larva";870;1
"Unit";"Zergling";"Larva";870;1
"Unit";"Zergling";"Larva";870;1
"Unit";"Zergling";"Larva";870;1
"Unit";"Zergling";"Larva";870;1
"Unit";"Zergling";"Larva";870;1
"Unit";"Zergling";"Larva";870;1
"Unit";"Zergling";"Larva";870;1
"Unit";"Zergling";"Larva";870;1
"Unit";"Zergling";"Larva";870;1
"Unit";"Zergling";"Larva";870;1
"Unit";"Zergling";"Larva";870;1
"Unit";"Zergling";"Larva";870;1
"Unit";"Zergling";"Larva";870;1
"Unit";"Zergling";"Larva";870;1
"Unit";"Zergling";"Larva";870;1
"Unit";"Zergling";"Larva";870;1
"Unit";"Zergling";"Larva";870;1
"Unit";"Zergling";"Larva";870;1
"Unit";"Zergling";"Larva";870;1
"Unit";"Zergling";"Larva";870;1
"Unit";"Zergling";"Larva";870;1
"Unit";"Zergling";"Larva";870;1
"Unit";"Zergling";"Larva";870;1
"Unit";"Zergling";"Larva";870;1
"Unit";"Zergling";"Larva";870;1
"Unit";"Zergling";"Larva";870;1
"Unit";"Zergling";"Larva";914;1
"Unit";"Zergling";"Larva";914;1
"Unit";"Zergling";"Larva";914;1
"Unit";"Zergling";"Larva";914;1
"Unit";"Zergling";"Larva";914;1
"Unit";"Zergling";"Larva";914;1
"Unit";"Zergling";"Larva";914;1
"Unit";"Zergling";"Larva";914;1
"Unit";"Zergling";"Larva";914;1
"Unit";"Zergling";"Larva";914;1
"Unit";"Zergling";"Larva";914;1
"Unit";"Zergling";"Larva";914;1
"Unit";"Zergling";"Larva";914;1
"Unit";"Zergling";"Larva";914;1
"Unit";"Zergling";"Larva";914;1
"Unit";"Zergling";"Larva";914;1
"Unit";"Zergling";"Larva";914;1
"Unit";"Zergling";"Larva";914;1
"Unit";"Zergling";"Larva";914;1
"Unit";"Zergling";"Larva";914;1
"Unit";"Zergling";"Larva";914;1
"Unit";"Zergling";"Larva";914;1
"Unit";"Zergling";"Larva";914;1
"Unit";"Zergling";"Larva";914;1
"Building";"CreepTumor";NA;914;0
"Unit";"Overlord";"Larva";938;0
"Unit";"Overlord";"Larva";938;0
"Unit";"Overlord";"Larva";938;0
"Unit";"Overlord";"Larva";938;0
