"type";"unit_name";"on_building";"total_supply";"supply"
"Unit";"Overlord";"Larva";12;0
"Building";"SpawningPool";NA;18;0
"Building";"Hatchery";NA;16;0
"Unit";"Zergling";"Larva";21;1
"Unit";"Zergling";"Larva";21;1
"Unit";"Overlord";"Larva";21;0
"Unit";"Queen";"Hatchery";21;2
"Unit";"Queen";"Hatchery";21;2
"Building";"Hatchery";NA;19;0
"Unit";"Zergling";"Larva";27;1
"Unit";"Zergling";"Larva";27;1
"Unit";"Queen";"Hatchery";25;2
"Unit";"Queen";"Hatchery";27;2
"Building";"Extractor";NA;31;0
"Building";"CreepTumorQueen";NA;36;0
"Building";"Extractor";NA;35;0
"Unit";"Overlord";"Larva";36;0
"Unit";"Queen";"Hatchery";35;2
"Building";"CreepTumorQueen";NA;44;0
"Building";"CreepTumorQueen";NA;57;0
"Building";"CreepTumor";NA;57;0
"Building";"CreepTumorQueen";NA;57;0
"Building";"SporeCrawler";NA;57;0
"Building";"CreepTumor";NA;57;0
"Building";"SporeCrawler";NA;57;0
"Building";"CreepTumorQueen";NA;57;0
"Building";"SporeCrawler";NA;57;0
"Building";"CreepTumor";NA;58;0
"Building";"CreepTumor";NA;58;0
"Unit";"Overlord";"Larva";58;0
"Building";"CreepTumor";NA;62;0
"Building";"CreepTumor";NA;63;0
"Building";"RoachWarren";NA;57;0
"Building";"CreepTumorQueen";NA;63;0
"Building";"CreepTumorQueen";NA;63;0
"Unit";"Overlord";"Larva";63;0
"Unit";"Overlord";"Larva";63;0
"Unit";"Overlord";"Larva";63;0
"Unit";"Overlord";"Larva";63;0
"Unit";"Overlord";"Larva";63;0
"Unit";"Roach";"Larva";63;2
"Building";"CreepTumor";NA;67;0
"Building";"CreepTumor";NA;67;0
"Building";"CreepTumor";NA;67;0
"Building";"CreepTumor";NA;67;0
"Building";"CreepTumor";NA;67;0
"Unit";"Roach";"Larva";67;2
"Unit";"Roach";"Larva";67;2
"Building";"CreepTumor";NA;69;0
"Unit";"Overlord";"Larva";69;0
"Unit";"Roach";"Larva";71;2
"Unit";"Roach";"Larva";71;2
"Unit";"Roach";"Larva";71;2
"Unit";"Roach";"Larva";71;2
"Unit";"Roach";"Larva";73;2
"Unit";"Roach";"Larva";75;2
"Unit";"Roach";"Larva";75;2
"Unit";"Roach";"Larva";75;2
"Unit";"Roach";"Larva";75;2
"Unit";"Roach";"Larva";75;2
"Unit";"Roach";"Larva";75;2
"Unit";"Roach";"Larva";75;2
"Unit";"Roach";"Larva";83;2
"Unit";"Roach";"Larva";83;2
"Unit";"Roach";"Larva";85;2
"Unit";"Roach";"Larva";87;2
"Unit";"Overlord";"Larva";91;0
"Upgrade";"GlialReconstitution";"RoachWarren";69;0
"Unit";"Overlord";"Larva";91;0
"Unit";"Overlord";"Larva";91;0
"Building";"Extractor";NA;99;0
"Building";"Extractor";NA;99;0
"Building";"HydraliskDen";NA;99;0
"Unit";"Hydralisk";"Larva";124;2
"Unit";"Hydralisk";"Larva";124;2
"Unit";"Hydralisk";"Larva";124;2
"Unit";"Hydralisk";"Larva";124;2
"Unit";"Hydralisk";"Larva";124;2
"Unit";"Overlord";"Larva";124;0
"Building";"Extractor";NA;124;0
"Building";"Extractor";NA;124;0
"Building";"CreepTumorQueen";NA;134;0
"Building";"CreepTumorQueen";NA;134;0
"Unit";"Overlord";"Larva";124;0
"Unit";"Overlord";"Larva";126;0
"Unit";"Overlord";"Larva";126;0
"Building";"CreepTumor";NA;134;0
"Upgrade";"EvolveGroovedSpines";"HydraliskDen";124;0
"Unit";"Hydralisk";"Larva";134;2
"Unit";"Hydralisk";"Larva";134;2
"Unit";"Hydralisk";"Larva";134;2
"Unit";"Roach";"Larva";142;2
"Unit";"Roach";"Larva";142;2
"Unit";"Roach";"Larva";142;2
"Unit";"Roach";"Larva";142;2
"Unit";"Hydralisk";"Larva";142;2
"Unit";"Hydralisk";"Larva";142;2
"Unit";"Hydralisk";"Larva";142;2
"Unit";"Hydralisk";"Larva";142;2
"Building";"Hatchery";NA;134;0
"Unit";"Overlord";"Larva";156;0
"Unit";"Overlord";"Larva";156;0
"Unit";"Overlord";"Larva";156;0
"Unit";"Overlord";"Larva";156;0
"Unit";"Queen";"Hatchery";148;2
"Building";"CreepTumorQueen";NA;164;0
"Building";"CreepTumor";NA;164;0
"Building";"CreepTumor";NA;164;0
"Building";"CreepTumor";NA;164;0
"Building";"CreepTumorQueen";NA;164;0
"Building";"CreepTumor";NA;164;0
"Unit";"Overlord";"Larva";164;0
"Unit";"Overlord";"Larva";164;0
"Unit";"Overlord";"Larva";164;0
"Unit";"Overlord";"Larva";164;0
"Unit";"Overlord";"Larva";164;0
"Building";"LurkerDenMP";NA;134;0
"Unit";"Hydralisk";"Larva";164;2
"Unit";"Hydralisk";"Larva";164;2
"Upgrade";"EvolveMuscularAugments";"HydraliskDen";148;0
"Unit";"Hydralisk";"Larva";164;2
"Unit";"Hydralisk";"Larva";164;2
"Unit";"Hydralisk";"Larva";164;2
"Unit";"Hydralisk";"Larva";164;2
"Unit";"Hydralisk";"Larva";166;2
"Unit";"Roach";"Larva";180;2
"Unit";"Roach";"Larva";180;2
"Unit";"Roach";"Larva";180;2
"Unit";"Hydralisk";"Larva";180;2
"Unit";"Hydralisk";"Larva";180;2
"Unit";"Hydralisk";"Larva";180;2
"Unit";"Roach";"Larva";180;2
"Unit";"Hydralisk";"Larva";180;2
"Unit";"Hydralisk";"Larva";180;2
"Unit";"Roach";"Larva";180;2
"Unit";"Roach";"Larva";180;2
"Unit";"Roach";"Larva";180;2
"Unit";"Hydralisk";"Larva";180;2
"Unit";"Hydralisk";"Larva";180;2
"Unit";"Roach";"Larva";192;2
"Unit";"Hydralisk";"Larva";192;2
"Unit";"Hydralisk";"Larva";192;2
"Unit";"Roach";"Larva";204;2
"Unit";"Roach";"Larva";204;2
"Unit";"Roach";"Larva";204;2
"Unit";"Roach";"Larva";204;2
"Unit";"Hydralisk";"Larva";204;2
"Unit";"Hydralisk";"Larva";204;2
"Unit";"Hydralisk";"Larva";204;2
"Unit";"Roach";"Larva";214;2
"Unit";"Hydralisk";"Larva";214;2
"Unit";"Roach";"Larva";228;2
"Unit";"Roach";"Larva";232;2
"Unit";"Roach";"Larva";232;2
"Building";"Hatchery";NA;198;0
"Unit";"Roach";"Larva";232;2
"Unit";"Roach";"Larva";234;2
