"type";"unit_name";"on_building";"total_supply_lag";"supply"
"Unit";"Overlord";"Larva";13;0
"Building";"Hatchery";NA;16;0
"Building";"Extractor";NA;19;0
"Building";"SpawningPool";NA;19;0
"Unit";"Overlord";"Larva";23;0
"Unit";"Zergling";"Larva";23;1
"Unit";"Zergling";"Larva";24;1
"Unit";"Zergling";"Larva";25;1
"Unit";"Zergling";"Larva";26;1
"Unit";"Queen";"Hatchery";27;2
"Unit";"Queen";"Hatchery";29;2
"Building";"Hatchery";NA;37;0
"Unit";"Overlord";"Larva";37;0
"Building";"CreepTumorQueen";NA;42;0
"Unit";"Queen";"Hatchery";48;2
"Unit";"Overlord";"Larva";50;0
"Building";"SporeCrawler";NA;50;0
"Building";"CreepTumor";NA;51;0
"Building";"SporeCrawler";NA;51;0
"Unit";"Queen";"Hatchery";58;2
"Unit";"Overlord";"Larva";60;0
"Unit";"Queen";"Hatchery";60;2
"Building";"EvolutionChamber";NA;64;0
"Building";"CreepTumor";NA;66;0
"Building";"SporeCrawler";NA;66;0
"Unit";"Overlord";"Larva";68;0
"Unit";"Overlord";"Larva";68;0
"Unit";"Queen";"Hatchery";68;2
"Building";"Extractor";NA;70;0
"Building";"Extractor";NA;70;0
"Unit";"Overlord";"Larva";72;0
"Building";"CreepTumor";NA;72;0
"Unit";"Queen";"Hatchery";72;2
"Unit";"Overlord";"Larva";74;0
"Building";"CreepTumorQueen";NA;82;0
"Building";"CreepTumorQueen";NA;82;0
"Building";"BanelingNest";NA;82;0
"Building";"CreepTumor";NA;87;0
"Unit";"Zergling";"Larva";87;1
"Unit";"Zergling";"Larva";88;1
"Unit";"Zergling";"Larva";89;1
"Unit";"Zergling";"Larva";90;1
"Unit";"Zergling";"Larva";91;1
"Unit";"Zergling";"Larva";92;1
"Unit";"Zergling";"Larva";93;1
"Unit";"Zergling";"Larva";94;1
"Unit";"Zergling";"Larva";95;1
"Unit";"Zergling";"Larva";96;1
"Unit";"Zergling";"Larva";97;1
"Unit";"Zergling";"Larva";98;1
"Unit";"Zergling";"Larva";99;1
"Unit";"Zergling";"Larva";100;1
"Unit";"Zergling";"Larva";101;1
"Unit";"Zergling";"Larva";102;1
"Building";"CreepTumor";NA;103;0
"Building";"Extractor";NA;103;0
"Building";"Extractor";NA;105;0
"Building";"CreepTumor";NA;106;0
"Building";"CreepTumor";NA;109;0
"Unit";"Baneling";"Zergling";113;0
"Unit";"Baneling";"Zergling";113;0
"Unit";"Baneling";"Zergling";113;0
"Unit";"Baneling";"Zergling";113;0
"Unit";"Zergling";"Larva";113;1
"Unit";"Zergling";"Larva";114;1
"Building";"SpineCrawler";NA;115;0
"Unit";"Overlord";"Larva";115;0
"Unit";"Overlord";"Larva";115;0
"Building";"CreepTumor";NA;115;0
"Unit";"Overlord";"Larva";115;0
"Building";"SpineCrawler";NA;115;0
"Unit";"Baneling";"Zergling";115;0
"Unit";"Baneling";"Zergling";115;0
"Unit";"Overlord";"Larva";115;0
"Building";"HydraliskDen";NA;123;0
"Building";"Hatchery";NA;123;0
"Building";"Extractor";NA;123;0
"Unit";"Zergling";"Larva";126;1
"Unit";"Zergling";"Larva";127;1
"Unit";"Zergling";"Larva";128;1
"Unit";"Zergling";"Larva";129;1
"Unit";"Zergling";"Larva";130;1
"Unit";"Zergling";"Larva";131;1
"Unit";"Zergling";"Larva";132;1
"Unit";"Zergling";"Larva";133;1
"Building";"CreepTumor";NA;134;0
"Building";"CreepTumor";NA;134;0
"Unit";"Overlord";"Larva";134;0
"Unit";"Zergling";"Larva";134;1
"Unit";"Zergling";"Larva";135;1
"Unit";"Zergling";"Larva";136;1
"Unit";"Zergling";"Larva";137;1
"Unit";"Zergling";"Larva";138;1
"Unit";"Zergling";"Larva";139;1
"Unit";"Zergling";"Larva";140;1
"Unit";"Zergling";"Larva";141;1
"Unit";"Overlord";"Larva";142;0
"Building";"CreepTumor";NA;142;0
"Building";"Spire";NA;142;0
"Building";"CreepTumorQueen";NA;142;0
"Building";"CreepTumorQueen";NA;142;0
"Building";"CreepTumorQueen";NA;142;0
"Building";"CreepTumorQueen";NA;142;0
"Building";"CreepTumorQueen";NA;142;0
"Building";"Hatchery";NA;142;0
"Building";"CreepTumor";NA;142;0
"Unit";"Hydralisk";"Larva";142;2
"Unit";"Hydralisk";"Larva";144;2
"Unit";"Hydralisk";"Larva";146;2
"Unit";"Hydralisk";"Larva";148;2
"Unit";"Hydralisk";"Larva";150;2
"Unit";"Hydralisk";"Larva";152;2
"Building";"CreepTumorQueen";NA;154;0
"Building";"CreepTumorQueen";NA;154;0
"Unit";"Hydralisk";"Larva";154;2
"Unit";"Hydralisk";"Larva";156;2
"Unit";"Hydralisk";"Larva";158;2
"Unit";"Hydralisk";"Larva";160;2
"Unit";"Overlord";"Larva";162;0
"Unit";"Hydralisk";"Larva";162;2
"Unit";"Hydralisk";"Larva";164;2
"Unit";"Hydralisk";"Larva";166;2
"Unit";"Hydralisk";"Larva";168;2
"Unit";"Overlord";"Larva";170;0
"Building";"CreepTumorQueen";NA;170;0
"Building";"CreepTumorQueen";NA;170;0
"Unit";"Overlord";"Larva";177;0
"Building";"CreepTumor";NA;177;0
"Building";"CreepTumor";NA;177;0
"Building";"Extractor";NA;177;0
"Building";"Extractor";NA;177;0
"Unit";"Zergling";"Larva";177;1
"Unit";"Zergling";"Larva";178;1
"Unit";"Zergling";"Larva";179;1
"Unit";"Zergling";"Larva";180;1
"Unit";"Zergling";"Larva";181;1
"Unit";"Zergling";"Larva";182;1
"Unit";"Zergling";"Larva";183;1
"Unit";"Zergling";"Larva";184;1
"Unit";"Zergling";"Larva";185;1
"Unit";"Zergling";"Larva";186;1
"Unit";"Zergling";"Larva";187;1
"Unit";"Zergling";"Larva";188;1
"Unit";"Zergling";"Larva";189;1
"Unit";"Zergling";"Larva";190;1
"Unit";"Zergling";"Larva";191;1
"Unit";"Zergling";"Larva";192;1
"Unit";"Zergling";"Larva";193;1
"Unit";"Zergling";"Larva";194;1
"Unit";"Zergling";"Larva";195;1
"Unit";"Zergling";"Larva";196;1
"Unit";"Zergling";"Larva";197;1
"Unit";"Zergling";"Larva";198;1
"Unit";"Zergling";"Larva";199;1
"Unit";"Zergling";"Larva";200;1
"Unit";"Zergling";"Larva";201;1
"Unit";"Zergling";"Larva";202;1
"Building";"CreepTumorQueen";NA;205;0
"Building";"CreepTumorQueen";NA;205;0
"Building";"CreepTumor";NA;205;0
"Building";"CreepTumor";NA;205;0
"Building";"CreepTumorQueen";NA;205;0
"Building";"CreepTumorQueen";NA;205;0
"Building";"CreepTumor";NA;205;0
"Unit";"Overlord";"Larva";205;0
"Unit";"Mutalisk";"Larva";205;2
"Unit";"Mutalisk";"Larva";207;2
"Unit";"Mutalisk";"Larva";209;2
"Unit";"Mutalisk";"Larva";211;2
"Unit";"Mutalisk";"Larva";213;2
"Unit";"Mutalisk";"Larva";215;2
"Unit";"Mutalisk";"Larva";217;2
"Unit";"Mutalisk";"Larva";219;2
"Unit";"Mutalisk";"Larva";221;2
"Unit";"Mutalisk";"Larva";223;2
"Unit";"Overlord";"Larva";225;0
"Unit";"Mutalisk";"Larva";225;2
"Unit";"Overlord";"Larva";227;0
"Building";"CreepTumor";NA;235;0
"Building";"CreepTumor";NA;235;0
"Building";"CreepTumor";NA;235;0
"Building";"CreepTumor";NA;235;0
"Unit";"Baneling";"Zergling";235;0
"Unit";"Baneling";"Zergling";235;0
"Unit";"Baneling";"Zergling";235;0
"Unit";"Baneling";"Zergling";235;0
"Unit";"Baneling";"Zergling";235;0
"Unit";"Baneling";"Zergling";235;0
"Unit";"Baneling";"Zergling";235;0
"Unit";"Baneling";"Zergling";235;0
"Unit";"Baneling";"Zergling";235;0
"Unit";"Baneling";"Zergling";235;0
"Unit";"Baneling";"Zergling";235;0
"Unit";"Baneling";"Zergling";235;0
"Building";"CreepTumor";NA;235;0
"Building";"CreepTumor";NA;235;0
"Building";"CreepTumor";NA;235;0
"Building";"CreepTumor";NA;235;0
"Building";"CreepTumor";NA;235;0
"Building";"Hatchery";NA;235;0
"Building";"CreepTumorQueen";NA;235;0
"Unit";"Zergling";"Larva";235;1
"Unit";"Zergling";"Larva";236;1
"Unit";"Zergling";"Larva";237;1
"Unit";"Zergling";"Larva";238;1
"Unit";"Zergling";"Larva";239;1
"Unit";"Zergling";"Larva";240;1
"Unit";"Zergling";"Larva";241;1
"Unit";"Zergling";"Larva";242;1
"Unit";"Zergling";"Larva";243;1
"Unit";"Zergling";"Larva";244;1
"Unit";"Zergling";"Larva";245;1
"Unit";"Zergling";"Larva";246;1
"Unit";"Zergling";"Larva";247;1
"Unit";"Zergling";"Larva";248;1
"Unit";"Zergling";"Larva";249;1
"Unit";"Zergling";"Larva";250;1
"Unit";"Zergling";"Larva";251;1
"Unit";"Zergling";"Larva";252;1
"Unit";"Zergling";"Larva";253;1
"Unit";"Zergling";"Larva";254;1
"Unit";"Zergling";"Larva";255;1
"Unit";"Zergling";"Larva";256;1
"Unit";"Zergling";"Larva";257;1
"Unit";"Zergling";"Larva";258;1
"Building";"CreepTumor";NA;259;0
"Building";"CreepTumor";NA;259;0
"Unit";"Zergling";"Larva";259;1
"Unit";"Zergling";"Larva";260;1
"Unit";"Zergling";"Larva";261;1
"Unit";"Zergling";"Larva";262;1
"Unit";"Zergling";"Larva";263;1
"Unit";"Zergling";"Larva";264;1
"Unit";"Zergling";"Larva";265;1
"Unit";"Zergling";"Larva";266;1
"Unit";"Zergling";"Larva";267;1
"Unit";"Zergling";"Larva";268;1
"Unit";"Overlord";"Larva";269;0
"Unit";"Overlord";"Larva";269;0
"Unit";"Baneling";"Zergling";269;0
"Unit";"Baneling";"Zergling";269;0
"Unit";"Baneling";"Zergling";269;0
"Unit";"Baneling";"Zergling";269;0
"Unit";"Baneling";"Zergling";269;0
"Unit";"Baneling";"Zergling";269;0
"Unit";"Baneling";"Zergling";269;0
"Unit";"Baneling";"Zergling";269;0
"Unit";"Baneling";"Zergling";269;0
"Unit";"Baneling";"Zergling";269;0
"Unit";"Baneling";"Zergling";269;0
"Unit";"Baneling";"Zergling";269;0
"Unit";"Baneling";"Zergling";269;0
"Unit";"Zergling";"Larva";269;1
"Unit";"Zergling";"Larva";270;1
"Unit";"Zergling";"Larva";271;1
"Unit";"Zergling";"Larva";272;1
"Unit";"Zergling";"Larva";273;1
"Unit";"Zergling";"Larva";274;1
"Unit";"Zergling";"Larva";275;1
"Unit";"Zergling";"Larva";276;1
"Unit";"Baneling";"Zergling";277;0
"Unit";"Baneling";"Zergling";277;0
"Unit";"Baneling";"Zergling";277;0
"Unit";"Baneling";"Zergling";277;0
"Unit";"Baneling";"Zergling";277;0
"Unit";"Baneling";"Zergling";277;0
"Unit";"Baneling";"Zergling";277;0
"Unit";"Baneling";"Zergling";277;0
"Unit";"Baneling";"Zergling";277;0
"Unit";"Baneling";"Zergling";277;0
"Unit";"Baneling";"Zergling";277;0
"Unit";"Baneling";"Zergling";277;0
"Unit";"Baneling";"Zergling";277;0
"Unit";"Baneling";"Zergling";277;0
"Unit";"Baneling";"Zergling";277;0
"Unit";"Baneling";"Zergling";277;0
"Unit";"Baneling";"Zergling";277;0
"Unit";"Baneling";"Zergling";277;0
"Unit";"Baneling";"Zergling";277;0
"Unit";"Baneling";"Zergling";277;0
"Unit";"Baneling";"Zergling";277;0
"Unit";"Baneling";"Zergling";277;0
"Unit";"Baneling";"Zergling";277;0
"Unit";"Baneling";"Zergling";277;0
"Unit";"Baneling";"Zergling";277;0
"Unit";"Baneling";"Zergling";277;0
"Unit";"Baneling";"Zergling";277;0
"Unit";"Zergling";"Larva";277;1
"Unit";"Zergling";"Larva";278;1
"Unit";"Zergling";"Larva";279;1
"Unit";"Zergling";"Larva";280;1
"Unit";"Zergling";"Larva";281;1
"Unit";"Zergling";"Larva";282;1
"Unit";"Zergling";"Larva";283;1
"Unit";"Zergling";"Larva";284;1
"Unit";"Zergling";"Larva";285;1
"Unit";"Zergling";"Larva";286;1
"Unit";"Zergling";"Larva";287;1
"Unit";"Zergling";"Larva";288;1
"Unit";"Zergling";"Larva";289;1
"Unit";"Zergling";"Larva";290;1
"Unit";"Zergling";"Larva";291;1
"Unit";"Zergling";"Larva";292;1
"Unit";"Zergling";"Larva";293;1
"Unit";"Zergling";"Larva";294;1
"Unit";"Zergling";"Larva";295;1
"Unit";"Zergling";"Larva";296;1
"Unit";"Zergling";"Larva";297;1
"Unit";"Zergling";"Larva";298;1
"Unit";"Zergling";"Larva";299;1
"Unit";"Zergling";"Larva";300;1
"Unit";"Zergling";"Larva";301;1
"Unit";"Zergling";"Larva";302;1
"Unit";"Zergling";"Larva";303;1
"Unit";"Zergling";"Larva";304;1
"Unit";"Zergling";"Larva";305;1
"Unit";"Zergling";"Larva";306;1
"Unit";"Zergling";"Larva";307;1
"Unit";"Zergling";"Larva";308;1
"Unit";"Zergling";"Larva";309;1
"Unit";"Zergling";"Larva";310;1
"Unit";"Zergling";"Larva";311;1
"Unit";"Zergling";"Larva";312;1
"Unit";"Zergling";"Larva";313;1
"Unit";"Zergling";"Larva";314;1
"Unit";"Zergling";"Larva";315;1
"Unit";"Zergling";"Larva";316;1
"Unit";"Zergling";"Larva";317;1
"Unit";"Zergling";"Larva";318;1
"Unit";"Zergling";"Larva";319;1
"Unit";"Zergling";"Larva";320;1
"Unit";"Zergling";"Larva";321;1
"Unit";"Zergling";"Larva";322;1
"Unit";"Zergling";"Larva";323;1
"Unit";"Zergling";"Larva";324;1
"Unit";"Zergling";"Larva";325;1
"Unit";"Zergling";"Larva";326;1
"Unit";"Zergling";"Larva";327;1
"Unit";"Zergling";"Larva";328;1
"Unit";"Zergling";"Larva";329;1
"Unit";"Zergling";"Larva";330;1
"Unit";"Zergling";"Larva";331;1
"Unit";"Zergling";"Larva";332;1
"Unit";"Zergling";"Larva";333;1
"Unit";"Zergling";"Larva";334;1
"Unit";"Zergling";"Larva";335;1
"Unit";"Zergling";"Larva";336;1
"Building";"CreepTumorQueen";NA;337;0
"Building";"CreepTumorQueen";NA;337;0
"Unit";"Mutalisk";"Larva";337;2
"Unit";"Mutalisk";"Larva";339;2
"Unit";"Mutalisk";"Larva";341;2
"Unit";"Mutalisk";"Larva";343;2
"Unit";"Mutalisk";"Larva";345;2
"Unit";"Mutalisk";"Larva";347;2
"Unit";"Hydralisk";"Larva";352;2
"Unit";"Hydralisk";"Larva";354;2
"Unit";"Hydralisk";"Larva";356;2
"Unit";"Hydralisk";"Larva";358;2
"Unit";"Hydralisk";"Larva";360;2
"Unit";"Baneling";"Zergling";362;0
"Unit";"Baneling";"Zergling";362;0
"Unit";"Baneling";"Zergling";362;0
"Unit";"Baneling";"Zergling";362;0
"Unit";"Baneling";"Zergling";362;0
"Unit";"Baneling";"Zergling";362;0
"Unit";"Baneling";"Zergling";362;0
"Unit";"Baneling";"Zergling";362;0
"Unit";"Baneling";"Zergling";362;0
"Unit";"Baneling";"Zergling";362;0
"Unit";"Baneling";"Zergling";362;0
"Unit";"Zergling";"Larva";362;1
"Unit";"Zergling";"Larva";363;1
"Unit";"Zergling";"Larva";364;1
"Unit";"Zergling";"Larva";365;1
"Unit";"Zergling";"Larva";366;1
"Unit";"Zergling";"Larva";367;1
"Unit";"Zergling";"Larva";368;1
"Unit";"Zergling";"Larva";369;1
"Unit";"Zergling";"Larva";370;1
"Unit";"Zergling";"Larva";371;1
"Unit";"Zergling";"Larva";372;1
"Unit";"Zergling";"Larva";373;1
"Building";"CreepTumor";NA;377;0
"Building";"CreepTumor";NA;377;0
"Unit";"Baneling";"Zergling";377;0
"Unit";"Hydralisk";"Larva";377;2
"Unit";"Hydralisk";"Larva";379;2
"Unit";"Hydralisk";"Larva";381;2
"Unit";"Hydralisk";"Larva";383;2
"Unit";"Hydralisk";"Larva";385;2
"Unit";"Hydralisk";"Larva";387;2
"Unit";"Hydralisk";"Larva";389;2
"Unit";"Hydralisk";"Larva";391;2
"Unit";"Zergling";"Larva";393;1
"Unit";"Zergling";"Larva";394;1
"Unit";"Zergling";"Larva";395;1
"Unit";"Zergling";"Larva";396;1
"Unit";"Zergling";"Larva";397;1
"Unit";"Zergling";"Larva";398;1
"Unit";"Zergling";"Larva";399;1
"Unit";"Zergling";"Larva";400;1
"Unit";"Zergling";"Larva";401;1
"Unit";"Zergling";"Larva";402;1
"Unit";"Zergling";"Larva";403;1
"Unit";"Zergling";"Larva";404;1
"Unit";"Zergling";"Larva";405;1
"Unit";"Zergling";"Larva";406;1
"Unit";"Zergling";"Larva";407;1
"Unit";"Zergling";"Larva";408;1
"Unit";"Zergling";"Larva";409;1
"Unit";"Zergling";"Larva";410;1
"Unit";"Zergling";"Larva";411;1
"Unit";"Zergling";"Larva";412;1
"Unit";"Zergling";"Larva";413;1
"Unit";"Zergling";"Larva";414;1
"Unit";"Zergling";"Larva";415;1
"Unit";"Zergling";"Larva";416;1
"Unit";"Zergling";"Larva";417;1
"Unit";"Zergling";"Larva";418;1
"Unit";"Zergling";"Larva";419;1
"Unit";"Zergling";"Larva";420;1
"Unit";"Zergling";"Larva";421;1
"Unit";"Zergling";"Larva";422;1
"Unit";"Zergling";"Larva";423;1
"Unit";"Zergling";"Larva";424;1
"Unit";"Zergling";"Larva";425;1
"Unit";"Zergling";"Larva";426;1
"Unit";"Zergling";"Larva";427;1
"Unit";"Zergling";"Larva";428;1
"Unit";"Zergling";"Larva";429;1
"Unit";"Zergling";"Larva";430;1
"Unit";"Zergling";"Larva";431;1
"Unit";"Zergling";"Larva";432;1
"Unit";"Zergling";"Larva";433;1
"Unit";"Zergling";"Larva";434;1
"Unit";"Zergling";"Larva";435;1
"Unit";"Zergling";"Larva";436;1
"Unit";"Baneling";"Zergling";437;0
"Unit";"Baneling";"Zergling";437;0
"Unit";"Baneling";"Zergling";437;0
"Unit";"Baneling";"Zergling";437;0
"Unit";"Baneling";"Zergling";437;0
"Unit";"Baneling";"Zergling";437;0
"Unit";"Baneling";"Zergling";437;0
"Unit";"Baneling";"Zergling";437;0
"Unit";"Baneling";"Zergling";437;0
"Unit";"Baneling";"Zergling";437;0
"Unit";"Baneling";"Zergling";437;0
"Unit";"Baneling";"Zergling";437;0
"Unit";"Baneling";"Zergling";437;0
"Unit";"Baneling";"Zergling";437;0
"Unit";"Baneling";"Zergling";437;0
"Unit";"Baneling";"Zergling";437;0
"Unit";"Baneling";"Zergling";437;0
"Unit";"Baneling";"Zergling";437;0
"Unit";"Baneling";"Zergling";437;0
"Unit";"Baneling";"Zergling";437;0
"Unit";"Baneling";"Zergling";437;0
"Unit";"Baneling";"Zergling";437;0
"Unit";"Baneling";"Zergling";437;0
"Unit";"Baneling";"Zergling";437;0
"Unit";"Baneling";"Zergling";437;0
"Unit";"Baneling";"Zergling";437;0
"Unit";"Baneling";"Zergling";437;0
"Unit";"Baneling";"Zergling";437;0
"Unit";"Baneling";"Zergling";437;0
"Unit";"Baneling";"Zergling";437;0
"Unit";"Baneling";"Zergling";437;0
"Building";"CreepTumor";NA;437;0
"Unit";"Zergling";"Larva";437;1
"Unit";"Zergling";"Larva";438;1
"Unit";"Zergling";"Larva";439;1
"Unit";"Zergling";"Larva";440;1
"Unit";"Zergling";"Larva";441;1
"Unit";"Zergling";"Larva";442;1
"Unit";"Zergling";"Larva";443;1
"Unit";"Zergling";"Larva";444;1
"Unit";"Zergling";"Larva";445;1
"Unit";"Zergling";"Larva";446;1
"Unit";"Zergling";"Larva";447;1
"Unit";"Zergling";"Larva";448;1
"Unit";"Zergling";"Larva";449;1
"Unit";"Zergling";"Larva";450;1
"Unit";"Zergling";"Larva";451;1
"Unit";"Zergling";"Larva";452;1
"Unit";"Zergling";"Larva";453;1
"Unit";"Zergling";"Larva";454;1
"Unit";"Zergling";"Larva";455;1
"Unit";"Zergling";"Larva";456;1
"Unit";"Baneling";"Zergling";457;0
"Unit";"Baneling";"Zergling";457;0
"Unit";"Baneling";"Zergling";457;0
"Unit";"Baneling";"Zergling";457;0
"Unit";"Baneling";"Zergling";457;0
"Unit";"Baneling";"Zergling";457;0
"Unit";"Zergling";"Larva";457;1
"Unit";"Zergling";"Larva";458;1
"Unit";"Zergling";"Larva";459;1
"Unit";"Zergling";"Larva";460;1
"Unit";"Zergling";"Larva";461;1
"Unit";"Zergling";"Larva";462;1
"Unit";"Zergling";"Larva";463;1
"Unit";"Zergling";"Larva";464;1
"Unit";"Baneling";"Zergling";465;0
"Unit";"Zergling";"Larva";465;1
"Unit";"Zergling";"Larva";466;1
"Upgrade";"SprayZerg";NA;467;0
"Upgrade";"SprayZerg";NA;467;0
"Upgrade";"SprayZerg";NA;467;0
"Upgrade";"zerglingmovementspeed";NA;467;0
"Upgrade";"SprayZerg";NA;467;0
"Upgrade";"SprayZerg";NA;467;0
"Upgrade";"ZergMeleeWeaponsLevel1";NA;467;0
"Upgrade";"SprayZerg";NA;467;0
"Upgrade";"SprayZerg";NA;467;0
"Upgrade";"CentrificalHooks";NA;467;0
"Upgrade";"EvolveGroovedSpines";NA;467;0
"Upgrade";"SprayZerg";NA;467;0
"Upgrade";"SprayZerg";NA;467;0
"Upgrade";"EvolveMuscularAugments";NA;467;0
"Upgrade";"overlordspeed";NA;467;0
"Upgrade";"ZergMeleeWeaponsLevel2";NA;467;0
"Upgrade";"SprayZerg";NA;467;0
"Upgrade";"ZergFlyerWeaponsLevel1";NA;467;0
"Upgrade";"SprayZerg";NA;467;0
