"type";"unit_name";"on_building";"total_supply";"supply"
"Unit";"Overlord";"Larva";14;0
"Building";"SpawningPool";NA;12;0
"Unit";"Zergling";"Larva";15;1
"Unit";"Zergling";"Larva";15;1
"Unit";"Zergling";"Larva";15;1
"Unit";"Zergling";"Larva";15;1
"Unit";"Zergling";"Larva";15;1
"Unit";"Zergling";"Larva";15;1
"Unit";"Zergling";"Larva";15;1
"Unit";"Zergling";"Larva";15;1
"Unit";"Overlord";"Larva";23;0
"Unit";"Queen";"Hatchery";23;2
"Building";"Hatchery";NA;21;0
"Unit";"Queen";"Hatchery";27;2
"Unit";"Overlord";"Larva";30;0
"Unit";"Zergling";"Larva";33;1
"Unit";"Zergling";"Larva";33;1
"Unit";"Zergling";"Larva";33;1
"Unit";"Zergling";"Larva";33;1
"Unit";"Queen";"Hatchery";30;2
"Building";"CreepTumorQueen";NA;41;0
"Unit";"Zergling";"Larva";37;1
"Unit";"Zergling";"Larva";37;1
"Building";"CreepTumor";NA;45;0
"Building";"CreepTumorQueen";NA;53;0
"Building";"Extractor";NA;53;0
"Building";"Extractor";NA;53;0
"Unit";"Overlord";"Larva";55;0
"Building";"Hatchery";NA;37;0
"Unit";"Overlord";"Larva";56;0
"Building";"CreepTumor";NA;56;0
"Building";"CreepTumor";NA;56;0
"Unit";"Overlord";"Larva";57;0
"Building";"CreepTumor";NA;63;0
"Building";"CreepTumor";NA;64;0
"Unit";"Overlord";"Larva";63;0
"Unit";"Overlord";"Larva";63;0
"Building";"SporeCrawler";NA;68;0
"Building";"SporeCrawler";NA;68;0
"Building";"SporeCrawler";NA;68;0
"Building";"CreepTumor";NA;72;0
"Building";"RoachWarren";NA;63;0
"Building";"CreepTumor";NA;73;0
"Unit";"Zergling";"Larva";75;1
"Unit";"Zergling";"Larva";75;1
"Unit";"Zergling";"Larva";75;1
"Unit";"Zergling";"Larva";75;1
"Unit";"Zergling";"Larva";75;1
"Unit";"Zergling";"Larva";75;1
"Unit";"Roach";"Larva";75;2
"Unit";"Roach";"Larva";75;2
"Unit";"Roach";"Larva";75;2
"Unit";"Roach";"Larva";75;2
"Unit";"Roach";"Larva";75;2
"Unit";"Roach";"Larva";75;2
"Unit";"Roach";"Larva";76;2
"Unit";"Roach";"Larva";76;2
"Unit";"Zergling";"Larva";76;1
"Unit";"Zergling";"Larva";76;1
"Unit";"Zergling";"Larva";76;1
"Unit";"Zergling";"Larva";76;1
"Unit";"Overlord";"Larva";76;0
"Unit";"Overlord";"Larva";76;0
"Building";"CreepTumor";NA;94;0
"Building";"CreepTumor";NA;94;0
"Unit";"Roach";"Larva";92;2
"Unit";"Queen";"Hatchery";102;2
"Building";"EvolutionChamber";NA;114;0
"Building";"Extractor";NA;117;0
"Building";"Extractor";NA;117;0
"Building";"HydraliskDen";NA;117;0
"Building";"CreepTumor";NA;126;0
"Unit";"Overlord";"Larva";119;0
"Unit";"Overlord";"Larva";121;0
"Building";"CreepTumor";NA;126;0
"Unit";"Overlord";"Larva";125;0
"Unit";"Overlord";"Larva";126;0
"Unit";"Overlord";"Larva";126;0
"Unit";"Queen";"Hatchery";119;2
"Unit";"Roach";"Larva";126;2
"Unit";"Roach";"Larva";126;2
"Unit";"Roach";"Larva";126;2
"Unit";"Roach";"Larva";126;2
"Unit";"Roach";"Larva";126;2
"Unit";"Roach";"Larva";126;2
"Unit";"Roach";"Larva";126;2
"Unit";"Roach";"Larva";126;2
"Unit";"Roach";"Larva";126;2
"Unit";"Roach";"Larva";126;2
"Unit";"Roach";"Larva";126;2
"Upgrade";"GlialReconstitution";"RoachWarren";119;0
"Unit";"Hydralisk";"Larva";128;2
"Building";"CreepTumor";NA;128;0
"Building";"CreepTumor";NA;130;0
"Unit";"Overlord";"Larva";150;0
"Building";"Hatchery";NA;126;0
"Unit";"Hydralisk";"Larva";152;2
"Unit";"Hydralisk";"Larva";152;2
"Unit";"Hydralisk";"Larva";152;2
"Building";"Extractor";NA;157;0
"Building";"Extractor";NA;157;0
"Building";"CreepTumor";NA;160;0
"Unit";"Overlord";"Larva";158;0
"Unit";"Overlord";"Larva";158;0
"Unit";"Overlord";"Larva";158;0
"Unit";"Hydralisk";"Larva";160;2
"Unit";"Hydralisk";"Larva";160;2
"Unit";"Overlord";"Larva";174;0
"Unit";"Overlord";"Larva";174;0
"Unit";"Overlord";"Larva";174;0
"Building";"CreepTumor";NA;178;0
"Unit";"Overlord";"Larva";174;0
"Unit";"Hydralisk";"Larva";174;2
"Unit";"Hydralisk";"Larva";174;2
"Unit";"Hydralisk";"Larva";174;2
"Upgrade";"ZergMissileWeaponsLevel1";"EvolutionChamber";128;0
"Unit";"Zergling";"Larva";179;1
"Unit";"Zergling";"Larva";179;1
"Unit";"Zergling";"Larva";179;1
"Unit";"Zergling";"Larva";179;1
"Unit";"Zergling";"Larva";179;1
"Unit";"Zergling";"Larva";179;1
"Unit";"Zergling";"Larva";179;1
"Unit";"Zergling";"Larva";179;1
"Unit";"Hydralisk";"Larva";179;2
"Unit";"Hydralisk";"Larva";179;2
"Unit";"Hydralisk";"Larva";179;2
"Unit";"Hydralisk";"Larva";179;2
"Unit";"Overlord";"Larva";185;0
"Building";"CreepTumor";NA;185;0
"Building";"CreepTumor";NA;185;0
"Building";"Extractor";NA;185;0
"Building";"Extractor";NA;185;0
"Upgrade";"EvolveGroovedSpines";"HydraliskDen";174;0
"Unit";"Zergling";"Larva";204;1
"Unit";"Zergling";"Larva";204;1
"Unit";"Zergling";"Larva";204;1
"Unit";"Zergling";"Larva";204;1
"Unit";"Zergling";"Larva";204;1
"Unit";"Zergling";"Larva";204;1
"Unit";"Zergling";"Larva";204;1
"Unit";"Zergling";"Larva";204;1
"Unit";"Zergling";"Larva";204;1
"Unit";"Zergling";"Larva";204;1
"Unit";"Zergling";"Larva";204;1
"Unit";"Zergling";"Larva";204;1
"Unit";"Zergling";"Larva";204;1
"Unit";"Zergling";"Larva";204;1
"Unit";"Zergling";"Larva";204;1
"Unit";"Zergling";"Larva";204;1
"Unit";"Zergling";"Larva";204;1
"Unit";"Zergling";"Larva";204;1
"Unit";"Zergling";"Larva";204;1
"Unit";"Zergling";"Larva";204;1
"Unit";"Zergling";"Larva";204;1
"Unit";"Zergling";"Larva";204;1
"Unit";"Hydralisk";"Larva";204;2
"Unit";"Hydralisk";"Larva";204;2
"Unit";"Hydralisk";"Larva";204;2
"Building";"CreepTumor";NA;226;0
"Unit";"Hydralisk";"Larva";226;2
"Unit";"Hydralisk";"Larva";226;2
"Unit";"Hydralisk";"Larva";226;2
"Unit";"Hydralisk";"Larva";226;2
"Unit";"Hydralisk";"Larva";226;2
"Unit";"Hydralisk";"Larva";226;2
"Unit";"Hydralisk";"Larva";226;2
"Building";"CreepTumor";NA;232;0
"Unit";"Overlord";"Larva";232;0
"Unit";"Overlord";"Larva";232;0
"Building";"LurkerDenMP";NA;196;0
"Upgrade";"EvolveMuscularAugments";"HydraliskDen";232;0
"Unit";"Overlord";"Larva";252;0
"Unit";"Hydralisk";"Larva";252;2
"Unit";"Hydralisk";"Larva";252;2
"Unit";"Hydralisk";"Larva";252;2
"Unit";"Hydralisk";"Larva";252;2
"Unit";"Hydralisk";"Larva";252;2
"Unit";"Hydralisk";"Larva";252;2
"Unit";"Hydralisk";"Larva";252;2
"Unit";"Hydralisk";"Larva";252;2
"Unit";"Overlord";"Larva";252;0
"Building";"CreepTumor";NA;268;0
"Building";"CreepTumor";NA;268;0
"Building";"Hatchery";NA;252;0
"Building";"Extractor";NA;271;0
"Building";"Extractor";NA;271;0
"Unit";"Hydralisk";"Larva";271;2
"Unit";"Hydralisk";"Larva";271;2
"Unit";"Hydralisk";"Larva";271;2
"Building";"SpineCrawler";NA;268;0
"Building";"SpineCrawler";NA;268;0
"Building";"SpineCrawler";NA;268;0
"Upgrade";"ZergMissileWeaponsLevel2";"EvolutionChamber";232;0
"Building";"EvolutionChamber";NA;271;0
"Building";"InfestationPit";NA;271;0
