"type";"unit_name";"on_building";"total_supply_lag";"supply"
"Building";"Pylon";NA;14;0
"Building";"Gateway";NA;16;0
"Building";"Assimilator";NA;17;0
"Building";"Nexus";NA;19;0
"Building";"CyberneticsCore";NA;20;0
"Building";"Assimilator";NA;21;0
"Building";"Pylon";NA;22;0
"Unit";"Adept";"Gateway";23;2
"Building";"TwilightCouncil";NA;27;0
"Unit";"Adept";"Gateway";29;2
"Building";"Gateway";NA;37;0
"Building";"DarkShrine";NA;37;0
"Building";"Gateway";NA;39;0
"Building";"Pylon";NA;40;0
"Building";"RoboticsFacility";NA;42;0
"Building";"Pylon";NA;43;0
"Building";"Assimilator";NA;43;0
"Building";"Pylon";NA;44;0
"Building";"Assimilator";NA;45;0
"Building";"DarkTemplar";NA;49;0
"Building";"DarkTemplar";NA;49;0
"Unit";"Observer";"Robotics Facility";49;1
"Building";"Nexus";NA;51;0
"Building";"Pylon";NA;52;0
"Building";"DarkTemplar";NA;52;0
"Unit";"Immortal";"Robotics Facility";54;4
"Upgrade";"Charge";"TwilightCouncil";58;0
"Unit";"Stalker";"Gateway";58;2
"Unit";"Stalker";"Gateway";60;2
"Unit";"Immortal";"Robotics Facility";65;4
"Unit";"Sentry";"Gateway";69;2
"Unit";"Zealot";"Gateway";71;2
"Unit";"Zealot";"Gateway";73;2
"Building";"Gateway";NA;76;0
"Building";"Gateway";NA;76;0
"Building";"Gateway";NA;76;0
"Unit";"Sentry";"Gateway";79;2
"Unit";"Sentry";"Gateway";81;2
"Unit";"Zealot";"Gateway";83;2
"Building";"Pylon";NA;85;0
"Building";"Pylon";NA;85;0
"Building";"Pylon";NA;85;0
"Building";"Pylon";NA;85;0
"Building";"Pylon";NA;85;0
"Unit";"Immortal";"Robotics Facility";85;4
"Unit";"Phoenix";"Stargate";89;2
"Unit";"Zealot";"Gateway";91;2
"Unit";"Zealot";"Gateway";93;2
"Unit";"Zealot";"Gateway";95;2
"Building";"Pylon";NA;99;0
"Unit";"Sentry";"Gateway";100;2
"Unit";"Zealot";"Gateway";102;2
"Building";"DarkTemplar";NA;107;0
"Unit";"Zealot";"Gateway";107;2
"Unit";"Zealot";"Gateway";109;2
"Unit";"Zealot";"Gateway";111;2
"Unit";"Observer";"Robotics Facility";116;1
"Unit";"Phoenix";"Stargate";117;2
"Building";"Pylon";NA;119;0
"Building";"Pylon";NA;119;0
"Building";"Forge";NA;119;0
"Building";"Forge";NA;119;0
"Unit";"Stalker";"Gateway";120;2
"Unit";"Stalker";"Gateway";122;2
"Unit";"Stalker";"Gateway";124;2
"Building";"RoboticsBay";NA;131;0
"Building";"Assimilator";NA;132;0
"Unit";"Phoenix";"Stargate";132;2
"Building";"Assimilator";NA;137;0
"Upgrade";"ProtossGroundWeaponsLevel1";"Forge";140;0
"Unit";"Stalker";"Gateway";143;2
"Unit";"Stalker";"Gateway";145;2
"Unit";"Stalker";"Gateway";147;2
"Unit";"Stalker";"Gateway";149;2
"Unit";"Stalker";"Gateway";151;2
"Unit";"Zealot";"Gateway";153;2
"Building";"Pylon";NA;156;0
"Building";"Pylon";NA;156;0
"Unit";"Phoenix";"Stargate";156;2
"Building";"Pylon";NA;158;0
"Building";"Pylon";NA;158;0
"Unit";"Colossus";"Robotics Facility";158;6
"Building";"Pylon";NA;164;0
"Unit";"Stalker";"Gateway";164;2
"Unit";"Stalker";"Gateway";166;2
"Unit";"Stalker";"Gateway";168;2
"Unit";"Stalker";"Gateway";170;2
"Unit";"Zealot";"Gateway";172;2
"Unit";"Zealot";"Gateway";174;2
"Building";"Pylon";NA;176;0
"Building";"Pylon";NA;176;0
"Building";"Nexus";NA;176;0
"Upgrade";"ExtendedThermalLance";"RoboticsBay";176;0
"Unit";"Colossus";"Robotics Facility";179;6
"Unit";"Phoenix";"Stargate";187;2
"Unit";"Zealot";"Gateway";189;2
"Upgrade";"ProtossGroundWeaponsLevel2";"Forge";191;0
"Building";"DarkTemplar";NA;191;0
"Building";"DarkTemplar";NA;191;0
"Building";"DarkTemplar";NA;191;0
"Building";"Gateway";NA;191;0
"Building";"Gateway";NA;191;0
"Unit";"Archon";"High Templar";191;0
"Unit";"Phoenix";"Stargate";191;2
"Unit";"Zealot";"Gateway";193;2
"Unit";"Zealot";"Gateway";195;2
"Unit";"Colossus";"Robotics Facility";197;6
"Unit";"Zealot";"Gateway";203;2
"Unit";"Zealot";"Gateway";205;2
"Unit";"Zealot";"Gateway";207;2
"Unit";"Zealot";"Gateway";209;2
"Unit";"Zealot";"Gateway";211;2
"Unit";"Zealot";"Gateway";213;2
"Building";"Gateway";NA;215;0
"Building";"Gateway";NA;215;0
"Building";"Gateway";NA;215;0
"Unit";"Zealot";"Gateway";215;2
"Unit";"Zealot";"Gateway";217;2
"Unit";"Zealot";"Gateway";219;2
"Unit";"Stalker";"Gateway";221;2
"Unit";"Stalker";"Gateway";223;2
"Unit";"Stalker";"Gateway";225;2
"Unit";"Colossus";"Robotics Facility";227;6
"Building";"Pylon";NA;233;0
"Building";"Assimilator";NA;236;0
"Building";"Assimilator";NA;236;0
"Building";"TemplarArchive";NA;236;0
"Building";"Pylon";NA;236;0
"Unit";"Phoenix";"Stargate";236;2
"Unit";"Stalker";"Gateway";238;2
"Unit";"Stalker";"Gateway";240;2
"Unit";"Stalker";"Gateway";242;2
"Unit";"Stalker";"Gateway";244;2
"Unit";"Stalker";"Gateway";246;2
"Unit";"Stalker";"Gateway";248;2
"Unit";"Stalker";"Gateway";250;2
"Unit";"Stalker";"Gateway";252;2
"Unit";"Stalker";"Gateway";254;2
"Unit";"Stalker";"Gateway";256;2
"Unit";"Stalker";"Gateway";258;2
"Building";"HighTemplar";NA;260;0
"Building";"HighTemplar";NA;260;0
"Building";"HighTemplar";NA;260;0
"Building";"HighTemplar";NA;260;0
"Unit";"Zealot";"Gateway";260;2
"Unit";"Zealot";"Gateway";262;2
"Unit";"Archon";"High Templar";264;0
"Upgrade";"ProtossGroundWeaponsLevel3";"Forge";264;0
"Unit";"Archon";"High Templar";264;0
"Building";"PhotonCannon";NA;264;0
"Building";"Pylon";NA;264;0
"Unit";"Phoenix";"Stargate";264;2
"Building";"HighTemplar";NA;266;0
"Building";"HighTemplar";NA;266;0
"Building";"DarkTemplar";NA;266;0
"Unit";"Archon";"High Templar";266;0
"Building";"DarkTemplar";NA;266;0
"Unit";"Zealot";"Gateway";266;2
"Unit";"Zealot";"Gateway";268;2
"Unit";"Zealot";"Gateway";270;2
"Building";"Gateway";NA;272;0
"Building";"Gateway";NA;272;0
"Unit";"Disruptor";"Robotics Facility";272;3
"Building";"RoboticsFacility";NA;275;0
"Building";"Nexus";NA;275;0
"Building";"Pylon";NA;275;0
"Building";"DarkTemplar";NA;275;0
"Unit";"Phoenix";"Stargate";275;2
"Unit";"Zealot";"Gateway";277;2
"Unit";"Zealot";"Gateway";279;2
"Unit";"Zealot";"Gateway";281;2
"Unit";"Zealot";"Gateway";283;2
"Unit";"Zealot";"Gateway";285;2
"Unit";"Zealot";"Gateway";287;2
"Building";"PhotonCannon";NA;289;0
"Building";"Stargate";NA;289;0
"Building";"DarkTemplar";NA;289;0
"Building";"DarkTemplar";NA;289;0
"Unit";"Zealot";"Gateway";289;2
"Unit";"Phoenix";"Stargate";291;2
"Unit";"Zealot";"Gateway";293;2
"Unit";"Zealot";"Gateway";295;2
"Unit";"Zealot";"Gateway";297;2
"Unit";"Zealot";"Gateway";299;2
"Building";"DarkTemplar";NA;301;0
"Unit";"Stalker";"Gateway";301;2
"Unit";"Stalker";"Gateway";303;2
"Unit";"Stalker";"Gateway";305;2
"Unit";"Disruptor";"Robotics Facility";312;3
"Unit";"Disruptor";"Robotics Facility";316;3
"Building";"FleetBeacon";NA;319;0
"Building";"Stargate";NA;321;0
"Unit";"Stalker";"Gateway";322;2
"Unit";"Disruptor";"Robotics Facility";324;3
"Building";"Assimilator";NA;329;0
"Building";"Assimilator";NA;332;0
"Unit";"Zealot";"Gateway";336;2
"Unit";"Zealot";"Gateway";338;2
"Unit";"Zealot";"Gateway";340;2
"Upgrade";"ProtossShieldsLevel1";"Forge";342;0
"Unit";"Zealot";"Gateway";342;2
"Unit";"Zealot";"Gateway";344;2
"Unit";"Zealot";"Gateway";346;2
"Unit";"Zealot";"Gateway";348;2
"Unit";"Zealot";"Gateway";350;2
"Unit";"Zealot";"Gateway";352;2
"Unit";"Zealot";"Gateway";354;2
"Unit";"Zealot";"Gateway";356;2
"Unit";"Zealot";"Gateway";358;2
"Unit";"Zealot";"Gateway";360;2
"Unit";"Zealot";"Gateway";362;2
"Unit";"Zealot";"Gateway";364;2
"Unit";"Stalker";"Gateway";368;2
"Unit";"Stalker";"Gateway";370;2
"Unit";"Stalker";"Gateway";372;2
"Unit";"Zealot";"Gateway";374;2
"Unit";"Zealot";"Gateway";376;2
"Unit";"Zealot";"Gateway";378;2
"Unit";"Stalker";"Gateway";380;2
"Unit";"Stalker";"Gateway";382;2
"Unit";"Stalker";"Gateway";384;2
"Unit";"Stalker";"Gateway";386;2
"Unit";"Phoenix";"Stargate";388;2
"Building";"HighTemplar";NA;390;0
"Building";"HighTemplar";NA;390;0
"Building";"HighTemplar";NA;390;0
"Building";"HighTemplar";NA;390;0
"Building";"HighTemplar";NA;390;0
"Building";"HighTemplar";NA;390;0
"Building";"HighTemplar";NA;390;0
"Building";"HighTemplar";NA;390;0
"Unit";"Archon";"High Templar";390;0
"Unit";"Archon";"High Templar";390;0
"Unit";"Archon";"High Templar";390;0
"Unit";"Archon";"High Templar";390;0
"Building";"Pylon";NA;390;0
"Building";"Pylon";NA;390;0
"Building";"DarkTemplar";NA;390;0
"Unit";"Zealot";"Gateway";390;2
"Unit";"Zealot";"Gateway";392;2
"Unit";"Zealot";"Gateway";394;2
"Unit";"Zealot";"Gateway";396;2
"Unit";"Stalker";"Gateway";398;2
"Unit";"Stalker";"Gateway";400;2
"Unit";"Stalker";"Gateway";402;2
"Unit";"Stalker";"Gateway";404;2
"Unit";"Stalker";"Gateway";406;2
"Unit";"Stalker";"Gateway";408;2
"Unit";"Stalker";"Gateway";410;2
"Unit";"Stalker";"Gateway";412;2
"Unit";"Tempest";"Stargate";414;4
"Unit";"Tempest";"Stargate";418;4
"Upgrade";"ProtossAirWeaponsLevel1";"CyberneticsCore";422;0
"Building";"DarkTemplar";NA;422;0
"Unit";"Zealot";"Gateway";422;2
"Unit";"Zealot";"Gateway";424;2
"Unit";"Zealot";"Gateway";426;2
"Unit";"Zealot";"Gateway";428;2
"Unit";"Zealot";"Gateway";430;2
"Unit";"Zealot";"Gateway";432;2
"Building";"DarkTemplar";NA;434;0
"Unit";"Zealot";"Gateway";434;2
"Unit";"Zealot";"Gateway";436;2
"Unit";"Zealot";"Gateway";438;2
"Unit";"Zealot";"Gateway";440;2
"Unit";"Zealot";"Gateway";442;2
"Unit";"Disruptor";"Robotics Facility";444;3
"Unit";"Disruptor";"Robotics Facility";447;3
"Building";"HighTemplar";NA;450;0
"Building";"HighTemplar";NA;450;0
"Building";"HighTemplar";NA;450;0
"Building";"HighTemplar";NA;450;0
"Unit";"Archon";"High Templar";450;0
"Unit";"Archon";"High Templar";450;0
"Unit";"Stalker";"Gateway";450;2
"Unit";"Stalker";"Gateway";452;2
"Unit";"Stalker";"Gateway";454;2
"Unit";"Stalker";"Gateway";456;2
"Unit";"Stalker";"Gateway";458;2
"Unit";"Zealot";"Gateway";460;2
"Unit";"Zealot";"Gateway";462;2
"Unit";"Zealot";"Gateway";464;2
"Unit";"Zealot";"Gateway";466;2
"Unit";"Zealot";"Gateway";468;2
"Unit";"Zealot";"Gateway";470;2
"Unit";"Zealot";"Gateway";472;2
"Unit";"Zealot";"Gateway";474;2
"Unit";"Zealot";"Gateway";476;2
"Upgrade";"SprayProtoss";NA;478;0
"Upgrade";"SprayProtoss";NA;478;0
"Upgrade";"WarpGateResearch";NA;478;0
"Upgrade";"SprayProtoss";NA;478;0
"Upgrade";"SprayProtoss";NA;478;0
"Upgrade";"SprayProtoss";NA;478;0
"Upgrade";"ProtossGroundArmorsLevel1";NA;478;0
"Upgrade";"BlinkTech";NA;478;0
"Upgrade";"SprayProtoss";NA;478;0
"Upgrade";"ProtossGroundArmorsLevel2";NA;478;0
"Upgrade";"SprayProtoss";NA;478;0
"Upgrade";"ProtossGroundArmorsLevel3";NA;478;0
"Upgrade";"SprayProtoss";NA;478;0
"Upgrade";"PsiStormTech";NA;478;0
