"type";"unit_name";"on_building";"total_supply_lag";"supply"
"Building";"Refinery";NA;15;0
"Building";"Barracks";NA;16;0
"Unit";"Reaper";"Barracks";19;1
"Building";"CommandCenter";NA;20;0
"Building";"Factory";NA;20;0
"Building";"BarracksReactor";NA;21;0
"Building";"Refinery";NA;22;0
"Unit";"Hellion";"Factory";24;2
"Building";"Starport";NA;26;0
"Unit";"Marine";"Barracks";26;1
"Unit";"Marine";"Barracks";27;1
"Unit";"Marine";"Barracks";30;1
"Unit";"Marine";"Barracks";31;1
"Unit";"Marine";"Barracks";33;1
"Unit";"Marine";"Barracks";34;1
"Unit";"Marine";"Barracks";39;1
"Unit";"Marine";"Barracks";40;1
"Building";"Bunker";NA;43;0
"Building";"FactoryTechLab";NA;43;0
"Unit";"Marine";"Barracks";44;1
"Unit";"Marine";"Barracks";45;1
"Unit";"Medivac";"Starport";46;2
"Building";"Barracks";NA;51;0
"Unit";"Marine";"Barracks";51;1
"Unit";"Marine";"Barracks";52;1
"Building";"Barracks";NA;55;0
"Unit";"Liberator";"Starport";55;3
"Unit";"Marine";"Barracks";58;1
"Unit";"Marine";"Barracks";61;1
"Unit";"Marine";"Barracks";63;1
"Building";"BarracksTechLab";NA;67;0
"Unit";"Marine";"Barracks";67;1
"Unit";"Marine";"Barracks";68;1
"Building";"Refinery";NA;70;0
"Building";"StarportReactor";NA;71;0
"Building";"FactoryReactor";NA;72;0
"Unit";"Marine";"Barracks";72;1
"Unit";"Reaper";"Barracks";73;1
"Unit";"Marine";"Barracks";75;1
"Unit";"Marine";"Barracks";76;1
"Building";"Barracks";NA;79;0
"Building";"Barracks";NA;79;0
"Unit";"Marine";"Barracks";79;1
"Unit";"Marine";"Barracks";80;1
"Unit";"Marine";"Barracks";81;1
"Building";"Refinery";NA;83;0
"Unit";"Marine";"Barracks";84;1
"Unit";"Medivac";"Starport";85;2
"Unit";"Marine";"Barracks";87;1
"Unit";"Marine";"Barracks";88;1
"Unit";"Marine";"Barracks";89;1
"Upgrade";"Stimpack";"TechLab";90;0
"Building";"EngineeringBay";NA;90;0
"Building";"CommandCenter";NA;90;0
"Unit";"Medivac";"Starport";90;2
"Unit";"Marine";"Barracks";92;1
"Unit";"Marine";"Barracks";93;1
"Unit";"Marauder";"Barracks";94;2
"Unit";"Medivac";"Starport";96;2
"Building";"BarracksTechLab";NA;98;0
"Building";"BarracksReactor";NA;98;0
"Unit";"Marine";"Barracks";98;1
"Unit";"Marine";"Barracks";99;1
"Building";"MissileTurret";NA;100;0
"Unit";"Marauder";"Barracks";100;2
"Unit";"Marauder";"Barracks";102;2
"Unit";"Medivac";"Starport";104;2
"Unit";"Marine";"Barracks";108;1
"Unit";"Marine";"Barracks";109;1
"Unit";"Marauder";"Barracks";110;2
"Unit";"Medivac";"Starport";114;2
"Upgrade";"TerranInfantryWeaponsLevel1";"EngineeringBay";116;0
"Unit";"Marine";"Barracks";116;1
"Unit";"Marine";"Barracks";117;1
"Unit";"Marine";"Barracks";118;1
"Unit";"Marine";"Barracks";119;1
"Unit";"Marine";"Barracks";122;1
"Unit";"Marauder";"Barracks";123;2
"Unit";"Marauder";"Barracks";125;2
"Unit";"Marine";"Barracks";128;1
"Unit";"Marine";"Barracks";129;1
"Unit";"Marine";"Barracks";130;1
"Unit";"Marine";"Barracks";131;1
"Unit";"Marine";"Barracks";132;1
"Unit";"Marauder";"Barracks";133;2
"Unit";"Marauder";"Barracks";135;2
"Unit";"Liberator";"Starport";139;3
"Unit";"Marine";"Barracks";142;1
"Unit";"Marine";"Barracks";143;1
"Unit";"Marine";"Barracks";144;1
"Unit";"Marine";"Barracks";145;1
"Unit";"Marauder";"Barracks";146;2
"Unit";"Marauder";"Barracks";148;2
"Unit";"Marauder";"Barracks";150;2
"Unit";"Marine";"Barracks";154;1
"Unit";"Marine";"Barracks";155;1
"Unit";"Marine";"Barracks";156;1
"Unit";"Marine";"Barracks";157;1
"Unit";"Marauder";"Barracks";158;2
"Unit";"Marauder";"Barracks";160;2
"Unit";"Medivac";"Starport";162;2
"Unit";"Marauder";"Barracks";164;2
"Unit";"Medivac";"Starport";166;2
"Unit";"Marine";"Barracks";168;1
"Unit";"Marine";"Barracks";169;1
"Unit";"Marine";"Barracks";170;1
"Unit";"Marine";"Barracks";171;1
"Unit";"Marine";"Barracks";174;1
"Unit";"Marine";"Barracks";175;1
"Building";"Armory";NA;176;0
"Building";"EngineeringBay";NA;176;0
"Unit";"Marauder";"Barracks";176;2
"Unit";"Marine";"Barracks";178;1
"Unit";"Marine";"Barracks";179;1
"Unit";"Marine";"Barracks";180;1
"Unit";"Marine";"Barracks";181;1
"Unit";"Marauder";"Barracks";182;2
"Unit";"Marauder";"Barracks";184;2
"Building";"Starport";NA;186;0
"Unit";"Marauder";"Barracks";186;2
"Unit";"Marine";"Barracks";188;1
"Unit";"Marine";"Barracks";189;1
"Unit";"Marine";"Barracks";190;1
"Unit";"Marine";"Barracks";191;1
"Building";"Refinery";NA;195;0
"Building";"Refinery";NA;195;0
"Unit";"Marauder";"Barracks";195;2
"Unit";"Marauder";"Barracks";197;2
"Unit";"Marine";"Barracks";202;1
"Unit";"Marine";"Barracks";203;1
"Unit";"Marine";"Barracks";204;1
"Unit";"Marine";"Barracks";205;1
"Unit";"Marine";"Barracks";206;1
"Unit";"Marauder";"Barracks";207;2
"Unit";"Marauder";"Barracks";209;2
"Unit";"Medivac";"Starport";211;2
"Unit";"Medivac";"Starport";213;2
"Unit";"Marine";"Barracks";215;1
"Unit";"Marine";"Barracks";216;1
"Unit";"Marine";"Barracks";217;1
"Unit";"Marine";"Barracks";218;1
"Unit";"Marauder";"Barracks";219;2
"Unit";"Marauder";"Barracks";221;2
"Unit";"Marauder";"Barracks";223;2
"Upgrade";"SprayTerran";NA;225;0
"Upgrade";"SprayTerran";NA;225;0
"Upgrade";"SprayTerran";NA;225;0
"Upgrade";"ShieldWall";NA;225;0
"Upgrade";"SprayTerran";NA;225;0
"Upgrade";"PunisherGrenades";NA;225;0
"Upgrade";"SprayTerran";NA;225;0
"Upgrade";"TerranInfantryArmorsLevel1";NA;225;0
