"type";"unit_name";"on_building";"total_supply_lag";"supply"
"Building";"Refinery";NA;15;0
"Building";"Barracks";NA;16;0
"Unit";"Reaper";"Barracks";19;1
"Building";"CommandCenter";NA;20;0
"Building";"Factory";NA;21;0
"Building";"BarracksReactor";NA;21;0
"Building";"Refinery";NA;22;0
"Unit";"Marine";"Barracks";24;1
"Unit";"Marine";"Barracks";25;1
"Unit";"Cyclone";"Factory";27;3
"Unit";"Marine";"Barracks";30;1
"Unit";"Marine";"Barracks";32;1
"Building";"EngineeringBay";NA;34;0
"Unit";"Marine";"Barracks";34;1
"Unit";"Cyclone";"Factory";35;3
"Unit";"Cyclone";"Factory";38;3
"Building";"MissileTurret";NA;43;0
"Building";"MissileTurret";NA;43;0
"Unit";"Marine";"Barracks";45;1
"Unit";"Marine";"Barracks";47;1
"Building";"Barracks";NA;49;0
"Building";"Barracks";NA;49;0
"Unit";"Marine";"Barracks";49;1
"Unit";"Marine";"Barracks";50;1
"Building";"FactoryTechLab";NA;53;0
"Unit";"Marine";"Barracks";55;1
"Unit";"Marine";"Barracks";56;1
"Building";"Barracks";NA;60;0
"Building";"Refinery";NA;60;0
"Building";"Barracks";NA;60;0
"Building";"BarracksReactor";NA;60;0
"Unit";"Marine";"Barracks";60;1
"Unit";"Marine";"Barracks";61;1
"Building";"FactoryTechLab";NA;63;0
"Unit";"Marine";"Barracks";64;1
"Unit";"Marine";"Barracks";66;1
"Building";"Starport";NA;68;0
"Upgrade";"TerranInfantryWeaponsLevel1";"EngineeringBay";68;0
"Unit";"Marine";"Barracks";69;1
"Unit";"Marine";"Barracks";70;1
"Building";"BarracksReactor";NA;73;0
"Upgrade";"Stimpack";"TechLab";73;0
"Building";"BarracksTechLab";NA;73;0
"Unit";"Marine";"Barracks";75;1
"Unit";"Marine";"Barracks";76;1
"Unit";"Marine";"Barracks";79;1
"Unit";"Marine";"Barracks";80;1
"Unit";"Marine";"Barracks";82;1
"Unit";"Marine";"Barracks";83;1
"Unit";"Marauder";"Barracks";86;2
"Building";"BarracksTechLab";NA;88;0
"Unit";"Marine";"Barracks";88;1
"Unit";"Marauder";"Barracks";89;2
"Unit";"Marine";"Barracks";91;1
"Unit";"Marine";"Barracks";93;1
"Unit";"Marine";"Barracks";94;1
"Unit";"Medivac";"Starport";96;2
"Unit";"Medivac";"Starport";98;2
"Unit";"Marine";"Barracks";101;1
"Unit";"Marine";"Barracks";102;1
"Unit";"Marine";"Barracks";104;1
"Unit";"Marauder";"Barracks";105;2
"Unit";"Marauder";"Barracks";107;2
"Unit";"Marine";"Barracks";109;1
"Unit";"Medivac";"Starport";111;2
"Unit";"Medivac";"Starport";113;2
"Unit";"Marine";"Barracks";115;1
"Unit";"Marine";"Barracks";116;1
"Unit";"Marine";"Barracks";117;1
"Unit";"Marauder";"Barracks";118;2
"Unit";"Marine";"Barracks";120;1
"Unit";"Marine";"Barracks";122;1
"Unit";"Marine";"Barracks";123;1
"Unit";"Marine";"Barracks";124;1
"Unit";"Marine";"Barracks";125;1
"Unit";"Marine";"Barracks";127;1
"Unit";"Marine";"Barracks";128;1
"Unit";"Marauder";"Barracks";129;2
"Unit";"Marine";"Barracks";132;1
"Unit";"Marauder";"Barracks";133;2
"Unit";"Marine";"Barracks";136;1
"Unit";"Marine";"Barracks";137;1
"Unit";"Liberator";"Starport";138;3
"Unit";"Marine";"Barracks";141;1
"Unit";"Marine";"Barracks";142;1
"Unit";"Marine";"Barracks";143;1
"Unit";"Marauder";"Barracks";144;2
"Unit";"Marauder";"Barracks";146;2
"Unit";"Marine";"Barracks";148;1
"Unit";"Marine";"Barracks";149;1
"Unit";"Marine";"Barracks";150;1
"Unit";"Liberator";"Starport";151;3
"Unit";"Marine";"Barracks";154;1
"Unit";"Marine";"Barracks";155;1
"Unit";"Marine";"Barracks";156;1
"Unit";"Marine";"Barracks";157;1
"Unit";"Marauder";"Barracks";158;2
"Unit";"Marauder";"Barracks";160;2
"Unit";"Marine";"Barracks";162;1
"Unit";"Marine";"Barracks";163;1
"Unit";"Marine";"Barracks";164;1
"Unit";"Marine";"Barracks";165;1
"Unit";"Marauder";"Barracks";166;2
"Unit";"Marauder";"Barracks";168;2
"Unit";"Marauder";"Barracks";170;2
"Unit";"Marine";"Barracks";172;1
"Unit";"Marine";"Barracks";173;1
"Unit";"Marine";"Barracks";174;1
"Building";"CommandCenter";NA;175;0
"Unit";"Marine";"Barracks";175;1
"Unit";"Medivac";"Starport";176;2
"Unit";"Marauder";"Barracks";178;2
"Unit";"Marine";"Barracks";180;1
"Unit";"Marine";"Barracks";181;1
"Unit";"Marine";"Barracks";182;1
"Unit";"Marine";"Barracks";183;1
"Unit";"Marauder";"Barracks";184;2
"Unit";"Marine";"Barracks";186;1
"Unit";"Marine";"Barracks";187;1
"Unit";"Marine";"Barracks";188;1
"Unit";"Marauder";"Barracks";189;2
"Unit";"Marine";"Barracks";191;1
"Unit";"Marine";"Barracks";192;1
"Unit";"Medivac";"Starport";193;2
"Unit";"Medivac";"Starport";195;2
"Unit";"Marine";"Barracks";197;1
"Unit";"Marine";"Barracks";198;1
"Unit";"Marine";"Barracks";199;1
"Unit";"Marauder";"Barracks";200;2
"Unit";"Marine";"Barracks";202;1
"Unit";"Marauder";"Barracks";203;2
"Unit";"Marine";"Barracks";205;1
"Unit";"Marine";"Barracks";206;1
"Unit";"Marine";"Barracks";207;1
"Unit";"Marine";"Barracks";208;1
"Unit";"Medivac";"Starport";209;2
"Unit";"Medivac";"Starport";211;2
"Unit";"Marauder";"Barracks";213;2
"Unit";"Marine";"Barracks";215;1
"Unit";"Marine";"Barracks";216;1
"Unit";"Marine";"Barracks";217;1
"Unit";"Marine";"Barracks";218;1
"Unit";"Marauder";"Barracks";219;2
"Unit";"Marauder";"Barracks";221;2
"Unit";"Marauder";"Barracks";223;2
"Unit";"Medivac";"Starport";225;2
"Unit";"Marine";"Barracks";230;1
"Upgrade";"SprayTerran";NA;231;0
"Upgrade";"SprayTerran";NA;231;0
"Upgrade";"ShieldWall";NA;231;0
"Upgrade";"PunisherGrenades";NA;231;0
"Upgrade";"SprayTerran";NA;231;0
"Upgrade";"SprayTerran";NA;231;0
"Upgrade";"TerranInfantryArmorsLevel1";NA;231;0
"Upgrade";"SprayTerran";NA;231;0
