"type";"unit_name";"on_building";"total_supply_lag";"supply"
"Building";"Barracks";NA;16;0
"Building";"Refinery";NA;16;0
"Building";"Refinery";NA;17;0
"Unit";"Reaper";"Barracks";19;1
"Building";"Factory";NA;20;0
"Unit";"Reaper";"Barracks";21;1
"Building";"Starport";NA;25;0
"Unit";"Cyclone";"Factory";26;3
"Unit";"Liberator";"Starport";31;3
"Unit";"Cyclone";"Factory";34;3
"Building";"CommandCenter";NA;38;0
"Building";"Barracks";NA;40;0
"Building";"StarportTechLab";NA;40;0
"Unit";"Cyclone";"Factory";40;3
"Building";"Barracks";NA;44;0
"Unit";"Banshee";"Starport";45;3
"Building";"BarracksTechLab";NA;50;0
"Building";"BarracksReactor";NA;50;0
"Building";"EngineeringBay";NA;50;0
"Unit";"Banshee";"Starport";50;3
"Building";"Refinery";NA;54;0
"Unit";"Marine";"Barracks";54;1
"Unit";"Marine";"Barracks";55;1
"Building";"MissileTurret";NA;57;0
"Unit";"Marine";"Barracks";57;1
"Unit";"Marine";"Barracks";58;1
"Unit";"Marine";"Barracks";61;1
"Unit";"Marine";"Barracks";62;1
"Upgrade";"Stimpack";"TechLab";65;0
"Unit";"Marine";"Barracks";65;1
"Unit";"Marine";"Barracks";67;1
"Unit";"Banshee";"Starport";69;3
"Unit";"Marine";"Barracks";72;1
"Building";"FactoryReactor";NA;73;0
"Unit";"Marine";"Barracks";74;1
"Unit";"Marine";"Barracks";75;1
"Building";"Barracks";NA;77;0
"Upgrade";"TerranInfantryWeaponsLevel1";"EngineeringBay";77;0
"Unit";"Marine";"Barracks";77;1
"Building";"Barracks";NA;78;0
"Unit";"Marine";"Barracks";79;1
"Building";"MissileTurret";NA;80;0
"Unit";"Marine";"Barracks";81;1
"Unit";"Marine";"Barracks";82;1
"Unit";"Banshee";"Starport";86;3
"Unit";"Marine";"Barracks";89;1
"Unit";"Marine";"Barracks";90;1
"Unit";"Marine";"Barracks";91;1
"Unit";"Marine";"Barracks";92;1
"Unit";"Marine";"Barracks";96;1
"Unit";"Marine";"Barracks";97;1
"Unit";"Marine";"Barracks";98;1
"Building";"BarracksTechLab";NA;101;0
"Unit";"Marine";"Barracks";101;1
"Unit";"Marine";"Barracks";103;1
"Unit";"Marine";"Barracks";104;1
"Unit";"Marine";"Barracks";105;1
"Unit";"Banshee";"Starport";108;3
"Building";"Starport";NA;112;0
"Building";"BarracksReactor";NA;112;0
"Unit";"Marine";"Barracks";112;1
"Unit";"Marine";"Barracks";113;1
"Unit";"Marine";"Barracks";114;1
"Unit";"Marine";"Barracks";115;1
"Building";"BarracksTechLab";NA;116;0
"Unit";"Marauder";"Barracks";118;2
"Unit";"Marine";"Barracks";120;1
"Unit";"Marine";"Barracks";121;1
"Unit";"Marauder";"Barracks";122;2
"Building";"Refinery";NA;124;0
"Unit";"Marauder";"Barracks";124;2
"Unit";"Marine";"Barracks";126;1
"Unit";"Marine";"Barracks";127;1
"Unit";"Marine";"Barracks";128;1
"Unit";"Marine";"Barracks";129;1
"Unit";"Marine";"Barracks";132;1
"Unit";"Marine";"Barracks";133;1
"Unit";"Banshee";"Starport";134;3
"Unit";"Marine";"Barracks";137;1
"Building";"EngineeringBay";NA;138;0
"Building";"Armory";NA;138;0
"Unit";"Marine";"Barracks";138;1
"Unit";"Marine";"Barracks";139;1
"Unit";"Marine";"Barracks";140;1
"Unit";"Marine";"Barracks";141;1
"Unit";"Marine";"Barracks";142;1
"Unit";"Medivac";"Starport";143;2
"Unit";"Medivac";"Starport";145;2
"Unit";"Marine";"Barracks";147;1
"Unit";"Marine";"Barracks";148;1
"Building";"CommandCenter";NA;149;0
"Unit";"Marine";"Barracks";149;1
"Unit";"Marine";"Barracks";150;1
"Unit";"Marine";"Barracks";151;1
"Unit";"Marine";"Barracks";152;1
"Unit";"Marine";"Barracks";153;1
"Unit";"Marine";"Barracks";154;1
"Unit";"Marine";"Barracks";155;1
"Unit";"Marine";"Barracks";156;1
"Unit";"Marine";"Barracks";157;1
"Unit";"Marine";"Barracks";158;1
"Unit";"Marine";"Barracks";159;1
"Unit";"Medivac";"Starport";160;2
"Unit";"Marine";"Barracks";162;1
"Unit";"Marine";"Barracks";163;1
"Unit";"Marine";"Barracks";164;1
"Unit";"Marine";"Barracks";165;1
"Unit";"Marine";"Barracks";166;1
"Unit";"Marine";"Barracks";167;1
"Unit";"Marine";"Barracks";168;1
"Unit";"Medivac";"Starport";169;2
"Unit";"Marine";"Barracks";171;1
"Unit";"Marine";"Barracks";172;1
"Upgrade";"TerranInfantryWeaponsLevel2";"EngineeringBay";173;0
"Unit";"Marine";"Barracks";173;1
"Unit";"Marine";"Barracks";174;1
"Unit";"Marine";"Barracks";175;1
"Unit";"Medivac";"Starport";176;2
"Unit";"Medivac";"Starport";178;2
"Unit";"Marauder";"Barracks";180;2
"Unit";"Marine";"Barracks";182;1
"Unit";"Marine";"Barracks";183;1
"Unit";"Marine";"Barracks";184;1
"Unit";"Marauder";"Barracks";185;2
"Unit";"Marine";"Barracks";187;1
"Unit";"Marine";"Barracks";188;1
"Building";"MissileTurret";NA;191;0
"Unit";"Marauder";"Barracks";191;2
"Unit";"Marauder";"Barracks";193;2
"Unit";"Marine";"Barracks";195;1
"Unit";"Marine";"Barracks";196;1
"Unit";"Marine";"Barracks";197;1
"Unit";"Marine";"Barracks";198;1
"Unit";"Medivac";"Starport";199;2
"Unit";"Medivac";"Starport";201;2
"Unit";"Marine";"Barracks";203;1
"Unit";"Marauder";"Barracks";204;2
"Unit";"Marine";"Barracks";206;1
"Unit";"Marine";"Barracks";207;1
"Building";"GhostAcademy";NA;208;0
"Unit";"Medivac";"Starport";208;2
"Unit";"Medivac";"Starport";210;2
"Unit";"Marauder";"Barracks";212;2
"Unit";"Marauder";"Barracks";214;2
"Unit";"Marine";"Barracks";216;1
"Unit";"Marine";"Barracks";217;1
"Unit";"Marine";"Barracks";218;1
"Unit";"Marauder";"Barracks";219;2
"Unit";"Marine";"Barracks";221;1
"Unit";"Marine";"Barracks";222;1
"Unit";"Marine";"Barracks";223;1
"Unit";"Marine";"Barracks";224;1
"Unit";"Marine";"Barracks";225;1
"Unit";"Marine";"Barracks";226;1
"Unit";"Marine";"Barracks";227;1
"Unit";"Marine";"Barracks";228;1
"Unit";"Marine";"Barracks";229;1
"Unit";"Marine";"Barracks";230;1
"Unit";"Marine";"Barracks";231;1
"Unit";"Marine";"Barracks";232;1
"Unit";"Marine";"Barracks";233;1
"Upgrade";"SprayTerran";NA;234;0
"Upgrade";"SprayTerran";NA;234;0
"Upgrade";"BansheeCloak";NA;234;0
"Upgrade";"ShieldWall";NA;234;0
"Upgrade";"SprayTerran";NA;234;0
"Upgrade";"TerranInfantryArmorsLevel1";NA;234;0
"Upgrade";"SprayTerran";NA;234;0
"Upgrade";"TerranInfantryArmorsLevel2";NA;234;0
