"type";"unit_name";"on_building";"total_supply_lag";"supply"
"Unit";"Overlord";"Larva";14;0
"Building";"Hatchery";NA;17;0
"Building";"SpawningPool";NA;19;0
"Building";"Extractor";NA;19;0
"Building";"Hatchery";NA;23;0
"Unit";"Queen";"Hatchery";24;2
"Unit";"Queen";"Hatchery";26;2
"Unit";"Zergling";"Larva";28;1
"Unit";"Zergling";"Larva";29;1
"Unit";"Overlord";"Larva";30;0
"Unit";"Queen";"Hatchery";38;2
"Unit";"Overlord";"Larva";41;0
"Unit";"Overlord";"Larva";47;0
"Building";"Extractor";NA;53;0
"Building";"BanelingNest";NA;53;0
"Unit";"Zergling";"Larva";53;1
"Unit";"Zergling";"Larva";54;1
"Unit";"Zergling";"Larva";55;1
"Unit";"Zergling";"Larva";56;1
"Unit";"Zergling";"Larva";57;1
"Unit";"Zergling";"Larva";58;1
"Unit";"Overlord";"Larva";59;0
"Building";"EvolutionChamber";NA;61;0
"Building";"EvolutionChamber";NA;62;0
"Building";"CreepTumorQueen";NA;62;0
"Unit";"Queen";"Hatchery";64;2
"Unit";"Overlord";"Larva";66;0
"Unit";"Zergling";"Larva";66;1
"Unit";"Zergling";"Larva";67;1
"Unit";"Zergling";"Larva";68;1
"Unit";"Zergling";"Larva";69;1
"Unit";"Queen";"Hatchery";72;2
"Unit";"Zergling";"Larva";75;1
"Unit";"Zergling";"Larva";76;1
"Unit";"Zergling";"Larva";77;1
"Unit";"Zergling";"Larva";78;1
"Unit";"Zergling";"Larva";79;1
"Unit";"Zergling";"Larva";80;1
"Unit";"Zergling";"Larva";81;1
"Unit";"Zergling";"Larva";82;1
"Building";"CreepTumor";NA;83;0
"Unit";"Zergling";"Larva";85;1
"Unit";"Zergling";"Larva";86;1
"Unit";"Zergling";"Larva";87;1
"Unit";"Zergling";"Larva";88;1
"Unit";"Zergling";"Larva";89;1
"Unit";"Zergling";"Larva";90;1
"Unit";"Zergling";"Larva";91;1
"Unit";"Zergling";"Larva";92;1
"Unit";"Zergling";"Larva";93;1
"Unit";"Zergling";"Larva";94;1
"Unit";"Zergling";"Larva";95;1
"Unit";"Zergling";"Larva";96;1
"Building";"CreepTumorQueen";NA;97;0
"Building";"CreepTumor";NA;97;0
"Building";"CreepTumorQueen";NA;97;0
"Unit";"Queen";"Hatchery";97;2
"Unit";"Overlord";"Larva";100;0
"Unit";"Overlord";"Larva";100;0
"Building";"Extractor";NA;100;0
"Unit";"Zergling";"Larva";100;1
"Unit";"Zergling";"Larva";101;1
"Unit";"Baneling";"Zergling";102;0
"Unit";"Baneling";"Zergling";102;0
"Unit";"Baneling";"Zergling";102;0
"Unit";"Zergling";"Larva";102;1
"Unit";"Zergling";"Larva";103;1
"Unit";"Zergling";"Larva";104;1
"Unit";"Zergling";"Larva";105;1
"Unit";"Zergling";"Larva";106;1
"Unit";"Zergling";"Larva";107;1
"Unit";"Zergling";"Larva";108;1
"Unit";"Zergling";"Larva";109;1
"Unit";"Zergling";"Larva";110;1
"Unit";"Zergling";"Larva";111;1
"Unit";"Zergling";"Larva";112;1
"Unit";"Zergling";"Larva";113;1
"Unit";"Zergling";"Larva";114;1
"Unit";"Zergling";"Larva";115;1
"Unit";"Zergling";"Larva";116;1
"Unit";"Zergling";"Larva";117;1
"Unit";"Zergling";"Larva";118;1
"Unit";"Zergling";"Larva";119;1
"Unit";"Zergling";"Larva";120;1
"Unit";"Zergling";"Larva";121;1
"Unit";"Zergling";"Larva";122;1
"Unit";"Zergling";"Larva";123;1
"Unit";"Zergling";"Larva";124;1
"Unit";"Zergling";"Larva";125;1
"Unit";"Zergling";"Larva";126;1
"Unit";"Zergling";"Larva";127;1
"Unit";"Zergling";"Larva";128;1
"Unit";"Zergling";"Larva";129;1
"Unit";"Zergling";"Larva";130;1
"Unit";"Zergling";"Larva";131;1
"Unit";"Zergling";"Larva";132;1
"Unit";"Zergling";"Larva";133;1
"Unit";"Zergling";"Larva";134;1
"Unit";"Zergling";"Larva";135;1
"Unit";"Zergling";"Larva";136;1
"Unit";"Zergling";"Larva";137;1
"Unit";"Zergling";"Larva";138;1
"Unit";"Zergling";"Larva";139;1
"Building";"CreepTumor";NA;140;0
"Building";"CreepTumor";NA;140;0
"Building";"CreepTumor";NA;140;0
"Building";"CreepTumorQueen";NA;140;0
"Building";"CreepTumorQueen";NA;140;0
"Building";"Extractor";NA;142;0
"Building";"Spire";NA;142;0
"Unit";"Zergling";"Larva";142;1
"Unit";"Zergling";"Larva";143;1
"Unit";"Zergling";"Larva";144;1
"Unit";"Zergling";"Larva";145;1
"Unit";"Zergling";"Larva";146;1
"Unit";"Zergling";"Larva";147;1
"Unit";"Zergling";"Larva";148;1
"Unit";"Zergling";"Larva";149;1
"Unit";"Zergling";"Larva";150;1
"Unit";"Zergling";"Larva";151;1
"Unit";"Zergling";"Larva";152;1
"Unit";"Zergling";"Larva";153;1
"Unit";"Zergling";"Larva";154;1
"Unit";"Zergling";"Larva";155;1
"Unit";"Zergling";"Larva";156;1
"Unit";"Zergling";"Larva";157;1
"Unit";"Zergling";"Larva";158;1
"Unit";"Zergling";"Larva";159;1
"Unit";"Zergling";"Larva";160;1
"Unit";"Zergling";"Larva";161;1
"Unit";"Zergling";"Larva";162;1
"Unit";"Zergling";"Larva";163;1
"Building";"Extractor";NA;164;0
"Building";"CreepTumor";NA;164;0
"Building";"Extractor";NA;164;0
"Building";"Hatchery";NA;173;0
"Building";"CreepTumor";NA;185;0
"Building";"CreepTumor";NA;185;0
"Building";"CreepTumor";NA;185;0
"Building";"CreepTumor";NA;185;0
"Building";"CreepTumor";NA;185;0
"Unit";"Overlord";"Larva";185;0
"Unit";"Mutalisk";"Larva";185;2
"Unit";"Mutalisk";"Larva";187;2
"Unit";"Mutalisk";"Larva";189;2
"Unit";"Mutalisk";"Larva";191;2
"Unit";"Overlord";"Larva";193;0
"Unit";"Overlord";"Larva";193;0
"Unit";"Queen";"Hatchery";193;2
"Building";"CreepTumor";NA;212;0
"Building";"CreepTumor";NA;212;0
"Building";"CreepTumor";NA;212;0
"Building";"CreepTumor";NA;212;0
"Building";"CreepTumor";NA;212;0
"Unit";"Mutalisk";"Larva";212;2
"Unit";"Mutalisk";"Larva";214;2
"Unit";"Mutalisk";"Larva";216;2
"Unit";"Mutalisk";"Larva";218;2
"Building";"Hatchery";NA;220;0
"Building";"CreepTumorQueen";NA;223;0
"Unit";"Overlord";"Larva";223;0
"Unit";"Queen";"Hatchery";223;2
"Unit";"Overlord";"Larva";225;0
"Unit";"Overlord";"Larva";225;0
"Building";"CreepTumor";NA;234;0
"Building";"InfestationPit";NA;234;0
"Building";"CreepTumorQueen";NA;234;0
"Building";"CreepTumor";NA;234;0
"Building";"CreepTumor";NA;234;0
"Building";"CreepTumor";NA;234;0
"Building";"Hatchery";NA;234;0
"Building";"CreepTumor";NA;234;0
"Unit";"Overlord";"Larva";234;0
"Unit";"Overlord";"Larva";234;0
"Unit";"Overlord";"Larva";234;0
"Unit";"Overlord";"Larva";234;0
"Building";"CreepTumorQueen";NA;243;0
"Building";"CreepTumor";NA;243;0
"Unit";"Mutalisk";"Larva";243;2
"Unit";"Mutalisk";"Larva";245;2
"Unit";"Mutalisk";"Larva";247;2
"Unit";"Mutalisk";"Larva";249;2
"Unit";"Mutalisk";"Larva";251;2
"Unit";"Mutalisk";"Larva";253;2
"Unit";"Mutalisk";"Larva";255;2
"Unit";"Mutalisk";"Larva";257;2
"Unit";"Overlord";"Larva";259;0
"Unit";"Overlord";"Larva";259;0
"Unit";"Zergling";"Larva";259;1
"Unit";"Zergling";"Larva";260;1
"Building";"Extractor";NA;261;0
"Unit";"Zergling";"Larva";261;1
"Unit";"Zergling";"Larva";262;1
"Unit";"Zergling";"Larva";263;1
"Unit";"Zergling";"Larva";264;1
"Unit";"Zergling";"Larva";265;1
"Unit";"Zergling";"Larva";266;1
"Unit";"Zergling";"Larva";267;1
"Unit";"Zergling";"Larva";268;1
"Unit";"Zergling";"Larva";269;1
"Unit";"Zergling";"Larva";270;1
"Unit";"Zergling";"Larva";271;1
"Unit";"Zergling";"Larva";272;1
"Unit";"Zergling";"Larva";273;1
"Unit";"Zergling";"Larva";274;1
"Unit";"Zergling";"Larva";275;1
"Unit";"Zergling";"Larva";276;1
"Unit";"Zergling";"Larva";277;1
"Unit";"Zergling";"Larva";278;1
"Unit";"Zergling";"Larva";279;1
"Unit";"Zergling";"Larva";280;1
"Building";"Extractor";NA;281;0
"Unit";"Zergling";"Larva";281;1
"Unit";"Zergling";"Larva";282;1
"Unit";"Zergling";"Larva";283;1
"Unit";"Zergling";"Larva";284;1
"Unit";"Queen";"Hatchery";285;2
"Building";"CreepTumor";NA;287;0
"Unit";"Baneling";"Zergling";287;0
"Unit";"Baneling";"Zergling";287;0
"Unit";"Baneling";"Zergling";287;0
"Unit";"Baneling";"Zergling";287;0
"Unit";"Baneling";"Zergling";287;0
"Unit";"Baneling";"Zergling";287;0
"Unit";"Baneling";"Zergling";287;0
"Unit";"Baneling";"Zergling";287;0
"Unit";"Baneling";"Zergling";287;0
"Unit";"Baneling";"Zergling";287;0
"Unit";"Baneling";"Zergling";287;0
"Unit";"Baneling";"Zergling";287;0
"Unit";"Baneling";"Zergling";287;0
"Unit";"Baneling";"Zergling";287;0
"Unit";"Baneling";"Zergling";287;0
"Unit";"Baneling";"Zergling";287;0
"Unit";"Baneling";"Zergling";287;0
"Unit";"Zergling";"Larva";287;1
"Unit";"Zergling";"Larva";288;1
"Unit";"Zergling";"Larva";289;1
"Unit";"Zergling";"Larva";290;1
"Unit";"Zergling";"Larva";291;1
"Unit";"Zergling";"Larva";292;1
"Unit";"Zergling";"Larva";293;1
"Unit";"Zergling";"Larva";294;1
"Unit";"Zergling";"Larva";295;1
"Unit";"Zergling";"Larva";296;1
"Unit";"Zergling";"Larva";297;1
"Unit";"Zergling";"Larva";298;1
"Unit";"Zergling";"Larva";299;1
"Unit";"Zergling";"Larva";300;1
"Unit";"Zergling";"Larva";301;1
"Unit";"Zergling";"Larva";302;1
"Unit";"Zergling";"Larva";303;1
"Unit";"Zergling";"Larva";304;1
"Unit";"Zergling";"Larva";305;1
"Unit";"Zergling";"Larva";306;1
"Unit";"Zergling";"Larva";307;1
"Unit";"Zergling";"Larva";308;1
"Unit";"Zergling";"Larva";309;1
"Unit";"Zergling";"Larva";310;1
"Unit";"Zergling";"Larva";311;1
"Unit";"Zergling";"Larva";312;1
"Unit";"Zergling";"Larva";313;1
"Unit";"Zergling";"Larva";314;1
"Unit";"Zergling";"Larva";315;1
"Unit";"Zergling";"Larva";316;1
"Unit";"Zergling";"Larva";317;1
"Unit";"Zergling";"Larva";318;1
"Unit";"Zergling";"Larva";319;1
"Unit";"Zergling";"Larva";320;1
"Unit";"Zergling";"Larva";321;1
"Unit";"Zergling";"Larva";322;1
"Unit";"Zergling";"Larva";323;1
"Unit";"Zergling";"Larva";324;1
"Unit";"Zergling";"Larva";325;1
"Unit";"Zergling";"Larva";326;1
"Unit";"Zergling";"Larva";327;1
"Unit";"Zergling";"Larva";328;1
"Unit";"Zergling";"Larva";329;1
"Unit";"Zergling";"Larva";330;1
"Unit";"Zergling";"Larva";331;1
"Unit";"Zergling";"Larva";332;1
"Unit";"Zergling";"Larva";333;1
"Unit";"Zergling";"Larva";334;1
"Unit";"Zergling";"Larva";335;1
"Unit";"Zergling";"Larva";336;1
"Unit";"Zergling";"Larva";337;1
"Unit";"Zergling";"Larva";338;1
"Unit";"Zergling";"Larva";339;1
"Unit";"Zergling";"Larva";340;1
"Unit";"Zergling";"Larva";341;1
"Unit";"Zergling";"Larva";342;1
"Unit";"Zergling";"Larva";343;1
"Unit";"Zergling";"Larva";344;1
"Unit";"Zergling";"Larva";345;1
"Unit";"Zergling";"Larva";346;1
"Unit";"Baneling";"Zergling";347;0
"Unit";"Baneling";"Zergling";347;0
"Unit";"Baneling";"Zergling";347;0
"Unit";"Baneling";"Zergling";347;0
"Upgrade";"SprayZerg";NA;347;0
"Upgrade";"SprayZerg";NA;347;0
"Upgrade";"SprayZerg";NA;347;0
"Upgrade";"SprayZerg";NA;347;0
"Upgrade";"zerglingmovementspeed";NA;347;0
"Upgrade";"ZergMeleeWeaponsLevel1";NA;347;0
"Upgrade";"ZergGroundArmorsLevel1";NA;347;0
"Upgrade";"SprayZerg";NA;347;0
"Upgrade";"CentrificalHooks";NA;347;0
"Upgrade";"SprayZerg";NA;347;0
"Upgrade";"overlordspeed";NA;347;0
"Upgrade";"SprayZerg";NA;347;0
"Upgrade";"ZergGroundArmorsLevel2";NA;347;0
"Upgrade";"SprayZerg";NA;347;0
"Upgrade";"SprayZerg";NA;347;0
"Upgrade";"ZergMeleeWeaponsLevel2";NA;347;0
"Upgrade";"ZergFlyerWeaponsLevel1";NA;347;0
"Upgrade";"SprayZerg";NA;347;0
