"Type";"UnitName";"OnBuilding";"TotalSupply";"Supply"
"Unit";"SCV";"Command Center";12;1
"Unit";"SCV";"Command Center";12;1
"Unit";"SCV";"Command Center";13;1
"Building";"SupplyDepot";NA;13;0
"Unit";"SCV";"Command Center";15;1
"Unit";"SCV";"Command Center";15;1
"Building";"Refinery";NA;15;0
"Unit";"SCV";"Command Center";16;1
"Building";"Barracks";NA;15;0
"Unit";"SCV";"Command Center";17;1
"Unit";"Reaper";"Barracks";19;1
"Unit";"SCV";"Command Center";19;1
"Unit";"SCV";"Command Center";20;1
"Building";"SupplyDepot";NA;21;0
"Unit";"SCV";"Command Center";21;1
"Building";"BarracksReactor";NA;20;0
"Unit";"SCV";"Command Center";22;1
"Building";"CommandCenter";NA;19;0
"Unit";"SCV";"Command Center";23;1
"Unit";"Marine";"Barracks";23;1
"Unit";"Marine";"Barracks";23;1
"Building";"Factory";NA;22;0
"Unit";"SCV";"Command Center";24;1
"Building";"Refinery";NA;24;0
"Building";"Bunker";NA;24;0
"Unit";"Marine";"Barracks";25;1
"Unit";"Marine";"Barracks";26;1
"Unit";"SCV";"Command Center";28;1
"Unit";"SCV";"Command Center";30;1
"Unit";"SCV";"Command Center";31;1
"Unit";"Marine";"Barracks";30;1
"Unit";"Marine";"Barracks";30;1
"Unit";"Cyclone";"Factory";28;3
"Unit";"SCV";"Command Center";31;1
"Unit";"SCV";"Command Center";32;1
"Unit";"SCV";"Command Center";38;1
"Building";"SupplyDepot";NA;35;0
"Unit";"SCV";"Command Center";40;1
"Building";"Starport";NA;31;0
"Building";"EngineeringBay";NA;38;0
"Building";"SupplyDepot";NA;38;0
"Unit";"SCV";"Command Center";40;1
"Unit";"Marine";"Barracks";40;1
"Unit";"Marine";"Barracks";40;1
"Building";"FactoryTechLab";NA;40;0
"Unit";"SCV";"Command Center";42;1
"Building";"SupplyDepot";NA;42;0
"Unit";"SCV";"Command Center";46;1
"Building";"SupplyDepot";NA;43;0
"Unit";"Liberator";"Starport";42;3
"Unit";"SCV";"Command Center";47;1
"Unit";"Marine";"Barracks";47;1
"Unit";"SCV";"Command Center";47;1
"Unit";"SCV";"Command Center";50;1
"Unit";"SCV";"Command Center";52;1
"Unit";"SCV";"Command Center";54;1
"Building";"Bunker";NA;51;0
"Unit";"Marine";"Barracks";54;1
"Unit";"Marine";"Barracks";54;1
"Unit";"SCV";"Command Center";55;1
"Unit";"SCV";"Command Center";57;1
"Building";"Barracks";NA;50;0
"Unit";"Marine";"Barracks";56;1
"Unit";"SCV";"Command Center";59;1
"Building";"SupplyDepot";NA;56;0
"Building";"Barracks";NA;53;0
"Building";"MissileTurret";NA;59;0
"Unit";"SCV";"Command Center";59;1
"Building";"CommandCenter";NA;47;0
"Unit";"SCV";"Command Center";61;1
"Building";"BarracksTechLab";NA;60;0
"Building";"Refinery";NA;60;0
"Unit";"SCV";"Command Center";62;1
"Building";"BarracksTechLab";NA;62;0
"Unit";"SCV";"Command Center";63;1
"Unit";"Marine";"Barracks";63;1
"Unit";"Marine";"Barracks";63;1
"Building";"MissileTurret";NA;63;0
"Upgrade";"TerranInfantryWeaponsLevel1";"EngineeringBay";50;0
"Unit";"SCV";"Command Center";64;1
"Unit";"SCV";"Command Center";65;1
"Unit";"SCV";"Command Center";68;1
"Building";"Refinery";NA;66;0
"Unit";"SCV";"Command Center";69;1
"Unit";"Marine";"Barracks";69;1
"Unit";"Marine";"Barracks";69;1
"Unit";"Marauder";"Barracks";68;2
"Unit";"Marauder";"Barracks";68;2
"Unit";"SCV";"Command Center";78;1
"Unit";"Marine";"Barracks";72;1
"Unit";"SCV";"Command Center";78;1
"Building";"StarportReactor";NA;69;0
"Unit";"Marine";"Barracks";78;1
"Unit";"Marine";"Barracks";78;1
"Unit";"Marauder";"Barracks";78;2
"Unit";"SCV";"Command Center";81;1
"Unit";"SCV";"Command Center";81;1
"Unit";"Marine";"Barracks";83;1
"Unit";"SCV";"Command Center";86;1
"Unit";"SCV";"Command Center";86;1
"Unit";"Marauder";"Barracks";85;2
"Building";"Barracks";NA;78;0
"Building";"Barracks";NA;78;0
"Building";"SupplyDepot";NA;87;0
"Building";"Armory";NA;78;0
"Unit";"Marine";"Barracks";90;1
"Building";"EngineeringBay";NA;87;0
"Building";"SupplyDepot";NA;87;0
"Unit";"Marine";"Barracks";92;1
"Building";"SupplyDepot";NA;90;0
"Building";"MissileTurret";NA;92;0
"Unit";"Marauder";"Barracks";92;2
"Building";"MissileTurret";NA;92;0
"Unit";"Marine";"Barracks";92;1
"Unit";"Marine";"Barracks";92;1
"Upgrade";"Stimpack";"TechLab";78;0
"Building";"BarracksReactor";NA;92;0
"Building";"BarracksReactor";NA;92;0
"Unit";"Medivac";"Starport";93;2
"Unit";"Medivac";"Starport";93;2
"Unit";"Marine";"Barracks";98;1
"Unit";"Marauder";"Barracks";98;2
"Unit";"Marine";"Barracks";98;1
"Unit";"Marine";"Barracks";98;1
"Unit";"Marine";"Barracks";102;1
"Unit";"Marine";"Barracks";102;1
"Unit";"Marauder";"Barracks";102;2
"Unit";"SCV";"Command Center";105;1
"Unit";"SCV";"Command Center";105;1
"Unit";"SCV";"Command Center";105;1
"Upgrade";"TerranInfantryArmorsLevel1";"EngineeringBay";87;0
"Unit";"Marine";"Barracks";105;1
"Unit";"Marine";"Barracks";105;1
"Unit";"Marauder";"Barracks";105;2
"Building";"GhostAcademy";NA;102;0
"Unit";"SCV";"Command Center";111;1
"Unit";"SCV";"Command Center";116;1
"Unit";"SCV";"Command Center";116;1
"Unit";"Marauder";"Barracks";109;2
"Building";"SupplyDepot";NA;111;0
"Unit";"SCV";"Command Center";121;1
"Unit";"SCV";"Command Center";121;1
"Building";"SupplyDepot";NA;118;0
"Building";"SupplyDepot";NA;123;0
"Building";"SupplyDepot";NA;123;0
"Unit";"SCV";"Command Center";125;1
"Unit";"SCV";"Command Center";125;1
"Unit";"Medivac";"Starport";123;2
"Unit";"Medivac";"Starport";123;2
"Building";"MissileTurret";NA;125;0
"Building";"Refinery";NA;125;0
"Building";"MissileTurret";NA;125;0
"Unit";"SCV";"Command Center";125;1
"Unit";"Marine";"Barracks";125;1
"Unit";"Marine";"Barracks";125;1
"Unit";"Marine";"Barracks";125;1
"Unit";"Marine";"Barracks";125;1
"Building";"Refinery";NA;125;0
"Building";"SupplyDepot";NA;125;0
"Unit";"SCV";"Command Center";131;1
"Unit";"SCV";"Command Center";131;1
"Unit";"SCV";"Command Center";136;1
"Building";"SupplyDepot";NA;129;0
"Building";"Barracks";NA;123;0
"Unit";"SCV";"Command Center";136;1
"Unit";"Marine";"Barracks";136;1
"Unit";"Marine";"Barracks";136;1
"Building";"SensorTower";NA;138;0
"Unit";"SCV";"Command Center";139;1
"Unit";"SCV";"Command Center";139;1
"Upgrade";"TerranInfantryWeaponsLevel2";"EngineeringBay";106;0
"Building";"Starport";NA;131;0
"Building";"BarracksTechLab";NA;140;0
"Building";"MissileTurret";NA;144;0
"Upgrade";"TerranVehicleWeaponsLevel1";"Armory";125;0
"Unit";"Marine";"Barracks";144;1
"Unit";"Marine";"Barracks";144;1
"Unit";"Marine";"Barracks";144;1
"Unit";"Marine";"Barracks";144;1
"Unit";"Marine";"Barracks";144;1
"Unit";"Marine";"Barracks";144;1
"Unit";"Marine";"Barracks";144;1
"Unit";"Marine";"Barracks";144;1
"Building";"StarportReactor";NA;144;0
"Building";"SupplyDepot";NA;144;0
"Building";"Starport";NA;144;0
"Unit";"Marine";"Barracks";144;1
"Building";"SupplyDepot";NA;144;0
"Upgrade";"TerranInfantryArmorsLevel2";"EngineeringBay";125;0
"Unit";"Marine";"Barracks";144;1
"Building";"SupplyDepot";NA;152;0
"Building";"CommandCenter";NA;141;0
"Building";"SupplyDepot";NA;153;0
"Unit";"Marine";"Barracks";154;1
"Unit";"Marine";"Barracks";154;1
"Unit";"Marine";"Barracks";154;1
"Unit";"Marine";"Barracks";154;1
"Unit";"Marine";"Barracks";154;1
"Unit";"Marine";"Barracks";154;1
"Unit";"SCV";"Command Center";160;1
"Unit";"SCV";"Command Center";160;1
"Unit";"SCV";"Command Center";160;1
"Unit";"Marine";"Barracks";160;1
"Unit";"Marine";"Barracks";160;1
"Unit";"Marine";"Barracks";160;1
"Unit";"Marine";"Barracks";160;1
"Unit";"Marine";"Barracks";160;1
"Unit";"Marauder";"Barracks";160;2
"Unit";"Marauder";"Barracks";160;2
"Unit";"Marauder";"Barracks";160;2
"Unit";"Marine";"Barracks";167;1
"Unit";"Marine";"Barracks";167;1
"Unit";"Marine";"Barracks";167;1
"Unit";"Marine";"Barracks";168;1
"Unit";"Marauder";"Barracks";168;2
"Unit";"Marauder";"Barracks";170;2
"Unit";"Marauder";"Barracks";172;2
"Unit";"SCV";"Command Center";174;1
"Unit";"SCV";"Command Center";174;1
"Unit";"SCV";"Command Center";174;1
"Unit";"Marine";"Barracks";184;1
"Unit";"Liberator";"Starport";174;3
"Unit";"SCV";"Command Center";188;1
"Unit";"SCV";"Command Center";188;1
"Upgrade";"TerranInfantryWeaponsLevel3";"EngineeringBay";154;0
"Unit";"Marine";"Barracks";188;1
"Unit";"Marine";"Barracks";188;1
"Unit";"Marine";"Barracks";188;1
"Unit";"Marine";"Barracks";188;1
"Unit";"Marine";"Barracks";188;1
"Unit";"Marauder";"Barracks";188;2
"Unit";"Marauder";"Barracks";188;2
"Unit";"Marauder";"Barracks";188;2
"Unit";"SCV";"Command Center";191;1
"Unit";"SCV";"Command Center";191;1
"Unit";"Marauder";"Barracks";198;2
"Unit";"Marauder";"Barracks";200;2
"Unit";"Medivac";"Starport";193;2
"Unit";"Medivac";"Starport";193;2
"Unit";"Marine";"Barracks";206;1
"Building";"MissileTurret";NA;206;0
"Building";"SensorTower";NA;210;0
"Building";"Refinery";NA;215;0
"Unit";"Marine";"Barracks";215;1
"Unit";"Marine";"Barracks";215;1
"Unit";"Marine";"Barracks";215;1
"Unit";"Marine";"Barracks";215;1
"Unit";"Marine";"Barracks";215;1
"Unit";"Marine";"Barracks";215;1
"Unit";"Marine";"Barracks";215;1
"Unit";"SCV";"Command Center";215;1
"Unit";"SCV";"Command Center";215;1
"Unit";"SCV";"Command Center";215;1
"Unit";"Marine";"Barracks";215;1
"Unit";"Marine";"Barracks";215;1
"Unit";"Marine";"Barracks";221;1
"Unit";"Marine";"Barracks";221;1
"Unit";"Marine";"Barracks";221;1
"Building";"Refinery";NA;215;0
"Building";"Refinery";NA;221;0
"Building";"SupplyDepot";NA;222;0
"Unit";"Marine";"Barracks";226;1
"Unit";"Marauder";"Barracks";225;2
"Unit";"Marine";"Barracks";230;1
"Unit";"Marauder";"Barracks";230;2
"Unit";"SCV";"Command Center";231;1
"Unit";"Liberator";"Starport";230;3
"Upgrade";"TerranShipWeaponsLevel1";"Armory";215;0
"Unit";"Marine";"Barracks";237;1
"Unit";"Marine";"Barracks";237;1
"Unit";"Marine";"Barracks";237;1
"Building";"MissileTurret";NA;237;0
"Unit";"Marine";"Barracks";243;1
"Unit";"Marine";"Barracks";243;1
"Unit";"Marine";"Barracks";243;1
"Unit";"Marine";"Barracks";243;1
"Unit";"Marine";"Barracks";243;1
"Unit";"Marauder";"Barracks";243;2
"Unit";"Marine";"Barracks";243;1
"Unit";"Marauder";"Barracks";243;2
"Unit";"Marine";"Barracks";253;1
"Unit";"Marine";"Barracks";253;1
"Unit";"SCV";"Command Center";253;1
"Unit";"Marine";"Barracks";253;1
"Unit";"SCV";"Command Center";253;1
"Unit";"Marine";"Barracks";253;1
"Unit";"Marine";"Barracks";253;1
"Unit";"Marauder";"Barracks";253;2
"Unit";"Marauder";"Barracks";253;2
"Unit";"Marauder";"Barracks";253;2
"Unit";"SCV";"Command Center";255;1
"Unit";"SCV";"Command Center";257;1
"Upgrade";"TerranInfantryArmorsLevel3";"EngineeringBay";237;0
"Unit";"SCV";"Command Center";266;1
"Unit";"Marauder";"Barracks";260;2
"Unit";"Marauder";"Barracks";262;2
"Unit";"Marine";"Barracks";268;1
"Unit";"Marine";"Barracks";268;1
"Unit";"Marine";"Barracks";268;1
"Unit";"Marine";"Barracks";268;1
"Unit";"Marine";"Barracks";268;1
"Unit";"Marine";"Barracks";268;1
"Unit";"Liberator";"Starport";253;3
"Unit";"Marauder";"Barracks";268;2
"Unit";"Marauder";"Barracks";269;2
"Unit";"Marauder";"Barracks";271;2
"Unit";"Marine";"Barracks";273;1
"Unit";"Marine";"Barracks";274;1
"Unit";"Marine";"Barracks";275;1
"Unit";"Marine";"Barracks";276;1
"Unit";"Marine";"Barracks";277;1
"Unit";"Marauder";"Barracks";282;2
"Unit";"Marine";"Barracks";284;1
"Unit";"Marauder";"Barracks";284;2
"Unit";"Marauder";"Barracks";286;2
"Unit";"Marine";"Barracks";288;1
"Unit";"Marine";"Barracks";293;1
"Unit";"Marine";"Barracks";293;1
"Unit";"Marine";"Barracks";293;1
"Unit";"Marine";"Barracks";293;1
"Unit";"SCV";"Command Center";296;1
"Unit";"SCV";"Command Center";296;1
"Unit";"Medivac";"Starport";284;2
"Unit";"Marine";"Barracks";293;1
"Unit";"Marine";"Barracks";295;1
"Unit";"Marine";"Barracks";296;1
"Unit";"Marine";"Barracks";298;1
"Unit";"Marine";"Barracks";303;1
"Unit";"Marine";"Barracks";303;1
"Unit";"Marine";"Barracks";309;1
"Unit";"Marine";"Barracks";310;1
"Unit";"Marauder";"Barracks";309;2
"Unit";"Marine";"Barracks";313;1
"Unit";"Marine";"Barracks";313;1
"Unit";"Marine";"Barracks";313;1
"Unit";"Marauder";"Barracks";311;2
"Unit";"Marine";"Barracks";317;1
"Unit";"Marine";"Barracks";319;1
"Unit";"Marine";"Barracks";325;1
"Building";"MissileTurret";NA;326;0
"Building";"MissileTurret";NA;326;0
"Building";"MissileTurret";NA;326;0
"Unit";"Marine";"Barracks";326;1
"Unit";"Marine";"Barracks";326;1
"Unit";"Marine";"Barracks";326;1
