"type";"unit_name";"on_building";"total_supply";"supply"
"Building";"Refinery";NA;15;0
"Building";"Barracks";NA;15;0
"Unit";"Reaper";"Barracks";19;1
"Unit";"Marine";"Barracks";19;1
"Building";"Bunker";NA;21;0
"Building";"CommandCenter";NA;19;0
"Building";"BarracksReactor";NA;23;0
"Building";"Factory";NA;21;0
"Building";"Bunker";NA;23;0
"Building";"Refinery";NA;24;0
"Unit";"Marine";"Barracks";25;1
"Unit";"Marine";"Barracks";25;1
"Unit";"Marine";"Barracks";28;1
"Unit";"Marine";"Barracks";28;1
"Building";"Bunker";NA;26;0
"Unit";"Cyclone";"Factory";28;3
"Unit";"Marine";"Barracks";30;1
"Unit";"Marine";"Barracks";31;1
"Building";"FactoryTechLab";NA;36;0
"Unit";"Marine";"Barracks";40;1
"Unit";"Marine";"Barracks";41;1
"Building";"Starport";NA;37;0
"Unit";"Marine";"Barracks";45;1
"Unit";"Marine";"Barracks";45;1
"Unit";"Marine";"Barracks";51;1
"Unit";"Marine";"Barracks";51;1
"Building";"Bunker";NA;51;0
"Unit";"Marine";"Barracks";55;1
"Unit";"Marine";"Barracks";55;1
"Building";"Bunker";NA;59;0
"Building";"Bunker";NA;59;0
"Unit";"Marine";"Barracks";61;1
"Unit";"Marine";"Barracks";61;1
"Unit";"Marine";"Barracks";65;1
"Unit";"Marine";"Barracks";65;1
"Building";"EngineeringBay";NA;63;0
"Unit";"Marine";"Barracks";70;1
"Unit";"Marine";"Barracks";70;1
"Unit";"Marine";"Barracks";75;1
"Unit";"Marine";"Barracks";75;1
"Building";"Refinery";NA;76;0
"Building";"Refinery";NA;76;0
"Building";"Barracks";NA;75;0
"Building";"Barracks";NA;76;0
"Unit";"Marine";"Barracks";84;1
"Unit";"Marine";"Barracks";86;1
"Building";"BarracksReactor";NA;84;0
"Building";"BarracksReactor";NA;84;0
"Building";"StarportReactor";NA;87;0
"Unit";"Marine";"Barracks";91;1
"Unit";"Marine";"Barracks";92;1
"Unit";"Marine";"Barracks";92;1
"Unit";"Marine";"Barracks";92;1
"Unit";"Marine";"Barracks";92;1
"Building";"Barracks";NA;87;0
"Building";"Barracks";NA;87;0
"Upgrade";"TerranInfantryWeaponsLevel1";"EngineeringBay";82;0
"Building";"CommandCenter";NA;84;0
"Unit";"Marine";"Barracks";99;1
"Unit";"Marine";"Barracks";99;1
"Unit";"Marine";"Barracks";99;1
"Unit";"Marine";"Barracks";99;1
"Building";"BarracksTechLab";NA;99;0
"Building";"BarracksTechLab";NA;99;0
"Unit";"Medivac";"Starport";93;2
"Unit";"Medivac";"Starport";94;2
"Unit";"Marine";"Barracks";101;1
"Unit";"Marine";"Barracks";101;1
"Unit";"Marine";"Barracks";102;1
"Unit";"Marine";"Barracks";105;1
"Unit";"Marauder";"Barracks";105;2
"Unit";"Marauder";"Barracks";105;2
"Upgrade";"Stimpack";"TechLab";89;0
"Unit";"Medivac";"Starport";105;2
"Unit";"Medivac";"Starport";107;2
"Unit";"Marine";"Barracks";112;1
"Unit";"Marine";"Barracks";112;1
"Unit";"Marine";"Barracks";113;1
"Unit";"Marine";"Barracks";113;1
"Building";"Refinery";NA;129;0
"Building";"Refinery";NA;129;0
"Building";"Armory";NA;119;0
"Unit";"Marine";"Barracks";129;1
"Unit";"Marine";"Barracks";129;1
"Unit";"Marine";"Barracks";129;1
"Unit";"Marine";"Barracks";129;1
"Unit";"Marauder";"Barracks";129;2
"Unit";"Marauder";"Barracks";129;2
"Unit";"Marauder";"Barracks";129;2
