"Type";"UnitName";"OnBuilding";"TotalSupply";"Supply"
"Unit";"SCV";"Command Center";12;1
"Unit";"SCV";"Command Center";12;1
"Unit";"SCV";"Command Center";13;1
"Building";"SupplyDepot";NA;13;0
"Unit";"SCV";"Command Center";15;1
"Unit";"SCV";"Command Center";15;1
"Building";"Refinery";NA;15;0
"Unit";"SCV";"Command Center";16;1
"Unit";"SCV";"Command Center";17;1
"Building";"Barracks";NA;15;0
"Unit";"Reaper";"Barracks";19;1
"Unit";"SCV";"Command Center";19;1
"Building";"SupplyDepot";NA;19;0
"Unit";"Marine";"Barracks";19;1
"Unit";"SCV";"Command Center";21;1
"Unit";"SCV";"Command Center";23;1
"Building";"Bunker";NA;21;0
"Building";"Refinery";NA;23;0
"Unit";"SCV";"Command Center";23;1
"Building";"CommandCenter";NA;19;0
"Unit";"SCV";"Command Center";24;1
"Building";"Factory";NA;22;0
"Building";"BarracksReactor";NA;23;0
"Unit";"SCV";"Command Center";25;1
"Building";"EngineeringBay";NA;25;0
"Unit";"Marine";"Barracks";26;1
"Unit";"Marine";"Barracks";26;1
"Unit";"SCV";"Command Center";26;1
"Unit";"SCV";"Command Center";27;1
"Unit";"SCV";"Command Center";29;1
"Unit";"Marine";"Barracks";30;1
"Unit";"Marine";"Barracks";30;1
"Unit";"SCV";"Command Center";30;1
"Building";"Starport";NA;27;0
"Unit";"SCV";"Command Center";32;1
"Unit";"SCV";"Command Center";34;1
"Unit";"Marine";"Barracks";35;1
"Unit";"SCV";"Command Center";37;1
"Unit";"SCV";"Command Center";37;1
"Unit";"Marine";"Barracks";37;1
"Building";"SupplyDepot";NA;36;0
"Building";"MissileTurret";NA;37;0
"Unit";"Marine";"Barracks";37;1
"Unit";"Medivac";"Starport";37;2
"Unit";"SCV";"Command Center";41;1
"Unit";"SCV";"Command Center";41;1
"Unit";"Marine";"Barracks";41;1
"Building";"SupplyDepot";NA;40;0
"Building";"SupplyDepot";NA;41;0
"Unit";"Marine";"Barracks";41;1
"Unit";"SCV";"Command Center";44;1
"Unit";"SCV";"Command Center";45;1
"Building";"FactoryTechLab";NA;42;0
"Unit";"SCV";"Command Center";48;1
"Unit";"SCV";"Command Center";49;1
"Building";"StarportTechLab";NA;47;0
"Building";"SupplyDepot";NA;47;0
"Unit";"Marine";"Barracks";48;1
"Unit";"Marine";"Barracks";48;1
"Unit";"SCV";"Command Center";50;1
"Unit";"SCV";"Command Center";52;1
"Building";"SupplyDepot";NA;52;0
"Unit";"SCV";"Command Center";54;1
"Unit";"SCV";"Command Center";55;1
"Unit";"Marine";"Barracks";54;1
"Building";"MissileTurret";NA;56;0
"Building";"Barracks";NA;50;0
"Building";"Refinery";NA;56;0
"Unit";"SCV";"Command Center";59;1
"Unit";"SCV";"Command Center";59;1
"Unit";"Raven";"Starport";54;2
"Unit";"SCV";"Command Center";60;1
"Building";"SupplyDepot";NA;59;0
"Building";"SupplyDepot";NA;59;0
"Unit";"Marine";"Barracks";59;1
"Unit";"Marine";"Barracks";59;1
"Unit";"Marine";"Barracks";59;1
"Building";"SupplyDepot";NA;59;0
"Unit";"SCV";"Command Center";60;1
"Building";"SupplyDepot";NA;60;0
"Building";"SupplyDepot";NA;60;0
"Unit";"SCV";"Command Center";68;1
"Unit";"Marine";"Barracks";68;1
"Unit";"Marine";"Barracks";68;1
"Building";"Refinery";NA;68;0
"Unit";"Marine";"Barracks";71;1
"Unit";"Marine";"Barracks";71;1
"Unit";"Marine";"Barracks";71;1
"Unit";"SCV";"Command Center";71;1
"Unit";"SCV";"Command Center";71;1
"Unit";"SCV";"Command Center";74;1
"Unit";"SCV";"Command Center";76;1
"Building";"Barracks";NA;68;0
"Unit";"Marine";"Barracks";76;1
"Building";"SupplyDepot";NA;75;0
"Unit";"Marine";"Barracks";76;1
"Building";"SupplyDepot";NA;76;0
"Building";"FactoryReactor";NA;71;0
"Unit";"SCV";"Command Center";78;1
"Unit";"Marine";"Barracks";78;1
"Unit";"Marine";"Barracks";79;1
"Building";"Barracks";NA;71;0
"Unit";"Marauder";"Barracks";78;2
"Building";"StarportReactor";NA;76;0
"Building";"Barracks";NA;74;0
"Building";"SupplyDepot";NA;81;0
"Building";"SupplyDepot";NA;81;0
"Building";"BarracksReactor";NA;80;0
"Building";"MissileTurret";NA;85;0
"Building";"MissileTurret";NA;85;0
"Unit";"Marine";"Barracks";85;1
"Unit";"Marine";"Barracks";85;1
"Unit";"Marine";"Barracks";85;1
"Unit";"Marine";"Barracks";85;1
"Unit";"Medivac";"Starport";85;2
"Unit";"Marine";"Barracks";85;1
"Unit";"Medivac";"Starport";85;2
"Unit";"Marine";"Barracks";85;1
"Upgrade";"TerranInfantryWeaponsLevel1";"EngineeringBay";76;0
"Unit";"Marine";"Barracks";85;1
"Upgrade";"Stimpack";"TechLab";76;0
"Building";"BarracksReactor";NA;85;0
"Unit";"Marine";"Barracks";86;1
"Unit";"Marine";"Barracks";88;1
"Unit";"Marauder";"Barracks";87;2
"Unit";"Marine";"Barracks";91;1
"Unit";"Marine";"Barracks";95;1
"Unit";"Marauder";"Barracks";97;2
"Unit";"Medivac";"Starport";95;2
"Unit";"Medivac";"Starport";95;2
"Unit";"Marauder";"Barracks";98;2
"Building";"CommandCenter";NA;85;0
"Unit";"Marine";"Barracks";102;1
"Unit";"Marine";"Barracks";110;1
"Unit";"Marauder";"Barracks";102;2
"Unit";"Marine";"Barracks";110;1
"Unit";"Marauder";"Barracks";108;2
"Unit";"Marine";"Barracks";111;1
"Unit";"Marine";"Barracks";111;1
"Unit";"Marine";"Barracks";111;1
"Unit";"Marine";"Barracks";111;1
"Unit";"Medivac";"Starport";111;2
"Unit";"Medivac";"Starport";111;2
"Unit";"Marauder";"Barracks";111;2
"Unit";"Marine";"Barracks";117;1
"Unit";"Marauder";"Barracks";115;2
"Unit";"Marine";"Barracks";120;1
"Unit";"Marine";"Barracks";120;1
"Unit";"SCV";"Command Center";127;1
"Building";"MissileTurret";NA;125;0
"Unit";"Marauder";"Barracks";125;2
"Unit";"Marauder";"Barracks";128;2
"Unit";"Marine";"Barracks";133;1
"Unit";"Marine";"Barracks";133;1
"Unit";"Marine";"Barracks";133;1
