"Type";"UnitName";"OnBuilding";"TotalSupply";"Supply"
"Unit";"SCV";"Command Center";12;1
"Unit";"SCV";"Command Center";12;1
"Unit";"SCV";"Command Center";13;1
"Building";"SupplyDepot";NA;13;0
"Unit";"SCV";"Command Center";15;1
"Building";"Refinery";NA;14;0
"Unit";"SCV";"Command Center";15;1
"Unit";"SCV";"Command Center";16;1
"Unit";"SCV";"Command Center";17;1
"Building";"Barracks";NA;15;0
"Unit";"Reaper";"Barracks";19;1
"Unit";"SCV";"Command Center";19;1
"Unit";"SCV";"Command Center";21;1
"Building";"SupplyDepot";NA;21;0
"Unit";"SCV";"Command Center";21;1
"Building";"Factory";NA;19;0
"Building";"Refinery";NA;21;0
"Building";"BarracksReactor";NA;20;0
"Unit";"SCV";"Command Center";22;1
"Building";"CommandCenter";NA;19;0
"Unit";"SCV";"Command Center";24;1
"Unit";"SCV";"Command Center";24;1
"Unit";"Cyclone";"Factory";25;3
"Unit";"SCV";"Command Center";26;1
"Unit";"SCV";"Command Center";29;1
"Building";"Barracks";NA;25;0
"Building";"Barracks";NA;25;0
"Unit";"SCV";"Command Center";31;1
"Building";"BarracksReactor";NA;26;0
"Unit";"SCV";"Command Center";31;1
"Building";"FactoryTechLab";NA;31;0
"Building";"BarracksTechLab";NA;31;0
"Unit";"Marine";"Barracks";32;1
"Unit";"Marine";"Barracks";32;1
"Unit";"Marine";"Barracks";32;1
"Unit";"Marine";"Barracks";32;1
"Unit";"SCV";"Command Center";33;1
"Unit";"Marine";"Barracks";33;1
"Unit";"Marine";"Barracks";33;1
"Unit";"Marine";"Barracks";37;1
"Unit";"Marine";"Barracks";37;1
"Unit";"Marine";"Barracks";37;1
"Unit";"SCV";"Command Center";39;1
"Unit";"Marine";"Barracks";39;1
"Building";"Starport";NA;33;0
"Unit";"Marine";"Barracks";39;1
"Unit";"SCV";"Command Center";44;1
"Unit";"Marine";"Barracks";44;1
"Unit";"Marine";"Barracks";44;1
"Unit";"Marine";"Barracks";44;1
"Building";"Bunker";NA;43;0
"Building";"SupplyDepot";NA;46;0
"Building";"SupplyDepot";NA;47;0
"Unit";"SCV";"Command Center";50;1
"Unit";"SCV";"Command Center";50;1
"Unit";"Marine";"Barracks";50;1
"Unit";"Marine";"Barracks";50;1
"Unit";"Marine";"Barracks";50;1
"Unit";"Marine";"Barracks";50;1
"Building";"StarportReactor";NA;46;0
"Unit";"SCV";"Command Center";50;1
"Unit";"SCV";"Command Center";50;1
"Unit";"Marine";"Barracks";52;1
"Building";"SupplyDepot";NA;52;0
"Unit";"SCV";"Command Center";56;1
"Unit";"Marine";"Barracks";58;1
"Unit";"SCV";"Command Center";58;1
"Unit";"Marine";"Barracks";60;1
"Building";"SupplyDepot";NA;60;0
"Unit";"Medivac";"Starport";58;2
"Unit";"SCV";"Command Center";62;1
"Unit";"Marine";"Barracks";62;1
"Upgrade";"Stimpack";"TechLab";44;0
"Unit";"Marine";"Barracks";62;1
"Unit";"Marine";"Barracks";62;1
"Unit";"Medivac";"Starport";60;2
"Unit";"Marine";"Barracks";62;1
"Unit";"Marine";"Barracks";62;1
"Building";"EngineeringBay";NA;66;0
"Unit";"SCV";"Command Center";73;1
"Unit";"SCV";"Command Center";73;1
"Unit";"Marine";"Barracks";72;1
"Unit";"Marine";"Barracks";72;1
"Unit";"Marine";"Barracks";72;1
"Unit";"Marine";"Barracks";73;1
"Unit";"SCV";"Command Center";79;1
"Unit";"Marine";"Barracks";79;1
"Unit";"Marine";"Barracks";79;1
"Unit";"Marine";"Barracks";79;1
"Unit";"Marine";"Barracks";79;1
"Unit";"Marine";"Barracks";79;1
"Unit";"SCV";"Command Center";79;1
"Unit";"SCV";"Command Center";79;1
"Unit";"Medivac";"Starport";79;2
"Unit";"Medivac";"Starport";79;2
"Unit";"Marine";"Barracks";80;1
"Unit";"Marine";"Barracks";86;1
"Building";"CommandCenter";NA;78;0
"Unit";"SCV";"Command Center";92;1
"Unit";"SCV";"Command Center";92;1
"Unit";"Marine";"Barracks";92;1
"Unit";"Marine";"Barracks";92;1
"Unit";"Marine";"Barracks";92;1
"Unit";"SCV";"Command Center";93;1
"Unit";"SCV";"Command Center";94;1
"Unit";"Marine";"Barracks";93;1
"Unit";"Marine";"Barracks";93;1
"Building";"Refinery";NA;93;0
"Building";"Refinery";NA;93;0
"Unit";"Marine";"Barracks";98;1
"Unit";"Marine";"Barracks";98;1
"Unit";"SCV";"Command Center";102;1
"Unit";"Marine";"Barracks";102;1
"Building";"Barracks";NA;92;0
"Unit";"Marine";"Barracks";102;1
"Unit";"Medivac";"Starport";98;2
"Unit";"SCV";"Command Center";104;1
"Building";"Barracks";NA;93;0
"Unit";"Marine";"Barracks";104;1
"Unit";"Marine";"Barracks";104;1
"Unit";"SCV";"Command Center";104;1
"Unit";"Marine";"Barracks";105;1
"Unit";"Marine";"Barracks";107;1
"Upgrade";"TerranInfantryWeaponsLevel1";"EngineeringBay";93;0
"Building";"BarracksReactor";NA;107;0
"Unit";"SCV";"Command Center";115;1
"Unit";"SCV";"Command Center";115;1
"Building";"BarracksReactor";NA;110;0
"Building";"SupplyDepot";NA;115;0
"Unit";"Marine";"Barracks";115;1
"Unit";"Marine";"Barracks";115;1
"Unit";"SCV";"Command Center";115;1
"Building";"SupplyDepot";NA;115;0
"Building";"SupplyDepot";NA;115;0
"Building";"SupplyDepot";NA;115;0
"Building";"Factory";NA;110;0
"Unit";"SCV";"Command Center";117;1
"Unit";"Marine";"Barracks";117;1
"Building";"FactoryTechLab";NA;120;0
"Unit";"Marine";"Barracks";122;1
"Unit";"Marine";"Barracks";122;1
"Unit";"Marine";"Barracks";122;1
"Unit";"Marine";"Barracks";122;1
"Unit";"Marine";"Barracks";122;1
"Unit";"Marine";"Barracks";122;1
"Unit";"Marine";"Barracks";128;1
"Unit";"Marine";"Barracks";128;1
"Unit";"SCV";"Command Center";128;1
"Unit";"SCV";"Command Center";128;1
"Unit";"Marine";"Barracks";128;1
"Unit";"Marine";"Barracks";128;1
"Unit";"Marine";"Barracks";128;1
"Unit";"Marine";"Barracks";128;1
"Unit";"Marine";"Barracks";128;1
"Unit";"Marine";"Barracks";128;1
"Unit";"Marine";"Barracks";128;1
"Unit";"SCV";"Command Center";130;1
"Unit";"SCV";"Command Center";130;1
"Unit";"SCV";"Command Center";131;1
"Unit";"SCV";"Command Center";139;1
"Unit";"Marine";"Barracks";137;1
"Unit";"Marine";"Barracks";137;1
"Unit";"Marine";"Barracks";137;1
"Unit";"Marine";"Barracks";137;1
"Unit";"Marine";"Barracks";137;1
"Unit";"Marine";"Barracks";137;1
"Building";"SensorTower";NA;137;0
"Unit";"Marine";"Barracks";137;1
"Unit";"Marine";"Barracks";137;1
"Unit";"Marine";"Barracks";142;1
"Upgrade";"TerranInfantryArmorsLevel1";"EngineeringBay";122;0
"Building";"Refinery";NA;142;0
"Building";"Refinery";NA;142;0
"Unit";"Marine";"Barracks";143;1
"Unit";"Marine";"Barracks";144;1
"Building";"Factory";NA;137;0
"Unit";"Liberator";"Starport";137;3
"Unit";"Liberator";"Starport";137;3
"Building";"SupplyDepot";NA;152;0
"Unit";"Marine";"Barracks";154;1
"Unit";"Marine";"Barracks";154;1
"Unit";"Marine";"Barracks";154;1
"Unit";"Marine";"Barracks";154;1
"Unit";"Marine";"Barracks";154;1
"Unit";"Marine";"Barracks";154;1
"Unit";"Marine";"Barracks";154;1
"Unit";"Marine";"Barracks";154;1
"Unit";"Marine";"Barracks";160;1
"Building";"FactoryTechLab";NA;160;0
"Unit";"Marine";"Barracks";160;1
"Unit";"Marine";"Barracks";161;1
"Unit";"Marine";"Barracks";165;1
"Unit";"Marine";"Barracks";165;1
"Unit";"Marine";"Barracks";166;1
"Unit";"Marine";"Barracks";167;1
"Building";"Armory";NA;152;0
"Unit";"Marine";"Barracks";169;1
"Unit";"Marine";"Barracks";169;1
"Unit";"Marine";"Barracks";169;1
"Unit";"Marine";"Barracks";169;1
"Unit";"Marine";"Barracks";179;1
"Unit";"Marine";"Barracks";179;1
"Unit";"Marine";"Barracks";179;1
"Unit";"Marine";"Barracks";179;1
"Unit";"Marine";"Barracks";179;1
"Unit";"Marine";"Barracks";179;1
"Unit";"Marine";"Barracks";179;1
"Unit";"Marine";"Barracks";179;1
"Unit";"Medivac";"Starport";179;2
"Unit";"Medivac";"Starport";179;2
"Unit";"Marine";"Barracks";179;1
"Unit";"Marine";"Barracks";179;1
"Unit";"Marine";"Barracks";180;1
"Unit";"SCV";"Command Center";187;1
"Unit";"SCV";"Command Center";187;1
"Unit";"Marine";"Barracks";183;1
"Unit";"Marine";"Barracks";183;1
"Unit";"SCV";"Command Center";187;1
"Unit";"Marine";"Barracks";183;1
"Building";"CommandCenter";NA;175;0
"Unit";"Marine";"Barracks";199;1
"Unit";"Marine";"Barracks";199;1
"Unit";"Marine";"Barracks";199;1
"Unit";"Marine";"Barracks";199;1
"Unit";"Marine";"Barracks";199;1
"Unit";"Marine";"Barracks";199;1
"Unit";"Marine";"Barracks";200;1
"Unit";"Medivac";"Starport";187;2
"Unit";"Medivac";"Starport";189;2
