"Type";"UnitName";"OnBuilding";"TotalSupply";"Supply"
"Unit";"SCV";"Command Center";12;1
"Unit";"SCV";"Command Center";12;1
"Unit";"SCV";"Command Center";13;1
"Building";"SupplyDepot";NA;13;0
"Building";"Refinery";NA;14;0
"Unit";"SCV";"Command Center";15;1
"Unit";"SCV";"Command Center";15;1
"Unit";"SCV";"Command Center";16;1
"Unit";"SCV";"Command Center";17;1
"Building";"Barracks";NA;15;0
"Unit";"Reaper";"Barracks";19;1
"Unit";"SCV";"Command Center";19;1
"Unit";"SCV";"Command Center";21;1
"Unit";"SCV";"Command Center";21;1
"Building";"SupplyDepot";NA;21;0
"Building";"BarracksReactor";NA;20;0
"Building";"Factory";NA;19;0
"Unit";"SCV";"Command Center";23;1
"Building";"CommandCenter";NA;19;0
"Unit";"SCV";"Command Center";23;1
"Building";"BarracksTechLab";NA;24;0
"Unit";"SCV";"Command Center";24;1
"Unit";"Hellion";"Factory";24;2
"Unit";"Hellion";"Factory";24;2
"Unit";"SCV";"Command Center";25;1
"Unit";"Marine";"Barracks";26;1
"Unit";"SCV";"Command Center";31;1
"Unit";"Hellion";"Factory";30;2
"Unit";"Hellion";"Factory";30;2
"Unit";"SCV";"Command Center";32;1
"Unit";"SCV";"Command Center";33;1
"Unit";"SCV";"Command Center";38;1
"Unit";"SCV";"Command Center";39;1
"Building";"Barracks";NA;30;0
"Unit";"SCV";"Command Center";39;1
"Building";"Barracks";NA;31;0
"Unit";"SCV";"Command Center";40;1
"Unit";"Marine";"Barracks";40;1
"Unit";"SCV";"Command Center";41;1
"Unit";"SCV";"Command Center";43;1
"Building";"Refinery";NA;42;0
"Unit";"Marine";"Barracks";43;1
"Unit";"Marine";"Barracks";45;1
"Building";"EngineeringBay";NA;42;0
"Unit";"Marine";"Barracks";45;1
"Building";"Refinery";NA;43;0
"Building";"FactoryReactor";NA;41;0
"Unit";"SCV";"Command Center";46;1
"Unit";"SCV";"Command Center";46;1
"Building";"BarracksReactor";NA;42;0
"Building";"Starport";NA;44;0
"Unit";"Marine";"Barracks";49;1
"Unit";"Marine";"Barracks";49;1
"Building";"SupplyDepot";NA;51;0
"Building";"SupplyDepot";NA;51;0
"Building";"FactoryTechLab";NA;51;0
"Building";"SupplyDepot";NA;51;0
"Unit";"SCV";"Command Center";53;1
"Upgrade";"Stimpack";"TechLab";39;0
"Unit";"SCV";"Command Center";53;1
"Unit";"Marine";"Barracks";53;1
"Unit";"Marine";"Barracks";53;1
"Unit";"Marine";"Barracks";53;1
"Unit";"Marine";"Barracks";53;1
"Unit";"SCV";"Command Center";53;1
"Unit";"SCV";"Command Center";54;1
"Unit";"SCV";"Command Center";59;1
"Unit";"SCV";"Command Center";60;1
"Unit";"Marine";"Barracks";60;1
"Unit";"Marine";"Barracks";60;1
"Unit";"Marine";"Barracks";60;1
"Unit";"Marine";"Barracks";60;1
"Unit";"Marine";"Barracks";61;1
"Unit";"SCV";"Command Center";61;1
"Unit";"SCV";"Command Center";62;1
"Building";"SupplyDepot";NA;61;0
"Building";"SupplyDepot";NA;62;0
"Building";"SupplyDepot";NA;62;0
"Unit";"SCV";"Command Center";68;1
"Unit";"Marine";"Barracks";68;1
"Unit";"Marine";"Barracks";68;1
"Unit";"Marine";"Barracks";68;1
"Unit";"Medivac";"Starport";62;2
"Unit";"Medivac";"Starport";62;2
"Unit";"SCV";"Command Center";71;1
"Unit";"Marine";"Barracks";70;1
"Unit";"Marine";"Barracks";70;1
"Unit";"SCV";"Command Center";74;1
"Unit";"Marine";"Barracks";78;1
"Unit";"Marine";"Barracks";78;1
"Unit";"Marine";"Barracks";78;1
"Building";"SupplyDepot";NA;74;0
"Unit";"Marine";"Barracks";81;1
"Unit";"Marine";"Barracks";81;1
"Building";"SupplyDepot";NA;82;0
"Building";"Refinery";NA;82;0
"Unit";"Marine";"Barracks";82;1
"Unit";"Marine";"Barracks";83;1
"Building";"Barracks";NA;74;0
"Unit";"Marine";"Barracks";87;1
"Unit";"Marine";"Barracks";87;1
"Unit";"Liberator";"Starport";81;3
"Unit";"Marine";"Barracks";87;1
"Upgrade";"TerranInfantryWeaponsLevel1";"EngineeringBay";63;0
"Unit";"Marine";"Barracks";89;1
"Unit";"Marauder";"Barracks";94;2
"Unit";"SCV";"Command Center";95;1
"Unit";"SCV";"Command Center";95;1
"Unit";"Marine";"Barracks";95;1
"Unit";"Marine";"Barracks";95;1
"Building";"CommandCenter";NA;78;0
"Unit";"Marine";"Barracks";95;1
"Building";"BarracksTechLab";NA;95;0
"Unit";"SCV";"Command Center";98;1
"Unit";"SCV";"Command Center";99;1
"Building";"SupplyDepot";NA;96;0
"Building";"SupplyDepot";NA;96;0
"Building";"EngineeringBay";NA;96;0
"Building";"Barracks";NA;91;0
"Unit";"Marine";"Barracks";103;1
"Unit";"Marine";"Barracks";103;1
"Unit";"Marine";"Barracks";103;1
"Unit";"Marauder";"Barracks";103;2
"Unit";"Marauder";"Barracks";103;2
"Unit";"Marine";"Barracks";105;1
"Building";"Armory";NA;96;0
"Unit";"Marine";"Barracks";105;1
"Unit";"Marine";"Barracks";112;1
"Unit";"Marine";"Barracks";112;1
"Unit";"Marauder";"Barracks";108;2
"Building";"BarracksTechLab";NA;112;0
"Unit";"Marine";"Barracks";118;1
"Unit";"Liberator";"Starport";108;3
"Unit";"Marine";"Barracks";118;1
"Unit";"Marine";"Barracks";118;1
"Unit";"Marine";"Barracks";118;1
"Unit";"SCV";"Command Center";118;1
"Unit";"SCV";"Command Center";118;1
"Unit";"Marauder";"Barracks";118;2
"Unit";"Marauder";"Barracks";118;2
"Unit";"Marauder";"Barracks";118;2
"Unit";"SCV";"Command Center";122;1
"Unit";"SCV";"Command Center";125;1
"Unit";"SCV";"Command Center";127;1
"Unit";"SCV";"Command Center";133;1
"Unit";"SCV";"Command Center";135;1
"Unit";"SCV";"Command Center";135;1
"Unit";"Marine";"Barracks";133;1
"Unit";"Marine";"Barracks";133;1
"Unit";"Marine";"Barracks";133;1
"Unit";"Marine";"Barracks";133;1
"Unit";"Marauder";"Barracks";133;2
"Unit";"Marauder";"Barracks";133;2
"Unit";"Marauder";"Barracks";133;2
"Upgrade";"TerranInfantryArmorsLevel1";"EngineeringBay";105;0
"Building";"Refinery";NA;134;0
"Building";"Refinery";NA;134;0
"Unit";"SCV";"Command Center";136;1
"Unit";"SCV";"Command Center";150;1
"Unit";"Marine";"Barracks";149;1
"Unit";"SCV";"Command Center";150;1
"Unit";"SCV";"Command Center";150;1
"Unit";"Marine";"Barracks";149;1
"Unit";"Marine";"Barracks";149;1
"Unit";"Marine";"Barracks";149;1
"Unit";"Marine";"Barracks";149;1
"Unit";"Marine";"Barracks";149;1
"Unit";"Marine";"Barracks";149;1
"Unit";"Liberator";"Starport";133;3
"Unit";"Liberator";"Starport";133;3
"Building";"SupplyDepot";NA;150;0
"Building";"SupplyDepot";NA;150;0
"Building";"SupplyDepot";NA;150;0
"Unit";"Marine";"Barracks";151;1
"Unit";"Marine";"Barracks";154;1
"Unit";"Marine";"Barracks";154;1
"Unit";"Marine";"Barracks";166;1
"Unit";"Marine";"Barracks";166;1
"Unit";"Marine";"Barracks";166;1
"Unit";"Marine";"Barracks";166;1
"Unit";"Marine";"Barracks";169;1
"Unit";"Marine";"Barracks";169;1
"Unit";"Marine";"Barracks";169;1
"Building";"SupplyDepot";NA;169;0
"Building";"SupplyDepot";NA;169;0
"Building";"SupplyDepot";NA;169;0
"Building";"SupplyDepot";NA;169;0
"Unit";"Marine";"Barracks";169;1
"Unit";"Marine";"Barracks";170;1
"Unit";"Marauder";"Barracks";170;2
"Unit";"Liberator";"Starport";166;3
"Unit";"Liberator";"Starport";166;3
"Unit";"Marine";"Barracks";176;1
"Unit";"Marauder";"Barracks";176;2
"Unit";"Marauder";"Barracks";177;2
"Unit";"Marine";"Barracks";186;1
"Unit";"Marine";"Barracks";186;1
"Unit";"Marauder";"Barracks";186;2
"Unit";"Marauder";"Barracks";187;2
"Unit";"Marine";"Barracks";191;1
"Unit";"Marine";"Barracks";191;1
"Unit";"Marine";"Barracks";192;1
"Unit";"Marine";"Barracks";193;1
"Unit";"Marine";"Barracks";193;1
"Unit";"Medivac";"Starport";187;2
"Unit";"Medivac";"Starport";187;2
"Upgrade";"TerranInfantryWeaponsLevel2";"EngineeringBay";166;0
"Unit";"Marine";"Barracks";197;1
"Unit";"Marauder";"Barracks";197;2
"Unit";"Marine";"Barracks";197;1
"Unit";"Marine";"Barracks";198;1
"Unit";"Marine";"Barracks";199;1
"Unit";"Marine";"Barracks";200;1
"Unit";"Marauder";"Barracks";201;2
"Unit";"Marauder";"Barracks";206;2
"Unit";"Marine";"Barracks";209;1
"Unit";"Marine";"Barracks";210;1
"Unit";"Marine";"Barracks";211;1
"Unit";"Marine";"Barracks";212;1
"Unit";"Marauder";"Barracks";207;2
"Upgrade";"TerranInfantryArmorsLevel2";"EngineeringBay";173;0
"Upgrade";"TerranShipWeaponsLevel1";"Armory";178;0
"Unit";"Marauder";"Barracks";213;2
"Unit";"Liberator";"Starport";206;3
"Unit";"Liberator";"Starport";206;3
"Unit";"Marine";"Barracks";223;1
"Unit";"Marine";"Barracks";223;1
"Unit";"Marine";"Barracks";223;1
"Unit";"Marine";"Barracks";223;1
"Unit";"Marauder";"Barracks";223;2
"Unit";"Marauder";"Barracks";223;2
"Building";"CommandCenter";NA;195;0
"Unit";"Marauder";"Barracks";223;2
"Building";"SupplyDepot";NA;225;0
"Building";"Barracks";NA;215;0
"Building";"Barracks";NA;215;0
"Building";"Barracks";NA;215;0
"Unit";"Marauder";"Barracks";235;2
"Unit";"Medivac";"Starport";234;2
"Unit";"Medivac";"Starport";234;2
"Unit";"Marine";"Barracks";241;1
"Unit";"Marine";"Barracks";241;1
"Unit";"Marine";"Barracks";241;1
"Unit";"Marine";"Barracks";241;1
"Unit";"Marauder";"Barracks";241;2
"Unit";"Marauder";"Barracks";241;2
"Building";"BarracksTechLab";NA;241;0
"Building";"BarracksTechLab";NA;241;0
"Building";"BarracksTechLab";NA;241;0
"Building";"Starport";NA;239;0
"Building";"SupplyDepot";NA;241;0
"Building";"SensorTower";NA;243;0
"Unit";"Marauder";"Barracks";241;2
"Building";"FusionCore";NA;241;0
"Unit";"Marine";"Barracks";255;1
"Unit";"Marine";"Barracks";255;1
"Unit";"Marine";"Barracks";255;1
"Unit";"Marine";"Barracks";255;1
"Unit";"Marine";"Barracks";255;1
"Unit";"Marine";"Barracks";255;1
"Building";"Refinery";NA;255;0
"Building";"StarportTechLab";NA;255;0
"Building";"Refinery";NA;255;0
"Unit";"Marauder";"Barracks";257;2
"Unit";"Marauder";"Barracks";257;2
"Unit";"Marauder";"Barracks";257;2
"Unit";"Marauder";"Barracks";257;2
"Building";"MissileTurret";NA;263;0
"Unit";"Liberator";"Starport";255;3
"Unit";"Marauder";"Barracks";263;2
"Unit";"Marine";"Barracks";274;1
"Unit";"Marauder";"Barracks";271;2
"Unit";"Marauder";"Barracks";274;2
"Unit";"Marauder";"Barracks";274;2
"Unit";"Marauder";"Barracks";274;2
"Unit";"Liberator";"Starport";263;3
"Upgrade";"TerranShipWeaponsLevel2";"Armory";243;0
"Building";"SensorTower";NA;285;0
"Upgrade";"TerranInfantryWeaponsLevel3";"EngineeringBay";241;0
"Upgrade";"TerranInfantryArmorsLevel3";"EngineeringBay";251;0
"Unit";"Liberator";"Starport";285;3
"Unit";"Marine";"Barracks";288;1
"Unit";"Marine";"Barracks";288;1
"Unit";"Marine";"Barracks";288;1
"Unit";"Marauder";"Barracks";288;2
"Unit";"Marauder";"Barracks";288;2
"Unit";"Marine";"Barracks";291;1
"Unit";"Marauder";"Barracks";291;2
"Unit";"Marine";"Barracks";291;1
"Unit";"Marauder";"Barracks";291;2
"Unit";"Marine";"Barracks";298;1
"Unit";"Marine";"Barracks";298;1
"Unit";"Marauder";"Barracks";298;2
"Unit";"Marauder";"Barracks";298;2
"Unit";"Marauder";"Barracks";304;2
"Unit";"Marauder";"Barracks";304;2
