"type";"unit_name";"on_building";"total_supply_lag";"supply"
"Building";"Refinery";NA;15;0
"Building";"Barracks";NA;16;0
"Unit";"Reaper";"Barracks";19;1
"Building";"CommandCenter";NA;20;0
"Building";"Factory";NA;20;0
"Building";"BarracksReactor";NA;21;0
"Building";"Refinery";NA;22;0
"Unit";"Marine";"Barracks";24;1
"Unit";"Marine";"Barracks";25;1
"Building";"Starport";NA;26;0
"Unit";"Marine";"Barracks";28;1
"Unit";"Marine";"Barracks";29;1
"Unit";"Medivac";"Starport";33;2
"Unit";"Marine";"Barracks";35;1
"Unit";"Marine";"Barracks";36;1
"Unit";"Marine";"Barracks";39;1
"Unit";"Marine";"Barracks";40;1
"Building";"Barracks";NA;41;0
"Unit";"Liberator";"Starport";41;3
"Building";"FactoryTechLab";NA;44;0
"Building";"Barracks";NA;46;0
"Building";"BarracksTechLab";NA;46;0
"Building";"EngineeringBay";NA;46;0
"Unit";"Marine";"Barracks";49;1
"Building";"Refinery";NA;50;0
"Building";"StarportReactor";NA;51;0
"Building";"Barracks";NA;52;0
"Building";"Barracks";NA;53;0
"Building";"Refinery";NA;53;0
"Unit";"Marine";"Barracks";54;1
"Unit";"Marine";"Barracks";55;1
"Upgrade";"Stimpack";"TechLab";56;0
"Building";"FactoryReactor";NA;57;0
"Unit";"Marauder";"Barracks";57;2
"Unit";"Marine";"Barracks";61;1
"Unit";"Marine";"Barracks";62;1
"Upgrade";"TerranInfantryWeaponsLevel1";"EngineeringBay";64;0
"Unit";"Medivac";"Starport";64;2
"Unit";"Medivac";"Starport";66;2
"Building";"BarracksReactor";NA;69;0
"Building";"BarracksTechLab";NA;70;0
"Unit";"Marine";"Barracks";70;1
"Unit";"Marine";"Barracks";71;1
"Unit";"Marauder";"Barracks";72;2
"Unit";"Marauder";"Barracks";74;2
"Unit";"Marauder";"Barracks";77;2
"Unit";"Marine";"Barracks";79;1
"Unit";"Marine";"Barracks";80;1
"Unit";"Marauder";"Barracks";81;2
"Unit";"Marauder";"Barracks";83;2
"Unit";"Marine";"Barracks";87;1
"Unit";"Marine";"Barracks";88;1
"Unit";"Marauder";"Barracks";89;2
"Unit";"Marine";"Barracks";91;1
"Unit";"Marine";"Barracks";92;1
"Unit";"Marauder";"Barracks";93;2
"Unit";"Medivac";"Starport";95;2
"Unit";"Medivac";"Starport";97;2
"Unit";"Marauder";"Barracks";99;2
"Unit";"Marine";"Barracks";101;1
"Unit";"Marine";"Barracks";102;1
"Unit";"Marine";"Barracks";103;1
"Unit";"Marine";"Barracks";104;1
"Unit";"Marine";"Barracks";105;1
"Unit";"Marauder";"Barracks";106;2
"Unit";"Marauder";"Barracks";108;2
"Unit";"Marauder";"Barracks";110;2
"Building";"CommandCenter";NA;112;0
"Unit";"Liberator";"Starport";112;3
"Unit";"Liberator";"Starport";115;3
"Unit";"Marine";"Barracks";118;1
"Unit";"Marine";"Barracks";119;1
"Unit";"Marauder";"Barracks";120;2
"Unit";"Marauder";"Barracks";122;2
"Unit";"Marauder";"Barracks";124;2
"Unit";"Marine";"Barracks";126;1
"Unit";"Marine";"Barracks";127;1
"Unit";"Marauder";"Barracks";128;2
"Unit";"Marauder";"Barracks";130;2
"Unit";"Marine";"Barracks";132;1
"Unit";"Marine";"Barracks";133;1
"Unit";"Marauder";"Barracks";134;2
"Unit";"Marine";"Barracks";136;1
"Unit";"Medivac";"Starport";137;2
"Unit";"Medivac";"Starport";139;2
"Unit";"Marine";"Barracks";141;1
"Unit";"Marine";"Barracks";142;1
"Unit";"Marauder";"Barracks";143;2
"Unit";"Marauder";"Barracks";145;2
"Unit";"Marauder";"Barracks";147;2
"Building";"Armory";NA;149;0
"Building";"EngineeringBay";NA;149;0
"Unit";"Marauder";"Barracks";149;2
"Unit";"Marine";"Barracks";151;1
"Unit";"Marine";"Barracks";152;1
"Unit";"Marine";"Barracks";153;1
"Unit";"Marine";"Barracks";154;1
"Unit";"Medivac";"Starport";155;2
"Unit";"Medivac";"Starport";157;2
"Unit";"Marine";"Barracks";161;1
"Unit";"Marine";"Barracks";162;1
"Unit";"Marauder";"Barracks";165;2
"Unit";"Marauder";"Barracks";167;2
"Unit";"Marauder";"Barracks";169;2
"Unit";"Marine";"Barracks";171;1
"Unit";"Marine";"Barracks";172;1
"Unit";"Marine";"Barracks";173;1
"Unit";"Marine";"Barracks";174;1
"Unit";"Marauder";"Barracks";175;2
"Unit";"Marine";"Barracks";177;1
"Unit";"Marine";"Barracks";178;1
"Unit";"Marine";"Barracks";179;1
"Building";"Starport";NA;180;0
"Building";"Refinery";NA;180;0
"Building";"FusionCore";NA;180;0
"Unit";"Marine";"Barracks";180;1
"Unit";"Marine";"Barracks";181;1
"Unit";"Marauder";"Barracks";182;2
"Upgrade";"TerranInfantryWeaponsLevel2";"EngineeringBay";184;0
"Unit";"Marauder";"Barracks";184;2
"Unit";"Liberator";"Starport";186;3
"Unit";"Liberator";"Starport";189;3
"Unit";"Marauder";"Barracks";192;2
"Unit";"Marauder";"Barracks";194;2
"Unit";"Marine";"Barracks";196;1
"Unit";"Marine";"Barracks";197;1
"Building";"StarportTechLab";NA;198;0
"Building";"MissileTurret";NA;198;0
"Unit";"Marauder";"Barracks";198;2
"Unit";"Marine";"Barracks";200;1
"Unit";"Marine";"Barracks";201;1
"Unit";"Marine";"Barracks";202;1
"Unit";"Marine";"Barracks";203;1
"Unit";"Liberator";"Starport";204;3
"Unit";"Liberator";"Starport";207;3
"Unit";"Marauder";"Barracks";210;2
"Unit";"Marauder";"Barracks";212;2
"Unit";"Marauder";"Barracks";214;2
"Unit";"Marine";"Barracks";218;1
"Unit";"Marine";"Barracks";219;1
"Unit";"Marine";"Barracks";220;1
"Unit";"Marauder";"Barracks";221;2
"Unit";"Marauder";"Barracks";223;2
"Unit";"Marauder";"Barracks";225;2
"Unit";"Marine";"Barracks";227;1
"Unit";"Marine";"Barracks";228;1
"Unit";"Marine";"Barracks";229;1
"Unit";"Marine";"Barracks";230;1
"Unit";"Marauder";"Barracks";231;2
"Unit";"Liberator";"Starport";233;3
"Unit";"Liberator";"Starport";236;3
"Unit";"Liberator";"Starport";239;3
"Unit";"Marauder";"Barracks";242;2
"Unit";"Marauder";"Barracks";244;2
"Unit";"Marine";"Barracks";246;1
"Unit";"Marine";"Barracks";247;1
"Unit";"Marauder";"Barracks";248;2
"Building";"CommandCenter";NA;250;0
"Unit";"Medivac";"Starport";250;2
"Building";"Refinery";NA;252;0
"Unit";"Medivac";"Starport";252;2
"Unit";"Marine";"Barracks";254;1
"Unit";"Marine";"Barracks";255;1
"Unit";"Marine";"Barracks";256;1
"Unit";"Marine";"Barracks";257;1
"Upgrade";"TerranShipWeaponsLevel1";"Armory";258;0
"Unit";"Marine";"Barracks";258;1
"Unit";"Marine";"Barracks";259;1
"Unit";"Marine";"Barracks";260;1
"Unit";"Marine";"Barracks";261;1
"Unit";"Marauder";"Barracks";262;2
"Unit";"Marauder";"Barracks";264;2
"Unit";"Marauder";"Barracks";266;2
"Unit";"Medivac";"Starport";268;2
"Unit";"Liberator";"Starport";270;3
"Unit";"Liberator";"Starport";273;3
"Building";"Refinery";NA;276;0
"Unit";"Liberator";"Starport";276;3
"Unit";"Marauder";"Barracks";279;2
"Unit";"Marauder";"Barracks";281;2
"Unit";"Marine";"Barracks";283;1
"Unit";"Marine";"Barracks";284;1
"Unit";"Marauder";"Barracks";285;2
"Unit";"Marine";"Barracks";287;1
"Unit";"Marine";"Barracks";288;1
"Unit";"Marine";"Barracks";289;1
"Unit";"Marauder";"Barracks";290;2
"Unit";"Liberator";"Starport";292;3
"Unit";"Liberator";"Starport";295;3
"Unit";"Marauder";"Barracks";298;2
"Unit";"Marine";"Barracks";300;1
"Unit";"Marine";"Barracks";301;1
"Unit";"Marauder";"Barracks";302;2
"Unit";"Marine";"Barracks";304;1
"Unit";"Marine";"Barracks";305;1
"Unit";"Marauder";"Barracks";306;2
"Unit";"Marauder";"Barracks";308;2
"Unit";"Marauder";"Barracks";310;2
"Upgrade";"SprayTerran";NA;312;0
"Upgrade";"SprayTerran";NA;312;0
"Upgrade";"ShieldWall";NA;312;0
"Upgrade";"PunisherGrenades";NA;312;0
"Upgrade";"SprayTerran";NA;312;0
"Upgrade";"SprayTerran";NA;312;0
"Upgrade";"TerranInfantryArmorsLevel1";NA;312;0
"Upgrade";"TerranInfantryArmorsLevel2";NA;312;0
"Upgrade";"SprayTerran";NA;312;0
"Upgrade";"LiberatorAGRangeUpgrade";NA;312;0
"Upgrade";"SprayTerran";NA;312;0
