"type";"unit_name";"on_building";"total_supply";"supply"
"Building";"Refinery";NA;17;0
"Building";"Barracks";NA;15;0
"Unit";"Marine";"Barracks";19;1
"Building";"BarracksTechLab";NA;20;0
"Unit";"Marauder";"Barracks";21;2
"Unit";"Marauder";"Barracks";21;2
"Building";"CommandCenter";NA;19;0
"Building";"Refinery";NA;24;0
"Building";"Barracks";NA;21;0
"Unit";"Marine";"Barracks";25;1
"Building";"Barracks";NA;21;0
"Unit";"Marine";"Barracks";30;1
"Unit";"Marine";"Barracks";30;1
"Building";"BarracksReactor";NA;28;0
"Building";"EngineeringBay";NA;31;0
"Unit";"Marine";"Barracks";36;1
"Unit";"Marine";"Barracks";36;1
"Unit";"Marine";"Barracks";36;1
"Unit";"Marauder";"Barracks";36;2
"Unit";"Marine";"Barracks";40;1
"Unit";"Marine";"Barracks";40;1
"Building";"MissileTurret";NA;44;0
"Unit";"Marine";"Barracks";44;1
"Unit";"Marauder";"Barracks";44;2
"Unit";"Marine";"Barracks";48;1
"Building";"Factory";NA;37;0
"Unit";"Marine";"Barracks";48;1
"Upgrade";"Stimpack";"TechLab";31;0
"Unit";"Marauder";"Barracks";51;2
"Unit";"Marine";"Barracks";53;1
"Unit";"Marine";"Barracks";54;1
"Building";"Refinery";NA;57;0
"Unit";"Marine";"Barracks";57;1
"Unit";"Marine";"Barracks";63;1
"Unit";"Marine";"Barracks";63;1
"Building";"Starport";NA;57;0
"Building";"FactoryReactor";NA;57;0
"Unit";"Marauder";"Barracks";63;2
"Unit";"Marine";"Barracks";69;1
"Unit";"Marine";"Barracks";69;1
"Unit";"Marine";"Barracks";70;1
"Upgrade";"TerranInfantryWeaponsLevel1";"EngineeringBay";48;0
"Unit";"Marine";"Barracks";77;1
"Unit";"Marine";"Barracks";77;1
"Unit";"Medivac";"Starport";72;2
"Unit";"Medivac";"Starport";72;2
"Building";"BarracksTechLab";NA;77;0
"Unit";"Marauder";"Barracks";76;2
"Building";"FactoryReactor";NA;72;0
"Unit";"Marine";"Barracks";85;1
"Unit";"Marine";"Barracks";85;1
"Unit";"Marauder";"Barracks";89;2
"Unit";"Marauder";"Barracks";89;2
"Unit";"Medivac";"Starport";83;2
"Unit";"Medivac";"Starport";85;2
"Unit";"Marine";"Barracks";91;1
"Unit";"Marine";"Barracks";91;1
"Unit";"Marine";"Barracks";101;1
"Unit";"Marine";"Barracks";101;1
"Building";"Barracks";NA;89;0
"Building";"Barracks";NA;91;0
"Unit";"Marauder";"Barracks";101;2
"Unit";"Marauder";"Barracks";101;2
"Unit";"Marine";"Barracks";101;1
"Unit";"Marine";"Barracks";102;1
"Building";"Refinery";NA;103;0
"Building";"BarracksTechLab";NA;107;0
"Unit";"Marauder";"Barracks";103;2
"Unit";"Marauder";"Barracks";105;2
"Unit";"Liberator";"Starport";101;3
"Unit";"Marine";"Barracks";107;1
"Unit";"Marine";"Barracks";109;1
"Building";"BarracksReactor";NA;107;0
"Unit";"Marine";"Barracks";109;1
"Unit";"Marauder";"Barracks";109;2
"Unit";"Marauder";"Barracks";111;2
"Unit";"Marine";"Barracks";116;1
"Unit";"Marine";"Barracks";117;1
"Unit";"Liberator";"Starport";107;3
"Unit";"Marine";"Barracks";118;1
"Unit";"Marine";"Barracks";121;1
"Unit";"Marine";"Barracks";123;1
"Unit";"Marine";"Barracks";123;1
"Unit";"Marauder";"Barracks";119;2
"Unit";"Marine";"Barracks";123;1
"Unit";"Marauder";"Barracks";128;2
"Unit";"Marine";"Barracks";130;1
"Unit";"Marine";"Barracks";130;1
"Unit";"Marauder";"Barracks";129;2
"Building";"CommandCenter";NA;107;0
"Unit";"Marauder";"Barracks";132;2
"Unit";"Marine";"Barracks";135;1
"Unit";"Marine";"Barracks";135;1
"Unit";"Marauder";"Barracks";135;2
"Unit";"Marine";"Barracks";141;1
"Unit";"Marauder";"Barracks";139;2
"Unit";"Marauder";"Barracks";141;2
"Unit";"Marine";"Barracks";143;1
"Unit";"Marauder";"Barracks";145;2
"Unit";"Marauder";"Barracks";148;2
"Unit";"Marine";"Barracks";153;1
"Unit";"Marine";"Barracks";153;1
"Unit";"Marauder";"Barracks";150;2
"Unit";"Marine";"Barracks";153;1
"Unit";"Marine";"Barracks";153;1
"Unit";"Medivac";"Starport";150;2
"Unit";"Medivac";"Starport";150;2
"Unit";"Marauder";"Barracks";154;2
"Unit";"Marauder";"Barracks";156;2
"Unit";"Marine";"Barracks";164;1
"Unit";"Marine";"Barracks";164;1
"Building";"EngineeringBay";NA;158;0
"Unit";"Marine";"Barracks";166;1
"Unit";"Medivac";"Starport";166;2
"Unit";"Medivac";"Starport";168;2
"Building";"MissileTurret";NA;174;0
"Unit";"Marine";"Barracks";176;1
"Building";"Armory";NA;158;0
"Unit";"Marine";"Barracks";180;1
"Unit";"Marine";"Barracks";180;1
"Unit";"Marine";"Barracks";180;1
"Unit";"Marine";"Barracks";180;1
"Unit";"Marine";"Barracks";187;1
"Building";"GhostAcademy";NA;187;0
"Unit";"Marine";"Barracks";191;1
"Unit";"Marine";"Barracks";191;1
"Unit";"Marine";"Barracks";191;1
"Unit";"Liberator";"Starport";186;3
"Unit";"Liberator";"Starport";186;3
"Unit";"Marauder";"Barracks";191;2
"Unit";"Marine";"Barracks";192;1
"Unit";"Marauder";"Barracks";192;2
"Unit";"Marauder";"Barracks";192;2
"Unit";"Marine";"Barracks";192;1
"Unit";"Marine";"Barracks";193;1
"Unit";"Marine";"Barracks";194;1
"Unit";"Marine";"Barracks";203;1
"Unit";"Marauder";"Barracks";201;2
"Upgrade";"TerranInfantryArmorsLevel1";"EngineeringBay";179;0
"Unit";"Marauder";"Barracks";204;2
"Unit";"Marauder";"Barracks";206;2
"Unit";"Marine";"Barracks";208;1
"Unit";"Marine";"Barracks";209;1
"Unit";"Marine";"Barracks";211;1
"Unit";"Marine";"Barracks";211;1
"Unit";"Liberator";"Starport";195;3
"Unit";"Marauder";"Barracks";212;2
"Unit";"Marauder";"Barracks";214;2
"Unit";"Marine";"Barracks";218;1
"Unit";"Marauder";"Barracks";216;2
"Unit";"Marine";"Barracks";219;1
"Unit";"Marine";"Barracks";220;1
"Unit";"Marine";"Barracks";221;1
