"Type";"UnitName";"OnBuilding";"TotalSupply";"Supply"
"Unit";"SCV";"Command Center";12;1
"Unit";"SCV";"Command Center";12;1
"Unit";"SCV";"Command Center";13;1
"Building";"SupplyDepot";NA;13;0
"Unit";"SCV";"Command Center";15;1
"Building";"Refinery";NA;14;0
"Unit";"SCV";"Command Center";16;1
"Unit";"SCV";"Command Center";17;1
"Unit";"SCV";"Command Center";17;1
"Building";"Barracks";NA;15;0
"Unit";"Reaper";"Barracks";19;1
"Unit";"SCV";"Command Center";19;1
"Building";"Refinery";NA;19;0
"Unit";"SCV";"Command Center";21;1
"Unit";"SCV";"Command Center";21;1
"Building";"BarracksReactor";NA;20;0
"Building";"Factory";NA;20;0
"Building";"SupplyDepot";NA;21;0
"Building";"CommandCenter";NA;19;0
"Unit";"SCV";"Command Center";23;1
"Unit";"Hellion";"Factory";23;2
"Unit";"Hellion";"Factory";23;2
"Unit";"Marine";"Barracks";23;1
"Building";"Starport";NA;23;0
"Unit";"SCV";"Command Center";28;1
"Unit";"Hellion";"Factory";24;2
"Unit";"Hellion";"Factory";26;2
"Unit";"SCV";"Command Center";30;1
"Unit";"SCV";"Command Center";30;1
"Unit";"SCV";"Command Center";34;1
"Unit";"Medivac";"Starport";29;2
"Unit";"SCV";"Command Center";35;1
"Unit";"SCV";"Command Center";36;1
"Building";"BarracksTechLab";NA;36;0
"Building";"SupplyDepot";NA;39;0
"Building";"SupplyDepot";NA;40;0
"Unit";"SCV";"Command Center";41;1
"Unit";"Medivac";"Starport";40;2
"Unit";"SCV";"Command Center";41;1
"Unit";"SCV";"Command Center";41;1
"Building";"Barracks";NA;39;0
"Building";"Barracks";NA;39;0
"Unit";"Marine";"Barracks";46;1
"Unit";"Medivac";"Starport";46;2
"Unit";"Marine";"Barracks";46;1
"Unit";"SCV";"Command Center";49;1
"Unit";"SCV";"Command Center";49;1
"Building";"BarracksReactor";NA;46;0
"Building";"BarracksReactor";NA;46;0
"Unit";"Marine";"Barracks";49;1
"Unit";"SCV";"Command Center";50;1
"Unit";"SCV";"Command Center";51;1
"Building";"SupplyDepot";NA;50;0
"Building";"SupplyDepot";NA;50;0
"Building";"SupplyDepot";NA;50;0
"Unit";"SCV";"Command Center";53;1
"Building";"SupplyDepot";NA;52;0
"Unit";"SCV";"Command Center";55;1
"Unit";"Marine";"Barracks";53;1
"Unit";"Marine";"Barracks";55;1
"Unit";"Marine";"Barracks";55;1
"Unit";"Marine";"Barracks";55;1
"Unit";"Marine";"Barracks";55;1
"Unit";"SCV";"Command Center";55;1
"Unit";"SCV";"Command Center";56;1
"Building";"Refinery";NA;57;0
"Unit";"Marauder";"Barracks";57;2
"Unit";"Marine";"Barracks";58;1
"Unit";"Marine";"Barracks";59;1
"Unit";"Marine";"Barracks";60;1
"Building";"Barracks";NA;52;0
"Unit";"Medivac";"Starport";58;2
"Unit";"Medivac";"Starport";58;2
"Unit";"Marine";"Barracks";69;1
"Unit";"Marine";"Barracks";69;1
"Unit";"Marauder";"Barracks";64;2
"Unit";"Marine";"Barracks";73;1
"Unit";"Marine";"Barracks";73;1
"Unit";"SCV";"Command Center";77;1
"Unit";"SCV";"Command Center";77;1
"Unit";"Marauder";"Barracks";75;2
"Unit";"Marine";"Barracks";79;1
"Unit";"Marine";"Barracks";79;1
"Unit";"SCV";"Command Center";79;1
"Unit";"SCV";"Command Center";80;1
"Building";"Refinery";NA;79;0
"Building";"GhostAcademy";NA;77;0
"Building";"BarracksTechLab";NA;79;0
"Building";"FactoryTechLab";NA;80;0
"Unit";"SCV";"Command Center";85;1
"Unit";"SCV";"Command Center";86;1
"Unit";"Marauder";"Barracks";81;2
"Unit";"Medivac";"Starport";81;2
"Unit";"Medivac";"Starport";81;2
"Building";"Barracks";NA;77;0
"Unit";"SCV";"Command Center";87;1
"Unit";"SCV";"Command Center";91;1
"Building";"Barracks";NA;79;0
"Building";"Barracks";NA;79;0
"Upgrade";"Stimpack";"TechLab";64;0
"Unit";"SCV";"Command Center";95;1
"Unit";"Ghost";"Barracks";91;2
"Unit";"Ghost";"Barracks";95;2
"Unit";"Marine";"Barracks";98;1
"Unit";"Marine";"Barracks";98;1
"Unit";"Marine";"Barracks";98;1
"Unit";"Marine";"Barracks";98;1
"Unit";"Marine";"Barracks";98;1
"Unit";"Marine";"Barracks";98;1
"Unit";"Marauder";"Barracks";98;2
"Unit";"Marauder";"Barracks";100;2
"Unit";"Marine";"Barracks";108;1
"Unit";"Marine";"Barracks";108;1
"Unit";"Marine";"Barracks";108;1
"Unit";"Marine";"Barracks";108;1
"Unit";"Marine";"Barracks";108;1
"Unit";"SCV";"Command Center";108;1
"Unit";"SCV";"Command Center";108;1
"Unit";"Marine";"Barracks";108;1
"Unit";"Marine";"Barracks";108;1
"Unit";"SCV";"Command Center";119;1
"Unit";"Marine";"Barracks";119;1
"Building";"BarracksTechLab";NA;121;0
"Building";"BarracksTechLab";NA;121;0
"Building";"BarracksTechLab";NA;121;0
"Unit";"SCV";"Command Center";123;1
"Unit";"Marine";"Barracks";123;1
"Unit";"Marine";"Barracks";123;1
"Unit";"Marauder";"Barracks";123;2
"Unit";"Marine";"Barracks";123;1
"Building";"SupplyDepot";NA;123;0
"Building";"SupplyDepot";NA;124;0
"Building";"SupplyDepot";NA;124;0
"Building";"SupplyDepot";NA;126;0
"Building";"SupplyDepot";NA;129;0
"Building";"SupplyDepot";NA;129;0
"Unit";"SCV";"Command Center";129;1
"Unit";"Marine";"Barracks";129;1
"Unit";"Marine";"Barracks";129;1
"Unit";"Marine";"Barracks";129;1
"Unit";"Marine";"Barracks";129;1
"Unit";"Marine";"Barracks";129;1
"Unit";"Marauder";"Barracks";129;2
"Unit";"Marauder";"Barracks";129;2
"Unit";"Marauder";"Barracks";129;2
"Unit";"SCV";"Command Center";129;1
"Unit";"Marine";"Barracks";129;1
"Unit";"Medivac";"Starport";129;2
"Unit";"Medivac";"Starport";129;2
"Unit";"Marine";"Barracks";130;1
"Unit";"Marauder";"Barracks";137;2
"Unit";"Marauder";"Barracks";137;2
"Unit";"Ghost";"Barracks";130;2
"Unit";"Marine";"Barracks";147;1
"Unit";"Ghost";"Barracks";135;2
"Building";"CommandCenter";NA;126;0
"Unit";"Marine";"Barracks";148;1
"Building";"EngineeringBay";NA;147;0
"Building";"EngineeringBay";NA;147;0
"Building";"CommandCenter";NA;129;0
"Unit";"SCV";"Command Center";158;1
"Unit";"SCV";"Command Center";158;1
"Unit";"SCV";"Command Center";158;1
"Unit";"Marine";"Barracks";158;1
"Unit";"Marine";"Barracks";158;1
"Unit";"Marauder";"Barracks";158;2
"Unit";"Marauder";"Barracks";158;2
"Unit";"Marine";"Barracks";167;1
"Unit";"Marine";"Barracks";167;1
"Unit";"Marauder";"Barracks";167;2
"Unit";"Marauder";"Barracks";167;2
"Unit";"Marine";"Barracks";167;1
"Unit";"Marine";"Barracks";167;1
"Unit";"Marine";"Barracks";167;1
"Unit";"Marauder";"Barracks";167;2
"Unit";"Marauder";"Barracks";167;2
"Unit";"SCV";"Command Center";173;1
"Unit";"SCV";"Command Center";173;1
"Unit";"SCV";"Command Center";173;1
"Unit";"SCV";"Command Center";180;1
"Unit";"SCV";"Command Center";181;1
"Unit";"SCV";"Command Center";182;1
"Unit";"Marine";"Barracks";180;1
"Unit";"Marauder";"Barracks";180;2
"Unit";"Marauder";"Barracks";180;2
"Unit";"SCV";"Command Center";191;1
"Unit";"SCV";"Command Center";191;1
"Unit";"SCV";"Command Center";191;1
"Unit";"Marine";"Barracks";191;1
"Unit";"Marine";"Barracks";191;1
"Unit";"Marine";"Barracks";191;1
"Unit";"Marine";"Barracks";191;1
"Building";"SensorTower";NA;191;0
"Unit";"Marauder";"Barracks";191;2
"Unit";"Marauder";"Barracks";191;2
"Unit";"SCV";"Command Center";191;1
"Unit";"SCV";"Command Center";192;1
"Unit";"Marine";"Barracks";204;1
"Unit";"Marine";"Barracks";204;1
"Unit";"Marine";"Barracks";204;1
"Unit";"Marine";"Barracks";204;1
"Unit";"Marauder";"Barracks";204;2
"Unit";"Marauder";"Barracks";204;2
"Unit";"Marauder";"Barracks";204;2
"Unit";"Marauder";"Barracks";204;2
"Upgrade";"TerranInfantryWeaponsLevel1";"EngineeringBay";185;0
"Upgrade";"TerranInfantryArmorsLevel1";"EngineeringBay";185;0
"Unit";"Marine";"Barracks";216;1
"Unit";"Marine";"Barracks";216;1
"Unit";"Marine";"Barracks";216;1
"Unit";"SCV";"Command Center";216;1
"Unit";"SCV";"Command Center";216;1
"Unit";"Marauder";"Barracks";216;2
"Unit";"Marauder";"Barracks";216;2
"Unit";"Marauder";"Barracks";216;2
"Unit";"Marauder";"Barracks";216;2
"Unit";"Marine";"Barracks";216;1
"Building";"Refinery";NA;216;0
"Building";"Refinery";NA;216;0
"Building";"SupplyDepot";NA;229;0
"Building";"SupplyDepot";NA;229;0
"Building";"SupplyDepot";NA;229;0
"Unit";"Ghost";"Barracks";216;2
"Unit";"Ghost";"Barracks";221;2
"Unit";"Ghost";"Barracks";223;2
"Unit";"Ghost";"Barracks";225;2
"Unit";"Ghost";"Barracks";227;2
"Unit";"Medivac";"Starport";230;2
"Unit";"Medivac";"Starport";230;2
"Unit";"Marine";"Barracks";230;1
"Unit";"Marine";"Barracks";230;1
"Building";"Armory";NA;216;0
"Unit";"Marauder";"Barracks";230;2
"Unit";"Marauder";"Barracks";232;2
"Unit";"Marauder";"Barracks";234;2
"Building";"MissileTurret";NA;244;0
"Building";"Factory";NA;230;0
"Building";"Starport";NA;232;0
"Unit";"Ghost";"Barracks";240;2
"Unit";"Medivac";"Starport";240;2
"Unit";"Medivac";"Starport";242;2
"Building";"CommandCenter";NA;229;0
"Unit";"Marine";"Barracks";254;1
"Unit";"Marine";"Barracks";254;1
"Unit";"Marine";"Barracks";254;1
"Unit";"Marine";"Barracks";254;1
"Unit";"Marauder";"Barracks";254;2
"Unit";"Marauder";"Barracks";254;2
"Unit";"Marauder";"Barracks";254;2
"Building";"StarportReactor";NA;254;0
"Building";"FactoryReactor";NA;254;0
"Unit";"Marine";"Barracks";268;1
"Unit";"Marine";"Barracks";268;1
"Unit";"Marauder";"Barracks";268;2
"Unit";"Marauder";"Barracks";268;2
"Unit";"Marine";"Barracks";274;1
"Unit";"Marine";"Barracks";274;1
"Unit";"Marine";"Barracks";274;1
"Unit";"Marine";"Barracks";274;1
"Unit";"Marauder";"Barracks";274;2
"Unit";"Marauder";"Barracks";274;2
"Unit";"Marauder";"Barracks";274;2
"Unit";"Marine";"Barracks";274;1
"Unit";"Marauder";"Barracks";274;2
"Unit";"Marine";"Barracks";274;1
"Unit";"Marine";"Barracks";275;1
"Unit";"Marine";"Barracks";276;1
"Unit";"Marine";"Barracks";277;1
"Unit";"Marauder";"Barracks";278;2
"Unit";"Marauder";"Barracks";280;2
"Unit";"Marine";"Barracks";287;1
"Unit";"Marine";"Barracks";287;1
"Unit";"Marauder";"Barracks";287;2
"Unit";"Marine";"Barracks";287;1
"Unit";"Marine";"Barracks";288;1
"Upgrade";"TerranInfantryWeaponsLevel2";"EngineeringBay";261;0
"Unit";"Marine";"Barracks";291;1
"Unit";"Marine";"Barracks";291;1
"Upgrade";"TerranInfantryArmorsLevel2";"EngineeringBay";264;0
"Unit";"Marauder";"Barracks";291;2
"Unit";"Marauder";"Barracks";293;2
"Unit";"Marauder";"Barracks";295;2
"Unit";"Marauder";"Barracks";296;2
"Upgrade";"TerranShipWeaponsLevel1";"Armory";270;0
"Unit";"Marine";"Barracks";299;1
"Unit";"Marine";"Barracks";300;1
"Unit";"Marauder";"Barracks";297;2
"Unit";"SCV";"Command Center";303;1
"Unit";"Marine";"Barracks";301;1
"Unit";"Ghost";"Barracks";315;2
"Unit";"Ghost";"Barracks";315;2
"Unit";"Ghost";"Barracks";315;2
"Unit";"Ghost";"Barracks";315;2
"Unit";"Marine";"Barracks";325;1
"Unit";"Marine";"Barracks";325;1
"Unit";"Marine";"Barracks";325;1
"Unit";"Marine";"Barracks";325;1
"Unit";"Marauder";"Barracks";325;2
"Unit";"Marine";"Barracks";325;1
"Unit";"Marauder";"Barracks";325;2
"Unit";"Marauder";"Barracks";325;2
"Unit";"Marauder";"Barracks";325;2
