"Type";"UnitName";"OnBuilding";"TotalSupply";"Supply"
"Unit";"SCV";"Command Center";12;1
"Unit";"SCV";"Command Center";12;1
"Unit";"SCV";"Command Center";13;1
"Building";"SupplyDepot";NA;13;0
"Unit";"SCV";"Command Center";15;1
"Building";"Refinery";NA;14;0
"Unit";"SCV";"Command Center";16;1
"Unit";"SCV";"Command Center";16;1
"Building";"Refinery";NA;16;0
"Unit";"SCV";"Command Center";18;1
"Building";"Barracks";NA;15;0
"Unit";"SCV";"Command Center";19;1
"Building";"BarracksReactor";NA;19;0
"Building";"Factory";NA;19;0
"Building";"SupplyDepot";NA;20;0
"Unit";"Marine";"Barracks";20;1
"Unit";"Marine";"Barracks";20;1
"Building";"FactoryTechLab";NA;20;0
"Unit";"Marine";"Barracks";20;1
"Unit";"Marine";"Barracks";21;1
"Building";"SupplyDepot";NA;22;0
"Building";"Starport";NA;20;0
"Unit";"Marine";"Barracks";24;1
"Unit";"Marine";"Barracks";24;1
"Unit";"Marine";"Barracks";26;1
"Unit";"Marine";"Barracks";26;1
"Unit";"Liberator";"Starport";24;3
"Unit";"Marine";"Barracks";26;1
"Unit";"Marine";"Barracks";27;1
"Unit";"Marine";"Barracks";31;1
"Unit";"Marine";"Barracks";32;1
"Unit";"Marine";"Barracks";35;1
"Building";"EngineeringBay";NA;35;0
"Building";"SupplyDepot";NA;36;0
"Building";"SupplyDepot";NA;36;0
"Unit";"Marine";"Barracks";36;1
"Unit";"Marine";"Barracks";36;1
"Unit";"Medivac";"Starport";36;2
"Unit";"Marine";"Barracks";36;1
"Unit";"Marine";"Barracks";36;1
"Unit";"SCV";"Command Center";40;1
"Unit";"Marine";"Barracks";40;1
"Unit";"Marine";"Barracks";40;1
"Unit";"Medivac";"Starport";40;2
"Building";"Barracks";NA;38;0
"Building";"Barracks";NA;38;0
"Unit";"Marine";"Barracks";47;1
"Unit";"Marine";"Barracks";48;1
"Building";"BarracksTechLab";NA;48;0
"Building";"BarracksTechLab";NA;48;0
"Unit";"Marine";"Barracks";48;1
"Unit";"Marine";"Barracks";48;1
"Unit";"Marine";"Barracks";51;1
"Unit";"Marine";"Barracks";51;1
"Unit";"Marine";"Barracks";51;1
"Unit";"Marine";"Barracks";52;1
"Unit";"Marine";"Barracks";53;1
"Unit";"Marine";"Barracks";54;1
"Building";"Barracks";NA;53;0
"Unit";"Marine";"Barracks";55;1
"Unit";"Marine";"Barracks";56;1
"Building";"MissileTurret";NA;57;0
"Unit";"Marine";"Barracks";57;1
"Unit";"Marine";"Barracks";58;1
"Unit";"Marine";"Barracks";59;1
"Building";"Barracks";NA;57;0
"Unit";"Marine";"Barracks";59;1
"Unit";"Marine";"Barracks";60;1
"Unit";"Marine";"Barracks";61;1
"Unit";"Marine";"Barracks";61;1
"Building";"SupplyDepot";NA;61;0
"Unit";"Marine";"Barracks";62;1
"Unit";"Marine";"Barracks";62;1
"Unit";"Marine";"Barracks";63;1
"Unit";"Marine";"Barracks";64;1
"Unit";"Marine";"Barracks";65;1
"Upgrade";"Stimpack";"TechLab";55;0
"Unit";"Marine";"Barracks";66;1
"Unit";"Marine";"Barracks";67;1
"Unit";"Marine";"Barracks";68;1
"Unit";"Marine";"Barracks";69;1
"Unit";"Marine";"Barracks";70;1
"Unit";"Marine";"Barracks";71;1
"Unit";"Marine";"Barracks";72;1
"Unit";"Marine";"Barracks";73;1
"Unit";"Marine";"Barracks";74;1
"Unit";"Marine";"Barracks";75;1
"Unit";"Marine";"Barracks";76;1
"Unit";"Marine";"Barracks";77;1
"Unit";"Marine";"Barracks";78;1
"Unit";"Marine";"Barracks";79;1
"Unit";"Marine";"Barracks";80;1
"Building";"SupplyDepot";NA;85;0
"Building";"SupplyDepot";NA;85;0
"Unit";"Marine";"Barracks";86;1
"Unit";"Marine";"Barracks";86;1
"Unit";"Marine";"Barracks";86;1
"Unit";"Marine";"Barracks";86;1
"Unit";"Marine";"Barracks";86;1
"Unit";"Marine";"Barracks";91;1
"Unit";"Marine";"Barracks";92;1
"Unit";"Marine";"Barracks";92;1
"Unit";"Marine";"Barracks";92;1
"Unit";"Marine";"Barracks";93;1
"Unit";"Marine";"Barracks";95;1
"Unit";"Marine";"Barracks";95;1
"Unit";"SCV";"Command Center";97;1
"Unit";"Marine";"Barracks";96;1
"Unit";"Marine";"Barracks";100;1
"Unit";"Marine";"Barracks";100;1
"Unit";"Marine";"Barracks";100;1
"Unit";"Marine";"Barracks";100;1
"Unit";"Marine";"Barracks";101;1
"Unit";"Marine";"Barracks";103;1
"Unit";"Marine";"Barracks";103;1
"Unit";"Marine";"Barracks";105;1
"Unit";"SCV";"Command Center";106;1
"Unit";"Marine";"Barracks";105;1
"Unit";"Marine";"Barracks";107;1
"Unit";"SCV";"Command Center";110;1
"Unit";"Marine";"Barracks";111;1
"Unit";"Marine";"Barracks";112;1
"Unit";"Marine";"Barracks";112;1
"Unit";"Marine";"Barracks";114;1
"Unit";"Marine";"Barracks";114;1
"Unit";"Marine";"Barracks";117;1
"Unit";"Marine";"Barracks";117;1
"Unit";"Marine";"Barracks";117;1
"Unit";"SCV";"Command Center";117;1
"Unit";"Marine";"Barracks";117;1
"Unit";"Marine";"Barracks";120;1
"Unit";"Marine";"Barracks";121;1
"Unit";"Marine";"Barracks";123;1
"Unit";"Marine";"Barracks";123;1
"Unit";"Marine";"Barracks";124;1
"Unit";"Marine";"Barracks";124;1
"Unit";"Marine";"Barracks";125;1
"Unit";"Marine";"Barracks";126;1
"Unit";"Marine";"Barracks";127;1
"Unit";"Marine";"Barracks";128;1
"Unit";"Marine";"Barracks";129;1
