"type";"unit_name";"on_building";"total_supply";"supply"
"Building";"Refinery";NA;15;0
"Building";"Barracks";NA;15;0
"Unit";"Reaper";"Barracks";19;1
"Building";"BarracksReactor";NA;20;0
"Building";"Bunker";NA;21;0
"Unit";"Marine";"Barracks";23;1
"Unit";"Marine";"Barracks";23;1
"Building";"Factory";NA;21;0
"Building";"CommandCenter";NA;19;0
"Unit";"Marine";"Barracks";24;1
"Unit";"Marine";"Barracks";25;1
"Unit";"Marine";"Barracks";30;1
"Unit";"Marine";"Barracks";30;1
"Unit";"Cyclone";"Factory";31;3
"Unit";"Marine";"Barracks";34;1
"Unit";"Marine";"Barracks";34;1
"Building";"Refinery";NA;39;0
"Unit";"Marine";"Barracks";41;1
"Unit";"Marine";"Barracks";41;1
"Building";"Starport";NA;34;0
"Building";"FactoryTechLab";NA;44;0
"Building";"CommandCenter";NA;31;0
"Unit";"Marine";"Barracks";48;1
"Unit";"Marine";"Barracks";48;1
"Unit";"Medivac";"Starport";48;2
"Unit";"Marine";"Barracks";52;1
"Unit";"Marine";"Barracks";52;1
"Building";"FactoryTechLab";NA;52;0
"Building";"Refinery";NA;54;0
"Building";"Refinery";NA;54;0
"Building";"Barracks";NA;48;0
"Building";"Barracks";NA;48;0
"Building";"BarracksTechLab";NA;64;0
"Building";"EngineeringBay";NA;64;0
"Building";"EngineeringBay";NA;65;0
"Unit";"Marine";"Barracks";66;1
"Unit";"Marine";"Barracks";66;1
"Unit";"Raven";"Starport";62;2
"Unit";"Marauder";"Barracks";66;2
"Unit";"Marauder";"Barracks";66;2
"Building";"Barracks";NA;64;0
"Building";"FactoryReactor";NA;66;0
"Building";"Barracks";NA;65;0
"Unit";"Marauder";"Barracks";79;2
"Unit";"Marine";"Barracks";80;1
"Unit";"Marine";"Barracks";80;1
"Unit";"Marauder";"Barracks";81;2
"Building";"StarportReactor";NA;80;0
"Unit";"Marine";"Barracks";84;1
"Unit";"Marine";"Barracks";85;1
"Unit";"Marauder";"Barracks";82;2
"Building";"BarracksReactor";NA;81;0
"Unit";"Marauder";"Barracks";88;2
"Unit";"Marine";"Barracks";90;1
"Unit";"Marine";"Barracks";90;1
"Unit";"Marine";"Barracks";96;1
"Building";"Refinery";NA;96;0
"Unit";"Marauder";"Barracks";96;2
"Unit";"Medivac";"Starport";92;2
"Unit";"Medivac";"Starport";93;2
"Building";"Refinery";NA;96;0
"Unit";"Marauder";"Barracks";96;2
"Unit";"Marine";"Barracks";102;1
"Unit";"Marine";"Barracks";102;1
"Unit";"Marine";"Barracks";102;1
"Unit";"Marauder";"Barracks";102;2
"Unit";"Marine";"Barracks";112;1
"Unit";"Marine";"Barracks";112;1
"Unit";"Marauder";"Barracks";112;2
"Upgrade";"Stimpack";"TechLab";81;0
"Unit";"Marine";"Barracks";117;1
"Unit";"Marine";"Barracks";118;1
"Upgrade";"TerranInfantryWeaponsLevel1";"EngineeringBay";84;0
"Unit";"Medivac";"Starport";114;2
"Unit";"Medivac";"Starport";114;2
"Unit";"Marine";"Barracks";125;1
"Unit";"Marine";"Barracks";125;1
"Building";"Armory";NA;102;0
"Upgrade";"TerranInfantryArmorsLevel1";"EngineeringBay";86;0
"Unit";"Marauder";"Barracks";125;2
"Unit";"Marauder";"Barracks";125;2
"Unit";"Marine";"Barracks";130;1
"Unit";"Marine";"Barracks";140;1
"Unit";"Marauder";"Barracks";140;2
"Unit";"Marauder";"Barracks";140;2
"Unit";"Marine";"Barracks";145;1
"Unit";"Marauder";"Barracks";145;2
"Unit";"Marine";"Barracks";145;1
"Unit";"Marine";"Barracks";146;1
"Unit";"Marine";"Barracks";146;1
"Unit";"Marauder";"Barracks";146;2
"Unit";"Marauder";"Barracks";148;2
"Unit";"Marine";"Barracks";151;1
"Unit";"Medivac";"Starport";146;2
"Unit";"Medivac";"Starport";146;2
"Unit";"Marauder";"Barracks";151;2
"Unit";"Marine";"Barracks";153;1
"Unit";"Marine";"Barracks";154;1
"Unit";"Marine";"Barracks";155;1
"Unit";"Marine";"Barracks";158;1
"Unit";"Marauder";"Barracks";156;2
"Unit";"Marine";"Barracks";160;1
"Unit";"Marine";"Barracks";167;1
"Unit";"Marine";"Barracks";168;1
"Unit";"Marauder";"Barracks";165;2
"Unit";"Marine";"Barracks";170;1
"Building";"Starport";NA;158;0
"Unit";"Marine";"Barracks";173;1
"Unit";"Marauder";"Barracks";170;2
"Unit";"Medivac";"Starport";170;2
"Unit";"Medivac";"Starport";170;2
"Unit";"Marauder";"Barracks";171;2
"Unit";"Marine";"Barracks";174;1
"Unit";"Marine";"Barracks";175;1
"Unit";"Marine";"Barracks";178;1
"Unit";"Marauder";"Barracks";176;2
"Unit";"Marine";"Barracks";179;1
"Unit";"Marine";"Barracks";188;1
"Unit";"Marauder";"Barracks";180;2
"Unit";"Marauder";"Barracks";186;2
"Unit";"Marine";"Barracks";189;1
"Unit";"Marine";"Barracks";190;1
"Unit";"Marauder";"Barracks";191;2
"Unit";"Marine";"Barracks";193;1
"Unit";"Marine";"Barracks";194;1
"Unit";"Liberator";"Starport";179;3
"Unit";"Marine";"Barracks";199;1
"Unit";"Liberator";"Starport";179;3
"Unit";"Marauder";"Barracks";195;2
"Unit";"Marauder";"Barracks";197;2
"Unit";"Liberator";"Starport";188;3
"Building";"CommandCenter";NA;170;0
"Unit";"Marine";"Barracks";200;1
"Unit";"Marine";"Barracks";203;1
"Unit";"Marauder";"Barracks";201;2
"Unit";"Marine";"Barracks";204;1
"Unit";"Marine";"Barracks";208;1
"Unit";"Marine";"Barracks";219;1
"Unit";"Marauder";"Barracks";212;2
"Unit";"Marauder";"Barracks";214;2
