"Type";"UnitName";"OnBuilding";"TotalSupply";"Supply"
"Unit";"SCV";"Command Center";12;1
"Unit";"SCV";"Command Center";12;1
"Unit";"SCV";"Command Center";14;1
"Building";"SupplyDepot";NA;13;0
"Unit";"SCV";"Command Center";15;1
"Unit";"SCV";"Command Center";15;1
"Building";"Refinery";NA;15;0
"Unit";"SCV";"Command Center";16;1
"Unit";"SCV";"Command Center";17;1
"Building";"Barracks";NA;15;0
"Unit";"Reaper";"Barracks";19;1
"Unit";"SCV";"Command Center";19;1
"Unit";"SCV";"Command Center";20;1
"Building";"BarracksTechLab";NA;21;0
"Building";"SupplyDepot";NA;21;0
"Unit";"SCV";"Command Center";21;1
"Unit";"SCV";"Command Center";22;1
"Unit";"Marauder";"Barracks";23;2
"Building";"Refinery";NA;23;0
"Unit";"SCV";"Command Center";24;1
"Building";"Barracks";NA;22;0
"Unit";"SCV";"Command Center";27;1
"Unit";"Marauder";"Barracks";24;2
"Unit";"SCV";"Command Center";28;1
"Unit";"Marine";"Barracks";28;1
"Building";"CommandCenter";NA;19;0
"Unit";"SCV";"Command Center";30;1
"Unit";"SCV";"Command Center";32;1
"Unit";"Marine";"Barracks";33;1
"Unit";"Marauder";"Barracks";32;2
"Unit";"SCV";"Command Center";33;1
"Unit";"Marine";"Barracks";34;1
"Unit";"Marauder";"Barracks";35;2
"Building";"SupplyDepot";NA;38;0
"Unit";"SCV";"Command Center";41;1
"Unit";"Marine";"Barracks";41;1
"Unit";"SCV";"Command Center";41;1
"Unit";"Marine";"Barracks";41;1
"Building";"SupplyDepot";NA;41;0
"Building";"Bunker";NA;41;0
"Unit";"Marine";"Barracks";42;1
"Unit";"SCV";"Command Center";43;1
"Unit";"SCV";"Command Center";45;1
"Unit";"Marine";"Barracks";44;1
"Unit";"SCV";"Command Center";46;1
"Unit";"SCV";"Command Center";47;1
"Building";"Factory";NA;42;0
"Unit";"SCV";"Command Center";49;1
"Unit";"SCV";"Command Center";50;1
"Building";"BarracksTechLab";NA;50;0
"Building";"EngineeringBay";NA;49;0
"Unit";"Marine";"Barracks";51;1
"Unit";"SCV";"Command Center";51;1
"Building";"Bunker";NA;49;0
"Unit";"SCV";"Command Center";52;1
"Unit";"SCV";"Command Center";54;1
"Building";"Starport";NA;52;0
"Unit";"SCV";"Command Center";57;1
"Unit";"Marine";"Barracks";57;1
"Unit";"Marauder";"Barracks";57;2
"Unit";"SCV";"Command Center";57;1
"Building";"FactoryTechLab";NA;58;0
"Unit";"Marine";"Barracks";58;1
"Unit";"Medivac";"Starport";57;2
"Unit";"Marauder";"Barracks";59;2
"Building";"MissileTurret";NA;62;0
"Building";"SupplyDepot";NA;63;0
"Building";"Barracks";NA;62;0
"Unit";"Marine";"Barracks";67;1
"Unit";"Marine";"Barracks";67;1
"Unit";"SCV";"Command Center";67;1
"Building";"SupplyDepot";NA;67;0
"Unit";"Medivac";"Starport";67;2
"Unit";"SCV";"Command Center";70;1
"Unit";"Marine";"Barracks";70;1
"Unit";"SCV";"Command Center";70;1
"Upgrade";"Stimpack";"TechLab";58;0
"Unit";"Marine";"Barracks";70;1
"Unit";"Marine";"Barracks";70;1
"Unit";"SCV";"Command Center";72;1
"Unit";"Marine";"Barracks";73;1
"Unit";"SCV";"Command Center";78;1
"Unit";"SCV";"Command Center";78;1
"Unit";"Marine";"Barracks";78;1
"Unit";"Marine";"Barracks";78;1
"Unit";"Marine";"Barracks";78;1
"Unit";"SCV";"Command Center";79;1
"Unit";"SCV";"Command Center";80;1
"Unit";"Marine";"Barracks";81;1
"Unit";"SCV";"Command Center";84;1
"Unit";"Marine";"Barracks";86;1
"Unit";"Marine";"Barracks";86;1
"Unit";"Marine";"Barracks";86;1
"Unit";"Marine";"Barracks";88;1
"Unit";"SCV";"Command Center";91;1
"Unit";"Cyclone";"Factory";90;3
"Unit";"SCV";"Command Center";91;1
"Unit";"Marauder";"Barracks";92;2
"Unit";"Marine";"Barracks";97;1
"Unit";"Marine";"Barracks";97;1
"Unit";"Marine";"Barracks";99;1
"Unit";"Marine";"Barracks";99;1
"Building";"StarportReactor";NA;99;0
"Unit";"Marine";"Barracks";102;1
"Unit";"Marine";"Barracks";102;1
"Unit";"Cyclone";"Factory";102;3
"Unit";"Medivac";"Starport";104;2
"Unit";"Medivac";"Starport";108;2
"Unit";"Marine";"Barracks";108;1
"Unit";"Marine";"Barracks";108;1
"Building";"SupplyDepot";NA;112;0
"Unit";"Medivac";"Starport";112;2
"Unit";"Marine";"Barracks";114;1
"Unit";"Marine";"Barracks";114;1
"Unit";"Marine";"Barracks";114;1
"Unit";"Marine";"Barracks";116;1
"Unit";"Marine";"Barracks";117;1
"Unit";"Marine";"Barracks";118;1
"Unit";"Medivac";"Starport";114;2
"Unit";"Cyclone";"Factory";119;3
"Unit";"Marine";"Barracks";119;1
"Unit";"Marine";"Barracks";120;1
"Unit";"Marine";"Barracks";121;1
"Unit";"Marine";"Barracks";127;1
"Unit";"Marine";"Barracks";128;1
"Unit";"Marine";"Barracks";129;1
"Unit";"Cyclone";"Factory";127;3
"Unit";"Marine";"Barracks";130;1
"Unit";"Marine";"Barracks";133;1
"Unit";"Marine";"Barracks";136;1
"Building";"SupplyDepot";NA;133;0
"Unit";"Marine";"Barracks";136;1
"Unit";"Marine";"Barracks";137;1
"Unit";"Marine";"Barracks";139;1
"Unit";"Cyclone";"Factory";139;3
"Unit";"Marine";"Barracks";139;1
"Unit";"Marine";"Barracks";141;1
"Upgrade";"TerranInfantryWeaponsLevel1";"EngineeringBay";127;0
"Unit";"Medivac";"Starport";147;2
"Unit";"Cyclone";"Factory";147;3
"Unit";"SCV";"Command Center";152;1
"Unit";"SCV";"Command Center";153;1
"Unit";"SCV";"Command Center";153;1
"Unit";"SCV";"Command Center";154;1
"Unit";"SCV";"Command Center";155;1
"Building";"MissileTurret";NA;157;0
"Unit";"SCV";"Command Center";157;1
"Building";"Barracks";NA;157;0
"Building";"Barracks";NA;157;0
"Unit";"SCV";"Command Center";157;1
"Building";"Barracks";NA;157;0
"Unit";"Marine";"Barracks";159;1
"Unit";"Marine";"Barracks";159;1
"Unit";"Marine";"Barracks";159;1
"Unit";"Marine";"Barracks";159;1
"Unit";"Marine";"Barracks";160;1
"Unit";"Marine";"Barracks";161;1
"Unit";"Marine";"Barracks";164;1
"Unit";"Marine";"Barracks";164;1
"Unit";"SCV";"Command Center";164;1
"Building";"Barracks";NA;161;0
"Building";"Barracks";NA;161;0
"Building";"Barracks";NA;161;0
"Unit";"Marine";"Barracks";164;1
"Unit";"Marine";"Barracks";165;1
"Unit";"Marine";"Barracks";169;1
"Unit";"Marine";"Barracks";169;1
"Unit";"Marine";"Barracks";169;1
"Unit";"Marine";"Barracks";169;1
"Unit";"Marine";"Barracks";169;1
"Unit";"Marine";"Barracks";169;1
"Unit";"Marine";"Barracks";170;1
"Unit";"Marine";"Barracks";171;1
"Unit";"SCV";"Command Center";178;1
"Unit";"Marine";"Barracks";178;1
"Unit";"Marine";"Barracks";178;1
"Unit";"Marine";"Barracks";178;1
"Unit";"Marine";"Barracks";178;1
"Unit";"Marine";"Barracks";178;1
"Unit";"Marine";"Barracks";178;1
"Unit";"SCV";"Command Center";178;1
"Unit";"Marine";"Barracks";186;1
"Unit";"Marine";"Barracks";186;1
"Unit";"Marine";"Barracks";186;1
"Unit";"Marine";"Barracks";186;1
"Unit";"Marine";"Barracks";186;1
"Unit";"Marine";"Barracks";186;1
"Building";"SupplyDepot";NA;186;0
"Unit";"Marine";"Barracks";192;1
"Unit";"Marine";"Barracks";192;1
"Unit";"Marine";"Barracks";192;1
"Unit";"Marine";"Barracks";192;1
"Unit";"Marine";"Barracks";192;1
"Unit";"Marine";"Barracks";192;1
"Unit";"Marine";"Barracks";192;1
"Unit";"Marine";"Barracks";193;1
"Unit";"Marine";"Barracks";193;1
"Building";"SupplyDepot";NA;199;0
"Building";"SupplyDepot";NA;199;0
"Building";"SupplyDepot";NA;201;0
"Building";"SupplyDepot";NA;201;0
"Building";"SupplyDepot";NA;201;0
