"type";"unit_name";"on_building";"total_supply_lag";"supply"
"Building";"Barracks";NA;16;0
"Building";"Refinery";NA;16;0
"Unit";"Marine";"Barracks";19;1
"Building";"CommandCenter";NA;20;0
"Building";"BarracksTechLab";NA;21;0
"Unit";"Marauder";"Barracks";23;2
"Building";"Barracks";NA;25;0
"Building";"Barracks";NA;26;0
"Unit";"Marauder";"Barracks";27;2
"Building";"EngineeringBay";NA;30;0
"Unit";"Marine";"Barracks";30;1
"Building";"BarracksReactor";NA;32;0
"Building";"MissileTurret";NA;33;0
"Building";"BarracksTechLab";NA;33;0
"Upgrade";"Stimpack";"TechLab";34;0
"Building";"MissileTurret";NA;34;0
"Unit";"Marauder";"Barracks";34;2
"Unit";"Marine";"Barracks";37;1
"Unit";"Marine";"Barracks";38;1
"Upgrade";"TerranInfantryWeaponsLevel1";"EngineeringBay";39;0
"Unit";"Marauder";"Barracks";40;2
"Unit";"Marine";"Barracks";43;1
"Unit";"Marine";"Barracks";44;1
"Building";"Refinery";NA;46;0
"Building";"Barracks";NA;46;0
"Building";"Barracks";NA;46;0
"Unit";"Marauder";"Barracks";46;2
"Building";"Refinery";NA;50;0
"Unit";"Marine";"Barracks";50;1
"Building";"Refinery";NA;51;0
"Unit";"Marine";"Barracks";52;1
"Unit";"Marine";"Barracks";53;1
"Unit";"Marine";"Barracks";54;1
"Unit";"Marine";"Barracks";57;1
"Building";"Factory";NA;59;0
"Unit";"Marine";"Barracks";59;1
"Unit";"Marine";"Barracks";60;1
"Unit";"Marine";"Barracks";61;1
"Building";"BarracksTechLab";NA;62;0
"Building";"BarracksReactor";NA;62;0
"Unit";"Marine";"Barracks";64;1
"Unit";"Marine";"Barracks";65;1
"Unit";"Marine";"Barracks";67;1
"Unit";"Marine";"Barracks";68;1
"Unit";"Marauder";"Barracks";70;2
"Unit";"Marauder";"Barracks";73;2
"Building";"Starport";NA;75;0
"Building";"FactoryReactor";NA;75;0
"Unit";"Marauder";"Barracks";77;2
"Unit";"Marine";"Barracks";79;1
"Unit";"Marine";"Barracks";80;1
"Unit";"Marine";"Barracks";81;1
"Unit";"Marauder";"Barracks";82;2
"Unit";"Marine";"Barracks";84;1
"Unit";"Marauder";"Barracks";85;2
"Unit";"Marauder";"Barracks";87;2
"Unit";"Marine";"Barracks";89;1
"Unit";"Marine";"Barracks";90;1
"Unit";"Marine";"Barracks";91;1
"Unit";"Marauder";"Barracks";92;2
"Unit";"Medivac";"Starport";94;2
"Unit";"Medivac";"Starport";96;2
"Unit";"Marine";"Barracks";98;1
"Unit";"Marine";"Barracks";99;1
"Unit";"Marine";"Barracks";100;1
"Unit";"Marine";"Barracks";101;1
"Unit";"Marine";"Barracks";102;1
"Building";"Armory";NA;103;0
"Unit";"Marine";"Barracks";103;1
"Unit";"Marine";"Barracks";104;1
"Unit";"Marine";"Barracks";105;1
"Unit";"Medivac";"Starport";106;2
"Unit";"Marauder";"Barracks";108;2
"Unit";"Medivac";"Starport";110;2
"Unit";"Marine";"Barracks";112;1
"Unit";"Marine";"Barracks";113;1
"Unit";"Marauder";"Barracks";114;2
"Unit";"Marauder";"Barracks";116;2
"Unit";"Marine";"Barracks";118;1
"Unit";"Marine";"Barracks";119;1
"Unit";"Marine";"Barracks";122;1
"Unit";"Marine";"Barracks";123;1
"Unit";"Marine";"Barracks";124;1
"Unit";"Liberator";"Starport";125;3
"Unit";"Marine";"Barracks";128;1
"Unit";"Marine";"Barracks";129;1
"Unit";"Marauder";"Barracks";130;2
"Unit";"Marine";"Barracks";132;1
"Unit";"Marauder";"Barracks";133;2
"Unit";"Liberator";"Starport";135;3
"Unit";"Marine";"Barracks";138;1
"Unit";"Marine";"Barracks";139;1
"Unit";"Marauder";"Barracks";140;2
"Unit";"Medivac";"Starport";142;2
"Unit";"Marine";"Barracks";144;1
"Unit";"Marine";"Barracks";145;1
"Unit";"Marine";"Barracks";146;1
"Unit";"Marauder";"Barracks";147;2
"Unit";"Marine";"Barracks";150;1
"Unit";"Marine";"Barracks";151;1
"Unit";"Medivac";"Starport";152;2
"Unit";"Marine";"Barracks";154;1
"Unit";"Marine";"Barracks";155;1
"Unit";"Marine";"Barracks";156;1
"Unit";"Marine";"Barracks";157;1
"Unit";"Marine";"Barracks";158;1
"Unit";"Marine";"Barracks";159;1
"Unit";"Marauder";"Barracks";160;2
"Unit";"Marine";"Barracks";162;1
"Unit";"Marine";"Barracks";163;1
"Unit";"Marine";"Barracks";164;1
"Unit";"Marauder";"Barracks";165;2
"Unit";"Medivac";"Starport";169;2
"Unit";"Marine";"Barracks";171;1
"Unit";"Marine";"Barracks";172;1
"Unit";"Marine";"Barracks";173;1
"Unit";"Marine";"Barracks";174;1
"Unit";"Marine";"Barracks";175;1
"Unit";"Marine";"Barracks";176;1
"Unit";"Marine";"Barracks";177;1
"Unit";"Liberator";"Starport";178;3
"Unit";"Marine";"Barracks";181;1
"Building";"GhostAcademy";NA;182;0
"Unit";"Marauder";"Barracks";182;2
"Unit";"Marine";"Barracks";184;1
"Unit";"Marine";"Barracks";185;1
"Upgrade";"TerranInfantryWeaponsLevel2";"EngineeringBay";186;0
"Unit";"Liberator";"Starport";186;3
"Unit";"Marauder";"Barracks";189;2
"Unit";"Marauder";"Barracks";191;2
"Unit";"Marine";"Barracks";193;1
"Unit";"Marine";"Barracks";194;1
"Unit";"Marauder";"Barracks";195;2
"Unit";"Marine";"Barracks";197;1
"Unit";"Marine";"Barracks";198;1
"Unit";"Marine";"Barracks";199;1
"Unit";"Ghost";"Barracks";200;2
"Unit";"Ghost";"Barracks";202;2
"Unit";"Ghost";"Barracks";204;2
"Unit";"Marine";"Barracks";206;1
"Unit";"Marine";"Barracks";207;1
"Unit";"Marine";"Barracks";208;1
"Unit";"Marine";"Barracks";209;1
"Unit";"Marine";"Barracks";210;1
"Unit";"Marine";"Barracks";211;1
"Unit";"Ghost";"Barracks";212;2
"Unit";"Marine";"Barracks";214;1
"Unit";"Ghost";"Barracks";215;2
"Unit";"Marine";"Barracks";217;1
"Unit";"Marauder";"Barracks";218;2
"Unit";"Marine";"Barracks";220;1
"Unit";"Marine";"Barracks";221;1
"Unit";"Marauder";"Barracks";222;2
"Unit";"Marine";"Barracks";224;1
"Unit";"Marine";"Barracks";225;1
"Unit";"Marauder";"Barracks";226;2
"Unit";"Marine";"Barracks";228;1
"Unit";"Marine";"Barracks";229;1
"Unit";"Marine";"Barracks";230;1
"Upgrade";"SprayTerran";NA;231;0
"Upgrade";"PunisherGrenades";NA;231;0
"Upgrade";"SprayTerran";NA;231;0
"Upgrade";"ShieldWall";NA;231;0
"Upgrade";"TerranInfantryArmorsLevel1";NA;231;0
