"type";"unit_name";"on_building";"total_supply";"supply"
"Building";"Refinery";NA;15;0
"Building";"Barracks";NA;15;0
"Unit";"Reaper";"Barracks";19;1
"Building";"Refinery";NA;19;0
"Building";"Factory";NA;20;0
"Building";"CommandCenter";NA;19;0
"Building";"BarracksReactor";NA;21;0
"Unit";"Hellion";"Factory";24;2
"Unit";"Hellion";"Factory";24;2
"Building";"BarracksTechLab";NA;25;0
"Building";"Starport";NA;24;0
"Building";"BarracksTechLab";NA;32;0
"Unit";"Medivac";"Starport";32;2
"Unit";"Marine";"Barracks";41;1
"Building";"EngineeringBay";NA;41;0
"Building";"Refinery";NA;44;0
"Building";"Refinery";NA;44;0
"Building";"StarportReactor";NA;43;0
"Building";"Barracks";NA;41;0
"Building";"Barracks";NA;41;0
"Unit";"Marine";"Barracks";50;1
"Building";"Barracks";NA;46;0
"Building";"Barracks";NA;46;0
"Unit";"Marine";"Barracks";53;1
"Unit";"Medivac";"Starport";52;2
"Unit";"Medivac";"Starport";52;2
"Building";"BarracksReactor";NA;52;0
"Building";"BarracksTechLab";NA;53;0
"Unit";"Marauder";"Barracks";53;2
"Unit";"Marauder";"Barracks";55;2
"Upgrade";"Stimpack";"TechLab";46;0
"Unit";"Marine";"Barracks";60;1
"Unit";"Marine";"Barracks";60;1
"Building";"BarracksReactor";NA;53;0
"Unit";"Marine";"Barracks";60;1
"Unit";"Marine";"Barracks";62;1
"Unit";"Marine";"Barracks";67;1
"Unit";"Marine";"Barracks";67;1
"Unit";"Marine";"Barracks";67;1
"Unit";"Marine";"Barracks";67;1
"Upgrade";"TerranInfantryWeaponsLevel1";"EngineeringBay";52;0
"Unit";"Marauder";"Barracks";67;2
"Unit";"Marauder";"Barracks";67;2
"Unit";"Marauder";"Barracks";67;2
"Unit";"Marine";"Barracks";68;1
"Unit";"Marauder";"Barracks";72;2
"Unit";"Marauder";"Barracks";74;2
"Unit";"Marauder";"Barracks";76;2
"Unit";"Marine";"Barracks";79;1
"Unit";"Marine";"Barracks";79;1
"Unit";"Marine";"Barracks";79;1
"Unit";"Marine";"Barracks";79;1
"Unit";"Liberator";"Starport";68;3
"Unit";"Marauder";"Barracks";79;2
"Unit";"Marauder";"Barracks";81;2
