"Type";"UnitName";"OnBuilding";"TotalSupply";"Supply"
"Unit";"SCV";"Command Center";12;1
"Unit";"SCV";"Command Center";12;1
"Unit";"SCV";"Command Center";13;1
"Building";"SupplyDepot";NA;13;0
"Unit";"SCV";"Command Center";15;1
"Building";"Refinery";NA;14;0
"Unit";"SCV";"Command Center";15;1
"Unit";"SCV";"Command Center";16;1
"Unit";"SCV";"Command Center";17;1
"Building";"Barracks";NA;15;0
"Unit";"Reaper";"Barracks";19;1
"Unit";"SCV";"Command Center";19;1
"Unit";"SCV";"Command Center";20;1
"Building";"Refinery";NA;20;0
"Unit";"SCV";"Command Center";21;1
"Building";"SupplyDepot";NA;21;0
"Building";"Factory";NA;19;0
"Building";"BarracksReactor";NA;20;0
"Unit";"SCV";"Command Center";23;1
"Building";"CommandCenter";NA;19;0
"Unit";"SCV";"Command Center";23;1
"Unit";"SCV";"Command Center";25;1
"Unit";"Cyclone";"Factory";24;3
"Unit";"Cyclone";"Factory";25;3
"Unit";"SCV";"Command Center";29;1
"Unit";"SCV";"Command Center";29;1
"Unit";"Hellion";"Factory";26;2
"Building";"BarracksTechLab";NA;29;0
"Unit";"SCV";"Command Center";32;1
"Unit";"SCV";"Command Center";33;1
"Unit";"Hellion";"Factory";29;2
"Building";"SupplyDepot";NA;32;0
"Unit";"SCV";"Command Center";37;1
"Unit";"SCV";"Command Center";38;1
"Unit";"Marine";"Barracks";36;1
"Unit";"SCV";"Command Center";40;1
"Unit";"SCV";"Command Center";41;1
"Unit";"SCV";"Command Center";43;1
"Unit";"SCV";"Command Center";44;1
"Unit";"SCV";"Command Center";45;1
"Building";"FactoryReactor";NA;42;0
"Unit";"SCV";"Command Center";46;1
"Unit";"Marine";"Barracks";45;1
"Building";"Barracks";NA;40;0
"Building";"Barracks";NA;40;0
"Unit";"SCV";"Command Center";47;1
"Unit";"SCV";"Command Center";49;1
"Building";"EngineeringBay";NA;47;0
"Unit";"Marine";"Barracks";49;1
"Building";"Bunker";NA;47;0
"Unit";"Marine";"Barracks";50;1
"Unit";"Marine";"Barracks";50;1
"Unit";"SCV";"Command Center";50;1
"Unit";"Marine";"Barracks";51;1
"Unit";"Marine";"Barracks";51;1
"Unit";"SCV";"Command Center";53;1
"Unit";"SCV";"Command Center";55;1
"Unit";"Marine";"Barracks";52;1
"Building";"MissileTurret";NA;53;0
"Unit";"Marine";"Barracks";53;1
"Unit";"Marine";"Barracks";55;1
"Building";"Refinery";NA;53;0
"Building";"Starport";NA;50;0
"Building";"FactoryReactor";NA;50;0
"Unit";"Marine";"Barracks";56;1
"Unit";"Marine";"Barracks";57;1
"Building";"SupplyDepot";NA;56;0
"Building";"SupplyDepot";NA;58;0
"Unit";"SCV";"Command Center";65;1
"Unit";"SCV";"Command Center";65;1
"Unit";"Marine";"Barracks";65;1
"Unit";"Marine";"Barracks";65;1
"Unit";"Marine";"Barracks";65;1
"Unit";"Marine";"Barracks";65;1
"Upgrade";"Stimpack";"TechLab";45;0
"Unit";"Marine";"Barracks";65;1
"Unit";"SCV";"Command Center";65;1
"Unit";"SCV";"Command Center";67;1
"Unit";"Marine";"Barracks";67;1
"Unit";"Marine";"Barracks";68;1
"Unit";"Marine";"Barracks";71;1
"Unit";"Marine";"Barracks";71;1
"Building";"SupplyDepot";NA;71;0
"Building";"SupplyDepot";NA;71;0
"Building";"SupplyDepot";NA;71;0
"Unit";"Marine";"Barracks";72;1
"Unit";"Medivac";"Starport";67;2
"Unit";"Medivac";"Starport";67;2
"Building";"FactoryReactor";NA;67;0
"Unit";"SCV";"Command Center";78;1
"Unit";"SCV";"Command Center";78;1
"Building";"Barracks";NA;65;0
"Unit";"Marine";"Barracks";78;1
"Unit";"Marine";"Barracks";78;1
"Unit";"Marine";"Barracks";78;1
"Building";"Barracks";NA;67;0
"Building";"SupplyDepot";NA;78;0
"Building";"SupplyDepot";NA;78;0
"Unit";"Marauder";"Barracks";78;2
"Unit";"SCV";"Command Center";83;1
"Unit";"Marine";"Barracks";83;1
"Unit";"SCV";"Command Center";85;1
"Unit";"SCV";"Command Center";90;1
"Unit";"Medivac";"Starport";83;2
"Unit";"Medivac";"Starport";83;2
"Upgrade";"TerranInfantryWeaponsLevel1";"EngineeringBay";65;0
"Building";"BarracksTechLab";NA;90;0
"Unit";"SCV";"Command Center";93;1
"Unit";"Marine";"Barracks";90;1
"Unit";"Marine";"Barracks";90;1
"Building";"BarracksTechLab";NA;91;0
"Unit";"Marauder";"Barracks";90;2
"Building";"SupplyDepot";NA;93;0
"Unit";"Marine";"Barracks";93;1
"Unit";"Marine";"Barracks";93;1
"Unit";"Marine";"Barracks";103;1
"Unit";"Marine";"Barracks";103;1
"Unit";"Marauder";"Barracks";101;2
"Unit";"Marauder";"Barracks";103;2
"Unit";"Marauder";"Barracks";103;2
"Unit";"Marine";"Barracks";107;1
"Unit";"Marine";"Barracks";107;1
"Unit";"Marine";"Barracks";107;1
"Unit";"Marine";"Barracks";107;1
"Unit";"SCV";"Command Center";113;1
"Unit";"SCV";"Command Center";113;1
"Unit";"Marauder";"Barracks";107;2
"Unit";"Marauder";"Barracks";109;2
"Unit";"Marine";"Barracks";113;1
"Unit";"Marine";"Barracks";113;1
"Unit";"Medivac";"Starport";113;2
"Unit";"Marine";"Barracks";117;1
"Unit";"Marine";"Barracks";117;1
"Unit";"Marine";"Barracks";117;1
"Unit";"Medivac";"Starport";113;2
"Unit";"Marauder";"Barracks";119;2
"Unit";"Marauder";"Barracks";121;2
"Unit";"Marauder";"Barracks";124;2
"Unit";"Marine";"Barracks";132;1
"Unit";"Marine";"Barracks";132;1
"Building";"Refinery";NA;132;0
"Building";"SupplyDepot";NA;132;0
"Building";"SupplyDepot";NA;132;0
"Unit";"Marine";"Barracks";136;1
"Unit";"Marine";"Barracks";136;1
"Unit";"Marauder";"Barracks";138;2
