"Type";"UnitName";"OnBuilding";"TotalSupply";"Supply"
"Unit";"SCV";"Command Center";12;1
"Unit";"SCV";"Command Center";12;1
"Unit";"SCV";"Command Center";13;1
"Building";"SupplyDepot";NA;13;0
"Unit";"SCV";"Command Center";15;1
"Building";"Refinery";NA;14;0
"Unit";"SCV";"Command Center";16;1
"Unit";"SCV";"Command Center";16;1
"Unit";"SCV";"Command Center";17;1
"Building";"Barracks";NA;15;0
"Unit";"Marine";"Barracks";19;1
"Unit";"SCV";"Command Center";20;1
"Building";"Refinery";NA;20;0
"Unit";"SCV";"Command Center";20;1
"Building";"Factory";NA;19;0
"Building";"BarracksReactor";NA;20;0
"Unit";"SCV";"Command Center";21;1
"Building";"SupplyDepot";NA;21;0
"Unit";"SCV";"Command Center";23;1
"Building";"CommandCenter";NA;19;0
"Unit";"Marine";"Barracks";23;1
"Unit";"SCV";"Command Center";24;1
"Unit";"Cyclone";"Factory";23;3
"Unit";"Cyclone";"Factory";23;3
"Unit";"SCV";"Command Center";25;1
"Building";"BarracksTechLab";NA;25;0
"Unit";"SCV";"Command Center";32;1
"Unit";"SCV";"Command Center";32;1
"Unit";"Hellion";"Factory";26;2
"Unit";"Hellion";"Factory";26;2
"Unit";"SCV";"Command Center";33;1
"Unit";"SCV";"Command Center";34;1
"Unit";"Marine";"Barracks";33;1
"Unit";"SCV";"Command Center";39;1
"Building";"SupplyDepot";NA;39;0
"Unit";"SCV";"Command Center";43;1
"Unit";"SCV";"Command Center";43;1
"Building";"FactoryTechLab";NA;42;0
"Unit";"Marine";"Barracks";42;1
"Building";"Barracks";NA;42;0
"Unit";"SCV";"Command Center";46;1
"Unit";"Marine";"Barracks";46;1
"Unit";"SCV";"Command Center";46;1
"Unit";"SCV";"Command Center";48;1
"Unit";"Marine";"Barracks";47;1
"Unit";"Marine";"Barracks";47;1
"Unit";"SCV";"Command Center";49;1
"Building";"SupplyDepot";NA;47;0
"Building";"SupplyDepot";NA;48;0
"Unit";"Marine";"Barracks";49;1
"Unit";"SCV";"Command Center";49;1
"Unit";"SCV";"Command Center";52;1
"Building";"EngineeringBay";NA;49;0
"Building";"SupplyDepot";NA;47;0
"Building";"Bunker";NA;47;0
"Unit";"SCV";"Command Center";55;1
"Building";"SupplyDepot";NA;53;0
"Unit";"SCV";"Command Center";55;1
"Upgrade";"Stimpack";"TechLab";43;0
"Unit";"Marine";"Barracks";56;1
"Unit";"Marine";"Barracks";56;1
"Unit";"Marine";"Barracks";56;1
"Unit";"SCV";"Command Center";56;1
"Unit";"SCV";"Command Center";57;1
"Building";"Barracks";NA;49;0
"Unit";"SCV";"Command Center";61;1
"Unit";"SCV";"Command Center";62;1
"Unit";"SCV";"Command Center";64;1
"Unit";"SCV";"Command Center";64;1
"Unit";"Marine";"Barracks";63;1
"Unit";"Marine";"Barracks";63;1
"Building";"Starport";NA;58;0
"Unit";"Marine";"Barracks";65;1
"Unit";"Marine";"Barracks";65;1
"Building";"FactoryReactor";NA;58;0
"Unit";"SCV";"Command Center";69;1
"Unit";"SCV";"Command Center";69;1
"Unit";"Marine";"Barracks";67;1
"Building";"SupplyDepot";NA;66;0
"Building";"SupplyDepot";NA;69;0
"Unit";"Marine";"Barracks";71;1
"Unit";"SCV";"Command Center";71;1
"Building";"Refinery";NA;69;0
"Unit";"SCV";"Command Center";73;1
"Building";"Refinery";NA;71;0
"Unit";"Marine";"Barracks";71;1
"Unit";"Marauder";"Barracks";71;2
"Unit";"SCV";"Command Center";75;1
"Unit";"SCV";"Command Center";76;1
"Building";"SupplyDepot";NA;74;0
"Building";"Barracks";NA;65;0
"Building";"SupplyDepot";NA;74;0
"Unit";"Marine";"Barracks";76;1
"Unit";"Marine";"Barracks";76;1
"Building";"Barracks";NA;69;0
"Unit";"SCV";"Command Center";80;1
"Unit";"SCV";"Command Center";81;1
"Building";"FactoryTechLab";NA;80;0
"Unit";"Medivac";"Starport";76;2
"Unit";"Medivac";"Starport";78;2
"Building";"BarracksTechLab";NA;82;0
"Unit";"Marauder";"Barracks";82;2
"Unit";"Marauder";"Barracks";82;2
"Unit";"Marine";"Barracks";86;1
"Unit";"Marine";"Barracks";86;1
"Upgrade";"TerranInfantryWeaponsLevel1";"EngineeringBay";67;0
"Unit";"Marine";"Barracks";94;1
"Building";"BarracksReactor";NA;84;0
"Unit";"Marine";"Barracks";94;1
"Unit";"Medivac";"Starport";88;2
"Unit";"Marauder";"Barracks";94;2
"Unit";"Marine";"Barracks";96;1
"Unit";"Marine";"Barracks";96;1
"Building";"GhostAcademy";NA;94;0
"Unit";"Medivac";"Starport";94;2
"Unit";"Marine";"Barracks";98;1
"Unit";"Marine";"Barracks";98;1
"Unit";"Marauder";"Barracks";98;2
"Unit";"Marauder";"Barracks";98;2
"Unit";"Marauder";"Barracks";102;2
"Building";"SupplyDepot";NA;108;0
"Building";"SupplyDepot";NA;112;0
"Unit";"Liberator";"Starport";104;3
"Unit";"Ghost";"Barracks";112;2
"Unit";"Marine";"Barracks";114;1
"Unit";"Marine";"Barracks";114;1
"Unit";"Marine";"Barracks";114;1
"Unit";"Marine";"Barracks";114;1
"Unit";"Liberator";"Starport";106;3
"Unit";"Ghost";"Barracks";114;2
"Unit";"Ghost";"Barracks";114;2
"Building";"MissileTurret";NA;128;0
"Unit";"Ghost";"Barracks";128;2
"Building";"SupplyDepot";NA;130;0
"Building";"SupplyDepot";NA;130;0
"Unit";"SCV";"Command Center";132;1
"Unit";"Marine";"Barracks";132;1
"Unit";"Marine";"Barracks";132;1
"Unit";"SCV";"Command Center";132;1
"Unit";"Marine";"Barracks";132;1
"Unit";"Marine";"Barracks";132;1
"Unit";"Marine";"Barracks";132;1
"Unit";"Liberator";"Starport";130;3
"Upgrade";"TerranInfantryArmorsLevel1";"EngineeringBay";114;0
"Unit";"Ghost";"Barracks";133;2
"Unit";"Liberator";"Starport";132;3
"Unit";"Marine";"Barracks";142;1
"Unit";"Marine";"Barracks";142;1
"Unit";"Marine";"Barracks";142;1
"Unit";"Marine";"Barracks";142;1
"Unit";"Marauder";"Barracks";142;2
"Unit";"Marauder";"Barracks";142;2
"Unit";"Marauder";"Barracks";142;2
"Unit";"Marine";"Barracks";147;1
"Unit";"Marine";"Barracks";148;1
"Unit";"Marine";"Barracks";149;1
"Unit";"Marine";"Barracks";150;1
"Unit";"Marauder";"Barracks";151;2
"Unit";"Marauder";"Barracks";153;2
"Unit";"Marine";"Barracks";155;1
"Unit";"Marine";"Barracks";157;1
"Unit";"Marine";"Barracks";158;1
"Unit";"Marine";"Barracks";159;1
"Unit";"Marine";"Barracks";160;1
"Unit";"Liberator";"Starport";147;3
"Unit";"Liberator";"Starport";148;3
"Unit";"Marine";"Barracks";163;1
"Unit";"Marine";"Barracks";165;1
"Unit";"Marauder";"Barracks";161;2
"Unit";"Marine";"Barracks";166;1
"Unit";"Marine";"Barracks";167;1
"Unit";"Marine";"Barracks";168;1
"Unit";"Marine";"Barracks";170;1
"Unit";"Liberator";"Starport";177;3
"Unit";"Liberator";"Starport";177;3
"Unit";"Ghost";"Barracks";184;2
"Unit";"Ghost";"Barracks";184;2
"Building";"Armory";NA;181;0
"Unit";"Marine";"Barracks";184;1
"Unit";"Marine";"Barracks";187;1
"Unit";"Marine";"Barracks";190;1
"Unit";"Marine";"Barracks";190;1
"Unit";"Ghost";"Barracks";184;2
"Building";"CommandCenter";NA;177;0
"Building";"EngineeringBay";NA;198;0
"Unit";"SCV";"Command Center";200;1
"Unit";"SCV";"Command Center";200;1
"Unit";"Marauder";"Barracks";200;2
"Unit";"Marauder";"Barracks";200;2
"Unit";"SCV";"Command Center";200;1
"Unit";"SCV";"Command Center";200;1
"Unit";"SCV";"Command Center";201;1
"Unit";"Marauder";"Barracks";207;2
"Unit";"Marauder";"Barracks";207;2
"Unit";"Marauder";"Barracks";207;2
"Upgrade";"PersonalCloaking";"GhostAcademy";198;0
"Unit";"Marine";"Barracks";209;1
"Unit";"Marine";"Barracks";209;1
"Unit";"Marine";"Barracks";215;1
"Unit";"Marine";"Barracks";215;1
"Unit";"Marauder";"Barracks";209;2
"Unit";"Marauder";"Barracks";211;2
"Unit";"Marauder";"Barracks";213;2
"Unit";"Marine";"Barracks";217;1
"Unit";"Marine";"Barracks";217;1
"Unit";"Marine";"Barracks";225;1
"Unit";"Marine";"Barracks";225;1
"Unit";"Marine";"Barracks";225;1
"Unit";"Medivac";"Starport";219;2
"Unit";"Liberator";"Starport";217;3
"Unit";"Ghost";"Barracks";227;2
"Upgrade";"TerranInfantryWeaponsLevel2";"EngineeringBay";206;0
"Unit";"Medivac";"Starport";230;2
"Unit";"Ghost";"Barracks";235;2
"Unit";"Ghost";"Barracks";235;2
"Unit";"SCV";"Command Center";239;1
"Unit";"SCV";"Command Center";239;1
