"type";"unit_name";"on_building";"total_supply";"supply"
"Building";"Refinery";NA;14;0
"Building";"Barracks";NA;15;0
"Unit";"Reaper";"Barracks";19;1
"Unit";"Marine";"Barracks";21;1
"Building";"Factory";NA;20;0
"Building";"Refinery";NA;23;0
"Building";"BarracksReactor";NA;23;0
"Building";"Bunker";NA;23;0
"Unit";"Cyclone";"Factory";24;3
"Unit";"Marine";"Barracks";25;1
"Unit";"Marine";"Barracks";25;1
"Unit";"Marine";"Barracks";29;1
