"Type";"UnitName";"OnBuilding";"TotalSupply";"Supply"
"Unit";"SCV";"Command Center";12;1
"Unit";"SCV";"Command Center";12;1
"Unit";"SCV";"Command Center";13;1
"Building";"SupplyDepot";NA;13;0
"Unit";"SCV";"Command Center";15;1
"Unit";"SCV";"Command Center";15;1
"Building";"Refinery";NA;15;0
"Unit";"SCV";"Command Center";16;1
"Building";"Barracks";NA;15;0
"Unit";"SCV";"Command Center";17;1
"Unit";"Reaper";"Barracks";19;1
"Unit";"SCV";"Command Center";19;1
"Unit";"SCV";"Command Center";21;1
"Unit";"SCV";"Command Center";22;1
"Unit";"SCV";"Command Center";23;1
"Building";"Refinery";NA;23;0
"Building";"Barracks";NA;22;0
"Unit";"SCV";"Command Center";24;1
"Building";"SupplyDepot";NA;24;0
"Building";"BarracksReactor";NA;23;0
"Building";"BarracksTechLab";NA;25;0
"Unit";"SCV";"Command Center";25;1
"Building";"Barracks";NA;23;0
"Unit";"Marine";"Barracks";25;1
"Unit";"Marine";"Barracks";25;1
"Unit";"SCV";"Command Center";25;1
"Unit";"SCV";"Command Center";28;1
"Building";"Factory";NA;25;0
"Unit";"Marine";"Barracks";26;1
"Unit";"SCV";"Command Center";29;1
"Building";"BarracksReactor";NA;26;0
"Building";"CommandCenter";NA;24;0
"Building";"SupplyDepot";NA;30;0
"Unit";"SCV";"Command Center";31;1
"Unit";"Marine";"Barracks";31;1
"Unit";"SCV";"Command Center";33;1
"Building";"Starport";NA;31;0
"Unit";"Marine";"Barracks";32;1
"Unit";"Marine";"Barracks";32;1
"Building";"FactoryReactor";NA;31;0
"Unit";"SCV";"Command Center";37;1
"Unit";"Marine";"Barracks";37;1
"Unit";"Marine";"Barracks";37;1
"Unit";"Marauder";"Barracks";37;2
"Unit";"SCV";"Command Center";37;1
"Unit";"Marine";"Barracks";37;1
"Unit";"Marine";"Barracks";37;1
"Building";"SupplyDepot";NA;38;0
"Unit";"Medivac";"Starport";38;2
"Unit";"Medivac";"Starport";38;2
"Unit";"Marine";"Barracks";43;1
"Unit";"SCV";"Command Center";45;1
"Unit";"SCV";"Command Center";45;1
"Unit";"Marine";"Barracks";45;1
"Unit";"Marauder";"Barracks";42;2
"Unit";"Marine";"Barracks";45;1
"Unit";"Marine";"Barracks";45;1
"Upgrade";"Stimpack";"TechLab";32;0
"Unit";"SCV";"Command Center";50;1
"Unit";"SCV";"Command Center";51;1
"Building";"FactoryReactor";NA;45;0
"Unit";"SCV";"Command Center";57;1
"Building";"SupplyDepot";NA;57;0
"Unit";"Medivac";"Starport";55;2
"Unit";"SCV";"Command Center";59;1
"Unit";"Marine";"Barracks";59;1
"Unit";"Marine";"Barracks";59;1
"Unit";"SCV";"Command Center";60;1
"Unit";"SCV";"Command Center";62;1
"Building";"Refinery";NA;60;0
"Building";"Refinery";NA;60;0
"Unit";"SCV";"Command Center";65;1
"Unit";"Medivac";"Starport";60;2
"Unit";"SCV";"Command Center";67;1
"Unit";"SCV";"Command Center";67;1
"Unit";"SCV";"Command Center";70;1
"Unit";"SCV";"Command Center";71;1
"Unit";"Marine";"Barracks";71;1
"Unit";"Marine";"Barracks";71;1
"Unit";"Marine";"Barracks";71;1
"Unit";"Marine";"Barracks";71;1
"Unit";"Marine";"Barracks";71;1
"Unit";"SCV";"Command Center";72;1
"Unit";"SCV";"Command Center";79;1
"Unit";"Marine";"Barracks";74;1
"Unit";"Marine";"Barracks";75;1
"Unit";"SCV";"Command Center";79;1
"Unit";"Marauder";"Barracks";79;2
"Unit";"SCV";"Command Center";84;1
"Building";"Barracks";NA;72;0
"Building";"Barracks";NA;72;0
"Unit";"Medivac";"Starport";80;2
"Building";"SupplyDepot";NA;84;0
"Building";"SupplyDepot";NA;84;0
"Building";"SupplyDepot";NA;86;0
"Building";"SupplyDepot";NA;86;0
"Building";"BarracksTechLab";NA;89;0
"Unit";"SCV";"Command Center";89;1
"Building";"BarracksTechLab";NA;89;0
"Unit";"SCV";"Command Center";89;1
"Building";"SupplyDepot";NA;89;0
"Unit";"Marine";"Barracks";89;1
"Unit";"Marine";"Barracks";89;1
"Unit";"Marine";"Barracks";89;1
"Unit";"Marine";"Barracks";89;1
"Building";"SupplyDepot";NA;89;0
"Unit";"Marauder";"Barracks";89;2
"Unit";"SCV";"Command Center";90;1
"Unit";"SCV";"Command Center";91;1
"Unit";"Marauder";"Barracks";90;2
"Unit";"Marauder";"Barracks";91;2
"Unit";"Marine";"Barracks";95;1
"Unit";"Marine";"Barracks";95;1
"Unit";"Marine";"Barracks";95;1
"Unit";"Marine";"Barracks";95;1
"Unit";"SCV";"Command Center";98;1
"Unit";"Liberator";"Starport";89;3
"Unit";"Liberator";"Starport";89;3
"Unit";"Marauder";"Barracks";98;2
"Unit";"Marine";"Barracks";103;1
"Unit";"SCV";"Command Center";114;1
"Unit";"Marauder";"Barracks";108;2
"Unit";"Marauder";"Barracks";108;2
"Unit";"Marauder";"Barracks";114;2
"Building";"SupplyDepot";NA;116;0
"Building";"SupplyDepot";NA;116;0
"Unit";"Marine";"Barracks";122;1
"Unit";"Marine";"Barracks";122;1
"Unit";"Marine";"Barracks";122;1
"Unit";"Marauder";"Barracks";118;2
"Unit";"Marine";"Barracks";124;1
"Unit";"Marine";"Barracks";124;1
"Unit";"Marauder";"Barracks";122;2
"Unit";"Marine";"Barracks";124;1
"Unit";"Marine";"Barracks";125;1
"Unit";"Marine";"Barracks";126;1
"Unit";"Marine";"Barracks";127;1
"Unit";"Marine";"Barracks";129;1
"Unit";"Marine";"Barracks";130;1
"Unit";"Liberator";"Starport";124;3
"Unit";"Liberator";"Starport";124;3
"Unit";"Marine";"Barracks";139;1
"Unit";"Marine";"Barracks";139;1
"Building";"SupplyDepot";NA;139;0
"Building";"SupplyDepot";NA;139;0
"Unit";"Marine";"Barracks";139;1
"Unit";"Marine";"Barracks";139;1
"Unit";"Marine";"Barracks";139;1
"Unit";"Marine";"Barracks";139;1
"Unit";"Marauder";"Barracks";139;2
