"Type";"UnitName";"OnBuilding";"TotalSupply";"Supply"
"Unit";"SCV";"Command Center";12;1
"Unit";"SCV";"Command Center";12;1
"Unit";"SCV";"Command Center";13;1
"Building";"SupplyDepot";NA;13;0
"Unit";"SCV";"Command Center";15;1
"Unit";"SCV";"Command Center";15;1
"Building";"Refinery";NA;15;0
"Unit";"SCV";"Command Center";16;1
"Unit";"SCV";"Command Center";17;1
"Building";"Barracks";NA;15;0
"Unit";"Reaper";"Barracks";19;1
"Unit";"SCV";"Command Center";19;1
"Building";"SupplyDepot";NA;19;0
"Unit";"SCV";"Command Center";20;1
"Unit";"Marine";"Barracks";19;1
"Unit";"SCV";"Command Center";21;1
"Building";"Refinery";NA;23;0
"Unit";"SCV";"Command Center";23;1
"Building";"CommandCenter";NA;19;0
"Unit";"SCV";"Command Center";24;1
"Building";"Factory";NA;23;0
"Building";"BarracksReactor";NA;23;0
"Unit";"SCV";"Command Center";25;1
"Unit";"SCV";"Command Center";26;1
"Unit";"Marine";"Barracks";26;1
"Unit";"Marine";"Barracks";26;1
"Unit";"SCV";"Command Center";27;1
"Unit";"SCV";"Command Center";28;1
"Building";"Starport";NA;26;0
"Unit";"Marine";"Barracks";28;1
"Unit";"Marine";"Barracks";29;1
"Unit";"SCV";"Command Center";30;1
"Unit";"SCV";"Command Center";31;1
"Unit";"SCV";"Command Center";34;1
"Unit";"SCV";"Command Center";35;1
"Building";"SupplyDepot";NA;32;0
"Unit";"Marine";"Barracks";35;1
"Unit";"Marine";"Barracks";35;1
"Unit";"Medivac";"Starport";32;2
"Unit";"SCV";"Command Center";38;1
"Unit";"SCV";"Command Center";38;1
"Unit";"Marine";"Barracks";38;1
"Unit";"Marine";"Barracks";39;1
"Unit";"SCV";"Command Center";42;1
"Unit";"SCV";"Command Center";42;1
"Building";"SupplyDepot";NA;40;0
"Building";"StarportTechLab";NA;44;0
"Building";"FactoryTechLab";NA;44;0
"Unit";"SCV";"Command Center";46;1
"Unit";"SCV";"Command Center";46;1
"Building";"Barracks";NA;37;0
"Building";"Barracks";NA;37;0
"Unit";"Marine";"Barracks";48;1
"Unit";"Marine";"Barracks";48;1
"Unit";"SCV";"Command Center";48;1
"Unit";"SCV";"Command Center";50;1
"Building";"SupplyDepot";NA;48;0
"Building";"EngineeringBay";NA;48;0
"Building";"Bunker";NA;46;0
"Unit";"SCV";"Command Center";54;1
"Unit";"SCV";"Command Center";54;1
"Unit";"Marine";"Barracks";50;1
"Unit";"Marine";"Barracks";51;1
"Building";"Refinery";NA;50;0
"Unit";"SCV";"Command Center";54;1
"Unit";"SCV";"Command Center";54;1
"Unit";"Raven";"Starport";48;2
"Unit";"Marauder";"Barracks";54;2
"Unit";"SCV";"Command Center";58;1
"Unit";"SCV";"Command Center";58;1
"Unit";"Marine";"Barracks";58;1
"Unit";"Marine";"Barracks";58;1
"Building";"SupplyDepot";NA;60;0
"Building";"FactoryReactor";NA;57;0
"Unit";"SCV";"Command Center";64;1
"Unit";"Marine";"Barracks";66;1
"Unit";"Marauder";"Barracks";64;2
"Unit";"SCV";"Command Center";68;1
"Unit";"Marine";"Barracks";68;1
"Building";"SupplyDepot";NA;68;0
"Unit";"SCV";"Command Center";72;1
"Unit";"Marauder";"Barracks";68;2
"Unit";"SCV";"Command Center";72;1
"Unit";"Marine";"Barracks";69;1
"Unit";"Marine";"Barracks";70;1
"Building";"StarportReactor";NA;68;0
"Unit";"Marine";"Barracks";74;1
"Building";"Refinery";NA;74;0
"Unit";"Marauder";"Barracks";75;2
"Building";"SupplyDepot";NA;80;0
"Building";"SupplyDepot";NA;80;0
"Building";"Barracks";NA;69;0
"Unit";"Marine";"Barracks";80;1
"Building";"Barracks";NA;72;0
"Unit";"Marine";"Barracks";80;1
"Building";"CommandCenter";NA;62;0
"Unit";"Marauder";"Barracks";80;2
"Unit";"SCV";"Command Center";83;1
"Building";"SupplyDepot";NA;83;0
"Unit";"Medivac";"Starport";80;2
"Unit";"Medivac";"Starport";80;2
"Unit";"Marauder";"Barracks";83;2
"Unit";"SCV";"Command Center";87;1
"Unit";"SCV";"Command Center";87;1
"Building";"BarracksTechLab";NA;85;0
"Unit";"Marauder";"Barracks";85;2
"Unit";"Marine";"Barracks";88;1
"Unit";"Marine";"Barracks";88;1
"Unit";"SCV";"Command Center";94;1
"Upgrade";"Stimpack";"TechLab";68;0
"Building";"BarracksReactor";NA;85;0
"Unit";"Medivac";"Starport";92;2
"Unit";"Marine";"Barracks";98;1
"Unit";"Marine";"Barracks";98;1
"Unit";"Marine";"Barracks";98;1
"Unit";"Marine";"Barracks";98;1
"Unit";"SCV";"Command Center";101;1
"Unit";"SCV";"Command Center";101;1
"Unit";"Marine";"Barracks";100;1
"Unit";"SCV";"Command Center";107;1
"Unit";"Marine";"Barracks";101;1
"Unit";"Marine";"Barracks";101;1
"Unit";"Marauder";"Barracks";103;2
"Unit";"Marine";"Barracks";110;1
"Building";"SupplyDepot";NA;106;0
"Unit";"Marauder";"Barracks";110;2
"Upgrade";"TerranInfantryWeaponsLevel1";"EngineeringBay";83;0
"Unit";"Marine";"Barracks";110;1
"Building";"EngineeringBay";NA;110;0
"Unit";"Marine";"Barracks";110;1
"Unit";"Marine";"Barracks";111;1
"Unit";"Marine";"Barracks";116;1
"Unit";"Marine";"Barracks";116;1
"Unit";"Marine";"Barracks";116;1
"Unit";"Marine";"Barracks";118;1
"Unit";"Marauder";"Barracks";116;2
"Unit";"Marauder";"Barracks";119;2
"Unit";"Marine";"Barracks";120;1
"Building";"Armory";NA;110;0
"Unit";"SCV";"Command Center";121;1
"Unit";"Medivac";"Starport";120;2
"Unit";"Marine";"Barracks";121;1
"Unit";"Marine";"Barracks";122;1
"Unit";"Marauder";"Barracks";123;2
"Unit";"Marine";"Barracks";129;1
"Unit";"Marine";"Barracks";129;1
"Unit";"Marine";"Barracks";129;1
"Unit";"SCV";"Command Center";131;1
"Unit";"SCV";"Command Center";131;1
"Unit";"Marauder";"Barracks";129;2
"Unit";"Marine";"Barracks";133;1
"Unit";"Marine";"Barracks";137;1
"Unit";"Marine";"Barracks";137;1
"Unit";"Marine";"Barracks";138;1
"Unit";"Marauder";"Barracks";135;2
"Unit";"Medivac";"Starport";133;2
"Building";"SupplyDepot";NA;144;0
"Unit";"Marine";"Barracks";150;1
"Unit";"Marine";"Barracks";150;1
"Unit";"Marine";"Barracks";150;1
"Unit";"Marine";"Barracks";150;1
"Unit";"Marine";"Barracks";150;1
"Unit";"Marauder";"Barracks";150;2
"Unit";"Marauder";"Barracks";150;2
"Unit";"Marine";"Barracks";152;1
"Unit";"Marine";"Barracks";153;1
"Unit";"Marine";"Barracks";154;1
"Unit";"Marine";"Barracks";155;1
"Unit";"Medivac";"Starport";152;2
"Unit";"Marine";"Barracks";159;1
"Unit";"Marauder";"Barracks";156;2
"Unit";"Marauder";"Barracks";157;2
"Unit";"SCV";"Command Center";161;1
"Unit";"SCV";"Command Center";161;1
"Unit";"SCV";"Command Center";161;1
"Building";"SupplyDepot";NA;161;0
"Unit";"Marine";"Barracks";161;1
"Unit";"Marine";"Barracks";162;1
"Unit";"Marine";"Barracks";163;1
"Building";"GhostAcademy";NA;161;0
"Unit";"Marine";"Barracks";164;1
"Unit";"Marine";"Barracks";167;1
"Unit";"SCV";"Command Center";172;1
"Unit";"SCV";"Command Center";173;1
"Unit";"Marine";"Barracks";170;1
"Unit";"Marauder";"Barracks";167;2
"Unit";"Medivac";"Starport";170;2
"Unit";"Medivac";"Starport";170;2
"Unit";"Marine";"Barracks";179;1
"Unit";"Marine";"Barracks";179;1
"Unit";"Marine";"Barracks";179;1
"Unit";"Marine";"Barracks";179;1
"Unit";"SCV";"Command Center";185;1
"Unit";"SCV";"Command Center";185;1
"Unit";"SCV";"Command Center";185;1
"Building";"Refinery";NA;185;0
"Building";"Barracks";NA;170;0
"Building";"Barracks";NA;170;0
"Unit";"Ghost";"Barracks";182;2
"Building";"Barracks";NA;170;0
"Unit";"Ghost";"Barracks";182;2
"Unit";"Ghost";"Barracks";183;2
"Unit";"Marine";"Barracks";189;1
"Unit";"Marine";"Barracks";190;1
"Building";"Refinery";NA;185;0
"Unit";"Marine";"Barracks";194;1
"Unit";"Marine";"Barracks";194;1
"Building";"SupplyDepot";NA;194;0
"Unit";"Medivac";"Starport";193;2
"Unit";"Medivac";"Starport";193;2
"Unit";"Marine";"Barracks";196;1
"Unit";"Marine";"Barracks";198;1
"Unit";"Marine";"Barracks";202;1
"Unit";"Marine";"Barracks";203;1
"Unit";"Marine";"Barracks";204;1
"Unit";"Marine";"Barracks";206;1
"Unit";"Marauder";"Barracks";200;2
"Building";"BarracksTechLab";NA;206;0
"Building";"BarracksTechLab";NA;206;0
"Upgrade";"TerranInfantryWeaponsLevel2";"EngineeringBay";161;0
"Unit";"SCV";"Command Center";218;1
"Unit";"SCV";"Command Center";218;1
"Unit";"Marine";"Barracks";212;1
"Unit";"Marine";"Barracks";213;1
"Unit";"Marauder";"Barracks";210;2
"Unit";"Marine";"Barracks";214;1
"Unit";"Marine";"Barracks";215;1
"Unit";"Marauder";"Barracks";211;2
"Building";"BarracksReactor";NA;206;0
"Building";"SupplyDepot";NA;218;0
"Building";"SupplyDepot";NA;218;0
"Unit";"Ghost";"Barracks";216;2
"Building";"SupplyDepot";NA;218;0
"Upgrade";"TerranInfantryArmorsLevel1";"EngineeringBay";182;0
"Unit";"Marine";"Barracks";220;1
"Unit";"Marine";"Barracks";221;1
"Unit";"Marine";"Barracks";222;1
"Unit";"Marine";"Barracks";224;1
"Unit";"Marine";"Barracks";225;1
"Unit";"Marauder";"Barracks";222;2
"Unit";"Ghost";"Barracks";221;2
"Unit";"Marine";"Barracks";228;1
"Unit";"Marine";"Barracks";228;1
"Unit";"Marine";"Barracks";228;1
"Unit";"Marauder";"Barracks";228;2
"Unit";"Marine";"Barracks";235;1
"Unit";"Marine";"Barracks";235;1
"Unit";"Marauder";"Barracks";232;2
"Unit";"Marauder";"Barracks";235;2
"Unit";"Marine";"Barracks";244;1
"Unit";"Marine";"Barracks";244;1
"Unit";"Marine";"Barracks";244;1
"Unit";"Marine";"Barracks";244;1
"Unit";"Marine";"Barracks";244;1
"Unit";"Marauder";"Barracks";244;2
"Unit";"Marauder";"Barracks";244;2
"Building";"CommandCenter";NA;218;0
"Unit";"Marine";"Barracks";250;1
"Unit";"Marine";"Barracks";250;1
"Unit";"Marine";"Barracks";250;1
"Unit";"Marauder";"Barracks";250;2
"Unit";"Marine";"Barracks";250;1
"Unit";"Marine";"Barracks";255;1
"Unit";"Marine";"Barracks";255;1
"Unit";"Marine";"Barracks";255;1
"Unit";"Marine";"Barracks";262;1
"Unit";"Marine";"Barracks";262;1
"Unit";"Marine";"Barracks";262;1
"Unit";"Marine";"Barracks";271;1
"Unit";"Marine";"Barracks";271;1
"Unit";"Marine";"Barracks";271;1
"Unit";"Marine";"Barracks";271;1
"Building";"Starport";NA;268;0
"Unit";"Marine";"Barracks";271;1
"Building";"Starport";NA;268;0
"Unit";"Marauder";"Barracks";271;2
"Unit";"Marauder";"Barracks";271;2
"Unit";"Marauder";"Barracks";271;2
"Unit";"Marauder";"Barracks";271;2
"Unit";"Marine";"Barracks";271;1
"Unit";"Marine";"Barracks";271;1
"Unit";"Marine";"Barracks";272;1
"Unit";"Marauder";"Barracks";271;2
"Unit";"Marauder";"Barracks";276;2
"Unit";"Liberator";"Starport";271;3
"Unit";"Liberator";"Starport";271;3
"Unit";"Marine";"Barracks";284;1
"Unit";"Marine";"Barracks";284;1
"Unit";"Marine";"Barracks";284;1
"Unit";"Marine";"Barracks";287;1
"Unit";"Marine";"Barracks";287;1
"Unit";"Marauder";"Barracks";287;2
"Unit";"Marine";"Barracks";289;1
"Unit";"Ghost";"Barracks";284;2
"Unit";"Ghost";"Barracks";284;2
"Unit";"Ghost";"Barracks";284;2
"Building";"StarportReactor";NA;284;0
"Building";"StarportReactor";NA;284;0
"Unit";"Marine";"Barracks";291;1
"Building";"Starport";NA;284;0
"Upgrade";"TerranInfantryWeaponsLevel3";"EngineeringBay";248;0
