"Type";"UnitName";"OnBuilding";"TotalSupply";"Supply"
"Unit";"SCV";"Command Center";12;1
"Unit";"SCV";"Command Center";12;1
"Unit";"SCV";"Command Center";13;1
"Building";"SupplyDepot";NA;13;0
"Unit";"SCV";"Command Center";15;1
"Building";"Refinery";NA;14;0
"Unit";"SCV";"Command Center";15;1
"Unit";"SCV";"Command Center";16;1
"Unit";"SCV";"Command Center";17;1
"Building";"Barracks";NA;15;0
"Unit";"Marine";"Barracks";19;1
"Unit";"SCV";"Command Center";20;1
"Unit";"SCV";"Command Center";20;1
"Building";"Refinery";NA;20;0
"Unit";"SCV";"Command Center";21;1
"Building";"SupplyDepot";NA;21;0
"Building";"Factory";NA;20;0
"Building";"BarracksReactor";NA;20;0
"Unit";"SCV";"Command Center";23;1
"Building";"CommandCenter";NA;19;0
"Unit";"Marine";"Barracks";23;1
"Unit";"SCV";"Command Center";24;1
"Unit";"Cyclone";"Factory";24;3
"Unit";"Cyclone";"Factory";24;3
"Unit";"SCV";"Command Center";26;1
"Building";"BarracksTechLab";NA;25;0
"Unit";"SCV";"Command Center";32;1
"Unit";"SCV";"Command Center";33;1
"Unit";"Hellion";"Factory";32;2
"Unit";"Hellion";"Factory";32;2
"Unit";"Marine";"Barracks";33;1
"Unit";"Marine";"Barracks";40;1
"Unit";"SCV";"Command Center";40;1
"Building";"FactoryTechLab";NA;40;0
"Unit";"SCV";"Command Center";42;1
"Unit";"Marine";"Barracks";42;1
"Unit";"SCV";"Command Center";44;1
"Unit";"Marine";"Barracks";44;1
"Unit";"SCV";"Command Center";44;1
"Unit";"SCV";"Command Center";44;1
"Unit";"SCV";"Command Center";47;1
"Building";"SupplyDepot";NA;44;0
"Unit";"Marine";"Barracks";46;1
"Building";"EngineeringBay";NA;44;0
"Unit";"SCV";"Command Center";47;1
"Unit";"SCV";"Command Center";50;1
"Unit";"SCV";"Command Center";51;1
"Unit";"Marine";"Barracks";51;1
"Building";"Bunker";NA;48;0
"Unit";"SCV";"Command Center";51;1
"Building";"Barracks";NA;40;0
"Upgrade";"Stimpack";"TechLab";42;0
"Unit";"SCV";"Command Center";55;1
"Unit";"SCV";"Command Center";55;1
"Unit";"Marine";"Barracks";55;1
"Building";"Barracks";NA;51;0
"Unit";"Marine";"Barracks";55;1
"Unit";"SCV";"Command Center";57;1
"Unit";"Marine";"Barracks";55;1
"Unit";"SCV";"Command Center";57;1
"Unit";"Marine";"Barracks";57;1
"Unit";"SCV";"Command Center";59;1
"Unit";"SCV";"Command Center";61;1
"Building";"Starport";NA;55;0
"Unit";"Marine";"Barracks";62;1
"Unit";"Marine";"Barracks";62;1
"Unit";"SCV";"Command Center";63;1
"Unit";"SCV";"Command Center";64;1
"Building";"FactoryReactor";NA;58;0
"Building";"SupplyDepot";NA;62;0
"Building";"Barracks";NA;57;0
"Building";"Barracks";NA;57;0
"Unit";"Marauder";"Barracks";65;2
"Unit";"Marauder";"Barracks";65;2
"Unit";"SCV";"Command Center";69;1
"Unit";"SCV";"Command Center";69;1
"Building";"Refinery";NA;68;0
"Building";"Refinery";NA;69;0
"Unit";"Marine";"Barracks";69;1
"Unit";"Marine";"Barracks";69;1
"Building";"SupplyDepot";NA;69;0
"Building";"FactoryTechLab";NA;69;0
"Building";"BarracksTechLab";NA;73;0
"Unit";"Marauder";"Barracks";73;2
"Unit";"SCV";"Command Center";77;1
"Upgrade";"TerranInfantryWeaponsLevel1";"EngineeringBay";55;0
"Unit";"SCV";"Command Center";77;1
"Unit";"Marine";"Barracks";77;1
"Building";"BarracksReactor";NA;73;0
"Building";"SupplyDepot";NA;77;0
"Building";"SupplyDepot";NA;77;0
"Unit";"Marauder";"Barracks";77;2
"Unit";"Marine";"Barracks";77;1
"Unit";"Medivac";"Starport";77;2
"Unit";"Medivac";"Starport";77;2
"Unit";"SCV";"Command Center";82;1
"Unit";"SCV";"Command Center";82;1
"Unit";"Marauder";"Barracks";82;2
"Unit";"Marauder";"Barracks";82;2
"Building";"SupplyDepot";NA;82;0
"Building";"SupplyDepot";NA;85;0
"Unit";"Marine";"Barracks";85;1
"Unit";"Marauder";"Barracks";85;2
"Unit";"Marine";"Barracks";85;1
"Unit";"SCV";"Command Center";91;1
"Unit";"Marine";"Barracks";91;1
"Unit";"Marine";"Barracks";91;1
"Unit";"SCV";"Command Center";95;1
"Unit";"Marauder";"Barracks";95;2
"Unit";"Marauder";"Barracks";95;2
"Unit";"Marine";"Barracks";100;1
"Unit";"Marauder";"Barracks";100;2
"Unit";"Medivac";"Starport";95;2
"Unit";"Medivac";"Starport";95;2
"Unit";"Marine";"Barracks";102;1
"Unit";"Marine";"Barracks";102;1
"Unit";"Marine";"Barracks";103;1
"Unit";"SCV";"Command Center";107;1
"Unit";"SCV";"Command Center";114;1
"Building";"SupplyDepot";NA;110;0
"Building";"SupplyDepot";NA;114;0
"Unit";"Marauder";"Barracks";114;2
"Unit";"SCV";"Command Center";118;1
"Building";"SupplyDepot";NA;116;0
"Unit";"Marine";"Barracks";122;1
"Unit";"Marine";"Barracks";122;1
"Unit";"Marauder";"Barracks";122;2
"Unit";"Marauder";"Barracks";122;2
"Unit";"Marine";"Barracks";122;1
"Unit";"Marine";"Barracks";122;1
"Upgrade";"TerranInfantryArmorsLevel1";"EngineeringBay";95;0
"Unit";"Marauder";"Barracks";122;2
"Unit";"Marine";"Barracks";122;1
"Unit";"Marine";"Barracks";123;1
"Unit";"Marine";"Barracks";126;1
"Unit";"Marine";"Barracks";128;1
"Unit";"Marine";"Barracks";129;1
"Unit";"Marauder";"Barracks";124;2
"Unit";"Liberator";"Starport";122;3
"Unit";"Marine";"Barracks";139;1
"Unit";"Marine";"Barracks";139;1
"Unit";"Marine";"Barracks";139;1
"Unit";"Liberator";"Starport";126;3
"Unit";"Marauder";"Barracks";139;2
"Unit";"Marauder";"Barracks";139;2
"Unit";"Marauder";"Barracks";139;2
