"Type";"UnitName";"OnBuilding";"TotalSupply";"Supply"
"Unit";"SCV";"Command Center";12;1
"Unit";"SCV";"Command Center";13;1
"Unit";"SCV";"Command Center";13;1
"Building";"SupplyDepot";NA;13;0
"Building";"Refinery";NA;14;0
"Unit";"SCV";"Command Center";15;1
"Unit";"SCV";"Command Center";16;1
"Unit";"SCV";"Command Center";16;1
"Unit";"SCV";"Command Center";17;1
"Building";"Barracks";NA;15;0
"Unit";"Reaper";"Barracks";19;1
"Unit";"SCV";"Command Center";19;1
"Unit";"SCV";"Command Center";21;1
"Building";"SupplyDepot";NA;20;0
"Unit";"SCV";"Command Center";21;1
"Building";"Refinery";NA;21;0
"Building";"Factory";NA;19;0
"Building";"BarracksReactor";NA;20;0
"Unit";"SCV";"Command Center";22;1
"Unit";"SCV";"Command Center";23;1
"Unit";"Marine";"Barracks";24;1
"Unit";"Marine";"Barracks";24;1
"Unit";"SCV";"Command Center";24;1
"Unit";"Cyclone";"Factory";24;3
"Building";"SupplyDepot";NA;25;0
"Unit";"Marine";"Barracks";25;1
"Unit";"SCV";"Command Center";31;1
"Unit";"Marine";"Barracks";31;1
"Building";"Starport";NA;25;0
"Unit";"Marine";"Barracks";32;1
"Building";"CommandCenter";NA;19;0
"Unit";"SCV";"Command Center";32;1
"Unit";"Marine";"Barracks";33;1
"Unit";"SCV";"Command Center";36;1
"Unit";"Marine";"Barracks";34;1
"Unit";"SCV";"Command Center";38;1
"Unit";"Marine";"Barracks";36;1
"Building";"FactoryTechLab";NA;37;0
"Unit";"Marine";"Barracks";38;1
"Unit";"Medivac";"Starport";36;2
"Unit";"SCV";"Command Center";39;1
"Unit";"SCV";"Command Center";39;1
"Unit";"Marine";"Barracks";40;1
"Unit";"SCV";"Command Center";44;1
"Unit";"SCV";"Command Center";45;1
"Unit";"SCV";"Command Center";47;1
"Unit";"SCV";"Command Center";48;1
"Building";"Barracks";NA;37;0
"Unit";"Marine";"Barracks";49;1
"Unit";"Marine";"Barracks";49;1
"Unit";"SCV";"Command Center";49;1
"Unit";"SCV";"Command Center";50;1
"Building";"EngineeringBay";NA;49;0
"Building";"StarportTechLab";NA;51;0
"Unit";"SCV";"Command Center";54;1
"Unit";"SCV";"Command Center";55;1
"Building";"Barracks";NA;40;0
"Unit";"Marine";"Barracks";51;1
"Unit";"Marine";"Barracks";52;1
"Unit";"SCV";"Command Center";55;1
"Unit";"SCV";"Command Center";59;1
"Unit";"Marine";"Barracks";59;1
"Unit";"Marine";"Barracks";59;1
"Unit";"SCV";"Command Center";60;1
"Building";"SupplyDepot";NA;59;0
"Unit";"SCV";"Command Center";61;1
"Unit";"Marine";"Barracks";60;1
"Unit";"Marine";"Barracks";60;1
"Building";"SupplyDepot";NA;44;0
"Unit";"Marine";"Barracks";61;1
"Unit";"Marine";"Barracks";61;1
"Unit";"SCV";"Command Center";64;1
"Unit";"SCV";"Command Center";64;1
"Building";"StarportReactor";NA;60;0
"Building";"Refinery";NA;63;0
"Unit";"Marine";"Barracks";67;1
"Unit";"Marine";"Barracks";67;1
"Unit";"SCV";"Command Center";71;1
"Unit";"SCV";"Command Center";71;1
"Unit";"Marine";"Barracks";67;1
"Building";"MissileTurret";NA;71;0
"Building";"SupplyDepot";NA;70;0
"Unit";"SCV";"Command Center";73;1
"Unit";"SCV";"Command Center";74;1
"Building";"FactoryReactor";NA;67;0
"Unit";"Medivac";"Starport";71;2
"Unit";"Medivac";"Starport";71;2
"Unit";"Marine";"Barracks";76;1
"Unit";"Marine";"Barracks";76;1
"Unit";"Marine";"Barracks";76;1
"Unit";"Marine";"Barracks";76;1
"Unit";"SCV";"Command Center";77;1
"Unit";"SCV";"Command Center";78;1
"Building";"SupplyDepot";NA;76;0
"Unit";"SCV";"Command Center";86;1
"Unit";"SCV";"Command Center";87;1
"Unit";"Marine";"Barracks";82;1
"Unit";"Marine";"Barracks";83;1
"Unit";"Marine";"Barracks";84;1
"Unit";"Marine";"Barracks";85;1
"Building";"SupplyDepot";NA;86;0
"Building";"SupplyDepot";NA;88;0
"Building";"Refinery";NA;88;0
"Unit";"Medivac";"Starport";88;2
"Unit";"Medivac";"Starport";88;2
"Unit";"Marauder";"Barracks";92;2
"Unit";"Marine";"Barracks";94;1
"Unit";"Marine";"Barracks";94;1
"Upgrade";"Stimpack";"TechLab";67;0
"Unit";"Marauder";"Barracks";94;2
"Building";"SupplyDepot";NA;94;0
"Upgrade";"TerranInfantryWeaponsLevel1";"EngineeringBay";71;0
"Unit";"Marine";"Barracks";100;1
"Unit";"Marauder";"Barracks";100;2
"Unit";"Marauder";"Barracks";102;2
"Unit";"Marine";"Barracks";105;1
"Unit";"Marine";"Barracks";105;1
"Unit";"Liberator";"Starport";100;3
"Unit";"Liberator";"Starport";100;3
"Unit";"Marauder";"Barracks";109;2
"Unit";"Marauder";"Barracks";109;2
"Unit";"Marine";"Barracks";117;1
"Unit";"Marine";"Barracks";117;1
"Unit";"Marauder";"Barracks";117;2
"Unit";"Marauder";"Barracks";119;2
"Unit";"Marine";"Barracks";123;1
"Unit";"Marine";"Barracks";123;1
"Building";"SupplyDepot";NA;123;0
"Unit";"Marauder";"Barracks";123;2
"Unit";"Liberator";"Starport";121;3
"Unit";"Liberator";"Starport";121;3
"Unit";"Marine";"Barracks";129;1
"Unit";"Marine";"Barracks";129;1
"Unit";"Marauder";"Barracks";129;2
"Building";"CommandCenter";NA;111;0
"Unit";"Marauder";"Barracks";129;2
"Unit";"Marauder";"Barracks";139;2
"Building";"SupplyDepot";NA;141;0
"Unit";"Marine";"Barracks";143;1
"Unit";"Marine";"Barracks";143;1
"Unit";"Marauder";"Barracks";143;2
"Upgrade";"TerranInfantryArmorsLevel1";"EngineeringBay";123;0
"Unit";"Liberator";"Starport";137;3
"Unit";"SCV";"Command Center";145;1
"Unit";"SCV";"Command Center";145;1
"Building";"Barracks";NA;139;0
"Building";"Barracks";NA;141;0
"Unit";"Liberator";"Starport";141;3
"Unit";"Marine";"Barracks";152;1
"Unit";"Marine";"Barracks";152;1
"Unit";"Marauder";"Barracks";152;2
"Unit";"Marauder";"Barracks";152;2
"Unit";"SCV";"Command Center";157;1
"Unit";"SCV";"Command Center";157;1
