"Type";"UnitName";"OnBuilding";"TotalSupply";"Supply"
"Unit";"SCV";"Command Center";12;1
"Unit";"SCV";"Command Center";12;1
"Unit";"SCV";"Command Center";13;1
"Building";"SupplyDepot";NA;13;0
"Unit";"SCV";"Command Center";15;1
"Unit";"SCV";"Command Center";15;1
"Building";"Refinery";NA;15;0
"Unit";"SCV";"Command Center";16;1
"Unit";"SCV";"Command Center";17;1
"Building";"Barracks";NA;15;0
"Unit";"Marine";"Barracks";19;1
"Building";"BarracksTechLab";NA;20;0
"Unit";"SCV";"Command Center";20;1
"Building";"Bunker";NA;20;0
"Building";"SupplyDepot";NA;20;0
"Unit";"SCV";"Command Center";21;1
"Unit";"Marauder";"Barracks";21;2
"Unit";"SCV";"Command Center";21;1
"Unit";"Marauder";"Barracks";22;2
"Unit";"SCV";"Command Center";24;1
"Building";"CommandCenter";NA;19;0
"Unit";"SCV";"Command Center";28;1
"Unit";"Marauder";"Barracks";27;2
"Unit";"SCV";"Command Center";28;1
"Building";"Barracks";NA;25;0
"Unit";"SCV";"Command Center";32;1
"Building";"Barracks";NA;25;0
"Unit";"Marauder";"Barracks";31;2
"Unit";"SCV";"Command Center";32;1
"Unit";"Marine";"Barracks";33;1
"Unit";"Marine";"Barracks";33;1
"Building";"Refinery";NA;32;0
"Unit";"SCV";"Command Center";35;1
"Unit";"SCV";"Command Center";36;1
"Building";"EngineeringBay";NA;35;0
"Unit";"SCV";"Command Center";38;1
"Unit";"Marauder";"Barracks";36;2
"Unit";"Marine";"Barracks";38;1
"Unit";"Marine";"Barracks";39;1
"Unit";"SCV";"Command Center";40;1
"Unit";"SCV";"Command Center";44;1
"Unit";"Marine";"Barracks";43;1
"Unit";"Marauder";"Barracks";41;2
"Unit";"SCV";"Command Center";46;1
"Unit";"Marine";"Barracks";44;1
"Building";"SupplyDepot";NA;46;0
"Unit";"Marine";"Barracks";47;1
"Building";"SupplyDepot";NA;47;0
"Unit";"SCV";"Command Center";52;1
"Unit";"SCV";"Command Center";52;1
"Unit";"Marauder";"Barracks";52;2
"Building";"SupplyDepot";NA;52;0
"Unit";"SCV";"Command Center";53;1
"Unit";"SCV";"Command Center";53;1
"Upgrade";"Stimpack";"TechLab";35;0
"Building";"BarracksTechLab";NA;53;0
"Unit";"SCV";"Command Center";57;1
"Unit";"SCV";"Command Center";59;1
"Building";"BarracksReactor";NA;53;0
"Building";"Factory";NA;52;0
"Unit";"Marauder";"Barracks";55;2
"Unit";"SCV";"Command Center";59;1
"Building";"Refinery";NA;59;0
"Unit";"SCV";"Command Center";61;1
"Unit";"Marine";"Barracks";61;1
"Unit";"SCV";"Command Center";63;1
"Unit";"Marine";"Barracks";61;1
"Unit";"Marine";"Barracks";63;1
"Building";"FactoryTechLab";NA;63;0
"Unit";"SCV";"Command Center";65;1
"Unit";"Marine";"Barracks";65;1
"Unit";"Marine";"Barracks";65;1
"Unit";"Marine";"Barracks";66;1
"Unit";"Marine";"Barracks";68;1
"Unit";"SCV";"Command Center";69;1
"Upgrade";"TerranInfantryWeaponsLevel1";"EngineeringBay";52;0
"Building";"Starport";NA;63;0
"Unit";"SCV";"Command Center";70;1
"Building";"SupplyDepot";NA;69;0
"Unit";"Marine";"Barracks";74;1
"Unit";"Marine";"Barracks";75;1
"Unit";"SCV";"Command Center";75;1
"Unit";"SCV";"Command Center";75;1
"Building";"SupplyDepot";NA;75;0
"Unit";"Marauder";"Barracks";75;2
"Unit";"SCV";"Command Center";78;1
"Building";"SupplyDepot";NA;76;0
"Unit";"Medivac";"Starport";75;2
"Unit";"Marine";"Barracks";82;1
"Unit";"Marine";"Barracks";82;1
"Unit";"SCV";"Command Center";83;1
"Building";"SupplyDepot";NA;82;0
"Unit";"Marauder";"Barracks";82;2
"Unit";"SCV";"Command Center";87;1
"Unit";"SCV";"Command Center";87;1
"Unit";"Marine";"Barracks";85;1
"Unit";"Marine";"Barracks";88;1
"Unit";"Marine";"Barracks";88;1
"Unit";"Marine";"Barracks";88;1
"Unit";"Medivac";"Starport";83;2
"Unit";"Marine";"Barracks";92;1
"Unit";"SCV";"Command Center";98;1
"Unit";"SCV";"Command Center";98;1
"Unit";"Marine";"Barracks";93;1
"Unit";"Marine";"Barracks";94;1
"Unit";"Marauder";"Barracks";95;2
"Unit";"SCV";"Command Center";99;1
"Unit";"Marine";"Barracks";98;1
"Unit";"SCV";"Command Center";103;1
"Unit";"Medivac";"Starport";96;2
"Unit";"Marine";"Barracks";101;1
"Unit";"SCV";"Command Center";105;1
"Unit";"Marauder";"Barracks";103;2
"Unit";"SCV";"Command Center";107;1
"Unit";"Marine";"Barracks";106;1
"Unit";"Marine";"Barracks";106;1
"Building";"SupplyDepot";NA;107;0
"Unit";"SCV";"Command Center";111;1
"Unit";"SCV";"Command Center";114;1
"Unit";"Marauder";"Barracks";112;2
"Unit";"Marine";"Barracks";118;1
"Unit";"SCV";"Command Center";119;1
"Unit";"Marine";"Barracks";118;1
"Unit";"SCV";"Command Center";119;1
"Unit";"Liberator";"Starport";108;3
"Unit";"Marine";"Barracks";121;1
"Unit";"Marauder";"Barracks";121;2
"Unit";"SCV";"Command Center";122;1
"Unit";"SCV";"Command Center";124;1
"Unit";"SCV";"Command Center";131;1
"Unit";"SCV";"Command Center";132;1
"Unit";"Marine";"Barracks";129;1
"Unit";"Marine";"Barracks";129;1
"Unit";"Marauder";"Barracks";128;2
"Unit";"Marauder";"Barracks";129;2
"Unit";"SCV";"Command Center";133;1
"Unit";"SCV";"Command Center";135;1
"Building";"Barracks";NA;121;0
"Unit";"Marine";"Barracks";139;1
"Building";"Refinery";NA;139;0
"Building";"Barracks";NA;128;0
"Building";"SupplyDepot";NA;142;0
"Unit";"Marine";"Barracks";143;1
"Building";"SupplyDepot";NA;142;0
"Unit";"SCV";"Command Center";144;1
"Unit";"SCV";"Command Center";144;1
"Building";"SupplyDepot";NA;144;0
"Unit";"Marine";"Barracks";144;1
"Unit";"Marauder";"Barracks";144;2
"Unit";"SCV";"Command Center";145;1
"Unit";"SCV";"Command Center";146;1
"Building";"StarportReactor";NA;144;0
"Unit";"Marine";"Barracks";145;1
"Unit";"Marine";"Barracks";145;1
"Unit";"Marauder";"Barracks";145;2
"Unit";"SCV";"Command Center";150;1
"Unit";"SCV";"Command Center";151;1
"Building";"MissileTurret";NA;148;0
"Unit";"Marauder";"Barracks";148;2
"Unit";"SCV";"Command Center";156;1
"Unit";"SCV";"Command Center";158;1
"Unit";"Marine";"Barracks";158;1
"Unit";"Marauder";"Barracks";158;2
"Unit";"SCV";"Command Center";161;1
"Unit";"SCV";"Command Center";161;1
"Unit";"Marine";"Barracks";161;1
"Unit";"Marine";"Barracks";161;1
"Unit";"Marauder";"Barracks";161;2
"Unit";"Marine";"Barracks";163;1
"Unit";"Marine";"Barracks";163;1
"Unit";"Marine";"Barracks";163;1
"Unit";"SCV";"Command Center";167;1
"Upgrade";"TerranInfantryArmorsLevel1";"EngineeringBay";144;0
"Unit";"SCV";"Command Center";167;1
"Building";"MissileTurret";NA;165;0
"Unit";"Marine";"Barracks";167;1
"Unit";"Medivac";"Starport";163;2
"Unit";"SCV";"Command Center";174;1
"Unit";"SCV";"Command Center";175;1
"Building";"SupplyDepot";NA;173;0
"Building";"SupplyDepot";NA;176;0
"Unit";"Medivac";"Starport";173;2
"Building";"SupplyDepot";NA;179;0
"Unit";"SCV";"Command Center";181;1
"Unit";"Marine";"Barracks";181;1
"Unit";"Marine";"Barracks";181;1
"Building";"BarracksTechLab";NA;181;0
"Unit";"Marauder";"Barracks";181;2
"Unit";"Marauder";"Barracks";181;2
"Building";"CommandCenter";NA;163;0
"Building";"SupplyDepot";NA;183;0
"Building";"SupplyDepot";NA;183;0
"Building";"BarracksReactor";NA;181;0
"Unit";"Marauder";"Barracks";190;2
"Unit";"Marine";"Barracks";190;1
"Unit";"Marine";"Barracks";190;1
"Unit";"Marine";"Barracks";190;1
"Unit";"Marauder";"Barracks";190;2
"Unit";"Marine";"Barracks";192;1
"Unit";"Marine";"Barracks";192;1
"Unit";"Marine";"Barracks";192;1
"Unit";"Marine";"Barracks";193;1
"Unit";"Marauder";"Barracks";190;2
"Building";"Armory";NA;190;0
"Unit";"Marauder";"Barracks";194;2
"Unit";"Marauder";"Barracks";197;2
