"Type";"UnitName";"OnBuilding";"TotalSupply";"Supply"
"Unit";"SCV";"Command Center";12;1
"Unit";"SCV";"Command Center";12;1
"Unit";"SCV";"Command Center";13;1
"Building";"SupplyDepot";NA;13;0
"Unit";"SCV";"Command Center";15;1
"Unit";"SCV";"Command Center";15;1
"Building";"Refinery";NA;15;0
"Unit";"SCV";"Command Center";16;1
"Building";"Barracks";NA;15;0
"Unit";"SCV";"Command Center";17;1
"Unit";"Marine";"Barracks";19;1
"Unit";"SCV";"Command Center";20;1
"Unit";"SCV";"Command Center";21;1
"Building";"SupplyDepot";NA;21;0
"Unit";"SCV";"Command Center";22;1
"Building";"BarracksReactor";NA;20;0
"Building";"Factory";NA;20;0
"Unit";"SCV";"Command Center";22;1
"Building";"Refinery";NA;22;0
"Building";"Bunker";NA;22;0
"Building";"CommandCenter";NA;20;0
"Unit";"Marine";"Barracks";23;1
"Unit";"Marine";"Barracks";23;1
"Unit";"SCV";"Command Center";24;1
"Unit";"SCV";"Command Center";26;1
"Building";"Starport";NA;23;0
"Unit";"Marine";"Barracks";27;1
"Unit";"Marine";"Barracks";27;1
"Unit";"SCV";"Command Center";28;1
"Unit";"SCV";"Command Center";30;1
"Unit";"SCV";"Command Center";30;1
"Unit";"SCV";"Command Center";31;1
"Unit";"SCV";"Command Center";32;1
"Unit";"Medivac";"Starport";28;2
"Unit";"SCV";"Command Center";33;1
"Building";"SupplyDepot";NA;33;0
"Unit";"SCV";"Command Center";37;1
"Unit";"Marine";"Barracks";33;1
"Unit";"SCV";"Command Center";38;1
"Unit";"SCV";"Command Center";38;1
"Building";"FactoryTechLab";NA;40;0
"Unit";"SCV";"Command Center";40;1
"Unit";"Marine";"Barracks";40;1
"Unit";"Marine";"Barracks";40;1
"Building";"EngineeringBay";NA;38;0
"Unit";"SCV";"Command Center";41;1
"Building";"SupplyDepot";NA;42;0
"Unit";"Liberator";"Starport";38;3
"Unit";"SCV";"Command Center";46;1
"Unit";"SCV";"Command Center";46;1
"Building";"SupplyDepot";NA;46;0
"Building";"MissileTurret";NA;46;0
"Unit";"Marine";"Barracks";46;1
"Unit";"Marine";"Barracks";46;1
"Building";"Refinery";NA;46;0
"Building";"Barracks";NA;40;0
"Unit";"SCV";"Command Center";49;1
"Unit";"SCV";"Command Center";51;1
"Unit";"SCV";"Command Center";53;1
"Unit";"SCV";"Command Center";54;1
"Unit";"Marine";"Barracks";53;1
"Unit";"Marine";"Barracks";53;1
"Building";"BarracksTechLab";NA;53;0
"Unit";"SCV";"Command Center";55;1
"Unit";"SCV";"Command Center";56;1
"Unit";"Marine";"Barracks";59;1
"Building";"StarportReactor";NA;53;0
"Building";"SupplyDepot";NA;60;0
"Building";"Barracks";NA;55;0
"Building";"SupplyDepot";NA;61;0
"Unit";"SCV";"Command Center";62;1
"Unit";"SCV";"Command Center";62;1
"Building";"Refinery";NA;62;0
"Unit";"Marine";"Barracks";62;1
"Unit";"Marine";"Barracks";62;1
"Unit";"Marine";"Barracks";62;1
"Unit";"SCV";"Command Center";62;1
"Unit";"SCV";"Command Center";62;1
"Building";"BarracksTechLab";NA;62;0
"Building";"SupplyDepot";NA;62;0
"Building";"SupplyDepot";NA;62;0
"Unit";"Marine";"Barracks";64;1
"Building";"StarportReactor";NA;62;0
"Upgrade";"TerranInfantryWeaponsLevel1";"EngineeringBay";55;0
"Building";"Barracks";NA;62;0
"Building";"Barracks";NA;62;0
"Unit";"Marine";"Barracks";69;1
"Unit";"Marauder";"Barracks";69;2
"Unit";"Marauder";"Barracks";69;2
"Unit";"Marine";"Barracks";70;1
"Unit";"Marine";"Barracks";71;1
"Unit";"Marine";"Barracks";71;1
"Building";"BarracksTechLab";NA;71;0
"Building";"SupplyDepot";NA;71;0
"Building";"SupplyDepot";NA;71;0
"Building";"SupplyDepot";NA;71;0
"Unit";"Medivac";"Starport";70;2
"Unit";"Medivac";"Starport";70;2
"Unit";"Marauder";"Barracks";75;2
"Unit";"Marauder";"Barracks";75;2
"Unit";"Marine";"Barracks";78;1
"Unit";"Marine";"Barracks";78;1
"Unit";"Marine";"Barracks";78;1
"Unit";"Marine";"Barracks";78;1
"Unit";"Marauder";"Barracks";78;2
"Upgrade";"Stimpack";"TechLab";62;0
"Unit";"Marauder";"Barracks";82;2
"Unit";"Marauder";"Barracks";84;2
"Building";"MissileTurret";NA;86;0
"Building";"MissileTurret";NA;90;0
"Unit";"Marine";"Barracks";92;1
"Unit";"Marine";"Barracks";92;1
"Unit";"Marine";"Barracks";92;1
"Unit";"Marine";"Barracks";92;1
"Unit";"Medivac";"Starport";86;2
"Building";"SupplyDepot";NA;92;0
"Unit";"Marauder";"Barracks";92;2
"Unit";"Liberator";"Starport";86;3
"Building";"SupplyDepot";NA;96;0
"Building";"SupplyDepot";NA;96;0
"Unit";"Marauder";"Barracks";96;2
"Unit";"Marauder";"Barracks";96;2
"Unit";"Marine";"Barracks";104;1
"Unit";"Marine";"Barracks";104;1
"Unit";"Marine";"Barracks";104;1
"Unit";"Marine";"Barracks";104;1
"Unit";"Marine";"Barracks";104;1
"Unit";"Marine";"Barracks";116;1
"Unit";"Marauder";"Barracks";111;2
"Unit";"Marauder";"Barracks";111;2
"Unit";"Marine";"Barracks";116;1
"Unit";"Marine";"Barracks";116;1
"Unit";"Marine";"Barracks";116;1
"Unit";"Marauder";"Barracks";115;2
"Unit";"Liberator";"Starport";104;3
"Building";"SupplyDepot";NA;116;0
"Building";"SupplyDepot";NA;116;0
"Unit";"Marine";"Barracks";116;1
"Unit";"Marine";"Barracks";116;1
"Unit";"Marine";"Barracks";119;1
"Unit";"Marine";"Barracks";121;1
"Unit";"Marine";"Barracks";126;1
"Unit";"Marine";"Barracks";126;1
"Unit";"Marauder";"Barracks";126;2
"Unit";"Marine";"Barracks";129;1
"Unit";"Marine";"Barracks";132;1
"Unit";"Marauder";"Barracks";129;2
"Unit";"Marauder";"Barracks";131;2
"Unit";"Marine";"Barracks";133;1
"Unit";"Marine";"Barracks";134;1
"Upgrade";"TerranInfantryArmorsLevel1";"EngineeringBay";104;0
"Unit";"Marauder";"Barracks";135;2
"Unit";"Marine";"Barracks";137;1
"Unit";"Marine";"Barracks";138;1
"Unit";"Marine";"Barracks";143;1
"Unit";"Marine";"Barracks";144;1
"Unit";"Marauder";"Barracks";139;2
"Unit";"Marauder";"Barracks";141;2
"Unit";"Marine";"Barracks";145;1
"Unit";"Liberator";"Starport";134;3
"Unit";"Marine";"Barracks";147;1
"Unit";"Marine";"Barracks";148;1
"Unit";"Marine";"Barracks";149;1
"Unit";"Marine";"Barracks";150;1
"Unit";"Marauder";"Barracks";151;2
"Unit";"Marauder";"Barracks";153;2
"Unit";"Marauder";"Barracks";155;2
"Unit";"Marine";"Barracks";159;1
"Unit";"Marine";"Barracks";160;1
"Unit";"Marine";"Barracks";161;1
"Unit";"Marine";"Barracks";162;1
"Unit";"Marauder";"Barracks";163;2
"Unit";"Marauder";"Barracks";165;2
"Unit";"Marine";"Barracks";167;1
"Unit";"Marine";"Barracks";169;1
"Unit";"Marine";"Barracks";170;1
"Unit";"Marine";"Barracks";171;1
"Unit";"Marine";"Barracks";172;1
"Unit";"Liberator";"Starport";161;3
"Unit";"Liberator";"Starport";161;3
"Unit";"Marauder";"Barracks";173;2
"Unit";"Marauder";"Barracks";175;2
"Unit";"Marauder";"Barracks";177;2
"Unit";"Marine";"Barracks";182;1
"Unit";"Marine";"Barracks";185;1
"Unit";"Marine";"Barracks";188;1
"Unit";"Marine";"Barracks";188;1
"Unit";"SCV";"Command Center";188;1
"Unit";"SCV";"Command Center";188;1
"Unit";"Medivac";"Starport";182;2
"Unit";"Medivac";"Starport";185;2
"Unit";"Marine";"Barracks";200;1
"Unit";"Marine";"Barracks";200;1
"Unit";"Marine";"Barracks";200;1
"Unit";"Marine";"Barracks";200;1
"Unit";"Marauder";"Barracks";200;2
"Unit";"Marauder";"Barracks";200;2
"Unit";"Marauder";"Barracks";200;2
"Unit";"Marine";"Barracks";208;1
"Unit";"Marine";"Barracks";208;1
"Unit";"Marine";"Barracks";208;1
"Unit";"Marine";"Barracks";208;1
"Unit";"Marine";"Barracks";210;1
"Unit";"Marauder";"Barracks";208;2
"Unit";"Marine";"Barracks";214;1
"Unit";"Marine";"Barracks";214;1
"Unit";"Marauder";"Barracks";218;2
"Unit";"Marine";"Barracks";221;1
"Unit";"Marine";"Barracks";221;1
"Unit";"Marauder";"Barracks";219;2
"Unit";"Marine";"Barracks";221;1
"Unit";"Marine";"Barracks";222;1
"Unit";"Marauder";"Barracks";221;2
"Unit";"Marine";"Barracks";225;1
"Unit";"Marine";"Barracks";226;1
"Unit";"Marine";"Barracks";226;1
"Unit";"Marine";"Barracks";229;1
"Unit";"Marauder";"Barracks";223;2
