"type";"unit_name";"on_building";"total_supply";"supply"
"Building";"Refinery";NA;14;0
"Building";"Barracks";NA;15;0
"Unit";"Reaper";"Barracks";19;1
"Building";"Factory";NA;19;0
"Building";"BarracksReactor";NA;20;0
"Building";"Refinery";NA;21;0
"Building";"CommandCenter";NA;19;0
"Building";"BarracksTechLab";NA;23;0
"Unit";"Hellion";"Factory";23;2
"Unit";"Hellion";"Factory";23;2
"Building";"Starport";NA;23;0
"Unit";"Hellion";"Factory";29;2
"Unit";"Hellion";"Factory";29;2
"Unit";"Medivac";"Starport";29;2
"Unit";"Marine";"Barracks";43;1
"Unit";"Marine";"Barracks";43;1
"Unit";"Liberator";"Starport";41;3
"Building";"Bunker";NA;43;0
"Building";"EngineeringBay";NA;45;0
"Unit";"Marine";"Barracks";48;1
"Unit";"Marine";"Barracks";48;1
"Building";"StarportReactor";NA;52;0
"Unit";"Marine";"Barracks";57;1
"Unit";"Marine";"Barracks";57;1
"Building";"BarracksTechLab";NA;63;0
"Building";"CommandCenter";NA;53;0
"Building";"StarportReactor";NA;63;0
"Building";"Refinery";NA;64;0
"Building";"Refinery";NA;64;0
"Building";"Barracks";NA;61;0
"Unit";"Marine";"Barracks";65;1
"Building";"Barracks";NA;63;0
"Unit";"Marine";"Barracks";68;1
"Unit";"Marine";"Barracks";68;1
"Unit";"Medivac";"Starport";67;2
"Unit";"Medivac";"Starport";67;2
"Unit";"Marine";"Barracks";71;1
"Unit";"Marine";"Barracks";71;1
"Unit";"Marine";"Barracks";71;1
"Unit";"Marine";"Barracks";71;1
"Unit";"Marine";"Barracks";78;1
"Unit";"Marine";"Barracks";78;1
"Unit";"Marine";"Barracks";84;1
"Unit";"Marine";"Barracks";84;1
"Unit";"Marine";"Barracks";84;1
"Building";"Barracks";NA;73;0
"Building";"Barracks";NA;73;0
"Unit";"Marine";"Barracks";90;1
"Unit";"Marine";"Barracks";90;1
"Unit";"Marine";"Barracks";91;1
"Unit";"Marine";"Barracks";91;1
"Unit";"Marine";"Barracks";91;1
"Unit";"Marine";"Barracks";91;1
"Unit";"Marine";"Barracks";92;1
"Upgrade";"TerranInfantryWeaponsLevel1";"EngineeringBay";69;0
"Unit";"Marine";"Barracks";93;1
"Building";"MissileTurret";NA;96;0
"Building";"MissileTurret";NA;96;0
"Building";"MissileTurret";NA;96;0
"Upgrade";"Stimpack";"TechLab";73;0
"Building";"BarracksReactor";NA;91;0
"Building";"BarracksReactor";NA;91;0
"Unit";"Marine";"Barracks";97;1
"Unit";"Marine";"Barracks";98;1
"Unit";"Marine";"Barracks";98;1
"Unit";"Medivac";"Starport";96;2
"Unit";"Medivac";"Starport";96;2
"Building";"Factory";NA;93;0
"Building";"MissileTurret";NA;102;0
"Unit";"Marine";"Barracks";105;1
"Unit";"Marine";"Barracks";105;1
"Unit";"Marine";"Barracks";105;1
"Unit";"Marine";"Barracks";105;1
"Unit";"Marine";"Barracks";105;1
"Unit";"Marine";"Barracks";105;1
"Unit";"Marine";"Barracks";105;1
"Unit";"Marine";"Barracks";110;1
"Unit";"Marine";"Barracks";110;1
"Unit";"Marine";"Barracks";110;1
"Unit";"Marine";"Barracks";111;1
"Unit";"Marine";"Barracks";117;1
"Unit";"Marine";"Barracks";117;1
"Building";"Refinery";NA;117;0
"Building";"Refinery";NA;117;0
"Unit";"Marine";"Barracks";117;1
"Unit";"Marine";"Barracks";117;1
"Unit";"Marine";"Barracks";117;1
"Building";"Bunker";NA;117;0
"Unit";"Marine";"Barracks";124;1
"Unit";"Marine";"Barracks";124;1
"Building";"FactoryTechLab";NA;126;0
"Unit";"Marine";"Barracks";129;1
"Unit";"Marine";"Barracks";129;1
"Unit";"Marine";"Barracks";129;1
"Unit";"Marine";"Barracks";129;1
"Unit";"Marine";"Barracks";129;1
"Unit";"Marine";"Barracks";129;1
"Building";"SensorTower";NA;134;0
"Unit";"Marine";"Barracks";142;1
"Unit";"Marine";"Barracks";142;1
"Unit";"Marine";"Barracks";143;1
"Unit";"Marine";"Barracks";143;1
"Unit";"Marine";"Barracks";143;1
"Unit";"Marine";"Barracks";143;1
"Building";"MissileTurret";NA;143;0
"Unit";"Marine";"Barracks";143;1
"Unit";"Marine";"Barracks";143;1
"Unit";"Marine";"Barracks";143;1
"Upgrade";"TerranInfantryArmorsLevel1";"EngineeringBay";109;0
"Unit";"Marine";"Barracks";143;1
"Unit";"Marine";"Barracks";144;1
"Unit";"Marine";"Barracks";145;1
"Unit";"Marine";"Barracks";146;1
"Unit";"Marine";"Barracks";147;1
"Unit";"Marine";"Barracks";152;1
"Unit";"Marine";"Barracks";152;1
"Building";"EngineeringBay";NA;152;0
"Building";"Factory";NA;152;0
"Building";"Barracks";NA;152;0
"Unit";"Marine";"Barracks";159;1
"Unit";"Marine";"Barracks";159;1
"Unit";"Marine";"Barracks";159;1
"Unit";"Marine";"Barracks";159;1
"Unit";"Marine";"Barracks";159;1
"Unit";"Marine";"Barracks";159;1
"Unit";"Marine";"Barracks";159;1
"Building";"Armory";NA;152;0
"Building";"FactoryTechLab";NA;159;0
"Building";"CommandCenter";NA;152;0
"Building";"BarracksReactor";NA;166;0
"Unit";"Marine";"Barracks";166;1
"Unit";"Marine";"Barracks";166;1
"Unit";"Marine";"Barracks";166;1
"Unit";"Marine";"Barracks";166;1
"Unit";"Marine";"Barracks";166;1
"Unit";"Marine";"Barracks";166;1
"Unit";"Marine";"Barracks";166;1
"Unit";"Marine";"Barracks";166;1
"Unit";"Marine";"Barracks";166;1
"Unit";"Marine";"Barracks";173;1
"Unit";"Marine";"Barracks";175;1
"Unit";"Marine";"Barracks";175;1
"Unit";"Marine";"Barracks";175;1
"Unit";"Marine";"Barracks";175;1
"Unit";"Marine";"Barracks";175;1
"Unit";"Marine";"Barracks";175;1
"Unit";"Marine";"Barracks";175;1
"Unit";"Medivac";"Starport";175;2
"Unit";"Marine";"Barracks";176;1
"Unit";"Marine";"Barracks";176;1
"Unit";"Marine";"Barracks";176;1
"Unit";"Marine";"Barracks";179;1
"Unit";"Marine";"Barracks";179;1
"Unit";"Marine";"Barracks";179;1
"Unit";"Medivac";"Starport";176;2
"Unit";"Marine";"Barracks";190;1
"Unit";"Marine";"Barracks";190;1
"Building";"MissileTurret";NA;190;0
"Unit";"Marine";"Barracks";190;1
"Unit";"Marine";"Barracks";190;1
"Unit";"Medivac";"Starport";197;2
"Unit";"Medivac";"Starport";197;2
"Upgrade";"TerranInfantryWeaponsLevel2";"EngineeringBay";173;0
"Upgrade";"TerranInfantryArmorsLevel2";"EngineeringBay";173;0
"Unit";"Marine";"Barracks";205;1
"Unit";"Marine";"Barracks";205;1
"Unit";"Marine";"Barracks";205;1
"Unit";"Marine";"Barracks";205;1
"Unit";"Marine";"Barracks";205;1
"Unit";"Marine";"Barracks";205;1
"Unit";"Marine";"Barracks";205;1
"Unit";"Marine";"Barracks";205;1
"Unit";"Marine";"Barracks";205;1
"Unit";"Marine";"Barracks";216;1
"Unit";"Marine";"Barracks";216;1
"Unit";"Marine";"Barracks";216;1
"Unit";"Marine";"Barracks";216;1
"Unit";"Marine";"Barracks";218;1
"Unit";"Marine";"Barracks";218;1
"Unit";"Marine";"Barracks";218;1
"Unit";"Marine";"Barracks";218;1
"Unit";"Marine";"Barracks";230;1
"Unit";"Marine";"Barracks";230;1
"Unit";"Marine";"Barracks";230;1
"Unit";"Marine";"Barracks";233;1
"Unit";"Marine";"Barracks";236;1
"Unit";"Marine";"Barracks";236;1
"Unit";"Marine";"Barracks";236;1
"Unit";"Marine";"Barracks";236;1
"Unit";"Marine";"Barracks";236;1
