"type";"unit_name";"on_building";"total_supply_lag"
"Unit";"Overlord";"Larva";14
"Building";"Hatchery";NA;17
"Building";"SpawningPool";NA;18
"Building";"Extractor";NA;18
"Unit";"Overlord";"Larva";22
"Unit";"Queen";"Hatchery";23
"Building";"Hatchery";NA;25
"Unit";"Zergling";"Larva";25
"Unit";"Zergling";"Larva";26
"Unit";"Queen";"Hatchery";28
"Building";"BanelingNest";NA;33
"Unit";"Zergling";"Larva";37
"Unit";"Zergling";"Larva";38
"Unit";"Zergling";"Larva";39
"Unit";"Zergling";"Larva";40
"Unit";"Zergling";"Larva";41
"Unit";"Zergling";"Larva";42
"Unit";"Overlord";"Larva";43
"Unit";"Zergling";"Larva";43
"Unit";"Zergling";"Larva";44
"Unit";"Zergling";"Larva";45
"Unit";"Zergling";"Larva";46
"Unit";"Zergling";"Larva";47
"Unit";"Zergling";"Larva";48
"Unit";"Zergling";"Larva";49
"Unit";"Zergling";"Larva";50
"Unit";"Baneling";"Zergling";51
"Unit";"Baneling";"Zergling";51
"Unit";"Zergling";"Larva";51
"Unit";"Zergling";"Larva";52
"Unit";"Zergling";"Larva";53
"Unit";"Zergling";"Larva";54
"Unit";"Zergling";"Larva";55
"Unit";"Zergling";"Larva";56
"Unit";"Zergling";"Larva";57
"Unit";"Zergling";"Larva";58
"Unit";"Zergling";"Larva";59
"Unit";"Zergling";"Larva";60
"Unit";"Zergling";"Larva";61
"Unit";"Zergling";"Larva";62
"Unit";"Zergling";"Larva";63
"Unit";"Zergling";"Larva";64
"Unit";"Zergling";"Larva";65
"Unit";"Zergling";"Larva";66
"Unit";"Zergling";"Larva";67
"Unit";"Zergling";"Larva";68
"Unit";"Zergling";"Larva";69
"Unit";"Zergling";"Larva";70
"Unit";"Zergling";"Larva";71
"Unit";"Zergling";"Larva";72
"Unit";"Zergling";"Larva";73
"Unit";"Zergling";"Larva";74
"Unit";"Zergling";"Larva";75
"Unit";"Zergling";"Larva";76
"Unit";"Zergling";"Larva";77
"Unit";"Zergling";"Larva";78
"Unit";"Baneling";"Zergling";79
"Unit";"Baneling";"Zergling";79
"Unit";"Zergling";"Larva";79
"Unit";"Zergling";"Larva";80
"Unit";"Zergling";"Larva";81
"Unit";"Zergling";"Larva";82
"Unit";"Zergling";"Larva";83
"Unit";"Zergling";"Larva";84
"Unit";"Zergling";"Larva";85
"Unit";"Zergling";"Larva";86
"Unit";"Zergling";"Larva";87
"Unit";"Zergling";"Larva";88
"Unit";"Zergling";"Larva";89
"Unit";"Zergling";"Larva";90
"Unit";"Zergling";"Larva";91
"Unit";"Zergling";"Larva";92
"Unit";"Zergling";"Larva";93
"Unit";"Zergling";"Larva";94
"Unit";"Zergling";"Larva";95
"Unit";"Zergling";"Larva";96
"Unit";"Zergling";"Larva";97
"Unit";"Zergling";"Larva";98
"Unit";"Zergling";"Larva";99
"Unit";"Zergling";"Larva";100
"Unit";"Zergling";"Larva";101
"Unit";"Zergling";"Larva";102
"Unit";"Zergling";"Larva";103
"Unit";"Zergling";"Larva";104
"Unit";"Zergling";"Larva";105
"Unit";"Zergling";"Larva";106
"Unit";"Zergling";"Larva";107
"Unit";"Zergling";"Larva";108
"Unit";"Zergling";"Larva";109
"Unit";"Zergling";"Larva";110
"Unit";"Zergling";"Larva";111
"Unit";"Zergling";"Larva";112
"Unit";"Zergling";"Larva";113
"Unit";"Zergling";"Larva";114
"Unit";"Queen";"Hatchery";115
"Unit";"Overlord";"Larva";117
"Unit";"Overlord";"Larva";117
"Unit";"Baneling";"Zergling";117
"Unit";"Baneling";"Zergling";117
"Unit";"Queen";"Hatchery";117
"Unit";"Zergling";"Larva";119
"Unit";"Zergling";"Larva";120
"Unit";"Zergling";"Larva";121
"Unit";"Zergling";"Larva";122
"Unit";"Zergling";"Larva";123
"Unit";"Zergling";"Larva";124
"Unit";"Zergling";"Larva";125
"Unit";"Zergling";"Larva";126
"Unit";"Zergling";"Larva";127
"Unit";"Zergling";"Larva";128
"Unit";"Zergling";"Larva";129
"Unit";"Zergling";"Larva";130
"Unit";"Zergling";"Larva";131
"Unit";"Zergling";"Larva";132
"Unit";"Zergling";"Larva";133
"Unit";"Zergling";"Larva";134
"Unit";"Zergling";"Larva";135
"Unit";"Zergling";"Larva";136
"Unit";"Zergling";"Larva";137
"Unit";"Zergling";"Larva";138
"Unit";"Zergling";"Larva";139
"Unit";"Zergling";"Larva";140
"Unit";"Baneling";"Zergling";141
"Unit";"Baneling";"Zergling";141
"Unit";"Baneling";"Zergling";141
"Unit";"Zergling";"Larva";141
"Unit";"Zergling";"Larva";142
"Unit";"Zergling";"Larva";143
"Unit";"Zergling";"Larva";144
"Unit";"Zergling";"Larva";145
"Unit";"Zergling";"Larva";146
"Unit";"Baneling";"Zergling";147
"Unit";"Zergling";"Larva";147
"Unit";"Zergling";"Larva";148
"Unit";"Zergling";"Larva";149
"Unit";"Zergling";"Larva";150
"Unit";"Zergling";"Larva";151
"Unit";"Zergling";"Larva";152
"Unit";"Zergling";"Larva";153
"Unit";"Zergling";"Larva";154
"Unit";"Zergling";"Larva";155
"Unit";"Zergling";"Larva";156
"Unit";"Zergling";"Larva";157
"Unit";"Zergling";"Larva";158
"Unit";"Zergling";"Larva";159
"Unit";"Zergling";"Larva";160
"Unit";"Zergling";"Larva";161
"Unit";"Zergling";"Larva";162
"Unit";"Zergling";"Larva";163
"Unit";"Zergling";"Larva";164
"Unit";"Zergling";"Larva";165
"Unit";"Zergling";"Larva";166
"Unit";"Zergling";"Larva";167
"Unit";"Zergling";"Larva";168
"Unit";"Zergling";"Larva";169
"Unit";"Zergling";"Larva";170
"Unit";"Zergling";"Larva";171
"Unit";"Zergling";"Larva";172
"Unit";"Baneling";"Zergling";173
"Unit";"Baneling";"Zergling";173
"Unit";"Baneling";"Zergling";173
"Unit";"Baneling";"Zergling";173
"Unit";"Baneling";"Zergling";173
"Unit";"Zergling";"Larva";173
"Unit";"Zergling";"Larva";174
"Unit";"Zergling";"Larva";175
"Unit";"Zergling";"Larva";176
"Unit";"Zergling";"Larva";177
"Unit";"Zergling";"Larva";178
"Unit";"Zergling";"Larva";179
"Unit";"Zergling";"Larva";180
"Unit";"Zergling";"Larva";181
"Unit";"Zergling";"Larva";182
"Unit";"Zergling";"Larva";183
"Unit";"Zergling";"Larva";184
"Unit";"Zergling";"Larva";185
"Unit";"Zergling";"Larva";186
"Unit";"Zergling";"Larva";187
"Unit";"Zergling";"Larva";188
"Unit";"Zergling";"Larva";189
"Unit";"Zergling";"Larva";190
"Unit";"Zergling";"Larva";191
"Unit";"Zergling";"Larva";192
"Unit";"Zergling";"Larva";193
"Unit";"Zergling";"Larva";194
"Unit";"Zergling";"Larva";195
"Unit";"Zergling";"Larva";196
"Unit";"Zergling";"Larva";197
"Unit";"Zergling";"Larva";198
"Building";"RoachWarren";NA;199
"Unit";"Zergling";"Larva";200
"Unit";"Zergling";"Larva";201
"Unit";"Zergling";"Larva";202
"Unit";"Zergling";"Larva";203
"Unit";"Zergling";"Larva";204
"Unit";"Zergling";"Larva";205
"Unit";"Zergling";"Larva";206
"Unit";"Zergling";"Larva";207
"Unit";"Zergling";"Larva";208
"Unit";"Zergling";"Larva";209
"Unit";"Zergling";"Larva";210
"Unit";"Zergling";"Larva";211
"Unit";"Zergling";"Larva";212
"Unit";"Zergling";"Larva";213
"Unit";"Zergling";"Larva";214
"Unit";"Zergling";"Larva";215
"Unit";"Zergling";"Larva";216
"Unit";"Zergling";"Larva";217
"Unit";"Zergling";"Larva";218
"Unit";"Zergling";"Larva";219
"Unit";"Zergling";"Larva";220
"Unit";"Zergling";"Larva";221
"Unit";"Zergling";"Larva";222
"Unit";"Zergling";"Larva";223
"Unit";"Zergling";"Larva";224
"Unit";"Zergling";"Larva";225
"Unit";"Baneling";"Zergling";226
"Unit";"Baneling";"Zergling";226
"Unit";"Baneling";"Zergling";226
"Unit";"Baneling";"Zergling";226
"Unit";"Baneling";"Zergling";226
"Unit";"Zergling";"Larva";226
"Unit";"Zergling";"Larva";227
"Unit";"Zergling";"Larva";228
"Unit";"Zergling";"Larva";229
"Unit";"Zergling";"Larva";230
"Unit";"Zergling";"Larva";231
"Unit";"Zergling";"Larva";232
"Unit";"Zergling";"Larva";233
"Unit";"Zergling";"Larva";234
"Unit";"Zergling";"Larva";235
"Unit";"Zergling";"Larva";236
"Unit";"Zergling";"Larva";237
"Unit";"Baneling";"Zergling";238
"Unit";"Baneling";"Zergling";238
"Unit";"Zergling";"Larva";238
"Unit";"Zergling";"Larva";239
"Unit";"Zergling";"Larva";240
"Unit";"Zergling";"Larva";241
"Unit";"Zergling";"Larva";242
"Unit";"Zergling";"Larva";243
"Unit";"Baneling";"Zergling";244
"Unit";"Baneling";"Zergling";244
"Unit";"Baneling";"Zergling";244
"Unit";"Zergling";"Larva";244
"Unit";"Zergling";"Larva";245
"Unit";"Zergling";"Larva";246
"Unit";"Zergling";"Larva";247
"Unit";"Zergling";"Larva";248
"Unit";"Zergling";"Larva";249
"Upgrade";"SprayZerg";NA;250
"Upgrade";"SprayZerg";NA;250
"Upgrade";"SprayZerg";NA;250
"Upgrade";"SprayZerg";NA;250
"Upgrade";"zerglingmovementspeed";NA;250
