"type";"unit_name";"on_building";"total_supply_lag";"supply"
"Building";"Pylon";NA;14;0
"Building";"Gateway";NA;16;0
"Building";"Assimilator";NA;17;0
"Building";"Nexus";NA;19;0
"Building";"CyberneticsCore";NA;20;0
"Building";"Assimilator";NA;21;0
"Building";"Pylon";NA;22;0
"Unit";"Adept";"Gateway";23;2
"Building";"TwilightCouncil";NA;27;0
"Unit";"Stalker";"Gateway";28;2
"Building";"RoboticsFacility";NA;34;0
"Building";"DarkShrine";NA;38;0
"Building";"Gateway";NA;40;0
"Building";"Gateway";NA;40;0
"Building";"Gateway";NA;40;0
"Building";"Pylon";NA;42;0
"Building";"Assimilator";NA;42;0
"Building";"Assimilator";NA;42;0
"Building";"Pylon";NA;44;0
"Building";"DarkTemplar";NA;49;0
"Building";"DarkTemplar";NA;49;0
"Building";"DarkTemplar";NA;49;0
"Building";"DarkTemplar";NA;49;0
"Building";"Pylon";NA;49;0
"Unit";"Immortal";"Robotics Facility";49;4
"Building";"Nexus";NA;53;0
"Unit";"Archon";"High Templar";53;0
"Unit";"Archon";"High Templar";53;0
"Upgrade";"Charge";"TwilightCouncil";54;0
"Building";"Gateway";NA;54;0
"Building";"Gateway";NA;54;0
"Unit";"Sentry";"Gateway";56;2
"Building";"Gateway";NA;58;0
"Building";"Gateway";NA;58;0
"Building";"Pylon";NA;58;0
"Building";"Pylon";NA;58;0
"Building";"TemplarArchive";NA;58;0
"Building";"Pylon";NA;58;0
"Unit";"Immortal";"Robotics Facility";58;4
"Building";"DarkTemplar";NA;64;0
"Building";"DarkTemplar";NA;64;0
"Unit";"Zealot";"Gateway";64;2
"Unit";"Zealot";"Gateway";66;2
"Unit";"Archon";"High Templar";69;0
"Building";"Forge";NA;72;0
"Unit";"Observer";"Robotics Facility";75;1
"Unit";"Phoenix";"Stargate";76;2
"Building";"Pylon";NA;79;0
"Building";"Assimilator";NA;80;0
"Building";"Pylon";NA;81;0
"Building";"Assimilator";NA;81;0
"Unit";"Zealot";"Gateway";81;2
"Unit";"Zealot";"Gateway";83;2
"Unit";"Zealot";"Gateway";85;2
"Unit";"Zealot";"Gateway";87;2
"Building";"DarkTemplar";NA;89;0
"Unit";"Sentry";"Gateway";92;2
"Unit";"Sentry";"Gateway";94;2
"Unit";"Immortal";"Robotics Facility";97;4
"Building";"Pylon";NA;103;0
"Upgrade";"ProtossGroundWeaponsLevel1";"Forge";103;0
"Building";"Pylon";NA;104;0
"Building";"PhotonCannon";NA;107;0
"Building";"PhotonCannon";NA;108;0
"Building";"PhotonCannon";NA;108;0
"Unit";"Immortal";"Robotics Facility";108;4
"Building";"HighTemplar";NA;112;0
"Building";"HighTemplar";NA;112;0
"Building";"HighTemplar";NA;112;0
"Building";"HighTemplar";NA;112;0
"Unit";"Archon";"High Templar";112;0
"Unit";"Archon";"High Templar";112;0
"Building";"Pylon";NA;112;0
"Building";"HighTemplar";NA;112;0
"Building";"HighTemplar";NA;112;0
"Unit";"Zealot";"Gateway";112;2
"Unit";"Archon";"High Templar";114;0
"Building";"DarkTemplar";NA;114;0
"Unit";"Zealot";"Gateway";114;2
"Unit";"Zealot";"Gateway";116;2
"Unit";"Zealot";"Gateway";118;2
"Unit";"Zealot";"Gateway";120;2
"Unit";"Zealot";"Gateway";122;2
"Building";"Gateway";NA;124;0
"Building";"Gateway";NA;124;0
"Building";"Pylon";NA;124;0
"Building";"Pylon";NA;124;0
"Unit";"Zealot";"Gateway";124;2
"Unit";"Zealot";"Gateway";126;2
"Unit";"Zealot";"Gateway";128;2
"Unit";"Zealot";"Gateway";130;2
"Building";"Pylon";NA;132;0
"Building";"Pylon";NA;132;0
"Unit";"Zealot";"Gateway";132;2
"Unit";"Zealot";"Gateway";134;2
"Building";"HighTemplar";NA;136;0
"Building";"HighTemplar";NA;136;0
"Building";"PhotonCannon";NA;136;0
"Building";"HighTemplar";NA;136;0
"Building";"HighTemplar";NA;136;0
"Unit";"Zealot";"Gateway";136;2
"Building";"PhotonCannon";NA;138;0
"Unit";"Archon";"High Templar";138;0
"Unit";"Archon";"High Templar";138;0
"Building";"PhotonCannon";NA;138;0
"Building";"PhotonCannon";NA;138;0
"Building";"PhotonCannon";NA;138;0
"Building";"PhotonCannon";NA;138;0
"Building";"DarkTemplar";NA;138;0
"Building";"DarkTemplar";NA;138;0
"Building";"DarkTemplar";NA;138;0
"Building";"DarkTemplar";NA;138;0
"Building";"PhotonCannon";NA;138;0
"Unit";"Archon";"High Templar";138;0
"Unit";"Zealot";"Gateway";138;2
"Unit";"Zealot";"Gateway";140;2
"Unit";"Zealot";"Gateway";142;2
"Unit";"Zealot";"Gateway";144;2
"Unit";"Zealot";"Gateway";146;2
"Unit";"Zealot";"Gateway";148;2
"Unit";"Zealot";"Gateway";150;2
"Building";"DarkTemplar";NA;152;0
"Building";"DarkTemplar";NA;152;0
"Unit";"Archon";"High Templar";152;0
"Building";"PhotonCannon";NA;152;0
"Building";"PhotonCannon";NA;152;0
"Building";"Nexus";NA;152;0
"Building";"Pylon";NA;152;0
"Unit";"Phoenix";"Stargate";152;2
"Unit";"Phoenix";"Stargate";154;2
"Building";"Pylon";NA;156;0
"Upgrade";"SprayProtoss";NA;156;0
"Upgrade";"SprayProtoss";NA;156;0
"Upgrade";"WarpGateResearch";NA;156;0
"Upgrade";"SprayProtoss";NA;156;0
"Upgrade";"SprayProtoss";NA;156;0
"Upgrade";"SprayProtoss";NA;156;0
"Upgrade";"SprayProtoss";NA;156;0
