"type";"unit_name";"on_building";"total_supply";"supply"
"Building";"Refinery";NA;14;0
"Building";"Barracks";NA;15;0
"Unit";"Reaper";"Barracks";19;1
"Building";"Factory";NA;19;0
"Building";"BarracksReactor";NA;21;0
"Building";"CommandCenter";NA;19;0
"Building";"Bunker";NA;22;0
"Unit";"Hellion";"Factory";23;2
"Unit";"Marine";"Barracks";23;1
"Unit";"Marine";"Barracks";23;1
"Building";"Starport";NA;23;0
"Unit";"Hellion";"Factory";25;2
"Unit";"Marine";"Barracks";30;1
"Unit";"Marine";"Barracks";30;1
"Unit";"Hellion";"Factory";33;2
"Unit";"Medivac";"Starport";30;2
"Unit";"Marine";"Barracks";36;1
"Unit";"Marine";"Barracks";36;1
"Unit";"Marine";"Barracks";43;1
"Unit";"Marine";"Barracks";44;1
"Building";"StarportTechLab";NA;48;0
"Building";"FactoryTechLab";NA;48;0
"Building";"EngineeringBay";NA;50;0
"Building";"Refinery";NA;51;0
"Building";"Refinery";NA;51;0
"Unit";"Marine";"Barracks";52;1
"Unit";"Marine";"Barracks";52;1
"Building";"Refinery";NA;52;0
"Building";"Barracks";NA;50;0
"Building";"Barracks";NA;51;0
"Building";"StarportReactor";NA;54;0
"Unit";"Marine";"Barracks";61;1
"Unit";"Marine";"Barracks";61;1
"Unit";"Marauder";"Barracks";61;2
"Building";"Barracks";NA;58;0
"Unit";"Marine";"Barracks";70;1
"Unit";"Marine";"Barracks";70;1
"Unit";"Marauder";"Barracks";70;2
"Unit";"Marauder";"Barracks";70;2
"Unit";"Medivac";"Starport";70;2
"Unit";"Medivac";"Starport";71;2
"Building";"Barracks";NA;66;0
"Building";"BarracksReactor";NA;71;0
"Building";"FactoryReactor";NA;71;0
"Unit";"Marine";"Barracks";78;1
"Unit";"Marine";"Barracks";78;1
"Unit";"Marauder";"Barracks";78;2
"Unit";"Marauder";"Barracks";78;2
"Unit";"Medivac";"Starport";78;2
"Unit";"Marine";"Barracks";84;1
"Unit";"Marine";"Barracks";84;1
"Building";"BarracksReactor";NA;82;0
"Unit";"Marauder";"Barracks";88;2
"Unit";"Medivac";"Starport";84;2
"Unit";"Marauder";"Barracks";88;2
"Unit";"Marine";"Barracks";90;1
"Unit";"Marine";"Barracks";90;1
"Building";"CommandCenter";NA;72;0
"Unit";"Marine";"Barracks";92;1
"Unit";"Marine";"Barracks";92;1
"Upgrade";"Stimpack";"TechLab";72;0
"Unit";"Marine";"Barracks";96;1
"Unit";"Marine";"Barracks";96;1
"Unit";"Marine";"Barracks";102;1
"Unit";"Marine";"Barracks";102;1
"Unit";"Marine";"Barracks";102;1
"Unit";"Marine";"Barracks";102;1
"Unit";"Marine";"Barracks";102;1
"Unit";"Marine";"Barracks";102;1
"Unit";"Marine";"Barracks";104;1
"Building";"Armory";NA;92;0
"Unit";"Liberator";"Starport";96;3
"Upgrade";"TerranInfantryWeaponsLevel1";"EngineeringBay";82;0
"Unit";"Liberator";"Starport";100;3
"Unit";"Marauder";"Barracks";105;2
"Unit";"Marauder";"Barracks";110;2
"Unit";"Marine";"Barracks";114;1
"Unit";"Marine";"Barracks";114;1
"Unit";"Marine";"Barracks";114;1
