"Type";"UnitName";"OnBuilding";"TotalSupply";"Supply"
"Unit";"SCV";"Command Center";12;1
"Unit";"SCV";"Command Center";12;1
"Unit";"SCV";"Command Center";13;1
"Building";"SupplyDepot";NA;13;0
"Building";"Refinery";NA;14;0
"Unit";"SCV";"Command Center";15;1
"Unit";"SCV";"Command Center";15;1
"Unit";"SCV";"Command Center";16;1
"Unit";"SCV";"Command Center";17;1
"Building";"Barracks";NA;15;0
"Unit";"Marine";"Barracks";19;1
"Building";"SupplyDepot";NA;19;0
"Unit";"SCV";"Command Center";20;1
"Building";"Factory";NA;19;0
"Unit";"SCV";"Command Center";20;1
"Building";"BarracksReactor";NA;20;0
"Unit";"SCV";"Command Center";22;1
"Unit";"SCV";"Command Center";22;1
"Building";"BarracksTechLab";NA;23;0
"Unit";"Hellion";"Factory";22;2
"Unit";"Hellion";"Factory";22;2
"Unit";"SCV";"Command Center";23;1
"Building";"SupplyDepot";NA;23;0
"Unit";"SCV";"Command Center";29;1
"Unit";"Marine";"Barracks";29;1
"Building";"Refinery";NA;29;0
"Unit";"SCV";"Command Center";30;1
"Building";"CommandCenter";NA;21;0
"Building";"SupplyDepot";NA;30;0
"Unit";"SCV";"Command Center";31;1
"Unit";"Marine";"Barracks";31;1
"Building";"FactoryReactor";NA;29;0
"Building";"Barracks";NA;29;0
"Building";"Barracks";NA;29;0
"Unit";"SCV";"Command Center";34;1
"Building";"EngineeringBay";NA;32;0
"Unit";"Marine";"Barracks";34;1
"Unit";"SCV";"Command Center";35;1
"Unit";"SCV";"Command Center";37;1
"Unit";"Marine";"Barracks";35;1
"Unit";"Marine";"Barracks";35;1
"Unit";"Marine";"Barracks";35;1
"Unit";"SCV";"Command Center";37;1
"Unit";"Marine";"Barracks";36;1
"Building";"MissileTurret";NA;36;0
"Building";"MissileTurret";NA;37;0
"Unit";"Marine";"Barracks";37;1
"Unit";"SCV";"Command Center";43;1
"Unit";"SCV";"Command Center";43;1
"Unit";"Marine";"Barracks";43;1
"Unit";"Marine";"Barracks";44;1
"Unit";"Marine";"Barracks";44;1
"Unit";"Marine";"Barracks";44;1
"Unit";"SCV";"Command Center";46;1
"Building";"Starport";NA;43;0
"Unit";"SCV";"Command Center";46;1
"Building";"FactoryReactor";NA;43;0
"Unit";"Marine";"Barracks";45;1
"Upgrade";"Stimpack";"TechLab";32;0
"Building";"Refinery";NA;45;0
"Unit";"Marine";"Barracks";47;1
"Unit";"SCV";"Command Center";50;1
"Unit";"SCV";"Command Center";51;1
"Unit";"Marine";"Barracks";50;1
"Building";"SupplyDepot";NA;48;0
"Unit";"SCV";"Command Center";54;1
"Unit";"Marine";"Barracks";53;1
"Unit";"SCV";"Command Center";55;1
"Unit";"Marine";"Barracks";57;1
"Unit";"Marine";"Barracks";57;1
"Unit";"SCV";"Command Center";57;1
"Unit";"Marine";"Barracks";57;1
"Unit";"Marine";"Barracks";58;1
"Unit";"Medivac";"Starport";55;2
"Unit";"Medivac";"Starport";56;2
"Building";"FactoryTechLab";NA;60;0
"Unit";"SCV";"Command Center";62;1
"Unit";"SCV";"Command Center";64;1
"Unit";"Marine";"Barracks";60;1
"Unit";"Marine";"Barracks";60;1
"Unit";"Marine";"Barracks";61;1
"Unit";"Marine";"Barracks";64;1
"Building";"SupplyDepot";NA;64;0
"Building";"SupplyDepot";NA;69;0
"Building";"SupplyDepot";NA;74;0
"Building";"SupplyDepot";NA;74;0
"Unit";"SCV";"Command Center";75;1
"Unit";"SCV";"Command Center";75;1
"Unit";"Marine";"Barracks";75;1
"Unit";"Marine";"Barracks";75;1
"Unit";"Marine";"Barracks";75;1
"Unit";"Marine";"Barracks";75;1
"Upgrade";"TerranInfantryWeaponsLevel1";"EngineeringBay";52;0
"Unit";"Marine";"Barracks";75;1
"Building";"SupplyDepot";NA;75;0
"Unit";"Medivac";"Starport";75;2
"Unit";"Medivac";"Starport";75;2
"Unit";"Marine";"Barracks";82;1
"Unit";"Marine";"Barracks";82;1
"Unit";"Marine";"Barracks";82;1
"Unit";"Marine";"Barracks";82;1
"Unit";"Marine";"Barracks";82;1
"Unit";"Marine";"Barracks";91;1
"Unit";"Marine";"Barracks";91;1
"Unit";"Marine";"Barracks";91;1
"Unit";"SCV";"Command Center";91;1
"Unit";"Marine";"Barracks";91;1
"Unit";"Marine";"Barracks";91;1
"Unit";"SCV";"Command Center";91;1
"Unit";"Medivac";"Starport";91;2
"Unit";"Medivac";"Starport";91;2
"Building";"SupplyDepot";NA;91;0
"Building";"SupplyDepot";NA;91;0
"Building";"Barracks";NA;91;0
"Building";"Barracks";NA;91;0
"Unit";"Marine";"Barracks";102;1
"Unit";"Marine";"Barracks";102;1
"Unit";"Marine";"Barracks";102;1
"Unit";"Marine";"Barracks";102;1
"Unit";"Marine";"Barracks";102;1
"Building";"CommandCenter";NA;91;0
"Unit";"Marine";"Barracks";102;1
"Unit";"Marine";"Barracks";103;1
"Unit";"Marine";"Barracks";104;1
"Unit";"Marine";"Barracks";106;1
"Unit";"Medivac";"Starport";102;2
"Unit";"Marine";"Barracks";107;1
"Unit";"Medivac";"Starport";102;2
"Unit";"Marine";"Barracks";107;1
"Unit";"Marine";"Barracks";109;1
"Unit";"Marine";"Barracks";110;1
"Building";"BarracksReactor";NA;106;0
"Building";"BarracksReactor";NA;106;0
"Unit";"Marine";"Barracks";110;1
"Unit";"Marine";"Barracks";113;1
"Building";"Factory";NA;106;0
"Unit";"Marine";"Barracks";116;1
"Unit";"Marine";"Barracks";117;1
"Unit";"Marine";"Barracks";118;1
"Unit";"SCV";"Command Center";121;1
"Unit";"SCV";"Command Center";121;1
"Unit";"Marine";"Barracks";119;1
"Unit";"Marine";"Barracks";119;1
"Unit";"Marine";"Barracks";119;1
"Unit";"Marine";"Barracks";119;1
"Unit";"Marine";"Barracks";120;1
"Unit";"Marine";"Barracks";121;1
"Unit";"Marine";"Barracks";121;1
"Unit";"SCV";"Command Center";124;1
"Unit";"SCV";"Command Center";125;1
"Unit";"Marine";"Barracks";122;1
"Unit";"Medivac";"Starport";119;2
"Unit";"Medivac";"Starport";119;2
"Unit";"Marine";"Barracks";128;1
"Unit";"Marine";"Barracks";129;1
"Unit";"Marine";"Barracks";129;1
"Unit";"Marine";"Barracks";132;1
"Unit";"Marine";"Barracks";132;1
"Unit";"Marine";"Barracks";132;1
"Unit";"Marine";"Barracks";132;1
"Unit";"SCV";"Command Center";133;1
"Unit";"SCV";"Command Center";134;1
"Unit";"Marine";"Barracks";132;1
"Unit";"Marine";"Barracks";135;1
"Unit";"Marine";"Barracks";140;1
"Unit";"Marine";"Barracks";141;1
"Unit";"Marine";"Barracks";142;1
"Building";"FactoryTechLab";NA;143;0
"Unit";"Marine";"Barracks";143;1
"Unit";"Medivac";"Starport";136;2
"Unit";"Medivac";"Starport";140;2
"Unit";"Marine";"Barracks";151;1
"Unit";"Marine";"Barracks";151;1
"Unit";"Marine";"Barracks";151;1
"Unit";"Marine";"Barracks";159;1
"Unit";"Marine";"Barracks";159;1
"Unit";"Marine";"Barracks";159;1
"Unit";"Marine";"Barracks";159;1
"Unit";"Marine";"Barracks";162;1
"Unit";"Marine";"Barracks";162;1
