"Type";"UnitName";"OnBuilding";"TotalSupply";"Supply"
"Unit";"SCV";"Command Center";12;1
"Unit";"SCV";"Command Center";12;1
"Unit";"SCV";"Command Center";13;1
"Building";"SupplyDepot";NA;13;0
"Building";"Refinery";NA;14;0
"Unit";"SCV";"Command Center";15;1
"Unit";"SCV";"Command Center";15;1
"Unit";"SCV";"Command Center";16;1
"Unit";"SCV";"Command Center";17;1
"Building";"Barracks";NA;15;0
"Unit";"Reaper";"Barracks";19;1
"Unit";"SCV";"Command Center";19;1
"Building";"SupplyDepot";NA;19;0
"Unit";"SCV";"Command Center";20;1
"Unit";"SCV";"Command Center";21;1
"Unit";"SCV";"Command Center";22;1
"Building";"BarracksReactor";NA;21;0
"Building";"CommandCenter";NA;19;0
"Unit";"SCV";"Command Center";23;1
"Unit";"SCV";"Command Center";24;1
"Unit";"Marine";"Barracks";24;1
"Unit";"Marine";"Barracks";24;1
"Building";"Factory";NA;22;0
"Building";"Bunker";NA;23;0
"Unit";"SCV";"Command Center";25;1
"Unit";"Marine";"Barracks";28;1
"Unit";"Marine";"Barracks";28;1
"Unit";"SCV";"Command Center";29;1
"Unit";"SCV";"Command Center";29;1
"Building";"Starport";NA;28;0
"Building";"Refinery";NA;29;0
"Unit";"SCV";"Command Center";31;1
"Unit";"Marine";"Barracks";30;1
"Unit";"Marine";"Barracks";31;1
"Unit";"SCV";"Command Center";32;1
"Unit";"SCV";"Command Center";33;1
"Unit";"SCV";"Command Center";36;1
"Building";"SupplyDepot";NA;33;0
"Unit";"SCV";"Command Center";37;1
"Unit";"Medivac";"Starport";33;2
"Unit";"SCV";"Command Center";39;1
"Building";"FactoryTechLab";NA;38;0
"Unit";"SCV";"Command Center";39;1
"Building";"Barracks";NA;32;0
"Unit";"SCV";"Command Center";42;1
"Building";"StarportTechLab";NA;42;0
"Building";"Barracks";NA;34;0
"Unit";"SCV";"Command Center";43;1
"Building";"SupplyDepot";NA;40;0
"Unit";"SCV";"Command Center";44;1
"Unit";"SCV";"Command Center";46;1
"Unit";"Marine";"Barracks";45;1
"Unit";"Marine";"Barracks";45;1
"Unit";"Marine";"Barracks";45;1
"Building";"SupplyDepot";NA;45;0
"Unit";"SCV";"Command Center";47;1
"Unit";"SCV";"Command Center";47;1
"Building";"SupplyDepot";NA;47;0
"Building";"SupplyDepot";NA;47;0
"Unit";"Marine";"Barracks";47;1
"Unit";"Marine";"Barracks";48;1
"Unit";"Marine";"Barracks";49;1
"Building";"FactoryReactor";NA;45;0
"Unit";"Marine";"Barracks";50;1
"Building";"StarportReactor";NA;47;0
"Unit";"Marine";"Barracks";53;1
"Unit";"SCV";"Command Center";57;1
"Unit";"SCV";"Command Center";57;1
"Unit";"Marine";"Barracks";57;1
"Unit";"Marine";"Barracks";57;1
"Unit";"Marauder";"Barracks";57;2
"Unit";"Marine";"Barracks";58;1
"Building";"SupplyDepot";NA;58;0
"Building";"SupplyDepot";NA;58;0
"Unit";"Medivac";"Starport";57;2
"Unit";"Medivac";"Starport";57;2
"Building";"Refinery";NA;60;0
"Unit";"Marine";"Barracks";60;1
"Unit";"Marine";"Barracks";69;1
"Unit";"Marine";"Barracks";69;1
"Unit";"Marine";"Barracks";69;1
"Unit";"Marine";"Barracks";69;1
"Unit";"SCV";"Command Center";70;1
"Unit";"SCV";"Command Center";70;1
"Unit";"Medivac";"Starport";69;2
"Unit";"Marine";"Barracks";73;1
"Building";"Refinery";NA;70;0
"Unit";"Marine";"Barracks";73;1
"Building";"SupplyDepot";NA;70;0
"Building";"EngineeringBay";NA;70;0
"Unit";"Marauder";"Barracks";73;2
"Unit";"Marauder";"Barracks";73;2
"Upgrade";"Stimpack";"TechLab";56;0
"Unit";"SCV";"Command Center";78;1
"Unit";"SCV";"Command Center";78;1
"Unit";"Medivac";"Starport";74;2
"Building";"SupplyDepot";NA;80;0
"Building";"SupplyDepot";NA;84;0
"Unit";"Marine";"Barracks";88;1
"Unit";"Marine";"Barracks";88;1
"Unit";"Marauder";"Barracks";88;2
"Unit";"Marauder";"Barracks";88;2
"Building";"SupplyDepot";NA;88;0
"Building";"SupplyDepot";NA;88;0
"Unit";"Marine";"Barracks";94;1
"Unit";"Marine";"Barracks";94;1
"Unit";"SCV";"Command Center";94;1
"Building";"MissileTurret";NA;94;0
"Unit";"SCV";"Command Center";94;1
"Unit";"Marauder";"Barracks";94;2
"Unit";"Marauder";"Barracks";94;2
"Building";"Barracks";NA;88;0
"Building";"Barracks";NA;88;0
"Unit";"Medivac";"Starport";94;2
"Unit";"Medivac";"Starport";94;2
"Building";"Barracks";NA;88;0
"Building";"SupplyDepot";NA;94;0
"Building";"MissileTurret";NA;102;0
"Unit";"Marine";"Barracks";102;1
"Unit";"Marine";"Barracks";102;1
"Unit";"Marauder";"Barracks";102;2
"Unit";"Marauder";"Barracks";102;2
"Building";"BarracksTechLab";NA;104;0
"Building";"BarracksTechLab";NA;104;0
"Building";"BarracksTechLab";NA;106;0
"Unit";"SCV";"Command Center";106;1
"Unit";"SCV";"Command Center";106;1
"Building";"CommandCenter";NA;88;0
"Unit";"Medivac";"Starport";106;2
"Upgrade";"TerranInfantryWeaponsLevel1";"EngineeringBay";94;0
"Unit";"SCV";"Command Center";114;1
"Unit";"SCV";"Command Center";114;1
"Unit";"Marine";"Barracks";114;1
"Unit";"Marine";"Barracks";114;1
"Unit";"Marauder";"Barracks";114;2
"Unit";"Marauder";"Barracks";114;2
"Unit";"Marauder";"Barracks";114;2
"Unit";"Marauder";"Barracks";114;2
"Unit";"Marauder";"Barracks";114;2
"Unit";"Medivac";"Starport";114;2
"Unit";"Marine";"Barracks";120;1
"Unit";"Marauder";"Barracks";120;2
"Unit";"Marauder";"Barracks";122;2
"Unit";"Marauder";"Barracks";124;2
"Unit";"Marauder";"Barracks";139;2
"Unit";"Marauder";"Barracks";139;2
"Unit";"Marauder";"Barracks";139;2
"Unit";"Marauder";"Barracks";139;2
"Unit";"Marine";"Barracks";139;1
"Unit";"Marine";"Barracks";139;1
"Unit";"Marauder";"Barracks";139;2
