"type";"unit_name";"on_building";"total_supply";"supply"
"Building";"Refinery";NA;15;0
"Building";"Barracks";NA;15;0
"Unit";"Reaper";"Barracks";19;1
"Building";"Barracks";NA;19;0
"Building";"BarracksReactor";NA;20;0
"Building";"CommandCenter";NA;19;0
"Unit";"Marine";"Barracks";23;1
"Unit";"Marine";"Barracks";23;1
"Building";"BarracksTechLab";NA;23;0
"Building";"Refinery";NA;23;0
"Building";"Factory";NA;22;0
"Unit";"Marine";"Barracks";27;1
"Unit";"Marine";"Barracks";27;1
"Building";"Bunker";NA;24;0
"Unit";"Marine";"Barracks";30;1
"Unit";"Marine";"Barracks";30;1
"Unit";"Marine";"Barracks";32;1
"Unit";"Marine";"Barracks";33;1
"Unit";"Marine";"Barracks";33;1
"Building";"FactoryReactor";NA;33;0
"Building";"Starport";NA;33;0
"Unit";"Marine";"Barracks";38;1
"Unit";"Marine";"Barracks";38;1
"Unit";"Marine";"Barracks";40;1
"Building";"EngineeringBay";NA;38;0
"Unit";"Marine";"Barracks";46;1
"Unit";"Marine";"Barracks";46;1
"Unit";"Marine";"Barracks";46;1
"Building";"MissileTurret";NA;47;0
"Unit";"Medivac";"Starport";46;2
"Unit";"Medivac";"Starport";46;2
"Unit";"Marine";"Barracks";52;1
"Unit";"Marine";"Barracks";52;1
"Unit";"Marine";"Barracks";52;1
"Upgrade";"Stimpack";"TechLab";33;0
"Building";"MissileTurret";NA;52;0
"Building";"Refinery";NA;54;0
"Unit";"Marine";"Barracks";61;1
"Unit";"Marine";"Barracks";61;1
"Unit";"Marine";"Barracks";62;1
"Unit";"Marine";"Barracks";69;1
"Unit";"Marine";"Barracks";69;1
"Unit";"Marine";"Barracks";69;1
"Unit";"Marine";"Barracks";71;1
"Unit";"Marine";"Barracks";72;1
"Unit";"Marine";"Barracks";73;1
"Unit";"Medivac";"Starport";71;2
"Unit";"Medivac";"Starport";71;2
"Building";"Refinery";NA;76;0
"Upgrade";"TerranInfantryWeaponsLevel1";"EngineeringBay";61;0
"Unit";"Marine";"Barracks";78;1
"Unit";"Marine";"Barracks";79;1
"Building";"FactoryReactor";NA;73;0
"Unit";"Marauder";"Barracks";79;2
"Building";"CommandCenter";NA;66;0
"Building";"Barracks";NA;73;0
"Building";"Barracks";NA;75;0
"Unit";"Marine";"Barracks";86;1
"Unit";"Marauder";"Barracks";88;2
"Unit";"Marine";"Barracks";93;1
"Building";"BarracksTechLab";NA;93;0
"Building";"MissileTurret";NA;93;0
"Unit";"Marine";"Barracks";97;1
"Unit";"Marauder";"Barracks";93;2
"Building";"BarracksReactor";NA;93;0
"Unit";"Medivac";"Starport";97;2
"Unit";"Medivac";"Starport";97;2
"Unit";"Marine";"Barracks";98;1
"Building";"Barracks";NA;93;0
"Unit";"Marine";"Barracks";103;1
"Unit";"Marine";"Barracks";103;1
"Unit";"Marauder";"Barracks";103;2
"Unit";"Marauder";"Barracks";103;2
"Unit";"Marine";"Barracks";109;1
"Unit";"Marine";"Barracks";109;1
"Building";"Barracks";NA;93;0
"Unit";"Medivac";"Starport";104;2
"Unit";"Marine";"Barracks";119;1
"Unit";"Marine";"Barracks";119;1
"Unit";"Marine";"Barracks";119;1
"Building";"BarracksTechLab";NA;119;0
"Building";"BarracksTechLab";NA;119;0
"Unit";"Marauder";"Barracks";119;2
"Upgrade";"TerranInfantryArmorsLevel1";"EngineeringBay";97;0
"Unit";"Marauder";"Barracks";121;2
"Unit";"Marine";"Barracks";121;1
"Unit";"Marine";"Barracks";126;1
"Unit";"Medivac";"Starport";121;2
"Unit";"Medivac";"Starport";121;2
"Unit";"Marauder";"Barracks";124;2
"Unit";"Marine";"Barracks";129;1
"Unit";"Marine";"Barracks";129;1
"Building";"EngineeringBay";NA;126;0
"Unit";"Marauder";"Barracks";131;2
"Unit";"Marine";"Barracks";135;1
"Unit";"Marine";"Barracks";136;1
"Unit";"Marine";"Barracks";140;1
"Unit";"Marauder";"Barracks";136;2
"Unit";"Marine";"Barracks";142;1
"Unit";"Marauder";"Barracks";142;2
"Building";"Armory";NA;128;0
"Unit";"Marine";"Barracks";147;1
"Unit";"Marine";"Barracks";147;1
"Unit";"Marine";"Barracks";148;1
"Unit";"Marauder";"Barracks";147;2
"Unit";"Medivac";"Starport";147;2
"Unit";"Medivac";"Starport";147;2
"Building";"Refinery";NA;155;0
"Building";"Refinery";NA;155;0
"Unit";"Marine";"Barracks";155;1
"Unit";"Marine";"Barracks";155;1
"Unit";"Marine";"Barracks";155;1
"Unit";"Marauder";"Barracks";155;2
"Unit";"Marauder";"Barracks";155;2
"Unit";"Marine";"Barracks";160;1
"Unit";"Marine";"Barracks";160;1
"Unit";"Marauder";"Barracks";160;2
"Unit";"Marine";"Barracks";169;1
"Unit";"Marine";"Barracks";169;1
"Unit";"Marauder";"Barracks";169;2
"Unit";"Marauder";"Barracks";169;2
"Unit";"Marine";"Barracks";174;1
"Unit";"Marine";"Barracks";175;1
"Unit";"Marauder";"Barracks";176;2
"Unit";"Marine";"Barracks";180;1
"Unit";"Marine";"Barracks";188;1
"Unit";"Marine";"Barracks";188;1
"Unit";"Marine";"Barracks";188;1
"Unit";"Marine";"Barracks";190;1
"Unit";"Marauder";"Barracks";188;2
"Unit";"Marauder";"Barracks";190;2
"Building";"Starport";NA;180;0
"Unit";"Marine";"Barracks";191;1
"Building";"CommandCenter";NA;160;0
"Unit";"Marine";"Barracks";191;1
"Unit";"Marine";"Barracks";192;1
"Unit";"Marauder";"Barracks";191;2
"Unit";"Marauder";"Barracks";195;2
"Unit";"Marine";"Barracks";200;1
"Unit";"Marine";"Barracks";200;1
"Unit";"Marine";"Barracks";200;1
"Building";"MissileTurret";NA;201;0
"Unit";"Marauder";"Barracks";200;2
"Unit";"Marauder";"Barracks";200;2
"Building";"FactoryReactor";NA;199;0
"Unit";"Marine";"Barracks";208;1
"Unit";"Marine";"Barracks";208;1
"Unit";"Marine";"Barracks";208;1
"Unit";"Marine";"Barracks";209;1
"Unit";"Marauder";"Barracks";208;2
"Upgrade";"TerranShipWeaponsLevel1";"Armory";186;0
"Building";"Refinery";NA;211;0
"Unit";"Marauder";"Barracks";211;2
"Building";"Refinery";NA;215;0
"Upgrade";"TerranInfantryWeaponsLevel2";"EngineeringBay";188;0
"Upgrade";"TerranInfantryArmorsLevel2";"EngineeringBay";188;0
"Building";"GhostAcademy";NA;229;0
