"Type";"UnitName";"OnBuilding";"TotalSupply";"Supply"
"Unit";"SCV";"Command Center";12;1
"Unit";"SCV";"Command Center";12;1
"Unit";"SCV";"Command Center";13;1
"Building";"SupplyDepot";NA;13;0
"Unit";"SCV";"Command Center";15;1
"Unit";"SCV";"Command Center";15;1
"Building";"Refinery";NA;15;0
"Unit";"SCV";"Command Center";16;1
"Building";"Barracks";NA;15;0
"Unit";"SCV";"Command Center";17;1
"Unit";"Reaper";"Barracks";19;1
"Unit";"SCV";"Command Center";19;1
"Unit";"Marine";"Barracks";20;1
"Unit";"SCV";"Command Center";21;1
"Building";"SupplyDepot";NA;21;0
"Building";"Refinery";NA;21;0
"Unit";"SCV";"Command Center";23;1
"Building";"Factory";NA;20;0
"Unit";"SCV";"Command Center";23;1
"Building";"CommandCenter";NA;19;0
"Building";"BarracksReactor";NA;22;0
"Unit";"SCV";"Command Center";24;1
"Building";"Bunker";NA;24;0
"Unit";"Marine";"Barracks";25;1
"Unit";"SCV";"Command Center";26;1
"Unit";"Marine";"Barracks";25;1
"Building";"Starport";NA;25;0
"Unit";"SCV";"Command Center";27;1
"Building";"FactoryTechLab";NA;26;0
"Unit";"SCV";"Command Center";29;1
"Unit";"Marine";"Barracks";29;1
"Unit";"Marine";"Barracks";29;1
"Unit";"SCV";"Command Center";29;1
"Unit";"SCV";"Command Center";31;1
"Building";"FactoryTechLab";NA;33;0
"Unit";"Marine";"Barracks";33;1
"Unit";"Marine";"Barracks";33;1
"Unit";"SCV";"Command Center";34;1
"Unit";"SCV";"Command Center";35;1
"Unit";"SCV";"Command Center";37;1
"Building";"SupplyDepot";NA;35;0
"Unit";"Marine";"Barracks";38;1
"Building";"SupplyDepot";NA;37;0
"Unit";"Raven";"Starport";33;2
"Unit";"Marine";"Barracks";40;1
"Unit";"SCV";"Command Center";40;1
"Unit";"SCV";"Command Center";40;1
"Building";"Refinery";NA;43;0
"Building";"SupplyDepot";NA;43;0
"Unit";"SCV";"Command Center";46;1
"Unit";"SCV";"Command Center";46;1
"Building";"Barracks";NA;39;0
"Building";"SupplyDepot";NA;46;0
"Unit";"Marine";"Barracks";47;1
"Building";"Barracks";NA;41;0
"Building";"SupplyDepot";NA;48;0
"Unit";"SCV";"Command Center";48;1
"Unit";"SCV";"Command Center";48;1
"Building";"StarportReactor";NA;46;0
"Unit";"Marine";"Barracks";48;1
"Unit";"Marine";"Barracks";48;1
"Unit";"SCV";"Command Center";49;1
"Unit";"SCV";"Command Center";50;1
"Unit";"Marine";"Barracks";50;1
"Building";"SupplyDepot";NA;49;0
"Unit";"Marine";"Barracks";51;1
"Unit";"SCV";"Command Center";55;1
"Unit";"Marine";"Barracks";54;1
"Building";"SupplyDepot";NA;51;0
"Unit";"Marine";"Barracks";55;1
"Unit";"Marine";"Barracks";55;1
"Unit";"SCV";"Command Center";56;1
"Unit";"Marine";"Barracks";56;1
"Unit";"SCV";"Command Center";57;1
"Building";"SupplyDepot";NA;56;0
"Unit";"Medivac";"Starport";55;2
"Unit";"Marine";"Barracks";56;1
"Building";"SupplyDepot";NA;56;0
"Unit";"Marine";"Barracks";59;1
"Unit";"Marine";"Barracks";59;1
"Unit";"Marine";"Barracks";60;1
"Unit";"Marine";"Barracks";62;1
"Unit";"SCV";"Command Center";67;1
"Unit";"SCV";"Command Center";67;1
"Unit";"Marine";"Barracks";66;1
"Building";"EngineeringBay";NA;70;0
"Unit";"Marine";"Barracks";73;1
"Unit";"Marine";"Barracks";74;1
"Unit";"Marine";"Barracks";74;1
"Unit";"Marine";"Barracks";74;1
"Unit";"SCV";"Command Center";74;1
"Unit";"Marine";"Barracks";74;1
"Unit";"SCV";"Command Center";74;1
"Building";"Refinery";NA;74;0
"Unit";"Marine";"Barracks";74;1
"Building";"StarportReactor";NA;74;0
"Unit";"Marine";"Barracks";81;1
"Unit";"Marine";"Barracks";81;1
"Unit";"Marine";"Barracks";81;1
"Unit";"Marine";"Barracks";81;1
"Building";"CommandCenter";NA;71;0
"Unit";"Marine";"Barracks";86;1
"Unit";"Marine";"Barracks";86;1
"Unit";"Marine";"Barracks";86;1
"Unit";"Marine";"Barracks";86;1
"Unit";"Marine";"Barracks";86;1
"Building";"Barracks";NA;81;0
"Building";"Barracks";NA;82;0
"Unit";"Marine";"Barracks";86;1
"Unit";"Marine";"Barracks";87;1
"Building";"EngineeringBay";NA;86;0
"Unit";"Liberator";"Starport";86;3
"Unit";"Liberator";"Starport";86;3
"Unit";"Marine";"Barracks";91;1
"Unit";"Marine";"Barracks";91;1
"Unit";"Marine";"Barracks";91;1
"Unit";"Marine";"Barracks";93;1
"Unit";"Marine";"Barracks";93;1
"Unit";"SCV";"Command Center";102;1
"Unit";"SCV";"Command Center";102;1
"Unit";"Marine";"Barracks";102;1
"Unit";"Marine";"Barracks";102;1
"Unit";"Marine";"Barracks";102;1
"Upgrade";"Stimpack";"TechLab";82;0
"Building";"SupplyDepot";NA;102;0
"Building";"BarracksReactor";NA;93;0
"Building";"BarracksReactor";NA;93;0
"Unit";"SCV";"Command Center";104;1
"Building";"SupplyDepot";NA;104;0
"Unit";"SCV";"Command Center";105;1
"Unit";"Marine";"Barracks";105;1
"Unit";"SCV";"Command Center";109;1
"Unit";"SCV";"Command Center";110;1
"Upgrade";"TerranInfantryWeaponsLevel1";"EngineeringBay";86;0
"Building";"Factory";NA;102;0
"Unit";"Marine";"Barracks";111;1
"Unit";"Marine";"Barracks";111;1
"Unit";"SCV";"Command Center";112;1
"Unit";"Medivac";"Starport";111;2
"Unit";"SCV";"Command Center";115;1
"Unit";"Marine";"Barracks";114;1
"Unit";"Marine";"Barracks";114;1
"Unit";"Marine";"Barracks";114;1
"Unit";"Marine";"Barracks";114;1
"Unit";"SCV";"Command Center";116;1
"Unit";"SCV";"Command Center";119;1
"Building";"Armory";NA;109;0
"Building";"SupplyDepot";NA;117;0
"Building";"SupplyDepot";NA;117;0
"Building";"SupplyDepot";NA;119;0
"Unit";"Marine";"Barracks";125;1
"Unit";"Marine";"Barracks";125;1
"Unit";"Marine";"Barracks";125;1
"Unit";"Marine";"Barracks";125;1
"Unit";"Marine";"Barracks";125;1
"Building";"FactoryTechLab";NA;125;0
"Building";"SupplyDepot";NA;125;0
"Building";"SupplyDepot";NA;125;0
"Unit";"Marine";"Barracks";126;1
"Unit";"Marine";"Barracks";126;1
"Unit";"SCV";"Command Center";126;1
"Unit";"Marine";"Barracks";126;1
"Unit";"Marine";"Barracks";126;1
"Building";"SupplyDepot";NA;126;0
"Building";"SupplyDepot";NA;127;0
"Unit";"Medivac";"Starport";131;2
"Unit";"Medivac";"Starport";131;2
"Building";"MissileTurret";NA;136;0
"Unit";"SCV";"Command Center";136;1
"Building";"MissileTurret";NA;136;0
"Building";"Refinery";NA;136;0
"Building";"Refinery";NA;136;0
"Upgrade";"TerranInfantryArmorsLevel1";"EngineeringBay";117;0
"Unit";"Marine";"Barracks";141;1
"Unit";"Marine";"Barracks";141;1
"Unit";"Marine";"Barracks";141;1
"Unit";"Marine";"Barracks";141;1
"Unit";"Marine";"Barracks";141;1
"Unit";"SCV";"Command Center";141;1
"Unit";"SCV";"Command Center";141;1
"Unit";"Marine";"Barracks";141;1
"Unit";"Marine";"Barracks";141;1
"Unit";"Marine";"Barracks";141;1
"Unit";"Marine";"Barracks";141;1
"Unit";"Medivac";"Starport";141;2
"Unit";"Medivac";"Starport";141;2
"Unit";"Marine";"Barracks";141;1
"Unit";"SCV";"Command Center";150;1
"Unit";"Marine";"Barracks";151;1
"Unit";"Marine";"Barracks";151;1
"Building";"SupplyDepot";NA;150;0
"Building";"SupplyDepot";NA;150;0
"Unit";"Marine";"Barracks";152;1
"Unit";"Marine";"Barracks";152;1
"Unit";"Marine";"Barracks";158;1
"Unit";"Marine";"Barracks";158;1
"Unit";"Marine";"Barracks";158;1
"Building";"MissileTurret";NA;158;0
"Unit";"Marauder";"Barracks";158;2
"Building";"SensorTower";NA;161;0
"Unit";"Marine";"Barracks";162;1
"Unit";"Marine";"Barracks";162;1
"Unit";"Marine";"Barracks";162;1
"Unit";"Marine";"Barracks";162;1
"Unit";"Marine";"Barracks";162;1
"Unit";"Marine";"Barracks";162;1
"Upgrade";"TerranVehicleWeaponsLevel1";"Armory";141;0
"Unit";"Marine";"Barracks";167;1
"Unit";"Marine";"Barracks";167;1
"Unit";"Marine";"Barracks";167;1
"Building";"MissileTurret";NA;169;0
"Building";"MissileTurret";NA;172;0
"Unit";"Marine";"Barracks";172;1
"Unit";"Marine";"Barracks";172;1
"Building";"MissileTurret";NA;173;0
"Building";"MissileTurret";NA;173;0
"Building";"MissileTurret";NA;173;0
"Unit";"Medivac";"Starport";169;2
"Building";"MissileTurret";NA;173;0
"Unit";"Marine";"Barracks";173;1
"Unit";"Marine";"Barracks";173;1
"Unit";"Marine";"Barracks";173;1
"Unit";"Marine";"Barracks";176;1
"Unit";"Marine";"Barracks";176;1
"Building";"CommandCenter";NA;157;0
"Upgrade";"TerranInfantryWeaponsLevel2";"EngineeringBay";141;0
"Unit";"Medivac";"Starport";176;2
"Unit";"Marine";"Barracks";183;1
"Unit";"Marine";"Barracks";183;1
"Unit";"Marine";"Barracks";183;1
"Unit";"Marine";"Barracks";185;1
"Unit";"Marine";"Barracks";185;1
"Unit";"Marine";"Barracks";185;1
"Unit";"Marine";"Barracks";185;1
"Unit";"Marine";"Barracks";185;1
"Unit";"Marine";"Barracks";185;1
"Unit";"Marine";"Barracks";187;1
"Unit";"Marine";"Barracks";188;1
"Unit";"Marine";"Barracks";189;1
"Unit";"Marine";"Barracks";190;1
"Unit";"Marine";"Barracks";191;1
"Unit";"Marine";"Barracks";192;1
"Unit";"Medivac";"Starport";185;2
"Unit";"Medivac";"Starport";185;2
"Upgrade";"TerranInfantryArmorsLevel2";"EngineeringBay";162;0
"Unit";"Marine";"Barracks";193;1
"Unit";"Marine";"Barracks";194;1
"Unit";"Marine";"Barracks";195;1
"Unit";"Marine";"Barracks";196;1
"Unit";"Marine";"Barracks";197;1
"Unit";"Marine";"Barracks";198;1
"Unit";"Marine";"Barracks";199;1
"Unit";"Marine";"Barracks";209;1
"Unit";"Marine";"Barracks";209;1
"Unit";"Marine";"Barracks";209;1
"Unit";"SCV";"Command Center";214;1
"Unit";"SCV";"Command Center";214;1
"Unit";"SCV";"Command Center";218;1
"Unit";"Marine";"Barracks";218;1
"Unit";"Marine";"Barracks";218;1
