"Type";"UnitName";"OnBuilding";"TotalSupply";"Supply"
"Unit";"SCV";"Command Center";12;1
"Unit";"SCV";"Command Center";12;1
"Unit";"SCV";"Command Center";13;1
"Building";"SupplyDepot";NA;13;0
"Building";"Refinery";NA;14;0
"Unit";"SCV";"Command Center";15;1
"Unit";"SCV";"Command Center";15;1
"Unit";"SCV";"Command Center";16;1
"Unit";"SCV";"Command Center";17;1
"Building";"Barracks";NA;15;0
"Unit";"Marine";"Barracks";19;1
"Building";"SupplyDepot";NA;19;0
"Unit";"SCV";"Command Center";20;1
"Building";"Factory";NA;19;0
"Unit";"SCV";"Command Center";21;1
"Building";"BarracksReactor";NA;20;0
"Unit";"SCV";"Command Center";22;1
"Unit";"SCV";"Command Center";23;1
"Building";"BarracksTechLab";NA;22;0
"Unit";"Hellion";"Factory";22;2
"Unit";"Hellion";"Factory";22;2
"Unit";"SCV";"Command Center";23;1
"Unit";"SCV";"Command Center";29;1
"Building";"Refinery";NA;24;0
"Building";"CommandCenter";NA;20;0
"Unit";"Marine";"Barracks";29;1
"Building";"Barracks";NA;23;0
"Unit";"SCV";"Command Center";30;1
"Building";"Barracks";NA;23;0
"Unit";"SCV";"Command Center";31;1
"Building";"EngineeringBay";NA;30;0
"Building";"FactoryReactor";NA;30;0
"Unit";"Marine";"Barracks";32;1
"Unit";"SCV";"Command Center";33;1
"Building";"MissileTurret";NA;33;0
"Unit";"SCV";"Command Center";34;1
"Unit";"SCV";"Command Center";34;1
"Unit";"Marine";"Barracks";34;1
"Unit";"Marine";"Barracks";34;1
"Unit";"SCV";"Command Center";35;1
"Unit";"Marine";"Barracks";35;1
"Unit";"Marine";"Barracks";35;1
"Unit";"Marine";"Barracks";35;1
"Building";"Starport";NA;33;0
"Unit";"SCV";"Command Center";39;1
"Unit";"SCV";"Command Center";43;1
"Unit";"Marine";"Barracks";39;1
"Unit";"Marine";"Barracks";39;1
"Building";"FactoryReactor";NA;35;0
"Unit";"Marine";"Barracks";40;1
"Unit";"Marine";"Barracks";43;1
"Unit";"Marine";"Barracks";43;1
"Upgrade";"Stimpack";"TechLab";32;0
"Building";"SupplyDepot";NA;47;0
"Building";"SupplyDepot";NA;48;0
"Unit";"SCV";"Command Center";50;1
"Unit";"SCV";"Command Center";50;1
"Building";"Refinery";NA;50;0
"Unit";"Marine";"Barracks";50;1
"Unit";"Marine";"Barracks";50;1
"Unit";"Marine";"Barracks";50;1
"Unit";"Marine";"Barracks";50;1
"Unit";"Marine";"Barracks";50;1
"Unit";"SCV";"Command Center";52;1
"Unit";"Medivac";"Starport";50;2
"Unit";"SCV";"Command Center";56;1
"Building";"SupplyDepot";NA;52;0
"Unit";"Marine";"Barracks";52;1
"Building";"SupplyDepot";NA;52;0
"Unit";"Medivac";"Starport";50;2
"Unit";"Marine";"Barracks";56;1
"Unit";"SCV";"Command Center";58;1
"Building";"FactoryReactor";NA;50;0
"Unit";"Marine";"Barracks";56;1
"Upgrade";"TerranInfantryWeaponsLevel1";"EngineeringBay";39;0
"Unit";"Marine";"Barracks";61;1
"Unit";"Marine";"Barracks";61;1
"Building";"SupplyDepot";NA;62;0
"Building";"SupplyDepot";NA;65;0
"Unit";"SCV";"Command Center";69;1
"Unit";"SCV";"Command Center";69;1
"Unit";"Marine";"Barracks";69;1
"Unit";"Marine";"Barracks";69;1
"Building";"FactoryTechLab";NA;69;0
"Unit";"Marine";"Barracks";69;1
"Unit";"Marine";"Barracks";69;1
"Unit";"Marine";"Barracks";69;1
"Unit";"Marine";"Barracks";73;1
"Unit";"Marine";"Barracks";73;1
"Building";"SupplyDepot";NA;71;0
"Unit";"SCV";"Command Center";76;1
"Unit";"SCV";"Command Center";76;1
"Unit";"Marine";"Barracks";76;1
"Unit";"Marine";"Barracks";76;1
"Unit";"Medivac";"Starport";73;2
"Unit";"Marine";"Barracks";78;1
"Unit";"Marine";"Barracks";78;1
"Unit";"SCV";"Command Center";78;1
"Unit";"Marine";"Barracks";78;1
"Building";"SupplyDepot";NA;78;0
"Unit";"Marine";"Barracks";84;1
"Unit";"Marine";"Barracks";84;1
"Building";"CommandCenter";NA;69;0
"Unit";"SCV";"Command Center";88;1
"Unit";"Marine";"Barracks";88;1
"Unit";"Marine";"Barracks";88;1
"Unit";"Marine";"Barracks";88;1
"Building";"SupplyDepot";NA;88;0
"Building";"Refinery";NA;88;0
"Unit";"SCV";"Command Center";90;1
"Unit";"Marine";"Barracks";94;1
"Unit";"Marine";"Barracks";94;1
"Unit";"Marine";"Barracks";94;1
"Unit";"Marine";"Barracks";94;1
"Unit";"Marine";"Barracks";94;1
"Unit";"SCV";"Command Center";95;1
"Upgrade";"TerranInfantryArmorsLevel1";"EngineeringBay";76;0
"Building";"Barracks";NA;88;0
"Building";"SupplyDepot";NA;95;0
"Unit";"Marine";"Barracks";95;1
"Unit";"Marine";"Barracks";96;1
"Unit";"Marine";"Barracks";97;1
"Unit";"Marine";"Barracks";101;1
"Unit";"Marine";"Barracks";101;1
"Building";"Factory";NA;95;0
"Unit";"Marine";"Barracks";104;1
"Unit";"SCV";"Command Center";104;1
"Unit";"Marine";"Barracks";104;1
"Unit";"SCV";"Command Center";104;1
"Unit";"Marine";"Barracks";104;1
"Unit";"SCV";"Command Center";106;1
"Unit";"SCV";"Command Center";107;1
"Unit";"SCV";"Command Center";109;1
"Building";"EngineeringBay";NA;104;0
"Building";"FactoryTechLab";NA;106;0
"Unit";"Marine";"Barracks";106;1
"Building";"SupplyDepot";NA;106;0
"Building";"SupplyDepot";NA;106;0
"Unit";"Marine";"Barracks";111;1
"Unit";"Marine";"Barracks";111;1
"Unit";"Marine";"Barracks";111;1
"Unit";"SCV";"Command Center";112;1
"Unit";"Marine";"Barracks";111;1
"Building";"Armory";NA;104;0
"Unit";"Marine";"Barracks";115;1
"Unit";"Marine";"Barracks";115;1
"Unit";"Marine";"Barracks";115;1
"Building";"SupplyDepot";NA;120;0
"Building";"SupplyDepot";NA;120;0
"Unit";"Marine";"Barracks";120;1
"Unit";"Marine";"Barracks";120;1
"Unit";"Marine";"Barracks";120;1
"Building";"SupplyDepot";NA;123;0
"Unit";"SCV";"Command Center";126;1
"Unit";"Marine";"Barracks";126;1
"Unit";"Marine";"Barracks";126;1
"Unit";"Marine";"Barracks";126;1
"Unit";"Marine";"Barracks";126;1
"Unit";"Marine";"Barracks";126;1
"Unit";"SCV";"Command Center";126;1
"Unit";"Medivac";"Starport";126;2
"Unit";"Marine";"Barracks";133;1
"Unit";"Marine";"Barracks";133;1
"Unit";"Marine";"Barracks";133;1
"Unit";"Marine";"Barracks";133;1
"Unit";"Marine";"Barracks";133;1
"Unit";"Marine";"Barracks";133;1
"Unit";"Marine";"Barracks";133;1
"Unit";"Marine";"Barracks";135;1
"Unit";"Marine";"Barracks";136;1
"Unit";"Marine";"Barracks";137;1
"Unit";"Marine";"Barracks";138;1
"Unit";"SCV";"Command Center";142;1
"Unit";"SCV";"Command Center";142;1
"Unit";"SCV";"Command Center";142;1
"Unit";"Medivac";"Starport";137;2
"Building";"Refinery";NA;142;0
"Building";"Refinery";NA;142;0
"Unit";"Medivac";"Starport";140;2
"Unit";"Marine";"Barracks";142;1
"Unit";"Marine";"Barracks";146;1
"Unit";"Marine";"Barracks";146;1
"Unit";"SCV";"Command Center";154;1
"Unit";"SCV";"Command Center";154;1
"Unit";"Marine";"Barracks";153;1
"Unit";"Marine";"Barracks";153;1
"Unit";"Marine";"Barracks";153;1
"Unit";"Medivac";"Starport";149;2
"Building";"MissileTurret";NA;156;0
"Building";"MissileTurret";NA;158;0
"Upgrade";"TerranInfantryWeaponsLevel2";"EngineeringBay";126;0
"Building";"MissileTurret";NA;161;0
"Building";"MissileTurret";NA;161;0
"Building";"MissileTurret";NA;161;0
"Unit";"Marine";"Barracks";161;1
"Unit";"Marine";"Barracks";161;1
"Unit";"Marine";"Barracks";161;1
"Unit";"Marine";"Barracks";161;1
"Unit";"Marine";"Barracks";161;1
"Unit";"Marine";"Barracks";161;1
"Unit";"Marine";"Barracks";163;1
"Upgrade";"TerranInfantryArmorsLevel2";"EngineeringBay";137;0
"Unit";"Marine";"Barracks";170;1
"Unit";"Marine";"Barracks";170;1
"Unit";"Marine";"Barracks";170;1
"Unit";"Marine";"Barracks";170;1
"Unit";"Marine";"Barracks";170;1
"Unit";"Marine";"Barracks";170;1
"Upgrade";"TerranVehicleWeaponsLevel1";"Armory";156;0
"Building";"SupplyDepot";NA;170;0
"Building";"SupplyDepot";NA;175;0
"Building";"SupplyDepot";NA;176;0
"Building";"SupplyDepot";NA;176;0
"Building";"SupplyDepot";NA;176;0
"Building";"CommandCenter";NA;169;0
"Building";"Barracks";NA;176;0
"Building";"Barracks";NA;176;0
"Building";"Barracks";NA;176;0
"Building";"Starport";NA;176;0
"Building";"FusionCore";NA;176;0
"Unit";"Marine";"Barracks";176;1
"Unit";"Marine";"Barracks";176;1
"Unit";"Marine";"Barracks";176;1
"Unit";"Marine";"Barracks";176;1
"Unit";"Marine";"Barracks";176;1
"Unit";"Marine";"Barracks";176;1
"Unit";"Marine";"Barracks";176;1
"Unit";"Marine";"Barracks";176;1
"Unit";"Marine";"Barracks";177;1
"Unit";"Marine";"Barracks";178;1
"Building";"BarracksTechLab";NA;179;0
"Unit";"Marine";"Barracks";179;1
"Unit";"Marine";"Barracks";180;1
"Unit";"Marine";"Barracks";181;1
"Unit";"Marine";"Barracks";182;1
"Building";"BarracksTechLab";NA;183;0
"Upgrade";"TerranInfantryWeaponsLevel3";"EngineeringBay";176;0
"Unit";"SCV";"Command Center";190;1
"Unit";"Marine";"Barracks";183;1
"Unit";"Marine";"Barracks";184;1
"Unit";"Marine";"Barracks";185;1
"Unit";"Marine";"Barracks";186;1
"Unit";"Marine";"Barracks";187;1
"Building";"BarracksReactor";NA;181;0
"Unit";"Marine";"Barracks";188;1
"Unit";"Marine";"Barracks";189;1
"Unit";"Marine";"Barracks";190;1
"Building";"StarportTechLab";NA;190;0
"Building";"Refinery";NA;190;0
"Building";"SensorTower";NA;190;0
"Building";"SensorTower";NA;190;0
"Building";"Refinery";NA;190;0
"Building";"Factory";NA;183;0
"Unit";"Marine";"Barracks";190;1
"Unit";"Marine";"Barracks";191;1
"Unit";"Marine";"Barracks";192;1
"Unit";"Marine";"Barracks";193;1
"Unit";"Marine";"Barracks";198;1
"Unit";"Marine";"Barracks";198;1
"Unit";"Marine";"Barracks";198;1
"Unit";"Liberator";"Starport";185;3
"Unit";"Liberator";"Starport";186;3
"Upgrade";"TerranInfantryArmorsLevel3";"EngineeringBay";176;0
"Building";"FactoryTechLab";NA;212;0
"Unit";"Liberator";"Starport";212;3
"Unit";"Liberator";"Starport";212;3
"Unit";"Marine";"Barracks";212;1
"Unit";"Liberator";"Starport";212;3
"Unit";"Marine";"Barracks";212;1
"Unit";"Marine";"Barracks";212;1
"Unit";"Marine";"Barracks";212;1
"Unit";"Marine";"Barracks";212;1
"Unit";"Marine";"Barracks";212;1
"Unit";"Marine";"Barracks";212;1
"Unit";"Marine";"Barracks";212;1
"Unit";"Marine";"Barracks";212;1
"Unit";"Marine";"Barracks";230;1
"Unit";"Liberator";"Starport";230;3
"Unit";"Liberator";"Starport";230;3
"Unit";"Liberator";"Starport";230;3
"Unit";"Marine";"Barracks";231;1
"Unit";"Marine";"Barracks";231;1
"Unit";"Marine";"Barracks";231;1
"Unit";"Marine";"Barracks";231;1
"Unit";"Marine";"Barracks";231;1
"Unit";"Marauder";"Barracks";231;2
"Unit";"Marauder";"Barracks";231;2
"Unit";"Marine";"Barracks";231;1
"Unit";"Marine";"Barracks";231;1
"Unit";"Marine";"Barracks";231;1
"Upgrade";"TerranVehicleWeaponsLevel2";"Armory";212;0
"Unit";"Marine";"Barracks";249;1
"Unit";"Marine";"Barracks";249;1
"Unit";"Marine";"Barracks";249;1
"Building";"FactoryTechLab";NA;255;0
"Unit";"Marine";"Barracks";255;1
"Unit";"Marine";"Barracks";255;1
"Unit";"Marine";"Barracks";255;1
"Unit";"Marine";"Barracks";255;1
"Unit";"Marauder";"Barracks";255;2
"Unit";"Marauder";"Barracks";255;2
"Unit";"Marauder";"Barracks";255;2
