"Type";"UnitName";"OnBuilding";"TotalSupply";"Supply"
"Unit";"SCV";"Command Center";12;1
"Unit";"SCV";"Command Center";12;1
"Unit";"SCV";"Command Center";13;1
"Building";"SupplyDepot";NA;13;0
"Unit";"SCV";"Command Center";15;1
"Unit";"SCV";"Command Center";15;1
"Building";"Refinery";NA;15;0
"Unit";"SCV";"Command Center";16;1
"Unit";"SCV";"Command Center";17;1
"Building";"Barracks";NA;15;0
"Unit";"Reaper";"Barracks";19;1
"Unit";"SCV";"Command Center";19;1
"Unit";"SCV";"Command Center";21;1
"Unit";"SCV";"Command Center";21;1
"Building";"SupplyDepot";NA;21;0
"Building";"Barracks";NA;19;0
"Building";"BarracksReactor";NA;21;0
"Unit";"SCV";"Command Center";23;1
"Building";"CommandCenter";NA;19;0
"Building";"BarracksTechLab";NA;23;0
"Unit";"SCV";"Command Center";23;1
"Unit";"Marine";"Barracks";24;1
"Unit";"Marine";"Barracks";24;1
"Building";"Barracks";NA;22;0
"Unit";"Marine";"Barracks";25;1
"Unit";"SCV";"Command Center";25;1
"Unit";"Marine";"Barracks";27;1
"Unit";"Marine";"Barracks";27;1
"Unit";"SCV";"Command Center";28;1
"Building";"EngineeringBay";NA;25;0
"Unit";"SCV";"Command Center";29;1
"Unit";"Marine";"Barracks";27;1
"Building";"Bunker";NA;25;0
"Unit";"Marine";"Barracks";29;1
"Unit";"Marine";"Barracks";34;1
"Unit";"Marine";"Barracks";34;1
"Unit";"Marine";"Barracks";34;1
"Unit";"SCV";"Command Center";35;1
"Unit";"SCV";"Command Center";35;1
"Building";"Refinery";NA;34;0
"Unit";"Marine";"Barracks";35;1
"Building";"MissileTurret";NA;37;0
"Unit";"SCV";"Command Center";41;1
"Building";"MissileTurret";NA;38;0
"Unit";"Marine";"Barracks";38;1
"Unit";"Marine";"Barracks";41;1
"Unit";"Marine";"Barracks";41;1
"Unit";"SCV";"Command Center";41;1
"Unit";"SCV";"Command Center";43;1
"Building";"Factory";NA;35;0
"Unit";"Marine";"Barracks";42;1
"Unit";"Marine";"Barracks";42;1
"Building";"SupplyDepot";NA;42;0
"Unit";"SCV";"Command Center";47;1
"Unit";"Marine";"Barracks";45;1
"Unit";"SCV";"Command Center";47;1
"Unit";"Marine";"Barracks";49;1
"Building";"BarracksTechLab";NA;49;0
"Unit";"Marine";"Barracks";49;1
"Unit";"SCV";"Command Center";52;1
"Unit";"SCV";"Command Center";52;1
"Unit";"Marine";"Barracks";52;1
"Building";"Refinery";NA;52;0
"Upgrade";"Stimpack";"TechLab";34;0
"Building";"SupplyDepot";NA;52;0
"Building";"Starport";NA;47;0
"Building";"FactoryReactor";NA;48;0
"Unit";"Marine";"Barracks";53;1
"Unit";"Marine";"Barracks";53;1
"Unit";"Marine";"Barracks";55;1
"Unit";"SCV";"Command Center";57;1
"Unit";"SCV";"Command Center";57;1
"Unit";"Marine";"Barracks";57;1
"Upgrade";"TerranInfantryWeaponsLevel1";"EngineeringBay";41;0
"Building";"SupplyDepot";NA;57;0
"Unit";"SCV";"Command Center";60;1
"Unit";"Marine";"Barracks";59;1
"Unit";"Marine";"Barracks";59;1
"Unit";"SCV";"Command Center";63;1
"Unit";"Marine";"Barracks";63;1
"Building";"SupplyDepot";NA;62;0
"Unit";"Marine";"Barracks";63;1
"Unit";"SCV";"Command Center";66;1
"Unit";"Medivac";"Starport";61;2
"Unit";"Marine";"Barracks";66;1
"Unit";"Marine";"Barracks";66;1
"Unit";"Medivac";"Starport";62;2
"Unit";"SCV";"Command Center";70;1
"Unit";"SCV";"Command Center";70;1
"Unit";"Marine";"Barracks";70;1
"Unit";"Marine";"Barracks";70;1
"Building";"FactoryReactor";NA;66;0
"Unit";"SCV";"Command Center";80;1
"Unit";"SCV";"Command Center";80;1
"Unit";"Marine";"Barracks";78;1
"Unit";"Marine";"Barracks";78;1
"Building";"Refinery";NA;80;0
"Unit";"Marine";"Barracks";82;1
"Unit";"Marine";"Barracks";82;1
"Building";"Barracks";NA;76;0
"Unit";"SCV";"Command Center";84;1
"Building";"Barracks";NA;76;0
"Unit";"Medivac";"Starport";80;2
"Unit";"SCV";"Command Center";84;1
"Unit";"Marine";"Barracks";84;1
"Unit";"Marine";"Barracks";84;1
"Building";"SupplyDepot";NA;84;0
"Unit";"Medivac";"Starport";82;2
"Building";"BarracksTechLab";NA;87;0
"Unit";"SCV";"Command Center";92;1
"Unit";"SCV";"Command Center";92;1
"Unit";"Marine";"Barracks";92;1
"Unit";"Marauder";"Barracks";92;2
"Building";"SupplyDepot";NA;92;0
"Building";"SupplyDepot";NA;92;0
"Building";"BarracksReactor";NA;87;0
"Unit";"Marine";"Barracks";96;1
"Unit";"Marauder";"Barracks";96;2
"Unit";"Marine";"Barracks";99;1
"Unit";"Marine";"Barracks";99;1
"Unit";"SCV";"Command Center";99;1
"Unit";"Marauder";"Barracks";99;2
"Unit";"Marine";"Barracks";99;1
"Unit";"Marine";"Barracks";100;1
"Unit";"Marine";"Barracks";100;1
"Unit";"Medivac";"Starport";99;2
"Building";"SupplyDepot";NA;100;0
"Unit";"Marauder";"Barracks";100;2
"Unit";"SCV";"Command Center";112;1
"Unit";"Marine";"Barracks";109;1
"Unit";"Marine";"Barracks";109;1
"Unit";"Marine";"Barracks";112;1
"Unit";"Marine";"Barracks";112;1
"Upgrade";"TerranInfantryArmorsLevel1";"EngineeringBay";86;0
"Unit";"Marine";"Barracks";112;1
"Unit";"SCV";"Command Center";114;1
"Unit";"Marauder";"Barracks";112;2
"Unit";"Marine";"Barracks";114;1
"Unit";"Marine";"Barracks";119;1
"Unit";"Marine";"Barracks";120;1
"Unit";"Marine";"Barracks";123;1
"Unit";"Marine";"Barracks";123;1
"Unit";"Medivac";"Starport";114;2
"Unit";"Medivac";"Starport";115;2
"Unit";"Marauder";"Barracks";123;2
"Unit";"Marauder";"Barracks";123;2
"Unit";"Marauder";"Barracks";123;2
"Unit";"Marine";"Barracks";124;1
"Unit";"Marine";"Barracks";125;1
