"type";"unit_name";"on_building";"total_supply";"supply"
"Building";"Refinery";NA;15;0
"Building";"Barracks";NA;15;0
"Unit";"Reaper";"Barracks";19;1
"Unit";"Marine";"Barracks";19;1
"Building";"Refinery";NA;23;0
"Building";"Factory";NA;20;0
"Building";"CommandCenter";NA;19;0
"Building";"BarracksReactor";NA;23;0
"Unit";"Marine";"Barracks";26;1
"Unit";"Marine";"Barracks";26;1
"Building";"Starport";NA;26;0
"Unit";"Marine";"Barracks";30;1
"Unit";"Marine";"Barracks";30;1
"Unit";"Cyclone";"Factory";30;3
"Unit";"Marine";"Barracks";36;1
"Unit";"Marine";"Barracks";36;1
"Building";"EngineeringBay";NA;34;0
"Unit";"Medivac";"Starport";34;2
"Building";"Bunker";NA;39;0
"Building";"FactoryTechLab";NA;43;0
"Unit";"Marine";"Barracks";43;1
"Unit";"Marine";"Barracks";43;1
"Building";"MissileTurret";NA;47;0
"Building";"Barracks";NA;43;0
"Building";"FactoryTechLab";NA;50;0
"Building";"Barracks";NA;43;0
"Unit";"Liberator";"Starport";45;3
"Unit";"Marine";"Barracks";50;1
"Unit";"Marine";"Barracks";53;1
"Building";"FactoryTechLab";NA;54;0
"Building";"Refinery";NA;54;0
"Unit";"Marine";"Barracks";55;1
"Unit";"Marine";"Barracks";57;1
"Building";"Refinery";NA;56;0
"Building";"StarportReactor";NA;53;0
"Unit";"Marauder";"Barracks";59;2
"Unit";"Marine";"Barracks";63;1
"Unit";"Marine";"Barracks";63;1
"Unit";"Marauder";"Barracks";63;2
"Unit";"Marauder";"Barracks";65;2
"Upgrade";"TerranInfantryWeaponsLevel1";"EngineeringBay";50;0
"Unit";"Marine";"Barracks";69;1
"Unit";"Marine";"Barracks";69;1
"Unit";"Marauder";"Barracks";71;2
"Building";"CommandCenter";NA;59;0
"Unit";"Marauder";"Barracks";75;2
"Unit";"Marine";"Barracks";79;1
"Unit";"Marine";"Barracks";79;1
"Unit";"Medivac";"Starport";75;2
"Unit";"Medivac";"Starport";75;2
"Unit";"Marauder";"Barracks";83;2
"Building";"Barracks";NA;75;0
"Building";"Barracks";NA;75;0
"Unit";"Marauder";"Barracks";85;2
"Upgrade";"Stimpack";"TechLab";63;0
"Unit";"Marine";"Barracks";95;1
"Unit";"Marine";"Barracks";97;1
"Unit";"Marauder";"Barracks";97;2
"Building";"BarracksTechLab";NA;97;0
"Unit";"Marauder";"Barracks";99;2
"Building";"BarracksReactor";NA;97;0
"Unit";"Marauder";"Barracks";103;2
"Building";"MissileTurret";NA;107;0
"Unit";"Marine";"Barracks";107;1
"Unit";"Marine";"Barracks";107;1
"Building";"FactoryReactor";NA;99;0
"Building";"EngineeringBay";NA;107;0
"Unit";"Medivac";"Starport";109;2
"Unit";"Medivac";"Starport";109;2
"Unit";"Marine";"Barracks";115;1
"Unit";"Marine";"Barracks";115;1
"Unit";"Marine";"Barracks";115;1
"Unit";"Marauder";"Barracks";114;2
"Unit";"Marauder";"Barracks";114;2
"Building";"Armory";NA;107;0
"Unit";"Marine";"Barracks";115;1
"Unit";"Marauder";"Barracks";115;2
"Building";"GhostAcademy";NA;115;0
"Upgrade";"TerranInfantryArmorsLevel1";"EngineeringBay";97;0
"Unit";"Marine";"Barracks";120;1
"Unit";"Marine";"Barracks";127;1
"Unit";"Marine";"Barracks";127;1
"Unit";"Marine";"Barracks";130;1
"Unit";"Marine";"Barracks";131;1
"Unit";"Medivac";"Starport";127;2
"Unit";"Medivac";"Starport";127;2
"Unit";"Ghost";"Barracks";131;2
"Unit";"Ghost";"Barracks";132;2
"Building";"MissileTurret";NA;139;0
"Building";"MissileTurret";NA;139;0
"Unit";"Marine";"Barracks";139;1
"Unit";"Marine";"Barracks";139;1
"Unit";"Marine";"Barracks";139;1
"Unit";"Marine";"Barracks";139;1
"Building";"Refinery";NA;139;0
"Building";"Refinery";NA;139;0
"Unit";"Marauder";"Barracks";139;2
"Unit";"Marine";"Barracks";139;1
"Building";"Bunker";NA;139;0
"Building";"Bunker";NA;139;0
"Unit";"Marine";"Barracks";147;1
"Unit";"Marine";"Barracks";147;1
"Unit";"Marine";"Barracks";147;1
"Unit";"Marauder";"Barracks";147;2
"Unit";"Marauder";"Barracks";147;2
"Building";"SensorTower";NA;156;0
"Unit";"Marine";"Barracks";160;1
"Unit";"Marine";"Barracks";160;1
"Unit";"Marine";"Barracks";160;1
"Unit";"Marine";"Barracks";160;1
"Unit";"Marauder";"Barracks";160;2
"Building";"Bunker";NA;160;0
"Unit";"Ghost";"Barracks";160;2
"Unit";"Ghost";"Barracks";160;2
"Unit";"Marine";"Barracks";163;1
"Building";"Barracks";NA;150;0
"Building";"Barracks";NA;150;0
"Unit";"Medivac";"Starport";173;2
"Building";"BarracksTechLab";NA;178;0
"Unit";"Medivac";"Starport";178;2
"Unit";"Marine";"Barracks";178;1
"Unit";"Marine";"Barracks";178;1
"Unit";"Marine";"Barracks";178;1
"Unit";"Marine";"Barracks";178;1
"Unit";"Marine";"Barracks";178;1
"Unit";"Marauder";"Barracks";178;2
"Unit";"Marauder";"Barracks";178;2
"Building";"BarracksReactor";NA;178;0
"Upgrade";"TerranInfantryWeaponsLevel2";"EngineeringBay";150;0
"Building";"CommandCenter";NA;172;0
"Building";"Starport";NA;180;0
"Unit";"Marine";"Barracks";191;1
"Unit";"Marine";"Barracks";191;1
"Unit";"Marine";"Barracks";191;1
"Unit";"Marine";"Barracks";191;1
"Unit";"Marine";"Barracks";191;1
"Unit";"Marine";"Barracks";191;1
"Unit";"Marauder";"Barracks";191;2
"Unit";"Marauder";"Barracks";191;2
"Unit";"Marauder";"Barracks";191;2
"Unit";"Marauder";"Barracks";191;2
"Upgrade";"TerranInfantryArmorsLevel2";"EngineeringBay";172;0
"Unit";"Marauder";"Barracks";197;2
"Unit";"Marine";"Barracks";205;1
"Unit";"Marine";"Barracks";205;1
"Unit";"Marine";"Barracks";205;1
"Unit";"Marine";"Barracks";205;1
"Unit";"Liberator";"Starport";191;3
"Unit";"Liberator";"Starport";191;3
"Unit";"Marauder";"Barracks";205;2
"Unit";"Marauder";"Barracks";205;2
"Unit";"Ghost";"Barracks";199;2
