"type";"unit_name";"on_building";"total_supply_lag";"supply"
"Building";"Refinery";NA;15;0
"Building";"Barracks";NA;16;0
"Unit";"Reaper";"Barracks";19;1
"Building";"CommandCenter";NA;20;0
"Building";"Factory";NA;20;0
"Building";"Refinery";NA;21;0
"Building";"BarracksReactor";NA;21;0
"Building";"Starport";NA;24;0
"Unit";"Marine";"Barracks";24;1
"Unit";"Marine";"Barracks";25;1
"Unit";"Marine";"Barracks";27;1
"Unit";"Marine";"Barracks";28;1
"Unit";"Medivac";"Starport";30;2
"Unit";"Marine";"Barracks";32;1
"Unit";"Marine";"Barracks";33;1
"Building";"FactoryTechLab";NA;36;0
"Building";"EngineeringBay";NA;38;0
"Unit";"Marine";"Barracks";38;1
"Unit";"Marine";"Barracks";39;1
"Unit";"Marine";"Barracks";42;1
"Unit";"Marine";"Barracks";43;1
"Building";"MissileTurret";NA;44;0
"Unit";"Marine";"Barracks";47;1
"Unit";"Marine";"Barracks";48;1
"Unit";"Liberator";"Starport";49;3
"Unit";"Marine";"Barracks";56;1
"Unit";"Marine";"Barracks";57;1
"Building";"FactoryReactor";NA;62;0
"Building";"Barracks";NA;62;0
"Unit";"Marine";"Barracks";62;1
"Building";"Barracks";NA;63;0
"Building";"Refinery";NA;63;0
"Building";"Refinery";NA;63;0
"Building";"StarportReactor";NA;63;0
"Upgrade";"TerranInfantryWeaponsLevel1";"EngineeringBay";65;0
"Building";"Barracks";NA;67;0
"Unit";"Marine";"Barracks";67;1
"Building";"Barracks";NA;68;0
"Upgrade";"Stimpack";"TechLab";69;0
"Unit";"Medivac";"Starport";69;2
"Unit";"Medivac";"Starport";71;2
"Building";"FactoryReactor";NA;75;0
"Building";"BarracksTechLab";NA;77;0
"Unit";"Medivac";"Starport";79;2
"Unit";"Medivac";"Starport";81;2
"Unit";"Marauder";"Barracks";83;2
"Unit";"Marauder";"Barracks";85;2
"Unit";"Marine";"Barracks";87;1
"Unit";"Marine";"Barracks";88;1
"Building";"BarracksTechLab";NA;89;0
"Building";"CommandCenter";NA;93;0
"Unit";"Marine";"Barracks";93;1
"Unit";"Marine";"Barracks";94;1
"Unit";"Marine";"Barracks";95;1
"Unit";"Marine";"Barracks";96;1
"Unit";"Marauder";"Barracks";97;2
"Unit";"Marauder";"Barracks";99;2
"Unit";"Marauder";"Barracks";101;2
"Unit";"Marine";"Barracks";103;1
"Unit";"Marine";"Barracks";104;1
"Unit";"Marine";"Barracks";105;1
"Unit";"Marine";"Barracks";106;1
"Building";"GhostAcademy";NA;107;0
"Unit";"Marine";"Barracks";107;1
"Unit";"Marauder";"Barracks";108;2
"Unit";"Marauder";"Barracks";110;2
"Unit";"Marauder";"Barracks";112;2
"Unit";"Marine";"Barracks";116;1
"Unit";"Marine";"Barracks";117;1
"Unit";"Marine";"Barracks";118;1
"Unit";"Marine";"Barracks";119;1
"Unit";"Ghost";"Barracks";122;2
"Unit";"Ghost";"Barracks";124;2
"Unit";"Ghost";"Barracks";126;2
"Unit";"Marine";"Barracks";128;1
"Unit";"Marine";"Barracks";129;1
"Unit";"Marine";"Barracks";130;1
"Building";"Armory";NA;131;0
"Building";"EngineeringBay";NA;131;0
"Unit";"Marine";"Barracks";133;1
"Unit";"Marine";"Barracks";134;1
"Unit";"Marine";"Barracks";135;1
"Unit";"Marine";"Barracks";136;1
"Building";"MissileTurret";NA;137;0
"Unit";"Marauder";"Barracks";137;2
"Unit";"Marine";"Barracks";139;1
"Unit";"Marine";"Barracks";140;1
"Building";"MissileTurret";NA;143;0
"Unit";"Marauder";"Barracks";143;2
"Unit";"Marauder";"Barracks";145;2
"Unit";"Marauder";"Barracks";147;2
"Building";"Barracks";NA;149;0
"Building";"Barracks";NA;149;0
"Building";"Barracks";NA;149;0
"Unit";"Marine";"Barracks";149;1
"Unit";"Marine";"Barracks";150;1
"Unit";"Marine";"Barracks";151;1
"Unit";"Marine";"Barracks";152;1
"Unit";"Medivac";"Starport";153;2
"Unit";"Medivac";"Starport";155;2
"Building";"SensorTower";NA;157;0
"Unit";"Marauder";"Barracks";157;2
"Unit";"Marauder";"Barracks";159;2
"Unit";"Marauder";"Barracks";161;2
"Upgrade";"TerranInfantryWeaponsLevel2";"EngineeringBay";163;0
"Unit";"Marauder";"Barracks";163;2
"Unit";"Marine";"Barracks";165;1
"Unit";"Marine";"Barracks";166;1
"Unit";"Marine";"Barracks";167;1
"Unit";"Marine";"Barracks";168;1
"Unit";"Marauder";"Barracks";169;2
"Unit";"Ghost";"Barracks";171;2
"Upgrade";"TerranShipWeaponsLevel1";"Armory";173;0
"Building";"Refinery";NA;173;0
"Building";"Refinery";NA;173;0
"Building";"BarracksTechLab";NA;173;0
"Building";"BarracksTechLab";NA;173;0
"Building";"BarracksReactor";NA;173;0
"Unit";"Ghost";"Barracks";173;2
"Building";"CommandCenter";NA;175;0
"Unit";"Ghost";"Barracks";175;2
"Unit";"Marine";"Barracks";177;1
"Unit";"Marine";"Barracks";178;1
"Unit";"Marine";"Barracks";179;1
"Unit";"Marine";"Barracks";180;1
"Unit";"Marauder";"Barracks";181;2
"Unit";"Marauder";"Barracks";183;2
"Unit";"Marauder";"Barracks";185;2
"Unit";"Marine";"Barracks";187;1
"Unit";"Marine";"Barracks";188;1
"Unit";"Marine";"Barracks";189;1
"Unit";"Marauder";"Barracks";190;2
"Unit";"Marauder";"Barracks";192;2
"Unit";"Marine";"Barracks";194;1
"Unit";"Marine";"Barracks";195;1
"Unit";"Marauder";"Barracks";196;2
"Building";"Starport";NA;198;0
"Building";"FusionCore";NA;198;0
"Unit";"Marauder";"Barracks";198;2
"Unit";"Marauder";"Barracks";200;2
"Unit";"Marauder";"Barracks";202;2
"Unit";"Marauder";"Barracks";204;2
"Unit";"Marine";"Barracks";206;1
"Unit";"Marine";"Barracks";207;1
"Unit";"Marine";"Barracks";208;1
"Unit";"Marine";"Barracks";209;1
"Unit";"Liberator";"Starport";210;3
"Building";"StarportTechLab";NA;213;0
"Unit";"Marauder";"Barracks";213;2
"Unit";"Marauder";"Barracks";215;2
"Unit";"Marauder";"Barracks";217;2
"Unit";"Marine";"Barracks";219;1
"Unit";"Marine";"Barracks";220;1
"Unit";"Marine";"Barracks";221;1
"Unit";"Marine";"Barracks";222;1
"Unit";"Marauder";"Barracks";223;2
"Unit";"Marauder";"Barracks";225;2
"Unit";"Marine";"Barracks";227;1
"Unit";"Marine";"Barracks";228;1
"Upgrade";"TerranInfantryWeaponsLevel3";"EngineeringBay";229;0
"Unit";"Marine";"Barracks";229;1
"Unit";"Marine";"Barracks";230;1
"Unit";"Marine";"Barracks";231;1
"Unit";"Marine";"Barracks";232;1
"Unit";"Marauder";"Barracks";233;2
"Unit";"Marauder";"Barracks";235;2
"Unit";"Marauder";"Barracks";237;2
"Unit";"Marauder";"Barracks";239;2
"Unit";"Marauder";"Barracks";241;2
"Unit";"Marine";"Barracks";243;1
"Unit";"Marine";"Barracks";244;1
"Unit";"Liberator";"Starport";245;3
"Unit";"Liberator";"Starport";248;3
"Unit";"Marauder";"Barracks";251;2
"Unit";"Liberator";"Starport";253;3
"Unit";"Marauder";"Barracks";256;2
"Unit";"Marauder";"Barracks";258;2
"Unit";"Marauder";"Barracks";260;2
"Unit";"Marine";"Barracks";262;1
"Unit";"Marine";"Barracks";263;1
"Unit";"Marine";"Barracks";264;1
"Unit";"Marine";"Barracks";265;1
"Unit";"Marauder";"Barracks";266;2
"Unit";"Marauder";"Barracks";268;2
"Unit";"Marine";"Barracks";270;1
"Unit";"Marine";"Barracks";271;1
"Unit";"Marine";"Barracks";272;1
"Unit";"Marine";"Barracks";273;1
"Unit";"Marine";"Barracks";274;1
"Unit";"Marine";"Barracks";275;1
"Unit";"Marauder";"Barracks";276;2
"Unit";"Marauder";"Barracks";278;2
"Unit";"Liberator";"Starport";280;3
"Unit";"Liberator";"Starport";283;3
"Unit";"Marine";"Barracks";286;1
"Unit";"Marine";"Barracks";287;1
"Unit";"Marine";"Barracks";288;1
"Unit";"Marine";"Barracks";289;1
"Unit";"Marauder";"Barracks";290;2
"Unit";"Marauder";"Barracks";292;2
"Unit";"Liberator";"Starport";294;3
"Building";"Refinery";NA;298;0
"Building";"Refinery";NA;298;0
"Unit";"Marauder";"Barracks";298;2
"Unit";"Marauder";"Barracks";300;2
"Unit";"Marine";"Barracks";302;1
"Unit";"Marine";"Barracks";303;1
"Unit";"Marauder";"Barracks";304;2
"Unit";"Marauder";"Barracks";306;2
"Unit";"Marine";"Barracks";308;1
"Unit";"Marine";"Barracks";309;1
"Unit";"Marine";"Barracks";310;1
"Unit";"Marine";"Barracks";311;1
"Unit";"Marauder";"Barracks";312;2
"Unit";"Marine";"Barracks";316;1
"Unit";"Marine";"Barracks";317;1
"Unit";"Marauder";"Barracks";318;2
"Unit";"Marauder";"Barracks";320;2
"Upgrade";"SprayTerran";NA;322;0
"Upgrade";"SprayTerran";NA;322;0
"Upgrade";"SprayTerran";NA;322;0
"Upgrade";"SprayTerran";NA;322;0
"Upgrade";"PunisherGrenades";NA;322;0
"Upgrade";"ShieldWall";NA;322;0
"Upgrade";"TerranInfantryArmorsLevel1";NA;322;0
"Upgrade";"SprayTerran";NA;322;0
"Upgrade";"TerranInfantryArmorsLevel2";NA;322;0
"Upgrade";"SprayTerran";NA;322;0
"Upgrade";"TerranInfantryArmorsLevel3";NA;322;0
"Upgrade";"LiberatorAGRangeUpgrade";NA;322;0
