"type";"unit_name";"on_building";"total_supply";"supply"
"Building";"Refinery";NA;15;0
"Building";"Barracks";NA;15;0
"Unit";"Reaper";"Barracks";19;1
"Building";"BarracksReactor";NA;20;0
"Building";"Barracks";NA;19;0
"Building";"Refinery";NA;23;0
"Unit";"Marine";"Barracks";23;1
"Building";"BarracksTechLab";NA;23;0
"Building";"CommandCenter";NA;19;0
"Building";"Factory";NA;22;0
"Unit";"Marine";"Barracks";25;1
"Unit";"Marine";"Barracks";25;1
"Unit";"Marine";"Barracks";26;1
"Unit";"Marine";"Barracks";28;1
"Unit";"Marine";"Barracks";28;1
"Unit";"Marine";"Barracks";30;1
"Unit";"Marine";"Barracks";33;1
"Unit";"Marine";"Barracks";33;1
"Building";"Starport";NA;30;0
"Unit";"Marine";"Barracks";36;1
"Building";"EngineeringBay";NA;35;0
"Building";"FactoryReactor";NA;31;0
"Unit";"Marine";"Barracks";40;1
"Unit";"Marine";"Barracks";40;1
"Building";"Bunker";NA;36;0
"Unit";"Marine";"Barracks";41;1
"Building";"MissileTurret";NA;43;0
"Unit";"Marine";"Barracks";48;1
"Unit";"Marine";"Barracks";48;1
"Building";"FactoryTechLab";NA;48;0
"Unit";"Medivac";"Starport";48;2
"Unit";"Medivac";"Starport";48;2
"Upgrade";"Stimpack";"TechLab";33;0
"Unit";"Marine";"Barracks";50;1
"Unit";"Marine";"Barracks";52;1
"Unit";"Marine";"Barracks";52;1
"Building";"Refinery";NA;52;0
"Unit";"Marine";"Barracks";59;1
"Unit";"Marine";"Barracks";59;1
"Unit";"Marine";"Barracks";62;1
"Unit";"Marine";"Barracks";64;1
"Unit";"Marine";"Barracks";64;1
"Unit";"Marine";"Barracks";68;1
"Building";"Refinery";NA;71;0
"Unit";"Marine";"Barracks";71;1
"Unit";"Marine";"Barracks";71;1
"Unit";"Marine";"Barracks";73;1
"Unit";"Medivac";"Starport";73;2
"Unit";"Medivac";"Starport";74;2
"Upgrade";"TerranInfantryWeaponsLevel1";"EngineeringBay";63;0
"Building";"CommandCenter";NA;66;0
"Unit";"Marine";"Barracks";84;1
"Building";"Barracks";NA;76;0
"Unit";"Marine";"Barracks";84;1
"Unit";"Marine";"Barracks";84;1
"Unit";"Medivac";"Starport";84;2
"Unit";"Marine";"Barracks";84;1
"Unit";"Marine";"Barracks";87;1
"Unit";"Marine";"Barracks";88;1
"Unit";"Marine";"Barracks";91;1
"Building";"BarracksReactor";NA;87;0
"Unit";"Marine";"Barracks";93;1
"Unit";"Marine";"Barracks";94;1
"Building";"Factory";NA;87;0
"Unit";"Marine";"Barracks";97;1
"Building";"Barracks";NA;89;0
"Building";"Barracks";NA;89;0
"Unit";"Marine";"Barracks";98;1
"Unit";"Marine";"Barracks";99;1
"Unit";"Marine";"Barracks";100;1
"Unit";"Marine";"Barracks";102;1
"Unit";"Marine";"Barracks";102;1
"Building";"Refinery";NA;102;0
"Building";"Refinery";NA;102;0
"Building";"SensorTower";NA;104;0
"Unit";"Marine";"Barracks";106;1
"Building";"FactoryTechLab";NA;108;0
"Unit";"Marine";"Barracks";110;1
"Unit";"Marine";"Barracks";110;1
"Unit";"Marine";"Barracks";110;1
"Building";"BarracksReactor";NA;104;0
"Building";"BarracksReactor";NA;104;0
"Unit";"Marine";"Barracks";114;1
"Unit";"Marine";"Barracks";114;1
"Unit";"Marine";"Barracks";116;1
"Unit";"Marine";"Barracks";117;1
"Unit";"Marine";"Barracks";118;1
"Upgrade";"TerranInfantryArmorsLevel1";"EngineeringBay";95;0
"Unit";"Medivac";"Starport";117;2
"Building";"EngineeringBay";NA;124;0
"Unit";"Marine";"Barracks";128;1
"Unit";"Marine";"Barracks";128;1
"Unit";"Marine";"Barracks";128;1
"Unit";"Marine";"Barracks";128;1
"Unit";"Marine";"Barracks";128;1
"Unit";"Marine";"Barracks";130;1
"Building";"Armory";NA;122;0
"Unit";"Marine";"Barracks";137;1
"Unit";"Marine";"Barracks";137;1
"Unit";"Marine";"Barracks";137;1
"Unit";"Marine";"Barracks";137;1
"Unit";"Marine";"Barracks";137;1
"Unit";"Marine";"Barracks";137;1
"Unit";"Marine";"Barracks";137;1
"Unit";"Marine";"Barracks";137;1
"Unit";"Medivac";"Starport";137;2
"Unit";"Marine";"Barracks";142;1
"Unit";"Medivac";"Starport";137;2
"Building";"MissileTurret";NA;150;0
"Unit";"Marine";"Barracks";150;1
"Unit";"Marine";"Barracks";150;1
"Unit";"Marine";"Barracks";150;1
"Unit";"Marine";"Barracks";150;1
"Unit";"Marine";"Barracks";150;1
"Unit";"Marine";"Barracks";150;1
"Unit";"Marine";"Barracks";150;1
"Unit";"Marine";"Barracks";150;1
"Unit";"Marine";"Barracks";150;1
"Unit";"Medivac";"Starport";148;2
"Building";"Factory";NA;138;0
"Unit";"Marine";"Barracks";153;1
"Unit";"Marine";"Barracks";154;1
"Unit";"Marine";"Barracks";155;1
"Unit";"Marine";"Barracks";156;1
"Unit";"Medivac";"Starport";151;2
"Unit";"Marine";"Barracks";161;1
"Unit";"Marine";"Barracks";162;1
"Unit";"Marine";"Barracks";162;1
"Unit";"Marine";"Barracks";162;1
"Unit";"Marine";"Barracks";162;1
"Building";"FactoryTechLab";NA;164;0
"Unit";"Marine";"Barracks";164;1
"Unit";"Marine";"Barracks";165;1
"Unit";"Marine";"Barracks";166;1
"Unit";"Marine";"Barracks";167;1
"Unit";"Medivac";"Starport";162;2
"Unit";"Marine";"Barracks";170;1
"Unit";"Marine";"Barracks";171;1
"Unit";"Marine";"Barracks";172;1
"Unit";"Marine";"Barracks";173;1
"Unit";"Marine";"Barracks";174;1
"Unit";"Marine";"Barracks";175;1
"Unit";"Marine";"Barracks";176;1
"Unit";"Marine";"Barracks";177;1
"Building";"SensorTower";NA;178;0
"Unit";"Marine";"Barracks";178;1
"Building";"SensorTower";NA;179;0
"Unit";"Marine";"Barracks";181;1
"Unit";"Marine";"Barracks";182;1
"Unit";"Marine";"Barracks";183;1
"Unit";"Marine";"Barracks";184;1
"Unit";"Marine";"Barracks";186;1
"Building";"CommandCenter";NA;153;0
"Unit";"Marine";"Barracks";186;1
"Unit";"Marine";"Barracks";187;1
"Unit";"Marine";"Barracks";190;1
"Unit";"Marine";"Barracks";190;1
"Unit";"Marine";"Barracks";193;1
"Unit";"Marine";"Barracks";193;1
"Unit";"Marine";"Barracks";193;1
"Unit";"Marine";"Barracks";193;1
"Upgrade";"TerranVehicleWeaponsLevel1";"Armory";161;0
"Unit";"Medivac";"Starport";194;2
"Upgrade";"TerranInfantryWeaponsLevel2";"EngineeringBay";161;0
"Upgrade";"TerranInfantryArmorsLevel2";"EngineeringBay";161;0
"Unit";"Marine";"Barracks";205;1
"Unit";"Marine";"Barracks";205;1
"Unit";"Marine";"Barracks";205;1
"Unit";"Marine";"Barracks";205;1
"Unit";"Marine";"Barracks";205;1
"Unit";"Marine";"Barracks";205;1
"Unit";"Marine";"Barracks";205;1
"Unit";"Marine";"Barracks";205;1
"Unit";"Marine";"Barracks";205;1
"Unit";"Medivac";"Starport";205;2
"Unit";"Marine";"Barracks";205;1
"Building";"SensorTower";NA;211;0
"Building";"Refinery";NA;211;0
"Building";"Refinery";NA;211;0
"Unit";"Marine";"Barracks";213;1
"Unit";"Marine";"Barracks";213;1
"Unit";"Marine";"Barracks";213;1
"Unit";"Marine";"Barracks";213;1
"Unit";"Marine";"Barracks";213;1
"Unit";"Marine";"Barracks";213;1
"Unit";"Marine";"Barracks";213;1
"Unit";"Marine";"Barracks";213;1
"Unit";"Marine";"Barracks";216;1
"Unit";"Marine";"Barracks";217;1
"Unit";"Marine";"Barracks";218;1
"Unit";"Marine";"Barracks";218;1
"Unit";"Marine";"Barracks";224;1
"Unit";"Marine";"Barracks";224;1
"Unit";"Marine";"Barracks";224;1
"Unit";"Marine";"Barracks";224;1
"Unit";"Marine";"Barracks";224;1
"Unit";"Marine";"Barracks";225;1
"Unit";"Medivac";"Starport";225;2
"Unit";"Marine";"Barracks";226;1
"Unit";"Marine";"Barracks";227;1
"Unit";"Marine";"Barracks";227;1
"Unit";"Marine";"Barracks";229;1
"Unit";"Marine";"Barracks";235;1
