"Type";"UnitName";"OnBuilding";"TotalSupply";"Supply"
"Unit";"SCV";"Command Center";12;1
"Unit";"SCV";"Command Center";12;1
"Unit";"SCV";"Command Center";13;1
"Building";"SupplyDepot";NA;13;0
"Unit";"SCV";"Command Center";15;1
"Unit";"SCV";"Command Center";16;1
"Building";"Refinery";NA;15;0
"Unit";"SCV";"Command Center";16;1
"Building";"Barracks";NA;15;0
"Unit";"SCV";"Command Center";18;1
"Unit";"Reaper";"Barracks";18;1
"Unit";"SCV";"Command Center";19;1
"Unit";"SCV";"Command Center";20;1
"Unit";"SCV";"Command Center";21;1
"Building";"SupplyDepot";NA;21;0
"Building";"BarracksReactor";NA;20;0
"Building";"Refinery";NA;22;0
"Unit";"SCV";"Command Center";23;1
"Building";"Barracks";NA;20;0
"Unit";"Marine";"Barracks";23;1
"Unit";"Marine";"Barracks";23;1
"Unit";"SCV";"Command Center";23;1
"Building";"CommandCenter";NA;19;0
"Building";"BarracksTechLab";NA;24;0
"Unit";"SCV";"Command Center";26;1
"Building";"Factory";NA;22;0
"Unit";"Marine";"Barracks";26;1
"Unit";"Marine";"Barracks";26;1
"Unit";"SCV";"Command Center";28;1
"Unit";"Marine";"Barracks";27;1
"Unit";"Marine";"Barracks";30;1
"Unit";"Marine";"Barracks";30;1
"Unit";"SCV";"Command Center";32;1
"Unit";"SCV";"Command Center";32;1
"Unit";"Marine";"Barracks";32;1
"Unit";"SCV";"Command Center";36;1
"Building";"Starport";NA;30;0
"Unit";"Marine";"Barracks";34;1
"Unit";"Marine";"Barracks";34;1
"Building";"FactoryReactor";NA;32;0
"Building";"EngineeringBay";NA;34;0
"Unit";"SCV";"Command Center";37;1
"Unit";"Marine";"Barracks";37;1
"Unit";"SCV";"Command Center";37;1
"Unit";"SCV";"Command Center";41;1
"Unit";"Marine";"Barracks";41;1
"Unit";"Marine";"Barracks";41;1
"Unit";"SCV";"Command Center";43;1
"Building";"SupplyDepot";NA;43;0
"Building";"MissileTurret";NA;43;0
"Unit";"Marine";"Barracks";43;1
"Unit";"SCV";"Command Center";47;1
"Unit";"SCV";"Command Center";47;1
"Unit";"Marine";"Barracks";47;1
"Unit";"Marine";"Barracks";47;1
"Building";"SupplyDepot";NA;47;0
"Unit";"Marine";"Barracks";48;1
"Building";"Refinery";NA;48;0
"Unit";"Medivac";"Starport";47;2
"Unit";"Medivac";"Starport";47;2
"Unit";"SCV";"Command Center";52;1
"Unit";"SCV";"Command Center";52;1
"Building";"SupplyDepot";NA;50;0
"Upgrade";"Stimpack";"TechLab";36;0
"Unit";"Marine";"Barracks";52;1
"Unit";"Marine";"Barracks";52;1
"Building";"FactoryTechLab";NA;52;0
"Unit";"SCV";"Command Center";57;1
"Unit";"SCV";"Command Center";59;1
"Building";"SupplyDepot";NA;53;0
"Unit";"Marine";"Barracks";59;1
"Unit";"SCV";"Command Center";62;1
"Unit";"Marine";"Barracks";63;1
"Unit";"Marine";"Barracks";63;1
"Unit";"SCV";"Command Center";65;1
"Unit";"Marine";"Barracks";68;1
"Unit";"Marine";"Barracks";68;1
"Unit";"Marine";"Barracks";68;1
"Unit";"SCV";"Command Center";69;1
"Unit";"SCV";"Command Center";69;1
"Unit";"Medivac";"Starport";68;2
"Unit";"Marine";"Barracks";69;1
"Unit";"Marine";"Barracks";71;1
"Unit";"Marine";"Barracks";71;1
"Building";"CommandCenter";NA;61;0
"Unit";"SCV";"Command Center";73;1
"Unit";"SCV";"Command Center";75;1
"Upgrade";"TerranInfantryWeaponsLevel1";"EngineeringBay";61;0
"Building";"Refinery";NA;71;0
"Unit";"SCV";"Command Center";78;1
"Unit";"Medivac";"Starport";71;2
"Unit";"Marine";"Barracks";78;1
"Unit";"Marine";"Barracks";78;1
"Unit";"SCV";"Command Center";80;1
"Unit";"Medivac";"Starport";73;2
"Unit";"SCV";"Command Center";80;1
"Unit";"Marine";"Barracks";80;1
"Building";"Barracks";NA;71;0
"Building";"Barracks";NA;71;0
"Building";"Barracks";NA;71;0
"Building";"SupplyDepot";NA;80;0
"Unit";"SCV";"Command Center";86;1
"Building";"SupplyDepot";NA;80;0
"Unit";"Marine";"Barracks";83;1
"Unit";"Marine";"Barracks";88;1
"Unit";"SCV";"Command Center";90;1
"Unit";"SCV";"Command Center";92;1
"Unit";"Marine";"Barracks";89;1
"Unit";"SCV";"Command Center";93;1
"Unit";"SCV";"Command Center";94;1
"Unit";"Medivac";"Starport";89;2
"Unit";"Medivac";"Starport";89;2
"Unit";"SCV";"Command Center";94;1
"Unit";"Marine";"Barracks";94;1
"Unit";"Marine";"Barracks";94;1
"Unit";"Marine";"Barracks";95;1
"Unit";"SCV";"Command Center";96;1
"Building";"BarracksReactor";NA;91;0
"Unit";"SCV";"Command Center";103;1
"Unit";"SCV";"Command Center";103;1
"Building";"BarracksReactor";NA;92;0
"Building";"BarracksReactor";NA;92;0
"Building";"Factory";NA;90;0
"Building";"Refinery";NA;96;0
"Building";"Refinery";NA;96;0
"Unit";"Marine";"Barracks";103;1
"Unit";"SCV";"Command Center";107;1
"Unit";"SCV";"Command Center";107;1
"Unit";"SCV";"Command Center";109;1
"Unit";"Marine";"Barracks";107;1
"Unit";"Marine";"Barracks";107;1
"Unit";"Marine";"Barracks";107;1
"Unit";"Marine";"Barracks";107;1
"Unit";"SCV";"Command Center";110;1
"Unit";"SCV";"Command Center";111;1
"Unit";"SCV";"Command Center";112;1
"Unit";"Marine";"Barracks";109;1
"Unit";"Marine";"Barracks";109;1
"Unit";"Marine";"Barracks";109;1
"Unit";"Medivac";"Starport";109;2
"Unit";"Medivac";"Starport";109;2
"Building";"FactoryTechLab";NA;117;0
"Unit";"SCV";"Command Center";118;1
"Unit";"SCV";"Command Center";118;1
"Building";"SupplyDepot";NA;115;0
"Building";"SupplyDepot";NA;117;0
"Building";"SupplyDepot";NA;117;0
"Unit";"Marine";"Barracks";122;1
"Unit";"Marine";"Barracks";123;1
"Unit";"Marine";"Barracks";123;1
"Building";"SensorTower";NA;123;0
"Unit";"SCV";"Command Center";129;1
"Upgrade";"TerranInfantryArmorsLevel1";"EngineeringBay";93;0
"Unit";"SCV";"Command Center";129;1
"Unit";"SCV";"Command Center";129;1
"Unit";"Marine";"Barracks";129;1
"Unit";"Marine";"Barracks";129;1
"Unit";"Marine";"Barracks";129;1
"Unit";"Marine";"Barracks";129;1
"Unit";"Marine";"Barracks";129;1
"Building";"EngineeringBay";NA;127;0
"Building";"SupplyDepot";NA;133;0
"Building";"SupplyDepot";NA;135;0
"Building";"Armory";NA;127;0
"Unit";"Marine";"Barracks";140;1
"Unit";"Marine";"Barracks";140;1
"Unit";"Marine";"Barracks";140;1
"Unit";"Marine";"Barracks";140;1
"Unit";"Marine";"Barracks";140;1
"Unit";"Marine";"Barracks";140;1
"Unit";"Marine";"Barracks";140;1
"Unit";"Marine";"Barracks";140;1
"Unit";"Marine";"Barracks";140;1
"Building";"MissileTurret";NA;140;0
"Building";"Factory";NA;133;0
"Unit";"Marine";"Barracks";140;1
"Unit";"Marine";"Barracks";141;1
"Unit";"Marine";"Barracks";142;1
"Unit";"Marine";"Barracks";143;1
"Building";"SupplyDepot";NA;140;0
"Building";"SupplyDepot";NA;144;0
"Unit";"Marine";"Barracks";149;1
"Unit";"Marine";"Barracks";153;1
"Unit";"Marine";"Barracks";153;1
"Unit";"Marine";"Barracks";153;1
"Unit";"Marine";"Barracks";153;1
"Unit";"Marine";"Barracks";153;1
"Unit";"Marine";"Barracks";153;1
"Unit";"Marine";"Barracks";153;1
"Unit";"Marine";"Barracks";153;1
"Building";"FactoryTechLab";NA;153;0
"Unit";"Marine";"Barracks";153;1
"Unit";"Medivac";"Starport";153;2
"Unit";"Medivac";"Starport";153;2
"Unit";"Marine";"Barracks";154;1
"Unit";"Marine";"Barracks";155;1
"Unit";"Marine";"Barracks";155;1
"Unit";"Marine";"Barracks";163;1
"Unit";"Marine";"Barracks";167;1
"Unit";"Marine";"Barracks";167;1
"Unit";"Marine";"Barracks";167;1
"Unit";"Marine";"Barracks";167;1
"Unit";"Marine";"Barracks";167;1
"Unit";"Marine";"Barracks";167;1
"Unit";"Marine";"Barracks";168;1
"Unit";"Marine";"Barracks";168;1
"Unit";"Medivac";"Starport";163;2
"Unit";"Medivac";"Starport";165;2
"Unit";"Marine";"Barracks";170;1
"Unit";"Marine";"Barracks";171;1
"Unit";"Marine";"Barracks";171;1
"Unit";"Marine";"Barracks";173;1
"Unit";"Marine";"Barracks";173;1
"Unit";"Marine";"Barracks";176;1
"Unit";"Marine";"Barracks";176;1
"Unit";"Marine";"Barracks";177;1
"Unit";"Marine";"Barracks";183;1
"Unit";"Marine";"Barracks";183;1
"Unit";"Marine";"Barracks";184;1
"Unit";"Marine";"Barracks";189;1
"Unit";"Marine";"Barracks";191;1
"Unit";"Marine";"Barracks";191;1
"Unit";"Marine";"Barracks";191;1
"Unit";"Medivac";"Starport";179;2
"Unit";"Medivac";"Starport";181;2
"Unit";"Marine";"Barracks";191;1
"Unit";"Marine";"Barracks";191;1
"Unit";"Marine";"Barracks";191;1
"Unit";"Marine";"Barracks";192;1
"Unit";"Marine";"Barracks";193;1
"Unit";"Marine";"Barracks";194;1
"Unit";"Marine";"Barracks";195;1
"Unit";"Marine";"Barracks";196;1
"Unit";"Marine";"Barracks";198;1
"Unit";"Marine";"Barracks";202;1
"Unit";"Marine";"Barracks";203;1
"Unit";"Marine";"Barracks";204;1
"Unit";"Marine";"Barracks";205;1
"Unit";"Marine";"Barracks";206;1
"Unit";"Medivac";"Starport";198;2
"Unit";"Medivac";"Starport";200;2
"Unit";"Marine";"Barracks";207;1
"Unit";"Marine";"Barracks";209;1
"Unit";"Marine";"Barracks";209;1
"Unit";"Marine";"Barracks";210;1
"Unit";"SCV";"Command Center";213;1
"Unit";"SCV";"Command Center";213;1
"Unit";"SCV";"Command Center";213;1
"Unit";"Marine";"Barracks";211;1
"Upgrade";"TerranInfantryWeaponsLevel2";"EngineeringBay";170;0
"Unit";"Marine";"Barracks";221;1
"Unit";"Marine";"Barracks";221;1
"Unit";"Marine";"Barracks";224;1
"Unit";"Marine";"Barracks";224;1
"Unit";"Marine";"Barracks";224;1
"Unit";"Marine";"Barracks";224;1
"Unit";"Marine";"Barracks";225;1
"Unit";"Marine";"Barracks";227;1
"Unit";"Marine";"Barracks";227;1
"Unit";"Medivac";"Starport";216;2
"Unit";"Medivac";"Starport";218;2
"Upgrade";"TerranVehicleWeaponsLevel1";"Armory";191;0
"Unit";"Marine";"Barracks";228;1
"Unit";"Marine";"Barracks";229;1
