"type";"unit_name";"on_building";"total_supply";"supply"
"Building";"Refinery";NA;14;0
"Building";"Barracks";NA;15;0
"Unit";"Marine";"Barracks";19;1
"Building";"BarracksReactor";NA;20;0
"Building";"Refinery";NA;20;0
"Building";"Factory";NA;20;0
"Building";"CommandCenter";NA;19;0
"Unit";"Marine";"Barracks";23;1
"Unit";"Marine";"Barracks";25;1
"Unit";"Cyclone";"Factory";24;3
"Unit";"Cyclone";"Factory";24;3
"Building";"EngineeringBay";NA;26;0
"Unit";"Hellion";"Factory";30;2
"Unit";"Hellion";"Factory";33;2
"Building";"BarracksTechLab";NA;34;0
"Building";"MissileTurret";NA;36;0
"Unit";"Marine";"Barracks";42;1
"Building";"Barracks";NA;40;0
"Unit";"Marine";"Barracks";45;1
"Building";"Bunker";NA;45;0
"Unit";"Marine";"Barracks";47;1
"Unit";"Marine";"Barracks";47;1
"Unit";"Marine";"Barracks";48;1
"Building";"FactoryReactor";NA;46;0
"Building";"Starport";NA;46;0
"Building";"Refinery";NA;50;0
"Unit";"Marine";"Barracks";53;1
"Unit";"Marine";"Barracks";53;1
"Unit";"Marine";"Barracks";55;1
"Building";"FactoryTechLab";NA;58;0
"Building";"Barracks";NA;50;0
"Unit";"Marine";"Barracks";60;1
"Unit";"Marine";"Barracks";60;1
"Unit";"Marine";"Barracks";60;1
"Unit";"Marine";"Barracks";62;1
"Unit";"Medivac";"Starport";60;2
"Unit";"Medivac";"Starport";60;2
"Unit";"Marine";"Barracks";66;1
"Unit";"Marine";"Barracks";66;1
"Unit";"Marine";"Barracks";66;1
"Unit";"Marine";"Barracks";68;1
"Upgrade";"Stimpack";"TechLab";55;0
"Upgrade";"TerranInfantryWeaponsLevel1";"EngineeringBay";56;0
"Unit";"Marine";"Barracks";80;1
"Unit";"Marine";"Barracks";80;1
"Unit";"Marine";"Barracks";80;1
"Building";"BarracksReactor";NA;78;0
"Unit";"Marine";"Barracks";82;1
"Unit";"Marine";"Barracks";83;1
"Unit";"Marine";"Barracks";85;1
"Unit";"Marine";"Barracks";86;1
"Unit";"Marine";"Barracks";86;1
"Unit";"Marine";"Barracks";86;1
"Building";"CommandCenter";NA;78;0
"Unit";"Marine";"Barracks";91;1
"Unit";"Marine";"Barracks";93;1
"Unit";"Marine";"Barracks";93;1
"Unit";"Marine";"Barracks";93;1
"Unit";"Marine";"Barracks";94;1
"Unit";"Marine";"Barracks";95;1
"Building";"Barracks";NA;89;0
"Building";"Barracks";NA;89;0
"Unit";"Marine";"Barracks";100;1
"Unit";"Marine";"Barracks";100;1
"Unit";"Marine";"Barracks";100;1
"Unit";"Marine";"Barracks";103;1
"Unit";"Marine";"Barracks";103;1
"Building";"Refinery";NA;106;0
"Unit";"Marine";"Barracks";106;1
"Unit";"Marine";"Barracks";106;1
"Unit";"Marine";"Barracks";106;1
"Building";"BarracksReactor";NA;103;0
"Building";"BarracksReactor";NA;103;0
"Unit";"Marine";"Barracks";114;1
"Unit";"Marine";"Barracks";115;1
"Unit";"Marine";"Barracks";115;1
"Unit";"Marine";"Barracks";115;1
"Unit";"Medivac";"Starport";110;2
"Unit";"Medivac";"Starport";110;2
"Unit";"Marine";"Barracks";115;1
"Unit";"Marine";"Barracks";115;1
"Unit";"Marine";"Barracks";115;1
"Upgrade";"TerranInfantryArmorsLevel1";"EngineeringBay";96;0
"Unit";"Marine";"Barracks";115;1
"Unit";"Marine";"Barracks";116;1
"Unit";"Marine";"Barracks";117;1
"Unit";"Marine";"Barracks";118;1
"Unit";"Marine";"Barracks";136;1
"Unit";"Marine";"Barracks";137;1
"Unit";"Marine";"Barracks";137;1
"Unit";"Marine";"Barracks";137;1
"Unit";"Marine";"Barracks";137;1
"Building";"EngineeringBay";NA;136;0
"Unit";"Marine";"Barracks";139;1
"Unit";"Marine";"Barracks";139;1
"Building";"Factory";NA;126;0
"Unit";"Marine";"Barracks";139;1
"Building";"Factory";NA;130;0
"Unit";"Marine";"Barracks";146;1
"Unit";"Marine";"Barracks";146;1
"Unit";"Medivac";"Starport";139;2
"Building";"Armory";NA;136;0
"Unit";"Medivac";"Starport";139;2
"Unit";"Marine";"Barracks";149;1
"Unit";"Marine";"Barracks";149;1
"Unit";"Marine";"Barracks";149;1
"Unit";"Marine";"Barracks";149;1
"Unit";"Marine";"Barracks";149;1
"Unit";"Marine";"Barracks";151;1
"Unit";"Marine";"Barracks";151;1
"Unit";"Marine";"Barracks";151;1
"Unit";"Marine";"Barracks";151;1
"Building";"FactoryTechLab";NA;151;0
"Building";"FactoryTechLab";NA;151;0
"Unit";"Marine";"Barracks";155;1
"Unit";"Marine";"Barracks";156;1
"Unit";"Marine";"Barracks";157;1
"Unit";"Marine";"Barracks";158;1
"Unit";"Marine";"Barracks";160;1
"Unit";"Marine";"Barracks";160;1
"Unit";"Marine";"Barracks";164;1
"Unit";"Marine";"Barracks";164;1
"Unit";"Marine";"Barracks";164;1
"Unit";"Medivac";"Starport";155;2
"Unit";"Medivac";"Starport";155;2
"Unit";"Marine";"Barracks";164;1
"Building";"Refinery";NA;164;0
"Building";"Refinery";NA;164;0
"Unit";"Marine";"Barracks";168;1
"Unit";"Marine";"Barracks";168;1
"Unit";"Marine";"Barracks";169;1
"Unit";"Marine";"Barracks";184;1
"Unit";"Marine";"Barracks";184;1
"Unit";"Marine";"Barracks";184;1
"Unit";"Marine";"Barracks";184;1
"Building";"SensorTower";NA;184;0
"Unit";"Marine";"Barracks";187;1
"Unit";"Marine";"Barracks";187;1
"Unit";"Marine";"Barracks";187;1
"Building";"BarracksReactor";NA;184;0
"Unit";"Marine";"Barracks";188;1
"Unit";"Marine";"Barracks";188;1
"Unit";"Marine";"Barracks";188;1
"Unit";"Marine";"Barracks";188;1
"Unit";"Marine";"Barracks";191;1
"Unit";"Marine";"Barracks";192;1
"Unit";"Marine";"Barracks";195;1
"Unit";"Marine";"Barracks";198;1
"Unit";"Marine";"Barracks";199;1
"Unit";"Marine";"Barracks";199;1
"Unit";"Marine";"Barracks";199;1
"Unit";"Marine";"Barracks";199;1
"Unit";"Marine";"Barracks";199;1
"Building";"CommandCenter";NA;184;0
"Unit";"Medivac";"Starport";199;2
"Unit";"Medivac";"Starport";199;2
"Unit";"Marine";"Barracks";208;1
"Unit";"Marine";"Barracks";208;1
"Unit";"Marine";"Barracks";208;1
"Unit";"Marine";"Barracks";208;1
"Unit";"Marine";"Barracks";208;1
"Unit";"Marine";"Barracks";208;1
"Unit";"Marine";"Barracks";208;1
"Unit";"Marine";"Barracks";208;1
"Upgrade";"TerranInfantryWeaponsLevel2";"EngineeringBay";181;0
"Unit";"Marine";"Barracks";208;1
"Upgrade";"TerranInfantryArmorsLevel2";"EngineeringBay";184;0
"Unit";"Marine";"Barracks";212;1
"Unit";"Marine";"Barracks";213;1
"Unit";"Marine";"Barracks";214;1
"Unit";"Marine";"Barracks";215;1
"Unit";"Marine";"Barracks";216;1
"Unit";"Marine";"Barracks";217;1
"Unit";"Marine";"Barracks";218;1
"Unit";"Marine";"Barracks";219;1
"Unit";"Marine";"Barracks";221;1
"Unit";"Marine";"Barracks";221;1
"Unit";"Marine";"Barracks";222;1
"Upgrade";"TerranVehicleWeaponsLevel1";"Armory";198;0
"Unit";"Marine";"Barracks";229;1
"Unit";"Medivac";"Starport";221;2
"Unit";"Medivac";"Starport";221;2
"Unit";"Marine";"Barracks";230;1
"Unit";"Marine";"Barracks";230;1
"Unit";"Marine";"Barracks";230;1
"Unit";"Marine";"Barracks";230;1
"Unit";"Marine";"Barracks";230;1
"Unit";"Marine";"Barracks";230;1
"Unit";"Marine";"Barracks";230;1
"Unit";"Marine";"Barracks";231;1
"Unit";"Marine";"Barracks";233;1
"Unit";"Marine";"Barracks";238;1
"Unit";"Marine";"Barracks";246;1
"Unit";"Medivac";"Starport";234;2
"Unit";"Medivac";"Starport";236;2
"Building";"SensorTower";NA;250;0
"Unit";"Marine";"Barracks";250;1
"Unit";"Marine";"Barracks";252;1
"Unit";"Marine";"Barracks";257;1
"Unit";"Marine";"Barracks";257;1
"Unit";"Marine";"Barracks";257;1
"Unit";"Marine";"Barracks";257;1
"Unit";"Marine";"Barracks";257;1
"Unit";"Marine";"Barracks";257;1
"Unit";"Marine";"Barracks";257;1
"Unit";"Marine";"Barracks";257;1
"Unit";"Medivac";"Starport";252;2
"Unit";"Medivac";"Starport";254;2
"Unit";"Marine";"Barracks";257;1
