"Type";"UnitName";"OnBuilding";"TotalSupply";"Supply"
"Unit";"SCV";"Command Center";12;1
"Unit";"SCV";"Command Center";12;1
"Unit";"SCV";"Command Center";13;1
"Building";"SupplyDepot";NA;13;0
"Unit";"SCV";"Command Center";15;1
"Unit";"SCV";"Command Center";15;1
"Building";"Refinery";NA;15;0
"Unit";"SCV";"Command Center";16;1
"Building";"Barracks";NA;15;0
"Unit";"SCV";"Command Center";18;1
"Unit";"Reaper";"Barracks";19;1
"Unit";"SCV";"Command Center";19;1
"Unit";"SCV";"Command Center";21;1
"Building";"SupplyDepot";NA;21;0
"Unit";"SCV";"Command Center";21;1
"Building";"BarracksReactor";NA;20;0
"Building";"Barracks";NA;19;0
"Building";"Refinery";NA;21;0
"Unit";"SCV";"Command Center";22;1
"Building";"CommandCenter";NA;19;0
"Unit";"Marine";"Barracks";23;1
"Unit";"Marine";"Barracks";23;1
"Building";"BarracksTechLab";NA;23;0
"Unit";"SCV";"Command Center";24;1
"Building";"Factory";NA;22;0
"Unit";"Marine";"Barracks";24;1
"Unit";"Marine";"Barracks";25;1
"Unit";"SCV";"Command Center";27;1
"Unit";"Marine";"Barracks";27;1
"Unit";"SCV";"Command Center";29;1
"Unit";"Marine";"Barracks";31;1
"Unit";"Marine";"Barracks";31;1
"Unit";"Marine";"Barracks";31;1
"Unit";"SCV";"Command Center";32;1
"Unit";"SCV";"Command Center";32;1
"Unit";"Marine";"Barracks";35;1
"Unit";"Marine";"Barracks";35;1
"Unit";"SCV";"Command Center";37;1
"Unit";"SCV";"Command Center";37;1
"Building";"Starport";NA;31;0
"Unit";"Marine";"Barracks";37;1
"Building";"FactoryReactor";NA;32;0
"Building";"EngineeringBay";NA;36;0
"Unit";"SCV";"Command Center";40;1
"Building";"SupplyDepot";NA;39;0
"Unit";"SCV";"Command Center";42;1
"Unit";"Marine";"Barracks";42;1
"Unit";"Marine";"Barracks";42;1
"Unit";"Marine";"Barracks";43;1
"Unit";"SCV";"Command Center";43;1
"Building";"MissileTurret";NA;43;0
"Unit";"SCV";"Command Center";43;1
"Building";"Bunker";NA;42;0
"Building";"SupplyDepot";NA;44;0
"Unit";"Marine";"Barracks";46;1
"Unit";"Marine";"Barracks";46;1
"Unit";"SCV";"Command Center";49;1
"Unit";"SCV";"Command Center";49;1
"Unit";"Medivac";"Starport";46;2
"Unit";"Medivac";"Starport";46;2
"Building";"SupplyDepot";NA;49;0
"Unit";"Marine";"Barracks";49;1
"Building";"FactoryTechLab";NA;49;0
"Building";"SupplyDepot";NA;49;0
"Unit";"SCV";"Command Center";51;1
"Unit";"SCV";"Command Center";53;1
"Unit";"Marine";"Barracks";51;1
"Unit";"Marine";"Barracks";51;1
"Upgrade";"Stimpack";"TechLab";36;0
"Unit";"SCV";"Command Center";58;1
"Unit";"SCV";"Command Center";59;1
"Building";"Refinery";NA;58;0
"Unit";"Marine";"Barracks";62;1
"Unit";"Marine";"Barracks";62;1
"Building";"SupplyDepot";NA;59;0
"Unit";"Marine";"Barracks";62;1
"Unit";"SCV";"Command Center";64;1
"Unit";"Marine";"Barracks";64;1
"Unit";"Marine";"Barracks";65;1
"Unit";"Marine";"Barracks";68;1
"Unit";"SCV";"Command Center";70;1
"Unit";"SCV";"Command Center";70;1
"Unit";"Marine";"Barracks";70;1
"Unit";"Marine";"Barracks";70;1
"Unit";"SCV";"Command Center";72;1
"Building";"SupplyDepot";NA;70;0
"Unit";"Marine";"Barracks";71;1
"Unit";"SCV";"Command Center";75;1
"Unit";"Marine";"Barracks";75;1
"Unit";"Marine";"Barracks";75;1
"Unit";"SCV";"Command Center";75;1
"Unit";"SCV";"Command Center";77;1
"Unit";"Marine";"Barracks";77;1
"Unit";"SCV";"Command Center";81;1
"Building";"Barracks";NA;70;0
"Building";"SupplyDepot";NA;78;0
"Unit";"Marine";"Barracks";81;1
"Unit";"Marine";"Barracks";81;1
"Building";"CommandCenter";NA;68;0
"Upgrade";"TerranInfantryWeaponsLevel1";"EngineeringBay";64;0
"Unit";"Marine";"Barracks";84;1
"Building";"Barracks";NA;76;0
"Building";"Barracks";NA;76;0
"Unit";"SCV";"Command Center";86;1
"Unit";"SCV";"Command Center";86;1
"Unit";"Marine";"Barracks";86;1
"Unit";"Marine";"Barracks";86;1
"Unit";"Marine";"Barracks";86;1
"Unit";"SCV";"Command Center";87;1
"Unit";"SCV";"Command Center";89;1
"Building";"BarracksReactor";NA;86;0
"Building";"Refinery";NA;87;0
"Building";"MissileTurret";NA;88;0
"Unit";"Marine";"Barracks";89;1
"Unit";"Marine";"Barracks";90;1
"Unit";"SCV";"Command Center";93;1
"Unit";"SCV";"Command Center";93;1
"Unit";"Marine";"Barracks";93;1
"Building";"BarracksReactor";NA;87;0
"Unit";"Marine";"Barracks";94;1
"Building";"BarracksReactor";NA;88;0
"Unit";"SCV";"Command Center";96;1
"Unit";"SCV";"Command Center";97;1
"Building";"Factory";NA;87;0
"Unit";"SCV";"Command Center";100;1
"Unit";"SCV";"Command Center";101;1
"Building";"Refinery";NA;98;0
"Unit";"Medivac";"Starport";94;2
"Building";"Refinery";NA;98;0
"Unit";"Medivac";"Starport";94;2
"Building";"SupplyDepot";NA;98;0
"Building";"SupplyDepot";NA;99;0
"Building";"MissileTurret";NA;102;0
"Unit";"Marine";"Barracks";102;1
"Unit";"Marine";"Barracks";102;1
"Unit";"Marine";"Barracks";102;1
"Unit";"SCV";"Command Center";108;1
"Unit";"SCV";"Command Center";108;1
"Building";"FactoryTechLab";NA;103;0
"Unit";"SCV";"Command Center";108;1
"Unit";"Marine";"Barracks";108;1
"Unit";"Marine";"Barracks";108;1
"Unit";"Marine";"Barracks";108;1
"Unit";"Marine";"Barracks";108;1
"Unit";"Marine";"Barracks";108;1
"Unit";"Marine";"Barracks";108;1
"Building";"SensorTower";NA;108;0
"Unit";"SCV";"Command Center";111;1
"Building";"SupplyDepot";NA;108;0
"Unit";"Marine";"Barracks";111;1
"Unit";"Marine";"Barracks";111;1
"Building";"SupplyDepot";NA;108;0
"Unit";"Marine";"Barracks";111;1
"Unit";"SCV";"Command Center";120;1
"Unit";"SCV";"Command Center";120;1
"Unit";"Marine";"Barracks";120;1
"Unit";"Marine";"Barracks";120;1
"Unit";"Marine";"Barracks";121;1
"Unit";"Marine";"Barracks";121;1
"Unit";"Marine";"Barracks";123;1
"Unit";"Marine";"Barracks";123;1
"Building";"EngineeringBay";NA;120;0
"Unit";"Marine";"Barracks";124;1
"Unit";"Marine";"Barracks";124;1
"Unit";"Marine";"Barracks";126;1
"Building";"SupplyDepot";NA;124;0
"Building";"SupplyDepot";NA;126;0
"Unit";"Marine";"Barracks";128;1
"Unit";"Marine";"Barracks";128;1
"Unit";"Marine";"Barracks";132;1
"Unit";"Marine";"Barracks";132;1
"Building";"Armory";NA;120;0
"Unit";"Marine";"Barracks";137;1
"Unit";"Marine";"Barracks";137;1
"Unit";"Marine";"Barracks";137;1
"Unit";"Marine";"Barracks";137;1
"Unit";"Marine";"Barracks";137;1
"Unit";"SCV";"Command Center";139;1
"Unit";"Marine";"Barracks";139;1
"Unit";"Marine";"Barracks";139;1
"Unit";"SCV";"Command Center";139;1
"Unit";"Marine";"Barracks";139;1
"Unit";"Marine";"Barracks";139;1
"Unit";"SCV";"Command Center";139;1
"Upgrade";"TerranInfantryArmorsLevel1";"EngineeringBay";108;0
"Building";"MissileTurret";NA;139;0
"Unit";"Medivac";"Starport";139;2
"Unit";"Medivac";"Starport";139;2
"Unit";"Marine";"Barracks";151;1
"Unit";"Marine";"Barracks";151;1
"Unit";"Marine";"Barracks";151;1
"Unit";"Marine";"Barracks";151;1
"Unit";"Marine";"Barracks";151;1
"Unit";"Marine";"Barracks";151;1
"Unit";"Marine";"Barracks";151;1
"Unit";"Marine";"Barracks";151;1
"Building";"SupplyDepot";NA;151;0
"Building";"SensorTower";NA;155;0
"Unit";"Marine";"Barracks";157;1
"Unit";"Marine";"Barracks";158;1
"Unit";"Marine";"Barracks";159;1
"Unit";"Marine";"Barracks";163;1
"Unit";"Marine";"Barracks";163;1
"Unit";"Marine";"Barracks";163;1
"Unit";"Marine";"Barracks";163;1
"Building";"SupplyDepot";NA;163;0
"Building";"SupplyDepot";NA;163;0
"Building";"CommandCenter";NA;139;0
"Unit";"Marine";"Barracks";166;1
"Unit";"Marine";"Barracks";170;1
"Building";"SupplyDepot";NA;170;0
"Building";"SupplyDepot";NA;170;0
"Unit";"Marine";"Barracks";171;1
"Unit";"Marine";"Barracks";171;1
"Unit";"Marine";"Barracks";171;1
"Unit";"Marine";"Barracks";171;1
"Unit";"Marine";"Barracks";171;1
"Unit";"Medivac";"Starport";170;2
"Unit";"Medivac";"Starport";170;2
"Unit";"Marine";"Barracks";171;1
"Unit";"Marine";"Barracks";172;1
"Unit";"Marine";"Barracks";172;1
"Unit";"Marine";"Barracks";172;1
"Unit";"Marine";"Barracks";172;1
"Unit";"Marine";"Barracks";173;1
"Unit";"Marine";"Barracks";174;1
"Unit";"Marine";"Barracks";175;1
"Unit";"Marine";"Barracks";176;1
"Unit";"Marine";"Barracks";181;1
"Upgrade";"TerranVehicleWeaponsLevel1";"Armory";163;0
"Unit";"Marine";"Barracks";182;1
"Unit";"Marine";"Barracks";183;1
"Unit";"Marine";"Barracks";184;1
"Unit";"Marine";"Barracks";191;1
"Unit";"Marine";"Barracks";191;1
"Unit";"Marine";"Barracks";191;1
"Unit";"Marine";"Barracks";191;1
"Upgrade";"TerranInfantryWeaponsLevel2";"EngineeringBay";163;0
"Building";"CommandCenter";NA;170;0
"Unit";"Marine";"Barracks";193;1
"Unit";"Marine";"Barracks";193;1
"Unit";"Marine";"Barracks";194;1
"Building";"SensorTower";NA;194;0
"Unit";"SCV";"Command Center";194;1
"Unit";"SCV";"Command Center";194;1
"Unit";"Marine";"Barracks";194;1
"Building";"Refinery";NA;194;0
"Building";"Refinery";NA;194;0
"Unit";"Marine";"Barracks";194;1
"Unit";"Marine";"Barracks";194;1
"Building";"MissileTurret";NA;198;0
"Upgrade";"TerranInfantryArmorsLevel2";"EngineeringBay";170;0
"Unit";"Marine";"Barracks";204;1
"Unit";"Marine";"Barracks";204;1
"Unit";"Marine";"Barracks";206;1
"Unit";"Marine";"Barracks";206;1
"Unit";"Marine";"Barracks";206;1
"Unit";"Marine";"Barracks";211;1
"Unit";"Marine";"Barracks";211;1
"Unit";"Marine";"Barracks";211;1
"Unit";"Marine";"Barracks";214;1
"Unit";"Marine";"Barracks";214;1
"Unit";"Marine";"Barracks";214;1
"Building";"Barracks";NA;211;0
"Building";"Barracks";NA;211;0
"Building";"Barracks";NA;211;0
