"Type";"UnitName";"OnBuilding";"TotalSupply";"Supply"
"Unit";"SCV";"Command Center";12;1
"Unit";"SCV";"Command Center";12;1
"Unit";"SCV";"Command Center";13;1
"Building";"SupplyDepot";NA;13;0
"Unit";"SCV";"Command Center";15;1
"Unit";"SCV";"Command Center";15;1
"Building";"Refinery";NA;15;0
"Unit";"SCV";"Command Center";16;1
"Unit";"SCV";"Command Center";17;1
"Building";"Barracks";NA;15;0
"Unit";"Reaper";"Barracks";19;1
"Unit";"SCV";"Command Center";19;1
"Unit";"SCV";"Command Center";21;1
"Building";"SupplyDepot";NA;20;0
"Unit";"SCV";"Command Center";21;1
"Building";"BarracksReactor";NA;20;0
"Building";"Barracks";NA;19;0
"Unit";"SCV";"Command Center";22;1
"Building";"CommandCenter";NA;19;0
"Unit";"Marine";"Barracks";23;1
"Unit";"Marine";"Barracks";23;1
"Unit";"SCV";"Command Center";23;1
"Building";"Refinery";NA;23;0
"Building";"BarracksTechLab";NA;23;0
"Building";"Barracks";NA;21;0
"Unit";"Marine";"Barracks";24;1
"Unit";"Marine";"Barracks";25;1
"Unit";"Marine";"Barracks";27;1
"Unit";"Marine";"Barracks";27;1
"Unit";"Marauder";"Barracks";27;2
"Unit";"SCV";"Command Center";29;1
"Unit";"SCV";"Command Center";29;1
"Unit";"Marine";"Barracks";29;1
"Unit";"Marine";"Barracks";29;1
"Unit";"SCV";"Command Center";33;1
"Unit";"SCV";"Command Center";35;1
"Unit";"SCV";"Command Center";37;1
"Unit";"Marauder";"Barracks";35;2
"Unit";"SCV";"Command Center";39;1
"Building";"SupplyDepot";NA;35;0
"Building";"BarracksTechLab";NA;37;0
"Unit";"Marine";"Barracks";38;1
"Unit";"Marine";"Barracks";38;1
"Unit";"SCV";"Command Center";45;1
"Unit";"SCV";"Command Center";45;1
"Unit";"Marine";"Barracks";43;1
"Unit";"Marine";"Barracks";44;1
"Unit";"Marauder";"Barracks";43;2
"Unit";"Marauder";"Barracks";43;2
"Unit";"SCV";"Command Center";47;1
"Building";"SupplyDepot";NA;45;0
"Unit";"SCV";"Command Center";47;1
"Unit";"Marine";"Barracks";54;1
"Unit";"Marine";"Barracks";54;1
"Unit";"Marine";"Barracks";55;1
"Building";"Factory";NA;45;0
"Unit";"Marauder";"Barracks";55;2
"Upgrade";"Stimpack";"TechLab";35;0
"Unit";"SCV";"Command Center";57;1
"Unit";"Marine";"Barracks";57;1
"Unit";"Marine";"Barracks";57;1
"Unit";"Marauder";"Barracks";57;2
"Building";"EngineeringBay";NA;57;0
"Unit";"SCV";"Command Center";63;1
"Unit";"Marauder";"Barracks";58;2
"Unit";"Marine";"Barracks";61;1
"Unit";"Marine";"Barracks";62;1
"Building";"FactoryReactor";NA;58;0
"Unit";"SCV";"Command Center";70;1
"Unit";"SCV";"Command Center";70;1
"Unit";"SCV";"Command Center";71;1
"Building";"MissileTurret";NA;70;0
"Unit";"SCV";"Command Center";72;1
"Unit";"Marine";"Barracks";72;1
"Building";"MissileTurret";NA;72;0
"Unit";"Marine";"Barracks";72;1
"Unit";"Marine";"Barracks";72;1
"Unit";"Marauder";"Barracks";72;2
"Unit";"SCV";"Command Center";77;1
"Building";"CommandCenter";NA;63;0
"Unit";"Marauder";"Barracks";76;2
"Building";"Starport";NA;74;0
"Unit";"Marauder";"Barracks";79;2
"Unit";"SCV";"Command Center";80;1
"Unit";"Marine";"Barracks";80;1
"Unit";"Marine";"Barracks";80;1
"Unit";"Marine";"Barracks";82;1
"Unit";"Marine";"Barracks";85;1
"Unit";"Medivac";"Starport";85;2
"Unit";"SCV";"Command Center";88;1
"Unit";"SCV";"Command Center";88;1
"Unit";"Marine";"Barracks";89;1
"Unit";"Marine";"Barracks";89;1
"Unit";"Marauder";"Barracks";89;2
"Unit";"Marauder";"Barracks";93;2
"Unit";"Marine";"Barracks";93;1
"Unit";"Marine";"Barracks";94;1
"Unit";"Marine";"Barracks";95;1
"Unit";"Medivac";"Starport";93;2
"Unit";"Marauder";"Barracks";97;2
"Unit";"SCV";"Command Center";101;1
"Unit";"SCV";"Command Center";101;1
"Unit";"Marine";"Barracks";99;1
"Unit";"Marine";"Barracks";100;1
"Building";"Barracks";NA;93;0
"Building";"Refinery";NA;102;0
"Building";"Refinery";NA;102;0
"Unit";"Medivac";"Starport";99;2
"Building";"SupplyDepot";NA;102;0
"Building";"SupplyDepot";NA;108;0
"Unit";"SCV";"Command Center";110;1
"Building";"SupplyDepot";NA;110;0
"Unit";"SCV";"Command Center";112;1
"Building";"FactoryReactor";NA;102;0
"Unit";"Marine";"Barracks";112;1
"Unit";"Marine";"Barracks";113;1
"Building";"BarracksReactor";NA;110;0
"Unit";"SCV";"Command Center";114;1
"Unit";"Marine";"Barracks";114;1
"Unit";"Marauder";"Barracks";114;2
"Unit";"Marine";"Barracks";115;1
"Unit";"Marine";"Barracks";115;1
"Unit";"Liberator";"Starport";113;3
"Unit";"Marine";"Barracks";117;1
"Unit";"Marine";"Barracks";118;1
"Unit";"Marine";"Barracks";118;1
"Unit";"SCV";"Command Center";121;1
"Unit";"Marine";"Barracks";118;1
"Building";"EngineeringBay";NA;117;0
"Unit";"Marine";"Barracks";120;1
"Unit";"Marine";"Barracks";126;1
"Unit";"Marine";"Barracks";126;1
"Unit";"Marauder";"Barracks";126;2
"Unit";"Marine";"Barracks";130;1
"Unit";"Marine";"Barracks";130;1
"Unit";"Marauder";"Barracks";130;2
"Unit";"Marine";"Barracks";131;1
"Unit";"Marine";"Barracks";132;1
"Unit";"Marine";"Barracks";135;1
"Unit";"Marauder";"Barracks";133;2
"Upgrade";"TerranInfantryArmorsLevel1";"EngineeringBay";114;0
"Building";"SupplyDepot";NA;137;0
"Unit";"Marauder";"Barracks";139;2
"Building";"SupplyDepot";NA;139;0
"Unit";"SCV";"Command Center";144;1
"Unit";"SCV";"Command Center";144;1
"Building";"SupplyDepot";NA;141;0
"Unit";"Marine";"Barracks";144;1
"Unit";"SCV";"Command Center";146;1
"Unit";"Marine";"Barracks";144;1
"Unit";"Marine";"Barracks";144;1
"Unit";"Marine";"Barracks";144;1
"Unit";"Marine";"Barracks";144;1
"Unit";"Liberator";"Starport";139;3
"Unit";"Liberator";"Starport";139;3
"Unit";"Marine";"Barracks";146;1
"Unit";"SCV";"Command Center";146;1
"Unit";"SCV";"Command Center";148;1
"Unit";"Marine";"Barracks";148;1
"Unit";"Marine";"Barracks";150;1
"Unit";"Marine";"Barracks";150;1
"Unit";"Marine";"Barracks";150;1
"Unit";"Marauder";"Barracks";153;2
"Unit";"Marauder";"Barracks";160;2
"Building";"MissileTurret";NA;163;0
"Unit";"Marine";"Barracks";163;1
"Unit";"Marauder";"Barracks";167;2
"Unit";"Marauder";"Barracks";169;2
"Unit";"Marine";"Barracks";172;1
"Unit";"Marine";"Barracks";172;1
"Unit";"Marine";"Barracks";172;1
"Unit";"Marine";"Barracks";174;1
"Unit";"Marine";"Barracks";174;1
"Unit";"SCV";"Command Center";176;1
"Unit";"Marine";"Barracks";174;1
"Unit";"Marine";"Barracks";176;1
"Unit";"Marine";"Barracks";177;1
"Unit";"Marine";"Barracks";178;1
"Unit";"SCV";"Command Center";181;1
"Upgrade";"TerranInfantryWeaponsLevel1";"EngineeringBay";148;0
"Building";"MissileTurret";NA;179;0
"Unit";"Marine";"Barracks";179;1
"Unit";"Marine";"Barracks";180;1
