"type";"unit_name";"on_building";"total_supply";"supply"
"Building";"Refinery";NA;15;0
"Building";"Barracks";NA;15;0
"Unit";"Reaper";"Barracks";19;1
"Building";"BarracksReactor";NA;20;0
"Building";"EngineeringBay";NA;22;0
"Unit";"Marine";"Barracks";23;1
"Building";"Barracks";NA;21;0
"Unit";"Marine";"Barracks";23;1
"Building";"CommandCenter";NA;19;0
"Building";"Barracks";NA;22;0
"Unit";"Marine";"Barracks";27;1
"Unit";"Marine";"Barracks";27;1
"Building";"BarracksTechLab";NA;27;0
"Unit";"Marine";"Barracks";28;1
"Unit";"Marine";"Barracks";29;1
"Unit";"Marine";"Barracks";31;1
"Building";"BarracksReactor";NA;28;0
"Unit";"Marine";"Barracks";33;1
"Unit";"Marine";"Barracks";34;1
"Unit";"Marine";"Barracks";35;1
"Unit";"Marine";"Barracks";38;1
"Unit";"Marine";"Barracks";38;1
"Unit";"Marine";"Barracks";38;1
"Unit";"Marine";"Barracks";39;1
"Unit";"Marine";"Barracks";41;1
"Unit";"Marine";"Barracks";43;1
"Unit";"Marine";"Barracks";44;1
"Building";"Refinery";NA;43;0
"Unit";"Marine";"Barracks";46;1
"Unit";"Marine";"Barracks";47;1
"Upgrade";"TerranInfantryWeaponsLevel1";"EngineeringBay";31;0
"Unit";"Marine";"Barracks";55;1
"Unit";"Marine";"Barracks";55;1
"Unit";"Marine";"Barracks";55;1
"Unit";"Marine";"Barracks";55;1
"Unit";"Marine";"Barracks";55;1
"Building";"Factory";NA;53;0
"Building";"Refinery";NA;57;0
"Unit";"Marine";"Barracks";62;1
"Unit";"Marine";"Barracks";62;1
"Unit";"Marine";"Barracks";62;1
"Unit";"Marine";"Barracks";64;1
"Unit";"Marine";"Barracks";64;1
"Building";"Barracks";NA;57;0
"Building";"Barracks";NA;57;0
"Unit";"Marine";"Barracks";73;1
"Unit";"Marine";"Barracks";73;1
"Unit";"Marine";"Barracks";73;1
"Unit";"Marine";"Barracks";73;1
"Unit";"Marine";"Barracks";73;1
"Unit";"Marine";"Barracks";80;1
"Unit";"Marine";"Barracks";80;1
"Unit";"Marine";"Barracks";80;1
"Unit";"Marine";"Barracks";80;1
"Building";"Starport";NA;73;0
"Building";"FactoryReactor";NA;73;0
"Unit";"Marine";"Barracks";80;1
"Building";"Refinery";NA;82;0
"Unit";"Marine";"Barracks";86;1
"Unit";"Marine";"Barracks";86;1
"Unit";"Marine";"Barracks";86;1
"Unit";"Marine";"Barracks";86;1
"Building";"BarracksReactor";NA;80;0
"Building";"BarracksReactor";NA;80;0
"Building";"EngineeringBay";NA;82;0
"Unit";"Marine";"Barracks";89;1
"Upgrade";"TerranInfantryArmorsLevel1";"EngineeringBay";73;0
"Building";"MissileTurret";NA;95;0
"Unit";"Marine";"Barracks";95;1
"Unit";"Marine";"Barracks";95;1
"Unit";"Marine";"Barracks";95;1
"Unit";"Marine";"Barracks";95;1
"Unit";"Marine";"Barracks";95;1
"Unit";"Marine";"Barracks";95;1
"Unit";"Medivac";"Starport";89;2
"Unit";"Medivac";"Starport";89;2
"Unit";"Marine";"Barracks";95;1
"Building";"Armory";NA;86;0
"Building";"CommandCenter";NA;75;0
"Upgrade";"Stimpack";"TechLab";73;0
"Unit";"Marine";"Barracks";98;1
"Unit";"Marine";"Barracks";98;1
"Unit";"Medivac";"Starport";109;2
"Unit";"Medivac";"Starport";109;2
"Unit";"Marine";"Barracks";113;1
"Unit";"Marine";"Barracks";113;1
"Unit";"Marine";"Barracks";113;1
"Unit";"Marine";"Barracks";113;1
"Unit";"Marine";"Barracks";113;1
"Unit";"Marine";"Barracks";114;1
"Unit";"Marine";"Barracks";115;1
"Building";"Refinery";NA;115;0
"Unit";"Marine";"Barracks";115;1
"Building";"FactoryReactor";NA;115;0
"Building";"Starport";NA;115;0
"Unit";"Marine";"Barracks";129;1
"Unit";"Marine";"Barracks";129;1
"Unit";"Marine";"Barracks";129;1
"Unit";"Marine";"Barracks";129;1
"Unit";"Marine";"Barracks";129;1
"Unit";"Marine";"Barracks";129;1
"Unit";"Marine";"Barracks";129;1
"Unit";"Marine";"Barracks";129;1
"Unit";"Marine";"Barracks";142;1
"Unit";"Marine";"Barracks";142;1
"Unit";"Marine";"Barracks";142;1
"Unit";"Marine";"Barracks";142;1
"Unit";"Marine";"Barracks";142;1
"Unit";"Marine";"Barracks";142;1
"Unit";"Marine";"Barracks";142;1
"Unit";"Marine";"Barracks";142;1
"Unit";"Marine";"Barracks";142;1
"Unit";"Liberator";"Starport";130;3
"Unit";"Liberator";"Starport";130;3
"Building";"Refinery";NA;142;0
"Unit";"Marine";"Barracks";153;1
"Unit";"Marine";"Barracks";153;1
"Unit";"Marine";"Barracks";153;1
"Unit";"Marine";"Barracks";153;1
"Unit";"Marine";"Barracks";153;1
"Unit";"Marine";"Barracks";153;1
"Building";"Starport";NA;142;0
"Upgrade";"TerranInfantryWeaponsLevel2";"EngineeringBay";128;0
"Unit";"Marine";"Barracks";167;1
"Unit";"Marine";"Barracks";167;1
"Unit";"Marine";"Barracks";167;1
"Unit";"Marine";"Barracks";167;1
"Unit";"Marine";"Barracks";167;1
"Unit";"Marine";"Barracks";167;1
"Unit";"Marine";"Barracks";167;1
"Unit";"Marine";"Barracks";167;1
"Unit";"Marauder";"Barracks";167;2
"Upgrade";"TerranShipWeaponsLevel1";"Armory";132;0
"Building";"FactoryTechLab";NA;177;0
"Building";"CommandCenter";NA;149;0
"Upgrade";"TerranInfantryArmorsLevel2";"EngineeringBay";140;0
"Building";"Refinery";NA;180;0
"Unit";"Marauder";"Barracks";180;2
"Building";"Refinery";NA;180;0
"Building";"FusionCore";NA;180;0
"Unit";"Raven";"Starport";185;2
"Unit";"Liberator";"Starport";185;3
"Unit";"Liberator";"Starport";185;3
"Building";"Starport";NA;185;0
"Unit";"Marine";"Barracks";193;1
"Unit";"Marine";"Barracks";193;1
"Unit";"Marine";"Barracks";193;1
"Unit";"Marine";"Barracks";193;1
"Unit";"Marine";"Barracks";193;1
"Unit";"Marine";"Barracks";193;1
"Unit";"Marine";"Barracks";193;1
"Unit";"Marine";"Barracks";193;1
"Building";"Starport";NA;193;0
"Unit";"Marauder";"Barracks";193;2
"Building";"Barracks";NA;185;0
"Building";"Barracks";NA;187;0
"Unit";"Medivac";"Starport";193;2
"Unit";"Medivac";"Starport";193;2
"Upgrade";"TerranInfantryWeaponsLevel3";"EngineeringBay";183;0
"Unit";"Liberator";"Starport";193;3
"Upgrade";"TerranShipWeaponsLevel2";"Armory";185;0
"Building";"StarportTechLab";NA;203;0
"Building";"BarracksTechLab";NA;203;0
"Building";"BarracksTechLab";NA;203;0
"Building";"SensorTower";NA;210;0
"Unit";"Marine";"Barracks";210;1
"Unit";"Marine";"Barracks";210;1
"Unit";"Marine";"Barracks";210;1
"Unit";"Marine";"Barracks";210;1
"Unit";"Marine";"Barracks";210;1
"Unit";"Marine";"Barracks";210;1
"Unit";"Marauder";"Barracks";210;2
"Unit";"Marine";"Barracks";210;1
"Unit";"Marine";"Barracks";210;1
"Building";"StarportReactor";NA;203;0
"Unit";"Liberator";"Starport";203;3
"Unit";"Medivac";"Starport";210;2
"Unit";"Liberator";"Starport";203;3
"Unit";"Medivac";"Starport";210;2
"Unit";"Marauder";"Barracks";210;2
"Unit";"Marauder";"Barracks";210;2
"Unit";"Raven";"Starport";210;2
"Unit";"Marauder";"Barracks";216;2
"Unit";"Liberator";"Starport";230;3
"Unit";"Marauder";"Barracks";238;2
"Upgrade";"TerranInfantryArmorsLevel3";"EngineeringBay";203;0
"Unit";"Marine";"Barracks";243;1
"Unit";"Marine";"Barracks";243;1
"Unit";"Marine";"Barracks";243;1
"Unit";"Marine";"Barracks";243;1
"Unit";"Marine";"Barracks";243;1
"Unit";"Marine";"Barracks";243;1
"Unit";"Marine";"Barracks";243;1
"Unit";"Marine";"Barracks";243;1
