"type";"unit_name";"on_building";"total_supply_lag";"supply"
"Building";"Refinery";NA;15;0
"Building";"Barracks";NA;16;0
"Unit";"Reaper";"Barracks";19;1
"Building";"CommandCenter";NA;20;0
"Building";"Factory";NA;20;0
"Building";"BarracksReactor";NA;21;0
"Building";"Refinery";NA;22;0
"Building";"Starport";NA;24;0
"Unit";"Hellion";"Factory";24;2
"Unit";"Hellion";"Factory";26;2
"Building";"BarracksTechLab";NA;29;0
"Unit";"Medivac";"Starport";31;2
"Unit";"Marine";"Barracks";39;1
"Unit";"Marine";"Barracks";40;1
"Building";"Barracks";NA;43;0
"Building";"StarportTechLab";NA;44;0
"Unit";"Marine";"Barracks";44;1
"Unit";"Marine";"Barracks";45;1
"Building";"Bunker";NA;47;0
"Unit";"Marine";"Barracks";51;1
"Building";"StarportReactor";NA;52;0
"Building";"CommandCenter";NA;53;0
"Unit";"Marine";"Barracks";54;1
"Building";"Refinery";NA;56;0
"Building";"Refinery";NA;56;0
"Building";"EngineeringBay";NA;56;0
"Unit";"Marine";"Barracks";56;1
"Unit";"Marine";"Barracks";57;1
"Unit";"Marine";"Barracks";60;1
"Unit";"Marine";"Barracks";63;1
"Unit";"Marine";"Barracks";64;1
"Unit";"Marine";"Barracks";65;1
"Unit";"Medivac";"Starport";66;2
"Upgrade";"Stimpack";"TechLab";68;0
"Building";"Barracks";NA;68;0
"Unit";"Marine";"Barracks";70;1
"Unit";"Marine";"Barracks";71;1
"Unit";"Medivac";"Starport";72;2
"Building";"Barracks";NA;74;0
"Building";"Barracks";NA;74;0
"Upgrade";"TerranInfantryWeaponsLevel1";"EngineeringBay";76;0
"Unit";"Marine";"Barracks";76;1
"Unit";"Marine";"Barracks";77;1
"Unit";"Marine";"Barracks";78;1
"Unit";"Medivac";"Starport";81;2
"Unit";"Marine";"Barracks";83;1
"Unit";"Medivac";"Starport";86;2
"Unit";"Marine";"Barracks";88;1
"Unit";"Marine";"Barracks";89;1
"Unit";"Marine";"Barracks";90;1
"Unit";"Marine";"Barracks";93;1
"Unit";"Marine";"Barracks";94;1
"Unit";"Marine";"Barracks";95;1
"Unit";"Marine";"Barracks";96;1
"Unit";"Medivac";"Starport";99;2
"Unit";"Marine";"Barracks";101;1
"Building";"Armory";NA;102;0
"Building";"EngineeringBay";NA;102;0
"Unit";"Marine";"Barracks";102;1
"Building";"FactoryReactor";NA;108;0
"Building";"BarracksTechLab";NA;108;0
"Building";"BarracksTechLab";NA;108;0
"Unit";"Marauder";"Barracks";108;2
"Unit";"Marine";"Barracks";110;1
"Unit";"Marine";"Barracks";111;1
"Building";"MissileTurret";NA;112;0
"Unit";"Marauder";"Barracks";115;2
"Unit";"Marine";"Barracks";119;1
"Unit";"Marine";"Barracks";120;1
"Unit";"Marine";"Barracks";121;1
"Unit";"Medivac";"Starport";123;2
"Unit";"Medivac";"Starport";125;2
"Unit";"Marauder";"Barracks";127;2
"Unit";"Marine";"Barracks";129;1
"Unit";"Marine";"Barracks";131;1
"Building";"Refinery";NA;134;0
"Unit";"Marine";"Barracks";134;1
"Unit";"Marine";"Barracks";135;1
"Unit";"Marauder";"Barracks";136;2
"Unit";"Marauder";"Barracks";139;2
"Building";"BarracksReactor";NA;142;0
"Unit";"Marauder";"Barracks";143;2
"Unit";"Marauder";"Barracks";145;2
"Upgrade";"TerranInfantryWeaponsLevel2";"EngineeringBay";148;0
"Unit";"Marine";"Barracks";148;1
"Unit";"Marine";"Barracks";149;1
"Unit";"Marauder";"Barracks";150;2
"Building";"Refinery";NA;155;0
"Unit";"Marauder";"Barracks";155;2
"Unit";"Marine";"Barracks";157;1
"Unit";"Medivac";"Starport";158;2
"Building";"MissileTurret";NA;160;0
"Building";"MissileTurret";NA;160;0
"Unit";"Marine";"Barracks";160;1
"Unit";"Marine";"Barracks";161;1
"Unit";"Marauder";"Barracks";162;2
"Unit";"Marine";"Barracks";164;1
"Unit";"Marine";"Barracks";165;1
"Unit";"Medivac";"Starport";166;2
"Unit";"Marine";"Barracks";171;1
"Unit";"Marauder";"Barracks";172;2
"Building";"Starport";NA;174;0
"Building";"FusionCore";NA;174;0
"Unit";"Marine";"Barracks";174;1
"Unit";"Marauder";"Barracks";175;2
"Unit";"Marauder";"Barracks";177;2
"Unit";"Marine";"Barracks";179;1
"Unit";"Marine";"Barracks";180;1
"Unit";"Marine";"Barracks";181;1
"Unit";"Marine";"Barracks";182;1
"Unit";"Marine";"Barracks";183;1
"Unit";"Liberator";"Starport";184;3
"Unit";"Marine";"Barracks";187;1
"Unit";"Marine";"Barracks";188;1
"Unit";"Marine";"Barracks";189;1
"Unit";"Marine";"Barracks";190;1
"Unit";"Marine";"Barracks";191;1
"Unit";"Liberator";"Starport";192;3
"Unit";"Marine";"Barracks";195;1
"Unit";"Marine";"Barracks";196;1
"Unit";"Marine";"Barracks";197;1
"Unit";"Marine";"Barracks";198;1
"Unit";"Marine";"Barracks";199;1
"Unit";"Marine";"Barracks";200;1
"Unit";"Marine";"Barracks";201;1
"Unit";"Marine";"Barracks";202;1
"Unit";"Marine";"Barracks";203;1
"Unit";"Marine";"Barracks";204;1
"Unit";"Marine";"Barracks";205;1
"Unit";"Marine";"Barracks";206;1
"Unit";"Marine";"Barracks";207;1
"Unit";"Marine";"Barracks";208;1
"Unit";"Marine";"Barracks";209;1
"Unit";"Marine";"Barracks";210;1
"Unit";"Marine";"Barracks";211;1
"Unit";"Marine";"Barracks";212;1
"Unit";"Marine";"Barracks";213;1
"Unit";"Marine";"Barracks";214;1
"Unit";"Marine";"Barracks";215;1
"Unit";"Marine";"Barracks";216;1
"Unit";"Marine";"Barracks";217;1
"Unit";"Marine";"Barracks";218;1
"Unit";"Marine";"Barracks";219;1
"Unit";"Marine";"Barracks";220;1
"Unit";"Marine";"Barracks";221;1
"Unit";"Marauder";"Barracks";222;2
"Unit";"Marine";"Barracks";224;1
"Unit";"Marine";"Barracks";225;1
"Unit";"Marine";"Barracks";226;1
"Unit";"Marine";"Barracks";227;1
"Unit";"Marine";"Barracks";228;1
"Unit";"Marine";"Barracks";229;1
"Unit";"Marine";"Barracks";230;1
"Unit";"Marine";"Barracks";231;1
"Unit";"Marine";"Barracks";232;1
"Unit";"Marine";"Barracks";233;1
"Unit";"Marine";"Barracks";234;1
"Unit";"Marine";"Barracks";235;1
"Unit";"Marine";"Barracks";236;1
"Unit";"Marine";"Barracks";237;1
"Upgrade";"SprayTerran";NA;238;0
"Upgrade";"SprayTerran";NA;238;0
"Upgrade";"SprayTerran";NA;238;0
"Upgrade";"SprayTerran";NA;238;0
"Upgrade";"ShieldWall";NA;238;0
"Upgrade";"TerranInfantryArmorsLevel1";NA;238;0
