"type";"unit_name";"on_building";"total_supply";"supply"
"Building";"Refinery";NA;14;0
"Building";"Refinery";NA;14;0
"Building";"Barracks";NA;14;0
"Unit";"Reaper";"Barracks";17;1
"Building";"Factory";NA;17;0
"Building";"Starport";NA;20;0
"Unit";"Cyclone";"Factory";21;3
"Building";"StarportTechLab";NA;23;0
"Unit";"Cyclone";"Factory";27;3
"Building";"BarracksReactor";NA;26;0
"Unit";"Banshee";"Starport";27;3
"Unit";"Marine";"Barracks";32;1
"Building";"Barracks";NA;28;0
"Unit";"Marine";"Barracks";32;1
"Building";"Barracks";NA;32;0
"Unit";"Cyclone";"Factory";35;3
"Unit";"Banshee";"Starport";32;3
"Unit";"Marine";"Barracks";42;1
"Unit";"Marine";"Barracks";42;1
"Unit";"Marine";"Barracks";42;1
"Building";"BarracksTechLab";NA;42;0
"Unit";"Cyclone";"Factory";42;3
"Unit";"Marine";"Barracks";49;1
"Unit";"Marine";"Barracks";49;1
"Unit";"Marine";"Barracks";49;1
"Unit";"Marine";"Barracks";49;1
"Unit";"Marine";"Barracks";52;1
"Unit";"Marine";"Barracks";53;1
"Unit";"Marine";"Barracks";54;1
"Unit";"Marine";"Barracks";56;1
"Unit";"Marine";"Barracks";56;1
"Unit";"Marine";"Barracks";57;1
"Unit";"Marine";"Barracks";59;1
"Unit";"Raven";"Starport";56;2
"Unit";"Marine";"Barracks";59;1
"Unit";"Marine";"Barracks";60;1
"Unit";"Marine";"Barracks";61;1
"Unit";"Marine";"Barracks";62;1
"Unit";"Cyclone";"Factory";62;3
"Unit";"Marine";"Barracks";65;1
"Unit";"Marine";"Barracks";66;1
"Unit";"Marine";"Barracks";67;1
"Unit";"Marine";"Barracks";68;1
"Unit";"Marine";"Barracks";72;1
"Unit";"Marine";"Barracks";73;1
"Unit";"Marine";"Barracks";74;1
"Unit";"Marine";"Barracks";75;1
"Unit";"Marine";"Barracks";77;1
"Unit";"Marine";"Barracks";77;1
