"Type";"UnitName";"OnBuilding";"TotalSupply";"Supply"
"Unit";"SCV";"Command Center";12;1
"Unit";"SCV";"Command Center";12;1
"Unit";"SCV";"Command Center";13;1
"Building";"SupplyDepot";NA;13;0
"Unit";"SCV";"Command Center";15;1
"Unit";"SCV";"Command Center";15;1
"Building";"Refinery";NA;15;0
"Unit";"SCV";"Command Center";16;1
"Unit";"SCV";"Command Center";17;1
"Building";"Barracks";NA;15;0
"Unit";"Reaper";"Barracks";19;1
"Unit";"SCV";"Command Center";19;1
"Unit";"SCV";"Command Center";21;1
"Building";"SupplyDepot";NA;21;0
"Unit";"SCV";"Command Center";21;1
"Building";"Barracks";NA;19;0
"Building";"Refinery";NA;21;0
"Building";"BarracksReactor";NA;20;0
"Unit";"SCV";"Command Center";22;1
"Building";"CommandCenter";NA;19;0
"Unit";"SCV";"Command Center";24;1
"Building";"BarracksTechLab";NA;24;0
"Unit";"Marine";"Barracks";24;1
"Unit";"Marine";"Barracks";24;1
"Building";"Factory";NA;22;0
"Unit";"SCV";"Command Center";25;1
"Unit";"Marine";"Barracks";25;1
"Unit";"Marine";"Barracks";26;1
"Unit";"SCV";"Command Center";28;1
"Unit";"Marine";"Barracks";27;1
"Unit";"SCV";"Command Center";32;1
"Unit";"Marine";"Barracks";32;1
"Unit";"SCV";"Command Center";32;1
"Unit";"Marine";"Barracks";32;1
"Building";"Starport";NA;28;0
"Unit";"Marine";"Barracks";32;1
"Unit";"SCV";"Command Center";35;1
"Unit";"SCV";"Command Center";35;1
"Building";"FactoryReactor";NA;31;0
"Building";"SupplyDepot";NA;32;0
"Unit";"Marine";"Barracks";36;1
"Building";"EngineeringBay";NA;32;0
"Unit";"Marine";"Barracks";36;1
"Unit";"SCV";"Command Center";37;1
"Unit";"SCV";"Command Center";38;1
"Unit";"Marine";"Barracks";37;1
"Unit";"SCV";"Command Center";41;1
"Unit";"SCV";"Command Center";42;1
"Unit";"SCV";"Command Center";44;1
"Building";"MissileTurret";NA;44;0
"Unit";"Marine";"Barracks";44;1
"Building";"Bunker";NA;40;0
"Unit";"Marine";"Barracks";44;1
"Unit";"Marine";"Barracks";44;1
"Unit";"Medivac";"Starport";43;2
"Unit";"SCV";"Command Center";46;1
"Unit";"Medivac";"Starport";43;2
"Building";"FactoryTechLab";NA;46;0
"Building";"SupplyDepot";NA;46;0
"Building";"SupplyDepot";NA;52;0
"Unit";"SCV";"Command Center";55;1
"Unit";"SCV";"Command Center";55;1
"Upgrade";"Stimpack";"TechLab";32;0
"Unit";"Marine";"Barracks";55;1
"Unit";"Marine";"Barracks";55;1
"Unit";"Marine";"Barracks";55;1
"Unit";"SCV";"Command Center";55;1
"Building";"SupplyDepot";NA;55;0
"Unit";"SCV";"Command Center";57;1
"Unit";"Marine";"Barracks";57;1
"Unit";"Marine";"Barracks";57;1
"Unit";"SCV";"Command Center";60;1
"Unit";"Marine";"Barracks";62;1
"Unit";"Marine";"Barracks";62;1
"Unit";"SCV";"Command Center";65;1
"Unit";"Marine";"Barracks";66;1
"Unit";"Marine";"Barracks";66;1
"Building";"SupplyDepot";NA;66;0
"Unit";"Marine";"Barracks";68;1
"Unit";"SCV";"Command Center";70;1
"Building";"SupplyDepot";NA;68;0
"Building";"SupplyDepot";NA;68;0
"Unit";"Medivac";"Starport";67;2
"Upgrade";"TerranInfantryWeaponsLevel1";"EngineeringBay";57;0
"Building";"Refinery";NA;66;0
"Unit";"SCV";"Command Center";74;1
"Unit";"SCV";"Command Center";74;1
"Unit";"Medivac";"Starport";70;2
"Unit";"Marine";"Barracks";74;1
"Unit";"SCV";"Command Center";74;1
"Unit";"SCV";"Command Center";75;1
"Building";"CommandCenter";NA;60;0
"Unit";"Marine";"Barracks";78;1
"Building";"SupplyDepot";NA;76;0
"Building";"SupplyDepot";NA;78;0
"Unit";"SCV";"Command Center";79;1
"Unit";"SCV";"Command Center";80;1
"Unit";"Marine";"Barracks";78;1
"Unit";"Marine";"Barracks";78;1
"Unit";"Marine";"Barracks";81;1
"Unit";"Marine";"Barracks";83;1
"Unit";"Marine";"Barracks";85;1
"Unit";"SCV";"Command Center";86;1
"Building";"Barracks";NA;74;0
"Unit";"SCV";"Command Center";87;1
"Unit";"Marine";"Barracks";86;1
"Unit";"SCV";"Command Center";89;1
"Unit";"Marine";"Barracks";87;1
"Unit";"Marine";"Barracks";88;1
"Unit";"SCV";"Command Center";90;1
"Unit";"SCV";"Command Center";92;1
"Unit";"Marine";"Barracks";91;1
"Unit";"SCV";"Command Center";95;1
"Unit";"Marine";"Barracks";93;1
"Unit";"Marine";"Barracks";94;1
"Building";"Refinery";NA;93;0
"Building";"Refinery";NA;93;0
"Building";"BarracksReactor";NA;91;0
"Unit";"SCV";"Command Center";99;1
"Unit";"SCV";"Command Center";99;1
"Unit";"SCV";"Command Center";99;1
"Building";"Barracks";NA;89;0
"Unit";"Marine";"Barracks";97;1
"Building";"Barracks";NA;89;0
"Unit";"Marine";"Barracks";99;1
"Unit";"Marine";"Barracks";100;1
"Unit";"SCV";"Command Center";101;1
"Unit";"SCV";"Command Center";104;1
"Unit";"SCV";"Command Center";104;1
"Unit";"Marine";"Barracks";104;1
"Building";"Refinery";NA;105;0
"Unit";"Marine";"Barracks";105;1
"Building";"SupplyDepot";NA;105;0
"Unit";"Marine";"Barracks";106;1
"Unit";"SCV";"Command Center";110;1
"Building";"SupplyDepot";NA;105;0
"Unit";"SCV";"Command Center";110;1
"Unit";"SCV";"Command Center";110;1
"Unit";"Marine";"Barracks";107;1
"Unit";"Marine";"Barracks";107;1
"Unit";"SCV";"Command Center";113;1
"Unit";"Marine";"Barracks";110;1
"Unit";"SCV";"Command Center";114;1
"Building";"BarracksReactor";NA;105;0
"Unit";"SCV";"Command Center";118;1
"Unit";"Marine";"Barracks";111;1
"Unit";"Marine";"Barracks";115;1
"Building";"Factory";NA;104;0
"Unit";"Marine";"Barracks";115;1
"Unit";"Marine";"Barracks";117;1
"Building";"BarracksReactor";NA;110;0
"Building";"SupplyDepot";NA;115;0
"Building";"SupplyDepot";NA;115;0
"Building";"MissileTurret";NA;118;0
"Unit";"Marine";"Barracks";119;1
"Unit";"SCV";"Command Center";124;1
"Unit";"SCV";"Command Center";124;1
"Unit";"SCV";"Command Center";124;1
"Unit";"Marine";"Barracks";121;1
"Unit";"Marine";"Barracks";121;1
"Unit";"Marine";"Barracks";122;1
"Unit";"Marine";"Barracks";123;1
"Unit";"Medivac";"Starport";118;2
"Unit";"Medivac";"Starport";118;2
"Unit";"Marine";"Barracks";124;1
"Unit";"Marine";"Barracks";125;1
"Building";"Factory";NA;111;0
"Upgrade";"TerranInfantryArmorsLevel1";"EngineeringBay";99;0
"Unit";"Marine";"Barracks";126;1
"Unit";"Marine";"Barracks";126;1
"Unit";"SCV";"Command Center";132;1
"Unit";"Marine";"Barracks";126;1
"Unit";"Marine";"Barracks";130;1
"Unit";"Marine";"Barracks";131;1
"Unit";"Marine";"Barracks";132;1
"Building";"SensorTower";NA;133;0
"Unit";"Marine";"Barracks";133;1
"Unit";"Marine";"Barracks";138;1
"Unit";"Marine";"Barracks";139;1
"Unit";"Marine";"Barracks";140;1
"Unit";"Marine";"Barracks";141;1
"Unit";"Marine";"Barracks";143;1
"Unit";"Marine";"Barracks";144;1
"Unit";"Marine";"Barracks";145;1
"Unit";"Marine";"Barracks";148;1
"Unit";"Marine";"Barracks";150;1
"Unit";"Marine";"Barracks";150;1
"Unit";"Marine";"Barracks";150;1
"Building";"FactoryTechLab";NA;150;0
"Building";"FactoryTechLab";NA;150;0
"Unit";"Marine";"Barracks";150;1
"Unit";"Marine";"Barracks";151;1
"Unit";"Marine";"Barracks";152;1
"Unit";"Marine";"Barracks";155;1
"Unit";"Marine";"Barracks";155;1
"Unit";"Marine";"Barracks";155;1
"Unit";"Marine";"Barracks";156;1
"Unit";"Marine";"Barracks";157;1
"Unit";"Marine";"Barracks";158;1
"Unit";"Marine";"Barracks";159;1
"Unit";"Medivac";"Starport";155;2
"Unit";"Medivac";"Starport";155;2
"Unit";"Marine";"Barracks";162;1
"Unit";"Marine";"Barracks";162;1
"Building";"EngineeringBay";NA;161;0
"Unit";"Marine";"Barracks";164;1
"Unit";"Marine";"Barracks";168;1
"Unit";"Marine";"Barracks";168;1
"Unit";"Marine";"Barracks";173;1
"Building";"SupplyDepot";NA;169;0
"Building";"SupplyDepot";NA;169;0
"Building";"SupplyDepot";NA;169;0
"Building";"Armory";NA;162;0
"Unit";"Medivac";"Starport";169;2
"Unit";"Medivac";"Starport";171;2
"Unit";"Marine";"Barracks";179;1
"Unit";"Marine";"Barracks";179;1
"Unit";"Marine";"Barracks";179;1
"Unit";"SCV";"Command Center";183;1
"Unit";"Medivac";"Starport";179;2
"Unit";"Medivac";"Starport";181;2
"Unit";"Marine";"Barracks";187;1
"Unit";"Marine";"Barracks";187;1
"Unit";"Marine";"Barracks";187;1
"Unit";"Marine";"Barracks";187;1
"Unit";"Marine";"Barracks";187;1
"Unit";"Marine";"Barracks";196;1
"Unit";"Marine";"Barracks";196;1
"Unit";"Marine";"Barracks";196;1
"Unit";"Medivac";"Starport";187;2
"Unit";"Medivac";"Starport";189;2
"Unit";"Marine";"Barracks";196;1
"Building";"CommandCenter";NA;183;0
"Unit";"Marine";"Barracks";204;1
"Unit";"Marine";"Barracks";204;1
"Unit";"Marine";"Barracks";204;1
"Unit";"Marine";"Barracks";204;1
"Unit";"Marine";"Barracks";204;1
"Unit";"Marine";"Barracks";204;1
"Unit";"Medivac";"Starport";204;2
"Building";"SensorTower";NA;204;0
"Building";"MissileTurret";NA;204;0
"Unit";"Marine";"Barracks";210;1
"Unit";"Marine";"Barracks";210;1
"Unit";"Marine";"Barracks";210;1
"Unit";"Marine";"Barracks";210;1
"Unit";"Marine";"Barracks";210;1
"Unit";"Marine";"Barracks";210;1
"Unit";"Marine";"Barracks";210;1
"Unit";"Marine";"Barracks";210;1
"Unit";"Marine";"Barracks";210;1
"Unit";"Marine";"Barracks";212;1
"Unit";"Marine";"Barracks";213;1
"Unit";"Marine";"Barracks";214;1
"Unit";"Marine";"Barracks";215;1
"Unit";"Marine";"Barracks";216;1
"Unit";"Marine";"Barracks";217;1
"Unit";"Marine";"Barracks";218;1
"Unit";"Marine";"Barracks";219;1
"Unit";"Marine";"Barracks";220;1
"Unit";"Medivac";"Starport";212;2
"Unit";"Marine";"Barracks";221;1
"Unit";"Marine";"Barracks";222;1
"Unit";"Marine";"Barracks";223;1
"Unit";"Marine";"Barracks";224;1
"Unit";"Marine";"Barracks";225;1
"Unit";"Marine";"Barracks";226;1
"Unit";"Medivac";"Starport";221;2
"Unit";"Marine";"Barracks";232;1
"Unit";"Marine";"Barracks";232;1
"Unit";"Marine";"Barracks";232;1
"Unit";"Medivac";"Starport";230;2
"Unit";"Marine";"Barracks";232;1
"Unit";"Marine";"Barracks";233;1
"Building";"Barracks";NA;221;0
"Building";"Barracks";NA;221;0
"Building";"Barracks";NA;221;0
"Unit";"Marine";"Barracks";238;1
"Unit";"Marine";"Barracks";238;1
"Unit";"Marine";"Barracks";238;1
"Unit";"Marine";"Barracks";238;1
