"Type";"UnitName";"OnBuilding";"TotalSupply";"Supply"
"Unit";"SCV";"Command Center";12;1
"Unit";"SCV";"Command Center";12;1
"Unit";"SCV";"Command Center";13;1
"Building";"SupplyDepot";NA;13;0
"Unit";"SCV";"Command Center";15;1
"Unit";"SCV";"Command Center";15;1
"Building";"Refinery";NA;15;0
"Unit";"SCV";"Command Center";16;1
"Unit";"SCV";"Command Center";17;1
"Building";"Barracks";NA;15;0
"Unit";"Reaper";"Barracks";19;1
"Unit";"SCV";"Command Center";19;1
"Building";"SupplyDepot";NA;19;0
"Unit";"SCV";"Command Center";21;1
"Unit";"SCV";"Command Center";21;1
"Building";"BarracksReactor";NA;20;0
"Unit";"SCV";"Command Center";22;1
"Building";"CommandCenter";NA;19;0
"Unit";"SCV";"Command Center";23;1
"Building";"Barracks";NA;21;0
"Unit";"Marine";"Barracks";24;1
"Unit";"Marine";"Barracks";24;1
"Unit";"SCV";"Command Center";24;1
"Building";"Barracks";NA;22;0
"Unit";"SCV";"Command Center";27;1
"Building";"BarracksTechLab";NA;25;0
"Unit";"Marine";"Barracks";25;1
"Unit";"Marine";"Barracks";26;1
"Unit";"SCV";"Command Center";28;1
"Unit";"SCV";"Command Center";28;1
"Building";"BarracksTechLab";NA;28;0
"Unit";"Marine";"Barracks";31;1
"Unit";"Marine";"Barracks";31;1
"Unit";"Marine";"Barracks";31;1
"Unit";"SCV";"Command Center";31;1
"Unit";"SCV";"Command Center";32;1
"Building";"Refinery";NA;31;0
"Building";"Factory";NA;28;0
"Unit";"SCV";"Command Center";36;1
"Unit";"SCV";"Command Center";37;1
"Unit";"Marine";"Barracks";33;1
"Unit";"Marine";"Barracks";33;1
"Unit";"SCV";"Command Center";38;1
"Unit";"SCV";"Command Center";39;1
"Unit";"Marine";"Barracks";38;1
"Unit";"Marine";"Barracks";38;1
"Unit";"Marine";"Barracks";40;1
"Unit";"SCV";"Command Center";42;1
"Unit";"SCV";"Command Center";43;1
"Unit";"Marine";"Barracks";42;1
"Building";"SupplyDepot";NA;42;0
"Unit";"Marine";"Barracks";44;1
"Unit";"SCV";"Command Center";47;1
"Unit";"SCV";"Command Center";48;1
"Building";"Refinery";NA;46;0
"Building";"Starport";NA;41;0
"Unit";"Marine";"Barracks";47;1
"Unit";"Marine";"Barracks";47;1
"Building";"SupplyDepot";NA;49;0
"Unit";"SCV";"Command Center";51;1
"Unit";"SCV";"Command Center";52;1
"Unit";"Marine";"Barracks";51;1
"Unit";"Marine";"Barracks";51;1
"Building";"FactoryReactor";NA;47;0
"Unit";"Marine";"Barracks";53;1
"Unit";"Marine";"Barracks";54;1
"Unit";"SCV";"Command Center";55;1
"Unit";"SCV";"Command Center";56;1
"Unit";"SCV";"Command Center";61;1
"Unit";"SCV";"Command Center";62;1
"Building";"SupplyDepot";NA;63;0
"Building";"Refinery";NA;63;0
"Unit";"Marauder";"Barracks";63;2
"Upgrade";"Stimpack";"TechLab";41;0
"Unit";"Medivac";"Starport";63;2
"Unit";"Medivac";"Starport";63;2
"Unit";"SCV";"Command Center";65;1
"Unit";"SCV";"Command Center";65;1
"Building";"SupplyDepot";NA;65;0
"Building";"FactoryReactor";NA;63;0
"Building";"SupplyDepot";NA;65;0
"Unit";"Marine";"Barracks";65;1
"Unit";"Marine";"Barracks";65;1
"Unit";"Marauder";"Barracks";65;2
"Building";"SupplyDepot";NA;65;0
"Building";"SupplyDepot";NA;65;0
"Unit";"Marauder";"Barracks";67;2
"Unit";"Medivac";"Starport";73;2
"Unit";"Medivac";"Starport";73;2
"Unit";"Marine";"Barracks";79;1
"Unit";"Marine";"Barracks";79;1
"Unit";"Marauder";"Barracks";79;2
"Unit";"Marauder";"Barracks";79;2
"Building";"Barracks";NA;79;0
"Building";"Barracks";NA;79;0
"Unit";"Marine";"Barracks";89;1
"Unit";"Marine";"Barracks";89;1
"Unit";"Marauder";"Barracks";87;2
"Unit";"Medivac";"Starport";83;2
"Unit";"Medivac";"Starport";83;2
"Building";"CommandCenter";NA;77;0
"Unit";"Marauder";"Barracks";89;2
"Unit";"Marine";"Barracks";89;1
"Unit";"Marine";"Barracks";90;1
"Unit";"SCV";"Command Center";93;1
"Unit";"SCV";"Command Center";95;1
"Building";"BarracksTechLab";NA;93;0
"Unit";"Marauder";"Barracks";91;2
"Unit";"Marine";"Barracks";99;1
"Unit";"Marine";"Barracks";100;1
"Unit";"Marauder";"Barracks";97;2
"Building";"BarracksReactor";NA;93;0
"Unit";"Marauder";"Barracks";103;2
"Unit";"Marine";"Barracks";107;1
"Unit";"Marine";"Barracks";109;1
"Unit";"Marauder";"Barracks";107;2
"Unit";"Marauder";"Barracks";107;2
"Unit";"Liberator";"Starport";99;3
"Unit";"SCV";"Command Center";111;1
"Unit";"Liberator";"Starport";99;3
"Unit";"SCV";"Command Center";111;1
"Unit";"SCV";"Command Center";111;1
"Unit";"Marine";"Barracks";109;1
"Unit";"Marine";"Barracks";109;1
"Unit";"Marauder";"Barracks";109;2
"Unit";"Marine";"Barracks";111;1
"Unit";"SCV";"Command Center";120;1
"Unit";"SCV";"Command Center";124;1
"Unit";"Marine";"Barracks";112;1
"Unit";"Marauder";"Barracks";113;2
"Unit";"Marauder";"Barracks";115;2
"Unit";"Marine";"Barracks";128;1
"Unit";"Marine";"Barracks";128;1
"Building";"Refinery";NA;128;0
"Unit";"Marauder";"Barracks";128;2
"Unit";"Marine";"Barracks";130;1
"Building";"SupplyDepot";NA;133;0
"Building";"SupplyDepot";NA;134;0
"Building";"SupplyDepot";NA;134;0
"Unit";"Liberator";"Starport";117;3
"Unit";"Liberator";"Starport";128;3
"Unit";"Marine";"Barracks";143;1
"Unit";"Marine";"Barracks";143;1
"Unit";"Marine";"Barracks";143;1
"Unit";"Marine";"Barracks";143;1
"Unit";"Marauder";"Barracks";143;2
"Unit";"Marauder";"Barracks";143;2
"Unit";"Marauder";"Barracks";143;2
