"Type";"UnitName";"OnBuilding";"TotalSupply";"Supply"
"Unit";"SCV";"Command Center";12;1
"Unit";"SCV";"Command Center";12;1
"Unit";"SCV";"Command Center";13;1
"Building";"SupplyDepot";NA;13;0
"Unit";"SCV";"Command Center";15;1
"Unit";"SCV";"Command Center";15;1
"Building";"Refinery";NA;15;0
"Unit";"SCV";"Command Center";16;1
"Building";"Barracks";NA;15;0
"Unit";"SCV";"Command Center";17;1
"Building";"BarracksTechLab";NA;18;0
"Unit";"SCV";"Command Center";19;1
"Unit";"Marauder";"Barracks";19;2
"Unit";"SCV";"Command Center";19;1
"Building";"SupplyDepot";NA;19;0
"Unit";"SCV";"Command Center";23;1
"Unit";"Marauder";"Barracks";23;2
"Unit";"SCV";"Command Center";23;1
"Building";"CommandCenter";NA;19;0
"Unit";"SCV";"Command Center";26;1
"Building";"Barracks";NA;23;0
"Unit";"Marauder";"Barracks";26;2
"Unit";"SCV";"Command Center";28;1
"Unit";"SCV";"Command Center";30;1
"Building";"Barracks";NA;24;0
"Unit";"Marine";"Barracks";30;1
"Building";"Refinery";NA;28;0
"Unit";"SCV";"Command Center";31;1
"Unit";"SCV";"Command Center";31;1
"Unit";"Marine";"Barracks";31;1
"Unit";"Marine";"Barracks";32;1
"Unit";"SCV";"Command Center";33;1
"Unit";"SCV";"Command Center";34;1
"Unit";"SCV";"Command Center";37;1
"Unit";"SCV";"Command Center";38;1
"Unit";"Marine";"Barracks";38;1
"Unit";"Marine";"Barracks";38;1
"Unit";"Marine";"Barracks";38;1
"Building";"Factory";NA;31;0
"Unit";"SCV";"Command Center";39;1
"Unit";"SCV";"Command Center";40;1
"Unit";"SCV";"Command Center";44;1
"Unit";"Marine";"Barracks";43;1
"Unit";"SCV";"Command Center";45;1
"Upgrade";"Stimpack";"TechLab";28;0
"Building";"SupplyDepot";NA;45;0
"Unit";"SCV";"Command Center";46;1
"Building";"SupplyDepot";NA;46;0
"Building";"FactoryReactor";NA;44;0
"Building";"Starport";NA;44;0
"Building";"BarracksReactor";NA;44;0
"Building";"BarracksReactor";NA;44;0
"Unit";"SCV";"Command Center";49;1
"Unit";"SCV";"Command Center";49;1
"Building";"SupplyDepot";NA;49;0
"Unit";"Marine";"Barracks";49;1
"Building";"SupplyDepot";NA;49;0
"Building";"Refinery";NA;50;0
"Unit";"Marine";"Barracks";52;1
"Unit";"Marine";"Barracks";52;1
"Unit";"Marine";"Barracks";52;1
"Unit";"Marine";"Barracks";52;1
"Unit";"SCV";"Command Center";53;1
"Unit";"SCV";"Command Center";53;1
"Unit";"Marine";"Barracks";52;1
"Building";"SupplyDepot";NA;53;0
"Building";"SupplyDepot";NA;53;0
"Building";"Refinery";NA;53;0
"Unit";"Medivac";"Starport";53;2
"Unit";"Medivac";"Starport";53;2
"Building";"EngineeringBay";NA;55;0
"Unit";"SCV";"Command Center";64;1
"Unit";"SCV";"Command Center";64;1
"Unit";"Marine";"Barracks";64;1
"Unit";"Marine";"Barracks";64;1
"Unit";"Marine";"Barracks";64;1
"Unit";"Marine";"Barracks";64;1
"Unit";"Marine";"Barracks";64;1
"Unit";"SCV";"Command Center";64;1
"Unit";"SCV";"Command Center";66;1
"Unit";"Medivac";"Starport";64;2
"Unit";"Medivac";"Starport";64;2
"Unit";"SCV";"Command Center";71;1
"Unit";"Marine";"Barracks";70;1
"Unit";"Marine";"Barracks";70;1
"Unit";"Marine";"Barracks";70;1
"Unit";"Marine";"Barracks";70;1
"Unit";"Marine";"Barracks";70;1
"Unit";"SCV";"Command Center";72;1
"Unit";"SCV";"Command Center";77;1
"Building";"CommandCenter";NA;53;0
"Unit";"SCV";"Command Center";84;1
"Unit";"SCV";"Command Center";84;1
"Unit";"SCV";"Command Center";87;1
"Unit";"SCV";"Command Center";87;1
"Building";"Barracks";NA;84;0
"Unit";"Marine";"Barracks";87;1
"Unit";"Marine";"Barracks";87;1
"Unit";"Marine";"Barracks";87;1
"Unit";"Marine";"Barracks";87;1
"Building";"Barracks";NA;84;0
"Unit";"Marauder";"Barracks";87;2
"Unit";"SCV";"Command Center";87;1
"Unit";"SCV";"Command Center";88;1
"Unit";"Medivac";"Starport";87;2
"Unit";"Medivac";"Starport";87;2
"Building";"BarracksTechLab";NA;93;0
"Unit";"SCV";"Command Center";95;1
"Unit";"SCV";"Command Center";96;1
"Building";"EngineeringBay";NA;93;0
"Unit";"SCV";"Command Center";101;1
"Unit";"SCV";"Command Center";102;1
"Unit";"SCV";"Command Center";103;1
"Unit";"Marine";"Barracks";101;1
"Unit";"Marine";"Barracks";101;1
"Unit";"Marine";"Barracks";101;1
"Building";"FactoryReactor";NA;93;0
"Unit";"Marine";"Barracks";101;1
"Unit";"Marine";"Barracks";101;1
"Building";"BarracksReactor";NA;93;0
"Unit";"SCV";"Command Center";103;1
"Building";"Armory";NA;93;0
"Upgrade";"TerranInfantryWeaponsLevel1";"EngineeringBay";86;0
"Unit";"Marine";"Barracks";106;1
"Unit";"Marine";"Barracks";107;1
"Unit";"Marine";"Barracks";112;1
"Unit";"Marine";"Barracks";112;1
"Unit";"Marine";"Barracks";112;1
"Unit";"Marine";"Barracks";112;1
"Unit";"Marine";"Barracks";112;1
"Unit";"Marauder";"Barracks";112;2
"Unit";"Marine";"Barracks";114;1
"Unit";"Marine";"Barracks";114;1
"Unit";"Marine";"Barracks";114;1
"Unit";"Marine";"Barracks";121;1
"Unit";"Marine";"Barracks";123;1
"Unit";"Marine";"Barracks";123;1
"Unit";"Marine";"Barracks";123;1
"Building";"SupplyDepot";NA;123;0
"Unit";"Marauder";"Barracks";123;2
"Unit";"Liberator";"Starport";114;3
"Unit";"Marauder";"Barracks";123;2
"Unit";"Liberator";"Starport";114;3
"Building";"SupplyDepot";NA;123;0
"Building";"SupplyDepot";NA;124;0
"Unit";"Marine";"Barracks";138;1
"Unit";"Marine";"Barracks";138;1
"Unit";"Marine";"Barracks";138;1
"Unit";"Marine";"Barracks";138;1
"Unit";"Marine";"Barracks";138;1
"Unit";"Marauder";"Barracks";128;2
"Unit";"Marauder";"Barracks";133;2
"Unit";"Marine";"Barracks";138;1
"Unit";"SCV";"Command Center";147;1
"Unit";"SCV";"Command Center";147;1
"Unit";"Marine";"Barracks";138;1
"Unit";"SCV";"Command Center";147;1
"Unit";"Marine";"Barracks";139;1
"Unit";"Marauder";"Barracks";143;2
"Unit";"Marauder";"Barracks";145;2
"Unit";"Liberator";"Starport";138;3
"Unit";"Liberator";"Starport";138;3
"Unit";"SCV";"Command Center";148;1
"Unit";"SCV";"Command Center";149;1
"Unit";"Marine";"Barracks";153;1
"Unit";"Marine";"Barracks";153;1
"Unit";"Marine";"Barracks";153;1
"Unit";"Marine";"Barracks";153;1
"Unit";"Marine";"Barracks";153;1
"Unit";"Marine";"Barracks";153;1
"Building";"Refinery";NA;152;0
"Building";"Refinery";NA;153;0
"Unit";"Marauder";"Barracks";153;2
"Unit";"Marauder";"Barracks";165;2
"Unit";"Marine";"Barracks";165;1
"Unit";"Marine";"Barracks";166;1
"Unit";"Marine";"Barracks";167;1
"Unit";"Marine";"Barracks";168;1
"Unit";"Marine";"Barracks";171;1
"Unit";"Marine";"Barracks";171;1
"Building";"Factory";NA;152;0
"Building";"Barracks";NA;148;0
"Building";"Barracks";NA;148;0
"Building";"Barracks";NA;148;0
"Unit";"Marauder";"Barracks";171;2
"Unit";"Marine";"Barracks";175;1
"Unit";"Marine";"Barracks";176;1
"Unit";"Marine";"Barracks";177;1
"Unit";"Marine";"Barracks";178;1
"Unit";"Marauder";"Barracks";173;2
"Upgrade";"TerranInfantryArmorsLevel1";"EngineeringBay";138;0
"Building";"SupplyDepot";NA;181;0
"Building";"SupplyDepot";NA;181;0
"Building";"SupplyDepot";NA;181;0
"Unit";"Medivac";"Starport";173;2
"Unit";"Medivac";"Starport";173;2
"Building";"BarracksTechLab";NA;183;0
"Building";"BarracksTechLab";NA;183;0
"Unit";"Marine";"Barracks";183;1
"Building";"CommandCenter";NA;153;0
"Unit";"Marauder";"Barracks";183;2
"Unit";"Marine";"Barracks";189;1
"Upgrade";"TerranInfantryWeaponsLevel2";"EngineeringBay";138;0
"Unit";"Marauder";"Barracks";189;2
"Unit";"Marine";"Barracks";193;1
"Unit";"Marine";"Barracks";193;1
"Unit";"Marine";"Barracks";193;1
