"type";"unit_name";"on_building";"total_supply_lag";"supply"
"Unit";"Overlord";"Larva";13;0
"Building";"Extractor";NA;17;0
"Building";"SpawningPool";NA;17;0
"Building";"Hatchery";NA;20;0
"Unit";"Zergling";"Larva";20;1
"Unit";"Zergling";"Larva";21;1
"Unit";"Zergling";"Larva";22;1
"Unit";"Zergling";"Larva";23;1
"Unit";"Queen";"Hatchery";24;2
"Unit";"Overlord";"Larva";27;0
"Unit";"Zergling";"Larva";27;1
"Unit";"Zergling";"Larva";28;1
"Unit";"Zergling";"Larva";29;1
"Unit";"Zergling";"Larva";30;1
"Unit";"Zergling";"Larva";31;1
"Unit";"Zergling";"Larva";32;1
"Unit";"Queen";"Hatchery";33;2
"Unit";"Queen";"Hatchery";35;2
"Unit";"Overlord";"Larva";42;0
"Building";"CreepTumorQueen";NA;42;0
"Unit";"Queen";"Hatchery";42;2
"Unit";"Zergling";"Larva";44;1
"Unit";"Zergling";"Larva";45;1
"Unit";"Zergling";"Larva";46;1
"Unit";"Zergling";"Larva";47;1
"Unit";"Zergling";"Larva";48;1
"Unit";"Zergling";"Larva";49;1
"Unit";"Zergling";"Larva";50;1
"Unit";"Zergling";"Larva";51;1
"Unit";"Zergling";"Larva";52;1
"Unit";"Zergling";"Larva";53;1
"Building";"CreepTumor";NA;54;0
"Unit";"Zergling";"Larva";54;1
"Unit";"Zergling";"Larva";55;1
"Unit";"Zergling";"Larva";56;1
"Unit";"Zergling";"Larva";57;1
"Building";"EvolutionChamber";NA;58;0
"Building";"CreepTumorQueen";NA;58;0
"Unit";"Queen";"Hatchery";58;2
"Unit";"Queen";"Hatchery";60;2
"Unit";"Overlord";"Larva";62;0
"Building";"CreepTumor";NA;62;0
"Building";"CreepTumorQueen";NA;62;0
"Building";"CreepTumorQueen";NA;67;0
"Unit";"Zergling";"Larva";67;1
"Unit";"Zergling";"Larva";68;1
"Unit";"Zergling";"Larva";69;1
"Unit";"Zergling";"Larva";70;1
"Building";"CreepTumor";NA;71;0
"Unit";"Overlord";"Larva";71;0
"Unit";"Overlord";"Larva";71;0
"Building";"CreepTumor";NA;71;0
"Building";"CreepTumor";NA;78;0
"Unit";"Queen";"Hatchery";78;2
"Building";"CreepTumor";NA;80;0
"Unit";"Overlord";"Larva";80;0
"Building";"CreepTumor";NA;80;0
"Building";"CreepTumor";NA;82;0
"Building";"RoachWarren";NA;82;0
"Building";"Extractor";NA;83;0
"Building";"Extractor";NA;83;0
"Building";"CreepTumor";NA;83;0
"Building";"CreepTumor";NA;83;0
"Unit";"Zergling";"Larva";89;1
"Unit";"Zergling";"Larva";90;1
"Unit";"Zergling";"Larva";91;1
"Unit";"Zergling";"Larva";92;1
"Unit";"Overlord";"Larva";93;0
"Unit";"Overlord";"Larva";93;0
"Unit";"Roach";"Larva";93;2
"Unit";"Roach";"Larva";95;2
"Unit";"Roach";"Larva";97;2
"Unit";"Roach";"Larva";99;2
"Unit";"Roach";"Larva";101;2
"Building";"CreepTumor";NA;103;0
"Unit";"Roach";"Larva";103;2
"Unit";"Roach";"Larva";105;2
"Unit";"Queen";"Hatchery";107;2
"Unit";"Queen";"Hatchery";109;2
"Unit";"Roach";"Larva";111;2
"Unit";"Roach";"Larva";113;2
"Unit";"Overlord";"Larva";115;0
"Unit";"Overlord";"Larva";115;0
"Building";"CreepTumorQueen";NA;115;0
"Building";"CreepTumorQueen";NA;119;0
"Building";"CreepTumor";NA;120;0
"Building";"CreepTumorQueen";NA;121;0
"Building";"CreepTumorQueen";NA;121;0
"Building";"CreepTumorQueen";NA;124;0
"Building";"Extractor";NA;124;0
"Unit";"Overlord";"Larva";124;0
"Unit";"Roach";"Larva";124;2
"Unit";"Roach";"Larva";126;2
"Building";"CreepTumor";NA;128;0
"Building";"CreepTumor";NA;128;0
"Building";"CreepTumor";NA;128;0
"Unit";"Overlord";"Larva";128;0
"Unit";"Roach";"Larva";128;2
"Unit";"Roach";"Larva";130;2
"Unit";"Roach";"Larva";132;2
"Unit";"Roach";"Larva";134;2
"Building";"Hatchery";NA;136;0
"Building";"CreepTumorQueen";NA;136;0
"Building";"CreepTumorQueen";NA;136;0
"Building";"CreepTumorQueen";NA;136;0
"Building";"CreepTumorQueen";NA;136;0
"Building";"CreepTumorQueen";NA;136;0
"Building";"CreepTumor";NA;140;0
"Building";"CreepTumorQueen";NA;140;0
"Building";"CreepTumor";NA;140;0
"Building";"CreepTumor";NA;140;0
"Unit";"Roach";"Larva";140;2
"Unit";"Roach";"Larva";142;2
"Building";"InfestationPit";NA;144;0
"Building";"CreepTumor";NA;148;0
"Building";"CreepTumor";NA;148;0
"Building";"CreepTumor";NA;148;0
"Building";"CreepTumor";NA;148;0
"Building";"CreepTumor";NA;148;0
"Building";"CreepTumor";NA;148;0
"Upgrade";"GlialReconstitution";"RoachWarren";149;0
"Building";"EvolutionChamber";NA;154;0
"Building";"CreepTumorQueen";NA;154;0
"Building";"CreepTumorQueen";NA;154;0
"Building";"CreepTumorQueen";NA;154;0
"Unit";"Roach";"Larva";154;2
"Unit";"Roach";"Larva";156;2
"Unit";"Roach";"Larva";158;2
"Building";"CreepTumor";NA;160;0
"Building";"CreepTumor";NA;160;0
"Unit";"Overlord";"Larva";160;0
"Unit";"Overlord";"Larva";160;0
"Building";"CreepTumor";NA;160;0
"Building";"CreepTumor";NA;160;0
"Unit";"Overlord";"Larva";160;0
"Unit";"Roach";"Larva";160;2
"Unit";"Roach";"Larva";162;2
"Unit";"Roach";"Larva";164;2
"Unit";"Overlord";"Larva";166;0
"Building";"Extractor";NA;171;0
"Building";"Extractor";NA;171;0
"Building";"CreepTumor";NA;171;0
"Building";"CreepTumor";NA;171;0
"Unit";"Queen";"Hatchery";171;2
"Unit";"Overlord";"Larva";173;0
"Building";"CreepTumor";NA;173;0
"Building";"CreepTumor";NA;173;0
"Building";"CreepTumor";NA;173;0
"Building";"CreepTumor";NA;173;0
"Unit";"Overlord";"Larva";173;0
"Unit";"Infestor";"Larva";173;2
"Unit";"Infestor";"Larva";178;2
"Unit";"Roach";"Larva";180;2
"Upgrade";"Burrow";"Hatchery";182;0
"Unit";"Roach";"Larva";184;2
"Unit";"Roach";"Larva";186;2
"Unit";"Roach";"Larva";188;2
"Building";"CreepTumor";NA;190;0
"Building";"CreepTumor";NA;190;0
"Building";"CreepTumor";NA;190;0
"Unit";"Infestor";"Larva";190;2
"Unit";"Roach";"Larva";192;2
"Unit";"Roach";"Larva";194;2
"Unit";"Roach";"Larva";196;2
"Unit";"Roach";"Larva";198;2
"Unit";"Roach";"Larva";200;2
"Building";"CreepTumorQueen";NA;202;0
"Building";"CreepTumorQueen";NA;202;0
"Building";"Hatchery";NA;202;0
"Unit";"Roach";"Larva";202;2
"Building";"Spire";NA;204;0
"Unit";"Roach";"Larva";204;2
"Unit";"Roach";"Larva";206;2
"Unit";"Roach";"Larva";208;2
"Building";"CreepTumorQueen";NA;210;0
"Building";"CreepTumorQueen";NA;210;0
"Building";"CreepTumor";NA;210;0
"Unit";"Roach";"Larva";210;2
"Unit";"Roach";"Larva";212;2
"Unit";"Roach";"Larva";214;2
"Unit";"Roach";"Larva";216;2
"Unit";"Overlord";"Larva";218;0
"Unit";"Overlord";"Larva";218;0
"Unit";"Overlord";"Larva";218;0
"Building";"CreepTumor";NA;218;0
"Building";"CreepTumor";NA;218;0
"Building";"CreepTumor";NA;218;0
"Building";"CreepTumor";NA;218;0
"Building";"CreepTumor";NA;218;0
"Building";"CreepTumor";NA;218;0
"Building";"SporeCrawler";NA;218;0
"Building";"SporeCrawler";NA;218;0
"Building";"Extractor";NA;218;0
"Unit";"Infestor";"Larva";218;2
"Unit";"Infestor";"Larva";220;2
"Unit";"Overlord";"Larva";222;0
"Unit";"Overlord";"Larva";222;0
"Unit";"Overlord";"Larva";222;0
"Building";"CreepTumor";NA;222;0
"Building";"CreepTumor";NA;222;0
"Building";"CreepTumor";NA;222;0
"Building";"CreepTumorQueen";NA;222;0
"Building";"CreepTumorQueen";NA;222;0
"Building";"CreepTumorQueen";NA;232;0
"Building";"CreepTumor";NA;232;0
"Building";"CreepTumor";NA;232;0
"Building";"CreepTumor";NA;232;0
"Unit";"Roach";"Larva";232;2
"Unit";"Roach";"Larva";234;2
"Unit";"Roach";"Larva";236;2
"Unit";"Roach";"Larva";238;2
"Unit";"Roach";"Larva";240;2
"Unit";"Roach";"Larva";242;2
"Unit";"Roach";"Larva";244;2
"Unit";"Roach";"Larva";246;2
"Building";"CreepTumor";NA;263;0
"Building";"CreepTumor";NA;263;0
"Building";"CreepTumor";NA;263;0
"Building";"CreepTumor";NA;263;0
"Building";"CreepTumorQueen";NA;263;0
"Unit";"Corruptor";"Larva";263;2
"Unit";"Corruptor";"Larva";265;2
"Unit";"Corruptor";"Larva";267;2
"Unit";"Corruptor";"Larva";269;2
"Unit";"Corruptor";"Larva";271;2
"Building";"CreepTumor";NA;273;0
"Building";"SporeCrawler";NA;273;0
"Building";"SpineCrawler";NA;273;0
"Building";"SpineCrawler";NA;273;0
"Building";"CreepTumor";NA;273;0
"Building";"CreepTumor";NA;273;0
"Building";"SpineCrawler";NA;273;0
"Building";"SpineCrawler";NA;273;0
"Building";"CreepTumor";NA;273;0
"Building";"CreepTumor";NA;273;0
"Building";"CreepTumor";NA;273;0
"Building";"CreepTumor";NA;273;0
"Building";"CreepTumor";NA;273;0
"Building";"Hatchery";NA;273;0
"Unit";"Corruptor";"Larva";273;2
"Unit";"Corruptor";"Larva";275;2
"Building";"CreepTumor";NA;277;0
"Building";"CreepTumor";NA;277;0
"Unit";"Corruptor";"Larva";277;2
"Building";"Extractor";NA;279;0
"Building";"Extractor";NA;279;0
"Building";"CreepTumorQueen";NA;279;0
"Building";"CreepTumorQueen";NA;279;0
"Building";"CreepTumorQueen";NA;279;0
"Building";"CreepTumorQueen";NA;279;0
"Building";"CreepTumor";NA;279;0
"Building";"CreepTumorQueen";NA;279;0
"Unit";"Corruptor";"Larva";279;2
"Unit";"Corruptor";"Larva";281;2
"Unit";"Corruptor";"Larva";283;2
"Unit";"Corruptor";"Larva";285;2
"Unit";"Roach";"Larva";287;2
"Building";"UltraliskCavern";NA;289;0
"Unit";"Corruptor";"Larva";289;2
"Unit";"Corruptor";"Larva";291;2
"Unit";"Corruptor";"Larva";293;2
"Unit";"Corruptor";"Larva";295;2
"Unit";"Corruptor";"Larva";297;2
"Unit";"Corruptor";"Larva";299;2
"Unit";"Corruptor";"Larva";301;2
"Unit";"Queen";"Hatchery";303;2
"Unit";"Queen";"Hatchery";305;2
"Unit";"Queen";"Hatchery";307;2
"Unit";"Queen";"Hatchery";309;2
"Unit";"Roach";"Larva";311;2
"Unit";"Roach";"Larva";313;2
"Unit";"Roach";"Larva";315;2
"Unit";"Roach";"Larva";317;2
"Unit";"Roach";"Larva";319;2
"Unit";"Roach";"Larva";321;2
"Unit";"Roach";"Larva";323;2
"Unit";"Roach";"Larva";325;2
"Unit";"Roach";"Larva";327;2
"Unit";"Roach";"Larva";329;2
"Unit";"Roach";"Larva";331;2
"Upgrade";"SprayZerg";NA;333;0
"Upgrade";"SprayZerg";NA;333;0
"Upgrade";"zerglingmovementspeed";NA;333;0
"Upgrade";"ZergGroundArmorsLevel1";NA;333;0
"Upgrade";"SprayZerg";NA;333;0
"Upgrade";"SprayZerg";NA;333;0
"Upgrade";"ZergMissileWeaponsLevel1";NA;333;0
"Upgrade";"SprayZerg";NA;333;0
"Upgrade";"SprayZerg";NA;333;0
"Upgrade";"InfestorEnergyUpgrade";NA;333;0
"Upgrade";"SprayZerg";NA;333;0
"Upgrade";"ZergGroundArmorsLevel2";NA;333;0
"Upgrade";"ZergMissileWeaponsLevel2";NA;333;0
"Upgrade";"SprayZerg";NA;333;0
"Upgrade";"SprayZerg";NA;333;0
"Upgrade";"SprayZerg";NA;333;0
"Upgrade";"ZergMeleeWeaponsLevel1";NA;333;0
"Upgrade";"SprayZerg";NA;333;0
"Upgrade";"ZergGroundArmorsLevel3";NA;333;0
