"type";"unit_name";"on_building";"total_supply_lag";"supply"
"Unit";"Overlord";"Larva";13;0
"Building";"SpawningPool";NA;17;0
"Building";"Hatchery";NA;18;0
"Building";"Extractor";NA;20;0
"Unit";"Queen";"Hatchery";21;2
"Unit";"Zergling";"Larva";23;1
"Unit";"Zergling";"Larva";24;1
"Unit";"Overlord";"Larva";25;0
"Unit";"Queen";"Hatchery";27;2
"Unit";"Queen";"Hatchery";30;2
"Unit";"Overlord";"Larva";35;0
"Unit";"Overlord";"Larva";35;0
"Unit";"Zergling";"Larva";35;1
"Unit";"Zergling";"Larva";36;1
"Unit";"Zergling";"Larva";37;1
"Unit";"Zergling";"Larva";38;1
"Unit";"Zergling";"Larva";39;1
"Unit";"Zergling";"Larva";40;1
"Unit";"Queen";"Hatchery";41;2
"Unit";"Overlord";"Larva";43;0
"Unit";"Zergling";"Larva";43;1
"Unit";"Zergling";"Larva";44;1
"Unit";"Zergling";"Larva";45;1
"Unit";"Zergling";"Larva";46;1
"Unit";"Queen";"Hatchery";47;2
"Building";"CreepTumorQueen";NA;49;0
"Unit";"Zergling";"Larva";49;1
"Unit";"Zergling";"Larva";50;1
"Unit";"Zergling";"Larva";51;1
"Unit";"Zergling";"Larva";52;1
"Unit";"Zergling";"Larva";53;1
"Unit";"Zergling";"Larva";54;1
"Unit";"Zergling";"Larva";55;1
"Unit";"Zergling";"Larva";56;1
"Unit";"Zergling";"Larva";57;1
"Unit";"Zergling";"Larva";58;1
"Unit";"Zergling";"Larva";59;1
"Unit";"Zergling";"Larva";60;1
"Unit";"Zergling";"Larva";61;1
"Unit";"Zergling";"Larva";62;1
"Unit";"Zergling";"Larva";63;1
"Unit";"Zergling";"Larva";64;1
"Unit";"Zergling";"Larva";65;1
"Unit";"Zergling";"Larva";66;1
"Unit";"Queen";"Hatchery";76;2
"Building";"CreepTumorQueen";NA;78;0
"Unit";"Zergling";"Larva";78;1
"Unit";"Zergling";"Larva";79;1
"Building";"CreepTumorQueen";NA;80;0
"Building";"Hatchery";NA;80;0
"Unit";"Zergling";"Larva";80;1
"Unit";"Zergling";"Larva";81;1
"Building";"CreepTumorQueen";NA;82;0
"Unit";"Zergling";"Larva";82;1
"Unit";"Zergling";"Larva";83;1
"Unit";"Zergling";"Larva";84;1
"Unit";"Zergling";"Larva";85;1
"Unit";"Zergling";"Larva";86;1
"Unit";"Zergling";"Larva";87;1
"Unit";"Zergling";"Larva";88;1
"Unit";"Zergling";"Larva";89;1
"Unit";"Zergling";"Larva";90;1
"Unit";"Zergling";"Larva";91;1
"Unit";"Zergling";"Larva";92;1
"Unit";"Zergling";"Larva";93;1
"Unit";"Zergling";"Larva";94;1
"Unit";"Zergling";"Larva";95;1
"Unit";"Zergling";"Larva";96;1
"Unit";"Zergling";"Larva";97;1
"Unit";"Zergling";"Larva";98;1
"Unit";"Zergling";"Larva";99;1
"Unit";"Zergling";"Larva";100;1
"Unit";"Zergling";"Larva";101;1
"Building";"CreepTumor";NA;102;0
"Building";"CreepTumor";NA;102;0
"Unit";"Queen";"Hatchery";102;2
"Building";"CreepTumorQueen";NA;104;0
"Unit";"Zergling";"Larva";104;1
"Unit";"Zergling";"Larva";105;1
"Unit";"Queen";"Hatchery";106;2
"Unit";"Zergling";"Larva";108;1
"Unit";"Zergling";"Larva";109;1
"Building";"CreepTumorQueen";NA;110;0
"Unit";"Zergling";"Larva";110;1
"Unit";"Zergling";"Larva";111;1
"Unit";"Zergling";"Larva";112;1
"Unit";"Zergling";"Larva";113;1
"Building";"CreepTumor";NA;114;0
"Unit";"Zergling";"Larva";114;1
"Unit";"Zergling";"Larva";115;1
"Unit";"Overlord";"Larva";116;0
"Unit";"Overlord";"Larva";116;0
"Building";"EvolutionChamber";NA;116;0
"Building";"EvolutionChamber";NA;116;0
"Unit";"Overlord";"Larva";116;0
"Building";"Extractor";NA;116;0
"Building";"Hatchery";NA;116;0
"Unit";"Zergling";"Larva";116;1
"Unit";"Zergling";"Larva";117;1
"Unit";"Zergling";"Larva";118;1
"Unit";"Zergling";"Larva";119;1
"Unit";"Zergling";"Larva";120;1
"Unit";"Zergling";"Larva";121;1
"Unit";"Zergling";"Larva";122;1
"Unit";"Zergling";"Larva";123;1
"Unit";"Zergling";"Larva";124;1
"Unit";"Zergling";"Larva";125;1
"Unit";"Zergling";"Larva";126;1
"Unit";"Zergling";"Larva";127;1
"Unit";"Zergling";"Larva";128;1
"Unit";"Zergling";"Larva";129;1
"Building";"CreepTumor";NA;134;0
"Building";"CreepTumorQueen";NA;134;0
"Building";"CreepTumorQueen";NA;134;0
"Building";"CreepTumor";NA;134;0
"Building";"CreepTumorQueen";NA;137;0
"Building";"CreepTumor";NA;153;0
"Unit";"Overlord";"Larva";157;0
"Unit";"Overlord";"Larva";159;0
"Building";"Extractor";NA;159;0
"Building";"Extractor";NA;161;0
"Building";"CreepTumor";NA;162;0
"Building";"CreepTumor";NA;162;0
"Building";"CreepTumor";NA;162;0
"Building";"CreepTumor";NA;162;0
"Building";"CreepTumor";NA;165;0
"Unit";"Overlord";"Larva";165;0
"Building";"BanelingNest";NA;167;0
"Building";"CreepTumorQueen";NA;168;0
"Building";"CreepTumorQueen";NA;168;0
"Unit";"Zergling";"Larva";172;1
"Unit";"Zergling";"Larva";173;1
"Unit";"Zergling";"Larva";174;1
"Unit";"Zergling";"Larva";175;1
"Unit";"Zergling";"Larva";176;1
"Unit";"Zergling";"Larva";177;1
"Unit";"Zergling";"Larva";178;1
"Unit";"Zergling";"Larva";179;1
"Unit";"Zergling";"Larva";180;1
"Unit";"Zergling";"Larva";181;1
"Unit";"Zergling";"Larva";182;1
"Unit";"Zergling";"Larva";183;1
"Unit";"Zergling";"Larva";184;1
"Unit";"Zergling";"Larva";185;1
"Unit";"Zergling";"Larva";186;1
"Unit";"Zergling";"Larva";187;1
"Building";"Extractor";NA;188;0
"Building";"CreepTumor";NA;188;0
"Building";"CreepTumor";NA;188;0
"Building";"CreepTumor";NA;188;0
"Unit";"Zergling";"Larva";188;1
"Unit";"Zergling";"Larva";189;1
"Building";"Hatchery";NA;190;0
"Building";"Spire";NA;190;0
"Building";"Extractor";NA;190;0
"Unit";"Zergling";"Larva";190;1
"Unit";"Zergling";"Larva";191;1
"Unit";"Zergling";"Larva";192;1
"Unit";"Zergling";"Larva";193;1
"Unit";"Zergling";"Larva";194;1
"Unit";"Zergling";"Larva";195;1
"Unit";"Zergling";"Larva";196;1
"Unit";"Zergling";"Larva";197;1
"Unit";"Zergling";"Larva";198;1
"Unit";"Zergling";"Larva";199;1
"Unit";"Zergling";"Larva";200;1
"Unit";"Zergling";"Larva";201;1
"Unit";"Zergling";"Larva";202;1
"Unit";"Zergling";"Larva";203;1
"Unit";"Zergling";"Larva";204;1
"Unit";"Zergling";"Larva";205;1
"Unit";"Zergling";"Larva";206;1
"Unit";"Zergling";"Larva";207;1
"Unit";"Zergling";"Larva";208;1
"Unit";"Zergling";"Larva";209;1
"Unit";"Zergling";"Larva";210;1
"Unit";"Zergling";"Larva";211;1
"Unit";"Zergling";"Larva";212;1
"Unit";"Zergling";"Larva";213;1
"Unit";"Zergling";"Larva";214;1
"Unit";"Zergling";"Larva";215;1
"Unit";"Zergling";"Larva";216;1
"Unit";"Zergling";"Larva";217;1
"Unit";"Zergling";"Larva";218;1
"Unit";"Zergling";"Larva";219;1
"Unit";"Zergling";"Larva";220;1
"Unit";"Zergling";"Larva";221;1
"Unit";"Zergling";"Larva";222;1
"Unit";"Zergling";"Larva";223;1
"Unit";"Zergling";"Larva";224;1
"Unit";"Zergling";"Larva";225;1
"Unit";"Zergling";"Larva";226;1
"Unit";"Zergling";"Larva";227;1
"Unit";"Zergling";"Larva";228;1
"Unit";"Zergling";"Larva";229;1
"Unit";"Zergling";"Larva";230;1
"Unit";"Zergling";"Larva";231;1
"Unit";"Overlord";"Larva";232;0
"Unit";"Overlord";"Larva";232;0
"Unit";"Overlord";"Larva";232;0
"Building";"CreepTumorQueen";NA;232;0
"Building";"CreepTumorQueen";NA;232;0
"Building";"CreepTumorQueen";NA;232;0
"Unit";"Overlord";"Larva";232;0
"Unit";"Overlord";"Larva";232;0
"Unit";"Overlord";"Larva";232;0
"Unit";"Zergling";"Larva";232;1
"Unit";"Zergling";"Larva";233;1
"Unit";"Zergling";"Larva";234;1
"Unit";"Zergling";"Larva";235;1
"Unit";"Zergling";"Larva";236;1
"Unit";"Zergling";"Larva";237;1
"Unit";"Zergling";"Larva";238;1
"Unit";"Zergling";"Larva";239;1
"Unit";"Zergling";"Larva";240;1
"Unit";"Zergling";"Larva";241;1
"Unit";"Zergling";"Larva";242;1
"Unit";"Zergling";"Larva";243;1
"Unit";"Zergling";"Larva";244;1
"Unit";"Zergling";"Larva";245;1
"Unit";"Zergling";"Larva";246;1
"Unit";"Zergling";"Larva";247;1
"Unit";"Zergling";"Larva";248;1
"Unit";"Zergling";"Larva";249;1
"Unit";"Zergling";"Larva";250;1
"Unit";"Zergling";"Larva";251;1
"Unit";"Zergling";"Larva";252;1
"Unit";"Zergling";"Larva";253;1
"Unit";"Zergling";"Larva";254;1
"Unit";"Zergling";"Larva";255;1
"Unit";"Zergling";"Larva";256;1
"Unit";"Zergling";"Larva";257;1
"Unit";"Zergling";"Larva";258;1
"Unit";"Zergling";"Larva";259;1
"Unit";"Zergling";"Larva";260;1
"Unit";"Zergling";"Larva";261;1
"Unit";"Mutalisk";"Larva";262;2
"Unit";"Mutalisk";"Larva";264;2
"Unit";"Mutalisk";"Larva";266;2
"Unit";"Mutalisk";"Larva";268;2
"Unit";"Mutalisk";"Larva";277;2
"Unit";"Mutalisk";"Larva";279;2
"Unit";"Mutalisk";"Larva";281;2
"Building";"CreepTumor";NA;283;0
"Building";"InfestationPit";NA;283;0
"Building";"CreepTumor";NA;283;0
"Building";"CreepTumor";NA;283;0
"Unit";"Mutalisk";"Larva";283;2
"Unit";"Zergling";"Larva";285;1
"Unit";"Zergling";"Larva";286;1
"Unit";"Zergling";"Larva";287;1
"Unit";"Zergling";"Larva";288;1
"Unit";"Zergling";"Larva";289;1
"Unit";"Zergling";"Larva";290;1
"Unit";"Zergling";"Larva";291;1
"Unit";"Zergling";"Larva";292;1
"Unit";"Zergling";"Larva";293;1
"Unit";"Zergling";"Larva";294;1
"Unit";"Zergling";"Larva";295;1
"Unit";"Zergling";"Larva";296;1
"Unit";"Zergling";"Larva";297;1
"Unit";"Zergling";"Larva";298;1
"Unit";"Zergling";"Larva";299;1
"Unit";"Zergling";"Larva";300;1
"Unit";"Zergling";"Larva";301;1
"Unit";"Zergling";"Larva";302;1
"Unit";"Zergling";"Larva";303;1
"Unit";"Zergling";"Larva";304;1
"Unit";"Zergling";"Larva";305;1
"Unit";"Zergling";"Larva";306;1
"Unit";"Zergling";"Larva";307;1
"Unit";"Zergling";"Larva";308;1
"Building";"CreepTumorQueen";NA;309;0
"Building";"CreepTumorQueen";NA;309;0
"Building";"CreepTumorQueen";NA;309;0
"Building";"Hatchery";NA;309;0
"Unit";"Mutalisk";"Larva";309;2
"Unit";"Mutalisk";"Larva";311;2
"Unit";"Mutalisk";"Larva";313;2
"Unit";"Mutalisk";"Larva";315;2
"Unit";"Mutalisk";"Larva";317;2
"Unit";"Mutalisk";"Larva";319;2
"Unit";"Zergling";"Larva";321;1
"Unit";"Zergling";"Larva";322;1
"Unit";"Zergling";"Larva";323;1
"Unit";"Zergling";"Larva";324;1
"Unit";"Zergling";"Larva";325;1
"Unit";"Zergling";"Larva";326;1
"Unit";"Zergling";"Larva";327;1
"Unit";"Zergling";"Larva";328;1
"Unit";"Zergling";"Larva";329;1
"Unit";"Zergling";"Larva";330;1
"Unit";"Zergling";"Larva";331;1
"Unit";"Zergling";"Larva";332;1
"Unit";"Zergling";"Larva";333;1
"Unit";"Zergling";"Larva";334;1
"Unit";"Zergling";"Larva";335;1
"Unit";"Zergling";"Larva";336;1
"Unit";"Zergling";"Larva";337;1
"Unit";"Zergling";"Larva";338;1
"Unit";"Zergling";"Larva";339;1
"Unit";"Zergling";"Larva";340;1
"Unit";"Zergling";"Larva";341;1
"Unit";"Zergling";"Larva";342;1
"Unit";"Zergling";"Larva";343;1
"Unit";"Zergling";"Larva";344;1
"Unit";"Zergling";"Larva";345;1
"Unit";"Zergling";"Larva";346;1
"Building";"CreepTumor";NA;347;0
"Building";"CreepTumor";NA;347;0
"Building";"CreepTumor";NA;347;0
"Building";"CreepTumor";NA;347;0
"Building";"CreepTumor";NA;347;0
"Building";"CreepTumorQueen";NA;347;0
"Building";"CreepTumor";NA;347;0
"Building";"CreepTumorQueen";NA;347;0
"Building";"CreepTumor";NA;347;0
"Unit";"Mutalisk";"Larva";347;2
"Unit";"Mutalisk";"Larva";349;2
"Unit";"Overlord";"Larva";351;0
"Unit";"Overlord";"Larva";351;0
"Unit";"Overlord";"Larva";351;0
"Building";"Hatchery";NA;351;0
"Unit";"Zergling";"Larva";351;1
"Unit";"Zergling";"Larva";352;1
"Unit";"Zergling";"Larva";353;1
"Unit";"Zergling";"Larva";354;1
"Unit";"Zergling";"Larva";355;1
"Unit";"Zergling";"Larva";356;1
"Unit";"Zergling";"Larva";357;1
"Unit";"Zergling";"Larva";358;1
"Unit";"Zergling";"Larva";359;1
"Unit";"Zergling";"Larva";360;1
"Unit";"Zergling";"Larva";361;1
"Unit";"Zergling";"Larva";362;1
"Unit";"Zergling";"Larva";363;1
"Unit";"Zergling";"Larva";364;1
"Building";"CreepTumorQueen";NA;365;0
"Building";"CreepTumor";NA;365;0
"Building";"UltraliskCavern";NA;365;0
"Building";"CreepTumor";NA;365;0
"Building";"CreepTumor";NA;365;0
"Building";"CreepTumor";NA;365;0
"Building";"CreepTumorQueen";NA;365;0
"Building";"CreepTumorQueen";NA;365;0
"Building";"CreepTumorQueen";NA;365;0
"Unit";"Zergling";"Larva";365;1
"Unit";"Zergling";"Larva";366;1
"Unit";"Zergling";"Larva";367;1
"Unit";"Zergling";"Larva";368;1
"Unit";"Zergling";"Larva";369;1
"Unit";"Zergling";"Larva";370;1
"Unit";"Zergling";"Larva";371;1
"Unit";"Zergling";"Larva";372;1
"Unit";"Zergling";"Larva";373;1
"Unit";"Zergling";"Larva";374;1
"Unit";"Zergling";"Larva";375;1
"Unit";"Zergling";"Larva";376;1
"Unit";"Zergling";"Larva";377;1
"Unit";"Zergling";"Larva";378;1
"Unit";"Queen";"Hatchery";379;2
"Unit";"Queen";"Hatchery";381;2
"Unit";"Zergling";"Larva";383;1
"Unit";"Zergling";"Larva";384;1
"Building";"CreepTumorQueen";NA;385;0
"Unit";"Zergling";"Larva";385;1
"Unit";"Zergling";"Larva";386;1
"Unit";"Zergling";"Larva";387;1
"Unit";"Zergling";"Larva";388;1
"Unit";"Zergling";"Larva";389;1
"Unit";"Zergling";"Larva";390;1
"Unit";"Zergling";"Larva";391;1
"Unit";"Zergling";"Larva";392;1
"Unit";"Zergling";"Larva";393;1
"Unit";"Zergling";"Larva";394;1
"Unit";"Zergling";"Larva";395;1
"Unit";"Zergling";"Larva";396;1
"Unit";"Zergling";"Larva";397;1
"Unit";"Zergling";"Larva";398;1
"Unit";"Zergling";"Larva";399;1
"Unit";"Zergling";"Larva";400;1
"Unit";"Zergling";"Larva";401;1
"Unit";"Zergling";"Larva";402;1
"Unit";"Baneling";"Zergling";403;0
"Unit";"Baneling";"Zergling";403;0
"Unit";"Baneling";"Zergling";403;0
"Unit";"Baneling";"Zergling";403;0
"Unit";"Baneling";"Zergling";403;0
"Unit";"Baneling";"Zergling";403;0
"Unit";"Baneling";"Zergling";403;0
"Unit";"Baneling";"Zergling";403;0
"Unit";"Baneling";"Zergling";403;0
"Unit";"Baneling";"Zergling";403;0
"Unit";"Baneling";"Zergling";403;0
"Unit";"Baneling";"Zergling";403;0
"Unit";"Baneling";"Zergling";403;0
"Unit";"Baneling";"Zergling";403;0
"Building";"CreepTumorQueen";NA;403;0
"Building";"CreepTumor";NA;403;0
"Unit";"Ultralisk";"Larva";403;6
"Unit";"Ultralisk";"Larva";409;6
"Upgrade";"ChitinousPlating";"UltraliskCavern";415;0
"Unit";"Ultralisk";"Larva";417;6
"Building";"Extractor";NA;423;0
"Unit";"Ultralisk";"Larva";423;6
"Unit";"Zergling";"Larva";429;1
"Unit";"Zergling";"Larva";430;1
"Unit";"Zergling";"Larva";431;1
"Unit";"Zergling";"Larva";432;1
"Unit";"Zergling";"Larva";433;1
"Unit";"Zergling";"Larva";434;1
"Unit";"Zergling";"Larva";435;1
"Unit";"Zergling";"Larva";436;1
"Unit";"Zergling";"Larva";437;1
"Unit";"Zergling";"Larva";438;1
"Unit";"Zergling";"Larva";439;1
"Unit";"Zergling";"Larva";440;1
"Unit";"Zergling";"Larva";441;1
"Unit";"Zergling";"Larva";442;1
"Unit";"Zergling";"Larva";443;1
"Unit";"Zergling";"Larva";444;1
"Unit";"Zergling";"Larva";445;1
"Unit";"Zergling";"Larva";446;1
"Unit";"Zergling";"Larva";447;1
"Unit";"Zergling";"Larva";448;1
"Unit";"Zergling";"Larva";449;1
"Unit";"Zergling";"Larva";450;1
"Unit";"Zergling";"Larva";451;1
"Unit";"Zergling";"Larva";452;1
"Unit";"Zergling";"Larva";453;1
"Unit";"Zergling";"Larva";454;1
"Unit";"Zergling";"Larva";455;1
"Unit";"Zergling";"Larva";456;1
"Unit";"Zergling";"Larva";457;1
"Unit";"Zergling";"Larva";458;1
"Unit";"Ultralisk";"Larva";459;6
"Unit";"Baneling";"Zergling";465;0
"Unit";"Baneling";"Zergling";465;0
"Unit";"Baneling";"Zergling";465;0
"Unit";"Baneling";"Zergling";465;0
"Unit";"Baneling";"Zergling";465;0
"Unit";"Baneling";"Zergling";465;0
"Unit";"Baneling";"Zergling";465;0
"Unit";"Overlord";"Larva";465;0
"Unit";"Overlord";"Larva";465;0
"Unit";"Overlord";"Larva";465;0
"Unit";"Overlord";"Larva";465;0
"Unit";"Baneling";"Zergling";465;0
"Unit";"Baneling";"Zergling";465;0
"Unit";"Baneling";"Zergling";465;0
"Unit";"Baneling";"Zergling";465;0
"Unit";"Baneling";"Zergling";465;0
"Unit";"Baneling";"Zergling";465;0
"Unit";"Baneling";"Zergling";465;0
"Unit";"Baneling";"Zergling";465;0
"Unit";"Baneling";"Zergling";465;0
"Unit";"Ultralisk";"Larva";465;6
"Unit";"Ultralisk";"Larva";471;6
"Unit";"Zergling";"Larva";477;1
"Unit";"Zergling";"Larva";478;1
"Unit";"Zergling";"Larva";479;1
"Unit";"Zergling";"Larva";480;1
"Unit";"Zergling";"Larva";481;1
"Unit";"Zergling";"Larva";482;1
"Unit";"Zergling";"Larva";483;1
"Unit";"Zergling";"Larva";484;1
"Unit";"Zergling";"Larva";485;1
"Unit";"Zergling";"Larva";486;1
"Unit";"Zergling";"Larva";487;1
"Unit";"Zergling";"Larva";488;1
"Unit";"Zergling";"Larva";489;1
"Unit";"Zergling";"Larva";490;1
"Unit";"Zergling";"Larva";491;1
"Unit";"Zergling";"Larva";492;1
"Unit";"Zergling";"Larva";493;1
"Unit";"Zergling";"Larva";494;1
"Unit";"Zergling";"Larva";495;1
"Unit";"Zergling";"Larva";496;1
"Unit";"Zergling";"Larva";497;1
"Unit";"Zergling";"Larva";498;1
"Unit";"Zergling";"Larva";499;1
"Unit";"Zergling";"Larva";500;1
"Unit";"Zergling";"Larva";501;1
"Unit";"Zergling";"Larva";502;1
"Unit";"Zergling";"Larva";503;1
"Unit";"Zergling";"Larva";504;1
"Unit";"Zergling";"Larva";505;1
"Unit";"Zergling";"Larva";506;1
"Unit";"Zergling";"Larva";507;1
"Unit";"Zergling";"Larva";508;1
"Unit";"Zergling";"Larva";509;1
"Unit";"Zergling";"Larva";510;1
"Unit";"Zergling";"Larva";511;1
"Unit";"Zergling";"Larva";512;1
"Unit";"Zergling";"Larva";513;1
"Unit";"Zergling";"Larva";514;1
"Unit";"Zergling";"Larva";515;1
"Unit";"Zergling";"Larva";516;1
"Unit";"Zergling";"Larva";517;1
"Unit";"Zergling";"Larva";518;1
"Building";"CreepTumorQueen";NA;519;0
"Building";"CreepTumorQueen";NA;519;0
"Building";"CreepTumorQueen";NA;519;0
"Building";"CreepTumor";NA;519;0
"Building";"CreepTumor";NA;519;0
"Building";"CreepTumorQueen";NA;519;0
"Unit";"Zergling";"Larva";519;1
"Unit";"Zergling";"Larva";520;1
"Unit";"Zergling";"Larva";521;1
"Unit";"Zergling";"Larva";522;1
"Unit";"Zergling";"Larva";523;1
"Unit";"Zergling";"Larva";524;1
"Unit";"Zergling";"Larva";525;1
"Unit";"Zergling";"Larva";526;1
"Unit";"Zergling";"Larva";527;1
"Unit";"Zergling";"Larva";528;1
"Unit";"Zergling";"Larva";529;1
"Unit";"Zergling";"Larva";530;1
"Unit";"Zergling";"Larva";531;1
"Unit";"Zergling";"Larva";532;1
"Unit";"Zergling";"Larva";533;1
"Unit";"Zergling";"Larva";534;1
"Unit";"Zergling";"Larva";535;1
"Unit";"Zergling";"Larva";536;1
"Building";"Hatchery";NA;537;0
"Unit";"Baneling";"Zergling";537;0
"Unit";"Baneling";"Zergling";537;0
"Unit";"Baneling";"Zergling";537;0
"Unit";"Baneling";"Zergling";537;0
"Unit";"Baneling";"Zergling";537;0
"Unit";"Baneling";"Zergling";537;0
"Unit";"Baneling";"Zergling";537;0
"Unit";"Mutalisk";"Larva";537;2
"Unit";"Mutalisk";"Larva";539;2
"Building";"CreepTumor";NA;541;0
"Building";"CreepTumor";NA;541;0
"Building";"CreepTumor";NA;541;0
"Building";"Hatchery";NA;541;0
"Building";"CreepTumor";NA;541;0
"Building";"CreepTumorQueen";NA;541;0
"Building";"CreepTumor";NA;541;0
"Building";"CreepTumor";NA;541;0
"Building";"CreepTumorQueen";NA;541;0
"Building";"CreepTumorQueen";NA;541;0
"Building";"CreepTumorQueen";NA;541;0
"Building";"CreepTumorQueen";NA;541;0
"Building";"CreepTumorQueen";NA;541;0
"Building";"CreepTumorQueen";NA;541;0
"Unit";"Ultralisk";"Larva";541;6
"Unit";"Ultralisk";"Larva";547;6
"Unit";"Ultralisk";"Larva";553;6
"Unit";"Queen";"Hatchery";559;2
"Unit";"Queen";"Hatchery";561;2
"Unit";"Queen";"Hatchery";563;2
"Unit";"Queen";"Hatchery";565;2
"Unit";"Ultralisk";"Larva";567;6
"Unit";"Baneling";"Zergling";573;0
"Unit";"Baneling";"Zergling";573;0
"Unit";"Baneling";"Zergling";573;0
"Unit";"Baneling";"Zergling";573;0
"Unit";"Baneling";"Zergling";573;0
"Unit";"Baneling";"Zergling";573;0
"Unit";"Baneling";"Zergling";573;0
"Unit";"Baneling";"Zergling";573;0
"Unit";"Baneling";"Zergling";573;0
"Unit";"Baneling";"Zergling";573;0
"Unit";"Baneling";"Zergling";573;0
"Unit";"Baneling";"Zergling";573;0
"Unit";"Baneling";"Zergling";573;0
"Unit";"Baneling";"Zergling";573;0
"Unit";"Baneling";"Zergling";573;0
"Building";"CreepTumorQueen";NA;573;0
"Building";"CreepTumor";NA;573;0
"Building";"CreepTumor";NA;573;0
"Building";"CreepTumor";NA;573;0
"Building";"CreepTumorQueen";NA;573;0
"Unit";"Ultralisk";"Larva";573;6
"Unit";"Ultralisk";"Larva";579;6
"Building";"CreepTumor";NA;585;0
"Building";"CreepTumor";NA;585;0
"Building";"CreepTumor";NA;585;0
"Unit";"Mutalisk";"Larva";585;2
"Unit";"Mutalisk";"Larva";587;2
"Unit";"Mutalisk";"Larva";589;2
"Unit";"Mutalisk";"Larva";591;2
"Unit";"Ultralisk";"Larva";593;6
"Unit";"Overlord";"Larva";599;0
"Unit";"Overlord";"Larva";599;0
"Unit";"Overlord";"Larva";599;0
"Building";"CreepTumor";NA;599;0
"Building";"CreepTumor";NA;599;0
"Building";"CreepTumor";NA;599;0
"Unit";"Overlord";"Larva";599;0
"Unit";"Overlord";"Larva";599;0
"Building";"CreepTumorQueen";NA;599;0
"Building";"CreepTumorQueen";NA;599;0
"Building";"CreepTumorQueen";NA;599;0
"Building";"Hatchery";NA;599;0
"Unit";"Corruptor";"Larva";599;2
"Unit";"Corruptor";"Larva";601;2
"Unit";"Corruptor";"Larva";603;2
"Unit";"Corruptor";"Larva";605;2
"Unit";"Corruptor";"Larva";607;2
"Unit";"Corruptor";"Larva";609;2
"Unit";"Ultralisk";"Larva";611;6
"Unit";"Ultralisk";"Larva";617;6
"Unit";"Ultralisk";"Larva";623;6
"Building";"CreepTumor";NA;629;0
"Unit";"Ultralisk";"Larva";629;6
"Building";"Hatchery";NA;635;0
"Unit";"Ultralisk";"Larva";635;6
"Unit";"Baneling";"Zergling";641;0
"Unit";"Baneling";"Zergling";641;0
"Unit";"Baneling";"Zergling";641;0
"Unit";"Baneling";"Zergling";641;0
"Building";"CreepTumorQueen";NA;641;0
"Building";"CreepTumorQueen";NA;641;0
"Building";"CreepTumorQueen";NA;641;0
"Building";"CreepTumorQueen";NA;641;0
"Unit";"Zergling";"Larva";641;1
"Unit";"Zergling";"Larva";642;1
"Unit";"Zergling";"Larva";643;1
"Unit";"Zergling";"Larva";644;1
"Unit";"Zergling";"Larva";645;1
"Unit";"Zergling";"Larva";646;1
"Unit";"Zergling";"Larva";647;1
"Unit";"Zergling";"Larva";648;1
"Unit";"Zergling";"Larva";649;1
"Unit";"Zergling";"Larva";650;1
"Building";"CreepTumorQueen";NA;651;0
"Building";"CreepTumorQueen";NA;651;0
"Building";"CreepTumorQueen";NA;651;0
"Unit";"Ultralisk";"Larva";651;6
"Unit";"Ultralisk";"Larva";657;6
"Building";"CreepTumor";NA;663;0
"Building";"CreepTumor";NA;663;0
"Building";"CreepTumor";NA;663;0
"Building";"CreepTumor";NA;663;0
"Building";"CreepTumorQueen";NA;663;0
"Building";"CreepTumor";NA;663;0
"Building";"CreepTumor";NA;663;0
"Building";"CreepTumorQueen";NA;663;0
"Unit";"Ultralisk";"Larva";663;6
"Building";"CreepTumorQueen";NA;669;0
"Building";"CreepTumorQueen";NA;669;0
"Building";"CreepTumorQueen";NA;669;0
"Unit";"Overlord";"Larva";669;0
"Building";"CreepTumor";NA;669;0
"Unit";"Zergling";"Larva";669;1
"Unit";"Zergling";"Larva";670;1
"Unit";"Zergling";"Larva";671;1
"Unit";"Zergling";"Larva";672;1
"Unit";"Zergling";"Larva";673;1
"Unit";"Zergling";"Larva";674;1
"Unit";"Zergling";"Larva";675;1
"Unit";"Zergling";"Larva";676;1
"Unit";"Zergling";"Larva";677;1
"Unit";"Zergling";"Larva";678;1
"Unit";"Zergling";"Larva";679;1
"Unit";"Zergling";"Larva";680;1
"Unit";"Zergling";"Larva";681;1
"Unit";"Zergling";"Larva";682;1
"Unit";"Zergling";"Larva";683;1
"Unit";"Zergling";"Larva";684;1
"Unit";"Zergling";"Larva";685;1
"Unit";"Zergling";"Larva";686;1
"Unit";"Zergling";"Larva";687;1
"Unit";"Zergling";"Larva";688;1
"Unit";"Zergling";"Larva";689;1
"Unit";"Zergling";"Larva";690;1
"Unit";"Zergling";"Larva";691;1
"Unit";"Zergling";"Larva";692;1
"Unit";"Zergling";"Larva";693;1
"Unit";"Zergling";"Larva";694;1
"Unit";"Zergling";"Larva";695;1
"Unit";"Zergling";"Larva";696;1
"Unit";"Zergling";"Larva";697;1
"Unit";"Zergling";"Larva";698;1
"Unit";"Zergling";"Larva";699;1
"Unit";"Zergling";"Larva";700;1
"Unit";"Zergling";"Larva";701;1
"Unit";"Zergling";"Larva";702;1
"Unit";"Zergling";"Larva";703;1
"Unit";"Zergling";"Larva";704;1
"Unit";"Zergling";"Larva";705;1
"Unit";"Zergling";"Larva";706;1
"Unit";"Zergling";"Larva";707;1
"Unit";"Zergling";"Larva";708;1
"Unit";"Zergling";"Larva";709;1
"Unit";"Zergling";"Larva";710;1
"Unit";"Zergling";"Larva";711;1
"Unit";"Zergling";"Larva";712;1
"Unit";"Zergling";"Larva";713;1
"Unit";"Zergling";"Larva";714;1
"Unit";"Zergling";"Larva";715;1
"Unit";"Zergling";"Larva";716;1
"Unit";"Zergling";"Larva";717;1
"Unit";"Zergling";"Larva";718;1
"Unit";"Zergling";"Larva";719;1
"Unit";"Zergling";"Larva";720;1
"Unit";"Zergling";"Larva";721;1
"Unit";"Zergling";"Larva";722;1
"Unit";"Overlord";"Larva";723;0
"Building";"CreepTumor";NA;723;0
"Building";"CreepTumor";NA;723;0
"Building";"CreepTumor";NA;723;0
"Building";"CreepTumor";NA;723;0
"Building";"CreepTumor";NA;723;0
"Building";"CreepTumor";NA;723;0
"Building";"CreepTumor";NA;723;0
"Building";"CreepTumorQueen";NA;723;0
"Building";"CreepTumorQueen";NA;723;0
"Unit";"Corruptor";"Larva";723;2
"Unit";"Overlord";"Larva";725;0
"Unit";"Overlord";"Larva";725;0
"Building";"CreepTumor";NA;725;0
"Building";"CreepTumor";NA;725;0
"Building";"CreepTumor";NA;725;0
"Building";"CreepTumor";NA;725;0
"Building";"CreepTumor";NA;725;0
"Building";"CreepTumor";NA;725;0
"Building";"CreepTumor";NA;725;0
"Unit";"Corruptor";"Larva";725;2
"Unit";"Corruptor";"Larva";727;2
"Unit";"Corruptor";"Larva";729;2
"Building";"CreepTumor";NA;731;0
"Building";"CreepTumor";NA;731;0
"Upgrade";"Burrow";"Hatchery";731;0
"Unit";"Corruptor";"Larva";731;2
"Unit";"Corruptor";"Larva";733;2
"Unit";"Zergling";"Larva";735;1
"Unit";"Zergling";"Larva";736;1
"Unit";"Zergling";"Larva";737;1
"Unit";"Zergling";"Larva";738;1
"Unit";"Zergling";"Larva";739;1
"Unit";"Zergling";"Larva";740;1
"Unit";"Zergling";"Larva";741;1
"Unit";"Zergling";"Larva";742;1
"Building";"CreepTumor";NA;743;0
"Building";"CreepTumor";NA;743;0
"Building";"CreepTumor";NA;743;0
"Building";"CreepTumor";NA;743;0
"Building";"CreepTumor";NA;743;0
"Unit";"Overlord";"Larva";743;0
"Building";"CreepTumor";NA;743;0
"Building";"CreepTumor";NA;743;0
"Building";"CreepTumor";NA;743;0
"Building";"CreepTumorQueen";NA;743;0
"Building";"CreepTumorQueen";NA;743;0
"Unit";"Baneling";"Zergling";743;0
"Unit";"Baneling";"Zergling";743;0
"Unit";"Baneling";"Zergling";743;0
"Unit";"Baneling";"Zergling";743;0
"Unit";"Baneling";"Zergling";743;0
"Unit";"Baneling";"Zergling";743;0
"Unit";"Baneling";"Zergling";743;0
"Unit";"Baneling";"Zergling";743;0
"Unit";"Baneling";"Zergling";743;0
"Unit";"Baneling";"Zergling";743;0
"Unit";"Baneling";"Zergling";743;0
"Unit";"Overlord";"Larva";743;0
"Unit";"Overlord";"Larva";743;0
"Building";"Extractor";NA;743;0
"Unit";"Corruptor";"Larva";743;2
"Unit";"Overlord";"Larva";745;0
"Unit";"Overlord";"Larva";745;0
"Building";"CreepTumor";NA;745;0
"Building";"CreepTumor";NA;745;0
"Unit";"Ultralisk";"Larva";745;6
"Unit";"Zergling";"Larva";751;1
"Unit";"Zergling";"Larva";752;1
"Unit";"Zergling";"Larva";753;1
"Unit";"Zergling";"Larva";754;1
"Unit";"Zergling";"Larva";755;1
"Unit";"Zergling";"Larva";756;1
"Unit";"Zergling";"Larva";757;1
"Unit";"Zergling";"Larva";758;1
"Unit";"Zergling";"Larva";759;1
"Unit";"Zergling";"Larva";760;1
"Unit";"Zergling";"Larva";761;1
"Unit";"Zergling";"Larva";762;1
"Unit";"Zergling";"Larva";763;1
"Unit";"Zergling";"Larva";764;1
"Unit";"Zergling";"Larva";765;1
"Unit";"Zergling";"Larva";766;1
"Unit";"Zergling";"Larva";767;1
"Unit";"Zergling";"Larva";768;1
"Unit";"Zergling";"Larva";769;1
"Unit";"Zergling";"Larva";770;1
"Unit";"Zergling";"Larva";771;1
"Unit";"Zergling";"Larva";772;1
"Unit";"Zergling";"Larva";773;1
"Unit";"Zergling";"Larva";774;1
"Unit";"Zergling";"Larva";775;1
"Unit";"Zergling";"Larva";776;1
"Unit";"Zergling";"Larva";777;1
"Unit";"Zergling";"Larva";778;1
"Unit";"Zergling";"Larva";779;1
"Unit";"Zergling";"Larva";780;1
"Unit";"Zergling";"Larva";781;1
"Unit";"Zergling";"Larva";782;1
"Unit";"Zergling";"Larva";783;1
"Unit";"Zergling";"Larva";784;1
"Unit";"Zergling";"Larva";785;1
"Unit";"Zergling";"Larva";786;1
"Unit";"Zergling";"Larva";787;1
"Unit";"Zergling";"Larva";788;1
"Unit";"Zergling";"Larva";789;1
"Unit";"Zergling";"Larva";790;1
"Unit";"Zergling";"Larva";791;1
"Unit";"Zergling";"Larva";792;1
"Unit";"Zergling";"Larva";793;1
"Unit";"Zergling";"Larva";794;1
"Unit";"Zergling";"Larva";795;1
"Unit";"Zergling";"Larva";796;1
"Unit";"Zergling";"Larva";797;1
"Unit";"Zergling";"Larva";798;1
"Unit";"Zergling";"Larva";799;1
"Unit";"Zergling";"Larva";800;1
"Unit";"Zergling";"Larva";801;1
"Unit";"Zergling";"Larva";802;1
"Unit";"Zergling";"Larva";803;1
"Unit";"Zergling";"Larva";804;1
"Unit";"Zergling";"Larva";805;1
"Unit";"Zergling";"Larva";806;1
"Unit";"Zergling";"Larva";807;1
"Unit";"Zergling";"Larva";808;1
"Unit";"Zergling";"Larva";809;1
"Unit";"Zergling";"Larva";810;1
"Unit";"Zergling";"Larva";811;1
"Unit";"Zergling";"Larva";812;1
"Unit";"Zergling";"Larva";813;1
"Unit";"Zergling";"Larva";814;1
"Unit";"Zergling";"Larva";815;1
"Unit";"Zergling";"Larva";816;1
"Unit";"Queen";"Hatchery";817;2
"Unit";"Queen";"Hatchery";819;2
"Unit";"Queen";"Hatchery";821;2
"Building";"Extractor";NA;823;0
"Building";"Extractor";NA;823;0
"Unit";"Zergling";"Larva";823;1
"Unit";"Zergling";"Larva";824;1
"Unit";"Zergling";"Larva";825;1
"Unit";"Zergling";"Larva";826;1
"Unit";"Zergling";"Larva";827;1
"Unit";"Zergling";"Larva";828;1
"Unit";"Zergling";"Larva";829;1
"Unit";"Zergling";"Larva";830;1
"Unit";"Zergling";"Larva";831;1
"Unit";"Zergling";"Larva";832;1
"Unit";"Zergling";"Larva";833;1
"Unit";"Zergling";"Larva";834;1
"Unit";"Zergling";"Larva";835;1
"Unit";"Zergling";"Larva";836;1
"Unit";"Zergling";"Larva";837;1
"Unit";"Zergling";"Larva";838;1
"Unit";"Zergling";"Larva";839;1
"Unit";"Zergling";"Larva";840;1
"Unit";"Zergling";"Larva";841;1
"Unit";"Zergling";"Larva";842;1
"Unit";"Zergling";"Larva";843;1
"Unit";"Zergling";"Larva";844;1
"Unit";"Zergling";"Larva";845;1
"Unit";"Zergling";"Larva";846;1
"Unit";"Zergling";"Larva";847;1
"Unit";"Zergling";"Larva";848;1
"Unit";"Ultralisk";"Larva";849;6
"Building";"CreepTumor";NA;862;0
"Building";"CreepTumor";NA;862;0
"Building";"CreepTumor";NA;862;0
"Upgrade";"SprayZerg";NA;862;0
"Upgrade";"SprayZerg";NA;862;0
"Upgrade";"zerglingmovementspeed";NA;862;0
"Upgrade";"SprayZerg";NA;862;0
"Upgrade";"SprayZerg";NA;862;0
"Upgrade";"SprayZerg";NA;862;0
"Upgrade";"SprayZerg";NA;862;0
"Upgrade";"SprayZerg";NA;862;0
"Upgrade";"ZergGroundArmorsLevel1";NA;862;0
"Upgrade";"ZergMeleeWeaponsLevel1";NA;862;0
"Upgrade";"SprayZerg";NA;862;0
"Upgrade";"CentrificalHooks";NA;862;0
"Upgrade";"overlordspeed";NA;862;0
"Upgrade";"ZergGroundArmorsLevel2";NA;862;0
"Upgrade";"SprayZerg";NA;862;0
"Upgrade";"SprayZerg";NA;862;0
"Upgrade";"ZergFlyerWeaponsLevel1";NA;862;0
"Upgrade";"ZergMeleeWeaponsLevel2";NA;862;0
"Upgrade";"SprayZerg";NA;862;0
"Upgrade";"SprayZerg";NA;862;0
"Upgrade";"ZergGroundArmorsLevel3";NA;862;0
"Upgrade";"ZergMeleeWeaponsLevel3";NA;862;0
"Upgrade";"SprayZerg";NA;862;0
"Upgrade";"SprayZerg";NA;862;0
"Upgrade";"zerglingattackspeed";NA;862;0
"Upgrade";"SprayZerg";NA;862;0
"Upgrade";"SprayZerg";NA;862;0
"Upgrade";"SprayZerg";NA;862;0
"Upgrade";"ZergFlyerArmorsLevel1";NA;862;0
"Upgrade";"SprayZerg";NA;862;0
"Upgrade";"SprayZerg";NA;862;0
"Upgrade";"SprayZerg";NA;862;0
"Upgrade";"SprayZerg";NA;862;0
"Upgrade";"ZergFlyerWeaponsLevel2";NA;862;0
