"type";"unit_name";"on_building";"total_supply_lag";"supply"
"Unit";"Overlord";"Larva";13;0
"Building";"Extractor";NA;17;0
"Building";"SpawningPool";NA;18;0
"Building";"Hatchery";NA;20;0
"Unit";"Queen";"Hatchery";22;2
"Unit";"Overlord";"Larva";24;0
"Unit";"Zergling";"Larva";24;1
"Unit";"Zergling";"Larva";25;1
"Unit";"Queen";"Hatchery";26;2
"Unit";"Queen";"Hatchery";31;2
"Unit";"Zergling";"Larva";34;1
"Unit";"Zergling";"Larva";35;1
"Unit";"Overlord";"Larva";36;0
"Unit";"Overlord";"Larva";40;0
"Unit";"Zergling";"Larva";40;1
"Unit";"Zergling";"Larva";41;1
"Building";"Hatchery";NA;43;0
"Building";"CreepTumorQueen";NA;45;0
"Unit";"Zergling";"Larva";48;1
"Unit";"Zergling";"Larva";49;1
"Unit";"Zergling";"Larva";50;1
"Unit";"Zergling";"Larva";51;1
"Building";"CreepTumor";NA;54;0
"Unit";"Queen";"Hatchery";54;2
"Building";"CreepTumorQueen";NA;56;0
"Unit";"Zergling";"Larva";56;1
"Unit";"Zergling";"Larva";57;1
"Unit";"Overlord";"Larva";59;0
"Unit";"Overlord";"Larva";59;0
"Building";"RoachWarren";NA;62;0
"Unit";"Zergling";"Larva";62;1
"Unit";"Zergling";"Larva";63;1
"Unit";"Zergling";"Larva";64;1
"Unit";"Zergling";"Larva";65;1
"Building";"CreepTumor";NA;66;0
"Building";"CreepTumorQueen";NA;66;0
"Building";"CreepTumor";NA;66;0
"Unit";"Queen";"Hatchery";67;2
"Building";"Extractor";NA;69;0
"Building";"Extractor";NA;69;0
"Unit";"Queen";"Hatchery";74;2
"Building";"EvolutionChamber";NA;79;0
"Building";"SporeCrawler";NA;79;0
"Building";"SporeCrawler";NA;79;0
"Building";"CreepTumor";NA;79;0
"Building";"CreepTumor";NA;79;0
"Building";"CreepTumorQueen";NA;79;0
"Unit";"Roach";"Larva";85;2
"Unit";"Roach";"Larva";87;2
"Unit";"Roach";"Larva";89;2
"Unit";"Roach";"Larva";91;2
"Building";"SporeCrawler";NA;94;0
"Unit";"Overlord";"Larva";101;0
"Unit";"Overlord";"Larva";101;0
"Unit";"Overlord";"Larva";101;0
"Building";"CreepTumor";NA;101;0
"Unit";"Overlord";"Larva";101;0
"Building";"Extractor";NA;102;0
"Upgrade";"GlialReconstitution";"RoachWarren";106;0
"Building";"CreepTumor";NA;115;0
"Building";"CreepTumor";NA;115;0
"Building";"CreepTumorQueen";NA;115;0
"Building";"CreepTumorQueen";NA;115;0
"Building";"Extractor";NA;116;0
"Building";"Extractor";NA;116;0
"Building";"InfestationPit";NA;117;0
"Unit";"Overlord";"Larva";117;0
"Unit";"Overlord";"Larva";117;0
"Building";"CreepTumorQueen";NA;117;0
"Building";"CreepTumor";NA;117;0
"Unit";"Roach";"Larva";117;2
"Unit";"Roach";"Larva";119;2
"Unit";"Roach";"Larva";121;2
"Unit";"Roach";"Larva";123;2
"Unit";"Roach";"Larva";125;2
"Building";"CreepTumor";NA;127;0
"Building";"CreepTumorQueen";NA;127;0
"Building";"CreepTumor";NA;127;0
"Unit";"Overlord";"Larva";130;0
"Unit";"Overlord";"Larva";130;0
"Building";"CreepTumorQueen";NA;130;0
"Unit";"Overlord";"Larva";130;0
"Upgrade";"Burrow";"Hatchery";132;0
"Building";"CreepTumor";NA;135;0
"Building";"CreepTumor";NA;135;0
"Building";"CreepTumorQueen";NA;135;0
"Building";"CreepTumor";NA;135;0
"Building";"CreepTumor";NA;135;0
"Building";"CreepTumor";NA;135;0
"Building";"CreepTumor";NA;135;0
"Building";"CreepTumor";NA;135;0
"Building";"Hatchery";NA;135;0
"Unit";"Infestor";"Larva";135;2
"Unit";"Infestor";"Larva";137;2
"Unit";"Infestor";"Larva";139;2
"Unit";"Roach";"Larva";141;2
"Unit";"Roach";"Larva";143;2
"Unit";"Roach";"Larva";145;2
"Building";"CreepTumorQueen";NA;147;0
"Unit";"Roach";"Larva";147;2
"Unit";"Roach";"Larva";149;2
"Unit";"Roach";"Larva";151;2
"Unit";"Roach";"Larva";153;2
"Building";"CreepTumor";NA;155;0
"Building";"CreepTumor";NA;155;0
"Building";"CreepTumorQueen";NA;155;0
"Building";"CreepTumor";NA;155;0
"Unit";"Roach";"Larva";155;2
"Unit";"Roach";"Larva";157;2
"Unit";"Roach";"Larva";159;2
"Unit";"Roach";"Larva";161;2
"Unit";"Roach";"Larva";163;2
"Building";"CreepTumor";NA;165;0
"Building";"CreepTumor";NA;165;0
"Building";"SporeCrawler";NA;165;0
"Building";"CreepTumor";NA;165;0
"Unit";"Overlord";"Larva";165;0
"Unit";"Overlord";"Larva";165;0
"Unit";"Overlord";"Larva";165;0
"Unit";"Overlord";"Larva";165;0
"Unit";"Overlord";"Larva";165;0
"Building";"CreepTumor";NA;165;0
"Building";"CreepTumor";NA;165;0
"Building";"CreepTumor";NA;165;0
"Unit";"Roach";"Larva";165;2
"Unit";"Roach";"Larva";167;2
"Unit";"Roach";"Larva";169;2
"Building";"Extractor";NA;180;0
"Building";"EvolutionChamber";NA;181;0
"Unit";"Roach";"Larva";181;2
"Unit";"Roach";"Larva";183;2
"Unit";"Roach";"Larva";185;2
"Unit";"Roach";"Larva";187;2
"Unit";"Roach";"Larva";189;2
"Unit";"Roach";"Larva";191;2
"Unit";"Roach";"Larva";193;2
"Unit";"Roach";"Larva";195;2
"Unit";"Roach";"Larva";197;2
"Unit";"Overlord";"Larva";199;0
"Unit";"Overlord";"Larva";199;0
"Unit";"Overlord";"Larva";199;0
"Unit";"Overlord";"Larva";199;0
"Building";"CreepTumor";NA;200;0
"Building";"CreepTumor";NA;200;0
"Building";"CreepTumor";NA;200;0
"Building";"CreepTumorQueen";NA;200;0
"Unit";"Roach";"Larva";200;2
"Unit";"Roach";"Larva";202;2
"Unit";"Roach";"Larva";204;2
"Unit";"Roach";"Larva";206;2
"Building";"CreepTumorQueen";NA;208;0
"Unit";"Queen";"Hatchery";214;2
"Unit";"Queen";"Hatchery";216;2
"Building";"UltraliskCavern";NA;220;0
"Building";"SporeCrawler";NA;221;0
"Building";"CreepTumor";NA;221;0
"Building";"CreepTumor";NA;221;0
"Building";"CreepTumor";NA;221;0
"Building";"CreepTumorQueen";NA;221;0
"Building";"CreepTumor";NA;223;0
"Building";"CreepTumor";NA;223;0
"Building";"CreepTumor";NA;223;0
"Building";"CreepTumor";NA;223;0
"Building";"CreepTumor";NA;223;0
"Building";"CreepTumor";NA;223;0
"Building";"CreepTumor";NA;223;0
"Building";"CreepTumor";NA;223;0
"Unit";"Queen";"Hatchery";223;2
"Building";"CreepTumorQueen";NA;225;0
"Unit";"Roach";"Larva";225;2
"Unit";"Roach";"Larva";227;2
"Unit";"Roach";"Larva";229;2
"Unit";"Roach";"Larva";231;2
"Unit";"Roach";"Larva";233;2
"Unit";"Roach";"Larva";235;2
"Unit";"Roach";"Larva";237;2
"Unit";"Roach";"Larva";239;2
"Unit";"Zergling";"Larva";241;1
"Unit";"Zergling";"Larva";242;1
"Unit";"Zergling";"Larva";243;1
"Unit";"Zergling";"Larva";244;1
"Unit";"Zergling";"Larva";245;1
"Unit";"Zergling";"Larva";246;1
"Unit";"Zergling";"Larva";247;1
"Unit";"Zergling";"Larva";248;1
"Unit";"Zergling";"Larva";249;1
"Unit";"Zergling";"Larva";250;1
"Unit";"Zergling";"Larva";251;1
"Unit";"Zergling";"Larva";252;1
"Unit";"Zergling";"Larva";253;1
"Unit";"Zergling";"Larva";254;1
"Unit";"Zergling";"Larva";255;1
"Unit";"Zergling";"Larva";256;1
"Unit";"Roach";"Larva";257;2
"Unit";"Roach";"Larva";259;2
"Unit";"Roach";"Larva";261;2
"Unit";"Roach";"Larva";263;2
"Unit";"Roach";"Larva";265;2
"Unit";"Roach";"Larva";267;2
"Unit";"Roach";"Larva";269;2
"Unit";"Roach";"Larva";271;2
"Unit";"Roach";"Larva";273;2
"Unit";"Roach";"Larva";275;2
"Unit";"Roach";"Larva";277;2
"Unit";"Roach";"Larva";279;2
"Unit";"Roach";"Larva";281;2
"Unit";"Roach";"Larva";283;2
"Unit";"Queen";"Hatchery";285;2
"Unit";"Overlord";"Larva";287;0
"Unit";"Overlord";"Larva";287;0
"Unit";"Overlord";"Larva";287;0
"Unit";"Overlord";"Larva";287;0
"Upgrade";"ChitinousPlating";"UltraliskCavern";287;0
"Building";"CreepTumor";NA;287;0
"Building";"CreepTumorQueen";NA;287;0
"Building";"CreepTumor";NA;287;0
"Building";"CreepTumorQueen";NA;287;0
"Building";"CreepTumorQueen";NA;287;0
"Building";"Hatchery";NA;287;0
"Building";"SporeCrawler";NA;287;0
"Building";"Hatchery";NA;287;0
"Building";"Extractor";NA;287;0
"Unit";"Infestor";"Larva";287;2
"Unit";"Infestor";"Larva";289;2
"Unit";"Infestor";"Larva";291;2
"Unit";"Zergling";"Larva";293;1
"Unit";"Zergling";"Larva";294;1
"Unit";"Zergling";"Larva";295;1
"Unit";"Zergling";"Larva";296;1
"Unit";"Zergling";"Larva";297;1
"Unit";"Zergling";"Larva";298;1
"Unit";"Zergling";"Larva";299;1
"Unit";"Zergling";"Larva";300;1
"Unit";"Zergling";"Larva";301;1
"Unit";"Zergling";"Larva";302;1
"Unit";"Zergling";"Larva";303;1
"Unit";"Zergling";"Larva";304;1
"Unit";"Zergling";"Larva";305;1
"Unit";"Zergling";"Larva";306;1
"Building";"CreepTumor";NA;307;0
"Building";"CreepTumor";NA;307;0
"Building";"CreepTumor";NA;307;0
"Building";"CreepTumor";NA;307;0
"Building";"CreepTumorQueen";NA;307;0
"Building";"CreepTumor";NA;307;0
"Building";"CreepTumor";NA;307;0
"Building";"CreepTumor";NA;307;0
"Building";"CreepTumor";NA;307;0
"Building";"CreepTumor";NA;307;0
"Building";"CreepTumorQueen";NA;307;0
"Unit";"Zergling";"Larva";307;1
"Unit";"Zergling";"Larva";308;1
"Unit";"Zergling";"Larva";309;1
"Unit";"Zergling";"Larva";310;1
"Unit";"Zergling";"Larva";311;1
"Unit";"Zergling";"Larva";312;1
"Unit";"Zergling";"Larva";313;1
"Unit";"Zergling";"Larva";314;1
"Unit";"Zergling";"Larva";315;1
"Unit";"Zergling";"Larva";316;1
"Unit";"Zergling";"Larva";317;1
"Unit";"Zergling";"Larva";318;1
"Building";"CreepTumorQueen";NA;319;0
"Building";"Extractor";NA;319;0
"Building";"Extractor";NA;319;0
"Unit";"Roach";"Larva";319;2
"Unit";"Roach";"Larva";321;2
"Unit";"Roach";"Larva";323;2
"Unit";"Roach";"Larva";325;2
"Unit";"Roach";"Larva";327;2
"Unit";"Roach";"Larva";329;2
"Unit";"Roach";"Larva";331;2
"Unit";"Roach";"Larva";333;2
"Unit";"Roach";"Larva";335;2
"Unit";"Infestor";"Larva";337;2
"Unit";"Queen";"Hatchery";339;2
"Unit";"Ultralisk";"Larva";341;6
"Unit";"Ultralisk";"Larva";347;6
"Unit";"Ultralisk";"Larva";353;6
"Building";"Extractor";NA;359;0
"Unit";"Queen";"Hatchery";362;2
"Building";"Hatchery";NA;364;0
"Unit";"Zergling";"Larva";370;1
"Unit";"Zergling";"Larva";371;1
"Unit";"Zergling";"Larva";372;1
"Unit";"Zergling";"Larva";373;1
"Unit";"Zergling";"Larva";374;1
"Unit";"Zergling";"Larva";375;1
"Unit";"Zergling";"Larva";376;1
"Unit";"Zergling";"Larva";377;1
"Unit";"Zergling";"Larva";378;1
"Unit";"Zergling";"Larva";379;1
"Unit";"Zergling";"Larva";380;1
"Unit";"Zergling";"Larva";381;1
"Unit";"Zergling";"Larva";382;1
"Unit";"Zergling";"Larva";383;1
"Building";"CreepTumor";NA;384;0
"Building";"CreepTumor";NA;384;0
"Building";"CreepTumor";NA;384;0
"Unit";"Queen";"Hatchery";384;2
"Unit";"Queen";"Hatchery";386;2
"Unit";"Queen";"Hatchery";388;2
"Building";"CreepTumorQueen";NA;392;0
"Building";"CreepTumorQueen";NA;392;0
"Building";"SpineCrawler";NA;393;0
"Building";"SpineCrawler";NA;395;0
"Building";"SporeCrawler";NA;395;0
"Building";"SpineCrawler";NA;395;0
"Building";"SporeCrawler";NA;399;0
"Building";"CreepTumor";NA;399;0
"Unit";"Ultralisk";"Larva";399;6
"Unit";"Ultralisk";"Larva";405;6
"Building";"CreepTumorQueen";NA;411;0
"Building";"CreepTumor";NA;411;0
"Building";"CreepTumorQueen";NA;411;0
"Building";"CreepTumor";NA;411;0
"Building";"CreepTumor";NA;411;0
"Building";"CreepTumorQueen";NA;411;0
"Building";"CreepTumor";NA;411;0
"Building";"CreepTumor";NA;411;0
"Unit";"Infestor";"Larva";411;2
"Building";"CreepTumorQueen";NA;413;0
"Building";"CreepTumorQueen";NA;413;0
"Unit";"Ultralisk";"Larva";413;6
"Unit";"Ultralisk";"Larva";419;6
"Building";"SpawningPool";NA;425;0
"Unit";"Ultralisk";"Larva";425;6
"Unit";"Ultralisk";"Larva";431;6
"Unit";"Zergling";"Larva";437;1
"Unit";"Zergling";"Larva";438;1
"Unit";"Zergling";"Larva";439;1
"Unit";"Zergling";"Larva";440;1
"Unit";"Zergling";"Larva";441;1
"Unit";"Zergling";"Larva";442;1
"Unit";"Zergling";"Larva";443;1
"Unit";"Zergling";"Larva";444;1
"Unit";"Zergling";"Larva";445;1
"Unit";"Zergling";"Larva";446;1
"Unit";"Zergling";"Larva";447;1
"Unit";"Zergling";"Larva";448;1
"Unit";"Zergling";"Larva";449;1
"Unit";"Zergling";"Larva";450;1
"Unit";"Zergling";"Larva";451;1
"Unit";"Zergling";"Larva";452;1
"Unit";"Infestor";"Larva";453;2
"Unit";"Infestor";"Larva";455;2
"Unit";"Infestor";"Larva";457;2
"Building";"Extractor";NA;459;0
"Unit";"Queen";"Hatchery";459;2
"Unit";"Queen";"Hatchery";461;2
"Unit";"Queen";"Hatchery";463;2
"Building";"CreepTumor";NA;465;0
"Building";"CreepTumor";NA;465;0
"Building";"CreepTumor";NA;465;0
"Building";"Hatchery";NA;465;0
"Building";"CreepTumorQueen";NA;465;0
"Building";"SpineCrawler";NA;465;0
"Building";"CreepTumorQueen";NA;465;0
"Unit";"Infestor";"Larva";465;2
"Unit";"Infestor";"Larva";467;2
"Building";"CreepTumor";NA;469;0
"Building";"Hatchery";NA;469;0
"Building";"CreepTumor";NA;469;0
"Building";"CreepTumor";NA;469;0
"Unit";"Queen";"Hatchery";469;2
"Unit";"Queen";"Hatchery";471;2
"Building";"CreepTumor";NA;473;0
"Building";"CreepTumorQueen";NA;473;0
"Building";"CreepTumor";NA;473;0
"Building";"CreepTumor";NA;473;0
"Building";"Spire";NA;473;0
"Building";"CreepTumor";NA;473;0
"Building";"CreepTumor";NA;473;0
"Building";"CreepTumor";NA;473;0
"Building";"CreepTumor";NA;473;0
"Unit";"Roach";"Larva";473;2
"Unit";"Roach";"Larva";475;2
"Unit";"Roach";"Larva";477;2
"Unit";"Roach";"Larva";479;2
"Unit";"Zergling";"Larva";481;1
"Unit";"Zergling";"Larva";482;1
"Unit";"Zergling";"Larva";483;1
"Unit";"Zergling";"Larva";484;1
"Unit";"Zergling";"Larva";485;1
"Unit";"Zergling";"Larva";486;1
"Unit";"Zergling";"Larva";487;1
"Unit";"Zergling";"Larva";488;1
"Unit";"Zergling";"Larva";489;1
"Unit";"Zergling";"Larva";490;1
"Unit";"Zergling";"Larva";491;1
"Unit";"Zergling";"Larva";492;1
"Unit";"Zergling";"Larva";493;1
"Unit";"Zergling";"Larva";494;1
"Unit";"Zergling";"Larva";495;1
"Unit";"Zergling";"Larva";496;1
"Unit";"Zergling";"Larva";497;1
"Unit";"Zergling";"Larva";498;1
"Unit";"Zergling";"Larva";499;1
"Unit";"Zergling";"Larva";500;1
"Unit";"Zergling";"Larva";501;1
"Unit";"Zergling";"Larva";502;1
"Unit";"Zergling";"Larva";503;1
"Unit";"Zergling";"Larva";504;1
"Unit";"Zergling";"Larva";505;1
"Unit";"Zergling";"Larva";506;1
"Unit";"Zergling";"Larva";507;1
"Unit";"Zergling";"Larva";508;1
"Unit";"Zergling";"Larva";509;1
"Unit";"Zergling";"Larva";510;1
"Unit";"Zergling";"Larva";511;1
"Unit";"Zergling";"Larva";512;1
"Unit";"Zergling";"Larva";513;1
"Unit";"Zergling";"Larva";514;1
"Building";"CreepTumor";NA;515;0
"Unit";"Infestor";"Larva";515;2
"Building";"CreepTumor";NA;517;0
"Building";"CreepTumorQueen";NA;517;0
"Building";"CreepTumorQueen";NA;517;0
"Building";"CreepTumorQueen";NA;517;0
"Unit";"Ultralisk";"Larva";517;6
"Building";"BanelingNest";NA;523;0
"Unit";"Ultralisk";"Larva";523;6
"Unit";"Ultralisk";"Larva";529;6
"Building";"Extractor";NA;535;0
"Building";"Extractor";NA;535;0
"Unit";"Ultralisk";"Larva";535;6
"Unit";"Ultralisk";"Larva";541;6
"Unit";"Roach";"Larva";547;2
"Unit";"Roach";"Larva";549;2
"Unit";"Roach";"Larva";551;2
"Unit";"Roach";"Larva";553;2
"Unit";"Roach";"Larva";555;2
"Unit";"Roach";"Larva";557;2
"Unit";"Zergling";"Larva";559;1
"Unit";"Zergling";"Larva";560;1
"Unit";"Zergling";"Larva";561;1
"Unit";"Zergling";"Larva";562;1
"Unit";"Zergling";"Larva";563;1
"Unit";"Zergling";"Larva";564;1
"Unit";"Zergling";"Larva";565;1
"Unit";"Zergling";"Larva";566;1
"Unit";"Zergling";"Larva";567;1
"Unit";"Zergling";"Larva";568;1
"Unit";"Zergling";"Larva";569;1
"Unit";"Zergling";"Larva";570;1
"Unit";"Zergling";"Larva";571;1
"Unit";"Zergling";"Larva";572;1
"Unit";"Zergling";"Larva";573;1
"Unit";"Zergling";"Larva";574;1
"Unit";"Queen";"Hatchery";575;2
"Building";"CreepTumor";NA;577;0
"Building";"CreepTumor";NA;577;0
"Building";"CreepTumorQueen";NA;577;0
"Building";"CreepTumorQueen";NA;577;0
"Building";"Hatchery";NA;577;0
"Building";"CreepTumorQueen";NA;577;0
"Building";"SporeCrawler";NA;577;0
"Building";"SpineCrawler";NA;577;0
"Building";"SpineCrawler";NA;577;0
"Building";"CreepTumor";NA;577;0
"Building";"CreepTumor";NA;577;0
"Building";"SpineCrawler";NA;577;0
"Building";"CreepTumor";NA;577;0
"Building";"CreepTumor";NA;577;0
"Building";"CreepTumor";NA;577;0
"Unit";"Zergling";"Larva";577;1
"Unit";"Zergling";"Larva";578;1
"Unit";"Zergling";"Larva";579;1
"Unit";"Zergling";"Larva";580;1
"Unit";"Zergling";"Larva";581;1
"Unit";"Zergling";"Larva";582;1
"Unit";"Zergling";"Larva";583;1
"Unit";"Zergling";"Larva";584;1
"Unit";"Zergling";"Larva";585;1
"Unit";"Zergling";"Larva";586;1
"Unit";"Zergling";"Larva";587;1
"Unit";"Zergling";"Larva";588;1
"Unit";"Zergling";"Larva";589;1
"Unit";"Zergling";"Larva";590;1
"Unit";"Zergling";"Larva";591;1
"Unit";"Zergling";"Larva";592;1
"Unit";"Zergling";"Larva";593;1
"Unit";"Zergling";"Larva";594;1
"Building";"CreepTumor";NA;595;0
"Building";"CreepTumor";NA;595;0
"Building";"CreepTumorQueen";NA;595;0
"Building";"CreepTumorQueen";NA;595;0
"Building";"Hatchery";NA;595;0
"Unit";"Ultralisk";"Larva";595;6
"Unit";"Zergling";"Larva";601;1
"Unit";"Zergling";"Larva";602;1
"Unit";"Zergling";"Larva";603;1
"Unit";"Zergling";"Larva";604;1
"Unit";"Zergling";"Larva";605;1
"Unit";"Zergling";"Larva";606;1
"Unit";"Zergling";"Larva";607;1
"Unit";"Zergling";"Larva";608;1
"Unit";"Zergling";"Larva";609;1
"Unit";"Zergling";"Larva";610;1
"Unit";"Zergling";"Larva";611;1
"Unit";"Zergling";"Larva";612;1
"Unit";"Zergling";"Larva";613;1
"Unit";"Zergling";"Larva";614;1
"Unit";"Zergling";"Larva";615;1
"Unit";"Zergling";"Larva";616;1
"Unit";"Zergling";"Larva";617;1
"Unit";"Zergling";"Larva";618;1
"Unit";"Queen";"Hatchery";619;2
"Building";"CreepTumor";NA;621;0
"Building";"CreepTumorQueen";NA;621;0
"Unit";"Ultralisk";"Larva";621;6
"Unit";"Zergling";"Larva";627;1
"Unit";"Zergling";"Larva";628;1
"Unit";"Zergling";"Larva";629;1
"Unit";"Zergling";"Larva";630;1
"Unit";"Zergling";"Larva";631;1
"Unit";"Zergling";"Larva";632;1
"Unit";"Zergling";"Larva";633;1
"Unit";"Zergling";"Larva";634;1
"Unit";"Zergling";"Larva";635;1
"Unit";"Zergling";"Larva";636;1
"Unit";"Zergling";"Larva";637;1
"Unit";"Zergling";"Larva";638;1
"Unit";"Zergling";"Larva";639;1
"Unit";"Zergling";"Larva";640;1
"Unit";"Zergling";"Larva";641;1
"Unit";"Zergling";"Larva";642;1
"Unit";"Zergling";"Larva";643;1
"Unit";"Zergling";"Larva";644;1
"Unit";"Zergling";"Larva";645;1
"Unit";"Zergling";"Larva";646;1
"Unit";"Zergling";"Larva";647;1
"Unit";"Zergling";"Larva";648;1
"Unit";"Zergling";"Larva";649;1
"Unit";"Zergling";"Larva";650;1
"Unit";"Zergling";"Larva";651;1
"Unit";"Zergling";"Larva";652;1
"Unit";"Zergling";"Larva";653;1
"Unit";"Zergling";"Larva";654;1
"Unit";"Zergling";"Larva";655;1
"Unit";"Zergling";"Larva";656;1
"Unit";"Zergling";"Larva";657;1
"Unit";"Zergling";"Larva";658;1
"Building";"CreepTumor";NA;659;0
"Building";"CreepTumor";NA;659;0
"Building";"CreepTumor";NA;659;0
"Building";"CreepTumor";NA;659;0
"Building";"CreepTumor";NA;659;0
"Building";"CreepTumor";NA;659;0
"Building";"CreepTumorQueen";NA;659;0
"Building";"CreepTumorQueen";NA;659;0
"Building";"SporeCrawler";NA;659;0
"Unit";"Corruptor";"Larva";659;2
"Unit";"Corruptor";"Larva";661;2
"Unit";"Corruptor";"Larva";663;2
"Building";"Extractor";NA;665;0
"Building";"Extractor";NA;665;0
"Building";"Extractor";NA;665;0
"Building";"CreepTumor";NA;665;0
"Unit";"Queen";"Hatchery";665;2
"Building";"CreepTumorQueen";NA;667;0
"Building";"CreepTumorQueen";NA;667;0
"Building";"CreepTumorQueen";NA;670;0
"Building";"CreepTumorQueen";NA;670;0
"Unit";"Corruptor";"Larva";670;2
"Building";"CreepTumor";NA;672;0
"Building";"CreepTumorQueen";NA;672;0
"Building";"CreepTumor";NA;672;0
"Building";"CreepTumor";NA;672;0
"Building";"CreepTumor";NA;672;0
"Building";"CreepTumor";NA;672;0
"Building";"CreepTumor";NA;672;0
"Building";"CreepTumor";NA;672;0
"Building";"CreepTumor";NA;672;0
"Building";"CreepTumor";NA;672;0
"Building";"CreepTumor";NA;672;0
"Unit";"Ultralisk";"Larva";672;6
"Unit";"Zergling";"Larva";678;1
"Unit";"Zergling";"Larva";679;1
"Unit";"Zergling";"Larva";680;1
"Unit";"Zergling";"Larva";681;1
"Unit";"Zergling";"Larva";682;1
"Unit";"Zergling";"Larva";683;1
"Unit";"Zergling";"Larva";684;1
"Unit";"Zergling";"Larva";685;1
"Unit";"Zergling";"Larva";686;1
"Unit";"Zergling";"Larva";687;1
"Unit";"Zergling";"Larva";688;1
"Unit";"Zergling";"Larva";689;1
"Unit";"Zergling";"Larva";690;1
"Unit";"Zergling";"Larva";691;1
"Unit";"Zergling";"Larva";692;1
"Unit";"Zergling";"Larva";693;1
"Unit";"Zergling";"Larva";694;1
"Unit";"Zergling";"Larva";695;1
"Unit";"Zergling";"Larva";696;1
"Unit";"Zergling";"Larva";697;1
"Building";"CreepTumor";NA;709;0
"Building";"CreepTumor";NA;709;0
"Unit";"Corruptor";"Larva";712;2
"Building";"CreepTumor";NA;714;0
"Building";"CreepTumor";NA;714;0
"Building";"CreepTumor";NA;714;0
"Unit";"Corruptor";"Larva";720;2
"Unit";"Corruptor";"Larva";722;2
"Unit";"Corruptor";"Larva";724;2
"Unit";"Corruptor";"Larva";726;2
"Unit";"Corruptor";"Larva";728;2
"Unit";"Corruptor";"Larva";730;2
"Unit";"Corruptor";"Larva";732;2
"Unit";"Corruptor";"Larva";734;2
"Building";"CreepTumor";NA;740;0
"Building";"CreepTumor";NA;740;0
"Building";"CreepTumor";NA;740;0
"Building";"CreepTumor";NA;740;0
"Building";"CreepTumor";NA;740;0
"Building";"CreepTumor";NA;740;0
"Unit";"Corruptor";"Larva";740;2
"Unit";"Corruptor";"Larva";742;2
"Building";"CreepTumor";NA;748;0
"Unit";"Queen";"Hatchery";748;2
"Building";"CreepTumor";NA;750;0
"Building";"CreepTumor";NA;750;0
"Building";"CreepTumor";NA;750;0
"Unit";"Roach";"Larva";750;2
"Unit";"Roach";"Larva";752;2
"Unit";"Roach";"Larva";754;2
"Unit";"Roach";"Larva";756;2
"Unit";"Zergling";"Larva";758;1
"Unit";"Zergling";"Larva";759;1
"Unit";"Zergling";"Larva";760;1
"Unit";"Zergling";"Larva";761;1
"Unit";"Zergling";"Larva";762;1
"Unit";"Zergling";"Larva";763;1
"Unit";"Zergling";"Larva";764;1
"Unit";"Zergling";"Larva";765;1
"Unit";"Zergling";"Larva";766;1
"Unit";"Zergling";"Larva";767;1
"Unit";"Zergling";"Larva";768;1
"Unit";"Zergling";"Larva";769;1
"Unit";"Zergling";"Larva";770;1
"Unit";"Zergling";"Larva";771;1
"Unit";"Zergling";"Larva";772;1
"Unit";"Zergling";"Larva";773;1
"Unit";"Zergling";"Larva";774;1
"Unit";"Zergling";"Larva";775;1
"Unit";"Zergling";"Larva";776;1
"Unit";"Zergling";"Larva";777;1
"Unit";"Zergling";"Larva";778;1
"Unit";"Zergling";"Larva";779;1
"Unit";"Zergling";"Larva";780;1
"Unit";"Zergling";"Larva";781;1
"Unit";"Zergling";"Larva";782;1
"Unit";"Zergling";"Larva";783;1
"Unit";"Zergling";"Larva";784;1
"Unit";"Zergling";"Larva";785;1
"Unit";"Zergling";"Larva";786;1
"Unit";"Zergling";"Larva";787;1
"Building";"CreepTumorQueen";NA;788;0
"Building";"CreepTumorQueen";NA;788;0
"Unit";"Corruptor";"Larva";788;2
"Unit";"Corruptor";"Larva";790;2
"Unit";"Corruptor";"Larva";792;2
"Unit";"Corruptor";"Larva";794;2
"Building";"CreepTumor";NA;796;0
"Building";"CreepTumor";NA;796;0
"Building";"CreepTumor";NA;796;0
"Building";"CreepTumor";NA;796;0
"Building";"CreepTumor";NA;796;0
"Unit";"Baneling";"Zergling";796;0
"Unit";"Baneling";"Zergling";796;0
"Unit";"Baneling";"Zergling";796;0
"Unit";"Baneling";"Zergling";796;0
"Unit";"Baneling";"Zergling";796;0
"Unit";"Baneling";"Zergling";796;0
"Unit";"Baneling";"Zergling";796;0
"Unit";"Baneling";"Zergling";796;0
"Unit";"Baneling";"Zergling";796;0
"Unit";"Baneling";"Zergling";796;0
"Unit";"Baneling";"Zergling";796;0
"Unit";"Baneling";"Zergling";796;0
"Building";"Extractor";NA;796;0
"Building";"CreepTumor";NA;796;0
"Building";"CreepTumor";NA;796;0
"Building";"CreepTumor";NA;796;0
"Building";"CreepTumor";NA;800;0
"Building";"CreepTumor";NA;800;0
"Building";"CreepTumor";NA;800;0
"Unit";"Baneling";"Zergling";800;0
"Unit";"Baneling";"Zergling";800;0
"Unit";"Baneling";"Zergling";800;0
"Unit";"Baneling";"Zergling";800;0
"Unit";"Baneling";"Zergling";800;0
"Unit";"Baneling";"Zergling";800;0
"Unit";"Baneling";"Zergling";800;0
"Unit";"Baneling";"Zergling";800;0
"Unit";"Baneling";"Zergling";800;0
"Unit";"Baneling";"Zergling";800;0
"Unit";"Baneling";"Zergling";800;0
"Unit";"Baneling";"Zergling";800;0
"Building";"Hatchery";NA;800;0
"Building";"CreepTumor";NA;800;0
"Building";"CreepTumor";NA;800;0
"Building";"CreepTumor";NA;800;0
"Building";"Extractor";NA;800;0
"Building";"Extractor";NA;800;0
"Building";"Extractor";NA;800;0
"Unit";"Ultralisk";"Larva";800;6
"Unit";"Ultralisk";"Larva";806;6
"Building";"Hatchery";NA;812;0
"Unit";"Queen";"Hatchery";812;2
"Building";"CreepTumor";NA;814;0
"Building";"CreepTumor";NA;814;0
"Building";"CreepTumorQueen";NA;814;0
"Building";"Hatchery";NA;814;0
"Building";"CreepTumorQueen";NA;814;0
"Building";"CreepTumorQueen";NA;814;0
"Building";"CreepTumorQueen";NA;814;0
"Building";"CreepTumor";NA;814;0
"Building";"CreepTumor";NA;814;0
"Building";"CreepTumor";NA;814;0
"Building";"CreepTumorQueen";NA;814;0
"Unit";"Queen";"Hatchery";814;2
"Upgrade";"SprayZerg";NA;816;0
"Upgrade";"SprayZerg";NA;816;0
"Upgrade";"zerglingmovementspeed";NA;816;0
"Upgrade";"SprayZerg";NA;816;0
"Upgrade";"SprayZerg";NA;816;0
"Upgrade";"SprayZerg";NA;816;0
"Upgrade";"ZergGroundArmorsLevel1";NA;816;0
"Upgrade";"SprayZerg";NA;816;0
"Upgrade";"ZergGroundArmorsLevel2";NA;816;0
"Upgrade";"ZergMeleeWeaponsLevel1";NA;816;0
"Upgrade";"SprayZerg";NA;816;0
"Upgrade";"SprayZerg";NA;816;0
"Upgrade";"InfestorEnergyUpgrade";NA;816;0
"Upgrade";"SprayZerg";NA;816;0
"Upgrade";"SprayZerg";NA;816;0
"Upgrade";"SprayZerg";NA;816;0
"Upgrade";"ZergMeleeWeaponsLevel2";NA;816;0
"Upgrade";"ZergGroundArmorsLevel3";NA;816;0
"Upgrade";"SprayZerg";NA;816;0
"Upgrade";"SprayZerg";NA;816;0
"Upgrade";"zerglingattackspeed";NA;816;0
"Upgrade";"ZergMissileWeaponsLevel1";NA;816;0
"Upgrade";"SprayZerg";NA;816;0
"Upgrade";"SprayZerg";NA;816;0
"Upgrade";"ZergMeleeWeaponsLevel3";NA;816;0
"Upgrade";"SprayZerg";NA;816;0
"Upgrade";"SprayZerg";NA;816;0
"Upgrade";"ZergMissileWeaponsLevel2";NA;816;0
"Upgrade";"SprayZerg";NA;816;0
"Upgrade";"SprayZerg";NA;816;0
"Upgrade";"SprayZerg";NA;816;0
"Upgrade";"SprayZerg";NA;816;0
"Upgrade";"overlordspeed";NA;816;0
"Upgrade";"CentrificalHooks";NA;816;0
"Upgrade";"ZergFlyerWeaponsLevel1";NA;816;0
"Upgrade";"SprayZerg";NA;816;0
"Upgrade";"SprayZerg";NA;816;0
"Upgrade";"SprayZerg";NA;816;0
"Upgrade";"SprayZerg";NA;816;0
"Upgrade";"SprayZerg";NA;816;0
"Upgrade";"ZergFlyerWeaponsLevel2";NA;816;0
"Upgrade";"SprayZerg";NA;816;0
