"Type";"UnitName";"OnBuilding";"TotalSupply";"Supply"
"Unit";"SCV";"Command Center";12;1
"Unit";"SCV";"Command Center";12;1
"Unit";"SCV";"Command Center";13;1
"Building";"SupplyDepot";NA;13;0
"Unit";"SCV";"Command Center";15;1
"Unit";"SCV";"Command Center";16;1
"Unit";"SCV";"Command Center";16;1
"Building";"Barracks";NA;15;0
"Building";"Barracks";NA;15;0
"Unit";"Marine";"Barracks";18;1
"Unit";"Marine";"Barracks";18;1
"Unit";"SCV";"Command Center";20;1
"Unit";"Marine";"Barracks";19;1
"Unit";"Marine";"Barracks";19;1
"Building";"Bunker";NA;18;0
"Unit";"Marine";"Barracks";21;1
"Building";"SupplyDepot";NA;23;0
"Building";"Bunker";NA;23;0
"Building";"Bunker";NA;23;0
"Building";"Refinery";NA;23;0
"Unit";"SCV";"Command Center";24;1
"Building";"Bunker";NA;24;0
"Unit";"Marine";"Barracks";24;1
"Unit";"Marine";"Barracks";24;1
"Unit";"SCV";"Command Center";27;1
"Unit";"Marine";"Barracks";25;1
"Unit";"Marine";"Barracks";25;1
"Unit";"Marine";"Barracks";28;1
"Unit";"Marine";"Barracks";28;1
"Unit";"SCV";"Command Center";32;1
"Unit";"SCV";"Command Center";32;1
"Building";"Refinery";NA;32;0
"Building";"Bunker";NA;32;0
"Unit";"SCV";"Command Center";33;1
"Building";"Factory";NA;32;0
"Unit";"SCV";"Command Center";34;1
"Building";"CommandCenter";NA;30;0
"Unit";"SCV";"Command Center";35;1
"Building";"SupplyDepot";NA;35;0
"Building";"FactoryTechLab";NA;36;0
"Unit";"SCV";"Command Center";37;1
"Building";"Barracks";NA;34;0
"Unit";"SCV";"Command Center";37;1
"Building";"Starport";NA;36;0
"Unit";"SCV";"Command Center";38;1
"Unit";"SCV";"Command Center";39;1
"Unit";"Marine";"Barracks";38;1
"Unit";"SCV";"Command Center";39;1
"Unit";"SCV";"Command Center";40;1
"Unit";"SCV";"Command Center";42;1
"Unit";"SCV";"Command Center";43;1
"Unit";"Marine";"Barracks";42;1
"Building";"Refinery";NA;42;0
"Unit";"Marine";"Barracks";42;1
"Building";"Refinery";NA;42;0
"Unit";"SCV";"Command Center";44;1
"Unit";"SCV";"Command Center";45;1
"Building";"SupplyDepot";NA;44;0
"Building";"Factory";NA;41;0
"Unit";"Banshee";"Starport";42;3
"Unit";"SCV";"Command Center";48;1
"Unit";"SCV";"Command Center";50;1
"Building";"FactoryTechLab";NA;49;0
"Unit";"SCV";"Command Center";53;1
"Building";"FactoryTechLab";NA;53;0
"Unit";"SCV";"Command Center";54;1
"Unit";"Marine";"Barracks";54;1
"Unit";"Marine";"Barracks";54;1
"Unit";"SCV";"Command Center";55;1
"Unit";"SCV";"Command Center";56;1
"Building";"SupplyDepot";NA;56;0
"Unit";"Banshee";"Starport";50;3
"Building";"SupplyDepot";NA;57;0
"Building";"CommandCenter";NA;48;0
"Unit";"SCV";"Command Center";64;1
"Unit";"SCV";"Command Center";64;1
"Unit";"SCV";"Command Center";64;1
"Unit";"SCV";"Command Center";65;1
"Building";"Factory";NA;64;0
"Building";"SupplyDepot";NA;66;0
"Unit";"SCV";"Command Center";66;1
"Unit";"SCV";"Command Center";67;1
"Building";"SupplyDepot";NA;66;0
"Unit";"SCV";"Command Center";68;1
"Unit";"Raven";"Starport";64;2
"Building";"Factory";NA;66;0
"Building";"FactoryReactor";NA;70;0
"Unit";"SCV";"Command Center";73;1
"Unit";"SCV";"Command Center";73;1
"Unit";"SCV";"Command Center";73;1
"Building";"Armory";NA;73;0
"Unit";"SCV";"Command Center";73;1
"Unit";"SCV";"Command Center";74;1
"Unit";"SCV";"Command Center";75;1
"Unit";"Hellion";"Factory";73;2
"Unit";"Hellion";"Factory";73;2
"Building";"FactoryReactor";NA;73;0
"Building";"Factory";NA;73;0
"Unit";"SCV";"Command Center";76;1
"Unit";"SCV";"Command Center";77;1
"Building";"Refinery";NA;77;0
"Unit";"Hellion";"Factory";79;2
"Unit";"Hellion";"Factory";81;2
"Building";"Refinery";NA;83;0
"Unit";"Hellion";"Factory";83;2
"Unit";"Hellion";"Factory";83;2
"Building";"Armory";NA;73;0
"Unit";"SCV";"Command Center";93;1
"Unit";"SCV";"Command Center";93;1
"Unit";"SCV";"Command Center";93;1
"Unit";"Hellion";"Factory";85;2
"Building";"SupplyDepot";NA;89;0
"Building";"SupplyDepot";NA;89;0
"Building";"SupplyDepot";NA;93;0
"Unit";"Hellion";"Factory";93;2
"Unit";"Hellion";"Factory";93;2
"Unit";"Hellion";"Factory";93;2
"Unit";"Hellion";"Factory";93;2
"Unit";"SCV";"Command Center";93;1
"Unit";"Hellion";"Factory";93;2
"Unit";"SCV";"Command Center";98;1
"Unit";"Hellion";"Factory";93;2
"Building";"SupplyDepot";NA;96;0
"Building";"SupplyDepot";NA;98;0
"Unit";"SCV";"Command Center";107;1
"Unit";"SCV";"Command Center";107;1
"Unit";"Hellion";"Factory";98;2
"Unit";"Hellion";"Factory";100;2
"Building";"SupplyDepot";NA;110;0
"Building";"SupplyDepot";NA;112;0
"Building";"SupplyDepot";NA;112;0
"Unit";"Hellion";"Factory";112;2
"Unit";"Hellion";"Factory";118;2
"Unit";"Hellion";"Factory";118;2
"Unit";"Hellion";"Factory";118;2
"Building";"SupplyDepot";NA;120;0
"Upgrade";"TerranVehicleWeaponsLevel1";"Armory";98;0
"Unit";"Hellion";"Factory";122;2
"Unit";"Hellion";"Factory";122;2
"Unit";"Thor";"Factory";118;6
"Building";"CommandCenter";NA;110;0
"Unit";"Hellion";"Factory";126;2
"Unit";"Hellion";"Factory";126;2
"Building";"SupplyDepot";NA;126;0
"Unit";"Hellion";"Factory";126;2
"Unit";"Hellion";"Factory";136;2
"Upgrade";"TerranVehicleAndShipArmorsLevel1";"Armory";118;0
"Unit";"Hellion";"Factory";136;2
"Unit";"Hellion";"Factory";138;2
"Unit";"Hellion";"Factory";140;2
"Unit";"Hellion";"Factory";142;2
"Unit";"Hellion";"Factory";144;2
"Unit";"Hellion";"Factory";150;2
"Unit";"Hellion";"Factory";150;2
"Unit";"Hellion";"Factory";150;2
"Unit";"Hellion";"Factory";152;2
"Unit";"Hellion";"Factory";154;2
"Unit";"Hellion";"Factory";156;2
"Unit";"Hellion";"Factory";158;2
"Unit";"Hellion";"Factory";160;2
"Unit";"Hellion";"Factory";162;2
"Unit";"Hellion";"Factory";164;2
"Unit";"Hellion";"Factory";170;2
"Unit";"Hellion";"Factory";170;2
"Unit";"Hellion";"Factory";170;2
"Unit";"Hellion";"Factory";172;2
"Unit";"Hellion";"Factory";174;2
"Unit";"Hellion";"Factory";176;2
"Unit";"Hellion";"Factory";178;2
"Unit";"Hellion";"Factory";180;2
"Unit";"Hellion";"Factory";182;2
"Unit";"Hellion";"Factory";184;2
