"type";"unit_name";"on_building";"total_supply";"supply"
"Building";"Refinery";NA;14;0
"Building";"Barracks";NA;15;0
"Unit";"Reaper";"Barracks";19;1
"Building";"Refinery";NA;20;0
"Building";"Factory";NA;19;0
"Building";"BarracksReactor";NA;20;0
"Building";"CommandCenter";NA;19;0
"Building";"BarracksTechLab";NA;24;0
"Unit";"Hellion";"Factory";23;2
"Unit";"Hellion";"Factory";23;2
"Building";"Starport";NA;23;0
"Unit";"Hellion";"Factory";30;2
"Unit";"Hellion";"Factory";30;2
"Unit";"Hellion";"Factory";41;2
"Unit";"Hellion";"Factory";42;2
"Building";"Refinery";NA;49;0
"Building";"Refinery";NA;49;0
"Unit";"Hellion";"Factory";51;2
"Unit";"Hellion";"Factory";51;2
"Unit";"Liberator";"Starport";44;3
"Building";"CommandCenter";NA;40;0
"Unit";"Cyclone";"Factory";63;3
"Unit";"Cyclone";"Factory";63;3
"Building";"BarracksTechLab";NA;65;0
"Building";"Armory";NA;54;0
"Building";"Armory";NA;54;0
"Unit";"Hellion";"Factory";67;2
"Unit";"Hellion";"Factory";70;2
"Building";"Factory";NA;63;0
"Building";"Factory";NA;63;0
"Unit";"Hellion";"Factory";76;2
"Unit";"Hellion";"Factory";78;2
"Building";"Refinery";NA;81;0
"Building";"Refinery";NA;81;0
"Unit";"Hellion";"Factory";83;2
"Building";"StarportReactor";NA;81;0
"Unit";"Hellion";"Factory";87;2
"Unit";"Thor";"Factory";81;6
"Unit";"Thor";"Factory";81;6
"Unit";"Hellion";"Factory";91;2
"Unit";"Medivac";"Starport";108;2
"Unit";"Medivac";"Starport";109;2
"Upgrade";"TerranVehicleWeaponsLevel1";"Armory";87;0
"Unit";"Hellion";"Factory";123;2
"Unit";"Hellion";"Factory";123;2
"Building";"EngineeringBay";NA;123;0
"Unit";"Medivac";"Starport";131;2
"Unit";"Medivac";"Starport";131;2
"Unit";"Hellion";"Factory";134;2
"Unit";"Hellion";"Factory";134;2
"Building";"CommandCenter";NA;123;0
"Building";"Refinery";NA;144;0
"Unit";"Medivac";"Starport";140;2
"Unit";"Medivac";"Starport";140;2
"Building";"Refinery";NA;144;0
"Unit";"Hellion";"Factory";144;2
"Unit";"Hellion";"Factory";144;2
"Building";"SensorTower";NA;144;0
"Unit";"Hellion";"Factory";152;2
"Unit";"Medivac";"Starport";148;2
"Unit";"Medivac";"Starport";148;2
"Building";"SensorTower";NA;152;0
"Unit";"Hellion";"Factory";152;2
"Unit";"Hellion";"Factory";152;2
"Upgrade";"TerranVehicleWeaponsLevel2";"Armory";138;0
"Building";"Factory";NA;152;0
"Building";"Factory";NA;152;0
"Unit";"Hellion";"Factory";160;2
"Unit";"Hellion";"Factory";162;2
"Unit";"Hellion";"Factory";162;2
"Unit";"Hellion";"Factory";164;2
"Building";"FactoryTechLab";NA;166;0
"Building";"FactoryTechLab";NA;166;0
"Unit";"Medivac";"Starport";164;2
"Unit";"Medivac";"Starport";164;2
"Unit";"Hellion";"Factory";166;2
"Unit";"Hellion";"Factory";166;2
"Unit";"Hellion";"Factory";169;2
"Building";"Refinery";NA;171;0
"Building";"SensorTower";NA;177;0
"Unit";"Hellion";"Factory";175;2
"Unit";"Hellion";"Factory";177;2
"Unit";"Hellion";"Factory";177;2
"Unit";"Medivac";"Starport";177;2
"Unit";"Medivac";"Starport";177;2
"Unit";"Hellion";"Factory";184;2
"Unit";"Hellion";"Factory";184;2
"Building";"SensorTower";NA;192;0
"Building";"Starport";NA;182;0
"Building";"Starport";NA;182;0
"Unit";"Hellion";"Factory";192;2
"Unit";"Thor";"Factory";182;6
"Unit";"Thor";"Factory";182;6
"Unit";"Medivac";"Starport";188;2
"Unit";"Hellion";"Factory";192;2
"Unit";"Hellion";"Factory";198;2
"Unit";"Hellion";"Factory";198;2
"Unit";"Hellion";"Factory";212;2
"Unit";"Hellion";"Factory";212;2
"Unit";"Hellion";"Factory";214;2
"Unit";"Hellion";"Factory";226;2
"Unit";"Hellion";"Factory";226;2
"Unit";"Thor";"Factory";226;6
"Unit";"Thor";"Factory";226;6
"Upgrade";"TerranVehicleWeaponsLevel3";"Armory";182;0
"Unit";"Hellion";"Factory";230;2
"Unit";"Hellion";"Factory";230;2
"Unit";"Thor";"Factory";226;6
"Unit";"Thor";"Factory";226;6
"Unit";"Hellion";"Factory";242;2
"Unit";"Hellion";"Factory";244;2
"Unit";"Medivac";"Starport";244;2
"Unit";"Medivac";"Starport";244;2
"Unit";"Medivac";"Starport";244;2
"Unit";"Medivac";"Starport";244;2
"Unit";"Thor";"Factory";230;6
"Building";"CommandCenter";NA;230;0
"Unit";"Thor";"Factory";246;6
"Unit";"Thor";"Factory";246;6
"Unit";"Thor";"Factory";258;6
"Unit";"Medivac";"Starport";262;2
"Building";"CommandCenter";NA;246;0
"Unit";"Hellion";"Factory";296;2
"Upgrade";"TerranShipWeaponsLevel1";"Armory";266;0
"Unit";"Thor";"Factory";296;6
"Unit";"Thor";"Factory";296;6
"Unit";"Thor";"Factory";296;6
"Unit";"Hellion";"Factory";316;2
"Unit";"Medivac";"Starport";310;2
"Unit";"Hellion";"Factory";316;2
"Unit";"Hellion";"Factory";316;2
"Unit";"Hellion";"Factory";316;2
