"type";"unit_name";"on_building";"total_supply";"supply"
"Building";"Refinery";NA;14;0
"Building";"Barracks";NA;15;0
"Unit";"Reaper";"Barracks";19;1
"Building";"Refinery";NA;21;0
"Building";"Factory";NA;19;0
"Building";"BarracksReactor";NA;20;0
"Building";"CommandCenter";NA;19;0
"Unit";"Hellion";"Factory";23;2
"Unit";"Hellion";"Factory";23;2
"Building";"Starport";NA;23;0
"Unit";"Reaper";"Barracks";24;1
"Unit";"Hellion";"Factory";25;2
"Unit";"Hellion";"Factory";27;2
"Unit";"Hellion";"Factory";36;2
"Unit";"Medivac";"Starport";30;2
"Unit";"Hellion";"Factory";37;2
"Building";"Armory";NA;36;0
"Unit";"Hellion";"Factory";45;2
"Unit";"Hellion";"Factory";45;2
"Unit";"Liberator";"Starport";45;3
"Building";"BarracksTechLab";NA;52;0
"Building";"FactoryTechLab";NA;52;0
"Building";"CommandCenter";NA;52;0
"Unit";"Hellion";"Factory";61;2
"Unit";"Marine";"Barracks";67;1
"Unit";"Hellion";"Factory";65;2
"Building";"EngineeringBay";NA;65;0
"Building";"StarportReactor";NA;69;0
"Building";"EngineeringBay";NA;72;0
"Building";"Refinery";NA;72;0
"Building";"Refinery";NA;72;0
"Unit";"Marine";"Barracks";74;1
"Building";"Barracks";NA;69;0
"Building";"Barracks";NA;69;0
"Building";"Barracks";NA;69;0
"Building";"Barracks";NA;70;0
"Unit";"Marine";"Barracks";80;1
"Unit";"Medivac";"Starport";77;2
"Unit";"Medivac";"Starport";77;2
"Unit";"Marine";"Barracks";82;1
"Unit";"Marine";"Barracks";82;1
"Building";"Bunker";NA;80;0
"Unit";"Marine";"Barracks";82;1
"Unit";"Marine";"Barracks";82;1
"Unit";"Marine";"Barracks";82;1
"Building";"EngineeringBay";NA;82;0
"Unit";"Marine";"Barracks";82;1
"Building";"Bunker";NA;82;0
"Unit";"Marine";"Barracks";89;1
"Unit";"Marine";"Barracks";90;1
"Unit";"Marine";"Barracks";93;1
"Unit";"Marine";"Barracks";94;1
"Unit";"Marine";"Barracks";95;1
"Unit";"Marine";"Barracks";97;1
"Unit";"Marine";"Barracks";97;1
"Building";"Barracks";NA;83;0
"Building";"Barracks";NA;83;0
"Upgrade";"Stimpack";"TechLab";74;0
"Unit";"Medivac";"Starport";97;2
"Unit";"Marine";"Barracks";104;1
"Unit";"Marine";"Barracks";104;1
"Unit";"Marine";"Barracks";104;1
"Building";"BarracksTechLab";NA;105;0
"Unit";"Medivac";"Starport";104;2
"Unit";"Marine";"Barracks";110;1
"Building";"BarracksReactor";NA;104;0
"Unit";"Marine";"Barracks";111;1
"Unit";"Marine";"Barracks";112;1
"Upgrade";"TerranVehicleWeaponsLevel1";"Armory";82;0
"Building";"BarracksReactor";NA;105;0
"Upgrade";"TerranInfantryArmorsLevel1";"EngineeringBay";91;0
"Unit";"Marine";"Barracks";117;1
"Unit";"Marine";"Barracks";118;1
"Unit";"Marine";"Barracks";119;1
"Unit";"Marine";"Barracks";119;1
"Unit";"Marine";"Barracks";120;1
"Unit";"Marine";"Barracks";120;1
"Unit";"Marine";"Barracks";120;1
"Unit";"Marine";"Barracks";122;1
"Unit";"Marine";"Barracks";122;1
"Unit";"Marauder";"Barracks";120;2
"Unit";"Medivac";"Starport";120;2
"Unit";"Medivac";"Starport";120;2
"Unit";"Marine";"Barracks";122;1
"Unit";"Marine";"Barracks";123;1
"Unit";"Marine";"Barracks";124;1
"Building";"Refinery";NA;123;0
"Building";"Refinery";NA;128;0
"Unit";"Marine";"Barracks";135;1
"Unit";"Marine";"Barracks";135;1
"Unit";"Marine";"Barracks";135;1
"Unit";"Marine";"Barracks";135;1
"Unit";"Marauder";"Barracks";132;2
"Unit";"Marine";"Barracks";142;1
"Unit";"Marine";"Barracks";143;1
"Unit";"Marine";"Barracks";143;1
"Unit";"Marine";"Barracks";143;1
"Unit";"Marine";"Barracks";157;1
"Unit";"Marine";"Barracks";157;1
"Unit";"Marine";"Barracks";157;1
"Unit";"Marine";"Barracks";157;1
"Unit";"Marine";"Barracks";157;1
"Unit";"Marine";"Barracks";157;1
"Unit";"Marine";"Barracks";157;1
"Unit";"Marine";"Barracks";157;1
"Unit";"Marauder";"Barracks";157;2
"Upgrade";"TerranInfantryWeaponsLevel1";"EngineeringBay";119;0
"Unit";"Marine";"Barracks";157;1
"Unit";"Marine";"Barracks";158;1
