"type";"unit_name";"on_building";"total_supply";"supply"
"Building";"Refinery";NA;14;0
"Building";"Barracks";NA;15;0
"Building";"BarracksReactor";NA;19;0
"Unit";"Marine";"Barracks";20;1
"Unit";"Marine";"Barracks";20;1
"Building";"Factory";NA;20;0
"Building";"CommandCenter";NA;19;0
"Unit";"Marine";"Barracks";23;1
"Unit";"Marine";"Barracks";23;1
"Building";"Refinery";NA;23;0
"Building";"Barracks";NA;23;0
"Unit";"Marine";"Barracks";26;1
"Unit";"Marine";"Barracks";26;1
"Building";"FactoryReactor";NA;23;0
"Building";"BarracksTechLab";NA;27;0
"Unit";"Hellion";"Factory";29;2
"Unit";"Hellion";"Factory";30;2
"Building";"Starport";NA;27;0
"Unit";"Hellion";"Factory";34;2
"Unit";"Marine";"Barracks";38;1
"Unit";"Marine";"Barracks";40;1
"Unit";"Marine";"Barracks";40;1
"Building";"Armory";NA;38;0
"Unit";"Hellion";"Factory";46;2
"Unit";"Hellion";"Factory";46;2
"Unit";"Medivac";"Starport";44;2
"Unit";"Marine";"Barracks";47;1
"Unit";"Marine";"Barracks";47;1
"Unit";"Marine";"Barracks";47;1
"Unit";"Hellion";"Factory";50;2
"Unit";"Hellion";"Factory";50;2
"Unit";"Marine";"Barracks";58;1
"Unit";"Marine";"Barracks";58;1
"Unit";"Marine";"Barracks";58;1
"Unit";"Medivac";"Starport";53;2
"Upgrade";"Stimpack";"TechLab";40;0
"Building";"EngineeringBay";NA;69;0
"Building";"Refinery";NA;69;0
"Unit";"Liberator";"Starport";69;3
"Unit";"Marine";"Barracks";71;1
"Unit";"Marine";"Barracks";71;1
"Unit";"Marine";"Barracks";71;1
"Building";"Barracks";NA;69;0
"Building";"Barracks";NA;69;0
"Building";"Barracks";NA;69;0
"Unit";"Marine";"Barracks";80;1
"Unit";"Marine";"Barracks";80;1
"Unit";"Marine";"Barracks";80;1
"Building";"CommandCenter";NA;69;0
"Unit";"Hellion";"Factory";80;2
"Unit";"Hellion";"Factory";80;2
"Unit";"Marine";"Barracks";80;1
"Unit";"Marine";"Barracks";83;1
"Unit";"Marine";"Barracks";83;1
"Unit";"Medivac";"Starport";83;2
"Unit";"Marine";"Barracks";90;1
"Unit";"Marine";"Barracks";90;1
"Unit";"Marauder";"Barracks";90;2
"Building";"BarracksTechLab";NA;92;0
"Building";"EngineeringBay";NA;92;0
"Building";"FactoryTechLab";NA;96;0
"Building";"BarracksReactor";NA;92;0
"Building";"BarracksReactor";NA;92;0
"Unit";"Marine";"Barracks";96;1
"Building";"StarportReactor";NA;92;0
"Unit";"Marine";"Barracks";96;1
"Unit";"Marine";"Barracks";96;1
"Unit";"Marauder";"Barracks";96;2
"Building";"Barracks";NA;96;0
"Unit";"Marine";"Barracks";101;1
"Unit";"Marine";"Barracks";101;1
"Unit";"Marine";"Barracks";101;1
"Unit";"Marine";"Barracks";101;1
"Unit";"Marine";"Barracks";101;1
"Unit";"Marine";"Barracks";101;1
"Unit";"Marauder";"Barracks";101;2
"Unit";"Marauder";"Barracks";101;2
"Unit";"Hellion";"Factory";101;2
"Unit";"Marine";"Barracks";101;1
"Unit";"Marauder";"Barracks";107;2
"Unit";"Marine";"Barracks";113;1
"Unit";"Marine";"Barracks";113;1
"Unit";"Marine";"Barracks";113;1
"Unit";"Marine";"Barracks";113;1
"Unit";"Marine";"Barracks";113;1
"Upgrade";"TerranVehicleWeaponsLevel1";"Armory";96;0
"Upgrade";"TerranInfantryWeaponsLevel1";"EngineeringBay";96;0
"Unit";"Marine";"Barracks";116;1
"Building";"Refinery";NA;116;0
"Unit";"Marauder";"Barracks";116;2
"Unit";"Marine";"Barracks";125;1
"Unit";"Marine";"Barracks";125;1
"Unit";"Marine";"Barracks";125;1
"Unit";"Marine";"Barracks";125;1
"Unit";"Marine";"Barracks";125;1
"Unit";"Medivac";"Starport";116;2
"Unit";"Medivac";"Starport";116;2
"Unit";"Marauder";"Barracks";125;2
"Building";"Factory";NA;116;0
"Unit";"Marine";"Barracks";130;1
"Building";"FactoryTechLab";NA;144;0
"Unit";"Marine";"Barracks";147;1
"Unit";"Marine";"Barracks";147;1
"Unit";"Marine";"Barracks";147;1
"Unit";"Marine";"Barracks";147;1
"Unit";"Marine";"Barracks";147;1
"Unit";"Marine";"Barracks";147;1
"Unit";"Marauder";"Barracks";147;2
"Unit";"Marauder";"Barracks";147;2
"Upgrade";"TerranInfantryArmorsLevel1";"EngineeringBay";127;0
"Building";"Barracks";NA;144;0
"Building";"Barracks";NA;144;0
"Unit";"Marine";"Barracks";157;1
"Unit";"Marine";"Barracks";157;1
"Unit";"Marine";"Barracks";157;1
"Unit";"Marine";"Barracks";157;1
"Unit";"Marine";"Barracks";157;1
"Building";"Barracks";NA;144;0
"Unit";"Marine";"Barracks";157;1
"Unit";"Marine";"Barracks";157;1
"Building";"Barracks";NA;147;0
"Unit";"Marauder";"Barracks";157;2
"Building";"BarracksTechLab";NA;157;0
"Building";"Refinery";NA;157;0
"Building";"CommandCenter";NA;147;0
"Building";"BarracksReactor";NA;157;0
"Unit";"Marine";"Barracks";170;1
"Unit";"Marine";"Barracks";170;1
"Unit";"Marine";"Barracks";170;1
"Unit";"Marine";"Barracks";170;1
"Unit";"Marine";"Barracks";170;1
"Unit";"Marine";"Barracks";170;1
"Unit";"Marine";"Barracks";170;1
"Building";"BarracksTechLab";NA;170;0
"Upgrade";"TerranInfantryWeaponsLevel2";"EngineeringBay";144;0
"Unit";"Marauder";"Barracks";170;2
"Unit";"Marauder";"Barracks";170;2
"Unit";"Marine";"Barracks";180;1
"Building";"BarracksReactor";NA;170;0
"Unit";"Marine";"Barracks";180;1
"Unit";"Marine";"Barracks";180;1
"Unit";"Marine";"Barracks";180;1
"Unit";"Marine";"Barracks";180;1
"Unit";"Marine";"Barracks";180;1
"Unit";"Marine";"Barracks";180;1
"Unit";"Marauder";"Barracks";180;2
"Unit";"Marine";"Barracks";191;1
"Unit";"Marine";"Barracks";191;1
"Unit";"Marine";"Barracks";192;1
"Unit";"Marine";"Barracks";192;1
"Unit";"Marine";"Barracks";192;1
"Unit";"Marine";"Barracks";192;1
"Unit";"Marine";"Barracks";192;1
"Unit";"Marine";"Barracks";192;1
"Unit";"Marine";"Barracks";192;1
"Unit";"Marine";"Barracks";205;1
"Unit";"Marine";"Barracks";205;1
"Unit";"Marine";"Barracks";205;1
"Unit";"Marine";"Barracks";205;1
"Unit";"Marine";"Barracks";205;1
"Unit";"Marine";"Barracks";205;1
"Unit";"Marauder";"Barracks";205;2
"Unit";"Marauder";"Barracks";205;2
"Unit";"Marauder";"Barracks";205;2
"Building";"Refinery";NA;205;0
"Upgrade";"TerranVehicleWeaponsLevel2";"Armory";170;0
"Unit";"Marine";"Barracks";220;1
"Unit";"Marine";"Barracks";220;1
"Unit";"Marine";"Barracks";220;1
"Unit";"Marine";"Barracks";220;1
"Unit";"Marine";"Barracks";220;1
