"type";"unit_name";"on_building";"total_supply";"supply"
"Building";"Barracks";NA;15;0
"Unit";"Marine";"Barracks";19;1
"Building";"Refinery";NA;19;0
"Building";"Refinery";NA;19;0
"Unit";"Marine";"Barracks";20;1
"Unit";"Marine";"Barracks";22;1
"Building";"CommandCenter";NA;19;0
"Building";"Bunker";NA;26;0
"Building";"Factory";NA;25;0
"Building";"BarracksReactor";NA;25;0
"Unit";"Hellion";"Factory";29;2
"Unit";"Hellion";"Factory";29;2
"Building";"Factory";NA;27;0
"Building";"Starport";NA;30;0
"Unit";"Hellion";"Factory";37;2
"Unit";"Hellion";"Factory";37;2
"Building";"BarracksReactor";NA;32;0
"Unit";"Hellion";"Factory";38;2
"Unit";"Hellion";"Factory";44;2
"Unit";"Hellion";"Factory";44;2
"Unit";"Hellion";"Factory";48;2
"Unit";"Hellion";"Factory";49;2
"Unit";"Medivac";"Starport";49;2
"Unit";"Medivac";"Starport";49;2
"Unit";"Hellion";"Factory";58;2
"Unit";"Hellion";"Factory";58;2
"Building";"Armory";NA;54;0
"Unit";"Hellion";"Factory";71;2
"Unit";"Hellion";"Factory";71;2
"Unit";"Hellion";"Factory";71;2
"Building";"Refinery";NA;77;0
"Building";"Refinery";NA;77;0
"Building";"FactoryTechLab";NA;81;0
"Building";"Factory";NA;77;0
"Building";"Factory";NA;77;0
"Unit";"Hellion";"Factory";81;2
"Unit";"Hellion";"Factory";81;2
"Building";"FactoryTechLab";NA;87;0
"Building";"CommandCenter";NA;79;0
"Building";"FactoryReactor";NA;87;0
"Unit";"Hellion";"Factory";87;2
"Unit";"Hellion";"Factory";87;2
"Unit";"Thor";"Factory";87;6
"Upgrade";"TerranVehicleWeaponsLevel1";"Armory";82;0
"Unit";"Hellion";"Factory";97;2
"Unit";"Hellion";"Factory";97;2
"Unit";"Hellion";"Factory";97;2
"Building";"EngineeringBay";NA;97;0
"Building";"Refinery";NA;97;0
"Building";"Refinery";NA;98;0
"Unit";"Thor";"Factory";97;6
"Unit";"Hellion";"Factory";106;2
"Unit";"Hellion";"Factory";106;2
"Unit";"Thor";"Factory";112;6
"Unit";"Hellion";"Factory";120;2
"Building";"Armory";NA;118;0
"Unit";"Hellion";"Factory";131;2
"Unit";"Hellion";"Factory";132;2
"Unit";"Hellion";"Factory";139;2
"Unit";"Hellion";"Factory";139;2
"Unit";"Hellion";"Factory";139;2
"Unit";"Hellion";"Factory";139;2
