"type";"unit_name";"on_building";"total_supply_lag";"supply"
"Building";"Refinery";NA;15;0
"Building";"Barracks";NA;16;0
"Unit";"Reaper";"Barracks";19;1
"Building";"CommandCenter";NA;20;0
"Building";"Factory";NA;20;0
"Building";"BarracksReactor";NA;21;0
"Building";"Refinery";NA;22;0
"Building";"Starport";NA;24;0
"Unit";"Hellion";"Factory";24;2
"Unit";"Hellion";"Factory";26;2
"Building";"BarracksTechLab";NA;29;0
"Unit";"Hellion";"Factory";30;2
"Unit";"Hellion";"Factory";32;2
"Unit";"Hellion";"Factory";40;2
"Unit";"Hellion";"Factory";42;2
"Unit";"Marauder";"Barracks";44;2
"Unit";"Medivac";"Starport";47;2
"Building";"Armory";NA;50;0
"Unit";"Hellion";"Factory";52;2
"Unit";"Hellion";"Factory";54;2
"Unit";"Banshee";"Starport";59;3
"Unit";"Hellion";"Factory";62;2
"Building";"CommandCenter";NA;66;0
"Unit";"Hellion";"Factory";68;2
"Unit";"Hellion";"Factory";70;2
"Unit";"Banshee";"Starport";74;3
"Unit";"Hellion";"Factory";77;2
"Building";"BarracksTechLab";NA;79;0
"Building";"Barracks";NA;79;0
"Building";"Barracks";NA;79;0
"Unit";"Hellion";"Factory";79;2
"Building";"EngineeringBay";NA;83;0
"Building";"EngineeringBay";NA;85;0
"Building";"Refinery";NA;87;0
"Building";"Refinery";NA;87;0
"Building";"FactoryReactor";NA;89;0
"Unit";"Marine";"Barracks";89;1
"Building";"Barracks";NA;90;0
"Building";"Barracks";NA;90;0
"Building";"StarportReactor";NA;90;0
"Building";"BarracksReactor";NA;92;0
"Unit";"Marine";"Barracks";93;1
"Unit";"Marine";"Barracks";94;1
"Unit";"Marine";"Barracks";95;1
"Upgrade";"Stimpack";"TechLab";99;0
"Unit";"Marine";"Barracks";101;1
"Building";"Bunker";NA;102;0
"Upgrade";"TerranInfantryWeaponsLevel1";"EngineeringBay";102;0
"Unit";"Marine";"Barracks";102;1
"Unit";"Marine";"Barracks";103;1
"Unit";"Medivac";"Starport";106;2
"Unit";"Marine";"Barracks";108;1
"Unit";"Medivac";"Starport";109;2
"Unit";"Marine";"Barracks";111;1
"Unit";"Marine";"Barracks";112;1
"Unit";"Marine";"Barracks";113;1
"Unit";"Marine";"Barracks";115;1
"Building";"BarracksReactor";NA;116;0
"Building";"BarracksReactor";NA;116;0
"Unit";"Marine";"Barracks";118;1
"Unit";"Marine";"Barracks";121;1
"Unit";"Marine";"Barracks";122;1
"Unit";"Marine";"Barracks";123;1
"Unit";"Marine";"Barracks";124;1
"Unit";"Medivac";"Starport";125;2
"Unit";"Marine";"Barracks";127;1
"Building";"Refinery";NA;128;0
"Unit";"Marine";"Barracks";128;1
"Unit";"Marine";"Barracks";129;1
"Unit";"Marine";"Barracks";130;1
"Unit";"Marine";"Barracks";131;1
"Unit";"Marine";"Barracks";132;1
"Unit";"Marine";"Barracks";133;1
"Unit";"Marine";"Barracks";134;1
"Unit";"Marine";"Barracks";135;1
"Unit";"Medivac";"Starport";136;2
"Unit";"Marine";"Barracks";138;1
"Unit";"Marine";"Barracks";139;1
"Unit";"Marine";"Barracks";140;1
"Unit";"Marine";"Barracks";141;1
"Unit";"Marine";"Barracks";142;1
"Unit";"Liberator";"Starport";143;3
"Unit";"Marine";"Barracks";146;1
"Building";"Barracks";NA;147;0
"Building";"Barracks";NA;147;0
"Building";"CommandCenter";NA;147;0
"Building";"SensorTower";NA;147;0
"Building";"Barracks";NA;147;0
"Unit";"Marine";"Barracks";147;1
"Unit";"Marauder";"Barracks";148;2
"Unit";"Marine";"Barracks";150;1
"Unit";"Medivac";"Starport";151;2
"Unit";"Marine";"Barracks";153;1
"Unit";"Marine";"Barracks";154;1
"Unit";"Marine";"Barracks";155;1
"Unit";"Marine";"Barracks";156;1
"Upgrade";"TerranVehicleWeaponsLevel1";"Armory";157;0
"Unit";"Marine";"Barracks";157;1
"Unit";"Marauder";"Barracks";158;2
"Unit";"Marine";"Barracks";160;1
"Unit";"Marine";"Barracks";161;1
"Unit";"Marine";"Barracks";162;1
"Unit";"Marine";"Barracks";163;1
"Unit";"Marine";"Barracks";164;1
"Unit";"Marine";"Barracks";165;1
"Unit";"Marine";"Barracks";166;1
"Unit";"Medivac";"Starport";167;2
"Unit";"Marine";"Barracks";169;1
"Building";"BarracksTechLab";NA;170;0
"Building";"BarracksTechLab";NA;170;0
"Building";"BarracksTechLab";NA;170;0
"Unit";"Marauder";"Barracks";170;2
"Unit";"Marine";"Barracks";172;1
"Unit";"Marine";"Barracks";173;1
"Upgrade";"TerranInfantryWeaponsLevel2";"EngineeringBay";174;0
"Unit";"Marine";"Barracks";174;1
"Unit";"Medivac";"Starport";175;2
"Unit";"Marine";"Barracks";177;1
"Unit";"Marine";"Barracks";178;1
"Unit";"Marine";"Barracks";179;1
"Unit";"Marauder";"Barracks";180;2
"Unit";"Marauder";"Barracks";182;2
"Unit";"Marine";"Barracks";184;1
"Unit";"Marine";"Barracks";185;1
"Building";"Factory";NA;186;0
"Building";"Refinery";NA;186;0
"Unit";"Marauder";"Barracks";186;2
"Unit";"Marine";"Barracks";188;1
"Unit";"Marine";"Barracks";189;1
"Unit";"Marine";"Barracks";190;1
"Unit";"Marine";"Barracks";191;1
"Unit";"Marine";"Barracks";192;1
"Unit";"Marine";"Barracks";193;1
"Unit";"Marine";"Barracks";194;1
"Unit";"Marauder";"Barracks";195;2
"Building";"MissileTurret";NA;197;0
"Unit";"Marauder";"Barracks";197;2
"Unit";"Marine";"Barracks";199;1
"Unit";"Marauder";"Barracks";200;2
"Unit";"Marauder";"Barracks";202;2
"Unit";"Marine";"Barracks";204;1
"Unit";"Marine";"Barracks";208;1
"Unit";"Marauder";"Barracks";209;2
"Unit";"Marine";"Barracks";211;1
"Unit";"Marine";"Barracks";212;1
"Unit";"Marauder";"Barracks";213;2
"Unit";"Marine";"Barracks";215;1
"Unit";"Marine";"Barracks";216;1
"Unit";"Marine";"Barracks";217;1
"Unit";"Marine";"Barracks";218;1
"Unit";"Marine";"Barracks";219;1
"Unit";"Marine";"Barracks";220;1
"Unit";"Marine";"Barracks";221;1
"Unit";"Marauder";"Barracks";222;2
"Unit";"Marine";"Barracks";224;1
"Unit";"Marauder";"Barracks";225;2
"Unit";"Liberator";"Starport";227;3
"Unit";"Liberator";"Starport";230;3
"Unit";"Marauder";"Barracks";233;2
"Unit";"Marine";"Barracks";235;1
"Unit";"Marine";"Barracks";236;1
"Unit";"Marine";"Barracks";237;1
"Unit";"Marine";"Barracks";238;1
"Building";"GhostAcademy";NA;239;0
"Building";"Refinery";NA;239;0
"Building";"Refinery";NA;239;0
"Unit";"Marine";"Barracks";239;1
"Unit";"Marine";"Barracks";240;1
"Unit";"Marine";"Barracks";241;1
"Unit";"Marauder";"Barracks";242;2
"Unit";"Marauder";"Barracks";244;2
"Unit";"Marauder";"Barracks";246;2
"Unit";"Marine";"Barracks";248;1
"Unit";"Marine";"Barracks";249;1
"Unit";"Marine";"Barracks";250;1
"Unit";"Marine";"Barracks";251;1
"Unit";"Marine";"Barracks";252;1
"Unit";"Marine";"Barracks";253;1
"Unit";"Marine";"Barracks";254;1
"Unit";"Marine";"Barracks";255;1
"Unit";"Marine";"Barracks";256;1
"Upgrade";"SprayTerran";NA;257;0
"Upgrade";"SprayTerran";NA;257;0
"Upgrade";"PunisherGrenades";NA;257;0
"Upgrade";"SprayTerran";NA;257;0
"Upgrade";"BansheeCloak";NA;257;0
"Upgrade";"SprayTerran";NA;257;0
"Upgrade";"TerranInfantryArmorsLevel1";NA;257;0
"Upgrade";"SprayTerran";NA;257;0
"Upgrade";"SprayTerran";NA;257;0
"Upgrade";"ShieldWall";NA;257;0
"Upgrade";"TerranInfantryArmorsLevel2";NA;257;0
