"type";"unit_name";"on_building";"total_supply";"supply"
"Building";"Refinery";NA;15;0
"Building";"Barracks";NA;15;0
"Unit";"Reaper";"Barracks";19;1
"Unit";"Marine";"Barracks";19;1
"Building";"Refinery";NA;22;0
"Building";"CommandCenter";NA;19;0
"Building";"Factory";NA;21;0
"Building";"BarracksReactor";NA;22;0
"Building";"GhostAcademy";NA;24;0
"Unit";"Hellion";"Factory";26;2
"Building";"BarracksTechLab";NA;26;0
"Unit";"Hellion";"Factory";26;2
"Unit";"Hellion";"Factory";27;2
"Unit";"Hellion";"Factory";29;2
"Unit";"Hellion";"Factory";39;2
"Unit";"Hellion";"Factory";39;2
"Unit";"Hellion";"Factory";40;2
"Unit";"Hellion";"Factory";42;2
"Building";"Armory";NA;44;0
"Unit";"Cyclone";"Factory";49;3
"Building";"Refinery";NA;51;0
"Building";"CommandCenter";NA;45;0
"Building";"Factory";NA;56;0
"Unit";"Cyclone";"Factory";57;3
"Unit";"Cyclone";"Factory";57;3
"Building";"Refinery";NA;57;0
"Unit";"Hellion";"Factory";59;2
"Unit";"Hellion";"Factory";62;2
"Building";"Factory";NA;57;0
"Building";"BarracksTechLab";NA;66;0
"Upgrade";"TerranVehicleWeaponsLevel1";"Armory";57;0
"Building";"Starport";NA;66;0
"Building";"BarracksTechLab";NA;76;0
"Unit";"Hellion";"Factory";76;2
"Unit";"Hellion";"Factory";76;2
"Unit";"Hellion";"Factory";76;2
"Unit";"Hellion";"Factory";78;2
"Unit";"Hellion";"Factory";84;2
"Unit";"Hellion";"Factory";84;2
"Unit";"Hellion";"Factory";90;2
"Unit";"Hellion";"Factory";90;2
"Building";"Refinery";NA;90;0
"Building";"Refinery";NA;92;0
"Unit";"Hellion";"Factory";94;2
"Unit";"Hellion";"Factory";94;2
"Unit";"Hellion";"Factory";94;2
"Unit";"Hellion";"Factory";96;2
"Unit";"Raven";"Starport";94;2
"Upgrade";"TerranVehicleWeaponsLevel2";"Armory";90;0
"Unit";"Hellion";"Factory";99;2
"Unit";"Hellion";"Factory";103;2
"Building";"Armory";NA;98;0
"Unit";"Hellion";"Factory";108;2
"Unit";"Hellion";"Factory";110;2
"Building";"CommandCenter";NA;94;0
"Unit";"Hellion";"Factory";112;2
"Building";"EngineeringBay";NA;112;0
"Building";"Factory";NA;112;0
"Building";"Factory";NA;112;0
"Building";"MissileTurret";NA;124;0
"Building";"MissileTurret";NA;124;0
"Building";"FactoryTechLab";NA;124;0
"Building";"Refinery";NA;125;0
"Building";"FactoryReactor";NA;125;0
"Unit";"Hellion";"Factory";127;2
"Unit";"Hellion";"Factory";127;2
"Unit";"Hellion";"Factory";127;2
"Unit";"Hellion";"Factory";127;2
"Unit";"Hellion";"Factory";127;2
"Unit";"Hellion";"Factory";129;2
"Unit";"Hellion";"Factory";131;2
"Building";"Starport";NA;135;0
"Unit";"Hellion";"Factory";137;2
"Unit";"Hellion";"Factory";137;2
"Unit";"Hellion";"Factory";143;2
"Unit";"Hellion";"Factory";143;2
"Unit";"Hellion";"Factory";143;2
"Building";"FusionCore";NA;135;0
"Unit";"Hellion";"Factory";146;2
"Unit";"Hellion";"Factory";148;2
"Unit";"Hellion";"Factory";150;2
"Unit";"Hellion";"Factory";152;2
"Unit";"Hellion";"Factory";154;2
"Upgrade";"TerranVehicleWeaponsLevel3";"Armory";127;0
"Unit";"Hellion";"Factory";166;2
"Unit";"Hellion";"Factory";166;2
"Unit";"Hellion";"Factory";166;2
"Building";"StarportReactor";NA;166;0
"Building";"MissileTurret";NA;178;0
"Building";"MissileTurret";NA;181;0
"Building";"Refinery";NA;181;0
"Unit";"Hellion";"Factory";186;2
"Unit";"Hellion";"Factory";186;2
"Unit";"Hellion";"Factory";186;2
"Unit";"Hellion";"Factory";186;2
"Unit";"Hellion";"Factory";186;2
"Unit";"Raven";"Starport";186;2
"Unit";"Hellion";"Factory";201;2
"Unit";"Hellion";"Factory";201;2
"Unit";"Hellion";"Factory";201;2
"Unit";"Hellion";"Factory";201;2
"Unit";"Hellion";"Factory";203;2
"Unit";"Hellion";"Factory";205;2
"Unit";"Hellion";"Factory";207;2
"Unit";"Hellion";"Factory";211;2
"Building";"CommandCenter";NA;188;0
"Upgrade";"TerranShipWeaponsLevel1";"Armory";187;0
"Building";"Refinery";NA;219;0
"Unit";"Hellion";"Factory";219;2
"Unit";"Hellion";"Factory";219;2
"Unit";"Hellion";"Factory";219;2
"Unit";"Hellion";"Factory";219;2
"Unit";"Hellion";"Factory";227;2
"Unit";"Hellion";"Factory";227;2
"Unit";"Hellion";"Factory";227;2
"Unit";"Hellion";"Factory";227;2
"Unit";"Raven";"Starport";219;2
"Unit";"Liberator";"Starport";223;3
"Unit";"Liberator";"Starport";225;3
"Unit";"Hellion";"Factory";244;2
"Unit";"Hellion";"Factory";244;2
"Unit";"Liberator";"Starport";244;3
"Unit";"Hellion";"Factory";248;2
"Unit";"Hellion";"Factory";248;2
"Unit";"Hellion";"Factory";248;2
"Unit";"Hellion";"Factory";248;2
"Unit";"Hellion";"Factory";251;2
"Unit";"Hellion";"Factory";253;2
"Unit";"Hellion";"Factory";255;2
"Unit";"Hellion";"Factory";257;2
"Unit";"Hellion";"Factory";266;2
"Unit";"Hellion";"Factory";266;2
"Unit";"Hellion";"Factory";274;2
"Unit";"Hellion";"Factory";274;2
"Unit";"Hellion";"Factory";274;2
"Unit";"Hellion";"Factory";274;2
"Unit";"Hellion";"Factory";274;2
"Unit";"Hellion";"Factory";274;2
"Unit";"Hellion";"Factory";274;2
"Unit";"Banshee";"Starport";270;3
"Unit";"Hellion";"Factory";274;2
"Unit";"Hellion";"Factory";276;2
"Unit";"Hellion";"Factory";278;2
"Unit";"Hellion";"Factory";280;2
"Building";"Refinery";NA;291;0
"Building";"Refinery";NA;291;0
"Unit";"Hellion";"Factory";291;2
"Unit";"Hellion";"Factory";291;2
"Unit";"Banshee";"Starport";288;3
"Unit";"Hellion";"Factory";299;2
"Unit";"Hellion";"Factory";299;2
"Unit";"Banshee";"Starport";308;3
"Unit";"Liberator";"Starport";313;3
"Unit";"Liberator";"Starport";315;3
"Unit";"Hellion";"Factory";323;2
"Unit";"Hellion";"Factory";323;2
"Unit";"Hellion";"Factory";323;2
"Unit";"Hellion";"Factory";323;2
"Unit";"Hellion";"Factory";323;2
"Building";"Refinery";NA;332;0
"Unit";"Hellion";"Factory";332;2
"Building";"Refinery";NA;334;0
"Unit";"Hellion";"Factory";334;2
"Unit";"Hellion";"Factory";336;2
"Unit";"Liberator";"Starport";342;3
"Building";"Starport";NA;354;0
"Building";"Starport";NA;354;0
"Unit";"Hellion";"Factory";357;2
"Unit";"Hellion";"Factory";357;2
"Unit";"Hellion";"Factory";357;2
"Unit";"Hellion";"Factory";357;2
"Unit";"Hellion";"Factory";357;2
"Unit";"Hellion";"Factory";361;2
"Unit";"Hellion";"Factory";361;2
"Unit";"Hellion";"Factory";372;2
"Unit";"Hellion";"Factory";372;2
"Unit";"Hellion";"Factory";372;2
"Unit";"Hellion";"Factory";372;2
"Unit";"Hellion";"Factory";372;2
"Unit";"Hellion";"Factory";374;2
"Unit";"Hellion";"Factory";380;2
"Unit";"Hellion";"Factory";380;2
"Unit";"Hellion";"Factory";380;2
"Unit";"Hellion";"Factory";382;2
"Unit";"Hellion";"Factory";392;2
"Unit";"Hellion";"Factory";392;2
"Unit";"Hellion";"Factory";392;2
