"type";"unit_name";"on_building";"total_supply";"supply"
"Building";"Refinery";NA;14;0
"Building";"Barracks";NA;15;0
"Unit";"Reaper";"Barracks";19;1
"Building";"Refinery";NA;20;0
"Building";"Factory";NA;19;0
"Building";"BarracksReactor";NA;20;0
"Building";"CommandCenter";NA;19;0
"Unit";"Hellion";"Factory";24;2
"Building";"BarracksTechLab";NA;24;0
"Unit";"Hellion";"Factory";24;2
"Building";"Starport";NA;23;0
"Unit";"Hellion";"Factory";27;2
"Unit";"Hellion";"Factory";31;2
"Building";"BarracksTechLab";NA;31;0
"Unit";"Hellion";"Factory";31;2
"Unit";"Banshee";"Starport";34;3
"Unit";"Cyclone";"Factory";44;3
"Unit";"Cyclone";"Factory";44;3
"Building";"Armory";NA;43;0
"Building";"BarracksTechLab";NA;61;0
"Building";"Refinery";NA;60;0
"Building";"Starport";NA;59;0
"Unit";"Hellion";"Factory";63;2
"Unit";"Hellion";"Factory";63;2
"Unit";"Banshee";"Starport";61;3
"Building";"Refinery";NA;65;0
"Building";"CommandCenter";NA;59;0
"Unit";"Hellion";"Factory";75;2
"Unit";"Hellion";"Factory";75;2
"Unit";"Banshee";"Starport";66;3
"Unit";"Banshee";"Starport";72;3
"Unit";"Hellion";"Factory";78;2
"Unit";"Hellion";"Factory";80;2
"Building";"EngineeringBay";NA;87;0
"Unit";"Hellion";"Factory";95;2
"Unit";"Hellion";"Factory";95;2
"Unit";"Banshee";"Starport";87;3
"Building";"Armory";NA;87;0
"Unit";"Banshee";"Starport";87;3
"Unit";"Hellion";"Factory";97;2
"Unit";"Hellion";"Factory";99;2
"Building";"Factory";NA;96;0
"Building";"Factory";NA;96;0
"Building";"Factory";NA;96;0
"Upgrade";"TerranShipWeaponsLevel1";"Armory";87;0
"Building";"CommandCenter";NA;95;0
"Unit";"Hellion";"Factory";114;2
"Building";"Refinery";NA;116;0
"Unit";"Banshee";"Starport";108;3
"Unit";"Banshee";"Starport";108;3
"Building";"Refinery";NA;116;0
"Building";"FactoryTechLab";NA;121;0
"Building";"FactoryTechLab";NA;121;0
"Unit";"Hellion";"Factory";121;2
"Unit";"Hellion";"Factory";121;2
"Unit";"Hellion";"Factory";141;2
"Unit";"Hellion";"Factory";141;2
"Unit";"Hellion";"Factory";141;2
"Unit";"Hellion";"Factory";141;2
"Unit";"Hellion";"Factory";141;2
"Unit";"Hellion";"Factory";144;2
"Unit";"Hellion";"Factory";146;2
"Unit";"Hellion";"Factory";148;2
"Unit";"Hellion";"Factory";150;2
"Unit";"Banshee";"Starport";142;3
"Unit";"Banshee";"Starport";142;3
"Building";"Refinery";NA;157;0
"Building";"Refinery";NA;157;0
"Unit";"Hellion";"Factory";157;2
"Unit";"Hellion";"Factory";159;2
"Unit";"Hellion";"Factory";176;2
"Unit";"Hellion";"Factory";178;2
"Upgrade";"TerranShipWeaponsLevel2";"Armory";141;0
"Unit";"Hellion";"Factory";181;2
"Unit";"Hellion";"Factory";183;2
"Unit";"Banshee";"Starport";180;3
"Unit";"Banshee";"Starport";180;3
"Unit";"Hellion";"Factory";190;2
"Unit";"Hellion";"Factory";192;2
"Building";"MissileTurret";NA;194;0
"Building";"SensorTower";NA;200;0
"Building";"MissileTurret";NA;200;0
"Building";"MissileTurret";NA;201;0
"Building";"MissileTurret";NA;201;0
"Building";"MissileTurret";NA;202;0
"Unit";"Hellion";"Factory";201;2
"Building";"Factory";NA;186;0
"Building";"Factory";NA;186;0
"Building";"Factory";NA;187;0
"Unit";"Hellion";"Factory";203;2
"Unit";"Raven";"Starport";202;2
"Unit";"Raven";"Starport";203;2
"Building";"FactoryTechLab";NA;215;0
"Unit";"Hellion";"Factory";215;2
"Unit";"Hellion";"Factory";215;2
"Building";"CommandCenter";NA;200;0
"Building";"Refinery";NA;217;0
"Building";"FactoryReactor";NA;216;0
"Unit";"Hellion";"Factory";221;2
"Unit";"Hellion";"Factory";223;2
"Building";"FactoryReactor";NA;217;0
"Unit";"Banshee";"Starport";217;3
"Building";"Refinery";NA;225;0
"Unit";"Hellion";"Factory";225;2
"Unit";"Hellion";"Factory";225;2
"Unit";"Hellion";"Factory";229;2
"Unit";"Hellion";"Factory";229;2
"Unit";"Hellion";"Factory";229;2
"Building";"MissileTurret";NA;232;0
"Building";"MissileTurret";NA;232;0
"Unit";"Hellion";"Factory";229;2
"Building";"MissileTurret";NA;232;0
"Unit";"Hellion";"Factory";229;2
"Building";"MissileTurret";NA;232;0
"Building";"MissileTurret";NA;232;0
"Building";"SensorTower";NA;232;0
"Building";"MissileTurret";NA;232;0
"Building";"MissileTurret";NA;232;0
"Building";"MissileTurret";NA;240;0
"Building";"MissileTurret";NA;242;0
"Unit";"Hellion";"Factory";232;2
"Unit";"Hellion";"Factory";234;2
"Unit";"Hellion";"Factory";236;2
"Unit";"Hellion";"Factory";246;2
"Unit";"Hellion";"Factory";246;2
"Unit";"Hellion";"Factory";246;2
"Unit";"Raven";"Starport";242;2
"Unit";"Raven";"Starport";242;2
"Unit";"Hellion";"Factory";252;2
"Building";"CommandCenter";NA;229;0
"Building";"MissileTurret";NA;267;0
"Building";"MissileTurret";NA;267;0
"Building";"MissileTurret";NA;267;0
"Building";"MissileTurret";NA;267;0
"Building";"MissileTurret";NA;267;0
"Building";"MissileTurret";NA;267;0
"Building";"MissileTurret";NA;267;0
"Unit";"Raven";"Starport";267;2
"Unit";"Raven";"Starport";267;2
"Unit";"Thor";"Factory";267;6
"Building";"Refinery";NA;267;0
"Building";"Refinery";NA;267;0
"Unit";"Cyclone";"Factory";267;3
"Unit";"Thor";"Factory";267;6
"Building";"MissileTurret";NA;280;0
"Building";"CommandCenter";NA;267;0
"Upgrade";"TerranShipWeaponsLevel3";"Armory";267;0
"Building";"Starport";NA;280;0
"Unit";"Hellion";"Factory";286;2
"Unit";"Hellion";"Factory";286;2
"Unit";"Hellion";"Factory";286;2
"Unit";"Hellion";"Factory";286;2
"Unit";"Hellion";"Factory";286;2
"Building";"Starport";NA;286;0
"Building";"Starport";NA;286;0
"Building";"Starport";NA;286;0
"Building";"Starport";NA;286;0
"Building";"Starport";NA;286;0
"Unit";"Thor";"Factory";286;6
"Unit";"Thor";"Factory";286;6
"Unit";"Thor";"Factory";286;6
"Unit";"Thor";"Factory";286;6
"Unit";"Raven";"Starport";286;2
"Unit";"Raven";"Starport";286;2
"Unit";"Thor";"Factory";314;6
"Unit";"Thor";"Factory";320;6
"Unit";"Thor";"Factory";326;6
"Unit";"Thor";"Factory";332;6
"Unit";"Raven";"Starport";339;2
"Unit";"Raven";"Starport";341;2
"Unit";"Thor";"Factory";355;6
"Unit";"Hellion";"Factory";403;2
"Unit";"Hellion";"Factory";403;2
"Unit";"Hellion";"Factory";403;2
"Unit";"Hellion";"Factory";403;2
"Unit";"Hellion";"Factory";403;2
"Unit";"Hellion";"Factory";403;2
"Unit";"Hellion";"Factory";403;2
"Unit";"Hellion";"Factory";403;2
"Unit";"Hellion";"Factory";403;2
"Unit";"Hellion";"Factory";403;2
"Building";"Refinery";NA;408;0
"Building";"Refinery";NA;408;0
"Unit";"Hellion";"Factory";411;2
"Unit";"Hellion";"Factory";413;2
"Unit";"Hellion";"Factory";415;2
"Unit";"Hellion";"Factory";417;2
"Unit";"Hellion";"Factory";417;2
"Unit";"Hellion";"Factory";421;2
"Building";"Refinery";NA;431;0
"Building";"Refinery";NA;431;0
"Unit";"Hellion";"Factory";431;2
"Unit";"Hellion";"Factory";431;2
"Unit";"Hellion";"Factory";431;2
"Building";"SensorTower";NA;431;0
"Building";"SensorTower";NA;431;0
"Building";"MissileTurret";NA;431;0
"Building";"MissileTurret";NA;433;0
"Unit";"Hellion";"Factory";443;2
"Unit";"Hellion";"Factory";443;2
"Unit";"Hellion";"Factory";449;2
"Unit";"Hellion";"Factory";449;2
"Building";"StarportTechLab";NA;453;0
"Building";"StarportTechLab";NA;453;0
"Building";"StarportTechLab";NA;453;0
"Building";"StarportTechLab";NA;453;0
"Building";"StarportTechLab";NA;453;0
"Building";"StarportTechLab";NA;457;0
"Unit";"Raven";"Starport";449;2
"Unit";"Raven";"Starport";449;2
"Unit";"Thor";"Factory";457;6
"Unit";"Thor";"Factory";457;6
"Upgrade";"TerranVehicleWeaponsLevel1";"Armory";449;0
"Unit";"Raven";"Starport";457;2
"Unit";"Raven";"Starport";459;2
"Unit";"Raven";"Starport";461;2
"Unit";"Raven";"Starport";461;2
"Unit";"Hellion";"Factory";461;2
"Building";"CommandCenter";NA;457;0
"Unit";"Raven";"Starport";461;2
"Unit";"Hellion";"Factory";483;2
"Unit";"Hellion";"Factory";483;2
"Unit";"Hellion";"Factory";483;2
"Unit";"Hellion";"Factory";483;2
"Unit";"Hellion";"Factory";483;2
"Unit";"Hellion";"Factory";483;2
"Unit";"Hellion";"Factory";483;2
"Unit";"Hellion";"Factory";483;2
"Unit";"Hellion";"Factory";483;2
"Unit";"Hellion";"Factory";483;2
"Unit";"Raven";"Starport";477;2
"Unit";"Raven";"Starport";477;2
"Unit";"Hellion";"Factory";485;2
"Unit";"Hellion";"Factory";487;2
"Unit";"Hellion";"Factory";489;2
"Unit";"Hellion";"Factory";489;2
"Unit";"Hellion";"Factory";489;2
"Unit";"Hellion";"Factory";495;2
"Unit";"Hellion";"Factory";497;2
"Unit";"Hellion";"Factory";497;2
