"Type";"UnitName";"OnBuilding";"TotalSupply";"Supply"
"Unit";"SCV";"Command Center";12;1
"Unit";"SCV";"Command Center";12;1
"Unit";"SCV";"Command Center";13;1
"Building";"SupplyDepot";NA;13;0
"Unit";"SCV";"Command Center";15;1
"Unit";"SCV";"Command Center";15;1
"Building";"Refinery";NA;15;0
"Unit";"SCV";"Command Center";16;1
"Unit";"SCV";"Command Center";17;1
"Building";"Barracks";NA;15;0
"Unit";"Reaper";"Barracks";19;1
"Unit";"SCV";"Command Center";19;1
"Building";"SupplyDepot";NA;19;0
"Unit";"Marine";"Barracks";19;1
"Unit";"SCV";"Command Center";21;1
"Unit";"SCV";"Command Center";23;1
"Unit";"SCV";"Command Center";23;1
"Building";"CommandCenter";NA;19;0
"Building";"BarracksReactor";NA;23;0
"Unit";"SCV";"Command Center";24;1
"Building";"Factory";NA;23;0
"Unit";"SCV";"Command Center";25;1
"Unit";"SCV";"Command Center";26;1
"Unit";"SCV";"Command Center";27;1
"Building";"Refinery";NA;27;0
"Unit";"SCV";"Command Center";28;1
"Building";"Starport";NA;26;0
"Unit";"SCV";"Command Center";28;1
"Unit";"Hellion";"Factory";28;2
"Unit";"Hellion";"Factory";28;2
"Unit";"SCV";"Command Center";29;1
"Building";"CommandCenter";NA;25;0
"Unit";"SCV";"Command Center";36;1
"Unit";"SCV";"Command Center";36;1
"Building";"BarracksTechLab";NA;36;0
"Unit";"Hellion";"Factory";35;2
"Unit";"Hellion";"Factory";35;2
"Unit";"SCV";"Command Center";36;1
"Unit";"SCV";"Command Center";37;1
"Unit";"SCV";"Command Center";42;1
"Unit";"SCV";"Command Center";43;1
"Building";"EngineeringBay";NA;42;0
"Building";"EngineeringBay";NA;42;0
"Unit";"SCV";"Command Center";44;1
"Unit";"SCV";"Command Center";45;1
"Unit";"SCV";"Command Center";46;1
"Unit";"SCV";"Command Center";48;1
"Unit";"SCV";"Command Center";48;1
"Building";"StarportReactor";NA;44;0
"Unit";"SCV";"Command Center";49;1
"Unit";"SCV";"Command Center";49;1
"Building";"FactoryReactor";NA;46;0
"Unit";"SCV";"Command Center";51;1
"Building";"Barracks";NA;45;0
"Unit";"SCV";"Command Center";51;1
"Unit";"Marine";"Barracks";51;1
"Building";"SupplyDepot";NA;51;0
"Unit";"SCV";"Command Center";52;1
"Building";"Refinery";NA;51;0
"Building";"Barracks";NA;46;0
"Building";"SupplyDepot";NA;51;0
"Building";"Refinery";NA;51;0
"Unit";"SCV";"Command Center";53;1
"Unit";"SCV";"Command Center";54;1
"Unit";"SCV";"Command Center";57;1
"Unit";"Marine";"Barracks";58;1
"Unit";"SCV";"Command Center";59;1
"Building";"EngineeringBay";NA;57;0
"Unit";"Marine";"Barracks";59;1
"Unit";"Marine";"Barracks";59;1
"Unit";"Marine";"Barracks";59;1
"Unit";"Marine";"Barracks";59;1
"Unit";"SCV";"Command Center";60;1
"Building";"FactoryTechLab";NA;60;0
"Unit";"Medivac";"Starport";59;2
"Unit";"Medivac";"Starport";59;2
"Unit";"SCV";"Command Center";64;1
"Unit";"Marine";"Barracks";62;1
"Unit";"SCV";"Command Center";66;1
"Building";"SupplyDepot";NA;65;0
"Building";"SupplyDepot";NA;66;0
"Unit";"Marine";"Barracks";67;1
"Unit";"Marine";"Barracks";67;1
"Unit";"Marine";"Barracks";67;1
"Unit";"SCV";"Command Center";74;1
"Unit";"SCV";"Command Center";74;1
"Unit";"SCV";"Command Center";74;1
"Unit";"SCV";"Command Center";77;1
"Unit";"SCV";"Command Center";78;1
"Upgrade";"TerranInfantryArmorsLevel1";"EngineeringBay";54;0
"Building";"Barracks";NA;64;0
"Building";"Barracks";NA;64;0
"Building";"SupplyDepot";NA;79;0
"Unit";"SCV";"Command Center";82;1
"Unit";"SCV";"Command Center";82;1
"Unit";"SCV";"Command Center";82;1
"Building";"SupplyDepot";NA;82;0
"Building";"SupplyDepot";NA;82;0
"Building";"SupplyDepot";NA;82;0
"Upgrade";"Stimpack";"TechLab";59;0
"Unit";"SCV";"Command Center";85;1
"Unit";"SCV";"Command Center";85;1
"Building";"SupplyDepot";NA;82;0
"Unit";"Marine";"Barracks";82;1
"Unit";"SCV";"Command Center";85;1
"Unit";"Marine";"Barracks";82;1
"Unit";"Marine";"Barracks";82;1
"Unit";"Marine";"Barracks";82;1
"Unit";"Marine";"Barracks";82;1
"Unit";"SCV";"Command Center";85;1
"Unit";"SCV";"Command Center";86;1
"Unit";"SCV";"Command Center";88;1
"Building";"BarracksReactor";NA;82;0
"Building";"BarracksReactor";NA;82;0
"Unit";"Marine";"Barracks";93;1
"Unit";"Marine";"Barracks";93;1
"Unit";"Marine";"Barracks";93;1
"Unit";"Marine";"Barracks";93;1
"Unit";"Marine";"Barracks";93;1
"Building";"Armory";NA;85;0
"Unit";"Marine";"Barracks";96;1
"Unit";"Marine";"Barracks";96;1
"Unit";"Marine";"Barracks";96;1
"Unit";"Marine";"Barracks";96;1
"Building";"SupplyDepot";NA;96;0
"Building";"SupplyDepot";NA;96;0
"Building";"SupplyDepot";NA;96;0
"Building";"SupplyDepot";NA;96;0
"Unit";"Marine";"Barracks";96;1
"Upgrade";"TerranInfantryWeaponsLevel1";"EngineeringBay";79;0
"Building";"SupplyDepot";NA;96;0
"Unit";"Marine";"Barracks";101;1
"Unit";"Marine";"Barracks";101;1
"Unit";"Marine";"Barracks";101;1
"Unit";"Marine";"Barracks";101;1
"Unit";"Medivac";"Starport";96;2
"Unit";"Medivac";"Starport";96;2
"Unit";"Marine";"Barracks";101;1
"Unit";"Marine";"Barracks";102;1
"Unit";"Marine";"Barracks";102;1
"Unit";"Marine";"Barracks";105;1
"Unit";"Marine";"Barracks";105;1
"Unit";"Marine";"Barracks";106;1
"Unit";"Marine";"Barracks";107;1
"Unit";"Marine";"Barracks";108;1
"Unit";"Marine";"Barracks";108;1
"Unit";"Marine";"Barracks";118;1
"Unit";"Marine";"Barracks";124;1
"Unit";"Marine";"Barracks";124;1
"Unit";"Marine";"Barracks";124;1
"Unit";"Marauder";"Barracks";124;2
"Building";"SupplyDepot";NA;124;0
"Building";"SupplyDepot";NA;124;0
"Building";"SupplyDepot";NA;124;0
"Unit";"Marine";"Barracks";127;1
"Unit";"Marine";"Barracks";127;1
"Unit";"Marine";"Barracks";127;1
"Unit";"Marine";"Barracks";127;1
"Unit";"Marine";"Barracks";127;1
"Unit";"Marine";"Barracks";127;1
"Unit";"Marine";"Barracks";127;1
"Unit";"Marine";"Barracks";127;1
"Unit";"Marauder";"Barracks";127;2
"Unit";"Medivac";"Starport";129;2
"Unit";"Medivac";"Starport";129;2
"Unit";"Marine";"Barracks";129;1
"Unit";"Marine";"Barracks";130;1
"Unit";"Marine";"Barracks";137;1
"Unit";"Marine";"Barracks";137;1
"Unit";"Marine";"Barracks";137;1
"Unit";"Marine";"Barracks";137;1
"Unit";"Marine";"Barracks";137;1
"Unit";"Marine";"Barracks";139;1
"Unit";"Marine";"Barracks";139;1
"Unit";"SCV";"Command Center";145;1
"Unit";"SCV";"Command Center";145;1
"Upgrade";"TerranVehicleAndShipArmorsLevel1";"Armory";123;0
"Building";"SupplyDepot";NA;152;0
"Building";"SupplyDepot";NA;152;0
"Upgrade";"TerranInfantryArmorsLevel2";"EngineeringBay";123;0
"Unit";"Marine";"Barracks";154;1
"Unit";"Marine";"Barracks";154;1
"Unit";"Marine";"Barracks";154;1
"Unit";"Marine";"Barracks";154;1
"Unit";"Marine";"Barracks";154;1
"Unit";"Marine";"Barracks";154;1
"Unit";"Marine";"Barracks";154;1
"Unit";"Marine";"Barracks";154;1
"Building";"Barracks";NA;145;0
"Unit";"Marauder";"Barracks";154;2
"Building";"Barracks";NA;152;0
"Unit";"Medivac";"Starport";154;2
"Building";"Barracks";NA;152;0
"Unit";"Medivac";"Starport";154;2
"Unit";"Marine";"Barracks";154;1
"Unit";"Marine";"Barracks";155;1
"Unit";"Marine";"Barracks";155;1
"Unit";"Marine";"Barracks";164;1
"Unit";"Marauder";"Barracks";164;2
"Unit";"Marine";"Barracks";166;1
"Unit";"Marine";"Barracks";169;1
"Unit";"Marine";"Barracks";171;1
"Unit";"Marine";"Barracks";171;1
"Unit";"Marine";"Barracks";171;1
"Unit";"Marine";"Barracks";171;1
"Building";"BarracksTechLab";NA;171;0
"Building";"BarracksTechLab";NA;171;0
"Unit";"Marine";"Barracks";171;1
"Unit";"Marine";"Barracks";171;1
"Unit";"Marine";"Barracks";174;1
"Unit";"Marine";"Barracks";174;1
"Unit";"Marauder";"Barracks";172;2
"Unit";"Marine";"Barracks";180;1
"Unit";"Marine";"Barracks";180;1
"Unit";"Marine";"Barracks";180;1
"Building";"CommandCenter";NA;154;0
"Unit";"Marine";"Barracks";182;1
"Unit";"Marine";"Barracks";182;1
"Unit";"Marine";"Barracks";182;1
"Unit";"Marine";"Barracks";182;1
"Unit";"Marine";"Barracks";182;1
"Unit";"Marauder";"Barracks";182;2
"Unit";"Marine";"Barracks";182;1
"Unit";"Marine";"Barracks";183;1
"Unit";"Marine";"Barracks";186;1
"Unit";"Marine";"Barracks";187;1
"Unit";"Marauder";"Barracks";184;2
"Upgrade";"TerranInfantryWeaponsLevel2";"EngineeringBay";154;0
"Building";"SupplyDepot";NA;194;0
"Unit";"Marine";"Barracks";197;1
"Unit";"Marine";"Barracks";197;1
"Unit";"Marine";"Barracks";197;1
"Unit";"Liberator";"Starport";182;3
"Unit";"Liberator";"Starport";182;3
"Unit";"Marauder";"Barracks";200;2
"Unit";"Marine";"Barracks";202;1
"Unit";"Marine";"Barracks";202;1
"Unit";"Marine";"Barracks";202;1
"Unit";"Marine";"Barracks";202;1
"Unit";"Marine";"Barracks";202;1
"Unit";"Marine";"Barracks";202;1
"Unit";"Marauder";"Barracks";202;2
"Unit";"Marauder";"Barracks";202;2
"Unit";"Marine";"Barracks";202;1
"Unit";"Marine";"Barracks";203;1
"Unit";"Marine";"Barracks";204;1
"Unit";"Marine";"Barracks";213;1
"Unit";"Marine";"Barracks";214;1
"Unit";"Marine";"Barracks";215;1
"Unit";"Marine";"Barracks";216;1
"Unit";"Marauder";"Barracks";211;2
"Unit";"Marauder";"Barracks";219;2
"Unit";"Marauder";"Barracks";221;2
"Unit";"Marine";"Barracks";226;1
"Unit";"Marine";"Barracks";226;1
"Unit";"Marine";"Barracks";226;1
"Unit";"Liberator";"Starport";211;3
"Unit";"Liberator";"Starport";211;3
"Unit";"Marine";"Barracks";245;1
"Unit";"Marine";"Barracks";245;1
"Unit";"Marine";"Barracks";245;1
"Unit";"Marine";"Barracks";245;1
"Unit";"Marine";"Barracks";246;1
"Unit";"Marine";"Barracks";246;1
"Unit";"Marine";"Barracks";246;1
"Unit";"Marine";"Barracks";246;1
"Unit";"Marine";"Barracks";246;1
"Unit";"Marine";"Barracks";246;1
"Unit";"Marauder";"Barracks";246;2
"Unit";"Marauder";"Barracks";246;2
"Unit";"Marauder";"Barracks";246;2
"Unit";"Marine";"Barracks";246;1
"Unit";"Medivac";"Starport";246;2
"Unit";"Medivac";"Starport";246;2
"Unit";"Marine";"Barracks";247;1
"Unit";"Marine";"Barracks";248;1
"Unit";"Marine";"Barracks";249;1
"Unit";"Marine";"Barracks";250;1
"Unit";"Marine";"Barracks";250;1
"Unit";"Marine";"Barracks";250;1
"Unit";"Marine";"Barracks";253;1
"Unit";"Marine";"Barracks";253;1
"Unit";"Marauder";"Barracks";255;2
"Unit";"Marauder";"Barracks";257;2
"Unit";"Marauder";"Barracks";259;2
"Unit";"Marine";"Barracks";261;1
"Unit";"Marine";"Barracks";266;1
"Unit";"Marine";"Barracks";267;1
"Unit";"Marine";"Barracks";268;1
"Unit";"Marine";"Barracks";269;1
"Unit";"Marine";"Barracks";274;1
"Unit";"Marine";"Barracks";274;1
"Unit";"Marine";"Barracks";274;1
"Unit";"Marauder";"Barracks";274;2
"Unit";"Marauder";"Barracks";276;2
"Unit";"Marauder";"Barracks";278;2
"Unit";"Marine";"Barracks";281;1
"Unit";"Marine";"Barracks";281;1
"Unit";"Marine";"Barracks";281;1
"Unit";"Marine";"Barracks";282;1
"Unit";"Marine";"Barracks";283;1
"Unit";"Marine";"Barracks";284;1
"Unit";"Liberator";"Starport";262;3
"Unit";"Liberator";"Starport";264;3
"Unit";"Marine";"Barracks";285;1
"Unit";"Marine";"Barracks";286;1
"Unit";"Marine";"Barracks";287;1
"Unit";"Marauder";"Barracks";288;2
"Unit";"Marauder";"Barracks";290;2
"Unit";"Marauder";"Barracks";292;2
"Unit";"Marine";"Barracks";309;1
"Unit";"Marine";"Barracks";309;1
"Unit";"Marine";"Barracks";309;1
"Unit";"Marine";"Barracks";309;1
"Unit";"Marine";"Barracks";309;1
"Unit";"Marine";"Barracks";309;1
"Unit";"Marine";"Barracks";309;1
"Unit";"Marine";"Barracks";309;1
"Unit";"Marine";"Barracks";309;1
"Unit";"Marauder";"Barracks";309;2
"Unit";"Marauder";"Barracks";311;2
"Unit";"Marauder";"Barracks";313;2
"Unit";"Marine";"Barracks";315;1
"Unit";"Marine";"Barracks";316;1
"Building";"SupplyDepot";NA;320;0
"Building";"EngineeringBay";NA;315;0
"Unit";"Marine";"Barracks";324;1
"Building";"EngineeringBay";NA;315;0
"Building";"SupplyDepot";NA;326;0
"Building";"SupplyDepot";NA;326;0
"Building";"SupplyDepot";NA;330;0
"Unit";"Medivac";"Starport";324;2
"Building";"SupplyDepot";NA;330;0
"Unit";"Marine";"Barracks";332;1
"Unit";"Marine";"Barracks";332;1
"Unit";"Marine";"Barracks";332;1
"Unit";"Marine";"Barracks";332;1
"Unit";"Marine";"Barracks";332;1
"Unit";"Marine";"Barracks";332;1
"Unit";"Marine";"Barracks";333;1
"Unit";"Marine";"Barracks";333;1
"Unit";"Marine";"Barracks";333;1
"Unit";"Medivac";"Starport";332;2
"Unit";"Marauder";"Barracks";333;2
"Unit";"Marauder";"Barracks";333;2
"Unit";"Marauder";"Barracks";333;2
"Unit";"Marine";"Barracks";335;1
"Unit";"Marine";"Barracks";335;1
"Unit";"Marine";"Barracks";335;1
"Unit";"Marine";"Barracks";341;1
"Unit";"Marine";"Barracks";341;1
"Unit";"Marine";"Barracks";341;1
"Unit";"Marine";"Barracks";341;1
"Unit";"Marine";"Barracks";341;1
"Unit";"Marine";"Barracks";343;1
"Unit";"Marauder";"Barracks";346;2
"Unit";"Marine";"Barracks";360;1
"Unit";"Marine";"Barracks";361;1
"Unit";"Marine";"Barracks";361;1
"Unit";"Marine";"Barracks";361;1
"Unit";"Marine";"Barracks";361;1
"Unit";"Marine";"Barracks";361;1
"Unit";"Marine";"Barracks";361;1
"Unit";"Marauder";"Barracks";360;2
"Unit";"Marauder";"Barracks";360;2
"Unit";"Marine";"Barracks";374;1
