"Type";"UnitName";"OnBuilding";"TotalSupply";"Supply"
"Unit";"SCV";"Command Center";12;1
"Unit";"SCV";"Command Center";12;1
"Unit";"SCV";"Command Center";13;1
"Building";"SupplyDepot";NA;13;0
"Unit";"SCV";"Command Center";15;1
"Unit";"SCV";"Command Center";15;1
"Building";"Refinery";NA;15;0
"Unit";"SCV";"Command Center";16;1
"Unit";"SCV";"Command Center";17;1
"Building";"Barracks";NA;15;0
"Unit";"Reaper";"Barracks";19;1
"Unit";"SCV";"Command Center";19;1
"Building";"SupplyDepot";NA;19;0
"Unit";"SCV";"Command Center";21;1
"Unit";"SCV";"Command Center";22;1
"Building";"Refinery";NA;21;0
"Building";"Factory";NA;21;0
"Unit";"SCV";"Command Center";23;1
"Building";"CommandCenter";NA;19;0
"Building";"BarracksReactor";NA;22;0
"Unit";"SCV";"Command Center";24;1
"Unit";"Hellion";"Factory";24;2
"Unit";"Hellion";"Factory";24;2
"Unit";"SCV";"Command Center";24;1
"Building";"Starport";NA;24;0
"Unit";"SCV";"Command Center";25;1
"Building";"BarracksTechLab";NA;25;0
"Unit";"SCV";"Command Center";29;1
"Unit";"SCV";"Command Center";30;1
"Unit";"Hellion";"Factory";30;2
"Unit";"Hellion";"Factory";30;2
"Unit";"SCV";"Command Center";32;1
"Unit";"SCV";"Command Center";33;1
"Unit";"SCV";"Command Center";38;1
"Building";"SupplyDepot";NA;39;0
"Unit";"SCV";"Command Center";40;1
"Unit";"SCV";"Command Center";40;1
"Building";"Barracks";NA;33;0
"Building";"FactoryReactor";NA;38;0
"Building";"Barracks";NA;33;0
"Building";"EngineeringBay";NA;40;0
"Unit";"SCV";"Command Center";42;1
"Unit";"SCV";"Command Center";42;1
"Unit";"SCV";"Command Center";42;1
"Unit";"SCV";"Command Center";43;1
"Unit";"SCV";"Command Center";44;1
"Unit";"SCV";"Command Center";45;1
"Building";"EngineeringBay";NA;44;0
"Unit";"SCV";"Command Center";46;1
"Building";"FactoryTechLab";NA;46;0
"Unit";"Marine";"Barracks";46;1
"Unit";"Marine";"Barracks";46;1
"Unit";"Marine";"Barracks";46;1
"Building";"CommandCenter";NA;40;0
"Unit";"SCV";"Command Center";49;1
"Building";"StarportReactor";NA;45;0
"Unit";"Marine";"Barracks";48;1
"Unit";"Marine";"Barracks";48;1
"Upgrade";"Stimpack";"TechLab";40;0
"Unit";"SCV";"Command Center";54;1
"Unit";"Marine";"Barracks";53;1
"Unit";"Marine";"Barracks";53;1
"Unit";"Marine";"Barracks";53;1
"Unit";"Marine";"Barracks";53;1
"Unit";"SCV";"Command Center";55;1
"Unit";"Marine";"Barracks";55;1
"Building";"Barracks";NA;48;0
"Building";"Refinery";NA;55;0
"Building";"Refinery";NA;55;0
"Building";"Barracks";NA;48;0
"Unit";"SCV";"Command Center";59;1
"Unit";"Medivac";"Starport";53;2
"Unit";"Medivac";"Starport";53;2
"Unit";"Marine";"Barracks";56;1
"Unit";"Marine";"Barracks";57;1
"Unit";"SCV";"Command Center";61;1
"Unit";"Marine";"Barracks";60;1
"Unit";"Marine";"Barracks";60;1
"Building";"SupplyDepot";NA;59;0
"Building";"SupplyDepot";NA;60;0
"Unit";"Marine";"Barracks";61;1
"Unit";"Marine";"Barracks";67;1
"Unit";"SCV";"Command Center";72;1
"Unit";"SCV";"Command Center";73;1
"Unit";"SCV";"Command Center";74;1
"Unit";"Marine";"Barracks";73;1
"Unit";"Marine";"Barracks";73;1
"Unit";"Marine";"Barracks";73;1
"Unit";"Marine";"Barracks";73;1
"Building";"BarracksReactor";NA;67;0
"Building";"BarracksReactor";NA;67;0
"Unit";"Marine";"Barracks";73;1
"Unit";"SCV";"Command Center";76;1
"Unit";"SCV";"Command Center";81;1
"Unit";"SCV";"Command Center";82;1
"Building";"SupplyDepot";NA;76;0
"Unit";"Medivac";"Starport";76;2
"Unit";"Marine";"Barracks";77;1
"Unit";"Marine";"Barracks";78;1
"Unit";"Marine";"Barracks";79;1
"Unit";"Marine";"Barracks";80;1
"Building";"SupplyDepot";NA;76;0
"Unit";"Marine";"Barracks";81;1
"Unit";"SCV";"Command Center";82;1
"Unit";"Marine";"Barracks";82;1
"Unit";"Marine";"Barracks";82;1
"Unit";"Marine";"Barracks";82;1
"Unit";"Liberator";"Starport";73;3
"Unit";"SCV";"Command Center";85;1
"Unit";"SCV";"Command Center";85;1
"Unit";"Marine";"Barracks";85;1
"Unit";"Marine";"Barracks";93;1
"Unit";"Marine";"Barracks";93;1
"Unit";"Marine";"Barracks";93;1
"Unit";"Marine";"Barracks";93;1
"Unit";"Marine";"Barracks";93;1
"Unit";"SCV";"Command Center";99;1
"Upgrade";"TerranInfantryWeaponsLevel1";"EngineeringBay";62;0
"Upgrade";"TerranInfantryArmorsLevel1";"EngineeringBay";62;0
"Unit";"Marine";"Barracks";93;1
"Unit";"Marine";"Barracks";99;1
"Unit";"Marine";"Barracks";99;1
"Unit";"Marine";"Barracks";101;1
"Unit";"SCV";"Command Center";111;1
"Unit";"Medivac";"Starport";101;2
"Unit";"SCV";"Command Center";112;1
"Unit";"SCV";"Command Center";112;1
"Unit";"SCV";"Command Center";117;1
"Unit";"SCV";"Command Center";117;1
"Unit";"SCV";"Command Center";117;1
"Unit";"Marine";"Barracks";117;1
"Unit";"Marine";"Barracks";117;1
"Building";"Factory";NA;112;0
"Building";"Barracks";NA;111;0
"Unit";"Marine";"Barracks";117;1
"Unit";"Marine";"Barracks";117;1
"Unit";"Marine";"Barracks";117;1
"Unit";"Marine";"Barracks";117;1
"Unit";"Marine";"Barracks";117;1
"Building";"FactoryTechLab";NA;122;0
"Building";"SupplyDepot";NA;122;0
"Unit";"Liberator";"Starport";117;3
"Unit";"SCV";"Command Center";127;1
"Building";"Barracks";NA;120;0
"Building";"Armory";NA;120;0
"Building";"Barracks";NA;122;0
"Unit";"Marine";"Barracks";127;1
"Unit";"Marine";"Barracks";127;1
"Unit";"Marine";"Barracks";127;1
"Unit";"Marine";"Barracks";127;1
"Unit";"Marine";"Barracks";127;1
"Unit";"Marine";"Barracks";127;1
"Unit";"Marine";"Barracks";127;1
"Building";"SupplyDepot";NA;127;0
"Unit";"Marine";"Barracks";130;1
"Building";"SupplyDepot";NA;127;0
"Building";"BarracksTechLab";NA;131;0
"Building";"BarracksTechLab";NA;131;0
"Unit";"Marine";"Barracks";138;1
"Building";"SupplyDepot";NA;131;0
"Unit";"SCV";"Command Center";139;1
"Unit";"Marine";"Barracks";138;1
"Unit";"Marauder";"Barracks";138;2
"Building";"Refinery";NA;139;0
"Building";"SupplyDepot";NA;139;0
"Building";"Refinery";NA;139;0
"Unit";"SCV";"Command Center";144;1
"Unit";"Marine";"Barracks";144;1
"Unit";"Marine";"Barracks";144;1
"Unit";"Marine";"Barracks";144;1
"Unit";"Marine";"Barracks";144;1
"Unit";"Marine";"Barracks";144;1
"Unit";"Marauder";"Barracks";142;2
"Unit";"Marauder";"Barracks";144;2
"Unit";"Marauder";"Barracks";144;2
"Unit";"Liberator";"Starport";139;3
"Unit";"Liberator";"Starport";139;3
"Unit";"Marine";"Barracks";144;1
"Unit";"Marine";"Barracks";144;1
"Building";"BarracksReactor";NA;144;0
"Unit";"Marauder";"Barracks";156;2
"Unit";"Marine";"Barracks";164;1
"Unit";"Marine";"Barracks";164;1
"Unit";"Marine";"Barracks";164;1
"Unit";"Marauder";"Barracks";162;2
"Unit";"Marine";"Barracks";169;1
"Unit";"Marine";"Barracks";169;1
"Unit";"Marine";"Barracks";169;1
"Unit";"Marine";"Barracks";171;1
"Unit";"Marine";"Barracks";171;1
"Unit";"Marine";"Barracks";171;1
"Unit";"Marauder";"Barracks";169;2
"Unit";"Marauder";"Barracks";169;2
"Unit";"Marauder";"Barracks";169;2
"Unit";"Medivac";"Starport";171;2
"Unit";"Marine";"Barracks";181;1
"Unit";"Marine";"Barracks";181;1
"Unit";"Marine";"Barracks";183;1
"Unit";"Marine";"Barracks";183;1
"Unit";"Marine";"Barracks";183;1
"Unit";"Marine";"Barracks";183;1
"Unit";"Marine";"Barracks";183;1
"Unit";"Marauder";"Barracks";177;2
"Unit";"Marauder";"Barracks";179;2
"Unit";"Marine";"Barracks";183;1
"Unit";"Marine";"Barracks";183;1
"Unit";"Marauder";"Barracks";181;2
"Unit";"Marine";"Barracks";183;1
"Unit";"Medivac";"Starport";183;2
"Unit";"Marauder";"Barracks";192;2
"Unit";"Marauder";"Barracks";194;2
"Building";"SupplyDepot";NA;201;0
"Unit";"Medivac";"Starport";190;2
"Building";"SensorTower";NA;201;0
"Building";"SensorTower";NA;201;0
"Building";"SupplyDepot";NA;201;0
"Upgrade";"TerranInfantryArmorsLevel2";"EngineeringBay";164;0
"Upgrade";"TerranInfantryWeaponsLevel2";"EngineeringBay";164;0
"Unit";"Marauder";"Barracks";207;2
"Unit";"Marauder";"Barracks";207;2
"Unit";"Marauder";"Barracks";207;2
"Building";"MissileTurret";NA;209;0
"Building";"MissileTurret";NA;215;0
"Unit";"Medivac";"Starport";209;2
"Unit";"Medivac";"Starport";209;2
"Building";"MissileTurret";NA;219;0
"Building";"Starport";NA;215;0
"Unit";"Marine";"Barracks";219;1
"Unit";"Marine";"Barracks";219;1
"Unit";"Marine";"Barracks";219;1
"Unit";"Marine";"Barracks";219;1
"Unit";"Marine";"Barracks";219;1
"Unit";"Marine";"Barracks";219;1
"Unit";"Marine";"Barracks";219;1
"Unit";"Marine";"Barracks";219;1
"Unit";"Marauder";"Barracks";219;2
"Unit";"Marine";"Barracks";219;1
"Unit";"Marine";"Barracks";220;1
"Unit";"Marine";"Barracks";221;1
"Unit";"Marauder";"Barracks";227;2
"Unit";"Marine";"Barracks";229;1
"Unit";"Marine";"Barracks";229;1
"Unit";"Marine";"Barracks";229;1
"Unit";"Marine";"Barracks";229;1
"Unit";"Marine";"Barracks";231;1
"Unit";"Marauder";"Barracks";232;2
"Building";"StarportReactor";NA;231;0
"Unit";"Marine";"Barracks";239;1
"Unit";"Marine";"Barracks";239;1
"Unit";"Marine";"Barracks";239;1
"Unit";"Marine";"Barracks";239;1
"Unit";"Marine";"Barracks";239;1
"Unit";"Marine";"Barracks";239;1
"Unit";"Marauder";"Barracks";239;2
"Building";"Refinery";NA;241;0
"Unit";"Marine";"Barracks";241;1
"Unit";"Marine";"Barracks";241;1
"Unit";"Marine";"Barracks";241;1
"Unit";"Marine";"Barracks";242;1
"Unit";"Marine";"Barracks";243;1
"Building";"SensorTower";NA;245;0
