"type";"unit_name";"on_building";"total_supply";"supply"
"Building";"Refinery";NA;15;0
"Building";"Barracks";NA;15;0
"Unit";"Reaper";"Barracks";19;1
"Unit";"Marine";"Barracks";19;1
"Building";"Refinery";NA;21;0
"Building";"Factory";NA;20;0
"Building";"CommandCenter";NA;19;0
"Building";"BarracksReactor";NA;23;0
"Unit";"Hellion";"Factory";26;2
"Unit";"Hellion";"Factory";26;2
"Building";"Starport";NA;25;0
"Building";"BarracksTechLab";NA;26;0
"Unit";"Hellion";"Factory";27;2
"Unit";"Hellion";"Factory";29;2
"Unit";"Marine";"Barracks";32;1
"Unit";"Marine";"Barracks";39;1
"Building";"StarportTechLab";NA;40;0
"Unit";"Marine";"Barracks";44;1
"Unit";"Marine";"Barracks";47;1
"Building";"StarportReactor";NA;45;0
"Building";"Barracks";NA;45;0
"Building";"Barracks";NA;46;0
"Unit";"Marine";"Barracks";52;1
"Building";"EngineeringBay";NA;51;0
"Building";"EngineeringBay";NA;51;0
"Building";"Refinery";NA;53;0
"Building";"Refinery";NA;54;0
"Upgrade";"Stimpack";"TechLab";40;0
"Building";"CommandCenter";NA;44;0
"Unit";"Marine";"Barracks";54;1
"Unit";"Marine";"Barracks";54;1
"Unit";"Marine";"Barracks";57;1
"Building";"StarportReactor";NA;54;0
"Unit";"Marine";"Barracks";61;1
"Unit";"Marine";"Barracks";61;1
"Unit";"Marine";"Barracks";62;1
"Unit";"Marine";"Barracks";62;1
"Unit";"Marine";"Barracks";64;1
"Unit";"Marine";"Barracks";64;1
"Unit";"Marine";"Barracks";67;1
"Unit";"Marine";"Barracks";70;1
"Unit";"Marine";"Barracks";70;1
"Unit";"Marine";"Barracks";70;1
"Unit";"Marine";"Barracks";71;1
"Unit";"Medivac";"Starport";70;2
"Unit";"Medivac";"Starport";70;2
"Unit";"Marine";"Barracks";74;1
"Unit";"Marine";"Barracks";85;1
"Unit";"Marine";"Barracks";85;1
"Unit";"Marine";"Barracks";85;1
"Unit";"Marine";"Barracks";85;1
"Unit";"Marine";"Barracks";85;1
"Building";"Armory";NA;72;0
"Unit";"Medivac";"Starport";85;2
"Unit";"Medivac";"Starport";85;2
"Unit";"Marine";"Barracks";88;1
"Unit";"Marine";"Barracks";89;1
"Unit";"Marine";"Barracks";90;1
"Building";"Factory";NA;78;0
"Unit";"Marine";"Barracks";91;1
"Upgrade";"TerranInfantryArmorsLevel1";"EngineeringBay";67;0
"Upgrade";"TerranInfantryWeaponsLevel1";"EngineeringBay";67;0
"Unit";"Marine";"Barracks";99;1
"Unit";"Marine";"Barracks";99;1
"Unit";"Marine";"Barracks";101;1
"Unit";"Marine";"Barracks";102;1
"Unit";"Marine";"Barracks";102;1
"Building";"Barracks";NA;88;0
"Building";"Barracks";NA;88;0
"Unit";"Marine";"Barracks";106;1
"Unit";"Marine";"Barracks";107;1
"Unit";"Marine";"Barracks";108;1
"Unit";"Marine";"Barracks";109;1
"Unit";"Marine";"Barracks";110;1
"Building";"FactoryTechLab";NA;111;0
"Building";"BarracksTechLab";NA;111;0
"Unit";"Medivac";"Starport";111;2
"Unit";"Medivac";"Starport";111;2
"Unit";"Marine";"Barracks";111;1
"Unit";"Marine";"Barracks";119;1
"Unit";"Marine";"Barracks";119;1
"Unit";"Marine";"Barracks";119;1
"Unit";"Marine";"Barracks";119;1
"Building";"BarracksReactor";NA;111;0
"Unit";"Marine";"Barracks";131;1
"Unit";"Marine";"Barracks";131;1
"Unit";"Marine";"Barracks";131;1
"Unit";"Marine";"Barracks";131;1
"Unit";"Marine";"Barracks";131;1
"Unit";"Marine";"Barracks";131;1
"Unit";"Marine";"Barracks";131;1
"Unit";"Marine";"Barracks";131;1
"Unit";"Marine";"Barracks";144;1
"Unit";"Marine";"Barracks";144;1
"Unit";"Marine";"Barracks";144;1
"Unit";"Marauder";"Barracks";144;2
"Unit";"Marine";"Barracks";144;1
"Unit";"Marine";"Barracks";144;1
"Unit";"Marauder";"Barracks";144;2
"Unit";"Marine";"Barracks";149;1
"Unit";"Marine";"Barracks";149;1
"Unit";"Marine";"Barracks";149;1
"Unit";"Marine";"Barracks";149;1
"Unit";"Marauder";"Barracks";149;2
"Building";"Refinery";NA;149;0
"Building";"Refinery";NA;149;0
"Upgrade";"TerranInfantryWeaponsLevel2";"EngineeringBay";131;0
"Upgrade";"TerranInfantryArmorsLevel2";"EngineeringBay";131;0
"Unit";"Marine";"Barracks";153;1
"Unit";"Medivac";"Starport";149;2
"Unit";"Marine";"Barracks";153;1
"Unit";"Medivac";"Starport";149;2
"Unit";"Marauder";"Barracks";153;2
"Unit";"Marine";"Barracks";159;1
"Unit";"Marine";"Barracks";159;1
"Unit";"Marine";"Barracks";159;1
"Unit";"Marine";"Barracks";159;1
"Unit";"Marauder";"Barracks";157;2
"Unit";"Marine";"Barracks";159;1
"Unit";"Marine";"Barracks";165;1
"Unit";"Marine";"Barracks";167;1
"Unit";"Marine";"Barracks";168;1
"Unit";"Marine";"Barracks";169;1
"Unit";"Marine";"Barracks";170;1
"Unit";"Marauder";"Barracks";165;2
"Unit";"Marauder";"Barracks";171;2
"Unit";"Marine";"Barracks";173;1
"Unit";"Marauder";"Barracks";179;2
"Unit";"Marine";"Barracks";183;1
"Unit";"Marine";"Barracks";183;1
"Unit";"Marine";"Barracks";183;1
"Unit";"Marine";"Barracks";183;1
"Unit";"Marine";"Barracks";183;1
"Building";"SensorTower";NA;184;0
"Unit";"Marauder";"Barracks";183;2
"Unit";"Marine";"Barracks";184;1
"Unit";"Marauder";"Barracks";184;2
"Unit";"Marine";"Barracks";193;1
"Unit";"Marine";"Barracks";193;1
"Unit";"Marine";"Barracks";193;1
"Unit";"Marine";"Barracks";193;1
"Unit";"Marine";"Barracks";193;1
"Unit";"Marine";"Barracks";193;1
"Unit";"Marauder";"Barracks";193;2
"Unit";"Marine";"Barracks";194;1
"Building";"CommandCenter";NA;175;0
"Unit";"Medivac";"Starport";194;2
"Unit";"Medivac";"Starport";194;2
"Unit";"Marine";"Barracks";201;1
"Unit";"Marine";"Barracks";201;1
"Unit";"Marine";"Barracks";201;1
"Unit";"Marauder";"Barracks";202;2
"Unit";"Marauder";"Barracks";207;2
"Unit";"Marine";"Barracks";208;1
"Unit";"Marine";"Barracks";208;1
"Unit";"Marine";"Barracks";208;1
"Unit";"Marine";"Barracks";217;1
"Unit";"Marine";"Barracks";217;1
"Unit";"Marine";"Barracks";217;1
"Unit";"Marauder";"Barracks";215;2
"Unit";"Marine";"Barracks";221;1
"Unit";"Marauder";"Barracks";217;2
"Unit";"Marine";"Barracks";224;1
"Unit";"Marine";"Barracks";224;1
"Unit";"Marine";"Barracks";227;1
"Unit";"Marine";"Barracks";227;1
"Unit";"Marine";"Barracks";227;1
"Unit";"Marine";"Barracks";229;1
"Unit";"Marine";"Barracks";229;1
"Unit";"Marine";"Barracks";234;1
"Unit";"Marine";"Barracks";234;1
"Unit";"Marine";"Barracks";234;1
"Unit";"Marine";"Barracks";238;1
"Unit";"Marine";"Barracks";238;1
"Unit";"Marine";"Barracks";238;1
"Building";"GhostAcademy";NA;234;0
"Unit";"Marauder";"Barracks";238;2
"Unit";"Marine";"Barracks";242;1
"Unit";"Marine";"Barracks";242;1
"Unit";"Marine";"Barracks";242;1
"Unit";"Marauder";"Barracks";242;2
"Unit";"Marine";"Barracks";242;1
"Unit";"Marine";"Barracks";245;1
"Unit";"Marine";"Barracks";245;1
"Unit";"Marine";"Barracks";245;1
"Upgrade";"TerranInfantryArmorsLevel3";"EngineeringBay";196;0
"Upgrade";"TerranInfantryWeaponsLevel3";"EngineeringBay";196;0
"Building";"Barracks";NA;238;0
"Building";"Barracks";NA;238;0
"Building";"Barracks";NA;238;0
"Unit";"Marine";"Barracks";256;1
"Unit";"Marine";"Barracks";256;1
"Unit";"Marine";"Barracks";256;1
"Unit";"Marine";"Barracks";256;1
"Unit";"Marine";"Barracks";256;1
"Unit";"Marine";"Barracks";256;1
"Unit";"Marine";"Barracks";256;1
"Unit";"Marauder";"Barracks";256;2
"Unit";"Marine";"Barracks";256;1
