"Type";"UnitName";"OnBuilding";"TotalSupply";"Supply"
"Unit";"SCV";"Command Center";12;1
"Unit";"SCV";"Command Center";12;1
"Unit";"SCV";"Command Center";13;1
"Building";"SupplyDepot";NA;13;0
"Unit";"SCV";"Command Center";15;1
"Building";"Refinery";NA;14;0
"Unit";"SCV";"Command Center";15;1
"Unit";"SCV";"Command Center";16;1
"Unit";"SCV";"Command Center";17;1
"Building";"Barracks";NA;15;0
"Unit";"Reaper";"Barracks";19;1
"Unit";"SCV";"Command Center";19;1
"Unit";"SCV";"Command Center";21;1
"Building";"SupplyDepot";NA;20;0
"Unit";"SCV";"Command Center";21;1
"Building";"Factory";NA;19;0
"Building";"Refinery";NA;21;0
"Building";"BarracksReactor";NA;21;0
"Unit";"SCV";"Command Center";23;1
"Building";"CommandCenter";NA;19;0
"Unit";"SCV";"Command Center";24;1
"Building";"BarracksTechLab";NA;24;0
"Unit";"Hellion";"Factory";24;2
"Unit";"Hellion";"Factory";24;2
"Unit";"SCV";"Command Center";24;1
"Unit";"SCV";"Command Center";29;1
"Building";"Starport";NA;24;0
"Unit";"SCV";"Command Center";29;1
"Unit";"Hellion";"Factory";25;2
"Unit";"Hellion";"Factory";27;2
"Building";"SupplyDepot";NA;29;0
"Unit";"SCV";"Command Center";30;1
"Unit";"SCV";"Command Center";31;1
"Unit";"SCV";"Command Center";36;1
"Unit";"SCV";"Command Center";37;1
"Building";"SupplyDepot";NA;36;0
"Unit";"SCV";"Command Center";38;1
"Unit";"SCV";"Command Center";39;1
"Unit";"SCV";"Command Center";41;1
"Unit";"SCV";"Command Center";41;1
"Unit";"Banshee";"Starport";37;3
"Unit";"SCV";"Command Center";42;1
"Unit";"SCV";"Command Center";43;1
"Building";"SupplyDepot";NA;44;0
"Unit";"Hellion";"Factory";49;2
"Unit";"Hellion";"Factory";49;2
"Unit";"SCV";"Command Center";49;1
"Unit";"SCV";"Command Center";49;1
"Unit";"Banshee";"Starport";44;3
"Building";"Refinery";NA;49;0
"Building";"Refinery";NA;49;0
"Unit";"SCV";"Command Center";53;1
"Unit";"SCV";"Command Center";54;1
"Building";"CommandCenter";NA;41;0
"Unit";"Hellion";"Factory";49;2
"Unit";"Hellion";"Factory";51;2
"Building";"BarracksTechLab";NA;58;0
"Unit";"SCV";"Command Center";58;1
"Unit";"SCV";"Command Center";59;1
"Unit";"SCV";"Command Center";60;1
"Building";"Armory";NA;49;0
"Building";"Armory";NA;49;0
"Unit";"SCV";"Command Center";64;1
"Unit";"SCV";"Command Center";66;1
"Unit";"Hellion";"Factory";64;2
"Unit";"Hellion";"Factory";64;2
"Unit";"SCV";"Command Center";67;1
"Unit";"SCV";"Command Center";68;1
"Building";"StarportReactor";NA;60;0
"Building";"Factory";NA;58;0
"Building";"Factory";NA;58;0
"Unit";"SCV";"Command Center";73;1
"Unit";"SCV";"Command Center";74;1
"Building";"SupplyDepot";NA;73;0
"Building";"EngineeringBay";NA;73;0
"Unit";"Hellion";"Factory";75;2
"Unit";"Hellion";"Factory";75;2
"Unit";"Medivac";"Starport";75;2
"Unit";"Medivac";"Starport";75;2
"Building";"SupplyDepot";NA;77;0
"Building";"SupplyDepot";NA;77;0
"Unit";"SCV";"Command Center";83;1
"Unit";"SCV";"Command Center";83;1
"Unit";"SCV";"Command Center";85;1
"Unit";"SCV";"Command Center";85;1
"Unit";"SCV";"Command Center";86;1
"Unit";"Thor";"Factory";77;6
"Building";"SupplyDepot";NA;85;0
"Unit";"SCV";"Command Center";87;1
"Unit";"SCV";"Command Center";88;1
"Building";"SupplyDepot";NA;87;0
"Building";"Refinery";NA;87;0
"Unit";"SCV";"Command Center";90;1
"Building";"Refinery";NA;87;0
"Unit";"Hellion";"Factory";87;2
"Unit";"Hellion";"Factory";87;2
"Unit";"SCV";"Command Center";96;1
"Unit";"SCV";"Command Center";97;1
"Unit";"SCV";"Command Center";105;1
"Unit";"SCV";"Command Center";105;1
"Upgrade";"TerranVehicleWeaponsLevel1";"Armory";81;0
"Upgrade";"TerranVehicleAndShipArmorsLevel1";"Armory";81;0
"Unit";"SCV";"Command Center";105;1
"Unit";"SCV";"Command Center";105;1
"Unit";"SCV";"Command Center";106;1
"Unit";"Hellion";"Factory";105;2
"Building";"SupplyDepot";NA;105;0
"Unit";"SCV";"Command Center";108;1
"Unit";"SCV";"Command Center";108;1
"Unit";"SCV";"Command Center";112;1
"Unit";"SCV";"Command Center";112;1
"Building";"SensorTower";NA;110;0
"Unit";"SCV";"Command Center";113;1
"Building";"SupplyDepot";NA;113;0
"Unit";"SCV";"Command Center";116;1
"Unit";"Thor";"Factory";107;6
"Building";"SupplyDepot";NA;114;0
"Unit";"Hellion";"Factory";114;2
"Unit";"Hellion";"Factory";116;2
"Building";"SupplyDepot";NA;114;0
"Building";"MissileTurret";NA;118;0
"Building";"MissileTurret";NA;118;0
"Building";"MissileTurret";NA;118;0
"Building";"MissileTurret";NA;118;0
"Unit";"SCV";"Command Center";128;1
"Unit";"SCV";"Command Center";128;1
"Building";"CommandCenter";NA;108;0
"Unit";"SCV";"Command Center";128;1
"Building";"SupplyDepot";NA;128;0
"Unit";"SCV";"Command Center";128;1
"Unit";"SCV";"Command Center";129;1
"Building";"SupplyDepot";NA;133;0
"Building";"Factory";NA;130;0
"Building";"Factory";NA;130;0
"Unit";"SCV";"Command Center";133;1
"Unit";"SCV";"Command Center";133;1
"Unit";"SCV";"Command Center";133;1
"Building";"Refinery";NA;136;0
"Building";"FactoryTechLab";NA;136;0
"Unit";"Hellion";"Factory";136;2
"Unit";"Hellion";"Factory";136;2
"Building";"FactoryReactor";NA;136;0
"Unit";"SCV";"Command Center";140;1
"Unit";"SCV";"Command Center";140;1
"Unit";"SCV";"Command Center";140;1
"Upgrade";"TerranVehicleWeaponsLevel2";"Armory";133;0
"Building";"Refinery";NA;140;0
"Upgrade";"TerranVehicleAndShipArmorsLevel2";"Armory";133;0
"Unit";"Hellion";"Factory";140;2
"Unit";"Hellion";"Factory";140;2
"Building";"SensorTower";NA;140;0
"Building";"MissileTurret";NA;140;0
"Unit";"Hellion";"Factory";147;2
"Unit";"Hellion";"Factory";147;2
"Unit";"Hellion";"Factory";147;2
"Unit";"Hellion";"Factory";147;2
"Unit";"Hellion";"Factory";147;2
"Unit";"Hellion";"Factory";149;2
"Unit";"Hellion";"Factory";155;2
"Unit";"Hellion";"Factory";155;2
"Building";"CommandCenter";NA;147;0
"Building";"CommandCenter";NA;147;0
"Unit";"Hellion";"Factory";163;2
"Unit";"Hellion";"Factory";163;2
"Unit";"Hellion";"Factory";163;2
