"Type";"UnitName";"OnBuilding";"TotalSupply";"Supply"
"Unit";"SCV";"Command Center";12;1
"Unit";"SCV";"Command Center";12;1
"Unit";"SCV";"Command Center";13;1
"Building";"SupplyDepot";NA;13;0
"Unit";"SCV";"Command Center";15;1
"Building";"Refinery";NA;14;0
"Unit";"SCV";"Command Center";15;1
"Unit";"SCV";"Command Center";16;1
"Unit";"SCV";"Command Center";17;1
"Building";"Barracks";NA;15;0
"Unit";"Reaper";"Barracks";19;1
"Unit";"SCV";"Command Center";19;1
"Unit";"SCV";"Command Center";21;1
"Building";"SupplyDepot";NA;21;0
"Building";"Refinery";NA;21;0
"Unit";"SCV";"Command Center";21;1
"Building";"Factory";NA;19;0
"Unit";"SCV";"Command Center";23;1
"Building";"BarracksReactor";NA;21;0
"Building";"CommandCenter";NA;19;0
"Unit";"SCV";"Command Center";24;1
"Unit";"Hellion";"Factory";24;2
"Unit";"Hellion";"Factory";24;2
"Building";"BarracksTechLab";NA;24;0
"Building";"SupplyDepot";NA;24;0
"Unit";"SCV";"Command Center";24;1
"Building";"Starport";NA;24;0
"Unit";"Hellion";"Factory";29;2
"Unit";"SCV";"Command Center";30;1
"Unit";"SCV";"Command Center";30;1
"Unit";"Hellion";"Factory";29;2
"Building";"SupplyDepot";NA;30;0
"Unit";"SCV";"Command Center";36;1
"Unit";"SCV";"Command Center";36;1
"Unit";"SCV";"Command Center";38;1
"Unit";"SCV";"Command Center";38;1
"Unit";"Banshee";"Starport";30;3
"Unit";"SCV";"Command Center";38;1
"Unit";"SCV";"Command Center";39;1
"Unit";"SCV";"Command Center";43;1
"Unit";"SCV";"Command Center";45;1
"Unit";"SCV";"Command Center";45;1
"Building";"SupplyDepot";NA;45;0
"Building";"Armory";NA;40;0
"Building";"Armory";NA;40;0
"Unit";"SCV";"Command Center";48;1
"Unit";"SCV";"Command Center";48;1
"Unit";"Banshee";"Starport";43;3
"Building";"CommandCenter";NA;36;0
"Unit";"Hellion";"Factory";48;2
"Unit";"Hellion";"Factory";48;2
"Building";"Refinery";NA;48;0
"Building";"Refinery";NA;48;0
"Unit";"SCV";"Command Center";48;1
"Unit";"SCV";"Command Center";49;1
"Unit";"SCV";"Command Center";57;1
"Unit";"SCV";"Command Center";58;1
"Building";"Factory";NA;48;0
"Unit";"SCV";"Command Center";59;1
"Unit";"SCV";"Command Center";60;1
"Building";"SupplyDepot";NA;59;0
"Unit";"Hellion";"Factory";59;2
"Unit";"Hellion";"Factory";59;2
"Building";"Factory";NA;53;0
"Unit";"SCV";"Command Center";63;1
"Unit";"SCV";"Command Center";63;1
"Building";"SupplyDepot";NA;63;0
"Unit";"SCV";"Command Center";67;1
"Unit";"SCV";"Command Center";68;1
"Building";"StarportReactor";NA;61;0
"Building";"FactoryTechLab";NA;69;0
"Unit";"SCV";"Command Center";69;1
"Unit";"SCV";"Command Center";70;1
"Building";"SupplyDepot";NA;69;0
"Building";"EngineeringBay";NA;69;0
"Building";"SupplyDepot";NA;71;0
"Unit";"SCV";"Command Center";71;1
"Unit";"SCV";"Command Center";72;1
"Unit";"Hellion";"Factory";71;2
"Unit";"Hellion";"Factory";71;2
"Unit";"SCV";"Command Center";73;1
"Unit";"SCV";"Command Center";74;1
"Unit";"Thor";"Factory";69;6
"Unit";"Medivac";"Starport";71;2
"Unit";"Medivac";"Starport";71;2
"Unit";"SCV";"Command Center";79;1
"Unit";"SCV";"Command Center";79;1
"Unit";"SCV";"Command Center";80;1
"Unit";"Hellion";"Factory";79;2
"Building";"Refinery";NA;79;0
"Unit";"SCV";"Command Center";91;1
"Building";"Refinery";NA;81;0
"Unit";"SCV";"Command Center";92;1
"Unit";"SCV";"Command Center";93;1
"Building";"SupplyDepot";NA;91;0
"Unit";"SCV";"Command Center";96;1
"Unit";"Thor";"Factory";79;6
"Upgrade";"TerranVehicleWeaponsLevel1";"Armory";69;0
"Unit";"Hellion";"Factory";97;2
"Unit";"Hellion";"Factory";97;2
"Upgrade";"TerranVehicleAndShipArmorsLevel1";"Armory";71;0
"Building";"SupplyDepot";NA;99;0
"Unit";"SCV";"Command Center";106;1
"Unit";"SCV";"Command Center";106;1
"Unit";"SCV";"Command Center";106;1
"Building";"SensorTower";NA;110;0
"Building";"Factory";NA;99;0
"Building";"SupplyDepot";NA;110;0
"Unit";"Hellion";"Factory";113;2
"Unit";"Hellion";"Factory";113;2
"Building";"Factory";NA;106;0
"Unit";"SCV";"Command Center";117;1
"Unit";"SCV";"Command Center";117;1
"Unit";"Hellion";"Factory";113;2
"Unit";"SCV";"Command Center";117;1
"Unit";"SCV";"Command Center";117;1
"Unit";"SCV";"Command Center";118;1
"Building";"SupplyDepot";NA;117;0
"Building";"FactoryTechLab";NA;117;0
"Building";"CommandCenter";NA;110;0
"Unit";"SCV";"Command Center";122;1
"Unit";"SCV";"Command Center";122;1
"Building";"FactoryReactor";NA;122;0
"Building";"SupplyDepot";NA;124;0
"Building";"SupplyDepot";NA;124;0
"Unit";"SCV";"Command Center";126;1
"Unit";"SCV";"Command Center";126;1
"Unit";"SCV";"Command Center";126;1
"Unit";"SCV";"Command Center";126;1
"Unit";"SCV";"Command Center";127;1
"Unit";"SCV";"Command Center";128;1
"Building";"MissileTurret";NA;129;0
"Building";"MissileTurret";NA;129;0
"Building";"SupplyDepot";NA;126;0
"Building";"MissileTurret";NA;129;0
"Building";"MissileTurret";NA;129;0
"Unit";"SCV";"Command Center";132;1
"Unit";"SCV";"Command Center";132;1
"Unit";"SCV";"Command Center";132;1
"Building";"SensorTower";NA;132;0
"Unit";"Hellion";"Factory";132;2
"Unit";"Hellion";"Factory";132;2
"Unit";"Hellion";"Factory";132;2
"Unit";"SCV";"Command Center";135;1
"Unit";"SCV";"Command Center";135;1
"Building";"CommandCenter";NA;126;0
"Unit";"SCV";"Command Center";141;1
"Unit";"SCV";"Command Center";141;1
"Unit";"SCV";"Command Center";142;1
"Unit";"SCV";"Command Center";143;1
"Unit";"Thor";"Factory";135;6
"Unit";"Hellion";"Factory";144;2
"Unit";"Hellion";"Factory";144;2
"Unit";"Hellion";"Factory";144;2
"Upgrade";"TerranVehicleWeaponsLevel2";"Armory";126;0
"Upgrade";"TerranVehicleAndShipArmorsLevel2";"Armory";126;0
"Unit";"Thor";"Factory";141;6
"Unit";"SCV";"Command Center";159;1
"Unit";"SCV";"Command Center";159;1
"Building";"MissileTurret";NA;153;0
"Unit";"SCV";"Command Center";159;1
"Unit";"SCV";"Command Center";159;1
"Building";"MissileTurret";NA;153;0
"Building";"MissileTurret";NA;153;0
"Building";"MissileTurret";NA;165;0
