"type";"unit_name";"on_building";"total_supply";"supply"
"Building";"Refinery";NA;14;0
"Building";"Barracks";NA;15;0
"Unit";"Reaper";"Barracks";19;1
"Building";"Refinery";NA;21;0
"Building";"Factory";NA;19;0
"Building";"BarracksReactor";NA;21;0
"Building";"CommandCenter";NA;19;0
"Building";"Starport";NA;23;0
"Building";"BarracksTechLab";NA;25;0
"Unit";"Hellion";"Factory";24;2
"Unit";"Hellion";"Factory";24;2
"Unit";"Hellion";"Factory";30;2
"Unit";"Hellion";"Factory";30;2
"Unit";"Hellion";"Factory";39;2
"Unit";"Hellion";"Factory";39;2
"Unit";"Hellion";"Factory";47;2
"Unit";"Hellion";"Factory";47;2
"Unit";"Liberator";"Starport";40;3
"Unit";"Hellion";"Factory";58;2
"Unit";"Hellion";"Factory";58;2
"Building";"Refinery";NA;60;0
"Building";"Refinery";NA;60;0
"Unit";"Hellion";"Factory";67;2
"Unit";"Hellion";"Factory";67;2
"Building";"Armory";NA;60;0
"Building";"Armory";NA;60;0
"Building";"CommandCenter";NA;42;0
"Building";"BarracksTechLab";NA;75;0
"Building";"Factory";NA;68;0
"Building";"Factory";NA;68;0
"Unit";"Cyclone";"Factory";76;3
"Unit";"Cyclone";"Factory";76;3
"Building";"StarportReactor";NA;75;0
"Unit";"Hellion";"Factory";80;2
"Unit";"Hellion";"Factory";83;2
"Building";"Refinery";NA;87;0
"Unit";"Thor";"Factory";79;6
"Building";"Refinery";NA;89;0
"Unit";"Hellion";"Factory";95;2
"Unit";"Hellion";"Factory";96;2
"Unit";"Thor";"Factory";89;6
"Unit";"Medivac";"Starport";96;2
"Unit";"Medivac";"Starport";96;2
"Unit";"Hellion";"Factory";108;2
"Unit";"Hellion";"Factory";112;2
"Upgrade";"TerranVehicleWeaponsLevel1";"Armory";88;0
"Building";"EngineeringBay";NA;128;0
"Unit";"Hellion";"Factory";131;2
"Unit";"Hellion";"Factory";131;2
"Building";"Factory";NA;125;0
"Building";"Factory";NA;127;0
"Unit";"Medivac";"Starport";133;2
"Unit";"Medivac";"Starport";133;2
"Unit";"Hellion";"Factory";139;2
"Unit";"Hellion";"Factory";139;2
"Building";"FactoryTechLab";NA;146;0
"Building";"FactoryTechLab";NA;146;0
"Unit";"Medivac";"Starport";142;2
"Unit";"Medivac";"Starport";144;2
"Unit";"Hellion";"Factory";150;2
"Unit";"Hellion";"Factory";150;2
"Unit";"Hellion";"Factory";150;2
"Unit";"Hellion";"Factory";150;2
"Unit";"Hellion";"Factory";150;2
"Unit";"Hellion";"Factory";150;2
"Building";"SensorTower";NA;162;0
"Unit";"Hellion";"Factory";158;2
"Unit";"Hellion";"Factory";162;2
"Building";"CommandCenter";NA;141;0
"Unit";"Hellion";"Factory";162;2
"Unit";"Hellion";"Factory";162;2
"Unit";"Hellion";"Factory";166;2
"Unit";"Medivac";"Starport";162;2
"Unit";"Medivac";"Starport";162;2
"Unit";"Hellion";"Factory";170;2
"Unit";"Hellion";"Factory";170;2
"Building";"SensorTower";NA;174;0
"Building";"Refinery";NA;174;0
"Unit";"Hellion";"Factory";174;2
"Building";"Refinery";NA;176;0
"Unit";"Hellion";"Factory";184;2
"Unit";"Medivac";"Starport";176;2
"Unit";"Hellion";"Factory";184;2
"Unit";"Hellion";"Factory";184;2
"Unit";"Thor";"Factory";184;6
"Unit";"Hellion";"Factory";192;2
"Unit";"Hellion";"Factory";192;2
"Unit";"Hellion";"Factory";194;2
"Upgrade";"TerranVehicleWeaponsLevel2";"Armory";166;0
"Unit";"Hellion";"Factory";200;2
"Unit";"Thor";"Factory";192;6
"Unit";"Hellion";"Factory";204;2
"Unit";"Hellion";"Factory";207;2
"Unit";"Hellion";"Factory";207;2
"Building";"CommandCenter";NA;186;0
"Unit";"Hellion";"Factory";210;2
"Unit";"Hellion";"Factory";210;2
"Unit";"Hellion";"Factory";216;2
"Unit";"Hellion";"Factory";216;2
"Unit";"Hellion";"Factory";220;2
"Unit";"Hellion";"Factory";228;2
"Unit";"Hellion";"Factory";228;2
"Unit";"Hellion";"Factory";233;2
"Unit";"Hellion";"Factory";233;2
"Unit";"Hellion";"Factory";233;2
"Unit";"Hellion";"Factory";237;2
"Unit";"Medivac";"Starport";236;2
"Unit";"Medivac";"Starport";236;2
"Unit";"Hellion";"Factory";252;2
"Unit";"Hellion";"Factory";254;2
"Unit";"Hellion";"Factory";254;2
"Unit";"Hellion";"Factory";258;2
"Unit";"Hellion";"Factory";258;2
"Unit";"Hellion";"Factory";258;2
"Unit";"Medivac";"Starport";258;2
"Unit";"Medivac";"Starport";258;2
"Unit";"Hellion";"Factory";261;2
"Unit";"Hellion";"Factory";266;2
"Unit";"Hellion";"Factory";266;2
"Unit";"Hellion";"Factory";268;2
"Unit";"Hellion";"Factory";274;2
"Building";"Refinery";NA;284;0
"Unit";"Hellion";"Factory";288;2
"Unit";"Hellion";"Factory";288;2
"Unit";"Hellion";"Factory";295;2
"Unit";"Hellion";"Factory";295;2
"Unit";"Hellion";"Factory";295;2
"Unit";"Hellion";"Factory";295;2
"Unit";"Hellion";"Factory";299;2
"Unit";"Hellion";"Factory";299;2
"Building";"SensorTower";NA;301;0
"Unit";"Hellion";"Factory";311;2
"Unit";"Hellion";"Factory";311;2
"Unit";"Hellion";"Factory";311;2
"Unit";"Thor";"Factory";301;6
"Unit";"Hellion";"Factory";311;2
"Unit";"Hellion";"Factory";311;2
"Unit";"Hellion";"Factory";315;2
"Unit";"Hellion";"Factory";323;2
"Upgrade";"TerranShipWeaponsLevel1";"Armory";299;0
"Unit";"Hellion";"Factory";323;2
"Unit";"Hellion";"Factory";323;2
"Unit";"Hellion";"Factory";325;2
"Unit";"Hellion";"Factory";325;2
"Unit";"Hellion";"Factory";329;2
"Unit";"Hellion";"Factory";333;2
"Upgrade";"TerranVehicleWeaponsLevel3";"Armory";299;0
"Unit";"Hellion";"Factory";339;2
"Unit";"Hellion";"Factory";339;2
"Unit";"Hellion";"Factory";339;2
"Building";"Refinery";NA;341;0
"Unit";"Hellion";"Factory";344;2
"Unit";"Hellion";"Factory";348;2
"Building";"Refinery";NA;350;0
"Unit";"Hellion";"Factory";350;2
"Unit";"Hellion";"Factory";353;2
"Unit";"Hellion";"Factory";355;2
