"Type";"UnitName";"OnBuilding";"TotalSupply";"Supply"
"Unit";"SCV";"Command Center";12;1
"Unit";"SCV";"Command Center";12;1
"Unit";"SCV";"Command Center";13;1
"Building";"SupplyDepot";NA;13;0
"Unit";"SCV";"Command Center";15;1
"Unit";"SCV";"Command Center";15;1
"Building";"Refinery";NA;15;0
"Unit";"SCV";"Command Center";16;1
"Building";"Barracks";NA;15;0
"Unit";"SCV";"Command Center";18;1
"Unit";"Reaper";"Barracks";18;1
"Building";"SupplyDepot";NA;19;0
"Unit";"SCV";"Command Center";20;1
"Unit";"Marine";"Barracks";19;1
"Unit";"SCV";"Command Center";21;1
"Unit";"SCV";"Command Center";22;1
"Building";"CommandCenter";NA;19;0
"Building";"Factory";NA;20;0
"Unit";"SCV";"Command Center";24;1
"Unit";"SCV";"Command Center";25;1
"Building";"Refinery";NA;24;0
"Building";"BarracksReactor";NA;24;0
"Unit";"SCV";"Command Center";25;1
"Building";"Starport";NA;24;0
"Unit";"SCV";"Command Center";26;1
"Unit";"SCV";"Command Center";26;1
"Unit";"SCV";"Command Center";27;1
"Unit";"Hellion";"Factory";26;2
"Unit";"Hellion";"Factory";26;2
"Unit";"SCV";"Command Center";29;1
"Building";"BarracksTechLab";NA;28;0
"Unit";"SCV";"Command Center";29;1
"Building";"CommandCenter";NA;24;0
"Unit";"SCV";"Command Center";34;1
"Unit";"SCV";"Command Center";35;1
"Unit";"Hellion";"Factory";30;2
"Unit";"Hellion";"Factory";32;2
"Unit";"Marine";"Barracks";36;1
"Unit";"SCV";"Command Center";36;1
"Unit";"SCV";"Command Center";42;1
"Unit";"SCV";"Command Center";43;1
"Unit";"Marine";"Barracks";44;1
"Unit";"SCV";"Command Center";46;1
"Unit";"SCV";"Command Center";46;1
"Unit";"SCV";"Command Center";46;1
"Building";"EngineeringBay";NA;46;0
"Building";"EngineeringBay";NA;46;0
"Unit";"SCV";"Command Center";47;1
"Building";"FactoryReactor";NA;44;0
"Building";"SupplyDepot";NA;46;0
"Unit";"SCV";"Command Center";50;1
"Unit";"SCV";"Command Center";50;1
"Building";"Barracks";NA;42;0
"Building";"SupplyDepot";NA;47;0
"Building";"Refinery";NA;47;0
"Building";"Barracks";NA;44;0
"Building";"Refinery";NA;47;0
"Unit";"SCV";"Command Center";51;1
"Unit";"Marine";"Barracks";50;1
"Unit";"SCV";"Command Center";51;1
"Unit";"SCV";"Command Center";52;1
"Building";"StarportReactor";NA;50;0
"Unit";"SCV";"Command Center";57;1
"Unit";"SCV";"Command Center";57;1
"Unit";"Marine";"Barracks";57;1
"Unit";"Marine";"Barracks";57;1
"Building";"FactoryTechLab";NA;57;0
"Unit";"Marine";"Barracks";59;1
"Unit";"Marine";"Barracks";59;1
"Unit";"Marine";"Barracks";59;1
"Unit";"SCV";"Command Center";61;1
"Unit";"Marine";"Barracks";61;1
"Unit";"SCV";"Command Center";61;1
"Unit";"Marine";"Barracks";61;1
"Unit";"SCV";"Command Center";61;1
"Unit";"Medivac";"Starport";60;2
"Unit";"Medivac";"Starport";61;2
"Unit";"Marine";"Barracks";61;1
"Unit";"SCV";"Command Center";73;1
"Upgrade";"Stimpack";"TechLab";50;0
"Building";"SupplyDepot";NA;69;0
"Unit";"SCV";"Command Center";74;1
"Building";"SupplyDepot";NA;69;0
"Unit";"SCV";"Command Center";75;1
"Unit";"SCV";"Command Center";75;1
"Unit";"SCV";"Command Center";75;1
"Building";"SupplyDepot";NA;69;0
"Unit";"Marine";"Barracks";75;1
"Unit";"Marine";"Barracks";75;1
"Unit";"Marine";"Barracks";75;1
"Unit";"Marine";"Barracks";75;1
"Building";"SupplyDepot";NA;76;0
"Unit";"SCV";"Command Center";76;1
"Building";"Barracks";NA;73;0
"Unit";"Marine";"Barracks";76;1
"Upgrade";"TerranInfantryWeaponsLevel1";"EngineeringBay";61;0
"Unit";"SCV";"Command Center";83;1
"Unit";"SCV";"Command Center";83;1
"Unit";"Marine";"Barracks";79;1
"Building";"Armory";NA;74;0
"Building";"Barracks";NA;74;0
"Unit";"Marine";"Barracks";83;1
"Unit";"Marine";"Barracks";83;1
"Unit";"Marine";"Barracks";83;1
"Building";"SupplyDepot";NA;79;0
"Unit";"Medivac";"Starport";76;2
"Unit";"Medivac";"Starport";76;2
"Building";"SupplyDepot";NA;84;0
"Building";"SupplyDepot";NA;84;0
"Unit";"SCV";"Command Center";95;1
"Unit";"SCV";"Command Center";95;1
"Unit";"SCV";"Command Center";95;1
"Unit";"Marine";"Barracks";91;1
"Unit";"Marine";"Barracks";91;1
"Unit";"Marine";"Barracks";95;1
"Unit";"Marine";"Barracks";95;1
"Unit";"Marine";"Barracks";95;1
"Unit";"SCV";"Command Center";95;1
"Unit";"SCV";"Command Center";96;1
"Unit";"SCV";"Command Center";97;1
"Building";"Refinery";NA;95;0
"Upgrade";"TerranInfantryArmorsLevel1";"EngineeringBay";73;0
"Building";"Refinery";NA;95;0
"Unit";"Marine";"Barracks";98;1
"Unit";"Marine";"Barracks";100;1
"Building";"BarracksReactor";NA;91;0
"Building";"BarracksReactor";NA;91;0
"Unit";"Marine";"Barracks";100;1
"Unit";"Marine";"Barracks";101;1
"Unit";"Marine";"Barracks";102;1
"Unit";"Medivac";"Starport";98;2
"Unit";"Marine";"Barracks";106;1
"Unit";"Marine";"Barracks";107;1
"Unit";"Marine";"Barracks";111;1
"Unit";"Marine";"Barracks";111;1
"Unit";"Marine";"Barracks";111;1
"Unit";"Marine";"Barracks";111;1
"Unit";"Marine";"Barracks";111;1
"Unit";"Marine";"Barracks";111;1
"Unit";"Marine";"Barracks";111;1
"Unit";"Marine";"Barracks";113;1
"Unit";"Marine";"Barracks";114;1
"Unit";"Medivac";"Starport";113;2
"Unit";"Medivac";"Starport";113;2
"Unit";"Marine";"Barracks";115;1
"Unit";"Marine";"Barracks";116;1
"Unit";"Marine";"Barracks";122;1
"Unit";"Marine";"Barracks";122;1
"Unit";"Marine";"Barracks";122;1
"Unit";"Marine";"Barracks";122;1
"Building";"SupplyDepot";NA;122;0
"Building";"SupplyDepot";NA;122;0
"Building";"SupplyDepot";NA;122;0
"Building";"SupplyDepot";NA;122;0
"Building";"SupplyDepot";NA;122;0
"Unit";"Marine";"Barracks";124;1
"Building";"SupplyDepot";NA;122;0
"Unit";"Marine";"Barracks";124;1
"Building";"SupplyDepot";NA;122;0
"Unit";"Marauder";"Barracks";122;2
"Unit";"Marine";"Barracks";128;1
"Unit";"Marine";"Barracks";129;1
"Unit";"Marine";"Barracks";130;1
"Unit";"Marine";"Barracks";131;1
"Unit";"Marine";"Barracks";131;1
"Unit";"Marine";"Barracks";133;1
"Unit";"Marine";"Barracks";134;1
"Unit";"Marine";"Barracks";140;1
"Unit";"Marine";"Barracks";140;1
"Unit";"Marine";"Barracks";140;1
"Unit";"Marine";"Barracks";140;1
"Upgrade";"TerranVehicleAndShipArmorsLevel1";"Armory";108;0
"Unit";"Medivac";"Starport";134;2
"Unit";"Marine";"Barracks";140;1
"Unit";"Marine";"Barracks";141;1
"Building";"CommandCenter";NA;122;0
"Unit";"Marine";"Barracks";151;1
"Unit";"Marine";"Barracks";151;1
"Unit";"Marine";"Barracks";151;1
"Unit";"Marine";"Barracks";152;1
"Unit";"Marine";"Barracks";152;1
"Upgrade";"TerranInfantryWeaponsLevel2";"EngineeringBay";111;0
"Unit";"Marine";"Barracks";153;1
"Unit";"Marine";"Barracks";153;1
"Unit";"Marine";"Barracks";153;1
"Unit";"Marauder";"Barracks";151;2
"Unit";"Medivac";"Starport";153;2
"Unit";"Medivac";"Starport";153;2
"Unit";"Marine";"Barracks";158;1
"Unit";"Marine";"Barracks";158;1
"Unit";"Marine";"Barracks";158;1
"Unit";"Marine";"Barracks";161;1
"Unit";"Marine";"Barracks";161;1
"Unit";"Marine";"Barracks";161;1
"Unit";"Marine";"Barracks";161;1
"Unit";"Marine";"Barracks";161;1
"Unit";"Marine";"Barracks";163;1
"Unit";"Marine";"Barracks";167;1
"Unit";"Marine";"Barracks";168;1
"Unit";"Marine";"Barracks";169;1
"Unit";"Marine";"Barracks";170;1
"Unit";"Marine";"Barracks";171;1
"Unit";"Marine";"Barracks";176;1
"Unit";"Medivac";"Starport";170;2
"Upgrade";"TerranInfantryArmorsLevel2";"EngineeringBay";140;0
"Unit";"Marine";"Barracks";181;1
"Unit";"Marine";"Barracks";181;1
"Unit";"Marine";"Barracks";181;1
"Unit";"Marine";"Barracks";181;1
"Unit";"Marine";"Barracks";181;1
"Unit";"Marine";"Barracks";181;1
"Unit";"Marine";"Barracks";181;1
"Unit";"Marine";"Barracks";181;1
"Unit";"SCV";"Command Center";184;1
"Unit";"SCV";"Command Center";184;1
"Building";"Barracks";NA;176;0
"Unit";"Marine";"Barracks";184;1
"Unit";"Marine";"Barracks";184;1
"Unit";"Marine";"Barracks";185;1
"Unit";"Marine";"Barracks";191;1
"Unit";"Marine";"Barracks";191;1
"Unit";"Marine";"Barracks";195;1
"Unit";"Marine";"Barracks";195;1
"Unit";"Marine";"Barracks";196;1
"Unit";"Marine";"Barracks";196;1
"Unit";"Marine";"Barracks";196;1
"Unit";"Marine";"Barracks";196;1
"Unit";"Marine";"Barracks";197;1
"Unit";"Marine";"Barracks";197;1
"Unit";"Marine";"Barracks";199;1
"Unit";"Marauder";"Barracks";195;2
"Unit";"SCV";"Command Center";199;1
"Unit";"SCV";"Command Center";199;1
"Unit";"SCV";"Command Center";199;1
"Unit";"Marine";"Barracks";199;1
"Unit";"Marine";"Barracks";200;1
"Unit";"Marine";"Barracks";201;1
"Unit";"Marine";"Barracks";201;1
"Building";"SupplyDepot";NA;199;0
"Building";"SupplyDepot";NA;199;0
"Unit";"Liberator";"Starport";199;3
"Unit";"Marine";"Barracks";217;1
"Unit";"Marine";"Barracks";217;1
"Unit";"Marine";"Barracks";217;1
"Unit";"Marine";"Barracks";220;1
"Unit";"Marine";"Barracks";220;1
"Unit";"Marine";"Barracks";220;1
"Unit";"Marine";"Barracks";220;1
"Unit";"Marine";"Barracks";220;1
"Unit";"Marine";"Barracks";220;1
"Unit";"Marine";"Barracks";220;1
"Unit";"Marine";"Barracks";220;1
"Unit";"Marine";"Barracks";221;1
"Unit";"Marine";"Barracks";222;1
