"Type";"UnitName";"OnBuilding";"TotalSupply";"Supply"
"Unit";"SCV";"Command Center";12;1
"Unit";"SCV";"Command Center";12;1
"Unit";"SCV";"Command Center";13;1
"Building";"SupplyDepot";NA;13;0
"Building";"Refinery";NA;13;0
"Unit";"SCV";"Command Center";15;1
"Unit";"SCV";"Command Center";16;1
"Unit";"SCV";"Command Center";16;1
"Building";"Barracks";NA;15;0
"Unit";"SCV";"Command Center";18;1
"Unit";"Reaper";"Barracks";19;1
"Unit";"SCV";"Command Center";19;1
"Unit";"SCV";"Command Center";20;1
"Building";"SupplyDepot";NA;21;0
"Unit";"SCV";"Command Center";22;1
"Building";"BarracksReactor";NA;20;0
"Building";"Factory";NA;19;0
"Unit";"SCV";"Command Center";22;1
"Building";"CommandCenter";NA;19;0
"Unit";"SCV";"Command Center";23;1
"Building";"Refinery";NA;23;0
"Unit";"Marine";"Barracks";24;1
"Unit";"SCV";"Command Center";24;1
"Unit";"Hellion";"Factory";24;2
"Unit";"Hellion";"Factory";24;2
"Building";"Starport";NA;23;0
"Unit";"SCV";"Command Center";26;1
"Unit";"Marine";"Barracks";29;1
"Unit";"SCV";"Command Center";32;1
"Unit";"Hellion";"Factory";31;2
"Unit";"Hellion";"Factory";31;2
"Unit";"SCV";"Command Center";33;1
"Unit";"Marine";"Barracks";32;1
"Unit";"SCV";"Command Center";36;1
"Unit";"SCV";"Command Center";38;1
"Building";"Armory";NA;27;0
"Unit";"Medivac";"Starport";32;2
"Unit";"Hellion";"Factory";36;2
"Building";"SupplyDepot";NA;40;0
"Unit";"SCV";"Command Center";46;1
"Unit";"SCV";"Command Center";46;1
"Building";"BarracksTechLab";NA;46;0
"Unit";"Hellion";"Factory";46;2
"Unit";"SCV";"Command Center";46;1
"Unit";"SCV";"Command Center";46;1
"Building";"SupplyDepot";NA;46;0
"Unit";"Hellion";"Factory";46;2
"Unit";"SCV";"Command Center";50;1
"Unit";"Liberator";"Starport";46;3
"Building";"SupplyDepot";NA;54;0
"Unit";"SCV";"Command Center";55;1
"Unit";"SCV";"Command Center";55;1
"Unit";"Marine";"Barracks";58;1
"Unit";"SCV";"Command Center";60;1
"Unit";"SCV";"Command Center";61;1
"Unit";"SCV";"Command Center";61;1
"Unit";"Marine";"Barracks";60;1
"Building";"FactoryTechLab";NA;61;0
"Building";"StarportReactor";NA;58;0
"Building";"Refinery";NA;61;0
"Building";"Refinery";NA;61;0
"Unit";"SCV";"Command Center";64;1
"Unit";"SCV";"Command Center";64;1
"Building";"CommandCenter";NA;52;0
"Unit";"Marine";"Barracks";65;1
"Building";"Barracks";NA;60;0
"Unit";"SCV";"Command Center";65;1
"Building";"Barracks";NA;60;0
"Unit";"SCV";"Command Center";67;1
"Unit";"SCV";"Command Center";69;1
"Unit";"Marine";"Barracks";67;1
"Unit";"SCV";"Command Center";70;1
"Building";"EngineeringBay";NA;67;0
"Building";"EngineeringBay";NA;67;0
"Unit";"Marine";"Barracks";69;1
"Unit";"Marine";"Barracks";69;1
"Unit";"SCV";"Command Center";70;1
"Unit";"SCV";"Command Center";72;1
"Unit";"Marine";"Barracks";71;1
"Unit";"Marine";"Barracks";72;1
"Unit";"Marine";"Barracks";72;1
"Unit";"SCV";"Command Center";75;1
"Unit";"Marine";"Barracks";73;1
"Unit";"Marine";"Barracks";74;1
"Building";"StarportReactor";NA;70;0
"Unit";"SCV";"Command Center";78;1
"Unit";"SCV";"Command Center";80;1
"Unit";"Marine";"Barracks";77;1
"Unit";"Marine";"Barracks";78;1
"Unit";"Marine";"Barracks";79;1
"Unit";"Marine";"Barracks";83;1
"Unit";"Marine";"Barracks";83;1
"Building";"SupplyDepot";NA;83;0
"Unit";"SCV";"Command Center";86;1
"Unit";"SCV";"Command Center";86;1
"Upgrade";"Stimpack";"TechLab";64;0
"Building";"SupplyDepot";NA;83;0
"Unit";"Marine";"Barracks";85;1
"Building";"SupplyDepot";NA;85;0
"Unit";"SCV";"Command Center";88;1
"Building";"SupplyDepot";NA;86;0
"Unit";"SCV";"Command Center";90;1
"Unit";"SCV";"Command Center";91;1
"Unit";"SCV";"Command Center";94;1
"Unit";"SCV";"Command Center";94;1
"Building";"SupplyDepot";NA;93;0
"Unit";"SCV";"Command Center";96;1
"Building";"Refinery";NA;95;0
"Unit";"Marine";"Barracks";96;1
"Unit";"Marine";"Barracks";96;1
"Unit";"SCV";"Command Center";96;1
"Unit";"Marine";"Barracks";96;1
"Unit";"Medivac";"Starport";92;2
"Unit";"Medivac";"Starport";92;2
"Unit";"SCV";"Command Center";97;1
"Building";"Refinery";NA;96;0
"Unit";"Marine";"Barracks";98;1
"Unit";"SCV";"Command Center";98;1
"Unit";"SCV";"Command Center";101;1
"Building";"Barracks";NA;92;0
"Building";"Barracks";NA;92;0
"Building";"SupplyDepot";NA;108;0
"Building";"SupplyDepot";NA;108;0
"Unit";"SCV";"Command Center";111;1
"Unit";"SCV";"Command Center";111;1
"Unit";"SCV";"Command Center";111;1
"Unit";"Marine";"Barracks";111;1
"Unit";"Marine";"Barracks";111;1
"Unit";"Marine";"Barracks";111;1
"Building";"Bunker";NA;108;0
"Upgrade";"TerranInfantryWeaponsLevel1";"EngineeringBay";88;0
"Upgrade";"TerranInfantryArmorsLevel1";"EngineeringBay";88;0
"Upgrade";"TerranVehicleAndShipArmorsLevel1";"Armory";91;0
"Unit";"SCV";"Command Center";117;1
"Unit";"SCV";"Command Center";117;1
"Unit";"SCV";"Command Center";117;1
"Building";"BarracksReactor";NA;111;0
"Building";"BarracksReactor";NA;111;0
"Unit";"Marine";"Barracks";117;1
"Unit";"Marine";"Barracks";117;1
"Unit";"Marine";"Barracks";117;1
"Unit";"Marine";"Barracks";117;1
"Building";"SupplyDepot";NA;117;0
"Unit";"Marine";"Barracks";124;1
"Unit";"Marine";"Barracks";124;1
"Unit";"Marine";"Barracks";124;1
"Unit";"Marine";"Barracks";124;1
"Unit";"Marine";"Barracks";124;1
"Unit";"Marine";"Barracks";124;1
"Unit";"Marine";"Barracks";124;1
"Unit";"Marine";"Barracks";124;1
"Unit";"Marine";"Barracks";124;1
"Unit";"SCV";"Command Center";124;1
"Unit";"SCV";"Command Center";124;1
"Unit";"SCV";"Command Center";124;1
"Building";"SupplyDepot";NA;124;0
"Building";"SupplyDepot";NA;124;0
"Unit";"SCV";"Command Center";133;1
"Unit";"SCV";"Command Center";134;1
"Unit";"SCV";"Command Center";135;1
"Unit";"Medivac";"Starport";124;2
"Unit";"Medivac";"Starport";124;2
"Building";"CommandCenter";NA;111;0
"Building";"Barracks";NA;120;0
"Building";"Barracks";NA;120;0
"Building";"Barracks";NA;124;0
"Building";"Factory";NA;130;0
"Unit";"SCV";"Command Center";143;1
"Unit";"SCV";"Command Center";143;1
"Unit";"SCV";"Command Center";143;1
"Building";"MissileTurret";NA;143;0
"Building";"Refinery";NA;143;0
"Building";"Refinery";NA;143;0
"Building";"BarracksTechLab";NA;143;0
"Building";"BarracksTechLab";NA;143;0
"Building";"BarracksTechLab";NA;143;0
"Unit";"Marine";"Barracks";143;1
"Unit";"Marine";"Barracks";143;1
"Unit";"Marine";"Barracks";143;1
"Unit";"Marine";"Barracks";143;1
"Unit";"Marine";"Barracks";143;1
"Unit";"Marauder";"Barracks";143;2
"Unit";"Marine";"Barracks";146;1
"Unit";"Marine";"Barracks";146;1
"Unit";"Marine";"Barracks";146;1
"Building";"FactoryTechLab";NA;151;0
"Unit";"SCV";"Command Center";153;1
"Unit";"Marauder";"Barracks";151;2
"Building";"GhostAcademy";NA;146;0
"Unit";"Marine";"Barracks";156;1
"Unit";"Marine";"Barracks";156;1
"Building";"Starport";NA;146;0
"Unit";"Marine";"Barracks";156;1
"Unit";"Marauder";"Barracks";156;2
"Unit";"Marauder";"Barracks";156;2
"Unit";"Marauder";"Barracks";156;2
"Unit";"Liberator";"Starport";151;3
"Unit";"Marauder";"Barracks";157;2
"Building";"FusionCore";NA;149;0
"Unit";"Marine";"Barracks";168;1
"Unit";"Marine";"Barracks";168;1
"Unit";"Marine";"Barracks";168;1
"Unit";"Marine";"Barracks";168;1
"Unit";"Marine";"Barracks";168;1
"Unit";"Marine";"Barracks";168;1
"Unit";"Marine";"Barracks";168;1
"Unit";"Marauder";"Barracks";162;2
"Unit";"Marauder";"Barracks";164;2
"Unit";"Marauder";"Barracks";168;2
"Unit";"Marauder";"Barracks";171;2
"Building";"SensorTower";NA;173;0
"Building";"SensorTower";NA;173;0
"Upgrade";"TerranVehicleAndShipArmorsLevel2";"Armory";143;0
"Unit";"Marine";"Barracks";174;1
"Unit";"Marine";"Barracks";174;1
"Upgrade";"TerranInfantryWeaponsLevel2";"EngineeringBay";143;0
"Upgrade";"TerranInfantryArmorsLevel2";"EngineeringBay";143;0
"Unit";"Marauder";"Barracks";180;2
"Building";"SensorTower";NA;186;0
"Building";"StarportTechLab";NA;186;0
"Building";"SupplyDepot";NA;186;0
"Unit";"Marauder";"Barracks";188;2
"Unit";"Marauder";"Barracks";188;2
"Unit";"Marauder";"Barracks";188;2
"Unit";"Marine";"Barracks";190;1
"Unit";"Marine";"Barracks";190;1
"Unit";"Marine";"Barracks";190;1
"Unit";"Liberator";"Starport";178;3
"Unit";"Liberator";"Starport";179;3
"Unit";"Marauder";"Barracks";192;2
"Unit";"Marauder";"Barracks";192;2
"Unit";"Marauder";"Barracks";192;2
"Unit";"Marauder";"Barracks";207;2
"Unit";"Marine";"Barracks";213;1
"Unit";"Marine";"Barracks";213;1
"Unit";"Marine";"Barracks";213;1
"Unit";"Marine";"Barracks";213;1
"Unit";"Ghost";"Barracks";213;2
"Unit";"Marauder";"Barracks";213;2
"Unit";"Marauder";"Barracks";213;2
"Unit";"Marauder";"Barracks";213;2
"Unit";"Liberator";"Starport";213;3
"Unit";"Liberator";"Starport";213;3
"Unit";"Marauder";"Barracks";219;2
"Unit";"Liberator";"Starport";213;3
"Building";"Refinery";NA;235;0
"Unit";"Marine";"Barracks";235;1
"Unit";"Marine";"Barracks";235;1
"Unit";"Marine";"Barracks";235;1
"Unit";"Marine";"Barracks";235;1
"Unit";"Marine";"Barracks";235;1
"Unit";"Marine";"Barracks";235;1
"Unit";"Marine";"Barracks";235;1
"Unit";"Marine";"Barracks";235;1
"Unit";"Marauder";"Barracks";235;2
"Unit";"Marauder";"Barracks";235;2
"Unit";"Marauder";"Barracks";235;2
"Unit";"Marauder";"Barracks";235;2
"Unit";"Liberator";"Starport";227;3
"Unit";"SCV";"Command Center";244;1
"Unit";"SCV";"Command Center";246;1
