"type";"unit_name";"on_building";"total_supply_lag";"supply"
"Building";"Barracks";NA;16;0
"Building";"Refinery";NA;16;0
"Unit";"Reaper";"Barracks";19;1
"Building";"CommandCenter";NA;20;0
"Unit";"Marine";"Barracks";21;1
"Building";"Factory";NA;23;0
"Building";"Refinery";NA;23;0
"Building";"BarracksReactor";NA;24;0
"Building";"Starport";NA;27;0
"Unit";"Hellion";"Factory";27;2
"Unit";"Hellion";"Factory";29;2
"Building";"BarracksTechLab";NA;31;0
"Unit";"Hellion";"Factory";34;2
"Unit";"Hellion";"Factory";36;2
"Unit";"Hellion";"Factory";42;2
"Unit";"Hellion";"Factory";44;2
"Building";"CommandCenter";NA;50;0
"Unit";"Liberator";"Starport";52;3
"Building";"BarracksTechLab";NA;55;0
"Building";"EngineeringBay";NA;59;0
"Building";"EngineeringBay";NA;59;0
"Unit";"Cyclone";"Factory";59;3
"Unit";"Cyclone";"Factory";62;3
"Unit";"Marine";"Barracks";65;1
"Building";"Barracks";NA;66;0
"Building";"Barracks";NA;67;0
"Building";"Refinery";NA;68;0
"Building";"Refinery";NA;68;0
"Unit";"Marine";"Barracks";70;1
"Upgrade";"Stimpack";"TechLab";75;0
"Unit";"Marine";"Barracks";75;1
"Building";"StarportReactor";NA;76;0
"Building";"Barracks";NA;77;0
"Building";"BarracksReactor";NA;77;0
"Building";"Barracks";NA;78;0
"Upgrade";"TerranInfantryWeaponsLevel1";"EngineeringBay";78;0
"Unit";"Marine";"Barracks";80;1
"Building";"Barracks";NA;83;0
"Building";"Armory";NA;83;0
"Unit";"Marine";"Barracks";84;1
"Unit";"Marine";"Barracks";85;1
"Unit";"Marine";"Barracks";86;1
"Unit";"Marine";"Barracks";87;1
"Unit";"Marine";"Barracks";88;1
"Unit";"Medivac";"Starport";89;2
"Unit";"Medivac";"Starport";91;2
"Building";"BarracksReactor";NA;96;0
"Building";"BarracksReactor";NA;97;0
"Unit";"Marine";"Barracks";98;1
"Unit";"Marine";"Barracks";99;1
"Unit";"Marine";"Barracks";104;1
"Unit";"Marine";"Barracks";105;1
"Unit";"Marine";"Barracks";106;1
"Unit";"Marine";"Barracks";107;1
"Unit";"Marine";"Barracks";108;1
"Building";"Factory";NA;109;0
"Unit";"Marine";"Barracks";111;1
"Unit";"Marine";"Barracks";112;1
"Building";"BarracksReactor";NA;113;0
"Unit";"Marine";"Barracks";113;1
"Unit";"Marine";"Barracks";114;1
"Unit";"Marine";"Barracks";115;1
"Unit";"Marine";"Barracks";116;1
"Unit";"Marine";"Barracks";117;1
"Unit";"Marine";"Barracks";118;1
"Unit";"Marine";"Barracks";119;1
"Unit";"Marine";"Barracks";120;1
"Unit";"Marine";"Barracks";121;1
"Unit";"Marine";"Barracks";122;1
"Unit";"Marine";"Barracks";123;1
"Unit";"Marine";"Barracks";124;1
"Unit";"Marine";"Barracks";125;1
"Unit";"Marine";"Barracks";126;1
"Unit";"Marine";"Barracks";127;1
"Unit";"Marine";"Barracks";128;1
"Unit";"Medivac";"Starport";129;2
"Unit";"Medivac";"Starport";131;2
"Building";"FactoryTechLab";NA;133;0
"Unit";"Marine";"Barracks";133;1
"Unit";"Marine";"Barracks";134;1
"Building";"Refinery";NA;135;0
"Building";"Refinery";NA;135;0
"Unit";"Marine";"Barracks";135;1
"Unit";"Marine";"Barracks";136;1
"Unit";"Marine";"Barracks";137;1
"Unit";"Marine";"Barracks";138;1
"Unit";"Marine";"Barracks";139;1
"Upgrade";"TerranInfantryWeaponsLevel2";"EngineeringBay";140;0
"Unit";"Marine";"Barracks";140;1
"Unit";"Marine";"Barracks";141;1
"Unit";"Marine";"Barracks";142;1
"Unit";"Marine";"Barracks";143;1
"Unit";"Marine";"Barracks";144;1
"Unit";"Marine";"Barracks";145;1
"Unit";"Marine";"Barracks";146;1
"Unit";"Marine";"Barracks";147;1
"Unit";"Marine";"Barracks";148;1
"Unit";"Marine";"Barracks";149;1
"Unit";"Marine";"Barracks";150;1
"Unit";"Marine";"Barracks";154;1
"Unit";"Marine";"Barracks";155;1
"Unit";"Marine";"Barracks";158;1
"Unit";"Marine";"Barracks";159;1
"Unit";"Marine";"Barracks";160;1
"Unit";"Marine";"Barracks";161;1
"Unit";"Marine";"Barracks";162;1
"Unit";"Marine";"Barracks";163;1
"Unit";"Marine";"Barracks";164;1
"Unit";"Marine";"Barracks";165;1
"Unit";"Marine";"Barracks";166;1
"Building";"BarracksTechLab";NA;167;0
"Unit";"Marine";"Barracks";167;1
"Unit";"Marine";"Barracks";168;1
"Unit";"Marine";"Barracks";169;1
"Unit";"Marine";"Barracks";170;1
"Unit";"Marine";"Barracks";171;1
"Unit";"Marine";"Barracks";172;1
"Building";"CommandCenter";NA;173;0
"Unit";"Marine";"Barracks";173;1
"Unit";"Marine";"Barracks";177;1
"Unit";"Marine";"Barracks";178;1
"Unit";"Marine";"Barracks";179;1
"Unit";"Marine";"Barracks";180;1
"Unit";"Marine";"Barracks";181;1
"Unit";"Marine";"Barracks";182;1
"Unit";"Marine";"Barracks";183;1
"Unit";"Marine";"Barracks";187;1
"Unit";"Marine";"Barracks";188;1
"Unit";"Marine";"Barracks";189;1
"Unit";"Medivac";"Starport";190;2
"Unit";"Marine";"Barracks";192;1
"Unit";"Marine";"Barracks";193;1
"Unit";"Marine";"Barracks";194;1
"Unit";"Marauder";"Barracks";195;2
"Unit";"Marauder";"Barracks";197;2
"Unit";"Marine";"Barracks";199;1
"Unit";"Marine";"Barracks";200;1
"Unit";"Marine";"Barracks";201;1
"Unit";"Marine";"Barracks";202;1
"Unit";"Marine";"Barracks";203;1
"Unit";"Marine";"Barracks";204;1
"Unit";"Marine";"Barracks";205;1
"Unit";"Marine";"Barracks";206;1
"Unit";"Medivac";"Starport";207;2
"Unit";"Marauder";"Barracks";209;2
"Unit";"Marauder";"Barracks";211;2
"Unit";"Marine";"Barracks";213;1
"Unit";"Marine";"Barracks";214;1
"Upgrade";"TerranVehicleWeaponsLevel1";"Armory";215;0
"Unit";"Medivac";"Starport";215;2
"Unit";"Marauder";"Barracks";217;2
"Unit";"Marauder";"Barracks";219;2
"Unit";"Marine";"Barracks";221;1
"Unit";"Marine";"Barracks";222;1
"Unit";"Marine";"Barracks";223;1
"Unit";"Marine";"Barracks";224;1
"Unit";"Marine";"Barracks";225;1
"Unit";"Marine";"Barracks";226;1
"Unit";"Medivac";"Starport";227;2
"Unit";"Marine";"Barracks";229;1
"Unit";"Marine";"Barracks";230;1
"Unit";"Marauder";"Barracks";231;2
"Unit";"Marauder";"Barracks";233;2
"Unit";"Marine";"Barracks";235;1
"Unit";"Marine";"Barracks";236;1
"Unit";"Marine";"Barracks";237;1
"Unit";"Marine";"Barracks";238;1
"Unit";"Marine";"Barracks";239;1
"Unit";"Marine";"Barracks";240;1
"Unit";"Medivac";"Starport";244;2
"Unit";"Marine";"Barracks";246;1
"Unit";"Marine";"Barracks";247;1
"Unit";"Medivac";"Starport";248;2
"Unit";"Marine";"Barracks";251;1
"Unit";"Marine";"Barracks";252;1
"Unit";"Marine";"Barracks";253;1
"Unit";"Marine";"Barracks";254;1
"Unit";"Marine";"Barracks";255;1
"Unit";"Marauder";"Barracks";256;2
"Unit";"Marauder";"Barracks";258;2
"Unit";"Marine";"Barracks";260;1
"Unit";"Marine";"Barracks";261;1
"Unit";"Marine";"Barracks";262;1
"Unit";"Marine";"Barracks";263;1
"Unit";"Marine";"Barracks";264;1
"Unit";"Marine";"Barracks";265;1
"Unit";"Marine";"Barracks";266;1
"Unit";"Marine";"Barracks";267;1
"Unit";"Marine";"Barracks";268;1
"Upgrade";"SprayTerran";NA;269;0
"Upgrade";"SprayTerran";NA;269;0
"Upgrade";"SprayTerran";NA;269;0
"Upgrade";"SprayTerran";NA;269;0
"Upgrade";"TerranInfantryArmorsLevel1";NA;269;0
"Upgrade";"ShieldWall";NA;269;0
"Upgrade";"SprayTerran";NA;269;0
"Upgrade";"SprayTerran";NA;269;0
"Upgrade";"TerranInfantryArmorsLevel2";NA;269;0
