"Type";"UnitName";"OnBuilding";"TotalSupply";"Supply"
"Unit";"SCV";"Command Center";12;1
"Unit";"SCV";"Command Center";12;1
"Unit";"SCV";"Command Center";13;1
"Building";"SupplyDepot";NA;13;0
"Building";"Refinery";NA;14;0
"Unit";"SCV";"Command Center";15;1
"Unit";"SCV";"Command Center";15;1
"Unit";"SCV";"Command Center";16;1
"Unit";"SCV";"Command Center";17;1
"Building";"Barracks";NA;15;0
"Unit";"Reaper";"Barracks";19;1
"Unit";"SCV";"Command Center";19;1
"Unit";"SCV";"Command Center";20;1
"Building";"Refinery";NA;19;0
"Unit";"SCV";"Command Center";21;1
"Building";"SupplyDepot";NA;21;0
"Building";"Factory";NA;19;0
"Building";"BarracksReactor";NA;20;0
"Unit";"SCV";"Command Center";23;1
"Building";"CommandCenter";NA;19;0
"Building";"BarracksTechLab";NA;24;0
"Unit";"Hellion";"Factory";23;2
"Unit";"Hellion";"Factory";24;2
"Unit";"SCV";"Command Center";24;1
"Building";"Starport";NA;23;0
"Unit";"Hellion";"Factory";24;2
"Building";"SupplyDepot";NA;28;0
"Unit";"SCV";"Command Center";29;1
"Unit";"Hellion";"Factory";29;2
"Unit";"SCV";"Command Center";29;1
"Building";"BarracksTechLab";NA;29;0
"Unit";"SCV";"Command Center";34;1
"Unit";"SCV";"Command Center";35;1
"Unit";"Hellion";"Factory";35;2
"Unit";"Hellion";"Factory";35;2
"Unit";"SCV";"Command Center";36;1
"Unit";"SCV";"Command Center";37;1
"Building";"SupplyDepot";NA;36;0
"Unit";"SCV";"Command Center";41;1
"Unit";"SCV";"Command Center";42;1
"Unit";"Marine";"Barracks";41;1
"Unit";"Marine";"Barracks";41;1
"Unit";"SCV";"Command Center";43;1
"Unit";"SCV";"Command Center";44;1
"Unit";"SCV";"Command Center";47;1
"Unit";"SCV";"Command Center";49;1
"Unit";"SCV";"Command Center";49;1
"Unit";"Marine";"Barracks";49;1
"Unit";"Marine";"Barracks";49;1
"Unit";"SCV";"Command Center";51;1
"Unit";"Raven";"Starport";45;2
"Unit";"SCV";"Command Center";51;1
"Unit";"SCV";"Command Center";54;1
"Unit";"SCV";"Command Center";57;1
"Unit";"SCV";"Command Center";58;1
"Building";"SupplyDepot";NA;58;0
"Unit";"SCV";"Command Center";60;1
"Unit";"SCV";"Command Center";60;1
"Building";"Refinery";NA;59;0
"Building";"Refinery";NA;60;0
"Building";"EngineeringBay";NA;59;0
"Building";"EngineeringBay";NA;59;0
"Unit";"SCV";"Command Center";61;1
"Building";"FactoryReactor";NA;58;0
"Unit";"SCV";"Command Center";62;1
"Unit";"Raven";"Starport";58;2
"Unit";"Marine";"Barracks";63;1
"Unit";"SCV";"Command Center";64;1
"Building";"Barracks";NA;59;0
"Building";"Barracks";NA;59;0
"Unit";"SCV";"Command Center";67;1
"Building";"CommandCenter";NA;54;0
"Unit";"SCV";"Command Center";69;1
"Unit";"Marine";"Barracks";69;1
"Unit";"SCV";"Command Center";70;1
"Unit";"Marine";"Barracks";69;1
"Unit";"Marine";"Barracks";69;1
"Building";"Barracks";NA;63;0
"Building";"Barracks";NA;63;0
"Unit";"Marine";"Barracks";71;1
"Unit";"Marine";"Barracks";71;1
"Building";"StarportReactor";NA;69;0
"Building";"SupplyDepot";NA;72;0
"Building";"SupplyDepot";NA;72;0
"Building";"SupplyDepot";NA;73;0
"Unit";"SCV";"Command Center";75;1
"Unit";"Marine";"Barracks";75;1
"Unit";"SCV";"Command Center";75;1
"Unit";"Marine";"Barracks";75;1
"Unit";"Marine";"Barracks";75;1
"Unit";"Marine";"Barracks";77;1
"Unit";"Marine";"Barracks";77;1
"Unit";"SCV";"Command Center";82;1
"Unit";"SCV";"Command Center";82;1
"Building";"BarracksReactor";NA;75;0
"Building";"BarracksReactor";NA;75;0
"Unit";"Marine";"Barracks";82;1
"Unit";"Marine";"Barracks";82;1
"Unit";"Marine";"Barracks";82;1
"Unit";"Medivac";"Starport";77;2
"Unit";"Medivac";"Starport";77;2
"Unit";"SCV";"Command Center";86;1
"Unit";"SCV";"Command Center";86;1
"Unit";"Marine";"Barracks";86;1
"Unit";"Marine";"Barracks";86;1
"Upgrade";"Stimpack";"TechLab";68;0
"Unit";"Marine";"Barracks";86;1
"Building";"Refinery";NA;89;0
"Unit";"SCV";"Command Center";93;1
"Unit";"Marine";"Barracks";93;1
"Unit";"Marine";"Barracks";93;1
"Unit";"Marine";"Barracks";93;1
"Unit";"Marine";"Barracks";95;1
"Unit";"Marine";"Barracks";95;1
"Unit";"Marine";"Barracks";95;1
"Unit";"SCV";"Command Center";98;1
"Building";"Refinery";NA;94;0
"Unit";"Marine";"Barracks";95;1
"Upgrade";"TerranInfantryWeaponsLevel1";"EngineeringBay";73;0
"Upgrade";"TerranInfantryArmorsLevel1";"EngineeringBay";73;0
"Unit";"Marine";"Barracks";98;1
"Building";"Factory";NA;84;0
"Unit";"Marine";"Barracks";98;1
"Unit";"SCV";"Command Center";102;1
"Unit";"Marine";"Barracks";99;1
"Building";"SupplyDepot";NA;102;0
"Building";"Armory";NA;91;0
"Building";"MissileTurret";NA;110;0
"Building";"MissileTurret";NA;110;0
"Unit";"SCV";"Command Center";111;1
"Building";"MissileTurret";NA;111;0
"Unit";"Marine";"Barracks";111;1
"Unit";"Marine";"Barracks";111;1
"Unit";"Marine";"Barracks";111;1
"Unit";"SCV";"Command Center";112;1
"Unit";"Medivac";"Starport";111;2
"Unit";"Medivac";"Starport";111;2
"Unit";"Marine";"Barracks";112;1
"Unit";"Marine";"Barracks";112;1
"Unit";"Marine";"Barracks";115;1
"Unit";"Marine";"Barracks";115;1
"Unit";"Marine";"Barracks";115;1
"Unit";"Marine";"Barracks";115;1
"Unit";"Marine";"Barracks";115;1
"Unit";"Marine";"Barracks";115;1
"Unit";"Marine";"Barracks";115;1
"Building";"FactoryTechLab";NA;120;0
"Unit";"Marine";"Barracks";120;1
"Unit";"Marine";"Barracks";121;1
"Unit";"Marine";"Barracks";128;1
"Unit";"Marine";"Barracks";128;1
"Unit";"Marine";"Barracks";128;1
"Unit";"Marine";"Barracks";128;1
"Unit";"Marine";"Barracks";128;1
"Unit";"Marine";"Barracks";128;1
"Building";"SupplyDepot";NA;128;0
"Building";"SupplyDepot";NA;128;0
"Building";"SupplyDepot";NA;129;0
"Unit";"Medivac";"Starport";128;2
"Unit";"SCV";"Command Center";137;1
"Unit";"Marine";"Barracks";137;1
"Unit";"Marine";"Barracks";137;1
"Unit";"Marine";"Barracks";137;1
"Unit";"Marine";"Barracks";137;1
"Unit";"Medivac";"Starport";137;2
"Unit";"Marine";"Barracks";140;1
"Unit";"Marine";"Barracks";140;1
"Unit";"Marine";"Barracks";140;1
"Unit";"Marine";"Barracks";140;1
"Unit";"Marine";"Barracks";140;1
"Unit";"Marine";"Barracks";144;1
"Unit";"Marine";"Barracks";144;1
"Unit";"Marine";"Barracks";144;1
"Unit";"Marine";"Barracks";144;1
"Unit";"Medivac";"Starport";140;2
"Unit";"Marine";"Barracks";146;1
"Unit";"Marine";"Barracks";147;1
"Unit";"Marine";"Barracks";151;1
"Unit";"Marine";"Barracks";151;1
"Building";"CommandCenter";NA;128;0
"Unit";"Marine";"Barracks";151;1
"Unit";"Marine";"Barracks";151;1
"Unit";"Medivac";"Starport";144;2
"Unit";"Marine";"Barracks";157;1
"Building";"SupplyDepot";NA;155;0
"Unit";"SCV";"Command Center";162;1
"Unit";"SCV";"Command Center";162;1
"Unit";"SCV";"Command Center";162;1
"Unit";"Marine";"Barracks";161;1
"Unit";"Marine";"Barracks";161;1
"Unit";"Marine";"Barracks";161;1
"Unit";"Marine";"Barracks";162;1
"Unit";"Marine";"Barracks";162;1
"Unit";"Marine";"Barracks";162;1
"Unit";"Marine";"Barracks";162;1
"Unit";"Marine";"Barracks";162;1
"Unit";"Marine";"Barracks";166;1
"Building";"MissileTurret";NA;166;0
"Unit";"Marine";"Barracks";169;1
"Unit";"Marine";"Barracks";172;1
"Unit";"Marine";"Barracks";172;1
"Unit";"Marine";"Barracks";176;1
"Unit";"Medivac";"Starport";166;2
"Unit";"Medivac";"Starport";166;2
"Building";"Barracks";NA;159;0
"Building";"Barracks";NA;162;0
"Building";"Refinery";NA;177;0
"Unit";"Marine";"Barracks";180;1
