"type";"unit_name";"on_building";"total_supply";"supply"
"Building";"Refinery";NA;14;0
"Building";"Barracks";NA;15;0
"Unit";"Reaper";"Barracks";19;1
"Building";"Refinery";NA;20;0
"Building";"Factory";NA;19;0
"Building";"BarracksReactor";NA;20;0
"Building";"CommandCenter";NA;19;0
"Building";"BarracksTechLab";NA;24;0
"Unit";"Hellion";"Factory";24;2
"Unit";"Hellion";"Factory";24;2
"Building";"Starport";NA;23;0
"Unit";"Hellion";"Factory";29;2
"Unit";"Hellion";"Factory";29;2
"Unit";"Hellion";"Factory";35;2
"Unit";"Hellion";"Factory";35;2
"Unit";"Hellion";"Factory";41;2
"Unit";"Hellion";"Factory";41;2
"Unit";"Liberator";"Starport";43;3
"Building";"Refinery";NA;50;0
"Building";"Refinery";NA;50;0
"Unit";"Cyclone";"Factory";54;3
"Unit";"Cyclone";"Factory";57;3
"Building";"CommandCenter";NA;49;0
"Building";"BarracksTechLab";NA;64;0
"Unit";"Hellion";"Factory";69;2
"Unit";"Hellion";"Factory";69;2
"Building";"Armory";NA;64;0
"Building";"Armory";NA;67;0
"Building";"Refinery";NA;71;0
"Unit";"Hellion";"Factory";78;2
"Unit";"Hellion";"Factory";78;2
"Building";"Refinery";NA;78;0
"Building";"StarportReactor";NA;71;0
"Building";"Factory";NA;71;0
"Building";"Factory";NA;71;0
"Unit";"Hellion";"Factory";81;2
"Unit";"Hellion";"Factory";83;2
"Unit";"Thor";"Factory";87;6
"Unit";"Hellion";"Factory";96;2
"Unit";"Hellion";"Factory";96;2
"Unit";"Thor";"Factory";88;6
"Unit";"Medivac";"Starport";96;2
"Unit";"Medivac";"Starport";96;2
"Unit";"Hellion";"Factory";125;2
"Unit";"Hellion";"Factory";125;2
"Building";"Factory";NA;105;0
"Building";"Factory";NA;105;0
"Unit";"Medivac";"Starport";124;2
"Unit";"Medivac";"Starport";124;2
"Upgrade";"TerranVehicleWeaponsLevel1";"Armory";93;0
"Building";"EngineeringBay";NA;127;0
"Unit";"Hellion";"Factory";133;2
"Unit";"Hellion";"Factory";133;2
"Unit";"Hellion";"Factory";137;2
"Unit";"Hellion";"Factory";139;2
"Unit";"Hellion";"Factory";143;2
"Unit";"Hellion";"Factory";143;2
"Building";"FactoryTechLab";NA;147;0
"Unit";"Medivac";"Starport";144;2
"Unit";"Medivac";"Starport";144;2
"Unit";"Hellion";"Factory";147;2
"Unit";"Hellion";"Factory";149;2
"Building";"MissileTurret";NA;159;0
"Building";"SensorTower";NA;159;0
"Unit";"Medivac";"Starport";153;2
"Unit";"Medivac";"Starport";155;2
"Building";"FactoryTechLab";NA;161;0
"Unit";"Hellion";"Factory";161;2
"Unit";"Hellion";"Factory";161;2
"Unit";"Thor";"Factory";153;6
"Building";"CommandCenter";NA;147;0
"Unit";"Hellion";"Factory";163;2
"Unit";"Hellion";"Factory";163;2
"Unit";"Hellion";"Factory";171;2
"Unit";"Hellion";"Factory";171;2
"Building";"Refinery";NA;177;0
"Building";"MissileTurret";NA;177;0
"Building";"Refinery";NA;177;0
"Unit";"Hellion";"Factory";181;2
"Unit";"Thor";"Factory";171;6
"Unit";"Hellion";"Factory";185;2
"Unit";"Hellion";"Factory";185;2
"Unit";"Hellion";"Factory";185;2
"Unit";"Thor";"Factory";181;6
"Unit";"Hellion";"Factory";185;2
"Unit";"Hellion";"Factory";187;2
"Unit";"Hellion";"Factory";193;2
"Unit";"Hellion";"Factory";197;2
"Upgrade";"TerranVehicleWeaponsLevel2";"Armory";163;0
"Building";"SensorTower";NA;207;0
"Unit";"Hellion";"Factory";207;2
"Unit";"Hellion";"Factory";207;2
"Unit";"Hellion";"Factory";207;2
"Unit";"Hellion";"Factory";209;2
"Unit";"Hellion";"Factory";217;2
"Unit";"Hellion";"Factory";219;2
"Unit";"Hellion";"Factory";219;2
"Unit";"Hellion";"Factory";221;2
"Building";"Factory";NA;213;0
"Unit";"Hellion";"Factory";221;2
"Unit";"Hellion";"Factory";221;2
"Unit";"Hellion";"Factory";221;2
"Unit";"Hellion";"Factory";223;2
"Unit";"Hellion";"Factory";227;2
"Building";"Refinery";NA;232;0
"Unit";"Hellion";"Factory";232;2
"Unit";"Hellion";"Factory";234;2
"Unit";"Hellion";"Factory";236;2
"Building";"FactoryTechLab";NA;240;0
"Unit";"Hellion";"Factory";238;2
"Unit";"Hellion";"Factory";242;2
"Building";"Starport";NA;238;0
"Unit";"Hellion";"Factory";242;2
"Unit";"Hellion";"Factory";244;2
"Unit";"Hellion";"Factory";246;2
"Building";"Starport";NA;240;0
"Unit";"Hellion";"Factory";248;2
"Unit";"Hellion";"Factory";248;2
"Unit";"Hellion";"Factory";249;2
"Building";"Starport";NA;246;0
"Building";"Starport";NA;248;0
"Building";"Starport";NA;248;0
"Building";"Starport";NA;248;0
"Unit";"Hellion";"Factory";260;2
"Unit";"Hellion";"Factory";264;2
"Unit";"Hellion";"Factory";264;2
"Unit";"Hellion";"Factory";264;2
"Unit";"Hellion";"Factory";268;2
"Unit";"Hellion";"Factory";274;2
"Unit";"Hellion";"Factory";274;2
"Unit";"Hellion";"Factory";274;2
"Unit";"Thor";"Factory";268;6
"Unit";"Thor";"Factory";272;6
"Unit";"Hellion";"Factory";280;2
"Unit";"Hellion";"Factory";280;2
"Unit";"Thor";"Factory";274;6
"Unit";"Hellion";"Factory";294;2
"Unit";"Hellion";"Factory";294;2
"Unit";"Medivac";"Starport";288;2
"Unit";"Medivac";"Starport";288;2
"Unit";"Thor";"Factory";280;6
"Unit";"Hellion";"Factory";298;2
"Unit";"Hellion";"Factory";304;2
"Building";"MissileTurret";NA;308;0
"Building";"StarportTechLab";NA;318;0
"Unit";"Hellion";"Factory";318;2
"Unit";"Thor";"Factory";304;6
"Unit";"Hellion";"Factory";322;2
"Unit";"Hellion";"Factory";322;2
"Unit";"Hellion";"Factory";322;2
"Unit";"Hellion";"Factory";322;2
"Building";"CommandCenter";NA;282;0
"Unit";"Hellion";"Factory";322;2
"Building";"Armory";NA;312;0
"Building";"CommandCenter";NA;308;0
"Unit";"Hellion";"Factory";340;2
"Unit";"Hellion";"Factory";340;2
"Unit";"Hellion";"Factory";340;2
"Unit";"Hellion";"Factory";340;2
"Unit";"Hellion";"Factory";340;2
"Unit";"Hellion";"Factory";340;2
"Building";"Refinery";NA;344;0
"Building";"Refinery";NA;344;0
"Building";"SensorTower";NA;348;0
"Unit";"Hellion";"Factory";352;2
"Unit";"Thor";"Factory";348;6
"Unit";"Thor";"Factory";352;6
"Unit";"Hellion";"Factory";355;2
"Unit";"Hellion";"Factory";355;2
"Unit";"Hellion";"Factory";355;2
"Unit";"Hellion";"Factory";367;2
"Unit";"Hellion";"Factory";381;2
"Unit";"Hellion";"Factory";386;2
"Unit";"Hellion";"Factory";388;2
"Unit";"Hellion";"Factory";388;2
"Unit";"Thor";"Factory";386;6
