"type";"unit_name";"on_building";"total_supply";"supply"
"Building";"Refinery";NA;14;0
"Building";"Barracks";NA;15;0
"Unit";"Reaper";"Barracks";18;1
"Building";"Bunker";NA;19;0
"Unit";"Marine";"Barracks";19;1
"Unit";"Marine";"Barracks";21;1
"Building";"Factory";NA;19;0
"Unit";"Marine";"Barracks";22;1
"Building";"BarracksReactor";NA;26;0
"Unit";"Hellion";"Factory";27;2
"Building";"Refinery";NA;27;0
"Building";"CommandCenter";NA;26;0
"Building";"Starport";NA;31;0
"Building";"Armory";NA;31;0
"Unit";"Marine";"Barracks";31;1
"Unit";"Hellion";"Factory";31;2
"Unit";"Hellion";"Factory";31;2
"Unit";"Medivac";"Starport";31;2
"Unit";"Hellion";"Factory";33;2
"Unit";"Hellion";"Factory";33;2
"Unit";"Hellion";"Factory";39;2
"Unit";"Hellion";"Factory";39;2
"Unit";"Medivac";"Starport";37;2
"Unit";"Marine";"Barracks";48;1
"Unit";"Hellion";"Factory";44;2
"Unit";"Hellion";"Factory";44;2
"Unit";"Hellion";"Factory";53;2
"Unit";"Marine";"Barracks";61;1
"Unit";"Marine";"Barracks";61;1
"Building";"FactoryTechLab";NA;63;0
"Upgrade";"TerranVehicleWeaponsLevel1";"Armory";48;0
"Building";"Factory";NA;61;0
"Building";"Factory";NA;61;0
"Unit";"Liberator";"Starport";64;3
"Unit";"Liberator";"Starport";64;3
"Unit";"Marine";"Barracks";70;1
"Building";"CommandCenter";NA;61;0
"Unit";"Cyclone";"Factory";71;3
"Building";"FactoryTechLab";NA;85;0
"Building";"FactoryTechLab";NA;85;0
"Building";"Refinery";NA;85;0
"Building";"Refinery";NA;86;0
"Building";"CommandCenter";NA;81;0
"Building";"Refinery";NA;97;0
"Building";"EngineeringBay";NA;97;0
"Building";"Refinery";NA;98;0
"Upgrade";"TerranVehicleWeaponsLevel2";"Armory";95;0
"Unit";"Hellion";"Factory";104;2
"Unit";"Hellion";"Factory";104;2
"Unit";"Cyclone";"Factory";106;3
"Unit";"Hellion";"Factory";111;2
"Unit";"Hellion";"Factory";114;2
"Building";"Factory";NA;111;0
"Building";"Refinery";NA;120;0
"Building";"Factory";NA;113;0
"Unit";"Hellion";"Factory";130;2
"Unit";"Hellion";"Factory";130;2
"Building";"SensorTower";NA;132;0
"Building";"FactoryTechLab";NA;140;0
"Unit";"Hellion";"Factory";142;2
"Unit";"Hellion";"Factory";142;2
"Building";"FactoryReactor";NA;138;0
"Building";"CommandCenter";NA;126;0
"Building";"CommandCenter";NA;126;0
"Unit";"Hellion";"Factory";142;2
"Unit";"Hellion";"Factory";145;2
"Unit";"Hellion";"Factory";146;2
"Unit";"Hellion";"Factory";148;2
"Unit";"Medivac";"Starport";146;2
"Unit";"Medivac";"Starport";146;2
"Building";"MissileTurret";NA;150;0
"Building";"MissileTurret";NA;152;0
"Unit";"Hellion";"Factory";152;2
"Unit";"Hellion";"Factory";152;2
"Unit";"Hellion";"Factory";158;2
"Unit";"Hellion";"Factory";158;2
"Unit";"Hellion";"Factory";158;2
"Unit";"Hellion";"Factory";158;2
"Building";"Armory";NA;148;0
"Building";"CommandCenter";NA;142;0
"Unit";"Hellion";"Factory";170;2
"Unit";"Medivac";"Starport";176;2
"Unit";"Medivac";"Starport";176;2
"Unit";"Cyclone";"Factory";176;3
"Unit";"Cyclone";"Factory";176;3
"Unit";"Hellion";"Factory";176;2
"Upgrade";"TerranVehicleWeaponsLevel3";"Armory";138;0
"Building";"CommandCenter";NA;152;0
"Unit";"Hellion";"Factory";178;2
"Unit";"Hellion";"Factory";180;2
"Unit";"Hellion";"Factory";185;2
"Unit";"Hellion";"Factory";188;2
"Unit";"Medivac";"Starport";190;2
"Unit";"Medivac";"Starport";190;2
"Unit";"Hellion";"Factory";202;2
"Unit";"Hellion";"Factory";202;2
"Unit";"Hellion";"Factory";202;2
"Unit";"Hellion";"Factory";202;2
"Building";"Factory";NA;202;0
"Building";"Factory";NA;202;0
"Unit";"Hellion";"Factory";206;2
"Unit";"Hellion";"Factory";208;2
