"type";"unit_name";"on_building";"total_supply";"supply"
"Building";"Refinery";NA;15;0
"Building";"Barracks";NA;15;0
"Unit";"Reaper";"Barracks";19;1
"Building";"Refinery";NA;21;0
"Building";"Barracks";NA;19;0
"Building";"BarracksReactor";NA;20;0
"Building";"CommandCenter";NA;19;0
"Unit";"Marine";"Barracks";23;1
"Unit";"Marine";"Barracks";23;1
"Building";"Factory";NA;22;0
"Building";"BarracksTechLab";NA;23;0
"Unit";"Marine";"Barracks";24;1
"Unit";"Marine";"Barracks";25;1
"Unit";"Marine";"Barracks";27;1
"Unit";"Marine";"Barracks";29;1
"Building";"Starport";NA;26;0
"Building";"FactoryReactor";NA;27;0
"Unit";"Marine";"Barracks";32;1
"Unit";"Marine";"Barracks";33;1
"Unit";"Marine";"Barracks";33;1
"Unit";"Marine";"Barracks";38;1
"Unit";"Marine";"Barracks";40;1
"Unit";"Marine";"Barracks";40;1
"Unit";"Medivac";"Starport";38;2
"Unit";"Medivac";"Starport";38;2
"Unit";"Marine";"Barracks";42;1
"Building";"EngineeringBay";NA;41;0
"Unit";"Marine";"Barracks";44;1
"Building";"EngineeringBay";NA;43;0
"Unit";"Marine";"Barracks";51;1
"Unit";"Marine";"Barracks";51;1
"Upgrade";"Stimpack";"TechLab";33;0
"Unit";"Marine";"Barracks";58;1
"Unit";"Marine";"Barracks";58;1
"Unit";"Marine";"Barracks";64;1
"Unit";"Medivac";"Starport";60;2
"Unit";"Marine";"Barracks";66;1
"Unit";"Marine";"Barracks";66;1
"Unit";"Marine";"Barracks";67;1
"Unit";"Marine";"Barracks";71;1
"Building";"Refinery";NA;73;0
"Building";"Refinery";NA;73;0
"Building";"CommandCenter";NA;60;0
"Building";"StarportReactor";NA;70;0
"Building";"FactoryReactor";NA;70;0
"Upgrade";"TerranInfantryArmorsLevel1";"EngineeringBay";64;0
"Upgrade";"TerranInfantryWeaponsLevel1";"EngineeringBay";64;0
"Building";"Armory";NA;71;0
"Building";"Barracks";NA;71;0
"Building";"Barracks";NA;72;0
"Building";"Barracks";NA;73;0
"Building";"FactoryTechLab";NA;83;0
"Unit";"Marine";"Barracks";84;1
"Unit";"Marine";"Barracks";84;1
"Unit";"Marine";"Barracks";84;1
"Unit";"Marine";"Barracks";84;1
"Unit";"Marauder";"Barracks";84;2
"Building";"StarportReactor";NA;83;0
"Unit";"Marine";"Barracks";86;1
"Unit";"Marine";"Barracks";86;1
"Unit";"Marine";"Barracks";86;1
"Unit";"Marine";"Barracks";86;1
"Unit";"Marine";"Barracks";86;1
"Unit";"Marine";"Barracks";87;1
"Unit";"Marine";"Barracks";87;1
"Unit";"Marine";"Barracks";89;1
"Unit";"Marauder";"Barracks";90;2
"Building";"Refinery";NA;103;0
"Unit";"Marine";"Barracks";103;1
"Unit";"Marine";"Barracks";103;1
"Unit";"Marine";"Barracks";105;1
"Unit";"Marine";"Barracks";105;1
"Building";"Barracks";NA;93;0
"Unit";"Marine";"Barracks";107;1
"Unit";"Marine";"Barracks";107;1
"Unit";"Marine";"Barracks";107;1
"Unit";"Marine";"Barracks";107;1
"Unit";"Marine";"Barracks";107;1
"Building";"Barracks";NA;94;0
"Building";"Barracks";NA;94;0
"Unit";"Marine";"Barracks";111;1
"Unit";"Marine";"Barracks";111;1
"Unit";"Marine";"Barracks";113;1
"Unit";"Marine";"Barracks";113;1
"Unit";"Marine";"Barracks";113;1
"Unit";"Marauder";"Barracks";117;2
"Unit";"Medivac";"Starport";111;2
"Unit";"Marine";"Barracks";122;1
"Unit";"Marine";"Barracks";123;1
"Unit";"Marine";"Barracks";123;1
"Unit";"Marine";"Barracks";126;1
"Unit";"Marine";"Barracks";130;1
"Unit";"Marine";"Barracks";130;1
"Unit";"Marauder";"Barracks";126;2
"Unit";"Marine";"Barracks";131;1
"Upgrade";"TerranVehicleWeaponsLevel1";"Armory";105;0
"Building";"BarracksTechLab";NA;136;0
"Building";"BarracksTechLab";NA;138;0
"Unit";"Marine";"Barracks";138;1
"Unit";"Marauder";"Barracks";136;2
"Unit";"Medivac";"Starport";138;2
"Unit";"Medivac";"Starport";138;2
"Upgrade";"TerranInfantryWeaponsLevel2";"EngineeringBay";107;0
"Unit";"Marine";"Barracks";140;1
"Unit";"Marine";"Barracks";140;1
"Unit";"Marine";"Barracks";140;1
"Unit";"Marine";"Barracks";140;1
"Unit";"Marine";"Barracks";142;1
"Unit";"Marine";"Barracks";142;1
"Unit";"Marine";"Barracks";142;1
"Unit";"Marine";"Barracks";142;1
"Unit";"Marine";"Barracks";142;1
"Unit";"Marauder";"Barracks";140;2
"Unit";"Marauder";"Barracks";140;2
"Unit";"Marauder";"Barracks";142;2
"Upgrade";"TerranInfantryArmorsLevel2";"EngineeringBay";113;0
"Unit";"Marine";"Barracks";161;1
"Unit";"Marine";"Barracks";161;1
"Unit";"Marine";"Barracks";161;1
"Unit";"Marine";"Barracks";161;1
"Unit";"Marine";"Barracks";161;1
"Unit";"Marine";"Barracks";161;1
"Unit";"Marine";"Barracks";161;1
"Unit";"Marine";"Barracks";161;1
"Unit";"Marine";"Barracks";161;1
"Unit";"Marauder";"Barracks";161;2
"Unit";"Marauder";"Barracks";161;2
"Unit";"Marauder";"Barracks";161;2
"Unit";"Liberator";"Starport";146;3
"Unit";"Liberator";"Starport";146;3
"Unit";"Marine";"Barracks";161;1
"Unit";"Marine";"Barracks";161;1
"Unit";"Marine";"Barracks";161;1
"Unit";"Marine";"Barracks";161;1
"Unit";"Marine";"Barracks";161;1
"Unit";"Marine";"Barracks";161;1
"Unit";"Marine";"Barracks";167;1
"Unit";"Marine";"Barracks";167;1
"Unit";"Marine";"Barracks";167;1
