"type";"unit_name";"on_building";"total_supply";"supply"
"Building";"Refinery";NA;14;0
"Building";"Refinery";NA;16;0
"Building";"Barracks";NA;15;0
"Building";"Bunker";NA;18;0
"Building";"BarracksReactor";NA;18;0
"Building";"Factory";NA;19;0
"Unit";"Hellion";"Factory";19;2
"Unit";"Hellion";"Factory";19;2
"Building";"Factory";NA;19;0
"Building";"BarracksReactor";NA;20;0
"Unit";"Cyclone";"Factory";26;3
"Building";"Armory";NA;25;0
"Unit";"Cyclone";"Factory";30;3
"Unit";"Cyclone";"Factory";30;3
"Unit";"Cyclone";"Factory";30;3
"Unit";"Hellion";"Factory";40;2
"Unit";"Hellion";"Factory";40;2
"Unit";"Hellion";"Factory";40;2
"Unit";"Cyclone";"Factory";48;3
"Unit";"Hellion";"Factory";48;2
"Unit";"Cyclone";"Factory";48;3
"Unit";"Cyclone";"Factory";56;3
"Unit";"Cyclone";"Factory";56;3
"Upgrade";"TerranVehicleWeaponsLevel1";"Armory";40;0
