"type";"unit_name";"on_building";"total_supply";"supply"
"Building";"Refinery";NA;14;0
"Building";"Barracks";NA;15;0
"Unit";"Reaper";"Barracks";19;1
"Building";"Factory";NA;19;0
"Building";"Refinery";NA;21;0
"Building";"BarracksReactor";NA;20;0
"Building";"CommandCenter";NA;19;0
"Building";"BarracksTechLab";NA;23;0
"Unit";"Hellion";"Factory";23;2
"Unit";"Hellion";"Factory";23;2
"Building";"Starport";NA;23;0
"Unit";"Hellion";"Factory";29;2
"Unit";"Hellion";"Factory";29;2
"Unit";"Hellion";"Factory";35;2
"Unit";"Hellion";"Factory";36;2
"Building";"BarracksReactor";NA;30;0
"Building";"BarracksTechLab";NA;46;0
"Building";"FactoryTechLab";NA;46;0
"Unit";"Liberator";"Starport";39;3
"Unit";"Marine";"Barracks";49;1
"Building";"Refinery";NA;53;0
"Building";"Refinery";NA;53;0
"Building";"EngineeringBay";NA;53;0
"Building";"EngineeringBay";NA;54;0
"Building";"CommandCenter";NA;46;0
"Unit";"Marine";"Barracks";57;1
"Building";"Barracks";NA;55;0
"Building";"StarportReactor";NA;57;0
"Building";"Barracks";NA;56;0
"Unit";"Marine";"Barracks";61;1
"Unit";"Marine";"Barracks";64;1
"Unit";"Marine";"Barracks";64;1
"Unit";"Marine";"Barracks";64;1
"Unit";"Marine";"Barracks";64;1
"Unit";"Marine";"Barracks";64;1
"Building";"Barracks";NA;62;0
"Unit";"Marine";"Barracks";68;1
"Unit";"Marine";"Barracks";69;1
"Unit";"Marine";"Barracks";74;1
"Unit";"Marine";"Barracks";74;1
"Unit";"Marine";"Barracks";75;1
"Unit";"Medivac";"Starport";68;2
"Unit";"Medivac";"Starport";68;2
"Upgrade";"Stimpack";"TechLab";57;0
"Unit";"Marine";"Barracks";75;1
"Unit";"Marine";"Barracks";76;1
"Building";"BarracksReactor";NA;75;0
"Unit";"Marine";"Barracks";88;1
"Unit";"Marine";"Barracks";88;1
"Unit";"Marine";"Barracks";88;1
"Unit";"Marine";"Barracks";88;1
"Building";"Barracks";NA;77;0
"Upgrade";"TerranInfantryWeaponsLevel1";"EngineeringBay";67;0
"Upgrade";"TerranInfantryArmorsLevel1";"EngineeringBay";67;0
"Unit";"Marine";"Barracks";91;1
"Unit";"Marine";"Barracks";91;1
"Unit";"Marine";"Barracks";91;1
"Unit";"Marine";"Barracks";92;1
"Unit";"Marine";"Barracks";93;1
"Unit";"Medivac";"Starport";95;2
"Unit";"Marine";"Barracks";102;1
"Unit";"Marine";"Barracks";103;1
"Unit";"Medivac";"Starport";95;2
"Unit";"Marine";"Barracks";103;1
"Building";"Armory";NA;88;0
"Unit";"Marine";"Barracks";105;1
"Unit";"Marine";"Barracks";105;1
"Unit";"Marine";"Barracks";105;1
"Unit";"Marine";"Barracks";105;1
"Unit";"Marine";"Barracks";108;1
"Building";"BarracksReactor";NA;103;0
"Building";"Bunker";NA;105;0
"Building";"Factory";NA;115;0
"Unit";"Marine";"Barracks";120;1
"Unit";"Marine";"Barracks";120;1
"Unit";"Marine";"Barracks";120;1
"Unit";"Marine";"Barracks";120;1
"Unit";"Marine";"Barracks";120;1
"Unit";"Marine";"Barracks";120;1
"Unit";"Marine";"Barracks";120;1
"Unit";"Marine";"Barracks";120;1
"Unit";"Marine";"Barracks";120;1
"Unit";"Marine";"Barracks";123;1
"Unit";"Marine";"Barracks";123;1
"Unit";"Marine";"Barracks";123;1
"Unit";"Marine";"Barracks";127;1
"Unit";"Marine";"Barracks";127;1
"Unit";"Marine";"Barracks";127;1
"Unit";"Marine";"Barracks";127;1
"Unit";"Marine";"Barracks";132;1
"Unit";"Marine";"Barracks";132;1
"Unit";"Marine";"Barracks";142;1
"Unit";"Marine";"Barracks";142;1
"Unit";"Marine";"Barracks";142;1
"Unit";"Marine";"Barracks";142;1
"Unit";"Marine";"Barracks";142;1
"Unit";"Marine";"Barracks";154;1
"Unit";"Marine";"Barracks";154;1
"Unit";"Marine";"Barracks";154;1
"Unit";"Marine";"Barracks";154;1
"Unit";"Marine";"Barracks";154;1
"Unit";"Marine";"Barracks";154;1
"Unit";"Marine";"Barracks";154;1
"Unit";"Marine";"Barracks";154;1
"Unit";"Marine";"Barracks";154;1
"Unit";"Medivac";"Starport";154;2
"Unit";"Marine";"Barracks";154;1
"Unit";"Marine";"Barracks";155;1
"Upgrade";"TerranVehicleWeaponsLevel1";"Armory";132;0
"Unit";"Marine";"Barracks";165;1
"Unit";"Marine";"Barracks";165;1
"Unit";"Marine";"Barracks";165;1
"Building";"Refinery";NA;169;0
"Building";"Refinery";NA;169;0
"Unit";"Marine";"Barracks";172;1
"Unit";"Marine";"Barracks";172;1
"Unit";"Marine";"Barracks";172;1
"Unit";"Marine";"Barracks";172;1
"Unit";"Marine";"Barracks";172;1
"Unit";"Marine";"Barracks";172;1
"Unit";"Marine";"Barracks";172;1
"Unit";"Marine";"Barracks";172;1
"Unit";"Marine";"Barracks";172;1
"Unit";"Marine";"Barracks";181;1
"Unit";"Marine";"Barracks";181;1
"Unit";"Marine";"Barracks";181;1
"Unit";"Marine";"Barracks";181;1
"Unit";"Marine";"Barracks";181;1
"Unit";"Marine";"Barracks";181;1
"Unit";"Marine";"Barracks";181;1
"Unit";"Marine";"Barracks";181;1
"Unit";"Marine";"Barracks";181;1
"Unit";"Medivac";"Starport";181;2
"Unit";"Marine";"Barracks";183;1
"Unit";"Marine";"Barracks";184;1
"Unit";"Marine";"Barracks";185;1
"Unit";"Marine";"Barracks";186;1
"Unit";"Marine";"Barracks";187;1
"Unit";"Marine";"Barracks";188;1
"Upgrade";"TerranInfantryWeaponsLevel2";"EngineeringBay";165;0
"Upgrade";"TerranInfantryArmorsLevel2";"EngineeringBay";165;0
"Unit";"Medivac";"Starport";190;2
"Unit";"Marine";"Barracks";200;1
"Unit";"Marine";"Barracks";200;1
"Unit";"Marine";"Barracks";200;1
"Unit";"Marine";"Barracks";200;1
"Unit";"Marine";"Barracks";200;1
"Unit";"Marine";"Barracks";200;1
"Unit";"Medivac";"Starport";200;2
"Unit";"Marauder";"Barracks";202;2
"Unit";"Marine";"Barracks";208;1
"Unit";"Marine";"Barracks";208;1
"Unit";"Marine";"Barracks";210;1
"Unit";"Marine";"Barracks";210;1
"Unit";"Marine";"Barracks";210;1
"Unit";"Medivac";"Starport";202;2
"Unit";"Marine";"Barracks";210;1
"Unit";"Marine";"Barracks";210;1
"Unit";"Marine";"Barracks";210;1
"Upgrade";"TerranVehicleWeaponsLevel2";"Armory";181;0
"Building";"CommandCenter";NA;192;0
"Unit";"Marine";"Barracks";212;1
"Unit";"Marine";"Barracks";213;1
"Unit";"Marauder";"Barracks";210;2
"Unit";"Medivac";"Starport";210;2
"Unit";"Marine";"Barracks";214;1
"Unit";"Marine";"Barracks";215;1
"Unit";"Marine";"Barracks";216;1
"Unit";"Marine";"Barracks";219;1
"Unit";"Marine";"Barracks";220;1
"Unit";"Marine";"Barracks";221;1
"Unit";"Marine";"Barracks";222;1
"Unit";"Marine";"Barracks";223;1
"Unit";"Medivac";"Starport";217;2
"Unit";"Marauder";"Barracks";224;2
"Unit";"Marine";"Barracks";228;1
"Unit";"Marine";"Barracks";229;1
"Unit";"Marine";"Barracks";230;1
"Unit";"Marine";"Barracks";231;1
"Unit";"Marine";"Barracks";232;1
"Unit";"Marine";"Barracks";244;1
"Unit";"Marine";"Barracks";245;1
"Unit";"Marine";"Barracks";245;1
"Unit";"Marine";"Barracks";245;1
"Unit";"Marine";"Barracks";245;1
"Unit";"Marine";"Barracks";245;1
"Unit";"Marine";"Barracks";245;1
"Unit";"Marauder";"Barracks";245;2
"Unit";"Marine";"Barracks";245;1
"Unit";"Medivac";"Starport";245;2
"Unit";"Medivac";"Starport";245;2
"Unit";"Marine";"Barracks";245;1
"Unit";"Marine";"Barracks";246;1
"Unit";"Marine";"Barracks";247;1
"Unit";"Marine";"Barracks";248;1
"Unit";"Marine";"Barracks";252;1
"Unit";"Marine";"Barracks";252;1
"Unit";"Marine";"Barracks";252;1
"Unit";"Marauder";"Barracks";252;2
"Unit";"Marine";"Barracks";266;1
"Unit";"Marine";"Barracks";266;1
"Unit";"Marine";"Barracks";266;1
"Unit";"Marine";"Barracks";266;1
"Unit";"Marine";"Barracks";266;1
"Unit";"Marine";"Barracks";266;1
"Building";"Barracks";NA;245;0
"Building";"Barracks";NA;245;0
"Building";"Barracks";NA;245;0
"Unit";"Marine";"Barracks";268;1
"Unit";"Marine";"Barracks";268;1
"Unit";"Marine";"Barracks";268;1
"Unit";"Marine";"Barracks";268;1
"Unit";"Marine";"Barracks";269;1
"Unit";"Marine";"Barracks";270;1
"Unit";"Marine";"Barracks";271;1
"Unit";"Marine";"Barracks";274;1
"Building";"BarracksTechLab";NA;277;0
"Building";"BarracksTechLab";NA;277;0
