"Type";"UnitName";"OnBuilding";"TotalSupply";"Supply"
"Unit";"SCV";"Command Center";12;1
"Unit";"SCV";"Command Center";12;1
"Unit";"SCV";"Command Center";13;1
"Building";"SupplyDepot";NA;13;0
"Building";"Refinery";NA;14;0
"Unit";"SCV";"Command Center";15;1
"Unit";"SCV";"Command Center";15;1
"Unit";"SCV";"Command Center";16;1
"Unit";"SCV";"Command Center";17;1
"Building";"Barracks";NA;15;0
"Unit";"Reaper";"Barracks";19;1
"Unit";"SCV";"Command Center";19;1
"Unit";"SCV";"Command Center";21;1
"Unit";"SCV";"Command Center";21;1
"Building";"BarracksReactor";NA;20;0
"Building";"SupplyDepot";NA;22;0
"Building";"Barracks";NA;20;0
"Unit";"SCV";"Command Center";23;1
"Unit";"Marine";"Barracks";23;1
"Unit";"Marine";"Barracks";23;1
"Building";"CommandCenter";NA;19;0
"Building";"BarracksTechLab";NA;23;0
"Unit";"SCV";"Command Center";24;1
"Building";"Refinery";NA;24;0
"Unit";"Marine";"Barracks";26;1
"Unit";"Marine";"Barracks";26;1
"Unit";"SCV";"Command Center";27;1
"Building";"Factory";NA;23;0
"Unit";"Marine";"Barracks";27;1
"Unit";"SCV";"Command Center";30;1
"Unit";"Marine";"Barracks";27;1
"Unit";"Marine";"Barracks";30;1
"Unit";"SCV";"Command Center";31;1
"Unit";"SCV";"Command Center";32;1
"Unit";"Marine";"Barracks";33;1
"Unit";"SCV";"Command Center";34;1
"Building";"Bunker";NA;30;0
"Unit";"SCV";"Command Center";36;1
"Unit";"Marine";"Barracks";34;1
"Building";"Starport";NA;30;0
"Unit";"SCV";"Command Center";37;1
"Unit";"SCV";"Command Center";38;1
"Building";"FactoryReactor";NA;34;0
"Unit";"SCV";"Command Center";40;1
"Unit";"Marine";"Barracks";40;1
"Unit";"Marine";"Barracks";40;1
"Building";"SupplyDepot";NA;40;0
"Unit";"Marine";"Barracks";40;1
"Unit";"SCV";"Command Center";41;1
"Building";"SupplyDepot";NA;42;0
"Unit";"SCV";"Command Center";45;1
"Unit";"SCV";"Command Center";46;1
"Unit";"Marine";"Barracks";45;1
"Unit";"Marine";"Barracks";45;1
"Building";"SupplyDepot";NA;45;0
"Unit";"SCV";"Command Center";47;1
"Unit";"Marine";"Barracks";47;1
"Unit";"SCV";"Command Center";52;1
"Unit";"SCV";"Command Center";53;1
"Unit";"Marine";"Barracks";51;1
"Unit";"Marine";"Barracks";51;1
"Unit";"Medivac";"Starport";47;2
"Building";"SupplyDepot";NA;51;0
"Unit";"Medivac";"Starport";47;2
"Unit";"Marine";"Barracks";52;1
"Unit";"SCV";"Command Center";53;1
"Unit";"SCV";"Command Center";54;1
"Upgrade";"Stimpack";"TechLab";36;0
"Unit";"Marine";"Barracks";55;1
"Unit";"Marine";"Barracks";56;1
"Unit";"SCV";"Command Center";62;1
"Unit";"SCV";"Command Center";66;1
"Unit";"Marine";"Barracks";64;1
"Unit";"SCV";"Command Center";66;1
"Unit";"Marine";"Barracks";64;1
"Unit";"Marine";"Barracks";67;1
"Building";"FactoryTechLab";NA;67;0
"Building";"EngineeringBay";NA;66;0
"Building";"EngineeringBay";NA;66;0
"Unit";"Marine";"Barracks";68;1
"Unit";"SCV";"Command Center";71;1
"Unit";"SCV";"Command Center";71;1
"Unit";"Marine";"Barracks";71;1
"Unit";"Marine";"Barracks";75;1
"Unit";"Marine";"Barracks";75;1
"Unit";"Marine";"Barracks";76;1
"Building";"CommandCenter";NA;62;0
"Building";"Barracks";NA;69;0
"Unit";"Medivac";"Starport";72;2
"Unit";"Medivac";"Starport";72;2
"Building";"Barracks";NA;69;0
"Building";"Barracks";NA;71;0
"Building";"Refinery";NA;76;0
"Building";"Refinery";NA;76;0
"Building";"SupplyDepot";NA;76;0
"Unit";"SCV";"Command Center";79;1
"Unit";"SCV";"Command Center";79;1
"Unit";"Marine";"Barracks";79;1
"Building";"SupplyDepot";NA;79;0
"Building";"SupplyDepot";NA;79;0
"Unit";"Marine";"Barracks";83;1
"Unit";"Marine";"Barracks";83;1
"Unit";"Marine";"Barracks";85;1
"Unit";"Marine";"Barracks";85;1
"Unit";"SCV";"Command Center";86;1
"Unit";"Marine";"Barracks";85;1
"Unit";"Marine";"Barracks";86;1
"Unit";"Marine";"Barracks";86;1
"Unit";"Marine";"Barracks";87;1
"Unit";"SCV";"Command Center";92;1
"Unit";"Marine";"Barracks";88;1
"Unit";"Marine";"Barracks";89;1
"Unit";"Marine";"Barracks";91;1
"Unit";"SCV";"Command Center";95;1
"Unit";"SCV";"Command Center";95;1
"Unit";"Marine";"Barracks";92;1
"Unit";"Marine";"Barracks";93;1
"Unit";"Marine";"Barracks";94;1
"Unit";"Marine";"Barracks";98;1
"Unit";"Marine";"Barracks";101;1
"Unit";"SCV";"Command Center";104;1
"Unit";"SCV";"Command Center";105;1
"Unit";"SCV";"Command Center";105;1
"Unit";"Marine";"Barracks";104;1
"Building";"BarracksTechLab";NA;104;0
"Building";"BarracksTechLab";NA;104;0
"Building";"BarracksTechLab";NA;104;0
"Building";"Bunker";NA;102;0
"Unit";"SCV";"Command Center";106;1
"Unit";"SCV";"Command Center";107;1
"Unit";"SCV";"Command Center";108;1
"Unit";"Marine";"Barracks";110;1
"Unit";"Marine";"Barracks";110;1
"Upgrade";"TerranInfantryWeaponsLevel1";"EngineeringBay";86;0
"Unit";"Medivac";"Starport";105;2
"Unit";"Medivac";"Starport";105;2
"Upgrade";"TerranInfantryArmorsLevel1";"EngineeringBay";88;0
"Unit";"Marauder";"Barracks";111;2
"Unit";"Marauder";"Barracks";111;2
"Unit";"Marauder";"Barracks";112;2
"Unit";"Marauder";"Barracks";113;2
"Unit";"SCV";"Command Center";117;1
"Unit";"Marine";"Barracks";115;1
"Unit";"Marine";"Barracks";115;1
"Building";"SupplyDepot";NA;115;0
"Building";"SupplyDepot";NA;115;0
"Building";"SupplyDepot";NA;115;0
"Unit";"Marine";"Barracks";119;1
"Unit";"SCV";"Command Center";128;1
"Unit";"Marine";"Barracks";128;1
"Unit";"Marine";"Barracks";130;1
"Unit";"Marine";"Barracks";130;1
"Unit";"Marine";"Barracks";130;1
"Unit";"Marine";"Barracks";130;1
"Unit";"SCV";"Command Center";133;1
"Building";"Armory";NA;119;0
"Unit";"Marine";"Barracks";133;1
"Unit";"SCV";"Command Center";138;1
"Unit";"Marine";"Barracks";134;1
"Unit";"Marine";"Barracks";134;1
"Unit";"Marine";"Barracks";134;1
"Unit";"Marine";"Barracks";135;1
"Unit";"Marine";"Barracks";136;1
"Unit";"SCV";"Command Center";139;1
"Unit";"SCV";"Command Center";139;1
"Unit";"Marine";"Barracks";139;1
"Unit";"SCV";"Command Center";145;1
"Unit";"Marine";"Barracks";140;1
"Unit";"Marine";"Barracks";141;1
"Unit";"Marine";"Barracks";142;1
"Unit";"Marine";"Barracks";143;1
"Unit";"Marine";"Barracks";144;1
"Unit";"SCV";"Command Center";147;1
"Unit";"SCV";"Command Center";147;1
"Unit";"SCV";"Command Center";148;1
"Unit";"Marine";"Barracks";147;1
"Unit";"SCV";"Command Center";154;1
"Unit";"Marine";"Barracks";149;1
"Unit";"Marine";"Barracks";150;1
"Unit";"Marine";"Barracks";151;1
"Unit";"SCV";"Command Center";158;1
"Unit";"SCV";"Command Center";159;1
"Unit";"SCV";"Command Center";159;1
"Unit";"Marine";"Barracks";162;1
"Unit";"Marine";"Barracks";162;1
"Unit";"Marine";"Barracks";162;1
"Unit";"Marine";"Barracks";162;1
"Unit";"SCV";"Command Center";163;1
"Building";"SupplyDepot";NA;162;0
"Unit";"SCV";"Command Center";163;1
"Unit";"SCV";"Command Center";164;1
"Building";"SupplyDepot";NA;162;0
"Building";"SupplyDepot";NA;162;0
"Building";"SupplyDepot";NA;162;0
"Building";"SupplyDepot";NA;162;0
"Building";"SupplyDepot";NA;162;0
"Building";"SupplyDepot";NA;163;0
"Unit";"SCV";"Command Center";169;1
"Unit";"SCV";"Command Center";170;1
"Unit";"Marauder";"Barracks";165;2
"Unit";"Marauder";"Barracks";165;2
"Unit";"SCV";"Command Center";172;1
"Unit";"Marine";"Barracks";172;1
"Unit";"Marine";"Barracks";172;1
"Unit";"Marine";"Barracks";172;1
"Unit";"Marauder";"Barracks";167;2
"Unit";"SCV";"Command Center";172;1
"Unit";"SCV";"Command Center";173;1
"Unit";"Marine";"Barracks";174;1
"Unit";"Marine";"Barracks";176;1
"Unit";"Marine";"Barracks";179;1
"Unit";"Marine";"Barracks";180;1
"Building";"Bunker";NA;172;0
"Unit";"Marine";"Barracks";181;1
"Unit";"Marine";"Barracks";185;1
"Building";"Factory";NA;172;0
"Unit";"Medivac";"Starport";174;2
"Unit";"Marine";"Barracks";186;1
"Unit";"Marine";"Barracks";187;1
"Unit";"Marine";"Barracks";188;1
"Unit";"Marine";"Barracks";189;1
"Unit";"Marine";"Barracks";190;1
"Unit";"Marine";"Barracks";191;1
"Unit";"Marine";"Barracks";194;1
"Unit";"Marine";"Barracks";195;1
"Unit";"Marine";"Barracks";196;1
"Unit";"Marine";"Barracks";197;1
"Unit";"Marine";"Barracks";198;1
"Unit";"Marine";"Barracks";199;1
"Unit";"Marine";"Barracks";200;1
"Unit";"Marine";"Barracks";202;1
"Unit";"Marine";"Barracks";205;1
"Upgrade";"TerranInfantryWeaponsLevel2";"EngineeringBay";167;0
"Unit";"Marine";"Barracks";205;1
"Unit";"Marine";"Barracks";205;1
"Unit";"Marine";"Barracks";205;1
"Unit";"Marine";"Barracks";206;1
"Unit";"Marine";"Barracks";207;1
"Unit";"SCV";"Command Center";208;1
"Unit";"SCV";"Command Center";208;1
"Unit";"SCV";"Command Center";209;1
"Upgrade";"TerranInfantryArmorsLevel2";"EngineeringBay";172;0
"Unit";"Marine";"Barracks";208;1
"Unit";"Marine";"Barracks";209;1
"Unit";"Marine";"Barracks";210;1
"Unit";"Marine";"Barracks";211;1
"Unit";"SCV";"Command Center";214;1
"Unit";"SCV";"Command Center";215;1
"Unit";"SCV";"Command Center";216;1
"Building";"FactoryTechLab";NA;212;0
"Unit";"Marine";"Barracks";212;1
"Unit";"Marine";"Barracks";213;1
"Unit";"Marine";"Barracks";217;1
"Unit";"Marine";"Barracks";218;1
"Unit";"Marine";"Barracks";219;1
"Unit";"Marine";"Barracks";220;1
"Unit";"SCV";"Command Center";226;1
"Unit";"SCV";"Command Center";226;1
"Unit";"SCV";"Command Center";226;1
"Unit";"Marine";"Barracks";224;1
"Unit";"Marine";"Barracks";225;1
"Unit";"Marine";"Barracks";226;1
"Unit";"Marine";"Barracks";227;1
"Unit";"Marine";"Barracks";228;1
"Unit";"Marine";"Barracks";229;1
"Unit";"Medivac";"Starport";226;2
"Unit";"Medivac";"Starport";226;2
"Unit";"Marine";"Barracks";233;1
"Building";"SupplyDepot";NA;230;0
"Unit";"Marine";"Barracks";234;1
"Building";"SupplyDepot";NA;233;0
"Building";"SupplyDepot";NA;233;0
"Unit";"Marine";"Barracks";235;1
"Unit";"Marine";"Barracks";236;1
"Unit";"Marine";"Barracks";237;1
"Unit";"Marine";"Barracks";238;1
"Unit";"Marine";"Barracks";243;1
"Unit";"Marine";"Barracks";244;1
"Unit";"Marine";"Barracks";245;1
"Unit";"Marine";"Barracks";246;1
"Unit";"Marine";"Barracks";247;1
"Unit";"Marine";"Barracks";248;1
"Unit";"Marine";"Barracks";249;1
"Unit";"Marine";"Barracks";250;1
"Unit";"Marine";"Barracks";251;1
"Unit";"Marine";"Barracks";252;1
"Unit";"Marine";"Barracks";253;1
"Unit";"Marine";"Barracks";254;1
"Unit";"Marine";"Barracks";255;1
"Unit";"Marine";"Barracks";256;1
"Unit";"Medivac";"Starport";255;2
"Unit";"Medivac";"Starport";255;2
"Unit";"Marine";"Barracks";257;1
"Unit";"Marine";"Barracks";258;1
"Unit";"Marine";"Barracks";259;1
"Unit";"Marine";"Barracks";260;1
"Building";"SupplyDepot";NA;257;0
"Unit";"Marine";"Barracks";261;1
"Unit";"Marine";"Barracks";262;1
"Building";"Refinery";NA;261;0
"Building";"Refinery";NA;263;0
"Unit";"Marine";"Barracks";267;1
"Unit";"Marine";"Barracks";268;1
"Unit";"Marine";"Barracks";269;1
"Unit";"Marine";"Barracks";270;1
"Building";"Barracks";NA;257;0
"Building";"Barracks";NA;257;0
"Unit";"Marine";"Barracks";271;1
"Unit";"Marine";"Barracks";272;1
"Unit";"Marine";"Barracks";273;1
"Unit";"Marine";"Barracks";274;1
"Unit";"Marine";"Barracks";275;1
"Unit";"Marine";"Barracks";276;1
