"Type";"UnitName";"OnBuilding";"TotalSupply";"Supply"
"Unit";"SCV";"Command Center";12;1
"Unit";"SCV";"Command Center";12;1
"Unit";"SCV";"Command Center";13;1
"Building";"SupplyDepot";NA;13;0
"Unit";"SCV";"Command Center";15;1
"Unit";"SCV";"Command Center";15;1
"Building";"Refinery";NA;15;0
"Unit";"SCV";"Command Center";16;1
"Building";"Barracks";NA;15;0
"Unit";"SCV";"Command Center";17;1
"Unit";"Reaper";"Barracks";19;1
"Unit";"SCV";"Command Center";19;1
"Unit";"SCV";"Command Center";21;1
"Building";"SupplyDepot";NA;20;0
"Unit";"SCV";"Command Center";21;1
"Building";"BarracksReactor";NA;20;0
"Building";"Refinery";NA;21;0
"Building";"Barracks";NA;19;0
"Unit";"SCV";"Command Center";23;1
"Building";"CommandCenter";NA;19;0
"Unit";"Marine";"Barracks";23;1
"Unit";"Marine";"Barracks";23;1
"Building";"BarracksTechLab";NA;23;0
"Unit";"SCV";"Command Center";24;1
"Building";"Factory";NA;22;0
"Unit";"Marine";"Barracks";26;1
"Unit";"Marine";"Barracks";26;1
"Unit";"SCV";"Command Center";26;1
"Unit";"Marine";"Barracks";26;1
"Unit";"SCV";"Command Center";29;1
"Unit";"Marine";"Barracks";29;1
"Unit";"Marine";"Barracks";29;1
"Unit";"SCV";"Command Center";32;1
"Unit";"Marine";"Barracks";31;1
"Unit";"SCV";"Command Center";32;1
"Unit";"SCV";"Command Center";37;1
"Building";"Starport";NA;31;0
"Unit";"Marine";"Barracks";34;1
"Unit";"Marine";"Barracks";34;1
"Building";"SupplyDepot";NA;34;0
"Unit";"SCV";"Command Center";37;1
"Building";"FactoryReactor";NA;31;0
"Unit";"Marine";"Barracks";37;1
"Unit";"SCV";"Command Center";37;1
"Building";"SupplyDepot";NA;37;0
"Unit";"SCV";"Command Center";40;1
"Unit";"Marine";"Barracks";40;1
"Unit";"Marine";"Barracks";40;1
"Unit";"SCV";"Command Center";42;1
"Unit";"SCV";"Command Center";44;1
"Building";"SupplyDepot";NA;43;0
"Building";"SupplyDepot";NA;43;0
"Unit";"SCV";"Command Center";47;1
"Unit";"Marine";"Barracks";47;1
"Unit";"Marine";"Barracks";47;1
"Unit";"SCV";"Command Center";47;1
"Unit";"Medivac";"Starport";43;2
"Unit";"Marine";"Barracks";47;1
"Unit";"Medivac";"Starport";44;2
"Unit";"SCV";"Command Center";48;1
"Building";"SupplyDepot";NA;48;0
"Unit";"SCV";"Command Center";51;1
"Unit";"Marine";"Barracks";50;1
"Unit";"SCV";"Command Center";57;1
"Building";"SupplyDepot";NA;51;0
"Unit";"SCV";"Command Center";58;1
"Upgrade";"Stimpack";"TechLab";34;0
"Unit";"Marine";"Barracks";58;1
"Unit";"Marine";"Barracks";58;1
"Unit";"SCV";"Command Center";60;1
"Building";"SupplyDepot";NA;59;0
"Unit";"Marine";"Barracks";60;1
"Building";"SupplyDepot";NA;60;0
"Unit";"SCV";"Command Center";64;1
"Unit";"SCV";"Command Center";65;1
"Unit";"Marine";"Barracks";62;1
"Unit";"Marine";"Barracks";63;1
"Unit";"Medivac";"Starport";61;2
"Unit";"Marine";"Barracks";65;1
"Unit";"SCV";"Command Center";66;1
"Unit";"SCV";"Command Center";67;1
"Unit";"Medivac";"Starport";62;2
"Unit";"Marine";"Barracks";68;1
"Unit";"Marine";"Barracks";70;1
"Unit";"Marine";"Barracks";72;1
"Building";"Refinery";NA;79;0
"Building";"Refinery";NA;79;0
"Unit";"Marine";"Barracks";80;1
"Unit";"Marine";"Barracks";80;1
"Unit";"Medivac";"Starport";77;2
"Unit";"Medivac";"Starport";77;2
"Unit";"Marauder";"Barracks";80;2
"Building";"Barracks";NA;72;0
"Unit";"SCV";"Command Center";80;1
"Unit";"SCV";"Command Center";80;1
"Building";"SupplyDepot";NA;80;0
"Building";"EngineeringBay";NA;80;0
"Building";"EngineeringBay";NA;80;0
"Building";"Barracks";NA;79;0
"Building";"Barracks";NA;80;0
"Unit";"SCV";"Command Center";90;1
"Unit";"SCV";"Command Center";90;1
"Unit";"Marine";"Barracks";90;1
"Unit";"Marauder";"Barracks";90;2
"Unit";"SCV";"Command Center";90;1
"Unit";"Medivac";"Starport";90;2
"Unit";"Marine";"Barracks";90;1
"Unit";"Marine";"Barracks";91;1
"Unit";"Marine";"Barracks";92;1
"Unit";"SCV";"Command Center";93;1
"Unit";"Marine";"Barracks";92;1
"Building";"BarracksReactor";NA;90;0
"Unit";"SCV";"Command Center";95;1
"Unit";"Marine";"Barracks";93;1
"Unit";"Marine";"Barracks";98;1
"Unit";"Marine";"Barracks";104;1
"Unit";"Marine";"Barracks";104;1
"Unit";"Marine";"Barracks";104;1
"Unit";"Marine";"Barracks";104;1
"Building";"FactoryTechLab";NA;105;0
"Unit";"Medivac";"Starport";96;2
"Unit";"Medivac";"Starport";96;2
"Unit";"Marine";"Barracks";105;1
"Building";"SupplyDepot";NA;105;0
"Building";"SupplyDepot";NA;105;0
"Building";"BarracksReactor";NA;103;0
"Building";"BarracksReactor";NA;103;0
"Unit";"Marine";"Barracks";106;1
"Unit";"Marine";"Barracks";110;1
"Unit";"Marine";"Barracks";110;1
"Unit";"Marine";"Barracks";110;1
"Unit";"Marine";"Barracks";114;1
"Unit";"Marine";"Barracks";119;1
"Unit";"Marine";"Barracks";119;1
"Unit";"Marine";"Barracks";119;1
"Unit";"Marine";"Barracks";119;1
"Unit";"Marine";"Barracks";119;1
"Unit";"Marine";"Barracks";119;1
"Unit";"Marine";"Barracks";119;1
"Unit";"Marauder";"Barracks";119;2
"Unit";"Marine";"Barracks";119;1
"Building";"SupplyDepot";NA;120;0
"Building";"SupplyDepot";NA;120;0
"Unit";"Marine";"Barracks";120;1
"Unit";"Marine";"Barracks";121;1
"Unit";"Marine";"Barracks";122;1
"Unit";"Marine";"Barracks";123;1
"Unit";"Marauder";"Barracks";127;2
"Building";"CommandCenter";NA;106;0
"Unit";"Marine";"Barracks";130;1
"Unit";"Marine";"Barracks";130;1
"Unit";"Marine";"Barracks";130;1
"Unit";"Marine";"Barracks";130;1
"Unit";"Marine";"Barracks";130;1
"Unit";"Marine";"Barracks";131;1
"Unit";"Marine";"Barracks";132;1
"Unit";"Marine";"Barracks";134;1
"Unit";"Marauder";"Barracks";134;2
"Unit";"Marine";"Barracks";136;1
"Unit";"Marine";"Barracks";137;1
"Unit";"Marine";"Barracks";138;1
"Unit";"Marine";"Barracks";140;1
"Unit";"Medivac";"Starport";134;2
"Unit";"Medivac";"Starport";134;2
"Unit";"Marine";"Barracks";140;1
"Unit";"Marine";"Barracks";141;1
"Unit";"Marine";"Barracks";142;1
"Unit";"Marine";"Barracks";143;1
"Upgrade";"TerranInfantryWeaponsLevel1";"EngineeringBay";119;0
"Unit";"Marine";"Barracks";146;1
"Unit";"Marine";"Barracks";147;1
"Unit";"Marine";"Barracks";148;1
"Unit";"Marauder";"Barracks";144;2
"Unit";"Marine";"Barracks";149;1
"Unit";"Marine";"Barracks";154;1
"Unit";"Marine";"Barracks";158;1
"Unit";"Marine";"Barracks";158;1
"Unit";"Marine";"Barracks";158;1
"Unit";"Marine";"Barracks";158;1
"Unit";"Marine";"Barracks";159;1
"Unit";"Marine";"Barracks";164;1
"Unit";"Marine";"Barracks";164;1
"Unit";"Marine";"Barracks";164;1
"Unit";"Marine";"Barracks";164;1
"Unit";"Medivac";"Starport";158;2
"Unit";"Medivac";"Starport";158;2
"Unit";"Marine";"Barracks";168;1
"Unit";"Marine";"Barracks";168;1
"Unit";"SCV";"Command Center";174;1
"Unit";"SCV";"Command Center";174;1
"Unit";"Marine";"Barracks";170;1
"Unit";"Marine";"Barracks";170;1
"Unit";"Marine";"Barracks";170;1
"Upgrade";"TerranInfantryArmorsLevel1";"EngineeringBay";134;0
"Unit";"Marine";"Barracks";170;1
"Unit";"Marine";"Barracks";171;1
"Building";"Refinery";NA;170;0
"Building";"Bunker";NA;168;0
"Building";"Refinery";NA;176;0
"Unit";"Marine";"Barracks";180;1
"Unit";"Marine";"Barracks";181;1
"Unit";"Marine";"Barracks";182;1
"Unit";"Marine";"Barracks";182;1
"Unit";"SCV";"Command Center";187;1
"Unit";"SCV";"Command Center";187;1
"Unit";"Marine";"Barracks";182;1
"Unit";"Marine";"Barracks";183;1
"Unit";"Marine";"Barracks";184;1
"Unit";"Marine";"Barracks";187;1
"Unit";"Marine";"Barracks";187;1
"Unit";"Marine";"Barracks";187;1
"Unit";"Marine";"Barracks";188;1
"Building";"Armory";NA;178;0
"Unit";"Marine";"Barracks";196;1
"Unit";"Marine";"Barracks";196;1
"Unit";"Marine";"Barracks";196;1
"Unit";"Marine";"Barracks";196;1
"Unit";"Marine";"Barracks";196;1
"Unit";"Marine";"Barracks";196;1
"Unit";"Marine";"Barracks";200;1
"Unit";"Marine";"Barracks";200;1
"Unit";"Marine";"Barracks";200;1
"Unit";"Marine";"Barracks";200;1
"Unit";"Marine";"Barracks";201;1
"Unit";"Medivac";"Starport";198;2
"Unit";"Medivac";"Starport";198;2
"Unit";"Marine";"Barracks";206;1
"Unit";"Marine";"Barracks";206;1
"Unit";"Marine";"Barracks";206;1
"Unit";"Marine";"Barracks";206;1
"Unit";"Marine";"Barracks";206;1
"Unit";"Marine";"Barracks";207;1
"Unit";"Marine";"Barracks";211;1
"Unit";"Marine";"Barracks";211;1
"Unit";"Marine";"Barracks";211;1
"Unit";"Marine";"Barracks";221;1
"Unit";"Marine";"Barracks";221;1
"Unit";"Marine";"Barracks";221;1
"Unit";"Marine";"Barracks";221;1
"Unit";"Marine";"Barracks";221;1
"Unit";"Marine";"Barracks";221;1
"Unit";"Marine";"Barracks";221;1
"Unit";"Marine";"Barracks";222;1
"Unit";"Medivac";"Starport";215;2
"Unit";"Medivac";"Starport";215;2
"Unit";"SCV";"Command Center";224;1
"Unit";"SCV";"Command Center";224;1
"Unit";"SCV";"Command Center";224;1
"Unit";"Marine";"Barracks";224;1
"Building";"Barracks";NA;211;0
"Unit";"Marine";"Barracks";224;1
"Unit";"Marine";"Barracks";225;1
"Unit";"Marine";"Barracks";226;1
"Unit";"Marine";"Barracks";227;1
"Unit";"Marine";"Barracks";228;1
"Unit";"Marine";"Barracks";229;1
"Unit";"Marine";"Barracks";236;1
"Unit";"Marine";"Barracks";239;1
"Unit";"Marine";"Barracks";239;1
"Unit";"Medivac";"Starport";236;2
"Unit";"Marine";"Barracks";246;1
"Unit";"Marine";"Barracks";246;1
"Unit";"Marine";"Barracks";246;1
"Unit";"Marine";"Barracks";246;1
"Unit";"Marine";"Barracks";246;1
"Building";"BarracksTechLab";NA;246;0
"Unit";"Marine";"Barracks";247;1
"Unit";"Marine";"Barracks";247;1
"Unit";"Marine";"Barracks";247;1
"Building";"Factory";NA;236;0
"Unit";"Marine";"Barracks";256;1
"Unit";"Marine";"Barracks";256;1
"Unit";"Marine";"Barracks";256;1
"Unit";"Marine";"Barracks";256;1
"Unit";"Marine";"Barracks";256;1
"Unit";"Marine";"Barracks";256;1
"Unit";"Marine";"Barracks";258;1
"Unit";"Marine";"Barracks";258;1
"Unit";"Marine";"Barracks";258;1
"Unit";"Marine";"Barracks";258;1
"Unit";"Marine";"Barracks";259;1
"Unit";"SCV";"Command Center";269;1
"Unit";"SCV";"Command Center";269;1
"Unit";"Marine";"Barracks";268;1
"Unit";"Marine";"Barracks";268;1
"Unit";"Marine";"Barracks";268;1
"Unit";"Marine";"Barracks";268;1
"Unit";"Marine";"Barracks";268;1
"Unit";"Marine";"Barracks";269;1
"Unit";"Marine";"Barracks";269;1
"Unit";"Marine";"Barracks";269;1
"Unit";"Marine";"Barracks";269;1
"Unit";"Marine";"Barracks";269;1
"Unit";"Marine";"Barracks";272;1
"Unit";"Marine";"Barracks";273;1
"Unit";"Marine";"Barracks";274;1
"Unit";"Marine";"Barracks";275;1
"Unit";"Marine";"Barracks";276;1
"Unit";"SCV";"Command Center";279;1
"Unit";"Marine";"Barracks";282;1
"Unit";"Marine";"Barracks";282;1
"Unit";"Marine";"Barracks";282;1
"Unit";"Marine";"Barracks";282;1
"Unit";"Marine";"Barracks";282;1
"Unit";"Marine";"Barracks";282;1
"Unit";"Marine";"Barracks";283;1
"Unit";"Marine";"Barracks";293;1
"Unit";"Marine";"Barracks";293;1
"Unit";"Marine";"Barracks";293;1
"Unit";"Marine";"Barracks";293;1
"Unit";"Marine";"Barracks";293;1
"Unit";"Marine";"Barracks";293;1
"Unit";"Marine";"Barracks";293;1
"Unit";"Marine";"Barracks";293;1
"Unit";"Marine";"Barracks";293;1
"Unit";"Marine";"Barracks";294;1
"Building";"FactoryTechLab";NA;295;0
"Unit";"Marine";"Barracks";295;1
"Unit";"Marine";"Barracks";296;1
"Unit";"Marauder";"Barracks";301;2
"Unit";"Marine";"Barracks";305;1
"Unit";"Marine";"Barracks";305;1
"Unit";"Marine";"Barracks";305;1
"Unit";"Marine";"Barracks";305;1
"Unit";"Marine";"Barracks";305;1
"Unit";"Marine";"Barracks";305;1
"Unit";"Marine";"Barracks";305;1
"Unit";"Medivac";"Starport";299;2
"Unit";"Marine";"Barracks";305;1
"Unit";"Marine";"Barracks";306;1
"Unit";"Marine";"Barracks";307;1
"Unit";"Marine";"Barracks";309;1
"Unit";"Marine";"Barracks";310;1
"Unit";"Marine";"Barracks";311;1
"Unit";"Marine";"Barracks";312;1
"Unit";"Marine";"Barracks";313;1
"Unit";"Marine";"Barracks";314;1
"Unit";"Marine";"Barracks";315;1
"Unit";"SCV";"Command Center";320;1
"Unit";"Marine";"Barracks";318;1
"Unit";"Marine";"Barracks";319;1
"Unit";"SCV";"Command Center";321;1
"Unit";"SCV";"Command Center";321;1
"Unit";"Marine";"Barracks";320;1
"Unit";"Marine";"Barracks";321;1
"Unit";"Marine";"Barracks";322;1
"Unit";"Marine";"Barracks";323;1
"Unit";"Marine";"Barracks";324;1
"Unit";"SCV";"Command Center";331;1
"Unit";"SCV";"Command Center";332;1
"Unit";"Marine";"Barracks";328;1
"Unit";"Marine";"Barracks";334;1
"Unit";"Marine";"Barracks";335;1
"Unit";"Marine";"Barracks";336;1
"Unit";"Marine";"Barracks";337;1
"Unit";"Marine";"Barracks";337;1
"Unit";"Marine";"Barracks";338;1
"Unit";"Marine";"Barracks";338;1
