"Type";"UnitName";"OnBuilding";"TotalSupply";"Supply"
"Unit";"SCV";"Command Center";12;1
"Unit";"SCV";"Command Center";12;1
"Unit";"SCV";"Command Center";13;1
"Building";"SupplyDepot";NA;13;0
"Unit";"SCV";"Command Center";15;1
"Unit";"SCV";"Command Center";15;1
"Building";"Refinery";NA;15;0
"Unit";"SCV";"Command Center";16;1
"Unit";"SCV";"Command Center";17;1
"Building";"Barracks";NA;15;0
"Unit";"Reaper";"Barracks";19;1
"Unit";"SCV";"Command Center";19;1
"Building";"SupplyDepot";NA;19;0
"Unit";"SCV";"Command Center";20;1
"Unit";"Marine";"Barracks";19;1
"Unit";"SCV";"Command Center";22;1
"Building";"Refinery";NA;21;0
"Unit";"SCV";"Command Center";23;1
"Building";"CommandCenter";NA;19;0
"Unit";"SCV";"Command Center";24;1
"Building";"Factory";NA;21;0
"Building";"BarracksReactor";NA;23;0
"Unit";"SCV";"Command Center";25;1
"Unit";"SCV";"Command Center";26;1
"Building";"BarracksTechLab";NA;27;0
"Unit";"SCV";"Command Center";27;1
"Unit";"Hellion";"Factory";27;2
"Unit";"Hellion";"Factory";27;2
"Unit";"SCV";"Command Center";28;1
"Building";"Starport";NA;26;0
"Building";"SupplyDepot";NA;28;0
"Building";"SupplyDepot";NA;28;0
"Unit";"SCV";"Command Center";34;1
"Unit";"SCV";"Command Center";34;1
"Unit";"Hellion";"Factory";34;2
"Unit";"Hellion";"Factory";34;2
"Unit";"SCV";"Command Center";34;1
"Unit";"SCV";"Command Center";35;1
"Building";"BarracksTechLab";NA;34;0
"Unit";"SCV";"Command Center";40;1
"Unit";"Hellion";"Factory";40;2
"Unit";"Hellion";"Factory";40;2
"Unit";"SCV";"Command Center";42;1
"Unit";"SCV";"Command Center";43;1
"Building";"SupplyDepot";NA;43;0
"Unit";"SCV";"Command Center";49;1
"Unit";"SCV";"Command Center";49;1
"Unit";"SCV";"Command Center";49;1
"Unit";"SCV";"Command Center";50;1
"Unit";"Marine";"Barracks";49;1
"Unit";"Marine";"Barracks";49;1
"Unit";"Banshee";"Starport";43;3
"Unit";"SCV";"Command Center";51;1
"Building";"Refinery";NA;51;0
"Building";"Refinery";NA;51;0
"Building";"EngineeringBay";NA;51;0
"Building";"EngineeringBay";NA;53;0
"Building";"CommandCenter";NA;42;0
"Unit";"SCV";"Command Center";59;1
"Unit";"SCV";"Command Center";59;1
"Unit";"SCV";"Command Center";61;1
"Unit";"SCV";"Command Center";61;1
"Unit";"SCV";"Command Center";61;1
"Unit";"Banshee";"Starport";59;3
"Unit";"SCV";"Command Center";63;1
"Unit";"Marine";"Barracks";61;1
"Building";"FactoryReactor";NA;59;0
"Unit";"SCV";"Command Center";63;1
"Building";"SupplyDepot";NA;63;0
"Building";"SupplyDepot";NA;63;0
"Building";"Barracks";NA;61;0
"Unit";"SCV";"Command Center";70;1
"Building";"Barracks";NA;61;0
"Unit";"Marine";"Barracks";70;1
"Unit";"Marine";"Barracks";70;1
"Unit";"Marine";"Barracks";70;1
"Building";"StarportReactor";NA;69;0
"Unit";"Marine";"Barracks";71;1
"Unit";"SCV";"Command Center";73;1
"Unit";"SCV";"Command Center";74;1
"Unit";"Marine";"Barracks";72;1
"Unit";"Marine";"Barracks";74;1
"Unit";"Marine";"Barracks";74;1
"Unit";"Marine";"Barracks";74;1
"Building";"Barracks";NA;70;0
"Unit";"SCV";"Command Center";75;1
"Unit";"SCV";"Command Center";76;1
"Unit";"Marine";"Barracks";74;1
"Unit";"SCV";"Command Center";77;1
"Building";"Barracks";NA;70;0
"Unit";"SCV";"Command Center";81;1
"Unit";"SCV";"Command Center";82;1
"Building";"SupplyDepot";NA;77;0
"Unit";"SCV";"Command Center";84;1
"Unit";"Marine";"Barracks";81;1
"Unit";"Marine";"Barracks";81;1
"Unit";"Marine";"Barracks";81;1
"Upgrade";"TerranInfantryWeaponsLevel1";"EngineeringBay";68;0
"Upgrade";"TerranInfantryArmorsLevel1";"EngineeringBay";68;0
"Unit";"Medivac";"Starport";81;2
"Unit";"Medivac";"Starport";81;2
"Unit";"SCV";"Command Center";91;1
"Unit";"SCV";"Command Center";91;1
"Unit";"SCV";"Command Center";91;1
"Unit";"Marine";"Barracks";91;1
"Unit";"Marine";"Barracks";91;1
"Unit";"Marine";"Barracks";91;1
"Unit";"Marine";"Barracks";91;1
"Unit";"Marine";"Barracks";91;1
"Building";"Armory";NA;77;0
"Upgrade";"Stimpack";"TechLab";70;0
"Building";"BarracksReactor";NA;85;0
"Building";"BarracksReactor";NA;87;0
"Unit";"Marine";"Barracks";97;1
"Unit";"Marine";"Barracks";99;1
"Unit";"Marine";"Barracks";100;1
"Unit";"Marine";"Barracks";101;1
"Building";"Refinery";NA;103;0
"Unit";"Marine";"Barracks";103;1
"Building";"Refinery";NA;103;0
"Unit";"SCV";"Command Center";103;1
"Unit";"SCV";"Command Center";103;1
"Unit";"SCV";"Command Center";103;1
"Building";"SupplyDepot";NA;103;0
"Unit";"Medivac";"Starport";95;2
"Unit";"Medivac";"Starport";95;2
"Unit";"Marine";"Barracks";103;1
"Unit";"SCV";"Command Center";108;1
"Unit";"Marine";"Barracks";107;1
"Unit";"Marine";"Barracks";107;1
"Unit";"Marine";"Barracks";107;1
"Unit";"Marine";"Barracks";107;1
"Unit";"Marine";"Barracks";107;1
"Unit";"Marine";"Barracks";107;1
"Unit";"Marine";"Barracks";107;1
"Building";"SupplyDepot";NA;107;0
"Building";"SupplyDepot";NA;107;0
"Unit";"Marine";"Barracks";111;1
"Unit";"Marine";"Barracks";115;1
"Unit";"Marine";"Barracks";124;1
"Unit";"Marine";"Barracks";124;1
"Unit";"Marine";"Barracks";124;1
"Unit";"Marine";"Barracks";125;1
"Unit";"Marine";"Barracks";125;1
"Unit";"Marine";"Barracks";125;1
"Unit";"Marine";"Barracks";125;1
"Unit";"Marine";"Barracks";126;1
"Unit";"Marine";"Barracks";126;1
"Unit";"Marine";"Barracks";126;1
"Unit";"Marine";"Barracks";127;1
"Unit";"Marine";"Barracks";128;1
"Unit";"Marine";"Barracks";129;1
"Building";"SupplyDepot";NA;133;0
"Building";"SupplyDepot";NA;133;0
"Unit";"Liberator";"Starport";125;3
"Unit";"Liberator";"Starport";125;3
"Unit";"Marine";"Barracks";139;1
"Unit";"Marine";"Barracks";139;1
"Unit";"Marine";"Barracks";139;1
"Unit";"Marine";"Barracks";139;1
"Unit";"Marine";"Barracks";139;1
"Unit";"Marine";"Barracks";139;1
"Unit";"Marine";"Barracks";139;1
"Unit";"Marine";"Barracks";145;1
"Unit";"Marine";"Barracks";145;1
"Unit";"Marine";"Barracks";145;1
"Unit";"Marine";"Barracks";146;1
"Unit";"Marine";"Barracks";147;1
"Unit";"Marine";"Barracks";148;1
"Unit";"Marine";"Barracks";149;1
"Unit";"Marine";"Barracks";150;1
"Unit";"Marine";"Barracks";151;1
"Unit";"Marine";"Barracks";152;1
"Unit";"Marauder";"Barracks";153;2
"Unit";"Marine";"Barracks";154;1
"Unit";"Marine";"Barracks";155;1
"Unit";"Marine";"Barracks";156;1
"Unit";"Marine";"Barracks";157;1
"Unit";"Marine";"Barracks";158;1
"Unit";"Marine";"Barracks";159;1
"Upgrade";"TerranInfantryWeaponsLevel2";"EngineeringBay";124;0
"Upgrade";"TerranInfantryArmorsLevel2";"EngineeringBay";124;0
"Unit";"Marine";"Barracks";161;1
"Unit";"Marine";"Barracks";161;1
"Building";"CommandCenter";NA;139;0
"Unit";"Marine";"Barracks";162;1
"Unit";"Marine";"Barracks";164;1
"Unit";"Marine";"Barracks";165;1
"Unit";"Marine";"Barracks";171;1
"Unit";"Marine";"Barracks";171;1
"Unit";"Marine";"Barracks";171;1
"Unit";"Marine";"Barracks";171;1
"Unit";"Marine";"Barracks";171;1
"Unit";"Marine";"Barracks";171;1
"Unit";"Marine";"Barracks";172;1
"Unit";"Marine";"Barracks";173;1
"Unit";"Marine";"Barracks";174;1
"Building";"Factory";NA;161;0
"Building";"Barracks";NA;161;0
"Building";"Barracks";NA;161;0
"Unit";"Medivac";"Starport";172;2
"Unit";"Medivac";"Starport";172;2
"Unit";"Marine";"Barracks";184;1
"Unit";"Marine";"Barracks";184;1
"Unit";"Marine";"Barracks";184;1
"Unit";"Marine";"Barracks";184;1
"Unit";"Marine";"Barracks";184;1
"Unit";"Marine";"Barracks";184;1
"Unit";"Marine";"Barracks";184;1
"Unit";"Marine";"Barracks";184;1
"Building";"BarracksTechLab";NA;188;0
"Building";"BarracksTechLab";NA;188;0
"Building";"FactoryTechLab";NA;188;0
"Unit";"Marine";"Barracks";188;1
"Unit";"Marine";"Barracks";189;1
"Unit";"Marine";"Barracks";190;1
"Unit";"Marine";"Barracks";191;1
"Unit";"Marine";"Barracks";192;1
"Unit";"Marine";"Barracks";193;1
"Unit";"Marine";"Barracks";195;1
"Unit";"Marine";"Barracks";195;1
"Unit";"Marine";"Barracks";195;1
"Unit";"Marine";"Barracks";196;1
"Unit";"Marine";"Barracks";196;1
"Unit";"Marine";"Barracks";196;1
"Unit";"Marine";"Barracks";197;1
"Unit";"Marine";"Barracks";198;1
"Unit";"Marine";"Barracks";199;1
"Unit";"Marine";"Barracks";200;1
"Unit";"Marine";"Barracks";201;1
"Unit";"Marine";"Barracks";202;1
"Unit";"Marine";"Barracks";204;1
"Unit";"SCV";"Command Center";205;1
"Unit";"SCV";"Command Center";205;1
"Unit";"SCV";"Command Center";205;1
"Unit";"Marauder";"Barracks";203;2
"Unit";"Marine";"Barracks";206;1
"Building";"Refinery";NA;205;0
"Unit";"Marauder";"Barracks";205;2
"Unit";"SCV";"Command Center";215;1
"Unit";"SCV";"Command Center";216;1
"Unit";"Marine";"Barracks";214;1
"Unit";"Marine";"Barracks";214;1
"Unit";"Marine";"Barracks";214;1
"Unit";"Marine";"Barracks";220;1
"Unit";"Marine";"Barracks";220;1
"Unit";"Marine";"Barracks";220;1
"Unit";"Marauder";"Barracks";218;2
"Unit";"Marauder";"Barracks";220;2
"Unit";"Marine";"Barracks";231;1
"Unit";"Marauder";"Barracks";229;2
"Unit";"Marine";"Barracks";235;1
"Unit";"Liberator";"Starport";231;3
"Unit";"Liberator";"Starport";231;3
"Unit";"Marine";"Barracks";238;1
"Unit";"Marine";"Barracks";238;1
"Unit";"Marine";"Barracks";238;1
"Unit";"Marauder";"Barracks";238;2
"Unit";"SCV";"Command Center";248;1
"Unit";"SCV";"Command Center";248;1
"Unit";"SCV";"Command Center";248;1
"Upgrade";"TerranInfantryWeaponsLevel3";"EngineeringBay";196;0
"Upgrade";"TerranInfantryArmorsLevel3";"EngineeringBay";196;0
"Unit";"SCV";"Command Center";250;1
"Unit";"Marine";"Barracks";250;1
"Unit";"Marine";"Barracks";250;1
"Unit";"Marine";"Barracks";250;1
"Unit";"Marine";"Barracks";250;1
"Unit";"Marauder";"Barracks";250;2
"Unit";"Marauder";"Barracks";250;2
"Unit";"Marauder";"Barracks";250;2
"Unit";"Marine";"Barracks";253;1
"Unit";"Marine";"Barracks";253;1
"Unit";"Marine";"Barracks";253;1
