"type";"unit_name";"on_building";"total_supply";"supply"
"Building";"Refinery";NA;15;0
"Building";"Barracks";NA;15;0
"Building";"BarracksReactor";NA;19;0
"Unit";"Marine";"Barracks";19;1
"Unit";"Marine";"Barracks";19;1
"Unit";"Marine";"Barracks";23;1
"Unit";"Marine";"Barracks";23;1
"Building";"CommandCenter";NA;19;0
"Unit";"Marine";"Barracks";24;1
"Unit";"Marine";"Barracks";25;1
"Building";"Barracks";NA;20;0
"Building";"Refinery";NA;27;0
"Building";"Factory";NA;24;0
"Unit";"Marine";"Barracks";28;1
"Unit";"Marine";"Barracks";29;1
"Building";"BarracksTechLab";NA;30;0
"Building";"FactoryTechLab";NA;30;0
"Unit";"Marine";"Barracks";30;1
"Unit";"Marine";"Barracks";31;1
"Unit";"Marine";"Barracks";33;1
"Unit";"Marine";"Barracks";33;1
"Unit";"Marine";"Barracks";37;1
"Unit";"Marine";"Barracks";40;1
"Unit";"Marine";"Barracks";40;1
"Unit";"Marine";"Barracks";40;1
"Building";"Barracks";NA;37;0
"Building";"Bunker";NA;38;0
"Unit";"Marine";"Barracks";42;1
"Unit";"Marine";"Barracks";45;1
"Unit";"Marine";"Barracks";46;1
"Unit";"Marine";"Barracks";48;1
"Unit";"Marine";"Barracks";50;1
"Building";"Starport";NA;46;0
"Unit";"Marine";"Barracks";51;1
"Unit";"Marine";"Barracks";51;1
"Upgrade";"Stimpack";"TechLab";38;0
"Building";"Refinery";NA;54;0
"Building";"Refinery";NA;57;0
"Unit";"Marine";"Barracks";57;1
"Unit";"Medivac";"Starport";57;2
"Unit";"Marine";"Barracks";59;1
"Unit";"Marine";"Barracks";59;1
"Unit";"Medivac";"Starport";57;2
"Unit";"Marine";"Barracks";67;1
"Unit";"Marine";"Barracks";69;1
"Unit";"Marine";"Barracks";69;1
"Building";"Bunker";NA;62;0
"Building";"EngineeringBay";NA;74;0
"Unit";"Medivac";"Starport";74;2
"Unit";"Marine";"Barracks";78;1
"Unit";"Marine";"Barracks";78;1
"Building";"BarracksReactor";NA;78;0
"Unit";"Marine";"Barracks";81;1
"Unit";"Marine";"Barracks";82;1
"Unit";"Medivac";"Starport";81;2
"Unit";"Marine";"Barracks";85;1
"Unit";"Marine";"Barracks";85;1
"Unit";"Medivac";"Starport";83;2
"Unit";"Marine";"Barracks";87;1
"Building";"CommandCenter";NA;80;0
"Unit";"Medivac";"Starport";85;2
"Unit";"Marine";"Barracks";91;1
"Building";"BarracksReactor";NA;85;0
"Building";"EngineeringBay";NA;91;0
"Building";"EngineeringBay";NA;91;0
"Building";"BarracksReactor";NA;87;0
"Unit";"Marine";"Barracks";92;1
"Building";"Factory";NA;87;0
"Building";"EngineeringBay";NA;92;0
"Unit";"Marine";"Barracks";97;1
"Unit";"Marine";"Barracks";97;1
"Unit";"Marine";"Barracks";97;1
"Building";"Factory";NA;91;0
"Unit";"Medivac";"Starport";92;2
"Unit";"Marine";"Barracks";103;1
"Unit";"Marine";"Barracks";103;1
"Unit";"Marine";"Barracks";103;1
"Unit";"Marine";"Barracks";103;1
"Unit";"Marine";"Barracks";103;1
"Unit";"Marine";"Barracks";103;1
"Unit";"Marine";"Barracks";103;1
"Unit";"Marine";"Barracks";106;1
"Unit";"Marine";"Barracks";106;1
"Building";"FactoryTechLab";NA;109;0
"Unit";"Marine";"Barracks";110;1
"Unit";"Marine";"Barracks";112;1
"Unit";"Marine";"Barracks";112;1
"Unit";"Marine";"Barracks";114;1
"Upgrade";"TerranInfantryWeaponsLevel1";"EngineeringBay";98;0
"Unit";"Marine";"Barracks";116;1
"Unit";"Medivac";"Starport";114;2
"Unit";"Marine";"Barracks";119;1
"Unit";"Marine";"Barracks";119;1
"Unit";"Marine";"Barracks";119;1
"Building";"SensorTower";NA;120;0
"Building";"SensorTower";NA;120;0
"Upgrade";"TerranInfantryArmorsLevel1";"EngineeringBay";103;0
"Building";"Barracks";NA;116;0
"Building";"Barracks";NA;116;0
"Unit";"Marine";"Barracks";129;1
"Unit";"Marine";"Barracks";129;1
"Unit";"Marine";"Barracks";129;1
"Building";"BarracksReactor";NA;120;0
"Building";"Refinery";NA;131;0
"Building";"Refinery";NA;131;0
"Unit";"Marine";"Barracks";135;1
"Unit";"Marine";"Barracks";135;1
"Unit";"Medivac";"Starport";135;2
"Building";"Armory";NA;130;0
"Unit";"Marine";"Barracks";138;1
"Unit";"Marine";"Barracks";138;1
"Unit";"Marine";"Barracks";138;1
"Unit";"Marine";"Barracks";138;1
"Unit";"Marine";"Barracks";138;1
"Unit";"Marine";"Barracks";140;1
"Unit";"Marine";"Barracks";140;1
"Unit";"Marine";"Barracks";140;1
"Unit";"Marine";"Barracks";142;1
"Unit";"Marine";"Barracks";143;1
"Unit";"Marine";"Barracks";144;1
"Unit";"Medivac";"Starport";140;2
"Unit";"Marine";"Barracks";150;1
"Unit";"Marine";"Barracks";150;1
"Unit";"Marine";"Barracks";150;1
"Unit";"Marine";"Barracks";150;1
"Unit";"Marine";"Barracks";151;1
"Unit";"Marine";"Barracks";155;1
"Unit";"Marine";"Barracks";155;1
"Building";"BarracksReactor";NA;150;0
"Building";"BarracksReactor";NA;150;0
"Unit";"Marine";"Barracks";156;1
"Unit";"Marine";"Barracks";162;1
"Unit";"Marine";"Barracks";162;1
"Unit";"Marine";"Barracks";162;1
"Unit";"Marine";"Barracks";162;1
"Unit";"Marine";"Barracks";162;1
"Unit";"Marine";"Barracks";162;1
"Unit";"Marine";"Barracks";162;1
"Unit";"Marine";"Barracks";170;1
"Unit";"Marine";"Barracks";170;1
"Unit";"Marine";"Barracks";170;1
"Unit";"Marine";"Barracks";170;1
"Building";"CommandCenter";NA;156;0
"Unit";"Medivac";"Starport";170;2
"Unit";"Medivac";"Starport";170;2
"Unit";"Marine";"Barracks";170;1
"Unit";"Marine";"Barracks";170;1
"Upgrade";"TerranVehicleWeaponsLevel1";"Armory";161;0
"Building";"MissileTurret";NA;180;0
"Unit";"Marine";"Barracks";180;1
"Unit";"Marine";"Barracks";180;1
"Building";"MissileTurret";NA;180;0
"Unit";"Marine";"Barracks";180;1
"Unit";"Marine";"Barracks";180;1
"Unit";"Marine";"Barracks";180;1
"Unit";"Marine";"Barracks";182;1
"Unit";"Marine";"Barracks";182;1
"Unit";"Marine";"Barracks";182;1
"Unit";"Marine";"Barracks";182;1
"Unit";"Marine";"Barracks";182;1
"Unit";"Medivac";"Starport";180;2
"Unit";"Medivac";"Starport";180;2
"Upgrade";"TerranInfantryWeaponsLevel2";"EngineeringBay";170;0
"Unit";"Marine";"Barracks";191;1
"Unit";"Marine";"Barracks";193;1
"Unit";"Marine";"Barracks";193;1
"Building";"MissileTurret";NA;193;0
"Unit";"Marine";"Barracks";200;1
"Unit";"Marine";"Barracks";200;1
"Unit";"Marine";"Barracks";200;1
"Unit";"Marine";"Barracks";200;1
"Unit";"Marine";"Barracks";202;1
"Unit";"Marine";"Barracks";202;1
"Upgrade";"TerranInfantryArmorsLevel2";"EngineeringBay";180;0
"Unit";"Marine";"Barracks";211;1
"Unit";"Marine";"Barracks";211;1
"Unit";"Marine";"Barracks";211;1
"Unit";"Marine";"Barracks";211;1
"Unit";"Marine";"Barracks";213;1
"Unit";"Marine";"Barracks";215;1
"Unit";"Marine";"Barracks";215;1
"Upgrade";"TerranVehicleWeaponsLevel2";"Armory";197;0
