"type";"unit_name";"on_building";"total_supply";"supply"
"Building";"Refinery";NA;14;0
"Building";"Refinery";NA;16;0
"Building";"Barracks";NA;15;0
"Building";"BarracksReactor";NA;19;0
"Building";"Factory";NA;19;0
"Unit";"Cyclone";"Factory";22;3
"Unit";"Cyclone";"Factory";22;3
"Building";"Armory";NA;21;0
"Unit";"Cyclone";"Factory";30;3
"Unit";"Cyclone";"Factory";35;3
"Unit";"Cyclone";"Factory";37;3
"Building";"Refinery";NA;40;0
"Building";"Refinery";NA;41;0
"Building";"CommandCenter";NA;31;0
"Unit";"Cyclone";"Factory";41;3
"Unit";"Cyclone";"Factory";45;3
"Upgrade";"TerranVehicleWeaponsLevel1";"Armory";36;0
"Unit";"Cyclone";"Factory";50;3
"Building";"Factory";NA;54;0
