"type";"unit_name";"on_building";"total_supply";"supply"
"Building";"Refinery";NA;14;0
"Building";"Barracks";NA;15;0
"Unit";"Reaper";"Barracks";19;1
"Building";"Refinery";NA;21;0
"Building";"Factory";NA;19;0
"Building";"BarracksReactor";NA;20;0
"Building";"CommandCenter";NA;19;0
"Building";"BarracksTechLab";NA;24;0
"Unit";"Hellion";"Factory";23;2
"Unit";"Hellion";"Factory";23;2
"Building";"Starport";NA;23;0
"Unit";"Hellion";"Factory";29;2
"Unit";"Hellion";"Factory";29;2
"Unit";"Hellion";"Factory";35;2
"Unit";"Hellion";"Factory";35;2
"Unit";"Hellion";"Factory";43;2
"Unit";"Hellion";"Factory";43;2
"Unit";"Hellion";"Factory";46;2
"Unit";"Hellion";"Factory";48;2
"Unit";"Liberator";"Starport";45;3
"Building";"Refinery";NA;57;0
"Building";"Refinery";NA;57;0
"Unit";"Cyclone";"Factory";62;3
"Building";"CommandCenter";NA;52;0
"Unit";"Cyclone";"Factory";69;3
"Unit";"Banshee";"Starport";68;3
"Building";"BarracksTechLab";NA;71;0
"Unit";"Hellion";"Factory";76;2
"Unit";"Hellion";"Factory";76;2
"Building";"Armory";NA;69;0
"Building";"Armory";NA;69;0
"Building";"Factory";NA;71;0
"Building";"Factory";NA;71;0
"Unit";"Hellion";"Factory";87;2
"Unit";"Hellion";"Factory";87;2
"Building";"StarportReactor";NA;81;0
"Unit";"Hellion";"Factory";89;2
"Unit";"Hellion";"Factory";91;2
"Building";"Refinery";NA;93;0
"Building";"Refinery";NA;93;0
"Unit";"Hellion";"Factory";99;2
"Unit";"Hellion";"Factory";99;2
"Unit";"Thor";"Factory";94;6
"Unit";"Thor";"Factory";94;6
"Unit";"Medivac";"Starport";99;2
"Unit";"Medivac";"Starport";99;2
"Unit";"Hellion";"Factory";106;2
"Unit";"Hellion";"Factory";107;2
"Upgrade";"TerranVehicleWeaponsLevel1";"Armory";94;0
"Unit";"Hellion";"Factory";130;2
"Unit";"Hellion";"Factory";130;2
"Building";"Refinery";NA;130;0
"Building";"Factory";NA;125;0
"Building";"Factory";NA;125;0
"Unit";"Medivac";"Starport";133;2
"Unit";"Medivac";"Starport";133;2
"Building";"FactoryTechLab";NA;140;0
"Building";"FactoryTechLab";NA;140;0
"Unit";"Hellion";"Factory";140;2
"Unit";"Hellion";"Factory";140;2
"Unit";"Hellion";"Factory";154;2
"Unit";"Hellion";"Factory";154;2
"Unit";"Hellion";"Factory";154;2
"Unit";"Thor";"Factory";143;6
"Unit";"Hellion";"Factory";157;2
"Unit";"Hellion";"Factory";159;2
"Unit";"Medivac";"Starport";157;2
"Unit";"Medivac";"Starport";157;2
"Unit";"Hellion";"Factory";179;2
"Unit";"Hellion";"Factory";179;2
"Unit";"Hellion";"Factory";179;2
"Building";"EngineeringBay";NA;179;0
"Unit";"Hellion";"Factory";179;2
"Unit";"Hellion";"Factory";181;2
"Unit";"Thor";"Factory";179;6
"Unit";"Thor";"Factory";179;6
"Upgrade";"TerranVehicleWeaponsLevel2";"Armory";155;0
"Unit";"Thor";"Factory";179;6
"Unit";"Hellion";"Factory";183;2
"Building";"Refinery";NA;185;0
"Building";"Refinery";NA;185;0
"Unit";"Hellion";"Factory";185;2
"Unit";"Hellion";"Factory";187;2
"Unit";"Hellion";"Factory";189;2
"Unit";"Hellion";"Factory";195;2
"Unit";"Hellion";"Factory";201;2
"Unit";"Hellion";"Factory";207;2
"Building";"CommandCenter";NA;179;0
"Unit";"Hellion";"Factory";209;2
"Unit";"Hellion";"Factory";211;2
"Building";"SensorTower";NA;217;0
"Unit";"Hellion";"Factory";213;2
"Building";"SensorTower";NA;219;0
"Unit";"Hellion";"Factory";217;2
"Unit";"Hellion";"Factory";221;2
"Unit";"Hellion";"Factory";221;2
"Unit";"Hellion";"Factory";227;2
"Unit";"Hellion";"Factory";227;2
"Unit";"Hellion";"Factory";232;2
"Unit";"Hellion";"Factory";232;2
"Building";"MissileTurret";NA;236;0
"Unit";"Hellion";"Factory";236;2
"Unit";"Hellion";"Factory";238;2
"Unit";"Hellion";"Factory";244;2
"Unit";"Hellion";"Factory";244;2
"Unit";"Hellion";"Factory";244;2
"Unit";"Hellion";"Factory";248;2
"Building";"Factory";NA;242;0
"Building";"Factory";NA;244;0
"Unit";"Hellion";"Factory";256;2
"Unit";"Hellion";"Factory";256;2
"Unit";"Hellion";"Factory";256;2
"Unit";"Medivac";"Starport";256;2
