"Type";"UnitName";"OnBuilding";"TotalSupply";"Supply"
"Unit";"SCV";"Command Center";12;1
"Unit";"SCV";"Command Center";12;1
"Unit";"SCV";"Command Center";13;1
"Building";"SupplyDepot";NA;13;0
"Unit";"SCV";"Command Center";15;1
"Unit";"SCV";"Command Center";15;1
"Building";"Refinery";NA;15;0
"Unit";"SCV";"Command Center";16;1
"Unit";"SCV";"Command Center";17;1
"Building";"Barracks";NA;15;0
"Unit";"Reaper";"Barracks";19;1
"Unit";"SCV";"Command Center";19;1
"Building";"SupplyDepot";NA;19;0
"Unit";"Marine";"Barracks";19;1
"Unit";"SCV";"Command Center";21;1
"Unit";"SCV";"Command Center";22;1
"Unit";"SCV";"Command Center";23;1
"Building";"CommandCenter";NA;19;0
"Building";"Factory";NA;21;0
"Building";"BarracksReactor";NA;22;0
"Unit";"SCV";"Command Center";24;1
"Building";"Refinery";NA;24;0
"Unit";"SCV";"Command Center";25;1
"Unit";"SCV";"Command Center";27;1
"Building";"BarracksTechLab";NA;27;0
"Unit";"SCV";"Command Center";27;1
"Unit";"Hellion";"Factory";26;2
"Unit";"Hellion";"Factory";26;2
"Unit";"SCV";"Command Center";27;1
"Building";"SupplyDepot";NA;27;0
"Building";"Starport";NA;26;0
"Unit";"SCV";"Command Center";28;1
"Unit";"SCV";"Command Center";33;1
"Unit";"Hellion";"Factory";29;2
"Unit";"Hellion";"Factory";31;2
"Unit";"SCV";"Command Center";34;1
"Building";"BarracksTechLab";NA;34;0
"Building";"SupplyDepot";NA;34;0
"Unit";"SCV";"Command Center";36;1
"Unit";"SCV";"Command Center";40;1
"Unit";"Hellion";"Factory";36;2
"Unit";"Hellion";"Factory";38;2
"Unit";"SCV";"Command Center";41;1
"Unit";"SCV";"Command Center";42;1
"Unit";"SCV";"Command Center";47;1
"Unit";"SCV";"Command Center";48;1
"Building";"SupplyDepot";NA;48;0
"Unit";"SCV";"Command Center";50;1
"Unit";"SCV";"Command Center";50;1
"Unit";"Marine";"Barracks";50;1
"Unit";"Marine";"Barracks";51;1
"Unit";"SCV";"Command Center";51;1
"Unit";"SCV";"Command Center";52;1
"Unit";"Raven";"Starport";49;2
"Unit";"SCV";"Command Center";57;1
"Unit";"Marine";"Barracks";57;1
"Unit";"SCV";"Command Center";57;1
"Unit";"Marine";"Barracks";57;1
"Unit";"SCV";"Command Center";59;1
"Building";"CommandCenter";NA;43;0
"Unit";"SCV";"Command Center";61;1
"Unit";"SCV";"Command Center";63;1
"Unit";"Marine";"Barracks";63;1
"Unit";"Marine";"Barracks";63;1
"Unit";"SCV";"Command Center";64;1
"Building";"Refinery";NA;63;0
"Building";"Refinery";NA;63;0
"Building";"EngineeringBay";NA;63;0
"Building";"EngineeringBay";NA;63;0
"Building";"SupplyDepot";NA;64;0
"Unit";"SCV";"Command Center";65;1
"Unit";"SCV";"Command Center";68;1
"Unit";"Raven";"Starport";59;2
"Unit";"SCV";"Command Center";69;1
"Unit";"SCV";"Command Center";70;1
"Unit";"SCV";"Command Center";71;1
"Unit";"Marine";"Barracks";70;1
"Building";"Barracks";NA;64;0
"Unit";"SCV";"Command Center";73;1
"Building";"Barracks";NA;64;0
"Unit";"SCV";"Command Center";74;1
"Building";"FactoryReactor";NA;69;0
"Unit";"SCV";"Command Center";75;1
"Unit";"SCV";"Command Center";77;1
"Unit";"SCV";"Command Center";78;1
"Building";"Barracks";NA;69;0
"Unit";"SCV";"Command Center";80;1
"Building";"Barracks";NA;69;0
"Unit";"Marine";"Barracks";78;1
"Building";"SupplyDepot";NA;78;0
"Building";"SupplyDepot";NA;78;0
"Unit";"SCV";"Command Center";81;1
"Unit";"SCV";"Command Center";81;1
"Building";"SupplyDepot";NA;80;0
"Building";"BarracksReactor";NA;78;0
"Building";"BarracksReactor";NA;78;0
"Unit";"SCV";"Command Center";85;1
"Building";"StarportReactor";NA;79;0
"Unit";"SCV";"Command Center";86;1
"Unit";"Marine";"Barracks";85;1
"Unit";"Marine";"Barracks";85;1
"Unit";"Marine";"Barracks";86;1
"Unit";"Marine";"Barracks";86;1
"Unit";"Marine";"Barracks";86;1
"Unit";"Marine";"Barracks";86;1
"Unit";"Marine";"Barracks";86;1
"Unit";"Marine";"Barracks";86;1
"Building";"SupplyDepot";NA;86;0
"Unit";"SCV";"Command Center";90;1
"Unit";"SCV";"Command Center";90;1
"Building";"Bunker";NA;86;0
"Unit";"Marine";"Barracks";90;1
"Unit";"Marine";"Barracks";90;1
"Unit";"SCV";"Command Center";96;1
"Unit";"Marine";"Barracks";93;1
"Unit";"Marine";"Barracks";93;1
"Unit";"Marine";"Barracks";93;1
"Unit";"Marine";"Barracks";93;1
"Unit";"SCV";"Command Center";96;1
"Unit";"Medivac";"Starport";90;2
"Unit";"Medivac";"Starport";90;2
"Building";"Barracks";NA;86;0
"Building";"Factory";NA;86;0
"Building";"Barracks";NA;86;0
"Unit";"Marine";"Barracks";100;1
"Unit";"Marine";"Barracks";100;1
"Unit";"Marine";"Barracks";100;1
"Unit";"Marine";"Barracks";100;1
"Unit";"Marine";"Barracks";100;1
"Unit";"SCV";"Command Center";106;1
"Unit";"SCV";"Command Center";106;1
"Unit";"SCV";"Command Center";106;1
"Building";"Refinery";NA;100;0
"Unit";"Marine";"Barracks";102;1
"Building";"Refinery";NA;100;0
"Upgrade";"TerranInfantryWeaponsLevel1";"EngineeringBay";80;0
"Upgrade";"TerranInfantryArmorsLevel1";"EngineeringBay";80;0
"Building";"SupplyDepot";NA;106;0
"Building";"SupplyDepot";NA;106;0
"Unit";"Marine";"Barracks";110;1
"Unit";"Marine";"Barracks";110;1
"Building";"BarracksTechLab";NA;110;0
"Building";"FactoryTechLab";NA;110;0
"Building";"BarracksTechLab";NA;110;0
"Unit";"Marine";"Barracks";119;1
"Upgrade";"Stimpack";"TechLab";84;0
"Unit";"Marine";"Barracks";119;1
"Unit";"Marine";"Barracks";119;1
"Unit";"Marine";"Barracks";119;1
"Unit";"Marine";"Barracks";119;1
"Building";"SupplyDepot";NA;119;0
"Building";"SupplyDepot";NA;119;0
"Unit";"SCV";"Command Center";121;1
"Unit";"SCV";"Command Center";121;1
"Unit";"Marine";"Barracks";119;1
"Unit";"Marine";"Barracks";119;1
"Unit";"SCV";"Command Center";121;1
"Unit";"SCV";"Command Center";126;1
"Unit";"Marine";"Barracks";121;1
"Unit";"Marine";"Barracks";121;1
"Unit";"Marine";"Barracks";121;1
"Unit";"Marine";"Barracks";121;1
"Unit";"Medivac";"Starport";119;2
"Unit";"Medivac";"Starport";119;2
"Unit";"SCV";"Command Center";131;1
"Unit";"SCV";"Command Center";131;1
"Unit";"Marine";"Barracks";131;1
"Unit";"Marine";"Barracks";131;1
"Building";"Armory";NA;119;0
"Unit";"Marine";"Barracks";131;1
"Unit";"Marine";"Barracks";131;1
"Unit";"Marine";"Barracks";131;1
"Unit";"Marauder";"Barracks";131;2
