"Type";"UnitName";"OnBuilding";"TotalSupply";"Supply"
"Unit";"SCV";"Command Center";12;1
"Unit";"SCV";"Command Center";12;1
"Unit";"SCV";"Command Center";13;1
"Building";"SupplyDepot";NA;13;0
"Unit";"SCV";"Command Center";15;1
"Unit";"SCV";"Command Center";15;1
"Building";"Refinery";NA;15;0
"Unit";"SCV";"Command Center";16;1
"Building";"Barracks";NA;15;0
"Unit";"SCV";"Command Center";17;1
"Unit";"Reaper";"Barracks";19;1
"Unit";"SCV";"Command Center";19;1
"Building";"SupplyDepot";NA;19;0
"Unit";"Marine";"Barracks";19;1
"Unit";"SCV";"Command Center";20;1
"Unit";"SCV";"Command Center";22;1
"Unit";"SCV";"Command Center";23;1
"Building";"CommandCenter";NA;19;0
"Unit";"SCV";"Command Center";24;1
"Building";"Factory";NA;21;0
"Building";"BarracksReactor";NA;23;0
"Unit";"SCV";"Command Center";26;1
"Building";"Refinery";NA;25;0
"Unit";"SCV";"Command Center";27;1
"Unit";"Hellion";"Factory";26;2
"Unit";"Hellion";"Factory";27;2
"Unit";"SCV";"Command Center";27;1
"Unit";"SCV";"Command Center";28;1
"Unit";"SCV";"Command Center";32;1
"Unit";"SCV";"Command Center";33;1
"Unit";"Hellion";"Factory";33;2
"Unit";"SCV";"Command Center";34;1
"Unit";"Hellion";"Factory";34;2
"Building";"Starport";NA;28;0
"Unit";"SCV";"Command Center";36;1
"Building";"BarracksTechLab";NA;34;0
"Building";"CommandCenter";NA;26;0
"Unit";"SCV";"Command Center";42;1
"Unit";"SCV";"Command Center";42;1
"Unit";"SCV";"Command Center";42;1
"Unit";"SCV";"Command Center";44;1
"Unit";"Marine";"Barracks";44;1
"Unit";"SCV";"Command Center";44;1
"Unit";"SCV";"Command Center";45;1
"Building";"Barracks";NA;42;0
"Building";"Barracks";NA;42;0
"Building";"FactoryReactor";NA;42;0
"Unit";"SCV";"Command Center";47;1
"Building";"SupplyDepot";NA;46;0
"Unit";"SCV";"Command Center";47;1
"Unit";"SCV";"Command Center";49;1
"Building";"EngineeringBay";NA;46;0
"Building";"EngineeringBay";NA;47;0
"Unit";"SCV";"Command Center";52;1
"Unit";"SCV";"Command Center";52;1
"Building";"FactoryTechLab";NA;52;0
"Unit";"Marine";"Barracks";52;1
"Unit";"Marine";"Barracks";52;1
"Unit";"Marine";"Barracks";52;1
"Unit";"Marine";"Barracks";52;1
"Building";"StarportReactor";NA;49;0
"Unit";"SCV";"Command Center";52;1
"Unit";"SCV";"Command Center";54;1
"Building";"Refinery";NA;52;0
"Unit";"Marine";"Barracks";54;1
"Building";"Refinery";NA;53;0
"Building";"SupplyDepot";NA;54;0
"Building";"SupplyDepot";NA;54;0
"Building";"SupplyDepot";NA;57;0
"Unit";"SCV";"Command Center";61;1
"Unit";"SCV";"Command Center";61;1
"Unit";"Marine";"Barracks";61;1
"Unit";"Marine";"Barracks";61;1
"Unit";"Marine";"Barracks";61;1
"Unit";"Marine";"Barracks";61;1
"Unit";"Marine";"Barracks";61;1
"Unit";"SCV";"Command Center";61;1
"Upgrade";"Stimpack";"TechLab";46;0
"Unit";"Medivac";"Starport";61;2
"Unit";"Medivac";"Starport";61;2
"Unit";"SCV";"Command Center";69;1
"Unit";"SCV";"Command Center";69;1
"Unit";"SCV";"Command Center";69;1
"Building";"SupplyDepot";NA;63;0
"Building";"SupplyDepot";NA;63;0
"Unit";"Marine";"Barracks";69;1
"Unit";"Marine";"Barracks";69;1
"Unit";"Marine";"Barracks";69;1
"Unit";"Marine";"Barracks";69;1
"Unit";"Marine";"Barracks";69;1
"Unit";"SCV";"Command Center";76;1
"Unit";"SCV";"Command Center";76;1
"Unit";"SCV";"Command Center";76;1
"Building";"SupplyDepot";NA;69;0
"Unit";"SCV";"Command Center";81;1
"Unit";"SCV";"Command Center";82;1
"Unit";"SCV";"Command Center";83;1
"Unit";"Marine";"Barracks";81;1
"Unit";"Marine";"Barracks";81;1
"Unit";"Marine";"Barracks";81;1
"Unit";"Marine";"Barracks";81;1
"Unit";"Marine";"Barracks";84;1
"Building";"Armory";NA;69;0
"Unit";"SCV";"Command Center";91;1
"Unit";"SCV";"Command Center";91;1
"Unit";"SCV";"Command Center";91;1
"Unit";"Marine";"Barracks";90;1
"Unit";"Marine";"Barracks";91;1
"Unit";"Marine";"Barracks";91;1
"Unit";"Marine";"Barracks";91;1
"Building";"Barracks";NA;76;0
"Upgrade";"TerranInfantryWeaponsLevel1";"EngineeringBay";61;0
"Upgrade";"TerranInfantryArmorsLevel1";"EngineeringBay";61;0
"Unit";"Marine";"Barracks";92;1
"Unit";"SCV";"Command Center";92;1
"Building";"Barracks";NA;81;0
"Unit";"SCV";"Command Center";95;1
"Unit";"SCV";"Command Center";95;1
"Building";"SupplyDepot";NA;92;0
"Building";"SupplyDepot";NA;92;0
"Building";"SupplyDepot";NA;92;0
"Unit";"SCV";"Command Center";100;1
"Unit";"Marine";"Barracks";99;1
"Unit";"Marine";"Barracks";99;1
"Unit";"Marine";"Barracks";99;1
"Unit";"Marine";"Barracks";99;1
"Unit";"SCV";"Command Center";103;1
"Unit";"SCV";"Command Center";103;1
"Building";"Refinery";NA;99;0
"Building";"Refinery";NA;99;0
"Unit";"SCV";"Command Center";103;1
"Building";"Factory";NA;92;0
"Unit";"Marine";"Barracks";110;1
"Unit";"Marine";"Barracks";110;1
"Unit";"Marine";"Barracks";110;1
"Unit";"Marine";"Barracks";110;1
"Unit";"Marine";"Barracks";111;1
"Building";"FactoryTechLab";NA;111;0
"Building";"BarracksReactor";NA;110;0
"Building";"BarracksReactor";NA;110;0
"Unit";"Marine";"Barracks";115;1
"Unit";"Marine";"Barracks";115;1
"Unit";"Marine";"Barracks";115;1
"Unit";"Marine";"Barracks";115;1
"Unit";"Medivac";"Starport";111;2
"Unit";"Medivac";"Starport";111;2
"Unit";"Marine";"Barracks";115;1
"Unit";"SCV";"Command Center";117;1
"Unit";"SCV";"Command Center";117;1
"Unit";"SCV";"Command Center";117;1
"Unit";"Marine";"Barracks";116;1
"Unit";"Marine";"Barracks";117;1
"Unit";"Marine";"Barracks";117;1
"Unit";"Marine";"Barracks";117;1
"Unit";"Marine";"Barracks";117;1
"Unit";"Marine";"Barracks";117;1
"Unit";"Marine";"Barracks";125;1
"Unit";"Marine";"Barracks";125;1
"Unit";"Marine";"Barracks";125;1
"Unit";"SCV";"Command Center";133;1
"Unit";"SCV";"Command Center";133;1
"Unit";"Marine";"Barracks";128;1
"Unit";"Marine";"Barracks";129;1
"Building";"Barracks";NA;116;0
"Building";"Barracks";NA;116;0
"Building";"Barracks";NA;116;0
"Unit";"Medivac";"Starport";125;2
"Unit";"Marine";"Barracks";134;1
"Unit";"Marine";"Barracks";134;1
"Unit";"Marine";"Barracks";134;1
"Unit";"Marine";"Barracks";134;1
"Unit";"Medivac";"Starport";125;2
"Unit";"Marine";"Barracks";134;1
"Unit";"Marauder";"Barracks";137;2
"Unit";"Marine";"Barracks";141;1
"Unit";"Marine";"Barracks";141;1
"Unit";"Marine";"Barracks";141;1
"Building";"BarracksTechLab";NA;155;0
"Building";"BarracksTechLab";NA;155;0
"Building";"BarracksTechLab";NA;155;0
"Upgrade";"TerranInfantryWeaponsLevel2";"EngineeringBay";115;0
"Building";"SupplyDepot";NA;155;0
"Building";"SupplyDepot";NA;155;0
"Unit";"Marine";"Barracks";155;1
"Unit";"Marine";"Barracks";155;1
"Unit";"Marine";"Barracks";155;1
"Unit";"Marine";"Barracks";155;1
"Unit";"Marine";"Barracks";155;1
"Unit";"Marine";"Barracks";155;1
"Unit";"Marine";"Barracks";155;1
"Building";"SupplyDepot";NA;155;0
"Building";"SupplyDepot";NA;155;0
"Unit";"Marine";"Barracks";155;1
"Building";"SupplyDepot";NA;155;0
"Unit";"Marine";"Barracks";155;1
"Building";"MissileTurret";NA;155;0
"Building";"CommandCenter";NA;117;0
"Building";"MissileTurret";NA;155;0
"Building";"MissileTurret";NA;155;0
"Unit";"Medivac";"Starport";155;2
"Unit";"Medivac";"Starport";155;2
"Upgrade";"TerranVehicleAndShipArmorsLevel1";"Armory";125;0
"Building";"MissileTurret";NA;163;0
"Building";"MissileTurret";NA;164;0
"Unit";"Marine";"Barracks";164;1
"Unit";"Marine";"Barracks";164;1
"Unit";"Marine";"Barracks";164;1
"Unit";"Marine";"Barracks";164;1
"Unit";"Marine";"Barracks";164;1
"Unit";"Marine";"Barracks";164;1
"Unit";"Marine";"Barracks";168;1
"Unit";"Marine";"Barracks";168;1
"Unit";"Marauder";"Barracks";168;2
"Upgrade";"TerranInfantryArmorsLevel2";"EngineeringBay";133;0
"Building";"MissileTurret";NA;171;0
"Unit";"Marine";"Barracks";178;1
"Unit";"Marine";"Barracks";178;1
"Building";"MissileTurret";NA;178;0
"Unit";"Marauder";"Barracks";178;2
"Unit";"Marauder";"Barracks";178;2
"Unit";"Marine";"Barracks";178;1
"Unit";"Marine";"Barracks";178;1
"Unit";"Marine";"Barracks";178;1
"Unit";"Marine";"Barracks";178;1
"Unit";"Marine";"Barracks";178;1
"Unit";"Marine";"Barracks";180;1
"Unit";"Marine";"Barracks";180;1
"Unit";"Marine";"Barracks";180;1
"Unit";"Marine";"Barracks";184;1
"Unit";"Marine";"Barracks";184;1
"Unit";"Marine";"Barracks";184;1
"Unit";"Marauder";"Barracks";184;2
"Unit";"Marine";"Barracks";189;1
"Unit";"Marine";"Barracks";189;1
"Unit";"Marine";"Barracks";189;1
"Unit";"Marine";"Barracks";189;1
"Unit";"Marine";"Barracks";192;1
"Unit";"Marine";"Barracks";192;1
"Unit";"Marine";"Barracks";192;1
"Unit";"Marine";"Barracks";197;1
"Unit";"Marine";"Barracks";197;1
"Unit";"Marauder";"Barracks";197;2
"Unit";"Marine";"Barracks";201;1
"Unit";"Marine";"Barracks";201;1
"Unit";"Marauder";"Barracks";201;2
"Unit";"Marine";"Barracks";204;1
"Unit";"Marine";"Barracks";204;1
"Unit";"Marauder";"Barracks";204;2
"Unit";"Marine";"Barracks";204;1
"Unit";"Marine";"Barracks";204;1
"Unit";"Marine";"Barracks";206;1
"Unit";"Marine";"Barracks";212;1
"Unit";"Marine";"Barracks";212;1
"Unit";"Marine";"Barracks";213;1
"Unit";"Marauder";"Barracks";212;2
"Unit";"Marine";"Barracks";219;1
"Unit";"Marine";"Barracks";221;1
"Unit";"Marine";"Barracks";221;1
