"Type";"UnitName";"OnBuilding";"TotalSupply";"Supply"
"Unit";"SCV";"Command Center";12;1
"Unit";"SCV";"Command Center";12;1
"Unit";"SCV";"Command Center";13;1
"Building";"SupplyDepot";NA;13;0
"Building";"Refinery";NA;14;0
"Unit";"SCV";"Command Center";15;1
"Unit";"SCV";"Command Center";15;1
"Unit";"SCV";"Command Center";16;1
"Unit";"SCV";"Command Center";17;1
"Building";"Barracks";NA;15;0
"Unit";"Reaper";"Barracks";19;1
"Unit";"SCV";"Command Center";19;1
"Unit";"SCV";"Command Center";20;1
"Building";"SupplyDepot";NA;21;0
"Unit";"SCV";"Command Center";21;1
"Building";"Factory";NA;19;0
"Building";"Refinery";NA;21;0
"Building";"BarracksReactor";NA;20;0
"Unit";"SCV";"Command Center";22;1
"Building";"CommandCenter";NA;19;0
"Unit";"SCV";"Command Center";23;1
"Unit";"Hellion";"Factory";24;2
"Unit";"Hellion";"Factory";24;2
"Building";"Starport";NA;23;0
"Unit";"SCV";"Command Center";29;1
"Unit";"Hellion";"Factory";25;2
"Unit";"Hellion";"Factory";27;2
"Unit";"SCV";"Command Center";29;1
"Unit";"SCV";"Command Center";30;1
"Building";"SupplyDepot";NA;30;0
"Unit";"SCV";"Command Center";35;1
"Unit";"Hellion";"Factory";34;2
"Unit";"SCV";"Command Center";36;1
"Unit";"Hellion";"Factory";34;2
"Building";"BarracksTechLab";NA;36;0
"Unit";"Liberator";"Starport";29;3
"Unit";"SCV";"Command Center";36;1
"Unit";"SCV";"Command Center";42;1
"Unit";"SCV";"Command Center";47;1
"Unit";"SCV";"Command Center";47;1
"Unit";"Hellion";"Factory";47;2
"Unit";"Hellion";"Factory";47;2
"Unit";"SCV";"Command Center";53;1
"Unit";"SCV";"Command Center";53;1
"Unit";"Hellion";"Factory";49;2
"Unit";"Hellion";"Factory";51;2
"Unit";"Liberator";"Starport";47;3
"Unit";"SCV";"Command Center";54;1
"Unit";"SCV";"Command Center";55;1
"Unit";"SCV";"Command Center";62;1
"Unit";"SCV";"Command Center";63;1
"Unit";"Marine";"Barracks";59;1
"Building";"FactoryTechLab";NA;64;0
"Unit";"SCV";"Command Center";67;1
"Unit";"SCV";"Command Center";67;1
"Unit";"Marine";"Barracks";67;1
"Building";"SupplyDepot";NA;67;0
"Building";"SupplyDepot";NA;67;0
"Building";"EngineeringBay";NA;67;0
"Building";"Refinery";NA;67;0
"Building";"Barracks";NA;64;0
"Building";"Barracks";NA;64;0
"Building";"Barracks";NA;64;0
"Building";"CommandCenter";NA;53;0
"Building";"Barracks";NA;64;0
"Unit";"SCV";"Command Center";70;1
"Unit";"SCV";"Command Center";70;1
"Building";"StarportReactor";NA;67;0
"Unit";"Marine";"Barracks";70;1
"Unit";"SCV";"Command Center";70;1
"Unit";"SCV";"Command Center";70;1
"Building";"Refinery";NA;72;0
"Unit";"SCV";"Command Center";73;1
"Unit";"SCV";"Command Center";73;1
"Unit";"Marine";"Barracks";75;1
"Unit";"Marine";"Barracks";75;1
"Unit";"Marine";"Barracks";75;1
"Unit";"SCV";"Command Center";75;1
"Unit";"SCV";"Command Center";75;1
"Unit";"SCV";"Command Center";80;1
"Unit";"SCV";"Command Center";80;1
"Unit";"Marine";"Barracks";77;1
"Unit";"Marine";"Barracks";80;1
"Unit";"Marine";"Barracks";80;1
"Unit";"Marine";"Barracks";80;1
"Unit";"Marine";"Barracks";82;1
"Building";"BarracksReactor";NA;75;0
"Building";"BarracksReactor";NA;75;0
"Building";"StarportReactor";NA;75;0
"Unit";"SCV";"Command Center";82;1
"Unit";"SCV";"Command Center";82;1
"Upgrade";"Stimpack";"TechLab";69;0
"Unit";"Marine";"Barracks";84;1
"Unit";"Marine";"Barracks";85;1
"Unit";"Marine";"Barracks";86;1
"Unit";"Marine";"Barracks";87;1
"Unit";"Marine";"Barracks";88;1
"Unit";"Marine";"Barracks";89;1
"Unit";"Marine";"Barracks";89;1
"Unit";"Marine";"Barracks";89;1
"Unit";"Marine";"Barracks";89;1
"Unit";"SCV";"Command Center";96;1
"Unit";"SCV";"Command Center";96;1
"Building";"SupplyDepot";NA;96;0
"Unit";"Marine";"Barracks";96;1
"Unit";"Marine";"Barracks";96;1
"Unit";"Marine";"Barracks";96;1
"Unit";"Marine";"Barracks";96;1
"Building";"SupplyDepot";NA;96;0
"Building";"SupplyDepot";NA;96;0
"Building";"SupplyDepot";NA;100;0
"Unit";"SCV";"Command Center";102;1
"Unit";"Medivac";"Starport";96;2
"Unit";"SCV";"Command Center";106;1
"Unit";"SCV";"Command Center";106;1
"Building";"EngineeringBay";NA;100;0
"Unit";"Marine";"Barracks";102;1
"Unit";"Marine";"Barracks";102;1
"Building";"Armory";NA;91;0
"Unit";"Marine";"Barracks";106;1
"Unit";"Marine";"Barracks";106;1
"Unit";"Marine";"Barracks";106;1
"Unit";"Marine";"Barracks";106;1
"Upgrade";"TerranInfantryWeaponsLevel1";"EngineeringBay";78;0
"Unit";"Marine";"Barracks";106;1
"Unit";"Marine";"Barracks";106;1
"Unit";"Marine";"Barracks";106;1
"Unit";"SCV";"Command Center";106;1
"Unit";"SCV";"Command Center";109;1
"Unit";"SCV";"Command Center";109;1
"Building";"SupplyDepot";NA;106;0
"Unit";"Medivac";"Starport";102;2
"Unit";"Marine";"Barracks";111;1
"Unit";"Marine";"Barracks";111;1
"Unit";"SCV";"Command Center";120;1
"Unit";"Marine";"Barracks";113;1
"Unit";"Marine";"Barracks";113;1
"Unit";"Marine";"Barracks";115;1
"Unit";"Marine";"Barracks";115;1
"Unit";"SCV";"Command Center";123;1
"Unit";"SCV";"Command Center";123;1
"Unit";"Marine";"Barracks";117;1
"Unit";"Marine";"Barracks";118;1
"Unit";"Marine";"Barracks";121;1
"Building";"Refinery";NA;123;0
"Unit";"SCV";"Command Center";134;1
"Unit";"SCV";"Command Center";134;1
"Building";"Refinery";NA;125;0
"Unit";"Marine";"Barracks";125;1
"Unit";"Marine";"Barracks";125;1
"Unit";"Marine";"Barracks";128;1
"Unit";"Marine";"Barracks";128;1
"Unit";"Marine";"Barracks";130;1
"Building";"SupplyDepot";NA;125;0
"Unit";"Marine";"Barracks";137;1
"Building";"SupplyDepot";NA;136;0
"Building";"SupplyDepot";NA;137;0
"Unit";"Marine";"Barracks";144;1
"Unit";"Marine";"Barracks";144;1
"Unit";"Marine";"Barracks";144;1
"Unit";"Medivac";"Starport";144;2
"Unit";"Medivac";"Starport";145;2
"Unit";"Marine";"Barracks";150;1
"Unit";"Marine";"Barracks";150;1
"Unit";"Marauder";"Barracks";150;2
"Unit";"Marine";"Barracks";152;1
"Unit";"Marine";"Barracks";152;1
"Unit";"Marine";"Barracks";152;1
"Unit";"Marine";"Barracks";152;1
"Unit";"Marine";"Barracks";152;1
"Unit";"Marine";"Barracks";152;1
