"type";"unit_name";"on_building";"total_supply";"supply"
"Building";"Refinery";NA;14;0
"Building";"Barracks";NA;15;0
"Unit";"Reaper";"Barracks";19;1
"Building";"Refinery";NA;21;0
"Building";"Factory";NA;19;0
"Building";"BarracksReactor";NA;21;0
"Unit";"Marine";"Barracks";24;1
"Unit";"Marine";"Barracks";24;1
"Unit";"Hellion";"Factory";24;2
"Building";"Starport";NA;24;0
"Building";"BarracksTechLab";NA;30;0
"Unit";"Hellion";"Factory";31;2
"Unit";"Hellion";"Factory";31;2
"Building";"CommandCenter";NA;24;0
"Unit";"Hellion";"Factory";32;2
"Unit";"Hellion";"Factory";34;2
"Building";"BarracksTechLab";NA;40;0
"Unit";"Banshee";"Starport";36;3
"Unit";"Marauder";"Barracks";51;2
"Building";"FactoryReactor";NA;49;0
"Building";"Barracks";NA;49;0
"Building";"CommandCenter";NA;44;0
"Building";"EngineeringBay";NA;53;0
"Building";"Barracks";NA;49;0
"Building";"EngineeringBay";NA;53;0
"Unit";"Marine";"Barracks";53;1
"Building";"StarportReactor";NA;51;0
"Unit";"Marine";"Barracks";61;1
"Unit";"Marine";"Barracks";61;1
"Building";"FactoryReactor";NA;58;0
"Unit";"Marine";"Barracks";62;1
"Unit";"Marine";"Barracks";62;1
"Unit";"Marine";"Barracks";62;1
"Unit";"Marine";"Barracks";67;1
"Unit";"Marine";"Barracks";67;1
"Unit";"Marine";"Barracks";67;1
"Unit";"Marine";"Barracks";71;1
"Unit";"Marine";"Barracks";71;1
"Upgrade";"Stimpack";"TechLab";53;0
"Unit";"Medivac";"Starport";69;2
"Unit";"Medivac";"Starport";70;2
"Unit";"Marine";"Barracks";72;1
"Unit";"Marine";"Barracks";73;1
"Building";"Refinery";NA;74;0
"Building";"Refinery";NA;75;0
"Unit";"Marine";"Barracks";85;1
"Unit";"Marine";"Barracks";85;1
"Unit";"Marine";"Barracks";85;1
"Unit";"Marine";"Barracks";85;1
"Unit";"Marine";"Barracks";85;1
"Building";"Barracks";NA;71;0
"Unit";"Hellion";"Factory";85;2
"Unit";"Hellion";"Factory";85;2
"Building";"Barracks";NA;72;0
"Building";"Factory";NA;74;0
"Building";"Armory";NA;75;0
"Unit";"Marine";"Barracks";85;1
"Unit";"Hellion";"Factory";96;2
"Unit";"Hellion";"Factory";96;2
"Upgrade";"TerranInfantryArmorsLevel1";"EngineeringBay";71;0
"Upgrade";"TerranInfantryWeaponsLevel1";"EngineeringBay";71;0
"Unit";"Marine";"Barracks";100;1
"Unit";"Hellion";"Factory";100;2
"Building";"BarracksReactor";NA;96;0
"Building";"BarracksReactor";NA;96;0
"Unit";"Medivac";"Starport";100;2
"Unit";"Medivac";"Starport";100;2
"Unit";"Hellion";"Factory";105;2
"Unit";"Hellion";"Factory";105;2
"Unit";"Marine";"Barracks";119;1
"Unit";"Marine";"Barracks";119;1
"Unit";"Marine";"Barracks";119;1
"Unit";"Marine";"Barracks";119;1
"Unit";"Marine";"Barracks";119;1
"Unit";"Marine";"Barracks";119;1
"Unit";"Marine";"Barracks";119;1
"Unit";"Marine";"Barracks";119;1
"Unit";"Marine";"Barracks";119;1
"Unit";"Hellion";"Factory";119;2
"Unit";"Hellion";"Factory";119;2
"Unit";"Hellion";"Factory";119;2
"Unit";"Marine";"Barracks";119;1
"Unit";"Marine";"Barracks";120;1
"Unit";"Marine";"Barracks";120;1
"Unit";"Marine";"Barracks";122;1
"Unit";"Marine";"Barracks";122;1
"Unit";"Medivac";"Starport";119;2
"Unit";"Medivac";"Starport";119;2
"Unit";"Marine";"Barracks";132;1
"Unit";"Marine";"Barracks";132;1
"Unit";"Marine";"Barracks";132;1
"Unit";"Marine";"Barracks";132;1
"Unit";"Hellion";"Factory";132;2
"Unit";"Hellion";"Factory";132;2
"Unit";"Marine";"Barracks";134;1
"Unit";"Marine";"Barracks";135;1
"Unit";"Marine";"Barracks";135;1
"Unit";"Marine";"Barracks";137;1
"Unit";"Marine";"Barracks";137;1
"Unit";"Marine";"Barracks";143;1
"Unit";"Marine";"Barracks";143;1
"Unit";"Marine";"Barracks";146;1
"Unit";"Marine";"Barracks";151;1
"Unit";"Medivac";"Starport";139;2
"Unit";"Hellion";"Factory";151;2
"Unit";"Hellion";"Factory";151;2
"Unit";"Marine";"Barracks";151;1
"Unit";"Marine";"Barracks";152;1
"Unit";"Marine";"Barracks";156;1
"Unit";"Marine";"Barracks";156;1
"Unit";"Thor";"Factory";134;6
"Unit";"Marine";"Barracks";159;1
"Unit";"Marine";"Barracks";159;1
"Unit";"Marine";"Barracks";159;1
"Unit";"Marine";"Barracks";159;1
"Unit";"Marine";"Barracks";159;1
"Unit";"Marine";"Barracks";166;1
"Unit";"Marine";"Barracks";170;1
"Unit";"Marine";"Barracks";170;1
"Unit";"Marine";"Barracks";170;1
"Unit";"Medivac";"Starport";159;2
"Unit";"Marine";"Barracks";176;1
"Unit";"Marine";"Barracks";176;1
"Unit";"Marine";"Barracks";178;1
"Unit";"Marine";"Barracks";178;1
"Unit";"Hellion";"Factory";170;2
"Unit";"Marine";"Barracks";180;1
"Unit";"Medivac";"Starport";170;2
"Unit";"Marine";"Barracks";181;1
"Upgrade";"TerranInfantryWeaponsLevel2";"EngineeringBay";119;0
"Upgrade";"TerranInfantryArmorsLevel2";"EngineeringBay";119;0
"Unit";"Marine";"Barracks";182;1
"Unit";"Marine";"Barracks";183;1
"Unit";"Marine";"Barracks";183;1
"Unit";"Marine";"Barracks";193;1
"Unit";"Marine";"Barracks";193;1
"Unit";"Marine";"Barracks";193;1
"Unit";"Marine";"Barracks";193;1
"Unit";"Marine";"Barracks";193;1
"Unit";"Marine";"Barracks";196;1
"Unit";"Marine";"Barracks";197;1
"Unit";"Marine";"Barracks";198;1
"Unit";"Marine";"Barracks";198;1
"Unit";"Hellion";"Factory";197;2
"Unit";"Hellion";"Factory";197;2
"Unit";"Hellion";"Factory";197;2
"Unit";"Marine";"Barracks";200;1
"Unit";"Marine";"Barracks";201;1
"Unit";"Marine";"Barracks";201;1
"Unit";"Marine";"Barracks";203;1
"Upgrade";"TerranVehicleWeaponsLevel1";"Armory";156;0
"Unit";"Marine";"Barracks";204;1
