"Type";"UnitName";"OnBuilding";"TotalSupply";"Supply"
"Unit";"SCV";"Command Center";12;1
"Unit";"SCV";"Command Center";12;1
"Unit";"SCV";"Command Center";13;1
"Building";"SupplyDepot";NA;13;0
"Unit";"SCV";"Command Center";15;1
"Unit";"SCV";"Command Center";15;1
"Building";"Refinery";NA;15;0
"Unit";"SCV";"Command Center";16;1
"Building";"Barracks";NA;15;0
"Unit";"SCV";"Command Center";17;1
"Unit";"Reaper";"Barracks";19;1
"Unit";"SCV";"Command Center";19;1
"Unit";"Marine";"Barracks";19;1
"Building";"SupplyDepot";NA;19;0
"Unit";"SCV";"Command Center";21;1
"Unit";"SCV";"Command Center";22;1
"Unit";"SCV";"Command Center";23;1
"Building";"Factory";NA;21;0
"Building";"CommandCenter";NA;19;0
"Unit";"SCV";"Command Center";25;1
"Building";"BarracksReactor";NA;23;0
"Unit";"SCV";"Command Center";26;1
"Building";"Refinery";NA;25;0
"Unit";"Hellion";"Factory";26;2
"Unit";"SCV";"Command Center";27;1
"Unit";"SCV";"Command Center";27;1
"Building";"BarracksTechLab";NA;27;0
"Unit";"Hellion";"Factory";27;2
"Building";"Starport";NA;26;0
"Building";"CommandCenter";NA;24;0
"Unit";"SCV";"Command Center";33;1
"Unit";"SCV";"Command Center";33;1
"Unit";"Hellion";"Factory";29;2
"Unit";"Hellion";"Factory";31;2
"Unit";"SCV";"Command Center";35;1
"Unit";"SCV";"Command Center";35;1
"Unit";"SCV";"Command Center";41;1
"Unit";"SCV";"Command Center";41;1
"Building";"BarracksTechLab";NA;41;0
"Unit";"SCV";"Command Center";43;1
"Unit";"SCV";"Command Center";43;1
"Unit";"SCV";"Command Center";43;1
"Unit";"Banshee";"Starport";39;3
"Building";"FactoryReactor";NA;41;0
"Unit";"SCV";"Command Center";43;1
"Unit";"SCV";"Command Center";44;1
"Unit";"SCV";"Command Center";45;1
"Unit";"Marine";"Barracks";43;1
"Building";"Barracks";NA;43;0
"Building";"Barracks";NA;43;0
"Building";"SupplyDepot";NA;49;0
"Unit";"Marine";"Barracks";53;1
"Unit";"SCV";"Command Center";53;1
"Unit";"SCV";"Command Center";53;1
"Unit";"SCV";"Command Center";53;1
"Building";"EngineeringBay";NA;52;0
"Building";"EngineeringBay";NA;53;0
"Unit";"SCV";"Command Center";57;1
"Building";"Refinery";NA;53;0
"Unit";"SCV";"Command Center";57;1
"Building";"StarportReactor";NA;53;0
"Building";"Refinery";NA;53;0
"Unit";"Marine";"Barracks";54;1
"Unit";"Marine";"Barracks";54;1
"Unit";"Marine";"Barracks";54;1
"Unit";"Marine";"Barracks";57;1
"Building";"SupplyDepot";NA;57;0
"Unit";"Marine";"Barracks";57;1
"Unit";"SCV";"Command Center";58;1
"Unit";"SCV";"Command Center";58;1
"Unit";"SCV";"Command Center";58;1
"Unit";"SCV";"Command Center";67;1
"Unit";"SCV";"Command Center";67;1
"Building";"SupplyDepot";NA;67;0
"Unit";"Marine";"Barracks";67;1
"Unit";"Marine";"Barracks";67;1
"Unit";"Marine";"Barracks";67;1
"Unit";"Medivac";"Starport";67;2
"Unit";"Medivac";"Starport";67;2
"Building";"SupplyDepot";NA;67;0
"Unit";"SCV";"Command Center";69;1
"Unit";"SCV";"Command Center";69;1
"Building";"SupplyDepot";NA;67;0
"Unit";"Marine";"Barracks";69;1
"Unit";"Marine";"Barracks";69;1
"Building";"SupplyDepot";NA;69;0
"Unit";"Marine";"Barracks";74;1
"Unit";"SCV";"Command Center";80;1
"Unit";"SCV";"Command Center";80;1
"Unit";"SCV";"Command Center";80;1
"Unit";"Marine";"Barracks";76;1
"Unit";"Marine";"Barracks";76;1
"Unit";"Marine";"Barracks";78;1
"Upgrade";"Stimpack";"TechLab";57;0
"Unit";"SCV";"Command Center";84;1
"Unit";"SCV";"Command Center";84;1
"Unit";"SCV";"Command Center";84;1
"Unit";"SCV";"Command Center";90;1
"Unit";"SCV";"Command Center";90;1
"Unit";"SCV";"Command Center";90;1
"Building";"Bunker";NA;86;0
"Unit";"Marine";"Barracks";90;1
"Unit";"Marine";"Barracks";90;1
"Unit";"Marine";"Barracks";90;1
"Unit";"Marine";"Barracks";90;1
"Unit";"Marine";"Barracks";90;1
"Building";"Barracks";NA;80;0
"Building";"Barracks";NA;81;0
"Building";"Factory";NA;87;0
"Building";"Refinery";NA;93;0
"Building";"Armory";NA;87;0
"Unit";"Medivac";"Starport";90;2
"Upgrade";"TerranInfantryWeaponsLevel1";"EngineeringBay";69;0
"Building";"SupplyDepot";NA;98;0
"Upgrade";"TerranInfantryArmorsLevel1";"EngineeringBay";69;0
"Building";"SupplyDepot";NA;98;0
"Building";"SupplyDepot";NA;98;0
"Unit";"Marine";"Barracks";98;1
"Unit";"Marine";"Barracks";98;1
"Unit";"Marine";"Barracks";98;1
"Building";"FactoryTechLab";NA;98;0
"Unit";"Marine";"Barracks";98;1
"Unit";"SCV";"Command Center";100;1
"Unit";"SCV";"Command Center";100;1
"Unit";"SCV";"Command Center";100;1
"Unit";"Marine";"Barracks";100;1
"Building";"BarracksReactor";NA;98;0
"Unit";"Marine";"Barracks";100;1
"Unit";"Marine";"Barracks";101;1
"Unit";"SCV";"Command Center";110;1
"Unit";"SCV";"Command Center";110;1
"Unit";"SCV";"Command Center";110;1
"Building";"SupplyDepot";NA;108;0
"Building";"BarracksReactor";NA;103;0
"Unit";"Marine";"Barracks";110;1
"Unit";"Marine";"Barracks";110;1
"Unit";"Marine";"Barracks";110;1
"Unit";"Marine";"Barracks";110;1
"Unit";"Marine";"Barracks";110;1
"Unit";"Marine";"Barracks";110;1
"Building";"SupplyDepot";NA;113;0
"Building";"SupplyDepot";NA;113;0
"Unit";"Marine";"Barracks";119;1
"Unit";"Marine";"Barracks";119;1
"Unit";"Marine";"Barracks";119;1
"Unit";"Marine";"Barracks";119;1
"Unit";"Marine";"Barracks";119;1
"Unit";"Marine";"Barracks";119;1
"Building";"Barracks";NA;110;0
"Building";"Barracks";NA;110;0
"Building";"Barracks";NA;110;0
"Unit";"Medivac";"Starport";113;2
"Building";"SupplyDepot";NA;119;0
"Building";"SupplyDepot";NA;119;0
"Unit";"Medivac";"Starport";119;2
"Building";"CommandCenter";NA;104;0
"Unit";"Marine";"Barracks";125;1
"Unit";"Marine";"Barracks";125;1
"Unit";"Marine";"Barracks";125;1
"Unit";"Marine";"Barracks";125;1
"Unit";"Marine";"Barracks";125;1
"Unit";"Marine";"Barracks";125;1
"Unit";"Marine";"Barracks";125;1
"Unit";"Marine";"Barracks";125;1
"Unit";"Marine";"Barracks";125;1
"Building";"BarracksTechLab";NA;127;0
"Building";"BarracksTechLab";NA;127;0
"Building";"SupplyDepot";NA;129;0
"Unit";"Marine";"Barracks";129;1
"Building";"SupplyDepot";NA;129;0
"Unit";"Marine";"Barracks";130;1
"Unit";"Marine";"Barracks";130;1
"Building";"SupplyDepot";NA;129;0
"Building";"BarracksReactor";NA;125;0
"Unit";"Marauder";"Barracks";137;2
"Unit";"Marine";"Barracks";138;1
"Unit";"Marine";"Barracks";138;1
"Unit";"Marine";"Barracks";138;1
"Unit";"Marine";"Barracks";138;1
"Unit";"Marine";"Barracks";138;1
"Unit";"Marauder";"Barracks";138;2
"Unit";"Marauder";"Barracks";138;2
"Unit";"Marine";"Barracks";138;1
"Unit";"Marine";"Barracks";139;1
"Unit";"Marine";"Barracks";139;1
"Unit";"Marine";"Barracks";141;1
"Unit";"Medivac";"Starport";138;2
"Unit";"Medivac";"Starport";138;2
"Unit";"Marine";"Barracks";143;1
"Unit";"Marine";"Barracks";143;1
"Upgrade";"TerranVehicleWeaponsLevel1";"Armory";119;0
"Unit";"Marine";"Barracks";143;1
"Unit";"Marine";"Barracks";144;1
"Unit";"Marine";"Barracks";145;1
"Unit";"Marine";"Barracks";145;1
"Unit";"Marine";"Barracks";147;1
"Unit";"Marine";"Barracks";148;1
"Unit";"Marine";"Barracks";155;1
"Unit";"Marine";"Barracks";155;1
"Unit";"Marine";"Barracks";155;1
"Unit";"Marauder";"Barracks";155;2
"Unit";"Marine";"Barracks";160;1
"Unit";"Marauder";"Barracks";155;2
"Upgrade";"TerranInfantryArmorsLevel2";"EngineeringBay";119;0
"Upgrade";"TerranInfantryWeaponsLevel2";"EngineeringBay";119;0
"Unit";"Marine";"Barracks";168;1
"Unit";"Marine";"Barracks";168;1
"Unit";"Marine";"Barracks";168;1
"Unit";"Marine";"Barracks";168;1
"Unit";"Marine";"Barracks";168;1
"Unit";"Marine";"Barracks";168;1
"Unit";"Marauder";"Barracks";167;2
"Unit";"Marauder";"Barracks";171;2
"Unit";"Marauder";"Barracks";174;2
"Building";"Refinery";NA;184;0
"Building";"MissileTurret";NA;186;0
"Building";"Refinery";NA;184;0
"Unit";"Marine";"Barracks";188;1
"Unit";"Marauder";"Barracks";188;2
"Unit";"Marine";"Barracks";191;1
"Unit";"Marine";"Barracks";191;1
"Unit";"Marine";"Barracks";191;1
"Unit";"Marine";"Barracks";191;1
"Unit";"Marine";"Barracks";191;1
"Unit";"Marine";"Barracks";191;1
"Unit";"Marine";"Barracks";191;1
"Unit";"Marine";"Barracks";191;1
"Unit";"Marine";"Barracks";191;1
"Unit";"Marine";"Barracks";191;1
"Unit";"Marauder";"Barracks";191;2
"Unit";"Marauder";"Barracks";191;2
"Unit";"Marauder";"Barracks";191;2
"Unit";"Marine";"Barracks";191;1
"Unit";"Marine";"Barracks";192;1
"Unit";"Medivac";"Starport";191;2
"Unit";"Medivac";"Starport";191;2
"Unit";"Marine";"Barracks";196;1
"Unit";"Marine";"Barracks";196;1
"Unit";"Marine";"Barracks";196;1
"Unit";"Marine";"Barracks";197;1
"Unit";"Marine";"Barracks";197;1
"Unit";"SCV";"Command Center";207;1
"Unit";"SCV";"Command Center";207;1
"Unit";"SCV";"Command Center";207;1
"Unit";"SCV";"Command Center";207;1
"Unit";"Marauder";"Barracks";201;2
"Unit";"Marauder";"Barracks";203;2
"Unit";"Marauder";"Barracks";205;2
"Unit";"Marine";"Barracks";218;1
"Unit";"Marine";"Barracks";218;1
"Unit";"Marine";"Barracks";218;1
"Unit";"Marine";"Barracks";218;1
"Unit";"Marine";"Barracks";218;1
"Unit";"Marine";"Barracks";218;1
"Unit";"Marine";"Barracks";218;1
"Unit";"Marine";"Barracks";218;1
"Unit";"Marine";"Barracks";218;1
"Unit";"Marine";"Barracks";218;1
"Unit";"SCV";"Command Center";228;1
"Unit";"SCV";"Command Center";228;1
"Unit";"SCV";"Command Center";228;1
"Unit";"SCV";"Command Center";228;1
"Unit";"Marine";"Barracks";226;1
"Unit";"Marauder";"Barracks";222;2
"Unit";"Marauder";"Barracks";224;2
"Unit";"Marine";"Barracks";228;1
"Unit";"Marine";"Barracks";229;1
"Unit";"Marine";"Barracks";229;1
"Unit";"Marine";"Barracks";231;1
"Unit";"Marine";"Barracks";231;1
"Unit";"Marine";"Barracks";233;1
"Unit";"Marauder";"Barracks";242;2
"Unit";"Marine";"Barracks";247;1
"Unit";"Marine";"Barracks";247;1
"Unit";"Marine";"Barracks";247;1
"Unit";"Marine";"Barracks";247;1
"Unit";"Marauder";"Barracks";243;2
"Unit";"Marauder";"Barracks";245;2
"Unit";"Medivac";"Starport";239;2
"Unit";"Medivac";"Starport";241;2
"Unit";"Marine";"Barracks";247;1
"Unit";"Marine";"Barracks";248;1
"Upgrade";"TerranInfantryArmorsLevel3";"EngineeringBay";191;0
"Building";"CommandCenter";NA;228;0
"Unit";"Marine";"Barracks";269;1
"Unit";"Marine";"Barracks";269;1
"Unit";"Marine";"Barracks";269;1
"Unit";"Marine";"Barracks";269;1
"Unit";"Marine";"Barracks";269;1
"Unit";"Marine";"Barracks";269;1
"Unit";"Marine";"Barracks";269;1
"Unit";"Marauder";"Barracks";269;2
"Unit";"Marauder";"Barracks";269;2
"Unit";"Marauder";"Barracks";269;2
"Building";"GhostAcademy";NA;269;0
"Unit";"Marauder";"Barracks";276;2
"Unit";"Marauder";"Barracks";278;2
"Unit";"Marauder";"Barracks";280;2
"Unit";"Liberator";"Starport";269;3
"Unit";"Liberator";"Starport";269;3
"Unit";"Ghost";"Barracks";288;2
"Unit";"Ghost";"Barracks";288;2
"Building";"MissileTurret";NA;294;0
"Upgrade";"TerranInfantryWeaponsLevel3";"EngineeringBay";267;0
"Unit";"Ghost";"Barracks";294;2
"Unit";"Ghost";"Barracks";294;2
"Unit";"Ghost";"Barracks";296;2
"Unit";"Liberator";"Starport";294;3
"Unit";"Liberator";"Starport";294;3
"Building";"CommandCenter";NA;294;0
"Unit";"Ghost";"Barracks";310;2
