"type";"unit_name";"on_building";"total_supply_lag";"supply"
"Building";"Refinery";NA;15;0
"Building";"Barracks";NA;16;0
"Unit";"Reaper";"Barracks";19;1
"Building";"CommandCenter";NA;20;0
"Building";"Factory";NA;20;0
"Building";"BarracksReactor";NA;21;0
"Building";"Refinery";NA;22;0
"Building";"Starport";NA;24;0
"Unit";"Hellion";"Factory";24;2
"Unit";"Hellion";"Factory";26;2
"Building";"BarracksTechLab";NA;29;0
"Unit";"Hellion";"Factory";30;2
"Unit";"Hellion";"Factory";32;2
"Unit";"Hellion";"Factory";39;2
"Unit";"Hellion";"Factory";41;2
"Unit";"Banshee";"Starport";45;3
"Building";"BarracksTechLab";NA;49;0
"Building";"CommandCenter";NA;51;0
"Unit";"Marine";"Barracks";53;1
"Unit";"Banshee";"Starport";56;3
"Building";"EngineeringBay";NA;60;0
"Building";"EngineeringBay";NA;60;0
"Unit";"Marine";"Barracks";61;1
"Upgrade";"Stimpack";"TechLab";64;0
"Building";"FactoryReactor";NA;64;0
"Building";"Barracks";NA;64;0
"Building";"Barracks";NA;64;0
"Building";"Refinery";NA;66;0
"Building";"Refinery";NA;66;0
"Unit";"Marine";"Barracks";66;1
"Building";"StarportReactor";NA;69;0
"Building";"Barracks";NA;69;0
"Building";"Barracks";NA;69;0
"Unit";"Marine";"Barracks";69;1
"Upgrade";"TerranInfantryWeaponsLevel1";"EngineeringBay";72;0
"Unit";"Marine";"Barracks";72;1
"Unit";"Marine";"Barracks";73;1
"Unit";"Marine";"Barracks";74;1
"Unit";"Marine";"Barracks";77;1
"Unit";"Marine";"Barracks";78;1
"Unit";"Medivac";"Starport";79;2
"Unit";"Marine";"Barracks";81;1
"Unit";"Medivac";"Starport";82;2
"Unit";"Marine";"Barracks";86;1
"Unit";"Marine";"Barracks";87;1
"Unit";"Marine";"Barracks";88;1
"Unit";"Marine";"Barracks";89;1
"Building";"BarracksReactor";NA;90;0
"Building";"BarracksReactor";NA;90;0
"Unit";"Marine";"Barracks";90;1
"Building";"Armory";NA;91;0
"Unit";"Marine";"Barracks";94;1
"Unit";"Marine";"Barracks";95;1
"Unit";"Marine";"Barracks";96;1
"Unit";"Marine";"Barracks";97;1
"Building";"Refinery";NA;98;0
"Unit";"Marine";"Barracks";98;1
"Unit";"Marine";"Barracks";99;1
"Unit";"Medivac";"Starport";100;2
"Unit";"Medivac";"Starport";102;2
"Unit";"Marine";"Barracks";107;1
"Unit";"Marine";"Barracks";109;1
"Unit";"Marine";"Barracks";110;1
"Unit";"Marine";"Barracks";111;1
"Unit";"Marine";"Barracks";112;1
"Unit";"Marine";"Barracks";113;1
"Unit";"Marine";"Barracks";114;1
"Unit";"Marine";"Barracks";115;1
"Building";"CommandCenter";NA;116;0
"Unit";"Marine";"Barracks";116;1
"Unit";"Marine";"Barracks";117;1
"Unit";"Marine";"Barracks";118;1
"Unit";"Marine";"Barracks";119;1
"Unit";"Marine";"Barracks";120;1
"Unit";"Marine";"Barracks";121;1
"Unit";"Medivac";"Starport";122;2
"Unit";"Marine";"Barracks";124;1
"Unit";"Medivac";"Starport";125;2
"Unit";"Marine";"Barracks";129;1
"Unit";"Marine";"Barracks";130;1
"Upgrade";"TerranInfantryWeaponsLevel2";"EngineeringBay";132;0
"Unit";"Marine";"Barracks";132;1
"Unit";"Marine";"Barracks";133;1
"Unit";"Marine";"Barracks";134;1
"Unit";"Marine";"Barracks";135;1
"Unit";"Marine";"Barracks";136;1
"Unit";"Marine";"Barracks";137;1
"Unit";"Marine";"Barracks";138;1
"Unit";"Marine";"Barracks";139;1
"Unit";"Marine";"Barracks";140;1
"Building";"Barracks";NA;141;0
"Unit";"Marine";"Barracks";141;1
"Unit";"Marine";"Barracks";142;1
"Unit";"Marine";"Barracks";143;1
"Unit";"Marine";"Barracks";144;1
"Unit";"Marine";"Barracks";145;1
"Unit";"Marine";"Barracks";146;1
"Building";"Barracks";NA;147;0
"Unit";"Marine";"Barracks";147;1
"Unit";"Marine";"Barracks";148;1
"Unit";"Marine";"Barracks";149;1
"Building";"Refinery";NA;150;0
"Unit";"Marine";"Barracks";150;1
"Unit";"Marine";"Barracks";151;1
"Unit";"Marine";"Barracks";152;1
"Unit";"Marine";"Barracks";153;1
"Unit";"Marine";"Barracks";154;1
"Unit";"Marine";"Barracks";155;1
"Unit";"Marine";"Barracks";156;1
"Unit";"Marine";"Barracks";157;1
"Unit";"Liberator";"Starport";158;3
"Unit";"Liberator";"Starport";161;3
"Building";"GhostAcademy";NA;164;0
"Building";"BarracksTechLab";NA;164;0
"Building";"BarracksTechLab";NA;164;0
"Unit";"Marine";"Barracks";164;1
"Unit";"Marine";"Barracks";165;1
"Unit";"Marine";"Barracks";166;1
"Unit";"Marine";"Barracks";167;1
"Unit";"Marine";"Barracks";168;1
"Unit";"Marine";"Barracks";169;1
"Building";"BarracksTechLab";NA;172;0
"Unit";"Marine";"Barracks";172;1
"Unit";"Ghost";"Barracks";179;2
"Unit";"Ghost";"Barracks";181;2
"Unit";"Ghost";"Barracks";183;2
"Unit";"Marine";"Barracks";185;1
"Unit";"Marine";"Barracks";186;1
"Unit";"Marine";"Barracks";187;1
"Unit";"Marine";"Barracks";188;1
"Unit";"Marine";"Barracks";189;1
"Unit";"Marine";"Barracks";190;1
"Unit";"Marine";"Barracks";191;1
"Unit";"Marine";"Barracks";194;1
"Unit";"Marine";"Barracks";196;1
"Unit";"Marine";"Barracks";197;1
"Unit";"Marine";"Barracks";198;1
"Unit";"Marine";"Barracks";199;1
"Unit";"Marine";"Barracks";200;1
"Unit";"Marine";"Barracks";201;1
"Building";"Bunker";NA;204;0
"Upgrade";"TerranInfantryWeaponsLevel3";"EngineeringBay";204;0
"Unit";"Ghost";"Barracks";204;2
"Unit";"Ghost";"Barracks";206;2
"Unit";"Ghost";"Barracks";211;2
"Unit";"Ghost";"Barracks";214;2
"Unit";"Marine";"Barracks";218;1
"Unit";"Marine";"Barracks";219;1
"Unit";"Marine";"Barracks";220;1
"Unit";"Marine";"Barracks";225;1
"Unit";"Marine";"Barracks";226;1
"Unit";"Marine";"Barracks";227;1
"Unit";"Ghost";"Barracks";228;2
"Unit";"Ghost";"Barracks";230;2
"Unit";"Ghost";"Barracks";232;2
"Unit";"Ghost";"Barracks";234;2
"Unit";"Marauder";"Barracks";236;2
"Unit";"Marauder";"Barracks";238;2
"Unit";"Marauder";"Barracks";240;2
"Unit";"Ghost";"Barracks";242;2
"Unit";"Ghost";"Barracks";244;2
"Unit";"Ghost";"Barracks";246;2
"Unit";"Liberator";"Starport";248;3
"Unit";"Ghost";"Barracks";251;2
"Unit";"Marine";"Barracks";253;1
"Unit";"Marine";"Barracks";254;1
"Unit";"Marine";"Barracks";255;1
"Unit";"Marine";"Barracks";256;1
"Unit";"Marine";"Barracks";257;1
"Unit";"Marine";"Barracks";258;1
"Building";"Refinery";NA;259;0
"Building";"Refinery";NA;259;0
"Unit";"Marauder";"Barracks";259;2
"Unit";"Marauder";"Barracks";261;2
"Upgrade";"SprayTerran";NA;263;0
"Upgrade";"SprayTerran";NA;263;0
"Upgrade";"SprayTerran";NA;263;0
"Upgrade";"BansheeCloak";NA;263;0
"Upgrade";"SprayTerran";NA;263;0
"Upgrade";"TerranInfantryArmorsLevel1";NA;263;0
"Upgrade";"SprayTerran";NA;263;0
"Upgrade";"ShieldWall";NA;263;0
"Upgrade";"SprayTerran";NA;263;0
"Upgrade";"TerranInfantryArmorsLevel2";NA;263;0
"Upgrade";"PunisherGrenades";NA;263;0
"Upgrade";"GhostMoebiusReactor";NA;263;0
"Upgrade";"SprayTerran";NA;263;0
"Upgrade";"TerranInfantryArmorsLevel3";NA;263;0
