"type";"unit_name";"on_building";"total_supply";"supply"
"Building";"Refinery";NA;15;0
"Building";"Barracks";NA;15;0
"Unit";"Marine";"Barracks";18;1
"Unit";"Marine";"Barracks";20;1
"Building";"Refinery";NA;20;0
"Building";"Bunker";NA;20;0
"Unit";"Marine";"Barracks";21;1
"Building";"Factory";NA;20;0
"Unit";"Marine";"Barracks";24;1
"Building";"Bunker";NA;22;0
"Building";"FactoryTechLab";NA;25;0
"Unit";"Marine";"Barracks";28;1
"Building";"Starport";NA;27;0
"Unit";"Marine";"Barracks";30;1
"Unit";"Marine";"Barracks";32;1
