"type";"unit_name";"on_building";"total_supply";"supply"
"Unit";"Overlord";"Larva";12;0
"Building";"SpawningPool";NA;17;0
"Unit";"Overlord";"Larva";21;0
"Building";"Hatchery";NA;17;0
"Unit";"Zergling";"Larva";21;1
"Unit";"Zergling";"Larva";21;1
"Unit";"Overlord";"Larva";21;0
"Unit";"Zergling";"Larva";21;1
"Unit";"Zergling";"Larva";21;1
"Unit";"Zergling";"Larva";21;1
"Unit";"Zergling";"Larva";21;1
"Building";"SpineCrawler";NA;21;0
"Unit";"Queen";"Hatchery";21;2
"Building";"SpineCrawler";NA;21;0
"Unit";"Zergling";"Larva";27;1
"Unit";"Zergling";"Larva";27;1
"Unit";"Zergling";"Larva";27;1
"Unit";"Zergling";"Larva";27;1
"Unit";"Queen";"Hatchery";23;2
"Building";"Extractor";NA;35;0
"Building";"Extractor";NA;35;0
"Unit";"Queen";"Hatchery";35;2
"Unit";"Zergling";"Larva";50;1
"Unit";"Zergling";"Larva";50;1
"Unit";"Zergling";"Larva";50;1
"Unit";"Zergling";"Larva";50;1
"Unit";"Zergling";"Larva";50;1
"Unit";"Zergling";"Larva";50;1
"Building";"SpineCrawler";NA;56;0
"Unit";"Overlord";"Larva";62;0
"Unit";"Overlord";"Larva";62;0
"Building";"RoachWarren";NA;56;0
"Unit";"Roach";"Larva";62;2
"Unit";"Roach";"Larva";62;2
"Unit";"Roach";"Larva";62;2
"Unit";"Roach";"Larva";62;2
"Unit";"Roach";"Larva";62;2
"Unit";"Roach";"Larva";62;2
"Unit";"Roach";"Larva";62;2
"Unit";"Roach";"Larva";62;2
"Building";"SpineCrawler";NA;62;0
"Unit";"Roach";"Larva";62;2
"Unit";"Roach";"Larva";62;2
"Unit";"Roach";"Larva";62;2
"Unit";"Overlord";"Larva";78;0
"Unit";"Overlord";"Larva";78;0
"Unit";"Roach";"Larva";84;2
"Unit";"Roach";"Larva";84;2
"Unit";"Roach";"Larva";84;2
"Unit";"Roach";"Larva";84;2
"Unit";"Roach";"Larva";84;2
"Unit";"Roach";"Larva";84;2
"Unit";"Roach";"Larva";84;2
"Unit";"Roach";"Larva";84;2
"Unit";"Roach";"Larva";84;2
"Unit";"Roach";"Larva";96;2
"Unit";"Roach";"Larva";102;2
"Unit";"Roach";"Larva";102;2
"Unit";"Roach";"Larva";102;2
"Unit";"Roach";"Larva";104;2
"Unit";"Roach";"Larva";104;2
"Unit";"Roach";"Larva";104;2
"Unit";"Roach";"Larva";104;2
"Unit";"Roach";"Larva";104;2
"Unit";"Roach";"Larva";104;2
"Unit";"Roach";"Larva";118;2
"Unit";"Roach";"Larva";118;2
"Unit";"Roach";"Larva";118;2
"Unit";"Roach";"Larva";122;2
"Unit";"Roach";"Larva";122;2
"Unit";"Roach";"Larva";122;2
"Unit";"Queen";"Hatchery";112;2
"Unit";"Queen";"Hatchery";112;2
"Unit";"Roach";"Larva";126;2
"Unit";"Roach";"Larva";128;2
"Unit";"Roach";"Larva";128;2
"Unit";"Roach";"Larva";128;2
"Unit";"Roach";"Larva";138;2
"Unit";"Roach";"Larva";142;2
"Unit";"Zergling";"Larva";142;1
"Unit";"Zergling";"Larva";142;1
"Unit";"Roach";"Larva";146;2
"Upgrade";"GlialReconstitution";"RoachWarren";128;0
"Unit";"Roach";"Larva";154;2
"Unit";"Roach";"Larva";154;2
"Unit";"Roach";"Larva";154;2
"Unit";"Roach";"Larva";154;2
"Unit";"Roach";"Larva";154;2
"Unit";"Zergling";"Larva";154;1
"Unit";"Zergling";"Larva";154;1
"Unit";"Roach";"Larva";154;2
"Unit";"Roach";"Larva";154;2
"Unit";"Overlord";"Larva";154;0
"Unit";"Overlord";"Larva";154;0
"Unit";"Overlord";"Larva";154;0
"Unit";"Roach";"Larva";170;2
"Unit";"Roach";"Larva";170;2
"Unit";"Roach";"Larva";170;2
"Unit";"Roach";"Larva";170;2
"Unit";"Roach";"Larva";170;2
"Unit";"Roach";"Larva";170;2
"Unit";"Roach";"Larva";174;2
"Unit";"Roach";"Larva";174;2
"Unit";"Roach";"Larva";174;2
"Unit";"Roach";"Larva";174;2
"Unit";"Roach";"Larva";194;2
"Unit";"Roach";"Larva";194;2
"Unit";"Roach";"Larva";194;2
"Unit";"Roach";"Larva";194;2
"Unit";"Roach";"Larva";194;2
"Unit";"Roach";"Larva";194;2
"Unit";"Roach";"Larva";194;2
"Unit";"Roach";"Larva";194;2
"Unit";"Roach";"Larva";194;2
"Unit";"Roach";"Larva";194;2
"Unit";"Roach";"Larva";208;2
"Unit";"Roach";"Larva";208;2
"Unit";"Roach";"Larva";208;2
"Building";"Extractor";NA;208;0
"Unit";"Zergling";"Larva";214;1
"Unit";"Zergling";"Larva";214;1
"Unit";"Roach";"Larva";214;2
"Unit";"Zergling";"Larva";214;1
"Unit";"Zergling";"Larva";214;1
"Unit";"Zergling";"Larva";214;1
"Unit";"Zergling";"Larva";214;1
"Unit";"Zergling";"Larva";214;1
"Unit";"Zergling";"Larva";214;1
"Unit";"Zergling";"Larva";214;1
"Unit";"Zergling";"Larva";214;1
"Unit";"Roach";"Larva";214;2
"Unit";"Roach";"Larva";220;2
"Unit";"Roach";"Larva";220;2
"Unit";"Roach";"Larva";220;2
"Unit";"Roach";"Larva";234;2
"Unit";"Roach";"Larva";234;2
"Unit";"Roach";"Larva";234;2
"Unit";"Roach";"Larva";240;2
"Unit";"Roach";"Larva";240;2
"Unit";"Roach";"Larva";240;2
"Unit";"Roach";"Larva";240;2
"Unit";"Queen";"Hatchery";240;2
"Unit";"Queen";"Hatchery";240;2
"Unit";"Roach";"Larva";254;2
"Unit";"Roach";"Larva";254;2
"Unit";"Roach";"Larva";254;2
"Unit";"Roach";"Larva";254;2
"Unit";"Roach";"Larva";254;2
"Unit";"Roach";"Larva";254;2
"Unit";"Roach";"Larva";258;2
"Unit";"Roach";"Larva";258;2
"Unit";"Roach";"Larva";258;2
"Unit";"Roach";"Larva";268;2
"Building";"Extractor";NA;268;0
"Unit";"Roach";"Larva";278;2
"Unit";"Roach";"Larva";278;2
"Unit";"Roach";"Larva";278;2
"Unit";"Roach";"Larva";278;2
"Unit";"Roach";"Larva";278;2
"Unit";"Roach";"Larva";278;2
"Unit";"Roach";"Larva";278;2
"Unit";"Roach";"Larva";278;2
"Unit";"Roach";"Larva";278;2
"Unit";"Roach";"Larva";278;2
"Unit";"Roach";"Larva";280;2
"Unit";"Roach";"Larva";280;2
"Unit";"Roach";"Larva";280;2
"Unit";"Roach";"Larva";280;2
