"type";"unit_name";"on_building";"total_supply";"supply"
"Unit";"Overlord";"Larva";13;0
"Building";"Extractor";NA;17;0
"Building";"SpawningPool";NA;18;0
"Building";"Hatchery";NA;17;0
"Unit";"Zergling";"Larva";23;1
"Unit";"Zergling";"Larva";23;1
"Unit";"Zergling";"Larva";23;1
"Unit";"Zergling";"Larva";23;1
"Unit";"Queen";"Hatchery";23;2
"Unit";"Queen";"Hatchery";23;2
"Unit";"Overlord";"Larva";27;0
"Unit";"Queen";"Hatchery";31;2
"Building";"SporeCrawler";NA;36;0
"Building";"SporeCrawler";NA;36;0
"Building";"Hatchery";NA;27;0
"Building";"CreepTumorQueen";NA;49;0
"Building";"SporeCrawler";NA;52;0
"Unit";"Overlord";"Larva";56;0
"Unit";"Overlord";"Larva";56;0
"Unit";"Overlord";"Larva";56;0
"Building";"CreepTumor";NA;56;0
"Building";"Extractor";NA;57;0
"Building";"Extractor";NA;57;0
"Building";"Extractor";NA;57;0
"Unit";"Overlord";"Larva";76;0
"Unit";"Overlord";"Larva";76;0
"Building";"EvolutionChamber";NA;76;0
"Unit";"Queen";"Hatchery";76;2
"Building";"Extractor";NA;93;0
"Building";"Extractor";NA;93;0
"Building";"HydraliskDen";NA;93;0
"Unit";"Queen";"Hatchery";93;2
"Unit";"Overlord";"Larva";93;0
"Unit";"Overlord";"Larva";93;0
"Unit";"Overlord";"Larva";93;0
"Unit";"Overlord";"Larva";93;0
"Unit";"Overlord";"Larva";93;0
"Unit";"Hydralisk";"Larva";93;2
"Unit";"Hydralisk";"Larva";93;2
"Unit";"Hydralisk";"Larva";93;2
"Unit";"Queen";"Hatchery";93;2
"Unit";"Queen";"Hatchery";93;2
"Unit";"Overlord";"Larva";95;0
"Unit";"Overlord";"Larva";95;0
"Unit";"Overlord";"Larva";96;0
"Unit";"Hydralisk";"Larva";104;2
"Unit";"Hydralisk";"Larva";104;2
"Unit";"Hydralisk";"Larva";104;2
"Unit";"Hydralisk";"Larva";104;2
"Unit";"Hydralisk";"Larva";104;2
"Unit";"Hydralisk";"Larva";104;2
"Unit";"Hydralisk";"Larva";104;2
"Unit";"Hydralisk";"Larva";104;2
"Unit";"Hydralisk";"Larva";104;2
"Unit";"Hydralisk";"Larva";104;2
"Unit";"Queen";"Hatchery";98;2
"Building";"CreepTumor";NA;113;0
"Upgrade";"ZergMissileWeaponsLevel1";"EvolutionChamber";93;0
"Unit";"Hydralisk";"Larva";138;2
"Unit";"Hydralisk";"Larva";138;2
"Unit";"Hydralisk";"Larva";138;2
"Unit";"Hydralisk";"Larva";138;2
"Unit";"Hydralisk";"Larva";138;2
"Unit";"Hydralisk";"Larva";138;2
"Unit";"Hydralisk";"Larva";138;2
"Building";"Hatchery";NA;95;0
"Upgrade";"EvolveMuscularAugments";"HydraliskDen";108;0
"Unit";"Hydralisk";"Larva";139;2
"Unit";"Hydralisk";"Larva";139;2
"Unit";"Hydralisk";"Larva";139;2
"Unit";"Hydralisk";"Larva";139;2
"Unit";"Hydralisk";"Larva";141;2
"Unit";"Hydralisk";"Larva";149;2
"Building";"LurkerDenMP";NA;104;0
"Unit";"Overlord";"Larva";161;0
"Unit";"Overlord";"Larva";161;0
"Unit";"Overlord";"Larva";161;0
"Unit";"Overlord";"Larva";161;0
"Unit";"Hydralisk";"Larva";153;2
"Unit";"Hydralisk";"Larva";153;2
"Unit";"Hydralisk";"Larva";153;2
"Unit";"Hydralisk";"Larva";153;2
"Unit";"Hydralisk";"Larva";165;2
"Unit";"Hydralisk";"Larva";165;2
"Unit";"Hydralisk";"Larva";173;2
"Unit";"Hydralisk";"Larva";173;2
"Unit";"Hydralisk";"Larva";173;2
"Unit";"Hydralisk";"Larva";173;2
"Unit";"Hydralisk";"Larva";173;2
"Unit";"Hydralisk";"Larva";173;2
"Unit";"Hydralisk";"Larva";173;2
"Unit";"Zergling";"Larva";173;1
"Unit";"Zergling";"Larva";173;1
"Unit";"Zergling";"Larva";173;1
"Unit";"Zergling";"Larva";173;1
"Unit";"Zergling";"Larva";173;1
"Unit";"Zergling";"Larva";173;1
"Unit";"Zergling";"Larva";173;1
"Unit";"Zergling";"Larva";173;1
"Unit";"Zergling";"Larva";173;1
"Unit";"Zergling";"Larva";173;1
"Unit";"Hydralisk";"Larva";173;2
"Unit";"Hydralisk";"Larva";173;2
"Unit";"Hydralisk";"Larva";173;2
"Upgrade";"EvolveGroovedSpines";"HydraliskDen";165;0
"Unit";"Hydralisk";"Larva";191;2
"Unit";"Hydralisk";"Larva";191;2
"Unit";"Hydralisk";"Larva";191;2
"Unit";"Hydralisk";"Larva";191;2
"Unit";"Hydralisk";"Larva";191;2
"Building";"CreepTumor";NA;207;0
"Unit";"Zergling";"Larva";207;1
"Unit";"Zergling";"Larva";207;1
"Unit";"Hydralisk";"Larva";207;2
"Unit";"Hydralisk";"Larva";207;2
"Unit";"Hydralisk";"Larva";207;2
"Unit";"Hydralisk";"Larva";207;2
"Unit";"Zergling";"Larva";217;1
"Unit";"Zergling";"Larva";217;1
"Unit";"Zergling";"Larva";217;1
"Unit";"Zergling";"Larva";217;1
"Unit";"Zergling";"Larva";219;1
"Unit";"Zergling";"Larva";219;1
"Unit";"Zergling";"Larva";219;1
"Unit";"Zergling";"Larva";219;1
"Unit";"Zergling";"Larva";219;1
"Unit";"Zergling";"Larva";219;1
"Unit";"Zergling";"Larva";219;1
"Unit";"Zergling";"Larva";219;1
"Unit";"Zergling";"Larva";219;1
"Unit";"Zergling";"Larva";219;1
"Unit";"Zergling";"Larva";219;1
"Unit";"Zergling";"Larva";219;1
"Unit";"Zergling";"Larva";219;1
"Unit";"Zergling";"Larva";219;1
"Unit";"Zergling";"Larva";219;1
"Unit";"Zergling";"Larva";219;1
"Upgrade";"ZergMissileWeaponsLevel2";"EvolutionChamber";161;0
"Unit";"Zergling";"Larva";227;1
"Unit";"Zergling";"Larva";227;1
"Unit";"Zergling";"Larva";227;1
"Unit";"Zergling";"Larva";227;1
"Unit";"Zergling";"Larva";227;1
"Unit";"Zergling";"Larva";227;1
"Unit";"Zergling";"Larva";251;1
"Unit";"Zergling";"Larva";251;1
"Unit";"Zergling";"Larva";253;1
"Unit";"Zergling";"Larva";253;1
"Unit";"Zergling";"Larva";253;1
"Unit";"Zergling";"Larva";253;1
"Unit";"Zergling";"Larva";253;1
"Unit";"Zergling";"Larva";253;1
"Unit";"Zergling";"Larva";253;1
"Unit";"Zergling";"Larva";253;1
"Unit";"Zergling";"Larva";253;1
"Unit";"Zergling";"Larva";253;1
"Unit";"Zergling";"Larva";253;1
"Unit";"Zergling";"Larva";253;1
"Unit";"Zergling";"Larva";253;1
"Unit";"Zergling";"Larva";253;1
"Unit";"Zergling";"Larva";253;1
"Unit";"Zergling";"Larva";253;1
"Unit";"Zergling";"Larva";253;1
"Unit";"Zergling";"Larva";253;1
"Unit";"Zergling";"Larva";253;1
"Unit";"Zergling";"Larva";253;1
"Unit";"Zergling";"Larva";253;1
"Unit";"Zergling";"Larva";253;1
"Unit";"Zergling";"Larva";253;1
"Unit";"Zergling";"Larva";253;1
"Unit";"Overlord";"Larva";253;0
"Unit";"Overlord";"Larva";253;0
"Unit";"Overlord";"Larva";253;0
"Unit";"Overlord";"Larva";253;0
"Unit";"Queen";"Hatchery";247;2
"Unit";"Overlord";"Larva";253;0
"Unit";"Hydralisk";"Larva";263;2
"Unit";"Hydralisk";"Larva";277;2
"Unit";"Hydralisk";"Larva";279;2
"Building";"CreepTumor";NA;279;0
"Unit";"Hydralisk";"Larva";279;2
"Unit";"Overlord";"Larva";279;0
"Unit";"Hydralisk";"Larva";279;2
"Unit";"Overlord";"Larva";279;0
"Unit";"Hydralisk";"Larva";291;2
"Unit";"Hydralisk";"Larva";291;2
"Unit";"Hydralisk";"Larva";291;2
"Unit";"Hydralisk";"Larva";291;2
"Unit";"Hydralisk";"Larva";291;2
"Unit";"Hydralisk";"Larva";291;2
"Unit";"Hydralisk";"Larva";291;2
"Unit";"Hydralisk";"Larva";291;2
