"type";"unit_name";"on_building";"total_supply_lag";"supply"
"Building";"Extractor";NA;13;0
"Building";"SpawningPool";NA;13;0
"Unit";"Overlord";"Larva";16;0
"Unit";"Zergling";"Larva";16;1
"Unit";"Zergling";"Larva";17;1
"Unit";"Zergling";"Larva";18;1
"Unit";"Zergling";"Larva";19;1
"Unit";"Zergling";"Larva";20;1
"Unit";"Zergling";"Larva";21;1
"Unit";"Zergling";"Larva";22;1
"Unit";"Zergling";"Larva";23;1
"Unit";"Zergling";"Larva";24;1
"Unit";"Zergling";"Larva";25;1
"Building";"BanelingNest";NA;26;0
"Unit";"Zergling";"Larva";26;1
"Unit";"Zergling";"Larva";27;1
"Unit";"Queen";"Hatchery";28;2
"Unit";"Overlord";"Larva";30;0
"Unit";"Zergling";"Larva";30;1
"Unit";"Zergling";"Larva";31;1
"Unit";"Baneling";"Zergling";33;0
"Unit";"Baneling";"Zergling";33;0
"Building";"Hatchery";NA;36;0
"Unit";"Baneling";"Zergling";39;0
"Unit";"Queen";"Hatchery";39;2
"Unit";"Baneling";"Zergling";42;0
"Unit";"Overlord";"Larva";44;0
"Unit";"Overlord";"Larva";44;0
"Unit";"Baneling";"Zergling";46;0
"Unit";"Baneling";"Zergling";46;0
"Unit";"Baneling";"Zergling";46;0
"Unit";"Zergling";"Larva";50;1
"Unit";"Zergling";"Larva";51;1
"Unit";"Queen";"Hatchery";60;2
"Unit";"Zergling";"Larva";62;1
"Unit";"Zergling";"Larva";63;1
"Building";"Hatchery";NA;64;0
"Unit";"Zergling";"Larva";64;1
"Unit";"Zergling";"Larva";65;1
"Building";"CreepTumorQueen";NA;66;0
"Building";"EvolutionChamber";NA;69;0
"Building";"CreepTumorQueen";NA;74;0
"Building";"RoachWarren";NA;74;0
"Building";"Extractor";NA;78;0
"Unit";"Overlord";"Larva";78;0
"Building";"CreepTumor";NA;80;0
"Building";"CreepTumor";NA;80;0
"Building";"CreepTumorQueen";NA;80;0
"Building";"Extractor";NA;80;0
"Unit";"Overlord";"Larva";80;0
"Unit";"Zergling";"Larva";81;1
"Unit";"Zergling";"Larva";82;1
"Unit";"Zergling";"Larva";83;1
"Unit";"Zergling";"Larva";84;1
"Unit";"Zergling";"Larva";85;1
"Unit";"Zergling";"Larva";86;1
"Unit";"Zergling";"Larva";87;1
"Unit";"Zergling";"Larva";88;1
"Unit";"Roach";"Larva";89;2
"Unit";"Roach";"Larva";91;2
"Unit";"Roach";"Larva";93;2
"Unit";"Roach";"Larva";95;2
"Unit";"Roach";"Larva";97;2
"Unit";"Roach";"Larva";99;2
"Unit";"Overlord";"Larva";101;0
"Building";"CreepTumor";NA;101;0
"Building";"CreepTumor";NA;101;0
"Unit";"Overlord";"Larva";105;0
"Building";"Extractor";NA;107;0
"Unit";"Roach";"Larva";107;2
"Upgrade";"GlialReconstitution";"RoachWarren";109;0
"Unit";"Roach";"Larva";109;2
"Unit";"Roach";"Larva";111;2
"Unit";"Roach";"Larva";113;2
"Unit";"Overlord";"Larva";124;0
"Building";"CreepTumor";NA;124;0
"Unit";"Overlord";"Larva";124;0
"Unit";"Overlord";"Larva";124;0
"Building";"InfestationPit";NA;130;0
"Building";"Extractor";NA;132;0
"Building";"Extractor";NA;132;0
"Building";"CreepTumor";NA;132;0
"Building";"CreepTumor";NA;132;0
"Unit";"Roach";"Larva";132;2
"Unit";"Roach";"Larva";134;2
"Unit";"Roach";"Larva";136;2
"Unit";"Roach";"Larva";138;2
"Unit";"Roach";"Larva";140;2
"Unit";"Roach";"Larva";142;2
"Unit";"Roach";"Larva";144;2
"Unit";"Roach";"Larva";146;2
"Unit";"Roach";"Larva";148;2
"Unit";"Roach";"Larva";150;2
"Unit";"Roach";"Larva";152;2
"Building";"CreepTumor";NA;154;0
"Unit";"Overlord";"Larva";154;0
"Unit";"Overlord";"Larva";154;0
"Unit";"Overlord";"Larva";154;0
"Unit";"Overlord";"Larva";154;0
"Unit";"Overlord";"Larva";154;0
"Building";"CreepTumor";NA;159;0
"Unit";"Roach";"Larva";161;2
"Unit";"Roach";"Larva";163;2
"Unit";"Roach";"Larva";165;2
"Unit";"Roach";"Larva";167;2
"Building";"CreepTumor";NA;169;0
"Building";"Hatchery";NA;169;0
"Unit";"Infestor";"Larva";169;2
"Unit";"Infestor";"Larva";171;2
"Building";"CreepTumor";NA;173;0
"Unit";"Infestor";"Larva";173;2
"Building";"CreepTumor";NA;175;0
"Unit";"Roach";"Larva";175;2
"Unit";"Roach";"Larva";177;2
"Unit";"Roach";"Larva";179;2
"Unit";"Roach";"Larva";181;2
"Unit";"Roach";"Larva";183;2
"Unit";"Roach";"Larva";185;2
"Unit";"Overlord";"Larva";187;0
"Unit";"Overlord";"Larva";187;0
"Unit";"Overlord";"Larva";187;0
"Unit";"Overlord";"Larva";187;0
"Building";"CreepTumor";NA;187;0
"Unit";"Overlord";"Larva";187;0
"Unit";"Roach";"Larva";187;2
"Unit";"Roach";"Larva";189;2
"Unit";"Roach";"Larva";191;2
"Unit";"Roach";"Larva";193;2
"Unit";"Roach";"Larva";195;2
"Unit";"Roach";"Larva";197;2
"Unit";"Roach";"Larva";199;2
"Unit";"Roach";"Larva";201;2
"Unit";"Roach";"Larva";203;2
"Unit";"Roach";"Larva";205;2
"Unit";"Roach";"Larva";207;2
"Unit";"Roach";"Larva";209;2
"Upgrade";"Burrow";"Hatchery";211;0
"Unit";"Roach";"Larva";211;2
"Unit";"Roach";"Larva";213;2
"Unit";"Roach";"Larva";215;2
"Unit";"Roach";"Larva";217;2
"Unit";"Roach";"Larva";219;2
"Unit";"Roach";"Larva";221;2
"Unit";"Roach";"Larva";223;2
"Unit";"Overlord";"Larva";225;0
"Unit";"Roach";"Larva";225;2
"Unit";"Roach";"Larva";227;2
"Unit";"Overlord";"Larva";229;0
"Unit";"Roach";"Larva";229;2
"Unit";"Overlord";"Larva";231;0
"Unit";"Roach";"Larva";231;2
"Unit";"Roach";"Larva";233;2
"Unit";"Roach";"Larva";235;2
"Unit";"Roach";"Larva";237;2
"Unit";"Roach";"Larva";239;2
"Building";"Extractor";NA;241;0
"Unit";"Roach";"Larva";241;2
"Unit";"Roach";"Larva";243;2
"Unit";"Roach";"Larva";245;2
"Unit";"Roach";"Larva";247;2
"Unit";"Roach";"Larva";249;2
"Unit";"Roach";"Larva";251;2
"Unit";"Roach";"Larva";253;2
"Unit";"Roach";"Larva";255;2
"Unit";"Roach";"Larva";257;2
"Unit";"Roach";"Larva";259;2
"Unit";"Roach";"Larva";261;2
"Unit";"Roach";"Larva";263;2
"Unit";"Roach";"Larva";265;2
"Building";"CreepTumor";NA;267;0
"Building";"HydraliskDen";NA;267;0
"Upgrade";"TunnelingClaws";"RoachWarren";267;0
"Unit";"Infestor";"Larva";267;2
"Unit";"Roach";"Larva";269;2
"Unit";"Roach";"Larva";271;2
"Unit";"Roach";"Larva";273;2
"Unit";"Roach";"Larva";275;2
"Unit";"Roach";"Larva";277;2
"Unit";"Roach";"Larva";279;2
"Unit";"Roach";"Larva";281;2
"Unit";"Roach";"Larva";283;2
"Unit";"Roach";"Larva";285;2
"Unit";"Roach";"Larva";287;2
"Unit";"Roach";"Larva";289;2
"Building";"CreepTumor";NA;291;0
"Unit";"Roach";"Larva";291;2
"Building";"CreepTumor";NA;293;0
"Building";"CreepTumor";NA;293;0
"Building";"SpineCrawler";NA;293;0
"Building";"SpineCrawler";NA;293;0
"Building";"SpineCrawler";NA;293;0
"Unit";"Roach";"Larva";296;2
"Unit";"Roach";"Larva";298;2
"Unit";"Roach";"Larva";300;2
"Unit";"Roach";"Larva";302;2
"Unit";"Roach";"Larva";304;2
"Unit";"Roach";"Larva";306;2
"Unit";"Roach";"Larva";308;2
"Unit";"Roach";"Larva";310;2
"Unit";"Roach";"Larva";312;2
"Unit";"Roach";"Larva";314;2
"Unit";"Roach";"Larva";316;2
"Unit";"Roach";"Larva";318;2
"Unit";"Roach";"Larva";320;2
"Unit";"Roach";"Larva";322;2
"Unit";"Roach";"Larva";324;2
"Unit";"Roach";"Larva";326;2
"Unit";"Roach";"Larva";328;2
"Unit";"Roach";"Larva";330;2
"Unit";"Roach";"Larva";332;2
"Unit";"Roach";"Larva";334;2
"Unit";"Roach";"Larva";336;2
"Unit";"Roach";"Larva";338;2
"Unit";"Roach";"Larva";340;2
"Unit";"Roach";"Larva";342;2
"Unit";"Roach";"Larva";344;2
"Unit";"Roach";"Larva";346;2
"Unit";"Roach";"Larva";348;2
"Unit";"Roach";"Larva";350;2
"Unit";"Roach";"Larva";352;2
"Unit";"Roach";"Larva";354;2
"Unit";"Roach";"Larva";356;2
"Unit";"Roach";"Larva";358;2
"Unit";"Roach";"Larva";360;2
"Unit";"Roach";"Larva";362;2
"Unit";"Roach";"Larva";364;2
"Unit";"Roach";"Larva";366;2
"Unit";"Roach";"Larva";368;2
"Unit";"Roach";"Larva";370;2
"Unit";"Roach";"Larva";372;2
"Unit";"Roach";"Larva";374;2
"Unit";"Roach";"Larva";376;2
"Unit";"Roach";"Larva";378;2
"Unit";"Roach";"Larva";380;2
"Unit";"Roach";"Larva";382;2
"Unit";"Roach";"Larva";384;2
"Unit";"Roach";"Larva";386;2
"Unit";"Roach";"Larva";388;2
"Unit";"Queen";"Hatchery";390;2
"Unit";"Roach";"Larva";392;2
"Building";"CreepTumor";NA;394;0
"Unit";"Roach";"Larva";394;2
"Unit";"Roach";"Larva";396;2
"Unit";"Roach";"Larva";398;2
"Building";"CreepTumor";NA;400;0
"Unit";"Roach";"Larva";400;2
"Building";"Extractor";NA;402;0
"Unit";"Roach";"Larva";402;2
"Unit";"Roach";"Larva";404;2
"Upgrade";"zerglingmovementspeed";NA;406;0
"Upgrade";"SprayZerg";NA;406;0
"Upgrade";"SprayZerg";NA;406;0
"Upgrade";"SprayZerg";NA;406;0
"Upgrade";"SprayZerg";NA;406;0
"Upgrade";"ZergMissileWeaponsLevel1";NA;406;0
"Upgrade";"SprayZerg";NA;406;0
"Upgrade";"overlordspeed";NA;406;0
"Upgrade";"SprayZerg";NA;406;0
"Upgrade";"ZergMissileWeaponsLevel2";NA;406;0
"Upgrade";"ZergGroundArmorsLevel1";NA;406;0
"Upgrade";"EvolveMuscularAugments";NA;406;0
"Upgrade";"SprayZerg";NA;406;0
