"type";"unit_name";"on_building";"total_supply_lag";"supply"
"Unit";"Overlord";"Larva";13;0
"Building";"SpawningPool";NA;16;0
"Building";"Hatchery";NA;18;0
"Building";"Extractor";NA;19;0
"Unit";"Zergling";"Larva";19;1
"Unit";"Zergling";"Larva";20;1
"Unit";"Zergling";"Larva";21;1
"Unit";"Zergling";"Larva";22;1
"Unit";"Zergling";"Larva";23;1
"Unit";"Zergling";"Larva";24;1
"Unit";"Queen";"Hatchery";25;2
"Unit";"Overlord";"Larva";27;0
"Unit";"Queen";"Hatchery";29;2
"Unit";"Queen";"Hatchery";32;2
"Unit";"Overlord";"Larva";38;0
"Unit";"Zergling";"Larva";38;1
"Unit";"Zergling";"Larva";39;1
"Unit";"Zergling";"Larva";40;1
"Unit";"Zergling";"Larva";41;1
"Unit";"Zergling";"Larva";42;1
"Unit";"Zergling";"Larva";43;1
"Building";"SpineCrawler";NA;44;0
"Unit";"Queen";"Hatchery";44;2
"Building";"CreepTumorQueen";NA;48;0
"Unit";"Zergling";"Larva";48;1
"Unit";"Zergling";"Larva";49;1
"Unit";"Zergling";"Larva";50;1
"Unit";"Zergling";"Larva";51;1
"Unit";"Zergling";"Larva";54;1
"Unit";"Zergling";"Larva";55;1
"Unit";"Zergling";"Larva";56;1
"Unit";"Zergling";"Larva";57;1
"Unit";"Zergling";"Larva";58;1
"Unit";"Zergling";"Larva";59;1
"Unit";"Zergling";"Larva";60;1
"Unit";"Zergling";"Larva";61;1
"Building";"CreepTumor";NA;65;0
"Unit";"Overlord";"Larva";66;0
"Building";"Hatchery";NA;66;0
"Building";"Extractor";NA;67;0
"Building";"RoachWarren";NA;67;0
"Unit";"Overlord";"Larva";67;0
"Unit";"Zergling";"Larva";71;1
"Unit";"Zergling";"Larva";72;1
"Unit";"Zergling";"Larva";73;1
"Unit";"Zergling";"Larva";74;1
"Unit";"Zergling";"Larva";75;1
"Unit";"Zergling";"Larva";76;1
"Unit";"Zergling";"Larva";77;1
"Unit";"Zergling";"Larva";78;1
"Unit";"Zergling";"Larva";79;1
"Unit";"Zergling";"Larva";80;1
"Unit";"Overlord";"Larva";81;0
"Building";"CreepTumorQueen";NA;81;0
"Unit";"Zergling";"Larva";81;1
"Unit";"Zergling";"Larva";82;1
"Unit";"Zergling";"Larva";83;1
"Unit";"Zergling";"Larva";84;1
"Unit";"Zergling";"Larva";85;1
"Unit";"Zergling";"Larva";86;1
"Unit";"Zergling";"Larva";87;1
"Unit";"Zergling";"Larva";88;1
"Unit";"Zergling";"Larva";89;1
"Unit";"Zergling";"Larva";90;1
"Building";"EvolutionChamber";NA;94;0
"Building";"CreepTumor";NA;94;0
"Building";"Extractor";NA;101;0
"Unit";"Roach";"Larva";101;2
"Unit";"Roach";"Larva";103;2
"Unit";"Roach";"Larva";105;2
"Unit";"Roach";"Larva";107;2
"Unit";"Roach";"Larva";109;2
"Unit";"Roach";"Larva";111;2
"Unit";"Roach";"Larva";113;2
"Unit";"Roach";"Larva";115;2
"Unit";"Roach";"Larva";117;2
"Unit";"Roach";"Larva";119;2
"Unit";"Roach";"Larva";121;2
"Unit";"Roach";"Larva";123;2
"Building";"CreepTumorQueen";NA;127;0
"Building";"CreepTumor";NA;127;0
"Building";"CreepTumor";NA;127;0
"Unit";"Overlord";"Larva";127;0
"Unit";"Overlord";"Larva";127;0
"Upgrade";"GlialReconstitution";"RoachWarren";127;0
"Building";"CreepTumor";NA;127;0
"Building";"CreepTumorQueen";NA;127;0
"Building";"CreepTumor";NA;127;0
"Unit";"Overlord";"Larva";127;0
"Unit";"Overlord";"Larva";137;0
"Unit";"Overlord";"Larva";137;0
"Building";"Extractor";NA;137;0
"Building";"Extractor";NA;141;0
"Unit";"Overlord";"Larva";145;0
"Building";"Spire";NA;145;0
"Building";"Extractor";NA;145;0
"Building";"CreepTumor";NA;145;0
"Building";"CreepTumor";NA;147;0
"Unit";"Overlord";"Larva";147;0
"Unit";"Roach";"Larva";152;2
"Unit";"Roach";"Larva";154;2
"Unit";"Roach";"Larva";156;2
"Unit";"Roach";"Larva";158;2
"Unit";"Roach";"Larva";160;2
"Unit";"Roach";"Larva";162;2
"Unit";"Roach";"Larva";164;2
"Building";"Hatchery";NA;166;0
"Building";"CreepTumor";NA;171;0
"Unit";"Overlord";"Larva";171;0
"Unit";"Overlord";"Larva";171;0
"Unit";"Mutalisk";"Larva";171;2
"Unit";"Mutalisk";"Larva";173;2
"Unit";"Mutalisk";"Larva";175;2
"Unit";"Mutalisk";"Larva";177;2
"Unit";"Mutalisk";"Larva";179;2
"Unit";"Mutalisk";"Larva";181;2
"Unit";"Mutalisk";"Larva";183;2
"Building";"CreepTumor";NA;185;0
"Unit";"Overlord";"Larva";186;0
"Unit";"Overlord";"Larva";186;0
"Unit";"Roach";"Larva";186;2
"Unit";"Roach";"Larva";188;2
"Unit";"Roach";"Larva";190;2
"Unit";"Roach";"Larva";192;2
"Unit";"Roach";"Larva";194;2
"Unit";"Roach";"Larva";196;2
"Unit";"Overlord";"Larva";198;0
"Upgrade";"Burrow";"Hatchery";198;0
"Upgrade";"TunnelingClaws";"RoachWarren";198;0
"Building";"InfestationPit";NA;198;0
"Unit";"Roach";"Larva";198;2
"Unit";"Roach";"Larva";200;2
"Unit";"Roach";"Larva";202;2
"Unit";"Roach";"Larva";204;2
"Unit";"Roach";"Larva";206;2
"Unit";"Roach";"Larva";208;2
"Unit";"Roach";"Larva";210;2
"Unit";"Roach";"Larva";212;2
"Unit";"Roach";"Larva";214;2
"Unit";"Roach";"Larva";216;2
"Unit";"Overlord";"Larva";218;0
"Unit";"Roach";"Larva";218;2
"Unit";"Roach";"Larva";220;2
"Unit";"Roach";"Larva";222;2
"Unit";"Roach";"Larva";224;2
"Unit";"Roach";"Larva";226;2
"Unit";"Overlord";"Larva";228;0
"Unit";"Overlord";"Larva";228;0
"Unit";"Overlord";"Larva";228;0
"Building";"CreepTumorQueen";NA;228;0
"Building";"CreepTumor";NA;228;0
"Unit";"Roach";"Larva";228;2
"Unit";"Roach";"Larva";230;2
"Unit";"Roach";"Larva";232;2
"Unit";"Roach";"Larva";234;2
"Unit";"Roach";"Larva";236;2
"Unit";"Roach";"Larva";238;2
"Unit";"Roach";"Larva";240;2
"Unit";"Roach";"Larva";242;2
"Unit";"Roach";"Larva";244;2
"Unit";"Roach";"Larva";246;2
"Unit";"Roach";"Larva";248;2
"Unit";"Roach";"Larva";250;2
"Unit";"Roach";"Larva";252;2
"Unit";"Roach";"Larva";254;2
"Unit";"Overlord";"Larva";256;0
"Unit";"Overlord";"Larva";256;0
"Unit";"Overlord";"Larva";256;0
"Unit";"Overlord";"Larva";256;0
"Unit";"Roach";"Larva";256;2
"Unit";"Roach";"Larva";258;2
"Unit";"Roach";"Larva";260;2
"Unit";"Roach";"Larva";262;2
"Unit";"Roach";"Larva";264;2
"Unit";"Roach";"Larva";266;2
"Unit";"Roach";"Larva";268;2
"Unit";"Roach";"Larva";270;2
"Unit";"Roach";"Larva";272;2
"Unit";"Roach";"Larva";274;2
"Unit";"Roach";"Larva";276;2
"Unit";"Roach";"Larva";278;2
"Unit";"Roach";"Larva";280;2
"Unit";"Roach";"Larva";282;2
"Unit";"Roach";"Larva";284;2
"Unit";"Roach";"Larva";286;2
"Unit";"Roach";"Larva";288;2
"Unit";"Roach";"Larva";290;2
"Unit";"Roach";"Larva";292;2
"Unit";"Infestor";"Larva";294;2
"Unit";"Infestor";"Larva";296;2
"Unit";"Infestor";"Larva";298;2
"Unit";"Infestor";"Larva";300;2
"Unit";"Infestor";"Larva";302;2
"Unit";"Infestor";"Larva";304;2
"Unit";"Infestor";"Larva";306;2
"Building";"Extractor";NA;308;0
"Building";"Extractor";NA;308;0
"Building";"SpineCrawler";NA;308;0
"Building";"SpineCrawler";NA;308;0
"Building";"SpineCrawler";NA;308;0
"Building";"CreepTumor";NA;308;0
"Unit";"Roach";"Larva";314;2
"Unit";"Roach";"Larva";316;2
"Unit";"Roach";"Larva";318;2
"Unit";"Roach";"Larva";320;2
"Unit";"Roach";"Larva";322;2
"Unit";"Roach";"Larva";324;2
"Unit";"Roach";"Larva";326;2
"Building";"SpineCrawler";NA;331;0
"Building";"SpineCrawler";NA;331;0
"Building";"SpineCrawler";NA;331;0
"Unit";"Roach";"Larva";331;2
"Unit";"Roach";"Larva";333;2
"Unit";"Roach";"Larva";335;2
"Unit";"Roach";"Larva";337;2
"Building";"SpineCrawler";NA;339;0
"Building";"SpineCrawler";NA;339;0
"Building";"SpineCrawler";NA;339;0
"Unit";"Roach";"Larva";339;2
"Unit";"Roach";"Larva";341;2
"Unit";"Roach";"Larva";343;2
"Unit";"Roach";"Larva";345;2
"Unit";"Roach";"Larva";347;2
"Building";"CreepTumor";NA;349;0
"Unit";"Overlord";"Larva";349;0
"Building";"SporeCrawler";NA;349;0
"Building";"SporeCrawler";NA;350;0
"Building";"CreepTumor";NA;350;0
"Building";"Hatchery";NA;350;0
"Unit";"Overlord";"Larva";350;0
"Building";"HydraliskDen";NA;350;0
"Unit";"Roach";"Larva";350;2
"Unit";"Roach";"Larva";352;2
"Unit";"Roach";"Larva";354;2
"Unit";"Roach";"Larva";356;2
"Unit";"Roach";"Larva";358;2
"Unit";"Roach";"Larva";360;2
"Unit";"Roach";"Larva";362;2
"Unit";"Roach";"Larva";364;2
"Unit";"Roach";"Larva";366;2
"Unit";"Roach";"Larva";368;2
"Unit";"Roach";"Larva";370;2
"Unit";"Roach";"Larva";372;2
"Unit";"Roach";"Larva";374;2
"Unit";"Roach";"Larva";376;2
"Unit";"Roach";"Larva";378;2
"Unit";"Roach";"Larva";380;2
"Unit";"Roach";"Larva";382;2
"Unit";"Roach";"Larva";384;2
"Building";"SporeCrawler";NA;386;0
"Building";"SpineCrawler";NA;386;0
"Unit";"Roach";"Larva";386;2
"Unit";"Roach";"Larva";388;2
"Unit";"Roach";"Larva";390;2
"Unit";"Roach";"Larva";392;2
"Unit";"Roach";"Larva";394;2
"Unit";"Roach";"Larva";396;2
"Unit";"Roach";"Larva";398;2
"Unit";"Roach";"Larva";400;2
"Unit";"Roach";"Larva";402;2
"Building";"SpineCrawler";NA;404;0
"Building";"EvolutionChamber";NA;404;0
"Building";"CreepTumorQueen";NA;404;0
"Building";"CreepTumorQueen";NA;404;0
"Building";"CreepTumor";NA;404;0
"Building";"CreepTumor";NA;407;0
"Building";"Extractor";NA;407;0
"Building";"Extractor";NA;407;0
"Unit";"Corruptor";"Larva";407;2
"Unit";"Corruptor";"Larva";409;2
"Unit";"Corruptor";"Larva";411;2
"Unit";"Corruptor";"Larva";413;2
"Unit";"Corruptor";"Larva";415;2
"Unit";"Corruptor";"Larva";417;2
"Unit";"Hydralisk";"Larva";422;2
"Building";"SporeCrawler";NA;424;0
"Unit";"Corruptor";"Larva";424;2
"Unit";"Corruptor";"Larva";426;2
"Unit";"Corruptor";"Larva";428;2
"Unit";"Hydralisk";"Larva";430;2
"Unit";"Hydralisk";"Larva";432;2
"Unit";"Hydralisk";"Larva";434;2
"Unit";"Hydralisk";"Larva";436;2
"Unit";"Hydralisk";"Larva";438;2
"Unit";"Hydralisk";"Larva";440;2
"Unit";"Hydralisk";"Larva";442;2
"Unit";"Hydralisk";"Larva";444;2
"Unit";"Hydralisk";"Larva";446;2
"Unit";"Hydralisk";"Larva";448;2
"Unit";"Hydralisk";"Larva";450;2
"Unit";"Hydralisk";"Larva";452;2
"Unit";"Hydralisk";"Larva";454;2
"Unit";"Hydralisk";"Larva";456;2
"Unit";"Hydralisk";"Larva";458;2
"Unit";"Hydralisk";"Larva";460;2
"Unit";"Hydralisk";"Larva";462;2
"Unit";"Hydralisk";"Larva";464;2
"Unit";"Hydralisk";"Larva";466;2
"Unit";"Hydralisk";"Larva";468;2
"Unit";"Hydralisk";"Larva";470;2
"Unit";"Hydralisk";"Larva";472;2
"Unit";"Infestor";"Larva";474;2
"Unit";"Infestor";"Larva";476;2
"Unit";"Overlord";"Larva";478;0
"Building";"UltraliskCavern";NA;478;0
"Unit";"Corruptor";"Larva";478;2
"Unit";"Corruptor";"Larva";480;2
"Unit";"Corruptor";"Larva";482;2
"Unit";"Corruptor";"Larva";484;2
"Unit";"Corruptor";"Larva";486;2
"Unit";"Corruptor";"Larva";488;2
"Unit";"Corruptor";"Larva";490;2
"Unit";"Corruptor";"Larva";492;2
"Unit";"Corruptor";"Larva";494;2
"Unit";"Corruptor";"Larva";496;2
"Building";"CreepTumor";NA;498;0
"Building";"Hatchery";NA;498;0
"Building";"Hatchery";NA;498;0
"Building";"Extractor";NA;498;0
"Building";"Extractor";NA;498;0
"Upgrade";"ChitinousPlating";"UltraliskCavern";498;0
"Building";"SporeCrawler";NA;499;0
"Building";"SpineCrawler";NA;499;0
"Upgrade";"SprayZerg";NA;502;0
"Upgrade";"SprayZerg";NA;502;0
"Upgrade";"zerglingmovementspeed";NA;502;0
"Upgrade";"SprayZerg";NA;502;0
"Upgrade";"SprayZerg";NA;502;0
"Upgrade";"SprayZerg";NA;502;0
"Upgrade";"ZergMissileWeaponsLevel1";NA;502;0
"Upgrade";"SprayZerg";NA;502;0
"Upgrade";"ZergMissileWeaponsLevel2";NA;502;0
"Upgrade";"SprayZerg";NA;502;0
"Upgrade";"ZergGroundArmorsLevel1";NA;502;0
"Upgrade";"SprayZerg";NA;502;0
"Upgrade";"EvolveMuscularAugments";NA;502;0
"Upgrade";"overlordspeed";NA;502;0
"Upgrade";"ZergMeleeWeaponsLevel1";NA;502;0
"Upgrade";"ZergMissileWeaponsLevel3";NA;502;0
"Upgrade";"ZergFlyerWeaponsLevel1";NA;502;0
"Upgrade";"ZergGroundArmorsLevel2";NA;502;0
"Upgrade";"SprayZerg";NA;502;0
"Upgrade";"SprayZerg";NA;502;0
"Upgrade";"ZergMeleeWeaponsLevel2";NA;502;0
"Upgrade";"SprayZerg";NA;502;0
"Upgrade";"SprayZerg";NA;502;0
"Upgrade";"ZergGroundArmorsLevel3";NA;502;0
