"type";"unit_name";"on_building";"total_supply_lag";"supply"
"Building";"Extractor";NA;13;0
"Building";"SpawningPool";NA;13;0
"Unit";"Overlord";"Larva";16;0
"Unit";"Zergling";"Larva";16;1
"Unit";"Zergling";"Larva";17;1
"Unit";"Zergling";"Larva";18;1
"Unit";"Zergling";"Larva";19;1
"Unit";"Zergling";"Larva";20;1
"Unit";"Zergling";"Larva";21;1
"Unit";"Zergling";"Larva";22;1
"Unit";"Zergling";"Larva";23;1
"Unit";"Zergling";"Larva";24;1
"Unit";"Zergling";"Larva";25;1
"Building";"BanelingNest";NA;26;0
"Unit";"Zergling";"Larva";26;1
"Unit";"Zergling";"Larva";27;1
"Unit";"Queen";"Hatchery";28;2
"Unit";"Overlord";"Larva";30;0
"Unit";"Queen";"Hatchery";32;2
"Unit";"Zergling";"Larva";34;1
"Unit";"Zergling";"Larva";35;1
"Unit";"Baneling";"Zergling";38;0
"Unit";"Baneling";"Zergling";42;0
"Building";"CreepTumorQueen";NA;42;0
"Unit";"Zergling";"Larva";42;1
"Unit";"Zergling";"Larva";43;1
"Unit";"Zergling";"Larva";44;1
"Unit";"Zergling";"Larva";45;1
"Unit";"Zergling";"Larva";46;1
"Unit";"Zergling";"Larva";47;1
"Unit";"Zergling";"Larva";48;1
"Unit";"Zergling";"Larva";49;1
"Building";"Hatchery";NA;50;0
"Unit";"Zergling";"Larva";50;1
"Unit";"Zergling";"Larva";51;1
"Unit";"Zergling";"Larva";52;1
"Unit";"Zergling";"Larva";53;1
"Unit";"Baneling";"Zergling";54;0
"Unit";"Zergling";"Larva";54;1
"Unit";"Zergling";"Larva";55;1
"Unit";"Queen";"Hatchery";56;2
"Unit";"Zergling";"Larva";58;1
"Unit";"Zergling";"Larva";59;1
"Building";"CreepTumor";NA;60;0
"Unit";"Baneling";"Zergling";60;0
"Unit";"Baneling";"Zergling";60;0
"Unit";"Queen";"Hatchery";62;2
"Building";"CreepTumor";NA;64;0
"Building";"CreepTumorQueen";NA;65;0
"Unit";"Zergling";"Larva";67;1
"Unit";"Zergling";"Larva";68;1
"Unit";"Zergling";"Larva";69;1
"Unit";"Zergling";"Larva";70;1
"Unit";"Zergling";"Larva";71;1
"Unit";"Zergling";"Larva";72;1
"Unit";"Zergling";"Larva";73;1
"Unit";"Zergling";"Larva";74;1
"Unit";"Zergling";"Larva";75;1
"Unit";"Zergling";"Larva";76;1
"Unit";"Overlord";"Larva";77;0
"Building";"CreepTumor";NA;77;0
"Building";"CreepTumor";NA;77;0
"Unit";"Overlord";"Larva";77;0
"Unit";"Baneling";"Zergling";77;0
"Unit";"Baneling";"Zergling";77;0
"Unit";"Zergling";"Larva";77;1
"Unit";"Zergling";"Larva";78;1
"Unit";"Zergling";"Larva";79;1
"Unit";"Zergling";"Larva";80;1
"Unit";"Zergling";"Larva";81;1
"Unit";"Zergling";"Larva";82;1
"Unit";"Zergling";"Larva";83;1
"Unit";"Zergling";"Larva";84;1
"Unit";"Zergling";"Larva";85;1
"Unit";"Zergling";"Larva";86;1
"Unit";"Zergling";"Larva";87;1
"Unit";"Zergling";"Larva";88;1
"Unit";"Zergling";"Larva";89;1
"Unit";"Zergling";"Larva";90;1
"Unit";"Zergling";"Larva";91;1
"Unit";"Zergling";"Larva";92;1
"Unit";"Baneling";"Zergling";93;0
"Unit";"Overlord";"Larva";96;0
"Unit";"Overlord";"Larva";98;0
"Unit";"Overlord";"Larva";99;0
"Building";"Hatchery";NA;100;0
"Unit";"Baneling";"Zergling";100;0
"Unit";"Baneling";"Zergling";100;0
"Unit";"Zergling";"Larva";107;1
"Unit";"Zergling";"Larva";108;1
"Unit";"Zergling";"Larva";109;1
"Unit";"Zergling";"Larva";110;1
"Unit";"Zergling";"Larva";111;1
"Unit";"Zergling";"Larva";112;1
"Unit";"Zergling";"Larva";113;1
"Unit";"Zergling";"Larva";114;1
"Unit";"Zergling";"Larva";115;1
"Unit";"Zergling";"Larva";116;1
"Unit";"Zergling";"Larva";117;1
"Unit";"Zergling";"Larva";118;1
"Unit";"Zergling";"Larva";119;1
"Unit";"Zergling";"Larva";120;1
"Building";"EvolutionChamber";NA;121;0
"Building";"RoachWarren";NA;122;0
"Building";"CreepTumor";NA;128;0
"Unit";"Baneling";"Zergling";129;0
"Building";"Extractor";NA;129;0
"Building";"Extractor";NA;129;0
"Unit";"Overlord";"Larva";136;0
"Building";"CreepTumor";NA;136;0
"Building";"CreepTumor";NA;136;0
"Unit";"Roach";"Larva";136;2
"Unit";"Roach";"Larva";138;2
"Unit";"Roach";"Larva";140;2
"Unit";"Roach";"Larva";142;2
"Unit";"Overlord";"Larva";144;0
"Unit";"Overlord";"Larva";144;0
"Unit";"Roach";"Larva";144;2
"Unit";"Roach";"Larva";146;2
"Unit";"Roach";"Larva";148;2
"Unit";"Roach";"Larva";150;2
"Building";"CreepTumor";NA;152;0
"Unit";"Roach";"Larva";152;2
"Unit";"Roach";"Larva";154;2
"Unit";"Roach";"Larva";156;2
"Unit";"Roach";"Larva";158;2
"Unit";"Roach";"Larva";160;2
"Building";"Extractor";NA;162;0
"Unit";"Roach";"Larva";165;2
"Unit";"Overlord";"Larva";167;0
"Building";"CreepTumor";NA;167;0
"Unit";"Overlord";"Larva";167;0
"Unit";"Overlord";"Larva";167;0
"Upgrade";"GlialReconstitution";"RoachWarren";167;0
"Unit";"Overlord";"Larva";167;0
"Unit";"Overlord";"Larva";167;0
"Unit";"Roach";"Larva";167;2
"Unit";"Roach";"Larva";169;2
"Unit";"Roach";"Larva";171;2
"Unit";"Roach";"Larva";173;2
"Unit";"Roach";"Larva";175;2
"Unit";"Roach";"Larva";177;2
"Unit";"Roach";"Larva";179;2
"Building";"EvolutionChamber";NA;181;0
"Unit";"Roach";"Larva";187;2
"Unit";"Roach";"Larva";189;2
"Building";"InfestationPit";NA;191;0
"Building";"CreepTumor";NA;191;0
"Building";"Extractor";NA;191;0
"Building";"Extractor";NA;194;0
"Unit";"Roach";"Larva";195;2
"Unit";"Roach";"Larva";197;2
"Unit";"Roach";"Larva";199;2
"Unit";"Roach";"Larva";201;2
"Unit";"Roach";"Larva";203;2
"Unit";"Roach";"Larva";205;2
"Unit";"Roach";"Larva";207;2
"Unit";"Roach";"Larva";209;2
"Unit";"Roach";"Larva";211;2
"Unit";"Overlord";"Larva";213;0
"Unit";"Overlord";"Larva";213;0
"Unit";"Overlord";"Larva";213;0
"Unit";"Overlord";"Larva";213;0
"Unit";"Overlord";"Larva";213;0
"Unit";"Roach";"Larva";213;2
"Unit";"Roach";"Larva";215;2
"Unit";"Roach";"Larva";217;2
"Unit";"Roach";"Larva";219;2
"Unit";"Roach";"Larva";221;2
"Unit";"Roach";"Larva";223;2
"Unit";"Roach";"Larva";225;2
"Unit";"Infestor";"Larva";227;2
"Unit";"Infestor";"Larva";229;2
"Unit";"Overlord";"Larva";231;0
"Unit";"Roach";"Larva";231;2
"Unit";"Roach";"Larva";233;2
"Unit";"Roach";"Larva";235;2
"Building";"CreepTumor";NA;237;0
"Building";"Hatchery";NA;237;0
"Unit";"Roach";"Larva";237;2
"Unit";"Roach";"Larva";239;2
"Unit";"Roach";"Larva";241;2
"Unit";"Roach";"Larva";243;2
"Unit";"Roach";"Larva";245;2
"Unit";"Roach";"Larva";247;2
"Unit";"Roach";"Larva";249;2
"Unit";"Roach";"Larva";251;2
"Unit";"Roach";"Larva";253;2
"Unit";"Roach";"Larva";255;2
"Unit";"Overlord";"Larva";261;0
"Unit";"Overlord";"Larva";261;0
"Unit";"Overlord";"Larva";261;0
"Unit";"Roach";"Larva";261;2
"Unit";"Roach";"Larva";263;2
"Unit";"Roach";"Larva";265;2
"Unit";"Roach";"Larva";267;2
"Unit";"Roach";"Larva";269;2
"Unit";"Roach";"Larva";271;2
"Unit";"Roach";"Larva";273;2
"Unit";"Roach";"Larva";275;2
"Unit";"Infestor";"Larva";277;2
"Building";"SpineCrawler";NA;283;0
"Building";"CreepTumor";NA;291;0
"Building";"SpineCrawler";NA;292;0
"Building";"Extractor";NA;292;0
"Building";"SpineCrawler";NA;292;0
"Upgrade";"Burrow";"Hatchery";292;0
"Building";"SpineCrawler";NA;292;0
"Building";"SpineCrawler";NA;292;0
"Building";"SpineCrawler";NA;292;0
"Building";"HydraliskDen";NA;292;0
"Unit";"Roach";"Larva";292;2
"Unit";"Roach";"Larva";294;2
"Unit";"Roach";"Larva";296;2
"Building";"SpineCrawler";NA;298;0
"Building";"SpineCrawler";NA;298;0
"Upgrade";"TunnelingClaws";"RoachWarren";298;0
"Unit";"Roach";"Larva";298;2
"Unit";"Roach";"Larva";300;2
"Unit";"Roach";"Larva";302;2
"Unit";"Roach";"Larva";304;2
"Unit";"Roach";"Larva";306;2
"Unit";"Roach";"Larva";308;2
"Unit";"Roach";"Larva";310;2
"Unit";"Roach";"Larva";312;2
"Unit";"Roach";"Larva";314;2
"Unit";"Roach";"Larva";316;2
"Unit";"Roach";"Larva";318;2
"Unit";"Roach";"Larva";320;2
"Unit";"Roach";"Larva";322;2
"Unit";"Roach";"Larva";324;2
"Unit";"Roach";"Larva";326;2
"Unit";"Roach";"Larva";328;2
"Unit";"Roach";"Larva";330;2
"Unit";"Roach";"Larva";332;2
"Unit";"Roach";"Larva";334;2
"Unit";"Roach";"Larva";336;2
"Unit";"Roach";"Larva";338;2
"Unit";"Roach";"Larva";340;2
"Unit";"Roach";"Larva";342;2
"Unit";"Roach";"Larva";344;2
"Unit";"Roach";"Larva";346;2
"Unit";"Roach";"Larva";348;2
"Unit";"Roach";"Larva";350;2
"Unit";"Roach";"Larva";352;2
"Unit";"Roach";"Larva";354;2
"Unit";"Roach";"Larva";356;2
"Unit";"Roach";"Larva";358;2
"Unit";"Roach";"Larva";360;2
"Unit";"Roach";"Larva";362;2
"Unit";"Roach";"Larva";364;2
"Unit";"Roach";"Larva";366;2
"Unit";"Roach";"Larva";368;2
"Unit";"Roach";"Larva";370;2
"Unit";"Roach";"Larva";372;2
"Unit";"Infestor";"Larva";374;2
"Unit";"Infestor";"Larva";376;2
"Unit";"Infestor";"Larva";378;2
"Unit";"Infestor";"Larva";380;2
"Unit";"Infestor";"Larva";382;2
"Unit";"Roach";"Larva";384;2
"Unit";"Roach";"Larva";386;2
"Unit";"Roach";"Larva";388;2
"Unit";"Roach";"Larva";390;2
"Building";"CreepTumor";NA;392;0
"Unit";"Roach";"Larva";392;2
"Unit";"Roach";"Larva";394;2
"Unit";"Roach";"Larva";396;2
"Unit";"Roach";"Larva";398;2
"Unit";"Roach";"Larva";400;2
"Building";"RoachWarren";NA;402;0
"Unit";"Roach";"Larva";402;2
"Unit";"Roach";"Larva";404;2
"Unit";"Roach";"Larva";406;2
"Unit";"Roach";"Larva";408;2
"Unit";"Roach";"Larva";410;2
"Unit";"Roach";"Larva";412;2
"Unit";"Roach";"Larva";414;2
"Unit";"Roach";"Larva";416;2
"Unit";"Roach";"Larva";418;2
"Unit";"Roach";"Larva";420;2
"Unit";"Roach";"Larva";422;2
"Unit";"Roach";"Larva";424;2
"Unit";"Roach";"Larva";426;2
"Unit";"Roach";"Larva";428;2
"Unit";"Roach";"Larva";430;2
"Unit";"Roach";"Larva";432;2
"Unit";"Roach";"Larva";434;2
"Unit";"Roach";"Larva";436;2
"Unit";"Roach";"Larva";438;2
"Unit";"Roach";"Larva";440;2
"Unit";"Roach";"Larva";442;2
"Unit";"Roach";"Larva";444;2
"Unit";"Roach";"Larva";446;2
"Unit";"Roach";"Larva";448;2
"Unit";"Roach";"Larva";450;2
"Unit";"Roach";"Larva";452;2
"Unit";"Roach";"Larva";454;2
"Unit";"Roach";"Larva";456;2
"Unit";"Roach";"Larva";458;2
"Unit";"Hydralisk";"Larva";460;2
"Unit";"Hydralisk";"Larva";462;2
"Unit";"Hydralisk";"Larva";464;2
"Building";"CreepTumor";NA;466;0
"Building";"CreepTumorQueen";NA;466;0
"Building";"Hatchery";NA;466;0
"Building";"CreepTumorQueen";NA;466;0
"Unit";"Roach";"Larva";466;2
"Unit";"Roach";"Larva";468;2
"Unit";"Roach";"Larva";470;2
"Building";"CreepTumorQueen";NA;472;0
"Unit";"Roach";"Larva";472;2
"Unit";"Infestor";"Larva";474;2
"Unit";"Infestor";"Larva";476;2
"Unit";"Infestor";"Larva";478;2
"Unit";"Roach";"Larva";480;2
"Unit";"Roach";"Larva";482;2
"Unit";"Roach";"Larva";484;2
"Unit";"Roach";"Larva";486;2
"Unit";"Roach";"Larva";488;2
"Unit";"Roach";"Larva";490;2
"Unit";"Roach";"Larva";492;2
"Unit";"Roach";"Larva";494;2
"Unit";"Roach";"Larva";496;2
"Unit";"Roach";"Larva";498;2
"Unit";"Roach";"Larva";500;2
"Unit";"Roach";"Larva";502;2
"Unit";"Roach";"Larva";504;2
"Unit";"Roach";"Larva";506;2
"Unit";"Roach";"Larva";508;2
"Unit";"Roach";"Larva";510;2
"Unit";"Roach";"Larva";512;2
"Unit";"Roach";"Larva";514;2
"Unit";"Infestor";"Larva";516;2
"Unit";"Infestor";"Larva";518;2
"Unit";"Roach";"Larva";520;2
"Unit";"Roach";"Larva";522;2
"Unit";"Roach";"Larva";524;2
"Unit";"Roach";"Larva";526;2
"Unit";"Roach";"Larva";528;2
"Unit";"Roach";"Larva";530;2
"Unit";"Roach";"Larva";532;2
"Unit";"Roach";"Larva";534;2
"Unit";"Roach";"Larva";536;2
"Unit";"Roach";"Larva";538;2
"Unit";"Roach";"Larva";540;2
"Unit";"Roach";"Larva";542;2
"Unit";"Roach";"Larva";544;2
"Unit";"Roach";"Larva";546;2
"Unit";"Roach";"Larva";548;2
"Unit";"Roach";"Larva";550;2
"Unit";"Roach";"Larva";552;2
"Unit";"Roach";"Larva";554;2
"Unit";"Roach";"Larva";556;2
"Unit";"Roach";"Larva";558;2
"Unit";"Roach";"Larva";560;2
"Unit";"Roach";"Larva";562;2
"Unit";"Roach";"Larva";564;2
"Unit";"Roach";"Larva";566;2
"Unit";"Roach";"Larva";568;2
"Unit";"Roach";"Larva";570;2
"Unit";"Roach";"Larva";572;2
"Unit";"Roach";"Larva";574;2
"Unit";"Roach";"Larva";576;2
"Unit";"Roach";"Larva";578;2
"Unit";"Roach";"Larva";580;2
"Unit";"Roach";"Larva";582;2
"Unit";"Roach";"Larva";584;2
"Unit";"Roach";"Larva";586;2
"Unit";"Roach";"Larva";588;2
"Unit";"Hydralisk";"Larva";590;2
"Unit";"Hydralisk";"Larva";592;2
"Unit";"Hydralisk";"Larva";594;2
"Unit";"Hydralisk";"Larva";596;2
"Unit";"Hydralisk";"Larva";598;2
"Unit";"Hydralisk";"Larva";600;2
"Unit";"Hydralisk";"Larva";602;2
"Unit";"Hydralisk";"Larva";604;2
"Unit";"Hydralisk";"Larva";606;2
"Unit";"Hydralisk";"Larva";608;2
"Unit";"Hydralisk";"Larva";610;2
"Unit";"Hydralisk";"Larva";612;2
"Unit";"Hydralisk";"Larva";614;2
"Unit";"Hydralisk";"Larva";616;2
"Unit";"Hydralisk";"Larva";618;2
"Building";"SpineCrawler";NA;620;0
"Building";"SpineCrawler";NA;620;0
"Building";"Extractor";NA;620;0
"Unit";"Hydralisk";"Larva";620;2
"Unit";"Hydralisk";"Larva";622;2
"Building";"SpineCrawler";NA;624;0
"Building";"SpineCrawler";NA;624;0
"Building";"SpineCrawler";NA;624;0
"Building";"CreepTumor";NA;624;0
"Unit";"Roach";"Larva";624;2
"Unit";"Roach";"Larva";626;2
"Unit";"Roach";"Larva";628;2
"Unit";"Roach";"Larva";630;2
"Building";"Extractor";NA;632;0
"Unit";"Roach";"Larva";632;2
"Building";"CreepTumor";NA;634;0
"Unit";"Roach";"Larva";634;2
"Unit";"Roach";"Larva";636;2
"Unit";"Roach";"Larva";638;2
"Unit";"Roach";"Larva";640;2
"Unit";"Roach";"Larva";642;2
"Unit";"Roach";"Larva";644;2
"Unit";"Roach";"Larva";646;2
"Unit";"Roach";"Larva";648;2
"Unit";"Roach";"Larva";650;2
"Unit";"Roach";"Larva";652;2
"Unit";"Roach";"Larva";654;2
"Unit";"Roach";"Larva";656;2
"Unit";"Roach";"Larva";658;2
"Unit";"Roach";"Larva";660;2
"Unit";"Roach";"Larva";662;2
"Unit";"Roach";"Larva";664;2
"Unit";"Roach";"Larva";666;2
"Unit";"Roach";"Larva";668;2
"Unit";"Roach";"Larva";670;2
"Unit";"Roach";"Larva";672;2
"Unit";"Roach";"Larva";674;2
"Unit";"Roach";"Larva";676;2
"Unit";"Roach";"Larva";678;2
"Unit";"Roach";"Larva";680;2
"Unit";"Roach";"Larva";682;2
"Unit";"Roach";"Larva";684;2
"Unit";"Roach";"Larva";686;2
"Unit";"Roach";"Larva";688;2
"Unit";"Roach";"Larva";690;2
"Unit";"Roach";"Larva";692;2
"Unit";"Roach";"Larva";694;2
"Unit";"Roach";"Larva";696;2
"Unit";"Roach";"Larva";698;2
"Unit";"Roach";"Larva";700;2
"Building";"Extractor";NA;702;0
"Unit";"Roach";"Larva";702;2
"Unit";"Roach";"Larva";704;2
"Unit";"Roach";"Larva";706;2
"Unit";"Roach";"Larva";708;2
"Unit";"Roach";"Larva";710;2
"Unit";"Roach";"Larva";712;2
"Unit";"Roach";"Larva";714;2
"Building";"Hatchery";NA;716;0
"Unit";"Roach";"Larva";716;2
"Unit";"Roach";"Larva";718;2
"Unit";"Roach";"Larva";720;2
"Unit";"Roach";"Larva";722;2
"Unit";"Roach";"Larva";724;2
"Unit";"Roach";"Larva";726;2
"Unit";"Roach";"Larva";728;2
"Unit";"Roach";"Larva";730;2
"Unit";"Roach";"Larva";732;2
"Unit";"Roach";"Larva";734;2
"Unit";"Roach";"Larva";736;2
"Unit";"Roach";"Larva";738;2
"Unit";"Roach";"Larva";740;2
"Unit";"Roach";"Larva";742;2
"Unit";"Roach";"Larva";744;2
"Unit";"Roach";"Larva";746;2
"Unit";"Roach";"Larva";754;2
"Unit";"Roach";"Larva";756;2
"Unit";"Roach";"Larva";758;2
"Unit";"Roach";"Larva";760;2
"Unit";"Roach";"Larva";762;2
"Building";"Extractor";NA;764;0
"Unit";"Roach";"Larva";764;2
"Unit";"Roach";"Larva";766;2
"Unit";"Roach";"Larva";768;2
"Upgrade";"zerglingmovementspeed";NA;770;0
"Upgrade";"SprayZerg";NA;770;0
"Upgrade";"SprayZerg";NA;770;0
"Upgrade";"SprayZerg";NA;770;0
"Upgrade";"SprayZerg";NA;770;0
"Upgrade";"SprayZerg";NA;770;0
"Upgrade";"SprayZerg";NA;770;0
"Upgrade";"ZergMissileWeaponsLevel1";NA;770;0
"Upgrade";"SprayZerg";NA;770;0
"Upgrade";"ZergMissileWeaponsLevel2";NA;770;0
"Upgrade";"ZergGroundArmorsLevel1";NA;770;0
"Upgrade";"SprayZerg";NA;770;0
"Upgrade";"overlordspeed";NA;770;0
"Upgrade";"ZergGroundArmorsLevel2";NA;770;0
"Upgrade";"SprayZerg";NA;770;0
"Upgrade";"EvolveMuscularAugments";NA;770;0
"Upgrade";"SprayZerg";NA;770;0
"Upgrade";"SprayZerg";NA;770;0
"Upgrade";"SprayZerg";NA;770;0
