"type";"unit_name";"on_building";"total_supply_lag";"supply"
"Building";"Barracks";NA;16;0
"Building";"Refinery";NA;16;0
"Unit";"Reaper";"Barracks";19;1
"Building";"CommandCenter";NA;20;0
"Building";"Barracks";NA;20;0
"Building";"BarracksReactor";NA;21;0
"Building";"Refinery";NA;22;0
"Building";"Factory";NA;23;0
"Unit";"Marine";"Barracks";24;1
"Unit";"Marine";"Barracks";25;1
"Building";"BarracksTechLab";NA;26;0
"Unit";"Marine";"Barracks";27;1
"Unit";"Marine";"Barracks";28;1
"Unit";"Marine";"Barracks";30;1
"Unit";"Marine";"Barracks";31;1
"Unit";"Marine";"Barracks";32;1
"Unit";"Marine";"Barracks";35;1
"Building";"Starport";NA;36;0
"Unit";"Marine";"Barracks";36;1
"Upgrade";"Stimpack";"TechLab";38;0
"Unit";"Marine";"Barracks";38;1
"Building";"FactoryReactor";NA;40;0
"Unit";"Marine";"Barracks";41;1
"Unit";"Marine";"Barracks";42;1
"Unit";"Marine";"Barracks";45;1
"Unit";"Marine";"Barracks";46;1
"Unit";"Marine";"Barracks";48;1
"Unit";"Marine";"Barracks";51;1
"Unit";"Marine";"Barracks";52;1
"Unit";"Medivac";"Starport";53;2
"Unit";"Medivac";"Starport";55;2
"Unit";"Marine";"Barracks";58;1
"Building";"EngineeringBay";NA;60;0
"Building";"EngineeringBay";NA;60;0
"Unit";"Marine";"Barracks";61;1
"Unit";"Marine";"Barracks";62;1
"Unit";"Marine";"Barracks";64;1
"Unit";"Marine";"Barracks";67;1
"Unit";"Marine";"Barracks";68;1
"Unit";"Marine";"Barracks";69;1
"Unit";"Medivac";"Starport";70;2
"Unit";"Marine";"Barracks";74;1
"Unit";"Marine";"Barracks";75;1
"Unit";"Marine";"Barracks";76;1
"Building";"CommandCenter";NA;77;0
"Upgrade";"TerranInfantryWeaponsLevel1";"EngineeringBay";77;0
"Unit";"Marine";"Barracks";79;1
"Unit";"Marine";"Barracks";80;1
"Unit";"Marine";"Barracks";81;1
"Building";"Barracks";NA;83;0
"Building";"Barracks";NA;83;0
"Building";"Barracks";NA;83;0
"Unit";"Marine";"Barracks";83;1
"Unit";"Marine";"Barracks";84;1
"Unit";"Marine";"Barracks";85;1
"Building";"FactoryTechLab";NA;86;0
"Unit";"Medivac";"Starport";88;2
"Unit";"Medivac";"Starport";90;2
"Building";"Refinery";NA;92;0
"Building";"Refinery";NA;92;0
"Building";"Armory";NA;93;0
"Unit";"Marine";"Barracks";94;1
"Building";"BarracksReactor";NA;96;0
"Building";"BarracksReactor";NA;96;0
"Unit";"Marine";"Barracks";96;1
"Building";"BarracksReactor";NA;97;0
"Unit";"Marauder";"Barracks";99;2
"Unit";"Marine";"Barracks";101;1
"Unit";"Marine";"Barracks";103;1
"Unit";"Medivac";"Starport";104;2
"Unit";"Marine";"Barracks";108;1
"Unit";"Marine";"Barracks";109;1
"Unit";"Marine";"Barracks";110;1
"Unit";"Marine";"Barracks";111;1
"Unit";"Marine";"Barracks";112;1
"Unit";"Marine";"Barracks";113;1
"Unit";"Marine";"Barracks";114;1
"Unit";"Marine";"Barracks";116;1
"Unit";"Marine";"Barracks";117;1
"Building";"Refinery";NA;119;0
"Unit";"Marine";"Barracks";119;1
"Building";"Refinery";NA;121;0
"Unit";"Marauder";"Barracks";125;2
"Upgrade";"TerranInfantryWeaponsLevel2";"EngineeringBay";127;0
"Unit";"Marine";"Barracks";127;1
"Unit";"Medivac";"Starport";128;2
"Unit";"Medivac";"Starport";130;2
"Unit";"Marine";"Barracks";132;1
"Unit";"Marine";"Barracks";133;1
"Unit";"Marine";"Barracks";134;1
"Unit";"Marine";"Barracks";135;1
"Unit";"Marine";"Barracks";136;1
"Unit";"Marine";"Barracks";137;1
"Unit";"Marauder";"Barracks";141;2
"Unit";"Marine";"Barracks";143;1
"Unit";"Marine";"Barracks";146;1
"Unit";"Marine";"Barracks";147;1
"Unit";"Marine";"Barracks";148;1
"Unit";"Marine";"Barracks";149;1
"Unit";"Marine";"Barracks";150;1
"Unit";"Marine";"Barracks";151;1
"Unit";"Marine";"Barracks";152;1
"Building";"Barracks";NA;153;0
"Building";"Barracks";NA;153;0
"Unit";"Marine";"Barracks";153;1
"Building";"Barracks";NA;154;0
"Unit";"Marine";"Barracks";154;1
"Unit";"Marine";"Barracks";155;1
"Unit";"Marine";"Barracks";156;1
"Unit";"Marine";"Barracks";157;1
"Unit";"Marine";"Barracks";158;1
"Unit";"Marauder";"Barracks";159;2
"Unit";"Marine";"Barracks";161;1
"Unit";"Marine";"Barracks";162;1
"Unit";"Marine";"Barracks";163;1
"Unit";"Marine";"Barracks";164;1
"Unit";"Marine";"Barracks";165;1
"Unit";"Marine";"Barracks";166;1
"Unit";"Marine";"Barracks";167;1
"Unit";"Marauder";"Barracks";168;2
"Building";"BarracksTechLab";NA;170;0
"Building";"BarracksTechLab";NA;170;0
"Building";"BarracksTechLab";NA;170;0
"Unit";"Marine";"Barracks";170;1
"Unit";"Marine";"Barracks";171;1
"Unit";"Marine";"Barracks";172;1
"Unit";"Marine";"Barracks";173;1
"Unit";"Marine";"Barracks";174;1
"Unit";"Marine";"Barracks";175;1
"Unit";"Marine";"Barracks";176;1
"Unit";"Marine";"Barracks";177;1
"Unit";"Marauder";"Barracks";178;2
"Unit";"Marine";"Barracks";180;1
"Unit";"Marauder";"Barracks";181;2
"Unit";"Marauder";"Barracks";183;2
"Building";"CommandCenter";NA;185;0
"Upgrade";"TerranVehicleWeaponsLevel1";"Armory";185;0
"Unit";"Marauder";"Barracks";185;2
"Unit";"Marauder";"Barracks";187;2
"Unit";"Marauder";"Barracks";189;2
"Unit";"Marine";"Barracks";191;1
"Unit";"Marine";"Barracks";192;1
"Unit";"Marine";"Barracks";193;1
"Unit";"Marine";"Barracks";194;1
"Upgrade";"TerranInfantryWeaponsLevel3";"EngineeringBay";195;0
"Unit";"Marauder";"Barracks";195;2
"Unit";"Marauder";"Barracks";198;2
"Unit";"Marine";"Barracks";200;1
"Unit";"Marine";"Barracks";201;1
"Unit";"Marauder";"Barracks";202;2
"Unit";"Marauder";"Barracks";204;2
"Unit";"Marine";"Barracks";206;1
"Unit";"Marine";"Barracks";207;1
"Unit";"Marine";"Barracks";208;1
"Unit";"Marine";"Barracks";209;1
"Unit";"Marauder";"Barracks";210;2
"Unit";"Marauder";"Barracks";212;2
"Unit";"Marine";"Barracks";214;1
"Unit";"Marine";"Barracks";215;1
"Unit";"Marine";"Barracks";216;1
"Unit";"Marine";"Barracks";217;1
"Unit";"Marine";"Barracks";218;1
"Unit";"Marine";"Barracks";219;1
"Unit";"Marine";"Barracks";220;1
"Unit";"Marine";"Barracks";221;1
"Unit";"Marine";"Barracks";222;1
"Building";"SensorTower";NA;223;0
"Unit";"Marine";"Barracks";223;1
"Unit";"Marauder";"Barracks";224;2
"Unit";"Marine";"Barracks";226;1
"Unit";"Marine";"Barracks";227;1
"Unit";"Marine";"Barracks";228;1
"Unit";"Marine";"Barracks";229;1
"Unit";"Marine";"Barracks";230;1
"Unit";"Marine";"Barracks";231;1
"Unit";"Marauder";"Barracks";232;2
"Unit";"Marauder";"Barracks";234;2
"Unit";"Marauder";"Barracks";236;2
"Unit";"Marine";"Barracks";238;1
"Unit";"Marauder";"Barracks";239;2
"Unit";"Marine";"Barracks";241;1
"Unit";"Marine";"Barracks";242;1
"Unit";"Marine";"Barracks";243;1
"Unit";"Marine";"Barracks";244;1
"Unit";"Marine";"Barracks";245;1
"Unit";"Marine";"Barracks";246;1
"Unit";"Marine";"Barracks";247;1
"Unit";"Marine";"Barracks";248;1
"Unit";"Medivac";"Starport";249;2
"Unit";"Medivac";"Starport";251;2
"Unit";"Marine";"Barracks";253;1
"Unit";"Marine";"Barracks";254;1
"Unit";"Marine";"Barracks";255;1
"Unit";"Marine";"Barracks";256;1
"Unit";"Marine";"Barracks";257;1
"Unit";"Marine";"Barracks";258;1
"Unit";"Marine";"Barracks";259;1
"Unit";"Marine";"Barracks";260;1
"Unit";"Marine";"Barracks";261;1
"Unit";"Marine";"Barracks";262;1
"Unit";"Marauder";"Barracks";263;2
"Unit";"Marauder";"Barracks";265;2
"Unit";"Marine";"Barracks";267;1
"Unit";"Marine";"Barracks";268;1
"Unit";"Marauder";"Barracks";269;2
"Unit";"Marine";"Barracks";271;1
"Unit";"Marine";"Barracks";272;1
"Unit";"Marine";"Barracks";273;1
"Unit";"Marine";"Barracks";274;1
"Unit";"Marine";"Barracks";275;1
"Unit";"Marine";"Barracks";276;1
"Unit";"Marine";"Barracks";277;1
"Unit";"Marauder";"Barracks";278;2
"Unit";"Marauder";"Barracks";280;2
"Unit";"Marauder";"Barracks";282;2
"Unit";"Marine";"Barracks";284;1
"Unit";"Marine";"Barracks";285;1
"Building";"Starport";NA;286;0
"Building";"Starport";NA;286;0
"Building";"CommandCenter";NA;286;0
"Unit";"Marauder";"Barracks";286;2
"Unit";"Marauder";"Barracks";288;2
"Unit";"Marauder";"Barracks";290;2
"Unit";"Marauder";"Barracks";292;2
"Unit";"Marauder";"Barracks";294;2
"Unit";"Marauder";"Barracks";296;2
"Unit";"Marauder";"Barracks";298;2
"Unit";"Marauder";"Barracks";300;2
"Unit";"Marine";"Barracks";302;1
"Unit";"Medivac";"Starport";303;2
"Unit";"Medivac";"Starport";305;2
"Unit";"Medivac";"Starport";307;2
"Unit";"Medivac";"Starport";309;2
"Upgrade";"TerranShipWeaponsLevel1";"Armory";311;0
"Unit";"Marauder";"Barracks";311;2
"Unit";"Marauder";"Barracks";313;2
"Unit";"Marauder";"Barracks";315;2
"Unit";"Marauder";"Barracks";317;2
"Unit";"Marine";"Barracks";319;1
"Unit";"Marine";"Barracks";320;1
"Unit";"Marine";"Barracks";321;1
"Unit";"Marine";"Barracks";322;1
"Unit";"Marine";"Barracks";323;1
"Unit";"Marine";"Barracks";324;1
"Unit";"Marine";"Barracks";325;1
"Unit";"Medivac";"Starport";326;2
"Unit";"Medivac";"Starport";328;2
"Unit";"Medivac";"Starport";330;2
"Unit";"Medivac";"Starport";332;2
"Unit";"Marauder";"Barracks";334;2
"Unit";"Marine";"Barracks";336;1
"Unit";"Marauder";"Barracks";337;2
"Unit";"Marine";"Barracks";339;1
"Unit";"Marine";"Barracks";340;1
"Unit";"Marine";"Barracks";341;1
"Unit";"Marine";"Barracks";342;1
"Unit";"Marine";"Barracks";343;1
"Unit";"Marine";"Barracks";344;1
"Unit";"Marine";"Barracks";345;1
"Unit";"Marine";"Barracks";346;1
"Unit";"Marauder";"Barracks";347;2
"Unit";"Marine";"Barracks";349;1
"Unit";"Marauder";"Barracks";350;2
"Unit";"Marine";"Barracks";352;1
"Unit";"Marauder";"Barracks";353;2
"Unit";"Marine";"Barracks";355;1
"Unit";"Marauder";"Barracks";356;2
"Unit";"Marauder";"Barracks";358;2
"Unit";"Marine";"Barracks";360;1
"Unit";"Marine";"Barracks";361;1
"Unit";"Marine";"Barracks";362;1
"Unit";"Marine";"Barracks";363;1
"Unit";"Marine";"Barracks";364;1
"Unit";"Marine";"Barracks";365;1
"Unit";"Marine";"Barracks";366;1
"Upgrade";"SprayTerran";NA;367;0
"Upgrade";"SprayTerran";NA;367;0
"Upgrade";"SprayTerran";NA;367;0
"Upgrade";"ShieldWall";NA;367;0
"Upgrade";"SprayTerran";NA;367;0
"Upgrade";"TerranInfantryArmorsLevel1";NA;367;0
"Upgrade";"PunisherGrenades";NA;367;0
"Upgrade";"TerranInfantryArmorsLevel2";NA;367;0
"Upgrade";"SprayTerran";NA;367;0
"Upgrade";"SprayTerran";NA;367;0
"Upgrade";"SprayTerran";NA;367;0
"Upgrade";"TerranInfantryArmorsLevel3";NA;367;0
"Upgrade";"SprayTerran";NA;367;0
"Upgrade";"SprayTerran";NA;367;0
