"type";"unit_name";"on_building";"total_supply_lag";"supply"
"Building";"Refinery";NA;15;0
"Building";"Barracks";NA;16;0
"Unit";"Reaper";"Barracks";19;1
"Building";"CommandCenter";NA;20;0
"Building";"Factory";NA;20;0
"Building";"BarracksReactor";NA;21;0
"Building";"Refinery";NA;22;0
"Building";"Starport";NA;24;0
"Unit";"Marine";"Barracks";24;1
"Unit";"Marine";"Barracks";25;1
"Building";"FactoryTechLab";NA;26;0
"Unit";"Marine";"Barracks";27;1
"Unit";"Marine";"Barracks";29;1
"Unit";"Marine";"Barracks";31;1
"Unit";"Marine";"Barracks";32;1
"Unit";"Marine";"Barracks";36;1
"Unit";"Marine";"Barracks";37;1
"Unit";"Marine";"Barracks";41;1
"Unit";"Marine";"Barracks";42;1
"Building";"CommandCenter";NA;45;0
"Building";"Bunker";NA;48;0
"Building";"StarportTechLab";NA;48;0
"Unit";"Marine";"Barracks";50;1
"Unit";"Marine";"Barracks";51;1
"Building";"StarportReactor";NA;54;0
"Building";"Barracks";NA;54;0
"Building";"FactoryReactor";NA;56;0
"Building";"Barracks";NA;56;0
"Unit";"Marine";"Barracks";56;1
"Building";"EngineeringBay";NA;57;0
"Building";"Refinery";NA;59;0
"Unit";"Marine";"Barracks";60;1
"Building";"Barracks";NA;62;0
"Building";"Barracks";NA;62;0
"Unit";"Medivac";"Starport";62;2
"Unit";"Medivac";"Starport";64;2
"Upgrade";"Stimpack";"TechLab";67;0
"Building";"MissileTurret";NA;67;0
"Building";"Refinery";NA;67;0
"Unit";"Marine";"Barracks";68;1
"Unit";"Marine";"Barracks";70;1
"Unit";"Marine";"Barracks";71;1
"Unit";"Marauder";"Barracks";73;2
"Unit";"Marauder";"Barracks";75;2
"Unit";"Medivac";"Starport";79;2
"Unit";"Medivac";"Starport";81;2
"Upgrade";"TerranInfantryWeaponsLevel1";"EngineeringBay";83;0
"Unit";"Marine";"Barracks";84;1
"Unit";"Marine";"Barracks";85;1
"Unit";"Marine";"Barracks";87;1
"Building";"BarracksReactor";NA;88;0
"Building";"BarracksTechLab";NA;88;0
"Unit";"Marine";"Barracks";90;1
"Unit";"Marine";"Barracks";92;1
"Unit";"Marine";"Barracks";93;1
"Building";"MissileTurret";NA;96;0
"Unit";"Marine";"Barracks";96;1
"Unit";"Marine";"Barracks";97;1
"Unit";"Liberator";"Starport";99;3
"Unit";"Liberator";"Starport";103;3
"Unit";"Marine";"Barracks";106;1
"Unit";"Marine";"Barracks";107;1
"Unit";"Marine";"Barracks";108;1
"Unit";"Marine";"Barracks";109;1
"Building";"Refinery";NA;110;0
"Unit";"Marine";"Barracks";110;1
"Building";"Refinery";NA;114;0
"Unit";"Marine";"Barracks";115;1
"Unit";"Marine";"Barracks";116;1
"Unit";"Marine";"Barracks";117;1
"Unit";"Marauder";"Barracks";118;2
"Unit";"Marauder";"Barracks";120;2
"Unit";"Marine";"Barracks";122;1
"Unit";"Marine";"Barracks";123;1
"Unit";"Liberator";"Starport";124;3
"Unit";"Marine";"Barracks";127;1
"Unit";"Marine";"Barracks";128;1
"Unit";"Liberator";"Starport";129;3
"Building";"MissileTurret";NA;132;0
"Building";"MissileTurret";NA;132;0
"Building";"Armory";NA;132;0
"Unit";"Marine";"Barracks";132;1
"Unit";"Marine";"Barracks";133;1
"Unit";"Marine";"Barracks";137;1
"Unit";"Marine";"Barracks";138;1
"Unit";"Marauder";"Barracks";142;2
"Unit";"Marauder";"Barracks";144;2
"Building";"EngineeringBay";NA;149;0
"Unit";"Marauder";"Barracks";152;2
"Unit";"Marauder";"Barracks";154;2
"Unit";"Marine";"Barracks";156;1
"Unit";"Marine";"Barracks";157;1
"Unit";"Marine";"Barracks";158;1
"Unit";"Marauder";"Barracks";162;2
"Unit";"Marine";"Barracks";164;1
"Unit";"Liberator";"Starport";165;3
"Unit";"Marauder";"Barracks";169;2
"Unit";"Marine";"Barracks";172;1
"Unit";"Marauder";"Barracks";176;2
"Unit";"Marine";"Barracks";178;1
"Unit";"Marauder";"Barracks";180;2
"Unit";"Liberator";"Starport";182;3
"Unit";"Marauder";"Barracks";187;2
"Unit";"Marine";"Barracks";189;1
"Unit";"Marine";"Barracks";190;1
"Unit";"Marine";"Barracks";191;1
"Unit";"Marauder";"Barracks";194;2
"Upgrade";"TerranInfantryWeaponsLevel2";"EngineeringBay";196;0
"Unit";"Marine";"Barracks";196;1
"Unit";"Marine";"Barracks";197;1
"Unit";"Marine";"Barracks";201;1
"Unit";"Marine";"Barracks";202;1
"Building";"CommandCenter";NA;203;0
"Unit";"Marine";"Barracks";203;1
"Unit";"Marine";"Barracks";204;1
"Unit";"Marine";"Barracks";205;1
"Unit";"Marine";"Barracks";206;1
"Unit";"Marauder";"Barracks";207;2
"Unit";"Marauder";"Barracks";209;2
"Building";"Starport";NA;211;0
"Unit";"Marine";"Barracks";211;1
"Unit";"Marine";"Barracks";212;1
"Unit";"Marine";"Barracks";213;1
"Unit";"Marine";"Barracks";216;1
"Unit";"Marine";"Barracks";217;1
"Unit";"Marine";"Barracks";219;1
"Unit";"Marine";"Barracks";220;1
"Unit";"Marine";"Barracks";221;1
"Unit";"Medivac";"Starport";222;2
"Unit";"Medivac";"Starport";224;2
"Unit";"Marine";"Barracks";226;1
"Unit";"Marine";"Barracks";227;1
"Unit";"Marauder";"Barracks";228;2
"Unit";"Marauder";"Barracks";230;2
"Building";"GhostAcademy";NA;232;0
"Building";"SensorTower";NA;232;0
"Upgrade";"TerranShipWeaponsLevel1";"Armory";235;0
"Unit";"Marine";"Barracks";235;1
"Unit";"Marine";"Barracks";236;1
"Unit";"Marine";"Barracks";237;1
"Unit";"Marine";"Barracks";238;1
"Unit";"Marine";"Barracks";239;1
"Unit";"Ghost";"Barracks";240;2
"Unit";"Ghost";"Barracks";242;2
"Unit";"Marine";"Barracks";244;1
"Unit";"Marine";"Barracks";245;1
"Unit";"Ghost";"Barracks";246;2
"Unit";"Ghost";"Barracks";248;2
"Unit";"Marauder";"Barracks";250;2
"Unit";"Marauder";"Barracks";252;2
"Unit";"Marine";"Barracks";254;1
"Unit";"Marine";"Barracks";255;1
"Upgrade";"TerranInfantryWeaponsLevel3";"EngineeringBay";256;0
"Unit";"Marine";"Barracks";258;1
"Unit";"Liberator";"Starport";259;3
"Unit";"Liberator";"Starport";262;3
"Unit";"Liberator";"Starport";265;3
"Unit";"Liberator";"Starport";268;3
"Building";"CommandCenter";NA;271;0
"Unit";"Marine";"Barracks";274;1
"Unit";"Marine";"Barracks";275;1
"Unit";"Marine";"Barracks";276;1
"Unit";"Marine";"Barracks";278;1
"Unit";"Marauder";"Barracks";279;2
"Unit";"Marauder";"Barracks";281;2
"Unit";"Marine";"Barracks";283;1
"Unit";"Marine";"Barracks";284;1
"Unit";"Marine";"Barracks";285;1
"Unit";"Marine";"Barracks";286;1
"Unit";"Marine";"Barracks";288;1
"Unit";"Liberator";"Starport";289;3
"Unit";"Marine";"Barracks";292;1
"Unit";"Marine";"Barracks";293;1
"Unit";"Marine";"Barracks";294;1
"Unit";"Marine";"Barracks";295;1
"Unit";"Marine";"Barracks";296;1
"Building";"SensorTower";NA;297;0
"Unit";"Liberator";"Starport";297;3
"Building";"Refinery";NA;300;0
"Unit";"Liberator";"Starport";300;3
"Building";"Refinery";NA;303;0
"Unit";"Marine";"Barracks";304;1
"Unit";"Marine";"Barracks";305;1
"Unit";"Marine";"Barracks";306;1
"Unit";"Liberator";"Starport";307;3
"Unit";"Marine";"Barracks";310;1
"Unit";"Marauder";"Barracks";311;2
"Unit";"Marauder";"Barracks";313;2
"Unit";"Marine";"Barracks";315;1
"Unit";"Marine";"Barracks";316;1
"Unit";"Marine";"Barracks";317;1
"Unit";"Marine";"Barracks";318;1
"Unit";"Marine";"Barracks";319;1
"Upgrade";"SprayTerran";NA;320;0
"Upgrade";"SprayTerran";NA;320;0
"Upgrade";"SprayTerran";NA;320;0
"Upgrade";"SprayTerran";NA;320;0
"Upgrade";"PunisherGrenades";NA;320;0
"Upgrade";"ShieldWall";NA;320;0
"Upgrade";"SprayTerran";NA;320;0
"Upgrade";"SprayTerran";NA;320;0
"Upgrade";"TerranInfantryArmorsLevel1";NA;320;0
"Upgrade";"SprayTerran";NA;320;0
"Upgrade";"TerranInfantryArmorsLevel2";NA;320;0
"Upgrade";"SprayTerran";NA;320;0
