"type";"unit_name";"on_building";"total_supply_lag";"supply"
"Building";"Barracks";NA;16;0
"Building";"Refinery";NA;16;0
"Unit";"Marine";"Barracks";19;1
"Building";"CommandCenter";NA;20;0
"Building";"Factory";NA;21;0
"Building";"BarracksReactor";NA;21;0
"Building";"Refinery";NA;22;0
"Unit";"Marine";"Barracks";24;1
"Unit";"Marine";"Barracks";25;1
"Building";"Starport";NA;26;0
"Building";"FactoryTechLab";NA;26;0
"Unit";"Marine";"Barracks";27;1
"Unit";"Marine";"Barracks";28;1
"Unit";"Marine";"Barracks";30;1
"Unit";"Marine";"Barracks";31;1
"Unit";"Banshee";"Starport";34;3
"Unit";"Marine";"Barracks";39;1
"Unit";"Marine";"Barracks";40;1
"Unit";"Marine";"Barracks";43;1
"Unit";"Marine";"Barracks";44;1
"Unit";"Banshee";"Starport";49;3
"Building";"Barracks";NA;52;0
"Building";"Barracks";NA;52;0
"Unit";"Marine";"Barracks";52;1
"Unit";"Marine";"Barracks";53;1
"Building";"FactoryTechLab";NA;56;0
"Building";"EngineeringBay";NA;56;0
"Building";"Refinery";NA;58;0
"Unit";"Marine";"Barracks";58;1
"Unit";"Marine";"Barracks";59;1
"Unit";"Banshee";"Starport";63;3
"Unit";"Marine";"Barracks";70;1
"Unit";"Marine";"Barracks";71;1
"Building";"FactoryReactor";NA;74;0
"Unit";"Marauder";"Barracks";78;2
"Unit";"Marine";"Barracks";80;1
"Unit";"Marine";"Barracks";81;1
"Unit";"Marine";"Barracks";82;1
"Building";"Refinery";NA;83;0
"Building";"CommandCenter";NA;83;0
"Upgrade";"Stimpack";"TechLab";85;0
"Building";"FactoryReactor";NA;87;0
"Unit";"Marauder";"Barracks";87;2
"Unit";"Marauder";"Barracks";89;2
"Unit";"Marine";"Barracks";91;1
"Unit";"Marine";"Barracks";92;1
"Building";"Bunker";NA;93;0
"Upgrade";"TerranInfantryWeaponsLevel1";"EngineeringBay";93;0
"Unit";"Medivac";"Starport";93;2
"Unit";"Marine";"Barracks";95;1
"Unit";"Marine";"Barracks";96;1
"Unit";"Marauder";"Barracks";97;2
"Unit";"Marauder";"Barracks";99;2
"Unit";"Medivac";"Starport";101;2
"Unit";"Marine";"Barracks";103;1
"Unit";"Marine";"Barracks";106;1
"Unit";"Marauder";"Barracks";107;2
"Unit";"Marauder";"Barracks";115;2
"Unit";"Marauder";"Barracks";117;2
"Unit";"Marine";"Barracks";119;1
"Unit";"Marine";"Barracks";120;1
"Building";"Barracks";NA;124;0
"Building";"Barracks";NA;124;0
"Unit";"Medivac";"Starport";124;2
"Unit";"Medivac";"Starport";126;2
"Unit";"Marine";"Barracks";130;1
"Unit";"Marine";"Barracks";131;1
"Unit";"Marauder";"Barracks";132;2
"Unit";"Marauder";"Barracks";134;2
"Unit";"Marine";"Barracks";136;1
"Unit";"Marine";"Barracks";137;1
"Unit";"Marauder";"Barracks";138;2
"Unit";"Marauder";"Barracks";140;2
"Building";"BarracksReactor";NA;145;0
"Building";"BarracksTechLab";NA;145;0
"Unit";"Medivac";"Starport";145;2
"Unit";"Medivac";"Starport";147;2
"Unit";"Marine";"Barracks";155;1
"Unit";"Marine";"Barracks";156;1
"Unit";"Marauder";"Barracks";157;2
"Unit";"Marauder";"Barracks";159;2
"Unit";"Marauder";"Barracks";161;2
"Building";"Refinery";NA;163;0
"Building";"Refinery";NA;163;0
"Unit";"Marauder";"Barracks";168;2
"Unit";"Marauder";"Barracks";171;2
"Unit";"Marine";"Barracks";173;1
"Unit";"Marine";"Barracks";174;1
"Building";"Armory";NA;176;0
"Building";"EngineeringBay";NA;176;0
"Building";"Starport";NA;176;0
"Building";"FusionCore";NA;176;0
"Unit";"Marauder";"Barracks";176;2
"Unit";"Marauder";"Barracks";178;2
"Unit";"Marauder";"Barracks";180;2
"Unit";"Marine";"Barracks";182;1
"Unit";"Marine";"Barracks";183;1
"Unit";"Marine";"Barracks";184;1
"Unit";"Marine";"Barracks";185;1
"Unit";"Liberator";"Starport";186;3
"Unit";"Liberator";"Starport";189;3
"Building";"StarportTechLab";NA;192;0
"Unit";"Marauder";"Barracks";192;2
"Unit";"Marine";"Barracks";194;1
"Unit";"Marine";"Barracks";195;1
"Unit";"Liberator";"Starport";196;3
"Unit";"Marine";"Barracks";199;1
"Unit";"Marine";"Barracks";200;1
"Unit";"Marauder";"Barracks";201;2
"Building";"CommandCenter";NA;203;0
"Unit";"Marauder";"Barracks";203;2
"Unit";"Liberator";"Starport";205;3
"Unit";"Liberator";"Starport";208;3
"Unit";"Marauder";"Barracks";211;2
"Unit";"Marauder";"Barracks";213;2
"Unit";"Marine";"Barracks";215;1
"Unit";"Marine";"Barracks";216;1
"Unit";"Marine";"Barracks";217;1
"Unit";"Marine";"Barracks";218;1
"Unit";"Liberator";"Starport";219;3
"Unit";"Marauder";"Barracks";222;2
"Unit";"Marauder";"Barracks";224;2
"Unit";"Marine";"Barracks";226;1
"Unit";"Marauder";"Barracks";227;2
"Unit";"Marine";"Barracks";229;1
"Unit";"Liberator";"Starport";230;3
"Unit";"Marine";"Barracks";233;1
"Unit";"Marine";"Barracks";234;1
"Upgrade";"TerranInfantryWeaponsLevel2";"EngineeringBay";235;0
"Building";"Barracks";NA;235;0
"Building";"Barracks";NA;235;0
"Building";"Barracks";NA;235;0
"Unit";"Marauder";"Barracks";235;2
"Unit";"Marauder";"Barracks";237;2
"Unit";"Marauder";"Barracks";239;2
"Unit";"Marine";"Barracks";241;1
"Unit";"Marine";"Barracks";242;1
"Unit";"Marine";"Barracks";243;1
"Unit";"Marine";"Barracks";244;1
"Unit";"Marauder";"Barracks";245;2
"Unit";"Marauder";"Barracks";247;2
"Building";"GhostAcademy";NA;249;0
"Unit";"Marauder";"Barracks";249;2
"Unit";"Marine";"Barracks";251;1
"Unit";"Marine";"Barracks";252;1
"Unit";"Marine";"Barracks";253;1
"Unit";"Marine";"Barracks";254;1
"Unit";"Marauder";"Barracks";255;2
"Unit";"Marauder";"Barracks";257;2
"Unit";"Marine";"Barracks";259;1
"Unit";"Marine";"Barracks";260;1
"Unit";"Marine";"Barracks";261;1
"Unit";"Marine";"Barracks";262;1
"Unit";"Marine";"Barracks";263;1
"Unit";"Marauder";"Barracks";264;2
"Unit";"Marine";"Barracks";266;1
"Unit";"Medivac";"Starport";267;2
"Unit";"Medivac";"Starport";269;2
"Unit";"Medivac";"Starport";271;2
"Building";"BarracksTechLab";NA;273;0
"Building";"BarracksTechLab";NA;273;0
"Building";"BarracksReactor";NA;273;0
"Unit";"Marauder";"Barracks";273;2
"Unit";"Marine";"Barracks";275;1
"Unit";"Marine";"Barracks";276;1
"Unit";"Marine";"Barracks";277;1
"Unit";"Marauder";"Barracks";278;2
"Unit";"Marine";"Barracks";280;1
"Building";"MissileTurret";NA;281;0
"Building";"MissileTurret";NA;281;0
"Unit";"Marauder";"Barracks";281;2
"Unit";"Ghost";"Barracks";283;2
"Unit";"Ghost";"Barracks";285;2
"Unit";"Ghost";"Barracks";287;2
"Unit";"Ghost";"Barracks";289;2
"Unit";"Marine";"Barracks";291;1
"Unit";"Marine";"Barracks";292;1
"Unit";"Marine";"Barracks";293;1
"Unit";"Marine";"Barracks";294;1
"Unit";"Marine";"Barracks";295;1
"Unit";"Marine";"Barracks";296;1
"Upgrade";"SprayTerran";NA;297;0
"Upgrade";"SprayTerran";NA;297;0
"Upgrade";"BansheeCloak";NA;297;0
"Upgrade";"SprayTerran";NA;297;0
"Upgrade";"SprayTerran";NA;297;0
"Upgrade";"PunisherGrenades";NA;297;0
"Upgrade";"ShieldWall";NA;297;0
"Upgrade";"TerranInfantryArmorsLevel1";NA;297;0
"Upgrade";"SprayTerran";NA;297;0
"Upgrade";"LiberatorAGRangeUpgrade";NA;297;0
"Upgrade";"SprayTerran";NA;297;0
"Upgrade";"TerranInfantryArmorsLevel2";NA;297;0
