"type";"unit_name";"on_building";"total_supply_lag";"supply"
"Building";"Barracks";NA;16;0
"Building";"Refinery";NA;16;0
"Building";"BarracksReactor";NA;19;0
"Building";"CommandCenter";NA;19;0
"Building";"Refinery";NA;20;0
"Unit";"Reaper";"Barracks";20;1
"Unit";"Reaper";"Barracks";21;1
"Building";"Barracks";NA;23;0
"Unit";"Reaper";"Barracks";25;1
"Unit";"Reaper";"Barracks";26;1
"Building";"Factory";NA;28;0
"Building";"BarracksTechLab";NA;29;0
"Unit";"Marine";"Barracks";30;1
"Unit";"Marine";"Barracks";31;1
"Unit";"Marine";"Barracks";34;1
"Unit";"Marine";"Barracks";35;1
"Unit";"Marine";"Barracks";37;1
"Building";"FactoryReactor";NA;39;0
"Building";"Starport";NA;39;0
"Unit";"Marine";"Barracks";39;1
"Unit";"Marine";"Barracks";40;1
"Unit";"Marine";"Barracks";42;1
"Upgrade";"Stimpack";"TechLab";44;0
"Unit";"Marine";"Barracks";45;1
"Unit";"Marine";"Barracks";46;1
"Unit";"Marine";"Barracks";48;1
"Unit";"Marine";"Barracks";50;1
"Unit";"Marine";"Barracks";51;1
"Unit";"Medivac";"Starport";54;2
"Unit";"Medivac";"Starport";56;2
"Unit";"Marine";"Barracks";59;1
"Unit";"Marine";"Barracks";61;1
"Unit";"Marine";"Barracks";62;1
"Unit";"Marine";"Barracks";64;1
"Building";"CommandCenter";NA;66;0
"Building";"EngineeringBay";NA;67;0
"Building";"EngineeringBay";NA;67;0
"Unit";"Marine";"Barracks";68;1
"Unit";"Marine";"Barracks";69;1
"Unit";"Marine";"Barracks";70;1
"Building";"FactoryReactor";NA;72;0
"Building";"Barracks";NA;73;0
"Building";"Refinery";NA;73;0
"Unit";"Marine";"Barracks";73;1
"Unit";"Marine";"Barracks";74;1
"Unit";"Marine";"Barracks";75;1
"Building";"Barracks";NA;76;0
"Building";"Barracks";NA;76;0
"Unit";"Marine";"Barracks";78;1
"Unit";"Marine";"Barracks";79;1
"Unit";"Marine";"Barracks";80;1
"Building";"Refinery";NA;83;0
"Unit";"Medivac";"Starport";83;2
"Unit";"Medivac";"Starport";85;2
"Unit";"Marine";"Barracks";88;1
"Unit";"Marine";"Barracks";89;1
"Unit";"Marine";"Barracks";90;1
"Upgrade";"TerranInfantryWeaponsLevel1";"EngineeringBay";91;0
"Building";"FactoryReactor";NA;91;0
"Unit";"Marine";"Barracks";91;1
"Unit";"Marine";"Barracks";92;1
"Building";"BarracksReactor";NA;95;0
"Building";"BarracksReactor";NA;95;0
"Unit";"Medivac";"Starport";97;2
"Unit";"Medivac";"Starport";99;2
"Unit";"Marine";"Barracks";101;1
"Unit";"Marine";"Barracks";102;1
"Unit";"Marine";"Barracks";103;1
"Unit";"Marine";"Barracks";104;1
"Unit";"Marine";"Barracks";105;1
"Building";"Armory";NA;107;0
"Building";"Bunker";NA;110;0
"Unit";"Marine";"Barracks";110;1
"Unit";"Marine";"Barracks";111;1
"Unit";"Medivac";"Starport";112;2
"Unit";"Medivac";"Starport";114;2
"Unit";"Marine";"Barracks";116;1
"Unit";"Marine";"Barracks";117;1
"Unit";"Marine";"Barracks";119;1
"Unit";"Marine";"Barracks";120;1
"Unit";"Marine";"Barracks";121;1
"Unit";"Marine";"Barracks";122;1
"Unit";"Marine";"Barracks";123;1
"Unit";"Marine";"Barracks";126;1
"Building";"Factory";NA;127;0
"Building";"Barracks";NA;127;0
"Building";"Barracks";NA;127;0
"Unit";"Marine";"Barracks";127;1
"Unit";"Marine";"Barracks";128;1
"Unit";"Marine";"Barracks";129;1
"Unit";"Marine";"Barracks";130;1
"Unit";"Marine";"Barracks";131;1
"Unit";"Marine";"Barracks";134;1
"Unit";"Marine";"Barracks";135;1
"Unit";"Marine";"Barracks";136;1
"Unit";"Marine";"Barracks";137;1
"Unit";"Marine";"Barracks";139;1
"Unit";"Marine";"Barracks";140;1
"Unit";"Marine";"Barracks";142;1
"Unit";"Marine";"Barracks";143;1
"Unit";"Marine";"Barracks";144;1
"Unit";"Marine";"Barracks";145;1
"Unit";"Marine";"Barracks";149;1
"Unit";"Marine";"Barracks";150;1
"Building";"FactoryTechLab";NA;151;0
"Building";"BarracksTechLab";NA;151;0
"Building";"BarracksTechLab";NA;151;0
"Upgrade";"TerranInfantryWeaponsLevel2";"EngineeringBay";151;0
"Building";"Refinery";NA;151;0
"Unit";"Medivac";"Starport";151;2
"Unit";"Medivac";"Starport";153;2
"Building";"Bunker";NA;155;0
"Unit";"Marauder";"Barracks";157;2
"Unit";"Marine";"Barracks";159;1
"Unit";"Marine";"Barracks";160;1
"Unit";"Marine";"Barracks";161;1
"Unit";"Marine";"Barracks";162;1
"Unit";"Marine";"Barracks";163;1
"Unit";"Marine";"Barracks";164;1
"Unit";"Marine";"Barracks";165;1
"Unit";"Marauder";"Barracks";168;2
"Unit";"Marauder";"Barracks";170;2
"Unit";"Marauder";"Barracks";172;2
"Unit";"Marine";"Barracks";174;1
"Unit";"Marine";"Barracks";175;1
"Unit";"Marine";"Barracks";176;1
"Unit";"Marine";"Barracks";177;1
"Unit";"Marine";"Barracks";178;1
"Unit";"Marine";"Barracks";179;1
"Unit";"Marine";"Barracks";180;1
"Unit";"Medivac";"Starport";183;2
"Unit";"Marauder";"Barracks";186;2
"Unit";"Marauder";"Barracks";188;2
"Unit";"Marine";"Barracks";190;1
"Unit";"Marine";"Barracks";191;1
"Unit";"Marauder";"Barracks";192;2
"Unit";"Marine";"Barracks";194;1
"Unit";"Marine";"Barracks";195;1
"Unit";"Marauder";"Barracks";196;2
"Unit";"Marauder";"Barracks";198;2
"Unit";"Marine";"Barracks";200;1
"Unit";"Marine";"Barracks";201;1
"Unit";"Marine";"Barracks";202;1
"Unit";"Marauder";"Barracks";203;2
"Unit";"Marine";"Barracks";205;1
"Unit";"Marine";"Barracks";206;1
"Unit";"Marine";"Barracks";207;1
"Unit";"Marine";"Barracks";208;1
"Unit";"Marine";"Barracks";209;1
"Unit";"Marine";"Barracks";210;1
"Unit";"Marine";"Barracks";211;1
"Unit";"Marine";"Barracks";212;1
"Unit";"Marine";"Barracks";213;1
"Unit";"Marine";"Barracks";214;1
"Unit";"Marine";"Barracks";216;1
"Unit";"Marine";"Barracks";217;1
"Unit";"Marine";"Barracks";218;1
"Unit";"Marine";"Barracks";219;1
"Unit";"Marine";"Barracks";220;1
"Unit";"Marine";"Barracks";221;1
"Unit";"Marine";"Barracks";222;1
"Unit";"Marine";"Barracks";223;1
"Unit";"Marine";"Barracks";224;1
"Unit";"Marine";"Barracks";225;1
"Unit";"Marauder";"Barracks";228;2
"Unit";"Marauder";"Barracks";230;2
"Unit";"Marine";"Barracks";232;1
"Unit";"Marine";"Barracks";233;1
"Unit";"Marine";"Barracks";234;1
"Unit";"Marine";"Barracks";235;1
"Unit";"Marauder";"Barracks";237;2
"Unit";"Marauder";"Barracks";239;2
"Unit";"Marauder";"Barracks";241;2
"Unit";"Marine";"Barracks";243;1
"Unit";"Marine";"Barracks";244;1
"Unit";"Marine";"Barracks";245;1
"Unit";"Marine";"Barracks";246;1
"Unit";"Marine";"Barracks";247;1
"Unit";"Marine";"Barracks";248;1
"Unit";"Marine";"Barracks";249;1
"Unit";"Marine";"Barracks";250;1
"Unit";"Medivac";"Starport";251;2
"Unit";"Medivac";"Starport";253;2
"Unit";"Marauder";"Barracks";255;2
"Unit";"Marauder";"Barracks";257;2
"Unit";"Marauder";"Barracks";259;2
"Unit";"Marauder";"Barracks";263;2
"Unit";"Marauder";"Barracks";265;2
"Unit";"Marine";"Barracks";267;1
"Upgrade";"SprayTerran";NA;268;0
"Upgrade";"SprayTerran";NA;268;0
"Upgrade";"SprayTerran";NA;268;0
"Upgrade";"SprayTerran";NA;268;0
"Upgrade";"ShieldWall";NA;268;0
"Upgrade";"TerranInfantryArmorsLevel1";NA;268;0
"Upgrade";"PunisherGrenades";NA;268;0
"Upgrade";"DrillClaws";NA;268;0
"Upgrade";"TerranInfantryArmorsLevel2";NA;268;0
