"type";"unit_name";"on_building";"total_supply_lag";"supply"
"Building";"Refinery";NA;15;0
"Building";"Barracks";NA;16;0
"Unit";"Reaper";"Barracks";19;1
"Building";"CommandCenter";NA;20;0
"Building";"Factory";NA;20;0
"Building";"Refinery";NA;21;0
"Building";"BarracksReactor";NA;21;0
"Building";"Starport";NA;24;0
"Unit";"Marine";"Barracks";24;1
"Unit";"Marine";"Barracks";25;1
"Unit";"Marine";"Barracks";27;1
"Unit";"Marine";"Barracks";29;1
"Building";"FactoryTechLab";NA;30;0
"Unit";"Medivac";"Starport";31;2
"Unit";"Marine";"Barracks";33;1
"Unit";"Marine";"Barracks";34;1
"Unit";"Hellion";"Factory";39;2
"Unit";"Hellion";"Factory";41;2
"Building";"BarracksTechLab";NA;44;0
"Unit";"Raven";"Starport";46;2
"Unit";"Hellion";"Factory";49;2
"Unit";"Hellion";"Factory";51;2
"Building";"CommandCenter";NA;57;0
"Upgrade";"Stimpack";"TechLab";59;0
"Building";"FactoryReactor";NA;59;0
"Building";"Barracks";NA;60;0
"Building";"Barracks";NA;60;0
"Unit";"Marine";"Barracks";60;1
"Unit";"Raven";"Starport";63;2
"Building";"EngineeringBay";NA;65;0
"Building";"Refinery";NA;65;0
"Building";"EngineeringBay";NA;65;0
"Building";"Refinery";NA;65;0
"Unit";"Marine";"Barracks";67;1
"Building";"FactoryReactor";NA;70;0
"Unit";"Marine";"Barracks";70;1
"Building";"Barracks";NA;74;0
"Building";"Barracks";NA;74;0
"Building";"StarportReactor";NA;74;0
"Unit";"Marine";"Barracks";74;1
"Unit";"Marine";"Barracks";75;1
"Unit";"Marine";"Barracks";76;1
"Unit";"Marine";"Barracks";77;1
"Unit";"Marine";"Barracks";78;1
"Unit";"Marine";"Barracks";81;1
"Upgrade";"TerranInfantryWeaponsLevel1";"EngineeringBay";82;0
"Unit";"Marine";"Barracks";82;1
"Unit";"Marine";"Barracks";83;1
"Unit";"Marine";"Barracks";84;1
"Unit";"Marine";"Barracks";85;1
"Unit";"Medivac";"Starport";88;2
"Unit";"Medivac";"Starport";90;2
"Unit";"Marine";"Barracks";95;1
"Building";"Armory";NA;96;0
"Building";"BarracksReactor";NA;96;0
"Building";"BarracksReactor";NA;96;0
"Unit";"Marine";"Barracks";96;1
"Unit";"Marine";"Barracks";97;1
"Unit";"Marine";"Barracks";98;1
"Unit";"Marine";"Barracks";99;1
"Unit";"Marine";"Barracks";103;1
"Unit";"Marine";"Barracks";104;1
"Unit";"Marine";"Barracks";108;1
"Unit";"Marine";"Barracks";109;1
"Unit";"Marine";"Barracks";110;1
"Unit";"Marine";"Barracks";111;1
"Unit";"Marine";"Barracks";112;1
"Unit";"Marine";"Barracks";113;1
"Building";"MissileTurret";NA;116;0
"Unit";"Marine";"Barracks";116;1
"Unit";"Marine";"Barracks";117;1
"Unit";"Marine";"Barracks";118;1
"Unit";"Marine";"Barracks";119;1
"Unit";"Marine";"Barracks";120;1
"Unit";"Marine";"Barracks";121;1
"Unit";"Marine";"Barracks";122;1
"Unit";"Marine";"Barracks";123;1
"Unit";"Medivac";"Starport";124;2
"Unit";"Medivac";"Starport";126;2
"Unit";"Marine";"Barracks";128;1
"Unit";"Marine";"Barracks";129;1
"Unit";"Marine";"Barracks";130;1
"Unit";"Marine";"Barracks";131;1
"Unit";"Marine";"Barracks";132;1
"Unit";"Marine";"Barracks";133;1
"Unit";"Marine";"Barracks";134;1
"Unit";"Marine";"Barracks";135;1
"Unit";"Marine";"Barracks";136;1
"Unit";"Marine";"Barracks";137;1
"Unit";"Marine";"Barracks";138;1
"Upgrade";"TerranInfantryWeaponsLevel2";"EngineeringBay";139;0
"Unit";"Marine";"Barracks";139;1
"Unit";"Marine";"Barracks";140;1
"Unit";"Medivac";"Starport";141;2
"Unit";"Medivac";"Starport";143;2
"Unit";"Marine";"Barracks";145;1
"Unit";"Marine";"Barracks";146;1
"Unit";"Marine";"Barracks";147;1
"Unit";"Marine";"Barracks";148;1
"Unit";"Marine";"Barracks";149;1
"Unit";"Marine";"Barracks";150;1
"Unit";"Marauder";"Barracks";151;2
"Unit";"Marine";"Barracks";153;1
"Unit";"Marine";"Barracks";154;1
"Building";"CommandCenter";NA;155;0
"Unit";"Marine";"Barracks";155;1
"Building";"Refinery";NA;156;0
"Building";"Refinery";NA;156;0
"Unit";"Marine";"Barracks";156;1
"Unit";"Marauder";"Barracks";157;2
"Unit";"Marine";"Barracks";159;1
"Unit";"Marine";"Barracks";160;1
"Unit";"Marine";"Barracks";161;1
"Unit";"Marine";"Barracks";162;1
"Unit";"Marine";"Barracks";163;1
"Unit";"Marine";"Barracks";164;1
"Unit";"Marauder";"Barracks";165;2
"Building";"Starport";NA;167;0
"Building";"FusionCore";NA;167;0
"Building";"Starport";NA;167;0
"Unit";"Marine";"Barracks";167;1
"Unit";"Marine";"Barracks";168;1
"Unit";"Marine";"Barracks";169;1
"Unit";"Marine";"Barracks";170;1
"Building";"MissileTurret";NA;171;0
"Unit";"Marine";"Barracks";171;1
"Unit";"Marauder";"Barracks";172;2
"Unit";"Marine";"Barracks";174;1
"Unit";"Marine";"Barracks";175;1
"Unit";"Marine";"Barracks";176;1
"Unit";"Marine";"Barracks";177;1
"Unit";"Marine";"Barracks";178;1
"Unit";"Marine";"Barracks";179;1
"Unit";"Marine";"Barracks";180;1
"Unit";"Marine";"Barracks";181;1
"Unit";"Marine";"Barracks";182;1
"Unit";"Marine";"Barracks";183;1
"Unit";"Marauder";"Barracks";184;2
"Unit";"Marine";"Barracks";186;1
"Unit";"Marine";"Barracks";187;1
"Unit";"Marine";"Barracks";188;1
"Unit";"Marine";"Barracks";189;1
"Unit";"Marine";"Barracks";190;1
"Unit";"Marine";"Barracks";191;1
"Building";"StarportReactor";NA;192;0
"Unit";"Liberator";"Starport";192;3
"Unit";"Liberator";"Starport";195;3
"Unit";"Liberator";"Starport";198;3
"Unit";"Marauder";"Barracks";201;2
"Unit";"Marine";"Barracks";203;1
"Unit";"Marine";"Barracks";204;1
"Unit";"Marine";"Barracks";205;1
"Unit";"Marine";"Barracks";206;1
"Unit";"Marine";"Barracks";207;1
"Unit";"Marine";"Barracks";208;1
"Unit";"Marine";"Barracks";209;1
"Unit";"Marine";"Barracks";210;1
"Unit";"Liberator";"Starport";211;3
"Unit";"Liberator";"Starport";214;3
"Unit";"Marine";"Barracks";217;1
"Unit";"Marine";"Barracks";218;1
"Unit";"Marine";"Barracks";219;1
"Unit";"Marine";"Barracks";220;1
"Unit";"Marine";"Barracks";221;1
"Unit";"Marine";"Barracks";222;1
"Unit";"Marine";"Barracks";223;1
"Unit";"Marine";"Barracks";224;1
"Unit";"Marine";"Barracks";225;1
"Unit";"Marine";"Barracks";226;1
"Unit";"Marine";"Barracks";227;1
"Unit";"Marine";"Barracks";228;1
"Unit";"Marine";"Barracks";229;1
"Unit";"Medivac";"Starport";230;2
"Unit";"Medivac";"Starport";232;2
"Unit";"Medivac";"Starport";234;2
"Unit";"Marine";"Barracks";236;1
"Unit";"Marine";"Barracks";237;1
"Unit";"Marine";"Barracks";238;1
"Unit";"Marine";"Barracks";239;1
"Unit";"Marine";"Barracks";240;1
"Unit";"Marine";"Barracks";241;1
"Unit";"Marine";"Barracks";242;1
"Unit";"Marine";"Barracks";243;1
"Unit";"Liberator";"Starport";244;3
"Unit";"Marine";"Barracks";247;1
"Upgrade";"TerranInfantryWeaponsLevel3";"EngineeringBay";248;0
"Building";"Refinery";NA;248;0
"Building";"Refinery";NA;248;0
"Unit";"Marauder";"Barracks";248;2
"Unit";"Marine";"Barracks";250;1
"Unit";"Marine";"Barracks";251;1
"Unit";"Marine";"Barracks";252;1
"Unit";"Marine";"Barracks";253;1
"Unit";"Marine";"Barracks";254;1
"Unit";"Marine";"Barracks";255;1
"Building";"CommandCenter";NA;256;0
"Unit";"Marine";"Barracks";256;1
"Unit";"Marine";"Barracks";257;1
"Unit";"Marine";"Barracks";258;1
"Unit";"Marine";"Barracks";259;1
"Unit";"Marauder";"Barracks";260;2
"Unit";"Liberator";"Starport";262;3
"Unit";"Marine";"Barracks";265;1
"Unit";"Marine";"Barracks";266;1
"Unit";"Marine";"Barracks";267;1
"Unit";"Liberator";"Starport";268;3
"Unit";"Marine";"Barracks";271;1
"Unit";"Marine";"Barracks";272;1
"Unit";"Marauder";"Barracks";273;2
"Unit";"Liberator";"Starport";275;3
"Unit";"Marine";"Barracks";278;1
"Unit";"Marine";"Barracks";279;1
"Unit";"Marine";"Barracks";280;1
"Building";"Barracks";NA;281;0
"Unit";"Marine";"Barracks";281;1
"Unit";"Marine";"Barracks";282;1
"Unit";"Liberator";"Starport";283;3
"Unit";"Liberator";"Starport";286;3
"Unit";"Marauder";"Barracks";289;2
"Unit";"Marine";"Barracks";291;1
"Unit";"Marine";"Barracks";292;1
"Unit";"Marine";"Barracks";293;1
"Unit";"Marine";"Barracks";294;1
"Unit";"Marine";"Barracks";295;1
"Unit";"Marine";"Barracks";296;1
"Unit";"Marine";"Barracks";297;1
"Unit";"Marine";"Barracks";298;1
"Unit";"Liberator";"Starport";299;3
"Building";"Barracks";NA;302;0
"Unit";"Marauder";"Barracks";302;2
"Building";"SensorTower";NA;304;0
"Unit";"Marine";"Barracks";304;1
"Unit";"Marine";"Barracks";305;1
"Building";"BarracksTechLab";NA;306;0
"Unit";"Liberator";"Starport";306;3
"Unit";"Liberator";"Starport";309;3
"Unit";"Medivac";"Starport";312;2
"Unit";"Banshee";"Starport";314;3
"Unit";"Marine";"Barracks";317;1
"Unit";"Marine";"Barracks";318;1
"Unit";"Liberator";"Starport";319;3
"Unit";"Marauder";"Barracks";322;2
"Building";"CommandCenter";NA;324;0
"Building";"SensorTower";NA;324;0
"Unit";"Marine";"Barracks";324;1
"Unit";"Marine";"Barracks";325;1
"Unit";"Marine";"Barracks";326;1
"Unit";"Marine";"Barracks";327;1
"Upgrade";"TerranShipWeaponsLevel1";"Armory";328;0
"Unit";"Marine";"Barracks";329;1
"Unit";"Marine";"Barracks";330;1
"Unit";"Marine";"Barracks";331;1
"Unit";"Marine";"Barracks";333;1
"Unit";"Marauder";"Barracks";334;2
"Unit";"Marine";"Barracks";337;1
"Unit";"Marauder";"Barracks";338;2
"Unit";"Marine";"Barracks";346;1
"Unit";"Marine";"Barracks";347;1
"Unit";"Liberator";"Starport";348;3
"Unit";"Liberator";"Starport";351;3
"Unit";"Marauder";"Barracks";354;2
"Unit";"Marauder";"Barracks";356;2
"Unit";"Marine";"Barracks";359;1
"Unit";"Marine";"Barracks";360;1
"Unit";"Medivac";"Starport";361;2
"Unit";"Medivac";"Starport";363;2
"Building";"BarracksTechLab";NA;365;0
"Unit";"Medivac";"Starport";368;2
"Building";"MissileTurret";NA;371;0
"Unit";"Marine";"Barracks";371;1
"Unit";"Marine";"Barracks";372;1
"Unit";"Marine";"Barracks";373;1
"Unit";"Medivac";"Starport";374;2
"Unit";"Liberator";"Starport";376;3
"Unit";"Liberator";"Starport";379;3
"Unit";"Liberator";"Starport";382;3
"Unit";"Marauder";"Barracks";385;2
"Unit";"Marine";"Barracks";387;1
"Unit";"Marine";"Barracks";388;1
"Unit";"Marauder";"Barracks";389;2
"Unit";"Marauder";"Barracks";391;2
"Unit";"Marine";"Barracks";393;1
"Unit";"Marine";"Barracks";394;1
"Unit";"Liberator";"Starport";395;3
"Unit";"Marine";"Barracks";398;1
"Unit";"Marine";"Barracks";399;1
"Unit";"Marine";"Barracks";400;1
"Unit";"Marauder";"Barracks";401;2
"Unit";"Liberator";"Starport";403;3
"Building";"Refinery";NA;406;0
"Building";"Refinery";NA;406;0
"Unit";"Marauder";"Barracks";406;2
"Unit";"Marauder";"Barracks";408;2
"Unit";"Marine";"Barracks";410;1
"Unit";"Marine";"Barracks";411;1
"Unit";"Liberator";"Starport";412;3
"Unit";"Liberator";"Starport";415;3
"Unit";"Marine";"Barracks";418;1
"Unit";"Marine";"Barracks";419;1
"Unit";"Marine";"Barracks";420;1
"Upgrade";"TerranShipWeaponsLevel2";"Armory";421;0
"Building";"CommandCenter";NA;421;0
"Unit";"Liberator";"Starport";421;3
"Unit";"Liberator";"Starport";424;3
"Unit";"Marauder";"Barracks";427;2
"Building";"SensorTower";NA;429;0
"Building";"GhostAcademy";NA;429;0
"Unit";"Marauder";"Barracks";429;2
"Unit";"Marauder";"Barracks";431;2
"Unit";"Marine";"Barracks";433;1
"Unit";"Marine";"Barracks";434;1
"Unit";"Liberator";"Starport";435;3
"Unit";"Liberator";"Starport";438;3
"Unit";"Liberator";"Starport";441;3
"Unit";"Liberator";"Starport";444;3
"Unit";"Liberator";"Starport";447;3
"Unit";"Marauder";"Barracks";450;2
"Unit";"Marauder";"Barracks";452;2
"Unit";"Marine";"Barracks";454;1
"Unit";"Marine";"Barracks";455;1
"Unit";"Marauder";"Barracks";456;2
"Unit";"Marine";"Barracks";458;1
"Unit";"Marine";"Barracks";459;1
"Unit";"Marine";"Barracks";460;1
"Unit";"Marine";"Barracks";461;1
"Unit";"Marine";"Barracks";462;1
"Building";"MissileTurret";NA;463;0
"Building";"MissileTurret";NA;463;0
"Unit";"Marauder";"Barracks";463;2
"Unit";"Marauder";"Barracks";465;2
"Unit";"Marine";"Barracks";467;1
"Unit";"Marine";"Barracks";468;1
"Unit";"Liberator";"Starport";469;3
"Unit";"Liberator";"Starport";472;3
"Unit";"Liberator";"Starport";475;3
"Unit";"Marauder";"Barracks";478;2
"Unit";"Liberator";"Starport";480;3
"Unit";"Liberator";"Starport";483;3
"Unit";"Marine";"Barracks";486;1
"Unit";"Marine";"Barracks";487;1
"Unit";"Marine";"Barracks";488;1
"Unit";"Marauder";"Barracks";489;2
"Unit";"Marauder";"Barracks";491;2
"Unit";"Marine";"Barracks";493;1
"Unit";"Marine";"Barracks";494;1
"Unit";"Marauder";"Barracks";495;2
"Building";"CommandCenter";NA;497;0
"Unit";"Marauder";"Barracks";497;2
"Unit";"Marauder";"Barracks";499;2
"Unit";"Marine";"Barracks";501;1
"Unit";"Marine";"Barracks";502;1
"Unit";"Marine";"Barracks";503;1
"Unit";"Marine";"Barracks";504;1
"Unit";"Liberator";"Starport";505;3
"Unit";"Liberator";"Starport";508;3
"Unit";"Liberator";"Starport";511;3
"Unit";"Marine";"Barracks";514;1
"Unit";"Marine";"Barracks";515;1
"Unit";"Marauder";"Barracks";516;2
"Unit";"Marine";"Barracks";518;1
"Unit";"Marine";"Barracks";519;1
"Unit";"Liberator";"Starport";520;3
"Unit";"Marine";"Barracks";523;1
"Unit";"Marine";"Barracks";524;1
"Unit";"Marine";"Barracks";525;1
"Unit";"Marauder";"Barracks";526;2
"Unit";"Marauder";"Barracks";528;2
"Unit";"Marine";"Barracks";530;1
"Unit";"Marine";"Barracks";531;1
"Unit";"Marine";"Barracks";532;1
"Unit";"Marine";"Barracks";533;1
"Unit";"Marine";"Barracks";534;1
"Unit";"Marine";"Barracks";535;1
"Upgrade";"TerranShipWeaponsLevel3";"Armory";536;0
"Unit";"Marine";"Barracks";536;1
"Unit";"Marine";"Barracks";537;1
"Unit";"Marine";"Barracks";538;1
"Unit";"Marine";"Barracks";539;1
"Unit";"Liberator";"Starport";540;3
"Unit";"Liberator";"Starport";543;3
"Unit";"Marauder";"Barracks";546;2
"Unit";"Marine";"Barracks";548;1
"Unit";"Marine";"Barracks";549;1
"Unit";"Liberator";"Starport";550;3
"Unit";"Marauder";"Barracks";553;2
"Unit";"Marine";"Barracks";555;1
"Unit";"Marine";"Barracks";556;1
"Unit";"Marine";"Barracks";557;1
"Unit";"Marine";"Barracks";558;1
"Unit";"Marine";"Barracks";559;1
"Unit";"Marine";"Barracks";560;1
"Unit";"Marine";"Barracks";561;1
"Unit";"Marauder";"Barracks";562;2
"Unit";"Marauder";"Barracks";564;2
"Unit";"Liberator";"Starport";566;3
"Unit";"Liberator";"Starport";569;3
"Unit";"Marine";"Barracks";572;1
"Unit";"Marine";"Barracks";573;1
"Unit";"Marine";"Barracks";574;1
"Unit";"Marine";"Barracks";575;1
"Unit";"Marine";"Barracks";576;1
"Unit";"Marine";"Barracks";577;1
"Unit";"Marine";"Barracks";578;1
"Unit";"Marine";"Barracks";579;1
"Unit";"Marine";"Barracks";580;1
"Unit";"Marine";"Barracks";581;1
"Unit";"Marauder";"Barracks";582;2
"Unit";"Marauder";"Barracks";584;2
"Unit";"Marine";"Barracks";586;1
"Unit";"Marine";"Barracks";587;1
"Unit";"Marauder";"Barracks";588;2
"Unit";"Marine";"Barracks";590;1
"Unit";"Marine";"Barracks";591;1
"Unit";"Marine";"Barracks";592;1
"Unit";"Marine";"Barracks";593;1
"Unit";"Marine";"Barracks";594;1
"Unit";"Marine";"Barracks";595;1
"Unit";"Liberator";"Starport";596;3
"Unit";"Liberator";"Starport";599;3
"Unit";"Marine";"Barracks";605;1
"Unit";"Marine";"Barracks";606;1
"Unit";"Marauder";"Barracks";607;2
"Unit";"Marine";"Barracks";609;1
"Unit";"Marine";"Barracks";610;1
"Unit";"Marine";"Barracks";611;1
"Unit";"Marine";"Barracks";612;1
"Unit";"Marine";"Barracks";613;1
"Unit";"Marine";"Barracks";614;1
"Unit";"Marine";"Barracks";615;1
"Unit";"Marine";"Barracks";616;1
"Unit";"Medivac";"Starport";617;2
"Unit";"Medivac";"Starport";619;2
"Unit";"Marine";"Barracks";621;1
"Unit";"Marauder";"Barracks";622;2
"Unit";"Marine";"Barracks";624;1
"Unit";"Marine";"Barracks";625;1
"Unit";"Marine";"Barracks";626;1
"Unit";"Marine";"Barracks";627;1
"Unit";"Marauder";"Barracks";628;2
"Unit";"Marauder";"Barracks";630;2
"Unit";"Marine";"Barracks";632;1
"Unit";"Marine";"Barracks";633;1
"Unit";"Marine";"Barracks";634;1
"Unit";"Marine";"Barracks";635;1
"Unit";"Marine";"Barracks";636;1
"Unit";"Marine";"Barracks";637;1
"Building";"MissileTurret";NA;638;0
"Building";"MissileTurret";NA;638;0
"Unit";"Marauder";"Barracks";638;2
"Unit";"Medivac";"Starport";640;2
"Unit";"Medivac";"Starport";642;2
"Unit";"Medivac";"Starport";644;2
"Building";"MissileTurret";NA;646;0
"Unit";"Medivac";"Starport";646;2
"Unit";"Medivac";"Starport";648;2
"Building";"MissileTurret";NA;650;0
"Unit";"Marine";"Barracks";650;1
"Unit";"Marauder";"Barracks";651;2
"Unit";"Marine";"Barracks";653;1
"Unit";"Marine";"Barracks";654;1
"Unit";"Marine";"Barracks";655;1
"Unit";"Marine";"Barracks";656;1
"Unit";"Liberator";"Starport";657;3
"Unit";"Liberator";"Starport";660;3
"Unit";"Marauder";"Barracks";663;2
"Unit";"Marine";"Barracks";665;1
"Unit";"Marine";"Barracks";666;1
"Unit";"Marine";"Barracks";667;1
"Unit";"Marine";"Barracks";668;1
"Unit";"Marine";"Barracks";669;1
"Unit";"Marine";"Barracks";670;1
"Unit";"Medivac";"Starport";671;2
"Unit";"Medivac";"Starport";673;2
"Unit";"Medivac";"Starport";675;2
"Unit";"Marauder";"Barracks";677;2
"Unit";"Marine";"Barracks";679;1
"Unit";"Marine";"Barracks";680;1
"Unit";"Marine";"Barracks";681;1
"Unit";"Marine";"Barracks";682;1
"Unit";"Marauder";"Barracks";687;2
"Unit";"Marauder";"Barracks";689;2
"Unit";"Marine";"Barracks";691;1
"Upgrade";"SprayTerran";NA;692;0
"Upgrade";"SprayTerran";NA;692;0
"Upgrade";"SprayTerran";NA;692;0
"Upgrade";"SprayTerran";NA;692;0
"Upgrade";"TerranInfantryArmorsLevel1";NA;692;0
"Upgrade";"ShieldWall";NA;692;0
"Upgrade";"SprayTerran";NA;692;0
"Upgrade";"PunisherGrenades";NA;692;0
"Upgrade";"TerranVehicleAndShipArmorsLevel1";NA;692;0
"Upgrade";"TerranInfantryArmorsLevel2";NA;692;0
"Upgrade";"SprayTerran";NA;692;0
"Upgrade";"LiberatorAGRangeUpgrade";NA;692;0
"Upgrade";"TerranVehicleAndShipArmorsLevel2";NA;692;0
"Upgrade";"SprayTerran";NA;692;0
"Upgrade";"SprayTerran";NA;692;0
"Upgrade";"TerranVehicleAndShipArmorsLevel3";NA;692;0
"Upgrade";"TerranInfantryArmorsLevel3";NA;692;0
"Upgrade";"SprayTerran";NA;692;0
"Upgrade";"SprayTerran";NA;692;0
"Upgrade";"SprayTerran";NA;692;0
"Upgrade";"SprayTerran";NA;692;0
"Upgrade";"SprayTerran";NA;692;0
"Upgrade";"SprayTerran";NA;692;0
