"type";"unit_name";"on_building";"total_supply";"supply"
"Building";"Pylon";NA;13;0
"Building";"Assimilator";NA;16;0
"Building";"Gateway";NA;15;0
"Building";"Assimilator";NA;20;0
"Building";"Pylon";NA;21;0
"Building";"CyberneticsCore";NA;19;0
"Unit";"Adept";"Gateway";22;2
"Building";"Nexus";NA;19;0
"Unit";"Adept";"Gateway";23;2
"Building";"Stargate";NA;24;0
"Unit";"Adept";"Gateway";28;2
"Building";"Pylon";NA;34;0
"Unit";"Phoenix";"Stargate";34;2
"Unit";"Phoenix";"Stargate";42;2
"Building";"Pylon";NA;46;0
"Building";"Assimilator";NA;44;0
"Unit";"Phoenix";"Stargate";47;2
"Building";"TwilightCouncil";NA;44;0
"Building";"Gateway";NA;43;0
"Building";"Gateway";NA;43;0
"Building";"ShieldBattery";NA;48;0
"Unit";"Phoenix";"Stargate";49;2
"Building";"Pylon";NA;53;0
"Building";"Pylon";NA;54;0
"Unit";"Adept";"Gateway";59;2
"Building";"Assimilator";NA;54;0
"Unit";"Adept";"Gateway";59;2
"Unit";"Adept";"Gateway";59;2
"Unit";"Phoenix";"Stargate";55;2
"Unit";"Adept";"Gateway";70;2
"Unit";"Adept";"Gateway";70;2
"Unit";"Adept";"Gateway";70;2
"Unit";"Phoenix";"Stargate";66;2
"Building";"Pylon";NA;70;0
"Unit";"Adept";"Gateway";79;2
"Unit";"Adept";"Gateway";79;2
"Unit";"Adept";"Gateway";79;2
"Unit";"Phoenix";"Stargate";79;2
"Unit";"Adept";"Gateway";87;2
"Unit";"Phoenix";"Stargate";85;2
"Building";"Pylon";NA;93;0
"Building";"RoboticsFacility";NA;87;0
"Building";"RoboticsFacility";NA;87;0
"Building";"Nexus";NA;85;0
"Unit";"Phoenix";"Stargate";95;2
"Unit";"Sentry";"Gateway";101;2
"Unit";"Adept";"Gateway";101;2
"Unit";"Adept";"Gateway";101;2
"Unit";"Immortal";"Robotics Facility";95;4
"Unit";"Immortal";"Robotics Facility";96;4
"Building";"Forge";NA;108;0
"Building";"TemplarArchive";NA;108;0
"Unit";"Immortal";"Robotics Facility";108;4
"Building";"Gateway";NA;108;0
"Unit";"Immortal";"Robotics Facility";108;4
"Building";"Gateway";NA;108;0
"Building";"Pylon";NA;116;0
"Building";"Gateway";NA;108;0
"Building";"Assimilator";NA;119;0
"Building";"Gateway";NA;108;0
"Upgrade";"Charge";"TwilightCouncil";99;0
"Building";"Assimilator";NA;119;0
"Unit";"Observer";"Robotics Facility";119;1
"Building";"Pylon";NA;130;0
"Building";"Gateway";NA;116;0
"Unit";"Immortal";"Robotics Facility";129;4
"Building";"HighTemplar";NA;135;0
"Building";"HighTemplar";NA;135;0
"Unit";"Immortal";"Robotics Facility";130;4
"Building";"Pylon";NA;135;0
"Building";"Pylon";NA;135;0
"Building";"HighTemplar";NA;143;0
"Unit";"Immortal";"Robotics Facility";135;4
"Building";"HighTemplar";NA;146;0
"Building";"HighTemplar";NA;146;0
"Building";"Pylon";NA;146;0
"Unit";"Immortal";"Robotics Facility";143;4
"Upgrade";"ProtossGroundWeaponsLevel1";"Forge";130;0
"Unit";"Zealot";"Gateway";156;2
"Unit";"Zealot";"Gateway";156;2
"Unit";"Zealot";"Gateway";156;2
"Unit";"Zealot";"Gateway";156;2
"Unit";"Zealot";"Gateway";156;2
"Building";"ShieldBattery";NA;146;0
"Building";"ShieldBattery";NA;146;0
"Building";"ShieldBattery";NA;146;0
"Building";"PhotonCannon";NA;146;0
"Building";"Nexus";NA;135;0
"Building";"Pylon";NA;152;0
"Unit";"Phoenix";"Stargate";156;2
"Building";"HighTemplar";NA;166;0
"Building";"HighTemplar";NA;166;0
"Unit";"Sentry";"Gateway";166;2
"Unit";"Zealot";"Gateway";166;2
"Unit";"Zealot";"Gateway";166;2
"Unit";"Zealot";"Gateway";166;2
"Unit";"Zealot";"Gateway";166;2
"Unit";"Zealot";"Gateway";166;2
"Unit";"Archon";"High Templar";166;0
"Unit";"Archon";"High Templar";178;0
"Building";"PhotonCannon";NA;166;0
"Building";"PhotonCannon";NA;166;0
"Building";"ShieldBattery";NA;166;0
"Building";"HighTemplar";NA;180;0
"Unit";"Immortal";"Robotics Facility";180;4
"Building";"Pylon";NA;180;0
"Building";"Pylon";NA;180;0
"Building";"Pylon";NA;180;0
"Building";"Pylon";NA;180;0
"Building";"Pylon";NA;180;0
"Building";"Pylon";NA;180;0
"Building";"HighTemplar";NA;184;0
"Building";"HighTemplar";NA;184;0
"Unit";"Zealot";"Gateway";184;2
"Unit";"Zealot";"Gateway";184;2
"Unit";"Zealot";"Gateway";184;2
"Unit";"Zealot";"Gateway";184;2
"Unit";"Zealot";"Gateway";184;2
"Unit";"Zealot";"Gateway";184;2
"Unit";"Archon";"High Templar";184;0
"Building";"Pylon";NA;196;0
"Building";"Assimilator";NA;196;0
"Building";"Assimilator";NA;196;0
"Unit";"Zealot";"Gateway";196;2
"Unit";"Zealot";"Gateway";196;2
"Unit";"Zealot";"Gateway";196;2
"Unit";"Zealot";"Gateway";196;2
"Unit";"Zealot";"Gateway";196;2
"Unit";"Zealot";"Gateway";196;2
"Unit";"Zealot";"Gateway";196;2
"Unit";"Zealot";"Gateway";196;2
"Upgrade";"ProtossGroundWeaponsLevel2";"Forge";168;0
"Unit";"Archon";"High Templar";196;0
"Unit";"Archon";"High Templar";196;0
"Unit";"Zealot";"Gateway";212;2
"Unit";"Zealot";"Gateway";212;2
"Unit";"Zealot";"Gateway";212;2
"Unit";"Zealot";"Gateway";212;2
"Unit";"Zealot";"Gateway";212;2
"Unit";"Zealot";"Gateway";212;2
"Unit";"Zealot";"Gateway";212;2
"Unit";"Zealot";"Gateway";212;2
"Unit";"Immortal";"Robotics Facility";196;4
"Unit";"Immortal";"Robotics Facility";212;4
"Building";"HighTemplar";NA;232;0
"Building";"HighTemplar";NA;232;0
"Building";"HighTemplar";NA;232;0
"Building";"HighTemplar";NA;232;0
"Building";"HighTemplar";NA;232;0
"Building";"HighTemplar";NA;232;0
"Building";"HighTemplar";NA;232;0
"Building";"HighTemplar";NA;232;0
"Unit";"Archon";"High Templar";236;0
"Unit";"Archon";"High Templar";236;0
"Building";"Pylon";NA;236;0
"Unit";"Zealot";"Gateway";236;2
"Unit";"Zealot";"Gateway";236;2
"Unit";"Zealot";"Gateway";236;2
"Unit";"Zealot";"Gateway";236;2
"Unit";"Zealot";"Gateway";236;2
"Unit";"Zealot";"Gateway";236;2
"Unit";"Zealot";"Gateway";236;2
"Unit";"Zealot";"Gateway";236;2
"Upgrade";"ProtossShieldsLevel1";"Forge";212;0
"Unit";"Zealot";"Gateway";252;2
"Unit";"Zealot";"Gateway";252;2
"Unit";"Zealot";"Gateway";252;2
"Unit";"Zealot";"Gateway";252;2
"Unit";"Zealot";"Gateway";252;2
"Unit";"Zealot";"Gateway";252;2
"Unit";"Zealot";"Gateway";252;2
"Unit";"Zealot";"Gateway";252;2
"Unit";"Immortal";"Robotics Facility";236;4
"Unit";"Immortal";"Robotics Facility";236;4
"Unit";"Zealot";"Gateway";276;2
"Unit";"Zealot";"Gateway";276;2
"Unit";"Zealot";"Gateway";276;2
"Unit";"Zealot";"Gateway";276;2
"Unit";"Zealot";"Gateway";276;2
"Unit";"Zealot";"Gateway";276;2
"Unit";"Zealot";"Gateway";276;2
"Unit";"Zealot";"Gateway";276;2
"Building";"Nexus";NA;236;0
"Building";"HighTemplar";NA;292;0
"Building";"HighTemplar";NA;292;0
"Building";"HighTemplar";NA;292;0
"Building";"HighTemplar";NA;292;0
"Building";"HighTemplar";NA;292;0
"Building";"HighTemplar";NA;292;0
"Building";"HighTemplar";NA;292;0
"Building";"HighTemplar";NA;292;0
"Unit";"Immortal";"Robotics Facility";276;4
"Unit";"Archon";"High Templar";296;0
"Unit";"Archon";"High Templar";296;0
"Building";"FleetBeacon";NA;292;0
"Building";"Stargate";NA;292;0
"Building";"Stargate";NA;292;0
"Building";"Pylon";NA;300;0
"Unit";"Zealot";"Gateway";305;2
"Unit";"Zealot";"Gateway";305;2
"Unit";"Zealot";"Gateway";305;2
"Unit";"Zealot";"Gateway";305;2
"Upgrade";"ProtossAirWeaponsLevel1";"CyberneticsCore";292;0
"Building";"Assimilator";NA;314;0
"Building";"Assimilator";NA;314;0
"Upgrade";"ProtossGroundWeaponsLevel3";"Forge";292;0
"Unit";"Zealot";"Gateway";314;2
"Unit";"Zealot";"Gateway";314;2
"Unit";"Zealot";"Gateway";314;2
"Unit";"Zealot";"Gateway";314;2
"Unit";"Zealot";"Gateway";314;2
"Unit";"Zealot";"Gateway";314;2
"Unit";"Zealot";"Gateway";314;2
"Unit";"Carrier";"Stargate";296;6
"Unit";"Zealot";"Gateway";314;2
"Unit";"Carrier";"Stargate";300;6
"Unit";"Carrier";"Stargate";300;6
"Unit";"Zealot";"Gateway";354;2
"Unit";"Zealot";"Gateway";354;2
"Building";"HighTemplar";NA;354;0
"Building";"HighTemplar";NA;354;0
"Unit";"Carrier";"Stargate";314;6
"Unit";"Zealot";"Gateway";375;2
"Unit";"Zealot";"Gateway";375;2
"Unit";"Zealot";"Gateway";375;2
"Unit";"Zealot";"Gateway";375;2
"Unit";"Carrier";"Stargate";342;6
"Unit";"Carrier";"Stargate";342;6
"Unit";"Sentry";"Gateway";395;2
"Unit";"Sentry";"Gateway";395;2
"Upgrade";"ProtossAirWeaponsLevel2";"CyberneticsCore";342;0
"Upgrade";"ProtossShieldsLevel2";"Forge";350;0
"Building";"HighTemplar";NA;399;0
"Building";"HighTemplar";NA;399;0
"Building";"HighTemplar";NA;399;0
"Unit";"Zealot";"Gateway";399;2
"Unit";"Zealot";"Gateway";399;2
"Unit";"Archon";"High Templar";399;0
"Unit";"Zealot";"Gateway";403;2
"Unit";"Zealot";"Gateway";403;2
"Building";"HighTemplar";NA;407;0
"Unit";"Carrier";"Stargate";365;6
"Building";"HighTemplar";NA;413;0
"Building";"HighTemplar";NA;413;0
"Building";"HighTemplar";NA;413;0
"Building";"HighTemplar";NA;413;0
"Unit";"Zealot";"Gateway";413;2
"Unit";"Zealot";"Gateway";413;2
"Unit";"Zealot";"Gateway";413;2
"Unit";"Archon";"High Templar";413;0
"Unit";"Archon";"High Templar";413;0
"Unit";"Carrier";"Stargate";383;6
"Building";"HighTemplar";NA;425;0
"Building";"HighTemplar";NA;425;0
"Unit";"Sentry";"Gateway";425;2
"Unit";"Zealot";"Gateway";425;2
