"type";"unit_name";"on_building";"total_supply";"supply"
"Building";"Pylon";NA;13;0
"Building";"Assimilator";NA;16;0
"Building";"Gateway";NA;15;0
"Building";"Assimilator";NA;20;0
"Building";"CyberneticsCore";NA;20;0
"Building";"Pylon";NA;21;0
"Unit";"Adept";"Gateway";22;2
"Building";"Nexus";NA;19;0
"Unit";"Adept";"Gateway";26;2
"Building";"Stargate";NA;23;0
"Building";"Pylon";NA;31;0
"Unit";"Phoenix";"Stargate";31;2
"Building";"Assimilator";NA;36;0
"Building";"Assimilator";NA;37;0
"Building";"Pylon";NA;43;0
"Unit";"Oracle";"Stargate";41;3
"Building";"Pylon";NA;44;0
"Building";"RoboticsFacility";NA;41;0
"Unit";"Zealot";"Gateway";53;2
"Building";"Gateway";NA;49;0
"Building";"Gateway";NA;50;0
"Building";"TwilightCouncil";NA;52;0
"Building";"Gateway";NA;50;0
"Unit";"Observer";"Robotics Facility";56;1
"Building";"Pylon";NA;56;0
"Building";"TemplarArchive";NA;56;0
"Building";"HighTemplar";NA;59;0
"Building";"HighTemplar";NA;59;0
"Building";"HighTemplar";NA;59;0
"Building";"HighTemplar";NA;59;0
"Building";"Forge";NA;56;0
"Unit";"Archon";"High Templar";60;0
"Unit";"Archon";"High Templar";60;0
"Building";"Pylon";NA;60;0
"Building";"Nexus";NA;56;0
"Building";"Forge";NA;59;0
"Unit";"Immortal";"Robotics Facility";59;4
"Building";"Pylon";NA;63;0
"Unit";"Zealot";"Gateway";70;2
"Unit";"Zealot";"Gateway";70;2
"Unit";"Sentry";"Gateway";70;2
"Unit";"Sentry";"Gateway";70;2
"Unit";"Immortal";"Robotics Facility";63;4
"Building";"HighTemplar";NA;82;0
"Building";"HighTemplar";NA;86;0
"Building";"OracleStasisTrap";NA;86;0
"Building";"OracleStasisTrap";NA;88;0
"Unit";"Archon";"High Templar";88;0
"Unit";"Zealot";"Gateway";88;2
"Upgrade";"Charge";"TwilightCouncil";63;0
"Building";"Gateway";NA;79;0
"Building";"Gateway";NA;79;0
"Building";"Gateway";NA;79;0
"Building";"Assimilator";NA;88;0
"Building";"Assimilator";NA;88;0
"Building";"Gateway";NA;82;0
"Unit";"Immortal";"Robotics Facility";86;4
"Unit";"Phoenix";"Stargate";88;2
"Building";"Pylon";NA;93;0
"Unit";"Phoenix";"Stargate";88;2
"Building";"Pylon";NA;93;0
"Building";"Pylon";NA;93;0
"Upgrade";"ProtossGroundWeaponsLevel1";"Forge";70;0
"Building";"HighTemplar";NA;104;0
"Unit";"Zealot";"Gateway";104;2
"Unit";"Zealot";"Gateway";104;2
"Unit";"Zealot";"Gateway";104;2
"Unit";"Zealot";"Gateway";104;2
"Unit";"Zealot";"Gateway";104;2
"Unit";"Immortal";"Robotics Facility";93;4
"Building";"PhotonCannon";NA;104;0
"Building";"Pylon";NA;121;0
"Building";"PhotonCannon";NA;117;0
"Upgrade";"ProtossGroundArmorsLevel1";"Forge";88;0
"Building";"OracleStasisTrap";NA;122;0
"Building";"HighTemplar";NA;122;0
"Building";"HighTemplar";NA;122;0
"Building";"Pylon";NA;122;0
"Building";"Pylon";NA;122;0
"Building";"Pylon";NA;122;0
"Building";"HighTemplar";NA;122;0
"Building";"HighTemplar";NA;122;0
"Unit";"Zealot";"Gateway";122;2
"Unit";"Zealot";"Gateway";122;2
"Unit";"Zealot";"Gateway";122;2
"Unit";"Zealot";"Gateway";122;2
"Unit";"Immortal";"Robotics Facility";122;4
"Building";"PhotonCannon";NA;130;0
"Building";"PhotonCannon";NA;130;0
"Building";"PhotonCannon";NA;130;0
"Building";"Nexus";NA;122;0
"Building";"PhotonCannon";NA;130;0
"Building";"PhotonCannon";NA;130;0
"Building";"HighTemplar";NA;134;0
"Building";"HighTemplar";NA;134;0
"Building";"ShieldBattery";NA;130;0
"Building";"HighTemplar";NA;134;0
"Unit";"Zealot";"Gateway";134;2
"Unit";"Zealot";"Gateway";134;2
"Unit";"Zealot";"Gateway";134;2
"Unit";"Zealot";"Gateway";134;2
"Unit";"Zealot";"Gateway";134;2
"Unit";"Archon";"High Templar";134;0
"Unit";"Immortal";"Robotics Facility";130;4
"Upgrade";"ProtossGroundWeaponsLevel2";"Forge";122;0
"Unit";"Observer";"Robotics Facility";134;1
"Building";"Gateway";NA;134;0
"Building";"Gateway";NA;134;0
"Building";"Gateway";NA;134;0
"Building";"RoboticsFacility";NA;134;0
"Unit";"Zealot";"Gateway";149;2
"Unit";"Zealot";"Gateway";149;2
"Unit";"Zealot";"Gateway";149;2
"Building";"PhotonCannon";NA;149;0
"Building";"PhotonCannon";NA;149;0
"Building";"HighTemplar";NA;155;0
"Building";"HighTemplar";NA;155;0
"Building";"ShieldBattery";NA;149;0
"Building";"PhotonCannon";NA;149;0
"Building";"PhotonCannon";NA;149;0
"Building";"ShieldBattery";NA;149;0
"Building";"FleetBeacon";NA;149;0
"Upgrade";"ProtossGroundArmorsLevel2";"Forge";130;0
"Unit";"Zealot";"Gateway";155;2
"Building";"Stargate";NA;149;0
"Building";"Assimilator";NA;155;0
"Building";"Pylon";NA;155;0
"Building";"Assimilator";NA;155;0
"Building";"Pylon";NA;155;0
"Building";"Pylon";NA;155;0
"Building";"OracleStasisTrap";NA;157;0
"Building";"Stargate";NA;155;0
"Building";"Stargate";NA;155;0
"Building";"OracleStasisTrap";NA;157;0
"Building";"Pylon";NA;157;0
"Unit";"Zealot";"Gateway";157;2
"Unit";"Zealot";"Gateway";157;2
"Unit";"Zealot";"Gateway";157;2
"Unit";"Zealot";"Gateway";157;2
"Unit";"Zealot";"Gateway";157;2
"Unit";"Zealot";"Gateway";167;2
"Unit";"Zealot";"Gateway";167;2
"Building";"PhotonCannon";NA;157;0
"Building";"PhotonCannon";NA;157;0
"Unit";"Carrier";"Stargate";155;6
"Building";"PhotonCannon";NA;157;0
"Unit";"Observer";"Robotics Facility";157;1
"Unit";"Zealot";"Gateway";178;2
"Unit";"Phoenix";"Stargate";171;2
"Unit";"Zealot";"Gateway";182;2
"Unit";"Zealot";"Gateway";182;2
"Unit";"Zealot";"Gateway";182;2
"Building";"HighTemplar";NA;188;0
"Building";"HighTemplar";NA;188;0
"Building";"HighTemplar";NA;188;0
"Unit";"Zealot";"Gateway";188;2
"Unit";"Zealot";"Gateway";188;2
"Unit";"Zealot";"Gateway";188;2
"Unit";"Carrier";"Stargate";157;6
"Unit";"Carrier";"Stargate";157;6
"Building";"HighTemplar";NA;206;0
"Building";"HighTemplar";NA;206;0
"Upgrade";"ProtossShieldsLevel1";"Forge";167;0
"Unit";"Carrier";"Stargate";177;6
"Upgrade";"ProtossAirWeaponsLevel1";"CyberneticsCore";178;0
"Unit";"Zealot";"Gateway";212;2
"Unit";"Zealot";"Gateway";212;2
"Unit";"Zealot";"Gateway";212;2
"Unit";"Zealot";"Gateway";212;2
"Unit";"Zealot";"Gateway";212;2
"Unit";"Zealot";"Gateway";212;2
"Unit";"Carrier";"Stargate";178;6
"Unit";"Archon";"High Templar";230;0
"Unit";"Stalker";"Gateway";230;2
"Unit";"Stalker";"Gateway";230;2
"Unit";"Stalker";"Gateway";230;2
