"type";"unit_name";"on_building";"total_supply_lag";"supply"
"Building";"Pylon";NA;14;0
"Building";"Nexus";NA;17;0
"Building";"Gateway";NA;18;0
"Building";"Assimilator";NA;19;0
"Building";"Assimilator";NA;20;0
"Building";"Pylon";NA;21;0
"Building";"CyberneticsCore";NA;22;0
"Unit";"Zealot";"Gateway";23;2
"Unit";"Stalker";"Gateway";31;2
"Building";"Stargate";NA;35;0
"Building";"Pylon";NA;36;0
"Unit";"Adept";"Gateway";38;2
"Building";"Pylon";NA;40;0
"Unit";"Oracle";"Stargate";43;3
"Building";"Nexus";NA;48;0
"Unit";"Adept";"Gateway";48;2
"Building";"Pylon";NA;50;0
"Unit";"Oracle";"Stargate";52;3
"Building";"Gateway";NA;57;0
"Building";"Assimilator";NA;57;0
"Building";"Assimilator";NA;58;0
"Building";"RoboticsFacility";NA;59;0
"Unit";"Phoenix";"Stargate";61;2
"Unit";"Adept";"Gateway";66;2
"Building";"ShieldBattery";NA;72;0
"Unit";"Sentry";"Gateway";74;2
"Building";"Gateway";NA;76;0
"Building";"Forge";NA;76;0
"Building";"Pylon";NA;77;0
"Unit";"Sentry";"Gateway";77;2
"Unit";"Immortal";"Robotics Facility";79;4
"Building";"TwilightCouncil";NA;83;0
"Building";"Pylon";NA;84;0
"Building";"Pylon";NA;86;0
"Unit";"Immortal";"Robotics Facility";88;4
"Unit";"Zealot";"Gateway";92;2
"Unit";"Zealot";"Gateway";94;2
"Building";"ShieldBattery";NA;96;0
"Building";"ShieldBattery";NA;96;0
"Building";"PhotonCannon";NA;96;0
"Building";"ShieldBattery";NA;96;0
"Building";"Pylon";NA;96;0
"Building";"PhotonCannon";NA;96;0
"Building";"PhotonCannon";NA;96;0
"Building";"PhotonCannon";NA;96;0
"Unit";"Sentry";"Gateway";96;2
"Building";"Pylon";NA;98;0
"Unit";"Immortal";"Robotics Facility";98;4
"Unit";"Sentry";"Gateway";102;2
"Unit";"Sentry";"Gateway";104;2
"Building";"OracleStasisTrap";NA;106;0
"Building";"Forge";NA;110;0
"Unit";"Zealot";"Gateway";110;2
"Unit";"Zealot";"Gateway";112;2
"Unit";"Immortal";"Robotics Facility";114;4
"Building";"Gateway";NA;118;0
"Building";"Gateway";NA;118;0
"Upgrade";"Charge";"TwilightCouncil";119;0
"Unit";"Zealot";"Gateway";120;2
"Unit";"Zealot";"Gateway";122;2
"Unit";"Immortal";"Robotics Facility";126;4
"Unit";"Zealot";"Gateway";130;2
"Unit";"Zealot";"Gateway";132;2
"Building";"Pylon";NA;135;0
"Unit";"Sentry";"Gateway";136;2
"Upgrade";"ProtossGroundWeaponsLevel1";"Forge";138;0
"Unit";"Sentry";"Gateway";138;2
"Building";"Gateway";NA;140;0
"Unit";"Zealot";"Gateway";140;2
"Unit";"Zealot";"Gateway";142;2
"Building";"Gateway";NA;146;0
"Building";"Pylon";NA;146;0
"Building";"Pylon";NA;147;0
"Building";"Pylon";NA;147;0
"Unit";"Zealot";"Gateway";147;2
"Unit";"Zealot";"Gateway";149;2
"Unit";"Zealot";"Gateway";151;2
"Unit";"Immortal";"Robotics Facility";153;4
"Building";"Pylon";NA;158;0
"Unit";"Zealot";"Gateway";160;2
"Unit";"Zealot";"Gateway";162;2
"Unit";"Zealot";"Gateway";164;2
"Building";"Assimilator";NA;167;0
"Building";"Assimilator";NA;167;0
"Building";"Pylon";NA;167;0
"Building";"Stargate";NA;168;0
"Unit";"Zealot";"Gateway";168;2
"Building";"Assimilator";NA;170;0
"Unit";"Observer";"Robotics Facility";170;1
"Building";"PhotonCannon";NA;174;0
"Building";"Gateway";NA;174;0
"Unit";"Zealot";"Gateway";177;2
"Unit";"Zealot";"Gateway";179;2
"Unit";"Zealot";"Gateway";181;2
"Building";"Nexus";NA;183;0
"Building";"Pylon";NA;183;0
"Unit";"Phoenix";"Stargate";183;2
"Building";"TemplarArchive";NA;185;0
"Unit";"Zealot";"Gateway";185;2
"Building";"Pylon";NA;187;0
"Unit";"Immortal";"Robotics Facility";189;4
"Upgrade";"ProtossGroundWeaponsLevel2";"Forge";194;0
"Building";"PhotonCannon";NA;194;0
"Building";"Pylon";NA;194;0
"Unit";"Zealot";"Gateway";198;2
"Unit";"Zealot";"Gateway";200;2
"Building";"HighTemplar";NA;202;0
"Building";"HighTemplar";NA;202;0
"Building";"ShieldBattery";NA;202;0
"Unit";"Archon";"High Templar";202;0
"Building";"Gateway";NA;202;0
"Unit";"Immortal";"Robotics Facility";202;4
"Building";"Gateway";NA;208;0
"Building";"Gateway";NA;208;0
"Building";"HighTemplar";NA;208;0
"Building";"HighTemplar";NA;208;0
"Building";"HighTemplar";NA;208;0
"Unit";"Zealot";"Gateway";208;2
"Unit";"Zealot";"Gateway";210;2
"Building";"Gateway";NA;212;0
"Building";"OracleStasisTrap";NA;212;0
"Building";"HighTemplar";NA;213;0
"Building";"HighTemplar";NA;213;0
"Unit";"Zealot";"Gateway";213;2
"Unit";"Zealot";"Gateway";215;2
"Unit";"Zealot";"Gateway";217;2
"Building";"ShieldBattery";NA;221;0
"Building";"PhotonCannon";NA;221;0
"Building";"Assimilator";NA;223;0
"Building";"HighTemplar";NA;223;0
"Building";"HighTemplar";NA;223;0
"Building";"Assimilator";NA;223;0
"Unit";"Archon";"High Templar";223;0
"Unit";"Immortal";"Robotics Facility";223;4
"Unit";"Zealot";"Gateway";227;2
"Unit";"Zealot";"Gateway";229;2
"Unit";"Zealot";"Gateway";231;2
"Building";"Pylon";NA;233;0
"Building";"Pylon";NA;233;0
"Building";"Stargate";NA;233;0
"Building";"Pylon";NA;233;0
"Building";"Pylon";NA;233;0
"Unit";"Zealot";"Gateway";233;2
"Unit";"Zealot";"Gateway";235;2
"Unit";"Zealot";"Gateway";237;2
"Unit";"Zealot";"Gateway";239;2
"Unit";"Zealot";"Gateway";241;2
"Unit";"Zealot";"Gateway";243;2
"Unit";"Zealot";"Gateway";245;2
"Building";"HighTemplar";NA;247;0
"Unit";"Zealot";"Gateway";247;2
"Unit";"Zealot";"Gateway";249;2
"Unit";"Zealot";"Gateway";251;2
"Unit";"Zealot";"Gateway";253;2
"Unit";"Zealot";"Gateway";255;2
"Unit";"Zealot";"Gateway";257;2
"Unit";"Zealot";"Gateway";259;2
"Unit";"Zealot";"Gateway";261;2
"Building";"OracleStasisTrap";NA;263;0
"Unit";"Immortal";"Robotics Facility";263;4
"Upgrade";"ProtossGroundWeaponsLevel3";"Forge";267;0
"Building";"HighTemplar";NA;267;0
"Building";"FleetBeacon";NA;267;0
"Building";"OracleStasisTrap";NA;267;0
"Unit";"Zealot";"Gateway";267;2
"Unit";"Zealot";"Gateway";269;2
"Unit";"Zealot";"Gateway";271;2
"Unit";"Zealot";"Gateway";273;2
"Unit";"Zealot";"Gateway";275;2
"Unit";"Zealot";"Gateway";277;2
"Unit";"Zealot";"Gateway";279;2
"Unit";"Zealot";"Gateway";281;2
"Unit";"Zealot";"Gateway";283;2
"Unit";"Immortal";"Robotics Facility";285;4
"Building";"HighTemplar";NA;289;0
"Unit";"Zealot";"Gateway";289;2
"Unit";"Zealot";"Gateway";291;2
"Unit";"Zealot";"Gateway";293;2
"Unit";"Zealot";"Gateway";295;2
"Unit";"Archon";"High Templar";297;0
"Unit";"Zealot";"Gateway";297;2
"Unit";"Zealot";"Gateway";299;2
"Unit";"Zealot";"Gateway";301;2
"Unit";"Zealot";"Gateway";303;2
"Unit";"Zealot";"Gateway";305;2
"Unit";"Archon";"High Templar";307;0
"Unit";"Zealot";"Gateway";307;2
"Unit";"Zealot";"Gateway";309;2
"Unit";"Zealot";"Gateway";311;2
"Unit";"Zealot";"Gateway";313;2
"Building";"OracleStasisTrap";NA;315;0
"Unit";"Zealot";"Gateway";315;2
"Unit";"Zealot";"Gateway";317;2
"Unit";"Zealot";"Gateway";319;2
"Unit";"Zealot";"Gateway";321;2
"Unit";"Zealot";"Gateway";323;2
"Unit";"Zealot";"Gateway";325;2
"Unit";"Zealot";"Gateway";328;2
"Unit";"Zealot";"Gateway";330;2
"Unit";"Zealot";"Gateway";332;2
"Unit";"Zealot";"Gateway";334;2
"Unit";"Zealot";"Gateway";336;2
"Unit";"Zealot";"Gateway";338;2
"Building";"HighTemplar";NA;340;0
"Building";"HighTemplar";NA;340;0
"Building";"HighTemplar";NA;340;0
"Building";"HighTemplar";NA;340;0
"Upgrade";"SprayProtoss";NA;340;0
"Upgrade";"SprayProtoss";NA;340;0
"Upgrade";"SprayProtoss";NA;340;0
"Upgrade";"WarpGateResearch";NA;340;0
"Upgrade";"SprayProtoss";NA;340;0
"Upgrade";"SprayProtoss";NA;340;0
"Upgrade";"SprayProtoss";NA;340;0
"Upgrade";"PsiStormTech";NA;340;0
