"type";"unit_name";"on_building";"total_supply";"supply"
"Building";"Pylon";NA;13;0
"Building";"Assimilator";NA;16;0
"Building";"Gateway";NA;15;0
"Building";"Pylon";NA;20;0
"Building";"CyberneticsCore";NA;20;0
"Building";"Assimilator";NA;22;0
"Unit";"Stalker";"Gateway";21;2
"Building";"Nexus";NA;20;0
"Unit";"Stalker";"Gateway";23;2
"Building";"ShieldBattery";NA;28;0
"Building";"RoboticsFacility";NA;26;0
"Unit";"Stalker";"Gateway";33;2
"Unit";"Observer";"Robotics Facility";34;1
"Building";"Pylon";NA;36;0
"Unit";"Observer";"Robotics Facility";39;1
"Building";"Gateway";NA;38;0
"Unit";"Stalker";"Gateway";47;2
"Building";"Assimilator";NA;45;0
"Building";"Gateway";NA;39;0
"Building";"Assimilator";NA;45;0
"Building";"Pylon";NA;46;0
"Building";"RoboticsBay";NA;42;0
"Unit";"Observer";"Robotics Facility";50;1
"Unit";"Stalker";"Gateway";57;2
"Unit";"Stalker";"Gateway";57;2
"Building";"Pylon";NA;56;0
"Building";"TwilightCouncil";NA;53;0
"Unit";"Disruptor";"Robotics Facility";54;3
"Building";"Pylon";NA;62;0
"Unit";"Disruptor";"Robotics Facility";65;3
"Building";"Pylon";NA;68;0
"Unit";"Stalker";"Gateway";74;2
"Building";"Forge";NA;70;0
"Unit";"Stalker";"Gateway";78;2
"Unit";"Stalker";"Gateway";78;2
"Unit";"Disruptor";"Robotics Facility";70;3
"Building";"Gateway";NA;69;0
"Building";"Gateway";NA;69;0
"Building";"Gateway";NA;69;0
"Building";"Nexus";NA;66;0
"Building";"Pylon";NA;78;0
"Building";"Pylon";NA;86;0
"Unit";"Stalker";"Gateway";86;2
"Unit";"Stalker";"Gateway";86;2
"Unit";"Adept";"Gateway";93;2
"Unit";"Adept";"Gateway";93;2
"Unit";"Adept";"Gateway";93;2
"Unit";"Adept";"Gateway";93;2
"Unit";"Disruptor";"Robotics Facility";86;3
"Building";"Gateway";NA;86;0
"Unit";"Stalker";"Gateway";105;2
"Unit";"Stalker";"Gateway";105;2
"Building";"RoboticsFacility";NA;86;0
"Unit";"Stalker";"Gateway";109;2
"Unit";"Stalker";"Gateway";109;2
"Unit";"Stalker";"Gateway";109;2
"Unit";"Stalker";"Gateway";109;2
"Unit";"Stalker";"Gateway";120;2
"Unit";"Disruptor";"Robotics Facility";109;3
"Building";"Pylon";NA;122;0
"Building";"Pylon";NA;122;0
"Building";"Forge";NA;120;0
"Building";"Forge";NA;120;0
"Building";"ShieldBattery";NA;122;0
"Building";"Assimilator";NA;128;0
"Building";"Assimilator";NA;128;0
"Building";"Pylon";NA;128;0
"Building";"ShieldBattery";NA;128;0
"Building";"ShieldBattery";NA;128;0
"Building";"Pylon";NA;128;0
"Building";"PhotonCannon";NA;128;0
"Building";"PhotonCannon";NA;128;0
"Building";"PhotonCannon";NA;128;0
"Building";"PhotonCannon";NA;130;0
"Upgrade";"Charge";"TwilightCouncil";120;0
"Unit";"Stalker";"Gateway";132;2
"Unit";"Stalker";"Gateway";132;2
"Unit";"Stalker";"Gateway";132;2
"Unit";"Disruptor";"Robotics Facility";130;3
"Building";"TemplarArchive";NA;130;0
"Unit";"Stalker";"Gateway";143;2
"Unit";"Stalker";"Gateway";143;2
"Building";"Pylon";NA;143;0
"Unit";"Stalker";"Gateway";147;2
"Unit";"Stalker";"Gateway";147;2
"Unit";"Stalker";"Gateway";147;2
"Unit";"Stalker";"Gateway";147;2
"Unit";"Stalker";"Gateway";147;2
"Building";"Gateway";NA;139;0
"Building";"Gateway";NA;139;0
"Upgrade";"ProtossGroundWeaponsLevel1";"Forge";130;0
"Building";"Pylon";NA;157;0
"Building";"Gateway";NA;143;0
"Upgrade";"ProtossGroundArmorsLevel1";"Forge";130;0
"Building";"Pylon";NA;161;0
"Unit";"Colossus";"Robotics Facility";147;6
"Unit";"Adept";"Gateway";168;2
"Unit";"Adept";"Gateway";168;2
"Unit";"Adept";"Gateway";168;2
"Unit";"Adept";"Gateway";168;2
"Unit";"Adept";"Gateway";168;2
"Unit";"Adept";"Gateway";168;2
"Unit";"Adept";"Gateway";168;2
"Unit";"Disruptor";"Robotics Facility";168;3
"Unit";"Disruptor";"Robotics Facility";168;3
"Building";"DarkShrine";NA;159;0
"Building";"DarkTemplar";NA;190;0
"Building";"DarkTemplar";NA;190;0
"Unit";"Disruptor";"Robotics Facility";184;3
"Unit";"Disruptor";"Robotics Facility";184;3
"Building";"DarkTemplar";NA;190;0
"Building";"Pylon";NA;190;0
"Building";"DarkTemplar";NA;193;0
"Unit";"Stalker";"Gateway";199;2
"Unit";"Stalker";"Gateway";199;2
"Unit";"Stalker";"Gateway";199;2
"Unit";"Stalker";"Gateway";199;2
"Unit";"Stalker";"Gateway";199;2
"Upgrade";"ProtossGroundWeaponsLevel2";"Forge";162;0
"Unit";"Disruptor";"Robotics Facility";190;3
"Upgrade";"ProtossGroundArmorsLevel2";"Forge";168;0
"Unit";"Disruptor";"Robotics Facility";190;3
"Unit";"Stalker";"Gateway";214;2
"Unit";"Stalker";"Gateway";214;2
"Unit";"Stalker";"Gateway";214;2
"Building";"PhotonCannon";NA;209;0
"Building";"Nexus";NA;190;0
"Unit";"Disruptor";"Robotics Facility";209;3
"Building";"DarkTemplar";NA;226;0
"Unit";"Stalker";"Gateway";233;2
"Unit";"Stalker";"Gateway";233;2
"Unit";"Stalker";"Gateway";233;2
"Unit";"Stalker";"Gateway";239;2
"Unit";"Stalker";"Gateway";239;2
"Unit";"Stalker";"Gateway";243;2
"Unit";"Stalker";"Gateway";243;2
"Unit";"Stalker";"Gateway";243;2
"Unit";"Stalker";"Gateway";249;2
"Unit";"Stalker";"Gateway";249;2
"Unit";"Stalker";"Gateway";249;2
"Unit";"Stalker";"Gateway";249;2
"Upgrade";"ExtendedThermalLance";"RoboticsBay";223;0
"Unit";"Stalker";"Gateway";249;2
"Unit";"Stalker";"Gateway";249;2
"Unit";"Colossus";"Robotics Facility";229;6
"Unit";"Stalker";"Gateway";267;2
"Unit";"Stalker";"Gateway";267;2
"Unit";"Stalker";"Gateway";267;2
"Upgrade";"ProtossGroundWeaponsLevel3";"Forge";223;0
"Building";"Assimilator";NA;273;0
"Building";"Assimilator";NA;273;0
"Unit";"Zealot";"Gateway";280;2
"Unit";"Zealot";"Gateway";280;2
"Unit";"Zealot";"Gateway";280;2
"Unit";"Zealot";"Gateway";280;2
"Unit";"Zealot";"Gateway";280;2
"Unit";"Zealot";"Gateway";280;2
"Unit";"Zealot";"Gateway";280;2
"Unit";"Zealot";"Gateway";280;2
"Unit";"Zealot";"Gateway";280;2
"Building";"ShieldBattery";NA;273;0
"Building";"PhotonCannon";NA;276;0
"Unit";"Disruptor";"Robotics Facility";273;3
"Unit";"Disruptor";"Robotics Facility";273;3
"Upgrade";"ProtossGroundArmorsLevel3";"Forge";237;0
"Unit";"Stalker";"Gateway";304;2
"Unit";"Stalker";"Gateway";304;2
"Unit";"Stalker";"Gateway";304;2
"Unit";"Stalker";"Gateway";304;2
"Unit";"Stalker";"Gateway";304;2
"Unit";"Stalker";"Gateway";304;2
"Unit";"Stalker";"Gateway";304;2
"Unit";"Stalker";"Gateway";304;2
