"type";"unit_name";"on_building";"total_supply";"supply"
"Building";"Pylon";NA;13;0
"Building";"Assimilator";NA;16;0
"Building";"Gateway";NA;15;0
"Building";"Assimilator";NA;20;0
"Building";"CyberneticsCore";NA;20;0
"Building";"Pylon";NA;21;0
"Unit";"Stalker";"Gateway";22;2
"Building";"Nexus";NA;19;0
"Unit";"Stalker";"Gateway";23;2
"Building";"TwilightCouncil";NA;23;0
"Unit";"Stalker";"Gateway";29;2
"Building";"Pylon";NA;43;0
"Building";"Gateway";NA;39;0
"Building";"Gateway";NA;40;0
"Building";"Pylon";NA;45;0
"Unit";"Stalker";"Gateway";47;2
"Unit";"Stalker";"Gateway";51;2
"Unit";"Sentry";"Gateway";53;2
"Building";"Pylon";NA;53;0
"Building";"Pylon";NA;53;0
"Unit";"Sentry";"Gateway";57;2
"Unit";"Stalker";"Gateway";61;2
"Unit";"Stalker";"Gateway";61;2
"Building";"Assimilator";NA;57;0
"Building";"Assimilator";NA;59;0
"Building";"RoboticsFacility";NA;53;0
"Unit";"Stalker";"Gateway";66;2
"Unit";"Stalker";"Gateway";66;2
"Building";"Nexus";NA;51;0
"Unit";"Sentry";"Gateway";71;2
"Unit";"Observer";"Robotics Facility";66;1
"Building";"Forge";NA;70;0
"Building";"Forge";NA;70;0
"Unit";"Zealot";"Gateway";81;2
"Unit";"Zealot";"Gateway";81;2
"Building";"Pylon";NA;81;0
"Building";"ShieldBattery";NA;79;0
"Unit";"Immortal";"Robotics Facility";77;4
"Building";"Gateway";NA;80;0
"Unit";"Stalker";"Gateway";97;2
"Unit";"Stalker";"Gateway";97;2
"Unit";"Stalker";"Gateway";97;2
"Unit";"Immortal";"Robotics Facility";91;4
"Upgrade";"Charge";"TwilightCouncil";80;0
"Building";"Gateway";NA;93;0
"Unit";"Zealot";"Gateway";110;2
"Unit";"Zealot";"Gateway";110;2
"Building";"Gateway";NA;96;0
"Unit";"Zealot";"Gateway";110;2
"Building";"Gateway";NA;97;0
"Building";"Assimilator";NA;110;0
"Unit";"Immortal";"Robotics Facility";107;4
"Building";"Assimilator";NA;110;0
"Upgrade";"ProtossGroundWeaponsLevel1";"Forge";91;0
"Building";"TemplarArchive";NA;107;0
"Upgrade";"ProtossGroundArmorsLevel1";"Forge";93;0
"Building";"HighTemplar";NA;125;0
"Building";"Gateway";NA;110;0
"Building";"Pylon";NA;125;0
"Building";"Pylon";NA;125;0
"Building";"Pylon";NA;125;0
"Unit";"Zealot";"Gateway";127;2
"Unit";"Zealot";"Gateway";127;2
"Unit";"Zealot";"Gateway";127;2
"Unit";"Zealot";"Gateway";127;2
"Unit";"Zealot";"Gateway";127;2
"Building";"PhotonCannon";NA;125;0
"Building";"Gateway";NA;123;0
"Building";"Pylon";NA;142;0
"Unit";"Immortal";"Robotics Facility";139;4
"Building";"Pylon";NA;144;0
"Unit";"Zealot";"Gateway";145;2
"Unit";"Zealot";"Gateway";145;2
"Unit";"Zealot";"Gateway";145;2
"Unit";"Zealot";"Gateway";145;2
"Unit";"Zealot";"Gateway";145;2
"Building";"Pylon";NA;145;0
"Building";"Pylon";NA;145;0
"Building";"Pylon";NA;145;0
"Building";"HighTemplar";NA;162;0
"Unit";"Zealot";"Gateway";162;2
"Unit";"Zealot";"Gateway";162;2
"Unit";"Zealot";"Gateway";166;2
"Unit";"Zealot";"Gateway";166;2
"Unit";"Zealot";"Gateway";166;2
"Unit";"Zealot";"Gateway";166;2
"Building";"ShieldBattery";NA;161;0
"Building";"Nexus";NA;140;0
"Building";"HighTemplar";NA;177;0
"Building";"HighTemplar";NA;177;0
"Building";"HighTemplar";NA;177;0
"Upgrade";"ProtossGroundWeaponsLevel2";"Forge";139;0
"Building";"HighTemplar";NA;180;0
"Building";"HighTemplar";NA;180;0
"Building";"Pylon";NA;175;0
"Upgrade";"ProtossGroundArmorsLevel2";"Forge";139;0
"Unit";"Immortal";"Robotics Facility";174;4
"Building";"HighTemplar";NA;180;0
"Building";"Assimilator";NA;180;0
"Building";"HighTemplar";NA;187;0
"Unit";"Zealot";"Gateway";187;2
"Unit";"Zealot";"Gateway";187;2
"Unit";"Zealot";"Gateway";187;2
"Unit";"Zealot";"Gateway";187;2
"Unit";"Zealot";"Gateway";187;2
"Unit";"Zealot";"Gateway";187;2
"Unit";"Zealot";"Gateway";187;2
"Building";"Assimilator";NA;184;0
"Unit";"Stalker";"Gateway";201;2
"Unit";"Stalker";"Gateway";201;2
"Unit";"Stalker";"Gateway";201;2
"Building";"Pylon";NA;201;0
"Building";"PhotonCannon";NA;201;0
"Unit";"Stalker";"Gateway";207;2
"Building";"PhotonCannon";NA;201;0
"Unit";"Stalker";"Gateway";207;2
"Building";"Gateway";NA;187;0
"Unit";"Stalker";"Gateway";207;2
"Unit";"Stalker";"Gateway";207;2
"Unit";"Stalker";"Gateway";207;2
"Unit";"Stalker";"Gateway";207;2
"Building";"Gateway";NA;187;0
"Building";"Gateway";NA;187;0
"Unit";"Zealot";"Gateway";219;2
"Unit";"Zealot";"Gateway";219;2
"Unit";"Zealot";"Gateway";219;2
"Unit";"Zealot";"Gateway";219;2
"Unit";"Zealot";"Gateway";219;2
"Unit";"Zealot";"Gateway";219;2
"Unit";"Zealot";"Gateway";219;2
"Building";"HighTemplar";NA;219;0
"Building";"HighTemplar";NA;219;0
"Building";"HighTemplar";NA;219;0
"Building";"HighTemplar";NA;219;0
"Unit";"Stalker";"Gateway";233;2
"Unit";"Stalker";"Gateway";233;2
"Unit";"Stalker";"Gateway";233;2
"Unit";"Stalker";"Gateway";233;2
"Unit";"Stalker";"Gateway";233;2
"Unit";"Stalker";"Gateway";233;2
"Unit";"Stalker";"Gateway";245;2
"Unit";"Stalker";"Gateway";245;2
"Building";"Stargate";NA;219;0
"Building";"Stargate";NA;219;0
"Upgrade";"ProtossGroundWeaponsLevel3";"Forge";201;0
"Upgrade";"ProtossGroundArmorsLevel3";"Forge";201;0
"Unit";"Stalker";"Gateway";249;2
"Unit";"Stalker";"Gateway";249;2
"Unit";"Stalker";"Gateway";249;2
"Unit";"Stalker";"Gateway";249;2
"Unit";"Stalker";"Gateway";249;2
"Building";"Nexus";NA;219;0
"Building";"FleetBeacon";NA;249;0
"Unit";"Zealot";"Gateway";259;2
"Unit";"Zealot";"Gateway";259;2
"Unit";"Zealot";"Gateway";259;2
"Unit";"Zealot";"Gateway";259;2
"Unit";"Zealot";"Gateway";259;2
"Unit";"Zealot";"Gateway";259;2
"Unit";"Zealot";"Gateway";259;2
"Unit";"Zealot";"Gateway";259;2
"Unit";"Zealot";"Gateway";259;2
"Unit";"Zealot";"Gateway";259;2
"Unit";"Zealot";"Gateway";259;2
"Building";"Pylon";NA;259;0
"Unit";"Stalker";"Gateway";281;2
"Unit";"Stalker";"Gateway";283;2
"Unit";"Stalker";"Gateway";283;2
"Building";"HighTemplar";NA;283;0
"Building";"HighTemplar";NA;283;0
"Building";"HighTemplar";NA;283;0
"Building";"HighTemplar";NA;283;0
"Unit";"Tempest";"Stargate";283;4
"Unit";"Tempest";"Stargate";283;4
"Building";"HighTemplar";NA;287;0
"Building";"HighTemplar";NA;287;0
"Building";"HighTemplar";NA;287;0
"Unit";"Zealot";"Gateway";287;2
"Unit";"Zealot";"Gateway";287;2
"Unit";"Zealot";"Gateway";291;2
"Unit";"Zealot";"Gateway";295;2
"Unit";"Zealot";"Gateway";295;2
"Unit";"Zealot";"Gateway";305;2
"Unit";"Zealot";"Gateway";305;2
"Unit";"Zealot";"Gateway";305;2
"Unit";"Zealot";"Gateway";305;2
"Building";"Assimilator";NA;305;0
"Building";"Assimilator";NA;305;0
"Building";"HighTemplar";NA;316;0
"Building";"HighTemplar";NA;316;0
"Unit";"Tempest";"Stargate";287;4
"Building";"HighTemplar";NA;316;0
