"type";"unit_name";"on_building";"total_supply";"supply"
"Building";"Pylon";NA;13;0
"Building";"Assimilator";NA;15;0
"Building";"Gateway";NA;15;0
"Building";"CyberneticsCore";NA;19;0
"Building";"Assimilator";NA;20;0
"Building";"Pylon";NA;22;0
"Building";"Nexus";NA;19;0
"Unit";"Stalker";"Gateway";22;2
"Building";"TwilightCouncil";NA;23;0
"Unit";"Stalker";"Gateway";24;2
"Unit";"Stalker";"Gateway";32;2
"Building";"Gateway";NA;29;0
"Building";"Gateway";NA;29;0
"Building";"ShieldBattery";NA;33;0
"Unit";"Stalker";"Gateway";37;2
"Building";"Pylon";NA;41;0
"Unit";"Stalker";"Gateway";46;2
"Unit";"Stalker";"Gateway";46;2
"Unit";"Stalker";"Gateway";46;2
"Building";"RoboticsFacility";NA;39;0
"Building";"Pylon";NA;46;0
"Building";"Assimilator";NA;53;0
"Building";"Pylon";NA;53;0
"Unit";"Stalker";"Gateway";55;2
"Unit";"Stalker";"Gateway";55;2
"Unit";"Stalker";"Gateway";55;2
"Building";"Pylon";NA;55;0
"Unit";"Observer";"Robotics Facility";55;1
"Building";"Pylon";NA;55;0
"Unit";"Stalker";"Gateway";66;2
"Unit";"Stalker";"Gateway";66;2
"Building";"Forge";NA;64;0
"Building";"Forge";NA;65;0
"Building";"Pylon";NA;70;0
"Building";"Pylon";NA;72;0
"Building";"Nexus";NA;70;0
"Upgrade";"Charge";"TwilightCouncil";70;0
"Unit";"Zealot";"Gateway";76;2
"Unit";"Zealot";"Gateway";76;2
"Unit";"Zealot";"Gateway";76;2
"Building";"Gateway";NA;72;0
"Building";"Gateway";NA;72;0
"Building";"Gateway";NA;72;0
"Building";"Gateway";NA;72;0
"Building";"Gateway";NA;74;0
"Building";"Pylon";NA;82;0
"Unit";"Sentry";"Gateway";86;2
"Unit";"Sentry";"Gateway";86;2
"Unit";"Sentry";"Gateway";86;2
"Unit";"Zealot";"Gateway";86;2
"Unit";"Zealot";"Gateway";86;2
"Unit";"Zealot";"Gateway";86;2
"Unit";"Zealot";"Gateway";86;2
"Unit";"Zealot";"Gateway";86;2
"Upgrade";"ProtossGroundWeaponsLevel1";"Forge";71;0
"Upgrade";"ProtossGroundArmorsLevel1";"Forge";71;0
"Building";"ShieldBattery";NA;82;0
"Building";"ShieldBattery";NA;82;0
"Building";"Pylon";NA;86;0
"Unit";"Zealot";"Gateway";104;2
"Unit";"Zealot";"Gateway";104;2
"Unit";"Zealot";"Gateway";104;2
"Unit";"Zealot";"Gateway";104;2
"Unit";"Zealot";"Gateway";104;2
"Unit";"Zealot";"Gateway";104;2
"Unit";"Zealot";"Gateway";104;2
"Unit";"Zealot";"Gateway";104;2
"Building";"Assimilator";NA;121;0
"Building";"Pylon";NA;121;0
"Building";"Pylon";NA;121;0
"Building";"Pylon";NA;122;0
"Building";"Pylon";NA;123;0
"Building";"TemplarArchive";NA;121;0
"Building";"Assimilator";NA;124;0
"Building";"Assimilator";NA;124;0
"Building";"HighTemplar";NA;127;0
"Building";"HighTemplar";NA;127;0
"Building";"HighTemplar";NA;127;0
"Unit";"Zealot";"Gateway";127;2
"Unit";"Zealot";"Gateway";127;2
"Unit";"Zealot";"Gateway";127;2
"Unit";"Zealot";"Gateway";127;2
"Unit";"Zealot";"Gateway";127;2
"Upgrade";"ProtossGroundWeaponsLevel2";"Forge";121;0
"Upgrade";"ProtossGroundArmorsLevel2";"Forge";121;0
"Building";"HighTemplar";NA;137;0
"Building";"HighTemplar";NA;137;0
"Building";"HighTemplar";NA;137;0
"Building";"Pylon";NA;137;0
"Building";"HighTemplar";NA;137;0
"Unit";"Zealot";"Gateway";137;2
"Unit";"Zealot";"Gateway";137;2
"Unit";"Zealot";"Gateway";137;2
"Unit";"Zealot";"Gateway";137;2
"Building";"Gateway";NA;137;0
"Building";"Gateway";NA;137;0
"Building";"Gateway";NA;137;0
"Building";"Gateway";NA;137;0
"Unit";"Stalker";"Gateway";145;2
"Unit";"Stalker";"Gateway";145;2
"Unit";"Stalker";"Gateway";145;2
"Unit";"Stalker";"Gateway";145;2
"Unit";"Stalker";"Gateway";153;2
"Unit";"Stalker";"Gateway";153;2
"Unit";"Stalker";"Gateway";153;2
"Unit";"Stalker";"Gateway";153;2
"Unit";"Zealot";"Gateway";162;2
"Unit";"Zealot";"Gateway";162;2
"Unit";"Zealot";"Gateway";162;2
"Unit";"Zealot";"Gateway";162;2
"Unit";"Zealot";"Gateway";162;2
"Unit";"Zealot";"Gateway";162;2
"Unit";"Zealot";"Gateway";162;2
"Unit";"Zealot";"Gateway";162;2
"Unit";"Archon";"High Templar";162;0
"Unit";"Archon";"High Templar";162;0
"Unit";"Archon";"High Templar";162;0
"Unit";"Zealot";"Gateway";178;2
"Unit";"Zealot";"Gateway";178;2
"Unit";"Zealot";"Gateway";178;2
"Unit";"Zealot";"Gateway";178;2
"Unit";"Zealot";"Gateway";178;2
"Unit";"Zealot";"Gateway";178;2
"Unit";"Zealot";"Gateway";178;2
"Unit";"Zealot";"Gateway";178;2
"Unit";"Zealot";"Gateway";178;2
"Unit";"Zealot";"Gateway";178;2
"Unit";"Zealot";"Gateway";178;2
"Unit";"Zealot";"Gateway";178;2
"Unit";"Stalker";"Gateway";202;2
"Unit";"Stalker";"Gateway";202;2
"Unit";"Stalker";"Gateway";202;2
"Unit";"Stalker";"Gateway";202;2
"Unit";"Stalker";"Gateway";202;2
"Unit";"Stalker";"Gateway";202;2
"Unit";"Stalker";"Gateway";202;2
"Unit";"Stalker";"Gateway";202;2
"Unit";"Stalker";"Gateway";202;2
"Unit";"Stalker";"Gateway";202;2
"Unit";"Stalker";"Gateway";202;2
"Unit";"Stalker";"Gateway";202;2
