"type";"unit_name";"on_building";"total_supply";"supply"
"Building";"Pylon";NA;13;0
"Building";"Assimilator";NA;16;0
"Building";"Gateway";NA;15;0
"Building";"Assimilator";NA;19;0
"Building";"Pylon";NA;20;0
"Building";"CyberneticsCore";NA;19;0
"Unit";"Stalker";"Gateway";20;2
"Building";"Nexus";NA;19;0
"Unit";"Stalker";"Gateway";23;2
"Building";"Gateway";NA;22;0
"Building";"TwilightCouncil";NA;26;0
"Unit";"Stalker";"Gateway";29;2
"Unit";"Stalker";"Gateway";30;2
"Unit";"Stalker";"Gateway";38;2
"Building";"Pylon";NA;39;0
"Unit";"Stalker";"Gateway";39;2
"Unit";"Stalker";"Gateway";46;2
"Unit";"Stalker";"Gateway";48;2
"Building";"ShieldBattery";NA;42;0
"Building";"Assimilator";NA;46;0
"Building";"RoboticsFacility";NA;39;0
"Unit";"Observer";"Robotics Facility";54;1
"Building";"Pylon";NA;56;0
"Building";"Assimilator";NA;56;0
"Building";"Pylon";NA;59;0
"Building";"Pylon";NA;61;0
"Building";"Nexus";NA;56;0
"Building";"Pylon";NA;63;0
"Building";"Forge";NA;59;0
"Building";"Pylon";NA;63;0
"Building";"Forge";NA;61;0
"Unit";"Stalker";"Gateway";68;2
"Unit";"Stalker";"Gateway";68;2
"Unit";"Immortal";"Robotics Facility";64;4
"Building";"RoboticsFacility";NA;66;0
"Building";"RoboticsBay";NA;66;0
"Unit";"Zealot";"Gateway";81;2
"Unit";"Zealot";"Gateway";81;2
"Unit";"Colossus";"Robotics Facility";78;6
"Building";"Gateway";NA;78;0
"Building";"Gateway";NA;78;0
"Building";"Gateway";NA;78;0
"Unit";"Colossus";"Robotics Facility";78;6
"Building";"Gateway";NA;78;0
"Upgrade";"Charge";"TwilightCouncil";78;0
"Building";"Gateway";NA;80;0
"Building";"Gateway";NA;80;0
"Unit";"Zealot";"Gateway";100;2
"Building";"TemplarArchive";NA;85;0
"Unit";"Stalker";"Gateway";107;2
"Unit";"Stalker";"Gateway";107;2
"Unit";"Stalker";"Gateway";107;2
"Unit";"Stalker";"Gateway";107;2
"Unit";"Stalker";"Gateway";107;2
"Unit";"Stalker";"Gateway";107;2
"Unit";"Colossus";"Robotics Facility";85;6
"Upgrade";"ProtossGroundWeaponsLevel1";"Forge";80;0
"Upgrade";"ProtossGroundArmorsLevel1";"Forge";80;0
"Unit";"Colossus";"Robotics Facility";91;6
"Building";"Assimilator";NA;119;0
"Building";"Assimilator";NA;119;0
"Upgrade";"ExtendedThermalLance";"RoboticsBay";91;0
"Building";"Pylon";NA;133;0
"Unit";"Zealot";"Gateway";137;2
"Unit";"Zealot";"Gateway";137;2
"Unit";"Stalker";"Gateway";141;2
"Unit";"Stalker";"Gateway";141;2
"Building";"Pylon";NA;135;0
"Building";"Pylon";NA;135;0
"Building";"Pylon";NA;135;0
"Building";"Pylon";NA;137;0
"Building";"Assimilator";NA;137;0
"Building";"Assimilator";NA;137;0
"Building";"HighTemplar";NA;145;0
"Building";"HighTemplar";NA;145;0
"Building";"HighTemplar";NA;145;0
"Building";"HighTemplar";NA;145;0
"Building";"Nexus";NA;133;0
"Unit";"Zealot";"Gateway";148;2
"Unit";"Zealot";"Gateway";148;2
"Unit";"Zealot";"Gateway";148;2
"Unit";"Zealot";"Gateway";148;2
"Unit";"Stalker";"Gateway";158;2
"Unit";"Stalker";"Gateway";159;2
"Unit";"Stalker";"Gateway";160;2
"Unit";"Stalker";"Gateway";160;2
"Unit";"Stalker";"Gateway";168;2
"Unit";"Stalker";"Gateway";168;2
"Unit";"Stalker";"Gateway";168;2
"Unit";"Stalker";"Gateway";168;2
"Upgrade";"ProtossGroundWeaponsLevel2";"Forge";133;0
"Unit";"Archon";"High Templar";176;0
"Building";"HighTemplar";NA;176;0
"Building";"HighTemplar";NA;176;0
"Building";"HighTemplar";NA;176;0
"Building";"HighTemplar";NA;176;0
"Upgrade";"ProtossGroundArmorsLevel2";"Forge";137;0
"Unit";"Stalker";"Gateway";178;2
"Unit";"Stalker";"Gateway";178;2
"Unit";"Stalker";"Gateway";178;2
"Unit";"Stalker";"Gateway";178;2
"Unit";"Zealot";"Gateway";191;2
"Unit";"Zealot";"Gateway";191;2
"Unit";"Zealot";"Gateway";191;2
"Unit";"Zealot";"Gateway";191;2
"Unit";"Zealot";"Gateway";191;2
"Unit";"Zealot";"Gateway";191;2
"Unit";"Zealot";"Gateway";191;2
"Unit";"Zealot";"Gateway";191;2
"Unit";"Colossus";"Robotics Facility";176;6
"Unit";"Colossus";"Robotics Facility";176;6
"Building";"Pylon";NA;219;0
"Building";"Pylon";NA;219;0
"Building";"Pylon";NA;219;0
"Unit";"Zealot";"Gateway";219;2
"Unit";"Zealot";"Gateway";219;2
"Unit";"Zealot";"Gateway";219;2
"Unit";"Zealot";"Gateway";219;2
"Unit";"Zealot";"Gateway";219;2
"Upgrade";"GraviticDrive";"RoboticsBay";207;0
"Building";"Nexus";NA;191;0
"Building";"Stargate";NA;219;0
"Unit";"Zealot";"Gateway";229;2
"Unit";"Zealot";"Gateway";229;2
"Unit";"Zealot";"Gateway";229;2
"Unit";"Zealot";"Gateway";229;2
"Unit";"Zealot";"Gateway";229;2
"Unit";"Zealot";"Gateway";229;2
"Unit";"Zealot";"Gateway";229;2
"Unit";"Zealot";"Gateway";229;2
"Building";"Stargate";NA;229;0
"Building";"FleetBeacon";NA;229;0
"Building";"Stargate";NA;229;0
"Building";"HighTemplar";NA;245;0
"Building";"HighTemplar";NA;245;0
"Building";"HighTemplar";NA;245;0
"Building";"HighTemplar";NA;245;0
"Building";"HighTemplar";NA;245;0
"Building";"HighTemplar";NA;245;0
"Building";"HighTemplar";NA;245;0
"Building";"HighTemplar";NA;245;0
"Building";"Assimilator";NA;245;0
"Building";"Pylon";NA;245;0
"Building";"Assimilator";NA;245;0
"Unit";"Archon";"High Templar";245;0
"Unit";"Archon";"High Templar";245;0
"Building";"Pylon";NA;245;0
"Unit";"Archon";"High Templar";245;0
"Unit";"Archon";"High Templar";245;0
"Upgrade";"ProtossAirWeaponsLevel1";"CyberneticsCore";245;0
"Upgrade";"ProtossGroundWeaponsLevel3";"Forge";245;0
"Upgrade";"ProtossGroundArmorsLevel3";"Forge";245;0
"Unit";"Carrier";"Stargate";245;6
"Unit";"Carrier";"Stargate";245;6
"Building";"DarkShrine";NA;245;0
"Building";"Stargate";NA;245;0
"Building";"Stargate";NA;245;0
"Building";"Stargate";NA;245;0
"Building";"Stargate";NA;245;0
"Building";"DarkTemplar";NA;257;0
"Building";"DarkTemplar";NA;257;0
"Building";"Pylon";NA;257;0
"Building";"Pylon";NA;257;0
"Upgrade";"ProtossAirWeaponsLevel2";"CyberneticsCore";245;0
"Upgrade";"ProtossShieldsLevel1";"Forge";245;0
"Unit";"Carrier";"Stargate";245;6
"Unit";"Carrier";"Stargate";245;6
"Building";"DarkTemplar";NA;257;0
"Building";"DarkTemplar";NA;257;0
"Unit";"Carrier";"Stargate";245;6
"Building";"DarkTemplar";NA;275;0
"Building";"DarkTemplar";NA;275;0
"Building";"Pylon";NA;275;0
"Building";"Pylon";NA;275;0
"Building";"Pylon";NA;275;0
"Building";"Nexus";NA;257;0
"Unit";"Carrier";"Stargate";257;6
"Unit";"Carrier";"Stargate";257;6
"Unit";"Carrier";"Stargate";257;6
"Building";"Pylon";NA;275;0
"Building";"DarkTemplar";NA;293;0
"Building";"DarkTemplar";NA;293;0
"Building";"DarkTemplar";NA;293;0
"Building";"DarkTemplar";NA;293;0
"Building";"DarkTemplar";NA;293;0
"Building";"DarkTemplar";NA;293;0
"Building";"Gateway";NA;275;0
"Building";"Gateway";NA;275;0
"Building";"Gateway";NA;275;0
"Building";"Gateway";NA;275;0
"Building";"Gateway";NA;275;0
"Building";"Gateway";NA;293;0
"Building";"Gateway";NA;293;0
"Building";"Gateway";NA;293;0
"Building";"Gateway";NA;293;0
"Building";"Gateway";NA;293;0
"Building";"Gateway";NA;293;0
"Building";"Gateway";NA;293;0
"Unit";"Archon";"High Templar";293;0
