"type";"unit_name";"on_building";"total_supply";"supply"
"Building";"Pylon";NA;13;0
"Building";"Assimilator";NA;16;0
"Building";"Pylon";NA;17;0
"Building";"Gateway";NA;15;0
"Unit";"Zealot";"Gateway";19;2
"Building";"CyberneticsCore";NA;19;0
"Unit";"Stalker";"Gateway";23;2
"Building";"Assimilator";NA;23;0
"Unit";"Stalker";"Gateway";24;2
"Building";"Nexus";NA;23;0
"Unit";"Stalker";"Gateway";28;2
"Building";"TwilightCouncil";NA;28;0
"Building";"Gateway";NA;28;0
"Building";"Gateway";NA;29;0
"Building";"ShieldBattery";NA;36;0
"Unit";"Stalker";"Gateway";42;2
"Unit";"Stalker";"Gateway";42;2
"Unit";"Sentry";"Gateway";42;2
"Building";"Pylon";NA;40;0
"Building";"Assimilator";NA;41;0
"Building";"Pylon";NA;48;0
"Building";"DarkShrine";NA;35;0
"Building";"Pylon";NA;50;0
"Building";"DarkTemplar";NA;51;0
"Building";"DarkTemplar";NA;52;0
"Building";"Pylon";NA;51;0
"Building";"DarkTemplar";NA;54;0
"Building";"Assimilator";NA;58;0
"Unit";"Sentry";"Gateway";62;2
"Building";"Pylon";NA;60;0
"Building";"Forge";NA;58;0
"Building";"Forge";NA;58;0
"Unit";"Phoenix";"Stargate";60;2
"Unit";"Sentry";"Gateway";65;2
"Unit";"Stalker";"Gateway";65;2
"Building";"Gateway";NA;58;0
"Building";"Gateway";NA;58;0
"Building";"Nexus";NA;58;0
"Building";"RoboticsFacility";NA;62;0
"Unit";"Stalker";"Gateway";77;2
"Unit";"Stalker";"Gateway";77;2
"Unit";"Stalker";"Gateway";77;2
"Upgrade";"Charge";"TwilightCouncil";60;0
"Building";"Pylon";NA;77;0
"Building";"TemplarArchive";NA;76;0
"Building";"Gateway";NA;74;0
"Building";"Gateway";NA;74;0
"Building";"HighTemplar";NA;89;0
"Building";"HighTemplar";NA;89;0
"Building";"ShieldBattery";NA;86;0
"Building";"Pylon";NA;89;0
"Building";"ShieldBattery";NA;86;0
"Building";"Pylon";NA;89;0
"Upgrade";"ProtossGroundWeaponsLevel1";"Forge";74;0
"Upgrade";"ProtossGroundArmorsLevel1";"Forge";75;0
"Building";"HighTemplar";NA;93;0
"Building";"Pylon";NA;90;0
"Building";"Pylon";NA;93;0
"Unit";"Zealot";"Gateway";97;2
"Unit";"Zealot";"Gateway";97;2
"Unit";"Zealot";"Gateway";97;2
"Unit";"Zealot";"Gateway";97;2
"Unit";"Phoenix";"Stargate";93;2
"Unit";"Phoenix";"Stargate";93;2
"Building";"Assimilator";NA;96;0
"Building";"Pylon";NA;96;0
"Building";"Assimilator";NA;97;0
"Building";"HighTemplar";NA;114;0
"Unit";"Zealot";"Gateway";114;2
"Unit";"Zealot";"Gateway";114;2
"Unit";"Zealot";"Gateway";114;2
"Unit";"Zealot";"Gateway";114;2
"Unit";"Zealot";"Gateway";114;2
"Unit";"Zealot";"Gateway";114;2
"Building";"Pylon";NA;126;0
"Building";"Pylon";NA;126;0
"Unit";"Stalker";"Gateway";126;2
"Unit";"Stalker";"Gateway";126;2
"Unit";"Stalker";"Gateway";126;2
"Unit";"Stalker";"Gateway";126;2
"Unit";"Stalker";"Gateway";126;2
"Unit";"Phoenix";"Stargate";126;2
"Building";"HighTemplar";NA;138;0
"Building";"HighTemplar";NA;138;0
"Building";"HighTemplar";NA;138;0
"Building";"HighTemplar";NA;138;0
"Building";"HighTemplar";NA;138;0
"Building";"HighTemplar";NA;138;0
"Upgrade";"ProtossGroundArmorsLevel2";"Forge";111;0
"Building";"Nexus";NA;126;0
"Unit";"Immortal";"Robotics Facility";138;4
"Unit";"Archon";"High Templar";138;0
"Unit";"Archon";"High Templar";138;0
"Building";"PhotonCannon";NA;138;0
"Building";"PhotonCannon";NA;138;0
"Building";"PhotonCannon";NA;138;0
"Building";"Pylon";NA;138;0
"Building";"HighTemplar";NA;142;0
"Upgrade";"ProtossGroundWeaponsLevel2";"Forge";114;0
"Building";"HighTemplar";NA;142;0
"Unit";"Zealot";"Gateway";142;2
"Building";"Gateway";NA;138;0
"Building";"PhotonCannon";NA;138;0
"Building";"Gateway";NA;138;0
"Building";"Gateway";NA;138;0
"Building";"Gateway";NA;138;0
"Unit";"Archon";"High Templar";144;0
"Unit";"Zealot";"Gateway";144;2
"Unit";"Zealot";"Gateway";144;2
"Unit";"Zealot";"Gateway";144;2
"Unit";"Zealot";"Gateway";144;2
"Unit";"Archon";"High Templar";144;0
"Building";"HighTemplar";NA;152;0
"Building";"HighTemplar";NA;152;0
"Unit";"Zealot";"Gateway";152;2
"Unit";"Zealot";"Gateway";154;2
"Unit";"Zealot";"Gateway";154;2
"Unit";"Zealot";"Gateway";154;2
"Unit";"Zealot";"Gateway";154;2
"Unit";"Zealot";"Gateway";154;2
"Unit";"Zealot";"Gateway";154;2
"Unit";"Zealot";"Gateway";154;2
"Unit";"Zealot";"Gateway";154;2
"Unit";"Zealot";"Gateway";154;2
"Building";"Pylon";NA;172;0
"Building";"Pylon";NA;172;0
"Building";"HighTemplar";NA;172;0
"Building";"HighTemplar";NA;172;0
"Building";"HighTemplar";NA;172;0
"Unit";"Zealot";"Gateway";172;2
"Unit";"Zealot";"Gateway";172;2
"Unit";"Zealot";"Gateway";172;2
"Unit";"Zealot";"Gateway";172;2
"Unit";"Zealot";"Gateway";172;2
"Unit";"Zealot";"Gateway";172;2
"Unit";"Zealot";"Gateway";172;2
"Unit";"Zealot";"Gateway";172;2
"Building";"RoboticsBay";NA;172;0
"Unit";"Archon";"High Templar";188;0
"Building";"RoboticsFacility";NA;172;0
"Unit";"Archon";"High Templar";188;0
"Building";"HighTemplar";NA;188;0
"Building";"HighTemplar";NA;188;0
"Building";"HighTemplar";NA;188;0
"Building";"HighTemplar";NA;188;0
"Building";"HighTemplar";NA;188;0
"Unit";"Zealot";"Gateway";188;2
"Unit";"Zealot";"Gateway";188;2
"Unit";"Zealot";"Gateway";188;2
"Unit";"Zealot";"Gateway";188;2
"Unit";"Zealot";"Gateway";188;2
"Unit";"Zealot";"Gateway";188;2
"Upgrade";"ProtossGroundWeaponsLevel3";"Forge";154;0
"Upgrade";"ProtossGroundArmorsLevel3";"Forge";172;0
"Unit";"Disruptor";"Robotics Facility";190;3
"Unit";"Disruptor";"Robotics Facility";200;3
"Unit";"Zealot";"Gateway";203;2
"Unit";"Zealot";"Gateway";203;2
"Unit";"Zealot";"Gateway";203;2
"Unit";"Zealot";"Gateway";203;2
"Unit";"Zealot";"Gateway";203;2
"Unit";"Stalker";"Gateway";216;2
"Unit";"Stalker";"Gateway";216;2
"Unit";"Stalker";"Gateway";216;2
"Unit";"Stalker";"Gateway";216;2
"Unit";"Stalker";"Gateway";216;2
"Unit";"Stalker";"Gateway";216;2
"Building";"Pylon";NA;228;0
"Building";"Pylon";NA;228;0
"Unit";"Archon";"High Templar";228;0
"Building";"HighTemplar";NA;228;0
"Building";"HighTemplar";NA;228;0
"Building";"HighTemplar";NA;228;0
"Unit";"Stalker";"Gateway";228;2
"Unit";"Stalker";"Gateway";228;2
"Unit";"Stalker";"Gateway";228;2
"Unit";"Stalker";"Gateway";228;2
"Unit";"Stalker";"Gateway";228;2
"Unit";"Stalker";"Gateway";228;2
"Unit";"Zealot";"Gateway";240;2
"Unit";"Zealot";"Gateway";240;2
"Unit";"Archon";"High Templar";240;0
"Unit";"Disruptor";"Robotics Facility";228;3
"Unit";"Disruptor";"Robotics Facility";228;3
"Building";"Nexus";NA;228;0
"Upgrade";"ProtossShieldsLevel1";"Forge";228;0
"Building";"Pylon";NA;250;0
"Unit";"Zealot";"Gateway";250;2
"Unit";"Zealot";"Gateway";250;2
"Unit";"Zealot";"Gateway";250;2
"Unit";"Zealot";"Gateway";250;2
"Unit";"Zealot";"Gateway";250;2
"Unit";"Zealot";"Gateway";250;2
"Unit";"Zealot";"Gateway";250;2
"Unit";"Zealot";"Gateway";250;2
"Unit";"Zealot";"Gateway";250;2
"Unit";"Zealot";"Gateway";250;2
"Unit";"Zealot";"Gateway";250;2
"Building";"Pylon";NA;250;0
"Unit";"Disruptor";"Robotics Facility";244;3
"Unit";"Zealot";"Gateway";275;2
"Unit";"Zealot";"Gateway";275;2
"Unit";"Zealot";"Gateway";275;2
"Unit";"Zealot";"Gateway";275;2
"Unit";"Zealot";"Gateway";275;2
"Building";"Nexus";NA;250;0
"Unit";"Disruptor";"Robotics Facility";275;3
"Unit";"Disruptor";"Robotics Facility";275;3
