"type";"unit_name";"on_building";"total_supply";"supply"
"Building";"Pylon";NA;13;0
"Building";"Assimilator";NA;15;0
"Building";"Gateway";NA;14;0
"Building";"CyberneticsCore";NA;20;0
"Building";"Pylon";NA;22;0
"Building";"Assimilator";NA;22;0
"Unit";"Stalker";"Gateway";22;2
"Building";"Nexus";NA;22;0
"Building";"TwilightCouncil";NA;24;0
"Unit";"Stalker";"Gateway";28;2
"Building";"Gateway";NA;28;0
"Building";"Gateway";NA;28;0
"Unit";"Stalker";"Gateway";33;2
"Building";"Pylon";NA;35;0
"Building";"ShieldBattery";NA;35;0
"Unit";"Stalker";"Gateway";42;2
"Unit";"Stalker";"Gateway";42;2
"Unit";"Stalker";"Gateway";42;2
"Building";"ShieldBattery";NA;37;0
"Building";"Pylon";NA;42;0
"Building";"Assimilator";NA;49;0
"Building";"Forge";NA;49;0
"Building";"Forge";NA;49;0
"Unit";"Zealot";"Gateway";56;2
"Unit";"Zealot";"Gateway";56;2
"Unit";"Zealot";"Gateway";56;2
"Building";"RoboticsFacility";NA;51;0
"Building";"Pylon";NA;62;0
"Unit";"Sentry";"Gateway";63;2
"Unit";"Sentry";"Gateway";63;2
"Unit";"Sentry";"Gateway";63;2
"Unit";"Observer";"Robotics Facility";63;1
"Building";"Pylon";NA;63;0
"Building";"Nexus";NA;55;0
"Unit";"Zealot";"Gateway";71;2
"Unit";"Zealot";"Gateway";71;2
"Unit";"Observer";"Robotics Facility";69;1
"Building";"Gateway";NA;63;0
"Building";"Gateway";NA;63;0
"Unit";"Zealot";"Gateway";72;2
"Building";"Gateway";NA;63;0
"Building";"Gateway";NA;63;0
"Building";"Pylon";NA;71;0
"Unit";"Sentry";"Gateway";80;2
"Unit";"Zealot";"Gateway";81;2
"Unit";"Zealot";"Gateway";82;2
"Unit";"Zealot";"Gateway";82;2
"Upgrade";"ProtossGroundArmorsLevel1";"Forge";62;0
"Upgrade";"ProtossGroundWeaponsLevel1";"Forge";62;0
"Upgrade";"Charge";"TwilightCouncil";63;0
"Unit";"Zealot";"Gateway";92;2
"Unit";"Zealot";"Gateway";92;2
"Unit";"Immortal";"Robotics Facility";80;4
"Building";"Pylon";NA;96;0
"Building";"Pylon";NA;98;0
"Building";"PhotonCannon";NA;102;0
"Building";"PhotonCannon";NA;104;0
"Building";"PhotonCannon";NA;104;0
"Building";"Pylon";NA;105;0
"Unit";"Immortal";"Robotics Facility";104;4
"Building";"Gateway";NA;104;0
"Building";"Gateway";NA;104;0
"Building";"Gateway";NA;104;0
"Building";"Pylon";NA;105;0
"Building";"PhotonCannon";NA;105;0
"Building";"Assimilator";NA;112;0
"Building";"Assimilator";NA;112;0
"Unit";"Sentry";"Gateway";114;2
"Unit";"Zealot";"Gateway";114;2
"Unit";"Zealot";"Gateway";114;2
"Unit";"Zealot";"Gateway";114;2
"Unit";"Zealot";"Gateway";114;2
"Upgrade";"ProtossGroundArmorsLevel2";"Forge";102;0
"Unit";"Zealot";"Gateway";114;2
"Unit";"Zealot";"Gateway";114;2
"Upgrade";"ProtossGroundWeaponsLevel2";"Forge";102;0
"Building";"ShieldBattery";NA;114;0
"Building";"TemplarArchive";NA;114;0
"Unit";"Zealot";"Gateway";128;2
"Building";"Nexus";NA;105;0
"Building";"RoboticsFacility";NA;114;0
"Building";"RoboticsFacility";NA;114;0
"Unit";"Immortal";"Robotics Facility";114;4
"Building";"PhotonCannon";NA;133;0
"Unit";"Zealot";"Gateway";140;2
"Unit";"Zealot";"Gateway";140;2
"Unit";"Immortal";"Robotics Facility";137;4
"Building";"Assimilator";NA;137;0
"Unit";"Immortal";"Robotics Facility";137;4
"Building";"Assimilator";NA;137;0
"Unit";"Immortal";"Robotics Facility";137;4
"Unit";"Zealot";"Gateway";158;2
"Unit";"Zealot";"Gateway";158;2
"Unit";"Zealot";"Gateway";158;2
"Unit";"Zealot";"Gateway";158;2
"Unit";"Zealot";"Gateway";158;2
"Unit";"Zealot";"Gateway";158;2
"Building";"HighTemplar";NA;158;0
"Unit";"Zealot";"Gateway";170;2
"Unit";"Zealot";"Gateway";170;2
"Unit";"Zealot";"Gateway";170;2
"Unit";"Zealot";"Gateway";170;2
"Building";"HighTemplar";NA;178;0
"Building";"HighTemplar";NA;178;0
"Building";"HighTemplar";NA;178;0
"Unit";"Zealot";"Gateway";178;2
"Unit";"Zealot";"Gateway";178;2
"Unit";"Archon";"High Templar";182;0
"Unit";"Archon";"High Templar";182;0
"Building";"HighTemplar";NA;182;0
"Building";"HighTemplar";NA;182;0
"Unit";"Zealot";"Gateway";184;2
"Unit";"Zealot";"Gateway";185;2
"Unit";"Zealot";"Gateway";186;2
"Unit";"Zealot";"Gateway";186;2
"Unit";"Archon";"High Templar";194;0
"Upgrade";"ProtossGroundArmorsLevel3";"Forge";137;0
"Unit";"Zealot";"Gateway";194;2
"Unit";"Zealot";"Gateway";194;2
"Unit";"Zealot";"Gateway";194;2
"Unit";"Zealot";"Gateway";194;2
"Unit";"Zealot";"Gateway";194;2
"Unit";"Zealot";"Gateway";194;2
"Unit";"Zealot";"Gateway";194;2
"Unit";"Zealot";"Gateway";194;2
"Unit";"Zealot";"Gateway";194;2
"Unit";"Zealot";"Gateway";194;2
"Upgrade";"ProtossGroundWeaponsLevel3";"Forge";145;0
"Building";"DarkShrine";NA;178;0
"Building";"HighTemplar";NA;214;0
"Building";"HighTemplar";NA;214;0
"Building";"HighTemplar";NA;214;0
"Building";"HighTemplar";NA;214;0
"Building";"DarkTemplar";NA;214;0
"Building";"DarkTemplar";NA;214;0
"Building";"Nexus";NA;182;0
"Building";"DarkTemplar";NA;218;0
"Unit";"Archon";"High Templar";218;0
"Unit";"Archon";"High Templar";218;0
"Unit";"Stalker";"Gateway";218;2
"Building";"Assimilator";NA;218;0
"Unit";"Stalker";"Gateway";222;2
"Unit";"Stalker";"Gateway";223;2
"Unit";"Stalker";"Gateway";224;2
"Unit";"Stalker";"Gateway";225;2
"Unit";"Stalker";"Gateway";225;2
"Building";"Pylon";NA;222;0
"Unit";"Stalker";"Gateway";236;2
"Unit";"Stalker";"Gateway";236;2
"Unit";"Stalker";"Gateway";236;2
"Unit";"Zealot";"Gateway";242;2
"Unit";"Zealot";"Gateway";242;2
"Unit";"Zealot";"Gateway";243;2
"Unit";"Zealot";"Gateway";244;2
"Upgrade";"ProtossShieldsLevel1";"Forge";236;0
"Unit";"Zealot";"Gateway";268;2
"Unit";"Zealot";"Gateway";268;2
"Unit";"Stalker";"Gateway";268;2
"Unit";"Stalker";"Gateway";268;2
"Unit";"Stalker";"Gateway";268;2
"Unit";"Stalker";"Gateway";268;2
"Building";"DarkTemplar";NA;280;0
"Building";"DarkTemplar";NA;280;0
"Building";"DarkTemplar";NA;280;0
"Building";"DarkTemplar";NA;280;0
"Building";"DarkTemplar";NA;280;0
"Building";"DarkTemplar";NA;280;0
"Building";"Nexus";NA;257;0
"Building";"Pylon";NA;280;0
"Building";"PhotonCannon";NA;280;0
"Unit";"Zealot";"Gateway";285;2
"Unit";"Zealot";"Gateway";285;2
"Unit";"Zealot";"Gateway";285;2
"Unit";"Zealot";"Gateway";285;2
"Unit";"Archon";"High Templar";293;0
"Unit";"Archon";"High Templar";293;0
"Building";"Stargate";NA;282;0
"Unit";"Zealot";"Gateway";293;2
"Unit";"Zealot";"Gateway";293;2
"Unit";"Zealot";"Gateway";293;2
"Unit";"Zealot";"Gateway";293;2
"Unit";"Zealot";"Gateway";293;2
"Unit";"Zealot";"Gateway";293;2
"Unit";"Zealot";"Gateway";293;2
"Unit";"Zealot";"Gateway";293;2
"Unit";"Zealot";"Gateway";293;2
"Unit";"Zealot";"Gateway";293;2
"Building";"Stargate";NA;282;0
"Building";"Pylon";NA;313;0
"Building";"FleetBeacon";NA;313;0
"Unit";"Zealot";"Gateway";313;2
"Unit";"Zealot";"Gateway";313;2
"Unit";"Zealot";"Gateway";313;2
"Unit";"Zealot";"Gateway";313;2
"Unit";"Zealot";"Gateway";313;2
"Unit";"Zealot";"Gateway";313;2
"Unit";"Zealot";"Gateway";313;2
"Unit";"Zealot";"Gateway";313;2
"Unit";"Zealot";"Gateway";313;2
"Unit";"Zealot";"Gateway";313;2
"Building";"Assimilator";NA;313;0
"Building";"Assimilator";NA;313;0
"Building";"Pylon";NA;313;0
"Building";"Assimilator";NA;313;0
"Building";"Assimilator";NA;313;0
"Building";"PhotonCannon";NA;313;0
"Building";"PhotonCannon";NA;313;0
"Building";"PhotonCannon";NA;313;0
"Building";"DarkTemplar";NA;333;0
"Unit";"Immortal";"Robotics Facility";333;4
"Building";"PhotonCannon";NA;333;0
"Building";"PhotonCannon";NA;333;0
"Building";"Stargate";NA;333;0
"Building";"Stargate";NA;333;0
"Unit";"Zealot";"Gateway";337;2
"Unit";"Zealot";"Gateway";337;2
"Unit";"Zealot";"Gateway";337;2
"Unit";"Zealot";"Gateway";337;2
"Unit";"Zealot";"Gateway";337;2
"Unit";"Zealot";"Gateway";337;2
"Unit";"Zealot";"Gateway";337;2
"Unit";"Zealot";"Gateway";337;2
"Unit";"Zealot";"Gateway";337;2
"Unit";"Zealot";"Gateway";337;2
"Unit";"Zealot";"Gateway";357;2
"Unit";"Zealot";"Gateway";357;2
"Unit";"Zealot";"Gateway";357;2
"Unit";"Zealot";"Gateway";357;2
"Unit";"Zealot";"Gateway";357;2
"Unit";"Zealot";"Gateway";357;2
"Unit";"Zealot";"Gateway";357;2
"Unit";"Zealot";"Gateway";357;2
"Unit";"Zealot";"Gateway";357;2
"Unit";"Zealot";"Gateway";357;2
"Upgrade";"ProtossShieldsLevel2";"Forge";333;0
