"type";"unit_name";"on_building";"total_supply";"supply"
"Building";"Pylon";NA;13;0
"Building";"Assimilator";NA;16;0
"Building";"Gateway";NA;15;0
"Building";"Assimilator";NA;20;0
"Building";"CyberneticsCore";NA;20;0
"Building";"Pylon";NA;21;0
"Unit";"Adept";"Gateway";22;2
"Building";"Nexus";NA;19;0
"Unit";"Adept";"Gateway";23;2
"Building";"Stargate";NA;24;0
"Unit";"Oracle";"Stargate";32;3
"Building";"Pylon";NA;37;0
"Building";"Gateway";NA;36;0
"Unit";"Oracle";"Stargate";42;3
"Building";"Gateway";NA;42;0
"Building";"Assimilator";NA;49;0
"Building";"Assimilator";NA;52;0
"Building";"Pylon";NA;55;0
"Building";"Pylon";NA;55;0
"Building";"Forge";NA;53;0
"Building";"TwilightCouncil";NA;53;0
"Unit";"Sentry";"Gateway";61;2
"Unit";"Sentry";"Gateway";61;2
"Building";"Nexus";NA;48;0
"Building";"Pylon";NA;60;0
"Building";"ShieldBattery";NA;60;0
"Building";"RoboticsFacility";NA;60;0
"Unit";"Adept";"Gateway";70;2
"Unit";"Adept";"Gateway";70;2
"Unit";"Sentry";"Gateway";70;2
"Building";"Pylon";NA;68;0
"Building";"Pylon";NA;70;0
"Building";"Gateway";NA;68;0
"Building";"Gateway";NA;68;0
"Building";"Gateway";NA;68;0
"Unit";"Stalker";"Gateway";81;2
"Building";"Gateway";NA;68;0
"Unit";"Stalker";"Gateway";86;2
"Unit";"Stalker";"Gateway";86;2
"Unit";"Stalker";"Gateway";86;2
"Upgrade";"ProtossGroundWeaponsLevel1";"Forge";60;0
"Building";"ShieldBattery";NA;78;0
"Unit";"Immortal";"Robotics Facility";78;4
"Building";"Pylon";NA;81;0
"Building";"Pylon";NA;86;0
"Unit";"Observer";"Robotics Facility";86;1
"Unit";"Stalker";"Gateway";97;2
"Unit";"Stalker";"Gateway";97;2
"Building";"Pylon";NA;96;0
"Building";"Pylon";NA;96;0
"Unit";"Stalker";"Gateway";102;2
"Unit";"Stalker";"Gateway";102;2
"Unit";"Stalker";"Gateway";102;2
"Unit";"Stalker";"Gateway";102;2
"Building";"Pylon";NA;96;0
"Building";"Forge";NA;92;0
"Building";"Pylon";NA;96;0
"Unit";"Stalker";"Gateway";102;2
"Building";"Assimilator";NA;96;0
"Building";"Assimilator";NA;97;0
"Unit";"Stalker";"Gateway";114;2
"Unit";"Stalker";"Gateway";114;2
"Unit";"Stalker";"Gateway";114;2
"Unit";"Observer";"Robotics Facility";112;1
"Unit";"Zealot";"Gateway";123;2
"Unit";"Zealot";"Gateway";123;2
"Unit";"Zealot";"Gateway";123;2
"Unit";"Phoenix";"Stargate";112;2
"Unit";"Phoenix";"Stargate";112;2
"Building";"Pylon";NA;130;0
"Building";"RoboticsBay";NA;112;0
"Unit";"Zealot";"Gateway";134;2
"Unit";"Zealot";"Gateway";134;2
"Unit";"Zealot";"Gateway";134;2
"Unit";"Zealot";"Gateway";134;2
"Unit";"Zealot";"Gateway";134;2
"Unit";"Zealot";"Gateway";134;2
"Unit";"Zealot";"Gateway";134;2
"Upgrade";"ProtossGroundArmorsLevel1";"Forge";96;0
"Upgrade";"ProtossGroundWeaponsLevel2";"Forge";112;0
"Building";"PhotonCannon";NA;148;0
"Building";"PhotonCannon";NA;148;0
"Unit";"Phoenix";"Stargate";148;2
"Building";"PhotonCannon";NA;148;0
"Building";"RoboticsFacility";NA;148;0
"Unit";"Stalker";"Gateway";150;2
"Unit";"Stalker";"Gateway";150;2
"Unit";"Stalker";"Gateway";150;2
"Upgrade";"Charge";"TwilightCouncil";146;0
"Building";"Nexus";NA;148;0
"Building";"TemplarArchive";NA;148;0
"Building";"Pylon";NA;157;0
"Unit";"Colossus";"Robotics Facility";148;6
"Building";"HighTemplar";NA;166;0
"Building";"Assimilator";NA;168;0
"Upgrade";"ExtendedThermalLance";"RoboticsBay";148;0
"Building";"Assimilator";NA;169;0
"Upgrade";"ProtossGroundArmorsLevel2";"Forge";148;0
"Unit";"Colossus";"Robotics Facility";157;6
"Unit";"Zealot";"Gateway";169;2
"Unit";"Zealot";"Gateway";169;2
"Unit";"Zealot";"Gateway";169;2
"Unit";"Zealot";"Gateway";169;2
"Unit";"Zealot";"Gateway";169;2
"Unit";"Zealot";"Gateway";169;2
"Unit";"Zealot";"Gateway";169;2
"Unit";"Colossus";"Robotics Facility";157;6
"Unit";"Phoenix";"Stargate";169;2
"Unit";"Phoenix";"Stargate";169;2
"Building";"FleetBeacon";NA;169;0
"Building";"Stargate";NA;169;0
"Unit";"Oracle";"Stargate";179;3
"Unit";"Disruptor";"Robotics Facility";195;3
"Unit";"Colossus";"Robotics Facility";195;6
"Upgrade";"ProtossGroundWeaponsLevel3";"Forge";160;0
"Unit";"Disruptor";"Robotics Facility";199;3
"Building";"HighTemplar";NA;211;0
"Building";"HighTemplar";NA;211;0
"Unit";"Zealot";"Gateway";211;2
"Unit";"Zealot";"Gateway";211;2
"Building";"OracleStasisTrap";NA;218;0
"Building";"Gateway";NA;199;0
"Building";"PhotonCannon";NA;205;0
"Building";"PhotonCannon";NA;205;0
"Building";"Gateway";NA;202;0
"Building";"OracleStasisTrap";NA;218;0
"Building";"Gateway";NA;202;0
"Unit";"Tempest";"Stargate";205;4
"Building";"PhotonCannon";NA;211;0
"Unit";"Tempest";"Stargate";205;4
"Building";"Gateway";NA;205;0
"Unit";"Immortal";"Robotics Facility";211;4
"Building";"DarkShrine";NA;199;0
"Unit";"Archon";"High Templar";230;0
"Building";"Nexus";NA;205;0
"Unit";"Stalker";"Gateway";230;2
"Unit";"Stalker";"Gateway";230;2
"Unit";"Stalker";"Gateway";230;2
"Unit";"Stalker";"Gateway";230;2
"Unit";"Zealot";"Gateway";238;2
"Unit";"Zealot";"Gateway";238;2
"Unit";"Zealot";"Gateway";238;2
"Unit";"Zealot";"Gateway";238;2
"Unit";"Zealot";"Gateway";238;2
"Unit";"Zealot";"Gateway";238;2
"Unit";"Zealot";"Gateway";238;2
"Unit";"Zealot";"Gateway";238;2
"Unit";"Zealot";"Gateway";238;2
"Unit";"Zealot";"Gateway";238;2
"Unit";"Zealot";"Gateway";238;2
"Building";"Pylon";NA;238;0
"Unit";"Tempest";"Stargate";230;4
"Building";"Pylon";NA;260;0
"Building";"Pylon";NA;260;0
"Unit";"Tempest";"Stargate";230;4
"Building";"PhotonCannon";NA;238;0
"Building";"HighTemplar";NA;264;0
"Building";"HighTemplar";NA;264;0
"Building";"HighTemplar";NA;264;0
"Building";"HighTemplar";NA;264;0
"Building";"HighTemplar";NA;264;0
"Unit";"Stalker";"Gateway";264;2
"Unit";"Stalker";"Gateway";264;2
"Unit";"Stalker";"Gateway";264;2
"Unit";"Stalker";"Gateway";264;2
"Upgrade";"ProtossGroundArmorsLevel3";"Forge";211;0
"Building";"PhotonCannon";NA;254;0
"Building";"PhotonCannon";NA;260;0
"Upgrade";"ProtossShieldsLevel1";"Forge";226;0
"Unit";"Immortal";"Robotics Facility";260;4
"Unit";"Colossus";"Robotics Facility";260;6
"Unit";"Immortal";"Robotics Facility";276;4
"Upgrade";"GraviticDrive";"RoboticsBay";282;0
"Building";"Assimilator";NA;288;0
"Unit";"Zealot";"Gateway";292;2
"Unit";"Zealot";"Gateway";292;2
"Unit";"Zealot";"Gateway";292;2
"Unit";"Zealot";"Gateway";292;2
"Unit";"Zealot";"Gateway";292;2
"Unit";"Zealot";"Gateway";292;2
"Unit";"Zealot";"Gateway";292;2
"Unit";"Zealot";"Gateway";292;2
"Unit";"Zealot";"Gateway";292;2
"Unit";"Zealot";"Gateway";292;2
"Building";"OracleStasisTrap";NA;312;0
"Building";"CyberneticsCore";NA;288;0
"Building";"OracleStasisTrap";NA;312;0
"Unit";"Colossus";"Robotics Facility";282;6
"Building";"HighTemplar";NA;312;0
"Unit";"Zealot";"Gateway";318;2
"Upgrade";"ProtossAirWeaponsLevel1";"CyberneticsCore";282;0
"Building";"Assimilator";NA;318;0
"Building";"Pylon";NA;320;0
"Unit";"Mothership";"Mothership Core";312;6
"Building";"Pylon";NA;320;0
"Upgrade";"ProtossShieldsLevel2";"Forge";292;0
"Building";"Gateway";NA;320;0
"Building";"Gateway";NA;320;0
"Building";"Gateway";NA;320;0
"Building";"Gateway";NA;320;0
"Building";"Gateway";NA;320;0
"Building";"Gateway";NA;320;0
