"type";"unit_name";"on_building";"total_supply";"supply"
"Building";"Pylon";NA;13;0
"Building";"Assimilator";NA;16;0
"Building";"Gateway";NA;15;0
"Building";"Assimilator";NA;20;0
"Building";"CyberneticsCore";NA;20;0
"Building";"Pylon";NA;21;0
"Building";"Nexus";NA;19;0
"Unit";"Stalker";"Gateway";22;2
"Building";"TwilightCouncil";NA;23;0
"Unit";"Stalker";"Gateway";24;2
"Unit";"Stalker";"Gateway";32;2
"Building";"Pylon";NA;38;0
"Building";"Gateway";NA;35;0
"Building";"Gateway";NA;35;0
"Building";"Assimilator";NA;40;0
"Unit";"Stalker";"Gateway";45;2
"Unit";"Stalker";"Gateway";45;2
"Unit";"Stalker";"Gateway";45;2
"Building";"RoboticsFacility";NA;40;0
"Building";"Pylon";NA;44;0
"Building";"Pylon";NA;52;0
"Building";"Pylon";NA;52;0
"Unit";"Observer";"Robotics Facility";52;1
"Unit";"Stalker";"Gateway";55;2
"Unit";"Stalker";"Gateway";55;2
"Unit";"Stalker";"Gateway";55;2
"Unit";"Observer";"Robotics Facility";54;1
"Unit";"Stalker";"Gateway";63;2
"Unit";"Stalker";"Gateway";63;2
"Unit";"Observer";"Robotics Facility";62;1
"Building";"Pylon";NA;63;0
"Building";"Pylon";NA;71;0
"Building";"Nexus";NA;56;0
"Building";"Forge";NA;72;0
"Building";"Forge";NA;72;0
"Unit";"Sentry";"Gateway";78;2
"Unit";"Sentry";"Gateway";78;2
"Unit";"Observer";"Robotics Facility";76;1
"Upgrade";"Charge";"TwilightCouncil";71;0
"Building";"Gateway";NA;76;0
"Building";"Gateway";NA;76;0
"Building";"Gateway";NA;76;0
"Building";"Pylon";NA;86;0
"Building";"Pylon";NA;86;0
"Building";"Gateway";NA;85;0
"Building";"Pylon";NA;89;0
"Building";"Gateway";NA;86;0
"Building";"Pylon";NA;92;0
"Unit";"Zealot";"Gateway";93;2
"Unit";"Zealot";"Gateway";93;2
"Unit";"Zealot";"Gateway";93;2
"Unit";"Zealot";"Gateway";93;2
"Unit";"Zealot";"Gateway";93;2
"Unit";"Zealot";"Gateway";93;2
"Building";"Assimilator";NA;93;0
"Unit";"Zealot";"Gateway";108;2
"Unit";"Zealot";"Gateway";108;2
"Building";"Assimilator";NA;93;0
"Unit";"Observer";"Robotics Facility";93;1
"Upgrade";"ProtossGroundArmorsLevel1";"Forge";82;0
"Building";"Gateway";NA;91;0
"Building";"Gateway";NA;91;0
"Upgrade";"ProtossGroundWeaponsLevel1";"Forge";85;0
"Building";"Gateway";NA;92;0
"Building";"Gateway";NA;92;0
"Building";"Pylon";NA;112;0
"Building";"Assimilator";NA;112;0
"Unit";"Zealot";"Gateway";115;2
"Unit";"Zealot";"Gateway";115;2
"Unit";"Zealot";"Gateway";115;2
"Unit";"Zealot";"Gateway";115;2
"Unit";"Zealot";"Gateway";115;2
"Building";"TemplarArchive";NA;113;0
"Unit";"Zealot";"Gateway";125;2
"Unit";"Zealot";"Gateway";125;2
"Unit";"Zealot";"Gateway";125;2
"Unit";"Zealot";"Gateway";125;2
"Unit";"Immortal";"Robotics Facility";113;4
"Building";"Nexus";NA;113;0
"Unit";"Stalker";"Gateway";137;2
"Unit";"Stalker";"Gateway";137;2
"Unit";"Stalker";"Gateway";137;2
"Unit";"Stalker";"Gateway";137;2
"Unit";"Stalker";"Gateway";137;2
"Unit";"Stalker";"Gateway";137;2
"Unit";"Stalker";"Gateway";137;2
"Building";"Pylon";NA;137;0
"Unit";"Immortal";"Robotics Facility";137;4
"Building";"Stargate";NA;137;0
"Upgrade";"ProtossGroundArmorsLevel2";"Forge";115;0
"Upgrade";"ProtossGroundWeaponsLevel2";"Forge";117;0
"Building";"HighTemplar";NA;163;0
"Building";"HighTemplar";NA;163;0
"Building";"HighTemplar";NA;163;0
"Building";"HighTemplar";NA;163;0
"Unit";"Immortal";"Robotics Facility";155;4
"Building";"HighTemplar";NA;165;0
"Building";"HighTemplar";NA;165;0
"Building";"Pylon";NA;165;0
"Building";"Pylon";NA;165;0
"Building";"FleetBeacon";NA;163;0
"Building";"Pylon";NA;169;0
"Building";"Stargate";NA;163;0
"Building";"Pylon";NA;169;0
"Building";"Pylon";NA;169;0
"Building";"HighTemplar";NA;172;0
"Building";"HighTemplar";NA;172;0
"Building";"Pylon";NA;169;0
"Building";"HighTemplar";NA;170;0
"Building";"Pylon";NA;172;0
"Building";"Pylon";NA;172;0
"Building";"Pylon";NA;172;0
"Building";"Pylon";NA;172;0
"Building";"Pylon";NA;172;0
"Building";"Pylon";NA;172;0
"Building";"PhotonCannon";NA;172;0
"Building";"Pylon";NA;172;0
"Building";"PhotonCannon";NA;172;0
"Building";"PhotonCannon";NA;172;0
"Building";"Pylon";NA;172;0
"Building";"Assimilator";NA;172;0
"Building";"Stargate";NA;172;0
"Building";"Pylon";NA;172;0
"Building";"Assimilator";NA;172;0
"Building";"PhotonCannon";NA;172;0
"Building";"PhotonCannon";NA;172;0
"Unit";"Carrier";"Stargate";172;6
"Building";"PhotonCannon";NA;175;0
"Unit";"Carrier";"Stargate";172;6
"Building";"PhotonCannon";NA;175;0
"Building";"ShieldBattery";NA;175;0
"Building";"ShieldBattery";NA;175;0
"Building";"Pylon";NA;176;0
"Building";"Pylon";NA;188;0
"Unit";"Stalker";"Gateway";188;2
"Unit";"Stalker";"Gateway";188;2
"Unit";"Stalker";"Gateway";188;2
"Unit";"Stalker";"Gateway";188;2
"Building";"Pylon";NA;188;0
"Building";"Pylon";NA;188;0
"Building";"Pylon";NA;188;0
"Upgrade";"ProtossAirWeaponsLevel1";"CyberneticsCore";172;0
"Unit";"Carrier";"Stargate";176;6
"Unit";"Carrier";"Stargate";176;6
"Unit";"Carrier";"Stargate";176;6
"Unit";"Stalker";"Gateway";202;2
"Unit";"Stalker";"Gateway";202;2
"Unit";"Stalker";"Gateway";202;2
"Unit";"Stalker";"Gateway";202;2
"Unit";"Stalker";"Gateway";214;2
"Building";"Nexus";NA;188;0
"Upgrade";"ProtossShieldsLevel1";"Forge";188;0
"Unit";"Zealot";"Gateway";224;2
"Unit";"Zealot";"Gateway";224;2
"Unit";"Zealot";"Gateway";224;2
"Unit";"Zealot";"Gateway";224;2
"Unit";"Archon";"High Templar";224;0
"Unit";"Zealot";"Gateway";232;2
"Unit";"Zealot";"Gateway";232;2
"Unit";"Zealot";"Gateway";232;2
"Unit";"Zealot";"Gateway";232;2
"Unit";"Zealot";"Gateway";232;2
"Building";"HighTemplar";NA;242;0
"Building";"HighTemplar";NA;242;0
"Building";"HighTemplar";NA;242;0
"Building";"HighTemplar";NA;242;0
"Upgrade";"ProtossGroundArmorsLevel3";"Forge";188;0
"Unit";"Mothership";"Mothership Core";196;6
"Unit";"Carrier";"Stargate";216;6
"Unit";"Carrier";"Stargate";218;6
"Building";"Assimilator";NA;252;0
"Unit";"Carrier";"Stargate";224;6
"Upgrade";"ProtossAirWeaponsLevel2";"CyberneticsCore";220;0
"Building";"Assimilator";NA;252;0
"Building";"Pylon";NA;252;0
"Unit";"Zealot";"Gateway";270;2
"Unit";"Zealot";"Gateway";270;2
"Unit";"Zealot";"Gateway";270;2
"Unit";"Zealot";"Gateway";270;2
"Unit";"Zealot";"Gateway";270;2
"Unit";"Zealot";"Gateway";270;2
"Unit";"Zealot";"Gateway";270;2
"Unit";"Zealot";"Gateway";270;2
"Unit";"Zealot";"Gateway";270;2
"Building";"PhotonCannon";NA;252;0
"Unit";"Archon";"High Templar";270;0
"Unit";"Zealot";"Gateway";280;2
"Building";"PhotonCannon";NA;252;0
"Building";"HighTemplar";NA;288;0
"Building";"HighTemplar";NA;290;0
"Building";"PhotonCannon";NA;264;0
"Building";"PhotonCannon";NA;264;0
"Building";"ShieldBattery";NA;264;0
"Unit";"Archon";"High Templar";290;0
"Unit";"Observer";"Robotics Facility";290;1
"Upgrade";"ProtossShieldsLevel2";"Forge";248;0
"Building";"HighTemplar";NA;291;0
"Building";"HighTemplar";NA;291;0
"Building";"HighTemplar";NA;291;0
"Building";"HighTemplar";NA;291;0
"Upgrade";"ProtossGroundWeaponsLevel3";"Forge";264;0
"Building";"Pylon";NA;291;0
"Building";"Pylon";NA;291;0
"Unit";"Archon";"High Templar";291;0
