"type";"unit_name";"on_building";"total_supply";"supply"
"Building";"Pylon";NA;13;0
"Building";"Assimilator";NA;16;0
"Building";"Gateway";NA;15;0
"Building";"Pylon";NA;21;0
"Unit";"Zealot";"Gateway";20;2
"Building";"CyberneticsCore";NA;20;0
"Building";"Assimilator";NA;21;0
"Unit";"Adept";"Gateway";21;2
"Building";"Nexus";NA;19;0
"Unit";"Adept";"Gateway";24;2
"Unit";"Sentry";"Gateway";33;2
"Building";"Gateway";NA;29;0
"Building";"Gateway";NA;30;0
"Building";"Pylon";NA;38;0
"Building";"Pylon";NA;40;0
"Building";"Pylon";NA;42;0
"Unit";"Stalker";"Gateway";44;2
"Unit";"Stalker";"Gateway";44;2
"Unit";"Stalker";"Gateway";44;2
"Building";"TwilightCouncil";NA;42;0
"Unit";"Stalker";"Gateway";54;2
"Unit";"Stalker";"Gateway";54;2
"Unit";"Stalker";"Gateway";54;2
"Unit";"Stalker";"Gateway";61;2
"Unit";"Stalker";"Gateway";61;2
"Unit";"Stalker";"Gateway";61;2
"Building";"Assimilator";NA;69;0
"Building";"Assimilator";NA;69;0
"Building";"Forge";NA;63;0
"Unit";"Zealot";"Gateway";73;2
"Unit";"Zealot";"Gateway";73;2
"Unit";"Zealot";"Gateway";73;2
"Building";"Pylon";NA;73;0
"Building";"RoboticsFacility";NA;69;0
"Building";"Pylon";NA;81;0
"Unit";"Zealot";"Gateway";85;2
"Unit";"Zealot";"Gateway";85;2
"Unit";"Zealot";"Gateway";85;2
"Unit";"Observer";"Robotics Facility";85;1
"Building";"Pylon";NA;93;0
"Unit";"Observer";"Robotics Facility";93;1
"Unit";"Zealot";"Gateway";97;2
"Unit";"Zealot";"Gateway";97;2
"Unit";"Zealot";"Gateway";97;2
"Building";"Forge";NA;94;0
"Building";"Pylon";NA;97;0
"Building";"Pylon";NA;97;0
"Building";"Nexus";NA;83;0
"Building";"Gateway";NA;94;0
"Building";"Gateway";NA;94;0
"Building";"Gateway";NA;94;0
"Unit";"Immortal";"Robotics Facility";94;4
"Building";"Pylon";NA;103;0
"Upgrade";"ProtossGroundArmorsLevel1";"Forge";83;0
"Unit";"Zealot";"Gateway";110;2
"Unit";"Zealot";"Gateway";110;2
"Unit";"Zealot";"Gateway";110;2
"Unit";"Immortal";"Robotics Facility";103;4
"Unit";"Zealot";"Gateway";118;2
"Unit";"Zealot";"Gateway";118;2
"Unit";"Zealot";"Gateway";118;2
"Upgrade";"Charge";"TwilightCouncil";97;0
"Building";"TemplarArchive";NA;110;0
"Unit";"Zealot";"Gateway";128;2
"Unit";"Zealot";"Gateway";128;2
"Unit";"Zealot";"Gateway";128;2
"Building";"Pylon";NA;128;0
"Building";"Pylon";NA;128;0
"Building";"HighTemplar";NA;134;0
"Building";"HighTemplar";NA;134;0
"Building";"HighTemplar";NA;134;0
"Unit";"Zealot";"Gateway";134;2
"Unit";"Zealot";"Gateway";134;2
"Unit";"Zealot";"Gateway";134;2
"Unit";"Observer";"Robotics Facility";128;1
"Unit";"Archon";"High Templar";140;0
"Unit";"Zealot";"Gateway";141;2
"Unit";"Zealot";"Gateway";141;2
"Unit";"Zealot";"Gateway";141;2
"Unit";"Zealot";"Gateway";141;2
"Unit";"Zealot";"Gateway";141;2
"Unit";"Zealot";"Gateway";141;2
"Unit";"Immortal";"Robotics Facility";134;4
"Unit";"Stalker";"Gateway";157;2
"Unit";"Stalker";"Gateway";157;2
"Unit";"Stalker";"Gateway";157;2
"Unit";"Zealot";"Gateway";157;2
"Unit";"Zealot";"Gateway";157;2
"Unit";"Zealot";"Gateway";157;2
"Upgrade";"ProtossGroundWeaponsLevel1";"Forge";128;0
"Upgrade";"ProtossGroundArmorsLevel2";"Forge";128;0
"Unit";"Immortal";"Robotics Facility";153;4
"Building";"Pylon";NA;169;0
"Building";"HighTemplar";NA;169;0
"Building";"HighTemplar";NA;169;0
"Building";"HighTemplar";NA;169;0
"Unit";"Zealot";"Gateway";169;2
"Building";"Assimilator";NA;169;0
"Building";"Assimilator";NA;169;0
"Unit";"Zealot";"Gateway";175;2
"Unit";"Zealot";"Gateway";175;2
"Building";"ShieldBattery";NA;169;0
"Unit";"Archon";"High Templar";175;0
"Building";"Gateway";NA;169;0
"Unit";"Stalker";"Gateway";179;2
"Building";"Gateway";NA;169;0
"Building";"Gateway";NA;169;0
"Unit";"Stalker";"Gateway";181;2
"Unit";"Stalker";"Gateway";181;2
"Building";"Gateway";NA;169;0
"Building";"RoboticsBay";NA;169;0
"Unit";"Zealot";"Gateway";185;2
"Unit";"Zealot";"Gateway";185;2
"Unit";"Zealot";"Gateway";185;2
"Unit";"Zealot";"Gateway";191;2
"Unit";"Zealot";"Gateway";193;2
"Unit";"Zealot";"Gateway";193;2
"Unit";"Zealot";"Gateway";197;2
"Unit";"Zealot";"Gateway";197;2
"Unit";"Zealot";"Gateway";197;2
"Unit";"Immortal";"Robotics Facility";185;4
"Unit";"Zealot";"Gateway";203;2
"Unit";"Zealot";"Gateway";203;2
"Unit";"Zealot";"Gateway";203;2
"Unit";"Zealot";"Gateway";207;2
"Unit";"Zealot";"Gateway";207;2
"Unit";"Zealot";"Gateway";217;2
"Unit";"Zealot";"Gateway";217;2
"Unit";"Zealot";"Gateway";217;2
"Upgrade";"ProtossGroundWeaponsLevel2";"Forge";175;0
"Building";"HighTemplar";NA;223;0
"Building";"HighTemplar";NA;223;0
"Building";"HighTemplar";NA;223;0
"Building";"HighTemplar";NA;223;0
"Building";"HighTemplar";NA;223;0
"Unit";"Immortal";"Robotics Facility";197;4
"Building";"HighTemplar";NA;223;0
"Building";"HighTemplar";NA;223;0
"Unit";"Archon";"High Templar";223;0
"Unit";"Archon";"High Templar";223;0
"Unit";"Archon";"High Templar";227;0
"Unit";"Zealot";"Gateway";227;2
"Unit";"Zealot";"Gateway";227;2
"Unit";"Zealot";"Gateway";227;2
"Upgrade";"ProtossGroundArmorsLevel3";"Forge";179;0
"Building";"HighTemplar";NA;233;0
"Unit";"Zealot";"Gateway";233;2
"Unit";"Zealot";"Gateway";233;2
"Unit";"Colossus";"Robotics Facility";223;6
"Building";"Pylon";NA;237;0
"Unit";"Stalker";"Gateway";243;2
"Unit";"Stalker";"Gateway";243;2
"Unit";"Stalker";"Gateway";243;2
"Unit";"Stalker";"Gateway";243;2
"Unit";"Stalker";"Gateway";243;2
"Unit";"Stalker";"Gateway";243;2
"Unit";"Stalker";"Gateway";255;2
"Building";"Pylon";NA;257;0
"Building";"Pylon";NA;257;0
"Building";"Pylon";NA;257;0
"Building";"HighTemplar";NA;257;0
"Building";"HighTemplar";NA;257;0
"Building";"Nexus";NA;233;0
"Unit";"Stalker";"Gateway";257;2
"Unit";"Colossus";"Robotics Facility";243;6
"Unit";"Archon";"High Templar";257;0
"Unit";"Stalker";"Gateway";257;2
"Unit";"Stalker";"Gateway";257;2
"Unit";"Stalker";"Gateway";257;2
"Unit";"Zealot";"Gateway";257;2
"Unit";"Zealot";"Gateway";257;2
"Unit";"Zealot";"Gateway";257;2
"Upgrade";"ExtendedThermalLance";"RoboticsBay";243;0
"Unit";"Stalker";"Gateway";277;2
"Unit";"Archon";"High Templar";277;0
"Unit";"Zealot";"Gateway";279;2
"Unit";"Zealot";"Gateway";279;2
"Unit";"Zealot";"Gateway";279;2
"Unit";"Zealot";"Gateway";279;2
"Unit";"Zealot";"Gateway";279;2
"Unit";"Zealot";"Gateway";279;2
"Unit";"Zealot";"Gateway";279;2
"Upgrade";"ProtossGroundWeaponsLevel3";"Forge";243;0
"Unit";"Stalker";"Gateway";293;2
"Unit";"Stalker";"Gateway";293;2
"Unit";"Stalker";"Gateway";293;2
"Unit";"Stalker";"Gateway";293;2
