"type";"unit_name";"on_building";"total_supply";"supply"
"Building";"Pylon";NA;13;0
"Building";"Assimilator";NA;16;0
"Building";"Gateway";NA;15;0
"Building";"Pylon";NA;19;0
"Unit";"Zealot";"Gateway";19;2
"Building";"CyberneticsCore";NA;19;0
"Unit";"Stalker";"Gateway";24;2
"Building";"Assimilator";NA;27;0
"Unit";"Stalker";"Gateway";27;2
"Building";"Nexus";NA;24;0
"Building";"Pylon";NA;32;0
"Building";"TwilightCouncil";NA;32;0
"Building";"Gateway";NA;32;0
"Building";"Gateway";NA;32;0
"Unit";"Stalker";"Gateway";43;2
"Unit";"Stalker";"Gateway";43;2
"Building";"ShieldBattery";NA;38;0
"Building";"RoboticsFacility";NA;36;0
"Unit";"Stalker";"Gateway";49;2
"Building";"Pylon";NA;49;0
"Building";"Assimilator";NA;49;0
"Building";"RoboticsFacility";NA;40;0
"Building";"Assimilator";NA;53;0
"Unit";"Sentry";"Gateway";56;2
"Unit";"Stalker";"Gateway";58;2
"Unit";"Observer";"Robotics Facility";54;1
"Unit";"Observer";"Robotics Facility";54;1
"Unit";"Stalker";"Gateway";62;2
"Building";"Pylon";NA;56;0
"Building";"Pylon";NA;62;0
"Unit";"Sentry";"Gateway";68;2
"Unit";"Observer";"Robotics Facility";66;1
"Unit";"Stalker";"Gateway";69;2
"Unit";"Zealot";"Gateway";69;2
"Building";"Pylon";NA;68;0
"Unit";"Immortal";"Robotics Facility";66;4
"Building";"Nexus";NA;54;0
"Building";"Pylon";NA;77;0
"Unit";"Stalker";"Gateway";84;2
"Unit";"Stalker";"Gateway";84;2
"Unit";"Stalker";"Gateway";84;2
"Unit";"Sentry";"Gateway";96;2
"Unit";"Sentry";"Gateway";96;2
"Unit";"Sentry";"Gateway";96;2
"Building";"Assimilator";NA;93;0
"Building";"Assimilator";NA;95;0
"Building";"RoboticsBay";NA;90;0
"Unit";"Stalker";"Gateway";108;2
"Unit";"Stalker";"Gateway";108;2
"Building";"Gateway";NA;90;0
"Building";"Gateway";NA;92;0
"Unit";"Stalker";"Gateway";112;2
"Building";"Gateway";NA;93;0
"Unit";"Immortal";"Robotics Facility";98;4
"Unit";"Immortal";"Robotics Facility";104;4
"Unit";"Zealot";"Gateway";122;2
"Unit";"Zealot";"Gateway";122;2
"Building";"Pylon";NA;122;0
"Building";"Pylon";NA;122;0
"Building";"Pylon";NA;122;0
"Unit";"Zealot";"Gateway";126;2
"Building";"Pylon";NA;122;0
"Building";"Pylon";NA;126;0
"Building";"ShieldBattery";NA;126;0
"Building";"Pylon";NA;128;0
"Unit";"Disruptor";"Robotics Facility";122;3
"Building";"ShieldBattery";NA;126;0
"Building";"Pylon";NA;128;0
"Unit";"Disruptor";"Robotics Facility";126;3
"Building";"Pylon";NA;128;0
"Unit";"Disruptor";"Robotics Facility";128;3
"Building";"Pylon";NA;134;0
"Building";"Gateway";NA;128;0
"Building";"Gateway";NA;128;0
"Building";"Gateway";NA;128;0
"Unit";"Disruptor";"Robotics Facility";131;3
"Building";"Pylon";NA;140;0
"Unit";"Zealot";"Gateway";143;2
"Unit";"Zealot";"Gateway";143;2
"Unit";"Zealot";"Gateway";143;2
"Unit";"Stalker";"Gateway";143;2
"Unit";"Stalker";"Gateway";143;2
"Unit";"Stalker";"Gateway";143;2
"Unit";"Stalker";"Gateway";143;2
"Unit";"Stalker";"Gateway";143;2
"Building";"Forge";NA;140;0
"Building";"Pylon";NA;143;0
"Unit";"Disruptor";"Robotics Facility";140;3
"Building";"Forge";NA;140;0
"Building";"Pylon";NA;143;0
"Upgrade";"Charge";"TwilightCouncil";131;0
"Unit";"Disruptor";"Robotics Facility";140;3
"Unit";"Zealot";"Gateway";165;2
"Unit";"Zealot";"Gateway";165;2
"Unit";"Zealot";"Gateway";165;2
"Unit";"Zealot";"Gateway";165;2
"Unit";"Zealot";"Gateway";165;2
"Unit";"Zealot";"Gateway";165;2
"Unit";"Zealot";"Gateway";165;2
"Unit";"Zealot";"Gateway";165;2
"Unit";"Zealot";"Gateway";165;2
"Building";"Nexus";NA;140;0
"Unit";"Zealot";"Gateway";183;2
"Unit";"Zealot";"Gateway";183;2
"Unit";"Zealot";"Gateway";183;2
"Unit";"Zealot";"Gateway";183;2
"Unit";"Zealot";"Gateway";183;2
"Unit";"Zealot";"Gateway";183;2
"Unit";"Zealot";"Gateway";183;2
"Unit";"Zealot";"Gateway";183;2
"Unit";"Zealot";"Gateway";183;2
"Unit";"Disruptor";"Robotics Facility";183;3
"Unit";"Disruptor";"Robotics Facility";183;3
"Building";"Assimilator";NA;201;0
"Building";"Assimilator";NA;204;0
"Unit";"Disruptor";"Robotics Facility";201;3
"Unit";"Disruptor";"Robotics Facility";201;3
"Unit";"Zealot";"Gateway";213;2
"Unit";"Zealot";"Gateway";213;2
"Unit";"Zealot";"Gateway";213;2
"Unit";"Zealot";"Gateway";213;2
"Unit";"Zealot";"Gateway";213;2
"Unit";"Zealot";"Gateway";213;2
"Unit";"Zealot";"Gateway";213;2
"Unit";"Zealot";"Gateway";213;2
"Unit";"Zealot";"Gateway";213;2
"Building";"TemplarArchive";NA;207;0
"Unit";"Disruptor";"Robotics Facility";207;3
"Unit";"Stalker";"Gateway";234;2
"Unit";"Stalker";"Gateway";234;2
"Unit";"Stalker";"Gateway";234;2
"Unit";"Stalker";"Gateway";234;2
"Unit";"Stalker";"Gateway";234;2
"Unit";"Stalker";"Gateway";234;2
"Unit";"Stalker";"Gateway";234;2
"Unit";"Stalker";"Gateway";234;2
"Unit";"Stalker";"Gateway";234;2
"Unit";"Disruptor";"Robotics Facility";213;3
"Upgrade";"ProtossGroundWeaponsLevel1";"Forge";204;0
"Upgrade";"ProtossGroundArmorsLevel1";"Forge";207;0
"Unit";"Disruptor";"Robotics Facility";231;3
"Unit";"Zealot";"Gateway";255;2
"Unit";"Zealot";"Gateway";255;2
"Unit";"Zealot";"Gateway";255;2
"Unit";"Zealot";"Gateway";255;2
"Unit";"Zealot";"Gateway";255;2
"Unit";"Zealot";"Gateway";255;2
"Unit";"Zealot";"Gateway";255;2
"Unit";"Zealot";"Gateway";255;2
"Unit";"Zealot";"Gateway";255;2
"Unit";"Disruptor";"Robotics Facility";252;3
"Building";"HighTemplar";NA;279;0
"Building";"HighTemplar";NA;279;0
"Building";"HighTemplar";NA;279;0
"Building";"HighTemplar";NA;279;0
"Building";"HighTemplar";NA;279;0
"Building";"HighTemplar";NA;279;0
"Building";"HighTemplar";NA;279;0
"Unit";"Sentry";"Gateway";279;2
"Unit";"Sentry";"Gateway";279;2
"Unit";"Archon";"High Templar";279;0
"Unit";"Archon";"High Templar";279;0
"Unit";"Archon";"High Templar";279;0
"Unit";"Immortal";"Robotics Facility";276;4
"Unit";"Zealot";"Gateway";290;2
"Unit";"Zealot";"Gateway";290;2
"Unit";"Stalker";"Gateway";294;2
"Unit";"Stalker";"Gateway";294;2
"Unit";"Stalker";"Gateway";294;2
"Unit";"Stalker";"Gateway";294;2
"Unit";"Stalker";"Gateway";294;2
"Unit";"Stalker";"Gateway";294;2
"Unit";"Stalker";"Gateway";294;2
"Unit";"Stalker";"Gateway";294;2
"Unit";"Stalker";"Gateway";294;2
"Unit";"Zealot";"Gateway";312;2
"Unit";"Zealot";"Gateway";312;2
"Unit";"Zealot";"Gateway";312;2
"Unit";"Zealot";"Gateway";312;2
"Unit";"Zealot";"Gateway";312;2
"Unit";"Zealot";"Gateway";312;2
"Unit";"Zealot";"Gateway";312;2
"Unit";"Zealot";"Gateway";312;2
"Unit";"Zealot";"Gateway";312;2
"Unit";"Zealot";"Gateway";330;2
"Unit";"Zealot";"Gateway";330;2
"Unit";"Zealot";"Gateway";330;2
"Unit";"Zealot";"Gateway";330;2
"Unit";"Zealot";"Gateway";330;2
"Unit";"Zealot";"Gateway";330;2
"Unit";"Zealot";"Gateway";330;2
"Unit";"Zealot";"Gateway";330;2
"Unit";"Zealot";"Gateway";330;2
"Upgrade";"ProtossGroundWeaponsLevel2";"Forge";281;0
"Upgrade";"ProtossGroundArmorsLevel2";"Forge";281;0
"Building";"HighTemplar";NA;348;0
"Building";"HighTemplar";NA;348;0
"Building";"HighTemplar";NA;348;0
"Building";"HighTemplar";NA;348;0
"Building";"HighTemplar";NA;348;0
"Building";"HighTemplar";NA;348;0
"Building";"HighTemplar";NA;348;0
"Building";"HighTemplar";NA;348;0
"Building";"HighTemplar";NA;348;0
"Unit";"Disruptor";"Robotics Facility";348;3
"Unit";"Disruptor";"Robotics Facility";348;3
"Unit";"Zealot";"Gateway";360;2
"Unit";"Zealot";"Gateway";360;2
"Unit";"Zealot";"Gateway";360;2
"Unit";"Zealot";"Gateway";360;2
"Unit";"Stalker";"Gateway";370;2
"Unit";"Stalker";"Gateway";370;2
"Unit";"Stalker";"Gateway";370;2
"Unit";"Stalker";"Gateway";370;2
"Unit";"Disruptor";"Robotics Facility";353;3
"Unit";"Archon";"High Templar";374;0
"Unit";"Archon";"High Templar";380;0
"Unit";"Archon";"High Templar";380;0
"Unit";"Archon";"High Templar";380;0
"Unit";"Archon";"High Templar";380;0
"Unit";"Disruptor";"Robotics Facility";360;3
"Building";"Pylon";NA;384;0
"Unit";"Disruptor";"Robotics Facility";370;3
"Building";"Pylon";NA;387;0
"Building";"HighTemplar";NA;389;0
"Building";"HighTemplar";NA;389;0
"Building";"HighTemplar";NA;389;0
"Building";"HighTemplar";NA;389;0
"Unit";"Zealot";"Gateway";389;2
"Unit";"Zealot";"Gateway";389;2
"Unit";"Zealot";"Gateway";389;2
"Unit";"Zealot";"Gateway";392;2
"Unit";"Disruptor";"Robotics Facility";380;3
"Unit";"Sentry";"Gateway";400;2
"Unit";"Archon";"High Templar";394;0
"Unit";"Archon";"High Templar";398;0
"Unit";"Disruptor";"Robotics Facility";392;3
"Unit";"Zealot";"Gateway";405;2
"Unit";"Zealot";"Gateway";405;2
"Unit";"Zealot";"Gateway";408;2
"Unit";"Zealot";"Gateway";408;2
"Unit";"Zealot";"Gateway";408;2
"Unit";"Zealot";"Gateway";408;2
"Unit";"Zealot";"Gateway";408;2
"Unit";"Zealot";"Gateway";408;2
"Unit";"Zealot";"Gateway";408;2
"Unit";"Disruptor";"Robotics Facility";400;3
