"type";"unit_name";"on_building";"total_supply";"supply"
"Building";"Pylon";NA;15;0
"Building";"Pylon";NA;16;0
"Building";"Forge";NA;15;0
"Building";"PhotonCannon";NA;18;0
"Building";"PhotonCannon";NA;19;0
"Building";"PhotonCannon";NA;20;0
"Building";"PhotonCannon";NA;20;0
"Building";"PhotonCannon";NA;20;0
"Building";"PhotonCannon";NA;20;0
"Building";"PhotonCannon";NA;20;0
"Building";"PhotonCannon";NA;20;0
