"type";"unit_name";"on_building";"total_supply";"supply"
"Building";"Pylon";NA;13;0
"Building";"Assimilator";NA;16;0
"Building";"Gateway";NA;15;0
"Building";"Assimilator";NA;18;0
"Building";"Assimilator";NA;18;0
"Building";"Pylon";NA;21;0
"Building";"CyberneticsCore";NA;20;0
"Unit";"Adept";"Gateway";23;2
"Building";"RoboticsFacility";NA;23;0
"Building";"Pylon";NA;26;0
"Building";"Nexus";NA;22;0
"Unit";"Stalker";"Gateway";26;2
"Unit";"Observer";"Robotics Facility";27;1
"Unit";"Stalker";"Gateway";28;2
"Unit";"Observer";"Robotics Facility";39;1
"Building";"Pylon";NA;41;0
"Unit";"Stalker";"Gateway";41;2
"Building";"ShieldBattery";NA;41;0
"Unit";"Observer";"Robotics Facility";44;1
"Building";"Gateway";NA;41;0
"Building";"Gateway";NA;41;0
"Building";"Assimilator";NA;48;0
"Building";"Assimilator";NA;49;0
"Unit";"Observer";"Robotics Facility";51;1
"Building";"Pylon";NA;53;0
"Unit";"Observer";"Robotics Facility";55;1
"Unit";"Stalker";"Gateway";58;2
"Unit";"Stalker";"Gateway";58;2
"Unit";"Stalker";"Gateway";58;2
"Building";"RoboticsBay";NA;51;0
"Building";"RoboticsFacility";NA;51;0
"Building";"Pylon";NA;55;0
"Building";"Pylon";NA;64;0
"Unit";"Disruptor";"Robotics Facility";55;3
"Unit";"Stalker";"Gateway";64;2
"Unit";"Stalker";"Gateway";64;2
"Unit";"Stalker";"Gateway";67;2
"Building";"Pylon";NA;64;0
"Unit";"Disruptor";"Robotics Facility";64;3
"Building";"Pylon";NA;75;0
"Building";"Forge";NA;75;0
"Unit";"Stalker";"Gateway";80;2
"Unit";"Stalker";"Gateway";80;2
"Unit";"Stalker";"Gateway";80;2
"Unit";"Disruptor";"Robotics Facility";78;3
"Building";"Gateway";NA;75;0
"Building";"Gateway";NA;75;0
"Building";"Pylon";NA;86;0
"Building";"Pylon";NA;89;0
"Unit";"Disruptor";"Robotics Facility";89;3
"Unit";"Observer";"Robotics Facility";89;1
"Building";"Pylon";NA;89;0
"Building";"PhotonCannon";NA;89;0
"Building";"PhotonCannon";NA;89;0
"Building";"PhotonCannon";NA;89;0
"Building";"ShieldBattery";NA;89;0
"Unit";"Observer";"Robotics Facility";92;1
"Building";"Stargate";NA;89;0
"Building";"Pylon";NA;95;0
"Building";"PhotonCannon";NA;95;0
"Building";"PhotonCannon";NA;95;0
"Building";"ShieldBattery";NA;95;0
"Building";"Nexus";NA;89;0
"Unit";"Phoenix";"Stargate";98;2
"Unit";"Colossus";"Robotics Facility";95;6
"Unit";"Colossus";"Robotics Facility";95;6
"Building";"Assimilator";NA;102;0
"Building";"Assimilator";NA;104;0
"Unit";"Phoenix";"Stargate";104;2
"Building";"Stargate";NA;104;0
"Unit";"Phoenix";"Stargate";121;2
"Upgrade";"ProtossGroundWeaponsLevel1";"Forge";98;0
"Building";"PhotonCannon";NA;123;0
"Building";"Pylon";NA;123;0
"Unit";"Phoenix";"Stargate";123;2
"Building";"PhotonCannon";NA;123;0
"Building";"FleetBeacon";NA;118;0
"Building";"Pylon";NA;130;0
"Unit";"Phoenix";"Stargate";130;2
"Unit";"Phoenix";"Stargate";130;2
"Building";"Pylon";NA;130;0
"Unit";"Disruptor";"Robotics Facility";130;3
"Building";"PhotonCannon";NA;130;0
"Building";"TwilightCouncil";NA;130;0
"Building";"PhotonCannon";NA;130;0
"Building";"ShieldBattery";NA;130;0
"Unit";"Disruptor";"Robotics Facility";130;3
"Unit";"Observer";"Robotics Facility";137;1
"Unit";"Observer";"Robotics Facility";140;1
"Upgrade";"ProtossAirWeaponsLevel1";"CyberneticsCore";130;0
"Unit";"Phoenix";"Stargate";140;2
"Unit";"Phoenix";"Stargate";140;2
"Building";"Nexus";NA;130;0
"Building";"PhotonCannon";NA;141;0
"Building";"PhotonCannon";NA;141;0
"Building";"PhotonCannon";NA;142;0
"Building";"PhotonCannon";NA;142;0
"Building";"ShieldBattery";NA;142;0
"Building";"ShieldBattery";NA;142;0
"Building";"PhotonCannon";NA;142;0
"Building";"ShieldBattery";NA;146;0
"Unit";"Stalker";"Gateway";146;2
"Unit";"Stalker";"Gateway";146;2
"Unit";"Stalker";"Gateway";146;2
"Unit";"Stalker";"Gateway";146;2
"Unit";"Phoenix";"Stargate";154;2
"Unit";"Phoenix";"Stargate";154;2
"Unit";"Stalker";"Gateway";154;2
"Unit";"Stalker";"Gateway";154;2
"Unit";"Stalker";"Gateway";154;2
"Unit";"Stalker";"Gateway";154;2
"Unit";"Stalker";"Gateway";154;2
"Upgrade";"ProtossGroundWeaponsLevel2";"Forge";142;0
"Unit";"Phoenix";"Stargate";154;2
"Unit";"Phoenix";"Stargate";154;2
"Unit";"Disruptor";"Robotics Facility";154;3
"Unit";"Disruptor";"Robotics Facility";154;3
"Unit";"Disruptor";"Robotics Facility";178;3
"Unit";"Disruptor";"Robotics Facility";178;3
"Unit";"Tempest";"Stargate";178;4
"Unit";"Tempest";"Stargate";178;4
"Building";"Pylon";NA;178;0
"Building";"Pylon";NA;178;0
"Building";"Assimilator";NA;178;0
"Building";"Assimilator";NA;181;0
"Building";"Stargate";NA;178;0
"Building";"Stargate";NA;178;0
"Unit";"Disruptor";"Robotics Facility";192;3
"Unit";"Disruptor";"Robotics Facility";192;3
"Unit";"Phoenix";"Stargate";195;2
"Unit";"Phoenix";"Stargate";195;2
"Building";"PhotonCannon";NA;195;0
"Building";"PhotonCannon";NA;195;0
"Building";"PhotonCannon";NA;195;0
"Building";"PhotonCannon";NA;195;0
"Building";"ShieldBattery";NA;195;0
"Building";"Nexus";NA;178;0
"Building";"ShieldBattery";NA;195;0
"Building";"ShieldBattery";NA;195;0
"Building";"PhotonCannon";NA;195;0
"Building";"Pylon";NA;205;0
"Unit";"Phoenix";"Stargate";205;2
"Unit";"Phoenix";"Stargate";205;2
"Unit";"Phoenix";"Stargate";205;2
"Unit";"Phoenix";"Stargate";205;2
"Unit";"Observer";"Robotics Facility";205;1
"Unit";"Observer";"Robotics Facility";205;1
"Upgrade";"ProtossAirWeaponsLevel2";"CyberneticsCore";195;0
"Unit";"Disruptor";"Robotics Facility";215;3
"Building";"Pylon";NA;217;0
"Unit";"Colossus";"Robotics Facility";215;6
"Building";"PhotonCannon";NA;220;0
"Building";"PhotonCannon";NA;220;0
"Unit";"Phoenix";"Stargate";220;2
"Unit";"Phoenix";"Stargate";220;2
"Unit";"Phoenix";"Stargate";220;2
"Unit";"Phoenix";"Stargate";220;2
"Building";"PhotonCannon";NA;220;0
"Building";"PhotonCannon";NA;220;0
"Building";"PhotonCannon";NA;220;0
"Unit";"Stalker";"Gateway";234;2
"Unit";"Stalker";"Gateway";234;2
"Unit";"Stalker";"Gateway";234;2
"Unit";"Stalker";"Gateway";234;2
"Unit";"Stalker";"Gateway";234;2
"Building";"Gateway";NA;226;0
"Upgrade";"ExtendedThermalLance";"RoboticsBay";217;0
"Building";"Gateway";NA;226;0
"Building";"Gateway";NA;226;0
"Building";"Gateway";NA;226;0
"Unit";"Stalker";"Gateway";244;2
"Unit";"Stalker";"Gateway";244;2
"Unit";"Stalker";"Gateway";244;2
"Unit";"Stalker";"Gateway";244;2
"Unit";"Stalker";"Gateway";244;2
"Upgrade";"ProtossGroundWeaponsLevel3";"Forge";217;0
"Building";"Pylon";NA;254;0
"Building";"Pylon";NA;254;0
"Unit";"Phoenix";"Stargate";254;2
"Unit";"Phoenix";"Stargate";254;2
"Unit";"Phoenix";"Stargate";254;2
"Unit";"Phoenix";"Stargate";254;2
"Unit";"Stalker";"Gateway";262;2
"Unit";"Stalker";"Gateway";262;2
"Unit";"Stalker";"Gateway";262;2
"Unit";"Stalker";"Gateway";262;2
"Unit";"Stalker";"Gateway";262;2
"Building";"Nexus";NA;254;0
"Building";"Assimilator";NA;272;0
"Building";"Assimilator";NA;272;0
"Building";"PhotonCannon";NA;272;0
"Building";"PhotonCannon";NA;272;0
"Building";"PhotonCannon";NA;272;0
"Building";"PhotonCannon";NA;272;0
"Building";"ShieldBattery";NA;272;0
"Building";"ShieldBattery";NA;272;0
"Unit";"Phoenix";"Stargate";272;2
"Unit";"Phoenix";"Stargate";272;2
"Unit";"Phoenix";"Stargate";272;2
"Unit";"Phoenix";"Stargate";272;2
"Unit";"Stalker";"Gateway";280;2
"Unit";"Stalker";"Gateway";280;2
"Unit";"Stalker";"Gateway";280;2
"Unit";"Stalker";"Gateway";280;2
"Unit";"Stalker";"Gateway";280;2
"Unit";"Stalker";"Gateway";280;2
"Unit";"Stalker";"Gateway";280;2
"Unit";"Stalker";"Gateway";280;2
"Unit";"Stalker";"Gateway";280;2
"Unit";"Zealot";"Gateway";298;2
"Unit";"Zealot";"Gateway";298;2
"Unit";"Zealot";"Gateway";298;2
"Unit";"Zealot";"Gateway";298;2
"Upgrade";"ProtossShieldsLevel1";"Forge";272;0
"Unit";"Observer";"Robotics Facility";306;1
"Upgrade";"ProtossAirWeaponsLevel3";"CyberneticsCore";272;0
"Upgrade";"Charge";"TwilightCouncil";298;0
"Building";"Pylon";NA;307;0
"Building";"Pylon";NA;307;0
"Building";"Assimilator";NA;307;0
"Building";"Assimilator";NA;307;0
"Building";"RoboticsFacility";NA;306;0
"Building";"RoboticsFacility";NA;306;0
"Unit";"Zealot";"Gateway";307;2
"Building";"Nexus";NA;307;0
