"type";"unit_name";"on_building";"total_supply";"supply"
"Building";"Pylon";NA;13;0
"Building";"Assimilator";NA;15;0
"Building";"Pylon";NA;17;0
"Building";"Gateway";NA;15;0
"Building";"CyberneticsCore";NA;19;0
"Unit";"Stalker";"Gateway";21;2
"Unit";"Stalker";"Gateway";26;2
"Building";"Nexus";NA;22;0
"Building";"Pylon";NA;30;0
"Building";"Assimilator";NA;27;0
"Unit";"Stalker";"Gateway";28;2
"Building";"Pylon";NA;31;0
"Building";"TwilightCouncil";NA;31;0
"Building";"ShieldBattery";NA;37;0
"Building";"Gateway";NA;39;0
"Unit";"Stalker";"Gateway";42;2
"Building";"Gateway";NA;40;0
"Unit";"Stalker";"Gateway";50;2
"Unit";"Stalker";"Gateway";53;2
"Unit";"Stalker";"Gateway";58;2
"Unit";"Stalker";"Gateway";60;2
"Building";"Assimilator";NA;56;0
"Building";"Assimilator";NA;56;0
"Building";"RoboticsFacility";NA;52;0
"Building";"Pylon";NA;60;0
"Unit";"Stalker";"Gateway";66;2
"Unit";"Stalker";"Gateway";66;2
"Building";"Pylon";NA;66;0
"Unit";"Observer";"Robotics Facility";68;1
"Building";"Nexus";NA;53;0
"Building";"Pylon";NA;71;0
"Building";"Pylon";NA;74;0
"Unit";"Stalker";"Gateway";74;2
"Unit";"Stalker";"Gateway";75;2
"Unit";"Stalker";"Gateway";76;2
"Building";"Forge";NA;71;0
"Building";"Forge";NA;71;0
"Building";"ShieldBattery";NA;74;0
"Unit";"Observer";"Robotics Facility";74;1
"Unit";"Stalker";"Gateway";89;2
"Unit";"Stalker";"Gateway";89;2
"Unit";"Stalker";"Gateway";89;2
"Building";"Assimilator";NA;96;0
"Building";"Assimilator";NA;97;0
"Unit";"Stalker";"Gateway";102;2
"Unit";"Stalker";"Gateway";102;2
"Unit";"Stalker";"Gateway";102;2
"Unit";"Immortal";"Robotics Facility";100;4
"Upgrade";"Charge";"TwilightCouncil";97;0
"Building";"Pylon";NA;117;0
"Building";"Pylon";NA;117;0
"Building";"Pylon";NA;117;0
"Building";"Gateway";NA;102;0
"Building";"Gateway";NA;102;0
"Building";"Gateway";NA;103;0
"Building";"TemplarArchive";NA;117;0
"Unit";"Stalker";"Gateway";118;2
"Unit";"Stalker";"Gateway";118;2
"Unit";"Stalker";"Gateway";118;2
"Unit";"Stalker";"Gateway";118;2
"Unit";"Stalker";"Gateway";118;2
"Building";"Pylon";NA;118;0
"Building";"Pylon";NA;118;0
"Unit";"Immortal";"Robotics Facility";118;4
"Upgrade";"ProtossGroundWeaponsLevel1";"Forge";102;0
"Upgrade";"ProtossGroundArmorsLevel1";"Forge";102;0
"Building";"HighTemplar";NA;136;0
"Building";"HighTemplar";NA;136;0
"Building";"HighTemplar";NA;137;0
"Building";"HighTemplar";NA;138;0
"Building";"HighTemplar";NA;139;0
"Building";"HighTemplar";NA;139;0
"Building";"Pylon";NA;139;0
"Building";"Pylon";NA;139;0
"Unit";"Observer";"Robotics Facility";142;1
"Unit";"Zealot";"Gateway";142;2
"Unit";"Zealot";"Gateway";142;2
"Unit";"Zealot";"Gateway";142;2
"Unit";"Zealot";"Gateway";142;2
"Unit";"Zealot";"Gateway";142;2
"Unit";"Zealot";"Gateway";142;2
"Building";"Assimilator";NA;142;0
"Building";"Assimilator";NA;142;0
"Building";"Pylon";NA;142;0
"Building";"Pylon";NA;142;0
"Building";"Pylon";NA;142;0
"Unit";"Observer";"Robotics Facility";142;1
"Unit";"Stalker";"Gateway";158;2
"Unit";"Stalker";"Gateway";158;2
"Unit";"Stalker";"Gateway";158;2
"Unit";"Stalker";"Gateway";158;2
"Unit";"Zealot";"Gateway";158;2
"Unit";"Zealot";"Gateway";158;2
"Building";"Nexus";NA;139;0
"Building";"HighTemplar";NA;175;0
"Building";"HighTemplar";NA;175;0
"Building";"HighTemplar";NA;175;0
"Building";"HighTemplar";NA;175;0
"Building";"HighTemplar";NA;175;0
"Unit";"Stalker";"Gateway";175;2
"Building";"PhotonCannon";NA;172;0
"Building";"PhotonCannon";NA;172;0
"Building";"PhotonCannon";NA;174;0
"Unit";"Observer";"Robotics Facility";179;1
"Unit";"Stalker";"Gateway";182;2
"Unit";"Stalker";"Gateway";182;2
"Unit";"Stalker";"Gateway";182;2
"Upgrade";"ProtossGroundWeaponsLevel2";"Forge";155;0
"Building";"Nexus";NA;170;0
"Unit";"Stalker";"Gateway";198;2
"Unit";"Stalker";"Gateway";198;2
"Unit";"Stalker";"Gateway";198;2
"Unit";"Stalker";"Gateway";198;2
"Building";"HighTemplar";NA;214;0
"Building";"HighTemplar";NA;214;0
"Unit";"Zealot";"Gateway";214;2
"Unit";"Zealot";"Gateway";214;2
"Building";"ShieldBattery";NA;202;0
"Building";"PhotonCannon";NA;208;0
"Building";"PhotonCannon";NA;210;0
"Unit";"Observer";"Robotics Facility";214;1
"Building";"Gateway";NA;202;0
"Building";"Gateway";NA;202;0
"Building";"Gateway";NA;202;0
"Unit";"Zealot";"Gateway";227;2
"Unit";"Zealot";"Gateway";227;2
"Unit";"Zealot";"Gateway";227;2
"Unit";"Zealot";"Gateway";227;2
"Unit";"Stalker";"Gateway";240;2
"Unit";"Stalker";"Gateway";240;2
"Unit";"Stalker";"Gateway";240;2
"Unit";"Stalker";"Gateway";240;2
"Building";"Stargate";NA;237;0
"Building";"Nexus";NA;226;0
"Unit";"Stalker";"Gateway";248;2
"Unit";"Stalker";"Gateway";248;2
"Unit";"Stalker";"Gateway";248;2
"Building";"HighTemplar";NA;260;0
"Building";"HighTemplar";NA;260;0
"Building";"HighTemplar";NA;260;0
"Building";"HighTemplar";NA;260;0
"Building";"PhotonCannon";NA;248;0
"Building";"PhotonCannon";NA;248;0
"Building";"ShieldBattery";NA;248;0
"Building";"PhotonCannon";NA;248;0
"Building";"PhotonCannon";NA;250;0
"Unit";"Zealot";"Gateway";262;2
"Unit";"Zealot";"Gateway";262;2
"Unit";"Zealot";"Gateway";262;2
"Unit";"Phoenix";"Stargate";251;2
"Unit";"Phoenix";"Stargate";268;2
"Unit";"Stalker";"Gateway";274;2
"Unit";"Stalker";"Gateway";274;2
"Unit";"Stalker";"Gateway";274;2
"Unit";"Stalker";"Gateway";274;2
"Unit";"Stalker";"Gateway";274;2
"Unit";"Stalker";"Gateway";284;2
"Unit";"Stalker";"Gateway";284;2
