"type";"unit_name";"on_building";"total_supply";"supply"
"Building";"Pylon";NA;13;0
"Building";"Assimilator";NA;15;0
"Building";"Gateway";NA;14;0
"Building";"Pylon";NA;20;0
"Building";"CyberneticsCore";NA;20;0
"Building";"Assimilator";NA;20;0
"Building";"Nexus";NA;20;0
"Unit";"Stalker";"Gateway";22;2
"Unit";"Stalker";"Gateway";24;2
"Building";"RoboticsFacility";NA;24;0
"Building";"ShieldBattery";NA;28;0
"Unit";"Stalker";"Gateway";29;2
"Unit";"Immortal";"Robotics Facility";33;4
"Building";"Pylon";NA;38;0
"Unit";"Stalker";"Gateway";35;2
"Building";"ShieldBattery";NA;36;0
"Unit";"Observer";"Robotics Facility";46;1
"Building";"Pylon";NA;46;0
"Building";"Assimilator";NA;48;0
"Unit";"Observer";"Robotics Facility";48;1
"Building";"Assimilator";NA;48;0
"Building";"Pylon";NA;50;0
"Building";"RoboticsBay";NA;47;0
"Building";"Gateway";NA;47;0
"Building";"Gateway";NA;47;0
"Unit";"Stalker";"Gateway";57;2
"Unit";"Stalker";"Gateway";57;2
"Building";"Pylon";NA;55;0
"Unit";"Disruptor";"Robotics Facility";53;3
"Unit";"Stalker";"Gateway";66;2
"Building";"TwilightCouncil";NA;57;0
"Building";"Gateway";NA;55;0
"Unit";"Zealot";"Gateway";69;2
"Unit";"Zealot";"Gateway";69;2
"Building";"Pylon";NA;66;0
"Building";"Gateway";NA;55;0
"Unit";"Disruptor";"Robotics Facility";58;3
"Unit";"Stalker";"Gateway";76;2
"Unit";"Stalker";"Gateway";76;2
"Unit";"Stalker";"Gateway";76;2
"Unit";"Disruptor";"Robotics Facility";73;3
"Building";"Pylon";NA;82;0
"Unit";"Stalker";"Gateway";87;2
"Unit";"Stalker";"Gateway";87;2
"Unit";"Stalker";"Gateway";87;2
"Building";"Pylon";NA;87;0
"Building";"ShieldBattery";NA;87;0
"Building";"ShieldBattery";NA;88;0
"Unit";"Stalker";"Gateway";97;2
"Building";"Pylon";NA;97;0
"Unit";"Stalker";"Gateway";102;2
"Unit";"Stalker";"Gateway";102;2
"Unit";"Disruptor";"Robotics Facility";97;3
"Building";"Pylon";NA;100;0
"Building";"ShieldBattery";NA;100;0
"Unit";"Stalker";"Gateway";111;2
"Unit";"Stalker";"Gateway";111;2
"Building";"Pylon";NA;109;0
"Building";"ShieldBattery";NA;102;0
"Unit";"Stalker";"Gateway";115;2
"Unit";"Stalker";"Gateway";117;2
"Unit";"Stalker";"Gateway";117;2
"Unit";"Disruptor";"Robotics Facility";106;3
"Building";"Nexus";NA;97;0
"Building";"Pylon";NA;125;0
"Unit";"Disruptor";"Robotics Facility";117;3
"Unit";"Stalker";"Gateway";134;2
"Unit";"Stalker";"Gateway";134;2
"Unit";"Stalker";"Gateway";134;2
"Unit";"Stalker";"Gateway";134;2
"Building";"Forge";NA;127;0
"Building";"RoboticsFacility";NA;126;0
"Building";"Pylon";NA;142;0
"Unit";"Disruptor";"Robotics Facility";142;3
"Building";"Assimilator";NA;144;0
"Building";"Forge";NA;144;0
"Unit";"Stalker";"Gateway";151;2
"Unit";"Stalker";"Gateway";151;2
"Building";"Assimilator";NA;146;0
"Building";"Pylon";NA;146;0
"Unit";"Disruptor";"Robotics Facility";144;3
"Unit";"Stalker";"Gateway";159;2
"Building";"Gateway";NA;146;0
"Unit";"Stalker";"Gateway";161;2
"Unit";"Stalker";"Gateway";161;2
"Unit";"Stalker";"Gateway";161;2
"Unit";"Stalker";"Gateway";161;2
"Unit";"Stalker";"Gateway";169;2
"Unit";"Stalker";"Gateway";169;2
"Unit";"Disruptor";"Robotics Facility";161;3
"Upgrade";"Charge";"TwilightCouncil";151;0
"Unit";"Stalker";"Gateway";182;2
"Unit";"Stalker";"Gateway";182;2
"Unit";"Stalker";"Gateway";182;2
"Building";"Forge";NA;176;0
"Building";"PhotonCannon";NA;180;0
"Building";"PhotonCannon";NA;182;0
"Building";"PhotonCannon";NA;182;0
"Building";"ShieldBattery";NA;182;0
"Building";"ShieldBattery";NA;191;0
"Building";"Pylon";NA;193;0
"Building";"Pylon";NA;193;0
"Building";"Pylon";NA;193;0
"Building";"RoboticsFacility";NA;191;0
"Unit";"Stalker";"Gateway";193;2
"Unit";"Stalker";"Gateway";193;2
"Unit";"Disruptor";"Robotics Facility";191;3
"Upgrade";"ProtossGroundWeaponsLevel1";"Forge";176;0
"Unit";"Zealot";"Gateway";201;2
"Unit";"Zealot";"Gateway";201;2
"Unit";"Zealot";"Gateway";201;2
"Unit";"Zealot";"Gateway";201;2
"Building";"DarkShrine";NA;191;0
"Unit";"Disruptor";"Robotics Facility";193;3
"Building";"TemplarArchive";NA;200;0
"Building";"DarkTemplar";NA;213;0
"Upgrade";"ProtossGroundArmorsLevel1";"Forge";193;0
"Building";"HighTemplar";NA;213;0
"Building";"HighTemplar";NA;213;0
"Building";"HighTemplar";NA;213;0
"Building";"Pylon";NA;212;0
"Building";"Pylon";NA;212;0
"Building";"HighTemplar";NA;213;0
"Unit";"Archon";"High Templar";213;0
"Building";"Pylon";NA;213;0
"Building";"DarkTemplar";NA;213;0
"Unit";"Archon";"High Templar";213;0
"Building";"Pylon";NA;213;0
"Building";"Pylon";NA;213;0
"Building";"Gateway";NA;209;0
"Building";"Gateway";NA;212;0
"Building";"Pylon";NA;213;0
"Building";"DarkTemplar";NA;214;0
"Building";"DarkTemplar";NA;214;0
"Unit";"Zealot";"Gateway";214;2
"Unit";"Zealot";"Gateway";214;2
"Unit";"Colossus";"Robotics Facility";213;6
"Unit";"Stalker";"Gateway";224;2
"Unit";"Stalker";"Gateway";224;2
"Unit";"Stalker";"Gateway";228;2
"Unit";"Stalker";"Gateway";228;2
"Building";"Nexus";NA;213;0
"Unit";"Stalker";"Gateway";233;2
"Unit";"Stalker";"Gateway";233;2
"Unit";"Stalker";"Gateway";233;2
"Unit";"Stalker";"Gateway";233;2
"Upgrade";"ProtossGroundWeaponsLevel2";"Forge";213;0
"Building";"HighTemplar";NA;243;0
"Building";"HighTemplar";NA;243;0
"Unit";"Stalker";"Gateway";243;2
"Unit";"Stalker";"Gateway";243;2
"Unit";"Stalker";"Gateway";243;2
"Unit";"Archon";"High Templar";243;0
"Upgrade";"ProtossGroundArmorsLevel2";"Forge";224;0
"Building";"Pylon";NA;243;0
"Unit";"Stalker";"Gateway";250;2
"Unit";"Stalker";"Gateway";250;2
"Unit";"Stalker";"Gateway";250;2
"Unit";"Colossus";"Robotics Facility";242;6
"Building";"ShieldBattery";NA;250;0
"Unit";"Zealot";"Gateway";262;2
"Unit";"Zealot";"Gateway";262;2
"Unit";"Zealot";"Gateway";262;2
"Unit";"Zealot";"Gateway";262;2
"Unit";"Zealot";"Gateway";262;2
"Unit";"Stalker";"Gateway";276;2
"Unit";"Stalker";"Gateway";276;2
"Unit";"Stalker";"Gateway";276;2
"Unit";"Stalker";"Gateway";276;2
"Unit";"Stalker";"Gateway";276;2
"Upgrade";"ExtendedThermalLance";"RoboticsBay";244;0
"Unit";"Disruptor";"Robotics Facility";276;3
"Unit";"Stalker";"Gateway";290;2
"Unit";"Stalker";"Gateway";290;2
"Unit";"Stalker";"Gateway";290;2
"Unit";"Stalker";"Gateway";290;2
"Unit";"Stalker";"Gateway";290;2
"Unit";"Stalker";"Gateway";290;2
"Unit";"Disruptor";"Robotics Facility";287;3
"Building";"Assimilator";NA;302;0
"Building";"Assimilator";NA;302;0
"Unit";"Stalker";"Gateway";305;2
"Unit";"Stalker";"Gateway";305;2
"Unit";"Stalker";"Gateway";305;2
"Unit";"Stalker";"Gateway";305;2
"Unit";"Stalker";"Gateway";305;2
"Unit";"Stalker";"Gateway";305;2
"Unit";"Stalker";"Gateway";305;2
"Unit";"Zealot";"Gateway";319;2
"Unit";"Disruptor";"Robotics Facility";305;3
"Unit";"Disruptor";"Robotics Facility";305;3
"Unit";"Zealot";"Gateway";322;2
"Unit";"Zealot";"Gateway";322;2
"Unit";"Zealot";"Gateway";322;2
"Unit";"Zealot";"Gateway";322;2
"Unit";"Zealot";"Gateway";322;2
"Unit";"Zealot";"Gateway";322;2
