"type";"unit_name";"on_building";"total_supply";"supply"
"Building";"Pylon";NA;13;0
"Building";"Assimilator";NA;16;0
"Building";"Gateway";NA;15;0
"Building";"Assimilator";NA;20;0
"Building";"CyberneticsCore";NA;20;0
"Building";"Pylon";NA;21;0
"Unit";"Stalker";"Gateway";22;2
"Building";"Nexus";NA;19;0
"Unit";"Stalker";"Gateway";26;2
"Building";"RoboticsFacility";NA;26;0
"Unit";"Observer";"Robotics Facility";35;1
"Building";"ShieldBattery";NA;37;0
"Building";"Gateway";NA;33;0
"Unit";"Observer";"Robotics Facility";40;1
"Building";"Pylon";NA;40;0
"Building";"Gateway";NA;35;0
"Building";"Pylon";NA;42;0
"Unit";"Stalker";"Gateway";47;2
"Unit";"Stalker";"Gateway";47;2
"Unit";"Stalker";"Gateway";47;2
"Building";"TwilightCouncil";NA;42;0
"Building";"Pylon";NA;49;0
"Building";"Assimilator";NA;55;0
"Unit";"Stalker";"Gateway";57;2
"Unit";"Stalker";"Gateway";57;2
"Building";"Pylon";NA;57;0
"Unit";"Stalker";"Gateway";63;2
"Building";"Assimilator";NA;56;0
"Unit";"Stalker";"Gateway";67;2
"Unit";"Stalker";"Gateway";67;2
"Unit";"Stalker";"Gateway";67;2
"Building";"Nexus";NA;55;0
"Unit";"Observer";"Robotics Facility";75;1
"Building";"Pylon";NA;77;0
"Building";"Pylon";NA;77;0
"Building";"Pylon";NA;77;0
"Building";"Pylon";NA;77;0
"Building";"Pylon";NA;78;0
"Unit";"Zealot";"Gateway";81;2
"Unit";"Zealot";"Gateway";81;2
"Unit";"Zealot";"Gateway";81;2
"Building";"Gateway";NA;77;0
"Building";"Gateway";NA;77;0
"Building";"Gateway";NA;78;0
"Building";"TemplarArchive";NA;78;0
"Unit";"Zealot";"Gateway";91;2
"Unit";"Zealot";"Gateway";91;2
"Unit";"Zealot";"Gateway";91;2
"Building";"Forge";NA;81;0
"Building";"Pylon";NA;90;0
"Unit";"Immortal";"Robotics Facility";81;4
"Unit";"Zealot";"Gateway";97;2
"Unit";"Zealot";"Gateway";97;2
"Unit";"Zealot";"Gateway";97;2
"Unit";"Zealot";"Gateway";107;2
"Unit";"Zealot";"Gateway";107;2
"Unit";"Zealot";"Gateway";107;2
"Unit";"Immortal";"Robotics Facility";97;4
"Unit";"Zealot";"Gateway";111;2
"Unit";"Zealot";"Gateway";111;2
"Unit";"Zealot";"Gateway";111;2
"Upgrade";"Charge";"TwilightCouncil";90;0
"Unit";"Zealot";"Gateway";123;2
"Unit";"Zealot";"Gateway";123;2
"Unit";"Zealot";"Gateway";123;2
"Unit";"Zealot";"Gateway";129;2
"Unit";"Zealot";"Gateway";129;2
"Unit";"Zealot";"Gateway";129;2
"Unit";"Zealot";"Gateway";135;2
"Unit";"Zealot";"Gateway";135;2
"Unit";"Zealot";"Gateway";135;2
"Unit";"Zealot";"Gateway";141;2
"Unit";"Zealot";"Gateway";141;2
"Unit";"Zealot";"Gateway";141;2
"Unit";"Immortal";"Robotics Facility";129;4
"Building";"HighTemplar";NA;147;0
"Building";"HighTemplar";NA;147;0
"Building";"Pylon";NA;147;0
"Unit";"Archon";"High Templar";151;0
"Building";"Pylon";NA;147;0
"Unit";"Zealot";"Gateway";151;2
"Unit";"Zealot";"Gateway";151;2
"Unit";"Zealot";"Gateway";151;2
"Unit";"Zealot";"Gateway";151;2
"Building";"Pylon";NA;147;0
"Building";"Pylon";NA;147;0
"Upgrade";"ProtossGroundArmorsLevel1";"Forge";111;0
"Building";"Pylon";NA;151;0
"Building";"Pylon";NA;151;0
"Building";"Pylon";NA;151;0
"Building";"Pylon";NA;151;0
"Unit";"Zealot";"Gateway";159;2
"Unit";"Zealot";"Gateway";159;2
"Unit";"Zealot";"Gateway";159;2
"Unit";"Zealot";"Gateway";159;2
"Unit";"Immortal";"Robotics Facility";159;4
"Building";"Pylon";NA;167;0
"Building";"Nexus";NA;147;0
"Unit";"Zealot";"Gateway";171;2
"Unit";"Zealot";"Gateway";171;2
"Unit";"Zealot";"Gateway";171;2
"Unit";"Zealot";"Gateway";171;2
"Building";"Pylon";NA;171;0
"Building";"Gateway";NA;159;0
"Building";"Pylon";NA;171;0
"Building";"Pylon";NA;171;0
"Building";"Gateway";NA;159;0
"Building";"Gateway";NA;167;0
"Unit";"Zealot";"Gateway";179;2
"Unit";"Zealot";"Gateway";179;2
"Unit";"Zealot";"Gateway";179;2
"Unit";"Zealot";"Gateway";179;2
"Unit";"Stalker";"Gateway";187;2
"Unit";"Stalker";"Gateway";187;2
"Unit";"Zealot";"Gateway";191;2
"Unit";"Zealot";"Gateway";191;2
"Unit";"Zealot";"Gateway";191;2
"Unit";"Zealot";"Gateway";191;2
"Unit";"Zealot";"Gateway";191;2
"Unit";"Zealot";"Gateway";191;2
"Unit";"Immortal";"Robotics Facility";179;4
"Unit";"Zealot";"Gateway";207;2
"Unit";"Zealot";"Gateway";207;2
"Unit";"Zealot";"Gateway";207;2
"Unit";"Zealot";"Gateway";207;2
"Unit";"Zealot";"Gateway";207;2
"Unit";"Zealot";"Gateway";207;2
"Building";"HighTemplar";NA;207;0
"Building";"HighTemplar";NA;219;0
"Building";"HighTemplar";NA;219;0
"Building";"HighTemplar";NA;219;0
"Building";"HighTemplar";NA;219;0
"Building";"HighTemplar";NA;219;0
"Building";"HighTemplar";NA;219;0
"Upgrade";"ProtossGroundArmorsLevel2";"Forge";179;0
"Building";"Assimilator";NA;219;0
"Unit";"Archon";"High Templar";219;0
"Unit";"Archon";"High Templar";219;0
"Unit";"Archon";"High Templar";219;0
"Building";"Nexus";NA;191;0
"Building";"HighTemplar";NA;219;0
"Unit";"Archon";"High Templar";219;0
"Unit";"Zealot";"Gateway";219;2
"Unit";"Zealot";"Gateway";219;2
"Unit";"Zealot";"Gateway";219;2
"Unit";"Zealot";"Gateway";219;2
"Unit";"Zealot";"Gateway";219;2
"Unit";"Zealot";"Gateway";219;2
"Building";"Assimilator";NA;219;0
"Building";"HighTemplar";NA;231;0
"Building";"HighTemplar";NA;231;0
"Building";"HighTemplar";NA;231;0
"Building";"HighTemplar";NA;231;0
"Building";"HighTemplar";NA;231;0
"Building";"HighTemplar";NA;231;0
"Building";"HighTemplar";NA;231;0
"Building";"Pylon";NA;231;0
"Unit";"Archon";"High Templar";231;0
"Unit";"Archon";"High Templar";231;0
"Unit";"Archon";"High Templar";231;0
"Building";"Assimilator";NA;231;0
"Building";"Pylon";NA;231;0
"Unit";"Immortal";"Robotics Facility";231;4
"Unit";"Stalker";"Gateway";231;2
"Unit";"Stalker";"Gateway";231;2
"Unit";"Stalker";"Gateway";231;2
"Unit";"Zealot";"Gateway";235;2
"Unit";"Zealot";"Gateway";235;2
"Unit";"Zealot";"Gateway";235;2
"Unit";"Zealot";"Gateway";235;2
"Upgrade";"ProtossGroundWeaponsLevel1";"Forge";219;0
"Unit";"Zealot";"Gateway";249;2
"Unit";"Zealot";"Gateway";249;2
"Unit";"Zealot";"Gateway";249;2
"Unit";"Zealot";"Gateway";249;2
"Unit";"Zealot";"Gateway";249;2
"Unit";"Zealot";"Gateway";249;2
"Unit";"Zealot";"Gateway";249;2
"Unit";"Immortal";"Robotics Facility";231;4
"Unit";"Stalker";"Gateway";267;2
"Unit";"Stalker";"Gateway";267;2
"Unit";"Stalker";"Gateway";267;2
"Unit";"Zealot";"Gateway";267;2
"Unit";"Zealot";"Gateway";267;2
"Unit";"Zealot";"Gateway";267;2
"Unit";"Zealot";"Gateway";267;2
"Unit";"Zealot";"Gateway";281;2
"Unit";"Zealot";"Gateway";281;2
"Unit";"Zealot";"Gateway";281;2
"Unit";"Zealot";"Gateway";281;2
"Unit";"Zealot";"Gateway";281;2
"Unit";"Zealot";"Gateway";281;2
"Unit";"Zealot";"Gateway";281;2
"Unit";"Zealot";"Gateway";295;2
"Unit";"Zealot";"Gateway";295;2
"Unit";"Zealot";"Gateway";295;2
"Building";"HighTemplar";NA;295;0
"Building";"HighTemplar";NA;295;0
"Building";"HighTemplar";NA;295;0
"Building";"HighTemplar";NA;295;0
"Building";"HighTemplar";NA;301;0
"Building";"HighTemplar";NA;301;0
"Building";"HighTemplar";NA;301;0
"Unit";"Immortal";"Robotics Facility";295;4
"Unit";"Archon";"High Templar";305;0
