"type";"unit_name";"on_building";"total_supply_lag";"supply"
"Unit";"Overlord";"Larva";13;0
"Building";"Extractor";NA;17;0
"Building";"SpawningPool";NA;17;0
"Building";"Hatchery";NA;19;0
"Unit";"Queen";"Hatchery";21;2
"Unit";"Overlord";"Larva";23;0
"Unit";"Zergling";"Larva";23;1
"Unit";"Zergling";"Larva";24;1
"Building";"Hatchery";NA;25;0
"Unit";"Zergling";"Larva";30;1
"Unit";"Zergling";"Larva";31;1
"Unit";"Zergling";"Larva";32;1
"Unit";"Zergling";"Larva";33;1
"Unit";"Zergling";"Larva";34;1
"Unit";"Zergling";"Larva";35;1
"Unit";"Zergling";"Larva";36;1
"Unit";"Zergling";"Larva";37;1
"Unit";"Overlord";"Larva";38;0
"Building";"EvolutionChamber";NA;40;0
"Unit";"Queen";"Hatchery";42;2
"Unit";"Queen";"Hatchery";47;2
"Unit";"Overlord";"Larva";54;0
"Unit";"Overlord";"Larva";55;0
"Unit";"Overlord";"Larva";65;0
"Building";"SporeCrawler";NA;65;0
"Building";"SporeCrawler";NA;65;0
"Building";"SporeCrawler";NA;69;0
"Unit";"Queen";"Hatchery";69;2
"Unit";"Zergling";"Larva";73;1
"Unit";"Zergling";"Larva";74;1
"Unit";"Zergling";"Larva";75;1
"Unit";"Zergling";"Larva";76;1
"Unit";"Zergling";"Larva";77;1
"Unit";"Zergling";"Larva";78;1
"Unit";"Zergling";"Larva";79;1
"Unit";"Zergling";"Larva";80;1
"Unit";"Zergling";"Larva";81;1
"Unit";"Zergling";"Larva";82;1
"Unit";"Zergling";"Larva";83;1
"Unit";"Zergling";"Larva";84;1
"Unit";"Zergling";"Larva";85;1
"Unit";"Zergling";"Larva";86;1
"Unit";"Zergling";"Larva";87;1
"Unit";"Zergling";"Larva";88;1
"Unit";"Overlord";"Larva";89;0
"Unit";"Zergling";"Larva";90;1
"Unit";"Zergling";"Larva";91;1
"Unit";"Zergling";"Larva";92;1
"Unit";"Zergling";"Larva";93;1
"Unit";"Zergling";"Larva";94;1
"Unit";"Zergling";"Larva";95;1
"Unit";"Overlord";"Larva";96;0
"Building";"CreepTumorQueen";NA;96;0
"Unit";"Overlord";"Larva";96;0
"Building";"CreepTumorQueen";NA;96;0
"Unit";"Overlord";"Larva";102;0
"Unit";"Overlord";"Larva";104;0
"Building";"Extractor";NA;104;0
"Building";"Extractor";NA;104;0
"Building";"CreepTumor";NA;104;0
"Building";"Extractor";NA;110;0
"Unit";"Overlord";"Larva";110;0
"Building";"SporeCrawler";NA;110;0
"Building";"SporeCrawler";NA;110;0
"Building";"SporeCrawler";NA;110;0
"Unit";"Zergling";"Larva";110;1
"Unit";"Zergling";"Larva";111;1
"Unit";"Zergling";"Larva";112;1
"Unit";"Zergling";"Larva";113;1
"Unit";"Zergling";"Larva";114;1
"Unit";"Zergling";"Larva";115;1
"Unit";"Zergling";"Larva";116;1
"Unit";"Zergling";"Larva";117;1
"Unit";"Zergling";"Larva";118;1
"Unit";"Zergling";"Larva";119;1
"Unit";"Zergling";"Larva";120;1
"Unit";"Zergling";"Larva";121;1
"Unit";"Zergling";"Larva";122;1
"Unit";"Zergling";"Larva";123;1
"Building";"Extractor";NA;124;0
"Building";"Extractor";NA;128;0
"Building";"EvolutionChamber";NA;128;0
"Unit";"Queen";"Hatchery";128;2
"Building";"Spire";NA;133;0
"Building";"CreepTumor";NA;133;0
"Unit";"Overlord";"Larva";133;0
"Building";"CreepTumorQueen";NA;135;0
"Unit";"Overlord";"Larva";135;0
"Building";"SporeCrawler";NA;138;0
"Building";"SporeCrawler";NA;138;0
"Building";"SporeCrawler";NA;138;0
"Unit";"Queen";"Hatchery";138;2
"Unit";"Queen";"Hatchery";140;2
"Building";"CreepTumor";NA;142;0
"Building";"CreepTumor";NA;142;0
"Unit";"Overlord";"Larva";148;0
"Unit";"Overlord";"Larva";157;0
"Unit";"Mutalisk";"Larva";157;2
"Unit";"Mutalisk";"Larva";159;2
"Unit";"Mutalisk";"Larva";161;2
"Unit";"Mutalisk";"Larva";163;2
"Unit";"Mutalisk";"Larva";165;2
"Unit";"Mutalisk";"Larva";167;2
"Unit";"Mutalisk";"Larva";169;2
"Unit";"Mutalisk";"Larva";171;2
"Unit";"Mutalisk";"Larva";173;2
"Unit";"Mutalisk";"Larva";175;2
"Unit";"Mutalisk";"Larva";177;2
"Unit";"Zergling";"Larva";179;1
"Unit";"Zergling";"Larva";180;1
"Unit";"Zergling";"Larva";181;1
"Unit";"Zergling";"Larva";182;1
"Building";"CreepTumor";NA;183;0
"Unit";"Overlord";"Larva";183;0
"Unit";"Zergling";"Larva";183;1
"Unit";"Zergling";"Larva";184;1
"Unit";"Zergling";"Larva";185;1
"Unit";"Zergling";"Larva";186;1
"Building";"Hatchery";NA;187;0
"Unit";"Zergling";"Larva";187;1
"Unit";"Zergling";"Larva";188;1
"Unit";"Zergling";"Larva";189;1
"Unit";"Zergling";"Larva";190;1
"Unit";"Zergling";"Larva";191;1
"Unit";"Zergling";"Larva";192;1
"Unit";"Zergling";"Larva";193;1
"Unit";"Zergling";"Larva";194;1
"Unit";"Zergling";"Larva";195;1
"Unit";"Zergling";"Larva";196;1
"Unit";"Zergling";"Larva";197;1
"Unit";"Zergling";"Larva";198;1
"Unit";"Zergling";"Larva";199;1
"Unit";"Zergling";"Larva";200;1
"Building";"InfestationPit";NA;201;0
"Unit";"Overlord";"Larva";201;0
"Building";"Extractor";NA;201;0
"Unit";"Corruptor";"Larva";201;2
"Unit";"Corruptor";"Larva";203;2
"Unit";"Corruptor";"Larva";205;2
"Unit";"Corruptor";"Larva";207;2
"Unit";"Corruptor";"Larva";209;2
"Unit";"Corruptor";"Larva";211;2
"Building";"Extractor";NA;213;0
"Unit";"Corruptor";"Larva";213;2
"Unit";"Corruptor";"Larva";215;2
"Unit";"Overlord";"Larva";223;0
"Unit";"Corruptor";"Larva";223;2
"Unit";"Corruptor";"Larva";225;2
"Building";"SporeCrawler";NA;227;0
"Unit";"Overlord";"Larva";227;0
"Unit";"Corruptor";"Larva";227;2
"Unit";"Corruptor";"Larva";229;2
"Building";"Hatchery";NA;231;0
"Unit";"Corruptor";"Larva";231;2
"Unit";"Corruptor";"Larva";233;2
"Unit";"Corruptor";"Larva";235;2
"Unit";"Corruptor";"Larva";237;2
"Unit";"Corruptor";"Larva";239;2
"Unit";"Overlord";"Larva";247;0
"Unit";"Mutalisk";"Larva";247;2
"Unit";"Mutalisk";"Larva";249;2
"Unit";"Mutalisk";"Larva";251;2
"Unit";"Mutalisk";"Larva";253;2
"Unit";"Mutalisk";"Larva";255;2
"Unit";"Zergling";"Larva";257;1
"Unit";"Zergling";"Larva";258;1
"Unit";"Zergling";"Larva";259;1
"Unit";"Zergling";"Larva";260;1
"Unit";"Zergling";"Larva";261;1
"Unit";"Zergling";"Larva";262;1
"Unit";"Zergling";"Larva";263;1
"Unit";"Zergling";"Larva";264;1
"Unit";"Zergling";"Larva";265;1
"Unit";"Zergling";"Larva";266;1
"Unit";"Zergling";"Larva";267;1
"Unit";"Zergling";"Larva";268;1
"Unit";"Zergling";"Larva";269;1
"Unit";"Zergling";"Larva";270;1
"Building";"Hatchery";NA;271;0
"Unit";"Mutalisk";"Larva";271;2
"Unit";"Mutalisk";"Larva";273;2
"Unit";"Mutalisk";"Larva";275;2
"Unit";"Overlord";"Larva";277;0
"Unit";"Overlord";"Larva";277;0
"Unit";"Overlord";"Larva";277;0
"Unit";"Mutalisk";"Larva";277;2
"Unit";"Mutalisk";"Larva";279;2
"Unit";"Mutalisk";"Larva";281;2
"Unit";"Mutalisk";"Larva";283;2
"Unit";"Overlord";"Larva";288;0
"Unit";"Overlord";"Larva";288;0
"Unit";"Mutalisk";"Larva";288;2
"Unit";"Mutalisk";"Larva";290;2
"Unit";"Overlord";"Larva";292;0
"Unit";"Mutalisk";"Larva";292;2
"Unit";"Mutalisk";"Larva";299;2
"Unit";"Mutalisk";"Larva";301;2
"Unit";"Mutalisk";"Larva";303;2
"Unit";"Mutalisk";"Larva";305;2
"Unit";"Mutalisk";"Larva";307;2
"Unit";"Mutalisk";"Larva";309;2
"Building";"Extractor";NA;315;0
"Building";"Extractor";NA;315;0
"Unit";"Overlord";"Larva";315;0
"Unit";"Mutalisk";"Larva";315;2
"Unit";"Mutalisk";"Larva";317;2
"Unit";"Mutalisk";"Larva";319;2
"Unit";"Mutalisk";"Larva";321;2
"Unit";"Overlord";"Larva";323;0
"Building";"SporeCrawler";NA;323;0
"Building";"SporeCrawler";NA;323;0
"Unit";"Corruptor";"Larva";323;2
"Unit";"Corruptor";"Larva";325;2
"Unit";"Overlord";"Larva";333;0
"Unit";"Overlord";"Larva";333;0
"Unit";"Infestor";"Larva";333;2
"Unit";"Infestor";"Larva";335;2
"Unit";"Infestor";"Larva";337;2
"Unit";"Corruptor";"Larva";339;2
"Unit";"Corruptor";"Larva";341;2
"Unit";"Corruptor";"Larva";343;2
"Unit";"Corruptor";"Larva";345;2
"Unit";"Zergling";"Larva";347;1
"Unit";"Zergling";"Larva";348;1
"Unit";"Zergling";"Larva";349;1
"Unit";"Zergling";"Larva";350;1
"Unit";"Zergling";"Larva";351;1
"Unit";"Zergling";"Larva";352;1
"Unit";"Zergling";"Larva";353;1
"Unit";"Zergling";"Larva";354;1
"Unit";"Zergling";"Larva";355;1
"Unit";"Zergling";"Larva";356;1
"Unit";"Zergling";"Larva";357;1
"Unit";"Zergling";"Larva";358;1
"Unit";"Zergling";"Larva";359;1
"Unit";"Zergling";"Larva";360;1
"Unit";"Zergling";"Larva";361;1
"Unit";"Zergling";"Larva";362;1
"Upgrade";"Burrow";"Hatchery";363;0
"Building";"CreepTumor";NA;363;0
"Building";"Hatchery";NA;370;0
"Building";"SporeCrawler";NA;370;0
"Building";"SporeCrawler";NA;370;0
"Building";"SporeCrawler";NA;370;0
"Building";"SporeCrawler";NA;370;0
"Building";"SporeCrawler";NA;370;0
"Building";"SporeCrawler";NA;370;0
"Building";"SporeCrawler";NA;370;0
"Unit";"Corruptor";"Larva";370;2
"Unit";"Corruptor";"Larva";372;2
"Unit";"Corruptor";"Larva";374;2
"Unit";"Corruptor";"Larva";376;2
"Unit";"Corruptor";"Larva";378;2
"Unit";"Corruptor";"Larva";380;2
"Unit";"Overlord";"Larva";382;0
"Unit";"Corruptor";"Larva";382;2
"Unit";"Corruptor";"Larva";384;2
"Building";"CreepTumor";NA;386;0
"Unit";"Mutalisk";"Larva";386;2
"Unit";"Mutalisk";"Larva";388;2
"Unit";"Mutalisk";"Larva";390;2
"Unit";"Mutalisk";"Larva";392;2
"Unit";"Mutalisk";"Larva";394;2
"Unit";"Mutalisk";"Larva";396;2
"Unit";"Mutalisk";"Larva";398;2
"Unit";"Mutalisk";"Larva";400;2
"Unit";"Mutalisk";"Larva";402;2
"Unit";"Infestor";"Larva";404;2
"Unit";"Infestor";"Larva";406;2
"Unit";"Infestor";"Larva";408;2
"Unit";"Corruptor";"Larva";410;2
"Unit";"Corruptor";"Larva";412;2
"Unit";"Corruptor";"Larva";414;2
"Unit";"Infestor";"Larva";416;2
"Unit";"Infestor";"Larva";418;2
"Unit";"Infestor";"Larva";420;2
"Unit";"Infestor";"Larva";422;2
"Unit";"Infestor";"Larva";424;2
"Building";"Extractor";NA;426;0
"Building";"Extractor";NA;426;0
"Unit";"Mutalisk";"Larva";426;2
"Unit";"Mutalisk";"Larva";428;2
"Unit";"Mutalisk";"Larva";430;2
"Unit";"Mutalisk";"Larva";432;2
"Unit";"Mutalisk";"Larva";434;2
"Building";"SporeCrawler";NA;436;0
"Building";"SporeCrawler";NA;436;0
"Building";"SporeCrawler";NA;436;0
"Building";"SporeCrawler";NA;436;0
"Unit";"Zergling";"Larva";436;1
"Unit";"Zergling";"Larva";437;1
"Unit";"Zergling";"Larva";438;1
"Unit";"Zergling";"Larva";439;1
"Unit";"Zergling";"Larva";440;1
"Unit";"Zergling";"Larva";441;1
"Unit";"Zergling";"Larva";442;1
"Unit";"Zergling";"Larva";443;1
"Unit";"Zergling";"Larva";444;1
"Unit";"Zergling";"Larva";445;1
"Unit";"Zergling";"Larva";446;1
"Unit";"Zergling";"Larva";447;1
"Unit";"Zergling";"Larva";448;1
"Unit";"Zergling";"Larva";449;1
"Unit";"Zergling";"Larva";450;1
"Unit";"Zergling";"Larva";451;1
"Unit";"Zergling";"Larva";452;1
"Unit";"Zergling";"Larva";453;1
"Unit";"Zergling";"Larva";454;1
"Unit";"Zergling";"Larva";455;1
"Unit";"Zergling";"Larva";456;1
"Unit";"Zergling";"Larva";457;1
"Unit";"Zergling";"Larva";458;1
"Unit";"Zergling";"Larva";459;1
"Unit";"Zergling";"Larva";460;1
"Unit";"Zergling";"Larva";461;1
"Unit";"Zergling";"Larva";462;1
"Unit";"Zergling";"Larva";463;1
"Unit";"Zergling";"Larva";464;1
"Unit";"Zergling";"Larva";465;1
"Unit";"Zergling";"Larva";466;1
"Unit";"Zergling";"Larva";467;1
"Unit";"Zergling";"Larva";468;1
"Unit";"Zergling";"Larva";469;1
"Unit";"Zergling";"Larva";470;1
"Unit";"Zergling";"Larva";471;1
"Upgrade";"NeuralParasite";"InfestationPit";472;0
"Unit";"Corruptor";"Larva";477;2
"Unit";"Corruptor";"Larva";479;2
"Unit";"Corruptor";"Larva";481;2
"Unit";"Corruptor";"Larva";483;2
"Unit";"Corruptor";"Larva";485;2
"Unit";"Corruptor";"Larva";487;2
"Unit";"Mutalisk";"Larva";489;2
"Unit";"Mutalisk";"Larva";491;2
"Unit";"Mutalisk";"Larva";493;2
"Unit";"Mutalisk";"Larva";495;2
"Unit";"Mutalisk";"Larva";497;2
"Unit";"Mutalisk";"Larva";499;2
"Unit";"Mutalisk";"Larva";501;2
"Unit";"Mutalisk";"Larva";503;2
"Unit";"Mutalisk";"Larva";505;2
"Unit";"Mutalisk";"Larva";507;2
"Unit";"Mutalisk";"Larva";509;2
"Unit";"Mutalisk";"Larva";511;2
"Unit";"Mutalisk";"Larva";513;2
"Unit";"Mutalisk";"Larva";515;2
"Unit";"Zergling";"Larva";517;1
"Unit";"Zergling";"Larva";518;1
"Unit";"Zergling";"Larva";519;1
"Unit";"Zergling";"Larva";520;1
"Unit";"Zergling";"Larva";521;1
"Unit";"Zergling";"Larva";522;1
"Unit";"Zergling";"Larva";523;1
"Unit";"Zergling";"Larva";524;1
"Unit";"Zergling";"Larva";525;1
"Unit";"Zergling";"Larva";526;1
"Unit";"Zergling";"Larva";527;1
"Unit";"Zergling";"Larva";528;1
"Unit";"Zergling";"Larva";529;1
"Unit";"Zergling";"Larva";530;1
"Unit";"Zergling";"Larva";531;1
"Unit";"Zergling";"Larva";532;1
"Unit";"Zergling";"Larva";533;1
"Unit";"Zergling";"Larva";534;1
"Unit";"Zergling";"Larva";535;1
"Unit";"Zergling";"Larva";536;1
"Unit";"Zergling";"Larva";537;1
"Unit";"Zergling";"Larva";538;1
"Unit";"Zergling";"Larva";539;1
"Unit";"Zergling";"Larva";540;1
"Unit";"Zergling";"Larva";541;1
"Unit";"Zergling";"Larva";542;1
"Upgrade";"SprayZerg";NA;543;0
"Upgrade";"SprayZerg";NA;543;0
"Upgrade";"SprayZerg";NA;543;0
"Upgrade";"zerglingmovementspeed";NA;543;0
"Upgrade";"SprayZerg";NA;543;0
"Upgrade";"SprayZerg";NA;543;0
"Upgrade";"ZergMissileWeaponsLevel1";NA;543;0
"Upgrade";"SprayZerg";NA;543;0
"Upgrade";"ZergFlyerWeaponsLevel1";NA;543;0
"Upgrade";"SprayZerg";NA;543;0
"Upgrade";"SprayZerg";NA;543;0
"Upgrade";"ZergGroundArmorsLevel1";NA;543;0
"Upgrade";"SprayZerg";NA;543;0
"Upgrade";"SprayZerg";NA;543;0
"Upgrade";"SprayZerg";NA;543;0
"Upgrade";"ZergFlyerArmorsLevel1";NA;543;0
"Upgrade";"SprayZerg";NA;543;0
"Upgrade";"SprayZerg";NA;543;0
"Upgrade";"overlordspeed";NA;543;0
"Upgrade";"ZergMeleeWeaponsLevel1";NA;543;0
"Upgrade";"ZergGroundArmorsLevel2";NA;543;0
"Upgrade";"ZergFlyerWeaponsLevel2";NA;543;0
