"type";"unit_name";"on_building";"total_supply";"supply"
"Building";"Refinery";NA;14;0
"Building";"Barracks";NA;15;0
"Unit";"Marine";"Barracks";19;1
"Building";"Refinery";NA;19;0
"Unit";"Marine";"Barracks";19;1
"Building";"Factory";NA;19;0
"Unit";"Marine";"Barracks";20;1
"Unit";"Marine";"Barracks";22;1
"Building";"Starport";NA;21;0
"Building";"BarracksTechLab";NA;26;0
"Unit";"Medivac";"Starport";26;2
"Building";"FactoryReactor";NA;27;0
"Building";"BarracksReactor";NA;28;0
"Unit";"Hellion";"Factory";31;2
"Unit";"Hellion";"Factory";31;2
"Unit";"Marine";"Barracks";31;1
"Unit";"Marine";"Barracks";31;1
"Unit";"Banshee";"Starport";31;3
"Building";"CommandCenter";NA;31;0
"Unit";"Hellion";"Factory";38;2
"Unit";"Marine";"Barracks";41;1
"Unit";"Marine";"Barracks";41;1
"Unit";"Hellion";"Factory";41;2
"Unit";"Marine";"Barracks";46;1
"Unit";"Marine";"Barracks";46;1
"Unit";"Hellion";"Factory";46;2
"Unit";"Hellion";"Factory";46;2
"Unit";"Banshee";"Starport";41;3
"Building";"Armory";NA;43;0
"Unit";"Marine";"Barracks";49;1
"Unit";"Marine";"Barracks";50;1
"Unit";"Hellion";"Factory";51;2
"Unit";"Hellion";"Factory";59;2
"Unit";"Banshee";"Starport";60;3
"Unit";"Marine";"Barracks";69;1
"Unit";"Hellion";"Factory";69;2
"Unit";"Hellion";"Factory";69;2
"Unit";"Banshee";"Starport";71;3
"Unit";"Hellion";"Factory";81;2
"Unit";"Hellion";"Factory";81;2
"Building";"Refinery";NA;81;0
"Building";"Factory";NA;81;0
"Building";"Factory";NA;81;0
"Building";"Armory";NA;81;0
"Unit";"Hellion";"Factory";88;2
"Building";"CommandCenter";NA;75;0
"Building";"Refinery";NA;94;0
"Building";"FactoryTechLab";NA;94;0
"Building";"FactoryTechLab";NA;94;0
"Building";"Factory";NA;96;0
"Building";"Factory";NA;97;0
"Building";"EngineeringBay";NA;99;0
"Building";"FactoryTechLab";NA;101;0
"Unit";"Thor";"Factory";99;6
"Building";"MissileTurret";NA;103;0
"Building";"MissileTurret";NA;103;0
"Unit";"Thor";"Factory";101;6
"Unit";"Raven";"Starport";101;2
"Building";"Refinery";NA;112;0
"Building";"Refinery";NA;112;0
"Unit";"Cyclone";"Factory";112;3
"Unit";"Hellion";"Factory";121;2
"Unit";"Hellion";"Factory";121;2
"Unit";"Hellion";"Factory";121;2
"Upgrade";"TerranVehicleWeaponsLevel1";"Armory";101;0
"Unit";"Thor";"Factory";112;6
"Unit";"Hellion";"Factory";130;2
"Unit";"Raven";"Starport";134;2
"Unit";"Hellion";"Factory";146;2
"Unit";"Hellion";"Factory";146;2
"Building";"MissileTurret";NA;151;0
"Building";"CommandCenter";NA;130;0
"Unit";"Thor";"Factory";146;6
"Unit";"Hellion";"Factory";158;2
"Unit";"Hellion";"Factory";158;2
"Building";"MissileTurret";NA;164;0
"Unit";"Hellion";"Factory";164;2
"Unit";"Hellion";"Factory";164;2
"Unit";"Hellion";"Factory";164;2
"Unit";"Raven";"Starport";156;2
"Building";"MissileTurret";NA;170;0
"Unit";"Hellion";"Factory";170;2
"Building";"Refinery";NA;178;0
"Building";"Refinery";NA;178;0
"Unit";"Hellion";"Factory";180;2
"Unit";"Hellion";"Factory";180;2
"Building";"SensorTower";NA;180;0
"Building";"MissileTurret";NA;180;0
"Building";"MissileTurret";NA;180;0
"Upgrade";"TerranVehicleWeaponsLevel2";"Armory";151;0
"Building";"MissileTurret";NA;185;0
"Building";"MissileTurret";NA;185;0
"Unit";"Hellion";"Factory";185;2
"Unit";"Raven";"Starport";180;2
"Building";"MissileTurret";NA;187;0
"Building";"SensorTower";NA;187;0
"Building";"Starport";NA;185;0
"Building";"Starport";NA;185;0
"Building";"CommandCenter";NA;180;0
"Unit";"Hellion";"Factory";192;2
"Unit";"Hellion";"Factory";192;2
"Building";"StarportTechLab";NA;192;0
"Building";"StarportTechLab";NA;192;0
"Unit";"Hellion";"Factory";192;2
"Building";"Starport";NA;196;0
"Building";"Starport";NA;196;0
"Unit";"Raven";"Starport";196;2
"Unit";"Hellion";"Factory";200;2
"Unit";"Hellion";"Factory";200;2
"Unit";"Hellion";"Factory";206;2
"Unit";"Hellion";"Factory";206;2
"Building";"Refinery";NA;206;0
"Building";"Refinery";NA;206;0
"Building";"SensorTower";NA;206;0
"Building";"StarportTechLab";NA;206;0
"Upgrade";"TerranVehicleWeaponsLevel3";"Armory";196;0
"Building";"StarportTechLab";NA;214;0
"Building";"CommandCenter";NA;206;0
"Unit";"Hellion";"Factory";214;2
"Unit";"Hellion";"Factory";214;2
"Building";"CommandCenter";NA;206;0
"Building";"FusionCore";NA;214;0
"Unit";"Hellion";"Factory";214;2
"Unit";"Raven";"Starport";214;2
"Unit";"Raven";"Starport";214;2
"Unit";"Raven";"Starport";214;2
"Building";"Refinery";NA;220;0
"Building";"MissileTurret";NA;220;0
"Building";"MissileTurret";NA;220;0
"Building";"MissileTurret";NA;220;0
"Building";"CommandCenter";NA;218;0
"Upgrade";"TerranShipWeaponsLevel1";"Armory";218;0
"Building";"Refinery";NA;226;0
"Building";"Refinery";NA;226;0
"Building";"MissileTurret";NA;226;0
"Building";"MissileTurret";NA;226;0
"Building";"MissileTurret";NA;226;0
"Building";"MissileTurret";NA;226;0
"Building";"MissileTurret";NA;226;0
"Building";"MissileTurret";NA;226;0
"Building";"MissileTurret";NA;226;0
"Unit";"Battlecruiser";"Starport";226;6
"Unit";"Battlecruiser";"Starport";226;6
"Unit";"Battlecruiser";"Starport";226;6
"Unit";"Battlecruiser";"Starport";226;6
"Unit";"Battlecruiser";"Starport";226;6
"Building";"CommandCenter";NA;226;0
"Building";"Refinery";NA;238;0
"Building";"CommandCenter";NA;226;0
"Building";"CommandCenter";NA;226;0
"Unit";"Hellion";"Factory";256;2
"Unit";"Hellion";"Factory";256;2
"Unit";"Hellion";"Factory";256;2
"Unit";"Hellion";"Factory";256;2
"Unit";"Hellion";"Factory";256;2
"Unit";"Hellion";"Factory";256;2
"Unit";"Hellion";"Factory";256;2
"Unit";"Battlecruiser";"Starport";238;6
"Unit";"Battlecruiser";"Starport";238;6
"Unit";"Battlecruiser";"Starport";238;6
"Unit";"Hellion";"Factory";256;2
"Unit";"Hellion";"Factory";258;2
"Unit";"Hellion";"Factory";260;2
"Unit";"Hellion";"Factory";262;2
"Unit";"Hellion";"Factory";262;2
"Unit";"Hellion";"Factory";270;2
"Unit";"Hellion";"Factory";270;2
"Unit";"Battlecruiser";"Starport";256;6
"Unit";"Battlecruiser";"Starport";256;6
"Unit";"Hellion";"Factory";288;2
"Unit";"Hellion";"Factory";290;2
"Unit";"Hellion";"Factory";292;2
"Unit";"Hellion";"Factory";302;2
"Unit";"Hellion";"Factory";302;2
"Upgrade";"TerranShipWeaponsLevel2";"Armory";256;0
"Unit";"Battlecruiser";"Starport";302;6
"Unit";"Battlecruiser";"Starport";302;6
"Unit";"Battlecruiser";"Starport";302;6
"Unit";"Hellion";"Factory";325;2
"Unit";"Hellion";"Factory";325;2
"Unit";"Hellion";"Factory";325;2
"Unit";"Hellion";"Factory";325;2
"Unit";"Hellion";"Factory";325;2
"Unit";"Hellion";"Factory";325;2
"Unit";"Hellion";"Factory";325;2
"Unit";"Battlecruiser";"Starport";321;6
"Unit";"Battlecruiser";"Starport";321;6
"Unit";"Hellion";"Factory";343;2
"Unit";"Hellion";"Factory";345;2
"Unit";"Hellion";"Factory";347;2
"Unit";"Hellion";"Factory";375;2
"Unit";"Hellion";"Factory";375;2
"Unit";"Hellion";"Factory";375;2
"Building";"Starport";NA;369;0
"Building";"Starport";NA;369;0
"Unit";"Battlecruiser";"Starport";325;6
"Unit";"Battlecruiser";"Starport";357;6
"Unit";"Battlecruiser";"Starport";357;6
"Unit";"Hellion";"Factory";381;2
"Unit";"Hellion";"Factory";381;2
"Unit";"Hellion";"Factory";381;2
"Unit";"Battlecruiser";"Starport";357;6
"Building";"StarportTechLab";NA;387;0
"Building";"StarportTechLab";NA;387;0
"Unit";"Battlecruiser";"Starport";375;6
"Unit";"Battlecruiser";"Starport";381;6
"Unit";"Battlecruiser";"Starport";387;6
