"Type";"UnitName";"OnBuilding";"TotalSupply";"Supply"
"Unit";"SCV";"Command Center";12;1
"Unit";"SCV";"Command Center";12;1
"Unit";"SCV";"Command Center";13;1
"Building";"SupplyDepot";NA;13;0
"Unit";"SCV";"Command Center";15;1
"Building";"Refinery";NA;14;0
"Unit";"SCV";"Command Center";15;1
"Unit";"SCV";"Command Center";16;1
"Unit";"SCV";"Command Center";17;1
"Building";"Barracks";NA;15;0
"Unit";"Reaper";"Barracks";19;1
"Unit";"SCV";"Command Center";19;1
"Unit";"SCV";"Command Center";21;1
"Unit";"SCV";"Command Center";21;1
"Building";"Factory";NA;19;0
"Building";"SupplyDepot";NA;21;0
"Building";"BarracksReactor";NA;20;0
"Building";"Refinery";NA;22;0
"Unit";"SCV";"Command Center";22;1
"Unit";"SCV";"Command Center";23;1
"Building";"CommandCenter";NA;19;0
"Unit";"Hellion";"Factory";23;2
"Unit";"Hellion";"Factory";23;2
"Building";"BarracksTechLab";NA;24;0
"Unit";"SCV";"Command Center";24;1
"Building";"Starport";NA;23;0
"Unit";"Hellion";"Factory";25;2
"Unit";"Hellion";"Factory";27;2
"Unit";"SCV";"Command Center";30;1
"Unit";"SCV";"Command Center";35;1
"Unit";"SCV";"Command Center";35;1
"Unit";"SCV";"Command Center";36;1
"Unit";"SCV";"Command Center";37;1
"Unit";"SCV";"Command Center";37;1
"Unit";"Hellion";"Factory";37;2
"Unit";"Hellion";"Factory";37;2
"Unit";"SCV";"Command Center";38;1
"Unit";"SCV";"Command Center";39;1
"Building";"SupplyDepot";NA;40;0
"Building";"BarracksTechLab";NA;44;0
"Unit";"Banshee";"Starport";38;3
"Unit";"SCV";"Command Center";46;1
"Unit";"SCV";"Command Center";46;1
"Building";"SupplyDepot";NA;46;0
"Unit";"SCV";"Command Center";51;1
"Unit";"SCV";"Command Center";51;1
"Unit";"SCV";"Command Center";53;1
"Unit";"SCV";"Command Center";53;1
"Building";"SupplyDepot";NA;51;0
"Unit";"Marine";"Barracks";53;1
"Unit";"SCV";"Command Center";53;1
"Unit";"SCV";"Command Center";54;1
"Building";"CommandCenter";NA;45;0
"Unit";"Banshee";"Starport";51;3
"Building";"FactoryReactor";NA;51;0
"Unit";"SCV";"Command Center";56;1
"Unit";"SCV";"Command Center";57;1
"Building";"SupplyDepot";NA;55;0
"Unit";"Marine";"Barracks";56;1
"Building";"EngineeringBay";NA;55;0
"Building";"EngineeringBay";NA;55;0
"Building";"Barracks";NA;53;0
"Building";"Barracks";NA;53;0
"Unit";"SCV";"Command Center";61;1
"Unit";"SCV";"Command Center";64;1
"Unit";"SCV";"Command Center";64;1
"Unit";"Marine";"Barracks";63;1
"Building";"SupplyDepot";NA;63;0
"Building";"Refinery";NA;64;0
"Building";"Refinery";NA;64;0
"Unit";"Marine";"Barracks";64;1
"Unit";"SCV";"Command Center";67;1
"Unit";"SCV";"Command Center";67;1
"Unit";"Marine";"Barracks";68;1
"Unit";"SCV";"Command Center";71;1
"Unit";"SCV";"Command Center";71;1
"Unit";"Marine";"Barracks";71;1
"Unit";"Marine";"Barracks";71;1
"Unit";"Marine";"Barracks";71;1
"Unit";"Marine";"Barracks";71;1
"Unit";"SCV";"Command Center";75;1
"Unit";"SCV";"Command Center";75;1
"Unit";"SCV";"Command Center";78;1
"Unit";"Marine";"Barracks";72;1
"Unit";"Marine";"Barracks";74;1
"Unit";"Marine";"Barracks";75;1
"Unit";"SCV";"Command Center";78;1
"Unit";"SCV";"Command Center";79;1
"Unit";"Marine";"Barracks";78;1
"Unit";"Marine";"Barracks";78;1
"Building";"StarportReactor";NA;72;0
"Upgrade";"Stimpack";"TechLab";58;0
"Unit";"Marine";"Barracks";81;1
"Unit";"SCV";"Command Center";84;1
"Building";"Armory";NA;71;0
"Unit";"SCV";"Command Center";84;1
"Unit";"SCV";"Command Center";88;1
"Unit";"SCV";"Command Center";89;1
"Unit";"SCV";"Command Center";90;1
"Building";"Barracks";NA;78;0
"Building";"Barracks";NA;78;0
"Unit";"SCV";"Command Center";91;1
"Unit";"Marine";"Barracks";91;1
"Unit";"Marine";"Barracks";91;1
"Unit";"Marine";"Barracks";91;1
"Unit";"Marine";"Barracks";91;1
"Unit";"Marine";"Barracks";91;1
"Building";"Refinery";NA;91;0
"Building";"Refinery";NA;91;0
"Unit";"SCV";"Command Center";94;1
"Unit";"SCV";"Command Center";94;1
"Upgrade";"TerranInfantryWeaponsLevel1";"EngineeringBay";71;0
"Upgrade";"TerranInfantryArmorsLevel1";"EngineeringBay";71;0
"Unit";"Medivac";"Starport";91;2
"Unit";"Medivac";"Starport";91;2
"Building";"SupplyDepot";NA;94;0
"Building";"SupplyDepot";NA;94;0
"Unit";"Marine";"Barracks";95;1
"Unit";"SCV";"Command Center";102;1
"Unit";"Marine";"Barracks";100;1
"Unit";"Marine";"Barracks";100;1
"Unit";"Marine";"Barracks";100;1
"Unit";"Marine";"Barracks";100;1
"Unit";"SCV";"Command Center";106;1
"Unit";"SCV";"Command Center";106;1
"Building";"Factory";NA;92;0
"Building";"BarracksReactor";NA;94;0
"Building";"BarracksReactor";NA;94;0
"Building";"CommandCenter";NA;84;0
"Unit";"SCV";"Command Center";107;1
"Unit";"SCV";"Command Center";112;1
"Unit";"SCV";"Command Center";113;1
"Unit";"Marine";"Barracks";112;1
"Unit";"Marine";"Barracks";112;1
"Unit";"Marine";"Barracks";112;1
"Building";"FactoryTechLab";NA;114;0
"Building";"SupplyDepot";NA;114;0
"Building";"SupplyDepot";NA;114;0
"Unit";"SCV";"Command Center";117;1
"Unit";"SCV";"Command Center";117;1
"Unit";"Marine";"Barracks";120;1
"Unit";"Marine";"Barracks";120;1
"Unit";"Marine";"Barracks";120;1
"Unit";"Marine";"Barracks";120;1
"Unit";"Marine";"Barracks";120;1
"Unit";"SCV";"Command Center";122;1
"Unit";"SCV";"Command Center";122;1
"Unit";"SCV";"Command Center";122;1
"Building";"SupplyDepot";NA;120;0
"Building";"SupplyDepot";NA;120;0
"Unit";"Medivac";"Starport";120;2
"Unit";"Medivac";"Starport";120;2
"Unit";"Marine";"Barracks";122;1
"Unit";"Marine";"Barracks";127;1
"Unit";"Marine";"Barracks";127;1
"Unit";"Marine";"Barracks";127;1
"Unit";"SCV";"Command Center";135;1
"Unit";"SCV";"Command Center";135;1
"Unit";"SCV";"Command Center";135;1
"Upgrade";"TerranVehicleWeaponsLevel1";"Armory";107;0
"Unit";"Marine";"Barracks";135;1
"Unit";"Marine";"Barracks";136;1
"Unit";"Marine";"Barracks";136;1
"Unit";"Marine";"Barracks";136;1
"Unit";"Marine";"Barracks";136;1
"Unit";"SCV";"Command Center";138;1
"Unit";"SCV";"Command Center";139;1
"Unit";"SCV";"Command Center";140;1
"Unit";"Medivac";"Starport";130;2
"Unit";"Medivac";"Starport";132;2
"Unit";"SCV";"Command Center";146;1
"Unit";"SCV";"Command Center";147;1
"Building";"Refinery";NA;153;0
"Building";"Refinery";NA;153;0
"Unit";"Marine";"Barracks";155;1
"Unit";"SCV";"Command Center";155;1
"Unit";"SCV";"Command Center";155;1
"Unit";"Marine";"Barracks";155;1
"Unit";"Marine";"Barracks";155;1
"Unit";"Marine";"Barracks";155;1
"Unit";"Marine";"Barracks";155;1
"Unit";"Marine";"Barracks";155;1
"Unit";"Marine";"Barracks";155;1
"Unit";"Marine";"Barracks";155;1
"Unit";"Marine";"Barracks";155;1
"Building";"Barracks";NA;141;0
"Building";"Barracks";NA;141;0
"Building";"Barracks";NA;141;0
"Building";"GhostAcademy";NA;155;0
"Unit";"SCV";"Command Center";166;1
"Unit";"SCV";"Command Center";166;1
"Unit";"Medivac";"Starport";155;2
"Unit";"Medivac";"Starport";155;2
"Unit";"Marine";"Barracks";166;1
"Unit";"Marine";"Barracks";166;1
"Unit";"Marine";"Barracks";166;1
"Unit";"Marine";"Barracks";166;1
"Unit";"Marine";"Barracks";166;1
"Unit";"Marine";"Barracks";166;1
"Unit";"Marine";"Barracks";166;1
"Unit";"SCV";"Command Center";166;1
"Upgrade";"TerranInfantryWeaponsLevel2";"EngineeringBay";127;0
"Upgrade";"TerranInfantryArmorsLevel2";"EngineeringBay";127;0
"Building";"SupplyDepot";NA;166;0
"Building";"SupplyDepot";NA;166;0
"Unit";"Marine";"Barracks";166;1
"Building";"BarracksTechLab";NA;172;0
"Building";"BarracksTechLab";NA;173;0
"Building";"BarracksTechLab";NA;179;0
"Unit";"SCV";"Command Center";181;1
"Unit";"SCV";"Command Center";181;1
"Unit";"SCV";"Command Center";181;1
"Unit";"Marine";"Barracks";181;1
"Building";"CommandCenter";NA;166;0
"Unit";"Marine";"Barracks";181;1
"Unit";"Marine";"Barracks";181;1
"Unit";"Marine";"Barracks";181;1
"Unit";"Marine";"Barracks";181;1
"Unit";"Marine";"Barracks";181;1
"Unit";"Marine";"Barracks";181;1
"Unit";"Marine";"Barracks";181;1
"Unit";"Ghost";"Barracks";181;2
"Unit";"Ghost";"Barracks";181;2
"Unit";"Ghost";"Barracks";181;2
"Unit";"Ghost";"Barracks";181;2
"Unit";"SCV";"Command Center";192;1
"Unit";"SCV";"Command Center";192;1
"Unit";"SCV";"Command Center";192;1
"Unit";"SCV";"Command Center";192;1
"Unit";"Marine";"Barracks";187;1
"Unit";"Marine";"Barracks";192;1
"Unit";"Marine";"Barracks";192;1
"Unit";"Marine";"Barracks";192;1
"Unit";"Marine";"Barracks";192;1
"Unit";"Marine";"Barracks";192;1
"Unit";"Marine";"Barracks";192;1
"Building";"MissileTurret";NA;205;0
"Upgrade";"TerranVehicleWeaponsLevel2";"Armory";180;0
"Building";"MissileTurret";NA;205;0
"Unit";"Ghost";"Barracks";192;2
"Unit";"Ghost";"Barracks";194;2
"Building";"Starport";NA;205;0
"Building";"Starport";NA;205;0
"Unit";"Marine";"Barracks";211;1
"Unit";"Marine";"Barracks";211;1
"Unit";"Marine";"Barracks";211;1
"Unit";"Marine";"Barracks";211;1
"Unit";"Marine";"Barracks";213;1
"Unit";"Marine";"Barracks";213;1
"Unit";"Marine";"Barracks";213;1
"Unit";"Marine";"Barracks";213;1
"Unit";"Marine";"Barracks";215;1
"Building";"FusionCore";NA;211;0
"Unit";"Ghost";"Barracks";215;2
"Unit";"Ghost";"Barracks";215;2
"Unit";"Ghost";"Barracks";215;2
"Building";"StarportTechLab";NA;223;0
"Building";"CommandCenter";NA;204;0
"Building";"CommandCenter";NA;204;0
"Unit";"Marine";"Barracks";228;1
"Unit";"Marine";"Barracks";228;1
"Unit";"Marine";"Barracks";228;1
"Unit";"Marine";"Barracks";228;1
"Unit";"Marine";"Barracks";228;1
"Unit";"Marine";"Barracks";228;1
"Unit";"Marine";"Barracks";228;1
"Unit";"Marine";"Barracks";228;1
"Building";"CommandCenter";NA;205;0
"Unit";"Ghost";"Barracks";223;2
"Building";"StarportReactor";NA;223;0
"Unit";"Ghost";"Barracks";224;2
"Unit";"Ghost";"Barracks";226;2
"Unit";"Marine";"Barracks";230;1
"Unit";"Marine";"Barracks";230;1
"Unit";"Marine";"Barracks";231;1
"Unit";"Marine";"Barracks";231;1
"Unit";"Marine";"Barracks";233;1
"Unit";"Marine";"Barracks";233;1
"Upgrade";"TerranInfantryArmorsLevel3";"EngineeringBay";185;0
"Upgrade";"TerranInfantryWeaponsLevel3";"EngineeringBay";185;0
