"Type";"UnitName";"OnBuilding";"TotalSupply";"Supply"
"Unit";"SCV";"Command Center";12;1
"Unit";"SCV";"Command Center";12;1
"Unit";"SCV";"Command Center";13;1
"Building";"SupplyDepot";NA;13;0
"Unit";"SCV";"Command Center";15;1
"Unit";"SCV";"Command Center";15;1
"Building";"Refinery";NA;15;0
"Unit";"SCV";"Command Center";16;1
"Building";"Barracks";NA;15;0
"Unit";"SCV";"Command Center";17;1
"Unit";"Reaper";"Barracks";19;1
"Unit";"SCV";"Command Center";19;1
"Unit";"Marine";"Barracks";19;1
"Unit";"SCV";"Command Center";21;1
"Building";"SupplyDepot";NA;21;0
"Unit";"SCV";"Command Center";23;1
"Building";"Factory";NA;20;0
"Building";"CommandCenter";NA;19;0
"Building";"BarracksReactor";NA;23;0
"Unit";"SCV";"Command Center";23;1
"Unit";"SCV";"Command Center";25;1
"Unit";"Hellion";"Factory";25;2
"Unit";"SCV";"Command Center";26;1
"Unit";"Hellion";"Factory";25;2
"Building";"Starport";NA;25;0
"Unit";"SCV";"Command Center";31;1
"Unit";"SCV";"Command Center";31;1
"Unit";"Hellion";"Factory";26;2
"Unit";"Hellion";"Factory";29;2
"Building";"BarracksTechLab";NA;31;0
"Unit";"SCV";"Command Center";31;1
"Building";"CommandCenter";NA;24;0
"Unit";"SCV";"Command Center";35;1
"Building";"Refinery";NA;33;0
"Unit";"SCV";"Command Center";38;1
"Unit";"Hellion";"Factory";33;2
"Unit";"Hellion";"Factory";35;2
"Unit";"SCV";"Command Center";38;1
"Unit";"SCV";"Command Center";45;1
"Unit";"SCV";"Command Center";45;1
"Building";"SupplyDepot";NA;42;0
"Unit";"Hellion";"Factory";42;2
"Unit";"Hellion";"Factory";45;2
"Unit";"SCV";"Command Center";45;1
"Unit";"SCV";"Command Center";45;1
"Building";"SupplyDepot";NA;46;0
"Unit";"Liberator";"Starport";39;3
"Unit";"SCV";"Command Center";53;1
"Unit";"SCV";"Command Center";53;1
"Unit";"SCV";"Command Center";53;1
"Building";"Refinery";NA;53;0
"Building";"Refinery";NA;53;0
"Unit";"SCV";"Command Center";56;1
"Unit";"Hellion";"Factory";53;2
"Unit";"Hellion";"Factory";53;2
"Unit";"SCV";"Command Center";58;1
"Unit";"SCV";"Command Center";58;1
"Unit";"SCV";"Command Center";60;1
"Unit";"SCV";"Command Center";64;1
"Building";"Armory";NA;53;0
"Building";"Armory";NA;53;0
"Unit";"SCV";"Command Center";66;1
"Unit";"SCV";"Command Center";66;1
"Building";"Refinery";NA;64;0
"Building";"Refinery";NA;64;0
"Building";"SupplyDepot";NA;66;0
"Unit";"SCV";"Command Center";68;1
"Unit";"SCV";"Command Center";68;1
"Unit";"SCV";"Command Center";69;1
"Building";"EngineeringBay";NA;67;0
"Unit";"Hellion";"Factory";68;2
"Unit";"Hellion";"Factory";68;2
"Unit";"SCV";"Command Center";70;1
"Unit";"SCV";"Command Center";72;1
"Unit";"SCV";"Command Center";72;1
"Building";"BarracksTechLab";NA;70;0
"Unit";"SCV";"Command Center";80;1
"Unit";"SCV";"Command Center";80;1
"Unit";"Hellion";"Factory";80;2
"Unit";"Hellion";"Factory";80;2
"Unit";"SCV";"Command Center";80;1
"Building";"MissileTurret";NA;80;0
"Building";"MissileTurret";NA;80;0
"Unit";"SCV";"Command Center";80;1
"Building";"Factory";NA;77;0
"Building";"MissileTurret";NA;80;0
"Building";"Factory";NA;80;0
"Unit";"SCV";"Command Center";88;1
"Unit";"SCV";"Command Center";88;1
"Unit";"SCV";"Command Center";88;1
"Building";"StarportReactor";NA;86;0
"Building";"SupplyDepot";NA;88;0
"Building";"SupplyDepot";NA;88;0
"Building";"SupplyDepot";NA;88;0
"Unit";"Hellion";"Factory";88;2
"Unit";"Hellion";"Factory";88;2
"Unit";"SCV";"Command Center";91;1
"Unit";"SCV";"Command Center";91;1
"Unit";"SCV";"Command Center";91;1
"Building";"SupplyDepot";NA;91;0
"Unit";"SCV";"Command Center";98;1
"Unit";"SCV";"Command Center";98;1
"Building";"SupplyDepot";NA;95;0
"Building";"Factory";NA;88;0
"Unit";"SCV";"Command Center";98;1
"Unit";"Medivac";"Starport";91;2
"Building";"Factory";NA;89;0
"Upgrade";"TerranVehicleWeaponsLevel1";"Armory";80;0
"Upgrade";"TerranVehicleAndShipArmorsLevel1";"Armory";80;0
"Unit";"SCV";"Command Center";100;1
"Unit";"Hellion";"Factory";98;2
"Unit";"Hellion";"Factory";98;2
"Building";"FactoryTechLab";NA;101;0
"Unit";"SCV";"Command Center";108;1
"Unit";"SCV";"Command Center";108;1
"Unit";"SCV";"Command Center";108;1
"Building";"FactoryReactor";NA;103;0
"Building";"SupplyDepot";NA;104;0
"Unit";"Hellion";"Factory";108;2
"Unit";"Hellion";"Factory";108;2
"Unit";"SCV";"Command Center";108;1
"Building";"SupplyDepot";NA;108;0
"Building";"SupplyDepot";NA;108;0
"Unit";"SCV";"Command Center";111;1
"Building";"CommandCenter";NA;98;0
"Unit";"SCV";"Command Center";117;1
"Unit";"SCV";"Command Center";117;1
"Unit";"SCV";"Command Center";117;1
"Unit";"Hellion";"Factory";117;2
"Unit";"Hellion";"Factory";117;2
"Unit";"Hellion";"Factory";117;2
"Unit";"Hellion";"Factory";117;2
"Building";"SupplyDepot";NA;117;0
"Unit";"SCV";"Command Center";128;1
"Unit";"SCV";"Command Center";128;1
"Unit";"SCV";"Command Center";128;1
"Unit";"Hellion";"Factory";128;2
"Unit";"Hellion";"Factory";128;2
"Unit";"Hellion";"Factory";128;2
"Building";"Refinery";NA;128;0
"Building";"Refinery";NA;128;0
"Building";"SensorTower";NA;137;0
"Unit";"Hellion";"Factory";137;2
"Unit";"Hellion";"Factory";137;2
"Unit";"Hellion";"Factory";137;2
"Unit";"Hellion";"Factory";137;2
"Upgrade";"TerranVehicleWeaponsLevel2";"Armory";117;0
"Upgrade";"TerranVehicleAndShipArmorsLevel2";"Armory";117;0
"Unit";"Hellion";"Factory";143;2
"Unit";"Hellion";"Factory";143;2
"Building";"Factory";NA;137;0
"Building";"Factory";NA;137;0
"Building";"Factory";NA;137;0
"Unit";"SCV";"Command Center";145;1
"Building";"MissileTurret";NA;145;0
"Building";"MissileTurret";NA;149;0
"Building";"MissileTurret";NA;149;0
"Building";"MissileTurret";NA;149;0
"Building";"FactoryTechLab";NA;150;0
"Unit";"Hellion";"Factory";149;2
"Building";"FactoryTechLab";NA;150;0
"Unit";"Hellion";"Factory";150;2
"Unit";"Hellion";"Factory";150;2
"Unit";"Hellion";"Factory";150;2
"Building";"FactoryReactor";NA;150;0
"Building";"MissileTurret";NA;152;0
