"type";"unit_name";"on_building";"total_supply";"supply"
"Building";"Refinery";NA;15;0
"Building";"Barracks";NA;15;0
"Unit";"Reaper";"Barracks";19;1
"Unit";"Marine";"Barracks";19;1
"Building";"Refinery";NA;21;0
"Building";"CommandCenter";NA;19;0
"Building";"Factory";NA;21;0
"Building";"BarracksReactor";NA;23;0
"Building";"BarracksTechLab";NA;26;0
"Unit";"Hellion";"Factory";26;2
"Unit";"Hellion";"Factory";26;2
"Building";"Starport";NA;26;0
"Building";"BarracksTechLab";NA;33;0
"Unit";"Hellion";"Factory";33;2
"Unit";"Hellion";"Factory";33;2
"Unit";"Hellion";"Factory";40;2
"Unit";"Hellion";"Factory";40;2
"Unit";"Banshee";"Starport";34;3
"Unit";"Marine";"Barracks";48;1
"Unit";"Marine";"Barracks";48;1
"Unit";"Banshee";"Starport";51;3
"Unit";"Marine";"Barracks";57;1
"Unit";"Marine";"Barracks";57;1
"Building";"CommandCenter";NA;44;0
"Unit";"Marine";"Barracks";64;1
"Unit";"Marine";"Barracks";64;1
"Unit";"Marine";"Barracks";70;1
"Unit";"Marine";"Barracks";70;1
"Building";"StarportReactor";NA;66;0
"Building";"Barracks";NA;64;0
"Building";"Refinery";NA;73;0
"Building";"Barracks";NA;66;0
"Building";"Refinery";NA;73;0
"Unit";"Marine";"Barracks";76;1
"Unit";"Marine";"Barracks";76;1
"Building";"EngineeringBay";NA;73;0
"Building";"EngineeringBay";NA;73;0
"Unit";"Marine";"Barracks";81;1
"Unit";"Marine";"Barracks";81;1
"Unit";"Marine";"Barracks";83;1
"Unit";"Marine";"Barracks";83;1
"Unit";"Marine";"Barracks";83;1
"Unit";"Marine";"Barracks";87;1
"Unit";"Marine";"Barracks";87;1
"Building";"StarportReactor";NA;82;0
"Unit";"Marine";"Barracks";88;1
"Unit";"Marine";"Barracks";91;1
"Unit";"Marine";"Barracks";91;1
"Building";"Barracks";NA;83;0
"Building";"Barracks";NA;83;0
"Unit";"Marine";"Barracks";102;1
"Unit";"Marine";"Barracks";102;1
"Unit";"Marine";"Barracks";102;1
"Unit";"Marine";"Barracks";102;1
"Unit";"Marine";"Barracks";102;1
"Unit";"Medivac";"Starport";102;2
"Unit";"Medivac";"Starport";102;2
"Building";"Refinery";NA;102;0
"Building";"Refinery";NA;102;0
"Unit";"Marine";"Barracks";105;1
"Building";"BarracksReactor";NA;102;0
"Building";"BarracksReactor";NA;102;0
"Unit";"Marine";"Barracks";106;1
"Unit";"Marine";"Barracks";117;1
"Unit";"Marine";"Barracks";117;1
"Unit";"Marine";"Barracks";117;1
"Unit";"Marine";"Barracks";117;1
"Upgrade";"TerranInfantryWeaponsLevel1";"EngineeringBay";93;0
"Upgrade";"TerranInfantryArmorsLevel1";"EngineeringBay";93;0
"Unit";"Medivac";"Starport";117;2
"Upgrade";"Stimpack";"TechLab";92;0
"Building";"Armory";NA;106;0
"Unit";"Marine";"Barracks";125;1
"Unit";"Marine";"Barracks";125;1
"Unit";"Marine";"Barracks";125;1
"Unit";"Marine";"Barracks";125;1
"Unit";"Marine";"Barracks";125;1
"Unit";"Marine";"Barracks";125;1
"Unit";"Marine";"Barracks";125;1
"Unit";"Marine";"Barracks";125;1
"Building";"Factory";NA;113;0
"Building";"Barracks";NA;113;0
"Building";"Barracks";NA;113;0
"Building";"CommandCenter";NA;102;0
"Unit";"Marine";"Barracks";128;1
"Unit";"Medivac";"Starport";126;2
"Unit";"Marine";"Barracks";128;1
"Unit";"Marine";"Barracks";129;1
"Unit";"Marine";"Barracks";130;1
"Unit";"Medivac";"Starport";126;2
"Building";"BarracksTechLab";NA;136;0
"Building";"BarracksTechLab";NA;136;0
"Unit";"Marine";"Barracks";136;1
"Unit";"Marine";"Barracks";136;1
"Unit";"Marine";"Barracks";136;1
"Unit";"Marine";"Barracks";136;1
"Unit";"Marine";"Barracks";136;1
"Unit";"Marine";"Barracks";139;1
"Building";"FactoryTechLab";NA;139;0
"Unit";"Marine";"Barracks";139;1
"Unit";"Marine";"Barracks";140;1
"Unit";"Marine";"Barracks";151;1
"Unit";"Marine";"Barracks";152;1
"Unit";"Marine";"Barracks";152;1
"Unit";"Marine";"Barracks";152;1
"Unit";"Marine";"Barracks";152;1
"Unit";"Marine";"Barracks";152;1
"Unit";"Marauder";"Barracks";149;2
"Unit";"Marine";"Barracks";152;1
"Unit";"Marine";"Barracks";152;1
"Unit";"Marauder";"Barracks";152;2
"Unit";"Marauder";"Barracks";152;2
"Unit";"Marine";"Barracks";152;1
"Unit";"Marine";"Barracks";162;1
"Unit";"Marauder";"Barracks";158;2
"Building";"Refinery";NA;166;0
"Unit";"Marine";"Barracks";168;1
"Building";"Refinery";NA;168;0
"Unit";"Marauder";"Barracks";168;2
"Unit";"Marine";"Barracks";172;1
"Unit";"Marine";"Barracks";172;1
"Unit";"Marine";"Barracks";172;1
"Unit";"Marine";"Barracks";172;1
"Unit";"Marine";"Barracks";172;1
"Unit";"Marine";"Barracks";172;1
"Unit";"Marine";"Barracks";172;1
"Unit";"Marine";"Barracks";172;1
"Unit";"Marauder";"Barracks";172;2
"Unit";"Marauder";"Barracks";173;2
"Unit";"Medivac";"Starport";172;2
"Unit";"Marine";"Barracks";185;1
"Unit";"Marine";"Barracks";185;1
"Unit";"Marine";"Barracks";187;1
"Unit";"Marine";"Barracks";187;1
"Unit";"Marine";"Barracks";187;1
"Unit";"Marine";"Barracks";187;1
"Unit";"Marine";"Barracks";187;1
"Unit";"Marine";"Barracks";187;1
"Unit";"Marauder";"Barracks";185;2
"Unit";"Marauder";"Barracks";185;2
"Unit";"Marauder";"Barracks";185;2
"Unit";"Marine";"Barracks";189;1
"Unit";"Marine";"Barracks";190;1
"Unit";"Marine";"Barracks";191;1
"Unit";"Marine";"Barracks";192;1
"Unit";"Marine";"Barracks";193;1
"Upgrade";"TerranInfantryWeaponsLevel2";"EngineeringBay";152;0
"Unit";"Marine";"Barracks";194;1
"Upgrade";"TerranInfantryArmorsLevel2";"EngineeringBay";152;0
"Unit";"Marine";"Barracks";195;1
