"Type";"UnitName";"OnBuilding";"TotalSupply";"Supply"
"Unit";"SCV";"Command Center";12;1
"Unit";"SCV";"Command Center";12;1
"Unit";"SCV";"Command Center";13;1
"Building";"SupplyDepot";NA;13;0
"Unit";"SCV";"Command Center";15;1
"Unit";"SCV";"Command Center";15;1
"Building";"Refinery";NA;15;0
"Unit";"SCV";"Command Center";16;1
"Building";"Barracks";NA;15;0
"Unit";"SCV";"Command Center";18;1
"Unit";"Reaper";"Barracks";19;1
"Unit";"SCV";"Command Center";19;1
"Building";"SupplyDepot";NA;19;0
"Unit";"Marine";"Barracks";19;1
"Unit";"SCV";"Command Center";21;1
"Unit";"SCV";"Command Center";22;1
"Building";"Refinery";NA;21;0
"Unit";"SCV";"Command Center";23;1
"Building";"CommandCenter";NA;19;0
"Building";"Factory";NA;21;0
"Unit";"SCV";"Command Center";24;1
"Building";"BarracksReactor";NA;23;0
"Unit";"SCV";"Command Center";25;1
"Building";"SupplyDepot";NA;25;0
"Unit";"SCV";"Command Center";26;1
"Building";"BarracksTechLab";NA;26;0
"Unit";"Hellion";"Factory";26;2
"Unit";"Hellion";"Factory";26;2
"Unit";"SCV";"Command Center";27;1
"Building";"Starport";NA;26;0
"Unit";"SCV";"Command Center";28;1
"Building";"SupplyDepot";NA;27;0
"Unit";"SCV";"Command Center";34;1
"Unit";"SCV";"Command Center";34;1
"Building";"BarracksTechLab";NA;33;0
"Unit";"Hellion";"Factory";33;2
"Unit";"Hellion";"Factory";33;2
"Unit";"SCV";"Command Center";36;1
"Unit";"SCV";"Command Center";36;1
"Building";"SupplyDepot";NA;34;0
"Unit";"SCV";"Command Center";41;1
"Unit";"SCV";"Command Center";41;1
"Unit";"Hellion";"Factory";40;2
"Unit";"Hellion";"Factory";40;2
"Unit";"Banshee";"Starport";34;3
"Unit";"SCV";"Command Center";46;1
"Unit";"SCV";"Command Center";46;1
"Unit";"Marine";"Barracks";48;1
"Unit";"Marine";"Barracks";48;1
"Unit";"SCV";"Command Center";53;1
"Unit";"SCV";"Command Center";53;1
"Building";"SupplyDepot";NA;53;0
"Unit";"SCV";"Command Center";57;1
"Unit";"SCV";"Command Center";57;1
"Unit";"Banshee";"Starport";51;3
"Unit";"Marine";"Barracks";57;1
"Unit";"Marine";"Barracks";57;1
"Unit";"SCV";"Command Center";57;1
"Unit";"SCV";"Command Center";58;1
"Building";"CommandCenter";NA;44;0
"Unit";"Marine";"Barracks";64;1
"Unit";"Marine";"Barracks";64;1
"Unit";"SCV";"Command Center";64;1
"Unit";"SCV";"Command Center";65;1
"Unit";"SCV";"Command Center";66;1
"Unit";"SCV";"Command Center";68;1
"Unit";"SCV";"Command Center";69;1
"Unit";"Marine";"Barracks";70;1
"Unit";"Marine";"Barracks";70;1
"Unit";"SCV";"Command Center";70;1
"Unit";"SCV";"Command Center";71;1
"Unit";"SCV";"Command Center";72;1
"Unit";"SCV";"Command Center";75;1
"Building";"StarportReactor";NA;66;0
"Building";"Barracks";NA;64;0
"Building";"Refinery";NA;73;0
"Building";"Barracks";NA;66;0
"Building";"Refinery";NA;73;0
"Building";"SupplyDepot";NA;73;0
"Unit";"Marine";"Barracks";76;1
"Unit";"Marine";"Barracks";76;1
"Building";"EngineeringBay";NA;73;0
"Building";"EngineeringBay";NA;73;0
"Unit";"SCV";"Command Center";79;1
"Unit";"SCV";"Command Center";81;1
"Unit";"SCV";"Command Center";81;1
"Unit";"Marine";"Barracks";81;1
"Unit";"Marine";"Barracks";81;1
"Unit";"SCV";"Command Center";82;1
"Unit";"SCV";"Command Center";83;1
"Unit";"Marine";"Barracks";83;1
"Unit";"Marine";"Barracks";83;1
"Unit";"Marine";"Barracks";83;1
"Unit";"SCV";"Command Center";86;1
"Unit";"SCV";"Command Center";87;1
"Unit";"SCV";"Command Center";87;1
"Unit";"Marine";"Barracks";87;1
"Unit";"Marine";"Barracks";87;1
"Building";"StarportReactor";NA;82;0
"Unit";"SCV";"Command Center";91;1
"Unit";"Marine";"Barracks";88;1
"Unit";"SCV";"Command Center";92;1
"Unit";"Marine";"Barracks";91;1
"Unit";"Marine";"Barracks";91;1
"Unit";"SCV";"Command Center";93;1
"Building";"Barracks";NA;83;0
"Building";"Barracks";NA;83;0
"Building";"SupplyDepot";NA;94;0
"Building";"SupplyDepot";NA;94;0
"Unit";"SCV";"Command Center";102;1
"Unit";"SCV";"Command Center";102;1
"Unit";"SCV";"Command Center";102;1
"Building";"SupplyDepot";NA;100;0
"Building";"SupplyDepot";NA;101;0
"Unit";"Marine";"Barracks";102;1
"Unit";"Marine";"Barracks";102;1
"Unit";"Marine";"Barracks";102;1
"Unit";"Marine";"Barracks";102;1
"Unit";"Marine";"Barracks";102;1
"Unit";"SCV";"Command Center";102;1
"Unit";"SCV";"Command Center";102;1
"Unit";"SCV";"Command Center";104;1
"Unit";"Medivac";"Starport";102;2
"Unit";"Medivac";"Starport";102;2
"Building";"Refinery";NA;102;0
"Building";"Refinery";NA;102;0
"Unit";"Marine";"Barracks";105;1
"Unit";"SCV";"Command Center";110;1
"Unit";"SCV";"Command Center";110;1
"Building";"BarracksReactor";NA;102;0
"Building";"BarracksReactor";NA;102;0
"Unit";"SCV";"Command Center";113;1
"Unit";"Marine";"Barracks";106;1
"Building";"SupplyDepot";NA;106;0
"Unit";"Marine";"Barracks";117;1
"Unit";"Marine";"Barracks";117;1
"Unit";"Marine";"Barracks";117;1
"Unit";"Marine";"Barracks";117;1
"Upgrade";"TerranInfantryWeaponsLevel1";"EngineeringBay";93;0
"Upgrade";"TerranInfantryArmorsLevel1";"EngineeringBay";93;0
"Unit";"Medivac";"Starport";117;2
"Upgrade";"Stimpack";"TechLab";92;0
"Building";"Armory";NA;106;0
"Unit";"Marine";"Barracks";125;1
"Unit";"Marine";"Barracks";125;1
"Unit";"Marine";"Barracks";125;1
"Unit";"Marine";"Barracks";125;1
"Unit";"Marine";"Barracks";125;1
"Unit";"Marine";"Barracks";125;1
"Unit";"Marine";"Barracks";125;1
"Unit";"Marine";"Barracks";125;1
"Building";"Factory";NA;113;0
"Building";"Barracks";NA;113;0
"Building";"Barracks";NA;113;0
"Building";"CommandCenter";NA;102;0
"Unit";"Marine";"Barracks";128;1
"Unit";"Medivac";"Starport";126;2
"Unit";"Marine";"Barracks";128;1
"Unit";"Marine";"Barracks";129;1
"Unit";"Marine";"Barracks";130;1
"Unit";"Medivac";"Starport";126;2
"Building";"BarracksTechLab";NA;136;0
"Building";"BarracksTechLab";NA;136;0
"Unit";"Marine";"Barracks";136;1
"Unit";"Marine";"Barracks";136;1
"Unit";"Marine";"Barracks";136;1
"Unit";"Marine";"Barracks";136;1
"Unit";"Marine";"Barracks";136;1
"Unit";"Marine";"Barracks";139;1
"Building";"FactoryTechLab";NA;139;0
"Unit";"Marine";"Barracks";139;1
"Unit";"Marine";"Barracks";140;1
"Unit";"Marine";"Barracks";151;1
"Unit";"Marine";"Barracks";152;1
"Unit";"Marine";"Barracks";152;1
"Unit";"Marine";"Barracks";152;1
"Unit";"Marine";"Barracks";152;1
"Unit";"Marine";"Barracks";152;1
"Unit";"Marauder";"Barracks";149;2
"Unit";"Marine";"Barracks";152;1
"Unit";"Marine";"Barracks";152;1
"Unit";"SCV";"Command Center";152;1
"Unit";"SCV";"Command Center";152;1
"Unit";"Marauder";"Barracks";152;2
"Unit";"Marauder";"Barracks";152;2
"Building";"SupplyDepot";NA;152;0
"Building";"SupplyDepot";NA;152;0
"Building";"SupplyDepot";NA;152;0
"Unit";"Marine";"Barracks";152;1
"Unit";"Marine";"Barracks";162;1
"Unit";"Marauder";"Barracks";158;2
"Building";"Refinery";NA;166;0
"Unit";"Marine";"Barracks";168;1
"Building";"Refinery";NA;168;0
"Building";"SupplyDepot";NA;168;0
"Unit";"Marauder";"Barracks";168;2
"Unit";"Marine";"Barracks";172;1
"Unit";"Marine";"Barracks";172;1
"Unit";"Marine";"Barracks";172;1
"Unit";"Marine";"Barracks";172;1
"Unit";"Marine";"Barracks";172;1
"Unit";"Marine";"Barracks";172;1
"Unit";"Marine";"Barracks";172;1
"Unit";"Marine";"Barracks";172;1
"Unit";"Marauder";"Barracks";172;2
"Unit";"Marauder";"Barracks";173;2
"Unit";"Medivac";"Starport";172;2
"Unit";"Marine";"Barracks";185;1
"Unit";"Marine";"Barracks";185;1
"Unit";"Marine";"Barracks";187;1
"Unit";"Marine";"Barracks";187;1
"Unit";"Marine";"Barracks";187;1
"Unit";"Marine";"Barracks";187;1
"Unit";"Marine";"Barracks";187;1
"Unit";"Marine";"Barracks";187;1
"Unit";"Marauder";"Barracks";185;2
"Unit";"Marauder";"Barracks";185;2
"Unit";"Marauder";"Barracks";185;2
"Unit";"Marine";"Barracks";189;1
"Unit";"Marine";"Barracks";190;1
"Unit";"Marine";"Barracks";191;1
"Unit";"Marine";"Barracks";192;1
"Unit";"Marine";"Barracks";193;1
"Upgrade";"TerranInfantryWeaponsLevel2";"EngineeringBay";152;0
"Unit";"Marine";"Barracks";194;1
"Upgrade";"TerranInfantryArmorsLevel2";"EngineeringBay";152;0
"Unit";"Marine";"Barracks";195;1
