"Type";"UnitName";"OnBuilding";"TotalSupply";"Supply"
"Unit";"SCV";"Command Center";12;1
"Unit";"SCV";"Command Center";12;1
"Unit";"SCV";"Command Center";13;1
"Building";"SupplyDepot";NA;13;0
"Unit";"SCV";"Command Center";15;1
"Unit";"SCV";"Command Center";16;1
"Building";"Refinery";NA;15;0
"Unit";"SCV";"Command Center";16;1
"Unit";"SCV";"Command Center";17;1
"Building";"Barracks";NA;15;0
"Unit";"Reaper";"Barracks";19;1
"Unit";"SCV";"Command Center";19;1
"Building";"SupplyDepot";NA;19;0
"Unit";"Marine";"Barracks";19;1
"Unit";"SCV";"Command Center";21;1
"Unit";"SCV";"Command Center";23;1
"Building";"Refinery";NA;21;0
"Unit";"SCV";"Command Center";24;1
"Building";"CommandCenter";NA;19;0
"Building";"Factory";NA;21;0
"Building";"BarracksReactor";NA;23;0
"Unit";"SCV";"Command Center";24;1
"Unit";"SCV";"Command Center";26;1
"Building";"BarracksTechLab";NA;26;0
"Unit";"SCV";"Command Center";26;1
"Unit";"Hellion";"Factory";26;2
"Unit";"Hellion";"Factory";26;2
"Building";"Starport";NA;26;0
"Unit";"SCV";"Command Center";27;1
"Unit";"SCV";"Command Center";28;1
"Unit";"SCV";"Command Center";32;1
"Building";"BarracksTechLab";NA;28;0
"Unit";"SCV";"Command Center";34;1
"Building";"SupplyDepot";NA;32;0
"Unit";"Hellion";"Factory";34;2
"Unit";"Hellion";"Factory";34;2
"Unit";"SCV";"Command Center";34;1
"Unit";"SCV";"Command Center";35;1
"Building";"SupplyDepot";NA;36;0
"Unit";"SCV";"Command Center";42;1
"Unit";"SCV";"Command Center";42;1
"Unit";"Hellion";"Factory";36;2
"Unit";"Hellion";"Factory";40;2
"Unit";"SCV";"Command Center";42;1
"Unit";"Banshee";"Starport";34;3
"Unit";"SCV";"Command Center";43;1
"Building";"SupplyDepot";NA;44;0
"Unit";"SCV";"Command Center";53;1
"Unit";"SCV";"Command Center";53;1
"Unit";"Marine";"Barracks";48;1
"Unit";"Marine";"Barracks";48;1
"Unit";"SCV";"Command Center";53;1
"Building";"SupplyDepot";NA;53;0
"Unit";"SCV";"Command Center";58;1
"Unit";"SCV";"Command Center";58;1
"Unit";"Banshee";"Starport";49;3
"Unit";"Marine";"Barracks";58;1
"Unit";"Marine";"Barracks";58;1
"Unit";"SCV";"Command Center";58;1
"Building";"SupplyDepot";NA;58;0
"Unit";"SCV";"Command Center";65;1
"Unit";"Marine";"Barracks";66;1
"Unit";"Marine";"Barracks";66;1
"Unit";"SCV";"Command Center";67;1
"Unit";"SCV";"Command Center";67;1
"Building";"CommandCenter";NA;53;0
"Unit";"SCV";"Command Center";69;1
"Unit";"Marine";"Barracks";69;1
"Unit";"Marine";"Barracks";69;1
"Building";"StarportReactor";NA;66;0
"Building";"Refinery";NA;69;0
"Building";"Refinery";NA;69;0
"Building";"EngineeringBay";NA;69;0
"Building";"EngineeringBay";NA;70;0
"Building";"Barracks";NA;66;0
"Building";"Barracks";NA;66;0
"Unit";"Marine";"Barracks";74;1
"Unit";"Marine";"Barracks";74;1
"Unit";"SCV";"Command Center";74;1
"Unit";"SCV";"Command Center";74;1
"Building";"Barracks";NA;69;0
"Building";"Barracks";NA;69;0
"Unit";"SCV";"Command Center";76;1
"Unit";"SCV";"Command Center";76;1
"Unit";"Marine";"Barracks";76;1
"Unit";"Marine";"Barracks";76;1
"Unit";"Marine";"Barracks";76;1
"Unit";"Marine";"Barracks";76;1
"Unit";"Marine";"Barracks";76;1
"Unit";"SCV";"Command Center";77;1
"Building";"BarracksTechLab";NA;78;0
"Unit";"SCV";"Command Center";80;1
"Unit";"SCV";"Command Center";80;1
"Unit";"Marine";"Barracks";80;1
"Unit";"SCV";"Command Center";86;1
"Building";"StarportReactor";NA;76;0
"Unit";"Marine";"Barracks";86;1
"Unit";"Marine";"Barracks";86;1
"Unit";"Marine";"Barracks";86;1
"Unit";"Marine";"Barracks";86;1
"Building";"BarracksReactor";NA;78;0
"Unit";"Marine";"Barracks";88;1
"Unit";"SCV";"Command Center";89;1
"Unit";"SCV";"Command Center";89;1
"Building";"SupplyDepot";NA;88;0
"Building";"SupplyDepot";NA;88;0
"Unit";"Marine";"Barracks";94;1
"Unit";"Marine";"Barracks";94;1
"Unit";"Marine";"Barracks";94;1
"Unit";"Marine";"Barracks";94;1
"Unit";"Marine";"Barracks";94;1
"Building";"Refinery";NA;94;0
"Building";"Refinery";NA;94;0
"Unit";"Marine";"Barracks";94;1
"Unit";"Marine";"Barracks";97;1
"Unit";"Marine";"Barracks";97;1
"Unit";"Medivac";"Starport";94;2
"Building";"SupplyDepot";NA;97;0
"Building";"Armory";NA;88;0
"Unit";"Marine";"Barracks";102;1
"Unit";"Marine";"Barracks";102;1
"Unit";"Marine";"Barracks";102;1
"Unit";"Marine";"Barracks";102;1
"Unit";"SCV";"Command Center";103;1
"Unit";"Medivac";"Starport";97;2
"Unit";"Marine";"Barracks";103;1
"Unit";"Marine";"Barracks";103;1
"Unit";"SCV";"Command Center";112;1
"Unit";"SCV";"Command Center";114;1
"Unit";"Marine";"Barracks";107;1
"Unit";"Marine";"Barracks";107;1
"Building";"SupplyDepot";NA;114;0
"Building";"SupplyDepot";NA;114;0
"Unit";"Marine";"Barracks";116;1
"Unit";"Marine";"Barracks";116;1
"Unit";"Marine";"Barracks";116;1
"Unit";"Marine";"Barracks";116;1
"Unit";"Marine";"Barracks";116;1
"Upgrade";"TerranInfantryWeaponsLevel1";"EngineeringBay";86;0
"Upgrade";"TerranInfantryArmorsLevel1";"EngineeringBay";86;0
"Unit";"Marine";"Barracks";116;1
"Unit";"Marine";"Barracks";120;1
"Unit";"Marine";"Barracks";120;1
"Unit";"Medivac";"Starport";117;2
"Unit";"Marine";"Barracks";120;1
"Unit";"Marine";"Barracks";121;1
"Unit";"Marine";"Barracks";122;1
"Building";"Factory";NA;116;0
"Building";"Barracks";NA;114;0
"Unit";"Medivac";"Starport";120;2
"Building";"Barracks";NA;116;0
"Building";"SupplyDepot";NA;126;0
"Unit";"SCV";"Command Center";133;1
"Unit";"SCV";"Command Center";133;1
"Upgrade";"Stimpack";"TechLab";97;0
"Unit";"Marine";"Barracks";133;1
"Unit";"Marine";"Barracks";133;1
"Unit";"Marine";"Barracks";133;1
"Unit";"Marine";"Barracks";133;1
"Building";"CommandCenter";NA;107;0
"Unit";"SCV";"Command Center";135;1
"Unit";"Marauder";"Barracks";133;2
"Unit";"Marauder";"Barracks";133;2
"Building";"SupplyDepot";NA;133;0
"Building";"SupplyDepot";NA;133;0
"Unit";"Marauder";"Barracks";142;2
"Unit";"Marine";"Barracks";146;1
"Unit";"Marine";"Barracks";146;1
"Unit";"Marine";"Barracks";146;1
"Unit";"Marine";"Barracks";146;1
"Building";"BarracksTechLab";NA;146;0
"Building";"FactoryTechLab";NA;146;0
"Unit";"Marine";"Barracks";146;1
"Unit";"Marine";"Barracks";146;1
"Unit";"Marine";"Barracks";146;1
"Unit";"Marine";"Barracks";148;1
"Unit";"SCV";"Command Center";152;1
"Building";"BarracksReactor";NA;146;0
"Unit";"SCV";"Command Center";152;1
"Unit";"SCV";"Command Center";152;1
"Unit";"Marauder";"Barracks";146;2
"Unit";"Medivac";"Starport";146;2
"Unit";"Medivac";"Starport";146;2
"Unit";"Marine";"Barracks";155;1
"Unit";"Marine";"Barracks";155;1
"Unit";"Marine";"Barracks";155;1
"Unit";"Marine";"Barracks";155;1
"Unit";"Marine";"Barracks";155;1
"Unit";"Marauder";"Barracks";155;2
"Unit";"Marauder";"Barracks";155;2
"Unit";"Marine";"Barracks";155;1
"Unit";"Marine";"Barracks";159;1
"Unit";"Marine";"Barracks";161;1
"Unit";"Marine";"Barracks";165;1
"Unit";"SCV";"Command Center";170;1
"Unit";"SCV";"Command Center";170;1
"Unit";"SCV";"Command Center";170;1
"Upgrade";"TerranVehicleAndShipArmorsLevel1";"Armory";133;0
"Unit";"Marine";"Barracks";165;1
"Unit";"Medivac";"Starport";165;2
"Building";"SupplyDepot";NA;176;0
"Building";"SupplyDepot";NA;176;0
"Building";"Starport";NA;165;0
"Building";"Starport";NA;165;0
"Building";"Refinery";NA;176;0
"Building";"SupplyDepot";NA;176;0
"Building";"Refinery";NA;176;0
"Building";"FusionCore";NA;161;0
"Unit";"Marine";"Barracks";182;1
"Unit";"Marauder";"Barracks";182;2
"Unit";"Marauder";"Barracks";182;2
"Upgrade";"TerranInfantryWeaponsLevel2";"EngineeringBay";146;0
"Unit";"Marine";"Barracks";184;1
"Unit";"Marine";"Barracks";184;1
"Unit";"Marine";"Barracks";184;1
"Unit";"Marine";"Barracks";184;1
"Unit";"Marine";"Barracks";184;1
"Unit";"Marine";"Barracks";184;1
"Unit";"Marine";"Barracks";184;1
"Building";"StarportTechLab";NA;184;0
"Unit";"Marauder";"Barracks";184;2
"Upgrade";"TerranInfantryArmorsLevel2";"EngineeringBay";146;0
"Unit";"Marine";"Barracks";187;1
"Unit";"SCV";"Command Center";196;1
"Unit";"Marauder";"Barracks";185;2
"Unit";"Marauder";"Barracks";187;2
"Unit";"Marine";"Barracks";189;1
"Unit";"Marine";"Barracks";196;1
"Unit";"Marine";"Barracks";196;1
"Unit";"Marine";"Barracks";196;1
"Unit";"Marine";"Barracks";196;1
"Building";"StarportReactor";NA;184;0
"Unit";"Marine";"Barracks";198;1
"Unit";"Marine";"Barracks";198;1
"Unit";"Marauder";"Barracks";196;2
"Unit";"Medivac";"Starport";189;2
"Unit";"Medivac";"Starport";189;2
"Unit";"Marine";"Barracks";199;1
"Unit";"Marine";"Barracks";204;1
"Unit";"Marauder";"Barracks";200;2
"Unit";"Marauder";"Barracks";202;2
"Unit";"Marine";"Barracks";205;1
"Unit";"Marine";"Barracks";211;1
"Unit";"Marine";"Barracks";211;1
"Unit";"Marine";"Barracks";211;1
"Unit";"Marine";"Barracks";211;1
"Unit";"Marine";"Barracks";211;1
"Unit";"Marine";"Barracks";211;1
"Unit";"Marine";"Barracks";217;1
"Unit";"Marine";"Barracks";218;1
"Unit";"Marine";"Barracks";219;1
"Unit";"Marine";"Barracks";224;1
"Unit";"Marine";"Barracks";224;1
"Unit";"Liberator";"Starport";199;3
"Unit";"Marine";"Barracks";224;1
"Unit";"Marauder";"Barracks";229;2
"Unit";"Marine";"Barracks";231;1
"Unit";"Marine";"Barracks";231;1
"Unit";"Marine";"Barracks";232;1
"Unit";"Marine";"Barracks";232;1
"Unit";"Marine";"Barracks";232;1
"Unit";"Marine";"Barracks";244;1
"Unit";"Marine";"Barracks";245;1
"Unit";"Marine";"Barracks";246;1
"Unit";"Marine";"Barracks";246;1
"Unit";"Marine";"Barracks";246;1
"Unit";"Marauder";"Barracks";245;2
"Unit";"Marauder";"Barracks";246;2
"Unit";"Marauder";"Barracks";246;2
"Unit";"Marine";"Barracks";246;1
"Unit";"Marine";"Barracks";246;1
"Unit";"Marine";"Barracks";246;1
"Unit";"Marine";"Barracks";246;1
"Unit";"Marine";"Barracks";247;1
"Unit";"Marine";"Barracks";248;1
