"type";"unit_name";"on_building";"total_supply";"supply"
"Building";"Refinery";NA;14;0
"Building";"Barracks";NA;14;0
"Building";"Barracks";NA;14;0
"Building";"Barracks";NA;16;0
"Building";"Factory";NA;16;0
"Unit";"Marine";"Barracks";17;1
"Building";"Bunker";NA;17;0
"Unit";"Marine";"Barracks";17;1
"Unit";"Marine";"Barracks";18;1
"Unit";"Marine";"Barracks";18;1
"Building";"FactoryReactor";NA;17;0
"Unit";"Marine";"Barracks";19;1
"Building";"Bunker";NA;19;0
"Unit";"Marine";"Barracks";22;1
"Unit";"Marine";"Barracks";22;1
"Building";"Armory";NA;19;0
"Unit";"Hellion";"Factory";25;2
"Unit";"Hellion";"Factory";25;2
"Building";"BarracksReactor";NA;25;0
"Unit";"Hellion";"Factory";26;2
"Unit";"Hellion";"Factory";28;2
"Unit";"Marine";"Barracks";30;1
"Unit";"Marine";"Barracks";30;1
"Unit";"Marine";"Barracks";32;1
"Building";"BarracksReactor";NA;30;0
"Unit";"Hellion";"Factory";30;2
"Unit";"Hellion";"Factory";32;2
"Unit";"Marine";"Barracks";34;1
"Unit";"Marine";"Barracks";35;1
"Unit";"Marine";"Barracks";36;1
"Unit";"Hellion";"Factory";37;2
"Unit";"Hellion";"Factory";39;2
"Unit";"Marine";"Barracks";41;1
"Unit";"Marine";"Barracks";41;1
"Unit";"Marine";"Barracks";41;1
"Unit";"Marine";"Barracks";42;1
"Building";"FactoryTechLab";NA;48;0
"Unit";"Marine";"Barracks";52;1
"Building";"Refinery";NA;48;0
"Unit";"Marine";"Barracks";52;1
"Unit";"Marine";"Barracks";52;1
"Unit";"Marine";"Barracks";55;1
"Unit";"Marine";"Barracks";55;1
"Unit";"Marine";"Barracks";55;1
"Unit";"Marine";"Barracks";55;1
"Unit";"Marine";"Barracks";55;1
"Unit";"Marine";"Barracks";55;1
"Unit";"Marine";"Barracks";55;1
"Unit";"Marine";"Barracks";62;1
"Unit";"Marine";"Barracks";62;1
"Unit";"Marine";"Barracks";64;1
"Unit";"Marine";"Barracks";64;1
"Unit";"Marine";"Barracks";64;1
"Unit";"Marine";"Barracks";67;1
"Unit";"Marine";"Barracks";67;1
"Unit";"Marine";"Barracks";67;1
"Unit";"Marine";"Barracks";67;1
"Unit";"Marine";"Barracks";67;1
"Unit";"Marine";"Barracks";67;1
"Unit";"Marine";"Barracks";67;1
"Unit";"Marine";"Barracks";68;1
"Unit";"Marine";"Barracks";71;1
"Unit";"Marine";"Barracks";71;1
"Unit";"Marine";"Barracks";71;1
"Unit";"Marine";"Barracks";73;1
"Unit";"Marine";"Barracks";73;1
"Unit";"Marine";"Barracks";75;1
"Unit";"Marine";"Barracks";75;1
"Unit";"Marine";"Barracks";80;1
"Unit";"Marine";"Barracks";82;1
"Unit";"Marine";"Barracks";82;1
"Unit";"Marine";"Barracks";82;1
"Unit";"Marine";"Barracks";86;1
"Unit";"Marine";"Barracks";86;1
"Unit";"Marine";"Barracks";86;1
"Unit";"Marine";"Barracks";86;1
"Unit";"Marine";"Barracks";86;1
"Unit";"Marine";"Barracks";86;1
"Unit";"Marine";"Barracks";86;1
"Unit";"Marine";"Barracks";91;1
"Unit";"Marine";"Barracks";91;1
"Unit";"Marine";"Barracks";91;1
"Unit";"Marine";"Barracks";91;1
"Unit";"Marine";"Barracks";93;1
"Unit";"Marine";"Barracks";93;1
"Unit";"Marine";"Barracks";93;1
"Unit";"Marine";"Barracks";94;1
"Unit";"Marine";"Barracks";95;1
"Unit";"Marine";"Barracks";97;1
"Unit";"Marine";"Barracks";102;1
"Unit";"Marine";"Barracks";102;1
"Unit";"Marine";"Barracks";102;1
"Unit";"Marine";"Barracks";103;1
"Unit";"Marine";"Barracks";103;1
"Unit";"Marine";"Barracks";103;1
"Unit";"Marine";"Barracks";104;1
"Unit";"Marine";"Barracks";105;1
"Unit";"Hellion";"Factory";102;2
"Unit";"Hellion";"Factory";102;2
"Unit";"Marine";"Barracks";107;1
"Unit";"Marine";"Barracks";108;1
"Unit";"Marine";"Barracks";109;1
"Unit";"Hellion";"Factory";112;2
"Unit";"Hellion";"Factory";114;2
"Unit";"Marine";"Barracks";123;1
"Unit";"Marine";"Barracks";123;1
"Unit";"Marine";"Barracks";123;1
"Unit";"Hellion";"Factory";119;2
"Unit";"Hellion";"Factory";121;2
"Unit";"Marine";"Barracks";130;1
"Unit";"Marine";"Barracks";130;1
"Unit";"Marauder";"Barracks";130;2
"Unit";"Marine";"Barracks";130;1
"Unit";"Marine";"Barracks";130;1
"Unit";"Marine";"Barracks";130;1
"Unit";"Hellion";"Factory";136;2
"Unit";"Hellion";"Factory";136;2
"Unit";"Marine";"Barracks";137;1
"Unit";"Marine";"Barracks";137;1
"Unit";"Hellion";"Factory";137;2
"Building";"Refinery";NA;145;0
"Building";"EngineeringBay";NA;145;0
"Building";"MissileTurret";NA;146;0
"Building";"MissileTurret";NA;146;0
"Building";"MissileTurret";NA;146;0
"Unit";"Marine";"Barracks";146;1
"Unit";"Marine";"Barracks";146;1
"Unit";"Marine";"Barracks";146;1
"Unit";"Marine";"Barracks";146;1
"Building";"CommandCenter";NA;146;0
"Unit";"Marine";"Barracks";151;1
"Unit";"Marine";"Barracks";151;1
"Unit";"Marine";"Barracks";151;1
"Unit";"Marine";"Barracks";151;1
"Unit";"Marine";"Barracks";151;1
"Unit";"Marine";"Barracks";151;1
"Building";"CommandCenter";NA;151;0
"Building";"CommandCenter";NA;157;0
"Building";"CommandCenter";NA;157;0
"Building";"CommandCenter";NA;166;0
