"type";"unit_name";"on_building";"total_supply";"supply"
"Building";"Refinery";NA;15;0
"Building";"Refinery";NA;15;0
"Building";"Barracks";NA;17;0
"Building";"BarracksReactor";NA;21;0
"Building";"Factory";NA;21;0
"Unit";"Cyclone";"Factory";23;3
"Unit";"Cyclone";"Factory";23;3
"Building";"CommandCenter";NA;22;0
"Unit";"Cyclone";"Factory";31;3
"Unit";"Cyclone";"Factory";31;3
"Building";"CommandCenter";NA;25;0
"Unit";"Cyclone";"Factory";42;3
"Unit";"Cyclone";"Factory";42;3
"Building";"Refinery";NA;44;0
"Building";"Refinery";NA;44;0
"Building";"Starport";NA;43;0
"Building";"CommandCenter";NA;39;0
"Building";"Factory";NA;45;0
"Building";"Factory";NA;47;0
"Building";"Armory";NA;53;0
"Building";"StarportReactor";NA;56;0
"Building";"FactoryTechLab";NA;60;0
"Building";"Armory";NA;56;0
"Unit";"Hellion";"Factory";60;2
"Unit";"Hellion";"Factory";60;2
"Building";"FactoryTechLab";NA;64;0
"Unit";"Hellion";"Factory";68;2
"Unit";"Hellion";"Factory";68;2
"Building";"Refinery";NA;70;0
"Unit";"Medivac";"Starport";68;2
"Unit";"Medivac";"Starport";68;2
"Unit";"Thor";"Factory";68;6
"Building";"Refinery";NA;70;0
"Building";"Refinery";NA;70;0
"Building";"Factory";NA;68;0
"Unit";"Hellion";"Factory";90;2
"Unit";"Hellion";"Factory";90;2
"Unit";"Hellion";"Factory";90;2
"Building";"Refinery";NA;94;0
"Building";"Factory";NA;90;0
"Unit";"Hellion";"Factory";94;2
"Unit";"Thor";"Factory";90;6
"Unit";"Hellion";"Factory";104;2
"Unit";"Hellion";"Factory";104;2
"Unit";"Hellion";"Factory";106;2
"Upgrade";"TerranVehicleWeaponsLevel1";"Armory";90;0
"Unit";"Hellion";"Factory";122;2
"Unit";"Hellion";"Factory";122;2
"Building";"FactoryReactor";NA;124;0
"Unit";"Hellion";"Factory";130;2
"Unit";"Hellion";"Factory";130;2
"Building";"FactoryTechLab";NA;133;0
"Unit";"Hellion";"Factory";141;2
"Unit";"Hellion";"Factory";141;2
"Building";"Starport";NA;149;0
"Building";"Starport";NA;149;0
"Building";"Starport";NA;149;0
"Building";"Barracks";NA;149;0
"Unit";"Hellion";"Factory";151;2
"Unit";"Hellion";"Factory";151;2
"Building";"FusionCore";NA;149;0
"Unit";"Hellion";"Factory";151;2
"Unit";"Hellion";"Factory";151;2
"Upgrade";"TerranVehicleWeaponsLevel2";"Armory";141;0
"Unit";"Hellion";"Factory";151;2
"Unit";"Hellion";"Factory";153;2
"Unit";"Hellion";"Factory";155;2
"Unit";"Hellion";"Factory";157;2
"Unit";"Hellion";"Factory";159;2
"Unit";"Hellion";"Factory";161;2
"Unit";"Hellion";"Factory";163;2
"Building";"Refinery";NA;172;0
"Unit";"Hellion";"Factory";175;2
"Unit";"Thor";"Factory";175;6
"Building";"StarportTechLab";NA;183;0
"Building";"StarportTechLab";NA;183;0
"Building";"CommandCenter";NA;175;0
"Building";"StarportTechLab";NA;183;0
"Unit";"Hellion";"Factory";183;2
"Unit";"Hellion";"Factory";183;2
"Unit";"Hellion";"Factory";183;2
"Unit";"Hellion";"Factory";183;2
"Building";"CommandCenter";NA;183;0
"Building";"Armory";NA;183;0
"Building";"Refinery";NA;191;0
"Unit";"Battlecruiser";"Starport";191;6
"Unit";"Battlecruiser";"Starport";191;6
"Unit";"Battlecruiser";"Starport";191;6
"Building";"Refinery";NA;191;0
"Building";"EngineeringBay";NA;191;0
"Unit";"Hellion";"Factory";210;2
"Unit";"Hellion";"Factory";210;2
"Unit";"Hellion";"Factory";210;2
"Unit";"Hellion";"Factory";210;2
"Upgrade";"TerranVehicleWeaponsLevel3";"Armory";191;0
"Unit";"Battlecruiser";"Starport";191;6
"Unit";"Battlecruiser";"Starport";197;6
"Unit";"Thor";"Factory";210;6
"Unit";"Thor";"Factory";210;6
"Unit";"Thor";"Factory";210;6
"Unit";"Hellion";"Factory";211;2
"Unit";"Hellion";"Factory";213;2
"Unit";"Battlecruiser";"Starport";209;6
"Unit";"Thor";"Factory";231;6
"Unit";"Thor";"Factory";237;6
"Unit";"Battlecruiser";"Starport";231;6
"Unit";"Battlecruiser";"Starport";231;6
"Building";"CommandCenter";NA;259;0
"Building";"CommandCenter";NA;259;0
"Unit";"Hellion";"Factory";283;2
"Unit";"Hellion";"Factory";283;2
"Upgrade";"TerranShipWeaponsLevel1";"Armory";259;0
"Unit";"Hellion";"Factory";283;2
"Unit";"Hellion";"Factory";283;2
"Unit";"Battlecruiser";"Starport";283;6
"Unit";"Battlecruiser";"Starport";283;6
"Unit";"Hellion";"Factory";287;2
"Unit";"Hellion";"Factory";287;2
"Unit";"Thor";"Factory";283;6
"Unit";"Hellion";"Factory";287;2
"Unit";"Hellion";"Factory";289;2
"Building";"Refinery";NA;291;0
"Building";"Refinery";NA;291;0
"Unit";"Thor";"Factory";287;6
"Unit";"Thor";"Factory";287;6
"Unit";"Battlecruiser";"Starport";283;6
"Unit";"Hellion";"Factory";335;2
"Unit";"Hellion";"Factory";335;2
"Unit";"Hellion";"Factory";335;2
"Unit";"Hellion";"Factory";335;2
"Unit";"Battlecruiser";"Starport";291;6
"Unit";"Battlecruiser";"Starport";297;6
"Unit";"Thor";"Factory";335;6
"Unit";"Thor";"Factory";335;6
"Unit";"Thor";"Factory";335;6
"Unit";"Hellion";"Factory";336;2
"Unit";"Hellion";"Factory";338;2
"Unit";"Hellion";"Factory";340;2
"Unit";"Hellion";"Factory";342;2
"Unit";"Battlecruiser";"Starport";335;6
"Unit";"Hellion";"Factory";383;2
"Unit";"Hellion";"Factory";383;2
"Unit";"Battlecruiser";"Starport";345;6
"Unit";"Battlecruiser";"Starport";357;6
