"type";"unit_name";"on_building";"total_supply";"supply"
"Building";"Refinery";NA;14;0
"Building";"Barracks";NA;15;0
"Unit";"Reaper";"Barracks";19;1
"Building";"Refinery";NA;19;0
"Building";"Factory";NA;19;0
"Building";"BarracksReactor";NA;20;0
"Building";"CommandCenter";NA;19;0
"Building";"BarracksTechLab";NA;24;0
"Unit";"Hellion";"Factory";24;2
"Unit";"Hellion";"Factory";24;2
"Building";"Starport";NA;23;0
"Unit";"Hellion";"Factory";26;2
"Unit";"Hellion";"Factory";28;2
"Unit";"Banshee";"Starport";31;3
"Building";"EngineeringBay";NA;44;0
"Building";"Refinery";NA;44;0
"Building";"Refinery";NA;44;0
"Building";"Armory";NA;44;0
"Building";"Armory";NA;44;0
"Building";"CommandCenter";NA;41;0
"Unit";"Banshee";"Starport";44;3
"Unit";"Hellion";"Factory";48;2
"Unit";"Hellion";"Factory";48;2
"Building";"Factory";NA;50;0
"Building";"Factory";NA;50;0
"Building";"StarportReactor";NA;59;0
"Unit";"Hellion";"Factory";62;2
"Unit";"Hellion";"Factory";62;2
"Building";"FactoryTechLab";NA;62;0
"Unit";"Hellion";"Factory";68;2
"Unit";"Hellion";"Factory";68;2
"Building";"MissileTurret";NA;71;0
"Building";"MissileTurret";NA;71;0
"Building";"MissileTurret";NA;71;0
"Unit";"Medivac";"Starport";68;2
"Building";"Refinery";NA;71;0
"Building";"Refinery";NA;72;0
"Unit";"Thor";"Factory";68;6
"Unit";"Thor";"Factory";68;6
"Upgrade";"TerranVehicleWeaponsLevel1";"Armory";62;0
"Unit";"Medivac";"Starport";81;2
"Unit";"Hellion";"Factory";98;2
"Unit";"Hellion";"Factory";98;2
"Building";"Factory";NA;107;0
"Building";"Factory";NA;107;0
"Building";"Refinery";NA;115;0
"Building";"FactoryTechLab";NA;115;0
"Building";"Refinery";NA;115;0
"Unit";"Hellion";"Factory";118;2
"Unit";"Hellion";"Factory";118;2
"Building";"FactoryReactor";NA;115;0
"Unit";"Hellion";"Factory";123;2
"Unit";"Hellion";"Factory";125;2
"Building";"MissileTurret";NA;127;0
"Building";"MissileTurret";NA;127;0
"Building";"SensorTower";NA;127;0
"Building";"MissileTurret";NA;127;0
"Building";"CommandCenter";NA;115;0
"Unit";"Hellion";"Factory";134;2
"Unit";"Hellion";"Factory";134;2
"Upgrade";"TerranVehicleWeaponsLevel2";"Armory";112;0
"Unit";"Hellion";"Factory";137;2
"Unit";"Hellion";"Factory";137;2
"Building";"MissileTurret";NA;137;0
"Building";"SensorTower";NA;141;0
"Unit";"Hellion";"Factory";147;2
"Unit";"Hellion";"Factory";147;2
"Unit";"Hellion";"Factory";147;2
"Unit";"Hellion";"Factory";147;2
"Unit";"Hellion";"Factory";147;2
"Unit";"Hellion";"Factory";151;2
"Unit";"Hellion";"Factory";151;2
"Building";"MissileTurret";NA;157;0
"Building";"MissileTurret";NA;157;0
"Building";"MissileTurret";NA;159;0
"Building";"MissileTurret";NA;159;0
"Unit";"Hellion";"Factory";161;2
"Unit";"Hellion";"Factory";161;2
