"type";"unit_name";"on_building";"total_supply";"supply"
"Building";"Refinery";NA;14;0
"Building";"Barracks";NA;15;0
"Unit";"Reaper";"Barracks";19;1
"Building";"Refinery";NA;21;0
"Building";"Factory";NA;19;0
"Building";"BarracksReactor";NA;20;0
"Building";"CommandCenter";NA;19;0
"Unit";"Hellion";"Factory";24;2
"Unit";"Hellion";"Factory";24;2
"Building";"BarracksTechLab";NA;24;0
"Building";"Starport";NA;23;0
"Building";"BarracksTechLab";NA;30;0
"Unit";"Hellion";"Factory";30;2
"Unit";"Hellion";"Factory";30;2
"Unit";"Hellion";"Factory";33;2
"Unit";"Hellion";"Factory";37;2
"Unit";"Banshee";"Starport";32;3
"Unit";"Banshee";"Starport";47;3
"Building";"EngineeringBay";NA;52;0
"Building";"EngineeringBay";NA;52;0
"Building";"FactoryReactor";NA;52;0
"Unit";"Marine";"Barracks";55;1
"Building";"Barracks";NA;52;0
"Building";"Barracks";NA;52;0
"Unit";"Marine";"Barracks";58;1
"Upgrade";"Stimpack";"TechLab";51;0
"Unit";"Banshee";"Starport";58;3
"Building";"BarracksReactor";NA;72;0
"Building";"StarportReactor";NA;72;0
"Building";"CommandCenter";NA;63;0
"Unit";"Marine";"Barracks";76;1
"Unit";"Marine";"Barracks";76;1
"Unit";"Marine";"Barracks";76;1
"Unit";"Marine";"Barracks";76;1
"Unit";"Marine";"Barracks";76;1
"Unit";"Marine";"Barracks";78;1
"Unit";"Marine";"Barracks";81;1
"Unit";"Marine";"Barracks";82;1
"Unit";"Marine";"Barracks";83;1
"Unit";"Marine";"Barracks";84;1
"Unit";"Medivac";"Starport";79;2
"Unit";"Medivac";"Starport";79;2
"Unit";"Marine";"Barracks";87;1
"Building";"Refinery";NA;94;0
"Unit";"Marine";"Barracks";99;1
"Unit";"Marine";"Barracks";100;1
"Unit";"Marine";"Barracks";100;1
"Unit";"Marine";"Barracks";100;1
"Unit";"Marine";"Barracks";100;1
"Upgrade";"TerranInfantryArmorsLevel1";"EngineeringBay";74;0
"Upgrade";"TerranInfantryWeaponsLevel1";"EngineeringBay";74;0
"Building";"Refinery";NA;100;0
"Building";"Armory";NA;88;0
"Unit";"Marine";"Barracks";103;1
"Unit";"Marine";"Barracks";104;1
"Unit";"Marine";"Barracks";104;1
"Unit";"Marine";"Barracks";106;1
"Unit";"Marine";"Barracks";106;1
"Unit";"Marine";"Barracks";110;1
"Unit";"Marine";"Barracks";111;1
"Unit";"Marine";"Barracks";111;1
"Unit";"Marine";"Barracks";113;1
"Unit";"Marine";"Barracks";113;1
"Unit";"Marine";"Barracks";120;1
"Unit";"Marine";"Barracks";121;1
"Unit";"Marine";"Barracks";121;1
"Unit";"Marine";"Barracks";123;1
"Unit";"Marine";"Barracks";123;1
"Unit";"Marine";"Barracks";126;1
"Unit";"Marine";"Barracks";127;1
"Unit";"Marine";"Barracks";127;1
"Building";"Barracks";NA;117;0
"Unit";"Marine";"Barracks";134;1
"Unit";"Marine";"Barracks";134;1
"Building";"Barracks";NA;119;0
"Building";"MissileTurret";NA;134;0
"Unit";"Hellion";"Factory";134;2
"Unit";"Hellion";"Factory";134;2
"Building";"MissileTurret";NA;135;0
"Building";"MissileTurret";NA;135;0
"Building";"MissileTurret";NA;135;0
"Unit";"Marine";"Barracks";135;1
"Unit";"Marine";"Barracks";136;1
"Unit";"Marine";"Barracks";136;1
"Unit";"Marine";"Barracks";138;1
"Unit";"Marine";"Barracks";139;1
"Unit";"Marine";"Barracks";147;1
"Unit";"Marine";"Barracks";152;1
"Unit";"Marine";"Barracks";152;1
"Unit";"Marine";"Barracks";152;1
"Unit";"Hellion";"Factory";152;2
"Unit";"Hellion";"Factory";152;2
"Building";"Factory";NA;140;0
"Unit";"Marauder";"Barracks";152;2
"Unit";"Marine";"Barracks";153;1
"Unit";"Marine";"Barracks";153;1
"Unit";"Medivac";"Starport";152;2
"Unit";"Marine";"Barracks";154;1
"Unit";"Medivac";"Starport";152;2
"Building";"BarracksReactor";NA;152;0
"Building";"BarracksReactor";NA;152;0
"Upgrade";"TerranInfantryWeaponsLevel2";"EngineeringBay";126;0
"Upgrade";"TerranInfantryArmorsLevel2";"EngineeringBay";126;0
"Upgrade";"TerranVehicleWeaponsLevel1";"Armory";134;0
"Unit";"Marine";"Barracks";164;1
"Unit";"Marine";"Barracks";169;1
"Unit";"Marine";"Barracks";169;1
"Unit";"Marine";"Barracks";169;1
"Unit";"Marine";"Barracks";169;1
"Unit";"Hellion";"Factory";169;2
"Unit";"Hellion";"Factory";169;2
"Unit";"Medivac";"Starport";169;2
"Unit";"Marine";"Barracks";169;1
"Unit";"Marine";"Barracks";170;1
"Unit";"Marine";"Barracks";174;1
"Unit";"Marine";"Barracks";174;1
"Unit";"Marine";"Barracks";174;1
"Unit";"Marine";"Barracks";174;1
"Unit";"Marine";"Barracks";174;1
"Unit";"Marine";"Barracks";174;1
"Unit";"Marine";"Barracks";174;1
"Unit";"Thor";"Factory";169;6
"Building";"CommandCenter";NA;153;0
"Unit";"Marine";"Barracks";180;1
"Unit";"Marine";"Barracks";189;1
"Unit";"Marine";"Barracks";189;1
"Unit";"Hellion";"Factory";189;2
"Unit";"Hellion";"Factory";189;2
"Unit";"Medivac";"Starport";189;2
"Unit";"Marine";"Barracks";195;1
"Unit";"Marine";"Barracks";195;1
"Unit";"Marine";"Barracks";195;1
"Unit";"Marine";"Barracks";195;1
"Unit";"Marine";"Barracks";195;1
"Unit";"Marine";"Barracks";195;1
"Unit";"Marine";"Barracks";195;1
"Unit";"Marine";"Barracks";202;1
"Unit";"Marine";"Barracks";202;1
"Unit";"Hellion";"Factory";202;2
"Unit";"Hellion";"Factory";202;2
"Unit";"Marine";"Barracks";204;1
"Unit";"Marine";"Barracks";204;1
"Building";"Refinery";NA;210;0
"Building";"Refinery";NA;211;0
"Unit";"Thor";"Factory";195;6
"Unit";"Marine";"Barracks";213;1
"Unit";"Marine";"Barracks";213;1
"Unit";"Marine";"Barracks";213;1
"Unit";"Marine";"Barracks";213;1
"Unit";"Marine";"Barracks";213;1
"Unit";"Marine";"Barracks";213;1
"Unit";"Marine";"Barracks";213;1
"Unit";"Marine";"Barracks";217;1
"Unit";"Marine";"Barracks";225;1
"Unit";"Marine";"Barracks";225;1
"Unit";"Marine";"Barracks";226;1
"Unit";"Marine";"Barracks";226;1
"Unit";"Marine";"Barracks";228;1
"Unit";"Marine";"Barracks";229;1
"Unit";"Marine";"Barracks";229;1
"Unit";"Hellion";"Factory";225;2
"Unit";"Hellion";"Factory";225;2
"Unit";"Marine";"Barracks";232;1
"Unit";"Marine";"Barracks";245;1
"Unit";"Hellion";"Factory";245;2
"Unit";"Marine";"Barracks";245;1
"Unit";"Marine";"Barracks";245;1
"Unit";"Marine";"Barracks";245;1
"Unit";"Hellion";"Factory";245;2
"Unit";"Marine";"Barracks";245;1
"Building";"MissileTurret";NA;248;0
"Unit";"Thor";"Factory";233;6
"Upgrade";"TerranVehicleWeaponsLevel2";"Armory";202;0
"Unit";"Hellion";"Factory";250;2
"Unit";"Medivac";"Starport";248;2
"Unit";"Medivac";"Starport";248;2
"Unit";"Marine";"Barracks";264;1
"Unit";"Marine";"Barracks";264;1
"Unit";"Marine";"Barracks";264;1
"Unit";"Marine";"Barracks";264;1
"Unit";"Marine";"Barracks";264;1
"Unit";"Marine";"Barracks";264;1
"Unit";"Marine";"Barracks";264;1
"Unit";"Marine";"Barracks";264;1
"Unit";"Marine";"Barracks";264;1
"Upgrade";"TerranInfantryWeaponsLevel3";"EngineeringBay";202;0
"Upgrade";"TerranInfantryArmorsLevel3";"EngineeringBay";204;0
"Unit";"Marine";"Barracks";270;1
"Unit";"Marine";"Barracks";271;1
"Unit";"Marine";"Barracks";272;1
"Unit";"Marine";"Barracks";273;1
"Unit";"Marine";"Barracks";274;1
"Unit";"Marine";"Barracks";275;1
"Unit";"Marine";"Barracks";275;1
"Unit";"Marine";"Barracks";277;1
"Unit";"Marine";"Barracks";277;1
"Unit";"Thor";"Factory";264;6
"Unit";"Marine";"Barracks";279;1
"Unit";"Marine";"Barracks";280;1
"Unit";"Marine";"Barracks";281;1
"Unit";"Marine";"Barracks";282;1
"Unit";"Marine";"Barracks";283;1
"Unit";"Marine";"Barracks";284;1
"Unit";"Marine";"Barracks";284;1
"Unit";"Marine";"Barracks";286;1
"Unit";"Marine";"Barracks";286;1
"Unit";"Hellion";"Factory";288;2
"Unit";"Hellion";"Factory";288;2
"Unit";"Hellion";"Factory";288;2
"Unit";"Marine";"Barracks";294;1
"Unit";"Marine";"Barracks";295;1
"Unit";"Marine";"Barracks";296;1
"Unit";"Marine";"Barracks";297;1
"Unit";"Marine";"Barracks";298;1
"Unit";"Marine";"Barracks";299;1
"Unit";"Marine";"Barracks";299;1
"Unit";"Marine";"Barracks";301;1
"Unit";"Marine";"Barracks";301;1
"Unit";"Medivac";"Starport";294;2
"Unit";"Medivac";"Starport";294;2
"Unit";"Marine";"Barracks";309;1
"Unit";"Marine";"Barracks";310;1
"Unit";"Marine";"Barracks";311;1
"Unit";"Marine";"Barracks";312;1
"Unit";"Marine";"Barracks";313;1
"Unit";"Marine";"Barracks";314;1
"Unit";"Marine";"Barracks";314;1
"Unit";"Marine";"Barracks";316;1
"Unit";"Marine";"Barracks";316;1
"Unit";"Hellion";"Factory";312;2
"Unit";"Hellion";"Factory";312;2
