"type";"unit_name";"on_building";"total_supply";"supply"
"Building";"Refinery";NA;15;0
"Building";"Barracks";NA;15;0
"Unit";"Reaper";"Barracks";19;1
"Building";"Refinery";NA;19;0
"Building";"CommandCenter";NA;19;0
"Building";"Factory";NA;21;0
"Building";"BarracksReactor";NA;21;0
"Building";"Refinery";NA;26;0
"Unit";"Cyclone";"Factory";26;3
"Unit";"Cyclone";"Factory";26;3
"Building";"Refinery";NA;26;0
"Building";"Armory";NA;26;0
"Unit";"Cyclone";"Factory";39;3
"Unit";"Cyclone";"Factory";39;3
"Building";"BarracksReactor";NA;41;0
"Building";"Factory";NA;40;0
"Unit";"Cyclone";"Factory";51;3
"Unit";"Cyclone";"Factory";52;3
"Unit";"Cyclone";"Factory";58;3
"Unit";"Cyclone";"Factory";58;3
"Unit";"Hellion";"Factory";63;2
"Unit";"Hellion";"Factory";63;2
"Building";"Factory";NA;53;0
"Unit";"Hellion";"Factory";71;2
"Unit";"Hellion";"Factory";71;2
"Upgrade";"TerranVehicleWeaponsLevel1";"Armory";51;0
"Unit";"Hellion";"Factory";75;2
"Unit";"Hellion";"Factory";75;2
"Building";"FactoryTechLab";NA;77;0
"Building";"Factory";NA;77;0
"Building";"Factory";NA;77;0
"Building";"CommandCenter";NA;63;0
"Unit";"Hellion";"Factory";87;2
"Unit";"Hellion";"Factory";87;2
"Unit";"Hellion";"Factory";87;2
"Unit";"Hellion";"Factory";87;2
"Building";"Refinery";NA;87;0
"Building";"Refinery";NA;87;0
"Unit";"Cyclone";"Factory";87;3
"Building";"FactoryReactor";NA;87;0
"Building";"FactoryReactor";NA;87;0
"Unit";"Cyclone";"Factory";97;3
"Unit";"Cyclone";"Factory";97;3
"Unit";"Cyclone";"Factory";100;3
"Unit";"Cyclone";"Factory";100;3
"Unit";"Cyclone";"Factory";100;3
"Unit";"Cyclone";"Factory";106;3
"Unit";"Cyclone";"Factory";106;3
"Unit";"Cyclone";"Factory";117;3
"Upgrade";"TerranVehicleWeaponsLevel2";"Armory";87;0
"Unit";"Cyclone";"Factory";126;3
"Unit";"Cyclone";"Factory";126;3
"Unit";"Cyclone";"Factory";129;3
"Unit";"Cyclone";"Factory";129;3
"Unit";"Cyclone";"Factory";129;3
"Unit";"Cyclone";"Factory";151;3
"Unit";"Hellion";"Factory";152;2
"Unit";"Hellion";"Factory";152;2
"Unit";"Cyclone";"Factory";155;3
"Unit";"Thor";"Factory";151;6
"Unit";"Cyclone";"Factory";155;3
"Unit";"Cyclone";"Factory";158;3
"Unit";"Cyclone";"Factory";158;3
"Unit";"Hellion";"Factory";162;2
"Unit";"Hellion";"Factory";162;2
"Unit";"Cyclone";"Factory";174;3
"Unit";"Thor";"Factory";165;6
"Unit";"Hellion";"Factory";186;2
"Unit";"Hellion";"Factory";186;2
"Unit";"Hellion";"Factory";186;2
"Unit";"Cyclone";"Factory";189;3
"Unit";"Cyclone";"Factory";189;3
"Unit";"Cyclone";"Factory";189;3
"Unit";"Cyclone";"Factory";189;3
"Unit";"Cyclone";"Factory";195;3
"Upgrade";"TerranVehicleWeaponsLevel3";"Armory";149;0
"Building";"CommandCenter";NA;177;0
"Unit";"Cyclone";"Factory";216;3
