"type";"unit_name";"on_building";"total_supply";"supply"
"Building";"Refinery";NA;15;0
"Building";"Barracks";NA;15;0
"Unit";"Reaper";"Barracks";18;1
"Unit";"Marine";"Barracks";19;1
"Building";"Refinery";NA;23;0
"Building";"CommandCenter";NA;19;0
"Building";"BarracksReactor";NA;23;0
"Building";"Factory";NA;22;0
"Building";"BarracksTechLab";NA;27;0
"Unit";"Hellion";"Factory";26;2
"Unit";"Hellion";"Factory";26;2
"Building";"Starport";NA;26;0
"Unit";"Hellion";"Factory";32;2
"Unit";"Hellion";"Factory";34;2
"Unit";"Hellion";"Factory";44;2
"Unit";"Hellion";"Factory";44;2
"Building";"BarracksTechLab";NA;50;0
"Building";"Refinery";NA;50;0
"Building";"Refinery";NA;50;0
"Unit";"Banshee";"Starport";45;3
"Unit";"Hellion";"Factory";50;2
"Building";"Factory";NA;46;0
"Building";"CommandCenter";NA;43;0
"Building";"Factory";NA;50;0
"Unit";"Hellion";"Factory";50;2
"Building";"FactoryTechLab";NA;59;0
"Unit";"Hellion";"Factory";59;2
"Unit";"Raven";"Starport";55;2
"Building";"EngineeringBay";NA;63;0
"Building";"Refinery";NA;67;0
"Building";"Armory";NA;63;0
"Building";"MissileTurret";NA;73;0
"Building";"MissileTurret";NA;73;0
"Unit";"Medivac";"Starport";74;2
"Building";"MissileTurret";NA;76;0
"Unit";"Hellion";"Factory";76;2
"Unit";"Hellion";"Factory";76;2
"Unit";"Hellion";"Factory";85;2
"Unit";"Hellion";"Factory";86;2
"Unit";"Thor";"Factory";78;6
"Building";"StarportReactor";NA;80;0
"Building";"Refinery";NA;88;0
"Unit";"Thor";"Factory";80;6
"Unit";"Hellion";"Factory";101;2
"Unit";"Hellion";"Factory";101;2
"Building";"Factory";NA;88;0
"Unit";"Medivac";"Starport";101;2
"Building";"Factory";NA;88;0
"Building";"Armory";NA;92;0
"Unit";"Hellion";"Factory";107;2
"Unit";"Hellion";"Factory";111;2
"Unit";"Hellion";"Factory";117;2
"Unit";"Hellion";"Factory";117;2
"Building";"FactoryReactor";NA;117;0
"Unit";"Hellion";"Factory";117;2
"Unit";"Hellion";"Factory";117;2
"Upgrade";"TerranVehicleWeaponsLevel1";"Armory";111;0
"Unit";"Hellion";"Factory";121;2
"Unit";"Hellion";"Factory";122;2
"Unit";"Hellion";"Factory";122;2
"Building";"CommandCenter";NA;117;0
"Unit";"Hellion";"Factory";128;2
"Unit";"Hellion";"Factory";137;2
"Unit";"Hellion";"Factory";137;2
"Building";"Refinery";NA;141;0
"Building";"Refinery";NA;141;0
"Unit";"Hellion";"Factory";141;2
"Unit";"Hellion";"Factory";141;2
"Unit";"Medivac";"Starport";141;2
"Unit";"Hellion";"Factory";141;2
"Unit";"Hellion";"Factory";145;2
"Unit";"Hellion";"Factory";148;2
"Unit";"Hellion";"Factory";158;2
"Unit";"Hellion";"Factory";158;2
"Unit";"Hellion";"Factory";164;2
"Unit";"Hellion";"Factory";166;2
"Building";"CommandCenter";NA;152;0
"Unit";"Hellion";"Factory";166;2
"Unit";"Hellion";"Factory";166;2
"Building";"Factory";NA;164;0
"Building";"Factory";NA;164;0
"Building";"Factory";NA;164;0
"Upgrade";"TerranVehicleWeaponsLevel2";"Armory";148;0
"Unit";"Thor";"Factory";166;6
"Building";"FactoryTechLab";NA;174;0
"Building";"FactoryTechLab";NA;174;0
"Building";"FactoryTechLab";NA;174;0
"Unit";"Thor";"Factory";170;6
"Unit";"Thor";"Factory";170;6
"Unit";"Hellion";"Factory";174;2
"Unit";"Hellion";"Factory";174;2
"Unit";"Hellion";"Factory";180;2
"Unit";"Hellion";"Factory";180;2
"Unit";"Thor";"Factory";174;6
"Unit";"Thor";"Factory";180;6
"Unit";"Thor";"Factory";200;6
"Unit";"Hellion";"Factory";212;2
"Unit";"Hellion";"Factory";212;2
"Building";"Refinery";NA;212;0
"Building";"Refinery";NA;212;0
"Unit";"Thor";"Factory";206;6
"Building";"MissileTurret";NA;213;0
"Building";"MissileTurret";NA;213;0
"Building";"CommandCenter";NA;196;0
"Building";"MissileTurret";NA;225;0
"Building";"MissileTurret";NA;225;0
"Unit";"Hellion";"Factory";231;2
"Unit";"Hellion";"Factory";231;2
"Unit";"Thor";"Factory";231;6
"Unit";"Thor";"Factory";231;6
"Upgrade";"TerranShipWeaponsLevel1";"Armory";215;0
"Building";"Refinery";NA;237;0
"Building";"Refinery";NA;237;0
"Upgrade";"TerranVehicleWeaponsLevel3";"Armory";212;0
"Unit";"Hellion";"Factory";249;2
"Unit";"Hellion";"Factory";249;2
"Unit";"Hellion";"Factory";249;2
"Unit";"Hellion";"Factory";249;2
"Unit";"Thor";"Factory";249;6
"Unit";"Thor";"Factory";249;6
"Building";"CommandCenter";NA;237;0
"Unit";"Hellion";"Factory";253;2
"Building";"Starport";NA;257;0
"Building";"Starport";NA;257;0
"Unit";"Thor";"Factory";257;6
"Unit";"Thor";"Factory";269;6
"Unit";"Hellion";"Factory";271;2
"Unit";"Hellion";"Factory";271;2
"Building";"StarportTechLab";NA;277;0
"Building";"StarportTechLab";NA;277;0
"Unit";"Thor";"Factory";271;6
"Unit";"Thor";"Factory";271;6
"Unit";"Hellion";"Factory";288;2
"Unit";"Hellion";"Factory";288;2
"Unit";"Hellion";"Factory";288;2
"Unit";"Hellion";"Factory";288;2
"Building";"Starport";NA;283;0
"Building";"Starport";NA;283;0
"Unit";"Thor";"Factory";288;6
"Upgrade";"TerranShipWeaponsLevel2";"Armory";271;0
"Building";"StarportTechLab";NA;314;0
"Building";"StarportTechLab";NA;314;0
"Building";"Starport";NA;314;0
"Building";"Starport";NA;314;0
"Building";"CommandCenter";NA;308;0
"Unit";"Hellion";"Factory";314;2
"Unit";"Hellion";"Factory";314;2
"Unit";"Hellion";"Factory";314;2
"Unit";"Hellion";"Factory";314;2
"Unit";"Hellion";"Factory";314;2
"Unit";"Hellion";"Factory";314;2
"Unit";"Hellion";"Factory";314;2
"Unit";"Raven";"Starport";314;2
"Unit";"Raven";"Starport";314;2
"Unit";"Raven";"Starport";314;2
"Unit";"Hellion";"Factory";314;2
"Unit";"Thor";"Factory";314;6
"Unit";"Thor";"Factory";314;6
"Building";"StarportTechLab";NA;328;0
"Building";"StarportTechLab";NA;334;0
