"Type";"UnitName";"OnBuilding";"TotalSupply";"Supply"
"Unit";"SCV";"Command Center";12;1
"Unit";"SCV";"Command Center";13;1
"Unit";"SCV";"Command Center";14;1
"Building";"SupplyDepot";NA;13;0
"Unit";"SCV";"Command Center";15;1
"Building";"Refinery";NA;14;0
"Unit";"SCV";"Command Center";15;1
"Unit";"SCV";"Command Center";16;1
"Unit";"SCV";"Command Center";17;1
"Building";"Barracks";NA;15;0
"Unit";"SCV";"Command Center";18;1
"Unit";"Reaper";"Barracks";19;1
"Unit";"SCV";"Command Center";21;1
"Building";"Refinery";NA;21;0
"Building";"BarracksReactor";NA;21;0
"Building";"Factory";NA;20;0
"Unit";"SCV";"Command Center";22;1
"Unit";"SCV";"Command Center";23;1
"Building";"CommandCenter";NA;20;0
"Building";"SupplyDepot";NA;22;0
"Unit";"SCV";"Command Center";24;1
"Unit";"Hellion";"Factory";24;2
"Unit";"Hellion";"Factory";24;2
"Unit";"SCV";"Command Center";24;1
"Building";"Factory";NA;22;0
"Building";"BarracksReactor";NA;23;0
"Unit";"SCV";"Command Center";30;1
"Unit";"SCV";"Command Center";30;1
"Unit";"Hellion";"Factory";29;2
"Unit";"Hellion";"Factory";29;2
"Unit";"SCV";"Command Center";30;1
"Unit";"SCV";"Command Center";31;1
"Unit";"Hellion";"Factory";32;2
"Unit";"Hellion";"Factory";36;2
"Unit";"Hellion";"Factory";37;2
"Unit";"Hellion";"Factory";38;2
"Unit";"SCV";"Command Center";40;1
"Building";"Armory";NA;30;0
"Unit";"SCV";"Command Center";42;1
"Unit";"Hellion";"Factory";46;2
"Unit";"SCV";"Command Center";48;1
"Unit";"Hellion";"Factory";47;2
"Unit";"SCV";"Command Center";48;1
"Building";"SupplyDepot";NA;48;0
"Building";"SupplyDepot";NA;48;0
"Building";"FactoryTechLab";NA;54;0
"Unit";"SCV";"Command Center";54;1
"Unit";"SCV";"Command Center";54;1
"Building";"FactoryTechLab";NA;54;0
"Unit";"SCV";"Command Center";54;1
"Unit";"SCV";"Command Center";55;1
"Building";"SupplyDepot";NA;54;0
"Unit";"SCV";"Command Center";56;1
"Unit";"SCV";"Command Center";57;1
"Building";"CommandCenter";NA;53;0
"Building";"SupplyDepot";NA;56;0
"Building";"SupplyDepot";NA;56;0
"Building";"SupplyDepot";NA;58;0
"Unit";"SCV";"Command Center";58;1
"Unit";"SCV";"Command Center";59;1
"Building";"Factory";NA;54;0
"Building";"Factory";NA;54;0
"Building";"Refinery";NA;60;0
"Building";"Refinery";NA;60;0
"Unit";"SCV";"Command Center";62;1
"Unit";"SCV";"Command Center";62;1
"Building";"SupplyDepot";NA;62;0
"Unit";"SCV";"Command Center";62;1
"Unit";"Hellion";"Factory";62;2
"Unit";"Hellion";"Factory";62;2
"Unit";"SCV";"Command Center";62;1
"Building";"Armory";NA;58;0
"Unit";"SCV";"Command Center";64;1
"Building";"BarracksTechLab";NA;62;0
"Unit";"SCV";"Command Center";64;1
"Unit";"SCV";"Command Center";69;1
"Unit";"SCV";"Command Center";70;1
"Unit";"Hellion";"Factory";70;2
"Unit";"Hellion";"Factory";70;2
"Unit";"Hellion";"Factory";71;2
"Unit";"SCV";"Command Center";72;1
"Unit";"SCV";"Command Center";74;1
"Unit";"SCV";"Command Center";74;1
"Building";"Refinery";NA;74;0
"Building";"Refinery";NA;74;0
"Unit";"SCV";"Command Center";81;1
"Unit";"SCV";"Command Center";83;1
"Unit";"SCV";"Command Center";83;1
"Unit";"Hellion";"Factory";80;2
"Unit";"Hellion";"Factory";80;2
"Unit";"Hellion";"Factory";80;2
"Unit";"Hellion";"Factory";80;2
"Unit";"SCV";"Command Center";83;1
"Upgrade";"TerranVehicleWeaponsLevel1";"Armory";62;0
"Unit";"SCV";"Command Center";94;1
"Unit";"Hellion";"Factory";94;2
"Unit";"Hellion";"Factory";94;2
"Unit";"SCV";"Command Center";95;1
"Unit";"SCV";"Command Center";96;1
"Unit";"SCV";"Command Center";96;1
"Building";"SupplyDepot";NA;96;0
"Building";"SupplyDepot";NA;96;0
"Building";"SupplyDepot";NA;96;0
"Building";"SupplyDepot";NA;96;0
"Unit";"Hellion";"Factory";103;2
"Unit";"SCV";"Command Center";103;1
"Unit";"SCV";"Command Center";103;1
"Unit";"SCV";"Command Center";103;1
"Upgrade";"TerranVehicleAndShipArmorsLevel1";"Armory";84;0
"Unit";"SCV";"Command Center";105;1
"Unit";"SCV";"Command Center";106;1
"Building";"SupplyDepot";NA;105;0
"Building";"SupplyDepot";NA;105;0
"Unit";"Hellion";"Factory";105;2
"Building";"SupplyDepot";NA;105;0
"Building";"SupplyDepot";NA;105;0
"Building";"Factory";NA;103;0
"Unit";"Hellion";"Factory";108;2
"Unit";"Hellion";"Factory";108;2
"Unit";"SCV";"Command Center";116;1
"Unit";"SCV";"Command Center";116;1
"Building";"SupplyDepot";NA;112;0
"Building";"SupplyDepot";NA;112;0
"Building";"Starport";NA;110;0
"Unit";"SCV";"Command Center";116;1
"Unit";"Hellion";"Factory";116;2
"Unit";"Hellion";"Factory";116;2
"Building";"CommandCenter";NA;105;0
"Unit";"Hellion";"Factory";118;2
"Unit";"SCV";"Command Center";123;1
"Upgrade";"TerranVehicleWeaponsLevel2";"Armory";109;0
"Unit";"Thor";"Factory";123;6
"Unit";"SCV";"Command Center";126;1
"Unit";"Thor";"Factory";126;6
"Unit";"Thor";"Factory";126;6
"Unit";"Hellion";"Factory";132;2
"Unit";"Hellion";"Factory";132;2
"Unit";"Hellion";"Factory";132;2
"Unit";"Hellion";"Factory";132;2
"Building";"Starport";NA;126;0
"Upgrade";"TerranVehicleAndShipArmorsLevel2";"Armory";118;0
"Unit";"Thor";"Factory";126;6
"Unit";"Hellion";"Factory";145;2
"Unit";"Hellion";"Factory";147;2
"Unit";"Hellion";"Factory";149;2
"Unit";"Hellion";"Factory";153;2
"Unit";"SCV";"Command Center";153;1
"Unit";"SCV";"Command Center";153;1
"Building";"Starport";NA;133;0
"Unit";"SCV";"Command Center";165;1
"Building";"Factory";NA;133;0
"Unit";"Hellion";"Factory";159;2
"Building";"Refinery";NA;165;0
"Unit";"Hellion";"Factory";169;2
"Unit";"Hellion";"Factory";169;2
"Unit";"Hellion";"Factory";169;2
"Building";"EngineeringBay";NA;165;0
"Building";"StarportReactor";NA;153;0
"Building";"Refinery";NA;169;0
"Unit";"SCV";"Command Center";178;1
"Unit";"SCV";"Command Center";178;1
"Building";"StarportTechLab";NA;178;0
"Unit";"Hellion";"Factory";178;2
"Unit";"Hellion";"Factory";178;2
"Building";"FactoryTechLab";NA;179;0
"Building";"SupplyDepot";NA;179;0
"Building";"SupplyDepot";NA;179;0
"Building";"SupplyDepot";NA;179;0
"Building";"SupplyDepot";NA;179;0
"Unit";"Thor";"Factory";178;6
"Unit";"Hellion";"Factory";179;2
"Unit";"Cyclone";"Factory";182;3
"Unit";"Thor";"Factory";178;6
"Building";"StarportReactor";NA;179;0
"Unit";"Thor";"Factory";178;6
"Building";"MissileTurret";NA;184;0
"Building";"MissileTurret";NA;192;0
"Unit";"Hellion";"Factory";192;2
"Unit";"Hellion";"Factory";192;2
"Upgrade";"TerranVehicleWeaponsLevel3";"Armory";169;0
"Unit";"Hellion";"Factory";211;2
"Unit";"Hellion";"Factory";211;2
"Unit";"Hellion";"Factory";211;2
"Unit";"Hellion";"Factory";211;2
"Unit";"Hellion";"Factory";211;2
"Building";"CommandCenter";NA;190;0
"Unit";"Hellion";"Factory";221;2
"Unit";"Hellion";"Factory";221;2
"Unit";"Hellion";"Factory";221;2
"Unit";"Hellion";"Factory";221;2
"Unit";"SCV";"Command Center";229;1
"Unit";"SCV";"Command Center";229;1
"Unit";"Hellion";"Factory";221;2
"Unit";"Hellion";"Factory";223;2
"Unit";"Hellion";"Factory";229;2
"Unit";"Hellion";"Factory";237;2
"Unit";"Hellion";"Factory";237;2
"Unit";"Hellion";"Factory";237;2
"Unit";"Hellion";"Factory";237;2
"Upgrade";"TerranVehicleAndShipArmorsLevel3";"Armory";207;0
"Unit";"Hellion";"Factory";237;2
"Unit";"Hellion";"Factory";239;2
"Unit";"Hellion";"Factory";245;2
"Unit";"SCV";"Command Center";249;1
"Unit";"SCV";"Command Center";249;1
"Unit";"Hellion";"Factory";249;2
"Unit";"Hellion";"Factory";253;2
"Unit";"Hellion";"Factory";253;2
"Building";"Refinery";NA;259;0
"Building";"Refinery";NA;259;0
"Unit";"Thor";"Factory";259;6
"Unit";"Thor";"Factory";259;6
"Unit";"Hellion";"Factory";259;2
"Unit";"Hellion";"Factory";259;2
"Unit";"Hellion";"Factory";259;2
"Unit";"Hellion";"Factory";259;2
