"Type";"UnitName";"OnBuilding";"TotalSupply";"Supply"
"Unit";"SCV";"Command Center";12;1
"Unit";"SCV";"Command Center";12;1
"Unit";"SCV";"Command Center";13;1
"Building";"SupplyDepot";NA;13;0
"Unit";"SCV";"Command Center";15;1
"Building";"Refinery";NA;14;0
"Unit";"SCV";"Command Center";15;1
"Unit";"SCV";"Command Center";16;1
"Unit";"SCV";"Command Center";17;1
"Building";"Barracks";NA;15;0
"Unit";"Reaper";"Barracks";19;1
"Unit";"SCV";"Command Center";19;1
"Unit";"SCV";"Command Center";21;1
"Building";"SupplyDepot";NA;20;0
"Unit";"SCV";"Command Center";21;1
"Building";"Factory";NA;19;0
"Building";"Refinery";NA;21;0
"Building";"BarracksReactor";NA;20;0
"Unit";"SCV";"Command Center";23;1
"Unit";"Marine";"Barracks";23;1
"Unit";"Marine";"Barracks";23;1
"Unit";"Cyclone";"Factory";23;3
"Unit";"SCV";"Command Center";26;1
"Unit";"Marine";"Barracks";26;1
"Building";"Bunker";NA;23;0
"Unit";"Marine";"Barracks";26;1
"Building";"Starport";NA;24;0
"Unit";"Marine";"Barracks";32;1
"Unit";"Marine";"Barracks";32;1
"Building";"StarportTechLab";NA;32;0
"Unit";"Cyclone";"Factory";32;3
"Unit";"SCV";"Command Center";32;1
"Unit";"SCV";"Command Center";38;1
"Building";"FactoryTechLab";NA;38;0
"Unit";"Banshee";"Starport";34;3
"Building";"CommandCenter";NA;32;0
"Unit";"Marine";"Barracks";38;1
"Building";"SupplyDepot";NA;39;0
"Unit";"Marine";"Barracks";43;1
"Unit";"Marine";"Barracks";43;1
"Unit";"Raven";"Starport";42;2
"Unit";"Marine";"Barracks";43;1
"Unit";"Marine";"Barracks";45;1
"Unit";"Marine";"Barracks";47;1
"Unit";"SCV";"Command Center";48;1
"Unit";"Marine";"Barracks";48;1
"Unit";"SCV";"Command Center";50;1
"Building";"Bunker";NA;50;0
"Unit";"SCV";"Command Center";53;1
"Unit";"Marine";"Barracks";53;1
"Unit";"Marine";"Barracks";53;1
"Unit";"Banshee";"Starport";49;3
"Unit";"SCV";"Command Center";53;1
"Unit";"Marine";"Barracks";54;1
"Unit";"SCV";"Command Center";59;1
"Unit";"SCV";"Command Center";60;1
"Unit";"SCV";"Command Center";62;1
"Unit";"SCV";"Command Center";62;1
"Unit";"SCV";"Command Center";63;1
"Unit";"SCV";"Command Center";64;1
"Building";"StarportReactor";NA;60;0
"Unit";"SCV";"Command Center";65;1
"Unit";"SCV";"Command Center";66;1
"Building";"EngineeringBay";NA;65;0
"Building";"EngineeringBay";NA;65;0
"Unit";"SCV";"Command Center";67;1
"Unit";"SCV";"Command Center";69;1
"Unit";"SCV";"Command Center";69;1
"Building";"Refinery";NA;69;0
"Building";"CommandCenter";NA;61;0
"Building";"Refinery";NA;69;0
"Unit";"Marine";"Barracks";70;1
"Unit";"SCV";"Command Center";71;1
"Building";"StarportReactor";NA;69;0
"Unit";"Marine";"Barracks";72;1
"Building";"SupplyDepot";NA;73;0
"Unit";"SCV";"Command Center";74;1
"Building";"Barracks";NA;69;0
"Building";"Barracks";NA;69;0
"Building";"SupplyDepot";NA;74;0
"Building";"SupplyDepot";NA;74;0
"Unit";"SCV";"Command Center";75;1
"Unit";"SCV";"Command Center";76;1
"Unit";"Marine";"Barracks";76;1
"Building";"SupplyDepot";NA;76;0
"Building";"SupplyDepot";NA;76;0
"Unit";"Marine";"Barracks";78;1
"Unit";"Marine";"Barracks";78;1
"Unit";"Marine";"Barracks";78;1
"Unit";"Marine";"Barracks";78;1
"Unit";"Marine";"Barracks";78;1
"Unit";"SCV";"Command Center";83;1
"Unit";"SCV";"Command Center";83;1
"Unit";"SCV";"Command Center";83;1
"Unit";"Marine";"Barracks";79;1
"Unit";"Marine";"Barracks";80;1
"Unit";"SCV";"Command Center";84;1
"Building";"MissileTurret";NA;84;0
"Unit";"SCV";"Command Center";89;1
"Unit";"SCV";"Command Center";89;1
"Building";"SupplyDepot";NA;84;0
"Unit";"Marine";"Barracks";87;1
"Unit";"Marine";"Barracks";87;1
"Unit";"Marine";"Barracks";87;1
"Unit";"Marine";"Barracks";87;1
"Unit";"SCV";"Command Center";89;1
"Unit";"SCV";"Command Center";90;1
"Unit";"SCV";"Command Center";95;1
"Building";"Armory";NA;83;0
"Upgrade";"Stimpack";"TechLab";76;0
"Unit";"SCV";"Command Center";96;1
"Unit";"Marine";"Barracks";92;1
"Unit";"Marine";"Barracks";93;1
"Unit";"Marine";"Barracks";94;1
"Unit";"Medivac";"Starport";89;2
"Unit";"Medivac";"Starport";90;2
"Unit";"SCV";"Command Center";97;1
"Unit";"Marine";"Barracks";97;1
"Unit";"Marine";"Barracks";97;1
"Upgrade";"TerranInfantryWeaponsLevel1";"EngineeringBay";78;0
"Unit";"SCV";"Command Center";105;1
"Unit";"SCV";"Command Center";105;1
"Upgrade";"TerranInfantryArmorsLevel1";"EngineeringBay";79;0
"Unit";"SCV";"Command Center";107;1
"Unit";"Marine";"Barracks";100;1
"Unit";"Marine";"Barracks";110;1
"Unit";"Marine";"Barracks";110;1
"Unit";"Marine";"Barracks";110;1
"Building";"SupplyDepot";NA;110;0
"Building";"SupplyDepot";NA;110;0
"Unit";"Marine";"Barracks";114;1
"Unit";"Marine";"Barracks";114;1
"Building";"Barracks";NA;100;0
"Unit";"Marine";"Barracks";114;1
"Unit";"Marine";"Barracks";115;1
"Building";"Barracks";NA;103;0
"Unit";"SCV";"Command Center";117;1
"Unit";"SCV";"Command Center";117;1
"Unit";"SCV";"Command Center";117;1
"Unit";"SCV";"Command Center";121;1
"Unit";"SCV";"Command Center";122;1
"Building";"Refinery";NA;121;0
"Unit";"Marine";"Barracks";124;1
"Building";"Refinery";NA;121;0
"Unit";"Marine";"Barracks";124;1
"Unit";"Marine";"Barracks";124;1
"Unit";"Marine";"Barracks";124;1
"Unit";"SCV";"Command Center";126;1
"Unit";"SCV";"Command Center";126;1
"Unit";"Marine";"Barracks";124;1
"Unit";"SCV";"Command Center";126;1
"Building";"BarracksReactor";NA;121;0
"Building";"BarracksReactor";NA;121;0
"Unit";"Marine";"Barracks";126;1
"Building";"SupplyDepot";NA;134;0
"Unit";"Medivac";"Starport";126;2
"Unit";"Medivac";"Starport";126;2
"Unit";"Marine";"Barracks";134;1
"Unit";"Marine";"Barracks";134;1
"Unit";"Marine";"Barracks";134;1
"Unit";"Marine";"Barracks";134;1
"Building";"SupplyDepot";NA;134;0
"Building";"SupplyDepot";NA;134;0
"Unit";"Marine";"Barracks";134;1
"Unit";"Marine";"Barracks";135;1
"Unit";"Marine";"Barracks";135;1
"Unit";"Marine";"Barracks";135;1
"Unit";"Marine";"Barracks";135;1
"Unit";"Marine";"Barracks";139;1
"Unit";"Marine";"Barracks";143;1
"Unit";"Marine";"Barracks";143;1
"Unit";"Marine";"Barracks";146;1
"Unit";"Marine";"Barracks";147;1
"Building";"SupplyDepot";NA;144;0
"Building";"SupplyDepot";NA;144;0
"Upgrade";"TerranVehicleWeaponsLevel1";"Armory";121;0
"Unit";"Marine";"Barracks";151;1
"Unit";"Marine";"Barracks";151;1
"Unit";"Marine";"Barracks";151;1
"Building";"SupplyDepot";NA;151;0
"Unit";"Medivac";"Starport";147;2
"Building";"SupplyDepot";NA;151;0
"Unit";"Medivac";"Starport";147;2
"Building";"SupplyDepot";NA;151;0
"Building";"SupplyDepot";NA;151;0
"Unit";"Marine";"Barracks";153;1
"Unit";"Marine";"Barracks";153;1
"Unit";"Marine";"Barracks";153;1
"Unit";"Marine";"Barracks";153;1
"Upgrade";"TerranInfantryWeaponsLevel2";"EngineeringBay";124;0
"Building";"Factory";NA;144;0
"Unit";"Marine";"Barracks";160;1
"Unit";"Marine";"Barracks";160;1
"Unit";"Marine";"Barracks";164;1
"Unit";"Marine";"Barracks";164;1
"Unit";"Marine";"Barracks";164;1
"Unit";"Marine";"Barracks";164;1
"Unit";"Marine";"Barracks";164;1
"Building";"FactoryTechLab";NA;164;0
"Upgrade";"TerranInfantryArmorsLevel2";"EngineeringBay";134;0
"Unit";"Marine";"Barracks";171;1
"Unit";"Marine";"Barracks";171;1
"Unit";"Marine";"Barracks";171;1
"Unit";"Marine";"Barracks";171;1
"Unit";"Marine";"Barracks";171;1
"Unit";"Marine";"Barracks";171;1
"Unit";"Marine";"Barracks";171;1
"Unit";"Marine";"Barracks";171;1
"Unit";"Marine";"Barracks";171;1
"Unit";"Marine";"Barracks";171;1
"Unit";"Marine";"Barracks";172;1
"Unit";"Marine";"Barracks";173;1
"Unit";"Marine";"Barracks";174;1
"Unit";"Marine";"Barracks";175;1
"Unit";"Marine";"Barracks";176;1
"Unit";"Marine";"Barracks";177;1
"Unit";"Marine";"Barracks";178;1
"Unit";"Marine";"Barracks";179;1
"Unit";"Medivac";"Starport";176;2
"Unit";"Medivac";"Starport";176;2
"Unit";"Marine";"Barracks";180;1
"Unit";"Marine";"Barracks";181;1
"Unit";"Marine";"Barracks";182;1
"Unit";"Marine";"Barracks";185;1
"Unit";"Marine";"Barracks";185;1
"Unit";"Marine";"Barracks";185;1
"Building";"CommandCenter";NA;171;0
"Unit";"Marine";"Barracks";189;1
"Unit";"Marine";"Barracks";189;1
"Unit";"Marine";"Barracks";189;1
"Unit";"Medivac";"Starport";189;2
"Unit";"Marine";"Barracks";199;1
"Unit";"Marine";"Barracks";199;1
"Unit";"Marine";"Barracks";199;1
"Unit";"Marine";"Barracks";199;1
"Unit";"Marine";"Barracks";199;1
"Unit";"Marauder";"Barracks";201;2
"Building";"Barracks";NA;188;0
"Building";"Barracks";NA;188;0
"Building";"Barracks";NA;189;0
"Upgrade";"TerranVehicleWeaponsLevel2";"Armory";171;0
"Unit";"Marine";"Barracks";211;1
"Unit";"Marine";"Barracks";211;1
"Unit";"Marine";"Barracks";211;1
"Unit";"Marine";"Barracks";211;1
"Unit";"Marine";"Barracks";211;1
"Building";"BarracksTechLab";NA;211;0
"Building";"BarracksTechLab";NA;211;0
"Unit";"Marauder";"Barracks";211;2
"Unit";"Marine";"Barracks";211;1
"Unit";"Marine";"Barracks";211;1
"Unit";"Marine";"Barracks";211;1
"Unit";"Marine";"Barracks";211;1
"Unit";"Marine";"Barracks";211;1
"Unit";"Marine";"Barracks";212;1
"Unit";"Marine";"Barracks";213;1
"Unit";"Marine";"Barracks";216;1
"Unit";"Marine";"Barracks";216;1
"Unit";"Marine";"Barracks";218;1
"Unit";"Marine";"Barracks";218;1
"Unit";"Marine";"Barracks";218;1
"Unit";"Marauder";"Barracks";218;2
"Unit";"Marine";"Barracks";227;1
"Unit";"Marine";"Barracks";227;1
"Unit";"Marine";"Barracks";227;1
"Unit";"Marauder";"Barracks";227;2
"Unit";"Marauder";"Barracks";228;2
"Unit";"Marine";"Barracks";232;1
"Unit";"Marine";"Barracks";232;1
"Unit";"Marine";"Barracks";232;1
"Unit";"Marauder";"Barracks";230;2
"Unit";"Marine";"Barracks";232;1
"Unit";"Marine";"Barracks";232;1
"Unit";"Marine";"Barracks";242;1
"Unit";"Marine";"Barracks";242;1
"Unit";"Marine";"Barracks";242;1
"Unit";"Marauder";"Barracks";235;2
"Unit";"Marauder";"Barracks";237;2
"Unit";"Marauder";"Barracks";242;2
"Unit";"Marine";"Barracks";246;1
"Unit";"Marine";"Barracks";246;1
"Unit";"Marauder";"Barracks";249;2
"Unit";"Marauder";"Barracks";251;2
"Unit";"Marauder";"Barracks";253;2
"Unit";"Marine";"Barracks";255;1
"Unit";"Marine";"Barracks";255;1
"Unit";"Marine";"Barracks";255;1
"Unit";"Marine";"Barracks";255;1
"Unit";"Marine";"Barracks";255;1
"Unit";"Marine";"Barracks";255;1
"Unit";"Marauder";"Barracks";257;2
"Unit";"Marauder";"Barracks";259;2
"Unit";"Marine";"Barracks";263;1
"Unit";"Marine";"Barracks";263;1
"Unit";"Marine";"Barracks";263;1
"Unit";"Marine";"Barracks";263;1
"Unit";"Marauder";"Barracks";261;2
"Unit";"Marine";"Barracks";269;1
"Unit";"Marine";"Barracks";269;1
"Unit";"Marine";"Barracks";269;1
"Unit";"Marine";"Barracks";269;1
"Unit";"Marine";"Barracks";269;1
"Unit";"Marine";"Barracks";273;1
"Unit";"Marine";"Barracks";274;1
"Unit";"Marine";"Barracks";275;1
"Unit";"Marine";"Barracks";276;1
"Unit";"Marauder";"Barracks";269;2
"Unit";"Marauder";"Barracks";271;2
"Unit";"Marine";"Barracks";281;1
"Unit";"Marine";"Barracks";281;1
"Unit";"Marauder";"Barracks";277;2
"Unit";"Marine";"Barracks";283;1
"Unit";"Marine";"Barracks";283;1
"Unit";"Marine";"Barracks";283;1
"Unit";"Marine";"Barracks";284;1
"Unit";"Marine";"Barracks";285;1
"Unit";"Marine";"Barracks";286;1
"Unit";"Marine";"Barracks";287;1
"Unit";"Marine";"Barracks";292;1
"Unit";"Marine";"Barracks";294;1
"Unit";"Medivac";"Starport";284;2
"Unit";"Medivac";"Starport";284;2
"Unit";"Marauder";"Barracks";288;2
"Unit";"Marauder";"Barracks";290;2
"Unit";"Marine";"Barracks";296;1
"Unit";"Marauder";"Barracks";294;2
"Building";"Refinery";NA;299;0
"Unit";"Marine";"Barracks";314;1
"Unit";"Marine";"Barracks";314;1
"Unit";"Marauder";"Barracks";309;2
"Unit";"Marauder";"Barracks";311;2
"Unit";"Marauder";"Barracks";314;2
"Unit";"Marine";"Barracks";318;1
"Unit";"Marine";"Barracks";318;1
"Unit";"Marine";"Barracks";318;1
"Unit";"Marine";"Barracks";318;1
"Unit";"Liberator";"Starport";305;3
"Unit";"Marauder";"Barracks";318;2
"Unit";"Liberator";"Starport";307;3
"Unit";"Marauder";"Barracks";320;2
"Unit";"Marauder";"Barracks";322;2
"Unit";"Marine";"Barracks";324;1
"Unit";"Marine";"Barracks";328;1
"Unit";"Marine";"Barracks";328;1
"Unit";"Marine";"Barracks";328;1
"Unit";"Marine";"Barracks";328;1
"Unit";"Marine";"Barracks";338;1
"Unit";"Marine";"Barracks";338;1
"Unit";"Marine";"Barracks";338;1
"Unit";"Marauder";"Barracks";331;2
"Unit";"Marauder";"Barracks";336;2
"Unit";"Marauder";"Barracks";338;2
"Unit";"Marine";"Barracks";352;1
"Unit";"Marine";"Barracks";352;1
"Unit";"Marine";"Barracks";352;1
"Unit";"Marine";"Barracks";352;1
