"Type";"UnitName";"OnBuilding";"TotalSupply";"Supply"
"Unit";"SCV";"Command Center";12;1
"Unit";"SCV";"Command Center";12;1
"Unit";"SCV";"Command Center";13;1
"Building";"SupplyDepot";NA;13;0
"Unit";"SCV";"Command Center";15;1
"Unit";"SCV";"Command Center";15;1
"Building";"Refinery";NA;15;0
"Unit";"SCV";"Command Center";16;1
"Building";"Barracks";NA;15;0
"Unit";"SCV";"Command Center";17;1
"Unit";"Reaper";"Barracks";19;1
"Unit";"SCV";"Command Center";19;1
"Unit";"SCV";"Command Center";20;1
"Building";"SupplyDepot";NA;19;0
"Unit";"Marine";"Barracks";20;1
"Unit";"SCV";"Command Center";22;1
"Unit";"SCV";"Command Center";24;1
"Building";"Factory";NA;21;0
"Building";"CommandCenter";NA;19;0
"Unit";"SCV";"Command Center";25;1
"Building";"BarracksReactor";NA;23;0
"Unit";"SCV";"Command Center";26;1
"Unit";"SCV";"Command Center";27;1
"Unit";"Marine";"Barracks";26;1
"Unit";"Marine";"Barracks";26;1
"Building";"FactoryTechLab";NA;26;0
"Unit";"SCV";"Command Center";27;1
"Unit";"SCV";"Command Center";27;1
"Building";"Starport";NA;26;0
"Unit";"SCV";"Command Center";30;1
"Unit";"SCV";"Command Center";31;1
"Building";"CommandCenter";NA;24;0
"Unit";"Hellion";"Factory";31;2
"Unit";"Hellion";"Factory";31;2
"Unit";"SCV";"Command Center";32;1
"Unit";"SCV";"Command Center";34;1
"Unit";"Marine";"Barracks";33;1
"Unit";"SCV";"Command Center";38;1
"Building";"Refinery";NA;34;0
"Unit";"SCV";"Command Center";41;1
"Unit";"Hellion";"Factory";39;2
"Unit";"Hellion";"Factory";39;2
"Unit";"SCV";"Command Center";41;1
"Unit";"Banshee";"Starport";33;3
"Unit";"SCV";"Command Center";42;1
"Unit";"SCV";"Command Center";47;1
"Building";"SupplyDepot";NA;43;0
"Unit";"SCV";"Command Center";51;1
"Unit";"Hellion";"Factory";47;2
"Unit";"Hellion";"Factory";47;2
"Building";"SupplyDepot";NA;48;0
"Unit";"SCV";"Command Center";53;1
"Unit";"SCV";"Command Center";53;1
"Unit";"SCV";"Command Center";58;1
"Building";"BarracksTechLab";NA;58;0
"Building";"EngineeringBay";NA;58;0
"Building";"EngineeringBay";NA;58;0
"Unit";"SCV";"Command Center";61;1
"Unit";"SCV";"Command Center";61;1
"Unit";"SCV";"Command Center";61;1
"Unit";"SCV";"Command Center";61;1
"Building";"Refinery";NA;61;0
"Unit";"SCV";"Command Center";62;1
"Building";"Refinery";NA;61;0
"Unit";"Marine";"Barracks";61;1
"Unit";"SCV";"Command Center";63;1
"Unit";"SCV";"Command Center";64;1
"Unit";"SCV";"Command Center";67;1
"Building";"SupplyDepot";NA;64;0
"Building";"SupplyDepot";NA;64;0
"Building";"SupplyDepot";NA;64;0
"Building";"Barracks";NA;59;0
"Building";"StarportReactor";NA;64;0
"Building";"Barracks";NA;62;0
"Unit";"Marine";"Barracks";70;1
"Unit";"SCV";"Command Center";70;1
"Unit";"SCV";"Command Center";70;1
"Unit";"Marine";"Barracks";70;1
"Unit";"Marine";"Barracks";70;1
"Unit";"SCV";"Command Center";71;1
"Unit";"SCV";"Command Center";72;1
"Unit";"Marine";"Barracks";70;1
"Unit";"Marine";"Barracks";73;1
"Unit";"SCV";"Command Center";75;1
"Unit";"Marine";"Barracks";73;1
"Unit";"SCV";"Command Center";79;1
"Unit";"SCV";"Command Center";79;1
"Unit";"Medivac";"Starport";73;2
"Unit";"Medivac";"Starport";73;2
"Unit";"SCV";"Command Center";79;1
"Building";"Barracks";NA;70;0
"Building";"Barracks";NA;70;0
"Building";"SupplyDepot";NA;79;0
"Unit";"SCV";"Command Center";81;1
"Building";"Barracks";NA;70;0
"Unit";"SCV";"Command Center";88;1
"Unit";"Marine";"Barracks";87;1
"Unit";"Marine";"Barracks";87;1
"Unit";"Marine";"Barracks";87;1
"Building";"SupplyDepot";NA;87;0
"Unit";"SCV";"Command Center";89;1
"Unit";"Marine";"Barracks";89;1
"Unit";"SCV";"Command Center";93;1
"Building";"SupplyDepot";NA;89;0
"Unit";"Marine";"Barracks";90;1
"Upgrade";"Stimpack";"TechLab";70;0
"Unit";"SCV";"Command Center";94;1
"Building";"Armory";NA;79;0
"Unit";"SCV";"Command Center";94;1
"Unit";"Marine";"Barracks";93;1
"Unit";"Marine";"Barracks";93;1
"Upgrade";"TerranInfantryWeaponsLevel1";"EngineeringBay";70;0
"Upgrade";"TerranInfantryArmorsLevel1";"EngineeringBay";70;0
"Building";"BarracksReactor";NA;89;0
"Building";"BarracksReactor";NA;89;0
"Building";"BarracksReactor";NA;89;0
"Building";"SupplyDepot";NA;94;0
"Unit";"Marine";"Barracks";94;1
"Building";"Barracks";NA;88;0
"Unit";"Marine";"Barracks";96;1
"Unit";"Medivac";"Starport";94;2
"Building";"Barracks";NA;88;0
"Unit";"Marine";"Barracks";99;1
"Unit";"Marine";"Barracks";100;1
"Building";"Barracks";NA;89;0
"Building";"SupplyDepot";NA;101;0
"Unit";"Marine";"Barracks";101;1
"Unit";"Marine";"Barracks";101;1
"Unit";"Marine";"Barracks";101;1
"Unit";"Marine";"Barracks";101;1
"Unit";"Medivac";"Starport";99;2
"Unit";"Marine";"Barracks";102;1
"Unit";"Marine";"Barracks";102;1
"Unit";"Marine";"Barracks";102;1
"Unit";"Marine";"Barracks";102;1
"Building";"SupplyDepot";NA;103;0
"Building";"BarracksTechLab";NA;105;0
"Unit";"Marine";"Barracks";107;1
"Unit";"Marine";"Barracks";107;1
"Unit";"Marine";"Barracks";115;1
"Building";"SupplyDepot";NA;107;0
"Unit";"Marine";"Barracks";116;1
"Unit";"Marine";"Barracks";116;1
"Unit";"Marine";"Barracks";116;1
"Unit";"Marine";"Barracks";116;1
"Unit";"Marine";"Barracks";116;1
"Unit";"Marine";"Barracks";116;1
"Unit";"Marine";"Barracks";116;1
"Building";"SupplyDepot";NA;116;0
"Unit";"Medivac";"Starport";107;2
"Building";"BarracksReactor";NA;107;0
"Building";"BarracksReactor";NA;107;0
"Unit";"Marauder";"Barracks";118;2
"Unit";"Marine";"Barracks";129;1
"Unit";"Marine";"Barracks";129;1
"Unit";"Marine";"Barracks";129;1
"Unit";"Marine";"Barracks";129;1
"Unit";"Marine";"Barracks";129;1
"Unit";"Marine";"Barracks";129;1
"Unit";"Marine";"Barracks";129;1
"Unit";"Marine";"Barracks";129;1
"Unit";"Marine";"Barracks";129;1
"Unit";"Marine";"Barracks";129;1
"Unit";"Marine";"Barracks";129;1
"Unit";"Marine";"Barracks";129;1
"Unit";"Marine";"Barracks";129;1
"Unit";"Marine";"Barracks";131;1
"Unit";"Marine";"Barracks";131;1
"Unit";"SCV";"Command Center";131;1
"Unit";"SCV";"Command Center";131;1
"Unit";"Marine";"Barracks";131;1
"Unit";"Medivac";"Starport";131;2
"Unit";"Medivac";"Starport";131;2
"Unit";"Marine";"Barracks";132;1
"Unit";"Marine";"Barracks";133;1
"Unit";"Marine";"Barracks";134;1
"Unit";"Marine";"Barracks";134;1
"Unit";"Marine";"Barracks";136;1
"Building";"SupplyDepot";NA;132;0
"Unit";"Marine";"Barracks";148;1
"Unit";"Marine";"Barracks";148;1
"Unit";"Marine";"Barracks";148;1
"Unit";"Marauder";"Barracks";148;2
"Unit";"Marauder";"Barracks";148;2
"Unit";"Marine";"Barracks";149;1
"Unit";"Marine";"Barracks";149;1
"Unit";"Marine";"Barracks";149;1
"Unit";"Marine";"Barracks";149;1
"Unit";"Marine";"Barracks";149;1
"Unit";"Marine";"Barracks";153;1
"Unit";"Marine";"Barracks";154;1
"Unit";"Marine";"Barracks";155;1
"Unit";"Marine";"Barracks";155;1
"Unit";"Marine";"Barracks";157;1
"Unit";"Marine";"Barracks";165;1
"Unit";"Marine";"Barracks";165;1
"Unit";"Marine";"Barracks";165;1
"Unit";"Marauder";"Barracks";161;2
"Unit";"Marine";"Barracks";165;1
"Unit";"Marine";"Barracks";170;1
"Unit";"Marine";"Barracks";170;1
"Unit";"Marauder";"Barracks";165;2
"Building";"SupplyDepot";NA;175;0
"Building";"SupplyDepot";NA;175;0
"Unit";"Marine";"Barracks";175;1
"Unit";"Marine";"Barracks";175;1
"Unit";"Marine";"Barracks";175;1
"Unit";"Marine";"Barracks";175;1
"Unit";"Marine";"Barracks";175;1
"Unit";"Marine";"Barracks";175;1
"Unit";"Medivac";"Starport";170;2
"Unit";"Medivac";"Starport";170;2
"Unit";"Marauder";"Barracks";175;2
"Unit";"Marine";"Barracks";175;1
"Unit";"Marine";"Barracks";176;1
"Building";"SupplyDepot";NA;175;0
"Upgrade";"TerranInfantryWeaponsLevel2";"EngineeringBay";125;0
"Upgrade";"TerranInfantryArmorsLevel2";"EngineeringBay";127;0
"Unit";"Marine";"Barracks";185;1
"Unit";"Marine";"Barracks";185;1
"Unit";"Marine";"Barracks";185;1
"Unit";"Marauder";"Barracks";185;2
"Unit";"Marauder";"Barracks";185;2
"Unit";"Marine";"Barracks";199;1
"Unit";"Marine";"Barracks";199;1
"Unit";"Marine";"Barracks";199;1
"Unit";"Marine";"Barracks";199;1
"Unit";"Marine";"Barracks";199;1
"Unit";"Marine";"Barracks";199;1
"Unit";"Marine";"Barracks";199;1
"Unit";"Marine";"Barracks";199;1
"Unit";"Marine";"Barracks";199;1
"Unit";"Marauder";"Barracks";199;2
"Building";"CommandCenter";NA;158;0
"Unit";"Marine";"Barracks";199;1
"Unit";"Marine";"Barracks";199;1
"Unit";"Marine";"Barracks";202;1
"Unit";"Marine";"Barracks";202;1
"Unit";"Medivac";"Starport";199;2
"Unit";"Medivac";"Starport";199;2
"Unit";"Marauder";"Barracks";202;2
"Unit";"Marine";"Barracks";215;1
"Unit";"Marine";"Barracks";215;1
"Unit";"Marine";"Barracks";215;1
"Unit";"Marine";"Barracks";217;1
"Building";"Refinery";NA;220;0
"Building";"Refinery";NA;221;0
"Unit";"Marine";"Barracks";230;1
"Unit";"Marine";"Barracks";230;1
"Building";"Starport";NA;219;0
"Building";"Starport";NA;220;0
"Unit";"Marine";"Barracks";233;1
"Unit";"Marine";"Barracks";233;1
"Building";"StarportTechLab";NA;233;0
"Building";"StarportTechLab";NA;233;0
"Unit";"Marine";"Barracks";233;1
"Unit";"Marine";"Barracks";233;1
"Unit";"Marine";"Barracks";233;1
"Unit";"Marine";"Barracks";233;1
"Unit";"Marauder";"Barracks";233;2
"Unit";"Marine";"Barracks";235;1
"Unit";"Marine";"Barracks";235;1
"Unit";"Marine";"Barracks";235;1
"Unit";"Marine";"Barracks";235;1
"Unit";"Marine";"Barracks";235;1
"Unit";"Marine";"Barracks";235;1
"Unit";"Marine";"Barracks";235;1
"Unit";"Marine";"Barracks";235;1
"Unit";"Marine";"Barracks";235;1
"Unit";"Marauder";"Barracks";235;2
