"Type";"UnitName";"OnBuilding";"TotalSupply";"Supply"
"Unit";"SCV";"Command Center";12;1
"Unit";"SCV";"Command Center";12;1
"Unit";"SCV";"Command Center";13;1
"Building";"SupplyDepot";NA;13;0
"Unit";"SCV";"Command Center";15;1
"Building";"Refinery";NA;14;0
"Unit";"SCV";"Command Center";15;1
"Unit";"SCV";"Command Center";16;1
"Building";"Barracks";NA;15;0
"Unit";"SCV";"Command Center";18;1
"Unit";"Reaper";"Barracks";19;1
"Unit";"SCV";"Command Center";19;1
"Unit";"SCV";"Command Center";20;1
"Building";"SupplyDepot";NA;20;0
"Unit";"SCV";"Command Center";21;1
"Building";"Factory";NA;19;0
"Building";"Refinery";NA;21;0
"Building";"BarracksReactor";NA;20;0
"Unit";"SCV";"Command Center";22;1
"Building";"CommandCenter";NA;19;0
"Unit";"SCV";"Command Center";24;1
"Building";"BarracksTechLab";NA;24;0
"Unit";"Hellion";"Factory";24;2
"Unit";"Hellion";"Factory";24;2
"Unit";"SCV";"Command Center";25;1
"Building";"Starport";NA;23;0
"Unit";"SCV";"Command Center";29;1
"Unit";"SCV";"Command Center";30;1
"Unit";"SCV";"Command Center";31;1
"Unit";"Hellion";"Factory";30;2
"Unit";"Hellion";"Factory";30;2
"Unit";"SCV";"Command Center";31;1
"Unit";"SCV";"Command Center";32;1
"Unit";"SCV";"Command Center";39;1
"Unit";"SCV";"Command Center";39;1
"Building";"BarracksReactor";NA;31;0
"Unit";"Hellion";"Factory";38;2
"Unit";"Hellion";"Factory";38;2
"Building";"SupplyDepot";NA;45;0
"Building";"SupplyDepot";NA;45;0
"Building";"FactoryTechLab";NA;45;0
"Unit";"SCV";"Command Center";45;1
"Unit";"SCV";"Command Center";45;1
"Unit";"Marine";"Barracks";45;1
"Unit";"Marine";"Barracks";45;1
"Unit";"SCV";"Command Center";45;1
"Unit";"SCV";"Command Center";46;1
"Building";"EngineeringBay";NA;45;0
"Building";"EngineeringBay";NA;45;0
"Unit";"SCV";"Command Center";49;1
"Unit";"SCV";"Command Center";50;1
"Unit";"Marine";"Barracks";49;1
"Unit";"Marine";"Barracks";49;1
"Building";"CommandCenter";NA;41;0
"Unit";"Banshee";"Starport";45;3
"Unit";"SCV";"Command Center";51;1
"Unit";"SCV";"Command Center";52;1
"Unit";"Marine";"Barracks";55;1
"Unit";"Marine";"Barracks";55;1
"Unit";"SCV";"Command Center";60;1
"Unit";"SCV";"Command Center";60;1
"Building";"Barracks";NA;49;0
"Building";"Refinery";NA;60;0
"Building";"Barracks";NA;51;0
"Building";"Refinery";NA;60;0
"Unit";"SCV";"Command Center";62;1
"Unit";"SCV";"Command Center";64;1
"Unit";"Marine";"Barracks";63;1
"Unit";"Marine";"Barracks";63;1
"Unit";"SCV";"Command Center";64;1
"Unit";"SCV";"Command Center";66;1
"Unit";"SCV";"Command Center";66;1
"Unit";"SCV";"Command Center";68;1
"Unit";"SCV";"Command Center";69;1
"Building";"StarportReactor";NA;65;0
"Unit";"Marine";"Barracks";71;1
"Building";"BarracksReactor";NA;66;0
"Building";"Armory";NA;64;0
"Building";"SupplyDepot";NA;73;0
"Building";"Barracks";NA;69;0
"Building";"Barracks";NA;70;0
"Unit";"SCV";"Command Center";74;1
"Building";"SupplyDepot";NA;74;0
"Building";"SupplyDepot";NA;74;0
"Unit";"SCV";"Command Center";74;1
"Building";"SupplyDepot";NA;74;0
"Unit";"Marine";"Barracks";74;1
"Unit";"Marine";"Barracks";74;1
"Unit";"Marine";"Barracks";74;1
"Building";"Armory";NA;71;0
"Upgrade";"TerranInfantryWeaponsLevel1";"EngineeringBay";64;0
"Upgrade";"TerranInfantryArmorsLevel1";"EngineeringBay";64;0
"Unit";"SCV";"Command Center";75;1
"Unit";"SCV";"Command Center";75;1
"Unit";"SCV";"Command Center";75;1
"Unit";"Marine";"Barracks";75;1
"Unit";"Marine";"Barracks";75;1
"Unit";"Marine";"Barracks";75;1
"Unit";"Marine";"Barracks";75;1
"Building";"SupplyDepot";NA;76;0
"Unit";"Marine";"Barracks";79;1
"Unit";"Marine";"Barracks";79;1
"Unit";"Marine";"Barracks";79;1
"Building";"SupplyDepot";NA;79;0
"Building";"SupplyDepot";NA;79;0
"Building";"BarracksReactor";NA;75;0
"Unit";"Marine";"Barracks";86;1
"Unit";"Marine";"Barracks";86;1
"Unit";"Marine";"Barracks";86;1
"Unit";"Marine";"Barracks";86;1
"Unit";"Medivac";"Starport";79;2
"Unit";"Medivac";"Starport";79;2
"Building";"Factory";NA;75;0
"Unit";"SCV";"Command Center";89;1
"Unit";"SCV";"Command Center";89;1
"Unit";"SCV";"Command Center";89;1
"Building";"SupplyDepot";NA;89;0
"Unit";"Marine";"Barracks";89;1
"Unit";"Marine";"Barracks";89;1
"Unit";"Marine";"Barracks";89;1
"Building";"Refinery";NA;89;0
"Unit";"SCV";"Command Center";97;1
"Unit";"SCV";"Command Center";98;1
"Building";"Refinery";NA;89;0
"Building";"FactoryTechLab";NA;99;0
"Unit";"Marine";"Barracks";100;1
"Unit";"Marine";"Barracks";100;1
"Unit";"Marine";"Barracks";100;1
"Building";"SupplyDepot";NA;100;0
"Building";"SupplyDepot";NA;101;0
"Building";"SupplyDepot";NA;103;0
"Unit";"SCV";"Command Center";105;1
"Unit";"SCV";"Command Center";105;1
"Unit";"SCV";"Command Center";105;1
"Unit";"Marine";"Barracks";105;1
"Unit";"Marine";"Barracks";105;1
"Unit";"Marine";"Barracks";105;1
"Unit";"Marine";"Barracks";105;1
"Upgrade";"Stimpack";"TechLab";74;0
"Building";"SupplyDepot";NA;103;0
"Unit";"Marine";"Barracks";111;1
"Unit";"Marine";"Barracks";111;1
"Unit";"Marine";"Barracks";115;1
"Unit";"Marine";"Barracks";115;1
"Unit";"Marine";"Barracks";115;1
"Unit";"Marine";"Barracks";115;1
"Unit";"Marine";"Barracks";115;1
"Unit";"Marine";"Barracks";115;1
"Unit";"Marine";"Barracks";115;1
"Unit";"Marine";"Barracks";115;1
"Unit";"Marine";"Barracks";117;1
"Unit";"Marine";"Barracks";117;1
"Unit";"SCV";"Command Center";122;1
"Unit";"SCV";"Command Center";122;1
"Unit";"SCV";"Command Center";122;1
"Upgrade";"TerranVehicleWeaponsLevel1";"Armory";89;0
"Unit";"Medivac";"Starport";117;2
"Unit";"Medivac";"Starport";117;2
"Unit";"Marine";"Barracks";125;1
"Unit";"Marine";"Barracks";125;1
"Unit";"SCV";"Command Center";130;1
"Unit";"Marine";"Barracks";126;1
"Unit";"Marine";"Barracks";126;1
"Unit";"Marine";"Barracks";126;1
"Unit";"Marine";"Barracks";126;1
"Unit";"Marine";"Barracks";126;1
"Building";"SupplyDepot";NA;130;0
"Building";"CommandCenter";NA;111;0
"Building";"SupplyDepot";NA;134;0
"Unit";"Marine";"Barracks";142;1
"Unit";"Marine";"Barracks";142;1
"Unit";"Marine";"Barracks";142;1
"Unit";"Marine";"Barracks";142;1
"Unit";"Marine";"Barracks";142;1
"Unit";"Marine";"Barracks";142;1
"Unit";"Medivac";"Starport";130;2
"Unit";"Medivac";"Starport";132;2
"Unit";"Marine";"Barracks";142;1
"Unit";"Marine";"Barracks";142;1
"Unit";"Marine";"Barracks";142;1
"Upgrade";"TerranInfantryWeaponsLevel2";"EngineeringBay";108;0
"Building";"SupplyDepot";NA;142;0
"Building";"SupplyDepot";NA;142;0
"Building";"Barracks";NA;130;0
"Building";"Barracks";NA;134;0
"Unit";"Marine";"Barracks";148;1
"Unit";"Marine";"Barracks";148;1
"Unit";"Marine";"Barracks";148;1
"Unit";"Marine";"Barracks";152;1
"Unit";"Marine";"Barracks";152;1
"Unit";"Marine";"Barracks";152;1
"Unit";"Medivac";"Starport";152;2
"Unit";"Marine";"Barracks";161;1
"Unit";"Marine";"Barracks";161;1
"Building";"BarracksTechLab";NA;163;0
"Building";"BarracksTechLab";NA;163;0
"Unit";"Marine";"Barracks";163;1
"Unit";"Marine";"Barracks";163;1
"Unit";"Marine";"Barracks";163;1
"Unit";"Marine";"Barracks";163;1
"Building";"SupplyDepot";NA;165;0
"Building";"SupplyDepot";NA;165;0
"Building";"SupplyDepot";NA;165;0
"Unit";"Marine";"Barracks";165;1
"Unit";"Medivac";"Starport";163;2
"Unit";"Medivac";"Starport";163;2
