"Type";"UnitName";"OnBuilding";"TotalSupply";"Supply"
"Unit";"SCV";"Command Center";12;1
"Unit";"SCV";"Command Center";12;1
"Unit";"SCV";"Command Center";13;1
"Building";"SupplyDepot";NA;13;0
"Building";"Refinery";NA;14;0
"Unit";"SCV";"Command Center";15;1
"Unit";"SCV";"Command Center";15;1
"Unit";"SCV";"Command Center";16;1
"Unit";"SCV";"Command Center";17;1
"Building";"Barracks";NA;15;0
"Unit";"SCV";"Command Center";18;1
"Unit";"Marine";"Barracks";20;1
"Building";"SupplyDepot";NA;20;0
"Building";"Factory";NA;19;0
"Unit";"SCV";"Command Center";21;1
"Unit";"SCV";"Command Center";22;1
"Building";"BarracksReactor";NA;21;0
"Building";"SupplyDepot";NA;21;0
"Unit";"SCV";"Command Center";22;1
"Unit";"SCV";"Command Center";23;1
"Unit";"Hellion";"Factory";23;2
"Unit";"Hellion";"Factory";23;2
"Building";"SupplyDepot";NA;23;0
"Unit";"SCV";"Command Center";25;1
"Unit";"Hellion";"Factory";25;2
"Unit";"Hellion";"Factory";27;2
"Building";"CommandCenter";NA;21;0
"Unit";"SCV";"Command Center";30;1
"Building";"Refinery";NA;30;0
"Building";"Armory";NA;24;0
"Unit";"Hellion";"Factory";30;2
"Unit";"Hellion";"Factory";32;2
"Building";"Refinery";NA;39;0
"Unit";"SCV";"Command Center";39;1
"Unit";"SCV";"Command Center";39;1
"Unit";"SCV";"Command Center";39;1
"Building";"Refinery";NA;39;0
"Unit";"Cyclone";"Factory";39;3
"Unit";"Cyclone";"Factory";39;3
"Unit";"SCV";"Command Center";42;1
"Unit";"SCV";"Command Center";42;1
"Unit";"SCV";"Command Center";48;1
"Unit";"SCV";"Command Center";49;1
"Unit";"Cyclone";"Factory";48;3
"Unit";"Cyclone";"Factory";49;3
"Unit";"SCV";"Command Center";50;1
"Unit";"SCV";"Command Center";51;1
"Unit";"SCV";"Command Center";58;1
"Unit";"SCV";"Command Center";60;1
"Building";"Factory";NA;49;0
"Unit";"SCV";"Command Center";60;1
"Unit";"SCV";"Command Center";61;1
"Building";"Factory";NA;50;0
"Unit";"Cyclone";"Factory";60;3
"Building";"SupplyDepot";NA;60;0
"Unit";"Cyclone";"Factory";60;3
"Unit";"SCV";"Command Center";62;1
"Unit";"SCV";"Command Center";63;1
"Upgrade";"TerranVehicleWeaponsLevel1";"Armory";42;0
"Unit";"SCV";"Command Center";72;1
"Building";"FactoryTechLab";NA;70;0
"Building";"FactoryTechLab";NA;70;0
"Unit";"SCV";"Command Center";72;1
"Unit";"SCV";"Command Center";72;1
"Unit";"Cyclone";"Factory";72;3
"Unit";"Cyclone";"Factory";72;3
"Building";"SupplyDepot";NA;73;0
"Building";"CommandCenter";NA;64;0
"Unit";"SCV";"Command Center";81;1
"Unit";"SCV";"Command Center";81;1
"Unit";"SCV";"Command Center";81;1
"Unit";"SCV";"Command Center";83;1
"Unit";"Cyclone";"Factory";81;3
"Unit";"Cyclone";"Factory";81;3
"Unit";"Cyclone";"Factory";81;3
"Unit";"Cyclone";"Factory";81;3
"Building";"SupplyDepot";NA;83;0
"Building";"SupplyDepot";NA;83;0
"Building";"SupplyDepot";NA;83;0
"Unit";"SCV";"Command Center";83;1
"Unit";"SCV";"Command Center";84;1
"Unit";"SCV";"Command Center";97;1
"Unit";"SCV";"Command Center";99;1
"Building";"SupplyDepot";NA;91;0
"Unit";"SCV";"Command Center";99;1
"Unit";"Hellion";"Factory";97;2
"Unit";"Hellion";"Factory";97;2
"Unit";"Hellion";"Factory";97;2
"Unit";"Hellion";"Factory";97;2
"Unit";"SCV";"Command Center";99;1
"Unit";"SCV";"Command Center";100;1
"Building";"Starport";NA;91;0
"Unit";"SCV";"Command Center";101;1
"Building";"Refinery";NA;101;0
"Unit";"SCV";"Command Center";110;1
"Building";"Refinery";NA;101;0
"Unit";"SCV";"Command Center";111;1
"Unit";"Hellion";"Factory";108;2
"Unit";"Hellion";"Factory";110;2
"Unit";"Hellion";"Factory";110;2
"Unit";"Hellion";"Factory";110;2
"Unit";"SCV";"Command Center";112;1
"Building";"StarportTechLab";NA;113;0
"Unit";"SCV";"Command Center";113;1
"Unit";"SCV";"Command Center";114;1
"Upgrade";"TerranVehicleWeaponsLevel2";"Armory";81;0
"Building";"SupplyDepot";NA;124;0
"Unit";"SCV";"Command Center";126;1
"Unit";"Hellion";"Factory";126;2
"Unit";"Hellion";"Factory";126;2
"Unit";"SCV";"Command Center";126;1
"Building";"Factory";NA;124;0
"Building";"Factory";NA;124;0
"Building";"EngineeringBay";NA;126;0
"Unit";"Raven";"Starport";124;2
"Unit";"Thor";"Factory";126;6
"Unit";"Thor";"Factory";126;6
"Unit";"Hellion";"Factory";132;2
"Unit";"Hellion";"Factory";132;2
"Building";"FactoryTechLab";NA;134;0
"Building";"FactoryTechLab";NA;134;0
"Unit";"SCV";"Command Center";150;1
"Building";"MissileTurret";NA;150;0
"Building";"MissileTurret";NA;150;0
"Building";"MissileTurret";NA;150;0
"Building";"MissileTurret";NA;150;0
"Building";"MissileTurret";NA;150;0
"Building";"MissileTurret";NA;150;0
"Building";"MissileTurret";NA;150;0
"Building";"MissileTurret";NA;150;0
"Building";"MissileTurret";NA;150;0
"Building";"MissileTurret";NA;151;0
"Building";"MissileTurret";NA;151;0
"Unit";"Thor";"Factory";134;6
"Unit";"Thor";"Factory";140;6
"Unit";"Raven";"Starport";150;2
"Unit";"SCV";"Command Center";163;1
"Unit";"Thor";"Factory";151;6
"Building";"SupplyDepot";NA;165;0
"Building";"SupplyDepot";NA;165;0
"Unit";"Thor";"Factory";163;6
"Unit";"Thor";"Factory";163;6
"Unit";"Thor";"Factory";163;6
"Building";"FactoryReactor";NA;163;0
"Unit";"Hellion";"Factory";190;2
"Unit";"Hellion";"Factory";190;2
"Unit";"SCV";"Command Center";190;1
"Building";"SupplyDepot";NA;190;0
"Building";"SupplyDepot";NA;190;0
