"Type";"UnitName";"OnBuilding";"TotalSupply";"Supply"
"Unit";"SCV";"Command Center";12;1
"Unit";"SCV";"Command Center";12;1
"Unit";"SCV";"Command Center";13;1
"Building";"SupplyDepot";NA;13;0
"Building";"Refinery";NA;14;0
"Unit";"SCV";"Command Center";15;1
"Unit";"SCV";"Command Center";15;1
"Unit";"SCV";"Command Center";16;1
"Unit";"SCV";"Command Center";17;1
"Building";"Barracks";NA;15;0
"Unit";"Reaper";"Barracks";19;1
"Unit";"SCV";"Command Center";19;1
"Unit";"SCV";"Command Center";21;1
"Building";"SupplyDepot";NA;20;0
"Unit";"SCV";"Command Center";21;1
"Building";"Refinery";NA;21;0
"Building";"Factory";NA;19;0
"Building";"BarracksReactor";NA;20;0
"Unit";"SCV";"Command Center";22;1
"Building";"CommandCenter";NA;19;0
"Unit";"SCV";"Command Center";23;1
"Building";"BarracksTechLab";NA;24;0
"Unit";"Hellion";"Factory";24;2
"Unit";"Hellion";"Factory";24;2
"Unit";"SCV";"Command Center";24;1
"Building";"Starport";NA;23;0
"Unit";"SCV";"Command Center";29;1
"Unit";"Hellion";"Factory";25;2
"Unit";"Hellion";"Factory";30;2
"Unit";"SCV";"Command Center";30;1
"Unit";"SCV";"Command Center";30;1
"Unit";"SCV";"Command Center";37;1
"Unit";"SCV";"Command Center";37;1
"Building";"SupplyDepot";NA;37;0
"Unit";"SCV";"Command Center";37;1
"Unit";"Banshee";"Starport";31;3
"Unit";"Hellion";"Factory";37;2
"Unit";"SCV";"Command Center";39;1
"Unit";"Hellion";"Factory";37;2
"Unit";"Marine";"Barracks";39;1
"Unit";"SCV";"Command Center";45;1
"Unit";"SCV";"Command Center";46;1
"Building";"SupplyDepot";NA;40;0
"Unit";"Marine";"Barracks";49;1
"Unit";"SCV";"Command Center";51;1
"Unit";"SCV";"Command Center";51;1
"Unit";"Hellion";"Factory";51;2
"Unit";"Banshee";"Starport";40;3
"Unit";"SCV";"Command Center";52;1
"Unit";"SCV";"Command Center";53;1
"Building";"BarracksTechLab";NA;54;0
"Unit";"SCV";"Command Center";59;1
"Unit";"SCV";"Command Center";61;1
"Unit";"SCV";"Command Center";62;1
"Unit";"Marine";"Barracks";62;1
"Building";"Bunker";NA;61;0
"Unit";"SCV";"Command Center";64;1
"Unit";"SCV";"Command Center";65;1
"Unit";"Banshee";"Starport";61;3
"Building";"SupplyDepot";NA;63;0
"Unit";"SCV";"Command Center";65;1
"Unit";"SCV";"Command Center";67;1
"Building";"CommandCenter";NA;54;0
"Building";"Barracks";NA;62;0
"Building";"Barracks";NA;62;0
"Unit";"Marine";"Barracks";66;1
"Building";"EngineeringBay";NA;65;0
"Unit";"SCV";"Command Center";70;1
"Building";"EngineeringBay";NA;66;0
"Unit";"SCV";"Command Center";71;1
"Building";"Refinery";NA;72;0
"Building";"Refinery";NA;72;0
"Unit";"SCV";"Command Center";74;1
"Building";"SupplyDepot";NA;72;0
"Unit";"SCV";"Command Center";75;1
"Unit";"SCV";"Command Center";75;1
"Unit";"Marine";"Barracks";75;1
"Building";"SupplyDepot";NA;74;0
"Unit";"SCV";"Command Center";76;1
"Building";"BarracksReactor";NA;73;0
"Building";"StarportReactor";NA;73;0
"Unit";"Marine";"Barracks";77;1
"Unit";"SCV";"Command Center";79;1
"Unit";"Marine";"Barracks";79;1
"Unit";"Marine";"Barracks";79;1
"Building";"MissileTurret";NA;79;0
"Unit";"SCV";"Command Center";81;1
"Building";"MissileTurret";NA;80;0
"Unit";"Marine";"Barracks";80;1
"Unit";"Marine";"Barracks";81;1
"Unit";"Marine";"Barracks";81;1
"Unit";"Marine";"Barracks";82;1
"Unit";"SCV";"Command Center";84;1
"Unit";"Marine";"Barracks";83;1
"Unit";"SCV";"Command Center";84;1
"Upgrade";"Stimpack";"TechLab";70;0
"Unit";"Marine";"Barracks";85;1
"Unit";"SCV";"Command Center";88;1
"Unit";"SCV";"Command Center";89;1
"Unit";"SCV";"Command Center";91;1
"Unit";"Marine";"Barracks";88;1
"Unit";"Marine";"Barracks";88;1
"Unit";"Medivac";"Starport";85;2
"Unit";"Medivac";"Starport";85;2
"Unit";"SCV";"Command Center";93;1
"Unit";"Marine";"Barracks";92;1
"Unit";"SCV";"Command Center";94;1
"Unit";"Marine";"Barracks";92;1
"Unit";"Marine";"Barracks";92;1
"Unit";"SCV";"Command Center";96;1
"Building";"SupplyDepot";NA;92;0
"Building";"SupplyDepot";NA;92;0
"Unit";"SCV";"Command Center";102;1
"Unit";"SCV";"Command Center";104;1
"Unit";"Marine";"Barracks";105;1
"Unit";"SCV";"Command Center";108;1
"Unit";"Marine";"Barracks";108;1
"Unit";"Marine";"Barracks";108;1
"Unit";"SCV";"Command Center";110;1
"Unit";"SCV";"Command Center";110;1
"Unit";"Marine";"Barracks";110;1
"Building";"SupplyDepot";NA;109;0
"Unit";"SCV";"Command Center";111;1
"Building";"SupplyDepot";NA;110;0
"Unit";"Marine";"Barracks";110;1
"Upgrade";"TerranInfantryWeaponsLevel1";"EngineeringBay";81;0
"Unit";"Medivac";"Starport";108;2
"Unit";"Medivac";"Starport";108;2
"Unit";"Marine";"Barracks";112;1
"Unit";"SCV";"Command Center";114;1
"Upgrade";"TerranInfantryArmorsLevel1";"EngineeringBay";84;0
"Building";"Barracks";NA;98;0
"Building";"SupplyDepot";NA;111;0
"Unit";"Marine";"Barracks";112;1
"Building";"Barracks";NA;98;0
"Building";"Armory";NA;102;0
"Unit";"SCV";"Command Center";117;1
"Unit";"Marine";"Barracks";115;1
"Unit";"Marine";"Barracks";117;1
"Unit";"Marine";"Barracks";118;1
"Building";"SupplyDepot";NA;119;0
"Unit";"Marine";"Barracks";123;1
"Building";"Refinery";NA;119;0
"Building";"Refinery";NA;123;0
"Unit";"SCV";"Command Center";129;1
"Unit";"Marine";"Barracks";127;1
"Unit";"Medivac";"Starport";119;2
"Unit";"Marine";"Barracks";130;1
"Unit";"Marine";"Barracks";130;1
"Unit";"Marine";"Barracks";130;1
"Unit";"Marine";"Barracks";130;1
"Unit";"Medivac";"Starport";127;2
"Unit";"SCV";"Command Center";133;1
"Unit";"SCV";"Command Center";133;1
"Unit";"SCV";"Command Center";133;1
"Unit";"Marine";"Barracks";131;1
"Unit";"Marine";"Barracks";135;1
"Unit";"Marine";"Barracks";136;1
"Building";"BarracksReactor";NA;130;0
"Building";"BarracksReactor";NA;130;0
"Unit";"Marine";"Barracks";139;1
"Unit";"Marine";"Barracks";139;1
"Unit";"Medivac";"Starport";133;2
"Unit";"Marine";"Barracks";144;1
"Unit";"Marine";"Barracks";145;1
"Unit";"Marine";"Barracks";146;1
"Unit";"Marine";"Barracks";147;1
"Unit";"Marine";"Barracks";147;1
"Unit";"Marine";"Barracks";147;1
"Unit";"Marine";"Barracks";148;1
"Unit";"Marine";"Barracks";149;1
"Unit";"Marine";"Barracks";149;1
"Unit";"Medivac";"Starport";145;2
"Unit";"Marine";"Barracks";151;1
"Unit";"Marine";"Barracks";152;1
"Unit";"Marine";"Barracks";153;1
"Building";"SupplyDepot";NA;152;0
"Building";"SupplyDepot";NA;152;0
"Unit";"Marine";"Barracks";156;1
"Unit";"Marine";"Barracks";156;1
"Building";"SupplyDepot";NA;154;0
"Unit";"SCV";"Command Center";162;1
"Unit";"Marine";"Barracks";156;1
"Unit";"Marine";"Barracks";157;1
"Unit";"Marine";"Barracks";158;1
"Unit";"Marine";"Barracks";159;1
"Building";"Factory";NA;147;0
"Unit";"Marine";"Barracks";162;1
"Building";"Barracks";NA;147;0
"Building";"Barracks";NA;147;0
"Unit";"Marine";"Barracks";163;1
"Unit";"Marine";"Barracks";165;1
"Unit";"Marine";"Barracks";165;1
"Unit";"Marine";"Barracks";166;1
"Unit";"Marine";"Barracks";168;1
"Unit";"Marine";"Barracks";169;1
"Unit";"Marine";"Barracks";170;1
"Unit";"Marine";"Barracks";171;1
"Unit";"Marine";"Barracks";173;1
"Building";"BarracksTechLab";NA;173;0
"Unit";"Medivac";"Starport";165;2
"Unit";"Medivac";"Starport";165;2
"Unit";"Marine";"Barracks";173;1
"Unit";"Marine";"Barracks";174;1
"Unit";"Marine";"Barracks";175;1
"Unit";"Marine";"Barracks";177;1
"Unit";"Marine";"Barracks";179;1
"Unit";"Marine";"Barracks";179;1
"Building";"CommandCenter";NA;151;0
"Building";"FactoryTechLab";NA;182;0
"Building";"BarracksTechLab";NA;182;0
"Building";"SupplyDepot";NA;182;0
"Upgrade";"TerranInfantryWeaponsLevel2";"EngineeringBay";145;0
"Upgrade";"TerranInfantryArmorsLevel2";"EngineeringBay";145;0
"Unit";"Marine";"Barracks";187;1
"Unit";"Marine";"Barracks";187;1
"Unit";"Marine";"Barracks";189;1
"Unit";"Marine";"Barracks";189;1
"Unit";"Marine";"Barracks";192;1
"Unit";"Marine";"Barracks";192;1
"Unit";"Marine";"Barracks";192;1
"Unit";"Marine";"Barracks";192;1
"Unit";"Marine";"Barracks";192;1
"Unit";"Marine";"Barracks";192;1
"Unit";"Marine";"Barracks";192;1
"Unit";"Medivac";"Starport";192;2
"Unit";"Medivac";"Starport";192;2
"Unit";"Marine";"Barracks";194;1
"Unit";"Marine";"Barracks";194;1
"Unit";"Marine";"Barracks";194;1
"Unit";"Marine";"Barracks";195;1
"Unit";"Marine";"Barracks";196;1
"Unit";"Marine";"Barracks";197;1
"Unit";"Marine";"Barracks";202;1
"Unit";"SCV";"Command Center";209;1
"Unit";"SCV";"Command Center";209;1
"Unit";"Marine";"Barracks";203;1
"Unit";"Marine";"Barracks";203;1
"Unit";"Marine";"Barracks";203;1
"Upgrade";"TerranVehicleWeaponsLevel1";"Armory";172;0
"Unit";"Marine";"Barracks";209;1
"Unit";"Marauder";"Barracks";209;2
"Unit";"Marine";"Barracks";213;1
"Building";"Refinery";NA;213;0
"Building";"Refinery";NA;213;0
"Building";"SensorTower";NA;219;0
"Unit";"Marauder";"Barracks";217;2
"Unit";"Marine";"Barracks";219;1
"Unit";"Marauder";"Barracks";219;2
"Unit";"Marine";"Barracks";223;1
"Unit";"Marine";"Barracks";223;1
"Unit";"Marine";"Barracks";223;1
"Unit";"Marine";"Barracks";223;1
"Building";"BarracksTechLab";NA;223;0
"Building";"Starport";NA;219;0
"Unit";"Marauder";"Barracks";226;2
"Unit";"SCV";"Command Center";232;1
"Building";"FusionCore";NA;220;0
"Building";"StarportTechLab";NA;232;0
"Unit";"Liberator";"Starport";225;3
"Building";"GhostAcademy";NA;232;0
"Unit";"Liberator";"Starport";230;3
"Unit";"Marauder";"Barracks";235;2
"Unit";"Marine";"Barracks";243;1
"Unit";"Marauder";"Barracks";243;2
"Unit";"Marauder";"Barracks";243;2
"Unit";"Marine";"Barracks";243;1
"Building";"CommandCenter";NA;232;0
"Unit";"Marauder";"Barracks";243;2
"Unit";"Marine";"Barracks";243;1
"Unit";"Marine";"Barracks";243;1
"Unit";"Marine";"Barracks";243;1
"Unit";"Marauder";"Barracks";243;2
"Unit";"Marine";"Barracks";249;1
"Unit";"Marauder";"Barracks";249;2
"Unit";"Marine";"Barracks";251;1
"Unit";"Liberator";"Starport";243;3
"Unit";"Liberator";"Starport";243;3
"Unit";"Liberator";"Starport";243;3
"Upgrade";"TerranInfantryWeaponsLevel3";"EngineeringBay";228;0
"Upgrade";"TerranInfantryArmorsLevel3";"EngineeringBay";228;0
"Unit";"Marine";"Barracks";256;1
"Unit";"Marine";"Barracks";256;1
"Unit";"Marine";"Barracks";256;1
"Unit";"Marine";"Barracks";256;1
"Unit";"Marine";"Barracks";256;1
"Unit";"Marine";"Barracks";256;1
