"Type";"UnitName";"OnBuilding";"TotalSupply";"Supply"
"Unit";"SCV";"Command Center";12;1
"Unit";"SCV";"Command Center";12;1
"Unit";"SCV";"Command Center";13;1
"Building";"SupplyDepot";NA;13;0
"Unit";"SCV";"Command Center";15;1
"Unit";"SCV";"Command Center";15;1
"Building";"Refinery";NA;15;0
"Unit";"SCV";"Command Center";16;1
"Building";"Barracks";NA;15;0
"Unit";"SCV";"Command Center";17;1
"Unit";"Reaper";"Barracks";18;1
"Unit";"SCV";"Command Center";19;1
"Building";"SupplyDepot";NA;19;0
"Unit";"SCV";"Command Center";20;1
"Unit";"SCV";"Command Center";21;1
"Building";"BarracksReactor";NA;20;0
"Unit";"SCV";"Command Center";22;1
"Building";"Refinery";NA;22;0
"Building";"Bunker";NA;22;0
"Building";"CommandCenter";NA;19;0
"Unit";"SCV";"Command Center";23;1
"Unit";"Marine";"Barracks";23;1
"Unit";"Marine";"Barracks";23;1
"Building";"Factory";NA;22;0
"Unit";"SCV";"Command Center";24;1
"Unit";"SCV";"Command Center";27;1
"Unit";"SCV";"Command Center";29;1
"Unit";"SCV";"Command Center";29;1
"Unit";"SCV";"Command Center";29;1
"Unit";"SCV";"Command Center";31;1
"Building";"Starport";NA;28;0
"Unit";"Hellion";"Factory";30;2
"Unit";"Hellion";"Factory";30;2
"Unit";"SCV";"Command Center";31;1
"Building";"BarracksTechLab";NA;31;0
"Unit";"SCV";"Command Center";32;1
"Unit";"SCV";"Command Center";37;1
"Building";"SupplyDepot";NA;33;0
"Building";"CommandCenter";NA;28;0
"Unit";"Hellion";"Factory";38;2
"Unit";"Hellion";"Factory";38;2
"Unit";"SCV";"Command Center";40;1
"Unit";"SCV";"Command Center";40;1
"Building";"SupplyDepot";NA;40;0
"Unit";"SCV";"Command Center";46;1
"Unit";"SCV";"Command Center";46;1
"Unit";"Hellion";"Factory";44;2
"Building";"Armory";NA;38;0
"Unit";"Hellion";"Factory";44;2
"Unit";"Banshee";"Starport";40;3
"Unit";"Marine";"Barracks";46;1
"Unit";"SCV";"Command Center";46;1
"Unit";"SCV";"Command Center";47;1
"Building";"SupplyDepot";NA;50;0
"Unit";"Hellion";"Factory";52;2
"Unit";"SCV";"Command Center";58;1
"Unit";"SCV";"Command Center";58;1
"Unit";"Hellion";"Factory";52;2
"Unit";"SCV";"Command Center";61;1
"Unit";"SCV";"Command Center";62;1
"Building";"BarracksTechLab";NA;62;0
"Unit";"Banshee";"Starport";52;3
"Building";"SupplyDepot";NA;64;0
"Building";"EngineeringBay";NA;64;0
"Unit";"SCV";"Command Center";66;1
"Unit";"SCV";"Command Center";66;1
"Building";"EngineeringBay";NA;64;0
"Unit";"SCV";"Command Center";66;1
"Unit";"Marine";"Barracks";66;1
"Unit";"SCV";"Command Center";69;1
"Building";"Barracks";NA;64;0
"Unit";"Hellion";"Factory";69;2
"Unit";"Hellion";"Factory";69;2
"Building";"Barracks";NA;64;0
"Unit";"SCV";"Command Center";73;1
"Unit";"SCV";"Command Center";73;1
"Unit";"SCV";"Command Center";74;1
"Unit";"SCV";"Command Center";78;1
"Unit";"Marine";"Barracks";78;1
"Building";"Refinery";NA;74;0
"Building";"Refinery";NA;74;0
"Unit";"SCV";"Command Center";81;1
"Unit";"SCV";"Command Center";81;1
"Unit";"SCV";"Command Center";81;1
"Building";"BarracksReactor";NA;78;0
"Building";"BarracksReactor";NA;78;0
"Building";"Refinery";NA;82;0
"Building";"Refinery";NA;82;0
"Unit";"Marine";"Barracks";86;1
"Building";"Barracks";NA;80;0
"Building";"Barracks";NA;80;0
"Unit";"SCV";"Command Center";86;1
"Unit";"SCV";"Command Center";86;1
"Unit";"SCV";"Command Center";86;1
"Unit";"Medivac";"Starport";86;2
"Unit";"Medivac";"Starport";86;2
"Building";"SupplyDepot";NA;94;0
"Building";"SupplyDepot";NA;94;0
"Building";"SupplyDepot";NA;94;0
"Building";"BarracksReactor";NA;87;0
"Building";"BarracksReactor";NA;87;0
"Unit";"SCV";"Command Center";94;1
"Unit";"SCV";"Command Center";94;1
"Unit";"SCV";"Command Center";94;1
"Unit";"Marine";"Barracks";94;1
"Unit";"Marine";"Barracks";94;1
"Unit";"Marine";"Barracks";94;1
"Unit";"Marine";"Barracks";94;1
"Unit";"Marine";"Barracks";94;1
"Unit";"SCV";"Command Center";94;1
"Unit";"SCV";"Command Center";94;1
"Unit";"SCV";"Command Center";96;1
"Unit";"Marine";"Barracks";94;1
"Unit";"Marine";"Barracks";94;1
"Unit";"Marine";"Barracks";94;1
"Unit";"Marine";"Barracks";94;1
"Unit";"Medivac";"Starport";94;2
"Unit";"Medivac";"Starport";94;2
"Building";"Factory";NA;94;0
"Upgrade";"TerranInfantryWeaponsLevel1";"EngineeringBay";86;0
"Upgrade";"TerranInfantryArmorsLevel1";"EngineeringBay";86;0
"Building";"Barracks";NA;94;0
"Building";"Barracks";NA;94;0
"Unit";"Marine";"Barracks";97;1
"Unit";"Marine";"Barracks";97;1
"Unit";"Marine";"Barracks";97;1
"Unit";"Marine";"Barracks";97;1
"Unit";"SCV";"Command Center";105;1
"Unit";"SCV";"Command Center";105;1
"Unit";"SCV";"Command Center";105;1
"Building";"Barracks";NA;94;0
"Upgrade";"Stimpack";"TechLab";86;0
"Unit";"Marine";"Barracks";117;1
"Unit";"Marine";"Barracks";117;1
"Unit";"Marine";"Barracks";117;1
"Unit";"Marine";"Barracks";117;1
"Unit";"Marine";"Barracks";117;1
"Unit";"Marine";"Barracks";117;1
"Unit";"Marine";"Barracks";117;1
"Unit";"Marine";"Barracks";117;1
"Building";"CommandCenter";NA;94;0
"Building";"FactoryTechLab";NA;120;0
"Building";"BarracksTechLab";NA;120;0
"Building";"BarracksTechLab";NA;120;0
"Unit";"Marine";"Barracks";120;1
"Unit";"SCV";"Command Center";128;1
"Unit";"SCV";"Command Center";128;1
"Unit";"SCV";"Command Center";128;1
"Building";"SupplyDepot";NA;120;0
"Unit";"Marine";"Barracks";128;1
"Unit";"Marine";"Barracks";128;1
"Unit";"Marine";"Barracks";128;1
"Unit";"Marine";"Barracks";129;1
"Unit";"Marine";"Barracks";129;1
"Unit";"Marine";"Barracks";129;1
"Unit";"Marine";"Barracks";129;1
"Unit";"Marine";"Barracks";129;1
"Unit";"Marine";"Barracks";129;1
"Unit";"Marine";"Barracks";129;1
"Unit";"Marine";"Barracks";129;1
"Building";"BarracksReactor";NA;120;0
"Building";"GhostAcademy";NA;128;0
"Unit";"Marine";"Barracks";132;1
"Unit";"Marine";"Barracks";132;1
"Upgrade";"TerranVehicleWeaponsLevel1";"Armory";105;0
"Unit";"Marine";"Barracks";143;1
"Building";"SupplyDepot";NA;145;0
"Unit";"Medivac";"Starport";143;2
"Unit";"Medivac";"Starport";143;2
"Unit";"Marine";"Barracks";146;1
"Unit";"Marine";"Barracks";146;1
"Unit";"Marine";"Barracks";146;1
"Unit";"Marine";"Barracks";146;1
"Unit";"Marine";"Barracks";146;1
"Unit";"Marine";"Barracks";146;1
"Unit";"Marine";"Barracks";146;1
"Unit";"Marine";"Barracks";146;1
"Building";"SupplyDepot";NA;150;0
"Building";"SupplyDepot";NA;150;0
"Building";"SupplyDepot";NA;150;0
"Building";"Refinery";NA;150;0
"Building";"Refinery";NA;150;0
"Unit";"Marine";"Barracks";158;1
"Unit";"Marine";"Barracks";158;1
"Unit";"Marine";"Barracks";158;1
"Unit";"Marine";"Barracks";158;1
"Unit";"Marine";"Barracks";158;1
"Unit";"Marine";"Barracks";158;1
"Unit";"Marine";"Barracks";158;1
"Unit";"Marine";"Barracks";158;1
"Unit";"Marine";"Barracks";158;1
"Unit";"Marine";"Barracks";158;1
"Unit";"Marine";"Barracks";158;1
"Unit";"Marine";"Barracks";158;1
"Unit";"Medivac";"Starport";158;2
"Unit";"Medivac";"Starport";158;2
"Upgrade";"TerranInfantryWeaponsLevel2";"EngineeringBay";134;0
"Upgrade";"TerranInfantryArmorsLevel2";"EngineeringBay";134;0
"Unit";"Marine";"Barracks";158;1
"Unit";"Marine";"Barracks";158;1
"Unit";"Marine";"Barracks";158;1
"Unit";"Marine";"Barracks";158;1
"Unit";"Marine";"Barracks";158;1
"Unit";"Marine";"Barracks";158;1
"Unit";"Marine";"Barracks";158;1
"Unit";"Marine";"Barracks";164;1
"Unit";"Marine";"Barracks";164;1
"Unit";"Marine";"Barracks";164;1
"Unit";"Marine";"Barracks";164;1
"Unit";"Marine";"Barracks";164;1
"Upgrade";"PersonalCloaking";"GhostAcademy";146;0
"Unit";"Marine";"Barracks";170;1
"Unit";"Marine";"Barracks";175;1
"Unit";"Marine";"Barracks";175;1
"Unit";"Marine";"Barracks";175;1
"Unit";"Marine";"Barracks";186;1
"Unit";"Marine";"Barracks";186;1
"Unit";"Marine";"Barracks";186;1
"Unit";"Marine";"Barracks";186;1
"Unit";"Marine";"Barracks";186;1
"Unit";"Marine";"Barracks";186;1
"Unit";"Marine";"Barracks";187;1
"Unit";"Marine";"Barracks";187;1
"Unit";"Marine";"Barracks";187;1
"Unit";"Marine";"Barracks";187;1
"Unit";"Marine";"Barracks";190;1
"Unit";"Marine";"Barracks";190;1
"Unit";"Marine";"Barracks";190;1
"Building";"SupplyDepot";NA;187;0
"Unit";"Marine";"Barracks";190;1
"Unit";"Marine";"Barracks";190;1
"Unit";"Marine";"Barracks";190;1
"Unit";"Marine";"Barracks";190;1
"Unit";"Marine";"Barracks";190;1
"Unit";"Marine";"Barracks";195;1
"Unit";"Marine";"Barracks";196;1
"Unit";"Marine";"Barracks";197;1
"Unit";"Marine";"Barracks";198;1
"Unit";"Marine";"Barracks";199;1
"Unit";"Medivac";"Starport";190;2
"Unit";"Marine";"Barracks";200;1
"Unit";"Marine";"Barracks";203;1
"Unit";"Marine";"Barracks";203;1
"Unit";"Marine";"Barracks";203;1
"Unit";"Marine";"Barracks";203;1
"Upgrade";"TerranVehicleWeaponsLevel2";"Armory";158;0
"Building";"SupplyDepot";NA;218;0
"Building";"Starport";NA;216;0
"Building";"Starport";NA;218;0
"Building";"Starport";NA;218;0
"Building";"FusionCore";NA;218;0
"Building";"StarportTechLab";NA;220;0
"Unit";"Marine";"Barracks";220;1
"Unit";"Marine";"Barracks";220;1
"Unit";"Marine";"Barracks";220;1
"Unit";"Marine";"Barracks";220;1
"Unit";"Marine";"Barracks";220;1
"Unit";"Marine";"Barracks";220;1
"Unit";"Marine";"Barracks";220;1
"Unit";"Marine";"Barracks";220;1
"Unit";"Marine";"Barracks";220;1
"Unit";"Marine";"Barracks";220;1
"Unit";"Marine";"Barracks";220;1
"Unit";"Marine";"Barracks";220;1
"Unit";"Marine";"Barracks";220;1
"Building";"StarportReactor";NA;220;0
"Unit";"Marine";"Barracks";220;1
"Unit";"Marine";"Barracks";221;1
"Unit";"Marine";"Barracks";221;1
"Unit";"Marine";"Barracks";221;1
"Unit";"Marine";"Barracks";224;1
"Unit";"Marine";"Barracks";225;1
"Unit";"Marine";"Barracks";225;1
"Unit";"Marine";"Barracks";227;1
"Unit";"Marine";"Barracks";228;1
"Unit";"Marine";"Barracks";229;1
"Unit";"Marine";"Barracks";229;1
"Unit";"Marine";"Barracks";231;1
"Unit";"Marine";"Barracks";231;1
"Unit";"Marine";"Barracks";233;1
"Unit";"Marine";"Barracks";234;1
"Unit";"Marine";"Barracks";234;1
"Unit";"Marine";"Barracks";246;1
"Unit";"Marine";"Barracks";246;1
"Unit";"Marine";"Barracks";246;1
"Unit";"Marine";"Barracks";246;1
"Unit";"Marine";"Barracks";246;1
"Unit";"Marine";"Barracks";246;1
"Unit";"Marine";"Barracks";246;1
"Unit";"Marine";"Barracks";246;1
"Unit";"Marine";"Barracks";246;1
"Upgrade";"TerranInfantryWeaponsLevel3";"EngineeringBay";220;0
"Upgrade";"TerranInfantryArmorsLevel3";"EngineeringBay";220;0
"Building";"StarportReactor";NA;233;0
"Building";"SupplyDepot";NA;246;0
"Unit";"Liberator";"Starport";242;3
"Unit";"Liberator";"Starport";246;3
"Unit";"Liberator";"Starport";246;3
"Unit";"Liberator";"Starport";246;3
"Unit";"Liberator";"Starport";246;3
"Unit";"Marine";"Barracks";258;1
"Unit";"Marine";"Barracks";258;1
"Unit";"Marine";"Barracks";258;1
"Unit";"Marine";"Barracks";258;1
"Unit";"Marine";"Barracks";258;1
"Unit";"Marine";"Barracks";258;1
"Unit";"Marine";"Barracks";258;1
"Unit";"Marine";"Barracks";258;1
"Unit";"Marine";"Barracks";258;1
"Upgrade";"TerranShipWeaponsLevel1";"Armory";220;0
"Unit";"Medivac";"Starport";258;2
"Unit";"Medivac";"Starport";258;2
"Unit";"Marine";"Barracks";282;1
"Unit";"Marine";"Barracks";282;1
"Unit";"Marine";"Barracks";282;1
"Unit";"Marine";"Barracks";282;1
"Unit";"Marine";"Barracks";282;1
"Unit";"Marine";"Barracks";282;1
"Unit";"Marine";"Barracks";282;1
"Unit";"Marine";"Barracks";282;1
"Unit";"Medivac";"Starport";258;2
"Unit";"Medivac";"Starport";261;2
"Unit";"Medivac";"Starport";264;2
"Unit";"Medivac";"Starport";267;2
"Unit";"Medivac";"Starport";270;2
"Building";"CommandCenter";NA;246;0
"Building";"Armory";NA;282;0
"Unit";"Marine";"Barracks";304;1
"Unit";"Marine";"Barracks";304;1
"Unit";"Marine";"Barracks";304;1
"Unit";"Marine";"Barracks";304;1
"Upgrade";"TerranShipWeaponsLevel2";"Armory";304;0
"Building";"SupplyDepot";NA;308;0
"Building";"Bunker";NA;308;0
"Unit";"Marine";"Barracks";308;1
"Unit";"Marine";"Barracks";308;1
"Unit";"Marine";"Barracks";308;1
"Unit";"Marine";"Barracks";308;1
"Unit";"Marine";"Barracks";308;1
"Unit";"Marine";"Barracks";308;1
"Unit";"Marauder";"Barracks";308;2
"Unit";"Marauder";"Barracks";308;2
"Unit";"Marauder";"Barracks";308;2
"Unit";"Marine";"Barracks";308;1
"Unit";"Marine";"Barracks";308;1
"Unit";"Marauder";"Barracks";314;2
"Unit";"Marauder";"Barracks";316;2
"Unit";"Marauder";"Barracks";318;2
"Upgrade";"TerranVehicleWeaponsLevel3";"Armory";304;0
"Unit";"Marine";"Barracks";322;1
"Unit";"Marine";"Barracks";322;1
"Unit";"Marine";"Barracks";322;1
"Unit";"Marine";"Barracks";322;1
"Unit";"Marine";"Barracks";322;1
"Unit";"Marine";"Barracks";322;1
"Unit";"Liberator";"Starport";310;3
"Unit";"Liberator";"Starport";310;3
"Unit";"Liberator";"Starport";310;3
"Unit";"Liberator";"Starport";310;3
"Unit";"Liberator";"Starport";310;3
"Building";"Starport";NA;320;0
"Unit";"Marine";"Barracks";328;1
"Unit";"Marine";"Barracks";328;1
"Unit";"Marauder";"Barracks";351;2
"Unit";"Marauder";"Barracks";351;2
"Unit";"Marine";"Barracks";351;1
"Unit";"Marine";"Barracks";351;1
"Unit";"Marine";"Barracks";351;1
"Unit";"Marine";"Barracks";351;1
"Unit";"Marine";"Barracks";351;1
"Unit";"Marine";"Barracks";351;1
"Unit";"Marine";"Barracks";351;1
"Unit";"Marine";"Barracks";351;1
"Unit";"Marine";"Barracks";351;1
"Unit";"Marine";"Barracks";351;1
"Unit";"Marine";"Barracks";353;1
"Unit";"Marine";"Barracks";366;1
"Unit";"Marine";"Barracks";366;1
"Unit";"Marine";"Barracks";366;1
"Unit";"Marine";"Barracks";366;1
"Unit";"Marine";"Barracks";366;1
"Unit";"Marine";"Barracks";366;1
"Unit";"Marine";"Barracks";366;1
"Unit";"Marine";"Barracks";366;1
"Unit";"Marine";"Barracks";366;1
"Unit";"Marine";"Barracks";366;1
"Unit";"Liberator";"Starport";366;3
"Unit";"Liberator";"Starport";366;3
"Unit";"Liberator";"Starport";366;3
"Unit";"Liberator";"Starport";366;3
"Unit";"Liberator";"Starport";366;3
"Unit";"Liberator";"Starport";366;3
"Unit";"Marine";"Barracks";366;1
"Unit";"Marine";"Barracks";367;1
"Building";"SupplyDepot";NA;376;0
"Building";"SupplyDepot";NA;376;0
"Unit";"Marine";"Barracks";396;1
"Unit";"Marine";"Barracks";396;1
"Unit";"Marine";"Barracks";396;1
"Unit";"Marine";"Barracks";396;1
"Unit";"Marine";"Barracks";396;1
"Unit";"Marine";"Barracks";396;1
"Unit";"Marine";"Barracks";396;1
"Unit";"Marauder";"Barracks";396;2
"Unit";"Marauder";"Barracks";396;2
"Unit";"Marauder";"Barracks";396;2
"Unit";"Marauder";"Barracks";403;2
"Unit";"Marauder";"Barracks";405;2
"Unit";"Marauder";"Barracks";407;2
"Building";"CommandCenter";NA;366;0
"Building";"CommandCenter";NA;366;0
"Unit";"Marauder";"Barracks";409;2
"Unit";"Marine";"Barracks";417;1
"Unit";"Marine";"Barracks";417;1
"Unit";"Marine";"Barracks";417;1
"Unit";"Marine";"Barracks";417;1
"Unit";"Marine";"Barracks";417;1
"Unit";"Marauder";"Barracks";417;2
"Unit";"Marauder";"Barracks";417;2
"Unit";"Marauder";"Barracks";417;2
"Unit";"Marine";"Barracks";422;1
"Unit";"Marine";"Barracks";422;1
"Unit";"Marine";"Barracks";422;1
"Unit";"Marine";"Barracks";422;1
"Unit";"Marine";"Barracks";422;1
"Unit";"Marine";"Barracks";422;1
"Unit";"Marine";"Barracks";422;1
"Unit";"Marine";"Barracks";422;1
"Unit";"Marine";"Barracks";422;1
"Unit";"Marine";"Barracks";422;1
"Unit";"Marauder";"Barracks";422;2
"Unit";"Marauder";"Barracks";424;2
"Unit";"Liberator";"Starport";428;3
"Unit";"Marine";"Barracks";442;1
"Unit";"Marine";"Barracks";442;1
"Unit";"Marine";"Barracks";442;1
"Unit";"Marine";"Barracks";442;1
"Unit";"Marine";"Barracks";442;1
"Unit";"Marine";"Barracks";442;1
"Unit";"Marine";"Barracks";442;1
"Unit";"Marine";"Barracks";442;1
"Unit";"Liberator";"Starport";438;3
"Building";"Refinery";NA;453;0
"Building";"Refinery";NA;453;0
"Building";"Refinery";NA;453;0
"Building";"Refinery";NA;456;0
"Unit";"Marine";"Barracks";456;1
"Unit";"Marine";"Barracks";456;1
"Unit";"Marine";"Barracks";456;1
"Unit";"Marine";"Barracks";456;1
"Unit";"Marine";"Barracks";456;1
"Unit";"Marine";"Barracks";456;1
"Unit";"Marine";"Barracks";456;1
"Unit";"Marine";"Barracks";456;1
"Unit";"Marine";"Barracks";456;1
"Unit";"Marine";"Barracks";456;1
"Unit";"Marine";"Barracks";456;1
"Unit";"Marine";"Barracks";456;1
"Unit";"Marine";"Barracks";456;1
"Unit";"Medivac";"Starport";456;2
"Unit";"Medivac";"Starport";456;2
"Unit";"Marine";"Barracks";473;1
"Unit";"Marine";"Barracks";473;1
"Unit";"Marine";"Barracks";473;1
"Unit";"Marine";"Barracks";473;1
"Unit";"Marine";"Barracks";473;1
"Unit";"Marine";"Barracks";473;1
"Unit";"Marauder";"Barracks";473;2
"Unit";"Marauder";"Barracks";473;2
"Unit";"Marauder";"Barracks";473;2
"Building";"Refinery";NA;473;0
"Building";"Refinery";NA;473;0
"Unit";"Marauder";"Barracks";479;2
"Unit";"Marauder";"Barracks";481;2
"Unit";"Marauder";"Barracks";483;2
"Unit";"Liberator";"Starport";473;3
"Unit";"Liberator";"Starport";473;3
"Unit";"Liberator";"Starport";473;3
"Unit";"Marine";"Barracks";500;1
"Unit";"Marine";"Barracks";500;1
"Upgrade";"TerranShipWeaponsLevel3";"Armory";473;0
"Unit";"Marine";"Barracks";502;1
"Unit";"Marine";"Barracks";502;1
"Unit";"Marine";"Barracks";502;1
"Unit";"Marine";"Barracks";502;1
"Unit";"Marine";"Barracks";502;1
"Unit";"Marine";"Barracks";502;1
"Unit";"Marine";"Barracks";502;1
"Unit";"Marine";"Barracks";502;1
"Unit";"Marine";"Barracks";502;1
"Unit";"Marine";"Barracks";502;1
"Unit";"Marine";"Barracks";502;1
"Unit";"Marine";"Barracks";502;1
"Unit";"Marine";"Barracks";502;1
"Unit";"Marine";"Barracks";502;1
"Unit";"Marine";"Barracks";503;1
"Unit";"Marine";"Barracks";504;1
"Unit";"Marine";"Barracks";505;1
"Unit";"Marine";"Barracks";506;1
"Unit";"Marine";"Barracks";506;1
"Unit";"Marine";"Barracks";508;1
"Unit";"Marine";"Barracks";508;1
"Unit";"Marine";"Barracks";510;1
"Unit";"Marine";"Barracks";510;1
"Unit";"Marine";"Barracks";512;1
"Unit";"Marine";"Barracks";512;1
"Unit";"Marine";"Barracks";514;1
"Unit";"Marine";"Barracks";515;1
"Unit";"Marine";"Barracks";516;1
"Unit";"Marine";"Barracks";517;1
"Unit";"Marine";"Barracks";518;1
"Unit";"Marine";"Barracks";519;1
"Unit";"Marine";"Barracks";519;1
"Unit";"Marine";"Barracks";521;1
"Unit";"Marine";"Barracks";521;1
"Unit";"Marine";"Barracks";523;1
"Unit";"Marine";"Barracks";523;1
"Upgrade";"TerranVehicleAndShipArmorsLevel1";"Armory";502;0
