"Type";"UnitName";"OnBuilding";"TotalSupply";"Supply"
"Unit";"SCV";"Command Center";12;1
"Unit";"SCV";"Command Center";12;1
"Unit";"SCV";"Command Center";13;1
"Building";"SupplyDepot";NA;13;0
"Building";"Refinery";NA;14;0
"Unit";"SCV";"Command Center";15;1
"Unit";"SCV";"Command Center";15;1
"Unit";"SCV";"Command Center";16;1
"Unit";"SCV";"Command Center";17;1
"Building";"Barracks";NA;15;0
"Unit";"Reaper";"Barracks";19;1
"Unit";"SCV";"Command Center";19;1
"Building";"SupplyDepot";NA;19;0
"Unit";"SCV";"Command Center";21;1
"Building";"Factory";NA;19;0
"Unit";"SCV";"Command Center";21;1
"Building";"Refinery";NA;21;0
"Building";"BarracksReactor";NA;20;0
"Unit";"SCV";"Command Center";22;1
"Building";"CommandCenter";NA;19;0
"Unit";"SCV";"Command Center";24;1
"Building";"BarracksTechLab";NA;24;0
"Unit";"SCV";"Command Center";24;1
"Unit";"Hellion";"Factory";24;2
"Unit";"Hellion";"Factory";24;2
"Building";"Starport";NA;24;0
"Unit";"SCV";"Command Center";30;1
"Unit";"SCV";"Command Center";30;1
"Building";"SupplyDepot";NA;25;0
"Unit";"Hellion";"Factory";28;2
"Unit";"Hellion";"Factory";30;2
"Unit";"SCV";"Command Center";30;1
"Unit";"SCV";"Command Center";37;1
"Unit";"SCV";"Command Center";37;1
"Unit";"Hellion";"Factory";36;2
"Unit";"Hellion";"Factory";36;2
"Unit";"SCV";"Command Center";37;1
"Unit";"SCV";"Command Center";43;1
"Building";"SupplyDepot";NA;37;0
"Building";"SupplyDepot";NA;37;0
"Building";"BarracksReactor";NA;36;0
"Unit";"SCV";"Command Center";45;1
"Unit";"SCV";"Command Center";45;1
"Building";"FactoryTechLab";NA;45;0
"Unit";"SCV";"Command Center";46;1
"Unit";"SCV";"Command Center";47;1
"Unit";"Marine";"Barracks";45;1
"Unit";"Marine";"Barracks";45;1
"Unit";"SCV";"Command Center";48;1
"Building";"EngineeringBay";NA;47;0
"Building";"EngineeringBay";NA;48;0
"Unit";"SCV";"Command Center";52;1
"Unit";"Liberator";"Starport";45;3
"Unit";"SCV";"Command Center";52;1
"Building";"BarracksTechLab";NA;52;0
"Building";"Refinery";NA;56;0
"Building";"Refinery";NA;56;0
"Unit";"SCV";"Command Center";57;1
"Building";"CommandCenter";NA;45;0
"Unit";"SCV";"Command Center";57;1
"Unit";"SCV";"Command Center";57;1
"Unit";"Marine";"Barracks";57;1
"Building";"SupplyDepot";NA;57;0
"Building";"SupplyDepot";NA;57;0
"Building";"Barracks";NA;52;0
"Building";"Barracks";NA;52;0
"Unit";"Marine";"Barracks";60;1
"Unit";"Marine";"Barracks";61;1
"Unit";"SCV";"Command Center";61;1
"Unit";"Marine";"Barracks";61;1
"Unit";"Marine";"Barracks";61;1
"Unit";"Marine";"Barracks";61;1
"Unit";"SCV";"Command Center";61;1
"Unit";"Marine";"Barracks";61;1
"Unit";"SCV";"Command Center";63;1
"Unit";"SCV";"Command Center";68;1
"Building";"StarportReactor";NA;61;0
"Unit";"SCV";"Command Center";69;1
"Unit";"Marine";"Barracks";68;1
"Unit";"Marine";"Barracks";68;1
"Unit";"Marine";"Barracks";68;1
"Unit";"Marine";"Barracks";71;1
"Building";"Barracks";NA;61;0
"Unit";"SCV";"Command Center";71;1
"Unit";"SCV";"Command Center";75;1
"Unit";"SCV";"Command Center";75;1
"Unit";"Marine";"Barracks";75;1
"Unit";"Medivac";"Starport";71;2
"Building";"Barracks";NA;68;0
"Unit";"Marine";"Barracks";75;1
"Unit";"Marine";"Barracks";75;1
"Upgrade";"TerranInfantryWeaponsLevel1";"EngineeringBay";59;0
"Upgrade";"TerranInfantryArmorsLevel1";"EngineeringBay";59;0
"Unit";"Medivac";"Starport";71;2
"Unit";"Marine";"Barracks";76;1
"Unit";"Marine";"Barracks";76;1
"Building";"Armory";NA;71;0
"Unit";"Marine";"Barracks";79;1
"Unit";"Marine";"Barracks";82;1
"Unit";"Marine";"Barracks";88;1
"Unit";"Marine";"Barracks";88;1
"Unit";"Marine";"Barracks";88;1
"Upgrade";"Stimpack";"TechLab";62;0
"Unit";"Marine";"Barracks";88;1
"Unit";"SCV";"Command Center";92;1
"Unit";"Marine";"Barracks";89;1
"Unit";"Marine";"Barracks";90;1
"Unit";"Marine";"Barracks";91;1
"Unit";"SCV";"Command Center";92;1
"Unit";"Marine";"Barracks";92;1
"Unit";"Medivac";"Starport";89;2
"Building";"BarracksReactor";NA;88;0
"Building";"BarracksReactor";NA;88;0
"Building";"Factory";NA;89;0
"Building";"SupplyDepot";NA;99;0
"Building";"SupplyDepot";NA;100;0
"Building";"SupplyDepot";NA;100;0
"Building";"SupplyDepot";NA;102;0
"Building";"SupplyDepot";NA;102;0
"Unit";"SCV";"Command Center";102;1
"Unit";"Marine";"Barracks";102;1
"Unit";"Marine";"Barracks";102;1
"Unit";"SCV";"Command Center";102;1
"Unit";"SCV";"Command Center";102;1
"Unit";"Marine";"Barracks";102;1
"Unit";"Marine";"Barracks";102;1
"Unit";"Marine";"Barracks";102;1
"Unit";"Marine";"Barracks";102;1
"Unit";"SCV";"Command Center";102;1
"Unit";"Marine";"Barracks";102;1
"Unit";"Marine";"Barracks";102;1
"Unit";"Marine";"Barracks";102;1
"Building";"SupplyDepot";NA;102;0
"Building";"SupplyDepot";NA;102;0
"Unit";"Marine";"Barracks";106;1
"Unit";"Marine";"Barracks";106;1
"Building";"Refinery";NA;106;0
"Building";"Refinery";NA;106;0
"Unit";"Marine";"Barracks";107;1
"Unit";"SCV";"Command Center";115;1
"Unit";"Marine";"Barracks";115;1
"Unit";"Marine";"Barracks";115;1
"Building";"SupplyDepot";NA;112;0
"Building";"SupplyDepot";NA;115;0
"Building";"SupplyDepot";NA;115;0
"Unit";"SCV";"Command Center";119;1
"Unit";"SCV";"Command Center";119;1
"Unit";"Marine";"Barracks";117;1
"Unit";"Marine";"Barracks";117;1
"Unit";"Marine";"Barracks";117;1
"Building";"MissileTurret";NA;121;0
"Unit";"Marine";"Barracks";121;1
"Unit";"Marine";"Barracks";121;1
"Unit";"Marine";"Barracks";121;1
"Unit";"Marine";"Barracks";121;1
"Unit";"Medivac";"Starport";119;2
"Building";"SupplyDepot";NA;121;0
"Unit";"Marine";"Barracks";123;1
"Unit";"Marine";"Barracks";124;1
"Unit";"Marine";"Barracks";125;1
"Unit";"SCV";"Command Center";126;1
"Unit";"Marine";"Barracks";126;1
"Unit";"Marine";"Barracks";126;1
"Building";"SupplyDepot";NA;126;0
"Unit";"Marine";"Barracks";136;1
"Unit";"Marine";"Barracks";136;1
"Unit";"Marine";"Barracks";136;1
"Unit";"Marine";"Barracks";136;1
"Unit";"Marine";"Barracks";136;1
"Upgrade";"TerranInfantryWeaponsLevel2";"EngineeringBay";102;0
"Unit";"Marine";"Barracks";138;1
"Unit";"Marine";"Barracks";138;1
"Unit";"Marine";"Barracks";138;1
"Unit";"Marine";"Barracks";138;1
"Upgrade";"TerranInfantryArmorsLevel2";"EngineeringBay";106;0
"Unit";"Marine";"Barracks";138;1
"Unit";"Marine";"Barracks";143;1
"Unit";"Marine";"Barracks";143;1
"Unit";"Marine";"Barracks";143;1
"Unit";"Marine";"Barracks";148;1
"Unit";"Marine";"Barracks";148;1
"Unit";"Marine";"Barracks";151;1
"Unit";"Marine";"Barracks";151;1
"Unit";"Marine";"Barracks";151;1
"Unit";"Marine";"Barracks";151;1
"Unit";"Marine";"Barracks";153;1
"Unit";"Marine";"Barracks";157;1
"Unit";"Marine";"Barracks";157;1
"Unit";"Marine";"Barracks";157;1
"Unit";"Marine";"Barracks";157;1
"Unit";"Marine";"Barracks";157;1
"Unit";"Marine";"Barracks";157;1
"Unit";"Marine";"Barracks";157;1
"Unit";"Marine";"Barracks";157;1
"Unit";"SCV";"Command Center";157;1
"Upgrade";"TerranVehicleWeaponsLevel1";"Armory";138;0
"Unit";"Marine";"Barracks";158;1
"Building";"Barracks";NA;153;0
"Unit";"Medivac";"Starport";157;2
"Unit";"Medivac";"Starport";157;2
"Building";"Barracks";NA;153;0
"Unit";"Marine";"Barracks";158;1
"Unit";"Marine";"Barracks";159;1
"Unit";"Marine";"Barracks";164;1
"Unit";"Marine";"Barracks";164;1
"Unit";"SCV";"Command Center";168;1
"Unit";"SCV";"Command Center";168;1
"Unit";"SCV";"Command Center";168;1
"Unit";"Marine";"Barracks";167;1
"Unit";"Marine";"Barracks";167;1
"Unit";"Marine";"Barracks";167;1
"Building";"CommandCenter";NA;151;0
"Building";"BarracksTechLab";NA;174;0
"Building";"BarracksTechLab";NA;174;0
"Unit";"SCV";"Command Center";176;1
"Unit";"SCV";"Command Center";177;1
"Unit";"Marine";"Barracks";184;1
"Unit";"Marine";"Barracks";184;1
"Unit";"Marine";"Barracks";184;1
"Unit";"Marine";"Barracks";184;1
"Unit";"Marine";"Barracks";184;1
"Unit";"Marauder";"Barracks";184;2
"Unit";"Marauder";"Barracks";184;2
"Unit";"SCV";"Command Center";184;1
"Unit";"SCV";"Command Center";184;1
"Unit";"SCV";"Command Center";184;1
"Unit";"Marine";"Barracks";184;1
"Unit";"Marine";"Barracks";184;1
"Unit";"Marine";"Barracks";184;1
"Unit";"Medivac";"Starport";184;2
"Unit";"Medivac";"Starport";184;2
"Unit";"Marauder";"Barracks";184;2
"Unit";"Marine";"Barracks";184;1
"Unit";"Marine";"Barracks";185;1
"Unit";"SCV";"Command Center";193;1
"Unit";"Marauder";"Barracks";189;2
"Unit";"Marine";"Barracks";196;1
"Unit";"Marauder";"Barracks";196;2
"Upgrade";"TerranInfantryWeaponsLevel3";"EngineeringBay";157;0
"Unit";"Marine";"Barracks";207;1
"Unit";"Marine";"Barracks";207;1
"Unit";"Marine";"Barracks";207;1
"Unit";"Marine";"Barracks";207;1
"Unit";"Marauder";"Barracks";207;2
"Unit";"Marine";"Barracks";217;1
"Unit";"Marine";"Barracks";217;1
"Unit";"Marine";"Barracks";219;1
"Building";"CommandCenter";NA;184;0
"Unit";"Marauder";"Barracks";217;2
"Unit";"Marauder";"Barracks";217;2
"Unit";"Marauder";"Barracks";219;2
"Unit";"Marine";"Barracks";222;1
"Unit";"Marine";"Barracks";222;1
"Unit";"Marine";"Barracks";222;1
"Unit";"Marine";"Barracks";222;1
"Unit";"Marauder";"Barracks";222;2
"Unit";"Marauder";"Barracks";224;2
"Building";"SensorTower";NA;228;0
"Unit";"Marine";"Barracks";228;1
"Unit";"Marine";"Barracks";228;1
"Unit";"Marine";"Barracks";228;1
"Unit";"Marauder";"Barracks";228;2
"Unit";"Marine";"Barracks";228;1
"Unit";"Marine";"Barracks";228;1
"Unit";"Marine";"Barracks";232;1
"Unit";"Marine";"Barracks";232;1
"Unit";"Marine";"Barracks";232;1
"Unit";"Marauder";"Barracks";232;2
"Unit";"Marauder";"Barracks";234;2
"Unit";"Marine";"Barracks";236;1
"Unit";"Marine";"Barracks";237;1
"Unit";"Medivac";"Starport";232;2
"Unit";"Medivac";"Starport";232;2
"Building";"MissileTurret";NA;239;0
"Building";"Refinery";NA;239;0
"Unit";"Marauder";"Barracks";239;2
"Unit";"Marine";"Barracks";252;1
"Unit";"Marine";"Barracks";252;1
"Unit";"Marine";"Barracks";252;1
"Unit";"Marine";"Barracks";252;1
"Unit";"Marine";"Barracks";252;1
"Unit";"Marauder";"Barracks";252;2
"Unit";"Marauder";"Barracks";252;2
"Unit";"Marine";"Barracks";256;1
"Unit";"Marine";"Barracks";256;1
"Unit";"Marine";"Barracks";258;1
"Unit";"Marauder";"Barracks";256;2
"Unit";"Marine";"Barracks";258;1
"Upgrade";"TerranInfantryArmorsLevel3";"EngineeringBay";219;0
"Unit";"Marauder";"Barracks";273;2
"Unit";"Marine";"Barracks";273;1
"Unit";"Marine";"Barracks";273;1
"Unit";"SCV";"Command Center";273;1
"Unit";"SCV";"Command Center";273;1
"Unit";"Marine";"Barracks";273;1
"Unit";"SCV";"Command Center";273;1
"Unit";"Marine";"Barracks";273;1
"Unit";"Marine";"Barracks";273;1
"Unit";"Marauder";"Barracks";273;2
"Unit";"Marauder";"Barracks";273;2
"Unit";"Marine";"Barracks";273;1
"Unit";"Marine";"Barracks";273;1
"Unit";"Marine";"Barracks";273;1
"Unit";"Medivac";"Starport";273;2
"Unit";"Medivac";"Starport";273;2
"Unit";"Marine";"Barracks";275;1
"Unit";"Marine";"Barracks";276;1
"Unit";"Marauder";"Barracks";273;2
"Unit";"Marine";"Barracks";279;1
"Unit";"Marine";"Barracks";287;1
"Unit";"Marine";"Barracks";287;1
"Unit";"Marine";"Barracks";287;1
"Unit";"Marauder";"Barracks";287;2
"Unit";"Marine";"Barracks";299;1
"Unit";"Marine";"Barracks";299;1
"Unit";"Marine";"Barracks";299;1
"Unit";"Marine";"Barracks";299;1
"Unit";"Marine";"Barracks";299;1
"Unit";"Marine";"Barracks";299;1
"Unit";"Medivac";"Starport";290;2
"Unit";"Marine";"Barracks";304;1
"Unit";"Marine";"Barracks";304;1
"Unit";"Marine";"Barracks";304;1
"Unit";"Marine";"Barracks";304;1
"Unit";"Marine";"Barracks";304;1
"Unit";"Marine";"Barracks";315;1
"Unit";"Marine";"Barracks";315;1
"Building";"GhostAcademy";NA;315;0
"Unit";"Marine";"Barracks";319;1
"Unit";"Marine";"Barracks";319;1
"Unit";"Marine";"Barracks";319;1
"Unit";"Marine";"Barracks";319;1
"Unit";"Marine";"Barracks";319;1
"Unit";"Marine";"Barracks";319;1
"Unit";"Marine";"Barracks";323;1
"Unit";"Marine";"Barracks";323;1
"Unit";"Marine";"Barracks";323;1
"Unit";"Marine";"Barracks";323;1
"Unit";"Ghost";"Barracks";323;2
"Unit";"Ghost";"Barracks";323;2
"Unit";"Ghost";"Barracks";323;2
"Unit";"Marine";"Barracks";325;1
"Unit";"Marine";"Barracks";325;1
"Unit";"Marine";"Barracks";329;1
"Unit";"Marauder";"Barracks";329;2
"Unit";"Marauder";"Barracks";331;2
"Unit";"Ghost";"Barracks";337;2
"Unit";"Marine";"Barracks";338;1
"Unit";"Marine";"Barracks";338;1
"Unit";"Marine";"Barracks";342;1
"Unit";"Marine";"Barracks";342;1
"Unit";"Ghost";"Barracks";338;2
"Unit";"Marine";"Barracks";344;1
"Unit";"Marine";"Barracks";344;1
"Unit";"Ghost";"Barracks";342;2
"Unit";"Marine";"Barracks";346;1
"Unit";"Marine";"Barracks";346;1
"Unit";"Marine";"Barracks";346;1
"Unit";"Ghost";"Barracks";342;2
"Unit";"Marine";"Barracks";346;1
"Building";"CommandCenter";NA;329;0
"Unit";"Marine";"Barracks";356;1
"Unit";"Marine";"Barracks";356;1
"Unit";"Ghost";"Barracks";348;2
"Unit";"Marine";"Barracks";360;1
"Unit";"Marine";"Barracks";360;1
"Unit";"Marine";"Barracks";360;1
"Unit";"Liberator";"Starport";346;3
"Unit";"Marine";"Barracks";360;1
"Unit";"Marine";"Barracks";360;1
"Unit";"Marine";"Barracks";360;1
"Unit";"Medivac";"Starport";360;2
"Unit";"Ghost";"Barracks";360;2
"Unit";"Ghost";"Barracks";360;2
"Unit";"Ghost";"Barracks";362;2
"Unit";"Medivac";"Starport";367;2
"Unit";"Medivac";"Starport";373;2
"Unit";"Ghost";"Barracks";383;2
"Unit";"Ghost";"Barracks";383;2
"Unit";"Ghost";"Barracks";385;2
"Unit";"Marine";"Barracks";385;1
"Unit";"Marine";"Barracks";385;1
"Unit";"Marine";"Barracks";389;1
"Unit";"SCV";"Command Center";393;1
"Unit";"Ghost";"Barracks";385;2
"Unit";"Marine";"Barracks";393;1
"Unit";"Marine";"Barracks";393;1
"Unit";"Marine";"Barracks";393;1
"Unit";"Ghost";"Barracks";389;2
"Unit";"Ghost";"Barracks";389;2
"Unit";"Marine";"Barracks";393;1
"Unit";"Marine";"Barracks";393;1
"Unit";"Marine";"Barracks";393;1
"Unit";"Liberator";"Starport";385;3
"Unit";"Liberator";"Starport";385;3
"Unit";"Marine";"Barracks";394;1
"Unit";"Marine";"Barracks";394;1
"Unit";"Marine";"Barracks";397;1
"Unit";"Ghost";"Barracks";395;2
"Unit";"Medivac";"Starport";407;2
"Unit";"Marine";"Barracks";416;1
"Unit";"Marine";"Barracks";416;1
"Unit";"Marine";"Barracks";416;1
"Unit";"Marine";"Barracks";416;1
"Unit";"Marine";"Barracks";416;1
"Unit";"Marauder";"Barracks";416;2
"Unit";"Marauder";"Barracks";416;2
"Unit";"Marauder";"Barracks";416;2
"Building";"Starport";NA;415;0
"Unit";"Medivac";"Starport";416;2
"Unit";"Marine";"Barracks";431;1
"Unit";"Marine";"Barracks";431;1
"Unit";"Marauder";"Barracks";431;2
"Unit";"Marauder";"Barracks";431;2
"Unit";"SCV";"Command Center";433;1
"Unit";"SCV";"Command Center";433;1
"Unit";"SCV";"Command Center";433;1
"Unit";"Marine";"Barracks";433;1
"Unit";"Marine";"Barracks";433;1
"Unit";"Marine";"Barracks";433;1
"Unit";"Marine";"Barracks";433;1
"Unit";"SCV";"Command Center";439;1
"Unit";"SCV";"Command Center";440;1
"Unit";"Marine";"Barracks";444;1
"Unit";"Marine";"Barracks";444;1
"Unit";"Marine";"Barracks";444;1
"Unit";"Marine";"Barracks";444;1
"Unit";"Marine";"Barracks";448;1
"Unit";"Marine";"Barracks";448;1
"Unit";"Marine";"Barracks";448;1
"Unit";"Marine";"Barracks";448;1
"Unit";"Marine";"Barracks";448;1
"Unit";"Marine";"Barracks";457;1
"Unit";"Marine";"Barracks";457;1
"Unit";"Marine";"Barracks";457;1
"Unit";"Marine";"Barracks";457;1
"Unit";"Marauder";"Barracks";457;2
"Unit";"Marauder";"Barracks";457;2
"Unit";"Marauder";"Barracks";457;2
"Upgrade";"PersonalCloaking";"GhostAcademy";452;0
"Unit";"Marine";"Barracks";467;1
"Unit";"Marine";"Barracks";467;1
"Unit";"Marine";"Barracks";467;1
"Unit";"Marauder";"Barracks";467;2
"Unit";"Marine";"Barracks";467;1
"Unit";"Marauder";"Barracks";467;2
"Unit";"Marine";"Barracks";467;1
"Unit";"Marine";"Barracks";467;1
"Unit";"Marine";"Barracks";475;1
"Unit";"SCV";"Command Center";477;1
"Unit";"Medivac";"Starport";477;2
"Unit";"Medivac";"Starport";477;2
"Unit";"Marine";"Barracks";483;1
"Unit";"Marine";"Barracks";483;1
"Unit";"Medivac";"Starport";479;2
"Unit";"Medivac";"Starport";481;2
"Unit";"Marine";"Barracks";487;1
"Unit";"Marine";"Barracks";487;1
"Unit";"Marine";"Barracks";487;1
"Unit";"Marauder";"Barracks";487;2
"Unit";"Marine";"Barracks";489;1
"Unit";"Marine";"Barracks";489;1
"Unit";"Marine";"Barracks";489;1
"Unit";"Marine";"Barracks";489;1
"Unit";"Marauder";"Barracks";489;2
"Unit";"Marine";"Barracks";497;1
"Unit";"Marine";"Barracks";498;1
"Unit";"Marine";"Barracks";498;1
"Unit";"Marine";"Barracks";498;1
"Unit";"Marauder";"Barracks";498;2
"Unit";"Ghost";"Barracks";498;2
"Unit";"Ghost";"Barracks";498;2
"Unit";"Marine";"Barracks";506;1
"Unit";"Marine";"Barracks";506;1
"Unit";"Ghost";"Barracks";504;2
"Unit";"Marine";"Barracks";510;1
"Unit";"Marine";"Barracks";510;1
"Unit";"Ghost";"Barracks";506;2
"Unit";"Ghost";"Barracks";508;2
"Unit";"Marine";"Barracks";516;1
"Unit";"Marine";"Barracks";516;1
"Unit";"Marine";"Barracks";520;1
"Unit";"Marine";"Barracks";520;1
"Unit";"Ghost";"Barracks";512;2
"Unit";"Marine";"Barracks";520;1
"Unit";"Marine";"Barracks";520;1
"Unit";"Marine";"Barracks";520;1
"Unit";"Ghost";"Barracks";516;2
"Unit";"Marine";"Barracks";526;1
"Unit";"Marine";"Barracks";526;1
"Unit";"Marine";"Barracks";526;1
"Unit";"Marine";"Barracks";534;1
"Unit";"Marine";"Barracks";534;1
"Unit";"Marine";"Barracks";534;1
"Unit";"Marine";"Barracks";534;1
"Unit";"Marine";"Barracks";534;1
"Unit";"Marauder";"Barracks";534;2
"Unit";"Marauder";"Barracks";534;2
"Unit";"Marine";"Barracks";534;1
"Unit";"Marine";"Barracks";534;1
"Unit";"Marine";"Barracks";534;1
"Unit";"Marauder";"Barracks";534;2
"Unit";"Marine";"Barracks";534;1
"Unit";"Marine";"Barracks";539;1
"Unit";"Marine";"Barracks";539;1
"Unit";"Marine";"Barracks";539;1
"Unit";"Marauder";"Barracks";539;2
"Unit";"Marauder";"Barracks";541;2
"Unit";"Marine";"Barracks";546;1
"Unit";"Marauder";"Barracks";546;2
"Unit";"Marine";"Barracks";556;1
"Unit";"Marine";"Barracks";556;1
"Unit";"Marauder";"Barracks";554;2
"Unit";"Ghost";"Barracks";552;2
"Unit";"Marine";"Barracks";559;1
"Unit";"Marine";"Barracks";559;1
"Unit";"Marine";"Barracks";563;1
"Unit";"Marine";"Barracks";563;1
"Unit";"Marine";"Barracks";563;1
"Unit";"Marine";"Barracks";563;1
"Unit";"Marine";"Barracks";563;1
"Unit";"Marine";"Barracks";563;1
"Building";"Refinery";NA;567;0
