"type";"unit_name";"on_building";"total_supply_lag";"supply"
"Building";"Barracks";NA;16;0
"Building";"Refinery";NA;16;0
"Unit";"Reaper";"Barracks";19;1
"Building";"CommandCenter";NA;20;0
"Unit";"Marine";"Barracks";21;1
"Building";"Factory";NA;23;0
"Building";"BarracksReactor";NA;24;0
"Building";"CommandCenter";NA;25;0
"Unit";"Hellion";"Factory";27;2
"Unit";"Hellion";"Factory";29;2
"Building";"BarracksTechLab";NA;32;0
"Unit";"Marine";"Barracks";34;1
"Building";"Barracks";NA;35;0
"Building";"Barracks";NA;37;0
"Building";"FactoryReactor";NA;37;0
"Unit";"Marine";"Barracks";39;1
"Building";"Refinery";NA;42;0
"Building";"Refinery";NA;42;0
"Upgrade";"Stimpack";"TechLab";42;0
"Unit";"Marine";"Barracks";42;1
"Building";"EngineeringBay";NA;47;0
"Building";"Starport";NA;47;0
"Unit";"Marine";"Barracks";47;1
"Building";"FactoryReactor";NA;49;0
"Building";"EngineeringBay";NA;49;0
"Unit";"Marine";"Barracks";51;1
"Unit";"Marine";"Barracks";52;1
"Unit";"Marine";"Barracks";55;1
"Unit";"Marine";"Barracks";56;1
"Unit";"Marine";"Barracks";58;1
"Unit";"Marine";"Barracks";59;1
"Unit";"Marine";"Barracks";63;1
"Unit";"Marine";"Barracks";64;1
"Unit";"Marine";"Barracks";65;1
"Unit";"Medivac";"Starport";67;2
"Unit";"Marine";"Barracks";69;1
"Unit";"Marine";"Barracks";70;1
"Unit";"Medivac";"Starport";73;2
"Unit";"Marine";"Barracks";76;1
"Building";"Refinery";NA;77;0
"Building";"FactoryTechLab";NA;77;0
"Upgrade";"TerranInfantryWeaponsLevel1";"EngineeringBay";79;0
"Unit";"Marine";"Barracks";80;1
"Unit";"Marine";"Barracks";83;1
"Unit";"Marine";"Barracks";84;1
"Unit";"Marine";"Barracks";86;1
"Unit";"Marine";"Barracks";87;1
"Building";"Armory";NA;90;0
"Building";"Barracks";NA;91;0
"Building";"Barracks";NA;91;0
"Unit";"Marine";"Barracks";94;1
"Unit";"Marine";"Barracks";95;1
"Unit";"Marine";"Barracks";96;1
"Unit";"Marine";"Barracks";97;1
"Unit";"Medivac";"Starport";101;2
"Unit";"Medivac";"Starport";103;2
"Unit";"Marine";"Barracks";105;1
"Building";"Refinery";NA;106;0
"Unit";"Marine";"Barracks";106;1
"Unit";"Marine";"Barracks";107;1
"Building";"Refinery";NA;108;0
"Unit";"Marine";"Barracks";109;1
"Unit";"Marine";"Barracks";111;1
"Unit";"Marine";"Barracks";112;1
"Unit";"Marine";"Barracks";113;1
"Unit";"Marine";"Barracks";115;1
"Unit";"Marine";"Barracks";116;1
"Unit";"Marine";"Barracks";117;1
"Unit";"Marine";"Barracks";118;1
"Unit";"Marine";"Barracks";119;1
"Building";"BarracksReactor";NA;120;0
"Building";"BarracksReactor";NA;120;0
"Unit";"Marine";"Barracks";120;1
"Building";"CommandCenter";NA;121;0
"Building";"Barracks";NA;121;0
"Building";"Barracks";NA;121;0
"Building";"Barracks";NA;121;0
"Unit";"Marine";"Barracks";121;1
"Unit";"Marine";"Barracks";122;1
"Building";"Factory";NA;123;0
"Unit";"Marine";"Barracks";123;1
"Unit";"Marine";"Barracks";124;1
"Unit";"Medivac";"Starport";125;2
"Upgrade";"TerranInfantryWeaponsLevel2";"EngineeringBay";127;0
"Unit";"Marine";"Barracks";127;1
"Unit";"Marine";"Barracks";131;1
"Unit";"Marine";"Barracks";132;1
"Unit";"Marine";"Barracks";133;1
"Unit";"Marine";"Barracks";134;1
"Unit";"Marine";"Barracks";135;1
"Unit";"Marine";"Barracks";136;1
"Unit";"Marine";"Barracks";137;1
"Unit";"Marine";"Barracks";138;1
"Unit";"Marine";"Barracks";139;1
"Unit";"Marine";"Barracks";140;1
"Unit";"Marine";"Barracks";141;1
"Unit";"Marine";"Barracks";142;1
"Building";"FactoryTechLab";NA;143;0
"Unit";"Marine";"Barracks";143;1
"Unit";"Marine";"Barracks";144;1
"Building";"BarracksTechLab";NA;145;0
"Building";"BarracksTechLab";NA;145;0
"Building";"BarracksTechLab";NA;145;0
"Unit";"Marine";"Barracks";145;1
"Unit";"Marine";"Barracks";146;1
"Unit";"Marine";"Barracks";147;1
"Unit";"Marine";"Barracks";148;1
"Unit";"Marine";"Barracks";149;1
"Unit";"Marine";"Barracks";150;1
"Unit";"Marine";"Barracks";151;1
"Unit";"Marine";"Barracks";152;1
"Unit";"Medivac";"Starport";153;2
"Unit";"Medivac";"Starport";155;2
"Unit";"Marine";"Barracks";157;1
"Unit";"Marine";"Barracks";158;1
"Unit";"Marine";"Barracks";159;1
"Unit";"Marine";"Barracks";160;1
"Unit";"Marine";"Barracks";161;1
"Unit";"Marine";"Barracks";162;1
"Unit";"Marine";"Barracks";163;1
"Unit";"Marine";"Barracks";164;1
"Unit";"Marine";"Barracks";165;1
"Unit";"Marine";"Barracks";166;1
"Unit";"Marine";"Barracks";167;1
"Unit";"Marine";"Barracks";168;1
"Unit";"Marine";"Barracks";169;1
"Unit";"Marine";"Barracks";170;1
"Unit";"Marine";"Barracks";171;1
"Unit";"Marine";"Barracks";172;1
"Unit";"Marine";"Barracks";173;1
"Unit";"Marine";"Barracks";174;1
"Unit";"Marine";"Barracks";175;1
"Unit";"Marine";"Barracks";176;1
"Unit";"Marine";"Barracks";177;1
"Unit";"Marine";"Barracks";178;1
"Unit";"Marine";"Barracks";179;1
"Unit";"Marine";"Barracks";180;1
"Unit";"Marauder";"Barracks";181;2
"Unit";"Marauder";"Barracks";183;2
"Unit";"Marauder";"Barracks";185;2
"Unit";"Marine";"Barracks";187;1
"Unit";"Marine";"Barracks";188;1
"Unit";"Marine";"Barracks";189;1
"Unit";"Marine";"Barracks";190;1
"Unit";"Marine";"Barracks";191;1
"Unit";"Marine";"Barracks";192;1
"Unit";"Marine";"Barracks";193;1
"Unit";"Marine";"Barracks";194;1
"Unit";"Marine";"Barracks";195;1
"Unit";"Marine";"Barracks";196;1
"Unit";"Marine";"Barracks";197;1
"Unit";"Marauder";"Barracks";198;2
"Unit";"Medivac";"Starport";200;2
"Unit";"Medivac";"Starport";202;2
"Unit";"Marauder";"Barracks";204;2
"Unit";"Marine";"Barracks";206;1
"Unit";"Marine";"Barracks";207;1
"Unit";"Marine";"Barracks";208;1
"Unit";"Marine";"Barracks";209;1
"Upgrade";"TerranInfantryWeaponsLevel3";"EngineeringBay";210;0
"Unit";"Marine";"Barracks";210;1
"Unit";"Marine";"Barracks";211;1
"Unit";"Marine";"Barracks";212;1
"Unit";"Marine";"Barracks";213;1
"Unit";"Marine";"Barracks";214;1
"Unit";"Marine";"Barracks";215;1
"Unit";"Marine";"Barracks";216;1
"Unit";"Marine";"Barracks";217;1
"Unit";"Marine";"Barracks";218;1
"Unit";"Marine";"Barracks";219;1
"Unit";"Marine";"Barracks";220;1
"Unit";"Marine";"Barracks";221;1
"Unit";"Marine";"Barracks";222;1
"Unit";"Marine";"Barracks";223;1
"Unit";"Marine";"Barracks";224;1
"Unit";"Marine";"Barracks";225;1
"Unit";"Medivac";"Starport";226;2
"Unit";"Medivac";"Starport";228;2
"Unit";"Marauder";"Barracks";230;2
"Unit";"Marauder";"Barracks";232;2
"Unit";"Marauder";"Barracks";234;2
"Unit";"Marauder";"Barracks";236;2
"Unit";"Marauder";"Barracks";238;2
"Building";"CommandCenter";NA;240;0
"Unit";"Marauder";"Barracks";240;2
"Unit";"Marine";"Barracks";242;1
"Unit";"Marine";"Barracks";243;1
"Unit";"Marine";"Barracks";244;1
"Unit";"Marine";"Barracks";245;1
"Unit";"Marine";"Barracks";246;1
"Unit";"Marine";"Barracks";247;1
"Unit";"Marine";"Barracks";248;1
"Unit";"Marauder";"Barracks";249;2
"Unit";"Marauder";"Barracks";251;2
"Unit";"Marine";"Barracks";253;1
"Unit";"Marauder";"Barracks";254;2
"Unit";"Marine";"Barracks";256;1
"Unit";"Marine";"Barracks";257;1
"Unit";"Marine";"Barracks";258;1
"Unit";"Medivac";"Starport";259;2
"Unit";"Marauder";"Barracks";261;2
"Unit";"Marine";"Barracks";263;1
"Unit";"Marine";"Barracks";264;1
"Unit";"Marauder";"Barracks";265;2
"Unit";"Marine";"Barracks";267;1
"Unit";"Marine";"Barracks";268;1
"Unit";"Marine";"Barracks";269;1
"Building";"Refinery";NA;270;0
"Building";"GhostAcademy";NA;270;0
"Unit";"Marauder";"Barracks";270;2
"Unit";"Marauder";"Barracks";272;2
"Unit";"Marine";"Barracks";274;1
"Unit";"Marine";"Barracks";275;1
"Unit";"Marine";"Barracks";276;1
"Unit";"Marine";"Barracks";277;1
"Unit";"Marine";"Barracks";278;1
"Unit";"Medivac";"Starport";279;2
"Unit";"Medivac";"Starport";281;2
"Unit";"Marauder";"Barracks";283;2
"Unit";"Marine";"Barracks";285;1
"Unit";"Marine";"Barracks";286;1
"Unit";"Marine";"Barracks";287;1
"Unit";"Marine";"Barracks";288;1
"Unit";"Marauder";"Barracks";289;2
"Unit";"Marine";"Barracks";291;1
"Unit";"Marine";"Barracks";292;1
"Unit";"Marine";"Barracks";293;1
"Unit";"Marine";"Barracks";294;1
"Unit";"Marine";"Barracks";295;1
"Unit";"Marine";"Barracks";296;1
"Unit";"Marauder";"Barracks";297;2
"Unit";"Liberator";"Starport";299;3
"Unit";"Liberator";"Starport";302;3
"Unit";"Marauder";"Barracks";305;2
"Unit";"Marauder";"Barracks";307;2
"Unit";"Marauder";"Barracks";309;2
"Unit";"Marine";"Barracks";311;1
"Unit";"Marine";"Barracks";312;1
"Unit";"Marine";"Barracks";313;1
"Unit";"Marine";"Barracks";314;1
"Unit";"Marine";"Barracks";315;1
"Unit";"Marine";"Barracks";316;1
"Unit";"Marauder";"Barracks";317;2
"Unit";"Marine";"Barracks";319;1
"Unit";"Marine";"Barracks";320;1
"Unit";"Marauder";"Barracks";321;2
"Unit";"Marauder";"Barracks";323;2
"Unit";"Marine";"Barracks";325;1
"Unit";"Marine";"Barracks";326;1
"Unit";"Liberator";"Starport";327;3
"Unit";"Marine";"Barracks";330;1
"Unit";"Marine";"Barracks";331;1
"Unit";"Marine";"Barracks";332;1
"Unit";"Marine";"Barracks";333;1
"Unit";"Marine";"Barracks";334;1
"Unit";"Marine";"Barracks";335;1
"Unit";"Marine";"Barracks";336;1
"Unit";"Marine";"Barracks";337;1
"Unit";"Marine";"Barracks";338;1
"Unit";"Ghost";"Barracks";339;2
"Unit";"Ghost";"Barracks";341;2
"Unit";"Ghost";"Barracks";343;2
"Unit";"Ghost";"Barracks";345;2
"Unit";"Medivac";"Starport";347;2
"Unit";"Marine";"Barracks";349;1
"Unit";"Marine";"Barracks";350;1
"Unit";"Marine";"Barracks";351;1
"Unit";"Ghost";"Barracks";352;2
"Unit";"Ghost";"Barracks";354;2
"Unit";"Ghost";"Barracks";356;2
"Unit";"Ghost";"Barracks";358;2
"Building";"Refinery";NA;360;0
"Building";"MissileTurret";NA;360;0
"Unit";"Marine";"Barracks";360;1
"Unit";"Marine";"Barracks";361;1
"Unit";"Marine";"Barracks";362;1
"Unit";"Marine";"Barracks";363;1
"Unit";"Marine";"Barracks";364;1
"Unit";"Marine";"Barracks";365;1
"Unit";"Marine";"Barracks";366;1
"Unit";"Marine";"Barracks";367;1
"Unit";"Marine";"Barracks";368;1
"Unit";"Marine";"Barracks";369;1
"Unit";"Marauder";"Barracks";370;2
"Unit";"Marauder";"Barracks";372;2
"Unit";"Marine";"Barracks";374;1
"Unit";"Marine";"Barracks";375;1
"Unit";"Marine";"Barracks";376;1
"Unit";"Marine";"Barracks";377;1
"Unit";"Marine";"Barracks";378;1
"Unit";"Marine";"Barracks";379;1
"Upgrade";"SprayTerran";NA;380;0
"Upgrade";"SprayTerran";NA;380;0
"Upgrade";"SprayTerran";NA;380;0
"Upgrade";"SprayTerran";NA;380;0
"Upgrade";"TerranInfantryArmorsLevel1";NA;380;0
"Upgrade";"ShieldWall";NA;380;0
"Upgrade";"SprayTerran";NA;380;0
"Upgrade";"SprayTerran";NA;380;0
"Upgrade";"TerranInfantryArmorsLevel2";NA;380;0
"Upgrade";"TerranVehicleAndShipArmorsLevel1";NA;380;0
"Upgrade";"SprayTerran";NA;380;0
"Upgrade";"TerranInfantryArmorsLevel3";NA;380;0
"Upgrade";"SprayTerran";NA;380;0
