"Type";"UnitName";"OnBuilding";"TotalSupply";"Supply"
"Unit";"SCV";"Command Center";12;1
"Unit";"SCV";"Command Center";13;1
"Unit";"SCV";"Command Center";13;1
"Building";"SupplyDepot";NA;13;0
"Unit";"SCV";"Command Center";15;1
"Unit";"SCV";"Command Center";16;1
"Building";"Refinery";NA;15;0
"Unit";"SCV";"Command Center";16;1
"Building";"Barracks";NA;15;0
"Unit";"SCV";"Command Center";17;1
"Unit";"Reaper";"Barracks";19;1
"Building";"Refinery";NA;19;0
"Unit";"SCV";"Command Center";19;1
"Building";"SupplyDepot";NA;19;0
"Unit";"SCV";"Command Center";20;1
"Unit";"SCV";"Command Center";21;1
"Building";"BarracksReactor";NA;20;0
"Building";"CommandCenter";NA;19;0
"Unit";"Marine";"Barracks";23;1
"Unit";"Marine";"Barracks";23;1
"Unit";"SCV";"Command Center";23;1
"Building";"Factory";NA;21;0
"Unit";"SCV";"Command Center";26;1
"Unit";"Marine";"Barracks";23;1
"Unit";"Marine";"Barracks";24;1
"Unit";"SCV";"Command Center";26;1
"Unit";"SCV";"Command Center";29;1
"Unit";"Marine";"Barracks";29;1
"Unit";"SCV";"Command Center";29;1
"Unit";"Marine";"Barracks";29;1
"Unit";"Cyclone";"Factory";27;3
"Building";"Starport";NA;26;0
"Unit";"SCV";"Command Center";30;1
"Unit";"SCV";"Command Center";32;1
"Building";"SupplyDepot";NA;30;0
"Unit";"Marine";"Barracks";37;1
"Unit";"Marine";"Barracks";37;1
"Unit";"SCV";"Command Center";37;1
"Unit";"SCV";"Command Center";39;1
"Unit";"SCV";"Command Center";43;1
"Building";"SupplyDepot";NA;39;0
"Unit";"SCV";"Command Center";43;1
"Unit";"Marine";"Barracks";43;1
"Unit";"Marine";"Barracks";43;1
"Unit";"Liberator";"Starport";37;3
"Unit";"SCV";"Command Center";47;1
"Unit";"SCV";"Command Center";47;1
"Building";"SupplyDepot";NA;45;0
"Unit";"Cyclone";"Factory";45;3
"Unit";"SCV";"Command Center";52;1
"Unit";"SCV";"Command Center";52;1
"Building";"BarracksTechLab";NA;51;0
"Unit";"SCV";"Command Center";57;1
"Unit";"SCV";"Command Center";57;1
"Unit";"Liberator";"Starport";50;3
"Building";"Refinery";NA;57;0
"Building";"FactoryReactor";NA;55;0
"Building";"Refinery";NA;57;0
"Unit";"SCV";"Command Center";57;1
"Unit";"SCV";"Command Center";59;1
"Building";"Barracks";NA;52;0
"Unit";"SCV";"Command Center";63;1
"Building";"Barracks";NA;55;0
"Building";"EngineeringBay";NA;59;0
"Unit";"SCV";"Command Center";63;1
"Building";"Barracks";NA;57;0
"Building";"EngineeringBay";NA;59;0
"Building";"CommandCenter";NA;47;0
"Unit";"SCV";"Command Center";65;1
"Building";"StarportReactor";NA;62;0
"Unit";"Marine";"Barracks";66;1
"Unit";"Marine";"Barracks";66;1
"Building";"FactoryTechLab";NA;66;0
"Unit";"Marine";"Barracks";67;1
"Unit";"Marine";"Barracks";67;1
"Unit";"Marine";"Barracks";67;1
"Unit";"Marine";"Barracks";67;1
"Building";"BarracksReactor";NA;66;0
"Unit";"SCV";"Command Center";69;1
"Unit";"SCV";"Command Center";69;1
"Building";"SupplyDepot";NA;69;0
"Unit";"Medivac";"Starport";67;2
"Unit";"Medivac";"Starport";67;2
"Building";"Barracks";NA;66;0
"Unit";"Marine";"Barracks";73;1
"Unit";"Marine";"Barracks";73;1
"Unit";"Marine";"Barracks";73;1
"Unit";"Marine";"Barracks";73;1
"Building";"SupplyDepot";NA;72;0
"Unit";"SCV";"Command Center";79;1
"Unit";"SCV";"Command Center";79;1
"Building";"SupplyDepot";NA;79;0
"Unit";"SCV";"Command Center";85;1
"Unit";"SCV";"Command Center";85;1
"Unit";"SCV";"Command Center";85;1
"Unit";"Marine";"Barracks";85;1
"Unit";"Marine";"Barracks";85;1
"Unit";"Medivac";"Starport";79;2
"Unit";"Medivac";"Starport";79;2
"Unit";"Marauder";"Barracks";85;2
"Upgrade";"Stimpack";"TechLab";65;0
"Unit";"SCV";"Command Center";85;1
"Unit";"SCV";"Command Center";86;1
"Building";"BarracksTechLab";NA;85;0
"Unit";"Marine";"Barracks";85;1
"Unit";"Marine";"Barracks";85;1
"Unit";"Marine";"Barracks";85;1
"Unit";"Marine";"Barracks";85;1
"Unit";"Marine";"Barracks";88;1
"Building";"SupplyDepot";NA;90;0
"Building";"SupplyDepot";NA;96;0
"Unit";"Marine";"Barracks";98;1
"Unit";"Medivac";"Starport";96;2
"Unit";"Medivac";"Starport";96;2
"Unit";"SCV";"Command Center";104;1
"Unit";"SCV";"Command Center";104;1
"Unit";"SCV";"Command Center";104;1
"Unit";"Marine";"Barracks";103;1
"Unit";"Marine";"Barracks";103;1
"Unit";"Marine";"Barracks";103;1
"Unit";"Marine";"Barracks";104;1
"Unit";"Marine";"Barracks";104;1
"Unit";"Marine";"Barracks";104;1
"Unit";"Marine";"Barracks";104;1
"Unit";"Marine";"Barracks";114;1
"Unit";"Marine";"Barracks";114;1
"Unit";"Marine";"Barracks";114;1
"Unit";"Marine";"Barracks";114;1
"Unit";"Marine";"Barracks";114;1
"Unit";"Marine";"Barracks";115;1
"Unit";"Marine";"Barracks";116;1
"Upgrade";"TerranInfantryWeaponsLevel1";"EngineeringBay";85;0
"Upgrade";"TerranInfantryArmorsLevel1";"EngineeringBay";85;0
"Unit";"SCV";"Command Center";118;1
"Unit";"SCV";"Command Center";118;1
"Unit";"SCV";"Command Center";118;1
"Building";"SupplyDepot";NA;118;0
"Building";"SupplyDepot";NA;122;0
"Building";"SupplyDepot";NA;122;0
"Unit";"Medivac";"Starport";118;2
"Unit";"SCV";"Command Center";128;1
"Unit";"SCV";"Command Center";128;1
"Unit";"SCV";"Command Center";128;1
"Unit";"SCV";"Command Center";131;1
"Building";"Armory";NA;118;0
"Unit";"SCV";"Command Center";133;1
"Unit";"SCV";"Command Center";133;1
"Unit";"Medivac";"Starport";128;2
"Building";"Barracks";NA;125;0
"Unit";"Marine";"Barracks";133;1
"Unit";"Marine";"Barracks";133;1
"Unit";"Marine";"Barracks";133;1
"Unit";"Marine";"Barracks";133;1
"Unit";"Marine";"Barracks";133;1
"Building";"Barracks";NA;128;0
"Unit";"Marauder";"Barracks";133;2
"Unit";"SCV";"Command Center";133;1
"Unit";"Marine";"Barracks";143;1
"Unit";"Marine";"Barracks";143;1
"Unit";"Marine";"Barracks";143;1
"Unit";"Marine";"Barracks";143;1
"Unit";"Marine";"Barracks";143;1
"Unit";"Marine";"Barracks";143;1
"Building";"BarracksTechLab";NA;146;0
"Unit";"Marauder";"Barracks";146;2
"Building";"BarracksReactor";NA;146;0
"Unit";"Marine";"Barracks";152;1
"Unit";"Marine";"Barracks";152;1
"Unit";"Marine";"Barracks";152;1
"Unit";"Marine";"Barracks";152;1
"Unit";"Marine";"Barracks";152;1
"Unit";"Marine";"Barracks";152;1
"Unit";"Marine";"Barracks";152;1
"Unit";"Marine";"Barracks";152;1
"Building";"SupplyDepot";NA;154;0
"Building";"SupplyDepot";NA;154;0
"Building";"SupplyDepot";NA;154;0
"Building";"SupplyDepot";NA;154;0
"Unit";"Marine";"Barracks";162;1
"Unit";"Marine";"Barracks";162;1
"Unit";"Marine";"Barracks";162;1
"Unit";"SCV";"Command Center";162;1
"Unit";"Marine";"Barracks";162;1
"Unit";"Marine";"Barracks";162;1
"Unit";"SCV";"Command Center";162;1
"Unit";"Marine";"Barracks";162;1
"Unit";"Marine";"Barracks";162;1
"Unit";"Marine";"Barracks";162;1
"Unit";"Marine";"Barracks";162;1
"Unit";"Marine";"Barracks";162;1
"Unit";"Marine";"Barracks";162;1
"Unit";"Marine";"Barracks";162;1
"Building";"CommandCenter";NA;152;0
"Unit";"SCV";"Command Center";176;1
"Unit";"SCV";"Command Center";176;1
"Unit";"Marine";"Barracks";175;1
"Unit";"Marine";"Barracks";175;1
"Unit";"Marine";"Barracks";175;1
"Unit";"Marine";"Barracks";176;1
"Unit";"Marine";"Barracks";176;1
"Unit";"Marine";"Barracks";176;1
"Unit";"Marauder";"Barracks";175;2
"Unit";"Marauder";"Barracks";175;2
"Building";"Refinery";NA;176;0
"Building";"Refinery";NA;176;0
"Unit";"Marine";"Barracks";176;1
"Unit";"Marine";"Barracks";176;1
"Unit";"Marine";"Barracks";176;1
