"Type";"UnitName";"OnBuilding";"TotalSupply";"Supply"
"Unit";"SCV";"Command Center";12;1
"Unit";"SCV";"Command Center";12;1
"Unit";"SCV";"Command Center";13;1
"Building";"SupplyDepot";NA;13;0
"Unit";"SCV";"Command Center";15;1
"Unit";"SCV";"Command Center";15;1
"Building";"Refinery";NA;15;0
"Unit";"SCV";"Command Center";16;1
"Unit";"SCV";"Command Center";17;1
"Building";"Barracks";NA;15;0
"Unit";"Reaper";"Barracks";19;1
"Unit";"SCV";"Command Center";19;1
"Building";"SupplyDepot";NA;19;0
"Unit";"SCV";"Command Center";20;1
"Unit";"Marine";"Barracks";20;1
"Unit";"SCV";"Command Center";21;1
"Building";"Refinery";NA;21;0
"Unit";"SCV";"Command Center";23;1
"Building";"CommandCenter";NA;19;0
"Building";"BarracksReactor";NA;23;0
"Building";"Factory";NA;21;0
"Building";"Bunker";NA;25;0
"Unit";"SCV";"Command Center";25;1
"Unit";"Marine";"Barracks";25;1
"Unit";"Marine";"Barracks";25;1
"Building";"Bunker";NA;25;0
"Building";"SupplyDepot";NA;25;0
"Unit";"SCV";"Command Center";25;1
"Unit";"Cyclone";"Factory";25;3
"Unit";"Marine";"Barracks";28;1
"Unit";"Marine";"Barracks";28;1
"Building";"Starport";NA;25;0
"Unit";"SCV";"Command Center";34;1
"Unit";"Marine";"Barracks";34;1
"Unit";"Marine";"Barracks";34;1
"Building";"FactoryTechLab";NA;34;0
"Building";"StarportTechLab";NA;37;0
"Unit";"Marine";"Barracks";37;1
"Unit";"Marine";"Barracks";37;1
"Unit";"SCV";"Command Center";39;1
"Unit";"Marine";"Barracks";39;1
"Unit";"Marine";"Barracks";39;1
"Unit";"Banshee";"Starport";37;3
"Unit";"Marine";"Barracks";42;1
"Unit";"Marine";"Barracks";42;1
"Unit";"Marine";"Barracks";47;1
"Unit";"Raven";"Starport";47;2
"Building";"SupplyDepot";NA;48;0
"Building";"SupplyDepot";NA;48;0
"Unit";"SCV";"Command Center";50;1
"Unit";"Marine";"Barracks";50;1
"Unit";"Marine";"Barracks";50;1
"Building";"CommandCenter";NA;47;0
"Unit";"SCV";"Command Center";50;1
"Unit";"SCV";"Command Center";51;1
"Building";"Barracks";NA;48;0
"Building";"Barracks";NA;48;0
"Building";"FactoryReactor";NA;50;0
"Unit";"SCV";"Command Center";53;1
"Unit";"SCV";"Command Center";54;1
"Unit";"Marine";"Barracks";53;1
"Unit";"Marine";"Barracks";53;1
"Building";"StarportReactor";NA;50;0
"Unit";"SCV";"Command Center";55;1
"Unit";"SCV";"Command Center";56;1
"Unit";"SCV";"Command Center";59;1
"Unit";"Marine";"Barracks";59;1
"Unit";"Marine";"Barracks";59;1
"Unit";"SCV";"Command Center";60;1
"Unit";"Marine";"Barracks";59;1
"Unit";"SCV";"Command Center";66;1
"Unit";"Marine";"Barracks";61;1
"Unit";"SCV";"Command Center";66;1
"Unit";"SCV";"Command Center";66;1
"Unit";"Marine";"Barracks";66;1
"Unit";"Marine";"Barracks";66;1
"Building";"FactoryTechLab";NA;66;0
"Unit";"Marine";"Barracks";66;1
"Unit";"Medivac";"Starport";61;2
"Unit";"Medivac";"Starport";62;2
"Unit";"Marine";"Barracks";68;1
"Unit";"SCV";"Command Center";70;1
"Unit";"Marine";"Barracks";70;1
"Unit";"Marine";"Barracks";77;1
"Unit";"Marine";"Barracks";77;1
"Unit";"Medivac";"Starport";77;2
"Building";"Refinery";NA;79;0
"Building";"Refinery";NA;79;0
"Building";"EngineeringBay";NA;79;0
"Building";"SupplyDepot";NA;80;0
"Building";"EngineeringBay";NA;79;0
"Building";"SupplyDepot";NA;80;0
"Building";"SupplyDepot";NA;80;0
"Building";"SupplyDepot";NA;80;0
"Unit";"SCV";"Command Center";84;1
"Unit";"SCV";"Command Center";84;1
"Unit";"Marine";"Barracks";84;1
"Unit";"Marine";"Barracks";84;1
"Unit";"Marine";"Barracks";84;1
"Unit";"Marine";"Barracks";84;1
"Upgrade";"Stimpack";"TechLab";66;0
"Unit";"SCV";"Command Center";84;1
"Unit";"Medivac";"Starport";84;2
"Unit";"Marine";"Barracks";86;1
"Unit";"Marine";"Barracks";86;1
"Building";"Barracks";NA;82;0
"Building";"Barracks";NA;82;0
"Unit";"Marine";"Barracks";95;1
"Unit";"Marine";"Barracks";95;1
"Unit";"Marine";"Barracks";95;1
"Unit";"Marine";"Barracks";95;1
"Unit";"Marine";"Barracks";95;1
"Unit";"Marine";"Barracks";95;1
"Unit";"Marine";"Barracks";95;1
"Unit";"Medivac";"Starport";95;2
"Unit";"Medivac";"Starport";95;2
"Unit";"Marine";"Barracks";95;1
"Unit";"Marine";"Barracks";96;1
"Unit";"Marine";"Barracks";97;1
"Unit";"Marine";"Barracks";98;1
"Unit";"SCV";"Command Center";102;1
"Unit";"SCV";"Command Center";102;1
"Unit";"SCV";"Command Center";102;1
"Unit";"Marauder";"Barracks";100;2
"Unit";"Marauder";"Barracks";101;2
"Unit";"SCV";"Command Center";110;1
"Unit";"SCV";"Command Center";111;1
"Unit";"Marine";"Barracks";106;1
"Unit";"Marine";"Barracks";110;1
"Unit";"Marine";"Barracks";110;1
"Unit";"Marine";"Barracks";110;1
"Unit";"Marine";"Barracks";113;1
"Building";"BarracksReactor";NA;102;0
"Building";"Refinery";NA;115;0
"Building";"Refinery";NA;117;0
"Unit";"Medivac";"Starport";111;2
"Unit";"Medivac";"Starport";112;2
"Unit";"Marauder";"Barracks";117;2
"Upgrade";"TerranInfantryWeaponsLevel1";"EngineeringBay";93;0
"Upgrade";"TerranInfantryArmorsLevel1";"EngineeringBay";93;0
"Building";"Factory";NA;106;0
"Unit";"Marine";"Barracks";124;1
"Building";"Barracks";NA;106;0
"Unit";"Marine";"Barracks";124;1
"Unit";"Marine";"Barracks";124;1
"Building";"Barracks";NA;106;0
"Unit";"Marine";"Barracks";124;1
"Unit";"Marauder";"Barracks";123;2
"Unit";"Marine";"Barracks";124;1
"Unit";"Marine";"Barracks";124;1
"Unit";"Marine";"Barracks";128;1
"Unit";"SCV";"Command Center";130;1
"Unit";"SCV";"Command Center";130;1
"Unit";"SCV";"Command Center";130;1
"Building";"SupplyDepot";NA;130;0
"Building";"SupplyDepot";NA;130;0
"Unit";"SCV";"Command Center";139;1
"Unit";"SCV";"Command Center";140;1
"Unit";"SCV";"Command Center";142;1
"Building";"BarracksTechLab";NA;142;0
"Building";"BarracksTechLab";NA;142;0
"Building";"FactoryTechLab";NA;142;0
"Unit";"SCV";"Command Center";142;1
"Unit";"Marine";"Barracks";142;1
"Unit";"Marine";"Barracks";142;1
"Unit";"Marine";"Barracks";142;1
"Unit";"Marine";"Barracks";142;1
"Unit";"Marine";"Barracks";142;1
"Unit";"Marine";"Barracks";142;1
"Unit";"Marauder";"Barracks";142;2
"Unit";"Marauder";"Barracks";142;2
"Building";"Armory";NA;130;0
"Building";"MissileTurret";NA;144;0
"Building";"MissileTurret";NA;144;0
"Unit";"Medivac";"Starport";142;2
"Unit";"Medivac";"Starport";142;2
