"type";"unit_name";"on_building";"total_supply";"supply"
"Building";"Refinery";NA;14;0
"Building";"Barracks";NA;15;0
"Unit";"Reaper";"Barracks";19;1
"Building";"Factory";NA;19;0
"Building";"BarracksReactor";NA;20;0
"Building";"CommandCenter";NA;19;0
"Unit";"Hellion";"Factory";23;2
"Unit";"Hellion";"Factory";23;2
"Building";"BarracksTechLab";NA;24;0
"Building";"Starport";NA;23;0
"Building";"Refinery";NA;24;0
"Unit";"Hellion";"Factory";29;2
"Building";"BarracksTechLab";NA;33;0
"Building";"CommandCenter";NA;24;0
"Unit";"Marine";"Barracks";37;1
"Unit";"Banshee";"Starport";33;3
"Building";"FactoryReactor";NA;35;0
"Building";"Barracks";NA;35;0
"Unit";"Marine";"Barracks";44;1
"Building";"Barracks";NA;37;0
"Unit";"Marine";"Barracks";45;1
"Unit";"Marine";"Barracks";45;1
"Building";"EngineeringBay";NA;45;0
"Building";"EngineeringBay";NA;45;0
"Building";"Refinery";NA;48;0
"Building";"Refinery";NA;48;0
"Unit";"Marine";"Barracks";52;1
"Unit";"Marine";"Barracks";52;1
"Unit";"Marine";"Barracks";53;1
"Building";"StarportReactor";NA;45;0
"Unit";"Marine";"Barracks";55;1
"Unit";"Marine";"Barracks";55;1
"Unit";"Marine";"Barracks";59;1
"Unit";"Marine";"Barracks";59;1
"Unit";"Marine";"Barracks";59;1
"Unit";"Medivac";"Starport";59;2
"Unit";"Medivac";"Starport";59;2
"Unit";"Marine";"Barracks";64;1
"Unit";"Marine";"Barracks";64;1
"Unit";"Marine";"Barracks";66;1
"Unit";"Marine";"Barracks";70;1
"Upgrade";"Stimpack";"TechLab";45;0
"Unit";"Marine";"Barracks";70;1
"Unit";"Marine";"Barracks";78;1
"Unit";"Marine";"Barracks";78;1
"Building";"Barracks";NA;64;0
"Building";"Barracks";NA;64;0
"Unit";"Marine";"Barracks";82;1
"Unit";"Marine";"Barracks";82;1
"Unit";"Marine";"Barracks";82;1
"Building";"Armory";NA;70;0
"Unit";"Marine";"Barracks";84;1
"Unit";"Marine";"Barracks";84;1
"Unit";"Marine";"Barracks";86;1
"Unit";"Marine";"Barracks";90;1
"Unit";"Marine";"Barracks";90;1
"Building";"BarracksReactor";NA;89;0
"Building";"BarracksReactor";NA;89;0
"Upgrade";"TerranInfantryWeaponsLevel1";"EngineeringBay";70;0
"Upgrade";"TerranInfantryArmorsLevel1";"EngineeringBay";70;0
"Unit";"Marine";"Barracks";98;1
"Unit";"Marine";"Barracks";98;1
"Unit";"Marine";"Barracks";98;1
"Unit";"Marine";"Barracks";98;1
"Unit";"Marauder";"Barracks";98;2
"Unit";"Medivac";"Starport";98;2
"Unit";"Medivac";"Starport";98;2
"Unit";"Marine";"Barracks";98;1
"Unit";"Marine";"Barracks";98;1
"Unit";"Marine";"Barracks";98;1
"Unit";"Marine";"Barracks";98;1
"Unit";"Marine";"Barracks";98;1
"Building";"Barracks";NA;98;0
"Building";"Barracks";NA;98;0
"Building";"Barracks";NA;98;0
"Unit";"Marine";"Barracks";116;1
"Unit";"Marine";"Barracks";116;1
"Unit";"Marine";"Barracks";116;1
"Unit";"Marine";"Barracks";116;1
"Unit";"Marine";"Barracks";116;1
"Unit";"Marine";"Barracks";116;1
"Unit";"Marine";"Barracks";116;1
"Unit";"Marauder";"Barracks";116;2
"Unit";"Medivac";"Starport";116;2
"Unit";"Medivac";"Starport";116;2
"Unit";"Marine";"Barracks";123;1
"Unit";"Marine";"Barracks";123;1
"Unit";"Marine";"Barracks";123;1
"Unit";"Marine";"Barracks";123;1
"Unit";"Marine";"Barracks";123;1
"Unit";"Marine";"Barracks";123;1
"Unit";"Marine";"Barracks";123;1
"Unit";"Marauder";"Barracks";123;2
"Building";"CommandCenter";NA;102;0
"Unit";"Marine";"Barracks";125;1
"Building";"BarracksTechLab";NA;125;0
"Building";"BarracksTechLab";NA;125;0
"Building";"BarracksTechLab";NA;125;0
"Unit";"Marine";"Barracks";129;1
"Unit";"Marine";"Barracks";130;1
"Unit";"Marine";"Barracks";131;1
"Unit";"Marine";"Barracks";136;1
"Unit";"Marine";"Barracks";136;1
"Unit";"Marine";"Barracks";136;1
"Unit";"Marine";"Barracks";136;1
"Unit";"Marauder";"Barracks";136;2
"Unit";"Marine";"Barracks";138;1
"Unit";"Marine";"Barracks";139;1
"Building";"Refinery";NA;138;0
"Building";"Refinery";NA;138;0
"Unit";"Marine";"Barracks";148;1
"Unit";"Marine";"Barracks";150;1
"Unit";"Marine";"Barracks";150;1
"Unit";"Marine";"Barracks";150;1
"Unit";"Marine";"Barracks";150;1
"Unit";"Marine";"Barracks";150;1
"Unit";"Marauder";"Barracks";148;2
"Unit";"Marauder";"Barracks";150;2
"Unit";"Marauder";"Barracks";150;2
"Unit";"Marine";"Barracks";152;1
"Unit";"Marauder";"Barracks";151;2
"Unit";"Marine";"Barracks";152;1
"Unit";"Marine";"Barracks";152;1
"Upgrade";"TerranInfantryWeaponsLevel2";"EngineeringBay";116;0
"Unit";"Marine";"Barracks";164;1
"Unit";"Marine";"Barracks";164;1
"Unit";"Marine";"Barracks";164;1
"Unit";"Marine";"Barracks";164;1
"Unit";"Marine";"Barracks";164;1
"Unit";"Marauder";"Barracks";158;2
"Unit";"Marauder";"Barracks";164;2
"Unit";"Marine";"Barracks";168;1
"Unit";"Marine";"Barracks";168;1
"Unit";"Marine";"Barracks";168;1
"Unit";"Marauder";"Barracks";168;2
"Unit";"Marauder";"Barracks";168;2
"Unit";"Marauder";"Barracks";174;2
"Unit";"Marine";"Barracks";178;1
"Unit";"Marine";"Barracks";178;1
"Unit";"Marine";"Barracks";178;1
"Unit";"Marauder";"Barracks";178;2
"Unit";"Marine";"Barracks";181;1
"Unit";"Marauder";"Barracks";181;2
"Unit";"Marauder";"Barracks";183;2
"Unit";"Marine";"Barracks";185;1
"Unit";"Marine";"Barracks";185;1
"Unit";"Marauder";"Barracks";185;2
"Unit";"Marine";"Barracks";190;1
"Unit";"Marine";"Barracks";193;1
"Unit";"Marine";"Barracks";193;1
"Unit";"Marine";"Barracks";193;1
"Unit";"Marine";"Barracks";195;1
"Unit";"Marine";"Barracks";195;1
"Unit";"Marine";"Barracks";197;1
"Unit";"Marauder";"Barracks";193;2
"Unit";"Marauder";"Barracks";193;2
"Unit";"Marauder";"Barracks";195;2
"Unit";"Marine";"Barracks";199;1
"Unit";"Marine";"Barracks";201;1
"Upgrade";"TerranInfantryArmorsLevel2";"EngineeringBay";152;0
"Unit";"Marauder";"Barracks";199;2
"Unit";"Marine";"Barracks";202;1
"Unit";"Marine";"Barracks";203;1
"Unit";"Marine";"Barracks";204;1
"Unit";"Marine";"Barracks";214;1
"Unit";"Marine";"Barracks";214;1
"Unit";"Marine";"Barracks";214;1
"Unit";"Marauder";"Barracks";208;2
"Unit";"Marauder";"Barracks";210;2
"Unit";"Marauder";"Barracks";212;2
