"Type";"UnitName";"OnBuilding";"TotalSupply";"Supply"
"Unit";"SCV";"Command Center";12;1
"Unit";"SCV";"Command Center";12;1
"Unit";"SCV";"Command Center";13;1
"Building";"SupplyDepot";NA;13;0
"Unit";"SCV";"Command Center";15;1
"Unit";"SCV";"Command Center";15;1
"Building";"Refinery";NA;15;0
"Unit";"SCV";"Command Center";16;1
"Unit";"SCV";"Command Center";17;1
"Building";"Barracks";NA;15;0
"Unit";"Reaper";"Barracks";19;1
"Unit";"SCV";"Command Center";19;1
"Building";"SupplyDepot";NA;19;0
"Unit";"Marine";"Barracks";19;1
"Unit";"SCV";"Command Center";21;1
"Unit";"SCV";"Command Center";23;1
"Unit";"SCV";"Command Center";23;1
"Building";"Factory";NA;21;0
"Building";"CommandCenter";NA;19;0
"Unit";"SCV";"Command Center";25;1
"Building";"BarracksReactor";NA;23;0
"Unit";"SCV";"Command Center";26;1
"Unit";"SCV";"Command Center";27;1
"Unit";"Hellion";"Factory";26;2
"Unit";"Hellion";"Factory";26;2
"Building";"BarracksTechLab";NA;26;0
"Unit";"SCV";"Command Center";27;1
"Unit";"SCV";"Command Center";27;1
"Building";"Refinery";NA;27;0
"Unit";"SCV";"Command Center";32;1
"Unit";"SCV";"Command Center";33;1
"Unit";"Marine";"Barracks";33;1
"Unit";"Hellion";"Factory";33;2
"Unit";"Hellion";"Factory";33;2
"Unit";"SCV";"Command Center";34;1
"Building";"CommandCenter";NA;25;0
"Unit";"SCV";"Command Center";35;1
"Unit";"SCV";"Command Center";41;1
"Building";"SupplyDepot";NA;35;0
"Unit";"Marine";"Barracks";42;1
"Unit";"SCV";"Command Center";42;1
"Unit";"SCV";"Command Center";43;1
"Unit";"SCV";"Command Center";45;1
"Building";"SupplyDepot";NA;44;0
"Unit";"Hellion";"Factory";44;2
"Unit";"Hellion";"Factory";44;2
"Unit";"SCV";"Command Center";46;1
"Unit";"SCV";"Command Center";47;1
"Unit";"SCV";"Command Center";47;1
"Building";"SupplyDepot";NA;47;0
"Unit";"SCV";"Command Center";52;1
"Unit";"Marine";"Barracks";47;1
"Building";"Bunker";NA;45;0
"Building";"SupplyDepot";NA;47;0
"Unit";"SCV";"Command Center";57;1
"Unit";"SCV";"Command Center";57;1
"Unit";"SCV";"Command Center";57;1
"Unit";"Marine";"Barracks";55;1
"Unit";"SCV";"Command Center";60;1
"Unit";"SCV";"Command Center";60;1
"Unit";"SCV";"Command Center";60;1
"Unit";"Cyclone";"Factory";57;3
"Unit";"Cyclone";"Factory";57;3
"Unit";"Marine";"Barracks";60;1
"Building";"SupplyDepot";NA;60;0
"Unit";"SCV";"Command Center";61;1
"Unit";"SCV";"Command Center";62;1
"Unit";"SCV";"Command Center";63;1
"Unit";"SCV";"Command Center";71;1
"Unit";"SCV";"Command Center";72;1
"Unit";"SCV";"Command Center";73;1
"Building";"Barracks";NA;57;0
"Building";"Refinery";NA;70;0
"Building";"Refinery";NA;70;0
"Building";"Barracks";NA;57;0
"Unit";"Marine";"Barracks";74;1
"Building";"EngineeringBay";NA;70;0
"Unit";"Cyclone";"Factory";71;3
"Unit";"Cyclone";"Factory";71;3
"Building";"EngineeringBay";NA;71;0
"Unit";"SCV";"Command Center";74;1
"Unit";"SCV";"Command Center";75;1
"Unit";"SCV";"Command Center";76;1
"Unit";"SCV";"Command Center";84;1
"Unit";"SCV";"Command Center";85;1
"Upgrade";"Stimpack";"TechLab";53;0
"Unit";"Marine";"Barracks";77;1
"Unit";"SCV";"Command Center";87;1
"Building";"Refinery";NA;87;0
"Building";"Refinery";NA;87;0
"Unit";"SCV";"Command Center";87;1
"Unit";"SCV";"Command Center";88;1
"Building";"FactoryTechLab";NA;87;0
"Building";"MissileTurret";NA;87;0
"Building";"MissileTurret";NA;87;0
"Building";"MissileTurret";NA;90;0
"Building";"MissileTurret";NA;91;0
"Building";"BarracksReactor";NA;87;0
"Unit";"SCV";"Command Center";93;1
"Unit";"SCV";"Command Center";93;1
"Unit";"SCV";"Command Center";93;1
"Unit";"Marine";"Barracks";93;1
"Unit";"Marine";"Barracks";93;1
"Unit";"Marine";"Barracks";93;1
"Unit";"SCV";"Command Center";93;1
"Unit";"SCV";"Command Center";94;1
"Unit";"SCV";"Command Center";95;1
"Unit";"Marine";"Barracks";96;1
"Unit";"Marine";"Barracks";96;1
"Unit";"Marine";"Barracks";96;1
"Unit";"Marine";"Barracks";99;1
"Unit";"Marine";"Barracks";99;1
"Building";"Barracks";NA;91;0
"Building";"SupplyDepot";NA;99;0
"Building";"Barracks";NA;92;0
"Building";"MissileTurret";NA;102;0
"Unit";"Marine";"Barracks";105;1
"Unit";"Marine";"Barracks";105;1
"Building";"SupplyDepot";NA;105;0
"Unit";"SCV";"Command Center";107;1
"Unit";"SCV";"Command Center";107;1
"Unit";"SCV";"Command Center";107;1
"Building";"SupplyDepot";NA;105;0
"Building";"Starport";NA;99;0
"Building";"MissileTurret";NA;107;0
"Unit";"Marine";"Barracks";107;1
"Unit";"Marine";"Barracks";107;1
"Unit";"Marine";"Barracks";109;1
"Unit";"Marine";"Barracks";109;1
"Unit";"Marine";"Barracks";109;1
"Building";"SupplyDepot";NA;112;0
"Building";"BarracksReactor";NA;107;0
"Building";"BarracksReactor";NA;107;0
"Building";"SupplyDepot";NA;112;0
"Unit";"Marine";"Barracks";114;1
"Unit";"Marine";"Barracks";114;1
"Unit";"Marine";"Barracks";117;1
"Upgrade";"TerranInfantryWeaponsLevel1";"EngineeringBay";99;0
"Upgrade";"TerranInfantryArmorsLevel1";"EngineeringBay";99;0
"Building";"SupplyDepot";NA;117;0
"Building";"Armory";NA;109;0
"Building";"SupplyDepot";NA;117;0
"Unit";"Marine";"Barracks";117;1
"Unit";"Marine";"Barracks";117;1
"Unit";"Medivac";"Starport";117;2
"Unit";"Medivac";"Starport";117;2
"Unit";"Marine";"Barracks";117;1
"Unit";"Marine";"Barracks";117;1
"Unit";"Marine";"Barracks";117;1
"Building";"BarracksReactor";NA;117;0
"Unit";"Marine";"Barracks";119;1
"Unit";"Marine";"Barracks";119;1
"Unit";"Marine";"Barracks";120;1
"Unit";"Marine";"Barracks";121;1
"Building";"SupplyDepot";NA;120;0
"Unit";"Marine";"Barracks";126;1
"Unit";"Marine";"Barracks";127;1
"Unit";"Marine";"Barracks";128;1
"Unit";"Marine";"Barracks";129;1
"Unit";"Marine";"Barracks";130;1
"Unit";"Medivac";"Starport";122;2
"Unit";"Medivac";"Starport";124;2
"Unit";"Marine";"Barracks";131;1
"Unit";"Marine";"Barracks";131;1
"Unit";"Marine";"Barracks";131;1
"Unit";"Marine";"Barracks";132;1
"Unit";"Marine";"Barracks";133;1
"Unit";"Marine";"Barracks";135;1
"Unit";"Marine";"Barracks";135;1
"Building";"MissileTurret";NA;136;0
"Unit";"Marine";"Barracks";136;1
"Unit";"Marine";"Barracks";137;1
"Unit";"Marine";"Barracks";142;1
"Unit";"Marine";"Barracks";143;1
"Unit";"Marine";"Barracks";149;1
"Unit";"Marine";"Barracks";149;1
"Unit";"Marine";"Barracks";149;1
"Unit";"Medivac";"Starport";138;2
"Unit";"Marine";"Barracks";149;1
"Unit";"Medivac";"Starport";140;2
"Unit";"Marine";"Barracks";153;1
"Unit";"Marine";"Barracks";153;1
"Unit";"Marine";"Barracks";153;1
"Unit";"Marine";"Barracks";153;1
"Unit";"Marine";"Barracks";153;1
"Unit";"Marine";"Barracks";153;1
"Unit";"Marine";"Barracks";154;1
"Unit";"Marine";"Barracks";161;1
"Unit";"Marine";"Barracks";161;1
"Unit";"Medivac";"Starport";155;2
"Unit";"Medivac";"Starport";158;2
"Unit";"Marine";"Barracks";161;1
"Unit";"Marine";"Barracks";162;1
"Unit";"Marine";"Barracks";166;1
"Unit";"Marine";"Barracks";166;1
"Unit";"Marine";"Barracks";166;1
"Building";"Factory";NA;153;0
"Unit";"Marine";"Barracks";170;1
"Unit";"Marine";"Barracks";170;1
"Unit";"Marine";"Barracks";170;1
"Unit";"Marine";"Barracks";170;1
"Unit";"Marine";"Barracks";174;1
"Unit";"Marine";"Barracks";179;1
"Unit";"Marine";"Barracks";179;1
"Unit";"Marine";"Barracks";179;1
"Unit";"Marine";"Barracks";179;1
"Upgrade";"TerranVehicleWeaponsLevel1";"Armory";142;0
"Unit";"Marine";"Barracks";179;1
"Unit";"Medivac";"Starport";170;2
"Unit";"Medivac";"Starport";172;2
"Unit";"Marine";"Barracks";183;1
"Unit";"Marine";"Barracks";183;1
"Unit";"Marine";"Barracks";183;1
"Unit";"Marine";"Barracks";183;1
"Unit";"SCV";"Command Center";188;1
"Unit";"SCV";"Command Center";188;1
"Unit";"SCV";"Command Center";188;1
"Unit";"Marine";"Barracks";184;1
"Building";"FactoryTechLab";NA;188;0
"Upgrade";"TerranInfantryWeaponsLevel2";"EngineeringBay";146;0
"Upgrade";"TerranInfantryArmorsLevel2";"EngineeringBay";147;0
"Building";"CommandCenter";NA;161;0
"Unit";"Marine";"Barracks";194;1
"Unit";"SCV";"Command Center";201;1
"Unit";"SCV";"Command Center";201;1
"Unit";"Marine";"Barracks";194;1
"Unit";"SCV";"Command Center";201;1
"Unit";"Marine";"Barracks";201;1
"Unit";"Marine";"Barracks";201;1
"Building";"Refinery";NA;201;0
"Unit";"Marine";"Barracks";201;1
"Unit";"Marine";"Barracks";201;1
"Unit";"Marine";"Barracks";201;1
"Building";"Refinery";NA;201;0
"Building";"SupplyDepot";NA;201;0
"Building";"SupplyDepot";NA;201;0
"Unit";"Marine";"Barracks";206;1
"Unit";"Marine";"Barracks";206;1
"Unit";"Marine";"Barracks";206;1
"Unit";"Marine";"Barracks";206;1
"Unit";"Liberator";"Starport";193;3
"Building";"CommandCenter";NA;179;0
"Unit";"Liberator";"Starport";193;3
"Unit";"Marine";"Barracks";206;1
"Unit";"Marine";"Barracks";208;1
"Unit";"Marine";"Barracks";208;1
"Unit";"Marine";"Barracks";209;1
"Unit";"Marine";"Barracks";210;1
"Unit";"Marine";"Barracks";211;1
"Unit";"Marine";"Barracks";212;1
"Unit";"Marine";"Barracks";221;1
"Unit";"Marine";"Barracks";221;1
"Unit";"Marine";"Barracks";221;1
"Unit";"Marine";"Barracks";222;1
"Unit";"Marine";"Barracks";228;1
"Unit";"Marine";"Barracks";228;1
"Unit";"Marine";"Barracks";228;1
"Unit";"Marine";"Barracks";228;1
"Unit";"Marine";"Barracks";229;1
"Building";"GhostAcademy";NA;232;0
"Building";"Barracks";NA;232;0
"Building";"Barracks";NA;232;0
"Unit";"Marine";"Barracks";237;1
"Unit";"Marine";"Barracks";237;1
"Unit";"Marine";"Barracks";237;1
"Unit";"Thor";"Factory";237;6
"Unit";"Thor";"Factory";237;6
