"type";"unit_name";"on_building";"total_supply";"supply"
"Building";"Refinery";NA;15;0
"Building";"Barracks";NA;15;0
"Unit";"Reaper";"Barracks";19;1
"Unit";"Marine";"Barracks";19;1
"Building";"Bunker";NA;23;0
"Building";"CommandCenter";NA;19;0
"Building";"Refinery";NA;24;0
"Building";"BarracksReactor";NA;23;0
"Building";"Factory";NA;21;0
"Unit";"Hellion";"Factory";27;2
"Unit";"Hellion";"Factory";27;2
"Building";"BarracksTechLab";NA;27;0
"Building";"Starport";NA;26;0
"Unit";"Hellion";"Factory";28;2
"Unit";"Hellion";"Factory";30;2
"Building";"FactoryTechLab";NA;42;0
"Unit";"Marine";"Barracks";43;1
"Unit";"Marine";"Barracks";43;1
"Unit";"Banshee";"Starport";35;3
"Unit";"Marine";"Barracks";50;1
"Unit";"Marine";"Barracks";50;1
"Unit";"Marine";"Barracks";54;1
"Unit";"Marine";"Barracks";55;1
"Building";"Refinery";NA;54;0
"Building";"Refinery";NA;54;0
"Unit";"Marine";"Barracks";62;1
"Unit";"Marine";"Barracks";64;1
"Unit";"Marine";"Barracks";65;1
"Building";"StarportReactor";NA;64;0
"Building";"EngineeringBay";NA;65;0
"Building";"CommandCenter";NA;56;0
"Building";"EngineeringBay";NA;65;0
"Building";"Barracks";NA;62;0
"Building";"Barracks";NA;62;0
"Building";"Barracks";NA;62;0
"Unit";"Marine";"Barracks";67;1
"Unit";"Marine";"Barracks";70;1
"Unit";"Marine";"Barracks";73;1
"Building";"BarracksTechLab";NA;73;0
"Unit";"Marine";"Barracks";76;1
"Unit";"Marine";"Barracks";76;1
"Building";"BarracksReactor";NA;74;0
"Building";"Refinery";NA;79;0
"Building";"Refinery";NA;79;0
"Unit";"Marine";"Barracks";84;1
"Unit";"Marine";"Barracks";84;1
"Unit";"Marine";"Barracks";84;1
"Unit";"Marine";"Barracks";84;1
"Building";"Barracks";NA;78;0
"Building";"Barracks";NA;78;0
"Unit";"Marine";"Barracks";87;1
"Unit";"Marine";"Barracks";87;1
"Unit";"Marine";"Barracks";87;1
"Building";"Factory";NA;82;0
"Unit";"Marine";"Barracks";94;1
"Unit";"Marine";"Barracks";94;1
"Unit";"Marine";"Barracks";94;1
"Building";"BarracksTechLab";NA;94;0
"Unit";"Marine";"Barracks";95;1
"Upgrade";"TerranInfantryWeaponsLevel1";"EngineeringBay";78;0
"Building";"FactoryTechLab";NA;99;0
"Upgrade";"TerranInfantryArmorsLevel1";"EngineeringBay";78;0
"Building";"BarracksReactor";NA;94;0
"Unit";"Marine";"Barracks";102;1
"Unit";"Marine";"Barracks";102;1
"Unit";"Marine";"Barracks";102;1
"Unit";"Marine";"Barracks";102;1
"Unit";"Marine";"Barracks";102;1
"Building";"Armory";NA;94;0
"Building";"Barracks";NA;95;0
"Unit";"Marine";"Barracks";105;1
"Unit";"Marine";"Barracks";105;1
"Unit";"Marine";"Barracks";105;1
"Unit";"Marine";"Barracks";105;1
"Unit";"Marine";"Barracks";105;1
"Unit";"Marine";"Barracks";105;1
"Unit";"Marine";"Barracks";107;1
"Unit";"Marine";"Barracks";108;1
"Upgrade";"Stimpack";"TechLab";85;0
"Unit";"Marine";"Barracks";118;1
"Unit";"Marine";"Barracks";118;1
"Unit";"Marine";"Barracks";118;1
"Unit";"Marine";"Barracks";118;1
"Unit";"Marine";"Barracks";118;1
"Unit";"Marine";"Barracks";118;1
"Unit";"Marine";"Barracks";118;1
"Building";"BarracksTechLab";NA;118;0
"Unit";"Medivac";"Starport";118;2
"Unit";"Medivac";"Starport";118;2
"Unit";"Marine";"Barracks";125;1
"Unit";"Marine";"Barracks";125;1
"Unit";"Marine";"Barracks";125;1
"Unit";"Marine";"Barracks";125;1
"Unit";"Marine";"Barracks";125;1
"Unit";"Marine";"Barracks";125;1
"Building";"CommandCenter";NA;110;0
"Unit";"Marine";"Barracks";125;1
"Unit";"Marine";"Barracks";125;1
"Unit";"Marine";"Barracks";125;1
"Unit";"Marine";"Barracks";135;1
"Unit";"Marine";"Barracks";135;1
"Unit";"Marine";"Barracks";135;1
"Unit";"Marine";"Barracks";135;1
"Unit";"Marine";"Barracks";135;1
"Unit";"Marine";"Barracks";135;1
"Unit";"Marauder";"Barracks";135;2
"Unit";"Marauder";"Barracks";135;2
"Unit";"Marauder";"Barracks";135;2
"Unit";"Marauder";"Barracks";135;2
"Unit";"Marine";"Barracks";138;1
"Unit";"Medivac";"Starport";135;2
"Unit";"Medivac";"Starport";138;2
"Upgrade";"TerranVehicleWeaponsLevel1";"Armory";125;0
"Building";"Refinery";NA;155;0
"Building";"Refinery";NA;157;0
"Unit";"Medivac";"Starport";155;2
"Unit";"Marine";"Barracks";157;1
"Unit";"Marine";"Barracks";157;1
"Unit";"Marine";"Barracks";157;1
"Unit";"Marine";"Barracks";157;1
"Unit";"Marine";"Barracks";157;1
"Unit";"Marine";"Barracks";157;1
"Unit";"Marine";"Barracks";157;1
"Unit";"Marine";"Barracks";157;1
"Unit";"Medivac";"Starport";155;2
"Unit";"Marauder";"Barracks";157;2
"Unit";"Marauder";"Barracks";157;2
"Upgrade";"TerranInfantryArmorsLevel2";"EngineeringBay";125;0
"Upgrade";"TerranInfantryWeaponsLevel2";"EngineeringBay";125;0
"Unit";"Marine";"Barracks";159;1
"Unit";"Marine";"Barracks";173;1
"Unit";"Marine";"Barracks";173;1
"Unit";"Marine";"Barracks";173;1
"Unit";"Marine";"Barracks";173;1
"Unit";"Marine";"Barracks";173;1
"Unit";"Marine";"Barracks";173;1
"Unit";"Marine";"Barracks";173;1
"Unit";"Marine";"Barracks";173;1
"Building";"CommandCenter";NA;157;0
"Unit";"Marine";"Barracks";182;1
"Unit";"Medivac";"Starport";182;2
"Unit";"Medivac";"Starport";182;2
"Unit";"Marine";"Barracks";183;1
"Unit";"Marine";"Barracks";183;1
"Unit";"Marine";"Barracks";183;1
"Unit";"Marine";"Barracks";183;1
"Unit";"Marine";"Barracks";183;1
"Unit";"Marine";"Barracks";183;1
"Unit";"Marine";"Barracks";183;1
"Unit";"Marine";"Barracks";183;1
"Unit";"Marauder";"Barracks";183;2
"Unit";"Marauder";"Barracks";183;2
"Unit";"Marine";"Barracks";187;1
"Unit";"Marine";"Barracks";188;1
"Unit";"Marine";"Barracks";189;1
"Unit";"Marine";"Barracks";189;1
"Unit";"Marine";"Barracks";191;1
"Unit";"Marine";"Barracks";191;1
"Unit";"Marine";"Barracks";193;1
"Unit";"Marine";"Barracks";199;1
"Unit";"Marauder";"Barracks";199;2
"Unit";"Marauder";"Barracks";199;2
"Building";"Refinery";NA;199;0
"Unit";"Marine";"Barracks";199;1
"Building";"Refinery";NA;199;0
"Unit";"Marine";"Barracks";200;1
"Unit";"Marine";"Barracks";207;1
"Unit";"Marine";"Barracks";207;1
"Unit";"Marine";"Barracks";207;1
"Unit";"Marine";"Barracks";207;1
"Unit";"Marine";"Barracks";207;1
"Unit";"Marine";"Barracks";207;1
"Upgrade";"TerranVehicleWeaponsLevel2";"Armory";182;0
"Unit";"Marine";"Barracks";207;1
"Unit";"Marine";"Barracks";209;1
"Unit";"Marine";"Barracks";225;1
"Unit";"Marine";"Barracks";225;1
"Unit";"Medivac";"Starport";213;2
"Unit";"Marine";"Barracks";233;1
"Unit";"Marine";"Barracks";233;1
"Unit";"Marine";"Barracks";233;1
"Unit";"Marine";"Barracks";233;1
"Upgrade";"TerranInfantryWeaponsLevel3";"EngineeringBay";187;0
"Upgrade";"TerranInfantryArmorsLevel3";"EngineeringBay";187;0
"Unit";"Marine";"Barracks";237;1
"Unit";"Marine";"Barracks";237;1
"Unit";"Marine";"Barracks";237;1
"Unit";"Marine";"Barracks";237;1
"Unit";"Marine";"Barracks";237;1
"Unit";"Marine";"Barracks";237;1
"Unit";"Marine";"Barracks";240;1
"Unit";"Marine";"Barracks";241;1
"Unit";"Marine";"Barracks";242;1
"Unit";"Marine";"Barracks";242;1
"Unit";"Marine";"Barracks";244;1
"Unit";"Marine";"Barracks";245;1
"Unit";"Marine";"Barracks";249;1
"Unit";"Marauder";"Barracks";245;2
"Unit";"Marauder";"Barracks";247;2
"Unit";"Marauder";"Barracks";248;2
"Unit";"Marine";"Barracks";250;1
"Unit";"Marine";"Barracks";251;1
"Unit";"Marine";"Barracks";254;1
"Unit";"Marine";"Barracks";254;1
"Unit";"Marauder";"Barracks";257;2
"Unit";"Liberator";"Starport";250;3
"Unit";"Liberator";"Starport";250;3
"Unit";"Thor";"Factory";254;6
"Unit";"Thor";"Factory";254;6
"Unit";"Marine";"Barracks";271;1
"Unit";"Marauder";"Barracks";271;2
"Unit";"Marauder";"Barracks";271;2
"Unit";"Medivac";"Starport";277;2
"Unit";"Medivac";"Starport";277;2
"Building";"Starport";NA;277;0
"Building";"CommandCenter";NA;267;0
"Building";"SensorTower";NA;298;0
"Unit";"Marine";"Barracks";298;1
"Unit";"Marine";"Barracks";298;1
"Unit";"Marine";"Barracks";298;1
"Unit";"Marine";"Barracks";298;1
"Unit";"Marine";"Barracks";298;1
"Unit";"Marauder";"Barracks";298;2
"Unit";"Marauder";"Barracks";298;2
"Unit";"Liberator";"Starport";298;3
"Unit";"Liberator";"Starport";298;3
"Unit";"Thor";"Factory";298;6
"Unit";"Thor";"Factory";298;6
"Building";"StarportReactor";NA;298;0
"Unit";"Medivac";"Starport";313;2
"Unit";"Medivac";"Starport";313;2
"Building";"FusionCore";NA;317;0
"Unit";"Liberator";"Starport";332;3
"Unit";"Liberator";"Starport";332;3
"Unit";"Medivac";"Starport";336;2
"Unit";"Medivac";"Starport";336;2
"Upgrade";"TerranVehicleWeaponsLevel3";"Armory";298;0
"Unit";"Thor";"Factory";336;6
"Unit";"Marine";"Barracks";342;1
"Unit";"Marine";"Barracks";342;1
"Unit";"Marine";"Barracks";342;1
"Unit";"Marine";"Barracks";342;1
"Unit";"Marine";"Barracks";342;1
"Unit";"Marine";"Barracks";342;1
"Unit";"Marauder";"Barracks";342;2
"Unit";"Marauder";"Barracks";342;2
"Unit";"Marine";"Barracks";362;1
"Unit";"Marine";"Barracks";362;1
"Unit";"Marine";"Barracks";362;1
"Unit";"Marine";"Barracks";362;1
"Unit";"Marine";"Barracks";362;1
"Unit";"Marine";"Barracks";362;1
"Unit";"Marine";"Barracks";362;1
"Unit";"Marine";"Barracks";362;1
"Unit";"Marine";"Barracks";362;1
"Unit";"Marine";"Barracks";362;1
"Unit";"Marine";"Barracks";362;1
"Unit";"Marine";"Barracks";363;1
"Unit";"Marine";"Barracks";364;1
"Unit";"Marine";"Barracks";365;1
"Unit";"Marine";"Barracks";365;1
"Unit";"Marauder";"Barracks";368;2
"Unit";"Marauder";"Barracks";369;2
"Unit";"Marauder";"Barracks";372;2
"Unit";"Marine";"Barracks";372;1
