"Type";"UnitName";"OnBuilding";"TotalSupply";"Supply"
"Unit";"SCV";"Command Center";12;1
"Unit";"SCV";"Command Center";12;1
"Unit";"SCV";"Command Center";13;1
"Building";"SupplyDepot";NA;13;0
"Unit";"SCV";"Command Center";15;1
"Unit";"SCV";"Command Center";15;1
"Building";"Refinery";NA;15;0
"Unit";"SCV";"Command Center";17;1
"Building";"Barracks";NA;15;0
"Unit";"SCV";"Command Center";17;1
"Building";"Barracks";NA;16;0
"Building";"SupplyDepot";NA;19;0
"Unit";"Reaper";"Barracks";18;1
"Unit";"SCV";"Command Center";19;1
"Unit";"Reaper";"Barracks";19;1
"Unit";"SCV";"Command Center";21;1
"Unit";"SCV";"Command Center";22;1
"Unit";"Reaper";"Barracks";20;1
"Unit";"SCV";"Command Center";23;1
"Building";"BarracksReactor";NA;22;0
"Unit";"SCV";"Command Center";26;1
"Building";"BarracksTechLab";NA;26;0
"Unit";"SCV";"Command Center";26;1
"Building";"Refinery";NA;26;0
"Unit";"SCV";"Command Center";27;1
"Building";"CommandCenter";NA;21;0
"Unit";"Marine";"Barracks";28;1
"Unit";"Marine";"Barracks";28;1
"Unit";"Marine";"Barracks";28;1
"Unit";"SCV";"Command Center";28;1
"Unit";"SCV";"Command Center";32;1
"Unit";"Marine";"Barracks";33;1
"Unit";"Marine";"Barracks";33;1
"Unit";"Marine";"Barracks";33;1
"Unit";"SCV";"Command Center";33;1
"Building";"CommandCenter";NA;26;0
"Unit";"SCV";"Command Center";37;1
"Unit";"Marine";"Barracks";38;1
"Unit";"Marine";"Barracks";38;1
"Unit";"Marine";"Barracks";38;1
"Unit";"SCV";"Command Center";39;1
"Building";"Factory";NA;33;0
"Unit";"Marine";"Barracks";39;1
"Unit";"Marine";"Barracks";40;1
"Unit";"Marine";"Barracks";41;1
"Unit";"SCV";"Command Center";43;1
"Unit";"SCV";"Command Center";43;1
"Unit";"SCV";"Command Center";43;1
"Unit";"SCV";"Command Center";46;1
"Unit";"SCV";"Command Center";47;1
"Unit";"Marine";"Barracks";43;1
"Unit";"SCV";"Command Center";49;1
"Unit";"Marine";"Barracks";48;1
"Unit";"Marine";"Barracks";48;1
"Building";"Barracks";NA;39;0
"Unit";"SCV";"Command Center";49;1
"Unit";"SCV";"Command Center";50;1
"Building";"FactoryReactor";NA;43;0
"Building";"Starport";NA;43;0
"Unit";"SCV";"Command Center";52;1
"Building";"SupplyDepot";NA;49;0
"Upgrade";"Stimpack";"TechLab";34;0
"Unit";"SCV";"Command Center";55;1
"Unit";"SCV";"Command Center";56;1
"Unit";"Marine";"Barracks";57;1
"Unit";"Marine";"Barracks";57;1
"Unit";"SCV";"Command Center";58;1
"Building";"EngineeringBay";NA;57;0
"Unit";"SCV";"Command Center";62;1
"Building";"EngineeringBay";NA;57;0
"Building";"FactoryTechLab";NA;60;0
"Unit";"SCV";"Command Center";62;1
"Unit";"Marine";"Barracks";62;1
"Building";"BarracksReactor";NA;57;0
"Unit";"Marine";"Barracks";62;1
"Unit";"Marine";"Barracks";62;1
"Unit";"SCV";"Command Center";63;1
"Building";"Refinery";NA;63;0
"Building";"Refinery";NA;63;0
"Unit";"SCV";"Command Center";64;1
"Unit";"Medivac";"Starport";63;2
"Building";"SupplyDepot";NA;69;0
"Unit";"SCV";"Command Center";70;1
"Unit";"SCV";"Command Center";70;1
"Unit";"SCV";"Command Center";72;1
"Building";"Barracks";NA;63;0
"Building";"Barracks";NA;63;0
"Building";"SupplyDepot";NA;70;0
"Building";"SupplyDepot";NA;70;0
"Unit";"Marine";"Barracks";70;1
"Unit";"Marine";"Barracks";70;1
"Unit";"Marine";"Barracks";70;1
"Unit";"Marine";"Barracks";70;1
"Unit";"Marine";"Barracks";70;1
"Unit";"SCV";"Command Center";72;1
"Unit";"SCV";"Command Center";72;1
"Unit";"SCV";"Command Center";74;1
"Building";"SupplyDepot";NA;72;0
"Unit";"Marine";"Barracks";75;1
"Unit";"Marine";"Barracks";75;1
"Unit";"SCV";"Command Center";80;1
"Unit";"SCV";"Command Center";80;1
"Unit";"SCV";"Command Center";82;1
"Unit";"Marine";"Barracks";80;1
"Unit";"Marine";"Barracks";80;1
"Unit";"SCV";"Command Center";85;1
"Building";"SupplyDepot";NA;83;0
"Building";"SupplyDepot";NA;83;0
"Building";"SupplyDepot";NA;83;0
"Building";"BarracksReactor";NA;80;0
"Building";"BarracksReactor";NA;80;0
"Unit";"Marine";"Barracks";90;1
"Unit";"Marine";"Barracks";91;1
"Unit";"Marine";"Barracks";91;1
"Unit";"Marine";"Barracks";91;1
"Unit";"Marauder";"Barracks";90;2
"Unit";"SCV";"Command Center";91;1
"Unit";"SCV";"Command Center";91;1
"Unit";"SCV";"Command Center";91;1
"Unit";"Medivac";"Starport";91;2
"Unit";"Marine";"Barracks";91;1
"Unit";"Medivac";"Starport";91;2
"Unit";"Marine";"Barracks";91;1
"Unit";"Marine";"Barracks";91;1
"Unit";"Marine";"Barracks";91;1
"Unit";"Marine";"Barracks";91;1
"Unit";"SCV";"Command Center";97;1
"Unit";"Marine";"Barracks";92;1
"Unit";"SCV";"Command Center";98;1
"Upgrade";"TerranInfantryWeaponsLevel1";"EngineeringBay";72;0
"Unit";"SCV";"Command Center";100;1
"Upgrade";"TerranInfantryArmorsLevel1";"EngineeringBay";72;0
"Building";"Armory";NA;91;0
"Unit";"Marine";"Barracks";113;1
"Unit";"Marine";"Barracks";113;1
"Unit";"Marine";"Barracks";113;1
"Unit";"Marine";"Barracks";113;1
"Unit";"Marine";"Barracks";113;1
"Unit";"Marine";"Barracks";113;1
"Unit";"Marine";"Barracks";113;1
"Unit";"Marine";"Barracks";113;1
"Unit";"Marauder";"Barracks";113;2
"Building";"Barracks";NA;100;0
"Unit";"SCV";"Command Center";113;1
"Unit";"SCV";"Command Center";113;1
"Unit";"SCV";"Command Center";113;1
"Building";"Barracks";NA;108;0
"Unit";"Marine";"Barracks";113;1
"Unit";"Marine";"Barracks";114;1
"Unit";"Marine";"Barracks";115;1
"Unit";"Marine";"Barracks";116;1
"Unit";"SCV";"Command Center";123;1
"Unit";"SCV";"Command Center";124;1
"Unit";"Marine";"Barracks";123;1
"Building";"CommandCenter";NA;91;0
"Unit";"Medivac";"Starport";113;2
"Unit";"Medivac";"Starport";113;2
"Unit";"Marine";"Barracks";123;1
"Unit";"Marauder";"Barracks";121;2
"Unit";"Marine";"Barracks";130;1
"Building";"BarracksTechLab";NA;131;0
"Unit";"Marine";"Barracks";132;1
"Unit";"Marauder";"Barracks";138;2
"Unit";"Marine";"Barracks";140;1
"Unit";"Marine";"Barracks";140;1
"Unit";"Marine";"Barracks";140;1
"Unit";"Marine";"Barracks";140;1
"Unit";"Marine";"Barracks";140;1
"Unit";"Marine";"Barracks";140;1
"Building";"BarracksReactor";NA;130;0
"Unit";"Marine";"Barracks";141;1
"Unit";"Marine";"Barracks";141;1
"Unit";"Marine";"Barracks";142;1
"Unit";"Marine";"Barracks";144;1
"Unit";"Marine";"Barracks";145;1
"Building";"Barracks";NA;132;0
"Unit";"Marauder";"Barracks";142;2
"Building";"MissileTurret";NA;150;0
"Building";"MissileTurret";NA;150;0
"Building";"Barracks";NA;133;0
"Unit";"Marine";"Barracks";151;1
"Unit";"Marine";"Barracks";151;1
"Unit";"Marine";"Barracks";151;1
"Building";"SupplyDepot";NA;152;0
"Unit";"Marauder";"Barracks";153;2
"Unit";"Medivac";"Starport";151;2
"Unit";"Medivac";"Starport";151;2
"Unit";"Marauder";"Barracks";155;2
"Unit";"Marine";"Barracks";160;1
"Unit";"Marine";"Barracks";160;1
"Unit";"Marine";"Barracks";160;1
"Unit";"Marine";"Barracks";160;1
"Unit";"Marine";"Barracks";160;1
"Unit";"Marine";"Barracks";160;1
"Unit";"Marine";"Barracks";160;1
"Unit";"Marine";"Barracks";160;1
"Unit";"Marine";"Barracks";160;1
"Unit";"Marine";"Barracks";160;1
"Unit";"Marauder";"Barracks";160;2
"Building";"BarracksTechLab";NA;168;0
"Unit";"Marauder";"Barracks";166;2
"Unit";"Marine";"Barracks";168;1
"Unit";"Marine";"Barracks";169;1
"Unit";"Marine";"Barracks";170;1
"Unit";"Marine";"Barracks";171;1
"Unit";"Marine";"Barracks";172;1
"Unit";"Marine";"Barracks";173;1
"Unit";"Marine";"Barracks";174;1
"Unit";"Marine";"Barracks";178;1
"Unit";"Marine";"Barracks";178;1
"Unit";"Marine";"Barracks";178;1
"Unit";"SCV";"Command Center";182;1
"Unit";"SCV";"Command Center";182;1
"Unit";"SCV";"Command Center";182;1
"Building";"BarracksReactor";NA;168;0
"Unit";"Marauder";"Barracks";178;2
"Unit";"Marauder";"Barracks";180;2
"Unit";"Marauder";"Barracks";180;2
"Unit";"Marine";"Barracks";182;1
"Unit";"Marine";"Barracks";183;1
"Unit";"Marine";"Barracks";184;1
"Unit";"Medivac";"Starport";178;2
"Building";"GhostAcademy";NA;180;0
"Unit";"Marine";"Barracks";192;1
"Upgrade";"TerranInfantryWeaponsLevel2";"EngineeringBay";142;0
"Unit";"Marine";"Barracks";192;1
"Unit";"Marine";"Barracks";192;1
"Upgrade";"TerranInfantryArmorsLevel2";"EngineeringBay";142;0
"Unit";"Marine";"Barracks";192;1
"Unit";"Marine";"Barracks";201;1
"Unit";"Marine";"Barracks";201;1
"Unit";"Marine";"Barracks";201;1
"Unit";"Marine";"Barracks";201;1
"Unit";"Marine";"Barracks";201;1
"Unit";"Marine";"Barracks";201;1
"Unit";"Marine";"Barracks";202;1
"Unit";"Marine";"Barracks";203;1
"Unit";"Marauder";"Barracks";201;2
"Unit";"Marauder";"Barracks";201;2
"Unit";"Marauder";"Barracks";201;2
"Unit";"Marine";"Barracks";206;1
"Unit";"Marine";"Barracks";210;1
"Unit";"Marine";"Barracks";210;1
"Unit";"Marine";"Barracks";210;1
"Unit";"Marine";"Barracks";210;1
"Unit";"Marine";"Barracks";225;1
"Unit";"Marine";"Barracks";225;1
"Unit";"Marine";"Barracks";225;1
"Unit";"Marauder";"Barracks";218;2
"Unit";"Marine";"Barracks";225;1
"Unit";"Marine";"Barracks";226;1
"Unit";"Marine";"Barracks";227;1
"Unit";"Marauder";"Barracks";220;2
"Unit";"Marine";"Barracks";227;1
"Unit";"Marine";"Barracks";227;1
"Unit";"Marauder";"Barracks";222;2
"Unit";"Marine";"Barracks";227;1
"Unit";"Marine";"Barracks";227;1
"Unit";"Marine";"Barracks";228;1
"Building";"CommandCenter";NA;192;0
"Unit";"Marine";"Barracks";229;1
"Unit";"Marine";"Barracks";230;1
"Unit";"Marine";"Barracks";231;1
"Unit";"Marine";"Barracks";245;1
"Unit";"Marine";"Barracks";245;1
"Unit";"Marine";"Barracks";245;1
"Unit";"Marine";"Barracks";245;1
"Unit";"Marauder";"Barracks";245;2
"Unit";"Marauder";"Barracks";245;2
"Unit";"Marine";"Barracks";246;1
"Unit";"Marine";"Barracks";246;1
"Unit";"Marine";"Barracks";249;1
"Unit";"Marauder";"Barracks";246;2
"Unit";"Marine";"Barracks";249;1
"Unit";"Marine";"Barracks";249;1
"Upgrade";"TerranVehicleAndShipArmorsLevel1";"Armory";206;0
"Unit";"Marauder";"Barracks";253;2
"Unit";"Marauder";"Barracks";255;2
"Unit";"Marine";"Barracks";258;1
"Unit";"Marine";"Barracks";260;1
"Unit";"Marine";"Barracks";260;1
"Unit";"Marine";"Barracks";260;1
"Unit";"Marine";"Barracks";260;1
"Unit";"Marine";"Barracks";262;1
"Unit";"Marine";"Barracks";262;1
"Unit";"Marine";"Barracks";262;1
"Unit";"Marine";"Barracks";262;1
"Unit";"Marine";"Barracks";262;1
"Unit";"Marine";"Barracks";263;1
"Unit";"Marauder";"Barracks";260;2
"Unit";"Marine";"Barracks";268;1
"Unit";"Marauder";"Barracks";264;2
"Unit";"Marauder";"Barracks";266;2
"Unit";"Marine";"Barracks";269;1
"Unit";"Marine";"Barracks";270;1
"Unit";"Marine";"Barracks";271;1
"Unit";"Marine";"Barracks";272;1
"Unit";"Marine";"Barracks";273;1
"Unit";"Marine";"Barracks";274;1
"Unit";"Marine";"Barracks";275;1
"Unit";"Marauder";"Barracks";279;2
"Unit";"Marine";"Barracks";281;1
"Unit";"Marine";"Barracks";281;1
"Unit";"Marine";"Barracks";281;1
"Unit";"Marine";"Barracks";286;1
"Unit";"Marine";"Barracks";286;1
"Unit";"Marine";"Barracks";293;1
"Unit";"Medivac";"Starport";281;2
"Unit";"Marine";"Barracks";293;1
"Unit";"Medivac";"Starport";281;2
"Unit";"Marine";"Barracks";293;1
"Unit";"Marine";"Barracks";293;1
"Unit";"Marine";"Barracks";293;1
"Unit";"Marine";"Barracks";293;1
"Unit";"Marine";"Barracks";298;1
"Unit";"Marine";"Barracks";298;1
"Unit";"Marine";"Barracks";298;1
"Unit";"Marauder";"Barracks";298;2
"Unit";"Marine";"Barracks";298;1
"Unit";"Marauder";"Barracks";298;2
"Unit";"Marine";"Barracks";300;1
"Building";"Refinery";NA;300;0
"Building";"Refinery";NA;300;0
"Unit";"Marauder";"Barracks";300;2
"Unit";"Marine";"Barracks";310;1
"Unit";"Medivac";"Starport";310;2
"Unit";"Medivac";"Starport";310;2
"Unit";"Marauder";"Barracks";313;2
"Upgrade";"TerranInfantryWeaponsLevel3";"EngineeringBay";268;0
"Upgrade";"TerranInfantryArmorsLevel3";"EngineeringBay";268;0
"Building";"SupplyDepot";NA;328;0
"Building";"SupplyDepot";NA;328;0
"Building";"Refinery";NA;328;0
"Building";"Refinery";NA;328;0
"Building";"BarracksReactor";NA;328;0
"Unit";"Marine";"Barracks";328;1
"Unit";"Medivac";"Starport";328;2
"Unit";"Medivac";"Starport";328;2
"Unit";"Marine";"Barracks";328;1
"Building";"SupplyDepot";NA;328;0
"Building";"SupplyDepot";NA;328;0
"Unit";"Ghost";"Barracks";328;2
"Unit";"Ghost";"Barracks";328;2
"Unit";"Ghost";"Barracks";328;2
"Upgrade";"TerranVehicleAndShipArmorsLevel2";"Armory";313;0
"Building";"CommandCenter";NA;328;0
"Unit";"Marauder";"Barracks";334;2
"Unit";"Medivac";"Starport";329;2
"Building";"BarracksTechLab";NA;340;0
"Building";"BarracksTechLab";NA;340;0
"Unit";"Ghost";"Barracks";340;2
"Unit";"Ghost";"Barracks";340;2
"Upgrade";"NeosteelFrame";"EngineeringBay";329;0
"Unit";"Ghost";"Barracks";340;2
"Unit";"Ghost";"Barracks";344;2
"Unit";"Ghost";"Barracks";346;2
"Unit";"Ghost";"Barracks";348;2
"Unit";"Ghost";"Barracks";348;2
"Unit";"Marauder";"Barracks";354;2
"Building";"CommandCenter";NA;340;0
"Unit";"Ghost";"Barracks";354;2
"Building";"CommandCenter";NA;342;0
