"type";"unit_name";"on_building";"total_supply_lag";"supply"
"Building";"Barracks";NA;16;0
"Building";"Refinery";NA;16;0
"Unit";"Reaper";"Barracks";19;1
"Building";"CommandCenter";NA;20;0
"Unit";"Marine";"Barracks";21;1
"Building";"Factory";NA;22;0
"Building";"Refinery";NA;23;0
"Building";"BarracksReactor";NA;24;0
"Building";"Starport";NA;27;0
"Unit";"Hellion";"Factory";28;2
"Unit";"Hellion";"Factory";30;2
"Building";"FusionCore";NA;36;0
"Building";"CommandCenter";NA;38;0
"Unit";"Hellion";"Factory";39;2
"Unit";"Hellion";"Factory";41;2
"Building";"StarportTechLab";NA;44;0
"Unit";"Hellion";"Factory";46;2
"Unit";"Hellion";"Factory";49;2
"Unit";"Liberator";"Starport";52;3
"Building";"Refinery";NA;57;0
"Unit";"Hellion";"Factory";57;2
"Building";"Refinery";NA;59;0
"Unit";"Hellion";"Factory";59;2
"Unit";"Hellion";"Factory";65;2
"Unit";"Hellion";"Factory";67;2
"Unit";"Liberator";"Starport";71;3
"Building";"Armory";NA;74;0
"Building";"Armory";NA;74;0
"Unit";"Cyclone";"Factory";79;3
"Unit";"Cyclone";"Factory";85;3
"Unit";"Marine";"Barracks";90;1
"Unit";"Hellion";"Factory";91;2
"Unit";"Liberator";"Starport";94;3
"Building";"Factory";NA;97;0
"Building";"Factory";NA;97;0
"Unit";"Hellion";"Factory";100;2
"Unit";"Hellion";"Factory";102;2
"Building";"Refinery";NA;104;0
"Building";"Refinery";NA;107;0
"Unit";"Hellion";"Factory";107;2
"Building";"BarracksReactor";NA;112;0
"Unit";"Hellion";"Factory";112;2
"Upgrade";"TerranVehicleWeaponsLevel1";"Armory";114;0
"Building";"StarportReactor";NA;117;0
"Unit";"Hellion";"Factory";117;2
"Building";"FactoryTechLab";NA;119;0
"Unit";"Hellion";"Factory";119;2
"Unit";"Hellion";"Factory";126;2
"Unit";"Hellion";"Factory";131;2
"Building";"Factory";NA;133;0
"Building";"Factory";NA;133;0
"Unit";"Liberator";"Starport";133;3
"Unit";"Liberator";"Starport";136;3
"Building";"CommandCenter";NA;139;0
"Unit";"Hellion";"Factory";139;2
"Unit";"Hellion";"Factory";141;2
"Unit";"Hellion";"Factory";143;2
"Building";"CommandCenter";NA;145;0
"Unit";"Hellion";"Factory";148;2
"Building";"FactoryTechLab";NA;150;0
"Building";"FactoryReactor";NA;150;0
"Unit";"Hellion";"Factory";151;2
"Unit";"Hellion";"Factory";153;2
"Building";"Refinery";NA;155;0
"Unit";"Hellion";"Factory";155;2
"Building";"Refinery";NA;157;0
"Unit";"Hellion";"Factory";157;2
"Unit";"Hellion";"Factory";159;2
"Unit";"Hellion";"Factory";161;2
"Building";"CommandCenter";NA;163;0
"Building";"EngineeringBay";NA;163;0
"Unit";"Hellion";"Factory";163;2
"Unit";"Hellion";"Factory";165;2
"Unit";"Hellion";"Factory";167;2
"Unit";"Hellion";"Factory";169;2
"Upgrade";"TerranVehicleWeaponsLevel2";"Armory";171;0
"Unit";"Hellion";"Factory";171;2
"Unit";"Hellion";"Factory";173;2
"Unit";"Hellion";"Factory";175;2
"Unit";"Hellion";"Factory";177;2
"Unit";"Hellion";"Factory";179;2
"Unit";"Liberator";"Starport";181;3
"Unit";"Liberator";"Starport";184;3
"Unit";"Hellion";"Factory";187;2
"Unit";"Hellion";"Factory";189;2
"Unit";"Hellion";"Factory";191;2
"Unit";"Hellion";"Factory";193;2
"Unit";"Hellion";"Factory";195;2
"Unit";"Hellion";"Factory";197;2
"Unit";"Hellion";"Factory";199;2
"Unit";"Hellion";"Factory";201;2
"Unit";"Hellion";"Factory";203;2
"Building";"CommandCenter";NA;205;0
"Building";"Refinery";NA;205;0
"Building";"Refinery";NA;205;0
"Building";"CommandCenter";NA;205;0
"Unit";"Hellion";"Factory";205;2
"Building";"Factory";NA;207;0
"Building";"Factory";NA;207;0
"Unit";"Hellion";"Factory";207;2
"Unit";"Hellion";"Factory";209;2
"Unit";"Hellion";"Factory";211;2
"Unit";"Hellion";"Factory";213;2
"Unit";"Hellion";"Factory";215;2
"Unit";"Hellion";"Factory";217;2
"Unit";"Hellion";"Factory";219;2
"Unit";"Hellion";"Factory";221;2
"Unit";"Hellion";"Factory";223;2
"Unit";"Hellion";"Factory";225;2
"Building";"FactoryReactor";NA;227;0
"Building";"FactoryTechLab";NA;227;0
"Unit";"Hellion";"Factory";227;2
"Unit";"Hellion";"Factory";229;2
"Building";"Starport";NA;231;0
"Building";"Starport";NA;231;0
"Building";"Starport";NA;231;0
"Unit";"Hellion";"Factory";231;2
"Unit";"Hellion";"Factory";233;2
"Unit";"Hellion";"Factory";235;2
"Unit";"Hellion";"Factory";237;2
"Unit";"Hellion";"Factory";239;2
"Unit";"Hellion";"Factory";241;2
"Unit";"Hellion";"Factory";243;2
"Unit";"Hellion";"Factory";245;2
"Unit";"Hellion";"Factory";247;2
"Unit";"Hellion";"Factory";249;2
"Unit";"Liberator";"Starport";251;3
"Upgrade";"TerranVehicleWeaponsLevel3";"Armory";254;0
"Unit";"Liberator";"Starport";254;3
"Unit";"Hellion";"Factory";257;2
"Unit";"Hellion";"Factory";259;2
"Unit";"Hellion";"Factory";261;2
"Building";"Refinery";NA;263;0
"Building";"MissileTurret";NA;263;0
"Building";"MissileTurret";NA;263;0
"Unit";"Liberator";"Starport";263;3
"Unit";"Liberator";"Starport";266;3
"Building";"BarracksTechLab";NA;269;0
"Unit";"Hellion";"Factory";269;2
"Unit";"Hellion";"Factory";271;2
"Unit";"Hellion";"Factory";273;2
"Unit";"Hellion";"Factory";275;2
"Unit";"Liberator";"Starport";277;3
"Unit";"Hellion";"Factory";280;2
"Unit";"Hellion";"Factory";282;2
"Unit";"Liberator";"Starport";284;3
"Unit";"Hellion";"Factory";287;2
"Unit";"Hellion";"Factory";289;2
"Unit";"Hellion";"Factory";291;2
"Unit";"Hellion";"Factory";293;2
"Unit";"Hellion";"Factory";295;2
"Unit";"Liberator";"Starport";297;3
"Unit";"Liberator";"Starport";300;3
"Unit";"Liberator";"Starport";303;3
"Unit";"Hellion";"Factory";306;2
"Unit";"Hellion";"Factory";308;2
"Building";"Refinery";NA;310;0
"Unit";"Hellion";"Factory";310;2
"Unit";"Hellion";"Factory";312;2
"Unit";"Liberator";"Starport";314;3
"Unit";"Thor";"Factory";317;6
"Unit";"Liberator";"Starport";323;3
"Unit";"Liberator";"Starport";326;3
"Upgrade";"TerranShipWeaponsLevel1";"Armory";329;0
"Unit";"Hellion";"Factory";329;2
"Unit";"Hellion";"Factory";331;2
"Unit";"Liberator";"Starport";333;3
"Unit";"Hellion";"Factory";336;2
"Unit";"Liberator";"Starport";338;3
"Unit";"Liberator";"Starport";341;3
"Unit";"Liberator";"Starport";344;3
"Unit";"Liberator";"Starport";347;3
"Unit";"Hellion";"Factory";350;2
"Unit";"Hellion";"Factory";352;2
"Unit";"Hellion";"Factory";354;2
"Unit";"Hellion";"Factory";356;2
"Unit";"Hellion";"Factory";358;2
"Unit";"Hellion";"Factory";360;2
"Unit";"Hellion";"Factory";362;2
"Upgrade";"SprayTerran";NA;364;0
"Upgrade";"SprayTerran";NA;364;0
"Upgrade";"SprayTerran";NA;364;0
"Upgrade";"SprayTerran";NA;364;0
"Upgrade";"LiberatorAGRangeUpgrade";NA;364;0
"Upgrade";"SprayTerran";NA;364;0
"Upgrade";"SprayTerran";NA;364;0
"Upgrade";"SprayTerran";NA;364;0
"Upgrade";"TerranVehicleAndShipArmorsLevel1";NA;364;0
"Upgrade";"SprayTerran";NA;364;0
"Upgrade";"SprayTerran";NA;364;0
"Upgrade";"SprayTerran";NA;364;0
"Upgrade";"SprayTerran";NA;364;0
"Upgrade";"SprayTerran";NA;364;0
"Upgrade";"HighCapacityBarrels";NA;364;0
"Upgrade";"SprayTerran";NA;364;0
"Upgrade";"SprayTerran";NA;364;0
"Upgrade";"TerranVehicleAndShipArmorsLevel2";NA;364;0
"Upgrade";"TerranVehicleAndShipArmorsLevel3";NA;364;0
"Upgrade";"SmartServos";NA;364;0
