"type";"unit_name";"on_building";"total_supply";"supply"
"Building";"Barracks";NA;13;0
"Building";"Barracks";NA;13;0
"Unit";"Marine";"Barracks";14;1
"Building";"Barracks";NA;13;0
"Unit";"Marine";"Barracks";15;1
"Unit";"Marine";"Barracks";16;1
"Unit";"Marine";"Barracks";16;1
"Unit";"Marine";"Barracks";17;1
"Unit";"Marine";"Barracks";17;1
"Unit";"Marine";"Barracks";18;1
"Unit";"Marine";"Barracks";19;1
"Unit";"Marine";"Barracks";23;1
"Unit";"Marine";"Barracks";23;1
"Unit";"Marine";"Barracks";23;1
"Building";"Bunker";NA;21;0
