"type";"unit_name";"on_building";"total_supply";"supply"
"Building";"Refinery";NA;14;0
"Building";"Barracks";NA;15;0
"Unit";"Marine";"Barracks";19;1
"Building";"Factory";NA;20;0
"Building";"BarracksReactor";NA;21;0
"Building";"BarracksTechLab";NA;22;0
"Unit";"Hellion";"Factory";22;2
"Unit";"Hellion";"Factory";22;2
"Unit";"Marine";"Barracks";23;1
"Building";"CommandCenter";NA;21;0
"Unit";"Marine";"Barracks";30;1
"Building";"Refinery";NA;30;0
"Building";"FactoryReactor";NA;30;0
"Building";"Barracks";NA;29;0
"Building";"Barracks";NA;29;0
"Unit";"Marine";"Barracks";33;1
"Building";"EngineeringBay";NA;34;0
"Unit";"Marine";"Barracks";35;1
"Unit";"Marine";"Barracks";35;1
"Unit";"Marine";"Barracks";36;1
"Unit";"Marine";"Barracks";37;1
"Unit";"Marine";"Barracks";37;1
"Building";"MissileTurret";NA;37;0
"Building";"MissileTurret";NA;41;0
"Unit";"Marine";"Barracks";43;1
"Unit";"Marine";"Barracks";43;1
"Upgrade";"Stimpack";"TechLab";31;0
"Unit";"Marine";"Barracks";44;1
"Unit";"Marine";"Barracks";44;1
"Unit";"Marine";"Barracks";44;1
"Building";"Starport";NA;41;0
"Building";"FactoryReactor";NA;43;0
"Unit";"Marine";"Barracks";51;1
"Unit";"Marine";"Barracks";51;1
"Unit";"Marine";"Barracks";52;1
"Unit";"Marine";"Barracks";52;1
"Unit";"Medivac";"Starport";54;2
"Unit";"Medivac";"Starport";54;2
"Unit";"Marine";"Barracks";60;1
"Unit";"Marine";"Barracks";60;1
"Unit";"Marine";"Barracks";60;1
"Unit";"Marine";"Barracks";60;1
"Unit";"Marine";"Barracks";65;1
"Unit";"Marine";"Barracks";66;1
"Unit";"Marine";"Barracks";71;1
"Unit";"Marine";"Barracks";71;1
"Unit";"Marine";"Barracks";74;1
"Unit";"Marine";"Barracks";74;1
"Building";"Refinery";NA;74;0
"Unit";"Marine";"Barracks";77;1
"Unit";"Marine";"Barracks";77;1
"Unit";"Marine";"Barracks";77;1
"Building";"FactoryReactor";NA;74;0
"Upgrade";"TerranInfantryWeaponsLevel1";"EngineeringBay";59;0
"Unit";"Marine";"Barracks";84;1
"Unit";"Marine";"Barracks";84;1
"Building";"Refinery";NA;82;0
"Unit";"Liberator";"Starport";81;3
"Unit";"Marine";"Barracks";86;1
"Unit";"Marine";"Barracks";86;1
"Unit";"Liberator";"Starport";81;3
"Unit";"Marine";"Barracks";86;1
"Building";"CommandCenter";NA;75;0
"Unit";"Marine";"Barracks";100;1
"Unit";"Marine";"Barracks";100;1
"Unit";"Marine";"Barracks";100;1
"Building";"EngineeringBay";NA;100;0
"Unit";"Marauder";"Barracks";100;2
"Unit";"Marine";"Barracks";105;1
"Unit";"Marine";"Barracks";105;1
"Building";"Armory";NA;99;0
"Unit";"Marine";"Barracks";109;1
"Unit";"Marine";"Barracks";109;1
"Unit";"Marine";"Barracks";109;1
"Unit";"Marauder";"Barracks";109;2
"Unit";"Marine";"Barracks";114;1
"Unit";"Marine";"Barracks";114;1
"Unit";"Marine";"Barracks";114;1
"Upgrade";"TerranInfantryArmorsLevel1";"EngineeringBay";100;0
"Unit";"Marauder";"Barracks";114;2
"Unit";"Marine";"Barracks";114;1
"Building";"Barracks";NA;109;0
"Building";"Barracks";NA;109;0
"Unit";"Marine";"Barracks";120;1
"Unit";"Marine";"Barracks";120;1
"Building";"GhostAcademy";NA;117;0
"Building";"Starport";NA;114;0
"Unit";"Marine";"Barracks";123;1
"Unit";"Marine";"Barracks";126;1
"Unit";"Marine";"Barracks";126;1
"Unit";"Marine";"Barracks";126;1
"Building";"FusionCore";NA;117;0
"Building";"BarracksTechLab";NA;126;0
"Building";"BarracksTechLab";NA;126;0
"Building";"StarportTechLab";NA;126;0
"Unit";"Marine";"Barracks";127;1
"Unit";"Medivac";"Starport";126;2
"Unit";"Marine";"Barracks";138;1
"Unit";"Marine";"Barracks";138;1
"Unit";"Marine";"Barracks";138;1
"Unit";"Marauder";"Barracks";138;2
"Unit";"Liberator";"Starport";138;3
"Unit";"Liberator";"Starport";138;3
"Unit";"Liberator";"Starport";138;3
"Unit";"Marine";"Barracks";144;1
"Building";"Refinery";NA;144;0
"Building";"Refinery";NA;144;0
"Upgrade";"TerranInfantryWeaponsLevel2";"EngineeringBay";133;0
"Unit";"Marine";"Barracks";157;1
"Unit";"Liberator";"Starport";157;3
"Unit";"Liberator";"Starport";157;3
"Unit";"Marine";"Barracks";157;1
"Unit";"Marine";"Barracks";157;1
"Unit";"Marine";"Barracks";157;1
"Unit";"Marauder";"Barracks";157;2
"Unit";"Marauder";"Barracks";157;2
"Unit";"Marauder";"Barracks";157;2
"Building";"CommandCenter";NA;144;0
"Unit";"Marine";"Barracks";157;1
"Unit";"Marine";"Barracks";164;1
"Unit";"Liberator";"Starport";157;3
"Unit";"Marine";"Barracks";174;1
"Unit";"Marine";"Barracks";174;1
"Unit";"Marauder";"Barracks";174;2
"Unit";"Marauder";"Barracks";174;2
"Upgrade";"TerranShipWeaponsLevel1";"Armory";157;0
"Unit";"Liberator";"Starport";158;3
"Building";"Barracks";NA;158;0
"Building";"Barracks";NA;165;0
"Building";"Barracks";NA;167;0
"Upgrade";"TerranInfantryArmorsLevel2";"EngineeringBay";157;0
"Unit";"Marine";"Barracks";190;1
"Unit";"Marine";"Barracks";190;1
"Unit";"Marine";"Barracks";190;1
"Unit";"Liberator";"Starport";178;3
"Unit";"Liberator";"Starport";178;3
"Unit";"Marauder";"Barracks";190;2
"Building";"BarracksTechLab";NA;190;0
"Building";"BarracksTechLab";NA;190;0
"Unit";"Liberator";"Starport";185;3
"Unit";"Marine";"Barracks";190;1
"Unit";"Marine";"Barracks";190;1
"Unit";"Marauder";"Barracks";190;2
"Unit";"Marine";"Barracks";203;1
"Unit";"Marine";"Barracks";203;1
"Unit";"Marauder";"Barracks";203;2
"Unit";"Marauder";"Barracks";203;2
"Unit";"Liberator";"Starport";193;3
"Unit";"Liberator";"Starport";196;3
"Building";"MissileTurret";NA;210;0
"Unit";"Marine";"Barracks";212;1
"Unit";"Marauder";"Barracks";216;2
