"Type";"UnitName";"OnBuilding";"TotalSupply";"Supply"
"Unit";"SCV";"Command Center";12;1
"Unit";"SCV";"Command Center";12;1
"Unit";"SCV";"Command Center";13;1
"Building";"SupplyDepot";NA;13;0
"Building";"Refinery";NA;14;0
"Unit";"SCV";"Command Center";15;1
"Unit";"SCV";"Command Center";15;1
"Unit";"SCV";"Command Center";16;1
"Unit";"SCV";"Command Center";17;1
"Building";"Barracks";NA;15;0
"Unit";"Marine";"Barracks";19;1
"Building";"BarracksTechLab";NA;20;0
"Unit";"SCV";"Command Center";20;1
"Building";"SupplyDepot";NA;20;0
"Unit";"SCV";"Command Center";21;1
"Unit";"Marine";"Barracks";20;1
"Unit";"SCV";"Command Center";22;1
"Unit";"Marine";"Barracks";22;1
"Unit";"SCV";"Command Center";24;1
"Building";"CommandCenter";NA;19;0
"Unit";"SCV";"Command Center";25;1
"Unit";"Marine";"Barracks";24;1
"Building";"Barracks";NA;22;0
"Unit";"SCV";"Command Center";26;1
"Unit";"Marine";"Barracks";27;1
"Building";"Barracks";NA;24;0
"Unit";"SCV";"Command Center";29;1
"Building";"EngineeringBay";NA;28;0
"Unit";"SCV";"Command Center";30;1
"Unit";"Marine";"Barracks";29;1
"Unit";"SCV";"Command Center";30;1
"Unit";"SCV";"Command Center";31;1
"Building";"BarracksReactor";NA;28;0
"Unit";"SCV";"Command Center";34;1
"Unit";"Marine";"Barracks";34;1
"Building";"BarracksReactor";NA;30;0
"Unit";"SCV";"Command Center";35;1
"Unit";"SCV";"Command Center";35;1
"Unit";"Marine";"Barracks";35;1
"Unit";"Marine";"Barracks";35;1
"Upgrade";"Stimpack";"TechLab";24;0
"Unit";"SCV";"Command Center";37;1
"Building";"Barracks";NA;31;0
"Building";"Barracks";NA;31;0
"Unit";"Marine";"Barracks";38;1
"Building";"SupplyDepot";NA;37;0
"Unit";"Marine";"Barracks";38;1
"Unit";"Marine";"Barracks";38;1
"Building";"SupplyDepot";NA;38;0
"Unit";"Marine";"Barracks";42;1
"Unit";"SCV";"Command Center";43;1
"Unit";"SCV";"Command Center";43;1
"Unit";"Marine";"Barracks";43;1
"Unit";"Marine";"Barracks";43;1
"Unit";"Marine";"Barracks";44;1
"Unit";"Marine";"Barracks";45;1
"Unit";"Marine";"Barracks";45;1
"Unit";"Marine";"Barracks";45;1
"Unit";"SCV";"Command Center";48;1
"Unit";"SCV";"Command Center";48;1
"Unit";"Marine";"Barracks";45;1
"Building";"SupplyDepot";NA;48;0
"Building";"SupplyDepot";NA;51;0
"Unit";"Marine";"Barracks";53;1
"Unit";"Marine";"Barracks";53;1
"Building";"SupplyDepot";NA;51;0
"Unit";"Marine";"Barracks";54;1
"Unit";"Marine";"Barracks";54;1
"Unit";"Marine";"Barracks";57;1
"Unit";"Marine";"Barracks";57;1
"Building";"Refinery";NA;57;0
"Unit";"Marine";"Barracks";57;1
"Unit";"Marine";"Barracks";59;1
"Unit";"Marine";"Barracks";59;1
"Unit";"Marine";"Barracks";61;1
"Unit";"Marine";"Barracks";61;1
"Unit";"SCV";"Command Center";63;1
"Unit";"Marine";"Barracks";61;1
"Unit";"SCV";"Command Center";66;1
"Building";"Factory";NA;57;0
"Unit";"Marine";"Barracks";64;1
"Upgrade";"TerranInfantryWeaponsLevel1";"EngineeringBay";44;0
"Unit";"SCV";"Command Center";72;1
"Unit";"SCV";"Command Center";72;1
"Unit";"SCV";"Command Center";72;1
"Unit";"SCV";"Command Center";73;1
"Building";"BarracksTechLab";NA;72;0
"Building";"BarracksTechLab";NA;72;0
"Unit";"Marine";"Barracks";72;1
"Unit";"Marine";"Barracks";72;1
"Unit";"Marine";"Barracks";72;1
"Unit";"Marine";"Barracks";72;1
"Unit";"Marauder";"Barracks";72;2
"Building";"Starport";NA;72;0
"Building";"FactoryReactor";NA;72;0
"Unit";"SCV";"Command Center";74;1
"Unit";"SCV";"Command Center";75;1
"Building";"Refinery";NA;74;0
"Unit";"Marine";"Barracks";76;1
"Unit";"Marine";"Barracks";82;1
"Unit";"SCV";"Command Center";84;1
"Unit";"SCV";"Command Center";84;1
"Unit";"Marine";"Barracks";84;1
"Unit";"Marine";"Barracks";84;1
"Unit";"SCV";"Command Center";86;1
"Unit";"SCV";"Command Center";87;1
"Unit";"Medivac";"Starport";84;2
"Unit";"Marine";"Barracks";88;1
"Unit";"Medivac";"Starport";84;2
"Unit";"Marine";"Barracks";88;1
"Unit";"Marine";"Barracks";88;1
"Building";"Refinery";NA;88;0
"Unit";"SCV";"Command Center";92;1
"Unit";"SCV";"Command Center";92;1
"Unit";"Marine";"Barracks";92;1
"Unit";"Marine";"Barracks";95;1
"Unit";"SCV";"Command Center";99;1
"Unit";"SCV";"Command Center";100;1
"Building";"EngineeringBay";NA;92;0
"Unit";"Marine";"Barracks";101;1
"Unit";"Marine";"Barracks";101;1
"Unit";"Marauder";"Barracks";101;2
"Unit";"Marauder";"Barracks";101;2
"Unit";"Medivac";"Starport";99;2
"Building";"Armory";NA;90;0
"Building";"SupplyDepot";NA;105;0
"Building";"SupplyDepot";NA;105;0
"Building";"SupplyDepot";NA;107;0
"Building";"CommandCenter";NA;88;0
"Upgrade";"TerranInfantryArmorsLevel1";"EngineeringBay";86;0
"Unit";"SCV";"Command Center";113;1
"Unit";"SCV";"Command Center";113;1
"Building";"FactoryReactor";NA;105;0
"Unit";"Marine";"Barracks";113;1
"Unit";"Marine";"Barracks";113;1
"Unit";"Marauder";"Barracks";113;2
"Unit";"SCV";"Command Center";113;1
"Unit";"SCV";"Command Center";113;1
"Unit";"Marine";"Barracks";113;1
"Unit";"Marine";"Barracks";113;1
"Unit";"Marauder";"Barracks";113;2
"Unit";"Marauder";"Barracks";113;2
"Unit";"SCV";"Command Center";119;1
"Unit";"SCV";"Command Center";119;1
"Unit";"Marine";"Barracks";119;1
"Unit";"Medivac";"Starport";113;2
"Unit";"Marauder";"Barracks";117;2
"Unit";"SCV";"Command Center";127;1
"Unit";"Marine";"Barracks";123;1
"Unit";"Marine";"Barracks";127;1
"Unit";"Marauder";"Barracks";123;2
"Unit";"Marauder";"Barracks";127;2
"Unit";"SCV";"Command Center";134;1
"Unit";"SCV";"Command Center";134;1
"Unit";"SCV";"Command Center";134;1
"Unit";"Marine";"Barracks";134;1
"Unit";"Marine";"Barracks";135;1
"Unit";"Marauder";"Barracks";134;2
"Building";"SupplyDepot";NA;135;0
"Unit";"Marine";"Barracks";143;1
"Unit";"Marine";"Barracks";143;1
"Unit";"Marauder";"Barracks";143;2
"Unit";"Marauder";"Barracks";144;2
"Unit";"SCV";"Command Center";148;1
"Building";"SupplyDepot";NA;146;0
"Building";"SupplyDepot";NA;146;0
"Building";"SupplyDepot";NA;148;0
"Unit";"Marine";"Barracks";148;1
"Unit";"Marine";"Barracks";148;1
"Building";"SupplyDepot";NA;150;0
"Unit";"Liberator";"Starport";142;3
"Unit";"Marine";"Barracks";152;1
"Unit";"Liberator";"Starport";143;3
"Unit";"Marauder";"Barracks";152;2
"Unit";"Marauder";"Barracks";152;2
"Unit";"Marauder";"Barracks";155;2
"Unit";"Marine";"Barracks";168;1
"Unit";"Marine";"Barracks";168;1
"Unit";"Marauder";"Barracks";168;2
"Unit";"Marauder";"Barracks";168;2
"Unit";"Marine";"Barracks";170;1
"Unit";"Marine";"Barracks";170;1
"Unit";"Marauder";"Barracks";170;2
"Unit";"Marine";"Barracks";170;1
"Unit";"Marine";"Barracks";171;1
"Unit";"Marauder";"Barracks";172;2
"Unit";"Marauder";"Barracks";174;2
"Upgrade";"TerranInfantryWeaponsLevel2";"EngineeringBay";137;0
"Upgrade";"TerranInfantryArmorsLevel2";"EngineeringBay";143;0
"Unit";"Marine";"Barracks";182;1
"Unit";"Marauder";"Barracks";182;2
"Unit";"Marauder";"Barracks";182;2
"Unit";"SCV";"Command Center";189;1
"Unit";"SCV";"Command Center";192;1
"Unit";"Marauder";"Barracks";192;2
"Unit";"SCV";"Command Center";192;1
"Unit";"SCV";"Command Center";193;1
"Unit";"SCV";"Command Center";193;1
"Unit";"SCV";"Command Center";195;1
"Unit";"Marine";"Barracks";196;1
"Unit";"SCV";"Command Center";196;1
"Unit";"Marine";"Barracks";198;1
"Unit";"Marine";"Barracks";199;1
"Unit";"SCV";"Command Center";199;1
"Unit";"Marine";"Barracks";199;1
"Unit";"Marauder";"Barracks";199;2
"Unit";"Marine";"Barracks";201;1
"Unit";"Marauder";"Barracks";201;2
"Unit";"Marauder";"Barracks";201;2
