"type";"unit_name";"on_building";"total_supply";"supply"
"Building";"Refinery";NA;15;0
"Building";"Barracks";NA;15;0
"Unit";"Reaper";"Barracks";19;1
"Building";"Factory";NA;19;0
"Building";"BarracksReactor";NA;21;0
"Building";"CommandCenter";NA;19;0
"Building";"BarracksTechLab";NA;24;0
"Unit";"Hellion";"Factory";24;2
"Unit";"Hellion";"Factory";24;2
"Building";"Starport";NA;24;0
"Unit";"Marine";"Barracks";30;1
"Unit";"Hellion";"Factory";26;2
"Unit";"Hellion";"Factory";30;2
"Building";"Barracks";NA;25;0
"Building";"Barracks";NA;25;0
"Unit";"Marauder";"Barracks";31;2
"Unit";"Medivac";"Starport";37;2
"Unit";"Hellion";"Factory";39;2
"Unit";"Hellion";"Factory";39;2
"Building";"BarracksTechLab";NA;43;0
"Building";"BarracksTechLab";NA;43;0
"Unit";"Marine";"Barracks";44;1
"Building";"Refinery";NA;49;0
"Building";"FactoryTechLab";NA;50;0
"Building";"EngineeringBay";NA;52;0
"Building";"StarportReactor";NA;52;0
"Unit";"Marine";"Barracks";52;1
"Unit";"Marine";"Barracks";52;1
"Unit";"Marine";"Barracks";52;1
"Unit";"Marine";"Barracks";52;1
"Building";"CommandCenter";NA;49;0
"Unit";"Marine";"Barracks";53;1
"Unit";"Marine";"Barracks";54;1
"Building";"Barracks";NA;52;0
"Unit";"Marine";"Barracks";57;1
"Unit";"Marine";"Barracks";57;1
"Building";"Refinery";NA;58;0
"Unit";"Medivac";"Starport";58;2
"Unit";"Marine";"Barracks";64;1
"Building";"MissileTurret";NA;64;0
"Building";"Bunker";NA;63;0
"Building";"MissileTurret";NA;65;0
"Building";"Barracks";NA;58;0
"Unit";"Marine";"Barracks";68;1
"Unit";"Marine";"Barracks";68;1
"Unit";"Marine";"Barracks";68;1
"Unit";"Marine";"Barracks";68;1
"Unit";"Marauder";"Barracks";68;2
"Building";"Refinery";NA;70;0
"Unit";"Marine";"Barracks";78;1
"Unit";"Marauder";"Barracks";78;2
"Building";"FactoryReactor";NA;73;0
"Unit";"Marine";"Barracks";79;1
"Unit";"Marine";"Barracks";80;1
"Unit";"Marine";"Barracks";80;1
"Unit";"Marauder";"Barracks";79;2
"Unit";"Marauder";"Barracks";80;2
"Unit";"Marine";"Barracks";83;1
"Unit";"Marine";"Barracks";83;1
"Unit";"Marine";"Barracks";84;1
"Unit";"Marine";"Barracks";85;1
"Unit";"Marauder";"Barracks";86;2
"Unit";"Marauder";"Barracks";88;2
"Unit";"Marine";"Barracks";91;1
"Unit";"Marine";"Barracks";91;1
"Unit";"Marine";"Barracks";96;1
"Unit";"Marauder";"Barracks";96;2
"Unit";"Marine";"Barracks";102;1
"Unit";"Marauder";"Barracks";102;2
"Unit";"Marine";"Barracks";105;1
"Unit";"Marine";"Barracks";105;1
"Building";"BarracksReactor";NA;99;0
"Unit";"Medivac";"Starport";102;2
"Unit";"Medivac";"Starport";102;2
"Upgrade";"TerranInfantryWeaponsLevel1";"EngineeringBay";83;0
"Building";"GhostAcademy";NA;106;0
"Unit";"Marine";"Barracks";112;1
"Unit";"Marine";"Barracks";113;1
"Unit";"Marine";"Barracks";113;1
"Unit";"Marauder";"Barracks";112;2
"Unit";"Marauder";"Barracks";113;2
"Unit";"Marauder";"Barracks";113;2
"Unit";"Marine";"Barracks";117;1
"Unit";"Marine";"Barracks";119;1
"Unit";"Marine";"Barracks";122;1
"Unit";"Marine";"Barracks";122;1
"Unit";"Marauder";"Barracks";122;2
"Unit";"Marauder";"Barracks";124;2
"Unit";"Marauder";"Barracks";126;2
"Unit";"Marine";"Barracks";131;1
"Building";"EngineeringBay";NA;129;0
"Unit";"Marine";"Barracks";131;1
"Building";"MissileTurret";NA;135;0
"Building";"Armory";NA;129;0
"Unit";"Marine";"Barracks";143;1
"Unit";"Marine";"Barracks";143;1
"Unit";"Marine";"Barracks";143;1
"Unit";"Marine";"Barracks";143;1
"Unit";"Marauder";"Barracks";143;2
"Unit";"Marauder";"Barracks";143;2
"Unit";"Marauder";"Barracks";143;2
"Upgrade";"Stimpack";"TechLab";119;0
"Unit";"Medivac";"Starport";143;2
"Building";"Refinery";NA;146;0
"Unit";"Marine";"Barracks";158;1
"Unit";"Marine";"Barracks";158;1
"Unit";"Marine";"Barracks";158;1
"Unit";"Marine";"Barracks";158;1
"Unit";"Marauder";"Barracks";158;2
"Unit";"Marauder";"Barracks";158;2
"Unit";"Marauder";"Barracks";158;2
"Unit";"Marine";"Barracks";158;1
"Unit";"Marine";"Barracks";159;1
"Unit";"Marine";"Barracks";160;1
"Upgrade";"TerranInfantryArmorsLevel1";"EngineeringBay";143;0
