"Type";"UnitName";"OnBuilding";"TotalSupply";"Supply"
"Unit";"SCV";"Command Center";12;1
"Unit";"SCV";"Command Center";12;1
"Unit";"SCV";"Command Center";13;1
"Building";"SupplyDepot";NA;13;0
"Unit";"SCV";"Command Center";15;1
"Unit";"SCV";"Command Center";15;1
"Building";"Refinery";NA;15;0
"Unit";"SCV";"Command Center";16;1
"Unit";"SCV";"Command Center";17;1
"Building";"Barracks";NA;15;0
"Unit";"SCV";"Command Center";18;1
"Building";"BarracksTechLab";NA;19;0
"Building";"SupplyDepot";NA;19;0
"Unit";"Marauder";"Barracks";20;2
"Unit";"SCV";"Command Center";22;1
"Unit";"Marauder";"Barracks";22;2
"Unit";"SCV";"Command Center";22;1
"Building";"SupplyDepot";NA;22;0
"Unit";"SCV";"Command Center";25;1
"Unit";"Marauder";"Barracks";23;2
"Building";"Refinery";NA;26;0
"Unit";"SCV";"Command Center";26;1
"Building";"CommandCenter";NA;20;0
"Unit";"SCV";"Command Center";29;1
"Unit";"Marauder";"Barracks";29;2
"Building";"Factory";NA;26;0
"Unit";"SCV";"Command Center";33;1
"Unit";"Marauder";"Barracks";31;2
"Unit";"Marauder";"Barracks";36;2
"Unit";"SCV";"Command Center";36;1
"Building";"Barracks";NA;33;0
"Unit";"SCV";"Command Center";38;1
"Unit";"SCV";"Command Center";39;1
"Unit";"Marauder";"Barracks";36;2
"Unit";"SCV";"Command Center";39;1
"Unit";"SCV";"Command Center";40;1
"Building";"Starport";NA;36;0
"Unit";"SCV";"Command Center";43;1
"Unit";"Marine";"Barracks";41;1
"Unit";"SCV";"Command Center";44;1
"Building";"SupplyDepot";NA;43;0
"Building";"BarracksReactor";NA;39;0
"Unit";"SCV";"Command Center";45;1
"Unit";"SCV";"Command Center";47;1
"Building";"Refinery";NA;45;0
"Unit";"Marine";"Barracks";46;1
"Building";"EngineeringBay";NA;45;0
"Building";"FactoryReactor";NA;43;0
"Unit";"SCV";"Command Center";48;1
"Unit";"SCV";"Command Center";49;1
"Building";"StarportReactor";NA;45;0
"Unit";"Marine";"Barracks";50;1
"Unit";"Marine";"Barracks";50;1
"Building";"SupplyDepot";NA;48;0
"Building";"Refinery";NA;49;0
"Unit";"Marine";"Barracks";50;1
"Building";"Barracks";NA;45;0
"Building";"MissileTurret";NA;51;0
"Building";"MissileTurret";NA;52;0
"Upgrade";"Stimpack";"TechLab";36;0
"Unit";"Marine";"Barracks";53;1
"Unit";"Marine";"Barracks";54;1
"Unit";"Marine";"Barracks";55;1
"Unit";"SCV";"Command Center";56;1
"Unit";"SCV";"Command Center";56;1
"Unit";"Medivac";"Starport";55;2
"Unit";"Medivac";"Starport";55;2
"Unit";"Marine";"Barracks";56;1
"Unit";"Marine";"Barracks";56;1
"Unit";"SCV";"Command Center";59;1
"Unit";"Marine";"Barracks";56;1
"Unit";"Marine";"Barracks";57;1
"Unit";"Marine";"Barracks";58;1
"Unit";"SCV";"Command Center";61;1
"Building";"SupplyDepot";NA;59;0
"Building";"FactoryReactor";NA;56;0
"Unit";"Marine";"Barracks";65;1
"Unit";"Marine";"Barracks";66;1
"Building";"SupplyDepot";NA;71;0
"Unit";"Marine";"Barracks";72;1
"Unit";"SCV";"Command Center";72;1
"Unit";"Marine";"Barracks";72;1
"Unit";"Marine";"Barracks";72;1
"Unit";"Marauder";"Barracks";72;2
"Unit";"Medivac";"Starport";72;2
"Building";"SupplyDepot";NA;74;0
"Unit";"Marine";"Barracks";74;1
"Unit";"SCV";"Command Center";82;1
"Unit";"Marine";"Barracks";82;1
"Unit";"Marine";"Barracks";82;1
"Unit";"Liberator";"Starport";74;3
"Unit";"Marine";"Barracks";89;1
"Unit";"Marauder";"Barracks";89;2
"Unit";"Marine";"Barracks";89;1
"Unit";"Marine";"Barracks";89;1
"Unit";"Marine";"Barracks";89;1
"Upgrade";"TerranInfantryWeaponsLevel1";"EngineeringBay";74;0
"Unit";"Marine";"Barracks";89;1
"Unit";"Marauder";"Barracks";90;2
"Unit";"Marine";"Barracks";98;1
"Unit";"Marine";"Barracks";98;1
"Unit";"Liberator";"Starport";92;3
"Unit";"Liberator";"Starport";92;3
"Unit";"Marauder";"Barracks";98;2
"Building";"Barracks";NA;92;0
"Building";"Barracks";NA;92;0
"Unit";"Marine";"Barracks";98;1
"Building";"CommandCenter";NA;90;0
"Unit";"Marauder";"Barracks";106;2
"Unit";"Marine";"Barracks";109;1
"Unit";"Marine";"Barracks";109;1
"Unit";"Liberator";"Starport";100;3
"Unit";"Marauder";"Barracks";109;2
"Unit";"Marine";"Barracks";112;1
"Unit";"Liberator";"Starport";109;3
"Unit";"Marine";"Barracks";113;1
"Unit";"Marine";"Barracks";113;1
"Unit";"Marine";"Barracks";113;1
"Unit";"Marauder";"Barracks";116;2
"Unit";"Marine";"Barracks";118;1
"Unit";"Marine";"Barracks";122;1
"Unit";"Marine";"Barracks";123;1
"Unit";"SCV";"Command Center";125;1
"Unit";"SCV";"Command Center";125;1
"Upgrade";"TerranInfantryArmorsLevel1";"EngineeringBay";98;0
"Unit";"Marine";"Barracks";125;1
"Unit";"Marine";"Barracks";127;1
"Unit";"Liberator";"Starport";113;3
"Building";"BarracksTechLab";NA;128;0
"Building";"BarracksTechLab";NA;128;0
"Unit";"Marauder";"Barracks";125;2
"Unit";"SCV";"Command Center";130;1
"Unit";"Marine";"Barracks";128;1
"Unit";"Liberator";"Starport";119;3
"Unit";"Marine";"Barracks";140;1
"Unit";"Marine";"Barracks";140;1
"Unit";"Marine";"Barracks";141;1
"Unit";"Marine";"Barracks";141;1
"Unit";"Marine";"Barracks";141;1
"Unit";"Marauder";"Barracks";137;2
"Unit";"Marauder";"Barracks";140;2
"Unit";"Marine";"Barracks";144;1
"Unit";"Marine";"Barracks";145;1
"Unit";"Marine";"Barracks";146;1
"Unit";"Marine";"Barracks";147;1
"Unit";"Marine";"Barracks";147;1
"Unit";"Liberator";"Starport";134;3
"Unit";"Marine";"Barracks";151;1
"Unit";"Marauder";"Barracks";149;2
"Unit";"Liberator";"Starport";141;3
"Building";"Refinery";NA;153;0
"Building";"Refinery";NA;153;0
"Unit";"Marine";"Barracks";153;1
"Unit";"Marine";"Barracks";154;1
"Unit";"Marine";"Barracks";155;1
"Unit";"Marine";"Barracks";156;1
"Unit";"Marauder";"Barracks";156;2
"Unit";"Marine";"Barracks";162;1
"Unit";"Marauder";"Barracks";167;2
"Unit";"Marine";"Barracks";174;1
"Unit";"Marine";"Barracks";176;1
"Unit";"Marauder";"Barracks";176;2
"Unit";"Marine";"Barracks";176;1
"Unit";"Marine";"Barracks";176;1
"Unit";"Marauder";"Barracks";176;2
"Unit";"Liberator";"Starport";167;3
"Unit";"Marauder";"Barracks";176;2
"Unit";"Marine";"Barracks";180;1
"Unit";"Marine";"Barracks";180;1
"Unit";"Marine";"Barracks";180;1
"Unit";"Marine";"Barracks";181;1
"Unit";"Marine";"Barracks";182;1
"Unit";"Liberator";"Starport";176;3
"Unit";"Marauder";"Barracks";178;2
"Unit";"Marine";"Barracks";187;1
"Building";"Starport";NA;177;0
"Unit";"Marine";"Barracks";189;1
"Unit";"Marauder";"Barracks";193;2
"Unit";"SCV";"Command Center";200;1
"Unit";"SCV";"Command Center";200;1
"Unit";"Marauder";"Barracks";197;2
"Unit";"Marine";"Barracks";200;1
"Unit";"Liberator";"Starport";184;3
"Unit";"Marauder";"Barracks";200;2
"Unit";"Marauder";"Barracks";201;2
"Building";"CommandCenter";NA;177;0
"Unit";"Liberator";"Starport";194;3
"Unit";"Marauder";"Barracks";205;2
"Building";"EngineeringBay";NA;201;0
"Unit";"Medivac";"Starport";208;2
"Unit";"Marine";"Barracks";213;1
"Unit";"Marauder";"Barracks";213;2
"Unit";"Marine";"Barracks";220;1
"Unit";"Marauder";"Barracks";220;2
"Building";"Armory";NA;203;0
"Unit";"SCV";"Command Center";220;1
"Unit";"Marine";"Barracks";220;1
"Unit";"Marine";"Barracks";220;1
"Unit";"Medivac";"Starport";215;2
"Unit";"Marauder";"Barracks";220;2
"Unit";"Marine";"Barracks";222;1
"Unit";"Marauder";"Barracks";223;2
"Unit";"Marine";"Barracks";229;1
"Unit";"Marauder";"Barracks";229;2
"Unit";"Marine";"Barracks";236;1
"Unit";"Marine";"Barracks";236;1
"Unit";"Marine";"Barracks";236;1
"Unit";"Marauder";"Barracks";236;2
"Unit";"Marauder";"Barracks";236;2
"Unit";"Marine";"Barracks";238;1
"Unit";"Marine";"Barracks";239;1
"Unit";"Medivac";"Starport";236;2
"Unit";"Medivac";"Starport";236;2
"Unit";"Medivac";"Starport";236;2
"Unit";"Marine";"Barracks";244;1
"Unit";"Marauder";"Barracks";244;2
"Unit";"Marine";"Barracks";250;1
"Unit";"Marauder";"Barracks";250;2
"Unit";"Marauder";"Barracks";250;2
"Unit";"Marauder";"Barracks";257;2
"Unit";"Marine";"Barracks";259;1
"Unit";"Marauder";"Barracks";260;2
"Unit";"Marauder";"Barracks";262;2
"Unit";"Marine";"Barracks";264;1
"Unit";"Marauder";"Barracks";264;2
"Unit";"Marine";"Barracks";267;1
"Unit";"Marauder";"Barracks";267;2
"Unit";"Marauder";"Barracks";269;2
"Unit";"Marine";"Barracks";272;1
"Unit";"Marauder";"Barracks";272;2
"Unit";"Marine";"Barracks";280;1
"Unit";"Marine";"Barracks";280;1
"Unit";"Marauder";"Barracks";280;2
"Unit";"Marauder";"Barracks";280;2
"Unit";"Marine";"Barracks";282;1
"Unit";"Marauder";"Barracks";282;2
"Unit";"Marine";"Barracks";289;1
"Unit";"Marine";"Barracks";291;1
