"type";"unit_name";"on_building";"total_supply_lag";"supply"
"Building";"Barracks";NA;16;0
"Building";"Refinery";NA;16;0
"Unit";"Reaper";"Barracks";19;1
"Building";"CommandCenter";NA;20;0
"Building";"BarracksReactor";NA;21;0
"Building";"CommandCenter";NA;23;0
"Unit";"Marine";"Barracks";24;1
"Unit";"Marine";"Barracks";25;1
"Building";"Barracks";NA;26;0
"Unit";"Marine";"Barracks";27;1
"Unit";"Marine";"Barracks";28;1
"Building";"EngineeringBay";NA;30;0
"Unit";"Marine";"Barracks";30;1
"Unit";"Marine";"Barracks";31;1
"Unit";"Marine";"Barracks";34;1
"Unit";"Marine";"Barracks";35;1
"Building";"BarracksTechLab";NA;36;0
"Building";"MissileTurret";NA;37;0
"Unit";"Marine";"Barracks";40;1
"Unit";"Marine";"Barracks";41;1
"Building";"Barracks";NA;44;0
"Unit";"Marine";"Barracks";45;1
"Building";"Bunker";NA;47;0
"Unit";"Marine";"Barracks";47;1
"Upgrade";"TerranInfantryWeaponsLevel1";"EngineeringBay";48;0
"Unit";"Marine";"Barracks";50;1
"Upgrade";"Stimpack";"TechLab";52;0
"Building";"MissileTurret";NA;52;0
"Unit";"Marine";"Barracks";52;1
"Unit";"Marine";"Barracks";54;1
"Building";"Factory";NA;57;0
"Unit";"Marine";"Barracks";57;1
"Unit";"Marine";"Barracks";59;1
"Building";"Refinery";NA;60;0
"Building";"Refinery";NA;60;0
"Building";"BarracksTechLab";NA;61;0
"Unit";"Marine";"Barracks";61;1
"Unit";"Marine";"Barracks";62;1
"Unit";"Marine";"Barracks";65;1
"Building";"Refinery";NA;66;0
"Unit";"Marine";"Barracks";68;1
"Unit";"Marine";"Barracks";70;1
"Unit";"Marine";"Barracks";71;1
"Building";"FactoryReactor";NA;73;0
"Building";"Starport";NA;74;0
"Unit";"Marine";"Barracks";74;1
"Unit";"Marine";"Barracks";76;1
"Unit";"Marine";"Barracks";80;1
"Unit";"Marine";"Barracks";81;1
"Building";"Refinery";NA;84;0
"Building";"Refinery";NA;84;0
"Unit";"Marine";"Barracks";85;1
"Unit";"Marine";"Barracks";86;1
"Building";"Barracks";NA;88;0
"Building";"Barracks";NA;88;0
"Unit";"Marine";"Barracks";90;1
"Unit";"Marine";"Barracks";91;1
"Unit";"Marauder";"Barracks";93;2
"Unit";"Marauder";"Barracks";95;2
"Building";"FactoryReactor";NA;98;0
"Building";"Armory";NA;98;0
"Building";"EngineeringBay";NA;98;0
"Unit";"Medivac";"Starport";98;2
"Unit";"Medivac";"Starport";100;2
"Building";"Starport";NA;105;0
"Unit";"Marauder";"Barracks";105;2
"Unit";"Marauder";"Barracks";107;2
"Unit";"Marine";"Barracks";109;1
"Unit";"Marine";"Barracks";110;1
"Building";"BarracksTechLab";NA;112;0
"Building";"BarracksReactor";NA;112;0
"Unit";"Medivac";"Starport";112;2
"Unit";"Medivac";"Starport";114;2
"Building";"FusionCore";NA;116;0
"Building";"StarportTechLab";NA;116;0
"Unit";"Marauder";"Barracks";116;2
"Unit";"Marauder";"Barracks";118;2
"Unit";"Marauder";"Barracks";120;2
"Building";"CommandCenter";NA;122;0
"Unit";"Liberator";"Starport";122;3
"Unit";"Liberator";"Starport";125;3
"Upgrade";"TerranShipWeaponsLevel1";"Armory";128;0
"Unit";"Marauder";"Barracks";128;2
"Unit";"Marauder";"Barracks";130;2
"Upgrade";"TerranInfantryWeaponsLevel2";"EngineeringBay";132;0
"Unit";"Marauder";"Barracks";132;2
"Unit";"Marauder";"Barracks";134;2
"Unit";"Liberator";"Starport";136;3
"Unit";"Liberator";"Starport";139;3
"Unit";"Marine";"Barracks";142;1
"Unit";"Marine";"Barracks";143;1
"Unit";"Marine";"Barracks";144;1
"Unit";"Marauder";"Barracks";145;2
"Unit";"Marauder";"Barracks";147;2
"Unit";"Marauder";"Barracks";149;2
"Unit";"Liberator";"Starport";151;3
"Unit";"Marauder";"Barracks";154;2
"Unit";"Marauder";"Barracks";156;2
"Unit";"Marauder";"Barracks";158;2
"Unit";"Marine";"Barracks";160;1
"Unit";"Marine";"Barracks";161;1
"Unit";"Marine";"Barracks";162;1
"Unit";"Marine";"Barracks";163;1
"Unit";"Marine";"Barracks";164;1
"Unit";"Marine";"Barracks";165;1
"Unit";"Liberator";"Starport";166;3
"Unit";"Marauder";"Barracks";169;2
"Unit";"Marauder";"Barracks";171;2
"Unit";"Marauder";"Barracks";173;2
"Unit";"Marine";"Barracks";175;1
"Building";"Barracks";NA;176;0
"Building";"Barracks";NA;176;0
"Unit";"Liberator";"Starport";176;3
"Building";"Barracks";NA;179;0
"Unit";"Marauder";"Barracks";179;2
"Building";"Refinery";NA;181;0
"Building";"SensorTower";NA;181;0
"Unit";"Marauder";"Barracks";181;2
"Unit";"Marine";"Barracks";183;1
"Unit";"Marine";"Barracks";184;1
"Unit";"Marine";"Barracks";185;1
"Building";"Refinery";NA;186;0
"Building";"MissileTurret";NA;186;0
"Building";"MissileTurret";NA;186;0
"Building";"MissileTurret";NA;186;0
"Unit";"Liberator";"Starport";187;3
"Unit";"Liberator";"Starport";190;3
"Unit";"Medivac";"Starport";193;2
"Unit";"Medivac";"Starport";197;2
"Building";"BarracksTechLab";NA;200;0
"Building";"BarracksTechLab";NA;200;0
"Building";"BarracksReactor";NA;200;0
"Unit";"Marine";"Barracks";200;1
"Unit";"Marauder";"Barracks";201;2
"Unit";"Marauder";"Barracks";203;2
"Upgrade";"TerranInfantryWeaponsLevel3";"EngineeringBay";205;0
"Building";"Starport";NA;205;0
"Upgrade";"TerranShipWeaponsLevel2";"Armory";205;0
"Building";"CommandCenter";NA;205;0
"Building";"FactoryReactor";NA;207;0
"Building";"Starport";NA;207;0
"Building";"GhostAcademy";NA;207;0
"Unit";"Raven";"Starport";207;2
"Building";"CommandCenter";NA;209;0
"Building";"MissileTurret";NA;209;0
"Unit";"Ghost";"Barracks";209;2
"Unit";"Ghost";"Barracks";211;2
"Unit";"Ghost";"Barracks";213;2
"Unit";"Raven";"Starport";215;2
"Upgrade";"PersonalCloaking";"GhostAcademy";217;0
"Building";"Refinery";NA;217;0
"Building";"MissileTurret";NA;217;0
"Building";"SensorTower";NA;217;0
"Building";"Refinery";NA;217;0
"Building";"CommandCenter";NA;217;0
"Building";"GhostAcademy";NA;217;0
"Building";"GhostAcademy";NA;217;0
"Building";"GhostAcademy";NA;217;0
"Unit";"Raven";"Starport";217;2
"Building";"Starport";NA;220;0
"Building";"Starport";NA;220;0
"Building";"Starport";NA;220;0
"Building";"Starport";NA;220;0
"Upgrade";"TerranShipWeaponsLevel3";"Armory";220;0
"Unit";"Ghost";"Barracks";220;2
"Unit";"Ghost";"Barracks";222;2
"Unit";"Ghost";"Barracks";224;2
"Building";"MissileTurret";NA;226;0
"Building";"CommandCenter";NA;226;0
"Building";"StarportTechLab";NA;226;0
"Building";"StarportTechLab";NA;226;0
"Building";"StarportTechLab";NA;226;0
"Building";"StarportTechLab";NA;226;0
"Building";"Refinery";NA;226;0
"Unit";"Ghost";"Barracks";226;2
"Building";"MissileTurret";NA;228;0
"Building";"MissileTurret";NA;228;0
"Building";"MissileTurret";NA;228;0
"Unit";"Raven";"Starport";228;2
"Building";"CommandCenter";NA;230;0
"Building";"MissileTurret";NA;230;0
"Building";"CommandCenter";NA;230;0
"Building";"MissileTurret";NA;230;0
"Building";"CommandCenter";NA;230;0
"Unit";"Raven";"Starport";230;2
"Unit";"Raven";"Starport";232;2
"Unit";"Raven";"Starport";234;2
"Building";"MissileTurret";NA;236;0
"Unit";"Raven";"Starport";241;2
"Building";"SensorTower";NA;243;0
"Building";"MissileTurret";NA;243;0
"Building";"Refinery";NA;243;0
"Unit";"Raven";"Starport";243;2
"Building";"MissileTurret";NA;245;0
"Building";"MissileTurret";NA;245;0
"Unit";"Ghost";"Barracks";245;2
"Unit";"Ghost";"Barracks";247;2
"Unit";"Ghost";"Barracks";249;2
"Unit";"Ghost";"Barracks";251;2
"Unit";"Ghost";"Barracks";253;2
"Building";"MissileTurret";NA;255;0
"Building";"MissileTurret";NA;255;0
"Building";"MissileTurret";NA;255;0
"Unit";"Ghost";"Barracks";255;2
"Unit";"Raven";"Starport";257;2
"Unit";"Raven";"Starport";259;2
"Unit";"Ghost";"Barracks";261;2
"Unit";"Raven";"Starport";263;2
"Unit";"Raven";"Starport";265;2
"Unit";"Ghost";"Barracks";267;2
"Unit";"Raven";"Starport";269;2
"Unit";"Ghost";"Barracks";271;2
"Unit";"Ghost";"Barracks";273;2
"Unit";"Marine";"Barracks";275;1
"Building";"SensorTower";NA;276;0
"Building";"MissileTurret";NA;276;0
"Building";"MissileTurret";NA;276;0
"Unit";"Ghost";"Barracks";276;2
"Unit";"Ghost";"Barracks";286;2
"Unit";"Marauder";"Barracks";288;2
"Unit";"Ghost";"Barracks";290;2
"Unit";"Ghost";"Barracks";292;2
"Building";"MissileTurret";NA;294;0
"Building";"MissileTurret";NA;294;0
"Building";"CommandCenter";NA;294;0
"Unit";"Raven";"Starport";294;2
"Unit";"Raven";"Starport";296;2
"Unit";"Raven";"Starport";298;2
"Unit";"Raven";"Starport";300;2
"Unit";"Raven";"Starport";302;2
"Unit";"Raven";"Starport";304;2
"Building";"Refinery";NA;306;0
"Building";"Refinery";NA;306;0
"Building";"CommandCenter";NA;306;0
"Building";"CommandCenter";NA;306;0
"Building";"CommandCenter";NA;306;0
"Building";"MissileTurret";NA;310;0
"Building";"CommandCenter";NA;310;0
"Building";"CommandCenter";NA;310;0
"Unit";"Ghost";"Barracks";310;2
"Unit";"Ghost";"Barracks";312;2
"Unit";"Liberator";"Starport";314;3
"Unit";"Liberator";"Starport";317;3
"Unit";"Liberator";"Starport";320;3
"Building";"CommandCenter";NA;323;0
"Building";"CommandCenter";NA;323;0
"Unit";"Battlecruiser";"Starport";323;6
"Unit";"Battlecruiser";"Starport";329;6
"Unit";"Battlecruiser";"Starport";335;6
"Unit";"Battlecruiser";"Starport";341;6
"Unit";"Ghost";"Barracks";347;2
"Unit";"Ghost";"Barracks";349;2
"Unit";"Marine";"Barracks";351;1
"Unit";"Marauder";"Barracks";352;2
"Unit";"Marine";"Barracks";354;1
"Unit";"Marauder";"Barracks";355;2
"Unit";"Marine";"Barracks";357;1
"Unit";"Marauder";"Barracks";358;2
"Unit";"Marine";"Barracks";360;1
"Unit";"Marine";"Barracks";361;1
"Building";"MissileTurret";NA;362;0
"Building";"MissileTurret";NA;362;0
"Unit";"Marauder";"Barracks";362;2
"Unit";"Marauder";"Barracks";364;2
"Unit";"Ghost";"Barracks";366;2
"Unit";"Ghost";"Barracks";368;2
"Unit";"Battlecruiser";"Starport";370;6
"Building";"CommandCenter";NA;376;0
"Building";"CommandCenter";NA;376;0
"Building";"CommandCenter";NA;376;0
"Building";"CommandCenter";NA;376;0
"Unit";"Battlecruiser";"Starport";376;6
"Unit";"Marauder";"Barracks";382;2
"Unit";"Marauder";"Barracks";384;2
"Unit";"Marauder";"Barracks";386;2
"Unit";"Marine";"Barracks";388;1
"Unit";"Marine";"Barracks";389;1
"Unit";"Marine";"Barracks";390;1
"Unit";"Marauder";"Barracks";391;2
"Unit";"Marine";"Barracks";393;1
"Unit";"Marauder";"Barracks";394;2
"Unit";"Marine";"Barracks";396;1
"Unit";"Marauder";"Barracks";397;2
"Unit";"Marine";"Barracks";399;1
"Unit";"Marauder";"Barracks";400;2
"Unit";"Marine";"Barracks";402;1
"Unit";"Marauder";"Barracks";403;2
"Unit";"Marine";"Barracks";405;1
"Unit";"Marine";"Barracks";406;1
"Unit";"Marine";"Barracks";407;1
"Unit";"Marauder";"Barracks";408;2
"Unit";"Marauder";"Barracks";410;2
"Unit";"Marine";"Barracks";412;1
"Unit";"Marauder";"Barracks";413;2
"Unit";"Marine";"Barracks";415;1
"Unit";"Marine";"Barracks";416;1
"Unit";"Marine";"Barracks";417;1
"Upgrade";"SprayTerran";NA;418;0
"Upgrade";"SprayTerran";NA;418;0
"Upgrade";"SprayTerran";NA;418;0
"Upgrade";"SprayTerran";NA;418;0
"Upgrade";"ShieldWall";NA;418;0
"Upgrade";"PunisherGrenades";NA;418;0
"Upgrade";"SprayTerran";NA;418;0
"Upgrade";"TerranInfantryArmorsLevel1";NA;418;0
"Upgrade";"SprayTerran";NA;418;0
"Upgrade";"LiberatorAGRangeUpgrade";NA;418;0
"Upgrade";"TerranInfantryArmorsLevel2";NA;418;0
"Upgrade";"SprayTerran";NA;418;0
"Upgrade";"SprayTerran";NA;418;0
"Upgrade";"SprayTerran";NA;418;0
"Upgrade";"TerranInfantryArmorsLevel3";NA;418;0
"Upgrade";"RavenCorvidReactor";NA;418;0
"Upgrade";"SprayTerran";NA;418;0
"Upgrade";"SprayTerran";NA;418;0
"Upgrade";"SprayTerran";NA;418;0
"Upgrade";"SprayTerran";NA;418;0
"Upgrade";"SprayTerran";NA;418;0
"Upgrade";"SprayTerran";NA;418;0
"Upgrade";"SprayTerran";NA;418;0
"Upgrade";"SprayTerran";NA;418;0
"Upgrade";"TerranBuildingArmor";NA;418;0
"Upgrade";"HiSecAutoTracking";NA;418;0
"Upgrade";"SprayTerran";NA;418;0
"Upgrade";"SprayTerran";NA;418;0
"Upgrade";"SprayTerran";NA;418;0
"Upgrade";"TerranVehicleAndShipArmorsLevel1";NA;418;0
"Upgrade";"SprayTerran";NA;418;0
"Upgrade";"SprayTerran";NA;418;0
"Upgrade";"SprayTerran";NA;418;0
"Upgrade";"SprayTerran";NA;418;0
"Upgrade";"SprayTerran";NA;418;0
"Upgrade";"TerranVehicleAndShipArmorsLevel2";NA;418;0
"Upgrade";"SprayTerran";NA;418;0
"Upgrade";"SprayTerran";NA;418;0
"Upgrade";"SprayTerran";NA;418;0
"Upgrade";"SprayTerran";NA;418;0
"Upgrade";"SprayTerran";NA;418;0
"Upgrade";"SprayTerran";NA;418;0
"Upgrade";"SprayTerran";NA;418;0
"Upgrade";"SprayTerran";NA;418;0
"Upgrade";"SprayTerran";NA;418;0
"Upgrade";"SprayTerran";NA;418;0
"Upgrade";"SprayTerran";NA;418;0
"Upgrade";"SprayTerran";NA;418;0
"Upgrade";"SprayTerran";NA;418;0
"Upgrade";"SprayTerran";NA;418;0
"Upgrade";"SprayTerran";NA;418;0
"Upgrade";"BattlecruiserEnableSpecializations";NA;418;0
"Upgrade";"TerranVehicleAndShipArmorsLevel3";NA;418;0
"Upgrade";"SprayTerran";NA;418;0
"Upgrade";"SprayTerran";NA;418;0
"Upgrade";"SprayTerran";NA;418;0
"Upgrade";"SprayTerran";NA;418;0
