"type";"unit_name";"on_building";"total_supply";"supply"
"Building";"Pylon";NA;13;0
"Building";"Assimilator";NA;16;0
"Building";"Gateway";NA;15;0
"Building";"Assimilator";NA;21;0
"Building";"Pylon";NA;21;0
"Building";"CyberneticsCore";NA;20;0
"Unit";"Adept";"Gateway";22;2
"Building";"Nexus";NA;19;0
"Building";"TwilightCouncil";NA;23;0
"Unit";"Stalker";"Gateway";24;2
"Building";"Pylon";NA;32;0
"Unit";"Stalker";"Gateway";29;2
"Unit";"Stalker";"Gateway";37;2
"Building";"Assimilator";NA;41;0
"Building";"Pylon";NA;42;0
"Building";"Gateway";NA;40;0
"Building";"Gateway";NA;41;0
"Building";"Pylon";NA;49;0
"Unit";"Stalker";"Gateway";52;2
"Unit";"Stalker";"Gateway";52;2
"Unit";"Stalker";"Gateway";52;2
"Building";"Assimilator";NA;51;0
"Building";"Forge";NA;49;0
"Building";"Forge";NA;49;0
"Unit";"Stalker";"Gateway";61;2
"Unit";"Stalker";"Gateway";61;2
"Building";"Nexus";NA;47;0
"Unit";"Stalker";"Gateway";67;2
"Building";"RoboticsFacility";NA;60;0
"Unit";"Stalker";"Gateway";74;2
"Unit";"Stalker";"Gateway";74;2
"Unit";"Stalker";"Gateway";74;2
"Building";"Pylon";NA;70;0
"Upgrade";"Charge";"TwilightCouncil";57;0
"Unit";"Observer";"Robotics Facility";75;1
"Building";"Pylon";NA;84;0
"Building";"Pylon";NA;84;0
"Unit";"Sentry";"Gateway";86;2
"Unit";"Sentry";"Gateway";86;2
"Unit";"Sentry";"Gateway";86;2
"Building";"Pylon";NA;84;0
"Building";"Assimilator";NA;84;0
"Building";"Assimilator";NA;84;0
"Upgrade";"ProtossGroundWeaponsLevel1";"Forge";62;0
"Building";"Gateway";NA;83;0
"Building";"Gateway";NA;83;0
"Building";"Gateway";NA;83;0
"Building";"Gateway";NA;83;0
"Building";"Pylon";NA;92;0
"Unit";"Immortal";"Robotics Facility";84;4
"Building";"Pylon";NA;92;0
"Upgrade";"ProtossGroundArmorsLevel1";"Forge";71;0
"Unit";"Zealot";"Gateway";99;2
"Unit";"Zealot";"Gateway";99;2
"Unit";"Zealot";"Gateway";99;2
"Unit";"Zealot";"Gateway";105;2
"Unit";"Zealot";"Gateway";105;2
"Unit";"Zealot";"Gateway";105;2
"Unit";"Zealot";"Gateway";105;2
"Building";"ShieldBattery";NA;95;0
"Unit";"Zealot";"Gateway";115;2
"Unit";"Zealot";"Gateway";115;2
"Unit";"Zealot";"Gateway";119;2
"Unit";"Immortal";"Robotics Facility";99;4
"Unit";"Zealot";"Gateway";119;2
"Unit";"Zealot";"Gateway";119;2
"Unit";"Zealot";"Gateway";119;2
"Unit";"Zealot";"Gateway";131;2
"Building";"RoboticsBay";NA;105;0
"Unit";"Sentry";"Gateway";133;2
"Unit";"Sentry";"Gateway";133;2
"Unit";"Sentry";"Gateway";133;2
"Unit";"Sentry";"Gateway";133;2
"Unit";"Sentry";"Gateway";133;2
"Building";"Pylon";NA;133;0
"Building";"PhotonCannon";NA;133;0
"Unit";"Zealot";"Gateway";148;2
"Unit";"Zealot";"Gateway";148;2
"Unit";"Zealot";"Gateway";148;2
"Unit";"Zealot";"Gateway";148;2
"Unit";"Zealot";"Gateway";148;2
"Unit";"Colossus";"Robotics Facility";133;6
"Building";"RoboticsFacility";NA;133;0
"Unit";"Stalker";"Gateway";164;2
"Unit";"Stalker";"Gateway";164;2
"Unit";"Sentry";"Gateway";164;2
"Unit";"Sentry";"Gateway";164;2
"Unit";"Sentry";"Gateway";164;2
"Building";"ShieldBattery";NA;164;0
"Building";"ShieldBattery";NA;164;0
"Upgrade";"ProtossGroundWeaponsLevel2";"Forge";133;0
"Unit";"Colossus";"Robotics Facility";158;6
"Unit";"Colossus";"Robotics Facility";164;6
"Upgrade";"ExtendedThermalLance";"RoboticsBay";146;0
"Upgrade";"ProtossGroundArmorsLevel2";"Forge";133;0
"Unit";"Sentry";"Gateway";186;2
"Unit";"Sentry";"Gateway";186;2
"Unit";"Sentry";"Gateway";186;2
"Unit";"Sentry";"Gateway";186;2
"Building";"Pylon";NA;186;0
"Unit";"Stalker";"Gateway";194;2
"Unit";"Stalker";"Gateway";194;2
"Unit";"Stalker";"Gateway";194;2
"Unit";"Stalker";"Gateway";194;2
"Unit";"Colossus";"Robotics Facility";174;6
"Unit";"Colossus";"Robotics Facility";174;6
"Building";"Gateway";NA;186;0
"Building";"Gateway";NA;186;0
"Building";"Gateway";NA;186;0
"Unit";"Zealot";"Gateway";214;2
"Unit";"Zealot";"Gateway";214;2
"Unit";"Zealot";"Gateway";214;2
"Unit";"Zealot";"Gateway";214;2
"Unit";"Stalker";"Gateway";222;2
"Unit";"Stalker";"Gateway";222;2
"Unit";"Stalker";"Gateway";222;2
"Unit";"Colossus";"Robotics Facility";194;6
"Unit";"Stalker";"Gateway";228;2
"Unit";"Stalker";"Gateway";228;2
"Unit";"Stalker";"Gateway";234;2
"Unit";"Stalker";"Gateway";234;2
"Unit";"Stalker";"Gateway";242;2
"Unit";"Stalker";"Gateway";242;2
"Unit";"Stalker";"Gateway";242;2
"Building";"Pylon";NA;228;0
"Unit";"Immortal";"Robotics Facility";214;4
"Building";"Gateway";NA;214;0
"Unit";"Stalker";"Gateway";252;2
"Unit";"Stalker";"Gateway";252;2
"Unit";"Stalker";"Gateway";252;2
"Unit";"Stalker";"Gateway";252;2
"Building";"Nexus";NA;214;0
"Unit";"Sentry";"Gateway";260;2
"Unit";"Sentry";"Gateway";260;2
"Unit";"Sentry";"Gateway";260;2
"Unit";"Sentry";"Gateway";260;2
"Unit";"Sentry";"Gateway";260;2
"Unit";"Sentry";"Gateway";260;2
"Unit";"Sentry";"Gateway";260;2
"Building";"Pylon";NA;260;0
"Unit";"Immortal";"Robotics Facility";252;4
"Upgrade";"ProtossGroundWeaponsLevel3";"Forge";214;0
"Building";"Assimilator";NA;274;0
"Building";"Assimilator";NA;274;0
"Unit";"Zealot";"Gateway";278;2
"Unit";"Zealot";"Gateway";278;2
"Unit";"Zealot";"Gateway";278;2
"Unit";"Zealot";"Gateway";278;2
"Unit";"Zealot";"Gateway";278;2
"Unit";"Zealot";"Gateway";278;2
"Unit";"Zealot";"Gateway";278;2
"Building";"PhotonCannon";NA;274;0
"Unit";"Immortal";"Robotics Facility";274;4
"Unit";"Immortal";"Robotics Facility";274;4
"Unit";"Zealot";"Gateway";300;2
"Unit";"Zealot";"Gateway";300;2
"Unit";"Zealot";"Gateway";300;2
"Unit";"Zealot";"Gateway";300;2
"Unit";"Zealot";"Gateway";308;2
"Unit";"Zealot";"Gateway";308;2
"Unit";"Zealot";"Gateway";308;2
"Unit";"Zealot";"Gateway";308;2
"Unit";"Zealot";"Gateway";308;2
"Unit";"Zealot";"Gateway";308;2
"Building";"Stargate";NA;300;0
"Building";"Pylon";NA;308;0
"Upgrade";"ProtossGroundArmorsLevel3";"Forge";260;0
"Building";"Pylon";NA;308;0
"Building";"Pylon";NA;320;0
"Unit";"Zealot";"Gateway";320;2
"Unit";"Zealot";"Gateway";320;2
"Unit";"Zealot";"Gateway";320;2
"Unit";"Zealot";"Gateway";320;2
"Unit";"Zealot";"Gateway";320;2
"Building";"Stargate";NA;308;0
"Building";"Stargate";NA;308;0
"Building";"Pylon";NA;320;0
"Unit";"Zealot";"Gateway";332;2
"Unit";"Zealot";"Gateway";332;2
"Unit";"Zealot";"Gateway";332;2
"Unit";"Zealot";"Gateway";332;2
"Unit";"Zealot";"Gateway";332;2
"Building";"FleetBeacon";NA;320;0
"Building";"PhotonCannon";NA;331;0
"Building";"Nexus";NA;308;0
"Unit";"Stalker";"Gateway";342;2
"Unit";"Stalker";"Gateway";342;2
"Unit";"Stalker";"Gateway";342;2
"Unit";"Stalker";"Gateway";342;2
"Unit";"Tempest";"Stargate";332;4
"Unit";"Tempest";"Stargate";342;4
"Upgrade";"ProtossAirWeaponsLevel1";"CyberneticsCore";330;0
"Unit";"Zealot";"Gateway";358;2
"Unit";"Zealot";"Gateway";358;2
"Unit";"Zealot";"Gateway";358;2
"Unit";"Zealot";"Gateway";358;2
"Unit";"Zealot";"Gateway";358;2
"Unit";"Zealot";"Gateway";358;2
"Unit";"Zealot";"Gateway";358;2
"Unit";"Zealot";"Gateway";358;2
"Unit";"Tempest";"Stargate";342;4
"Building";"Assimilator";NA;358;0
"Building";"Assimilator";NA;358;0
"Upgrade";"ProtossShieldsLevel1";"Forge";342;0
"Unit";"Zealot";"Gateway";378;2
"Unit";"Zealot";"Gateway";378;2
"Unit";"Zealot";"Gateway";378;2
"Unit";"Zealot";"Gateway";378;2
"Unit";"Zealot";"Gateway";378;2
"Unit";"Zealot";"Gateway";378;2
"Unit";"Zealot";"Gateway";378;2
"Unit";"Tempest";"Stargate";378;4
"Unit";"Stalker";"Gateway";396;2
"Unit";"Stalker";"Gateway";396;2
"Unit";"Stalker";"Gateway";396;2
"Unit";"Stalker";"Gateway";396;2
"Unit";"Stalker";"Gateway";396;2
"Unit";"Stalker";"Gateway";396;2
"Unit";"Sentry";"Gateway";396;2
"Unit";"Sentry";"Gateway";396;2
"Unit";"Immortal";"Robotics Facility";396;4
"Unit";"Immortal";"Robotics Facility";396;4
"Unit";"Zealot";"Gateway";420;2
"Unit";"Zealot";"Gateway";420;2
"Unit";"Zealot";"Gateway";420;2
"Unit";"Zealot";"Gateway";420;2
"Unit";"Zealot";"Gateway";420;2
