"type";"unit_name";"on_building";"total_supply";"supply"
"Building";"Pylon";NA;13;0
"Building";"Assimilator";NA;15;0
"Building";"Gateway";NA;15;0
"Building";"Assimilator";NA;20;0
"Building";"CyberneticsCore";NA;20;0
"Building";"Pylon";NA;21;0
"Unit";"Adept";"Gateway";22;2
"Building";"Nexus";NA;20;0
"Unit";"Adept";"Gateway";24;2
"Building";"Pylon";NA;28;0
"Unit";"Adept";"Gateway";28;2
"Building";"RoboticsFacility";NA;28;0
"Unit";"Adept";"Gateway";35;2
"Unit";"Immortal";"Robotics Facility";39;4
"Building";"ShieldBattery";NA;44;0
"Building";"Gateway";NA;40;0
"Building";"Assimilator";NA;44;0
"Building";"Gateway";NA;40;0
"Building";"Assimilator";NA;44;0
"Building";"Pylon";NA;50;0
"Building";"Pylon";NA;50;0
"Unit";"Sentry";"Gateway";52;2
"Unit";"Sentry";"Gateway";52;2
"Unit";"Sentry";"Gateway";52;2
"Unit";"Observer";"Robotics Facility";52;1
"Building";"Forge";NA;52;0
"Building";"RoboticsBay";NA;52;0
"Building";"Pylon";NA;62;0
"Unit";"Stalker";"Gateway";64;2
"Unit";"Stalker";"Gateway";64;2
"Unit";"Stalker";"Gateway";64;2
"Building";"Pylon";NA;64;0
"Unit";"Adept";"Gateway";70;2
"Unit";"Adept";"Gateway";70;2
"Unit";"Adept";"Gateway";70;2
"Building";"Nexus";NA;64;0
"Unit";"Sentry";"Gateway";82;2
"Unit";"Sentry";"Gateway";82;2
"Unit";"Sentry";"Gateway";82;2
"Upgrade";"ProtossGroundWeaponsLevel1";"Forge";68;0
"Unit";"Adept";"Gateway";95;2
"Unit";"Adept";"Gateway";100;2
"Unit";"Adept";"Gateway";102;2
"Unit";"Colossus";"Robotics Facility";89;6
"Unit";"Stalker";"Gateway";110;2
"Unit";"Stalker";"Gateway";110;2
"Unit";"Stalker";"Gateway";110;2
"Building";"Pylon";NA;124;0
"Building";"Pylon";NA;124;0
"Unit";"Sentry";"Gateway";125;2
"Unit";"Sentry";"Gateway";125;2
"Unit";"Sentry";"Gateway";125;2
"Unit";"Colossus";"Robotics Facility";124;6
"Building";"Assimilator";NA;125;0
"Building";"Assimilator";NA;125;0
"Building";"Pylon";NA;125;0
"Upgrade";"ExtendedThermalLance";"RoboticsBay";124;0
"Upgrade";"ProtossGroundArmorsLevel1";"Forge";109;0
"Building";"Forge";NA;125;0
"Building";"TwilightCouncil";NA;125;0
"Unit";"Stalker";"Gateway";143;2
"Unit";"Stalker";"Gateway";143;2
"Unit";"Stalker";"Gateway";143;2
"Unit";"Colossus";"Robotics Facility";133;6
"Building";"Pylon";NA;150;0
"Building";"Gateway";NA;141;0
"Building";"Gateway";NA;142;0
"Building";"Gateway";NA;142;0
"Building";"Pylon";NA;156;0
"Unit";"Observer";"Robotics Facility";150;1
"Building";"PhotonCannon";NA;150;0
"Building";"PhotonCannon";NA;150;0
"Unit";"Stalker";"Gateway";163;2
"Unit";"Stalker";"Gateway";163;2
"Unit";"Stalker";"Gateway";163;2
"Unit";"Observer";"Robotics Facility";162;1
"Upgrade";"Charge";"TwilightCouncil";150;0
"Building";"Nexus";NA;150;0
"Unit";"Adept";"Gateway";177;2
"Unit";"Adept";"Gateway";177;2
"Unit";"Adept";"Gateway";177;2
"Unit";"Adept";"Gateway";177;2
"Unit";"Adept";"Gateway";177;2
"Unit";"Adept";"Gateway";177;2
"Building";"TemplarArchive";NA;176;0
"Unit";"Immortal";"Robotics Facility";177;4
"Upgrade";"ProtossGroundWeaponsLevel2";"Forge";150;0
"Upgrade";"ProtossGroundArmorsLevel2";"Forge";156;0
"Unit";"Stalker";"Gateway";189;2
"Unit";"Stalker";"Gateway";189;2
"Unit";"Stalker";"Gateway";200;2
"Unit";"Stalker";"Gateway";200;2
"Unit";"Stalker";"Gateway";200;2
"Building";"PhotonCannon";NA;198;0
"Building";"HighTemplar";NA;209;0
"Building";"HighTemplar";NA;209;0
"Building";"HighTemplar";NA;209;0
"Unit";"Zealot";"Gateway";214;2
"Unit";"Zealot";"Gateway";214;2
"Unit";"Zealot";"Gateway";214;2
"Unit";"Zealot";"Gateway";214;2
"Unit";"Zealot";"Gateway";214;2
"Unit";"Zealot";"Gateway";214;2
"Building";"Gateway";NA;211;0
"Building";"Gateway";NA;212;0
"Building";"Assimilator";NA;213;0
"Building";"Gateway";NA;213;0
"Building";"Assimilator";NA;213;0
"Unit";"Zealot";"Gateway";226;2
"Unit";"Zealot";"Gateway";226;2
"Unit";"Zealot";"Gateway";226;2
"Unit";"Zealot";"Gateway";226;2
"Unit";"Zealot";"Gateway";226;2
"Building";"HighTemplar";NA;236;0
"Building";"HighTemplar";NA;236;0
"Building";"HighTemplar";NA;236;0
"Building";"HighTemplar";NA;241;0
"Building";"HighTemplar";NA;241;0
"Building";"HighTemplar";NA;241;0
"Unit";"Zealot";"Gateway";241;2
"Unit";"Zealot";"Gateway";241;2
"Unit";"Immortal";"Robotics Facility";226;4
"Building";"Pylon";NA;237;0
"Building";"Pylon";NA;241;0
"Unit";"Zealot";"Gateway";254;2
"Unit";"Zealot";"Gateway";254;2
"Unit";"Zealot";"Gateway";254;2
"Building";"HighTemplar";NA;261;0
"Building";"HighTemplar";NA;261;0
"Building";"HighTemplar";NA;261;0
"Building";"HighTemplar";NA;261;0
"Building";"RoboticsFacility";NA;241;0
"Unit";"Archon";"High Templar";261;0
"Unit";"Archon";"High Templar";261;0
"Upgrade";"ProtossGroundWeaponsLevel3";"Forge";213;0
"Upgrade";"ProtossGroundArmorsLevel3";"Forge";213;0
"Unit";"Stalker";"Gateway";261;2
"Unit";"Stalker";"Gateway";261;2
"Unit";"Stalker";"Gateway";261;2
"Unit";"Stalker";"Gateway";261;2
"Unit";"Colossus";"Robotics Facility";251;6
"Building";"Pylon";NA;261;0
"Unit";"Stalker";"Gateway";275;2
"Unit";"Stalker";"Gateway";275;2
"Unit";"Stalker";"Gateway";275;2
"Unit";"Stalker";"Gateway";275;2
"Unit";"Stalker";"Gateway";283;2
"Unit";"Stalker";"Gateway";283;2
"Unit";"Stalker";"Gateway";283;2
"Unit";"Stalker";"Gateway";283;2
"Building";"DarkShrine";NA;252;0
"Unit";"Immortal";"Robotics Facility";261;4
