"type";"unit_name";"on_building";"total_supply";"supply"
"Building";"Pylon";NA;13;0
"Building";"Assimilator";NA;16;0
"Building";"Assimilator";NA;17;0
"Building";"Gateway";NA;15;0
"Building";"Assimilator";NA;18;0
"Building";"Pylon";NA;21;0
"Building";"CyberneticsCore";NA;20;0
"Building";"Pylon";NA;23;0
"Unit";"Adept";"Gateway";23;2
"Unit";"Sentry";"Gateway";24;2
"Building";"Stargate";NA;24;0
"Building";"Pylon";NA;30;0
"Unit";"Stalker";"Gateway";30;2
"Building";"Nexus";NA;24;0
"Unit";"Phoenix";"Stargate";31;2
"Building";"ShieldBattery";NA;35;0
"Unit";"Stalker";"Gateway";35;2
"Unit";"Phoenix";"Stargate";38;2
"Building";"Pylon";NA;45;0
"Unit";"Phoenix";"Stargate";48;2
"Building";"TwilightCouncil";NA;48;0
"Building";"Pylon";NA;52;0
"Building";"Assimilator";NA;52;0
"Building";"Assimilator";NA;54;0
"Building";"Forge";NA;52;0
"Building";"Forge";NA;52;0
"Building";"Gateway";NA;55;0
"Building";"Gateway";NA;55;0
"Unit";"Zealot";"Gateway";61;2
"Unit";"Zealot";"Gateway";63;2
"Unit";"Zealot";"Gateway";63;2
"Building";"Gateway";NA;59;0
"Building";"Gateway";NA;59;0
"Building";"Gateway";NA;59;0
"Building";"Pylon";NA;63;0
"Upgrade";"Charge";"TwilightCouncil";57;0
"Building";"Pylon";NA;63;0
"Building";"RoboticsFacility";NA;59;0
"Unit";"Zealot";"Gateway";67;2
"Unit";"Zealot";"Gateway";69;2
"Unit";"Zealot";"Gateway";69;2
"Unit";"Zealot";"Gateway";69;2
"Unit";"Zealot";"Gateway";69;2
"Unit";"Zealot";"Gateway";69;2
"Upgrade";"ProtossGroundArmorsLevel1";"Forge";59;0
"Unit";"Observer";"Robotics Facility";69;1
"Unit";"Zealot";"Gateway";80;2
"Unit";"Zealot";"Gateway";80;2
"Unit";"Zealot";"Gateway";80;2
"Unit";"Zealot";"Gateway";80;2
"Unit";"Zealot";"Gateway";80;2
"Unit";"Zealot";"Gateway";80;2
"Unit";"Phoenix";"Stargate";69;2
"Upgrade";"ProtossGroundWeaponsLevel1";"Forge";59;0
"Unit";"Observer";"Robotics Facility";80;1
"Building";"Nexus";NA;63;0
"Unit";"Zealot";"Gateway";94;2
"Unit";"Zealot";"Gateway";94;2
"Unit";"Zealot";"Gateway";94;2
"Unit";"Zealot";"Gateway";94;2
"Unit";"Zealot";"Gateway";94;2
"Unit";"Zealot";"Gateway";94;2
"Unit";"Phoenix";"Stargate";95;2
"Unit";"Observer";"Robotics Facility";111;1
"Unit";"Phoenix";"Stargate";111;2
"Building";"RoboticsBay";NA;111;0
"Building";"RoboticsFacility";NA;111;0
"Building";"Assimilator";NA;112;0
"Unit";"Sentry";"Gateway";119;2
"Unit";"Sentry";"Gateway";119;2
"Building";"Pylon";NA;117;0
"Building";"Assimilator";NA;114;0
"Unit";"Observer";"Robotics Facility";114;1
"Building";"Pylon";NA;117;0
"Building";"Nexus";NA;114;0
"Unit";"Colossus";"Robotics Facility";124;6
"Upgrade";"ProtossGroundWeaponsLevel2";"Forge";111;0
"Upgrade";"ProtossGroundArmorsLevel2";"Forge";111;0
"Unit";"Colossus";"Robotics Facility";124;6
"Building";"Pylon";NA;131;0
"Building";"Pylon";NA;131;0
"Unit";"Observer";"Robotics Facility";145;1
"Building";"Gateway";NA;127;0
"Unit";"Observer";"Robotics Facility";145;1
"Building";"Gateway";NA;128;0
"Building";"Gateway";NA;128;0
"Building";"Gateway";NA;129;0
"Upgrade";"ProtossAirWeaponsLevel1";"CyberneticsCore";124;0
"Building";"DarkShrine";NA;127;0
"Upgrade";"ExtendedThermalLance";"RoboticsBay";127;0
"Building";"PhotonCannon";NA;147;0
"Building";"PhotonCannon";NA;147;0
"Building";"ShieldBattery";NA;147;0
"Building";"FleetBeacon";NA;145;0
"Unit";"Disruptor";"Robotics Facility";146;3
"Unit";"Disruptor";"Robotics Facility";146;3
"Building";"Pylon";NA;147;0
"Unit";"Zealot";"Gateway";153;2
"Unit";"Zealot";"Gateway";153;2
"Unit";"Zealot";"Gateway";153;2
"Unit";"Zealot";"Gateway";153;2
"Unit";"Zealot";"Gateway";153;2
"Unit";"Zealot";"Gateway";153;2
"Building";"PhotonCannon";NA;147;0
"Building";"ShieldBattery";NA;147;0
"Unit";"Disruptor";"Robotics Facility";147;3
"Unit";"Disruptor";"Robotics Facility";147;3
"Building";"Stargate";NA;147;0
"Unit";"Tempest";"Stargate";161;4
"Unit";"Disruptor";"Robotics Facility";171;3
"Unit";"Disruptor";"Robotics Facility";171;3
"Building";"Pylon";NA;175;0
"Building";"Pylon";NA;175;0
"Unit";"Tempest";"Stargate";175;4
"Unit";"Tempest";"Stargate";175;4
"Unit";"Zealot";"Gateway";181;2
"Unit";"Zealot";"Gateway";181;2
"Unit";"Zealot";"Gateway";181;2
"Unit";"Zealot";"Gateway";181;2
"Unit";"Zealot";"Gateway";181;2
"Unit";"Zealot";"Gateway";181;2
"Upgrade";"ProtossGroundWeaponsLevel3";"Forge";147;0
"Upgrade";"ProtossGroundArmorsLevel3";"Forge";147;0
"Unit";"Zealot";"Gateway";201;2
"Unit";"Zealot";"Gateway";201;2
"Unit";"Zealot";"Gateway";201;2
"Unit";"Zealot";"Gateway";201;2
"Unit";"Zealot";"Gateway";201;2
"Unit";"Zealot";"Gateway";201;2
"Building";"Pylon";NA;216;0
"Unit";"Phoenix";"Stargate";216;2
"Unit";"Phoenix";"Stargate";216;2
"Building";"Pylon";NA;216;0
"Unit";"Disruptor";"Robotics Facility";203;3
"Unit";"Disruptor";"Robotics Facility";207;3
"Building";"Assimilator";NA;216;0
"Building";"Assimilator";NA;216;0
"Building";"Pylon";NA;216;0
"Building";"Pylon";NA;216;0
"Unit";"Phoenix";"Stargate";216;2
"Unit";"Phoenix";"Stargate";216;2
"Building";"Nexus";NA;216;0
"Unit";"Phoenix";"Stargate";230;2
"Unit";"Phoenix";"Stargate";230;2
"Building";"DarkTemplar";NA;234;0
"Building";"Pylon";NA;230;0
"Building";"Pylon";NA;230;0
"Unit";"Colossus";"Robotics Facility";230;6
"Unit";"Colossus";"Robotics Facility";230;6
"Building";"Stargate";NA;230;0
"Building";"Stargate";NA;230;0
"Upgrade";"ProtossAirWeaponsLevel2";"CyberneticsCore";226;0
"Unit";"Immortal";"Robotics Facility";234;4
"Unit";"Immortal";"Robotics Facility";234;4
"Unit";"Stalker";"Gateway";254;2
"Unit";"Stalker";"Gateway";258;2
"Unit";"Stalker";"Gateway";258;2
"Unit";"Stalker";"Gateway";258;2
"Unit";"Stalker";"Gateway";258;2
"Building";"Nexus";NA;230;0
"Upgrade";"ProtossShieldsLevel1";"Forge";230;0
"Unit";"Phoenix";"Stargate";250;2
"Unit";"Phoenix";"Stargate";250;2
"Unit";"Phoenix";"Stargate";250;2
"Unit";"Phoenix";"Stargate";250;2
"Building";"RoboticsFacility";NA;249;0
"Building";"RoboticsFacility";NA;249;0
"Building";"DarkTemplar";NA;276;0
"Upgrade";"GraviticDrive";"RoboticsBay";258;0
"Unit";"Disruptor";"Robotics Facility";268;3
"Unit";"Zealot";"Gateway";279;2
"Unit";"Zealot";"Gateway";279;2
"Unit";"Zealot";"Gateway";279;2
"Unit";"Zealot";"Gateway";279;2
"Unit";"Zealot";"Gateway";279;2
"Unit";"Zealot";"Gateway";279;2
"Unit";"Zealot";"Gateway";279;2
"Unit";"Zealot";"Gateway";279;2
"Unit";"Zealot";"Gateway";279;2
"Unit";"Zealot";"Gateway";279;2
"Unit";"Phoenix";"Stargate";299;2
"Unit";"Phoenix";"Stargate";299;2
"Unit";"Phoenix";"Stargate";299;2
"Unit";"Phoenix";"Stargate";299;2
"Building";"Assimilator";NA;299;0
"Building";"Assimilator";NA;299;0
"Unit";"Immortal";"Robotics Facility";299;4
"Upgrade";"ProtossAirWeaponsLevel3";"CyberneticsCore";276;0
"Building";"RoboticsFacility";NA;299;0
"Unit";"Colossus";"Robotics Facility";299;6
"Unit";"Colossus";"Robotics Facility";299;6
"Building";"DarkTemplar";NA;323;0
"Unit";"Tempest";"Stargate";307;4
"Unit";"Tempest";"Stargate";307;4
"Unit";"Tempest";"Stargate";307;4
"Unit";"Tempest";"Stargate";307;4
"Unit";"Disruptor";"Robotics Facility";323;3
"Unit";"Immortal";"Robotics Facility";323;4
"Unit";"Immortal";"Robotics Facility";323;4
"Unit";"Immortal";"Robotics Facility";339;4
"Upgrade";"ProtossAirArmorsLevel1";"CyberneticsCore";323;0
"Building";"Pylon";NA;350;0
"Building";"Pylon";NA;350;0
"Building";"Assimilator";NA;354;0
"Building";"Assimilator";NA;354;0
"Unit";"Phoenix";"Stargate";354;2
"Unit";"Phoenix";"Stargate";354;2
"Unit";"Phoenix";"Stargate";354;2
"Unit";"Phoenix";"Stargate";354;2
