"type";"unit_name";"on_building";"total_supply";"supply"
"Building";"Pylon";NA;13;0
"Building";"Assimilator";NA;16;0
"Building";"Gateway";NA;15;0
"Building";"Assimilator";NA;20;0
"Building";"CyberneticsCore";NA;20;0
"Building";"Pylon";NA;21;0
"Building";"Nexus";NA;20;0
"Unit";"Stalker";"Gateway";22;2
"Building";"Pylon";NA;23;0
"Unit";"Stalker";"Gateway";24;2
"Building";"RoboticsFacility";NA;27;0
"Unit";"Stalker";"Gateway";33;2
"Unit";"Observer";"Robotics Facility";37;1
"Building";"ShieldBattery";NA;37;0
"Building";"Pylon";NA;41;0
"Unit";"Observer";"Robotics Facility";43;1
"Building";"Gateway";NA;37;0
"Building";"Gateway";NA;37;0
"Unit";"Sentry";"Gateway";49;2
"Building";"Pylon";NA;47;0
"Building";"Pylon";NA;51;0
"Unit";"Stalker";"Gateway";56;2
"Unit";"Stalker";"Gateway";56;2
"Building";"Forge";NA;53;0
"Building";"TwilightCouncil";NA;53;0
"Building";"Forge";NA;53;0
"Building";"Nexus";NA;46;0
"Unit";"Immortal";"Robotics Facility";55;4
"Building";"Assimilator";NA;61;0
"Building";"Gateway";NA;55;0
"Building";"Gateway";NA;55;0
"Building";"Pylon";NA;70;0
"Building";"Pylon";NA;70;0
"Building";"Pylon";NA;70;0
"Building";"Pylon";NA;70;0
"Building";"Pylon";NA;73;0
"Unit";"Zealot";"Gateway";73;2
"Unit";"Zealot";"Gateway";74;2
"Unit";"Zealot";"Gateway";74;2
"Building";"Pylon";NA;73;0
"Unit";"Immortal";"Robotics Facility";70;4
"Unit";"Zealot";"Gateway";87;2
"Unit";"Zealot";"Gateway";87;2
"Building";"Assimilator";NA;81;0
"Building";"Assimilator";NA;85;0
"Upgrade";"Charge";"TwilightCouncil";70;0
"Building";"Gateway";NA;74;0
"Building";"Gateway";NA;75;0
"Building";"Gateway";NA;75;0
"Upgrade";"ProtossGroundWeaponsLevel1";"Forge";70;0
"Building";"Gateway";NA;81;0
"Unit";"Zealot";"Gateway";96;2
"Unit";"Zealot";"Gateway";96;2
"Unit";"Zealot";"Gateway";97;2
"Unit";"Zealot";"Gateway";97;2
"Building";"Assimilator";NA;92;0
"Upgrade";"ProtossGroundArmorsLevel1";"Forge";73;0
"Building";"Pylon";NA;97;0
"Unit";"Immortal";"Robotics Facility";91;4
"Building";"Pylon";NA;106;0
"Building";"TemplarArchive";NA;95;0
"Unit";"Zealot";"Gateway";111;2
"Unit";"Zealot";"Gateway";111;2
"Unit";"Zealot";"Gateway";111;2
"Building";"PhotonCannon";NA;106;0
"Building";"Gateway";NA;95;0
"Building";"Gateway";NA;96;0
"Building";"HighTemplar";NA;117;0
"Building";"HighTemplar";NA;117;0
"Unit";"Zealot";"Gateway";117;2
"Unit";"Zealot";"Gateway";117;2
"Unit";"Zealot";"Gateway";117;2
"Unit";"Zealot";"Gateway";117;2
"Unit";"Zealot";"Gateway";117;2
"Unit";"Immortal";"Robotics Facility";110;4
"Unit";"Zealot";"Gateway";131;2
"Unit";"Zealot";"Gateway";131;2
"Unit";"Zealot";"Gateway";131;2
"Unit";"Stalker";"Gateway";137;2
"Unit";"Stalker";"Gateway";137;2
"Unit";"Stalker";"Gateway";137;2
"Building";"HighTemplar";NA;137;0
"Building";"HighTemplar";NA;143;0
"Building";"HighTemplar";NA;143;0
"Building";"Pylon";NA;137;0
"Building";"HighTemplar";NA;143;0
"Building";"Pylon";NA;137;0
"Building";"HighTemplar";NA;144;0
"Unit";"Adept";"Gateway";137;2
"Building";"Assimilator";NA;143;0
"Building";"Assimilator";NA;143;0
"Building";"Pylon";NA;145;0
"Building";"HighTemplar";NA;147;0
"Unit";"Zealot";"Gateway";147;2
"Building";"Pylon";NA;145;0
"Unit";"Zealot";"Gateway";147;2
"Building";"Pylon";NA;145;0
"Upgrade";"ProtossGroundWeaponsLevel2";"Forge";111;0
"Upgrade";"ProtossGroundArmorsLevel2";"Forge";115;0
"Building";"Nexus";NA;137;0
"Unit";"Zealot";"Gateway";151;2
"Unit";"Zealot";"Gateway";151;2
"Unit";"Zealot";"Gateway";151;2
"Unit";"Zealot";"Gateway";151;2
"Unit";"Zealot";"Gateway";151;2
"Unit";"Zealot";"Gateway";151;2
"Unit";"Zealot";"Gateway";151;2
"Unit";"Zealot";"Gateway";151;2
"Unit";"Immortal";"Robotics Facility";147;4
"Building";"HighTemplar";NA;167;0
"Building";"PhotonCannon";NA;171;0
"Unit";"Immortal";"Robotics Facility";171;4
"Building";"Gateway";NA;171;0
"Building";"RoboticsFacility";NA;171;0
"Building";"RoboticsFacility";NA;172;0
"Building";"RoboticsBay";NA;172;0
"Unit";"Stalker";"Gateway";178;2
"Unit";"Stalker";"Gateway";178;2
"Unit";"Stalker";"Gateway";178;2
"Unit";"Stalker";"Gateway";178;2
"Unit";"Stalker";"Gateway";178;2
"Unit";"Stalker";"Gateway";178;2
"Unit";"Stalker";"Gateway";178;2
"Unit";"Stalker";"Gateway";178;2
"Unit";"Stalker";"Gateway";178;2
"Unit";"Stalker";"Gateway";178;2
"Unit";"Stalker";"Gateway";178;2
"Unit";"Archon";"High Templar";198;0
"Unit";"Archon";"High Templar";200;0
"Upgrade";"ProtossGroundArmorsLevel3";"Forge";151;0
"Upgrade";"ProtossGroundWeaponsLevel3";"Forge";171;0
"Unit";"Immortal";"Robotics Facility";178;4
"Unit";"Stalker";"Gateway";204;2
"Unit";"Stalker";"Gateway";204;2
"Unit";"Stalker";"Gateway";204;2
"Unit";"Stalker";"Gateway";204;2
"Unit";"Archon";"High Templar";212;0
"Unit";"Colossus";"Robotics Facility";204;6
"Unit";"Colossus";"Robotics Facility";204;6
"Unit";"Stalker";"Gateway";212;2
"Unit";"Stalker";"Gateway";212;2
"Unit";"Stalker";"Gateway";212;2
"Unit";"Stalker";"Gateway";212;2
"Unit";"Stalker";"Gateway";212;2
"Unit";"Stalker";"Gateway";212;2
"Unit";"Stalker";"Gateway";212;2
"Unit";"Stalker";"Gateway";212;2
"Unit";"Stalker";"Gateway";212;2
"Unit";"Stalker";"Gateway";212;2
"Unit";"Stalker";"Gateway";212;2
"Unit";"Colossus";"Robotics Facility";204;6
"Unit";"Stalker";"Gateway";254;2
"Unit";"Stalker";"Gateway";254;2
"Unit";"Stalker";"Gateway";254;2
"Unit";"Stalker";"Gateway";254;2
"Unit";"Stalker";"Gateway";254;2
"Unit";"Stalker";"Gateway";254;2
"Building";"HighTemplar";NA;266;0
"Building";"HighTemplar";NA;266;0
"Unit";"Colossus";"Robotics Facility";212;6
"Building";"Pylon";NA;266;0
"Building";"Pylon";NA;266;0
"Unit";"Colossus";"Robotics Facility";254;6
"Upgrade";"ExtendedThermalLance";"RoboticsBay";248;0
"Unit";"Zealot";"Gateway";278;2
"Unit";"Zealot";"Gateway";278;2
"Unit";"Zealot";"Gateway";278;2
"Unit";"Zealot";"Gateway";278;2
"Unit";"Zealot";"Gateway";278;2
"Upgrade";"ProtossShieldsLevel1";"Forge";254;0
"Unit";"Zealot";"Gateway";288;2
"Building";"Nexus";NA;266;0
"Unit";"Zealot";"Gateway";290;2
"Unit";"Zealot";"Gateway";290;2
"Unit";"Zealot";"Gateway";290;2
"Building";"Nexus";NA;266;0
"Building";"HighTemplar";NA;296;0
"Building";"HighTemplar";NA;296;0
"Unit";"Observer";"Robotics Facility";296;1
"Unit";"Zealot";"Gateway";297;2
"Building";"DarkShrine";NA;288;0
"Unit";"Zealot";"Gateway";299;2
"Unit";"Zealot";"Gateway";299;2
"Unit";"Zealot";"Gateway";299;2
"Unit";"Colossus";"Robotics Facility";296;6
"Building";"DarkTemplar";NA;305;0
"Building";"DarkTemplar";NA;305;0
"Building";"DarkTemplar";NA;305;0
"Building";"DarkTemplar";NA;311;0
"Building";"DarkTemplar";NA;311;0
