"type";"unit_name";"on_building";"total_supply";"supply"
"Building";"Pylon";NA;13;0
"Building";"Assimilator";NA;16;0
"Building";"Gateway";NA;15;0
"Building";"Assimilator";NA;20;0
"Building";"Pylon";NA;21;0
"Building";"CyberneticsCore";NA;19;0
"Unit";"Stalker";"Gateway";21;2
"Building";"Nexus";NA;19;0
"Unit";"Stalker";"Gateway";25;2
"Building";"Pylon";NA;30;0
"Building";"Pylon";NA;35;0
"Unit";"Stalker";"Gateway";32;2
"Building";"Pylon";NA;45;0
"Unit";"Stalker";"Gateway";48;2
"Building";"Gateway";NA;42;0
"Building";"Gateway";NA;42;0
"Building";"Assimilator";NA;47;0
"Building";"TwilightCouncil";NA;45;0
"Unit";"Stalker";"Gateway";54;2
"Unit";"Stalker";"Gateway";54;2
"Unit";"Stalker";"Gateway";61;2
"Building";"Nexus";NA;43;0
"Unit";"Stalker";"Gateway";65;2
"Building";"Forge";NA;53;0
"Unit";"Stalker";"Gateway";67;2
"Building";"Forge";NA;60;0
"Unit";"Stalker";"Gateway";74;2
"Unit";"Stalker";"Gateway";74;2
"Building";"Pylon";NA;84;0
"Unit";"Stalker";"Gateway";85;2
"Unit";"Stalker";"Gateway";85;2
"Unit";"Stalker";"Gateway";85;2
"Building";"RoboticsFacility";NA;81;0
"Building";"Pylon";NA;85;0
"Unit";"Sentry";"Gateway";94;2
"Unit";"Sentry";"Gateway";94;2
"Unit";"Zealot";"Gateway";94;2
"Building";"Gateway";NA;85;0
"Building";"Gateway";NA;85;0
"Unit";"Observer";"Robotics Facility";92;1
"Building";"Pylon";NA;98;0
"Building";"Pylon";NA;98;0
"Upgrade";"ProtossGroundWeaponsLevel1";"Forge";81;0
"Unit";"Zealot";"Gateway";101;2
"Unit";"Zealot";"Gateway";101;2
"Unit";"Zealot";"Gateway";101;2
"Unit";"Zealot";"Gateway";101;2
"Unit";"Zealot";"Gateway";101;2
"Building";"RoboticsFacility";NA;92;0
"Building";"Gateway";NA;92;0
"Upgrade";"ProtossGroundArmorsLevel1";"Forge";85;0
"Building";"Gateway";NA;92;0
"Unit";"Immortal";"Robotics Facility";101;4
"Building";"Pylon";NA;115;0
"Building";"Gateway";NA;100;0
"Unit";"Zealot";"Gateway";118;2
"Unit";"Zealot";"Gateway";118;2
"Unit";"Zealot";"Gateway";118;2
"Building";"Assimilator";NA;114;0
"Upgrade";"Charge";"TwilightCouncil";94;0
"Building";"Pylon";NA;117;0
"Building";"Assimilator";NA;116;0
"Building";"Assimilator";NA;122;0
"Unit";"Zealot";"Gateway";130;2
"Unit";"Observer";"Robotics Facility";123;1
"Unit";"Zealot";"Gateway";130;2
"Unit";"Zealot";"Gateway";130;2
"Unit";"Zealot";"Gateway";130;2
"Building";"Pylon";NA;130;0
"Unit";"Zealot";"Gateway";139;2
"Unit";"Zealot";"Gateway";139;2
"Unit";"Zealot";"Gateway";143;2
"Unit";"Zealot";"Gateway";143;2
"Unit";"Zealot";"Gateway";143;2
"Unit";"Zealot";"Gateway";143;2
"Unit";"Zealot";"Gateway";143;2
"Unit";"Zealot";"Gateway";153;2
"Unit";"Zealot";"Gateway";153;2
"Unit";"Zealot";"Gateway";157;2
"Unit";"Stalker";"Gateway";159;2
"Unit";"Stalker";"Gateway";159;2
"Building";"RoboticsBay";NA;139;0
"Unit";"Stalker";"Gateway";159;2
"Unit";"Stalker";"Gateway";159;2
"Unit";"Stalker";"Gateway";159;2
"Building";"Nexus";NA;130;0
"Unit";"Immortal";"Robotics Facility";153;4
"Building";"Pylon";NA;169;0
"Upgrade";"ProtossGroundWeaponsLevel2";"Forge";130;0
"Upgrade";"ProtossGroundArmorsLevel2";"Forge";130;0
"Unit";"Zealot";"Gateway";180;2
"Unit";"Zealot";"Gateway";180;2
"Unit";"Zealot";"Gateway";180;2
"Unit";"Zealot";"Gateway";180;2
"Unit";"Zealot";"Gateway";180;2
"Unit";"Zealot";"Gateway";180;2
"Unit";"Zealot";"Gateway";180;2
"Unit";"Zealot";"Gateway";180;2
"Unit";"Colossus";"Robotics Facility";177;6
"Building";"PhotonCannon";NA;196;0
"Building";"Pylon";NA;197;0
"Unit";"Zealot";"Gateway";204;2
"Unit";"Zealot";"Gateway";205;2
"Unit";"Zealot";"Gateway";205;2
"Unit";"Zealot";"Gateway";206;2
"Unit";"Zealot";"Gateway";206;2
"Building";"PhotonCannon";NA;197;0
"Building";"Pylon";NA;198;0
"Building";"ShieldBattery";NA;197;0
"Unit";"Zealot";"Gateway";218;2
"Unit";"Zealot";"Gateway";218;2
"Unit";"Zealot";"Gateway";218;2
"Upgrade";"ExtendedThermalLance";"RoboticsBay";177;0
"Unit";"Zealot";"Gateway";224;2
"Unit";"Zealot";"Gateway";224;2
"Unit";"Zealot";"Gateway";224;2
"Unit";"Zealot";"Gateway";224;2
"Unit";"Zealot";"Gateway";224;2
"Building";"Pylon";NA;224;0
"Unit";"Colossus";"Robotics Facility";198;6
"Building";"DarkShrine";NA;198;0
"Building";"Stargate";NA;224;0
"Building";"Assimilator";NA;240;0
"Building";"PhotonCannon";NA;240;0
"Building";"ShieldBattery";NA;240;0
"Upgrade";"ProtossGroundWeaponsLevel3";"Forge";196;0
"Unit";"Zealot";"Gateway";251;2
"Unit";"Zealot";"Gateway";251;2
"Unit";"Zealot";"Gateway";251;2
"Unit";"Zealot";"Gateway";251;2
"Unit";"Zealot";"Gateway";251;2
"Upgrade";"ProtossGroundArmorsLevel3";"Forge";197;0
"Unit";"Zealot";"Gateway";263;2
"Unit";"Zealot";"Gateway";263;2
"Unit";"Colossus";"Robotics Facility";240;6
"Unit";"Colossus";"Robotics Facility";240;6
"Unit";"Zealot";"Gateway";279;2
"Unit";"Zealot";"Gateway";279;2
"Building";"PhotonCannon";NA;251;0
"Building";"PhotonCannon";NA;262;0
"Building";"Assimilator";NA;267;0
"Building";"Assimilator";NA;267;0
"Building";"Pylon";NA;279;0
"Building";"TemplarArchive";NA;262;0
"Building";"HighTemplar";NA;283;0
"Building";"HighTemplar";NA;283;0
"Building";"HighTemplar";NA;283;0
"Building";"HighTemplar";NA;283;0
"Unit";"Zealot";"Gateway";283;2
"Unit";"Zealot";"Gateway";283;2
"Unit";"Zealot";"Gateway";283;2
"Unit";"Zealot";"Gateway";283;2
"Building";"FleetBeacon";NA;283;0
"Unit";"Archon";"High Templar";291;0
"Unit";"Archon";"High Templar";291;0
"Unit";"Zealot";"Gateway";291;2
"Unit";"Zealot";"Gateway";291;2
"Unit";"Zealot";"Gateway";291;2
"Unit";"Zealot";"Gateway";291;2
"Building";"Pylon";NA;291;0
"Building";"Pylon";NA;291;0
"Upgrade";"ProtossShieldsLevel1";"Forge";279;0
"Unit";"Colossus";"Robotics Facility";283;6
"Unit";"Colossus";"Robotics Facility";283;6
"Building";"Stargate";NA;283;0
"Building";"HighTemplar";NA;311;0
"Building";"HighTemplar";NA;311;0
"Unit";"Tempest";"Stargate";299;4
"Unit";"Tempest";"Stargate";299;4
"Unit";"Colossus";"Robotics Facility";299;6
"Building";"Assimilator";NA;311;0
"Building";"Nexus";NA;291;0
"Unit";"Colossus";"Robotics Facility";299;6
"Building";"Assimilator";NA;311;0
"Unit";"Zealot";"Gateway";331;2
"Unit";"Zealot";"Gateway";331;2
"Building";"HighTemplar";NA;335;0
"Building";"HighTemplar";NA;335;0
"Upgrade";"ProtossAirWeaponsLevel1";"CyberneticsCore";299;0
"Unit";"Tempest";"Stargate";315;4
"Unit";"Tempest";"Stargate";319;4
"Building";"PhotonCannon";NA;335;0
"Building";"PhotonCannon";NA;335;0
"Building";"ShieldBattery";NA;345;0
"Building";"CyberneticsCore";NA;345;0
"Building";"DarkTemplar";NA;345;0
"Building";"DarkTemplar";NA;345;0
"Building";"Assimilator";NA;345;0
"Unit";"Archon";"High Templar";345;0
"Unit";"Zealot";"Gateway";345;2
"Unit";"Archon";"High Templar";345;0
"Unit";"Zealot";"Gateway";345;2
"Unit";"Zealot";"Gateway";345;2
"Unit";"Zealot";"Gateway";345;2
"Unit";"Zealot";"Gateway";345;2
"Unit";"Zealot";"Gateway";345;2
"Unit";"Zealot";"Gateway";357;2
"Unit";"Zealot";"Gateway";357;2
"Upgrade";"GraviticDrive";"RoboticsBay";345;0
"Building";"Assimilator";NA;357;0
"Building";"Pylon";NA;361;0
"Upgrade";"ProtossShieldsLevel2";"Forge";345;0
"Building";"Pylon";NA;361;0
