"type";"unit_name";"on_building";"total_supply";"supply"
"Building";"Pylon";NA;13;0
"Building";"Assimilator";NA;16;0
"Building";"Gateway";NA;15;0
"Building";"Assimilator";NA;20;0
"Building";"Pylon";NA;20;0
"Building";"CyberneticsCore";NA;20;0
"Unit";"Adept";"Gateway";21;2
"Building";"Nexus";NA;19;0
"Unit";"Stalker";"Gateway";23;2
"Building";"Stargate";NA;22;0
"Unit";"Oracle";"Stargate";30;3
"Building";"Pylon";NA;43;0
"Building";"Gateway";NA;36;0
"Building";"Gateway";NA;36;0
"Unit";"Phoenix";"Stargate";43;2
"Building";"Assimilator";NA;45;0
"Unit";"Phoenix";"Stargate";50;2
"Building";"Pylon";NA;52;0
"Unit";"Phoenix";"Stargate";54;2
"Building";"Pylon";NA;56;0
"Unit";"Phoenix";"Stargate";57;2
"Building";"Forge";NA;60;0
"Building";"Forge";NA;60;0
"Building";"Pylon";NA;62;0
"Building";"Gateway";NA;57;0
"Building";"Gateway";NA;57;0
"Building";"Nexus";NA;52;0
"Building";"Pylon";NA;64;0
"Unit";"Phoenix";"Stargate";64;2
"Building";"TwilightCouncil";NA;60;0
"Unit";"Zealot";"Gateway";75;2
"Building";"Assimilator";NA;73;0
"Building";"Assimilator";NA;73;0
"Unit";"Zealot";"Gateway";81;2
"Building";"Gateway";NA;70;0
"Building";"Assimilator";NA;75;0
"Unit";"Zealot";"Gateway";81;2
"Unit";"Zealot";"Gateway";81;2
"Unit";"Zealot";"Gateway";90;2
"Unit";"Zealot";"Gateway";90;2
"Building";"TemplarArchive";NA;73;0
"Building";"RoboticsFacility";NA;73;0
"Building";"HighTemplar";NA;96;0
"Building";"HighTemplar";NA;96;0
"Upgrade";"ProtossGroundWeaponsLevel1";"Forge";70;0
"Building";"Pylon";NA;97;0
"Building";"Pylon";NA;97;0
"Building";"Pylon";NA;97;0
"Unit";"Immortal";"Robotics Facility";86;4
"Upgrade";"ProtossGroundArmorsLevel1";"Forge";70;0
"Unit";"Zealot";"Gateway";102;2
"Unit";"Zealot";"Gateway";102;2
"Unit";"Zealot";"Gateway";102;2
"Unit";"Zealot";"Gateway";102;2
"Unit";"Archon";"High Templar";102;0
"Building";"Pylon";NA;98;0
"Building";"Pylon";NA;98;0
"Upgrade";"Charge";"TwilightCouncil";80;0
"Unit";"Zealot";"Gateway";112;2
"Unit";"Zealot";"Gateway";112;2
"Building";"Gateway";NA;97;0
"Unit";"Zealot";"Gateway";116;2
"Unit";"Zealot";"Gateway";116;2
"Unit";"Zealot";"Gateway";116;2
"Building";"Gateway";NA;98;0
"Unit";"Zealot";"Gateway";122;2
"Unit";"Zealot";"Gateway";124;2
"Unit";"Zealot";"Gateway";124;2
"Unit";"Zealot";"Gateway";124;2
"Unit";"Zealot";"Gateway";124;2
"Unit";"Zealot";"Gateway";124;2
"Unit";"Zealot";"Gateway";124;2
"Building";"HighTemplar";NA;136;0
"Building";"HighTemplar";NA;136;0
"Building";"HighTemplar";NA;136;0
"Building";"HighTemplar";NA;136;0
"Building";"HighTemplar";NA;136;0
"Building";"HighTemplar";NA;136;0
"Building";"HighTemplar";NA;136;0
"Building";"Pylon";NA;136;0
"Building";"Pylon";NA;136;0
"Unit";"Immortal";"Robotics Facility";126;4
"Unit";"Archon";"High Templar";136;0
"Unit";"Archon";"High Templar";136;0
"Unit";"Archon";"High Templar";136;0
"Building";"Pylon";NA;136;0
"Building";"Pylon";NA;136;0
"Building";"Pylon";NA;136;0
"Unit";"Zealot";"Gateway";140;2
"Building";"Pylon";NA;136;0
"Building";"Assimilator";NA;136;0
"Unit";"Zealot";"Gateway";142;2
"Unit";"Zealot";"Gateway";142;2
"Unit";"Zealot";"Gateway";142;2
"Unit";"Zealot";"Gateway";142;2
"Unit";"Zealot";"Gateway";142;2
"Unit";"Zealot";"Gateway";142;2
"Building";"Assimilator";NA;136;0
"Unit";"Immortal";"Robotics Facility";136;4
"Unit";"Zealot";"Gateway";154;2
"Unit";"Zealot";"Gateway";154;2
"Unit";"Stalker";"Gateway";162;2
"Unit";"Stalker";"Gateway";162;2
"Unit";"Stalker";"Gateway";162;2
"Unit";"Stalker";"Gateway";162;2
"Unit";"Stalker";"Gateway";162;2
"Unit";"Stalker";"Gateway";162;2
"Unit";"Phoenix";"Stargate";142;2
"Unit";"Zealot";"Gateway";176;2
"Unit";"Zealot";"Gateway";176;2
"Unit";"Phoenix";"Stargate";172;2
"Building";"Pylon";NA;176;0
"Building";"Pylon";NA;176;0
"Unit";"Zealot";"Gateway";182;2
"Unit";"Zealot";"Gateway";182;2
"Unit";"Zealot";"Gateway";182;2
"Unit";"Zealot";"Gateway";182;2
"Unit";"Zealot";"Gateway";182;2
"Unit";"Zealot";"Gateway";182;2
"Unit";"Immortal";"Robotics Facility";162;4
"Unit";"Zealot";"Gateway";198;2
"Unit";"Zealot";"Gateway";198;2
"Unit";"Zealot";"Gateway";202;2
"Unit";"Zealot";"Gateway";202;2
"Unit";"Zealot";"Gateway";202;2
"Unit";"Zealot";"Gateway";202;2
"Unit";"Zealot";"Gateway";202;2
"Unit";"Zealot";"Gateway";202;2
"Unit";"Phoenix";"Stargate";198;2
"Unit";"Sentry";"Gateway";214;2
"Unit";"Zealot";"Gateway";214;2
"Unit";"Zealot";"Gateway";220;2
"Unit";"Zealot";"Gateway";220;2
"Unit";"Zealot";"Gateway";220;2
"Unit";"Zealot";"Gateway";220;2
"Unit";"Zealot";"Gateway";220;2
"Unit";"Immortal";"Robotics Facility";198;4
"Unit";"Zealot";"Gateway";230;2
"Unit";"Zealot";"Gateway";236;2
"Unit";"Zealot";"Gateway";236;2
"Unit";"Zealot";"Gateway";236;2
"Unit";"Zealot";"Gateway";236;2
"Unit";"Zealot";"Gateway";236;2
"Unit";"Zealot";"Gateway";236;2
"Unit";"Phoenix";"Stargate";236;2
"Upgrade";"ProtossGroundWeaponsLevel2";"Forge";180;0
"Upgrade";"ProtossGroundArmorsLevel2";"Forge";182;0
"Building";"HighTemplar";NA;248;0
"Building";"HighTemplar";NA;248;0
"Building";"HighTemplar";NA;248;0
"Building";"HighTemplar";NA;248;0
"Building";"HighTemplar";NA;248;0
"Building";"HighTemplar";NA;248;0
"Building";"HighTemplar";NA;248;0
"Building";"HighTemplar";NA;250;0
"Unit";"Archon";"High Templar";250;0
"Unit";"Archon";"High Templar";250;0
"Unit";"Archon";"High Templar";250;0
"Unit";"Archon";"High Templar";250;0
"Unit";"Phoenix";"Stargate";248;2
"Building";"Pylon";NA;250;0
"Unit";"Zealot";"Gateway";252;2
"Unit";"Zealot";"Gateway";252;2
"Unit";"Zealot";"Gateway";252;2
"Unit";"Zealot";"Gateway";252;2
"Unit";"Zealot";"Gateway";252;2
"Unit";"Zealot";"Gateway";252;2
"Unit";"Phoenix";"Stargate";250;2
"Building";"HighTemplar";NA;266;0
"Building";"HighTemplar";NA;266;0
"Building";"HighTemplar";NA;266;0
"Building";"HighTemplar";NA;266;0
"Unit";"Zealot";"Gateway";266;2
"Unit";"Zealot";"Gateway";266;2
"Unit";"Zealot";"Gateway";266;2
"Unit";"Zealot";"Gateway";266;2
"Building";"RoboticsFacility";NA;250;0
"Unit";"Archon";"High Templar";266;0
"Unit";"Archon";"High Templar";266;0
"Unit";"Phoenix";"Stargate";264;2
"Building";"Nexus";NA;250;0
"Unit";"Zealot";"Gateway";276;2
"Unit";"Zealot";"Gateway";276;2
"Unit";"Zealot";"Gateway";276;2
"Unit";"Zealot";"Gateway";276;2
"Building";"RoboticsFacility";NA;274;0
"Building";"HighTemplar";NA;284;0
"Building";"HighTemplar";NA;284;0
"Unit";"Zealot";"Gateway";284;2
"Unit";"Zealot";"Gateway";284;2
"Unit";"Zealot";"Gateway";284;2
"Unit";"Zealot";"Gateway";284;2
"Unit";"Zealot";"Gateway";284;2
"Unit";"Zealot";"Gateway";284;2
"Unit";"Phoenix";"Stargate";284;2
"Unit";"Archon";"High Templar";302;0
"Building";"Assimilator";NA;284;0
"Upgrade";"ProtossGroundWeaponsLevel3";"Forge";250;0
"Upgrade";"ProtossGroundArmorsLevel3";"Forge";250;0
"Building";"HighTemplar";NA;302;0
"Building";"HighTemplar";NA;302;0
"Building";"HighTemplar";NA;302;0
"Building";"HighTemplar";NA;302;0
"Unit";"Zealot";"Gateway";302;2
"Unit";"Zealot";"Gateway";302;2
"Unit";"Phoenix";"Stargate";302;2
"Unit";"Immortal";"Robotics Facility";284;4
"Building";"RoboticsFacility";NA;284;0
"Unit";"Archon";"High Templar";312;0
"Unit";"Archon";"High Templar";312;0
"Unit";"Phoenix";"Stargate";302;2
"Unit";"Zealot";"Gateway";314;2
"Unit";"Zealot";"Gateway";314;2
"Unit";"Zealot";"Gateway";314;2
"Unit";"Zealot";"Gateway";314;2
"Unit";"Zealot";"Gateway";314;2
"Unit";"Zealot";"Gateway";314;2
"Unit";"Zealot";"Gateway";314;2
"Unit";"Zealot";"Gateway";314;2
"Building";"HighTemplar";NA;332;0
"Building";"HighTemplar";NA;332;0
"Building";"HighTemplar";NA;332;0
"Building";"HighTemplar";NA;332;0
"Unit";"Zealot";"Gateway";332;2
"Building";"Pylon";NA;330;0
"Building";"Pylon";NA;330;0
"Building";"RoboticsBay";NA;312;0
"Unit";"Immortal";"Robotics Facility";314;4
"Unit";"Immortal";"Robotics Facility";314;4
"Unit";"Archon";"High Templar";334;0
"Unit";"Archon";"High Templar";334;0
"Unit";"Colossus";"Robotics Facility";334;6
"Unit";"Colossus";"Robotics Facility";342;6
"Building";"Pylon";NA;342;0
"Building";"Pylon";NA;342;0
"Building";"Assimilator";NA;348;0
"Building";"Assimilator";NA;348;0
"Building";"HighTemplar";NA;354;0
"Building";"HighTemplar";NA;354;0
"Building";"HighTemplar";NA;354;0
"Building";"HighTemplar";NA;354;0
"Unit";"Zealot";"Gateway";354;2
"Upgrade";"ExtendedThermalLance";"RoboticsBay";342;0
"Unit";"Archon";"High Templar";354;0
"Unit";"Archon";"High Templar";354;0
"Unit";"Colossus";"Robotics Facility";342;6
