"type";"unit_name";"on_building";"total_supply";"supply"
"Building";"Pylon";NA;13;0
"Building";"Assimilator";NA;16;0
"Building";"Gateway";NA;15;0
"Building";"Assimilator";NA;20;0
"Building";"Pylon";NA;21;0
"Building";"CyberneticsCore";NA;20;0
"Unit";"Stalker";"Gateway";22;2
"Building";"Nexus";NA;19;0
"Unit";"Stalker";"Gateway";25;2
"Building";"Pylon";NA;32;0
"Unit";"Stalker";"Gateway";30;2
"Building";"ShieldBattery";NA;36;0
"Building";"ShieldBattery";NA;36;0
"Building";"Gateway";NA;38;0
"Building";"Gateway";NA;38;0
"Building";"Pylon";NA;46;0
"Unit";"Stalker";"Gateway";53;2
"Unit";"Stalker";"Gateway";53;2
"Unit";"Stalker";"Gateway";53;2
"Building";"Assimilator";NA;53;0
"Building";"Nexus";NA;45;0
"Building";"Forge";NA;53;0
"Building";"TwilightCouncil";NA;51;0
"Building";"Forge";NA;53;0
"Unit";"Stalker";"Gateway";65;2
"Unit";"Stalker";"Gateway";65;2
"Unit";"Stalker";"Gateway";66;2
"Building";"Pylon";NA;65;0
"Unit";"Sentry";"Gateway";76;2
"Unit";"Sentry";"Gateway";76;2
"Building";"RoboticsFacility";NA;62;0
"Unit";"Stalker";"Gateway";82;2
"Unit";"Observer";"Robotics Facility";84;1
"Unit";"Stalker";"Gateway";87;2
"Building";"Pylon";NA;87;0
"Unit";"Zealot";"Gateway";90;2
"Unit";"Zealot";"Gateway";90;2
"Building";"Pylon";NA;90;0
"Building";"Gateway";NA;84;0
"Unit";"Stalker";"Gateway";94;2
"Building";"Gateway";NA;84;0
"Unit";"Observer";"Robotics Facility";90;1
"Building";"Gateway";NA;84;0
"Building";"Pylon";NA;94;0
"Building";"Gateway";NA;87;0
"Building";"Gateway";NA;87;0
"Unit";"Zealot";"Gateway";100;2
"Unit";"Zealot";"Gateway";100;2
"Unit";"Zealot";"Gateway";100;2
"Unit";"Zealot";"Gateway";100;2
"Building";"Pylon";NA;97;0
"Upgrade";"ProtossGroundArmorsLevel1";"Forge";80;0
"Building";"Pylon";NA;97;0
"Unit";"Zealot";"Gateway";109;2
"Unit";"Zealot";"Gateway";109;2
"Unit";"Zealot";"Gateway";109;2
"Upgrade";"ProtossGroundWeaponsLevel1";"Forge";84;0
"Building";"Pylon";NA;100;0
"Unit";"Zealot";"Gateway";115;2
"Building";"Pylon";NA;108;0
"Unit";"Immortal";"Robotics Facility";96;4
"Unit";"Stalker";"Gateway";117;2
"Unit";"Stalker";"Gateway";117;2
"Unit";"Stalker";"Gateway";121;2
"Building";"Pylon";NA;115;0
"Unit";"Zealot";"Gateway";127;2
"Unit";"Zealot";"Gateway";127;2
"Unit";"Zealot";"Gateway";127;2
"Unit";"Zealot";"Gateway";129;2
"Building";"Gateway";NA;100;0
"Building";"Gateway";NA;100;0
"Building";"Assimilator";NA;135;0
"Unit";"Zealot";"Gateway";138;2
"Unit";"Zealot";"Gateway";138;2
"Unit";"Zealot";"Gateway";138;2
"Unit";"Zealot";"Gateway";138;2
"Unit";"Zealot";"Gateway";138;2
"Unit";"Zealot";"Gateway";138;2
"Building";"Assimilator";NA;135;0
"Unit";"Zealot";"Gateway";138;2
"Building";"Assimilator";NA;135;0
"Building";"Pylon";NA;138;0
"Building";"Pylon";NA;138;0
"Unit";"Stalker";"Gateway";153;2
"Unit";"Stalker";"Gateway";153;2
"Unit";"Stalker";"Gateway";153;2
"Unit";"Zealot";"Gateway";159;2
"Unit";"Zealot";"Gateway";159;2
"Unit";"Zealot";"Gateway";159;2
"Unit";"Zealot";"Gateway";159;2
"Unit";"Zealot";"Gateway";159;2
"Unit";"Zealot";"Gateway";159;2
"Unit";"Zealot";"Gateway";159;2
"Upgrade";"Charge";"TwilightCouncil";117;0
"Unit";"Zealot";"Gateway";173;2
"Unit";"Zealot";"Gateway";173;2
"Unit";"Zealot";"Gateway";173;2
"Unit";"Zealot";"Gateway";173;2
"Building";"Pylon";NA;173;0
"Upgrade";"ProtossGroundWeaponsLevel2";"Forge";133;0
"Upgrade";"ProtossGroundArmorsLevel2";"Forge";135;0
"Unit";"Zealot";"Gateway";181;2
"Unit";"Zealot";"Gateway";181;2
"Unit";"Zealot";"Gateway";181;2
"Unit";"Zealot";"Gateway";181;2
"Unit";"Zealot";"Gateway";181;2
"Unit";"Zealot";"Gateway";181;2
"Unit";"Zealot";"Gateway";181;2
"Unit";"Zealot";"Gateway";181;2
"Unit";"Zealot";"Gateway";181;2
"Unit";"Immortal";"Robotics Facility";173;4
"Building";"RoboticsBay";NA;173;0
"Building";"RoboticsFacility";NA;173;0
"Building";"Nexus";NA;173;0
"Unit";"Zealot";"Gateway";203;2
"Unit";"Zealot";"Gateway";203;2
"Unit";"Zealot";"Gateway";203;2
"Unit";"Zealot";"Gateway";203;2
"Unit";"Zealot";"Gateway";203;2
"Unit";"Zealot";"Gateway";203;2
"Unit";"Zealot";"Gateway";203;2
"Building";"PhotonCannon";NA;203;0
"Building";"PhotonCannon";NA;203;0
"Building";"ShieldBattery";NA;203;0
"Unit";"Colossus";"Robotics Facility";203;6
"Unit";"Stalker";"Gateway";219;2
"Unit";"Stalker";"Gateway";225;2
"Unit";"Stalker";"Gateway";225;2
"Unit";"Stalker";"Gateway";225;2
"Unit";"Sentry";"Gateway";233;2
"Unit";"Zealot";"Gateway";239;2
"Unit";"Zealot";"Gateway";239;2
"Unit";"Zealot";"Gateway";239;2
"Unit";"Zealot";"Gateway";239;2
"Building";"Assimilator";NA;233;0
"Building";"Assimilator";NA;233;0
"Unit";"Stalker";"Gateway";247;2
"Unit";"Stalker";"Gateway";247;2
"Unit";"Stalker";"Gateway";247;2
"Unit";"Stalker";"Gateway";247;2
"Unit";"Stalker";"Gateway";247;2
"Unit";"Colossus";"Robotics Facility";217;6
"Unit";"Stalker";"Gateway";263;2
"Unit";"Stalker";"Gateway";263;2
"Unit";"Stalker";"Gateway";263;2
"Unit";"Colossus";"Robotics Facility";219;6
"Unit";"Zealot";"Gateway";275;2
"Unit";"Zealot";"Gateway";275;2
"Unit";"Zealot";"Gateway";275;2
"Unit";"Zealot";"Gateway";275;2
"Upgrade";"ProtossGroundArmorsLevel3";"Forge";203;0
"Unit";"Zealot";"Gateway";283;2
"Unit";"Zealot";"Gateway";283;2
"Unit";"Zealot";"Gateway";283;2
"Unit";"Zealot";"Gateway";283;2
"Unit";"Zealot";"Gateway";283;2
"Upgrade";"ProtossGroundWeaponsLevel3";"Forge";203;0
"Building";"Stargate";NA;257;0
"Unit";"Zealot";"Gateway";293;2
"Unit";"Zealot";"Gateway";293;2
"Unit";"Zealot";"Gateway";293;2
"Unit";"Zealot";"Gateway";293;2
"Unit";"Zealot";"Gateway";293;2
"Unit";"Zealot";"Gateway";293;2
"Unit";"Zealot";"Gateway";293;2
"Unit";"Zealot";"Gateway";293;2
"Unit";"Zealot";"Gateway";293;2
"Unit";"Zealot";"Gateway";293;2
"Unit";"Colossus";"Robotics Facility";269;6
"Unit";"Immortal";"Robotics Facility";293;4
"Unit";"Zealot";"Gateway";323;2
"Unit";"Zealot";"Gateway";323;2
"Unit";"Zealot";"Gateway";323;2
"Unit";"Zealot";"Gateway";323;2
"Unit";"Zealot";"Gateway";323;2
"Unit";"Zealot";"Gateway";323;2
"Unit";"Zealot";"Gateway";323;2
"Unit";"Zealot";"Gateway";323;2
"Unit";"Zealot";"Gateway";323;2
"Unit";"Zealot";"Gateway";341;2
"Unit";"Immortal";"Robotics Facility";319;4
"Building";"FleetBeacon";NA;319;0
"Upgrade";"ProtossShieldsLevel1";"Forge";293;0
"Unit";"Immortal";"Robotics Facility";319;4
"Upgrade";"GraviticDrive";"RoboticsBay";341;0
