"type";"unit_name";"on_building";"total_supply";"supply"
"Building";"Pylon";NA;14;0
"Building";"Assimilator";NA;16;0
"Building";"Assimilator";NA;16;0
"Building";"Gateway";NA;15;0
"Building";"Assimilator";NA;17;0
"Building";"Pylon";NA;20;0
"Building";"CyberneticsCore";NA;20;0
"Unit";"Adept";"Gateway";22;2
"Unit";"Adept";"Gateway";23;2
"Building";"RoboticsFacility";NA;23;0
"Unit";"Observer";"Robotics Facility";28;1
"Building";"Stargate";NA;26;0
"Building";"Pylon";NA;28;0
"Unit";"Phoenix";"Stargate";31;2
"Unit";"Immortal";"Robotics Facility";30;4
"Building";"Nexus";NA;26;0
"Building";"Pylon";NA;31;0
"Unit";"Phoenix";"Stargate";31;2
"Unit";"Observer";"Robotics Facility";37;1
"Unit";"Observer";"Robotics Facility";45;1
"Unit";"Phoenix";"Stargate";46;2
"Unit";"Observer";"Robotics Facility";51;1
"Building";"Pylon";NA;55;0
"Building";"ShieldBattery";NA;55;0
"Building";"Assimilator";NA;55;0
"Building";"Assimilator";NA;55;0
"Unit";"Phoenix";"Stargate";58;2
"Building";"Nexus";NA;51;0
"Building";"Pylon";NA;62;0
"Building";"Forge";NA;58;0
"Building";"RoboticsFacility";NA;58;0
"Unit";"Immortal";"Robotics Facility";62;4
"Building";"RoboticsBay";NA;62;0
"Building";"Gateway";NA;62;0
"Building";"Gateway";NA;62;0
"Building";"Gateway";NA;62;0
"Building";"Pylon";NA;65;0
"Building";"Pylon";NA;75;0
"Unit";"Colossus";"Robotics Facility";65;6
"Unit";"Colossus";"Robotics Facility";65;6
"Building";"Pylon";NA;76;0
"Unit";"Phoenix";"Stargate";78;2
"Building";"Assimilator";NA;90;0
"Building";"Assimilator";NA;90;0
"Building";"Pylon";NA;95;0
"Unit";"Disruptor";"Robotics Facility";90;3
"Unit";"Disruptor";"Robotics Facility";90;3
"Building";"PhotonCannon";NA;93;0
"Building";"PhotonCannon";NA;94;0
"Building";"PhotonCannon";NA;95;0
"Building";"ShieldBattery";NA;95;0
"Building";"ShieldBattery";NA;95;0
"Upgrade";"ExtendedThermalLance";"RoboticsBay";78;0
"Building";"Pylon";NA;104;0
"Upgrade";"ProtossGroundWeaponsLevel1";"Forge";78;0
"Unit";"Disruptor";"Robotics Facility";106;3
"Unit";"Disruptor";"Robotics Facility";107;3
"Unit";"Zealot";"Gateway";110;2
"Unit";"Zealot";"Gateway";110;2
"Unit";"Zealot";"Gateway";110;2
"Unit";"Zealot";"Gateway";110;2
"Building";"Pylon";NA;110;0
"Building";"Pylon";NA;110;0
"Building";"FleetBeacon";NA;110;0
"Building";"Pylon";NA;124;0
"Unit";"Stalker";"Gateway";124;2
"Unit";"Stalker";"Gateway";124;2
"Unit";"Stalker";"Gateway";124;2
"Unit";"Stalker";"Gateway";124;2
"Building";"Stargate";NA;110;0
"Upgrade";"ProtossAirWeaponsLevel1";"CyberneticsCore";98;0
"Building";"TwilightCouncil";NA;124;0
"Unit";"Phoenix";"Stargate";124;2
"Building";"Nexus";NA;109;0
"Unit";"Phoenix";"Stargate";132;2
"Unit";"Observer";"Robotics Facility";134;1
"Unit";"Observer";"Robotics Facility";134;1
"Building";"Assimilator";NA;134;0
"Building";"Assimilator";NA;136;0
"Building";"PhotonCannon";NA;134;0
"Building";"PhotonCannon";NA;136;0
"Building";"PhotonCannon";NA;137;0
"Building";"PhotonCannon";NA;137;0
"Building";"ShieldBattery";NA;137;0
"Building";"PhotonCannon";NA;138;0
"Building";"ShieldBattery";NA;138;0
"Building";"ShieldBattery";NA;138;0
"Building";"Pylon";NA;138;0
"Building";"Pylon";NA;138;0
"Unit";"Disruptor";"Robotics Facility";138;3
"Unit";"Disruptor";"Robotics Facility";138;3
"Unit";"Phoenix";"Stargate";138;2
"Unit";"Phoenix";"Stargate";138;2
"Building";"PhotonCannon";NA;138;0
"Upgrade";"ProtossAirWeaponsLevel2";"CyberneticsCore";134;0
"Building";"Gateway";NA;138;0
"Building";"Gateway";NA;138;0
"Building";"Gateway";NA;141;0
"Building";"Gateway";NA;144;0
"Unit";"Disruptor";"Robotics Facility";148;3
"Building";"Gateway";NA;144;0
"Unit";"Disruptor";"Robotics Facility";148;3
"Upgrade";"ProtossGroundWeaponsLevel2";"Forge";138;0
"Building";"Stargate";NA;148;0
"Building";"Stargate";NA;148;0
"Unit";"Phoenix";"Stargate";154;2
"Unit";"Phoenix";"Stargate";154;2
"Building";"RoboticsFacility";NA;148;0
"Unit";"Observer";"Robotics Facility";154;1
"Building";"RoboticsFacility";NA;148;0
"Unit";"Observer";"Robotics Facility";154;1
"Unit";"Stalker";"Gateway";160;2
"Unit";"Stalker";"Gateway";160;2
"Unit";"Stalker";"Gateway";160;2
"Unit";"Stalker";"Gateway";160;2
"Unit";"Stalker";"Gateway";160;2
"Unit";"Stalker";"Gateway";160;2
"Unit";"Stalker";"Gateway";160;2
"Unit";"Phoenix";"Stargate";160;2
"Unit";"Phoenix";"Stargate";160;2
"Unit";"Phoenix";"Stargate";160;2
"Unit";"Phoenix";"Stargate";160;2
"Building";"Pylon";NA;182;0
"Building";"Pylon";NA;182;0
"Building";"Pylon";NA;182;0
"Upgrade";"Charge";"TwilightCouncil";160;0
"Unit";"Tempest";"Stargate";182;4
"Unit";"Tempest";"Stargate";182;4
"Unit";"Tempest";"Stargate";182;4
"Upgrade";"ProtossAirWeaponsLevel3";"CyberneticsCore";154;0
"Upgrade";"ProtossGroundWeaponsLevel3";"Forge";160;0
"Unit";"Tempest";"Stargate";182;4
"Unit";"Tempest";"Stargate";194;4
"Unit";"Tempest";"Stargate";194;4
"Building";"Pylon";NA;206;0
"Building";"Pylon";NA;206;0
"Upgrade";"GraviticDrive";"RoboticsBay";206;0
"Building";"Assimilator";NA;206;0
"Building";"Assimilator";NA;206;0
"Upgrade";"ProtossAirArmorsLevel1";"CyberneticsCore";194;0
"Upgrade";"ProtossShieldsLevel1";"Forge";206;0
"Unit";"Stalker";"Gateway";206;2
"Unit";"Stalker";"Gateway";206;2
"Unit";"Stalker";"Gateway";206;2
"Unit";"Stalker";"Gateway";206;2
"Unit";"Stalker";"Gateway";206;2
"Unit";"Stalker";"Gateway";206;2
"Unit";"Stalker";"Gateway";206;2
"Unit";"Stalker";"Gateway";206;2
"Unit";"Stalker";"Gateway";206;2
"Building";"Nexus";NA;206;0
"Unit";"Phoenix";"Stargate";206;2
"Unit";"Phoenix";"Stargate";206;2
"Unit";"Phoenix";"Stargate";206;2
"Unit";"Phoenix";"Stargate";206;2
"Unit";"Disruptor";"Robotics Facility";206;3
"Unit";"Disruptor";"Robotics Facility";206;3
"Unit";"Zealot";"Gateway";232;2
"Unit";"Zealot";"Gateway";232;2
"Unit";"Disruptor";"Robotics Facility";206;3
"Unit";"Zealot";"Gateway";232;2
"Unit";"Zealot";"Gateway";232;2
"Unit";"Disruptor";"Robotics Facility";206;3
"Unit";"Zealot";"Gateway";232;2
"Unit";"Zealot";"Gateway";232;2
"Unit";"Zealot";"Gateway";232;2
"Unit";"Zealot";"Gateway";232;2
"Unit";"Zealot";"Gateway";232;2
"Unit";"Stalker";"Gateway";262;2
"Unit";"Stalker";"Gateway";262;2
"Unit";"Stalker";"Gateway";262;2
"Unit";"Stalker";"Gateway";262;2
"Unit";"Stalker";"Gateway";262;2
"Unit";"Stalker";"Gateway";262;2
"Unit";"Stalker";"Gateway";262;2
"Unit";"Stalker";"Gateway";262;2
"Unit";"Stalker";"Gateway";262;2
"Unit";"Observer";"Robotics Facility";280;1
"Unit";"Phoenix";"Stargate";280;2
"Unit";"Phoenix";"Stargate";280;2
"Unit";"Phoenix";"Stargate";280;2
"Unit";"Phoenix";"Stargate";280;2
"Upgrade";"ProtossAirArmorsLevel2";"CyberneticsCore";262;0
"Upgrade";"ProtossShieldsLevel2";"Forge";262;0
"Building";"PhotonCannon";NA;289;0
"Building";"PhotonCannon";NA;289;0
"Building";"Pylon";NA;289;0
"Building";"PhotonCannon";NA;289;0
"Building";"Pylon";NA;289;0
"Building";"Assimilator";NA;289;0
"Building";"Assimilator";NA;289;0
"Building";"Nexus";NA;289;0
"Unit";"Stalker";"Gateway";289;2
"Unit";"Stalker";"Gateway";289;2
"Unit";"Stalker";"Gateway";289;2
"Unit";"Stalker";"Gateway";289;2
"Unit";"Stalker";"Gateway";289;2
"Unit";"Stalker";"Gateway";289;2
"Unit";"Stalker";"Gateway";289;2
"Unit";"Stalker";"Gateway";289;2
"Unit";"Stalker";"Gateway";289;2
"Unit";"Disruptor";"Robotics Facility";289;3
"Unit";"Disruptor";"Robotics Facility";289;3
"Unit";"Disruptor";"Robotics Facility";289;3
"Unit";"Disruptor";"Robotics Facility";289;3
"Unit";"Phoenix";"Stargate";289;2
"Unit";"Phoenix";"Stargate";289;2
"Unit";"Phoenix";"Stargate";289;2
"Unit";"Phoenix";"Stargate";289;2
"Building";"PhotonCannon";NA;307;0
"Building";"PhotonCannon";NA;319;0
"Unit";"Phoenix";"Stargate";327;2
"Unit";"Phoenix";"Stargate";327;2
"Unit";"Phoenix";"Stargate";327;2
"Unit";"Phoenix";"Stargate";327;2
"Building";"PhotonCannon";NA;327;0
"Building";"PhotonCannon";NA;327;0
"Building";"ShieldBattery";NA;327;0
"Building";"ShieldBattery";NA;327;0
"Unit";"Phoenix";"Stargate";335;2
"Unit";"Phoenix";"Stargate";335;2
"Unit";"Phoenix";"Stargate";335;2
"Unit";"Phoenix";"Stargate";335;2
"Unit";"Disruptor";"Robotics Facility";335;3
"Unit";"Disruptor";"Robotics Facility";335;3
"Unit";"Disruptor";"Robotics Facility";335;3
"Unit";"Disruptor";"Robotics Facility";335;3
"Unit";"Stalker";"Gateway";355;2
"Unit";"Stalker";"Gateway";355;2
"Unit";"Stalker";"Gateway";355;2
"Unit";"Stalker";"Gateway";355;2
"Unit";"Stalker";"Gateway";355;2
"Unit";"Stalker";"Gateway";355;2
"Unit";"Stalker";"Gateway";355;2
"Unit";"Stalker";"Gateway";355;2
"Unit";"Stalker";"Gateway";355;2
"Upgrade";"ProtossAirArmorsLevel3";"CyberneticsCore";327;0
"Upgrade";"ProtossShieldsLevel3";"Forge";327;0
"Unit";"Colossus";"Robotics Facility";355;6
"Unit";"Colossus";"Robotics Facility";355;6
"Unit";"Colossus";"Robotics Facility";355;6
"Unit";"Colossus";"Robotics Facility";355;6
"Building";"Pylon";NA;373;0
"Building";"Pylon";NA;373;0
"Building";"Assimilator";NA;373;0
"Building";"Assimilator";NA;397;0
