"type";"unit_name";"on_building";"total_supply";"supply"
"Building";"Pylon";NA;13;0
"Building";"Assimilator";NA;15;0
"Building";"Pylon";NA;17;0
"Building";"Gateway";NA;15;0
"Unit";"Zealot";"Gateway";19;2
"Building";"CyberneticsCore";NA;19;0
"Unit";"Stalker";"Gateway";22;2
"Building";"Assimilator";NA;22;0
"Building";"Pylon";NA;23;0
"Unit";"Stalker";"Gateway";23;2
"Building";"Nexus";NA;22;0
"Building";"ShieldBattery";NA;26;0
"Unit";"Stalker";"Gateway";27;2
