"type";"unit_name";"on_building";"total_supply_lag";"supply"
"Building";"Pylon";NA;14;0
"Building";"Gateway";NA;16;0
"Building";"Assimilator";NA;17;0
"Building";"Assimilator";NA;18;0
"Building";"CyberneticsCore";NA;20;0
"Building";"Pylon";NA;22;0
"Building";"Nexus";NA;23;0
"Building";"Stargate";NA;23;0
"Unit";"Adept";"Gateway";23;2
"Building";"Pylon";NA;27;0
"Unit";"Adept";"Gateway";27;2
"Unit";"Oracle";"Stargate";30;3
"Unit";"Adept";"Gateway";35;2
"Unit";"Oracle";"Stargate";40;3
"Building";"Pylon";NA;46;0
"Building";"Gateway";NA;50;0
"Building";"Gateway";NA;50;0
"Building";"Assimilator";NA;54;0
"Building";"Assimilator";NA;54;0
"Building";"Pylon";NA;57;0
"Building";"TwilightCouncil";NA;57;0
"Building";"Forge";NA;57;0
"Building";"Nexus";NA;57;0
"Unit";"Sentry";"Gateway";59;2
"Unit";"Stalker";"Gateway";61;2
"Unit";"Stalker";"Gateway";63;2
"Building";"Pylon";NA;65;0
"Building";"Gateway";NA;65;0
"Building";"Pylon";NA;65;0
"Building";"Gateway";NA;65;0
"Building";"RoboticsFacility";NA;68;0
"Upgrade";"ProtossGroundWeaponsLevel1";"Forge";69;0
"Unit";"Stalker";"Gateway";69;2
"Unit";"Phoenix";"Stargate";74;2
"Unit";"Observer";"Robotics Facility";80;1
"Unit";"Stalker";"Gateway";84;2
"Unit";"Sentry";"Gateway";89;2
"Unit";"Sentry";"Gateway";91;2
"Unit";"Sentry";"Gateway";93;2
"Unit";"Observer";"Robotics Facility";96;1
"Unit";"Stalker";"Gateway";98;2
"Unit";"Stalker";"Gateway";100;2
"Building";"Gateway";NA;109;0
"Unit";"Adept";"Gateway";109;2
"Unit";"Immortal";"Robotics Facility";111;4
"Unit";"Adept";"Gateway";121;2
"Unit";"Adept";"Gateway";123;2
"Unit";"Adept";"Gateway";125;2
"Unit";"Adept";"Gateway";127;2
"Building";"RoboticsBay";NA;132;0
"Building";"Pylon";NA;132;0
"Building";"Pylon";NA;132;0
"Building";"PhotonCannon";NA;132;0
"Building";"Pylon";NA;132;0
"Building";"Pylon";NA;132;0
"Building";"Pylon";NA;132;0
"Unit";"Stalker";"Gateway";134;2
"Unit";"Stalker";"Gateway";136;2
"Unit";"Stalker";"Gateway";138;2
"Unit";"Stalker";"Gateway";140;2
"Unit";"Colossus";"Robotics Facility";146;6
"Unit";"Stalker";"Gateway";154;2
"Unit";"Stalker";"Gateway";156;2
"Unit";"Stalker";"Gateway";158;2
"Unit";"Stalker";"Gateway";160;2
"Unit";"Stalker";"Gateway";163;2
"Building";"Assimilator";NA;166;0
"Building";"Assimilator";NA;166;0
"Upgrade";"ExtendedThermalLance";"RoboticsBay";166;0
"Building";"Gateway";NA;166;0
"Unit";"Adept";"Gateway";166;2
"Unit";"Adept";"Gateway";168;2
"Building";"Gateway";NA;170;0
"Unit";"Colossus";"Robotics Facility";170;6
"Unit";"Stalker";"Gateway";176;2
"Unit";"Stalker";"Gateway";178;2
"Building";"Nexus";NA;180;0
"Building";"Pylon";NA;180;0
"Building";"Pylon";NA;180;0
"Building";"Pylon";NA;180;0
"Building";"Pylon";NA;180;0
"Unit";"Adept";"Gateway";180;2
"Unit";"Adept";"Gateway";182;2
"Unit";"Adept";"Gateway";184;2
"Unit";"Adept";"Gateway";186;2
"Unit";"Adept";"Gateway";188;2
"Unit";"Adept";"Gateway";190;2
"Unit";"Observer";"Robotics Facility";192;1
"Unit";"Stalker";"Gateway";193;2
"Unit";"Stalker";"Gateway";195;2
"Unit";"Stalker";"Gateway";197;2
"Unit";"Stalker";"Gateway";199;2
"Unit";"Stalker";"Gateway";201;2
"Unit";"Stalker";"Gateway";203;2
"Unit";"Stalker";"Gateway";205;2
"Unit";"Stalker";"Gateway";207;2
"Unit";"Stalker";"Gateway";209;2
"Unit";"Stalker";"Gateway";211;2
"Unit";"Stalker";"Gateway";213;2
"Unit";"Stalker";"Gateway";215;2
"Unit";"Stalker";"Gateway";217;2
"Unit";"Stalker";"Gateway";219;2
"Unit";"Stalker";"Gateway";221;2
"Unit";"Stalker";"Gateway";223;2
"Unit";"Colossus";"Robotics Facility";225;6
"Building";"Pylon";NA;231;0
"Building";"Pylon";NA;231;0
"Unit";"Adept";"Gateway";231;2
"Unit";"Adept";"Gateway";233;2
"Unit";"Adept";"Gateway";235;2
"Unit";"Adept";"Gateway";237;2
"Unit";"Adept";"Gateway";239;2
"Unit";"Adept";"Gateway";241;2
"Upgrade";"Charge";"TwilightCouncil";243;0
"Building";"FleetBeacon";NA;246;0
"Unit";"Adept";"Gateway";246;2
"Unit";"Adept";"Gateway";248;2
"Unit";"Adept";"Gateway";250;2
"Unit";"Adept";"Gateway";252;2
"Unit";"Adept";"Gateway";254;2
"Unit";"Adept";"Gateway";256;2
"Unit";"Adept";"Gateway";258;2
"Unit";"Adept";"Gateway";260;2
"Unit";"Colossus";"Robotics Facility";262;6
"Building";"Stargate";NA;268;0
"Building";"PhotonCannon";NA;268;0
"Building";"PhotonCannon";NA;270;0
"Unit";"Tempest";"Stargate";274;4
"Unit";"Colossus";"Robotics Facility";278;6
"Unit";"Tempest";"Stargate";285;4
"Unit";"Stalker";"Gateway";297;2
"Unit";"Stalker";"Gateway";299;2
"Unit";"Stalker";"Gateway";301;2
"Unit";"Stalker";"Gateway";303;2
"Building";"Assimilator";NA;307;0
"Building";"Assimilator";NA;307;0
"Unit";"Disruptor";"Robotics Facility";307;3
"Unit";"Tempest";"Stargate";310;4
"Unit";"Stalker";"Gateway";314;2
"Unit";"Stalker";"Gateway";316;2
"Unit";"Stalker";"Gateway";318;2
"Unit";"Stalker";"Gateway";320;2
"Unit";"Stalker";"Gateway";322;2
"Unit";"Stalker";"Gateway";324;2
"Building";"Nexus";NA;326;0
"Unit";"Zealot";"Gateway";326;2
"Unit";"Zealot";"Gateway";328;2
"Unit";"Zealot";"Gateway";330;2
"Unit";"Zealot";"Gateway";332;2
"Building";"Gateway";NA;334;0
"Building";"Gateway";NA;334;0
"Building";"Gateway";NA;334;0
"Unit";"Oracle";"Stargate";334;3
"Building";"Pylon";NA;337;0
"Unit";"Disruptor";"Robotics Facility";337;3
"Unit";"Tempest";"Stargate";340;4
"Building";"Pylon";NA;344;0
"Building";"Pylon";NA;344;0
"Unit";"Stalker";"Gateway";344;2
"Unit";"Stalker";"Gateway";346;2
"Unit";"Stalker";"Gateway";348;2
"Unit";"Stalker";"Gateway";350;2
"Unit";"Stalker";"Gateway";352;2
"Unit";"Stalker";"Gateway";354;2
"Unit";"Stalker";"Gateway";356;2
"Unit";"Stalker";"Gateway";358;2
"Unit";"Disruptor";"Robotics Facility";360;3
"Unit";"Stalker";"Gateway";363;2
"Unit";"Stalker";"Gateway";365;2
"Unit";"Stalker";"Gateway";367;2
"Unit";"Stalker";"Gateway";369;2
"Unit";"Stalker";"Gateway";371;2
"Unit";"Stalker";"Gateway";373;2
"Unit";"Stalker";"Gateway";375;2
"Unit";"Stalker";"Gateway";377;2
"Building";"RoboticsFacility";NA;379;0
"Unit";"Zealot";"Gateway";379;2
"Unit";"Zealot";"Gateway";381;2
"Unit";"Zealot";"Gateway";383;2
"Unit";"Zealot";"Gateway";385;2
"Unit";"Zealot";"Gateway";387;2
"Unit";"Zealot";"Gateway";389;2
"Unit";"Zealot";"Gateway";391;2
"Unit";"Zealot";"Gateway";393;2
"Unit";"Zealot";"Gateway";395;2
"Unit";"Zealot";"Gateway";397;2
"Unit";"Zealot";"Gateway";399;2
"Unit";"Colossus";"Robotics Facility";401;6
"Unit";"Zealot";"Gateway";407;2
"Unit";"Zealot";"Gateway";409;2
"Unit";"Zealot";"Gateway";411;2
"Unit";"Zealot";"Gateway";413;2
"Unit";"Zealot";"Gateway";415;2
"Unit";"Zealot";"Gateway";417;2
"Unit";"Zealot";"Gateway";419;2
"Unit";"Zealot";"Gateway";421;2
"Unit";"Zealot";"Gateway";423;2
"Unit";"Zealot";"Gateway";425;2
"Unit";"Zealot";"Gateway";427;2
"Unit";"Zealot";"Gateway";429;2
"Unit";"Zealot";"Gateway";431;2
"Unit";"Zealot";"Gateway";433;2
"Unit";"Zealot";"Gateway";435;2
"Unit";"Zealot";"Gateway";437;2
"Unit";"Zealot";"Gateway";439;2
"Unit";"Zealot";"Gateway";441;2
"Unit";"Zealot";"Gateway";443;2
"Unit";"Zealot";"Gateway";445;2
"Unit";"Zealot";"Gateway";447;2
"Unit";"Zealot";"Gateway";449;2
"Unit";"Colossus";"Robotics Facility";451;6
"Unit";"Sentry";"Gateway";457;2
"Unit";"Sentry";"Gateway";459;2
"Unit";"Stalker";"Gateway";461;2
"Unit";"Stalker";"Gateway";463;2
"Unit";"Stalker";"Gateway";465;2
"Unit";"Stalker";"Gateway";467;2
"Unit";"Stalker";"Gateway";469;2
"Building";"RoboticsFacility";NA;471;0
"Building";"TemplarArchive";NA;471;0
"Unit";"Stalker";"Gateway";471;2
"Unit";"Stalker";"Gateway";473;2
"Unit";"Stalker";"Gateway";475;2
"Upgrade";"ProtossGroundWeaponsLevel2";"Forge";477;0
"Unit";"Oracle";"Stargate";477;3
"Unit";"Observer";"Robotics Facility";480;1
"Unit";"Colossus";"Robotics Facility";481;6
"Unit";"Adept";"Gateway";487;2
"Unit";"Adept";"Gateway";489;2
"Unit";"Adept";"Gateway";491;2
"Building";"HighTemplar";NA;493;0
"Building";"HighTemplar";NA;493;0
"Unit";"Tempest";"Stargate";493;4
"Unit";"Archon";"High Templar";497;0
"Unit";"Stalker";"Gateway";497;2
"Unit";"Stalker";"Gateway";499;2
"Unit";"Stalker";"Gateway";501;2
"Unit";"Stalker";"Gateway";503;2
"Unit";"Stalker";"Gateway";505;2
"Unit";"Tempest";"Stargate";507;4
"Building";"HighTemplar";NA;511;0
"Building";"HighTemplar";NA;511;0
"Unit";"Archon";"High Templar";511;0
"Unit";"Zealot";"Gateway";511;2
"Unit";"Zealot";"Gateway";513;2
"Unit";"Zealot";"Gateway";515;2
"Unit";"Zealot";"Gateway";517;2
"Unit";"Zealot";"Gateway";519;2
"Building";"Assimilator";NA;521;0
"Unit";"Tempest";"Stargate";521;4
"Unit";"Stalker";"Gateway";525;2
"Unit";"Stalker";"Gateway";527;2
"Unit";"Stalker";"Gateway";529;2
"Unit";"Stalker";"Gateway";531;2
"Unit";"Stalker";"Gateway";533;2
"Unit";"Stalker";"Gateway";535;2
"Unit";"Stalker";"Gateway";537;2
"Unit";"Stalker";"Gateway";539;2
"Unit";"Stalker";"Gateway";541;2
"Unit";"Zealot";"Gateway";543;2
"Unit";"Zealot";"Gateway";545;2
"Unit";"Zealot";"Gateway";547;2
"Unit";"Zealot";"Gateway";549;2
"Unit";"Zealot";"Gateway";551;2
"Unit";"Zealot";"Gateway";553;2
"Unit";"Zealot";"Gateway";555;2
"Unit";"Zealot";"Gateway";557;2
"Unit";"Zealot";"Gateway";559;2
"Unit";"Zealot";"Gateway";561;2
"Unit";"Zealot";"Gateway";563;2
"Unit";"Disruptor";"Robotics Facility";565;3
"Unit";"Disruptor";"Robotics Facility";568;3
"Unit";"Zealot";"Gateway";571;2
"Unit";"Zealot";"Gateway";573;2
"Unit";"Zealot";"Gateway";575;2
"Unit";"Zealot";"Gateway";577;2
"Building";"HighTemplar";NA;579;0
"Building";"HighTemplar";NA;579;0
"Unit";"Zealot";"Gateway";579;2
"Building";"HighTemplar";NA;581;0
"Building";"HighTemplar";NA;581;0
"Unit";"Zealot";"Gateway";581;2
"Unit";"Zealot";"Gateway";583;2
"Unit";"Zealot";"Gateway";585;2
"Unit";"Archon";"High Templar";587;0
"Unit";"Phoenix";"Stargate";587;2
"Unit";"Zealot";"Gateway";589;2
"Unit";"Zealot";"Gateway";591;2
"Upgrade";"SprayProtoss";NA;593;0
"Upgrade";"SprayProtoss";NA;593;0
"Upgrade";"WarpGateResearch";NA;593;0
"Upgrade";"SprayProtoss";NA;593;0
"Upgrade";"SprayProtoss";NA;593;0
"Upgrade";"BlinkTech";NA;593;0
"Upgrade";"AdeptPiercingAttack";NA;593;0
"Upgrade";"ProtossGroundArmorsLevel1";NA;593;0
"Upgrade";"SprayProtoss";NA;593;0
"Upgrade";"SprayProtoss";NA;593;0
"Upgrade";"ProtossGroundArmorsLevel2";NA;593;0
"Upgrade";"SprayProtoss";NA;593;0
"Upgrade";"SprayProtoss";NA;593;0
