"type";"unit_name";"on_building";"total_supply_lag";"supply"
"Unit";"Overlord";"Larva";13;0
"Building";"SpawningPool";NA;17;0
"Building";"Hatchery";NA;19;0
"Building";"Extractor";NA;19;0
"Unit";"Queen";"Hatchery";20;2
"Unit";"Zergling";"Larva";22;1
"Unit";"Zergling";"Larva";23;1
"Unit";"Zergling";"Larva";24;1
"Unit";"Zergling";"Larva";25;1
"Unit";"Zergling";"Larva";26;1
"Unit";"Zergling";"Larva";27;1
"Unit";"Overlord";"Larva";28;0
"Unit";"Queen";"Hatchery";28;2
"Unit";"Queen";"Hatchery";32;2
"Building";"EvolutionChamber";NA;42;0
"Building";"CreepTumorQueen";NA;42;0
"Building";"RoachWarren";NA;42;0
"Unit";"Overlord";"Larva";43;0
"Building";"SpineCrawler";NA;43;0
"Building";"EvolutionChamber";NA;43;0
"Unit";"Queen";"Hatchery";43;2
"Building";"Extractor";NA;51;0
"Building";"Extractor";NA;51;0
"Building";"CreepTumor";NA;51;0
"Unit";"Overlord";"Larva";53;0
"Upgrade";"GlialReconstitution";"RoachWarren";56;0
"Building";"CreepTumor";NA;56;0
"Unit";"Overlord";"Larva";64;0
"Unit";"Overlord";"Larva";64;0
"Unit";"Overlord";"Larva";64;0
"Building";"CreepTumor";NA;64;0
"Unit";"Roach";"Larva";64;2
"Unit";"Roach";"Larva";66;2
"Unit";"Roach";"Larva";68;2
"Unit";"Roach";"Larva";70;2
"Unit";"Roach";"Larva";72;2
"Unit";"Roach";"Larva";74;2
"Unit";"Roach";"Larva";76;2
"Unit";"Roach";"Larva";78;2
"Unit";"Overlord";"Larva";80;0
"Unit";"Overlord";"Larva";80;0
"Unit";"Roach";"Larva";80;2
"Unit";"Roach";"Larva";82;2
"Unit";"Roach";"Larva";84;2
"Unit";"Roach";"Larva";86;2
"Unit";"Roach";"Larva";88;2
"Unit";"Roach";"Larva";90;2
"Unit";"Roach";"Larva";92;2
"Unit";"Overlord";"Larva";94;0
"Unit";"Overlord";"Larva";94;0
"Building";"Extractor";NA;94;0
"Building";"Hatchery";NA;94;0
"Unit";"Roach";"Larva";94;2
"Unit";"Roach";"Larva";96;2
"Unit";"Roach";"Larva";98;2
"Unit";"Roach";"Larva";100;2
"Unit";"Roach";"Larva";102;2
"Unit";"Roach";"Larva";104;2
"Upgrade";"Burrow";"Hatchery";108;0
"Upgrade";"TunnelingClaws";"RoachWarren";108;0
"Building";"CreepTumorQueen";NA;108;0
"Unit";"Overlord";"Larva";108;0
"Unit";"Overlord";"Larva";108;0
"Unit";"Roach";"Larva";108;2
"Unit";"Roach";"Larva";110;2
"Building";"CreepTumorQueen";NA;112;0
"Building";"CreepTumorQueen";NA;112;0
"Unit";"Roach";"Larva";112;2
"Unit";"Overlord";"Larva";114;0
"Unit";"Overlord";"Larva";114;0
"Building";"CreepTumor";NA;114;0
"Unit";"Roach";"Larva";114;2
"Unit";"Roach";"Larva";116;2
"Unit";"Roach";"Larva";118;2
"Unit";"Roach";"Larva";120;2
"Unit";"Roach";"Larva";122;2
"Unit";"Roach";"Larva";124;2
"Unit";"Roach";"Larva";126;2
"Unit";"Roach";"Larva";128;2
"Unit";"Roach";"Larva";130;2
"Unit";"Roach";"Larva";132;2
"Unit";"Roach";"Larva";134;2
"Unit";"Roach";"Larva";136;2
"Unit";"Roach";"Larva";138;2
"Unit";"Roach";"Larva";140;2
"Unit";"Roach";"Larva";142;2
"Unit";"Roach";"Larva";144;2
"Unit";"Roach";"Larva";146;2
"Unit";"Roach";"Larva";148;2
"Unit";"Roach";"Larva";150;2
"Building";"CreepTumor";NA;152;0
"Unit";"Roach";"Larva";156;2
"Unit";"Roach";"Larva";158;2
"Unit";"Roach";"Larva";160;2
"Unit";"Roach";"Larva";162;2
"Unit";"Roach";"Larva";164;2
"Unit";"Roach";"Larva";166;2
"Unit";"Roach";"Larva";168;2
"Unit";"Roach";"Larva";170;2
"Unit";"Queen";"Hatchery";172;2
"Building";"Spire";NA;174;0
"Building";"Hatchery";NA;174;0
"Unit";"Roach";"Larva";174;2
"Unit";"Roach";"Larva";176;2
"Unit";"Roach";"Larva";178;2
"Unit";"Roach";"Larva";180;2
"Unit";"Roach";"Larva";182;2
"Unit";"Roach";"Larva";184;2
"Unit";"Roach";"Larva";186;2
"Unit";"Roach";"Larva";188;2
"Unit";"Roach";"Larva";190;2
"Unit";"Mutalisk";"Larva";192;2
"Unit";"Mutalisk";"Larva";194;2
"Unit";"Mutalisk";"Larva";196;2
"Unit";"Mutalisk";"Larva";198;2
"Unit";"Mutalisk";"Larva";200;2
"Unit";"Mutalisk";"Larva";202;2
"Unit";"Mutalisk";"Larva";204;2
"Unit";"Mutalisk";"Larva";206;2
"Unit";"Mutalisk";"Larva";208;2
"Unit";"Overlord";"Larva";210;0
"Unit";"Overlord";"Larva";210;0
"Unit";"Mutalisk";"Larva";210;2
"Unit";"Mutalisk";"Larva";212;2
"Unit";"Mutalisk";"Larva";214;2
"Building";"Extractor";NA;219;0
"Unit";"Mutalisk";"Larva";219;2
"Unit";"Mutalisk";"Larva";221;2
"Building";"CreepTumor";NA;223;0
"Unit";"Roach";"Larva";223;2
"Unit";"Roach";"Larva";225;2
"Unit";"Roach";"Larva";227;2
"Unit";"Roach";"Larva";229;2
"Unit";"Roach";"Larva";231;2
"Unit";"Roach";"Larva";233;2
"Unit";"Roach";"Larva";235;2
"Unit";"Roach";"Larva";237;2
"Unit";"Roach";"Larva";239;2
"Unit";"Roach";"Larva";241;2
"Unit";"Roach";"Larva";243;2
"Unit";"Roach";"Larva";245;2
"Unit";"Roach";"Larva";247;2
"Unit";"Queen";"Hatchery";260;2
"Building";"HydraliskDen";NA;273;0
"Building";"Hatchery";NA;273;0
"Building";"Extractor";NA;273;0
"Unit";"Roach";"Larva";273;2
"Unit";"Roach";"Larva";275;2
"Unit";"Roach";"Larva";277;2
"Unit";"Roach";"Larva";279;2
"Unit";"Roach";"Larva";281;2
"Unit";"Roach";"Larva";283;2
"Unit";"Roach";"Larva";285;2
"Unit";"Roach";"Larva";287;2
"Unit";"Roach";"Larva";289;2
"Unit";"Roach";"Larva";291;2
"Building";"CreepTumor";NA;293;0
"Building";"CreepTumor";NA;293;0
"Building";"CreepTumor";NA;293;0
"Unit";"Queen";"Hatchery";293;2
"Unit";"Hydralisk";"Larva";295;2
"Unit";"Hydralisk";"Larva";297;2
"Unit";"Hydralisk";"Larva";299;2
"Unit";"Hydralisk";"Larva";301;2
"Unit";"Hydralisk";"Larva";303;2
"Unit";"Hydralisk";"Larva";305;2
"Unit";"Hydralisk";"Larva";307;2
"Unit";"Hydralisk";"Larva";309;2
"Unit";"Hydralisk";"Larva";311;2
"Unit";"Overlord";"Larva";314;0
"Unit";"Overlord";"Larva";314;0
"Unit";"Overlord";"Larva";314;0
"Unit";"Overlord";"Larva";314;0
"Unit";"Overlord";"Larva";314;0
"Unit";"Overlord";"Larva";314;0
"Unit";"Overlord";"Larva";314;0
"Upgrade";"SprayZerg";NA;314;0
"Upgrade";"SprayZerg";NA;314;0
"Upgrade";"ZergMissileWeaponsLevel1";NA;314;0
"Upgrade";"SprayZerg";NA;314;0
"Upgrade";"SprayZerg";NA;314;0
"Upgrade";"ZergMissileWeaponsLevel2";NA;314;0
"Upgrade";"SprayZerg";NA;314;0
"Upgrade";"SprayZerg";NA;314;0
"Upgrade";"ZergFlyerWeaponsLevel1";NA;314;0
"Upgrade";"ZergGroundArmorsLevel1";NA;314;0
"Upgrade";"SprayZerg";NA;314;0
"Upgrade";"SprayZerg";NA;314;0
"Upgrade";"overlordspeed";NA;314;0
