"type";"unit_name";"on_building";"total_supply";"supply"
"Unit";"Overlord";"Larva";12;0
"Building";"Extractor";NA;18;0
"Building";"SpawningPool";NA;19;0
"Unit";"Overlord";"Larva";22;0
"Building";"Hatchery";NA;17;0
"Unit";"Zergling";"Larva";25;1
"Unit";"Zergling";"Larva";25;1
"Unit";"Zergling";"Larva";25;1
"Unit";"Zergling";"Larva";25;1
"Unit";"Queen";"Hatchery";22;2
"Unit";"Queen";"Hatchery";22;2
"Unit";"Overlord";"Larva";35;0
"Unit";"Zergling";"Larva";35;1
"Unit";"Zergling";"Larva";35;1
"Unit";"Queen";"Hatchery";33;2
"Building";"CreepTumorQueen";NA;40;0
"Unit";"Overlord";"Larva";36;0
"Building";"Hatchery";NA;25;0
"Building";"SporeCrawler";NA;44;0
"Unit";"Overlord";"Larva";54;0
"Unit";"Queen";"Hatchery";49;2
"Building";"Extractor";NA;55;0
"Building";"CreepTumor";NA;58;0
"Unit";"Overlord";"Larva";58;0
"Unit";"Zergling";"Larva";58;1
"Unit";"Zergling";"Larva";58;1
"Unit";"Zergling";"Larva";58;1
"Unit";"Zergling";"Larva";58;1
"Unit";"Zergling";"Larva";58;1
"Unit";"Zergling";"Larva";58;1
"Unit";"Zergling";"Larva";60;1
"Unit";"Zergling";"Larva";60;1
"Unit";"Zergling";"Larva";60;1
"Unit";"Zergling";"Larva";60;1
"Unit";"Zergling";"Larva";60;1
"Unit";"Zergling";"Larva";60;1
"Unit";"Zergling";"Larva";60;1
"Unit";"Zergling";"Larva";60;1
"Unit";"Zergling";"Larva";60;1
"Unit";"Zergling";"Larva";60;1
"Unit";"Overlord";"Larva";60;0
"Unit";"Overlord";"Larva";60;0
"Building";"EvolutionChamber";NA;60;0
"Building";"SporeCrawler";NA;62;0
"Building";"RoachWarren";NA;60;0
"Building";"CreepTumor";NA;82;0
"Unit";"Overlord";"Larva";83;0
"Building";"CreepTumorQueen";NA;88;0
"Building";"CreepTumorQueen";NA;88;0
"Unit";"Roach";"Larva";88;2
"Unit";"Roach";"Larva";88;2
"Unit";"Roach";"Larva";88;2
"Unit";"Roach";"Larva";88;2
"Unit";"Roach";"Larva";88;2
"Building";"Extractor";NA;88;0
"Building";"Extractor";NA;88;0
"Building";"CreepTumorQueen";NA;98;0
"Unit";"Overlord";"Larva";104;0
"Unit";"Overlord";"Larva";104;0
"Unit";"Overlord";"Larva";104;0
"Unit";"Overlord";"Larva";104;0
"Unit";"Overlord";"Larva";104;0
"Unit";"Overlord";"Larva";106;0
"Unit";"Overlord";"Larva";106;0
"Building";"BanelingNest";NA;98;0
"Unit";"Roach";"Larva";106;2
"Unit";"Roach";"Larva";106;2
"Unit";"Roach";"Larva";106;2
"Unit";"Roach";"Larva";106;2
"Unit";"Roach";"Larva";106;2
"Unit";"Roach";"Larva";106;2
"Unit";"Roach";"Larva";106;2
"Unit";"Roach";"Larva";106;2
"Unit";"Roach";"Larva";106;2
"Unit";"Overlord";"Larva";106;0
"Unit";"Overlord";"Larva";106;0
"Building";"Extractor";NA;124;0
"Building";"Extractor";NA;124;0
"Unit";"Overlord";"Larva";124;0
"Unit";"Overlord";"Larva";124;0
"Upgrade";"ZergMissileWeaponsLevel1";"EvolutionChamber";101;0
"Building";"CreepTumor";NA;133;0
"Unit";"Queen";"Hatchery";124;2
"Building";"CreepTumor";NA;133;0
"Building";"CreepTumorQueen";NA;133;0
"Building";"CreepTumor";NA;133;0
"Building";"CreepTumorQueen";NA;133;0
"Building";"CreepTumorQueen";NA;139;0
"Unit";"Overlord";"Larva";139;0
"Unit";"Roach";"Larva";139;2
"Unit";"Roach";"Larva";139;2
"Unit";"Roach";"Larva";139;2
"Unit";"Roach";"Larva";139;2
"Building";"CreepTumor";NA;141;0
"Building";"CreepTumor";NA;141;0
"Unit";"Roach";"Larva";149;2
"Unit";"Roach";"Larva";149;2
"Unit";"Roach";"Larva";149;2
"Unit";"Roach";"Larva";149;2
"Unit";"Roach";"Larva";149;2
"Unit";"Roach";"Larva";149;2
"Unit";"Roach";"Larva";149;2
"Unit";"Roach";"Larva";149;2
"Unit";"Roach";"Larva";149;2
"Unit";"Roach";"Larva";149;2
"Unit";"Roach";"Larva";149;2
"Unit";"Overlord";"Larva";149;0
"Unit";"Zergling";"Larva";149;1
"Unit";"Zergling";"Larva";149;1
"Unit";"Zergling";"Larva";149;1
"Unit";"Zergling";"Larva";149;1
"Upgrade";"GlialReconstitution";"RoachWarren";133;0
"Unit";"Baneling";"Zergling";149;0
"Unit";"Baneling";"Zergling";149;0
"Unit";"Baneling";"Zergling";149;0
"Unit";"Baneling";"Zergling";149;0
"Unit";"Baneling";"Zergling";149;0
"Unit";"Baneling";"Zergling";149;0
"Unit";"Baneling";"Zergling";149;0
"Unit";"Baneling";"Zergling";149;0
"Unit";"Baneling";"Zergling";149;0
"Unit";"Baneling";"Zergling";149;0
"Unit";"Baneling";"Zergling";149;0
"Unit";"Baneling";"Zergling";149;0
"Unit";"Baneling";"Zergling";149;0
"Unit";"Zergling";"Larva";171;1
"Unit";"Zergling";"Larva";171;1
"Unit";"Zergling";"Larva";171;1
"Unit";"Zergling";"Larva";171;1
"Unit";"Zergling";"Larva";171;1
"Unit";"Zergling";"Larva";171;1
"Unit";"Zergling";"Larva";171;1
"Unit";"Zergling";"Larva";171;1
"Unit";"Zergling";"Larva";171;1
"Unit";"Zergling";"Larva";171;1
"Unit";"Zergling";"Larva";171;1
"Unit";"Zergling";"Larva";171;1
"Unit";"Zergling";"Larva";175;1
"Unit";"Zergling";"Larva";175;1
"Unit";"Zergling";"Larva";175;1
"Unit";"Zergling";"Larva";175;1
"Unit";"Zergling";"Larva";175;1
"Unit";"Zergling";"Larva";175;1
"Unit";"Zergling";"Larva";175;1
"Unit";"Zergling";"Larva";175;1
"Unit";"Zergling";"Larva";175;1
"Unit";"Zergling";"Larva";175;1
"Unit";"Zergling";"Larva";175;1
"Unit";"Zergling";"Larva";175;1
"Unit";"Zergling";"Larva";175;1
"Unit";"Zergling";"Larva";175;1
"Unit";"Zergling";"Larva";175;1
"Unit";"Zergling";"Larva";175;1
"Unit";"Roach";"Larva";187;2
"Unit";"Roach";"Larva";187;2
"Unit";"Roach";"Larva";187;2
"Unit";"Roach";"Larva";203;2
"Unit";"Roach";"Larva";203;2
"Unit";"Roach";"Larva";203;2
"Unit";"Roach";"Larva";203;2
"Unit";"Roach";"Larva";203;2
"Unit";"Roach";"Larva";203;2
"Building";"Hatchery";NA;151;0
"Unit";"Roach";"Larva";209;2
"Unit";"Roach";"Larva";209;2
"Unit";"Roach";"Larva";209;2
"Unit";"Baneling";"Zergling";209;0
"Unit";"Baneling";"Zergling";209;0
"Unit";"Baneling";"Zergling";209;0
"Unit";"Baneling";"Zergling";209;0
"Unit";"Baneling";"Zergling";209;0
"Unit";"Baneling";"Zergling";209;0
"Unit";"Baneling";"Zergling";209;0
"Unit";"Baneling";"Zergling";209;0
"Unit";"Baneling";"Zergling";209;0
"Unit";"Baneling";"Zergling";209;0
"Unit";"Baneling";"Zergling";209;0
"Unit";"Baneling";"Zergling";209;0
"Unit";"Baneling";"Zergling";209;0
"Unit";"Baneling";"Zergling";209;0
"Unit";"Baneling";"Zergling";209;0
"Unit";"Baneling";"Zergling";209;0
"Building";"CreepTumor";NA;221;0
"Unit";"Roach";"Larva";221;2
"Unit";"Roach";"Larva";221;2
"Unit";"Roach";"Larva";221;2
"Building";"CreepTumorQueen";NA;221;0
"Building";"CreepTumorQueen";NA;227;0
"Building";"CreepTumorQueen";NA;227;0
"Unit";"Roach";"Larva";221;2
"Unit";"Roach";"Larva";221;2
"Unit";"Roach";"Larva";221;2
"Unit";"Roach";"Larva";221;2
"Upgrade";"ZergMissileWeaponsLevel2";"EvolutionChamber";149;0
"Unit";"Zergling";"Larva";227;1
"Unit";"Zergling";"Larva";227;1
"Unit";"Zergling";"Larva";227;1
"Unit";"Zergling";"Larva";227;1
"Unit";"Zergling";"Larva";227;1
"Unit";"Zergling";"Larva";227;1
"Unit";"Zergling";"Larva";227;1
"Unit";"Zergling";"Larva";227;1
"Unit";"Zergling";"Larva";227;1
"Unit";"Zergling";"Larva";227;1
"Unit";"Zergling";"Larva";227;1
"Unit";"Zergling";"Larva";227;1
"Unit";"Zergling";"Larva";227;1
"Unit";"Zergling";"Larva";227;1
