"type";"unit_name";"on_building";"total_supply";"supply"
"Unit";"Overlord";"Larva";12;0
"Building";"Extractor";NA;17;0
"Unit";"Overlord";"Larva";21;0
"Building";"SpawningPool";NA;19;0
"Building";"Hatchery";NA;17;0
"Unit";"Zergling";"Larva";23;1
"Unit";"Zergling";"Larva";23;1
"Unit";"Zergling";"Larva";23;1
"Unit";"Zergling";"Larva";23;1
"Unit";"Queen";"Hatchery";23;2
"Unit";"Queen";"Hatchery";23;2
"Unit";"Overlord";"Larva";37;0
"Unit";"Overlord";"Larva";37;0
"Unit";"Zergling";"Larva";40;1
"Unit";"Zergling";"Larva";40;1
"Unit";"Overlord";"Larva";47;0
"Building";"EvolutionChamber";NA;41;0
"Building";"CreepTumorQueen";NA;51;0
"Building";"Hatchery";NA;36;0
"Unit";"Overlord";"Larva";51;0
"Unit";"Overlord";"Larva";51;0
"Unit";"Zergling";"Larva";51;1
"Unit";"Zergling";"Larva";51;1
"Unit";"Queen";"Hatchery";49;2
"Unit";"Zergling";"Larva";51;1
"Unit";"Zergling";"Larva";51;1
"Unit";"Queen";"Hatchery";51;2
"Unit";"Zergling";"Larva";51;1
"Unit";"Zergling";"Larva";51;1
"Unit";"Zergling";"Larva";51;1
"Unit";"Zergling";"Larva";51;1
"Unit";"Zergling";"Larva";51;1
"Unit";"Zergling";"Larva";51;1
"Building";"CreepTumorQueen";NA;58;0
"Building";"CreepTumor";NA;60;0
"Building";"SporeCrawler";NA;51;0
"Building";"SporeCrawler";NA;57;0
"Unit";"Zergling";"Larva";69;1
"Unit";"Zergling";"Larva";69;1
"Unit";"Zergling";"Larva";69;1
"Unit";"Zergling";"Larva";69;1
"Unit";"Zergling";"Larva";69;1
"Unit";"Zergling";"Larva";69;1
"Unit";"Zergling";"Larva";69;1
"Unit";"Zergling";"Larva";69;1
"Unit";"Zergling";"Larva";69;1
"Unit";"Zergling";"Larva";69;1
"Unit";"Zergling";"Larva";70;1
"Unit";"Zergling";"Larva";70;1
"Unit";"Zergling";"Larva";70;1
"Unit";"Zergling";"Larva";70;1
"Building";"SporeCrawler";NA;70;0
"Unit";"Zergling";"Larva";81;1
"Unit";"Zergling";"Larva";81;1
"Unit";"Zergling";"Larva";81;1
"Unit";"Zergling";"Larva";81;1
"Unit";"Zergling";"Larva";86;1
"Unit";"Zergling";"Larva";86;1
"Unit";"Zergling";"Larva";86;1
"Unit";"Zergling";"Larva";86;1
"Unit";"Zergling";"Larva";86;1
"Unit";"Zergling";"Larva";86;1
"Unit";"Zergling";"Larva";86;1
"Unit";"Zergling";"Larva";86;1
"Unit";"Zergling";"Larva";86;1
"Unit";"Zergling";"Larva";86;1
"Unit";"Overlord";"Larva";86;0
"Unit";"Zergling";"Larva";90;1
"Unit";"Zergling";"Larva";90;1
"Unit";"Zergling";"Larva";90;1
"Unit";"Zergling";"Larva";90;1
"Unit";"Zergling";"Larva";90;1
"Unit";"Zergling";"Larva";90;1
"Unit";"Zergling";"Larva";92;1
"Unit";"Zergling";"Larva";92;1
"Unit";"Zergling";"Larva";92;1
"Unit";"Zergling";"Larva";92;1
"Unit";"Zergling";"Larva";94;1
"Unit";"Zergling";"Larva";94;1
"Unit";"Zergling";"Larva";94;1
"Unit";"Zergling";"Larva";94;1
"Unit";"Zergling";"Larva";94;1
"Unit";"Zergling";"Larva";94;1
"Building";"CreepTumor";NA;100;0
"Building";"CreepTumorQueen";NA;100;0
"Building";"Extractor";NA;100;0
"Building";"Extractor";NA;100;0
"Building";"CreepTumor";NA;116;0
"Building";"RoachWarren";NA;86;0
"Unit";"Overlord";"Larva";116;0
"Unit";"Overlord";"Larva";116;0
"Upgrade";"ZergMeleeWeaponsLevel1";"EvolutionChamber";70;0
"Unit";"Overlord";"Larva";119;0
"Unit";"Zergling";"Larva";120;1
"Unit";"Zergling";"Larva";120;1
"Unit";"Zergling";"Larva";120;1
"Unit";"Zergling";"Larva";120;1
"Unit";"Zergling";"Larva";120;1
"Unit";"Zergling";"Larva";120;1
"Unit";"Zergling";"Larva";120;1
"Unit";"Zergling";"Larva";120;1
"Unit";"Zergling";"Larva";120;1
"Unit";"Zergling";"Larva";120;1
"Unit";"Zergling";"Larva";120;1
"Unit";"Zergling";"Larva";120;1
"Unit";"Zergling";"Larva";120;1
"Unit";"Zergling";"Larva";120;1
"Unit";"Zergling";"Larva";120;1
"Unit";"Zergling";"Larva";120;1
"Unit";"Zergling";"Larva";120;1
"Unit";"Zergling";"Larva";120;1
"Unit";"Zergling";"Larva";120;1
"Unit";"Zergling";"Larva";120;1
"Unit";"Zergling";"Larva";120;1
"Unit";"Zergling";"Larva";120;1
"Unit";"Zergling";"Larva";120;1
"Unit";"Zergling";"Larva";120;1
"Unit";"Zergling";"Larva";120;1
"Unit";"Zergling";"Larva";120;1
"Unit";"Zergling";"Larva";120;1
"Unit";"Zergling";"Larva";120;1
"Unit";"Zergling";"Larva";120;1
"Unit";"Zergling";"Larva";120;1
"Building";"CreepTumor";NA;144;0
"Building";"CreepTumorQueen";NA;144;0
"Building";"CreepTumor";NA;144;0
"Building";"CreepTumorQueen";NA;144;0
"Building";"CreepTumorQueen";NA;144;0
"Building";"CreepTumor";NA;154;0
"Building";"CreepTumor";NA;159;0
"Building";"CreepTumor";NA;159;0
"Building";"CreepTumor";NA;159;0
"Building";"CreepTumor";NA;159;0
"Building";"CreepTumor";NA;159;0
"Unit";"Overlord";"Larva";159;0
"Unit";"Overlord";"Larva";159;0
"Building";"Extractor";NA;159;0
"Building";"HydraliskDen";NA;159;0
"Unit";"Zergling";"Larva";160;1
"Unit";"Zergling";"Larva";160;1
"Unit";"Zergling";"Larva";160;1
"Unit";"Zergling";"Larva";160;1
"Unit";"Zergling";"Larva";160;1
"Unit";"Zergling";"Larva";160;1
"Unit";"Zergling";"Larva";160;1
"Unit";"Zergling";"Larva";160;1
"Unit";"Zergling";"Larva";160;1
"Unit";"Zergling";"Larva";160;1
"Unit";"Zergling";"Larva";160;1
"Unit";"Zergling";"Larva";160;1
"Unit";"Zergling";"Larva";160;1
"Unit";"Zergling";"Larva";160;1
"Unit";"Zergling";"Larva";160;1
"Unit";"Zergling";"Larva";160;1
"Building";"CreepTumor";NA;164;0
"Building";"BanelingNest";NA;159;0
"Unit";"Hydralisk";"Larva";180;2
"Unit";"Hydralisk";"Larva";180;2
"Unit";"Hydralisk";"Larva";180;2
"Unit";"Hydralisk";"Larva";180;2
"Unit";"Hydralisk";"Larva";180;2
"Unit";"Hydralisk";"Larva";180;2
"Unit";"Hydralisk";"Larva";180;2
"Building";"Hatchery";NA;159;0
"Unit";"Zergling";"Larva";181;1
"Unit";"Zergling";"Larva";181;1
"Unit";"Zergling";"Larva";181;1
"Unit";"Zergling";"Larva";181;1
"Unit";"Zergling";"Larva";181;1
"Unit";"Zergling";"Larva";181;1
"Unit";"Zergling";"Larva";181;1
"Unit";"Zergling";"Larva";181;1
"Unit";"Zergling";"Larva";181;1
"Unit";"Zergling";"Larva";181;1
"Unit";"Zergling";"Larva";181;1
"Unit";"Zergling";"Larva";181;1
"Unit";"Zergling";"Larva";181;1
"Unit";"Zergling";"Larva";181;1
"Building";"CreepTumor";NA;195;0
"Building";"CreepTumor";NA;195;0
"Building";"CreepTumor";NA;195;0
"Building";"CreepTumor";NA;195;0
"Building";"CreepTumor";NA;195;0
"Building";"Extractor";NA;195;0
"Upgrade";"ZergMissileWeaponsLevel1";"EvolutionChamber";159;0
"Building";"Extractor";NA;195;0
"Unit";"Zergling";"Larva";197;1
"Unit";"Zergling";"Larva";197;1
"Unit";"Hydralisk";"Larva";195;2
"Unit";"Hydralisk";"Larva";195;2
"Unit";"Hydralisk";"Larva";195;2
"Unit";"Hydralisk";"Larva";195;2
"Unit";"Hydralisk";"Larva";195;2
"Unit";"Baneling";"Zergling";211;0
"Unit";"Baneling";"Zergling";211;0
"Unit";"Baneling";"Zergling";211;0
"Unit";"Baneling";"Zergling";211;0
"Unit";"Baneling";"Zergling";211;0
"Unit";"Baneling";"Zergling";211;0
"Unit";"Baneling";"Zergling";211;0
"Unit";"Baneling";"Zergling";211;0
"Unit";"Baneling";"Zergling";211;0
"Unit";"Baneling";"Zergling";211;0
"Upgrade";"EvolveMuscularAugments";"HydraliskDen";181;0
"Unit";"Zergling";"Larva";227;1
"Unit";"Zergling";"Larva";227;1
"Unit";"Zergling";"Larva";227;1
"Unit";"Zergling";"Larva";227;1
"Building";"CreepTumor";NA;233;0
"Unit";"Hydralisk";"Larva";227;2
"Building";"CreepTumor";NA;233;0
"Unit";"Overlord";"Larva";233;0
"Unit";"Hydralisk";"Larva";227;2
"Unit";"Hydralisk";"Larva";228;2
