"type";"unit_name";"on_building";"total_supply";"supply"
"Unit";"Overlord";"Larva";13;0
"Building";"Extractor";NA;18;0
"Unit";"Overlord";"Larva";21;0
"Building";"SpawningPool";NA;19;0
"Building";"Hatchery";NA;17;0
"Unit";"Zergling";"Larva";23;1
"Unit";"Zergling";"Larva";23;1
"Unit";"Queen";"Hatchery";22;2
"Unit";"Queen";"Hatchery";26;2
"Unit";"Overlord";"Larva";33;0
"Unit";"Zergling";"Larva";33;1
"Unit";"Zergling";"Larva";33;1
"Unit";"Zergling";"Larva";33;1
"Unit";"Zergling";"Larva";33;1
"Building";"CreepTumorQueen";NA;35;0
"Unit";"Queen";"Hatchery";29;2
"Unit";"Overlord";"Larva";35;0
"Building";"CreepTumor";NA;46;0
"Building";"SporeCrawler";NA;43;0
"Building";"SporeCrawler";NA;43;0
"Building";"CreepTumorQueen";NA;48;0
"Unit";"Overlord";"Larva";48;0
"Building";"Hatchery";NA;33;0
"Building";"CreepTumor";NA;52;0
"Building";"CreepTumor";NA;53;0
"Unit";"Queen";"Hatchery";49;2
"Building";"CreepTumorQueen";NA;57;0
"Building";"CreepTumor";NA;64;0
"Building";"Extractor";NA;57;0
"Building";"Extractor";NA;57;0
"Building";"CreepTumor";NA;64;0
"Building";"SporeCrawler";NA;63;0
"Unit";"Overlord";"Larva";67;0
"Building";"CreepTumor";NA;70;0
"Building";"CreepTumorQueen";NA;72;0
"Unit";"Overlord";"Larva";69;0
"Building";"Extractor";NA;70;0
"Unit";"Overlord";"Larva";73;0
"Building";"CreepTumor";NA;80;0
"Building";"CreepTumor";NA;80;0
"Building";"CreepTumor";NA;81;0
"Building";"CreepTumor";NA;81;0
"Unit";"Zergling";"Larva";80;1
"Unit";"Zergling";"Larva";80;1
"Unit";"Zergling";"Larva";80;1
"Unit";"Zergling";"Larva";80;1
"Building";"HydraliskDen";NA;74;0
"Unit";"Zergling";"Larva";81;1
"Unit";"Zergling";"Larva";81;1
"Unit";"Zergling";"Larva";81;1
"Unit";"Zergling";"Larva";81;1
"Unit";"Zergling";"Larva";81;1
"Unit";"Zergling";"Larva";81;1
"Unit";"Overlord";"Larva";86;0
"Unit";"Overlord";"Larva";86;0
"Building";"CreepTumorQueen";NA;94;0
"Building";"CreepTumor";NA;96;0
"Building";"CreepTumor";NA;96;0
"Building";"CreepTumor";NA;96;0
"Building";"CreepTumor";NA;96;0
"Unit";"Hydralisk";"Larva";96;2
"Unit";"Hydralisk";"Larva";96;2
"Unit";"Hydralisk";"Larva";96;2
"Unit";"Hydralisk";"Larva";96;2
"Building";"Extractor";NA;96;0
"Unit";"Overlord";"Larva";96;0
"Building";"CreepTumorQueen";NA;112;0
"Building";"CreepTumor";NA;112;0
"Building";"CreepTumor";NA;112;0
"Building";"CreepTumor";NA;112;0
"Building";"CreepTumorQueen";NA;120;0
"Unit";"Hydralisk";"Larva";112;2
"Unit";"Hydralisk";"Larva";112;2
"Unit";"Hydralisk";"Larva";112;2
"Unit";"Hydralisk";"Larva";112;2
"Building";"BanelingNest";NA;110;0
"Upgrade";"EvolveMuscularAugments";"HydraliskDen";96;0
"Unit";"Hydralisk";"Larva";120;2
"Unit";"Hydralisk";"Larva";120;2
"Unit";"Overlord";"Larva";120;0
"Unit";"Hydralisk";"Larva";120;2
"Unit";"Hydralisk";"Larva";128;2
"Unit";"Hydralisk";"Larva";128;2
"Unit";"Hydralisk";"Larva";128;2
"Unit";"Hydralisk";"Larva";128;2
"Building";"Hatchery";NA;103;0
"Building";"CreepTumor";NA;134;0
"Unit";"Overlord";"Larva";134;0
"Unit";"Overlord";"Larva";134;0
"Unit";"Overlord";"Larva";134;0
"Unit";"Queen";"Hatchery";124;2
"Unit";"Overlord";"Larva";134;0
"Building";"CreepTumor";NA;134;0
"Building";"CreepTumor";NA;134;0
"Building";"CreepTumorQueen";NA;142;0
"Building";"CreepTumor";NA;142;0
"Unit";"Zergling";"Larva";144;1
"Unit";"Zergling";"Larva";144;1
"Unit";"Zergling";"Larva";144;1
"Unit";"Zergling";"Larva";144;1
"Unit";"Zergling";"Larva";144;1
"Unit";"Zergling";"Larva";144;1
"Unit";"Hydralisk";"Larva";144;2
"Unit";"Hydralisk";"Larva";144;2
"Unit";"Hydralisk";"Larva";144;2
"Unit";"Hydralisk";"Larva";144;2
"Unit";"Hydralisk";"Larva";144;2
"Unit";"Hydralisk";"Larva";144;2
"Building";"CreepTumorQueen";NA;148;0
"Unit";"Zergling";"Larva";148;1
"Unit";"Zergling";"Larva";148;1
"Unit";"Zergling";"Larva";148;1
"Unit";"Zergling";"Larva";148;1
"Unit";"Zergling";"Larva";148;1
"Unit";"Zergling";"Larva";148;1
"Unit";"Zergling";"Larva";148;1
"Unit";"Zergling";"Larva";148;1
"Unit";"Zergling";"Larva";148;1
"Unit";"Zergling";"Larva";148;1
"Building";"CreepTumor";NA;148;0
"Building";"CreepTumor";NA;148;0
"Building";"CreepTumor";NA;148;0
"Unit";"Zergling";"Larva";148;1
"Unit";"Zergling";"Larva";148;1
"Unit";"Zergling";"Larva";148;1
"Unit";"Zergling";"Larva";148;1
"Unit";"Zergling";"Larva";176;1
"Unit";"Zergling";"Larva";176;1
"Unit";"Zergling";"Larva";176;1
"Unit";"Zergling";"Larva";176;1
"Unit";"Zergling";"Larva";176;1
"Unit";"Zergling";"Larva";176;1
"Unit";"Zergling";"Larva";176;1
"Unit";"Zergling";"Larva";176;1
"Unit";"Zergling";"Larva";176;1
"Unit";"Zergling";"Larva";176;1
"Unit";"Zergling";"Larva";176;1
"Unit";"Zergling";"Larva";176;1
"Unit";"Zergling";"Larva";176;1
"Unit";"Zergling";"Larva";176;1
"Unit";"Zergling";"Larva";176;1
"Unit";"Zergling";"Larva";176;1
"Unit";"Zergling";"Larva";176;1
"Unit";"Zergling";"Larva";176;1
"Unit";"Zergling";"Larva";176;1
"Unit";"Zergling";"Larva";176;1
"Unit";"Zergling";"Larva";176;1
"Unit";"Zergling";"Larva";176;1
"Unit";"Zergling";"Larva";176;1
"Unit";"Zergling";"Larva";176;1
"Unit";"Zergling";"Larva";176;1
"Unit";"Zergling";"Larva";176;1
"Building";"CreepTumor";NA;180;0
"Building";"CreepTumor";NA;180;0
"Upgrade";"EvolveGroovedSpines";"HydraliskDen";144;0
"Building";"CreepTumorQueen";NA;180;0
"Building";"CreepTumor";NA;180;0
"Unit";"Overlord";"Larva";180;0
"Unit";"Overlord";"Larva";180;0
"Unit";"Overlord";"Larva";180;0
"Unit";"Overlord";"Larva";180;0
"Unit";"Hydralisk";"Larva";180;2
"Unit";"Overlord";"Larva";206;0
"Unit";"Baneling";"Zergling";206;0
"Unit";"Baneling";"Zergling";206;0
"Unit";"Baneling";"Zergling";206;0
"Unit";"Baneling";"Zergling";206;0
"Unit";"Baneling";"Zergling";206;0
"Unit";"Baneling";"Zergling";206;0
"Unit";"Baneling";"Zergling";206;0
"Unit";"Baneling";"Zergling";206;0
"Unit";"Baneling";"Zergling";206;0
"Unit";"Baneling";"Zergling";206;0
"Unit";"Baneling";"Zergling";206;0
"Unit";"Baneling";"Zergling";206;0
"Unit";"Baneling";"Zergling";206;0
"Unit";"Baneling";"Zergling";206;0
"Building";"Extractor";NA;206;0
"Building";"CreepTumor";NA;206;0
"Building";"CreepTumor";NA;206;0
"Building";"EvolutionChamber";NA;206;0
"Building";"CreepTumor";NA;211;0
"Building";"CreepTumor";NA;211;0
"Unit";"Overlord";"Larva";211;0
"Building";"Extractor";NA;208;0
"Building";"Extractor";NA;211;0
"Building";"CreepTumor";NA;220;0
"Building";"CreepTumor";NA;220;0
"Building";"CreepTumorQueen";NA;220;0
"Unit";"Hydralisk";"Larva";220;2
"Unit";"Hydralisk";"Larva";220;2
"Unit";"Hydralisk";"Larva";220;2
"Unit";"Hydralisk";"Larva";220;2
"Unit";"Hydralisk";"Larva";220;2
"Unit";"Hydralisk";"Larva";220;2
"Unit";"Hydralisk";"Larva";220;2
"Unit";"Hydralisk";"Larva";220;2
"Unit";"Hydralisk";"Larva";220;2
"Unit";"Zergling";"Larva";220;1
"Unit";"Zergling";"Larva";220;1
"Unit";"Zergling";"Larva";220;1
"Unit";"Zergling";"Larva";220;1
"Unit";"Zergling";"Larva";220;1
"Unit";"Zergling";"Larva";220;1
"Unit";"Zergling";"Larva";220;1
"Unit";"Zergling";"Larva";220;1
"Unit";"Zergling";"Larva";220;1
"Unit";"Zergling";"Larva";220;1
"Unit";"Zergling";"Larva";220;1
"Unit";"Zergling";"Larva";220;1
"Building";"CreepTumor";NA;220;0
"Building";"CreepTumor";NA;220;0
"Building";"SpineCrawler";NA;220;0
"Building";"LurkerDenMP";NA;206;0
"Building";"CreepTumor";NA;220;0
"Building";"CreepTumor";NA;240;0
"Building";"CreepTumor";NA;250;0
"Building";"CreepTumor";NA;250;0
"Building";"CreepTumorQueen";NA;250;0
"Building";"Hatchery";NA;220;0
"Building";"CreepTumor";NA;256;0
"Unit";"Overlord";"Larva";256;0
"Unit";"Overlord";"Larva";256;0
"Building";"CreepTumor";NA;256;0
"Building";"CreepTumor";NA;256;0
"Unit";"Hydralisk";"Larva";256;2
"Unit";"Hydralisk";"Larva";256;2
"Unit";"Hydralisk";"Larva";256;2
"Building";"InfestationPit";NA;250;0
"Building";"SpineCrawler";NA;256;0
"Unit";"Zergling";"Larva";256;1
"Unit";"Zergling";"Larva";256;1
"Unit";"Zergling";"Larva";256;1
"Unit";"Zergling";"Larva";256;1
"Unit";"Zergling";"Larva";256;1
"Unit";"Zergling";"Larva";256;1
"Unit";"Zergling";"Larva";256;1
"Unit";"Zergling";"Larva";256;1
"Unit";"Zergling";"Larva";256;1
"Unit";"Zergling";"Larva";256;1
"Unit";"Zergling";"Larva";256;1
"Unit";"Zergling";"Larva";256;1
"Unit";"Zergling";"Larva";256;1
"Unit";"Zergling";"Larva";256;1
"Unit";"Zergling";"Larva";256;1
"Unit";"Zergling";"Larva";256;1
"Unit";"Zergling";"Larva";256;1
"Unit";"Zergling";"Larva";256;1
"Unit";"Zergling";"Larva";256;1
"Unit";"Zergling";"Larva";256;1
"Unit";"Zergling";"Larva";256;1
"Unit";"Zergling";"Larva";256;1
"Unit";"Zergling";"Larva";256;1
"Unit";"Zergling";"Larva";256;1
"Unit";"Zergling";"Larva";256;1
"Unit";"Zergling";"Larva";256;1
"Unit";"Zergling";"Larva";256;1
"Unit";"Zergling";"Larva";256;1
"Unit";"Zergling";"Larva";256;1
"Unit";"Zergling";"Larva";256;1
"Upgrade";"ZergMissileWeaponsLevel1";"EvolutionChamber";220;0
"Building";"CreepTumorQueen";NA;262;0
"Unit";"Baneling";"Zergling";292;0
"Unit";"Baneling";"Zergling";292;0
"Unit";"Baneling";"Zergling";292;0
"Unit";"Baneling";"Zergling";292;0
"Unit";"Baneling";"Zergling";292;0
"Unit";"Baneling";"Zergling";292;0
"Unit";"Baneling";"Zergling";292;0
"Unit";"Baneling";"Zergling";292;0
"Unit";"Baneling";"Zergling";292;0
"Unit";"Baneling";"Zergling";292;0
"Unit";"Baneling";"Zergling";292;0
"Unit";"Baneling";"Zergling";292;0
"Unit";"Hydralisk";"Larva";292;2
"Unit";"Hydralisk";"Larva";292;2
"Unit";"Hydralisk";"Larva";292;2
"Unit";"Hydralisk";"Larva";292;2
"Unit";"Hydralisk";"Larva";292;2
"Unit";"Hydralisk";"Larva";292;2
"Unit";"Hydralisk";"Larva";292;2
"Unit";"Hydralisk";"Larva";292;2
"Unit";"Hydralisk";"Larva";292;2
"Unit";"Hydralisk";"Larva";292;2
"Unit";"Hydralisk";"Larva";292;2
"Unit";"Hydralisk";"Larva";292;2
"Unit";"Hydralisk";"Larva";292;2
"Unit";"Hydralisk";"Larva";292;2
"Unit";"Hydralisk";"Larva";292;2
"Building";"CreepTumor";NA;292;0
"Building";"CreepTumor";NA;292;0
"Building";"CreepTumor";NA;292;0
"Building";"CreepTumor";NA;292;0
"Unit";"Hydralisk";"Larva";292;2
"Unit";"Hydralisk";"Larva";292;2
"Unit";"Hydralisk";"Larva";292;2
"Unit";"Hydralisk";"Larva";292;2
"Unit";"Hydralisk";"Larva";292;2
"Unit";"Hydralisk";"Larva";292;2
"Unit";"Hydralisk";"Larva";292;2
"Unit";"Hydralisk";"Larva";292;2
"Unit";"Zergling";"Larva";322;1
"Unit";"Zergling";"Larva";322;1
"Unit";"Zergling";"Larva";322;1
"Unit";"Zergling";"Larva";322;1
"Unit";"Zergling";"Larva";322;1
"Unit";"Zergling";"Larva";322;1
"Unit";"Zergling";"Larva";322;1
"Unit";"Zergling";"Larva";322;1
"Unit";"Zergling";"Larva";322;1
"Unit";"Zergling";"Larva";322;1
"Unit";"Zergling";"Larva";322;1
"Unit";"Zergling";"Larva";322;1
"Unit";"Zergling";"Larva";322;1
"Unit";"Zergling";"Larva";322;1
"Unit";"Zergling";"Larva";322;1
"Unit";"Zergling";"Larva";322;1
"Unit";"Zergling";"Larva";322;1
"Unit";"Zergling";"Larva";322;1
"Unit";"Zergling";"Larva";322;1
"Unit";"Zergling";"Larva";322;1
"Unit";"Zergling";"Larva";322;1
"Unit";"Zergling";"Larva";322;1
"Unit";"Zergling";"Larva";322;1
"Unit";"Zergling";"Larva";322;1
"Unit";"Zergling";"Larva";322;1
"Unit";"Zergling";"Larva";322;1
"Unit";"Zergling";"Larva";322;1
"Unit";"Zergling";"Larva";322;1
"Unit";"Zergling";"Larva";322;1
"Unit";"Zergling";"Larva";322;1
"Unit";"Zergling";"Larva";322;1
"Unit";"Zergling";"Larva";322;1
"Building";"CreepTumorQueen";NA;338;0
"Unit";"Zergling";"Larva";322;1
"Unit";"Zergling";"Larva";322;1
"Unit";"Zergling";"Larva";322;1
"Unit";"Zergling";"Larva";322;1
"Unit";"Zergling";"Larva";322;1
"Unit";"Zergling";"Larva";322;1
"Building";"CreepTumor";NA;338;0
"Unit";"Zergling";"Larva";338;1
"Unit";"Zergling";"Larva";338;1
"Building";"Extractor";NA;338;0
"Unit";"Zergling";"Larva";338;1
"Unit";"Zergling";"Larva";338;1
"Unit";"Zergling";"Larva";338;1
"Unit";"Zergling";"Larva";338;1
"Unit";"Zergling";"Larva";338;1
"Unit";"Zergling";"Larva";338;1
"Unit";"Zergling";"Larva";338;1
"Unit";"Zergling";"Larva";338;1
"Unit";"Zergling";"Larva";338;1
"Unit";"Zergling";"Larva";338;1
"Unit";"Zergling";"Larva";338;1
"Unit";"Zergling";"Larva";338;1
"Unit";"Zergling";"Larva";338;1
"Unit";"Zergling";"Larva";338;1
"Building";"CreepTumor";NA;370;0
"Building";"Extractor";NA;338;0
"Unit";"Zergling";"Larva";370;1
"Unit";"Zergling";"Larva";370;1
"Unit";"Zergling";"Larva";370;1
"Unit";"Zergling";"Larva";370;1
"Unit";"Zergling";"Larva";370;1
"Unit";"Zergling";"Larva";370;1
"Unit";"Zergling";"Larva";376;1
"Unit";"Zergling";"Larva";376;1
"Unit";"Zergling";"Larva";376;1
"Unit";"Zergling";"Larva";376;1
"Unit";"Zergling";"Larva";376;1
"Unit";"Zergling";"Larva";376;1
"Unit";"Zergling";"Larva";378;1
"Unit";"Zergling";"Larva";378;1
"Unit";"Zergling";"Larva";378;1
"Unit";"Zergling";"Larva";378;1
"Unit";"Zergling";"Larva";378;1
"Unit";"Zergling";"Larva";378;1
"Unit";"Zergling";"Larva";378;1
"Unit";"Zergling";"Larva";378;1
"Unit";"Hydralisk";"Larva";412;2
"Unit";"Hydralisk";"Larva";412;2
"Unit";"Hydralisk";"Larva";412;2
"Unit";"Hydralisk";"Larva";412;2
"Unit";"Hydralisk";"Larva";412;2
"Unit";"Hydralisk";"Larva";412;2
"Unit";"Hydralisk";"Larva";412;2
"Unit";"Hydralisk";"Larva";412;2
"Unit";"Hydralisk";"Larva";412;2
"Unit";"Hydralisk";"Larva";412;2
"Unit";"Hydralisk";"Larva";412;2
"Unit";"Zergling";"Larva";412;1
"Unit";"Zergling";"Larva";412;1
"Unit";"Zergling";"Larva";412;1
"Unit";"Zergling";"Larva";412;1
"Unit";"Zergling";"Larva";412;1
"Unit";"Zergling";"Larva";412;1
"Unit";"Zergling";"Larva";412;1
"Unit";"Zergling";"Larva";412;1
"Unit";"Zergling";"Larva";412;1
"Unit";"Zergling";"Larva";412;1
"Unit";"Zergling";"Larva";412;1
"Unit";"Zergling";"Larva";412;1
"Building";"SpineCrawler";NA;412;0
"Building";"SpineCrawler";NA;412;0
"Building";"SpineCrawler";NA;412;0
"Unit";"Zergling";"Larva";446;1
"Unit";"Zergling";"Larva";446;1
"Unit";"Zergling";"Larva";446;1
"Unit";"Zergling";"Larva";446;1
"Unit";"Zergling";"Larva";446;1
"Unit";"Zergling";"Larva";446;1
"Unit";"Zergling";"Larva";446;1
"Unit";"Zergling";"Larva";446;1
"Unit";"Zergling";"Larva";446;1
"Unit";"Zergling";"Larva";446;1
"Unit";"Zergling";"Larva";446;1
"Unit";"Zergling";"Larva";446;1
"Unit";"Zergling";"Larva";446;1
"Unit";"Zergling";"Larva";446;1
"Unit";"Zergling";"Larva";446;1
"Unit";"Zergling";"Larva";446;1
"Unit";"Zergling";"Larva";446;1
"Unit";"Zergling";"Larva";446;1
"Unit";"Zergling";"Larva";446;1
"Unit";"Zergling";"Larva";446;1
"Unit";"Zergling";"Larva";446;1
"Unit";"Zergling";"Larva";446;1
"Unit";"Zergling";"Larva";446;1
"Unit";"Zergling";"Larva";446;1
