"type";"unit_name";"on_building";"total_supply";"supply"
"Building";"Extractor";NA;13;0
"Unit";"Overlord";"Larva";15;0
"Building";"SpawningPool";NA;13;0
"Unit";"Zergling";"Larva";16;1
"Unit";"Zergling";"Larva";16;1
"Unit";"Zergling";"Larva";16;1
"Unit";"Zergling";"Larva";16;1
"Unit";"Zergling";"Larva";16;1
"Unit";"Zergling";"Larva";16;1
"Unit";"Overlord";"Larva";26;0
"Unit";"Queen";"Hatchery";25;2
"Building";"Hatchery";NA;23;0
"Unit";"Queen";"Hatchery";32;2
"Building";"Hatchery";NA;30;0
"Building";"CreepTumorQueen";NA;45;0
"Unit";"Overlord";"Larva";45;0
"Unit";"Zergling";"Larva";45;1
"Unit";"Zergling";"Larva";45;1
"Unit";"Zergling";"Larva";45;1
"Unit";"Zergling";"Larva";45;1
"Unit";"Zergling";"Larva";45;1
"Unit";"Zergling";"Larva";45;1
"Unit";"Overlord";"Larva";45;0
"Unit";"Zergling";"Larva";45;1
"Unit";"Zergling";"Larva";45;1
"Unit";"Zergling";"Larva";45;1
"Unit";"Zergling";"Larva";45;1
"Unit";"Zergling";"Larva";45;1
"Unit";"Zergling";"Larva";45;1
"Unit";"Zergling";"Larva";45;1
"Unit";"Zergling";"Larva";45;1
"Unit";"Zergling";"Larva";46;1
"Unit";"Zergling";"Larva";46;1
"Unit";"Queen";"Hatchery";45;2
"Unit";"Zergling";"Larva";52;1
"Unit";"Zergling";"Larva";52;1
"Unit";"Overlord";"Larva";52;0
"Building";"CreepTumor";NA;60;0
"Unit";"Zergling";"Larva";52;1
"Unit";"Zergling";"Larva";52;1
"Unit";"Queen";"Hatchery";45;2
"Unit";"Zergling";"Larva";52;1
"Unit";"Zergling";"Larva";52;1
"Unit";"Zergling";"Larva";52;1
"Unit";"Zergling";"Larva";52;1
"Building";"Extractor";NA;71;0
"Building";"CreepTumorQueen";NA;87;0
"Unit";"Overlord";"Larva";84;0
"Unit";"Overlord";"Larva";87;0
"Building";"SporeCrawler";NA;93;0
"Building";"Extractor";NA;93;0
"Building";"Extractor";NA;93;0
"Building";"CreepTumorQueen";NA;101;0
"Building";"EvolutionChamber";NA;95;0
"Building";"CreepTumor";NA;101;0
"Building";"CreepTumor";NA;101;0
"Building";"HydraliskDen";NA;95;0
"Building";"CreepTumorQueen";NA;114;0
"Unit";"Overlord";"Larva";113;0
"Building";"Extractor";NA;109;0
"Building";"Extractor";NA;109;0
"Unit";"Overlord";"Larva";114;0
"Unit";"Overlord";"Larva";115;0
"Unit";"Overlord";"Larva";119;0
"Unit";"Overlord";"Larva";119;0
"Building";"CreepTumor";NA;119;0
"Building";"CreepTumor";NA;119;0
"Unit";"Hydralisk";"Larva";119;2
"Building";"CreepTumorQueen";NA;120;0
"Unit";"Hydralisk";"Larva";119;2
"Unit";"Hydralisk";"Larva";119;2
"Unit";"Hydralisk";"Larva";119;2
"Unit";"Hydralisk";"Larva";119;2
"Unit";"Hydralisk";"Larva";119;2
"Unit";"Overlord";"Larva";119;0
"Unit";"Overlord";"Larva";119;0
"Unit";"Hydralisk";"Larva";119;2
"Unit";"Hydralisk";"Larva";119;2
"Building";"CreepTumor";NA;133;0
"Building";"CreepTumor";NA;133;0
"Building";"CreepTumorQueen";NA;133;0
"Unit";"Zergling";"Larva";120;1
"Unit";"Zergling";"Larva";120;1
"Unit";"Hydralisk";"Larva";120;2
"Unit";"Hydralisk";"Larva";120;2
"Unit";"Hydralisk";"Larva";120;2
"Unit";"Hydralisk";"Larva";120;2
"Unit";"Zergling";"Larva";137;1
"Unit";"Zergling";"Larva";137;1
"Upgrade";"EvolveGroovedSpines";"HydraliskDen";119;0
"Building";"CreepTumor";NA;148;0
"Building";"CreepTumor";NA;150;0
"Building";"CreepTumor";NA;150;0
"Building";"CreepTumorQueen";NA;150;0
"Unit";"Hydralisk";"Larva";146;2
"Unit";"Hydralisk";"Larva";146;2
"Unit";"Hydralisk";"Larva";146;2
"Unit";"Hydralisk";"Larva";148;2
"Unit";"Zergling";"Larva";150;1
"Unit";"Zergling";"Larva";150;1
"Unit";"Zergling";"Larva";150;1
"Unit";"Zergling";"Larva";150;1
"Unit";"Hydralisk";"Larva";150;2
"Building";"CreepTumor";NA;156;0
"Building";"CreepTumor";NA;162;0
"Unit";"Hydralisk";"Larva";150;2
"Unit";"Hydralisk";"Larva";152;2
"Unit";"Overlord";"Larva";168;0
"Unit";"Overlord";"Larva";168;0
"Upgrade";"ZergMissileWeaponsLevel1";"EvolutionChamber";120;0
"Unit";"Hydralisk";"Larva";162;2
"Unit";"Hydralisk";"Larva";162;2
"Unit";"Hydralisk";"Larva";166;2
"Building";"Hatchery";NA;138;0
"Building";"Hatchery";NA;146;0
"Building";"CreepTumor";NA;178;0
"Unit";"Zergling";"Larva";178;1
"Unit";"Zergling";"Larva";178;1
"Unit";"Zergling";"Larva";178;1
"Unit";"Zergling";"Larva";178;1
"Unit";"Zergling";"Larva";178;1
"Unit";"Zergling";"Larva";178;1
"Building";"CreepTumor";NA;178;0
"Building";"CreepTumor";NA;178;0
"Unit";"Hydralisk";"Larva";178;2
"Unit";"Hydralisk";"Larva";178;2
"Unit";"Hydralisk";"Larva";178;2
"Unit";"Hydralisk";"Larva";178;2
"Unit";"Hydralisk";"Larva";178;2
"Unit";"Hydralisk";"Larva";178;2
"Unit";"Hydralisk";"Larva";178;2
"Unit";"Hydralisk";"Larva";178;2
"Unit";"Zergling";"Larva";178;1
"Unit";"Zergling";"Larva";178;1
"Unit";"Zergling";"Larva";178;1
"Unit";"Zergling";"Larva";178;1
"Building";"CreepTumorQueen";NA;180;0
"Unit";"Hydralisk";"Larva";178;2
"Upgrade";"EvolveMuscularAugments";"HydraliskDen";168;0
"Building";"Extractor";NA;178;0
"Unit";"Zergling";"Larva";184;1
"Unit";"Zergling";"Larva";184;1
"Unit";"Zergling";"Larva";185;1
"Unit";"Zergling";"Larva";185;1
"Building";"Extractor";NA;178;0
"Unit";"Overlord";"Larva";201;0
"Unit";"Hydralisk";"Larva";180;2
"Unit";"Hydralisk";"Larva";184;2
"Unit";"Hydralisk";"Larva";201;2
"Unit";"Zergling";"Larva";212;1
"Unit";"Zergling";"Larva";212;1
"Unit";"Zergling";"Larva";212;1
"Unit";"Zergling";"Larva";212;1
"Unit";"Hydralisk";"Larva";212;2
"Unit";"Hydralisk";"Larva";218;2
"Unit";"Hydralisk";"Larva";223;2
"Building";"SpineCrawler";NA;212;0
"Building";"LurkerDenMP";NA;172;0
"Unit";"Hydralisk";"Larva";227;2
"Unit";"Hydralisk";"Larva";227;2
"Unit";"Hydralisk";"Larva";227;2
"Unit";"Hydralisk";"Larva";227;2
"Unit";"Hydralisk";"Larva";227;2
"Unit";"Hydralisk";"Larva";227;2
"Unit";"Hydralisk";"Larva";227;2
"Unit";"Hydralisk";"Larva";227;2
"Unit";"Hydralisk";"Larva";227;2
"Unit";"Hydralisk";"Larva";227;2
"Unit";"Hydralisk";"Larva";231;2
"Unit";"Hydralisk";"Larva";231;2
"Unit";"Hydralisk";"Larva";231;2
"Unit";"Hydralisk";"Larva";231;2
"Unit";"Hydralisk";"Larva";231;2
"Unit";"Hydralisk";"Larva";233;2
"Unit";"Hydralisk";"Larva";233;2
"Unit";"Hydralisk";"Larva";233;2
"Unit";"Zergling";"Larva";253;1
"Unit";"Zergling";"Larva";253;1
"Unit";"Zergling";"Larva";253;1
"Unit";"Zergling";"Larva";253;1
"Building";"CreepTumorQueen";NA;257;0
"Building";"CreepTumor";NA;255;0
"Building";"CreepTumor";NA;257;0
"Building";"CreepTumorQueen";NA;265;0
"Unit";"Overlord";"Larva";265;0
"Unit";"Overlord";"Larva";265;0
"Unit";"Hydralisk";"Larva";280;2
"Unit";"Hydralisk";"Larva";280;2
"Building";"CreepTumor";NA;280;0
"Building";"CreepTumor";NA;280;0
"Building";"CreepTumor";NA;280;0
"Unit";"Overlord";"Larva";280;0
"Building";"CreepTumor";NA;282;0
"Unit";"Hydralisk";"Larva";280;2
"Unit";"Hydralisk";"Larva";280;2
"Unit";"Hydralisk";"Larva";280;2
"Building";"CreepTumor";NA;282;0
"Unit";"Zergling";"Larva";282;1
"Unit";"Zergling";"Larva";282;1
"Upgrade";"ZergMissileWeaponsLevel2";"EvolutionChamber";227;0
"Unit";"Overlord";"Larva";284;0
"Unit";"Hydralisk";"Larva";282;2
"Unit";"Overlord";"Larva";284;0
"Building";"CreepTumor";NA;291;0
"Building";"CreepTumor";NA;291;0
"Unit";"Overlord";"Larva";284;0
"Building";"CreepTumor";NA;293;0
"Building";"CreepTumor";NA;293;0
"Building";"CreepTumorQueen";NA;293;0
"Building";"CreepTumor";NA;293;0
"Building";"CreepTumorQueen";NA;295;0
"Unit";"Hydralisk";"Larva";291;2
"Building";"InfestationPit";NA;284;0
"Unit";"Hydralisk";"Larva";293;2
"Unit";"Hydralisk";"Larva";295;2
"Unit";"Hydralisk";"Larva";295;2
"Unit";"Hydralisk";"Larva";295;2
"Unit";"Hydralisk";"Larva";297;2
