"type";"unit_name";"on_building";"total_supply";"supply"
"Unit";"Overlord";"Larva";12;0
"Building";"Extractor";NA;18;0
"Building";"Hatchery";NA;16;0
"Building";"SpawningPool";NA;19;0
"Unit";"Overlord";"Larva";22;0
"Unit";"Zergling";"Larva";23;1
"Unit";"Zergling";"Larva";23;1
"Unit";"Zergling";"Larva";23;1
"Unit";"Zergling";"Larva";23;1
"Unit";"Queen";"Hatchery";23;2
"Unit";"Queen";"Hatchery";23;2
"Unit";"Overlord";"Larva";37;0
"Unit";"Zergling";"Larva";37;1
"Unit";"Zergling";"Larva";37;1
"Unit";"Zergling";"Larva";37;1
"Unit";"Zergling";"Larva";37;1
"Unit";"Overlord";"Larva";37;0
"Building";"CreepTumorQueen";NA;39;0
"Unit";"Queen";"Hatchery";39;2
"Building";"CreepTumor";NA;49;0
"Building";"CreepTumorQueen";NA;51;0
"Building";"Hatchery";NA;37;0
"Building";"SporeCrawler";NA;56;0
"Building";"SporeCrawler";NA;56;0
"Unit";"Queen";"Hatchery";54;2
"Building";"CreepTumor";NA;63;0
"Building";"CreepTumor";NA;63;0
"Unit";"Overlord";"Larva";59;0
"Unit";"Overlord";"Larva";59;0
"Unit";"Overlord";"Larva";63;0
"Building";"CreepTumorQueen";NA;65;0
"Unit";"Overlord";"Larva";65;0
"Unit";"Overlord";"Larva";65;0
"Building";"RoachWarren";NA;63;0
"Building";"CreepTumor";NA;73;0
"Building";"EvolutionChamber";NA;65;0
"Building";"CreepTumorQueen";NA;73;0
"Building";"CreepTumor";NA;73;0
"Building";"CreepTumor";NA;73;0
"Unit";"Overlord";"Larva";76;0
"Unit";"Zergling";"Larva";77;1
"Unit";"Zergling";"Larva";77;1
"Unit";"Zergling";"Larva";77;1
"Unit";"Zergling";"Larva";77;1
"Unit";"Zergling";"Larva";77;1
"Unit";"Zergling";"Larva";77;1
"Building";"Extractor";NA;77;0
"Unit";"Zergling";"Larva";79;1
"Unit";"Zergling";"Larva";79;1
"Unit";"Zergling";"Larva";79;1
"Unit";"Zergling";"Larva";79;1
"Building";"CreepTumorQueen";NA;82;0
"Building";"CreepTumor";NA;82;0
"Building";"CreepTumor";NA;82;0
"Building";"CreepTumor";NA;88;0
"Unit";"Roach";"Larva";82;2
"Unit";"Roach";"Larva";82;2
"Unit";"Roach";"Larva";82;2
"Unit";"Roach";"Larva";98;2
"Unit";"Roach";"Larva";98;2
"Unit";"Roach";"Larva";98;2
"Unit";"Roach";"Larva";98;2
"Building";"Extractor";NA;107;0
"Building";"Extractor";NA;115;0
"Unit";"Zergling";"Larva";123;1
"Unit";"Zergling";"Larva";123;1
"Unit";"Zergling";"Larva";123;1
"Unit";"Zergling";"Larva";123;1
"Unit";"Zergling";"Larva";123;1
"Unit";"Zergling";"Larva";123;1
"Building";"CreepTumor";NA;124;0
"Building";"HydraliskDen";NA;115;0
"Unit";"Zergling";"Larva";123;1
"Unit";"Zergling";"Larva";123;1
"Unit";"Zergling";"Larva";124;1
"Unit";"Zergling";"Larva";124;1
"Unit";"Zergling";"Larva";124;1
"Unit";"Zergling";"Larva";124;1
"Unit";"Zergling";"Larva";124;1
"Unit";"Zergling";"Larva";124;1
"Building";"CreepTumor";NA;124;0
"Building";"CreepTumor";NA;124;0
"Building";"CreepTumor";NA;130;0
"Unit";"Zergling";"Larva";124;1
"Unit";"Zergling";"Larva";124;1
"Unit";"Zergling";"Larva";124;1
"Unit";"Zergling";"Larva";124;1
"Unit";"Zergling";"Larva";124;1
"Unit";"Zergling";"Larva";124;1
"Unit";"Zergling";"Larva";124;1
"Unit";"Zergling";"Larva";124;1
"Unit";"Zergling";"Larva";124;1
"Unit";"Zergling";"Larva";124;1
"Unit";"Roach";"Larva";130;2
"Unit";"Overlord";"Larva";130;0
"Unit";"Roach";"Larva";130;2
"Unit";"Overlord";"Larva";130;0
"Unit";"Roach";"Larva";138;2
"Unit";"Roach";"Larva";148;2
"Unit";"Roach";"Larva";148;2
"Unit";"Roach";"Larva";148;2
"Unit";"Roach";"Larva";148;2
"Upgrade";"ZergMeleeWeaponsLevel1";"EvolutionChamber";107;0
"Unit";"Roach";"Larva";152;2
"Unit";"Roach";"Larva";152;2
"Unit";"Roach";"Larva";152;2
"Unit";"Roach";"Larva";152;2
"Unit";"Roach";"Larva";154;2
"Building";"BanelingNest";NA;138;0
"Building";"Hatchery";NA;138;0
"Building";"CreepTumor";NA;186;0
"Building";"CreepTumor";NA;186;0
"Building";"CreepTumor";NA;186;0
"Building";"CreepTumor";NA;186;0
"Unit";"Zergling";"Larva";186;1
"Unit";"Zergling";"Larva";186;1
"Unit";"Zergling";"Larva";186;1
"Unit";"Zergling";"Larva";186;1
"Unit";"Zergling";"Larva";186;1
"Unit";"Zergling";"Larva";186;1
"Unit";"Zergling";"Larva";186;1
"Unit";"Zergling";"Larva";186;1
"Unit";"Queen";"Hatchery";186;2
"Unit";"Roach";"Larva";186;2
"Unit";"Roach";"Larva";186;2
"Unit";"Queen";"Hatchery";186;2
"Unit";"Roach";"Larva";192;2
"Unit";"Roach";"Larva";192;2
"Unit";"Roach";"Larva";192;2
"Unit";"Roach";"Larva";196;2
"Unit";"Roach";"Larva";196;2
"Unit";"Roach";"Larva";208;2
"Unit";"Roach";"Larva";208;2
"Unit";"Roach";"Larva";208;2
"Unit";"Zergling";"Larva";208;1
"Unit";"Zergling";"Larva";208;1
"Upgrade";"GlialReconstitution";"RoachWarren";186;0
"Building";"CreepTumor";NA;231;0
"Building";"CreepTumor";NA;232;0
"Building";"CreepTumor";NA;234;0
"Building";"CreepTumor";NA;237;0
"Unit";"Queen";"Hatchery";226;2
"Unit";"Hydralisk";"Larva";237;2
"Unit";"Hydralisk";"Larva";237;2
"Unit";"Hydralisk";"Larva";237;2
"Unit";"Hydralisk";"Larva";243;2
"Unit";"Hydralisk";"Larva";243;2
"Unit";"Hydralisk";"Larva";243;2
"Unit";"Hydralisk";"Larva";243;2
"Unit";"Hydralisk";"Larva";245;2
"Unit";"Hydralisk";"Larva";247;2
"Unit";"Hydralisk";"Larva";249;2
"Unit";"Hydralisk";"Larva";249;2
"Unit";"Hydralisk";"Larva";249;2
"Unit";"Hydralisk";"Larva";265;2
"Unit";"Hydralisk";"Larva";265;2
"Unit";"Zergling";"Larva";271;1
"Unit";"Zergling";"Larva";271;1
"Unit";"Zergling";"Larva";271;1
"Unit";"Zergling";"Larva";271;1
"Unit";"Zergling";"Larva";271;1
"Unit";"Zergling";"Larva";271;1
"Unit";"Zergling";"Larva";271;1
"Unit";"Zergling";"Larva";271;1
"Unit";"Zergling";"Larva";271;1
"Unit";"Zergling";"Larva";271;1
"Unit";"Zergling";"Larva";271;1
"Unit";"Zergling";"Larva";271;1
"Unit";"Zergling";"Larva";271;1
"Unit";"Zergling";"Larva";271;1
"Building";"CreepTumor";NA;271;0
"Building";"CreepTumor";NA;271;0
"Unit";"Hydralisk";"Larva";267;2
"Unit";"Hydralisk";"Larva";267;2
"Building";"CreepTumor";NA;271;0
"Building";"CreepTumor";NA;271;0
"Unit";"Overlord";"Larva";271;0
"Unit";"Overlord";"Larva";271;0
"Unit";"Zergling";"Larva";293;1
"Unit";"Zergling";"Larva";293;1
"Unit";"Zergling";"Larva";293;1
"Unit";"Zergling";"Larva";293;1
"Unit";"Hydralisk";"Larva";293;2
"Unit";"Hydralisk";"Larva";293;2
"Unit";"Overlord";"Larva";294;0
"Unit";"Overlord";"Larva";295;0
"Unit";"Hydralisk";"Larva";293;2
"Unit";"Queen";"Hatchery";293;2
"Unit";"Queen";"Hatchery";293;2
"Unit";"Hydralisk";"Larva";301;2
"Unit";"Overlord";"Larva";305;0
"Unit";"Overlord";"Larva";305;0
"Unit";"Hydralisk";"Larva";307;2
"Unit";"Hydralisk";"Larva";307;2
"Unit";"Hydralisk";"Larva";307;2
"Unit";"Hydralisk";"Larva";307;2
"Unit";"Hydralisk";"Larva";307;2
"Unit";"Zergling";"Larva";311;1
"Unit";"Zergling";"Larva";311;1
"Unit";"Zergling";"Larva";311;1
"Unit";"Zergling";"Larva";311;1
"Unit";"Zergling";"Larva";311;1
"Unit";"Zergling";"Larva";311;1
"Unit";"Zergling";"Larva";311;1
"Unit";"Zergling";"Larva";311;1
"Building";"HydraliskDen";NA;311;0
"Building";"CreepTumorQueen";NA;331;0
"Unit";"Zergling";"Larva";331;1
"Unit";"Zergling";"Larva";331;1
"Unit";"Zergling";"Larva";331;1
"Unit";"Zergling";"Larva";331;1
"Unit";"Zergling";"Larva";331;1
"Unit";"Zergling";"Larva";331;1
"Unit";"Zergling";"Larva";331;1
"Unit";"Zergling";"Larva";331;1
"Unit";"Zergling";"Larva";331;1
"Unit";"Zergling";"Larva";331;1
"Unit";"Zergling";"Larva";331;1
"Unit";"Zergling";"Larva";331;1
"Unit";"Zergling";"Larva";331;1
"Unit";"Zergling";"Larva";331;1
"Unit";"Hydralisk";"Larva";331;2
"Unit";"Hydralisk";"Larva";331;2
"Unit";"Hydralisk";"Larva";331;2
"Unit";"Hydralisk";"Larva";331;2
"Unit";"Hydralisk";"Larva";331;2
"Unit";"Hydralisk";"Larva";331;2
"Unit";"Hydralisk";"Larva";331;2
"Upgrade";"ZergMissileWeaponsLevel1";"EvolutionChamber";301;0
"Unit";"Overlord";"Larva";331;0
"Unit";"Overlord";"Larva";331;0
"Building";"CreepTumor";NA;337;0
"Unit";"Overlord";"Larva";345;0
"Unit";"Overlord";"Larva";345;0
"Unit";"Queen";"Hatchery";331;2
"Building";"Extractor";NA;359;0
"Building";"Extractor";NA;359;0
"Building";"CreepTumor";NA;359;0
"Building";"CreepTumorQueen";NA;359;0
"Unit";"Zergling";"Larva";359;1
"Unit";"Zergling";"Larva";359;1
"Unit";"Zergling";"Larva";359;1
"Unit";"Zergling";"Larva";359;1
"Unit";"Zergling";"Larva";359;1
"Unit";"Zergling";"Larva";359;1
"Unit";"Zergling";"Larva";359;1
"Unit";"Zergling";"Larva";359;1
"Unit";"Zergling";"Larva";359;1
"Unit";"Zergling";"Larva";359;1
"Unit";"Zergling";"Larva";359;1
"Unit";"Zergling";"Larva";359;1
"Unit";"Zergling";"Larva";361;1
"Unit";"Zergling";"Larva";361;1
"Unit";"Hydralisk";"Larva";359;2
"Unit";"Hydralisk";"Larva";359;2
"Unit";"Hydralisk";"Larva";359;2
"Unit";"Zergling";"Larva";361;1
"Unit";"Zergling";"Larva";361;1
"Unit";"Zergling";"Larva";361;1
"Unit";"Zergling";"Larva";361;1
"Unit";"Zergling";"Larva";361;1
"Unit";"Zergling";"Larva";361;1
"Building";"Hatchery";NA;331;0
"Unit";"Zergling";"Larva";361;1
"Unit";"Zergling";"Larva";361;1
"Unit";"Zergling";"Larva";373;1
"Unit";"Zergling";"Larva";373;1
"Unit";"Zergling";"Larva";373;1
"Unit";"Zergling";"Larva";373;1
"Unit";"Zergling";"Larva";373;1
"Unit";"Zergling";"Larva";373;1
"Unit";"Zergling";"Larva";389;1
"Unit";"Zergling";"Larva";389;1
"Unit";"Zergling";"Larva";389;1
"Unit";"Zergling";"Larva";389;1
"Unit";"Zergling";"Larva";389;1
"Unit";"Zergling";"Larva";389;1
"Unit";"Zergling";"Larva";389;1
"Unit";"Zergling";"Larva";389;1
"Unit";"Zergling";"Larva";406;1
"Unit";"Zergling";"Larva";406;1
"Unit";"Zergling";"Larva";406;1
"Unit";"Zergling";"Larva";406;1
"Unit";"Zergling";"Larva";406;1
"Unit";"Zergling";"Larva";406;1
"Unit";"Zergling";"Larva";406;1
"Unit";"Zergling";"Larva";406;1
"Unit";"Zergling";"Larva";406;1
"Unit";"Zergling";"Larva";406;1
"Unit";"Zergling";"Larva";406;1
"Unit";"Zergling";"Larva";406;1
"Unit";"Zergling";"Larva";406;1
"Unit";"Zergling";"Larva";406;1
"Unit";"Zergling";"Larva";406;1
"Unit";"Zergling";"Larva";406;1
"Upgrade";"EvolveGroovedSpines";"HydraliskDen";389;0
"Unit";"Zergling";"Larva";406;1
"Unit";"Zergling";"Larva";406;1
"Unit";"Zergling";"Larva";406;1
"Unit";"Zergling";"Larva";406;1
"Unit";"Zergling";"Larva";406;1
"Unit";"Zergling";"Larva";406;1
"Unit";"Hydralisk";"Larva";422;2
"Unit";"Hydralisk";"Larva";422;2
"Unit";"Hydralisk";"Larva";422;2
"Unit";"Hydralisk";"Larva";422;2
"Unit";"Hydralisk";"Larva";428;2
"Unit";"Hydralisk";"Larva";428;2
"Unit";"Hydralisk";"Larva";428;2
"Unit";"Zergling";"Larva";437;1
"Unit";"Zergling";"Larva";437;1
"Unit";"Zergling";"Larva";437;1
"Unit";"Zergling";"Larva";437;1
"Unit";"Zergling";"Larva";437;1
"Unit";"Zergling";"Larva";437;1
"Unit";"Zergling";"Larva";438;1
"Unit";"Zergling";"Larva";438;1
"Building";"Hatchery";NA;406;0
"Unit";"Zergling";"Larva";446;1
"Unit";"Zergling";"Larva";446;1
"Unit";"Zergling";"Larva";446;1
"Unit";"Zergling";"Larva";446;1
"Unit";"Zergling";"Larva";446;1
"Unit";"Zergling";"Larva";446;1
"Building";"CreepTumor";NA;454;0
"Building";"CreepTumorQueen";NA;463;0
"Unit";"Zergling";"Larva";463;1
"Unit";"Zergling";"Larva";463;1
"Unit";"Hydralisk";"Larva";463;2
"Unit";"Hydralisk";"Larva";463;2
"Unit";"Hydralisk";"Larva";463;2
"Unit";"Hydralisk";"Larva";463;2
"Unit";"Hydralisk";"Larva";463;2
"Unit";"Baneling";"Zergling";465;0
"Unit";"Baneling";"Zergling";465;0
"Unit";"Baneling";"Zergling";465;0
"Unit";"Baneling";"Zergling";465;0
"Unit";"Baneling";"Zergling";465;0
"Unit";"Baneling";"Zergling";465;0
"Upgrade";"EvolveMuscularAugments";"HydraliskDen";454;0
"Unit";"Zergling";"Larva";469;1
"Unit";"Zergling";"Larva";469;1
"Unit";"Zergling";"Larva";469;1
"Unit";"Zergling";"Larva";469;1
"Unit";"Zergling";"Larva";469;1
"Unit";"Zergling";"Larva";469;1
"Unit";"Zergling";"Larva";469;1
"Unit";"Zergling";"Larva";469;1
"Unit";"Zergling";"Larva";469;1
"Unit";"Zergling";"Larva";469;1
"Unit";"Zergling";"Larva";469;1
"Unit";"Zergling";"Larva";469;1
"Unit";"Zergling";"Larva";469;1
"Unit";"Zergling";"Larva";469;1
"Unit";"Zergling";"Larva";483;1
"Unit";"Zergling";"Larva";483;1
"Unit";"Zergling";"Larva";483;1
"Unit";"Zergling";"Larva";483;1
"Unit";"Zergling";"Larva";483;1
"Unit";"Zergling";"Larva";483;1
"Unit";"Zergling";"Larva";483;1
"Unit";"Zergling";"Larva";483;1
"Unit";"Zergling";"Larva";483;1
"Unit";"Zergling";"Larva";483;1
"Unit";"Hydralisk";"Larva";475;2
"Unit";"Hydralisk";"Larva";475;2
"Unit";"Zergling";"Larva";489;1
"Unit";"Zergling";"Larva";489;1
"Unit";"Zergling";"Larva";489;1
"Unit";"Zergling";"Larva";489;1
"Unit";"Zergling";"Larva";489;1
"Unit";"Zergling";"Larva";489;1
"Building";"CreepTumorQueen";NA;495;0
"Building";"CreepTumor";NA;489;0
"Unit";"Zergling";"Larva";489;1
"Unit";"Zergling";"Larva";489;1
"Unit";"Zergling";"Larva";489;1
"Unit";"Zergling";"Larva";489;1
"Unit";"Zergling";"Larva";489;1
"Unit";"Zergling";"Larva";489;1
"Unit";"Zergling";"Larva";489;1
"Unit";"Zergling";"Larva";489;1
"Unit";"Zergling";"Larva";489;1
"Unit";"Zergling";"Larva";489;1
"Unit";"Zergling";"Larva";489;1
"Unit";"Zergling";"Larva";489;1
"Unit";"Zergling";"Larva";489;1
"Unit";"Zergling";"Larva";489;1
"Unit";"Zergling";"Larva";491;1
"Unit";"Zergling";"Larva";491;1
"Unit";"Zergling";"Larva";493;1
"Unit";"Zergling";"Larva";493;1
"Unit";"Zergling";"Larva";503;1
"Unit";"Zergling";"Larva";503;1
"Building";"Hatchery";NA;463;0
"Unit";"Zergling";"Larva";509;1
"Unit";"Zergling";"Larva";509;1
"Unit";"Zergling";"Larva";509;1
"Unit";"Zergling";"Larva";509;1
"Building";"CreepTumor";NA;521;0
"Unit";"Zergling";"Larva";527;1
"Unit";"Zergling";"Larva";527;1
"Building";"CreepTumor";NA;529;0
"Building";"CreepTumor";NA;529;0
"Unit";"Hydralisk";"Larva";523;2
"Unit";"Hydralisk";"Larva";523;2
"Unit";"Hydralisk";"Larva";523;2
"Unit";"Zergling";"Larva";529;1
"Unit";"Zergling";"Larva";529;1
"Unit";"Zergling";"Larva";529;1
"Unit";"Zergling";"Larva";529;1
"Unit";"Zergling";"Larva";529;1
"Unit";"Zergling";"Larva";529;1
"Unit";"Zergling";"Larva";529;1
"Unit";"Zergling";"Larva";529;1
"Unit";"Baneling";"Zergling";533;0
"Unit";"Baneling";"Zergling";533;0
"Unit";"Baneling";"Zergling";533;0
"Unit";"Baneling";"Zergling";533;0
"Unit";"Baneling";"Zergling";533;0
"Unit";"Baneling";"Zergling";533;0
"Unit";"Baneling";"Zergling";533;0
"Unit";"Baneling";"Zergling";533;0
"Unit";"Baneling";"Zergling";533;0
"Unit";"Baneling";"Zergling";533;0
"Unit";"Baneling";"Zergling";533;0
"Upgrade";"ZergMeleeWeaponsLevel2";"EvolutionChamber";465;0
"Unit";"Hydralisk";"Larva";539;2
"Unit";"Hydralisk";"Larva";541;2
"Unit";"Hydralisk";"Larva";541;2
"Building";"CreepTumor";NA;567;0
"Building";"CreepTumor";NA;567;0
"Unit";"Hydralisk";"Larva";549;2
"Unit";"Hydralisk";"Larva";549;2
"Unit";"Baneling";"Zergling";567;0
"Unit";"Baneling";"Zergling";567;0
"Unit";"Baneling";"Zergling";567;0
"Unit";"Baneling";"Zergling";567;0
"Unit";"Baneling";"Zergling";567;0
"Building";"LurkerDenMP";NA;509;0
"Unit";"Hydralisk";"Larva";567;2
"Unit";"Hydralisk";"Larva";567;2
"Unit";"Hydralisk";"Larva";567;2
"Unit";"Zergling";"Larva";569;1
"Unit";"Zergling";"Larva";569;1
"Unit";"Zergling";"Larva";569;1
"Unit";"Zergling";"Larva";569;1
"Unit";"Hydralisk";"Larva";569;2
"Unit";"Hydralisk";"Larva";569;2
"Unit";"Hydralisk";"Larva";569;2
"Building";"CreepTumor";NA;589;0
"Building";"CreepTumor";NA;589;0
"Unit";"Zergling";"Larva";583;1
"Unit";"Zergling";"Larva";583;1
"Unit";"Zergling";"Larva";583;1
"Unit";"Zergling";"Larva";583;1
"Unit";"Zergling";"Larva";583;1
"Unit";"Zergling";"Larva";583;1
"Unit";"Zergling";"Larva";583;1
"Unit";"Zergling";"Larva";583;1
"Unit";"Zergling";"Larva";583;1
"Unit";"Zergling";"Larva";583;1
"Unit";"Zergling";"Larva";583;1
"Unit";"Zergling";"Larva";583;1
"Unit";"Zergling";"Larva";583;1
"Unit";"Zergling";"Larva";583;1
"Unit";"Zergling";"Larva";583;1
"Unit";"Zergling";"Larva";583;1
"Unit";"Zergling";"Larva";583;1
"Unit";"Zergling";"Larva";583;1
"Unit";"Zergling";"Larva";583;1
"Unit";"Zergling";"Larva";583;1
"Unit";"Zergling";"Larva";583;1
"Unit";"Zergling";"Larva";583;1
"Unit";"Zergling";"Larva";583;1
"Unit";"Zergling";"Larva";583;1
"Unit";"Zergling";"Larva";583;1
"Unit";"Zergling";"Larva";583;1
"Unit";"Zergling";"Larva";583;1
"Unit";"Zergling";"Larva";583;1
"Unit";"Zergling";"Larva";583;1
"Unit";"Zergling";"Larva";583;1
"Unit";"Zergling";"Larva";583;1
"Unit";"Zergling";"Larva";583;1
"Unit";"Zergling";"Larva";583;1
"Unit";"Zergling";"Larva";583;1
"Building";"CreepTumor";NA;589;0
"Building";"CreepTumor";NA;589;0
"Building";"CreepTumorQueen";NA;623;0
"Unit";"Overlord";"Larva";591;0
"Unit";"Overlord";"Larva";591;0
"Unit";"Overlord";"Larva";595;0
"Unit";"Overlord";"Larva";623;0
"Unit";"Overlord";"Larva";623;0
"Unit";"Overlord";"Larva";623;0
"Unit";"Zergling";"Larva";623;1
"Unit";"Zergling";"Larva";623;1
"Unit";"Zergling";"Larva";623;1
"Unit";"Zergling";"Larva";623;1
"Unit";"Zergling";"Larva";623;1
"Unit";"Zergling";"Larva";623;1
"Unit";"Zergling";"Larva";623;1
"Unit";"Zergling";"Larva";623;1
"Unit";"Zergling";"Larva";623;1
"Unit";"Zergling";"Larva";623;1
"Unit";"Zergling";"Larva";623;1
"Unit";"Zergling";"Larva";623;1
"Unit";"Zergling";"Larva";623;1
"Unit";"Zergling";"Larva";623;1
"Unit";"Zergling";"Larva";623;1
"Unit";"Zergling";"Larva";623;1
"Unit";"Zergling";"Larva";623;1
"Unit";"Zergling";"Larva";623;1
"Unit";"Zergling";"Larva";623;1
"Unit";"Zergling";"Larva";623;1
"Unit";"Zergling";"Larva";623;1
"Unit";"Zergling";"Larva";623;1
"Unit";"Zergling";"Larva";623;1
"Unit";"Zergling";"Larva";623;1
"Unit";"Zergling";"Larva";623;1
"Unit";"Zergling";"Larva";623;1
"Unit";"Zergling";"Larva";623;1
"Unit";"Zergling";"Larva";623;1
"Unit";"Zergling";"Larva";623;1
"Unit";"Zergling";"Larva";623;1
"Unit";"Baneling";"Zergling";659;0
"Unit";"Baneling";"Zergling";659;0
"Unit";"Baneling";"Zergling";659;0
"Unit";"Baneling";"Zergling";659;0
"Unit";"Baneling";"Zergling";659;0
"Unit";"Baneling";"Zergling";659;0
"Unit";"Baneling";"Zergling";659;0
"Building";"Extractor";NA;623;0
"Building";"Extractor";NA;623;0
"Unit";"Baneling";"Zergling";659;0
"Building";"InfestationPit";NA;623;0
"Unit";"Zergling";"Larva";662;1
"Unit";"Zergling";"Larva";662;1
"Unit";"Zergling";"Larva";662;1
"Unit";"Zergling";"Larva";662;1
"Unit";"Zergling";"Larva";672;1
"Unit";"Zergling";"Larva";672;1
"Unit";"Zergling";"Larva";672;1
"Unit";"Zergling";"Larva";672;1
"Unit";"Zergling";"Larva";672;1
"Unit";"Zergling";"Larva";672;1
"Unit";"Zergling";"Larva";672;1
"Unit";"Zergling";"Larva";672;1
"Unit";"Zergling";"Larva";672;1
"Unit";"Zergling";"Larva";672;1
"Unit";"Zergling";"Larva";672;1
"Unit";"Zergling";"Larva";672;1
"Unit";"Zergling";"Larva";672;1
"Unit";"Zergling";"Larva";672;1
"Unit";"Zergling";"Larva";672;1
"Unit";"Zergling";"Larva";672;1
"Unit";"Zergling";"Larva";672;1
"Unit";"Zergling";"Larva";672;1
"Unit";"Zergling";"Larva";672;1
"Unit";"Zergling";"Larva";672;1
"Unit";"Zergling";"Larva";672;1
"Unit";"Zergling";"Larva";672;1
"Unit";"Zergling";"Larva";672;1
"Unit";"Zergling";"Larva";672;1
"Unit";"Baneling";"Zergling";677;0
"Unit";"Baneling";"Zergling";677;0
"Unit";"Baneling";"Zergling";677;0
"Unit";"Baneling";"Zergling";677;0
"Unit";"Baneling";"Zergling";677;0
"Unit";"Baneling";"Zergling";677;0
"Unit";"Baneling";"Zergling";677;0
"Unit";"Hydralisk";"Larva";677;2
"Unit";"Hydralisk";"Larva";677;2
"Unit";"Hydralisk";"Larva";677;2
"Upgrade";"ZergGroundArmorsLevel1";"EvolutionChamber";633;0
"Unit";"Zergling";"Larva";707;1
"Unit";"Zergling";"Larva";707;1
"Unit";"Zergling";"Larva";707;1
"Unit";"Zergling";"Larva";707;1
"Unit";"Zergling";"Larva";707;1
"Unit";"Zergling";"Larva";707;1
"Unit";"Zergling";"Larva";707;1
"Unit";"Zergling";"Larva";707;1
"Unit";"Zergling";"Larva";707;1
"Unit";"Zergling";"Larva";707;1
"Unit";"Zergling";"Larva";707;1
"Unit";"Zergling";"Larva";707;1
"Unit";"Hydralisk";"Larva";701;2
"Unit";"Hydralisk";"Larva";701;2
"Unit";"Hydralisk";"Larva";701;2
"Unit";"Hydralisk";"Larva";701;2
"Unit";"Hydralisk";"Larva";701;2
"Unit";"Hydralisk";"Larva";707;2
"Unit";"Hydralisk";"Larva";707;2
"Unit";"Zergling";"Larva";709;1
"Unit";"Zergling";"Larva";709;1
"Unit";"Zergling";"Larva";709;1
"Unit";"Zergling";"Larva";709;1
"Unit";"Hydralisk";"Larva";707;2
"Unit";"Hydralisk";"Larva";707;2
"Unit";"Hydralisk";"Larva";707;2
"Unit";"Hydralisk";"Larva";707;2
"Building";"Extractor";NA;729;0
"Unit";"Zergling";"Larva";733;1
"Unit";"Zergling";"Larva";733;1
"Building";"Extractor";NA;729;0
"Unit";"Zergling";"Larva";733;1
"Unit";"Zergling";"Larva";733;1
"Unit";"Zergling";"Larva";733;1
"Unit";"Zergling";"Larva";733;1
"Unit";"Zergling";"Larva";733;1
"Unit";"Zergling";"Larva";733;1
"Unit";"Zergling";"Larva";733;1
"Unit";"Zergling";"Larva";733;1
"Unit";"Zergling";"Larva";733;1
"Unit";"Zergling";"Larva";733;1
"Unit";"Zergling";"Larva";733;1
"Unit";"Zergling";"Larva";733;1
"Unit";"Zergling";"Larva";733;1
"Unit";"Zergling";"Larva";733;1
"Unit";"Zergling";"Larva";733;1
"Unit";"Zergling";"Larva";733;1
"Unit";"Zergling";"Larva";733;1
"Unit";"Zergling";"Larva";733;1
"Unit";"Zergling";"Larva";733;1
"Unit";"Zergling";"Larva";733;1
"Unit";"Zergling";"Larva";733;1
"Unit";"Zergling";"Larva";733;1
"Unit";"Zergling";"Larva";733;1
"Unit";"Zergling";"Larva";733;1
"Unit";"Zergling";"Larva";733;1
"Unit";"Zergling";"Larva";733;1
"Unit";"Zergling";"Larva";737;1
"Unit";"Zergling";"Larva";737;1
"Unit";"Zergling";"Larva";737;1
"Unit";"Zergling";"Larva";737;1
"Unit";"Zergling";"Larva";737;1
"Unit";"Zergling";"Larva";737;1
"Building";"Hatchery";NA;701;0
"Unit";"Zergling";"Larva";773;1
"Unit";"Zergling";"Larva";773;1
"Unit";"Zergling";"Larva";773;1
"Unit";"Zergling";"Larva";773;1
"Unit";"Zergling";"Larva";773;1
"Unit";"Zergling";"Larva";773;1
"Unit";"Zergling";"Larva";773;1
"Unit";"Zergling";"Larva";773;1
"Unit";"Zergling";"Larva";773;1
"Unit";"Zergling";"Larva";773;1
"Unit";"Zergling";"Larva";779;1
"Unit";"Zergling";"Larva";779;1
"Unit";"Zergling";"Larva";779;1
"Unit";"Zergling";"Larva";779;1
"Unit";"Zergling";"Larva";779;1
"Unit";"Zergling";"Larva";779;1
"Unit";"Hydralisk";"Larva";779;2
"Unit";"Hydralisk";"Larva";779;2
"Unit";"Hydralisk";"Larva";779;2
"Unit";"Hydralisk";"Larva";789;2
"Unit";"Hydralisk";"Larva";789;2
"Unit";"Hydralisk";"Larva";789;2
"Unit";"Zergling";"Larva";795;1
"Unit";"Zergling";"Larva";795;1
"Unit";"Zergling";"Larva";795;1
"Unit";"Zergling";"Larva";795;1
"Unit";"Zergling";"Larva";795;1
"Unit";"Zergling";"Larva";795;1
"Unit";"Zergling";"Larva";795;1
"Unit";"Zergling";"Larva";795;1
"Unit";"Zergling";"Larva";795;1
"Unit";"Zergling";"Larva";795;1
"Unit";"Zergling";"Larva";817;1
"Unit";"Zergling";"Larva";817;1
"Unit";"Zergling";"Larva";817;1
"Unit";"Zergling";"Larva";817;1
"Unit";"Zergling";"Larva";817;1
"Unit";"Zergling";"Larva";817;1
"Unit";"Zergling";"Larva";817;1
"Unit";"Zergling";"Larva";817;1
"Unit";"Hydralisk";"Larva";817;2
"Unit";"Hydralisk";"Larva";817;2
"Unit";"Hydralisk";"Larva";817;2
"Unit";"Hydralisk";"Larva";817;2
"Unit";"Zergling";"Larva";825;1
"Unit";"Zergling";"Larva";825;1
"Unit";"Zergling";"Larva";825;1
"Unit";"Zergling";"Larva";825;1
"Unit";"Zergling";"Larva";825;1
"Unit";"Zergling";"Larva";825;1
"Unit";"Zergling";"Larva";825;1
"Unit";"Zergling";"Larva";825;1
"Unit";"Zergling";"Larva";825;1
"Unit";"Zergling";"Larva";825;1
"Building";"Hatchery";NA;789;0
"Unit";"Hydralisk";"Larva";825;2
"Unit";"Zergling";"Larva";829;1
"Unit";"Zergling";"Larva";829;1
"Unit";"Hydralisk";"Larva";843;2
"Unit";"Hydralisk";"Larva";843;2
"Unit";"Hydralisk";"Larva";843;2
"Unit";"Zergling";"Larva";847;1
"Unit";"Zergling";"Larva";847;1
"Unit";"Zergling";"Larva";847;1
"Unit";"Zergling";"Larva";847;1
"Unit";"Zergling";"Larva";847;1
"Unit";"Zergling";"Larva";847;1
"Unit";"Zergling";"Larva";847;1
"Unit";"Zergling";"Larva";847;1
"Unit";"Zergling";"Larva";847;1
"Unit";"Zergling";"Larva";847;1
