"type";"unit_name";"on_building";"total_supply_lag";"supply"
"Unit";"Overlord";"Larva";13;0
"Building";"Hatchery";NA;16;0
"Building";"Extractor";NA;19;0
"Building";"SpawningPool";NA;19;0
"Unit";"Overlord";"Larva";23;0
"Unit";"Queen";"Hatchery";23;2
"Unit";"Queen";"Hatchery";25;2
"Unit";"Zergling";"Larva";27;1
"Unit";"Zergling";"Larva";28;1
"Unit";"Zergling";"Larva";29;1
"Unit";"Zergling";"Larva";30;1
"Building";"Hatchery";NA;35;0
"Building";"CreepTumorQueen";NA;36;0
"Unit";"Queen";"Hatchery";36;2
"Unit";"Overlord";"Larva";38;0
"Unit";"Zergling";"Larva";40;1
"Unit";"Zergling";"Larva";41;1
"Unit";"Zergling";"Larva";42;1
"Unit";"Zergling";"Larva";43;1
"Building";"CreepTumorQueen";NA;46;0
"Building";"CreepTumor";NA;49;0
"Unit";"Overlord";"Larva";49;0
"Unit";"Queen";"Hatchery";49;2
"Building";"SporeCrawler";NA;52;0
"Building";"CreepTumor";NA;53;0
"Unit";"Overlord";"Larva";56;0
"Building";"CreepTumorQueen";NA;60;0
"Building";"CreepTumor";NA;61;0
"Building";"CreepTumorQueen";NA;63;0
"Unit";"Overlord";"Larva";65;0
"Building";"SporeCrawler";NA;66;0
"Building";"RoachWarren";NA;66;0
"Building";"Extractor";NA;66;0
"Building";"Extractor";NA;67;0
"Unit";"Overlord";"Larva";69;0
"Building";"CreepTumor";NA;70;0
"Building";"CreepTumor";NA;70;0
"Building";"CreepTumor";NA;70;0
"Unit";"Overlord";"Larva";73;0
"Unit";"Overlord";"Larva";73;0
"Building";"SporeCrawler";NA;75;0
"Unit";"Zergling";"Larva";75;1
"Unit";"Zergling";"Larva";76;1
"Unit";"Zergling";"Larva";77;1
"Unit";"Zergling";"Larva";78;1
"Unit";"Zergling";"Larva";79;1
"Unit";"Zergling";"Larva";80;1
"Unit";"Zergling";"Larva";81;1
"Unit";"Zergling";"Larva";82;1
"Unit";"Roach";"Larva";83;2
"Unit";"Roach";"Larva";85;2
"Unit";"Roach";"Larva";87;2
"Unit";"Roach";"Larva";92;2
"Building";"CreepTumor";NA;98;0
"Building";"CreepTumor";NA;99;0
"Building";"CreepTumor";NA;101;0
"Building";"CreepTumorQueen";NA;101;0
"Upgrade";"GlialReconstitution";"RoachWarren";101;0
"Unit";"Overlord";"Larva";101;0
"Unit";"Roach";"Larva";101;2
"Unit";"Roach";"Larva";103;2
"Unit";"Roach";"Larva";105;2
"Unit";"Roach";"Larva";107;2
"Unit";"Roach";"Larva";109;2
"Unit";"Roach";"Larva";111;2
"Unit";"Overlord";"Larva";113;0
"Building";"Extractor";NA;113;0
"Unit";"Roach";"Larva";113;2
"Unit";"Roach";"Larva";115;2
"Unit";"Roach";"Larva";117;2
"Unit";"Roach";"Larva";119;2
"Building";"HydraliskDen";NA;121;0
"Unit";"Overlord";"Larva";131;0
"Building";"CreepTumorQueen";NA;132;0
"Building";"CreepTumorQueen";NA;132;0
"Building";"Extractor";NA;135;0
"Building";"EvolutionChamber";NA;135;0
"Unit";"Overlord";"Larva";135;0
"Unit";"Roach";"Larva";135;2
"Unit";"Roach";"Larva";137;2
"Unit";"Overlord";"Larva";139;0
"Building";"Extractor";NA;142;0
"Building";"LurkerDenMP";NA;142;0
"Building";"CreepTumor";NA;146;0
"Unit";"Overlord";"Larva";146;0
"Unit";"Hydralisk";"Larva";146;2
"Building";"Hatchery";NA;148;0
"Unit";"Overlord";"Larva";148;0
"Unit";"Roach";"Larva";148;2
"Unit";"Roach";"Larva";150;2
"Unit";"Roach";"Larva";152;2
"Unit";"Roach";"Larva";154;2
"Unit";"Roach";"Larva";156;2
"Building";"CreepTumorQueen";NA;158;0
"Building";"CreepTumorQueen";NA;158;0
"Unit";"Overlord";"Larva";158;0
"Unit";"Overlord";"Larva";158;0
"Unit";"Hydralisk";"Larva";158;2
"Unit";"Hydralisk";"Larva";160;2
"Unit";"Hydralisk";"Larva";162;2
"Unit";"Hydralisk";"Larva";164;2
"Unit";"Overlord";"Larva";166;0
"Unit";"Overlord";"Larva";166;0
"Unit";"Hydralisk";"Larva";166;2
"Unit";"Hydralisk";"Larva";168;2
"Unit";"Hydralisk";"Larva";170;2
"Unit";"Hydralisk";"Larva";172;2
"Unit";"Hydralisk";"Larva";174;2
"Building";"CreepTumor";NA;176;0
"Building";"CreepTumor";NA;176;0
"Unit";"Hydralisk";"Larva";176;2
"Unit";"Hydralisk";"Larva";178;2
"Unit";"Overlord";"Larva";180;0
"Unit";"Overlord";"Larva";180;0
"Building";"CreepTumor";NA;180;0
"Unit";"Hydralisk";"Larva";180;2
"Unit";"Hydralisk";"Larva";182;2
"Unit";"Hydralisk";"Larva";184;2
"Unit";"Hydralisk";"Larva";186;2
"Unit";"Hydralisk";"Larva";188;2
"Unit";"Hydralisk";"Larva";190;2
"Unit";"Hydralisk";"Larva";192;2
"Building";"CreepTumorQueen";NA;194;0
"Building";"CreepTumorQueen";NA;194;0
"Unit";"Overlord";"Larva";194;0
"Unit";"Zergling";"Larva";194;1
"Unit";"Zergling";"Larva";195;1
"Unit";"Zergling";"Larva";196;1
"Unit";"Zergling";"Larva";197;1
"Unit";"Zergling";"Larva";198;1
"Unit";"Zergling";"Larva";199;1
"Unit";"Zergling";"Larva";200;1
"Unit";"Zergling";"Larva";201;1
"Unit";"Zergling";"Larva";202;1
"Unit";"Zergling";"Larva";203;1
"Unit";"Zergling";"Larva";204;1
"Unit";"Zergling";"Larva";205;1
"Unit";"Zergling";"Larva";206;1
"Unit";"Zergling";"Larva";207;1
"Unit";"Hydralisk";"Larva";208;2
"Unit";"Hydralisk";"Larva";210;2
"Unit";"Hydralisk";"Larva";212;2
"Unit";"Hydralisk";"Larva";214;2
"Unit";"Hydralisk";"Larva";216;2
"Unit";"Zergling";"Larva";218;1
"Unit";"Zergling";"Larva";219;1
"Unit";"Overlord";"Larva";220;0
"Unit";"Zergling";"Larva";220;1
"Unit";"Zergling";"Larva";221;1
"Unit";"Zergling";"Larva";222;1
"Unit";"Zergling";"Larva";223;1
"Unit";"Zergling";"Larva";224;1
"Unit";"Zergling";"Larva";225;1
"Unit";"Zergling";"Larva";226;1
"Unit";"Zergling";"Larva";227;1
"Unit";"Zergling";"Larva";228;1
"Unit";"Zergling";"Larva";229;1
"Unit";"Zergling";"Larva";230;1
"Unit";"Zergling";"Larva";231;1
"Unit";"Zergling";"Larva";232;1
"Unit";"Zergling";"Larva";233;1
"Unit";"Zergling";"Larva";234;1
"Unit";"Zergling";"Larva";235;1
"Unit";"Hydralisk";"Larva";236;2
"Unit";"Hydralisk";"Larva";238;2
"Unit";"Hydralisk";"Larva";240;2
"Unit";"Overlord";"Larva";242;0
"Unit";"Zergling";"Larva";242;1
"Unit";"Zergling";"Larva";243;1
"Unit";"Zergling";"Larva";244;1
"Unit";"Zergling";"Larva";245;1
"Unit";"Zergling";"Larva";246;1
"Unit";"Zergling";"Larva";247;1
"Unit";"Zergling";"Larva";248;1
"Unit";"Zergling";"Larva";249;1
"Unit";"Zergling";"Larva";250;1
"Unit";"Zergling";"Larva";251;1
"Unit";"Hydralisk";"Larva";252;2
"Unit";"Hydralisk";"Larva";254;2
"Unit";"Hydralisk";"Larva";256;2
"Unit";"Hydralisk";"Larva";258;2
"Unit";"Hydralisk";"Larva";260;2
"Unit";"Hydralisk";"Larva";262;2
"Unit";"Hydralisk";"Larva";264;2
"Unit";"Hydralisk";"Larva";266;2
"Unit";"Hydralisk";"Larva";268;2
"Unit";"Hydralisk";"Larva";270;2
"Unit";"Hydralisk";"Larva";272;2
"Unit";"Hydralisk";"Larva";274;2
"Unit";"Zergling";"Larva";276;1
"Unit";"Zergling";"Larva";277;1
"Unit";"Zergling";"Larva";278;1
"Unit";"Zergling";"Larva";279;1
"Unit";"Zergling";"Larva";280;1
"Unit";"Zergling";"Larva";281;1
"Unit";"Zergling";"Larva";282;1
"Unit";"Zergling";"Larva";283;1
"Unit";"Zergling";"Larva";284;1
"Unit";"Zergling";"Larva";285;1
"Unit";"Zergling";"Larva";286;1
"Unit";"Zergling";"Larva";287;1
"Unit";"Zergling";"Larva";288;1
"Unit";"Zergling";"Larva";289;1
"Unit";"Zergling";"Larva";290;1
"Unit";"Zergling";"Larva";291;1
"Unit";"Zergling";"Larva";292;1
"Unit";"Zergling";"Larva";293;1
"Unit";"Zergling";"Larva";294;1
"Unit";"Zergling";"Larva";295;1
"Unit";"Zergling";"Larva";296;1
"Unit";"Zergling";"Larva";297;1
"Unit";"Zergling";"Larva";298;1
"Unit";"Zergling";"Larva";299;1
"Unit";"Hydralisk";"Larva";300;2
"Unit";"Hydralisk";"Larva";302;2
"Building";"Hatchery";NA;304;0
"Unit";"Hydralisk";"Larva";304;2
"Unit";"Hydralisk";"Larva";306;2
"Unit";"Hydralisk";"Larva";308;2
"Unit";"Hydralisk";"Larva";310;2
"Unit";"Hydralisk";"Larva";312;2
"Unit";"Hydralisk";"Larva";314;2
"Unit";"Hydralisk";"Larva";316;2
"Unit";"Zergling";"Larva";318;1
"Unit";"Zergling";"Larva";319;1
"Unit";"Zergling";"Larva";320;1
"Unit";"Zergling";"Larva";321;1
"Unit";"Zergling";"Larva";322;1
"Unit";"Zergling";"Larva";323;1
"Unit";"Zergling";"Larva";324;1
"Unit";"Zergling";"Larva";325;1
"Unit";"Zergling";"Larva";326;1
"Unit";"Zergling";"Larva";327;1
"Unit";"Zergling";"Larva";328;1
"Unit";"Zergling";"Larva";329;1
"Unit";"Zergling";"Larva";330;1
"Unit";"Zergling";"Larva";331;1
"Unit";"Zergling";"Larva";332;1
"Unit";"Zergling";"Larva";333;1
"Unit";"Zergling";"Larva";334;1
"Unit";"Zergling";"Larva";335;1
"Unit";"Zergling";"Larva";336;1
"Unit";"Zergling";"Larva";337;1
"Unit";"Zergling";"Larva";338;1
"Unit";"Zergling";"Larva";339;1
"Unit";"Zergling";"Larva";340;1
"Unit";"Zergling";"Larva";341;1
"Unit";"Hydralisk";"Larva";342;2
"Unit";"Hydralisk";"Larva";344;2
"Unit";"Hydralisk";"Larva";346;2
"Unit";"Hydralisk";"Larva";348;2
"Unit";"Hydralisk";"Larva";350;2
"Unit";"Hydralisk";"Larva";352;2
"Unit";"Hydralisk";"Larva";354;2
"Unit";"Hydralisk";"Larva";356;2
"Unit";"Hydralisk";"Larva";358;2
"Unit";"Zergling";"Larva";360;1
"Unit";"Zergling";"Larva";361;1
"Unit";"Zergling";"Larva";362;1
"Unit";"Zergling";"Larva";363;1
"Unit";"Zergling";"Larva";364;1
"Unit";"Zergling";"Larva";365;1
"Unit";"Zergling";"Larva";366;1
"Unit";"Zergling";"Larva";367;1
"Unit";"Zergling";"Larva";368;1
"Unit";"Zergling";"Larva";369;1
"Upgrade";"SprayZerg";NA;370;0
"Upgrade";"SprayZerg";NA;370;0
"Upgrade";"SprayZerg";NA;370;0
"Upgrade";"zerglingmovementspeed";NA;370;0
"Upgrade";"SprayZerg";NA;370;0
"Upgrade";"SprayZerg";NA;370;0
"Upgrade";"EvolveMuscularAugments";NA;370;0
"Upgrade";"SprayZerg";NA;370;0
"Upgrade";"ZergMissileWeaponsLevel1";NA;370;0
"Upgrade";"EvolveGroovedSpines";NA;370;0
"Upgrade";"SprayZerg";NA;370;0
"Upgrade";"SprayZerg";NA;370;0
"Upgrade";"SprayZerg";NA;370;0
