"type";"unit_name";"on_building";"total_supply";"supply"
"Unit";"Overlord";"Larva";13;0
"Building";"Extractor";NA;18;0
"Building";"SpawningPool";NA;19;0
"Building";"Hatchery";NA;17;0
"Unit";"Zergling";"Larva";23;1
"Unit";"Zergling";"Larva";23;1
"Unit";"Overlord";"Larva";23;0
"Unit";"Queen";"Hatchery";23;2
"Unit";"Zergling";"Larva";27;1
"Unit";"Zergling";"Larva";27;1
"Building";"Hatchery";NA;22;0
"Unit";"Overlord";"Larva";34;0
"Unit";"Queen";"Hatchery";30;2
"Building";"CreepTumorQueen";NA;37;0
"Unit";"Zergling";"Larva";43;1
"Unit";"Zergling";"Larva";43;1
"Unit";"Zergling";"Larva";43;1
"Unit";"Zergling";"Larva";43;1
"Unit";"Queen";"Hatchery";37;2
"Unit";"Overlord";"Larva";43;0
"Unit";"Queen";"Hatchery";37;2
"Unit";"Overlord";"Larva";43;0
"Building";"SporeCrawler";NA;47;0
"Building";"SporeCrawler";NA;47;0
"Building";"CreepTumorQueen";NA;56;0
"Building";"CreepTumor";NA;56;0
"Building";"SporeCrawler";NA;56;0
"Building";"Extractor";NA;56;0
"Building";"Extractor";NA;56;0
"Building";"CreepTumorQueen";NA;66;0
"Building";"RoachWarren";NA;64;0
"Building";"CreepTumor";NA;71;0
"Unit";"Overlord";"Larva";71;0
"Building";"CreepTumor";NA;71;0
"Unit";"Overlord";"Larva";71;0
"Unit";"Overlord";"Larva";71;0
"Unit";"Overlord";"Larva";71;0
"Building";"Extractor";NA;71;0
"Unit";"Roach";"Larva";74;2
"Unit";"Roach";"Larva";74;2
"Unit";"Roach";"Larva";74;2
"Unit";"Roach";"Larva";74;2
"Building";"CreepTumor";NA;74;0
"Building";"CreepTumorQueen";NA;82;0
"Building";"CreepTumor";NA;82;0
"Unit";"Roach";"Larva";82;2
"Unit";"Roach";"Larva";82;2
"Unit";"Roach";"Larva";82;2
"Unit";"Roach";"Larva";82;2
"Unit";"Overlord";"Larva";82;0
"Unit";"Queen";"Hatchery";74;2
"Building";"CreepTumor";NA;82;0
"Unit";"Roach";"Larva";82;2
"Unit";"Roach";"Larva";82;2
"Unit";"Roach";"Larva";82;2
"Unit";"Roach";"Larva";82;2
"Unit";"Zergling";"Larva";82;1
"Unit";"Zergling";"Larva";82;1
"Unit";"Zergling";"Larva";82;1
"Unit";"Zergling";"Larva";82;1
"Unit";"Zergling";"Larva";82;1
"Unit";"Zergling";"Larva";82;1
"Unit";"Zergling";"Larva";82;1
"Unit";"Zergling";"Larva";82;1
"Unit";"Zergling";"Larva";82;1
"Unit";"Zergling";"Larva";82;1
"Unit";"Overlord";"Larva";86;0
"Building";"CreepTumor";NA;92;0
"Unit";"Overlord";"Larva";92;0
"Building";"CreepTumor";NA;100;0
"Building";"CreepTumor";NA;102;0
"Unit";"Roach";"Larva";100;2
"Unit";"Roach";"Larva";100;2
"Unit";"Roach";"Larva";100;2
"Unit";"Roach";"Larva";100;2
"Unit";"Overlord";"Larva";100;0
"Unit";"Zergling";"Larva";112;1
"Unit";"Zergling";"Larva";112;1
"Unit";"Zergling";"Larva";114;1
"Unit";"Zergling";"Larva";114;1
"Unit";"Overlord";"Larva";110;0
"Unit";"Overlord";"Larva";110;0
"Unit";"Roach";"Larva";110;2
"Unit";"Roach";"Larva";110;2
"Unit";"Roach";"Larva";110;2
"Unit";"Roach";"Larva";110;2
"Building";"CreepTumor";NA;118;0
"Upgrade";"GlialReconstitution";"RoachWarren";82;0
"Building";"CreepTumor";NA;118;0
"Unit";"Roach";"Larva";135;2
"Unit";"Roach";"Larva";135;2
"Unit";"Roach";"Larva";135;2
"Unit";"Roach";"Larva";135;2
"Unit";"Roach";"Larva";135;2
"Unit";"Roach";"Larva";135;2
"Unit";"Roach";"Larva";135;2
"Unit";"Roach";"Larva";135;2
"Building";"Extractor";NA;135;0
"Building";"EvolutionChamber";NA;135;0
"Building";"HydraliskDen";NA;135;0
"Unit";"Roach";"Larva";160;2
"Unit";"Roach";"Larva";160;2
"Unit";"Roach";"Larva";160;2
"Unit";"Roach";"Larva";160;2
"Unit";"Roach";"Larva";160;2
"Unit";"Overlord";"Larva";160;0
"Unit";"Overlord";"Larva";160;0
"Building";"Extractor";NA;160;0
"Unit";"Roach";"Larva";170;2
"Unit";"Roach";"Larva";170;2
"Unit";"Roach";"Larva";170;2
"Unit";"Roach";"Larva";170;2
"Unit";"Roach";"Larva";170;2
"Unit";"Roach";"Larva";170;2
"Unit";"Roach";"Larva";170;2
"Unit";"Roach";"Larva";170;2
"Unit";"Roach";"Larva";170;2
"Unit";"Roach";"Larva";170;2
"Unit";"Roach";"Larva";170;2
"Unit";"Roach";"Larva";170;2
"Unit";"Roach";"Larva";170;2
"Unit";"Hydralisk";"Larva";196;2
"Unit";"Hydralisk";"Larva";196;2
"Unit";"Hydralisk";"Larva";196;2
"Unit";"Hydralisk";"Larva";196;2
"Unit";"Hydralisk";"Larva";196;2
"Building";"Hatchery";NA;170;0
"Unit";"Hydralisk";"Larva";200;2
"Unit";"Hydralisk";"Larva";200;2
"Unit";"Hydralisk";"Larva";200;2
"Unit";"Hydralisk";"Larva";200;2
"Unit";"Hydralisk";"Larva";200;2
"Building";"CreepTumor";NA;210;0
"Building";"CreepTumor";NA;210;0
"Building";"CreepTumor";NA;212;0
"Unit";"Overlord";"Larva";210;0
"Unit";"Overlord";"Larva";210;0
"Building";"CreepTumor";NA;212;0
"Upgrade";"ZergMissileWeaponsLevel1";"EvolutionChamber";170;0
"Unit";"Hydralisk";"Larva";220;2
"Unit";"Hydralisk";"Larva";220;2
"Unit";"Hydralisk";"Larva";220;2
"Unit";"Hydralisk";"Larva";220;2
"Unit";"Hydralisk";"Larva";220;2
"Unit";"Queen";"Hatchery";210;2
"Unit";"Overlord";"Larva";228;0
"Building";"SporeCrawler";NA;228;0
"Building";"CreepTumorQueen";NA;228;0
"Upgrade";"EvolveMuscularAugments";"HydraliskDen";200;0
"Building";"LurkerDenMP";NA;196;0
"Unit";"Hydralisk";"Larva";228;2
"Unit";"Hydralisk";"Larva";228;2
"Unit";"Hydralisk";"Larva";228;2
"Unit";"Hydralisk";"Larva";228;2
"Unit";"Hydralisk";"Larva";228;2
"Building";"CreepTumorQueen";NA;240;0
"Building";"CreepTumorQueen";NA;240;0
"Building";"CreepTumorQueen";NA;240;0
"Unit";"Hydralisk";"Larva";240;2
"Unit";"Hydralisk";"Larva";240;2
"Unit";"Hydralisk";"Larva";240;2
"Unit";"Hydralisk";"Larva";240;2
"Unit";"Hydralisk";"Larva";240;2
"Building";"Extractor";NA;240;0
"Building";"Extractor";NA;240;0
"Unit";"Hydralisk";"Larva";250;2
"Unit";"Hydralisk";"Larva";250;2
"Unit";"Hydralisk";"Larva";250;2
"Unit";"Roach";"Larva";260;2
"Unit";"Overlord";"Larva";260;0
"Unit";"Overlord";"Larva";260;0
"Unit";"Overlord";"Larva";260;0
"Unit";"Overlord";"Larva";260;0
"Unit";"Roach";"Larva";260;2
"Unit";"Overlord";"Larva";260;0
"Unit";"Roach";"Larva";260;2
"Unit";"Roach";"Larva";260;2
