"type";"unit_name";"on_building";"total_supply";"supply"
"Unit";"Overlord";"Larva";12;0
"Building";"Hatchery";NA;16;0
"Unit";"Overlord";"Larva";23;0
"Building";"SpawningPool";NA;26;0
"Unit";"Overlord";"Larva";33;0
"Unit";"Overlord";"Larva";33;0
"Building";"Extractor";NA;33;0
"Building";"Hatchery";NA;25;0
"Unit";"Overlord";"Larva";36;0
"Unit";"Queen";"Hatchery";33;2
"Unit";"Queen";"Hatchery";33;2
"Unit";"Queen";"Hatchery";37;2
"Building";"Extractor";NA;44;0
"Building";"Extractor";NA;45;0
"Building";"SporeCrawler";NA;45;0
"Building";"SporeCrawler";NA;46;0
"Building";"SporeCrawler";NA;48;0
"Unit";"Overlord";"Larva";56;0
"Building";"Extractor";NA;56;0
"Unit";"Queen";"Hatchery";54;2
"Unit";"Queen";"Hatchery";54;2
"Building";"EvolutionChamber";NA;56;0
"Unit";"Overlord";"Larva";68;0
"Unit";"Overlord";"Larva";68;0
"Unit";"Overlord";"Larva";68;0
"Building";"CreepTumorQueen";NA;75;0
"Building";"CreepTumorQueen";NA;75;0
"Unit";"Overlord";"Larva";75;0
"Unit";"Overlord";"Larva";75;0
"Unit";"Overlord";"Larva";75;0
"Building";"Extractor";NA;75;0
"Building";"CreepTumor";NA;80;0
"Building";"Extractor";NA;75;0
"Building";"HydraliskDen";NA;75;0
"Building";"CreepTumorQueen";NA;92;0
"Unit";"Overlord";"Larva";83;0
"Building";"CreepTumorQueen";NA;92;0
"Building";"CreepTumor";NA;92;0
"Unit";"Overlord";"Larva";92;0
"Unit";"Queen";"Hatchery";82;2
"Building";"CreepTumorQueen";NA;92;0
"Building";"CreepTumorQueen";NA;92;0
"Unit";"Queen";"Hatchery";82;2
"Unit";"Hydralisk";"Larva";92;2
"Unit";"Hydralisk";"Larva";92;2
"Unit";"Overlord";"Larva";92;0
"Unit";"Hydralisk";"Larva";92;2
"Unit";"Hydralisk";"Larva";92;2
"Unit";"Hydralisk";"Larva";92;2
"Building";"CreepTumor";NA;96;0
"Building";"CreepTumor";NA;100;0
"Building";"CreepTumorQueen";NA;100;0
"Building";"CreepTumorQueen";NA;100;0
"Building";"CreepTumorQueen";NA;100;0
"Building";"CreepTumorQueen";NA;106;0
"Unit";"Overlord";"Larva";100;0
"Unit";"Overlord";"Larva";100;0
"Upgrade";"ZergMissileWeaponsLevel1";"EvolutionChamber";82;0
"Unit";"Hydralisk";"Larva";102;2
"Unit";"Hydralisk";"Larva";106;2
"Unit";"Hydralisk";"Larva";106;2
"Unit";"Hydralisk";"Larva";106;2
"Unit";"Hydralisk";"Larva";106;2
"Unit";"Hydralisk";"Larva";106;2
"Unit";"Hydralisk";"Larva";106;2
"Building";"CreepTumor";NA;106;0
"Building";"CreepTumor";NA;106;0
"Unit";"Overlord";"Larva";106;0
"Unit";"Overlord";"Larva";106;0
"Unit";"Queen";"Hatchery";100;2
"Building";"CreepTumor";NA;106;0
"Building";"CreepTumor";NA;106;0
"Upgrade";"EvolveGroovedSpines";"HydraliskDen";92;0
"Building";"CreepTumor";NA;106;0
"Building";"CreepTumor";NA;106;0
"Building";"Hatchery";NA;92;0
"Building";"CreepTumorQueen";NA;120;0
"Building";"CreepTumorQueen";NA;120;0
"Building";"CreepTumorQueen";NA;122;0
"Building";"CreepTumorQueen";NA;122;0
"Building";"CreepTumorQueen";NA;122;0
"Unit";"Hydralisk";"Larva";120;2
"Unit";"Hydralisk";"Larva";120;2
"Unit";"Hydralisk";"Larva";120;2
"Unit";"Hydralisk";"Larva";120;2
"Unit";"Hydralisk";"Larva";120;2
"Unit";"Hydralisk";"Larva";120;2
"Unit";"Hydralisk";"Larva";120;2
"Building";"EvolutionChamber";NA;120;0
"Building";"CreepTumor";NA;122;0
"Building";"CreepTumor";NA;122;0
"Unit";"Overlord";"Larva";122;0
"Unit";"Overlord";"Larva";122;0
"Unit";"Overlord";"Larva";122;0
"Unit";"Overlord";"Larva";122;0
"Unit";"Queen";"Hatchery";120;2
"Building";"CreepTumor";NA;136;0
"Building";"CreepTumor";NA;136;0
"Unit";"Hydralisk";"Larva";122;2
"Unit";"Hydralisk";"Larva";124;2
"Unit";"Hydralisk";"Larva";124;2
"Unit";"Hydralisk";"Larva";126;2
"Unit";"Hydralisk";"Larva";126;2
"Building";"CreepTumorQueen";NA;138;0
"Building";"CreepTumorQueen";NA;148;0
"Building";"CreepTumorQueen";NA;148;0
"Upgrade";"EvolveMuscularAugments";"HydraliskDen";136;0
"Unit";"Hydralisk";"Larva";148;2
"Unit";"Hydralisk";"Larva";148;2
"Unit";"Hydralisk";"Larva";148;2
"Unit";"Hydralisk";"Larva";148;2
"Unit";"Hydralisk";"Larva";148;2
"Unit";"Hydralisk";"Larva";148;2
"Unit";"Hydralisk";"Larva";148;2
"Building";"SporeCrawler";NA;148;0
"Unit";"Hydralisk";"Larva";148;2
"Unit";"Hydralisk";"Larva";148;2
"Unit";"Hydralisk";"Larva";148;2
"Unit";"Hydralisk";"Larva";148;2
"Unit";"Hydralisk";"Larva";148;2
"Unit";"Hydralisk";"Larva";148;2
"Unit";"Hydralisk";"Larva";148;2
"Building";"CreepTumor";NA;162;0
"Building";"CreepTumor";NA;162;0
"Unit";"Hydralisk";"Larva";162;2
"Unit";"Hydralisk";"Larva";162;2
"Unit";"Hydralisk";"Larva";162;2
"Unit";"Hydralisk";"Larva";162;2
"Unit";"Hydralisk";"Larva";162;2
"Unit";"Hydralisk";"Larva";162;2
"Unit";"Hydralisk";"Larva";162;2
"Building";"CreepTumor";NA;176;0
"Unit";"Overlord";"Larva";176;0
"Unit";"Overlord";"Larva";176;0
"Unit";"Overlord";"Larva";176;0
"Unit";"Overlord";"Larva";176;0
