"type";"unit_name";"on_building";"total_supply";"supply"
"Unit";"Overlord";"Larva";13;0
"Building";"Extractor";NA;17;0
"Unit";"Overlord";"Larva";22;0
"Building";"SpawningPool";NA;19;0
"Building";"Hatchery";NA;16;0
"Unit";"Zergling";"Larva";23;1
"Unit";"Zergling";"Larva";23;1
"Unit";"Queen";"Hatchery";22;2
"Unit";"Queen";"Hatchery";23;2
"Unit";"Zergling";"Larva";34;1
"Unit";"Zergling";"Larva";34;1
"Unit";"Zergling";"Larva";35;1
"Unit";"Zergling";"Larva";35;1
"Unit";"Overlord";"Larva";36;0
"Unit";"Overlord";"Larva";40;0
"Unit";"Queen";"Hatchery";36;2
"Unit";"Overlord";"Larva";41;0
"Unit";"Zergling";"Larva";41;1
"Unit";"Zergling";"Larva";41;1
"Building";"CreepTumorQueen";NA;48;0
"Building";"SporeCrawler";NA;41;0
"Building";"SporeCrawler";NA;48;0
"Building";"Hatchery";NA;34;0
"Unit";"Overlord";"Larva";53;0
"Unit";"Queen";"Hatchery";53;2
"Unit";"Overlord";"Larva";58;0
"Building";"CreepTumor";NA;61;0
"Building";"CreepTumorQueen";NA;64;0
"Unit";"Overlord";"Larva";64;0
"Building";"SporeCrawler";NA;66;0
"Building";"CreepTumor";NA;72;0
"Building";"RoachWarren";NA;62;0
"Building";"Extractor";NA;66;0
"Building";"CreepTumor";NA;72;0
"Building";"Extractor";NA;68;0
"Building";"CreepTumorQueen";NA;75;0
"Unit";"Overlord";"Larva";78;0
"Unit";"Zergling";"Larva";78;1
"Unit";"Zergling";"Larva";78;1
"Unit";"Zergling";"Larva";78;1
"Unit";"Zergling";"Larva";78;1
"Unit";"Zergling";"Larva";78;1
"Unit";"Zergling";"Larva";78;1
"Unit";"Roach";"Larva";78;2
"Unit";"Roach";"Larva";78;2
"Unit";"Roach";"Larva";78;2
"Unit";"Roach";"Larva";78;2
"Unit";"Overlord";"Larva";78;0
"Unit";"Overlord";"Larva";78;0
"Building";"Extractor";NA;78;0
"Building";"CreepTumorQueen";NA;92;0
"Unit";"Zergling";"Larva";93;1
"Unit";"Zergling";"Larva";93;1
"Unit";"Zergling";"Larva";93;1
"Unit";"Zergling";"Larva";93;1
"Unit";"Zergling";"Larva";93;1
"Unit";"Zergling";"Larva";93;1
"Unit";"Zergling";"Larva";93;1
"Unit";"Zergling";"Larva";93;1
"Unit";"Zergling";"Larva";93;1
"Unit";"Zergling";"Larva";93;1
"Unit";"Zergling";"Larva";93;1
"Unit";"Zergling";"Larva";93;1
"Unit";"Zergling";"Larva";93;1
"Unit";"Zergling";"Larva";93;1
"Unit";"Zergling";"Larva";93;1
"Unit";"Zergling";"Larva";93;1
"Unit";"Zergling";"Larva";93;1
"Unit";"Zergling";"Larva";93;1
"Unit";"Zergling";"Larva";93;1
"Unit";"Zergling";"Larva";93;1
"Unit";"Zergling";"Larva";93;1
"Unit";"Zergling";"Larva";93;1
"Unit";"Queen";"Hatchery";78;2
"Unit";"Queen";"Hatchery";80;2
"Unit";"Queen";"Hatchery";93;2
"Building";"CreepTumor";NA;130;0
"Building";"EvolutionChamber";NA;127;0
"Building";"CreepTumor";NA;134;0
"Building";"CreepTumor";NA;134;0
"Building";"HydraliskDen";NA;127;0
"Unit";"Overlord";"Larva";134;0
"Unit";"Overlord";"Larva";134;0
"Unit";"Overlord";"Larva";134;0
"Building";"EvolutionChamber";NA;135;0
"Building";"CreepTumor";NA;140;0
"Building";"CreepTumor";NA;140;0
"Unit";"Hydralisk";"Larva";139;2
"Unit";"Hydralisk";"Larva";139;2
"Building";"CreepTumor";NA;140;0
"Unit";"Queen";"Hatchery";137;2
"Unit";"Hydralisk";"Larva";140;2
"Unit";"Hydralisk";"Larva";140;2
"Unit";"Hydralisk";"Larva";140;2
"Unit";"Hydralisk";"Larva";140;2
"Unit";"Hydralisk";"Larva";140;2
"Unit";"Hydralisk";"Larva";140;2
"Building";"Extractor";NA;140;0
"Building";"CreepTumor";NA;147;0
"Building";"CreepTumor";NA;147;0
"Building";"Extractor";NA;144;0
"Building";"Hatchery";NA;134;0
"Building";"CreepTumor";NA;153;0
"Unit";"Hydralisk";"Larva";147;2
"Building";"CreepTumor";NA;166;0
"Unit";"Hydralisk";"Larva";166;2
"Unit";"Hydralisk";"Larva";166;2
"Unit";"Hydralisk";"Larva";166;2
"Unit";"Hydralisk";"Larva";166;2
"Unit";"Overlord";"Larva";166;0
"Upgrade";"EvolveGroovedSpines";"HydraliskDen";140;0
"Unit";"Roach";"Larva";169;2
"Unit";"Hydralisk";"Larva";168;2
"Unit";"Hydralisk";"Larva";168;2
"Unit";"Hydralisk";"Larva";168;2
"Unit";"Overlord";"Larva";169;0
"Unit";"Hydralisk";"Larva";169;2
"Unit";"Hydralisk";"Larva";169;2
"Unit";"Overlord";"Larva";177;0
"Unit";"Overlord";"Larva";177;0
"Unit";"Overlord";"Larva";177;0
"Unit";"Hydralisk";"Larva";185;2
"Unit";"Hydralisk";"Larva";185;2
"Unit";"Hydralisk";"Larva";185;2
"Unit";"Hydralisk";"Larva";185;2
"Upgrade";"ZergMissileWeaponsLevel1";"EvolutionChamber";147;0
"Unit";"Hydralisk";"Larva";189;2
"Unit";"Hydralisk";"Larva";189;2
"Unit";"Hydralisk";"Larva";189;2
"Unit";"Hydralisk";"Larva";189;2
"Unit";"Hydralisk";"Larva";189;2
"Unit";"Hydralisk";"Larva";189;2
"Unit";"Hydralisk";"Larva";189;2
"Unit";"Hydralisk";"Larva";189;2
"Unit";"Hydralisk";"Larva";189;2
"Unit";"Zergling";"Larva";197;1
"Unit";"Zergling";"Larva";197;1
"Unit";"Zergling";"Larva";197;1
"Unit";"Zergling";"Larva";197;1
"Unit";"Zergling";"Larva";197;1
"Unit";"Zergling";"Larva";197;1
"Unit";"Zergling";"Larva";197;1
"Unit";"Zergling";"Larva";197;1
"Unit";"Zergling";"Larva";197;1
"Unit";"Zergling";"Larva";197;1
"Unit";"Zergling";"Larva";197;1
"Unit";"Zergling";"Larva";197;1
"Upgrade";"ZergGroundArmorsLevel1";"EvolutionChamber";166;0
"Building";"LurkerDenMP";NA;166;0
"Unit";"Hydralisk";"Larva";197;2
"Unit";"Hydralisk";"Larva";197;2
"Unit";"Roach";"Larva";197;2
"Unit";"Roach";"Larva";197;2
"Upgrade";"EvolveMuscularAugments";"HydraliskDen";189;0
"Unit";"Hydralisk";"Larva";197;2
"Unit";"Hydralisk";"Larva";197;2
"Unit";"Hydralisk";"Larva";209;2
"Unit";"Hydralisk";"Larva";209;2
"Unit";"Hydralisk";"Larva";231;2
"Unit";"Hydralisk";"Larva";231;2
"Unit";"Hydralisk";"Larva";231;2
"Building";"CreepTumor";NA;243;0
"Unit";"Overlord";"Larva";243;0
"Unit";"Hydralisk";"Larva";244;2
"Unit";"Hydralisk";"Larva";244;2
"Unit";"Hydralisk";"Larva";244;2
"Unit";"Hydralisk";"Larva";244;2
"Unit";"Zergling";"Larva";250;1
"Unit";"Zergling";"Larva";250;1
"Unit";"Hydralisk";"Larva";250;2
"Unit";"Hydralisk";"Larva";250;2
"Unit";"Hydralisk";"Larva";250;2
"Unit";"Zergling";"Larva";260;1
"Unit";"Zergling";"Larva";260;1
"Unit";"Hydralisk";"Larva";260;2
"Unit";"Hydralisk";"Larva";260;2
"Unit";"Hydralisk";"Larva";260;2
"Unit";"Hydralisk";"Larva";260;2
"Unit";"Hydralisk";"Larva";260;2
"Building";"Hatchery";NA;244;0
"Unit";"Hydralisk";"Larva";266;2
"Unit";"Hydralisk";"Larva";266;2
"Unit";"Hydralisk";"Larva";268;2
"Unit";"Hydralisk";"Larva";270;2
"Unit";"Hydralisk";"Larva";270;2
"Unit";"Hydralisk";"Larva";270;2
