"type";"unit_name";"on_building";"total_supply";"supply"
"Unit";"Overlord";"Larva";12;0
"Building";"Extractor";NA;18;0
"Building";"SpawningPool";NA;18;0
"Building";"Hatchery";NA;16;0
"Unit";"Overlord";"Larva";22;0
"Unit";"Zergling";"Larva";22;1
"Unit";"Zergling";"Larva";22;1
"Unit";"Queen";"Hatchery";22;2
"Unit";"Queen";"Hatchery";22;2
"Building";"CreepTumorQueen";NA;34;0
"Unit";"Overlord";"Larva";34;0
"Unit";"Queen";"Hatchery";33;2
"Building";"CreepTumor";NA;34;0
"Building";"CreepTumorQueen";NA;44;0
"Building";"Extractor";NA;47;0
"Building";"Extractor";NA;47;0
"Unit";"Overlord";"Larva";47;0
"Unit";"Overlord";"Larva";47;0
"Building";"CreepTumor";NA;49;0
"Building";"CreepTumorQueen";NA;49;0
"Building";"Hatchery";NA;34;0
"Building";"CreepTumor";NA;49;0
"Unit";"Overlord";"Larva";49;0
"Building";"RoachWarren";NA;47;0
"Building";"CreepTumor";NA;54;0
"Building";"CreepTumor";NA;54;0
"Building";"CreepTumor";NA;54;0
"Unit";"Overlord";"Larva";56;0
"Unit";"Roach";"Larva";56;2
"Unit";"Roach";"Larva";56;2
"Unit";"Roach";"Larva";56;2
"Building";"Extractor";NA;56;0
"Unit";"Roach";"Larva";56;2
"Unit";"Roach";"Larva";56;2
"Unit";"Roach";"Larva";56;2
"Unit";"Roach";"Larva";56;2
"Unit";"Roach";"Larva";56;2
"Building";"CreepTumor";NA;58;0
"Building";"CreepTumor";NA;58;0
"Unit";"Overlord";"Larva";64;0
"Unit";"Roach";"Larva";64;2
"Unit";"Roach";"Larva";64;2
"Unit";"Roach";"Larva";64;2
"Unit";"Roach";"Larva";64;2
"Unit";"Overlord";"Larva";64;0
"Unit";"Overlord";"Larva";64;0
"Building";"CreepTumor";NA;83;0
"Building";"CreepTumor";NA;83;0
"Building";"CreepTumor";NA;83;0
"Unit";"Roach";"Larva";83;2
"Unit";"Roach";"Larva";83;2
"Unit";"Roach";"Larva";100;2
"Building";"HydraliskDen";NA;83;0
"Unit";"Overlord";"Larva";106;0
"Unit";"Overlord";"Larva";106;0
"Building";"Extractor";NA;106;0
"Building";"Extractor";NA;106;0
"Unit";"Overlord";"Larva";108;0
"Unit";"Overlord";"Larva";108;0
"Building";"CreepTumor";NA;110;0
"Building";"CreepTumor";NA;110;0
"Building";"EvolutionChamber";NA;108;0
"Building";"EvolutionChamber";NA;108;0
"Unit";"Overlord";"Larva";116;0
"Unit";"Overlord";"Larva";116;0
"Building";"CreepTumor";NA;116;0
"Unit";"Hydralisk";"Larva";116;2
"Unit";"Hydralisk";"Larva";116;2
"Unit";"Hydralisk";"Larva";116;2
"Unit";"Hydralisk";"Larva";116;2
"Unit";"Hydralisk";"Larva";116;2
"Unit";"Hydralisk";"Larva";116;2
"Unit";"Overlord";"Larva";116;0
"Unit";"Overlord";"Larva";116;0
"Unit";"Overlord";"Larva";116;0
"Unit";"Hydralisk";"Larva";116;2
"Unit";"Hydralisk";"Larva";128;2
"Unit";"Hydralisk";"Larva";128;2
"Unit";"Hydralisk";"Larva";128;2
"Unit";"Overlord";"Larva";128;0
"Unit";"Overlord";"Larva";128;0
"Unit";"Hydralisk";"Larva";128;2
"Unit";"Hydralisk";"Larva";128;2
"Unit";"Hydralisk";"Larva";128;2
"Unit";"Hydralisk";"Larva";128;2
"Upgrade";"EvolveGroovedSpines";"HydraliskDen";116;0
"Unit";"Hydralisk";"Larva";136;2
"Unit";"Hydralisk";"Larva";136;2
"Unit";"Hydralisk";"Larva";136;2
"Unit";"Hydralisk";"Larva";136;2
"Unit";"Hydralisk";"Larva";136;2
"Unit";"Hydralisk";"Larva";136;2
"Unit";"Hydralisk";"Larva";136;2
"Unit";"Hydralisk";"Larva";136;2
"Unit";"Hydralisk";"Larva";144;2
"Building";"Hatchery";NA;116;0
"Unit";"Hydralisk";"Larva";146;2
"Unit";"Hydralisk";"Larva";152;2
"Unit";"Hydralisk";"Larva";154;2
"Unit";"Hydralisk";"Larva";158;2
"Unit";"Hydralisk";"Larva";158;2
"Unit";"Hydralisk";"Larva";158;2
"Unit";"Hydralisk";"Larva";160;2
"Unit";"Hydralisk";"Larva";160;2
"Unit";"Hydralisk";"Larva";160;2
"Unit";"Overlord";"Larva";162;0
"Unit";"Overlord";"Larva";162;0
"Unit";"Overlord";"Larva";162;0
"Unit";"Overlord";"Larva";162;0
"Unit";"Overlord";"Larva";162;0
"Unit";"Hydralisk";"Larva";162;2
"Unit";"Hydralisk";"Larva";162;2
"Unit";"Hydralisk";"Larva";162;2
"Upgrade";"ZergMissileWeaponsLevel1";"EvolutionChamber";134;0
"Upgrade";"ZergGroundArmorsLevel1";"EvolutionChamber";136;0
"Building";"LurkerDenMP";NA;130;0
"Upgrade";"EvolveMuscularAugments";"HydraliskDen";164;0
"Unit";"Hydralisk";"Larva";186;2
"Unit";"Hydralisk";"Larva";186;2
"Unit";"Hydralisk";"Larva";186;2
"Unit";"Hydralisk";"Larva";186;2
"Unit";"Hydralisk";"Larva";186;2
"Unit";"Hydralisk";"Larva";186;2
"Unit";"Hydralisk";"Larva";186;2
"Unit";"Hydralisk";"Larva";186;2
"Unit";"Hydralisk";"Larva";186;2
"Unit";"Hydralisk";"Larva";186;2
"Unit";"Hydralisk";"Larva";186;2
"Unit";"Hydralisk";"Larva";186;2
"Unit";"Hydralisk";"Larva";186;2
"Unit";"Hydralisk";"Larva";186;2
"Unit";"Hydralisk";"Larva";186;2
"Unit";"Hydralisk";"Larva";186;2
"Unit";"Hydralisk";"Larva";186;2
"Unit";"Hydralisk";"Larva";186;2
"Unit";"Hydralisk";"Larva";186;2
"Unit";"Hydralisk";"Larva";186;2
"Unit";"Hydralisk";"Larva";186;2
"Unit";"Hydralisk";"Larva";186;2
"Unit";"Hydralisk";"Larva";186;2
"Unit";"Hydralisk";"Larva";186;2
"Unit";"Hydralisk";"Larva";204;2
"Unit";"Hydralisk";"Larva";224;2
"Unit";"Hydralisk";"Larva";224;2
"Unit";"Zergling";"Larva";224;1
"Unit";"Zergling";"Larva";224;1
"Unit";"Zergling";"Larva";224;1
"Unit";"Zergling";"Larva";224;1
"Unit";"Zergling";"Larva";224;1
"Unit";"Zergling";"Larva";224;1
"Building";"CreepTumor";NA;236;0
"Unit";"Zergling";"Larva";236;1
"Unit";"Zergling";"Larva";236;1
"Unit";"Zergling";"Larva";236;1
"Unit";"Zergling";"Larva";236;1
"Unit";"Zergling";"Larva";236;1
"Unit";"Zergling";"Larva";236;1
"Unit";"Zergling";"Larva";236;1
"Unit";"Zergling";"Larva";236;1
"Unit";"Zergling";"Larva";246;1
"Unit";"Zergling";"Larva";246;1
"Unit";"Zergling";"Larva";246;1
"Unit";"Zergling";"Larva";246;1
"Unit";"Zergling";"Larva";246;1
"Unit";"Zergling";"Larva";246;1
"Unit";"Zergling";"Larva";246;1
"Unit";"Zergling";"Larva";246;1
"Unit";"Zergling";"Larva";246;1
"Unit";"Zergling";"Larva";246;1
"Unit";"Zergling";"Larva";246;1
"Unit";"Zergling";"Larva";246;1
"Unit";"Zergling";"Larva";246;1
"Unit";"Zergling";"Larva";246;1
"Unit";"Zergling";"Larva";246;1
"Unit";"Zergling";"Larva";246;1
"Unit";"Hydralisk";"Larva";246;2
"Unit";"Hydralisk";"Larva";272;2
"Unit";"Hydralisk";"Larva";272;2
"Unit";"Hydralisk";"Larva";272;2
"Unit";"Hydralisk";"Larva";272;2
"Unit";"Hydralisk";"Larva";272;2
"Unit";"Hydralisk";"Larva";272;2
"Unit";"Hydralisk";"Larva";272;2
"Unit";"Hydralisk";"Larva";272;2
"Building";"Hatchery";NA;236;0
"Unit";"Hydralisk";"Larva";288;2
"Unit";"Hydralisk";"Larva";288;2
"Unit";"Hydralisk";"Larva";288;2
"Unit";"Hydralisk";"Larva";288;2
"Unit";"Hydralisk";"Larva";288;2
"Unit";"Hydralisk";"Larva";288;2
"Unit";"Hydralisk";"Larva";288;2
"Unit";"Hydralisk";"Larva";288;2
"Unit";"Hydralisk";"Larva";288;2
"Unit";"Hydralisk";"Larva";288;2
"Unit";"Hydralisk";"Larva";288;2
"Unit";"Hydralisk";"Larva";288;2
"Unit";"Hydralisk";"Larva";312;2
"Unit";"Hydralisk";"Larva";312;2
"Unit";"Hydralisk";"Larva";312;2
"Unit";"Hydralisk";"Larva";312;2
"Unit";"Hydralisk";"Larva";312;2
"Unit";"Hydralisk";"Larva";312;2
"Unit";"Hydralisk";"Larva";312;2
"Unit";"Zergling";"Larva";312;1
"Unit";"Zergling";"Larva";312;1
"Unit";"Zergling";"Larva";312;1
"Unit";"Zergling";"Larva";312;1
"Unit";"Zergling";"Larva";312;1
"Unit";"Zergling";"Larva";312;1
"Unit";"Zergling";"Larva";312;1
"Unit";"Zergling";"Larva";312;1
"Unit";"Zergling";"Larva";312;1
"Unit";"Zergling";"Larva";312;1
"Unit";"Zergling";"Larva";312;1
"Unit";"Zergling";"Larva";312;1
"Unit";"Zergling";"Larva";312;1
"Unit";"Zergling";"Larva";312;1
"Unit";"Zergling";"Larva";312;1
"Unit";"Zergling";"Larva";312;1
"Unit";"Zergling";"Larva";312;1
"Unit";"Zergling";"Larva";312;1
"Unit";"Zergling";"Larva";312;1
"Unit";"Zergling";"Larva";312;1
"Unit";"Zergling";"Larva";312;1
"Unit";"Zergling";"Larva";312;1
"Unit";"Zergling";"Larva";312;1
"Unit";"Zergling";"Larva";312;1
"Unit";"Zergling";"Larva";312;1
"Unit";"Zergling";"Larva";312;1
"Unit";"Zergling";"Larva";312;1
"Unit";"Zergling";"Larva";312;1
