"type";"unit_name";"on_building";"total_supply_lag";"supply"
"Unit";"Overlord";"Larva";13;0
"Building";"Hatchery";NA;16;0
"Building";"Extractor";NA;18;0
"Building";"SpawningPool";NA;18;0
"Unit";"Overlord";"Larva";21;0
"Unit";"Queen";"Hatchery";22;2
"Unit";"Zergling";"Larva";24;1
"Unit";"Zergling";"Larva";25;1
"Unit";"Queen";"Hatchery";26;2
"Unit";"Zergling";"Larva";28;1
"Unit";"Zergling";"Larva";29;1
"Building";"Hatchery";NA;35;0
"Building";"CreepTumorQueen";NA;35;0
"Unit";"Overlord";"Larva";37;0
"Unit";"Zergling";"Larva";39;1
"Unit";"Zergling";"Larva";40;1
"Unit";"Queen";"Hatchery";41;2
"Unit";"Zergling";"Larva";44;1
"Unit";"Zergling";"Larva";45;1
"Unit";"Zergling";"Larva";46;1
"Unit";"Zergling";"Larva";47;1
"Unit";"Overlord";"Larva";48;0
"Building";"CreepTumor";NA;50;0
"Unit";"Overlord";"Larva";50;0
"Unit";"Overlord";"Larva";50;0
"Building";"SporeCrawler";NA;50;0
"Building";"SporeCrawler";NA;50;0
"Building";"CreepTumor";NA;53;0
"Unit";"Queen";"Hatchery";53;2
"Building";"SporeCrawler";NA;66;0
"Building";"CreepTumor";NA;66;0
"Unit";"Zergling";"Larva";67;1
"Unit";"Zergling";"Larva";68;1
"Unit";"Zergling";"Larva";69;1
"Unit";"Zergling";"Larva";70;1
"Building";"CreepTumorQueen";NA;71;0
"Building";"Extractor";NA;72;0
"Building";"EvolutionChamber";NA;73;0
"Unit";"Overlord";"Larva";74;0
"Unit";"Overlord";"Larva";75;0
"Building";"CreepTumorQueen";NA;78;0
"Building";"CreepTumor";NA;78;0
"Building";"BanelingNest";NA;82;0
"Building";"Extractor";NA;83;0
"Building";"Extractor";NA;83;0
"Unit";"Overlord";"Larva";87;0
"Unit";"Zergling";"Larva";87;1
"Unit";"Zergling";"Larva";88;1
"Unit";"Zergling";"Larva";89;1
"Unit";"Zergling";"Larva";90;1
"Unit";"Zergling";"Larva";91;1
"Unit";"Zergling";"Larva";92;1
"Building";"Extractor";NA;93;0
"Building";"HydraliskDen";NA;93;0
"Unit";"Overlord";"Larva";96;0
"Unit";"Overlord";"Larva";96;0
"Unit";"Zergling";"Larva";96;1
"Unit";"Zergling";"Larva";97;1
"Unit";"Zergling";"Larva";98;1
"Unit";"Zergling";"Larva";99;1
"Unit";"Zergling";"Larva";100;1
"Unit";"Zergling";"Larva";101;1
"Unit";"Zergling";"Larva";102;1
"Unit";"Zergling";"Larva";103;1
"Unit";"Zergling";"Larva";104;1
"Unit";"Zergling";"Larva";105;1
"Unit";"Overlord";"Larva";106;0
"Unit";"Overlord";"Larva";106;0
"Unit";"Overlord";"Larva";106;0
"Unit";"Overlord";"Larva";106;0
"Unit";"Overlord";"Larva";106;0
"Building";"CreepTumor";NA;106;0
"Building";"CreepTumor";NA;106;0
"Unit";"Hydralisk";"Larva";106;2
"Unit";"Hydralisk";"Larva";108;2
"Unit";"Hydralisk";"Larva";110;2
"Unit";"Hydralisk";"Larva";112;2
"Building";"CreepTumor";NA;114;0
"Unit";"Hydralisk";"Larva";114;2
"Unit";"Hydralisk";"Larva";116;2
"Unit";"Hydralisk";"Larva";119;2
"Unit";"Hydralisk";"Larva";123;2
"Unit";"Hydralisk";"Larva";125;2
"Unit";"Hydralisk";"Larva";127;2
"Unit";"Hydralisk";"Larva";129;2
"Building";"CreepTumor";NA;131;0
"Building";"CreepTumor";NA;131;0
"Unit";"Hydralisk";"Larva";131;2
"Unit";"Hydralisk";"Larva";133;2
"Unit";"Hydralisk";"Larva";135;2
"Unit";"Overlord";"Larva";137;0
"Unit";"Hydralisk";"Larva";137;2
"Unit";"Hydralisk";"Larva";139;2
"Unit";"Hydralisk";"Larva";141;2
"Unit";"Zergling";"Larva";143;1
"Unit";"Zergling";"Larva";144;1
"Unit";"Zergling";"Larva";145;1
"Unit";"Zergling";"Larva";146;1
"Building";"CreepTumor";NA;147;0
"Unit";"Overlord";"Larva";147;0
"Unit";"Overlord";"Larva";147;0
"Unit";"Zergling";"Larva";147;1
"Unit";"Zergling";"Larva";148;1
"Unit";"Zergling";"Larva";149;1
"Unit";"Zergling";"Larva";150;1
"Unit";"Zergling";"Larva";151;1
"Unit";"Zergling";"Larva";152;1
"Unit";"Zergling";"Larva";153;1
"Unit";"Zergling";"Larva";154;1
"Unit";"Zergling";"Larva";155;1
"Unit";"Zergling";"Larva";156;1
"Unit";"Zergling";"Larva";157;1
"Unit";"Zergling";"Larva";158;1
"Unit";"Zergling";"Larva";159;1
"Unit";"Zergling";"Larva";160;1
"Unit";"Zergling";"Larva";161;1
"Unit";"Zergling";"Larva";162;1
"Unit";"Zergling";"Larva";163;1
"Unit";"Zergling";"Larva";164;1
"Unit";"Baneling";"Zergling";165;0
"Unit";"Baneling";"Zergling";165;0
"Unit";"Baneling";"Zergling";165;0
"Unit";"Baneling";"Zergling";165;0
"Unit";"Baneling";"Zergling";165;0
"Unit";"Baneling";"Zergling";165;0
"Unit";"Baneling";"Zergling";165;0
"Unit";"Baneling";"Zergling";165;0
"Unit";"Zergling";"Larva";165;1
"Unit";"Zergling";"Larva";166;1
"Unit";"Baneling";"Zergling";167;0
"Unit";"Baneling";"Zergling";167;0
"Unit";"Baneling";"Zergling";167;0
"Unit";"Baneling";"Zergling";167;0
"Unit";"Baneling";"Zergling";167;0
"Unit";"Baneling";"Zergling";167;0
"Unit";"Baneling";"Zergling";167;0
"Unit";"Baneling";"Zergling";167;0
"Unit";"Baneling";"Zergling";167;0
"Unit";"Baneling";"Zergling";167;0
"Unit";"Baneling";"Zergling";167;0
"Unit";"Baneling";"Zergling";167;0
"Unit";"Baneling";"Zergling";167;0
"Upgrade";"SprayZerg";NA;167;0
"Upgrade";"SprayZerg";NA;167;0
"Upgrade";"SprayZerg";NA;167;0
"Upgrade";"zerglingmovementspeed";NA;167;0
"Upgrade";"SprayZerg";NA;167;0
"Upgrade";"ZergMissileWeaponsLevel1";NA;167;0
"Upgrade";"EvolveMuscularAugments";NA;167;0
