"type";"unit_name";"on_building";"total_supply";"supply"
"Unit";"Overlord";"Larva";13;0
"Building";"Extractor";NA;18;0
"Building";"Hatchery";NA;16;0
"Building";"SpawningPool";NA;19;0
"Unit";"Overlord";"Larva";22;0
"Unit";"Zergling";"Larva";22;1
"Unit";"Zergling";"Larva";22;1
"Unit";"Zergling";"Larva";22;1
"Unit";"Zergling";"Larva";22;1
"Unit";"Queen";"Hatchery";22;2
"Unit";"Queen";"Hatchery";22;2
"Unit";"Overlord";"Larva";35;0
"Building";"CreepTumorQueen";NA;39;0
"Unit";"Zergling";"Larva";42;1
"Unit";"Zergling";"Larva";42;1
"Unit";"Overlord";"Larva";42;0
"Unit";"Zergling";"Larva";42;1
"Unit";"Zergling";"Larva";42;1
"Building";"Hatchery";NA;35;0
"Building";"Extractor";NA;51;0
"Building";"Extractor";NA;51;0
"Unit";"Overlord";"Larva";54;0
"Building";"CreepTumor";NA;59;0
"Unit";"Overlord";"Larva";59;0
"Building";"CreepTumorQueen";NA;61;0
"Unit";"Overlord";"Larva";61;0
"Unit";"Queen";"Hatchery";54;2
"Unit";"Queen";"Hatchery";54;2
"Building";"RoachWarren";NA;54;0
"Unit";"Zergling";"Larva";61;1
"Unit";"Zergling";"Larva";61;1
"Unit";"Zergling";"Larva";61;1
"Unit";"Zergling";"Larva";61;1
"Unit";"Zergling";"Larva";61;1
"Unit";"Zergling";"Larva";61;1
"Unit";"Zergling";"Larva";61;1
"Unit";"Zergling";"Larva";61;1
"Unit";"Zergling";"Larva";61;1
"Unit";"Zergling";"Larva";61;1
"Unit";"Zergling";"Larva";61;1
"Unit";"Zergling";"Larva";61;1
"Unit";"Zergling";"Larva";61;1
"Unit";"Zergling";"Larva";61;1
"Unit";"Overlord";"Larva";61;0
"Unit";"Roach";"Larva";65;2
"Unit";"Roach";"Larva";65;2
"Unit";"Roach";"Larva";65;2
"Building";"CreepTumorQueen";NA;79;0
"Unit";"Roach";"Larva";65;2
"Unit";"Roach";"Larva";65;2
"Building";"CreepTumor";NA;79;0
"Unit";"Roach";"Larva";79;2
"Unit";"Roach";"Larva";79;2
"Unit";"Roach";"Larva";79;2
"Unit";"Roach";"Larva";79;2
"Unit";"Queen";"Hatchery";65;2
"Unit";"Roach";"Larva";85;2
"Unit";"Roach";"Larva";87;2
"Building";"CreepTumor";NA;112;0
"Upgrade";"GlialReconstitution";"RoachWarren";89;0
"Unit";"Overlord";"Larva";112;0
"Building";"CreepTumor";NA;116;0
"Building";"CreepTumor";NA;116;0
"Building";"EvolutionChamber";NA;116;0
"Unit";"Overlord";"Larva";121;0
"Unit";"Overlord";"Larva";121;0
"Unit";"Overlord";"Larva";121;0
"Unit";"Queen";"Hatchery";116;2
"Unit";"Queen";"Hatchery";121;2
"Building";"CreepTumor";NA;122;0
"Building";"Extractor";NA;122;0
"Building";"Extractor";NA;122;0
"Building";"CreepTumor";NA;132;0
"Building";"CreepTumor";NA;135;0
"Unit";"Overlord";"Larva";137;0
"Unit";"Roach";"Larva";137;2
"Unit";"Roach";"Larva";137;2
"Unit";"Roach";"Larva";137;2
"Unit";"Roach";"Larva";137;2
"Unit";"Roach";"Larva";137;2
"Unit";"Roach";"Larva";137;2
"Building";"CreepTumorQueen";NA;137;0
"Building";"CreepTumorQueen";NA;137;0
"Building";"CreepTumorQueen";NA;137;0
"Building";"CreepTumorQueen";NA;137;0
"Unit";"Roach";"Larva";149;2
"Unit";"Roach";"Larva";149;2
"Unit";"Roach";"Larva";149;2
"Unit";"Roach";"Larva";149;2
"Unit";"Roach";"Larva";149;2
"Unit";"Roach";"Larva";149;2
"Unit";"Roach";"Larva";149;2
"Unit";"Roach";"Larva";149;2
"Building";"Spire";NA;122;0
"Building";"CreepTumor";NA;149;0
"Unit";"Overlord";"Larva";149;0
"Unit";"Overlord";"Larva";149;0
"Unit";"Overlord";"Larva";149;0
"Building";"CreepTumor";NA;165;0
"Building";"CreepTumor";NA;165;0
"Building";"CreepTumor";NA;165;0
"Building";"CreepTumor";NA;165;0
"Unit";"Overlord";"Larva";165;0
"Unit";"Overlord";"Larva";165;0
"Unit";"Roach";"Larva";165;2
"Unit";"Roach";"Larva";165;2
"Unit";"Roach";"Larva";165;2
"Unit";"Roach";"Larva";165;2
"Unit";"Roach";"Larva";165;2
"Unit";"Roach";"Larva";165;2
"Unit";"Roach";"Larva";165;2
"Unit";"Overlord";"Larva";165;0
"Unit";"Overlord";"Larva";165;0
"Unit";"Overlord";"Larva";165;0
"Building";"Hatchery";NA;137;0
"Upgrade";"ZergMissileWeaponsLevel1";"EvolutionChamber";137;0
"Unit";"Mutalisk";"Larva";183;2
"Unit";"Mutalisk";"Larva";183;2
"Unit";"Mutalisk";"Larva";183;2
"Unit";"Mutalisk";"Larva";183;2
"Unit";"Mutalisk";"Larva";183;2
"Unit";"Mutalisk";"Larva";183;2
"Unit";"Mutalisk";"Larva";183;2
"Unit";"Mutalisk";"Larva";183;2
"Unit";"Roach";"Larva";206;2
"Unit";"Roach";"Larva";206;2
"Unit";"Roach";"Larva";206;2
"Unit";"Roach";"Larva";206;2
"Unit";"Roach";"Larva";206;2
"Unit";"Queen";"Hatchery";183;2
"Unit";"Roach";"Larva";208;2
"Unit";"Roach";"Larva";208;2
"Building";"Extractor";NA;208;0
"Building";"Extractor";NA;218;0
"Building";"Extractor";NA;218;0
"Unit";"Roach";"Larva";221;2
"Unit";"Roach";"Larva";222;2
"Unit";"Roach";"Larva";233;2
"Unit";"Roach";"Larva";233;2
"Unit";"Roach";"Larva";233;2
"Unit";"Roach";"Larva";233;2
"Unit";"Roach";"Larva";233;2
"Unit";"Roach";"Larva";233;2
"Unit";"Roach";"Larva";233;2
"Unit";"Roach";"Larva";233;2
"Unit";"Roach";"Larva";233;2
"Unit";"Roach";"Larva";233;2
"Unit";"Roach";"Larva";233;2
"Unit";"Roach";"Larva";233;2
"Unit";"Overlord";"Larva";233;0
"Unit";"Overlord";"Larva";233;0
"Unit";"Overlord";"Larva";233;0
"Unit";"Overlord";"Larva";233;0
"Unit";"Roach";"Larva";257;2
"Unit";"Roach";"Larva";257;2
"Unit";"Roach";"Larva";257;2
"Unit";"Roach";"Larva";257;2
"Unit";"Roach";"Larva";257;2
"Unit";"Roach";"Larva";257;2
"Unit";"Roach";"Larva";257;2
"Unit";"Roach";"Larva";257;2
"Unit";"Roach";"Larva";257;2
"Unit";"Roach";"Larva";257;2
"Unit";"Roach";"Larva";257;2
"Unit";"Roach";"Larva";257;2
"Unit";"Roach";"Larva";257;2
"Unit";"Roach";"Larva";257;2
"Unit";"Roach";"Larva";257;2
"Unit";"Roach";"Larva";257;2
"Unit";"Roach";"Larva";257;2
"Unit";"Roach";"Larva";279;2
"Unit";"Roach";"Larva";291;2
"Unit";"Roach";"Larva";291;2
"Unit";"Roach";"Larva";291;2
"Unit";"Roach";"Larva";291;2
"Unit";"Roach";"Larva";291;2
"Unit";"Roach";"Larva";291;2
"Unit";"Roach";"Larva";291;2
"Unit";"Roach";"Larva";291;2
"Unit";"Roach";"Larva";291;2
"Unit";"Roach";"Larva";291;2
"Unit";"Roach";"Larva";291;2
"Unit";"Roach";"Larva";291;2
"Unit";"Roach";"Larva";291;2
"Unit";"Roach";"Larva";293;2
"Unit";"Roach";"Larva";293;2
"Unit";"Roach";"Larva";293;2
"Unit";"Roach";"Larva";293;2
"Unit";"Roach";"Larva";293;2
"Unit";"Roach";"Larva";293;2
"Unit";"Roach";"Larva";293;2
"Upgrade";"ZergMissileWeaponsLevel2";"EvolutionChamber";233;0
"Unit";"Roach";"Larva";293;2
