"type";"unit_name";"on_building";"total_supply";"supply"
"Unit";"Overlord";"Larva";12;0
"Building";"Extractor";NA;18;0
"Building";"SpawningPool";NA;18;0
"Building";"Hatchery";NA;16;0
"Unit";"Zergling";"Larva";24;1
"Unit";"Zergling";"Larva";24;1
"Unit";"Overlord";"Larva";24;0
"Unit";"Queen";"Hatchery";23;2
"Unit";"Queen";"Hatchery";23;2
"Unit";"Overlord";"Larva";34;0
"Building";"CreepTumorQueen";NA;39;0
"Unit";"Queen";"Hatchery";36;2
"Building";"EvolutionChamber";NA;38;0
"Unit";"Zergling";"Larva";44;1
"Unit";"Zergling";"Larva";44;1
"Unit";"Zergling";"Larva";44;1
"Unit";"Zergling";"Larva";44;1
"Unit";"Overlord";"Larva";44;0
"Building";"Hatchery";NA;30;0
"Building";"CreepTumor";NA;48;0
"Building";"CreepTumorQueen";NA;48;0
"Building";"SporeCrawler";NA;46;0
"Building";"SporeCrawler";NA;48;0
"Unit";"Zergling";"Larva";52;1
"Unit";"Zergling";"Larva";52;1
"Unit";"Zergling";"Larva";52;1
"Unit";"Zergling";"Larva";52;1
"Unit";"Zergling";"Larva";54;1
"Unit";"Zergling";"Larva";54;1
"Unit";"Zergling";"Larva";54;1
"Unit";"Zergling";"Larva";54;1
"Unit";"Zergling";"Larva";56;1
"Unit";"Zergling";"Larva";56;1
"Unit";"Zergling";"Larva";56;1
"Unit";"Zergling";"Larva";56;1
"Unit";"Zergling";"Larva";56;1
"Unit";"Zergling";"Larva";56;1
"Unit";"Zergling";"Larva";56;1
"Unit";"Zergling";"Larva";56;1
"Unit";"Zergling";"Larva";56;1
"Unit";"Zergling";"Larva";56;1
"Unit";"Zergling";"Larva";56;1
"Unit";"Zergling";"Larva";56;1
"Unit";"Queen";"Hatchery";52;2
"Unit";"Zergling";"Larva";56;1
"Unit";"Zergling";"Larva";56;1
"Building";"CreepTumorQueen";NA;66;0
"Building";"CreepTumor";NA;68;0
"Building";"CreepTumor";NA;68;0
"Unit";"Overlord";"Larva";66;0
"Unit";"Overlord";"Larva";66;0
"Unit";"Overlord";"Larva";70;0
"Unit";"Zergling";"Larva";80;1
"Unit";"Zergling";"Larva";80;1
"Unit";"Zergling";"Larva";80;1
"Unit";"Zergling";"Larva";80;1
"Unit";"Zergling";"Larva";80;1
"Unit";"Zergling";"Larva";80;1
"Unit";"Zergling";"Larva";80;1
"Unit";"Zergling";"Larva";80;1
"Unit";"Zergling";"Larva";80;1
"Unit";"Zergling";"Larva";80;1
"Unit";"Zergling";"Larva";80;1
"Unit";"Zergling";"Larva";80;1
"Unit";"Zergling";"Larva";88;1
"Unit";"Zergling";"Larva";88;1
"Unit";"Zergling";"Larva";88;1
"Unit";"Zergling";"Larva";88;1
"Unit";"Zergling";"Larva";88;1
"Unit";"Zergling";"Larva";88;1
"Building";"SporeCrawler";NA;88;0
"Building";"CreepTumor";NA;98;0
"Building";"CreepTumor";NA;104;0
"Building";"Extractor";NA;98;0
"Building";"Extractor";NA;98;0
"Building";"BanelingNest";NA;82;0
"Upgrade";"ZergMeleeWeaponsLevel1";"EvolutionChamber";60;0
"Unit";"Zergling";"Larva";114;1
"Unit";"Zergling";"Larva";114;1
"Building";"CreepTumor";NA;123;0
"Unit";"Zergling";"Larva";123;1
"Unit";"Zergling";"Larva";123;1
"Building";"CreepTumor";NA;123;0
"Unit";"Zergling";"Larva";123;1
"Unit";"Zergling";"Larva";123;1
"Unit";"Zergling";"Larva";123;1
"Unit";"Zergling";"Larva";123;1
"Unit";"Zergling";"Larva";123;1
"Unit";"Zergling";"Larva";123;1
"Unit";"Zergling";"Larva";123;1
"Unit";"Zergling";"Larva";123;1
"Building";"CreepTumor";NA;123;0
"Unit";"Overlord";"Larva";123;0
"Unit";"Zergling";"Larva";125;1
"Unit";"Zergling";"Larva";125;1
"Unit";"Overlord";"Larva";125;0
"Building";"Extractor";NA;125;0
"Unit";"Overlord";"Larva";141;0
"Unit";"Zergling";"Larva";142;1
"Unit";"Zergling";"Larva";142;1
"Unit";"Zergling";"Larva";142;1
"Unit";"Zergling";"Larva";142;1
"Unit";"Zergling";"Larva";142;1
"Unit";"Zergling";"Larva";142;1
"Unit";"Zergling";"Larva";142;1
"Unit";"Zergling";"Larva";142;1
"Building";"HydraliskDen";NA;135;0
"Unit";"Zergling";"Larva";142;1
"Unit";"Zergling";"Larva";142;1
"Unit";"Zergling";"Larva";142;1
"Unit";"Zergling";"Larva";142;1
"Unit";"Zergling";"Larva";142;1
"Unit";"Zergling";"Larva";142;1
"Unit";"Zergling";"Larva";142;1
"Unit";"Zergling";"Larva";142;1
"Unit";"Zergling";"Larva";142;1
"Unit";"Zergling";"Larva";142;1
"Unit";"Zergling";"Larva";142;1
"Unit";"Zergling";"Larva";142;1
"Unit";"Zergling";"Larva";142;1
"Unit";"Zergling";"Larva";142;1
"Unit";"Zergling";"Larva";142;1
"Unit";"Zergling";"Larva";142;1
"Unit";"Zergling";"Larva";142;1
"Unit";"Zergling";"Larva";142;1
"Building";"Hatchery";NA;119;0
"Building";"CreepTumor";NA;160;0
"Building";"CreepTumor";NA;160;0
"Unit";"Zergling";"Larva";160;1
"Unit";"Zergling";"Larva";160;1
"Unit";"Zergling";"Larva";160;1
"Unit";"Zergling";"Larva";160;1
"Unit";"Zergling";"Larva";160;1
"Unit";"Zergling";"Larva";160;1
"Unit";"Zergling";"Larva";160;1
"Unit";"Zergling";"Larva";160;1
"Unit";"Zergling";"Larva";160;1
"Unit";"Zergling";"Larva";160;1
"Unit";"Zergling";"Larva";160;1
"Unit";"Zergling";"Larva";160;1
"Unit";"Zergling";"Larva";168;1
"Unit";"Zergling";"Larva";168;1
"Building";"Extractor";NA;180;0
"Building";"Extractor";NA;180;0
"Unit";"Overlord";"Larva";182;0
"Unit";"Zergling";"Larva";182;1
"Unit";"Zergling";"Larva";182;1
"Unit";"Zergling";"Larva";182;1
"Unit";"Zergling";"Larva";182;1
"Unit";"Zergling";"Larva";182;1
"Unit";"Zergling";"Larva";182;1
"Unit";"Zergling";"Larva";182;1
"Unit";"Zergling";"Larva";182;1
"Unit";"Zergling";"Larva";182;1
"Unit";"Zergling";"Larva";182;1
"Building";"Hatchery";NA;142;0
"Unit";"Zergling";"Larva";192;1
"Unit";"Zergling";"Larva";192;1
"Unit";"Zergling";"Larva";192;1
"Unit";"Zergling";"Larva";192;1
"Unit";"Zergling";"Larva";192;1
"Unit";"Zergling";"Larva";192;1
"Unit";"Zergling";"Larva";192;1
"Unit";"Zergling";"Larva";192;1
"Unit";"Zergling";"Larva";192;1
"Unit";"Zergling";"Larva";192;1
"Unit";"Zergling";"Larva";192;1
"Unit";"Zergling";"Larva";192;1
"Unit";"Zergling";"Larva";192;1
"Unit";"Zergling";"Larva";192;1
"Unit";"Zergling";"Larva";202;1
"Unit";"Zergling";"Larva";202;1
"Unit";"Zergling";"Larva";202;1
"Unit";"Zergling";"Larva";202;1
"Unit";"Zergling";"Larva";202;1
"Unit";"Zergling";"Larva";202;1
"Unit";"Zergling";"Larva";202;1
"Unit";"Zergling";"Larva";202;1
"Upgrade";"EvolveMuscularAugments";"HydraliskDen";168;0
