"type";"unit_name";"on_building";"total_supply";"supply"
"Unit";"Overlord";"Larva";13;0
"Building";"Extractor";NA;19;0
"Unit";"Overlord";"Larva";21;0
"Building";"Hatchery";NA;17;0
"Building";"SpawningPool";NA;19;0
"Unit";"Zergling";"Larva";24;1
"Unit";"Zergling";"Larva";24;1
"Unit";"Queen";"Hatchery";22;2
"Unit";"Queen";"Hatchery";22;2
"Unit";"Zergling";"Larva";36;1
"Unit";"Zergling";"Larva";36;1
"Unit";"Zergling";"Larva";36;1
"Unit";"Zergling";"Larva";36;1
"Unit";"Overlord";"Larva";36;0
"Unit";"Queen";"Hatchery";43;2
"Building";"SporeCrawler";NA;43;0
"Building";"SporeCrawler";NA;43;0
"Building";"Hatchery";NA;36;0
"Unit";"Overlord";"Larva";50;0
"Unit";"Overlord";"Larva";50;0
"Unit";"Overlord";"Larva";50;0
"Building";"CreepTumorQueen";NA;52;0
"Unit";"Overlord";"Larva";52;0
"Unit";"Overlord";"Larva";52;0
"Building";"CreepTumorQueen";NA;56;0
"Unit";"Queen";"Hatchery";52;2
"Building";"SporeCrawler";NA;56;0
"Building";"Extractor";NA;56;0
"Building";"Extractor";NA;56;0
"Building";"CreepTumor";NA;61;0
"Unit";"Overlord";"Larva";68;0
"Unit";"Overlord";"Larva";68;0
"Building";"CreepTumor";NA;76;0
"Building";"Extractor";NA;76;0
"Building";"CreepTumor";NA;80;0
"Building";"CreepTumorQueen";NA;80;0
"Building";"Extractor";NA;76;0
"Building";"HydraliskDen";NA;75;0
"Unit";"Overlord";"Larva";80;0
"Unit";"Overlord";"Larva";80;0
"Unit";"Overlord";"Larva";80;0
"Unit";"Overlord";"Larva";80;0
"Unit";"Overlord";"Larva";82;0
"Building";"Extractor";NA;80;0
"Building";"CreepTumor";NA;87;0
"Building";"CreepTumor";NA;90;0
"Building";"CreepTumor";NA;90;0
"Building";"BanelingNest";NA;80;0
"Unit";"Zergling";"Larva";93;1
"Unit";"Zergling";"Larva";93;1
"Unit";"Zergling";"Larva";93;1
"Unit";"Zergling";"Larva";93;1
"Unit";"Hydralisk";"Larva";93;2
"Unit";"Hydralisk";"Larva";93;2
"Unit";"Hydralisk";"Larva";93;2
"Unit";"Hydralisk";"Larva";93;2
"Unit";"Hydralisk";"Larva";93;2
"Unit";"Hydralisk";"Larva";96;2
"Unit";"Hydralisk";"Larva";96;2
"Unit";"Hydralisk";"Larva";96;2
"Unit";"Hydralisk";"Larva";96;2
"Unit";"Zergling";"Larva";113;1
"Unit";"Zergling";"Larva";113;1
"Unit";"Zergling";"Larva";113;1
"Unit";"Zergling";"Larva";113;1
"Upgrade";"EvolveGroovedSpines";"HydraliskDen";93;0
"Unit";"Zergling";"Larva";119;1
"Unit";"Zergling";"Larva";119;1
"Unit";"Zergling";"Larva";121;1
"Unit";"Zergling";"Larva";121;1
"Unit";"Zergling";"Larva";121;1
"Unit";"Zergling";"Larva";121;1
"Unit";"Zergling";"Larva";121;1
"Unit";"Zergling";"Larva";121;1
"Unit";"Zergling";"Larva";121;1
"Unit";"Zergling";"Larva";121;1
"Unit";"Zergling";"Larva";121;1
"Unit";"Zergling";"Larva";121;1
"Unit";"Zergling";"Larva";121;1
"Unit";"Zergling";"Larva";121;1
"Unit";"Zergling";"Larva";121;1
"Unit";"Zergling";"Larva";121;1
"Unit";"Zergling";"Larva";121;1
"Unit";"Zergling";"Larva";121;1
"Unit";"Zergling";"Larva";121;1
"Unit";"Zergling";"Larva";121;1
"Unit";"Zergling";"Larva";125;1
"Unit";"Zergling";"Larva";125;1
"Unit";"Zergling";"Larva";125;1
"Unit";"Zergling";"Larva";125;1
"Building";"CreepTumorQueen";NA;145;0
"Building";"EvolutionChamber";NA;145;0
"Unit";"Hydralisk";"Larva";145;2
"Unit";"Hydralisk";"Larva";145;2
"Unit";"Hydralisk";"Larva";145;2
"Unit";"Hydralisk";"Larva";145;2
"Unit";"Hydralisk";"Larva";145;2
"Unit";"Hydralisk";"Larva";145;2
"Unit";"Hydralisk";"Larva";145;2
"Building";"CreepTumor";NA;149;0
"Building";"CreepTumor";NA;149;0
"Unit";"Overlord";"Larva";149;0
"Unit";"Overlord";"Larva";149;0
"Unit";"Hydralisk";"Larva";149;2
"Unit";"Hydralisk";"Larva";149;2
"Unit";"Hydralisk";"Larva";149;2
"Unit";"Baneling";"Zergling";163;0
"Unit";"Baneling";"Zergling";163;0
"Unit";"Baneling";"Zergling";163;0
"Unit";"Baneling";"Zergling";163;0
"Unit";"Baneling";"Zergling";163;0
"Unit";"Baneling";"Zergling";163;0
"Upgrade";"EvolveMuscularAugments";"HydraliskDen";149;0
"Unit";"Hydralisk";"Larva";163;2
"Unit";"Hydralisk";"Larva";163;2
"Unit";"Hydralisk";"Larva";163;2
"Unit";"Hydralisk";"Larva";163;2
"Unit";"Hydralisk";"Larva";163;2
"Unit";"Hydralisk";"Larva";163;2
"Unit";"Baneling";"Zergling";170;0
"Unit";"Baneling";"Zergling";170;0
"Unit";"Baneling";"Zergling";170;0
"Unit";"Baneling";"Zergling";170;0
"Unit";"Baneling";"Zergling";170;0
"Unit";"Baneling";"Zergling";170;0
"Unit";"Baneling";"Zergling";170;0
"Unit";"Baneling";"Zergling";170;0
"Unit";"Baneling";"Zergling";170;0
"Unit";"Baneling";"Zergling";170;0
"Unit";"Baneling";"Zergling";170;0
"Unit";"Zergling";"Larva";170;1
"Unit";"Zergling";"Larva";170;1
"Unit";"Zergling";"Larva";170;1
"Unit";"Zergling";"Larva";170;1
"Unit";"Zergling";"Larva";170;1
"Unit";"Zergling";"Larva";170;1
"Unit";"Zergling";"Larva";170;1
"Unit";"Zergling";"Larva";170;1
"Unit";"Zergling";"Larva";170;1
"Unit";"Zergling";"Larva";170;1
"Unit";"Zergling";"Larva";170;1
"Unit";"Zergling";"Larva";170;1
"Unit";"Zergling";"Larva";170;1
"Unit";"Zergling";"Larva";170;1
"Unit";"Zergling";"Larva";170;1
"Unit";"Zergling";"Larva";170;1
"Unit";"Zergling";"Larva";170;1
"Unit";"Zergling";"Larva";170;1
"Unit";"Zergling";"Larva";182;1
"Unit";"Zergling";"Larva";182;1
"Unit";"Zergling";"Larva";182;1
"Unit";"Zergling";"Larva";182;1
"Unit";"Zergling";"Larva";182;1
"Unit";"Zergling";"Larva";182;1
"Unit";"Overlord";"Larva";182;0
"Unit";"Overlord";"Larva";182;0
"Unit";"Overlord";"Larva";182;0
"Unit";"Overlord";"Larva";182;0
"Building";"Hatchery";NA;149;0
"Building";"Extractor";NA;200;0
"Building";"Extractor";NA;200;0
"Unit";"Zergling";"Larva";206;1
"Unit";"Zergling";"Larva";206;1
"Unit";"Zergling";"Larva";206;1
"Unit";"Zergling";"Larva";206;1
"Unit";"Zergling";"Larva";206;1
"Unit";"Zergling";"Larva";206;1
"Unit";"Zergling";"Larva";206;1
"Unit";"Zergling";"Larva";206;1
"Unit";"Zergling";"Larva";206;1
"Unit";"Zergling";"Larva";206;1
"Unit";"Zergling";"Larva";206;1
"Unit";"Zergling";"Larva";206;1
"Unit";"Zergling";"Larva";206;1
"Unit";"Zergling";"Larva";206;1
"Unit";"Zergling";"Larva";206;1
"Unit";"Zergling";"Larva";206;1
"Unit";"Zergling";"Larva";206;1
"Unit";"Zergling";"Larva";206;1
"Unit";"Zergling";"Larva";206;1
"Unit";"Zergling";"Larva";206;1
"Unit";"Zergling";"Larva";206;1
"Unit";"Zergling";"Larva";206;1
"Unit";"Zergling";"Larva";206;1
"Unit";"Zergling";"Larva";206;1
"Unit";"Zergling";"Larva";206;1
"Unit";"Zergling";"Larva";206;1
"Unit";"Zergling";"Larva";232;1
"Unit";"Zergling";"Larva";232;1
"Unit";"Zergling";"Larva";232;1
"Unit";"Zergling";"Larva";232;1
"Unit";"Zergling";"Larva";232;1
"Unit";"Zergling";"Larva";232;1
"Unit";"Zergling";"Larva";232;1
"Unit";"Zergling";"Larva";232;1
"Unit";"Zergling";"Larva";232;1
"Unit";"Zergling";"Larva";232;1
"Unit";"Zergling";"Larva";232;1
"Unit";"Zergling";"Larva";232;1
"Unit";"Zergling";"Larva";232;1
"Unit";"Zergling";"Larva";232;1
"Unit";"Zergling";"Larva";232;1
"Unit";"Zergling";"Larva";232;1
"Unit";"Zergling";"Larva";232;1
"Unit";"Zergling";"Larva";232;1
"Unit";"Zergling";"Larva";232;1
"Unit";"Zergling";"Larva";232;1
"Building";"LurkerDenMP";NA;170;0
"Unit";"Baneling";"Zergling";232;0
"Unit";"Baneling";"Zergling";232;0
"Unit";"Baneling";"Zergling";232;0
"Unit";"Baneling";"Zergling";232;0
"Unit";"Baneling";"Zergling";232;0
"Unit";"Baneling";"Zergling";232;0
"Unit";"Baneling";"Zergling";232;0
"Unit";"Baneling";"Zergling";232;0
"Unit";"Baneling";"Zergling";232;0
"Unit";"Baneling";"Zergling";232;0
"Unit";"Baneling";"Zergling";232;0
"Unit";"Hydralisk";"Larva";232;2
"Upgrade";"ZergMeleeWeaponsLevel1";"EvolutionChamber";200;0
"Unit";"Hydralisk";"Larva";232;2
"Unit";"Hydralisk";"Larva";232;2
"Unit";"Hydralisk";"Larva";232;2
"Unit";"Hydralisk";"Larva";232;2
"Unit";"Hydralisk";"Larva";232;2
"Unit";"Hydralisk";"Larva";232;2
"Unit";"Hydralisk";"Larva";232;2
"Unit";"Hydralisk";"Larva";252;2
"Unit";"Hydralisk";"Larva";252;2
"Unit";"Hydralisk";"Larva";252;2
"Unit";"Hydralisk";"Larva";252;2
"Unit";"Hydralisk";"Larva";252;2
"Unit";"Hydralisk";"Larva";252;2
"Unit";"Hydralisk";"Larva";252;2
"Unit";"Hydralisk";"Larva";252;2
"Unit";"Zergling";"Larva";268;1
"Unit";"Zergling";"Larva";268;1
"Unit";"Zergling";"Larva";268;1
"Unit";"Zergling";"Larva";268;1
"Unit";"Zergling";"Larva";268;1
"Unit";"Zergling";"Larva";268;1
"Unit";"Zergling";"Larva";268;1
"Unit";"Zergling";"Larva";268;1
"Unit";"Zergling";"Larva";268;1
"Unit";"Zergling";"Larva";268;1
"Unit";"Zergling";"Larva";268;1
"Unit";"Zergling";"Larva";268;1
"Unit";"Zergling";"Larva";268;1
"Unit";"Zergling";"Larva";268;1
"Unit";"Zergling";"Larva";268;1
"Unit";"Zergling";"Larva";268;1
"Unit";"Zergling";"Larva";268;1
"Unit";"Zergling";"Larva";268;1
"Unit";"Zergling";"Larva";268;1
"Unit";"Zergling";"Larva";268;1
"Unit";"Zergling";"Larva";268;1
"Unit";"Zergling";"Larva";268;1
"Unit";"Zergling";"Larva";306;1
"Unit";"Zergling";"Larva";306;1
"Unit";"Hydralisk";"Larva";284;2
"Unit";"Hydralisk";"Larva";286;2
"Unit";"Hydralisk";"Larva";286;2
"Unit";"Hydralisk";"Larva";292;2
"Unit";"Hydralisk";"Larva";300;2
"Unit";"Hydralisk";"Larva";306;2
"Unit";"Zergling";"Larva";306;1
"Unit";"Zergling";"Larva";306;1
"Unit";"Zergling";"Larva";306;1
"Unit";"Zergling";"Larva";306;1
"Unit";"Zergling";"Larva";306;1
"Unit";"Zergling";"Larva";306;1
"Unit";"Zergling";"Larva";306;1
"Unit";"Zergling";"Larva";306;1
"Unit";"Zergling";"Larva";306;1
"Unit";"Zergling";"Larva";306;1
"Unit";"Zergling";"Larva";306;1
"Unit";"Zergling";"Larva";306;1
"Unit";"Zergling";"Larva";332;1
"Unit";"Zergling";"Larva";332;1
"Unit";"Zergling";"Larva";332;1
"Unit";"Zergling";"Larva";332;1
"Unit";"Zergling";"Larva";332;1
"Unit";"Zergling";"Larva";332;1
"Unit";"Zergling";"Larva";332;1
"Unit";"Zergling";"Larva";332;1
"Unit";"Zergling";"Larva";332;1
"Unit";"Zergling";"Larva";332;1
"Unit";"Zergling";"Larva";332;1
"Unit";"Zergling";"Larva";332;1
"Unit";"Zergling";"Larva";332;1
"Unit";"Zergling";"Larva";332;1
"Unit";"Zergling";"Larva";332;1
"Unit";"Zergling";"Larva";332;1
"Unit";"Zergling";"Larva";332;1
"Unit";"Zergling";"Larva";332;1
"Unit";"Zergling";"Larva";332;1
"Unit";"Zergling";"Larva";332;1
"Unit";"Zergling";"Larva";332;1
"Unit";"Zergling";"Larva";332;1
"Unit";"Zergling";"Larva";332;1
"Unit";"Zergling";"Larva";332;1
"Unit";"Zergling";"Larva";332;1
"Unit";"Zergling";"Larva";332;1
"Unit";"Zergling";"Larva";332;1
"Unit";"Zergling";"Larva";332;1
