"type";"unit_name";"on_building";"total_supply";"supply"
"Unit";"Overlord";"Larva";13;0
"Building";"Extractor";NA;18;0
"Unit";"Overlord";"Larva";21;0
"Building";"SpawningPool";NA;19;0
"Building";"Hatchery";NA;17;0
"Unit";"Zergling";"Larva";22;1
"Unit";"Zergling";"Larva";22;1
"Unit";"Queen";"Hatchery";22;2
"Unit";"Queen";"Hatchery";23;2
"Unit";"Zergling";"Larva";28;1
"Unit";"Zergling";"Larva";28;1
"Building";"CreepTumorQueen";NA;34;0
"Unit";"Overlord";"Larva";36;0
"Unit";"Zergling";"Larva";36;1
"Unit";"Zergling";"Larva";36;1
"Unit";"Queen";"Hatchery";34;2
"Unit";"Overlord";"Larva";36;0
"Building";"CreepTumor";NA;41;0
"Unit";"Overlord";"Larva";41;0
"Unit";"Overlord";"Larva";45;0
"Building";"CreepTumorQueen";NA;47;0
"Building";"Hatchery";NA;32;0
"Building";"CreepTumor";NA;49;0
"Building";"CreepTumorQueen";NA;51;0
"Building";"CreepTumor";NA;51;0
"Unit";"Queen";"Hatchery";47;2
"Building";"CreepTumor";NA;62;0
"Building";"CreepTumor";NA;63;0
"Building";"Extractor";NA;57;0
"Building";"Extractor";NA;57;0
"Building";"CreepTumor";NA;64;0
"Building";"RoachWarren";NA;53;0
"Unit";"Overlord";"Larva";66;0
"Building";"CreepTumorQueen";NA;73;0
"Building";"Extractor";NA;71;0
"Unit";"Overlord";"Larva";75;0
"Building";"CreepTumor";NA;76;0
"Unit";"Roach";"Larva";76;2
"Unit";"Roach";"Larva";76;2
"Unit";"Roach";"Larva";76;2
"Unit";"Roach";"Larva";76;2
"Building";"CreepTumor";NA;76;0
"Unit";"Queen";"Hatchery";73;2
"Unit";"Roach";"Larva";76;2
"Unit";"Overlord";"Larva";76;0
"Unit";"Overlord";"Larva";76;0
"Unit";"Overlord";"Larva";76;0
"Unit";"Roach";"Larva";76;2
"Unit";"Roach";"Larva";76;2
"Unit";"Roach";"Larva";76;2
"Unit";"Roach";"Larva";76;2
"Unit";"Overlord";"Larva";84;0
"Upgrade";"GlialReconstitution";"RoachWarren";76;0
"Building";"Extractor";NA;96;0
"Unit";"Overlord";"Larva";100;0
"Building";"CreepTumor";NA;106;0
"Building";"CreepTumor";NA;106;0
"Unit";"Overlord";"Larva";106;0
"Building";"CreepTumorQueen";NA;111;0
"Building";"CreepTumorQueen";NA;111;0
"Unit";"Roach";"Larva";109;2
"Unit";"Roach";"Larva";109;2
"Unit";"Roach";"Larva";109;2
"Unit";"Roach";"Larva";109;2
"Unit";"Roach";"Larva";109;2
"Unit";"Roach";"Larva";109;2
"Unit";"Roach";"Larva";110;2
"Unit";"Roach";"Larva";110;2
"Unit";"Roach";"Larva";111;2
"Unit";"Roach";"Larva";111;2
"Unit";"Roach";"Larva";111;2
"Unit";"Roach";"Larva";111;2
"Unit";"Roach";"Larva";111;2
"Unit";"Roach";"Larva";111;2
"Unit";"Roach";"Larva";123;2
"Building";"CreepTumor";NA;131;0
"Unit";"Roach";"Larva";127;2
"Unit";"Roach";"Larva";129;2
"Unit";"Roach";"Larva";133;2
"Unit";"Roach";"Larva";133;2
"Unit";"Roach";"Larva";133;2
"Building";"CreepTumor";NA;139;0
"Building";"CreepTumor";NA;139;0
"Building";"CreepTumor";NA;141;0
"Unit";"Overlord";"Larva";137;0
"Building";"CreepTumorQueen";NA;145;0
"Unit";"Roach";"Larva";141;2
"Unit";"Roach";"Larva";141;2
"Unit";"Overlord";"Larva";145;0
"Unit";"Overlord";"Larva";145;0
"Unit";"Roach";"Larva";155;2
"Unit";"Roach";"Larva";155;2
"Unit";"Roach";"Larva";155;2
"Unit";"Roach";"Larva";155;2
"Unit";"Roach";"Larva";155;2
"Unit";"Roach";"Larva";155;2
"Unit";"Roach";"Larva";155;2
"Unit";"Roach";"Larva";155;2
"Unit";"Roach";"Larva";155;2
"Unit";"Zergling";"Larva";155;1
"Unit";"Zergling";"Larva";155;1
"Unit";"Zergling";"Larva";155;1
"Unit";"Zergling";"Larva";155;1
"Unit";"Zergling";"Larva";155;1
"Unit";"Zergling";"Larva";155;1
"Unit";"Roach";"Larva";155;2
"Unit";"Roach";"Larva";155;2
"Unit";"Roach";"Larva";157;2
"Unit";"Zergling";"Larva";165;1
"Unit";"Zergling";"Larva";165;1
"Unit";"Zergling";"Larva";165;1
"Unit";"Zergling";"Larva";165;1
"Unit";"Zergling";"Larva";165;1
"Unit";"Zergling";"Larva";165;1
"Unit";"Zergling";"Larva";165;1
"Unit";"Zergling";"Larva";165;1
"Unit";"Roach";"Larva";181;2
"Unit";"Roach";"Larva";181;2
"Unit";"Roach";"Larva";181;2
"Unit";"Roach";"Larva";181;2
"Building";"HydraliskDen";NA;179;0
"Building";"CreepTumor";NA;193;0
"Building";"CreepTumor";NA;193;0
"Building";"EvolutionChamber";NA;193;0
"Unit";"Roach";"Larva";201;2
"Unit";"Roach";"Larva";201;2
"Unit";"Roach";"Larva";201;2
"Unit";"Roach";"Larva";201;2
"Unit";"Roach";"Larva";201;2
"Unit";"Roach";"Larva";201;2
"Unit";"Roach";"Larva";201;2
"Unit";"Roach";"Larva";201;2
"Building";"CreepTumor";NA;201;0
"Building";"CreepTumor";NA;201;0
"Building";"Extractor";NA;201;0
"Building";"CreepTumor";NA;220;0
"Building";"CreepTumorQueen";NA;224;0
"Building";"CreepTumorQueen";NA;224;0
"Building";"CreepTumorQueen";NA;224;0
"Unit";"Zergling";"Larva";223;1
"Unit";"Zergling";"Larva";223;1
"Unit";"Zergling";"Larva";223;1
"Unit";"Zergling";"Larva";223;1
"Unit";"Zergling";"Larva";223;1
"Unit";"Zergling";"Larva";223;1
"Unit";"Zergling";"Larva";223;1
"Unit";"Zergling";"Larva";223;1
"Unit";"Zergling";"Larva";223;1
"Unit";"Zergling";"Larva";223;1
"Unit";"Zergling";"Larva";223;1
"Unit";"Zergling";"Larva";223;1
"Unit";"Zergling";"Larva";223;1
"Unit";"Zergling";"Larva";223;1
"Unit";"Zergling";"Larva";224;1
"Unit";"Zergling";"Larva";224;1
"Unit";"Zergling";"Larva";224;1
"Unit";"Zergling";"Larva";224;1
"Unit";"Hydralisk";"Larva";224;2
"Unit";"Hydralisk";"Larva";224;2
"Unit";"Hydralisk";"Larva";224;2
"Unit";"Hydralisk";"Larva";224;2
"Building";"Hatchery";NA;201;0
"Building";"CreepTumor";NA;242;0
"Unit";"Overlord";"Larva";242;0
"Building";"CreepTumor";NA;242;0
"Building";"CreepTumor";NA;242;0
"Building";"CreepTumor";NA;242;0
"Unit";"Hydralisk";"Larva";242;2
"Unit";"Overlord";"Larva";242;0
"Unit";"Hydralisk";"Larva";242;2
"Unit";"Hydralisk";"Larva";242;2
"Unit";"Overlord";"Larva";242;0
"Building";"LurkerDenMP";NA;201;0
"Unit";"Roach";"Larva";250;2
"Unit";"Roach";"Larva";250;2
"Unit";"Roach";"Larva";250;2
"Unit";"Roach";"Larva";250;2
"Unit";"Roach";"Larva";250;2
"Unit";"Roach";"Larva";250;2
"Unit";"Hydralisk";"Larva";256;2
"Unit";"Hydralisk";"Larva";256;2
"Unit";"Zergling";"Larva";256;1
"Unit";"Zergling";"Larva";256;1
"Unit";"Zergling";"Larva";256;1
"Unit";"Zergling";"Larva";256;1
"Unit";"Zergling";"Larva";256;1
"Unit";"Zergling";"Larva";256;1
"Unit";"Zergling";"Larva";256;1
"Unit";"Zergling";"Larva";256;1
"Unit";"Zergling";"Larva";256;1
"Unit";"Zergling";"Larva";256;1
"Unit";"Zergling";"Larva";256;1
"Unit";"Zergling";"Larva";256;1
"Building";"CreepTumor";NA;268;0
"Building";"CreepTumor";NA;268;0
"Building";"CreepTumor";NA;268;0
"Building";"CreepTumor";NA;268;0
"Building";"CreepTumor";NA;268;0
"Building";"CreepTumor";NA;268;0
"Upgrade";"ZergMissileWeaponsLevel1";"EvolutionChamber";224;0
"Unit";"Hydralisk";"Larva";284;2
"Unit";"Hydralisk";"Larva";284;2
"Building";"CreepTumorQueen";NA;284;0
"Building";"CreepTumorQueen";NA;284;0
"Unit";"Hydralisk";"Larva";284;2
"Unit";"Hydralisk";"Larva";284;2
"Building";"CreepTumor";NA;284;0
"Building";"CreepTumor";NA;288;0
"Building";"CreepTumor";NA;288;0
"Unit";"Hydralisk";"Larva";297;2
"Unit";"Hydralisk";"Larva";297;2
"Unit";"Hydralisk";"Larva";297;2
"Unit";"Hydralisk";"Larva";297;2
"Unit";"Hydralisk";"Larva";297;2
"Unit";"Hydralisk";"Larva";297;2
"Unit";"Hydralisk";"Larva";297;2
"Unit";"Hydralisk";"Larva";297;2
"Unit";"Zergling";"Larva";297;1
"Unit";"Zergling";"Larva";297;1
"Unit";"Zergling";"Larva";297;1
"Unit";"Zergling";"Larva";297;1
"Unit";"Zergling";"Larva";297;1
"Unit";"Zergling";"Larva";297;1
"Unit";"Zergling";"Larva";297;1
"Unit";"Zergling";"Larva";297;1
"Unit";"Zergling";"Larva";297;1
"Unit";"Zergling";"Larva";297;1
"Unit";"Zergling";"Larva";297;1
"Unit";"Zergling";"Larva";297;1
"Unit";"Zergling";"Larva";297;1
"Unit";"Zergling";"Larva";297;1
"Unit";"Zergling";"Larva";297;1
"Unit";"Zergling";"Larva";297;1
"Upgrade";"EvolveMuscularAugments";"HydraliskDen";284;0
"Building";"CreepTumor";NA;305;0
"Building";"CreepTumor";NA;305;0
"Building";"CreepTumorQueen";NA;313;0
"Building";"CreepTumorQueen";NA;329;0
"Building";"InfestationPit";NA;305;0
"Unit";"Hydralisk";"Larva";329;2
"Unit";"Hydralisk";"Larva";329;2
"Unit";"Hydralisk";"Larva";329;2
"Unit";"Hydralisk";"Larva";329;2
"Unit";"Hydralisk";"Larva";329;2
"Building";"CreepTumor";NA;329;0
"Building";"CreepTumor";NA;329;0
"Building";"CreepTumor";NA;329;0
"Unit";"Overlord";"Larva";329;0
"Building";"CreepTumor";NA;339;0
"Unit";"Hydralisk";"Larva";329;2
"Unit";"Hydralisk";"Larva";329;2
"Unit";"Hydralisk";"Larva";329;2
"Building";"CreepTumor";NA;346;0
"Unit";"Hydralisk";"Larva";346;2
"Unit";"Hydralisk";"Larva";346;2
"Unit";"Hydralisk";"Larva";346;2
"Unit";"Hydralisk";"Larva";346;2
"Unit";"Hydralisk";"Larva";346;2
"Unit";"Hydralisk";"Larva";346;2
"Upgrade";"ZergMissileWeaponsLevel2";"EvolutionChamber";303;0
"Unit";"Zergling";"Larva";358;1
"Unit";"Zergling";"Larva";358;1
"Unit";"Zergling";"Larva";358;1
"Unit";"Zergling";"Larva";358;1
"Unit";"Zergling";"Larva";358;1
"Unit";"Zergling";"Larva";358;1
"Building";"CreepTumor";NA;358;0
"Unit";"Overlord";"Larva";358;0
"Unit";"Overlord";"Larva";358;0
"Unit";"Zergling";"Larva";364;1
"Unit";"Zergling";"Larva";364;1
"Unit";"Zergling";"Larva";364;1
"Unit";"Zergling";"Larva";364;1
"Unit";"Zergling";"Larva";364;1
"Unit";"Zergling";"Larva";364;1
"Unit";"Zergling";"Larva";364;1
"Unit";"Zergling";"Larva";364;1
"Unit";"Zergling";"Larva";364;1
"Unit";"Zergling";"Larva";364;1
"Unit";"Zergling";"Larva";364;1
"Unit";"Zergling";"Larva";364;1
"Unit";"Zergling";"Larva";364;1
"Unit";"Zergling";"Larva";364;1
"Unit";"Zergling";"Larva";364;1
"Unit";"Zergling";"Larva";364;1
"Unit";"Zergling";"Larva";364;1
"Unit";"Zergling";"Larva";364;1
"Unit";"Zergling";"Larva";364;1
"Unit";"Zergling";"Larva";364;1
"Unit";"Zergling";"Larva";364;1
"Unit";"Zergling";"Larva";364;1
"Unit";"Zergling";"Larva";364;1
"Unit";"Zergling";"Larva";364;1
"Unit";"Zergling";"Larva";364;1
"Unit";"Zergling";"Larva";364;1
"Unit";"Zergling";"Larva";364;1
"Unit";"Zergling";"Larva";364;1
"Unit";"Zergling";"Larva";364;1
"Unit";"Zergling";"Larva";364;1
"Unit";"Overlord";"Larva";364;0
"Unit";"Overlord";"Larva";364;0
"Building";"CreepTumor";NA;394;0
"Unit";"Overlord";"Larva";364;0
"Building";"CreepTumorQueen";NA;394;0
"Building";"CreepTumorQueen";NA;395;0
"Building";"CreepTumorQueen";NA;395;0
"Building";"CreepTumor";NA;395;0
"Building";"CreepTumor";NA;395;0
"Building";"Hatchery";NA;358;0
"Building";"Hatchery";NA;358;0
"Building";"CreepTumor";NA;407;0
"Upgrade";"ZergGroundArmorsLevel1";"EvolutionChamber";364;0
"Building";"CreepTumor";NA;407;0
"Unit";"Hydralisk";"Larva";407;2
"Unit";"Hydralisk";"Larva";407;2
"Unit";"Hydralisk";"Larva";407;2
"Unit";"Hydralisk";"Larva";407;2
"Unit";"Hydralisk";"Larva";407;2
"Building";"CreepTumorQueen";NA;407;0
"Building";"CreepTumorQueen";NA;407;0
"Unit";"Hydralisk";"Larva";407;2
"Unit";"Hydralisk";"Larva";407;2
"Unit";"Zergling";"Larva";421;1
"Unit";"Zergling";"Larva";421;1
"Unit";"Zergling";"Larva";421;1
"Unit";"Zergling";"Larva";421;1
"Unit";"Zergling";"Larva";421;1
"Unit";"Zergling";"Larva";421;1
"Unit";"Zergling";"Larva";421;1
"Unit";"Zergling";"Larva";421;1
"Unit";"Zergling";"Larva";421;1
"Unit";"Zergling";"Larva";421;1
"Unit";"Hydralisk";"Larva";421;2
"Unit";"Hydralisk";"Larva";421;2
"Unit";"Hydralisk";"Larva";421;2
"Unit";"Hydralisk";"Larva";421;2
"Unit";"Hydralisk";"Larva";421;2
"Unit";"Hydralisk";"Larva";421;2
"Unit";"Hydralisk";"Larva";421;2
"Unit";"Hydralisk";"Larva";421;2
"Unit";"Hydralisk";"Larva";421;2
"Unit";"Hydralisk";"Larva";421;2
"Unit";"Zergling";"Larva";421;1
"Unit";"Zergling";"Larva";421;1
"Unit";"Zergling";"Larva";421;1
"Unit";"Zergling";"Larva";421;1
"Building";"Hatchery";NA;417;0
