"type";"unit_name";"on_building";"total_supply_lag";"supply"
"Unit";"Overlord";"Larva";13;0
"Building";"Hatchery";NA;16;0
"Building";"Extractor";NA;19;0
"Building";"SpawningPool";NA;19;0
"Building";"Hatchery";NA;23;0
"Unit";"Queen";"Hatchery";25;2
"Unit";"Overlord";"Larva";29;0
"Unit";"Queen";"Hatchery";29;2
"Unit";"Zergling";"Larva";31;1
"Unit";"Zergling";"Larva";32;1
"Unit";"Zergling";"Larva";33;1
"Unit";"Zergling";"Larva";34;1
"Unit";"Zergling";"Larva";35;1
"Unit";"Zergling";"Larva";36;1
"Unit";"Zergling";"Larva";37;1
"Unit";"Zergling";"Larva";38;1
"Unit";"Queen";"Hatchery";41;2
"Unit";"Zergling";"Larva";44;1
"Unit";"Zergling";"Larva";45;1
"Building";"SporeCrawler";NA;54;0
"Building";"SporeCrawler";NA;54;0
"Building";"CreepTumorQueen";NA;56;0
"Unit";"Queen";"Hatchery";56;2
"Unit";"Overlord";"Larva";58;0
"Unit";"Overlord";"Larva";67;0
"Unit";"Overlord";"Larva";67;0
"Building";"CreepTumorQueen";NA;67;0
"Building";"Extractor";NA;67;0
"Unit";"Overlord";"Larva";67;0
"Building";"SporeCrawler";NA;67;0
"Building";"CreepTumor";NA;72;0
"Building";"CreepTumor";NA;76;0
"Building";"BanelingNest";NA;78;0
"Unit";"Zergling";"Larva";82;1
"Unit";"Zergling";"Larva";83;1
"Building";"CreepTumor";NA;84;0
"Unit";"Zergling";"Larva";84;1
"Unit";"Zergling";"Larva";85;1
"Unit";"Zergling";"Larva";86;1
"Unit";"Zergling";"Larva";87;1
"Unit";"Zergling";"Larva";88;1
"Unit";"Zergling";"Larva";89;1
"Unit";"Zergling";"Larva";90;1
"Unit";"Zergling";"Larva";91;1
"Building";"Extractor";NA;92;0
"Unit";"Zergling";"Larva";92;1
"Unit";"Zergling";"Larva";93;1
"Building";"CreepTumor";NA;94;0
"Unit";"Overlord";"Larva";94;0
"Unit";"Overlord";"Larva";94;0
"Unit";"Overlord";"Larva";94;0
"Building";"HydraliskDen";NA;105;0
"Building";"EvolutionChamber";NA;113;0
"Building";"CreepTumor";NA;113;0
"Building";"Extractor";NA;113;0
"Unit";"Zergling";"Larva";113;1
"Unit";"Zergling";"Larva";114;1
"Unit";"Zergling";"Larva";115;1
"Unit";"Zergling";"Larva";116;1
"Unit";"Zergling";"Larva";117;1
"Unit";"Zergling";"Larva";118;1
"Unit";"Zergling";"Larva";119;1
"Unit";"Zergling";"Larva";120;1
"Unit";"Zergling";"Larva";121;1
"Unit";"Zergling";"Larva";122;1
"Unit";"Zergling";"Larva";123;1
"Unit";"Zergling";"Larva";124;1
"Unit";"Zergling";"Larva";125;1
"Unit";"Zergling";"Larva";126;1
"Unit";"Zergling";"Larva";127;1
"Unit";"Zergling";"Larva";128;1
"Unit";"Baneling";"Zergling";129;0
"Unit";"Baneling";"Zergling";129;0
"Unit";"Baneling";"Zergling";129;0
"Unit";"Baneling";"Zergling";129;0
"Unit";"Baneling";"Zergling";129;0
"Unit";"Baneling";"Zergling";129;0
"Unit";"Zergling";"Larva";129;1
"Unit";"Zergling";"Larva";130;1
"Unit";"Baneling";"Zergling";131;0
"Unit";"Baneling";"Zergling";131;0
"Unit";"Zergling";"Larva";131;1
"Unit";"Zergling";"Larva";132;1
"Unit";"Zergling";"Larva";133;1
"Unit";"Zergling";"Larva";134;1
"Unit";"Overlord";"Larva";135;0
"Unit";"Baneling";"Zergling";135;0
"Unit";"Baneling";"Zergling";135;0
"Unit";"Baneling";"Zergling";135;0
"Unit";"Overlord";"Larva";135;0
"Unit";"Overlord";"Larva";135;0
"Unit";"Overlord";"Larva";135;0
"Unit";"Zergling";"Larva";135;1
"Unit";"Zergling";"Larva";136;1
"Unit";"Zergling";"Larva";137;1
"Unit";"Zergling";"Larva";138;1
"Unit";"Zergling";"Larva";139;1
"Unit";"Zergling";"Larva";140;1
"Unit";"Zergling";"Larva";141;1
"Unit";"Zergling";"Larva";142;1
"Unit";"Zergling";"Larva";143;1
"Unit";"Zergling";"Larva";144;1
"Unit";"Zergling";"Larva";145;1
"Unit";"Zergling";"Larva";146;1
"Unit";"Zergling";"Larva";147;1
"Unit";"Zergling";"Larva";148;1
"Unit";"Zergling";"Larva";149;1
"Unit";"Zergling";"Larva";150;1
"Unit";"Zergling";"Larva";151;1
"Unit";"Zergling";"Larva";152;1
"Unit";"Zergling";"Larva";153;1
"Unit";"Zergling";"Larva";154;1
"Unit";"Zergling";"Larva";155;1
"Unit";"Zergling";"Larva";156;1
"Unit";"Queen";"Hatchery";157;2
"Unit";"Queen";"Hatchery";159;2
"Unit";"Queen";"Hatchery";161;2
"Unit";"Zergling";"Larva";163;1
"Unit";"Zergling";"Larva";164;1
"Unit";"Zergling";"Larva";165;1
"Unit";"Zergling";"Larva";166;1
"Unit";"Zergling";"Larva";167;1
"Unit";"Zergling";"Larva";168;1
"Unit";"Zergling";"Larva";169;1
"Unit";"Zergling";"Larva";170;1
"Building";"Hatchery";NA;182;0
"Building";"Extractor";NA;182;0
"Building";"Extractor";NA;182;0
"Building";"CreepTumorQueen";NA;186;0
"Building";"CreepTumor";NA;186;0
"Building";"CreepTumorQueen";NA;186;0
"Unit";"Hydralisk";"Larva";186;2
"Unit";"Hydralisk";"Larva";188;2
"Unit";"Hydralisk";"Larva";190;2
"Unit";"Hydralisk";"Larva";192;2
"Unit";"Hydralisk";"Larva";194;2
"Building";"CreepTumorQueen";NA;196;0
"Building";"CreepTumor";NA;196;0
"Unit";"Hydralisk";"Larva";196;2
"Building";"CreepTumorQueen";NA;198;0
"Unit";"Hydralisk";"Larva";198;2
"Building";"CreepTumorQueen";NA;200;0
"Unit";"Hydralisk";"Larva";200;2
"Building";"CreepTumorQueen";NA;202;0
"Unit";"Hydralisk";"Larva";202;2
"Unit";"Hydralisk";"Larva";204;2
"Unit";"Hydralisk";"Larva";206;2
"Unit";"Hydralisk";"Larva";208;2
"Unit";"Overlord";"Larva";210;0
"Unit";"Hydralisk";"Larva";210;2
"Unit";"Hydralisk";"Larva";212;2
"Building";"CreepTumor";NA;214;0
"Building";"CreepTumor";NA;214;0
"Building";"CreepTumor";NA;214;0
"Building";"CreepTumor";NA;214;0
"Unit";"Overlord";"Larva";214;0
"Building";"CreepTumor";NA;214;0
"Unit";"Overlord";"Larva";214;0
"Building";"CreepTumorQueen";NA;214;0
"Building";"CreepTumorQueen";NA;214;0
"Unit";"Hydralisk";"Larva";214;2
"Unit";"Hydralisk";"Larva";216;2
"Building";"CreepTumor";NA;218;0
"Building";"CreepTumor";NA;218;0
"Unit";"Hydralisk";"Larva";223;2
"Building";"CreepTumorQueen";NA;225;0
"Building";"CreepTumorQueen";NA;225;0
"Unit";"Overlord";"Larva";225;0
"Building";"CreepTumor";NA;225;0
"Unit";"Overlord";"Larva";225;0
"Unit";"Zergling";"Larva";225;1
"Unit";"Zergling";"Larva";226;1
"Unit";"Zergling";"Larva";227;1
"Unit";"Zergling";"Larva";228;1
"Unit";"Zergling";"Larva";229;1
"Unit";"Zergling";"Larva";230;1
"Unit";"Zergling";"Larva";231;1
"Unit";"Zergling";"Larva";232;1
"Unit";"Zergling";"Larva";233;1
"Unit";"Zergling";"Larva";234;1
"Unit";"Zergling";"Larva";235;1
"Unit";"Zergling";"Larva";236;1
"Unit";"Zergling";"Larva";237;1
"Unit";"Zergling";"Larva";238;1
"Unit";"Zergling";"Larva";239;1
"Unit";"Zergling";"Larva";240;1
"Unit";"Zergling";"Larva";241;1
"Unit";"Zergling";"Larva";242;1
"Unit";"Zergling";"Larva";243;1
"Unit";"Zergling";"Larva";244;1
"Unit";"Baneling";"Zergling";245;0
"Unit";"Baneling";"Zergling";245;0
"Unit";"Baneling";"Zergling";245;0
"Unit";"Baneling";"Zergling";245;0
"Unit";"Baneling";"Zergling";245;0
"Unit";"Baneling";"Zergling";245;0
"Unit";"Zergling";"Larva";245;1
"Unit";"Zergling";"Larva";246;1
"Unit";"Zergling";"Larva";247;1
"Unit";"Zergling";"Larva";248;1
"Unit";"Zergling";"Larva";249;1
"Unit";"Zergling";"Larva";250;1
"Unit";"Zergling";"Larva";251;1
"Unit";"Zergling";"Larva";252;1
"Unit";"Zergling";"Larva";253;1
"Unit";"Zergling";"Larva";254;1
"Unit";"Zergling";"Larva";255;1
"Unit";"Zergling";"Larva";256;1
"Unit";"Zergling";"Larva";257;1
"Unit";"Zergling";"Larva";258;1
"Unit";"Zergling";"Larva";259;1
"Unit";"Zergling";"Larva";260;1
"Unit";"Zergling";"Larva";261;1
"Unit";"Zergling";"Larva";262;1
"Unit";"Zergling";"Larva";263;1
"Unit";"Zergling";"Larva";264;1
"Unit";"Zergling";"Larva";265;1
"Unit";"Zergling";"Larva";266;1
"Unit";"Zergling";"Larva";267;1
"Unit";"Zergling";"Larva";268;1
"Building";"Spire";NA;269;0
"Building";"EvolutionChamber";NA;271;0
"Unit";"Zergling";"Larva";271;1
"Unit";"Zergling";"Larva";272;1
"Building";"Extractor";NA;273;0
"Unit";"Zergling";"Larva";273;1
"Unit";"Zergling";"Larva";274;1
"Unit";"Zergling";"Larva";275;1
"Unit";"Zergling";"Larva";276;1
"Unit";"Zergling";"Larva";277;1
"Unit";"Zergling";"Larva";278;1
"Building";"CreepTumor";NA;279;0
"Unit";"Zergling";"Larva";279;1
"Unit";"Zergling";"Larva";280;1
"Building";"CreepTumor";NA;281;0
"Building";"CreepTumor";NA;281;0
"Building";"CreepTumor";NA;281;0
"Building";"CreepTumor";NA;281;0
"Building";"CreepTumor";NA;281;0
"Building";"CreepTumor";NA;281;0
"Unit";"Zergling";"Larva";281;1
"Unit";"Zergling";"Larva";282;1
"Unit";"Zergling";"Larva";283;1
"Unit";"Zergling";"Larva";284;1
"Unit";"Zergling";"Larva";285;1
"Unit";"Zergling";"Larva";286;1
"Unit";"Zergling";"Larva";287;1
"Unit";"Zergling";"Larva";288;1
"Unit";"Zergling";"Larva";289;1
"Unit";"Zergling";"Larva";290;1
"Unit";"Overlord";"Larva";291;0
"Unit";"Queen";"Hatchery";291;2
"Building";"CreepTumor";NA;293;0
"Unit";"Zergling";"Larva";293;1
"Unit";"Zergling";"Larva";294;1
"Unit";"Zergling";"Larva";295;1
"Unit";"Zergling";"Larva";296;1
"Unit";"Zergling";"Larva";297;1
"Unit";"Zergling";"Larva";298;1
"Unit";"Zergling";"Larva";299;1
"Unit";"Zergling";"Larva";300;1
"Unit";"Zergling";"Larva";301;1
"Unit";"Zergling";"Larva";302;1
"Unit";"Zergling";"Larva";303;1
"Unit";"Zergling";"Larva";304;1
"Unit";"Zergling";"Larva";305;1
"Unit";"Zergling";"Larva";306;1
"Unit";"Zergling";"Larva";307;1
"Unit";"Zergling";"Larva";308;1
"Unit";"Zergling";"Larva";309;1
"Unit";"Zergling";"Larva";310;1
"Unit";"Zergling";"Larva";311;1
"Unit";"Zergling";"Larva";312;1
"Unit";"Zergling";"Larva";313;1
"Unit";"Zergling";"Larva";314;1
"Building";"CreepTumor";NA;315;0
"Building";"CreepTumor";NA;315;0
"Building";"CreepTumor";NA;315;0
"Unit";"Baneling";"Zergling";315;0
"Unit";"Baneling";"Zergling";315;0
"Unit";"Baneling";"Zergling";315;0
"Unit";"Baneling";"Zergling";315;0
"Unit";"Baneling";"Zergling";315;0
"Unit";"Baneling";"Zergling";315;0
"Unit";"Baneling";"Zergling";315;0
"Unit";"Baneling";"Zergling";315;0
"Unit";"Baneling";"Zergling";315;0
"Unit";"Baneling";"Zergling";315;0
"Unit";"Baneling";"Zergling";315;0
"Unit";"Baneling";"Zergling";315;0
"Building";"CreepTumor";NA;315;0
"Building";"InfestationPit";NA;317;0
"Unit";"Hydralisk";"Larva";317;2
"Unit";"Hydralisk";"Larva";319;2
"Unit";"Hydralisk";"Larva";321;2
"Building";"CreepTumor";NA;324;0
"Unit";"Baneling";"Zergling";324;0
"Unit";"Baneling";"Zergling";324;0
"Unit";"Baneling";"Zergling";324;0
"Unit";"Baneling";"Zergling";324;0
"Unit";"Baneling";"Zergling";324;0
"Unit";"Baneling";"Zergling";324;0
"Unit";"Baneling";"Zergling";324;0
"Unit";"Baneling";"Zergling";324;0
"Unit";"Baneling";"Zergling";324;0
"Unit";"Baneling";"Zergling";324;0
"Unit";"Baneling";"Zergling";324;0
"Unit";"Baneling";"Zergling";324;0
"Unit";"Baneling";"Zergling";324;0
"Building";"CreepTumorQueen";NA;324;0
"Unit";"Baneling";"Zergling";324;0
"Unit";"Baneling";"Zergling";324;0
"Unit";"Baneling";"Zergling";324;0
"Unit";"Baneling";"Zergling";324;0
"Unit";"Baneling";"Zergling";324;0
"Unit";"Baneling";"Zergling";324;0
"Unit";"Baneling";"Zergling";324;0
"Unit";"Baneling";"Zergling";324;0
"Unit";"Baneling";"Zergling";324;0
"Unit";"Baneling";"Zergling";324;0
"Unit";"Baneling";"Zergling";324;0
"Unit";"Baneling";"Zergling";324;0
"Building";"Hatchery";NA;324;0
"Unit";"Zergling";"Larva";324;1
"Unit";"Zergling";"Larva";325;1
"Building";"CreepTumorQueen";NA;326;0
"Unit";"Baneling";"Zergling";326;0
"Unit";"Baneling";"Zergling";326;0
"Unit";"Baneling";"Zergling";326;0
"Unit";"Baneling";"Zergling";326;0
"Unit";"Baneling";"Zergling";326;0
"Unit";"Baneling";"Zergling";326;0
"Unit";"Zergling";"Larva";326;1
"Unit";"Zergling";"Larva";327;1
"Unit";"Zergling";"Larva";328;1
"Unit";"Zergling";"Larva";329;1
"Unit";"Zergling";"Larva";330;1
"Unit";"Zergling";"Larva";331;1
"Unit";"Zergling";"Larva";332;1
"Unit";"Zergling";"Larva";333;1
"Unit";"Zergling";"Larva";334;1
"Unit";"Zergling";"Larva";335;1
"Unit";"Zergling";"Larva";336;1
"Unit";"Zergling";"Larva";337;1
"Unit";"Zergling";"Larva";338;1
"Unit";"Zergling";"Larva";339;1
"Unit";"Zergling";"Larva";340;1
"Unit";"Zergling";"Larva";341;1
"Unit";"Zergling";"Larva";342;1
"Unit";"Zergling";"Larva";343;1
"Unit";"Zergling";"Larva";344;1
"Unit";"Zergling";"Larva";345;1
"Unit";"Zergling";"Larva";346;1
"Unit";"Zergling";"Larva";347;1
"Unit";"Zergling";"Larva";348;1
"Unit";"Zergling";"Larva";349;1
"Unit";"Zergling";"Larva";350;1
"Unit";"Zergling";"Larva";351;1
"Unit";"Zergling";"Larva";352;1
"Unit";"Zergling";"Larva";353;1
"Unit";"Zergling";"Larva";354;1
"Unit";"Zergling";"Larva";355;1
"Unit";"Zergling";"Larva";356;1
"Unit";"Zergling";"Larva";357;1
"Unit";"Zergling";"Larva";358;1
"Unit";"Zergling";"Larva";359;1
"Unit";"Zergling";"Larva";360;1
"Unit";"Zergling";"Larva";361;1
"Unit";"Zergling";"Larva";362;1
"Unit";"Zergling";"Larva";363;1
"Unit";"Zergling";"Larva";364;1
"Unit";"Zergling";"Larva";365;1
"Unit";"Baneling";"Zergling";366;0
"Unit";"Baneling";"Zergling";366;0
"Unit";"Baneling";"Zergling";366;0
"Unit";"Baneling";"Zergling";366;0
"Unit";"Baneling";"Zergling";366;0
"Unit";"Baneling";"Zergling";366;0
"Building";"CreepTumorQueen";NA;366;0
"Building";"CreepTumorQueen";NA;366;0
"Building";"CreepTumorQueen";NA;366;0
"Unit";"Hydralisk";"Larva";366;2
"Unit";"Hydralisk";"Larva";368;2
"Building";"CreepTumorQueen";NA;370;0
"Building";"CreepTumor";NA;370;0
"Unit";"Zergling";"Larva";370;1
"Unit";"Zergling";"Larva";371;1
"Unit";"Zergling";"Larva";372;1
"Unit";"Zergling";"Larva";373;1
"Unit";"Zergling";"Larva";374;1
"Unit";"Zergling";"Larva";375;1
"Unit";"Zergling";"Larva";376;1
"Unit";"Zergling";"Larva";377;1
"Unit";"Zergling";"Larva";378;1
"Unit";"Zergling";"Larva";379;1
"Unit";"Zergling";"Larva";380;1
"Unit";"Zergling";"Larva";381;1
"Unit";"Zergling";"Larva";382;1
"Unit";"Zergling";"Larva";383;1
"Unit";"Zergling";"Larva";384;1
"Unit";"Zergling";"Larva";385;1
"Unit";"Baneling";"Zergling";386;0
"Unit";"Baneling";"Zergling";386;0
"Unit";"Baneling";"Zergling";386;0
"Unit";"Baneling";"Zergling";386;0
"Unit";"Baneling";"Zergling";386;0
"Unit";"Baneling";"Zergling";386;0
"Unit";"Baneling";"Zergling";386;0
"Unit";"Baneling";"Zergling";386;0
"Unit";"Baneling";"Zergling";386;0
"Unit";"Baneling";"Zergling";386;0
"Unit";"Baneling";"Zergling";386;0
"Building";"CreepTumor";NA;386;0
"Unit";"Zergling";"Larva";386;1
"Unit";"Zergling";"Larva";387;1
"Unit";"Zergling";"Larva";388;1
"Unit";"Zergling";"Larva";389;1
"Unit";"Zergling";"Larva";390;1
"Unit";"Zergling";"Larva";391;1
"Unit";"Zergling";"Larva";392;1
"Unit";"Zergling";"Larva";393;1
"Unit";"Baneling";"Zergling";394;0
"Unit";"Baneling";"Zergling";394;0
"Unit";"Baneling";"Zergling";394;0
"Unit";"Baneling";"Zergling";394;0
"Unit";"Zergling";"Larva";394;1
"Unit";"Zergling";"Larva";395;1
"Unit";"Zergling";"Larva";396;1
"Unit";"Zergling";"Larva";397;1
"Unit";"Zergling";"Larva";398;1
"Unit";"Zergling";"Larva";399;1
"Unit";"Zergling";"Larva";400;1
"Unit";"Zergling";"Larva";401;1
"Unit";"Zergling";"Larva";402;1
"Unit";"Zergling";"Larva";403;1
"Unit";"Zergling";"Larva";404;1
"Unit";"Zergling";"Larva";405;1
"Unit";"Baneling";"Zergling";406;0
"Unit";"Baneling";"Zergling";406;0
"Unit";"Baneling";"Zergling";406;0
"Unit";"Baneling";"Zergling";406;0
"Unit";"Baneling";"Zergling";406;0
"Unit";"Baneling";"Zergling";406;0
"Unit";"Baneling";"Zergling";406;0
"Unit";"Baneling";"Zergling";406;0
"Unit";"Baneling";"Zergling";406;0
"Unit";"Baneling";"Zergling";406;0
"Unit";"Baneling";"Zergling";406;0
"Unit";"Baneling";"Zergling";406;0
"Unit";"Zergling";"Larva";406;1
"Unit";"Zergling";"Larva";407;1
"Unit";"Zergling";"Larva";408;1
"Unit";"Zergling";"Larva";409;1
"Unit";"Zergling";"Larva";410;1
"Unit";"Zergling";"Larva";411;1
"Unit";"Zergling";"Larva";412;1
"Unit";"Zergling";"Larva";413;1
"Unit";"Zergling";"Larva";414;1
"Unit";"Zergling";"Larva";415;1
"Unit";"Zergling";"Larva";416;1
"Unit";"Zergling";"Larva";417;1
"Unit";"Zergling";"Larva";418;1
"Unit";"Zergling";"Larva";419;1
"Unit";"Zergling";"Larva";420;1
"Unit";"Zergling";"Larva";421;1
"Unit";"Zergling";"Larva";422;1
"Unit";"Zergling";"Larva";423;1
"Unit";"Zergling";"Larva";424;1
"Unit";"Zergling";"Larva";425;1
"Unit";"Zergling";"Larva";426;1
"Unit";"Zergling";"Larva";427;1
"Unit";"Zergling";"Larva";428;1
"Unit";"Zergling";"Larva";429;1
"Unit";"Zergling";"Larva";430;1
"Unit";"Zergling";"Larva";431;1
"Unit";"Zergling";"Larva";432;1
"Unit";"Zergling";"Larva";433;1
"Unit";"Hydralisk";"Larva";435;2
"Unit";"Hydralisk";"Larva";437;2
"Unit";"Hydralisk";"Larva";439;2
"Unit";"Hydralisk";"Larva";441;2
"Unit";"Hydralisk";"Larva";443;2
"Unit";"Hydralisk";"Larva";445;2
"Unit";"Zergling";"Larva";447;1
"Unit";"Zergling";"Larva";448;1
"Unit";"Zergling";"Larva";449;1
"Unit";"Zergling";"Larva";450;1
"Unit";"Hydralisk";"Larva";451;2
"Unit";"Hydralisk";"Larva";453;2
"Unit";"Hydralisk";"Larva";455;2
"Unit";"Hydralisk";"Larva";457;2
"Unit";"Hydralisk";"Larva";459;2
"Building";"CreepTumor";NA;470;0
"Unit";"Zergling";"Larva";470;1
"Unit";"Zergling";"Larva";471;1
"Unit";"Zergling";"Larva";472;1
"Unit";"Zergling";"Larva";473;1
"Unit";"Zergling";"Larva";474;1
"Unit";"Zergling";"Larva";475;1
"Unit";"Zergling";"Larva";476;1
"Unit";"Zergling";"Larva";477;1
"Unit";"Zergling";"Larva";478;1
"Unit";"Zergling";"Larva";479;1
"Building";"CreepTumor";NA;480;0
"Unit";"Zergling";"Larva";480;1
"Unit";"Zergling";"Larva";481;1
"Unit";"Zergling";"Larva";482;1
"Unit";"Zergling";"Larva";483;1
"Unit";"Overlord";"Larva";484;0
"Unit";"Overlord";"Larva";484;0
"Building";"CreepTumor";NA;484;0
"Building";"CreepTumor";NA;484;0
"Building";"CreepTumor";NA;484;0
"Unit";"Overlord";"Larva";484;0
"Unit";"Mutalisk";"Larva";484;2
"Unit";"Mutalisk";"Larva";486;2
"Unit";"Mutalisk";"Larva";488;2
"Unit";"Mutalisk";"Larva";490;2
"Unit";"Mutalisk";"Larva";492;2
"Unit";"Mutalisk";"Larva";494;2
"Unit";"Mutalisk";"Larva";496;2
"Unit";"Mutalisk";"Larva";498;2
"Unit";"Mutalisk";"Larva";500;2
"Unit";"Mutalisk";"Larva";502;2
"Unit";"Mutalisk";"Larva";504;2
"Building";"CreepTumor";NA;506;0
"Building";"CreepTumor";NA;506;0
"Unit";"Zergling";"Larva";506;1
"Unit";"Zergling";"Larva";507;1
"Unit";"Zergling";"Larva";508;1
"Unit";"Zergling";"Larva";509;1
"Unit";"Zergling";"Larva";510;1
"Unit";"Zergling";"Larva";511;1
"Unit";"Zergling";"Larva";512;1
"Unit";"Zergling";"Larva";513;1
"Unit";"Zergling";"Larva";514;1
"Unit";"Zergling";"Larva";515;1
"Unit";"Zergling";"Larva";516;1
"Unit";"Zergling";"Larva";517;1
"Unit";"Zergling";"Larva";518;1
"Unit";"Zergling";"Larva";519;1
"Unit";"Zergling";"Larva";520;1
"Unit";"Zergling";"Larva";521;1
"Unit";"Zergling";"Larva";522;1
"Unit";"Zergling";"Larva";523;1
"Unit";"Zergling";"Larva";524;1
"Unit";"Zergling";"Larva";525;1
"Unit";"Zergling";"Larva";526;1
"Unit";"Zergling";"Larva";527;1
"Unit";"Zergling";"Larva";528;1
"Unit";"Zergling";"Larva";529;1
"Unit";"Zergling";"Larva";530;1
"Unit";"Zergling";"Larva";531;1
"Unit";"Zergling";"Larva";532;1
"Unit";"Zergling";"Larva";533;1
"Unit";"Zergling";"Larva";534;1
"Unit";"Zergling";"Larva";535;1
"Unit";"Zergling";"Larva";536;1
"Unit";"Zergling";"Larva";537;1
"Unit";"Zergling";"Larva";538;1
"Unit";"Zergling";"Larva";539;1
"Unit";"Zergling";"Larva";540;1
"Unit";"Zergling";"Larva";541;1
"Unit";"Zergling";"Larva";542;1
"Unit";"Zergling";"Larva";543;1
"Building";"CreepTumorQueen";NA;544;0
"Building";"CreepTumorQueen";NA;544;0
"Unit";"Zergling";"Larva";544;1
"Unit";"Zergling";"Larva";545;1
"Unit";"Zergling";"Larva";546;1
"Unit";"Zergling";"Larva";547;1
"Unit";"Zergling";"Larva";548;1
"Unit";"Zergling";"Larva";549;1
"Unit";"Zergling";"Larva";550;1
"Unit";"Zergling";"Larva";551;1
"Unit";"Zergling";"Larva";552;1
"Unit";"Zergling";"Larva";553;1
"Unit";"Zergling";"Larva";554;1
"Unit";"Zergling";"Larva";555;1
"Unit";"Baneling";"Zergling";556;0
"Unit";"Baneling";"Zergling";556;0
"Unit";"Baneling";"Zergling";556;0
"Unit";"Baneling";"Zergling";556;0
"Unit";"Baneling";"Zergling";556;0
"Unit";"Baneling";"Zergling";556;0
"Unit";"Baneling";"Zergling";556;0
"Unit";"Baneling";"Zergling";556;0
"Unit";"Baneling";"Zergling";556;0
"Unit";"Baneling";"Zergling";556;0
"Unit";"Baneling";"Zergling";556;0
"Unit";"Baneling";"Zergling";556;0
"Unit";"Baneling";"Zergling";556;0
"Unit";"Baneling";"Zergling";556;0
"Unit";"Baneling";"Zergling";556;0
"Unit";"Baneling";"Zergling";556;0
"Unit";"Baneling";"Zergling";556;0
"Unit";"Baneling";"Zergling";556;0
"Building";"CreepTumorQueen";NA;556;0
"Unit";"Zergling";"Larva";556;1
"Unit";"Zergling";"Larva";557;1
"Unit";"Zergling";"Larva";558;1
"Unit";"Zergling";"Larva";559;1
"Unit";"Zergling";"Larva";560;1
"Unit";"Zergling";"Larva";561;1
"Unit";"Baneling";"Zergling";562;0
"Unit";"Baneling";"Zergling";562;0
"Unit";"Baneling";"Zergling";562;0
"Unit";"Baneling";"Zergling";562;0
"Unit";"Baneling";"Zergling";562;0
"Unit";"Baneling";"Zergling";562;0
"Unit";"Baneling";"Zergling";562;0
"Unit";"Baneling";"Zergling";562;0
"Unit";"Baneling";"Zergling";562;0
"Unit";"Baneling";"Zergling";562;0
"Unit";"Baneling";"Zergling";562;0
"Unit";"Baneling";"Zergling";562;0
"Unit";"Baneling";"Zergling";562;0
"Unit";"Baneling";"Zergling";562;0
"Unit";"Baneling";"Zergling";562;0
"Unit";"Baneling";"Zergling";562;0
"Unit";"Zergling";"Larva";562;1
"Unit";"Zergling";"Larva";563;1
"Unit";"Zergling";"Larva";564;1
"Unit";"Zergling";"Larva";565;1
"Unit";"Zergling";"Larva";566;1
"Unit";"Zergling";"Larva";567;1
"Unit";"Zergling";"Larva";568;1
"Unit";"Zergling";"Larva";569;1
"Unit";"Zergling";"Larva";570;1
"Unit";"Zergling";"Larva";571;1
"Unit";"Zergling";"Larva";572;1
"Unit";"Zergling";"Larva";573;1
"Unit";"Zergling";"Larva";574;1
"Unit";"Zergling";"Larva";575;1
"Unit";"Zergling";"Larva";576;1
"Unit";"Zergling";"Larva";577;1
"Unit";"Zergling";"Larva";578;1
"Unit";"Zergling";"Larva";579;1
"Unit";"Zergling";"Larva";580;1
"Unit";"Zergling";"Larva";581;1
"Unit";"Zergling";"Larva";582;1
"Unit";"Zergling";"Larva";583;1
"Unit";"Zergling";"Larva";584;1
"Unit";"Zergling";"Larva";585;1
"Unit";"Zergling";"Larva";586;1
"Unit";"Zergling";"Larva";587;1
"Unit";"Zergling";"Larva";588;1
"Unit";"Zergling";"Larva";589;1
"Unit";"Zergling";"Larva";590;1
"Unit";"Zergling";"Larva";591;1
"Unit";"Zergling";"Larva";592;1
"Unit";"Zergling";"Larva";593;1
"Unit";"Zergling";"Larva";594;1
"Unit";"Zergling";"Larva";595;1
"Unit";"Zergling";"Larva";596;1
"Unit";"Zergling";"Larva";597;1
"Unit";"Zergling";"Larva";598;1
"Unit";"Zergling";"Larva";599;1
"Unit";"Zergling";"Larva";600;1
"Unit";"Zergling";"Larva";601;1
"Unit";"Zergling";"Larva";602;1
"Unit";"Zergling";"Larva";603;1
"Unit";"Zergling";"Larva";604;1
"Unit";"Zergling";"Larva";605;1
"Unit";"Zergling";"Larva";606;1
"Unit";"Zergling";"Larva";607;1
"Unit";"Zergling";"Larva";608;1
"Unit";"Zergling";"Larva";609;1
"Unit";"Zergling";"Larva";610;1
"Unit";"Zergling";"Larva";611;1
"Unit";"Zergling";"Larva";612;1
"Unit";"Zergling";"Larva";613;1
"Unit";"Zergling";"Larva";614;1
"Unit";"Zergling";"Larva";615;1
"Unit";"Zergling";"Larva";616;1
"Unit";"Zergling";"Larva";617;1
"Unit";"Zergling";"Larva";618;1
"Unit";"Zergling";"Larva";619;1
"Unit";"Zergling";"Larva";620;1
"Unit";"Zergling";"Larva";621;1
"Unit";"Zergling";"Larva";622;1
"Unit";"Zergling";"Larva";623;1
"Unit";"Zergling";"Larva";624;1
"Unit";"Zergling";"Larva";625;1
"Unit";"Zergling";"Larva";626;1
"Unit";"Zergling";"Larva";627;1
"Unit";"Corruptor";"Larva";628;2
"Unit";"Corruptor";"Larva";630;2
"Unit";"Corruptor";"Larva";632;2
"Unit";"Hydralisk";"Larva";634;2
"Unit";"Hydralisk";"Larva";636;2
"Unit";"Hydralisk";"Larva";638;2
"Unit";"Hydralisk";"Larva";640;2
"Unit";"Baneling";"Zergling";642;0
"Unit";"Baneling";"Zergling";642;0
"Unit";"Baneling";"Zergling";642;0
"Unit";"Baneling";"Zergling";642;0
"Unit";"Baneling";"Zergling";642;0
"Unit";"Baneling";"Zergling";642;0
"Unit";"Baneling";"Zergling";642;0
"Unit";"Baneling";"Zergling";642;0
"Unit";"Baneling";"Zergling";642;0
"Unit";"Baneling";"Zergling";642;0
"Unit";"Baneling";"Zergling";642;0
"Unit";"Baneling";"Zergling";642;0
"Unit";"Baneling";"Zergling";642;0
"Unit";"Baneling";"Zergling";642;0
"Unit";"Baneling";"Zergling";642;0
"Unit";"Baneling";"Zergling";642;0
"Unit";"Baneling";"Zergling";642;0
"Unit";"Baneling";"Zergling";642;0
"Unit";"Baneling";"Zergling";642;0
"Unit";"Baneling";"Zergling";642;0
"Unit";"Baneling";"Zergling";642;0
"Unit";"Baneling";"Zergling";642;0
"Unit";"Baneling";"Zergling";642;0
"Unit";"Baneling";"Zergling";642;0
"Unit";"Baneling";"Zergling";642;0
"Unit";"Baneling";"Zergling";642;0
"Unit";"Zergling";"Larva";642;1
"Unit";"Zergling";"Larva";643;1
"Unit";"Zergling";"Larva";644;1
"Unit";"Zergling";"Larva";645;1
"Unit";"Baneling";"Zergling";646;0
"Unit";"Baneling";"Zergling";646;0
"Unit";"Baneling";"Zergling";646;0
"Unit";"Baneling";"Zergling";646;0
"Unit";"Baneling";"Zergling";646;0
"Unit";"Baneling";"Zergling";646;0
"Unit";"Baneling";"Zergling";646;0
"Unit";"Baneling";"Zergling";646;0
"Unit";"Baneling";"Zergling";646;0
"Unit";"Baneling";"Zergling";646;0
"Unit";"Baneling";"Zergling";646;0
"Unit";"Baneling";"Zergling";646;0
"Unit";"Baneling";"Zergling";646;0
"Unit";"Baneling";"Zergling";646;0
"Unit";"Baneling";"Zergling";646;0
"Unit";"Baneling";"Zergling";646;0
"Unit";"Baneling";"Zergling";646;0
"Unit";"Baneling";"Zergling";646;0
"Unit";"Baneling";"Zergling";646;0
"Unit";"Baneling";"Zergling";646;0
"Unit";"Baneling";"Zergling";646;0
"Unit";"Baneling";"Zergling";646;0
"Upgrade";"SprayZerg";NA;646;0
"Upgrade";"SprayZerg";NA;646;0
"Upgrade";"SprayZerg";NA;646;0
"Upgrade";"SprayZerg";NA;646;0
"Upgrade";"zerglingmovementspeed";NA;646;0
"Upgrade";"SprayZerg";NA;646;0
"Upgrade";"SprayZerg";NA;646;0
"Upgrade";"EvolveGroovedSpines";NA;646;0
"Upgrade";"ZergMeleeWeaponsLevel1";NA;646;0
"Upgrade";"CentrificalHooks";NA;646;0
"Upgrade";"overlordspeed";NA;646;0
"Upgrade";"EvolveMuscularAugments";NA;646;0
"Upgrade";"SprayZerg";NA;646;0
"Upgrade";"ZergMeleeWeaponsLevel2";NA;646;0
"Upgrade";"SprayZerg";NA;646;0
"Upgrade";"ZergMissileWeaponsLevel1";NA;646;0
"Upgrade";"SprayZerg";NA;646;0
