"type";"unit_name";"on_building";"total_supply_lag";"supply"
"Unit";"Overlord";"Larva";15;0
"Building";"Hatchery";NA;15;0
"Building";"SpawningPool";NA;19;0
"Building";"Extractor";NA;20;0
"Unit";"Queen";"Hatchery";27;2
"Unit";"Zergling";"Larva";29;1
"Unit";"Zergling";"Larva";30;1
"Unit";"Overlord";"Larva";31;0
"Unit";"Queen";"Hatchery";31;2
"Unit";"Zergling";"Larva";33;1
"Unit";"Zergling";"Larva";34;1
"Unit";"Zergling";"Larva";35;1
"Unit";"Zergling";"Larva";36;1
"Unit";"Overlord";"Larva";42;0
"Building";"CreepTumorQueen";NA;42;0
"Building";"Hatchery";NA;44;0
"Unit";"Queen";"Hatchery";50;2
"Building";"CreepTumor";NA;52;0
"Unit";"Queen";"Hatchery";52;2
"Unit";"Overlord";"Larva";54;0
"Unit";"Overlord";"Larva";56;0
"Unit";"Overlord";"Larva";56;0
"Unit";"Overlord";"Larva";56;0
"Building";"SporeCrawler";NA;56;0
"Unit";"Queen";"Hatchery";56;2
"Building";"EvolutionChamber";NA;59;0
"Building";"SporeCrawler";NA;59;0
"Building";"CreepTumorQueen";NA;62;0
"Building";"CreepTumor";NA;63;0
"Unit";"Queen";"Hatchery";66;2
"Building";"CreepTumor";NA;75;0
"Building";"SporeCrawler";NA;77;0
"Unit";"Overlord";"Larva";81;0
"Building";"CreepTumor";NA;81;0
"Unit";"Zergling";"Larva";81;1
"Unit";"Zergling";"Larva";82;1
"Unit";"Overlord";"Larva";83;0
"Unit";"Zergling";"Larva";83;1
"Unit";"Zergling";"Larva";84;1
"Unit";"Zergling";"Larva";85;1
"Unit";"Zergling";"Larva";86;1
"Unit";"Zergling";"Larva";87;1
"Unit";"Zergling";"Larva";88;1
"Unit";"Zergling";"Larva";89;1
"Unit";"Zergling";"Larva";90;1
"Unit";"Zergling";"Larva";91;1
"Unit";"Zergling";"Larva";92;1
"Unit";"Zergling";"Larva";93;1
"Unit";"Zergling";"Larva";94;1
"Unit";"Overlord";"Larva";95;0
"Unit";"Zergling";"Larva";95;1
"Unit";"Zergling";"Larva";96;1
"Building";"CreepTumor";NA;97;0
"Unit";"Zergling";"Larva";97;1
"Unit";"Zergling";"Larva";98;1
"Building";"Hatchery";NA;99;0
"Unit";"Zergling";"Larva";99;1
"Unit";"Zergling";"Larva";100;1
"Unit";"Overlord";"Larva";101;0
"Unit";"Zergling";"Larva";101;1
"Unit";"Zergling";"Larva";102;1
"Unit";"Zergling";"Larva";103;1
"Unit";"Zergling";"Larva";104;1
"Unit";"Zergling";"Larva";105;1
"Unit";"Zergling";"Larva";106;1
"Unit";"Zergling";"Larva";107;1
"Unit";"Zergling";"Larva";108;1
"Unit";"Zergling";"Larva";109;1
"Unit";"Zergling";"Larva";110;1
"Unit";"Zergling";"Larva";111;1
"Unit";"Zergling";"Larva";112;1
"Unit";"Zergling";"Larva";113;1
"Unit";"Zergling";"Larva";114;1
"Unit";"Zergling";"Larva";115;1
"Unit";"Zergling";"Larva";116;1
"Unit";"Zergling";"Larva";117;1
"Unit";"Zergling";"Larva";118;1
"Unit";"Zergling";"Larva";119;1
"Unit";"Zergling";"Larva";120;1
"Unit";"Zergling";"Larva";121;1
"Unit";"Zergling";"Larva";122;1
"Building";"CreepTumor";NA;123;0
"Unit";"Zergling";"Larva";123;1
"Unit";"Zergling";"Larva";124;1
"Unit";"Zergling";"Larva";125;1
"Unit";"Zergling";"Larva";126;1
"Building";"CreepTumorQueen";NA;127;0
"Building";"Extractor";NA;128;0
"Building";"BanelingNest";NA;138;0
"Building";"Extractor";NA;138;0
"Unit";"Zergling";"Larva";138;1
"Unit";"Zergling";"Larva";139;1
"Unit";"Zergling";"Larva";140;1
"Unit";"Zergling";"Larva";141;1
"Unit";"Zergling";"Larva";142;1
"Unit";"Zergling";"Larva";143;1
"Unit";"Zergling";"Larva";144;1
"Unit";"Zergling";"Larva";145;1
"Building";"Extractor";NA;146;0
"Unit";"Zergling";"Larva";146;1
"Unit";"Zergling";"Larva";147;1
"Unit";"Zergling";"Larva";148;1
"Unit";"Zergling";"Larva";149;1
"Unit";"Overlord";"Larva";150;0
"Building";"SporeCrawler";NA;150;0
"Unit";"Queen";"Hatchery";150;2
"Building";"SporeCrawler";NA;152;0
"Building";"SporeCrawler";NA;152;0
"Unit";"Queen";"Hatchery";152;2
"Building";"SporeCrawler";NA;154;0
"Building";"SporeCrawler";NA;154;0
"Building";"SporeCrawler";NA;154;0
"Unit";"Zergling";"Larva";154;1
"Unit";"Zergling";"Larva";155;1
"Unit";"Zergling";"Larva";156;1
"Unit";"Zergling";"Larva";157;1
"Unit";"Zergling";"Larva";158;1
"Unit";"Zergling";"Larva";159;1
"Unit";"Zergling";"Larva";160;1
"Unit";"Zergling";"Larva";161;1
"Unit";"Zergling";"Larva";162;1
"Unit";"Zergling";"Larva";163;1
"Unit";"Zergling";"Larva";164;1
"Unit";"Zergling";"Larva";165;1
"Unit";"Zergling";"Larva";166;1
"Unit";"Zergling";"Larva";167;1
"Unit";"Zergling";"Larva";168;1
"Unit";"Zergling";"Larva";169;1
"Unit";"Zergling";"Larva";170;1
"Unit";"Zergling";"Larva";171;1
"Unit";"Zergling";"Larva";172;1
"Unit";"Zergling";"Larva";173;1
"Unit";"Zergling";"Larva";174;1
"Unit";"Zergling";"Larva";175;1
"Building";"SporeCrawler";NA;176;0
"Building";"SporeCrawler";NA;176;0
"Unit";"Zergling";"Larva";176;1
"Unit";"Zergling";"Larva";177;1
"Unit";"Zergling";"Larva";178;1
"Unit";"Zergling";"Larva";179;1
"Unit";"Zergling";"Larva";180;1
"Unit";"Zergling";"Larva";181;1
"Unit";"Zergling";"Larva";182;1
"Unit";"Zergling";"Larva";183;1
"Unit";"Zergling";"Larva";184;1
"Unit";"Zergling";"Larva";185;1
"Unit";"Zergling";"Larva";186;1
"Unit";"Zergling";"Larva";187;1
"Unit";"Zergling";"Larva";188;1
"Unit";"Zergling";"Larva";189;1
"Unit";"Zergling";"Larva";190;1
"Unit";"Zergling";"Larva";191;1
"Unit";"Baneling";"Zergling";192;0
"Unit";"Baneling";"Zergling";192;0
"Unit";"Baneling";"Zergling";192;0
"Unit";"Baneling";"Zergling";192;0
"Unit";"Baneling";"Zergling";192;0
"Unit";"Baneling";"Zergling";192;0
"Unit";"Baneling";"Zergling";192;0
"Unit";"Baneling";"Zergling";192;0
"Unit";"Zergling";"Larva";192;1
"Unit";"Zergling";"Larva";193;1
"Unit";"Zergling";"Larva";194;1
"Unit";"Zergling";"Larva";195;1
"Unit";"Zergling";"Larva";196;1
"Unit";"Zergling";"Larva";197;1
"Building";"Spire";NA;211;0
"Unit";"Zergling";"Larva";211;1
"Unit";"Zergling";"Larva";212;1
"Unit";"Zergling";"Larva";213;1
"Unit";"Zergling";"Larva";214;1
"Unit";"Zergling";"Larva";215;1
"Unit";"Zergling";"Larva";216;1
"Unit";"Zergling";"Larva";217;1
"Unit";"Zergling";"Larva";218;1
"Unit";"Zergling";"Larva";219;1
"Unit";"Zergling";"Larva";220;1
"Unit";"Zergling";"Larva";221;1
"Unit";"Zergling";"Larva";222;1
"Unit";"Zergling";"Larva";223;1
"Unit";"Zergling";"Larva";224;1
"Unit";"Zergling";"Larva";225;1
"Unit";"Zergling";"Larva";226;1
"Building";"Extractor";NA;227;0
"Unit";"Zergling";"Larva";231;1
"Unit";"Zergling";"Larva";232;1
"Building";"Extractor";NA;235;0
"Unit";"Zergling";"Larva";235;1
"Unit";"Zergling";"Larva";236;1
"Unit";"Zergling";"Larva";237;1
"Unit";"Zergling";"Larva";238;1
"Unit";"Zergling";"Larva";239;1
"Unit";"Zergling";"Larva";240;1
"Unit";"Zergling";"Larva";241;1
"Unit";"Zergling";"Larva";242;1
"Unit";"Zergling";"Larva";243;1
"Unit";"Zergling";"Larva";244;1
"Unit";"Zergling";"Larva";245;1
"Unit";"Zergling";"Larva";246;1
"Unit";"Zergling";"Larva";247;1
"Unit";"Zergling";"Larva";248;1
"Unit";"Zergling";"Larva";249;1
"Unit";"Zergling";"Larva";250;1
"Unit";"Zergling";"Larva";251;1
"Unit";"Zergling";"Larva";252;1
"Unit";"Zergling";"Larva";253;1
"Unit";"Zergling";"Larva";254;1
"Unit";"Zergling";"Larva";255;1
"Unit";"Zergling";"Larva";256;1
"Unit";"Zergling";"Larva";257;1
"Unit";"Zergling";"Larva";258;1
"Unit";"Zergling";"Larva";259;1
"Unit";"Zergling";"Larva";260;1
"Unit";"Zergling";"Larva";263;1
"Unit";"Zergling";"Larva";264;1
"Building";"CreepTumor";NA;265;0
"Unit";"Overlord";"Larva";266;0
"Building";"SporeCrawler";NA;266;0
"Building";"Extractor";NA;267;0
"Unit";"Mutalisk";"Larva";267;2
"Unit";"Mutalisk";"Larva";269;2
"Unit";"Mutalisk";"Larva";271;2
"Unit";"Mutalisk";"Larva";273;2
"Unit";"Mutalisk";"Larva";275;2
"Unit";"Mutalisk";"Larva";277;2
"Unit";"Mutalisk";"Larva";279;2
"Unit";"Overlord";"Larva";281;0
"Unit";"Overlord";"Larva";281;0
"Unit";"Overlord";"Larva";281;0
"Unit";"Overlord";"Larva";281;0
"Unit";"Mutalisk";"Larva";281;2
"Unit";"Mutalisk";"Larva";283;2
"Unit";"Mutalisk";"Larva";285;2
"Unit";"Mutalisk";"Larva";287;2
"Unit";"Mutalisk";"Larva";289;2
"Unit";"Mutalisk";"Larva";291;2
"Unit";"Mutalisk";"Larva";303;2
"Building";"Extractor";NA;305;0
"Unit";"Overlord";"Larva";305;0
"Unit";"Zergling";"Larva";305;1
"Unit";"Zergling";"Larva";306;1
"Unit";"Zergling";"Larva";307;1
"Unit";"Zergling";"Larva";308;1
"Unit";"Mutalisk";"Larva";309;2
"Unit";"Zergling";"Larva";311;1
"Unit";"Zergling";"Larva";312;1
"Unit";"Mutalisk";"Larva";313;2
"Unit";"Mutalisk";"Larva";315;2
"Building";"Hatchery";NA;317;0
"Unit";"Mutalisk";"Larva";317;2
"Unit";"Mutalisk";"Larva";319;2
"Unit";"Mutalisk";"Larva";321;2
"Unit";"Mutalisk";"Larva";323;2
"Unit";"Zergling";"Larva";325;1
"Unit";"Zergling";"Larva";326;1
"Unit";"Zergling";"Larva";327;1
"Unit";"Zergling";"Larva";328;1
"Unit";"Zergling";"Larva";329;1
"Unit";"Zergling";"Larva";330;1
"Unit";"Zergling";"Larva";331;1
"Unit";"Zergling";"Larva";332;1
"Unit";"Zergling";"Larva";333;1
"Unit";"Zergling";"Larva";334;1
"Unit";"Zergling";"Larva";335;1
"Unit";"Zergling";"Larva";336;1
"Unit";"Mutalisk";"Larva";337;2
"Unit";"Mutalisk";"Larva";339;2
"Building";"SpineCrawler";NA;341;0
"Unit";"Mutalisk";"Larva";341;2
"Unit";"Mutalisk";"Larva";343;2
"Unit";"Mutalisk";"Larva";345;2
"Unit";"Zergling";"Larva";347;1
"Unit";"Zergling";"Larva";348;1
"Unit";"Zergling";"Larva";349;1
"Unit";"Zergling";"Larva";350;1
"Unit";"Zergling";"Larva";351;1
"Unit";"Zergling";"Larva";352;1
"Unit";"Zergling";"Larva";353;1
"Unit";"Zergling";"Larva";354;1
"Unit";"Zergling";"Larva";355;1
"Unit";"Zergling";"Larva";356;1
"Unit";"Zergling";"Larva";357;1
"Unit";"Zergling";"Larva";358;1
"Unit";"Zergling";"Larva";359;1
"Unit";"Zergling";"Larva";360;1
"Unit";"Zergling";"Larva";361;1
"Unit";"Zergling";"Larva";362;1
"Unit";"Zergling";"Larva";363;1
"Unit";"Zergling";"Larva";364;1
"Unit";"Zergling";"Larva";365;1
"Unit";"Zergling";"Larva";366;1
"Unit";"Zergling";"Larva";367;1
"Unit";"Zergling";"Larva";368;1
"Unit";"Mutalisk";"Larva";369;2
"Unit";"Mutalisk";"Larva";371;2
"Unit";"Mutalisk";"Larva";373;2
"Unit";"Zergling";"Larva";375;1
"Unit";"Zergling";"Larva";376;1
"Unit";"Zergling";"Larva";377;1
"Unit";"Zergling";"Larva";378;1
"Upgrade";"SprayZerg";NA;383;0
"Upgrade";"SprayZerg";NA;383;0
"Upgrade";"SprayZerg";NA;383;0
"Upgrade";"SprayZerg";NA;383;0
"Upgrade";"zerglingmovementspeed";NA;383;0
"Upgrade";"SprayZerg";NA;383;0
"Upgrade";"SprayZerg";NA;383;0
"Upgrade";"ZergMeleeWeaponsLevel1";NA;383;0
"Upgrade";"SprayZerg";NA;383;0
"Upgrade";"SprayZerg";NA;383;0
"Upgrade";"SprayZerg";NA;383;0
