"type";"unit_name";"on_building";"total_supply";"supply"
"Unit";"Overlord";"Larva";13;0
"Building";"Extractor";NA;18;0
"Unit";"Overlord";"Larva";21;0
"Building";"SpawningPool";NA;19;0
"Building";"Hatchery";NA;17;0
"Unit";"Zergling";"Larva";22;1
"Unit";"Zergling";"Larva";22;1
"Unit";"Zergling";"Larva";23;1
"Unit";"Zergling";"Larva";23;1
"Unit";"Queen";"Hatchery";22;2
"Unit";"Queen";"Hatchery";23;2
"Unit";"Overlord";"Larva";37;0
"Unit";"Zergling";"Larva";37;1
"Unit";"Zergling";"Larva";37;1
"Building";"CreepTumorQueen";NA;39;0
"Unit";"Overlord";"Larva";37;0
"Unit";"Queen";"Hatchery";37;2
"Unit";"Overlord";"Larva";39;0
"Building";"SporeCrawler";NA;39;0
"Building";"CreepTumor";NA;48;0
"Building";"Hatchery";NA;35;0
"Building";"EvolutionChamber";NA;47;0
"Unit";"Queen";"Hatchery";45;2
"Unit";"Overlord";"Larva";48;0
"Building";"CreepTumorQueen";NA;53;0
"Building";"SporeCrawler";NA;51;0
"Building";"CreepTumor";NA;57;0
"Unit";"Zergling";"Larva";57;1
"Unit";"Zergling";"Larva";57;1
"Unit";"Zergling";"Larva";57;1
"Unit";"Zergling";"Larva";57;1
"Unit";"Zergling";"Larva";57;1
"Unit";"Zergling";"Larva";57;1
"Unit";"Zergling";"Larva";57;1
"Unit";"Zergling";"Larva";57;1
"Unit";"Zergling";"Larva";57;1
"Unit";"Zergling";"Larva";57;1
"Unit";"Zergling";"Larva";60;1
"Unit";"Zergling";"Larva";60;1
"Unit";"Zergling";"Larva";60;1
"Unit";"Zergling";"Larva";60;1
"Unit";"Zergling";"Larva";60;1
"Unit";"Zergling";"Larva";60;1
"Unit";"Zergling";"Larva";60;1
"Unit";"Zergling";"Larva";60;1
"Building";"CreepTumor";NA;60;0
"Building";"CreepTumorQueen";NA;78;0
"Building";"Extractor";NA;70;0
"Unit";"Overlord";"Larva";82;0
"Building";"RoachWarren";NA;60;0
"Building";"CreepTumor";NA;84;0
"Unit";"Overlord";"Larva";84;0
"Building";"CreepTumor";NA;84;0
"Unit";"Overlord";"Larva";84;0
"Unit";"Overlord";"Larva";84;0
"Unit";"Zergling";"Larva";88;1
"Unit";"Zergling";"Larva";88;1
"Unit";"Roach";"Larva";88;2
"Building";"CreepTumorQueen";NA;88;0
"Unit";"Zergling";"Larva";88;1
"Unit";"Zergling";"Larva";88;1
"Unit";"Roach";"Larva";88;2
"Unit";"Roach";"Larva";88;2
"Unit";"Roach";"Larva";88;2
"Unit";"Zergling";"Larva";88;1
"Unit";"Zergling";"Larva";88;1
"Unit";"Zergling";"Larva";88;1
"Unit";"Zergling";"Larva";88;1
"Unit";"Roach";"Larva";88;2
"Unit";"Roach";"Larva";88;2
"Unit";"Zergling";"Larva";88;1
"Unit";"Zergling";"Larva";88;1
"Unit";"Zergling";"Larva";88;1
"Unit";"Zergling";"Larva";88;1
"Unit";"Zergling";"Larva";88;1
"Unit";"Zergling";"Larva";88;1
"Unit";"Roach";"Larva";88;2
"Unit";"Roach";"Larva";88;2
"Unit";"Zergling";"Larva";100;1
"Unit";"Zergling";"Larva";100;1
"Unit";"Zergling";"Larva";100;1
"Unit";"Zergling";"Larva";100;1
"Unit";"Zergling";"Larva";100;1
"Unit";"Zergling";"Larva";100;1
"Unit";"Zergling";"Larva";100;1
"Unit";"Zergling";"Larva";100;1
"Unit";"Zergling";"Larva";100;1
"Unit";"Zergling";"Larva";100;1
"Unit";"Roach";"Larva";100;2
"Upgrade";"ZergMeleeWeaponsLevel1";"EvolutionChamber";70;0
"Unit";"Zergling";"Larva";114;1
"Unit";"Zergling";"Larva";114;1
"Unit";"Zergling";"Larva";114;1
"Unit";"Zergling";"Larva";114;1
"Unit";"Zergling";"Larva";114;1
"Unit";"Zergling";"Larva";114;1
"Unit";"Roach";"Larva";114;2
"Unit";"Zergling";"Larva";128;1
"Unit";"Zergling";"Larva";128;1
"Unit";"Zergling";"Larva";128;1
"Unit";"Zergling";"Larva";128;1
"Building";"Extractor";NA;118;0
"Unit";"Zergling";"Larva";130;1
"Unit";"Zergling";"Larva";130;1
"Unit";"Zergling";"Larva";130;1
"Unit";"Zergling";"Larva";130;1
"Unit";"Zergling";"Larva";136;1
"Unit";"Zergling";"Larva";136;1
"Unit";"Zergling";"Larva";136;1
"Unit";"Zergling";"Larva";136;1
"Unit";"Zergling";"Larva";136;1
"Unit";"Zergling";"Larva";136;1
"Unit";"Zergling";"Larva";164;1
"Unit";"Zergling";"Larva";164;1
"Unit";"Zergling";"Larva";164;1
"Unit";"Zergling";"Larva";164;1
"Unit";"Zergling";"Larva";164;1
"Unit";"Zergling";"Larva";164;1
"Unit";"Zergling";"Larva";164;1
"Unit";"Zergling";"Larva";164;1
"Unit";"Zergling";"Larva";164;1
"Unit";"Zergling";"Larva";164;1
"Unit";"Zergling";"Larva";164;1
"Unit";"Zergling";"Larva";164;1
"Unit";"Zergling";"Larva";165;1
"Unit";"Zergling";"Larva";165;1
"Unit";"Zergling";"Larva";165;1
"Unit";"Zergling";"Larva";165;1
"Unit";"Zergling";"Larva";165;1
"Unit";"Zergling";"Larva";165;1
"Building";"HydraliskDen";NA;164;0
"Unit";"Zergling";"Larva";177;1
"Unit";"Zergling";"Larva";177;1
"Unit";"Zergling";"Larva";177;1
"Unit";"Zergling";"Larva";177;1
"Unit";"Zergling";"Larva";177;1
"Unit";"Zergling";"Larva";177;1
"Unit";"Zergling";"Larva";177;1
"Unit";"Zergling";"Larva";177;1
"Unit";"Roach";"Larva";183;2
"Unit";"Roach";"Larva";183;2
"Unit";"Roach";"Larva";183;2
"Unit";"Hydralisk";"Larva";183;2
"Building";"Extractor";NA;187;0
"Unit";"Hydralisk";"Larva";197;2
"Unit";"Hydralisk";"Larva";197;2
"Unit";"Hydralisk";"Larva";197;2
"Unit";"Hydralisk";"Larva";197;2
"Unit";"Hydralisk";"Larva";197;2
"Building";"Hatchery";NA;165;0
"Upgrade";"EvolveGroovedSpines";"HydraliskDen";197;0
