"type";"unit_name";"on_building";"total_supply";"supply"
"Unit";"Overlord";"Larva";12;0
"Building";"Extractor";NA;18;0
"Unit";"Overlord";"Larva";22;0
"Building";"SpawningPool";NA;19;0
"Building";"Hatchery";NA;16;0
"Unit";"Zergling";"Larva";22;1
"Unit";"Zergling";"Larva";22;1
"Unit";"Zergling";"Larva";22;1
"Unit";"Zergling";"Larva";22;1
"Unit";"Queen";"Hatchery";29;2
"Unit";"Overlord";"Larva";32;0
"Building";"Hatchery";NA;23;0
"Unit";"Queen";"Hatchery";34;2
"Building";"SporeCrawler";NA;39;0
"Building";"SporeCrawler";NA;39;0
"Unit";"Overlord";"Larva";40;0
"Unit";"Queen";"Hatchery";39;2
"Building";"SporeCrawler";NA;46;0
"Building";"Extractor";NA;46;0
"Building";"RoachWarren";NA;46;0
"Unit";"Overlord";"Larva";56;0
"Unit";"Overlord";"Larva";56;0
"Unit";"Queen";"Hatchery";56;2
"Unit";"Overlord";"Larva";56;0
"Unit";"Overlord";"Larva";56;0
"Unit";"Roach";"Larva";57;2
"Unit";"Roach";"Larva";57;2
"Unit";"Roach";"Larva";57;2
"Unit";"Queen";"Hatchery";56;2
"Unit";"Roach";"Larva";57;2
"Unit";"Roach";"Larva";57;2
"Unit";"Roach";"Larva";57;2
"Unit";"Roach";"Larva";59;2
"Unit";"Roach";"Larva";59;2
"Building";"CreepTumorQueen";NA;67;0
"Unit";"Overlord";"Larva";65;0
"Building";"Extractor";NA;65;0
"Building";"CreepTumorQueen";NA;76;0
"Unit";"Overlord";"Larva";80;0
"Unit";"Overlord";"Larva";80;0
"Unit";"Roach";"Larva";87;2
"Unit";"Roach";"Larva";87;2
"Unit";"Roach";"Larva";87;2
"Unit";"Roach";"Larva";87;2
"Building";"HydraliskDen";NA;87;0
"Unit";"Overlord";"Larva";100;0
"Unit";"Overlord";"Larva";100;0
"Unit";"Overlord";"Larva";100;0
"Unit";"Hydralisk";"Larva";100;2
"Unit";"Hydralisk";"Larva";100;2
"Unit";"Hydralisk";"Larva";100;2
"Unit";"Hydralisk";"Larva";100;2
"Building";"Extractor";NA;120;0
"Building";"Extractor";NA;120;0
"Upgrade";"EvolveGroovedSpines";"HydraliskDen";107;0
"Unit";"Roach";"Larva";128;2
"Unit";"Roach";"Larva";128;2
"Unit";"Roach";"Larva";128;2
"Unit";"Roach";"Larva";128;2
"Building";"Extractor";NA;127;0
"Unit";"Overlord";"Larva";128;0
"Building";"EvolutionChamber";NA;120;0
"Building";"EvolutionChamber";NA;124;0
"Unit";"Hydralisk";"Larva";128;2
"Unit";"Hydralisk";"Larva";128;2
"Unit";"Hydralisk";"Larva";128;2
"Building";"CreepTumor";NA;128;0
"Unit";"Zergling";"Larva";142;1
"Unit";"Zergling";"Larva";142;1
"Unit";"Zergling";"Larva";142;1
"Unit";"Zergling";"Larva";142;1
"Unit";"Zergling";"Larva";142;1
"Unit";"Zergling";"Larva";142;1
"Unit";"Zergling";"Larva";142;1
"Unit";"Zergling";"Larva";142;1
"Unit";"Zergling";"Larva";142;1
"Unit";"Zergling";"Larva";142;1
"Unit";"Zergling";"Larva";142;1
"Unit";"Zergling";"Larva";142;1
"Unit";"Zergling";"Larva";142;1
"Unit";"Zergling";"Larva";142;1
"Unit";"Zergling";"Larva";142;1
"Unit";"Zergling";"Larva";142;1
"Unit";"Zergling";"Larva";142;1
"Unit";"Zergling";"Larva";142;1
"Unit";"Overlord";"Larva";142;0
"Unit";"Overlord";"Larva";142;0
"Unit";"Overlord";"Larva";142;0
"Unit";"Overlord";"Larva";142;0
"Building";"CreepTumor";NA;142;0
"Building";"CreepTumorQueen";NA;144;0
"Building";"CreepTumorQueen";NA;160;0
"Unit";"Overlord";"Larva";160;0
"Unit";"Overlord";"Larva";160;0
"Building";"CreepTumor";NA;160;0
"Building";"Hatchery";NA;128;0
"Building";"CreepTumorQueen";NA;171;0
"Unit";"Roach";"Larva";171;2
"Unit";"Roach";"Larva";171;2
"Unit";"Roach";"Larva";171;2
"Unit";"Roach";"Larva";171;2
"Unit";"Roach";"Larva";171;2
"Unit";"Hydralisk";"Larva";171;2
"Unit";"Hydralisk";"Larva";171;2
"Unit";"Hydralisk";"Larva";171;2
"Unit";"Hydralisk";"Larva";171;2
"Unit";"Hydralisk";"Larva";171;2
"Upgrade";"EvolveMuscularAugments";"HydraliskDen";160;0
"Unit";"Overlord";"Larva";171;0
"Unit";"Overlord";"Larva";171;0
"Unit";"Roach";"Larva";171;2
"Unit";"Roach";"Larva";171;2
"Unit";"Hydralisk";"Larva";171;2
"Unit";"Hydralisk";"Larva";171;2
"Building";"CreepTumorQueen";NA;191;0
"Building";"CreepTumor";NA;191;0
"Building";"CreepTumorQueen";NA;195;0
"Unit";"Overlord";"Larva";191;0
"Unit";"Queen";"Hatchery";171;2
"Building";"Extractor";NA;191;0
"Unit";"Overlord";"Larva";191;0
"Unit";"Overlord";"Larva";191;0
"Building";"Extractor";NA;191;0
"Unit";"Roach";"Larva";191;2
"Unit";"Roach";"Larva";191;2
"Unit";"Roach";"Larva";193;2
"Building";"LurkerDenMP";NA;160;0
"Unit";"Hydralisk";"Larva";191;2
"Unit";"Hydralisk";"Larva";191;2
"Unit";"Queen";"Hatchery";191;2
"Upgrade";"ZergMissileWeaponsLevel1";"EvolutionChamber";160;0
"Upgrade";"ZergGroundArmorsLevel1";"EvolutionChamber";171;0
"Building";"CreepTumor";NA;214;0
"Building";"CreepTumor";NA;219;0
"Building";"CreepTumor";NA;219;0
"Building";"CreepTumor";NA;219;0
"Unit";"Roach";"Larva";219;2
"Unit";"Roach";"Larva";219;2
"Unit";"Roach";"Larva";219;2
"Unit";"Roach";"Larva";219;2
"Unit";"Roach";"Larva";219;2
"Unit";"Hydralisk";"Larva";219;2
"Unit";"Hydralisk";"Larva";219;2
"Unit";"Hydralisk";"Larva";219;2
"Unit";"Hydralisk";"Larva";219;2
"Building";"SpineCrawler";NA;219;0
"Building";"SpineCrawler";NA;219;0
"Building";"SpineCrawler";NA;219;0
"Building";"SpineCrawler";NA;219;0
"Building";"SpineCrawler";NA;219;0
"Unit";"Roach";"Larva";237;2
"Unit";"Hydralisk";"Larva";237;2
"Building";"InfestationPit";NA;227;0
"Unit";"Roach";"Larva";239;2
"Unit";"Roach";"Larva";239;2
"Unit";"Roach";"Larva";239;2
"Unit";"Roach";"Larva";239;2
"Unit";"Roach";"Larva";239;2
"Unit";"Roach";"Larva";239;2
"Unit";"Roach";"Larva";239;2
"Unit";"Roach";"Larva";239;2
"Unit";"Hydralisk";"Larva";239;2
"Unit";"Hydralisk";"Larva";239;2
"Unit";"Hydralisk";"Larva";239;2
"Unit";"Hydralisk";"Larva";239;2
"Unit";"Hydralisk";"Larva";239;2
"Unit";"Hydralisk";"Larva";239;2
"Unit";"Hydralisk";"Larva";239;2
"Unit";"Roach";"Larva";241;2
"Unit";"Roach";"Larva";241;2
"Unit";"Roach";"Larva";241;2
"Unit";"Hydralisk";"Larva";241;2
"Unit";"Hydralisk";"Larva";241;2
"Unit";"Hydralisk";"Larva";241;2
"Unit";"Roach";"Larva";271;2
"Unit";"Roach";"Larva";271;2
"Unit";"Roach";"Larva";271;2
"Unit";"Hydralisk";"Larva";271;2
"Unit";"Hydralisk";"Larva";271;2
"Unit";"Hydralisk";"Larva";271;2
"Unit";"Roach";"Larva";283;2
"Unit";"Roach";"Larva";283;2
"Unit";"Roach";"Larva";283;2
"Unit";"Hydralisk";"Larva";283;2
"Unit";"Hydralisk";"Larva";283;2
"Unit";"Hydralisk";"Larva";283;2
"Unit";"Zergling";"Larva";295;1
"Unit";"Zergling";"Larva";295;1
"Unit";"Zergling";"Larva";295;1
"Unit";"Zergling";"Larva";295;1
"Unit";"Zergling";"Larva";295;1
"Unit";"Zergling";"Larva";295;1
"Unit";"Zergling";"Larva";295;1
"Unit";"Zergling";"Larva";295;1
"Unit";"Zergling";"Larva";295;1
"Unit";"Zergling";"Larva";295;1
"Unit";"Zergling";"Larva";295;1
"Unit";"Zergling";"Larva";295;1
"Unit";"Zergling";"Larva";295;1
"Unit";"Zergling";"Larva";295;1
"Unit";"Zergling";"Larva";295;1
"Unit";"Zergling";"Larva";295;1
"Unit";"Zergling";"Larva";295;1
"Unit";"Zergling";"Larva";295;1
"Unit";"Zergling";"Larva";295;1
"Unit";"Zergling";"Larva";295;1
"Unit";"Zergling";"Larva";295;1
"Unit";"Zergling";"Larva";295;1
"Upgrade";"ZergMissileWeaponsLevel2";"EvolutionChamber";237;0
"Unit";"Overlord";"Larva";307;0
"Unit";"Overlord";"Larva";307;0
"Unit";"Overlord";"Larva";307;0
"Unit";"Overlord";"Larva";307;0
"Unit";"Overlord";"Larva";307;0
"Upgrade";"ZergGroundArmorsLevel2";"EvolutionChamber";241;0
"Unit";"Roach";"Larva";329;2
"Unit";"Roach";"Larva";329;2
"Unit";"Roach";"Larva";329;2
"Unit";"Roach";"Larva";329;2
"Unit";"Roach";"Larva";329;2
"Unit";"Roach";"Larva";329;2
"Unit";"Roach";"Larva";329;2
"Unit";"Roach";"Larva";329;2
"Unit";"Roach";"Larva";329;2
"Unit";"Hydralisk";"Larva";329;2
"Unit";"Hydralisk";"Larva";329;2
"Unit";"Hydralisk";"Larva";329;2
"Unit";"Hydralisk";"Larva";329;2
"Unit";"Hydralisk";"Larva";329;2
"Unit";"Hydralisk";"Larva";329;2
"Unit";"Hydralisk";"Larva";329;2
"Unit";"Hydralisk";"Larva";329;2
"Unit";"Hydralisk";"Larva";329;2
"Unit";"Roach";"Larva";329;2
"Unit";"Hydralisk";"Larva";329;2
"Unit";"Roach";"Larva";367;2
"Unit";"Roach";"Larva";367;2
"Unit";"Hydralisk";"Larva";367;2
"Unit";"Hydralisk";"Larva";367;2
"Unit";"Hydralisk";"Larva";367;2
"Unit";"Zergling";"Larva";379;1
"Unit";"Zergling";"Larva";379;1
"Unit";"Zergling";"Larva";379;1
"Unit";"Zergling";"Larva";379;1
"Unit";"Zergling";"Larva";379;1
"Unit";"Zergling";"Larva";379;1
"Unit";"Zergling";"Larva";379;1
"Unit";"Zergling";"Larva";379;1
"Unit";"Zergling";"Larva";379;1
"Unit";"Zergling";"Larva";379;1
"Unit";"Zergling";"Larva";379;1
"Unit";"Zergling";"Larva";379;1
"Unit";"Roach";"Larva";391;2
"Unit";"Roach";"Larva";391;2
"Unit";"Roach";"Larva";391;2
"Unit";"Roach";"Larva";391;2
"Unit";"Roach";"Larva";391;2
"Unit";"Roach";"Larva";391;2
"Unit";"Roach";"Larva";391;2
"Unit";"Roach";"Larva";391;2
"Unit";"Roach";"Larva";391;2
"Unit";"Roach";"Larva";391;2
"Unit";"Hydralisk";"Larva";391;2
"Unit";"Hydralisk";"Larva";391;2
"Unit";"Hydralisk";"Larva";391;2
"Unit";"Hydralisk";"Larva";391;2
"Unit";"Hydralisk";"Larva";391;2
"Unit";"Hydralisk";"Larva";391;2
"Unit";"Hydralisk";"Larva";391;2
"Unit";"Hydralisk";"Larva";391;2
"Unit";"Hydralisk";"Larva";391;2
"Unit";"Roach";"Larva";391;2
"Unit";"Hydralisk";"Larva";391;2
"Building";"Spire";NA;369;0
"Unit";"Roach";"Larva";399;2
"Unit";"Hydralisk";"Larva";399;2
"Unit";"Hydralisk";"Larva";429;2
"Unit";"Hydralisk";"Larva";429;2
"Unit";"Hydralisk";"Larva";429;2
"Unit";"Hydralisk";"Larva";429;2
"Unit";"Roach";"Larva";433;2
"Unit";"Roach";"Larva";435;2
"Unit";"Hydralisk";"Larva";435;2
"Building";"Hatchery";NA;389;0
"Unit";"Roach";"Larva";437;2
"Unit";"Hydralisk";"Larva";437;2
"Unit";"Roach";"Larva";445;2
"Unit";"Roach";"Larva";445;2
"Unit";"Roach";"Larva";445;2
"Unit";"Roach";"Larva";445;2
"Building";"LurkerDenMP";NA;431;0
"Building";"SpawningPool";NA;463;0
