"type";"unit_name";"on_building";"total_supply";"supply"
"Unit";"Overlord";"Larva";12;0
"Building";"Extractor";NA;18;0
"Unit";"Overlord";"Larva";21;0
"Building";"SpawningPool";NA;19;0
"Building";"Hatchery";NA;17;0
"Unit";"Zergling";"Larva";23;1
"Unit";"Zergling";"Larva";23;1
"Unit";"Zergling";"Larva";23;1
"Unit";"Zergling";"Larva";23;1
"Unit";"Queen";"Hatchery";23;2
"Unit";"Queen";"Hatchery";23;2
"Unit";"Zergling";"Larva";35;1
"Unit";"Zergling";"Larva";35;1
"Unit";"Zergling";"Larva";35;1
"Unit";"Zergling";"Larva";35;1
"Unit";"Overlord";"Larva";36;0
"Unit";"Overlord";"Larva";41;0
"Unit";"Overlord";"Larva";41;0
"Building";"CreepTumorQueen";NA;41;0
"Building";"Extractor";NA;41;0
"Unit";"Queen";"Hatchery";37;2
"Building";"Hatchery";NA;30;0
"Building";"CreepTumor";NA;51;0
"Building";"RoachWarren";NA;45;0
"Unit";"Overlord";"Larva";53;0
"Building";"CreepTumor";NA;58;0
"Building";"SporeCrawler";NA;58;0
"Building";"SporeCrawler";NA;58;0
"Building";"SporeCrawler";NA;58;0
"Unit";"Roach";"Larva";58;2
"Unit";"Roach";"Larva";58;2
"Unit";"Roach";"Larva";58;2
"Unit";"Roach";"Larva";58;2
"Unit";"Roach";"Larva";58;2
"Unit";"Roach";"Larva";58;2
"Unit";"Roach";"Larva";58;2
"Unit";"Overlord";"Larva";80;0
"Unit";"Overlord";"Larva";80;0
"Unit";"Overlord";"Larva";80;0
"Building";"Extractor";NA;80;0
"Unit";"Overlord";"Larva";83;0
"Unit";"Overlord";"Larva";83;0
"Unit";"Roach";"Larva";83;2
"Unit";"Roach";"Larva";83;2
"Unit";"Roach";"Larva";83;2
"Unit";"Roach";"Larva";83;2
"Unit";"Roach";"Larva";83;2
"Unit";"Roach";"Larva";83;2
"Unit";"Roach";"Larva";83;2
"Upgrade";"GlialReconstitution";"RoachWarren";74;0
"Unit";"Roach";"Larva";83;2
"Unit";"Roach";"Larva";83;2
"Unit";"Roach";"Larva";83;2
"Unit";"Roach";"Larva";83;2
"Unit";"Roach";"Larva";83;2
"Building";"CreepTumor";NA;97;0
"Unit";"Roach";"Larva";107;2
"Unit";"Roach";"Larva";107;2
"Unit";"Roach";"Larva";107;2
"Unit";"Roach";"Larva";107;2
"Unit";"Roach";"Larva";107;2
"Unit";"Roach";"Larva";107;2
"Unit";"Roach";"Larva";107;2
"Unit";"Roach";"Larva";107;2
"Building";"SpineCrawler";NA;107;0
"Building";"SpineCrawler";NA;107;0
"Building";"Hatchery";NA;107;0
"Unit";"Roach";"Larva";126;2
"Unit";"Roach";"Larva";126;2
"Unit";"Roach";"Larva";126;2
"Unit";"Roach";"Larva";126;2
"Unit";"Roach";"Larva";126;2
"Unit";"Roach";"Larva";126;2
"Unit";"Roach";"Larva";126;2
"Unit";"Roach";"Larva";126;2
"Unit";"Overlord";"Larva";134;0
"Unit";"Overlord";"Larva";134;0
"Unit";"Overlord";"Larva";134;0
"Building";"CreepTumor";NA;142;0
"Unit";"Roach";"Larva";142;2
"Unit";"Roach";"Larva";142;2
"Building";"Extractor";NA;148;0
"Building";"EvolutionChamber";NA;148;0
"Unit";"Roach";"Larva";148;2
"Unit";"Roach";"Larva";148;2
"Unit";"Roach";"Larva";148;2
"Unit";"Roach";"Larva";148;2
"Building";"InfestationPit";NA;142;0
"Building";"SpineCrawler";NA;148;0
"Unit";"Overlord";"Larva";152;0
"Unit";"Overlord";"Larva";152;0
"Unit";"Roach";"Larva";152;2
"Unit";"Roach";"Larva";152;2
"Unit";"Roach";"Larva";152;2
"Unit";"Roach";"Larva";152;2
"Building";"Hatchery";NA;148;0
"Building";"CreepTumor";NA;168;0
"Unit";"Roach";"Larva";168;2
"Unit";"Roach";"Larva";168;2
"Unit";"Roach";"Larva";168;2
"Unit";"Roach";"Larva";168;2
"Unit";"Queen";"Hatchery";168;2
"Building";"SporeCrawler";NA;168;0
"Unit";"Roach";"Larva";174;2
"Unit";"Roach";"Larva";174;2
"Unit";"Roach";"Larva";174;2
"Unit";"Roach";"Larva";174;2
"Unit";"Roach";"Larva";174;2
"Building";"CreepTumor";NA;178;0
"Building";"SpineCrawler";NA;174;0
"Building";"SpineCrawler";NA;174;0
"Building";"SpineCrawler";NA;174;0
"Unit";"Overlord";"Larva";188;0
"Unit";"Overlord";"Larva";188;0
"Unit";"Overlord";"Larva";188;0
"Unit";"Overlord";"Larva";188;0
"Unit";"Queen";"Hatchery";176;2
"Building";"SpineCrawler";NA;188;0
"Building";"SpineCrawler";NA;188;0
"Unit";"Roach";"Larva";195;2
"Unit";"Roach";"Larva";195;2
"Unit";"Roach";"Larva";195;2
"Unit";"Roach";"Larva";195;2
"Unit";"Roach";"Larva";195;2
"Unit";"Roach";"Larva";195;2
"Unit";"Roach";"Larva";195;2
"Unit";"Roach";"Larva";195;2
"Unit";"Roach";"Larva";195;2
"Unit";"Roach";"Larva";195;2
"Unit";"Roach";"Larva";195;2
"Unit";"Roach";"Larva";195;2
"Upgrade";"ZergMissileWeaponsLevel1";"EvolutionChamber";178;0
"Unit";"Roach";"Larva";219;2
"Unit";"Roach";"Larva";219;2
"Unit";"Roach";"Larva";219;2
"Unit";"Roach";"Larva";219;2
"Unit";"Roach";"Larva";219;2
"Unit";"Roach";"Larva";219;2
"Building";"Hatchery";NA;193;0
"Unit";"Roach";"Larva";231;2
"Unit";"Roach";"Larva";231;2
"Unit";"Roach";"Larva";231;2
"Unit";"Roach";"Larva";231;2
"Unit";"Roach";"Larva";231;2
"Unit";"Roach";"Larva";231;2
"Unit";"Roach";"Larva";231;2
"Unit";"Roach";"Larva";231;2
"Unit";"Roach";"Larva";231;2
"Unit";"Roach";"Larva";231;2
"Unit";"Roach";"Larva";231;2
"Unit";"Roach";"Larva";231;2
"Unit";"Roach";"Larva";231;2
"Unit";"Roach";"Larva";231;2
"Unit";"Roach";"Larva";231;2
"Building";"CreepTumorQueen";NA;264;0
"Building";"CreepTumorQueen";NA;264;0
"Building";"CreepTumor";NA;270;0
"Unit";"Roach";"Larva";269;2
"Unit";"Roach";"Larva";270;2
"Unit";"Roach";"Larva";270;2
"Unit";"Roach";"Larva";270;2
"Unit";"Roach";"Larva";270;2
"Building";"CreepTumorQueen";NA;272;0
"Building";"CreepTumor";NA;270;0
"Building";"CreepTumor";NA;270;0
"Building";"CreepTumorQueen";NA;280;0
"Building";"Hatchery";NA;264;0
"Unit";"Roach";"Larva";286;2
"Unit";"Roach";"Larva";286;2
"Unit";"Roach";"Larva";286;2
"Unit";"Roach";"Larva";286;2
"Unit";"Overlord";"Larva";286;0
"Unit";"Overlord";"Larva";286;0
"Unit";"Overlord";"Larva";286;0
"Unit";"Overlord";"Larva";286;0
"Unit";"Overlord";"Larva";286;0
"Unit";"Roach";"Larva";294;2
"Unit";"Roach";"Larva";294;2
"Unit";"Roach";"Larva";294;2
"Unit";"Roach";"Larva";294;2
"Unit";"Roach";"Larva";294;2
"Unit";"Roach";"Larva";294;2
"Unit";"Roach";"Larva";294;2
"Unit";"Roach";"Larva";294;2
"Unit";"Roach";"Larva";294;2
"Building";"CreepTumor";NA;294;0
"Building";"CreepTumor";NA;294;0
"Building";"CreepTumor";NA;294;0
"Building";"CreepTumor";NA;294;0
"Building";"HydraliskDen";NA;294;0
"Unit";"Overlord";"Larva";297;0
"Unit";"Roach";"Larva";297;2
"Unit";"Roach";"Larva";297;2
"Unit";"Roach";"Larva";299;2
"Building";"CreepTumor";NA;315;0
"Building";"SporeCrawler";NA;315;0
"Building";"Extractor";NA;315;0
"Building";"Extractor";NA;315;0
"Unit";"Roach";"Larva";315;2
"Unit";"Roach";"Larva";315;2
"Unit";"Roach";"Larva";315;2
"Unit";"Roach";"Larva";315;2
"Building";"SpineCrawler";NA;315;0
"Building";"SpineCrawler";NA;315;0
"Upgrade";"ZergMissileWeaponsLevel2";"EvolutionChamber";286;0
"Building";"SpineCrawler";NA;315;0
"Building";"SpineCrawler";NA;315;0
"Building";"CreepTumor";NA;329;0
"Building";"CreepTumor";NA;329;0
"Building";"CreepTumor";NA;329;0
"Building";"CreepTumor";NA;329;0
"Unit";"Hydralisk";"Larva";329;2
"Unit";"Hydralisk";"Larva";329;2
"Unit";"Hydralisk";"Larva";329;2
"Unit";"Hydralisk";"Larva";329;2
"Unit";"Hydralisk";"Larva";329;2
"Unit";"Hydralisk";"Larva";329;2
"Unit";"Hydralisk";"Larva";329;2
"Unit";"Hydralisk";"Larva";329;2
"Unit";"Hydralisk";"Larva";329;2
"Unit";"Hydralisk";"Larva";329;2
"Unit";"Hydralisk";"Larva";329;2
"Upgrade";"EvolveGroovedSpines";"HydraliskDen";329;0
"Building";"Hatchery";NA;321;0
"Building";"SpineCrawler";NA;329;0
"Building";"SpineCrawler";NA;329;0
"Building";"CreepTumor";NA;355;0
"Building";"CreepTumor";NA;355;0
"Building";"CreepTumor";NA;355;0
"Building";"CreepTumor";NA;355;0
"Unit";"Hydralisk";"Larva";355;2
"Unit";"Hydralisk";"Larva";355;2
"Unit";"Hydralisk";"Larva";355;2
"Unit";"Hydralisk";"Larva";355;2
"Unit";"Hydralisk";"Larva";355;2
"Unit";"Hydralisk";"Larva";355;2
"Unit";"Hydralisk";"Larva";355;2
"Unit";"Hydralisk";"Larva";355;2
"Unit";"Hydralisk";"Larva";355;2
"Unit";"Hydralisk";"Larva";355;2
"Building";"CreepTumor";NA;355;0
"Upgrade";"EvolveMuscularAugments";"HydraliskDen";355;0
"Building";"CreepTumor";NA;375;0
"Building";"CreepTumor";NA;375;0
"Building";"CreepTumor";NA;375;0
"Upgrade";"ZergGroundArmorsLevel1";"EvolutionChamber";355;0
"Building";"Spire";NA;355;0
"Building";"CreepTumor";NA;375;0
"Unit";"Hydralisk";"Larva";375;2
"Unit";"Hydralisk";"Larva";375;2
"Unit";"Hydralisk";"Larva";375;2
"Unit";"Hydralisk";"Larva";375;2
"Unit";"Hydralisk";"Larva";375;2
"Unit";"Hydralisk";"Larva";375;2
"Unit";"Hydralisk";"Larva";375;2
"Unit";"Hydralisk";"Larva";375;2
"Unit";"Hydralisk";"Larva";375;2
"Unit";"Hydralisk";"Larva";375;2
"Unit";"Hydralisk";"Larva";375;2
"Unit";"Hydralisk";"Larva";375;2
"Unit";"Hydralisk";"Larva";375;2
"Unit";"Hydralisk";"Larva";375;2
"Unit";"Hydralisk";"Larva";375;2
"Unit";"Hydralisk";"Larva";375;2
"Unit";"Hydralisk";"Larva";375;2
"Unit";"Hydralisk";"Larva";375;2
"Unit";"Hydralisk";"Larva";375;2
"Unit";"Hydralisk";"Larva";375;2
"Unit";"Hydralisk";"Larva";375;2
"Unit";"Hydralisk";"Larva";375;2
"Unit";"Hydralisk";"Larva";375;2
"Building";"CreepTumor";NA;421;0
"Building";"CreepTumor";NA;421;0
"Building";"CreepTumor";NA;421;0
"Building";"Hatchery";NA;375;0
"Building";"SpawningPool";NA;403;0
"Building";"CreepTumor";NA;421;0
"Building";"CreepTumor";NA;421;0
"Building";"CreepTumor";NA;421;0
"Building";"CreepTumor";NA;421;0
"Building";"CreepTumor";NA;421;0
