"type";"unit_name";"on_building";"total_supply";"supply"
"Unit";"Overlord";"Larva";12;0
"Building";"SpawningPool";NA;18;0
"Building";"Hatchery";NA;17;0
"Unit";"Queen";"Hatchery";21;2
"Unit";"Overlord";"Larva";22;0
"Unit";"Queen";"Hatchery";22;2
"Building";"Hatchery";NA;19;0
"Unit";"Zergling";"Larva";26;1
"Unit";"Zergling";"Larva";26;1
"Building";"Extractor";NA;26;0
"Building";"CreepTumorQueen";NA;31;0
"Unit";"Zergling";"Larva";31;1
"Unit";"Zergling";"Larva";31;1
"Building";"CreepTumor";NA;41;0
"Unit";"Queen";"Hatchery";31;2
"Unit";"Overlord";"Larva";39;0
"Unit";"Overlord";"Larva";41;0
"Building";"CreepTumorQueen";NA;48;0
"Building";"Extractor";NA;48;0
"Building";"SporeCrawler";NA;49;0
"Building";"SporeCrawler";NA;51;0
"Building";"SporeCrawler";NA;52;0
"Building";"RoachWarren";NA;48;0
"Building";"CreepTumor";NA;57;0
"Unit";"Overlord";"Larva";58;0
"Building";"CreepTumor";NA;61;0
"Building";"Extractor";NA;68;0
"Unit";"Overlord";"Larva";68;0
"Building";"CreepTumor";NA;69;0
"Building";"EvolutionChamber";NA;76;0
"Building";"EvolutionChamber";NA;77;0
"Building";"Extractor";NA;78;0
"Building";"CreepTumor";NA;88;0
"Building";"CreepTumor";NA;90;0
"Unit";"Overlord";"Larva";88;0
"Unit";"Overlord";"Larva";88;0
"Unit";"Overlord";"Larva";93;0
"Unit";"Roach";"Larva";93;2
"Unit";"Overlord";"Larva";93;0
"Unit";"Overlord";"Larva";95;0
"Unit";"Overlord";"Larva";95;0
"Unit";"Roach";"Larva";95;2
"Unit";"Roach";"Larva";95;2
"Unit";"Roach";"Larva";95;2
"Building";"Extractor";NA;95;0
"Unit";"Roach";"Larva";95;2
"Unit";"Roach";"Larva";95;2
"Unit";"Roach";"Larva";95;2
"Unit";"Roach";"Larva";95;2
"Unit";"Roach";"Larva";97;2
"Unit";"Roach";"Larva";97;2
"Unit";"Roach";"Larva";97;2
"Building";"CreepTumor";NA;117;0
"Building";"Hatchery";NA;84;0
"Unit";"Roach";"Larva";113;2
"Unit";"Roach";"Larva";113;2
"Unit";"Roach";"Larva";113;2
"Unit";"Roach";"Larva";113;2
"Unit";"Roach";"Larva";113;2
"Unit";"Roach";"Larva";115;2
"Unit";"Roach";"Larva";118;2
"Unit";"Roach";"Larva";118;2
"Building";"Extractor";NA;118;0
"Unit";"Roach";"Larva";119;2
"Unit";"Roach";"Larva";119;2
"Unit";"Roach";"Larva";119;2
"Unit";"Roach";"Larva";120;2
"Building";"BanelingNest";NA;107;0
"Unit";"Zergling";"Larva";143;1
"Unit";"Zergling";"Larva";143;1
"Unit";"Zergling";"Larva";143;1
"Unit";"Zergling";"Larva";143;1
"Unit";"Zergling";"Larva";143;1
"Unit";"Zergling";"Larva";143;1
"Unit";"Zergling";"Larva";143;1
"Unit";"Zergling";"Larva";143;1
"Unit";"Zergling";"Larva";145;1
"Unit";"Zergling";"Larva";145;1
"Unit";"Zergling";"Larva";145;1
"Unit";"Zergling";"Larva";145;1
"Unit";"Zergling";"Larva";145;1
"Unit";"Zergling";"Larva";145;1
"Unit";"Queen";"Hatchery";120;2
"Unit";"Overlord";"Larva";148;0
"Unit";"Overlord";"Larva";148;0
"Unit";"Overlord";"Larva";148;0
"Building";"SporeCrawler";NA;148;0
"Upgrade";"ZergMissileWeaponsLevel1";"EvolutionChamber";97;0
"Upgrade";"ZergGroundArmorsLevel1";"EvolutionChamber";97;0
"Upgrade";"GlialReconstitution";"RoachWarren";119;0
"Unit";"Overlord";"Larva";163;0
"Unit";"Baneling";"Zergling";166;0
"Unit";"Baneling";"Zergling";167;0
"Unit";"Baneling";"Zergling";168;0
"Unit";"Baneling";"Zergling";168;0
"Unit";"Overlord";"Larva";166;0
"Unit";"Baneling";"Zergling";168;0
"Unit";"Overlord";"Larva";166;0
"Unit";"Baneling";"Zergling";168;0
"Unit";"Baneling";"Zergling";168;0
"Unit";"Baneling";"Zergling";168;0
"Unit";"Baneling";"Zergling";168;0
"Unit";"Baneling";"Zergling";168;0
"Unit";"Baneling";"Zergling";168;0
"Unit";"Baneling";"Zergling";168;0
"Unit";"Baneling";"Zergling";168;0
"Unit";"Baneling";"Zergling";168;0
"Unit";"Baneling";"Zergling";168;0
"Unit";"Baneling";"Zergling";168;0
"Unit";"Baneling";"Zergling";168;0
"Unit";"Baneling";"Zergling";168;0
"Unit";"Roach";"Larva";173;2
"Unit";"Roach";"Larva";173;2
"Unit";"Roach";"Larva";173;2
"Unit";"Roach";"Larva";173;2
"Unit";"Roach";"Larva";174;2
"Unit";"Roach";"Larva";174;2
"Unit";"Roach";"Larva";177;2
"Unit";"Roach";"Larva";177;2
"Unit";"Roach";"Larva";177;2
"Unit";"Roach";"Larva";177;2
"Unit";"Roach";"Larva";177;2
"Unit";"Roach";"Larva";177;2
"Unit";"Roach";"Larva";177;2
"Unit";"Roach";"Larva";177;2
"Unit";"Roach";"Larva";179;2
"Unit";"Roach";"Larva";181;2
"Unit";"Roach";"Larva";181;2
"Unit";"Roach";"Larva";187;2
"Unit";"Roach";"Larva";189;2
"Unit";"Roach";"Larva";189;2
"Unit";"Roach";"Larva";193;2
"Unit";"Roach";"Larva";193;2
"Unit";"Roach";"Larva";197;2
"Unit";"Overlord";"Larva";199;0
"Unit";"Zergling";"Larva";205;1
"Unit";"Zergling";"Larva";205;1
"Unit";"Zergling";"Larva";207;1
"Unit";"Zergling";"Larva";207;1
"Unit";"Zergling";"Larva";207;1
"Unit";"Zergling";"Larva";207;1
"Building";"CreepTumorQueen";NA;223;0
"Unit";"Zergling";"Larva";217;1
"Unit";"Zergling";"Larva";217;1
"Unit";"Zergling";"Larva";219;1
"Unit";"Zergling";"Larva";219;1
"Building";"CreepTumor";NA;226;0
"Unit";"Zergling";"Larva";226;1
"Unit";"Zergling";"Larva";226;1
"Unit";"Zergling";"Larva";226;1
"Unit";"Zergling";"Larva";226;1
"Unit";"Zergling";"Larva";226;1
"Unit";"Zergling";"Larva";226;1
"Unit";"Zergling";"Larva";226;1
"Unit";"Zergling";"Larva";226;1
"Unit";"Zergling";"Larva";232;1
"Unit";"Zergling";"Larva";232;1
"Unit";"Zergling";"Larva";232;1
"Unit";"Zergling";"Larva";232;1
"Unit";"Zergling";"Larva";232;1
"Unit";"Zergling";"Larva";232;1
"Unit";"Zergling";"Larva";232;1
"Unit";"Zergling";"Larva";232;1
"Unit";"Zergling";"Larva";236;1
"Unit";"Zergling";"Larva";236;1
"Unit";"Zergling";"Larva";236;1
"Unit";"Zergling";"Larva";236;1
"Unit";"Zergling";"Larva";248;1
"Unit";"Zergling";"Larva";248;1
"Unit";"Zergling";"Larva";252;1
"Unit";"Zergling";"Larva";252;1
"Unit";"Zergling";"Larva";252;1
"Unit";"Zergling";"Larva";252;1
"Unit";"Roach";"Larva";256;2
"Unit";"Roach";"Larva";256;2
"Unit";"Roach";"Larva";256;2
"Unit";"Roach";"Larva";256;2
"Unit";"Roach";"Larva";256;2
"Unit";"Roach";"Larva";256;2
"Unit";"Roach";"Larva";256;2
"Unit";"Roach";"Larva";256;2
"Unit";"Roach";"Larva";256;2
"Unit";"Roach";"Larva";258;2
"Unit";"Roach";"Larva";258;2
"Unit";"Roach";"Larva";258;2
"Unit";"Roach";"Larva";258;2
"Unit";"Roach";"Larva";258;2
"Unit";"Roach";"Larva";258;2
"Unit";"Roach";"Larva";258;2
"Unit";"Roach";"Larva";262;2
"Unit";"Roach";"Larva";262;2
"Upgrade";"ZergMissileWeaponsLevel2";"EvolutionChamber";181;0
"Upgrade";"ZergGroundArmorsLevel2";"EvolutionChamber";181;0
"Unit";"Roach";"Larva";262;2
"Unit";"Roach";"Larva";262;2
"Unit";"Roach";"Larva";262;2
"Unit";"Roach";"Larva";270;2
"Unit";"Roach";"Larva";278;2
"Unit";"Roach";"Larva";294;2
"Unit";"Roach";"Larva";294;2
"Building";"Hatchery";NA;236;0
"Unit";"Roach";"Larva";298;2
"Unit";"Roach";"Larva";304;2
"Unit";"Roach";"Larva";304;2
"Unit";"Roach";"Larva";304;2
"Unit";"Roach";"Larva";306;2
"Unit";"Roach";"Larva";308;2
"Unit";"Baneling";"Zergling";312;0
"Unit";"Baneling";"Zergling";312;0
"Unit";"Baneling";"Zergling";312;0
"Unit";"Baneling";"Zergling";312;0
"Building";"CreepTumor";NA;314;0
"Unit";"Roach";"Larva";314;2
"Building";"Extractor";NA;314;0
"Unit";"Roach";"Larva";314;2
"Unit";"Roach";"Larva";314;2
"Building";"Extractor";NA;314;0
"Unit";"Roach";"Larva";320;2
"Unit";"Roach";"Larva";320;2
"Unit";"Roach";"Larva";322;2
"Unit";"Overlord";"Larva";326;0
"Unit";"Overlord";"Larva";326;0
"Unit";"Overlord";"Larva";326;0
"Unit";"Queen";"Hatchery";314;2
"Unit";"Roach";"Larva";338;2
"Unit";"Roach";"Larva";338;2
"Unit";"Roach";"Larva";338;2
"Unit";"Roach";"Larva";340;2
"Unit";"Roach";"Larva";340;2
"Unit";"Roach";"Larva";340;2
"Unit";"Roach";"Larva";340;2
"Unit";"Roach";"Larva";340;2
"Unit";"Roach";"Larva";340;2
"Unit";"Roach";"Larva";340;2
"Unit";"Roach";"Larva";340;2
"Unit";"Roach";"Larva";340;2
"Unit";"Roach";"Larva";340;2
"Unit";"Roach";"Larva";340;2
"Unit";"Roach";"Larva";340;2
"Unit";"Roach";"Larva";340;2
"Unit";"Roach";"Larva";340;2
"Unit";"Roach";"Larva";340;2
"Building";"CreepTumor";NA;356;0
"Unit";"Overlord";"Larva";354;0
"Unit";"Roach";"Larva";354;2
"Unit";"Roach";"Larva";354;2
"Unit";"Roach";"Larva";354;2
"Unit";"Roach";"Larva";362;2
"Building";"Spire";NA;326;0
"Unit";"Roach";"Larva";362;2
"Unit";"Roach";"Larva";362;2
