"type";"unit_name";"on_building";"total_supply";"supply"
"Unit";"Overlord";"Larva";12;0
"Building";"Extractor";NA;17;0
"Building";"SpawningPool";NA;18;0
"Unit";"Overlord";"Larva";21;0
"Building";"Hatchery";NA;16;0
"Unit";"Zergling";"Larva";22;1
"Unit";"Zergling";"Larva";22;1
"Unit";"Zergling";"Larva";22;1
"Unit";"Zergling";"Larva";22;1
"Unit";"Queen";"Hatchery";22;2
"Unit";"Queen";"Hatchery";22;2
"Building";"CreepTumorQueen";NA;35;0
"Unit";"Zergling";"Larva";35;1
"Unit";"Zergling";"Larva";35;1
"Unit";"Zergling";"Larva";36;1
"Unit";"Zergling";"Larva";36;1
"Unit";"Zergling";"Larva";36;1
"Unit";"Zergling";"Larva";36;1
"Unit";"Zergling";"Larva";36;1
"Unit";"Zergling";"Larva";36;1
"Building";"CreepTumorQueen";NA;36;0
"Building";"CreepTumor";NA;36;0
"Unit";"Queen";"Hatchery";35;2
"Unit";"Overlord";"Larva";36;0
"Unit";"Overlord";"Larva";46;0
"Building";"Hatchery";NA;34;0
"Unit";"Overlord";"Larva";52;0
"Building";"CreepTumor";NA;53;0
"Building";"SporeCrawler";NA;52;0
"Building";"SporeCrawler";NA;52;0
"Building";"CreepTumor";NA;59;0
"Building";"CreepTumor";NA;61;0
"Building";"Extractor";NA;58;0
"Building";"SporeCrawler";NA;58;0
"Building";"CreepTumorQueen";NA;61;0
"Unit";"Queen";"Hatchery";53;2
"Unit";"Overlord";"Larva";65;0
"Building";"RoachWarren";NA;58;0
"Building";"CreepTumor";NA;67;0
"Building";"CreepTumor";NA;67;0
"Unit";"Overlord";"Larva";67;0
"Building";"Extractor";NA;74;0
"Unit";"Overlord";"Larva";74;0
"Unit";"Overlord";"Larva";74;0
"Building";"CreepTumor";NA;80;0
"Building";"CreepTumor";NA;85;0
"Building";"Extractor";NA;80;0
"Building";"CreepTumor";NA;89;0
"Building";"Extractor";NA;89;0
"Building";"Extractor";NA;89;0
"Unit";"Zergling";"Larva";89;1
"Unit";"Zergling";"Larva";89;1
"Unit";"Zergling";"Larva";89;1
"Unit";"Zergling";"Larva";89;1
"Unit";"Zergling";"Larva";89;1
"Unit";"Zergling";"Larva";89;1
"Unit";"Zergling";"Larva";89;1
"Unit";"Zergling";"Larva";89;1
"Unit";"Zergling";"Larva";89;1
"Unit";"Zergling";"Larva";89;1
"Unit";"Zergling";"Larva";89;1
"Unit";"Zergling";"Larva";89;1
"Unit";"Zergling";"Larva";89;1
"Unit";"Zergling";"Larva";89;1
"Unit";"Zergling";"Larva";89;1
"Unit";"Zergling";"Larva";89;1
"Unit";"Zergling";"Larva";89;1
"Unit";"Zergling";"Larva";89;1
"Building";"EvolutionChamber";NA;89;0
"Unit";"Overlord";"Larva";89;0
"Unit";"Overlord";"Larva";89;0
"Unit";"Overlord";"Larva";89;0
"Unit";"Overlord";"Larva";89;0
"Building";"CreepTumor";NA;91;0
"Building";"CreepTumor";NA;91;0
"Building";"CreepTumor";NA;91;0
"Building";"HydraliskDen";NA;89;0
"Unit";"Overlord";"Larva";109;0
"Unit";"Overlord";"Larva";109;0
"Unit";"Overlord";"Larva";111;0
"Unit";"Overlord";"Larva";112;0
"Building";"CreepTumor";NA;112;0
"Unit";"Overlord";"Larva";112;0
"Unit";"Hydralisk";"Larva";112;2
"Unit";"Zergling";"Larva";112;1
"Unit";"Zergling";"Larva";112;1
"Unit";"Hydralisk";"Larva";112;2
"Unit";"Hydralisk";"Larva";112;2
"Unit";"Hydralisk";"Larva";112;2
"Unit";"Zergling";"Larva";112;1
"Unit";"Zergling";"Larva";112;1
"Unit";"Hydralisk";"Larva";112;2
"Unit";"Hydralisk";"Larva";112;2
"Unit";"Zergling";"Larva";112;1
"Unit";"Zergling";"Larva";112;1
"Unit";"Hydralisk";"Larva";112;2
"Unit";"Hydralisk";"Larva";112;2
"Unit";"Hydralisk";"Larva";112;2
"Unit";"Hydralisk";"Larva";112;2
"Unit";"Hydralisk";"Larva";112;2
"Unit";"Hydralisk";"Larva";112;2
"Unit";"Hydralisk";"Larva";112;2
"Unit";"Hydralisk";"Larva";112;2
"Unit";"Hydralisk";"Larva";112;2
"Unit";"Hydralisk";"Larva";112;2
"Building";"CreepTumor";NA;144;0
"Building";"CreepTumor";NA;150;0
"Unit";"Hydralisk";"Larva";144;2
"Unit";"Hydralisk";"Larva";144;2
"Unit";"Hydralisk";"Larva";144;2
"Unit";"Hydralisk";"Larva";144;2
"Unit";"Hydralisk";"Larva";144;2
"Unit";"Hydralisk";"Larva";144;2
"Upgrade";"EvolveMuscularAugments";"HydraliskDen";112;0
"Unit";"Hydralisk";"Larva";155;2
"Unit";"Hydralisk";"Larva";155;2
"Unit";"Hydralisk";"Larva";155;2
"Unit";"Hydralisk";"Larva";167;2
"Upgrade";"ZergMissileWeaponsLevel1";"EvolutionChamber";112;0
"Unit";"Hydralisk";"Larva";168;2
"Building";"CreepTumor";NA;181;0
"Unit";"Hydralisk";"Larva";170;2
"Unit";"Hydralisk";"Larva";171;2
"Unit";"Hydralisk";"Larva";174;2
"Unit";"Hydralisk";"Larva";175;2
"Unit";"Hydralisk";"Larva";183;2
"Unit";"Hydralisk";"Larva";183;2
"Unit";"Hydralisk";"Larva";183;2
"Unit";"Hydralisk";"Larva";191;2
"Unit";"Hydralisk";"Larva";191;2
"Unit";"Hydralisk";"Larva";191;2
"Unit";"Hydralisk";"Larva";191;2
"Unit";"Hydralisk";"Larva";191;2
"Building";"CreepTumor";NA;197;0
"Building";"LurkerDenMP";NA;155;0
"Upgrade";"EvolveGroovedSpines";"HydraliskDen";183;0
"Building";"CreepTumor";NA;215;0
"Unit";"Hydralisk";"Larva";207;2
"Unit";"Hydralisk";"Larva";207;2
"Unit";"Hydralisk";"Larva";207;2
"Unit";"Hydralisk";"Larva";207;2
"Unit";"Hydralisk";"Larva";207;2
"Unit";"Hydralisk";"Larva";207;2
"Unit";"Hydralisk";"Larva";207;2
"Building";"CreepTumor";NA;215;0
"Building";"CreepTumor";NA;215;0
"Unit";"Queen";"Hatchery";207;2
"Building";"Hatchery";NA;183;0
"Unit";"Overlord";"Larva";229;0
"Unit";"Zergling";"Larva";229;1
"Unit";"Zergling";"Larva";229;1
"Unit";"Zergling";"Larva";229;1
"Unit";"Zergling";"Larva";229;1
"Unit";"Zergling";"Larva";229;1
"Unit";"Zergling";"Larva";229;1
"Unit";"Zergling";"Larva";229;1
"Unit";"Zergling";"Larva";229;1
"Unit";"Zergling";"Larva";229;1
"Unit";"Zergling";"Larva";229;1
"Unit";"Zergling";"Larva";229;1
"Unit";"Zergling";"Larva";229;1
"Unit";"Zergling";"Larva";229;1
"Unit";"Zergling";"Larva";229;1
"Unit";"Zergling";"Larva";229;1
"Unit";"Zergling";"Larva";229;1
"Unit";"Zergling";"Larva";231;1
"Unit";"Zergling";"Larva";231;1
"Unit";"Zergling";"Larva";231;1
"Unit";"Zergling";"Larva";231;1
"Unit";"Zergling";"Larva";231;1
"Unit";"Zergling";"Larva";231;1
"Unit";"Zergling";"Larva";231;1
"Unit";"Zergling";"Larva";231;1
"Unit";"Zergling";"Larva";231;1
"Unit";"Zergling";"Larva";231;1
"Unit";"Zergling";"Larva";231;1
"Unit";"Zergling";"Larva";231;1
"Unit";"Zergling";"Larva";231;1
"Unit";"Zergling";"Larva";231;1
"Unit";"Zergling";"Larva";231;1
"Unit";"Zergling";"Larva";231;1
"Unit";"Zergling";"Larva";231;1
"Unit";"Zergling";"Larva";231;1
"Unit";"Zergling";"Larva";231;1
"Unit";"Zergling";"Larva";231;1
"Unit";"Zergling";"Larva";231;1
"Unit";"Zergling";"Larva";231;1
"Unit";"Zergling";"Larva";231;1
"Unit";"Zergling";"Larva";231;1
"Building";"Extractor";NA;231;0
"Unit";"Overlord";"Larva";231;0
"Unit";"Overlord";"Larva";231;0
"Building";"Extractor";NA;231;0
"Unit";"Hydralisk";"Larva";272;2
"Unit";"Hydralisk";"Larva";272;2
"Unit";"Hydralisk";"Larva";272;2
"Unit";"Hydralisk";"Larva";272;2
"Unit";"Hydralisk";"Larva";272;2
"Building";"SpineCrawler";NA;247;0
"Unit";"Zergling";"Larva";272;1
"Unit";"Zergling";"Larva";272;1
"Unit";"Zergling";"Larva";272;1
"Unit";"Zergling";"Larva";272;1
"Unit";"Zergling";"Larva";272;1
"Unit";"Zergling";"Larva";272;1
"Unit";"Zergling";"Larva";272;1
"Unit";"Zergling";"Larva";272;1
"Building";"SpineCrawler";NA;248;0
"Unit";"Hydralisk";"Larva";272;2
"Unit";"Hydralisk";"Larva";272;2
"Unit";"Queen";"Hatchery";272;2
"Unit";"Hydralisk";"Larva";272;2
"Unit";"Hydralisk";"Larva";272;2
"Unit";"Hydralisk";"Larva";272;2
"Unit";"Hydralisk";"Larva";290;2
"Unit";"Hydralisk";"Larva";290;2
"Unit";"Hydralisk";"Larva";290;2
"Unit";"Hydralisk";"Larva";290;2
"Unit";"Hydralisk";"Larva";290;2
"Unit";"Hydralisk";"Larva";312;2
"Unit";"Hydralisk";"Larva";312;2
"Unit";"Hydralisk";"Larva";312;2
"Unit";"Hydralisk";"Larva";312;2
"Unit";"Hydralisk";"Larva";312;2
"Unit";"Hydralisk";"Larva";312;2
"Unit";"Hydralisk";"Larva";312;2
"Unit";"Hydralisk";"Larva";312;2
"Unit";"Hydralisk";"Larva";312;2
"Unit";"Overlord";"Larva";312;0
"Unit";"Overlord";"Larva";312;0
"Unit";"Overlord";"Larva";312;0
"Unit";"Hydralisk";"Larva";312;2
"Upgrade";"ZergMissileWeaponsLevel2";"EvolutionChamber";248;0
"Unit";"Overlord";"Larva";330;0
"Unit";"Overlord";"Larva";330;0
"Unit";"Overlord";"Larva";330;0
"Building";"InfestationPit";NA;312;0
"Building";"SpineCrawler";NA;330;0
"Unit";"Hydralisk";"Larva";333;2
"Unit";"Hydralisk";"Larva";333;2
"Unit";"Hydralisk";"Larva";333;2
"Unit";"Hydralisk";"Larva";333;2
"Unit";"Hydralisk";"Larva";333;2
"Unit";"Hydralisk";"Larva";333;2
"Unit";"Hydralisk";"Larva";333;2
"Unit";"Hydralisk";"Larva";333;2
"Unit";"Hydralisk";"Larva";333;2
