"type";"unit_name";"on_building";"total_supply";"supply"
"Unit";"Overlord";"Larva";13;0
"Building";"Extractor";NA;17;0
"Unit";"Overlord";"Larva";21;0
"Building";"SpawningPool";NA;18;0
"Building";"Hatchery";NA;16;0
"Unit";"Zergling";"Larva";23;1
"Unit";"Zergling";"Larva";23;1
"Unit";"Queen";"Hatchery";22;2
"Unit";"Queen";"Hatchery";22;2
"Unit";"Overlord";"Larva";34;0
"Unit";"Overlord";"Larva";36;0
"Unit";"Overlord";"Larva";38;0
"Unit";"Overlord";"Larva";38;0
"Unit";"Queen";"Hatchery";36;2
"Unit";"Overlord";"Larva";44;0
"Building";"RoachWarren";NA;38;0
"Building";"CreepTumorQueen";NA;46;0
"Building";"Extractor";NA;44;0
"Building";"Extractor";NA;44;0
"Unit";"Roach";"Larva";46;2
"Unit";"Roach";"Larva";46;2
"Unit";"Roach";"Larva";46;2
"Unit";"Queen";"Hatchery";44;2
"Unit";"Overlord";"Larva";50;0
"Unit";"Roach";"Larva";50;2
"Unit";"Roach";"Larva";50;2
"Unit";"Roach";"Larva";50;2
"Building";"CreepTumor";NA;56;0
"Unit";"Roach";"Larva";50;2
"Unit";"Roach";"Larva";50;2
"Building";"SporeCrawler";NA;58;0
"Unit";"Roach";"Larva";64;2
"Unit";"Roach";"Larva";68;2
"Unit";"Roach";"Larva";68;2
"Unit";"Roach";"Larva";68;2
"Unit";"Overlord";"Larva";70;0
"Unit";"Roach";"Larva";70;2
"Building";"CreepTumorQueen";NA;76;0
"Building";"CreepTumorQueen";NA;76;0
"Unit";"Roach";"Larva";78;2
"Unit";"Roach";"Larva";78;2
"Unit";"Roach";"Larva";78;2
"Building";"CreepTumor";NA;78;0
"Unit";"Zergling";"Larva";78;1
"Unit";"Zergling";"Larva";78;1
"Unit";"Overlord";"Larva";86;0
"Unit";"Overlord";"Larva";86;0
"Building";"CreepTumorQueen";NA;86;0
"Unit";"Overlord";"Larva";86;0
"Unit";"Overlord";"Larva";86;0
"Building";"Hatchery";NA;76;0
"Unit";"Overlord";"Larva";86;0
"Unit";"Overlord";"Larva";86;0
"Unit";"Overlord";"Larva";86;0
"Unit";"Roach";"Larva";86;2
"Building";"CreepTumorQueen";NA;87;0
"Building";"CreepTumorQueen";NA;87;0
"Building";"CreepTumor";NA;89;0
"Unit";"Roach";"Larva";89;2
"Unit";"Roach";"Larva";89;2
"Unit";"Roach";"Larva";89;2
"Unit";"Roach";"Larva";89;2
"Unit";"Roach";"Larva";89;2
"Unit";"Roach";"Larva";89;2
"Building";"CreepTumor";NA;89;0
"Unit";"Roach";"Larva";89;2
"Building";"CreepTumor";NA;101;0
"Unit";"Roach";"Larva";101;2
"Unit";"Roach";"Larva";101;2
"Building";"EvolutionChamber";NA;103;0
"Unit";"Roach";"Larva";107;2
"Unit";"Roach";"Larva";107;2
"Unit";"Roach";"Larva";107;2
"Upgrade";"GlialReconstitution";"RoachWarren";101;0
"Unit";"Roach";"Larva";107;2
"Unit";"Roach";"Larva";107;2
"Unit";"Roach";"Larva";107;2
"Unit";"Roach";"Larva";107;2
"Building";"CreepTumor";NA;113;0
"Unit";"Roach";"Larva";107;2
"Unit";"Roach";"Larva";107;2
"Unit";"Queen";"Hatchery";107;2
"Building";"Extractor";NA;107;0
"Unit";"Queen";"Hatchery";107;2
"Unit";"Roach";"Larva";121;2
"Unit";"Roach";"Larva";121;2
"Unit";"Roach";"Larva";121;2
"Unit";"Roach";"Larva";121;2
"Unit";"Roach";"Larva";121;2
"Unit";"Roach";"Larva";121;2
"Unit";"Roach";"Larva";127;2
"Unit";"Roach";"Larva";127;2
"Unit";"Roach";"Larva";145;2
"Unit";"Roach";"Larva";145;2
"Unit";"Roach";"Larva";145;2
"Unit";"Roach";"Larva";145;2
"Unit";"Roach";"Larva";145;2
"Unit";"Roach";"Larva";145;2
"Unit";"Roach";"Larva";145;2
"Unit";"Roach";"Larva";145;2
"Unit";"Roach";"Larva";145;2
"Unit";"Roach";"Larva";168;2
"Building";"CreepTumor";NA;173;0
"Building";"CreepTumor";NA;173;0
"Building";"CreepTumor";NA;173;0
"Unit";"Roach";"Larva";175;2
"Unit";"Roach";"Larva";175;2
"Unit";"Roach";"Larva";175;2
"Unit";"Roach";"Larva";175;2
"Unit";"Roach";"Larva";175;2
"Building";"Spire";NA;166;0
"Unit";"Overlord";"Larva";185;0
"Unit";"Overlord";"Larva";185;0
"Upgrade";"ZergMissileWeaponsLevel1";"EvolutionChamber";168;0
"Unit";"Overlord";"Larva";185;0
"Unit";"Mutalisk";"Larva";185;2
"Unit";"Mutalisk";"Larva";185;2
"Unit";"Mutalisk";"Larva";185;2
"Unit";"Mutalisk";"Larva";185;2
"Unit";"Mutalisk";"Larva";185;2
"Unit";"Mutalisk";"Larva";185;2
"Unit";"Mutalisk";"Larva";185;2
"Unit";"Mutalisk";"Larva";185;2
"Unit";"Mutalisk";"Larva";185;2
"Unit";"Mutalisk";"Larva";185;2
"Building";"Hatchery";NA;185;0
"Unit";"Overlord";"Larva";208;0
"Unit";"Overlord";"Larva";208;0
"Unit";"Overlord";"Larva";208;0
"Building";"SporeCrawler";NA;208;0
"Unit";"Roach";"Larva";208;2
"Unit";"Roach";"Larva";208;2
"Unit";"Roach";"Larva";208;2
"Unit";"Roach";"Larva";208;2
"Unit";"Roach";"Larva";208;2
"Unit";"Roach";"Larva";220;2
"Unit";"Roach";"Larva";220;2
"Unit";"Roach";"Larva";220;2
"Unit";"Overlord";"Larva";224;0
"Unit";"Roach";"Larva";230;2
"Unit";"Roach";"Larva";230;2
"Building";"CreepTumorQueen";NA;231;0
"Unit";"Overlord";"Larva";231;0
"Unit";"Roach";"Larva";231;2
"Unit";"Roach";"Larva";231;2
"Unit";"Roach";"Larva";231;2
"Unit";"Roach";"Larva";231;2
"Unit";"Roach";"Larva";243;2
"Unit";"Roach";"Larva";243;2
"Unit";"Roach";"Larva";243;2
"Unit";"Roach";"Larva";243;2
"Unit";"Roach";"Larva";243;2
"Unit";"Roach";"Larva";243;2
"Unit";"Roach";"Larva";243;2
"Unit";"Roach";"Larva";243;2
"Unit";"Roach";"Larva";243;2
"Upgrade";"ZergMissileWeaponsLevel2";"EvolutionChamber";210;0
"Unit";"Roach";"Larva";243;2
"Unit";"Roach";"Larva";243;2
"Unit";"Roach";"Larva";243;2
"Unit";"Roach";"Larva";261;2
"Unit";"Roach";"Larva";261;2
"Unit";"Zergling";"Larva";267;1
"Unit";"Zergling";"Larva";267;1
"Unit";"Zergling";"Larva";267;1
"Unit";"Zergling";"Larva";267;1
"Unit";"Zergling";"Larva";267;1
"Unit";"Zergling";"Larva";267;1
"Unit";"Zergling";"Larva";267;1
"Unit";"Zergling";"Larva";267;1
"Unit";"Zergling";"Larva";267;1
"Unit";"Zergling";"Larva";267;1
