"type";"unit_name";"on_building";"total_supply";"supply"
"Unit";"Overlord";"Larva";12;0
"Building";"Extractor";NA;17;0
"Building";"SpawningPool";NA;17;0
"Unit";"Zergling";"Larva";20;1
"Unit";"Zergling";"Larva";20;1
"Unit";"Overlord";"Larva";20;0
"Unit";"Queen";"Hatchery";20;2
"Building";"Hatchery";NA;20;0
"Unit";"Queen";"Hatchery";29;2
"Building";"Hatchery";NA;24;0
"Building";"EvolutionChamber";NA;30;0
"Unit";"Zergling";"Larva";34;1
"Unit";"Zergling";"Larva";34;1
"Unit";"Zergling";"Larva";34;1
"Unit";"Zergling";"Larva";34;1
"Unit";"Zergling";"Larva";34;1
"Unit";"Zergling";"Larva";34;1
"Unit";"Zergling";"Larva";37;1
"Unit";"Zergling";"Larva";37;1
"Building";"CreepTumorQueen";NA;44;0
"Unit";"Overlord";"Larva";44;0
"Unit";"Queen";"Hatchery";44;2
"Building";"SporeCrawler";NA;46;0
"Unit";"Zergling";"Larva";47;1
"Unit";"Zergling";"Larva";47;1
"Unit";"Zergling";"Larva";47;1
"Unit";"Zergling";"Larva";47;1
"Unit";"Zergling";"Larva";47;1
"Unit";"Zergling";"Larva";47;1
"Unit";"Zergling";"Larva";47;1
"Unit";"Zergling";"Larva";47;1
"Unit";"Zergling";"Larva";47;1
"Unit";"Zergling";"Larva";47;1
"Building";"SporeCrawler";NA;47;0
"Unit";"Zergling";"Larva";47;1
"Unit";"Zergling";"Larva";47;1
"Unit";"Zergling";"Larva";65;1
"Unit";"Zergling";"Larva";65;1
"Building";"CreepTumorQueen";NA;69;0
"Unit";"Overlord";"Larva";76;0
"Unit";"Overlord";"Larva";76;0
"Unit";"Overlord";"Larva";76;0
"Unit";"Overlord";"Larva";76;0
"Unit";"Overlord";"Larva";76;0
"Unit";"Overlord";"Larva";77;0
"Upgrade";"ZergMeleeWeaponsLevel1";"EvolutionChamber";47;0
"Unit";"Zergling";"Larva";77;1
"Unit";"Zergling";"Larva";77;1
"Unit";"Zergling";"Larva";77;1
"Unit";"Zergling";"Larva";77;1
"Unit";"Zergling";"Larva";77;1
"Unit";"Zergling";"Larva";77;1
"Unit";"Zergling";"Larva";77;1
"Unit";"Zergling";"Larva";77;1
"Unit";"Zergling";"Larva";77;1
"Unit";"Zergling";"Larva";77;1
"Unit";"Zergling";"Larva";77;1
"Unit";"Zergling";"Larva";77;1
"Unit";"Zergling";"Larva";77;1
"Unit";"Zergling";"Larva";77;1
"Unit";"Zergling";"Larva";77;1
"Unit";"Zergling";"Larva";77;1
"Unit";"Zergling";"Larva";77;1
"Unit";"Zergling";"Larva";77;1
"Building";"CreepTumor";NA;77;0
"Unit";"Queen";"Hatchery";76;2
"Unit";"Zergling";"Larva";98;1
"Unit";"Zergling";"Larva";98;1
"Unit";"Zergling";"Larva";98;1
"Unit";"Zergling";"Larva";98;1
"Unit";"Queen";"Hatchery";91;2
"Unit";"Queen";"Hatchery";96;2
"Unit";"Zergling";"Larva";104;1
"Unit";"Zergling";"Larva";104;1
"Unit";"Zergling";"Larva";104;1
"Unit";"Zergling";"Larva";104;1
"Unit";"Zergling";"Larva";104;1
"Unit";"Zergling";"Larva";104;1
"Unit";"Zergling";"Larva";104;1
"Unit";"Zergling";"Larva";104;1
"Unit";"Zergling";"Larva";104;1
"Unit";"Zergling";"Larva";104;1
"Unit";"Zergling";"Larva";104;1
"Unit";"Zergling";"Larva";104;1
"Unit";"Zergling";"Larva";104;1
"Unit";"Zergling";"Larva";104;1
"Unit";"Zergling";"Larva";104;1
"Unit";"Zergling";"Larva";104;1
"Building";"CreepTumorQueen";NA;114;0
"Unit";"Overlord";"Larva";114;0
"Unit";"Overlord";"Larva";114;0
"Building";"BanelingNest";NA;114;0
"Unit";"Overlord";"Larva";139;0
"Building";"CreepTumorQueen";NA;141;0
"Building";"CreepTumor";NA;141;0
"Building";"Extractor";NA;141;0
"Building";"Extractor";NA;141;0
"Unit";"Zergling";"Larva";147;1
"Unit";"Zergling";"Larva";147;1
"Unit";"Zergling";"Larva";147;1
"Unit";"Zergling";"Larva";147;1
"Unit";"Zergling";"Larva";147;1
"Unit";"Zergling";"Larva";147;1
"Building";"InfestationPit";NA;141;0
"Unit";"Zergling";"Larva";150;1
"Unit";"Zergling";"Larva";150;1
"Unit";"Zergling";"Larva";150;1
"Unit";"Zergling";"Larva";150;1
"Unit";"Zergling";"Larva";150;1
"Unit";"Zergling";"Larva";150;1
"Building";"EvolutionChamber";NA;150;0
"Building";"Extractor";NA;150;0
"Building";"Extractor";NA;150;0
"Unit";"Overlord";"Larva";156;0
"Unit";"Zergling";"Larva";156;1
"Unit";"Zergling";"Larva";156;1
"Unit";"Zergling";"Larva";156;1
"Unit";"Zergling";"Larva";156;1
"Unit";"Zergling";"Larva";156;1
"Unit";"Zergling";"Larva";156;1
"Unit";"Zergling";"Larva";156;1
"Unit";"Zergling";"Larva";156;1
"Unit";"Zergling";"Larva";156;1
"Unit";"Zergling";"Larva";156;1
"Unit";"Zergling";"Larva";156;1
"Unit";"Zergling";"Larva";156;1
"Unit";"Zergling";"Larva";156;1
"Unit";"Zergling";"Larva";156;1
"Unit";"Zergling";"Larva";156;1
"Unit";"Zergling";"Larva";156;1
"Unit";"Zergling";"Larva";156;1
"Unit";"Zergling";"Larva";156;1
"Unit";"Zergling";"Larva";156;1
"Unit";"Zergling";"Larva";156;1
"Unit";"Zergling";"Larva";162;1
"Unit";"Zergling";"Larva";162;1
"Unit";"Zergling";"Larva";162;1
"Unit";"Zergling";"Larva";162;1
"Unit";"Zergling";"Larva";162;1
"Unit";"Zergling";"Larva";162;1
"Building";"CreepTumor";NA;182;0
"Unit";"Zergling";"Larva";182;1
"Unit";"Zergling";"Larva";182;1
"Unit";"Zergling";"Larva";182;1
"Unit";"Zergling";"Larva";182;1
"Unit";"Zergling";"Larva";182;1
"Unit";"Zergling";"Larva";182;1
"Unit";"Zergling";"Larva";182;1
"Unit";"Zergling";"Larva";182;1
"Unit";"Zergling";"Larva";182;1
"Unit";"Zergling";"Larva";182;1
"Unit";"Zergling";"Larva";182;1
"Unit";"Zergling";"Larva";182;1
"Unit";"Queen";"Hatchery";162;2
"Unit";"Queen";"Hatchery";162;2
"Unit";"Queen";"Hatchery";162;2
"Unit";"Overlord";"Larva";182;0
"Unit";"Zergling";"Larva";214;1
"Unit";"Zergling";"Larva";214;1
"Unit";"Zergling";"Larva";214;1
"Unit";"Zergling";"Larva";214;1
"Unit";"Zergling";"Larva";214;1
"Unit";"Zergling";"Larva";214;1
"Building";"CreepTumor";NA;214;0
"Building";"Hatchery";NA;156;0
"Building";"CreepTumorQueen";NA;214;0
"Unit";"Zergling";"Larva";214;1
"Unit";"Zergling";"Larva";214;1
"Unit";"Zergling";"Larva";214;1
"Unit";"Zergling";"Larva";214;1
"Unit";"Zergling";"Larva";214;1
"Unit";"Zergling";"Larva";214;1
"Building";"Extractor";NA;214;0
"Unit";"Overlord";"Larva";214;0
"Building";"CreepTumor";NA;220;0
"Building";"CreepTumorQueen";NA;220;0
"Unit";"Overlord";"Larva";220;0
"Unit";"Overlord";"Larva";220;0
"Unit";"Overlord";"Larva";220;0
"Unit";"Overlord";"Larva";220;0
"Building";"CreepTumorQueen";NA;220;0
"Building";"CreepTumorQueen";NA;226;0
"Building";"CreepTumorQueen";NA;226;0
"Unit";"Zergling";"Larva";220;1
"Unit";"Zergling";"Larva";220;1
"Unit";"Baneling";"Zergling";226;0
"Building";"CreepTumorQueen";NA;226;0
"Unit";"Baneling";"Zergling";226;0
"Unit";"Baneling";"Zergling";226;0
"Unit";"Baneling";"Zergling";226;0
"Unit";"Baneling";"Zergling";226;0
"Unit";"Baneling";"Zergling";226;0
"Unit";"Baneling";"Zergling";226;0
"Unit";"Baneling";"Zergling";226;0
"Unit";"Baneling";"Zergling";226;0
"Unit";"Baneling";"Zergling";226;0
"Unit";"Baneling";"Zergling";226;0
"Unit";"Baneling";"Zergling";226;0
"Unit";"Baneling";"Zergling";226;0
"Upgrade";"ZergGroundArmorsLevel1";"EvolutionChamber";162;0
"Unit";"Zergling";"Larva";226;1
"Unit";"Zergling";"Larva";226;1
"Unit";"Zergling";"Larva";228;1
"Unit";"Zergling";"Larva";228;1
"Unit";"Baneling";"Zergling";230;0
"Unit";"Baneling";"Zergling";230;0
"Unit";"Baneling";"Zergling";230;0
"Unit";"Baneling";"Zergling";230;0
"Unit";"Baneling";"Zergling";230;0
"Unit";"Baneling";"Zergling";230;0
"Unit";"Zergling";"Larva";230;1
"Unit";"Zergling";"Larva";230;1
"Upgrade";"NeuralParasite";"InfestationPit";226;0
"Unit";"Zergling";"Larva";232;1
"Unit";"Zergling";"Larva";232;1
"Unit";"Zergling";"Larva";232;1
"Unit";"Zergling";"Larva";232;1
"Unit";"Zergling";"Larva";232;1
"Unit";"Zergling";"Larva";232;1
"Unit";"Zergling";"Larva";232;1
"Unit";"Zergling";"Larva";232;1
"Unit";"Zergling";"Larva";232;1
"Unit";"Zergling";"Larva";232;1
"Unit";"Zergling";"Larva";232;1
"Unit";"Zergling";"Larva";232;1
"Unit";"Zergling";"Larva";232;1
"Unit";"Zergling";"Larva";232;1
"Unit";"Zergling";"Larva";232;1
"Unit";"Zergling";"Larva";232;1
"Unit";"Zergling";"Larva";232;1
"Unit";"Zergling";"Larva";232;1
"Unit";"Zergling";"Larva";232;1
"Unit";"Zergling";"Larva";232;1
"Unit";"Zergling";"Larva";232;1
"Unit";"Zergling";"Larva";232;1
"Unit";"Zergling";"Larva";232;1
"Unit";"Zergling";"Larva";232;1
"Unit";"Zergling";"Larva";232;1
"Unit";"Zergling";"Larva";232;1
"Unit";"Zergling";"Larva";232;1
"Unit";"Zergling";"Larva";232;1
"Unit";"Zergling";"Larva";232;1
"Unit";"Zergling";"Larva";232;1
"Unit";"Zergling";"Larva";232;1
"Unit";"Zergling";"Larva";232;1
"Unit";"Zergling";"Larva";234;1
"Unit";"Zergling";"Larva";234;1
"Unit";"Infestor";"Larva";232;2
"Unit";"Infestor";"Larva";232;2
"Unit";"Zergling";"Larva";258;1
"Unit";"Zergling";"Larva";258;1
"Unit";"Baneling";"Zergling";266;0
"Unit";"Baneling";"Zergling";266;0
"Unit";"Baneling";"Zergling";266;0
"Unit";"Baneling";"Zergling";266;0
"Unit";"Baneling";"Zergling";266;0
"Unit";"Baneling";"Zergling";266;0
"Unit";"Baneling";"Zergling";266;0
"Unit";"Baneling";"Zergling";266;0
"Unit";"Baneling";"Zergling";268;0
"Unit";"Zergling";"Larva";266;1
"Unit";"Zergling";"Larva";266;1
"Unit";"Zergling";"Larva";266;1
"Unit";"Zergling";"Larva";266;1
"Unit";"Zergling";"Larva";266;1
"Unit";"Zergling";"Larva";266;1
"Unit";"Zergling";"Larva";266;1
"Unit";"Zergling";"Larva";266;1
"Unit";"Zergling";"Larva";266;1
"Unit";"Zergling";"Larva";266;1
"Unit";"Zergling";"Larva";266;1
"Unit";"Zergling";"Larva";266;1
"Unit";"Infestor";"Larva";234;2
"Unit";"Infestor";"Larva";234;2
"Unit";"Zergling";"Larva";274;1
"Unit";"Zergling";"Larva";274;1
"Unit";"Zergling";"Larva";274;1
"Unit";"Zergling";"Larva";274;1
"Unit";"Zergling";"Larva";274;1
"Unit";"Zergling";"Larva";274;1
"Upgrade";"ZergMeleeWeaponsLevel2";"EvolutionChamber";228;0
"Unit";"Zergling";"Larva";296;1
"Unit";"Zergling";"Larva";296;1
"Unit";"Zergling";"Larva";296;1
"Unit";"Zergling";"Larva";296;1
"Unit";"Zergling";"Larva";296;1
"Unit";"Zergling";"Larva";296;1
"Unit";"Zergling";"Larva";296;1
"Unit";"Zergling";"Larva";296;1
"Unit";"Zergling";"Larva";296;1
"Unit";"Zergling";"Larva";296;1
"Unit";"Zergling";"Larva";317;1
"Unit";"Zergling";"Larva";317;1
"Unit";"Zergling";"Larva";317;1
"Unit";"Zergling";"Larva";317;1
"Unit";"Zergling";"Larva";317;1
"Unit";"Zergling";"Larva";317;1
"Unit";"Zergling";"Larva";317;1
"Unit";"Zergling";"Larva";317;1
"Unit";"Zergling";"Larva";317;1
"Unit";"Zergling";"Larva";317;1
"Unit";"Zergling";"Larva";317;1
"Unit";"Zergling";"Larva";317;1
"Unit";"Zergling";"Larva";317;1
"Unit";"Zergling";"Larva";317;1
"Unit";"Baneling";"Zergling";317;0
"Unit";"Baneling";"Zergling";317;0
"Unit";"Baneling";"Zergling";317;0
"Unit";"Baneling";"Zergling";317;0
"Unit";"Baneling";"Zergling";317;0
"Unit";"Baneling";"Zergling";317;0
"Unit";"Baneling";"Zergling";317;0
"Unit";"Baneling";"Zergling";317;0
"Unit";"Baneling";"Zergling";317;0
"Unit";"Baneling";"Zergling";317;0
"Unit";"Baneling";"Zergling";317;0
"Unit";"Baneling";"Zergling";317;0
"Building";"Hatchery";NA;268;0
"Building";"CreepTumor";NA;317;0
"Building";"CreepTumor";NA;317;0
"Building";"CreepTumor";NA;317;0
"Building";"CreepTumor";NA;317;0
"Building";"CreepTumor";NA;317;0
"Building";"Extractor";NA;317;0
"Building";"Extractor";NA;317;0
"Unit";"Zergling";"Larva";323;1
"Unit";"Zergling";"Larva";323;1
"Unit";"Zergling";"Larva";325;1
"Unit";"Zergling";"Larva";325;1
"Unit";"Zergling";"Larva";329;1
"Unit";"Zergling";"Larva";329;1
"Unit";"Zergling";"Larva";329;1
"Unit";"Zergling";"Larva";329;1
"Unit";"Zergling";"Larva";331;1
"Unit";"Zergling";"Larva";331;1
"Unit";"Zergling";"Larva";331;1
"Unit";"Zergling";"Larva";331;1
"Unit";"Overlord";"Larva";331;0
"Unit";"Zergling";"Larva";332;1
"Unit";"Zergling";"Larva";332;1
"Unit";"Zergling";"Larva";332;1
"Unit";"Zergling";"Larva";332;1
"Unit";"Zergling";"Larva";332;1
"Unit";"Zergling";"Larva";332;1
"Unit";"Zergling";"Larva";332;1
"Unit";"Zergling";"Larva";332;1
"Unit";"Zergling";"Larva";332;1
"Unit";"Zergling";"Larva";332;1
"Unit";"Zergling";"Larva";332;1
"Unit";"Zergling";"Larva";332;1
"Unit";"Zergling";"Larva";344;1
"Unit";"Zergling";"Larva";344;1
"Unit";"Zergling";"Larva";344;1
"Unit";"Zergling";"Larva";344;1
"Unit";"Queen";"Hatchery";331;2
"Unit";"Baneling";"Zergling";356;0
"Unit";"Baneling";"Zergling";356;0
"Unit";"Baneling";"Zergling";356;0
"Unit";"Baneling";"Zergling";356;0
"Unit";"Baneling";"Zergling";356;0
"Unit";"Baneling";"Zergling";356;0
"Unit";"Baneling";"Zergling";356;0
"Unit";"Baneling";"Zergling";356;0
"Unit";"Baneling";"Zergling";356;0
"Unit";"Baneling";"Zergling";356;0
"Unit";"Baneling";"Zergling";356;0
"Unit";"Baneling";"Zergling";356;0
"Unit";"Baneling";"Zergling";356;0
"Unit";"Baneling";"Zergling";356;0
"Unit";"Baneling";"Zergling";356;0
"Unit";"Baneling";"Zergling";356;0
"Unit";"Baneling";"Zergling";356;0
"Unit";"Baneling";"Zergling";356;0
"Unit";"Baneling";"Zergling";356;0
"Unit";"Baneling";"Zergling";356;0
"Unit";"Baneling";"Zergling";356;0
"Building";"CreepTumor";NA;360;0
"Unit";"Overlord";"Larva";356;0
"Unit";"Overlord";"Larva";356;0
"Unit";"Overlord";"Larva";356;0
"Unit";"Overlord";"Larva";356;0
"Unit";"Overlord";"Larva";356;0
"Unit";"Overlord";"Larva";356;0
"Unit";"Zergling";"Larva";362;1
"Unit";"Zergling";"Larva";362;1
"Unit";"Zergling";"Larva";362;1
"Unit";"Zergling";"Larva";362;1
"Unit";"Zergling";"Larva";362;1
"Unit";"Zergling";"Larva";362;1
"Unit";"Zergling";"Larva";362;1
"Unit";"Zergling";"Larva";362;1
"Unit";"Zergling";"Larva";362;1
"Unit";"Zergling";"Larva";362;1
"Unit";"Infestor";"Larva";356;2
"Building";"Extractor";NA;362;0
"Building";"Extractor";NA;362;0
"Unit";"Baneling";"Zergling";362;0
"Unit";"Baneling";"Zergling";362;0
"Unit";"Baneling";"Zergling";362;0
"Unit";"Baneling";"Zergling";362;0
"Unit";"Baneling";"Zergling";362;0
"Unit";"Baneling";"Zergling";362;0
"Unit";"Baneling";"Zergling";362;0
"Unit";"Baneling";"Zergling";362;0
"Unit";"Baneling";"Zergling";362;0
"Unit";"Baneling";"Zergling";362;0
"Unit";"Baneling";"Zergling";362;0
"Unit";"Baneling";"Zergling";362;0
"Unit";"Baneling";"Zergling";362;0
"Unit";"Baneling";"Zergling";362;0
"Unit";"Baneling";"Zergling";362;0
"Unit";"Baneling";"Zergling";362;0
"Unit";"Baneling";"Zergling";362;0
"Unit";"Baneling";"Zergling";362;0
"Unit";"Baneling";"Zergling";362;0
"Building";"Hatchery";NA;332;0
"Unit";"Zergling";"Larva";372;1
"Unit";"Zergling";"Larva";372;1
"Unit";"Zergling";"Larva";372;1
"Unit";"Zergling";"Larva";372;1
"Unit";"Zergling";"Larva";372;1
"Unit";"Zergling";"Larva";372;1
"Unit";"Zergling";"Larva";372;1
"Unit";"Zergling";"Larva";372;1
"Building";"SporeCrawler";NA;374;0
"Unit";"Baneling";"Zergling";382;0
"Unit";"Baneling";"Zergling";382;0
"Unit";"Baneling";"Zergling";382;0
"Unit";"Baneling";"Zergling";382;0
"Unit";"Baneling";"Zergling";382;0
"Unit";"Baneling";"Zergling";382;0
"Unit";"Baneling";"Zergling";382;0
"Unit";"Baneling";"Zergling";382;0
"Unit";"Baneling";"Zergling";382;0
"Unit";"Baneling";"Zergling";382;0
"Unit";"Baneling";"Zergling";382;0
"Unit";"Baneling";"Zergling";382;0
"Unit";"Baneling";"Zergling";382;0
"Unit";"Baneling";"Zergling";382;0
"Upgrade";"ZergGroundArmorsLevel2";"EvolutionChamber";332;0
"Unit";"Infestor";"Larva";378;2
"Unit";"Infestor";"Larva";380;2
"Unit";"Zergling";"Larva";382;1
"Unit";"Zergling";"Larva";382;1
"Unit";"Zergling";"Larva";382;1
"Unit";"Zergling";"Larva";382;1
"Unit";"Zergling";"Larva";382;1
"Unit";"Zergling";"Larva";382;1
"Unit";"Zergling";"Larva";382;1
"Unit";"Zergling";"Larva";382;1
"Unit";"Zergling";"Larva";382;1
"Unit";"Zergling";"Larva";382;1
"Unit";"Zergling";"Larva";382;1
"Unit";"Zergling";"Larva";382;1
"Unit";"Zergling";"Larva";382;1
"Unit";"Zergling";"Larva";382;1
"Unit";"Zergling";"Larva";382;1
"Unit";"Zergling";"Larva";382;1
"Unit";"Zergling";"Larva";382;1
"Unit";"Zergling";"Larva";382;1
"Unit";"Zergling";"Larva";382;1
"Unit";"Zergling";"Larva";382;1
"Unit";"Zergling";"Larva";382;1
"Unit";"Zergling";"Larva";382;1
"Unit";"Zergling";"Larva";382;1
"Unit";"Zergling";"Larva";382;1
"Unit";"Zergling";"Larva";382;1
"Unit";"Zergling";"Larva";382;1
"Unit";"Zergling";"Larva";382;1
"Unit";"Zergling";"Larva";382;1
"Unit";"Zergling";"Larva";382;1
"Unit";"Zergling";"Larva";382;1
"Unit";"Zergling";"Larva";382;1
"Unit";"Zergling";"Larva";382;1
"Unit";"Zergling";"Larva";382;1
"Unit";"Zergling";"Larva";382;1
"Unit";"Zergling";"Larva";382;1
"Unit";"Zergling";"Larva";382;1
"Unit";"Zergling";"Larva";382;1
"Unit";"Zergling";"Larva";382;1
"Unit";"Zergling";"Larva";382;1
"Unit";"Zergling";"Larva";382;1
"Unit";"Zergling";"Larva";382;1
"Unit";"Zergling";"Larva";382;1
"Unit";"Zergling";"Larva";382;1
"Unit";"Zergling";"Larva";382;1
"Unit";"Zergling";"Larva";382;1
"Unit";"Zergling";"Larva";382;1
"Upgrade";"ZergMeleeWeaponsLevel3";"EvolutionChamber";344;0
"Unit";"Zergling";"Larva";396;1
"Unit";"Zergling";"Larva";396;1
"Unit";"Zergling";"Larva";408;1
"Unit";"Zergling";"Larva";408;1
"Unit";"Zergling";"Larva";432;1
"Unit";"Zergling";"Larva";432;1
"Unit";"Zergling";"Larva";432;1
"Unit";"Zergling";"Larva";432;1
"Unit";"Zergling";"Larva";432;1
"Unit";"Zergling";"Larva";432;1
"Unit";"Zergling";"Larva";432;1
"Unit";"Zergling";"Larva";432;1
"Unit";"Zergling";"Larva";432;1
"Unit";"Zergling";"Larva";432;1
"Unit";"Infestor";"Larva";382;2
"Unit";"Infestor";"Larva";382;2
"Unit";"Infestor";"Larva";382;2
"Unit";"Infestor";"Larva";432;2
"Unit";"Zergling";"Larva";436;1
"Unit";"Zergling";"Larva";436;1
"Unit";"Zergling";"Larva";436;1
"Unit";"Zergling";"Larva";436;1
"Unit";"Zergling";"Larva";444;1
"Unit";"Zergling";"Larva";444;1
"Unit";"Zergling";"Larva";444;1
"Unit";"Zergling";"Larva";444;1
"Unit";"Zergling";"Larva";452;1
"Unit";"Zergling";"Larva";452;1
"Unit";"Zergling";"Larva";452;1
"Unit";"Zergling";"Larva";452;1
"Unit";"Zergling";"Larva";452;1
"Unit";"Zergling";"Larva";452;1
"Unit";"Zergling";"Larva";452;1
"Unit";"Zergling";"Larva";452;1
"Unit";"Zergling";"Larva";452;1
"Unit";"Zergling";"Larva";452;1
"Unit";"Zergling";"Larva";452;1
"Unit";"Zergling";"Larva";452;1
"Unit";"Zergling";"Larva";452;1
"Unit";"Zergling";"Larva";452;1
"Unit";"Infestor";"Larva";462;2
"Unit";"Infestor";"Larva";462;2
"Unit";"Infestor";"Larva";462;2
"Unit";"Baneling";"Zergling";482;0
"Unit";"Baneling";"Zergling";486;0
"Unit";"Baneling";"Zergling";486;0
"Unit";"Baneling";"Zergling";486;0
"Unit";"Baneling";"Zergling";486;0
"Unit";"Baneling";"Zergling";486;0
"Unit";"Baneling";"Zergling";486;0
"Unit";"Baneling";"Zergling";486;0
"Unit";"Baneling";"Zergling";486;0
"Unit";"Baneling";"Zergling";486;0
"Unit";"Infestor";"Larva";470;2
"Unit";"Infestor";"Larva";472;2
"Unit";"Infestor";"Larva";472;2
"Unit";"Infestor";"Larva";480;2
"Unit";"Infestor";"Larva";480;2
"Unit";"Infestor";"Larva";480;2
"Unit";"Infestor";"Larva";480;2
"Unit";"Infestor";"Larva";480;2
"Unit";"Zergling";"Larva";500;1
"Unit";"Zergling";"Larva";500;1
"Unit";"Zergling";"Larva";500;1
"Unit";"Zergling";"Larva";500;1
"Unit";"Zergling";"Larva";500;1
"Unit";"Zergling";"Larva";500;1
"Unit";"Zergling";"Larva";500;1
"Unit";"Zergling";"Larva";500;1
"Unit";"Zergling";"Larva";500;1
"Unit";"Zergling";"Larva";500;1
"Unit";"Zergling";"Larva";500;1
"Unit";"Zergling";"Larva";500;1
"Unit";"Zergling";"Larva";500;1
"Unit";"Zergling";"Larva";500;1
"Unit";"Zergling";"Larva";500;1
"Unit";"Zergling";"Larva";500;1
"Unit";"Zergling";"Larva";500;1
"Unit";"Zergling";"Larva";500;1
"Unit";"Zergling";"Larva";500;1
"Unit";"Zergling";"Larva";500;1
"Unit";"Zergling";"Larva";500;1
"Unit";"Zergling";"Larva";500;1
"Unit";"Zergling";"Larva";500;1
"Unit";"Zergling";"Larva";500;1
"Unit";"Zergling";"Larva";500;1
"Unit";"Zergling";"Larva";500;1
"Unit";"Zergling";"Larva";500;1
"Unit";"Zergling";"Larva";500;1
"Unit";"Zergling";"Larva";500;1
"Unit";"Zergling";"Larva";500;1
"Unit";"Zergling";"Larva";500;1
"Unit";"Zergling";"Larva";500;1
"Unit";"Zergling";"Larva";510;1
"Unit";"Zergling";"Larva";510;1
"Unit";"Zergling";"Larva";510;1
"Unit";"Zergling";"Larva";510;1
"Unit";"Zergling";"Larva";510;1
"Unit";"Zergling";"Larva";510;1
"Unit";"Viper";"Larva";500;3
"Unit";"Zergling";"Larva";510;1
"Unit";"Zergling";"Larva";510;1
"Unit";"Infestor";"Larva";500;2
"Unit";"Infestor";"Larva";500;2
"Unit";"Infestor";"Larva";500;2
"Building";"CreepTumorQueen";NA;542;0
"Building";"CreepTumor";NA;542;0
"Unit";"Zergling";"Larva";510;1
"Unit";"Zergling";"Larva";510;1
"Unit";"Zergling";"Larva";510;1
"Unit";"Zergling";"Larva";510;1
"Unit";"Zergling";"Larva";510;1
"Unit";"Zergling";"Larva";510;1
"Building";"CreepTumorQueen";NA;542;0
"Unit";"Infestor";"Larva";510;2
"Unit";"Queen";"Hatchery";510;2
