"type";"unit_name";"on_building";"total_supply";"supply"
"Unit";"Overlord";"Larva";13;0
"Building";"Extractor";NA;17;0
"Building";"SpawningPool";NA;19;0
"Building";"Hatchery";NA;17;0
"Unit";"Zergling";"Larva";24;1
"Unit";"Zergling";"Larva";24;1
"Unit";"Queen";"Hatchery";23;2
"Unit";"Overlord";"Larva";28;0
"Unit";"Zergling";"Larva";33;1
"Unit";"Zergling";"Larva";33;1
"Unit";"Zergling";"Larva";33;1
"Unit";"Zergling";"Larva";33;1
"Unit";"Zergling";"Larva";33;1
"Unit";"Zergling";"Larva";33;1
"Building";"Hatchery";NA;23;0
"Unit";"Overlord";"Larva";33;0
"Unit";"Queen";"Hatchery";33;2
"Unit";"Queen";"Hatchery";40;2
"Unit";"Overlord";"Larva";45;0
"Unit";"Queen";"Hatchery";45;2
"Building";"CreepTumorQueen";NA;55;0
"Building";"Extractor";NA;53;0
"Building";"Extractor";NA;55;0
"Unit";"Overlord";"Larva";60;0
"Unit";"Overlord";"Larva";64;0
"Unit";"Zergling";"Larva";68;1
"Unit";"Zergling";"Larva";68;1
"Unit";"Zergling";"Larva";68;1
"Unit";"Zergling";"Larva";68;1
"Unit";"Zergling";"Larva";68;1
"Unit";"Zergling";"Larva";68;1
"Unit";"Overlord";"Larva";68;0
"Unit";"Zergling";"Larva";68;1
"Unit";"Zergling";"Larva";68;1
"Unit";"Zergling";"Larva";68;1
"Unit";"Zergling";"Larva";68;1
"Unit";"Zergling";"Larva";68;1
"Unit";"Zergling";"Larva";68;1
"Unit";"Zergling";"Larva";69;1
"Unit";"Zergling";"Larva";69;1
"Unit";"Zergling";"Larva";69;1
"Unit";"Zergling";"Larva";69;1
"Unit";"Zergling";"Larva";69;1
"Unit";"Zergling";"Larva";69;1
"Unit";"Zergling";"Larva";78;1
"Unit";"Zergling";"Larva";78;1
"Unit";"Zergling";"Larva";80;1
"Unit";"Zergling";"Larva";80;1
"Building";"SporeCrawler";NA;80;0
"Building";"SporeCrawler";NA;80;0
"Building";"SporeCrawler";NA;84;0
"Unit";"Zergling";"Larva";92;1
"Unit";"Zergling";"Larva";92;1
"Unit";"Zergling";"Larva";93;1
"Unit";"Zergling";"Larva";93;1
"Unit";"Overlord";"Larva";97;0
"Building";"BanelingNest";NA;73;0
"Building";"HydraliskDen";NA;97;0
"Unit";"Overlord";"Larva";105;0
"Unit";"Overlord";"Larva";105;0
"Building";"Extractor";NA;108;0
"Building";"Extractor";NA;108;0
"Building";"EvolutionChamber";NA;112;0
"Building";"EvolutionChamber";NA;112;0
"Unit";"Overlord";"Larva";118;0
"Unit";"Hydralisk";"Larva";118;2
"Unit";"Hydralisk";"Larva";118;2
"Unit";"Hydralisk";"Larva";118;2
"Unit";"Hydralisk";"Larva";118;2
"Unit";"Overlord";"Larva";126;0
"Unit";"Hydralisk";"Larva";124;2
"Unit";"Hydralisk";"Larva";124;2
"Unit";"Hydralisk";"Larva";126;2
"Unit";"Overlord";"Larva";126;0
"Building";"Extractor";NA;126;0
"Unit";"Overlord";"Larva";126;0
"Unit";"Overlord";"Larva";132;0
"Upgrade";"EvolveGroovedSpines";"HydraliskDen";118;0
"Unit";"Overlord";"Larva";140;0
"Unit";"Overlord";"Larva";140;0
"Unit";"Hydralisk";"Larva";140;2
"Unit";"Hydralisk";"Larva";140;2
"Unit";"Hydralisk";"Larva";140;2
"Unit";"Hydralisk";"Larva";140;2
"Unit";"Hydralisk";"Larva";140;2
"Unit";"Hydralisk";"Larva";140;2
"Unit";"Hydralisk";"Larva";140;2
"Building";"InfestationPit";NA;140;0
"Unit";"Hydralisk";"Larva";144;2
"Unit";"Hydralisk";"Larva";144;2
"Unit";"Hydralisk";"Larva";144;2
"Unit";"Zergling";"Larva";144;1
"Unit";"Zergling";"Larva";144;1
"Building";"SpineCrawler";NA;140;0
"Unit";"Hydralisk";"Larva";154;2
"Unit";"Hydralisk";"Larva";154;2
"Unit";"Hydralisk";"Larva";154;2
"Unit";"Hydralisk";"Larva";154;2
"Unit";"Zergling";"Larva";166;1
"Unit";"Zergling";"Larva";166;1
"Unit";"Zergling";"Larva";166;1
"Unit";"Zergling";"Larva";166;1
"Unit";"Zergling";"Larva";166;1
"Unit";"Zergling";"Larva";166;1
"Unit";"Zergling";"Larva";166;1
"Unit";"Zergling";"Larva";166;1
"Unit";"Hydralisk";"Larva";166;2
"Unit";"Hydralisk";"Larva";166;2
"Building";"CreepTumorQueen";NA;166;0
"Unit";"Zergling";"Larva";166;1
"Unit";"Zergling";"Larva";166;1
"Building";"CreepTumor";NA;166;0
"Building";"CreepTumorQueen";NA;174;0
"Unit";"Baneling";"Zergling";174;0
"Unit";"Baneling";"Zergling";174;0
"Unit";"Baneling";"Zergling";174;0
"Unit";"Baneling";"Zergling";174;0
"Unit";"Zergling";"Larva";174;1
"Unit";"Zergling";"Larva";174;1
"Unit";"Zergling";"Larva";174;1
"Unit";"Zergling";"Larva";174;1
"Unit";"Zergling";"Larva";174;1
"Unit";"Zergling";"Larva";174;1
"Unit";"Zergling";"Larva";174;1
"Unit";"Zergling";"Larva";174;1
"Unit";"Zergling";"Larva";174;1
"Unit";"Zergling";"Larva";174;1
"Unit";"Zergling";"Larva";174;1
"Unit";"Zergling";"Larva";174;1
"Unit";"Zergling";"Larva";174;1
"Unit";"Zergling";"Larva";174;1
"Unit";"Zergling";"Larva";176;1
"Unit";"Zergling";"Larva";176;1
"Unit";"Zergling";"Larva";176;1
"Unit";"Zergling";"Larva";176;1
"Upgrade";"ZergMissileWeaponsLevel1";"EvolutionChamber";140;0
"Upgrade";"ZergGroundArmorsLevel1";"EvolutionChamber";140;0
"Unit";"Baneling";"Zergling";188;0
"Unit";"Baneling";"Zergling";188;0
"Unit";"Zergling";"Larva";188;1
"Unit";"Zergling";"Larva";188;1
"Unit";"Baneling";"Zergling";206;0
"Unit";"Baneling";"Zergling";206;0
"Unit";"Baneling";"Zergling";206;0
"Unit";"Baneling";"Zergling";206;0
"Unit";"Baneling";"Zergling";206;0
"Unit";"Baneling";"Zergling";206;0
"Unit";"Baneling";"Zergling";206;0
"Unit";"Baneling";"Zergling";206;0
"Unit";"Baneling";"Zergling";206;0
"Unit";"Zergling";"Larva";202;1
"Unit";"Zergling";"Larva";202;1
"Unit";"Zergling";"Larva";204;1
"Unit";"Zergling";"Larva";204;1
"Upgrade";"EvolveMuscularAugments";"HydraliskDen";166;0
"Building";"Hatchery";NA;152;0
"Unit";"Zergling";"Larva";206;1
"Unit";"Zergling";"Larva";206;1
"Unit";"Hydralisk";"Larva";224;2
"Unit";"Hydralisk";"Larva";224;2
"Unit";"Hydralisk";"Larva";224;2
"Unit";"Hydralisk";"Larva";224;2
"Unit";"Hydralisk";"Larva";224;2
"Unit";"Hydralisk";"Larva";224;2
"Unit";"Zergling";"Larva";224;1
"Unit";"Zergling";"Larva";224;1
"Unit";"Zergling";"Larva";224;1
"Unit";"Zergling";"Larva";224;1
"Unit";"Zergling";"Larva";224;1
"Unit";"Zergling";"Larva";224;1
"Unit";"Zergling";"Larva";224;1
"Unit";"Zergling";"Larva";224;1
"Unit";"Zergling";"Larva";224;1
"Unit";"Zergling";"Larva";224;1
"Unit";"Zergling";"Larva";224;1
"Unit";"Zergling";"Larva";224;1
"Unit";"Zergling";"Larva";224;1
"Unit";"Zergling";"Larva";224;1
