"type";"unit_name";"on_building";"total_supply_lag";"supply"
"Unit";"Overlord";"Larva";13;0
"Building";"Hatchery";NA;18;0
"Building";"Extractor";NA;20;0
"Building";"SpawningPool";NA;21;0
"Unit";"Queen";"Hatchery";27;2
"Unit";"Queen";"Hatchery";29;2
"Unit";"Overlord";"Larva";31;0
"Unit";"Zergling";"Larva";31;1
"Unit";"Zergling";"Larva";32;1
"Unit";"Zergling";"Larva";33;1
"Unit";"Zergling";"Larva";34;1
"Unit";"Zergling";"Larva";35;1
"Unit";"Zergling";"Larva";36;1
"Unit";"Zergling";"Larva";37;1
"Unit";"Zergling";"Larva";38;1
"Unit";"Zergling";"Larva";40;1
"Unit";"Zergling";"Larva";41;1
"Unit";"Queen";"Hatchery";42;2
"Unit";"Overlord";"Larva";45;0
"Unit";"Queen";"Hatchery";45;2
"Building";"EvolutionChamber";NA;47;0
"Unit";"Zergling";"Larva";47;1
"Unit";"Zergling";"Larva";48;1
"Unit";"Zergling";"Larva";49;1
"Unit";"Zergling";"Larva";50;1
"Unit";"Zergling";"Larva";51;1
"Unit";"Zergling";"Larva";52;1
"Building";"CreepTumorQueen";NA;55;0
"Building";"CreepTumorQueen";NA;57;0
"Unit";"Overlord";"Larva";58;0
"Building";"CreepTumor";NA;59;0
"Building";"Hatchery";NA;59;0
"Unit";"Overlord";"Larva";59;0
"Unit";"Zergling";"Larva";60;1
"Unit";"Zergling";"Larva";61;1
"Unit";"Zergling";"Larva";66;1
"Unit";"Zergling";"Larva";67;1
"Building";"CreepTumor";NA;70;0
"Unit";"Overlord";"Larva";70;0
"Building";"SporeCrawler";NA;70;0
"Building";"SporeCrawler";NA;70;0
"Building";"CreepTumor";NA;70;0
"Building";"CreepTumorQueen";NA;75;0
"Unit";"Overlord";"Larva";80;0
"Building";"Extractor";NA;80;0
"Building";"Extractor";NA;80;0
"Building";"CreepTumor";NA;80;0
"Building";"CreepTumorQueen";NA;80;0
"Building";"CreepTumor";NA;80;0
"Unit";"Queen";"Hatchery";86;2
"Unit";"Zergling";"Larva";88;1
"Unit";"Zergling";"Larva";89;1
"Unit";"Zergling";"Larva";90;1
"Unit";"Zergling";"Larva";91;1
"Unit";"Zergling";"Larva";92;1
"Unit";"Zergling";"Larva";93;1
"Building";"CreepTumor";NA;94;0
"Building";"RoachWarren";NA;94;0
"Building";"CreepTumor";NA;94;0
"Unit";"Zergling";"Larva";97;1
"Unit";"Zergling";"Larva";98;1
"Unit";"Zergling";"Larva";99;1
"Unit";"Zergling";"Larva";100;1
"Building";"SporeCrawler";NA;101;0
"Unit";"Zergling";"Larva";101;1
"Unit";"Zergling";"Larva";102;1
"Unit";"Zergling";"Larva";103;1
"Unit";"Zergling";"Larva";104;1
"Unit";"Zergling";"Larva";105;1
"Unit";"Zergling";"Larva";106;1
"Unit";"Zergling";"Larva";107;1
"Unit";"Zergling";"Larva";108;1
"Unit";"Zergling";"Larva";109;1
"Unit";"Zergling";"Larva";110;1
"Unit";"Zergling";"Larva";111;1
"Unit";"Zergling";"Larva";112;1
"Unit";"Zergling";"Larva";113;1
"Unit";"Zergling";"Larva";114;1
"Unit";"Zergling";"Larva";115;1
"Unit";"Zergling";"Larva";116;1
"Unit";"Overlord";"Larva";117;0
"Unit";"Zergling";"Larva";117;1
"Unit";"Zergling";"Larva";118;1
"Unit";"Zergling";"Larva";119;1
"Unit";"Zergling";"Larva";120;1
"Unit";"Zergling";"Larva";121;1
"Unit";"Zergling";"Larva";122;1
"Unit";"Zergling";"Larva";123;1
"Unit";"Zergling";"Larva";124;1
"Unit";"Zergling";"Larva";125;1
"Unit";"Zergling";"Larva";126;1
"Unit";"Zergling";"Larva";127;1
"Unit";"Zergling";"Larva";128;1
"Unit";"Zergling";"Larva";129;1
"Unit";"Zergling";"Larva";130;1
"Unit";"Zergling";"Larva";131;1
"Unit";"Zergling";"Larva";132;1
"Building";"CreepTumor";NA;144;0
"Building";"CreepTumor";NA;144;0
"Unit";"Roach";"Larva";144;2
"Unit";"Roach";"Larva";146;2
"Unit";"Roach";"Larva";148;2
"Upgrade";"GlialReconstitution";"RoachWarren";150;0
"Unit";"Roach";"Larva";150;2
"Building";"CreepTumor";NA;152;0
"Unit";"Roach";"Larva";152;2
"Unit";"Roach";"Larva";154;2
"Unit";"Overlord";"Larva";156;0
"Unit";"Overlord";"Larva";156;0
"Unit";"Overlord";"Larva";156;0
"Unit";"Overlord";"Larva";156;0
"Unit";"Overlord";"Larva";156;0
"Unit";"Roach";"Larva";156;2
"Unit";"Roach";"Larva";158;2
"Unit";"Roach";"Larva";160;2
"Unit";"Roach";"Larva";162;2
"Unit";"Roach";"Larva";164;2
"Unit";"Roach";"Larva";166;2
"Unit";"Roach";"Larva";168;2
"Unit";"Roach";"Larva";170;2
"Unit";"Roach";"Larva";172;2
"Unit";"Roach";"Larva";174;2
"Unit";"Roach";"Larva";176;2
"Unit";"Roach";"Larva";178;2
"Unit";"Roach";"Larva";180;2
"Unit";"Roach";"Larva";182;2
"Building";"CreepTumor";NA;184;0
"Building";"CreepTumor";NA;184;0
"Building";"CreepTumorQueen";NA;184;0
"Unit";"Roach";"Larva";184;2
"Unit";"Roach";"Larva";186;2
"Unit";"Roach";"Larva";188;2
"Unit";"Roach";"Larva";190;2
"Unit";"Roach";"Larva";192;2
"Unit";"Overlord";"Larva";194;0
"Unit";"Roach";"Larva";194;2
"Unit";"Roach";"Larva";196;2
"Unit";"Overlord";"Larva";198;0
"Unit";"Overlord";"Larva";198;0
"Unit";"Overlord";"Larva";198;0
"Building";"CreepTumor";NA;198;0
"Unit";"Zergling";"Larva";198;1
"Unit";"Zergling";"Larva";199;1
"Unit";"Zergling";"Larva";200;1
"Unit";"Zergling";"Larva";201;1
"Building";"CreepTumor";NA;202;0
"Unit";"Overlord";"Larva";202;0
"Unit";"Zergling";"Larva";202;1
"Unit";"Zergling";"Larva";203;1
"Unit";"Zergling";"Larva";204;1
"Unit";"Zergling";"Larva";205;1
"Unit";"Zergling";"Larva";206;1
"Unit";"Zergling";"Larva";207;1
"Unit";"Zergling";"Larva";208;1
"Unit";"Zergling";"Larva";209;1
"Unit";"Zergling";"Larva";210;1
"Unit";"Zergling";"Larva";211;1
"Unit";"Zergling";"Larva";212;1
"Unit";"Zergling";"Larva";213;1
"Unit";"Zergling";"Larva";214;1
"Unit";"Zergling";"Larva";215;1
"Unit";"Zergling";"Larva";216;1
"Unit";"Zergling";"Larva";217;1
"Unit";"Zergling";"Larva";218;1
"Unit";"Zergling";"Larva";219;1
"Unit";"Zergling";"Larva";220;1
"Unit";"Zergling";"Larva";221;1
"Unit";"Zergling";"Larva";222;1
"Unit";"Zergling";"Larva";223;1
"Unit";"Zergling";"Larva";224;1
"Unit";"Zergling";"Larva";225;1
"Unit";"Zergling";"Larva";226;1
"Unit";"Zergling";"Larva";227;1
"Unit";"Zergling";"Larva";228;1
"Unit";"Zergling";"Larva";229;1
"Unit";"Zergling";"Larva";230;1
"Unit";"Zergling";"Larva";231;1
"Unit";"Zergling";"Larva";232;1
"Unit";"Zergling";"Larva";233;1
"Unit";"Zergling";"Larva";234;1
"Unit";"Zergling";"Larva";235;1
"Unit";"Zergling";"Larva";236;1
"Unit";"Zergling";"Larva";237;1
"Unit";"Zergling";"Larva";238;1
"Unit";"Zergling";"Larva";239;1
"Unit";"Zergling";"Larva";240;1
"Unit";"Zergling";"Larva";241;1
"Unit";"Zergling";"Larva";242;1
"Unit";"Zergling";"Larva";243;1
"Unit";"Zergling";"Larva";244;1
"Unit";"Zergling";"Larva";245;1
"Unit";"Zergling";"Larva";246;1
"Unit";"Zergling";"Larva";247;1
"Unit";"Zergling";"Larva";248;1
"Unit";"Zergling";"Larva";249;1
"Unit";"Zergling";"Larva";250;1
"Unit";"Zergling";"Larva";251;1
"Unit";"Queen";"Hatchery";252;2
"Unit";"Queen";"Hatchery";254;2
"Unit";"Zergling";"Larva";256;1
"Unit";"Zergling";"Larva";257;1
"Unit";"Zergling";"Larva";258;1
"Unit";"Zergling";"Larva";259;1
"Unit";"Zergling";"Larva";260;1
"Unit";"Zergling";"Larva";261;1
"Unit";"Zergling";"Larva";262;1
"Unit";"Zergling";"Larva";263;1
"Unit";"Zergling";"Larva";264;1
"Unit";"Zergling";"Larva";265;1
"Unit";"Zergling";"Larva";266;1
"Unit";"Zergling";"Larva";267;1
"Unit";"Zergling";"Larva";268;1
"Unit";"Zergling";"Larva";269;1
"Building";"HydraliskDen";NA;277;0
"Building";"Extractor";NA;279;0
"Building";"Hatchery";NA;282;0
"Building";"Extractor";NA;287;0
"Building";"Extractor";NA;287;0
"Building";"LurkerDenMP";NA;298;0
"Unit";"Roach";"Larva";298;2
"Unit";"Roach";"Larva";300;2
"Unit";"Hydralisk";"Larva";302;2
"Unit";"Hydralisk";"Larva";304;2
"Building";"CreepTumor";NA;306;0
"Building";"CreepTumor";NA;306;0
"Building";"CreepTumor";NA;306;0
"Unit";"Hydralisk";"Larva";306;2
"Unit";"Hydralisk";"Larva";308;2
"Unit";"Hydralisk";"Larva";310;2
"Unit";"Hydralisk";"Larva";312;2
"Unit";"Hydralisk";"Larva";314;2
"Unit";"Hydralisk";"Larva";316;2
"Building";"CreepTumor";NA;318;0
"Unit";"Hydralisk";"Larva";318;2
"Unit";"Hydralisk";"Larva";320;2
"Building";"Extractor";NA;322;0
"Building";"Extractor";NA;322;0
"Building";"CreepTumor";NA;322;0
"Unit";"Overlord";"Larva";322;0
"Unit";"Hydralisk";"Larva";322;2
"Unit";"Hydralisk";"Larva";324;2
"Unit";"Hydralisk";"Larva";326;2
"Building";"CreepTumorQueen";NA;328;0
"Unit";"Hydralisk";"Larva";328;2
"Unit";"Hydralisk";"Larva";330;2
"Unit";"Zergling";"Larva";332;1
"Unit";"Zergling";"Larva";333;1
"Unit";"Hydralisk";"Larva";341;2
"Unit";"Hydralisk";"Larva";343;2
"Unit";"Hydralisk";"Larva";345;2
"Building";"CreepTumorQueen";NA;347;0
"Building";"CreepTumorQueen";NA;347;0
"Building";"CreepTumor";NA;352;0
"Building";"CreepTumor";NA;352;0
"Building";"Hatchery";NA;352;0
"Unit";"Hydralisk";"Larva";352;2
"Unit";"Hydralisk";"Larva";354;2
"Unit";"Hydralisk";"Larva";356;2
"Building";"CreepTumor";NA;358;0
"Building";"CreepTumor";NA;358;0
"Unit";"Hydralisk";"Larva";358;2
"Unit";"Hydralisk";"Larva";360;2
"Unit";"Hydralisk";"Larva";362;2
"Unit";"Hydralisk";"Larva";364;2
"Unit";"Roach";"Larva";366;2
"Unit";"Zergling";"Larva";368;1
"Unit";"Zergling";"Larva";369;1
"Unit";"Zergling";"Larva";370;1
"Unit";"Zergling";"Larva";371;1
"Building";"CreepTumorQueen";NA;372;0
"Building";"CreepTumor";NA;372;0
"Unit";"Zergling";"Larva";372;1
"Unit";"Zergling";"Larva";373;1
"Unit";"Zergling";"Larva";374;1
"Unit";"Zergling";"Larva";375;1
"Unit";"Zergling";"Larva";376;1
"Unit";"Zergling";"Larva";377;1
"Building";"CreepTumor";NA;378;0
"Unit";"Zergling";"Larva";378;1
"Unit";"Zergling";"Larva";379;1
"Unit";"Zergling";"Larva";380;1
"Unit";"Zergling";"Larva";381;1
"Unit";"Zergling";"Larva";382;1
"Unit";"Zergling";"Larva";383;1
"Unit";"Zergling";"Larva";384;1
"Unit";"Zergling";"Larva";385;1
"Unit";"Zergling";"Larva";386;1
"Unit";"Zergling";"Larva";387;1
"Unit";"Zergling";"Larva";388;1
"Unit";"Zergling";"Larva";389;1
"Unit";"Zergling";"Larva";390;1
"Unit";"Zergling";"Larva";391;1
"Unit";"Zergling";"Larva";392;1
"Unit";"Zergling";"Larva";393;1
"Unit";"Zergling";"Larva";394;1
"Unit";"Zergling";"Larva";395;1
"Unit";"Hydralisk";"Larva";396;2
"Unit";"Hydralisk";"Larva";398;2
"Unit";"Hydralisk";"Larva";400;2
"Unit";"Zergling";"Larva";402;1
"Unit";"Zergling";"Larva";403;1
"Unit";"Zergling";"Larva";404;1
"Unit";"Zergling";"Larva";405;1
"Unit";"Zergling";"Larva";406;1
"Unit";"Zergling";"Larva";407;1
"Unit";"Overlord";"Larva";408;0
"Unit";"Overlord";"Larva";408;0
"Unit";"Overlord";"Larva";408;0
"Building";"CreepTumor";NA;408;0
"Building";"InfestationPit";NA;408;0
"Building";"CreepTumor";NA;408;0
"Building";"CreepTumor";NA;408;0
"Building";"CreepTumor";NA;408;0
"Building";"CreepTumor";NA;408;0
"Building";"CreepTumor";NA;408;0
"Building";"CreepTumor";NA;408;0
"Unit";"Zergling";"Larva";408;1
"Unit";"Zergling";"Larva";409;1
"Unit";"Zergling";"Larva";410;1
"Unit";"Zergling";"Larva";411;1
"Unit";"Zergling";"Larva";412;1
"Unit";"Zergling";"Larva";413;1
"Unit";"Zergling";"Larva";414;1
"Unit";"Zergling";"Larva";415;1
"Unit";"Zergling";"Larva";416;1
"Unit";"Zergling";"Larva";417;1
"Unit";"Zergling";"Larva";418;1
"Unit";"Zergling";"Larva";419;1
"Unit";"Zergling";"Larva";420;1
"Unit";"Zergling";"Larva";421;1
"Unit";"Zergling";"Larva";422;1
"Unit";"Zergling";"Larva";423;1
"Unit";"Zergling";"Larva";424;1
"Unit";"Zergling";"Larva";425;1
"Unit";"Zergling";"Larva";426;1
"Unit";"Zergling";"Larva";427;1
"Unit";"Zergling";"Larva";428;1
"Unit";"Zergling";"Larva";429;1
"Unit";"Zergling";"Larva";430;1
"Unit";"Zergling";"Larva";431;1
"Unit";"Zergling";"Larva";432;1
"Unit";"Zergling";"Larva";433;1
"Unit";"Zergling";"Larva";434;1
"Unit";"Zergling";"Larva";435;1
"Unit";"Zergling";"Larva";436;1
"Unit";"Zergling";"Larva";437;1
"Unit";"Zergling";"Larva";438;1
"Unit";"Zergling";"Larva";439;1
"Unit";"Zergling";"Larva";440;1
"Unit";"Zergling";"Larva";441;1
"Unit";"Zergling";"Larva";442;1
"Unit";"Zergling";"Larva";443;1
"Unit";"Zergling";"Larva";444;1
"Unit";"Zergling";"Larva";445;1
"Unit";"Zergling";"Larva";446;1
"Unit";"Zergling";"Larva";447;1
"Building";"CreepTumorQueen";NA;448;0
"Unit";"Zergling";"Larva";448;1
"Unit";"Zergling";"Larva";449;1
"Unit";"Zergling";"Larva";450;1
"Unit";"Zergling";"Larva";451;1
"Unit";"Zergling";"Larva";452;1
"Unit";"Zergling";"Larva";453;1
"Unit";"Zergling";"Larva";454;1
"Unit";"Zergling";"Larva";455;1
"Unit";"Zergling";"Larva";456;1
"Unit";"Zergling";"Larva";457;1
"Unit";"Zergling";"Larva";458;1
"Unit";"Zergling";"Larva";459;1
"Unit";"Zergling";"Larva";460;1
"Unit";"Zergling";"Larva";461;1
"Unit";"Zergling";"Larva";462;1
"Unit";"Zergling";"Larva";463;1
"Upgrade";"SprayZerg";NA;464;0
"Upgrade";"SprayZerg";NA;464;0
"Upgrade";"SprayZerg";NA;464;0
"Upgrade";"zerglingmovementspeed";NA;464;0
"Upgrade";"SprayZerg";NA;464;0
"Upgrade";"SprayZerg";NA;464;0
"Upgrade";"ZergMeleeWeaponsLevel1";NA;464;0
"Upgrade";"ZergMissileWeaponsLevel1";NA;464;0
"Upgrade";"SprayZerg";NA;464;0
"Upgrade";"SprayZerg";NA;464;0
"Upgrade";"ZergMissileWeaponsLevel2";NA;464;0
"Upgrade";"SprayZerg";NA;464;0
"Upgrade";"EvolveGroovedSpines";NA;464;0
"Upgrade";"SprayZerg";NA;464;0
"Upgrade";"EvolveMuscularAugments";NA;464;0
"Upgrade";"ZergMeleeWeaponsLevel2";NA;464;0
