"type";"unit_name";"on_building";"total_supply_lag";"supply"
"Unit";"Overlord";"Larva";13;0
"Building";"Hatchery";NA;17;0
"Building";"Extractor";NA;19;0
"Building";"SpawningPool";NA;19;0
"Unit";"Overlord";"Larva";22;0
"Unit";"Queen";"Hatchery";23;2
"Unit";"Queen";"Hatchery";26;2
"Unit";"Zergling";"Larva";28;1
"Unit";"Zergling";"Larva";29;1
"Building";"Hatchery";NA;35;0
"Building";"CreepTumorQueen";NA;36;0
"Unit";"Queen";"Hatchery";36;2
"Unit";"Zergling";"Larva";38;1
"Unit";"Zergling";"Larva";39;1
"Unit";"Overlord";"Larva";40;0
"Unit";"Zergling";"Larva";40;1
"Unit";"Zergling";"Larva";41;1
"Unit";"Zergling";"Larva";42;1
"Unit";"Zergling";"Larva";43;1
"Unit";"Zergling";"Larva";46;1
"Unit";"Zergling";"Larva";47;1
"Building";"CreepTumor";NA;50;0
"Building";"SporeCrawler";NA;53;0
"Unit";"Queen";"Hatchery";53;2
"Building";"SporeCrawler";NA;56;0
"Building";"CreepTumorQueen";NA;58;0
"Building";"CreepTumor";NA;58;0
"Unit";"Overlord";"Larva";58;0
"Unit";"Overlord";"Larva";64;0
"Building";"CreepTumor";NA;64;0
"Building";"CreepTumor";NA;64;0
"Unit";"Overlord";"Larva";64;0
"Unit";"Overlord";"Larva";68;0
"Building";"SporeCrawler";NA;69;0
"Building";"CreepTumorQueen";NA;71;0
"Building";"RoachWarren";NA;73;0
"Unit";"Zergling";"Larva";74;1
"Unit";"Zergling";"Larva";75;1
"Unit";"Zergling";"Larva";76;1
"Unit";"Zergling";"Larva";77;1
"Unit";"Zergling";"Larva";78;1
"Unit";"Zergling";"Larva";79;1
"Building";"Extractor";NA;81;0
"Building";"Extractor";NA;81;0
"Building";"CreepTumor";NA;81;0
"Unit";"Queen";"Hatchery";81;2
"Building";"CreepTumor";NA;84;0
"Unit";"Overlord";"Larva";90;0
"Unit";"Roach";"Larva";97;2
"Unit";"Roach";"Larva";99;2
"Unit";"Roach";"Larva";101;2
"Unit";"Roach";"Larva";103;2
"Unit";"Roach";"Larva";105;2
"Unit";"Roach";"Larva";107;2
"Unit";"Overlord";"Larva";109;0
"Unit";"Overlord";"Larva";109;0
"Unit";"Zergling";"Larva";109;1
"Unit";"Zergling";"Larva";110;1
"Building";"EvolutionChamber";NA;111;0
"Unit";"Overlord";"Larva";111;0
"Building";"CreepTumor";NA;111;0
"Building";"CreepTumor";NA;111;0
"Unit";"Overlord";"Larva";112;0
"Unit";"Overlord";"Larva";112;0
"Unit";"Zergling";"Larva";112;1
"Unit";"Zergling";"Larva";113;1
"Unit";"Zergling";"Larva";114;1
"Unit";"Zergling";"Larva";115;1
"Unit";"Zergling";"Larva";116;1
"Unit";"Zergling";"Larva";117;1
"Unit";"Zergling";"Larva";118;1
"Unit";"Zergling";"Larva";119;1
"Upgrade";"GlialReconstitution";"RoachWarren";126;0
"Unit";"Overlord";"Larva";128;0
"Unit";"Overlord";"Larva";129;0
"Building";"CreepTumorQueen";NA;130;0
"Unit";"Overlord";"Larva";130;0
"Building";"CreepTumorQueen";NA;130;0
"Building";"CreepTumorQueen";NA;130;0
"Building";"Extractor";NA;130;0
"Building";"Extractor";NA;130;0
"Building";"HydraliskDen";NA;130;0
"Unit";"Roach";"Larva";130;2
"Unit";"Roach";"Larva";132;2
"Building";"Extractor";NA;134;0
"Unit";"Roach";"Larva";134;2
"Unit";"Roach";"Larva";136;2
"Building";"CreepTumorQueen";NA;138;0
"Building";"CreepTumorQueen";NA;138;0
"Building";"Hatchery";NA;150;0
"Unit";"Overlord";"Larva";150;0
"Building";"CreepTumor";NA;150;0
"Building";"CreepTumor";NA;150;0
"Building";"CreepTumor";NA;150;0
"Building";"CreepTumor";NA;150;0
"Building";"CreepTumor";NA;150;0
"Building";"CreepTumorQueen";NA;150;0
"Building";"CreepTumorQueen";NA;150;0
"Unit";"Hydralisk";"Larva";150;2
"Unit";"Hydralisk";"Larva";152;2
"Unit";"Hydralisk";"Larva";154;2
"Unit";"Hydralisk";"Larva";156;2
"Unit";"Hydralisk";"Larva";158;2
"Unit";"Hydralisk";"Larva";160;2
"Building";"CreepTumor";NA;162;0
"Building";"LurkerDenMP";NA;162;0
"Unit";"Hydralisk";"Larva";164;2
"Unit";"Hydralisk";"Larva";166;2
"Unit";"Hydralisk";"Larva";168;2
"Building";"CreepTumor";NA;172;0
"Building";"CreepTumor";NA;172;0
"Building";"CreepTumor";NA;172;0
"Building";"CreepTumor";NA;172;0
"Building";"CreepTumor";NA;172;0
"Building";"CreepTumor";NA;172;0
"Building";"CreepTumor";NA;172;0
"Unit";"Overlord";"Larva";172;0
"Building";"CreepTumorQueen";NA;172;0
"Building";"CreepTumorQueen";NA;172;0
"Building";"CreepTumorQueen";NA;172;0
"Building";"CreepTumorQueen";NA;175;0
"Building";"CreepTumor";NA;175;0
"Building";"CreepTumor";NA;175;0
"Building";"Extractor";NA;182;0
"Unit";"Overlord";"Larva";183;0
"Unit";"Hydralisk";"Larva";183;2
"Unit";"Hydralisk";"Larva";185;2
"Building";"CreepTumor";NA;187;0
"Building";"CreepTumor";NA;187;0
"Building";"CreepTumor";NA;187;0
"Building";"CreepTumor";NA;187;0
"Unit";"Hydralisk";"Larva";187;2
"Unit";"Hydralisk";"Larva";189;2
"Unit";"Hydralisk";"Larva";191;2
"Building";"CreepTumor";NA;193;0
"Building";"CreepTumor";NA;193;0
"Building";"CreepTumor";NA;193;0
"Unit";"Overlord";"Larva";193;0
"Unit";"Hydralisk";"Larva";193;2
"Unit";"Hydralisk";"Larva";195;2
"Unit";"Hydralisk";"Larva";197;2
"Unit";"Roach";"Larva";199;2
"Unit";"Roach";"Larva";201;2
"Unit";"Roach";"Larva";203;2
"Unit";"Roach";"Larva";205;2
"Unit";"Hydralisk";"Larva";207;2
"Unit";"Roach";"Larva";209;2
"Unit";"Roach";"Larva";211;2
"Unit";"Roach";"Larva";213;2
"Unit";"Overlord";"Larva";215;0
"Unit";"Overlord";"Larva";215;0
"Unit";"Overlord";"Larva";215;0
"Building";"CreepTumor";NA;215;0
"Building";"CreepTumor";NA;215;0
"Unit";"Hydralisk";"Larva";215;2
"Unit";"Hydralisk";"Larva";217;2
"Unit";"Hydralisk";"Larva";219;2
"Unit";"Roach";"Larva";221;2
"Unit";"Overlord";"Larva";223;0
"Unit";"Overlord";"Larva";223;0
"Unit";"Hydralisk";"Larva";223;2
"Unit";"Hydralisk";"Larva";225;2
"Unit";"Hydralisk";"Larva";227;2
"Unit";"Hydralisk";"Larva";229;2
"Unit";"Roach";"Larva";231;2
"Unit";"Roach";"Larva";233;2
"Unit";"Roach";"Larva";235;2
"Unit";"Roach";"Larva";237;2
"Unit";"Roach";"Larva";239;2
"Unit";"Roach";"Larva";241;2
"Unit";"Roach";"Larva";243;2
"Unit";"Hydralisk";"Larva";245;2
"Unit";"Hydralisk";"Larva";247;2
"Unit";"Hydralisk";"Larva";249;2
"Unit";"Hydralisk";"Larva";251;2
"Building";"Hatchery";NA;253;0
"Unit";"Overlord";"Larva";253;0
"Unit";"Overlord";"Larva";253;0
"Unit";"Overlord";"Larva";253;0
"Unit";"Hydralisk";"Larva";253;2
"Unit";"Hydralisk";"Larva";255;2
"Unit";"Roach";"Larva";257;2
"Unit";"Roach";"Larva";259;2
"Unit";"Roach";"Larva";261;2
"Unit";"Roach";"Larva";263;2
"Unit";"Roach";"Larva";265;2
"Unit";"Roach";"Larva";267;2
"Unit";"Roach";"Larva";269;2
"Unit";"Roach";"Larva";271;2
"Unit";"Roach";"Larva";273;2
"Unit";"Hydralisk";"Larva";275;2
"Unit";"Hydralisk";"Larva";277;2
"Building";"CreepTumor";NA;279;0
"Building";"CreepTumor";NA;279;0
"Building";"CreepTumor";NA;279;0
"Building";"CreepTumor";NA;279;0
"Building";"CreepTumor";NA;279;0
"Building";"InfestationPit";NA;279;0
"Unit";"Hydralisk";"Larva";279;2
"Unit";"Hydralisk";"Larva";281;2
"Unit";"Hydralisk";"Larva";283;2
"Unit";"Hydralisk";"Larva";285;2
"Unit";"Hydralisk";"Larva";287;2
"Unit";"Hydralisk";"Larva";289;2
"Unit";"Hydralisk";"Larva";291;2
"Unit";"Roach";"Larva";293;2
"Unit";"Overlord";"Larva";295;0
"Unit";"Roach";"Larva";295;2
"Unit";"Overlord";"Larva";297;0
"Unit";"Hydralisk";"Larva";297;2
"Unit";"Hydralisk";"Larva";299;2
"Unit";"Hydralisk";"Larva";301;2
"Unit";"Roach";"Larva";303;2
"Unit";"Roach";"Larva";305;2
"Unit";"Roach";"Larva";307;2
"Unit";"Roach";"Larva";309;2
"Unit";"Roach";"Larva";311;2
"Unit";"Roach";"Larva";313;2
"Unit";"Roach";"Larva";315;2
"Unit";"Roach";"Larva";317;2
"Unit";"Roach";"Larva";319;2
"Unit";"Roach";"Larva";321;2
"Unit";"Roach";"Larva";323;2
"Unit";"Hydralisk";"Larva";325;2
"Unit";"Hydralisk";"Larva";327;2
"Unit";"Hydralisk";"Larva";329;2
"Unit";"Hydralisk";"Larva";331;2
"Unit";"Hydralisk";"Larva";333;2
"Unit";"Roach";"Larva";335;2
"Unit";"Roach";"Larva";337;2
"Unit";"Roach";"Larva";339;2
"Unit";"Roach";"Larva";341;2
"Unit";"Roach";"Larva";343;2
"Unit";"Roach";"Larva";345;2
"Unit";"Roach";"Larva";347;2
"Unit";"Roach";"Larva";349;2
"Unit";"Overlord";"Larva";351;0
"Building";"CreepTumor";NA;351;0
"Building";"CreepTumor";NA;351;0
"Building";"CreepTumor";NA;351;0
"Building";"CreepTumor";NA;351;0
"Building";"CreepTumor";NA;351;0
"Building";"CreepTumor";NA;351;0
"Unit";"Hydralisk";"Larva";351;2
"Unit";"Hydralisk";"Larva";353;2
"Unit";"Hydralisk";"Larva";355;2
"Unit";"Hydralisk";"Larva";357;2
"Unit";"Hydralisk";"Larva";359;2
"Unit";"Hydralisk";"Larva";361;2
"Unit";"Hydralisk";"Larva";363;2
"Unit";"Hydralisk";"Larva";365;2
"Unit";"Hydralisk";"Larva";367;2
"Unit";"Hydralisk";"Larva";369;2
"Unit";"Hydralisk";"Larva";371;2
"Unit";"Hydralisk";"Larva";373;2
"Unit";"Roach";"Larva";375;2
"Unit";"Roach";"Larva";377;2
"Unit";"Roach";"Larva";379;2
"Unit";"Roach";"Larva";381;2
"Unit";"Roach";"Larva";383;2
"Unit";"Roach";"Larva";385;2
"Building";"Extractor";NA;387;0
"Building";"Extractor";NA;390;0
"Unit";"Roach";"Larva";390;2
"Unit";"Roach";"Larva";392;2
"Unit";"Roach";"Larva";394;2
"Unit";"Roach";"Larva";396;2
"Unit";"Roach";"Larva";398;2
"Unit";"Roach";"Larva";400;2
"Unit";"Roach";"Larva";402;2
"Unit";"Roach";"Larva";404;2
"Unit";"Hydralisk";"Larva";406;2
"Unit";"Hydralisk";"Larva";408;2
"Unit";"Hydralisk";"Larva";410;2
"Unit";"Hydralisk";"Larva";412;2
"Unit";"Hydralisk";"Larva";414;2
"Building";"Hatchery";NA;416;0
"Unit";"Roach";"Larva";416;2
"Unit";"Roach";"Larva";418;2
"Unit";"Roach";"Larva";420;2
"Unit";"Roach";"Larva";422;2
"Unit";"Roach";"Larva";424;2
"Unit";"Roach";"Larva";426;2
"Unit";"Roach";"Larva";428;2
"Unit";"Roach";"Larva";430;2
"Unit";"Roach";"Larva";432;2
"Unit";"Roach";"Larva";434;2
"Unit";"Roach";"Larva";436;2
"Unit";"Roach";"Larva";438;2
"Unit";"Roach";"Larva";440;2
"Unit";"Roach";"Larva";442;2
"Unit";"Roach";"Larva";444;2
"Unit";"Roach";"Larva";446;2
"Unit";"Roach";"Larva";448;2
"Unit";"Roach";"Larva";450;2
"Unit";"Roach";"Larva";452;2
"Unit";"Roach";"Larva";454;2
"Unit";"Hydralisk";"Larva";456;2
"Unit";"Hydralisk";"Larva";458;2
"Unit";"Hydralisk";"Larva";460;2
"Unit";"Roach";"Larva";462;2
"Unit";"Roach";"Larva";464;2
"Unit";"Roach";"Larva";466;2
"Unit";"Roach";"Larva";468;2
"Unit";"Roach";"Larva";470;2
"Unit";"Roach";"Larva";472;2
"Unit";"Zergling";"Larva";474;1
"Unit";"Zergling";"Larva";475;1
"Unit";"Zergling";"Larva";476;1
"Unit";"Zergling";"Larva";477;1
"Unit";"Zergling";"Larva";478;1
"Unit";"Zergling";"Larva";479;1
"Unit";"Zergling";"Larva";480;1
"Unit";"Zergling";"Larva";481;1
"Unit";"Zergling";"Larva";482;1
"Unit";"Zergling";"Larva";483;1
"Unit";"Zergling";"Larva";484;1
"Unit";"Zergling";"Larva";485;1
"Unit";"Zergling";"Larva";486;1
"Unit";"Zergling";"Larva";487;1
"Unit";"Zergling";"Larva";488;1
"Unit";"Zergling";"Larva";489;1
"Building";"CreepTumor";NA;490;0
"Building";"CreepTumor";NA;490;0
"Building";"CreepTumor";NA;490;0
"Building";"CreepTumor";NA;490;0
"Unit";"Hydralisk";"Larva";490;2
"Unit";"Hydralisk";"Larva";492;2
"Unit";"Hydralisk";"Larva";494;2
"Unit";"Hydralisk";"Larva";496;2
"Unit";"Hydralisk";"Larva";498;2
"Unit";"Roach";"Larva";500;2
"Unit";"Roach";"Larva";502;2
"Unit";"Roach";"Larva";504;2
"Unit";"Roach";"Larva";506;2
"Building";"CreepTumor";NA;508;0
"Building";"CreepTumor";NA;508;0
"Unit";"Hydralisk";"Larva";508;2
"Unit";"Hydralisk";"Larva";510;2
"Unit";"Hydralisk";"Larva";512;2
"Unit";"Hydralisk";"Larva";514;2
"Unit";"Hydralisk";"Larva";516;2
"Unit";"Hydralisk";"Larva";518;2
"Unit";"Hydralisk";"Larva";520;2
"Unit";"Hydralisk";"Larva";522;2
"Unit";"Hydralisk";"Larva";524;2
"Unit";"Hydralisk";"Larva";526;2
"Unit";"Hydralisk";"Larva";528;2
"Unit";"Hydralisk";"Larva";530;2
"Unit";"Hydralisk";"Larva";532;2
"Unit";"Hydralisk";"Larva";534;2
"Unit";"Roach";"Larva";536;2
"Unit";"Roach";"Larva";538;2
"Unit";"Roach";"Larva";540;2
"Unit";"Roach";"Larva";542;2
"Unit";"Roach";"Larva";544;2
"Unit";"Roach";"Larva";546;2
"Unit";"Roach";"Larva";548;2
"Unit";"Roach";"Larva";550;2
"Unit";"Roach";"Larva";552;2
"Unit";"Roach";"Larva";554;2
"Unit";"Roach";"Larva";556;2
"Building";"CreepTumor";NA;558;0
"Building";"CreepTumor";NA;558;0
"Unit";"Hydralisk";"Larva";561;2
"Unit";"Hydralisk";"Larva";563;2
"Unit";"Hydralisk";"Larva";565;2
"Unit";"Hydralisk";"Larva";567;2
"Unit";"Hydralisk";"Larva";569;2
"Unit";"Roach";"Larva";571;2
"Unit";"Roach";"Larva";573;2
"Unit";"Roach";"Larva";575;2
"Unit";"Roach";"Larva";577;2
"Unit";"Roach";"Larva";579;2
"Unit";"Roach";"Larva";581;2
"Unit";"Roach";"Larva";583;2
"Unit";"Hydralisk";"Larva";585;2
"Unit";"Hydralisk";"Larva";587;2
"Unit";"Hydralisk";"Larva";589;2
"Unit";"Hydralisk";"Larva";591;2
"Unit";"Hydralisk";"Larva";593;2
"Unit";"Hydralisk";"Larva";595;2
"Unit";"Hydralisk";"Larva";597;2
"Unit";"Hydralisk";"Larva";599;2
"Unit";"Roach";"Larva";601;2
"Unit";"Roach";"Larva";603;2
"Unit";"Roach";"Larva";605;2
"Unit";"Hydralisk";"Larva";607;2
"Unit";"Roach";"Larva";609;2
"Unit";"Roach";"Larva";611;2
"Unit";"Roach";"Larva";613;2
"Unit";"Roach";"Larva";615;2
"Unit";"Roach";"Larva";617;2
"Unit";"Roach";"Larva";619;2
"Unit";"Roach";"Larva";621;2
"Unit";"Roach";"Larva";623;2
"Unit";"Roach";"Larva";625;2
"Building";"CreepTumor";NA;627;0
"Unit";"Hydralisk";"Larva";627;2
"Unit";"Hydralisk";"Larva";629;2
"Unit";"Roach";"Larva";631;2
"Unit";"Roach";"Larva";633;2
"Unit";"Roach";"Larva";635;2
"Unit";"Hydralisk";"Larva";639;2
"Unit";"Hydralisk";"Larva";641;2
"Unit";"Hydralisk";"Larva";643;2
"Unit";"Hydralisk";"Larva";645;2
"Unit";"Hydralisk";"Larva";647;2
"Unit";"Hydralisk";"Larva";649;2
"Unit";"Hydralisk";"Larva";651;2
"Unit";"Hydralisk";"Larva";653;2
"Unit";"Hydralisk";"Larva";655;2
"Unit";"Hydralisk";"Larva";657;2
"Unit";"Hydralisk";"Larva";659;2
"Unit";"Hydralisk";"Larva";661;2
"Unit";"Hydralisk";"Larva";663;2
"Unit";"Hydralisk";"Larva";665;2
"Unit";"Hydralisk";"Larva";667;2
"Unit";"Hydralisk";"Larva";669;2
"Unit";"Hydralisk";"Larva";671;2
"Unit";"Hydralisk";"Larva";673;2
"Unit";"Hydralisk";"Larva";675;2
"Unit";"Hydralisk";"Larva";677;2
"Unit";"Zergling";"Larva";679;1
"Unit";"Zergling";"Larva";680;1
"Unit";"Zergling";"Larva";681;1
"Unit";"Zergling";"Larva";682;1
"Unit";"Hydralisk";"Larva";683;2
"Unit";"Hydralisk";"Larva";685;2
"Unit";"Hydralisk";"Larva";687;2
"Unit";"Hydralisk";"Larva";689;2
"Unit";"Hydralisk";"Larva";691;2
"Unit";"Roach";"Larva";693;2
"Unit";"Roach";"Larva";695;2
"Unit";"Roach";"Larva";697;2
"Unit";"Roach";"Larva";699;2
"Unit";"Roach";"Larva";701;2
"Unit";"Roach";"Larva";703;2
"Unit";"Roach";"Larva";705;2
"Unit";"Roach";"Larva";707;2
"Building";"Hatchery";NA;709;0
"Unit";"Hydralisk";"Larva";709;2
"Unit";"Hydralisk";"Larva";711;2
"Unit";"Hydralisk";"Larva";713;2
"Unit";"Hydralisk";"Larva";715;2
"Unit";"Roach";"Larva";717;2
"Unit";"Roach";"Larva";719;2
"Unit";"Roach";"Larva";721;2
"Unit";"Roach";"Larva";723;2
"Unit";"Roach";"Larva";725;2
"Unit";"Hydralisk";"Larva";727;2
"Unit";"Hydralisk";"Larva";729;2
"Unit";"Hydralisk";"Larva";731;2
"Unit";"Roach";"Larva";733;2
"Unit";"Roach";"Larva";735;2
"Unit";"Hydralisk";"Larva";737;2
"Unit";"Roach";"Larva";739;2
"Unit";"Roach";"Larva";741;2
"Building";"Hatchery";NA;743;0
"Unit";"Roach";"Larva";743;2
"Unit";"Roach";"Larva";745;2
"Unit";"Roach";"Larva";747;2
"Unit";"Roach";"Larva";749;2
"Unit";"Roach";"Larva";751;2
"Unit";"Roach";"Larva";761;2
"Unit";"Roach";"Larva";763;2
"Unit";"Roach";"Larva";765;2
"Unit";"Roach";"Larva";767;2
"Unit";"Roach";"Larva";769;2
"Unit";"Roach";"Larva";771;2
"Unit";"Roach";"Larva";773;2
"Unit";"Roach";"Larva";775;2
"Unit";"Roach";"Larva";777;2
"Unit";"Roach";"Larva";779;2
"Unit";"Hydralisk";"Larva";787;2
"Unit";"Hydralisk";"Larva";789;2
"Unit";"Hydralisk";"Larva";791;2
"Building";"CreepTumorQueen";NA;793;0
"Building";"CreepTumorQueen";NA;793;0
"Building";"CreepTumorQueen";NA;793;0
"Unit";"Hydralisk";"Larva";793;2
"Unit";"Hydralisk";"Larva";795;2
"Unit";"Hydralisk";"Larva";797;2
"Unit";"Hydralisk";"Larva";799;2
"Unit";"Hydralisk";"Larva";801;2
"Unit";"Hydralisk";"Larva";803;2
"Unit";"Hydralisk";"Larva";805;2
"Building";"Hatchery";NA;807;0
"Unit";"Hydralisk";"Larva";807;2
"Unit";"Hydralisk";"Larva";809;2
"Unit";"Hydralisk";"Larva";811;2
"Unit";"Hydralisk";"Larva";813;2
"Unit";"Hydralisk";"Larva";815;2
"Unit";"Hydralisk";"Larva";817;2
"Unit";"Hydralisk";"Larva";819;2
"Unit";"Hydralisk";"Larva";821;2
"Unit";"Hydralisk";"Larva";823;2
"Unit";"Hydralisk";"Larva";825;2
"Unit";"Hydralisk";"Larva";827;2
"Unit";"Hydralisk";"Larva";829;2
"Unit";"Roach";"Larva";831;2
"Unit";"Roach";"Larva";833;2
"Unit";"Roach";"Larva";835;2
"Unit";"Hydralisk";"Larva";837;2
"Unit";"Hydralisk";"Larva";839;2
"Unit";"Hydralisk";"Larva";841;2
"Unit";"Hydralisk";"Larva";843;2
"Unit";"Roach";"Larva";845;2
"Unit";"Roach";"Larva";847;2
"Unit";"Roach";"Larva";849;2
"Unit";"Hydralisk";"Larva";851;2
"Unit";"Hydralisk";"Larva";853;2
"Unit";"Roach";"Larva";855;2
"Building";"Extractor";NA;857;0
"Unit";"Roach";"Larva";857;2
"Unit";"Roach";"Larva";859;2
"Unit";"Roach";"Larva";861;2
"Unit";"Roach";"Larva";863;2
"Unit";"Roach";"Larva";865;2
"Building";"CreepTumor";NA;867;0
"Building";"CreepTumor";NA;867;0
"Building";"CreepTumor";NA;867;0
"Unit";"Roach";"Larva";867;2
"Unit";"Roach";"Larva";869;2
"Unit";"Roach";"Larva";871;2
"Unit";"Roach";"Larva";873;2
"Unit";"Roach";"Larva";875;2
"Unit";"Roach";"Larva";877;2
"Unit";"Hydralisk";"Larva";879;2
"Unit";"Zergling";"Larva";881;1
"Unit";"Zergling";"Larva";882;1
"Unit";"Zergling";"Larva";883;1
"Unit";"Zergling";"Larva";884;1
"Unit";"Zergling";"Larva";885;1
"Unit";"Zergling";"Larva";886;1
"Unit";"Zergling";"Larva";887;1
"Unit";"Zergling";"Larva";888;1
"Unit";"Zergling";"Larva";889;1
"Unit";"Zergling";"Larva";890;1
"Unit";"Zergling";"Larva";891;1
"Unit";"Zergling";"Larva";892;1
"Unit";"Zergling";"Larva";893;1
"Unit";"Zergling";"Larva";894;1
"Unit";"Zergling";"Larva";895;1
"Unit";"Zergling";"Larva";896;1
"Unit";"Zergling";"Larva";897;1
"Unit";"Zergling";"Larva";898;1
"Unit";"Zergling";"Larva";899;1
"Unit";"Zergling";"Larva";900;1
"Unit";"Zergling";"Larva";901;1
"Unit";"Zergling";"Larva";902;1
"Unit";"Zergling";"Larva";903;1
"Unit";"Zergling";"Larva";904;1
"Unit";"Zergling";"Larva";905;1
"Unit";"Zergling";"Larva";906;1
"Unit";"Zergling";"Larva";907;1
"Unit";"Zergling";"Larva";908;1
"Unit";"Zergling";"Larva";909;1
"Unit";"Zergling";"Larva";910;1
"Building";"Extractor";NA;911;0
"Unit";"Hydralisk";"Larva";911;2
"Unit";"Roach";"Larva";913;2
"Unit";"Zergling";"Larva";915;1
"Unit";"Zergling";"Larva";916;1
"Unit";"Zergling";"Larva";917;1
"Unit";"Zergling";"Larva";918;1
"Unit";"Zergling";"Larva";919;1
"Unit";"Zergling";"Larva";920;1
"Unit";"Zergling";"Larva";921;1
"Unit";"Zergling";"Larva";922;1
"Unit";"Zergling";"Larva";923;1
"Unit";"Zergling";"Larva";924;1
"Unit";"Roach";"Larva";925;2
"Unit";"Roach";"Larva";927;2
"Unit";"Roach";"Larva";929;2
"Unit";"Zergling";"Larva";931;1
"Unit";"Zergling";"Larva";932;1
"Unit";"Zergling";"Larva";933;1
"Unit";"Zergling";"Larva";934;1
"Unit";"Zergling";"Larva";935;1
"Unit";"Zergling";"Larva";936;1
"Building";"Extractor";NA;937;0
"Unit";"Roach";"Larva";937;2
"Unit";"Roach";"Larva";939;2
"Unit";"Roach";"Larva";941;2
"Unit";"Roach";"Larva";943;2
"Unit";"Roach";"Larva";945;2
"Unit";"Zergling";"Larva";947;1
"Unit";"Zergling";"Larva";948;1
"Unit";"Zergling";"Larva";949;1
"Unit";"Zergling";"Larva";950;1
"Unit";"Zergling";"Larva";951;1
"Unit";"Zergling";"Larva";952;1
"Unit";"Zergling";"Larva";953;1
"Unit";"Zergling";"Larva";954;1
"Unit";"Zergling";"Larva";955;1
"Unit";"Zergling";"Larva";956;1
"Unit";"Zergling";"Larva";957;1
"Unit";"Zergling";"Larva";958;1
"Unit";"Zergling";"Larva";959;1
"Unit";"Zergling";"Larva";960;1
"Unit";"Zergling";"Larva";961;1
"Unit";"Zergling";"Larva";962;1
"Unit";"Queen";"Hatchery";963;2
"Unit";"Queen";"Hatchery";965;2
"Unit";"Queen";"Hatchery";967;2
"Unit";"Queen";"Hatchery";969;2
"Unit";"Queen";"Hatchery";971;2
"Unit";"Queen";"Hatchery";973;2
"Unit";"Roach";"Larva";975;2
"Unit";"Roach";"Larva";977;2
"Unit";"Roach";"Larva";979;2
"Unit";"Zergling";"Larva";981;1
"Unit";"Zergling";"Larva";982;1
"Unit";"Roach";"Larva";983;2
"Unit";"Hydralisk";"Larva";985;2
"Unit";"Hydralisk";"Larva";987;2
"Unit";"Zergling";"Larva";989;1
"Unit";"Zergling";"Larva";990;1
"Unit";"Zergling";"Larva";991;1
"Unit";"Zergling";"Larva";992;1
"Unit";"Zergling";"Larva";993;1
"Unit";"Zergling";"Larva";994;1
"Unit";"Zergling";"Larva";995;1
"Unit";"Zergling";"Larva";996;1
"Unit";"Zergling";"Larva";997;1
"Unit";"Zergling";"Larva";998;1
"Unit";"Zergling";"Larva";999;1
"Unit";"Zergling";"Larva";1000;1
"Unit";"Zergling";"Larva";1001;1
"Unit";"Zergling";"Larva";1002;1
"Unit";"Zergling";"Larva";1003;1
"Unit";"Zergling";"Larva";1004;1
"Unit";"Zergling";"Larva";1005;1
"Unit";"Zergling";"Larva";1006;1
"Unit";"Zergling";"Larva";1007;1
"Unit";"Zergling";"Larva";1008;1
"Unit";"Hydralisk";"Larva";1009;2
"Unit";"Hydralisk";"Larva";1011;2
"Unit";"Hydralisk";"Larva";1013;2
"Building";"Hatchery";NA;1015;0
"Unit";"Hydralisk";"Larva";1015;2
"Unit";"Hydralisk";"Larva";1017;2
"Unit";"Hydralisk";"Larva";1019;2
"Unit";"Queen";"Hatchery";1021;2
"Unit";"Queen";"Hatchery";1023;2
"Unit";"Queen";"Hatchery";1025;2
"Unit";"Queen";"Hatchery";1027;2
"Unit";"Roach";"Larva";1029;2
"Unit";"Roach";"Larva";1031;2
"Building";"CreepTumorQueen";NA;1033;0
"Building";"CreepTumorQueen";NA;1033;0
"Unit";"Roach";"Larva";1033;2
"Building";"CreepTumor";NA;1035;0
"Building";"CreepTumor";NA;1035;0
"Unit";"Roach";"Larva";1035;2
"Unit";"Roach";"Larva";1037;2
"Unit";"Roach";"Larva";1039;2
"Unit";"Roach";"Larva";1041;2
"Unit";"Roach";"Larva";1043;2
"Building";"Extractor";NA;1045;0
"Unit";"Overlord";"Larva";1045;0
"Unit";"Hydralisk";"Larva";1045;2
"Unit";"Roach";"Larva";1047;2
"Building";"CreepTumor";NA;1049;0
"Unit";"Roach";"Larva";1049;2
"Unit";"Roach";"Larva";1051;2
"Unit";"Roach";"Larva";1053;2
"Unit";"Roach";"Larva";1055;2
"Unit";"Roach";"Larva";1057;2
"Unit";"Roach";"Larva";1059;2
"Unit";"Roach";"Larva";1061;2
"Unit";"Hydralisk";"Larva";1063;2
"Unit";"Hydralisk";"Larva";1065;2
"Unit";"Hydralisk";"Larva";1067;2
"Unit";"Roach";"Larva";1069;2
"Unit";"Roach";"Larva";1071;2
"Unit";"Roach";"Larva";1073;2
"Unit";"Zergling";"Larva";1075;1
"Unit";"Zergling";"Larva";1076;1
"Unit";"Zergling";"Larva";1077;1
"Unit";"Zergling";"Larva";1078;1
"Unit";"Zergling";"Larva";1079;1
"Unit";"Zergling";"Larva";1080;1
"Unit";"Zergling";"Larva";1081;1
"Unit";"Zergling";"Larva";1082;1
"Unit";"Zergling";"Larva";1083;1
"Unit";"Zergling";"Larva";1084;1
"Unit";"Zergling";"Larva";1085;1
"Unit";"Zergling";"Larva";1086;1
"Unit";"Zergling";"Larva";1087;1
"Unit";"Zergling";"Larva";1088;1
"Unit";"Zergling";"Larva";1089;1
"Unit";"Zergling";"Larva";1090;1
"Unit";"Zergling";"Larva";1091;1
"Unit";"Zergling";"Larva";1092;1
"Unit";"Zergling";"Larva";1093;1
"Unit";"Zergling";"Larva";1094;1
"Unit";"Zergling";"Larva";1095;1
"Unit";"Zergling";"Larva";1096;1
"Unit";"Zergling";"Larva";1097;1
"Unit";"Zergling";"Larva";1098;1
"Unit";"Zergling";"Larva";1099;1
"Unit";"Zergling";"Larva";1100;1
"Unit";"Hydralisk";"Larva";1101;2
"Unit";"Zergling";"Larva";1103;1
"Unit";"Zergling";"Larva";1104;1
"Unit";"Zergling";"Larva";1105;1
"Unit";"Zergling";"Larva";1106;1
"Unit";"Zergling";"Larva";1107;1
"Unit";"Zergling";"Larva";1108;1
"Unit";"Roach";"Larva";1109;2
"Unit";"Roach";"Larva";1111;2
"Building";"Extractor";NA;1113;0
"Unit";"Hydralisk";"Larva";1113;2
"Unit";"Hydralisk";"Larva";1115;2
"Unit";"Hydralisk";"Larva";1117;2
"Unit";"Hydralisk";"Larva";1119;2
"Unit";"Hydralisk";"Larva";1121;2
"Unit";"Hydralisk";"Larva";1123;2
"Unit";"Hydralisk";"Larva";1125;2
"Building";"CreepTumorQueen";NA;1127;0
"Building";"CreepTumorQueen";NA;1127;0
"Building";"CreepTumorQueen";NA;1127;0
"Unit";"Hydralisk";"Larva";1127;2
"Unit";"Hydralisk";"Larva";1129;2
"Unit";"Zergling";"Larva";1131;1
"Unit";"Zergling";"Larva";1132;1
"Unit";"Zergling";"Larva";1133;1
"Unit";"Zergling";"Larva";1134;1
"Unit";"Zergling";"Larva";1135;1
"Unit";"Zergling";"Larva";1136;1
"Unit";"Zergling";"Larva";1137;1
"Unit";"Zergling";"Larva";1138;1
"Unit";"Zergling";"Larva";1139;1
"Unit";"Zergling";"Larva";1140;1
"Unit";"Zergling";"Larva";1141;1
"Unit";"Zergling";"Larva";1142;1
"Unit";"Zergling";"Larva";1143;1
"Unit";"Zergling";"Larva";1144;1
"Unit";"Zergling";"Larva";1145;1
"Unit";"Zergling";"Larva";1146;1
"Building";"CreepTumorQueen";NA;1147;0
"Building";"Extractor";NA;1149;0
"Unit";"Hydralisk";"Larva";1149;2
"Unit";"Hydralisk";"Larva";1151;2
"Unit";"Hydralisk";"Larva";1153;2
"Unit";"Hydralisk";"Larva";1155;2
"Unit";"Hydralisk";"Larva";1157;2
"Unit";"Roach";"Larva";1159;2
"Unit";"Roach";"Larva";1161;2
"Unit";"Roach";"Larva";1163;2
"Unit";"Roach";"Larva";1165;2
"Unit";"Roach";"Larva";1167;2
"Unit";"Roach";"Larva";1169;2
"Unit";"Roach";"Larva";1171;2
"Unit";"Roach";"Larva";1173;2
"Unit";"Roach";"Larva";1175;2
"Unit";"Roach";"Larva";1177;2
"Unit";"Roach";"Larva";1179;2
"Unit";"Hydralisk";"Larva";1181;2
"Unit";"Hydralisk";"Larva";1183;2
"Unit";"Hydralisk";"Larva";1185;2
"Unit";"Roach";"Larva";1187;2
"Building";"CreepTumor";NA;1189;0
"Building";"CreepTumor";NA;1189;0
"Building";"CreepTumorQueen";NA;1189;0
"Building";"CreepTumor";NA;1189;0
"Building";"CreepTumor";NA;1189;0
"Building";"CreepTumor";NA;1189;0
"Building";"CreepTumorQueen";NA;1189;0
"Building";"CreepTumorQueen";NA;1189;0
"Unit";"Hydralisk";"Larva";1189;2
"Unit";"Hydralisk";"Larva";1191;2
"Unit";"Hydralisk";"Larva";1193;2
"Unit";"Hydralisk";"Larva";1195;2
"Unit";"Hydralisk";"Larva";1197;2
"Unit";"Hydralisk";"Larva";1199;2
"Unit";"Hydralisk";"Larva";1201;2
"Unit";"Hydralisk";"Larva";1203;2
"Unit";"Hydralisk";"Larva";1205;2
"Unit";"Hydralisk";"Larva";1207;2
"Unit";"Hydralisk";"Larva";1209;2
"Unit";"Hydralisk";"Larva";1211;2
"Unit";"Hydralisk";"Larva";1213;2
"Unit";"Hydralisk";"Larva";1215;2
"Unit";"Hydralisk";"Larva";1217;2
"Unit";"Hydralisk";"Larva";1219;2
"Unit";"Hydralisk";"Larva";1221;2
"Unit";"Hydralisk";"Larva";1223;2
"Unit";"Hydralisk";"Larva";1225;2
"Building";"CreepTumorQueen";NA;1227;0
"Unit";"Hydralisk";"Larva";1227;2
"Unit";"Hydralisk";"Larva";1229;2
"Unit";"Hydralisk";"Larva";1231;2
"Unit";"Zergling";"Larva";1233;1
"Unit";"Zergling";"Larva";1234;1
"Building";"CreepTumorQueen";NA;1235;0
"Building";"Hatchery";NA;1235;0
"Unit";"Hydralisk";"Larva";1235;2
"Unit";"Hydralisk";"Larva";1237;2
"Unit";"Hydralisk";"Larva";1239;2
"Unit";"Hydralisk";"Larva";1241;2
"Unit";"Zergling";"Larva";1243;1
"Unit";"Zergling";"Larva";1244;1
"Unit";"Hydralisk";"Larva";1245;2
"Unit";"Zergling";"Larva";1247;1
"Unit";"Zergling";"Larva";1248;1
"Building";"CreepTumorQueen";NA;1249;0
"Building";"CreepTumorQueen";NA;1249;0
"Unit";"Hydralisk";"Larva";1249;2
"Unit";"Hydralisk";"Larva";1251;2
"Unit";"Hydralisk";"Larva";1253;2
"Unit";"Hydralisk";"Larva";1255;2
"Unit";"Hydralisk";"Larva";1257;2
"Unit";"Hydralisk";"Larva";1259;2
"Unit";"Hydralisk";"Larva";1261;2
"Unit";"Hydralisk";"Larva";1263;2
"Unit";"Hydralisk";"Larva";1265;2
"Unit";"Hydralisk";"Larva";1267;2
"Unit";"Hydralisk";"Larva";1269;2
"Unit";"Hydralisk";"Larva";1271;2
"Unit";"Hydralisk";"Larva";1273;2
"Unit";"Hydralisk";"Larva";1275;2
"Unit";"Hydralisk";"Larva";1277;2
"Unit";"Hydralisk";"Larva";1279;2
"Unit";"Hydralisk";"Larva";1281;2
"Unit";"Hydralisk";"Larva";1283;2
"Unit";"Hydralisk";"Larva";1285;2
"Unit";"Hydralisk";"Larva";1287;2
"Unit";"Hydralisk";"Larva";1289;2
"Unit";"Hydralisk";"Larva";1291;2
"Unit";"Hydralisk";"Larva";1293;2
"Unit";"Zergling";"Larva";1295;1
"Unit";"Zergling";"Larva";1296;1
"Unit";"Zergling";"Larva";1297;1
"Unit";"Zergling";"Larva";1298;1
"Unit";"Zergling";"Larva";1299;1
"Unit";"Zergling";"Larva";1300;1
"Unit";"Zergling";"Larva";1301;1
"Unit";"Zergling";"Larva";1302;1
"Unit";"Hydralisk";"Larva";1303;2
"Unit";"Hydralisk";"Larva";1305;2
"Unit";"Hydralisk";"Larva";1307;2
"Unit";"Hydralisk";"Larva";1309;2
"Unit";"Hydralisk";"Larva";1311;2
"Unit";"Roach";"Larva";1313;2
"Unit";"Roach";"Larva";1315;2
"Unit";"Roach";"Larva";1317;2
"Building";"Extractor";NA;1319;0
"Building";"Extractor";NA;1322;0
"Unit";"Hydralisk";"Larva";1325;2
"Unit";"Hydralisk";"Larva";1327;2
"Unit";"Hydralisk";"Larva";1329;2
"Building";"CreepTumorQueen";NA;1331;0
"Building";"CreepTumorQueen";NA;1331;0
"Unit";"Hydralisk";"Larva";1331;2
"Unit";"Hydralisk";"Larva";1333;2
"Unit";"Hydralisk";"Larva";1335;2
"Unit";"Hydralisk";"Larva";1337;2
"Unit";"Hydralisk";"Larva";1339;2
"Building";"CreepTumorQueen";NA;1341;0
"Unit";"Hydralisk";"Larva";1341;2
"Unit";"Zergling";"Larva";1343;1
"Unit";"Zergling";"Larva";1344;1
"Building";"Hatchery";NA;1345;0
"Unit";"Queen";"Hatchery";1345;2
"Unit";"Queen";"Hatchery";1347;2
"Building";"Hatchery";NA;1349;0
"Unit";"Queen";"Hatchery";1349;2
"Unit";"Overlord";"Larva";1351;0
"Unit";"Overlord";"Larva";1351;0
"Building";"CreepTumor";NA;1351;0
"Building";"CreepTumor";NA;1351;0
"Building";"CreepTumor";NA;1351;0
"Building";"CreepTumorQueen";NA;1351;0
"Building";"CreepTumorQueen";NA;1351;0
"Building";"CreepTumorQueen";NA;1351;0
"Building";"CreepTumorQueen";NA;1351;0
"Unit";"Queen";"Hatchery";1351;2
"Building";"CreepTumorQueen";NA;1353;0
"Building";"CreepTumorQueen";NA;1353;0
"Building";"CreepTumorQueen";NA;1353;0
"Building";"CreepTumorQueen";NA;1353;0
"Building";"CreepTumor";NA;1353;0
"Building";"Extractor";NA;1353;0
"Building";"Extractor";NA;1353;0
"Building";"CreepTumorQueen";NA;1355;0
"Building";"CreepTumorQueen";NA;1355;0
"Unit";"Zergling";"Larva";1355;1
"Unit";"Zergling";"Larva";1356;1
"Unit";"Zergling";"Larva";1357;1
"Unit";"Zergling";"Larva";1358;1
"Unit";"Zergling";"Larva";1359;1
"Unit";"Zergling";"Larva";1360;1
"Unit";"Zergling";"Larva";1361;1
"Unit";"Zergling";"Larva";1362;1
"Unit";"Zergling";"Larva";1363;1
"Unit";"Zergling";"Larva";1364;1
"Unit";"Zergling";"Larva";1365;1
"Unit";"Zergling";"Larva";1366;1
"Unit";"Zergling";"Larva";1367;1
"Unit";"Zergling";"Larva";1368;1
"Building";"Hatchery";NA;1369;0
"Building";"CreepTumorQueen";NA;1369;0
"Building";"CreepTumorQueen";NA;1369;0
"Building";"CreepTumorQueen";NA;1369;0
"Unit";"Hydralisk";"Larva";1369;2
"Unit";"Hydralisk";"Larva";1371;2
"Unit";"Hydralisk";"Larva";1373;2
"Unit";"Hydralisk";"Larva";1375;2
"Unit";"Hydralisk";"Larva";1385;2
"Unit";"Hydralisk";"Larva";1387;2
"Unit";"Hydralisk";"Larva";1389;2
"Unit";"Hydralisk";"Larva";1391;2
"Unit";"Hydralisk";"Larva";1393;2
"Building";"CreepTumorQueen";NA;1395;0
"Building";"CreepTumorQueen";NA;1395;0
"Building";"CreepTumorQueen";NA;1395;0
"Building";"CreepTumorQueen";NA;1395;0
"Building";"CreepTumorQueen";NA;1395;0
"Building";"CreepTumorQueen";NA;1395;0
"Building";"CreepTumorQueen";NA;1395;0
"Building";"CreepTumorQueen";NA;1395;0
"Building";"CreepTumorQueen";NA;1395;0
"Building";"CreepTumorQueen";NA;1395;0
"Upgrade";"SprayZerg";NA;1395;0
"Upgrade";"SprayZerg";NA;1395;0
"Upgrade";"SprayZerg";NA;1395;0
"Upgrade";"zerglingmovementspeed";NA;1395;0
"Upgrade";"SprayZerg";NA;1395;0
"Upgrade";"SprayZerg";NA;1395;0
"Upgrade";"SprayZerg";NA;1395;0
"Upgrade";"ZergMissileWeaponsLevel1";NA;1395;0
"Upgrade";"EvolveGroovedSpines";NA;1395;0
"Upgrade";"overlordspeed";NA;1395;0
"Upgrade";"EvolveMuscularAugments";NA;1395;0
"Upgrade";"SprayZerg";NA;1395;0
"Upgrade";"ZergMissileWeaponsLevel2";NA;1395;0
"Upgrade";"SprayZerg";NA;1395;0
"Upgrade";"ZergGroundArmorsLevel1";NA;1395;0
"Upgrade";"SprayZerg";NA;1395;0
"Upgrade";"DiggingClaws";NA;1395;0
"Upgrade";"SprayZerg";NA;1395;0
"Upgrade";"ZergMissileWeaponsLevel3";NA;1395;0
"Upgrade";"SprayZerg";NA;1395;0
"Upgrade";"SprayZerg";NA;1395;0
"Upgrade";"SprayZerg";NA;1395;0
"Upgrade";"SprayZerg";NA;1395;0
"Upgrade";"SprayZerg";NA;1395;0
"Upgrade";"SprayZerg";NA;1395;0
"Upgrade";"SprayZerg";NA;1395;0
"Upgrade";"SprayZerg";NA;1395;0
"Upgrade";"SprayZerg";NA;1395;0
"Upgrade";"SprayZerg";NA;1395;0
"Upgrade";"SprayZerg";NA;1395;0
"Upgrade";"ZergMeleeWeaponsLevel1";NA;1395;0
"Upgrade";"SprayZerg";NA;1395;0
"Upgrade";"SprayZerg";NA;1395;0
"Upgrade";"SprayZerg";NA;1395;0
"Upgrade";"SprayZerg";NA;1395;0
"Upgrade";"SprayZerg";NA;1395;0
"Upgrade";"SprayZerg";NA;1395;0
