"type";"unit_name";"on_building";"total_supply";"supply"
"Unit";"Overlord";"Larva";13;0
"Building";"Extractor";NA;17;0
"Building";"SpawningPool";NA;18;0
"Unit";"Overlord";"Larva";21;0
"Building";"Hatchery";NA;16;0
"Unit";"Zergling";"Larva";22;1
"Unit";"Zergling";"Larva";22;1
"Unit";"Zergling";"Larva";22;1
"Unit";"Zergling";"Larva";22;1
"Unit";"Queen";"Hatchery";22;2
"Unit";"Queen";"Hatchery";22;2
"Building";"CreepTumorQueen";NA;35;0
"Unit";"Overlord";"Larva";35;0
"Building";"CreepTumor";NA;38;0
"Building";"CreepTumorQueen";NA;40;0
"Unit";"Overlord";"Larva";40;0
"Unit";"Queen";"Hatchery";40;2
"Building";"CreepTumor";NA;45;0
"Building";"SporeCrawler";NA;42;0
"Building";"CreepTumor";NA;45;0
"Building";"SporeCrawler";NA;43;0
"Building";"Hatchery";NA;35;0
"Unit";"Overlord";"Larva";50;0
"Building";"Extractor";NA;49;0
"Building";"SporeCrawler";NA;50;0
"Building";"Extractor";NA;50;0
"Unit";"Queen";"Hatchery";50;2
"Unit";"Overlord";"Larva";55;0
"Building";"CreepTumor";NA;55;0
"Building";"CreepTumor";NA;55;0
"Building";"CreepTumorQueen";NA;57;0
"Building";"CreepTumor";NA;58;0
"Building";"CreepTumorQueen";NA;69;0
"Building";"CreepTumorQueen";NA;69;0
"Building";"EvolutionChamber";NA;58;0
"Building";"RoachWarren";NA;58;0
"Unit";"Zergling";"Larva";69;1
"Unit";"Zergling";"Larva";69;1
"Unit";"Zergling";"Larva";69;1
"Unit";"Zergling";"Larva";69;1
"Unit";"Zergling";"Larva";69;1
"Unit";"Zergling";"Larva";69;1
"Unit";"Zergling";"Larva";69;1
"Unit";"Zergling";"Larva";69;1
"Unit";"Zergling";"Larva";69;1
"Unit";"Zergling";"Larva";69;1
"Unit";"Zergling";"Larva";69;1
"Unit";"Zergling";"Larva";69;1
"Unit";"Zergling";"Larva";69;1
"Unit";"Zergling";"Larva";69;1
"Unit";"Zergling";"Larva";69;1
"Unit";"Zergling";"Larva";69;1
"Unit";"Zergling";"Larva";69;1
"Unit";"Zergling";"Larva";69;1
"Building";"Extractor";NA;69;0
"Building";"CreepTumor";NA;69;0
"Building";"CreepTumor";NA;87;0
"Building";"CreepTumor";NA;87;0
"Building";"CreepTumor";NA;92;0
"Building";"CreepTumor";NA;92;0
"Unit";"Overlord";"Larva";92;0
"Unit";"Overlord";"Larva";92;0
"Unit";"Overlord";"Larva";92;0
"Building";"CreepTumorQueen";NA;92;0
"Unit";"Roach";"Larva";92;2
"Unit";"Roach";"Larva";92;2
"Unit";"Roach";"Larva";92;2
"Unit";"Roach";"Larva";92;2
"Unit";"Roach";"Larva";92;2
"Unit";"Roach";"Larva";92;2
"Unit";"Roach";"Larva";92;2
"Unit";"Roach";"Larva";92;2
"Building";"CreepTumor";NA;92;0
"Unit";"Roach";"Larva";92;2
"Unit";"Roach";"Larva";92;2
"Building";"CreepTumor";NA;92;0
"Building";"CreepTumor";NA;92;0
"Building";"CreepTumor";NA;92;0
"Building";"HydraliskDen";NA;92;0
"Unit";"Overlord";"Larva";92;0
"Unit";"Overlord";"Larva";92;0
"Unit";"Overlord";"Larva";92;0
"Unit";"Roach";"Larva";112;2
"Unit";"Roach";"Larva";112;2
"Upgrade";"GlialReconstitution";"RoachWarren";92;0
"Unit";"Roach";"Larva";112;2
"Unit";"Roach";"Larva";112;2
"Unit";"Roach";"Larva";112;2
"Unit";"Roach";"Larva";112;2
"Unit";"Roach";"Larva";112;2
"Unit";"Roach";"Larva";112;2
"Unit";"Roach";"Larva";112;2
"Unit";"Roach";"Larva";112;2
"Unit";"Roach";"Larva";112;2
"Unit";"Roach";"Larva";116;2
"Unit";"Roach";"Larva";116;2
"Unit";"Roach";"Larva";116;2
"Unit";"Roach";"Larva";116;2
"Unit";"Roach";"Larva";116;2
"Unit";"Roach";"Larva";134;2
"Upgrade";"ZergMissileWeaponsLevel1";"EvolutionChamber";92;0
"Unit";"Roach";"Larva";134;2
"Unit";"Roach";"Larva";134;2
"Unit";"Roach";"Larva";134;2
"Unit";"Roach";"Larva";134;2
"Unit";"Roach";"Larva";144;2
"Unit";"Roach";"Larva";144;2
"Unit";"Roach";"Larva";144;2
"Unit";"Roach";"Larva";154;2
"Unit";"Roach";"Larva";154;2
"Unit";"Roach";"Larva";154;2
"Unit";"Roach";"Larva";160;2
"Unit";"Roach";"Larva";160;2
"Unit";"Roach";"Larva";160;2
"Unit";"Roach";"Larva";160;2
"Unit";"Roach";"Larva";160;2
"Unit";"Overlord";"Larva";166;0
"Unit";"Overlord";"Larva";166;0
"Unit";"Overlord";"Larva";166;0
"Unit";"Roach";"Larva";176;2
"Unit";"Roach";"Larva";176;2
"Unit";"Roach";"Larva";176;2
"Unit";"Roach";"Larva";176;2
"Unit";"Roach";"Larva";176;2
"Unit";"Roach";"Larva";176;2
"Unit";"Roach";"Larva";176;2
"Unit";"Roach";"Larva";176;2
"Unit";"Roach";"Larva";176;2
"Unit";"Roach";"Larva";178;2
"Unit";"Roach";"Larva";186;2
"Unit";"Roach";"Larva";186;2
"Unit";"Roach";"Larva";186;2
"Unit";"Roach";"Larva";194;2
"Unit";"Roach";"Larva";194;2
"Building";"Hatchery";NA;176;0
"Unit";"Roach";"Larva";194;2
"Unit";"Roach";"Larva";194;2
"Unit";"Roach";"Larva";194;2
"Unit";"Roach";"Larva";194;2
"Unit";"Roach";"Larva";194;2
"Unit";"Roach";"Larva";194;2
"Unit";"Roach";"Larva";204;2
"Unit";"Roach";"Larva";206;2
"Unit";"Roach";"Larva";206;2
"Unit";"Roach";"Larva";206;2
"Building";"CreepTumor";NA;218;0
"Building";"CreepTumor";NA;220;0
"Building";"CreepTumor";NA;226;0
"Building";"CreepTumor";NA;226;0
"Building";"CreepTumor";NA;233;0
"Unit";"Overlord";"Larva";233;0
"Unit";"Overlord";"Larva";233;0
"Building";"CreepTumor";NA;233;0
"Unit";"Queen";"Hatchery";226;2
"Unit";"Hydralisk";"Larva";233;2
"Unit";"Hydralisk";"Larva";233;2
"Unit";"Hydralisk";"Larva";233;2
"Unit";"Hydralisk";"Larva";233;2
"Unit";"Overlord";"Larva";235;0
"Unit";"Overlord";"Larva";235;0
"Building";"CreepTumor";NA;243;0
"Unit";"Hydralisk";"Larva";235;2
"Unit";"Hydralisk";"Larva";235;2
"Unit";"Hydralisk";"Larva";235;2
"Unit";"Hydralisk";"Larva";235;2
"Building";"CreepTumor";NA;243;0
"Building";"Extractor";NA;243;0
"Building";"Extractor";NA;243;0
"Building";"CreepTumor";NA;252;0
"Building";"CreepTumor";NA;263;0
"Building";"CreepTumor";NA;263;0
"Building";"CreepTumor";NA;263;0
"Upgrade";"EvolveGroovedSpines";"HydraliskDen";243;0
"Building";"CreepTumor";NA;269;0
"Unit";"Overlord";"Larva";269;0
"Unit";"Hydralisk";"Larva";269;2
"Upgrade";"ZergMissileWeaponsLevel2";"EvolutionChamber";233;0
"Building";"CreepTumor";NA;271;0
"Building";"CreepTumor";NA;271;0
"Building";"CreepTumor";NA;271;0
"Unit";"Overlord";"Larva";271;0
"Unit";"Overlord";"Larva";271;0
"Unit";"Overlord";"Larva";271;0
"Unit";"Overlord";"Larva";271;0
"Unit";"Overlord";"Larva";271;0
"Unit";"Overlord";"Larva";271;0
"Unit";"Overlord";"Larva";271;0
"Unit";"Overlord";"Larva";271;0
"Building";"CreepTumor";NA;271;0
"Unit";"Hydralisk";"Larva";271;2
"Unit";"Hydralisk";"Larva";271;2
"Unit";"Hydralisk";"Larva";271;2
"Unit";"Hydralisk";"Larva";271;2
"Building";"LurkerDenMP";NA;263;0
"Upgrade";"EvolveMuscularAugments";"HydraliskDen";271;0
"Building";"CreepTumor";NA;279;0
"Building";"CreepTumor";NA;279;0
"Building";"Hatchery";NA;269;0
"Building";"CreepTumor";NA;279;0
"Unit";"Hydralisk";"Larva";279;2
"Unit";"Hydralisk";"Larva";279;2
"Unit";"Hydralisk";"Larva";279;2
"Unit";"Hydralisk";"Larva";279;2
"Unit";"Hydralisk";"Larva";279;2
"Unit";"Hydralisk";"Larva";279;2
"Unit";"Hydralisk";"Larva";279;2
"Unit";"Hydralisk";"Larva";279;2
"Unit";"Hydralisk";"Larva";279;2
"Building";"CreepTumor";NA;279;0
"Unit";"Hydralisk";"Larva";279;2
"Unit";"Hydralisk";"Larva";279;2
"Unit";"Hydralisk";"Larva";279;2
"Unit";"Hydralisk";"Larva";279;2
"Building";"CreepTumor";NA;297;0
"Building";"CreepTumor";NA;297;0
"Building";"InfestationPit";NA;279;0
"Building";"CreepTumor";NA;297;0
"Building";"SpawningPool";NA;305;0
"Building";"CreepTumor";NA;324;0
"Building";"SporeCrawler";NA;324;0
"Building";"SporeCrawler";NA;324;0
"Upgrade";"ZergGroundArmorsLevel1";"EvolutionChamber";305;0
"Building";"SporeCrawler";NA;324;0
"Building";"CreepTumor";NA;332;0
"Building";"CreepTumorQueen";NA;332;0
"Building";"CreepTumorQueen";NA;332;0
"Building";"SporeCrawler";NA;332;0
"Building";"SpineCrawler";NA;332;0
"Building";"SpineCrawler";NA;332;0
"Building";"CreepTumor";NA;332;0
"Building";"LurkerDenMP";NA;305;0
"Unit";"Hydralisk";"Larva";332;2
"Unit";"Hydralisk";"Larva";332;2
"Unit";"Hydralisk";"Larva";332;2
"Unit";"Hydralisk";"Larva";332;2
"Unit";"Hydralisk";"Larva";332;2
"Unit";"Hydralisk";"Larva";332;2
"Unit";"Hydralisk";"Larva";332;2
"Unit";"Hydralisk";"Larva";332;2
"Unit";"Hydralisk";"Larva";332;2
"Unit";"Hydralisk";"Larva";332;2
"Unit";"Hydralisk";"Larva";332;2
"Building";"CreepTumor";NA;332;0
"Building";"CreepTumor";NA;332;0
"Building";"Extractor";NA;332;0
"Building";"Extractor";NA;332;0
"Building";"CreepTumor";NA;354;0
"Building";"SporeCrawler";NA;336;0
"Building";"CreepTumor";NA;354;0
"Building";"SporeCrawler";NA;354;0
"Building";"SpineCrawler";NA;332;0
"Building";"SpineCrawler";NA;336;0
"Building";"Extractor";NA;354;0
"Building";"Extractor";NA;354;0
"Building";"CreepTumor";NA;354;0
"Building";"CreepTumor";NA;363;0
"Building";"Spire";NA;332;0
"Building";"Hatchery";NA;332;0
"Building";"SporeCrawler";NA;363;0
"Building";"SporeCrawler";NA;363;0
"Building";"SporeCrawler";NA;363;0
"Building";"CreepTumor";NA;363;0
"Building";"SporeCrawler";NA;363;0
"Building";"SpineCrawler";NA;363;0
"Building";"SpineCrawler";NA;363;0
"Building";"SpineCrawler";NA;363;0
"Building";"SpineCrawler";NA;363;0
"Building";"SpineCrawler";NA;363;0
"Building";"CreepTumor";NA;367;0
"Upgrade";"ZergMissileWeaponsLevel3";"EvolutionChamber";354;0
"Building";"SpineCrawler";NA;367;0
"Building";"SpineCrawler";NA;367;0
"Building";"SpineCrawler";NA;367;0
"Unit";"Hydralisk";"Larva";373;2
"Unit";"Hydralisk";"Larva";373;2
"Unit";"Hydralisk";"Larva";373;2
"Unit";"Hydralisk";"Larva";373;2
"Unit";"Hydralisk";"Larva";373;2
"Unit";"Hydralisk";"Larva";373;2
"Unit";"Hydralisk";"Larva";373;2
"Unit";"Hydralisk";"Larva";373;2
"Unit";"Hydralisk";"Larva";373;2
"Unit";"Hydralisk";"Larva";373;2
"Unit";"Hydralisk";"Larva";373;2
"Unit";"Hydralisk";"Larva";373;2
"Unit";"Hydralisk";"Larva";373;2
"Unit";"Hydralisk";"Larva";373;2
"Unit";"Hydralisk";"Larva";401;2
"Building";"SpineCrawler";NA;401;0
"Building";"SpineCrawler";NA;401;0
"Building";"SpineCrawler";NA;401;0
"Building";"SpineCrawler";NA;401;0
"Building";"SpineCrawler";NA;401;0
"Unit";"Roach";"Larva";403;2
"Unit";"Roach";"Larva";403;2
"Unit";"Roach";"Larva";403;2
"Unit";"Roach";"Larva";403;2
"Unit";"Roach";"Larva";403;2
"Unit";"Roach";"Larva";403;2
"Unit";"Roach";"Larva";403;2
"Unit";"Roach";"Larva";403;2
"Unit";"Roach";"Larva";403;2
"Building";"CreepTumor";NA;403;0
"Building";"CreepTumor";NA;403;0
"Unit";"Hydralisk";"Larva";403;2
"Unit";"Hydralisk";"Larva";403;2
