"type";"unit_name";"on_building";"total_supply";"supply"
"Unit";"Overlord";"Larva";12;0
"Building";"Extractor";NA;16;0
"Unit";"Overlord";"Larva";21;0
"Building";"Hatchery";NA;16;0
"Building";"SpawningPool";NA;19;0
"Unit";"Zergling";"Larva";22;1
"Unit";"Zergling";"Larva";22;1
"Unit";"Zergling";"Larva";22;1
"Unit";"Zergling";"Larva";22;1
"Unit";"Queen";"Hatchery";22;2
"Unit";"Queen";"Hatchery";22;2
"Unit";"Overlord";"Larva";37;0
"Building";"CreepTumorQueen";NA;39;0
"Unit";"Zergling";"Larva";42;1
"Unit";"Zergling";"Larva";42;1
"Unit";"Zergling";"Larva";42;1
"Unit";"Zergling";"Larva";42;1
"Unit";"Zergling";"Larva";42;1
"Unit";"Zergling";"Larva";42;1
"Unit";"Zergling";"Larva";42;1
"Unit";"Zergling";"Larva";42;1
"Unit";"Zergling";"Larva";42;1
"Unit";"Zergling";"Larva";42;1
"Building";"SporeCrawler";NA;42;0
"Building";"Hatchery";NA;37;0
"Building";"SporeCrawler";NA;48;0
"Unit";"Overlord";"Larva";55;0
"Unit";"Overlord";"Larva";55;0
"Unit";"Overlord";"Larva";55;0
"Building";"CreepTumor";NA;55;0
"Building";"Extractor";NA;55;0
"Building";"Extractor";NA;55;0
"Unit";"Overlord";"Larva";63;0
"Building";"RoachWarren";NA;55;0
"Unit";"Queen";"Hatchery";56;2
"Building";"CreepTumor";NA;69;0
"Unit";"Overlord";"Larva";69;0
"Unit";"Overlord";"Larva";69;0
"Unit";"Overlord";"Larva";69;0
"Unit";"Roach";"Larva";75;2
"Unit";"Roach";"Larva";75;2
"Unit";"Roach";"Larva";75;2
"Building";"Extractor";NA;75;0
"Unit";"Overlord";"Larva";75;0
"Unit";"Roach";"Larva";75;2
"Unit";"Roach";"Larva";75;2
"Unit";"Roach";"Larva";75;2
"Unit";"Roach";"Larva";75;2
"Unit";"Roach";"Larva";75;2
"Unit";"Roach";"Larva";81;2
"Unit";"Roach";"Larva";81;2
"Unit";"Overlord";"Larva";81;0
"Unit";"Roach";"Larva";81;2
"Unit";"Roach";"Larva";83;2
"Unit";"Roach";"Larva";85;2
"Unit";"Roach";"Larva";91;2
"Unit";"Roach";"Larva";91;2
"Unit";"Roach";"Larva";91;2
"Building";"CreepTumor";NA;101;0
"Unit";"Overlord";"Larva";95;0
"Unit";"Roach";"Larva";101;2
"Unit";"Roach";"Larva";101;2
"Unit";"Roach";"Larva";101;2
"Unit";"Overlord";"Larva";101;0
"Unit";"Overlord";"Larva";101;0
"Upgrade";"GlialReconstitution";"RoachWarren";81;0
"Unit";"Queen";"Hatchery";107;2
"Unit";"Roach";"Larva";115;2
"Unit";"Roach";"Larva";115;2
"Unit";"Roach";"Larva";115;2
"Unit";"Roach";"Larva";115;2
"Unit";"Roach";"Larva";115;2
"Unit";"Roach";"Larva";115;2
"Unit";"Roach";"Larva";115;2
"Building";"CreepTumor";NA;115;0
"Unit";"Overlord";"Larva";115;0
"Unit";"Overlord";"Larva";115;0
"Unit";"Queen";"Hatchery";113;2
"Unit";"Overlord";"Larva";131;0
"Unit";"Overlord";"Larva";131;0
"Unit";"Roach";"Larva";143;2
"Unit";"Roach";"Larva";143;2
"Unit";"Roach";"Larva";143;2
"Unit";"Roach";"Larva";143;2
"Unit";"Roach";"Larva";143;2
"Unit";"Roach";"Larva";143;2
"Unit";"Roach";"Larva";143;2
"Unit";"Roach";"Larva";143;2
"Unit";"Overlord";"Larva";165;0
"Building";"Extractor";NA;165;0
"Building";"CreepTumorQueen";NA;169;0
"Building";"Extractor";NA;165;0
"Unit";"Roach";"Larva";165;2
"Unit";"Roach";"Larva";165;2
"Unit";"Roach";"Larva";165;2
"Unit";"Roach";"Larva";165;2
"Unit";"Roach";"Larva";165;2
"Unit";"Queen";"Hatchery";165;2
"Unit";"Roach";"Larva";182;2
"Unit";"Roach";"Larva";182;2
"Unit";"Roach";"Larva";182;2
"Unit";"Roach";"Larva";182;2
"Building";"Spire";NA;159;0
"Building";"EvolutionChamber";NA;182;0
"Building";"CreepTumorQueen";NA;192;0
"Building";"CreepTumor";NA;192;0
"Unit";"Roach";"Larva";192;2
"Unit";"Roach";"Larva";192;2
"Unit";"Roach";"Larva";192;2
"Unit";"Roach";"Larva";192;2
"Unit";"Roach";"Larva";192;2
"Unit";"Roach";"Larva";192;2
"Unit";"Roach";"Larva";192;2
"Unit";"Roach";"Larva";192;2
"Unit";"Roach";"Larva";192;2
"Unit";"Roach";"Larva";192;2
"Unit";"Overlord";"Larva";192;0
"Unit";"Overlord";"Larva";192;0
"Building";"Hatchery";NA;169;0
"Unit";"Mutalisk";"Larva";192;2
"Unit";"Mutalisk";"Larva";192;2
"Unit";"Mutalisk";"Larva";192;2
"Unit";"Mutalisk";"Larva";192;2
"Unit";"Mutalisk";"Larva";192;2
"Unit";"Mutalisk";"Larva";192;2
"Unit";"Overlord";"Larva";192;0
"Unit";"Overlord";"Larva";192;0
"Unit";"Mutalisk";"Larva";192;2
"Building";"CreepTumorQueen";NA;212;0
"Unit";"Overlord";"Larva";212;0
"Unit";"Overlord";"Larva";212;0
"Unit";"Queen";"Hatchery";192;2
"Unit";"Queen";"Hatchery";192;2
"Unit";"Queen";"Hatchery";192;2
"Building";"CreepTumor";NA;224;0
"Unit";"Overlord";"Larva";212;0
"Unit";"Mutalisk";"Larva";214;2
"Unit";"Mutalisk";"Larva";216;2
"Unit";"Overlord";"Larva";226;0
"Unit";"Roach";"Larva";226;2
"Unit";"Roach";"Larva";226;2
"Unit";"Roach";"Larva";232;2
"Unit";"Roach";"Larva";232;2
"Unit";"Roach";"Larva";232;2
"Building";"CreepTumorQueen";NA;241;0
"Building";"CreepTumorQueen";NA;245;0
"Unit";"Queen";"Hatchery";232;2
"Unit";"Overlord";"Larva";245;0
"Unit";"Roach";"Larva";245;2
"Unit";"Roach";"Larva";245;2
"Unit";"Roach";"Larva";245;2
"Unit";"Roach";"Larva";245;2
"Unit";"Roach";"Larva";245;2
"Unit";"Roach";"Larva";245;2
"Building";"CreepTumor";NA;267;0
"Unit";"Mutalisk";"Larva";267;2
"Building";"CreepTumor";NA;267;0
"Building";"CreepTumor";NA;267;0
"Building";"CreepTumor";NA;267;0
"Building";"CreepTumorQueen";NA;267;0
"Building";"CreepTumorQueen";NA;267;0
"Unit";"Roach";"Larva";267;2
"Unit";"Roach";"Larva";267;2
"Unit";"Roach";"Larva";267;2
"Building";"CreepTumorQueen";NA;269;0
"Building";"CreepTumorQueen";NA;269;0
"Building";"HydraliskDen";NA;267;0
"Upgrade";"ZergMissileWeaponsLevel1";"EvolutionChamber";245;0
"Building";"InfestationPit";NA;267;0
"Building";"CreepTumor";NA;287;0
"Unit";"Queen";"Hatchery";275;2
"Building";"CreepTumorQueen";NA;294;0
"Building";"CreepTumorQueen";NA;294;0
"Building";"CreepTumor";NA;294;0
"Building";"CreepTumor";NA;294;0
"Building";"CreepTumor";NA;294;0
"Building";"CreepTumor";NA;294;0
"Unit";"Queen";"Hatchery";275;2
"Unit";"Roach";"Larva";299;2
"Unit";"Roach";"Larva";299;2
"Building";"Extractor";NA;301;0
"Building";"CreepTumor";NA;303;0
"Building";"CreepTumor";NA;303;0
"Building";"CreepTumor";NA;303;0
"Unit";"Roach";"Larva";307;2
"Unit";"Roach";"Larva";307;2
"Unit";"Roach";"Larva";307;2
"Unit";"Roach";"Larva";307;2
"Unit";"Roach";"Larva";307;2
"Unit";"Roach";"Larva";307;2
"Unit";"Roach";"Larva";307;2
"Unit";"Roach";"Larva";307;2
"Unit";"Roach";"Larva";307;2
"Unit";"Roach";"Larva";307;2
"Unit";"Roach";"Larva";307;2
"Unit";"Roach";"Larva";307;2
"Unit";"Roach";"Larva";307;2
"Unit";"Roach";"Larva";307;2
"Unit";"Roach";"Larva";307;2
"Unit";"Roach";"Larva";307;2
"Unit";"Roach";"Larva";307;2
"Unit";"Roach";"Larva";307;2
"Unit";"Roach";"Larva";307;2
"Unit";"Roach";"Larva";307;2
"Unit";"Roach";"Larva";307;2
"Unit";"Roach";"Larva";307;2
"Unit";"Roach";"Larva";307;2
"Unit";"Roach";"Larva";307;2
"Unit";"Roach";"Larva";335;2
"Unit";"Roach";"Larva";335;2
