"type";"unit_name";"on_building";"total_supply";"supply"
"Unit";"Overlord";"Larva";12;0
"Building";"Extractor";NA;18;0
"Building";"SpawningPool";NA;19;0
"Building";"Hatchery";NA;17;0
"Unit";"Zergling";"Larva";23;1
"Unit";"Zergling";"Larva";23;1
"Unit";"Zergling";"Larva";23;1
"Unit";"Zergling";"Larva";23;1
"Unit";"Zergling";"Larva";23;1
"Unit";"Zergling";"Larva";23;1
"Unit";"Zergling";"Larva";23;1
"Unit";"Zergling";"Larva";23;1
"Unit";"Zergling";"Larva";23;1
"Unit";"Zergling";"Larva";23;1
"Unit";"Overlord";"Larva";33;0
"Unit";"Queen";"Hatchery";33;2
"Unit";"Queen";"Hatchery";33;2
"Unit";"Overlord";"Larva";44;0
"Building";"BanelingNest";NA;33;0
"Building";"Hatchery";NA;33;0
"Unit";"Overlord";"Larva";50;0
"Unit";"Overlord";"Larva";51;0
"Unit";"Overlord";"Larva";54;0
"Unit";"Overlord";"Larva";54;0
"Unit";"Queen";"Hatchery";46;2
"Unit";"Overlord";"Larva";69;0
"Unit";"Overlord";"Larva";69;0
"Unit";"Overlord";"Larva";69;0
"Building";"Extractor";NA;69;0
"Building";"Extractor";NA;69;0
"Building";"RoachWarren";NA;65;0
"Building";"SporeCrawler";NA;71;0
"Building";"SporeCrawler";NA;71;0
"Building";"SporeCrawler";NA;71;0
"Unit";"Overlord";"Larva";75;0
"Unit";"Overlord";"Larva";86;0
"Unit";"Overlord";"Larva";86;0
"Unit";"Roach";"Larva";86;2
"Building";"Extractor";NA;86;0
"Unit";"Roach";"Larva";86;2
"Unit";"Roach";"Larva";86;2
"Unit";"Roach";"Larva";86;2
"Building";"Extractor";NA;86;0
"Unit";"Overlord";"Larva";86;0
"Unit";"Overlord";"Larva";86;0
"Unit";"Overlord";"Larva";86;0
"Unit";"Overlord";"Larva";86;0
"Unit";"Queen";"Hatchery";94;2
"Building";"Extractor";NA;94;0
"Unit";"Overlord";"Larva";107;0
"Unit";"Overlord";"Larva";107;0
"Unit";"Overlord";"Larva";107;0
"Building";"HydraliskDen";NA;94;0
"Building";"NydusNetwork";NA;94;0
"Building";"SporeCrawler";NA;107;0
"Unit";"Queen";"Hatchery";107;2
"Unit";"Queen";"Hatchery";107;2
"Unit";"Hydralisk";"Larva";109;2
"Unit";"Hydralisk";"Larva";109;2
"Unit";"Hydralisk";"Larva";109;2
"Unit";"Hydralisk";"Larva";109;2
"Unit";"Hydralisk";"Larva";109;2
"Unit";"Hydralisk";"Larva";109;2
"Unit";"Hydralisk";"Larva";109;2
"Unit";"Hydralisk";"Larva";109;2
"Unit";"Hydralisk";"Larva";109;2
"Unit";"Hydralisk";"Larva";109;2
"Unit";"Hydralisk";"Larva";109;2
"Unit";"Hydralisk";"Larva";109;2
"Unit";"Hydralisk";"Larva";109;2
"Building";"CreepTumorQueen";NA;123;0
"Unit";"Overlord";"Larva";139;0
"Unit";"Overlord";"Larva";139;0
"Unit";"Overlord";"Larva";139;0
"Unit";"Overlord";"Larva";139;0
"Unit";"Overlord";"Larva";139;0
"Unit";"Hydralisk";"Larva";139;2
"Unit";"Hydralisk";"Larva";139;2
"Unit";"Hydralisk";"Larva";139;2
"Unit";"Hydralisk";"Larva";139;2
"Building";"NydusCanal";NA;139;0
"Building";"SpawningPool";NA;139;0
"Unit";"Hydralisk";"Larva";143;2
"Unit";"Hydralisk";"Larva";147;2
"Unit";"Hydralisk";"Larva";147;2
"Unit";"Hydralisk";"Larva";147;2
"Unit";"Hydralisk";"Larva";147;2
"Upgrade";"EvolveGroovedSpines";"HydraliskDen";139;0
"Unit";"Hydralisk";"Larva";147;2
"Unit";"Hydralisk";"Larva";147;2
"Unit";"Hydralisk";"Larva";147;2
"Unit";"Hydralisk";"Larva";147;2
"Building";"CreepTumorQueen";NA;165;0
"Building";"CreepTumorQueen";NA;165;0
"Building";"CreepTumorQueen";NA;165;0
"Unit";"Hydralisk";"Larva";157;2
"Unit";"Hydralisk";"Larva";157;2
"Unit";"Hydralisk";"Larva";157;2
"Unit";"Hydralisk";"Larva";157;2
"Unit";"Hydralisk";"Larva";157;2
"Unit";"Roach";"Larva";175;2
"Unit";"Roach";"Larva";175;2
"Unit";"Roach";"Larva";175;2
"Unit";"Roach";"Larva";175;2
"Unit";"Roach";"Larva";175;2
"Unit";"Roach";"Larva";175;2
"Unit";"Roach";"Larva";175;2
"Unit";"Roach";"Larva";175;2
"Unit";"Roach";"Larva";175;2
"Unit";"Roach";"Larva";175;2
"Unit";"Roach";"Larva";175;2
"Unit";"Roach";"Larva";175;2
"Unit";"Queen";"Hatchery";165;2
"Unit";"Queen";"Hatchery";165;2
"Unit";"Queen";"Hatchery";165;2
"Building";"CreepTumor";NA;175;0
"Building";"CreepTumor";NA;175;0
"Building";"CreepTumor";NA;205;0
"Building";"SporeCrawler";NA;205;0
"Building";"SporeCrawler";NA;205;0
"Building";"SporeCrawler";NA;205;0
"Building";"SporeCrawler";NA;205;0
"Unit";"Hydralisk";"Larva";205;2
"Unit";"Hydralisk";"Larva";205;2
"Unit";"Hydralisk";"Larva";205;2
"Unit";"Hydralisk";"Larva";205;2
"Unit";"Hydralisk";"Larva";205;2
"Unit";"Hydralisk";"Larva";205;2
"Unit";"Hydralisk";"Larva";205;2
"Unit";"Hydralisk";"Larva";205;2
"Building";"EvolutionChamber";NA;205;0
"Unit";"Hydralisk";"Larva";205;2
"Unit";"Hydralisk";"Larva";205;2
"Unit";"Hydralisk";"Larva";205;2
"Unit";"Hydralisk";"Larva";205;2
"Unit";"Hydralisk";"Larva";205;2
"Building";"CreepTumor";NA;221;0
"Building";"CreepTumorQueen";NA;221;0
"Unit";"Queen";"Hatchery";205;2
"Building";"Hatchery";NA;175;0
"Upgrade";"EvolveMuscularAugments";"HydraliskDen";205;0
"Unit";"Hydralisk";"Larva";245;2
"Unit";"Hydralisk";"Larva";245;2
"Unit";"Hydralisk";"Larva";245;2
"Unit";"Hydralisk";"Larva";245;2
"Unit";"Hydralisk";"Larva";245;2
"Unit";"Hydralisk";"Larva";245;2
"Unit";"Hydralisk";"Larva";245;2
"Unit";"Hydralisk";"Larva";245;2
"Unit";"Hydralisk";"Larva";245;2
"Unit";"Hydralisk";"Larva";245;2
"Unit";"Hydralisk";"Larva";245;2
"Unit";"Hydralisk";"Larva";267;2
"Unit";"Hydralisk";"Larva";267;2
"Unit";"Hydralisk";"Larva";267;2
"Unit";"Hydralisk";"Larva";267;2
"Unit";"Hydralisk";"Larva";267;2
"Unit";"Hydralisk";"Larva";267;2
"Unit";"Hydralisk";"Larva";267;2
"Unit";"Hydralisk";"Larva";267;2
"Unit";"Hydralisk";"Larva";267;2
"Upgrade";"ZergMissileWeaponsLevel1";"EvolutionChamber";245;0
"Building";"SporeCrawler";NA;267;0
