"type";"unit_name";"on_building";"total_supply_lag";"supply"
"Unit";"Overlord";"Larva";13;0
"Building";"Hatchery";NA;16;0
"Building";"Extractor";NA;19;0
"Building";"SpawningPool";NA;19;0
"Building";"Hatchery";NA;23;0
"Unit";"Queen";"Hatchery";23;2
"Unit";"Queen";"Hatchery";28;2
"Unit";"Overlord";"Larva";30;0
"Unit";"Zergling";"Larva";30;1
"Unit";"Zergling";"Larva";31;1
"Unit";"Zergling";"Larva";32;1
"Unit";"Zergling";"Larva";33;1
"Unit";"Overlord";"Larva";35;0
"Unit";"Zergling";"Larva";39;1
"Unit";"Zergling";"Larva";40;1
"Unit";"Zergling";"Larva";41;1
"Unit";"Zergling";"Larva";42;1
"Unit";"Queen";"Hatchery";44;2
"Unit";"Overlord";"Larva";48;0
"Building";"CreepTumorQueen";NA;48;0
"Building";"EvolutionChamber";NA;50;0
"Unit";"Zergling";"Larva";53;1
"Unit";"Zergling";"Larva";54;1
"Unit";"Zergling";"Larva";55;1
"Unit";"Zergling";"Larva";56;1
"Unit";"Overlord";"Larva";58;0
"Building";"SporeCrawler";NA;58;0
"Building";"SporeCrawler";NA;58;0
"Building";"SporeCrawler";NA;58;0
"Unit";"Queen";"Hatchery";66;2
"Building";"CreepTumorQueen";NA;73;0
"Unit";"Overlord";"Larva";73;0
"Unit";"Overlord";"Larva";73;0
"Unit";"Overlord";"Larva";74;0
"Building";"Extractor";NA;74;0
"Building";"BanelingNest";NA;75;0
"Building";"CreepTumor";NA;75;0
"Unit";"Overlord";"Larva";79;0
"Unit";"Queen";"Hatchery";79;2
"Unit";"Zergling";"Larva";86;1
"Unit";"Zergling";"Larva";87;1
"Building";"Hatchery";NA;88;0
"Unit";"Zergling";"Larva";88;1
"Unit";"Zergling";"Larva";89;1
"Unit";"Zergling";"Larva";90;1
"Unit";"Zergling";"Larva";91;1
"Unit";"Zergling";"Larva";92;1
"Unit";"Zergling";"Larva";93;1
"Unit";"Zergling";"Larva";94;1
"Unit";"Zergling";"Larva";95;1
"Unit";"Zergling";"Larva";96;1
"Unit";"Zergling";"Larva";97;1
"Unit";"Zergling";"Larva";98;1
"Unit";"Zergling";"Larva";99;1
"Unit";"Zergling";"Larva";100;1
"Unit";"Zergling";"Larva";101;1
"Unit";"Zergling";"Larva";102;1
"Unit";"Zergling";"Larva";103;1
"Building";"Extractor";NA;112;0
"Building";"Extractor";NA;112;0
"Building";"CreepTumorQueen";NA;112;0
"Unit";"Overlord";"Larva";113;0
"Building";"Extractor";NA;118;0
"Unit";"Overlord";"Larva";118;0
"Building";"CreepTumor";NA;118;0
"Unit";"Zergling";"Larva";118;1
"Unit";"Zergling";"Larva";119;1
"Unit";"Zergling";"Larva";120;1
"Unit";"Zergling";"Larva";121;1
"Unit";"Zergling";"Larva";122;1
"Unit";"Zergling";"Larva";123;1
"Unit";"Zergling";"Larva";124;1
"Unit";"Zergling";"Larva";125;1
"Unit";"Zergling";"Larva";126;1
"Unit";"Zergling";"Larva";127;1
"Building";"CreepTumorQueen";NA;128;0
"Unit";"Zergling";"Larva";130;1
"Unit";"Zergling";"Larva";131;1
"Unit";"Zergling";"Larva";132;1
"Unit";"Zergling";"Larva";133;1
"Unit";"Zergling";"Larva";134;1
"Unit";"Zergling";"Larva";135;1
"Building";"CreepTumorQueen";NA;136;0
"Unit";"Zergling";"Larva";136;1
"Unit";"Zergling";"Larva";137;1
"Unit";"Zergling";"Larva";138;1
"Unit";"Zergling";"Larva";139;1
"Unit";"Overlord";"Larva";140;0
"Unit";"Baneling";"Zergling";140;0
"Unit";"Baneling";"Zergling";140;0
"Unit";"Baneling";"Zergling";140;0
"Unit";"Baneling";"Zergling";140;0
"Unit";"Baneling";"Zergling";140;0
"Unit";"Baneling";"Zergling";140;0
"Building";"CreepTumor";NA;143;0
"Building";"HydraliskDen";NA;143;0
"Unit";"Zergling";"Larva";143;1
"Unit";"Zergling";"Larva";144;1
"Unit";"Zergling";"Larva";145;1
"Unit";"Zergling";"Larva";146;1
"Unit";"Zergling";"Larva";147;1
"Unit";"Zergling";"Larva";148;1
"Unit";"Zergling";"Larva";153;1
"Unit";"Zergling";"Larva";154;1
"Unit";"Zergling";"Larva";155;1
"Unit";"Zergling";"Larva";156;1
"Unit";"Zergling";"Larva";157;1
"Unit";"Zergling";"Larva";158;1
"Unit";"Zergling";"Larva";159;1
"Unit";"Zergling";"Larva";160;1
"Unit";"Zergling";"Larva";161;1
"Unit";"Zergling";"Larva";162;1
"Unit";"Zergling";"Larva";163;1
"Unit";"Zergling";"Larva";164;1
"Unit";"Zergling";"Larva";165;1
"Unit";"Zergling";"Larva";166;1
"Unit";"Zergling";"Larva";167;1
"Unit";"Zergling";"Larva";168;1
"Unit";"Zergling";"Larva";169;1
"Unit";"Zergling";"Larva";170;1
"Unit";"Zergling";"Larva";171;1
"Unit";"Zergling";"Larva";172;1
"Building";"CreepTumor";NA;176;0
"Building";"CreepTumor";NA;176;0
"Building";"CreepTumor";NA;176;0
"Building";"CreepTumor";NA;177;0
"Unit";"Hydralisk";"Larva";178;2
"Unit";"Hydralisk";"Larva";180;2
"Unit";"Hydralisk";"Larva";182;2
"Unit";"Hydralisk";"Larva";184;2
"Building";"CreepTumorQueen";NA;186;0
"Unit";"Hydralisk";"Larva";186;2
"Unit";"Hydralisk";"Larva";188;2
"Unit";"Hydralisk";"Larva";190;2
"Unit";"Hydralisk";"Larva";192;2
"Unit";"Zergling";"Larva";194;1
"Unit";"Zergling";"Larva";195;1
"Unit";"Hydralisk";"Larva";196;2
"Unit";"Hydralisk";"Larva";198;2
"Unit";"Zergling";"Larva";200;1
"Unit";"Zergling";"Larva";201;1
"Unit";"Zergling";"Larva";202;1
"Unit";"Zergling";"Larva";203;1
"Unit";"Hydralisk";"Larva";204;2
"Unit";"Hydralisk";"Larva";206;2
"Unit";"Zergling";"Larva";208;1
"Unit";"Zergling";"Larva";209;1
"Unit";"Zergling";"Larva";210;1
"Unit";"Zergling";"Larva";211;1
"Unit";"Overlord";"Larva";212;0
"Unit";"Overlord";"Larva";212;0
"Unit";"Overlord";"Larva";213;0
"Unit";"Overlord";"Larva";213;0
"Unit";"Overlord";"Larva";213;0
"Unit";"Overlord";"Larva";213;0
"Unit";"Overlord";"Larva";213;0
"Unit";"Overlord";"Larva";213;0
"Unit";"Overlord";"Larva";213;0
"Unit";"Hydralisk";"Larva";213;2
"Unit";"Hydralisk";"Larva";215;2
"Unit";"Hydralisk";"Larva";217;2
"Unit";"Zergling";"Larva";219;1
"Unit";"Zergling";"Larva";220;1
"Unit";"Zergling";"Larva";221;1
"Unit";"Zergling";"Larva";222;1
"Unit";"Zergling";"Larva";223;1
"Unit";"Zergling";"Larva";224;1
"Unit";"Zergling";"Larva";225;1
"Unit";"Zergling";"Larva";226;1
"Building";"CreepTumor";NA;227;0
"Building";"CreepTumorQueen";NA;227;0
"Unit";"Baneling";"Zergling";227;0
"Unit";"Baneling";"Zergling";227;0
"Unit";"Baneling";"Zergling";227;0
"Unit";"Baneling";"Zergling";227;0
"Unit";"Baneling";"Zergling";227;0
"Unit";"Baneling";"Zergling";227;0
"Unit";"Baneling";"Zergling";227;0
"Unit";"Baneling";"Zergling";227;0
"Unit";"Zergling";"Larva";227;1
"Unit";"Zergling";"Larva";228;1
"Unit";"Zergling";"Larva";229;1
"Unit";"Zergling";"Larva";230;1
"Unit";"Zergling";"Larva";231;1
"Unit";"Zergling";"Larva";232;1
"Unit";"Baneling";"Zergling";233;0
"Unit";"Baneling";"Zergling";233;0
"Unit";"Zergling";"Larva";233;1
"Unit";"Zergling";"Larva";234;1
"Unit";"Zergling";"Larva";235;1
"Unit";"Zergling";"Larva";236;1
"Unit";"Zergling";"Larva";237;1
"Unit";"Zergling";"Larva";238;1
"Unit";"Zergling";"Larva";239;1
"Unit";"Zergling";"Larva";240;1
"Unit";"Zergling";"Larva";241;1
"Unit";"Zergling";"Larva";242;1
"Unit";"Baneling";"Zergling";243;0
"Unit";"Baneling";"Zergling";243;0
"Unit";"Baneling";"Zergling";243;0
"Unit";"Zergling";"Larva";243;1
"Unit";"Zergling";"Larva";244;1
"Unit";"Zergling";"Larva";245;1
"Unit";"Zergling";"Larva";246;1
"Unit";"Zergling";"Larva";247;1
"Unit";"Zergling";"Larva";248;1
"Unit";"Baneling";"Zergling";249;0
"Unit";"Baneling";"Zergling";249;0
"Unit";"Zergling";"Larva";249;1
"Unit";"Zergling";"Larva";250;1
"Unit";"Zergling";"Larva";251;1
"Unit";"Zergling";"Larva";252;1
"Unit";"Zergling";"Larva";253;1
"Unit";"Zergling";"Larva";254;1
"Unit";"Zergling";"Larva";255;1
"Unit";"Zergling";"Larva";256;1
"Unit";"Zergling";"Larva";257;1
"Unit";"Zergling";"Larva";258;1
"Unit";"Hydralisk";"Larva";259;2
"Unit";"Hydralisk";"Larva";261;2
"Unit";"Zergling";"Larva";263;1
"Unit";"Zergling";"Larva";264;1
"Unit";"Baneling";"Zergling";265;0
"Unit";"Baneling";"Zergling";265;0
"Unit";"Baneling";"Zergling";265;0
"Unit";"Zergling";"Larva";265;1
"Unit";"Zergling";"Larva";266;1
"Unit";"Zergling";"Larva";267;1
"Unit";"Zergling";"Larva";268;1
"Unit";"Zergling";"Larva";269;1
"Unit";"Zergling";"Larva";270;1
"Unit";"Zergling";"Larva";271;1
"Unit";"Zergling";"Larva";272;1
"Unit";"Zergling";"Larva";273;1
"Unit";"Zergling";"Larva";274;1
"Unit";"Zergling";"Larva";275;1
"Unit";"Zergling";"Larva";276;1
"Unit";"Zergling";"Larva";277;1
"Unit";"Zergling";"Larva";278;1
"Unit";"Zergling";"Larva";279;1
"Unit";"Zergling";"Larva";280;1
"Unit";"Hydralisk";"Larva";281;2
"Unit";"Hydralisk";"Larva";283;2
"Unit";"Zergling";"Larva";285;1
"Unit";"Zergling";"Larva";286;1
"Unit";"Zergling";"Larva";287;1
"Unit";"Zergling";"Larva";288;1
"Unit";"Zergling";"Larva";289;1
"Unit";"Zergling";"Larva";290;1
"Unit";"Zergling";"Larva";291;1
"Unit";"Zergling";"Larva";292;1
"Unit";"Zergling";"Larva";293;1
"Unit";"Zergling";"Larva";294;1
"Unit";"Hydralisk";"Larva";295;2
"Unit";"Hydralisk";"Larva";297;2
"Unit";"Hydralisk";"Larva";299;2
"Unit";"Hydralisk";"Larva";301;2
"Unit";"Hydralisk";"Larva";303;2
"Unit";"Hydralisk";"Larva";305;2
"Unit";"Zergling";"Larva";307;1
"Unit";"Zergling";"Larva";308;1
"Unit";"Zergling";"Larva";309;1
"Unit";"Zergling";"Larva";310;1
"Unit";"Zergling";"Larva";311;1
"Unit";"Zergling";"Larva";312;1
"Unit";"Zergling";"Larva";313;1
"Unit";"Zergling";"Larva";314;1
"Unit";"Zergling";"Larva";315;1
"Unit";"Zergling";"Larva";316;1
"Unit";"Zergling";"Larva";317;1
"Unit";"Zergling";"Larva";318;1
"Unit";"Zergling";"Larva";319;1
"Unit";"Zergling";"Larva";320;1
"Building";"CreepTumor";NA;321;0
"Building";"CreepTumor";NA;321;0
"Building";"CreepTumor";NA;321;0
"Building";"CreepTumor";NA;321;0
"Building";"CreepTumor";NA;321;0
"Unit";"Baneling";"Zergling";321;0
"Unit";"Baneling";"Zergling";321;0
"Unit";"Baneling";"Zergling";321;0
"Unit";"Baneling";"Zergling";321;0
"Unit";"Baneling";"Zergling";321;0
"Unit";"Baneling";"Zergling";321;0
"Unit";"Baneling";"Zergling";321;0
"Unit";"Baneling";"Zergling";321;0
"Unit";"Baneling";"Zergling";321;0
"Unit";"Baneling";"Zergling";321;0
"Unit";"Baneling";"Zergling";321;0
"Unit";"Baneling";"Zergling";321;0
"Unit";"Zergling";"Larva";321;1
"Unit";"Zergling";"Larva";322;1
"Unit";"Zergling";"Larva";323;1
"Unit";"Zergling";"Larva";324;1
"Unit";"Zergling";"Larva";325;1
"Unit";"Zergling";"Larva";326;1
"Unit";"Zergling";"Larva";327;1
"Unit";"Zergling";"Larva";328;1
"Unit";"Zergling";"Larva";329;1
"Unit";"Zergling";"Larva";330;1
"Unit";"Zergling";"Larva";331;1
"Unit";"Zergling";"Larva";332;1
"Unit";"Zergling";"Larva";333;1
"Unit";"Zergling";"Larva";334;1
"Unit";"Zergling";"Larva";335;1
"Unit";"Zergling";"Larva";336;1
"Unit";"Zergling";"Larva";337;1
"Unit";"Zergling";"Larva";338;1
"Unit";"Zergling";"Larva";339;1
"Unit";"Zergling";"Larva";340;1
"Unit";"Zergling";"Larva";341;1
"Unit";"Zergling";"Larva";342;1
"Unit";"Zergling";"Larva";343;1
"Unit";"Zergling";"Larva";344;1
"Unit";"Zergling";"Larva";345;1
"Unit";"Zergling";"Larva";346;1
"Unit";"Zergling";"Larva";347;1
"Unit";"Zergling";"Larva";348;1
"Unit";"Zergling";"Larva";349;1
"Unit";"Zergling";"Larva";350;1
"Unit";"Zergling";"Larva";351;1
"Unit";"Zergling";"Larva";352;1
"Unit";"Zergling";"Larva";353;1
"Unit";"Zergling";"Larva";354;1
"Unit";"Baneling";"Zergling";355;0
"Unit";"Baneling";"Zergling";355;0
"Unit";"Baneling";"Zergling";355;0
"Unit";"Baneling";"Zergling";355;0
"Unit";"Baneling";"Zergling";355;0
"Unit";"Baneling";"Zergling";355;0
"Unit";"Baneling";"Zergling";355;0
"Unit";"Baneling";"Zergling";355;0
"Unit";"Baneling";"Zergling";355;0
"Unit";"Baneling";"Zergling";355;0
"Unit";"Baneling";"Zergling";355;0
"Unit";"Zergling";"Larva";355;1
"Unit";"Zergling";"Larva";356;1
"Unit";"Zergling";"Larva";357;1
"Unit";"Zergling";"Larva";358;1
"Building";"CreepTumor";NA;359;0
"Unit";"Baneling";"Zergling";359;0
"Unit";"Zergling";"Larva";359;1
"Unit";"Zergling";"Larva";360;1
"Unit";"Zergling";"Larva";361;1
"Unit";"Zergling";"Larva";362;1
"Unit";"Zergling";"Larva";363;1
"Unit";"Zergling";"Larva";364;1
"Unit";"Baneling";"Zergling";365;0
"Unit";"Baneling";"Zergling";365;0
"Unit";"Baneling";"Zergling";365;0
"Unit";"Baneling";"Zergling";365;0
"Unit";"Baneling";"Zergling";365;0
"Unit";"Baneling";"Zergling";365;0
"Upgrade";"SprayZerg";NA;365;0
"Upgrade";"SprayZerg";NA;365;0
"Upgrade";"SprayZerg";NA;365;0
"Upgrade";"SprayZerg";NA;365;0
"Upgrade";"zerglingmovementspeed";NA;365;0
"Upgrade";"SprayZerg";NA;365;0
"Upgrade";"ZergMeleeWeaponsLevel1";NA;365;0
"Upgrade";"SprayZerg";NA;365;0
"Upgrade";"EvolveMuscularAugments";NA;365;0
"Upgrade";"CentrificalHooks";NA;365;0
"Upgrade";"ZergMeleeWeaponsLevel2";NA;365;0
"Upgrade";"EvolveGroovedSpines";NA;365;0
