"type";"unit_name";"on_building";"total_supply_lag";"supply"
"Unit";"Overlord";"Larva";13;0
"Building";"Extractor";NA;17;0
"Building";"SpawningPool";NA;18;0
"Building";"Hatchery";NA;21;0
"Unit";"Queen";"Hatchery";22;2
"Unit";"Zergling";"Larva";24;1
"Unit";"Zergling";"Larva";25;1
"Unit";"Overlord";"Larva";26;0
"Unit";"Zergling";"Larva";26;1
"Unit";"Zergling";"Larva";27;1
"Unit";"Zergling";"Larva";28;1
"Unit";"Zergling";"Larva";29;1
"Unit";"Queen";"Hatchery";30;2
"Building";"Hatchery";NA;34;0
"Unit";"Zergling";"Larva";34;1
"Unit";"Zergling";"Larva";35;1
"Unit";"Zergling";"Larva";36;1
"Unit";"Zergling";"Larva";37;1
"Unit";"Zergling";"Larva";42;1
"Unit";"Zergling";"Larva";43;1
"Unit";"Zergling";"Larva";44;1
"Unit";"Zergling";"Larva";45;1
"Unit";"Zergling";"Larva";46;1
"Unit";"Zergling";"Larva";47;1
"Unit";"Overlord";"Larva";55;0
"Unit";"Overlord";"Larva";55;0
"Building";"Extractor";NA;67;0
"Unit";"Queen";"Hatchery";67;2
"Building";"Extractor";NA;69;0
"Unit";"Overlord";"Larva";69;0
"Building";"SporeCrawler";NA;71;0
"Unit";"Queen";"Hatchery";72;2
"Building";"SporeCrawler";NA;74;0
"Building";"SporeCrawler";NA;74;0
"Building";"HydraliskDen";NA;78;0
"Building";"CreepTumorQueen";NA;79;0
"Unit";"Overlord";"Larva";84;0
"Unit";"Overlord";"Larva";84;0
"Unit";"Overlord";"Larva";84;0
"Unit";"Overlord";"Larva";84;0
"Unit";"Overlord";"Larva";84;0
"Building";"CreepTumorQueen";NA;84;0
"Unit";"Overlord";"Larva";88;0
"Unit";"Overlord";"Larva";88;0
"Building";"CreepTumorQueen";NA;88;0
"Building";"Extractor";NA;88;0
"Unit";"Hydralisk";"Larva";88;2
"Unit";"Hydralisk";"Larva";90;2
"Unit";"Hydralisk";"Larva";92;2
"Unit";"Hydralisk";"Larva";94;2
"Unit";"Hydralisk";"Larva";96;2
"Unit";"Hydralisk";"Larva";98;2
"Unit";"Hydralisk";"Larva";100;2
"Unit";"Hydralisk";"Larva";102;2
"Unit";"Hydralisk";"Larva";104;2
"Unit";"Hydralisk";"Larva";106;2
"Building";"CreepTumorQueen";NA;108;0
"Unit";"Overlord";"Larva";108;0
"Unit";"Overlord";"Larva";108;0
"Building";"CreepTumor";NA;108;0
"Unit";"Hydralisk";"Larva";108;2
"Unit";"Hydralisk";"Larva";110;2
"Building";"CreepTumor";NA;112;0
"Unit";"Hydralisk";"Larva";112;2
"Unit";"Hydralisk";"Larva";114;2
"Unit";"Hydralisk";"Larva";116;2
"Building";"CreepTumorQueen";NA;118;0
"Unit";"Zergling";"Larva";118;1
"Unit";"Zergling";"Larva";119;1
"Unit";"Zergling";"Larva";120;1
"Unit";"Zergling";"Larva";121;1
"Building";"CreepTumorQueen";NA;122;0
"Unit";"Zergling";"Larva";123;1
"Unit";"Zergling";"Larva";124;1
"Unit";"Zergling";"Larva";125;1
"Unit";"Zergling";"Larva";126;1
"Building";"CreepTumor";NA;127;0
"Building";"EvolutionChamber";NA;128;0
"Unit";"Hydralisk";"Larva";128;2
"Unit";"Hydralisk";"Larva";130;2
"Unit";"Zergling";"Larva";132;1
"Unit";"Zergling";"Larva";133;1
"Building";"CreepTumor";NA;134;0
"Unit";"Hydralisk";"Larva";134;2
"Unit";"Zergling";"Larva";136;1
"Unit";"Zergling";"Larva";137;1
"Building";"CreepTumor";NA;138;0
"Unit";"Hydralisk";"Larva";138;2
"Unit";"Hydralisk";"Larva";140;2
"Unit";"Zergling";"Larva";142;1
"Unit";"Zergling";"Larva";143;1
"Unit";"Hydralisk";"Larva";144;2
"Unit";"Zergling";"Larva";146;1
"Unit";"Zergling";"Larva";147;1
"Building";"CreepTumor";NA;148;0
"Building";"CreepTumor";NA;148;0
"Unit";"Hydralisk";"Larva";148;2
"Unit";"Hydralisk";"Larva";150;2
"Unit";"Hydralisk";"Larva";152;2
"Unit";"Hydralisk";"Larva";154;2
"Unit";"Zergling";"Larva";156;1
"Unit";"Zergling";"Larva";157;1
"Unit";"Zergling";"Larva";158;1
"Unit";"Zergling";"Larva";159;1
"Unit";"Zergling";"Larva";160;1
"Unit";"Zergling";"Larva";161;1
"Unit";"Zergling";"Larva";162;1
"Unit";"Zergling";"Larva";163;1
"Unit";"Zergling";"Larva";164;1
"Unit";"Zergling";"Larva";165;1
"Unit";"Zergling";"Larva";166;1
"Unit";"Zergling";"Larva";167;1
"Unit";"Zergling";"Larva";168;1
"Unit";"Zergling";"Larva";169;1
"Unit";"Zergling";"Larva";170;1
"Unit";"Zergling";"Larva";171;1
"Unit";"Zergling";"Larva";172;1
"Unit";"Zergling";"Larva";173;1
"Unit";"Zergling";"Larva";174;1
"Unit";"Zergling";"Larva";175;1
"Unit";"Hydralisk";"Larva";176;2
"Unit";"Zergling";"Larva";178;1
"Unit";"Zergling";"Larva";179;1
"Building";"CreepTumor";NA;180;0
"Building";"CreepTumor";NA;180;0
"Building";"CreepTumor";NA;180;0
"Building";"CreepTumor";NA;180;0
"Unit";"Hydralisk";"Larva";180;2
"Unit";"Hydralisk";"Larva";182;2
"Unit";"Hydralisk";"Larva";184;2
"Unit";"Hydralisk";"Larva";186;2
"Unit";"Zergling";"Larva";188;1
"Unit";"Zergling";"Larva";189;1
"Unit";"Hydralisk";"Larva";190;2
"Unit";"Zergling";"Larva";192;1
"Unit";"Zergling";"Larva";193;1
"Unit";"Hydralisk";"Larva";194;2
"Unit";"Zergling";"Larva";196;1
"Unit";"Zergling";"Larva";197;1
"Building";"Extractor";NA;198;0
"Unit";"Hydralisk";"Larva";198;2
"Unit";"Zergling";"Larva";200;1
"Unit";"Zergling";"Larva";201;1
"Unit";"Hydralisk";"Larva";202;2
"Unit";"Hydralisk";"Larva";204;2
"Unit";"Zergling";"Larva";206;1
"Unit";"Zergling";"Larva";207;1
"Unit";"Zergling";"Larva";208;1
"Unit";"Zergling";"Larva";209;1
"Unit";"Zergling";"Larva";210;1
"Unit";"Zergling";"Larva";211;1
"Unit";"Zergling";"Larva";212;1
"Unit";"Zergling";"Larva";213;1
"Unit";"Hydralisk";"Larva";214;2
"Building";"CreepTumor";NA;218;0
"Building";"CreepTumor";NA;218;0
"Building";"CreepTumor";NA;218;0
"Upgrade";"SprayZerg";NA;221;0
"Upgrade";"SprayZerg";NA;221;0
"Upgrade";"SprayZerg";NA;221;0
"Upgrade";"zerglingmovementspeed";NA;221;0
"Upgrade";"SprayZerg";NA;221;0
"Upgrade";"EvolveMuscularAugments";NA;221;0
