"type";"unit_name";"on_building";"total_supply";"supply"
"Unit";"Overlord";"Larva";12;0
"Building";"Extractor";NA;17;0
"Unit";"Overlord";"Larva";22;0
"Building";"SpawningPool";NA;19;0
"Building";"Hatchery";NA;17;0
"Unit";"Zergling";"Larva";23;1
"Unit";"Zergling";"Larva";23;1
"Unit";"Zergling";"Larva";23;1
"Unit";"Zergling";"Larva";23;1
"Unit";"Zergling";"Larva";23;1
"Unit";"Zergling";"Larva";23;1
"Building";"SpineCrawler";NA;23;0
"Unit";"Zergling";"Larva";29;1
"Unit";"Zergling";"Larva";29;1
"Unit";"Zergling";"Larva";29;1
"Unit";"Zergling";"Larva";29;1
"Unit";"Zergling";"Larva";29;1
"Unit";"Zergling";"Larva";29;1
"Unit";"Zergling";"Larva";31;1
"Unit";"Zergling";"Larva";31;1
"Unit";"Zergling";"Larva";31;1
"Unit";"Zergling";"Larva";31;1
"Unit";"Queen";"Hatchery";42;2
"Unit";"Queen";"Hatchery";44;2
"Unit";"Overlord";"Larva";53;0
"Unit";"Overlord";"Larva";57;0
"Building";"CreepTumorQueen";NA;57;0
"Unit";"Queen";"Hatchery";57;2
"Building";"SpineCrawler";NA;57;0
"Unit";"Zergling";"Larva";62;1
"Unit";"Zergling";"Larva";62;1
"Unit";"Zergling";"Larva";62;1
"Unit";"Zergling";"Larva";62;1
"Building";"CreepTumor";NA;62;0
"Building";"RoachWarren";NA;57;0
"Building";"CreepTumorQueen";NA;73;0
"Building";"Extractor";NA;74;0
"Building";"Extractor";NA;74;0
"Building";"SporeCrawler";NA;74;0
"Unit";"Zergling";"Larva";78;1
"Unit";"Zergling";"Larva";78;1
"Unit";"Zergling";"Larva";78;1
"Unit";"Zergling";"Larva";78;1
"Unit";"Zergling";"Larva";78;1
"Unit";"Zergling";"Larva";78;1
"Unit";"Zergling";"Larva";78;1
"Unit";"Zergling";"Larva";78;1
"Unit";"Zergling";"Larva";78;1
"Unit";"Zergling";"Larva";78;1
"Building";"CreepTumor";NA;90;0
"Building";"CreepTumor";NA;90;0
"Unit";"Overlord";"Larva";90;0
"Unit";"Overlord";"Larva";90;0
"Unit";"Overlord";"Larva";90;0
"Unit";"Overlord";"Larva";90;0
"Building";"CreepTumorQueen";NA;90;0
"Building";"Hatchery";NA;71;0
"Unit";"Overlord";"Larva";92;0
"Unit";"Overlord";"Larva";92;0
"Building";"HydraliskDen";NA;92;0
"Building";"CreepTumor";NA;92;0
"Building";"CreepTumor";NA;92;0
"Building";"CreepTumor";NA;92;0
"Building";"Extractor";NA;92;0
"Unit";"Hydralisk";"Larva";100;2
"Unit";"Hydralisk";"Larva";100;2
"Unit";"Hydralisk";"Larva";100;2
"Unit";"Hydralisk";"Larva";100;2
"Unit";"Hydralisk";"Larva";100;2
"Building";"CreepTumor";NA;100;0
"Unit";"Hydralisk";"Larva";100;2
"Unit";"Hydralisk";"Larva";100;2
"Building";"CreepTumor";NA;100;0
"Building";"CreepTumor";NA;100;0
"Unit";"Hydralisk";"Larva";100;2
"Unit";"Hydralisk";"Larva";100;2
"Unit";"Hydralisk";"Larva";100;2
"Unit";"Hydralisk";"Larva";100;2
"Unit";"Overlord";"Larva";114;0
"Unit";"Hydralisk";"Larva";100;2
"Unit";"Hydralisk";"Larva";100;2
"Unit";"Hydralisk";"Larva";114;2
"Unit";"Hydralisk";"Larva";118;2
"Unit";"Hydralisk";"Larva";118;2
"Unit";"Hydralisk";"Larva";118;2
"Unit";"Overlord";"Larva";122;0
"Unit";"Overlord";"Larva";122;0
"Upgrade";"EvolveGroovedSpines";"HydraliskDen";100;0
"Unit";"Hydralisk";"Larva";126;2
"Unit";"Hydralisk";"Larva";126;2
"Unit";"Hydralisk";"Larva";128;2
"Unit";"Zergling";"Larva";134;1
"Unit";"Zergling";"Larva";134;1
"Unit";"Zergling";"Larva";134;1
"Unit";"Zergling";"Larva";134;1
"Unit";"Zergling";"Larva";134;1
"Unit";"Zergling";"Larva";134;1
"Unit";"Zergling";"Larva";134;1
"Unit";"Zergling";"Larva";134;1
"Unit";"Zergling";"Larva";134;1
"Unit";"Zergling";"Larva";134;1
"Unit";"Hydralisk";"Larva";134;2
"Unit";"Hydralisk";"Larva";134;2
"Unit";"Zergling";"Larva";154;1
"Unit";"Zergling";"Larva";154;1
"Unit";"Zergling";"Larva";154;1
"Unit";"Zergling";"Larva";154;1
"Unit";"Zergling";"Larva";154;1
"Unit";"Zergling";"Larva";154;1
"Unit";"Zergling";"Larva";154;1
"Unit";"Zergling";"Larva";154;1
"Unit";"Zergling";"Larva";154;1
"Unit";"Zergling";"Larva";154;1
"Unit";"Hydralisk";"Larva";154;2
"Unit";"Hydralisk";"Larva";154;2
"Unit";"Hydralisk";"Larva";154;2
"Unit";"Hydralisk";"Larva";154;2
"Unit";"Hydralisk";"Larva";154;2
"Unit";"Hydralisk";"Larva";154;2
"Unit";"Hydralisk";"Larva";154;2
"Unit";"Hydralisk";"Larva";154;2
"Unit";"Hydralisk";"Larva";154;2
"Unit";"Hydralisk";"Larva";154;2
"Unit";"Hydralisk";"Larva";154;2
"Upgrade";"EvolveMuscularAugments";"HydraliskDen";154;0
"Unit";"Hydralisk";"Larva";178;2
"Unit";"Zergling";"Larva";178;1
"Unit";"Zergling";"Larva";178;1
"Unit";"Zergling";"Larva";178;1
"Unit";"Zergling";"Larva";178;1
"Unit";"Zergling";"Larva";178;1
"Unit";"Zergling";"Larva";178;1
"Building";"EvolutionChamber";NA;186;0
"Unit";"Zergling";"Larva";202;1
"Unit";"Zergling";"Larva";202;1
"Unit";"Zergling";"Larva";202;1
"Unit";"Zergling";"Larva";202;1
"Unit";"Zergling";"Larva";202;1
"Unit";"Zergling";"Larva";202;1
"Unit";"Hydralisk";"Larva";202;2
"Unit";"Hydralisk";"Larva";202;2
"Unit";"Hydralisk";"Larva";202;2
"Unit";"Hydralisk";"Larva";202;2
"Unit";"Zergling";"Larva";202;1
"Unit";"Zergling";"Larva";202;1
"Unit";"Zergling";"Larva";202;1
"Unit";"Zergling";"Larva";202;1
"Unit";"Zergling";"Larva";202;1
"Unit";"Zergling";"Larva";202;1
"Unit";"Hydralisk";"Larva";202;2
"Unit";"Hydralisk";"Larva";202;2
"Unit";"Hydralisk";"Larva";202;2
"Unit";"Hydralisk";"Larva";202;2
"Unit";"Hydralisk";"Larva";202;2
"Unit";"Hydralisk";"Larva";202;2
"Unit";"Hydralisk";"Larva";202;2
"Building";"SporeCrawler";NA;216;0
