"type";"unit_name";"on_building";"total_supply";"supply"
"Unit";"Overlord";"Larva";12;0
"Building";"Extractor";NA;17;0
"Unit";"Overlord";"Larva";21;0
"Building";"SpawningPool";NA;19;0
"Building";"Hatchery";NA;17;0
"Unit";"Zergling";"Larva";23;1
"Unit";"Zergling";"Larva";23;1
"Unit";"Zergling";"Larva";23;1
"Unit";"Zergling";"Larva";23;1
"Unit";"Queen";"Hatchery";23;2
"Unit";"Queen";"Hatchery";23;2
"Unit";"Overlord";"Larva";38;0
"Building";"CreepTumorQueen";NA;40;0
"Unit";"Overlord";"Larva";40;0
"Unit";"Queen";"Hatchery";39;2
"Unit";"Zergling";"Larva";40;1
"Unit";"Zergling";"Larva";40;1
"Building";"SporeCrawler";NA;40;0
"Building";"Hatchery";NA;36;0
"Building";"SporeCrawler";NA;46;0
"Building";"EvolutionChamber";NA;50;0
"Building";"CreepTumor";NA;56;0
"Unit";"Queen";"Hatchery";52;2
"Unit";"Overlord";"Larva";61;0
"Unit";"Overlord";"Larva";65;0
"Unit";"Overlord";"Larva";65;0
"Building";"SporeCrawler";NA;65;0
"Building";"CreepTumorQueen";NA;69;0
"Building";"CreepTumorQueen";NA;69;0
"Unit";"Overlord";"Larva";69;0
"Building";"CreepTumor";NA;69;0
"Building";"Extractor";NA;69;0
"Building";"Extractor";NA;69;0
"Unit";"Overlord";"Larva";71;0
"Unit";"Overlord";"Larva";71;0
"Building";"RoachWarren";NA;69;0
"Building";"CreepTumor";NA;77;0
"Building";"CreepTumor";NA;77;0
"Building";"CreepTumorQueen";NA;77;0
"Unit";"Overlord";"Larva";77;0
"Unit";"Overlord";"Larva";77;0
"Unit";"Roach";"Larva";77;2
"Unit";"Roach";"Larva";77;2
"Unit";"Roach";"Larva";77;2
"Unit";"Roach";"Larva";77;2
"Unit";"Roach";"Larva";77;2
"Unit";"Roach";"Larva";77;2
"Unit";"Roach";"Larva";77;2
"Unit";"Roach";"Larva";78;2
"Unit";"Roach";"Larva";78;2
"Unit";"Roach";"Larva";78;2
"Unit";"Roach";"Larva";78;2
"Unit";"Roach";"Larva";78;2
"Unit";"Zergling";"Larva";94;1
"Unit";"Zergling";"Larva";94;1
"Unit";"Zergling";"Larva";94;1
"Unit";"Zergling";"Larva";94;1
"Unit";"Roach";"Larva";94;2
"Unit";"Roach";"Larva";94;2
"Building";"CreepTumor";NA;102;0
"Unit";"Overlord";"Larva";102;0
"Unit";"Overlord";"Larva";102;0
"Unit";"Overlord";"Larva";102;0
"Unit";"Overlord";"Larva";102;0
"Building";"CreepTumor";NA;110;0
"Unit";"Roach";"Larva";110;2
"Unit";"Roach";"Larva";110;2
"Upgrade";"ZergMissileWeaponsLevel1";"EvolutionChamber";77;0
"Building";"CreepTumor";NA;116;0
"Unit";"Overlord";"Larva";116;0
"Unit";"Roach";"Larva";116;2
"Unit";"Roach";"Larva";116;2
"Unit";"Overlord";"Larva";120;0
"Building";"Extractor";NA;120;0
"Unit";"Roach";"Larva";120;2
"Unit";"Roach";"Larva";120;2
"Unit";"Roach";"Larva";120;2
"Unit";"Roach";"Larva";128;2
"Unit";"Roach";"Larva";128;2
"Unit";"Roach";"Larva";128;2
"Unit";"Roach";"Larva";128;2
"Unit";"Roach";"Larva";128;2
"Unit";"Roach";"Larva";128;2
"Unit";"Roach";"Larva";128;2
"Unit";"Roach";"Larva";128;2
"Unit";"Roach";"Larva";130;2
"Unit";"Roach";"Larva";132;2
"Unit";"Roach";"Larva";134;2
"Unit";"Zergling";"Larva";134;1
"Unit";"Zergling";"Larva";134;1
"Unit";"Zergling";"Larva";134;1
"Unit";"Zergling";"Larva";134;1
"Unit";"Zergling";"Larva";134;1
"Unit";"Zergling";"Larva";134;1
"Unit";"Zergling";"Larva";134;1
"Unit";"Zergling";"Larva";134;1
"Unit";"Zergling";"Larva";134;1
"Unit";"Zergling";"Larva";134;1
"Building";"CreepTumor";NA;148;0
"Upgrade";"GlialReconstitution";"RoachWarren";120;0
"Unit";"Zergling";"Larva";148;1
"Unit";"Zergling";"Larva";148;1
"Building";"Extractor";NA;148;0
"Unit";"Zergling";"Larva";156;1
"Unit";"Zergling";"Larva";156;1
"Unit";"Zergling";"Larva";156;1
"Unit";"Zergling";"Larva";156;1
"Building";"Hatchery";NA;116;0
"Unit";"Overlord";"Larva";170;0
"Unit";"Overlord";"Larva";170;0
"Unit";"Overlord";"Larva";170;0
"Building";"Extractor";NA;176;0
"Building";"HydraliskDen";NA;176;0
"Unit";"Roach";"Larva";177;2
"Unit";"Roach";"Larva";177;2
"Unit";"Roach";"Larva";177;2
"Unit";"Roach";"Larva";177;2
"Unit";"Roach";"Larva";177;2
"Unit";"Roach";"Larva";177;2
"Unit";"Roach";"Larva";177;2
"Unit";"Roach";"Larva";177;2
"Unit";"Roach";"Larva";177;2
"Unit";"Roach";"Larva";177;2
"Unit";"Roach";"Larva";177;2
"Unit";"Roach";"Larva";177;2
"Unit";"Zergling";"Larva";178;1
"Unit";"Zergling";"Larva";178;1
"Unit";"Zergling";"Larva";178;1
"Unit";"Zergling";"Larva";178;1
"Unit";"Zergling";"Larva";193;1
"Unit";"Zergling";"Larva";193;1
"Unit";"Zergling";"Larva";201;1
"Unit";"Zergling";"Larva";201;1
"Unit";"Zergling";"Larva";205;1
"Unit";"Zergling";"Larva";205;1
"Unit";"Zergling";"Larva";205;1
"Unit";"Zergling";"Larva";205;1
"Unit";"Roach";"Larva";205;2
"Unit";"Roach";"Larva";205;2
"Unit";"Roach";"Larva";205;2
"Unit";"Zergling";"Larva";209;1
"Unit";"Zergling";"Larva";209;1
"Unit";"Zergling";"Larva";209;1
"Unit";"Zergling";"Larva";209;1
"Unit";"Zergling";"Larva";209;1
"Unit";"Zergling";"Larva";209;1
"Unit";"Roach";"Larva";209;2
"Unit";"Roach";"Larva";209;2
"Unit";"Roach";"Larva";209;2
"Unit";"Roach";"Larva";209;2
"Unit";"Roach";"Larva";209;2
"Unit";"Overlord";"Larva";223;0
"Unit";"Zergling";"Larva";229;1
"Unit";"Zergling";"Larva";229;1
"Unit";"Hydralisk";"Larva";223;2
"Unit";"Hydralisk";"Larva";227;2
"Unit";"Hydralisk";"Larva";229;2
"Unit";"Hydralisk";"Larva";229;2
"Unit";"Zergling";"Larva";239;1
"Unit";"Zergling";"Larva";239;1
"Unit";"Zergling";"Larva";239;1
"Unit";"Zergling";"Larva";239;1
"Unit";"Zergling";"Larva";239;1
"Unit";"Zergling";"Larva";239;1
"Building";"CreepTumor";NA;241;0
"Unit";"Hydralisk";"Larva";239;2
"Unit";"Zergling";"Larva";249;1
"Unit";"Zergling";"Larva";249;1
"Unit";"Hydralisk";"Larva";241;2
"Upgrade";"ZergMissileWeaponsLevel2";"EvolutionChamber";176;0
"Unit";"Hydralisk";"Larva";249;2
"Unit";"Hydralisk";"Larva";249;2
"Unit";"Hydralisk";"Larva";249;2
"Unit";"Hydralisk";"Larva";249;2
"Unit";"Hydralisk";"Larva";253;2
"Unit";"Hydralisk";"Larva";253;2
"Unit";"Hydralisk";"Larva";255;2
"Unit";"Hydralisk";"Larva";255;2
"Unit";"Zergling";"Larva";255;1
"Unit";"Zergling";"Larva";255;1
"Unit";"Zergling";"Larva";255;1
"Unit";"Zergling";"Larva";255;1
"Unit";"Zergling";"Larva";261;1
"Unit";"Zergling";"Larva";261;1
"Unit";"Hydralisk";"Larva";257;2
"Unit";"Hydralisk";"Larva";259;2
"Unit";"Zergling";"Larva";273;1
"Unit";"Zergling";"Larva";273;1
"Unit";"Hydralisk";"Larva";261;2
"Unit";"Hydralisk";"Larva";261;2
"Unit";"Hydralisk";"Larva";273;2
"Unit";"Hydralisk";"Larva";273;2
"Unit";"Hydralisk";"Larva";273;2
"Building";"Hatchery";NA;239;0
"Unit";"Hydralisk";"Larva";281;2
"Unit";"Zergling";"Larva";287;1
"Unit";"Zergling";"Larva";287;1
"Unit";"Zergling";"Larva";287;1
"Unit";"Zergling";"Larva";287;1
"Upgrade";"EvolveGroovedSpines";"HydraliskDen";255;0
"Unit";"Hydralisk";"Larva";283;2
"Unit";"Hydralisk";"Larva";283;2
"Unit";"Zergling";"Larva";293;1
"Unit";"Zergling";"Larva";293;1
"Unit";"Zergling";"Larva";293;1
"Unit";"Zergling";"Larva";293;1
"Unit";"Hydralisk";"Larva";293;2
"Unit";"Hydralisk";"Larva";293;2
"Unit";"Zergling";"Larva";297;1
"Unit";"Zergling";"Larva";297;1
"Unit";"Hydralisk";"Larva";299;2
"Unit";"Hydralisk";"Larva";305;2
"Unit";"Hydralisk";"Larva";305;2
"Unit";"Hydralisk";"Larva";329;2
"Unit";"Hydralisk";"Larva";329;2
"Unit";"Hydralisk";"Larva";329;2
"Unit";"Hydralisk";"Larva";332;2
"Unit";"Hydralisk";"Larva";332;2
"Unit";"Hydralisk";"Larva";332;2
"Unit";"Zergling";"Larva";336;1
"Unit";"Zergling";"Larva";336;1
"Unit";"Zergling";"Larva";336;1
"Unit";"Zergling";"Larva";336;1
"Unit";"Zergling";"Larva";336;1
"Unit";"Zergling";"Larva";336;1
"Unit";"Zergling";"Larva";336;1
"Unit";"Zergling";"Larva";336;1
"Unit";"Zergling";"Larva";340;1
"Unit";"Zergling";"Larva";340;1
"Unit";"Zergling";"Larva";340;1
"Unit";"Zergling";"Larva";340;1
"Unit";"Zergling";"Larva";342;1
"Unit";"Zergling";"Larva";342;1
"Unit";"Zergling";"Larva";342;1
"Unit";"Zergling";"Larva";342;1
"Unit";"Zergling";"Larva";342;1
"Unit";"Zergling";"Larva";342;1
"Unit";"Zergling";"Larva";342;1
"Unit";"Zergling";"Larva";342;1
"Unit";"Zergling";"Larva";342;1
"Unit";"Zergling";"Larva";342;1
"Unit";"Hydralisk";"Larva";342;2
"Unit";"Hydralisk";"Larva";342;2
"Upgrade";"EvolveMuscularAugments";"HydraliskDen";332;0
"Unit";"Zergling";"Larva";366;1
"Unit";"Zergling";"Larva";366;1
"Unit";"Zergling";"Larva";366;1
"Unit";"Zergling";"Larva";366;1
"Unit";"Zergling";"Larva";366;1
"Unit";"Zergling";"Larva";366;1
"Unit";"Zergling";"Larva";366;1
"Unit";"Zergling";"Larva";366;1
"Unit";"Zergling";"Larva";367;1
"Unit";"Zergling";"Larva";367;1
"Unit";"Zergling";"Larva";367;1
"Unit";"Zergling";"Larva";367;1
"Unit";"Zergling";"Larva";367;1
"Unit";"Zergling";"Larva";367;1
"Unit";"Zergling";"Larva";379;1
"Unit";"Zergling";"Larva";379;1
"Unit";"Zergling";"Larva";379;1
"Unit";"Zergling";"Larva";379;1
"Unit";"Zergling";"Larva";379;1
"Unit";"Zergling";"Larva";379;1
"Unit";"Zergling";"Larva";379;1
"Unit";"Zergling";"Larva";379;1
"Building";"BanelingNest";NA;348;0
"Unit";"Zergling";"Larva";393;1
"Unit";"Zergling";"Larva";393;1
"Unit";"Zergling";"Larva";393;1
"Unit";"Zergling";"Larva";393;1
"Unit";"Zergling";"Larva";393;1
"Unit";"Zergling";"Larva";393;1
"Upgrade";"ZergMeleeWeaponsLevel1";"EvolutionChamber";333;0
"Unit";"Hydralisk";"Larva";401;2
"Unit";"Hydralisk";"Larva";401;2
"Unit";"Hydralisk";"Larva";401;2
"Unit";"Zergling";"Larva";401;1
"Unit";"Zergling";"Larva";401;1
"Unit";"Zergling";"Larva";401;1
"Unit";"Zergling";"Larva";401;1
"Unit";"Zergling";"Larva";401;1
"Unit";"Zergling";"Larva";401;1
"Unit";"Zergling";"Larva";401;1
"Unit";"Zergling";"Larva";401;1
"Unit";"Hydralisk";"Larva";401;2
"Unit";"Hydralisk";"Larva";401;2
"Unit";"Hydralisk";"Larva";401;2
"Unit";"Hydralisk";"Larva";401;2
"Unit";"Hydralisk";"Larva";401;2
"Building";"CreepTumorQueen";NA;421;0
"Unit";"Hydralisk";"Larva";407;2
"Unit";"Hydralisk";"Larva";407;2
"Unit";"Hydralisk";"Larva";407;2
"Building";"CreepTumorQueen";NA;421;0
"Building";"CreepTumorQueen";NA;431;0
"Building";"CreepTumorQueen";NA;437;0
"Unit";"Hydralisk";"Larva";421;2
"Unit";"Hydralisk";"Larva";421;2
"Unit";"Hydralisk";"Larva";421;2
"Unit";"Hydralisk";"Larva";421;2
"Building";"CreepTumorQueen";NA;437;0
"Unit";"Hydralisk";"Larva";433;2
"Unit";"Hydralisk";"Larva";435;2
"Building";"CreepTumor";NA;449;0
"Building";"CreepTumor";NA;449;0
"Unit";"Hydralisk";"Larva";441;2
"Unit";"Hydralisk";"Larva";441;2
"Unit";"Hydralisk";"Larva";445;2
"Unit";"Zergling";"Larva";445;1
"Unit";"Zergling";"Larva";445;1
"Unit";"Zergling";"Larva";445;1
"Unit";"Zergling";"Larva";445;1
"Unit";"Baneling";"Zergling";449;0
"Unit";"Baneling";"Zergling";449;0
"Unit";"Baneling";"Zergling";449;0
"Unit";"Baneling";"Zergling";449;0
"Unit";"Baneling";"Zergling";449;0
"Unit";"Zergling";"Larva";459;1
"Unit";"Zergling";"Larva";459;1
"Unit";"Zergling";"Larva";459;1
"Unit";"Zergling";"Larva";459;1
"Unit";"Zergling";"Larva";459;1
"Unit";"Zergling";"Larva";459;1
"Unit";"Zergling";"Larva";459;1
"Unit";"Zergling";"Larva";459;1
"Unit";"Zergling";"Larva";459;1
"Unit";"Zergling";"Larva";459;1
"Unit";"Zergling";"Larva";459;1
"Unit";"Zergling";"Larva";459;1
"Unit";"Zergling";"Larva";459;1
"Unit";"Zergling";"Larva";459;1
"Unit";"Zergling";"Larva";459;1
"Unit";"Zergling";"Larva";459;1
"Unit";"Zergling";"Larva";459;1
"Unit";"Zergling";"Larva";459;1
"Unit";"Zergling";"Larva";459;1
"Unit";"Zergling";"Larva";459;1
"Unit";"Hydralisk";"Larva";459;2
"Building";"Hatchery";NA;431;0
"Unit";"Hydralisk";"Larva";459;2
"Unit";"Hydralisk";"Larva";459;2
"Unit";"Baneling";"Zergling";485;0
"Unit";"Baneling";"Zergling";485;0
"Unit";"Baneling";"Zergling";485;0
"Unit";"Baneling";"Zergling";485;0
"Unit";"Baneling";"Zergling";485;0
"Building";"Hatchery";NA;449;0
"Unit";"Zergling";"Larva";485;1
"Unit";"Zergling";"Larva";485;1
"Unit";"Zergling";"Larva";485;1
"Unit";"Zergling";"Larva";485;1
"Unit";"Zergling";"Larva";485;1
"Unit";"Zergling";"Larva";485;1
"Unit";"Zergling";"Larva";485;1
"Unit";"Zergling";"Larva";485;1
"Unit";"Zergling";"Larva";485;1
"Unit";"Zergling";"Larva";485;1
"Unit";"Zergling";"Larva";485;1
"Unit";"Zergling";"Larva";485;1
"Unit";"Zergling";"Larva";485;1
"Unit";"Zergling";"Larva";485;1
"Unit";"Zergling";"Larva";485;1
"Unit";"Zergling";"Larva";485;1
"Unit";"Zergling";"Larva";485;1
"Unit";"Zergling";"Larva";485;1
"Unit";"Zergling";"Larva";485;1
"Unit";"Zergling";"Larva";485;1
"Unit";"Zergling";"Larva";485;1
"Unit";"Zergling";"Larva";485;1
"Unit";"Zergling";"Larva";485;1
"Unit";"Zergling";"Larva";485;1
"Unit";"Zergling";"Larva";485;1
"Unit";"Zergling";"Larva";485;1
"Unit";"Zergling";"Larva";485;1
"Unit";"Zergling";"Larva";485;1
"Unit";"Zergling";"Larva";485;1
"Unit";"Zergling";"Larva";485;1
"Unit";"Zergling";"Larva";485;1
"Unit";"Zergling";"Larva";485;1
"Unit";"Zergling";"Larva";485;1
"Unit";"Zergling";"Larva";485;1
"Unit";"Baneling";"Zergling";485;0
"Unit";"Baneling";"Zergling";485;0
"Unit";"Baneling";"Zergling";485;0
"Unit";"Baneling";"Zergling";485;0
"Unit";"Baneling";"Zergling";485;0
"Unit";"Baneling";"Zergling";485;0
"Unit";"Baneling";"Zergling";485;0
"Unit";"Baneling";"Zergling";485;0
"Unit";"Baneling";"Zergling";485;0
"Unit";"Baneling";"Zergling";485;0
"Unit";"Baneling";"Zergling";485;0
"Unit";"Baneling";"Zergling";485;0
"Unit";"Baneling";"Zergling";485;0
"Unit";"Baneling";"Zergling";485;0
"Unit";"Baneling";"Zergling";485;0
"Unit";"Baneling";"Zergling";485;0
"Unit";"Baneling";"Zergling";485;0
"Unit";"Baneling";"Zergling";485;0
"Building";"CreepTumor";NA;487;0
"Unit";"Queen";"Hatchery";485;2
"Building";"CreepTumor";NA;529;0
"Building";"Extractor";NA;524;0
"Unit";"Baneling";"Zergling";526;0
"Unit";"Baneling";"Zergling";526;0
"Unit";"Baneling";"Zergling";526;0
"Unit";"Baneling";"Zergling";526;0
"Unit";"Baneling";"Zergling";526;0
"Unit";"Baneling";"Zergling";526;0
"Unit";"Zergling";"Larva";524;1
"Unit";"Zergling";"Larva";524;1
"Unit";"Baneling";"Zergling";526;0
"Unit";"Baneling";"Zergling";526;0
"Unit";"Baneling";"Zergling";526;0
"Unit";"Baneling";"Zergling";526;0
"Unit";"Baneling";"Zergling";526;0
"Unit";"Baneling";"Zergling";526;0
"Unit";"Baneling";"Zergling";526;0
"Unit";"Baneling";"Zergling";526;0
"Unit";"Baneling";"Zergling";526;0
"Unit";"Zergling";"Larva";524;1
"Unit";"Zergling";"Larva";524;1
"Unit";"Baneling";"Zergling";526;0
"Unit";"Zergling";"Larva";524;1
"Unit";"Zergling";"Larva";524;1
"Unit";"Zergling";"Larva";524;1
"Unit";"Zergling";"Larva";524;1
"Unit";"Zergling";"Larva";524;1
"Unit";"Zergling";"Larva";524;1
"Unit";"Zergling";"Larva";524;1
"Unit";"Zergling";"Larva";524;1
"Unit";"Zergling";"Larva";524;1
"Unit";"Zergling";"Larva";524;1
"Unit";"Baneling";"Zergling";526;0
"Unit";"Zergling";"Larva";524;1
"Unit";"Zergling";"Larva";524;1
"Unit";"Zergling";"Larva";524;1
"Unit";"Zergling";"Larva";524;1
"Unit";"Overlord";"Larva";529;0
"Unit";"Overlord";"Larva";529;0
"Unit";"Overlord";"Larva";547;0
"Unit";"Overlord";"Larva";547;0
"Upgrade";"ZergMeleeWeaponsLevel2";"EvolutionChamber";459;0
"Unit";"Hydralisk";"Larva";547;2
"Unit";"Hydralisk";"Larva";549;2
"Unit";"Hydralisk";"Larva";549;2
"Unit";"Hydralisk";"Larva";549;2
"Unit";"Hydralisk";"Larva";549;2
"Unit";"Hydralisk";"Larva";549;2
"Unit";"Hydralisk";"Larva";549;2
"Unit";"Hydralisk";"Larva";549;2
"Unit";"Hydralisk";"Larva";549;2
"Unit";"Hydralisk";"Larva";549;2
"Unit";"Hydralisk";"Larva";549;2
"Unit";"Hydralisk";"Larva";549;2
"Unit";"Hydralisk";"Larva";549;2
"Unit";"Hydralisk";"Larva";549;2
"Unit";"Hydralisk";"Larva";549;2
"Unit";"Hydralisk";"Larva";549;2
"Unit";"Hydralisk";"Larva";549;2
"Unit";"Zergling";"Larva";549;1
"Unit";"Zergling";"Larva";549;1
"Unit";"Zergling";"Larva";549;1
"Unit";"Zergling";"Larva";549;1
"Unit";"Zergling";"Larva";549;1
"Unit";"Zergling";"Larva";549;1
"Unit";"Zergling";"Larva";549;1
"Unit";"Zergling";"Larva";549;1
"Unit";"Zergling";"Larva";549;1
"Unit";"Zergling";"Larva";549;1
"Unit";"Zergling";"Larva";549;1
"Unit";"Zergling";"Larva";549;1
"Unit";"Zergling";"Larva";549;1
"Unit";"Zergling";"Larva";549;1
"Unit";"Zergling";"Larva";549;1
"Unit";"Zergling";"Larva";549;1
"Unit";"Zergling";"Larva";549;1
"Unit";"Zergling";"Larva";549;1
"Unit";"Zergling";"Larva";549;1
"Unit";"Zergling";"Larva";549;1
"Unit";"Zergling";"Larva";549;1
"Unit";"Zergling";"Larva";549;1
"Unit";"Zergling";"Larva";549;1
"Unit";"Zergling";"Larva";549;1
"Unit";"Zergling";"Larva";549;1
"Unit";"Zergling";"Larva";549;1
"Unit";"Zergling";"Larva";551;1
"Unit";"Zergling";"Larva";551;1
"Unit";"Zergling";"Larva";551;1
"Unit";"Zergling";"Larva";551;1
"Unit";"Zergling";"Larva";593;1
"Unit";"Zergling";"Larva";593;1
"Unit";"Zergling";"Larva";593;1
"Unit";"Zergling";"Larva";593;1
"Unit";"Zergling";"Larva";593;1
"Unit";"Zergling";"Larva";593;1
"Unit";"Zergling";"Larva";593;1
"Unit";"Zergling";"Larva";593;1
"Unit";"Zergling";"Larva";593;1
"Unit";"Zergling";"Larva";593;1
"Unit";"Hydralisk";"Larva";601;2
"Unit";"Hydralisk";"Larva";603;2
"Unit";"Hydralisk";"Larva";607;2
"Unit";"Hydralisk";"Larva";609;2
"Unit";"Hydralisk";"Larva";611;2
"Unit";"Hydralisk";"Larva";611;2
"Unit";"Hydralisk";"Larva";611;2
"Unit";"Hydralisk";"Larva";611;2
