"type";"unit_name";"on_building";"total_supply";"supply"
"Building";"Pylon";NA;13;0
"Building";"Assimilator";NA;15;0
"Building";"Gateway";NA;15;0
"Building";"Assimilator";NA;20;0
"Building";"CyberneticsCore";NA;20;0
"Building";"Pylon";NA;21;0
"Unit";"Adept";"Gateway";22;2
"Building";"Nexus";NA;19;0
"Unit";"Adept";"Gateway";23;2
"Building";"Stargate";NA;22;0
"Unit";"Oracle";"Stargate";27;3
"Building";"Pylon";NA;33;0
"Unit";"Stalker";"Gateway";34;2
"Building";"ShieldBattery";NA;38;0
"Unit";"Oracle";"Stargate";38;3
"Building";"Gateway";NA;38;0
"Building";"Gateway";NA;38;0
"Unit";"Phoenix";"Stargate";43;2
"Unit";"Phoenix";"Stargate";49;2
"Building";"Pylon";NA;53;0
"Unit";"Stalker";"Gateway";58;2
"Unit";"Stalker";"Gateway";58;2
"Unit";"Stalker";"Gateway";58;2
"Unit";"Phoenix";"Stargate";57;2
"Building";"Assimilator";NA;58;0
"Building";"Assimilator";NA;62;0
"Building";"Pylon";NA;66;0
"Building";"Pylon";NA;66;0
"Building";"Nexus";NA;53;0
"Building";"Forge";NA;66;0
"Building";"TwilightCouncil";NA;66;0
"Unit";"Zealot";"Gateway";71;2
"Unit";"Zealot";"Gateway";71;2
"Unit";"Zealot";"Gateway";71;2
"Building";"Gateway";NA;68;0
"Unit";"Phoenix";"Stargate";70;2
"Building";"Gateway";NA;68;0
"Unit";"Sentry";"Gateway";83;2
"Unit";"Phoenix";"Stargate";79;2
"Unit";"Sentry";"Gateway";83;2
"Building";"Pylon";NA;82;0
"Building";"Pylon";NA;82;0
"Building";"Pylon";NA;83;0
"Building";"Pylon";NA;83;0
"Unit";"Zealot";"Gateway";92;2
"Unit";"Zealot";"Gateway";92;2
"Unit";"Zealot";"Gateway";93;2
"Building";"ShieldBattery";NA;83;0
"Building";"Gateway";NA;81;0
"Building";"Gateway";NA;82;0
"Building";"Gateway";NA;82;0
"Upgrade";"Charge";"TwilightCouncil";78;0
"Building";"Pylon";NA;100;0
"Building";"Assimilator";NA;100;0
"Building";"Assimilator";NA;100;0
"Unit";"Zealot";"Gateway";103;2
"Building";"PhotonCannon";NA;100;0
"Unit";"Zealot";"Gateway";103;2
"Unit";"Zealot";"Gateway";103;2
"Unit";"Zealot";"Gateway";103;2
"Unit";"Zealot";"Gateway";103;2
"Building";"PhotonCannon";NA;103;0
"Upgrade";"ProtossGroundArmorsLevel1";"Forge";82;0
"Building";"TemplarArchive";NA;101;0
"Building";"Pylon";NA;117;0
"Unit";"Zealot";"Gateway";123;2
"Unit";"Zealot";"Gateway";123;2
"Unit";"Zealot";"Gateway";123;2
"Unit";"Zealot";"Gateway";123;2
"Unit";"Zealot";"Gateway";123;2
"Unit";"Zealot";"Gateway";123;2
"Unit";"Zealot";"Gateway";135;2
"Unit";"Zealot";"Gateway";135;2
"Unit";"Zealot";"Gateway";135;2
"Unit";"Zealot";"Gateway";135;2
"Unit";"Zealot";"Gateway";135;2
"Unit";"Zealot";"Gateway";135;2
"Unit";"Zealot";"Gateway";135;2
"Unit";"Zealot";"Gateway";135;2
"Building";"HighTemplar";NA;151;0
"Building";"HighTemplar";NA;151;0
"Building";"HighTemplar";NA;151;0
"Building";"HighTemplar";NA;151;0
"Building";"HighTemplar";NA;151;0
"Building";"HighTemplar";NA;151;0
"Building";"HighTemplar";NA;151;0
"Unit";"Phoenix";"Stargate";135;2
"Unit";"Sentry";"Gateway";155;2
"Building";"Pylon";NA;151;0
"Unit";"Archon";"High Templar";155;0
"Unit";"Archon";"High Templar";155;0
"Building";"Pylon";NA;155;0
"Unit";"Phoenix";"Stargate";154;2
"Building";"Pylon";NA;155;0
"Building";"PhotonCannon";NA;155;0
"Building";"Pylon";NA;158;0
"Building";"HighTemplar";NA;161;0
"Building";"HighTemplar";NA;161;0
"Unit";"Zealot";"Gateway";162;2
"Unit";"Zealot";"Gateway";162;2
"Unit";"Zealot";"Gateway";162;2
"Building";"RoboticsFacility";NA;151;0
"Unit";"Zealot";"Gateway";162;2
"Unit";"Zealot";"Gateway";162;2
"Building";"RoboticsFacility";NA;151;0
"Building";"Pylon";NA;161;0
"Unit";"Archon";"High Templar";162;0
"Upgrade";"ProtossGroundArmorsLevel2";"Forge";123;0
"Building";"Forge";NA;157;0
"Unit";"Phoenix";"Stargate";159;2
"Building";"HighTemplar";NA;174;0
"Unit";"Zealot";"Gateway";174;2
"Unit";"Zealot";"Gateway";174;2
"Unit";"Zealot";"Gateway";174;2
"Unit";"Zealot";"Gateway";174;2
"Unit";"Zealot";"Gateway";174;2
"Building";"PhotonCannon";NA;172;0
"Unit";"Observer";"Robotics Facility";184;1
"Unit";"Phoenix";"Stargate";184;2
"Building";"Assimilator";NA;185;0
"Unit";"Zealot";"Gateway";189;2
"Unit";"Zealot";"Gateway";189;2
"Unit";"Zealot";"Gateway";189;2
"Unit";"Zealot";"Gateway";189;2
"Unit";"Zealot";"Gateway";189;2
"Unit";"Zealot";"Gateway";189;2
"Unit";"Zealot";"Gateway";189;2
"Building";"PhotonCannon";NA;186;0
"Building";"PhotonCannon";NA;186;0
"Building";"Nexus";NA;184;0
"Building";"FleetBeacon";NA;186;0
"Unit";"Observer";"Robotics Facility";203;1
"Unit";"Observer";"Robotics Facility";203;1
"Upgrade";"ProtossGroundWeaponsLevel1";"Forge";184;0
"Unit";"Oracle";"Stargate";203;3
"Building";"RoboticsBay";NA;203;0
"Building";"Assimilator";NA;205;0
"Building";"PhotonCannon";NA;205;0
"Building";"PhotonCannon";NA;205;0
"Building";"PhotonCannon";NA;205;0
"Building";"PhotonCannon";NA;205;0
"Unit";"Stalker";"Gateway";208;2
"Unit";"Stalker";"Gateway";208;2
"Unit";"Stalker";"Gateway";208;2
"Unit";"Stalker";"Gateway";208;2
"Unit";"Stalker";"Gateway";208;2
"Unit";"Stalker";"Gateway";208;2
"Unit";"Stalker";"Gateway";208;2
"Unit";"Stalker";"Gateway";208;2
"Building";"PhotonCannon";NA;208;0
"Building";"ShieldBattery";NA;208;0
"Building";"PhotonCannon";NA;208;0
"Building";"PhotonCannon";NA;208;0
"Building";"Stargate";NA;208;0
"Building";"Stargate";NA;208;0
"Upgrade";"ProtossGroundArmorsLevel3";"Forge";189;0
"Unit";"Archon";"High Templar";224;0
"Unit";"Zealot";"Gateway";224;2
"Unit";"Zealot";"Gateway";224;2
"Unit";"Zealot";"Gateway";224;2
"Unit";"Zealot";"Gateway";224;2
"Unit";"Zealot";"Gateway";224;2
"Unit";"Zealot";"Gateway";234;2
"Unit";"Zealot";"Gateway";234;2
"Unit";"Zealot";"Gateway";234;2
"Building";"HighTemplar";NA;240;0
"Building";"HighTemplar";NA;240;0
"Building";"HighTemplar";NA;240;0
"Building";"Pylon";NA;241;0
"Building";"HighTemplar";NA;241;0
"Building";"HighTemplar";NA;241;0
"Building";"Pylon";NA;241;0
"Unit";"Archon";"High Templar";241;0
"Upgrade";"ProtossGroundWeaponsLevel2";"Forge";208;0
"Unit";"Disruptor";"Robotics Facility";240;3
"Unit";"Disruptor";"Robotics Facility";240;3
"Building";"PhotonCannon";NA;241;0
"Building";"PhotonCannon";NA;241;0
"Building";"Assimilator";NA;241;0
"Building";"PhotonCannon";NA;241;0
"Building";"PhotonCannon";NA;241;0
"Unit";"Disruptor";"Robotics Facility";241;3
"Unit";"Disruptor";"Robotics Facility";241;3
"Unit";"Tempest";"Stargate";241;4
"Unit";"Tempest";"Stargate";241;4
"Unit";"Tempest";"Stargate";241;4
"Building";"Nexus";NA;240;0
"Building";"ShieldBattery";NA;250;0
"Building";"ShieldBattery";NA;250;0
"Unit";"Zealot";"Gateway";269;2
"Unit";"Zealot";"Gateway";269;2
"Unit";"Archon";"High Templar";261;0
"Unit";"Zealot";"Gateway";273;2
"Unit";"Zealot";"Gateway";273;2
"Unit";"Zealot";"Gateway";273;2
"Unit";"Zealot";"Gateway";273;2
"Unit";"Zealot";"Gateway";273;2
"Unit";"Zealot";"Gateway";273;2
"Upgrade";"ProtossShieldsLevel1";"Forge";247;0
"Building";"Pylon";NA;288;0
"Unit";"Tempest";"Stargate";285;4
"Unit";"Tempest";"Stargate";285;4
"Unit";"Tempest";"Stargate";285;4
"Unit";"Zealot";"Gateway";301;2
"Unit";"Zealot";"Gateway";301;2
"Unit";"Zealot";"Gateway";301;2
"Unit";"Zealot";"Gateway";301;2
"Unit";"Zealot";"Gateway";301;2
"Unit";"Zealot";"Gateway";301;2
"Unit";"Disruptor";"Robotics Facility";289;3
"Unit";"Disruptor";"Robotics Facility";289;3
"Unit";"Zealot";"Gateway";319;2
"Unit";"Zealot";"Gateway";319;2
"Unit";"Zealot";"Gateway";319;2
"Unit";"Zealot";"Gateway";319;2
"Unit";"Zealot";"Gateway";319;2
"Unit";"Zealot";"Gateway";319;2
"Unit";"Zealot";"Gateway";319;2
"Unit";"Zealot";"Gateway";319;2
"Building";"Gateway";NA;313;0
"Building";"Gateway";NA;313;0
"Building";"Gateway";NA;319;0
