"type";"unit_name";"on_building";"total_supply";"supply"
"Building";"Pylon";NA;13;0
"Building";"Assimilator";NA;15;0
"Building";"Gateway";NA;14;0
"Building";"CyberneticsCore";NA;20;0
"Building";"Assimilator";NA;20;0
"Building";"Pylon";NA;21;0
"Building";"Nexus";NA;19;0
"Unit";"Stalker";"Gateway";22;2
"Unit";"Stalker";"Gateway";26;2
"Building";"RoboticsFacility";NA;32;0
"Building";"Pylon";NA;41;0
"Building";"Gateway";NA;36;0
"Building";"ShieldBattery";NA;39;0
"Unit";"Observer";"Robotics Facility";43;1
"Building";"Gateway";NA;37;0
"Building";"Pylon";NA;45;0
"Unit";"Stalker";"Gateway";49;2
"Unit";"Stalker";"Gateway";49;2
"Unit";"Stalker";"Gateway";50;2
"Unit";"Immortal";"Robotics Facility";48;4
"Building";"Pylon";NA;56;0
"Unit";"Observer";"Robotics Facility";58;1
"Building";"Forge";NA;58;0
"Building";"TwilightCouncil";NA;56;0
"Building";"Forge";NA;58;0
"Unit";"Stalker";"Gateway";65;2
"Unit";"Stalker";"Gateway";65;2
"Unit";"Stalker";"Gateway";65;2
"Building";"Pylon";NA;64;0
"Building";"Assimilator";NA;64;0
"Building";"Assimilator";NA;65;0
"Building";"Nexus";NA;64;0
"Building";"Pylon";NA;75;0
"Unit";"Immortal";"Robotics Facility";75;4
"Building";"Pylon";NA;76;0
"Building";"Gateway";NA;76;0
"Building";"Gateway";NA;76;0
"Upgrade";"ProtossGroundWeaponsLevel1";"Forge";71;0
"Building";"Gateway";NA;76;0
"Building";"Gateway";NA;76;0
"Building";"Gateway";NA;76;0
"Upgrade";"ProtossGroundArmorsLevel1";"Forge";73;0
"Unit";"Immortal";"Robotics Facility";79;4
"Building";"Pylon";NA;88;0
"Building";"Assimilator";NA;88;0
"Unit";"Sentry";"Gateway";97;2
"Unit";"Sentry";"Gateway";97;2
"Upgrade";"Charge";"TwilightCouncil";76;0
"Building";"TemplarArchive";NA;86;0
"Unit";"Zealot";"Gateway";102;2
"Unit";"Zealot";"Gateway";102;2
"Unit";"Zealot";"Gateway";102;2
"Building";"Gateway";NA;86;0
"Building";"Gateway";NA;86;0
"Building";"Pylon";NA;95;0
"Building";"Assimilator";NA;95;0
"Unit";"Zealot";"Gateway";110;2
"Unit";"Zealot";"Gateway";110;2
"Building";"Pylon";NA;97;0
"Building";"Pylon";NA;97;0
"Unit";"Zealot";"Gateway";114;2
"Unit";"Zealot";"Gateway";114;2
"Unit";"Zealot";"Gateway";114;2
"Unit";"Zealot";"Gateway";114;2
"Unit";"Zealot";"Gateway";114;2
"Unit";"Zealot";"Gateway";124;2
"Unit";"Zealot";"Gateway";124;2
"Unit";"Zealot";"Gateway";124;2
"Unit";"Zealot";"Gateway";124;2
"Building";"HighTemplar";NA;132;0
"Building";"HighTemplar";NA;132;0
"Building";"HighTemplar";NA;132;0
"Building";"HighTemplar";NA;132;0
"Building";"HighTemplar";NA;132;0
"Unit";"Zealot";"Gateway";132;2
"Unit";"Zealot";"Gateway";132;2
"Unit";"Immortal";"Robotics Facility";124;4
"Building";"ShieldBattery";NA;132;0
"Building";"ShieldBattery";NA;132;0
"Building";"ShieldBattery";NA;132;0
"Building";"Pylon";NA;136;0
"Building";"Pylon";NA;140;0
"Upgrade";"ProtossGroundWeaponsLevel2";"Forge";102;0
"Upgrade";"ProtossGroundArmorsLevel2";"Forge";104;0
"Building";"Pylon";NA;140;0
"Building";"HighTemplar";NA;140;0
"Unit";"Zealot";"Gateway";140;2
"Unit";"Zealot";"Gateway";140;2
"Unit";"Zealot";"Gateway";140;2
"Unit";"Zealot";"Gateway";140;2
"Unit";"Zealot";"Gateway";140;2
"Building";"Pylon";NA;140;0
"Building";"Pylon";NA;140;0
"Building";"HighTemplar";NA;150;0
"Building";"HighTemplar";NA;150;0
"Unit";"Zealot";"Gateway";150;2
"Unit";"Zealot";"Gateway";150;2
"Unit";"Immortal";"Robotics Facility";140;4
"Unit";"Zealot";"Gateway";158;2
"Unit";"Zealot";"Gateway";158;2
"Unit";"Zealot";"Gateway";158;2
"Unit";"Zealot";"Gateway";158;2
"Unit";"Zealot";"Gateway";158;2
"Unit";"Zealot";"Gateway";158;2
"Unit";"Zealot";"Gateway";158;2
"Unit";"Zealot";"Gateway";158;2
"Building";"Pylon";NA;174;0
"Unit";"Immortal";"Robotics Facility";174;4
"Building";"HighTemplar";NA;174;0
"Building";"HighTemplar";NA;174;0
"Building";"HighTemplar";NA;174;0
"Building";"HighTemplar";NA;174;0
"Building";"HighTemplar";NA;174;0
"Unit";"Zealot";"Gateway";174;2
"Unit";"Zealot";"Gateway";174;2
"Unit";"Zealot";"Gateway";174;2
"Unit";"Zealot";"Gateway";174;2
"Unit";"Zealot";"Gateway";174;2
"Unit";"Stalker";"Gateway";188;2
"Unit";"Stalker";"Gateway";188;2
"Unit";"Stalker";"Gateway";188;2
"Unit";"Stalker";"Gateway";188;2
"Unit";"Stalker";"Gateway";188;2
"Building";"Nexus";NA;174;0
"Upgrade";"ProtossGroundArmorsLevel3";"Forge";154;0
"Unit";"Immortal";"Robotics Facility";178;4
"Upgrade";"ProtossGroundWeaponsLevel3";"Forge";154;0
"Unit";"Stalker";"Gateway";202;2
"Unit";"Stalker";"Gateway";202;2
"Unit";"Zealot";"Gateway";202;2
"Unit";"Zealot";"Gateway";202;2
"Unit";"Zealot";"Gateway";202;2
"Unit";"Zealot";"Gateway";202;2
"Unit";"Zealot";"Gateway";202;2
"Unit";"Zealot";"Gateway";202;2
"Unit";"Zealot";"Gateway";202;2
"Unit";"Zealot";"Gateway";202;2
"Building";"Pylon";NA;198;0
"Building";"Pylon";NA;202;0
"Unit";"Archon";"High Templar";222;0
"Unit";"Stalker";"Gateway";222;2
"Unit";"Stalker";"Gateway";222;2
"Unit";"Stalker";"Gateway";222;2
"Unit";"Stalker";"Gateway";222;2
"Unit";"Stalker";"Gateway";222;2
"Unit";"Zealot";"Gateway";222;2
"Unit";"Zealot";"Gateway";222;2
"Unit";"Zealot";"Gateway";222;2
"Unit";"Zealot";"Gateway";222;2
"Unit";"Zealot";"Gateway";222;2
"Unit";"Archon";"High Templar";242;0
"Building";"Assimilator";NA;222;0
"Building";"RoboticsBay";NA;222;0
"Building";"Nexus";NA;198;0
"Unit";"Stalker";"Gateway";242;2
"Building";"RoboticsFacility";NA;222;0
"Building";"HighTemplar";NA;242;0
"Building";"HighTemplar";NA;242;0
"Building";"HighTemplar";NA;242;0
"Building";"HighTemplar";NA;242;0
"Building";"HighTemplar";NA;242;0
"Unit";"Zealot";"Gateway";242;2
"Unit";"Zealot";"Gateway";242;2
"Unit";"Zealot";"Gateway";242;2
"Unit";"Zealot";"Gateway";242;2
"Unit";"Immortal";"Robotics Facility";222;4
"Unit";"Sentry";"Gateway";256;2
"Unit";"Sentry";"Gateway";256;2
"Unit";"Zealot";"Gateway";256;2
"Unit";"Zealot";"Gateway";256;2
"Unit";"Zealot";"Gateway";256;2
"Upgrade";"ProtossShieldsLevel1";"Forge";222;0
"Building";"Assimilator";NA;256;0
"Unit";"Archon";"High Templar";266;0
"Building";"HighTemplar";NA;266;0
"Unit";"Stalker";"Gateway";266;2
"Unit";"Stalker";"Gateway";266;2
"Unit";"Stalker";"Gateway";266;2
"Unit";"Stalker";"Gateway";266;2
"Unit";"Stalker";"Gateway";266;2
"Unit";"Stalker";"Gateway";266;2
"Unit";"Stalker";"Gateway";266;2
"Unit";"Stalker";"Gateway";266;2
"Unit";"Zealot";"Gateway";266;2
"Unit";"Immortal";"Robotics Facility";266;4
"Unit";"Immortal";"Robotics Facility";266;4
"Unit";"Sentry";"Gateway";288;2
"Unit";"Sentry";"Gateway";288;2
"Unit";"Zealot";"Gateway";288;2
"Unit";"Zealot";"Gateway";288;2
"Unit";"Zealot";"Gateway";288;2
"Unit";"Zealot";"Gateway";288;2
"Unit";"Zealot";"Gateway";288;2
"Unit";"Zealot";"Gateway";288;2
"Unit";"Zealot";"Gateway";288;2
"Unit";"Zealot";"Gateway";288;2
"Building";"Assimilator";NA;284;0
"Building";"Assimilator";NA;284;0
"Unit";"Disruptor";"Robotics Facility";288;3
"Unit";"Zealot";"Gateway";312;2
"Unit";"Zealot";"Gateway";312;2
"Unit";"Zealot";"Gateway";312;2
"Unit";"Zealot";"Gateway";312;2
"Unit";"Zealot";"Gateway";312;2
"Unit";"Zealot";"Gateway";312;2
"Unit";"Zealot";"Gateway";312;2
"Unit";"Zealot";"Gateway";312;2
"Unit";"Zealot";"Gateway";312;2
"Unit";"Zealot";"Gateway";312;2
"Unit";"Disruptor";"Robotics Facility";288;3
"Building";"Stargate";NA;288;0
"Unit";"Disruptor";"Robotics Facility";312;3
"Building";"PhotonCannon";NA;338;0
"Building";"PhotonCannon";NA;338;0
"Unit";"Colossus";"Robotics Facility";312;6
"Unit";"Disruptor";"Robotics Facility";338;3
"Upgrade";"ProtossShieldsLevel2";"Forge";288;0
"Unit";"Disruptor";"Robotics Facility";341;3
"Upgrade";"ProtossAirWeaponsLevel1";"CyberneticsCore";312;0
"Building";"FleetBeacon";NA;341;0
"Building";"Stargate";NA;341;0
"Unit";"Stalker";"Gateway";353;2
"Unit";"Stalker";"Gateway";353;2
"Unit";"Stalker";"Gateway";353;2
"Unit";"Stalker";"Gateway";353;2
"Unit";"Stalker";"Gateway";353;2
"Unit";"Stalker";"Gateway";353;2
"Unit";"Stalker";"Gateway";353;2
"Unit";"Stalker";"Gateway";353;2
"Unit";"Disruptor";"Robotics Facility";347;3
"Unit";"Stalker";"Gateway";372;2
"Unit";"Stalker";"Gateway";372;2
"Unit";"Disruptor";"Robotics Facility";350;3
"Building";"Nexus";NA;347;0
"Unit";"Disruptor";"Robotics Facility";369;3
"Unit";"Stalker";"Gateway";382;2
"Unit";"Stalker";"Gateway";382;2
"Unit";"Stalker";"Gateway";382;2
"Unit";"Stalker";"Gateway";382;2
"Unit";"Stalker";"Gateway";382;2
"Unit";"Stalker";"Gateway";382;2
"Unit";"Stalker";"Gateway";382;2
"Unit";"Stalker";"Gateway";382;2
"Building";"Pylon";NA;379;0
"Unit";"Tempest";"Stargate";372;4
"Unit";"Tempest";"Stargate";372;4
"Building";"Pylon";NA;379;0
