"type";"unit_name";"on_building";"total_supply";"supply"
"Building";"Pylon";NA;13;0
"Building";"Assimilator";NA;16;0
"Building";"Gateway";NA;15;0
"Building";"Assimilator";NA;19;0
"Building";"CyberneticsCore";NA;19;0
"Building";"Pylon";NA;20;0
"Unit";"Adept";"Gateway";21;2
"Building";"Nexus";NA;19;0
"Unit";"Stalker";"Gateway";22;2
"Unit";"Stalker";"Gateway";30;2
"Building";"TwilightCouncil";NA;33;0
"Building";"Gateway";NA;35;0
"Building";"Gateway";NA;39;0
"Building";"Pylon";NA;45;0
"Building";"Assimilator";NA;45;0
"Building";"Assimilator";NA;46;0
"Unit";"Stalker";"Gateway";49;2
"Unit";"Stalker";"Gateway";50;2
"Building";"Pylon";NA;48;0
"Building";"RoboticsFacility";NA;43;0
"Unit";"Stalker";"Gateway";54;2
"Building";"ShieldBattery";NA;48;0
"Unit";"Observer";"Robotics Facility";54;1
"Building";"Forge";NA;49;0
"Unit";"Stalker";"Gateway";58;2
"Unit";"Stalker";"Gateway";62;2
"Building";"Pylon";NA;57;0
"Unit";"Observer";"Robotics Facility";57;1
"Unit";"Stalker";"Gateway";65;2
"Unit";"Observer";"Robotics Facility";64;1
"Unit";"Stalker";"Gateway";68;2
"Unit";"Stalker";"Gateway";68;2
"Building";"RoboticsBay";NA;58;0
"Building";"Pylon";NA;67;0
"Unit";"Stalker";"Gateway";72;2
"Unit";"Observer";"Robotics Facility";72;1
"Building";"Nexus";NA;67;0
"Building";"RoboticsFacility";NA;72;0
"Unit";"Disruptor";"Robotics Facility";77;3
"Building";"Pylon";NA;83;0
"Upgrade";"ProtossGroundWeaponsLevel1";"Forge";72;0
"Unit";"Disruptor";"Robotics Facility";86;3
"Building";"Gateway";NA;86;0
"Building";"Gateway";NA;86;0
"Unit";"Disruptor";"Robotics Facility";89;3
"Building";"Gateway";NA;86;0
"Building";"Pylon";NA;94;0
"Building";"Pylon";NA;95;0
"Building";"Forge";NA;91;0
"Unit";"Stalker";"Gateway";106;2
"Unit";"Stalker";"Gateway";106;2
"Unit";"Stalker";"Gateway";106;2
"Building";"Assimilator";NA;100;0
"Building";"Assimilator";NA;100;0
"Unit";"Zealot";"Gateway";116;2
"Unit";"Zealot";"Gateway";116;2
"Unit";"Disruptor";"Robotics Facility";100;3
"Unit";"Zealot";"Gateway";116;2
"Unit";"Zealot";"Gateway";116;2
"Unit";"Zealot";"Gateway";116;2
"Unit";"Zealot";"Gateway";116;2
"Building";"Pylon";NA;114;0
"Unit";"Disruptor";"Robotics Facility";104;3
"Upgrade";"Charge";"TwilightCouncil";91;0
"Unit";"Stalker";"Gateway";137;2
"Unit";"Stalker";"Gateway";137;2
"Unit";"Stalker";"Gateway";137;2
"Unit";"Stalker";"Gateway";137;2
"Unit";"Disruptor";"Robotics Facility";123;3
"Unit";"Disruptor";"Robotics Facility";134;3
"Upgrade";"ProtossGroundArmorsLevel1";"Forge";112;0
"Building";"Pylon";NA;149;0
"Building";"Pylon";NA;149;0
"Building";"Pylon";NA;149;0
"Unit";"Zealot";"Gateway";155;2
"Unit";"Zealot";"Gateway";155;2
"Unit";"Zealot";"Gateway";162;2
"Unit";"Zealot";"Gateway";162;2
"Unit";"Zealot";"Gateway";162;2
"Building";"Pylon";NA;160;0
"Building";"Pylon";NA;161;0
"Unit";"Disruptor";"Robotics Facility";155;3
"Upgrade";"ProtossGroundWeaponsLevel2";"Forge";137;0
"Unit";"Stalker";"Gateway";173;2
"Unit";"Stalker";"Gateway";173;2
"Unit";"Stalker";"Gateway";173;2
"Unit";"Disruptor";"Robotics Facility";168;3
"Unit";"Disruptor";"Robotics Facility";171;3
"Unit";"Stalker";"Gateway";186;2
"Unit";"Stalker";"Gateway";186;2
"Building";"Pylon";NA;186;0
"Unit";"Stalker";"Gateway";190;2
"Unit";"Stalker";"Gateway";192;2
"Unit";"Stalker";"Gateway";192;2
"Unit";"Disruptor";"Robotics Facility";186;3
"Unit";"Stalker";"Gateway";196;2
"Unit";"Stalker";"Gateway";196;2
"Unit";"Disruptor";"Robotics Facility";186;3
"Unit";"Stalker";"Gateway";206;2
"Building";"Nexus";NA;186;0
"Unit";"Disruptor";"Robotics Facility";206;3
"Unit";"Disruptor";"Robotics Facility";208;3
"Building";"Assimilator";NA;215;0
"Unit";"Stalker";"Gateway";220;2
"Unit";"Stalker";"Gateway";220;2
"Unit";"Stalker";"Gateway";220;2
"Unit";"Observer";"Robotics Facility";219;1
"Unit";"Observer";"Robotics Facility";219;1
"Unit";"Stalker";"Gateway";226;2
"Upgrade";"ProtossGroundArmorsLevel2";"Forge";192;0
"Unit";"Stalker";"Gateway";230;2
"Unit";"Stalker";"Gateway";230;2
"Unit";"Stalker";"Gateway";230;2
"Unit";"Stalker";"Gateway";234;2
"Building";"Pylon";NA;230;0
"Unit";"Observer";"Robotics Facility";230;1
"Unit";"Zealot";"Gateway";238;2
"Unit";"Stalker";"Gateway";241;2
"Unit";"Stalker";"Gateway";241;2
"Unit";"Zealot";"Gateway";245;2
"Unit";"Zealot";"Gateway";245;2
"Unit";"Zealot";"Gateway";245;2
"Unit";"Zealot";"Gateway";245;2
"Unit";"Disruptor";"Robotics Facility";241;3
"Building";"Pylon";NA;260;0
"Building";"Pylon";NA;262;0
"Unit";"Stalker";"Gateway";262;2
"Unit";"Stalker";"Gateway";262;2
"Unit";"Stalker";"Gateway";266;2
"Building";"Pylon";NA;262;0
"Unit";"Stalker";"Gateway";266;2
"Unit";"Stalker";"Gateway";270;2
"Upgrade";"ProtossGroundWeaponsLevel3";"Forge";230;0
"Unit";"Disruptor";"Robotics Facility";262;3
"Unit";"Stalker";"Gateway";272;2
"Unit";"Stalker";"Gateway";277;2
"Unit";"Stalker";"Gateway";277;2
"Unit";"Stalker";"Gateway";277;2
"Unit";"Stalker";"Gateway";277;2
"Unit";"Disruptor";"Robotics Facility";272;3
"Building";"Nexus";NA;262;0
"Unit";"Disruptor";"Robotics Facility";277;3
"Unit";"Disruptor";"Robotics Facility";277;3
"Unit";"Disruptor";"Robotics Facility";290;3
"Unit";"Zealot";"Gateway";302;2
"Unit";"Zealot";"Gateway";302;2
"Unit";"Zealot";"Gateway";302;2
"Unit";"Disruptor";"Robotics Facility";293;3
"Building";"TemplarArchive";NA;296;0
"Upgrade";"ProtossGroundArmorsLevel3";"Forge";266;0
"Building";"RoboticsFacility";NA;299;0
"Unit";"Stalker";"Gateway";316;2
"Unit";"Stalker";"Gateway";316;2
"Unit";"Stalker";"Gateway";316;2
"Unit";"Stalker";"Gateway";316;2
"Unit";"Stalker";"Gateway";316;2
"Unit";"Disruptor";"Robotics Facility";312;3
"Unit";"Disruptor";"Robotics Facility";315;3
"Unit";"Stalker";"Gateway";332;2
"Building";"Assimilator";NA;326;0
"Building";"Assimilator";NA;326;0
"Unit";"Disruptor";"Robotics Facility";316;3
"Unit";"Stalker";"Gateway";334;2
"Unit";"Stalker";"Gateway";334;2
"Unit";"Disruptor";"Robotics Facility";326;3
"Unit";"Stalker";"Gateway";343;2
"Unit";"Disruptor";"Robotics Facility";332;3
"Unit";"Disruptor";"Robotics Facility";334;3
"Unit";"Observer";"Robotics Facility";343;1
"Unit";"Observer";"Robotics Facility";349;1
"Unit";"Stalker";"Gateway";357;2
"Unit";"Stalker";"Gateway";357;2
"Unit";"Stalker";"Gateway";357;2
"Unit";"Stalker";"Gateway";357;2
"Unit";"Stalker";"Gateway";357;2
"Unit";"Stalker";"Gateway";357;2
"Unit";"Disruptor";"Robotics Facility";352;3
"Unit";"Disruptor";"Robotics Facility";356;3
"Unit";"Disruptor";"Robotics Facility";356;3
"Unit";"Stalker";"Gateway";378;2
"Unit";"Stalker";"Gateway";378;2
"Unit";"Stalker";"Gateway";378;2
"Unit";"Stalker";"Gateway";378;2
"Unit";"Stalker";"Gateway";378;2
"Unit";"Disruptor";"Robotics Facility";369;3
"Upgrade";"ProtossShieldsLevel1";"Forge";349;0
"Unit";"Stalker";"Gateway";393;2
"Unit";"Stalker";"Gateway";393;2
"Unit";"Stalker";"Gateway";393;2
"Unit";"Stalker";"Gateway";393;2
"Unit";"Stalker";"Gateway";393;2
"Unit";"Stalker";"Gateway";393;2
"Building";"Nexus";NA;372;0
"Building";"Pylon";NA;405;0
"Unit";"Disruptor";"Robotics Facility";405;3
"Building";"Pylon";NA;405;0
"Unit";"Disruptor";"Robotics Facility";405;3
"Unit";"Stalker";"Gateway";414;2
"Unit";"Stalker";"Gateway";414;2
"Unit";"Stalker";"Gateway";414;2
"Unit";"Stalker";"Gateway";414;2
"Unit";"Stalker";"Gateway";414;2
"Unit";"Stalker";"Gateway";414;2
"Building";"Gateway";NA;405;0
"Building";"Gateway";NA;405;0
"Building";"Gateway";NA;405;0
"Unit";"Observer";"Robotics Facility";414;1
"Building";"Assimilator";NA;426;0
"Building";"Assimilator";NA;426;0
"Unit";"Disruptor";"Robotics Facility";414;3
"Building";"DarkShrine";NA;405;0
"Unit";"Disruptor";"Robotics Facility";426;3
"Unit";"Stalker";"Gateway";433;2
"Unit";"Stalker";"Gateway";433;2
"Unit";"Stalker";"Gateway";433;2
"Unit";"Disruptor";"Robotics Facility";427;3
"Unit";"Stalker";"Gateway";433;2
"Unit";"Disruptor";"Robotics Facility";427;3
"Unit";"Stalker";"Gateway";447;2
"Unit";"Stalker";"Gateway";447;2
"Unit";"Disruptor";"Robotics Facility";433;3
"Building";"Pylon";NA;447;0
"Building";"Pylon";NA;447;0
"Unit";"Zealot";"Gateway";454;2
"Unit";"Zealot";"Gateway";454;2
"Unit";"Zealot";"Gateway";454;2
"Unit";"Zealot";"Gateway";454;2
"Unit";"Disruptor";"Robotics Facility";439;3
