"type";"unit_name";"on_building";"total_supply";"supply"
"Building";"Pylon";NA;13;0
"Building";"Assimilator";NA;15;0
"Building";"Gateway";NA;15;0
"Building";"Assimilator";NA;20;0
"Building";"CyberneticsCore";NA;20;0
"Building";"Pylon";NA;21;0
"Unit";"Adept";"Gateway";22;2
"Building";"Nexus";NA;19;0
"Unit";"Stalker";"Gateway";24;2
"Building";"TwilightCouncil";NA;23;0
"Unit";"Stalker";"Gateway";31;2
"Building";"Pylon";NA;41;0
"Building";"Gateway";NA;35;0
"Building";"Gateway";NA;36;0
"Building";"Assimilator";NA;43;0
"Unit";"Stalker";"Gateway";47;2
"Unit";"Stalker";"Gateway";47;2
"Building";"Assimilator";NA;43;0
"Building";"RoboticsFacility";NA;41;0
"Building";"Forge";NA;45;0
"Building";"Pylon";NA;51;0
"Building";"Pylon";NA;53;0
"Unit";"Stalker";"Gateway";56;2
"Unit";"Stalker";"Gateway";56;2
"Unit";"Observer";"Robotics Facility";54;1
"Unit";"Stalker";"Gateway";62;2
"Building";"RoboticsBay";NA;53;0
"Unit";"Stalker";"Gateway";65;2
"Unit";"Observer";"Robotics Facility";60;1
"Building";"Pylon";NA;61;0
"Unit";"Stalker";"Gateway";68;2
"Building";"Pylon";NA;65;0
"Unit";"Stalker";"Gateway";73;2
"Unit";"Observer";"Robotics Facility";69;1
"Unit";"Stalker";"Gateway";78;2
"Building";"Nexus";NA;56;0
"Building";"Pylon";NA;76;0
"Upgrade";"ProtossGroundWeaponsLevel1";"Forge";56;0
"Unit";"Colossus";"Robotics Facility";73;6
"Unit";"Stalker";"Gateway";93;2
"Unit";"Stalker";"Gateway";93;2
"Unit";"Stalker";"Gateway";93;2
"Upgrade";"Charge";"TwilightCouncil";71;0
"Building";"Gateway";NA;81;0
"Building";"Gateway";NA;81;0
"Unit";"Observer";"Robotics Facility";87;1
"Building";"Gateway";NA;81;0
"Building";"Pylon";NA;102;0
"Unit";"Stalker";"Gateway";106;2
"Building";"Pylon";NA;102;0
"Unit";"Stalker";"Gateway";106;2
"Unit";"Stalker";"Gateway";106;2
"Building";"RoboticsFacility";NA;84;0
"Building";"Assimilator";NA;105;0
"Building";"Pylon";NA;106;0
"Building";"Assimilator";NA;106;0
"Building";"Pylon";NA;106;0
"Unit";"Observer";"Robotics Facility";106;1
"Upgrade";"ExtendedThermalLance";"RoboticsBay";102;0
"Building";"Pylon";NA;118;0
"Building";"Pylon";NA;118;0
"Building";"Pylon";NA;118;0
"Unit";"Colossus";"Robotics Facility";114;6
"Building";"PhotonCannon";NA;118;0
"Building";"PhotonCannon";NA;118;0
"Building";"PhotonCannon";NA;118;0
"Building";"PhotonCannon";NA;118;0
"Building";"PhotonCannon";NA;118;0
"Unit";"Colossus";"Robotics Facility";118;6
"Building";"PhotonCannon";NA;118;0
"Building";"ShieldBattery";NA;118;0
"Building";"ShieldBattery";NA;118;0
"Building";"PhotonCannon";NA;118;0
"Building";"PhotonCannon";NA;118;0
"Building";"ShieldBattery";NA;124;0
"Building";"PhotonCannon";NA;124;0
"Building";"Nexus";NA;118;0
"Building";"Forge";NA;130;0
"Unit";"Colossus";"Robotics Facility";124;6
"Unit";"Stalker";"Gateway";140;2
"Unit";"Stalker";"Gateway";140;2
"Unit";"Stalker";"Gateway";140;2
"Unit";"Stalker";"Gateway";140;2
"Building";"PhotonCannon";NA;136;0
"Unit";"Observer";"Robotics Facility";139;1
"Upgrade";"ProtossGroundWeaponsLevel2";"Forge";118;0
"Building";"Assimilator";NA;154;0
"Building";"Assimilator";NA;154;0
"Unit";"Colossus";"Robotics Facility";133;6
"Building";"RoboticsFacility";NA;134;0
"Building";"PhotonCannon";NA;154;0
"Building";"PhotonCannon";NA;155;0
"Building";"PhotonCannon";NA;155;0
"Unit";"Observer";"Robotics Facility";155;1
"Building";"ShieldBattery";NA;155;0
"Building";"PhotonCannon";NA;156;0
"Building";"PhotonCannon";NA;156;0
"Building";"Pylon";NA;162;0
"Building";"PhotonCannon";NA;162;0
"Unit";"Sentry";"Gateway";163;2
"Unit";"Sentry";"Gateway";163;2
"Unit";"Sentry";"Gateway";163;2
"Unit";"Sentry";"Gateway";163;2
"Unit";"Sentry";"Gateway";163;2
"Unit";"Sentry";"Gateway";163;2
"Building";"ShieldBattery";NA;162;0
"Building";"PhotonCannon";NA;162;0
"Building";"PhotonCannon";NA;162;0
"Building";"PhotonCannon";NA;163;0
"Building";"PhotonCannon";NA;163;0
"Building";"ShieldBattery";NA;163;0
"Unit";"Colossus";"Robotics Facility";162;6
"Building";"Pylon";NA;175;0
"Building";"Pylon";NA;175;0
"Building";"Pylon";NA;175;0
"Building";"Pylon";NA;175;0
"Building";"Pylon";NA;181;0
"Unit";"Colossus";"Robotics Facility";175;6
"Building";"PhotonCannon";NA;181;0
"Building";"PhotonCannon";NA;181;0
"Building";"PhotonCannon";NA;181;0
"Building";"ShieldBattery";NA;181;0
"Building";"ShieldBattery";NA;181;0
"Building";"ShieldBattery";NA;181;0
"Building";"PhotonCannon";NA;181;0
"Building";"PhotonCannon";NA;181;0
"Building";"PhotonCannon";NA;187;0
"Unit";"Stalker";"Gateway";187;2
"Unit";"Stalker";"Gateway";187;2
"Unit";"Stalker";"Gateway";187;2
"Building";"ShieldBattery";NA;187;0
"Unit";"Stalker";"Gateway";187;2
"Unit";"Stalker";"Gateway";187;2
"Unit";"Stalker";"Gateway";187;2
"Building";"ShieldBattery";NA;187;0
"Building";"PhotonCannon";NA;187;0
"Unit";"Colossus";"Robotics Facility";181;6
"Building";"PhotonCannon";NA;187;0
"Building";"PhotonCannon";NA;187;0
