"type";"unit_name";"on_building";"total_supply";"supply"
"Building";"Pylon";NA;13;0
"Building";"Assimilator";NA;16;0
"Building";"Gateway";NA;15;0
"Building";"CyberneticsCore";NA;20;0
"Building";"Pylon";NA;22;0
"Building";"Assimilator";NA;22;0
"Unit";"Adept";"Gateway";22;2
"Building";"Nexus";NA;21;0
"Unit";"Stalker";"Gateway";24;2
"Building";"Stargate";NA;27;0
"Unit";"Stalker";"Gateway";33;2
"Building";"Gateway";NA;32;0
"Building";"Gateway";NA;32;0
"Building";"Pylon";NA;41;0
"Unit";"Oracle";"Stargate";37;3
"Building";"Pylon";NA;43;0
"Unit";"Phoenix";"Stargate";47;2
"Building";"Assimilator";NA;48;0
"Unit";"Phoenix";"Stargate";48;2
"Building";"Forge";NA;48;0
"Building";"TwilightCouncil";NA;48;0
"Building";"Nexus";NA;43;0
"Unit";"Phoenix";"Stargate";58;2
"Building";"Pylon";NA;59;0
"Building";"Pylon";NA;59;0
"Building";"Assimilator";NA;59;0
"Unit";"Stalker";"Gateway";67;2
"Unit";"Stalker";"Gateway";67;2
"Unit";"Stalker";"Gateway";75;2
"Unit";"Stalker";"Gateway";82;2
"Unit";"Stalker";"Gateway";82;2
"Building";"Assimilator";NA;76;0
"Building";"Assimilator";NA;79;0
"Unit";"Stalker";"Gateway";89;2
"Building";"Gateway";NA;74;0
"Building";"Gateway";NA;74;0
"Building";"Gateway";NA;75;0
"Upgrade";"ProtossGroundWeaponsLevel1";"Forge";65;0
"Building";"Pylon";NA;95;0
"Building";"Pylon";NA;95;0
"Building";"Pylon";NA;95;0
"Building";"Pylon";NA;95;0
"Building";"Pylon";NA;95;0
"Building";"Pylon";NA;96;0
"Building";"Pylon";NA;97;0
"Building";"Pylon";NA;97;0
"Unit";"Stalker";"Gateway";98;2
"Unit";"Stalker";"Gateway";98;2
"Unit";"Stalker";"Gateway";98;2
"Unit";"Stalker";"Gateway";98;2
"Unit";"Stalker";"Gateway";98;2
"Unit";"Stalker";"Gateway";98;2
"Building";"Pylon";NA;97;0
"Building";"Pylon";NA;110;0
"Building";"Pylon";NA;112;0
"Unit";"Zealot";"Gateway";114;2
"Unit";"Zealot";"Gateway";114;2
"Unit";"Zealot";"Gateway";114;2
"Unit";"Zealot";"Gateway";114;2
"Unit";"Zealot";"Gateway";114;2
"Unit";"Zealot";"Gateway";114;2
"Building";"Forge";NA;110;0
"Building";"Pylon";NA;113;0
"Building";"Gateway";NA;110;0
"Building";"Gateway";NA;110;0
"Unit";"Stalker";"Gateway";126;2
"Unit";"Stalker";"Gateway";126;2
"Unit";"Stalker";"Gateway";126;2
"Unit";"Stalker";"Gateway";126;2
"Unit";"Stalker";"Gateway";126;2
"Unit";"Zealot";"Gateway";126;2
"Building";"PhotonCannon";NA;126;0
"Building";"Nexus";NA;112;0
"Unit";"Zealot";"Gateway";138;2
"Unit";"Zealot";"Gateway";138;2
"Unit";"Zealot";"Gateway";138;2
"Unit";"Zealot";"Gateway";138;2
"Unit";"Zealot";"Gateway";138;2
"Unit";"Zealot";"Gateway";138;2
"Unit";"Zealot";"Gateway";138;2
"Unit";"Zealot";"Gateway";138;2
"Upgrade";"Charge";"TwilightCouncil";113;0
"Upgrade";"ProtossGroundWeaponsLevel2";"Forge";112;0
"Unit";"Zealot";"Gateway";158;2
"Unit";"Zealot";"Gateway";158;2
"Unit";"Zealot";"Gateway";158;2
"Unit";"Zealot";"Gateway";158;2
"Unit";"Zealot";"Gateway";158;2
"Unit";"Zealot";"Gateway";158;2
"Unit";"Zealot";"Gateway";158;2
"Unit";"Zealot";"Gateway";158;2
"Upgrade";"ProtossGroundArmorsLevel1";"Forge";126;0
"Unit";"Zealot";"Gateway";174;2
"Unit";"Zealot";"Gateway";174;2
"Unit";"Zealot";"Gateway";174;2
"Unit";"Zealot";"Gateway";174;2
"Unit";"Zealot";"Gateway";174;2
"Unit";"Zealot";"Gateway";174;2
"Unit";"Zealot";"Gateway";174;2
"Unit";"Zealot";"Gateway";174;2
"Building";"PhotonCannon";NA;174;0
"Building";"Gateway";NA;174;0
"Building";"Gateway";NA;174;0
"Building";"Gateway";NA;174;0
"Unit";"Stalker";"Gateway";194;2
"Unit";"Stalker";"Gateway";194;2
"Unit";"Stalker";"Gateway";194;2
"Unit";"Stalker";"Gateway";194;2
"Unit";"Stalker";"Gateway";194;2
"Unit";"Stalker";"Gateway";194;2
"Unit";"Stalker";"Gateway";194;2
"Unit";"Zealot";"Gateway";208;2
"Building";"PhotonCannon";NA;191;0
"Building";"PhotonCannon";NA;191;0
"Building";"Pylon";NA;210;0
"Unit";"Stalker";"Gateway";210;2
"Unit";"Stalker";"Gateway";210;2
"Unit";"Stalker";"Gateway";210;2
"Unit";"Stalker";"Gateway";210;2
"Unit";"Stalker";"Gateway";210;2
"Unit";"Stalker";"Gateway";210;2
"Unit";"Stalker";"Gateway";210;2
"Unit";"Stalker";"Gateway";210;2
"Unit";"Stalker";"Gateway";210;2
"Unit";"Stalker";"Gateway";210;2
"Unit";"Stalker";"Gateway";210;2
"Building";"Nexus";NA;190;0
"Building";"RoboticsFacility";NA;198;0
"Upgrade";"ProtossGroundWeaponsLevel3";"Forge";174;0
"Building";"PhotonCannon";NA;210;0
"Building";"TemplarArchive";NA;210;0
"Building";"PhotonCannon";NA;214;0
"Building";"PhotonCannon";NA;232;0
"Upgrade";"ProtossGroundArmorsLevel2";"Forge";190;0
"Unit";"Stalker";"Gateway";237;2
"Unit";"Stalker";"Gateway";237;2
"Unit";"Stalker";"Gateway";237;2
"Unit";"Zealot";"Gateway";237;2
"Unit";"Zealot";"Gateway";237;2
"Unit";"Zealot";"Gateway";237;2
"Unit";"Zealot";"Gateway";237;2
"Unit";"Zealot";"Gateway";237;2
"Building";"RoboticsFacility";NA;210;0
"Unit";"Zealot";"Gateway";237;2
"Unit";"Zealot";"Gateway";237;2
"Unit";"Zealot";"Gateway";237;2
"Building";"Nexus";NA;210;0
"Unit";"Zealot";"Gateway";259;2
"Unit";"Zealot";"Gateway";260;2
"Unit";"Zealot";"Gateway";260;2
"Unit";"Zealot";"Gateway";260;2
"Unit";"Zealot";"Gateway";260;2
"Building";"Assimilator";NA;259;0
"Unit";"Immortal";"Robotics Facility";237;4
"Building";"Assimilator";NA;259;0
"Unit";"Immortal";"Robotics Facility";237;4
"Unit";"Zealot";"Gateway";279;2
"Unit";"Zealot";"Gateway";279;2
"Unit";"Zealot";"Gateway";279;2
"Unit";"Zealot";"Gateway";279;2
"Unit";"Zealot";"Gateway";279;2
"Unit";"Zealot";"Gateway";279;2
"Unit";"Zealot";"Gateway";293;2
"Unit";"Zealot";"Gateway";293;2
"Unit";"Zealot";"Gateway";293;2
"Unit";"Zealot";"Gateway";293;2
"Unit";"Zealot";"Gateway";293;2
"Unit";"Zealot";"Gateway";293;2
"Unit";"Zealot";"Gateway";293;2
"Unit";"Zealot";"Gateway";293;2
"Unit";"Zealot";"Gateway";293;2
"Unit";"Zealot";"Gateway";293;2
"Unit";"Immortal";"Robotics Facility";270;4
"Unit";"Immortal";"Robotics Facility";274;4
"Building";"Assimilator";NA;293;0
"Unit";"Zealot";"Gateway";323;2
"Building";"Assimilator";NA;293;0
"Unit";"Observer";"Robotics Facility";293;1
"Unit";"Observer";"Robotics Facility";293;1
"Building";"HighTemplar";NA;328;0
"Building";"HighTemplar";NA;328;0
"Building";"HighTemplar";NA;328;0
"Building";"HighTemplar";NA;328;0
"Building";"HighTemplar";NA;328;0
"Building";"HighTemplar";NA;328;0
"Building";"HighTemplar";NA;328;0
"Building";"HighTemplar";NA;328;0
"Building";"HighTemplar";NA;328;0
"Building";"HighTemplar";NA;328;0
"Building";"Stargate";NA;293;0
"Unit";"Archon";"High Templar";328;0
"Unit";"Archon";"High Templar";328;0
"Unit";"Archon";"High Templar";328;0
"Building";"RoboticsBay";NA;293;0
"Unit";"Archon";"High Templar";328;0
"Unit";"Archon";"High Templar";328;0
"Unit";"Zealot";"Gateway";328;2
"Upgrade";"ProtossShieldsLevel1";"Forge";279;0
"Unit";"Zealot";"Gateway";330;2
"Unit";"Zealot";"Gateway";330;2
"Unit";"Zealot";"Gateway";330;2
"Unit";"Zealot";"Gateway";330;2
"Unit";"Zealot";"Gateway";330;2
"Unit";"Zealot";"Gateway";330;2
"Unit";"Zealot";"Gateway";330;2
"Unit";"Zealot";"Gateway";330;2
"Unit";"Zealot";"Gateway";330;2
"Unit";"Disruptor";"Robotics Facility";330;3
"Upgrade";"ProtossGroundArmorsLevel3";"Forge";292;0
"Unit";"Disruptor";"Robotics Facility";330;3
"Building";"Assimilator";NA;348;0
"Building";"Assimilator";NA;348;0
"Building";"FleetBeacon";NA;330;0
"Unit";"Zealot";"Gateway";356;2
"Unit";"Zealot";"Gateway";356;2
"Unit";"Zealot";"Gateway";356;2
"Unit";"Zealot";"Gateway";356;2
"Unit";"Zealot";"Gateway";356;2
"Unit";"Zealot";"Gateway";356;2
"Unit";"Zealot";"Gateway";356;2
"Unit";"Zealot";"Gateway";356;2
"Unit";"Stalker";"Gateway";356;2
"Unit";"Stalker";"Gateway";356;2
"Unit";"Stalker";"Gateway";356;2
"Building";"PhotonCannon";NA;348;0
"Building";"PhotonCannon";NA;348;0
"Building";"PhotonCannon";NA;349;0
"Building";"PhotonCannon";NA;349;0
"Building";"PhotonCannon";NA;349;0
"Unit";"Disruptor";"Robotics Facility";352;3
"Unit";"Disruptor";"Robotics Facility";355;3
"Unit";"Stalker";"Gateway";384;2
"Building";"Pylon";NA;384;0
"Unit";"Stalker";"Gateway";384;2
"Unit";"Stalker";"Gateway";384;2
"Unit";"Stalker";"Gateway";384;2
"Unit";"Stalker";"Gateway";384;2
"Unit";"Stalker";"Gateway";384;2
"Unit";"Stalker";"Gateway";384;2
"Unit";"Stalker";"Gateway";384;2
"Unit";"Stalker";"Gateway";384;2
"Upgrade";"ExtendedThermalLance";"RoboticsBay";348;0
"Unit";"Stalker";"Gateway";384;2
"Unit";"Disruptor";"Robotics Facility";378;3
"Unit";"Disruptor";"Robotics Facility";381;3
"Unit";"Stalker";"Gateway";410;2
"Building";"Nexus";NA;356;0
"Building";"Stargate";NA;384;0
"Building";"Stargate";NA;384;0
"Building";"Stargate";NA;384;0
"Unit";"Tempest";"Stargate";384;4
"Building";"Assimilator";NA;416;0
"Unit";"Tempest";"Stargate";410;4
"Unit";"Tempest";"Stargate";410;4
"Building";"Assimilator";NA;416;0
"Unit";"Tempest";"Stargate";412;4
"Unit";"Tempest";"Stargate";412;4
"Building";"HighTemplar";NA;432;0
"Building";"HighTemplar";NA;432;0
"Building";"HighTemplar";NA;432;0
"Building";"HighTemplar";NA;432;0
"Unit";"Disruptor";"Robotics Facility";416;3
"Unit";"Disruptor";"Robotics Facility";416;3
"Upgrade";"ProtossAirWeaponsLevel1";"CyberneticsCore";410;0
"Unit";"Tempest";"Stargate";416;4
"Unit";"Observer";"Robotics Facility";432;1
"Upgrade";"ProtossShieldsLevel2";"Forge";410;0
"Building";"PhotonCannon";NA;432;0
"Building";"Pylon";NA;442;0
"Building";"PhotonCannon";NA;438;0
"Building";"Pylon";NA;442;0
"Building";"PhotonCannon";NA;438;0
"Unit";"Zealot";"Gateway";443;2
"Unit";"Zealot";"Gateway";443;2
"Unit";"Zealot";"Gateway";443;2
