"type";"unit_name";"on_building";"total_supply";"supply"
"Building";"Pylon";NA;13;0
"Building";"Assimilator";NA;16;0
"Building";"Gateway";NA;15;0
"Building";"Assimilator";NA;20;0
"Building";"CyberneticsCore";NA;19;0
"Building";"Pylon";NA;21;0
"Building";"Nexus";NA;19;0
"Unit";"Stalker";"Gateway";22;2
"Unit";"Stalker";"Gateway";25;2
"Building";"Pylon";NA;30;0
"Unit";"Stalker";"Gateway";33;2
"Building";"Gateway";NA;37;0
"Building";"Gateway";NA;37;0
"Building";"Pylon";NA;47;0
"Building";"Assimilator";NA;46;0
"Unit";"Stalker";"Gateway";49;2
"Unit";"Stalker";"Gateway";49;2
"Building";"TwilightCouncil";NA;45;0
"Unit";"Stalker";"Gateway";55;2
"Building";"Pylon";NA;49;0
"Unit";"Stalker";"Gateway";60;2
"Building";"Nexus";NA;43;0
"Unit";"Stalker";"Gateway";63;2
"Building";"Forge";NA;68;0
"Unit";"Sentry";"Gateway";75;2
"Unit";"Sentry";"Gateway";75;2
"Unit";"Sentry";"Gateway";76;2
"Building";"Forge";NA;69;0
"Building";"Pylon";NA;72;0
"Building";"Pylon";NA;76;0
"Building";"RoboticsFacility";NA;70;0
"Unit";"Zealot";"Gateway";84;2
"Unit";"Zealot";"Gateway";84;2
"Unit";"Zealot";"Gateway";84;2
"Building";"Pylon";NA;84;0
"Unit";"Observer";"Robotics Facility";84;1
"Building";"ShieldBattery";NA;84;0
"Building";"Pylon";NA;90;0
"Unit";"Stalker";"Gateway";91;2
"Unit";"Stalker";"Gateway";91;2
"Unit";"Stalker";"Gateway";91;2
"Building";"Gateway";NA;84;0
"Building";"Gateway";NA;84;0
"Building";"Gateway";NA;84;0
"Unit";"Stalker";"Gateway";97;2
"Unit";"Stalker";"Gateway";97;2
"Building";"Gateway";NA;84;0
"Building";"Gateway";NA;84;0
"Unit";"Zealot";"Gateway";101;2
"Unit";"Zealot";"Gateway";101;2
"Unit";"Zealot";"Gateway";101;2
"Unit";"Zealot";"Gateway";101;2
"Unit";"Immortal";"Robotics Facility";91;4
"Unit";"Zealot";"Gateway";113;2
"Unit";"Zealot";"Gateway";113;2
"Upgrade";"ProtossGroundWeaponsLevel1";"Forge";84;0
"Unit";"Zealot";"Gateway";113;2
"Upgrade";"ProtossGroundArmorsLevel1";"Forge";84;0
"Unit";"Zealot";"Gateway";113;2
"Building";"Gateway";NA;97;0
"Upgrade";"Charge";"TwilightCouncil";90;0
"Building";"Pylon";NA;121;0
"Building";"Pylon";NA;121;0
"Building";"Pylon";NA;121;0
"Unit";"Zealot";"Gateway";121;2
"Unit";"Zealot";"Gateway";121;2
"Unit";"Zealot";"Gateway";121;2
"Unit";"Zealot";"Gateway";121;2
"Unit";"Zealot";"Gateway";121;2
"Unit";"Zealot";"Gateway";121;2
"Unit";"Immortal";"Robotics Facility";109;4
"Unit";"Zealot";"Gateway";137;2
"Unit";"Zealot";"Gateway";137;2
"Building";"Gateway";NA;113;0
"Building";"Gateway";NA;113;0
"Unit";"Stalker";"Gateway";141;2
"Unit";"Stalker";"Gateway";141;2
"Unit";"Stalker";"Gateway";141;2
"Unit";"Stalker";"Gateway";141;2
"Unit";"Stalker";"Gateway";141;2
"Unit";"Stalker";"Gateway";141;2
"Unit";"Zealot";"Gateway";153;2
"Unit";"Zealot";"Gateway";153;2
"Unit";"Zealot";"Gateway";157;2
"Unit";"Zealot";"Gateway";157;2
"Unit";"Zealot";"Gateway";157;2
"Unit";"Zealot";"Gateway";157;2
"Unit";"Zealot";"Gateway";157;2
"Unit";"Zealot";"Gateway";157;2
"Unit";"Zealot";"Gateway";169;2
"Unit";"Zealot";"Gateway";169;2
"Building";"Pylon";NA;157;0
"Unit";"Zealot";"Gateway";173;2
"Unit";"Zealot";"Gateway";173;2
"Unit";"Zealot";"Gateway";173;2
"Building";"Pylon";NA;169;0
"Unit";"Zealot";"Gateway";179;2
"Unit";"Zealot";"Gateway";179;2
"Building";"Pylon";NA;173;0
"Building";"ShieldBattery";NA;173;0
"Unit";"Stalker";"Gateway";183;2
"Unit";"Stalker";"Gateway";183;2
"Unit";"Stalker";"Gateway";183;2
"Unit";"Stalker";"Gateway";183;2
"Upgrade";"ProtossGroundWeaponsLevel2";"Forge";121;0
"Unit";"Stalker";"Gateway";191;2
"Unit";"Stalker";"Gateway";191;2
"Upgrade";"ProtossGroundArmorsLevel2";"Forge";137;0
"Unit";"Zealot";"Gateway";195;2
"Unit";"Zealot";"Gateway";195;2
"Unit";"Zealot";"Gateway";195;2
"Building";"Nexus";NA;157;0
"Unit";"Zealot";"Gateway";201;2
"Unit";"Zealot";"Gateway";201;2
"Unit";"Zealot";"Gateway";201;2
"Unit";"Zealot";"Gateway";201;2
"Unit";"Stalker";"Gateway";209;2
"Unit";"Stalker";"Gateway";209;2
"Unit";"Stalker";"Gateway";209;2
"Unit";"Zealot";"Gateway";209;2
"Unit";"Zealot";"Gateway";209;2
"Unit";"Zealot";"Gateway";219;2
"Unit";"Zealot";"Gateway";219;2
"Unit";"Zealot";"Gateway";219;2
"Unit";"Zealot";"Gateway";219;2
"Unit";"Zealot";"Gateway";219;2
"Unit";"Zealot";"Gateway";219;2
"Unit";"Stalker";"Gateway";231;2
"Unit";"Stalker";"Gateway";231;2
"Unit";"Zealot";"Gateway";231;2
"Unit";"Zealot";"Gateway";237;2
"Unit";"Zealot";"Gateway";237;2
"Unit";"Zealot";"Gateway";237;2
"Unit";"Zealot";"Gateway";237;2
"Unit";"Zealot";"Gateway";237;2
"Unit";"Immortal";"Robotics Facility";219;4
"Unit";"Sentry";"Gateway";251;2
"Unit";"Zealot";"Gateway";253;2
"Unit";"Zealot";"Gateway";253;2
"Unit";"Zealot";"Gateway";253;2
"Unit";"Zealot";"Gateway";253;2
"Unit";"Zealot";"Gateway";253;2
"Unit";"Zealot";"Gateway";263;2
"Unit";"Zealot";"Gateway";263;2
"Unit";"Zealot";"Gateway";263;2
"Unit";"Zealot";"Gateway";263;2
"Unit";"Zealot";"Gateway";263;2
"Unit";"Zealot";"Gateway";263;2
"Unit";"Immortal";"Robotics Facility";237;4
"Unit";"Zealot";"Gateway";279;2
"Unit";"Zealot";"Gateway";279;2
"Unit";"Zealot";"Gateway";279;2
"Unit";"Zealot";"Gateway";279;2
"Unit";"Zealot";"Gateway";279;2
"Unit";"Zealot";"Gateway";289;2
"Unit";"Zealot";"Gateway";289;2
"Unit";"Zealot";"Gateway";289;2
"Upgrade";"ProtossGroundArmorsLevel3";"Forge";201;0
"Upgrade";"ProtossGroundWeaponsLevel3";"Forge";201;0
"Unit";"Zealot";"Gateway";295;2
"Unit";"Zealot";"Gateway";295;2
"Unit";"Zealot";"Gateway";295;2
"Unit";"Zealot";"Gateway";295;2
"Unit";"Zealot";"Gateway";295;2
"Unit";"Zealot";"Gateway";305;2
"Unit";"Immortal";"Robotics Facility";275;4
"Unit";"Zealot";"Gateway";305;2
"Unit";"Zealot";"Gateway";305;2
"Unit";"Zealot";"Gateway";305;2
"Building";"Pylon";NA;317;0
"Building";"Pylon";NA;317;0
"Unit";"Zealot";"Gateway";317;2
"Unit";"Zealot";"Gateway";317;2
"Building";"Pylon";NA;317;0
"Building";"Pylon";NA;317;0
"Building";"Pylon";NA;317;0
"Building";"Pylon";NA;317;0
"Unit";"Zealot";"Gateway";321;2
"Unit";"Zealot";"Gateway";321;2
"Unit";"Zealot";"Gateway";321;2
"Unit";"Zealot";"Gateway";321;2
"Unit";"Zealot";"Gateway";321;2
"Unit";"Zealot";"Gateway";321;2
"Unit";"Zealot";"Gateway";321;2
"Building";"Assimilator";NA;335;0
"Unit";"Stalker";"Gateway";335;2
"Unit";"Stalker";"Gateway";335;2
"Unit";"Stalker";"Gateway";335;2
"Unit";"Stalker";"Gateway";335;2
"Unit";"Stalker";"Gateway";335;2
"Building";"Assimilator";NA;335;0
"Building";"TemplarArchive";NA;335;0
"Building";"Nexus";NA;321;0
"Building";"Assimilator";NA;345;0
