"type";"unit_name";"on_building";"total_supply";"supply"
"Building";"Pylon";NA;13;0
"Building";"Assimilator";NA;16;0
"Building";"Assimilator";NA;17;0
"Building";"Gateway";NA;15;0
"Building";"Gateway";NA;18;0
"Building";"Pylon";NA;21;0
"Building";"CyberneticsCore";NA;19;0
"Unit";"Sentry";"Gateway";22;2
"Unit";"Stalker";"Gateway";21;2
"Building";"Pylon";NA;27;0
"Unit";"Stalker";"Gateway";27;2
"Unit";"Sentry";"Gateway";31;2
"Unit";"Phoenix";"Stargate";32;2
"Building";"Pylon";NA;36;0
"Unit";"Stalker";"Gateway";33;2
"Building";"RoboticsFacility";NA;32;0
"Building";"Nexus";NA;28;0
"Building";"Pylon";NA;41;0
"Unit";"Observer";"Robotics Facility";42;1
"Building";"ShieldBattery";NA;44;0
"Unit";"Sentry";"Gateway";49;2
"Building";"ShieldBattery";NA;46;0
"Unit";"Observer";"Robotics Facility";49;1
"Building";"Forge";NA;47;0
"Building";"Pylon";NA;53;0
"Building";"TwilightCouncil";NA;48;0
"Building";"Assimilator";NA;54;0
"Building";"Assimilator";NA;55;0
"Unit";"Stalker";"Gateway";62;2
"Unit";"Stalker";"Gateway";62;2
"Unit";"Immortal";"Robotics Facility";60;4
"Unit";"Adept";"Gateway";74;2
"Unit";"Adept";"Gateway";74;2
"Unit";"Immortal";"Robotics Facility";68;4
"Building";"Gateway";NA;67;0
"Building";"Gateway";NA;68;0
"Building";"Gateway";NA;68;0
"Building";"Pylon";NA;74;0
"Building";"ShieldBattery";NA;74;0
"Building";"PhotonCannon";NA;74;0
"Building";"ShieldBattery";NA;74;0
"Upgrade";"ProtossGroundWeaponsLevel1";"Forge";61;0
"Building";"TemplarArchive";NA;74;0
"Building";"HighTemplar";NA;82;0
"Unit";"Adept";"Gateway";82;2
"Upgrade";"Charge";"TwilightCouncil";67;0
"Building";"Gateway";NA;74;0
"Building";"Pylon";NA;83;0
"Building";"Pylon";NA;85;0
"Unit";"Immortal";"Robotics Facility";82;4
"Building";"Pylon";NA;85;0
"Building";"HighTemplar";NA;89;0
"Building";"HighTemplar";NA;89;0
"Building";"HighTemplar";NA;89;0
"Unit";"Zealot";"Gateway";89;2
"Unit";"Zealot";"Gateway";89;2
"Unit";"Archon";"High Templar";89;0
"Unit";"Archon";"High Templar";89;0
"Building";"Forge";NA;85;0
"Unit";"Zealot";"Gateway";94;2
"Unit";"Zealot";"Gateway";96;2
"Unit";"Zealot";"Gateway";96;2
"Unit";"Zealot";"Gateway";101;2
"Unit";"Zealot";"Gateway";101;2
"Unit";"Zealot";"Gateway";101;2
"Unit";"Immortal";"Robotics Facility";94;4
"Unit";"Phoenix";"Stargate";110;2
"Building";"PhotonCannon";NA;110;0
"Building";"PhotonCannon";NA;110;0
"Upgrade";"ProtossGroundWeaponsLevel2";"Forge";89;0
"Building";"Pylon";NA;116;0
"Building";"Pylon";NA;116;0
"Unit";"Immortal";"Robotics Facility";114;4
"Building";"Pylon";NA;116;0
"Building";"Pylon";NA;116;0
"Building";"HighTemplar";NA;120;0
"Building";"HighTemplar";NA;120;0
"Unit";"Phoenix";"Stargate";116;2
"Building";"PhotonCannon";NA;120;0
"Upgrade";"ProtossGroundArmorsLevel1";"Forge";110;0
"Unit";"Zealot";"Gateway";124;2
"Unit";"Zealot";"Gateway";124;2
"Unit";"Zealot";"Gateway";124;2
"Building";"Nexus";NA;114;0
"Unit";"Archon";"High Templar";124;0
"Building";"RoboticsBay";NA;116;0
"Building";"RoboticsFacility";NA;120;0
"Building";"ShieldBattery";NA;124;0
"Building";"ShieldBattery";NA;125;0
"Unit";"Disruptor";"Robotics Facility";135;3
"Unit";"Zealot";"Gateway";142;2
"Unit";"Zealot";"Gateway";142;2
"Unit";"Zealot";"Gateway";142;2
"Unit";"Zealot";"Gateway";142;2
"Unit";"Zealot";"Gateway";142;2
"Unit";"Zealot";"Gateway";142;2
"Unit";"Disruptor";"Robotics Facility";135;3
"Unit";"Disruptor";"Robotics Facility";142;3
"Unit";"Disruptor";"Robotics Facility";160;3
"Unit";"Phoenix";"Stargate";163;2
"Building";"Assimilator";NA;166;0
"Unit";"Disruptor";"Robotics Facility";160;3
"Building";"Assimilator";NA;169;0
"Building";"Pylon";NA;172;0
"Upgrade";"ProtossGroundWeaponsLevel3";"Forge";135;0
"Building";"HighTemplar";NA;183;0
"Building";"HighTemplar";NA;183;0
"Building";"Pylon";NA;180;0
"Building";"HighTemplar";NA;186;0
"Unit";"Archon";"High Templar";186;0
"Building";"Pylon";NA;186;0
"Building";"Pylon";NA;186;0
"Unit";"Immortal";"Robotics Facility";180;4
"Unit";"Disruptor";"Robotics Facility";183;3
"Building";"Nexus";NA;169;0
"Unit";"Zealot";"Gateway";196;2
"Unit";"Zealot";"Gateway";196;2
"Unit";"Zealot";"Gateway";196;2
"Unit";"Zealot";"Gateway";200;2
"Upgrade";"ProtossShieldsLevel1";"Forge";172;0
"Building";"Stargate";NA;188;0
"Building";"PhotonCannon";NA;196;0
"Building";"Gateway";NA;195;0
"Building";"Gateway";NA;195;0
"Building";"Gateway";NA;195;0
"Unit";"Zealot";"Gateway";212;2
"Unit";"Zealot";"Gateway";212;2
"Unit";"Zealot";"Gateway";212;2
"Building";"HighTemplar";NA;218;0
"Building";"HighTemplar";NA;218;0
"Building";"HighTemplar";NA;218;0
"Unit";"Disruptor";"Robotics Facility";208;3
"Unit";"Disruptor";"Robotics Facility";208;3
"Building";"Pylon";NA;219;0
"Unit";"Archon";"High Templar";228;0
"Unit";"Zealot";"Gateway";228;2
"Unit";"Zealot";"Gateway";228;2
"Unit";"Zealot";"Gateway";228;2
"Building";"Assimilator";NA;219;0
"Building";"Assimilator";NA;225;0
"Unit";"Disruptor";"Robotics Facility";219;3
"Unit";"Disruptor";"Robotics Facility";222;3
"Building";"HighTemplar";NA;242;0
"Building";"HighTemplar";NA;242;0
"Building";"HighTemplar";NA;242;0
"Building";"HighTemplar";NA;242;0
"Building";"HighTemplar";NA;242;0
"Building";"PhotonCannon";NA;235;0
"Building";"ShieldBattery";NA;235;0
"Building";"PhotonCannon";NA;236;0
"Unit";"Archon";"High Templar";242;0
"Unit";"Archon";"High Templar";242;0
"Building";"Pylon";NA;242;0
"Building";"HighTemplar";NA;242;0
"Unit";"Zealot";"Gateway";242;2
"Building";"Pylon";NA;242;0
"Unit";"Disruptor";"Robotics Facility";242;3
"Building";"Pylon";NA;242;0
"Building";"HighTemplar";NA;247;0
"Building";"HighTemplar";NA;247;0
"Building";"Pylon";NA;242;0
"Building";"PhotonCannon";NA;242;0
"Building";"PhotonCannon";NA;242;0
"Unit";"Archon";"High Templar";247;0
"Unit";"Oracle";"Stargate";242;3
"Building";"PhotonCannon";NA;247;0
"Building";"PhotonCannon";NA;247;0
"Unit";"Zealot";"Gateway";250;2
"Unit";"Zealot";"Gateway";250;2
"Unit";"Zealot";"Gateway";250;2
"Unit";"Immortal";"Robotics Facility";247;4
"Unit";"Zealot";"Gateway";256;2
"Unit";"Zealot";"Gateway";256;2
"Unit";"Zealot";"Gateway";256;2
"Unit";"Zealot";"Gateway";256;2
"Unit";"Archon";"High Templar";250;0
"Unit";"Zealot";"Gateway";268;2
"Unit";"Zealot";"Gateway";268;2
"Building";"Nexus";NA;242;0
"Unit";"Archon";"High Templar";272;0
"Unit";"Zealot";"Gateway";272;2
"Unit";"Zealot";"Gateway";272;2
"Unit";"Zealot";"Gateway";276;2
"Unit";"Zealot";"Gateway";276;2
"Unit";"Zealot";"Gateway";276;2
"Unit";"Zealot";"Gateway";276;2
"Unit";"Disruptor";"Robotics Facility";268;3
"Unit";"Disruptor";"Robotics Facility";268;3
"Unit";"Stalker";"Gateway";282;2
"Building";"DarkShrine";NA;247;0
"Unit";"Zealot";"Gateway";296;2
"Unit";"Zealot";"Gateway";296;2
"Unit";"Zealot";"Gateway";296;2
"Unit";"Zealot";"Gateway";296;2
"Unit";"Zealot";"Gateway";296;2
"Unit";"Zealot";"Gateway";296;2
"Unit";"Zealot";"Gateway";296;2
"Unit";"Zealot";"Gateway";296;2
"Unit";"Stalker";"Gateway";312;2
"Unit";"Disruptor";"Robotics Facility";284;3
"Unit";"Disruptor";"Robotics Facility";287;3
"Building";"HighTemplar";NA;321;0
"Building";"HighTemplar";NA;321;0
"Building";"HighTemplar";NA;321;0
"Building";"HighTemplar";NA;321;0
"Unit";"Archon";"High Templar";321;0
"Unit";"Zealot";"Gateway";321;2
"Unit";"Zealot";"Gateway";321;2
"Building";"PhotonCannon";NA;320;0
"Building";"PhotonCannon";NA;320;0
"Unit";"Disruptor";"Robotics Facility";314;3
"Unit";"Disruptor";"Robotics Facility";317;3
"Building";"Assimilator";NA;321;0
"Unit";"Stalker";"Gateway";331;2
"Unit";"Stalker";"Gateway";331;2
"Unit";"Stalker";"Gateway";331;2
"Unit";"Stalker";"Gateway";331;2
"Unit";"Stalker";"Gateway";331;2
"Unit";"Stalker";"Gateway";331;2
"Unit";"Immortal";"Robotics Facility";328;4
"Unit";"Stalker";"Gateway";347;2
"Unit";"Stalker";"Gateway";347;2
"Unit";"Stalker";"Gateway";347;2
"Unit";"Stalker";"Gateway";347;2
"Unit";"Stalker";"Gateway";347;2
"Unit";"Stalker";"Gateway";347;2
"Unit";"Observer";"Robotics Facility";343;1
"Unit";"Immortal";"Robotics Facility";343;4
"Building";"Gateway";NA;343;0
"Building";"Gateway";NA;343;0
"Building";"Gateway";NA;343;0
"Building";"Gateway";NA;343;0
"Building";"Gateway";NA;343;0
