"type";"unit_name";"on_building";"total_supply";"supply"
"Building";"Pylon";NA;13;0
"Building";"Assimilator";NA;16;0
"Building";"Assimilator";NA;17;0
"Building";"Gateway";NA;14;0
"Building";"Gateway";NA;18;0
"Building";"Pylon";NA;21;0
"Building";"CyberneticsCore";NA;20;0
"Building";"Pylon";NA;23;0
"Unit";"Sentry";"Gateway";23;2
"Unit";"Stalker";"Gateway";23;2
"Unit";"Sentry";"Gateway";25;2
"Building";"Pylon";NA;30;0
"Unit";"Stalker";"Gateway";29;2
"Building";"ShieldBattery";NA;32;0
"Unit";"Phoenix";"Stargate";34;2
"Building";"ShieldBattery";NA;35;0
"Unit";"Phoenix";"Stargate";39;2
"Building";"Nexus";NA;32;0
"Unit";"Stalker";"Gateway";44;2
"Unit";"Stalker";"Gateway";44;2
"Building";"RoboticsFacility";NA;36;0
"Building";"Pylon";NA;48;0
"Unit";"Stalker";"Gateway";53;2
"Unit";"Stalker";"Gateway";53;2
"Unit";"Observer";"Robotics Facility";51;1
"Unit";"Stalker";"Gateway";62;2
"Unit";"Stalker";"Gateway";62;2
"Building";"Forge";NA;53;0
"Building";"TwilightCouncil";NA;62;0
"Building";"Pylon";NA;70;0
"Building";"Pylon";NA;71;0
"Building";"Assimilator";NA;73;0
"Building";"Assimilator";NA;73;0
"Unit";"Phoenix";"Stargate";73;2
"Building";"Pylon";NA;75;0
"Building";"Pylon";NA;76;0
"Building";"Gateway";NA;71;0
"Building";"Gateway";NA;71;0
"Building";"Pylon";NA;82;0
"Upgrade";"ProtossGroundWeaponsLevel1";"Forge";70;0
"Building";"TemplarArchive";NA;82;0
"Building";"Pylon";NA;84;0
"Building";"Pylon";NA;85;0
"Building";"HighTemplar";NA;85;0
"Building";"HighTemplar";NA;85;0
"Building";"HighTemplar";NA;85;0
"Building";"HighTemplar";NA;85;0
"Upgrade";"Charge";"TwilightCouncil";77;0
"Building";"Gateway";NA;84;0
"Building";"Gateway";NA;84;0
"Building";"PhotonCannon";NA;85;0
"Building";"Nexus";NA;82;0
"Unit";"Archon";"High Templar";86;0
"Unit";"Archon";"High Templar";86;0
"Unit";"Phoenix";"Stargate";85;2
"Building";"HighTemplar";NA;89;0
"Building";"HighTemplar";NA;89;0
"Unit";"Immortal";"Robotics Facility";85;4
"Unit";"Zealot";"Gateway";89;2
"Building";"Nexus";NA;85;0
"Unit";"Archon";"High Templar";89;0
"Building";"PhotonCannon";NA;87;0
"Unit";"Zealot";"Gateway";96;2
"Unit";"Zealot";"Gateway";96;2
"Unit";"Zealot";"Gateway";96;2
"Building";"PhotonCannon";NA;87;0
"Building";"PhotonCannon";NA;87;0
"Unit";"Immortal";"Robotics Facility";87;4
"Building";"ShieldBattery";NA;89;0
"Building";"HighTemplar";NA;102;0
"Building";"HighTemplar";NA;102;0
"Unit";"Zealot";"Gateway";109;2
"Unit";"Archon";"High Templar";106;0
"Unit";"Zealot";"Gateway";109;2
"Unit";"Zealot";"Gateway";109;2
"Unit";"Zealot";"Gateway";109;2
"Upgrade";"ProtossGroundWeaponsLevel2";"Forge";85;0
"Unit";"Phoenix";"Stargate";109;2
"Unit";"Immortal";"Robotics Facility";102;4
"Unit";"Zealot";"Gateway";130;2
"Unit";"Zealot";"Gateway";130;2
"Unit";"Zealot";"Gateway";130;2
"Building";"ShieldBattery";NA;120;0
"Unit";"Zealot";"Gateway";139;2
"Unit";"Zealot";"Gateway";139;2
"Unit";"Zealot";"Gateway";139;2
"Building";"Assimilator";NA;129;0
"Building";"Assimilator";NA;130;0
"Building";"HighTemplar";NA;145;0
"Building";"HighTemplar";NA;145;0
"Unit";"Zealot";"Gateway";145;2
"Unit";"Phoenix";"Stargate";136;2
"Unit";"Archon";"High Templar";147;0
"Unit";"Immortal";"Robotics Facility";145;4
"Building";"ShieldBattery";NA;145;0
"Building";"Pylon";NA;149;0
"Building";"Pylon";NA;149;0
"Building";"Pylon";NA;149;0
"Building";"Pylon";NA;149;0
"Building";"HighTemplar";NA;153;0
"Building";"HighTemplar";NA;153;0
"Building";"Gateway";NA;145;0
"Unit";"Zealot";"Gateway";153;2
"Unit";"Zealot";"Gateway";153;2
"Unit";"Zealot";"Gateway";153;2
"Unit";"Zealot";"Gateway";153;2
"Building";"Gateway";NA;145;0
"Unit";"Archon";"High Templar";161;0
"Unit";"Zealot";"Gateway";161;2
"Unit";"Zealot";"Gateway";161;2
"Unit";"Zealot";"Gateway";161;2
"Unit";"Zealot";"Gateway";161;2
"Unit";"Zealot";"Gateway";161;2
"Unit";"Immortal";"Robotics Facility";153;4
"Unit";"Phoenix";"Stargate";161;2
"Building";"Pylon";NA;161;0
"Building";"Assimilator";NA;161;0
"Building";"Assimilator";NA;161;0
"Building";"HighTemplar";NA;181;0
"Building";"Assimilator";NA;161;0
"Building";"HighTemplar";NA;181;0
"Unit";"Zealot";"Gateway";181;2
"Building";"PhotonCannon";NA;161;0
"Upgrade";"ProtossGroundWeaponsLevel3";"Forge";130;0
"Building";"PhotonCannon";NA;164;0
"Unit";"Zealot";"Gateway";183;2
"Unit";"Zealot";"Gateway";183;2
"Unit";"Zealot";"Gateway";183;2
"Unit";"Zealot";"Gateway";183;2
"Unit";"Zealot";"Gateway";183;2
"Unit";"Archon";"High Templar";183;0
"Building";"Gateway";NA;161;0
"Building";"Gateway";NA;161;0
"Building";"Pylon";NA;193;0
"Building";"Pylon";NA;193;0
"Unit";"Zealot";"Gateway";196;2
"Building";"HighTemplar";NA;200;0
"Building";"HighTemplar";NA;200;0
"Building";"HighTemplar";NA;200;0
"Building";"HighTemplar";NA;200;0
"Building";"HighTemplar";NA;200;0
"Building";"HighTemplar";NA;200;0
"Building";"HighTemplar";NA;200;0
"Building";"HighTemplar";NA;200;0
"Building";"HighTemplar";NA;200;0
"Building";"HighTemplar";NA;200;0
"Building";"Gateway";NA;200;0
"Building";"Gateway";NA;200;0
"Upgrade";"ProtossShieldsLevel1";"Forge";193;0
"Building";"Gateway";NA;200;0
"Building";"Gateway";NA;200;0
"Unit";"Archon";"High Templar";200;0
"Unit";"Archon";"High Templar";200;0
"Unit";"Archon";"High Templar";200;0
"Unit";"Archon";"High Templar";200;0
"Unit";"Archon";"High Templar";200;0
"Unit";"Immortal";"Robotics Facility";200;4
"Building";"Gateway";NA;200;0
"Unit";"Zealot";"Gateway";204;2
"Building";"Gateway";NA;200;0
"Unit";"Zealot";"Gateway";204;2
"Unit";"Zealot";"Gateway";204;2
"Unit";"Zealot";"Gateway";204;2
"Unit";"Zealot";"Gateway";204;2
"Unit";"Zealot";"Gateway";204;2
"Building";"Gateway";NA;200;0
"Unit";"Zealot";"Gateway";204;2
"Unit";"Zealot";"Gateway";204;2
"Unit";"Zealot";"Gateway";204;2
"Unit";"Zealot";"Gateway";204;2
"Building";"Gateway";NA;200;0
"Building";"Pylon";NA;204;0
"Building";"Pylon";NA;204;0
"Unit";"Zealot";"Gateway";224;2
"Unit";"Zealot";"Gateway";224;2
"Unit";"Zealot";"Gateway";224;2
"Unit";"Zealot";"Gateway";224;2
"Building";"Pylon";NA;204;0
"Unit";"Zealot";"Gateway";232;2
"Unit";"Zealot";"Gateway";232;2
"Unit";"Zealot";"Gateway";232;2
"Unit";"Zealot";"Gateway";232;2
"Unit";"Immortal";"Robotics Facility";204;4
"Unit";"Zealot";"Gateway";244;2
"Unit";"Zealot";"Gateway";244;2
"Unit";"Zealot";"Gateway";244;2
"Unit";"Zealot";"Gateway";244;2
"Unit";"Zealot";"Gateway";244;2
"Unit";"Zealot";"Gateway";244;2
"Unit";"Zealot";"Gateway";244;2
"Unit";"Zealot";"Gateway";244;2
"Unit";"Zealot";"Gateway";244;2
"Building";"HighTemplar";NA;262;0
"Building";"HighTemplar";NA;262;0
"Building";"HighTemplar";NA;262;0
"Building";"HighTemplar";NA;262;0
"Unit";"Archon";"High Templar";262;0
"Unit";"Zealot";"Gateway";262;2
"Unit";"Archon";"High Templar";262;0
"Unit";"Zealot";"Gateway";262;2
"Unit";"Zealot";"Gateway";262;2
"Unit";"Zealot";"Gateway";262;2
"Unit";"Zealot";"Gateway";262;2
"Unit";"Zealot";"Gateway";262;2
"Building";"Nexus";NA;204;0
"Unit";"Immortal";"Robotics Facility";262;4
"Building";"HighTemplar";NA;274;0
"Building";"HighTemplar";NA;274;0
"Unit";"Zealot";"Gateway";274;2
"Unit";"Zealot";"Gateway";274;2
"Unit";"Zealot";"Gateway";274;2
"Unit";"Zealot";"Gateway";274;2
"Unit";"Archon";"High Templar";286;0
"Building";"DarkShrine";NA;230;0
"Unit";"Zealot";"Gateway";286;2
"Unit";"Zealot";"Gateway";286;2
"Unit";"Zealot";"Gateway";286;2
"Unit";"Zealot";"Gateway";286;2
"Unit";"Zealot";"Gateway";286;2
"Unit";"Zealot";"Gateway";286;2
"Unit";"Zealot";"Gateway";286;2
"Unit";"Zealot";"Gateway";286;2
"Unit";"Zealot";"Gateway";286;2
"Upgrade";"ProtossShieldsLevel2";"Forge";204;0
"Unit";"Zealot";"Gateway";304;2
"Unit";"Zealot";"Gateway";304;2
"Unit";"Zealot";"Gateway";304;2
"Unit";"Zealot";"Gateway";304;2
"Unit";"Zealot";"Gateway";312;2
"Unit";"Zealot";"Gateway";312;2
"Unit";"Zealot";"Gateway";312;2
"Building";"HighTemplar";NA;318;0
"Building";"HighTemplar";NA;318;0
"Building";"HighTemplar";NA;318;0
"Building";"HighTemplar";NA;318;0
"Building";"HighTemplar";NA;318;0
"Building";"HighTemplar";NA;318;0
"Building";"Assimilator";NA;318;0
