"type";"unit_name";"on_building";"total_supply";"supply"
"Building";"Pylon";NA;13;0
"Building";"Assimilator";NA;16;0
"Building";"Assimilator";NA;16;0
"Building";"Gateway";NA;15;0
"Building";"Gateway";NA;18;0
"Building";"Pylon";NA;20;0
"Building";"CyberneticsCore";NA;19;0
"Unit";"Stalker";"Gateway";21;2
"Unit";"Stalker";"Gateway";21;2
"Building";"Pylon";NA;27;0
"Unit";"Stalker";"Gateway";23;2
"Unit";"Stalker";"Gateway";23;2
"Building";"Nexus";NA;27;0
"Building";"Pylon";NA;33;0
"Building";"RoboticsFacility";NA;32;0
"Building";"ShieldBattery";NA;34;0
"Unit";"Stalker";"Gateway";37;2
"Unit";"Stalker";"Gateway";37;2
"Unit";"Observer";"Robotics Facility";35;1
"Building";"TwilightCouncil";NA;42;0
"Building";"Gateway";NA;43;0
"Unit";"Immortal";"Robotics Facility";44;4
"Unit";"Stalker";"Gateway";54;2
"Building";"Pylon";NA;59;0
"Unit";"Observer";"Robotics Facility";60;1
"Building";"Assimilator";NA;65;0
"Building";"Assimilator";NA;66;0
"Building";"TemplarArchive";NA;63;0
"Building";"HighTemplar";NA;70;0
"Building";"HighTemplar";NA;70;0
"Building";"HighTemplar";NA;70;0
"Building";"HighTemplar";NA;81;0
"Building";"HighTemplar";NA;81;0
"Building";"HighTemplar";NA;81;0
"Building";"Pylon";NA;79;0
"Building";"Pylon";NA;83;0
"Building";"Pylon";NA;83;0
"Upgrade";"Charge";"TwilightCouncil";76;0
"Building";"HighTemplar";NA;85;0
"Building";"HighTemplar";NA;85;0
"Unit";"Zealot";"Gateway";85;2
"Building";"Gateway";NA;81;0
"Unit";"Observer";"Robotics Facility";83;1
"Building";"Gateway";NA;81;0
"Unit";"Archon";"High Templar";87;0
"Building";"Forge";NA;83;0
"Building";"Gateway";NA;81;0
"Building";"Nexus";NA;79;0
"Unit";"Observer";"Robotics Facility";89;1
"Building";"PhotonCannon";NA;93;0
"Building";"PhotonCannon";NA;93;0
"Building";"PhotonCannon";NA;94;0
"Building";"PhotonCannon";NA;94;0
"Building";"HighTemplar";NA;101;0
"Building";"HighTemplar";NA;101;0
"Building";"Gateway";NA;92;0
"Building";"HighTemplar";NA;101;0
"Building";"HighTemplar";NA;101;0
"Unit";"Zealot";"Gateway";101;2
"Unit";"Zealot";"Gateway";101;2
"Building";"Gateway";NA;93;0
"Building";"Gateway";NA;93;0
"Building";"Assimilator";NA;99;0
"Unit";"Archon";"High Templar";101;0
"Unit";"Archon";"High Templar";102;0
"Building";"Assimilator";NA;99;0
"Unit";"Immortal";"Robotics Facility";97;4
"Building";"Pylon";NA;107;0
"Building";"Pylon";NA;107;0
"Unit";"Zealot";"Gateway";112;2
"Unit";"Zealot";"Gateway";112;2
"Building";"Pylon";NA;107;0
"Unit";"Zealot";"Gateway";116;2
"Unit";"Zealot";"Gateway";116;2
"Unit";"Zealot";"Gateway";116;2
"Unit";"Zealot";"Gateway";116;2
"Building";"PhotonCannon";NA;107;0
"Upgrade";"ProtossGroundWeaponsLevel1";"Forge";94;0
"Building";"PhotonCannon";NA;107;0
"Unit";"Zealot";"Gateway";127;2
"Unit";"Zealot";"Gateway";127;2
"Building";"Pylon";NA;116;0
"Building";"Pylon";NA;116;0
"Unit";"Archon";"High Templar";131;0
"Unit";"Zealot";"Gateway";131;2
"Unit";"Zealot";"Gateway";131;2
"Unit";"Zealot";"Gateway";131;2
"Unit";"Zealot";"Gateway";137;2
"Unit";"Zealot";"Gateway";137;2
"Unit";"Zealot";"Gateway";137;2
"Unit";"Zealot";"Gateway";137;2
"Unit";"Zealot";"Gateway";137;2
"Unit";"Zealot";"Gateway";137;2
"Building";"HighTemplar";NA;149;0
"Building";"HighTemplar";NA;149;0
"Building";"Pylon";NA;149;0
"Unit";"Zealot";"Gateway";149;2
"Unit";"Zealot";"Gateway";149;2
"Unit";"Zealot";"Gateway";149;2
"Unit";"Zealot";"Gateway";149;2
"Unit";"Zealot";"Gateway";149;2
"Unit";"Zealot";"Gateway";149;2
"Unit";"Zealot";"Gateway";149;2
"Unit";"Archon";"High Templar";149;0
"Building";"HighTemplar";NA;163;0
"Building";"HighTemplar";NA;163;0
"Unit";"Observer";"Robotics Facility";153;1
"Building";"HighTemplar";NA;163;0
"Building";"HighTemplar";NA;163;0
"Building";"HighTemplar";NA;163;0
"Building";"HighTemplar";NA;163;0
"Unit";"Zealot";"Gateway";163;2
"Unit";"Archon";"High Templar";164;0
"Unit";"Archon";"High Templar";164;0
"Unit";"Archon";"High Templar";164;0
"Unit";"Zealot";"Gateway";166;2
"Unit";"Zealot";"Gateway";166;2
"Unit";"Zealot";"Gateway";166;2
"Unit";"Zealot";"Gateway";166;2
"Unit";"Zealot";"Gateway";166;2
"Unit";"Zealot";"Gateway";166;2
"Unit";"Zealot";"Gateway";166;2
"Unit";"Zealot";"Gateway";166;2
"Unit";"Zealot";"Gateway";166;2
"Building";"Pylon";NA;166;0
"Building";"Pylon";NA;166;0
"Unit";"Immortal";"Robotics Facility";166;4
"Unit";"Zealot";"Gateway";188;2
"Unit";"Zealot";"Gateway";188;2
"Unit";"Zealot";"Gateway";188;2
"Unit";"Zealot";"Gateway";188;2
"Unit";"Zealot";"Gateway";188;2
"Building";"Pylon";NA;184;0
"Building";"Pylon";NA;184;0
"Upgrade";"ProtossGroundArmorsLevel1";"Forge";163;0
"Unit";"Zealot";"Gateway";198;2
"Unit";"Zealot";"Gateway";198;2
"Unit";"Zealot";"Gateway";202;2
"Building";"Pylon";NA;184;0
"Unit";"Zealot";"Gateway";202;2
"Building";"Pylon";NA;184;0
"Building";"HighTemplar";NA;206;0
"Building";"HighTemplar";NA;206;0
"Building";"HighTemplar";NA;206;0
"Building";"HighTemplar";NA;206;0
"Unit";"Zealot";"Gateway";206;2
"Unit";"Zealot";"Gateway";206;2
"Unit";"Zealot";"Gateway";206;2
"Building";"HighTemplar";NA;206;0
"Building";"HighTemplar";NA;206;0
"Unit";"Archon";"High Templar";206;0
"Unit";"Archon";"High Templar";206;0
"Unit";"Archon";"High Templar";212;0
"Building";"Nexus";NA;184;0
"Unit";"Zealot";"Gateway";212;2
"Unit";"Zealot";"Gateway";212;2
"Unit";"Zealot";"Gateway";212;2
"Building";"HighTemplar";NA;218;0
"Building";"HighTemplar";NA;218;0
"Building";"HighTemplar";NA;218;0
"Building";"HighTemplar";NA;218;0
"Building";"HighTemplar";NA;218;0
"Building";"HighTemplar";NA;218;0
"Unit";"Archon";"High Templar";218;0
"Unit";"Archon";"High Templar";218;0
"Unit";"Archon";"High Templar";220;0
"Unit";"Zealot";"Gateway";223;2
"Unit";"Zealot";"Gateway";223;2
"Unit";"Zealot";"Gateway";223;2
"Unit";"Observer";"Robotics Facility";222;1
"Unit";"Zealot";"Gateway";230;2
"Unit";"Zealot";"Gateway";230;2
"Unit";"Zealot";"Gateway";230;2
"Unit";"Zealot";"Gateway";230;2
"Unit";"Zealot";"Gateway";230;2
"Unit";"Zealot";"Gateway";230;2
"Unit";"Observer";"Robotics Facility";223;1
"Building";"PhotonCannon";NA;223;0
"Building";"PhotonCannon";NA;223;0
"Building";"PhotonCannon";NA;223;0
"Unit";"Zealot";"Gateway";243;2
"Unit";"Zealot";"Gateway";243;2
"Unit";"Zealot";"Gateway";243;2
"Upgrade";"ProtossGroundWeaponsLevel2";"Forge";206;0
"Building";"ShieldBattery";NA;229;0
"Building";"ShieldBattery";NA;229;0
"Building";"PhotonCannon";NA;230;0
"Building";"PhotonCannon";NA;230;0
"Building";"HighTemplar";NA;249;0
"Building";"HighTemplar";NA;249;0
"Building";"HighTemplar";NA;249;0
"Building";"HighTemplar";NA;249;0
"Building";"HighTemplar";NA;249;0
"Building";"HighTemplar";NA;249;0
"Unit";"Zealot";"Gateway";249;2
"Unit";"Zealot";"Gateway";249;2
"Unit";"Zealot";"Gateway";249;2
"Building";"Assimilator";NA;249;0
"Building";"Assimilator";NA;249;0
"Unit";"Archon";"High Templar";249;0
"Unit";"Archon";"High Templar";249;0
"Unit";"Archon";"High Templar";249;0
"Building";"Stargate";NA;249;0
"Unit";"Zealot";"Gateway";255;2
"Unit";"Zealot";"Gateway";255;2
"Unit";"Zealot";"Gateway";255;2
"Unit";"Zealot";"Gateway";255;2
"Unit";"Zealot";"Gateway";255;2
"Unit";"Zealot";"Gateway";255;2
"Unit";"Zealot";"Gateway";255;2
"Unit";"Zealot";"Gateway";255;2
"Unit";"Stalker";"Gateway";271;2
"Unit";"Observer";"Robotics Facility";271;1
"Unit";"Stalker";"Gateway";273;2
"Unit";"Stalker";"Gateway";274;2
"Unit";"Stalker";"Gateway";274;2
"Unit";"Stalker";"Gateway";274;2
"Unit";"Stalker";"Gateway";274;2
"Unit";"Stalker";"Gateway";274;2
"Unit";"Stalker";"Gateway";274;2
"Unit";"Stalker";"Gateway";274;2
"Building";"Stargate";NA;255;0
"Building";"Stargate";NA;255;0
"Building";"Stargate";NA;255;0
