"type";"unit_name";"on_building";"total_supply";"supply"
"Building";"Pylon";NA;13;0
"Building";"Assimilator";NA;15;0
"Building";"Assimilator";NA;16;0
"Building";"Gateway";NA;14;0
"Building";"Gateway";NA;18;0
"Building";"CyberneticsCore";NA;19;0
"Building";"Pylon";NA;21;0
"Building";"Pylon";NA;23;0
"Unit";"Stalker";"Gateway";22;2
"Unit";"Stalker";"Gateway";22;2
"Building";"Stargate";NA;28;0
"Unit";"Phoenix";"Stargate";28;2
"Building";"Nexus";NA;28;0
"Building";"Assimilator";NA;30;0
"Unit";"Phoenix";"Stargate";30;2
"Unit";"Phoenix";"Stargate";34;2
"Building";"ShieldBattery";NA;34;0
"Building";"Stargate";NA;33;0
"Building";"Assimilator";NA;38;0
"Building";"ShieldBattery";NA;42;0
"Unit";"Phoenix";"Stargate";44;2
"Unit";"Phoenix";"Stargate";46;2
"Unit";"Phoenix";"Stargate";46;2
"Unit";"Phoenix";"Stargate";48;2
"Building";"Pylon";NA;52;0
"Building";"Pylon";NA;57;0
"Building";"Pylon";NA;57;0
"Unit";"Phoenix";"Stargate";57;2
"Building";"Stargate";NA;52;0
"Unit";"Phoenix";"Stargate";57;2
"Unit";"Phoenix";"Stargate";58;2
"Unit";"Phoenix";"Stargate";63;2
"Building";"FleetBeacon";NA;61;0
"Unit";"Phoenix";"Stargate";63;2
"Building";"Pylon";NA;65;0
"Unit";"Phoenix";"Stargate";65;2
"Unit";"Phoenix";"Stargate";69;2
"Unit";"Phoenix";"Stargate";75;2
"Building";"Pylon";NA;77;0
"Unit";"Phoenix";"Stargate";77;2
"Unit";"Phoenix";"Stargate";79;2
"Building";"Pylon";NA;85;0
"Unit";"Phoenix";"Stargate";87;2
"Building";"RoboticsFacility";NA;87;0
"Unit";"Phoenix";"Stargate";90;2
"Unit";"Phoenix";"Stargate";90;2
"Unit";"Phoenix";"Stargate";90;2
"Building";"Nexus";NA;85;0
"Unit";"Phoenix";"Stargate";90;2
"Unit";"Phoenix";"Stargate";92;2
"Unit";"Phoenix";"Stargate";96;2
"Upgrade";"ProtossAirWeaponsLevel1";"CyberneticsCore";87;0
"Unit";"Phoenix";"Stargate";96;2
"Unit";"Phoenix";"Stargate";102;2
"Building";"Assimilator";NA;105;0
"Unit";"Immortal";"Robotics Facility";96;4
"Building";"Pylon";NA;107;0
"Building";"Assimilator";NA;107;0
"Building";"Pylon";NA;112;0
"Unit";"Immortal";"Robotics Facility";112;4
"Building";"Pylon";NA;124;0
"Building";"Nexus";NA;112;0
"Unit";"Carrier";"Stargate";112;6
"Building";"Gateway";NA;126;0
"Building";"Gateway";NA;126;0
"Unit";"Carrier";"Stargate";119;6
"Unit";"Observer";"Robotics Facility";126;1
"Building";"Gateway";NA;126;0
"Building";"Gateway";NA;126;0
"Building";"Assimilator";NA;136;0
"Building";"Pylon";NA;144;0
"Building";"Assimilator";NA;143;0
"Building";"Pylon";NA;144;0
"Unit";"Carrier";"Stargate";126;6
"Upgrade";"ProtossAirWeaponsLevel2";"CyberneticsCore";126;0
"Unit";"Carrier";"Stargate";126;6
"Building";"Pylon";NA;162;0
"Building";"ShieldBattery";NA;155;0
"Unit";"Phoenix";"Stargate";156;2
"Building";"ShieldBattery";NA;155;0
"Building";"ShieldBattery";NA;162;0
"Unit";"Carrier";"Stargate";144;6
"Building";"Pylon";NA;164;0
"Unit";"Sentry";"Gateway";170;2
"Unit";"Sentry";"Gateway";170;2
"Unit";"Phoenix";"Stargate";162;2
"Building";"ShieldBattery";NA;162;0
"Unit";"Mothership";"Mothership Core";152;6
"Building";"ShieldBattery";NA;164;0
"Building";"ShieldBattery";NA;164;0
"Unit";"Carrier";"Stargate";146;6
"Building";"TwilightCouncil";NA;170;0
"Building";"Forge";NA;194;0
"Unit";"Carrier";"Stargate";164;6
"Building";"TemplarArchive";NA;192;0
"Unit";"Carrier";"Stargate";178;6
"Unit";"Carrier";"Stargate";178;6
"Building";"HighTemplar";NA;218;0
"Upgrade";"ProtossAirWeaponsLevel3";"CyberneticsCore";164;0
"Building";"HighTemplar";NA;218;0
"Building";"HighTemplar";NA;218;0
"Building";"HighTemplar";NA;218;0
"Unit";"Archon";"High Templar";218;0
"Unit";"Archon";"High Templar";218;0
"Building";"PhotonCannon";NA;204;0
"Building";"HighTemplar";NA;220;0
"Building";"HighTemplar";NA;220;0
"Building";"PhotonCannon";NA;204;0
"Unit";"Archon";"High Templar";220;0
"Building";"HighTemplar";NA;221;0
"Building";"HighTemplar";NA;221;0
"Building";"HighTemplar";NA;221;0
"Building";"HighTemplar";NA;221;0
"Building";"PhotonCannon";NA;220;0
"Unit";"Carrier";"Stargate";194;6
"Unit";"Archon";"High Templar";224;0
"Building";"PhotonCannon";NA;220;0
"Unit";"Archon";"High Templar";224;0
"Upgrade";"Charge";"TwilightCouncil";204;0
"Building";"Pylon";NA;224;0
"Building";"Pylon";NA;224;0
"Building";"Pylon";NA;224;0
"Unit";"Carrier";"Stargate";204;6
"Unit";"Carrier";"Stargate";204;6
"Building";"HighTemplar";NA;230;0
"Building";"HighTemplar";NA;230;0
"Unit";"Archon";"High Templar";242;0
"Unit";"Observer";"Robotics Facility";230;1
"Unit";"Oracle";"Stargate";230;3
"Upgrade";"ProtossShieldsLevel1";"Forge";220;0
"Building";"Pylon";NA;244;0
"Building";"Pylon";NA;244;0
"Building";"Pylon";NA;247;0
"Unit";"Observer";"Robotics Facility";244;1
"Building";"HighTemplar";NA;248;0
"Building";"HighTemplar";NA;248;0
"Building";"HighTemplar";NA;248;0
"Building";"HighTemplar";NA;248;0
"Unit";"Archon";"High Templar";248;0
"Unit";"Archon";"High Templar";248;0
"Unit";"Observer";"Robotics Facility";247;1
"Building";"Assimilator";NA;248;0
"Upgrade";"ProtossAirArmorsLevel1";"CyberneticsCore";230;0
"Building";"Assimilator";NA;249;0
"Building";"Nexus";NA;244;0
"Unit";"Phoenix";"Stargate";252;2
"Unit";"Phoenix";"Stargate";252;2
"Unit";"Phoenix";"Stargate";255;2
"Building";"HighTemplar";NA;262;0
"Building";"HighTemplar";NA;262;0
"Building";"HighTemplar";NA;262;0
"Building";"HighTemplar";NA;262;0
"Building";"HighTemplar";NA;262;0
"Building";"HighTemplar";NA;262;0
"Building";"Gateway";NA;252;0
"Building";"Gateway";NA;252;0
"Unit";"Archon";"High Templar";262;0
"Building";"Gateway";NA;252;0
"Unit";"Archon";"High Templar";262;0
"Building";"Gateway";NA;256;0
"Unit";"Archon";"High Templar";262;0
"Building";"PhotonCannon";NA;256;0
"Building";"PhotonCannon";NA;262;0
"Building";"PhotonCannon";NA;262;0
"Building";"PhotonCannon";NA;262;0
"Building";"PhotonCannon";NA;262;0
"Building";"PhotonCannon";NA;262;0
"Building";"ShieldBattery";NA;262;0
"Unit";"Stalker";"Gateway";262;2
"Unit";"Stalker";"Gateway";262;2
"Unit";"Stalker";"Gateway";262;2
"Unit";"Stalker";"Gateway";262;2
"Unit";"Stalker";"Gateway";262;2
"Unit";"Stalker";"Gateway";262;2
"Unit";"Stalker";"Gateway";262;2
"Unit";"Stalker";"Gateway";262;2
"Unit";"Phoenix";"Stargate";262;2
"Unit";"Phoenix";"Stargate";262;2
"Unit";"Phoenix";"Stargate";262;2
