"type";"unit_name";"on_building";"total_supply";"supply"
"Building";"Pylon";NA;13;0
"Building";"Assimilator";NA;16;0
"Building";"Assimilator";NA;17;0
"Building";"Gateway";NA;15;0
"Building";"Pylon";NA;20;0
"Building";"Gateway";NA;18;0
"Building";"CyberneticsCore";NA;19;0
"Unit";"Adept";"Gateway";23;2
"Unit";"Adept";"Gateway";23;2
"Building";"Pylon";NA;24;0
"Building";"Pylon";NA;24;0
"Unit";"Stalker";"Gateway";28;2
"Unit";"Stalker";"Gateway";28;2
"Unit";"Sentry";"Gateway";30;2
"Unit";"Sentry";"Gateway";30;2
"Building";"ShieldBattery";NA;32;0
"Unit";"Stalker";"Gateway";32;2
"Unit";"Sentry";"Gateway";36;2
"Building";"Nexus";NA;28;0
"Building";"RoboticsFacility";NA;32;0
"Building";"ShieldBattery";NA;37;0
"Building";"Pylon";NA;42;0
"Unit";"Stalker";"Gateway";43;2
"Unit";"Stalker";"Gateway";43;2
"Unit";"Sentry";"Gateway";47;2
"Unit";"Stalker";"Gateway";49;2
"Unit";"Stalker";"Gateway";52;2
"Unit";"Immortal";"Robotics Facility";47;4
"Unit";"Stalker";"Gateway";54;2
"Unit";"Stalker";"Gateway";60;2
"Unit";"Stalker";"Gateway";63;2
"Unit";"Immortal";"Robotics Facility";54;4
"Building";"Pylon";NA;60;0
"Unit";"Adept";"Gateway";71;2
"Unit";"Observer";"Robotics Facility";65;1
"Unit";"Sentry";"Gateway";78;2
"Unit";"Sentry";"Gateway";78;2
"Building";"Gateway";NA;76;0
"Building";"Pylon";NA;84;0
"Building";"Gateway";NA;78;0
"Unit";"Stalker";"Gateway";84;2
"Unit";"Stalker";"Gateway";84;2
"Building";"Gateway";NA;83;0
"Building";"Pylon";NA;88;0
"Building";"Pylon";NA;88;0
"Unit";"Stalker";"Gateway";88;2
"Unit";"Stalker";"Gateway";88;2
"Unit";"Stalker";"Gateway";88;2
"Unit";"Stalker";"Gateway";88;2
"Unit";"Immortal";"Robotics Facility";84;4
"Unit";"Phoenix";"Stargate";88;2
"Building";"Forge";NA;88;0
"Building";"Assimilator";NA;102;0
"Building";"Assimilator";NA;102;0
"Building";"Pylon";NA;102;0
"Unit";"Adept";"Gateway";107;2
"Unit";"Adept";"Gateway";107;2
"Unit";"Phoenix";"Stargate";105;2
"Building";"PhotonCannon";NA;106;0
"Building";"PhotonCannon";NA;106;0
"Unit";"Adept";"Gateway";118;2
"Unit";"Adept";"Gateway";118;2
"Unit";"Adept";"Gateway";118;2
"Unit";"Adept";"Gateway";118;2
"Unit";"Adept";"Gateway";118;2
"Building";"RoboticsBay";NA;115;0
"Building";"RoboticsFacility";NA;117;0
"Unit";"Disruptor";"Robotics Facility";118;3
"Unit";"Stalker";"Gateway";131;2
"Unit";"Stalker";"Gateway";131;2
"Unit";"Stalker";"Gateway";131;2
"Unit";"Stalker";"Gateway";131;2
"Unit";"Stalker";"Gateway";131;2
"Unit";"Disruptor";"Robotics Facility";128;3
"Unit";"Disruptor";"Robotics Facility";128;3
"Unit";"Disruptor";"Robotics Facility";144;3
"Building";"TwilightCouncil";NA;144;0
"Building";"Pylon";NA;154;0
"Unit";"Stalker";"Gateway";157;2
"Unit";"Stalker";"Gateway";157;2
"Unit";"Stalker";"Gateway";157;2
"Unit";"Sentry";"Gateway";163;2
"Unit";"Sentry";"Gateway";163;2
"Unit";"Phoenix";"Stargate";157;2
"Unit";"Disruptor";"Robotics Facility";157;3
"Unit";"Disruptor";"Robotics Facility";157;3
"Unit";"Adept";"Gateway";178;2
"Building";"Nexus";NA;155;0
"Unit";"Stalker";"Gateway";180;2
"Unit";"Disruptor";"Robotics Facility";163;3
"Unit";"Adept";"Gateway";182;2
"Unit";"Adept";"Gateway";182;2
"Unit";"Disruptor";"Robotics Facility";165;3
"Unit";"Stalker";"Gateway";192;2
"Unit";"Stalker";"Gateway";192;2
"Unit";"Stalker";"Gateway";196;2
"Unit";"Stalker";"Gateway";196;2
"Unit";"Stalker";"Gateway";200;2
"Unit";"Stalker";"Gateway";200;2
"Unit";"Stalker";"Gateway";207;2
"Unit";"Stalker";"Gateway";207;2
"Unit";"Stalker";"Gateway";207;2
"Unit";"Disruptor";"Robotics Facility";200;3
"Unit";"Stalker";"Gateway";220;2
"Unit";"Stalker";"Gateway";220;2
"Unit";"Stalker";"Gateway";220;2
"Unit";"Disruptor";"Robotics Facility";207;3
"Building";"PhotonCannon";NA;217;0
"Unit";"Stalker";"Gateway";230;2
"Unit";"Stalker";"Gateway";230;2
"Unit";"Stalker";"Gateway";230;2
"Building";"Assimilator";NA;229;0
"Building";"Assimilator";NA;229;0
"Building";"ShieldBattery";NA;229;0
"Building";"PhotonCannon";NA;229;0
"Building";"TemplarArchive";NA;229;0
"Upgrade";"ProtossGroundWeaponsLevel1";"Forge";213;0
"Unit";"Stalker";"Gateway";240;2
"Unit";"Stalker";"Gateway";240;2
"Unit";"Stalker";"Gateway";240;2
"Unit";"Stalker";"Gateway";247;2
"Unit";"Disruptor";"Robotics Facility";240;3
"Unit";"Disruptor";"Robotics Facility";240;3
"Building";"Pylon";NA;249;0
"Building";"Pylon";NA;249;0
"Building";"Pylon";NA;249;0
"Building";"Pylon";NA;249;0
"Unit";"Zealot";"Gateway";255;2
"Unit";"Zealot";"Gateway";255;2
"Building";"Pylon";NA;255;0
"Unit";"Stalker";"Gateway";259;2
"Unit";"Stalker";"Gateway";259;2
"Unit";"Stalker";"Gateway";259;2
"Building";"Pylon";NA;257;0
"Unit";"Stalker";"Gateway";265;2
"Unit";"Disruptor";"Robotics Facility";255;3
"Unit";"Disruptor";"Robotics Facility";255;3
"Building";"HighTemplar";NA;273;0
"Building";"HighTemplar";NA;273;0
"Unit";"Archon";"High Templar";273;0
"Unit";"Observer";"Robotics Facility";273;1
"Unit";"Zealot";"Gateway";273;2
"Unit";"Zealot";"Gateway";273;2
"Building";"Pylon";NA;273;0
"Unit";"Zealot";"Gateway";278;2
"Building";"Assimilator";NA;273;0
"Building";"Assimilator";NA;273;0
"Building";"Pylon";NA;278;0
"Unit";"Stalker";"Gateway";280;2
"Unit";"Stalker";"Gateway";280;2
"Unit";"Stalker";"Gateway";280;2
"Upgrade";"Charge";"TwilightCouncil";270;0
"Unit";"Zealot";"Gateway";286;2
"Unit";"Zealot";"Gateway";286;2
"Building";"Nexus";NA;273;0
