"type";"unit_name";"on_building";"total_supply";"supply"
"Building";"Pylon";NA;13;0
"Building";"Assimilator";NA;15;0
"Building";"Assimilator";NA;17;0
"Building";"Gateway";NA;15;0
"Building";"Pylon";NA;20;0
"Building";"CyberneticsCore";NA;19;0
"Building";"Gateway";NA;19;0
"Unit";"Adept";"Gateway";23;2
"Unit";"Adept";"Gateway";23;2
"Building";"Pylon";NA;23;0
"Building";"Stargate";NA;23;0
"Unit";"Stalker";"Gateway";29;2
"Unit";"Stalker";"Gateway";29;2
"Unit";"Oracle";"Stargate";30;3
"Unit";"Oracle";"Stargate";34;3
"Building";"ShieldBattery";NA;37;0
"Building";"RoboticsFacility";NA;38;0
"Building";"Pylon";NA;43;0
"Building";"Nexus";NA;37;0
"Building";"ShieldBattery";NA;43;0
"Unit";"Observer";"Robotics Facility";44;1
"Unit";"Stalker";"Gateway";46;2
"Building";"Pylon";NA;44;0
"Building";"Assimilator";NA;45;0
"Unit";"Oracle";"Stargate";44;3
"Building";"OracleStasisTrap";NA;53;0
"Building";"Pylon";NA;57;0
"Unit";"Immortal";"Robotics Facility";51;4
"Building";"Assimilator";NA;57;0
"Building";"RoboticsBay";NA;59;0
"Building";"Pylon";NA;71;0
"Building";"Pylon";NA;71;0
"Unit";"Disruptor";"Robotics Facility";69;3
"Building";"RoboticsFacility";NA;69;0
"Unit";"Phoenix";"Stargate";73;2
"Unit";"Stalker";"Gateway";77;2
"Unit";"Stalker";"Gateway";77;2
"Building";"Gateway";NA;72;0
"Building";"Gateway";NA;72;0
"Building";"Nexus";NA;69;0
"Building";"Gateway";NA;74;0
"Building";"TwilightCouncil";NA;77;0
"Unit";"Disruptor";"Robotics Facility";84;3
"Unit";"Disruptor";"Robotics Facility";84;3
"Building";"OracleStasisTrap";NA;93;0
"Unit";"Stalker";"Gateway";96;2
"Unit";"Stalker";"Gateway";96;2
"Building";"Assimilator";NA;87;0
"Building";"OracleStasisTrap";NA;100;0
"Building";"ShieldBattery";NA;87;0
"Building";"OracleStasisTrap";NA;100;0
"Building";"ShieldBattery";NA;87;0
"Building";"Pylon";NA;96;0
"Unit";"Disruptor";"Robotics Facility";87;3
"Unit";"Disruptor";"Robotics Facility";88;3
"Building";"Forge";NA;93;0
"Building";"Pylon";NA;100;0
"Building";"Assimilator";NA;100;0
"Unit";"Disruptor";"Robotics Facility";100;3
"Building";"Pylon";NA;110;0
"Unit";"Disruptor";"Robotics Facility";106;3
"Building";"OracleStasisTrap";NA;117;0
"Building";"OracleStasisTrap";NA;117;0
"Unit";"Stalker";"Gateway";118;2
"Unit";"Stalker";"Gateway";118;2
"Unit";"Stalker";"Gateway";118;2
"Building";"Gateway";NA;102;0
"Building";"PhotonCannon";NA;110;0
"Building";"PhotonCannon";NA;110;0
"Building";"PhotonCannon";NA;111;0
"Unit";"Disruptor";"Robotics Facility";111;3
"Building";"OracleStasisTrap";NA;127;0
"Building";"OracleStasisTrap";NA;127;0
"Building";"Pylon";NA;124;0
"Unit";"Stalker";"Gateway";127;2
"Unit";"Stalker";"Gateway";127;2
"Unit";"Stalker";"Gateway";127;2
"Unit";"Stalker";"Gateway";127;2
"Unit";"Disruptor";"Robotics Facility";118;3
"Building";"PhotonCannon";NA;124;0
"Building";"Pylon";NA;127;0
"Building";"TemplarArchive";NA;127;0
"Unit";"Disruptor";"Robotics Facility";127;3
"Upgrade";"ProtossGroundWeaponsLevel1";"Forge";111;0
"Building";"Pylon";NA;138;0
"Unit";"Stalker";"Gateway";141;2
"Unit";"Stalker";"Gateway";141;2
"Unit";"Stalker";"Gateway";141;2
"Building";"HighTemplar";NA;143;0
"Building";"HighTemplar";NA;145;0
"Unit";"Archon";"High Templar";147;0
"Building";"Pylon";NA;141;0
"Unit";"Disruptor";"Robotics Facility";138;3
"Building";"PhotonCannon";NA;141;0
"Building";"PhotonCannon";NA;141;0
"Building";"Pylon";NA;147;0
"Building";"OracleStasisTrap";NA;150;0
"Unit";"Stalker";"Gateway";150;2
"Unit";"Stalker";"Gateway";150;2
"Unit";"Stalker";"Gateway";150;2
"Unit";"Stalker";"Gateway";150;2
"Building";"HighTemplar";NA;158;0
"Building";"HighTemplar";NA;158;0
"Unit";"Archon";"High Templar";158;0
"Building";"OracleStasisTrap";NA;158;0
"Building";"OracleStasisTrap";NA;158;0
"Building";"ShieldBattery";NA;158;0
"Building";"HighTemplar";NA;158;0
"Building";"HighTemplar";NA;158;0
"Building";"HighTemplar";NA;158;0
"Building";"HighTemplar";NA;158;0
"Building";"Pylon";NA;158;0
"Upgrade";"Charge";"TwilightCouncil";147;0
"Building";"Pylon";NA;158;0
"Building";"PhotonCannon";NA;158;0
"Building";"Gateway";NA;158;0
"Unit";"Archon";"High Templar";158;0
"Unit";"Archon";"High Templar";158;0
"Building";"PhotonCannon";NA;158;0
"Building";"Gateway";NA;158;0
"Building";"Nexus";NA;147;0
"Building";"Assimilator";NA;158;0
"Building";"Pylon";NA;158;0
"Building";"Assimilator";NA;158;0
"Building";"Pylon";NA;158;0
"Unit";"Observer";"Robotics Facility";158;1
"Unit";"Zealot";"Gateway";162;2
"Unit";"Zealot";"Gateway";162;2
"Unit";"Zealot";"Gateway";162;2
"Unit";"Zealot";"Gateway";162;2
"Unit";"Zealot";"Gateway";162;2
"Unit";"Zealot";"Gateway";172;2
"Unit";"Zealot";"Gateway";172;2
"Unit";"Zealot";"Gateway";172;2
"Unit";"Zealot";"Gateway";172;2
"Unit";"Zealot";"Gateway";172;2
"Building";"HighTemplar";NA;183;0
"Building";"HighTemplar";NA;183;0
"Building";"HighTemplar";NA;183;0
"Building";"HighTemplar";NA;183;0
"Building";"PhotonCannon";NA;182;0
"Building";"PhotonCannon";NA;182;0
"Building";"ShieldBattery";NA;182;0
"Building";"OracleStasisTrap";NA;183;0
"Building";"OracleStasisTrap";NA;183;0
"Unit";"Archon";"High Templar";183;0
"Unit";"Archon";"High Templar";183;0
"Building";"OracleStasisTrap";NA;183;0
"Unit";"Stalker";"Gateway";183;2
"Unit";"Stalker";"Gateway";183;2
"Unit";"Stalker";"Gateway";183;2
"Building";"RoboticsFacility";NA;182;0
"Building";"Pylon";NA;189;0
"Unit";"Zealot";"Gateway";189;2
"Unit";"Zealot";"Gateway";189;2
"Building";"Pylon";NA;189;0
"Upgrade";"ProtossGroundWeaponsLevel2";"Forge";172;0
"Building";"Gateway";NA;183;0
"Building";"Gateway";NA;183;0
"Building";"Gateway";NA;183;0
"Building";"PhotonCannon";NA;193;0
"Building";"PhotonCannon";NA;193;0
"Building";"FleetBeacon";NA;189;0
"Building";"OracleStasisTrap";NA;195;0
"Building";"PhotonCannon";NA;193;0
"Building";"Stargate";NA;189;0
"Building";"PhotonCannon";NA;193;0
"Building";"Stargate";NA;189;0
"Building";"Stargate";NA;189;0
"Building";"PhotonCannon";NA;193;0
"Building";"PhotonCannon";NA;193;0
"Building";"PhotonCannon";NA;195;0
"Building";"PhotonCannon";NA;195;0
"Unit";"Stalker";"Gateway";195;2
"Unit";"Stalker";"Gateway";195;2
"Unit";"Stalker";"Gateway";195;2
"Unit";"Stalker";"Gateway";195;2
"Unit";"Stalker";"Gateway";195;2
"Unit";"Stalker";"Gateway";195;2
"Unit";"Stalker";"Gateway";195;2
"Building";"DarkShrine";NA;189;0
"Unit";"Disruptor";"Robotics Facility";195;3
"Unit";"Disruptor";"Robotics Facility";195;3
"Unit";"Stalker";"Gateway";215;2
"Unit";"Stalker";"Gateway";215;2
"Unit";"Stalker";"Gateway";215;2
"Unit";"Stalker";"Gateway";215;2
"Unit";"Stalker";"Gateway";215;2
"Unit";"Stalker";"Gateway";215;2
"Unit";"Stalker";"Gateway";215;2
"Unit";"Stalker";"Gateway";215;2
"Unit";"Stalker";"Gateway";215;2
"Unit";"Stalker";"Gateway";215;2
"Building";"HighTemplar";NA;235;0
"Building";"HighTemplar";NA;235;0
"Building";"HighTemplar";NA;235;0
"Building";"HighTemplar";NA;235;0
"Building";"HighTemplar";NA;235;0
"Building";"HighTemplar";NA;235;0
"Building";"HighTemplar";NA;235;0
"Building";"HighTemplar";NA;235;0
"Unit";"Archon";"High Templar";235;0
"Unit";"Archon";"High Templar";235;0
"Unit";"Archon";"High Templar";235;0
"Unit";"Archon";"High Templar";235;0
"Unit";"Zealot";"Gateway";235;2
"Unit";"Zealot";"Gateway";235;2
"Unit";"Zealot";"Gateway";235;2
"Unit";"Zealot";"Gateway";235;2
"Unit";"Zealot";"Gateway";235;2
"Unit";"Carrier";"Stargate";235;6
"Unit";"Carrier";"Stargate";235;6
"Unit";"Carrier";"Stargate";235;6
"Unit";"Disruptor";"Robotics Facility";235;3
"Upgrade";"ProtossGroundWeaponsLevel3";"Forge";215;0
"Unit";"Zealot";"Gateway";266;2
"Unit";"Zealot";"Gateway";266;2
"Unit";"Zealot";"Gateway";266;2
"Unit";"Zealot";"Gateway";266;2
"Unit";"Stalker";"Gateway";274;2
"Unit";"Stalker";"Gateway";274;2
"Unit";"Stalker";"Gateway";274;2
"Unit";"Stalker";"Gateway";274;2
"Unit";"Stalker";"Gateway";274;2
"Unit";"Stalker";"Gateway";274;2
"Unit";"Carrier";"Stargate";235;6
