"type";"unit_name";"on_building";"total_supply";"supply"
"Building";"Pylon";NA;13;0
"Building";"Assimilator";NA;15;0
"Building";"Gateway";NA;14;0
"Unit";"Zealot";"Gateway";19;2
"Building";"Pylon";NA;20;0
"Building";"CyberneticsCore";NA;20;0
"Unit";"Zealot";"Gateway";22;2
"Unit";"Stalker";"Gateway";22;2
"Building";"ShieldBattery";NA;24;0
"Unit";"Stalker";"Gateway";26;2
