"type";"unit_name";"on_building";"total_supply";"supply"
"Building";"Pylon";NA;13;0
"Building";"Assimilator";NA;16;0
"Building";"Assimilator";NA;17;0
"Building";"Gateway";NA;15;0
"Building";"Pylon";NA;20;0
"Building";"Gateway";NA;18;0
"Building";"CyberneticsCore";NA;19;0
"Unit";"Stalker";"Gateway";22;2
"Unit";"Stalker";"Gateway";22;2
"Building";"Pylon";NA;23;0
"Unit";"Stalker";"Gateway";27;2
"Unit";"Stalker";"Gateway";27;2
"Building";"Gateway";NA;27;0
"Building";"Pylon";NA;31;0
"Building";"Gateway";NA;27;0
"Unit";"Stalker";"Gateway";31;2
"Unit";"Stalker";"Gateway";31;2
"Building";"ShieldBattery";NA;31;0
"Unit";"Stalker";"Gateway";35;2
"Unit";"Stalker";"Gateway";35;2
"Unit";"Stalker";"Gateway";35;2
"Unit";"Adept";"Gateway";35;2
"Unit";"Stalker";"Gateway";43;2
"Unit";"Sentry";"Gateway";43;2
"Building";"Pylon";NA;43;0
"Unit";"Stalker";"Gateway";47;2
"Unit";"Adept";"Gateway";47;2
"Unit";"Adept";"Gateway";47;2
"Unit";"Adept";"Gateway";53;2
"Unit";"Adept";"Gateway";53;2
"Building";"Pylon";NA;58;0
"Unit";"Sentry";"Gateway";60;2
"Unit";"Sentry";"Gateway";60;2
"Unit";"Adept";"Gateway";59;2
"Unit";"Adept";"Gateway";59;2
"Building";"Nexus";NA;53;0
"Building";"RoboticsFacility";NA;58;0
"Unit";"Adept";"Gateway";73;2
"Unit";"Immortal";"Robotics Facility";68;4
"Building";"Pylon";NA;83;0
"Unit";"Adept";"Gateway";87;2
"Unit";"Adept";"Gateway";88;2
"Unit";"Observer";"Robotics Facility";85;1
"Building";"TwilightCouncil";NA;83;0
"Unit";"Sentry";"Gateway";93;2
"Unit";"Sentry";"Gateway";93;2
"Building";"Pylon";NA;87;0
"Building";"Pylon";NA;98;0
"Unit";"Stalker";"Gateway";99;2
"Unit";"Adept";"Gateway";99;2
"Unit";"Adept";"Gateway";99;2
"Unit";"Adept";"Gateway";105;2
"Unit";"Adept";"Gateway";107;2
"Unit";"Adept";"Gateway";107;2
"Building";"Gateway";NA;99;0
"Building";"Gateway";NA;99;0
"Unit";"Adept";"Gateway";113;2
"Unit";"Adept";"Gateway";113;2
"Unit";"Adept";"Gateway";119;2
"Unit";"Adept";"Gateway";119;2
"Unit";"Zealot";"Gateway";128;2
"Unit";"Immortal";"Robotics Facility";115;4
"Unit";"Zealot";"Gateway";128;2
"Unit";"Zealot";"Gateway";128;2
"Unit";"Zealot";"Gateway";128;2
"Upgrade";"Charge";"TwilightCouncil";105;0
"Unit";"Zealot";"Gateway";141;2
"Unit";"Zealot";"Gateway";141;2
"Building";"TemplarArchive";NA;127;0
"Building";"Assimilator";NA;141;0
"Unit";"Zealot";"Gateway";147;2
"Unit";"Zealot";"Gateway";147;2
"Unit";"Zealot";"Gateway";154;2
"Unit";"Zealot";"Gateway";154;2
"Unit";"Zealot";"Gateway";154;2
"Unit";"Zealot";"Gateway";154;2
"Building";"Assimilator";NA;154;0
"Building";"Pylon";NA;167;0
"Building";"Forge";NA;163;0
"Building";"HighTemplar";NA;173;0
"Building";"HighTemplar";NA;173;0
"Building";"HighTemplar";NA;173;0
"Building";"HighTemplar";NA;173;0
"Unit";"Zealot";"Gateway";173;2
"Unit";"Archon";"High Templar";173;0
"Unit";"Archon";"High Templar";173;0
"Building";"Pylon";NA;175;0
"Building";"Pylon";NA;175;0
"Building";"Pylon";NA;175;0
"Building";"Pylon";NA;176;0
"Building";"Pylon";NA;177;0
"Building";"Pylon";NA;177;0
"Building";"Nexus";NA;173;0
"Building";"HighTemplar";NA;179;0
"Building";"HighTemplar";NA;179;0
"Building";"HighTemplar";NA;179;0
"Building";"HighTemplar";NA;179;0
"Building";"HighTemplar";NA;179;0
"Building";"HighTemplar";NA;179;0
"Upgrade";"ProtossGroundWeaponsLevel1";"Forge";173;0
"Unit";"Archon";"High Templar";180;0
"Unit";"Archon";"High Templar";180;0
"Unit";"Archon";"High Templar";180;0
"Building";"Assimilator";NA;180;0
"Building";"Assimilator";NA;181;0
"Unit";"Immortal";"Robotics Facility";180;4
"Unit";"Zealot";"Gateway";195;2
"Unit";"Zealot";"Gateway";195;2
"Unit";"Zealot";"Gateway";195;2
"Unit";"Zealot";"Gateway";195;2
"Unit";"Zealot";"Gateway";195;2
"Unit";"Zealot";"Gateway";195;2
"Building";"Gateway";NA;195;0
"Building";"Gateway";NA;195;0
"Building";"Gateway";NA;195;0
"Unit";"Zealot";"Gateway";207;2
"Unit";"Zealot";"Gateway";207;2
"Unit";"Zealot";"Gateway";207;2
"Unit";"Zealot";"Gateway";207;2
"Unit";"Zealot";"Gateway";207;2
"Unit";"Zealot";"Gateway";207;2
"Unit";"Immortal";"Robotics Facility";207;4
"Building";"HighTemplar";NA;219;0
"Building";"HighTemplar";NA;219;0
"Building";"HighTemplar";NA;219;0
"Upgrade";"ProtossGroundWeaponsLevel2";"Forge";193;0
"Building";"Pylon";NA;219;0
"Building";"Pylon";NA;219;0
"Building";"Pylon";NA;223;0
"Building";"Pylon";NA;223;0
"Building";"Pylon";NA;223;0
"Building";"HighTemplar";NA;223;0
"Building";"HighTemplar";NA;223;0
"Building";"HighTemplar";NA;223;0
"Unit";"Zealot";"Gateway";223;2
"Unit";"Zealot";"Gateway";223;2
"Unit";"Zealot";"Gateway";223;2
"Unit";"Archon";"High Templar";223;0
"Unit";"Zealot";"Gateway";229;2
"Unit";"Zealot";"Gateway";229;2
"Unit";"Zealot";"Gateway";229;2
"Unit";"Phoenix";"Stargate";223;2
"Unit";"Archon";"High Templar";229;0
"Unit";"Archon";"High Templar";229;0
"Unit";"Zealot";"Gateway";237;2
"Unit";"Zealot";"Gateway";237;2
"Unit";"Zealot";"Gateway";237;2
"Unit";"Zealot";"Gateway";237;2
"Unit";"Zealot";"Gateway";237;2
"Unit";"Zealot";"Gateway";237;2
"Building";"Nexus";NA;219;0
"Unit";"Zealot";"Gateway";249;2
"Unit";"Zealot";"Gateway";249;2
"Unit";"Zealot";"Gateway";249;2
"Unit";"Zealot";"Gateway";249;2
"Unit";"Zealot";"Gateway";249;2
"Unit";"Zealot";"Gateway";249;2
"Unit";"Zealot";"Gateway";249;2
"Unit";"Zealot";"Gateway";249;2
"Unit";"Zealot";"Gateway";249;2
"Unit";"Zealot";"Gateway";267;2
"Unit";"Zealot";"Gateway";267;2
"Unit";"Zealot";"Gateway";267;2
"Unit";"Zealot";"Gateway";267;2
"Unit";"Zealot";"Gateway";267;2
"Unit";"Zealot";"Gateway";267;2
"Unit";"Zealot";"Gateway";267;2
"Unit";"Zealot";"Gateway";267;2
"Unit";"Zealot";"Gateway";267;2
