"type";"unit_name";"on_building";"total_supply";"supply"
"Building";"Pylon";NA;13;0
"Building";"Assimilator";NA;15;0
"Building";"Gateway";NA;14;0
"Building";"Assimilator";NA;17;0
"Building";"Pylon";NA;19;0
"Building";"Gateway";NA;18;0
"Building";"CyberneticsCore";NA;19;0
"Unit";"Adept";"Gateway";20;2
"Unit";"Adept";"Gateway";20;2
"Building";"Pylon";NA;26;0
"Unit";"Stalker";"Gateway";26;2
"Building";"Stargate";NA;22;0
"Building";"ShieldBattery";NA;26;0
"Building";"Forge";NA;28;0
"Unit";"Oracle";"Stargate";28;3
"Unit";"Stalker";"Gateway";28;2
"Unit";"Stalker";"Gateway";31;2
"Building";"Pylon";NA;31;0
"Building";"PhotonCannon";NA;31;0
"Building";"ShieldBattery";NA;33;0
"Building";"Pylon";NA;37;0
"Unit";"Sentry";"Gateway";37;2
"Unit";"Stalker";"Gateway";37;2
"Unit";"Phoenix";"Stargate";43;2
"Building";"PhotonCannon";NA;44;0
"Building";"Nexus";NA;37;0
"Unit";"Phoenix";"Stargate";48;2
"Building";"Pylon";NA;50;0
"Unit";"Sentry";"Gateway";54;2
"Unit";"Phoenix";"Stargate";50;2
"Building";"PhotonCannon";NA;50;0
"Unit";"Stalker";"Gateway";62;2
"Unit";"Stalker";"Gateway";62;2
"Upgrade";"ProtossGroundWeaponsLevel1";"Forge";48;0
"Building";"ShieldBattery";NA;62;0
"Building";"ShieldBattery";NA;66;0
"Building";"ShieldBattery";NA;68;0
"Building";"Assimilator";NA;68;0
"Building";"Assimilator";NA;68;0
"Building";"Pylon";NA;72;0
"Building";"RoboticsFacility";NA;68;0
"Building";"TwilightCouncil";NA;72;0
"Unit";"Phoenix";"Stargate";74;2
"Building";"Pylon";NA;79;0
"Building";"Pylon";NA;79;0
"Unit";"Zealot";"Gateway";83;2
"Unit";"Zealot";"Gateway";83;2
"Unit";"Observer";"Robotics Facility";79;1
"Upgrade";"ProtossGroundArmorsLevel1";"Forge";76;0
"Building";"DarkShrine";NA;79;0
"Building";"Nexus";NA;79;0
"Unit";"Observer";"Robotics Facility";87;1
"Building";"Assimilator";NA;90;0
"Building";"Assimilator";NA;90;0
"Building";"DarkTemplar";NA;93;0
"Building";"DarkTemplar";NA;93;0
"Building";"Gateway";NA;88;0
"Building";"Gateway";NA;89;0
"Building";"Gateway";NA;90;0
"Building";"Gateway";NA;90;0
"Building";"Gateway";NA;90;0
"Building";"Pylon";NA;93;0
"Building";"Pylon";NA;95;0
"Building";"DarkTemplar";NA;97;0
"Upgrade";"Charge";"TwilightCouncil";92;0
"Building";"DarkTemplar";NA;99;0
"Building";"DarkTemplar";NA;99;0
"Building";"DarkTemplar";NA;99;0
"Building";"DarkTemplar";NA;99;0
"Building";"DarkTemplar";NA;99;0
"Building";"DarkTemplar";NA;99;0
"Upgrade";"ProtossGroundWeaponsLevel2";"Forge";92;0
"Building";"Pylon";NA;99;0
"Building";"PhotonCannon";NA;99;0
"Building";"PhotonCannon";NA;99;0
"Building";"Stargate";NA;99;0
"Building";"FleetBeacon";NA;99;0
"Building";"Assimilator";NA;100;0
"Building";"Pylon";NA;100;0
"Building";"Assimilator";NA;100;0
"Unit";"Phoenix";"Stargate";100;2
"Unit";"Phoenix";"Stargate";100;2
"Upgrade";"ProtossAirWeaponsLevel1";"CyberneticsCore";99;0
"Building";"Nexus";NA;100;0
"Unit";"Phoenix";"Stargate";100;2
"Building";"Pylon";NA;106;0
"Unit";"Phoenix";"Stargate";100;2
"Building";"Pylon";NA;106;0
"Unit";"Phoenix";"Stargate";106;2
"Unit";"Phoenix";"Stargate";108;2
"Building";"DarkTemplar";NA;114;0
"Building";"DarkTemplar";NA;114;0
"Building";"DarkTemplar";NA;114;0
"Building";"DarkTemplar";NA;114;0
"Building";"DarkTemplar";NA;114;0
"Building";"DarkTemplar";NA;114;0
"Building";"DarkTemplar";NA;114;0
"Unit";"Tempest";"Stargate";114;4
"Unit";"Tempest";"Stargate";114;4
"Upgrade";"ProtossGroundWeaponsLevel3";"Forge";100;0
"Unit";"Archon";"High Templar";129;0
"Unit";"Archon";"High Templar";129;0
"Unit";"Archon";"High Templar";129;0
"Unit";"Archon";"High Templar";129;0
"Unit";"Archon";"High Templar";129;0
"Unit";"Archon";"High Templar";129;0
"Unit";"Archon";"High Templar";129;0
"Unit";"Archon";"High Templar";129;0
"Unit";"Stalker";"Gateway";129;2
"Unit";"Stalker";"Gateway";129;2
"Unit";"Stalker";"Gateway";129;2
"Unit";"Stalker";"Gateway";129;2
"Unit";"Stalker";"Gateway";129;2
"Unit";"Stalker";"Gateway";129;2
"Unit";"Stalker";"Gateway";129;2
"Unit";"Carrier";"Stargate";114;6
"Upgrade";"ProtossAirWeaponsLevel2";"CyberneticsCore";125;0
"Upgrade";"ProtossShieldsLevel1";"Forge";129;0
"Unit";"Carrier";"Stargate";129;6
"Building";"Pylon";NA;158;0
"Building";"Pylon";NA;158;0
"Building";"Pylon";NA;158;0
"Building";"Pylon";NA;158;0
"Building";"Pylon";NA;158;0
"Building";"Stargate";NA;152;0
"Building";"Assimilator";NA;158;0
"Building";"Assimilator";NA;158;0
"Unit";"Carrier";"Stargate";146;6
"Building";"Pylon";NA;158;0
"Building";"Assimilator";NA;158;0
"Building";"Pylon";NA;158;0
"Building";"Pylon";NA;158;0
"Unit";"Zealot";"Gateway";164;2
"Unit";"Zealot";"Gateway";164;2
"Unit";"Zealot";"Gateway";164;2
"Building";"Nexus";NA;158;0
"Unit";"Carrier";"Stargate";152;6
"Upgrade";"ProtossShieldsLevel2";"Forge";152;0
"Unit";"Carrier";"Stargate";158;6
"Building";"Nexus";NA;158;0
"Upgrade";"ProtossAirWeaponsLevel3";"CyberneticsCore";152;0
"Unit";"Carrier";"Stargate";158;6
"Unit";"Zealot";"Gateway";182;2
"Unit";"Zealot";"Gateway";182;2
"Unit";"Zealot";"Gateway";182;2
"Building";"Gateway";NA;170;0
"Building";"Gateway";NA;170;0
"Building";"Gateway";NA;176;0
"Building";"Gateway";NA;176;0
"Building";"Gateway";NA;176;0
"Unit";"Mothership";"Mothership Core";164;6
"Unit";"Stalker";"Gateway";200;2
"Unit";"Stalker";"Gateway";200;2
"Building";"DarkTemplar";NA;200;0
"Building";"DarkTemplar";NA;200;0
"Building";"DarkTemplar";NA;200;0
"Building";"DarkTemplar";NA;200;0
"Building";"DarkTemplar";NA;200;0
"Building";"DarkTemplar";NA;200;0
"Building";"DarkTemplar";NA;200;0
"Building";"Stargate";NA;194;0
"Building";"Stargate";NA;194;0
"Unit";"Observer";"Robotics Facility";204;1
"Upgrade";"ProtossAirArmorsLevel1";"CyberneticsCore";194;0
"Unit";"Observer";"Robotics Facility";204;1
