"type";"unit_name";"on_building";"total_supply_lag";"supply"
"Building";"Refinery";NA;15;0
"Building";"Barracks";NA;16;0
"Unit";"Reaper";"Barracks";19;1
"Building";"CommandCenter";NA;20;0
"Building";"Factory";NA;20;0
"Building";"Refinery";NA;21;0
"Building";"BarracksReactor";NA;21;0
"Building";"Starport";NA;24;0
"Unit";"Hellion";"Factory";24;2
"Unit";"Hellion";"Factory";26;2
"Unit";"Marine";"Barracks";29;1
"Building";"BarracksTechLab";NA;31;0
"Unit";"Medivac";"Starport";32;2
"Unit";"Hellion";"Factory";36;2
"Unit";"Hellion";"Factory";38;2
"Unit";"Hellion";"Factory";43;2
"Unit";"Hellion";"Factory";45;2
"Unit";"Liberator";"Starport";47;3
"Upgrade";"Stimpack";"TechLab";50;0
"Building";"Armory";NA;50;0
"Unit";"Hellion";"Factory";52;2
"Unit";"Hellion";"Factory";54;2
"Building";"CommandCenter";NA;58;0
"Unit";"Liberator";"Starport";58;3
"Unit";"Marine";"Barracks";63;1
"Building";"EngineeringBay";NA;64;0
"Building";"FactoryReactor";NA;64;0
"Building";"Barracks";NA;64;0
"Building";"EngineeringBay";NA;66;0
"Unit";"Marine";"Barracks";70;1
"Building";"StarportReactor";NA;71;0
"Building";"Barracks";NA;71;0
"Building";"FactoryReactor";NA;73;0
"Unit";"Marine";"Barracks";73;1
"Unit";"Marine";"Barracks";74;1
"Unit";"Marine";"Barracks";75;1
"Building";"Refinery";NA;78;0
"Building";"Barracks";NA;80;0
"Unit";"Marine";"Barracks";80;1
"Unit";"Marine";"Barracks";81;1
"Building";"Refinery";NA;82;0
"Unit";"Marine";"Barracks";82;1
"Building";"Barracks";NA;84;0
"Unit";"Marine";"Barracks";84;1
"Upgrade";"TerranInfantryWeaponsLevel1";"EngineeringBay";85;0
"Unit";"Marine";"Barracks";85;1
"Unit";"Marine";"Barracks";86;1
"Unit";"Marine";"Barracks";88;1
"Unit";"Marine";"Barracks";89;1
"Unit";"Medivac";"Starport";90;2
"Unit";"Medivac";"Starport";92;2
"Unit";"Marine";"Barracks";95;1
"Unit";"Marine";"Barracks";96;1
"Unit";"Marine";"Barracks";97;1
"Unit";"Marine";"Barracks";100;1
"Unit";"Marine";"Barracks";101;1
"Building";"BarracksReactor";NA;102;0
"Building";"Factory";NA;103;0
"Unit";"Marine";"Barracks";104;1
"Unit";"Marine";"Barracks";105;1
"Building";"Refinery";NA;108;0
"Unit";"Marine";"Barracks";108;1
"Unit";"Marine";"Barracks";109;1
"Unit";"Marine";"Barracks";110;1
"Building";"BarracksReactor";NA;111;0
"Unit";"Marine";"Barracks";114;1
"Unit";"Marine";"Barracks";115;1
"Unit";"Medivac";"Starport";116;2
"Unit";"Medivac";"Starport";118;2
"Unit";"Marine";"Barracks";120;1
"Unit";"Marine";"Barracks";121;1
"Unit";"Marine";"Barracks";123;1
"Unit";"Marine";"Barracks";125;1
"Unit";"Marine";"Barracks";126;1
"Unit";"Marine";"Barracks";127;1
"Unit";"Marine";"Barracks";128;1
"Unit";"Marine";"Barracks";129;1
"Unit";"Marine";"Barracks";130;1
"Unit";"Medivac";"Starport";131;2
"Unit";"Medivac";"Starport";133;2
"Building";"FactoryTechLab";NA;135;0
"Unit";"Marine";"Barracks";138;1
"Unit";"Marine";"Barracks";139;1
"Unit";"Marine";"Barracks";140;1
"Unit";"Marine";"Barracks";141;1
"Unit";"Marine";"Barracks";142;1
"Unit";"Marine";"Barracks";143;1
"Unit";"Marine";"Barracks";144;1
"Unit";"Marine";"Barracks";145;1
"Unit";"Marine";"Barracks";146;1
"Unit";"Marine";"Barracks";147;1
"Unit";"Marine";"Barracks";148;1
"Unit";"Marine";"Barracks";149;1
"Unit";"Marine";"Barracks";150;1
"Unit";"Medivac";"Starport";151;2
"Unit";"Marine";"Barracks";153;1
"Unit";"Marine";"Barracks";154;1
"Unit";"Marine";"Barracks";155;1
"Unit";"Marine";"Barracks";156;1
"Unit";"Marine";"Barracks";157;1
"Unit";"Medivac";"Starport";159;2
"Unit";"Marine";"Barracks";161;1
"Unit";"Marine";"Barracks";162;1
"Unit";"Marine";"Barracks";163;1
"Unit";"Marine";"Barracks";164;1
"Unit";"Marine";"Barracks";165;1
"Unit";"Marine";"Barracks";168;1
"Unit";"Marine";"Barracks";169;1
"Unit";"Marine";"Barracks";170;1
"Unit";"Marine";"Barracks";171;1
"Upgrade";"TerranInfantryWeaponsLevel2";"EngineeringBay";172;0
"Unit";"Medivac";"Starport";172;2
"Unit";"Marine";"Barracks";174;1
"Unit";"Marine";"Barracks";175;1
"Unit";"Marine";"Barracks";176;1
"Unit";"Marine";"Barracks";177;1
"Building";"CommandCenter";NA;178;0
"Unit";"Marine";"Barracks";178;1
"Unit";"Marine";"Barracks";179;1
"Unit";"Marine";"Barracks";180;1
"Unit";"Marine";"Barracks";181;1
"Unit";"Marine";"Barracks";182;1
"Unit";"Marine";"Barracks";183;1
"Unit";"Marine";"Barracks";184;1
"Unit";"Marine";"Barracks";185;1
"Unit";"Medivac";"Starport";186;2
"Unit";"Marauder";"Barracks";188;2
"Building";"CommandCenter";NA;190;0
"Unit";"Marine";"Barracks";190;1
"Unit";"Marine";"Barracks";191;1
"Unit";"Marine";"Barracks";192;1
"Unit";"Marine";"Barracks";193;1
"Unit";"Marine";"Barracks";194;1
"Unit";"Marine";"Barracks";195;1
"Unit";"Marine";"Barracks";196;1
"Unit";"Marine";"Barracks";197;1
"Unit";"Liberator";"Starport";198;3
"Unit";"Liberator";"Starport";201;3
"Unit";"Marine";"Barracks";204;1
"Unit";"Thor";"Factory";205;6
"Unit";"Marine";"Barracks";211;1
"Unit";"Marine";"Barracks";212;1
"Unit";"Marine";"Barracks";213;1
"Unit";"Marine";"Barracks";214;1
"Unit";"Marine";"Barracks";215;1
"Unit";"Marine";"Barracks";216;1
"Unit";"Marine";"Barracks";217;1
"Unit";"Marine";"Barracks";218;1
"Unit";"Marine";"Barracks";219;1
"Unit";"Marine";"Barracks";220;1
"Unit";"Marine";"Barracks";221;1
"Unit";"Marine";"Barracks";222;1
"Unit";"Medivac";"Starport";223;2
"Unit";"Medivac";"Starport";225;2
"Unit";"Marine";"Barracks";227;1
"Unit";"Marine";"Barracks";228;1
"Unit";"Marine";"Barracks";229;1
"Unit";"Marine";"Barracks";230;1
"Unit";"Thor";"Factory";231;6
"Building";"Refinery";NA;237;0
"Unit";"Medivac";"Starport";237;2
"Unit";"Marine";"Barracks";239;1
"Unit";"Marine";"Barracks";240;1
"Unit";"Marine";"Barracks";241;1
"Unit";"Marine";"Barracks";242;1
"Unit";"Marine";"Barracks";243;1
"Unit";"Marine";"Barracks";244;1
"Unit";"Marine";"Barracks";245;1
"Unit";"Marine";"Barracks";246;1
"Unit";"Marine";"Barracks";247;1
"Unit";"Marine";"Barracks";248;1
"Unit";"Marine";"Barracks";249;1
"Unit";"Marine";"Barracks";250;1
"Unit";"Marine";"Barracks";251;1
"Unit";"Marine";"Barracks";252;1
"Building";"Barracks";NA;253;0
"Building";"Barracks";NA;253;0
"Building";"Barracks";NA;253;0
"Unit";"Marine";"Barracks";253;1
"Unit";"Marine";"Barracks";254;1
"Unit";"Marine";"Barracks";255;1
"Upgrade";"TerranInfantryWeaponsLevel3";"EngineeringBay";256;0
"Unit";"Liberator";"Starport";256;3
"Unit";"Liberator";"Starport";259;3
"Unit";"Marine";"Barracks";262;1
"Unit";"Marine";"Barracks";263;1
"Unit";"Marine";"Barracks";265;1
"Unit";"Marine";"Barracks";266;1
"Unit";"Marine";"Barracks";267;1
"Unit";"Marine";"Barracks";268;1
"Unit";"Marine";"Barracks";269;1
"Unit";"Marine";"Barracks";270;1
"Unit";"Marine";"Barracks";272;1
"Unit";"Thor";"Factory";273;6
"Unit";"Marine";"Barracks";279;1
"Unit";"Marine";"Barracks";280;1
"Unit";"Marine";"Barracks";281;1
"Unit";"Marine";"Barracks";282;1
"Unit";"Marine";"Barracks";283;1
"Unit";"Marine";"Barracks";284;1
"Unit";"Marine";"Barracks";285;1
"Unit";"Marauder";"Barracks";286;2
"Unit";"Marine";"Barracks";288;1
"Unit";"Marine";"Barracks";289;1
"Unit";"Marine";"Barracks";290;1
"Unit";"Marine";"Barracks";291;1
"Unit";"Marine";"Barracks";292;1
"Unit";"Marine";"Barracks";293;1
"Unit";"Marauder";"Barracks";294;2
"Building";"BarracksTechLab";NA;296;0
"Building";"BarracksTechLab";NA;296;0
"Building";"BarracksTechLab";NA;296;0
"Unit";"Marine";"Barracks";296;1
"Unit";"Marine";"Barracks";297;1
"Unit";"Marine";"Barracks";298;1
"Unit";"Marine";"Barracks";299;1
"Unit";"Marine";"Barracks";300;1
"Unit";"Marine";"Barracks";301;1
"Unit";"Marine";"Barracks";302;1
"Unit";"Marine";"Barracks";303;1
"Unit";"Liberator";"Starport";304;3
"Unit";"Liberator";"Starport";307;3
"Unit";"Thor";"Factory";310;6
"Unit";"Marauder";"Barracks";316;2
"Unit";"Marine";"Barracks";318;1
"Unit";"Marine";"Barracks";319;1
"Unit";"Marine";"Barracks";320;1
"Unit";"Marine";"Barracks";321;1
"Unit";"Marine";"Barracks";322;1
"Unit";"Marine";"Barracks";323;1
"Unit";"Marine";"Barracks";324;1
"Unit";"Marine";"Barracks";325;1
"Unit";"Marine";"Barracks";326;1
"Unit";"Marine";"Barracks";327;1
"Unit";"Marine";"Barracks";328;1
"Building";"Refinery";NA;329;0
"Unit";"Marauder";"Barracks";329;2
"Unit";"Marine";"Barracks";331;1
"Unit";"Marine";"Barracks";332;1
"Building";"Refinery";NA;333;0
"Unit";"Marine";"Barracks";333;1
"Unit";"Liberator";"Starport";334;3
"Unit";"Liberator";"Starport";337;3
"Unit";"Marine";"Barracks";340;1
"Unit";"Marine";"Barracks";341;1
"Unit";"Marine";"Barracks";342;1
"Unit";"Marine";"Barracks";343;1
"Unit";"Marine";"Barracks";344;1
"Unit";"Marine";"Barracks";345;1
"Unit";"Marine";"Barracks";346;1
"Unit";"Marauder";"Barracks";347;2
"Unit";"Marauder";"Barracks";349;2
"Unit";"Marauder";"Barracks";351;2
"Unit";"Marine";"Barracks";353;1
"Unit";"Marine";"Barracks";354;1
"Unit";"Marine";"Barracks";355;1
"Unit";"Marine";"Barracks";356;1
"Unit";"Marine";"Barracks";357;1
"Unit";"Marine";"Barracks";358;1
"Unit";"Marine";"Barracks";359;1
"Unit";"Marine";"Barracks";360;1
"Unit";"Marine";"Barracks";361;1
"Building";"Refinery";NA;362;0
"Building";"Factory";NA;362;0
"Building";"Starport";NA;362;0
"Unit";"Marauder";"Barracks";362;2
"Building";"CommandCenter";NA;364;0
"Unit";"Marine";"Barracks";364;1
"Unit";"Marine";"Barracks";365;1
"Unit";"Thor";"Factory";366;6
"Unit";"Marine";"Barracks";372;1
"Unit";"Marine";"Barracks";373;1
"Unit";"Marine";"Barracks";374;1
"Unit";"Marine";"Barracks";375;1
"Unit";"Marine";"Barracks";376;1
"Unit";"Marine";"Barracks";377;1
"Unit";"Marauder";"Barracks";378;2
"Unit";"Marauder";"Barracks";380;2
"Unit";"Marine";"Barracks";382;1
"Unit";"Marauder";"Barracks";383;2
"Unit";"Marine";"Barracks";385;1
"Unit";"Marine";"Barracks";386;1
"Unit";"Marine";"Barracks";387;1
"Unit";"Marine";"Barracks";388;1
"Unit";"Marine";"Barracks";389;1
"Unit";"Marine";"Barracks";390;1
"Unit";"Marine";"Barracks";391;1
"Unit";"Liberator";"Starport";392;3
"Unit";"Marauder";"Barracks";395;2
"Unit";"Marauder";"Barracks";397;2
"Unit";"Marine";"Barracks";399;1
"Unit";"Marine";"Barracks";400;1
"Building";"Refinery";NA;401;0
"Unit";"Marauder";"Barracks";401;2
"Unit";"Marine";"Barracks";403;1
"Unit";"Marauder";"Barracks";404;2
"Unit";"Marine";"Barracks";406;1
"Unit";"Marine";"Barracks";407;1
"Unit";"Marine";"Barracks";408;1
"Unit";"Marine";"Barracks";409;1
"Unit";"Marauder";"Barracks";410;2
"Unit";"Marauder";"Barracks";412;2
"Upgrade";"SprayTerran";NA;414;0
"Upgrade";"SprayTerran";NA;414;0
"Upgrade";"SprayTerran";NA;414;0
"Upgrade";"SprayTerran";NA;414;0
"Upgrade";"ShieldWall";NA;414;0
"Upgrade";"PunisherGrenades";NA;414;0
"Upgrade";"TerranInfantryArmorsLevel1";NA;414;0
"Upgrade";"TerranVehicleAndShipArmorsLevel1";NA;414;0
"Upgrade";"SprayTerran";NA;414;0
"Upgrade";"SprayTerran";NA;414;0
"Upgrade";"TerranInfantryArmorsLevel2";NA;414;0
"Upgrade";"SprayTerran";NA;414;0
"Upgrade";"SprayTerran";NA;414;0
"Upgrade";"DrillClaws";NA;414;0
"Upgrade";"TerranInfantryArmorsLevel3";NA;414;0
"Upgrade";"SprayTerran";NA;414;0
"Upgrade";"TerranVehicleAndShipArmorsLevel2";NA;414;0
"Upgrade";"SprayTerran";NA;414;0
