"type";"unit_name";"on_building";"total_supply_lag";"supply"
"Building";"Refinery";NA;15;0
"Building";"Barracks";NA;16;0
"Unit";"Reaper";"Barracks";19;1
"Building";"CommandCenter";NA;20;0
"Building";"Factory";NA;20;0
"Building";"BarracksReactor";NA;21;0
"Building";"Refinery";NA;22;0
"Unit";"Marine";"Barracks";24;1
"Unit";"Marine";"Barracks";25;1
"Building";"Starport";NA;26;0
"Unit";"Marine";"Barracks";27;1
"Unit";"Marine";"Barracks";28;1
"Unit";"Marine";"Barracks";31;1
"Unit";"Marine";"Barracks";32;1
"Unit";"Medivac";"Starport";33;2
"Building";"CommandCenter";NA;39;0
"Unit";"Marine";"Barracks";39;1
"Unit";"Marine";"Barracks";40;1
"Building";"EngineeringBay";NA;43;0
"Building";"EngineeringBay";NA;43;0
"Building";"BarracksTechLab";NA;46;0
"Building";"Barracks";NA;46;0
"Building";"Barracks";NA;46;0
"Building";"FactoryReactor";NA;46;0
"Building";"Refinery";NA;47;0
"Building";"Refinery";NA;47;0
"Unit";"Marine";"Barracks";51;1
"Building";"StarportReactor";NA;53;0
"Building";"FactoryReactor";NA;54;0
"Upgrade";"Stimpack";"TechLab";55;0
"Unit";"Marine";"Barracks";55;1
"Unit";"Marine";"Barracks";56;1
"Unit";"Marine";"Barracks";57;1
"Unit";"Marine";"Barracks";58;1
"Unit";"Marine";"Barracks";59;1
"Upgrade";"TerranInfantryWeaponsLevel1";"EngineeringBay";62;0
"Unit";"Marine";"Barracks";63;1
"Unit";"Marine";"Barracks";64;1
"Unit";"Marine";"Barracks";66;1
"Unit";"Marine";"Barracks";67;1
"Building";"Barracks";NA;68;0
"Unit";"Marine";"Barracks";68;1
"Building";"Barracks";NA;70;0
"Unit";"Medivac";"Starport";71;2
"Unit";"Medivac";"Starport";75;2
"Building";"Armory";NA;77;0
"Unit";"Marine";"Barracks";78;1
"Unit";"Marine";"Barracks";79;1
"Unit";"Marine";"Barracks";80;1
"Unit";"Marine";"Barracks";81;1
"Unit";"Marine";"Barracks";82;1
"Unit";"Marine";"Barracks";85;1
"Building";"BarracksReactor";NA;87;0
"Building";"BarracksReactor";NA;87;0
"Unit";"Marine";"Barracks";89;1
"Unit";"Marine";"Barracks";90;1
"Unit";"Marine";"Barracks";91;1
"Unit";"Marine";"Barracks";92;1
"Unit";"Marine";"Barracks";93;1
"Unit";"Marine";"Barracks";94;1
"Unit";"Marine";"Barracks";95;1
"Unit";"Marine";"Barracks";96;1
"Unit";"Marine";"Barracks";97;1
"Unit";"Marine";"Barracks";98;1
"Unit";"Medivac";"Starport";99;2
"Building";"Barracks";NA;101;0
"Building";"Barracks";NA;101;0
"Building";"Barracks";NA;101;0
"Unit";"Medivac";"Starport";101;2
"Unit";"Marine";"Barracks";103;1
"Unit";"Marine";"Barracks";104;1
"Unit";"Marine";"Barracks";105;1
"Unit";"Marine";"Barracks";106;1
"Unit";"Marine";"Barracks";107;1
"Unit";"Marine";"Barracks";108;1
"Unit";"Marine";"Barracks";109;1
"Unit";"Marine";"Barracks";110;1
"Unit";"Marine";"Barracks";111;1
"Unit";"Marine";"Barracks";112;1
"Unit";"Marine";"Barracks";113;1
"Unit";"Marine";"Barracks";114;1
"Unit";"Marine";"Barracks";115;1
"Upgrade";"TerranInfantryWeaponsLevel2";"EngineeringBay";116;0
"Unit";"Marine";"Barracks";116;1
"Unit";"Medivac";"Starport";117;2
"Unit";"Marine";"Barracks";119;1
"Unit";"Marine";"Barracks";120;1
"Unit";"Medivac";"Starport";121;2
"Unit";"Marine";"Barracks";123;1
"Unit";"Marine";"Barracks";124;1
"Unit";"Marine";"Barracks";125;1
"Unit";"Marine";"Barracks";126;1
"Building";"BarracksTechLab";NA;127;0
"Building";"BarracksReactor";NA;127;0
"Building";"BarracksTechLab";NA;127;0
"Unit";"Marine";"Barracks";127;1
"Unit";"Marine";"Barracks";128;1
"Unit";"Marine";"Barracks";129;1
"Unit";"Marine";"Barracks";130;1
"Unit";"Marauder";"Barracks";131;2
"Unit";"Marine";"Barracks";133;1
"Unit";"Medivac";"Starport";134;2
"Unit";"Medivac";"Starport";136;2
"Unit";"Marauder";"Barracks";138;2
"Unit";"Marine";"Barracks";140;1
"Unit";"Marauder";"Barracks";141;2
"Unit";"Marine";"Barracks";143;1
"Unit";"Marauder";"Barracks";144;2
"Unit";"Marine";"Barracks";146;1
"Unit";"Marine";"Barracks";147;1
"Unit";"Marine";"Barracks";148;1
"Unit";"Marine";"Barracks";149;1
"Unit";"Marine";"Barracks";150;1
"Unit";"Marine";"Barracks";151;1
"Unit";"Marine";"Barracks";152;1
"Unit";"Marine";"Barracks";153;1
"Unit";"Marine";"Barracks";154;1
"Unit";"Marine";"Barracks";155;1
"Unit";"Marine";"Barracks";156;1
"Unit";"Marine";"Barracks";157;1
"Unit";"Marauder";"Barracks";158;2
"Unit";"Marine";"Barracks";160;1
"Unit";"Medivac";"Starport";161;2
"Unit";"Marauder";"Barracks";163;2
"Unit";"Marauder";"Barracks";165;2
"Unit";"Marine";"Barracks";167;1
"Unit";"Marine";"Barracks";168;1
"Unit";"Marine";"Barracks";169;1
"Unit";"Marine";"Barracks";170;1
"Unit";"Marine";"Barracks";171;1
"Unit";"Marine";"Barracks";172;1
"Unit";"Marine";"Barracks";173;1
"Unit";"Marine";"Barracks";174;1
"Unit";"Marauder";"Barracks";175;2
"Unit";"Marauder";"Barracks";177;2
"Unit";"Marauder";"Barracks";179;2
"Unit";"Marine";"Barracks";181;1
"Unit";"Marine";"Barracks";182;1
"Unit";"Marine";"Barracks";183;1
"Unit";"Marine";"Barracks";184;1
"Unit";"Marine";"Barracks";185;1
"Unit";"Marine";"Barracks";186;1
"Unit";"Medivac";"Starport";187;2
"Unit";"Marauder";"Barracks";189;2
"Unit";"Marauder";"Barracks";191;2
"Unit";"Marauder";"Barracks";193;2
"Unit";"Marine";"Barracks";195;1
"Unit";"Marine";"Barracks";196;1
"Unit";"Marine";"Barracks";197;1
"Unit";"Marine";"Barracks";198;1
"Unit";"Marine";"Barracks";199;1
"Upgrade";"SprayTerran";NA;200;0
"Upgrade";"SprayTerran";NA;200;0
"Upgrade";"SprayTerran";NA;200;0
"Upgrade";"SprayTerran";NA;200;0
"Upgrade";"TerranInfantryArmorsLevel1";NA;200;0
"Upgrade";"ShieldWall";NA;200;0
"Upgrade";"TerranInfantryArmorsLevel2";NA;200;0
