"type";"unit_name";"on_building";"total_supply_lag";"supply"
"Building";"Barracks";NA;16;0
"Building";"Refinery";NA;16;0
"Unit";"Marine";"Barracks";19;1
"Building";"CommandCenter";NA;20;0
"Unit";"Marine";"Barracks";20;1
"Building";"BarracksReactor";NA;22;0
"Building";"Factory";NA;22;0
"Building";"Refinery";NA;23;0
"Unit";"Marine";"Barracks";25;1
"Unit";"Marine";"Barracks";26;1
"Building";"Starport";NA;28;0
"Unit";"Marine";"Barracks";29;1
"Unit";"Marine";"Barracks";30;1
"Unit";"Marine";"Barracks";34;1
"Unit";"Marine";"Barracks";35;1
"Building";"FactoryTechLab";NA;36;0
"Unit";"Medivac";"Starport";36;2
"Building";"CommandCenter";NA;42;0
"Unit";"Medivac";"Starport";44;2
"Unit";"Marine";"Barracks";46;1
"Unit";"Marine";"Barracks";47;1
"Building";"Barracks";NA;51;0
"Unit";"Marine";"Barracks";51;1
"Building";"Barracks";NA;52;0
"Unit";"Liberator";"Starport";53;3
"Building";"FactoryReactor";NA;56;0
"Unit";"Marine";"Barracks";59;1
"Building";"EngineeringBay";NA;61;0
"Building";"EngineeringBay";NA;61;0
"Building";"Refinery";NA;62;0
"Upgrade";"Stimpack";"TechLab";62;0
"Building";"Refinery";NA;62;0
"Building";"Barracks";NA;63;0
"Unit";"Marine";"Barracks";63;1
"Building";"FactoryReactor";NA;65;0
"Unit";"Marine";"Barracks";66;1
"Unit";"Marine";"Barracks";67;1
"Building";"StarportReactor";NA;68;0
"Building";"Barracks";NA;69;0
"Unit";"Marine";"Barracks";70;1
"Unit";"Marine";"Barracks";71;1
"Unit";"Marine";"Barracks";72;1
"Unit";"Marine";"Barracks";74;1
"Unit";"Marine";"Barracks";75;1
"Unit";"Marine";"Barracks";79;1
"Unit";"Marine";"Barracks";81;1
"Unit";"Marine";"Barracks";82;1
"Building";"BarracksReactor";NA;83;0
"Unit";"Medivac";"Starport";83;2
"Unit";"Medivac";"Starport";85;2
"Upgrade";"TerranInfantryWeaponsLevel1";"EngineeringBay";87;0
"Unit";"Marine";"Barracks";87;1
"Unit";"Marine";"Barracks";90;1
"Unit";"Marine";"Barracks";91;1
"Unit";"Marine";"Barracks";92;1
"Building";"BarracksReactor";NA;93;0
"Unit";"Marine";"Barracks";94;1
"Unit";"Marine";"Barracks";95;1
"Unit";"Marine";"Barracks";98;1
"Unit";"Marine";"Barracks";99;1
"Unit";"Marine";"Barracks";100;1
"Unit";"Marine";"Barracks";101;1
"Unit";"Marine";"Barracks";102;1
"Unit";"Medivac";"Starport";103;2
"Unit";"Medivac";"Starport";105;2
"Unit";"Marine";"Barracks";108;1
"Unit";"Marine";"Barracks";109;1
"Unit";"Marine";"Barracks";110;1
"Unit";"Marine";"Barracks";111;1
"Unit";"Marine";"Barracks";112;1
"Unit";"Marine";"Barracks";113;1
"Unit";"Marine";"Barracks";114;1
"Unit";"Marine";"Barracks";115;1
"Unit";"Marine";"Barracks";116;1
"Unit";"Marine";"Barracks";120;1
"Unit";"Marine";"Barracks";121;1
"Unit";"Marine";"Barracks";122;1
"Unit";"Marine";"Barracks";123;1
"Unit";"Marine";"Barracks";124;1
"Unit";"Marine";"Barracks";125;1
"Unit";"Marine";"Barracks";126;1
"Unit";"Marine";"Barracks";127;1
"Unit";"Marine";"Barracks";131;1
"Unit";"Medivac";"Starport";132;2
"Unit";"Medivac";"Starport";134;2
"Building";"Armory";NA;136;0
"Unit";"Marine";"Barracks";136;1
"Unit";"Marine";"Barracks";137;1
"Unit";"Marauder";"Barracks";138;2
"Unit";"Marine";"Barracks";140;1
"Unit";"Marine";"Barracks";141;1
"Unit";"Marine";"Barracks";142;1
"Unit";"Marine";"Barracks";143;1
"Unit";"Marine";"Barracks";144;1
"Unit";"Marine";"Barracks";145;1
"Unit";"Marine";"Barracks";146;1
"Unit";"Marine";"Barracks";147;1
"Unit";"Marauder";"Barracks";148;2
"Building";"Barracks";NA;150;0
"Building";"Barracks";NA;150;0
"Building";"Barracks";NA;150;0
"Unit";"Marine";"Barracks";150;1
"Unit";"Marine";"Barracks";151;1
"Unit";"Marine";"Barracks";152;1
"Unit";"Marine";"Barracks";153;1
"Building";"MissileTurret";NA;154;0
"Building";"MissileTurret";NA;154;0
"Building";"MissileTurret";NA;154;0
"Unit";"Marine";"Barracks";154;1
"Unit";"Marine";"Barracks";155;1
"Unit";"Marine";"Barracks";156;1
"Unit";"Marine";"Barracks";157;1
"Unit";"Medivac";"Starport";158;2
"Unit";"Medivac";"Starport";160;2
"Building";"Refinery";NA;162;0
"Unit";"Marauder";"Barracks";162;2
"Unit";"Marine";"Barracks";164;1
"Unit";"Marine";"Barracks";165;1
"Unit";"Marine";"Barracks";166;1
"Unit";"Marine";"Barracks";167;1
"Building";"MissileTurret";NA;168;0
"Unit";"Marine";"Barracks";168;1
"Unit";"Marine";"Barracks";169;1
"Unit";"Marine";"Barracks";170;1
"Unit";"Marine";"Barracks";171;1
"Unit";"Marauder";"Barracks";172;2
"Unit";"Marine";"Barracks";174;1
"Unit";"Marine";"Barracks";175;1
"Unit";"Marine";"Barracks";176;1
"Unit";"Marine";"Barracks";177;1
"Building";"BarracksTechLab";NA;178;0
"Building";"BarracksTechLab";NA;178;0
"Building";"BarracksReactor";NA;178;0
"Unit";"Medivac";"Starport";178;2
"Unit";"Medivac";"Starport";180;2
"Unit";"Marine";"Barracks";182;1
"Unit";"Marauder";"Barracks";183;2
"Upgrade";"TerranInfantryWeaponsLevel2";"EngineeringBay";185;0
"Unit";"Marauder";"Barracks";185;2
"Unit";"Marine";"Barracks";187;1
"Unit";"Marine";"Barracks";188;1
"Unit";"Marine";"Barracks";189;1
"Unit";"Marine";"Barracks";190;1
"Unit";"Marine";"Barracks";191;1
"Unit";"Marine";"Barracks";192;1
"Unit";"Marine";"Barracks";193;1
"Unit";"Marine";"Barracks";194;1
"Unit";"Marine";"Barracks";195;1
"Unit";"Marine";"Barracks";196;1
"Unit";"Medivac";"Starport";197;2
"Unit";"Medivac";"Starport";199;2
"Unit";"Marauder";"Barracks";201;2
"Unit";"Marine";"Barracks";203;1
"Unit";"Marine";"Barracks";204;1
"Unit";"Marine";"Barracks";205;1
"Unit";"Marine";"Barracks";206;1
"Unit";"Marine";"Barracks";207;1
"Unit";"Marine";"Barracks";208;1
"Unit";"Marine";"Barracks";209;1
"Unit";"Marine";"Barracks";210;1
"Unit";"Marine";"Barracks";211;1
"Unit";"Marauder";"Barracks";212;2
"Unit";"Marine";"Barracks";214;1
"Unit";"Marine";"Barracks";215;1
"Unit";"Marine";"Barracks";216;1
"Unit";"Marine";"Barracks";217;1
"Unit";"Marauder";"Barracks";218;2
"Unit";"Marine";"Barracks";220;1
"Building";"CommandCenter";NA;221;0
"Unit";"Marauder";"Barracks";221;2
"Unit";"Marine";"Barracks";223;1
"Unit";"Marine";"Barracks";224;1
"Unit";"Marine";"Barracks";225;1
"Unit";"Marine";"Barracks";226;1
"Unit";"Liberator";"Starport";227;3
"Unit";"Marine";"Barracks";230;1
"Unit";"Marine";"Barracks";231;1
"Unit";"Marauder";"Barracks";232;2
"Unit";"Marine";"Barracks";234;1
"Unit";"Marauder";"Barracks";235;2
"Unit";"Marine";"Barracks";237;1
"Unit";"Marauder";"Barracks";238;2
"Unit";"Marine";"Barracks";240;1
"Unit";"Marine";"Barracks";241;1
"Unit";"Marine";"Barracks";242;1
"Unit";"Marine";"Barracks";243;1
"Unit";"Marauder";"Barracks";244;2
"Unit";"Marine";"Barracks";246;1
"Unit";"Marine";"Barracks";247;1
"Unit";"Marine";"Barracks";248;1
"Unit";"Marine";"Barracks";249;1
"Unit";"Marine";"Barracks";250;1
"Upgrade";"SprayTerran";NA;251;0
"Upgrade";"SprayTerran";NA;251;0
"Upgrade";"SprayTerran";NA;251;0
"Upgrade";"SprayTerran";NA;251;0
"Upgrade";"TerranInfantryArmorsLevel1";NA;251;0
"Upgrade";"ShieldWall";NA;251;0
"Upgrade";"SprayTerran";NA;251;0
"Upgrade";"SprayTerran";NA;251;0
