"type";"unit_name";"on_building";"total_supply";"supply"
"Unit";"Overlord";"Larva";13;0
"Building";"SpawningPool";NA;16;0
"Building";"Extractor";NA;18;0
"Unit";"Zergling";"Larva";21;1
"Unit";"Zergling";"Larva";21;1
"Unit";"Zergling";"Larva";21;1
"Unit";"Zergling";"Larva";21;1
"Unit";"Overlord";"Larva";21;0
"Unit";"Queen";"Hatchery";21;2
"Building";"Hatchery";NA;18;0
"Building";"RoachWarren";NA;25;0
"Unit";"Queen";"Hatchery";29;2
"Unit";"Roach";"Larva";29;2
"Unit";"Roach";"Larva";29;2
"Unit";"Roach";"Larva";29;2
"Unit";"Roach";"Larva";29;2
"Unit";"Overlord";"Larva";29;0
"Unit";"Overlord";"Larva";44;0
"Unit";"Overlord";"Larva";55;0
"Unit";"Overlord";"Larva";55;0
"Building";"Extractor";NA;55;0
"Building";"Extractor";NA;55;0
"Building";"EvolutionChamber";NA;55;0
"Building";"CreepTumorQueen";NA;69;0
"Unit";"Roach";"Larva";67;2
"Unit";"Roach";"Larva";67;2
"Unit";"Overlord";"Larva";69;0
"Unit";"Overlord";"Larva";69;0
"Unit";"Overlord";"Larva";69;0
"Unit";"Roach";"Larva";69;2
"Unit";"Overlord";"Larva";69;0
"Unit";"Overlord";"Larva";69;0
"Unit";"Overlord";"Larva";69;0
"Unit";"Overlord";"Larva";69;0
"Building";"CreepTumor";NA;75;0
"Unit";"Roach";"Larva";75;2
"Unit";"Roach";"Larva";75;2
"Unit";"Roach";"Larva";75;2
"Unit";"Roach";"Larva";75;2
"Unit";"Roach";"Larva";75;2
"Unit";"Roach";"Larva";75;2
"Unit";"Queen";"Hatchery";73;2
"Building";"Hatchery";NA;61;0
"Unit";"Roach";"Larva";75;2
"Unit";"Roach";"Larva";75;2
"Unit";"Overlord";"Larva";87;0
"Unit";"Overlord";"Larva";87;0
"Building";"CreepTumor";NA;92;0
"Building";"Extractor";NA;90;0
"Building";"CreepTumorQueen";NA;94;0
"Unit";"Roach";"Larva";94;2
"Unit";"Roach";"Larva";94;2
"Unit";"Roach";"Larva";94;2
"Unit";"Roach";"Larva";94;2
"Unit";"Roach";"Larva";94;2
"Upgrade";"ZergMissileWeaponsLevel1";"EvolutionChamber";69;0
"Building";"CreepTumor";NA;94;0
"Unit";"Queen";"Hatchery";94;2
"Unit";"Roach";"Larva";98;2
"Unit";"Roach";"Larva";98;2
"Unit";"Roach";"Larva";98;2
"Unit";"Roach";"Larva";98;2
"Upgrade";"GlialReconstitution";"RoachWarren";87;0
"Unit";"Roach";"Larva";98;2
"Unit";"Roach";"Larva";98;2
"Building";"CreepTumor";NA;108;0
"Building";"CreepTumorQueen";NA;108;0
"Unit";"Roach";"Larva";110;2
"Building";"CreepTumor";NA;124;0
"Unit";"Zergling";"Larva";112;1
"Unit";"Zergling";"Larva";112;1
"Unit";"Zergling";"Larva";116;1
"Unit";"Zergling";"Larva";116;1
"Unit";"Zergling";"Larva";118;1
"Unit";"Zergling";"Larva";118;1
"Unit";"Roach";"Larva";124;2
"Unit";"Roach";"Larva";124;2
"Unit";"Zergling";"Larva";132;1
"Unit";"Zergling";"Larva";132;1
"Unit";"Zergling";"Larva";132;1
"Unit";"Zergling";"Larva";132;1
"Unit";"Zergling";"Larva";132;1
"Unit";"Zergling";"Larva";132;1
"Unit";"Overlord";"Larva";136;0
"Unit";"Overlord";"Larva";136;0
"Unit";"Overlord";"Larva";136;0
"Unit";"Overlord";"Larva";136;0
"Unit";"Overlord";"Larva";136;0
"Unit";"Overlord";"Larva";138;0
"Unit";"Overlord";"Larva";142;0
"Unit";"Overlord";"Larva";142;0
"Unit";"Zergling";"Larva";142;1
"Unit";"Zergling";"Larva";142;1
"Unit";"Zergling";"Larva";142;1
"Unit";"Zergling";"Larva";142;1
"Unit";"Zergling";"Larva";142;1
"Unit";"Zergling";"Larva";142;1
"Unit";"Zergling";"Larva";142;1
"Unit";"Zergling";"Larva";142;1
"Unit";"Zergling";"Larva";142;1
"Unit";"Zergling";"Larva";142;1
"Unit";"Zergling";"Larva";142;1
"Unit";"Zergling";"Larva";142;1
"Unit";"Zergling";"Larva";142;1
"Unit";"Zergling";"Larva";142;1
"Unit";"Zergling";"Larva";142;1
"Unit";"Zergling";"Larva";142;1
"Unit";"Zergling";"Larva";142;1
"Unit";"Zergling";"Larva";142;1
"Unit";"Zergling";"Larva";142;1
"Unit";"Zergling";"Larva";142;1
"Unit";"Zergling";"Larva";142;1
"Unit";"Zergling";"Larva";142;1
"Building";"CreepTumor";NA;142;0
"Unit";"Zergling";"Larva";142;1
"Unit";"Zergling";"Larva";142;1
"Unit";"Overlord";"Larva";168;0
"Unit";"Overlord";"Larva";168;0
"Unit";"Zergling";"Larva";168;1
"Unit";"Zergling";"Larva";168;1
"Unit";"Zergling";"Larva";168;1
"Unit";"Zergling";"Larva";168;1
"Unit";"Zergling";"Larva";168;1
"Unit";"Zergling";"Larva";168;1
"Unit";"Zergling";"Larva";168;1
"Unit";"Zergling";"Larva";168;1
"Unit";"Zergling";"Larva";168;1
"Unit";"Zergling";"Larva";168;1
"Unit";"Zergling";"Larva";168;1
"Unit";"Zergling";"Larva";168;1
"Unit";"Zergling";"Larva";168;1
"Unit";"Zergling";"Larva";168;1
"Unit";"Zergling";"Larva";168;1
"Unit";"Zergling";"Larva";168;1
"Unit";"Zergling";"Larva";168;1
"Unit";"Zergling";"Larva";168;1
"Unit";"Zergling";"Larva";168;1
"Unit";"Zergling";"Larva";168;1
"Unit";"Zergling";"Larva";168;1
"Unit";"Zergling";"Larva";168;1
"Unit";"Zergling";"Larva";168;1
"Unit";"Zergling";"Larva";168;1
"Building";"CreepTumor";NA;188;0
"Unit";"Roach";"Larva";170;2
"Unit";"Roach";"Larva";178;2
"Unit";"Roach";"Larva";184;2
"Unit";"Roach";"Larva";188;2
"Unit";"Roach";"Larva";188;2
"Unit";"Roach";"Larva";188;2
"Unit";"Roach";"Larva";200;2
"Unit";"Roach";"Larva";200;2
"Unit";"Roach";"Larva";200;2
"Unit";"Roach";"Larva";200;2
"Unit";"Roach";"Larva";200;2
"Unit";"Roach";"Larva";200;2
"Unit";"Roach";"Larva";200;2
"Building";"Hatchery";NA;168;0
"Building";"Extractor";NA;218;0
"Unit";"Zergling";"Larva";218;1
"Unit";"Zergling";"Larva";218;1
"Unit";"Zergling";"Larva";218;1
"Unit";"Zergling";"Larva";218;1
"Unit";"Zergling";"Larva";218;1
"Unit";"Zergling";"Larva";218;1
"Unit";"Zergling";"Larva";218;1
"Unit";"Zergling";"Larva";218;1
"Building";"CreepTumor";NA;229;0
"Building";"CreepTumor";NA;229;0
"Unit";"Overlord";"Larva";229;0
"Building";"CreepTumorQueen";NA;235;0
"Upgrade";"ZergMissileWeaponsLevel2";"EvolutionChamber";168;0
"Building";"CreepTumorQueen";NA;237;0
"Unit";"Zergling";"Larva";237;1
"Unit";"Zergling";"Larva";237;1
"Unit";"Zergling";"Larva";237;1
"Unit";"Zergling";"Larva";237;1
"Building";"CreepTumor";NA;237;0
"Building";"CreepTumorQueen";NA;237;0
"Building";"InfestationPit";NA;229;0
"Unit";"Overlord";"Larva";237;0
"Unit";"Overlord";"Larva";237;0
"Unit";"Zergling";"Larva";241;1
"Unit";"Zergling";"Larva";241;1
"Unit";"Zergling";"Larva";241;1
"Unit";"Zergling";"Larva";241;1
"Unit";"Zergling";"Larva";241;1
"Unit";"Zergling";"Larva";241;1
"Unit";"Zergling";"Larva";241;1
"Unit";"Zergling";"Larva";241;1
"Unit";"Zergling";"Larva";241;1
"Unit";"Zergling";"Larva";241;1
"Building";"Extractor";NA;241;0
"Building";"EvolutionChamber";NA;241;0
"Building";"SpineCrawler";NA;237;0
"Building";"Extractor";NA;241;0
"Building";"SpineCrawler";NA;237;0
"Unit";"Zergling";"Larva";241;1
"Unit";"Zergling";"Larva";241;1
"Unit";"Overlord";"Larva";263;0
"Unit";"Overlord";"Larva";263;0
"Unit";"Roach";"Larva";263;2
"Unit";"Roach";"Larva";263;2
"Unit";"Roach";"Larva";263;2
"Unit";"Roach";"Larva";263;2
"Unit";"Roach";"Larva";263;2
"Unit";"Roach";"Larva";263;2
"Unit";"Roach";"Larva";263;2
"Unit";"Roach";"Larva";263;2
"Unit";"Roach";"Larva";263;2
"Unit";"Roach";"Larva";263;2
"Unit";"Infestor";"Larva";261;2
"Unit";"Roach";"Larva";263;2
"Unit";"Zergling";"Larva";263;1
"Unit";"Zergling";"Larva";263;1
"Unit";"Roach";"Larva";263;2
"Unit";"Zergling";"Larva";263;1
"Unit";"Zergling";"Larva";263;1
"Unit";"Roach";"Larva";263;2
"Unit";"Zergling";"Larva";263;1
"Unit";"Zergling";"Larva";263;1
"Unit";"Roach";"Larva";263;2
"Unit";"Roach";"Larva";263;2
"Unit";"Roach";"Larva";263;2
"Unit";"Roach";"Larva";263;2
"Unit";"Roach";"Larva";263;2
"Unit";"Roach";"Larva";263;2
"Unit";"Roach";"Larva";263;2
"Building";"CreepTumor";NA;311;0
"Unit";"Queen";"Hatchery";263;2
"Unit";"Roach";"Larva";311;2
"Unit";"Roach";"Larva";311;2
"Unit";"Roach";"Larva";311;2
"Unit";"Roach";"Larva";311;2
"Unit";"Roach";"Larva";311;2
"Unit";"Roach";"Larva";311;2
"Unit";"Roach";"Larva";311;2
"Unit";"Roach";"Larva";311;2
"Unit";"Roach";"Larva";311;2
"Unit";"Overlord";"Larva";313;0
"Unit";"Overlord";"Larva";313;0
"Unit";"Overlord";"Larva";313;0
"Unit";"Overlord";"Larva";313;0
"Unit";"Roach";"Larva";331;2
"Unit";"Roach";"Larva";331;2
"Unit";"Roach";"Larva";331;2
"Unit";"Roach";"Larva";331;2
"Unit";"Roach";"Larva";331;2
"Unit";"Roach";"Larva";331;2
"Unit";"Roach";"Larva";331;2
