"type";"unit_name";"on_building";"total_supply";"supply"
"Unit";"Overlord";"Larva";12;0
"Building";"Extractor";NA;14;0
"Building";"SpawningPool";NA;17;0
"Unit";"Zergling";"Larva";21;1
"Unit";"Zergling";"Larva";21;1
"Unit";"Overlord";"Larva";21;0
"Unit";"Queen";"Hatchery";20;2
"Building";"Hatchery";NA;19;0
"Unit";"Queen";"Hatchery";25;2
"Building";"SporeCrawler";NA;29;0
"Unit";"Overlord";"Larva";36;0
"Unit";"Queen";"Hatchery";39;2
"Building";"Extractor";NA;41;0
"Unit";"Zergling";"Larva";46;1
"Unit";"Zergling";"Larva";46;1
"Unit";"Zergling";"Larva";46;1
"Unit";"Zergling";"Larva";46;1
"Unit";"Zergling";"Larva";46;1
"Unit";"Zergling";"Larva";46;1
"Unit";"Zergling";"Larva";46;1
"Unit";"Zergling";"Larva";46;1
"Building";"CreepTumorQueen";NA;48;0
"Unit";"Overlord";"Larva";48;0
"Building";"BanelingNest";NA;44;0
"Building";"Extractor";NA;49;0
"Unit";"Overlord";"Larva";57;0
"Unit";"Zergling";"Larva";57;1
"Unit";"Zergling";"Larva";57;1
"Unit";"Zergling";"Larva";57;1
"Unit";"Zergling";"Larva";57;1
"Unit";"Zergling";"Larva";57;1
"Unit";"Zergling";"Larva";57;1
"Unit";"Zergling";"Larva";57;1
"Unit";"Zergling";"Larva";57;1
"Unit";"Zergling";"Larva";57;1
"Unit";"Zergling";"Larva";57;1
"Unit";"Zergling";"Larva";57;1
"Unit";"Zergling";"Larva";57;1
"Unit";"Baneling";"Zergling";58;0
"Unit";"Baneling";"Zergling";58;0
"Unit";"Baneling";"Zergling";58;0
"Unit";"Baneling";"Zergling";58;0
"Unit";"Baneling";"Zergling";58;0
"Unit";"Baneling";"Zergling";58;0
"Unit";"Baneling";"Zergling";58;0
"Unit";"Overlord";"Larva";58;0
"Unit";"Queen";"Hatchery";58;2
"Unit";"Zergling";"Larva";70;1
"Unit";"Zergling";"Larva";70;1
"Unit";"Zergling";"Larva";70;1
"Unit";"Zergling";"Larva";70;1
"Unit";"Zergling";"Larva";70;1
"Unit";"Zergling";"Larva";70;1
"Unit";"Zergling";"Larva";70;1
"Unit";"Zergling";"Larva";70;1
"Unit";"Zergling";"Larva";70;1
"Unit";"Zergling";"Larva";70;1
"Unit";"Zergling";"Larva";70;1
"Unit";"Zergling";"Larva";70;1
"Unit";"Zergling";"Larva";70;1
"Unit";"Zergling";"Larva";70;1
"Unit";"Zergling";"Larva";70;1
"Unit";"Zergling";"Larva";70;1
"Unit";"Zergling";"Larva";70;1
"Unit";"Zergling";"Larva";70;1
"Unit";"Baneling";"Zergling";82;0
"Unit";"Baneling";"Zergling";82;0
"Unit";"Zergling";"Larva";82;1
"Unit";"Zergling";"Larva";82;1
"Unit";"Zergling";"Larva";82;1
"Unit";"Zergling";"Larva";82;1
"Unit";"Zergling";"Larva";82;1
"Unit";"Zergling";"Larva";82;1
"Unit";"Baneling";"Zergling";82;0
"Unit";"Zergling";"Larva";82;1
"Unit";"Zergling";"Larva";82;1
"Unit";"Zergling";"Larva";82;1
"Unit";"Zergling";"Larva";82;1
"Unit";"Queen";"Hatchery";90;2
"Unit";"Overlord";"Larva";108;0
"Building";"Spire";NA;70;0
"Building";"Extractor";NA;110;0
"Unit";"Overlord";"Larva";110;0
"Unit";"Mutalisk";"Larva";116;2
"Unit";"Mutalisk";"Larva";116;2
"Unit";"Mutalisk";"Larva";116;2
"Unit";"Mutalisk";"Larva";116;2
"Unit";"Mutalisk";"Larva";116;2
"Unit";"Mutalisk";"Larva";116;2
"Unit";"Mutalisk";"Larva";116;2
"Building";"EvolutionChamber";NA;120;0
"Building";"EvolutionChamber";NA;120;0
"Unit";"Overlord";"Larva";132;0
"Unit";"Overlord";"Larva";132;0
"Building";"Hatchery";NA;116;0
"Unit";"Queen";"Hatchery";124;2
"Unit";"Overlord";"Larva";132;0
"Unit";"Zergling";"Larva";139;1
"Unit";"Zergling";"Larva";139;1
"Unit";"Zergling";"Larva";139;1
"Unit";"Zergling";"Larva";139;1
"Unit";"Zergling";"Larva";139;1
"Unit";"Zergling";"Larva";139;1
"Unit";"Zergling";"Larva";139;1
"Unit";"Zergling";"Larva";139;1
"Unit";"Zergling";"Larva";139;1
"Unit";"Zergling";"Larva";139;1
"Unit";"Zergling";"Larva";139;1
"Unit";"Zergling";"Larva";139;1
"Unit";"Zergling";"Larva";139;1
"Unit";"Zergling";"Larva";139;1
"Unit";"Zergling";"Larva";139;1
"Unit";"Zergling";"Larva";139;1
"Unit";"Zergling";"Larva";139;1
"Unit";"Zergling";"Larva";139;1
"Unit";"Zergling";"Larva";139;1
"Unit";"Zergling";"Larva";139;1
"Unit";"Zergling";"Larva";139;1
"Unit";"Zergling";"Larva";139;1
"Unit";"Zergling";"Larva";139;1
"Unit";"Zergling";"Larva";139;1
"Building";"HydraliskDen";NA;139;0
"Unit";"Overlord";"Larva";166;0
"Unit";"Hydralisk";"Larva";166;2
"Unit";"Hydralisk";"Larva";166;2
"Unit";"Hydralisk";"Larva";166;2
"Unit";"Hydralisk";"Larva";166;2
"Unit";"Hydralisk";"Larva";166;2
"Unit";"Hydralisk";"Larva";166;2
"Unit";"Hydralisk";"Larva";166;2
"Unit";"Hydralisk";"Larva";166;2
"Unit";"Hydralisk";"Larva";166;2
"Unit";"Overlord";"Larva";166;0
"Unit";"Overlord";"Larva";166;0
"Upgrade";"ZergGroundArmorsLevel1";"EvolutionChamber";139;0
"Unit";"Overlord";"Larva";185;0
"Unit";"Hydralisk";"Larva";169;2
"Unit";"Hydralisk";"Larva";185;2
"Unit";"Hydralisk";"Larva";185;2
"Unit";"Hydralisk";"Larva";185;2
"Unit";"Overlord";"Larva";185;0
"Unit";"Hydralisk";"Larva";185;2
"Unit";"Hydralisk";"Larva";185;2
"Unit";"Hydralisk";"Larva";185;2
"Unit";"Hydralisk";"Larva";185;2
"Unit";"Hydralisk";"Larva";185;2
"Building";"Extractor";NA;185;0
"Upgrade";"EvolveGroovedSpines";"HydraliskDen";167;0
"Upgrade";"ZergMissileWeaponsLevel1";"EvolutionChamber";166;0
"Building";"InfestationPit";NA;193;0
"Building";"Extractor";NA;210;0
"Unit";"Overlord";"Larva";214;0
"Unit";"Hydralisk";"Larva";214;2
"Unit";"Hydralisk";"Larva";214;2
"Unit";"Hydralisk";"Larva";214;2
"Unit";"Hydralisk";"Larva";214;2
"Unit";"Hydralisk";"Larva";214;2
"Unit";"Hydralisk";"Larva";214;2
"Unit";"Hydralisk";"Larva";214;2
"Unit";"Overlord";"Larva";214;0
"Unit";"Overlord";"Larva";214;0
"Building";"Extractor";NA;214;0
"Building";"Extractor";NA;214;0
"Unit";"Baneling";"Zergling";222;0
"Unit";"Baneling";"Zergling";224;0
"Unit";"Baneling";"Zergling";226;0
"Unit";"Baneling";"Zergling";226;0
"Upgrade";"EvolveMuscularAugments";"HydraliskDen";214;0
"Unit";"Hydralisk";"Larva";222;2
"Unit";"Hydralisk";"Larva";222;2
"Unit";"Hydralisk";"Larva";222;2
"Unit";"Hydralisk";"Larva";222;2
"Unit";"Hydralisk";"Larva";222;2
"Building";"Hatchery";NA;214;0
"Unit";"Overlord";"Larva";231;0
"Unit";"Queen";"Hatchery";244;2
"Unit";"Viper";"Larva";249;3
"Unit";"Viper";"Larva";249;3
"Unit";"Viper";"Larva";249;3
"Unit";"Viper";"Larva";249;3
"Building";"EvolutionChamber";NA;249;0
"Building";"EvolutionChamber";NA;249;0
"Building";"EvolutionChamber";NA;249;0
"Building";"EvolutionChamber";NA;249;0
"Unit";"Corruptor";"Larva";252;2
"Upgrade";"ZergMissileWeaponsLevel2";"EvolutionChamber";214;0
"Unit";"Corruptor";"Larva";253;2
"Unit";"Corruptor";"Larva";267;2
"Unit";"Corruptor";"Larva";267;2
"Unit";"Overlord";"Larva";271;0
"Unit";"Overlord";"Larva";271;0
"Unit";"Overlord";"Larva";279;0
"Unit";"Overlord";"Larva";279;0
"Unit";"Corruptor";"Larva";279;2
"Unit";"Corruptor";"Larva";279;2
"Building";"SpineCrawler";NA;279;0
"Building";"SpineCrawler";NA;279;0
"Building";"Hatchery";NA;271;0
"Unit";"Corruptor";"Larva";284;2
"Unit";"Corruptor";"Larva";284;2
"Unit";"Corruptor";"Larva";284;2
"Unit";"Corruptor";"Larva";284;2
"Unit";"Overlord";"Larva";284;0
"Unit";"Zergling";"Larva";284;1
"Unit";"Zergling";"Larva";284;1
"Unit";"Zergling";"Larva";284;1
"Unit";"Zergling";"Larva";284;1
"Unit";"Zergling";"Larva";284;1
"Unit";"Zergling";"Larva";284;1
"Unit";"Overlord";"Larva";292;0
"Unit";"Zergling";"Larva";298;1
"Unit";"Zergling";"Larva";298;1
"Unit";"Zergling";"Larva";298;1
"Unit";"Zergling";"Larva";298;1
"Unit";"Zergling";"Larva";298;1
"Unit";"Zergling";"Larva";298;1
"Unit";"Zergling";"Larva";298;1
"Unit";"Zergling";"Larva";298;1
"Unit";"Zergling";"Larva";298;1
"Unit";"Zergling";"Larva";298;1
"Unit";"Zergling";"Larva";298;1
"Unit";"Zergling";"Larva";298;1
"Unit";"Zergling";"Larva";298;1
"Unit";"Zergling";"Larva";298;1
"Unit";"Zergling";"Larva";298;1
"Unit";"Zergling";"Larva";298;1
"Unit";"Zergling";"Larva";298;1
"Unit";"Zergling";"Larva";298;1
"Unit";"Zergling";"Larva";298;1
"Unit";"Zergling";"Larva";298;1
"Unit";"Zergling";"Larva";298;1
"Unit";"Zergling";"Larva";298;1
"Unit";"Zergling";"Larva";298;1
"Unit";"Zergling";"Larva";298;1
"Unit";"Zergling";"Larva";298;1
"Unit";"Zergling";"Larva";298;1
"Unit";"Zergling";"Larva";298;1
"Unit";"Zergling";"Larva";298;1
"Unit";"Zergling";"Larva";298;1
"Unit";"Zergling";"Larva";298;1
"Unit";"Zergling";"Larva";298;1
"Unit";"Zergling";"Larva";298;1
"Unit";"Zergling";"Larva";298;1
"Unit";"Zergling";"Larva";298;1
"Unit";"Zergling";"Larva";298;1
"Unit";"Zergling";"Larva";298;1
"Unit";"Zergling";"Larva";298;1
"Unit";"Zergling";"Larva";298;1
"Unit";"Zergling";"Larva";298;1
"Unit";"Zergling";"Larva";298;1
"Unit";"Zergling";"Larva";298;1
"Unit";"Zergling";"Larva";298;1
"Unit";"Zergling";"Larva";298;1
"Unit";"Zergling";"Larva";298;1
"Unit";"Zergling";"Larva";298;1
"Unit";"Zergling";"Larva";298;1
"Unit";"Zergling";"Larva";298;1
"Unit";"Zergling";"Larva";298;1
"Unit";"Zergling";"Larva";298;1
"Unit";"Zergling";"Larva";298;1
"Unit";"Zergling";"Larva";298;1
"Unit";"Zergling";"Larva";298;1
"Unit";"Zergling";"Larva";298;1
"Unit";"Zergling";"Larva";298;1
"Unit";"Zergling";"Larva";298;1
"Unit";"Zergling";"Larva";298;1
"Unit";"Zergling";"Larva";298;1
"Unit";"Zergling";"Larva";298;1
"Unit";"Zergling";"Larva";298;1
"Unit";"Zergling";"Larva";298;1
"Upgrade";"ZergMeleeWeaponsLevel1";"EvolutionChamber";284;0
"Unit";"Queen";"Hatchery";298;2
"Unit";"Corruptor";"Larva";358;2
"Unit";"Corruptor";"Larva";358;2
"Unit";"Corruptor";"Larva";358;2
"Unit";"Corruptor";"Larva";358;2
"Unit";"Hydralisk";"Larva";358;2
"Unit";"Hydralisk";"Larva";358;2
"Unit";"Hydralisk";"Larva";358;2
"Unit";"Hydralisk";"Larva";358;2
"Unit";"Corruptor";"Larva";358;2
"Unit";"Corruptor";"Larva";358;2
"Unit";"Corruptor";"Larva";358;2
"Unit";"Corruptor";"Larva";368;2
"Unit";"Corruptor";"Larva";368;2
"Unit";"Corruptor";"Larva";368;2
"Unit";"Corruptor";"Larva";368;2
"Unit";"Corruptor";"Larva";368;2
"Unit";"Hydralisk";"Larva";382;2
"Unit";"Hydralisk";"Larva";382;2
"Unit";"Zergling";"Larva";405;1
"Unit";"Zergling";"Larva";405;1
"Unit";"Zergling";"Larva";406;1
"Unit";"Zergling";"Larva";406;1
"Unit";"Zergling";"Larva";407;1
"Unit";"Zergling";"Larva";407;1
"Unit";"Zergling";"Larva";407;1
"Unit";"Zergling";"Larva";407;1
"Unit";"Zergling";"Larva";407;1
"Unit";"Zergling";"Larva";407;1
"Unit";"Zergling";"Larva";407;1
"Unit";"Zergling";"Larva";407;1
"Unit";"Zergling";"Larva";408;1
"Unit";"Zergling";"Larva";408;1
"Unit";"Zergling";"Larva";408;1
"Unit";"Zergling";"Larva";408;1
"Unit";"Zergling";"Larva";408;1
"Unit";"Zergling";"Larva";408;1
"Unit";"Zergling";"Larva";408;1
"Unit";"Zergling";"Larva";408;1
"Building";"Extractor";NA;409;0
"Building";"Extractor";NA;409;0
"Unit";"Overlord";"Larva";433;0
"Unit";"Hydralisk";"Larva";433;2
"Unit";"Hydralisk";"Larva";433;2
"Unit";"Hydralisk";"Larva";433;2
"Unit";"Hydralisk";"Larva";433;2
"Unit";"Hydralisk";"Larva";433;2
"Unit";"Hydralisk";"Larva";433;2
"Unit";"Hydralisk";"Larva";433;2
"Unit";"Hydralisk";"Larva";433;2
"Unit";"Hydralisk";"Larva";433;2
"Upgrade";"ZergMeleeWeaponsLevel2";"EvolutionChamber";376;0
"Unit";"Overlord";"Larva";435;0
"Unit";"Overlord";"Larva";451;0
"Unit";"Corruptor";"Larva";451;2
"Unit";"Corruptor";"Larva";451;2
"Unit";"Corruptor";"Larva";451;2
"Unit";"Corruptor";"Larva";451;2
"Unit";"Corruptor";"Larva";451;2
"Unit";"Zergling";"Larva";451;1
"Unit";"Zergling";"Larva";451;1
"Unit";"Zergling";"Larva";451;1
"Unit";"Zergling";"Larva";451;1
"Unit";"Zergling";"Larva";451;1
"Unit";"Zergling";"Larva";451;1
"Unit";"Zergling";"Larva";451;1
"Unit";"Zergling";"Larva";451;1
"Unit";"Zergling";"Larva";451;1
"Unit";"Zergling";"Larva";451;1
"Unit";"Zergling";"Larva";451;1
"Unit";"Zergling";"Larva";451;1
"Unit";"Zergling";"Larva";452;1
"Unit";"Zergling";"Larva";452;1
"Unit";"Overlord";"Larva";466;0
"Unit";"Queen";"Hatchery";456;2
"Building";"SpineCrawler";NA;490;0
"Building";"SpineCrawler";NA;490;0
"Building";"SpineCrawler";NA;490;0
"Building";"SpineCrawler";NA;490;0
"Unit";"Overlord";"Larva";496;0
"Unit";"Overlord";"Larva";496;0
"Building";"Extractor";NA;496;0
"Building";"Extractor";NA;496;0
"Building";"Hatchery";NA;496;0
"Unit";"Zergling";"Larva";496;1
"Unit";"Zergling";"Larva";496;1
"Unit";"Zergling";"Larva";496;1
"Unit";"Zergling";"Larva";496;1
"Unit";"Zergling";"Larva";496;1
"Unit";"Zergling";"Larva";496;1
"Unit";"Zergling";"Larva";496;1
"Unit";"Zergling";"Larva";496;1
"Unit";"Zergling";"Larva";496;1
"Unit";"Zergling";"Larva";496;1
"Unit";"Zergling";"Larva";496;1
"Unit";"Zergling";"Larva";496;1
"Unit";"Zergling";"Larva";496;1
"Unit";"Zergling";"Larva";496;1
"Unit";"Zergling";"Larva";496;1
"Unit";"Zergling";"Larva";496;1
"Unit";"Zergling";"Larva";496;1
"Unit";"Zergling";"Larva";496;1
"Unit";"Zergling";"Larva";496;1
"Unit";"Zergling";"Larva";496;1
"Unit";"Zergling";"Larva";496;1
"Unit";"Zergling";"Larva";496;1
"Unit";"Zergling";"Larva";496;1
"Unit";"Zergling";"Larva";496;1
"Unit";"Zergling";"Larva";496;1
"Unit";"Zergling";"Larva";496;1
"Unit";"Zergling";"Larva";496;1
"Unit";"Zergling";"Larva";496;1
"Upgrade";"ZergMeleeWeaponsLevel3";"EvolutionChamber";490;0
"Upgrade";"Burrow";"Hatchery";496;0
"Unit";"Corruptor";"Larva";496;2
"Unit";"Corruptor";"Larva";496;2
"Unit";"Corruptor";"Larva";496;2
"Unit";"Corruptor";"Larva";496;2
"Unit";"Corruptor";"Larva";496;2
"Unit";"Corruptor";"Larva";496;2
"Unit";"Corruptor";"Larva";496;2
"Unit";"Overlord";"Larva";532;0
"Building";"SporeCrawler";NA;530;0
"Unit";"Corruptor";"Larva";548;2
"Unit";"Corruptor";"Larva";548;2
"Unit";"Corruptor";"Larva";548;2
"Upgrade";"NeuralParasite";"InfestationPit";530;0
"Unit";"Corruptor";"Larva";554;2
"Unit";"Corruptor";"Larva";554;2
"Unit";"Corruptor";"Larva";554;2
"Unit";"Corruptor";"Larva";554;2
"Unit";"Corruptor";"Larva";554;2
"Unit";"Corruptor";"Larva";554;2
"Unit";"Corruptor";"Larva";554;2
"Unit";"Corruptor";"Larva";554;2
"Building";"Hatchery";NA;548;0
"Unit";"Hydralisk";"Larva";554;2
"Unit";"Queen";"Hatchery";554;2
"Building";"Extractor";NA;554;0
"Building";"Extractor";NA;570;0
"Building";"SpineCrawler";NA;554;0
"Building";"SpineCrawler";NA;554;0
"Building";"SpineCrawler";NA;554;0
"Building";"SpineCrawler";NA;554;0
"Unit";"Hydralisk";"Larva";574;2
"Unit";"Hydralisk";"Larva";574;2
"Unit";"Hydralisk";"Larva";574;2
"Unit";"Hydralisk";"Larva";574;2
"Unit";"Hydralisk";"Larva";574;2
"Unit";"Hydralisk";"Larva";574;2
"Unit";"Hydralisk";"Larva";574;2
"Unit";"Hydralisk";"Larva";574;2
"Unit";"Zergling";"Larva";574;1
"Unit";"Zergling";"Larva";574;1
"Unit";"Zergling";"Larva";574;1
"Unit";"Zergling";"Larva";574;1
"Unit";"Zergling";"Larva";574;1
"Unit";"Zergling";"Larva";574;1
"Unit";"Zergling";"Larva";574;1
"Unit";"Zergling";"Larva";574;1
"Unit";"Zergling";"Larva";574;1
"Unit";"Zergling";"Larva";574;1
"Unit";"Zergling";"Larva";574;1
"Unit";"Zergling";"Larva";574;1
"Unit";"Zergling";"Larva";574;1
"Unit";"Zergling";"Larva";574;1
"Unit";"Zergling";"Larva";574;1
"Unit";"Zergling";"Larva";574;1
"Unit";"Zergling";"Larva";574;1
"Unit";"Zergling";"Larva";574;1
"Unit";"Zergling";"Larva";574;1
"Unit";"Zergling";"Larva";574;1
"Unit";"Zergling";"Larva";574;1
"Unit";"Zergling";"Larva";574;1
"Unit";"Corruptor";"Larva";574;2
"Unit";"Hydralisk";"Larva";614;2
"Unit";"Hydralisk";"Larva";614;2
"Unit";"Hydralisk";"Larva";614;2
"Unit";"Hydralisk";"Larva";614;2
"Unit";"Hydralisk";"Larva";614;2
"Unit";"Hydralisk";"Larva";614;2
"Unit";"Hydralisk";"Larva";614;2
"Unit";"Hydralisk";"Larva";614;2
"Unit";"Hydralisk";"Larva";614;2
"Unit";"Hydralisk";"Larva";614;2
"Unit";"Hydralisk";"Larva";614;2
"Unit";"Hydralisk";"Larva";614;2
"Unit";"Hydralisk";"Larva";614;2
"Unit";"Hydralisk";"Larva";614;2
"Unit";"Zergling";"Larva";643;1
"Unit";"Zergling";"Larva";643;1
"Unit";"Hydralisk";"Larva";643;2
"Unit";"Hydralisk";"Larva";643;2
"Unit";"Hydralisk";"Larva";643;2
"Unit";"Hydralisk";"Larva";643;2
"Unit";"Hydralisk";"Larva";643;2
"Unit";"Hydralisk";"Larva";643;2
"Unit";"Hydralisk";"Larva";643;2
"Unit";"Hydralisk";"Larva";643;2
"Unit";"Hydralisk";"Larva";643;2
"Unit";"Hydralisk";"Larva";643;2
"Unit";"Hydralisk";"Larva";643;2
"Unit";"Hydralisk";"Larva";643;2
"Unit";"Hydralisk";"Larva";643;2
"Unit";"Hydralisk";"Larva";645;2
"Unit";"Hydralisk";"Larva";645;2
"Unit";"Hydralisk";"Larva";645;2
"Unit";"Hydralisk";"Larva";671;2
"Unit";"Hydralisk";"Larva";671;2
"Unit";"Hydralisk";"Larva";671;2
"Unit";"Viper";"Larva";671;3
"Unit";"Viper";"Larva";671;3
"Unit";"Hydralisk";"Larva";671;2
"Unit";"Hydralisk";"Larva";671;2
"Unit";"Hydralisk";"Larva";671;2
"Unit";"Hydralisk";"Larva";671;2
"Building";"HydraliskDen";NA;671;0
"Unit";"Overlord";"Larva";683;0
"Unit";"Overlord";"Larva";683;0
"Unit";"Overlord";"Larva";683;0
"Unit";"Overlord";"Larva";683;0
"Unit";"Overlord";"Larva";698;0
"Unit";"Overlord";"Larva";698;0
"Unit";"Overlord";"Larva";698;0
"Unit";"Overlord";"Larva";698;0
"Unit";"Overlord";"Larva";698;0
"Unit";"Overlord";"Larva";698;0
"Building";"Spire";NA;671;0
"Unit";"Overlord";"Larva";698;0
"Unit";"Overlord";"Larva";698;0
"Unit";"Mutalisk";"Larva";698;2
"Unit";"Mutalisk";"Larva";698;2
"Unit";"Mutalisk";"Larva";698;2
"Unit";"Mutalisk";"Larva";698;2
"Unit";"Mutalisk";"Larva";698;2
"Unit";"Mutalisk";"Larva";698;2
"Unit";"Overlord";"Larva";704;0
"Unit";"Overlord";"Larva";704;0
"Unit";"Overlord";"Larva";704;0
"Building";"Hatchery";NA;698;0
