"type";"unit_name";"on_building";"total_supply";"supply"
"Unit";"Overlord";"Larva";13;0
"Building";"Extractor";NA;18;0
"Unit";"Overlord";"Larva";21;0
"Building";"SpawningPool";NA;19;0
"Building";"Hatchery";NA;17;0
"Unit";"Zergling";"Larva";23;1
"Unit";"Zergling";"Larva";23;1
"Unit";"Zergling";"Larva";23;1
"Unit";"Zergling";"Larva";23;1
"Unit";"Zergling";"Larva";23;1
"Unit";"Zergling";"Larva";23;1
"Unit";"Queen";"Hatchery";22;2
"Unit";"Queen";"Hatchery";23;2
"Unit";"Overlord";"Larva";35;0
"Unit";"Overlord";"Larva";40;0
"Unit";"Zergling";"Larva";45;1
"Unit";"Zergling";"Larva";45;1
"Unit";"Zergling";"Larva";45;1
"Unit";"Zergling";"Larva";45;1
"Unit";"Zergling";"Larva";45;1
"Unit";"Zergling";"Larva";45;1
"Unit";"Zergling";"Larva";45;1
"Unit";"Zergling";"Larva";45;1
"Building";"Hatchery";NA;30;0
"Unit";"Overlord";"Larva";45;0
"Unit";"Overlord";"Larva";53;0
"Unit";"Queen";"Hatchery";53;2
"Unit";"Queen";"Hatchery";53;2
"Unit";"Queen";"Hatchery";53;2
"Unit";"Overlord";"Larva";60;0
"Building";"Extractor";NA;60;0
"Building";"CreepTumorQueen";NA;66;0
"Unit";"Zergling";"Larva";62;1
"Unit";"Zergling";"Larva";62;1
"Unit";"Zergling";"Larva";66;1
"Unit";"Zergling";"Larva";66;1
"Unit";"Zergling";"Larva";66;1
"Unit";"Zergling";"Larva";66;1
"Unit";"Zergling";"Larva";66;1
"Unit";"Zergling";"Larva";66;1
"Unit";"Zergling";"Larva";66;1
"Unit";"Zergling";"Larva";66;1
"Unit";"Zergling";"Larva";66;1
"Unit";"Zergling";"Larva";66;1
"Unit";"Zergling";"Larva";66;1
"Unit";"Zergling";"Larva";66;1
"Building";"CreepTumorQueen";NA;66;0
"Unit";"Overlord";"Larva";66;0
"Unit";"Overlord";"Larva";66;0
"Unit";"Zergling";"Larva";66;1
"Unit";"Zergling";"Larva";66;1
"Unit";"Zergling";"Larva";66;1
"Unit";"Zergling";"Larva";66;1
"Unit";"Zergling";"Larva";66;1
"Unit";"Zergling";"Larva";66;1
"Unit";"Zergling";"Larva";66;1
"Unit";"Zergling";"Larva";66;1
"Building";"BanelingNest";NA;60;0
"Unit";"Zergling";"Larva";80;1
"Unit";"Zergling";"Larva";80;1
"Unit";"Zergling";"Larva";80;1
"Unit";"Zergling";"Larva";80;1
"Unit";"Overlord";"Larva";80;0
"Unit";"Overlord";"Larva";80;0
"Unit";"Zergling";"Larva";88;1
"Unit";"Zergling";"Larva";88;1
"Unit";"Baneling";"Zergling";88;0
"Unit";"Baneling";"Zergling";88;0
"Unit";"Baneling";"Zergling";88;0
"Unit";"Baneling";"Zergling";88;0
"Unit";"Baneling";"Zergling";88;0
"Unit";"Baneling";"Zergling";88;0
"Unit";"Baneling";"Zergling";88;0
"Unit";"Baneling";"Zergling";88;0
"Unit";"Baneling";"Zergling";88;0
"Unit";"Baneling";"Zergling";88;0
"Unit";"Zergling";"Larva";92;1
"Unit";"Zergling";"Larva";92;1
"Unit";"Zergling";"Larva";92;1
"Unit";"Zergling";"Larva";92;1
"Unit";"Baneling";"Zergling";98;0
"Unit";"Baneling";"Zergling";98;0
"Unit";"Baneling";"Zergling";98;0
"Unit";"Baneling";"Zergling";98;0
"Unit";"Queen";"Hatchery";94;2
"Unit";"Queen";"Hatchery";94;2
"Unit";"Overlord";"Larva";98;0
"Building";"CreepTumorQueen";NA;98;0
"Unit";"Queen";"Hatchery";98;2
"Building";"CreepTumorQueen";NA;98;0
"Unit";"Zergling";"Larva";98;1
"Unit";"Zergling";"Larva";98;1
"Unit";"Zergling";"Larva";98;1
"Unit";"Zergling";"Larva";98;1
"Unit";"Zergling";"Larva";98;1
"Unit";"Zergling";"Larva";98;1
"Unit";"Zergling";"Larva";98;1
"Unit";"Zergling";"Larva";98;1
"Unit";"Zergling";"Larva";98;1
"Unit";"Zergling";"Larva";98;1
"Unit";"Zergling";"Larva";98;1
"Unit";"Zergling";"Larva";98;1
"Unit";"Zergling";"Larva";98;1
"Unit";"Zergling";"Larva";98;1
"Unit";"Zergling";"Larva";98;1
"Unit";"Zergling";"Larva";98;1
"Unit";"Zergling";"Larva";98;1
"Unit";"Zergling";"Larva";98;1
"Unit";"Zergling";"Larva";98;1
"Unit";"Zergling";"Larva";98;1
"Unit";"Zergling";"Larva";98;1
"Unit";"Zergling";"Larva";98;1
"Unit";"Baneling";"Zergling";98;0
"Unit";"Baneling";"Zergling";98;0
"Unit";"Baneling";"Zergling";98;0
"Unit";"Baneling";"Zergling";98;0
"Building";"CreepTumorQueen";NA;104;0
"Building";"CreepTumorQueen";NA;104;0
"Building";"CreepTumorQueen";NA;104;0
"Building";"CreepTumorQueen";NA;126;0
"Unit";"Overlord";"Larva";104;0
"Unit";"Zergling";"Larva";126;1
"Unit";"Zergling";"Larva";126;1
"Unit";"Zergling";"Larva";126;1
"Unit";"Zergling";"Larva";126;1
"Unit";"Zergling";"Larva";126;1
"Unit";"Zergling";"Larva";126;1
"Unit";"Zergling";"Larva";126;1
"Unit";"Zergling";"Larva";126;1
"Unit";"Zergling";"Larva";126;1
"Unit";"Zergling";"Larva";126;1
"Unit";"Zergling";"Larva";126;1
"Unit";"Zergling";"Larva";126;1
"Unit";"Zergling";"Larva";126;1
"Unit";"Zergling";"Larva";126;1
"Unit";"Zergling";"Larva";126;1
"Unit";"Zergling";"Larva";126;1
"Unit";"Zergling";"Larva";126;1
"Unit";"Zergling";"Larva";126;1
"Unit";"Zergling";"Larva";126;1
"Unit";"Zergling";"Larva";126;1
"Unit";"Zergling";"Larva";126;1
"Unit";"Zergling";"Larva";126;1
"Unit";"Zergling";"Larva";126;1
"Unit";"Zergling";"Larva";126;1
"Unit";"Zergling";"Larva";126;1
"Unit";"Zergling";"Larva";126;1
"Unit";"Zergling";"Larva";126;1
"Unit";"Zergling";"Larva";126;1
"Building";"CreepTumor";NA;126;0
"Building";"CreepTumor";NA;126;0
"Building";"CreepTumor";NA;126;0
"Building";"CreepTumor";NA;126;0
"Building";"CreepTumorQueen";NA;126;0
"Building";"CreepTumorQueen";NA;126;0
"Building";"CreepTumor";NA;126;0
"Building";"CreepTumorQueen";NA;126;0
"Unit";"Baneling";"Zergling";154;0
"Unit";"Baneling";"Zergling";154;0
"Unit";"Baneling";"Zergling";154;0
"Unit";"Baneling";"Zergling";154;0
"Unit";"Baneling";"Zergling";154;0
"Unit";"Baneling";"Zergling";154;0
"Unit";"Baneling";"Zergling";154;0
"Unit";"Baneling";"Zergling";154;0
"Unit";"Baneling";"Zergling";154;0
"Unit";"Baneling";"Zergling";154;0
"Unit";"Baneling";"Zergling";154;0
"Unit";"Baneling";"Zergling";154;0
"Unit";"Baneling";"Zergling";154;0
"Building";"CreepTumor";NA;154;0
"Building";"CreepTumor";NA;154;0
"Building";"CreepTumor";NA;154;0
"Building";"CreepTumor";NA;154;0
"Building";"CreepTumor";NA;154;0
"Building";"CreepTumor";NA;154;0
"Building";"CreepTumor";NA;154;0
"Building";"CreepTumor";NA;154;0
"Unit";"Zergling";"Larva";154;1
"Unit";"Zergling";"Larva";154;1
"Unit";"Zergling";"Larva";154;1
"Unit";"Zergling";"Larva";154;1
"Unit";"Zergling";"Larva";154;1
"Unit";"Zergling";"Larva";154;1
"Unit";"Zergling";"Larva";154;1
"Unit";"Zergling";"Larva";154;1
"Unit";"Zergling";"Larva";154;1
"Unit";"Zergling";"Larva";154;1
"Unit";"Zergling";"Larva";154;1
"Unit";"Zergling";"Larva";154;1
"Unit";"Zergling";"Larva";154;1
"Unit";"Zergling";"Larva";154;1
"Unit";"Zergling";"Larva";154;1
"Unit";"Zergling";"Larva";154;1
"Building";"CreepTumor";NA;154;0
"Building";"CreepTumorQueen";NA;154;0
"Building";"CreepTumorQueen";NA;154;0
"Building";"CreepTumorQueen";NA;154;0
"Building";"CreepTumorQueen";NA;154;0
"Unit";"Zergling";"Larva";170;1
"Unit";"Zergling";"Larva";170;1
"Unit";"Zergling";"Larva";170;1
"Unit";"Zergling";"Larva";170;1
"Unit";"Zergling";"Larva";170;1
"Unit";"Zergling";"Larva";170;1
"Unit";"Zergling";"Larva";170;1
"Unit";"Zergling";"Larva";170;1
"Unit";"Zergling";"Larva";170;1
"Unit";"Zergling";"Larva";170;1
"Unit";"Zergling";"Larva";170;1
"Unit";"Zergling";"Larva";170;1
"Unit";"Zergling";"Larva";170;1
"Unit";"Zergling";"Larva";170;1
"Unit";"Zergling";"Larva";170;1
"Unit";"Zergling";"Larva";170;1
"Unit";"Zergling";"Larva";170;1
"Unit";"Zergling";"Larva";170;1
"Unit";"Zergling";"Larva";170;1
"Unit";"Zergling";"Larva";170;1
"Unit";"Zergling";"Larva";170;1
"Unit";"Zergling";"Larva";170;1
"Unit";"Zergling";"Larva";170;1
"Unit";"Zergling";"Larva";170;1
"Unit";"Zergling";"Larva";170;1
"Unit";"Zergling";"Larva";170;1
"Unit";"Zergling";"Larva";170;1
"Unit";"Zergling";"Larva";170;1
"Unit";"Zergling";"Larva";170;1
"Unit";"Zergling";"Larva";170;1
"Unit";"Zergling";"Larva";170;1
"Unit";"Zergling";"Larva";170;1
"Building";"CreepTumor";NA;170;0
"Building";"CreepTumor";NA;170;0
"Building";"CreepTumor";NA;170;0
"Building";"CreepTumor";NA;170;0
"Building";"CreepTumor";NA;170;0
"Building";"CreepTumor";NA;170;0
"Building";"CreepTumor";NA;170;0
"Building";"CreepTumor";NA;170;0
"Building";"CreepTumor";NA;170;0
"Building";"CreepTumor";NA;170;0
"Building";"CreepTumor";NA;170;0
"Building";"CreepTumorQueen";NA;170;0
"Building";"CreepTumor";NA;170;0
"Building";"CreepTumorQueen";NA;170;0
"Building";"CreepTumor";NA;170;0
"Building";"CreepTumorQueen";NA;170;0
"Building";"CreepTumorQueen";NA;202;0
"Unit";"Zergling";"Larva";202;1
"Unit";"Zergling";"Larva";202;1
"Unit";"Zergling";"Larva";202;1
"Unit";"Zergling";"Larva";202;1
"Unit";"Zergling";"Larva";202;1
"Unit";"Zergling";"Larva";202;1
"Unit";"Zergling";"Larva";202;1
"Unit";"Zergling";"Larva";202;1
"Unit";"Zergling";"Larva";202;1
"Unit";"Zergling";"Larva";202;1
"Unit";"Zergling";"Larva";202;1
"Unit";"Zergling";"Larva";202;1
"Unit";"Zergling";"Larva";202;1
"Unit";"Zergling";"Larva";202;1
"Building";"CreepTumorQueen";NA;202;0
"Building";"EvolutionChamber";NA;202;0
"Unit";"Zergling";"Larva";202;1
"Unit";"Zergling";"Larva";202;1
"Unit";"Zergling";"Larva";202;1
"Unit";"Zergling";"Larva";202;1
"Unit";"Zergling";"Larva";202;1
"Unit";"Zergling";"Larva";202;1
"Unit";"Zergling";"Larva";202;1
"Unit";"Zergling";"Larva";202;1
"Unit";"Zergling";"Larva";202;1
"Unit";"Zergling";"Larva";202;1
"Unit";"Zergling";"Larva";202;1
"Unit";"Zergling";"Larva";202;1
"Unit";"Zergling";"Larva";202;1
"Unit";"Zergling";"Larva";202;1
"Unit";"Zergling";"Larva";202;1
"Unit";"Zergling";"Larva";202;1
"Unit";"Zergling";"Larva";202;1
"Unit";"Zergling";"Larva";202;1
"Unit";"Zergling";"Larva";202;1
"Unit";"Zergling";"Larva";202;1
"Building";"CreepTumor";NA;216;0
"Building";"CreepTumor";NA;216;0
"Building";"CreepTumor";NA;216;0
"Building";"CreepTumor";NA;216;0
"Building";"CreepTumor";NA;216;0
"Building";"CreepTumor";NA;216;0
"Building";"CreepTumor";NA;216;0
"Building";"CreepTumor";NA;216;0
"Building";"CreepTumor";NA;216;0
"Building";"CreepTumor";NA;216;0
"Building";"CreepTumor";NA;216;0
"Unit";"Zergling";"Larva";236;1
"Unit";"Zergling";"Larva";236;1
"Unit";"Zergling";"Larva";236;1
"Unit";"Zergling";"Larva";236;1
"Unit";"Zergling";"Larva";236;1
"Unit";"Zergling";"Larva";236;1
"Building";"CreepTumor";NA;240;0
"Building";"CreepTumor";NA;240;0
"Building";"CreepTumor";NA;240;0
"Building";"CreepTumor";NA;240;0
"Building";"CreepTumor";NA;240;0
"Building";"CreepTumor";NA;240;0
"Building";"CreepTumor";NA;240;0
"Building";"CreepTumor";NA;240;0
"Building";"CreepTumor";NA;240;0
"Building";"CreepTumor";NA;240;0
"Building";"CreepTumor";NA;246;0
"Building";"CreepTumor";NA;246;0
"Building";"CreepTumor";NA;246;0
"Building";"CreepTumorQueen";NA;248;0
"Building";"CreepTumorQueen";NA;248;0
"Unit";"Zergling";"Larva";246;1
"Unit";"Zergling";"Larva";246;1
"Unit";"Zergling";"Larva";248;1
"Unit";"Zergling";"Larva";248;1
"Unit";"Zergling";"Larva";248;1
"Unit";"Zergling";"Larva";248;1
"Unit";"Zergling";"Larva";248;1
"Unit";"Zergling";"Larva";248;1
"Unit";"Zergling";"Larva";248;1
"Unit";"Zergling";"Larva";248;1
"Unit";"Zergling";"Larva";248;1
"Unit";"Zergling";"Larva";248;1
"Unit";"Zergling";"Larva";248;1
"Unit";"Zergling";"Larva";248;1
"Unit";"Zergling";"Larva";248;1
"Unit";"Zergling";"Larva";248;1
"Unit";"Zergling";"Larva";248;1
"Unit";"Zergling";"Larva";248;1
"Unit";"Zergling";"Larva";248;1
"Unit";"Zergling";"Larva";248;1
"Building";"CreepTumorQueen";NA;248;0
"Building";"CreepTumorQueen";NA;248;0
"Building";"CreepTumorQueen";NA;248;0
"Building";"CreepTumor";NA;250;0
"Building";"CreepTumor";NA;260;0
"Building";"CreepTumor";NA;268;0
"Building";"CreepTumor";NA;268;0
"Building";"CreepTumor";NA;268;0
"Building";"CreepTumor";NA;268;0
"Building";"CreepTumor";NA;268;0
"Building";"CreepTumor";NA;268;0
"Building";"CreepTumor";NA;268;0
"Building";"CreepTumor";NA;268;0
"Building";"CreepTumor";NA;271;0
"Building";"CreepTumor";NA;271;0
"Building";"CreepTumor";NA;271;0
"Building";"CreepTumor";NA;271;0
"Building";"Extractor";NA;271;0
"Building";"CreepTumor";NA;271;0
"Building";"CreepTumor";NA;271;0
"Building";"CreepTumor";NA;271;0
"Building";"CreepTumor";NA;271;0
"Building";"EvolutionChamber";NA;271;0
"Building";"Extractor";NA;271;0
"Building";"Extractor";NA;271;0
"Building";"CreepTumorQueen";NA;284;0
"Building";"HydraliskDen";NA;271;0
"Unit";"Zergling";"Larva";284;1
"Unit";"Zergling";"Larva";284;1
"Unit";"Zergling";"Larva";284;1
"Unit";"Zergling";"Larva";284;1
"Unit";"Zergling";"Larva";284;1
"Unit";"Zergling";"Larva";284;1
"Unit";"Zergling";"Larva";284;1
"Unit";"Zergling";"Larva";284;1
"Unit";"Zergling";"Larva";284;1
"Unit";"Zergling";"Larva";284;1
"Unit";"Zergling";"Larva";284;1
"Unit";"Zergling";"Larva";284;1
"Unit";"Zergling";"Larva";284;1
"Unit";"Zergling";"Larva";284;1
"Unit";"Zergling";"Larva";284;1
"Unit";"Zergling";"Larva";284;1
"Unit";"Zergling";"Larva";284;1
"Unit";"Zergling";"Larva";284;1
"Unit";"Zergling";"Larva";284;1
"Unit";"Zergling";"Larva";284;1
"Unit";"Zergling";"Larva";284;1
"Unit";"Zergling";"Larva";284;1
"Unit";"Zergling";"Larva";284;1
"Unit";"Zergling";"Larva";284;1
"Unit";"Zergling";"Larva";284;1
"Unit";"Zergling";"Larva";284;1
"Unit";"Zergling";"Larva";284;1
"Unit";"Zergling";"Larva";284;1
"Unit";"Zergling";"Larva";284;1
"Unit";"Zergling";"Larva";284;1
"Unit";"Zergling";"Larva";284;1
"Unit";"Zergling";"Larva";284;1
"Unit";"Zergling";"Larva";284;1
"Unit";"Zergling";"Larva";284;1
"Unit";"Baneling";"Zergling";298;0
"Unit";"Baneling";"Zergling";298;0
"Unit";"Baneling";"Zergling";298;0
"Unit";"Baneling";"Zergling";298;0
"Unit";"Baneling";"Zergling";298;0
"Unit";"Baneling";"Zergling";298;0
"Unit";"Baneling";"Zergling";298;0
"Unit";"Baneling";"Zergling";298;0
"Unit";"Baneling";"Zergling";298;0
"Unit";"Baneling";"Zergling";298;0
"Unit";"Baneling";"Zergling";298;0
"Unit";"Baneling";"Zergling";298;0
"Unit";"Baneling";"Zergling";298;0
"Unit";"Baneling";"Zergling";298;0
"Unit";"Zergling";"Larva";304;1
"Unit";"Zergling";"Larva";304;1
"Unit";"Zergling";"Larva";304;1
"Unit";"Zergling";"Larva";304;1
"Unit";"Zergling";"Larva";304;1
"Unit";"Zergling";"Larva";304;1
"Unit";"Zergling";"Larva";304;1
"Unit";"Zergling";"Larva";304;1
"Unit";"Zergling";"Larva";304;1
"Unit";"Zergling";"Larva";304;1
"Unit";"Zergling";"Larva";318;1
"Unit";"Zergling";"Larva";318;1
"Building";"CreepTumor";NA;328;0
"Building";"CreepTumor";NA;328;0
"Unit";"Zergling";"Larva";318;1
"Unit";"Zergling";"Larva";318;1
"Unit";"Zergling";"Larva";318;1
"Unit";"Zergling";"Larva";318;1
"Unit";"Zergling";"Larva";318;1
"Unit";"Zergling";"Larva";318;1
"Unit";"Zergling";"Larva";318;1
"Unit";"Zergling";"Larva";318;1
"Unit";"Zergling";"Larva";318;1
"Unit";"Zergling";"Larva";318;1
"Unit";"Zergling";"Larva";318;1
"Unit";"Zergling";"Larva";318;1
"Unit";"Zergling";"Larva";318;1
"Unit";"Zergling";"Larva";318;1
"Unit";"Zergling";"Larva";318;1
"Unit";"Zergling";"Larva";318;1
"Unit";"Zergling";"Larva";318;1
"Unit";"Zergling";"Larva";318;1
"Building";"CreepTumor";NA;328;0
"Building";"CreepTumor";NA;328;0
"Building";"CreepTumor";NA;328;0
"Building";"CreepTumor";NA;328;0
"Building";"CreepTumor";NA;328;0
"Building";"CreepTumor";NA;328;0
"Building";"CreepTumor";NA;328;0
"Unit";"Baneling";"Zergling";328;0
"Unit";"Baneling";"Zergling";328;0
"Unit";"Baneling";"Zergling";328;0
"Unit";"Baneling";"Zergling";328;0
"Unit";"Baneling";"Zergling";328;0
"Unit";"Baneling";"Zergling";328;0
"Unit";"Baneling";"Zergling";328;0
"Unit";"Baneling";"Zergling";328;0
"Unit";"Baneling";"Zergling";328;0
"Unit";"Baneling";"Zergling";328;0
"Unit";"Baneling";"Zergling";328;0
"Unit";"Baneling";"Zergling";328;0
"Unit";"Baneling";"Zergling";328;0
"Unit";"Baneling";"Zergling";328;0
"Unit";"Baneling";"Zergling";328;0
"Building";"CreepTumor";NA;348;0
"Building";"CreepTumor";NA;348;0
"Building";"CreepTumor";NA;348;0
"Building";"CreepTumor";NA;348;0
"Building";"CreepTumor";NA;348;0
"Unit";"Zergling";"Larva";328;1
"Unit";"Zergling";"Larva";328;1
"Building";"CreepTumor";NA;348;0
"Unit";"Zergling";"Larva";328;1
"Unit";"Zergling";"Larva";328;1
"Unit";"Zergling";"Larva";328;1
"Unit";"Zergling";"Larva";328;1
"Building";"CreepTumor";NA;348;0
"Unit";"Zergling";"Larva";328;1
"Unit";"Zergling";"Larva";328;1
"Unit";"Zergling";"Larva";328;1
"Unit";"Zergling";"Larva";328;1
"Upgrade";"ZergMeleeWeaponsLevel1";"EvolutionChamber";284;0
"Building";"CreepTumor";NA;348;0
"Unit";"Hydralisk";"Larva";358;2
"Unit";"Hydralisk";"Larva";358;2
"Unit";"Hydralisk";"Larva";358;2
"Unit";"Hydralisk";"Larva";358;2
"Unit";"Hydralisk";"Larva";358;2
"Building";"CreepTumor";NA;358;0
"Building";"CreepTumor";NA;358;0
"Building";"CreepTumor";NA;358;0
"Building";"CreepTumor";NA;358;0
"Building";"CreepTumor";NA;358;0
"Building";"CreepTumor";NA;358;0
"Building";"CreepTumor";NA;358;0
"Building";"CreepTumor";NA;358;0
"Building";"CreepTumor";NA;358;0
"Building";"CreepTumor";NA;358;0
"Building";"Extractor";NA;368;0
"Unit";"Zergling";"Larva";368;1
"Unit";"Zergling";"Larva";368;1
"Unit";"Zergling";"Larva";368;1
"Unit";"Zergling";"Larva";368;1
"Unit";"Zergling";"Larva";368;1
"Unit";"Zergling";"Larva";368;1
"Unit";"Zergling";"Larva";368;1
"Unit";"Zergling";"Larva";368;1
"Unit";"Zergling";"Larva";368;1
"Unit";"Zergling";"Larva";368;1
"Unit";"Zergling";"Larva";368;1
"Unit";"Zergling";"Larva";368;1
"Unit";"Zergling";"Larva";368;1
"Unit";"Zergling";"Larva";368;1
"Unit";"Zergling";"Larva";368;1
"Unit";"Zergling";"Larva";368;1
"Unit";"Zergling";"Larva";368;1
"Unit";"Zergling";"Larva";368;1
"Unit";"Zergling";"Larva";368;1
"Unit";"Zergling";"Larva";368;1
"Unit";"Zergling";"Larva";368;1
"Unit";"Zergling";"Larva";368;1
"Building";"CreepTumor";NA;368;0
"Building";"CreepTumor";NA;368;0
"Unit";"Hydralisk";"Larva";368;2
"Unit";"Hydralisk";"Larva";368;2
"Unit";"Hydralisk";"Larva";368;2
"Unit";"Hydralisk";"Larva";368;2
"Unit";"Hydralisk";"Larva";368;2
"Building";"CreepTumor";NA;368;0
"Building";"InfestationPit";NA;368;0
"Building";"CreepTumor";NA;368;0
"Building";"CreepTumor";NA;368;0
"Building";"CreepTumor";NA;368;0
"Building";"CreepTumor";NA;368;0
"Building";"CreepTumor";NA;368;0
"Building";"CreepTumor";NA;368;0
"Building";"Hatchery";NA;358;0
"Unit";"Zergling";"Larva";390;1
"Unit";"Zergling";"Larva";390;1
"Unit";"Zergling";"Larva";390;1
"Unit";"Zergling";"Larva";390;1
"Unit";"Zergling";"Larva";390;1
"Unit";"Zergling";"Larva";390;1
"Unit";"Zergling";"Larva";390;1
"Unit";"Zergling";"Larva";390;1
"Unit";"Zergling";"Larva";390;1
"Unit";"Zergling";"Larva";390;1
"Unit";"Zergling";"Larva";390;1
"Unit";"Zergling";"Larva";390;1
"Unit";"Zergling";"Larva";390;1
"Unit";"Zergling";"Larva";390;1
"Unit";"Zergling";"Larva";390;1
"Unit";"Zergling";"Larva";390;1
"Unit";"Zergling";"Larva";390;1
"Unit";"Zergling";"Larva";390;1
"Unit";"Baneling";"Zergling";400;0
"Unit";"Baneling";"Zergling";400;0
"Unit";"Baneling";"Zergling";400;0
"Unit";"Baneling";"Zergling";400;0
"Unit";"Baneling";"Zergling";400;0
"Unit";"Baneling";"Zergling";400;0
"Unit";"Baneling";"Zergling";400;0
"Unit";"Baneling";"Zergling";400;0
"Unit";"Baneling";"Zergling";400;0
"Unit";"Baneling";"Zergling";400;0
"Unit";"Baneling";"Zergling";400;0
"Unit";"Baneling";"Zergling";400;0
"Building";"Hatchery";NA;368;0
"Unit";"Zergling";"Larva";418;1
"Unit";"Zergling";"Larva";418;1
"Unit";"Zergling";"Larva";418;1
"Unit";"Zergling";"Larva";418;1
"Unit";"Queen";"Hatchery";400;2
"Unit";"Zergling";"Larva";418;1
"Unit";"Zergling";"Larva";418;1
"Unit";"Zergling";"Larva";418;1
"Unit";"Zergling";"Larva";418;1
"Unit";"Zergling";"Larva";418;1
"Unit";"Zergling";"Larva";418;1
"Unit";"Zergling";"Larva";418;1
"Unit";"Zergling";"Larva";418;1
"Unit";"Zergling";"Larva";418;1
"Unit";"Zergling";"Larva";418;1
"Unit";"Zergling";"Larva";418;1
"Unit";"Zergling";"Larva";418;1
"Building";"CreepTumor";NA;418;0
"Building";"CreepTumor";NA;418;0
"Unit";"Zergling";"Larva";418;1
"Unit";"Zergling";"Larva";418;1
"Unit";"Zergling";"Larva";418;1
"Unit";"Zergling";"Larva";418;1
"Unit";"Zergling";"Larva";418;1
"Unit";"Zergling";"Larva";418;1
"Unit";"Zergling";"Larva";418;1
"Unit";"Zergling";"Larva";418;1
"Unit";"Zergling";"Larva";418;1
"Unit";"Zergling";"Larva";418;1
"Unit";"Zergling";"Larva";418;1
"Unit";"Zergling";"Larva";418;1
"Unit";"Zergling";"Larva";418;1
"Unit";"Zergling";"Larva";418;1
"Building";"CreepTumor";NA;436;0
"Building";"CreepTumor";NA;436;0
"Unit";"Zergling";"Larva";450;1
"Unit";"Zergling";"Larva";450;1
"Unit";"Zergling";"Larva";450;1
"Unit";"Zergling";"Larva";450;1
"Unit";"Zergling";"Larva";450;1
"Unit";"Zergling";"Larva";450;1
"Unit";"Zergling";"Larva";450;1
"Unit";"Zergling";"Larva";450;1
"Unit";"Zergling";"Larva";450;1
"Unit";"Zergling";"Larva";450;1
"Unit";"Zergling";"Larva";450;1
"Unit";"Zergling";"Larva";450;1
"Unit";"Zergling";"Larva";450;1
"Unit";"Zergling";"Larva";450;1
"Unit";"Zergling";"Larva";450;1
"Unit";"Zergling";"Larva";450;1
"Unit";"Zergling";"Larva";450;1
"Unit";"Zergling";"Larva";450;1
"Unit";"Zergling";"Larva";450;1
"Unit";"Zergling";"Larva";450;1
"Unit";"Zergling";"Larva";450;1
"Unit";"Zergling";"Larva";450;1
"Unit";"Queen";"Hatchery";450;2
"Unit";"Zergling";"Larva";460;1
"Unit";"Zergling";"Larva";460;1
"Unit";"Zergling";"Larva";460;1
"Unit";"Zergling";"Larva";460;1
"Unit";"Zergling";"Larva";460;1
"Unit";"Zergling";"Larva";460;1
"Unit";"Zergling";"Larva";460;1
"Unit";"Zergling";"Larva";460;1
"Unit";"Zergling";"Larva";460;1
"Unit";"Zergling";"Larva";460;1
"Building";"CreepTumor";NA;472;0
"Building";"CreepTumor";NA;472;0
"Building";"CreepTumor";NA;474;0
"Unit";"Zergling";"Larva";484;1
"Unit";"Zergling";"Larva";484;1
"Unit";"Zergling";"Larva";484;1
"Unit";"Zergling";"Larva";484;1
"Unit";"Zergling";"Larva";484;1
"Unit";"Zergling";"Larva";484;1
"Unit";"Zergling";"Larva";484;1
"Unit";"Zergling";"Larva";484;1
"Unit";"Zergling";"Larva";484;1
"Unit";"Zergling";"Larva";484;1
"Unit";"Zergling";"Larva";484;1
"Unit";"Zergling";"Larva";484;1
"Unit";"Zergling";"Larva";484;1
"Unit";"Zergling";"Larva";484;1
"Unit";"Zergling";"Larva";484;1
"Unit";"Zergling";"Larva";484;1
"Unit";"Zergling";"Larva";484;1
"Unit";"Zergling";"Larva";484;1
"Unit";"Zergling";"Larva";484;1
"Unit";"Zergling";"Larva";484;1
"Unit";"Zergling";"Larva";484;1
"Unit";"Zergling";"Larva";484;1
"Unit";"Zergling";"Larva";484;1
"Unit";"Zergling";"Larva";484;1
"Unit";"Zergling";"Larva";484;1
"Unit";"Zergling";"Larva";484;1
"Upgrade";"ZergGroundArmorsLevel1";"EvolutionChamber";436;0
"Building";"CreepTumor";NA;512;0
"Building";"CreepTumor";NA;512;0
"Building";"CreepTumor";NA;512;0
"Building";"CreepTumor";NA;512;0
"Building";"CreepTumor";NA;512;0
"Building";"CreepTumor";NA;512;0
"Building";"CreepTumor";NA;512;0
"Unit";"Zergling";"Larva";524;1
"Unit";"Zergling";"Larva";524;1
"Unit";"Zergling";"Larva";524;1
"Unit";"Zergling";"Larva";524;1
"Unit";"Zergling";"Larva";524;1
"Unit";"Zergling";"Larva";524;1
"Unit";"Zergling";"Larva";524;1
"Unit";"Zergling";"Larva";524;1
"Unit";"Zergling";"Larva";524;1
"Unit";"Zergling";"Larva";524;1
"Unit";"Zergling";"Larva";524;1
"Unit";"Zergling";"Larva";524;1
"Unit";"Zergling";"Larva";524;1
"Unit";"Zergling";"Larva";524;1
"Unit";"Zergling";"Larva";524;1
"Unit";"Zergling";"Larva";524;1
"Unit";"Zergling";"Larva";524;1
"Unit";"Zergling";"Larva";524;1
"Unit";"Zergling";"Larva";524;1
"Unit";"Zergling";"Larva";524;1
"Unit";"Zergling";"Larva";524;1
"Unit";"Zergling";"Larva";524;1
"Unit";"Zergling";"Larva";524;1
"Unit";"Zergling";"Larva";524;1
"Unit";"Zergling";"Larva";524;1
"Unit";"Zergling";"Larva";524;1
"Unit";"Zergling";"Larva";524;1
"Unit";"Zergling";"Larva";524;1
"Upgrade";"ZergMeleeWeaponsLevel2";"EvolutionChamber";474;0
"Unit";"Zergling";"Larva";524;1
"Unit";"Zergling";"Larva";524;1
"Unit";"Zergling";"Larva";524;1
"Unit";"Zergling";"Larva";524;1
"Unit";"Zergling";"Larva";524;1
"Unit";"Zergling";"Larva";524;1
"Unit";"Zergling";"Larva";524;1
"Unit";"Zergling";"Larva";524;1
"Unit";"Zergling";"Larva";524;1
"Unit";"Zergling";"Larva";524;1
"Unit";"Zergling";"Larva";524;1
"Unit";"Zergling";"Larva";524;1
"Building";"CreepTumor";NA;524;0
"Building";"CreepTumor";NA;524;0
"Building";"CreepTumor";NA;524;0
"Building";"CreepTumor";NA;524;0
"Building";"CreepTumor";NA;552;0
"Building";"CreepTumor";NA;552;0
"Building";"CreepTumor";NA;552;0
"Building";"CreepTumor";NA;554;0
"Building";"CreepTumor";NA;564;0
"Building";"UltraliskCavern";NA;524;0
"Building";"CreepTumor";NA;564;0
"Building";"CreepTumor";NA;564;0
"Building";"CreepTumor";NA;564;0
"Building";"CreepTumor";NA;564;0
"Building";"CreepTumor";NA;564;0
"Building";"CreepTumor";NA;564;0
"Building";"CreepTumor";NA;564;0
"Building";"CreepTumor";NA;564;0
"Building";"CreepTumor";NA;564;0
"Building";"CreepTumor";NA;564;0
"Unit";"Ultralisk";"Larva";564;6
"Unit";"Ultralisk";"Larva";564;6
"Unit";"Ultralisk";"Larva";564;6
"Unit";"Ultralisk";"Larva";564;6
"Unit";"Ultralisk";"Larva";564;6
"Unit";"Ultralisk";"Larva";564;6
"Upgrade";"ZergGroundArmorsLevel2";"EvolutionChamber";524;0
"Building";"Extractor";NA;564;0
"Building";"Extractor";NA;600;0
"Unit";"Hydralisk";"Larva";600;2
"Unit";"Hydralisk";"Larva";600;2
"Unit";"Hydralisk";"Larva";600;2
"Unit";"Hydralisk";"Larva";600;2
"Unit";"Hydralisk";"Larva";600;2
"Unit";"Hydralisk";"Larva";600;2
"Unit";"Hydralisk";"Larva";600;2
"Unit";"Hydralisk";"Larva";600;2
"Building";"LurkerDenMP";NA;564;0
"Building";"CreepTumor";NA;616;0
"Building";"CreepTumor";NA;616;0
"Building";"CreepTumor";NA;632;0
"Building";"CreepTumor";NA;632;0
"Building";"CreepTumor";NA;632;0
"Building";"CreepTumor";NA;632;0
"Building";"Hatchery";NA;600;0
"Unit";"Overlord";"Larva";632;0
"Unit";"Overlord";"Larva";632;0
"Unit";"Overlord";"Larva";632;0
"Unit";"Overlord";"Larva";632;0
"Unit";"Overlord";"Larva";632;0
"Unit";"Overlord";"Larva";632;0
"Unit";"Overlord";"Larva";632;0
"Unit";"Queen";"Hatchery";616;2
"Upgrade";"ChitinousPlating";"UltraliskCavern";600;0
"Building";"CreepTumor";NA;632;0
"Building";"CreepTumorQueen";NA;634;0
"Unit";"Overlord";"Larva";634;0
"Unit";"Overlord";"Larva";634;0
"Unit";"Overlord";"Larva";634;0
"Upgrade";"ZergMeleeWeaponsLevel3";"EvolutionChamber";616;0
"Building";"Extractor";NA;641;0
"Unit";"Zergling";"Larva";641;1
"Unit";"Zergling";"Larva";641;1
"Unit";"Zergling";"Larva";641;1
"Unit";"Zergling";"Larva";641;1
"Unit";"Zergling";"Larva";641;1
"Unit";"Zergling";"Larva";641;1
"Unit";"Zergling";"Larva";641;1
"Unit";"Zergling";"Larva";641;1
"Unit";"Zergling";"Larva";641;1
"Unit";"Zergling";"Larva";641;1
"Unit";"Hydralisk";"Larva";641;2
"Unit";"Zergling";"Larva";641;1
"Unit";"Zergling";"Larva";641;1
"Unit";"Hydralisk";"Larva";641;2
"Unit";"Hydralisk";"Larva";641;2
"Unit";"Hydralisk";"Larva";641;2
"Unit";"Hydralisk";"Larva";641;2
"Unit";"Hydralisk";"Larva";641;2
"Unit";"Hydralisk";"Larva";641;2
"Unit";"Hydralisk";"Larva";641;2
"Unit";"Hydralisk";"Larva";641;2
"Unit";"Hydralisk";"Larva";641;2
"Unit";"Hydralisk";"Larva";641;2
"Unit";"Hydralisk";"Larva";641;2
"Unit";"Hydralisk";"Larva";641;2
"Unit";"Hydralisk";"Larva";641;2
"Unit";"Hydralisk";"Larva";641;2
"Unit";"Hydralisk";"Larva";641;2
"Unit";"Hydralisk";"Larva";641;2
"Unit";"Hydralisk";"Larva";641;2
"Unit";"Hydralisk";"Larva";641;2
"Unit";"Hydralisk";"Larva";641;2
"Unit";"Zergling";"Larva";641;1
"Unit";"Zergling";"Larva";641;1
"Unit";"Zergling";"Larva";641;1
"Unit";"Zergling";"Larva";641;1
"Unit";"Zergling";"Larva";641;1
"Unit";"Zergling";"Larva";641;1
"Upgrade";"EvolveGroovedSpines";"HydraliskDen";634;0
"Upgrade";"ZergGroundArmorsLevel3";"EvolutionChamber";634;0
"Building";"CreepTumorQueen";NA;699;0
"Building";"CreepTumorQueen";NA;699;0
"Unit";"Zergling";"Larva";699;1
"Unit";"Zergling";"Larva";699;1
"Unit";"Zergling";"Larva";699;1
"Unit";"Zergling";"Larva";699;1
"Unit";"Zergling";"Larva";699;1
"Unit";"Zergling";"Larva";699;1
"Unit";"Zergling";"Larva";699;1
"Unit";"Zergling";"Larva";699;1
"Unit";"Zergling";"Larva";699;1
"Unit";"Zergling";"Larva";699;1
"Unit";"Zergling";"Larva";699;1
"Unit";"Zergling";"Larva";699;1
"Unit";"Zergling";"Larva";699;1
"Unit";"Zergling";"Larva";699;1
"Unit";"Zergling";"Larva";699;1
"Unit";"Zergling";"Larva";699;1
"Unit";"Zergling";"Larva";699;1
"Unit";"Zergling";"Larva";699;1
"Building";"CreepTumorQueen";NA;699;0
"Building";"CreepTumor";NA;699;0
"Building";"Extractor";NA;699;0
"Building";"CreepTumorQueen";NA;699;0
"Building";"CreepTumor";NA;699;0
"Unit";"Ultralisk";"Larva";699;6
"Unit";"Ultralisk";"Larva";699;6
"Unit";"Ultralisk";"Larva";699;6
"Unit";"Ultralisk";"Larva";699;6
"Unit";"Ultralisk";"Larva";699;6
"Unit";"Zergling";"Larva";717;1
"Unit";"Zergling";"Larva";717;1
"Unit";"Zergling";"Larva";717;1
"Unit";"Zergling";"Larva";717;1
"Unit";"Zergling";"Larva";717;1
"Unit";"Zergling";"Larva";717;1
"Unit";"Zergling";"Larva";717;1
"Unit";"Zergling";"Larva";717;1
"Unit";"Zergling";"Larva";717;1
"Unit";"Zergling";"Larva";717;1
"Unit";"Zergling";"Larva";717;1
"Unit";"Zergling";"Larva";717;1
"Unit";"Zergling";"Larva";717;1
"Unit";"Zergling";"Larva";717;1
"Unit";"Zergling";"Larva";717;1
"Unit";"Zergling";"Larva";717;1
"Unit";"Zergling";"Larva";717;1
"Unit";"Zergling";"Larva";717;1
"Unit";"Zergling";"Larva";717;1
"Unit";"Zergling";"Larva";717;1
"Unit";"Zergling";"Larva";717;1
"Unit";"Zergling";"Larva";717;1
"Unit";"Zergling";"Larva";717;1
"Unit";"Zergling";"Larva";717;1
"Unit";"Zergling";"Larva";717;1
"Unit";"Zergling";"Larva";717;1
"Unit";"Zergling";"Larva";717;1
"Unit";"Zergling";"Larva";717;1
"Unit";"Zergling";"Larva";717;1
"Unit";"Zergling";"Larva";717;1
"Unit";"Zergling";"Larva";717;1
"Unit";"Zergling";"Larva";717;1
"Unit";"Zergling";"Larva";717;1
"Unit";"Zergling";"Larva";717;1
"Unit";"Zergling";"Larva";717;1
"Unit";"Zergling";"Larva";717;1
"Unit";"Zergling";"Larva";717;1
"Unit";"Zergling";"Larva";717;1
"Unit";"Zergling";"Larva";717;1
"Unit";"Zergling";"Larva";717;1
"Upgrade";"EvolveMuscularAugments";"HydraliskDen";699;0
"Unit";"Baneling";"Zergling";787;0
"Unit";"Baneling";"Zergling";787;0
"Unit";"Baneling";"Zergling";787;0
"Unit";"Baneling";"Zergling";787;0
"Unit";"Baneling";"Zergling";787;0
"Unit";"Baneling";"Zergling";787;0
"Unit";"Baneling";"Zergling";787;0
"Unit";"Baneling";"Zergling";787;0
"Unit";"Baneling";"Zergling";787;0
"Unit";"Baneling";"Zergling";787;0
"Unit";"Baneling";"Zergling";787;0
"Unit";"Baneling";"Zergling";787;0
"Unit";"Baneling";"Zergling";787;0
"Unit";"Baneling";"Zergling";787;0
"Unit";"Baneling";"Zergling";787;0
"Building";"Hatchery";NA;787;0
"Unit";"Hydralisk";"Larva";787;2
"Unit";"Hydralisk";"Larva";787;2
"Unit";"Hydralisk";"Larva";787;2
"Unit";"Hydralisk";"Larva";787;2
"Unit";"Hydralisk";"Larva";787;2
"Unit";"Hydralisk";"Larva";787;2
"Unit";"Hydralisk";"Larva";787;2
"Unit";"Hydralisk";"Larva";787;2
"Unit";"Zergling";"Larva";787;1
"Unit";"Zergling";"Larva";787;1
"Unit";"Zergling";"Larva";787;1
"Unit";"Zergling";"Larva";787;1
"Unit";"Zergling";"Larva";787;1
"Unit";"Zergling";"Larva";787;1
"Unit";"Zergling";"Larva";787;1
"Unit";"Zergling";"Larva";787;1
"Unit";"Zergling";"Larva";787;1
"Unit";"Zergling";"Larva";787;1
"Unit";"Zergling";"Larva";787;1
"Unit";"Zergling";"Larva";787;1
"Unit";"Zergling";"Larva";787;1
"Unit";"Zergling";"Larva";787;1
"Unit";"Zergling";"Larva";787;1
"Unit";"Zergling";"Larva";787;1
"Unit";"Zergling";"Larva";787;1
"Unit";"Zergling";"Larva";787;1
"Unit";"Zergling";"Larva";787;1
"Unit";"Zergling";"Larva";787;1
"Unit";"Zergling";"Larva";787;1
"Unit";"Zergling";"Larva";787;1
"Unit";"Zergling";"Larva";787;1
"Unit";"Zergling";"Larva";787;1
"Unit";"Zergling";"Larva";787;1
"Unit";"Zergling";"Larva";787;1
"Unit";"Ultralisk";"Larva";787;6
"Unit";"Ultralisk";"Larva";787;6
"Unit";"Hydralisk";"Larva";803;2
"Unit";"Hydralisk";"Larva";803;2
"Unit";"Hydralisk";"Larva";803;2
"Building";"CreepTumor";NA;841;0
"Building";"CreepTumor";NA;841;0
"Building";"CreepTumor";NA;841;0
"Building";"CreepTumor";NA;841;0
"Unit";"Hydralisk";"Larva";847;2
"Unit";"Hydralisk";"Larva";847;2
"Unit";"Hydralisk";"Larva";847;2
"Unit";"Hydralisk";"Larva";847;2
"Unit";"Hydralisk";"Larva";847;2
"Unit";"Hydralisk";"Larva";847;2
"Unit";"Hydralisk";"Larva";847;2
"Unit";"Hydralisk";"Larva";847;2
"Unit";"Hydralisk";"Larva";847;2
"Unit";"Hydralisk";"Larva";847;2
"Unit";"Baneling";"Zergling";847;0
"Unit";"Baneling";"Zergling";847;0
"Unit";"Baneling";"Zergling";847;0
"Unit";"Baneling";"Zergling";847;0
"Unit";"Baneling";"Zergling";847;0
"Unit";"Baneling";"Zergling";847;0
"Unit";"Baneling";"Zergling";847;0
"Unit";"Baneling";"Zergling";847;0
"Unit";"Baneling";"Zergling";847;0
"Unit";"Baneling";"Zergling";847;0
"Unit";"Baneling";"Zergling";847;0
"Unit";"Baneling";"Zergling";847;0
"Unit";"Baneling";"Zergling";847;0
"Unit";"Baneling";"Zergling";847;0
"Unit";"Baneling";"Zergling";847;0
"Unit";"Baneling";"Zergling";847;0
"Unit";"Baneling";"Zergling";847;0
"Unit";"Baneling";"Zergling";847;0
"Unit";"Baneling";"Zergling";847;0
"Unit";"Baneling";"Zergling";847;0
"Unit";"Baneling";"Zergling";847;0
"Building";"CreepTumor";NA;867;0
"Building";"CreepTumor";NA;867;0
"Building";"CreepTumor";NA;867;0
"Building";"CreepTumor";NA;867;0
"Unit";"Hydralisk";"Larva";867;2
"Unit";"Hydralisk";"Larva";867;2
"Unit";"Hydralisk";"Larva";867;2
"Unit";"Hydralisk";"Larva";867;2
"Unit";"Hydralisk";"Larva";867;2
"Unit";"Hydralisk";"Larva";867;2
"Unit";"Hydralisk";"Larva";867;2
"Unit";"Hydralisk";"Larva";867;2
"Unit";"Hydralisk";"Larva";867;2
"Unit";"Hydralisk";"Larva";867;2
"Unit";"Hydralisk";"Larva";867;2
"Unit";"Hydralisk";"Larva";867;2
"Unit";"Hydralisk";"Larva";867;2
"Unit";"Hydralisk";"Larva";867;2
"Unit";"Hydralisk";"Larva";867;2
"Unit";"Hydralisk";"Larva";867;2
"Unit";"Hydralisk";"Larva";883;2
"Unit";"Hydralisk";"Larva";883;2
"Unit";"Hydralisk";"Larva";883;2
"Unit";"Hydralisk";"Larva";883;2
"Unit";"Hydralisk";"Larva";883;2
"Unit";"Hydralisk";"Larva";883;2
"Unit";"Hydralisk";"Larva";883;2
"Unit";"Hydralisk";"Larva";883;2
"Unit";"Zergling";"Larva";905;1
"Unit";"Zergling";"Larva";905;1
"Unit";"Zergling";"Larva";905;1
"Unit";"Zergling";"Larva";905;1
"Unit";"Zergling";"Larva";905;1
"Unit";"Zergling";"Larva";905;1
"Unit";"Zergling";"Larva";905;1
"Unit";"Zergling";"Larva";905;1
"Unit";"Zergling";"Larva";905;1
"Unit";"Zergling";"Larva";905;1
"Unit";"Zergling";"Larva";905;1
"Unit";"Zergling";"Larva";905;1
"Unit";"Zergling";"Larva";905;1
"Unit";"Zergling";"Larva";905;1
"Unit";"Zergling";"Larva";905;1
"Unit";"Zergling";"Larva";905;1
"Unit";"Zergling";"Larva";915;1
"Unit";"Zergling";"Larva";915;1
"Unit";"Zergling";"Larva";915;1
"Unit";"Zergling";"Larva";915;1
"Unit";"Ultralisk";"Larva";905;6
"Unit";"Ultralisk";"Larva";905;6
"Building";"Extractor";NA;935;0
"Unit";"Ultralisk";"Larva";915;6
"Unit";"Ultralisk";"Larva";935;6
"Unit";"Ultralisk";"Larva";935;6
