"type";"unit_name";"on_building";"total_supply";"supply"
"Unit";"Overlord";"Larva";13;0
"Building";"Extractor";NA;21;0
"Building";"SpawningPool";NA;19;0
"Building";"Hatchery";NA;17;0
"Unit";"Zergling";"Larva";23;1
"Unit";"Zergling";"Larva";23;1
"Unit";"Zergling";"Larva";23;1
"Unit";"Zergling";"Larva";23;1
"Unit";"Queen";"Hatchery";23;2
"Unit";"Overlord";"Larva";23;0
"Unit";"Queen";"Hatchery";23;2
"Building";"Hatchery";NA;21;0
"Unit";"Overlord";"Larva";31;0
"Unit";"Overlord";"Larva";35;0
"Unit";"Overlord";"Larva";40;0
"Unit";"Overlord";"Larva";44;0
"Building";"RoachWarren";NA;38;0
"Unit";"Roach";"Larva";47;2
"Unit";"Roach";"Larva";47;2
"Unit";"Roach";"Larva";47;2
"Unit";"Roach";"Larva";47;2
"Unit";"Roach";"Larva";47;2
"Unit";"Roach";"Larva";47;2
"Unit";"Roach";"Larva";47;2
"Unit";"Roach";"Larva";47;2
"Unit";"Roach";"Larva";47;2
"Unit";"Roach";"Larva";47;2
"Unit";"Roach";"Larva";47;2
"Unit";"Roach";"Larva";47;2
"Unit";"Overlord";"Larva";70;0
"Unit";"Queen";"Hatchery";68;2
"Unit";"Overlord";"Larva";79;0
"Unit";"Overlord";"Larva";79;0
"Unit";"Overlord";"Larva";79;0
"Unit";"Overlord";"Larva";79;0
"Unit";"Roach";"Larva";91;2
"Unit";"Roach";"Larva";91;2
"Unit";"Roach";"Larva";93;2
"Unit";"Roach";"Larva";93;2
"Unit";"Roach";"Larva";93;2
"Building";"SporeCrawler";NA;96;0
"Building";"SporeCrawler";NA;96;0
"Unit";"Roach";"Larva";100;2
"Unit";"Roach";"Larva";100;2
"Building";"SporeCrawler";NA;100;0
"Building";"SporeCrawler";NA;100;0
"Unit";"Queen";"Hatchery";95;2
"Building";"SporeCrawler";NA;106;0
"Building";"Extractor";NA;108;0
"Building";"Extractor";NA;110;0
"Building";"CreepTumorQueen";NA;129;0
"Building";"Extractor";NA;127;0
"Building";"Extractor";NA;127;0
"Building";"Extractor";NA;130;0
"Unit";"Roach";"Larva";132;2
"Building";"HydraliskDen";NA;130;0
"Unit";"Overlord";"Larva";132;0
"Unit";"Overlord";"Larva";132;0
"Unit";"Overlord";"Larva";132;0
"Building";"EvolutionChamber";NA;131;0
"Building";"EvolutionChamber";NA;132;0
"Unit";"Queen";"Hatchery";130;2
"Unit";"Hydralisk";"Larva";139;2
"Unit";"Hydralisk";"Larva";139;2
"Unit";"Hydralisk";"Larva";139;2
"Unit";"Hydralisk";"Larva";139;2
"Unit";"Hydralisk";"Larva";139;2
"Unit";"Hydralisk";"Larva";143;2
"Unit";"Hydralisk";"Larva";143;2
"Unit";"Hydralisk";"Larva";143;2
"Unit";"Hydralisk";"Larva";143;2
"Unit";"Queen";"Hatchery";143;2
"Unit";"Hydralisk";"Larva";153;2
"Unit";"Hydralisk";"Larva";153;2
"Unit";"Hydralisk";"Larva";153;2
"Unit";"Hydralisk";"Larva";153;2
"Building";"CreepTumorQueen";NA;172;0
"Unit";"Roach";"Larva";163;2
"Unit";"Roach";"Larva";163;2
"Unit";"Roach";"Larva";163;2
"Unit";"Roach";"Larva";163;2
"Unit";"Roach";"Larva";163;2
"Unit";"Roach";"Larva";163;2
"Unit";"Roach";"Larva";163;2
"Unit";"Roach";"Larva";163;2
"Unit";"Overlord";"Larva";173;0
"Unit";"Overlord";"Larva";173;0
"Unit";"Overlord";"Larva";174;0
"Unit";"Roach";"Larva";193;2
"Unit";"Roach";"Larva";193;2
"Unit";"Roach";"Larva";193;2
"Unit";"Roach";"Larva";193;2
"Unit";"Roach";"Larva";193;2
"Unit";"Roach";"Larva";193;2
"Unit";"Roach";"Larva";193;2
"Unit";"Roach";"Larva";193;2
"Unit";"Roach";"Larva";193;2
"Unit";"Roach";"Larva";196;2
"Unit";"Roach";"Larva";196;2
"Upgrade";"EvolveGroovedSpines";"HydraliskDen";176;0
"Unit";"Roach";"Larva";196;2
"Unit";"Roach";"Larva";196;2
"Unit";"Roach";"Larva";196;2
"Unit";"Roach";"Larva";214;2
"Unit";"Roach";"Larva";214;2
"Unit";"Roach";"Larva";214;2
"Unit";"Roach";"Larva";220;2
"Unit";"Roach";"Larva";220;2
"Unit";"Roach";"Larva";220;2
"Unit";"Roach";"Larva";220;2
"Unit";"Roach";"Larva";220;2
"Unit";"Roach";"Larva";222;2
"Unit";"Hydralisk";"Larva";222;2
"Upgrade";"GlialReconstitution";"RoachWarren";193;0
"Unit";"Roach";"Larva";224;2
"Unit";"Roach";"Larva";224;2
"Unit";"Roach";"Larva";224;2
"Building";"CreepTumorQueen";NA;244;0
"Unit";"Overlord";"Larva";244;0
"Unit";"Overlord";"Larva";244;0
"Unit";"Overlord";"Larva";244;0
"Unit";"Overlord";"Larva";244;0
"Building";"CreepTumorQueen";NA;251;0
"Building";"CreepTumorQueen";NA;251;0
"Unit";"Hydralisk";"Larva";246;2
"Upgrade";"ZergMissileWeaponsLevel1";"EvolutionChamber";196;0
"Upgrade";"ZergGroundArmorsLevel1";"EvolutionChamber";198;0
"Unit";"Roach";"Larva";251;2
"Unit";"Roach";"Larva";251;2
"Unit";"Roach";"Larva";251;2
"Unit";"Roach";"Larva";251;2
"Unit";"Roach";"Larva";251;2
"Unit";"Hydralisk";"Larva";251;2
"Unit";"Hydralisk";"Larva";251;2
"Unit";"Hydralisk";"Larva";251;2
"Unit";"Hydralisk";"Larva";251;2
"Unit";"Hydralisk";"Larva";251;2
"Unit";"Roach";"Larva";251;2
"Unit";"Roach";"Larva";253;2
"Unit";"Roach";"Larva";253;2
"Unit";"Hydralisk";"Larva";253;2
"Unit";"Roach";"Larva";253;2
"Building";"Hatchery";NA;224;0
"Upgrade";"EvolveMuscularAugments";"HydraliskDen";244;0
"Unit";"Hydralisk";"Larva";253;2
"Unit";"Roach";"Larva";263;2
"Unit";"Roach";"Larva";273;2
"Unit";"Roach";"Larva";273;2
"Unit";"Hydralisk";"Larva";263;2
"Unit";"Hydralisk";"Larva";263;2
"Unit";"Roach";"Larva";277;2
"Unit";"Roach";"Larva";285;2
"Unit";"Roach";"Larva";285;2
"Unit";"Roach";"Larva";291;2
"Unit";"Roach";"Larva";295;2
"Unit";"Roach";"Larva";295;2
"Unit";"Roach";"Larva";295;2
"Unit";"Roach";"Larva";297;2
"Unit";"Roach";"Larva";309;2
"Unit";"Hydralisk";"Larva";311;2
"Unit";"Roach";"Larva";319;2
"Unit";"Hydralisk";"Larva";319;2
"Unit";"Hydralisk";"Larva";319;2
"Unit";"Hydralisk";"Larva";319;2
"Unit";"Hydralisk";"Larva";319;2
"Unit";"Hydralisk";"Larva";319;2
"Unit";"Roach";"Larva";321;2
"Unit";"Hydralisk";"Larva";321;2
"Unit";"Hydralisk";"Larva";321;2
"Unit";"Hydralisk";"Larva";321;2
"Unit";"Hydralisk";"Larva";323;2
"Unit";"Roach";"Larva";331;2
"Unit";"Roach";"Larva";331;2
"Unit";"Hydralisk";"Larva";331;2
"Unit";"Roach";"Larva";335;2
"Unit";"Hydralisk";"Larva";335;2
"Unit";"Hydralisk";"Larva";343;2
"Unit";"Hydralisk";"Larva";347;2
"Building";"CreepTumor";NA;353;0
"Building";"CreepTumor";NA;353;0
"Unit";"Hydralisk";"Larva";357;2
"Unit";"Hydralisk";"Larva";357;2
"Upgrade";"ZergMissileWeaponsLevel2";"EvolutionChamber";319;0
"Upgrade";"ZergGroundArmorsLevel2";"EvolutionChamber";319;0
"Unit";"Hydralisk";"Larva";359;2
"Unit";"Hydralisk";"Larva";359;2
"Unit";"Hydralisk";"Larva";359;2
"Unit";"Hydralisk";"Larva";359;2
"Unit";"Roach";"Larva";363;2
"Unit";"Roach";"Larva";363;2
"Unit";"Roach";"Larva";363;2
"Unit";"Roach";"Larva";363;2
"Unit";"Roach";"Larva";371;2
"Unit";"Roach";"Larva";371;2
"Unit";"Roach";"Larva";371;2
"Unit";"Roach";"Larva";371;2
"Unit";"Hydralisk";"Larva";379;2
"Unit";"Hydralisk";"Larva";383;2
"Unit";"Hydralisk";"Larva";385;2
"Unit";"Roach";"Larva";387;2
