"type";"unit_name";"on_building";"total_supply_lag";"supply"
"Unit";"Overlord";"Larva";14;0
"Building";"Hatchery";NA;17;0
"Building";"Extractor";NA;19;0
"Building";"SpawningPool";NA;19;0
"Unit";"Overlord";"Larva";22;0
"Unit";"Queen";"Hatchery";22;2
"Unit";"Zergling";"Larva";24;1
"Unit";"Zergling";"Larva";25;1
"Unit";"Queen";"Hatchery";26;2
"Unit";"Zergling";"Larva";28;1
"Unit";"Zergling";"Larva";29;1
"Unit";"Zergling";"Larva";30;1
"Unit";"Zergling";"Larva";31;1
"Unit";"Queen";"Hatchery";36;2
"Unit";"Overlord";"Larva";41;0
"Unit";"Overlord";"Larva";42;0
"Building";"CreepTumorQueen";NA;42;0
"Building";"Hatchery";NA;50;0
"Building";"CreepTumor";NA;52;0
"Building";"CreepTumorQueen";NA;52;0
"Unit";"Queen";"Hatchery";52;2
"Unit";"Queen";"Hatchery";54;2
"Unit";"Overlord";"Larva";59;0
"Unit";"Zergling";"Larva";59;1
"Unit";"Zergling";"Larva";60;1
"Unit";"Zergling";"Larva";61;1
"Unit";"Zergling";"Larva";62;1
"Unit";"Zergling";"Larva";63;1
"Unit";"Zergling";"Larva";64;1
"Unit";"Overlord";"Larva";65;0
"Building";"CreepTumor";NA;65;0
"Unit";"Overlord";"Larva";65;0
"Building";"CreepTumor";NA;65;0
"Building";"CreepTumorQueen";NA;68;0
"Unit";"Queen";"Hatchery";73;2
"Unit";"Queen";"Hatchery";75;2
"Unit";"Zergling";"Larva";77;1
"Unit";"Zergling";"Larva";78;1
"Unit";"Zergling";"Larva";79;1
"Unit";"Zergling";"Larva";80;1
"Unit";"Zergling";"Larva";81;1
"Unit";"Zergling";"Larva";82;1
"Building";"CreepTumor";NA;83;0
"Building";"CreepTumor";NA;83;0
"Building";"CreepTumor";NA;84;0
"Building";"EvolutionChamber";NA;86;0
"Building";"EvolutionChamber";NA;86;0
"Unit";"Queen";"Hatchery";86;2
"Unit";"Overlord";"Larva";92;0
"Unit";"Overlord";"Larva";92;0
"Unit";"Overlord";"Larva";92;0
"Unit";"Overlord";"Larva";92;0
"Building";"SporeCrawler";NA;92;0
"Unit";"Zergling";"Larva";92;1
"Unit";"Zergling";"Larva";93;1
"Unit";"Zergling";"Larva";94;1
"Unit";"Zergling";"Larva";95;1
"Unit";"Zergling";"Larva";96;1
"Unit";"Zergling";"Larva";97;1
"Unit";"Zergling";"Larva";98;1
"Unit";"Zergling";"Larva";99;1
"Unit";"Zergling";"Larva";100;1
"Unit";"Zergling";"Larva";101;1
"Unit";"Zergling";"Larva";102;1
"Unit";"Zergling";"Larva";103;1
"Building";"RoachWarren";NA;105;0
"Building";"Extractor";NA;106;0
"Building";"CreepTumor";NA;110;0
"Unit";"Overlord";"Larva";114;0
"Building";"CreepTumor";NA;114;0
"Building";"Extractor";NA;116;0
"Building";"Extractor";NA;116;0
"Building";"CreepTumorQueen";NA;117;0
"Building";"CreepTumorQueen";NA;117;0
"Building";"Extractor";NA;120;0
"Building";"Extractor";NA;120;0
"Unit";"Overlord";"Larva";120;0
"Unit";"Zergling";"Larva";120;1
"Unit";"Zergling";"Larva";121;1
"Building";"CreepTumorQueen";NA;122;0
"Building";"CreepTumorQueen";NA;122;0
"Building";"CreepTumor";NA;130;0
"Unit";"Roach";"Larva";130;2
"Unit";"Roach";"Larva";132;2
"Unit";"Roach";"Larva";134;2
"Building";"CreepTumor";NA;136;0
"Unit";"Overlord";"Larva";136;0
"Building";"InfestationPit";NA;136;0
"Unit";"Overlord";"Larva";136;0
"Unit";"Overlord";"Larva";136;0
"Building";"Hatchery";NA;136;0
"Building";"CreepTumor";NA;136;0
"Building";"CreepTumor";NA;136;0
"Unit";"Overlord";"Larva";136;0
"Unit";"Overlord";"Larva";136;0
"Upgrade";"GlialReconstitution";"RoachWarren";136;0
"Unit";"Overlord";"Larva";136;0
"Unit";"Roach";"Larva";136;2
"Unit";"Roach";"Larva";138;2
"Unit";"Roach";"Larva";140;2
"Unit";"Roach";"Larva";142;2
"Unit";"Roach";"Larva";144;2
"Unit";"Roach";"Larva";146;2
"Unit";"Roach";"Larva";148;2
"Unit";"Roach";"Larva";150;2
"Unit";"Roach";"Larva";152;2
"Unit";"Roach";"Larva";154;2
"Building";"CreepTumor";NA;156;0
"Building";"CreepTumor";NA;156;0
"Building";"CreepTumor";NA;156;0
"Building";"CreepTumor";NA;156;0
"Building";"CreepTumor";NA;156;0
"Unit";"Overlord";"Larva";156;0
"Building";"CreepTumor";NA;156;0
"Building";"CreepTumorQueen";NA;156;0
"Unit";"Roach";"Larva";156;2
"Unit";"Roach";"Larva";158;2
"Unit";"Roach";"Larva";160;2
"Unit";"Roach";"Larva";162;2
"Unit";"Roach";"Larva";164;2
"Unit";"Roach";"Larva";166;2
"Unit";"Roach";"Larva";168;2
"Building";"CreepTumorQueen";NA;170;0
"Unit";"Infestor";"Larva";170;2
"Unit";"Infestor";"Larva";172;2
"Building";"CreepTumor";NA;177;0
"Building";"CreepTumor";NA;177;0
"Building";"CreepTumor";NA;186;0
"Building";"CreepTumor";NA;186;0
"Building";"CreepTumor";NA;186;0
"Building";"CreepTumor";NA;186;0
"Building";"CreepTumor";NA;186;0
"Unit";"Zergling";"Larva";186;1
"Unit";"Zergling";"Larva";187;1
"Unit";"Zergling";"Larva";188;1
"Unit";"Zergling";"Larva";189;1
"Unit";"Zergling";"Larva";190;1
"Unit";"Zergling";"Larva";191;1
"Unit";"Overlord";"Larva";192;0
"Unit";"Zergling";"Larva";192;1
"Unit";"Zergling";"Larva";193;1
"Unit";"Overlord";"Larva";194;0
"Building";"Extractor";NA;194;0
"Building";"CreepTumor";NA;194;0
"Building";"Extractor";NA;194;0
"Unit";"Overlord";"Larva";194;0
"Building";"CreepTumor";NA;194;0
"Building";"CreepTumor";NA;194;0
"Building";"CreepTumorQueen";NA;194;0
"Unit";"Zergling";"Larva";195;1
"Unit";"Zergling";"Larva";196;1
"Unit";"Zergling";"Larva";197;1
"Unit";"Zergling";"Larva";198;1
"Building";"SpineCrawler";NA;199;0
"Building";"CreepTumor";NA;199;0
"Unit";"Zergling";"Larva";199;1
"Unit";"Zergling";"Larva";200;1
"Unit";"Zergling";"Larva";201;1
"Unit";"Zergling";"Larva";202;1
"Building";"CreepTumor";NA;203;0
"Unit";"Zergling";"Larva";203;1
"Unit";"Zergling";"Larva";204;1
"Unit";"Zergling";"Larva";205;1
"Unit";"Zergling";"Larva";206;1
"Unit";"Zergling";"Larva";207;1
"Unit";"Zergling";"Larva";208;1
"Unit";"Overlord";"Larva";209;0
"Unit";"Overlord";"Larva";209;0
"Unit";"Roach";"Larva";210;2
"Unit";"Roach";"Larva";212;2
"Unit";"Zergling";"Larva";214;1
"Unit";"Zergling";"Larva";215;1
"Unit";"Zergling";"Larva";216;1
"Unit";"Zergling";"Larva";217;1
"Unit";"Zergling";"Larva";218;1
"Unit";"Zergling";"Larva";219;1
"Building";"UltraliskCavern";NA;220;0
"Unit";"Zergling";"Larva";220;1
"Unit";"Zergling";"Larva";221;1
"Building";"CreepTumor";NA;222;0
"Building";"CreepTumor";NA;222;0
"Unit";"Zergling";"Larva";222;1
"Unit";"Zergling";"Larva";223;1
"Unit";"Zergling";"Larva";224;1
"Unit";"Zergling";"Larva";225;1
"Unit";"Zergling";"Larva";226;1
"Unit";"Zergling";"Larva";227;1
"Unit";"Zergling";"Larva";228;1
"Unit";"Zergling";"Larva";229;1
"Unit";"Zergling";"Larva";230;1
"Unit";"Zergling";"Larva";231;1
"Building";"CreepTumor";NA;232;0
"Building";"CreepTumor";NA;232;0
"Building";"CreepTumor";NA;232;0
"Building";"CreepTumor";NA;232;0
"Building";"CreepTumor";NA;232;0
"Unit";"Zergling";"Larva";232;1
"Unit";"Zergling";"Larva";233;1
"Unit";"Zergling";"Larva";234;1
"Unit";"Zergling";"Larva";235;1
"Unit";"Overlord";"Larva";236;0
"Unit";"Zergling";"Larva";236;1
"Unit";"Zergling";"Larva";237;1
"Unit";"Zergling";"Larva";238;1
"Unit";"Zergling";"Larva";239;1
"Unit";"Zergling";"Larva";240;1
"Unit";"Zergling";"Larva";241;1
"Unit";"Zergling";"Larva";242;1
"Unit";"Zergling";"Larva";243;1
"Unit";"Zergling";"Larva";244;1
"Unit";"Zergling";"Larva";245;1
"Unit";"Zergling";"Larva";246;1
"Unit";"Zergling";"Larva";247;1
"Unit";"Zergling";"Larva";248;1
"Unit";"Zergling";"Larva";249;1
"Unit";"Zergling";"Larva";250;1
"Unit";"Zergling";"Larva";251;1
"Unit";"Zergling";"Larva";252;1
"Unit";"Zergling";"Larva";253;1
"Unit";"Zergling";"Larva";254;1
"Unit";"Zergling";"Larva";255;1
"Unit";"Roach";"Larva";256;2
"Unit";"Roach";"Larva";258;2
"Unit";"Roach";"Larva";260;2
"Unit";"Roach";"Larva";262;2
"Unit";"Roach";"Larva";264;2
"Unit";"Roach";"Larva";266;2
"Unit";"Roach";"Larva";268;2
"Unit";"Ultralisk";"Larva";270;6
"Unit";"Ultralisk";"Larva";276;6
"Unit";"Ultralisk";"Larva";282;6
"Unit";"Ultralisk";"Larva";288;6
"Unit";"Zergling";"Larva";294;1
"Unit";"Zergling";"Larva";295;1
"Upgrade";"ChitinousPlating";"UltraliskCavern";296;0
"Unit";"Roach";"Larva";296;2
"Unit";"Roach";"Larva";298;2
"Unit";"Roach";"Larva";300;2
"Unit";"Roach";"Larva";302;2
"Unit";"Roach";"Larva";304;2
"Unit";"Roach";"Larva";306;2
"Unit";"Roach";"Larva";308;2
"Unit";"Roach";"Larva";310;2
"Unit";"Roach";"Larva";312;2
"Unit";"Roach";"Larva";314;2
"Unit";"Roach";"Larva";316;2
"Unit";"Roach";"Larva";318;2
"Unit";"Roach";"Larva";320;2
"Unit";"Roach";"Larva";322;2
"Unit";"Ultralisk";"Larva";324;6
"Unit";"Ultralisk";"Larva";330;6
"Unit";"Ultralisk";"Larva";336;6
"Unit";"Zergling";"Larva";342;1
"Unit";"Zergling";"Larva";343;1
"Unit";"Zergling";"Larva";344;1
"Unit";"Zergling";"Larva";345;1
"Unit";"Zergling";"Larva";346;1
"Unit";"Zergling";"Larva";347;1
"Unit";"Zergling";"Larva";348;1
"Unit";"Zergling";"Larva";349;1
"Unit";"Zergling";"Larva";350;1
"Unit";"Zergling";"Larva";351;1
"Unit";"Zergling";"Larva";352;1
"Unit";"Zergling";"Larva";353;1
"Unit";"Zergling";"Larva";354;1
"Unit";"Zergling";"Larva";355;1
"Unit";"Roach";"Larva";356;2
"Unit";"Roach";"Larva";358;2
"Unit";"Roach";"Larva";360;2
"Unit";"Roach";"Larva";362;2
"Unit";"Roach";"Larva";364;2
"Unit";"Roach";"Larva";366;2
"Building";"Hatchery";NA;368;0
"Unit";"Roach";"Larva";368;2
"Unit";"Roach";"Larva";370;2
"Unit";"Roach";"Larva";372;2
"Unit";"Roach";"Larva";374;2
"Unit";"Ultralisk";"Larva";376;6
"Unit";"Ultralisk";"Larva";382;6
"Building";"Extractor";NA;396;0
"Building";"CreepTumor";NA;401;0
"Unit";"Zergling";"Larva";401;1
"Unit";"Zergling";"Larva";402;1
"Unit";"Zergling";"Larva";403;1
"Unit";"Zergling";"Larva";404;1
"Unit";"Zergling";"Larva";405;1
"Unit";"Zergling";"Larva";406;1
"Unit";"Zergling";"Larva";407;1
"Unit";"Zergling";"Larva";408;1
"Unit";"Zergling";"Larva";409;1
"Unit";"Zergling";"Larva";410;1
"Unit";"Zergling";"Larva";411;1
"Unit";"Zergling";"Larva";412;1
"Building";"CreepTumor";NA;413;0
"Building";"CreepTumor";NA;413;0
"Building";"CreepTumor";NA;413;0
"Building";"CreepTumor";NA;413;0
"Building";"CreepTumor";NA;413;0
"Unit";"Zergling";"Larva";413;1
"Unit";"Zergling";"Larva";414;1
"Unit";"Zergling";"Larva";415;1
"Unit";"Zergling";"Larva";416;1
"Unit";"Zergling";"Larva";417;1
"Unit";"Zergling";"Larva";418;1
"Unit";"Zergling";"Larva";419;1
"Unit";"Zergling";"Larva";420;1
"Unit";"Zergling";"Larva";421;1
"Unit";"Zergling";"Larva";422;1
"Unit";"Zergling";"Larva";423;1
"Unit";"Zergling";"Larva";424;1
"Unit";"Ultralisk";"Larva";425;6
"Unit";"Zergling";"Larva";431;1
"Unit";"Zergling";"Larva";432;1
"Unit";"Zergling";"Larva";433;1
"Unit";"Zergling";"Larva";434;1
"Unit";"Zergling";"Larva";435;1
"Unit";"Zergling";"Larva";436;1
"Unit";"Infestor";"Larva";437;2
"Unit";"Zergling";"Larva";439;1
"Unit";"Zergling";"Larva";440;1
"Unit";"Zergling";"Larva";441;1
"Unit";"Zergling";"Larva";442;1
"Unit";"Zergling";"Larva";443;1
"Unit";"Zergling";"Larva";444;1
"Unit";"Zergling";"Larva";445;1
"Unit";"Zergling";"Larva";446;1
"Unit";"Zergling";"Larva";447;1
"Unit";"Zergling";"Larva";448;1
"Unit";"Zergling";"Larva";449;1
"Unit";"Zergling";"Larva";450;1
"Unit";"Zergling";"Larva";451;1
"Unit";"Zergling";"Larva";452;1
"Unit";"Zergling";"Larva";453;1
"Unit";"Zergling";"Larva";454;1
"Unit";"Zergling";"Larva";455;1
"Unit";"Zergling";"Larva";456;1
"Unit";"Zergling";"Larva";457;1
"Unit";"Zergling";"Larva";458;1
"Unit";"Zergling";"Larva";459;1
"Unit";"Zergling";"Larva";460;1
"Upgrade";"SprayZerg";NA;462;0
"Upgrade";"SprayZerg";NA;462;0
"Upgrade";"zerglingmovementspeed";NA;462;0
"Upgrade";"SprayZerg";NA;462;0
"Upgrade";"SprayZerg";NA;462;0
"Upgrade";"SprayZerg";NA;462;0
"Upgrade";"ZergGroundArmorsLevel1";NA;462;0
"Upgrade";"ZergMissileWeaponsLevel1";NA;462;0
"Upgrade";"SprayZerg";NA;462;0
"Upgrade";"overlordspeed";NA;462;0
"Upgrade";"ZergMeleeWeaponsLevel1";NA;462;0
"Upgrade";"ZergGroundArmorsLevel2";NA;462;0
"Upgrade";"zerglingattackspeed";NA;462;0
"Upgrade";"SprayZerg";NA;462;0
"Upgrade";"SprayZerg";NA;462;0
