"type";"unit_name";"on_building";"total_supply";"supply"
"Unit";"Overlord";"Larva";13;0
"Building";"Extractor";NA;14;0
"Building";"SpawningPool";NA;17;0
"Unit";"Zergling";"Larva";20;1
"Unit";"Zergling";"Larva";20;1
"Unit";"Zergling";"Larva";20;1
"Unit";"Zergling";"Larva";20;1
"Unit";"Zergling";"Larva";20;1
"Unit";"Zergling";"Larva";20;1
"Unit";"Overlord";"Larva";26;0
"Unit";"Queen";"Hatchery";20;2
"Building";"Hatchery";NA;20;0
"Unit";"Queen";"Hatchery";26;2
"Building";"CreepTumorQueen";NA;33;0
"Unit";"Queen";"Hatchery";30;2
"Unit";"Overlord";"Larva";35;0
"Unit";"Overlord";"Larva";41;0
"Building";"CreepTumor";NA;45;0
"Unit";"Queen";"Hatchery";41;2
"Building";"CreepTumorQueen";NA;50;0
"Building";"CreepTumorQueen";NA;50;0
"Building";"Extractor";NA;48;0
"Unit";"Overlord";"Larva";56;0
"Unit";"Overlord";"Larva";56;0
"Unit";"Queen";"Hatchery";50;2
"Unit";"Overlord";"Larva";56;0
"Unit";"Overlord";"Larva";56;0
"Building";"RoachWarren";NA;50;0
"Building";"SporeCrawler";NA;56;0
"Building";"SporeCrawler";NA;56;0
"Building";"SporeCrawler";NA;56;0
"Unit";"Roach";"Larva";58;2
"Unit";"Roach";"Larva";58;2
"Unit";"Roach";"Larva";58;2
"Unit";"Roach";"Larva";58;2
"Unit";"Roach";"Larva";58;2
"Unit";"Roach";"Larva";58;2
"Building";"CreepTumor";NA;58;0
"Unit";"Roach";"Larva";58;2
"Unit";"Queen";"Hatchery";58;2
"Building";"CreepTumorQueen";NA;75;0
"Building";"CreepTumorQueen";NA;77;0
"Building";"CreepTumorQueen";NA;77;0
"Building";"CreepTumorQueen";NA;83;0
"Building";"CreepTumor";NA;83;0
"Building";"CreepTumor";NA;83;0
"Building";"CreepTumor";NA;83;0
"Building";"Extractor";NA;83;0
"Building";"CreepTumor";NA;83;0
"Building";"CreepTumorQueen";NA;85;0
"Building";"EvolutionChamber";NA;83;0
"Building";"CreepTumorQueen";NA;86;0
"Building";"CreepTumorQueen";NA;86;0
"Unit";"Overlord";"Larva";86;0
"Building";"Extractor";NA;85;0
"Unit";"Overlord";"Larva";86;0
"Building";"CreepTumor";NA;89;0
"Building";"CreepTumor";NA;89;0
"Building";"CreepTumor";NA;89;0
"Building";"CreepTumor";NA;89;0
"Unit";"Roach";"Larva";89;2
"Unit";"Roach";"Larva";89;2
"Unit";"Roach";"Larva";89;2
"Unit";"Roach";"Larva";89;2
"Unit";"Roach";"Larva";89;2
"Building";"CreepTumor";NA;89;0
"Building";"CreepTumor";NA;89;0
"Building";"Hatchery";NA;83;0
"Building";"CreepTumor";NA;94;0
"Building";"CreepTumorQueen";NA;94;0
"Building";"HydraliskDen";NA;89;0
"Building";"CreepTumorQueen";NA;94;0
"Building";"CreepTumorQueen";NA;96;0
"Building";"CreepTumorQueen";NA;104;0
"Building";"CreepTumorQueen";NA;104;0
"Building";"CreepTumor";NA;113;0
"Building";"CreepTumor";NA;113;0
"Unit";"Overlord";"Larva";109;0
"Unit";"Overlord";"Larva";109;0
"Building";"CreepTumor";NA;113;0
"Building";"CreepTumor";NA;113;0
"Building";"InfestationPit";NA;109;0
"Unit";"Hydralisk";"Larva";113;2
"Building";"CreepTumor";NA;116;0
"Building";"CreepTumor";NA;116;0
"Building";"Extractor";NA;116;0
"Unit";"Hydralisk";"Larva";116;2
"Unit";"Hydralisk";"Larva";116;2
"Unit";"Hydralisk";"Larva";116;2
"Unit";"Hydralisk";"Larva";116;2
"Building";"Extractor";NA;118;0
"Building";"CreepTumor";NA;120;0
"Building";"CreepTumor";NA;120;0
"Unit";"Overlord";"Larva";120;0
"Unit";"Overlord";"Larva";120;0
"Upgrade";"GlialReconstitution";"RoachWarren";109;0
"Building";"CreepTumor";NA;129;0
"Building";"CreepTumor";NA;129;0
"Upgrade";"EvolveGroovedSpines";"HydraliskDen";113;0
"Unit";"Overlord";"Larva";129;0
"Unit";"Overlord";"Larva";129;0
"Building";"CreepTumor";NA;130;0
"Building";"CreepTumor";NA;130;0
"Unit";"Hydralisk";"Larva";130;2
"Unit";"Hydralisk";"Larva";130;2
"Unit";"Hydralisk";"Larva";130;2
"Unit";"Hydralisk";"Larva";130;2
"Unit";"Hydralisk";"Larva";130;2
"Unit";"Hydralisk";"Larva";130;2
"Unit";"Hydralisk";"Larva";130;2
"Unit";"Hydralisk";"Larva";130;2
"Building";"CreepTumor";NA;130;0
"Building";"CreepTumor";NA;130;0
"Unit";"Overlord";"Larva";130;0
"Unit";"Overlord";"Larva";130;0
"Unit";"Overlord";"Larva";130;0
"Building";"CreepTumor";NA;130;0
"Building";"CreepTumor";NA;130;0
"Building";"CreepTumor";NA;130;0
"Upgrade";"ZergMissileWeaponsLevel1";"EvolutionChamber";113;0
"Building";"CreepTumorQueen";NA;130;0
"Building";"CreepTumorQueen";NA;140;0
"Building";"CreepTumorQueen";NA;146;0
"Unit";"Overlord";"Larva";146;0
"Unit";"Overlord";"Larva";146;0
"Building";"Hatchery";NA;120;0
"Unit";"Hydralisk";"Larva";146;2
"Unit";"Hydralisk";"Larva";146;2
"Unit";"Hydralisk";"Larva";146;2
"Unit";"Hydralisk";"Larva";146;2
"Unit";"Hydralisk";"Larva";150;2
"Unit";"Hydralisk";"Larva";150;2
"Unit";"Hydralisk";"Larva";150;2
"Unit";"Viper";"Larva";150;3
"Building";"CreepTumor";NA;164;0
"Unit";"Viper";"Larva";150;3
"Unit";"Viper";"Larva";150;3
"Building";"CreepTumorQueen";NA;164;0
"Unit";"Overlord";"Larva";164;0
"Building";"CreepTumorQueen";NA;167;0
"Unit";"Overlord";"Larva";164;0
"Building";"CreepTumorQueen";NA;167;0
"Building";"CreepTumorQueen";NA;173;0
"Building";"CreepTumorQueen";NA;173;0
"Building";"CreepTumorQueen";NA;173;0
"Building";"Extractor";NA;164;0
"Building";"CreepTumor";NA;176;0
"Unit";"Hydralisk";"Larva";164;2
"Unit";"Hydralisk";"Larva";164;2
"Unit";"Hydralisk";"Larva";164;2
"Unit";"Hydralisk";"Larva";164;2
"Building";"CreepTumor";NA;178;0
"Building";"CreepTumorQueen";NA;186;0
"Building";"CreepTumor";NA;186;0
"Building";"CreepTumor";NA;186;0
"Building";"CreepTumorQueen";NA;186;0
"Unit";"Hydralisk";"Larva";178;2
"Unit";"Hydralisk";"Larva";178;2
"Unit";"Hydralisk";"Larva";178;2
"Unit";"Hydralisk";"Larva";178;2
"Unit";"Hydralisk";"Larva";178;2
"Unit";"Hydralisk";"Larva";178;2
"Unit";"Hydralisk";"Larva";178;2
"Unit";"Hydralisk";"Larva";178;2
"Building";"CreepTumorQueen";NA;186;0
"Building";"CreepTumorQueen";NA;186;0
"Building";"CreepTumorQueen";NA;186;0
"Unit";"Overlord";"Larva";186;0
"Unit";"Overlord";"Larva";186;0
"Building";"CreepTumor";NA;208;0
"Unit";"Roach";"Larva";202;2
"Building";"CreepTumor";NA;208;0
"Unit";"Roach";"Larva";202;2
"Unit";"Roach";"Larva";202;2
"Unit";"Roach";"Larva";202;2
"Building";"CreepTumor";NA;208;0
"Building";"CreepTumorQueen";NA;208;0
"Building";"CreepTumorQueen";NA;208;0
"Building";"CreepTumor";NA;208;0
"Building";"CreepTumor";NA;208;0
"Building";"CreepTumor";NA;208;0
"Building";"CreepTumor";NA;208;0
"Building";"CreepTumor";NA;208;0
"Building";"CreepTumorQueen";NA;208;0
"Building";"CreepTumor";NA;208;0
"Building";"CreepTumor";NA;208;0
"Building";"CreepTumor";NA;208;0
"Building";"CreepTumor";NA;208;0
"Building";"CreepTumor";NA;216;0
"Unit";"Hydralisk";"Larva";216;2
"Unit";"Hydralisk";"Larva";216;2
"Unit";"Hydralisk";"Larva";216;2
"Unit";"Hydralisk";"Larva";216;2
"Unit";"Roach";"Larva";224;2
"Unit";"Roach";"Larva";224;2
"Unit";"Roach";"Larva";224;2
"Unit";"Roach";"Larva";224;2
"Unit";"Roach";"Larva";224;2
"Unit";"Roach";"Larva";224;2
"Unit";"Roach";"Larva";224;2
"Unit";"Roach";"Larva";224;2
"Unit";"Hydralisk";"Larva";224;2
"Unit";"Hydralisk";"Larva";224;2
"Unit";"Hydralisk";"Larva";224;2
"Unit";"Hydralisk";"Larva";224;2
"Unit";"Hydralisk";"Larva";224;2
"Unit";"Hydralisk";"Larva";224;2
"Unit";"Hydralisk";"Larva";224;2
"Unit";"Hydralisk";"Larva";224;2
"Unit";"Hydralisk";"Larva";224;2
"Unit";"Viper";"Larva";224;3
"Upgrade";"ZergMissileWeaponsLevel2";"EvolutionChamber";208;0
"Unit";"Roach";"Larva";261;2
"Unit";"Roach";"Larva";261;2
"Unit";"Roach";"Larva";261;2
"Unit";"Roach";"Larva";261;2
"Unit";"Roach";"Larva";261;2
"Unit";"Roach";"Larva";261;2
"Unit";"Hydralisk";"Larva";261;2
"Unit";"Hydralisk";"Larva";261;2
"Unit";"Hydralisk";"Larva";261;2
"Unit";"Hydralisk";"Larva";261;2
"Unit";"Hydralisk";"Larva";261;2
"Unit";"Hydralisk";"Larva";261;2
"Unit";"Hydralisk";"Larva";273;2
"Unit";"Hydralisk";"Larva";273;2
"Unit";"Hydralisk";"Larva";273;2
"Unit";"Hydralisk";"Larva";273;2
"Unit";"Hydralisk";"Larva";273;2
"Building";"CreepTumor";NA;285;0
"Building";"CreepTumor";NA;287;0
"Building";"CreepTumor";NA;287;0
"Unit";"Hydralisk";"Larva";285;2
"Unit";"Hydralisk";"Larva";285;2
"Unit";"Hydralisk";"Larva";285;2
"Unit";"Hydralisk";"Larva";285;2
"Unit";"Hydralisk";"Larva";285;2
"Unit";"Hydralisk";"Larva";285;2
"Unit";"Hydralisk";"Larva";285;2
"Unit";"Hydralisk";"Larva";285;2
"Unit";"Hydralisk";"Larva";285;2
"Unit";"Hydralisk";"Larva";285;2
"Building";"Extractor";NA;295;0
"Building";"UltraliskCavern";NA;285;0
"Unit";"Roach";"Larva";315;2
"Unit";"Roach";"Larva";315;2
"Unit";"Roach";"Larva";315;2
"Unit";"Roach";"Larva";315;2
"Unit";"Roach";"Larva";315;2
"Unit";"Roach";"Larva";315;2
"Unit";"Hydralisk";"Larva";315;2
"Unit";"Hydralisk";"Larva";315;2
"Unit";"Hydralisk";"Larva";315;2
"Unit";"Hydralisk";"Larva";315;2
"Unit";"Hydralisk";"Larva";315;2
"Unit";"Hydralisk";"Larva";315;2
"Unit";"Hydralisk";"Larva";315;2
"Unit";"Hydralisk";"Larva";315;2
"Unit";"Hydralisk";"Larva";343;2
"Unit";"Hydralisk";"Larva";343;2
"Unit";"Hydralisk";"Larva";343;2
"Unit";"Hydralisk";"Larva";343;2
"Unit";"Hydralisk";"Larva";343;2
"Unit";"Hydralisk";"Larva";343;2
"Unit";"Hydralisk";"Larva";343;2
"Unit";"Hydralisk";"Larva";343;2
"Unit";"Zergling";"Larva";343;1
"Unit";"Zergling";"Larva";343;1
"Unit";"Zergling";"Larva";343;1
"Unit";"Zergling";"Larva";343;1
"Unit";"Zergling";"Larva";343;1
"Unit";"Zergling";"Larva";343;1
"Unit";"Zergling";"Larva";343;1
"Unit";"Zergling";"Larva";343;1
"Unit";"Zergling";"Larva";343;1
"Unit";"Zergling";"Larva";343;1
"Unit";"Zergling";"Larva";343;1
"Unit";"Zergling";"Larva";343;1
"Unit";"Zergling";"Larva";343;1
"Unit";"Zergling";"Larva";343;1
"Unit";"Zergling";"Larva";343;1
"Unit";"Zergling";"Larva";343;1
"Unit";"Zergling";"Larva";343;1
"Unit";"Zergling";"Larva";343;1
"Building";"CreepTumor";NA;359;0
"Building";"CreepTumor";NA;359;0
"Building";"CreepTumor";NA;359;0
"Building";"CreepTumor";NA;359;0
"Unit";"Ultralisk";"Larva";343;6
"Building";"CreepTumor";NA;359;0
"Unit";"Ultralisk";"Larva";343;6
"Building";"CreepTumor";NA;359;0
"Building";"CreepTumor";NA;359;0
"Unit";"Zergling";"Larva";359;1
"Unit";"Zergling";"Larva";359;1
"Unit";"Zergling";"Larva";359;1
"Unit";"Zergling";"Larva";359;1
"Unit";"Zergling";"Larva";365;1
"Unit";"Zergling";"Larva";365;1
"Unit";"Zergling";"Larva";365;1
"Unit";"Zergling";"Larva";365;1
"Unit";"Zergling";"Larva";367;1
"Unit";"Zergling";"Larva";367;1
"Unit";"Zergling";"Larva";367;1
"Unit";"Zergling";"Larva";367;1
"Unit";"Zergling";"Larva";371;1
"Unit";"Zergling";"Larva";371;1
"Upgrade";"ZergMissileWeaponsLevel3";"EvolutionChamber";295;0
"Building";"CreepTumor";NA;389;0
"Building";"CreepTumor";NA;389;0
"Building";"CreepTumor";NA;389;0
"Building";"CreepTumor";NA;389;0
"Building";"BanelingNest";NA;343;0
"Building";"SporeCrawler";NA;389;0
"Unit";"Zergling";"Larva";403;1
"Unit";"Zergling";"Larva";403;1
"Unit";"Zergling";"Larva";403;1
"Unit";"Zergling";"Larva";403;1
"Unit";"Zergling";"Larva";403;1
"Unit";"Zergling";"Larva";403;1
"Unit";"Zergling";"Larva";403;1
"Unit";"Zergling";"Larva";403;1
"Unit";"Zergling";"Larva";403;1
"Unit";"Zergling";"Larva";403;1
"Unit";"Zergling";"Larva";403;1
"Unit";"Zergling";"Larva";403;1
"Unit";"Zergling";"Larva";403;1
"Unit";"Zergling";"Larva";403;1
"Unit";"Zergling";"Larva";403;1
"Unit";"Zergling";"Larva";403;1
"Building";"SporeCrawler";NA;389;0
"Building";"SporeCrawler";NA;403;0
"Unit";"Baneling";"Zergling";403;0
"Unit";"Baneling";"Zergling";403;0
"Unit";"Baneling";"Zergling";403;0
"Unit";"Baneling";"Zergling";403;0
"Unit";"Baneling";"Zergling";403;0
"Unit";"Baneling";"Zergling";403;0
"Unit";"Baneling";"Zergling";403;0
"Unit";"Baneling";"Zergling";403;0
"Unit";"Baneling";"Zergling";403;0
"Unit";"Baneling";"Zergling";403;0
"Unit";"Baneling";"Zergling";403;0
"Unit";"Baneling";"Zergling";403;0
"Unit";"Baneling";"Zergling";403;0
"Unit";"Baneling";"Zergling";403;0
"Unit";"Baneling";"Zergling";403;0
"Unit";"Baneling";"Zergling";403;0
"Unit";"Baneling";"Zergling";403;0
"Unit";"Baneling";"Zergling";403;0
"Unit";"Baneling";"Zergling";403;0
"Unit";"Baneling";"Zergling";403;0
"Unit";"Baneling";"Zergling";403;0
"Unit";"Baneling";"Zergling";403;0
"Unit";"Baneling";"Zergling";403;0
"Unit";"Baneling";"Zergling";403;0
"Unit";"Baneling";"Zergling";403;0
"Unit";"Baneling";"Zergling";403;0
"Unit";"Baneling";"Zergling";403;0
"Unit";"Baneling";"Zergling";403;0
"Unit";"Baneling";"Zergling";403;0
"Unit";"Baneling";"Zergling";403;0
"Unit";"Baneling";"Zergling";403;0
"Unit";"Baneling";"Zergling";403;0
"Building";"CreepTumor";NA;419;0
"Building";"CreepTumor";NA;419;0
"Unit";"Zergling";"Larva";403;1
"Unit";"Zergling";"Larva";403;1
"Unit";"Zergling";"Larva";403;1
"Unit";"Zergling";"Larva";403;1
"Unit";"Zergling";"Larva";403;1
"Unit";"Zergling";"Larva";403;1
"Unit";"Zergling";"Larva";403;1
"Unit";"Zergling";"Larva";403;1
"Unit";"Zergling";"Larva";403;1
"Unit";"Zergling";"Larva";403;1
"Unit";"Zergling";"Larva";403;1
"Unit";"Zergling";"Larva";403;1
"Unit";"Zergling";"Larva";403;1
"Unit";"Zergling";"Larva";403;1
"Unit";"Zergling";"Larva";403;1
"Unit";"Zergling";"Larva";403;1
"Unit";"Zergling";"Larva";403;1
"Unit";"Zergling";"Larva";403;1
"Unit";"Zergling";"Larva";403;1
"Unit";"Zergling";"Larva";403;1
"Building";"CreepTumor";NA;439;0
"Building";"CreepTumor";NA;439;0
"Building";"CreepTumor";NA;439;0
"Unit";"Zergling";"Larva";439;1
"Unit";"Zergling";"Larva";439;1
"Unit";"Zergling";"Larva";439;1
"Unit";"Zergling";"Larva";439;1
"Unit";"Zergling";"Larva";439;1
"Unit";"Zergling";"Larva";439;1
"Unit";"Zergling";"Larva";439;1
"Unit";"Zergling";"Larva";439;1
"Unit";"Zergling";"Larva";439;1
"Unit";"Zergling";"Larva";439;1
"Unit";"Zergling";"Larva";439;1
"Unit";"Zergling";"Larva";439;1
"Unit";"Zergling";"Larva";439;1
"Unit";"Zergling";"Larva";439;1
"Unit";"Zergling";"Larva";439;1
"Unit";"Zergling";"Larva";439;1
"Unit";"Zergling";"Larva";439;1
"Unit";"Zergling";"Larva";439;1
"Unit";"Baneling";"Zergling";439;0
"Unit";"Baneling";"Zergling";439;0
"Unit";"Baneling";"Zergling";439;0
"Unit";"Baneling";"Zergling";439;0
"Unit";"Baneling";"Zergling";439;0
"Unit";"Baneling";"Zergling";439;0
"Unit";"Baneling";"Zergling";439;0
"Unit";"Baneling";"Zergling";439;0
"Unit";"Baneling";"Zergling";439;0
"Upgrade";"ChitinousPlating";"UltraliskCavern";403;0
"Unit";"Baneling";"Zergling";457;0
"Unit";"Baneling";"Zergling";457;0
"Unit";"Baneling";"Zergling";457;0
"Unit";"Baneling";"Zergling";457;0
"Unit";"Baneling";"Zergling";457;0
"Unit";"Baneling";"Zergling";457;0
"Unit";"Baneling";"Zergling";457;0
"Unit";"Baneling";"Zergling";457;0
"Unit";"Baneling";"Zergling";457;0
"Unit";"Baneling";"Zergling";457;0
"Unit";"Baneling";"Zergling";457;0
"Unit";"Baneling";"Zergling";457;0
"Unit";"Baneling";"Zergling";457;0
"Unit";"Baneling";"Zergling";457;0
"Unit";"Baneling";"Zergling";457;0
"Unit";"Baneling";"Zergling";457;0
"Unit";"Baneling";"Zergling";457;0
"Unit";"Baneling";"Zergling";457;0
"Unit";"Zergling";"Larva";457;1
"Unit";"Zergling";"Larva";457;1
"Unit";"Zergling";"Larva";457;1
"Unit";"Zergling";"Larva";457;1
"Unit";"Zergling";"Larva";457;1
"Unit";"Zergling";"Larva";457;1
"Unit";"Zergling";"Larva";457;1
"Unit";"Zergling";"Larva";457;1
"Unit";"Zergling";"Larva";457;1
"Unit";"Zergling";"Larva";457;1
"Unit";"Zergling";"Larva";457;1
"Unit";"Zergling";"Larva";457;1
"Unit";"Zergling";"Larva";457;1
"Unit";"Zergling";"Larva";457;1
"Unit";"Zergling";"Larva";457;1
"Unit";"Zergling";"Larva";457;1
"Unit";"Zergling";"Larva";457;1
"Unit";"Zergling";"Larva";457;1
"Unit";"Zergling";"Larva";457;1
"Unit";"Zergling";"Larva";457;1
"Unit";"Zergling";"Larva";457;1
"Unit";"Zergling";"Larva";457;1
"Building";"CreepTumor";NA;457;0
"Building";"CreepTumor";NA;488;0
"Building";"Hatchery";NA;439;0
"Upgrade";"ZergGroundArmorsLevel1";"EvolutionChamber";439;0
"Building";"Extractor";NA;488;0
"Unit";"Ultralisk";"Larva";488;6
"Unit";"Ultralisk";"Larva";488;6
"Unit";"Ultralisk";"Larva";488;6
"Unit";"Ultralisk";"Larva";488;6
"Unit";"Ultralisk";"Larva";488;6
"Building";"SporeCrawler";NA;488;0
"Building";"Spire";NA;479;0
"Building";"CreepTumor";NA;532;0
"Building";"CreepTumor";NA;538;0
"Building";"CreepTumor";NA;538;0
"Unit";"Zergling";"Larva";538;1
"Unit";"Zergling";"Larva";538;1
"Unit";"Zergling";"Larva";538;1
"Unit";"Zergling";"Larva";538;1
"Unit";"Zergling";"Larva";538;1
"Unit";"Zergling";"Larva";538;1
"Unit";"Zergling";"Larva";538;1
"Unit";"Zergling";"Larva";538;1
"Unit";"Zergling";"Larva";538;1
"Unit";"Zergling";"Larva";538;1
"Unit";"Zergling";"Larva";538;1
"Unit";"Zergling";"Larva";538;1
"Unit";"Zergling";"Larva";538;1
"Unit";"Zergling";"Larva";538;1
"Unit";"Zergling";"Larva";538;1
"Unit";"Zergling";"Larva";538;1
"Unit";"Zergling";"Larva";538;1
"Unit";"Zergling";"Larva";538;1
"Unit";"Zergling";"Larva";538;1
"Unit";"Zergling";"Larva";538;1
"Unit";"Zergling";"Larva";538;1
"Unit";"Zergling";"Larva";538;1
"Unit";"Zergling";"Larva";538;1
"Unit";"Zergling";"Larva";538;1
"Unit";"Zergling";"Larva";538;1
"Unit";"Zergling";"Larva";538;1
"Unit";"Zergling";"Larva";538;1
"Unit";"Zergling";"Larva";538;1
"Unit";"Zergling";"Larva";538;1
"Unit";"Zergling";"Larva";538;1
"Unit";"Zergling";"Larva";538;1
"Unit";"Zergling";"Larva";538;1
"Unit";"Zergling";"Larva";538;1
"Unit";"Zergling";"Larva";538;1
"Upgrade";"ZergMeleeWeaponsLevel1";"EvolutionChamber";538;0
"Unit";"Ultralisk";"Larva";572;6
"Unit";"Hydralisk";"Larva";572;2
"Unit";"Hydralisk";"Larva";572;2
"Unit";"Hydralisk";"Larva";572;2
"Unit";"Hydralisk";"Larva";572;2
"Unit";"Hydralisk";"Larva";572;2
"Unit";"Hydralisk";"Larva";572;2
"Unit";"Hydralisk";"Larva";572;2
"Unit";"Hydralisk";"Larva";572;2
"Unit";"Hydralisk";"Larva";572;2
"Unit";"Hydralisk";"Larva";572;2
"Unit";"Hydralisk";"Larva";572;2
"Unit";"Hydralisk";"Larva";572;2
