"type";"unit_name";"on_building";"total_supply";"supply"
"Unit";"Overlord";"Larva";13;0
"Building";"Extractor";NA;14;0
"Building";"SpawningPool";NA;17;0
"Unit";"Zergling";"Larva";20;1
"Unit";"Zergling";"Larva";20;1
"Unit";"Zergling";"Larva";20;1
"Unit";"Zergling";"Larva";20;1
"Unit";"Overlord";"Larva";20;0
"Unit";"Queen";"Hatchery";20;2
"Building";"Hatchery";NA;19;0
"Unit";"Zergling";"Larva";25;1
"Unit";"Zergling";"Larva";25;1
"Unit";"Queen";"Hatchery";29;2
"Unit";"Zergling";"Larva";33;1
"Unit";"Zergling";"Larva";33;1
"Unit";"Zergling";"Larva";33;1
"Unit";"Zergling";"Larva";33;1
"Unit";"Zergling";"Larva";33;1
"Unit";"Zergling";"Larva";33;1
"Unit";"Zergling";"Larva";33;1
"Unit";"Zergling";"Larva";33;1
"Unit";"Zergling";"Larva";33;1
"Unit";"Zergling";"Larva";33;1
"Unit";"Overlord";"Larva";44;0
"Building";"BanelingNest";NA;40;0
"Unit";"Overlord";"Larva";49;0
"Building";"SporeCrawler";NA;49;0
"Building";"SporeCrawler";NA;49;0
"Building";"Extractor";NA;58;0
"Building";"Extractor";NA;58;0
"Building";"Extractor";NA;58;0
"Building";"SpineCrawler";NA;58;0
"Unit";"Zergling";"Larva";64;1
"Unit";"Zergling";"Larva";64;1
"Unit";"Zergling";"Larva";64;1
"Unit";"Zergling";"Larva";64;1
"Unit";"Zergling";"Larva";64;1
"Unit";"Zergling";"Larva";64;1
"Unit";"Overlord";"Larva";64;0
"Unit";"Zergling";"Larva";67;1
"Unit";"Zergling";"Larva";67;1
"Building";"SporeCrawler";NA;67;0
"Unit";"Queen";"Hatchery";64;2
"Unit";"Baneling";"Zergling";77;0
"Unit";"Baneling";"Zergling";77;0
"Unit";"Baneling";"Zergling";77;0
"Unit";"Baneling";"Zergling";77;0
"Unit";"Baneling";"Zergling";77;0
"Unit";"Baneling";"Zergling";77;0
"Unit";"Zergling";"Larva";75;1
"Unit";"Zergling";"Larva";75;1
"Unit";"Zergling";"Larva";75;1
"Unit";"Zergling";"Larva";75;1
"Building";"CreepTumorQueen";NA;86;0
"Building";"CreepTumorQueen";NA;86;0
"Unit";"Baneling";"Zergling";87;0
"Building";"CreepTumor";NA;88;0
"Unit";"Overlord";"Larva";88;0
"Unit";"Overlord";"Larva";88;0
"Unit";"Overlord";"Larva";88;0
"Building";"RoachWarren";NA;86;0
"Unit";"Queen";"Hatchery";90;2
"Building";"Spire";NA;86;0
"Unit";"Overlord";"Larva";90;0
"Unit";"Mutalisk";"Larva";92;2
"Unit";"Mutalisk";"Larva";92;2
"Unit";"Mutalisk";"Larva";92;2
"Unit";"Mutalisk";"Larva";92;2
"Unit";"Mutalisk";"Larva";92;2
"Unit";"Mutalisk";"Larva";92;2
"Unit";"Mutalisk";"Larva";92;2
"Unit";"Zergling";"Larva";92;1
"Unit";"Zergling";"Larva";92;1
"Unit";"Zergling";"Larva";92;1
"Unit";"Zergling";"Larva";92;1
"Building";"CreepTumor";NA;92;0
"Building";"CreepTumorQueen";NA;92;0
"Unit";"Roach";"Larva";113;2
"Unit";"Roach";"Larva";113;2
"Building";"CreepTumor";NA;117;0
"Building";"CreepTumor";NA;117;0
"Building";"CreepTumorQueen";NA;117;0
"Building";"CreepTumorQueen";NA;117;0
"Unit";"Overlord";"Larva";117;0
"Unit";"Overlord";"Larva";117;0
"Unit";"Overlord";"Larva";117;0
"Unit";"Overlord";"Larva";117;0
"Unit";"Overlord";"Larva";117;0
"Unit";"Overlord";"Larva";117;0
"Building";"Hatchery";NA;92;0
"Upgrade";"GlialReconstitution";"RoachWarren";113;0
"Unit";"Roach";"Larva";119;2
"Unit";"Overlord";"Larva";119;0
"Unit";"Overlord";"Larva";119;0
"Building";"Extractor";NA;119;0
"Building";"Extractor";NA;119;0
"Unit";"Zergling";"Larva";119;1
"Unit";"Zergling";"Larva";119;1
"Building";"CreepTumor";NA;121;0
"Building";"CreepTumor";NA;121;0
"Unit";"Zergling";"Larva";119;1
"Unit";"Zergling";"Larva";119;1
"Unit";"Zergling";"Larva";119;1
"Unit";"Zergling";"Larva";119;1
"Unit";"Zergling";"Larva";119;1
"Unit";"Zergling";"Larva";119;1
"Building";"CreepTumor";NA;121;0
"Building";"EvolutionChamber";NA;119;0
"Building";"CreepTumor";NA;121;0
"Building";"EvolutionChamber";NA;119;0
"Unit";"Mutalisk";"Larva";119;2
"Unit";"Mutalisk";"Larva";119;2
"Unit";"Mutalisk";"Larva";119;2
"Unit";"Mutalisk";"Larva";119;2
"Unit";"Baneling";"Zergling";121;0
"Unit";"Baneling";"Zergling";121;0
"Unit";"Zergling";"Larva";121;1
"Unit";"Zergling";"Larva";121;1
"Unit";"Roach";"Larva";121;2
"Unit";"Roach";"Larva";121;2
"Unit";"Roach";"Larva";121;2
"Unit";"Roach";"Larva";121;2
"Unit";"Baneling";"Zergling";139;0
"Unit";"Baneling";"Zergling";139;0
"Unit";"Zergling";"Larva";139;1
"Unit";"Zergling";"Larva";139;1
"Unit";"Zergling";"Larva";139;1
"Unit";"Zergling";"Larva";139;1
"Building";"CreepTumor";NA;159;0
"Unit";"Zergling";"Larva";156;1
"Unit";"Zergling";"Larva";156;1
"Unit";"Zergling";"Larva";156;1
"Unit";"Zergling";"Larva";156;1
"Unit";"Zergling";"Larva";157;1
"Unit";"Zergling";"Larva";157;1
"Unit";"Zergling";"Larva";157;1
"Unit";"Zergling";"Larva";157;1
"Unit";"Zergling";"Larva";157;1
"Unit";"Zergling";"Larva";157;1
"Building";"CreepTumor";NA;159;0
"Unit";"Zergling";"Larva";159;1
"Unit";"Zergling";"Larva";159;1
"Unit";"Zergling";"Larva";159;1
"Unit";"Zergling";"Larva";159;1
"Unit";"Zergling";"Larva";159;1
"Unit";"Zergling";"Larva";159;1
"Unit";"Zergling";"Larva";159;1
"Unit";"Zergling";"Larva";159;1
"Unit";"Mutalisk";"Larva";159;2
"Unit";"Mutalisk";"Larva";159;2
"Building";"CreepTumor";NA;180;0
"Building";"CreepTumorQueen";NA;190;0
"Unit";"Mutalisk";"Larva";169;2
"Unit";"Baneling";"Zergling";192;0
"Unit";"Baneling";"Zergling";192;0
"Unit";"Baneling";"Zergling";192;0
"Unit";"Baneling";"Zergling";192;0
"Unit";"Zergling";"Larva";192;1
"Unit";"Zergling";"Larva";192;1
"Unit";"Zergling";"Larva";192;1
"Unit";"Zergling";"Larva";192;1
"Unit";"Zergling";"Larva";192;1
"Unit";"Zergling";"Larva";192;1
"Building";"InfestationPit";NA;169;0
"Building";"CreepTumor";NA;194;0
"Building";"CreepTumor";NA;194;0
"Building";"CreepTumor";NA;194;0
"Building";"Extractor";NA;194;0
"Building";"Extractor";NA;194;0
"Unit";"Zergling";"Larva";194;1
"Unit";"Zergling";"Larva";194;1
"Unit";"Zergling";"Larva";194;1
"Unit";"Zergling";"Larva";194;1
"Unit";"Zergling";"Larva";194;1
"Unit";"Zergling";"Larva";194;1
"Unit";"Zergling";"Larva";194;1
"Unit";"Zergling";"Larva";194;1
"Unit";"Zergling";"Larva";194;1
"Unit";"Zergling";"Larva";194;1
"Unit";"Zergling";"Larva";194;1
"Unit";"Zergling";"Larva";194;1
"Unit";"Zergling";"Larva";194;1
"Unit";"Zergling";"Larva";194;1
"Unit";"Zergling";"Larva";194;1
"Unit";"Zergling";"Larva";194;1
"Unit";"Zergling";"Larva";194;1
"Unit";"Zergling";"Larva";194;1
"Unit";"Zergling";"Larva";194;1
"Unit";"Zergling";"Larva";194;1
"Unit";"Zergling";"Larva";194;1
"Unit";"Zergling";"Larva";194;1
"Unit";"Zergling";"Larva";194;1
"Unit";"Zergling";"Larva";194;1
"Upgrade";"ZergMeleeWeaponsLevel1";"EvolutionChamber";159;0
"Upgrade";"ZergGroundArmorsLevel1";"EvolutionChamber";159;0
"Unit";"Zergling";"Larva";224;1
"Unit";"Zergling";"Larva";224;1
"Unit";"Baneling";"Zergling";224;0
"Unit";"Baneling";"Zergling";224;0
"Unit";"Zergling";"Larva";224;1
"Unit";"Zergling";"Larva";224;1
"Unit";"Baneling";"Zergling";224;0
"Unit";"Zergling";"Larva";224;1
"Unit";"Zergling";"Larva";224;1
"Unit";"Zergling";"Larva";224;1
"Unit";"Zergling";"Larva";224;1
"Unit";"Zergling";"Larva";224;1
"Unit";"Zergling";"Larva";224;1
"Unit";"Zergling";"Larva";224;1
"Unit";"Zergling";"Larva";224;1
"Unit";"Zergling";"Larva";224;1
"Unit";"Zergling";"Larva";224;1
"Unit";"Zergling";"Larva";224;1
"Unit";"Zergling";"Larva";224;1
"Unit";"Zergling";"Larva";224;1
"Unit";"Zergling";"Larva";224;1
"Unit";"Baneling";"Zergling";224;0
"Unit";"Baneling";"Zergling";224;0
"Unit";"Zergling";"Larva";224;1
"Unit";"Zergling";"Larva";224;1
"Unit";"Baneling";"Zergling";224;0
"Unit";"Baneling";"Zergling";224;0
"Unit";"Baneling";"Zergling";224;0
"Unit";"Baneling";"Zergling";224;0
"Unit";"Baneling";"Zergling";224;0
"Unit";"Baneling";"Zergling";224;0
"Unit";"Zergling";"Larva";244;1
"Unit";"Zergling";"Larva";244;1
"Unit";"Zergling";"Larva";244;1
"Unit";"Zergling";"Larva";244;1
"Unit";"Zergling";"Larva";244;1
"Unit";"Zergling";"Larva";244;1
"Building";"CreepTumor";NA;244;0
"Building";"Hatchery";NA;194;0
"Unit";"Mutalisk";"Larva";244;2
"Unit";"Mutalisk";"Larva";244;2
"Unit";"Mutalisk";"Larva";244;2
"Unit";"Mutalisk";"Larva";244;2
"Building";"CreepTumor";NA;244;0
"Building";"CreepTumor";NA;244;0
"Unit";"Baneling";"Zergling";261;0
"Unit";"Baneling";"Zergling";261;0
"Unit";"Baneling";"Zergling";261;0
"Unit";"Baneling";"Zergling";261;0
"Unit";"Zergling";"Larva";264;1
"Unit";"Zergling";"Larva";264;1
"Unit";"Zergling";"Larva";264;1
"Unit";"Zergling";"Larva";264;1
"Unit";"Zergling";"Larva";264;1
"Unit";"Zergling";"Larva";264;1
"Unit";"Zergling";"Larva";264;1
"Unit";"Zergling";"Larva";264;1
"Unit";"Zergling";"Larva";264;1
"Unit";"Zergling";"Larva";264;1
"Unit";"Zergling";"Larva";264;1
"Unit";"Zergling";"Larva";264;1
"Unit";"Zergling";"Larva";264;1
"Unit";"Zergling";"Larva";264;1
"Unit";"Zergling";"Larva";264;1
"Unit";"Zergling";"Larva";264;1
"Unit";"Zergling";"Larva";264;1
"Unit";"Zergling";"Larva";264;1
"Unit";"Zergling";"Larva";264;1
"Unit";"Zergling";"Larva";264;1
"Unit";"Zergling";"Larva";264;1
"Unit";"Zergling";"Larva";264;1
"Unit";"Zergling";"Larva";264;1
"Unit";"Zergling";"Larva";264;1
"Unit";"Zergling";"Larva";264;1
"Unit";"Zergling";"Larva";264;1
"Unit";"Zergling";"Larva";264;1
"Unit";"Zergling";"Larva";264;1
"Unit";"Zergling";"Larva";264;1
"Unit";"Zergling";"Larva";264;1
"Unit";"Zergling";"Larva";264;1
"Unit";"Zergling";"Larva";264;1
"Unit";"Zergling";"Larva";264;1
"Unit";"Zergling";"Larva";264;1
"Unit";"Zergling";"Larva";264;1
"Unit";"Zergling";"Larva";264;1
"Unit";"Zergling";"Larva";264;1
"Unit";"Zergling";"Larva";264;1
"Unit";"Zergling";"Larva";264;1
"Unit";"Zergling";"Larva";264;1
"Unit";"Zergling";"Larva";282;1
"Unit";"Zergling";"Larva";282;1
"Unit";"Zergling";"Larva";284;1
"Unit";"Zergling";"Larva";284;1
"Unit";"Zergling";"Larva";284;1
"Unit";"Zergling";"Larva";284;1
"Unit";"Baneling";"Zergling";284;0
"Unit";"Baneling";"Zergling";284;0
"Unit";"Baneling";"Zergling";284;0
"Unit";"Baneling";"Zergling";284;0
"Unit";"Baneling";"Zergling";284;0
"Unit";"Baneling";"Zergling";284;0
"Unit";"Baneling";"Zergling";284;0
"Unit";"Zergling";"Larva";284;1
"Unit";"Zergling";"Larva";284;1
"Building";"CreepTumor";NA;306;0
"Unit";"Baneling";"Zergling";312;0
"Unit";"Baneling";"Zergling";314;0
"Unit";"Baneling";"Zergling";314;0
"Unit";"Baneling";"Zergling";314;0
"Unit";"Baneling";"Zergling";314;0
"Unit";"Baneling";"Zergling";314;0
"Unit";"Baneling";"Zergling";314;0
"Unit";"Baneling";"Zergling";314;0
"Unit";"Baneling";"Zergling";314;0
"Unit";"Baneling";"Zergling";314;0
"Unit";"Baneling";"Zergling";314;0
"Unit";"Baneling";"Zergling";314;0
"Unit";"Baneling";"Zergling";314;0
"Unit";"Baneling";"Zergling";314;0
"Unit";"Zergling";"Larva";314;1
"Unit";"Zergling";"Larva";314;1
"Unit";"Zergling";"Larva";314;1
"Unit";"Zergling";"Larva";314;1
"Unit";"Zergling";"Larva";314;1
"Unit";"Zergling";"Larva";314;1
"Unit";"Zergling";"Larva";314;1
"Unit";"Zergling";"Larva";314;1
"Unit";"Baneling";"Zergling";314;0
"Unit";"Baneling";"Zergling";314;0
"Unit";"Baneling";"Zergling";314;0
"Unit";"Baneling";"Zergling";314;0
"Unit";"Zergling";"Larva";314;1
"Unit";"Zergling";"Larva";314;1
