"type";"unit_name";"on_building";"total_supply";"supply"
"Unit";"Overlord";"Larva";13;0
"Building";"Extractor";NA;17;0
"Unit";"Overlord";"Larva";21;0
"Building";"SpawningPool";NA;19;0
"Building";"Hatchery";NA;17;0
"Unit";"Zergling";"Larva";22;1
"Unit";"Zergling";"Larva";22;1
"Unit";"Zergling";"Larva";23;1
"Unit";"Zergling";"Larva";23;1
"Unit";"Queen";"Hatchery";22;2
"Unit";"Queen";"Hatchery";23;2
"Unit";"Overlord";"Larva";34;0
"Unit";"Overlord";"Larva";37;0
"Building";"Hatchery";NA;27;0
"Building";"Extractor";NA;46;0
"Unit";"Overlord";"Larva";47;0
"Unit";"Queen";"Hatchery";39;2
"Unit";"Queen";"Hatchery";39;2
"Unit";"Zergling";"Larva";50;1
"Unit";"Zergling";"Larva";50;1
"Unit";"Zergling";"Larva";50;1
"Unit";"Zergling";"Larva";50;1
"Unit";"Zergling";"Larva";50;1
"Unit";"Zergling";"Larva";50;1
"Unit";"Zergling";"Larva";50;1
"Unit";"Zergling";"Larva";50;1
"Unit";"Zergling";"Larva";50;1
"Unit";"Zergling";"Larva";50;1
"Unit";"Zergling";"Larva";50;1
"Unit";"Zergling";"Larva";50;1
"Unit";"Zergling";"Larva";50;1
"Unit";"Zergling";"Larva";50;1
"Unit";"Zergling";"Larva";50;1
"Unit";"Zergling";"Larva";50;1
"Unit";"Zergling";"Larva";54;1
"Unit";"Zergling";"Larva";54;1
"Unit";"Queen";"Hatchery";48;2
"Building";"CreepTumorQueen";NA;54;0
"Building";"CreepTumorQueen";NA;64;0
"Unit";"Overlord";"Larva";70;0
"Unit";"Overlord";"Larva";70;0
"Building";"BanelingNest";NA;50;0
"Unit";"Overlord";"Larva";74;0
"Unit";"Zergling";"Larva";74;1
"Unit";"Zergling";"Larva";74;1
"Unit";"Zergling";"Larva";74;1
"Unit";"Zergling";"Larva";74;1
"Unit";"Zergling";"Larva";74;1
"Unit";"Zergling";"Larva";74;1
"Unit";"Baneling";"Zergling";74;0
"Unit";"Baneling";"Zergling";74;0
"Unit";"Baneling";"Zergling";74;0
"Unit";"Baneling";"Zergling";74;0
"Unit";"Zergling";"Larva";74;1
"Unit";"Zergling";"Larva";74;1
"Unit";"Zergling";"Larva";74;1
"Unit";"Zergling";"Larva";74;1
"Unit";"Zergling";"Larva";74;1
"Unit";"Zergling";"Larva";74;1
"Unit";"Zergling";"Larva";74;1
"Unit";"Zergling";"Larva";74;1
"Unit";"Zergling";"Larva";74;1
"Unit";"Zergling";"Larva";74;1
"Unit";"Zergling";"Larva";74;1
"Unit";"Zergling";"Larva";74;1
"Unit";"Baneling";"Zergling";74;0
"Unit";"Overlord";"Larva";74;0
"Building";"CreepTumorQueen";NA;110;0
"Building";"CreepTumor";NA;110;0
"Building";"CreepTumorQueen";NA;110;0
"Building";"Extractor";NA;108;0
"Building";"CreepTumorQueen";NA;110;0
"Unit";"Overlord";"Larva";110;0
"Unit";"Overlord";"Larva";110;0
"Building";"CreepTumorQueen";NA;110;0
"Building";"EvolutionChamber";NA;110;0
"Building";"EvolutionChamber";NA;110;0
"Building";"HydraliskDen";NA;110;0
"Building";"Extractor";NA;110;0
"Building";"Extractor";NA;110;0
"Unit";"Overlord";"Larva";117;0
"Unit";"Overlord";"Larva";117;0
"Unit";"Overlord";"Larva";117;0
"Unit";"Overlord";"Larva";117;0
"Building";"CreepTumor";NA;117;0
"Building";"CreepTumor";NA;117;0
"Building";"CreepTumor";NA;117;0
"Building";"CreepTumor";NA;117;0
"Building";"CreepTumor";NA;117;0
"Unit";"Zergling";"Larva";117;1
"Unit";"Zergling";"Larva";117;1
"Unit";"Queen";"Hatchery";117;2
"Unit";"Queen";"Hatchery";117;2
"Unit";"Zergling";"Larva";117;1
"Unit";"Zergling";"Larva";117;1
"Unit";"Queen";"Hatchery";117;2
"Unit";"Zergling";"Larva";117;1
"Unit";"Zergling";"Larva";117;1
"Unit";"Zergling";"Larva";117;1
"Unit";"Zergling";"Larva";117;1
"Unit";"Zergling";"Larva";117;1
"Unit";"Zergling";"Larva";117;1
"Unit";"Zergling";"Larva";117;1
"Unit";"Zergling";"Larva";117;1
"Unit";"Zergling";"Larva";117;1
"Unit";"Zergling";"Larva";117;1
"Building";"CreepTumorQueen";NA;123;0
"Building";"CreepTumorQueen";NA;125;0
"Unit";"Hydralisk";"Larva";125;2
"Unit";"Hydralisk";"Larva";125;2
"Unit";"Hydralisk";"Larva";125;2
"Unit";"Hydralisk";"Larva";125;2
"Unit";"Hydralisk";"Larva";125;2
"Unit";"Hydralisk";"Larva";125;2
"Unit";"Hydralisk";"Larva";125;2
"Building";"CreepTumorQueen";NA;145;0
"Building";"CreepTumor";NA;145;0
"Building";"CreepTumor";NA;145;0
"Building";"CreepTumor";NA;147;0
"Building";"CreepTumor";NA;147;0
"Building";"CreepTumorQueen";NA;159;0
"Building";"CreepTumor";NA;159;0
"Upgrade";"EvolveGroovedSpines";"HydraliskDen";121;0
"Building";"CreepTumorQueen";NA;159;0
"Building";"CreepTumorQueen";NA;159;0
"Building";"CreepTumorQueen";NA;159;0
"Unit";"Zergling";"Larva";159;1
"Unit";"Zergling";"Larva";159;1
"Unit";"Zergling";"Larva";159;1
"Unit";"Zergling";"Larva";159;1
"Unit";"Zergling";"Larva";159;1
"Unit";"Zergling";"Larva";159;1
"Unit";"Zergling";"Larva";159;1
"Unit";"Zergling";"Larva";159;1
"Unit";"Zergling";"Larva";159;1
"Unit";"Zergling";"Larva";159;1
"Unit";"Zergling";"Larva";159;1
"Unit";"Zergling";"Larva";159;1
"Unit";"Zergling";"Larva";159;1
"Unit";"Zergling";"Larva";159;1
"Unit";"Zergling";"Larva";159;1
"Unit";"Zergling";"Larva";159;1
"Unit";"Zergling";"Larva";159;1
"Unit";"Zergling";"Larva";159;1
"Unit";"Zergling";"Larva";159;1
"Unit";"Zergling";"Larva";159;1
"Unit";"Zergling";"Larva";159;1
"Unit";"Zergling";"Larva";159;1
"Unit";"Hydralisk";"Larva";159;2
"Unit";"Hydralisk";"Larva";159;2
"Unit";"Hydralisk";"Larva";159;2
"Unit";"Hydralisk";"Larva";159;2
"Building";"CreepTumor";NA;181;0
"Building";"CreepTumor";NA;181;0
"Building";"CreepTumor";NA;183;0
"Building";"CreepTumor";NA;183;0
"Building";"InfestationPit";NA;159;0
"Building";"CreepTumorQueen";NA;191;0
"Building";"CreepTumor";NA;191;0
"Building";"CreepTumor";NA;191;0
"Building";"CreepTumor";NA;191;0
"Building";"CreepTumorQueen";NA;191;0
"Building";"CreepTumor";NA;191;0
"Building";"CreepTumorQueen";NA;192;0
"Building";"CreepTumor";NA;191;0
"Building";"CreepTumor";NA;191;0
"Building";"CreepTumorQueen";NA;192;0
"Upgrade";"ZergMeleeWeaponsLevel1";"EvolutionChamber";124;0
"Upgrade";"ZergGroundArmorsLevel1";"EvolutionChamber";125;0
"Building";"CreepTumorQueen";NA;192;0
"Unit";"Zergling";"Larva";192;1
"Unit";"Zergling";"Larva";192;1
"Unit";"Overlord";"Larva";192;0
"Unit";"Overlord";"Larva";192;0
"Unit";"Overlord";"Larva";192;0
"Unit";"Overlord";"Larva";192;0
"Unit";"Overlord";"Larva";192;0
"Unit";"Overlord";"Larva";192;0
"Building";"CreepTumorQueen";NA;194;0
"Building";"CreepTumor";NA;194;0
"Building";"CreepTumor";NA;194;0
"Building";"CreepTumorQueen";NA;194;0
"Building";"CreepTumorQueen";NA;194;0
"Building";"CreepTumorQueen";NA;194;0
"Building";"CreepTumor";NA;194;0
"Building";"CreepTumor";NA;194;0
"Building";"CreepTumor";NA;194;0
"Building";"CreepTumor";NA;194;0
"Building";"CreepTumor";NA;194;0
"Building";"CreepTumorQueen";NA;194;0
"Building";"CreepTumorQueen";NA;194;0
"Building";"CreepTumor";NA;194;0
"Building";"CreepTumor";NA;194;0
"Building";"CreepTumor";NA;194;0
"Building";"CreepTumor";NA;194;0
"Building";"Hatchery";NA;159;0
"Building";"CreepTumor";NA;194;0
"Building";"CreepTumor";NA;194;0
"Building";"CreepTumor";NA;194;0
"Building";"CreepTumorQueen";NA;194;0
"Building";"LurkerDenMP";NA;159;0
"Unit";"Baneling";"Zergling";194;0
"Unit";"Baneling";"Zergling";194;0
"Unit";"Baneling";"Zergling";194;0
"Unit";"Baneling";"Zergling";194;0
"Unit";"Baneling";"Zergling";194;0
"Unit";"Baneling";"Zergling";194;0
"Unit";"Baneling";"Zergling";194;0
"Unit";"Baneling";"Zergling";194;0
"Unit";"Baneling";"Zergling";194;0
"Unit";"Baneling";"Zergling";194;0
"Unit";"Baneling";"Zergling";194;0
"Unit";"Baneling";"Zergling";194;0
"Unit";"Baneling";"Zergling";194;0
"Unit";"Baneling";"Zergling";194;0
"Unit";"Baneling";"Zergling";194;0
"Unit";"Baneling";"Zergling";194;0
"Unit";"Zergling";"Larva";194;1
"Unit";"Zergling";"Larva";194;1
"Unit";"Zergling";"Larva";194;1
"Unit";"Zergling";"Larva";194;1
"Unit";"Zergling";"Larva";194;1
"Unit";"Zergling";"Larva";194;1
"Unit";"Zergling";"Larva";194;1
"Unit";"Zergling";"Larva";194;1
"Unit";"Zergling";"Larva";194;1
"Unit";"Zergling";"Larva";194;1
"Unit";"Zergling";"Larva";194;1
"Unit";"Zergling";"Larva";194;1
"Unit";"Zergling";"Larva";194;1
"Unit";"Zergling";"Larva";194;1
"Unit";"Zergling";"Larva";194;1
"Unit";"Zergling";"Larva";194;1
"Unit";"Zergling";"Larva";194;1
"Unit";"Zergling";"Larva";194;1
"Unit";"Zergling";"Larva";194;1
"Unit";"Zergling";"Larva";194;1
"Unit";"Zergling";"Larva";194;1
"Unit";"Zergling";"Larva";194;1
"Unit";"Zergling";"Larva";194;1
"Unit";"Zergling";"Larva";194;1
"Unit";"Zergling";"Larva";194;1
"Unit";"Zergling";"Larva";194;1
"Unit";"Zergling";"Larva";194;1
"Unit";"Zergling";"Larva";194;1
"Unit";"Zergling";"Larva";194;1
"Unit";"Zergling";"Larva";194;1
"Unit";"Zergling";"Larva";194;1
"Unit";"Zergling";"Larva";194;1
"Unit";"Zergling";"Larva";194;1
"Unit";"Zergling";"Larva";194;1
"Unit";"Zergling";"Larva";194;1
"Unit";"Zergling";"Larva";194;1
"Unit";"Zergling";"Larva";194;1
"Unit";"Zergling";"Larva";194;1
"Upgrade";"EvolveMuscularAugments";"HydraliskDen";194;0
"Building";"CreepTumor";NA;233;0
"Building";"CreepTumor";NA;234;0
"Building";"CreepTumorQueen";NA;237;0
"Building";"CreepTumor";NA;235;0
"Building";"CreepTumorQueen";NA;237;0
"Building";"CreepTumorQueen";NA;237;0
"Building";"CreepTumorQueen";NA;237;0
"Unit";"Zergling";"Larva";237;1
"Unit";"Zergling";"Larva";237;1
"Unit";"Zergling";"Larva";237;1
"Unit";"Zergling";"Larva";237;1
"Unit";"Zergling";"Larva";237;1
"Unit";"Zergling";"Larva";237;1
"Unit";"Zergling";"Larva";237;1
"Unit";"Zergling";"Larva";237;1
"Unit";"Zergling";"Larva";237;1
"Unit";"Zergling";"Larva";237;1
"Unit";"Zergling";"Larva";237;1
"Unit";"Zergling";"Larva";237;1
"Unit";"Zergling";"Larva";237;1
"Unit";"Zergling";"Larva";237;1
"Unit";"Zergling";"Larva";237;1
"Unit";"Zergling";"Larva";237;1
"Unit";"Zergling";"Larva";237;1
"Unit";"Zergling";"Larva";237;1
"Unit";"Zergling";"Larva";237;1
"Unit";"Zergling";"Larva";237;1
"Unit";"Zergling";"Larva";237;1
"Unit";"Zergling";"Larva";237;1
"Unit";"Zergling";"Larva";237;1
"Unit";"Zergling";"Larva";237;1
"Unit";"Zergling";"Larva";237;1
"Unit";"Zergling";"Larva";237;1
"Unit";"Zergling";"Larva";237;1
"Unit";"Zergling";"Larva";237;1
"Unit";"Zergling";"Larva";237;1
"Unit";"Zergling";"Larva";237;1
"Unit";"Hydralisk";"Larva";237;2
"Unit";"Hydralisk";"Larva";237;2
"Unit";"Hydralisk";"Larva";237;2
"Unit";"Hydralisk";"Larva";237;2
"Unit";"Hydralisk";"Larva";237;2
"Unit";"Hydralisk";"Larva";237;2
"Unit";"Hydralisk";"Larva";237;2
"Unit";"Hydralisk";"Larva";237;2
"Unit";"Hydralisk";"Larva";237;2
"Unit";"Zergling";"Larva";237;1
"Unit";"Zergling";"Larva";237;1
"Unit";"Zergling";"Larva";237;1
"Unit";"Zergling";"Larva";237;1
"Upgrade";"ZergMeleeWeaponsLevel2";"EvolutionChamber";194;0
"Upgrade";"ZergGroundArmorsLevel2";"EvolutionChamber";194;0
"Unit";"Baneling";"Zergling";269;0
"Unit";"Baneling";"Zergling";271;0
"Unit";"Baneling";"Zergling";275;0
"Unit";"Baneling";"Zergling";275;0
"Unit";"Baneling";"Zergling";281;0
"Unit";"Baneling";"Zergling";281;0
"Unit";"Baneling";"Zergling";283;0
"Unit";"Baneling";"Zergling";283;0
"Unit";"Baneling";"Zergling";285;0
"Unit";"Baneling";"Zergling";285;0
"Unit";"Baneling";"Zergling";285;0
"Unit";"Baneling";"Zergling";285;0
"Unit";"Baneling";"Zergling";285;0
"Unit";"Baneling";"Zergling";285;0
"Unit";"Baneling";"Zergling";285;0
"Building";"CreepTumor";NA;285;0
"Building";"UltraliskCavern";NA;237;0
"Building";"CreepTumor";NA;299;0
"Building";"CreepTumor";NA;299;0
"Building";"Extractor";NA;267;0
"Building";"CreepTumor";NA;299;0
"Building";"CreepTumor";NA;299;0
"Building";"CreepTumor";NA;299;0
"Building";"CreepTumor";NA;299;0
"Building";"CreepTumor";NA;299;0
"Building";"CreepTumor";NA;299;0
"Building";"CreepTumor";NA;299;0
"Building";"CreepTumor";NA;299;0
"Building";"CreepTumor";NA;299;0
"Building";"CreepTumorQueen";NA;299;0
"Building";"CreepTumorQueen";NA;299;0
"Building";"CreepTumorQueen";NA;299;0
"Building";"CreepTumorQueen";NA;299;0
"Unit";"Zergling";"Larva";299;1
"Unit";"Zergling";"Larva";299;1
"Unit";"Zergling";"Larva";299;1
"Unit";"Zergling";"Larva";299;1
"Unit";"Zergling";"Larva";299;1
"Unit";"Zergling";"Larva";299;1
"Unit";"Zergling";"Larva";299;1
"Unit";"Zergling";"Larva";299;1
"Unit";"Zergling";"Larva";299;1
"Unit";"Zergling";"Larva";299;1
"Unit";"Zergling";"Larva";299;1
"Unit";"Zergling";"Larva";299;1
"Unit";"Zergling";"Larva";299;1
"Unit";"Zergling";"Larva";299;1
"Unit";"Zergling";"Larva";299;1
"Unit";"Zergling";"Larva";299;1
"Unit";"Zergling";"Larva";299;1
"Unit";"Zergling";"Larva";299;1
"Unit";"Zergling";"Larva";299;1
"Unit";"Zergling";"Larva";299;1
"Unit";"Zergling";"Larva";299;1
"Unit";"Zergling";"Larva";299;1
"Unit";"Zergling";"Larva";299;1
"Unit";"Zergling";"Larva";299;1
"Unit";"Zergling";"Larva";299;1
"Unit";"Zergling";"Larva";299;1
"Unit";"Zergling";"Larva";299;1
"Unit";"Zergling";"Larva";299;1
"Unit";"Zergling";"Larva";299;1
"Unit";"Zergling";"Larva";299;1
"Unit";"Zergling";"Larva";299;1
"Unit";"Zergling";"Larva";299;1
"Unit";"Zergling";"Larva";299;1
"Unit";"Zergling";"Larva";299;1
"Unit";"Zergling";"Larva";299;1
"Unit";"Zergling";"Larva";299;1
"Unit";"Zergling";"Larva";299;1
"Unit";"Zergling";"Larva";299;1
"Unit";"Zergling";"Larva";299;1
"Unit";"Zergling";"Larva";299;1
"Unit";"Zergling";"Larva";299;1
"Unit";"Zergling";"Larva";299;1
"Unit";"Zergling";"Larva";299;1
"Unit";"Zergling";"Larva";299;1
"Building";"Extractor";NA;299;0
"Unit";"Zergling";"Larva";343;1
"Unit";"Zergling";"Larva";343;1
"Building";"CreepTumor";NA;343;0
"Building";"CreepTumor";NA;343;0
"Unit";"Zergling";"Larva";343;1
"Unit";"Zergling";"Larva";343;1
"Unit";"Zergling";"Larva";343;1
"Unit";"Zergling";"Larva";343;1
"Unit";"Zergling";"Larva";343;1
"Unit";"Zergling";"Larva";343;1
"Unit";"Zergling";"Larva";343;1
"Unit";"Zergling";"Larva";343;1
"Unit";"Zergling";"Larva";343;1
"Unit";"Zergling";"Larva";343;1
"Building";"CreepTumorQueen";NA;343;0
"Building";"CreepTumorQueen";NA;343;0
"Building";"CreepTumorQueen";NA;355;0
"Building";"CreepTumorQueen";NA;355;0
"Building";"CreepTumor";NA;355;0
"Building";"CreepTumor";NA;355;0
"Building";"CreepTumor";NA;355;0
"Building";"CreepTumor";NA;355;0
"Building";"CreepTumor";NA;355;0
"Building";"CreepTumor";NA;355;0
"Building";"CreepTumor";NA;355;0
"Building";"CreepTumor";NA;355;0
"Building";"CreepTumor";NA;355;0
"Building";"CreepTumor";NA;355;0
"Building";"CreepTumor";NA;355;0
"Unit";"Overlord";"Larva";355;0
"Unit";"Overlord";"Larva";355;0
"Unit";"Overlord";"Larva";355;0
"Unit";"Zergling";"Larva";355;1
"Unit";"Zergling";"Larva";355;1
"Unit";"Zergling";"Larva";355;1
"Unit";"Zergling";"Larva";355;1
"Unit";"Zergling";"Larva";355;1
"Unit";"Zergling";"Larva";355;1
"Unit";"Zergling";"Larva";355;1
"Unit";"Zergling";"Larva";355;1
"Unit";"Zergling";"Larva";355;1
"Unit";"Zergling";"Larva";355;1
"Unit";"Zergling";"Larva";355;1
"Unit";"Zergling";"Larva";355;1
"Unit";"Zergling";"Larva";355;1
"Unit";"Zergling";"Larva";355;1
"Unit";"Zergling";"Larva";355;1
"Unit";"Zergling";"Larva";355;1
"Unit";"Zergling";"Larva";355;1
"Unit";"Zergling";"Larva";355;1
"Unit";"Zergling";"Larva";355;1
"Unit";"Zergling";"Larva";355;1
"Unit";"Zergling";"Larva";355;1
"Unit";"Zergling";"Larva";355;1
"Unit";"Zergling";"Larva";355;1
"Unit";"Zergling";"Larva";355;1
"Unit";"Zergling";"Larva";355;1
"Unit";"Zergling";"Larva";355;1
"Upgrade";"ChitinousPlating";"UltraliskCavern";343;0
"Building";"CreepTumor";NA;355;0
"Building";"CreepTumor";NA;355;0
"Building";"CreepTumor";NA;355;0
"Building";"CreepTumor";NA;355;0
"Unit";"Ultralisk";"Larva";355;6
"Unit";"Ultralisk";"Larva";355;6
"Unit";"Ultralisk";"Larva";355;6
"Building";"CreepTumor";NA;381;0
"Building";"CreepTumor";NA;399;0
"Building";"CreepTumorQueen";NA;399;0
"Building";"CreepTumor";NA;393;0
"Building";"CreepTumorQueen";NA;399;0
"Building";"CreepTumorQueen";NA;399;0
"Building";"CreepTumorQueen";NA;399;0
"Building";"CreepTumorQueen";NA;399;0
"Unit";"Queen";"Hatchery";381;2
"Unit";"Overlord";"Larva";399;0
"Unit";"Overlord";"Larva";399;0
"Unit";"Hydralisk";"Larva";401;2
"Unit";"Hydralisk";"Larva";401;2
"Building";"CreepTumor";NA;410;0
"Building";"CreepTumor";NA;410;0
"Building";"CreepTumor";NA;410;0
"Building";"CreepTumor";NA;410;0
"Building";"CreepTumor";NA;410;0
"Building";"CreepTumor";NA;410;0
"Building";"CreepTumor";NA;410;0
"Building";"CreepTumor";NA;410;0
"Building";"CreepTumor";NA;410;0
"Building";"CreepTumor";NA;410;0
"Building";"CreepTumor";NA;410;0
"Building";"CreepTumor";NA;410;0
"Building";"CreepTumor";NA;410;0
"Building";"CreepTumor";NA;410;0
"Building";"CreepTumor";NA;410;0
"Building";"CreepTumor";NA;410;0
"Building";"CreepTumor";NA;410;0
"Unit";"Hydralisk";"Larva";410;2
"Building";"CreepTumor";NA;410;0
"Unit";"Hydralisk";"Larva";410;2
"Unit";"Hydralisk";"Larva";410;2
"Unit";"Hydralisk";"Larva";410;2
"Unit";"Ultralisk";"Larva";401;6
"Unit";"Ultralisk";"Larva";401;6
"Unit";"Ultralisk";"Larva";401;6
"Unit";"Ultralisk";"Larva";401;6
"Upgrade";"ZergMeleeWeaponsLevel3";"EvolutionChamber";355;0
"Building";"CreepTumor";NA;422;0
"Building";"Extractor";NA;414;0
"Building";"CreepTumor";NA;422;0
"Building";"CreepTumor";NA;422;0
"Unit";"Hydralisk";"Larva";414;2
"Unit";"Hydralisk";"Larva";414;2
"Unit";"Hydralisk";"Larva";414;2
"Unit";"Hydralisk";"Larva";414;2
"Unit";"Hydralisk";"Larva";414;2
"Unit";"Hydralisk";"Larva";414;2
"Unit";"Hydralisk";"Larva";414;2
"Unit";"Baneling";"Zergling";446;0
"Unit";"Baneling";"Zergling";446;0
"Unit";"Baneling";"Zergling";446;0
"Unit";"Baneling";"Zergling";446;0
"Unit";"Baneling";"Zergling";446;0
"Unit";"Baneling";"Zergling";446;0
"Unit";"Baneling";"Zergling";446;0
"Unit";"Baneling";"Zergling";446;0
"Unit";"Baneling";"Zergling";446;0
"Unit";"Baneling";"Zergling";446;0
"Unit";"Baneling";"Zergling";446;0
"Unit";"Baneling";"Zergling";446;0
"Unit";"Baneling";"Zergling";446;0
"Building";"Hatchery";NA;399;0
"Upgrade";"ZergGroundArmorsLevel3";"EvolutionChamber";381;0
"Unit";"Zergling";"Larva";460;1
"Unit";"Zergling";"Larva";460;1
"Unit";"Zergling";"Larva";460;1
"Unit";"Zergling";"Larva";460;1
"Unit";"Zergling";"Larva";460;1
"Unit";"Zergling";"Larva";460;1
"Unit";"Zergling";"Larva";460;1
"Unit";"Zergling";"Larva";460;1
"Unit";"Zergling";"Larva";460;1
"Unit";"Zergling";"Larva";460;1
"Unit";"Zergling";"Larva";460;1
"Unit";"Zergling";"Larva";460;1
"Unit";"Zergling";"Larva";460;1
"Unit";"Zergling";"Larva";460;1
"Unit";"Zergling";"Larva";460;1
"Unit";"Zergling";"Larva";460;1
"Unit";"Zergling";"Larva";460;1
"Unit";"Zergling";"Larva";460;1
"Unit";"Zergling";"Larva";460;1
"Unit";"Zergling";"Larva";460;1
"Unit";"Zergling";"Larva";460;1
"Unit";"Zergling";"Larva";460;1
"Unit";"Zergling";"Larva";460;1
"Unit";"Zergling";"Larva";460;1
"Unit";"Zergling";"Larva";460;1
"Unit";"Zergling";"Larva";460;1
"Unit";"Zergling";"Larva";460;1
"Unit";"Zergling";"Larva";460;1
"Unit";"Zergling";"Larva";460;1
"Unit";"Zergling";"Larva";460;1
"Unit";"Zergling";"Larva";460;1
"Unit";"Zergling";"Larva";460;1
"Unit";"Zergling";"Larva";460;1
"Unit";"Zergling";"Larva";460;1
"Unit";"Zergling";"Larva";460;1
"Unit";"Zergling";"Larva";460;1
"Unit";"Zergling";"Larva";460;1
"Unit";"Zergling";"Larva";460;1
"Unit";"Zergling";"Larva";460;1
"Unit";"Zergling";"Larva";460;1
"Unit";"Zergling";"Larva";460;1
"Unit";"Zergling";"Larva";460;1
"Unit";"Zergling";"Larva";460;1
"Unit";"Zergling";"Larva";460;1
"Unit";"Zergling";"Larva";460;1
"Unit";"Zergling";"Larva";460;1
"Unit";"Hydralisk";"Larva";460;2
"Unit";"Hydralisk";"Larva";460;2
"Unit";"Hydralisk";"Larva";460;2
"Unit";"Hydralisk";"Larva";460;2
"Unit";"Hydralisk";"Larva";460;2
"Unit";"Hydralisk";"Larva";460;2
"Unit";"Hydralisk";"Larva";460;2
"Unit";"Hydralisk";"Larva";460;2
"Unit";"Hydralisk";"Larva";460;2
"Unit";"Zergling";"Larva";460;1
"Unit";"Zergling";"Larva";460;1
"Unit";"Zergling";"Larva";460;1
"Unit";"Zergling";"Larva";460;1
"Unit";"Zergling";"Larva";460;1
"Unit";"Zergling";"Larva";460;1
"Unit";"Zergling";"Larva";460;1
"Unit";"Zergling";"Larva";460;1
"Unit";"Zergling";"Larva";460;1
"Unit";"Zergling";"Larva";460;1
"Unit";"Zergling";"Larva";460;1
"Unit";"Zergling";"Larva";460;1
"Building";"CreepTumor";NA;460;0
"Building";"CreepTumor";NA;460;0
"Building";"CreepTumor";NA;460;0
"Unit";"Zergling";"Larva";460;1
"Unit";"Zergling";"Larva";460;1
"Building";"CreepTumor";NA;460;0
"Building";"CreepTumor";NA;460;0
"Building";"CreepTumor";NA;460;0
"Unit";"Zergling";"Larva";460;1
"Unit";"Zergling";"Larva";460;1
"Building";"CreepTumor";NA;460;0
"Building";"CreepTumor";NA;460;0
"Building";"CreepTumor";NA;462;0
"Unit";"Ultralisk";"Larva";460;6
"Unit";"Ultralisk";"Larva";460;6
"Unit";"Baneling";"Zergling";540;0
"Unit";"Baneling";"Zergling";540;0
"Unit";"Baneling";"Zergling";540;0
"Unit";"Baneling";"Zergling";540;0
"Unit";"Baneling";"Zergling";540;0
"Unit";"Baneling";"Zergling";540;0
"Unit";"Baneling";"Zergling";540;0
"Unit";"Baneling";"Zergling";540;0
"Unit";"Baneling";"Zergling";540;0
"Unit";"Baneling";"Zergling";540;0
"Unit";"Baneling";"Zergling";540;0
"Unit";"Baneling";"Zergling";540;0
"Unit";"Baneling";"Zergling";540;0
"Unit";"Baneling";"Zergling";540;0
"Unit";"Baneling";"Zergling";540;0
"Unit";"Baneling";"Zergling";540;0
"Unit";"Baneling";"Zergling";540;0
"Unit";"Baneling";"Zergling";540;0
"Unit";"Baneling";"Zergling";540;0
"Unit";"Baneling";"Zergling";540;0
"Unit";"Baneling";"Zergling";540;0
"Unit";"Baneling";"Zergling";540;0
"Unit";"Baneling";"Zergling";540;0
"Building";"CreepTumorQueen";NA;552;0
"Unit";"Baneling";"Zergling";540;0
"Building";"CreepTumorQueen";NA;552;0
"Building";"CreepTumorQueen";NA;552;0
"Unit";"Baneling";"Zergling";540;0
"Building";"CreepTumor";NA;552;0
"Building";"CreepTumor";NA;552;0
"Building";"CreepTumor";NA;552;0
"Building";"CreepTumor";NA;552;0
"Building";"CreepTumor";NA;552;0
"Building";"CreepTumor";NA;552;0
"Building";"CreepTumor";NA;552;0
"Building";"CreepTumor";NA;552;0
"Building";"CreepTumor";NA;552;0
"Building";"CreepTumor";NA;552;0
"Building";"CreepTumor";NA;552;0
"Building";"CreepTumor";NA;552;0
"Building";"CreepTumor";NA;552;0
"Building";"CreepTumorQueen";NA;552;0
"Building";"CreepTumorQueen";NA;552;0
"Building";"CreepTumorQueen";NA;552;0
"Building";"CreepTumorQueen";NA;552;0
"Building";"CreepTumorQueen";NA;552;0
"Building";"CreepTumorQueen";NA;552;0
"Building";"Spire";NA;552;0
"Unit";"Zergling";"Larva";552;1
"Unit";"Zergling";"Larva";552;1
"Unit";"Zergling";"Larva";552;1
"Unit";"Zergling";"Larva";552;1
"Unit";"Zergling";"Larva";552;1
"Unit";"Zergling";"Larva";552;1
"Unit";"Zergling";"Larva";552;1
"Unit";"Zergling";"Larva";552;1
"Unit";"Zergling";"Larva";552;1
"Unit";"Zergling";"Larva";552;1
"Unit";"Zergling";"Larva";552;1
"Unit";"Zergling";"Larva";552;1
"Unit";"Zergling";"Larva";552;1
"Unit";"Zergling";"Larva";552;1
"Unit";"Zergling";"Larva";552;1
"Unit";"Zergling";"Larva";552;1
"Unit";"Zergling";"Larva";552;1
"Unit";"Zergling";"Larva";552;1
"Unit";"Zergling";"Larva";552;1
"Unit";"Zergling";"Larva";552;1
"Unit";"Zergling";"Larva";552;1
"Unit";"Zergling";"Larva";552;1
"Unit";"Zergling";"Larva";552;1
"Unit";"Zergling";"Larva";552;1
"Unit";"Zergling";"Larva";552;1
"Unit";"Zergling";"Larva";552;1
"Unit";"Zergling";"Larva";552;1
"Unit";"Zergling";"Larva";552;1
"Unit";"Zergling";"Larva";552;1
"Unit";"Zergling";"Larva";552;1
"Unit";"Zergling";"Larva";552;1
"Unit";"Zergling";"Larva";552;1
"Unit";"Zergling";"Larva";552;1
"Unit";"Zergling";"Larva";552;1
"Unit";"Zergling";"Larva";552;1
"Unit";"Zergling";"Larva";552;1
"Unit";"Zergling";"Larva";552;1
"Unit";"Zergling";"Larva";552;1
"Unit";"Zergling";"Larva";552;1
"Unit";"Zergling";"Larva";552;1
"Unit";"Zergling";"Larva";552;1
"Unit";"Zergling";"Larva";552;1
"Unit";"Zergling";"Larva";552;1
"Unit";"Zergling";"Larva";552;1
"Unit";"Zergling";"Larva";552;1
"Unit";"Zergling";"Larva";552;1
"Unit";"Zergling";"Larva";552;1
"Unit";"Zergling";"Larva";552;1
"Unit";"Zergling";"Larva";552;1
"Unit";"Zergling";"Larva";552;1
"Unit";"Zergling";"Larva";552;1
"Unit";"Zergling";"Larva";552;1
"Unit";"Zergling";"Larva";552;1
"Unit";"Zergling";"Larva";552;1
"Unit";"Zergling";"Larva";552;1
"Unit";"Zergling";"Larva";552;1
"Unit";"Zergling";"Larva";552;1
"Unit";"Zergling";"Larva";552;1
"Unit";"Zergling";"Larva";552;1
"Unit";"Zergling";"Larva";552;1
"Unit";"Zergling";"Larva";552;1
"Unit";"Zergling";"Larva";552;1
"Unit";"Zergling";"Larva";552;1
"Unit";"Zergling";"Larva";552;1
"Unit";"Zergling";"Larva";552;1
"Unit";"Zergling";"Larva";552;1
"Unit";"Zergling";"Larva";552;1
"Unit";"Zergling";"Larva";552;1
"Unit";"Zergling";"Larva";552;1
"Unit";"Zergling";"Larva";552;1
"Unit";"Hydralisk";"Larva";552;2
"Unit";"Hydralisk";"Larva";552;2
"Unit";"Hydralisk";"Larva";552;2
"Unit";"Hydralisk";"Larva";552;2
"Unit";"Hydralisk";"Larva";552;2
"Unit";"Hydralisk";"Larva";552;2
"Unit";"Hydralisk";"Larva";552;2
"Unit";"Hydralisk";"Larva";552;2
"Building";"CreepTumor";NA;552;0
"Building";"CreepTumor";NA;552;0
"Building";"CreepTumor";NA;552;0
"Building";"CreepTumor";NA;552;0
"Building";"CreepTumor";NA;552;0
"Building";"CreepTumor";NA;622;0
"Building";"CreepTumor";NA;622;0
"Building";"CreepTumor";NA;622;0
"Building";"CreepTumor";NA;622;0
"Building";"CreepTumor";NA;622;0
"Building";"CreepTumor";NA;622;0
"Building";"CreepTumor";NA;638;0
"Building";"CreepTumor";NA;638;0
"Unit";"Baneling";"Zergling";638;0
"Unit";"Baneling";"Zergling";638;0
"Unit";"Baneling";"Zergling";638;0
"Unit";"Baneling";"Zergling";638;0
"Unit";"Baneling";"Zergling";638;0
"Unit";"Baneling";"Zergling";638;0
"Unit";"Baneling";"Zergling";638;0
"Unit";"Baneling";"Zergling";638;0
"Unit";"Baneling";"Zergling";638;0
"Unit";"Baneling";"Zergling";638;0
"Unit";"Baneling";"Zergling";638;0
"Unit";"Baneling";"Zergling";638;0
"Unit";"Baneling";"Zergling";638;0
"Unit";"Baneling";"Zergling";638;0
"Unit";"Baneling";"Zergling";638;0
"Unit";"Baneling";"Zergling";638;0
"Unit";"Baneling";"Zergling";638;0
"Unit";"Baneling";"Zergling";638;0
"Unit";"Baneling";"Zergling";638;0
"Unit";"Baneling";"Zergling";638;0
"Unit";"Baneling";"Zergling";638;0
"Unit";"Baneling";"Zergling";638;0
"Unit";"Baneling";"Zergling";638;0
"Unit";"Baneling";"Zergling";638;0
"Unit";"Baneling";"Zergling";638;0
"Unit";"Baneling";"Zergling";638;0
"Unit";"Baneling";"Zergling";638;0
"Unit";"Baneling";"Zergling";638;0
"Unit";"Baneling";"Zergling";638;0
"Unit";"Baneling";"Zergling";638;0
"Unit";"Baneling";"Zergling";638;0
"Unit";"Baneling";"Zergling";638;0
"Unit";"Baneling";"Zergling";638;0
"Unit";"Baneling";"Zergling";638;0
"Unit";"Baneling";"Zergling";638;0
"Unit";"Baneling";"Zergling";638;0
"Unit";"Baneling";"Zergling";638;0
"Unit";"Baneling";"Zergling";638;0
"Unit";"Baneling";"Zergling";638;0
"Unit";"Baneling";"Zergling";638;0
"Building";"Extractor";NA;638;0
"Building";"CreepTumor";NA;638;0
"Building";"CreepTumor";NA;638;0
"Building";"CreepTumor";NA;638;0
"Building";"CreepTumor";NA;638;0
"Building";"CreepTumor";NA;638;0
"Building";"CreepTumor";NA;638;0
"Building";"CreepTumor";NA;638;0
"Building";"CreepTumor";NA;638;0
"Building";"CreepTumor";NA;638;0
"Building";"CreepTumor";NA;638;0
"Building";"CreepTumor";NA;638;0
"Building";"CreepTumor";NA;638;0
"Building";"CreepTumor";NA;638;0
"Unit";"Hydralisk";"Larva";638;2
"Unit";"Hydralisk";"Larva";638;2
"Unit";"Hydralisk";"Larva";638;2
"Unit";"Hydralisk";"Larva";638;2
"Unit";"Hydralisk";"Larva";638;2
"Unit";"Hydralisk";"Larva";638;2
"Unit";"Hydralisk";"Larva";638;2
"Unit";"Hydralisk";"Larva";638;2
"Unit";"Hydralisk";"Larva";638;2
"Unit";"Hydralisk";"Larva";638;2
"Unit";"Hydralisk";"Larva";638;2
"Unit";"Hydralisk";"Larva";638;2
"Unit";"Hydralisk";"Larva";638;2
"Unit";"Zergling";"Larva";638;1
"Unit";"Zergling";"Larva";638;1
"Unit";"Hydralisk";"Larva";638;2
"Unit";"Zergling";"Larva";638;1
"Unit";"Zergling";"Larva";638;1
"Unit";"Zergling";"Larva";638;1
"Unit";"Zergling";"Larva";638;1
"Unit";"Zergling";"Larva";638;1
"Unit";"Zergling";"Larva";638;1
"Unit";"Zergling";"Larva";638;1
"Unit";"Zergling";"Larva";638;1
"Unit";"Zergling";"Larva";638;1
"Unit";"Zergling";"Larva";638;1
"Unit";"Zergling";"Larva";638;1
"Unit";"Zergling";"Larva";638;1
"Unit";"Zergling";"Larva";638;1
"Unit";"Zergling";"Larva";638;1
"Unit";"Zergling";"Larva";638;1
"Unit";"Zergling";"Larva";638;1
"Unit";"Zergling";"Larva";638;1
"Unit";"Zergling";"Larva";638;1
"Building";"CreepTumor";NA;638;0
"Building";"CreepTumor";NA;638;0
"Building";"CreepTumor";NA;668;0
"Building";"CreepTumor";NA;668;0
"Building";"CreepTumor";NA;674;0
"Building";"CreepTumor";NA;678;0
"Building";"CreepTumor";NA;678;0
"Building";"CreepTumorQueen";NA;686;0
"Building";"CreepTumorQueen";NA;686;0
"Building";"CreepTumor";NA;686;0
"Building";"CreepTumor";NA;686;0
"Building";"CreepTumor";NA;686;0
"Building";"CreepTumor";NA;686;0
"Building";"CreepTumor";NA;686;0
"Building";"CreepTumor";NA;686;0
"Upgrade";"ZergMissileWeaponsLevel1";"EvolutionChamber";638;0
"Building";"CreepTumorQueen";NA;686;0
"Building";"CreepTumorQueen";NA;686;0
"Building";"CreepTumorQueen";NA;686;0
"Building";"CreepTumorQueen";NA;686;0
"Building";"CreepTumorQueen";NA;686;0
"Building";"CreepTumorQueen";NA;686;0
"Building";"CreepTumorQueen";NA;686;0
"Building";"Hatchery";NA;686;0
"Building";"CreepTumorQueen";NA;686;0
"Building";"CreepTumorQueen";NA;686;0
"Building";"CreepTumorQueen";NA;686;0
"Building";"CreepTumorQueen";NA;686;0
"Building";"CreepTumorQueen";NA;686;0
"Building";"CreepTumorQueen";NA;686;0
"Building";"CreepTumorQueen";NA;686;0
"Building";"CreepTumorQueen";NA;686;0
"Building";"CreepTumorQueen";NA;686;0
