"type";"unit_name";"on_building";"total_supply";"supply"
"Unit";"Overlord";"Larva";12;0
"Building";"SpawningPool";NA;17;0
"Building";"Extractor";NA;18;0
"Unit";"Zergling";"Larva";21;1
"Unit";"Zergling";"Larva";21;1
"Unit";"Zergling";"Larva";21;1
"Unit";"Zergling";"Larva";21;1
"Unit";"Overlord";"Larva";21;0
"Unit";"Queen";"Hatchery";21;2
"Building";"Hatchery";NA;18;0
"Unit";"Queen";"Hatchery";25;2
"Unit";"Overlord";"Larva";35;0
"Unit";"Queen";"Hatchery";31;2
"Building";"CreepTumorQueen";NA;41;0
"Building";"CreepTumorQueen";NA;42;0
"Unit";"Queen";"Hatchery";39;2
"Unit";"Overlord";"Larva";46;0
"Building";"CreepTumorQueen";NA;50;0
"Unit";"Overlord";"Larva";50;0
"Building";"CreepTumor";NA;50;0
"Building";"CreepTumorQueen";NA;50;0
"Building";"CreepTumor";NA;50;0
"Unit";"Overlord";"Larva";50;0
"Unit";"Zergling";"Larva";51;1
"Unit";"Zergling";"Larva";51;1
"Unit";"Zergling";"Larva";56;1
"Unit";"Zergling";"Larva";56;1
"Unit";"Zergling";"Larva";56;1
"Unit";"Zergling";"Larva";56;1
"Unit";"Queen";"Hatchery";50;2
"Unit";"Zergling";"Larva";56;1
"Unit";"Zergling";"Larva";56;1
"Building";"Hatchery";NA;46;0
"Unit";"Zergling";"Larva";58;1
"Unit";"Zergling";"Larva";58;1
"Unit";"Zergling";"Larva";58;1
"Unit";"Zergling";"Larva";58;1
"Building";"RoachWarren";NA;50;0
"Unit";"Overlord";"Larva";58;0
"Building";"Extractor";NA;56;0
"Building";"CreepTumor";NA;67;0
"Building";"CreepTumor";NA;67;0
"Unit";"Overlord";"Larva";67;0
"Unit";"Overlord";"Larva";67;0
"Unit";"Roach";"Larva";71;2
"Unit";"Roach";"Larva";71;2
"Unit";"Roach";"Larva";71;2
"Unit";"Roach";"Larva";71;2
"Unit";"Roach";"Larva";71;2
"Unit";"Queen";"Hatchery";58;2
"Unit";"Queen";"Hatchery";66;2
"Unit";"Roach";"Larva";71;2
"Unit";"Roach";"Larva";71;2
"Unit";"Roach";"Larva";71;2
"Unit";"Roach";"Larva";71;2
"Unit";"Roach";"Larva";71;2
"Unit";"Roach";"Larva";71;2
"Unit";"Roach";"Larva";71;2
"Unit";"Overlord";"Larva";104;0
"Building";"CreepTumor";NA;106;0
"Building";"CreepTumor";NA;106;0
"Building";"CreepTumor";NA;106;0
"Building";"CreepTumorQueen";NA;106;0
"Building";"CreepTumor";NA;106;0
"Building";"CreepTumorQueen";NA;106;0
"Unit";"Roach";"Larva";106;2
"Unit";"Roach";"Larva";106;2
"Building";"CreepTumorQueen";NA;106;0
"Building";"EvolutionChamber";NA;106;0
"Building";"EvolutionChamber";NA;106;0
"Building";"CreepTumorQueen";NA;109;0
"Unit";"Overlord";"Larva";106;0
"Unit";"Overlord";"Larva";106;0
"Unit";"Queen";"Hatchery";104;2
"Building";"CreepTumorQueen";NA;109;0
"Unit";"Roach";"Larva";106;2
"Unit";"Overlord";"Larva";109;0
"Unit";"Overlord";"Larva";109;0
"Building";"CreepTumor";NA;113;0
"Building";"CreepTumor";NA;115;0
"Unit";"Overlord";"Larva";113;0
"Building";"CreepTumor";NA;117;0
"Building";"CreepTumor";NA;117;0
"Building";"CreepTumor";NA;117;0
"Building";"Extractor";NA;117;0
"Building";"CreepTumorQueen";NA;123;0
"Building";"CreepTumorQueen";NA;123;0
"Building";"CreepTumor";NA;123;0
"Building";"CreepTumor";NA;123;0
"Building";"Extractor";NA;123;0
"Unit";"Zergling";"Larva";127;1
"Unit";"Zergling";"Larva";127;1
"Unit";"Zergling";"Larva";127;1
"Unit";"Zergling";"Larva";127;1
"Unit";"Zergling";"Larva";127;1
"Unit";"Zergling";"Larva";127;1
"Unit";"Zergling";"Larva";127;1
"Unit";"Zergling";"Larva";127;1
"Unit";"Zergling";"Larva";127;1
"Unit";"Zergling";"Larva";127;1
"Unit";"Zergling";"Larva";127;1
"Unit";"Zergling";"Larva";127;1
"Unit";"Zergling";"Larva";130;1
"Unit";"Zergling";"Larva";130;1
"Unit";"Zergling";"Larva";132;1
"Unit";"Zergling";"Larva";132;1
"Unit";"Zergling";"Larva";132;1
"Unit";"Zergling";"Larva";132;1
"Unit";"Zergling";"Larva";132;1
"Unit";"Zergling";"Larva";132;1
"Unit";"Zergling";"Larva";132;1
"Unit";"Zergling";"Larva";132;1
"Building";"CreepTumor";NA;146;0
"Unit";"Overlord";"Larva";144;0
"Unit";"Overlord";"Larva";145;0
"Building";"CreepTumor";NA;146;0
"Building";"CreepTumor";NA;146;0
"Building";"CreepTumor";NA;146;0
"Unit";"Roach";"Larva";146;2
"Unit";"Roach";"Larva";146;2
"Unit";"Roach";"Larva";146;2
"Unit";"Roach";"Larva";146;2
"Unit";"Roach";"Larva";148;2
"Unit";"Roach";"Larva";150;2
"Building";"CreepTumor";NA;168;0
"Building";"CreepTumor";NA;168;0
"Building";"CreepTumor";NA;168;0
"Building";"CreepTumor";NA;168;0
"Building";"CreepTumor";NA;168;0
"Building";"Extractor";NA;168;0
"Building";"Extractor";NA;168;0
"Building";"CreepTumor";NA;175;0
"Building";"CreepTumor";NA;175;0
"Unit";"Overlord";"Larva";168;0
"Unit";"Overlord";"Larva";168;0
"Unit";"Overlord";"Larva";168;0
"Building";"HydraliskDen";NA;168;0
"Building";"CreepTumorQueen";NA;177;0
"Building";"CreepTumorQueen";NA;177;0
"Building";"CreepTumorQueen";NA;177;0
"Building";"CreepTumor";NA;177;0
"Building";"CreepTumor";NA;177;0
"Building";"CreepTumor";NA;177;0
"Unit";"Overlord";"Larva";177;0
"Unit";"Overlord";"Larva";177;0
"Unit";"Overlord";"Larva";177;0
"Unit";"Overlord";"Larva";177;0
"Unit";"Roach";"Larva";177;2
"Upgrade";"ZergMissileWeaponsLevel1";"EvolutionChamber";144;0
"Unit";"Overlord";"Larva";180;0
"Building";"CreepTumor";NA;182;0
"Building";"CreepTumor";NA;182;0
"Building";"CreepTumor";NA;182;0
"Unit";"Hydralisk";"Larva";180;2
"Building";"CreepTumor";NA;182;0
"Unit";"Hydralisk";"Larva";180;2
"Unit";"Hydralisk";"Larva";180;2
"Unit";"Hydralisk";"Larva";180;2
"Unit";"Hydralisk";"Larva";180;2
"Unit";"Hydralisk";"Larva";180;2
"Building";"CreepTumorQueen";NA;188;0
"Building";"CreepTumorQueen";NA;199;0
"Building";"CreepTumor";NA;189;0
"Building";"CreepTumor";NA;189;0
"Building";"CreepTumorQueen";NA;201;0
"Building";"CreepTumorQueen";NA;201;0
"Upgrade";"ZergGroundArmorsLevel1";"EvolutionChamber";168;0
"Building";"Hatchery";NA;177;0
"Building";"InfestationPit";NA;182;0
"Building";"CreepTumor";NA;206;0
"Upgrade";"GlialReconstitution";"RoachWarren";180;0
"Unit";"Hydralisk";"Larva";206;2
"Unit";"Hydralisk";"Larva";206;2
"Unit";"Hydralisk";"Larva";206;2
"Unit";"Hydralisk";"Larva";206;2
"Building";"CreepTumorQueen";NA;206;0
"Building";"CreepTumorQueen";NA;206;0
"Building";"CreepTumorQueen";NA;206;0
"Building";"CreepTumorQueen";NA;206;0
"Unit";"Hydralisk";"Larva";206;2
"Unit";"Hydralisk";"Larva";206;2
"Unit";"Hydralisk";"Larva";206;2
"Unit";"Hydralisk";"Larva";206;2
"Upgrade";"EvolveGroovedSpines";"HydraliskDen";184;0
"Building";"CreepTumor";NA;214;0
"Unit";"Hydralisk";"Larva";206;2
"Unit";"Hydralisk";"Larva";208;2
"Unit";"Hydralisk";"Larva";208;2
"Unit";"Hydralisk";"Larva";212;2
"Unit";"Hydralisk";"Larva";212;2
"Unit";"Hydralisk";"Larva";214;2
"Unit";"Hydralisk";"Larva";214;2
"Building";"CreepTumor";NA;236;0
"Building";"CreepTumor";NA;236;0
"Building";"CreepTumor";NA;236;0
"Building";"CreepTumor";NA;236;0
"Building";"CreepTumor";NA;236;0
"Building";"CreepTumor";NA;236;0
"Building";"CreepTumor";NA;236;0
"Unit";"Hydralisk";"Larva";236;2
"Unit";"Hydralisk";"Larva";236;2
"Unit";"Hydralisk";"Larva";236;2
"Unit";"Hydralisk";"Larva";236;2
"Unit";"Hydralisk";"Larva";236;2
"Unit";"Hydralisk";"Larva";236;2
"Unit";"Hydralisk";"Larva";236;2
"Building";"CreepTumor";NA;236;0
"Building";"Hatchery";NA;206;0
"Building";"CreepTumor";NA;236;0
"Building";"CreepTumor";NA;236;0
"Building";"CreepTumor";NA;236;0
"Building";"CreepTumor";NA;236;0
"Building";"CreepTumor";NA;236;0
"Building";"CreepTumor";NA;236;0
"Building";"Extractor";NA;236;0
"Building";"Extractor";NA;236;0
"Building";"CreepTumor";NA;250;0
"Building";"CreepTumor";NA;250;0
"Building";"CreepTumor";NA;250;0
"Building";"CreepTumor";NA;250;0
"Building";"CreepTumor";NA;250;0
"Building";"CreepTumor";NA;250;0
"Building";"CreepTumorQueen";NA;250;0
"Building";"CreepTumorQueen";NA;250;0
"Building";"CreepTumorQueen";NA;250;0
"Building";"CreepTumorQueen";NA;250;0
"Upgrade";"ZergMissileWeaponsLevel2";"EvolutionChamber";222;0
"Unit";"Viper";"Larva";250;3
"Unit";"Viper";"Larva";250;3
"Unit";"Viper";"Larva";250;3
"Unit";"Viper";"Larva";250;3
"Building";"CreepTumor";NA;250;0
"Building";"CreepTumorQueen";NA;262;0
"Unit";"Viper";"Larva";250;3
"Unit";"Viper";"Larva";250;3
"Building";"CreepTumorQueen";NA;262;0
"Unit";"Hydralisk";"Larva";262;2
"Unit";"Hydralisk";"Larva";262;2
"Unit";"Hydralisk";"Larva";262;2
"Unit";"Hydralisk";"Larva";262;2
"Unit";"Hydralisk";"Larva";262;2
"Unit";"Hydralisk";"Larva";262;2
"Unit";"Hydralisk";"Larva";262;2
"Unit";"Hydralisk";"Larva";268;2
"Unit";"Hydralisk";"Larva";268;2
"Unit";"Hydralisk";"Larva";268;2
"Unit";"Hydralisk";"Larva";268;2
"Unit";"Hydralisk";"Larva";268;2
"Unit";"Hydralisk";"Larva";268;2
"Unit";"Hydralisk";"Larva";268;2
"Unit";"Hydralisk";"Larva";268;2
"Unit";"Hydralisk";"Larva";268;2
"Unit";"Hydralisk";"Larva";268;2
"Unit";"Hydralisk";"Larva";268;2
"Unit";"Roach";"Larva";282;2
"Unit";"Roach";"Larva";282;2
"Unit";"Roach";"Larva";282;2
"Unit";"Hydralisk";"Larva";282;2
"Unit";"Hydralisk";"Larva";282;2
"Unit";"Hydralisk";"Larva";282;2
"Unit";"Zergling";"Larva";282;1
"Unit";"Zergling";"Larva";282;1
"Unit";"Zergling";"Larva";282;1
"Unit";"Zergling";"Larva";282;1
"Unit";"Zergling";"Larva";282;1
"Unit";"Zergling";"Larva";282;1
"Unit";"Zergling";"Larva";282;1
"Unit";"Zergling";"Larva";282;1
"Unit";"Zergling";"Larva";282;1
"Unit";"Zergling";"Larva";282;1
"Unit";"Zergling";"Larva";282;1
"Unit";"Zergling";"Larva";282;1
"Unit";"Zergling";"Larva";282;1
"Unit";"Zergling";"Larva";282;1
"Unit";"Zergling";"Larva";282;1
"Unit";"Zergling";"Larva";282;1
"Unit";"Zergling";"Larva";282;1
"Unit";"Zergling";"Larva";282;1
"Unit";"Zergling";"Larva";282;1
"Unit";"Zergling";"Larva";282;1
"Unit";"Zergling";"Larva";282;1
"Unit";"Zergling";"Larva";282;1
"Unit";"Zergling";"Larva";282;1
"Unit";"Zergling";"Larva";282;1
"Unit";"Zergling";"Larva";282;1
"Unit";"Zergling";"Larva";282;1
"Unit";"Zergling";"Larva";282;1
"Unit";"Zergling";"Larva";282;1
"Unit";"Zergling";"Larva";282;1
"Unit";"Zergling";"Larva";282;1
"Unit";"Zergling";"Larva";282;1
"Unit";"Zergling";"Larva";282;1
"Unit";"Zergling";"Larva";282;1
"Unit";"Zergling";"Larva";282;1
"Unit";"Zergling";"Larva";282;1
"Unit";"Zergling";"Larva";282;1
"Unit";"Zergling";"Larva";282;1
"Unit";"Zergling";"Larva";282;1
"Unit";"Zergling";"Larva";282;1
"Unit";"Zergling";"Larva";282;1
"Unit";"Zergling";"Larva";282;1
"Unit";"Zergling";"Larva";282;1
"Unit";"Zergling";"Larva";282;1
"Unit";"Zergling";"Larva";282;1
"Unit";"Zergling";"Larva";282;1
"Unit";"Zergling";"Larva";282;1
"Unit";"Zergling";"Larva";282;1
"Unit";"Zergling";"Larva";282;1
"Unit";"Zergling";"Larva";282;1
"Unit";"Zergling";"Larva";282;1
"Upgrade";"ZergGroundArmorsLevel2";"EvolutionChamber";250;0
"Building";"Extractor";NA;304;0
"Building";"Extractor";NA;304;0
"Unit";"Hydralisk";"Larva";308;2
"Unit";"Hydralisk";"Larva";308;2
"Unit";"Hydralisk";"Larva";308;2
"Unit";"Hydralisk";"Larva";310;2
"Unit";"Hydralisk";"Larva";310;2
"Unit";"Hydralisk";"Larva";310;2
"Unit";"Roach";"Larva";366;2
"Unit";"Roach";"Larva";366;2
"Unit";"Roach";"Larva";366;2
"Unit";"Hydralisk";"Larva";378;2
"Unit";"Hydralisk";"Larva";378;2
"Unit";"Hydralisk";"Larva";378;2
"Unit";"Hydralisk";"Larva";378;2
"Unit";"Hydralisk";"Larva";378;2
"Unit";"Hydralisk";"Larva";378;2
"Unit";"Hydralisk";"Larva";378;2
"Unit";"Hydralisk";"Larva";378;2
"Unit";"Hydralisk";"Larva";378;2
"Unit";"Hydralisk";"Larva";384;2
"Unit";"Hydralisk";"Larva";384;2
"Building";"Hatchery";NA;366;0
"Unit";"Hydralisk";"Larva";405;2
"Unit";"Hydralisk";"Larva";405;2
"Unit";"Hydralisk";"Larva";405;2
"Unit";"Hydralisk";"Larva";405;2
"Unit";"Hydralisk";"Larva";405;2
"Unit";"Hydralisk";"Larva";405;2
"Unit";"Hydralisk";"Larva";405;2
"Unit";"Hydralisk";"Larva";409;2
"Unit";"Hydralisk";"Larva";409;2
"Unit";"Hydralisk";"Larva";409;2
"Unit";"Hydralisk";"Larva";409;2
"Unit";"Hydralisk";"Larva";409;2
"Unit";"Hydralisk";"Larva";409;2
"Unit";"Hydralisk";"Larva";409;2
"Unit";"Roach";"Larva";409;2
"Unit";"Roach";"Larva";409;2
"Unit";"Roach";"Larva";409;2
"Unit";"Hydralisk";"Larva";409;2
"Unit";"Hydralisk";"Larva";409;2
"Unit";"Roach";"Larva";423;2
"Unit";"Roach";"Larva";423;2
"Unit";"Roach";"Larva";423;2
"Unit";"Roach";"Larva";423;2
"Unit";"Roach";"Larva";423;2
"Upgrade";"EvolveMuscularAugments";"HydraliskDen";409;0
"Unit";"Hydralisk";"Larva";447;2
"Unit";"Hydralisk";"Larva";447;2
"Unit";"Hydralisk";"Larva";447;2
"Unit";"Hydralisk";"Larva";447;2
"Unit";"Hydralisk";"Larva";447;2
"Unit";"Hydralisk";"Larva";447;2
"Building";"CreepTumor";NA;457;0
"Building";"Hatchery";NA;409;0
"Unit";"Hydralisk";"Larva";457;2
"Unit";"Hydralisk";"Larva";457;2
"Unit";"Hydralisk";"Larva";457;2
"Unit";"Hydralisk";"Larva";457;2
"Unit";"Hydralisk";"Larva";457;2
"Unit";"Hydralisk";"Larva";457;2
"Building";"CreepTumor";NA;474;0
"Building";"CreepTumor";NA;474;0
"Building";"CreepTumor";NA;474;0
"Building";"CreepTumor";NA;474;0
"Unit";"Queen";"Hatchery";469;2
"Building";"CreepTumorQueen";NA;493;0
"Building";"CreepTumor";NA;493;0
"Unit";"Hydralisk";"Larva";493;2
"Unit";"Hydralisk";"Larva";493;2
"Unit";"Hydralisk";"Larva";493;2
"Unit";"Hydralisk";"Larva";493;2
"Unit";"Hydralisk";"Larva";493;2
"Unit";"Hydralisk";"Larva";493;2
"Unit";"Hydralisk";"Larva";493;2
"Unit";"Hydralisk";"Larva";493;2
"Unit";"Hydralisk";"Larva";493;2
"Unit";"Hydralisk";"Larva";493;2
"Unit";"Hydralisk";"Larva";493;2
"Unit";"Hydralisk";"Larva";493;2
"Unit";"Hydralisk";"Larva";493;2
"Unit";"Hydralisk";"Larva";493;2
"Unit";"Hydralisk";"Larva";493;2
"Unit";"Hydralisk";"Larva";493;2
"Unit";"Hydralisk";"Larva";493;2
"Building";"CreepTumorQueen";NA;493;0
"Building";"Extractor";NA;493;0
"Unit";"Viper";"Larva";493;3
"Building";"Spire";NA;491;0
"Building";"Extractor";NA;527;0
"Unit";"Hydralisk";"Larva";530;2
"Unit";"Hydralisk";"Larva";530;2
"Unit";"Hydralisk";"Larva";530;2
"Unit";"Hydralisk";"Larva";530;2
"Unit";"Hydralisk";"Larva";530;2
"Unit";"Hydralisk";"Larva";530;2
"Unit";"Hydralisk";"Larva";530;2
"Unit";"Hydralisk";"Larva";530;2
"Unit";"Hydralisk";"Larva";530;2
"Unit";"Hydralisk";"Larva";530;2
"Unit";"Hydralisk";"Larva";530;2
"Unit";"Hydralisk";"Larva";530;2
"Building";"CreepTumor";NA;530;0
"Building";"Extractor";NA;530;0
"Building";"CreepTumor";NA;530;0
"Unit";"Viper";"Larva";530;3
"Building";"CreepTumorQueen";NA;530;0
"Unit";"Viper";"Larva";530;3
"Unit";"Viper";"Larva";530;3
"Building";"CreepTumor";NA;559;0
"Building";"CreepTumor";NA;559;0
"Building";"CreepTumor";NA;559;0
"Unit";"Hydralisk";"Larva";556;2
"Building";"CreepTumor";NA;559;0
"Upgrade";"ZergMissileWeaponsLevel3";"EvolutionChamber";493;0
"Building";"CreepTumorQueen";NA;567;0
"Building";"CreepTumorQueen";NA;568;0
"Unit";"Corruptor";"Larva";568;2
"Unit";"Corruptor";"Larva";568;2
"Unit";"Corruptor";"Larva";568;2
"Unit";"Corruptor";"Larva";568;2
"Building";"CreepTumorQueen";NA;576;0
"Building";"CreepTumorQueen";NA;576;0
"Building";"CreepTumor";NA;576;0
"Unit";"Overlord";"Larva";576;0
"Unit";"Overlord";"Larva";576;0
"Unit";"Overlord";"Larva";576;0
"Building";"CreepTumor";NA;576;0
"Upgrade";"ZergGroundArmorsLevel3";"EvolutionChamber";568;0
"Unit";"Corruptor";"Larva";576;2
"Unit";"Corruptor";"Larva";576;2
"Unit";"Corruptor";"Larva";576;2
"Unit";"Corruptor";"Larva";576;2
"Building";"CreepTumor";NA;584;0
"Building";"CreepTumor";NA;584;0
"Building";"UltraliskCavern";NA;584;0
"Unit";"Corruptor";"Larva";584;2
"Unit";"Corruptor";"Larva";584;2
"Unit";"Corruptor";"Larva";584;2
"Unit";"Corruptor";"Larva";584;2
"Unit";"Hydralisk";"Larva";584;2
"Unit";"Hydralisk";"Larva";584;2
"Unit";"Hydralisk";"Larva";584;2
"Unit";"Hydralisk";"Larva";584;2
"Unit";"Hydralisk";"Larva";584;2
"Unit";"Hydralisk";"Larva";584;2
"Unit";"Hydralisk";"Larva";584;2
"Unit";"Hydralisk";"Larva";584;2
"Unit";"Corruptor";"Larva";584;2
"Unit";"Corruptor";"Larva";584;2
"Unit";"Corruptor";"Larva";584;2
"Unit";"Corruptor";"Larva";584;2
"Unit";"Corruptor";"Larva";584;2
"Unit";"Corruptor";"Larva";584;2
"Unit";"Corruptor";"Larva";584;2
"Upgrade";"ZergMeleeWeaponsLevel1";"EvolutionChamber";584;0
"Building";"SporeCrawler";NA;592;0
"Building";"CreepTumor";NA;608;0
"Building";"CreepTumor";NA;608;0
"Building";"SporeCrawler";NA;592;0
"Unit";"Infestor";"Larva";592;2
"Unit";"Infestor";"Larva";592;2
"Unit";"Infestor";"Larva";592;2
"Unit";"Infestor";"Larva";592;2
"Unit";"Infestor";"Larva";592;2
"Unit";"Infestor";"Larva";592;2
"Building";"SporeCrawler";NA;608;0
"Building";"SpineCrawler";NA;592;0
"Building";"SpineCrawler";NA;592;0
"Building";"SpineCrawler";NA;608;0
"Building";"SpineCrawler";NA;608;0
"Building";"CreepTumor";NA;637;0
"Unit";"Infestor";"Larva";622;2
"Unit";"Infestor";"Larva";622;2
"Unit";"Infestor";"Larva";622;2
"Unit";"Infestor";"Larva";622;2
"Unit";"Infestor";"Larva";622;2
"Unit";"Infestor";"Larva";622;2
"Unit";"Infestor";"Larva";622;2
"Unit";"Infestor";"Larva";622;2
"Building";"CreepTumor";NA;637;0
"Building";"CreepTumor";NA;653;0
"Building";"SpineCrawler";NA;653;0
"Building";"SpineCrawler";NA;653;0
"Building";"SpineCrawler";NA;653;0
"Upgrade";"ChitinousPlating";"UltraliskCavern";637;0
"Unit";"Corruptor";"Larva";656;2
"Unit";"Corruptor";"Larva";656;2
"Unit";"Corruptor";"Larva";656;2
"Unit";"Corruptor";"Larva";656;2
"Unit";"Corruptor";"Larva";656;2
"Unit";"Corruptor";"Larva";656;2
"Unit";"Corruptor";"Larva";656;2
"Unit";"Corruptor";"Larva";656;2
"Unit";"Corruptor";"Larva";656;2
"Unit";"Corruptor";"Larva";656;2
"Building";"SporeCrawler";NA;656;0
"Building";"SporeCrawler";NA;656;0
"Upgrade";"Burrow";"Hatchery";656;0
"Unit";"Hydralisk";"Larva";676;2
"Unit";"Hydralisk";"Larva";676;2
"Unit";"Hydralisk";"Larva";676;2
"Unit";"Hydralisk";"Larva";676;2
"Unit";"Hydralisk";"Larva";676;2
"Unit";"Hydralisk";"Larva";676;2
"Unit";"Hydralisk";"Larva";676;2
"Building";"Hatchery";NA;676;0
"Unit";"Corruptor";"Larva";676;2
"Unit";"Corruptor";"Larva";676;2
"Unit";"Corruptor";"Larva";676;2
"Unit";"Corruptor";"Larva";676;2
"Unit";"Hydralisk";"Larva";698;2
"Unit";"Hydralisk";"Larva";698;2
"Unit";"Hydralisk";"Larva";698;2
"Unit";"Hydralisk";"Larva";698;2
"Unit";"Hydralisk";"Larva";698;2
"Unit";"Hydralisk";"Larva";698;2
"Unit";"Hydralisk";"Larva";698;2
"Unit";"Hydralisk";"Larva";698;2
"Unit";"Hydralisk";"Larva";698;2
"Unit";"Zergling";"Larva";698;1
"Unit";"Zergling";"Larva";698;1
"Unit";"Zergling";"Larva";698;1
"Unit";"Zergling";"Larva";698;1
"Unit";"Zergling";"Larva";698;1
"Unit";"Zergling";"Larva";698;1
"Unit";"Zergling";"Larva";698;1
"Unit";"Zergling";"Larva";698;1
"Unit";"Zergling";"Larva";698;1
"Unit";"Zergling";"Larva";698;1
"Unit";"Zergling";"Larva";698;1
"Unit";"Zergling";"Larva";698;1
"Unit";"Zergling";"Larva";698;1
"Unit";"Zergling";"Larva";698;1
"Unit";"Zergling";"Larva";698;1
"Unit";"Zergling";"Larva";698;1
"Unit";"Zergling";"Larva";698;1
"Unit";"Zergling";"Larva";698;1
"Unit";"Zergling";"Larva";698;1
"Unit";"Zergling";"Larva";698;1
"Unit";"Zergling";"Larva";698;1
"Unit";"Zergling";"Larva";698;1
"Unit";"Zergling";"Larva";698;1
"Unit";"Zergling";"Larva";698;1
"Unit";"Zergling";"Larva";698;1
"Unit";"Zergling";"Larva";698;1
"Unit";"Zergling";"Larva";698;1
"Unit";"Zergling";"Larva";698;1
"Unit";"Zergling";"Larva";698;1
"Unit";"Zergling";"Larva";698;1
"Unit";"Zergling";"Larva";698;1
"Unit";"Zergling";"Larva";698;1
"Unit";"Zergling";"Larva";698;1
"Unit";"Zergling";"Larva";698;1
"Unit";"Zergling";"Larva";698;1
"Unit";"Zergling";"Larva";698;1
"Unit";"Zergling";"Larva";698;1
"Unit";"Zergling";"Larva";698;1
"Unit";"Zergling";"Larva";698;1
"Unit";"Zergling";"Larva";698;1
"Unit";"Zergling";"Larva";698;1
"Unit";"Zergling";"Larva";698;1
"Unit";"Zergling";"Larva";698;1
"Unit";"Zergling";"Larva";698;1
"Unit";"Zergling";"Larva";698;1
"Unit";"Zergling";"Larva";698;1
"Unit";"Zergling";"Larva";698;1
"Unit";"Zergling";"Larva";698;1
"Unit";"Zergling";"Larva";698;1
"Unit";"Zergling";"Larva";698;1
"Unit";"Zergling";"Larva";698;1
"Unit";"Zergling";"Larva";698;1
"Unit";"Zergling";"Larva";698;1
"Unit";"Zergling";"Larva";698;1
"Unit";"Zergling";"Larva";698;1
"Unit";"Zergling";"Larva";698;1
"Unit";"Zergling";"Larva";698;1
"Unit";"Zergling";"Larva";698;1
"Unit";"Zergling";"Larva";698;1
"Unit";"Zergling";"Larva";698;1
"Unit";"Zergling";"Larva";698;1
"Unit";"Zergling";"Larva";698;1
"Unit";"Zergling";"Larva";698;1
"Unit";"Zergling";"Larva";698;1
"Unit";"Zergling";"Larva";698;1
"Unit";"Zergling";"Larva";698;1
