"type";"unit_name";"on_building";"total_supply";"supply"
"Unit";"Overlord";"Larva";13;0
"Building";"Extractor";NA;16;0
"Building";"SpawningPool";NA;17;0
"Unit";"Zergling";"Larva";21;1
"Unit";"Zergling";"Larva";21;1
"Unit";"Overlord";"Larva";23;0
"Unit";"Queen";"Hatchery";21;2
"Building";"RoachWarren";NA;21;0
"Building";"Hatchery";NA;20;0
"Unit";"Roach";"Larva";25;2
"Unit";"Roach";"Larva";25;2
"Unit";"Roach";"Larva";25;2
"Unit";"Roach";"Larva";26;2
"Unit";"Overlord";"Larva";32;0
"Unit";"Queen";"Hatchery";26;2
"Unit";"Queen";"Hatchery";39;2
"Unit";"Overlord";"Larva";44;0
"Unit";"Overlord";"Larva";44;0
"Building";"CreepTumorQueen";NA;46;0
"Building";"CreepTumorQueen";NA;60;0
"Building";"EvolutionChamber";NA;46;0
"Building";"Hatchery";NA;46;0
"Unit";"Zergling";"Larva";60;1
"Unit";"Zergling";"Larva";60;1
"Unit";"Zergling";"Larva";60;1
"Unit";"Zergling";"Larva";60;1
"Building";"Extractor";NA;60;0
"Unit";"Zergling";"Larva";60;1
"Unit";"Zergling";"Larva";60;1
"Building";"Extractor";NA;60;0
"Building";"CreepTumor";NA;64;0
"Building";"CreepTumor";NA;64;0
"Unit";"Zergling";"Larva";64;1
"Unit";"Zergling";"Larva";64;1
"Unit";"Zergling";"Larva";64;1
"Unit";"Zergling";"Larva";64;1
"Unit";"Zergling";"Larva";64;1
"Unit";"Zergling";"Larva";64;1
"Unit";"Zergling";"Larva";64;1
"Unit";"Zergling";"Larva";64;1
"Unit";"Zergling";"Larva";64;1
"Unit";"Zergling";"Larva";64;1
"Building";"CreepTumorQueen";NA;80;0
"Building";"CreepTumor";NA;80;0
"Unit";"Overlord";"Larva";80;0
"Unit";"Overlord";"Larva";80;0
"Unit";"Overlord";"Larva";80;0
"Building";"CreepTumor";NA;82;0
"Building";"EvolutionChamber";NA;82;0
"Unit";"Queen";"Hatchery";82;2
"Unit";"Queen";"Hatchery";82;2
"Unit";"Queen";"Hatchery";82;2
"Building";"CreepTumor";NA;98;0
"Unit";"Overlord";"Larva";98;0
"Unit";"Overlord";"Larva";98;0
"Unit";"Overlord";"Larva";98;0
"Unit";"Overlord";"Larva";98;0
"Building";"Extractor";NA;98;0
"Building";"SporeCrawler";NA;103;0
"Unit";"Roach";"Larva";103;2
"Unit";"Roach";"Larva";103;2
"Unit";"Roach";"Larva";103;2
"Unit";"Roach";"Larva";103;2
"Unit";"Roach";"Larva";103;2
"Unit";"Queen";"Hatchery";103;2
"Building";"CreepTumor";NA;105;0
"Building";"SporeCrawler";NA;103;0
"Upgrade";"GlialReconstitution";"RoachWarren";98;0
"Building";"CreepTumor";NA;118;0
"Building";"HydraliskDen";NA;103;0
"Building";"CreepTumor";NA;123;0
"Unit";"Roach";"Larva";118;2
"Unit";"Roach";"Larva";118;2
"Unit";"Roach";"Larva";118;2
"Unit";"Roach";"Larva";118;2
"Unit";"Roach";"Larva";118;2
"Unit";"Roach";"Larva";118;2
"Unit";"Roach";"Larva";118;2
"Upgrade";"ZergGroundArmorsLevel1";"EvolutionChamber";91;0
"Building";"Extractor";NA;123;0
"Building";"Extractor";NA;123;0
"Unit";"Roach";"Larva";137;2
"Building";"CreepTumor";NA;140;0
"Unit";"Overlord";"Larva";140;0
"Unit";"Overlord";"Larva";140;0
"Unit";"Overlord";"Larva";140;0
"Unit";"Overlord";"Larva";140;0
"Unit";"Zergling";"Larva";140;1
"Unit";"Zergling";"Larva";140;1
"Unit";"Zergling";"Larva";140;1
"Unit";"Zergling";"Larva";140;1
"Upgrade";"ZergMissileWeaponsLevel1";"EvolutionChamber";103;0
"Unit";"Hydralisk";"Larva";142;2
"Unit";"Hydralisk";"Larva";142;2
"Unit";"Hydralisk";"Larva";142;2
"Unit";"Roach";"Larva";155;2
"Unit";"Roach";"Larva";155;2
"Unit";"Roach";"Larva";155;2
"Unit";"Roach";"Larva";155;2
"Unit";"Roach";"Larva";155;2
"Unit";"Roach";"Larva";155;2
"Unit";"Roach";"Larva";155;2
"Unit";"Roach";"Larva";155;2
"Unit";"Roach";"Larva";155;2
"Unit";"Roach";"Larva";155;2
"Unit";"Roach";"Larva";155;2
"Unit";"Roach";"Larva";155;2
"Unit";"Roach";"Larva";155;2
"Building";"CreepTumor";NA;155;0
"Building";"CreepTumor";NA;155;0
"Building";"CreepTumorQueen";NA;181;0
"Upgrade";"EvolveGroovedSpines";"HydraliskDen";149;0
"Building";"InfestationPit";NA;155;0
"Unit";"Overlord";"Larva";181;0
"Unit";"Overlord";"Larva";181;0
"Unit";"Overlord";"Larva";181;0
"Building";"CreepTumor";NA;181;0
"Building";"CreepTumor";NA;181;0
"Building";"CreepTumor";NA;181;0
"Building";"CreepTumorQueen";NA;181;0
"Building";"CreepTumorQueen";NA;181;0
"Building";"Hatchery";NA;181;0
"Building";"CreepTumor";NA;181;0
"Upgrade";"ZergGroundArmorsLevel2";"EvolutionChamber";155;0
"Building";"CreepTumor";NA;181;0
"Building";"CreepTumor";NA;181;0
"Unit";"Roach";"Larva";181;2
"Unit";"Roach";"Larva";181;2
"Unit";"Roach";"Larva";181;2
"Building";"CreepTumor";NA;181;0
"Building";"Extractor";NA;181;0
"Building";"Extractor";NA;181;0
"Unit";"Queen";"Hatchery";181;2
"Building";"CreepTumor";NA;196;0
"Building";"CreepTumor";NA;196;0
"Unit";"Overlord";"Larva";196;0
"Unit";"Overlord";"Larva";196;0
"Unit";"Overlord";"Larva";196;0
"Upgrade";"Burrow";"Hatchery";190;0
"Upgrade";"ZergMissileWeaponsLevel2";"EvolutionChamber";181;0
"Building";"CreepTumorQueen";NA;198;0
"Building";"CreepTumorQueen";NA;198;0
"Unit";"Hydralisk";"Larva";198;2
"Unit";"Hydralisk";"Larva";198;2
"Unit";"Hydralisk";"Larva";198;2
"Unit";"Hydralisk";"Larva";198;2
"Unit";"Hydralisk";"Larva";198;2
"Unit";"Hydralisk";"Larva";198;2
"Unit";"Hydralisk";"Larva";198;2
"Unit";"Hydralisk";"Larva";198;2
"Unit";"Hydralisk";"Larva";198;2
"Unit";"Hydralisk";"Larva";198;2
"Unit";"Hydralisk";"Larva";198;2
"Unit";"Hydralisk";"Larva";198;2
"Unit";"Hydralisk";"Larva";198;2
"Building";"CreepTumor";NA;199;0
"Upgrade";"EvolveMuscularAugments";"HydraliskDen";198;0
"Unit";"Overlord";"Larva";228;0
"Unit";"Overlord";"Larva";228;0
"Building";"CreepTumor";NA;228;0
"Building";"CreepTumorQueen";NA;228;0
"Building";"CreepTumor";NA;228;0
"Unit";"Viper";"Larva";228;3
"Unit";"Viper";"Larva";228;3
"Unit";"Viper";"Larva";228;3
"Building";"CreepTumor";NA;228;0
"Building";"CreepTumor";NA;234;0
"Building";"CreepTumor";NA;234;0
"Building";"CreepTumor";NA;234;0
"Unit";"Zergling";"Larva";234;1
"Unit";"Zergling";"Larva";234;1
"Unit";"Zergling";"Larva";234;1
"Unit";"Zergling";"Larva";234;1
"Unit";"Zergling";"Larva";234;1
"Unit";"Zergling";"Larva";234;1
"Unit";"Zergling";"Larva";234;1
"Unit";"Zergling";"Larva";234;1
"Unit";"Zergling";"Larva";234;1
"Unit";"Zergling";"Larva";234;1
"Unit";"Zergling";"Larva";234;1
"Unit";"Zergling";"Larva";234;1
"Unit";"Zergling";"Larva";234;1
"Unit";"Zergling";"Larva";234;1
"Unit";"Zergling";"Larva";234;1
"Unit";"Zergling";"Larva";234;1
"Unit";"Zergling";"Larva";234;1
"Unit";"Zergling";"Larva";234;1
"Unit";"Zergling";"Larva";234;1
"Unit";"Zergling";"Larva";234;1
"Unit";"Zergling";"Larva";234;1
"Unit";"Zergling";"Larva";234;1
"Building";"BanelingNest";NA;228;0
"Building";"CreepTumor";NA;265;0
"Building";"CreepTumor";NA;265;0
"Building";"SpineCrawler";NA;228;0
"Building";"CreepTumorQueen";NA;265;0
"Building";"SpineCrawler";NA;232;0
"Building";"SpineCrawler";NA;234;0
"Building";"Hatchery";NA;228;0
"Unit";"Baneling";"Zergling";265;0
"Unit";"Baneling";"Zergling";265;0
"Unit";"Baneling";"Zergling";265;0
"Unit";"Baneling";"Zergling";265;0
"Unit";"Baneling";"Zergling";265;0
"Unit";"Baneling";"Zergling";265;0
"Unit";"Baneling";"Zergling";265;0
"Unit";"Baneling";"Zergling";265;0
"Unit";"Baneling";"Zergling";265;0
"Unit";"Baneling";"Zergling";265;0
"Unit";"Baneling";"Zergling";265;0
"Unit";"Baneling";"Zergling";265;0
"Unit";"Baneling";"Zergling";265;0
"Unit";"Baneling";"Zergling";265;0
"Unit";"Baneling";"Zergling";265;0
"Unit";"Baneling";"Zergling";265;0
"Unit";"Baneling";"Zergling";265;0
"Unit";"Baneling";"Zergling";265;0
"Unit";"Baneling";"Zergling";265;0
"Unit";"Baneling";"Zergling";265;0
"Unit";"Baneling";"Zergling";265;0
"Unit";"Baneling";"Zergling";265;0
"Building";"CreepTumor";NA;276;0
"Building";"CreepTumor";NA;276;0
"Unit";"Zergling";"Larva";279;1
"Unit";"Zergling";"Larva";279;1
"Unit";"Zergling";"Larva";279;1
"Unit";"Zergling";"Larva";279;1
"Unit";"Zergling";"Larva";279;1
"Unit";"Zergling";"Larva";279;1
"Unit";"Zergling";"Larva";279;1
"Unit";"Zergling";"Larva";279;1
"Unit";"Zergling";"Larva";279;1
"Unit";"Zergling";"Larva";279;1
"Unit";"Zergling";"Larva";279;1
"Unit";"Zergling";"Larva";279;1
"Building";"Spire";NA;278;0
"Upgrade";"ZergGroundArmorsLevel3";"EvolutionChamber";276;0
"Upgrade";"ZergMissileWeaponsLevel3";"EvolutionChamber";276;0
"Unit";"Hydralisk";"Larva";296;2
"Unit";"Hydralisk";"Larva";296;2
"Unit";"Hydralisk";"Larva";296;2
"Unit";"Hydralisk";"Larva";296;2
"Unit";"Hydralisk";"Larva";296;2
"Unit";"Hydralisk";"Larva";296;2
"Unit";"Hydralisk";"Larva";296;2
"Unit";"Hydralisk";"Larva";296;2
"Unit";"Hydralisk";"Larva";296;2
"Unit";"Hydralisk";"Larva";296;2
"Unit";"Hydralisk";"Larva";296;2
"Unit";"Hydralisk";"Larva";296;2
"Unit";"Hydralisk";"Larva";296;2
"Unit";"Hydralisk";"Larva";296;2
"Unit";"Hydralisk";"Larva";296;2
"Building";"CreepTumor";NA;296;0
"Building";"CreepTumor";NA;296;0
"Building";"CreepTumor";NA;296;0
"Building";"Extractor";NA;296;0
"Unit";"Zergling";"Larva";326;1
"Unit";"Zergling";"Larva";326;1
"Unit";"Zergling";"Larva";326;1
"Unit";"Zergling";"Larva";326;1
"Unit";"Zergling";"Larva";326;1
"Unit";"Zergling";"Larva";326;1
"Unit";"Zergling";"Larva";326;1
"Unit";"Zergling";"Larva";326;1
"Unit";"Zergling";"Larva";326;1
"Unit";"Zergling";"Larva";326;1
"Unit";"Zergling";"Larva";326;1
"Unit";"Zergling";"Larva";326;1
"Unit";"Zergling";"Larva";326;1
"Unit";"Zergling";"Larva";326;1
"Unit";"Zergling";"Larva";326;1
"Unit";"Zergling";"Larva";326;1
"Unit";"Zergling";"Larva";326;1
"Unit";"Zergling";"Larva";326;1
"Unit";"Zergling";"Larva";326;1
"Unit";"Zergling";"Larva";326;1
"Unit";"Zergling";"Larva";326;1
"Unit";"Zergling";"Larva";326;1
"Unit";"Zergling";"Larva";326;1
"Unit";"Zergling";"Larva";326;1
"Building";"SpineCrawler";NA;326;0
"Building";"SpineCrawler";NA;326;0
"Building";"SpineCrawler";NA;326;0
"Building";"CreepTumor";NA;350;0
"Unit";"Hydralisk";"Larva";350;2
"Unit";"Hydralisk";"Larva";350;2
"Unit";"Hydralisk";"Larva";350;2
"Unit";"Hydralisk";"Larva";350;2
"Unit";"Corruptor";"Larva";350;2
"Building";"Hatchery";NA;326;0
"Unit";"Baneling";"Zergling";358;0
"Unit";"Baneling";"Zergling";358;0
"Unit";"Baneling";"Zergling";358;0
"Unit";"Baneling";"Zergling";358;0
"Unit";"Baneling";"Zergling";358;0
"Unit";"Baneling";"Zergling";358;0
"Unit";"Baneling";"Zergling";358;0
"Unit";"Baneling";"Zergling";358;0
"Unit";"Baneling";"Zergling";358;0
"Unit";"Baneling";"Zergling";358;0
"Unit";"Baneling";"Zergling";358;0
"Unit";"Baneling";"Zergling";358;0
"Unit";"Baneling";"Zergling";358;0
"Unit";"Baneling";"Zergling";358;0
"Unit";"Baneling";"Zergling";358;0
"Unit";"Baneling";"Zergling";358;0
"Unit";"Baneling";"Zergling";358;0
"Unit";"Baneling";"Zergling";358;0
"Unit";"Baneling";"Zergling";358;0
"Unit";"Baneling";"Zergling";358;0
"Building";"SpineCrawler";NA;350;0
"Building";"SpineCrawler";NA;358;0
"Building";"SpineCrawler";NA;358;0
"Building";"CreepTumor";NA;360;0
"Unit";"Hydralisk";"Larva";360;2
"Unit";"Hydralisk";"Larva";360;2
"Unit";"Hydralisk";"Larva";360;2
"Unit";"Hydralisk";"Larva";360;2
"Unit";"Hydralisk";"Larva";360;2
"Unit";"Hydralisk";"Larva";360;2
"Unit";"Hydralisk";"Larva";360;2
"Unit";"Hydralisk";"Larva";360;2
"Unit";"Hydralisk";"Larva";360;2
"Unit";"Hydralisk";"Larva";360;2
"Unit";"Hydralisk";"Larva";360;2
"Building";"CreepTumor";NA;382;0
"Unit";"Corruptor";"Larva";382;2
"Unit";"Corruptor";"Larva";382;2
"Unit";"Corruptor";"Larva";382;2
"Unit";"Corruptor";"Larva";382;2
"Unit";"Corruptor";"Larva";382;2
"Unit";"Corruptor";"Larva";382;2
"Building";"CreepTumor";NA;382;0
"Building";"CreepTumor";NA;382;0
"Building";"Extractor";NA;382;0
"Building";"Extractor";NA;394;0
"Building";"Hatchery";NA;360;0
"Building";"Extractor";NA;394;0
"Building";"SporeCrawler";NA;394;0
"Building";"SporeCrawler";NA;394;0
"Building";"SpineCrawler";NA;394;0
"Building";"SpineCrawler";NA;394;0
"Building";"CreepTumor";NA;402;0
"Unit";"Mutalisk";"Larva";405;2
"Unit";"Mutalisk";"Larva";405;2
"Unit";"Mutalisk";"Larva";405;2
"Unit";"Mutalisk";"Larva";405;2
"Unit";"Mutalisk";"Larva";405;2
"Unit";"Mutalisk";"Larva";405;2
"Unit";"Mutalisk";"Larva";405;2
"Unit";"Mutalisk";"Larva";405;2
"Unit";"Mutalisk";"Larva";405;2
"Unit";"Mutalisk";"Larva";405;2
"Unit";"Mutalisk";"Larva";405;2
"Unit";"Mutalisk";"Larva";405;2
"Unit";"Mutalisk";"Larva";405;2
"Unit";"Mutalisk";"Larva";405;2
"Unit";"Mutalisk";"Larva";405;2
"Unit";"Mutalisk";"Larva";405;2
"Unit";"Mutalisk";"Larva";405;2
"Unit";"Mutalisk";"Larva";405;2
"Unit";"Mutalisk";"Larva";405;2
"Unit";"Mutalisk";"Larva";405;2
"Unit";"Hydralisk";"Larva";445;2
"Unit";"Hydralisk";"Larva";445;2
"Unit";"Hydralisk";"Larva";445;2
"Unit";"Hydralisk";"Larva";445;2
"Unit";"Hydralisk";"Larva";445;2
"Unit";"Hydralisk";"Larva";445;2
"Unit";"Hydralisk";"Larva";445;2
"Unit";"Hydralisk";"Larva";445;2
"Unit";"Hydralisk";"Larva";445;2
"Unit";"Hydralisk";"Larva";445;2
"Unit";"Hydralisk";"Larva";445;2
"Unit";"Hydralisk";"Larva";445;2
"Unit";"Hydralisk";"Larva";445;2
"Unit";"Hydralisk";"Larva";445;2
"Unit";"Hydralisk";"Larva";445;2
"Building";"SpineCrawler";NA;475;0
"Building";"SpineCrawler";NA;475;0
"Building";"SpineCrawler";NA;475;0
"Building";"SpineCrawler";NA;475;0
"Unit";"Hydralisk";"Larva";480;2
"Unit";"Hydralisk";"Larva";480;2
"Unit";"Hydralisk";"Larva";480;2
"Unit";"Hydralisk";"Larva";480;2
"Unit";"Hydralisk";"Larva";480;2
"Unit";"Hydralisk";"Larva";480;2
"Unit";"Hydralisk";"Larva";480;2
"Unit";"Hydralisk";"Larva";480;2
"Unit";"Hydralisk";"Larva";480;2
"Unit";"Hydralisk";"Larva";480;2
"Unit";"Hydralisk";"Larva";480;2
"Unit";"Hydralisk";"Larva";480;2
"Unit";"Hydralisk";"Larva";480;2
"Unit";"Hydralisk";"Larva";480;2
"Unit";"Hydralisk";"Larva";480;2
"Building";"CreepTumorQueen";NA;510;0
"Unit";"Queen";"Hatchery";480;2
"Building";"CreepTumorQueen";NA;510;0
"Unit";"Queen";"Hatchery";480;2
"Building";"SpineCrawler";NA;510;0
"Building";"CreepTumorQueen";NA;514;0
"Unit";"Hydralisk";"Larva";514;2
"Unit";"Hydralisk";"Larva";514;2
"Unit";"Hydralisk";"Larva";514;2
"Unit";"Hydralisk";"Larva";514;2
"Unit";"Hydralisk";"Larva";514;2
"Unit";"Hydralisk";"Larva";514;2
"Unit";"Hydralisk";"Larva";514;2
"Unit";"Hydralisk";"Larva";514;2
"Unit";"Hydralisk";"Larva";514;2
"Unit";"Hydralisk";"Larva";514;2
"Unit";"Hydralisk";"Larva";514;2
"Unit";"Hydralisk";"Larva";514;2
"Unit";"Hydralisk";"Larva";514;2
"Unit";"Hydralisk";"Larva";514;2
"Unit";"Hydralisk";"Larva";514;2
"Unit";"Hydralisk";"Larva";514;2
"Building";"CreepTumor";NA;524;0
"Building";"SpineCrawler";NA;514;0
"Building";"SpineCrawler";NA;514;0
"Building";"CreepTumor";NA;546;0
"Building";"CreepTumor";NA;546;0
"Building";"CreepTumorQueen";NA;546;0
"Building";"CreepTumorQueen";NA;546;0
"Unit";"Viper";"Larva";546;3
"Unit";"Viper";"Larva";546;3
"Unit";"Viper";"Larva";546;3
"Unit";"Viper";"Larva";546;3
"Building";"CreepTumorQueen";NA;546;0
"Building";"SpineCrawler";NA;546;0
"Building";"SpineCrawler";NA;546;0
