"type";"unit_name";"on_building";"total_supply";"supply"
"Building";"Extractor";NA;13;0
"Unit";"Overlord";"Larva";16;0
"Building";"SpawningPool";NA;15;0
"Unit";"Zergling";"Larva";17;1
"Unit";"Zergling";"Larva";17;1
"Unit";"Queen";"Hatchery";17;2
"Unit";"Zergling";"Larva";21;1
"Unit";"Zergling";"Larva";21;1
"Unit";"Zergling";"Larva";21;1
"Unit";"Zergling";"Larva";21;1
"Unit";"Zergling";"Larva";25;1
"Unit";"Zergling";"Larva";25;1
"Unit";"Overlord";"Larva";25;0
"Unit";"Overlord";"Larva";29;0
"Building";"Hatchery";NA;21;0
"Unit";"Queen";"Hatchery";29;2
"Building";"CreepTumorQueen";NA;33;0
"Unit";"Queen";"Hatchery";35;2
"Building";"CreepTumor";NA;45;0
"Building";"CreepTumorQueen";NA;45;0
"Unit";"Queen";"Hatchery";43;2
"Unit";"Overlord";"Larva";50;0
"Building";"CreepTumorQueen";NA;54;0
"Unit";"Overlord";"Larva";54;0
"Unit";"Overlord";"Larva";54;0
"Building";"CreepTumor";NA;54;0
"Building";"CreepTumor";NA;54;0
"Building";"CreepTumorQueen";NA;54;0
"Building";"Extractor";NA;54;0
"Building";"Extractor";NA;54;0
"Building";"Hatchery";NA;43;0
"Building";"RoachWarren";NA;54;0
"Building";"EvolutionChamber";NA;57;0
"Unit";"Overlord";"Larva";60;0
"Building";"CreepTumor";NA;62;0
"Building";"CreepTumor";NA;62;0
"Building";"CreepTumor";NA;67;0
"Building";"CreepTumorQueen";NA;69;0
"Unit";"Overlord";"Larva";67;0
"Unit";"Queen";"Hatchery";60;2
"Unit";"Roach";"Larva";69;2
"Unit";"Roach";"Larva";69;2
"Unit";"Roach";"Larva";69;2
"Unit";"Roach";"Larva";69;2
"Building";"CreepTumor";NA;71;0
"Building";"SporeCrawler";NA;69;0
"Building";"SporeCrawler";NA;69;0
"Building";"CreepTumor";NA;79;0
"Building";"CreepTumor";NA;80;0
"Building";"CreepTumor";NA;81;0
"Building";"CreepTumorQueen";NA;84;0
"Building";"SporeCrawler";NA;79;0
"Building";"CreepTumorQueen";NA;84;0
"Unit";"Roach";"Larva";81;2
"Unit";"Roach";"Larva";81;2
"Unit";"Roach";"Larva";81;2
"Unit";"Roach";"Larva";81;2
"Unit";"Roach";"Larva";81;2
"Unit";"Roach";"Larva";81;2
"Unit";"Overlord";"Larva";84;0
"Unit";"Overlord";"Larva";84;0
"Unit";"Zergling";"Larva";84;1
"Unit";"Zergling";"Larva";84;1
"Unit";"Zergling";"Larva";84;1
"Unit";"Zergling";"Larva";84;1
"Unit";"Zergling";"Larva";84;1
"Unit";"Zergling";"Larva";84;1
"Unit";"Zergling";"Larva";84;1
"Unit";"Zergling";"Larva";84;1
"Unit";"Zergling";"Larva";84;1
"Unit";"Zergling";"Larva";84;1
"Unit";"Zergling";"Larva";84;1
"Unit";"Zergling";"Larva";84;1
"Building";"CreepTumor";NA;96;0
"Building";"CreepTumor";NA;96;0
"Building";"CreepTumor";NA;106;0
"Building";"CreepTumor";NA;108;0
"Building";"CreepTumor";NA;108;0
"Building";"CreepTumor";NA;112;0
"Building";"CreepTumorQueen";NA;120;0
"Building";"CreepTumorQueen";NA;120;0
"Unit";"Overlord";"Larva";112;0
"Unit";"Overlord";"Larva";112;0
"Unit";"Overlord";"Larva";112;0
"Building";"BanelingNest";NA;96;0
"Building";"CreepTumorQueen";NA;120;0
"Unit";"Zergling";"Larva";120;1
"Unit";"Zergling";"Larva";120;1
"Unit";"Zergling";"Larva";120;1
"Unit";"Zergling";"Larva";120;1
"Unit";"Zergling";"Larva";120;1
"Unit";"Zergling";"Larva";120;1
"Unit";"Zergling";"Larva";120;1
"Unit";"Zergling";"Larva";120;1
"Unit";"Zergling";"Larva";120;1
"Unit";"Zergling";"Larva";120;1
"Unit";"Zergling";"Larva";120;1
"Unit";"Zergling";"Larva";120;1
"Unit";"Zergling";"Larva";120;1
"Unit";"Zergling";"Larva";120;1
"Upgrade";"ZergMissileWeaponsLevel1";"EvolutionChamber";81;0
"Building";"CreepTumor";NA;120;0
"Unit";"Overlord";"Larva";120;0
"Unit";"Roach";"Larva";120;2
"Unit";"Roach";"Larva";120;2
"Unit";"Roach";"Larva";120;2
"Upgrade";"GlialReconstitution";"RoachWarren";112;0
"Unit";"Roach";"Larva";134;2
"Building";"CreepTumor";NA;140;0
"Building";"CreepTumor";NA;140;0
"Building";"CreepTumor";NA;140;0
"Unit";"Roach";"Larva";134;2
"Unit";"Roach";"Larva";134;2
"Unit";"Roach";"Larva";134;2
"Building";"Extractor";NA;134;0
"Unit";"Roach";"Larva";134;2
"Building";"CreepTumorQueen";NA;146;0
"Building";"CreepTumor";NA;146;0
"Unit";"Roach";"Larva";144;2
"Unit";"Roach";"Larva";146;2
"Unit";"Roach";"Larva";146;2
"Unit";"Zergling";"Larva";146;1
"Unit";"Zergling";"Larva";146;1
"Building";"CreepTumor";NA;154;0
"Unit";"Overlord";"Larva";148;0
"Building";"CreepTumorQueen";NA;154;0
"Unit";"Overlord";"Larva";152;0
"Unit";"Overlord";"Larva";152;0
"Building";"CreepTumor";NA;154;0
"Building";"CreepTumor";NA;156;0
"Unit";"Baneling";"Zergling";162;0
"Unit";"Baneling";"Zergling";162;0
"Unit";"Baneling";"Zergling";162;0
"Unit";"Baneling";"Zergling";162;0
"Unit";"Baneling";"Zergling";162;0
"Unit";"Baneling";"Zergling";162;0
"Unit";"Baneling";"Zergling";162;0
"Unit";"Baneling";"Zergling";162;0
"Unit";"Zergling";"Larva";162;1
"Unit";"Zergling";"Larva";162;1
"Unit";"Zergling";"Larva";162;1
"Unit";"Zergling";"Larva";162;1
"Unit";"Zergling";"Larva";162;1
"Unit";"Zergling";"Larva";162;1
"Unit";"Zergling";"Larva";162;1
"Unit";"Zergling";"Larva";162;1
"Unit";"Zergling";"Larva";162;1
"Unit";"Zergling";"Larva";162;1
"Unit";"Zergling";"Larva";162;1
"Unit";"Zergling";"Larva";162;1
"Unit";"Zergling";"Larva";162;1
"Unit";"Zergling";"Larva";162;1
"Unit";"Zergling";"Larva";162;1
"Unit";"Zergling";"Larva";162;1
"Unit";"Zergling";"Larva";162;1
"Unit";"Zergling";"Larva";162;1
"Unit";"Zergling";"Larva";162;1
"Unit";"Zergling";"Larva";162;1
"Unit";"Zergling";"Larva";162;1
"Unit";"Zergling";"Larva";162;1
"Unit";"Zergling";"Larva";184;1
"Unit";"Zergling";"Larva";184;1
"Unit";"Zergling";"Larva";184;1
"Unit";"Zergling";"Larva";184;1
"Unit";"Zergling";"Larva";184;1
"Unit";"Zergling";"Larva";184;1
"Unit";"Zergling";"Larva";184;1
"Unit";"Zergling";"Larva";184;1
"Unit";"Zergling";"Larva";184;1
"Unit";"Zergling";"Larva";184;1
"Unit";"Zergling";"Larva";184;1
"Unit";"Zergling";"Larva";184;1
"Unit";"Zergling";"Larva";184;1
"Unit";"Zergling";"Larva";184;1
"Unit";"Zergling";"Larva";184;1
"Unit";"Zergling";"Larva";184;1
"Unit";"Zergling";"Larva";184;1
"Unit";"Zergling";"Larva";184;1
"Unit";"Baneling";"Zergling";184;0
"Unit";"Baneling";"Zergling";184;0
"Unit";"Baneling";"Zergling";184;0
"Unit";"Baneling";"Zergling";184;0
"Unit";"Baneling";"Zergling";184;0
"Unit";"Baneling";"Zergling";184;0
"Unit";"Baneling";"Zergling";184;0
"Unit";"Baneling";"Zergling";184;0
"Unit";"Baneling";"Zergling";184;0
"Unit";"Baneling";"Zergling";184;0
"Unit";"Baneling";"Zergling";184;0
"Unit";"Baneling";"Zergling";184;0
"Unit";"Baneling";"Zergling";184;0
"Unit";"Baneling";"Zergling";184;0
"Unit";"Baneling";"Zergling";184;0
"Building";"CreepTumor";NA;184;0
"Unit";"Zergling";"Larva";184;1
"Unit";"Zergling";"Larva";184;1
"Unit";"Zergling";"Larva";184;1
"Unit";"Zergling";"Larva";184;1
"Unit";"Zergling";"Larva";184;1
"Unit";"Zergling";"Larva";184;1
"Unit";"Zergling";"Larva";184;1
"Unit";"Zergling";"Larva";184;1
"Unit";"Zergling";"Larva";184;1
"Unit";"Zergling";"Larva";184;1
"Building";"CreepTumorQueen";NA;202;0
"Building";"CreepTumor";NA;202;0
"Building";"CreepTumor";NA;202;0
"Building";"CreepTumorQueen";NA;212;0
"Unit";"Zergling";"Larva";212;1
"Unit";"Zergling";"Larva";212;1
"Unit";"Zergling";"Larva";212;1
"Unit";"Zergling";"Larva";212;1
"Unit";"Zergling";"Larva";212;1
"Unit";"Zergling";"Larva";212;1
"Unit";"Zergling";"Larva";212;1
"Unit";"Zergling";"Larva";212;1
"Unit";"Zergling";"Larva";212;1
"Unit";"Zergling";"Larva";212;1
"Unit";"Zergling";"Larva";212;1
"Unit";"Zergling";"Larva";212;1
"Unit";"Zergling";"Larva";212;1
"Unit";"Zergling";"Larva";212;1
"Unit";"Zergling";"Larva";212;1
"Unit";"Zergling";"Larva";212;1
"Unit";"Zergling";"Larva";212;1
"Unit";"Zergling";"Larva";212;1
"Building";"EvolutionChamber";NA;212;0
"Unit";"Roach";"Larva";230;2
"Unit";"Roach";"Larva";230;2
"Unit";"Roach";"Larva";230;2
"Unit";"Roach";"Larva";230;2
"Unit";"Roach";"Larva";230;2
"Unit";"Roach";"Larva";230;2
"Unit";"Roach";"Larva";230;2
"Unit";"Roach";"Larva";230;2
"Unit";"Roach";"Larva";230;2
"Building";"Hatchery";NA;184;0
"Building";"CreepTumorQueen";NA;248;0
"Building";"CreepTumor";NA;248;0
"Building";"Hatchery";NA;202;0
"Building";"CreepTumor";NA;248;0
"Building";"CreepTumor";NA;248;0
"Building";"CreepTumor";NA;248;0
"Building";"CreepTumor";NA;256;0
"Building";"CreepTumor";NA;256;0
"Building";"CreepTumorQueen";NA;264;0
"Building";"CreepTumor";NA;261;0
"Building";"CreepTumorQueen";NA;268;0
"Unit";"Roach";"Larva";256;2
"Unit";"Roach";"Larva";256;2
"Unit";"Roach";"Larva";256;2
"Unit";"Overlord";"Larva";256;0
"Unit";"Overlord";"Larva";256;0
"Building";"CreepTumorQueen";NA;268;0
"Building";"CreepTumor";NA;268;0
"Building";"CreepTumorQueen";NA;268;0
"Building";"CreepTumor";NA;268;0
"Building";"CreepTumorQueen";NA;268;0
"Unit";"Roach";"Larva";268;2
"Unit";"Roach";"Larva";268;2
"Unit";"Roach";"Larva";268;2
"Unit";"Roach";"Larva";268;2
"Unit";"Queen";"Hatchery";268;2
"Unit";"Roach";"Larva";274;2
"Unit";"Roach";"Larva";274;2
"Unit";"Roach";"Larva";274;2
"Unit";"Roach";"Larva";274;2
"Unit";"Roach";"Larva";274;2
"Unit";"Roach";"Larva";274;2
"Unit";"Roach";"Larva";274;2
"Unit";"Roach";"Larva";274;2
"Unit";"Roach";"Larva";274;2
"Unit";"Roach";"Larva";274;2
"Building";"CreepTumor";NA;282;0
"Building";"CreepTumor";NA;283;0
"Building";"Extractor";NA;282;0
"Building";"CreepTumor";NA;283;0
"Building";"CreepTumor";NA;285;0
"Building";"Extractor";NA;282;0
"Building";"HydraliskDen";NA;274;0
"Building";"CreepTumor";NA;305;0
"Building";"CreepTumor";NA;305;0
"Unit";"Zergling";"Larva";308;1
"Unit";"Zergling";"Larva";308;1
"Unit";"Zergling";"Larva";308;1
"Unit";"Zergling";"Larva";308;1
"Unit";"Zergling";"Larva";308;1
"Unit";"Zergling";"Larva";308;1
"Unit";"Zergling";"Larva";308;1
"Unit";"Zergling";"Larva";308;1
"Unit";"Zergling";"Larva";308;1
"Unit";"Zergling";"Larva";308;1
"Unit";"Zergling";"Larva";308;1
"Unit";"Zergling";"Larva";308;1
"Unit";"Zergling";"Larva";308;1
"Unit";"Zergling";"Larva";308;1
"Unit";"Zergling";"Larva";308;1
"Unit";"Zergling";"Larva";308;1
"Unit";"Zergling";"Larva";308;1
"Unit";"Zergling";"Larva";308;1
"Unit";"Zergling";"Larva";308;1
"Unit";"Zergling";"Larva";308;1
"Upgrade";"ZergGroundArmorsLevel1";"EvolutionChamber";256;0
"Unit";"Zergling";"Larva";308;1
"Unit";"Zergling";"Larva";308;1
"Unit";"Zergling";"Larva";308;1
"Unit";"Zergling";"Larva";308;1
"Unit";"Zergling";"Larva";308;1
"Unit";"Zergling";"Larva";308;1
"Unit";"Zergling";"Larva";308;1
"Unit";"Zergling";"Larva";308;1
"Unit";"Zergling";"Larva";308;1
"Unit";"Zergling";"Larva";308;1
"Unit";"Overlord";"Larva";328;0
"Unit";"Overlord";"Larva";328;0
"Unit";"Overlord";"Larva";328;0
"Building";"InfestationPit";NA;308;0
"Upgrade";"ZergMissileWeaponsLevel2";"EvolutionChamber";256;0
"Unit";"Baneling";"Zergling";338;0
"Unit";"Baneling";"Zergling";338;0
"Unit";"Baneling";"Zergling";338;0
"Unit";"Baneling";"Zergling";338;0
"Unit";"Baneling";"Zergling";338;0
"Unit";"Baneling";"Zergling";338;0
"Unit";"Baneling";"Zergling";338;0
"Unit";"Baneling";"Zergling";338;0
"Unit";"Baneling";"Zergling";338;0
"Unit";"Zergling";"Larva";338;1
"Unit";"Zergling";"Larva";338;1
"Unit";"Baneling";"Zergling";338;0
"Unit";"Baneling";"Zergling";338;0
"Unit";"Baneling";"Zergling";338;0
"Unit";"Baneling";"Zergling";338;0
"Unit";"Baneling";"Zergling";338;0
"Unit";"Baneling";"Zergling";338;0
"Unit";"Baneling";"Zergling";338;0
"Unit";"Baneling";"Zergling";338;0
"Unit";"Baneling";"Zergling";338;0
"Unit";"Baneling";"Zergling";338;0
"Unit";"Baneling";"Zergling";338;0
"Unit";"Zergling";"Larva";338;1
"Unit";"Zergling";"Larva";338;1
"Unit";"Zergling";"Larva";338;1
"Unit";"Zergling";"Larva";338;1
"Unit";"Zergling";"Larva";338;1
"Unit";"Zergling";"Larva";338;1
"Unit";"Zergling";"Larva";338;1
"Unit";"Zergling";"Larva";338;1
"Unit";"Zergling";"Larva";338;1
"Unit";"Zergling";"Larva";338;1
"Unit";"Zergling";"Larva";338;1
"Unit";"Zergling";"Larva";338;1
"Unit";"Zergling";"Larva";338;1
"Unit";"Zergling";"Larva";338;1
"Unit";"Zergling";"Larva";338;1
"Unit";"Zergling";"Larva";338;1
"Unit";"Zergling";"Larva";338;1
"Unit";"Zergling";"Larva";338;1
"Unit";"Zergling";"Larva";338;1
"Unit";"Zergling";"Larva";338;1
"Unit";"Zergling";"Larva";338;1
"Unit";"Zergling";"Larva";338;1
"Unit";"Zergling";"Larva";338;1
"Unit";"Zergling";"Larva";338;1
"Unit";"Zergling";"Larva";338;1
"Unit";"Zergling";"Larva";338;1
"Unit";"Zergling";"Larva";338;1
"Unit";"Zergling";"Larva";338;1
"Building";"CreepTumor";NA;338;0
"Building";"CreepTumor";NA;338;0
"Building";"CreepTumor";NA;338;0
"Building";"CreepTumor";NA;338;0
"Building";"CreepTumorQueen";NA;368;0
"Building";"CreepTumorQueen";NA;368;0
"Building";"SpineCrawler";NA;338;0
"Building";"CreepTumorQueen";NA;368;0
"Unit";"Zergling";"Larva";368;1
"Unit";"Zergling";"Larva";368;1
"Unit";"Zergling";"Larva";368;1
"Unit";"Zergling";"Larva";368;1
"Unit";"Zergling";"Larva";368;1
"Unit";"Zergling";"Larva";368;1
"Unit";"Zergling";"Larva";368;1
"Unit";"Zergling";"Larva";368;1
"Unit";"Zergling";"Larva";368;1
"Unit";"Zergling";"Larva";368;1
"Unit";"Zergling";"Larva";368;1
"Unit";"Zergling";"Larva";368;1
"Unit";"Zergling";"Larva";368;1
"Unit";"Zergling";"Larva";368;1
"Unit";"Zergling";"Larva";368;1
"Unit";"Zergling";"Larva";368;1
"Building";"Extractor";NA;368;0
"Building";"Extractor";NA;368;0
"Building";"CreepTumorQueen";NA;368;0
"Unit";"Zergling";"Larva";384;1
"Unit";"Zergling";"Larva";384;1
"Unit";"Zergling";"Larva";384;1
"Unit";"Zergling";"Larva";384;1
"Unit";"Zergling";"Larva";384;1
"Unit";"Zergling";"Larva";384;1
"Unit";"Zergling";"Larva";384;1
"Unit";"Zergling";"Larva";384;1
"Unit";"Zergling";"Larva";384;1
"Unit";"Zergling";"Larva";384;1
"Unit";"Zergling";"Larva";384;1
"Unit";"Zergling";"Larva";384;1
"Unit";"Zergling";"Larva";384;1
"Unit";"Zergling";"Larva";384;1
"Unit";"Zergling";"Larva";384;1
"Unit";"Zergling";"Larva";384;1
"Unit";"Zergling";"Larva";384;1
"Unit";"Zergling";"Larva";384;1
"Unit";"Zergling";"Larva";384;1
"Unit";"Zergling";"Larva";384;1
"Unit";"Zergling";"Larva";384;1
"Unit";"Zergling";"Larva";384;1
"Unit";"Zergling";"Larva";384;1
"Unit";"Zergling";"Larva";384;1
"Unit";"Zergling";"Larva";384;1
"Unit";"Zergling";"Larva";384;1
"Unit";"Zergling";"Larva";384;1
"Unit";"Zergling";"Larva";384;1
"Unit";"Zergling";"Larva";384;1
"Unit";"Zergling";"Larva";384;1
"Unit";"Zergling";"Larva";384;1
"Unit";"Zergling";"Larva";384;1
"Unit";"Zergling";"Larva";384;1
"Unit";"Zergling";"Larva";384;1
"Unit";"Zergling";"Larva";384;1
"Unit";"Zergling";"Larva";384;1
"Unit";"Zergling";"Larva";384;1
"Unit";"Zergling";"Larva";384;1
"Unit";"Zergling";"Larva";384;1
"Unit";"Zergling";"Larva";384;1
"Unit";"Zergling";"Larva";384;1
"Unit";"Zergling";"Larva";384;1
"Unit";"Zergling";"Larva";384;1
"Unit";"Zergling";"Larva";384;1
"Unit";"Zergling";"Larva";384;1
"Unit";"Zergling";"Larva";384;1
"Unit";"Zergling";"Larva";384;1
"Unit";"Zergling";"Larva";384;1
"Unit";"Zergling";"Larva";384;1
"Unit";"Zergling";"Larva";384;1
"Unit";"Zergling";"Larva";384;1
"Unit";"Zergling";"Larva";384;1
"Unit";"Zergling";"Larva";384;1
"Unit";"Zergling";"Larva";384;1
"Unit";"Zergling";"Larva";384;1
"Unit";"Zergling";"Larva";384;1
"Building";"CreepTumorQueen";NA;440;0
"Building";"CreepTumor";NA;440;0
"Building";"UltraliskCavern";NA;440;0
"Building";"CreepTumor";NA;440;0
"Building";"CreepTumor";NA;440;0
"Unit";"Hydralisk";"Larva";440;2
"Building";"CreepTumor";NA;441;0
"Unit";"Hydralisk";"Larva";440;2
"Unit";"Hydralisk";"Larva";440;2
"Unit";"Hydralisk";"Larva";440;2
"Unit";"Hydralisk";"Larva";440;2
"Unit";"Hydralisk";"Larva";440;2
"Unit";"Hydralisk";"Larva";440;2
"Unit";"Hydralisk";"Larva";440;2
"Unit";"Hydralisk";"Larva";440;2
"Unit";"Hydralisk";"Larva";440;2
"Unit";"Hydralisk";"Larva";440;2
"Unit";"Hydralisk";"Larva";440;2
"Unit";"Hydralisk";"Larva";440;2
"Unit";"Hydralisk";"Larva";440;2
"Building";"EvolutionChamber";NA;440;0
"Building";"CreepTumor";NA;441;0
"Building";"CreepTumor";NA;441;0
"Building";"CreepTumor";NA;441;0
"Building";"CreepTumor";NA;441;0
"Building";"CreepTumor";NA;469;0
"Building";"CreepTumor";NA;469;0
"Unit";"Ultralisk";"Larva";443;6
"Unit";"Ultralisk";"Larva";447;6
"Unit";"Zergling";"Larva";469;1
"Unit";"Zergling";"Larva";469;1
"Unit";"Ultralisk";"Larva";455;6
"Unit";"Zergling";"Larva";469;1
"Unit";"Zergling";"Larva";469;1
"Unit";"Ultralisk";"Larva";463;6
"Unit";"Zergling";"Larva";469;1
"Unit";"Zergling";"Larva";469;1
"Upgrade";"EvolveGroovedSpines";"HydraliskDen";441;0
"Unit";"Ultralisk";"Larva";469;6
"Building";"CreepTumor";NA;469;0
"Unit";"Baneling";"Zergling";469;0
"Unit";"Baneling";"Zergling";469;0
"Unit";"Baneling";"Zergling";469;0
"Unit";"Baneling";"Zergling";469;0
"Unit";"Baneling";"Zergling";469;0
"Unit";"Baneling";"Zergling";469;0
"Unit";"Baneling";"Zergling";469;0
"Unit";"Baneling";"Zergling";469;0
"Unit";"Baneling";"Zergling";469;0
"Unit";"Baneling";"Zergling";469;0
"Unit";"Baneling";"Zergling";469;0
"Building";"CreepTumor";NA;469;0
"Unit";"Baneling";"Zergling";469;0
"Unit";"Baneling";"Zergling";469;0
"Unit";"Baneling";"Zergling";469;0
"Unit";"Baneling";"Zergling";469;0
"Unit";"Baneling";"Zergling";469;0
"Unit";"Baneling";"Zergling";469;0
"Unit";"Baneling";"Zergling";469;0
"Unit";"Baneling";"Zergling";469;0
"Unit";"Baneling";"Zergling";469;0
"Unit";"Baneling";"Zergling";469;0
"Unit";"Baneling";"Zergling";469;0
"Building";"CreepTumor";NA;469;0
"Upgrade";"ZergMeleeWeaponsLevel1";"EvolutionChamber";440;0
"Building";"SpineCrawler";NA;469;0
"Building";"SpineCrawler";NA;469;0
"Building";"CreepTumorQueen";NA;499;0
"Building";"SpineCrawler";NA;469;0
"Building";"CreepTumorQueen";NA;499;0
"Upgrade";"ZergGroundArmorsLevel2";"EvolutionChamber";440;0
"Building";"CreepTumorQueen";NA;499;0
"Upgrade";"ChitinousPlating";"UltraliskCavern";469;0
"Unit";"Zergling";"Larva";505;1
"Unit";"Zergling";"Larva";505;1
"Unit";"Zergling";"Larva";505;1
"Unit";"Zergling";"Larva";505;1
"Unit";"Zergling";"Larva";505;1
"Unit";"Zergling";"Larva";505;1
"Upgrade";"EvolveMuscularAugments";"HydraliskDen";505;0
"Unit";"Zergling";"Larva";511;1
"Unit";"Zergling";"Larva";511;1
"Unit";"Zergling";"Larva";511;1
"Unit";"Zergling";"Larva";511;1
"Unit";"Zergling";"Larva";511;1
"Unit";"Zergling";"Larva";511;1
"Unit";"Zergling";"Larva";511;1
"Unit";"Zergling";"Larva";511;1
"Unit";"Zergling";"Larva";511;1
"Unit";"Zergling";"Larva";511;1
"Unit";"Zergling";"Larva";511;1
"Unit";"Zergling";"Larva";511;1
"Unit";"Zergling";"Larva";511;1
"Unit";"Zergling";"Larva";511;1
"Unit";"Zergling";"Larva";511;1
"Unit";"Zergling";"Larva";511;1
"Unit";"Zergling";"Larva";511;1
"Unit";"Zergling";"Larva";511;1
"Unit";"Zergling";"Larva";511;1
"Unit";"Zergling";"Larva";511;1
"Unit";"Zergling";"Larva";511;1
"Unit";"Zergling";"Larva";511;1
"Unit";"Zergling";"Larva";511;1
"Unit";"Zergling";"Larva";511;1
"Unit";"Zergling";"Larva";511;1
"Unit";"Zergling";"Larva";511;1
"Unit";"Zergling";"Larva";511;1
"Unit";"Zergling";"Larva";511;1
"Unit";"Zergling";"Larva";511;1
"Unit";"Zergling";"Larva";511;1
"Unit";"Zergling";"Larva";511;1
"Unit";"Zergling";"Larva";511;1
"Unit";"Zergling";"Larva";511;1
"Unit";"Zergling";"Larva";511;1
"Unit";"Zergling";"Larva";511;1
"Unit";"Zergling";"Larva";511;1
"Unit";"Zergling";"Larva";511;1
"Unit";"Zergling";"Larva";511;1
"Unit";"Zergling";"Larva";511;1
"Unit";"Zergling";"Larva";511;1
"Unit";"Zergling";"Larva";511;1
"Unit";"Zergling";"Larva";511;1
"Unit";"Zergling";"Larva";511;1
"Unit";"Zergling";"Larva";511;1
"Unit";"Ultralisk";"Larva";511;6
"Unit";"Ultralisk";"Larva";511;6
"Unit";"Ultralisk";"Larva";511;6
"Unit";"Ultralisk";"Larva";511;6
"Unit";"Ultralisk";"Larva";511;6
"Unit";"Zergling";"Larva";585;1
"Unit";"Zergling";"Larva";585;1
"Unit";"Zergling";"Larva";585;1
"Unit";"Zergling";"Larva";585;1
"Unit";"Zergling";"Larva";585;1
"Unit";"Zergling";"Larva";585;1
"Unit";"Overlord";"Larva";585;0
"Unit";"Overlord";"Larva";585;0
"Upgrade";"ZergMissileWeaponsLevel3";"EvolutionChamber";505;0
"Upgrade";"ZergMeleeWeaponsLevel2";"EvolutionChamber";511;0
"Building";"Hatchery";NA;555;0
"Unit";"Zergling";"Larva";594;1
"Unit";"Zergling";"Larva";594;1
"Unit";"Zergling";"Larva";594;1
"Unit";"Zergling";"Larva";594;1
"Unit";"Zergling";"Larva";594;1
"Unit";"Zergling";"Larva";594;1
"Unit";"Zergling";"Larva";594;1
"Unit";"Zergling";"Larva";594;1
"Unit";"Zergling";"Larva";594;1
"Unit";"Zergling";"Larva";594;1
"Unit";"Zergling";"Larva";594;1
"Unit";"Zergling";"Larva";594;1
"Upgrade";"ZergGroundArmorsLevel3";"EvolutionChamber";511;0
"Building";"SpineCrawler";NA;594;0
"Building";"SpineCrawler";NA;594;0
"Building";"SpineCrawler";NA;594;0
"Unit";"Zergling";"Larva";594;1
"Unit";"Zergling";"Larva";594;1
"Unit";"Zergling";"Larva";594;1
"Unit";"Zergling";"Larva";594;1
"Unit";"Zergling";"Larva";594;1
"Unit";"Zergling";"Larva";594;1
"Unit";"Zergling";"Larva";594;1
"Unit";"Zergling";"Larva";594;1
"Unit";"Zergling";"Larva";594;1
"Unit";"Zergling";"Larva";594;1
"Unit";"Zergling";"Larva";594;1
"Unit";"Zergling";"Larva";594;1
"Unit";"Zergling";"Larva";594;1
"Unit";"Zergling";"Larva";594;1
"Unit";"Ultralisk";"Larva";594;6
"Unit";"Ultralisk";"Larva";594;6
"Unit";"Ultralisk";"Larva";594;6
"Unit";"Ultralisk";"Larva";594;6
"Unit";"Ultralisk";"Larva";594;6
"Unit";"Ultralisk";"Larva";594;6
"Unit";"Ultralisk";"Larva";594;6
"Unit";"Baneling";"Zergling";662;0
"Unit";"Baneling";"Zergling";662;0
"Unit";"Baneling";"Zergling";662;0
"Building";"Extractor";NA;606;0
"Unit";"Zergling";"Larva";662;1
"Unit";"Zergling";"Larva";662;1
"Unit";"Zergling";"Larva";662;1
"Unit";"Zergling";"Larva";662;1
"Unit";"Zergling";"Larva";662;1
"Unit";"Zergling";"Larva";662;1
"Unit";"Zergling";"Larva";662;1
"Unit";"Zergling";"Larva";662;1
"Unit";"Zergling";"Larva";662;1
"Unit";"Zergling";"Larva";662;1
"Building";"CreepTumor";NA;662;0
"Building";"CreepTumor";NA;662;0
"Building";"CreepTumor";NA;662;0
"Building";"CreepTumor";NA;662;0
"Building";"CreepTumor";NA;662;0
"Unit";"Queen";"Hatchery";662;2
"Unit";"Queen";"Hatchery";662;2
"Building";"Extractor";NA;662;0
"Building";"Hatchery";NA;662;0
"Building";"SpineCrawler";NA;662;0
