"type";"unit_name";"on_building";"total_supply";"supply"
"Unit";"Overlord";"Larva";12;0
"Building";"Extractor";NA;18;0
"Unit";"Overlord";"Larva";21;0
"Building";"SpawningPool";NA;19;0
"Building";"Hatchery";NA;17;0
"Unit";"Zergling";"Larva";22;1
"Unit";"Zergling";"Larva";22;1
"Unit";"Zergling";"Larva";22;1
"Unit";"Zergling";"Larva";22;1
"Unit";"Zergling";"Larva";22;1
"Unit";"Zergling";"Larva";22;1
"Unit";"Queen";"Hatchery";22;2
"Unit";"Queen";"Hatchery";22;2
"Unit";"Overlord";"Larva";37;0
"Unit";"Queen";"Hatchery";37;2
"Unit";"Overlord";"Larva";40;0
"Building";"CreepTumorQueen";NA;40;0
"Building";"Extractor";NA;48;0
"Building";"CreepTumor";NA;51;0
"Building";"CreepTumorQueen";NA;51;0
"Building";"Extractor";NA;51;0
"Unit";"Overlord";"Larva";51;0
"Unit";"Overlord";"Larva";51;0
"Building";"RoachWarren";NA;48;0
"Unit";"Overlord";"Larva";54;0
"Unit";"Roach";"Larva";54;2
"Unit";"Roach";"Larva";54;2
"Unit";"Roach";"Larva";54;2
"Unit";"Roach";"Larva";54;2
"Unit";"Roach";"Larva";54;2
"Unit";"Roach";"Larva";54;2
"Unit";"Roach";"Larva";54;2
"Unit";"Roach";"Larva";54;2
"Building";"CreepTumor";NA;54;0
"Building";"CreepTumor";NA;54;0
"Building";"Hatchery";NA;48;0
"Unit";"Roach";"Larva";54;2
"Unit";"Roach";"Larva";54;2
"Unit";"Zergling";"Larva";70;1
"Unit";"Zergling";"Larva";70;1
"Unit";"Roach";"Larva";66;2
"Unit";"Roach";"Larva";70;2
"Unit";"Roach";"Larva";70;2
"Unit";"Roach";"Larva";70;2
"Unit";"Zergling";"Larva";84;1
"Unit";"Zergling";"Larva";84;1
"Unit";"Roach";"Larva";84;2
"Unit";"Roach";"Larva";84;2
"Unit";"Roach";"Larva";84;2
"Unit";"Overlord";"Larva";84;0
"Unit";"Overlord";"Larva";84;0
"Unit";"Overlord";"Larva";103;0
"Unit";"Overlord";"Larva";103;0
"Unit";"Overlord";"Larva";103;0
"Unit";"Overlord";"Larva";103;0
"Unit";"Overlord";"Larva";103;0
"Unit";"Overlord";"Larva";103;0
"Unit";"Zergling";"Larva";103;1
"Unit";"Zergling";"Larva";103;1
"Unit";"Zergling";"Larva";103;1
"Unit";"Zergling";"Larva";103;1
"Unit";"Zergling";"Larva";103;1
"Unit";"Zergling";"Larva";103;1
"Unit";"Zergling";"Larva";103;1
"Unit";"Zergling";"Larva";103;1
"Unit";"Zergling";"Larva";103;1
"Unit";"Zergling";"Larva";103;1
"Unit";"Zergling";"Larva";103;1
"Unit";"Zergling";"Larva";103;1
"Unit";"Zergling";"Larva";103;1
"Unit";"Zergling";"Larva";103;1
"Unit";"Zergling";"Larva";103;1
"Unit";"Zergling";"Larva";103;1
"Unit";"Roach";"Larva";120;2
"Unit";"Roach";"Larva";120;2
"Unit";"Roach";"Larva";120;2
"Unit";"Roach";"Larva";120;2
"Unit";"Roach";"Larva";120;2
"Unit";"Roach";"Larva";120;2
"Unit";"Roach";"Larva";120;2
"Unit";"Roach";"Larva";120;2
"Unit";"Zergling";"Larva";120;1
"Unit";"Zergling";"Larva";120;1
"Unit";"Zergling";"Larva";120;1
"Unit";"Zergling";"Larva";120;1
"Unit";"Zergling";"Larva";120;1
"Unit";"Zergling";"Larva";120;1
"Unit";"Zergling";"Larva";120;1
"Unit";"Zergling";"Larva";120;1
"Unit";"Zergling";"Larva";120;1
"Unit";"Zergling";"Larva";120;1
"Unit";"Roach";"Larva";142;2
"Unit";"Roach";"Larva";146;2
"Unit";"Roach";"Larva";146;2
"Unit";"Roach";"Larva";146;2
"Unit";"Roach";"Larva";146;2
"Unit";"Roach";"Larva";146;2
"Unit";"Roach";"Larva";146;2
"Unit";"Roach";"Larva";146;2
"Unit";"Roach";"Larva";146;2
"Building";"Extractor";NA;146;0
"Unit";"Zergling";"Larva";173;1
"Unit";"Zergling";"Larva";173;1
"Unit";"Zergling";"Larva";173;1
"Unit";"Zergling";"Larva";173;1
"Unit";"Zergling";"Larva";173;1
"Unit";"Zergling";"Larva";173;1
"Unit";"Zergling";"Larva";173;1
"Unit";"Zergling";"Larva";173;1
"Unit";"Roach";"Larva";173;2
"Unit";"Roach";"Larva";173;2
"Unit";"Roach";"Larva";173;2
"Unit";"Roach";"Larva";173;2
"Unit";"Roach";"Larva";173;2
"Unit";"Roach";"Larva";173;2
"Unit";"Roach";"Larva";173;2
"Unit";"Roach";"Larva";173;2
"Unit";"Zergling";"Larva";173;1
"Unit";"Zergling";"Larva";173;1
"Unit";"Zergling";"Larva";173;1
"Unit";"Zergling";"Larva";173;1
"Unit";"Zergling";"Larva";173;1
"Unit";"Zergling";"Larva";173;1
"Building";"Extractor";NA;197;0
"Unit";"Zergling";"Larva";206;1
"Unit";"Zergling";"Larva";206;1
"Unit";"Zergling";"Larva";206;1
"Unit";"Zergling";"Larva";206;1
"Unit";"Zergling";"Larva";206;1
"Unit";"Zergling";"Larva";206;1
"Unit";"Zergling";"Larva";206;1
"Unit";"Zergling";"Larva";206;1
"Unit";"Zergling";"Larva";206;1
"Unit";"Zergling";"Larva";206;1
"Unit";"Zergling";"Larva";206;1
"Unit";"Zergling";"Larva";206;1
"Unit";"Zergling";"Larva";206;1
"Unit";"Zergling";"Larva";206;1
"Unit";"Zergling";"Larva";206;1
"Unit";"Zergling";"Larva";206;1
"Unit";"Zergling";"Larva";206;1
"Unit";"Zergling";"Larva";206;1
"Building";"Extractor";NA;206;0
"Building";"EvolutionChamber";NA;207;0
"Unit";"Zergling";"Larva";227;1
"Unit";"Zergling";"Larva";227;1
"Unit";"Zergling";"Larva";227;1
"Unit";"Zergling";"Larva";227;1
"Unit";"Zergling";"Larva";227;1
"Unit";"Zergling";"Larva";227;1
"Unit";"Zergling";"Larva";227;1
"Unit";"Zergling";"Larva";227;1
"Unit";"Zergling";"Larva";227;1
"Unit";"Zergling";"Larva";227;1
"Unit";"Zergling";"Larva";227;1
"Unit";"Zergling";"Larva";227;1
"Unit";"Zergling";"Larva";227;1
"Unit";"Zergling";"Larva";227;1
"Unit";"Zergling";"Larva";227;1
"Unit";"Zergling";"Larva";227;1
"Unit";"Overlord";"Larva";227;0
"Unit";"Overlord";"Larva";227;0
"Unit";"Overlord";"Larva";227;0
"Unit";"Overlord";"Larva";227;0
"Unit";"Overlord";"Larva";227;0
"Building";"HydraliskDen";NA;243;0
"Unit";"Zergling";"Larva";243;1
"Unit";"Zergling";"Larva";243;1
"Unit";"Zergling";"Larva";243;1
"Unit";"Zergling";"Larva";243;1
"Unit";"Zergling";"Larva";243;1
"Unit";"Zergling";"Larva";243;1
"Unit";"Zergling";"Larva";243;1
"Unit";"Zergling";"Larva";243;1
"Unit";"Zergling";"Larva";243;1
"Unit";"Zergling";"Larva";243;1
"Unit";"Zergling";"Larva";243;1
"Unit";"Zergling";"Larva";243;1
"Unit";"Zergling";"Larva";243;1
"Unit";"Zergling";"Larva";243;1
"Unit";"Zergling";"Larva";243;1
"Unit";"Zergling";"Larva";243;1
"Unit";"Zergling";"Larva";243;1
"Unit";"Zergling";"Larva";243;1
"Unit";"Zergling";"Larva";243;1
"Unit";"Zergling";"Larva";243;1
"Unit";"Zergling";"Larva";243;1
"Unit";"Zergling";"Larva";243;1
"Building";"BanelingNest";NA;243;0
"Building";"CreepTumor";NA;271;0
"Building";"CreepTumor";NA;271;0
"Unit";"Zergling";"Larva";271;1
"Unit";"Zergling";"Larva";271;1
"Unit";"Zergling";"Larva";271;1
"Unit";"Zergling";"Larva";271;1
"Unit";"Zergling";"Larva";271;1
"Unit";"Zergling";"Larva";271;1
"Building";"CreepTumorQueen";NA;271;0
"Unit";"Hydralisk";"Larva";271;2
"Unit";"Hydralisk";"Larva";271;2
"Unit";"Hydralisk";"Larva";271;2
"Unit";"Overlord";"Larva";271;0
"Unit";"Overlord";"Larva";271;0
"Unit";"Overlord";"Larva";271;0
"Unit";"Baneling";"Zergling";277;0
"Unit";"Baneling";"Zergling";277;0
"Unit";"Baneling";"Zergling";277;0
"Unit";"Baneling";"Zergling";283;0
"Unit";"Baneling";"Zergling";283;0
"Upgrade";"GlialReconstitution";"RoachWarren";249;0
"Unit";"Hydralisk";"Larva";277;2
"Unit";"Hydralisk";"Larva";277;2
"Unit";"Hydralisk";"Larva";277;2
"Unit";"Zergling";"Larva";283;1
"Unit";"Zergling";"Larva";283;1
"Unit";"Zergling";"Larva";283;1
"Unit";"Zergling";"Larva";283;1
"Unit";"Zergling";"Larva";283;1
"Unit";"Zergling";"Larva";283;1
"Unit";"Zergling";"Larva";283;1
"Unit";"Zergling";"Larva";283;1
"Unit";"Queen";"Hatchery";271;2
"Unit";"Queen";"Hatchery";271;2
"Upgrade";"ZergMissileWeaponsLevel1";"EvolutionChamber";243;0
"Building";"CreepTumor";NA;295;0
"Unit";"Zergling";"Larva";283;1
"Unit";"Zergling";"Larva";283;1
"Unit";"Zergling";"Larva";283;1
"Unit";"Zergling";"Larva";283;1
"Unit";"Zergling";"Larva";283;1
"Unit";"Zergling";"Larva";283;1
"Unit";"Zergling";"Larva";283;1
"Unit";"Zergling";"Larva";283;1
"Unit";"Zergling";"Larva";283;1
"Unit";"Zergling";"Larva";283;1
"Unit";"Zergling";"Larva";283;1
"Unit";"Zergling";"Larva";283;1
"Unit";"Zergling";"Larva";283;1
"Unit";"Zergling";"Larva";283;1
"Unit";"Zergling";"Larva";283;1
"Unit";"Zergling";"Larva";283;1
"Building";"CreepTumor";NA;297;0
"Building";"Hatchery";NA;249;0
"Upgrade";"EvolveGroovedSpines";"HydraliskDen";277;0
"Unit";"Hydralisk";"Larva";301;2
"Unit";"Hydralisk";"Larva";301;2
"Unit";"Hydralisk";"Larva";301;2
"Unit";"Hydralisk";"Larva";323;2
"Unit";"Hydralisk";"Larva";323;2
"Unit";"Hydralisk";"Larva";323;2
"Unit";"Hydralisk";"Larva";323;2
"Unit";"Hydralisk";"Larva";323;2
"Unit";"Hydralisk";"Larva";323;2
"Unit";"Hydralisk";"Larva";323;2
"Unit";"Hydralisk";"Larva";323;2
"Unit";"Hydralisk";"Larva";323;2
"Unit";"Hydralisk";"Larva";323;2
"Unit";"Hydralisk";"Larva";323;2
"Building";"CreepTumor";NA;323;0
"Building";"CreepTumor";NA;323;0
"Unit";"Zergling";"Larva";323;1
"Unit";"Zergling";"Larva";323;1
"Unit";"Zergling";"Larva";323;1
"Unit";"Zergling";"Larva";323;1
"Unit";"Hydralisk";"Larva";323;2
"Unit";"Hydralisk";"Larva";323;2
"Unit";"Hydralisk";"Larva";323;2
"Unit";"Hydralisk";"Larva";323;2
"Unit";"Hydralisk";"Larva";323;2
"Unit";"Hydralisk";"Larva";323;2
"Unit";"Hydralisk";"Larva";323;2
"Unit";"Hydralisk";"Larva";323;2
"Unit";"Zergling";"Larva";345;1
"Unit";"Zergling";"Larva";345;1
"Unit";"Zergling";"Larva";345;1
"Unit";"Zergling";"Larva";345;1
"Unit";"Zergling";"Larva";345;1
"Unit";"Zergling";"Larva";345;1
"Unit";"Zergling";"Larva";359;1
"Unit";"Zergling";"Larva";359;1
"Unit";"Zergling";"Larva";359;1
"Unit";"Zergling";"Larva";359;1
"Building";"CreepTumor";NA;373;0
"Unit";"Hydralisk";"Larva";359;2
"Upgrade";"EvolveMuscularAugments";"HydraliskDen";323;0
"Unit";"Baneling";"Zergling";373;0
"Unit";"Baneling";"Zergling";373;0
"Unit";"Zergling";"Larva";373;1
"Unit";"Zergling";"Larva";373;1
"Unit";"Baneling";"Zergling";373;0
"Unit";"Baneling";"Zergling";373;0
"Unit";"Zergling";"Larva";373;1
"Unit";"Zergling";"Larva";373;1
"Unit";"Zergling";"Larva";373;1
"Unit";"Zergling";"Larva";373;1
"Unit";"Zergling";"Larva";373;1
"Unit";"Zergling";"Larva";373;1
"Unit";"Zergling";"Larva";373;1
"Unit";"Zergling";"Larva";373;1
"Unit";"Zergling";"Larva";373;1
"Unit";"Zergling";"Larva";373;1
"Unit";"Zergling";"Larva";373;1
"Unit";"Zergling";"Larva";373;1
"Unit";"Zergling";"Larva";373;1
"Unit";"Zergling";"Larva";373;1
"Unit";"Zergling";"Larva";373;1
"Unit";"Zergling";"Larva";373;1
"Unit";"Zergling";"Larva";373;1
"Unit";"Zergling";"Larva";373;1
"Unit";"Zergling";"Larva";373;1
"Unit";"Zergling";"Larva";373;1
