"type";"unit_name";"on_building";"total_supply";"supply"
"Unit";"Overlord";"Larva";13;0
"Building";"SpawningPool";NA;16;0
"Unit";"Zergling";"Larva";20;1
"Unit";"Zergling";"Larva";20;1
"Unit";"Zergling";"Larva";20;1
"Unit";"Zergling";"Larva";20;1
"Unit";"Zergling";"Larva";20;1
"Unit";"Zergling";"Larva";20;1
"Unit";"Overlord";"Larva";20;0
"Unit";"Queen";"Hatchery";20;2
"Unit";"Overlord";"Larva";26;0
"Building";"Hatchery";NA;20;0
"Building";"Extractor";NA;29;0
"Unit";"Queen";"Hatchery";26;2
"Unit";"Overlord";"Larva";31;0
"Unit";"Queen";"Hatchery";31;2
"Unit";"Queen";"Hatchery";31;2
"Building";"CreepTumorQueen";NA;46;0
"Building";"CreepTumorQueen";NA;46;0
"Building";"CreepTumor";NA;54;0
"Unit";"Zergling";"Larva";52;1
"Unit";"Zergling";"Larva";52;1
"Building";"CreepTumor";NA;54;0
"Unit";"Zergling";"Larva";52;1
"Unit";"Zergling";"Larva";52;1
"Unit";"Zergling";"Larva";52;1
"Unit";"Zergling";"Larva";52;1
"Unit";"Overlord";"Larva";54;0
"Building";"SporeCrawler";NA;61;0
"Building";"SporeCrawler";NA;61;0
"Unit";"Zergling";"Larva";65;1
"Unit";"Zergling";"Larva";65;1
"Unit";"Zergling";"Larva";65;1
"Unit";"Zergling";"Larva";65;1
"Building";"Hatchery";NA;44;0
"Building";"CreepTumor";NA;66;0
"Building";"SporeCrawler";NA;65;0
"Unit";"Zergling";"Larva";66;1
"Unit";"Zergling";"Larva";66;1
"Unit";"Zergling";"Larva";66;1
"Unit";"Zergling";"Larva";66;1
"Unit";"Zergling";"Larva";66;1
"Unit";"Zergling";"Larva";66;1
"Unit";"Zergling";"Larva";66;1
"Unit";"Zergling";"Larva";66;1
"Building";"SpineCrawler";NA;65;0
"Unit";"Overlord";"Larva";70;0
"Unit";"Overlord";"Larva";82;0
"Unit";"Overlord";"Larva";82;0
"Building";"CreepTumor";NA;82;0
"Building";"BanelingNest";NA;70;0
"Building";"Extractor";NA;82;0
"Building";"Extractor";NA;82;0
"Building";"Extractor";NA;82;0
"Unit";"Queen";"Hatchery";82;2
"Unit";"Queen";"Hatchery";82;2
"Unit";"Baneling";"Zergling";82;0
"Building";"HydraliskDen";NA;82;0
"Building";"CreepTumor";NA;113;0
"Unit";"Hydralisk";"Larva";111;2
"Unit";"Overlord";"Larva";113;0
"Unit";"Overlord";"Larva";113;0
"Unit";"Hydralisk";"Larva";111;2
"Unit";"Overlord";"Larva";113;0
"Building";"CreepTumorQueen";NA;115;0
"Unit";"Overlord";"Larva";115;0
"Unit";"Zergling";"Larva";119;1
"Unit";"Zergling";"Larva";119;1
"Unit";"Hydralisk";"Larva";119;2
"Unit";"Hydralisk";"Larva";119;2
"Unit";"Hydralisk";"Larva";119;2
"Unit";"Hydralisk";"Larva";119;2
"Unit";"Hydralisk";"Larva";119;2
"Unit";"Hydralisk";"Larva";119;2
"Unit";"Hydralisk";"Larva";119;2
"Unit";"Hydralisk";"Larva";119;2
"Unit";"Hydralisk";"Larva";119;2
"Building";"Extractor";NA;119;0
"Building";"Extractor";NA;119;0
"Unit";"Zergling";"Larva";119;1
"Unit";"Zergling";"Larva";119;1
"Unit";"Zergling";"Larva";119;1
"Unit";"Zergling";"Larva";119;1
"Unit";"Zergling";"Larva";119;1
"Unit";"Zergling";"Larva";119;1
"Unit";"Zergling";"Larva";119;1
"Unit";"Zergling";"Larva";119;1
"Upgrade";"EvolveMuscularAugments";"HydraliskDen";115;0
"Building";"Hatchery";NA;113;0
"Unit";"Hydralisk";"Larva";147;2
"Unit";"Hydralisk";"Larva";147;2
"Unit";"Hydralisk";"Larva";147;2
"Unit";"Hydralisk";"Larva";147;2
"Unit";"Hydralisk";"Larva";147;2
"Unit";"Hydralisk";"Larva";147;2
"Unit";"Hydralisk";"Larva";147;2
"Building";"CreepTumor";NA;152;0
"Unit";"Overlord";"Larva";152;0
"Unit";"Overlord";"Larva";152;0
"Building";"CreepTumorQueen";NA;166;0
"Building";"CreepTumorQueen";NA;166;0
"Building";"CreepTumorQueen";NA;166;0
"Building";"CreepTumorQueen";NA;166;0
"Building";"CreepTumor";NA;166;0
"Unit";"Overlord";"Larva";166;0
"Building";"CreepTumorQueen";NA;174;0
"Unit";"Overlord";"Larva";166;0
"Building";"CreepTumorQueen";NA;174;0
"Building";"CreepTumorQueen";NA;174;0
"Building";"CreepTumorQueen";NA;174;0
"Unit";"Zergling";"Larva";166;1
"Unit";"Zergling";"Larva";166;1
"Unit";"Zergling";"Larva";166;1
"Unit";"Zergling";"Larva";166;1
"Unit";"Zergling";"Larva";166;1
"Unit";"Zergling";"Larva";166;1
"Unit";"Zergling";"Larva";166;1
"Unit";"Zergling";"Larva";166;1
"Unit";"Zergling";"Larva";166;1
"Unit";"Zergling";"Larva";166;1
"Unit";"Zergling";"Larva";174;1
"Unit";"Zergling";"Larva";174;1
"Unit";"Zergling";"Larva";174;1
"Unit";"Zergling";"Larva";174;1
"Building";"EvolutionChamber";NA;174;0
"Building";"CreepTumorQueen";NA;184;0
"Building";"EvolutionChamber";NA;174;0
"Building";"CreepTumorQueen";NA;184;0
"Building";"EvolutionChamber";NA;174;0
"Building";"CreepTumorQueen";NA;188;0
"Unit";"Baneling";"Zergling";184;0
"Unit";"Zergling";"Larva";184;1
"Unit";"Zergling";"Larva";184;1
"Unit";"Baneling";"Zergling";186;0
"Unit";"Baneling";"Zergling";186;0
"Unit";"Baneling";"Zergling";186;0
"Unit";"Baneling";"Zergling";186;0
"Unit";"Baneling";"Zergling";186;0
"Unit";"Baneling";"Zergling";186;0
"Building";"CreepTumorQueen";NA;188;0
"Unit";"Zergling";"Larva";184;1
"Unit";"Zergling";"Larva";184;1
"Unit";"Zergling";"Larva";184;1
"Unit";"Zergling";"Larva";184;1
"Unit";"Zergling";"Larva";184;1
"Unit";"Zergling";"Larva";184;1
"Unit";"Zergling";"Larva";184;1
"Unit";"Zergling";"Larva";184;1
"Unit";"Zergling";"Larva";184;1
"Unit";"Zergling";"Larva";184;1
"Unit";"Zergling";"Larva";184;1
"Unit";"Zergling";"Larva";184;1
"Unit";"Zergling";"Larva";184;1
"Unit";"Zergling";"Larva";184;1
"Unit";"Zergling";"Larva";184;1
"Unit";"Zergling";"Larva";184;1
"Unit";"Zergling";"Larva";188;1
"Unit";"Zergling";"Larva";188;1
"Unit";"Zergling";"Larva";188;1
"Unit";"Zergling";"Larva";188;1
"Building";"Hatchery";NA;152;0
"Building";"CreepTumorQueen";NA;206;0
"Building";"CreepTumorQueen";NA;206;0
"Building";"CreepTumor";NA;206;0
"Building";"CreepTumor";NA;206;0
"Building";"CreepTumorQueen";NA;210;0
"Building";"CreepTumor";NA;206;0
"Building";"CreepTumor";NA;206;0
"Building";"CreepTumorQueen";NA;217;0
"Building";"CreepTumorQueen";NA;217;0
"Unit";"Overlord";"Larva";210;0
"Unit";"Overlord";"Larva";210;0
"Building";"CreepTumor";NA;217;0
"Building";"CreepTumor";NA;217;0
"Building";"CreepTumor";NA;217;0
"Building";"CreepTumor";NA;217;0
"Building";"CreepTumorQueen";NA;217;0
"Building";"CreepTumorQueen";NA;217;0
"Building";"CreepTumorQueen";NA;217;0
"Building";"CreepTumorQueen";NA;217;0
"Building";"CreepTumorQueen";NA;217;0
"Unit";"Hydralisk";"Larva";217;2
"Unit";"Hydralisk";"Larva";217;2
"Unit";"Hydralisk";"Larva";217;2
"Unit";"Hydralisk";"Larva";217;2
"Unit";"Hydralisk";"Larva";217;2
"Unit";"Hydralisk";"Larva";217;2
"Unit";"Baneling";"Zergling";217;0
"Unit";"Baneling";"Zergling";217;0
"Unit";"Baneling";"Zergling";217;0
"Unit";"Baneling";"Zergling";217;0
"Unit";"Baneling";"Zergling";217;0
"Unit";"Baneling";"Zergling";217;0
"Unit";"Baneling";"Zergling";217;0
"Unit";"Baneling";"Zergling";217;0
"Unit";"Baneling";"Zergling";217;0
"Unit";"Baneling";"Zergling";217;0
"Unit";"Baneling";"Zergling";217;0
"Unit";"Baneling";"Zergling";217;0
"Unit";"Baneling";"Zergling";217;0
"Unit";"Baneling";"Zergling";217;0
"Unit";"Baneling";"Zergling";217;0
"Unit";"Baneling";"Zergling";217;0
"Unit";"Baneling";"Zergling";217;0
"Unit";"Baneling";"Zergling";217;0
"Unit";"Baneling";"Zergling";217;0
"Unit";"Baneling";"Zergling";217;0
"Unit";"Baneling";"Zergling";217;0
"Unit";"Baneling";"Zergling";217;0
"Unit";"Baneling";"Zergling";217;0
"Unit";"Baneling";"Zergling";217;0
"Unit";"Baneling";"Zergling";217;0
"Unit";"Baneling";"Zergling";217;0
"Unit";"Baneling";"Zergling";217;0
"Building";"CreepTumor";NA;229;0
"Building";"CreepTumor";NA;229;0
"Building";"SporeCrawler";NA;217;0
"Unit";"Zergling";"Larva";217;1
"Unit";"Zergling";"Larva";217;1
"Building";"CreepTumor";NA;229;0
"Building";"CreepTumor";NA;229;0
"Unit";"Zergling";"Larva";217;1
"Unit";"Zergling";"Larva";217;1
"Unit";"Zergling";"Larva";219;1
"Unit";"Zergling";"Larva";219;1
"Unit";"Zergling";"Larva";219;1
"Unit";"Zergling";"Larva";219;1
"Unit";"Zergling";"Larva";219;1
"Unit";"Zergling";"Larva";219;1
"Unit";"Zergling";"Larva";219;1
"Unit";"Zergling";"Larva";219;1
"Building";"CreepTumor";NA;229;0
"Unit";"Zergling";"Larva";219;1
"Unit";"Zergling";"Larva";219;1
"Building";"CreepTumorQueen";NA;230;0
"Building";"CreepTumor";NA;230;0
"Building";"CreepTumor";NA;230;0
"Building";"CreepTumor";NA;230;0
"Building";"CreepTumor";NA;230;0
"Building";"CreepTumor";NA;230;0
"Building";"CreepTumor";NA;230;0
"Building";"CreepTumor";NA;230;0
"Building";"CreepTumor";NA;230;0
"Unit";"Zergling";"Larva";230;1
"Unit";"Zergling";"Larva";230;1
"Unit";"Zergling";"Larva";230;1
"Unit";"Zergling";"Larva";230;1
"Unit";"Zergling";"Larva";230;1
"Unit";"Zergling";"Larva";230;1
"Unit";"Zergling";"Larva";230;1
"Unit";"Zergling";"Larva";230;1
"Unit";"Zergling";"Larva";230;1
"Unit";"Zergling";"Larva";230;1
"Unit";"Zergling";"Larva";230;1
"Unit";"Zergling";"Larva";230;1
"Unit";"Zergling";"Larva";230;1
"Unit";"Zergling";"Larva";230;1
"Unit";"Zergling";"Larva";230;1
"Unit";"Zergling";"Larva";230;1
"Unit";"Zergling";"Larva";230;1
"Unit";"Zergling";"Larva";230;1
"Unit";"Zergling";"Larva";230;1
"Unit";"Zergling";"Larva";230;1
"Unit";"Zergling";"Larva";230;1
"Unit";"Zergling";"Larva";230;1
"Unit";"Zergling";"Larva";230;1
"Unit";"Zergling";"Larva";230;1
"Unit";"Zergling";"Larva";244;1
"Unit";"Zergling";"Larva";244;1
"Unit";"Overlord";"Larva";244;0
"Unit";"Overlord";"Larva";244;0
"Upgrade";"EvolveGroovedSpines";"HydraliskDen";230;0
"Unit";"Zergling";"Larva";270;1
"Unit";"Zergling";"Larva";270;1
"Unit";"Zergling";"Larva";270;1
"Unit";"Zergling";"Larva";270;1
"Unit";"Zergling";"Larva";270;1
"Unit";"Zergling";"Larva";270;1
"Unit";"Zergling";"Larva";270;1
"Unit";"Zergling";"Larva";270;1
"Unit";"Zergling";"Larva";270;1
"Unit";"Zergling";"Larva";270;1
"Unit";"Zergling";"Larva";270;1
"Unit";"Zergling";"Larva";270;1
"Unit";"Zergling";"Larva";270;1
"Unit";"Zergling";"Larva";270;1
"Unit";"Zergling";"Larva";270;1
"Unit";"Zergling";"Larva";270;1
"Unit";"Zergling";"Larva";270;1
"Unit";"Zergling";"Larva";270;1
"Unit";"Zergling";"Larva";270;1
"Unit";"Zergling";"Larva";270;1
"Unit";"Zergling";"Larva";270;1
"Unit";"Zergling";"Larva";270;1
"Unit";"Zergling";"Larva";270;1
"Unit";"Zergling";"Larva";270;1
"Unit";"Zergling";"Larva";270;1
"Unit";"Zergling";"Larva";270;1
"Unit";"Zergling";"Larva";270;1
"Unit";"Zergling";"Larva";270;1
"Unit";"Zergling";"Larva";270;1
"Unit";"Zergling";"Larva";270;1
"Upgrade";"ZergMissileWeaponsLevel1";"EvolutionChamber";217;0
"Upgrade";"ZergGroundArmorsLevel1";"EvolutionChamber";217;0
"Building";"CreepTumor";NA;270;0
"Building";"CreepTumor";NA;270;0
"Building";"CreepTumor";NA;270;0
"Upgrade";"ZergMeleeWeaponsLevel1";"EvolutionChamber";217;0
"Building";"CreepTumor";NA;270;0
"Building";"CreepTumor";NA;270;0
"Building";"CreepTumor";NA;286;0
"Building";"CreepTumor";NA;298;0
"Building";"CreepTumor";NA;300;0
"Building";"Extractor";NA;270;0
"Building";"Extractor";NA;270;0
"Building";"CreepTumor";NA;300;0
"Building";"CreepTumor";NA;300;0
"Building";"CreepTumor";NA;300;0
"Unit";"Zergling";"Larva";300;1
"Unit";"Zergling";"Larva";300;1
"Unit";"Zergling";"Larva";300;1
"Unit";"Zergling";"Larva";300;1
"Unit";"Zergling";"Larva";300;1
"Unit";"Zergling";"Larva";300;1
"Unit";"Zergling";"Larva";300;1
"Unit";"Zergling";"Larva";300;1
"Unit";"Zergling";"Larva";300;1
"Unit";"Zergling";"Larva";300;1
"Unit";"Zergling";"Larva";300;1
"Unit";"Zergling";"Larva";300;1
"Unit";"Zergling";"Larva";300;1
"Unit";"Zergling";"Larva";300;1
"Unit";"Zergling";"Larva";300;1
"Unit";"Zergling";"Larva";300;1
"Unit";"Zergling";"Larva";300;1
"Unit";"Zergling";"Larva";300;1
"Unit";"Zergling";"Larva";300;1
"Unit";"Zergling";"Larva";300;1
"Unit";"Zergling";"Larva";300;1
"Unit";"Zergling";"Larva";300;1
"Unit";"Zergling";"Larva";300;1
"Unit";"Zergling";"Larva";300;1
"Unit";"Zergling";"Larva";300;1
"Unit";"Zergling";"Larva";300;1
"Unit";"Zergling";"Larva";300;1
"Unit";"Zergling";"Larva";300;1
"Unit";"Zergling";"Larva";300;1
"Unit";"Zergling";"Larva";300;1
"Unit";"Zergling";"Larva";300;1
"Unit";"Zergling";"Larva";300;1
"Building";"InfestationPit";NA;270;0
"Building";"SpineCrawler";NA;270;0
"Unit";"Zergling";"Larva";332;1
"Unit";"Zergling";"Larva";332;1
"Unit";"Zergling";"Larva";332;1
"Unit";"Zergling";"Larva";332;1
"Unit";"Zergling";"Larva";332;1
"Unit";"Zergling";"Larva";332;1
"Unit";"Zergling";"Larva";332;1
"Unit";"Zergling";"Larva";332;1
"Unit";"Zergling";"Larva";332;1
"Unit";"Zergling";"Larva";332;1
"Unit";"Zergling";"Larva";332;1
"Unit";"Zergling";"Larva";332;1
"Unit";"Zergling";"Larva";332;1
"Unit";"Zergling";"Larva";332;1
"Unit";"Zergling";"Larva";332;1
"Unit";"Zergling";"Larva";332;1
"Unit";"Zergling";"Larva";332;1
"Unit";"Zergling";"Larva";332;1
"Unit";"Zergling";"Larva";332;1
"Unit";"Zergling";"Larva";332;1
"Unit";"Zergling";"Larva";332;1
"Unit";"Zergling";"Larva";332;1
"Unit";"Zergling";"Larva";332;1
"Unit";"Zergling";"Larva";332;1
"Unit";"Zergling";"Larva";332;1
"Unit";"Zergling";"Larva";332;1
"Building";"Hatchery";NA;270;0
"Unit";"Zergling";"Larva";332;1
"Unit";"Zergling";"Larva";332;1
"Unit";"Zergling";"Larva";332;1
"Unit";"Zergling";"Larva";332;1
"Building";"CreepTumor";NA;358;0
"Building";"CreepTumor";NA;358;0
"Building";"CreepTumor";NA;358;0
"Building";"CreepTumor";NA;358;0
"Unit";"Hydralisk";"Larva";332;2
"Building";"CreepTumor";NA;358;0
"Unit";"Hydralisk";"Larva";332;2
"Unit";"Hydralisk";"Larva";332;2
"Unit";"Hydralisk";"Larva";332;2
"Unit";"Hydralisk";"Larva";332;2
"Unit";"Hydralisk";"Larva";332;2
"Unit";"Zergling";"Larva";334;1
"Unit";"Zergling";"Larva";334;1
"Unit";"Hydralisk";"Larva";332;2
"Unit";"Hydralisk";"Larva";332;2
"Unit";"Hydralisk";"Larva";332;2
"Unit";"Hydralisk";"Larva";332;2
"Unit";"Hydralisk";"Larva";332;2
"Unit";"Zergling";"Larva";344;1
"Unit";"Zergling";"Larva";344;1
"Unit";"Zergling";"Larva";344;1
"Unit";"Zergling";"Larva";344;1
"Building";"CreepTumor";NA;358;0
"Unit";"Baneling";"Zergling";358;0
"Unit";"Baneling";"Zergling";358;0
"Unit";"Baneling";"Zergling";358;0
"Unit";"Baneling";"Zergling";358;0
"Unit";"Baneling";"Zergling";358;0
"Unit";"Baneling";"Zergling";358;0
"Unit";"Baneling";"Zergling";358;0
"Unit";"Baneling";"Zergling";358;0
"Unit";"Baneling";"Zergling";358;0
"Unit";"Baneling";"Zergling";358;0
"Unit";"Baneling";"Zergling";358;0
"Unit";"Baneling";"Zergling";358;0
"Unit";"Baneling";"Zergling";358;0
"Unit";"Baneling";"Zergling";358;0
"Unit";"Baneling";"Zergling";358;0
"Unit";"Baneling";"Zergling";358;0
"Unit";"Baneling";"Zergling";358;0
"Unit";"Baneling";"Zergling";358;0
"Unit";"Baneling";"Zergling";358;0
"Unit";"Baneling";"Zergling";358;0
"Unit";"Baneling";"Zergling";358;0
"Unit";"Baneling";"Zergling";358;0
"Unit";"Baneling";"Zergling";358;0
"Unit";"Baneling";"Zergling";358;0
"Unit";"Baneling";"Zergling";358;0
"Building";"CreepTumor";NA;390;0
"Building";"CreepTumor";NA;390;0
"Building";"CreepTumor";NA;390;0
"Building";"CreepTumor";NA;393;0
"Unit";"Zergling";"Larva";390;1
"Unit";"Zergling";"Larva";390;1
"Unit";"Zergling";"Larva";390;1
"Unit";"Zergling";"Larva";390;1
"Unit";"Zergling";"Larva";390;1
"Unit";"Zergling";"Larva";390;1
"Unit";"Zergling";"Larva";390;1
"Unit";"Zergling";"Larva";390;1
"Unit";"Zergling";"Larva";390;1
"Unit";"Zergling";"Larva";390;1
"Unit";"Zergling";"Larva";390;1
"Unit";"Zergling";"Larva";390;1
"Building";"CreepTumor";NA;397;0
"Building";"CreepTumor";NA;397;0
"Building";"CreepTumor";NA;397;0
"Building";"CreepTumor";NA;397;0
"Building";"CreepTumor";NA;397;0
"Building";"CreepTumor";NA;397;0
"Building";"CreepTumor";NA;397;0
"Building";"CreepTumor";NA;397;0
"Building";"CreepTumor";NA;397;0
"Building";"CreepTumor";NA;397;0
"Building";"CreepTumor";NA;398;0
"Building";"CreepTumor";NA;398;0
"Building";"CreepTumor";NA;398;0
"Building";"CreepTumor";NA;398;0
"Unit";"Zergling";"Larva";398;1
"Unit";"Zergling";"Larva";398;1
"Unit";"Zergling";"Larva";398;1
"Unit";"Zergling";"Larva";398;1
"Unit";"Zergling";"Larva";398;1
"Unit";"Zergling";"Larva";398;1
"Unit";"Zergling";"Larva";398;1
"Unit";"Zergling";"Larva";398;1
"Unit";"Zergling";"Larva";398;1
"Unit";"Zergling";"Larva";398;1
"Unit";"Zergling";"Larva";398;1
"Unit";"Zergling";"Larva";398;1
"Unit";"Zergling";"Larva";398;1
"Unit";"Zergling";"Larva";398;1
"Unit";"Zergling";"Larva";398;1
"Unit";"Zergling";"Larva";398;1
"Unit";"Zergling";"Larva";398;1
"Unit";"Zergling";"Larva";398;1
"Unit";"Zergling";"Larva";398;1
"Unit";"Zergling";"Larva";398;1
"Unit";"Zergling";"Larva";398;1
"Unit";"Zergling";"Larva";398;1
"Unit";"Zergling";"Larva";398;1
"Unit";"Zergling";"Larva";398;1
"Unit";"Zergling";"Larva";398;1
"Unit";"Zergling";"Larva";398;1
"Unit";"Zergling";"Larva";398;1
"Unit";"Zergling";"Larva";398;1
"Unit";"Zergling";"Larva";410;1
"Unit";"Zergling";"Larva";410;1
"Unit";"Zergling";"Larva";410;1
"Unit";"Zergling";"Larva";410;1
"Unit";"Zergling";"Larva";410;1
"Unit";"Zergling";"Larva";410;1
"Unit";"Zergling";"Larva";410;1
"Unit";"Zergling";"Larva";410;1
"Unit";"Zergling";"Larva";410;1
"Unit";"Zergling";"Larva";410;1
"Unit";"Zergling";"Larva";410;1
"Unit";"Zergling";"Larva";410;1
"Unit";"Zergling";"Larva";410;1
"Unit";"Zergling";"Larva";410;1
"Unit";"Zergling";"Larva";410;1
"Unit";"Zergling";"Larva";410;1
"Unit";"Zergling";"Larva";410;1
"Unit";"Zergling";"Larva";410;1
"Unit";"Zergling";"Larva";410;1
"Unit";"Zergling";"Larva";410;1
"Building";"CreepTumor";NA;438;0
"Building";"CreepTumor";NA;438;0
"Building";"CreepTumorQueen";NA;458;0
"Building";"CreepTumorQueen";NA;458;0
"Building";"CreepTumorQueen";NA;458;0
"Building";"CreepTumorQueen";NA;458;0
"Upgrade";"ZergMeleeWeaponsLevel2";"EvolutionChamber";358;0
"Upgrade";"ZergGroundArmorsLevel2";"EvolutionChamber";358;0
"Upgrade";"ZergMissileWeaponsLevel2";"EvolutionChamber";358;0
"Building";"Spire";NA;390;0
"Unit";"Overlord";"Larva";458;0
