"type";"unit_name";"on_building";"total_supply";"supply"
"Unit";"Overlord";"Larva";13;0
"Building";"Extractor";NA;18;0
"Unit";"Overlord";"Larva";21;0
"Building";"SpawningPool";NA;19;0
"Building";"Hatchery";NA;17;0
"Unit";"Zergling";"Larva";22;1
"Unit";"Zergling";"Larva";22;1
"Unit";"Zergling";"Larva";23;1
"Unit";"Zergling";"Larva";23;1
"Unit";"Queen";"Hatchery";22;2
"Unit";"Queen";"Hatchery";23;2
"Building";"CreepTumorQueen";NA;34;0
"Unit";"Overlord";"Larva";34;0
"Building";"CreepTumor";NA;39;0
"Building";"Hatchery";NA;25;0
"Unit";"Zergling";"Larva";42;1
"Unit";"Zergling";"Larva";42;1
"Unit";"Zergling";"Larva";42;1
"Unit";"Zergling";"Larva";42;1
"Unit";"Zergling";"Larva";45;1
"Unit";"Zergling";"Larva";45;1
"Unit";"Overlord";"Larva";45;0
"Unit";"Zergling";"Larva";45;1
"Unit";"Zergling";"Larva";45;1
"Unit";"Zergling";"Larva";45;1
"Unit";"Zergling";"Larva";45;1
"Building";"CreepTumor";NA;49;0
"Unit";"Queen";"Hatchery";45;2
"Unit";"Queen";"Hatchery";45;2
"Unit";"Queen";"Hatchery";45;2
"Unit";"Zergling";"Larva";61;1
"Unit";"Zergling";"Larva";61;1
"Unit";"Zergling";"Larva";61;1
"Unit";"Zergling";"Larva";61;1
"Unit";"Overlord";"Larva";61;0
"Building";"CreepTumor";NA;61;0
"Building";"CreepTumorQueen";NA;65;0
"Building";"CreepTumorQueen";NA;65;0
"Building";"SporeCrawler";NA;61;0
"Building";"SporeCrawler";NA;61;0
"Unit";"Queen";"Hatchery";61;2
"Unit";"Queen";"Hatchery";61;2
"Unit";"Queen";"Hatchery";61;2
"Building";"EvolutionChamber";NA;73;0
"Building";"EvolutionChamber";NA;73;0
"Building";"CreepTumor";NA;87;0
"Building";"CreepTumorQueen";NA;87;0
"Unit";"Overlord";"Larva";87;0
"Building";"CreepTumor";NA;87;0
"Unit";"Overlord";"Larva";87;0
"Building";"CreepTumor";NA;87;0
"Unit";"Queen";"Hatchery";87;2
"Unit";"Overlord";"Larva";93;0
"Unit";"Overlord";"Larva";93;0
"Unit";"Queen";"Hatchery";87;2
"Building";"CreepTumor";NA;93;0
"Building";"CreepTumorQueen";NA;97;0
"Building";"CreepTumorQueen";NA;97;0
"Building";"CreepTumor";NA;97;0
"Unit";"Zergling";"Larva";97;1
"Unit";"Zergling";"Larva";97;1
"Unit";"Zergling";"Larva";97;1
"Unit";"Zergling";"Larva";97;1
"Unit";"Zergling";"Larva";97;1
"Unit";"Zergling";"Larva";97;1
"Building";"CreepTumor";NA;97;0
"Building";"CreepTumorQueen";NA;112;0
"Building";"CreepTumor";NA;112;0
"Building";"CreepTumor";NA;112;0
"Building";"CreepTumor";NA;112;0
"Unit";"Overlord";"Larva";113;0
"Unit";"Overlord";"Larva";113;0
"Unit";"Overlord";"Larva";113;0
"Building";"CreepTumor";NA;118;0
"Building";"Hatchery";NA;93;0
"Building";"BanelingNest";NA;112;0
"Building";"CreepTumorQueen";NA;118;0
"Building";"CreepTumorQueen";NA;118;0
"Building";"Extractor";NA;118;0
"Building";"Extractor";NA;118;0
"Building";"CreepTumor";NA;118;0
"Building";"Extractor";NA;118;0
"Building";"Extractor";NA;118;0
"Building";"Extractor";NA;118;0
"Building";"SporeCrawler";NA;118;0
"Unit";"Zergling";"Larva";118;1
"Unit";"Zergling";"Larva";118;1
"Unit";"Zergling";"Larva";118;1
"Unit";"Zergling";"Larva";118;1
"Unit";"Zergling";"Larva";118;1
"Unit";"Zergling";"Larva";118;1
"Unit";"Zergling";"Larva";118;1
"Unit";"Zergling";"Larva";118;1
"Unit";"Zergling";"Larva";118;1
"Unit";"Zergling";"Larva";118;1
"Unit";"Zergling";"Larva";118;1
"Unit";"Zergling";"Larva";118;1
"Unit";"Zergling";"Larva";118;1
"Unit";"Zergling";"Larva";118;1
"Building";"SporeCrawler";NA;118;0
"Upgrade";"ZergMeleeWeaponsLevel1";"EvolutionChamber";108;0
"Upgrade";"ZergGroundArmorsLevel1";"EvolutionChamber";112;0
"Building";"CreepTumor";NA;150;0
"Building";"CreepTumor";NA;150;0
"Building";"CreepTumor";NA;150;0
"Building";"CreepTumor";NA;152;0
"Building";"CreepTumor";NA;153;0
"Building";"HydraliskDen";NA;142;0
"Unit";"Queen";"Hatchery";150;2
"Unit";"Overlord";"Larva";158;0
"Unit";"Overlord";"Larva";158;0
"Unit";"Overlord";"Larva";158;0
"Unit";"Overlord";"Larva";158;0
"Building";"CreepTumorQueen";NA;158;0
"Building";"CreepTumor";NA;158;0
"Building";"CreepTumor";NA;158;0
"Building";"CreepTumor";NA;158;0
"Building";"CreepTumorQueen";NA;166;0
"Building";"CreepTumorQueen";NA;166;0
"Building";"CreepTumor";NA;166;0
"Unit";"Zergling";"Larva";166;1
"Unit";"Zergling";"Larva";166;1
"Unit";"Zergling";"Larva";166;1
"Unit";"Zergling";"Larva";166;1
"Unit";"Zergling";"Larva";166;1
"Unit";"Zergling";"Larva";166;1
"Building";"CreepTumor";NA;168;0
"Unit";"Baneling";"Zergling";168;0
"Unit";"Baneling";"Zergling";168;0
"Unit";"Baneling";"Zergling";168;0
"Unit";"Baneling";"Zergling";168;0
"Unit";"Baneling";"Zergling";168;0
"Unit";"Zergling";"Larva";168;1
"Unit";"Zergling";"Larva";168;1
"Unit";"Zergling";"Larva";168;1
"Unit";"Zergling";"Larva";168;1
"Unit";"Zergling";"Larva";168;1
"Unit";"Zergling";"Larva";168;1
"Unit";"Zergling";"Larva";168;1
"Unit";"Zergling";"Larva";168;1
"Unit";"Zergling";"Larva";168;1
"Unit";"Zergling";"Larva";168;1
"Unit";"Zergling";"Larva";168;1
"Unit";"Zergling";"Larva";168;1
"Unit";"Zergling";"Larva";168;1
"Unit";"Zergling";"Larva";168;1
"Building";"CreepTumor";NA;188;0
"Building";"CreepTumor";NA;188;0
"Building";"CreepTumor";NA;188;0
"Unit";"Hydralisk";"Larva";174;2
"Unit";"Hydralisk";"Larva";174;2
"Unit";"Hydralisk";"Larva";174;2
"Unit";"Hydralisk";"Larva";174;2
"Unit";"Hydralisk";"Larva";174;2
"Building";"CreepTumor";NA;188;0
"Building";"CreepTumor";NA;188;0
"Unit";"Hydralisk";"Larva";174;2
"Unit";"Hydralisk";"Larva";188;2
"Building";"CreepTumor";NA;188;0
"Unit";"Hydralisk";"Larva";188;2
"Building";"Hatchery";NA;158;0
"Unit";"Hydralisk";"Larva";188;2
"Building";"CreepTumorQueen";NA;200;0
"Building";"CreepTumorQueen";NA;202;0
"Building";"CreepTumorQueen";NA;202;0
"Upgrade";"EvolveGroovedSpines";"HydraliskDen";168;0
"Unit";"Baneling";"Zergling";207;0
"Unit";"Baneling";"Zergling";207;0
"Unit";"Baneling";"Zergling";207;0
"Unit";"Baneling";"Zergling";207;0
"Unit";"Baneling";"Zergling";207;0
"Unit";"Baneling";"Zergling";207;0
"Unit";"Overlord";"Larva";207;0
"Building";"InfestationPit";NA;188;0
"Unit";"Baneling";"Zergling";207;0
"Unit";"Baneling";"Zergling";207;0
"Unit";"Baneling";"Zergling";207;0
"Unit";"Baneling";"Zergling";207;0
"Unit";"Overlord";"Larva";207;0
"Building";"CreepTumor";NA;207;0
"Unit";"Overlord";"Larva";207;0
"Unit";"Overlord";"Larva";207;0
"Unit";"Hydralisk";"Larva";207;2
"Unit";"Overlord";"Larva";207;0
"Unit";"Hydralisk";"Larva";207;2
"Unit";"Hydralisk";"Larva";207;2
"Unit";"Hydralisk";"Larva";207;2
"Unit";"Hydralisk";"Larva";207;2
"Unit";"Zergling";"Larva";207;1
"Unit";"Zergling";"Larva";207;1
"Unit";"Zergling";"Larva";209;1
"Unit";"Zergling";"Larva";209;1
"Unit";"Zergling";"Larva";211;1
"Unit";"Zergling";"Larva";211;1
"Unit";"Zergling";"Larva";211;1
"Unit";"Zergling";"Larva";211;1
"Unit";"Zergling";"Larva";211;1
"Unit";"Zergling";"Larva";211;1
"Unit";"Zergling";"Larva";211;1
"Unit";"Zergling";"Larva";211;1
"Unit";"Zergling";"Larva";211;1
"Unit";"Zergling";"Larva";211;1
"Unit";"Zergling";"Larva";211;1
"Unit";"Zergling";"Larva";211;1
"Unit";"Zergling";"Larva";213;1
"Unit";"Zergling";"Larva";213;1
"Unit";"Zergling";"Larva";213;1
"Unit";"Zergling";"Larva";213;1
"Unit";"Zergling";"Larva";213;1
"Unit";"Zergling";"Larva";213;1
"Unit";"Zergling";"Larva";215;1
"Unit";"Zergling";"Larva";215;1
"Unit";"Zergling";"Larva";215;1
"Unit";"Zergling";"Larva";215;1
"Unit";"Zergling";"Larva";215;1
"Unit";"Zergling";"Larva";215;1
"Upgrade";"ZergMissileWeaponsLevel1";"EvolutionChamber";188;0
"Building";"CreepTumor";NA;243;0
"Unit";"Baneling";"Zergling";217;0
"Unit";"Baneling";"Zergling";217;0
"Building";"Extractor";NA;217;0
"Unit";"Baneling";"Zergling";217;0
"Building";"CreepTumor";NA;249;0
"Unit";"Baneling";"Zergling";217;0
"Building";"Extractor";NA;217;0
"Unit";"Baneling";"Zergling";217;0
"Building";"CreepTumor";NA;247;0
"Unit";"Baneling";"Zergling";217;0
"Unit";"Baneling";"Zergling";217;0
"Unit";"Baneling";"Zergling";219;0
"Unit";"Baneling";"Zergling";219;0
"Unit";"Baneling";"Zergling";219;0
"Unit";"Baneling";"Zergling";221;0
"Upgrade";"ZergMeleeWeaponsLevel2";"EvolutionChamber";188;0
"Building";"Hatchery";NA;207;0
"Upgrade";"EvolveMuscularAugments";"HydraliskDen";217;0
"Building";"SporeCrawler";NA;249;0
"Unit";"Zergling";"Larva";249;1
"Unit";"Zergling";"Larva";249;1
"Unit";"Zergling";"Larva";249;1
"Unit";"Zergling";"Larva";249;1
"Unit";"Zergling";"Larva";249;1
"Unit";"Zergling";"Larva";249;1
"Unit";"Zergling";"Larva";249;1
"Unit";"Zergling";"Larva";249;1
"Unit";"Zergling";"Larva";249;1
"Unit";"Zergling";"Larva";249;1
"Unit";"Zergling";"Larva";249;1
"Unit";"Zergling";"Larva";249;1
"Unit";"Zergling";"Larva";249;1
"Unit";"Zergling";"Larva";249;1
"Unit";"Zergling";"Larva";262;1
"Unit";"Zergling";"Larva";262;1
"Unit";"Zergling";"Larva";262;1
"Unit";"Zergling";"Larva";262;1
"Unit";"Zergling";"Larva";262;1
"Unit";"Zergling";"Larva";262;1
"Unit";"Zergling";"Larva";262;1
"Unit";"Zergling";"Larva";262;1
"Unit";"Zergling";"Larva";262;1
"Unit";"Zergling";"Larva";262;1
"Unit";"Zergling";"Larva";262;1
"Unit";"Zergling";"Larva";262;1
"Unit";"Zergling";"Larva";262;1
"Unit";"Zergling";"Larva";262;1
"Unit";"Zergling";"Larva";262;1
"Unit";"Zergling";"Larva";262;1
"Unit";"Zergling";"Larva";262;1
"Unit";"Zergling";"Larva";262;1
"Building";"SpineCrawler";NA;249;0
"Unit";"Zergling";"Larva";262;1
"Unit";"Zergling";"Larva";262;1
"Building";"SpineCrawler";NA;249;0
"Building";"SpineCrawler";NA;249;0
"Unit";"Zergling";"Larva";262;1
"Unit";"Zergling";"Larva";262;1
"Unit";"Zergling";"Larva";262;1
"Unit";"Zergling";"Larva";262;1
"Unit";"Zergling";"Larva";262;1
"Unit";"Zergling";"Larva";262;1
"Unit";"Zergling";"Larva";262;1
"Unit";"Zergling";"Larva";262;1
"Building";"CreepTumor";NA;276;0
"Building";"CreepTumor";NA;276;0
"Building";"CreepTumor";NA;276;0
"Unit";"Zergling";"Larva";304;1
"Unit";"Zergling";"Larva";304;1
"Unit";"Zergling";"Larva";304;1
"Unit";"Zergling";"Larva";304;1
"Unit";"Zergling";"Larva";304;1
"Unit";"Zergling";"Larva";304;1
"Unit";"Zergling";"Larva";304;1
"Unit";"Zergling";"Larva";304;1
"Unit";"Zergling";"Larva";304;1
"Unit";"Zergling";"Larva";304;1
"Unit";"Zergling";"Larva";304;1
"Unit";"Zergling";"Larva";304;1
"Unit";"Zergling";"Larva";304;1
"Unit";"Zergling";"Larva";304;1
"Unit";"Zergling";"Larva";304;1
"Unit";"Zergling";"Larva";304;1
"Unit";"Zergling";"Larva";304;1
"Unit";"Zergling";"Larva";304;1
"Unit";"Zergling";"Larva";304;1
"Unit";"Zergling";"Larva";304;1
"Unit";"Zergling";"Larva";304;1
"Unit";"Zergling";"Larva";304;1
"Unit";"Zergling";"Larva";304;1
"Unit";"Zergling";"Larva";304;1
"Unit";"Zergling";"Larva";304;1
"Unit";"Zergling";"Larva";304;1
"Unit";"Zergling";"Larva";304;1
"Unit";"Zergling";"Larva";304;1
"Unit";"Zergling";"Larva";304;1
"Unit";"Zergling";"Larva";304;1
"Unit";"Zergling";"Larva";304;1
"Unit";"Zergling";"Larva";304;1
"Unit";"Zergling";"Larva";304;1
"Unit";"Zergling";"Larva";304;1
"Unit";"Zergling";"Larva";304;1
"Unit";"Zergling";"Larva";304;1
"Unit";"Zergling";"Larva";304;1
"Unit";"Zergling";"Larva";304;1
"Unit";"Zergling";"Larva";304;1
"Unit";"Zergling";"Larva";304;1
"Unit";"Zergling";"Larva";304;1
"Unit";"Zergling";"Larva";304;1
"Unit";"Zergling";"Larva";304;1
"Unit";"Zergling";"Larva";304;1
"Unit";"Zergling";"Larva";304;1
"Unit";"Zergling";"Larva";304;1
"Unit";"Zergling";"Larva";304;1
"Unit";"Zergling";"Larva";304;1
"Unit";"Zergling";"Larva";304;1
"Unit";"Zergling";"Larva";304;1
"Building";"Extractor";NA;328;0
"Building";"Extractor";NA;328;0
"Building";"CreepTumor";NA;354;0
"Building";"CreepTumor";NA;359;0
"Building";"CreepTumor";NA;360;0
"Building";"CreepTumorQueen";NA;362;0
"Building";"CreepTumorQueen";NA;362;0
"Unit";"Queen";"Hatchery";304;2
"Building";"CreepTumorQueen";NA;362;0
"Unit";"Baneling";"Zergling";362;0
"Unit";"Baneling";"Zergling";362;0
"Unit";"Baneling";"Zergling";362;0
"Unit";"Baneling";"Zergling";362;0
"Unit";"Baneling";"Zergling";362;0
"Unit";"Baneling";"Zergling";362;0
"Unit";"Baneling";"Zergling";362;0
"Unit";"Baneling";"Zergling";362;0
"Unit";"Baneling";"Zergling";362;0
"Unit";"Baneling";"Zergling";362;0
"Unit";"Baneling";"Zergling";362;0
"Unit";"Baneling";"Zergling";362;0
"Unit";"Baneling";"Zergling";362;0
"Unit";"Viper";"Larva";362;3
"Unit";"Viper";"Larva";362;3
"Unit";"Viper";"Larva";362;3
"Unit";"Viper";"Larva";362;3
"Building";"CreepTumorQueen";NA;364;0
"Building";"CreepTumor";NA;364;0
"Building";"CreepTumor";NA;364;0
"Building";"CreepTumor";NA;364;0
"Building";"CreepTumor";NA;376;0
"Building";"CreepTumor";NA;376;0
"Building";"SporeCrawler";NA;376;0
"Building";"UltraliskCavern";NA;362;0
"Unit";"Baneling";"Zergling";376;0
"Unit";"Baneling";"Zergling";376;0
"Unit";"Baneling";"Zergling";376;0
"Unit";"Hydralisk";"Larva";376;2
"Unit";"Hydralisk";"Larva";376;2
"Unit";"Hydralisk";"Larva";376;2
"Unit";"Hydralisk";"Larva";376;2
"Unit";"Zergling";"Larva";376;1
"Unit";"Zergling";"Larva";376;1
"Unit";"Zergling";"Larva";376;1
"Unit";"Zergling";"Larva";376;1
"Unit";"Zergling";"Larva";376;1
"Unit";"Zergling";"Larva";376;1
"Unit";"Zergling";"Larva";376;1
"Unit";"Zergling";"Larva";376;1
"Unit";"Zergling";"Larva";376;1
"Unit";"Zergling";"Larva";376;1
"Unit";"Zergling";"Larva";376;1
"Unit";"Zergling";"Larva";376;1
"Unit";"Zergling";"Larva";376;1
"Unit";"Zergling";"Larva";376;1
"Unit";"Zergling";"Larva";376;1
"Unit";"Zergling";"Larva";376;1
"Unit";"Zergling";"Larva";376;1
"Unit";"Zergling";"Larva";376;1
"Unit";"Zergling";"Larva";376;1
"Unit";"Zergling";"Larva";376;1
"Unit";"Zergling";"Larva";376;1
"Unit";"Zergling";"Larva";376;1
"Unit";"Overlord";"Larva";376;0
"Unit";"Overlord";"Larva";376;0
"Unit";"Overlord";"Larva";376;0
"Unit";"Overlord";"Larva";376;0
"Building";"CreepTumorQueen";NA;406;0
"Building";"Spire";NA;362;0
"Upgrade";"ZergMissileWeaponsLevel2";"EvolutionChamber";304;0
"Building";"CreepTumorQueen";NA;406;0
"Building";"CreepTumorQueen";NA;406;0
"Building";"CreepTumor";NA;406;0
"Upgrade";"ZergGroundArmorsLevel2";"EvolutionChamber";304;0
"Building";"CreepTumor";NA;406;0
"Building";"CreepTumor";NA;406;0
"Building";"CreepTumor";NA;406;0
"Building";"CreepTumorQueen";NA;406;0
"Building";"CreepTumorQueen";NA;406;0
"Building";"CreepTumorQueen";NA;406;0
"Building";"CreepTumor";NA;406;0
"Building";"CreepTumor";NA;406;0
"Unit";"Ultralisk";"Larva";406;6
"Unit";"Ultralisk";"Larva";406;6
"Unit";"Ultralisk";"Larva";406;6
"Unit";"Overlord";"Larva";406;0
"Unit";"Overlord";"Larva";406;0
"Upgrade";"ChitinousPlating";"UltraliskCavern";406;0
"Building";"CreepTumor";NA;427;0
"Building";"Hatchery";NA;406;0
"Unit";"Zergling";"Larva";427;1
"Unit";"Zergling";"Larva";427;1
"Unit";"Zergling";"Larva";427;1
"Unit";"Zergling";"Larva";427;1
"Unit";"Zergling";"Larva";427;1
"Unit";"Zergling";"Larva";427;1
"Unit";"Zergling";"Larva";427;1
"Unit";"Zergling";"Larva";427;1
"Unit";"Zergling";"Larva";427;1
"Unit";"Zergling";"Larva";427;1
"Unit";"Zergling";"Larva";427;1
"Unit";"Zergling";"Larva";427;1
"Unit";"Zergling";"Larva";427;1
"Unit";"Zergling";"Larva";427;1
"Unit";"Zergling";"Larva";427;1
"Unit";"Zergling";"Larva";427;1
"Unit";"Zergling";"Larva";427;1
"Unit";"Zergling";"Larva";427;1
"Unit";"Zergling";"Larva";427;1
"Unit";"Zergling";"Larva";427;1
"Unit";"Zergling";"Larva";427;1
"Unit";"Zergling";"Larva";427;1
"Unit";"Zergling";"Larva";427;1
"Unit";"Zergling";"Larva";427;1
"Unit";"Zergling";"Larva";427;1
"Unit";"Zergling";"Larva";427;1
"Unit";"Baneling";"Zergling";427;0
"Unit";"Baneling";"Zergling";427;0
"Unit";"Baneling";"Zergling";427;0
"Unit";"Baneling";"Zergling";427;0
"Unit";"Baneling";"Zergling";427;0
"Unit";"Baneling";"Zergling";427;0
"Unit";"Baneling";"Zergling";427;0
"Unit";"Baneling";"Zergling";427;0
"Unit";"Baneling";"Zergling";427;0
"Unit";"Baneling";"Zergling";427;0
"Unit";"Baneling";"Zergling";427;0
"Unit";"Baneling";"Zergling";427;0
"Unit";"Baneling";"Zergling";427;0
"Unit";"Baneling";"Zergling";427;0
"Unit";"Baneling";"Zergling";427;0
"Unit";"Baneling";"Zergling";427;0
"Unit";"Baneling";"Zergling";427;0
"Unit";"Baneling";"Zergling";427;0
"Unit";"Baneling";"Zergling";427;0
"Unit";"Baneling";"Zergling";427;0
"Unit";"Baneling";"Zergling";427;0
"Unit";"Baneling";"Zergling";427;0
"Unit";"Baneling";"Zergling";427;0
"Unit";"Baneling";"Zergling";427;0
"Unit";"Baneling";"Zergling";427;0
"Unit";"Ultralisk";"Larva";427;6
"Unit";"Ultralisk";"Larva";427;6
"Unit";"Ultralisk";"Larva";427;6
"Building";"SpineCrawler";NA;439;0
"Building";"SpineCrawler";NA;439;0
"Unit";"Zergling";"Larva";471;1
"Unit";"Zergling";"Larva";471;1
"Unit";"Zergling";"Larva";471;1
"Unit";"Zergling";"Larva";471;1
"Unit";"Zergling";"Larva";471;1
"Unit";"Zergling";"Larva";471;1
"Unit";"Zergling";"Larva";471;1
"Unit";"Zergling";"Larva";471;1
"Unit";"Zergling";"Larva";471;1
"Unit";"Zergling";"Larva";471;1
"Unit";"Zergling";"Larva";471;1
"Unit";"Zergling";"Larva";471;1
"Unit";"Zergling";"Larva";471;1
"Unit";"Zergling";"Larva";471;1
"Unit";"Zergling";"Larva";471;1
"Unit";"Zergling";"Larva";471;1
"Unit";"Zergling";"Larva";471;1
"Unit";"Zergling";"Larva";471;1
"Unit";"Zergling";"Larva";471;1
"Unit";"Zergling";"Larva";471;1
"Unit";"Zergling";"Larva";471;1
"Unit";"Zergling";"Larva";471;1
"Unit";"Zergling";"Larva";471;1
"Unit";"Zergling";"Larva";471;1
"Unit";"Zergling";"Larva";471;1
"Unit";"Zergling";"Larva";471;1
"Unit";"Zergling";"Larva";471;1
"Unit";"Zergling";"Larva";471;1
"Unit";"Zergling";"Larva";471;1
"Unit";"Zergling";"Larva";471;1
"Unit";"Zergling";"Larva";471;1
"Unit";"Zergling";"Larva";471;1
"Unit";"Zergling";"Larva";471;1
"Unit";"Zergling";"Larva";471;1
"Unit";"Zergling";"Larva";471;1
"Unit";"Zergling";"Larva";471;1
"Unit";"Zergling";"Larva";471;1
"Unit";"Zergling";"Larva";471;1
"Unit";"Zergling";"Larva";471;1
"Unit";"Zergling";"Larva";471;1
"Unit";"Zergling";"Larva";471;1
"Unit";"Zergling";"Larva";471;1
"Unit";"Zergling";"Larva";471;1
"Unit";"Zergling";"Larva";471;1
"Unit";"Zergling";"Larva";471;1
"Unit";"Zergling";"Larva";471;1
"Unit";"Zergling";"Larva";471;1
"Unit";"Zergling";"Larva";471;1
"Unit";"Zergling";"Larva";471;1
"Unit";"Zergling";"Larva";471;1
"Unit";"Zergling";"Larva";471;1
"Unit";"Zergling";"Larva";471;1
"Unit";"Zergling";"Larva";471;1
"Unit";"Zergling";"Larva";471;1
"Unit";"Zergling";"Larva";471;1
"Unit";"Zergling";"Larva";471;1
"Unit";"Zergling";"Larva";471;1
"Unit";"Zergling";"Larva";471;1
"Unit";"Zergling";"Larva";471;1
"Unit";"Zergling";"Larva";471;1
"Unit";"Zergling";"Larva";471;1
"Unit";"Zergling";"Larva";471;1
"Unit";"Zergling";"Larva";471;1
"Unit";"Zergling";"Larva";471;1
"Unit";"Zergling";"Larva";471;1
"Unit";"Zergling";"Larva";471;1
"Building";"SpineCrawler";NA;439;0
"Unit";"Zergling";"Larva";471;1
"Unit";"Zergling";"Larva";471;1
"Unit";"Zergling";"Larva";471;1
"Unit";"Zergling";"Larva";471;1
"Unit";"Zergling";"Larva";471;1
"Unit";"Zergling";"Larva";471;1
"Upgrade";"ZergMeleeWeaponsLevel3";"EvolutionChamber";406;0
"Upgrade";"ZergGroundArmorsLevel3";"EvolutionChamber";406;0
"Building";"SpineCrawler";NA;441;0
"Building";"CreepTumorQueen";NA;513;0
"Building";"SporeCrawler";NA;546;0
"Unit";"Baneling";"Zergling";546;0
"Unit";"Baneling";"Zergling";546;0
"Unit";"Baneling";"Zergling";546;0
"Unit";"Baneling";"Zergling";546;0
"Unit";"Baneling";"Zergling";546;0
"Unit";"Baneling";"Zergling";546;0
"Building";"CreepTumor";NA;546;0
"Unit";"Baneling";"Zergling";546;0
"Unit";"Baneling";"Zergling";546;0
"Unit";"Baneling";"Zergling";546;0
"Unit";"Baneling";"Zergling";546;0
"Unit";"Baneling";"Zergling";546;0
"Unit";"Baneling";"Zergling";546;0
"Unit";"Baneling";"Zergling";546;0
"Unit";"Baneling";"Zergling";546;0
"Unit";"Baneling";"Zergling";546;0
"Building";"CreepTumorQueen";NA;546;0
"Building";"CreepTumorQueen";NA;546;0
"Building";"CreepTumorQueen";NA;548;0
"Building";"CreepTumorQueen";NA;548;0
"Building";"SpineCrawler";NA;546;0
"Building";"SpineCrawler";NA;546;0
"Building";"SpineCrawler";NA;546;0
"Building";"SpineCrawler";NA;546;0
"Unit";"Corruptor";"Larva";548;2
"Unit";"Corruptor";"Larva";548;2
"Unit";"Corruptor";"Larva";548;2
"Unit";"Corruptor";"Larva";548;2
"Unit";"Corruptor";"Larva";548;2
"Unit";"Corruptor";"Larva";548;2
"Unit";"Corruptor";"Larva";548;2
"Unit";"Corruptor";"Larva";548;2
"Unit";"Baneling";"Zergling";549;0
"Building";"CreepTumorQueen";NA;551;0
"Building";"CreepTumor";NA;551;0
"Building";"CreepTumor";NA;551;0
"Building";"CreepTumorQueen";NA;551;0
"Unit";"Viper";"Larva";567;3
"Unit";"Viper";"Larva";567;3
"Building";"CreepTumor";NA;573;0
"Building";"CreepTumor";NA;573;0
"Building";"CreepTumor";NA;573;0
"Building";"CreepTumor";NA;573;0
"Building";"CreepTumor";NA;573;0
"Building";"CreepTumor";NA;573;0
"Building";"CreepTumor";NA;573;0
"Building";"CreepTumorQueen";NA;573;0
"Building";"CreepTumorQueen";NA;573;0
"Unit";"Overlord";"Larva";573;0
"Unit";"Overlord";"Larva";573;0
"Unit";"Zergling";"Larva";573;1
"Unit";"Zergling";"Larva";573;1
"Unit";"Zergling";"Larva";573;1
"Unit";"Zergling";"Larva";573;1
"Unit";"Zergling";"Larva";573;1
"Unit";"Zergling";"Larva";573;1
"Unit";"Zergling";"Larva";573;1
"Unit";"Zergling";"Larva";573;1
"Unit";"Zergling";"Larva";573;1
"Unit";"Zergling";"Larva";573;1
"Unit";"Zergling";"Larva";573;1
"Unit";"Zergling";"Larva";573;1
"Unit";"Zergling";"Larva";573;1
"Unit";"Zergling";"Larva";573;1
"Unit";"Zergling";"Larva";573;1
"Unit";"Zergling";"Larva";573;1
"Unit";"Zergling";"Larva";573;1
"Unit";"Zergling";"Larva";573;1
"Unit";"Zergling";"Larva";573;1
"Unit";"Zergling";"Larva";573;1
"Unit";"Zergling";"Larva";573;1
"Unit";"Zergling";"Larva";573;1
"Unit";"Zergling";"Larva";573;1
"Unit";"Zergling";"Larva";573;1
"Unit";"Zergling";"Larva";573;1
"Unit";"Zergling";"Larva";573;1
"Unit";"Zergling";"Larva";573;1
"Unit";"Zergling";"Larva";573;1
"Unit";"Zergling";"Larva";573;1
"Unit";"Zergling";"Larva";573;1
"Unit";"Zergling";"Larva";573;1
"Unit";"Zergling";"Larva";573;1
"Unit";"Zergling";"Larva";573;1
"Unit";"Zergling";"Larva";573;1
"Unit";"Zergling";"Larva";573;1
"Unit";"Zergling";"Larva";573;1
"Unit";"Zergling";"Larva";573;1
"Unit";"Zergling";"Larva";573;1
"Unit";"Zergling";"Larva";573;1
"Unit";"Zergling";"Larva";573;1
"Building";"CreepTumor";NA;573;0
"Unit";"Hydralisk";"Larva";573;2
"Unit";"Hydralisk";"Larva";573;2
"Unit";"Hydralisk";"Larva";573;2
"Unit";"Hydralisk";"Larva";573;2
"Unit";"Hydralisk";"Larva";573;2
"Unit";"Hydralisk";"Larva";573;2
"Unit";"Hydralisk";"Larva";573;2
"Unit";"Hydralisk";"Larva";573;2
"Unit";"Hydralisk";"Larva";573;2
"Unit";"Hydralisk";"Larva";573;2
"Unit";"Hydralisk";"Larva";573;2
"Unit";"Hydralisk";"Larva";573;2
"Building";"CreepTumor";NA;573;0
"Building";"CreepTumor";NA;573;0
"Building";"CreepTumor";NA;573;0
"Building";"CreepTumor";NA;573;0
"Building";"CreepTumor";NA;573;0
"Unit";"Baneling";"Zergling";613;0
"Unit";"Baneling";"Zergling";613;0
"Unit";"Baneling";"Zergling";613;0
"Unit";"Baneling";"Zergling";613;0
"Unit";"Baneling";"Zergling";613;0
"Unit";"Baneling";"Zergling";613;0
"Unit";"Baneling";"Zergling";613;0
"Unit";"Baneling";"Zergling";613;0
"Unit";"Baneling";"Zergling";613;0
"Unit";"Baneling";"Zergling";613;0
"Unit";"Baneling";"Zergling";613;0
"Unit";"Baneling";"Zergling";613;0
"Unit";"Baneling";"Zergling";613;0
"Unit";"Baneling";"Zergling";613;0
"Unit";"Baneling";"Zergling";613;0
"Unit";"Baneling";"Zergling";613;0
"Unit";"Baneling";"Zergling";613;0
"Unit";"Baneling";"Zergling";613;0
"Unit";"Baneling";"Zergling";613;0
"Building";"CreepTumor";NA;637;0
"Unit";"Ultralisk";"Larva";573;6
"Unit";"Ultralisk";"Larva";573;6
"Unit";"Ultralisk";"Larva";573;6
"Unit";"Ultralisk";"Larva";573;6
"Unit";"Baneling";"Zergling";637;0
"Unit";"Baneling";"Zergling";637;0
"Unit";"Baneling";"Zergling";637;0
"Unit";"Baneling";"Zergling";637;0
"Unit";"Baneling";"Zergling";637;0
"Unit";"Baneling";"Zergling";637;0
"Unit";"Baneling";"Zergling";637;0
"Unit";"Baneling";"Zergling";637;0
"Unit";"Baneling";"Zergling";637;0
"Unit";"Baneling";"Zergling";637;0
"Unit";"Ultralisk";"Larva";613;6
"Unit";"Ultralisk";"Larva";613;6
"Unit";"Ultralisk";"Larva";613;6
"Unit";"Ultralisk";"Larva";615;6
"Building";"CreepTumor";NA;661;0
"Building";"CreepTumor";NA;661;0
"Building";"SporeCrawler";NA;685;0
"Building";"CreepTumor";NA;685;0
"Building";"CreepTumor";NA;685;0
