"type";"unit_name";"on_building";"total_supply";"supply"
"Unit";"Overlord";"Larva";13;0
"Building";"SpawningPool";NA;14;0
"Building";"Extractor";NA;18;0
"Unit";"Zergling";"Larva";20;1
"Unit";"Zergling";"Larva";20;1
"Unit";"Overlord";"Larva";21;0
"Unit";"Queen";"Hatchery";21;2
"Unit";"Zergling";"Larva";23;1
"Unit";"Zergling";"Larva";23;1
"Building";"Hatchery";NA;18;0
"Unit";"Queen";"Hatchery";24;2
"Unit";"Overlord";"Larva";39;0
"Unit";"Overlord";"Larva";39;0
"Unit";"Zergling";"Larva";41;1
"Unit";"Zergling";"Larva";41;1
"Unit";"Zergling";"Larva";44;1
"Unit";"Zergling";"Larva";44;1
"Unit";"Zergling";"Larva";44;1
"Unit";"Zergling";"Larva";44;1
"Building";"Extractor";NA;41;0
"Unit";"Zergling";"Larva";47;1
"Unit";"Zergling";"Larva";47;1
"Unit";"Queen";"Hatchery";41;2
"Unit";"Overlord";"Larva";55;0
"Building";"Extractor";NA;51;0
"Building";"Extractor";NA;55;0
"Building";"CreepTumorQueen";NA;60;0
"Unit";"Overlord";"Larva";63;0
"Building";"SpineCrawler";NA;58;0
"Unit";"Overlord";"Larva";63;0
"Unit";"Queen";"Hatchery";60;2
"Building";"SporeCrawler";NA;63;0
"Building";"CreepTumorQueen";NA;67;0
"Building";"CreepTumorQueen";NA;67;0
"Building";"CreepTumor";NA;67;0
"Building";"Spire";NA;60;0
"Building";"CreepTumor";NA;82;0
"Building";"CreepTumor";NA;82;0
"Unit";"Overlord";"Larva";82;0
"Building";"CreepTumor";NA;82;0
"Building";"BanelingNest";NA;76;0
"Unit";"Mutalisk";"Larva";85;2
"Unit";"Mutalisk";"Larva";85;2
"Unit";"Mutalisk";"Larva";85;2
"Unit";"Mutalisk";"Larva";85;2
"Unit";"Mutalisk";"Larva";85;2
"Building";"CreepTumor";NA;85;0
"Unit";"Mutalisk";"Larva";85;2
"Building";"CreepTumor";NA;85;0
"Building";"CreepTumor";NA;91;0
"Unit";"Mutalisk";"Larva";85;2
"Unit";"Mutalisk";"Larva";85;2
"Building";"EvolutionChamber";NA;95;0
"Building";"EvolutionChamber";NA;95;0
"Building";"CreepTumorQueen";NA;104;0
"Building";"HydraliskDen";NA;97;0
"Building";"CreepTumorQueen";NA;104;0
"Unit";"Overlord";"Larva";103;0
"Unit";"Overlord";"Larva";104;0
"Unit";"Zergling";"Larva";104;1
"Unit";"Zergling";"Larva";104;1
"Unit";"Zergling";"Larva";104;1
"Unit";"Zergling";"Larva";104;1
"Unit";"Zergling";"Larva";104;1
"Unit";"Zergling";"Larva";104;1
"Building";"CreepTumor";NA;112;0
"Building";"CreepTumor";NA;112;0
"Building";"CreepTumor";NA;112;0
"Building";"CreepTumorQueen";NA;114;0
"Building";"CreepTumorQueen";NA;114;0
"Building";"Hatchery";NA;93;0
"Building";"CreepTumor";NA;124;0
"Building";"CreepTumor";NA;124;0
"Building";"CreepTumor";NA;124;0
"Building";"CreepTumor";NA;124;0
"Building";"CreepTumor";NA;124;0
"Building";"CreepTumor";NA;126;0
"Building";"CreepTumorQueen";NA;126;0
"Building";"Extractor";NA;124;0
"Building";"Extractor";NA;124;0
"Upgrade";"EvolveMuscularAugments";"HydraliskDen";114;0
"Building";"InfestationPit";NA;124;0
"Building";"CreepTumorQueen";NA;129;0
"Unit";"Overlord";"Larva";132;0
"Unit";"Overlord";"Larva";132;0
"Unit";"Overlord";"Larva";132;0
"Unit";"Overlord";"Larva";132;0
"Unit";"Hydralisk";"Larva";132;2
"Unit";"Hydralisk";"Larva";132;2
"Unit";"Hydralisk";"Larva";132;2
"Unit";"Hydralisk";"Larva";132;2
"Unit";"Baneling";"Zergling";132;0
"Unit";"Baneling";"Zergling";132;0
"Unit";"Baneling";"Zergling";132;0
"Unit";"Baneling";"Zergling";132;0
"Unit";"Baneling";"Zergling";132;0
"Unit";"Hydralisk";"Larva";132;2
"Unit";"Hydralisk";"Larva";132;2
"Unit";"Baneling";"Zergling";132;0
"Unit";"Baneling";"Zergling";132;0
"Unit";"Baneling";"Zergling";132;0
"Unit";"Baneling";"Zergling";132;0
"Unit";"Hydralisk";"Larva";132;2
"Unit";"Baneling";"Zergling";132;0
"Unit";"Overlord";"Larva";132;0
"Unit";"Overlord";"Larva";132;0
"Unit";"Overlord";"Larva";132;0
"Upgrade";"ZergMissileWeaponsLevel1";"EvolutionChamber";120;0
"Upgrade";"ZergGroundArmorsLevel1";"EvolutionChamber";120;0
"Unit";"Hydralisk";"Larva";132;2
"Unit";"Hydralisk";"Larva";132;2
"Unit";"Hydralisk";"Larva";132;2
"Unit";"Hydralisk";"Larva";146;2
"Unit";"Hydralisk";"Larva";146;2
"Unit";"Hydralisk";"Larva";146;2
"Unit";"Hydralisk";"Larva";146;2
"Unit";"Zergling";"Larva";146;1
"Unit";"Zergling";"Larva";146;1
"Unit";"Zergling";"Larva";146;1
"Unit";"Zergling";"Larva";146;1
"Unit";"Zergling";"Larva";146;1
"Unit";"Zergling";"Larva";146;1
"Unit";"Hydralisk";"Larva";146;2
"Unit";"Hydralisk";"Larva";146;2
"Upgrade";"EvolveGroovedSpines";"HydraliskDen";132;0
"Unit";"Zergling";"Larva";152;1
"Unit";"Zergling";"Larva";152;1
"Unit";"Zergling";"Larva";152;1
"Unit";"Zergling";"Larva";152;1
"Building";"Hatchery";NA;132;0
"Unit";"Hydralisk";"Larva";152;2
"Unit";"Hydralisk";"Larva";152;2
"Unit";"Hydralisk";"Larva";152;2
"Unit";"Zergling";"Larva";156;1
"Unit";"Zergling";"Larva";156;1
"Unit";"Zergling";"Larva";156;1
"Unit";"Zergling";"Larva";156;1
"Unit";"Zergling";"Larva";156;1
"Unit";"Zergling";"Larva";156;1
"Unit";"Zergling";"Larva";158;1
"Unit";"Zergling";"Larva";158;1
"Unit";"Zergling";"Larva";160;1
"Unit";"Zergling";"Larva";160;1
"Unit";"Baneling";"Zergling";170;0
"Unit";"Baneling";"Zergling";170;0
"Unit";"Baneling";"Zergling";170;0
"Unit";"Baneling";"Zergling";170;0
"Unit";"Baneling";"Zergling";170;0
"Unit";"Baneling";"Zergling";170;0
"Unit";"Baneling";"Zergling";170;0
"Unit";"Zergling";"Larva";170;1
"Unit";"Zergling";"Larva";170;1
"Unit";"Zergling";"Larva";170;1
"Unit";"Zergling";"Larva";170;1
"Unit";"Zergling";"Larva";170;1
"Unit";"Zergling";"Larva";170;1
"Unit";"Zergling";"Larva";170;1
"Unit";"Zergling";"Larva";170;1
"Unit";"Hydralisk";"Larva";190;2
"Unit";"Hydralisk";"Larva";190;2
"Unit";"Hydralisk";"Larva";190;2
"Unit";"Hydralisk";"Larva";190;2
"Unit";"Zergling";"Larva";198;1
"Unit";"Zergling";"Larva";198;1
"Unit";"Zergling";"Larva";198;1
"Unit";"Zergling";"Larva";198;1
"Unit";"Zergling";"Larva";198;1
"Unit";"Zergling";"Larva";198;1
"Unit";"Zergling";"Larva";198;1
"Unit";"Zergling";"Larva";198;1
"Unit";"Zergling";"Larva";198;1
"Unit";"Zergling";"Larva";198;1
"Unit";"Zergling";"Larva";198;1
"Unit";"Zergling";"Larva";198;1
"Unit";"Zergling";"Larva";218;1
"Unit";"Zergling";"Larva";218;1
"Unit";"Zergling";"Larva";218;1
"Unit";"Zergling";"Larva";218;1
"Unit";"Zergling";"Larva";218;1
"Unit";"Zergling";"Larva";218;1
"Unit";"Zergling";"Larva";218;1
"Unit";"Zergling";"Larva";218;1
"Unit";"Zergling";"Larva";218;1
"Unit";"Zergling";"Larva";218;1
"Unit";"Zergling";"Larva";218;1
"Unit";"Zergling";"Larva";218;1
"Unit";"Zergling";"Larva";218;1
"Unit";"Zergling";"Larva";218;1
"Unit";"Zergling";"Larva";218;1
"Unit";"Zergling";"Larva";218;1
"Unit";"Zergling";"Larva";218;1
"Unit";"Zergling";"Larva";218;1
"Building";"CreepTumor";NA;236;0
"Building";"CreepTumor";NA;236;0
"Building";"CreepTumor";NA;241;0
"Building";"CreepTumorQueen";NA;241;0
"Building";"CreepTumor";NA;241;0
"Building";"CreepTumor";NA;241;0
"Building";"CreepTumorQueen";NA;241;0
"Building";"CreepTumorQueen";NA;241;0
"Building";"CreepTumorQueen";NA;241;0
"Building";"CreepTumorQueen";NA;241;0
"Unit";"Overlord";"Larva";241;0
"Unit";"Overlord";"Larva";241;0
"Unit";"Overlord";"Larva";241;0
"Building";"CreepTumor";NA;241;0
"Building";"CreepTumor";NA;241;0
"Unit";"Baneling";"Zergling";241;0
"Unit";"Baneling";"Zergling";241;0
"Unit";"Baneling";"Zergling";241;0
"Unit";"Baneling";"Zergling";241;0
"Unit";"Baneling";"Zergling";241;0
"Unit";"Baneling";"Zergling";241;0
"Unit";"Baneling";"Zergling";241;0
"Unit";"Baneling";"Zergling";241;0
"Unit";"Baneling";"Zergling";241;0
"Building";"CreepTumor";NA;244;0
"Building";"CreepTumor";NA;244;0
"Building";"CreepTumor";NA;244;0
"Building";"CreepTumor";NA;244;0
"Building";"CreepTumorQueen";NA;245;0
"Building";"CreepTumorQueen";NA;245;0
"Building";"SpineCrawler";NA;241;0
"Building";"SpineCrawler";NA;241;0
"Unit";"Hydralisk";"Larva";245;2
"Unit";"Hydralisk";"Larva";245;2
"Unit";"Hydralisk";"Larva";245;2
"Unit";"Hydralisk";"Larva";245;2
"Unit";"Hydralisk";"Larva";245;2
"Unit";"Hydralisk";"Larva";245;2
"Unit";"Hydralisk";"Larva";245;2
"Unit";"Hydralisk";"Larva";245;2
"Unit";"Hydralisk";"Larva";245;2
"Unit";"Overlord";"Larva";245;0
"Unit";"Overlord";"Larva";245;0
"Unit";"Overlord";"Larva";245;0
"Unit";"Overlord";"Larva";245;0
"Upgrade";"ZergMissileWeaponsLevel2";"EvolutionChamber";241;0
"Upgrade";"ZergGroundArmorsLevel2";"EvolutionChamber";241;0
"Building";"Extractor";NA;245;0
"Building";"Extractor";NA;245;0
"Building";"CreepTumor";NA;263;0
"Building";"CreepTumor";NA;263;0
"Building";"CreepTumor";NA;263;0
"Building";"Hatchery";NA;241;0
"Building";"CreepTumor";NA;263;0
"Building";"CreepTumor";NA;263;0
"Unit";"Zergling";"Larva";263;1
"Unit";"Zergling";"Larva";263;1
"Unit";"Zergling";"Larva";263;1
"Unit";"Zergling";"Larva";263;1
"Unit";"Zergling";"Larva";263;1
"Unit";"Zergling";"Larva";263;1
"Building";"CreepTumor";NA;266;0
"Unit";"Zergling";"Larva";263;1
"Unit";"Zergling";"Larva";263;1
"Building";"CreepTumor";NA;266;0
"Building";"CreepTumor";NA;267;0
"Building";"CreepTumor";NA;269;0
"Unit";"Hydralisk";"Larva";263;2
"Building";"CreepTumor";NA;269;0
"Unit";"Hydralisk";"Larva";263;2
"Unit";"Hydralisk";"Larva";263;2
"Unit";"Hydralisk";"Larva";263;2
"Unit";"Hydralisk";"Larva";263;2
"Unit";"Hydralisk";"Larva";263;2
"Unit";"Hydralisk";"Larva";263;2
"Building";"CreepTumor";NA;269;0
"Building";"CreepTumor";NA;271;0
"Unit";"Zergling";"Larva";291;1
"Unit";"Zergling";"Larva";291;1
"Unit";"Zergling";"Larva";291;1
"Unit";"Zergling";"Larva";291;1
"Unit";"Zergling";"Larva";291;1
"Unit";"Zergling";"Larva";291;1
"Unit";"Zergling";"Larva";291;1
"Unit";"Zergling";"Larva";291;1
"Unit";"Zergling";"Larva";291;1
"Unit";"Zergling";"Larva";291;1
"Unit";"Zergling";"Larva";291;1
"Unit";"Zergling";"Larva";291;1
"Unit";"Zergling";"Larva";291;1
"Unit";"Zergling";"Larva";291;1
"Building";"CreepTumor";NA;291;0
"Building";"CreepTumor";NA;291;0
"Unit";"Hydralisk";"Larva";291;2
"Unit";"Hydralisk";"Larva";291;2
"Unit";"Baneling";"Zergling";291;0
"Unit";"Baneling";"Zergling";291;0
"Unit";"Baneling";"Zergling";291;0
"Unit";"Baneling";"Zergling";291;0
"Unit";"Baneling";"Zergling";291;0
"Unit";"Baneling";"Zergling";291;0
"Unit";"Baneling";"Zergling";291;0
"Unit";"Baneling";"Zergling";291;0
"Unit";"Baneling";"Zergling";291;0
"Unit";"Baneling";"Zergling";291;0
"Unit";"Baneling";"Zergling";291;0
"Unit";"Baneling";"Zergling";291;0
"Unit";"Baneling";"Zergling";291;0
"Unit";"Baneling";"Zergling";291;0
"Unit";"Baneling";"Zergling";291;0
"Unit";"Baneling";"Zergling";291;0
"Building";"CreepTumor";NA;309;0
"Building";"CreepTumor";NA;309;0
"Building";"CreepTumor";NA;309;0
"Building";"CreepTumor";NA;309;0
"Building";"CreepTumor";NA;309;0
"Building";"CreepTumor";NA;309;0
"Building";"CreepTumor";NA;309;0
"Building";"CreepTumor";NA;309;0
"Unit";"Baneling";"Zergling";309;0
"Unit";"Baneling";"Zergling";309;0
"Unit";"Baneling";"Zergling";309;0
"Unit";"Baneling";"Zergling";309;0
"Unit";"Baneling";"Zergling";309;0
"Building";"CreepTumor";NA;309;0
"Building";"CreepTumor";NA;309;0
"Building";"CreepTumor";NA;309;0
"Building";"CreepTumor";NA;309;0
"Building";"SpineCrawler";NA;309;0
"Building";"SpineCrawler";NA;309;0
"Upgrade";"ZergMeleeWeaponsLevel1";"EvolutionChamber";305;0
"Unit";"Zergling";"Larva";309;1
"Unit";"Zergling";"Larva";309;1
"Unit";"Zergling";"Larva";309;1
"Unit";"Zergling";"Larva";309;1
"Unit";"Zergling";"Larva";309;1
"Unit";"Zergling";"Larva";309;1
"Unit";"Zergling";"Larva";309;1
"Unit";"Zergling";"Larva";309;1
"Unit";"Zergling";"Larva";309;1
"Unit";"Zergling";"Larva";309;1
"Unit";"Zergling";"Larva";309;1
"Unit";"Zergling";"Larva";309;1
"Unit";"Zergling";"Larva";309;1
"Unit";"Zergling";"Larva";309;1
"Unit";"Zergling";"Larva";309;1
"Unit";"Zergling";"Larva";309;1
"Unit";"Zergling";"Larva";309;1
"Unit";"Zergling";"Larva";309;1
"Unit";"Zergling";"Larva";309;1
"Unit";"Zergling";"Larva";309;1
"Unit";"Zergling";"Larva";309;1
"Unit";"Zergling";"Larva";309;1
"Unit";"Zergling";"Larva";309;1
"Unit";"Zergling";"Larva";309;1
"Unit";"Zergling";"Larva";309;1
"Unit";"Zergling";"Larva";309;1
"Unit";"Zergling";"Larva";309;1
"Unit";"Zergling";"Larva";309;1
"Unit";"Zergling";"Larva";309;1
"Unit";"Zergling";"Larva";309;1
"Unit";"Zergling";"Larva";309;1
"Unit";"Zergling";"Larva";309;1
"Unit";"Zergling";"Larva";309;1
"Unit";"Zergling";"Larva";309;1
"Building";"CreepTumor";NA;309;0
"Unit";"Hydralisk";"Larva";309;2
"Unit";"Hydralisk";"Larva";309;2
"Unit";"Hydralisk";"Larva";309;2
"Unit";"Hydralisk";"Larva";309;2
"Unit";"Hydralisk";"Larva";309;2
"Unit";"Hydralisk";"Larva";309;2
"Unit";"Hydralisk";"Larva";309;2
"Unit";"Hydralisk";"Larva";309;2
"Unit";"Hydralisk";"Larva";309;2
"Unit";"Hydralisk";"Larva";309;2
"Unit";"Hydralisk";"Larva";309;2
"Unit";"Hydralisk";"Larva";309;2
"Building";"CreepTumor";NA;309;0
"Building";"CreepTumor";NA;309;0
"Building";"CreepTumor";NA;309;0
"Building";"CreepTumor";NA;309;0
"Building";"CreepTumor";NA;309;0
"Building";"CreepTumor";NA;309;0
"Building";"CreepTumor";NA;309;0
"Building";"CreepTumor";NA;321;0
"Building";"CreepTumor";NA;343;0
"Unit";"Baneling";"Zergling";367;0
"Unit";"Baneling";"Zergling";367;0
"Unit";"Baneling";"Zergling";367;0
"Unit";"Baneling";"Zergling";367;0
"Unit";"Baneling";"Zergling";367;0
"Unit";"Baneling";"Zergling";367;0
"Unit";"Baneling";"Zergling";367;0
"Unit";"Baneling";"Zergling";367;0
"Unit";"Baneling";"Zergling";367;0
"Unit";"Baneling";"Zergling";367;0
"Unit";"Baneling";"Zergling";367;0
"Unit";"Baneling";"Zergling";367;0
"Unit";"Baneling";"Zergling";367;0
"Unit";"Baneling";"Zergling";367;0
"Unit";"Baneling";"Zergling";367;0
"Unit";"Baneling";"Zergling";367;0
"Unit";"Baneling";"Zergling";367;0
"Unit";"Baneling";"Zergling";367;0
"Unit";"Baneling";"Zergling";367;0
"Unit";"Baneling";"Zergling";367;0
"Unit";"Baneling";"Zergling";367;0
"Unit";"Baneling";"Zergling";367;0
"Unit";"Baneling";"Zergling";367;0
"Unit";"Baneling";"Zergling";367;0
"Unit";"Baneling";"Zergling";367;0
"Unit";"Baneling";"Zergling";367;0
"Unit";"Baneling";"Zergling";367;0
"Unit";"Baneling";"Zergling";367;0
"Unit";"Baneling";"Zergling";367;0
"Unit";"Baneling";"Zergling";367;0
"Unit";"Baneling";"Zergling";367;0
"Building";"CreepTumor";NA;367;0
"Building";"CreepTumor";NA;367;0
"Building";"CreepTumor";NA;367;0
"Building";"CreepTumor";NA;367;0
"Building";"CreepTumor";NA;367;0
"Building";"CreepTumor";NA;367;0
"Building";"CreepTumor";NA;367;0
"Building";"CreepTumor";NA;367;0
"Building";"UltraliskCavern";NA;367;0
"Building";"CreepTumor";NA;367;0
"Building";"CreepTumor";NA;367;0
"Building";"CreepTumor";NA;367;0
"Unit";"Viper";"Larva";367;3
"Unit";"Viper";"Larva";367;3
"Unit";"Hydralisk";"Larva";367;2
"Unit";"Viper";"Larva";367;3
"Unit";"Hydralisk";"Larva";367;2
"Unit";"Viper";"Larva";367;3
"Unit";"Hydralisk";"Larva";367;2
"Building";"CreepTumor";NA;367;0
"Unit";"Zergling";"Larva";367;1
"Unit";"Zergling";"Larva";367;1
"Building";"Extractor";NA;367;0
"Building";"CreepTumor";NA;387;0
"Building";"CreepTumor";NA;387;0
"Building";"Extractor";NA;387;0
"Building";"CreepTumor";NA;387;0
"Building";"SpineCrawler";NA;385;0
"Building";"SpineCrawler";NA;385;0
"Building";"CreepTumor";NA;387;0
"Building";"CreepTumor";NA;387;0
"Upgrade";"ZergMissileWeaponsLevel3";"EvolutionChamber";367;0
"Upgrade";"ZergGroundArmorsLevel3";"EvolutionChamber";367;0
"Building";"CreepTumor";NA;387;0
"Building";"CreepTumor";NA;387;0
"Unit";"Zergling";"Larva";387;1
"Unit";"Zergling";"Larva";387;1
"Unit";"Zergling";"Larva";387;1
"Unit";"Zergling";"Larva";387;1
"Unit";"Zergling";"Larva";387;1
"Unit";"Zergling";"Larva";387;1
"Unit";"Zergling";"Larva";387;1
"Unit";"Zergling";"Larva";387;1
"Unit";"Zergling";"Larva";387;1
"Unit";"Zergling";"Larva";387;1
"Unit";"Zergling";"Larva";387;1
"Unit";"Zergling";"Larva";387;1
"Unit";"Zergling";"Larva";387;1
"Unit";"Zergling";"Larva";387;1
"Unit";"Zergling";"Larva";387;1
"Unit";"Zergling";"Larva";387;1
"Unit";"Zergling";"Larva";387;1
"Unit";"Zergling";"Larva";387;1
"Unit";"Zergling";"Larva";387;1
"Unit";"Zergling";"Larva";387;1
"Unit";"Zergling";"Larva";387;1
"Unit";"Zergling";"Larva";387;1
"Unit";"Zergling";"Larva";387;1
"Unit";"Zergling";"Larva";387;1
"Unit";"Zergling";"Larva";387;1
"Unit";"Zergling";"Larva";387;1
"Unit";"Zergling";"Larva";387;1
"Unit";"Zergling";"Larva";387;1
"Unit";"Zergling";"Larva";387;1
"Unit";"Zergling";"Larva";387;1
"Unit";"Zergling";"Larva";387;1
"Unit";"Zergling";"Larva";387;1
"Unit";"Zergling";"Larva";387;1
"Unit";"Zergling";"Larva";387;1
"Unit";"Zergling";"Larva";387;1
"Unit";"Zergling";"Larva";387;1
"Unit";"Zergling";"Larva";387;1
"Unit";"Zergling";"Larva";387;1
"Unit";"Zergling";"Larva";387;1
"Unit";"Zergling";"Larva";387;1
"Unit";"Zergling";"Larva";387;1
"Unit";"Zergling";"Larva";387;1
"Unit";"Zergling";"Larva";387;1
"Unit";"Zergling";"Larva";387;1
"Unit";"Zergling";"Larva";387;1
"Unit";"Zergling";"Larva";387;1
"Unit";"Zergling";"Larva";387;1
"Unit";"Zergling";"Larva";387;1
"Unit";"Zergling";"Larva";387;1
"Unit";"Zergling";"Larva";387;1
"Unit";"Zergling";"Larva";387;1
"Unit";"Zergling";"Larva";387;1
"Unit";"Hydralisk";"Larva";387;2
"Unit";"Hydralisk";"Larva";387;2
"Unit";"Hydralisk";"Larva";387;2
"Unit";"Hydralisk";"Larva";387;2
"Unit";"Hydralisk";"Larva";387;2
"Unit";"Hydralisk";"Larva";387;2
"Unit";"Hydralisk";"Larva";387;2
"Unit";"Hydralisk";"Larva";387;2
"Unit";"Hydralisk";"Larva";387;2
"Unit";"Hydralisk";"Larva";387;2
"Unit";"Hydralisk";"Larva";387;2
"Unit";"Hydralisk";"Larva";387;2
"Unit";"Hydralisk";"Larva";387;2
"Unit";"Hydralisk";"Larva";387;2
"Unit";"Hydralisk";"Larva";387;2
"Unit";"Hydralisk";"Larva";387;2
"Unit";"Hydralisk";"Larva";387;2
"Unit";"Hydralisk";"Larva";387;2
"Unit";"Hydralisk";"Larva";387;2
"Unit";"Hydralisk";"Larva";387;2
"Unit";"Hydralisk";"Larva";387;2
"Unit";"Hydralisk";"Larva";387;2
"Unit";"Hydralisk";"Larva";387;2
"Upgrade";"ChitinousPlating";"UltraliskCavern";387;0
"Unit";"Baneling";"Zergling";439;0
"Unit";"Baneling";"Zergling";439;0
"Unit";"Baneling";"Zergling";439;0
"Unit";"Baneling";"Zergling";439;0
"Unit";"Baneling";"Zergling";439;0
"Unit";"Baneling";"Zergling";439;0
"Unit";"Baneling";"Zergling";439;0
"Unit";"Baneling";"Zergling";439;0
"Unit";"Baneling";"Zergling";439;0
"Unit";"Baneling";"Zergling";439;0
"Unit";"Baneling";"Zergling";439;0
"Unit";"Baneling";"Zergling";439;0
"Unit";"Baneling";"Zergling";439;0
"Unit";"Baneling";"Zergling";439;0
"Unit";"Baneling";"Zergling";439;0
"Unit";"Baneling";"Zergling";439;0
"Unit";"Baneling";"Zergling";439;0
"Unit";"Baneling";"Zergling";439;0
"Unit";"Baneling";"Zergling";439;0
"Unit";"Baneling";"Zergling";439;0
"Unit";"Baneling";"Zergling";439;0
"Unit";"Baneling";"Zergling";439;0
"Unit";"Baneling";"Zergling";439;0
"Unit";"Baneling";"Zergling";439;0
"Unit";"Baneling";"Zergling";439;0
"Unit";"Baneling";"Zergling";439;0
"Unit";"Baneling";"Zergling";439;0
"Unit";"Baneling";"Zergling";439;0
"Unit";"Baneling";"Zergling";439;0
"Unit";"Baneling";"Zergling";439;0
"Unit";"Baneling";"Zergling";439;0
"Unit";"Hydralisk";"Larva";485;2
"Unit";"Hydralisk";"Larva";485;2
"Unit";"Hydralisk";"Larva";485;2
"Unit";"Hydralisk";"Larva";485;2
"Unit";"Hydralisk";"Larva";485;2
"Unit";"Hydralisk";"Larva";485;2
"Unit";"Hydralisk";"Larva";485;2
"Unit";"Hydralisk";"Larva";485;2
"Unit";"Hydralisk";"Larva";485;2
"Unit";"Hydralisk";"Larva";485;2
"Unit";"Hydralisk";"Larva";485;2
"Unit";"Hydralisk";"Larva";485;2
"Unit";"Hydralisk";"Larva";485;2
"Unit";"Hydralisk";"Larva";485;2
"Unit";"Hydralisk";"Larva";485;2
"Unit";"Hydralisk";"Larva";485;2
"Unit";"Hydralisk";"Larva";485;2
"Unit";"Hydralisk";"Larva";485;2
"Unit";"Hydralisk";"Larva";485;2
"Unit";"Zergling";"Larva";485;1
"Unit";"Zergling";"Larva";485;1
"Unit";"Zergling";"Larva";485;1
"Unit";"Zergling";"Larva";485;1
"Unit";"Zergling";"Larva";485;1
"Unit";"Zergling";"Larva";485;1
"Unit";"Zergling";"Larva";485;1
"Unit";"Zergling";"Larva";485;1
"Unit";"Zergling";"Larva";485;1
"Unit";"Zergling";"Larva";485;1
"Unit";"Zergling";"Larva";485;1
"Unit";"Zergling";"Larva";485;1
"Unit";"Zergling";"Larva";485;1
"Unit";"Zergling";"Larva";485;1
"Unit";"Zergling";"Larva";485;1
"Unit";"Zergling";"Larva";485;1
"Unit";"Zergling";"Larva";485;1
"Unit";"Zergling";"Larva";485;1
"Unit";"Zergling";"Larva";485;1
"Unit";"Zergling";"Larva";485;1
"Unit";"Zergling";"Larva";485;1
"Unit";"Zergling";"Larva";485;1
"Unit";"Viper";"Larva";485;3
"Unit";"Viper";"Larva";485;3
"Unit";"Zergling";"Larva";545;1
"Unit";"Zergling";"Larva";545;1
"Unit";"Zergling";"Larva";545;1
"Unit";"Zergling";"Larva";545;1
"Unit";"Zergling";"Larva";545;1
"Unit";"Zergling";"Larva";545;1
"Building";"CreepTumor";NA;545;0
"Building";"CreepTumor";NA;545;0
"Unit";"Hydralisk";"Larva";545;2
"Building";"CreepTumor";NA;548;0
"Unit";"Hydralisk";"Larva";545;2
"Unit";"Hydralisk";"Larva";545;2
"Unit";"Hydralisk";"Larva";545;2
"Unit";"Hydralisk";"Larva";545;2
"Unit";"Hydralisk";"Larva";545;2
"Unit";"Hydralisk";"Larva";545;2
"Unit";"Hydralisk";"Larva";545;2
"Unit";"Hydralisk";"Larva";545;2
"Unit";"Hydralisk";"Larva";545;2
"Unit";"Hydralisk";"Larva";545;2
"Unit";"Hydralisk";"Larva";545;2
"Unit";"Hydralisk";"Larva";545;2
"Unit";"Baneling";"Zergling";557;0
"Unit";"Baneling";"Zergling";557;0
"Unit";"Baneling";"Zergling";559;0
"Unit";"Baneling";"Zergling";559;0
"Unit";"Baneling";"Zergling";559;0
"Unit";"Baneling";"Zergling";559;0
"Unit";"Baneling";"Zergling";559;0
"Unit";"Baneling";"Zergling";559;0
"Unit";"Baneling";"Zergling";559;0
"Unit";"Baneling";"Zergling";559;0
"Unit";"Baneling";"Zergling";563;0
"Unit";"Baneling";"Zergling";563;0
"Unit";"Baneling";"Zergling";567;0
"Unit";"Baneling";"Zergling";567;0
"Unit";"Baneling";"Zergling";571;0
"Building";"CreepTumor";NA;583;0
"Building";"Extractor";NA;583;0
"Building";"Extractor";NA;583;0
"Building";"CreepTumorQueen";NA;583;0
