"type";"unit_name";"on_building";"total_supply";"supply"
"Unit";"Overlord";"Larva";13;0
"Building";"Extractor";NA;17;0
"Unit";"Overlord";"Larva";21;0
"Building";"SpawningPool";NA;19;0
"Building";"Hatchery";NA;17;0
"Unit";"Zergling";"Larva";22;1
"Unit";"Zergling";"Larva";22;1
"Unit";"Zergling";"Larva";22;1
"Unit";"Zergling";"Larva";22;1
"Unit";"Queen";"Hatchery";22;2
"Unit";"Queen";"Hatchery";22;2
"Unit";"Overlord";"Larva";35;0
"Unit";"Overlord";"Larva";40;0
"Unit";"Overlord";"Larva";40;0
"Building";"RoachWarren";NA;35;0
"Unit";"Roach";"Larva";40;2
"Unit";"Roach";"Larva";40;2
"Unit";"Roach";"Larva";40;2
"Unit";"Roach";"Larva";40;2
"Unit";"Roach";"Larva";40;2
"Unit";"Roach";"Larva";40;2
"Unit";"Roach";"Larva";40;2
"Unit";"Zergling";"Larva";40;1
"Unit";"Zergling";"Larva";40;1
"Unit";"Zergling";"Larva";40;1
"Unit";"Zergling";"Larva";40;1
"Unit";"Zergling";"Larva";40;1
"Unit";"Zergling";"Larva";40;1
"Unit";"Roach";"Larva";40;2
"Unit";"Roach";"Larva";40;2
"Unit";"Roach";"Larva";40;2
"Unit";"Roach";"Larva";40;2
"Unit";"Overlord";"Larva";40;0
"Unit";"Zergling";"Larva";68;1
"Unit";"Zergling";"Larva";68;1
"Unit";"Zergling";"Larva";68;1
"Unit";"Zergling";"Larva";68;1
"Unit";"Overlord";"Larva";68;0
"Unit";"Overlord";"Larva";68;0
"Unit";"Zergling";"Larva";72;1
"Unit";"Zergling";"Larva";72;1
"Unit";"Zergling";"Larva";72;1
"Unit";"Zergling";"Larva";72;1
"Unit";"Zergling";"Larva";72;1
"Unit";"Zergling";"Larva";72;1
"Unit";"Zergling";"Larva";72;1
"Unit";"Zergling";"Larva";72;1
"Unit";"Zergling";"Larva";72;1
"Unit";"Zergling";"Larva";72;1
"Unit";"Zergling";"Larva";72;1
"Unit";"Zergling";"Larva";72;1
"Unit";"Zergling";"Larva";72;1
"Unit";"Zergling";"Larva";72;1
"Unit";"Zergling";"Larva";72;1
"Unit";"Zergling";"Larva";72;1
"Unit";"Zergling";"Larva";88;1
"Unit";"Zergling";"Larva";88;1
"Unit";"Zergling";"Larva";88;1
"Unit";"Zergling";"Larva";88;1
"Unit";"Zergling";"Larva";88;1
"Unit";"Zergling";"Larva";88;1
"Building";"Hatchery";NA;60;0
"Unit";"Queen";"Hatchery";88;2
"Unit";"Queen";"Hatchery";88;2
"Building";"Extractor";NA;99;0
"Unit";"Overlord";"Larva";100;0
"Building";"Extractor";NA;100;0
"Building";"CreepTumorQueen";NA;111;0
"Unit";"Queen";"Hatchery";99;2
"Unit";"Roach";"Larva";106;2
"Building";"SporeCrawler";NA;106;0
"Unit";"Roach";"Larva";106;2
"Building";"SporeCrawler";NA;106;0
"Building";"CreepTumor";NA;117;0
"Unit";"Overlord";"Larva";117;0
"Building";"CreepTumorQueen";NA;126;0
"Building";"CreepTumorQueen";NA;130;0
"Building";"CreepTumor";NA;130;0
"Unit";"Overlord";"Larva";130;0
"Unit";"Roach";"Larva";134;2
"Unit";"Roach";"Larva";134;2
"Unit";"Roach";"Larva";134;2
"Unit";"Roach";"Larva";134;2
"Unit";"Roach";"Larva";134;2
"Building";"CreepTumor";NA;134;0
"Building";"CreepTumor";NA;144;0
"Building";"Extractor";NA;134;0
"Unit";"Overlord";"Larva";134;0
"Building";"CreepTumor";NA;152;0
"Building";"EvolutionChamber";NA;152;0
"Building";"CreepTumor";NA;157;0
"Building";"Extractor";NA;157;0
"Building";"Extractor";NA;157;0
"Unit";"Roach";"Larva";163;2
"Unit";"Roach";"Larva";163;2
"Unit";"Roach";"Larva";163;2
"Unit";"Roach";"Larva";163;2
"Unit";"Roach";"Larva";166;2
"Building";"InfestationPit";NA;163;0
"Unit";"Overlord";"Larva";166;0
"Unit";"Overlord";"Larva";166;0
"Unit";"Overlord";"Larva";166;0
"Unit";"Overlord";"Larva";166;0
"Unit";"Overlord";"Larva";166;0
"Building";"CreepTumor";NA;176;0
"Building";"CreepTumor";NA;176;0
"Building";"EvolutionChamber";NA;174;0
"Building";"CreepTumorQueen";NA;176;0
"Building";"BanelingNest";NA;166;0
"Unit";"Roach";"Larva";176;2
"Unit";"Roach";"Larva";176;2
"Unit";"Roach";"Larva";176;2
"Unit";"Roach";"Larva";176;2
"Unit";"Roach";"Larva";176;2
"Unit";"Roach";"Larva";176;2
"Unit";"Roach";"Larva";176;2
"Unit";"Roach";"Larva";176;2
"Unit";"Roach";"Larva";176;2
"Building";"Hatchery";NA;163;0
"Upgrade";"GlialReconstitution";"RoachWarren";166;0
"Unit";"Roach";"Larva";178;2
"Unit";"Roach";"Larva";186;2
"Unit";"Roach";"Larva";186;2
"Unit";"Roach";"Larva";186;2
"Unit";"Roach";"Larva";186;2
"Unit";"Roach";"Larva";194;2
"Unit";"Roach";"Larva";194;2
"Unit";"Roach";"Larva";194;2
"Unit";"Roach";"Larva";194;2
"Unit";"Roach";"Larva";194;2
"Unit";"Overlord";"Larva";214;0
"Unit";"Overlord";"Larva";214;0
"Building";"CreepTumor";NA;214;0
"Building";"CreepTumorQueen";NA;221;0
"Building";"Spire";NA;176;0
"Unit";"Overlord";"Larva";221;0
"Unit";"Overlord";"Larva";221;0
"Unit";"Overlord";"Larva";221;0
"Building";"Extractor";NA;221;0
"Building";"Extractor";NA;221;0
"Unit";"Roach";"Larva";230;2
"Unit";"Roach";"Larva";230;2
"Unit";"Roach";"Larva";230;2
"Unit";"Roach";"Larva";230;2
"Unit";"Roach";"Larva";230;2
"Building";"CreepTumor";NA;230;0
"Building";"SporeCrawler";NA;230;0
"Unit";"Roach";"Larva";240;2
"Unit";"Roach";"Larva";240;2
"Unit";"Roach";"Larva";240;2
"Unit";"Roach";"Larva";240;2
"Unit";"Corruptor";"Larva";240;2
"Unit";"Corruptor";"Larva";240;2
"Unit";"Corruptor";"Larva";240;2
"Unit";"Corruptor";"Larva";240;2
"Unit";"Zergling";"Larva";248;1
"Unit";"Zergling";"Larva";248;1
"Building";"CreepTumor";NA;248;0
"Building";"CreepTumorQueen";NA;248;0
"Unit";"Corruptor";"Larva";248;2
"Unit";"Corruptor";"Larva";248;2
"Upgrade";"ZergMissileWeaponsLevel1";"EvolutionChamber";230;0
"Upgrade";"ZergGroundArmorsLevel1";"EvolutionChamber";230;0
"Unit";"Queen";"Hatchery";248;2
"Unit";"Queen";"Hatchery";248;2
"Unit";"Queen";"Hatchery";248;2
"Unit";"Queen";"Hatchery";248;2
"Building";"HydraliskDen";NA;270;0
"Unit";"Roach";"Larva";273;2
"Unit";"Roach";"Larva";273;2
"Unit";"Roach";"Larva";273;2
"Unit";"Roach";"Larva";273;2
"Unit";"Roach";"Larva";273;2
"Unit";"Roach";"Larva";273;2
"Unit";"Roach";"Larva";273;2
"Unit";"Roach";"Larva";273;2
"Unit";"Roach";"Larva";273;2
"Unit";"Roach";"Larva";273;2
"Unit";"Roach";"Larva";273;2
"Unit";"Roach";"Larva";273;2
"Unit";"Roach";"Larva";273;2
"Unit";"Roach";"Larva";273;2
"Unit";"Roach";"Larva";273;2
"Unit";"Roach";"Larva";273;2
"Unit";"Overlord";"Larva";273;0
"Unit";"Overlord";"Larva";273;0
"Unit";"Overlord";"Larva";273;0
"Building";"CreepTumor";NA;305;0
"Unit";"Corruptor";"Larva";281;2
"Unit";"Corruptor";"Larva";281;2
"Building";"Extractor";NA;305;0
"Unit";"Corruptor";"Larva";305;2
"Unit";"Corruptor";"Larva";305;2
"Unit";"Zergling";"Larva";320;1
"Unit";"Zergling";"Larva";320;1
"Unit";"Zergling";"Larva";320;1
"Unit";"Zergling";"Larva";320;1
"Unit";"Zergling";"Larva";320;1
"Unit";"Zergling";"Larva";320;1
"Unit";"Zergling";"Larva";320;1
"Unit";"Zergling";"Larva";320;1
"Unit";"Zergling";"Larva";320;1
"Unit";"Zergling";"Larva";320;1
"Unit";"Zergling";"Larva";320;1
"Unit";"Zergling";"Larva";320;1
"Unit";"Zergling";"Larva";320;1
"Unit";"Zergling";"Larva";320;1
"Unit";"Zergling";"Larva";320;1
"Unit";"Zergling";"Larva";320;1
"Unit";"Zergling";"Larva";320;1
"Unit";"Zergling";"Larva";320;1
"Unit";"Zergling";"Larva";320;1
"Unit";"Zergling";"Larva";320;1
"Unit";"Zergling";"Larva";320;1
"Unit";"Zergling";"Larva";320;1
"Unit";"Zergling";"Larva";320;1
"Unit";"Zergling";"Larva";320;1
"Unit";"Zergling";"Larva";320;1
"Unit";"Zergling";"Larva";320;1
"Unit";"Zergling";"Larva";320;1
"Unit";"Zergling";"Larva";320;1
"Unit";"Zergling";"Larva";320;1
"Unit";"Zergling";"Larva";320;1
"Unit";"Zergling";"Larva";320;1
"Unit";"Zergling";"Larva";320;1
"Unit";"Corruptor";"Larva";320;2
"Unit";"Corruptor";"Larva";320;2
"Unit";"Corruptor";"Larva";320;2
"Unit";"Corruptor";"Larva";320;2
"Unit";"Corruptor";"Larva";320;2
