"type";"unit_name";"on_building";"total_supply";"supply"
"Unit";"Overlord";"Larva";13;0
"Building";"Extractor";NA;18;0
"Unit";"Overlord";"Larva";21;0
"Building";"SpawningPool";NA;19;0
"Building";"Hatchery";NA;17;0
"Unit";"Zergling";"Larva";22;1
"Unit";"Zergling";"Larva";22;1
"Unit";"Zergling";"Larva";22;1
"Unit";"Zergling";"Larva";22;1
"Unit";"Queen";"Hatchery";22;2
"Unit";"Queen";"Hatchery";22;2
"Building";"CreepTumorQueen";NA;32;0
"Unit";"Overlord";"Larva";35;0
"Unit";"Queen";"Hatchery";33;2
"Unit";"Overlord";"Larva";38;0
"Unit";"Zergling";"Larva";40;1
"Unit";"Zergling";"Larva";40;1
"Unit";"Zergling";"Larva";41;1
"Unit";"Zergling";"Larva";41;1
"Building";"CreepTumorQueen";NA;45;0
"Building";"Hatchery";NA;28;0
"Building";"CreepTumor";NA;45;0
"Unit";"Overlord";"Larva";49;0
"Building";"CreepTumor";NA;51;0
"Unit";"Zergling";"Larva";51;1
"Unit";"Zergling";"Larva";51;1
"Unit";"Zergling";"Larva";51;1
"Unit";"Zergling";"Larva";51;1
"Unit";"Zergling";"Larva";51;1
"Unit";"Zergling";"Larva";51;1
"Building";"CreepTumor";NA;54;0
"Unit";"Queen";"Hatchery";49;2
"Unit";"Queen";"Hatchery";49;2
"Unit";"Overlord";"Larva";54;0
"Building";"CreepTumor";NA;70;0
"Building";"SporeCrawler";NA;70;0
"Building";"CreepTumor";NA;70;0
"Building";"SporeCrawler";NA;70;0
"Building";"RoachWarren";NA;65;0
"Building";"SporeCrawler";NA;70;0
"Unit";"Queen";"Hatchery";70;2
"Unit";"Queen";"Hatchery";70;2
"Building";"CreepTumor";NA;72;0
"Unit";"Queen";"Hatchery";70;2
"Building";"CreepTumorQueen";NA;73;0
"Unit";"Overlord";"Larva";76;0
"Unit";"Overlord";"Larva";82;0
"Building";"CreepTumor";NA;89;0
"Unit";"Roach";"Larva";89;2
"Unit";"Roach";"Larva";89;2
"Building";"Extractor";NA;89;0
"Building";"Extractor";NA;89;0
"Unit";"Roach";"Larva";89;2
"Building";"EvolutionChamber";NA;89;0
"Building";"EvolutionChamber";NA;89;0
"Unit";"Roach";"Larva";89;2
"Unit";"Roach";"Larva";89;2
"Unit";"Queen";"Hatchery";87;2
"Unit";"Roach";"Larva";89;2
"Unit";"Overlord";"Larva";103;0
"Unit";"Overlord";"Larva";118;0
"Unit";"Overlord";"Larva";118;0
"Unit";"Overlord";"Larva";118;0
"Building";"CreepTumor";NA;118;0
"Building";"CreepTumor";NA;118;0
"Building";"CreepTumorQueen";NA;118;0
"Building";"CreepTumorQueen";NA;118;0
"Unit";"Overlord";"Larva";118;0
"Building";"Extractor";NA;118;0
"Building";"CreepTumorQueen";NA;118;0
"Building";"Extractor";NA;118;0
"Building";"Extractor";NA;118;0
"Unit";"Overlord";"Larva";118;0
"Building";"CreepTumor";NA;118;0
"Building";"CreepTumor";NA;118;0
"Building";"CreepTumor";NA;119;0
"Unit";"Queen";"Hatchery";118;2
"Unit";"Queen";"Hatchery";118;2
"Unit";"Roach";"Larva";118;2
"Unit";"Roach";"Larva";121;2
"Building";"CreepTumor";NA;126;0
"Unit";"Queen";"Hatchery";118;2
"Unit";"Roach";"Larva";126;2
"Unit";"Roach";"Larva";126;2
"Unit";"Roach";"Larva";126;2
"Building";"CreepTumor";NA;136;0
"Building";"CreepTumor";NA;138;0
"Building";"CreepTumor";NA;140;0
"Building";"CreepTumorQueen";NA;142;0
"Unit";"Overlord";"Larva";140;0
"Unit";"Overlord";"Larva";140;0
"Unit";"Roach";"Larva";142;2
"Unit";"Roach";"Larva";142;2
"Unit";"Roach";"Larva";142;2
"Unit";"Roach";"Larva";142;2
"Unit";"Queen";"Hatchery";132;2
"Unit";"Queen";"Hatchery";136;2
"Unit";"Roach";"Larva";142;2
"Unit";"Roach";"Larva";142;2
"Building";"CreepTumor";NA;142;0
"Building";"CreepTumor";NA;142;0
"Building";"CreepTumor";NA;150;0
"Unit";"Overlord";"Larva";142;0
"Unit";"Roach";"Larva";152;2
"Unit";"Roach";"Larva";152;2
"Unit";"Roach";"Larva";152;2
"Unit";"Roach";"Larva";152;2
"Building";"CreepTumor";NA;159;0
"Building";"Hatchery";NA;124;0
"Building";"CreepTumor";NA;159;0
"Building";"CreepTumor";NA;159;0
"Unit";"Overlord";"Larva";159;0
"Unit";"Overlord";"Larva";159;0
"Unit";"Overlord";"Larva";159;0
"Upgrade";"ZergMissileWeaponsLevel1";"EvolutionChamber";123;0
"Upgrade";"ZergGroundArmorsLevel1";"EvolutionChamber";123;0
"Building";"CreepTumor";NA;167;0
"Unit";"Roach";"Larva";167;2
"Unit";"Roach";"Larva";167;2
"Unit";"Roach";"Larva";167;2
"Unit";"Roach";"Larva";167;2
"Unit";"Roach";"Larva";167;2
"Building";"CreepTumor";NA;167;0
"Unit";"Zergling";"Larva";167;1
"Unit";"Zergling";"Larva";167;1
"Building";"InfestationPit";NA;159;0
"Building";"CreepTumor";NA;180;0
"Building";"Hatchery";NA;142;0
"Building";"CreepTumor";NA;182;0
"Unit";"Overlord";"Larva";180;0
"Building";"CreepTumor";NA;182;0
"Unit";"Overlord";"Larva";180;0
"Building";"CreepTumor";NA;182;0
"Building";"Extractor";NA;182;0
"Building";"Extractor";NA;182;0
"Upgrade";"GlialReconstitution";"RoachWarren";179;0
"Unit";"Infestor";"Larva";182;2
"Unit";"Infestor";"Larva";182;2
"Building";"CreepTumor";NA;188;0
"Building";"CreepTumorQueen";NA;188;0
"Building";"CreepTumor";NA;188;0
"Building";"HydraliskDen";NA;182;0
"Building";"CreepTumorQueen";NA;188;0
"Unit";"Overlord";"Larva";192;0
"Unit";"Overlord";"Larva";192;0
"Building";"CreepTumorQueen";NA;192;0
"Unit";"Hydralisk";"Larva";192;2
"Unit";"Hydralisk";"Larva";192;2
"Unit";"Hydralisk";"Larva";192;2
"Unit";"Hydralisk";"Larva";192;2
"Unit";"Hydralisk";"Larva";192;2
"Unit";"Hydralisk";"Larva";192;2
"Unit";"Hydralisk";"Larva";192;2
"Unit";"Hydralisk";"Larva";192;2
"Unit";"Hydralisk";"Larva";192;2
"Unit";"Hydralisk";"Larva";192;2
"Unit";"Hydralisk";"Larva";192;2
"Building";"SpineCrawler";NA;192;0
"Building";"SpineCrawler";NA;192;0
"Building";"SpineCrawler";NA;192;0
"Building";"CreepTumor";NA;216;0
"Building";"CreepTumor";NA;216;0
"Upgrade";"ZergMissileWeaponsLevel2";"EvolutionChamber";182;0
"Unit";"Roach";"Larva";216;2
"Unit";"Roach";"Larva";216;2
"Unit";"Hydralisk";"Larva";216;2
"Building";"CreepTumor";NA;216;0
"Unit";"Hydralisk";"Larva";216;2
"Unit";"Hydralisk";"Larva";216;2
"Unit";"Hydralisk";"Larva";216;2
"Unit";"Hydralisk";"Larva";216;2
"Unit";"Hydralisk";"Larva";216;2
"Unit";"Viper";"Larva";216;3
"Unit";"Viper";"Larva";216;3
"Building";"CreepTumor";NA;216;0
"Building";"CreepTumor";NA;216;0
"Unit";"Viper";"Larva";216;3
"Unit";"Roach";"Larva";216;2
"Unit";"Roach";"Larva";216;2
"Upgrade";"ZergGroundArmorsLevel2";"EvolutionChamber";182;0
"Building";"Hatchery";NA;192;0
"Upgrade";"EvolveMuscularAugments";"HydraliskDen";194;0
"Building";"CreepTumor";NA;248;0
"Building";"CreepTumor";NA;248;0
"Building";"CreepTumor";NA;248;0
"Unit";"Roach";"Larva";248;2
"Unit";"Roach";"Larva";248;2
"Unit";"Roach";"Larva";248;2
"Building";"Extractor";NA;248;0
"Unit";"Hydralisk";"Larva";248;2
"Unit";"Hydralisk";"Larva";248;2
"Unit";"Hydralisk";"Larva";248;2
"Unit";"Hydralisk";"Larva";248;2
"Unit";"Hydralisk";"Larva";248;2
"Building";"Extractor";NA;248;0
"Building";"CreepTumor";NA;248;0
"Unit";"Hydralisk";"Larva";248;2
"Unit";"Hydralisk";"Larva";248;2
"Unit";"Hydralisk";"Larva";248;2
"Unit";"Hydralisk";"Larva";248;2
"Unit";"Hydralisk";"Larva";248;2
"Unit";"Hydralisk";"Larva";248;2
"Unit";"Hydralisk";"Larva";248;2
"Upgrade";"EvolveGroovedSpines";"HydraliskDen";248;0
"Building";"Spire";NA;248;0
"Unit";"Roach";"Larva";264;2
"Unit";"Roach";"Larva";264;2
"Unit";"Roach";"Larva";264;2
"Unit";"Roach";"Larva";264;2
"Unit";"Roach";"Larva";264;2
"Unit";"Roach";"Larva";264;2
"Unit";"Roach";"Larva";264;2
"Unit";"Roach";"Larva";264;2
"Unit";"Roach";"Larva";264;2
"Unit";"Roach";"Larva";264;2
"Unit";"Roach";"Larva";264;2
"Unit";"Roach";"Larva";264;2
"Unit";"Roach";"Larva";264;2
"Unit";"Roach";"Larva";264;2
"Unit";"Roach";"Larva";264;2
"Unit";"Roach";"Larva";264;2
"Unit";"Roach";"Larva";264;2
"Unit";"Roach";"Larva";278;2
"Unit";"Roach";"Larva";278;2
"Unit";"Roach";"Larva";278;2
"Unit";"Roach";"Larva";278;2
"Unit";"Zergling";"Larva";278;1
"Unit";"Zergling";"Larva";278;1
"Unit";"Zergling";"Larva";278;1
"Unit";"Zergling";"Larva";278;1
"Unit";"Zergling";"Larva";278;1
"Unit";"Zergling";"Larva";278;1
"Upgrade";"Burrow";"Hatchery";250;0
"Unit";"Roach";"Larva";278;2
"Unit";"Roach";"Larva";278;2
"Unit";"Roach";"Larva";278;2
"Unit";"Roach";"Larva";278;2
"Unit";"Roach";"Larva";278;2
"Unit";"Roach";"Larva";278;2
"Unit";"Roach";"Larva";278;2
"Unit";"Roach";"Larva";278;2
"Unit";"Roach";"Larva";278;2
"Unit";"Roach";"Larva";278;2
"Unit";"Roach";"Larva";288;2
"Unit";"Roach";"Larva";312;2
"Unit";"Roach";"Larva";312;2
"Unit";"Roach";"Larva";326;2
"Unit";"Roach";"Larva";326;2
"Unit";"Roach";"Larva";326;2
"Unit";"Hydralisk";"Larva";346;2
"Unit";"Hydralisk";"Larva";346;2
"Unit";"Hydralisk";"Larva";346;2
"Unit";"Hydralisk";"Larva";352;2
"Unit";"Hydralisk";"Larva";352;2
"Unit";"Hydralisk";"Larva";358;2
"Unit";"Hydralisk";"Larva";358;2
"Building";"CreepTumor";NA;368;0
"Building";"CreepTumorQueen";NA;378;0
"Unit";"Viper";"Larva";378;3
"Unit";"Viper";"Larva";378;3
"Unit";"Viper";"Larva";378;3
"Building";"CreepTumorQueen";NA;378;0
"Building";"CreepTumor";NA;378;0
"Unit";"Hydralisk";"Larva";378;2
"Unit";"Hydralisk";"Larva";378;2
"Building";"CreepTumorQueen";NA;391;0
"Unit";"Hydralisk";"Larva";391;2
"Unit";"Hydralisk";"Larva";391;2
"Unit";"Hydralisk";"Larva";391;2
"Unit";"Hydralisk";"Larva";391;2
"Unit";"Hydralisk";"Larva";391;2
"Building";"Hatchery";NA;372;0
"Unit";"Hydralisk";"Larva";391;2
"Unit";"Hydralisk";"Larva";391;2
"Building";"CreepTumor";NA;409;0
"Building";"CreepTumor";NA;409;0
"Unit";"Roach";"Larva";405;2
"Unit";"Roach";"Larva";405;2
"Unit";"Roach";"Larva";405;2
"Unit";"Roach";"Larva";405;2
"Unit";"Roach";"Larva";405;2
"Unit";"Roach";"Larva";405;2
"Unit";"Roach";"Larva";405;2
"Unit";"Roach";"Larva";405;2
"Unit";"Roach";"Larva";405;2
"Building";"CreepTumor";NA;409;0
"Building";"CreepTumor";NA;409;0
"Building";"CreepTumor";NA;409;0
"Building";"CreepTumor";NA;425;0
"Unit";"Roach";"Larva";427;2
"Unit";"Roach";"Larva";427;2
"Unit";"Roach";"Larva";427;2
"Unit";"Roach";"Larva";427;2
"Unit";"Roach";"Larva";427;2
"Unit";"Roach";"Larva";427;2
"Unit";"Roach";"Larva";427;2
"Unit";"Overlord";"Larva";427;0
"Unit";"Roach";"Larva";427;2
"Unit";"Roach";"Larva";427;2
"Building";"CreepTumor";NA;433;0
"Unit";"Roach";"Larva";441;2
"Unit";"Roach";"Larva";441;2
"Unit";"Roach";"Larva";441;2
"Unit";"Roach";"Larva";441;2
"Building";"CreepTumor";NA;453;0
"Building";"CreepTumor";NA;453;0
"Building";"CreepTumor";NA;453;0
"Building";"CreepTumor";NA;453;0
"Building";"CreepTumor";NA;453;0
"Building";"Hatchery";NA;427;0
"Upgrade";"ZergMissileWeaponsLevel3";"EvolutionChamber";405;0
"Upgrade";"ZergGroundArmorsLevel3";"EvolutionChamber";405;0
"Building";"SpineCrawler";NA;453;0
"Building";"SpineCrawler";NA;453;0
"Unit";"Corruptor";"Larva";453;2
"Unit";"Corruptor";"Larva";453;2
"Unit";"Corruptor";"Larva";453;2
"Unit";"Corruptor";"Larva";453;2
"Unit";"Corruptor";"Larva";453;2
"Unit";"Corruptor";"Larva";453;2
"Unit";"Corruptor";"Larva";453;2
"Building";"CreepTumor";NA;453;0
"Building";"CreepTumor";NA;453;0
"Building";"CreepTumor";NA;453;0
"Building";"CreepTumor";NA;467;0
"Building";"CreepTumor";NA;470;0
"Building";"CreepTumor";NA;476;0
"Unit";"Overlord";"Larva";476;0
"Unit";"Roach";"Larva";476;2
"Unit";"Roach";"Larva";476;2
"Unit";"Roach";"Larva";476;2
"Unit";"Roach";"Larva";476;2
"Unit";"Roach";"Larva";476;2
"Unit";"Roach";"Larva";476;2
"Unit";"Roach";"Larva";476;2
"Unit";"Roach";"Larva";476;2
"Unit";"Hydralisk";"Larva";476;2
"Unit";"Hydralisk";"Larva";476;2
"Unit";"Hydralisk";"Larva";476;2
"Unit";"Hydralisk";"Larva";476;2
"Unit";"Hydralisk";"Larva";476;2
"Unit";"Hydralisk";"Larva";476;2
"Unit";"Hydralisk";"Larva";476;2
"Unit";"Hydralisk";"Larva";476;2
"Unit";"Hydralisk";"Larva";476;2
"Unit";"Hydralisk";"Larva";476;2
"Unit";"Hydralisk";"Larva";476;2
"Unit";"Hydralisk";"Larva";476;2
"Unit";"Hydralisk";"Larva";476;2
"Unit";"Hydralisk";"Larva";476;2
"Unit";"Hydralisk";"Larva";476;2
"Unit";"Hydralisk";"Larva";476;2
"Unit";"Roach";"Larva";476;2
"Unit";"Roach";"Larva";476;2
"Unit";"Roach";"Larva";476;2
"Unit";"Roach";"Larva";476;2
"Unit";"Roach";"Larva";476;2
"Unit";"Roach";"Larva";476;2
"Unit";"Roach";"Larva";476;2
"Unit";"Roach";"Larva";476;2
"Unit";"Roach";"Larva";476;2
"Unit";"Roach";"Larva";524;2
"Unit";"Roach";"Larva";524;2
"Unit";"Roach";"Larva";524;2
"Unit";"Roach";"Larva";524;2
"Unit";"Roach";"Larva";524;2
"Unit";"Roach";"Larva";524;2
"Unit";"Roach";"Larva";524;2
"Building";"CreepTumor";NA;542;0
"Building";"CreepTumor";NA;542;0
"Unit";"Viper";"Larva";556;3
"Unit";"Viper";"Larva";556;3
