"type";"unit_name";"on_building";"total_supply";"supply"
"Unit";"Overlord";"Larva";13;0
"Building";"SpawningPool";NA;13;0
"Unit";"Zergling";"Larva";16;1
"Unit";"Zergling";"Larva";16;1
"Unit";"Zergling";"Larva";16;1
"Unit";"Zergling";"Larva";16;1
"Unit";"Queen";"Hatchery";16;2
"Unit";"Overlord";"Larva";22;0
"Building";"CreepTumorQueen";NA;24;0
