"type";"unit_name";"on_building";"total_supply";"supply"
"Unit";"Overlord";"Larva";13;0
"Building";"Extractor";NA;18;0
"Unit";"Overlord";"Larva";21;0
"Building";"SpawningPool";NA;19;0
"Building";"Hatchery";NA;17;0
"Unit";"Zergling";"Larva";22;1
"Unit";"Zergling";"Larva";22;1
"Unit";"Zergling";"Larva";23;1
"Unit";"Zergling";"Larva";23;1
"Unit";"Queen";"Hatchery";22;2
"Unit";"Queen";"Hatchery";23;2
"Unit";"Overlord";"Larva";34;0
"Building";"CreepTumorQueen";NA;39;0
"Unit";"Overlord";"Larva";39;0
"Unit";"Queen";"Hatchery";39;2
"Unit";"Overlord";"Larva";40;0
"Building";"Hatchery";NA;34;0
"Building";"CreepTumor";NA;49;0
"Building";"CreepTumorQueen";NA;49;0
"Unit";"Zergling";"Larva";49;1
"Unit";"Zergling";"Larva";49;1
"Unit";"Zergling";"Larva";49;1
"Unit";"Zergling";"Larva";49;1
"Unit";"Zergling";"Larva";49;1
"Unit";"Zergling";"Larva";49;1
"Unit";"Zergling";"Larva";49;1
"Unit";"Zergling";"Larva";49;1
"Unit";"Queen";"Hatchery";46;2
"Unit";"Overlord";"Larva";49;0
"Unit";"Overlord";"Larva";50;0
"Building";"CreepTumorQueen";NA;63;0
"Building";"CreepTumorQueen";NA;63;0
"Unit";"Overlord";"Larva";63;0
"Unit";"Queen";"Hatchery";50;2
"Building";"CreepTumor";NA;71;0
"Building";"CreepTumor";NA;71;0
"Building";"Extractor";NA;69;0
"Building";"CreepTumor";NA;71;0
"Building";"CreepTumorQueen";NA;75;0
"Unit";"Overlord";"Larva";71;0
"Building";"BanelingNest";NA;64;0
"Building";"SporeCrawler";NA;76;0
"Building";"CreepTumor";NA;78;0
"Building";"CreepTumor";NA;80;0
"Building";"EvolutionChamber";NA;76;0
"Building";"CreepTumor";NA;81;0
"Building";"EvolutionChamber";NA;76;0
"Building";"Extractor";NA;78;0
"Building";"Extractor";NA;78;0
"Building";"CreepTumor";NA;87;0
"Building";"CreepTumorQueen";NA;87;0
"Unit";"Baneling";"Zergling";87;0
"Unit";"Baneling";"Zergling";87;0
"Unit";"Baneling";"Zergling";87;0
"Unit";"Baneling";"Zergling";87;0
"Unit";"Zergling";"Larva";89;1
"Unit";"Zergling";"Larva";89;1
"Unit";"Overlord";"Larva";87;0
"Unit";"Zergling";"Larva";89;1
"Unit";"Zergling";"Larva";89;1
"Unit";"Zergling";"Larva";89;1
"Unit";"Zergling";"Larva";89;1
"Unit";"Zergling";"Larva";89;1
"Unit";"Zergling";"Larva";89;1
"Unit";"Zergling";"Larva";89;1
"Unit";"Zergling";"Larva";89;1
"Unit";"Zergling";"Larva";89;1
"Unit";"Zergling";"Larva";89;1
"Unit";"Zergling";"Larva";89;1
"Unit";"Zergling";"Larva";89;1
"Unit";"Zergling";"Larva";89;1
"Unit";"Zergling";"Larva";89;1
"Unit";"Zergling";"Larva";89;1
"Unit";"Zergling";"Larva";89;1
"Building";"CreepTumor";NA;107;0
"Unit";"Overlord";"Larva";107;0
"Unit";"Overlord";"Larva";107;0
"Unit";"Overlord";"Larva";107;0
"Unit";"Overlord";"Larva";107;0
"Unit";"Zergling";"Larva";111;1
"Unit";"Zergling";"Larva";111;1
"Unit";"Zergling";"Larva";112;1
"Unit";"Zergling";"Larva";112;1
"Unit";"Zergling";"Larva";112;1
"Unit";"Zergling";"Larva";112;1
"Unit";"Zergling";"Larva";113;1
"Unit";"Zergling";"Larva";113;1
"Unit";"Zergling";"Larva";113;1
"Unit";"Zergling";"Larva";113;1
"Unit";"Zergling";"Larva";113;1
"Unit";"Zergling";"Larva";113;1
"Unit";"Zergling";"Larva";113;1
"Unit";"Zergling";"Larva";113;1
"Unit";"Overlord";"Larva";113;0
"Unit";"Overlord";"Larva";113;0
"Building";"Extractor";NA;113;0
"Unit";"Baneling";"Zergling";127;0
"Unit";"Baneling";"Zergling";127;0
"Unit";"Baneling";"Zergling";127;0
"Unit";"Baneling";"Zergling";127;0
"Unit";"Baneling";"Zergling";127;0
"Unit";"Baneling";"Zergling";127;0
"Unit";"Baneling";"Zergling";127;0
"Building";"CreepTumor";NA;131;0
"Building";"CreepTumor";NA;131;0
"Building";"CreepTumor";NA;133;0
"Unit";"Overlord";"Larva";130;0
"Building";"HydraliskDen";NA;127;0
"Building";"CreepTumorQueen";NA;133;0
"Building";"CreepTumorQueen";NA;133;0
"Building";"Hatchery";NA;107;0
"Unit";"Overlord";"Larva";133;0
"Unit";"Baneling";"Zergling";134;0
"Unit";"Baneling";"Zergling";138;0
"Unit";"Overlord";"Larva";139;0
"Unit";"Zergling";"Larva";139;1
"Unit";"Zergling";"Larva";139;1
"Unit";"Zergling";"Larva";141;1
"Unit";"Zergling";"Larva";141;1
"Unit";"Zergling";"Larva";142;1
"Unit";"Zergling";"Larva";142;1
"Unit";"Zergling";"Larva";142;1
"Unit";"Zergling";"Larva";142;1
"Unit";"Zergling";"Larva";142;1
"Unit";"Zergling";"Larva";142;1
"Unit";"Zergling";"Larva";143;1
"Unit";"Zergling";"Larva";143;1
"Unit";"Zergling";"Larva";143;1
"Unit";"Zergling";"Larva";143;1
"Upgrade";"ZergGroundArmorsLevel1";"EvolutionChamber";113;0
"Unit";"Zergling";"Larva";143;1
"Unit";"Zergling";"Larva";143;1
"Unit";"Overlord";"Larva";143;0
"Unit";"Zergling";"Larva";153;1
"Unit";"Zergling";"Larva";153;1
"Unit";"Zergling";"Larva";153;1
"Unit";"Zergling";"Larva";153;1
"Unit";"Zergling";"Larva";153;1
"Unit";"Zergling";"Larva";153;1
"Upgrade";"ZergMeleeWeaponsLevel1";"EvolutionChamber";113;0
"Building";"CreepTumor";NA;165;0
"Building";"CreepTumor";NA;165;0
"Unit";"Queen";"Hatchery";143;2
"Building";"CreepTumor";NA;165;0
"Building";"Extractor";NA;159;0
"Unit";"Baneling";"Zergling";165;0
"Unit";"Baneling";"Zergling";165;0
"Unit";"Baneling";"Zergling";165;0
"Unit";"Overlord";"Larva";165;0
"Unit";"Baneling";"Zergling";165;0
"Unit";"Baneling";"Zergling";165;0
"Building";"Hatchery";NA;133;0
"Unit";"Zergling";"Larva";166;1
"Unit";"Zergling";"Larva";166;1
"Unit";"Zergling";"Larva";169;1
"Unit";"Zergling";"Larva";169;1
"Unit";"Zergling";"Larva";169;1
"Unit";"Zergling";"Larva";169;1
"Unit";"Zergling";"Larva";169;1
"Unit";"Zergling";"Larva";169;1
"Unit";"Zergling";"Larva";169;1
"Unit";"Zergling";"Larva";169;1
"Unit";"Zergling";"Larva";169;1
"Unit";"Zergling";"Larva";169;1
"Unit";"Overlord";"Larva";175;0
"Building";"Extractor";NA;175;0
"Unit";"Zergling";"Larva";187;1
"Unit";"Zergling";"Larva";187;1
"Unit";"Zergling";"Larva";187;1
"Unit";"Zergling";"Larva";187;1
"Unit";"Zergling";"Larva";187;1
"Unit";"Zergling";"Larva";187;1
"Unit";"Zergling";"Larva";187;1
"Unit";"Zergling";"Larva";187;1
"Unit";"Zergling";"Larva";187;1
"Unit";"Zergling";"Larva";187;1
"Unit";"Zergling";"Larva";187;1
"Unit";"Zergling";"Larva";187;1
"Unit";"Zergling";"Larva";187;1
"Unit";"Zergling";"Larva";187;1
"Unit";"Zergling";"Larva";187;1
"Unit";"Zergling";"Larva";187;1
"Unit";"Zergling";"Larva";187;1
"Unit";"Zergling";"Larva";187;1
"Unit";"Zergling";"Larva";187;1
"Unit";"Zergling";"Larva";187;1
"Unit";"Zergling";"Larva";187;1
"Unit";"Zergling";"Larva";187;1
"Unit";"Zergling";"Larva";187;1
"Unit";"Zergling";"Larva";187;1
"Unit";"Zergling";"Larva";187;1
"Unit";"Zergling";"Larva";187;1
"Unit";"Zergling";"Larva";187;1
"Unit";"Zergling";"Larva";187;1
"Upgrade";"EvolveGroovedSpines";"HydraliskDen";165;0
"Unit";"Queen";"Hatchery";177;2
"Building";"InfestationPit";NA;187;0
"Unit";"Hydralisk";"Larva";187;2
"Unit";"Hydralisk";"Larva";187;2
"Unit";"Hydralisk";"Larva";187;2
"Unit";"Hydralisk";"Larva";187;2
"Unit";"Hydralisk";"Larva";187;2
"Unit";"Hydralisk";"Larva";187;2
"Unit";"Hydralisk";"Larva";187;2
"Unit";"Hydralisk";"Larva";189;2
"Unit";"Baneling";"Zergling";226;0
"Unit";"Baneling";"Zergling";228;0
"Unit";"Baneling";"Zergling";230;0
"Unit";"Baneling";"Zergling";234;0
"Unit";"Zergling";"Larva";234;1
"Unit";"Zergling";"Larva";234;1
"Unit";"Zergling";"Larva";234;1
"Unit";"Zergling";"Larva";234;1
"Unit";"Zergling";"Larva";234;1
"Unit";"Zergling";"Larva";234;1
"Unit";"Zergling";"Larva";234;1
"Unit";"Zergling";"Larva";234;1
"Unit";"Zergling";"Larva";234;1
"Unit";"Zergling";"Larva";234;1
"Unit";"Zergling";"Larva";234;1
"Unit";"Zergling";"Larva";234;1
"Unit";"Zergling";"Larva";234;1
"Unit";"Zergling";"Larva";234;1
"Unit";"Zergling";"Larva";234;1
"Unit";"Zergling";"Larva";234;1
"Unit";"Hydralisk";"Larva";218;2
"Unit";"Hydralisk";"Larva";218;2
"Unit";"Hydralisk";"Larva";218;2
"Unit";"Hydralisk";"Larva";218;2
"Unit";"Hydralisk";"Larva";218;2
"Building";"CreepTumor";NA;234;0
"Building";"CreepTumor";NA;234;0
"Unit";"Overlord";"Larva";234;0
"Unit";"Overlord";"Larva";234;0
"Unit";"Overlord";"Larva";234;0
"Building";"CreepTumorQueen";NA;260;0
"Building";"CreepTumor";NA;260;0
"Unit";"Zergling";"Larva";262;1
"Unit";"Zergling";"Larva";262;1
"Unit";"Zergling";"Larva";262;1
"Unit";"Zergling";"Larva";262;1
"Unit";"Zergling";"Larva";262;1
"Unit";"Zergling";"Larva";262;1
"Unit";"Zergling";"Larva";262;1
"Unit";"Zergling";"Larva";262;1
"Unit";"Zergling";"Larva";262;1
"Unit";"Zergling";"Larva";262;1
"Unit";"Zergling";"Larva";262;1
"Unit";"Zergling";"Larva";262;1
"Unit";"Zergling";"Larva";262;1
"Unit";"Zergling";"Larva";262;1
"Unit";"Zergling";"Larva";262;1
"Unit";"Zergling";"Larva";262;1
"Unit";"Zergling";"Larva";262;1
"Unit";"Zergling";"Larva";262;1
"Unit";"Zergling";"Larva";262;1
"Unit";"Zergling";"Larva";262;1
"Unit";"Zergling";"Larva";262;1
"Unit";"Zergling";"Larva";262;1
"Unit";"Zergling";"Larva";262;1
"Unit";"Zergling";"Larva";262;1
"Unit";"Zergling";"Larva";262;1
"Unit";"Zergling";"Larva";262;1
"Unit";"Zergling";"Larva";262;1
"Unit";"Zergling";"Larva";262;1
"Unit";"Zergling";"Larva";262;1
"Unit";"Zergling";"Larva";262;1
"Unit";"Zergling";"Larva";262;1
"Unit";"Zergling";"Larva";262;1
"Unit";"Zergling";"Larva";262;1
"Unit";"Zergling";"Larva";262;1
"Unit";"Zergling";"Larva";262;1
"Unit";"Zergling";"Larva";262;1
"Unit";"Zergling";"Larva";262;1
"Unit";"Zergling";"Larva";262;1
"Building";"SpineCrawler";NA;234;0
"Building";"SpineCrawler";NA;234;0
"Upgrade";"ZergGroundArmorsLevel2";"EvolutionChamber";187;0
"Building";"SpineCrawler";NA;234;0
"Unit";"Baneling";"Zergling";262;0
"Unit";"Baneling";"Zergling";262;0
"Unit";"Baneling";"Zergling";262;0
"Unit";"Baneling";"Zergling";262;0
"Unit";"Baneling";"Zergling";262;0
"Unit";"Baneling";"Zergling";262;0
"Unit";"Baneling";"Zergling";262;0
"Unit";"Baneling";"Zergling";262;0
"Building";"CreepTumor";NA;262;0
"Building";"CreepTumor";NA;264;0
"Building";"CreepTumorQueen";NA;300;0
"Building";"CreepTumorQueen";NA;300;0
"Building";"CreepTumorQueen";NA;300;0
"Upgrade";"EvolveMuscularAugments";"HydraliskDen";234;0
"Unit";"Baneling";"Zergling";300;0
"Unit";"Baneling";"Zergling";300;0
"Unit";"Baneling";"Zergling";300;0
"Unit";"Baneling";"Zergling";300;0
"Unit";"Baneling";"Zergling";300;0
"Unit";"Baneling";"Zergling";300;0
"Unit";"Baneling";"Zergling";300;0
"Unit";"Baneling";"Zergling";300;0
"Unit";"Baneling";"Zergling";300;0
"Unit";"Baneling";"Zergling";300;0
"Unit";"Baneling";"Zergling";300;0
"Unit";"Baneling";"Zergling";300;0
"Unit";"Baneling";"Zergling";300;0
"Unit";"Baneling";"Zergling";300;0
"Unit";"Baneling";"Zergling";300;0
"Unit";"Baneling";"Zergling";300;0
"Unit";"Hydralisk";"Larva";300;2
"Unit";"Hydralisk";"Larva";300;2
"Upgrade";"ZergMeleeWeaponsLevel2";"EvolutionChamber";215;0
"Unit";"Hydralisk";"Larva";300;2
"Unit";"Hydralisk";"Larva";300;2
"Unit";"Hydralisk";"Larva";300;2
"Unit";"Hydralisk";"Larva";300;2
"Unit";"Baneling";"Zergling";302;0
"Unit";"Baneling";"Zergling";304;0
"Unit";"Baneling";"Zergling";304;0
"Unit";"Baneling";"Zergling";304;0
"Unit";"Baneling";"Zergling";308;0
"Building";"Extractor";NA;300;0
"Unit";"Overlord";"Larva";312;0
"Unit";"Overlord";"Larva";312;0
"Unit";"Overlord";"Larva";312;0
"Unit";"Zergling";"Larva";317;1
"Unit";"Zergling";"Larva";317;1
"Unit";"Zergling";"Larva";317;1
"Unit";"Zergling";"Larva";317;1
"Unit";"Zergling";"Larva";317;1
"Unit";"Zergling";"Larva";317;1
"Unit";"Zergling";"Larva";317;1
"Unit";"Zergling";"Larva";317;1
"Unit";"Zergling";"Larva";317;1
"Unit";"Zergling";"Larva";317;1
"Unit";"Zergling";"Larva";317;1
"Unit";"Zergling";"Larva";317;1
"Unit";"Zergling";"Larva";317;1
"Unit";"Zergling";"Larva";317;1
"Unit";"Zergling";"Larva";317;1
"Unit";"Zergling";"Larva";317;1
"Unit";"Zergling";"Larva";317;1
"Unit";"Zergling";"Larva";317;1
"Unit";"Zergling";"Larva";317;1
"Unit";"Zergling";"Larva";317;1
"Unit";"Zergling";"Larva";317;1
"Unit";"Zergling";"Larva";317;1
"Unit";"Zergling";"Larva";317;1
"Unit";"Zergling";"Larva";317;1
"Unit";"Zergling";"Larva";317;1
"Unit";"Zergling";"Larva";317;1
"Unit";"Zergling";"Larva";317;1
"Unit";"Zergling";"Larva";317;1
"Unit";"Zergling";"Larva";317;1
"Unit";"Zergling";"Larva";317;1
"Unit";"Hydralisk";"Larva";317;2
"Building";"CreepTumorQueen";NA;349;0
"Building";"CreepTumorQueen";NA;349;0
"Building";"CreepTumorQueen";NA;349;0
"Unit";"Viper";"Larva";317;3
"Unit";"Viper";"Larva";319;3
"Building";"CreepTumor";NA;349;0
"Building";"CreepTumor";NA;349;0
"Building";"CreepTumor";NA;349;0
"Unit";"Zergling";"Larva";352;1
"Unit";"Zergling";"Larva";352;1
"Unit";"Zergling";"Larva";355;1
"Unit";"Zergling";"Larva";355;1
"Unit";"Zergling";"Larva";355;1
"Unit";"Zergling";"Larva";355;1
"Unit";"Zergling";"Larva";355;1
"Unit";"Zergling";"Larva";355;1
"Unit";"Zergling";"Larva";355;1
"Unit";"Zergling";"Larva";355;1
"Unit";"Zergling";"Larva";355;1
"Unit";"Zergling";"Larva";355;1
"Unit";"Zergling";"Larva";355;1
"Unit";"Zergling";"Larva";355;1
"Unit";"Zergling";"Larva";355;1
"Unit";"Zergling";"Larva";355;1
"Unit";"Zergling";"Larva";355;1
"Unit";"Zergling";"Larva";355;1
"Unit";"Zergling";"Larva";355;1
"Unit";"Zergling";"Larva";355;1
"Unit";"Zergling";"Larva";355;1
"Unit";"Zergling";"Larva";355;1
"Unit";"Zergling";"Larva";355;1
"Unit";"Zergling";"Larva";355;1
"Unit";"Zergling";"Larva";355;1
"Unit";"Zergling";"Larva";355;1
"Unit";"Zergling";"Larva";355;1
"Unit";"Zergling";"Larva";355;1
"Unit";"Zergling";"Larva";355;1
"Unit";"Zergling";"Larva";355;1
"Unit";"Zergling";"Larva";355;1
"Unit";"Zergling";"Larva";355;1
"Unit";"Zergling";"Larva";355;1
"Unit";"Zergling";"Larva";355;1
"Unit";"Zergling";"Larva";355;1
"Unit";"Zergling";"Larva";355;1
"Unit";"Zergling";"Larva";355;1
"Unit";"Zergling";"Larva";355;1
"Unit";"Zergling";"Larva";355;1
"Unit";"Zergling";"Larva";355;1
"Unit";"Zergling";"Larva";355;1
"Unit";"Zergling";"Larva";355;1
"Unit";"Zergling";"Larva";355;1
"Unit";"Zergling";"Larva";355;1
"Unit";"Baneling";"Zergling";355;0
"Unit";"Baneling";"Zergling";355;0
"Unit";"Baneling";"Zergling";355;0
"Unit";"Baneling";"Zergling";355;0
"Unit";"Baneling";"Zergling";355;0
"Unit";"Baneling";"Zergling";355;0
"Unit";"Baneling";"Zergling";355;0
"Unit";"Baneling";"Zergling";355;0
"Building";"CreepTumor";NA;399;0
"Building";"CreepTumor";NA;399;0
"Building";"CreepTumor";NA;399;0
"Building";"CreepTumor";NA;399;0
"Building";"CreepTumor";NA;399;0
"Building";"CreepTumorQueen";NA;399;0
"Building";"CreepTumorQueen";NA;399;0
"Building";"CreepTumor";NA;399;0
"Building";"Hatchery";NA;349;0
"Unit";"Zergling";"Larva";404;1
"Unit";"Zergling";"Larva";404;1
"Unit";"Zergling";"Larva";404;1
"Unit";"Zergling";"Larva";404;1
"Unit";"Zergling";"Larva";404;1
"Unit";"Zergling";"Larva";404;1
"Unit";"Zergling";"Larva";404;1
"Unit";"Zergling";"Larva";404;1
"Unit";"Zergling";"Larva";404;1
"Unit";"Zergling";"Larva";404;1
"Unit";"Zergling";"Larva";404;1
"Unit";"Zergling";"Larva";404;1
"Unit";"Zergling";"Larva";404;1
"Unit";"Zergling";"Larva";404;1
"Unit";"Zergling";"Larva";404;1
"Unit";"Zergling";"Larva";404;1
"Unit";"Hydralisk";"Larva";404;2
"Unit";"Hydralisk";"Larva";404;2
"Unit";"Hydralisk";"Larva";404;2
"Unit";"Hydralisk";"Larva";404;2
"Unit";"Hydralisk";"Larva";404;2
"Unit";"Hydralisk";"Larva";404;2
"Unit";"Hydralisk";"Larva";404;2
"Unit";"Hydralisk";"Larva";404;2
"Unit";"Hydralisk";"Larva";404;2
"Unit";"Hydralisk";"Larva";404;2
"Building";"CreepTumor";NA;420;0
"Unit";"Zergling";"Larva";418;1
"Unit";"Zergling";"Larva";418;1
"Unit";"Zergling";"Larva";420;1
"Unit";"Zergling";"Larva";420;1
"Unit";"Zergling";"Larva";420;1
"Unit";"Zergling";"Larva";420;1
"Unit";"Zergling";"Larva";420;1
"Unit";"Zergling";"Larva";420;1
"Unit";"Zergling";"Larva";420;1
"Unit";"Zergling";"Larva";420;1
"Unit";"Zergling";"Larva";420;1
"Unit";"Zergling";"Larva";420;1
"Unit";"Zergling";"Larva";420;1
"Unit";"Zergling";"Larva";420;1
"Unit";"Zergling";"Larva";420;1
"Unit";"Zergling";"Larva";420;1
"Unit";"Zergling";"Larva";420;1
"Unit";"Zergling";"Larva";420;1
"Unit";"Zergling";"Larva";420;1
"Unit";"Zergling";"Larva";420;1
"Unit";"Zergling";"Larva";420;1
"Unit";"Zergling";"Larva";420;1
"Unit";"Zergling";"Larva";420;1
"Unit";"Zergling";"Larva";420;1
"Unit";"Zergling";"Larva";420;1
"Unit";"Zergling";"Larva";420;1
"Unit";"Zergling";"Larva";420;1
"Unit";"Zergling";"Larva";420;1
"Unit";"Zergling";"Larva";420;1
"Unit";"Zergling";"Larva";420;1
"Unit";"Zergling";"Larva";420;1
"Unit";"Zergling";"Larva";420;1
"Unit";"Zergling";"Larva";420;1
"Unit";"Zergling";"Larva";420;1
"Unit";"Zergling";"Larva";420;1
"Unit";"Zergling";"Larva";420;1
"Unit";"Baneling";"Zergling";422;0
"Unit";"Baneling";"Zergling";424;0
"Unit";"Baneling";"Zergling";426;0
"Unit";"Baneling";"Zergling";430;0
"Unit";"Baneling";"Zergling";430;0
"Unit";"Baneling";"Zergling";430;0
"Unit";"Baneling";"Zergling";436;0
"Unit";"Baneling";"Zergling";436;0
"Unit";"Baneling";"Zergling";438;0
"Unit";"Baneling";"Zergling";438;0
"Unit";"Hydralisk";"Larva";412;2
"Unit";"Viper";"Larva";404;3
"Unit";"Viper";"Larva";404;3
"Building";"Extractor";NA;476;0
"Unit";"Baneling";"Zergling";484;0
"Unit";"Baneling";"Zergling";484;0
"Unit";"Baneling";"Zergling";484;0
"Unit";"Baneling";"Zergling";484;0
"Unit";"Baneling";"Zergling";484;0
"Unit";"Baneling";"Zergling";484;0
"Unit";"Baneling";"Zergling";484;0
"Unit";"Baneling";"Zergling";484;0
"Unit";"Baneling";"Zergling";484;0
"Unit";"Baneling";"Zergling";484;0
"Unit";"Baneling";"Zergling";484;0
"Unit";"Queen";"Hatchery";456;2
"Building";"SpineCrawler";NA;476;0
"Building";"SpineCrawler";NA;476;0
"Building";"CreepTumorQueen";NA;489;0
"Building";"CreepTumorQueen";NA;491;0
"Building";"CreepTumorQueen";NA;491;0
"Building";"CreepTumorQueen";NA;491;0
"Unit";"Zergling";"Larva";491;1
"Unit";"Zergling";"Larva";491;1
"Unit";"Zergling";"Larva";491;1
"Unit";"Zergling";"Larva";491;1
"Unit";"Zergling";"Larva";491;1
"Unit";"Zergling";"Larva";491;1
"Unit";"Zergling";"Larva";491;1
"Unit";"Zergling";"Larva";491;1
"Unit";"Zergling";"Larva";491;1
"Unit";"Zergling";"Larva";491;1
"Unit";"Zergling";"Larva";491;1
"Unit";"Zergling";"Larva";491;1
"Unit";"Zergling";"Larva";491;1
"Unit";"Zergling";"Larva";491;1
"Unit";"Zergling";"Larva";491;1
"Unit";"Zergling";"Larva";491;1
"Unit";"Zergling";"Larva";491;1
"Unit";"Zergling";"Larva";491;1
"Unit";"Zergling";"Larva";491;1
"Unit";"Zergling";"Larva";491;1
"Unit";"Zergling";"Larva";491;1
"Unit";"Zergling";"Larva";491;1
"Unit";"Zergling";"Larva";491;1
"Unit";"Zergling";"Larva";491;1
"Unit";"Zergling";"Larva";491;1
"Unit";"Zergling";"Larva";491;1
"Unit";"Zergling";"Larva";491;1
"Unit";"Zergling";"Larva";491;1
"Unit";"Zergling";"Larva";491;1
"Unit";"Zergling";"Larva";491;1
"Building";"CreepTumorQueen";NA;491;0
"Upgrade";"ZergGroundArmorsLevel3";"EvolutionChamber";399;0
"Unit";"Baneling";"Zergling";491;0
"Unit";"Baneling";"Zergling";491;0
"Building";"CreepTumorQueen";NA;491;0
"Unit";"Hydralisk";"Larva";491;2
"Unit";"Hydralisk";"Larva";491;2
"Unit";"Hydralisk";"Larva";491;2
"Unit";"Hydralisk";"Larva";491;2
"Unit";"Hydralisk";"Larva";491;2
"Building";"UltraliskCavern";NA;489;0
"Building";"Spire";NA;440;0
"Upgrade";"ZergMeleeWeaponsLevel3";"EvolutionChamber";404;0
"Building";"CreepTumorQueen";NA;521;0
"Building";"CreepTumor";NA;521;0
"Building";"CreepTumorQueen";NA;525;0
"Building";"CreepTumor";NA;521;0
"Building";"CreepTumorQueen";NA;531;0
"Building";"CreepTumorQueen";NA;531;0
"Building";"CreepTumorQueen";NA;531;0
"Unit";"Zergling";"Larva";531;1
"Unit";"Zergling";"Larva";531;1
"Unit";"Zergling";"Larva";531;1
"Unit";"Zergling";"Larva";531;1
"Unit";"Zergling";"Larva";531;1
"Unit";"Zergling";"Larva";531;1
"Unit";"Zergling";"Larva";531;1
"Unit";"Zergling";"Larva";531;1
"Unit";"Zergling";"Larva";531;1
"Unit";"Zergling";"Larva";531;1
"Unit";"Zergling";"Larva";531;1
"Unit";"Zergling";"Larva";531;1
"Unit";"Zergling";"Larva";531;1
"Unit";"Zergling";"Larva";531;1
"Unit";"Zergling";"Larva";531;1
"Unit";"Zergling";"Larva";531;1
"Unit";"Zergling";"Larva";531;1
"Unit";"Zergling";"Larva";531;1
"Unit";"Zergling";"Larva";531;1
"Unit";"Zergling";"Larva";531;1
"Unit";"Zergling";"Larva";531;1
"Unit";"Zergling";"Larva";531;1
"Unit";"Zergling";"Larva";531;1
"Unit";"Zergling";"Larva";531;1
"Unit";"Zergling";"Larva";531;1
"Unit";"Zergling";"Larva";531;1
"Unit";"Zergling";"Larva";531;1
"Unit";"Zergling";"Larva";531;1
"Unit";"Zergling";"Larva";531;1
"Unit";"Zergling";"Larva";531;1
"Unit";"Zergling";"Larva";531;1
"Unit";"Zergling";"Larva";531;1
"Unit";"Hydralisk";"Larva";531;2
"Building";"CreepTumor";NA;563;0
"Unit";"Baneling";"Zergling";531;0
"Building";"CreepTumor";NA;563;0
"Unit";"Baneling";"Zergling";533;0
"Unit";"Baneling";"Zergling";533;0
"Unit";"Baneling";"Zergling";533;0
"Unit";"Baneling";"Zergling";533;0
"Unit";"Baneling";"Zergling";533;0
"Unit";"Viper";"Larva";531;3
"Unit";"Viper";"Larva";531;3
"Building";"CreepTumorQueen";NA;565;0
"Unit";"Corruptor";"Larva";531;2
"Unit";"Corruptor";"Larva";531;2
"Unit";"Corruptor";"Larva";531;2
"Unit";"Ultralisk";"Larva";531;6
"Building";"CreepTumor";NA;565;0
"Unit";"Ultralisk";"Larva";531;6
"Unit";"Ultralisk";"Larva";531;6
"Building";"CreepTumor";NA;565;0
"Building";"CreepTumor";NA;565;0
"Building";"CreepTumorQueen";NA;565;0
"Building";"CreepTumor";NA;565;0
"Building";"CreepTumor";NA;565;0
"Building";"CreepTumorQueen";NA;565;0
"Building";"Extractor";NA;563;0
"Unit";"Corruptor";"Larva";531;2
"Unit";"Baneling";"Zergling";571;0
"Unit";"Baneling";"Zergling";571;0
"Unit";"Baneling";"Zergling";571;0
"Unit";"Baneling";"Zergling";571;0
"Unit";"Corruptor";"Larva";565;2
"Unit";"Corruptor";"Larva";565;2
"Building";"CreepTumorQueen";NA;597;0
"Upgrade";"ChitinousPlating";"UltraliskCavern";531;0
"Building";"Hatchery";NA;531;0
"Building";"CreepTumorQueen";NA;597;0
"Unit";"Baneling";"Zergling";597;0
"Upgrade";"ZergMissileWeaponsLevel1";"EvolutionChamber";531;0
"Unit";"Queen";"Hatchery";601;2
"Unit";"Zergling";"Larva";605;1
"Unit";"Zergling";"Larva";605;1
"Unit";"Zergling";"Larva";605;1
"Unit";"Zergling";"Larva";605;1
"Unit";"Zergling";"Larva";605;1
"Unit";"Zergling";"Larva";605;1
"Unit";"Zergling";"Larva";605;1
"Unit";"Zergling";"Larva";605;1
"Unit";"Zergling";"Larva";605;1
"Unit";"Zergling";"Larva";605;1
"Unit";"Zergling";"Larva";605;1
"Unit";"Zergling";"Larva";605;1
"Unit";"Zergling";"Larva";605;1
"Unit";"Zergling";"Larva";605;1
"Unit";"Zergling";"Larva";605;1
"Unit";"Zergling";"Larva";605;1
"Unit";"Zergling";"Larva";605;1
"Unit";"Zergling";"Larva";605;1
"Unit";"Zergling";"Larva";605;1
"Unit";"Zergling";"Larva";605;1
"Unit";"Zergling";"Larva";605;1
"Unit";"Zergling";"Larva";605;1
"Unit";"Zergling";"Larva";605;1
"Unit";"Zergling";"Larva";605;1
"Unit";"Zergling";"Larva";605;1
"Unit";"Zergling";"Larva";605;1
"Unit";"Zergling";"Larva";605;1
"Unit";"Zergling";"Larva";605;1
"Unit";"Zergling";"Larva";605;1
"Unit";"Zergling";"Larva";605;1
"Unit";"Hydralisk";"Larva";601;2
"Unit";"Hydralisk";"Larva";602;2
"Unit";"Hydralisk";"Larva";605;2
"Unit";"Hydralisk";"Larva";605;2
"Unit";"Corruptor";"Larva";601;2
"Unit";"Baneling";"Zergling";641;0
"Unit";"Baneling";"Zergling";641;0
"Unit";"Baneling";"Zergling";641;0
"Unit";"Baneling";"Zergling";641;0
"Unit";"Baneling";"Zergling";641;0
"Unit";"Baneling";"Zergling";641;0
"Unit";"Corruptor";"Larva";605;2
"Unit";"Corruptor";"Larva";605;2
"Unit";"Queen";"Hatchery";605;2
"Unit";"Baneling";"Zergling";647;0
"Unit";"Baneling";"Zergling";647;0
"Unit";"Baneling";"Zergling";647;0
"Unit";"Baneling";"Zergling";647;0
"Building";"SpineCrawler";NA;647;0
"Building";"SpineCrawler";NA;647;0
"Building";"SpineCrawler";NA;647;0
"Building";"SpineCrawler";NA;647;0
"Unit";"Queen";"Hatchery";647;2
"Unit";"Hydralisk";"Larva";653;2
"Unit";"Hydralisk";"Larva";653;2
"Unit";"Hydralisk";"Larva";653;2
"Unit";"Queen";"Hatchery";647;2
"Unit";"Corruptor";"Larva";653;2
"Unit";"Corruptor";"Larva";653;2
"Unit";"Zergling";"Larva";663;1
"Unit";"Zergling";"Larva";663;1
"Unit";"Zergling";"Larva";663;1
"Unit";"Zergling";"Larva";663;1
"Unit";"Zergling";"Larva";663;1
"Unit";"Zergling";"Larva";663;1
"Unit";"Hydralisk";"Larva";663;2
"Unit";"Corruptor";"Larva";663;2
"Unit";"Corruptor";"Larva";663;2
"Unit";"Corruptor";"Larva";663;2
"Unit";"Corruptor";"Larva";663;2
"Unit";"Corruptor";"Larva";663;2
"Building";"CreepTumor";NA;685;0
"Unit";"Zergling";"Larva";685;1
"Unit";"Zergling";"Larva";685;1
"Unit";"Hydralisk";"Larva";685;2
"Unit";"Corruptor";"Larva";675;2
"Unit";"Corruptor";"Larva";675;2
"Building";"CreepTumorQueen";NA;693;0
"Building";"CreepTumorQueen";NA;693;0
"Unit";"Hydralisk";"Larva";685;2
"Unit";"Hydralisk";"Larva";685;2
"Unit";"Hydralisk";"Larva";685;2
"Unit";"Hydralisk";"Larva";685;2
"Unit";"Hydralisk";"Larva";685;2
"Unit";"Hydralisk";"Larva";685;2
"Unit";"Hydralisk";"Larva";685;2
"Unit";"Hydralisk";"Larva";685;2
"Unit";"Hydralisk";"Larva";685;2
"Unit";"Zergling";"Larva";689;1
"Unit";"Zergling";"Larva";689;1
"Unit";"Zergling";"Larva";693;1
"Unit";"Zergling";"Larva";693;1
"Unit";"Zergling";"Larva";693;1
"Unit";"Zergling";"Larva";693;1
"Unit";"Zergling";"Larva";693;1
"Unit";"Zergling";"Larva";693;1
"Unit";"Zergling";"Larva";693;1
"Unit";"Zergling";"Larva";693;1
"Unit";"Zergling";"Larva";693;1
"Unit";"Zergling";"Larva";693;1
"Unit";"Zergling";"Larva";693;1
"Unit";"Zergling";"Larva";693;1
"Unit";"Hydralisk";"Larva";687;2
"Unit";"Hydralisk";"Larva";687;2
"Unit";"Corruptor";"Larva";687;2
"Unit";"Corruptor";"Larva";687;2
