"type";"unit_name";"on_building";"total_supply_lag";"supply"
"Building";"Barracks";NA;16;0
"Building";"Refinery";NA;16;0
"Unit";"Reaper";"Barracks";19;1
"Building";"CommandCenter";NA;20;0
"Unit";"Marine";"Barracks";21;1
"Building";"Factory";NA;22;0
"Building";"Refinery";NA;23;0
"Building";"BarracksReactor";NA;24;0
"Building";"Starport";NA;26;0
"Unit";"Hellion";"Factory";27;2
"Unit";"Hellion";"Factory";29;2
"Building";"BarracksTechLab";NA;32;0
"Unit";"Hellion";"Factory";34;2
"Unit";"Hellion";"Factory";36;2
"Unit";"Raven";"Starport";40;2
"Building";"BarracksTechLab";NA;42;0
"Building";"CommandCenter";NA;42;0
"Building";"Barracks";NA;46;0
"Building";"Barracks";NA;48;0
"Unit";"Marine";"Barracks";48;1
"Upgrade";"Stimpack";"TechLab";51;0
"Building";"EngineeringBay";NA;53;0
"Unit";"Marine";"Barracks";53;1
"Building";"StarportReactor";NA;54;0
"Building";"Bunker";NA;54;0
"Building";"Bunker";NA;54;0
"Unit";"Marine";"Barracks";56;1
"Unit";"Marine";"Barracks";57;1
"Unit";"Marine";"Barracks";58;1
"Unit";"Marine";"Barracks";61;1
"Unit";"Marine";"Barracks";62;1
"Unit";"Marine";"Barracks";63;1
"Unit";"Marine";"Barracks";64;1
"Unit";"Marine";"Barracks";67;1
"Unit";"Medivac";"Starport";68;2
"Unit";"Marine";"Barracks";70;1
"Unit";"Medivac";"Starport";71;2
"Upgrade";"TerranInfantryWeaponsLevel1";"EngineeringBay";73;0
"Unit";"Marine";"Barracks";73;1
"Unit";"Marine";"Barracks";74;1
"Unit";"Marine";"Barracks";75;1
"Unit";"Marine";"Barracks";76;1
"Unit";"Marine";"Barracks";77;1
"Unit";"Marine";"Barracks";78;1
"Unit";"Marine";"Barracks";79;1
"Unit";"Marine";"Barracks";80;1
"Unit";"Marine";"Barracks";81;1
"Unit";"Marine";"Barracks";82;1
"Unit";"Marine";"Barracks";83;1
"Unit";"Marine";"Barracks";84;1
"Unit";"Marine";"Barracks";88;1
"Unit";"Marine";"Barracks";89;1
"Unit";"Marine";"Barracks";90;1
"Unit";"Marine";"Barracks";91;1
"Unit";"Marine";"Barracks";92;1
"Unit";"Marine";"Barracks";94;1
"Unit";"Marine";"Barracks";95;1
"Unit";"Marine";"Barracks";96;1
"Unit";"Medivac";"Starport";97;2
"Unit";"Marine";"Barracks";99;1
"Unit";"Medivac";"Starport";100;2
"Unit";"Marine";"Barracks";102;1
"Unit";"Marine";"Barracks";103;1
"Unit";"Marine";"Barracks";104;1
"Unit";"Marine";"Barracks";108;1
"Unit";"Marine";"Barracks";109;1
"Unit";"Marine";"Barracks";110;1
"Unit";"Marine";"Barracks";111;1
"Unit";"Marine";"Barracks";115;1
"Unit";"Medivac";"Starport";116;2
"Unit";"Marine";"Barracks";118;1
"Building";"BarracksReactor";NA;119;0
"Unit";"Marine";"Barracks";120;1
"Unit";"Marine";"Barracks";123;1
"Unit";"Marine";"Barracks";127;1
"Unit";"Marine";"Barracks";128;1
"Unit";"Marine";"Barracks";129;1
"Unit";"Marine";"Barracks";130;1
"Unit";"Marine";"Barracks";131;1
"Unit";"Marine";"Barracks";132;1
"Unit";"Marine";"Barracks";133;1
"Unit";"Marine";"Barracks";137;1
"Unit";"Marine";"Barracks";138;1
"Unit";"Marine";"Barracks";139;1
"Unit";"Marine";"Barracks";140;1
"Unit";"Marine";"Barracks";141;1
"Unit";"Medivac";"Starport";142;2
"Unit";"Marine";"Barracks";144;1
"Unit";"Marine";"Barracks";145;1
"Unit";"Marine";"Barracks";149;1
"Unit";"Marine";"Barracks";150;1
"Unit";"Marine";"Barracks";151;1
"Unit";"Marine";"Barracks";153;1
"Unit";"Marine";"Barracks";154;1
"Unit";"Marine";"Barracks";155;1
"Unit";"Marine";"Barracks";156;1
"Building";"Refinery";NA;157;0
"Building";"Refinery";NA;157;0
"Unit";"Marine";"Barracks";157;1
"Building";"Barracks";NA;158;0
"Building";"Barracks";NA;158;0
"Unit";"Marine";"Barracks";158;1
"Unit";"Liberator";"Starport";159;3
"Unit";"Marine";"Barracks";163;1
"Unit";"Marine";"Barracks";164;1
"Building";"Armory";NA;165;0
"Unit";"Marine";"Barracks";165;1
"Unit";"Marine";"Barracks";166;1
"Unit";"Marine";"Barracks";167;1
"Unit";"Marine";"Barracks";168;1
"Unit";"Marine";"Barracks";169;1
"Unit";"Marine";"Barracks";170;1
"Unit";"Marine";"Barracks";171;1
"Unit";"Marine";"Barracks";172;1
"Unit";"Marine";"Barracks";173;1
"Unit";"Marauder";"Barracks";174;2
"Unit";"Marine";"Barracks";176;1
"Unit";"Marine";"Barracks";177;1
"Unit";"Marine";"Barracks";180;1
"Unit";"Marine";"Barracks";181;1
"Building";"BarracksReactor";NA;182;0
"Building";"BarracksReactor";NA;182;0
"Building";"EngineeringBay";NA;183;0
"Unit";"Marine";"Barracks";185;1
"Unit";"Marine";"Barracks";186;1
"Unit";"Marine";"Barracks";187;1
"Unit";"Marine";"Barracks";188;1
"Unit";"Marine";"Barracks";189;1
"Unit";"Marine";"Barracks";193;1
"Unit";"Marine";"Barracks";194;1
"Unit";"Marine";"Barracks";195;1
"Unit";"Marine";"Barracks";196;1
"Unit";"Marine";"Barracks";197;1
"Unit";"Marine";"Barracks";198;1
"Unit";"Marauder";"Barracks";199;2
"Unit";"Medivac";"Starport";201;2
"Unit";"Medivac";"Starport";203;2
"Upgrade";"TerranInfantryWeaponsLevel2";"EngineeringBay";205;0
"Unit";"Marine";"Barracks";205;1
"Unit";"Marine";"Barracks";206;1
"Unit";"Marine";"Barracks";207;1
"Unit";"Marine";"Barracks";208;1
"Unit";"Marine";"Barracks";209;1
"Unit";"Marine";"Barracks";210;1
"Unit";"Marauder";"Barracks";211;2
"Unit";"Marine";"Barracks";213;1
"Unit";"Marine";"Barracks";214;1
"Unit";"Marine";"Barracks";215;1
"Unit";"Marine";"Barracks";216;1
"Unit";"Marine";"Barracks";217;1
"Building";"Bunker";NA;218;0
"Unit";"Marine";"Barracks";218;1
"Unit";"Marine";"Barracks";219;1
"Unit";"Marine";"Barracks";220;1
"Unit";"Marine";"Barracks";221;1
"Unit";"Marauder";"Barracks";222;2
"Unit";"Liberator";"Starport";224;3
"Unit";"Liberator";"Starport";227;3
"Unit";"Marine";"Barracks";230;1
"Unit";"Marine";"Barracks";231;1
"Unit";"Marine";"Barracks";232;1
"Unit";"Marine";"Barracks";233;1
"Unit";"Marine";"Barracks";234;1
"Unit";"Marine";"Barracks";235;1
"Unit";"Marauder";"Barracks";236;2
"Unit";"Marine";"Barracks";238;1
"Unit";"Marine";"Barracks";239;1
"Unit";"Marine";"Barracks";240;1
"Unit";"Marine";"Barracks";241;1
"Unit";"Marauder";"Barracks";242;2
"Unit";"Marine";"Barracks";244;1
"Unit";"Marine";"Barracks";245;1
"Upgrade";"SprayTerran";NA;246;0
"Upgrade";"SprayTerran";NA;246;0
"Upgrade";"SprayTerran";NA;246;0
"Upgrade";"SprayTerran";NA;246;0
"Upgrade";"ShieldWall";NA;246;0
"Upgrade";"PunisherGrenades";NA;246;0
