"type";"unit_name";"on_building";"total_supply_lag";"supply"
"Building";"Refinery";NA;15;0
"Building";"Barracks";NA;16;0
"Unit";"Reaper";"Barracks";19;1
"Building";"CommandCenter";NA;20;0
"Building";"Factory";NA;20;0
"Building";"BarracksReactor";NA;21;0
"Building";"Refinery";NA;22;0
"Building";"Starport";NA;24;0
"Unit";"Hellion";"Factory";25;2
"Unit";"Hellion";"Factory";27;2
"Building";"BarracksTechLab";NA;29;0
"Unit";"Medivac";"Starport";33;2
"Unit";"Hellion";"Factory";37;2
"Unit";"Hellion";"Factory";39;2
"Unit";"Banshee";"Starport";44;3
"Unit";"Hellion";"Factory";48;2
"Unit";"Hellion";"Factory";51;2
"Building";"Armory";NA;54;0
"Unit";"Hellion";"Factory";57;2
"Unit";"Banshee";"Starport";60;3
"Building";"BarracksTechLab";NA;63;0
"Unit";"Hellion";"Factory";63;2
"Building";"CommandCenter";NA;65;0
"Unit";"Hellion";"Factory";67;2
"Unit";"Hellion";"Factory";73;2
"Unit";"Hellion";"Factory";75;2
"Building";"Barracks";NA;78;0
"Building";"Barracks";NA;78;0
"Building";"EngineeringBay";NA;78;0
"Unit";"Marine";"Barracks";78;1
"Building";"EngineeringBay";NA;79;0
"Building";"Refinery";NA;81;0
"Building";"Refinery";NA;81;0
"Unit";"Hellion";"Factory";81;2
"Unit";"Hellion";"Factory";83;2
"Building";"StarportReactor";NA;85;0
"Unit";"Marine";"Barracks";85;1
"Building";"Barracks";NA;87;0
"Upgrade";"Stimpack";"TechLab";87;0
"Unit";"Marine";"Barracks";87;1
"Building";"Barracks";NA;88;0
"Building";"BarracksReactor";NA;89;0
"Unit";"Liberator";"Starport";89;3
"Unit";"Medivac";"Starport";92;2
"Unit";"Marine";"Barracks";94;1
"Upgrade";"TerranInfantryWeaponsLevel1";"EngineeringBay";97;0
"Unit";"Marine";"Barracks";101;1
"Building";"BarracksReactor";NA;103;0
"Unit";"Marine";"Barracks";104;1
"Unit";"Marine";"Barracks";105;1
"Unit";"Marine";"Barracks";106;1
"Building";"BarracksReactor";NA;107;0
"Building";"Bunker";NA;108;0
"Unit";"Marine";"Barracks";109;1
"Unit";"Marine";"Barracks";111;1
"Unit";"Marine";"Barracks";112;1
"Unit";"Marine";"Barracks";113;1
"Unit";"Medivac";"Starport";115;2
"Unit";"Medivac";"Starport";117;2
"Unit";"Marine";"Barracks";119;1
"Unit";"Marine";"Barracks";122;1
"Unit";"Marine";"Barracks";124;1
"Unit";"Marine";"Barracks";125;1
"Unit";"Marine";"Barracks";126;1
"Unit";"Marine";"Barracks";127;1
"Unit";"Marine";"Barracks";128;1
"Unit";"Marine";"Barracks";129;1
"Unit";"Marine";"Barracks";130;1
"Unit";"Marine";"Barracks";131;1
"Unit";"Marine";"Barracks";132;1
"Unit";"Marine";"Barracks";133;1
"Unit";"Medivac";"Starport";134;2
"Unit";"Marine";"Barracks";137;1
"Unit";"Marine";"Barracks";138;1
"Building";"Factory";NA;139;0
"Unit";"Marine";"Barracks";139;1
"Building";"Refinery";NA;140;0
"Building";"Refinery";NA;140;0
"Unit";"Marine";"Barracks";141;1
"Unit";"Marine";"Barracks";142;1
"Unit";"Marine";"Barracks";143;1
"Unit";"Marine";"Barracks";144;1
"Unit";"Medivac";"Starport";145;2
"Unit";"Marine";"Barracks";147;1
"Unit";"Marine";"Barracks";148;1
"Unit";"Marine";"Barracks";149;1
"Unit";"Marine";"Barracks";150;1
"Unit";"Marine";"Barracks";151;1
"Unit";"Marine";"Barracks";152;1
"Building";"CommandCenter";NA;153;0
"Building";"Barracks";NA;153;0
"Building";"Barracks";NA;153;0
"Building";"Barracks";NA;153;0
"Unit";"Marine";"Barracks";153;1
"Unit";"Marine";"Barracks";154;1
"Unit";"Marine";"Barracks";155;1
"Unit";"Marine";"Barracks";156;1
"Unit";"Marine";"Barracks";157;1
"Unit";"Marine";"Barracks";158;1
"Unit";"Marine";"Barracks";159;1
"Building";"FactoryTechLab";NA;160;0
"Unit";"Marine";"Barracks";160;1
"Unit";"Marine";"Barracks";161;1
"Unit";"Medivac";"Starport";162;2
"Unit";"Marine";"Barracks";164;1
"Unit";"Marine";"Barracks";165;1
"Unit";"Marine";"Barracks";166;1
"Unit";"Marine";"Barracks";167;1
"Unit";"Marine";"Barracks";168;1
"Unit";"Marine";"Barracks";169;1
"Upgrade";"TerranVehicleWeaponsLevel1";"Armory";170;0
"Upgrade";"TerranInfantryWeaponsLevel2";"EngineeringBay";170;0
"Unit";"Marine";"Barracks";170;1
"Unit";"Marine";"Barracks";171;1
"Unit";"Marine";"Barracks";172;1
"Unit";"Medivac";"Starport";173;2
"Building";"SensorTower";NA;178;0
"Unit";"Marine";"Barracks";178;1
"Building";"BarracksTechLab";NA;179;0
"Building";"BarracksTechLab";NA;179;0
"Unit";"Marine";"Barracks";180;1
"Unit";"Marauder";"Barracks";181;2
"Unit";"Marine";"Barracks";183;1
"Unit";"Marine";"Barracks";184;1
"Unit";"Marine";"Barracks";185;1
"Unit";"Marine";"Barracks";186;1
"Unit";"Marine";"Barracks";187;1
"Unit";"Marine";"Barracks";188;1
"Unit";"Marine";"Barracks";189;1
"Building";"BarracksTechLab";NA;190;0
"Unit";"Marine";"Barracks";190;1
"Unit";"Marauder";"Barracks";191;2
"Unit";"Marauder";"Barracks";193;2
"Unit";"Marine";"Barracks";195;1
"Unit";"Marine";"Barracks";196;1
"Unit";"Marine";"Barracks";197;1
"Unit";"Marine";"Barracks";198;1
"Unit";"Marine";"Barracks";199;1
"Unit";"Marine";"Barracks";200;1
"Unit";"Marine";"Barracks";201;1
"Unit";"Marine";"Barracks";202;1
"Unit";"Marine";"Barracks";203;1
"Unit";"Marine";"Barracks";204;1
"Unit";"Marine";"Barracks";205;1
"Unit";"Marine";"Barracks";206;1
"Unit";"Marine";"Barracks";207;1
"Unit";"Marine";"Barracks";208;1
"Unit";"Marine";"Barracks";209;1
"Unit";"Marine";"Barracks";210;1
"Unit";"Marine";"Barracks";211;1
"Unit";"Marine";"Barracks";212;1
"Unit";"Marine";"Barracks";213;1
"Unit";"Marine";"Barracks";214;1
"Unit";"Marine";"Barracks";215;1
"Unit";"Marauder";"Barracks";216;2
"Unit";"Marine";"Barracks";218;1
"Unit";"Marine";"Barracks";219;1
"Unit";"Marine";"Barracks";220;1
"Unit";"Liberator";"Starport";221;3
"Unit";"Liberator";"Starport";224;3
"Unit";"Marine";"Barracks";227;1
"Unit";"Marine";"Barracks";228;1
"Unit";"Marine";"Barracks";229;1
"Unit";"Marine";"Barracks";230;1
"Unit";"Marine";"Barracks";231;1
"Unit";"Marine";"Barracks";232;1
"Unit";"Marine";"Barracks";233;1
"Unit";"Marine";"Barracks";234;1
"Unit";"Marine";"Barracks";235;1
"Unit";"Marine";"Barracks";236;1
"Unit";"Marine";"Barracks";237;1
"Unit";"Marine";"Barracks";238;1
"Unit";"Marine";"Barracks";239;1
"Unit";"Marine";"Barracks";240;1
"Unit";"Marine";"Barracks";241;1
"Unit";"Marine";"Barracks";242;1
"Unit";"Marauder";"Barracks";243;2
"Unit";"Marine";"Barracks";245;1
"Unit";"Marine";"Barracks";246;1
"Unit";"Marine";"Barracks";247;1
"Unit";"Marauder";"Barracks";248;2
"Unit";"Marauder";"Barracks";250;2
"Unit";"Marauder";"Barracks";252;2
"Unit";"Marine";"Barracks";254;1
"Unit";"Marauder";"Barracks";255;2
"Unit";"Marine";"Barracks";257;1
"Unit";"Marauder";"Barracks";258;2
"Unit";"Marine";"Barracks";260;1
"Unit";"Marine";"Barracks";261;1
"Unit";"Marine";"Barracks";262;1
"Unit";"Marine";"Barracks";263;1
"Unit";"Marauder";"Barracks";264;2
"Unit";"Marine";"Barracks";266;1
"Unit";"Marine";"Barracks";267;1
"Unit";"Marine";"Barracks";268;1
"Unit";"Marine";"Barracks";269;1
"Unit";"Marine";"Barracks";270;1
"Unit";"Marine";"Barracks";271;1
"Unit";"Marine";"Barracks";272;1
"Unit";"Marauder";"Barracks";273;2
"Unit";"Marine";"Barracks";275;1
"Unit";"Liberator";"Starport";276;3
"Unit";"Marine";"Barracks";279;1
"Unit";"Marine";"Barracks";280;1
"Unit";"Marine";"Barracks";281;1
"Unit";"Marine";"Barracks";282;1
"Unit";"Marine";"Barracks";283;1
"Unit";"Marine";"Barracks";284;1
"Unit";"Marine";"Barracks";285;1
"Unit";"Marauder";"Barracks";286;2
"Unit";"Marine";"Barracks";288;1
"Unit";"Marine";"Barracks";289;1
"Unit";"Marine";"Barracks";290;1
"Unit";"Marine";"Barracks";291;1
"Unit";"Marine";"Barracks";292;1
"Unit";"Marine";"Barracks";293;1
"Unit";"Marine";"Barracks";294;1
"Upgrade";"SprayTerran";NA;295;0
"Upgrade";"SprayTerran";NA;295;0
"Upgrade";"BansheeCloak";NA;295;0
"Upgrade";"SprayTerran";NA;295;0
"Upgrade";"SprayTerran";NA;295;0
"Upgrade";"TerranInfantryArmorsLevel1";NA;295;0
"Upgrade";"SprayTerran";NA;295;0
"Upgrade";"ShieldWall";NA;295;0
"Upgrade";"SprayTerran";NA;295;0
"Upgrade";"TerranInfantryArmorsLevel2";NA;295;0
"Upgrade";"DrillClaws";NA;295;0
