"type";"unit_name";"on_building";"total_supply_lag";"supply"
"Building";"Barracks";NA;16;0
"Building";"Refinery";NA;16;0
"Unit";"Marine";"Barracks";19;1
"Building";"CommandCenter";NA;20;0
"Unit";"Marine";"Barracks";20;1
"Building";"Factory";NA;22;0
"Building";"BarracksReactor";NA;23;0
"Building";"Refinery";NA;23;0
"Building";"Starport";NA;26;0
"Unit";"Hellion";"Factory";26;2
"Unit";"Hellion";"Factory";28;2
"Building";"BarracksTechLab";NA;31;0
"Unit";"Hellion";"Factory";32;2
"Unit";"Hellion";"Factory";34;2
"Unit";"Marine";"Barracks";39;1
"Unit";"Hellion";"Factory";42;2
"Unit";"Hellion";"Factory";44;2
"Unit";"Banshee";"Starport";46;3
"Building";"CommandCenter";NA;51;0
"Building";"BarracksTechLab";NA;54;0
"Building";"Barracks";NA;55;0
"Building";"Barracks";NA;55;0
"Building";"FactoryReactor";NA;55;0
"Unit";"Banshee";"Starport";56;3
"Building";"EngineeringBay";NA;61;0
"Building";"EngineeringBay";NA;61;0
"Unit";"Marine";"Barracks";62;1
"Building";"Refinery";NA;65;0
"Building";"Refinery";NA;66;0
"Unit";"Marine";"Barracks";66;1
"Unit";"Marine";"Barracks";68;1
"Unit";"Marine";"Barracks";71;1
"Unit";"Marine";"Barracks";72;1
"Building";"StarportReactor";NA;75;0
"Unit";"Marine";"Barracks";75;1
"Unit";"Marine";"Barracks";76;1
"Unit";"Marine";"Barracks";77;1
"Building";"Barracks";NA;78;0
"Building";"Barracks";NA;78;0
"Upgrade";"TerranInfantryWeaponsLevel1";"EngineeringBay";79;0
"Unit";"Marine";"Barracks";80;1
"Unit";"Marine";"Barracks";81;1
"Unit";"Marine";"Barracks";82;1
"Unit";"Marine";"Barracks";84;1
"Unit";"Marine";"Barracks";86;1
"Upgrade";"Stimpack";"TechLab";87;0
"Unit";"Marine";"Barracks";87;1
"Unit";"Marine";"Barracks";88;1
"Unit";"Medivac";"Starport";92;2
"Unit";"Medivac";"Starport";94;2
"Unit";"Marine";"Barracks";96;1
"Unit";"Marine";"Barracks";97;1
"Unit";"Marine";"Barracks";100;1
"Unit";"Marine";"Barracks";101;1
"Unit";"Marine";"Barracks";103;1
"Building";"BarracksReactor";NA;104;0
"Building";"BarracksReactor";NA;104;0
"Unit";"Marine";"Barracks";104;1
"Building";"Armory";NA;105;0
"Unit";"Marine";"Barracks";106;1
"Unit";"Marine";"Barracks";109;1
"Unit";"Marine";"Barracks";110;1
"Unit";"Marine";"Barracks";114;1
"Unit";"Marine";"Barracks";115;1
"Unit";"Marine";"Barracks";116;1
"Building";"Refinery";NA;118;0
"Unit";"Marine";"Barracks";121;1
"Unit";"Marine";"Barracks";122;1
"Unit";"Marine";"Barracks";123;1
"Unit";"Marine";"Barracks";124;1
"Unit";"Marine";"Barracks";125;1
"Unit";"Marine";"Barracks";126;1
"Unit";"Marine";"Barracks";127;1
"Unit";"Medivac";"Starport";128;2
"Unit";"Medivac";"Starport";130;2
"Unit";"Marauder";"Barracks";133;2
"Unit";"Marine";"Barracks";136;1
"Unit";"Marine";"Barracks";137;1
"Unit";"Marine";"Barracks";138;1
"Unit";"Marine";"Barracks";139;1
"Unit";"Marine";"Barracks";140;1
"Unit";"Marine";"Barracks";141;1
"Unit";"Medivac";"Starport";145;2
"Unit";"Medivac";"Starport";147;2
"Unit";"Marine";"Barracks";149;1
"Unit";"Marine";"Barracks";150;1
"Unit";"Marine";"Barracks";151;1
"Unit";"Marauder";"Barracks";152;2
"Unit";"Marine";"Barracks";154;1
"Unit";"Marine";"Barracks";155;1
"Unit";"Marine";"Barracks";156;1
"Building";"Refinery";NA;157;0
"Building";"Factory";NA;157;0
"Upgrade";"TerranInfantryWeaponsLevel2";"EngineeringBay";157;0
"Unit";"Marine";"Barracks";157;1
"Unit";"Marine";"Barracks";158;1
"Unit";"Marine";"Barracks";159;1
"Unit";"Marine";"Barracks";160;1
"Unit";"Marine";"Barracks";161;1
"Unit";"Marine";"Barracks";162;1
"Unit";"Marine";"Barracks";163;1
"Unit";"Marauder";"Barracks";164;2
"Building";"Barracks";NA;169;0
"Building";"Barracks";NA;169;0
"Building";"Barracks";NA;169;0
"Unit";"Medivac";"Starport";169;2
"Unit";"Medivac";"Starport";171;2
"Unit";"Marine";"Barracks";174;1
"Unit";"Marauder";"Barracks";175;2
"Unit";"Marine";"Barracks";177;1
"Unit";"Marine";"Barracks";178;1
"Unit";"Marine";"Barracks";179;1
"Unit";"Marine";"Barracks";180;1
"Unit";"Marine";"Barracks";181;1
"Unit";"Marine";"Barracks";182;1
"Unit";"Marine";"Barracks";183;1
"Unit";"Marine";"Barracks";184;1
"Building";"FactoryTechLab";NA;185;0
"Unit";"Marine";"Barracks";185;1
"Unit";"Marine";"Barracks";186;1
"Unit";"Marine";"Barracks";187;1
"Unit";"Marine";"Barracks";188;1
"Building";"CommandCenter";NA;189;0
"Unit";"Marine";"Barracks";189;1
"Unit";"Marine";"Barracks";190;1
"Unit";"Marine";"Barracks";191;1
"Unit";"Marine";"Barracks";192;1
"Unit";"Marine";"Barracks";193;1
"Unit";"Marine";"Barracks";194;1
"Unit";"Marine";"Barracks";195;1
"Unit";"Medivac";"Starport";202;2
"Unit";"Medivac";"Starport";204;2
"Unit";"Marauder";"Barracks";209;2
"Unit";"Marine";"Barracks";211;1
"Unit";"Marine";"Barracks";212;1
"Unit";"Marine";"Barracks";213;1
"Unit";"Marine";"Barracks";214;1
"Unit";"Marine";"Barracks";215;1
"Unit";"Marine";"Barracks";216;1
"Unit";"Marine";"Barracks";217;1
"Unit";"Marine";"Barracks";218;1
"Unit";"Marine";"Barracks";219;1
"Unit";"Marine";"Barracks";220;1
"Unit";"Marauder";"Barracks";221;2
"Unit";"Marine";"Barracks";223;1
"Unit";"Marine";"Barracks";224;1
"Upgrade";"TerranInfantryWeaponsLevel3";"EngineeringBay";225;0
"Unit";"Marine";"Barracks";225;1
"Unit";"Marine";"Barracks";226;1
"Unit";"Marine";"Barracks";227;1
"Unit";"Marine";"Barracks";228;1
"Unit";"Marine";"Barracks";229;1
"Unit";"Marine";"Barracks";230;1
"Unit";"Marine";"Barracks";231;1
"Unit";"Marine";"Barracks";232;1
"Unit";"Marine";"Barracks";233;1
"Upgrade";"TerranVehicleWeaponsLevel1";"Armory";234;0
"Unit";"Marauder";"Barracks";234;2
"Unit";"Marine";"Barracks";236;1
"Unit";"Marine";"Barracks";240;1
"Unit";"Marine";"Barracks";241;1
"Unit";"Marauder";"Barracks";242;2
"Unit";"Marine";"Barracks";244;1
"Unit";"Marine";"Barracks";245;1
"Unit";"Marine";"Barracks";246;1
"Unit";"Marine";"Barracks";247;1
"Unit";"Marine";"Barracks";248;1
"Unit";"Marine";"Barracks";249;1
"Unit";"Marine";"Barracks";250;1
"Unit";"Marine";"Barracks";251;1
"Unit";"Marine";"Barracks";252;1
"Unit";"Marine";"Barracks";253;1
"Unit";"Marine";"Barracks";254;1
"Unit";"Marauder";"Barracks";255;2
"Unit";"Marine";"Barracks";257;1
"Unit";"Marine";"Barracks";258;1
"Unit";"Marine";"Barracks";259;1
"Unit";"Marine";"Barracks";260;1
"Unit";"Marine";"Barracks";261;1
"Unit";"Marauder";"Barracks";262;2
"Building";"CommandCenter";NA;264;0
"Unit";"Marine";"Barracks";264;1
"Unit";"Marine";"Barracks";265;1
"Unit";"Marine";"Barracks";266;1
"Building";"BarracksTechLab";NA;267;0
"Building";"BarracksTechLab";NA;267;0
"Building";"BarracksTechLab";NA;267;0
"Unit";"Marauder";"Barracks";267;2
"Unit";"Marine";"Barracks";269;1
"Unit";"Marine";"Barracks";270;1
"Unit";"Marine";"Barracks";271;1
"Unit";"Marine";"Barracks";272;1
"Unit";"Marine";"Barracks";273;1
"Unit";"Marine";"Barracks";274;1
"Unit";"Marine";"Barracks";275;1
"Unit";"Marine";"Barracks";276;1
"Unit";"Marine";"Barracks";277;1
"Unit";"Marine";"Barracks";278;1
"Unit";"Marine";"Barracks";279;1
"Unit";"Marauder";"Barracks";280;2
"Unit";"Marine";"Barracks";282;1
"Unit";"Marauder";"Barracks";283;2
"Unit";"Marine";"Barracks";285;1
"Unit";"Marauder";"Barracks";289;2
"Unit";"Marine";"Barracks";291;1
"Unit";"Marine";"Barracks";292;1
"Unit";"Marine";"Barracks";293;1
"Unit";"Marine";"Barracks";294;1
"Unit";"Marine";"Barracks";295;1
"Unit";"Marine";"Barracks";296;1
"Unit";"Marine";"Barracks";297;1
"Unit";"Marauder";"Barracks";298;2
"Unit";"Marauder";"Barracks";303;2
"Unit";"Liberator";"Starport";305;3
"Unit";"Liberator";"Starport";308;3
"Building";"MissileTurret";NA;312;0
"Unit";"Marauder";"Barracks";312;2
"Unit";"Marine";"Barracks";314;1
"Unit";"Marauder";"Barracks";315;2
"Unit";"Marine";"Barracks";317;1
"Unit";"Marine";"Barracks";318;1
"Unit";"Marine";"Barracks";319;1
"Unit";"Marine";"Barracks";320;1
"Unit";"Marine";"Barracks";321;1
"Unit";"Marine";"Barracks";322;1
"Unit";"Marine";"Barracks";323;1
"Unit";"Marine";"Barracks";324;1
"Unit";"Marine";"Barracks";325;1
"Unit";"Marauder";"Barracks";326;2
"Unit";"Marine";"Barracks";328;1
"Unit";"Marine";"Barracks";329;1
"Unit";"Marine";"Barracks";330;1
"Unit";"Marine";"Barracks";331;1
"Unit";"Marine";"Barracks";332;1
"Unit";"Marine";"Barracks";333;1
"Unit";"Marine";"Barracks";334;1
"Unit";"Marauder";"Barracks";335;2
"Unit";"Marauder";"Barracks";337;2
"Unit";"Marine";"Barracks";339;1
"Unit";"Marine";"Barracks";340;1
"Unit";"Marine";"Barracks";341;1
"Unit";"Marine";"Barracks";342;1
"Unit";"Marine";"Barracks";343;1
"Unit";"Marine";"Barracks";344;1
"Unit";"Marine";"Barracks";345;1
"Unit";"Marauder";"Barracks";346;2
"Unit";"Marauder";"Barracks";348;2
"Unit";"Marauder";"Barracks";350;2
"Unit";"Marine";"Barracks";352;1
"Unit";"Marine";"Barracks";353;1
"Unit";"Marine";"Barracks";354;1
"Unit";"Marine";"Barracks";355;1
"Unit";"Marauder";"Barracks";356;2
"Unit";"Marine";"Barracks";358;1
"Unit";"Marine";"Barracks";359;1
"Unit";"Marine";"Barracks";360;1
"Unit";"Marine";"Barracks";361;1
"Unit";"Marine";"Barracks";364;1
"Unit";"Marine";"Barracks";365;1
"Unit";"Medivac";"Starport";366;2
"Unit";"Medivac";"Starport";368;2
"Unit";"Marine";"Barracks";370;1
"Unit";"Marauder";"Barracks";371;2
"Unit";"Marauder";"Barracks";375;2
"Unit";"Marine";"Barracks";377;1
"Unit";"Marine";"Barracks";378;1
"Unit";"Marine";"Barracks";379;1
"Unit";"Marine";"Barracks";380;1
"Unit";"Marauder";"Barracks";381;2
"Unit";"Marine";"Barracks";383;1
"Unit";"Marine";"Barracks";384;1
"Upgrade";"SprayTerran";NA;385;0
"Upgrade";"SprayTerran";NA;385;0
"Upgrade";"SprayTerran";NA;385;0
"Upgrade";"BansheeCloak";NA;385;0
"Upgrade";"SprayTerran";NA;385;0
"Upgrade";"TerranInfantryArmorsLevel1";NA;385;0
"Upgrade";"SprayTerran";NA;385;0
"Upgrade";"TerranInfantryArmorsLevel2";NA;385;0
"Upgrade";"ShieldWall";NA;385;0
"Upgrade";"SprayTerran";NA;385;0
"Upgrade";"SprayTerran";NA;385;0
"Upgrade";"TerranInfantryArmorsLevel3";NA;385;0
"Upgrade";"SprayTerran";NA;385;0
"Upgrade";"PunisherGrenades";NA;385;0
