"type";"unit_name";"on_building";"total_supply_lag";"supply"
"Building";"Refinery";NA;15;0
"Building";"Barracks";NA;16;0
"Unit";"Reaper";"Barracks";19;1
"Building";"CommandCenter";NA;20;0
"Building";"Factory";NA;20;0
"Building";"BarracksReactor";NA;21;0
"Building";"Refinery";NA;21;0
"Building";"Starport";NA;24;0
"Unit";"Hellion";"Factory";24;2
"Unit";"Hellion";"Factory";26;2
"Building";"BarracksTechLab";NA;29;0
"Unit";"Hellion";"Factory";30;2
"Unit";"Hellion";"Factory";32;2
"Unit";"Hellion";"Factory";37;2
"Unit";"Hellion";"Factory";39;2
"Unit";"Banshee";"Starport";41;3
"Building";"BarracksTechLab";NA;46;0
"Unit";"Marine";"Barracks";48;1
"Building";"CommandCenter";NA;51;0
"Unit";"Banshee";"Starport";51;3
"Unit";"Marine";"Barracks";56;1
"Building";"FactoryReactor";NA;59;0
"Building";"Barracks";NA;59;0
"Upgrade";"Stimpack";"TechLab";59;0
"Unit";"Marine";"Barracks";59;1
"Building";"Barracks";NA;60;0
"Building";"EngineeringBay";NA;61;0
"Building";"EngineeringBay";NA;61;0
"Building";"Refinery";NA;63;0
"Building";"Refinery";NA;63;0
"Unit";"Marine";"Barracks";63;1
"Building";"FactoryReactor";NA;66;0
"Building";"StarportReactor";NA;66;0
"Unit";"Marine";"Barracks";66;1
"Unit";"Marine";"Barracks";67;1
"Building";"Barracks";NA;70;0
"Building";"Barracks";NA;70;0
"Unit";"Marine";"Barracks";70;1
"Unit";"Marine";"Barracks";71;1
"Unit";"Marine";"Barracks";72;1
"Unit";"Marine";"Barracks";75;1
"Upgrade";"TerranInfantryWeaponsLevel1";"EngineeringBay";76;0
"Unit";"Marine";"Barracks";76;1
"Unit";"Marine";"Barracks";77;1
"Unit";"Marine";"Barracks";78;1
"Unit";"Marine";"Barracks";81;1
"Unit";"Marine";"Barracks";82;1
"Unit";"Medivac";"Starport";83;2
"Unit";"Medivac";"Starport";85;2
"Building";"FactoryReactor";NA;87;0
"Unit";"Marine";"Barracks";88;1
"Unit";"Marine";"Barracks";89;1
"Unit";"Marine";"Barracks";90;1
"Building";"BarracksReactor";NA;91;0
"Building";"BarracksReactor";NA;91;0
"Unit";"Medivac";"Starport";91;2
"Unit";"Medivac";"Starport";93;2
"Building";"Armory";NA;98;0
"Unit";"Marine";"Barracks";98;1
"Unit";"Marine";"Barracks";99;1
"Unit";"Marine";"Barracks";100;1
"Unit";"Marine";"Barracks";101;1
"Unit";"Marine";"Barracks";102;1
"Building";"Factory";NA;103;0
"Unit";"Marine";"Barracks";103;1
"Unit";"Marine";"Barracks";104;1
"Unit";"Marine";"Barracks";105;1
"Unit";"Marine";"Barracks";106;1
"Unit";"Marine";"Barracks";107;1
"Unit";"Marine";"Barracks";112;1
"Unit";"Marine";"Barracks";113;1
"Unit";"Marine";"Barracks";114;1
"Unit";"Marine";"Barracks";115;1
"Unit";"Marine";"Barracks";116;1
"Unit";"Marine";"Barracks";117;1
"Unit";"Marine";"Barracks";120;1
"Unit";"Marine";"Barracks";121;1
"Unit";"Marine";"Barracks";122;1
"Unit";"Marine";"Barracks";123;1
"Unit";"Marine";"Barracks";124;1
"Unit";"Marine";"Barracks";125;1
"Unit";"Marine";"Barracks";126;1
"Unit";"Marine";"Barracks";127;1
"Unit";"Marine";"Barracks";128;1
"Unit";"Thor";"Factory";129;6
"Unit";"Medivac";"Starport";135;2
"Unit";"Medivac";"Starport";137;2
"Unit";"Marine";"Barracks";139;1
"Unit";"Marine";"Barracks";140;1
"Unit";"Marine";"Barracks";141;1
"Unit";"Marine";"Barracks";142;1
"Unit";"Marine";"Barracks";143;1
"Unit";"Marine";"Barracks";144;1
"Unit";"Marine";"Barracks";145;1
"Unit";"Marine";"Barracks";146;1
"Unit";"Marine";"Barracks";147;1
"Unit";"Marine";"Barracks";148;1
"Unit";"Marine";"Barracks";149;1
"Unit";"Marine";"Barracks";150;1
"Unit";"Marine";"Barracks";151;1
"Unit";"Marine";"Barracks";152;1
"Unit";"Marine";"Barracks";153;1
"Upgrade";"TerranInfantryWeaponsLevel2";"EngineeringBay";154;0
"Unit";"Marine";"Barracks";154;1
"Unit";"Marine";"Barracks";155;1
"Unit";"Marine";"Barracks";156;1
"Unit";"Thor";"Factory";157;6
"Building";"CommandCenter";NA;168;0
"Building";"MissileTurret";NA;168;0
"Building";"MissileTurret";NA;168;0
"Unit";"Marine";"Barracks";168;1
"Unit";"Marine";"Barracks";169;1
"Unit";"Marine";"Barracks";170;1
"Unit";"Marine";"Barracks";171;1
"Unit";"Marine";"Barracks";172;1
"Unit";"Marine";"Barracks";173;1
"Unit";"Marine";"Barracks";174;1
"Unit";"Marine";"Barracks";175;1
"Unit";"Marine";"Barracks";176;1
"Building";"Refinery";NA;177;0
"Building";"Refinery";NA;177;0
"Unit";"Marine";"Barracks";177;1
"Unit";"Marine";"Barracks";178;1
"Unit";"Marine";"Barracks";179;1
"Unit";"Marine";"Barracks";180;1
"Unit";"Marine";"Barracks";181;1
"Unit";"Marine";"Barracks";182;1
"Unit";"Marine";"Barracks";183;1
"Unit";"Marine";"Barracks";184;1
"Unit";"Marine";"Barracks";185;1
"Unit";"Marine";"Barracks";186;1
"Unit";"Marine";"Barracks";187;1
"Unit";"Thor";"Factory";188;6
"Unit";"Marine";"Barracks";194;1
"Unit";"Marine";"Barracks";195;1
"Unit";"Marine";"Barracks";196;1
"Unit";"Marine";"Barracks";197;1
"Unit";"Marine";"Barracks";198;1
"Unit";"Marine";"Barracks";199;1
"Unit";"Marine";"Barracks";200;1
"Unit";"Marine";"Barracks";201;1
"Unit";"Medivac";"Starport";202;2
"Unit";"Medivac";"Starport";204;2
"Unit";"Marauder";"Barracks";206;2
"Unit";"Marine";"Barracks";208;1
"Unit";"Marine";"Barracks";209;1
"Unit";"Marine";"Barracks";210;1
"Unit";"Marine";"Barracks";211;1
"Unit";"Marine";"Barracks";212;1
"Unit";"Marine";"Barracks";213;1
"Unit";"Marine";"Barracks";214;1
"Unit";"Marine";"Barracks";215;1
"Unit";"Marine";"Barracks";216;1
"Unit";"Marine";"Barracks";217;1
"Unit";"Marine";"Barracks";218;1
"Unit";"Marine";"Barracks";219;1
"Unit";"Marine";"Barracks";220;1
"Unit";"Marine";"Barracks";221;1
"Unit";"Marine";"Barracks";222;1
"Unit";"Medivac";"Starport";223;2
"Unit";"Medivac";"Starport";225;2
"Upgrade";"TerranInfantryWeaponsLevel3";"EngineeringBay";227;0
"Building";"CommandCenter";NA;227;0
"Unit";"Marine";"Barracks";227;1
"Unit";"Marine";"Barracks";228;1
"Unit";"Marine";"Barracks";229;1
"Unit";"Thor";"Factory";230;6
"Unit";"Marine";"Barracks";236;1
"Unit";"Marine";"Barracks";237;1
"Unit";"Marine";"Barracks";238;1
"Unit";"Marine";"Barracks";239;1
"Unit";"Marine";"Barracks";240;1
"Unit";"Marine";"Barracks";241;1
"Unit";"Marine";"Barracks";242;1
"Unit";"Marauder";"Barracks";243;2
"Unit";"Marine";"Barracks";245;1
"Unit";"Marine";"Barracks";246;1
"Unit";"Marine";"Barracks";247;1
"Unit";"Marine";"Barracks";248;1
"Unit";"Medivac";"Starport";249;2
"Unit";"Medivac";"Starport";251;2
"Unit";"Marauder";"Barracks";253;2
"Unit";"Marine";"Barracks";255;1
"Unit";"Medivac";"Starport";256;2
"Unit";"Medivac";"Starport";258;2
"Unit";"Marine";"Barracks";260;1
"Unit";"Marine";"Barracks";261;1
"Unit";"Marine";"Barracks";262;1
"Unit";"Marine";"Barracks";263;1
"Unit";"Marauder";"Barracks";264;2
"Unit";"Marine";"Barracks";266;1
"Unit";"Marine";"Barracks";267;1
"Unit";"Marine";"Barracks";268;1
"Unit";"Marine";"Barracks";269;1
"Unit";"Marine";"Barracks";270;1
"Unit";"Marine";"Barracks";271;1
"Unit";"Marine";"Barracks";272;1
"Unit";"Marine";"Barracks";273;1
"Unit";"Marine";"Barracks";274;1
"Unit";"Marine";"Barracks";275;1
"Unit";"Marauder";"Barracks";276;2
"Unit";"Marine";"Barracks";278;1
"Unit";"Marine";"Barracks";279;1
"Unit";"Medivac";"Starport";280;2
"Unit";"Marine";"Barracks";282;1
"Unit";"Marine";"Barracks";283;1
"Unit";"Marine";"Barracks";284;1
"Unit";"Marine";"Barracks";285;1
"Unit";"Marauder";"Barracks";286;2
"Unit";"Marine";"Barracks";288;1
"Unit";"Marine";"Barracks";289;1
"Unit";"Marine";"Barracks";290;1
"Unit";"Marine";"Barracks";291;1
"Unit";"Marine";"Barracks";292;1
"Unit";"Medivac";"Starport";293;2
"Unit";"Medivac";"Starport";295;2
"Unit";"Marine";"Barracks";297;1
"Unit";"Marine";"Barracks";298;1
"Unit";"Marine";"Barracks";299;1
"Unit";"Marine";"Barracks";300;1
"Unit";"Marine";"Barracks";301;1
"Unit";"Marine";"Barracks";302;1
"Unit";"Marauder";"Barracks";303;2
"Upgrade";"SprayTerran";NA;305;0
"Upgrade";"SprayTerran";NA;305;0
"Upgrade";"SprayTerran";NA;305;0
"Upgrade";"BansheeCloak";NA;305;0
"Upgrade";"SprayTerran";NA;305;0
"Upgrade";"TerranInfantryArmorsLevel1";NA;305;0
"Upgrade";"ShieldWall";NA;305;0
"Upgrade";"SprayTerran";NA;305;0
"Upgrade";"SprayTerran";NA;305;0
"Upgrade";"TerranInfantryArmorsLevel2";NA;305;0
"Upgrade";"SprayTerran";NA;305;0
"Upgrade";"SprayTerran";NA;305;0
"Upgrade";"TerranInfantryArmorsLevel3";NA;305;0
"Upgrade";"TerranVehicleAndShipArmorsLevel1";NA;305;0
