"type";"unit_name";"on_building";"total_supply_lag";"supply"
"Building";"Pylon";NA;14;0
"Building";"Gateway";NA;16;0
"Building";"Assimilator";NA;16;0
"Building";"Assimilator";NA;17;0
"Building";"Gateway";NA;18;0
"Building";"CyberneticsCore";NA;20;0
"Building";"Pylon";NA;21;0
"Unit";"Stalker";"Gateway";23;2
"Unit";"Stalker";"Gateway";25;2
"Building";"Pylon";NA;27;0
"Unit";"Stalker";"Gateway";28;2
"Unit";"Stalker";"Gateway";30;2
"Building";"Nexus";NA;32;0
"Building";"Stargate";NA;32;0
"Building";"Pylon";NA;35;0
"Unit";"Oracle";"Stargate";36;3
"Building";"Pylon";NA;39;0
"Unit";"Sentry";"Gateway";40;2
"Unit";"Stalker";"Gateway";42;2
"Unit";"Adept";"Gateway";44;2
"Unit";"Adept";"Gateway";46;2
"Building";"Pylon";NA;48;0
"Building";"Pylon";NA;48;0
"Unit";"Adept";"Gateway";48;2
"Unit";"Adept";"Gateway";50;2
"Building";"Pylon";NA;52;0
"Unit";"Adept";"Gateway";52;2
"Unit";"Adept";"Gateway";54;2
"Building";"RoboticsFacility";NA;57;0
"Unit";"Adept";"Gateway";57;2
"Unit";"Adept";"Gateway";59;2
"Building";"Nexus";NA;63;0
"Building";"Pylon";NA;64;0
"Building";"OracleStasisTrap";NA;64;0
"Unit";"Observer";"Robotics Facility";64;1
"Unit";"Stalker";"Gateway";65;2
"Unit";"Stalker";"Gateway";67;2
"Building";"TwilightCouncil";NA;70;0
"Unit";"Stalker";"Gateway";71;2
"Unit";"Stalker";"Gateway";73;2
"Unit";"Observer";"Robotics Facility";77;1
"Building";"Assimilator";NA;79;0
"Building";"Assimilator";NA;79;0
"Unit";"Immortal";"Robotics Facility";81;4
"Building";"Forge";NA;89;0
"Building";"Pylon";NA;89;0
"Unit";"Sentry";"Gateway";89;2
"Unit";"Stalker";"Gateway";91;2
"Building";"OracleStasisTrap";NA;93;0
"Unit";"Immortal";"Robotics Facility";93;4
"Building";"Gateway";NA;97;0
"Building";"Gateway";NA;97;0
"Building";"Nexus";NA;97;0
"Building";"TemplarArchive";NA;97;0
"Building";"Pylon";NA;97;0
"Unit";"Immortal";"Robotics Facility";97;4
"Building";"OracleStasisTrap";NA;101;0
"Unit";"Phoenix";"Stargate";101;2
"Upgrade";"ProtossGroundWeaponsLevel1";"Forge";103;0
"Building";"Pylon";NA;103;0
"Building";"Pylon";NA;103;0
"Building";"Pylon";NA;103;0
"Building";"HighTemplar";NA;105;0
"Building";"HighTemplar";NA;105;0
"Unit";"Stalker";"Gateway";105;2
"Building";"Pylon";NA;107;0
"Unit";"Stalker";"Gateway";107;2
"Building";"HighTemplar";NA;113;0
"Building";"HighTemplar";NA;113;0
"Unit";"Archon";"High Templar";114;0
"Unit";"Archon";"High Templar";114;0
"Unit";"Observer";"Robotics Facility";116;1
"Building";"Pylon";NA;118;0
"Building";"Gateway";NA;120;0
"Building";"Gateway";NA;121;0
"Unit";"Sentry";"Gateway";121;2
"Unit";"Adept";"Gateway";123;2
"Building";"Assimilator";NA;131;0
"Upgrade";"ProtossGroundWeaponsLevel2";"Forge";131;0
"Building";"Assimilator";NA;132;0
"Unit";"Phoenix";"Stargate";136;2
"Unit";"Stalker";"Gateway";139;2
"Unit";"Stalker";"Gateway";141;2
"Unit";"Stalker";"Gateway";143;2
"Building";"Pylon";NA;147;0
"Building";"Gateway";NA;147;0
"Building";"Gateway";NA;147;0
"Unit";"Immortal";"Robotics Facility";147;4
"Building";"HighTemplar";NA;151;0
"Building";"HighTemplar";NA;151;0
"Unit";"Adept";"Gateway";151;2
"Unit";"Adept";"Gateway";153;2
"Unit";"Adept";"Gateway";155;2
"Unit";"Adept";"Gateway";157;2
"Unit";"Archon";"High Templar";159;0
"Unit";"Phoenix";"Stargate";163;2
"Building";"PhotonCannon";NA;165;0
"Unit";"Immortal";"Robotics Facility";165;4
"Building";"HighTemplar";NA;169;0
"Building";"HighTemplar";NA;169;0
"Building";"HighTemplar";NA;169;0
"Building";"HighTemplar";NA;169;0
"Building";"Nexus";NA;169;0
"Unit";"Archon";"High Templar";169;0
"Unit";"Archon";"High Templar";169;0
"Building";"RoboticsBay";NA;169;0
"Building";"Pylon";NA;169;0
"Building";"RoboticsFacility";NA;169;0
"Building";"Pylon";NA;169;0
"Building";"Pylon";NA;172;0
"Unit";"Stalker";"Gateway";172;2
"Unit";"Stalker";"Gateway";174;2
"Unit";"Stalker";"Gateway";176;2
"Unit";"Stalker";"Gateway";178;2
"Unit";"Stalker";"Gateway";180;2
"Upgrade";"ProtossGroundWeaponsLevel3";"Forge";182;0
"Unit";"Disruptor";"Robotics Facility";182;3
"Unit";"Disruptor";"Robotics Facility";185;3
"Unit";"Adept";"Gateway";188;2
"Unit";"Adept";"Gateway";190;2
"Unit";"Adept";"Gateway";192;2
"Unit";"Adept";"Gateway";194;2
"Unit";"Adept";"Gateway";196;2
"Unit";"Adept";"Gateway";198;2
"Unit";"Adept";"Gateway";200;2
"Building";"Assimilator";NA;202;0
"Building";"Assimilator";NA;202;0
"Unit";"Disruptor";"Robotics Facility";202;3
"Unit";"Disruptor";"Robotics Facility";205;3
"Building";"PhotonCannon";NA;208;0
"Building";"PhotonCannon";NA;208;0
"Building";"PhotonCannon";NA;208;0
"Building";"PhotonCannon";NA;208;0
"Unit";"Stalker";"Gateway";208;2
"Unit";"Stalker";"Gateway";210;2
"Unit";"Stalker";"Gateway";212;2
"Unit";"Stalker";"Gateway";214;2
"Unit";"Stalker";"Gateway";216;2
"Unit";"Stalker";"Gateway";218;2
"Unit";"Stalker";"Gateway";220;2
"Unit";"Stalker";"Gateway";222;2
"Unit";"Disruptor";"Robotics Facility";224;3
"Unit";"Disruptor";"Robotics Facility";227;3
"Unit";"Stalker";"Gateway";230;2
"Unit";"Stalker";"Gateway";232;2
"Unit";"Stalker";"Gateway";234;2
"Unit";"Stalker";"Gateway";236;2
"Unit";"Stalker";"Gateway";238;2
"Unit";"Stalker";"Gateway";240;2
"Unit";"Disruptor";"Robotics Facility";242;3
"Unit";"Stalker";"Gateway";245;2
"Unit";"Stalker";"Gateway";247;2
"Unit";"Stalker";"Gateway";249;2
"Unit";"Stalker";"Gateway";251;2
"Unit";"Stalker";"Gateway";253;2
"Unit";"Stalker";"Gateway";255;2
"Unit";"Stalker";"Gateway";257;2
"Unit";"Stalker";"Gateway";259;2
"Building";"Stargate";NA;261;0
"Unit";"Disruptor";"Robotics Facility";261;3
"Unit";"Disruptor";"Robotics Facility";264;3
"Unit";"Stalker";"Gateway";267;2
"Unit";"Stalker";"Gateway";269;2
"Unit";"Stalker";"Gateway";272;2
"Unit";"Disruptor";"Robotics Facility";277;3
"Unit";"Adept";"Gateway";280;2
"Unit";"Adept";"Gateway";282;2
"Unit";"Adept";"Gateway";284;2
"Unit";"Adept";"Gateway";286;2
"Unit";"Adept";"Gateway";288;2
"Unit";"Adept";"Gateway";290;2
"Unit";"Adept";"Gateway";292;2
"Unit";"Adept";"Gateway";294;2
"Unit";"Oracle";"Stargate";296;3
"Upgrade";"ProtossShieldsLevel1";"Forge";299;0
"Unit";"Disruptor";"Robotics Facility";299;3
"Building";"Nexus";NA;302;0
"Unit";"Disruptor";"Robotics Facility";302;3
"Unit";"Adept";"Gateway";305;2
"Unit";"Adept";"Gateway";307;2
"Unit";"Adept";"Gateway";309;2
"Unit";"Adept";"Gateway";311;2
"Unit";"Adept";"Gateway";313;2
"Unit";"Adept";"Gateway";315;2
"Unit";"Disruptor";"Robotics Facility";317;3
"Building";"Pylon";NA;320;0
"Unit";"Adept";"Gateway";320;2
"Unit";"Adept";"Gateway";322;2
"Unit";"Adept";"Gateway";324;2
"Unit";"Adept";"Gateway";326;2
"Unit";"Adept";"Gateway";328;2
"Unit";"Adept";"Gateway";330;2
"Unit";"Disruptor";"Robotics Facility";332;3
"Unit";"Disruptor";"Robotics Facility";335;3
"Unit";"Disruptor";"Robotics Facility";338;3
"Building";"Assimilator";NA;341;0
"Unit";"Stalker";"Gateway";341;2
"Unit";"Stalker";"Gateway";343;2
"Unit";"Stalker";"Gateway";345;2
"Building";"Assimilator";NA;349;0
"Building";"PhotonCannon";NA;349;0
"Unit";"Adept";"Gateway";349;2
"Unit";"Adept";"Gateway";351;2
"Unit";"Adept";"Gateway";353;2
"Unit";"Adept";"Gateway";355;2
"Unit";"Adept";"Gateway";357;2
"Unit";"Adept";"Gateway";359;2
"Unit";"Adept";"Gateway";361;2
"Unit";"Adept";"Gateway";363;2
"Unit";"Adept";"Gateway";365;2
"Unit";"Adept";"Gateway";367;2
"Unit";"Adept";"Gateway";369;2
"Unit";"Disruptor";"Robotics Facility";371;3
"Unit";"Disruptor";"Robotics Facility";374;3
"Building";"Nexus";NA;377;0
"Unit";"Oracle";"Stargate";377;3
"Unit";"Adept";"Gateway";380;2
"Unit";"Adept";"Gateway";382;2
"Unit";"Adept";"Gateway";384;2
"Unit";"Adept";"Gateway";386;2
"Unit";"Adept";"Gateway";388;2
"Unit";"Adept";"Gateway";390;2
"Unit";"Adept";"Gateway";392;2
"Unit";"Adept";"Gateway";394;2
"Unit";"Disruptor";"Robotics Facility";396;3
"Unit";"Disruptor";"Robotics Facility";399;3
"Unit";"Stalker";"Gateway";402;2
"Unit";"Stalker";"Gateway";404;2
"Unit";"Stalker";"Gateway";406;2
"Unit";"Stalker";"Gateway";408;2
"Unit";"Stalker";"Gateway";410;2
"Unit";"Stalker";"Gateway";412;2
"Unit";"Stalker";"Gateway";414;2
"Unit";"Stalker";"Gateway";416;2
"Building";"Assimilator";NA;418;0
"Building";"Gateway";NA;418;0
"Building";"Gateway";NA;418;0
"Building";"Gateway";NA;418;0
"Upgrade";"Charge";"TwilightCouncil";418;0
"Unit";"Disruptor";"Robotics Facility";418;3
"Unit";"Disruptor";"Robotics Facility";421;3
"Building";"Pylon";NA;424;0
"Unit";"Stalker";"Gateway";424;2
"Unit";"Stalker";"Gateway";426;2
"Unit";"Stalker";"Gateway";428;2
"Unit";"Stalker";"Gateway";430;2
"Unit";"Stalker";"Gateway";432;2
"Unit";"Stalker";"Gateway";434;2
"Unit";"Stalker";"Gateway";436;2
"Unit";"Stalker";"Gateway";438;2
"Building";"PhotonCannon";NA;440;0
"Building";"Pylon";NA;440;0
"Unit";"Stalker";"Gateway";440;2
"Unit";"Stalker";"Gateway";442;2
"Unit";"Stalker";"Gateway";444;2
"Upgrade";"SprayProtoss";NA;446;0
"Upgrade";"WarpGateResearch";NA;446;0
"Upgrade";"SprayProtoss";NA;446;0
"Upgrade";"SprayProtoss";NA;446;0
"Upgrade";"SprayProtoss";NA;446;0
"Upgrade";"SprayProtoss";NA;446;0
"Upgrade";"BlinkTech";NA;446;0
"Upgrade";"SprayProtoss";NA;446;0
"Upgrade";"AdeptPiercingAttack";NA;446;0
"Upgrade";"SprayProtoss";NA;446;0
"Upgrade";"SprayProtoss";NA;446;0
"Upgrade";"SprayProtoss";NA;446;0
"Upgrade";"SprayProtoss";NA;446;0
"Upgrade";"SprayProtoss";NA;446;0
"Upgrade";"SprayProtoss";NA;446;0
"Upgrade";"SprayProtoss";NA;446;0
