"type";"unit_name";"on_building";"total_supply_lag";"supply"
"Building";"Pylon";NA;14;0
"Building";"Gateway";NA;16;0
"Building";"Assimilator";NA;16;0
"Building";"Gateway";NA;18;0
"Building";"CyberneticsCore";NA;19;0
"Unit";"Zealot";"Gateway";19;2
"Building";"Pylon";NA;21;0
"Unit";"Adept";"Gateway";22;2
"Unit";"Adept";"Gateway";24;2
"Unit";"Adept";"Gateway";26;2
"Unit";"Adept";"Gateway";29;2
"Building";"Nexus";NA;32;0
"Building";"Pylon";NA;33;0
"Building";"Assimilator";NA;33;0
"Unit";"Adept";"Gateway";34;2
"Unit";"Adept";"Gateway";36;2
"Building";"TwilightCouncil";NA;40;0
"Building";"Gateway";NA;44;0
"Unit";"Adept";"Gateway";45;2
"Unit";"Adept";"Gateway";47;2
"Unit";"Stalker";"Gateway";52;2
"Unit";"Sentry";"Gateway";54;2
"Building";"RoboticsFacility";NA;57;0
"Building";"Pylon";NA;59;0
"Building";"Pylon";NA;60;0
"Building";"Assimilator";NA;62;0
"Building";"DarkShrine";NA;62;0
"Building";"Assimilator";NA;62;0
"Unit";"Adept";"Gateway";64;2
"Unit";"Adept";"Gateway";66;2
"Unit";"Adept";"Gateway";68;2
"Building";"Pylon";NA;71;0
"Building";"Pylon";NA;72;0
"Unit";"Immortal";"Robotics Facility";75;4
"Building";"Pylon";NA;79;0
"Building";"Nexus";NA;80;0
"Unit";"Adept";"Gateway";81;2
"Unit";"Adept";"Gateway";83;2
"Building";"DarkTemplar";NA;85;0
"Building";"Pylon";NA;85;0
"Unit";"Immortal";"Robotics Facility";85;4
"Building";"DarkTemplar";NA;89;0
"Building";"DarkTemplar";NA;89;0
"Unit";"Immortal";"Robotics Facility";91;4
"Unit";"Sentry";"Gateway";96;2
"Building";"Gateway";NA;98;0
"Building";"Gateway";NA;98;0
"Building";"Gateway";NA;98;0
"Building";"Gateway";NA;98;0
"Building";"Gateway";NA;98;0
"Unit";"Sentry";"Gateway";99;2
"Unit";"Sentry";"Gateway";101;2
"Building";"Pylon";NA;105;0
"Building";"Pylon";NA;106;0
"Building";"Forge";NA;107;0
"Unit";"Observer";"Robotics Facility";107;1
"Building";"Assimilator";NA;110;0
"Building";"Assimilator";NA;110;0
"Building";"TemplarArchive";NA;110;0
"Building";"Pylon";NA;110;0
"Unit";"Zealot";"Gateway";110;2
"Building";"DarkTemplar";NA;112;0
"Unit";"Zealot";"Gateway";112;2
"Unit";"Zealot";"Gateway";114;2
"Unit";"Zealot";"Gateway";116;2
"Unit";"Zealot";"Gateway";118;2
"Unit";"Zealot";"Gateway";120;2
"Building";"PhotonCannon";NA;125;0
"Unit";"Immortal";"Robotics Facility";125;4
"Building";"Pylon";NA;129;0
"Building";"Stargate";NA;131;0
"Building";"PhotonCannon";NA;131;0
"Building";"PhotonCannon";NA;131;0
"Building";"PhotonCannon";NA;131;0
"Building";"Pylon";NA;131;0
"Building";"Pylon";NA;131;0
"Building";"HighTemplar";NA;131;0
"Building";"HighTemplar";NA;131;0
"Upgrade";"ProtossGroundWeaponsLevel1";"Forge";131;0
"Unit";"Stalker";"Gateway";131;2
"Unit";"Stalker";"Gateway";133;2
"Unit";"Archon";"High Templar";135;0
"Unit";"Immortal";"Robotics Facility";135;4
"Building";"HighTemplar";NA;139;0
"Unit";"Stalker";"Gateway";142;2
"Unit";"Stalker";"Gateway";144;2
"Unit";"Stalker";"Gateway";146;2
"Unit";"Stalker";"Gateway";148;2
"Upgrade";"Charge";"TwilightCouncil";150;0
"Building";"HighTemplar";NA;150;0
"Building";"Pylon";NA;150;0
"Building";"Nexus";NA;150;0
"Building";"Pylon";NA;150;0
"Building";"HighTemplar";NA;151;0
"Building";"Pylon";NA;151;0
"Building";"HighTemplar";NA;151;0
"Building";"Pylon";NA;151;0
"Unit";"Zealot";"Gateway";151;2
"Unit";"Zealot";"Gateway";153;2
"Unit";"Zealot";"Gateway";155;2
"Unit";"Zealot";"Gateway";157;2
"Unit";"Zealot";"Gateway";159;2
"Unit";"Zealot";"Gateway";161;2
"Unit";"Zealot";"Gateway";163;2
"Unit";"Zealot";"Gateway";165;2
"Unit";"Zealot";"Gateway";167;2
"Building";"Pylon";NA;169;0
"Building";"PhotonCannon";NA;169;0
"Unit";"Immortal";"Robotics Facility";169;4
"Building";"PhotonCannon";NA;173;0
"Building";"HighTemplar";NA;173;0
"Building";"HighTemplar";NA;173;0
"Building";"HighTemplar";NA;173;0
"Building";"HighTemplar";NA;173;0
"Unit";"Archon";"High Templar";173;0
"Unit";"Archon";"High Templar";173;0
"Unit";"Zealot";"Gateway";173;2
"Unit";"Zealot";"Gateway";175;2
"Unit";"Zealot";"Gateway";177;2
"Unit";"Zealot";"Gateway";179;2
"Building";"Gateway";NA;181;0
"Building";"Gateway";NA;181;0
"Unit";"Immortal";"Robotics Facility";181;4
"Unit";"Zealot";"Gateway";185;2
"Unit";"Zealot";"Gateway";187;2
"Unit";"Zealot";"Gateway";189;2
"Unit";"Zealot";"Gateway";191;2
"Upgrade";"ProtossGroundWeaponsLevel2";"Forge";193;0
"Unit";"Zealot";"Gateway";193;2
"Unit";"Zealot";"Gateway";195;2
"Unit";"Zealot";"Gateway";197;2
"Unit";"Zealot";"Gateway";199;2
"Building";"HighTemplar";NA;201;0
"Building";"HighTemplar";NA;201;0
"Unit";"Immortal";"Robotics Facility";201;4
"Unit";"Zealot";"Gateway";205;2
"Unit";"Zealot";"Gateway";207;2
"Building";"Assimilator";NA;209;0
"Building";"PhotonCannon";NA;209;0
"Building";"HighTemplar";NA;211;0
"Building";"HighTemplar";NA;211;0
"Unit";"Archon";"High Templar";211;0
"Unit";"Zealot";"Gateway";211;2
"Unit";"Zealot";"Gateway";213;2
"Unit";"Zealot";"Gateway";215;2
"Unit";"Zealot";"Gateway";217;2
"Unit";"Immortal";"Robotics Facility";219;4
"Unit";"Zealot";"Gateway";223;2
"Unit";"Zealot";"Gateway";225;2
"Building";"FleetBeacon";NA;227;0
"Unit";"Zealot";"Gateway";227;2
"Unit";"Zealot";"Gateway";229;2
"Unit";"Zealot";"Gateway";231;2
"Unit";"Zealot";"Gateway";233;2
"Unit";"Zealot";"Gateway";235;2
"Building";"HighTemplar";NA;237;0
"Building";"HighTemplar";NA;237;0
"Unit";"Immortal";"Robotics Facility";237;4
"Building";"Stargate";NA;241;0
"Building";"Nexus";NA;241;0
"Building";"Stargate";NA;241;0
"Building";"HighTemplar";NA;241;0
"Building";"HighTemplar";NA;241;0
"Building";"Pylon";NA;241;0
"Building";"Assimilator";NA;241;0
"Building";"Assimilator";NA;241;0
"Unit";"Adept";"Gateway";241;2
"Unit";"Adept";"Gateway";243;2
"Unit";"Adept";"Gateway";245;2
"Unit";"Adept";"Gateway";247;2
"Building";"PhotonCannon";NA;249;0
"Building";"PhotonCannon";NA;249;0
"Unit";"Phoenix";"Stargate";249;2
"Building";"PhotonCannon";NA;251;0
"Building";"PhotonCannon";NA;251;0
"Upgrade";"ProtossGroundWeaponsLevel3";"Forge";251;0
"Building";"PhotonCannon";NA;251;0
"Building";"PhotonCannon";NA;251;0
"Building";"PhotonCannon";NA;251;0
"Unit";"Immortal";"Robotics Facility";255;4
"Building";"HighTemplar";NA;261;0
"Building";"HighTemplar";NA;261;0
"Unit";"Zealot";"Gateway";261;2
"Unit";"Zealot";"Gateway";263;2
"Unit";"Zealot";"Gateway";265;2
"Unit";"Zealot";"Gateway";267;2
"Unit";"Archon";"High Templar";269;0
"Unit";"Carrier";"Stargate";271;6
"Unit";"Carrier";"Stargate";277;6
"Unit";"Immortal";"Robotics Facility";283;4
"Unit";"Carrier";"Stargate";287;6
"Building";"Nexus";NA;293;0
"Unit";"Zealot";"Gateway";293;2
"Unit";"Zealot";"Gateway";295;2
"Unit";"Zealot";"Gateway";297;2
"Unit";"Zealot";"Gateway";299;2
"Unit";"Zealot";"Gateway";301;2
"Building";"Pylon";NA;303;0
"Unit";"Zealot";"Gateway";303;2
"Unit";"Zealot";"Gateway";305;2
"Unit";"Zealot";"Gateway";307;2
"Unit";"Zealot";"Gateway";309;2
"Unit";"Zealot";"Gateway";311;2
"Unit";"Zealot";"Gateway";313;2
"Unit";"Zealot";"Gateway";315;2
"Unit";"Zealot";"Gateway";317;2
"Unit";"Zealot";"Gateway";319;2
"Unit";"Zealot";"Gateway";321;2
"Building";"PhotonCannon";NA;323;0
"Unit";"Stalker";"Gateway";323;2
"Unit";"Stalker";"Gateway";325;2
"Unit";"Stalker";"Gateway";327;2
"Unit";"Stalker";"Gateway";329;2
"Unit";"Stalker";"Gateway";331;2
"Unit";"Stalker";"Gateway";333;2
"Unit";"Stalker";"Gateway";335;2
"Unit";"Stalker";"Gateway";337;2
"Unit";"Stalker";"Gateway";339;2
"Upgrade";"ProtossAirWeaponsLevel1";"CyberneticsCore";341;0
"Unit";"Carrier";"Stargate";341;6
"Unit";"Zealot";"Gateway";347;2
"Building";"HighTemplar";NA;349;0
"Unit";"Zealot";"Gateway";349;2
"Unit";"Zealot";"Gateway";351;2
"Unit";"Zealot";"Gateway";353;2
"Unit";"Zealot";"Gateway";355;2
"Unit";"Zealot";"Gateway";357;2
"Unit";"Zealot";"Gateway";360;2
"Unit";"Zealot";"Gateway";362;2
"Building";"HighTemplar";NA;364;0
"Building";"HighTemplar";NA;364;0
"Building";"HighTemplar";NA;364;0
"Building";"HighTemplar";NA;364;0
"Building";"HighTemplar";NA;364;0
"Building";"HighTemplar";NA;364;0
"Building";"HighTemplar";NA;364;0
"Unit";"Archon";"High Templar";364;0
"Unit";"Archon";"High Templar";364;0
"Unit";"Archon";"High Templar";364;0
"Building";"HighTemplar";NA;364;0
"Unit";"Zealot";"Gateway";364;2
"Unit";"Zealot";"Gateway";366;2
"Unit";"Archon";"High Templar";368;0
"Unit";"Zealot";"Gateway";368;2
"Unit";"Zealot";"Gateway";370;2
"Unit";"Zealot";"Gateway";372;2
"Unit";"Zealot";"Gateway";374;2
"Unit";"Zealot";"Gateway";376;2
"Unit";"Zealot";"Gateway";378;2
"Unit";"Zealot";"Gateway";380;2
"Unit";"Zealot";"Gateway";382;2
"Building";"HighTemplar";NA;384;0
"Unit";"Stalker";"Gateway";384;2
"Unit";"Stalker";"Gateway";386;2
"Unit";"Stalker";"Gateway";388;2
"Unit";"Stalker";"Gateway";390;2
"Unit";"Stalker";"Gateway";392;2
"Unit";"Zealot";"Gateway";394;2
"Unit";"Zealot";"Gateway";396;2
"Unit";"Zealot";"Gateway";398;2
"Unit";"Zealot";"Gateway";400;2
"Unit";"Carrier";"Stargate";402;6
"Building";"HighTemplar";NA;408;0
"Building";"Pylon";NA;408;0
"Building";"DarkTemplar";NA;408;0
"Unit";"Zealot";"Gateway";408;2
"Unit";"Zealot";"Gateway";410;2
"Unit";"Zealot";"Gateway";412;2
"Unit";"Zealot";"Gateway";414;2
"Building";"DarkTemplar";NA;416;0
"Building";"HighTemplar";NA;416;0
"Building";"HighTemplar";NA;416;0
"Building";"DarkTemplar";NA;421;0
"Building";"DarkTemplar";NA;421;0
"Building";"DarkTemplar";NA;421;0
"Building";"DarkTemplar";NA;421;0
"Building";"DarkTemplar";NA;421;0
"Building";"DarkTemplar";NA;421;0
"Building";"HighTemplar";NA;421;0
"Building";"HighTemplar";NA;421;0
"Unit";"Zealot";"Gateway";421;2
"Unit";"Zealot";"Gateway";423;2
"Unit";"Zealot";"Gateway";425;2
"Unit";"Zealot";"Gateway";427;2
"Unit";"Zealot";"Gateway";429;2
"Unit";"Zealot";"Gateway";431;2
"Building";"DarkTemplar";NA;433;0
"Building";"HighTemplar";NA;433;0
"Building";"HighTemplar";NA;433;0
"Unit";"Zealot";"Gateway";433;2
"Unit";"Zealot";"Gateway";435;2
"Unit";"Zealot";"Gateway";437;2
"Unit";"Zealot";"Gateway";439;2
"Unit";"Zealot";"Gateway";441;2
"Building";"DarkTemplar";NA;443;0
"Building";"HighTemplar";NA;443;0
"Building";"HighTemplar";NA;443;0
"Unit";"Zealot";"Gateway";443;2
"Unit";"Zealot";"Gateway";445;2
"Unit";"Zealot";"Gateway";447;2
"Unit";"Zealot";"Gateway";449;2
"Unit";"Archon";"High Templar";451;0
"Unit";"Zealot";"Gateway";451;2
"Unit";"Zealot";"Gateway";453;2
"Building";"HighTemplar";NA;455;0
"Building";"HighTemplar";NA;455;0
"Upgrade";"SprayProtoss";NA;455;0
"Upgrade";"WarpGateResearch";NA;455;0
"Upgrade";"SprayProtoss";NA;455;0
"Upgrade";"AdeptPiercingAttack";NA;455;0
"Upgrade";"SprayProtoss";NA;455;0
"Upgrade";"SprayProtoss";NA;455;0
"Upgrade";"SprayProtoss";NA;455;0
"Upgrade";"PsiStormTech";NA;455;0
"Upgrade";"SprayProtoss";NA;455;0
"Upgrade";"SprayProtoss";NA;455;0
"Upgrade";"SprayProtoss";NA;455;0
"Upgrade";"CarrierLaunchSpeedUpgrade";NA;455;0
"Upgrade";"SprayProtoss";NA;455;0
"Upgrade";"SprayProtoss";NA;455;0
"Upgrade";"SprayProtoss";NA;455;0
"Upgrade";"SprayProtoss";NA;455;0
"Upgrade";"SprayProtoss";NA;455;0
