"type";"unit_name";"on_building";"total_supply";"supply"
"Unit";"Overlord";"Larva";13;0
"Building";"Extractor";NA;17;0
"Building";"Hatchery";NA;16;0
"Building";"SpawningPool";NA;19;0
"Unit";"Overlord";"Larva";22;0
"Unit";"Zergling";"Larva";23;1
"Unit";"Zergling";"Larva";23;1
"Unit";"Zergling";"Larva";23;1
"Unit";"Zergling";"Larva";23;1
"Unit";"Queen";"Hatchery";23;2
"Unit";"Queen";"Hatchery";23;2
"Building";"BanelingNest";NA;28;0
"Unit";"Zergling";"Larva";40;1
"Unit";"Zergling";"Larva";40;1
"Unit";"Zergling";"Larva";40;1
"Unit";"Zergling";"Larva";40;1
"Unit";"Zergling";"Larva";40;1
"Unit";"Zergling";"Larva";40;1
"Unit";"Overlord";"Larva";40;0
"Unit";"Zergling";"Larva";44;1
"Unit";"Zergling";"Larva";44;1
"Unit";"Overlord";"Larva";46;0
"Unit";"Zergling";"Larva";46;1
"Unit";"Zergling";"Larva";46;1
"Unit";"Zergling";"Larva";46;1
"Unit";"Zergling";"Larva";46;1
"Unit";"Zergling";"Larva";46;1
"Unit";"Zergling";"Larva";46;1
"Unit";"Baneling";"Zergling";46;0
"Unit";"Baneling";"Zergling";46;0
"Unit";"Zergling";"Larva";48;1
"Unit";"Zergling";"Larva";48;1
"Building";"Hatchery";NA;40;0
"Unit";"Zergling";"Larva";56;1
"Unit";"Zergling";"Larva";56;1
"Unit";"Zergling";"Larva";56;1
"Unit";"Zergling";"Larva";56;1
"Unit";"Baneling";"Zergling";59;0
"Building";"EvolutionChamber";NA;56;0
"Unit";"Queen";"Hatchery";48;2
"Unit";"Zergling";"Larva";59;1
"Unit";"Zergling";"Larva";59;1
"Unit";"Zergling";"Larva";59;1
"Unit";"Zergling";"Larva";59;1
"Unit";"Zergling";"Larva";59;1
"Unit";"Zergling";"Larva";59;1
"Building";"RoachWarren";NA;56;0
"Building";"CreepTumorQueen";NA;69;0
"Building";"CreepTumorQueen";NA;80;0
"Building";"CreepTumor";NA;80;0
"Unit";"Overlord";"Larva";77;0
"Building";"Extractor";NA;77;0
"Unit";"Baneling";"Zergling";85;0
"Unit";"Baneling";"Zergling";85;0
"Unit";"Overlord";"Larva";85;0
"Unit";"Queen";"Hatchery";77;2
"Unit";"Overlord";"Larva";85;0
"Unit";"Overlord";"Larva";85;0
"Unit";"Roach";"Larva";85;2
"Unit";"Roach";"Larva";85;2
"Unit";"Roach";"Larva";85;2
"Unit";"Roach";"Larva";85;2
"Unit";"Zergling";"Larva";85;1
"Unit";"Zergling";"Larva";85;1
"Unit";"Zergling";"Larva";85;1
"Unit";"Zergling";"Larva";85;1
"Unit";"Zergling";"Larva";85;1
"Unit";"Zergling";"Larva";85;1
"Unit";"Baneling";"Zergling";95;0
"Unit";"Baneling";"Zergling";95;0
"Unit";"Roach";"Larva";106;2
"Unit";"Roach";"Larva";106;2
"Unit";"Roach";"Larva";106;2
"Unit";"Roach";"Larva";106;2
"Building";"Extractor";NA;106;0
"Unit";"Zergling";"Larva";106;1
"Unit";"Zergling";"Larva";106;1
"Unit";"Roach";"Larva";106;2
"Unit";"Zergling";"Larva";106;1
"Unit";"Zergling";"Larva";106;1
"Unit";"Zergling";"Larva";106;1
"Unit";"Zergling";"Larva";106;1
"Unit";"Zergling";"Larva";106;1
"Unit";"Zergling";"Larva";106;1
"Unit";"Zergling";"Larva";106;1
"Unit";"Zergling";"Larva";106;1
"Unit";"Zergling";"Larva";106;1
"Unit";"Zergling";"Larva";106;1
"Unit";"Roach";"Larva";112;2
"Unit";"Roach";"Larva";112;2
"Unit";"Roach";"Larva";112;2
"Unit";"Roach";"Larva";128;2
"Unit";"Roach";"Larva";128;2
"Upgrade";"GlialReconstitution";"RoachWarren";106;0
"Unit";"Zergling";"Larva";128;1
"Unit";"Zergling";"Larva";128;1
"Unit";"Roach";"Larva";128;2
"Unit";"Zergling";"Larva";128;1
"Unit";"Zergling";"Larva";128;1
"Unit";"Zergling";"Larva";128;1
"Unit";"Zergling";"Larva";128;1
"Unit";"Zergling";"Larva";128;1
"Unit";"Zergling";"Larva";128;1
"Upgrade";"ZergMissileWeaponsLevel1";"EvolutionChamber";87;0
"Unit";"Queen";"Hatchery";128;2
"Unit";"Queen";"Hatchery";128;2
"Unit";"Roach";"Larva";134;2
"Unit";"Roach";"Larva";134;2
"Unit";"Roach";"Larva";138;2
"Unit";"Roach";"Larva";138;2
"Unit";"Overlord";"Larva";152;0
"Unit";"Overlord";"Larva";156;0
"Unit";"Zergling";"Larva";156;1
"Unit";"Zergling";"Larva";156;1
"Unit";"Roach";"Larva";160;2
"Unit";"Roach";"Larva";160;2
"Unit";"Roach";"Larva";160;2
"Unit";"Roach";"Larva";160;2
"Unit";"Roach";"Larva";160;2
"Unit";"Roach";"Larva";160;2
"Unit";"Roach";"Larva";160;2
"Unit";"Roach";"Larva";162;2
"Unit";"Roach";"Larva";162;2
"Unit";"Roach";"Larva";162;2
"Unit";"Roach";"Larva";162;2
"Unit";"Roach";"Larva";162;2
"Unit";"Roach";"Larva";162;2
"Unit";"Roach";"Larva";162;2
"Unit";"Zergling";"Larva";186;1
"Unit";"Zergling";"Larva";186;1
"Unit";"Roach";"Larva";186;2
"Unit";"Zergling";"Larva";186;1
"Unit";"Zergling";"Larva";186;1
"Unit";"Zergling";"Larva";186;1
"Unit";"Zergling";"Larva";186;1
"Unit";"Zergling";"Larva";186;1
"Unit";"Zergling";"Larva";186;1
"Unit";"Zergling";"Larva";186;1
"Unit";"Zergling";"Larva";186;1
"Unit";"Roach";"Larva";186;2
"Unit";"Roach";"Larva";186;2
"Building";"CreepTumorQueen";NA;190;0
"Building";"CreepTumor";NA;190;0
"Building";"Hatchery";NA;160;0
"Unit";"Roach";"Larva";190;2
"Unit";"Roach";"Larva";190;2
"Unit";"Roach";"Larva";206;2
"Unit";"Roach";"Larva";206;2
"Unit";"Overlord";"Larva";206;0
"Unit";"Roach";"Larva";210;2
"Unit";"Roach";"Larva";210;2
"Unit";"Roach";"Larva";210;2
"Unit";"Roach";"Larva";210;2
"Unit";"Roach";"Larva";210;2
"Unit";"Roach";"Larva";210;2
"Unit";"Roach";"Larva";212;2
"Unit";"Roach";"Larva";212;2
"Unit";"Roach";"Larva";214;2
"Unit";"Roach";"Larva";214;2
"Unit";"Roach";"Larva";228;2
"Unit";"Roach";"Larva";228;2
"Unit";"Roach";"Larva";228;2
"Unit";"Roach";"Larva";232;2
"Unit";"Roach";"Larva";232;2
"Unit";"Roach";"Larva";234;2
"Unit";"Roach";"Larva";234;2
"Unit";"Roach";"Larva";240;2
"Unit";"Roach";"Larva";240;2
"Unit";"Roach";"Larva";244;2
"Unit";"Roach";"Larva";244;2
"Unit";"Roach";"Larva";244;2
"Unit";"Zergling";"Larva";244;1
"Unit";"Zergling";"Larva";244;1
"Unit";"Zergling";"Larva";244;1
"Unit";"Zergling";"Larva";244;1
"Unit";"Zergling";"Larva";244;1
"Unit";"Zergling";"Larva";244;1
"Unit";"Overlord";"Larva";248;0
"Building";"Extractor";NA;244;0
