"type";"unit_name";"on_building";"total_supply";"supply"
"Unit";"Overlord";"Larva";13;0
"Building";"Extractor";NA;20;0
"Unit";"Overlord";"Larva";21;0
"Building";"SpawningPool";NA;19;0
"Building";"Hatchery";NA;17;0
"Unit";"Zergling";"Larva";22;1
"Unit";"Zergling";"Larva";22;1
"Unit";"Zergling";"Larva";22;1
"Unit";"Zergling";"Larva";22;1
"Unit";"Zergling";"Larva";22;1
"Unit";"Zergling";"Larva";22;1
"Unit";"Zergling";"Larva";22;1
"Unit";"Zergling";"Larva";22;1
"Unit";"Queen";"Hatchery";22;2
"Unit";"Queen";"Hatchery";32;2
"Unit";"Overlord";"Larva";37;0
"Unit";"Overlord";"Larva";40;0
"Unit";"Zergling";"Larva";45;1
"Unit";"Zergling";"Larva";45;1
"Unit";"Overlord";"Larva";51;0
"Unit";"Overlord";"Larva";59;0
"Building";"EvolutionChamber";NA;61;0
"Building";"EvolutionChamber";NA;61;0
"Building";"CreepTumorQueen";NA;66;0
"Building";"RoachWarren";NA;61;0
"Unit";"Queen";"Hatchery";61;2
"Building";"Extractor";NA;62;0
"Building";"Extractor";NA;62;0
"Unit";"Overlord";"Larva";68;0
"Unit";"Overlord";"Larva";73;0
"Unit";"Overlord";"Larva";73;0
"Unit";"Roach";"Larva";73;2
"Unit";"Overlord";"Larva";73;0
"Unit";"Overlord";"Larva";73;0
"Building";"CreepTumor";NA;73;0
"Unit";"Roach";"Larva";75;2
"Unit";"Roach";"Larva";75;2
"Unit";"Roach";"Larva";75;2
"Unit";"Roach";"Larva";75;2
"Unit";"Roach";"Larva";75;2
"Unit";"Roach";"Larva";75;2
"Unit";"Roach";"Larva";75;2
"Unit";"Roach";"Larva";75;2
"Building";"SpineCrawler";NA;75;0
"Unit";"Roach";"Larva";87;2
"Unit";"Roach";"Larva";87;2
"Unit";"Roach";"Larva";87;2
"Building";"CreepTumor";NA;92;0
"Unit";"Roach";"Larva";92;2
"Unit";"Roach";"Larva";92;2
"Unit";"Roach";"Larva";92;2
"Unit";"Roach";"Larva";92;2
"Building";"CreepTumorQueen";NA;98;0
"Unit";"Queen";"Hatchery";92;2
"Unit";"Overlord";"Larva";98;0
"Unit";"Overlord";"Larva";98;0
"Unit";"Roach";"Larva";98;2
"Unit";"Roach";"Larva";98;2
"Unit";"Roach";"Larva";98;2
"Upgrade";"GlialReconstitution";"RoachWarren";75;0
"Upgrade";"ZergMissileWeaponsLevel1";"EvolutionChamber";73;0
"Building";"CreepTumor";NA;114;0
"Unit";"Roach";"Larva";114;2
"Unit";"Roach";"Larva";114;2
"Unit";"Roach";"Larva";114;2
"Unit";"Roach";"Larva";114;2
"Unit";"Roach";"Larva";114;2
"Unit";"Roach";"Larva";114;2
"Unit";"Roach";"Larva";114;2
"Unit";"Roach";"Larva";114;2
"Unit";"Overlord";"Larva";114;0
"Unit";"Roach";"Larva";114;2
"Building";"Hatchery";NA;98;0
"Building";"CreepTumor";NA;130;0
"Building";"Extractor";NA;130;0
"Unit";"Overlord";"Larva";133;0
"Building";"HydraliskDen";NA;130;0
"Unit";"Hydralisk";"Larva";141;2
"Unit";"Hydralisk";"Larva";141;2
"Unit";"Hydralisk";"Larva";141;2
"Building";"CreepTumor";NA;149;0
"Building";"CreepTumorQueen";NA;149;0
"Unit";"Overlord";"Larva";149;0
"Unit";"Overlord";"Larva";149;0
"Unit";"Roach";"Larva";149;2
"Unit";"Roach";"Larva";149;2
"Unit";"Roach";"Larva";149;2
"Unit";"Hydralisk";"Larva";149;2
"Unit";"Hydralisk";"Larva";149;2
"Unit";"Overlord";"Larva";149;0
"Unit";"Overlord";"Larva";149;0
"Unit";"Overlord";"Larva";149;0
"Building";"Extractor";NA;149;0
"Unit";"Overlord";"Larva";155;0
"Building";"CreepTumor";NA;165;0
"Unit";"Roach";"Larva";165;2
"Unit";"Roach";"Larva";165;2
"Unit";"Hydralisk";"Larva";165;2
"Upgrade";"EvolveGroovedSpines";"HydraliskDen";149;0
"Unit";"Hydralisk";"Larva";170;2
"Unit";"Hydralisk";"Larva";170;2
"Unit";"Hydralisk";"Larva";170;2
"Unit";"Hydralisk";"Larva";170;2
"Building";"Extractor";NA;170;0
"Unit";"Roach";"Larva";170;2
"Upgrade";"ZergMissileWeaponsLevel2";"EvolutionChamber";134;0
"Unit";"Roach";"Larva";174;2
"Unit";"Hydralisk";"Larva";177;2
"Unit";"Hydralisk";"Larva";180;2
"Unit";"Hydralisk";"Larva";180;2
"Unit";"Hydralisk";"Larva";180;2
"Unit";"Hydralisk";"Larva";188;2
"Unit";"Hydralisk";"Larva";188;2
"Unit";"Overlord";"Larva";192;0
"Unit";"Hydralisk";"Larva";192;2
"Unit";"Hydralisk";"Larva";192;2
"Unit";"Overlord";"Larva";204;0
"Unit";"Overlord";"Larva";204;0
"Unit";"Hydralisk";"Larva";200;2
"Unit";"Hydralisk";"Larva";200;2
"Unit";"Overlord";"Larva";208;0
"Unit";"Overlord";"Larva";208;0
"Unit";"Roach";"Larva";208;2
"Unit";"Roach";"Larva";208;2
"Unit";"Roach";"Larva";208;2
"Unit";"Roach";"Larva";208;2
"Unit";"Roach";"Larva";208;2
"Unit";"Roach";"Larva";208;2
"Upgrade";"ZergGroundArmorsLevel1";"EvolutionChamber";177;0
"Unit";"Hydralisk";"Larva";212;2
"Unit";"Hydralisk";"Larva";212;2
"Unit";"Hydralisk";"Larva";212;2
"Unit";"Roach";"Larva";212;2
"Unit";"Roach";"Larva";212;2
"Unit";"Roach";"Larva";212;2
"Unit";"Roach";"Larva";224;2
"Unit";"Roach";"Larva";224;2
"Unit";"Roach";"Larva";224;2
"Upgrade";"EvolveMuscularAugments";"HydraliskDen";208;0
"Unit";"Roach";"Larva";232;2
"Unit";"Roach";"Larva";232;2
"Unit";"Roach";"Larva";234;2
"Unit";"Roach";"Larva";234;2
"Unit";"Roach";"Larva";238;2
"Unit";"Hydralisk";"Larva";244;2
"Unit";"Hydralisk";"Larva";244;2
"Unit";"Hydralisk";"Larva";244;2
"Unit";"Hydralisk";"Larva";244;2
"Unit";"Hydralisk";"Larva";248;2
"Unit";"Hydralisk";"Larva";252;2
"Unit";"Hydralisk";"Larva";254;2
"Unit";"Hydralisk";"Larva";254;2
"Unit";"Hydralisk";"Larva";254;2
"Building";"Hatchery";NA;212;0
"Unit";"Hydralisk";"Larva";254;2
"Unit";"Overlord";"Larva";264;0
"Unit";"Hydralisk";"Larva";264;2
"Unit";"Hydralisk";"Larva";264;2
"Unit";"Hydralisk";"Larva";264;2
"Unit";"Overlord";"Larva";272;0
"Building";"CreepTumor";NA;276;0
"Unit";"Roach";"Larva";276;2
"Unit";"Roach";"Larva";276;2
"Unit";"Roach";"Larva";276;2
"Unit";"Roach";"Larva";276;2
"Unit";"Roach";"Larva";276;2
"Unit";"Roach";"Larva";276;2
"Unit";"Roach";"Larva";282;2
"Unit";"Roach";"Larva";282;2
"Unit";"Roach";"Larva";282;2
"Unit";"Hydralisk";"Larva";282;2
"Unit";"Roach";"Larva";282;2
"Unit";"Roach";"Larva";282;2
"Unit";"Roach";"Larva";282;2
"Unit";"Roach";"Larva";282;2
"Unit";"Roach";"Larva";294;2
"Unit";"Roach";"Larva";294;2
"Unit";"Roach";"Larva";294;2
"Unit";"Roach";"Larva";294;2
"Unit";"Roach";"Larva";294;2
"Unit";"Hydralisk";"Larva";294;2
"Unit";"Hydralisk";"Larva";294;2
"Unit";"Overlord";"Larva";312;0
"Unit";"Overlord";"Larva";312;0
"Unit";"Roach";"Larva";324;2
"Unit";"Roach";"Larva";324;2
"Unit";"Roach";"Larva";324;2
"Unit";"Roach";"Larva";324;2
"Unit";"Roach";"Larva";324;2
"Unit";"Roach";"Larva";324;2
"Unit";"Roach";"Larva";324;2
"Unit";"Roach";"Larva";324;2
"Unit";"Roach";"Larva";324;2
"Unit";"Roach";"Larva";324;2
"Unit";"Roach";"Larva";324;2
"Unit";"Roach";"Larva";324;2
"Unit";"Roach";"Larva";324;2
"Unit";"Roach";"Larva";324;2
"Unit";"Roach";"Larva";324;2
"Unit";"Roach";"Larva";324;2
"Unit";"Roach";"Larva";324;2
"Unit";"Roach";"Larva";324;2
"Unit";"Roach";"Larva";324;2
"Unit";"Roach";"Larva";324;2
"Unit";"Roach";"Larva";324;2
"Unit";"Roach";"Larva";324;2
"Unit";"Hydralisk";"Larva";354;2
"Unit";"Hydralisk";"Larva";354;2
"Unit";"Hydralisk";"Larva";368;2
"Unit";"Hydralisk";"Larva";368;2
"Unit";"Hydralisk";"Larva";368;2
