"type";"unit_name";"on_building";"total_supply";"supply"
"Unit";"Overlord";"Larva";13;0
"Building";"Extractor";NA;18;0
"Unit";"Overlord";"Larva";21;0
"Building";"SpawningPool";NA;19;0
"Building";"Hatchery";NA;17;0
"Unit";"Zergling";"Larva";22;1
"Unit";"Zergling";"Larva";22;1
"Unit";"Zergling";"Larva";22;1
"Unit";"Zergling";"Larva";22;1
"Unit";"Zergling";"Larva";22;1
"Unit";"Zergling";"Larva";22;1
"Unit";"Queen";"Hatchery";22;2
"Unit";"Queen";"Hatchery";22;2
"Building";"BanelingNest";NA;31;0
"Unit";"Overlord";"Larva";40;0
"Unit";"Zergling";"Larva";40;1
"Unit";"Zergling";"Larva";40;1
"Unit";"Zergling";"Larva";40;1
"Unit";"Zergling";"Larva";40;1
"Unit";"Zergling";"Larva";40;1
"Unit";"Zergling";"Larva";40;1
"Unit";"Zergling";"Larva";40;1
"Unit";"Zergling";"Larva";40;1
"Unit";"Zergling";"Larva";42;1
"Unit";"Zergling";"Larva";42;1
"Unit";"Zergling";"Larva";44;1
"Unit";"Zergling";"Larva";44;1
"Unit";"Zergling";"Larva";44;1
"Unit";"Zergling";"Larva";44;1
"Unit";"Zergling";"Larva";44;1
"Unit";"Zergling";"Larva";44;1
"Unit";"Zergling";"Larva";44;1
"Unit";"Zergling";"Larva";44;1
"Unit";"Baneling";"Zergling";44;0
"Unit";"Baneling";"Zergling";48;0
"Unit";"Baneling";"Zergling";48;0
"Unit";"Zergling";"Larva";44;1
"Unit";"Zergling";"Larva";44;1
"Unit";"Baneling";"Zergling";48;0
"Unit";"Baneling";"Zergling";48;0
"Unit";"Baneling";"Zergling";48;0
"Unit";"Baneling";"Zergling";48;0
"Unit";"Zergling";"Larva";48;1
"Unit";"Zergling";"Larva";48;1
"Unit";"Zergling";"Larva";48;1
"Unit";"Zergling";"Larva";48;1
"Unit";"Zergling";"Larva";58;1
"Unit";"Zergling";"Larva";58;1
"Unit";"Zergling";"Larva";60;1
"Unit";"Zergling";"Larva";60;1
"Building";"Hatchery";NA;39;0
"Unit";"Zergling";"Larva";62;1
"Unit";"Zergling";"Larva";62;1
"Unit";"Zergling";"Larva";64;1
"Unit";"Zergling";"Larva";64;1
"Unit";"Zergling";"Larva";64;1
"Unit";"Zergling";"Larva";64;1
"Unit";"Zergling";"Larva";66;1
"Unit";"Zergling";"Larva";66;1
"Unit";"Zergling";"Larva";66;1
"Unit";"Zergling";"Larva";66;1
"Unit";"Overlord";"Larva";68;0
"Unit";"Overlord";"Larva";68;0
"Unit";"Baneling";"Zergling";68;0
"Unit";"Zergling";"Larva";68;1
"Unit";"Zergling";"Larva";68;1
"Unit";"Baneling";"Zergling";70;0
"Unit";"Zergling";"Larva";68;1
"Unit";"Zergling";"Larva";68;1
"Unit";"Zergling";"Larva";70;1
"Unit";"Zergling";"Larva";70;1
"Unit";"Zergling";"Larva";78;1
"Unit";"Zergling";"Larva";78;1
"Unit";"Zergling";"Larva";82;1
"Unit";"Zergling";"Larva";82;1
"Unit";"Zergling";"Larva";82;1
"Unit";"Zergling";"Larva";82;1
"Unit";"Zergling";"Larva";84;1
"Unit";"Zergling";"Larva";84;1
"Unit";"Zergling";"Larva";86;1
"Unit";"Zergling";"Larva";86;1
"Unit";"Zergling";"Larva";86;1
"Unit";"Zergling";"Larva";86;1
"Unit";"Zergling";"Larva";86;1
"Unit";"Zergling";"Larva";86;1
"Unit";"Zergling";"Larva";86;1
"Unit";"Zergling";"Larva";86;1
"Unit";"Zergling";"Larva";86;1
"Unit";"Zergling";"Larva";86;1
"Unit";"Zergling";"Larva";86;1
"Unit";"Zergling";"Larva";86;1
"Unit";"Zergling";"Larva";86;1
"Unit";"Zergling";"Larva";86;1
"Unit";"Baneling";"Zergling";90;0
"Unit";"Zergling";"Larva";88;1
"Unit";"Zergling";"Larva";88;1
"Unit";"Zergling";"Larva";92;1
"Unit";"Zergling";"Larva";92;1
"Unit";"Zergling";"Larva";92;1
"Unit";"Zergling";"Larva";92;1
"Unit";"Zergling";"Larva";104;1
"Unit";"Zergling";"Larva";104;1
"Unit";"Zergling";"Larva";104;1
"Unit";"Zergling";"Larva";104;1
"Unit";"Zergling";"Larva";107;1
"Unit";"Zergling";"Larva";107;1
"Unit";"Baneling";"Zergling";109;0
"Unit";"Baneling";"Zergling";109;0
"Unit";"Baneling";"Zergling";109;0
"Unit";"Baneling";"Zergling";109;0
"Unit";"Zergling";"Larva";109;1
"Unit";"Zergling";"Larva";109;1
"Unit";"Zergling";"Larva";109;1
"Unit";"Zergling";"Larva";109;1
"Unit";"Baneling";"Zergling";113;0
"Unit";"Baneling";"Zergling";113;0
"Unit";"Zergling";"Larva";119;1
"Unit";"Zergling";"Larva";119;1
"Unit";"Zergling";"Larva";119;1
"Unit";"Zergling";"Larva";119;1
"Unit";"Zergling";"Larva";123;1
"Unit";"Zergling";"Larva";123;1
"Unit";"Zergling";"Larva";123;1
"Unit";"Zergling";"Larva";123;1
"Unit";"Zergling";"Larva";123;1
"Unit";"Zergling";"Larva";123;1
"Unit";"Zergling";"Larva";123;1
"Unit";"Zergling";"Larva";123;1
"Unit";"Zergling";"Larva";123;1
"Unit";"Zergling";"Larva";123;1
"Unit";"Zergling";"Larva";123;1
"Unit";"Zergling";"Larva";123;1
"Unit";"Zergling";"Larva";123;1
"Unit";"Zergling";"Larva";123;1
"Unit";"Zergling";"Larva";123;1
"Unit";"Zergling";"Larva";123;1
"Unit";"Baneling";"Zergling";127;0
"Unit";"Baneling";"Zergling";127;0
"Unit";"Baneling";"Zergling";127;0
"Unit";"Baneling";"Zergling";127;0
"Unit";"Zergling";"Larva";127;1
"Unit";"Zergling";"Larva";127;1
"Unit";"Zergling";"Larva";143;1
"Unit";"Zergling";"Larva";143;1
"Unit";"Zergling";"Larva";143;1
"Unit";"Zergling";"Larva";143;1
"Unit";"Zergling";"Larva";143;1
"Unit";"Zergling";"Larva";143;1
"Unit";"Baneling";"Zergling";145;0
"Unit";"Zergling";"Larva";145;1
"Unit";"Zergling";"Larva";145;1
"Unit";"Zergling";"Larva";145;1
"Unit";"Zergling";"Larva";145;1
"Unit";"Zergling";"Larva";147;1
"Unit";"Zergling";"Larva";147;1
