"type";"unit_name";"on_building";"total_supply";"supply"
"Unit";"Overlord";"Larva";13;0
"Building";"Extractor";NA;21;0
"Building";"SpawningPool";NA;19;0
"Building";"Hatchery";NA;16;0
"Unit";"Zergling";"Larva";23;1
"Unit";"Zergling";"Larva";23;1
"Unit";"Zergling";"Larva";23;1
"Unit";"Zergling";"Larva";23;1
"Unit";"Queen";"Hatchery";23;2
"Unit";"Queen";"Hatchery";23;2
"Unit";"Overlord";"Larva";27;0
"Building";"RoachWarren";NA;23;0
"Unit";"Roach";"Larva";34;2
"Unit";"Roach";"Larva";34;2
"Unit";"Roach";"Larva";34;2
"Unit";"Roach";"Larva";34;2
"Unit";"Overlord";"Larva";34;0
"Unit";"Overlord";"Larva";42;0
"Unit";"Roach";"Larva";46;2
"Building";"EvolutionChamber";NA;48;0
"Unit";"Overlord";"Larva";50;0
"Unit";"Roach";"Larva";50;2
"Unit";"Roach";"Larva";50;2
"Unit";"Roach";"Larva";50;2
"Unit";"Overlord";"Larva";50;0
"Building";"Extractor";NA;50;0
"Building";"Extractor";NA;50;0
"Unit";"Overlord";"Larva";63;0
"Building";"Extractor";NA;70;0
"Unit";"Overlord";"Larva";77;0
"Unit";"Overlord";"Larva";77;0
"Unit";"Overlord";"Larva";77;0
"Unit";"Roach";"Larva";77;2
"Unit";"Roach";"Larva";77;2
"Unit";"Roach";"Larva";77;2
"Upgrade";"GlialReconstitution";"RoachWarren";70;0
"Unit";"Overlord";"Larva";77;0
"Unit";"Overlord";"Larva";77;0
"Unit";"Roach";"Larva";77;2
"Unit";"Roach";"Larva";77;2
"Unit";"Roach";"Larva";77;2
"Unit";"Roach";"Larva";77;2
"Unit";"Roach";"Larva";83;2
"Unit";"Roach";"Larva";83;2
"Building";"HydraliskDen";NA;83;0
"Unit";"Roach";"Larva";83;2
"Unit";"Roach";"Larva";83;2
"Unit";"Roach";"Larva";83;2
"Unit";"Roach";"Larva";83;2
"Unit";"Roach";"Larva";83;2
"Unit";"Roach";"Larva";83;2
"Unit";"Roach";"Larva";95;2
"Unit";"Roach";"Larva";95;2
"Unit";"Roach";"Larva";95;2
"Unit";"Roach";"Larva";107;2
"Upgrade";"ZergMissileWeaponsLevel1";"EvolutionChamber";77;0
"Unit";"Overlord";"Larva";115;0
"Unit";"Overlord";"Larva";115;0
"Unit";"Hydralisk";"Larva";115;2
"Unit";"Hydralisk";"Larva";115;2
"Unit";"Hydralisk";"Larva";115;2
"Unit";"Hydralisk";"Larva";115;2
"Unit";"Hydralisk";"Larva";115;2
"Unit";"Hydralisk";"Larva";115;2
"Unit";"Hydralisk";"Larva";115;2
"Unit";"Hydralisk";"Larva";115;2
"Unit";"Hydralisk";"Larva";115;2
"Unit";"Hydralisk";"Larva";115;2
"Unit";"Overlord";"Larva";131;0
"Unit";"Overlord";"Larva";131;0
"Unit";"Overlord";"Larva";131;0
"Unit";"Hydralisk";"Larva";129;2
"Unit";"Hydralisk";"Larva";131;2
"Upgrade";"EvolveMuscularAugments";"HydraliskDen";115;0
"Building";"Hatchery";NA;115;0
"Unit";"Hydralisk";"Larva";139;2
"Unit";"Hydralisk";"Larva";139;2
"Unit";"Hydralisk";"Larva";139;2
"Unit";"Hydralisk";"Larva";139;2
"Unit";"Hydralisk";"Larva";139;2
"Unit";"Hydralisk";"Larva";139;2
"Unit";"Hydralisk";"Larva";144;2
"Unit";"Hydralisk";"Larva";144;2
"Unit";"Hydralisk";"Larva";144;2
"Unit";"Overlord";"Larva";156;0
"Unit";"Overlord";"Larva";156;0
"Unit";"Hydralisk";"Larva";156;2
"Unit";"Hydralisk";"Larva";156;2
"Unit";"Hydralisk";"Larva";156;2
"Unit";"Hydralisk";"Larva";156;2
"Unit";"Overlord";"Larva";162;0
"Unit";"Overlord";"Larva";162;0
"Unit";"Overlord";"Larva";162;0
"Upgrade";"ZergMissileWeaponsLevel2";"EvolutionChamber";131;0
"Unit";"Overlord";"Larva";170;0
"Unit";"Overlord";"Larva";170;0
"Unit";"Hydralisk";"Larva";170;2
"Unit";"Hydralisk";"Larva";170;2
"Unit";"Hydralisk";"Larva";170;2
"Unit";"Hydralisk";"Larva";170;2
"Unit";"Hydralisk";"Larva";170;2
"Upgrade";"EvolveGroovedSpines";"HydraliskDen";162;0
"Unit";"Hydralisk";"Larva";170;2
"Unit";"Hydralisk";"Larva";178;2
"Unit";"Hydralisk";"Larva";178;2
"Unit";"Hydralisk";"Larva";178;2
"Unit";"Hydralisk";"Larva";178;2
"Unit";"Hydralisk";"Larva";178;2
"Unit";"Hydralisk";"Larva";182;2
"Unit";"Hydralisk";"Larva";182;2
"Unit";"Hydralisk";"Larva";182;2
"Building";"LurkerDenMP";NA;162;0
"Building";"Extractor";NA;182;0
"Building";"Extractor";NA;182;0
"Unit";"Roach";"Larva";202;2
"Unit";"Roach";"Larva";202;2
"Unit";"Roach";"Larva";202;2
"Unit";"Roach";"Larva";202;2
"Unit";"Roach";"Larva";202;2
"Unit";"Roach";"Larva";202;2
"Unit";"Roach";"Larva";202;2
"Unit";"Roach";"Larva";202;2
"Unit";"Roach";"Larva";202;2
"Unit";"Roach";"Larva";202;2
"Unit";"Roach";"Larva";202;2
"Unit";"Roach";"Larva";202;2
"Unit";"Roach";"Larva";226;2
"Unit";"Roach";"Larva";226;2
"Unit";"Roach";"Larva";226;2
"Unit";"Roach";"Larva";226;2
"Unit";"Roach";"Larva";226;2
"Unit";"Roach";"Larva";226;2
"Unit";"Roach";"Larva";226;2
"Unit";"Roach";"Larva";226;2
"Unit";"Roach";"Larva";226;2
"Unit";"Overlord";"Larva";226;0
"Unit";"Roach";"Larva";244;2
"Unit";"Roach";"Larva";244;2
"Unit";"Roach";"Larva";244;2
"Unit";"Roach";"Larva";250;2
"Unit";"Roach";"Larva";250;2
"Unit";"Roach";"Larva";250;2
"Unit";"Roach";"Larva";250;2
"Unit";"Roach";"Larva";250;2
"Unit";"Roach";"Larva";250;2
"Unit";"Roach";"Larva";250;2
"Unit";"Roach";"Larva";250;2
"Unit";"Roach";"Larva";250;2
"Unit";"Roach";"Larva";268;2
"Unit";"Roach";"Larva";268;2
"Unit";"Roach";"Larva";268;2
"Unit";"Roach";"Larva";268;2
"Unit";"Roach";"Larva";268;2
"Unit";"Roach";"Larva";268;2
"Unit";"Roach";"Larva";268;2
"Unit";"Roach";"Larva";268;2
"Unit";"Roach";"Larva";268;2
"Unit";"Roach";"Larva";268;2
"Unit";"Roach";"Larva";268;2
"Unit";"Roach";"Larva";290;2
"Unit";"Roach";"Larva";290;2
"Unit";"Roach";"Larva";290;2
"Unit";"Roach";"Larva";290;2
"Unit";"Roach";"Larva";290;2
"Unit";"Roach";"Larva";290;2
"Unit";"Roach";"Larva";290;2
"Unit";"Roach";"Larva";290;2
"Unit";"Roach";"Larva";290;2
"Unit";"Roach";"Larva";290;2
"Unit";"Roach";"Larva";290;2
"Unit";"Roach";"Larva";312;2
"Unit";"Roach";"Larva";312;2
"Unit";"Roach";"Larva";312;2
"Unit";"Roach";"Larva";312;2
"Unit";"Roach";"Larva";312;2
"Unit";"Roach";"Larva";312;2
"Unit";"Roach";"Larva";312;2
"Unit";"Roach";"Larva";312;2
"Unit";"Roach";"Larva";312;2
"Unit";"Roach";"Larva";312;2
"Unit";"Roach";"Larva";312;2
"Unit";"Roach";"Larva";312;2
"Building";"InfestationPit";NA;330;0
"Unit";"Roach";"Larva";336;2
"Unit";"Roach";"Larva";336;2
"Unit";"Roach";"Larva";336;2
"Unit";"Roach";"Larva";336;2
"Unit";"Roach";"Larva";336;2
"Unit";"Roach";"Larva";336;2
"Unit";"Roach";"Larva";336;2
"Unit";"Roach";"Larva";350;2
"Unit";"Roach";"Larva";350;2
"Unit";"Roach";"Larva";350;2
"Unit";"Roach";"Larva";350;2
"Unit";"Roach";"Larva";350;2
"Unit";"Roach";"Larva";350;2
"Unit";"Roach";"Larva";350;2
"Unit";"Roach";"Larva";350;2
"Unit";"Roach";"Larva";350;2
"Unit";"Roach";"Larva";350;2
"Unit";"Roach";"Larva";350;2
"Unit";"Roach";"Larva";350;2
"Unit";"Roach";"Larva";350;2
"Unit";"Roach";"Larva";350;2
"Unit";"Roach";"Larva";350;2
"Unit";"Roach";"Larva";350;2
"Unit";"Hydralisk";"Larva";350;2
"Unit";"Hydralisk";"Larva";350;2
"Unit";"Hydralisk";"Larva";350;2
"Unit";"Roach";"Larva";388;2
"Unit";"Roach";"Larva";388;2
"Unit";"Roach";"Larva";388;2
"Unit";"Roach";"Larva";388;2
"Unit";"Roach";"Larva";388;2
"Unit";"Roach";"Larva";388;2
"Unit";"Roach";"Larva";388;2
"Unit";"Roach";"Larva";388;2
"Unit";"Roach";"Larva";388;2
"Unit";"Roach";"Larva";388;2
"Unit";"Roach";"Larva";388;2
"Unit";"Roach";"Larva";388;2
"Unit";"Roach";"Larva";388;2
"Unit";"Roach";"Larva";388;2
"Unit";"Roach";"Larva";388;2
"Unit";"Roach";"Larva";388;2
"Unit";"Hydralisk";"Larva";420;2
"Unit";"Hydralisk";"Larva";420;2
"Unit";"Hydralisk";"Larva";420;2
"Unit";"Hydralisk";"Larva";420;2
"Unit";"Hydralisk";"Larva";420;2
"Unit";"Hydralisk";"Larva";420;2
"Unit";"Hydralisk";"Larva";420;2
"Unit";"Hydralisk";"Larva";420;2
"Unit";"Hydralisk";"Larva";420;2
"Unit";"Hydralisk";"Larva";420;2
"Unit";"Hydralisk";"Larva";420;2
"Unit";"Hydralisk";"Larva";420;2
"Unit";"Hydralisk";"Larva";420;2
"Unit";"Hydralisk";"Larva";420;2
"Unit";"Hydralisk";"Larva";420;2
"Unit";"Hydralisk";"Larva";420;2
"Unit";"Overlord";"Larva";444;0
"Unit";"Hydralisk";"Larva";452;2
"Unit";"Hydralisk";"Larva";452;2
"Unit";"Hydralisk";"Larva";452;2
"Unit";"Hydralisk";"Larva";452;2
"Building";"Hatchery";NA;420;0
"Building";"Hatchery";NA;420;0
"Unit";"Hydralisk";"Larva";460;2
"Unit";"Hydralisk";"Larva";460;2
"Unit";"Hydralisk";"Larva";460;2
"Unit";"Hydralisk";"Larva";460;2
"Unit";"Hydralisk";"Larva";468;2
"Unit";"Hydralisk";"Larva";468;2
"Unit";"Hydralisk";"Larva";468;2
"Unit";"Hydralisk";"Larva";468;2
"Unit";"Hydralisk";"Larva";468;2
"Unit";"Hydralisk";"Larva";468;2
"Unit";"Hydralisk";"Larva";468;2
"Unit";"Hydralisk";"Larva";468;2
"Building";"Extractor";NA;484;0
