"type";"unit_name";"on_building";"total_supply";"supply"
"Building";"Extractor";NA;13;0
"Unit";"Overlord";"Larva";15;0
"Building";"SpawningPool";NA;13;0
"Unit";"Zergling";"Larva";16;1
"Unit";"Zergling";"Larva";16;1
"Unit";"Zergling";"Larva";16;1
"Unit";"Zergling";"Larva";16;1
"Unit";"Zergling";"Larva";16;1
"Unit";"Zergling";"Larva";16;1
"Unit";"Zergling";"Larva";16;1
"Unit";"Zergling";"Larva";16;1
"Unit";"Zergling";"Larva";22;1
"Unit";"Zergling";"Larva";22;1
"Unit";"Zergling";"Larva";24;1
"Unit";"Zergling";"Larva";24;1
"Building";"BanelingNest";NA;22;0
"Unit";"Overlord";"Larva";26;0
"Unit";"Queen";"Hatchery";26;2
"Unit";"Baneling";"Zergling";28;0
"Unit";"Baneling";"Zergling";28;0
"Unit";"Zergling";"Larva";28;1
"Unit";"Zergling";"Larva";28;1
"Unit";"Baneling";"Zergling";28;0
"Unit";"Zergling";"Larva";28;1
"Unit";"Zergling";"Larva";28;1
"Unit";"Baneling";"Zergling";28;0
"Unit";"Zergling";"Larva";30;1
"Unit";"Zergling";"Larva";30;1
"Unit";"Zergling";"Larva";34;1
"Unit";"Zergling";"Larva";34;1
"Unit";"Zergling";"Larva";36;1
"Unit";"Zergling";"Larva";36;1
"Unit";"Zergling";"Larva";38;1
"Unit";"Zergling";"Larva";38;1
"Unit";"Zergling";"Larva";38;1
"Unit";"Zergling";"Larva";38;1
"Unit";"Zergling";"Larva";38;1
"Unit";"Zergling";"Larva";38;1
"Unit";"Baneling";"Zergling";40;0
"Unit";"Baneling";"Zergling";40;0
"Unit";"Zergling";"Larva";40;1
"Unit";"Zergling";"Larva";40;1
"Unit";"Zergling";"Larva";40;1
"Unit";"Zergling";"Larva";40;1
"Unit";"Zergling";"Larva";46;1
"Unit";"Zergling";"Larva";46;1
"Unit";"Baneling";"Zergling";48;0
"Unit";"Zergling";"Larva";50;1
"Unit";"Zergling";"Larva";50;1
"Unit";"Zergling";"Larva";52;1
"Unit";"Zergling";"Larva";52;1
"Unit";"Zergling";"Larva";52;1
"Unit";"Zergling";"Larva";52;1
"Unit";"Zergling";"Larva";52;1
"Unit";"Zergling";"Larva";52;1
"Unit";"Baneling";"Zergling";60;0
"Unit";"Baneling";"Zergling";60;0
"Unit";"Baneling";"Zergling";60;0
"Unit";"Baneling";"Zergling";64;0
"Unit";"Baneling";"Zergling";64;0
"Unit";"Baneling";"Zergling";64;0
"Building";"Hatchery";NA;54;0
"Unit";"Queen";"Hatchery";64;2
"Unit";"Overlord";"Larva";77;0
"Unit";"Baneling";"Zergling";77;0
"Unit";"Baneling";"Zergling";77;0
"Unit";"Baneling";"Zergling";77;0
"Building";"SpineCrawler";NA;69;0
"Unit";"Overlord";"Larva";77;0
"Unit";"Queen";"Hatchery";77;2
"Unit";"Zergling";"Larva";77;1
"Unit";"Zergling";"Larva";77;1
"Unit";"Zergling";"Larva";77;1
"Unit";"Zergling";"Larva";77;1
"Unit";"Zergling";"Larva";77;1
"Unit";"Zergling";"Larva";77;1
"Unit";"Zergling";"Larva";77;1
"Unit";"Zergling";"Larva";77;1
"Unit";"Zergling";"Larva";77;1
"Unit";"Zergling";"Larva";77;1
"Unit";"Zergling";"Larva";77;1
"Unit";"Zergling";"Larva";77;1
"Unit";"Zergling";"Larva";79;1
"Unit";"Zergling";"Larva";79;1
"Unit";"Zergling";"Larva";79;1
"Unit";"Zergling";"Larva";79;1
"Unit";"Zergling";"Larva";79;1
"Unit";"Zergling";"Larva";79;1
"Unit";"Zergling";"Larva";79;1
"Unit";"Zergling";"Larva";79;1
"Unit";"Zergling";"Larva";79;1
"Unit";"Zergling";"Larva";79;1
"Building";"EvolutionChamber";NA;79;0
"Unit";"Overlord";"Larva";91;0
"Unit";"Zergling";"Larva";91;1
"Unit";"Zergling";"Larva";91;1
"Unit";"Zergling";"Larva";91;1
"Unit";"Zergling";"Larva";91;1
"Unit";"Baneling";"Zergling";101;0
"Unit";"Baneling";"Zergling";101;0
"Unit";"Baneling";"Zergling";101;0
"Unit";"Baneling";"Zergling";101;0
"Unit";"Baneling";"Zergling";101;0
"Unit";"Baneling";"Zergling";101;0
"Unit";"Baneling";"Zergling";101;0
"Unit";"Baneling";"Zergling";101;0
"Unit";"Baneling";"Zergling";101;0
"Unit";"Zergling";"Larva";105;1
"Unit";"Zergling";"Larva";105;1
"Unit";"Zergling";"Larva";105;1
"Unit";"Zergling";"Larva";105;1
"Unit";"Zergling";"Larva";105;1
"Unit";"Zergling";"Larva";105;1
"Unit";"Zergling";"Larva";105;1
"Unit";"Zergling";"Larva";105;1
"Unit";"Zergling";"Larva";113;1
"Unit";"Zergling";"Larva";113;1
"Unit";"Zergling";"Larva";113;1
"Unit";"Zergling";"Larva";113;1
"Unit";"Zergling";"Larva";113;1
"Unit";"Zergling";"Larva";113;1
"Unit";"Zergling";"Larva";113;1
"Unit";"Zergling";"Larva";113;1
"Unit";"Zergling";"Larva";113;1
"Unit";"Zergling";"Larva";113;1
"Unit";"Zergling";"Larva";113;1
"Unit";"Zergling";"Larva";113;1
"Unit";"Zergling";"Larva";113;1
"Unit";"Zergling";"Larva";113;1
"Unit";"Zergling";"Larva";113;1
"Unit";"Zergling";"Larva";113;1
"Unit";"Zergling";"Larva";113;1
"Unit";"Zergling";"Larva";113;1
"Unit";"Zergling";"Larva";113;1
"Unit";"Zergling";"Larva";113;1
"Unit";"Zergling";"Larva";113;1
"Unit";"Zergling";"Larva";113;1
"Unit";"Zergling";"Larva";113;1
"Unit";"Zergling";"Larva";113;1
"Unit";"Baneling";"Zergling";129;0
"Unit";"Baneling";"Zergling";129;0
"Unit";"Baneling";"Zergling";129;0
"Unit";"Baneling";"Zergling";129;0
"Unit";"Baneling";"Zergling";129;0
"Unit";"Zergling";"Larva";137;1
"Unit";"Zergling";"Larva";137;1
"Unit";"Zergling";"Larva";137;1
"Unit";"Zergling";"Larva";137;1
"Unit";"Zergling";"Larva";137;1
"Unit";"Zergling";"Larva";137;1
"Unit";"Zergling";"Larva";137;1
"Unit";"Zergling";"Larva";137;1
"Unit";"Zergling";"Larva";143;1
"Unit";"Zergling";"Larva";143;1
"Unit";"Zergling";"Larva";143;1
"Unit";"Zergling";"Larva";143;1
"Unit";"Zergling";"Larva";143;1
"Unit";"Zergling";"Larva";143;1
"Unit";"Zergling";"Larva";143;1
"Unit";"Zergling";"Larva";143;1
"Unit";"Zergling";"Larva";143;1
"Unit";"Zergling";"Larva";143;1
"Unit";"Zergling";"Larva";143;1
"Unit";"Zergling";"Larva";143;1
"Unit";"Zergling";"Larva";143;1
"Unit";"Zergling";"Larva";143;1
"Unit";"Zergling";"Larva";143;1
"Unit";"Zergling";"Larva";143;1
"Unit";"Zergling";"Larva";161;1
"Unit";"Zergling";"Larva";161;1
"Unit";"Zergling";"Larva";161;1
"Unit";"Zergling";"Larva";161;1
"Unit";"Zergling";"Larva";161;1
"Unit";"Zergling";"Larva";161;1
"Unit";"Zergling";"Larva";161;1
"Unit";"Zergling";"Larva";161;1
"Unit";"Zergling";"Larva";161;1
"Unit";"Zergling";"Larva";161;1
"Unit";"Zergling";"Larva";161;1
"Unit";"Zergling";"Larva";161;1
"Unit";"Zergling";"Larva";161;1
"Unit";"Zergling";"Larva";161;1
"Unit";"Zergling";"Larva";161;1
"Unit";"Zergling";"Larva";161;1
"Unit";"Zergling";"Larva";161;1
"Unit";"Zergling";"Larva";161;1
"Unit";"Zergling";"Larva";161;1
"Unit";"Zergling";"Larva";161;1
"Unit";"Baneling";"Zergling";167;0
"Unit";"Zergling";"Larva";167;1
"Unit";"Zergling";"Larva";167;1
"Unit";"Zergling";"Larva";167;1
"Unit";"Zergling";"Larva";167;1
"Unit";"Zergling";"Larva";181;1
"Unit";"Zergling";"Larva";181;1
"Unit";"Baneling";"Zergling";181;0
"Unit";"Baneling";"Zergling";181;0
"Unit";"Baneling";"Zergling";181;0
"Unit";"Baneling";"Zergling";181;0
"Unit";"Baneling";"Zergling";181;0
"Unit";"Baneling";"Zergling";181;0
"Unit";"Zergling";"Larva";181;1
"Unit";"Zergling";"Larva";181;1
"Unit";"Zergling";"Larva";181;1
"Unit";"Zergling";"Larva";181;1
"Unit";"Zergling";"Larva";181;1
"Unit";"Zergling";"Larva";181;1
"Unit";"Zergling";"Larva";181;1
"Unit";"Zergling";"Larva";181;1
"Unit";"Baneling";"Zergling";181;0
"Unit";"Baneling";"Zergling";181;0
"Unit";"Zergling";"Larva";185;1
"Unit";"Zergling";"Larva";185;1
"Unit";"Zergling";"Larva";187;1
"Unit";"Zergling";"Larva";187;1
"Unit";"Baneling";"Zergling";195;0
"Unit";"Baneling";"Zergling";195;0
"Unit";"Zergling";"Larva";195;1
"Unit";"Zergling";"Larva";195;1
"Unit";"Zergling";"Larva";195;1
"Unit";"Zergling";"Larva";195;1
"Unit";"Zergling";"Larva";195;1
"Unit";"Zergling";"Larva";195;1
"Unit";"Zergling";"Larva";195;1
"Unit";"Zergling";"Larva";195;1
"Unit";"Baneling";"Zergling";207;0
"Unit";"Baneling";"Zergling";207;0
"Unit";"Baneling";"Zergling";207;0
"Unit";"Zergling";"Larva";207;1
"Unit";"Zergling";"Larva";207;1
"Unit";"Zergling";"Larva";207;1
"Unit";"Zergling";"Larva";207;1
"Unit";"Zergling";"Larva";207;1
"Unit";"Zergling";"Larva";207;1
"Unit";"Zergling";"Larva";207;1
"Unit";"Zergling";"Larva";207;1
"Unit";"Zergling";"Larva";207;1
"Unit";"Zergling";"Larva";207;1
"Unit";"Zergling";"Larva";207;1
"Unit";"Zergling";"Larva";207;1
"Unit";"Zergling";"Larva";207;1
"Unit";"Zergling";"Larva";207;1
"Unit";"Zergling";"Larva";207;1
"Unit";"Zergling";"Larva";207;1
"Unit";"Zergling";"Larva";207;1
"Unit";"Zergling";"Larva";207;1
"Unit";"Zergling";"Larva";207;1
"Unit";"Zergling";"Larva";207;1
"Unit";"Zergling";"Larva";207;1
"Unit";"Zergling";"Larva";207;1
"Unit";"Zergling";"Larva";207;1
"Unit";"Zergling";"Larva";207;1
"Unit";"Zergling";"Larva";207;1
"Unit";"Zergling";"Larva";207;1
"Unit";"Zergling";"Larva";207;1
"Unit";"Zergling";"Larva";207;1
"Unit";"Baneling";"Zergling";227;0
"Unit";"Baneling";"Zergling";227;0
"Unit";"Baneling";"Zergling";227;0
"Unit";"Zergling";"Larva";227;1
"Unit";"Zergling";"Larva";227;1
"Unit";"Zergling";"Larva";227;1
"Unit";"Zergling";"Larva";227;1
"Unit";"Zergling";"Larva";227;1
"Unit";"Zergling";"Larva";227;1
"Unit";"Zergling";"Larva";227;1
"Unit";"Zergling";"Larva";227;1
"Unit";"Baneling";"Zergling";235;0
"Unit";"Zergling";"Larva";227;1
"Unit";"Zergling";"Larva";227;1
"Unit";"Zergling";"Larva";235;1
"Unit";"Zergling";"Larva";235;1
"Unit";"Zergling";"Larva";235;1
"Unit";"Zergling";"Larva";235;1
"Unit";"Zergling";"Larva";235;1
"Unit";"Zergling";"Larva";235;1
"Unit";"Zergling";"Larva";235;1
"Unit";"Zergling";"Larva";235;1
