"type";"unit_name";"on_building";"total_supply";"supply"
"Unit";"Overlord";"Larva";12;0
"Building";"Extractor";NA;18;0
"Building";"SpawningPool";NA;19;0
"Unit";"Overlord";"Larva";21;0
"Building";"Hatchery";NA;17;0
"Unit";"Zergling";"Larva";22;1
"Unit";"Zergling";"Larva";22;1
"Unit";"Zergling";"Larva";22;1
"Unit";"Zergling";"Larva";22;1
"Unit";"Zergling";"Larva";22;1
"Unit";"Zergling";"Larva";22;1
"Unit";"Queen";"Hatchery";22;2
"Unit";"Queen";"Hatchery";22;2
"Unit";"Overlord";"Larva";36;0
"Unit";"Zergling";"Larva";40;1
"Unit";"Zergling";"Larva";40;1
"Unit";"Zergling";"Larva";40;1
"Unit";"Zergling";"Larva";40;1
"Unit";"Zergling";"Larva";40;1
"Unit";"Zergling";"Larva";40;1
"Unit";"Zergling";"Larva";40;1
"Unit";"Zergling";"Larva";40;1
"Building";"BanelingNest";NA;36;0
"Unit";"Zergling";"Larva";40;1
"Unit";"Zergling";"Larva";40;1
"Unit";"Zergling";"Larva";40;1
"Unit";"Zergling";"Larva";40;1
"Unit";"Zergling";"Larva";40;1
"Unit";"Zergling";"Larva";40;1
"Unit";"Zergling";"Larva";48;1
"Unit";"Zergling";"Larva";48;1
"Unit";"Zergling";"Larva";48;1
"Unit";"Zergling";"Larva";48;1
"Unit";"Zergling";"Larva";48;1
"Unit";"Zergling";"Larva";48;1
"Unit";"Zergling";"Larva";48;1
"Unit";"Zergling";"Larva";48;1
"Unit";"Baneling";"Zergling";48;0
"Unit";"Baneling";"Zergling";48;0
"Unit";"Baneling";"Zergling";48;0
"Building";"Hatchery";NA;32;0
"Unit";"Zergling";"Larva";54;1
"Unit";"Zergling";"Larva";54;1
"Unit";"Zergling";"Larva";54;1
"Unit";"Zergling";"Larva";54;1
"Unit";"Zergling";"Larva";54;1
"Unit";"Zergling";"Larva";54;1
"Unit";"Baneling";"Zergling";54;0
"Unit";"Zergling";"Larva";56;1
"Unit";"Zergling";"Larva";56;1
"Unit";"Zergling";"Larva";62;1
"Unit";"Zergling";"Larva";62;1
"Unit";"Zergling";"Larva";62;1
"Unit";"Zergling";"Larva";62;1
"Unit";"Zergling";"Larva";62;1
"Unit";"Zergling";"Larva";62;1
"Unit";"Zergling";"Larva";62;1
"Unit";"Zergling";"Larva";62;1
"Unit";"Zergling";"Larva";62;1
"Unit";"Zergling";"Larva";62;1
"Unit";"Baneling";"Zergling";68;0
"Unit";"Baneling";"Zergling";85;0
"Unit";"Baneling";"Zergling";85;0
"Unit";"Baneling";"Zergling";85;0
"Unit";"Queen";"Hatchery";80;2
"Unit";"Overlord";"Larva";85;0
"Building";"CreepTumorQueen";NA;85;0
"Building";"CreepTumorQueen";NA;85;0
"Unit";"Overlord";"Larva";87;0
"Unit";"Overlord";"Larva";87;0
"Building";"CreepTumor";NA;96;0
"Building";"CreepTumor";NA;96;0
"Unit";"Zergling";"Larva";94;1
"Unit";"Zergling";"Larva";94;1
"Unit";"Zergling";"Larva";94;1
"Unit";"Zergling";"Larva";94;1
"Unit";"Zergling";"Larva";94;1
"Unit";"Zergling";"Larva";94;1
"Building";"EvolutionChamber";NA;94;0
"Building";"Extractor";NA;96;0
"Building";"Extractor";NA;96;0
"Unit";"Baneling";"Zergling";104;0
"Unit";"Baneling";"Zergling";104;0
"Building";"RoachWarren";NA;94;0
"Unit";"Baneling";"Zergling";111;0
"Unit";"Zergling";"Larva";117;1
"Unit";"Zergling";"Larva";117;1
"Building";"CreepTumor";NA;117;0
"Building";"CreepTumor";NA;119;0
"Unit";"Roach";"Larva";117;2
"Building";"Extractor";NA;117;0
"Unit";"Overlord";"Larva";117;0
"Unit";"Overlord";"Larva";117;0
"Building";"Extractor";NA;117;0
"Unit";"Overlord";"Larva";117;0
"Unit";"Baneling";"Zergling";119;0
"Unit";"Roach";"Larva";119;2
"Unit";"Overlord";"Larva";119;0
"Unit";"Overlord";"Larva";119;0
"Unit";"Roach";"Larva";119;2
"Unit";"Overlord";"Larva";119;0
"Building";"CreepTumor";NA;121;0
"Building";"CreepTumor";NA;121;0
"Unit";"Roach";"Larva";129;2
"Unit";"Roach";"Larva";130;2
"Unit";"Roach";"Larva";131;2
"Building";"Extractor";NA;125;0
"Unit";"Roach";"Larva";131;2
"Unit";"Roach";"Larva";131;2
"Unit";"Roach";"Larva";131;2
"Building";"CreepTumor";NA;144;0
"Building";"CreepTumor";NA;144;0
"Unit";"Roach";"Larva";144;2
"Unit";"Roach";"Larva";144;2
"Unit";"Roach";"Larva";144;2
"Unit";"Roach";"Larva";144;2
"Unit";"Roach";"Larva";144;2
"Unit";"Roach";"Larva";144;2
"Unit";"Roach";"Larva";144;2
"Unit";"Roach";"Larva";144;2
"Unit";"Roach";"Larva";144;2
"Unit";"Overlord";"Larva";150;0
"Unit";"Overlord";"Larva";150;0
"Unit";"Roach";"Larva";150;2
"Unit";"Roach";"Larva";150;2
"Upgrade";"GlialReconstitution";"RoachWarren";138;0
"Unit";"Roach";"Larva";171;2
"Building";"HydraliskDen";NA;171;0
"Unit";"Roach";"Larva";171;2
"Unit";"Roach";"Larva";171;2
"Unit";"Roach";"Larva";171;2
"Unit";"Roach";"Larva";171;2
"Unit";"Roach";"Larva";171;2
"Unit";"Roach";"Larva";171;2
"Unit";"Roach";"Larva";175;2
"Unit";"Roach";"Larva";175;2
"Unit";"Roach";"Larva";175;2
"Unit";"Roach";"Larva";175;2
"Upgrade";"ZergMissileWeaponsLevel1";"EvolutionChamber";150;0
"Unit";"Roach";"Larva";200;2
"Unit";"Overlord";"Larva";200;0
"Unit";"Overlord";"Larva";200;0
"Unit";"Roach";"Larva";200;2
"Unit";"Overlord";"Larva";200;0
"Building";"CreepTumor";NA;200;0
"Unit";"Overlord";"Larva";200;0
"Unit";"Overlord";"Larva";200;0
"Unit";"Overlord";"Larva";200;0
"Unit";"Overlord";"Larva";200;0
