"type";"unit_name";"on_building";"total_supply";"supply"
"Unit";"Overlord";"Larva";12;0
"Building";"Extractor";NA;18;0
"Unit";"Overlord";"Larva";21;0
"Building";"SpawningPool";NA;19;0
"Building";"Hatchery";NA;17;0
"Unit";"Zergling";"Larva";22;1
"Unit";"Zergling";"Larva";22;1
"Unit";"Zergling";"Larva";22;1
"Unit";"Zergling";"Larva";22;1
"Unit";"Queen";"Hatchery";22;2
"Unit";"Queen";"Hatchery";22;2
"Building";"BanelingNest";NA;29;0
"Unit";"Overlord";"Larva";38;0
"Unit";"Baneling";"Zergling";38;0
"Unit";"Baneling";"Zergling";38;0
"Unit";"Zergling";"Larva";41;1
"Unit";"Zergling";"Larva";41;1
"Unit";"Zergling";"Larva";41;1
"Unit";"Zergling";"Larva";41;1
"Unit";"Zergling";"Larva";41;1
"Unit";"Zergling";"Larva";41;1
"Unit";"Zergling";"Larva";41;1
"Unit";"Zergling";"Larva";41;1
"Unit";"Zergling";"Larva";41;1
"Unit";"Zergling";"Larva";41;1
"Unit";"Zergling";"Larva";41;1
"Unit";"Zergling";"Larva";41;1
"Unit";"Overlord";"Larva";41;0
"Building";"Hatchery";NA;38;0
"Unit";"Queen";"Hatchery";53;2
"Unit";"Overlord";"Larva";59;0
"Building";"Extractor";NA;60;0
"Unit";"Zergling";"Larva";65;1
"Unit";"Zergling";"Larva";65;1
"Unit";"Zergling";"Larva";65;1
"Unit";"Zergling";"Larva";65;1
"Unit";"Zergling";"Larva";65;1
"Unit";"Zergling";"Larva";65;1
"Unit";"Zergling";"Larva";65;1
"Unit";"Zergling";"Larva";65;1
"Unit";"Zergling";"Larva";65;1
"Unit";"Zergling";"Larva";65;1
"Unit";"Zergling";"Larva";65;1
"Unit";"Zergling";"Larva";65;1
"Unit";"Overlord";"Larva";65;0
"Unit";"Overlord";"Larva";65;0
"Unit";"Zergling";"Larva";65;1
"Unit";"Zergling";"Larva";65;1
"Unit";"Zergling";"Larva";65;1
"Unit";"Zergling";"Larva";65;1
"Building";"RoachWarren";NA;63;0
"Unit";"Baneling";"Zergling";77;0
"Unit";"Zergling";"Larva";65;1
"Unit";"Zergling";"Larva";65;1
"Unit";"Baneling";"Zergling";77;0
"Unit";"Zergling";"Larva";65;1
"Unit";"Zergling";"Larva";65;1
"Unit";"Baneling";"Zergling";77;0
"Unit";"Baneling";"Zergling";77;0
"Building";"EvolutionChamber";NA;65;0
"Unit";"Baneling";"Zergling";83;0
"Unit";"Baneling";"Zergling";83;0
"Unit";"Baneling";"Zergling";85;0
"Unit";"Zergling";"Larva";81;1
"Unit";"Zergling";"Larva";81;1
"Unit";"Zergling";"Larva";81;1
"Unit";"Zergling";"Larva";81;1
"Unit";"Zergling";"Larva";81;1
"Unit";"Zergling";"Larva";81;1
"Unit";"Zergling";"Larva";81;1
"Unit";"Zergling";"Larva";81;1
"Unit";"Zergling";"Larva";81;1
"Unit";"Zergling";"Larva";81;1
"Unit";"Zergling";"Larva";85;1
"Unit";"Zergling";"Larva";85;1
"Unit";"Zergling";"Larva";85;1
"Unit";"Zergling";"Larva";85;1
"Unit";"Zergling";"Larva";85;1
"Unit";"Zergling";"Larva";85;1
"Unit";"Zergling";"Larva";85;1
"Unit";"Zergling";"Larva";85;1
"Unit";"Zergling";"Larva";85;1
"Unit";"Zergling";"Larva";85;1
"Unit";"Zergling";"Larva";85;1
"Unit";"Zergling";"Larva";85;1
"Unit";"Zergling";"Larva";85;1
"Unit";"Zergling";"Larva";85;1
"Unit";"Zergling";"Larva";85;1
"Unit";"Zergling";"Larva";85;1
"Unit";"Zergling";"Larva";85;1
"Unit";"Zergling";"Larva";85;1
"Unit";"Baneling";"Zergling";113;0
"Unit";"Baneling";"Zergling";113;0
"Unit";"Baneling";"Zergling";113;0
"Unit";"Baneling";"Zergling";113;0
"Unit";"Baneling";"Zergling";116;0
"Unit";"Baneling";"Zergling";116;0
"Unit";"Queen";"Hatchery";113;2
"Unit";"Baneling";"Zergling";121;0
"Unit";"Baneling";"Zergling";121;0
"Unit";"Baneling";"Zergling";135;0
"Unit";"Baneling";"Zergling";135;0
"Unit";"Baneling";"Zergling";135;0
"Unit";"Roach";"Larva";138;2
"Unit";"Roach";"Larva";138;2
"Unit";"Roach";"Larva";138;2
"Unit";"Roach";"Larva";138;2
"Unit";"Roach";"Larva";138;2
"Unit";"Roach";"Larva";138;2
"Building";"Extractor";NA;138;0
"Unit";"Baneling";"Zergling";138;0
"Unit";"Baneling";"Zergling";138;0
"Unit";"Overlord";"Larva";138;0
"Unit";"Overlord";"Larva";138;0
"Unit";"Baneling";"Zergling";150;0
"Unit";"Baneling";"Zergling";150;0
"Unit";"Baneling";"Zergling";150;0
"Unit";"Baneling";"Zergling";150;0
"Upgrade";"ZergMissileWeaponsLevel1";"EvolutionChamber";124;0
"Building";"SpineCrawler";NA;138;0
"Unit";"Queen";"Hatchery";138;2
"Unit";"Roach";"Larva";150;2
"Unit";"Roach";"Larva";150;2
"Unit";"Roach";"Larva";150;2
"Unit";"Roach";"Larva";150;2
"Unit";"Overlord";"Larva";150;0
"Unit";"Overlord";"Larva";150;0
"Unit";"Overlord";"Larva";150;0
"Building";"CreepTumorQueen";NA;150;0
"Unit";"Roach";"Larva";150;2
"Unit";"Roach";"Larva";150;2
"Building";"SpineCrawler";NA;150;0
"Unit";"Roach";"Larva";150;2
"Unit";"Roach";"Larva";150;2
"Unit";"Overlord";"Larva";152;0
"Unit";"Overlord";"Larva";152;0
"Unit";"Roach";"Larva";160;2
"Unit";"Roach";"Larva";160;2
"Unit";"Roach";"Larva";160;2
"Unit";"Roach";"Larva";160;2
"Unit";"Roach";"Larva";160;2
"Unit";"Roach";"Larva";160;2
"Building";"CreepTumorQueen";NA;170;0
"Building";"CreepTumorQueen";NA;174;0
"Building";"Extractor";NA;168;0
"Unit";"Roach";"Larva";180;2
"Unit";"Roach";"Larva";184;2
"Unit";"Roach";"Larva";184;2
"Unit";"Baneling";"Zergling";184;0
"Unit";"Roach";"Larva";184;2
"Unit";"Roach";"Larva";184;2
"Unit";"Roach";"Larva";184;2
"Unit";"Roach";"Larva";186;2
"Unit";"Roach";"Larva";186;2
"Unit";"Zergling";"Larva";190;1
"Unit";"Zergling";"Larva";190;1
"Unit";"Zergling";"Larva";190;1
"Unit";"Zergling";"Larva";190;1
"Unit";"Zergling";"Larva";190;1
"Unit";"Zergling";"Larva";190;1
"Unit";"Roach";"Larva";192;2
"Unit";"Roach";"Larva";194;2
"Unit";"Roach";"Larva";194;2
