"type";"unit_name";"on_building";"total_supply";"supply"
"Unit";"Overlord";"Larva";13;0
"Building";"Extractor";NA;19;0
"Unit";"Overlord";"Larva";21;0
"Building";"SpawningPool";NA;19;0
"Building";"Hatchery";NA;17;0
"Unit";"Zergling";"Larva";22;1
"Unit";"Zergling";"Larva";22;1
"Unit";"Zergling";"Larva";22;1
"Unit";"Zergling";"Larva";22;1
"Unit";"Zergling";"Larva";22;1
"Unit";"Zergling";"Larva";22;1
"Unit";"Queen";"Hatchery";22;2
"Unit";"Queen";"Hatchery";22;2
"Unit";"Overlord";"Larva";34;0
"Building";"BanelingNest";NA;30;0
"Unit";"Zergling";"Larva";39;1
"Unit";"Zergling";"Larva";39;1
"Unit";"Overlord";"Larva";39;0
"Unit";"Zergling";"Larva";39;1
"Unit";"Zergling";"Larva";39;1
"Unit";"Zergling";"Larva";42;1
"Unit";"Zergling";"Larva";42;1
"Unit";"Zergling";"Larva";42;1
"Unit";"Zergling";"Larva";42;1
"Unit";"Baneling";"Zergling";44;0
"Unit";"Baneling";"Zergling";44;0
"Unit";"Baneling";"Zergling";50;0
"Unit";"Baneling";"Zergling";50;0
"Unit";"Zergling";"Larva";50;1
"Unit";"Zergling";"Larva";50;1
"Unit";"Zergling";"Larva";50;1
"Unit";"Zergling";"Larva";50;1
"Unit";"Zergling";"Larva";50;1
"Unit";"Zergling";"Larva";50;1
"Unit";"Zergling";"Larva";50;1
"Unit";"Zergling";"Larva";50;1
"Unit";"Zergling";"Larva";50;1
"Unit";"Zergling";"Larva";50;1
"Unit";"Baneling";"Zergling";50;0
"Unit";"Baneling";"Zergling";50;0
"Building";"Hatchery";NA;39;0
"Unit";"Zergling";"Larva";50;1
"Unit";"Zergling";"Larva";50;1
"Unit";"Zergling";"Larva";50;1
"Unit";"Zergling";"Larva";50;1
"Unit";"Zergling";"Larva";50;1
"Unit";"Zergling";"Larva";50;1
"Unit";"Zergling";"Larva";50;1
"Unit";"Zergling";"Larva";50;1
"Unit";"Zergling";"Larva";50;1
"Unit";"Zergling";"Larva";50;1
"Unit";"Zergling";"Larva";50;1
"Unit";"Zergling";"Larva";50;1
"Unit";"Baneling";"Zergling";72;0
"Unit";"Baneling";"Zergling";72;0
"Unit";"Baneling";"Zergling";72;0
"Unit";"Baneling";"Zergling";72;0
"Building";"Extractor";NA;72;0
"Building";"Extractor";NA;72;0
"Building";"RoachWarren";NA;72;0
"Unit";"Zergling";"Larva";78;1
"Unit";"Zergling";"Larva";78;1
"Unit";"Zergling";"Larva";78;1
"Unit";"Zergling";"Larva";78;1
"Unit";"Zergling";"Larva";78;1
"Unit";"Zergling";"Larva";78;1
"Unit";"Zergling";"Larva";78;1
"Unit";"Zergling";"Larva";78;1
"Unit";"Zergling";"Larva";78;1
"Unit";"Zergling";"Larva";78;1
"Unit";"Zergling";"Larva";78;1
"Unit";"Zergling";"Larva";78;1
"Unit";"Zergling";"Larva";78;1
"Unit";"Zergling";"Larva";78;1
"Unit";"Zergling";"Larva";78;1
"Unit";"Zergling";"Larva";78;1
"Unit";"Zergling";"Larva";78;1
"Unit";"Zergling";"Larva";78;1
"Unit";"Zergling";"Larva";78;1
"Unit";"Zergling";"Larva";78;1
"Unit";"Baneling";"Zergling";100;0
"Unit";"Baneling";"Zergling";100;0
"Unit";"Baneling";"Zergling";100;0
"Unit";"Queen";"Hatchery";100;2
"Unit";"Overlord";"Larva";108;0
"Unit";"Overlord";"Larva";108;0
"Unit";"Overlord";"Larva";108;0
"Unit";"Zergling";"Larva";108;1
"Unit";"Zergling";"Larva";108;1
"Unit";"Baneling";"Zergling";109;0
"Unit";"Baneling";"Zergling";109;0
"Unit";"Baneling";"Zergling";111;0
"Unit";"Baneling";"Zergling";113;0
"Unit";"Zergling";"Larva";113;1
"Unit";"Zergling";"Larva";113;1
"Unit";"Zergling";"Larva";113;1
"Unit";"Zergling";"Larva";113;1
"Unit";"Zergling";"Larva";113;1
"Unit";"Zergling";"Larva";113;1
"Unit";"Zergling";"Larva";113;1
"Unit";"Zergling";"Larva";113;1
"Unit";"Zergling";"Larva";113;1
"Unit";"Zergling";"Larva";113;1
"Unit";"Zergling";"Larva";113;1
"Unit";"Zergling";"Larva";113;1
"Unit";"Zergling";"Larva";113;1
"Unit";"Zergling";"Larva";113;1
"Unit";"Zergling";"Larva";113;1
"Unit";"Zergling";"Larva";113;1
"Unit";"Zergling";"Larva";113;1
"Unit";"Zergling";"Larva";113;1
"Unit";"Zergling";"Larva";113;1
"Unit";"Zergling";"Larva";113;1
"Unit";"Zergling";"Larva";113;1
"Unit";"Zergling";"Larva";113;1
"Unit";"Zergling";"Larva";113;1
"Unit";"Zergling";"Larva";113;1
"Unit";"Zergling";"Larva";113;1
"Unit";"Zergling";"Larva";113;1
"Unit";"Zergling";"Larva";113;1
"Unit";"Zergling";"Larva";113;1
"Unit";"Zergling";"Larva";113;1
"Unit";"Zergling";"Larva";113;1
"Unit";"Zergling";"Larva";131;1
"Unit";"Zergling";"Larva";131;1
"Unit";"Zergling";"Larva";131;1
"Unit";"Zergling";"Larva";131;1
"Unit";"Zergling";"Larva";131;1
"Unit";"Zergling";"Larva";131;1
"Unit";"Zergling";"Larva";131;1
"Unit";"Zergling";"Larva";131;1
"Unit";"Zergling";"Larva";131;1
"Unit";"Zergling";"Larva";131;1
"Unit";"Roach";"Larva";143;2
"Unit";"Roach";"Larva";143;2
"Unit";"Baneling";"Zergling";143;0
"Unit";"Baneling";"Zergling";143;0
"Unit";"Baneling";"Zergling";143;0
"Unit";"Roach";"Larva";143;2
"Unit";"Roach";"Larva";143;2
"Unit";"Queen";"Hatchery";143;2
"Unit";"Roach";"Larva";166;2
"Unit";"Roach";"Larva";166;2
"Unit";"Roach";"Larva";166;2
"Unit";"Roach";"Larva";168;2
"Unit";"Roach";"Larva";168;2
"Unit";"Roach";"Larva";168;2
"Unit";"Roach";"Larva";168;2
"Unit";"Overlord";"Larva";168;0
"Unit";"Overlord";"Larva";168;0
"Unit";"Overlord";"Larva";168;0
"Unit";"Overlord";"Larva";168;0
"Building";"EvolutionChamber";NA;168;0
"Unit";"Overlord";"Larva";168;0
"Unit";"Baneling";"Zergling";182;0
"Unit";"Baneling";"Zergling";182;0
"Unit";"Baneling";"Zergling";182;0
"Unit";"Baneling";"Zergling";182;0
"Unit";"Roach";"Larva";168;2
"Building";"Extractor";NA;168;0
"Upgrade";"GlialReconstitution";"RoachWarren";162;0
"Unit";"Roach";"Larva";182;2
"Unit";"Roach";"Larva";182;2
"Unit";"Roach";"Larva";182;2
"Unit";"Roach";"Larva";182;2
"Unit";"Roach";"Larva";182;2
"Unit";"Roach";"Larva";182;2
"Unit";"Roach";"Larva";182;2
"Unit";"Roach";"Larva";182;2
"Unit";"Roach";"Larva";182;2
"Unit";"Roach";"Larva";182;2
"Unit";"Roach";"Larva";182;2
"Unit";"Roach";"Larva";182;2
"Unit";"Roach";"Larva";187;2
"Unit";"Roach";"Larva";191;2
"Unit";"Roach";"Larva";207;2
"Unit";"Roach";"Larva";209;2
"Unit";"Roach";"Larva";211;2
"Unit";"Overlord";"Larva";213;0
"Unit";"Overlord";"Larva";215;0
"Unit";"Overlord";"Larva";215;0
"Unit";"Overlord";"Larva";215;0
"Unit";"Roach";"Larva";223;2
"Unit";"Roach";"Larva";223;2
"Unit";"Roach";"Larva";223;2
"Unit";"Roach";"Larva";223;2
"Unit";"Roach";"Larva";223;2
"Unit";"Roach";"Larva";223;2
"Unit";"Overlord";"Larva";223;0
"Building";"Extractor";NA;223;0
"Building";"Extractor";NA;223;0
"Unit";"Roach";"Larva";241;2
"Unit";"Roach";"Larva";241;2
"Unit";"Roach";"Larva";241;2
"Unit";"Roach";"Larva";241;2
"Unit";"Roach";"Larva";241;2
"Upgrade";"ZergMissileWeaponsLevel1";"EvolutionChamber";221;0
"Unit";"Roach";"Larva";255;2
"Unit";"Roach";"Larva";259;2
"Unit";"Roach";"Larva";259;2
"Unit";"Roach";"Larva";259;2
"Unit";"Roach";"Larva";259;2
"Unit";"Roach";"Larva";259;2
"Unit";"Roach";"Larva";259;2
"Unit";"Roach";"Larva";259;2
"Unit";"Roach";"Larva";261;2
"Unit";"Roach";"Larva";261;2
"Unit";"Roach";"Larva";269;2
"Unit";"Roach";"Larva";269;2
"Unit";"Roach";"Larva";269;2
"Unit";"Roach";"Larva";269;2
"Unit";"Roach";"Larva";269;2
"Unit";"Roach";"Larva";289;2
"Unit";"Roach";"Larva";289;2
"Unit";"Roach";"Larva";289;2
"Unit";"Roach";"Larva";289;2
"Unit";"Roach";"Larva";289;2
"Unit";"Roach";"Larva";289;2
"Unit";"Roach";"Larva";289;2
"Unit";"Roach";"Larva";289;2
"Building";"Hatchery";NA;259;0
"Unit";"Roach";"Larva";289;2
"Unit";"Roach";"Larva";289;2
"Unit";"Roach";"Larva";289;2
"Unit";"Roach";"Larva";289;2
"Unit";"Overlord";"Larva";289;0
"Unit";"Roach";"Larva";305;2
"Unit";"Roach";"Larva";305;2
"Unit";"Roach";"Larva";319;2
"Unit";"Roach";"Larva";319;2
"Unit";"Roach";"Larva";319;2
"Building";"HydraliskDen";NA;319;0
"Unit";"Roach";"Larva";333;2
"Unit";"Roach";"Larva";333;2
"Unit";"Roach";"Larva";333;2
"Unit";"Roach";"Larva";333;2
"Unit";"Overlord";"Larva";333;0
"Unit";"Overlord";"Larva";333;0
"Unit";"Overlord";"Larva";333;0
"Unit";"Overlord";"Larva";333;0
"Unit";"Overlord";"Larva";333;0
"Unit";"Overlord";"Larva";333;0
"Unit";"Roach";"Larva";333;2
"Unit";"Roach";"Larva";333;2
"Unit";"Roach";"Larva";333;2
"Unit";"Roach";"Larva";335;2
"Unit";"Roach";"Larva";337;2
"Unit";"Roach";"Larva";339;2
"Unit";"Roach";"Larva";341;2
"Unit";"Roach";"Larva";341;2
"Unit";"Hydralisk";"Larva";341;2
"Unit";"Hydralisk";"Larva";341;2
"Unit";"Hydralisk";"Larva";341;2
"Unit";"Hydralisk";"Larva";341;2
"Upgrade";"ZergMissileWeaponsLevel2";"EvolutionChamber";305;0
"Unit";"Hydralisk";"Larva";341;2
"Unit";"Hydralisk";"Larva";341;2
"Unit";"Hydralisk";"Larva";357;2
"Unit";"Hydralisk";"Larva";357;2
"Unit";"Hydralisk";"Larva";357;2
"Unit";"Queen";"Hatchery";341;2
"Unit";"Hydralisk";"Larva";357;2
"Unit";"Hydralisk";"Larva";357;2
"Unit";"Hydralisk";"Larva";357;2
"Upgrade";"EvolveGroovedSpines";"HydraliskDen";341;0
"Unit";"Hydralisk";"Larva";365;2
"Unit";"Hydralisk";"Larva";365;2
"Unit";"Hydralisk";"Larva";365;2
"Unit";"Hydralisk";"Larva";369;2
"Unit";"Hydralisk";"Larva";369;2
"Unit";"Hydralisk";"Larva";369;2
"Unit";"Hydralisk";"Larva";369;2
"Unit";"Overlord";"Larva";389;0
"Unit";"Hydralisk";"Larva";383;2
"Unit";"Hydralisk";"Larva";383;2
"Unit";"Hydralisk";"Larva";383;2
"Unit";"Hydralisk";"Larva";383;2
"Unit";"Hydralisk";"Larva";383;2
"Unit";"Roach";"Larva";400;2
"Unit";"Roach";"Larva";400;2
"Unit";"Overlord";"Larva";410;0
"Unit";"Overlord";"Larva";410;0
"Building";"SpineCrawler";NA;400;0
"Unit";"Roach";"Larva";414;2
"Building";"SpineCrawler";NA;410;0
"Unit";"Roach";"Larva";414;2
"Unit";"Roach";"Larva";414;2
"Unit";"Roach";"Larva";414;2
"Unit";"Roach";"Larva";414;2
"Unit";"Roach";"Larva";414;2
"Unit";"Roach";"Larva";414;2
"Unit";"Roach";"Larva";414;2
"Unit";"Roach";"Larva";414;2
"Unit";"Roach";"Larva";414;2
"Unit";"Roach";"Larva";414;2
"Unit";"Roach";"Larva";414;2
"Building";"SpineCrawler";NA;410;0
"Unit";"Roach";"Larva";414;2
"Unit";"Roach";"Larva";414;2
"Upgrade";"ZergGroundArmorsLevel1";"EvolutionChamber";400;0
"Unit";"Roach";"Larva";442;2
"Unit";"Roach";"Larva";442;2
"Unit";"Roach";"Larva";442;2
"Unit";"Roach";"Larva";442;2
"Unit";"Roach";"Larva";442;2
"Unit";"Roach";"Larva";442;2
"Unit";"Roach";"Larva";442;2
"Unit";"Roach";"Larva";442;2
"Unit";"Roach";"Larva";442;2
"Unit";"Roach";"Larva";442;2
"Unit";"Roach";"Larva";442;2
"Unit";"Roach";"Larva";442;2
"Unit";"Roach";"Larva";442;2
"Unit";"Roach";"Larva";442;2
"Unit";"Roach";"Larva";442;2
"Unit";"Roach";"Larva";442;2
