"type";"unit_name";"on_building";"total_supply_lag";"supply"
"Unit";"Overlord";"Larva";13;0
"Building";"SpawningPool";NA;17;0
"Building";"Hatchery";NA;18;0
"Building";"Extractor";NA;20;0
"Unit";"Queen";"Hatchery";21;2
"Unit";"Zergling";"Larva";23;1
"Unit";"Zergling";"Larva";24;1
"Unit";"Zergling";"Larva";25;1
"Unit";"Zergling";"Larva";26;1
"Building";"SpineCrawler";NA;27;0
"Unit";"Zergling";"Larva";27;1
"Unit";"Zergling";"Larva";28;1
"Unit";"Zergling";"Larva";29;1
"Unit";"Zergling";"Larva";30;1
"Unit";"Overlord";"Larva";40;0
"Unit";"Overlord";"Larva";48;0
"Building";"Hatchery";NA;49;0
"Unit";"Queen";"Hatchery";49;2
"Unit";"Zergling";"Larva";53;1
"Unit";"Zergling";"Larva";54;1
"Unit";"Zergling";"Larva";55;1
"Unit";"Zergling";"Larva";56;1
"Unit";"Zergling";"Larva";57;1
"Unit";"Zergling";"Larva";58;1
"Unit";"Zergling";"Larva";59;1
"Unit";"Zergling";"Larva";60;1
"Unit";"Zergling";"Larva";61;1
"Unit";"Zergling";"Larva";62;1
"Unit";"Zergling";"Larva";63;1
"Unit";"Zergling";"Larva";64;1
"Unit";"Overlord";"Larva";65;0
"Unit";"Overlord";"Larva";66;0
"Building";"EvolutionChamber";NA;70;0
"Building";"RoachWarren";NA;72;0
"Building";"Extractor";NA;74;0
"Unit";"Overlord";"Larva";78;0
"Building";"Extractor";NA;81;0
"Unit";"Overlord";"Larva";81;0
"Unit";"Roach";"Larva";81;2
"Unit";"Roach";"Larva";83;2
"Unit";"Roach";"Larva";85;2
"Unit";"Roach";"Larva";87;2
"Building";"Extractor";NA;96;0
"Unit";"Queen";"Hatchery";97;2
"Unit";"Roach";"Larva";99;2
"Unit";"Roach";"Larva";101;2
"Unit";"Roach";"Larva";103;2
"Unit";"Roach";"Larva";105;2
"Unit";"Overlord";"Larva";107;0
"Unit";"Overlord";"Larva";107;0
"Unit";"Roach";"Larva";107;2
"Unit";"Roach";"Larva";109;2
"Unit";"Roach";"Larva";111;2
"Unit";"Roach";"Larva";113;2
"Unit";"Overlord";"Larva";115;0
"Unit";"Overlord";"Larva";115;0
"Unit";"Overlord";"Larva";115;0
"Unit";"Roach";"Larva";115;2
"Unit";"Roach";"Larva";117;2
"Unit";"Roach";"Larva";119;2
"Unit";"Roach";"Larva";121;2
"Unit";"Roach";"Larva";123;2
"Unit";"Roach";"Larva";125;2
"Unit";"Roach";"Larva";127;2
"Unit";"Roach";"Larva";129;2
"Unit";"Roach";"Larva";131;2
"Unit";"Roach";"Larva";133;2
"Unit";"Roach";"Larva";135;2
"Unit";"Roach";"Larva";137;2
"Building";"Extractor";NA;139;0
"Unit";"Overlord";"Larva";139;0
"Unit";"Overlord";"Larva";146;0
"Building";"EvolutionChamber";NA;146;0
"Unit";"Overlord";"Larva";149;0
"Upgrade";"GlialReconstitution";"RoachWarren";149;0
"Unit";"Roach";"Larva";155;2
"Unit";"Roach";"Larva";157;2
"Unit";"Roach";"Larva";159;2
"Unit";"Roach";"Larva";161;2
"Unit";"Roach";"Larva";163;2
"Building";"Hatchery";NA;165;0
"Unit";"Overlord";"Larva";165;0
"Unit";"Roach";"Larva";165;2
"Unit";"Roach";"Larva";167;2
"Unit";"Overlord";"Larva";169;0
"Unit";"Overlord";"Larva";169;0
"Unit";"Roach";"Larva";169;2
"Unit";"Roach";"Larva";171;2
"Unit";"Roach";"Larva";173;2
"Unit";"Roach";"Larva";175;2
"Building";"Extractor";NA;177;0
"Unit";"Roach";"Larva";177;2
"Unit";"Roach";"Larva";179;2
"Unit";"Roach";"Larva";181;2
"Unit";"Roach";"Larva";185;2
"Unit";"Roach";"Larva";187;2
"Unit";"Roach";"Larva";189;2
"Unit";"Roach";"Larva";191;2
"Unit";"Roach";"Larva";193;2
"Unit";"Roach";"Larva";195;2
"Unit";"Roach";"Larva";197;2
"Unit";"Overlord";"Larva";199;0
"Unit";"Overlord";"Larva";199;0
"Building";"HydraliskDen";NA;199;0
"Unit";"Overlord";"Larva";200;0
"Unit";"Overlord";"Larva";200;0
"Upgrade";"TunnelingClaws";"RoachWarren";200;0
"Upgrade";"Burrow";"Hatchery";200;0
"Unit";"Overlord";"Larva";200;0
"Unit";"Roach";"Larva";200;2
"Unit";"Roach";"Larva";202;2
"Unit";"Roach";"Larva";204;2
"Unit";"Roach";"Larva";206;2
"Unit";"Roach";"Larva";208;2
"Unit";"Roach";"Larva";210;2
"Unit";"Roach";"Larva";212;2
"Unit";"Roach";"Larva";214;2
"Unit";"Roach";"Larva";216;2
"Unit";"Roach";"Larva";218;2
"Unit";"Roach";"Larva";220;2
"Unit";"Roach";"Larva";222;2
"Unit";"Roach";"Larva";224;2
"Unit";"Roach";"Larva";226;2
"Unit";"Roach";"Larva";228;2
"Unit";"Roach";"Larva";230;2
"Building";"LurkerDenMP";NA;232;0
"Unit";"Roach";"Larva";232;2
"Building";"SpineCrawler";NA;238;0
"Unit";"Hydralisk";"Larva";238;2
"Unit";"Hydralisk";"Larva";240;2
"Unit";"Hydralisk";"Larva";242;2
"Unit";"Hydralisk";"Larva";244;2
"Unit";"Hydralisk";"Larva";246;2
"Building";"SpineCrawler";NA;248;0
"Building";"SpineCrawler";NA;248;0
"Building";"SpineCrawler";NA;248;0
"Unit";"Roach";"Larva";248;2
"Unit";"Roach";"Larva";250;2
"Unit";"Roach";"Larva";252;2
"Unit";"Roach";"Larva";254;2
"Unit";"Roach";"Larva";256;2
"Unit";"Roach";"Larva";258;2
"Unit";"Roach";"Larva";260;2
"Building";"InfestationPit";NA;268;0
"Building";"Hatchery";NA;268;0
"Unit";"Hydralisk";"Larva";268;2
"Unit";"Hydralisk";"Larva";270;2
"Unit";"Hydralisk";"Larva";272;2
"Building";"Spire";NA;274;0
"Building";"SpineCrawler";NA;274;0
"Unit";"Roach";"Larva";274;2
"Unit";"Roach";"Larva";276;2
"Unit";"Roach";"Larva";278;2
"Unit";"Roach";"Larva";280;2
"Unit";"Roach";"Larva";282;2
"Unit";"Roach";"Larva";284;2
"Unit";"Roach";"Larva";286;2
"Unit";"Roach";"Larva";288;2
"Unit";"Roach";"Larva";290;2
"Unit";"Roach";"Larva";292;2
"Unit";"Roach";"Larva";294;2
"Unit";"Roach";"Larva";296;2
"Unit";"Roach";"Larva";298;2
"Unit";"Roach";"Larva";300;2
"Unit";"Roach";"Larva";302;2
"Unit";"Roach";"Larva";304;2
"Unit";"Roach";"Larva";306;2
"Unit";"Roach";"Larva";308;2
"Unit";"Roach";"Larva";310;2
"Unit";"Roach";"Larva";312;2
"Unit";"Roach";"Larva";314;2
"Unit";"Roach";"Larva";316;2
"Unit";"Roach";"Larva";318;2
"Unit";"Roach";"Larva";320;2
"Unit";"Roach";"Larva";322;2
"Unit";"Roach";"Larva";324;2
"Unit";"Roach";"Larva";326;2
"Unit";"Roach";"Larva";328;2
"Unit";"Roach";"Larva";330;2
"Unit";"Roach";"Larva";332;2
"Unit";"Roach";"Larva";334;2
"Unit";"Roach";"Larva";336;2
"Unit";"Roach";"Larva";338;2
"Unit";"Roach";"Larva";340;2
"Unit";"Roach";"Larva";342;2
"Unit";"Roach";"Larva";344;2
"Unit";"Roach";"Larva";346;2
"Unit";"Roach";"Larva";348;2
"Unit";"Roach";"Larva";350;2
"Unit";"Roach";"Larva";352;2
"Unit";"Roach";"Larva";354;2
"Unit";"Roach";"Larva";356;2
"Unit";"Roach";"Larva";358;2
"Unit";"Roach";"Larva";360;2
"Unit";"Roach";"Larva";362;2
"Unit";"Roach";"Larva";364;2
"Unit";"Roach";"Larva";366;2
"Unit";"Roach";"Larva";368;2
"Unit";"Roach";"Larva";370;2
"Unit";"Roach";"Larva";372;2
"Unit";"Roach";"Larva";374;2
"Unit";"Roach";"Larva";376;2
"Unit";"Roach";"Larva";378;2
"Unit";"Roach";"Larva";380;2
"Unit";"Roach";"Larva";382;2
"Unit";"Roach";"Larva";384;2
"Unit";"Roach";"Larva";386;2
"Building";"Extractor";NA;388;0
"Unit";"Roach";"Larva";388;2
"Unit";"Roach";"Larva";390;2
"Building";"Extractor";NA;392;0
"Building";"SpineCrawler";NA;392;0
"Unit";"Roach";"Larva";392;2
"Building";"SpineCrawler";NA;394;0
"Building";"SpineCrawler";NA;394;0
"Unit";"Roach";"Larva";394;2
"Unit";"Roach";"Larva";396;2
"Unit";"Roach";"Larva";398;2
"Unit";"Roach";"Larva";400;2
"Unit";"Roach";"Larva";402;2
"Unit";"Roach";"Larva";404;2
"Unit";"Roach";"Larva";406;2
"Unit";"Roach";"Larva";408;2
"Unit";"Roach";"Larva";410;2
"Unit";"Roach";"Larva";412;2
"Unit";"Roach";"Larva";414;2
"Unit";"Roach";"Larva";416;2
"Unit";"Roach";"Larva";418;2
"Unit";"Roach";"Larva";420;2
"Unit";"Roach";"Larva";422;2
"Unit";"Roach";"Larva";424;2
"Unit";"Roach";"Larva";426;2
"Unit";"Roach";"Larva";428;2
"Unit";"Roach";"Larva";430;2
"Unit";"Roach";"Larva";432;2
"Unit";"Roach";"Larva";434;2
"Unit";"Roach";"Larva";436;2
"Unit";"Roach";"Larva";438;2
"Unit";"Roach";"Larva";440;2
"Unit";"Roach";"Larva";442;2
"Unit";"Roach";"Larva";444;2
"Unit";"Roach";"Larva";446;2
"Unit";"Roach";"Larva";448;2
"Unit";"Roach";"Larva";450;2
"Unit";"Roach";"Larva";452;2
"Unit";"Roach";"Larva";454;2
"Unit";"Roach";"Larva";456;2
"Unit";"Roach";"Larva";458;2
"Unit";"Roach";"Larva";460;2
"Unit";"Roach";"Larva";462;2
"Unit";"Roach";"Larva";464;2
"Unit";"Roach";"Larva";466;2
"Unit";"Roach";"Larva";468;2
"Unit";"Hydralisk";"Larva";470;2
"Unit";"Hydralisk";"Larva";472;2
"Unit";"Hydralisk";"Larva";474;2
"Building";"SpineCrawler";NA;476;0
"Building";"SpineCrawler";NA;476;0
"Building";"SpineCrawler";NA;476;0
"Unit";"Roach";"Larva";479;2
"Unit";"Roach";"Larva";481;2
"Unit";"Roach";"Larva";483;2
"Unit";"Roach";"Larva";485;2
"Unit";"Roach";"Larva";487;2
"Unit";"Roach";"Larva";489;2
"Unit";"Roach";"Larva";491;2
"Unit";"Roach";"Larva";493;2
"Unit";"Roach";"Larva";495;2
"Unit";"Roach";"Larva";497;2
"Unit";"Roach";"Larva";499;2
"Unit";"Roach";"Larva";501;2
"Unit";"Roach";"Larva";503;2
"Upgrade";"SprayZerg";NA;505;0
"Upgrade";"SprayZerg";NA;505;0
"Upgrade";"SprayZerg";NA;505;0
"Upgrade";"zerglingmovementspeed";NA;505;0
"Upgrade";"SprayZerg";NA;505;0
"Upgrade";"ZergMissileWeaponsLevel1";NA;505;0
"Upgrade";"SprayZerg";NA;505;0
"Upgrade";"SprayZerg";NA;505;0
"Upgrade";"ZergMissileWeaponsLevel2";NA;505;0
"Upgrade";"ZergGroundArmorsLevel1";NA;505;0
"Upgrade";"overlordspeed";NA;505;0
"Upgrade";"SprayZerg";NA;505;0
"Upgrade";"EvolveMuscularAugments";NA;505;0
"Upgrade";"ZergGroundArmorsLevel2";NA;505;0
"Upgrade";"SprayZerg";NA;505;0
"Upgrade";"DiggingClaws";NA;505;0
"Upgrade";"ZergMissileWeaponsLevel3";NA;505;0
