"type";"unit_name";"on_building";"total_supply";"supply"
"Unit";"Overlord";"Larva";13;0
"Building";"Extractor";NA;17;0
"Building";"SpawningPool";NA;19;0
"Unit";"Overlord";"Larva";22;0
"Building";"Hatchery";NA;17;0
"Unit";"Zergling";"Larva";22;1
"Unit";"Zergling";"Larva";22;1
"Unit";"Zergling";"Larva";22;1
"Unit";"Zergling";"Larva";22;1
"Unit";"Zergling";"Larva";22;1
"Unit";"Zergling";"Larva";22;1
"Unit";"Queen";"Hatchery";22;2
"Unit";"Queen";"Hatchery";22;2
"Unit";"Overlord";"Larva";38;0
"Building";"BanelingNest";NA;36;0
"Unit";"Zergling";"Larva";41;1
"Unit";"Zergling";"Larva";41;1
"Unit";"Zergling";"Larva";41;1
"Unit";"Zergling";"Larva";41;1
"Unit";"Zergling";"Larva";41;1
"Unit";"Zergling";"Larva";41;1
"Unit";"Zergling";"Larva";41;1
"Unit";"Zergling";"Larva";41;1
"Unit";"Zergling";"Larva";41;1
"Unit";"Zergling";"Larva";41;1
"Unit";"Zergling";"Larva";41;1
"Unit";"Zergling";"Larva";41;1
"Unit";"Zergling";"Larva";41;1
"Unit";"Zergling";"Larva";41;1
"Unit";"Queen";"Hatchery";41;2
"Building";"Hatchery";NA;36;0
"Unit";"Zergling";"Larva";45;1
"Unit";"Zergling";"Larva";45;1
"Unit";"Zergling";"Larva";45;1
"Unit";"Zergling";"Larva";45;1
"Unit";"Baneling";"Zergling";49;0
"Unit";"Zergling";"Larva";45;1
"Unit";"Zergling";"Larva";45;1
"Unit";"Baneling";"Zergling";49;0
"Unit";"Overlord";"Larva";57;0
"Unit";"Overlord";"Larva";57;0
"Unit";"Zergling";"Larva";87;1
"Unit";"Zergling";"Larva";87;1
"Unit";"Zergling";"Larva";87;1
"Unit";"Zergling";"Larva";87;1
"Unit";"Zergling";"Larva";91;1
"Unit";"Zergling";"Larva";91;1
"Unit";"Zergling";"Larva";91;1
"Unit";"Zergling";"Larva";91;1
"Unit";"Queen";"Hatchery";85;2
"Unit";"Zergling";"Larva";91;1
"Unit";"Zergling";"Larva";91;1
"Building";"Extractor";NA;91;0
"Unit";"Zergling";"Larva";91;1
"Unit";"Zergling";"Larva";91;1
"Unit";"Zergling";"Larva";91;1
"Unit";"Zergling";"Larva";91;1
"Building";"Extractor";NA;91;0
"Unit";"Baneling";"Zergling";95;0
"Unit";"Baneling";"Zergling";95;0
"Building";"EvolutionChamber";NA;91;0
"Building";"SpineCrawler";NA;91;0
"Unit";"Zergling";"Larva";99;1
"Unit";"Zergling";"Larva";99;1
"Unit";"Zergling";"Larva";99;1
"Unit";"Zergling";"Larva";99;1
"Unit";"Zergling";"Larva";99;1
"Unit";"Zergling";"Larva";99;1
"Unit";"Zergling";"Larva";99;1
"Unit";"Zergling";"Larva";99;1
"Unit";"Zergling";"Larva";99;1
"Unit";"Zergling";"Larva";99;1
"Building";"RoachWarren";NA;91;0
"Unit";"Overlord";"Larva";118;0
"Unit";"Overlord";"Larva";118;0
"Unit";"Overlord";"Larva";118;0
"Unit";"Overlord";"Larva";118;0
"Unit";"Overlord";"Larva";118;0
"Unit";"Overlord";"Larva";122;0
"Unit";"Roach";"Larva";122;2
"Unit";"Roach";"Larva";122;2
"Unit";"Roach";"Larva";122;2
"Unit";"Roach";"Larva";122;2
"Unit";"Roach";"Larva";122;2
"Unit";"Roach";"Larva";122;2
"Unit";"Roach";"Larva";135;2
"Unit";"Roach";"Larva";135;2
"Unit";"Roach";"Larva";135;2
"Building";"Extractor";NA;135;0
"Building";"Extractor";NA;135;0
"Unit";"Roach";"Larva";135;2
"Unit";"Roach";"Larva";135;2
"Unit";"Roach";"Larva";147;2
"Unit";"Roach";"Larva";147;2
"Unit";"Roach";"Larva";151;2
"Building";"SpineCrawler";NA;135;0
"Building";"SpineCrawler";NA;135;0
"Unit";"Zergling";"Larva";153;1
"Unit";"Zergling";"Larva";153;1
"Unit";"Zergling";"Larva";153;1
"Unit";"Zergling";"Larva";153;1
"Unit";"Zergling";"Larva";153;1
"Unit";"Zergling";"Larva";153;1
"Unit";"Zergling";"Larva";153;1
"Unit";"Zergling";"Larva";153;1
"Unit";"Zergling";"Larva";153;1
"Unit";"Zergling";"Larva";153;1
"Unit";"Zergling";"Larva";153;1
"Unit";"Zergling";"Larva";153;1
"Unit";"Zergling";"Larva";153;1
"Unit";"Zergling";"Larva";153;1
"Unit";"Zergling";"Larva";153;1
"Unit";"Zergling";"Larva";153;1
"Upgrade";"ZergMissileWeaponsLevel1";"EvolutionChamber";119;0
"Unit";"Roach";"Larva";153;2
"Unit";"Roach";"Larva";159;2
"Unit";"Roach";"Larva";159;2
"Upgrade";"GlialReconstitution";"RoachWarren";137;0
"Unit";"Overlord";"Larva";189;0
"Unit";"Overlord";"Larva";189;0
"Unit";"Overlord";"Larva";189;0
"Building";"Extractor";NA;189;0
"Unit";"Overlord";"Larva";194;0
"Unit";"Overlord";"Larva";194;0
"Unit";"Overlord";"Larva";194;0
"Unit";"Overlord";"Larva";196;0
"Unit";"Overlord";"Larva";196;0
"Unit";"Overlord";"Larva";196;0
"Building";"CreepTumorQueen";NA;196;0
"Unit";"Roach";"Larva";196;2
"Unit";"Roach";"Larva";196;2
"Unit";"Roach";"Larva";196;2
"Unit";"Roach";"Larva";196;2
"Unit";"Roach";"Larva";196;2
"Unit";"Roach";"Larva";203;2
"Unit";"Roach";"Larva";203;2
"Unit";"Roach";"Larva";203;2
"Unit";"Roach";"Larva";203;2
"Building";"Hatchery";NA;194;0
"Unit";"Roach";"Larva";213;2
"Unit";"Roach";"Larva";213;2
"Unit";"Roach";"Larva";213;2
"Unit";"Roach";"Larva";213;2
"Unit";"Roach";"Larva";213;2
"Unit";"Roach";"Larva";213;2
"Unit";"Roach";"Larva";219;2
"Unit";"Roach";"Larva";219;2
"Unit";"Roach";"Larva";219;2
"Unit";"Roach";"Larva";219;2
"Unit";"Roach";"Larva";219;2
"Building";"CreepTumor";NA;225;0
"Unit";"Roach";"Larva";225;2
"Unit";"Roach";"Larva";225;2
"Unit";"Roach";"Larva";225;2
"Unit";"Roach";"Larva";225;2
"Unit";"Roach";"Larva";225;2
"Unit";"Roach";"Larva";233;2
"Unit";"Roach";"Larva";233;2
"Building";"Hatchery";NA;196;0
"Unit";"Roach";"Larva";233;2
"Unit";"Roach";"Larva";233;2
"Upgrade";"Burrow";"Hatchery";213;0
"Unit";"Roach";"Larva";243;2
"Unit";"Roach";"Larva";243;2
"Upgrade";"TunnelingClaws";"RoachWarren";213;0
"Unit";"Roach";"Larva";255;2
"Unit";"Roach";"Larva";255;2
"Unit";"Roach";"Larva";255;2
"Unit";"Roach";"Larva";255;2
"Unit";"Roach";"Larva";255;2
"Unit";"Roach";"Larva";255;2
"Unit";"Roach";"Larva";255;2
"Unit";"Roach";"Larva";255;2
"Unit";"Roach";"Larva";255;2
"Unit";"Roach";"Larva";261;2
"Unit";"Roach";"Larva";261;2
"Unit";"Roach";"Larva";261;2
"Unit";"Roach";"Larva";261;2
"Unit";"Overlord";"Larva";265;0
"Unit";"Overlord";"Larva";265;0
"Unit";"Overlord";"Larva";265;0
"Unit";"Overlord";"Larva";265;0
"Upgrade";"ZergMissileWeaponsLevel2";"EvolutionChamber";203;0
"Unit";"Overlord";"Larva";291;0
"Building";"HydraliskDen";NA;291;0
"Building";"InfestationPit";NA;291;0
"Unit";"Roach";"Larva";291;2
"Unit";"Roach";"Larva";291;2
"Unit";"Roach";"Larva";291;2
"Unit";"Roach";"Larva";291;2
"Unit";"Roach";"Larva";291;2
"Unit";"Roach";"Larva";291;2
"Unit";"Roach";"Larva";291;2
"Unit";"Roach";"Larva";291;2
"Unit";"Roach";"Larva";291;2
"Unit";"Roach";"Larva";291;2
"Unit";"Roach";"Larva";291;2
"Unit";"Roach";"Larva";291;2
"Unit";"Roach";"Larva";291;2
"Unit";"Roach";"Larva";291;2
"Unit";"Roach";"Larva";291;2
"Unit";"Roach";"Larva";291;2
"Building";"SpineCrawler";NA;291;0
"Building";"SpineCrawler";NA;291;0
"Building";"SpineCrawler";NA;291;0
"Unit";"Roach";"Larva";323;2
"Unit";"Roach";"Larva";323;2
"Unit";"Roach";"Larva";323;2
"Unit";"Roach";"Larva";323;2
"Unit";"Roach";"Larva";323;2
"Unit";"Roach";"Larva";323;2
"Unit";"Roach";"Larva";323;2
"Unit";"Roach";"Larva";323;2
"Unit";"Overlord";"Larva";323;0
"Unit";"Overlord";"Larva";323;0
"Unit";"Roach";"Larva";339;2
"Unit";"Roach";"Larva";339;2
"Unit";"Roach";"Larva";339;2
"Unit";"Roach";"Larva";339;2
"Unit";"Roach";"Larva";339;2
"Unit";"Roach";"Larva";339;2
"Unit";"Roach";"Larva";339;2
"Unit";"Roach";"Larva";339;2
"Unit";"Roach";"Larva";339;2
"Unit";"Roach";"Larva";339;2
"Unit";"Roach";"Larva";339;2
"Unit";"Roach";"Larva";339;2
"Building";"CreepTumor";NA;339;0
"Building";"Extractor";NA;339;0
"Building";"Extractor";NA;339;0
"Unit";"Roach";"Larva";363;2
"Building";"LurkerDenMP";NA;339;0
"Unit";"Roach";"Larva";363;2
"Unit";"Roach";"Larva";363;2
"Unit";"Roach";"Larva";363;2
"Unit";"Roach";"Larva";363;2
"Unit";"Roach";"Larva";363;2
"Unit";"Roach";"Larva";363;2
"Unit";"Roach";"Larva";363;2
"Unit";"Roach";"Larva";363;2
"Unit";"Roach";"Larva";363;2
"Unit";"Roach";"Larva";363;2
"Unit";"Roach";"Larva";363;2
"Unit";"Roach";"Larva";363;2
"Unit";"Roach";"Larva";363;2
"Unit";"Roach";"Larva";363;2
"Unit";"Roach";"Larva";363;2
"Unit";"Roach";"Larva";363;2
"Unit";"Roach";"Larva";363;2
"Unit";"Roach";"Larva";363;2
"Unit";"Roach";"Larva";363;2
"Unit";"Roach";"Larva";363;2
"Unit";"Roach";"Larva";363;2
"Building";"Hatchery";NA;339;0
"Unit";"Roach";"Larva";363;2
"Unit";"Roach";"Larva";363;2
"Unit";"Roach";"Larva";363;2
"Unit";"Roach";"Larva";363;2
"Unit";"Roach";"Larva";407;2
"Unit";"Roach";"Larva";407;2
"Unit";"Roach";"Larva";407;2
"Unit";"Roach";"Larva";407;2
"Building";"Hatchery";NA;363;0
"Unit";"Roach";"Larva";407;2
"Unit";"Roach";"Larva";407;2
"Unit";"Roach";"Larva";407;2
"Unit";"Roach";"Larva";407;2
"Unit";"Roach";"Larva";415;2
"Upgrade";"ZergGroundArmorsLevel1";"EvolutionChamber";363;0
"Unit";"Roach";"Larva";423;2
"Unit";"Roach";"Larva";423;2
"Unit";"Roach";"Larva";423;2
"Building";"CreepTumor";NA;431;0
"Unit";"Queen";"Hatchery";415;2
"Unit";"Hydralisk";"Larva";431;2
"Unit";"Hydralisk";"Larva";431;2
"Unit";"Hydralisk";"Larva";431;2
"Unit";"Hydralisk";"Larva";431;2
"Unit";"Roach";"Larva";443;2
"Unit";"Roach";"Larva";443;2
"Unit";"Roach";"Larva";443;2
"Unit";"Roach";"Larva";443;2
"Unit";"Roach";"Larva";443;2
"Unit";"Roach";"Larva";443;2
"Unit";"Roach";"Larva";443;2
"Unit";"Roach";"Larva";443;2
"Unit";"Roach";"Larva";443;2
"Unit";"Roach";"Larva";443;2
"Unit";"Roach";"Larva";443;2
"Unit";"Roach";"Larva";443;2
"Unit";"Roach";"Larva";443;2
"Unit";"Roach";"Larva";451;2
"Unit";"Roach";"Larva";451;2
"Unit";"Roach";"Larva";451;2
"Unit";"Roach";"Larva";451;2
"Unit";"Roach";"Larva";451;2
"Unit";"Roach";"Larva";453;2
"Unit";"Roach";"Larva";463;2
"Unit";"Roach";"Larva";463;2
"Unit";"Roach";"Larva";471;2
"Unit";"Roach";"Larva";471;2
"Unit";"Roach";"Larva";471;2
"Unit";"Roach";"Larva";471;2
"Unit";"Hydralisk";"Larva";501;2
"Unit";"Hydralisk";"Larva";501;2
"Unit";"Hydralisk";"Larva";501;2
"Building";"CreepTumor";NA;508;0
"Unit";"Hydralisk";"Larva";508;2
"Unit";"Hydralisk";"Larva";508;2
"Unit";"Hydralisk";"Larva";508;2
"Unit";"Hydralisk";"Larva";508;2
"Unit";"Hydralisk";"Larva";508;2
"Building";"Extractor";NA;514;0
"Unit";"Queen";"Hatchery";514;2
"Building";"CreepTumor";NA;524;0
"Unit";"Roach";"Larva";524;2
"Unit";"Roach";"Larva";524;2
"Unit";"Roach";"Larva";524;2
"Unit";"Roach";"Larva";524;2
"Unit";"Roach";"Larva";524;2
"Unit";"Roach";"Larva";526;2
"Unit";"Roach";"Larva";526;2
"Unit";"Roach";"Larva";526;2
"Unit";"Roach";"Larva";526;2
"Unit";"Roach";"Larva";526;2
"Unit";"Roach";"Larva";526;2
"Unit";"Roach";"Larva";526;2
"Unit";"Roach";"Larva";526;2
"Unit";"Roach";"Larva";526;2
"Building";"Hatchery";NA;514;0
"Unit";"Roach";"Larva";536;2
"Unit";"Roach";"Larva";536;2
"Unit";"Roach";"Larva";536;2
"Unit";"Roach";"Larva";536;2
"Unit";"Roach";"Larva";536;2
