"type";"unit_name";"on_building";"total_supply";"supply"
"Unit";"Overlord";"Larva";12;0
"Building";"Extractor";NA;18;0
"Building";"SpawningPool";NA;19;0
"Building";"Hatchery";NA;16;0
"Unit";"Overlord";"Larva";22;0
"Unit";"Zergling";"Larva";22;1
"Unit";"Zergling";"Larva";22;1
"Unit";"Zergling";"Larva";22;1
"Unit";"Zergling";"Larva";22;1
"Unit";"Zergling";"Larva";22;1
"Unit";"Zergling";"Larva";22;1
"Unit";"Queen";"Hatchery";22;2
"Unit";"Queen";"Hatchery";22;2
"Unit";"Zergling";"Larva";28;1
"Unit";"Zergling";"Larva";28;1
"Unit";"Zergling";"Larva";28;1
"Unit";"Zergling";"Larva";28;1
"Unit";"Zergling";"Larva";28;1
"Unit";"Zergling";"Larva";28;1
"Unit";"Zergling";"Larva";28;1
"Unit";"Zergling";"Larva";28;1
"Building";"BanelingNest";NA;28;0
"Unit";"Baneling";"Zergling";40;0
"Unit";"Baneling";"Zergling";40;0
"Unit";"Baneling";"Zergling";40;0
"Unit";"Baneling";"Zergling";40;0
"Unit";"Queen";"Hatchery";40;2
"Unit";"Baneling";"Zergling";45;0
"Unit";"Baneling";"Zergling";45;0
"Unit";"Zergling";"Larva";50;1
"Unit";"Zergling";"Larva";50;1
"Unit";"Zergling";"Larva";52;1
"Unit";"Zergling";"Larva";52;1
"Unit";"Zergling";"Larva";53;1
"Unit";"Zergling";"Larva";53;1
"Unit";"Zergling";"Larva";55;1
"Unit";"Zergling";"Larva";55;1
"Unit";"Overlord";"Larva";66;0
"Building";"CreepTumorQueen";NA;68;0
"Building";"CreepTumorQueen";NA;68;0
"Unit";"Overlord";"Larva";68;0
"Building";"RoachWarren";NA;68;0
"Building";"CreepTumor";NA;74;0
"Building";"CreepTumor";NA;77;0
"Building";"Extractor";NA;73;0
"Building";"Extractor";NA;73;0
"Unit";"Roach";"Larva";77;2
"Unit";"Roach";"Larva";77;2
"Building";"CreepTumor";NA;80;0
"Unit";"Overlord";"Larva";80;0
"Unit";"Overlord";"Larva";80;0
"Building";"CreepTumor";NA;80;0
"Unit";"Overlord";"Larva";87;0
"Unit";"Roach";"Larva";87;2
"Unit";"Roach";"Larva";87;2
"Unit";"Roach";"Larva";87;2
"Unit";"Roach";"Larva";87;2
"Unit";"Roach";"Larva";87;2
"Unit";"Roach";"Larva";87;2
"Unit";"Roach";"Larva";87;2
"Unit";"Baneling";"Zergling";101;0
"Unit";"Baneling";"Zergling";101;0
"Unit";"Baneling";"Zergling";101;0
"Unit";"Roach";"Larva";95;2
"Unit";"Roach";"Larva";95;2
"Unit";"Roach";"Larva";95;2
"Unit";"Roach";"Larva";95;2
"Unit";"Roach";"Larva";95;2
"Unit";"Overlord";"Larva";101;0
"Unit";"Overlord";"Larva";101;0
"Building";"CreepTumor";NA;111;0
"Building";"CreepTumorQueen";NA;111;0
"Unit";"Overlord";"Larva";111;0
"Building";"CreepTumorQueen";NA;111;0
"Unit";"Queen";"Hatchery";111;2
"Unit";"Roach";"Larva";114;2
"Unit";"Roach";"Larva";114;2
"Unit";"Roach";"Larva";114;2
"Unit";"Roach";"Larva";114;2
"Building";"EvolutionChamber";NA;114;0
"Unit";"Roach";"Larva";116;2
"Unit";"Roach";"Larva";116;2
"Unit";"Roach";"Larva";126;2
"Unit";"Overlord";"Larva";126;0
"Building";"CreepTumorQueen";NA;132;0
"Building";"CreepTumor";NA;132;0
"Building";"CreepTumor";NA;132;0
"Unit";"Roach";"Larva";132;2
"Building";"CreepTumorQueen";NA;132;0
"Unit";"Roach";"Larva";132;2
"Unit";"Roach";"Larva";132;2
"Unit";"Roach";"Larva";132;2
"Building";"CreepTumorQueen";NA;132;0
"Unit";"Overlord";"Larva";132;0
"Unit";"Overlord";"Larva";132;0
"Building";"CreepTumor";NA;140;0
"Building";"CreepTumor";NA;140;0
"Unit";"Overlord";"Larva";140;0
"Building";"CreepTumor";NA;140;0
"Building";"CreepTumor";NA;140;0
"Building";"CreepTumor";NA;140;0
"Building";"CreepTumorQueen";NA;140;0
"Unit";"Overlord";"Larva";140;0
"Unit";"Roach";"Larva";140;2
"Unit";"Roach";"Larva";140;2
"Unit";"Roach";"Larva";140;2
"Unit";"Roach";"Larva";140;2
"Unit";"Roach";"Larva";140;2
"Unit";"Roach";"Larva";140;2
"Unit";"Roach";"Larva";140;2
"Unit";"Roach";"Larva";140;2
"Unit";"Roach";"Larva";140;2
"Unit";"Roach";"Larva";140;2
"Unit";"Roach";"Larva";140;2
"Building";"Extractor";NA;140;0
"Upgrade";"GlialReconstitution";"RoachWarren";132;0
"Unit";"Roach";"Larva";142;2
"Unit";"Roach";"Larva";152;2
"Unit";"Roach";"Larva";162;2
"Unit";"Overlord";"Larva";162;0
"Unit";"Roach";"Larva";162;2
"Unit";"Roach";"Larva";162;2
"Unit";"Roach";"Larva";162;2
"Unit";"Overlord";"Larva";162;0
"Unit";"Overlord";"Larva";166;0
"Building";"Hatchery";NA;140;0
"Upgrade";"ZergMissileWeaponsLevel1";"EvolutionChamber";140;0
"Building";"CreepTumorQueen";NA;174;0
"Building";"CreepTumor";NA;174;0
"Building";"CreepTumor";NA;174;0
"Building";"CreepTumor";NA;174;0
"Unit";"Overlord";"Larva";174;0
"Unit";"Overlord";"Larva";174;0
"Unit";"Roach";"Larva";174;2
"Unit";"Roach";"Larva";174;2
"Unit";"Roach";"Larva";174;2
"Unit";"Roach";"Larva";174;2
"Unit";"Roach";"Larva";174;2
"Unit";"Roach";"Larva";174;2
"Unit";"Roach";"Larva";174;2
"Unit";"Roach";"Larva";174;2
"Unit";"Roach";"Larva";174;2
"Unit";"Roach";"Larva";174;2
"Unit";"Roach";"Larva";174;2
"Unit";"Roach";"Larva";174;2
"Unit";"Roach";"Larva";184;2
"Unit";"Roach";"Larva";184;2
"Unit";"Roach";"Larva";184;2
"Unit";"Roach";"Larva";188;2
"Unit";"Roach";"Larva";188;2
"Unit";"Roach";"Larva";188;2
"Building";"CreepTumor";NA;198;0
"Building";"CreepTumor";NA;200;0
"Building";"CreepTumor";NA;204;0
"Unit";"Roach";"Larva";198;2
"Unit";"Roach";"Larva";198;2
"Unit";"Roach";"Larva";198;2
"Building";"CreepTumor";NA;204;0
"Unit";"Roach";"Larva";210;2
"Unit";"Roach";"Larva";210;2
"Unit";"Roach";"Larva";210;2
"Building";"SporeCrawler";NA;216;0
"Building";"SporeCrawler";NA;216;0
"Building";"CreepTumor";NA;222;0
"Building";"CreepTumor";NA;222;0
"Building";"HydraliskDen";NA;222;0
"Building";"CreepTumor";NA;230;0
"Building";"CreepTumor";NA;230;0
"Unit";"Overlord";"Larva";222;0
"Building";"SporeCrawler";NA;222;0
"Building";"SporeCrawler";NA;222;0
"Building";"SporeCrawler";NA;222;0
"Unit";"Overlord";"Larva";230;0
"Building";"CreepTumor";NA;232;0
"Unit";"Hydralisk";"Larva";232;2
"Unit";"Overlord";"Larva";232;0
"Unit";"Hydralisk";"Larva";232;2
"Unit";"Hydralisk";"Larva";232;2
"Unit";"Overlord";"Larva";232;0
"Unit";"Overlord";"Larva";232;0
"Upgrade";"Burrow";"Hatchery";230;0
"Upgrade";"EvolveGroovedSpines";"HydraliskDen";232;0
"Unit";"Hydralisk";"Larva";238;2
"Unit";"Hydralisk";"Larva";238;2
"Unit";"Hydralisk";"Larva";238;2
"Unit";"Hydralisk";"Larva";238;2
"Upgrade";"ZergMissileWeaponsLevel2";"EvolutionChamber";222;0
"Unit";"Hydralisk";"Larva";238;2
"Unit";"Hydralisk";"Larva";238;2
"Unit";"Hydralisk";"Larva";238;2
"Building";"CreepTumor";NA;252;0
"Building";"CreepTumor";NA;252;0
"Unit";"Queen";"Hatchery";238;2
"Unit";"Hydralisk";"Larva";246;2
"Unit";"Hydralisk";"Larva";246;2
"Building";"CreepTumor";NA;252;0
"Unit";"Hydralisk";"Larva";252;2
"Unit";"Hydralisk";"Larva";252;2
"Unit";"Hydralisk";"Larva";252;2
"Building";"CreepTumor";NA;258;0
"Building";"CreepTumor";NA;258;0
"Building";"CreepTumor";NA;264;0
"Unit";"Hydralisk";"Larva";258;2
"Upgrade";"EvolveMuscularAugments";"HydraliskDen";252;0
"Building";"CreepTumor";NA;266;0
"Building";"Hatchery";NA;258;0
"Unit";"Hydralisk";"Larva";266;2
"Unit";"Hydralisk";"Larva";266;2
"Unit";"Hydralisk";"Larva";266;2
"Unit";"Hydralisk";"Larva";266;2
"Unit";"Hydralisk";"Larva";266;2
"Unit";"Hydralisk";"Larva";266;2
"Unit";"Hydralisk";"Larva";266;2
"Unit";"Hydralisk";"Larva";266;2
"Unit";"Hydralisk";"Larva";266;2
"Unit";"Hydralisk";"Larva";266;2
