"type";"unit_name";"on_building";"total_supply";"supply"
"Unit";"Overlord";"Larva";13;0
"Building";"Extractor";NA;18;0
"Unit";"Overlord";"Larva";21;0
"Building";"SpawningPool";NA;19;0
"Building";"Hatchery";NA;17;0
"Unit";"Zergling";"Larva";22;1
"Unit";"Zergling";"Larva";22;1
"Unit";"Zergling";"Larva";22;1
"Unit";"Zergling";"Larva";22;1
"Unit";"Queen";"Hatchery";22;2
"Unit";"Queen";"Hatchery";22;2
"Unit";"Overlord";"Larva";36;0
"Unit";"Zergling";"Larva";38;1
"Unit";"Zergling";"Larva";38;1
"Building";"BanelingNest";NA;36;0
"Unit";"Zergling";"Larva";41;1
"Unit";"Zergling";"Larva";41;1
"Unit";"Zergling";"Larva";41;1
"Unit";"Zergling";"Larva";41;1
"Unit";"Zergling";"Larva";41;1
"Unit";"Zergling";"Larva";41;1
"Unit";"Zergling";"Larva";41;1
"Unit";"Zergling";"Larva";41;1
"Unit";"Zergling";"Larva";41;1
"Unit";"Zergling";"Larva";41;1
"Unit";"Zergling";"Larva";41;1
"Unit";"Zergling";"Larva";41;1
"Unit";"Zergling";"Larva";41;1
"Unit";"Zergling";"Larva";41;1
"Unit";"Zergling";"Larva";41;1
"Unit";"Zergling";"Larva";41;1
"Unit";"Zergling";"Larva";43;1
"Unit";"Zergling";"Larva";43;1
"Building";"Hatchery";NA;35;0
"Unit";"Overlord";"Larva";53;0
"Unit";"Overlord";"Larva";57;0
"Unit";"Baneling";"Zergling";59;0
"Unit";"Baneling";"Zergling";59;0
"Unit";"Baneling";"Zergling";59;0
"Unit";"Baneling";"Zergling";59;0
"Unit";"Zergling";"Larva";69;1
"Unit";"Zergling";"Larva";69;1
"Unit";"Zergling";"Larva";70;1
"Unit";"Zergling";"Larva";70;1
"Unit";"Zergling";"Larva";70;1
"Unit";"Zergling";"Larva";70;1
"Unit";"Zergling";"Larva";70;1
"Unit";"Zergling";"Larva";70;1
"Unit";"Zergling";"Larva";71;1
"Unit";"Zergling";"Larva";71;1
"Unit";"Zergling";"Larva";71;1
"Unit";"Zergling";"Larva";71;1
"Unit";"Zergling";"Larva";71;1
"Unit";"Zergling";"Larva";71;1
"Unit";"Zergling";"Larva";71;1
"Unit";"Zergling";"Larva";71;1
"Unit";"Baneling";"Zergling";72;0
"Unit";"Baneling";"Zergling";72;0
"Unit";"Zergling";"Larva";72;1
"Unit";"Zergling";"Larva";72;1
"Unit";"Zergling";"Larva";72;1
"Unit";"Zergling";"Larva";72;1
"Unit";"Zergling";"Larva";72;1
"Unit";"Zergling";"Larva";72;1
"Building";"EvolutionChamber";NA;72;0
"Unit";"Queen";"Hatchery";88;2
"Unit";"Overlord";"Larva";96;0
"Building";"RoachWarren";NA;88;0
"Building";"Extractor";NA;102;0
"Building";"Extractor";NA;102;0
"Unit";"Overlord";"Larva";107;0
"Unit";"Roach";"Larva";111;2
"Unit";"Roach";"Larva";111;2
"Unit";"Roach";"Larva";111;2
"Unit";"Roach";"Larva";111;2
"Unit";"Overlord";"Larva";117;0
"Building";"Extractor";NA;117;0
"Building";"Extractor";NA;117;0
"Unit";"Roach";"Larva";117;2
"Unit";"Roach";"Larva";117;2
"Unit";"Overlord";"Larva";125;0
"Unit";"Overlord";"Larva";125;0
"Unit";"Overlord";"Larva";125;0
"Unit";"Roach";"Larva";137;2
"Unit";"Roach";"Larva";137;2
"Unit";"Roach";"Larva";137;2
"Unit";"Roach";"Larva";137;2
"Unit";"Roach";"Larva";137;2
"Unit";"Overlord";"Larva";141;0
"Unit";"Overlord";"Larva";143;0
"Unit";"Roach";"Larva";147;2
"Unit";"Roach";"Larva";147;2
"Unit";"Roach";"Larva";147;2
"Upgrade";"ZergMissileWeaponsLevel1";"EvolutionChamber";117;0
"Upgrade";"GlialReconstitution";"RoachWarren";129;0
"Unit";"Roach";"Larva";147;2
"Unit";"Queen";"Hatchery";137;2
"Unit";"Roach";"Larva";151;2
"Unit";"Roach";"Larva";151;2
"Unit";"Roach";"Larva";151;2
"Unit";"Roach";"Larva";151;2
"Unit";"Roach";"Larva";151;2
"Unit";"Roach";"Larva";151;2
"Unit";"Roach";"Larva";155;2
"Unit";"Roach";"Larva";155;2
"Unit";"Roach";"Larva";155;2
"Unit";"Roach";"Larva";157;2
"Building";"Hatchery";NA;129;0
"Unit";"Roach";"Larva";161;2
"Unit";"Roach";"Larva";161;2
"Unit";"Roach";"Larva";169;2
"Unit";"Overlord";"Larva";169;0
"Building";"EvolutionChamber";NA;173;0
"Unit";"Roach";"Larva";185;2
"Unit";"Roach";"Larva";185;2
"Unit";"Roach";"Larva";185;2
"Unit";"Roach";"Larva";187;2
"Unit";"Roach";"Larva";187;2
"Unit";"Roach";"Larva";187;2
"Unit";"Roach";"Larva";187;2
"Unit";"Overlord";"Larva";187;0
"Unit";"Roach";"Larva";187;2
"Unit";"Roach";"Larva";189;2
"Unit";"Roach";"Larva";199;2
"Unit";"Roach";"Larva";199;2
"Unit";"Roach";"Larva";199;2
"Unit";"Roach";"Larva";199;2
"Unit";"Roach";"Larva";199;2
"Unit";"Roach";"Larva";208;2
"Unit";"Roach";"Larva";208;2
"Unit";"Roach";"Larva";208;2
"Unit";"Roach";"Larva";208;2
"Unit";"Roach";"Larva";208;2
"Unit";"Roach";"Larva";208;2
"Building";"Hatchery";NA;187;0
"Unit";"Roach";"Larva";231;2
"Unit";"Roach";"Larva";234;2
"Unit";"Roach";"Larva";235;2
"Unit";"Roach";"Larva";237;2
"Unit";"Roach";"Larva";237;2
"Unit";"Roach";"Larva";237;2
"Unit";"Roach";"Larva";237;2
"Unit";"Roach";"Larva";237;2
"Unit";"Roach";"Larva";237;2
"Unit";"Roach";"Larva";241;2
"Unit";"Roach";"Larva";241;2
"Unit";"Roach";"Larva";243;2
"Unit";"Roach";"Larva";247;2
"Unit";"Roach";"Larva";247;2
"Unit";"Roach";"Larva";247;2
"Unit";"Roach";"Larva";249;2
"Unit";"Roach";"Larva";249;2
"Unit";"Roach";"Larva";249;2
"Unit";"Roach";"Larva";255;2
"Unit";"Roach";"Larva";255;2
"Upgrade";"ZergMissileWeaponsLevel2";"EvolutionChamber";201;0
"Unit";"Roach";"Larva";261;2
"Unit";"Roach";"Larva";261;2
"Unit";"Roach";"Larva";261;2
"Unit";"Roach";"Larva";261;2
"Unit";"Roach";"Larva";267;2
"Unit";"Roach";"Larva";269;2
"Unit";"Roach";"Larva";271;2
"Unit";"Overlord";"Larva";277;0
"Unit";"Overlord";"Larva";277;0
"Unit";"Overlord";"Larva";291;0
"Unit";"Overlord";"Larva";291;0
"Unit";"Overlord";"Larva";291;0
"Upgrade";"ZergGroundArmorsLevel1";"EvolutionChamber";237;0
"Unit";"Roach";"Larva";291;2
"Unit";"Roach";"Larva";291;2
"Unit";"Roach";"Larva";291;2
"Unit";"Roach";"Larva";291;2
"Unit";"Roach";"Larva";291;2
"Unit";"Roach";"Larva";291;2
"Unit";"Roach";"Larva";291;2
"Unit";"Roach";"Larva";291;2
"Unit";"Roach";"Larva";291;2
"Unit";"Roach";"Larva";297;2
"Unit";"Roach";"Larva";297;2
"Unit";"Roach";"Larva";297;2
"Unit";"Roach";"Larva";297;2
"Building";"Hatchery";NA;285;0
"Unit";"Overlord";"Larva";309;0
"Unit";"Overlord";"Larva";309;0
"Unit";"Overlord";"Larva";309;0
"Unit";"Overlord";"Larva";309;0
"Unit";"Roach";"Larva";317;2
"Unit";"Roach";"Larva";317;2
"Unit";"Roach";"Larva";317;2
"Unit";"Roach";"Larva";317;2
"Unit";"Roach";"Larva";317;2
"Unit";"Roach";"Larva";317;2
"Unit";"Roach";"Larva";317;2
"Unit";"Roach";"Larva";317;2
"Unit";"Roach";"Larva";317;2
"Unit";"Roach";"Larva";317;2
"Unit";"Roach";"Larva";317;2
"Unit";"Roach";"Larva";317;2
"Unit";"Roach";"Larva";329;2
"Unit";"Roach";"Larva";329;2
"Unit";"Roach";"Larva";329;2
"Unit";"Roach";"Larva";329;2
"Unit";"Roach";"Larva";329;2
"Unit";"Roach";"Larva";329;2
"Unit";"Roach";"Larva";341;2
"Unit";"Roach";"Larva";341;2
"Unit";"Roach";"Larva";341;2
"Unit";"Roach";"Larva";353;2
"Unit";"Roach";"Larva";353;2
"Unit";"Roach";"Larva";353;2
"Unit";"Roach";"Larva";353;2
"Unit";"Roach";"Larva";359;2
"Unit";"Roach";"Larva";359;2
"Upgrade";"ZergGroundArmorsLevel2";"EvolutionChamber";317;0
"Unit";"Roach";"Larva";367;2
"Unit";"Roach";"Larva";367;2
"Unit";"Roach";"Larva";367;2
"Unit";"Roach";"Larva";367;2
"Unit";"Roach";"Larva";367;2
"Unit";"Roach";"Larva";367;2
"Unit";"Roach";"Larva";367;2
"Unit";"Roach";"Larva";371;2
"Unit";"Roach";"Larva";371;2
"Unit";"Roach";"Larva";371;2
"Unit";"Roach";"Larva";371;2
"Unit";"Roach";"Larva";371;2
"Unit";"Roach";"Larva";371;2
"Unit";"Roach";"Larva";371;2
"Unit";"Roach";"Larva";371;2
"Unit";"Roach";"Larva";385;2
"Unit";"Roach";"Larva";385;2
"Unit";"Roach";"Larva";385;2
"Unit";"Roach";"Larva";385;2
"Unit";"Roach";"Larva";385;2
