"type";"unit_name";"on_building";"total_supply";"supply"
"Unit";"Overlord";"Larva";13;0
"Building";"SpawningPool";NA;12;0
"Unit";"Zergling";"Larva";15;1
"Unit";"Zergling";"Larva";15;1
"Unit";"Zergling";"Larva";15;1
"Unit";"Zergling";"Larva";15;1
"Unit";"Zergling";"Larva";15;1
"Unit";"Zergling";"Larva";15;1
"Unit";"Zergling";"Larva";15;1
"Unit";"Zergling";"Larva";15;1
"Unit";"Zergling";"Larva";21;1
"Unit";"Zergling";"Larva";21;1
"Unit";"Zergling";"Larva";23;1
"Unit";"Zergling";"Larva";23;1
"Unit";"Overlord";"Larva";25;0
"Unit";"Queen";"Hatchery";23;2
"Building";"Hatchery";NA;19;0
"Unit";"Queen";"Hatchery";28;2
"Building";"CreepTumorQueen";NA;34;0
"Unit";"Queen";"Hatchery";31;2
"Building";"SpineCrawler";NA;33;0
"Unit";"Overlord";"Larva";41;0
"Building";"EvolutionChamber";NA;45;0
"Building";"EvolutionChamber";NA;45;0
"Building";"Extractor";NA;54;0
"Building";"Extractor";NA;54;0
"Building";"Extractor";NA;54;0
"Building";"RoachWarren";NA;52;0
"Unit";"Overlord";"Larva";64;0
"Unit";"Overlord";"Larva";64;0
"Building";"CreepTumor";NA;65;0
"Unit";"Overlord";"Larva";65;0
"Unit";"Zergling";"Larva";65;1
"Unit";"Zergling";"Larva";65;1
"Unit";"Zergling";"Larva";65;1
"Unit";"Zergling";"Larva";65;1
"Unit";"Zergling";"Larva";65;1
"Unit";"Zergling";"Larva";65;1
"Unit";"Zergling";"Larva";65;1
"Unit";"Zergling";"Larva";65;1
"Unit";"Roach";"Larva";65;2
"Unit";"Roach";"Larva";65;2
"Unit";"Roach";"Larva";65;2
"Building";"CreepTumor";NA;83;0
"Unit";"Overlord";"Larva";83;0
"Unit";"Overlord";"Larva";83;0
"Unit";"Overlord";"Larva";83;0
"Building";"CreepTumorQueen";NA;102;0
"Building";"Hatchery";NA;83;0
"Upgrade";"ZergMissileWeaponsLevel1";"EvolutionChamber";82;0
"Unit";"Roach";"Larva";98;2
"Unit";"Roach";"Larva";102;2
"Unit";"Roach";"Larva";102;2
"Unit";"Roach";"Larva";102;2
"Unit";"Roach";"Larva";102;2
"Unit";"Overlord";"Larva";102;0
"Unit";"Roach";"Larva";102;2
"Unit";"Roach";"Larva";102;2
"Upgrade";"GlialReconstitution";"RoachWarren";93;0
"Unit";"Roach";"Larva";106;2
"Unit";"Overlord";"Larva";112;0
"Unit";"Roach";"Larva";112;2
"Unit";"Overlord";"Larva";112;0
"Unit";"Overlord";"Larva";112;0
"Unit";"Roach";"Larva";116;2
"Unit";"Roach";"Larva";116;2
"Unit";"Roach";"Larva";116;2
"Unit";"Roach";"Larva";116;2
"Building";"Hatchery";NA;95;0
"Unit";"Roach";"Larva";118;2
"Unit";"Roach";"Larva";120;2
"Unit";"Roach";"Larva";120;2
"Unit";"Roach";"Larva";120;2
"Unit";"Roach";"Larva";120;2
"Unit";"Roach";"Larva";120;2
"Unit";"Roach";"Larva";120;2
"Unit";"Roach";"Larva";120;2
"Unit";"Roach";"Larva";120;2
"Unit";"Roach";"Larva";128;2
"Unit";"Roach";"Larva";128;2
"Unit";"Roach";"Larva";128;2
"Unit";"Roach";"Larva";128;2
"Unit";"Roach";"Larva";128;2
"Unit";"Roach";"Larva";128;2
"Unit";"Roach";"Larva";130;2
"Unit";"Roach";"Larva";130;2
"Unit";"Roach";"Larva";130;2
"Unit";"Roach";"Larva";130;2
"Unit";"Overlord";"Larva";146;0
"Unit";"Roach";"Larva";148;2
"Unit";"Overlord";"Larva";166;0
"Unit";"Overlord";"Larva";166;0
"Unit";"Overlord";"Larva";166;0
"Unit";"Roach";"Larva";166;2
"Unit";"Roach";"Larva";166;2
"Unit";"Overlord";"Larva";166;0
"Unit";"Roach";"Larva";166;2
"Unit";"Roach";"Larva";166;2
"Unit";"Overlord";"Larva";168;0
"Unit";"Roach";"Larva";168;2
"Unit";"Roach";"Larva";168;2
"Unit";"Roach";"Larva";168;2
"Unit";"Roach";"Larva";168;2
"Unit";"Roach";"Larva";168;2
"Unit";"Roach";"Larva";168;2
"Unit";"Roach";"Larva";176;2
"Unit";"Roach";"Larva";176;2
"Unit";"Roach";"Larva";185;2
"Unit";"Roach";"Larva";185;2
"Building";"Hatchery";NA;148;0
"Unit";"Roach";"Larva";198;2
"Unit";"Roach";"Larva";198;2
"Unit";"Roach";"Larva";198;2
"Unit";"Roach";"Larva";198;2
"Unit";"Roach";"Larva";198;2
"Unit";"Roach";"Larva";198;2
"Unit";"Roach";"Larva";198;2
"Unit";"Roach";"Larva";198;2
"Unit";"Roach";"Larva";198;2
"Unit";"Roach";"Larva";206;2
"Unit";"Roach";"Larva";206;2
"Unit";"Roach";"Larva";206;2
"Unit";"Roach";"Larva";208;2
"Unit";"Roach";"Larva";210;2
"Unit";"Roach";"Larva";212;2
"Unit";"Roach";"Larva";216;2
"Unit";"Roach";"Larva";216;2
"Unit";"Roach";"Larva";216;2
"Unit";"Roach";"Larva";224;2
"Unit";"Roach";"Larva";224;2
"Upgrade";"ZergGroundArmorsLevel1";"EvolutionChamber";168;0
"Unit";"Roach";"Larva";232;2
"Building";"Extractor";NA;228;0
"Building";"Extractor";NA;230;0
"Unit";"Roach";"Larva";240;2
"Unit";"Roach";"Larva";240;2
"Unit";"Roach";"Larva";242;2
"Unit";"Roach";"Larva";242;2
"Unit";"Roach";"Larva";246;2
"Upgrade";"ZergMissileWeaponsLevel2";"EvolutionChamber";168;0
"Unit";"Roach";"Larva";246;2
"Unit";"Overlord";"Larva";248;0
"Unit";"Roach";"Larva";248;2
"Unit";"Roach";"Larva";248;2
"Building";"Extractor";NA;248;0
"Unit";"Roach";"Larva";248;2
"Unit";"Roach";"Larva";254;2
"Unit";"Roach";"Larva";254;2
"Unit";"Roach";"Larva";256;2
"Unit";"Queen";"Hatchery";248;2
"Unit";"Roach";"Larva";260;2
"Unit";"Roach";"Larva";260;2
"Unit";"Roach";"Larva";262;2
"Unit";"Roach";"Larva";262;2
"Unit";"Roach";"Larva";266;2
"Unit";"Roach";"Larva";266;2
"Unit";"Roach";"Larva";266;2
"Unit";"Roach";"Larva";266;2
"Unit";"Roach";"Larva";266;2
"Unit";"Roach";"Larva";270;2
"Unit";"Roach";"Larva";272;2
"Unit";"Queen";"Hatchery";256;2
"Unit";"Roach";"Larva";282;2
"Unit";"Roach";"Larva";282;2
"Unit";"Overlord";"Larva";293;0
"Unit";"Roach";"Larva";293;2
"Unit";"Overlord";"Larva";295;0
"Building";"SporeCrawler";NA;301;0
"Building";"SporeCrawler";NA;307;0
"Unit";"Roach";"Larva";307;2
"Unit";"Roach";"Larva";307;2
"Building";"SporeCrawler";NA;307;0
"Unit";"Roach";"Larva";311;2
"Unit";"Roach";"Larva";311;2
"Unit";"Roach";"Larva";313;2
"Unit";"Roach";"Larva";313;2
"Unit";"Roach";"Larva";313;2
"Unit";"Roach";"Larva";313;2
"Unit";"Roach";"Larva";313;2
"Unit";"Roach";"Larva";313;2
"Unit";"Roach";"Larva";313;2
"Unit";"Roach";"Larva";313;2
"Unit";"Roach";"Larva";317;2
"Unit";"Overlord";"Larva";333;0
"Unit";"Roach";"Larva";339;2
"Unit";"Roach";"Larva";339;2
"Unit";"Roach";"Larva";339;2
"Unit";"Roach";"Larva";339;2
"Unit";"Roach";"Larva";339;2
"Unit";"Roach";"Larva";339;2
"Unit";"Roach";"Larva";339;2
"Unit";"Roach";"Larva";339;2
"Unit";"Roach";"Larva";339;2
"Unit";"Roach";"Larva";339;2
"Unit";"Roach";"Larva";339;2
"Unit";"Roach";"Larva";339;2
"Unit";"Roach";"Larva";339;2
"Unit";"Roach";"Larva";339;2
"Unit";"Roach";"Larva";339;2
"Unit";"Roach";"Larva";339;2
"Unit";"Roach";"Larva";339;2
"Unit";"Roach";"Larva";339;2
"Unit";"Roach";"Larva";339;2
"Unit";"Roach";"Larva";339;2
"Unit";"Roach";"Larva";339;2
"Unit";"Roach";"Larva";339;2
"Unit";"Roach";"Larva";339;2
