"type";"unit_name";"on_building";"total_supply_lag";"supply"
"Unit";"Overlord";"Larva";13;0
"Building";"SpawningPool";NA;16;0
"Building";"Hatchery";NA;18;0
"Unit";"Zergling";"Larva";19;1
"Unit";"Zergling";"Larva";20;1
"Unit";"Zergling";"Larva";21;1
"Unit";"Zergling";"Larva";22;1
"Unit";"Zergling";"Larva";23;1
"Unit";"Zergling";"Larva";24;1
"Unit";"Queen";"Hatchery";25;2
"Unit";"Zergling";"Larva";27;1
"Unit";"Zergling";"Larva";28;1
"Building";"Extractor";NA;29;0
"Unit";"Zergling";"Larva";29;1
"Unit";"Zergling";"Larva";30;1
"Unit";"Zergling";"Larva";31;1
"Unit";"Zergling";"Larva";32;1
"Unit";"Overlord";"Larva";33;0
"Unit";"Queen";"Hatchery";33;2
"Unit";"Queen";"Hatchery";36;2
"Unit";"Zergling";"Larva";39;1
"Unit";"Zergling";"Larva";40;1
"Building";"CreepTumorQueen";NA;41;0
"Unit";"Overlord";"Larva";42;0
"Building";"CreepTumor";NA;45;0
"Unit";"Overlord";"Larva";48;0
"Building";"CreepTumorQueen";NA;48;0
"Building";"BanelingNest";NA;54;0
"Unit";"Zergling";"Larva";54;1
"Unit";"Zergling";"Larva";55;1
"Unit";"Zergling";"Larva";56;1
"Unit";"Zergling";"Larva";57;1
"Unit";"Zergling";"Larva";58;1
"Unit";"Zergling";"Larva";59;1
"Unit";"Zergling";"Larva";60;1
"Unit";"Zergling";"Larva";61;1
"Unit";"Overlord";"Larva";62;0
"Building";"CreepTumor";NA;62;0
"Building";"CreepTumor";NA;62;0
"Unit";"Zergling";"Larva";62;1
"Unit";"Zergling";"Larva";63;1
"Building";"EvolutionChamber";NA;64;0
"Building";"RoachWarren";NA;64;0
"Unit";"Baneling";"Zergling";71;0
"Unit";"Overlord";"Larva";71;0
"Unit";"Baneling";"Zergling";71;0
"Unit";"Baneling";"Zergling";71;0
"Building";"Hatchery";NA;75;0
"Building";"Extractor";NA;76;0
"Building";"CreepTumor";NA;76;0
"Unit";"Queen";"Hatchery";76;2
"Building";"CreepTumor";NA;78;0
"Unit";"Roach";"Larva";78;2
"Unit";"Roach";"Larva";80;2
"Unit";"Roach";"Larva";82;2
"Unit";"Roach";"Larva";84;2
"Unit";"Zergling";"Larva";86;1
"Unit";"Zergling";"Larva";87;1
"Unit";"Zergling";"Larva";88;1
"Unit";"Zergling";"Larva";89;1
"Unit";"Zergling";"Larva";90;1
"Unit";"Zergling";"Larva";91;1
"Building";"Extractor";NA;92;0
"Unit";"Roach";"Larva";92;2
"Unit";"Zergling";"Larva";94;1
"Unit";"Zergling";"Larva";95;1
"Unit";"Zergling";"Larva";96;1
"Unit";"Zergling";"Larva";97;1
"Unit";"Zergling";"Larva";98;1
"Unit";"Zergling";"Larva";99;1
"Unit";"Zergling";"Larva";100;1
"Unit";"Zergling";"Larva";101;1
"Unit";"Zergling";"Larva";102;1
"Unit";"Zergling";"Larva";103;1
"Unit";"Overlord";"Larva";104;0
"Unit";"Overlord";"Larva";104;0
"Building";"CreepTumor";NA;104;0
"Unit";"Overlord";"Larva";108;0
"Unit";"Overlord";"Larva";108;0
"Unit";"Overlord";"Larva";108;0
"Unit";"Overlord";"Larva";108;0
"Unit";"Overlord";"Larva";108;0
"Building";"CreepTumor";NA;108;0
"Unit";"Baneling";"Zergling";109;0
"Unit";"Baneling";"Zergling";109;0
"Unit";"Baneling";"Zergling";109;0
"Unit";"Overlord";"Larva";109;0
"Unit";"Zergling";"Larva";109;1
"Unit";"Zergling";"Larva";110;1
"Unit";"Zergling";"Larva";111;1
"Unit";"Zergling";"Larva";112;1
"Unit";"Zergling";"Larva";113;1
"Unit";"Zergling";"Larva";114;1
"Unit";"Zergling";"Larva";115;1
"Unit";"Zergling";"Larva";116;1
"Unit";"Zergling";"Larva";117;1
"Unit";"Zergling";"Larva";118;1
"Unit";"Zergling";"Larva";119;1
"Unit";"Zergling";"Larva";120;1
"Unit";"Roach";"Larva";121;2
"Unit";"Roach";"Larva";123;2
"Unit";"Roach";"Larva";125;2
"Unit";"Roach";"Larva";127;2
"Unit";"Roach";"Larva";129;2
"Unit";"Roach";"Larva";131;2
"Unit";"Roach";"Larva";133;2
"Unit";"Roach";"Larva";135;2
"Unit";"Baneling";"Zergling";143;0
"Unit";"Baneling";"Zergling";143;0
"Unit";"Zergling";"Larva";150;1
"Unit";"Zergling";"Larva";151;1
"Unit";"Zergling";"Larva";152;1
"Unit";"Zergling";"Larva";153;1
"Unit";"Zergling";"Larva";154;1
"Unit";"Zergling";"Larva";155;1
"Unit";"Zergling";"Larva";156;1
"Unit";"Zergling";"Larva";157;1
"Unit";"Zergling";"Larva";158;1
"Unit";"Zergling";"Larva";159;1
"Unit";"Zergling";"Larva";160;1
"Unit";"Zergling";"Larva";161;1
"Unit";"Zergling";"Larva";162;1
"Unit";"Zergling";"Larva";163;1
"Unit";"Zergling";"Larva";164;1
"Unit";"Zergling";"Larva";165;1
"Unit";"Zergling";"Larva";166;1
"Unit";"Zergling";"Larva";167;1
"Unit";"Zergling";"Larva";168;1
"Unit";"Zergling";"Larva";169;1
"Unit";"Zergling";"Larva";170;1
"Unit";"Zergling";"Larva";171;1
"Unit";"Zergling";"Larva";172;1
"Unit";"Zergling";"Larva";173;1
"Unit";"Zergling";"Larva";174;1
"Unit";"Zergling";"Larva";175;1
"Unit";"Zergling";"Larva";176;1
"Unit";"Zergling";"Larva";177;1
"Unit";"Zergling";"Larva";178;1
"Unit";"Zergling";"Larva";179;1
"Unit";"Zergling";"Larva";180;1
"Unit";"Zergling";"Larva";181;1
"Unit";"Zergling";"Larva";182;1
"Unit";"Zergling";"Larva";183;1
"Unit";"Roach";"Larva";184;2
"Unit";"Roach";"Larva";186;2
"Unit";"Roach";"Larva";188;2
"Unit";"Roach";"Larva";190;2
"Unit";"Roach";"Larva";192;2
"Unit";"Roach";"Larva";194;2
"Unit";"Roach";"Larva";196;2
"Unit";"Roach";"Larva";198;2
"Unit";"Roach";"Larva";200;2
"Unit";"Baneling";"Zergling";202;0
"Unit";"Baneling";"Zergling";202;0
"Unit";"Baneling";"Zergling";202;0
"Unit";"Baneling";"Zergling";202;0
"Unit";"Roach";"Larva";202;2
"Unit";"Roach";"Larva";204;2
"Unit";"Roach";"Larva";206;2
"Unit";"Roach";"Larva";208;2
"Unit";"Roach";"Larva";210;2
"Unit";"Roach";"Larva";212;2
"Unit";"Roach";"Larva";214;2
"Unit";"Roach";"Larva";216;2
"Unit";"Roach";"Larva";218;2
"Unit";"Roach";"Larva";220;2
"Unit";"Roach";"Larva";222;2
"Unit";"Roach";"Larva";224;2
"Unit";"Roach";"Larva";226;2
"Unit";"Roach";"Larva";228;2
"Unit";"Roach";"Larva";230;2
"Upgrade";"GlialReconstitution";"RoachWarren";232;0
"Unit";"Roach";"Larva";232;2
"Unit";"Roach";"Larva";234;2
"Unit";"Roach";"Larva";236;2
"Unit";"Roach";"Larva";238;2
"Unit";"Overlord";"Larva";253;0
"Unit";"Queen";"Hatchery";253;2
"Unit";"Overlord";"Larva";255;0
"Unit";"Queen";"Hatchery";255;2
"Unit";"Roach";"Larva";257;2
"Unit";"Roach";"Larva";259;2
"Unit";"Roach";"Larva";261;2
"Unit";"Roach";"Larva";263;2
"Building";"SporeCrawler";NA;265;0
"Building";"SporeCrawler";NA;265;0
"Unit";"Roach";"Larva";265;2
"Unit";"Roach";"Larva";267;2
"Unit";"Queen";"Hatchery";269;2
"Unit";"Roach";"Larva";271;2
"Unit";"Roach";"Larva";273;2
"Building";"CreepTumor";NA;275;0
"Unit";"Roach";"Larva";275;2
"Unit";"Roach";"Larva";277;2
"Unit";"Roach";"Larva";279;2
"Unit";"Roach";"Larva";281;2
"Unit";"Roach";"Larva";283;2
"Unit";"Roach";"Larva";285;2
"Unit";"Roach";"Larva";287;2
"Unit";"Roach";"Larva";289;2
"Unit";"Roach";"Larva";291;2
"Building";"SporeCrawler";NA;293;0
"Unit";"Zergling";"Larva";293;1
"Unit";"Zergling";"Larva";294;1
"Unit";"Zergling";"Larva";295;1
"Unit";"Zergling";"Larva";296;1
"Unit";"Zergling";"Larva";297;1
"Unit";"Zergling";"Larva";298;1
"Unit";"Zergling";"Larva";299;1
"Unit";"Zergling";"Larva";300;1
"Unit";"Zergling";"Larva";301;1
"Unit";"Zergling";"Larva";302;1
"Unit";"Queen";"Hatchery";303;2
"Unit";"Queen";"Hatchery";305;2
"Building";"RoachWarren";NA;307;0
"Unit";"Queen";"Hatchery";307;2
"Unit";"Queen";"Hatchery";309;2
"Unit";"Queen";"Hatchery";311;2
"Unit";"Overlord";"Larva";321;0
"Building";"Extractor";NA;321;0
"Building";"Extractor";NA;321;0
"Building";"Extractor";NA;321;0
"Unit";"Queen";"Hatchery";321;2
"Building";"CreepTumor";NA;323;0
"Unit";"Roach";"Larva";323;2
"Unit";"Roach";"Larva";325;2
"Unit";"Roach";"Larva";327;2
"Unit";"Roach";"Larva";329;2
"Unit";"Roach";"Larva";331;2
"Unit";"Roach";"Larva";333;2
"Unit";"Roach";"Larva";335;2
"Unit";"Roach";"Larva";337;2
"Unit";"Roach";"Larva";339;2
"Unit";"Roach";"Larva";341;2
"Unit";"Roach";"Larva";343;2
"Unit";"Queen";"Hatchery";345;2
"Building";"CreepTumor";NA;347;0
"Unit";"Roach";"Larva";347;2
"Unit";"Roach";"Larva";349;2
"Unit";"Roach";"Larva";351;2
"Unit";"Roach";"Larva";353;2
"Unit";"Roach";"Larva";355;2
"Unit";"Roach";"Larva";357;2
"Unit";"Overlord";"Larva";359;0
"Unit";"Overlord";"Larva";359;0
"Upgrade";"Burrow";"Hatchery";359;0
"Unit";"Overlord";"Larva";359;0
"Unit";"Overlord";"Larva";359;0
"Unit";"Overlord";"Larva";359;0
"Upgrade";"TunnelingClaws";"RoachWarren";359;0
"Unit";"Queen";"Hatchery";359;2
"Unit";"Queen";"Hatchery";361;2
"Unit";"Overlord";"Larva";363;0
"Unit";"Overlord";"Larva";363;0
"Building";"SporeCrawler";NA;363;0
"Building";"SporeCrawler";NA;363;0
"Unit";"Overlord";"Larva";363;0
"Unit";"Overlord";"Larva";363;0
"Unit";"Roach";"Larva";363;2
"Unit";"Roach";"Larva";365;2
"Unit";"Roach";"Larva";367;2
"Unit";"Roach";"Larva";369;2
"Unit";"Roach";"Larva";371;2
"Unit";"Roach";"Larva";373;2
"Unit";"Roach";"Larva";375;2
"Unit";"Roach";"Larva";377;2
"Unit";"Roach";"Larva";379;2
"Unit";"Roach";"Larva";381;2
"Unit";"Roach";"Larva";383;2
"Unit";"Roach";"Larva";385;2
"Unit";"Roach";"Larva";387;2
"Unit";"Roach";"Larva";389;2
"Unit";"Roach";"Larva";391;2
"Unit";"Roach";"Larva";393;2
"Unit";"Roach";"Larva";395;2
"Building";"CreepTumor";NA;397;0
"Unit";"Roach";"Larva";397;2
"Unit";"Roach";"Larva";399;2
"Unit";"Roach";"Larva";401;2
"Unit";"Roach";"Larva";403;2
"Unit";"Roach";"Larva";405;2
"Unit";"Roach";"Larva";407;2
"Unit";"Roach";"Larva";409;2
"Upgrade";"SprayZerg";NA;411;0
"Upgrade";"SprayZerg";NA;411;0
"Upgrade";"zerglingmovementspeed";NA;411;0
"Upgrade";"SprayZerg";NA;411;0
"Upgrade";"SprayZerg";NA;411;0
"Upgrade";"ZergMissileWeaponsLevel1";NA;411;0
"Upgrade";"ZergMissileWeaponsLevel2";NA;411;0
