"type";"unit_name";"on_building";"total_supply";"supply"
"Unit";"Overlord";"Larva";12;0
"Building";"Extractor";NA;16;0
"Building";"SpawningPool";NA;17;0
"Unit";"Overlord";"Larva";21;0
"Unit";"Zergling";"Larva";21;1
"Unit";"Zergling";"Larva";21;1
"Unit";"Queen";"Hatchery";21;2
"Unit";"Zergling";"Larva";23;1
"Unit";"Zergling";"Larva";23;1
"Building";"Hatchery";NA;20;0
"Unit";"Zergling";"Larva";28;1
"Unit";"Zergling";"Larva";28;1
"Unit";"Zergling";"Larva";29;1
"Unit";"Zergling";"Larva";29;1
"Unit";"Queen";"Hatchery";24;2
"Unit";"Zergling";"Larva";29;1
"Unit";"Zergling";"Larva";29;1
"Building";"SpineCrawler";NA;29;0
"Building";"BanelingNest";NA;28;0
"Unit";"Zergling";"Larva";33;1
"Unit";"Zergling";"Larva";33;1
"Unit";"Queen";"Hatchery";31;2
"Unit";"Zergling";"Larva";37;1
"Unit";"Zergling";"Larva";37;1
"Unit";"Zergling";"Larva";37;1
"Unit";"Zergling";"Larva";37;1
"Unit";"Zergling";"Larva";37;1
"Unit";"Zergling";"Larva";37;1
"Unit";"Zergling";"Larva";40;1
"Unit";"Zergling";"Larva";40;1
"Unit";"Zergling";"Larva";40;1
"Unit";"Zergling";"Larva";40;1
"Unit";"Zergling";"Larva";40;1
"Unit";"Zergling";"Larva";40;1
"Unit";"Zergling";"Larva";40;1
"Unit";"Zergling";"Larva";40;1
"Unit";"Zergling";"Larva";48;1
"Unit";"Zergling";"Larva";48;1
"Unit";"Zergling";"Larva";58;1
"Unit";"Zergling";"Larva";58;1
"Unit";"Zergling";"Larva";58;1
"Unit";"Zergling";"Larva";58;1
"Unit";"Zergling";"Larva";58;1
"Unit";"Zergling";"Larva";58;1
"Unit";"Baneling";"Zergling";58;0
"Unit";"Baneling";"Zergling";62;0
"Unit";"Baneling";"Zergling";62;0
"Unit";"Zergling";"Larva";64;1
"Unit";"Zergling";"Larva";64;1
"Unit";"Baneling";"Zergling";65;0
"Unit";"Baneling";"Zergling";65;0
"Unit";"Zergling";"Larva";67;1
"Unit";"Zergling";"Larva";67;1
"Unit";"Zergling";"Larva";67;1
"Unit";"Zergling";"Larva";67;1
"Unit";"Zergling";"Larva";67;1
"Unit";"Zergling";"Larva";67;1
"Unit";"Queen";"Hatchery";67;2
"Unit";"Zergling";"Larva";84;1
"Unit";"Zergling";"Larva";84;1
"Unit";"Baneling";"Zergling";84;0
"Unit";"Baneling";"Zergling";84;0
"Unit";"Zergling";"Larva";84;1
"Unit";"Zergling";"Larva";84;1
"Unit";"Baneling";"Zergling";87;0
"Unit";"Baneling";"Zergling";89;0
"Unit";"Zergling";"Larva";85;1
"Unit";"Zergling";"Larva";85;1
"Unit";"Baneling";"Zergling";89;0
"Unit";"Zergling";"Larva";85;1
"Unit";"Zergling";"Larva";85;1
"Unit";"Zergling";"Larva";85;1
"Unit";"Zergling";"Larva";85;1
"Unit";"Overlord";"Larva";101;0
"Unit";"Overlord";"Larva";103;0
"Unit";"Queen";"Hatchery";95;2
"Unit";"Overlord";"Larva";105;0
"Building";"CreepTumorQueen";NA;111;0
"Unit";"Zergling";"Larva";105;1
"Unit";"Zergling";"Larva";105;1
"Unit";"Zergling";"Larva";105;1
"Unit";"Zergling";"Larva";105;1
"Unit";"Baneling";"Zergling";110;0
"Unit";"Baneling";"Zergling";110;0
"Building";"Extractor";NA;105;0
"Unit";"Queen";"Hatchery";105;2
"Building";"SpineCrawler";NA;105;0
"Unit";"Baneling";"Zergling";120;0
"Unit";"Baneling";"Zergling";120;0
"Unit";"Baneling";"Zergling";120;0
"Building";"CreepTumor";NA;122;0
"Unit";"Overlord";"Larva";124;0
"Building";"CreepTumorQueen";NA;128;0
"Building";"Extractor";NA;128;0
"Building";"Extractor";NA;128;0
"Unit";"Overlord";"Larva";130;0
"Unit";"Zergling";"Larva";134;1
"Unit";"Zergling";"Larva";134;1
"Unit";"Zergling";"Larva";134;1
"Unit";"Zergling";"Larva";134;1
"Unit";"Zergling";"Larva";134;1
"Unit";"Zergling";"Larva";134;1
"Unit";"Zergling";"Larva";134;1
"Unit";"Zergling";"Larva";134;1
"Unit";"Zergling";"Larva";134;1
"Unit";"Zergling";"Larva";134;1
"Building";"CreepTumor";NA;137;0
"Building";"CreepTumorQueen";NA;137;0
"Unit";"Baneling";"Zergling";147;0
"Unit";"Baneling";"Zergling";147;0
"Building";"Hatchery";NA;128;0
"Building";"CreepTumor";NA;147;0
"Building";"CreepTumor";NA;147;0
"Building";"CreepTumor";NA;147;0
"Unit";"Zergling";"Larva";147;1
"Unit";"Zergling";"Larva";147;1
"Unit";"Zergling";"Larva";147;1
"Unit";"Zergling";"Larva";147;1
"Unit";"Baneling";"Zergling";152;0
"Unit";"Overlord";"Larva";147;0
"Unit";"Baneling";"Zergling";152;0
"Unit";"Zergling";"Larva";152;1
"Unit";"Zergling";"Larva";152;1
"Unit";"Zergling";"Larva";152;1
"Unit";"Zergling";"Larva";152;1
"Unit";"Zergling";"Larva";152;1
"Unit";"Zergling";"Larva";152;1
"Unit";"Baneling";"Zergling";153;0
"Unit";"Baneling";"Zergling";153;0
"Unit";"Zergling";"Larva";153;1
"Unit";"Zergling";"Larva";153;1
"Unit";"Zergling";"Larva";153;1
"Unit";"Zergling";"Larva";153;1
"Unit";"Overlord";"Larva";153;0
"Unit";"Queen";"Hatchery";152;2
"Building";"CreepTumor";NA;165;0
"Building";"CreepTumor";NA;167;0
"Building";"Extractor";NA;165;0
"Building";"Extractor";NA;165;0
"Unit";"Queen";"Hatchery";160;2
"Building";"Spire";NA;147;0
"Unit";"Overlord";"Larva";176;0
"Building";"SporeCrawler";NA;177;0
"Unit";"Overlord";"Larva";181;0
"Unit";"Mutalisk";"Larva";181;2
"Unit";"Mutalisk";"Larva";181;2
"Unit";"Mutalisk";"Larva";181;2
"Unit";"Mutalisk";"Larva";181;2
"Unit";"Mutalisk";"Larva";181;2
"Unit";"Mutalisk";"Larva";181;2
"Unit";"Mutalisk";"Larva";181;2
"Unit";"Mutalisk";"Larva";181;2
"Unit";"Mutalisk";"Larva";182;2
"Unit";"Mutalisk";"Larva";182;2
"Unit";"Zergling";"Larva";182;1
"Unit";"Zergling";"Larva";182;1
"Unit";"Mutalisk";"Larva";182;2
"Unit";"Mutalisk";"Larva";182;2
"Unit";"Zergling";"Larva";206;1
"Unit";"Zergling";"Larva";206;1
"Unit";"Overlord";"Larva";206;0
"Unit";"Zergling";"Larva";206;1
"Unit";"Zergling";"Larva";206;1
"Unit";"Overlord";"Larva";206;0
"Unit";"Zergling";"Larva";206;1
"Unit";"Zergling";"Larva";206;1
"Unit";"Zergling";"Larva";210;1
"Unit";"Zergling";"Larva";210;1
"Unit";"Mutalisk";"Larva";208;2
"Unit";"Mutalisk";"Larva";208;2
"Unit";"Mutalisk";"Larva";208;2
"Unit";"Zergling";"Larva";216;1
"Unit";"Zergling";"Larva";216;1
"Unit";"Baneling";"Zergling";216;0
"Unit";"Mutalisk";"Larva";216;2
"Unit";"Baneling";"Zergling";216;0
"Unit";"Baneling";"Zergling";216;0
"Unit";"Zergling";"Larva";228;1
"Unit";"Zergling";"Larva";228;1
"Unit";"Mutalisk";"Larva";224;2
"Unit";"Mutalisk";"Larva";224;2
"Unit";"Zergling";"Larva";228;1
"Unit";"Zergling";"Larva";228;1
"Unit";"Zergling";"Larva";228;1
"Unit";"Zergling";"Larva";228;1
"Building";"Hatchery";NA;202;0
"Unit";"Mutalisk";"Larva";226;2
"Unit";"Zergling";"Larva";238;1
"Unit";"Zergling";"Larva";238;1
"Unit";"Zergling";"Larva";238;1
"Unit";"Zergling";"Larva";238;1
"Unit";"Mutalisk";"Larva";238;2
"Unit";"Mutalisk";"Larva";238;2
"Unit";"Mutalisk";"Larva";238;2
"Unit";"Mutalisk";"Larva";238;2
"Unit";"Queen";"Hatchery";240;2
"Unit";"Overlord";"Larva";266;0
"Building";"Extractor";NA;266;0
"Building";"Extractor";NA;266;0
"Unit";"Queen";"Hatchery";266;2
"Unit";"Zergling";"Larva";274;1
"Unit";"Zergling";"Larva";274;1
"Unit";"Overlord";"Larva";274;0
"Unit";"Overlord";"Larva";274;0
"Unit";"Zergling";"Larva";278;1
"Unit";"Zergling";"Larva";278;1
"Unit";"Zergling";"Larva";278;1
"Unit";"Zergling";"Larva";278;1
"Unit";"Zergling";"Larva";278;1
"Unit";"Zergling";"Larva";278;1
"Unit";"Zergling";"Larva";278;1
"Unit";"Zergling";"Larva";278;1
"Unit";"Zergling";"Larva";278;1
"Unit";"Zergling";"Larva";278;1
"Unit";"Zergling";"Larva";278;1
"Unit";"Zergling";"Larva";278;1
"Unit";"Zergling";"Larva";278;1
"Unit";"Zergling";"Larva";278;1
"Unit";"Zergling";"Larva";278;1
"Unit";"Zergling";"Larva";278;1
"Unit";"Zergling";"Larva";278;1
"Unit";"Zergling";"Larva";278;1
"Unit";"Zergling";"Larva";278;1
"Unit";"Zergling";"Larva";278;1
"Unit";"Zergling";"Larva";278;1
"Unit";"Zergling";"Larva";278;1
"Unit";"Zergling";"Larva";278;1
"Unit";"Zergling";"Larva";278;1
"Unit";"Zergling";"Larva";278;1
"Unit";"Zergling";"Larva";278;1
"Unit";"Zergling";"Larva";278;1
"Unit";"Zergling";"Larva";278;1
"Building";"CreepTumor";NA;278;0
"Unit";"Zergling";"Larva";278;1
"Unit";"Zergling";"Larva";278;1
"Unit";"Baneling";"Zergling";278;0
"Unit";"Baneling";"Zergling";278;0
"Building";"CreepTumor";NA;279;0
"Unit";"Zergling";"Larva";279;1
"Unit";"Zergling";"Larva";279;1
"Unit";"Zergling";"Larva";279;1
"Unit";"Zergling";"Larva";279;1
"Unit";"Baneling";"Zergling";310;0
"Unit";"Baneling";"Zergling";310;0
"Unit";"Baneling";"Zergling";310;0
"Unit";"Baneling";"Zergling";310;0
"Unit";"Baneling";"Zergling";310;0
"Unit";"Baneling";"Zergling";310;0
"Unit";"Baneling";"Zergling";310;0
"Unit";"Queen";"Hatchery";278;2
"Building";"InfestationPit";NA;314;0
