"type";"unit_name";"on_building";"total_supply";"supply"
"Unit";"Overlord";"Larva";12;0
"Building";"Extractor";NA;19;0
"Building";"SpawningPool";NA;19;0
"Unit";"Overlord";"Larva";22;0
"Building";"Hatchery";NA;17;0
"Unit";"Zergling";"Larva";22;1
"Unit";"Zergling";"Larva";22;1
"Unit";"Zergling";"Larva";22;1
"Unit";"Zergling";"Larva";22;1
"Unit";"Queen";"Hatchery";22;2
"Unit";"Queen";"Hatchery";22;2
"Building";"BanelingNest";NA;33;0
"Unit";"Overlord";"Larva";38;0
"Unit";"Overlord";"Larva";42;0
"Unit";"Baneling";"Zergling";42;0
"Unit";"Baneling";"Zergling";42;0
"Unit";"Zergling";"Larva";43;1
"Unit";"Zergling";"Larva";43;1
"Unit";"Zergling";"Larva";43;1
"Unit";"Zergling";"Larva";43;1
"Unit";"Zergling";"Larva";43;1
"Unit";"Zergling";"Larva";43;1
"Unit";"Zergling";"Larva";43;1
"Unit";"Zergling";"Larva";43;1
"Unit";"Zergling";"Larva";43;1
"Unit";"Zergling";"Larva";43;1
"Unit";"Zergling";"Larva";43;1
"Unit";"Zergling";"Larva";43;1
"Building";"EvolutionChamber";NA;43;0
"Unit";"Zergling";"Larva";43;1
"Unit";"Zergling";"Larva";43;1
"Building";"Hatchery";NA;38;0
"Unit";"Zergling";"Larva";43;1
"Unit";"Zergling";"Larva";43;1
"Unit";"Zergling";"Larva";43;1
"Unit";"Zergling";"Larva";43;1
"Unit";"Zergling";"Larva";43;1
"Unit";"Zergling";"Larva";43;1
"Unit";"Zergling";"Larva";43;1
"Unit";"Zergling";"Larva";43;1
"Unit";"Zergling";"Larva";43;1
"Unit";"Zergling";"Larva";43;1
"Unit";"Baneling";"Zergling";55;0
"Unit";"Baneling";"Zergling";55;0
"Unit";"Baneling";"Zergling";55;0
"Unit";"Baneling";"Zergling";55;0
"Building";"Extractor";NA;55;0
"Unit";"Zergling";"Larva";67;1
"Unit";"Zergling";"Larva";67;1
"Unit";"Zergling";"Larva";67;1
"Unit";"Zergling";"Larva";67;1
"Unit";"Zergling";"Larva";67;1
"Unit";"Zergling";"Larva";67;1
"Unit";"Zergling";"Larva";67;1
"Unit";"Zergling";"Larva";67;1
"Unit";"Baneling";"Zergling";68;0
"Unit";"Baneling";"Zergling";68;0
"Unit";"Baneling";"Zergling";68;0
"Unit";"Baneling";"Zergling";68;0
"Unit";"Zergling";"Larva";76;1
"Unit";"Zergling";"Larva";76;1
"Unit";"Zergling";"Larva";76;1
"Unit";"Zergling";"Larva";76;1
"Unit";"Zergling";"Larva";76;1
"Unit";"Zergling";"Larva";76;1
"Unit";"Zergling";"Larva";76;1
"Unit";"Zergling";"Larva";76;1
"Unit";"Zergling";"Larva";76;1
"Unit";"Zergling";"Larva";76;1
"Unit";"Baneling";"Zergling";78;0
"Unit";"Overlord";"Larva";88;0
"Unit";"Baneling";"Zergling";88;0
"Unit";"Baneling";"Zergling";88;0
"Unit";"Baneling";"Zergling";88;0
"Unit";"Zergling";"Larva";88;1
"Unit";"Zergling";"Larva";88;1
"Unit";"Zergling";"Larva";88;1
"Unit";"Zergling";"Larva";88;1
"Unit";"Baneling";"Zergling";93;0
"Unit";"Baneling";"Zergling";93;0
"Unit";"Baneling";"Zergling";93;0
"Unit";"Zergling";"Larva";97;1
"Unit";"Zergling";"Larva";97;1
"Unit";"Zergling";"Larva";97;1
"Unit";"Zergling";"Larva";97;1
"Unit";"Zergling";"Larva";97;1
"Unit";"Zergling";"Larva";97;1
"Unit";"Zergling";"Larva";97;1
"Unit";"Zergling";"Larva";97;1
"Unit";"Zergling";"Larva";97;1
"Unit";"Zergling";"Larva";97;1
"Unit";"Zergling";"Larva";97;1
"Unit";"Zergling";"Larva";97;1
"Unit";"Zergling";"Larva";97;1
"Unit";"Zergling";"Larva";97;1
"Unit";"Zergling";"Larva";97;1
"Unit";"Zergling";"Larva";97;1
"Unit";"Zergling";"Larva";97;1
"Unit";"Zergling";"Larva";97;1
"Unit";"Zergling";"Larva";97;1
"Unit";"Zergling";"Larva";97;1
"Unit";"Zergling";"Larva";97;1
"Unit";"Zergling";"Larva";97;1
"Unit";"Zergling";"Larva";97;1
"Unit";"Zergling";"Larva";97;1
"Unit";"Zergling";"Larva";97;1
"Unit";"Zergling";"Larva";97;1
"Unit";"Baneling";"Zergling";113;0
"Unit";"Baneling";"Zergling";113;0
"Unit";"Baneling";"Zergling";113;0
"Unit";"Baneling";"Zergling";123;0
"Unit";"Baneling";"Zergling";123;0
"Unit";"Overlord";"Larva";123;0
"Building";"RoachWarren";NA;113;0
"Unit";"Zergling";"Larva";130;1
"Unit";"Zergling";"Larva";130;1
"Unit";"Zergling";"Larva";130;1
"Unit";"Zergling";"Larva";130;1
"Unit";"Zergling";"Larva";130;1
"Unit";"Zergling";"Larva";130;1
"Unit";"Zergling";"Larva";130;1
"Unit";"Zergling";"Larva";130;1
"Unit";"Zergling";"Larva";130;1
"Unit";"Zergling";"Larva";130;1
"Upgrade";"ZergMeleeWeaponsLevel1";"EvolutionChamber";93;0
"Unit";"Zergling";"Larva";130;1
"Unit";"Zergling";"Larva";130;1
"Unit";"Zergling";"Larva";130;1
"Unit";"Zergling";"Larva";130;1
"Unit";"Zergling";"Larva";130;1
"Unit";"Zergling";"Larva";130;1
"Unit";"Zergling";"Larva";130;1
"Unit";"Zergling";"Larva";130;1
"Unit";"Zergling";"Larva";130;1
"Unit";"Zergling";"Larva";130;1
"Unit";"Zergling";"Larva";130;1
"Unit";"Zergling";"Larva";130;1
"Unit";"Zergling";"Larva";130;1
"Unit";"Zergling";"Larva";130;1
"Unit";"Zergling";"Larva";130;1
"Unit";"Zergling";"Larva";130;1
"Unit";"Zergling";"Larva";130;1
"Unit";"Zergling";"Larva";130;1
"Unit";"Queen";"Hatchery";130;2
"Unit";"Zergling";"Larva";150;1
"Unit";"Zergling";"Larva";150;1
"Unit";"Zergling";"Larva";150;1
"Unit";"Zergling";"Larva";150;1
"Unit";"Zergling";"Larva";152;1
"Unit";"Zergling";"Larva";152;1
"Unit";"Zergling";"Larva";154;1
"Unit";"Zergling";"Larva";154;1
"Unit";"Zergling";"Larva";158;1
"Unit";"Zergling";"Larva";158;1
"Unit";"Baneling";"Zergling";164;0
"Unit";"Baneling";"Zergling";164;0
"Unit";"Baneling";"Zergling";164;0
"Unit";"Baneling";"Zergling";164;0
"Unit";"Baneling";"Zergling";164;0
"Unit";"Zergling";"Larva";164;1
"Unit";"Zergling";"Larva";164;1
"Unit";"Zergling";"Larva";164;1
"Unit";"Zergling";"Larva";164;1
"Building";"CreepTumorQueen";NA;170;0
"Unit";"Roach";"Larva";170;2
"Unit";"Roach";"Larva";170;2
"Unit";"Baneling";"Zergling";170;0
"Unit";"Baneling";"Zergling";170;0
"Unit";"Zergling";"Larva";174;1
"Unit";"Zergling";"Larva";174;1
"Unit";"Zergling";"Larva";174;1
"Unit";"Zergling";"Larva";174;1
"Unit";"Baneling";"Zergling";178;0
"Unit";"Baneling";"Zergling";178;0
"Unit";"Roach";"Larva";174;2
"Unit";"Zergling";"Larva";178;1
"Unit";"Zergling";"Larva";178;1
"Unit";"Zergling";"Larva";178;1
"Unit";"Zergling";"Larva";178;1
"Unit";"Zergling";"Larva";178;1
"Unit";"Zergling";"Larva";178;1
"Unit";"Zergling";"Larva";178;1
"Unit";"Zergling";"Larva";178;1
"Unit";"Baneling";"Zergling";192;0
"Unit";"Baneling";"Zergling";192;0
"Unit";"Zergling";"Larva";192;1
"Unit";"Zergling";"Larva";192;1
"Unit";"Baneling";"Zergling";192;0
"Unit";"Baneling";"Zergling";192;0
"Unit";"Zergling";"Larva";192;1
"Unit";"Zergling";"Larva";192;1
"Unit";"Zergling";"Larva";192;1
"Unit";"Zergling";"Larva";192;1
"Unit";"Zergling";"Larva";192;1
"Unit";"Zergling";"Larva";192;1
"Unit";"Zergling";"Larva";192;1
"Unit";"Zergling";"Larva";192;1
"Building";"CreepTumorQueen";NA;192;0
"Unit";"Baneling";"Zergling";192;0
"Unit";"Overlord";"Larva";192;0
"Unit";"Overlord";"Larva";192;0
"Unit";"Overlord";"Larva";192;0
"Unit";"Baneling";"Zergling";192;0
"Unit";"Baneling";"Zergling";192;0
"Unit";"Baneling";"Zergling";192;0
"Unit";"Baneling";"Zergling";192;0
"Unit";"Baneling";"Zergling";194;0
"Unit";"Zergling";"Larva";192;1
"Unit";"Zergling";"Larva";192;1
"Building";"Hatchery";NA;174;0
"Upgrade";"ZergMissileWeaponsLevel1";"EvolutionChamber";174;0
"Unit";"Zergling";"Larva";202;1
"Unit";"Zergling";"Larva";202;1
"Unit";"Zergling";"Larva";202;1
"Unit";"Zergling";"Larva";202;1
"Unit";"Zergling";"Larva";202;1
"Unit";"Zergling";"Larva";202;1
"Unit";"Zergling";"Larva";204;1
"Unit";"Zergling";"Larva";204;1
"Unit";"Zergling";"Larva";204;1
"Unit";"Zergling";"Larva";204;1
"Unit";"Zergling";"Larva";204;1
"Unit";"Zergling";"Larva";204;1
"Unit";"Baneling";"Zergling";204;0
"Unit";"Baneling";"Zergling";204;0
"Unit";"Roach";"Larva";204;2
"Unit";"Roach";"Larva";204;2
"Unit";"Baneling";"Zergling";204;0
"Unit";"Zergling";"Larva";204;1
"Unit";"Zergling";"Larva";204;1
"Unit";"Zergling";"Larva";204;1
"Unit";"Zergling";"Larva";204;1
"Unit";"Zergling";"Larva";204;1
"Unit";"Zergling";"Larva";204;1
"Unit";"Zergling";"Larva";204;1
"Unit";"Zergling";"Larva";204;1
"Unit";"Zergling";"Larva";204;1
"Unit";"Zergling";"Larva";204;1
"Unit";"Zergling";"Larva";204;1
"Unit";"Zergling";"Larva";204;1
"Unit";"Baneling";"Zergling";220;0
"Unit";"Baneling";"Zergling";220;0
"Unit";"Zergling";"Larva";232;1
"Unit";"Zergling";"Larva";232;1
"Unit";"Zergling";"Larva";232;1
"Unit";"Zergling";"Larva";232;1
"Unit";"Zergling";"Larva";232;1
"Unit";"Zergling";"Larva";232;1
"Unit";"Zergling";"Larva";232;1
"Unit";"Zergling";"Larva";232;1
"Unit";"Zergling";"Larva";232;1
"Unit";"Zergling";"Larva";232;1
"Unit";"Zergling";"Larva";232;1
"Unit";"Zergling";"Larva";232;1
"Unit";"Zergling";"Larva";232;1
"Unit";"Zergling";"Larva";232;1
"Unit";"Zergling";"Larva";232;1
"Unit";"Zergling";"Larva";232;1
"Unit";"Baneling";"Zergling";232;0
"Unit";"Roach";"Larva";232;2
"Unit";"Roach";"Larva";232;2
"Unit";"Roach";"Larva";232;2
"Unit";"Roach";"Larva";232;2
"Unit";"Roach";"Larva";232;2
"Unit";"Baneling";"Zergling";248;0
"Unit";"Baneling";"Zergling";261;0
"Unit";"Roach";"Larva";258;2
"Unit";"Roach";"Larva";258;2
"Unit";"Roach";"Larva";258;2
"Unit";"Baneling";"Zergling";261;0
"Unit";"Baneling";"Zergling";261;0
"Unit";"Baneling";"Zergling";261;0
"Building";"Extractor";NA;261;0
"Unit";"Zergling";"Larva";272;1
"Unit";"Zergling";"Larva";272;1
"Unit";"Zergling";"Larva";272;1
"Unit";"Zergling";"Larva";272;1
"Unit";"Zergling";"Larva";272;1
"Unit";"Zergling";"Larva";272;1
"Unit";"Zergling";"Larva";272;1
"Unit";"Zergling";"Larva";272;1
"Unit";"Zergling";"Larva";272;1
"Unit";"Zergling";"Larva";272;1
"Unit";"Zergling";"Larva";272;1
"Unit";"Zergling";"Larva";272;1
"Unit";"Zergling";"Larva";272;1
"Unit";"Zergling";"Larva";272;1
"Unit";"Zergling";"Larva";272;1
"Unit";"Zergling";"Larva";272;1
"Unit";"Zergling";"Larva";272;1
"Unit";"Zergling";"Larva";272;1
"Unit";"Zergling";"Larva";272;1
"Unit";"Zergling";"Larva";272;1
"Unit";"Zergling";"Larva";272;1
"Unit";"Zergling";"Larva";272;1
"Unit";"Zergling";"Larva";272;1
"Unit";"Zergling";"Larva";272;1
"Unit";"Roach";"Larva";286;2
"Unit";"Roach";"Larva";286;2
"Unit";"Roach";"Larva";286;2
"Unit";"Zergling";"Larva";286;1
"Unit";"Zergling";"Larva";286;1
"Unit";"Baneling";"Zergling";302;0
"Unit";"Baneling";"Zergling";302;0
"Unit";"Baneling";"Zergling";302;0
"Unit";"Baneling";"Zergling";302;0
"Unit";"Baneling";"Zergling";302;0
"Unit";"Baneling";"Zergling";302;0
"Unit";"Baneling";"Zergling";302;0
"Unit";"Baneling";"Zergling";302;0
"Unit";"Overlord";"Larva";296;0
"Unit";"Overlord";"Larva";296;0
"Unit";"Overlord";"Larva";298;0
"Unit";"Zergling";"Larva";304;1
"Unit";"Zergling";"Larva";304;1
"Unit";"Zergling";"Larva";304;1
"Unit";"Zergling";"Larva";304;1
"Unit";"Zergling";"Larva";304;1
"Unit";"Zergling";"Larva";304;1
"Unit";"Zergling";"Larva";304;1
"Unit";"Zergling";"Larva";304;1
"Unit";"Zergling";"Larva";304;1
"Unit";"Zergling";"Larva";304;1
"Unit";"Zergling";"Larva";304;1
"Unit";"Zergling";"Larva";304;1
"Unit";"Zergling";"Larva";304;1
"Unit";"Zergling";"Larva";304;1
"Unit";"Zergling";"Larva";304;1
"Unit";"Zergling";"Larva";304;1
"Unit";"Zergling";"Larva";304;1
"Unit";"Zergling";"Larva";304;1
"Unit";"Zergling";"Larva";304;1
"Unit";"Zergling";"Larva";304;1
"Unit";"Zergling";"Larva";304;1
"Unit";"Zergling";"Larva";304;1
"Building";"CreepTumor";NA;304;0
"Building";"CreepTumor";NA;308;0
"Building";"CreepTumor";NA;329;0
"Building";"CreepTumor";NA;329;0
"Unit";"Overlord";"Larva";329;0
"Unit";"Overlord";"Larva";329;0
"Unit";"Overlord";"Larva";329;0
"Building";"Extractor";NA;332;0
"Building";"Extractor";NA;340;0
"Building";"Extractor";NA;340;0
"Building";"CreepTumor";NA;344;0
"Building";"CreepTumor";NA;344;0
"Unit";"Overlord";"Larva";344;0
"Unit";"Overlord";"Larva";344;0
"Unit";"Overlord";"Larva";344;0
"Unit";"Overlord";"Larva";344;0
"Unit";"Baneling";"Zergling";347;0
"Unit";"Baneling";"Zergling";347;0
"Unit";"Baneling";"Zergling";347;0
"Unit";"Baneling";"Zergling";347;0
"Unit";"Baneling";"Zergling";347;0
"Unit";"Baneling";"Zergling";347;0
"Unit";"Baneling";"Zergling";347;0
"Unit";"Baneling";"Zergling";347;0
"Unit";"Baneling";"Zergling";347;0
"Unit";"Baneling";"Zergling";347;0
"Unit";"Baneling";"Zergling";347;0
"Unit";"Baneling";"Zergling";347;0
"Unit";"Baneling";"Zergling";347;0
"Building";"CreepTumor";NA;347;0
"Unit";"Overlord";"Larva";347;0
"Unit";"Overlord";"Larva";347;0
"Unit";"Roach";"Larva";347;2
"Unit";"Roach";"Larva";347;2
"Unit";"Roach";"Larva";347;2
"Unit";"Roach";"Larva";347;2
"Unit";"Roach";"Larva";347;2
"Unit";"Roach";"Larva";347;2
"Unit";"Roach";"Larva";347;2
"Unit";"Roach";"Larva";347;2
"Unit";"Roach";"Larva";347;2
"Unit";"Roach";"Larva";347;2
"Unit";"Roach";"Larva";347;2
"Unit";"Roach";"Larva";347;2
"Unit";"Roach";"Larva";347;2
"Unit";"Roach";"Larva";363;2
"Unit";"Roach";"Larva";373;2
"Unit";"Roach";"Larva";373;2
"Unit";"Roach";"Larva";373;2
"Unit";"Roach";"Larva";373;2
"Unit";"Roach";"Larva";373;2
"Unit";"Roach";"Larva";373;2
"Unit";"Roach";"Larva";373;2
"Unit";"Roach";"Larva";373;2
"Unit";"Roach";"Larva";373;2
"Upgrade";"ZergMeleeWeaponsLevel2";"EvolutionChamber";340;0
"Building";"Hatchery";NA;344;0
"Unit";"Overlord";"Larva";373;0
"Unit";"Overlord";"Larva";373;0
"Building";"CreepTumor";NA;393;0
"Upgrade";"GlialReconstitution";"RoachWarren";373;0
"Building";"CreepTumor";NA;393;0
"Building";"CreepTumorQueen";NA;393;0
"Building";"CreepTumor";NA;393;0
"Building";"CreepTumorQueen";NA;393;0
"Building";"CreepTumorQueen";NA;393;0
"Building";"Extractor";NA;393;0
"Building";"Extractor";NA;393;0
"Building";"CreepTumorQueen";NA;415;0
"Building";"CreepTumorQueen";NA;415;0
"Building";"CreepTumor";NA;415;0
"Building";"CreepTumor";NA;415;0
"Building";"CreepTumor";NA;415;0
"Building";"CreepTumor";NA;415;0
"Building";"CreepTumorQueen";NA;415;0
"Building";"CreepTumor";NA;415;0
"Building";"CreepTumor";NA;415;0
"Upgrade";"ZergMissileWeaponsLevel2";"EvolutionChamber";393;0
"Unit";"Queen";"Hatchery";415;2
"Unit";"Baneling";"Zergling";415;0
"Unit";"Baneling";"Zergling";415;0
"Unit";"Baneling";"Zergling";415;0
"Unit";"Baneling";"Zergling";415;0
"Unit";"Baneling";"Zergling";415;0
"Unit";"Baneling";"Zergling";415;0
"Unit";"Baneling";"Zergling";415;0
"Unit";"Baneling";"Zergling";415;0
"Unit";"Baneling";"Zergling";415;0
"Unit";"Baneling";"Zergling";415;0
"Unit";"Baneling";"Zergling";415;0
"Unit";"Baneling";"Zergling";415;0
"Unit";"Baneling";"Zergling";415;0
"Unit";"Baneling";"Zergling";415;0
"Unit";"Baneling";"Zergling";415;0
"Unit";"Baneling";"Zergling";415;0
"Unit";"Baneling";"Zergling";415;0
"Unit";"Baneling";"Zergling";415;0
"Unit";"Baneling";"Zergling";415;0
"Unit";"Baneling";"Zergling";415;0
"Unit";"Baneling";"Zergling";415;0
"Unit";"Baneling";"Zergling";415;0
"Unit";"Baneling";"Zergling";415;0
"Unit";"Baneling";"Zergling";415;0
"Unit";"Baneling";"Zergling";415;0
"Unit";"Baneling";"Zergling";415;0
"Unit";"Baneling";"Zergling";415;0
"Unit";"Baneling";"Zergling";415;0
"Unit";"Baneling";"Zergling";415;0
"Unit";"Baneling";"Zergling";415;0
"Unit";"Baneling";"Zergling";415;0
"Unit";"Baneling";"Zergling";415;0
"Unit";"Baneling";"Zergling";415;0
"Unit";"Baneling";"Zergling";415;0
"Unit";"Baneling";"Zergling";415;0
"Unit";"Baneling";"Zergling";415;0
"Unit";"Baneling";"Zergling";415;0
"Building";"Hatchery";NA;415;0
"Building";"CreepTumor";NA;417;0
"Building";"CreepTumor";NA;417;0
"Building";"CreepTumor";NA;417;0
"Building";"CreepTumor";NA;417;0
"Building";"CreepTumor";NA;417;0
"Building";"CreepTumor";NA;417;0
"Building";"CreepTumor";NA;417;0
"Building";"CreepTumor";NA;417;0
"Building";"CreepTumor";NA;417;0
"Building";"CreepTumor";NA;417;0
"Building";"CreepTumor";NA;417;0
"Building";"CreepTumorQueen";NA;417;0
"Building";"CreepTumor";NA;417;0
"Building";"CreepTumor";NA;417;0
"Building";"CreepTumor";NA;417;0
"Building";"CreepTumor";NA;417;0
"Building";"CreepTumor";NA;417;0
"Building";"CreepTumor";NA;417;0
"Building";"CreepTumor";NA;417;0
"Building";"CreepTumorQueen";NA;417;0
"Building";"CreepTumorQueen";NA;417;0
"Building";"CreepTumor";NA;417;0
"Building";"CreepTumor";NA;417;0
"Building";"CreepTumor";NA;417;0
"Building";"CreepTumor";NA;417;0
"Building";"CreepTumor";NA;417;0
"Building";"CreepTumor";NA;417;0
"Building";"CreepTumorQueen";NA;417;0
"Building";"Extractor";NA;417;0
"Building";"CreepTumor";NA;417;0
"Building";"Extractor";NA;417;0
"Building";"CreepTumor";NA;417;0
"Building";"CreepTumor";NA;417;0
"Building";"CreepTumor";NA;417;0
"Building";"CreepTumor";NA;417;0
"Building";"CreepTumorQueen";NA;417;0
"Building";"CreepTumor";NA;417;0
"Building";"CreepTumor";NA;417;0
"Building";"CreepTumor";NA;417;0
"Building";"CreepTumor";NA;417;0
"Building";"CreepTumor";NA;417;0
"Building";"CreepTumor";NA;417;0
"Building";"CreepTumor";NA;417;0
"Building";"CreepTumor";NA;417;0
"Building";"CreepTumor";NA;417;0
"Building";"CreepTumor";NA;417;0
"Building";"CreepTumor";NA;417;0
"Building";"CreepTumor";NA;417;0
"Building";"Hatchery";NA;417;0
"Building";"CreepTumor";NA;417;0
"Building";"CreepTumor";NA;417;0
"Building";"Hatchery";NA;417;0
"Building";"CreepTumorQueen";NA;417;0
"Building";"CreepTumor";NA;417;0
"Building";"CreepTumor";NA;417;0
"Building";"CreepTumor";NA;417;0
"Building";"CreepTumor";NA;417;0
"Building";"CreepTumor";NA;417;0
"Building";"CreepTumor";NA;417;0
"Building";"CreepTumor";NA;417;0
"Building";"CreepTumor";NA;417;0
"Building";"CreepTumor";NA;417;0
"Building";"CreepTumor";NA;417;0
"Building";"CreepTumor";NA;417;0
"Building";"CreepTumor";NA;417;0
"Building";"InfestationPit";NA;417;0
"Building";"CreepTumor";NA;417;0
"Building";"CreepTumor";NA;417;0
"Building";"CreepTumor";NA;417;0
"Building";"CreepTumor";NA;417;0
"Building";"CreepTumor";NA;417;0
"Building";"CreepTumorQueen";NA;417;0
"Building";"CreepTumor";NA;417;0
"Building";"CreepTumor";NA;417;0
"Building";"CreepTumor";NA;417;0
"Building";"CreepTumor";NA;417;0
"Building";"CreepTumor";NA;417;0
"Building";"CreepTumor";NA;417;0
"Building";"CreepTumor";NA;417;0
"Building";"CreepTumor";NA;417;0
"Building";"CreepTumor";NA;417;0
"Building";"CreepTumor";NA;417;0
"Building";"CreepTumor";NA;417;0
"Building";"CreepTumor";NA;417;0
"Building";"CreepTumor";NA;417;0
"Building";"CreepTumor";NA;417;0
"Building";"CreepTumor";NA;417;0
"Building";"CreepTumor";NA;417;0
"Building";"CreepTumor";NA;417;0
"Building";"CreepTumor";NA;417;0
"Building";"CreepTumor";NA;417;0
"Building";"CreepTumor";NA;417;0
"Building";"CreepTumor";NA;417;0
"Building";"CreepTumor";NA;417;0
"Building";"CreepTumor";NA;417;0
"Building";"CreepTumor";NA;417;0
"Building";"CreepTumor";NA;417;0
"Building";"CreepTumor";NA;417;0
"Building";"CreepTumor";NA;417;0
"Building";"CreepTumor";NA;417;0
"Building";"CreepTumor";NA;417;0
"Building";"CreepTumor";NA;417;0
"Building";"CreepTumorQueen";NA;417;0
"Building";"CreepTumorQueen";NA;417;0
"Building";"Extractor";NA;417;0
"Building";"CreepTumorQueen";NA;417;0
"Building";"Extractor";NA;417;0
"Building";"CreepTumorQueen";NA;417;0
"Building";"Extractor";NA;417;0
"Building";"Extractor";NA;417;0
"Unit";"Zergling";"Larva";426;1
"Unit";"Zergling";"Larva";426;1
"Unit";"Zergling";"Larva";426;1
"Unit";"Zergling";"Larva";426;1
"Unit";"Zergling";"Larva";426;1
"Unit";"Zergling";"Larva";426;1
"Unit";"Zergling";"Larva";426;1
"Unit";"Zergling";"Larva";426;1
"Unit";"Zergling";"Larva";426;1
"Unit";"Zergling";"Larva";426;1
"Unit";"Zergling";"Larva";426;1
"Unit";"Zergling";"Larva";426;1
"Unit";"Zergling";"Larva";426;1
"Unit";"Zergling";"Larva";426;1
"Unit";"Zergling";"Larva";426;1
"Unit";"Zergling";"Larva";426;1
"Unit";"Zergling";"Larva";426;1
"Unit";"Zergling";"Larva";426;1
"Unit";"Zergling";"Larva";426;1
"Unit";"Zergling";"Larva";426;1
"Unit";"Zergling";"Larva";426;1
"Unit";"Zergling";"Larva";426;1
"Unit";"Zergling";"Larva";426;1
"Unit";"Zergling";"Larva";426;1
"Unit";"Zergling";"Larva";426;1
"Unit";"Zergling";"Larva";426;1
"Unit";"Zergling";"Larva";426;1
"Unit";"Zergling";"Larva";426;1
"Unit";"Zergling";"Larva";426;1
"Unit";"Zergling";"Larva";426;1
"Unit";"Zergling";"Larva";426;1
"Unit";"Zergling";"Larva";426;1
"Unit";"Zergling";"Larva";426;1
"Unit";"Zergling";"Larva";426;1
"Unit";"Zergling";"Larva";426;1
"Unit";"Zergling";"Larva";426;1
"Unit";"Zergling";"Larva";426;1
"Unit";"Zergling";"Larva";426;1
"Unit";"Zergling";"Larva";426;1
"Unit";"Zergling";"Larva";426;1
"Unit";"Zergling";"Larva";426;1
"Unit";"Zergling";"Larva";426;1
"Unit";"Zergling";"Larva";426;1
"Unit";"Zergling";"Larva";426;1
"Unit";"Zergling";"Larva";426;1
"Unit";"Zergling";"Larva";426;1
"Unit";"Zergling";"Larva";426;1
"Unit";"Zergling";"Larva";426;1
"Unit";"Zergling";"Larva";426;1
"Unit";"Zergling";"Larva";426;1
"Unit";"Zergling";"Larva";426;1
"Unit";"Zergling";"Larva";426;1
"Unit";"Zergling";"Larva";426;1
"Unit";"Zergling";"Larva";426;1
"Unit";"Zergling";"Larva";426;1
"Unit";"Zergling";"Larva";426;1
"Unit";"Zergling";"Larva";426;1
"Unit";"Zergling";"Larva";426;1
"Unit";"Zergling";"Larva";426;1
"Unit";"Zergling";"Larva";426;1
"Unit";"Zergling";"Larva";426;1
"Unit";"Zergling";"Larva";426;1
"Unit";"Zergling";"Larva";426;1
"Unit";"Zergling";"Larva";426;1
"Unit";"Zergling";"Larva";426;1
"Unit";"Zergling";"Larva";426;1
"Unit";"Zergling";"Larva";426;1
"Unit";"Zergling";"Larva";426;1
"Unit";"Zergling";"Larva";426;1
"Unit";"Zergling";"Larva";426;1
"Unit";"Zergling";"Larva";426;1
"Unit";"Zergling";"Larva";426;1
"Unit";"Zergling";"Larva";426;1
"Unit";"Zergling";"Larva";426;1
"Unit";"Zergling";"Larva";426;1
"Unit";"Zergling";"Larva";426;1
"Unit";"Zergling";"Larva";426;1
"Unit";"Zergling";"Larva";426;1
"Unit";"Zergling";"Larva";426;1
"Unit";"Zergling";"Larva";426;1
"Unit";"Zergling";"Larva";426;1
"Unit";"Zergling";"Larva";426;1
"Unit";"Zergling";"Larva";426;1
"Unit";"Zergling";"Larva";426;1
"Unit";"Zergling";"Larva";426;1
"Unit";"Zergling";"Larva";426;1
"Unit";"Zergling";"Larva";426;1
"Unit";"Zergling";"Larva";426;1
"Unit";"Zergling";"Larva";426;1
"Unit";"Zergling";"Larva";426;1
"Unit";"Zergling";"Larva";426;1
"Unit";"Zergling";"Larva";426;1
"Unit";"Zergling";"Larva";426;1
"Unit";"Zergling";"Larva";426;1
"Unit";"Zergling";"Larva";426;1
"Unit";"Zergling";"Larva";426;1
"Unit";"Zergling";"Larva";426;1
"Unit";"Zergling";"Larva";426;1
"Unit";"Zergling";"Larva";426;1
"Unit";"Zergling";"Larva";426;1
"Unit";"Zergling";"Larva";426;1
"Unit";"Zergling";"Larva";426;1
"Unit";"Zergling";"Larva";426;1
"Unit";"Zergling";"Larva";426;1
"Unit";"Zergling";"Larva";426;1
"Unit";"Zergling";"Larva";426;1
"Unit";"Zergling";"Larva";426;1
"Unit";"Zergling";"Larva";426;1
"Unit";"Zergling";"Larva";426;1
"Unit";"Zergling";"Larva";426;1
"Unit";"Zergling";"Larva";426;1
"Unit";"Zergling";"Larva";426;1
"Unit";"Zergling";"Larva";426;1
"Unit";"Zergling";"Larva";426;1
"Unit";"Zergling";"Larva";426;1
"Unit";"Zergling";"Larva";426;1
"Unit";"Zergling";"Larva";426;1
"Unit";"Zergling";"Larva";426;1
"Unit";"Zergling";"Larva";426;1
"Unit";"Zergling";"Larva";426;1
"Unit";"Zergling";"Larva";426;1
"Unit";"Zergling";"Larva";426;1
"Unit";"Zergling";"Larva";426;1
"Unit";"Zergling";"Larva";426;1
"Building";"Hatchery";NA;426;0
"Building";"Hatchery";NA;426;0
"Building";"Hatchery";NA;426;0
"Unit";"Baneling";"Zergling";550;0
"Unit";"Baneling";"Zergling";550;0
"Unit";"Baneling";"Zergling";550;0
"Unit";"Baneling";"Zergling";550;0
"Unit";"Baneling";"Zergling";550;0
"Unit";"Baneling";"Zergling";550;0
"Unit";"Baneling";"Zergling";550;0
"Unit";"Baneling";"Zergling";550;0
"Unit";"Baneling";"Zergling";550;0
"Unit";"Baneling";"Zergling";550;0
"Unit";"Baneling";"Zergling";550;0
"Unit";"Baneling";"Zergling";550;0
"Unit";"Baneling";"Zergling";550;0
"Unit";"Baneling";"Zergling";550;0
"Unit";"Baneling";"Zergling";550;0
"Unit";"Baneling";"Zergling";550;0
"Unit";"Baneling";"Zergling";550;0
"Unit";"Baneling";"Zergling";550;0
"Unit";"Baneling";"Zergling";550;0
"Unit";"Baneling";"Zergling";550;0
"Unit";"Baneling";"Zergling";550;0
"Unit";"Baneling";"Zergling";550;0
"Unit";"Baneling";"Zergling";550;0
"Unit";"Baneling";"Zergling";550;0
"Unit";"Baneling";"Zergling";550;0
"Unit";"Baneling";"Zergling";550;0
"Unit";"Baneling";"Zergling";550;0
"Unit";"Baneling";"Zergling";550;0
"Unit";"Baneling";"Zergling";550;0
"Unit";"Baneling";"Zergling";550;0
"Unit";"Baneling";"Zergling";550;0
"Unit";"Baneling";"Zergling";550;0
"Unit";"Baneling";"Zergling";550;0
"Unit";"Baneling";"Zergling";550;0
"Unit";"Baneling";"Zergling";550;0
"Unit";"Baneling";"Zergling";550;0
"Unit";"Baneling";"Zergling";550;0
"Unit";"Baneling";"Zergling";550;0
"Unit";"Baneling";"Zergling";550;0
"Unit";"Baneling";"Zergling";550;0
"Unit";"Baneling";"Zergling";550;0
"Unit";"Baneling";"Zergling";550;0
"Unit";"Baneling";"Zergling";550;0
"Unit";"Baneling";"Zergling";550;0
"Unit";"Baneling";"Zergling";550;0
"Unit";"Baneling";"Zergling";550;0
"Unit";"Baneling";"Zergling";550;0
"Unit";"Baneling";"Zergling";550;0
"Unit";"Baneling";"Zergling";550;0
"Unit";"Baneling";"Zergling";550;0
"Unit";"Baneling";"Zergling";550;0
"Unit";"Baneling";"Zergling";550;0
"Unit";"Baneling";"Zergling";550;0
"Unit";"Baneling";"Zergling";550;0
"Unit";"Baneling";"Zergling";550;0
"Unit";"Baneling";"Zergling";550;0
"Unit";"Baneling";"Zergling";550;0
"Unit";"Baneling";"Zergling";550;0
"Unit";"Baneling";"Zergling";550;0
"Unit";"Baneling";"Zergling";550;0
"Unit";"Baneling";"Zergling";550;0
"Unit";"Baneling";"Zergling";550;0
"Unit";"Baneling";"Zergling";550;0
"Unit";"Baneling";"Zergling";550;0
"Unit";"Baneling";"Zergling";550;0
"Unit";"Baneling";"Zergling";550;0
"Unit";"Baneling";"Zergling";550;0
"Unit";"Baneling";"Zergling";550;0
"Unit";"Baneling";"Zergling";550;0
"Unit";"Baneling";"Zergling";550;0
"Unit";"Baneling";"Zergling";550;0
"Unit";"Baneling";"Zergling";550;0
"Unit";"Baneling";"Zergling";550;0
"Unit";"Baneling";"Zergling";550;0
"Unit";"Baneling";"Zergling";550;0
"Unit";"Baneling";"Zergling";550;0
"Unit";"Baneling";"Zergling";550;0
"Unit";"Baneling";"Zergling";550;0
"Unit";"Baneling";"Zergling";550;0
"Unit";"Baneling";"Zergling";550;0
"Unit";"Baneling";"Zergling";550;0
"Unit";"Baneling";"Zergling";550;0
"Unit";"Baneling";"Zergling";550;0
"Unit";"Baneling";"Zergling";550;0
"Unit";"Baneling";"Zergling";550;0
"Unit";"Baneling";"Zergling";550;0
"Unit";"Baneling";"Zergling";550;0
"Unit";"Baneling";"Zergling";550;0
"Unit";"Baneling";"Zergling";550;0
"Unit";"Baneling";"Zergling";550;0
"Unit";"Baneling";"Zergling";550;0
"Unit";"Baneling";"Zergling";550;0
"Unit";"Baneling";"Zergling";550;0
"Unit";"Baneling";"Zergling";550;0
"Unit";"Baneling";"Zergling";550;0
"Unit";"Baneling";"Zergling";550;0
"Unit";"Baneling";"Zergling";550;0
"Unit";"Baneling";"Zergling";550;0
"Unit";"Baneling";"Zergling";550;0
"Unit";"Baneling";"Zergling";550;0
"Unit";"Baneling";"Zergling";550;0
"Unit";"Baneling";"Zergling";550;0
"Unit";"Baneling";"Zergling";550;0
"Unit";"Baneling";"Zergling";550;0
"Unit";"Baneling";"Zergling";550;0
"Unit";"Baneling";"Zergling";550;0
"Unit";"Baneling";"Zergling";550;0
"Unit";"Baneling";"Zergling";550;0
"Unit";"Baneling";"Zergling";550;0
"Unit";"Baneling";"Zergling";550;0
"Unit";"Baneling";"Zergling";550;0
"Unit";"Baneling";"Zergling";550;0
"Unit";"Baneling";"Zergling";550;0
"Unit";"Baneling";"Zergling";550;0
"Unit";"Baneling";"Zergling";550;0
"Unit";"Baneling";"Zergling";550;0
"Unit";"Baneling";"Zergling";550;0
"Unit";"Baneling";"Zergling";550;0
"Unit";"Baneling";"Zergling";550;0
"Unit";"Baneling";"Zergling";550;0
"Unit";"Baneling";"Zergling";550;0
"Unit";"Baneling";"Zergling";550;0
"Unit";"Baneling";"Zergling";550;0
"Unit";"Baneling";"Zergling";550;0
"Building";"Extractor";NA;550;0
"Building";"Extractor";NA;550;0
"Building";"CreepTumor";NA;550;0
"Upgrade";"ZergMeleeWeaponsLevel3";"EvolutionChamber";550;0
