"type";"unit_name";"on_building";"total_supply";"supply"
"Unit";"Overlord";"Larva";12;0
"Building";"Extractor";NA;17;0
"Unit";"Overlord";"Larva";22;0
"Building";"SpawningPool";NA;19;0
"Building";"Hatchery";NA;17;0
"Unit";"Zergling";"Larva";22;1
"Unit";"Zergling";"Larva";22;1
"Unit";"Queen";"Hatchery";22;2
"Unit";"Queen";"Hatchery";22;2
"Unit";"Zergling";"Larva";34;1
"Unit";"Zergling";"Larva";34;1
"Unit";"Zergling";"Larva";34;1
"Unit";"Zergling";"Larva";34;1
"Unit";"Overlord";"Larva";34;0
"Unit";"Zergling";"Larva";34;1
"Unit";"Zergling";"Larva";34;1
"Unit";"Zergling";"Larva";34;1
"Unit";"Zergling";"Larva";34;1
"Unit";"Zergling";"Larva";34;1
"Unit";"Zergling";"Larva";34;1
"Building";"BanelingNest";NA;34;0
"Unit";"Queen";"Hatchery";34;2
"Unit";"Overlord";"Larva";49;0
"Unit";"Overlord";"Larva";50;0
"Unit";"Baneling";"Zergling";52;0
"Unit";"Baneling";"Zergling";52;0
"Building";"Hatchery";NA;34;0
"Building";"CreepTumorQueen";NA;52;0
"Unit";"Zergling";"Larva";52;1
"Unit";"Zergling";"Larva";52;1
"Unit";"Zergling";"Larva";52;1
"Unit";"Zergling";"Larva";52;1
"Unit";"Zergling";"Larva";52;1
"Unit";"Zergling";"Larva";52;1
"Unit";"Baneling";"Zergling";52;0
"Unit";"Baneling";"Zergling";52;0
"Unit";"Zergling";"Larva";52;1
"Unit";"Zergling";"Larva";52;1
"Unit";"Zergling";"Larva";52;1
"Unit";"Zergling";"Larva";52;1
"Unit";"Zergling";"Larva";52;1
"Unit";"Zergling";"Larva";52;1
"Unit";"Zergling";"Larva";52;1
"Unit";"Zergling";"Larva";52;1
"Unit";"Zergling";"Larva";52;1
"Unit";"Zergling";"Larva";52;1
"Unit";"Zergling";"Larva";52;1
"Unit";"Zergling";"Larva";52;1
"Unit";"Queen";"Hatchery";52;2
"Unit";"Zergling";"Larva";58;1
"Unit";"Zergling";"Larva";58;1
"Unit";"Zergling";"Larva";58;1
"Unit";"Zergling";"Larva";58;1
"Unit";"Zergling";"Larva";58;1
"Unit";"Zergling";"Larva";58;1
"Unit";"Zergling";"Larva";58;1
"Unit";"Zergling";"Larva";58;1
"Unit";"Zergling";"Larva";58;1
"Unit";"Zergling";"Larva";58;1
"Unit";"Overlord";"Larva";70;0
"Unit";"Overlord";"Larva";70;0
"Unit";"Baneling";"Zergling";70;0
"Unit";"Baneling";"Zergling";70;0
"Unit";"Baneling";"Zergling";84;0
"Building";"EvolutionChamber";NA;72;0
"Unit";"Zergling";"Larva";87;1
"Unit";"Zergling";"Larva";87;1
"Unit";"Zergling";"Larva";87;1
"Unit";"Zergling";"Larva";87;1
"Unit";"Zergling";"Larva";87;1
"Unit";"Zergling";"Larva";87;1
"Unit";"Zergling";"Larva";87;1
"Unit";"Zergling";"Larva";87;1
"Unit";"Zergling";"Larva";87;1
"Unit";"Zergling";"Larva";87;1
"Unit";"Zergling";"Larva";87;1
"Unit";"Zergling";"Larva";87;1
"Unit";"Zergling";"Larva";87;1
"Unit";"Zergling";"Larva";87;1
"Unit";"Zergling";"Larva";87;1
"Unit";"Zergling";"Larva";87;1
"Unit";"Zergling";"Larva";87;1
"Unit";"Zergling";"Larva";87;1
"Unit";"Zergling";"Larva";95;1
"Unit";"Zergling";"Larva";95;1
"Unit";"Zergling";"Larva";95;1
"Unit";"Zergling";"Larva";95;1
"Unit";"Zergling";"Larva";95;1
"Unit";"Zergling";"Larva";95;1
"Unit";"Zergling";"Larva";99;1
"Unit";"Zergling";"Larva";99;1
"Unit";"Zergling";"Larva";99;1
"Unit";"Zergling";"Larva";99;1
"Unit";"Zergling";"Larva";99;1
"Unit";"Zergling";"Larva";99;1
"Unit";"Baneling";"Zergling";109;0
"Unit";"Baneling";"Zergling";109;0
"Building";"Extractor";NA;115;0
"Building";"Extractor";NA;115;0
"Unit";"Zergling";"Larva";121;1
"Unit";"Zergling";"Larva";121;1
"Unit";"Zergling";"Larva";121;1
"Unit";"Zergling";"Larva";121;1
"Building";"RoachWarren";NA;121;0
"Unit";"Overlord";"Larva";139;0
"Unit";"Overlord";"Larva";139;0
"Unit";"Overlord";"Larva";139;0
"Unit";"Zergling";"Larva";139;1
"Unit";"Zergling";"Larva";139;1
"Unit";"Zergling";"Larva";139;1
"Unit";"Zergling";"Larva";139;1
"Unit";"Zergling";"Larva";139;1
"Unit";"Zergling";"Larva";139;1
"Unit";"Zergling";"Larva";139;1
"Unit";"Zergling";"Larva";139;1
"Unit";"Zergling";"Larva";139;1
"Unit";"Zergling";"Larva";139;1
"Unit";"Roach";"Larva";139;2
"Unit";"Roach";"Larva";139;2
"Unit";"Roach";"Larva";139;2
"Building";"Extractor";NA;139;0
"Building";"CreepTumor";NA;147;0
"Unit";"Baneling";"Zergling";163;0
"Unit";"Baneling";"Zergling";163;0
"Unit";"Baneling";"Zergling";163;0
"Unit";"Roach";"Larva";157;2
"Unit";"Roach";"Larva";157;2
"Upgrade";"ZergMissileWeaponsLevel1";"EvolutionChamber";130;0
"Unit";"Overlord";"Larva";170;0
"Unit";"Overlord";"Larva";170;0
"Unit";"Roach";"Larva";172;2
"Building";"Extractor";NA;170;0
"Unit";"Roach";"Larva";174;2
"Unit";"Roach";"Larva";174;2
"Unit";"Zergling";"Larva";177;1
"Unit";"Zergling";"Larva";177;1
"Unit";"Zergling";"Larva";177;1
"Unit";"Zergling";"Larva";177;1
"Unit";"Roach";"Larva";177;2
"Unit";"Zergling";"Larva";177;1
"Unit";"Zergling";"Larva";177;1
"Unit";"Roach";"Larva";177;2
"Unit";"Zergling";"Larva";183;1
"Unit";"Zergling";"Larva";183;1
"Unit";"Zergling";"Larva";183;1
"Unit";"Zergling";"Larva";183;1
"Unit";"Roach";"Larva";183;2
"Unit";"Roach";"Larva";183;2
"Unit";"Roach";"Larva";183;2
"Unit";"Roach";"Larva";183;2
"Unit";"Roach";"Larva";183;2
"Unit";"Zergling";"Larva";183;1
"Unit";"Zergling";"Larva";183;1
"Unit";"Zergling";"Larva";183;1
"Unit";"Zergling";"Larva";183;1
"Unit";"Zergling";"Larva";183;1
"Unit";"Zergling";"Larva";183;1
"Unit";"Zergling";"Larva";183;1
"Unit";"Zergling";"Larva";183;1
"Unit";"Roach";"Larva";193;2
"Unit";"Roach";"Larva";193;2
"Unit";"Roach";"Larva";195;2
"Unit";"Roach";"Larva";197;2
"Upgrade";"GlialReconstitution";"RoachWarren";177;0
"Unit";"Overlord";"Larva";209;0
"Unit";"Overlord";"Larva";211;0
"Unit";"Overlord";"Larva";211;0
"Building";"Hatchery";NA;170;0
"Building";"CreepTumor";NA;215;0
"Building";"Extractor";NA;215;0
"Unit";"Overlord";"Larva";215;0
"Unit";"Overlord";"Larva";215;0
"Unit";"Roach";"Larva";223;2
"Unit";"Roach";"Larva";223;2
"Unit";"Roach";"Larva";223;2
"Unit";"Queen";"Hatchery";197;2
"Unit";"Roach";"Larva";223;2
"Unit";"Queen";"Hatchery";215;2
"Unit";"Roach";"Larva";241;2
"Unit";"Roach";"Larva";241;2
"Unit";"Roach";"Larva";241;2
"Unit";"Roach";"Larva";241;2
"Unit";"Roach";"Larva";241;2
"Unit";"Roach";"Larva";241;2
"Unit";"Roach";"Larva";241;2
"Unit";"Queen";"Hatchery";223;2
"Unit";"Roach";"Larva";241;2
"Unit";"Roach";"Larva";241;2
"Unit";"Roach";"Larva";241;2
"Unit";"Roach";"Larva";241;2
"Unit";"Roach";"Larva";241;2
"Unit";"Roach";"Larva";241;2
"Unit";"Roach";"Larva";241;2
"Unit";"Roach";"Larva";241;2
"Unit";"Roach";"Larva";241;2
"Unit";"Overlord";"Larva";241;0
"Unit";"Overlord";"Larva";241;0
"Unit";"Roach";"Larva";265;2
"Unit";"Roach";"Larva";265;2
"Unit";"Roach";"Larva";265;2
"Unit";"Roach";"Larva";265;2
"Unit";"Roach";"Larva";265;2
"Unit";"Roach";"Larva";265;2
"Building";"CreepTumorQueen";NA;275;0
"Unit";"Overlord";"Larva";275;0
"Unit";"Overlord";"Larva";275;0
"Upgrade";"ZergMissileWeaponsLevel2";"EvolutionChamber";215;0
"Unit";"Roach";"Larva";275;2
"Unit";"Roach";"Larva";275;2
"Unit";"Roach";"Larva";275;2
"Unit";"Roach";"Larva";275;2
"Unit";"Roach";"Larva";275;2
"Unit";"Roach";"Larva";279;2
"Unit";"Roach";"Larva";285;2
"Unit";"Roach";"Larva";285;2
"Unit";"Roach";"Larva";285;2
"Unit";"Roach";"Larva";287;2
"Unit";"Roach";"Larva";287;2
"Unit";"Roach";"Larva";287;2
"Unit";"Roach";"Larva";287;2
"Unit";"Roach";"Larva";287;2
"Unit";"Roach";"Larva";315;2
"Unit";"Roach";"Larva";315;2
"Unit";"Roach";"Larva";315;2
"Unit";"Roach";"Larva";315;2
"Unit";"Roach";"Larva";315;2
"Unit";"Roach";"Larva";315;2
"Unit";"Roach";"Larva";315;2
"Unit";"Roach";"Larva";315;2
"Unit";"Roach";"Larva";315;2
"Unit";"Roach";"Larva";315;2
"Unit";"Roach";"Larva";315;2
"Building";"HydraliskDen";NA;307;0
"Unit";"Roach";"Larva";315;2
"Unit";"Roach";"Larva";315;2
"Unit";"Roach";"Larva";315;2
"Unit";"Roach";"Larva";315;2
"Unit";"Roach";"Larva";315;2
"Unit";"Roach";"Larva";315;2
"Building";"Extractor";NA;315;0
"Unit";"Roach";"Larva";341;2
"Unit";"Roach";"Larva";345;2
"Unit";"Roach";"Larva";345;2
"Unit";"Roach";"Larva";345;2
"Unit";"Roach";"Larva";345;2
"Unit";"Roach";"Larva";345;2
"Unit";"Roach";"Larva";345;2
"Unit";"Roach";"Larva";345;2
"Unit";"Roach";"Larva";349;2
"Unit";"Roach";"Larva";349;2
"Unit";"Roach";"Larva";349;2
