"type";"unit_name";"on_building";"total_supply";"supply"
"Unit";"Overlord";"Larva";12;0
"Building";"Extractor";NA;17;0
"Building";"SpawningPool";NA;19;0
"Unit";"Overlord";"Larva";22;0
"Building";"Hatchery";NA;17;0
"Unit";"Zergling";"Larva";24;1
"Unit";"Zergling";"Larva";24;1
"Unit";"Queen";"Hatchery";22;2
"Unit";"Zergling";"Larva";25;1
"Unit";"Zergling";"Larva";25;1
"Unit";"Queen";"Hatchery";23;2
"Unit";"Zergling";"Larva";25;1
"Unit";"Zergling";"Larva";25;1
"Unit";"Zergling";"Larva";25;1
"Unit";"Zergling";"Larva";25;1
"Building";"SpineCrawler";NA;24;0
"Unit";"Overlord";"Larva";29;0
"Unit";"Overlord";"Larva";34;0
"Unit";"Zergling";"Larva";38;1
"Unit";"Zergling";"Larva";38;1
"Unit";"Zergling";"Larva";38;1
"Unit";"Zergling";"Larva";38;1
"Unit";"Queen";"Hatchery";38;2
"Unit";"Overlord";"Larva";48;0
"Building";"BanelingNest";NA;39;0
"Unit";"Zergling";"Larva";53;1
"Unit";"Zergling";"Larva";53;1
"Unit";"Zergling";"Larva";53;1
"Unit";"Zergling";"Larva";53;1
"Unit";"Zergling";"Larva";53;1
"Unit";"Zergling";"Larva";53;1
"Unit";"Zergling";"Larva";53;1
"Unit";"Zergling";"Larva";53;1
"Unit";"Zergling";"Larva";53;1
"Unit";"Zergling";"Larva";53;1
"Unit";"Zergling";"Larva";53;1
"Unit";"Zergling";"Larva";53;1
"Unit";"Zergling";"Larva";53;1
"Unit";"Zergling";"Larva";53;1
"Unit";"Overlord";"Larva";53;0
"Unit";"Zergling";"Larva";55;1
"Unit";"Zergling";"Larva";55;1
"Unit";"Zergling";"Larva";59;1
"Unit";"Zergling";"Larva";59;1
"Unit";"Baneling";"Zergling";67;0
"Unit";"Baneling";"Zergling";67;0
"Unit";"Baneling";"Zergling";67;0
"Unit";"Baneling";"Zergling";67;0
"Unit";"Baneling";"Zergling";67;0
"Building";"CreepTumorQueen";NA;67;0
"Unit";"Zergling";"Larva";67;1
"Unit";"Zergling";"Larva";67;1
"Unit";"Zergling";"Larva";67;1
"Unit";"Zergling";"Larva";67;1
"Unit";"Zergling";"Larva";67;1
"Unit";"Zergling";"Larva";67;1
"Building";"CreepTumorQueen";NA;71;0
"Unit";"Zergling";"Larva";71;1
"Unit";"Zergling";"Larva";71;1
"Unit";"Overlord";"Larva";71;0
"Building";"CreepTumor";NA;80;0
"Unit";"Baneling";"Zergling";83;0
"Unit";"Baneling";"Zergling";83;0
"Unit";"Baneling";"Zergling";83;0
"Unit";"Baneling";"Zergling";83;0
"Unit";"Baneling";"Zergling";83;0
"Building";"CreepTumorQueen";NA;83;0
"Building";"CreepTumor";NA;83;0
"Building";"Hatchery";NA;53;0
"Building";"Extractor";NA;83;0
"Building";"EvolutionChamber";NA;83;0
"Unit";"Zergling";"Larva";89;1
"Unit";"Zergling";"Larva";89;1
"Unit";"Zergling";"Larva";89;1
"Unit";"Zergling";"Larva";89;1
"Unit";"Zergling";"Larva";89;1
"Unit";"Zergling";"Larva";89;1
"Unit";"Zergling";"Larva";89;1
"Unit";"Zergling";"Larva";89;1
"Unit";"Zergling";"Larva";89;1
"Unit";"Zergling";"Larva";89;1
"Unit";"Zergling";"Larva";89;1
"Unit";"Zergling";"Larva";89;1
"Unit";"Zergling";"Larva";89;1
"Unit";"Zergling";"Larva";89;1
"Unit";"Zergling";"Larva";89;1
"Unit";"Zergling";"Larva";89;1
"Unit";"Zergling";"Larva";89;1
"Unit";"Zergling";"Larva";89;1
"Unit";"Zergling";"Larva";89;1
"Unit";"Zergling";"Larva";89;1
"Building";"CreepTumor";NA;89;0
"Building";"CreepTumor";NA;89;0
"Unit";"Zergling";"Larva";89;1
"Unit";"Zergling";"Larva";89;1
"Unit";"Zergling";"Larva";89;1
"Unit";"Zergling";"Larva";89;1
"Building";"CreepTumor";NA;89;0
"Unit";"Zergling";"Larva";89;1
"Unit";"Zergling";"Larva";89;1
"Unit";"Zergling";"Larva";89;1
"Unit";"Zergling";"Larva";89;1
"Unit";"Zergling";"Larva";91;1
"Unit";"Zergling";"Larva";91;1
"Building";"RoachWarren";NA;89;0
"Building";"Extractor";NA;119;0
"Building";"CreepTumor";NA;122;0
"Building";"CreepTumor";NA;130;0
"Unit";"Roach";"Larva";130;2
"Unit";"Roach";"Larva";130;2
"Unit";"Roach";"Larva";130;2
"Unit";"Roach";"Larva";130;2
"Building";"CreepTumor";NA;130;0
"Unit";"Overlord";"Larva";130;0
"Unit";"Overlord";"Larva";130;0
"Unit";"Overlord";"Larva";130;0
"Unit";"Overlord";"Larva";130;0
"Building";"CreepTumorQueen";NA;140;0
"Unit";"Overlord";"Larva";140;0
"Unit";"Overlord";"Larva";140;0
"Unit";"Overlord";"Larva";140;0
"Building";"CreepTumor";NA;140;0
"Unit";"Roach";"Larva";140;2
"Unit";"Roach";"Larva";140;2
"Unit";"Roach";"Larva";140;2
"Unit";"Roach";"Larva";140;2
"Building";"CreepTumor";NA;140;0
"Unit";"Roach";"Larva";140;2
"Building";"Extractor";NA;140;0
"Building";"CreepTumor";NA;144;0
"Unit";"Roach";"Larva";140;2
"Unit";"Roach";"Larva";140;2
"Unit";"Roach";"Larva";144;2
"Unit";"Roach";"Larva";144;2
"Unit";"Roach";"Larva";144;2
"Upgrade";"ZergMissileWeaponsLevel1";"EvolutionChamber";113;0
"Building";"CreepTumor";NA;154;0
"Unit";"Roach";"Larva";144;2
"Unit";"Roach";"Larva";144;2
"Unit";"Roach";"Larva";144;2
"Building";"CreepTumor";NA;158;0
"Unit";"Zergling";"Larva";158;1
"Unit";"Zergling";"Larva";158;1
"Unit";"Zergling";"Larva";158;1
"Unit";"Zergling";"Larva";158;1
"Unit";"Zergling";"Larva";158;1
"Unit";"Zergling";"Larva";158;1
"Unit";"Zergling";"Larva";158;1
"Unit";"Zergling";"Larva";158;1
"Unit";"Zergling";"Larva";158;1
"Unit";"Zergling";"Larva";158;1
"Unit";"Zergling";"Larva";158;1
"Unit";"Zergling";"Larva";158;1
"Upgrade";"GlialReconstitution";"RoachWarren";140;0
"Building";"CreepTumor";NA;182;0
"Unit";"Roach";"Larva";170;2
"Unit";"Roach";"Larva";170;2
"Unit";"Roach";"Larva";170;2
"Unit";"Roach";"Larva";170;2
"Unit";"Roach";"Larva";170;2
"Unit";"Roach";"Larva";170;2
"Unit";"Roach";"Larva";170;2
"Building";"CreepTumor";NA;182;0
"Unit";"Baneling";"Zergling";182;0
"Unit";"Baneling";"Zergling";182;0
"Unit";"Baneling";"Zergling";182;0
"Unit";"Baneling";"Zergling";182;0
"Unit";"Baneling";"Zergling";182;0
"Unit";"Baneling";"Zergling";182;0
"Unit";"Baneling";"Zergling";182;0
"Unit";"Baneling";"Zergling";182;0
"Unit";"Baneling";"Zergling";182;0
"Unit";"Baneling";"Zergling";182;0
"Unit";"Baneling";"Zergling";182;0
"Unit";"Baneling";"Zergling";182;0
"Unit";"Baneling";"Zergling";182;0
"Building";"CreepTumor";NA;196;0
"Unit";"Overlord";"Larva";196;0
"Unit";"Overlord";"Larva";196;0
"Building";"CreepTumor";NA;203;0
"Building";"Extractor";NA;196;0
"Building";"Extractor";NA;196;0
"Unit";"Baneling";"Zergling";203;0
"Unit";"Baneling";"Zergling";203;0
"Unit";"Baneling";"Zergling";203;0
"Unit";"Baneling";"Zergling";203;0
"Unit";"Baneling";"Zergling";203;0
"Unit";"Baneling";"Zergling";203;0
"Unit";"Baneling";"Zergling";203;0
"Unit";"Baneling";"Zergling";203;0
"Unit";"Baneling";"Zergling";203;0
"Unit";"Baneling";"Zergling";203;0
"Unit";"Zergling";"Larva";203;1
"Unit";"Zergling";"Larva";203;1
"Unit";"Zergling";"Larva";203;1
"Unit";"Zergling";"Larva";203;1
"Unit";"Zergling";"Larva";203;1
"Unit";"Zergling";"Larva";203;1
"Unit";"Zergling";"Larva";203;1
"Unit";"Zergling";"Larva";203;1
"Unit";"Zergling";"Larva";203;1
"Unit";"Zergling";"Larva";203;1
"Unit";"Zergling";"Larva";215;1
"Unit";"Zergling";"Larva";215;1
"Unit";"Zergling";"Larva";215;1
"Unit";"Zergling";"Larva";215;1
"Unit";"Zergling";"Larva";215;1
"Unit";"Zergling";"Larva";215;1
"Unit";"Zergling";"Larva";215;1
"Unit";"Zergling";"Larva";215;1
"Unit";"Zergling";"Larva";215;1
"Unit";"Zergling";"Larva";215;1
"Unit";"Zergling";"Larva";215;1
"Unit";"Zergling";"Larva";215;1
"Unit";"Zergling";"Larva";215;1
"Unit";"Zergling";"Larva";215;1
"Unit";"Zergling";"Larva";215;1
"Unit";"Zergling";"Larva";215;1
"Unit";"Zergling";"Larva";215;1
"Unit";"Zergling";"Larva";215;1
"Unit";"Zergling";"Larva";215;1
"Unit";"Zergling";"Larva";215;1
"Unit";"Zergling";"Larva";215;1
"Unit";"Zergling";"Larva";215;1
