"type";"unit_name";"on_building";"total_supply";"supply"
"Unit";"Overlord";"Larva";12;0
"Building";"Extractor";NA;18;0
"Unit";"Overlord";"Larva";21;0
"Building";"SpawningPool";NA;19;0
"Building";"Hatchery";NA;17;0
"Unit";"Zergling";"Larva";22;1
"Unit";"Zergling";"Larva";22;1
"Unit";"Zergling";"Larva";22;1
"Unit";"Zergling";"Larva";22;1
"Unit";"Zergling";"Larva";22;1
"Unit";"Zergling";"Larva";22;1
"Unit";"Queen";"Hatchery";22;2
"Unit";"Queen";"Hatchery";22;2
"Unit";"Overlord";"Larva";38;0
"Unit";"Overlord";"Larva";39;0
"Unit";"Overlord";"Larva";40;0
"Unit";"Zergling";"Larva";48;1
"Unit";"Zergling";"Larva";48;1
"Building";"Hatchery";NA;37;0
"Unit";"Zergling";"Larva";49;1
"Unit";"Zergling";"Larva";49;1
"Unit";"Zergling";"Larva";49;1
"Unit";"Zergling";"Larva";49;1
"Unit";"Zergling";"Larva";49;1
"Unit";"Zergling";"Larva";49;1
"Unit";"Zergling";"Larva";49;1
"Unit";"Zergling";"Larva";49;1
"Unit";"Zergling";"Larva";50;1
"Unit";"Zergling";"Larva";50;1
"Unit";"Zergling";"Larva";50;1
"Unit";"Zergling";"Larva";50;1
"Unit";"Zergling";"Larva";51;1
"Unit";"Zergling";"Larva";51;1
"Unit";"Zergling";"Larva";51;1
"Unit";"Zergling";"Larva";51;1
"Unit";"Zergling";"Larva";61;1
"Unit";"Zergling";"Larva";61;1
"Unit";"Zergling";"Larva";65;1
"Unit";"Zergling";"Larva";65;1
"Building";"EvolutionChamber";NA;51;0
"Unit";"Overlord";"Larva";69;0
"Unit";"Overlord";"Larva";71;0
"Building";"RoachWarren";NA;53;0
"Building";"Extractor";NA;73;0
"Unit";"Overlord";"Larva";78;0
"Building";"Extractor";NA;78;0
"Unit";"Queen";"Hatchery";85;2
"Unit";"Roach";"Larva";92;2
"Unit";"Overlord";"Larva";92;0
"Unit";"Roach";"Larva";92;2
"Unit";"Roach";"Larva";92;2
"Unit";"Roach";"Larva";92;2
"Building";"Extractor";NA;92;0
"Unit";"Roach";"Larva";92;2
"Unit";"Overlord";"Larva";92;0
"Unit";"Roach";"Larva";94;2
"Unit";"Roach";"Larva";96;2
"Unit";"Roach";"Larva";96;2
"Unit";"Roach";"Larva";96;2
"Unit";"Roach";"Larva";96;2
"Unit";"Roach";"Larva";104;2
"Unit";"Roach";"Larva";106;2
"Unit";"Roach";"Larva";106;2
"Building";"HydraliskDen";NA;110;0
"Upgrade";"ZergMissileWeaponsLevel1";"EvolutionChamber";89;0
"Upgrade";"GlialReconstitution";"RoachWarren";98;0
"Unit";"Overlord";"Larva";136;0
"Unit";"Overlord";"Larva";137;0
"Unit";"Overlord";"Larva";137;0
"Unit";"Overlord";"Larva";137;0
"Building";"SporeCrawler";NA;138;0
"Building";"SporeCrawler";NA;138;0
"Building";"SporeCrawler";NA;138;0
"Unit";"Roach";"Larva";140;2
"Unit";"Roach";"Larva";140;2
"Unit";"Roach";"Larva";140;2
"Building";"Extractor";NA;140;0
"Building";"Extractor";NA;140;0
"Unit";"Roach";"Larva";140;2
"Unit";"Roach";"Larva";140;2
"Unit";"Hydralisk";"Larva";140;2
"Unit";"Hydralisk";"Larva";140;2
"Unit";"Hydralisk";"Larva";140;2
"Unit";"Hydralisk";"Larva";140;2
"Unit";"Hydralisk";"Larva";140;2
"Unit";"Hydralisk";"Larva";146;2
"Unit";"Hydralisk";"Larva";148;2
"Unit";"Hydralisk";"Larva";148;2
"Unit";"Hydralisk";"Larva";148;2
"Unit";"Hydralisk";"Larva";150;2
"Unit";"Hydralisk";"Larva";150;2
"Unit";"Hydralisk";"Larva";150;2
"Unit";"Hydralisk";"Larva";152;2
"Upgrade";"EvolveMuscularAugments";"HydraliskDen";140;0
"Unit";"Hydralisk";"Larva";160;2
"Unit";"Hydralisk";"Larva";162;2
"Unit";"Roach";"Larva";162;2
"Unit";"Roach";"Larva";162;2
"Unit";"Roach";"Larva";164;2
"Unit";"Roach";"Larva";164;2
"Unit";"Roach";"Larva";168;2
"Unit";"Overlord";"Larva";172;0
"Unit";"Overlord";"Larva";172;0
"Unit";"Overlord";"Larva";172;0
"Building";"CreepTumorQueen";NA;176;0
"Unit";"Hydralisk";"Larva";172;2
"Unit";"Hydralisk";"Larva";176;2
"Unit";"Hydralisk";"Larva";176;2
"Unit";"Roach";"Larva";184;2
"Unit";"Roach";"Larva";188;2
"Unit";"Roach";"Larva";190;2
"Unit";"Roach";"Larva";190;2
"Unit";"Roach";"Larva";190;2
"Unit";"Roach";"Larva";190;2
"Unit";"Overlord";"Larva";192;0
"Unit";"Overlord";"Larva";192;0
"Unit";"Roach";"Larva";194;2
"Unit";"Roach";"Larva";200;2
"Unit";"Roach";"Larva";200;2
"Unit";"Roach";"Larva";208;2
"Unit";"Roach";"Larva";208;2
"Unit";"Roach";"Larva";208;2
"Unit";"Roach";"Larva";208;2
"Unit";"Roach";"Larva";208;2
"Unit";"Roach";"Larva";208;2
"Unit";"Roach";"Larva";210;2
"Unit";"Overlord";"Larva";210;0
"Unit";"Overlord";"Larva";210;0
"Unit";"Overlord";"Larva";210;0
"Unit";"Roach";"Larva";210;2
"Unit";"Roach";"Larva";210;2
"Unit";"Roach";"Larva";210;2
"Unit";"Roach";"Larva";226;2
"Unit";"Roach";"Larva";228;2
"Unit";"Roach";"Larva";228;2
"Unit";"Roach";"Larva";228;2
"Unit";"Roach";"Larva";228;2
"Upgrade";"ZergMissileWeaponsLevel2";"EvolutionChamber";164;0
"Unit";"Roach";"Larva";234;2
"Unit";"Roach";"Larva";234;2
"Unit";"Roach";"Larva";234;2
"Unit";"Roach";"Larva";234;2
"Building";"Hatchery";NA;192;0
"Unit";"Roach";"Larva";234;2
"Unit";"Roach";"Larva";234;2
"Unit";"Roach";"Larva";234;2
"Unit";"Roach";"Larva";234;2
"Unit";"Roach";"Larva";234;2
