"type";"unit_name";"on_building";"total_supply";"supply"
"Unit";"Overlord";"Larva";13;0
"Building";"Extractor";NA;17;0
"Unit";"Overlord";"Larva";21;0
"Building";"SpawningPool";NA;19;0
"Building";"Hatchery";NA;17;0
"Unit";"Zergling";"Larva";22;1
"Unit";"Zergling";"Larva";22;1
"Unit";"Zergling";"Larva";22;1
"Unit";"Zergling";"Larva";22;1
"Unit";"Zergling";"Larva";22;1
"Unit";"Zergling";"Larva";22;1
"Unit";"Zergling";"Larva";22;1
"Unit";"Zergling";"Larva";22;1
"Unit";"Zergling";"Larva";22;1
"Unit";"Zergling";"Larva";22;1
"Unit";"Queen";"Hatchery";22;2
"Unit";"Zergling";"Larva";28;1
"Unit";"Zergling";"Larva";28;1
"Unit";"Zergling";"Larva";34;1
"Unit";"Zergling";"Larva";34;1
"Building";"BanelingNest";NA;30;0
"Unit";"Zergling";"Larva";39;1
"Unit";"Zergling";"Larva";39;1
"Unit";"Zergling";"Larva";39;1
"Unit";"Zergling";"Larva";39;1
"Unit";"Overlord";"Larva";39;0
"Unit";"Queen";"Hatchery";39;2
"Unit";"Overlord";"Larva";43;0
"Building";"CreepTumorQueen";NA;49;0
"Building";"Hatchery";NA;39;0
"Building";"CreepTumor";NA;54;0
"Building";"CreepTumor";NA;60;0
"Unit";"Queen";"Hatchery";56;2
"Building";"Extractor";NA;63;0
"Building";"Extractor";NA;63;0
"Building";"CreepTumor";NA;72;0
"Building";"Hatchery";NA;53;0
"Unit";"Overlord";"Larva";74;0
"Unit";"Overlord";"Larva";74;0
"Building";"RoachWarren";NA;70;0
"Unit";"Overlord";"Larva";76;0
"Building";"CreepTumor";NA;80;0
"Unit";"Overlord";"Larva";80;0
"Building";"Extractor";NA;80;0
"Building";"EvolutionChamber";NA;80;0
"Building";"Extractor";NA;92;0
"Unit";"Overlord";"Larva";92;0
"Unit";"Overlord";"Larva";92;0
"Unit";"Overlord";"Larva";92;0
"Unit";"Overlord";"Larva";99;0
"Unit";"Roach";"Larva";99;2
"Unit";"Roach";"Larva";99;2
"Unit";"Roach";"Larva";99;2
"Unit";"Roach";"Larva";99;2
"Unit";"Roach";"Larva";99;2
"Unit";"Roach";"Larva";99;2
"Unit";"Roach";"Larva";99;2
"Building";"CreepTumor";NA;99;0
"Unit";"Roach";"Larva";99;2
"Unit";"Roach";"Larva";99;2
"Unit";"Roach";"Larva";99;2
"Unit";"Roach";"Larva";99;2
"Unit";"Roach";"Larva";99;2
"Unit";"Roach";"Larva";99;2
"Unit";"Roach";"Larva";99;2
"Unit";"Roach";"Larva";99;2
"Unit";"Roach";"Larva";99;2
"Unit";"Roach";"Larva";99;2
"Unit";"Roach";"Larva";113;2
"Unit";"Roach";"Larva";115;2
"Unit";"Roach";"Larva";115;2
"Unit";"Roach";"Larva";115;2
"Unit";"Roach";"Larva";117;2
"Unit";"Overlord";"Larva";129;0
"Unit";"Overlord";"Larva";129;0
"Unit";"Roach";"Larva";137;2
"Unit";"Roach";"Larva";137;2
"Unit";"Roach";"Larva";137;2
"Unit";"Roach";"Larva";137;2
"Unit";"Roach";"Larva";137;2
"Unit";"Roach";"Larva";137;2
"Unit";"Roach";"Larva";137;2
"Unit";"Roach";"Larva";137;2
"Unit";"Roach";"Larva";137;2
"Unit";"Roach";"Larva";139;2
"Unit";"Roach";"Larva";143;2
"Upgrade";"GlialReconstitution";"RoachWarren";113;0
"Unit";"Roach";"Larva";143;2
"Building";"Extractor";NA;143;0
"Unit";"Roach";"Larva";143;2
"Unit";"Roach";"Larva";143;2
"Unit";"Roach";"Larva";143;2
"Unit";"Roach";"Larva";143;2
"Building";"CreepTumor";NA;163;0
"Unit";"Roach";"Larva";161;2
"Unit";"Roach";"Larva";161;2
"Unit";"Zergling";"Larva";163;1
"Unit";"Zergling";"Larva";163;1
"Upgrade";"ZergMissileWeaponsLevel1";"EvolutionChamber";99;0
"Unit";"Roach";"Larva";163;2
"Unit";"Queen";"Hatchery";143;2
"Unit";"Zergling";"Larva";175;1
"Unit";"Zergling";"Larva";175;1
"Unit";"Zergling";"Larva";175;1
"Unit";"Zergling";"Larva";175;1
"Unit";"Zergling";"Larva";175;1
"Unit";"Zergling";"Larva";175;1
"Unit";"Zergling";"Larva";175;1
"Unit";"Zergling";"Larva";175;1
"Unit";"Zergling";"Larva";175;1
"Unit";"Zergling";"Larva";175;1
"Unit";"Roach";"Larva";183;2
"Unit";"Roach";"Larva";183;2
"Unit";"Roach";"Larva";183;2
"Unit";"Roach";"Larva";185;2
"Unit";"Roach";"Larva";185;2
"Unit";"Roach";"Larva";185;2
"Unit";"Roach";"Larva";185;2
"Unit";"Roach";"Larva";185;2
"Building";"HydraliskDen";NA;195;0
"Unit";"Roach";"Larva";204;2
"Unit";"Roach";"Larva";204;2
"Unit";"Roach";"Larva";204;2
"Unit";"Roach";"Larva";204;2
"Unit";"Overlord";"Larva";214;0
"Unit";"Roach";"Larva";214;2
"Unit";"Overlord";"Larva";214;0
"Unit";"Overlord";"Larva";214;0
"Unit";"Overlord";"Larva";214;0
"Building";"CreepTumor";NA;222;0
"Unit";"Roach";"Larva";222;2
"Unit";"Roach";"Larva";222;2
"Unit";"Roach";"Larva";222;2
"Unit";"Roach";"Larva";222;2
"Unit";"Roach";"Larva";222;2
"Unit";"Roach";"Larva";224;2
"Unit";"Roach";"Larva";224;2
"Unit";"Roach";"Larva";224;2
"Unit";"Roach";"Larva";224;2
"Unit";"Roach";"Larva";224;2
"Unit";"Roach";"Larva";224;2
"Unit";"Roach";"Larva";234;2
"Unit";"Roach";"Larva";234;2
"Building";"Hatchery";NA;204;0
"Unit";"Roach";"Larva";236;2
"Unit";"Roach";"Larva";236;2
"Unit";"Overlord";"Larva";246;0
"Unit";"Overlord";"Larva";246;0
"Unit";"Overlord";"Larva";246;0
"Unit";"Roach";"Larva";250;2
"Unit";"Roach";"Larva";250;2
"Unit";"Roach";"Larva";250;2
"Unit";"Roach";"Larva";250;2
"Unit";"Roach";"Larva";250;2
"Unit";"Roach";"Larva";250;2
"Unit";"Roach";"Larva";254;2
"Unit";"Roach";"Larva";254;2
"Unit";"Roach";"Larva";254;2
"Unit";"Roach";"Larva";254;2
"Building";"CreepTumor";NA;266;0
"Unit";"Roach";"Larva";277;2
"Unit";"Roach";"Larva";277;2
"Unit";"Roach";"Larva";277;2
"Building";"Extractor";NA;280;0
"Upgrade";"ZergMissileWeaponsLevel2";"EvolutionChamber";224;0
"Unit";"Hydralisk";"Larva";280;2
"Unit";"Hydralisk";"Larva";280;2
"Unit";"Hydralisk";"Larva";280;2
"Unit";"Hydralisk";"Larva";280;2
"Unit";"Queen";"Hatchery";280;2
"Unit";"Roach";"Larva";286;2
"Unit";"Hydralisk";"Larva";286;2
"Unit";"Roach";"Larva";286;2
"Unit";"Roach";"Larva";286;2
"Unit";"Hydralisk";"Larva";286;2
"Unit";"Hydralisk";"Larva";286;2
"Unit";"Hydralisk";"Larva";286;2
"Unit";"Hydralisk";"Larva";286;2
"Upgrade";"EvolveGroovedSpines";"HydraliskDen";279;0
"Unit";"Roach";"Larva";296;2
"Unit";"Roach";"Larva";296;2
"Unit";"Roach";"Larva";296;2
"Unit";"Roach";"Larva";296;2
"Unit";"Roach";"Larva";296;2
"Unit";"Roach";"Larva";296;2
"Unit";"Roach";"Larva";296;2
"Unit";"Overlord";"Larva";296;0
"Building";"LurkerDenMP";NA;266;0
"Building";"Extractor";NA;312;0
"Unit";"Roach";"Larva";326;2
"Unit";"Roach";"Larva";326;2
"Unit";"Roach";"Larva";326;2
"Unit";"Roach";"Larva";326;2
"Unit";"Roach";"Larva";326;2
"Unit";"Roach";"Larva";326;2
"Unit";"Roach";"Larva";326;2
"Unit";"Zergling";"Larva";329;1
"Unit";"Zergling";"Larva";329;1
"Upgrade";"EvolveMuscularAugments";"HydraliskDen";329;0
"Unit";"Roach";"Larva";345;2
"Unit";"Roach";"Larva";345;2
"Unit";"Roach";"Larva";345;2
"Unit";"Roach";"Larva";345;2
"Unit";"Roach";"Larva";345;2
"Unit";"Roach";"Larva";345;2
"Unit";"Roach";"Larva";345;2
"Unit";"Roach";"Larva";345;2
"Unit";"Roach";"Larva";345;2
"Unit";"Roach";"Larva";345;2
"Unit";"Roach";"Larva";345;2
"Unit";"Roach";"Larva";345;2
"Unit";"Roach";"Larva";345;2
"Unit";"Roach";"Larva";345;2
"Unit";"Roach";"Larva";345;2
"Unit";"Roach";"Larva";345;2
"Unit";"Roach";"Larva";345;2
"Unit";"Hydralisk";"Larva";372;2
"Unit";"Hydralisk";"Larva";372;2
"Unit";"Hydralisk";"Larva";372;2
"Unit";"Hydralisk";"Larva";372;2
"Unit";"Hydralisk";"Larva";372;2
"Unit";"Hydralisk";"Larva";372;2
"Upgrade";"ZergGroundArmorsLevel1";"EvolutionChamber";343;0
"Unit";"Roach";"Larva";400;2
"Unit";"Roach";"Larva";400;2
"Unit";"Roach";"Larva";400;2
"Unit";"Roach";"Larva";400;2
"Unit";"Roach";"Larva";400;2
"Unit";"Roach";"Larva";400;2
"Unit";"Roach";"Larva";400;2
"Unit";"Roach";"Larva";400;2
"Unit";"Roach";"Larva";400;2
"Unit";"Roach";"Larva";400;2
