"type";"unit_name";"on_building";"total_supply";"supply"
"Unit";"Overlord";"Larva";12;0
"Building";"Extractor";NA;18;0
"Building";"SpawningPool";NA;19;0
"Unit";"Overlord";"Larva";21;0
"Building";"Hatchery";NA;17;0
"Unit";"Zergling";"Larva";22;1
"Unit";"Zergling";"Larva";22;1
"Unit";"Queen";"Hatchery";22;2
"Unit";"Queen";"Hatchery";22;2
"Unit";"Queen";"Hatchery";33;2
"Unit";"Overlord";"Larva";33;0
"Unit";"Zergling";"Larva";35;1
"Unit";"Zergling";"Larva";35;1
"Unit";"Zergling";"Larva";35;1
"Unit";"Zergling";"Larva";35;1
"Unit";"Zergling";"Larva";35;1
"Unit";"Zergling";"Larva";35;1
"Building";"BanelingNest";NA;33;0
"Unit";"Zergling";"Larva";37;1
"Unit";"Zergling";"Larva";37;1
"Building";"CreepTumorQueen";NA;43;0
"Unit";"Zergling";"Larva";43;1
"Unit";"Zergling";"Larva";43;1
"Unit";"Zergling";"Larva";43;1
"Unit";"Zergling";"Larva";43;1
"Unit";"Zergling";"Larva";43;1
"Unit";"Zergling";"Larva";43;1
"Unit";"Zergling";"Larva";43;1
"Unit";"Zergling";"Larva";43;1
"Unit";"Zergling";"Larva";43;1
"Unit";"Zergling";"Larva";43;1
"Unit";"Zergling";"Larva";43;1
"Unit";"Zergling";"Larva";43;1
"Building";"Hatchery";NA;29;0
"Unit";"Overlord";"Larva";47;0
"Unit";"Baneling";"Zergling";59;0
"Unit";"Baneling";"Zergling";59;0
"Unit";"Baneling";"Zergling";59;0
"Unit";"Baneling";"Zergling";59;0
"Unit";"Zergling";"Larva";59;1
"Unit";"Zergling";"Larva";59;1
"Unit";"Zergling";"Larva";59;1
"Unit";"Zergling";"Larva";59;1
"Unit";"Zergling";"Larva";59;1
"Unit";"Zergling";"Larva";59;1
"Unit";"Zergling";"Larva";60;1
"Unit";"Zergling";"Larva";60;1
"Unit";"Zergling";"Larva";60;1
"Unit";"Zergling";"Larva";60;1
"Unit";"Zergling";"Larva";73;1
"Unit";"Zergling";"Larva";73;1
"Unit";"Zergling";"Larva";73;1
"Unit";"Zergling";"Larva";73;1
"Unit";"Zergling";"Larva";73;1
"Unit";"Zergling";"Larva";73;1
"Unit";"Zergling";"Larva";73;1
"Unit";"Zergling";"Larva";73;1
"Unit";"Zergling";"Larva";73;1
"Unit";"Zergling";"Larva";73;1
"Unit";"Zergling";"Larva";73;1
"Unit";"Zergling";"Larva";73;1
"Unit";"Zergling";"Larva";73;1
"Unit";"Zergling";"Larva";73;1
"Unit";"Baneling";"Zergling";73;0
"Unit";"Zergling";"Larva";85;1
"Unit";"Zergling";"Larva";85;1
"Unit";"Zergling";"Larva";85;1
"Unit";"Zergling";"Larva";85;1
"Unit";"Zergling";"Larva";85;1
"Unit";"Zergling";"Larva";85;1
"Unit";"Zergling";"Larva";85;1
"Unit";"Zergling";"Larva";85;1
"Unit";"Zergling";"Larva";87;1
"Unit";"Zergling";"Larva";87;1
"Unit";"Zergling";"Larva";87;1
"Unit";"Zergling";"Larva";87;1
"Unit";"Baneling";"Zergling";87;0
"Unit";"Baneling";"Zergling";87;0
"Unit";"Baneling";"Zergling";87;0
"Unit";"Baneling";"Zergling";87;0
"Unit";"Baneling";"Zergling";87;0
"Unit";"Baneling";"Zergling";87;0
"Unit";"Zergling";"Larva";87;1
"Unit";"Zergling";"Larva";87;1
"Unit";"Zergling";"Larva";87;1
"Unit";"Zergling";"Larva";87;1
"Unit";"Zergling";"Larva";95;1
"Unit";"Zergling";"Larva";95;1
"Unit";"Zergling";"Larva";95;1
"Unit";"Zergling";"Larva";95;1
"Unit";"Zergling";"Larva";95;1
"Unit";"Zergling";"Larva";95;1
"Unit";"Zergling";"Larva";95;1
"Unit";"Zergling";"Larva";95;1
"Unit";"Baneling";"Zergling";99;0
"Unit";"Baneling";"Zergling";99;0
"Unit";"Zergling";"Larva";99;1
"Unit";"Zergling";"Larva";99;1
"Unit";"Zergling";"Larva";99;1
"Unit";"Zergling";"Larva";99;1
"Unit";"Zergling";"Larva";99;1
"Unit";"Zergling";"Larva";99;1
"Unit";"Zergling";"Larva";99;1
"Unit";"Zergling";"Larva";99;1
"Unit";"Zergling";"Larva";99;1
"Unit";"Zergling";"Larva";99;1
"Building";"CreepTumor";NA;111;0
"Unit";"Overlord";"Larva";99;0
"Unit";"Overlord";"Larva";99;0
"Unit";"Baneling";"Zergling";111;0
"Unit";"Baneling";"Zergling";111;0
"Unit";"Baneling";"Zergling";111;0
"Unit";"Overlord";"Larva";111;0
"Unit";"Zergling";"Larva";119;1
"Unit";"Zergling";"Larva";119;1
"Unit";"Zergling";"Larva";119;1
"Unit";"Zergling";"Larva";119;1
"Unit";"Zergling";"Larva";121;1
"Unit";"Zergling";"Larva";121;1
"Unit";"Zergling";"Larva";121;1
"Unit";"Zergling";"Larva";121;1
"Unit";"Zergling";"Larva";121;1
"Unit";"Zergling";"Larva";121;1
"Unit";"Baneling";"Zergling";121;0
"Unit";"Baneling";"Zergling";121;0
"Unit";"Zergling";"Larva";125;1
"Unit";"Zergling";"Larva";125;1
"Unit";"Zergling";"Larva";125;1
"Unit";"Zergling";"Larva";125;1
"Unit";"Zergling";"Larva";125;1
"Unit";"Zergling";"Larva";125;1
"Unit";"Zergling";"Larva";125;1
"Unit";"Zergling";"Larva";125;1
"Unit";"Zergling";"Larva";125;1
"Unit";"Zergling";"Larva";125;1
"Unit";"Zergling";"Larva";125;1
"Unit";"Zergling";"Larva";125;1
"Unit";"Zergling";"Larva";125;1
"Unit";"Zergling";"Larva";125;1
"Unit";"Zergling";"Larva";125;1
"Unit";"Zergling";"Larva";125;1
"Unit";"Zergling";"Larva";131;1
"Unit";"Zergling";"Larva";131;1
"Unit";"Zergling";"Larva";131;1
"Unit";"Zergling";"Larva";131;1
"Unit";"Zergling";"Larva";133;1
"Unit";"Zergling";"Larva";133;1
"Unit";"Zergling";"Larva";137;1
"Unit";"Zergling";"Larva";137;1
"Unit";"Zergling";"Larva";137;1
"Unit";"Zergling";"Larva";137;1
"Unit";"Zergling";"Larva";139;1
"Unit";"Zergling";"Larva";139;1
"Unit";"Baneling";"Zergling";147;0
"Unit";"Baneling";"Zergling";147;0
"Unit";"Zergling";"Larva";147;1
"Unit";"Zergling";"Larva";147;1
"Unit";"Zergling";"Larva";147;1
"Unit";"Zergling";"Larva";147;1
"Unit";"Zergling";"Larva";147;1
"Unit";"Zergling";"Larva";147;1
"Unit";"Zergling";"Larva";147;1
"Unit";"Zergling";"Larva";147;1
"Unit";"Zergling";"Larva";159;1
"Unit";"Zergling";"Larva";159;1
"Building";"EvolutionChamber";NA;147;0
"Unit";"Baneling";"Zergling";168;0
"Unit";"Baneling";"Zergling";168;0
"Building";"RoachWarren";NA;147;0
"Unit";"Baneling";"Zergling";176;0
"Unit";"Baneling";"Zergling";176;0
"Unit";"Zergling";"Larva";176;1
"Unit";"Zergling";"Larva";176;1
"Unit";"Zergling";"Larva";176;1
"Unit";"Zergling";"Larva";176;1
"Unit";"Zergling";"Larva";176;1
"Unit";"Zergling";"Larva";176;1
"Unit";"Zergling";"Larva";176;1
"Unit";"Zergling";"Larva";176;1
"Unit";"Zergling";"Larva";176;1
"Unit";"Zergling";"Larva";176;1
"Unit";"Zergling";"Larva";176;1
"Unit";"Zergling";"Larva";176;1
"Unit";"Baneling";"Zergling";176;0
"Unit";"Queen";"Hatchery";170;2
"Unit";"Baneling";"Zergling";194;0
"Unit";"Zergling";"Larva";194;1
"Unit";"Zergling";"Larva";194;1
"Unit";"Queen";"Hatchery";176;2
"Unit";"Zergling";"Larva";194;1
"Unit";"Zergling";"Larva";194;1
"Unit";"Zergling";"Larva";194;1
"Unit";"Zergling";"Larva";194;1
"Unit";"Zergling";"Larva";194;1
"Unit";"Zergling";"Larva";194;1
"Unit";"Zergling";"Larva";194;1
"Unit";"Zergling";"Larva";194;1
"Unit";"Zergling";"Larva";194;1
"Unit";"Zergling";"Larva";194;1
"Unit";"Zergling";"Larva";194;1
"Unit";"Zergling";"Larva";194;1
"Unit";"Zergling";"Larva";194;1
"Unit";"Zergling";"Larva";194;1
"Unit";"Baneling";"Zergling";194;0
"Unit";"Baneling";"Zergling";194;0
"Building";"Extractor";NA;194;0
"Building";"Extractor";NA;194;0
"Unit";"Roach";"Larva";198;2
"Unit";"Zergling";"Larva";212;1
"Unit";"Zergling";"Larva";212;1
"Unit";"Baneling";"Zergling";212;0
"Unit";"Zergling";"Larva";212;1
"Unit";"Zergling";"Larva";212;1
"Unit";"Zergling";"Larva";212;1
"Unit";"Zergling";"Larva";212;1
"Unit";"Zergling";"Larva";212;1
"Unit";"Zergling";"Larva";212;1
"Unit";"Zergling";"Larva";212;1
"Unit";"Zergling";"Larva";212;1
"Unit";"Zergling";"Larva";212;1
"Unit";"Zergling";"Larva";212;1
"Unit";"Zergling";"Larva";212;1
"Unit";"Zergling";"Larva";212;1
"Unit";"Zergling";"Larva";212;1
"Unit";"Zergling";"Larva";212;1
"Unit";"Zergling";"Larva";212;1
"Unit";"Zergling";"Larva";212;1
"Unit";"Baneling";"Zergling";228;0
"Unit";"Baneling";"Zergling";228;0
"Unit";"Baneling";"Zergling";228;0
"Unit";"Zergling";"Larva";222;1
"Unit";"Zergling";"Larva";222;1
"Unit";"Zergling";"Larva";224;1
"Unit";"Zergling";"Larva";224;1
"Unit";"Zergling";"Larva";226;1
"Unit";"Zergling";"Larva";226;1
"Unit";"Zergling";"Larva";228;1
"Unit";"Zergling";"Larva";228;1
"Unit";"Zergling";"Larva";228;1
"Unit";"Zergling";"Larva";228;1
"Unit";"Zergling";"Larva";228;1
"Unit";"Zergling";"Larva";228;1
"Upgrade";"ZergMissileWeaponsLevel1";"EvolutionChamber";184;0
"Unit";"Baneling";"Zergling";232;0
"Unit";"Roach";"Larva";232;2
"Unit";"Overlord";"Larva";232;0
"Unit";"Roach";"Larva";232;2
"Unit";"Zergling";"Larva";232;1
"Unit";"Zergling";"Larva";232;1
"Unit";"Overlord";"Larva";232;0
"Unit";"Baneling";"Zergling";244;0
"Unit";"Baneling";"Zergling";244;0
"Unit";"Baneling";"Zergling";244;0
"Unit";"Overlord";"Larva";244;0
"Unit";"Overlord";"Larva";244;0
"Unit";"Overlord";"Larva";244;0
"Unit";"Overlord";"Larva";244;0
"Unit";"Baneling";"Zergling";250;0
"Unit";"Zergling";"Larva";250;1
"Unit";"Zergling";"Larva";250;1
"Unit";"Roach";"Larva";250;2
"Unit";"Roach";"Larva";250;2
"Unit";"Roach";"Larva";250;2
"Unit";"Zergling";"Larva";250;1
"Unit";"Zergling";"Larva";250;1
"Unit";"Baneling";"Zergling";250;0
"Unit";"Baneling";"Zergling";250;0
"Unit";"Baneling";"Zergling";250;0
"Building";"Extractor";NA;250;0
"Unit";"Baneling";"Zergling";250;0
"Unit";"Baneling";"Zergling";258;0
"Unit";"Zergling";"Larva";250;1
"Unit";"Zergling";"Larva";250;1
"Unit";"Zergling";"Larva";250;1
"Unit";"Zergling";"Larva";250;1
"Unit";"Baneling";"Zergling";258;0
"Unit";"Roach";"Larva";250;2
"Unit";"Roach";"Larva";260;2
"Unit";"Roach";"Larva";260;2
"Unit";"Zergling";"Larva";260;1
"Unit";"Zergling";"Larva";260;1
"Unit";"Zergling";"Larva";260;1
"Unit";"Zergling";"Larva";260;1
"Unit";"Zergling";"Larva";260;1
"Unit";"Zergling";"Larva";260;1
"Unit";"Zergling";"Larva";260;1
"Unit";"Zergling";"Larva";260;1
"Unit";"Zergling";"Larva";260;1
"Unit";"Zergling";"Larva";260;1
"Unit";"Zergling";"Larva";260;1
"Unit";"Zergling";"Larva";260;1
"Unit";"Roach";"Larva";266;2
"Unit";"Roach";"Larva";266;2
"Unit";"Roach";"Larva";266;2
"Unit";"Zergling";"Larva";266;1
"Unit";"Zergling";"Larva";266;1
"Unit";"Zergling";"Larva";266;1
"Unit";"Zergling";"Larva";266;1
"Unit";"Zergling";"Larva";266;1
"Unit";"Zergling";"Larva";266;1
"Unit";"Zergling";"Larva";266;1
"Unit";"Zergling";"Larva";266;1
"Unit";"Zergling";"Larva";266;1
"Unit";"Zergling";"Larva";266;1
"Unit";"Roach";"Larva";270;2
"Unit";"Zergling";"Larva";278;1
"Unit";"Zergling";"Larva";278;1
"Unit";"Zergling";"Larva";282;1
"Unit";"Zergling";"Larva";282;1
"Unit";"Roach";"Larva";298;2
