"type";"unit_name";"on_building";"total_supply";"supply"
"Unit";"Overlord";"Larva";12;0
"Building";"SpawningPool";NA;14;0
"Unit";"Zergling";"Larva";17;1
"Unit";"Zergling";"Larva";17;1
"Unit";"Zergling";"Larva";17;1
"Unit";"Zergling";"Larva";17;1
"Unit";"Zergling";"Larva";17;1
"Unit";"Zergling";"Larva";17;1
"Unit";"Zergling";"Larva";17;1
"Unit";"Zergling";"Larva";17;1
"Unit";"Zergling";"Larva";23;1
"Unit";"Zergling";"Larva";23;1
"Unit";"Zergling";"Larva";25;1
"Unit";"Zergling";"Larva";25;1
"Building";"Hatchery";NA;17;0
"Unit";"Zergling";"Larva";27;1
"Unit";"Zergling";"Larva";27;1
"Unit";"Zergling";"Larva";29;1
"Unit";"Zergling";"Larva";29;1
"Unit";"Zergling";"Larva";31;1
"Unit";"Zergling";"Larva";31;1
"Unit";"Zergling";"Larva";33;1
"Unit";"Zergling";"Larva";33;1
"Unit";"Overlord";"Larva";42;0
"Unit";"Overlord";"Larva";42;0
"Building";"Hatchery";NA;42;0
"Unit";"Queen";"Hatchery";48;2
"Building";"Extractor";NA;51;0
"Unit";"Overlord";"Larva";53;0
"Unit";"Queen";"Hatchery";51;2
"Unit";"Queen";"Hatchery";55;2
"Unit";"Overlord";"Larva";62;0
"Unit";"Queen";"Hatchery";59;2
"Building";"SporeCrawler";NA;65;0
"Building";"SporeCrawler";NA;66;0
"Building";"SporeCrawler";NA;68;0
"Building";"CreepTumorQueen";NA;79;0
"Unit";"Overlord";"Larva";74;0
"Building";"Extractor";NA;82;0
"Unit";"Overlord";"Larva";84;0
"Building";"Extractor";NA;84;0
"Unit";"Queen";"Hatchery";79;2
"Building";"EvolutionChamber";NA;92;0
"Building";"Extractor";NA;95;0
"Building";"Extractor";NA;95;0
"Building";"Extractor";NA;109;0
"Building";"EvolutionChamber";NA;103;0
"Building";"HydraliskDen";NA;103;0
"Unit";"Overlord";"Larva";109;0
"Unit";"Overlord";"Larva";111;0
"Unit";"Zergling";"Larva";113;1
"Unit";"Zergling";"Larva";113;1
"Unit";"Zergling";"Larva";113;1
"Unit";"Zergling";"Larva";113;1
"Unit";"Zergling";"Larva";113;1
"Unit";"Zergling";"Larva";113;1
"Unit";"Zergling";"Larva";113;1
"Unit";"Zergling";"Larva";113;1
"Unit";"Overlord";"Larva";113;0
"Unit";"Zergling";"Larva";113;1
"Unit";"Zergling";"Larva";113;1
"Unit";"Zergling";"Larva";113;1
"Unit";"Zergling";"Larva";113;1
"Unit";"Zergling";"Larva";113;1
"Unit";"Zergling";"Larva";113;1
"Unit";"Zergling";"Larva";113;1
"Unit";"Zergling";"Larva";113;1
"Unit";"Zergling";"Larva";113;1
"Unit";"Zergling";"Larva";113;1
"Unit";"Zergling";"Larva";121;1
"Unit";"Zergling";"Larva";121;1
"Unit";"Zergling";"Larva";121;1
"Unit";"Zergling";"Larva";121;1
"Unit";"Zergling";"Larva";121;1
"Unit";"Zergling";"Larva";121;1
"Building";"CreepTumorQueen";NA;132;0
"Unit";"Overlord";"Larva";121;0
"Unit";"Hydralisk";"Larva";127;2
"Unit";"Overlord";"Larva";142;0
"Unit";"Overlord";"Larva";142;0
"Building";"Hatchery";NA;109;0
"Unit";"Overlord";"Larva";142;0
"Unit";"Hydralisk";"Larva";142;2
"Unit";"Hydralisk";"Larva";142;2
"Unit";"Hydralisk";"Larva";144;2
"Unit";"Hydralisk";"Larva";144;2
"Building";"CreepTumorQueen";NA;150;0
"Unit";"Hydralisk";"Larva";144;2
"Building";"CreepTumor";NA;150;0
"Building";"Extractor";NA;147;0
"Building";"Extractor";NA;150;0
"Upgrade";"EvolveGroovedSpines";"HydraliskDen";141;0
"Building";"SporeCrawler";NA;150;0
"Unit";"Queen";"Hatchery";148;2
"Upgrade";"ZergMissileWeaponsLevel1";"EvolutionChamber";113;0
"Unit";"Overlord";"Larva";167;0
"Unit";"Overlord";"Larva";167;0
"Unit";"Hydralisk";"Larva";163;2
"Unit";"Hydralisk";"Larva";163;2
"Building";"CreepTumor";NA;171;0
"Unit";"Hydralisk";"Larva";169;2
"Unit";"Hydralisk";"Larva";169;2
"Unit";"Hydralisk";"Larva";171;2
"Unit";"Hydralisk";"Larva";171;2
"Unit";"Hydralisk";"Larva";171;2
"Unit";"Hydralisk";"Larva";171;2
"Upgrade";"ZergGroundArmorsLevel1";"EvolutionChamber";138;0
"Unit";"Overlord";"Larva";173;0
"Unit";"Hydralisk";"Larva";171;2
"Unit";"Hydralisk";"Larva";171;2
"Unit";"Hydralisk";"Larva";173;2
"Building";"CreepTumor";NA;181;0
"Unit";"Hydralisk";"Larva";173;2
"Unit";"Hydralisk";"Larva";175;2
"Unit";"Hydralisk";"Larva";181;2
"Unit";"Hydralisk";"Larva";181;2
"Unit";"Hydralisk";"Larva";181;2
"Building";"CreepTumor";NA;197;0
"Unit";"Hydralisk";"Larva";189;2
"Unit";"Hydralisk";"Larva";189;2
"Unit";"Hydralisk";"Larva";189;2
"Unit";"Zergling";"Larva";197;1
"Unit";"Zergling";"Larva";197;1
"Unit";"Zergling";"Larva";197;1
"Unit";"Zergling";"Larva";197;1
"Unit";"Zergling";"Larva";197;1
"Unit";"Zergling";"Larva";197;1
"Building";"CreepTumorQueen";NA;203;0
"Unit";"Zergling";"Larva";197;1
"Unit";"Zergling";"Larva";197;1
"Building";"CreepTumor";NA;203;0
"Unit";"Hydralisk";"Larva";195;2
"Unit";"Zergling";"Larva";199;1
"Unit";"Zergling";"Larva";199;1
"Unit";"Zergling";"Larva";199;1
"Unit";"Zergling";"Larva";199;1
"Unit";"Zergling";"Larva";199;1
"Unit";"Zergling";"Larva";199;1
"Unit";"Zergling";"Larva";199;1
"Unit";"Zergling";"Larva";199;1
"Unit";"Zergling";"Larva";199;1
"Unit";"Zergling";"Larva";199;1
"Building";"Hatchery";NA;164;0
"Unit";"Zergling";"Larva";205;1
"Unit";"Zergling";"Larva";205;1
"Unit";"Zergling";"Larva";205;1
"Unit";"Zergling";"Larva";205;1
"Unit";"Zergling";"Larva";205;1
"Unit";"Zergling";"Larva";205;1
"Unit";"Zergling";"Larva";205;1
"Unit";"Zergling";"Larva";205;1
"Unit";"Zergling";"Larva";205;1
"Unit";"Zergling";"Larva";205;1
"Unit";"Overlord";"Larva";211;0
"Unit";"Overlord";"Larva";211;0
"Upgrade";"EvolveMuscularAugments";"HydraliskDen";181;0
"Unit";"Overlord";"Larva";219;0
"Unit";"Overlord";"Larva";219;0
"Building";"CreepTumor";NA;241;0
"Building";"CreepTumor";NA;241;0
"Unit";"Hydralisk";"Larva";231;2
"Unit";"Overlord";"Larva";241;0
"Unit";"Overlord";"Larva";241;0
"Unit";"Overlord";"Larva";241;0
"Unit";"Hydralisk";"Larva";231;2
"Unit";"Hydralisk";"Larva";231;2
"Unit";"Hydralisk";"Larva";231;2
"Building";"CreepTumor";NA;241;0
"Unit";"Hydralisk";"Larva";241;2
"Unit";"Hydralisk";"Larva";241;2
"Unit";"Hydralisk";"Larva";241;2
"Building";"InfestationPit";NA;231;0
"Unit";"Hydralisk";"Larva";241;2
"Unit";"Hydralisk";"Larva";241;2
"Unit";"Hydralisk";"Larva";241;2
"Unit";"Hydralisk";"Larva";241;2
"Unit";"Hydralisk";"Larva";241;2
"Unit";"Hydralisk";"Larva";241;2
"Unit";"Hydralisk";"Larva";243;2
"Unit";"Hydralisk";"Larva";243;2
"Unit";"Hydralisk";"Larva";249;2
"Unit";"Hydralisk";"Larva";251;2
"Unit";"Hydralisk";"Larva";251;2
"Building";"CreepTumor";NA;267;0
"Unit";"Hydralisk";"Larva";257;2
"Unit";"Hydralisk";"Larva";261;2
"Unit";"Zergling";"Larva";277;1
"Unit";"Zergling";"Larva";277;1
"Unit";"Zergling";"Larva";277;1
"Unit";"Zergling";"Larva";277;1
"Unit";"Zergling";"Larva";281;1
"Unit";"Zergling";"Larva";281;1
"Unit";"Zergling";"Larva";281;1
"Unit";"Zergling";"Larva";281;1
"Unit";"Zergling";"Larva";281;1
"Unit";"Zergling";"Larva";281;1
"Unit";"Zergling";"Larva";281;1
"Unit";"Zergling";"Larva";281;1
"Unit";"Zergling";"Larva";281;1
"Unit";"Zergling";"Larva";281;1
"Unit";"Zergling";"Larva";281;1
"Unit";"Zergling";"Larva";281;1
"Unit";"Zergling";"Larva";281;1
"Unit";"Zergling";"Larva";281;1
"Unit";"Zergling";"Larva";281;1
"Unit";"Zergling";"Larva";281;1
"Unit";"Zergling";"Larva";281;1
"Unit";"Zergling";"Larva";281;1
"Unit";"Zergling";"Larva";281;1
"Unit";"Zergling";"Larva";281;1
"Unit";"Zergling";"Larva";281;1
"Unit";"Zergling";"Larva";281;1
"Unit";"Zergling";"Larva";281;1
"Unit";"Zergling";"Larva";281;1
"Upgrade";"ZergMissileWeaponsLevel2";"EvolutionChamber";215;0
"Unit";"Zergling";"Larva";281;1
"Unit";"Zergling";"Larva";281;1
"Unit";"Zergling";"Larva";281;1
"Unit";"Zergling";"Larva";281;1
"Unit";"Zergling";"Larva";281;1
"Unit";"Zergling";"Larva";281;1
"Unit";"Zergling";"Larva";281;1
"Unit";"Zergling";"Larva";281;1
"Unit";"Zergling";"Larva";285;1
"Unit";"Zergling";"Larva";285;1
"Unit";"Hydralisk";"Larva";281;2
"Unit";"Hydralisk";"Larva";281;2
"Unit";"Hydralisk";"Larva";281;2
"Unit";"Zergling";"Larva";285;1
"Unit";"Zergling";"Larva";285;1
