"type";"unit_name";"on_building";"total_supply";"supply"
"Unit";"Overlord";"Larva";12;0
"Building";"Extractor";NA;17;0
"Building";"SpawningPool";NA;19;0
"Unit";"Zergling";"Larva";21;1
"Unit";"Zergling";"Larva";21;1
"Unit";"Overlord";"Larva";21;0
"Unit";"Zergling";"Larva";24;1
"Unit";"Zergling";"Larva";24;1
"Unit";"Queen";"Hatchery";21;2
"Unit";"Zergling";"Larva";24;1
"Unit";"Zergling";"Larva";24;1
"Building";"Hatchery";NA;21;0
"Unit";"Queen";"Hatchery";30;2
"Building";"CreepTumorQueen";NA;33;0
"Unit";"Queen";"Hatchery";30;2
"Unit";"Overlord";"Larva";38;0
"Unit";"Overlord";"Larva";38;0
"Building";"Hatchery";NA;30;0
"Building";"CreepTumor";NA;44;0
"Building";"EvolutionChamber";NA;44;0
"Building";"SporeCrawler";NA;44;0
"Building";"SporeCrawler";NA;44;0
"Building";"SporeCrawler";NA;44;0
"Building";"CreepTumorQueen";NA;54;0
"Unit";"Overlord";"Larva";61;0
"Unit";"Overlord";"Larva";61;0
"Building";"CreepTumor";NA;61;0
"Building";"Extractor";NA;61;0
"Unit";"Queen";"Hatchery";63;2
"Unit";"Zergling";"Larva";73;1
"Unit";"Zergling";"Larva";73;1
"Unit";"Zergling";"Larva";73;1
"Unit";"Zergling";"Larva";73;1
"Unit";"Zergling";"Larva";73;1
"Unit";"Zergling";"Larva";73;1
"Unit";"Zergling";"Larva";73;1
"Unit";"Zergling";"Larva";73;1
"Unit";"Zergling";"Larva";73;1
"Unit";"Zergling";"Larva";73;1
"Unit";"Zergling";"Larva";73;1
"Unit";"Zergling";"Larva";73;1
"Unit";"Zergling";"Larva";73;1
"Unit";"Zergling";"Larva";73;1
"Building";"CreepTumor";NA;75;0
"Unit";"Overlord";"Larva";75;0
"Unit";"Overlord";"Larva";75;0
"Unit";"Overlord";"Larva";75;0
"Unit";"Overlord";"Larva";76;0
"Unit";"Overlord";"Larva";76;0
"Unit";"Overlord";"Larva";76;0
"Unit";"Zergling";"Larva";90;1
"Unit";"Zergling";"Larva";90;1
"Unit";"Zergling";"Larva";90;1
"Unit";"Zergling";"Larva";90;1
"Unit";"Zergling";"Larva";90;1
"Unit";"Zergling";"Larva";90;1
"Unit";"Zergling";"Larva";90;1
"Unit";"Zergling";"Larva";90;1
"Unit";"Zergling";"Larva";90;1
"Unit";"Zergling";"Larva";90;1
"Unit";"Zergling";"Larva";90;1
"Unit";"Zergling";"Larva";90;1
"Building";"Hatchery";NA;63;0
"Upgrade";"ZergMeleeWeaponsLevel1";"EvolutionChamber";63;0
"Building";"HydraliskDen";NA;90;0
"Building";"Extractor";NA;90;0
"Building";"Extractor";NA;90;0
"Unit";"Zergling";"Larva";102;1
"Unit";"Zergling";"Larva";102;1
"Unit";"Zergling";"Larva";102;1
"Unit";"Zergling";"Larva";102;1
"Unit";"Zergling";"Larva";102;1
"Unit";"Zergling";"Larva";102;1
"Unit";"Zergling";"Larva";102;1
"Unit";"Zergling";"Larva";102;1
"Unit";"Zergling";"Larva";102;1
"Unit";"Zergling";"Larva";102;1
"Unit";"Zergling";"Larva";102;1
"Unit";"Zergling";"Larva";102;1
"Unit";"Zergling";"Larva";102;1
"Unit";"Zergling";"Larva";102;1
"Unit";"Zergling";"Larva";102;1
"Unit";"Zergling";"Larva";102;1
"Unit";"Zergling";"Larva";102;1
"Unit";"Zergling";"Larva";102;1
"Unit";"Zergling";"Larva";102;1
"Unit";"Zergling";"Larva";102;1
"Building";"Extractor";NA;132;0
"Building";"Extractor";NA;132;0
"Unit";"Hydralisk";"Larva";141;2
"Unit";"Hydralisk";"Larva";142;2
"Unit";"Hydralisk";"Larva";142;2
"Unit";"Hydralisk";"Larva";142;2
"Unit";"Hydralisk";"Larva";142;2
"Unit";"Hydralisk";"Larva";142;2
"Unit";"Hydralisk";"Larva";142;2
"Unit";"Hydralisk";"Larva";149;2
"Upgrade";"EvolveGroovedSpines";"HydraliskDen";132;0
"Building";"Extractor";NA;149;0
"Building";"Extractor";NA;149;0
"Unit";"Hydralisk";"Larva";149;2
"Unit";"Hydralisk";"Larva";149;2
"Unit";"Hydralisk";"Larva";149;2
"Unit";"Zergling";"Larva";163;1
"Unit";"Zergling";"Larva";163;1
"Unit";"Zergling";"Larva";163;1
"Unit";"Zergling";"Larva";163;1
"Unit";"Zergling";"Larva";163;1
"Unit";"Zergling";"Larva";163;1
"Unit";"Zergling";"Larva";163;1
"Unit";"Zergling";"Larva";163;1
"Unit";"Zergling";"Larva";163;1
"Unit";"Zergling";"Larva";163;1
"Unit";"Zergling";"Larva";163;1
"Unit";"Zergling";"Larva";163;1
"Unit";"Hydralisk";"Larva";163;2
"Unit";"Hydralisk";"Larva";163;2
"Unit";"Hydralisk";"Larva";163;2
"Unit";"Zergling";"Larva";171;1
"Unit";"Zergling";"Larva";171;1
"Unit";"Overlord";"Larva";183;0
"Unit";"Overlord";"Larva";183;0
"Unit";"Overlord";"Larva";183;0
"Unit";"Overlord";"Larva";183;0
"Unit";"Overlord";"Larva";183;0
"Unit";"Hydralisk";"Larva";171;2
"Unit";"Hydralisk";"Larva";171;2
"Building";"CreepTumor";NA;189;0
"Unit";"Overlord";"Larva";191;0
"Unit";"Overlord";"Larva";191;0
"Unit";"Overlord";"Larva";191;0
"Unit";"Overlord";"Larva";191;0
"Unit";"Hydralisk";"Larva";193;2
"Unit";"Hydralisk";"Larva";195;2
"Unit";"Hydralisk";"Larva";195;2
"Unit";"Hydralisk";"Larva";195;2
"Unit";"Hydralisk";"Larva";195;2
"Upgrade";"ZergMeleeWeaponsLevel2";"EvolutionChamber";139;0
"Unit";"Zergling";"Larva";205;1
"Unit";"Zergling";"Larva";205;1
"Unit";"Zergling";"Larva";205;1
"Unit";"Zergling";"Larva";205;1
"Unit";"Zergling";"Larva";205;1
"Unit";"Zergling";"Larva";205;1
"Unit";"Zergling";"Larva";205;1
"Unit";"Zergling";"Larva";205;1
"Unit";"Zergling";"Larva";205;1
"Unit";"Zergling";"Larva";205;1
"Unit";"Zergling";"Larva";205;1
"Unit";"Zergling";"Larva";205;1
"Unit";"Zergling";"Larva";205;1
"Unit";"Zergling";"Larva";205;1
"Unit";"Zergling";"Larva";205;1
"Unit";"Zergling";"Larva";205;1
"Unit";"Zergling";"Larva";205;1
"Unit";"Zergling";"Larva";205;1
"Unit";"Zergling";"Larva";205;1
"Unit";"Zergling";"Larva";205;1
"Unit";"Zergling";"Larva";205;1
"Unit";"Zergling";"Larva";205;1
"Unit";"Zergling";"Larva";205;1
"Unit";"Zergling";"Larva";205;1
"Unit";"Zergling";"Larva";205;1
"Unit";"Zergling";"Larva";205;1
"Unit";"Zergling";"Larva";205;1
"Unit";"Zergling";"Larva";205;1
"Unit";"Zergling";"Larva";205;1
"Unit";"Zergling";"Larva";205;1
"Unit";"Zergling";"Larva";205;1
"Unit";"Zergling";"Larva";205;1
"Unit";"Hydralisk";"Larva";237;2
"Unit";"Hydralisk";"Larva";237;2
"Unit";"Hydralisk";"Larva";237;2
"Unit";"Hydralisk";"Larva";237;2
"Unit";"Hydralisk";"Larva";237;2
"Unit";"Hydralisk";"Larva";237;2
"Unit";"Hydralisk";"Larva";237;2
"Unit";"Hydralisk";"Larva";237;2
"Unit";"Hydralisk";"Larva";237;2
"Unit";"Hydralisk";"Larva";237;2
"Upgrade";"EvolveMuscularAugments";"HydraliskDen";205;0
"Building";"Spire";NA;205;0
"Unit";"Hydralisk";"Larva";237;2
"Unit";"Hydralisk";"Larva";237;2
"Unit";"Hydralisk";"Larva";237;2
"Unit";"Hydralisk";"Larva";237;2
"Unit";"Hydralisk";"Larva";237;2
"Building";"Hatchery";NA;205;0
"Building";"CreepTumor";NA;267;0
"Unit";"Mutalisk";"Larva";257;2
"Unit";"Mutalisk";"Larva";257;2
"Unit";"Mutalisk";"Larva";257;2
"Unit";"Overlord";"Larva";267;0
"Unit";"Overlord";"Larva";267;0
"Unit";"Overlord";"Larva";267;0
"Unit";"Overlord";"Larva";267;0
"Upgrade";"ZergMissileWeaponsLevel1";"EvolutionChamber";237;0
"Building";"LurkerDenMP";NA;237;0
"Building";"Hatchery";NA;237;0
"Unit";"Hydralisk";"Larva";279;2
"Unit";"Hydralisk";"Larva";279;2
"Unit";"Hydralisk";"Larva";279;2
"Unit";"Hydralisk";"Larva";279;2
"Unit";"Hydralisk";"Larva";279;2
"Unit";"Hydralisk";"Larva";279;2
"Unit";"Hydralisk";"Larva";279;2
"Unit";"Hydralisk";"Larva";279;2
"Unit";"Zergling";"Larva";279;1
"Unit";"Zergling";"Larva";279;1
"Unit";"Zergling";"Larva";279;1
"Unit";"Zergling";"Larva";279;1
"Unit";"Zergling";"Larva";279;1
"Unit";"Zergling";"Larva";279;1
"Unit";"Zergling";"Larva";279;1
"Unit";"Zergling";"Larva";279;1
"Unit";"Zergling";"Larva";279;1
"Unit";"Zergling";"Larva";279;1
"Unit";"Zergling";"Larva";279;1
"Unit";"Zergling";"Larva";279;1
"Unit";"Zergling";"Larva";279;1
"Unit";"Zergling";"Larva";279;1
"Unit";"Zergling";"Larva";279;1
"Unit";"Zergling";"Larva";279;1
"Unit";"Zergling";"Larva";311;1
"Unit";"Zergling";"Larva";311;1
"Unit";"Zergling";"Larva";311;1
"Unit";"Zergling";"Larva";311;1
"Unit";"Zergling";"Larva";311;1
"Unit";"Zergling";"Larva";311;1
"Unit";"Zergling";"Larva";311;1
"Unit";"Zergling";"Larva";311;1
"Unit";"Zergling";"Larva";311;1
"Unit";"Zergling";"Larva";311;1
"Unit";"Zergling";"Larva";311;1
"Unit";"Zergling";"Larva";311;1
"Unit";"Zergling";"Larva";311;1
"Unit";"Zergling";"Larva";311;1
"Unit";"Zergling";"Larva";311;1
"Unit";"Zergling";"Larva";311;1
"Unit";"Zergling";"Larva";311;1
"Unit";"Zergling";"Larva";311;1
"Unit";"Zergling";"Larva";311;1
"Unit";"Zergling";"Larva";311;1
"Unit";"Zergling";"Larva";311;1
"Unit";"Zergling";"Larva";311;1
"Unit";"Zergling";"Larva";311;1
"Unit";"Zergling";"Larva";311;1
"Unit";"Zergling";"Larva";311;1
"Unit";"Zergling";"Larva";311;1
"Unit";"Zergling";"Larva";311;1
"Unit";"Zergling";"Larva";311;1
"Unit";"Queen";"Hatchery";295;2
"Unit";"Zergling";"Larva";331;1
"Unit";"Zergling";"Larva";331;1
"Unit";"Zergling";"Larva";331;1
"Unit";"Zergling";"Larva";331;1
"Unit";"Zergling";"Larva";331;1
"Unit";"Zergling";"Larva";331;1
"Unit";"Zergling";"Larva";331;1
"Unit";"Zergling";"Larva";331;1
"Unit";"Zergling";"Larva";339;1
"Unit";"Zergling";"Larva";339;1
"Unit";"Zergling";"Larva";339;1
"Unit";"Zergling";"Larva";339;1
"Unit";"Zergling";"Larva";339;1
"Unit";"Zergling";"Larva";339;1
"Unit";"Zergling";"Larva";349;1
"Unit";"Zergling";"Larva";349;1
"Unit";"Zergling";"Larva";349;1
"Unit";"Zergling";"Larva";349;1
"Unit";"Zergling";"Larva";349;1
"Unit";"Zergling";"Larva";349;1
"Unit";"Zergling";"Larva";349;1
"Unit";"Zergling";"Larva";349;1
"Unit";"Zergling";"Larva";349;1
"Unit";"Zergling";"Larva";349;1
"Unit";"Zergling";"Larva";349;1
"Unit";"Zergling";"Larva";349;1
"Unit";"Zergling";"Larva";349;1
"Unit";"Zergling";"Larva";349;1
"Unit";"Zergling";"Larva";349;1
"Unit";"Zergling";"Larva";349;1
"Unit";"Zergling";"Larva";349;1
"Unit";"Zergling";"Larva";349;1
"Unit";"Zergling";"Larva";355;1
"Unit";"Zergling";"Larva";355;1
"Unit";"Zergling";"Larva";355;1
"Unit";"Zergling";"Larva";355;1
"Unit";"Zergling";"Larva";355;1
"Unit";"Zergling";"Larva";355;1
"Unit";"Zergling";"Larva";355;1
"Unit";"Zergling";"Larva";355;1
"Unit";"Zergling";"Larva";355;1
"Unit";"Zergling";"Larva";355;1
"Unit";"Zergling";"Larva";355;1
"Unit";"Zergling";"Larva";355;1
"Unit";"Zergling";"Larva";355;1
"Unit";"Zergling";"Larva";355;1
