"type";"unit_name";"on_building";"total_supply";"supply"
"Unit";"Overlord";"Larva";13;0
"Building";"Extractor";NA;17;0
"Unit";"Overlord";"Larva";21;0
"Building";"Hatchery";NA;16;0
"Building";"SpawningPool";NA;19;0
"Unit";"Queen";"Hatchery";22;2
"Unit";"Queen";"Hatchery";22;2
"Unit";"Overlord";"Larva";33;0
"Unit";"Zergling";"Larva";33;1
"Unit";"Zergling";"Larva";33;1
"Unit";"Zergling";"Larva";33;1
"Unit";"Zergling";"Larva";33;1
"Unit";"Zergling";"Larva";33;1
"Unit";"Zergling";"Larva";33;1
"Unit";"Zergling";"Larva";33;1
"Unit";"Zergling";"Larva";33;1
"Unit";"Queen";"Hatchery";33;2
"Building";"CreepTumorQueen";NA;39;0
"Unit";"Overlord";"Larva";33;0
"Unit";"Overlord";"Larva";42;0
"Building";"CreepTumor";NA;48;0
"Building";"Hatchery";NA;28;0
"Building";"CreepTumorQueen";NA;52;0
"Unit";"Queen";"Hatchery";45;2
"Building";"SporeCrawler";NA;52;0
"Building";"SporeCrawler";NA;54;0
"Building";"CreepTumor";NA;60;0
"Building";"CreepTumor";NA;60;0
"Unit";"Queen";"Hatchery";53;2
"Building";"SporeCrawler";NA;59;0
"Unit";"Zergling";"Larva";61;1
"Unit";"Zergling";"Larva";61;1
"Unit";"Zergling";"Larva";61;1
"Unit";"Zergling";"Larva";61;1
"Building";"CreepTumorQueen";NA;67;0
"Unit";"Overlord";"Larva";66;0
"Building";"CreepTumorQueen";NA;74;0
"Building";"CreepTumor";NA;76;0
"Building";"CreepTumorQueen";NA;79;0
"Unit";"Overlord";"Larva";81;0
"Building";"Extractor";NA;81;0
"Unit";"Zergling";"Larva";81;1
"Unit";"Zergling";"Larva";81;1
"Unit";"Zergling";"Larva";81;1
"Unit";"Zergling";"Larva";81;1
"Unit";"Zergling";"Larva";81;1
"Unit";"Zergling";"Larva";81;1
"Building";"EvolutionChamber";NA;79;0
"Building";"Extractor";NA;81;0
"Building";"Extractor";NA;81;0
"Unit";"Overlord";"Larva";88;0
"Unit";"Overlord";"Larva";88;0
"Unit";"Overlord";"Larva";89;0
"Unit";"Overlord";"Larva";89;0
"Building";"RoachWarren";NA;79;0
"Unit";"Overlord";"Larva";89;0
"Unit";"Zergling";"Larva";95;1
"Unit";"Zergling";"Larva";95;1
"Unit";"Zergling";"Larva";95;1
"Unit";"Zergling";"Larva";95;1
"Unit";"Zergling";"Larva";95;1
"Unit";"Zergling";"Larva";95;1
"Unit";"Zergling";"Larva";95;1
"Unit";"Zergling";"Larva";95;1
"Unit";"Zergling";"Larva";95;1
"Unit";"Zergling";"Larva";95;1
"Unit";"Zergling";"Larva";95;1
"Unit";"Zergling";"Larva";95;1
"Unit";"Zergling";"Larva";95;1
"Unit";"Zergling";"Larva";95;1
"Building";"Extractor";NA;95;0
"Building";"EvolutionChamber";NA;95;0
"Building";"Extractor";NA;95;0
"Building";"CreepTumor";NA;114;0
"Building";"CreepTumor";NA;121;0
"Building";"CreepTumor";NA;122;0
"Building";"CreepTumorQueen";NA;128;0
"Building";"BanelingNest";NA;115;0
"Building";"CreepTumor";NA;133;0
"Building";"CreepTumor";NA;134;0
"Unit";"Zergling";"Larva";133;1
"Unit";"Zergling";"Larva";133;1
"Upgrade";"GlialReconstitution";"RoachWarren";119;0
"Building";"HydraliskDen";NA;133;0
"Building";"HydraliskDen";NA;133;0
"Unit";"Overlord";"Larva";139;0
"Unit";"Overlord";"Larva";142;0
"Building";"SporeCrawler";NA;139;0
"Unit";"Overlord";"Larva";142;0
"Unit";"Overlord";"Larva";142;0
"Upgrade";"ZergMissileWeaponsLevel1";"EvolutionChamber";116;0
"Building";"CreepTumor";NA;144;0
"Building";"CreepTumor";NA;144;0
"Unit";"Overlord";"Larva";144;0
"Unit";"Overlord";"Larva";144;0
"Unit";"Hydralisk";"Larva";144;2
"Unit";"Hydralisk";"Larva";144;2
"Unit";"Hydralisk";"Larva";144;2
"Unit";"Hydralisk";"Larva";144;2
"Unit";"Hydralisk";"Larva";144;2
"Unit";"Hydralisk";"Larva";144;2
"Unit";"Hydralisk";"Larva";144;2
"Unit";"Hydralisk";"Larva";144;2
"Building";"Hatchery";NA;130;0
"Unit";"Hydralisk";"Larva";144;2
"Building";"CreepTumor";NA;144;0
"Building";"Extractor";NA;144;0
"Unit";"Hydralisk";"Larva";144;2
"Unit";"Hydralisk";"Larva";144;2
"Building";"Extractor";NA;160;0
"Unit";"Overlord";"Larva";160;0
"Unit";"Hydralisk";"Larva";160;2
"Unit";"Hydralisk";"Larva";160;2
"Upgrade";"ZergMeleeWeaponsLevel1";"EvolutionChamber";134;0
"Unit";"Hydralisk";"Larva";162;2
"Unit";"Hydralisk";"Larva";162;2
"Unit";"Zergling";"Larva";166;1
"Unit";"Zergling";"Larva";166;1
"Unit";"Zergling";"Larva";166;1
"Unit";"Zergling";"Larva";166;1
"Unit";"Zergling";"Larva";166;1
"Unit";"Zergling";"Larva";166;1
"Unit";"Zergling";"Larva";166;1
"Unit";"Zergling";"Larva";166;1
"Unit";"Hydralisk";"Larva";162;2
"Unit";"Hydralisk";"Larva";162;2
"Unit";"Hydralisk";"Larva";162;2
"Unit";"Hydralisk";"Larva";162;2
"Unit";"Zergling";"Larva";170;1
"Unit";"Zergling";"Larva";170;1
"Unit";"Zergling";"Larva";170;1
"Unit";"Zergling";"Larva";170;1
"Unit";"Zergling";"Larva";170;1
"Unit";"Zergling";"Larva";170;1
"Building";"SpineCrawler";NA;160;0
"Unit";"Zergling";"Larva";170;1
"Unit";"Zergling";"Larva";170;1
"Upgrade";"EvolveGroovedSpines";"HydraliskDen";144;0
"Upgrade";"EvolveMuscularAugments";"HydraliskDen";144;0
"Building";"CreepTumorQueen";NA;174;0
"Unit";"Overlord";"Larva";170;0
"Unit";"Overlord";"Larva";170;0
"Unit";"Baneling";"Zergling";176;0
"Unit";"Baneling";"Zergling";176;0
"Unit";"Baneling";"Zergling";176;0
"Unit";"Baneling";"Zergling";176;0
"Building";"CreepTumorQueen";NA;186;0
"Unit";"Baneling";"Zergling";176;0
"Unit";"Baneling";"Zergling";176;0
"Unit";"Zergling";"Larva";170;1
"Unit";"Zergling";"Larva";170;1
"Unit";"Baneling";"Zergling";176;0
"Unit";"Baneling";"Zergling";176;0
"Unit";"Baneling";"Zergling";176;0
"Unit";"Baneling";"Zergling";178;0
"Unit";"Zergling";"Larva";170;1
"Unit";"Zergling";"Larva";170;1
"Unit";"Zergling";"Larva";170;1
"Unit";"Zergling";"Larva";170;1
"Unit";"Zergling";"Larva";170;1
"Unit";"Zergling";"Larva";170;1
"Unit";"Zergling";"Larva";170;1
"Unit";"Zergling";"Larva";170;1
"Building";"CreepTumorQueen";NA;190;0
"Unit";"Hydralisk";"Larva";186;2
"Unit";"Hydralisk";"Larva";190;2
"Unit";"Hydralisk";"Larva";190;2
"Unit";"Hydralisk";"Larva";198;2
"Unit";"Hydralisk";"Larva";208;2
"Unit";"Hydralisk";"Larva";208;2
"Unit";"Zergling";"Larva";214;1
"Unit";"Zergling";"Larva";214;1
"Building";"SpineCrawler";NA;198;0
"Unit";"Zergling";"Larva";214;1
"Unit";"Zergling";"Larva";214;1
"Unit";"Baneling";"Zergling";216;0
"Unit";"Baneling";"Zergling";216;0
"Unit";"Baneling";"Zergling";216;0
"Unit";"Baneling";"Zergling";216;0
"Unit";"Hydralisk";"Larva";210;2
"Building";"InfestationPit";NA;208;0
"Unit";"Hydralisk";"Larva";210;2
"Unit";"Hydralisk";"Larva";210;2
"Unit";"Hydralisk";"Larva";210;2
"Unit";"Hydralisk";"Larva";210;2
"Unit";"Zergling";"Larva";216;1
"Unit";"Zergling";"Larva";216;1
"Unit";"Zergling";"Larva";216;1
"Unit";"Zergling";"Larva";216;1
"Unit";"Zergling";"Larva";216;1
"Unit";"Zergling";"Larva";216;1
"Building";"CreepTumor";NA;236;0
"Unit";"Zergling";"Larva";224;1
"Unit";"Zergling";"Larva";224;1
"Unit";"Zergling";"Larva";224;1
"Unit";"Zergling";"Larva";224;1
"Building";"CreepTumor";NA;236;0
"Unit";"Zergling";"Larva";224;1
"Unit";"Zergling";"Larva";224;1
"Unit";"Zergling";"Larva";234;1
"Unit";"Zergling";"Larva";234;1
"Unit";"Zergling";"Larva";234;1
"Unit";"Zergling";"Larva";234;1
"Unit";"Zergling";"Larva";236;1
"Unit";"Zergling";"Larva";236;1
"Building";"CreepTumorQueen";NA;242;0
"Building";"CreepTumorQueen";NA;242;0
"Unit";"Zergling";"Larva";236;1
"Unit";"Zergling";"Larva";236;1
"Unit";"Zergling";"Larva";238;1
"Unit";"Zergling";"Larva";238;1
"Unit";"Zergling";"Larva";242;1
"Unit";"Zergling";"Larva";242;1
"Unit";"Zergling";"Larva";242;1
"Unit";"Zergling";"Larva";242;1
"Unit";"Baneling";"Zergling";242;0
"Unit";"Baneling";"Zergling";242;0
"Unit";"Baneling";"Zergling";242;0
"Unit";"Baneling";"Zergling";242;0
"Unit";"Baneling";"Zergling";242;0
"Unit";"Baneling";"Zergling";242;0
"Unit";"Baneling";"Zergling";242;0
"Unit";"Baneling";"Zergling";246;0
"Unit";"Zergling";"Larva";242;1
"Unit";"Zergling";"Larva";242;1
"Unit";"Zergling";"Larva";242;1
"Unit";"Zergling";"Larva";242;1
"Unit";"Zergling";"Larva";242;1
"Unit";"Zergling";"Larva";242;1
"Unit";"Zergling";"Larva";246;1
"Unit";"Zergling";"Larva";246;1
"Unit";"Zergling";"Larva";254;1
"Unit";"Zergling";"Larva";254;1
"Unit";"Zergling";"Larva";254;1
"Unit";"Zergling";"Larva";254;1
"Unit";"Zergling";"Larva";254;1
"Unit";"Zergling";"Larva";254;1
"Unit";"Zergling";"Larva";254;1
"Unit";"Zergling";"Larva";254;1
"Unit";"Zergling";"Larva";254;1
"Unit";"Zergling";"Larva";254;1
"Unit";"Zergling";"Larva";258;1
"Unit";"Zergling";"Larva";258;1
"Unit";"Zergling";"Larva";258;1
"Unit";"Zergling";"Larva";258;1
"Upgrade";"ZergMissileWeaponsLevel2";"EvolutionChamber";170;0
"Unit";"Zergling";"Larva";258;1
"Unit";"Zergling";"Larva";258;1
"Unit";"Zergling";"Larva";260;1
"Unit";"Zergling";"Larva";260;1
"Unit";"Zergling";"Larva";262;1
"Unit";"Zergling";"Larva";262;1
"Unit";"Overlord";"Larva";262;0
"Building";"CreepTumor";NA;270;0
"Building";"CreepTumor";NA;270;0
"Building";"CreepTumor";NA;270;0
"Unit";"Baneling";"Zergling";270;0
"Unit";"Baneling";"Zergling";270;0
"Unit";"Baneling";"Zergling";270;0
"Unit";"Baneling";"Zergling";270;0
"Unit";"Baneling";"Zergling";270;0
"Unit";"Baneling";"Zergling";270;0
"Unit";"Zergling";"Larva";270;1
"Unit";"Zergling";"Larva";270;1
"Unit";"Zergling";"Larva";270;1
"Unit";"Zergling";"Larva";270;1
"Unit";"Zergling";"Larva";290;1
"Unit";"Zergling";"Larva";290;1
"Unit";"Zergling";"Larva";290;1
"Unit";"Zergling";"Larva";290;1
"Unit";"Zergling";"Larva";290;1
"Unit";"Zergling";"Larva";290;1
"Unit";"Zergling";"Larva";290;1
"Unit";"Zergling";"Larva";290;1
"Unit";"Zergling";"Larva";290;1
"Unit";"Zergling";"Larva";290;1
"Unit";"Zergling";"Larva";290;1
"Unit";"Zergling";"Larva";290;1
"Unit";"Zergling";"Larva";292;1
"Unit";"Zergling";"Larva";292;1
"Unit";"Baneling";"Zergling";294;0
"Unit";"Baneling";"Zergling";294;0
"Unit";"Baneling";"Zergling";294;0
"Unit";"Baneling";"Zergling";294;0
"Unit";"Baneling";"Zergling";294;0
"Unit";"Baneling";"Zergling";294;0
"Unit";"Baneling";"Zergling";294;0
"Unit";"Baneling";"Zergling";294;0
"Unit";"Baneling";"Zergling";294;0
"Unit";"Baneling";"Zergling";294;0
"Unit";"Baneling";"Zergling";294;0
"Unit";"Baneling";"Zergling";294;0
"Unit";"Baneling";"Zergling";294;0
"Unit";"Baneling";"Zergling";294;0
"Unit";"Baneling";"Zergling";294;0
"Unit";"Baneling";"Zergling";294;0
"Unit";"Baneling";"Zergling";294;0
"Unit";"Zergling";"Larva";294;1
"Unit";"Zergling";"Larva";294;1
"Building";"Spire";NA;236;0
"Unit";"Hydralisk";"Larva";294;2
"Building";"CreepTumor";NA;308;0
"Unit";"Zergling";"Larva";296;1
"Unit";"Zergling";"Larva";296;1
"Unit";"Zergling";"Larva";298;1
"Unit";"Zergling";"Larva";298;1
"Unit";"Zergling";"Larva";298;1
"Unit";"Zergling";"Larva";298;1
"Unit";"Zergling";"Larva";298;1
"Unit";"Zergling";"Larva";298;1
"Unit";"Zergling";"Larva";308;1
"Unit";"Zergling";"Larva";308;1
"Unit";"Zergling";"Larva";308;1
"Unit";"Zergling";"Larva";308;1
"Unit";"Zergling";"Larva";308;1
"Unit";"Zergling";"Larva";308;1
"Unit";"Baneling";"Zergling";310;0
"Unit";"Baneling";"Zergling";310;0
"Unit";"Baneling";"Zergling";310;0
"Unit";"Baneling";"Zergling";310;0
"Unit";"Baneling";"Zergling";310;0
"Unit";"Baneling";"Zergling";310;0
"Unit";"Baneling";"Zergling";310;0
"Unit";"Baneling";"Zergling";310;0
"Unit";"Baneling";"Zergling";310;0
"Unit";"Baneling";"Zergling";310;0
"Unit";"Zergling";"Larva";308;1
"Unit";"Zergling";"Larva";308;1
"Unit";"Zergling";"Larva";308;1
"Unit";"Zergling";"Larva";308;1
"Unit";"Zergling";"Larva";308;1
"Unit";"Zergling";"Larva";308;1
"Unit";"Zergling";"Larva";312;1
"Unit";"Zergling";"Larva";312;1
"Unit";"Zergling";"Larva";318;1
"Unit";"Zergling";"Larva";318;1
"Unit";"Zergling";"Larva";320;1
"Unit";"Zergling";"Larva";320;1
"Unit";"Zergling";"Larva";322;1
"Unit";"Zergling";"Larva";322;1
"Unit";"Zergling";"Larva";326;1
"Unit";"Zergling";"Larva";326;1
"Unit";"Zergling";"Larva";326;1
"Unit";"Zergling";"Larva";326;1
"Unit";"Zergling";"Larva";326;1
"Unit";"Zergling";"Larva";326;1
"Unit";"Zergling";"Larva";326;1
"Unit";"Zergling";"Larva";326;1
"Unit";"Zergling";"Larva";332;1
"Unit";"Zergling";"Larva";332;1
"Unit";"Baneling";"Zergling";336;0
"Unit";"Baneling";"Zergling";336;0
"Unit";"Baneling";"Zergling";336;0
"Unit";"Baneling";"Zergling";336;0
"Unit";"Baneling";"Zergling";336;0
"Unit";"Baneling";"Zergling";336;0
"Unit";"Baneling";"Zergling";336;0
"Unit";"Baneling";"Zergling";336;0
"Unit";"Baneling";"Zergling";336;0
"Unit";"Baneling";"Zergling";336;0
"Unit";"Baneling";"Zergling";336;0
"Unit";"Baneling";"Zergling";336;0
"Unit";"Baneling";"Zergling";336;0
"Unit";"Baneling";"Zergling";336;0
"Unit";"Baneling";"Zergling";336;0
"Unit";"Baneling";"Zergling";336;0
"Unit";"Zergling";"Larva";336;1
"Unit";"Zergling";"Larva";336;1
"Unit";"Zergling";"Larva";336;1
"Unit";"Zergling";"Larva";336;1
"Unit";"Zergling";"Larva";336;1
"Unit";"Zergling";"Larva";336;1
"Upgrade";"ZergGroundArmorsLevel1";"EvolutionChamber";272;0
"Building";"LurkerDenMP";NA;270;0
"Unit";"Zergling";"Larva";356;1
"Unit";"Zergling";"Larva";356;1
"Unit";"Zergling";"Larva";356;1
"Unit";"Zergling";"Larva";356;1
"Building";"CreepTumorQueen";NA;356;0
"Building";"CreepTumorQueen";NA;356;0
"Building";"CreepTumorQueen";NA;360;0
"Unit";"Corruptor";"Larva";356;2
"Unit";"Zergling";"Larva";356;1
"Unit";"Zergling";"Larva";356;1
"Unit";"Corruptor";"Larva";356;2
"Unit";"Corruptor";"Larva";356;2
"Unit";"Zergling";"Larva";356;1
"Unit";"Zergling";"Larva";356;1
"Unit";"Zergling";"Larva";356;1
"Unit";"Zergling";"Larva";356;1
"Unit";"Corruptor";"Larva";356;2
"Unit";"Corruptor";"Larva";356;2
"Unit";"Corruptor";"Larva";356;2
"Unit";"Zergling";"Larva";356;1
"Unit";"Zergling";"Larva";356;1
"Unit";"Zergling";"Larva";356;1
"Unit";"Zergling";"Larva";356;1
"Building";"CreepTumorQueen";NA;362;0
"Unit";"Zergling";"Larva";386;1
"Unit";"Zergling";"Larva";386;1
"Building";"SpineCrawler";NA;360;0
"Building";"SpineCrawler";NA;361;0
"Unit";"Hydralisk";"Larva";386;2
"Unit";"Hydralisk";"Larva";386;2
"Building";"CreepTumor";NA;386;0
"Unit";"Zergling";"Larva";386;1
"Unit";"Zergling";"Larva";386;1
"Building";"Hatchery";NA;356;0
"Unit";"Zergling";"Larva";386;1
"Unit";"Zergling";"Larva";386;1
"Unit";"Zergling";"Larva";386;1
"Unit";"Zergling";"Larva";386;1
"Unit";"Zergling";"Larva";386;1
"Unit";"Zergling";"Larva";386;1
"Unit";"Zergling";"Larva";386;1
"Unit";"Zergling";"Larva";386;1
"Unit";"Zergling";"Larva";386;1
"Unit";"Zergling";"Larva";386;1
"Unit";"Zergling";"Larva";386;1
"Unit";"Zergling";"Larva";386;1
"Unit";"Zergling";"Larva";386;1
"Unit";"Zergling";"Larva";386;1
"Unit";"Zergling";"Larva";386;1
"Unit";"Zergling";"Larva";386;1
"Unit";"Zergling";"Larva";386;1
"Unit";"Zergling";"Larva";386;1
"Unit";"Baneling";"Zergling";394;0
"Unit";"Baneling";"Zergling";396;0
"Unit";"Baneling";"Zergling";396;0
"Unit";"Baneling";"Zergling";396;0
"Unit";"Baneling";"Zergling";396;0
"Unit";"Baneling";"Zergling";396;0
"Unit";"Baneling";"Zergling";396;0
"Unit";"Baneling";"Zergling";396;0
"Unit";"Baneling";"Zergling";396;0
"Unit";"Baneling";"Zergling";396;0
"Unit";"Baneling";"Zergling";396;0
"Unit";"Baneling";"Zergling";402;0
"Building";"CreepTumor";NA;413;0
"Building";"CreepTumor";NA;413;0
"Building";"SpineCrawler";NA;388;0
"Unit";"Hydralisk";"Larva";413;2
"Unit";"Hydralisk";"Larva";413;2
"Unit";"Hydralisk";"Larva";413;2
"Unit";"Hydralisk";"Larva";413;2
"Unit";"Hydralisk";"Larva";413;2
"Unit";"Hydralisk";"Larva";413;2
"Unit";"Hydralisk";"Larva";413;2
"Unit";"Hydralisk";"Larva";413;2
"Unit";"Hydralisk";"Larva";413;2
"Unit";"Zergling";"Larva";418;1
"Unit";"Zergling";"Larva";418;1
"Unit";"Baneling";"Zergling";418;0
"Unit";"Baneling";"Zergling";418;0
"Unit";"Baneling";"Zergling";418;0
"Unit";"Baneling";"Zergling";418;0
"Unit";"Hydralisk";"Larva";418;2
"Unit";"Hydralisk";"Larva";418;2
"Unit";"Hydralisk";"Larva";418;2
"Unit";"Hydralisk";"Larva";418;2
"Unit";"Zergling";"Larva";418;1
"Unit";"Zergling";"Larva";418;1
"Unit";"Zergling";"Larva";418;1
"Unit";"Zergling";"Larva";418;1
"Unit";"Zergling";"Larva";418;1
"Unit";"Zergling";"Larva";418;1
"Unit";"Hydralisk";"Larva";418;2
"Unit";"Hydralisk";"Larva";418;2
"Unit";"Zergling";"Larva";432;1
"Unit";"Zergling";"Larva";432;1
"Unit";"Zergling";"Larva";432;1
"Unit";"Zergling";"Larva";432;1
"Unit";"Zergling";"Larva";432;1
"Unit";"Zergling";"Larva";432;1
"Unit";"Overlord";"Larva";446;0
"Unit";"Hydralisk";"Larva";434;2
"Unit";"Zergling";"Larva";458;1
"Unit";"Zergling";"Larva";458;1
"Unit";"Overlord";"Larva";460;0
"Unit";"Zergling";"Larva";462;1
"Unit";"Zergling";"Larva";462;1
"Unit";"Zergling";"Larva";462;1
"Unit";"Zergling";"Larva";462;1
"Unit";"Zergling";"Larva";462;1
"Unit";"Zergling";"Larva";462;1
"Unit";"Zergling";"Larva";462;1
"Unit";"Zergling";"Larva";462;1
"Unit";"Overlord";"Larva";462;0
"Unit";"Overlord";"Larva";462;0
"Unit";"Queen";"Hatchery";458;2
"Unit";"Queen";"Hatchery";458;2
"Unit";"Overlord";"Larva";462;0
"Unit";"Zergling";"Larva";470;1
"Unit";"Zergling";"Larva";470;1
"Unit";"Zergling";"Larva";470;1
"Unit";"Zergling";"Larva";470;1
