"type";"unit_name";"on_building";"total_supply_lag";"supply"
"Unit";"Overlord";"Larva";13;0
"Building";"Hatchery";NA;16;0
"Building";"Extractor";NA;19;0
"Building";"SpawningPool";NA;19;0
"Unit";"Overlord";"Larva";22;0
"Unit";"Queen";"Hatchery";23;2
"Unit";"Queen";"Hatchery";25;2
"Unit";"Zergling";"Larva";27;1
"Unit";"Zergling";"Larva";28;1
"Unit";"Zergling";"Larva";29;1
"Unit";"Zergling";"Larva";30;1
"Building";"Hatchery";NA;39;0
"Unit";"Overlord";"Larva";39;0
"Unit";"Zergling";"Larva";39;1
"Unit";"Zergling";"Larva";40;1
"Unit";"Zergling";"Larva";41;1
"Unit";"Zergling";"Larva";42;1
"Unit";"Zergling";"Larva";43;1
"Unit";"Zergling";"Larva";44;1
"Building";"CreepTumorQueen";NA;51;0
"Building";"SporeCrawler";NA;53;0
"Building";"SporeCrawler";NA;53;0
"Unit";"Overlord";"Larva";53;0
"Unit";"Zergling";"Larva";53;1
"Unit";"Zergling";"Larva";54;1
"Unit";"Queen";"Hatchery";55;2
"Building";"CreepTumor";NA;57;0
"Unit";"Overlord";"Larva";57;0
"Unit";"Overlord";"Larva";57;0
"Building";"EvolutionChamber";NA;57;0
"Unit";"Zergling";"Larva";62;1
"Unit";"Zergling";"Larva";63;1
"Unit";"Zergling";"Larva";64;1
"Unit";"Zergling";"Larva";65;1
"Unit";"Queen";"Hatchery";66;2
"Unit";"Zergling";"Larva";68;1
"Unit";"Zergling";"Larva";69;1
"Unit";"Zergling";"Larva";70;1
"Unit";"Zergling";"Larva";71;1
"Building";"SporeCrawler";NA;82;0
"Building";"CreepTumor";NA;83;0
"Building";"CreepTumorQueen";NA;85;0
"Building";"SporeCrawler";NA;88;0
"Unit";"Queen";"Hatchery";89;2
"Unit";"Overlord";"Larva";91;0
"Unit";"Overlord";"Larva";95;0
"Building";"CreepTumor";NA;95;0
"Unit";"Overlord";"Larva";95;0
"Building";"CreepTumor";NA;95;0
"Unit";"Zergling";"Larva";103;1
"Unit";"Zergling";"Larva";104;1
"Unit";"Zergling";"Larva";105;1
"Unit";"Zergling";"Larva";106;1
"Unit";"Zergling";"Larva";107;1
"Unit";"Zergling";"Larva";108;1
"Unit";"Zergling";"Larva";109;1
"Unit";"Zergling";"Larva";110;1
"Unit";"Zergling";"Larva";111;1
"Unit";"Zergling";"Larva";112;1
"Unit";"Zergling";"Larva";113;1
"Unit";"Zergling";"Larva";114;1
"Building";"CreepTumorQueen";NA;115;0
"Building";"CreepTumorQueen";NA;115;0
"Building";"Extractor";NA;117;0
"Building";"Extractor";NA;117;0
"Building";"Extractor";NA;117;0
"Building";"BanelingNest";NA;117;0
"Building";"CreepTumor";NA;119;0
"Building";"CreepTumor";NA;121;0
"Unit";"Overlord";"Larva";121;0
"Building";"Hatchery";NA;124;0
"Building";"Extractor";NA;126;0
"Building";"Extractor";NA;126;0
"Building";"CreepTumor";NA;126;0
"Building";"CreepTumor";NA;126;0
"Unit";"Overlord";"Larva";126;0
"Unit";"Overlord";"Larva";133;0
"Unit";"Zergling";"Larva";133;1
"Unit";"Zergling";"Larva";134;1
"Unit";"Zergling";"Larva";135;1
"Unit";"Zergling";"Larva";136;1
"Unit";"Zergling";"Larva";137;1
"Unit";"Zergling";"Larva";138;1
"Unit";"Zergling";"Larva";139;1
"Unit";"Zergling";"Larva";140;1
"Unit";"Zergling";"Larva";141;1
"Unit";"Zergling";"Larva";142;1
"Unit";"Zergling";"Larva";143;1
"Unit";"Zergling";"Larva";144;1
"Building";"HydraliskDen";NA;145;0
"Unit";"Queen";"Hatchery";145;2
"Unit";"Zergling";"Larva";147;1
"Unit";"Zergling";"Larva";148;1
"Unit";"Zergling";"Larva";149;1
"Unit";"Zergling";"Larva";150;1
"Building";"SpineCrawler";NA;151;0
"Unit";"Queen";"Hatchery";151;2
"Unit";"Zergling";"Larva";153;1
"Unit";"Zergling";"Larva";154;1
"Building";"CreepTumor";NA;155;0
"Building";"CreepTumor";NA;155;0
"Unit";"Baneling";"Zergling";155;0
"Unit";"Baneling";"Zergling";155;0
"Unit";"Baneling";"Zergling";155;0
"Unit";"Baneling";"Zergling";155;0
"Unit";"Baneling";"Zergling";155;0
"Unit";"Baneling";"Zergling";155;0
"Unit";"Zergling";"Larva";155;1
"Unit";"Zergling";"Larva";156;1
"Unit";"Zergling";"Larva";157;1
"Unit";"Zergling";"Larva";158;1
"Unit";"Baneling";"Zergling";159;0
"Unit";"Baneling";"Zergling";159;0
"Unit";"Baneling";"Zergling";159;0
"Unit";"Baneling";"Zergling";159;0
"Building";"CreepTumor";NA;159;0
"Unit";"Zergling";"Larva";159;1
"Unit";"Zergling";"Larva";160;1
"Building";"SpineCrawler";NA;161;0
"Unit";"Baneling";"Zergling";161;0
"Unit";"Baneling";"Zergling";161;0
"Unit";"Baneling";"Zergling";161;0
"Unit";"Baneling";"Zergling";161;0
"Unit";"Baneling";"Zergling";161;0
"Unit";"Baneling";"Zergling";161;0
"Unit";"Zergling";"Larva";161;1
"Unit";"Zergling";"Larva";162;1
"Unit";"Zergling";"Larva";163;1
"Unit";"Zergling";"Larva";164;1
"Unit";"Zergling";"Larva";165;1
"Unit";"Zergling";"Larva";166;1
"Unit";"Zergling";"Larva";167;1
"Unit";"Zergling";"Larva";168;1
"Unit";"Zergling";"Larva";169;1
"Unit";"Zergling";"Larva";170;1
"Building";"CreepTumor";NA;171;0
"Unit";"Overlord";"Larva";171;0
"Building";"CreepTumor";NA;171;0
"Building";"CreepTumor";NA;171;0
"Unit";"Overlord";"Larva";177;0
"Building";"CreepTumor";NA;177;0
"Unit";"Overlord";"Larva";177;0
"Unit";"Hydralisk";"Larva";182;2
"Unit";"Hydralisk";"Larva";184;2
"Unit";"Hydralisk";"Larva";186;2
"Unit";"Hydralisk";"Larva";188;2
"Building";"SporeCrawler";NA;190;0
"Unit";"Hydralisk";"Larva";190;2
"Unit";"Hydralisk";"Larva";192;2
"Building";"Hatchery";NA;194;0
"Building";"CreepTumor";NA;199;0
"Unit";"Baneling";"Zergling";203;0
"Unit";"Baneling";"Zergling";203;0
"Unit";"Baneling";"Zergling";203;0
"Unit";"Baneling";"Zergling";203;0
"Unit";"Hydralisk";"Larva";203;2
"Unit";"Hydralisk";"Larva";205;2
"Unit";"Hydralisk";"Larva";207;2
"Unit";"Zergling";"Larva";209;1
"Unit";"Zergling";"Larva";210;1
"Unit";"Zergling";"Larva";211;1
"Unit";"Zergling";"Larva";212;1
"Unit";"Baneling";"Zergling";213;0
"Unit";"Baneling";"Zergling";213;0
"Unit";"Baneling";"Zergling";213;0
"Unit";"Baneling";"Zergling";213;0
"Unit";"Baneling";"Zergling";213;0
"Unit";"Zergling";"Larva";213;1
"Unit";"Zergling";"Larva";214;1
"Unit";"Zergling";"Larva";215;1
"Unit";"Zergling";"Larva";216;1
"Unit";"Hydralisk";"Larva";217;2
"Unit";"Hydralisk";"Larva";219;2
"Unit";"Hydralisk";"Larva";221;2
"Unit";"Hydralisk";"Larva";223;2
"Unit";"Hydralisk";"Larva";225;2
"Unit";"Overlord";"Larva";227;0
"Unit";"Zergling";"Larva";227;1
"Unit";"Zergling";"Larva";228;1
"Unit";"Zergling";"Larva";229;1
"Unit";"Zergling";"Larva";230;1
"Unit";"Zergling";"Larva";231;1
"Unit";"Zergling";"Larva";232;1
"Unit";"Zergling";"Larva";233;1
"Unit";"Zergling";"Larva";234;1
"Unit";"Zergling";"Larva";235;1
"Unit";"Zergling";"Larva";236;1
"Unit";"Zergling";"Larva";237;1
"Unit";"Zergling";"Larva";238;1
"Unit";"Zergling";"Larva";239;1
"Unit";"Zergling";"Larva";240;1
"Unit";"Zergling";"Larva";241;1
"Unit";"Zergling";"Larva";242;1
"Unit";"Zergling";"Larva";243;1
"Unit";"Zergling";"Larva";244;1
"Unit";"Zergling";"Larva";245;1
"Unit";"Zergling";"Larva";246;1
"Unit";"Zergling";"Larva";247;1
"Unit";"Zergling";"Larva";248;1
"Unit";"Hydralisk";"Larva";249;2
"Unit";"Hydralisk";"Larva";251;2
"Unit";"Hydralisk";"Larva";253;2
"Unit";"Hydralisk";"Larva";255;2
"Unit";"Hydralisk";"Larva";257;2
"Unit";"Zergling";"Larva";259;1
"Unit";"Zergling";"Larva";260;1
"Unit";"Baneling";"Zergling";261;0
"Unit";"Baneling";"Zergling";261;0
"Unit";"Baneling";"Zergling";261;0
"Unit";"Baneling";"Zergling";261;0
"Unit";"Zergling";"Larva";261;1
"Unit";"Zergling";"Larva";262;1
"Unit";"Zergling";"Larva";263;1
"Unit";"Zergling";"Larva";264;1
"Unit";"Zergling";"Larva";265;1
"Unit";"Zergling";"Larva";266;1
"Unit";"Baneling";"Zergling";267;0
"Unit";"Baneling";"Zergling";267;0
"Unit";"Baneling";"Zergling";267;0
"Unit";"Baneling";"Zergling";267;0
"Unit";"Baneling";"Zergling";267;0
"Unit";"Baneling";"Zergling";267;0
"Unit";"Baneling";"Zergling";267;0
"Unit";"Baneling";"Zergling";267;0
"Unit";"Hydralisk";"Larva";267;2
"Unit";"Hydralisk";"Larva";269;2
"Unit";"Overlord";"Larva";271;0
"Unit";"Overlord";"Larva";271;0
"Unit";"Zergling";"Larva";271;1
"Unit";"Zergling";"Larva";272;1
"Unit";"Overlord";"Larva";273;0
"Unit";"Zergling";"Larva";273;1
"Unit";"Zergling";"Larva";274;1
"Unit";"Zergling";"Larva";275;1
"Unit";"Zergling";"Larva";276;1
"Unit";"Zergling";"Larva";277;1
"Unit";"Zergling";"Larva";278;1
"Unit";"Overlord";"Larva";279;0
"Building";"CreepTumor";NA;279;0
"Unit";"Zergling";"Larva";279;1
"Unit";"Zergling";"Larva";280;1
"Unit";"Zergling";"Larva";281;1
"Unit";"Zergling";"Larva";282;1
"Unit";"Zergling";"Larva";283;1
"Unit";"Zergling";"Larva";284;1
"Building";"CreepTumor";NA;287;0
"Unit";"Hydralisk";"Larva";287;2
"Unit";"Hydralisk";"Larva";289;2
"Unit";"Hydralisk";"Larva";291;2
"Unit";"Hydralisk";"Larva";293;2
"Unit";"Hydralisk";"Larva";295;2
"Unit";"Hydralisk";"Larva";297;2
"Unit";"Hydralisk";"Larva";299;2
"Unit";"Zergling";"Larva";301;1
"Unit";"Zergling";"Larva";302;1
"Unit";"Zergling";"Larva";303;1
"Unit";"Zergling";"Larva";304;1
"Unit";"Zergling";"Larva";305;1
"Unit";"Zergling";"Larva";306;1
"Unit";"Zergling";"Larva";307;1
"Unit";"Zergling";"Larva";308;1
"Unit";"Zergling";"Larva";309;1
"Unit";"Zergling";"Larva";310;1
"Unit";"Zergling";"Larva";311;1
"Unit";"Zergling";"Larva";312;1
"Unit";"Zergling";"Larva";313;1
"Unit";"Zergling";"Larva";314;1
"Unit";"Zergling";"Larva";315;1
"Unit";"Zergling";"Larva";316;1
"Building";"CreepTumor";NA;317;0
"Building";"CreepTumor";NA;317;0
"Unit";"Overlord";"Larva";317;0
"Building";"Hatchery";NA;317;0
"Unit";"Zergling";"Larva";317;1
"Unit";"Zergling";"Larva";318;1
"Unit";"Zergling";"Larva";319;1
"Unit";"Zergling";"Larva";320;1
"Unit";"Zergling";"Larva";321;1
"Unit";"Zergling";"Larva";322;1
"Unit";"Zergling";"Larva";323;1
"Unit";"Zergling";"Larva";324;1
"Unit";"Zergling";"Larva";325;1
"Unit";"Zergling";"Larva";326;1
"Unit";"Zergling";"Larva";327;1
"Unit";"Zergling";"Larva";328;1
"Unit";"Zergling";"Larva";329;1
"Unit";"Zergling";"Larva";330;1
"Unit";"Zergling";"Larva";331;1
"Unit";"Zergling";"Larva";332;1
"Unit";"Zergling";"Larva";333;1
"Unit";"Zergling";"Larva";334;1
"Unit";"Zergling";"Larva";335;1
"Unit";"Zergling";"Larva";336;1
"Unit";"Zergling";"Larva";337;1
"Unit";"Zergling";"Larva";338;1
"Unit";"Overlord";"Larva";339;0
"Unit";"Baneling";"Zergling";339;0
"Unit";"Baneling";"Zergling";339;0
"Unit";"Baneling";"Zergling";339;0
"Unit";"Baneling";"Zergling";339;0
"Unit";"Baneling";"Zergling";339;0
"Unit";"Baneling";"Zergling";339;0
"Unit";"Baneling";"Zergling";339;0
"Unit";"Baneling";"Zergling";339;0
"Unit";"Baneling";"Zergling";339;0
"Unit";"Baneling";"Zergling";339;0
"Unit";"Baneling";"Zergling";339;0
"Unit";"Baneling";"Zergling";339;0
"Unit";"Baneling";"Zergling";339;0
"Unit";"Baneling";"Zergling";339;0
"Unit";"Baneling";"Zergling";339;0
"Unit";"Baneling";"Zergling";339;0
"Unit";"Baneling";"Zergling";339;0
"Unit";"Baneling";"Zergling";339;0
"Unit";"Baneling";"Zergling";339;0
"Unit";"Baneling";"Zergling";339;0
"Unit";"Baneling";"Zergling";339;0
"Unit";"Baneling";"Zergling";339;0
"Unit";"Baneling";"Zergling";339;0
"Unit";"Baneling";"Zergling";339;0
"Unit";"Baneling";"Zergling";339;0
"Building";"CreepTumor";NA;339;0
"Unit";"Zergling";"Larva";339;1
"Unit";"Zergling";"Larva";340;1
"Unit";"Zergling";"Larva";341;1
"Unit";"Zergling";"Larva";342;1
"Unit";"Zergling";"Larva";343;1
"Unit";"Zergling";"Larva";344;1
"Unit";"Zergling";"Larva";345;1
"Unit";"Zergling";"Larva";346;1
"Unit";"Zergling";"Larva";347;1
"Unit";"Zergling";"Larva";348;1
"Unit";"Zergling";"Larva";349;1
"Unit";"Zergling";"Larva";350;1
"Unit";"Zergling";"Larva";351;1
"Unit";"Zergling";"Larva";352;1
"Unit";"Zergling";"Larva";353;1
"Unit";"Zergling";"Larva";354;1
"Unit";"Zergling";"Larva";355;1
"Unit";"Zergling";"Larva";356;1
"Unit";"Zergling";"Larva";357;1
"Unit";"Zergling";"Larva";358;1
"Unit";"Zergling";"Larva";359;1
"Unit";"Zergling";"Larva";360;1
"Unit";"Zergling";"Larva";361;1
"Unit";"Zergling";"Larva";362;1
"Unit";"Zergling";"Larva";363;1
"Unit";"Zergling";"Larva";364;1
"Unit";"Zergling";"Larva";365;1
"Unit";"Zergling";"Larva";366;1
"Unit";"Zergling";"Larva";367;1
"Unit";"Zergling";"Larva";368;1
"Unit";"Zergling";"Larva";369;1
"Unit";"Zergling";"Larva";370;1
"Unit";"Baneling";"Zergling";371;0
"Unit";"Baneling";"Zergling";371;0
"Unit";"Baneling";"Zergling";371;0
"Unit";"Baneling";"Zergling";371;0
"Unit";"Baneling";"Zergling";371;0
"Unit";"Baneling";"Zergling";371;0
"Unit";"Baneling";"Zergling";371;0
"Unit";"Baneling";"Zergling";371;0
"Unit";"Baneling";"Zergling";371;0
"Unit";"Baneling";"Zergling";371;0
"Unit";"Baneling";"Zergling";371;0
"Unit";"Baneling";"Zergling";371;0
"Unit";"Zergling";"Larva";371;1
"Unit";"Zergling";"Larva";372;1
"Unit";"Zergling";"Larva";373;1
"Unit";"Zergling";"Larva";374;1
"Unit";"Zergling";"Larva";375;1
"Unit";"Zergling";"Larva";376;1
"Unit";"Overlord";"Larva";377;0
"Building";"CreepTumor";NA;377;0
"Unit";"Baneling";"Zergling";377;0
"Unit";"Baneling";"Zergling";377;0
"Unit";"Baneling";"Zergling";377;0
"Unit";"Baneling";"Zergling";377;0
"Unit";"Baneling";"Zergling";377;0
"Unit";"Baneling";"Zergling";377;0
"Unit";"Baneling";"Zergling";377;0
"Unit";"Baneling";"Zergling";377;0
"Unit";"Baneling";"Zergling";377;0
"Unit";"Baneling";"Zergling";377;0
"Unit";"Baneling";"Zergling";377;0
"Unit";"Baneling";"Zergling";377;0
"Unit";"Baneling";"Zergling";377;0
"Unit";"Baneling";"Zergling";377;0
"Unit";"Baneling";"Zergling";377;0
"Unit";"Baneling";"Zergling";377;0
"Unit";"Baneling";"Zergling";377;0
"Unit";"Baneling";"Zergling";377;0
"Unit";"Baneling";"Zergling";377;0
"Unit";"Baneling";"Zergling";377;0
"Unit";"Baneling";"Zergling";377;0
"Unit";"Baneling";"Zergling";377;0
"Unit";"Zergling";"Larva";377;1
"Unit";"Zergling";"Larva";378;1
"Unit";"Zergling";"Larva";379;1
"Unit";"Zergling";"Larva";380;1
"Unit";"Zergling";"Larva";381;1
"Unit";"Zergling";"Larva";382;1
"Unit";"Zergling";"Larva";383;1
"Unit";"Zergling";"Larva";384;1
"Unit";"Zergling";"Larva";385;1
"Unit";"Zergling";"Larva";386;1
"Unit";"Zergling";"Larva";387;1
"Unit";"Zergling";"Larva";388;1
"Unit";"Zergling";"Larva";389;1
"Unit";"Zergling";"Larva";390;1
"Unit";"Zergling";"Larva";391;1
"Unit";"Zergling";"Larva";392;1
"Unit";"Zergling";"Larva";393;1
"Unit";"Zergling";"Larva";394;1
"Unit";"Zergling";"Larva";395;1
"Unit";"Zergling";"Larva";396;1
"Unit";"Zergling";"Larva";397;1
"Unit";"Zergling";"Larva";398;1
"Unit";"Zergling";"Larva";399;1
"Unit";"Zergling";"Larva";400;1
"Unit";"Zergling";"Larva";401;1
"Unit";"Zergling";"Larva";402;1
"Building";"CreepTumorQueen";NA;403;0
"Upgrade";"SprayZerg";NA;403;0
"Upgrade";"SprayZerg";NA;403;0
"Upgrade";"SprayZerg";NA;403;0
"Upgrade";"zerglingmovementspeed";NA;403;0
"Upgrade";"SprayZerg";NA;403;0
"Upgrade";"overlordspeed";NA;403;0
"Upgrade";"SprayZerg";NA;403;0
"Upgrade";"ZergMeleeWeaponsLevel1";NA;403;0
"Upgrade";"SprayZerg";NA;403;0
"Upgrade";"SprayZerg";NA;403;0
"Upgrade";"EvolveGroovedSpines";NA;403;0
"Upgrade";"CentrificalHooks";NA;403;0
"Upgrade";"SprayZerg";NA;403;0
"Upgrade";"SprayZerg";NA;403;0
"Upgrade";"EvolveMuscularAugments";NA;403;0
"Upgrade";"ZergMeleeWeaponsLevel2";NA;403;0
"Upgrade";"SprayZerg";NA;403;0
