"type";"unit_name";"on_building";"total_supply";"supply"
"Unit";"Overlord";"Larva";12;0
"Building";"Extractor";NA;17;0
"Unit";"Overlord";"Larva";21;0
"Building";"SpawningPool";NA;19;0
"Building";"Hatchery";NA;17;0
"Unit";"Zergling";"Larva";24;1
"Unit";"Zergling";"Larva";24;1
"Unit";"Zergling";"Larva";24;1
"Unit";"Zergling";"Larva";24;1
"Unit";"Queen";"Hatchery";22;2
"Unit";"Queen";"Hatchery";23;2
"Unit";"Overlord";"Larva";35;0
"Unit";"Overlord";"Larva";35;0
"Unit";"Queen";"Hatchery";35;2
"Unit";"Overlord";"Larva";41;0
"Building";"Hatchery";NA;35;0
"Unit";"Overlord";"Larva";46;0
"Unit";"Overlord";"Larva";50;0
"Building";"SporeCrawler";NA;51;0
"Building";"SporeCrawler";NA;51;0
"Unit";"Overlord";"Larva";57;0
"Building";"Extractor";NA;57;0
"Unit";"Queen";"Hatchery";51;2
"Building";"SporeCrawler";NA;57;0
"Building";"EvolutionChamber";NA;57;0
"Building";"CreepTumorQueen";NA;70;0
"Building";"RoachWarren";NA;60;0
"Building";"CreepTumorQueen";NA;70;0
"Unit";"Roach";"Larva";77;2
"Unit";"Roach";"Larva";77;2
"Unit";"Roach";"Larva";77;2
"Unit";"Roach";"Larva";77;2
"Unit";"Roach";"Larva";77;2
"Unit";"Roach";"Larva";77;2
"Building";"CreepTumor";NA;77;0
"Building";"CreepTumor";NA;77;0
"Unit";"Zergling";"Larva";88;1
"Unit";"Zergling";"Larva";88;1
"Unit";"Zergling";"Larva";90;1
"Unit";"Zergling";"Larva";90;1
"Building";"CreepTumorQueen";NA;90;0
"Building";"Extractor";NA;78;0
"Unit";"Roach";"Larva";94;2
"Unit";"Roach";"Larva";94;2
"Building";"CreepTumor";NA;98;0
"Building";"CreepTumor";NA;98;0
"Unit";"Overlord";"Larva";98;0
"Unit";"Overlord";"Larva";98;0
"Unit";"Overlord";"Larva";98;0
"Unit";"Roach";"Larva";102;2
"Unit";"Roach";"Larva";102;2
"Unit";"Roach";"Larva";102;2
"Unit";"Roach";"Larva";102;2
"Unit";"Roach";"Larva";102;2
"Unit";"Roach";"Larva";102;2
"Unit";"Roach";"Larva";102;2
"Unit";"Roach";"Larva";102;2
"Unit";"Roach";"Larva";102;2
"Unit";"Roach";"Larva";102;2
"Upgrade";"GlialReconstitution";"RoachWarren";94;0
"Building";"Hatchery";NA;88;0
"Building";"CreepTumor";NA;123;0
"Upgrade";"ZergMissileWeaponsLevel1";"EvolutionChamber";88;0
"Unit";"Roach";"Larva";125;2
"Unit";"Roach";"Larva";125;2
"Unit";"Overlord";"Larva";125;0
"Unit";"Roach";"Larva";125;2
"Unit";"Roach";"Larva";125;2
"Unit";"Roach";"Larva";125;2
"Unit";"Overlord";"Larva";125;0
"Unit";"Overlord";"Larva";125;0
"Unit";"Overlord";"Larva";125;0
"Unit";"Overlord";"Larva";125;0
"Building";"Extractor";NA;125;0
"Building";"CreepTumor";NA;126;0
"Building";"CreepTumor";NA;126;0
"Building";"CreepTumor";NA;136;0
"Unit";"Roach";"Larva";136;2
"Unit";"Roach";"Larva";136;2
"Unit";"Roach";"Larva";136;2
"Unit";"Roach";"Larva";136;2
"Unit";"Roach";"Larva";136;2
"Unit";"Roach";"Larva";136;2
"Unit";"Roach";"Larva";136;2
"Unit";"Roach";"Larva";136;2
"Building";"Extractor";NA;136;0
"Building";"CreepTumor";NA;165;0
"Building";"CreepTumor";NA;165;0
"Building";"Hatchery";NA;130;0
"Building";"Extractor";NA;165;0
"Unit";"Overlord";"Larva";183;0
"Unit";"Overlord";"Larva";183;0
"Building";"Spire";NA;165;0
"Building";"Extractor";NA;183;0
"Building";"Extractor";NA;183;0
"Unit";"Zergling";"Larva";183;1
"Unit";"Zergling";"Larva";183;1
"Unit";"Zergling";"Larva";183;1
"Unit";"Zergling";"Larva";183;1
"Unit";"Zergling";"Larva";183;1
"Unit";"Zergling";"Larva";183;1
"Unit";"Zergling";"Larva";183;1
"Unit";"Zergling";"Larva";183;1
"Unit";"Zergling";"Larva";183;1
"Unit";"Zergling";"Larva";183;1
"Unit";"Zergling";"Larva";183;1
"Unit";"Zergling";"Larva";183;1
"Unit";"Zergling";"Larva";183;1
"Unit";"Zergling";"Larva";183;1
"Unit";"Zergling";"Larva";183;1
"Unit";"Zergling";"Larva";183;1
"Unit";"Zergling";"Larva";183;1
"Unit";"Zergling";"Larva";183;1
"Unit";"Zergling";"Larva";183;1
"Unit";"Zergling";"Larva";183;1
"Unit";"Zergling";"Larva";183;1
"Unit";"Zergling";"Larva";183;1
"Unit";"Zergling";"Larva";183;1
"Unit";"Zergling";"Larva";183;1
"Unit";"Zergling";"Larva";183;1
"Unit";"Zergling";"Larva";183;1
"Unit";"Zergling";"Larva";183;1
"Unit";"Zergling";"Larva";183;1
"Unit";"Zergling";"Larva";183;1
"Unit";"Zergling";"Larva";183;1
"Unit";"Zergling";"Larva";183;1
"Unit";"Zergling";"Larva";183;1
"Unit";"Zergling";"Larva";183;1
"Unit";"Zergling";"Larva";183;1
"Unit";"Zergling";"Larva";183;1
"Unit";"Zergling";"Larva";183;1
"Unit";"Zergling";"Larva";183;1
"Unit";"Zergling";"Larva";183;1
"Unit";"Zergling";"Larva";183;1
"Unit";"Zergling";"Larva";183;1
"Unit";"Zergling";"Larva";183;1
"Unit";"Zergling";"Larva";183;1
"Unit";"Zergling";"Larva";183;1
"Unit";"Zergling";"Larva";183;1
"Unit";"Zergling";"Larva";183;1
"Unit";"Zergling";"Larva";183;1
"Upgrade";"ZergMissileWeaponsLevel2";"EvolutionChamber";165;0
"Unit";"Overlord";"Larva";229;0
"Unit";"Overlord";"Larva";229;0
"Unit";"Overlord";"Larva";229;0
"Building";"Hatchery";NA;183;0
"Building";"InfestationPit";NA;229;0
"Unit";"Roach";"Larva";229;2
"Unit";"Roach";"Larva";229;2
"Unit";"Roach";"Larva";229;2
"Unit";"Roach";"Larva";229;2
"Unit";"Roach";"Larva";229;2
"Unit";"Roach";"Larva";229;2
"Unit";"Roach";"Larva";229;2
"Unit";"Roach";"Larva";229;2
"Unit";"Roach";"Larva";229;2
"Unit";"Roach";"Larva";229;2
"Unit";"Roach";"Larva";229;2
"Unit";"Roach";"Larva";229;2
"Unit";"Roach";"Larva";229;2
"Unit";"Roach";"Larva";229;2
"Unit";"Roach";"Larva";229;2
"Unit";"Roach";"Larva";229;2
"Unit";"Roach";"Larva";229;2
"Unit";"Roach";"Larva";229;2
"Unit";"Roach";"Larva";266;2
"Unit";"Roach";"Larva";266;2
"Unit";"Roach";"Larva";266;2
"Unit";"Roach";"Larva";266;2
"Unit";"Roach";"Larva";266;2
"Building";"HydraliskDen";NA;266;0
"Building";"Hatchery";NA;229;0
"Unit";"Roach";"Larva";276;2
"Unit";"Roach";"Larva";276;2
"Unit";"Roach";"Larva";276;2
"Unit";"Roach";"Larva";276;2
"Unit";"Roach";"Larva";276;2
"Unit";"Roach";"Larva";276;2
"Unit";"Roach";"Larva";276;2
"Unit";"Roach";"Larva";276;2
"Unit";"Roach";"Larva";276;2
"Unit";"Roach";"Larva";276;2
"Unit";"Roach";"Larva";276;2
"Unit";"Roach";"Larva";276;2
"Unit";"Roach";"Larva";276;2
"Unit";"Roach";"Larva";276;2
"Unit";"Roach";"Larva";276;2
"Unit";"Roach";"Larva";276;2
"Unit";"Roach";"Larva";276;2
"Unit";"Roach";"Larva";276;2
"Unit";"Roach";"Larva";276;2
"Unit";"Roach";"Larva";276;2
"Unit";"Roach";"Larva";276;2
"Unit";"Roach";"Larva";276;2
"Unit";"Roach";"Larva";276;2
"Unit";"Roach";"Larva";276;2
"Unit";"Roach";"Larva";314;2
"Unit";"Roach";"Larva";314;2
"Unit";"Roach";"Larva";314;2
"Unit";"Roach";"Larva";314;2
"Unit";"Roach";"Larva";314;2
"Unit";"Roach";"Larva";314;2
"Unit";"Roach";"Larva";314;2
"Upgrade";"ZergGroundArmorsLevel1";"EvolutionChamber";266;0
