"type";"unit_name";"on_building";"total_supply";"supply"
"Unit";"Overlord";"Larva";12;0
"Building";"SpawningPool";NA;17;0
"Building";"Extractor";NA;18;0
"Unit";"Overlord";"Larva";20;0
"Unit";"Zergling";"Larva";21;1
"Unit";"Zergling";"Larva";21;1
"Unit";"Queen";"Hatchery";21;2
"Building";"Hatchery";NA;18;0
"Unit";"Queen";"Hatchery";27;2
"Building";"CreepTumorQueen";NA;29;0
"Unit";"Zergling";"Larva";27;1
"Unit";"Zergling";"Larva";27;1
"Unit";"Overlord";"Larva";33;0
"Building";"Hatchery";NA;27;0
"Unit";"Overlord";"Larva";38;0
"Building";"CreepTumor";NA;42;0
"Building";"SporeCrawler";NA;42;0
"Unit";"Queen";"Hatchery";42;2
"Building";"SporeCrawler";NA;42;0
"Building";"SporeCrawler";NA;42;0
"Building";"CreepTumorQueen";NA;58;0
"Building";"Extractor";NA;69;0
"Unit";"Overlord";"Larva";69;0
"Unit";"Overlord";"Larva";69;0
"Unit";"Overlord";"Larva";69;0
"Building";"Extractor";NA;69;0
"Building";"EvolutionChamber";NA;69;0
"Unit";"Overlord";"Larva";69;0
"Unit";"Overlord";"Larva";69;0
"Unit";"Overlord";"Larva";69;0
"Building";"BanelingNest";NA;69;0
"Building";"CreepTumorQueen";NA;73;0
"Building";"CreepTumor";NA;77;0
"Building";"CreepTumorQueen";NA;81;0
"Unit";"Queen";"Hatchery";77;2
"Building";"Extractor";NA;84;0
"Unit";"Zergling";"Larva";84;1
"Unit";"Zergling";"Larva";84;1
"Unit";"Zergling";"Larva";84;1
"Unit";"Zergling";"Larva";84;1
"Unit";"Zergling";"Larva";84;1
"Unit";"Zergling";"Larva";84;1
"Unit";"Zergling";"Larva";84;1
"Unit";"Zergling";"Larva";84;1
"Building";"Extractor";NA;84;0
"Unit";"Zergling";"Larva";89;1
"Unit";"Zergling";"Larva";89;1
"Building";"CreepTumor";NA;95;0
"Building";"CreepTumorQueen";NA;101;0
"Building";"CreepTumor";NA;101;0
"Building";"CreepTumor";NA;101;0
"Building";"HydraliskDen";NA;93;0
"Unit";"Zergling";"Larva";105;1
"Unit";"Zergling";"Larva";105;1
"Unit";"Zergling";"Larva";105;1
"Unit";"Zergling";"Larva";105;1
"Unit";"Zergling";"Larva";105;1
"Unit";"Zergling";"Larva";105;1
"Unit";"Zergling";"Larva";105;1
"Unit";"Zergling";"Larva";105;1
"Unit";"Zergling";"Larva";105;1
"Unit";"Zergling";"Larva";105;1
"Unit";"Zergling";"Larva";105;1
"Unit";"Zergling";"Larva";105;1
"Unit";"Zergling";"Larva";105;1
"Unit";"Zergling";"Larva";105;1
"Unit";"Zergling";"Larva";105;1
"Unit";"Zergling";"Larva";105;1
"Unit";"Zergling";"Larva";105;1
"Unit";"Zergling";"Larva";105;1
"Unit";"Zergling";"Larva";105;1
"Unit";"Zergling";"Larva";105;1
"Unit";"Zergling";"Larva";105;1
"Unit";"Zergling";"Larva";105;1
"Unit";"Zergling";"Larva";105;1
"Unit";"Zergling";"Larva";105;1
"Unit";"Zergling";"Larva";105;1
"Unit";"Zergling";"Larva";105;1
"Unit";"Zergling";"Larva";105;1
"Unit";"Zergling";"Larva";105;1
"Unit";"Overlord";"Larva";105;0
"Unit";"Overlord";"Larva";105;0
"Unit";"Overlord";"Larva";105;0
"Building";"SpineCrawler";NA;105;0
"Unit";"Overlord";"Larva";123;0
"Unit";"Overlord";"Larva";123;0
"Building";"Hatchery";NA;89;0
"Building";"Hatchery";NA;89;0
"Building";"CreepTumorQueen";NA;133;0
"Upgrade";"ZergMissileWeaponsLevel1";"EvolutionChamber";89;0
"Building";"CreepTumorQueen";NA;133;0
"Unit";"Hydralisk";"Larva";133;2
"Unit";"Queen";"Hatchery";105;2
"Unit";"Hydralisk";"Larva";133;2
"Unit";"Hydralisk";"Larva";133;2
"Unit";"Hydralisk";"Larva";133;2
"Unit";"Hydralisk";"Larva";133;2
"Unit";"Hydralisk";"Larva";133;2
"Unit";"Hydralisk";"Larva";133;2
"Unit";"Hydralisk";"Larva";133;2
"Unit";"Hydralisk";"Larva";133;2
"Unit";"Hydralisk";"Larva";133;2
"Unit";"Hydralisk";"Larva";133;2
"Unit";"Hydralisk";"Larva";133;2
"Unit";"Hydralisk";"Larva";133;2
"Unit";"Zergling";"Larva";133;1
"Unit";"Zergling";"Larva";133;1
"Unit";"Hydralisk";"Larva";133;2
"Unit";"Hydralisk";"Larva";133;2
"Unit";"Hydralisk";"Larva";133;2
"Building";"CreepTumorQueen";NA;161;0
"Unit";"Zergling";"Larva";149;1
"Unit";"Zergling";"Larva";149;1
"Unit";"Zergling";"Larva";149;1
"Unit";"Zergling";"Larva";149;1
"Unit";"Zergling";"Larva";149;1
"Unit";"Zergling";"Larva";149;1
"Unit";"Zergling";"Larva";149;1
"Unit";"Zergling";"Larva";149;1
"Unit";"Zergling";"Larva";149;1
"Unit";"Zergling";"Larva";149;1
"Unit";"Zergling";"Larva";149;1
"Unit";"Zergling";"Larva";149;1
"Building";"CreepTumor";NA;163;0
"Building";"CreepTumor";NA;163;0
"Unit";"Queen";"Hatchery";133;2
"Unit";"Baneling";"Zergling";183;0
"Unit";"Baneling";"Zergling";184;0
"Unit";"Baneling";"Zergling";184;0
"Unit";"Baneling";"Zergling";184;0
"Unit";"Baneling";"Zergling";184;0
"Unit";"Baneling";"Zergling";184;0
"Unit";"Baneling";"Zergling";186;0
"Unit";"Baneling";"Zergling";188;0
"Unit";"Baneling";"Zergling";188;0
"Unit";"Baneling";"Zergling";188;0
"Unit";"Overlord";"Larva";201;0
"Unit";"Overlord";"Larva";202;0
"Unit";"Overlord";"Larva";202;0
"Unit";"Overlord";"Larva";202;0
"Unit";"Overlord";"Larva";202;0
"Upgrade";"EvolveGroovedSpines";"HydraliskDen";169;0
"Building";"CreepTumorQueen";NA;204;0
"Building";"CreepTumorQueen";NA;204;0
"Building";"CreepTumorQueen";NA;204;0
"Building";"CreepTumorQueen";NA;222;0
"Building";"Extractor";NA;204;0
"Building";"Extractor";NA;204;0
"Unit";"Hydralisk";"Larva";204;2
"Unit";"Hydralisk";"Larva";204;2
"Unit";"Hydralisk";"Larva";204;2
"Building";"Extractor";NA;225;0
"Building";"LurkerDenMP";NA;183;0
"Unit";"Hydralisk";"Larva";225;2
"Unit";"Hydralisk";"Larva";225;2
"Unit";"Hydralisk";"Larva";225;2
"Unit";"Hydralisk";"Larva";225;2
"Building";"CreepTumor";NA;225;0
"Unit";"Zergling";"Larva";225;1
"Unit";"Zergling";"Larva";225;1
"Unit";"Zergling";"Larva";225;1
"Unit";"Zergling";"Larva";225;1
"Unit";"Zergling";"Larva";225;1
"Unit";"Zergling";"Larva";225;1
"Unit";"Zergling";"Larva";225;1
"Unit";"Zergling";"Larva";225;1
"Unit";"Hydralisk";"Larva";225;2
"Upgrade";"EvolveMuscularAugments";"HydraliskDen";204;0
"Building";"InfestationPit";NA;225;0
"Unit";"Zergling";"Larva";249;1
"Unit";"Zergling";"Larva";249;1
"Unit";"Zergling";"Larva";249;1
"Unit";"Zergling";"Larva";249;1
"Unit";"Zergling";"Larva";249;1
"Unit";"Zergling";"Larva";249;1
"Unit";"Zergling";"Larva";249;1
"Unit";"Zergling";"Larva";249;1
"Unit";"Zergling";"Larva";249;1
"Unit";"Zergling";"Larva";249;1
"Unit";"Zergling";"Larva";249;1
"Unit";"Zergling";"Larva";249;1
"Unit";"Zergling";"Larva";249;1
"Unit";"Zergling";"Larva";249;1
"Unit";"Zergling";"Larva";249;1
"Unit";"Zergling";"Larva";249;1
"Unit";"Zergling";"Larva";249;1
"Unit";"Zergling";"Larva";249;1
"Unit";"Zergling";"Larva";249;1
"Unit";"Zergling";"Larva";249;1
"Unit";"Zergling";"Larva";249;1
"Unit";"Zergling";"Larva";249;1
"Unit";"Zergling";"Larva";249;1
"Unit";"Zergling";"Larva";249;1
"Building";"CreepTumor";NA;249;0
"Unit";"Baneling";"Zergling";249;0
"Unit";"Baneling";"Zergling";249;0
"Unit";"Baneling";"Zergling";249;0
"Unit";"Baneling";"Zergling";249;0
"Unit";"Baneling";"Zergling";249;0
"Building";"CreepTumor";NA;273;0
"Unit";"Hydralisk";"Larva";249;2
"Unit";"Hydralisk";"Larva";249;2
"Unit";"Hydralisk";"Larva";249;2
"Unit";"Hydralisk";"Larva";249;2
"Unit";"Hydralisk";"Larva";249;2
"Unit";"Hydralisk";"Larva";249;2
"Unit";"Hydralisk";"Larva";249;2
"Unit";"Hydralisk";"Larva";249;2
"Building";"Hatchery";NA;205;0
"Building";"Hatchery";NA;225;0
"Building";"CreepTumorQueen";NA;289;0
"Building";"CreepTumorQueen";NA;289;0
"Building";"SporeCrawler";NA;273;0
"Unit";"Zergling";"Larva";289;1
"Unit";"Zergling";"Larva";289;1
"Unit";"Zergling";"Larva";289;1
"Unit";"Zergling";"Larva";289;1
"Unit";"Zergling";"Larva";289;1
"Unit";"Zergling";"Larva";289;1
"Unit";"Zergling";"Larva";289;1
"Unit";"Zergling";"Larva";289;1
"Unit";"Zergling";"Larva";289;1
"Unit";"Zergling";"Larva";289;1
"Unit";"Zergling";"Larva";289;1
"Unit";"Zergling";"Larva";289;1
"Unit";"Zergling";"Larva";289;1
"Unit";"Zergling";"Larva";289;1
"Unit";"Zergling";"Larva";289;1
"Unit";"Zergling";"Larva";289;1
"Unit";"Zergling";"Larva";289;1
"Unit";"Zergling";"Larva";289;1
"Unit";"Zergling";"Larva";289;1
"Unit";"Zergling";"Larva";289;1
"Unit";"Zergling";"Larva";289;1
"Unit";"Zergling";"Larva";289;1
"Unit";"Zergling";"Larva";289;1
"Unit";"Zergling";"Larva";289;1
"Unit";"Zergling";"Larva";289;1
"Unit";"Zergling";"Larva";289;1
"Unit";"Hydralisk";"Larva";289;2
"Unit";"Hydralisk";"Larva";289;2
"Unit";"Hydralisk";"Larva";289;2
"Unit";"Hydralisk";"Larva";289;2
"Unit";"Hydralisk";"Larva";289;2
"Unit";"Hydralisk";"Larva";289;2
"Building";"SpineCrawler";NA;273;0
"Building";"SpineCrawler";NA;273;0
"Building";"SpineCrawler";NA;273;0
"Building";"SpineCrawler";NA;273;0
"Building";"SpineCrawler";NA;273;0
"Building";"Extractor";NA;289;0
"Building";"Extractor";NA;289;0
"Building";"SporeCrawler";NA;289;0
"Unit";"Zergling";"Larva";315;1
"Unit";"Zergling";"Larva";315;1
"Unit";"Zergling";"Larva";315;1
"Unit";"Zergling";"Larva";315;1
"Unit";"Zergling";"Larva";315;1
"Unit";"Zergling";"Larva";315;1
"Unit";"Zergling";"Larva";315;1
"Unit";"Zergling";"Larva";315;1
"Unit";"Zergling";"Larva";315;1
"Unit";"Zergling";"Larva";315;1
"Unit";"Zergling";"Larva";315;1
"Unit";"Zergling";"Larva";315;1
"Unit";"Zergling";"Larva";315;1
"Unit";"Zergling";"Larva";315;1
"Unit";"Zergling";"Larva";315;1
"Unit";"Zergling";"Larva";315;1
"Unit";"Zergling";"Larva";315;1
"Unit";"Zergling";"Larva";315;1
"Unit";"Zergling";"Larva";315;1
"Unit";"Zergling";"Larva";315;1
"Unit";"Zergling";"Larva";315;1
"Unit";"Zergling";"Larva";315;1
"Unit";"Zergling";"Larva";315;1
"Unit";"Zergling";"Larva";315;1
"Unit";"Zergling";"Larva";315;1
"Unit";"Zergling";"Larva";315;1
"Unit";"Zergling";"Larva";315;1
"Unit";"Zergling";"Larva";315;1
"Unit";"Zergling";"Larva";315;1
"Unit";"Zergling";"Larva";315;1
"Building";"CreepTumor";NA;327;0
"Unit";"Overlord";"Larva";327;0
"Unit";"Overlord";"Larva";327;0
"Unit";"Overlord";"Larva";327;0
"Building";"CreepTumor";NA;327;0
"Building";"CreepTumor";NA;327;0
"Building";"CreepTumor";NA;327;0
"Building";"CreepTumor";NA;327;0
"Building";"CreepTumor";NA;327;0
"Building";"CreepTumor";NA;327;0
"Building";"SpineCrawler";NA;289;0
"Building";"Extractor";NA;327;0
"Building";"SpineCrawler";NA;289;0
"Building";"CreepTumorQueen";NA;357;0
"Building";"CreepTumorQueen";NA;357;0
"Unit";"Overlord";"Larva";357;0
"Unit";"Overlord";"Larva";357;0
"Upgrade";"ZergMissileWeaponsLevel2";"EvolutionChamber";249;0
"Building";"CreepTumor";NA;360;0
"Building";"CreepTumor";NA;360;0
"Building";"CreepTumor";NA;360;0
"Building";"EvolutionChamber";NA;360;0
"Unit";"Baneling";"Zergling";360;0
"Unit";"Baneling";"Zergling";360;0
"Unit";"Baneling";"Zergling";360;0
"Unit";"Baneling";"Zergling";360;0
"Unit";"Baneling";"Zergling";360;0
"Unit";"Baneling";"Zergling";360;0
"Unit";"Baneling";"Zergling";360;0
"Unit";"Baneling";"Zergling";360;0
"Unit";"Baneling";"Zergling";360;0
"Unit";"Baneling";"Zergling";360;0
"Unit";"Baneling";"Zergling";360;0
"Unit";"Baneling";"Zergling";360;0
"Unit";"Baneling";"Zergling";360;0
"Unit";"Baneling";"Zergling";360;0
"Unit";"Baneling";"Zergling";360;0
"Unit";"Baneling";"Zergling";360;0
"Unit";"Baneling";"Zergling";360;0
"Unit";"Baneling";"Zergling";360;0
"Unit";"Baneling";"Zergling";360;0
"Unit";"Baneling";"Zergling";360;0
"Unit";"Baneling";"Zergling";360;0
"Unit";"Baneling";"Zergling";360;0
"Unit";"Baneling";"Zergling";360;0
"Unit";"Baneling";"Zergling";360;0
"Unit";"Baneling";"Zergling";360;0
"Unit";"Baneling";"Zergling";360;0
"Unit";"Baneling";"Zergling";360;0
"Unit";"Baneling";"Zergling";360;0
"Unit";"Baneling";"Zergling";360;0
"Building";"SpineCrawler";NA;360;0
"Building";"SpineCrawler";NA;360;0
"Building";"SpineCrawler";NA;360;0
"Building";"SpineCrawler";NA;360;0
"Building";"CreepTumor";NA;360;0
"Building";"CreepTumor";NA;360;0
"Unit";"Hydralisk";"Larva";360;2
"Unit";"Hydralisk";"Larva";360;2
"Unit";"Hydralisk";"Larva";360;2
"Unit";"Hydralisk";"Larva";360;2
"Unit";"Hydralisk";"Larva";360;2
"Building";"Spire";NA;360;0
"Unit";"Hydralisk";"Larva";370;2
"Unit";"Zergling";"Larva";370;1
"Unit";"Zergling";"Larva";370;1
"Unit";"Hydralisk";"Larva";370;2
"Unit";"Hydralisk";"Larva";370;2
"Unit";"Hydralisk";"Larva";370;2
"Unit";"Hydralisk";"Larva";370;2
"Unit";"Hydralisk";"Larva";370;2
"Unit";"Zergling";"Larva";370;1
"Unit";"Zergling";"Larva";370;1
"Unit";"Hydralisk";"Larva";370;2
"Unit";"Zergling";"Larva";370;1
"Unit";"Zergling";"Larva";370;1
"Unit";"Zergling";"Larva";370;1
"Unit";"Zergling";"Larva";370;1
"Unit";"Hydralisk";"Larva";370;2
"Unit";"Hydralisk";"Larva";370;2
"Unit";"Hydralisk";"Larva";370;2
"Unit";"Zergling";"Larva";370;1
"Unit";"Zergling";"Larva";370;1
"Unit";"Zergling";"Larva";370;1
"Unit";"Zergling";"Larva";370;1
"Unit";"Hydralisk";"Larva";370;2
"Unit";"Zergling";"Larva";370;1
"Unit";"Zergling";"Larva";370;1
"Unit";"Hydralisk";"Larva";370;2
"Unit";"Hydralisk";"Larva";370;2
"Unit";"Hydralisk";"Larva";370;2
"Unit";"Zergling";"Larva";370;1
"Unit";"Zergling";"Larva";370;1
"Unit";"Zergling";"Larva";370;1
"Unit";"Zergling";"Larva";370;1
"Unit";"Zergling";"Larva";370;1
"Unit";"Zergling";"Larva";370;1
"Unit";"Hydralisk";"Larva";370;2
"Unit";"Zergling";"Larva";370;1
"Unit";"Zergling";"Larva";370;1
"Unit";"Zergling";"Larva";370;1
"Unit";"Zergling";"Larva";370;1
"Unit";"Zergling";"Larva";370;1
"Unit";"Zergling";"Larva";370;1
"Unit";"Zergling";"Larva";370;1
"Unit";"Zergling";"Larva";370;1
"Unit";"Zergling";"Larva";370;1
"Unit";"Zergling";"Larva";370;1
"Unit";"Zergling";"Larva";370;1
"Unit";"Zergling";"Larva";370;1
"Unit";"Zergling";"Larva";370;1
"Unit";"Zergling";"Larva";370;1
"Unit";"Zergling";"Larva";370;1
"Unit";"Zergling";"Larva";370;1
"Unit";"Zergling";"Larva";370;1
"Unit";"Zergling";"Larva";370;1
"Unit";"Zergling";"Larva";370;1
"Unit";"Zergling";"Larva";370;1
"Unit";"Zergling";"Larva";370;1
"Unit";"Zergling";"Larva";370;1
"Unit";"Zergling";"Larva";370;1
"Unit";"Zergling";"Larva";370;1
"Unit";"Zergling";"Larva";370;1
"Unit";"Zergling";"Larva";370;1
"Unit";"Zergling";"Larva";370;1
"Unit";"Zergling";"Larva";370;1
"Unit";"Zergling";"Larva";370;1
"Unit";"Zergling";"Larva";370;1
"Unit";"Zergling";"Larva";370;1
"Unit";"Zergling";"Larva";370;1
"Unit";"Zergling";"Larva";370;1
"Unit";"Zergling";"Larva";370;1
"Unit";"Zergling";"Larva";370;1
"Unit";"Zergling";"Larva";370;1
"Unit";"Zergling";"Larva";370;1
"Unit";"Zergling";"Larva";370;1
"Unit";"Zergling";"Larva";370;1
"Unit";"Zergling";"Larva";370;1
"Unit";"Zergling";"Larva";370;1
"Unit";"Zergling";"Larva";370;1
"Unit";"Zergling";"Larva";370;1
"Unit";"Zergling";"Larva";370;1
"Unit";"Zergling";"Larva";370;1
"Unit";"Zergling";"Larva";370;1
"Unit";"Baneling";"Zergling";454;0
"Unit";"Baneling";"Zergling";454;0
"Unit";"Baneling";"Zergling";454;0
"Unit";"Baneling";"Zergling";454;0
"Unit";"Baneling";"Zergling";454;0
"Unit";"Baneling";"Zergling";454;0
"Unit";"Baneling";"Zergling";454;0
"Unit";"Baneling";"Zergling";466;0
"Unit";"Baneling";"Zergling";466;0
"Unit";"Baneling";"Zergling";466;0
"Unit";"Baneling";"Zergling";466;0
"Unit";"Baneling";"Zergling";466;0
"Unit";"Baneling";"Zergling";466;0
"Unit";"Baneling";"Zergling";466;0
"Unit";"Baneling";"Zergling";466;0
"Unit";"Baneling";"Zergling";466;0
"Unit";"Baneling";"Zergling";466;0
"Unit";"Baneling";"Zergling";466;0
"Upgrade";"ZergMeleeWeaponsLevel1";"EvolutionChamber";360;0
"Unit";"Hydralisk";"Larva";466;2
"Unit";"Hydralisk";"Larva";466;2
"Unit";"Hydralisk";"Larva";466;2
"Unit";"Hydralisk";"Larva";466;2
"Unit";"Hydralisk";"Larva";466;2
"Unit";"Hydralisk";"Larva";466;2
