"type";"unit_name";"on_building";"total_supply_lag";"supply"
"Unit";"Overlord";"Larva";13;0
"Building";"Hatchery";NA;16;0
"Building";"SpawningPool";NA;18;0
"Building";"Extractor";NA;18;0
"Unit";"Overlord";"Larva";22;0
"Unit";"Queen";"Hatchery";23;2
"Unit";"Queen";"Hatchery";25;2
"Unit";"Zergling";"Larva";27;1
"Unit";"Zergling";"Larva";28;1
"Building";"Hatchery";NA;34;0
"Building";"CreepTumorQueen";NA;35;0
"Unit";"Queen";"Hatchery";36;2
"Unit";"Overlord";"Larva";38;0
"Unit";"Zergling";"Larva";38;1
"Unit";"Zergling";"Larva";39;1
"Unit";"Overlord";"Larva";44;0
"Building";"CreepTumor";NA;47;0
"Unit";"Queen";"Hatchery";49;2
"Unit";"Overlord";"Larva";51;0
"Building";"SporeCrawler";NA;53;0
"Building";"CreepTumor";NA;54;0
"Building";"CreepTumorQueen";NA;54;0
"Unit";"Queen";"Hatchery";57;2
"Unit";"Overlord";"Larva";59;0
"Building";"Extractor";NA;62;0
"Building";"Extractor";NA;62;0
"Building";"CreepTumor";NA;65;0
"Building";"CreepTumor";NA;65;0
"Unit";"Queen";"Hatchery";65;2
"Building";"CreepTumorQueen";NA;68;0
"Unit";"Zergling";"Larva";73;1
"Unit";"Zergling";"Larva";74;1
"Unit";"Zergling";"Larva";75;1
"Unit";"Zergling";"Larva";76;1
"Unit";"Zergling";"Larva";77;1
"Unit";"Zergling";"Larva";78;1
"Unit";"Overlord";"Larva";79;0
"Unit";"Zergling";"Larva";79;1
"Unit";"Zergling";"Larva";80;1
"Unit";"Zergling";"Larva";81;1
"Unit";"Zergling";"Larva";82;1
"Unit";"Zergling";"Larva";83;1
"Unit";"Zergling";"Larva";84;1
"Unit";"Zergling";"Larva";85;1
"Unit";"Zergling";"Larva";86;1
"Unit";"Zergling";"Larva";87;1
"Unit";"Zergling";"Larva";88;1
"Unit";"Zergling";"Larva";89;1
"Unit";"Zergling";"Larva";90;1
"Building";"HydraliskDen";NA;91;0
"Unit";"Overlord";"Larva";96;0
"Building";"CreepTumorQueen";NA;96;0
"Unit";"Overlord";"Larva";96;0
"Building";"CreepTumor";NA;96;0
"Unit";"Overlord";"Larva";96;0
"Building";"CreepTumor";NA;96;0
"Unit";"Zergling";"Larva";96;1
"Unit";"Zergling";"Larva";97;1
"Unit";"Zergling";"Larva";98;1
"Unit";"Zergling";"Larva";99;1
"Unit";"Zergling";"Larva";100;1
"Unit";"Zergling";"Larva";101;1
"Unit";"Zergling";"Larva";102;1
"Unit";"Zergling";"Larva";103;1
"Unit";"Overlord";"Larva";104;0
"Unit";"Overlord";"Larva";104;0
"Unit";"Hydralisk";"Larva";104;2
"Unit";"Hydralisk";"Larva";106;2
"Unit";"Hydralisk";"Larva";108;2
"Unit";"Hydralisk";"Larva";110;2
"Unit";"Hydralisk";"Larva";112;2
"Unit";"Hydralisk";"Larva";114;2
"Building";"Extractor";NA;120;0
"Building";"EvolutionChamber";NA;120;0
"Building";"CreepTumor";NA;122;0
"Building";"BanelingNest";NA;122;0
"Unit";"Hydralisk";"Larva";122;2
"Building";"CreepTumor";NA;124;0
"Building";"CreepTumor";NA;124;0
"Unit";"Hydralisk";"Larva";124;2
"Building";"CreepTumorQueen";NA;126;0
"Building";"CreepTumorQueen";NA;126;0
"Unit";"Hydralisk";"Larva";126;2
"Unit";"Hydralisk";"Larva";128;2
"Building";"Extractor";NA;130;0
"Unit";"Overlord";"Larva";133;0
"Building";"CreepTumorQueen";NA;133;0
"Building";"CreepTumorQueen";NA;133;0
"Unit";"Hydralisk";"Larva";136;2
"Unit";"Hydralisk";"Larva";138;2
"Unit";"Hydralisk";"Larva";140;2
"Building";"CreepTumor";NA;142;0
"Unit";"Zergling";"Larva";144;1
"Unit";"Zergling";"Larva";145;1
"Unit";"Zergling";"Larva";146;1
"Unit";"Zergling";"Larva";147;1
"Unit";"Zergling";"Larva";148;1
"Unit";"Zergling";"Larva";149;1
"Unit";"Zergling";"Larva";150;1
"Unit";"Zergling";"Larva";151;1
"Building";"CreepTumor";NA;152;0
"Building";"CreepTumor";NA;152;0
"Building";"CreepTumorQueen";NA;152;0
"Building";"CreepTumor";NA;152;0
"Building";"CreepTumorQueen";NA;152;0
"Building";"CreepTumorQueen";NA;152;0
"Unit";"Overlord";"Larva";152;0
"Building";"CreepTumorQueen";NA;152;0
"Unit";"Overlord";"Larva";152;0
"Building";"Extractor";NA;152;0
"Unit";"Overlord";"Larva";156;0
"Unit";"Hydralisk";"Larva";156;2
"Unit";"Hydralisk";"Larva";158;2
"Unit";"Hydralisk";"Larva";160;2
"Unit";"Zergling";"Larva";162;1
"Unit";"Zergling";"Larva";163;1
"Building";"CreepTumor";NA;164;0
"Building";"CreepTumor";NA;164;0
"Building";"CreepTumor";NA;164;0
"Unit";"Zergling";"Larva";164;1
"Unit";"Zergling";"Larva";165;1
"Unit";"Zergling";"Larva";166;1
"Unit";"Zergling";"Larva";167;1
"Unit";"Zergling";"Larva";168;1
"Unit";"Zergling";"Larva";169;1
"Unit";"Zergling";"Larva";170;1
"Unit";"Zergling";"Larva";171;1
"Building";"CreepTumor";NA;172;0
"Building";"CreepTumor";NA;172;0
"Building";"CreepTumor";NA;172;0
"Building";"CreepTumor";NA;172;0
"Building";"CreepTumor";NA;172;0
"Building";"CreepTumor";NA;172;0
"Building";"CreepTumor";NA;172;0
"Unit";"Overlord";"Larva";172;0
"Unit";"Baneling";"Zergling";172;0
"Unit";"Baneling";"Zergling";172;0
"Unit";"Baneling";"Zergling";172;0
"Unit";"Baneling";"Zergling";172;0
"Unit";"Baneling";"Zergling";172;0
"Unit";"Baneling";"Zergling";172;0
"Unit";"Zergling";"Larva";172;1
"Unit";"Zergling";"Larva";173;1
"Unit";"Zergling";"Larva";174;1
"Unit";"Zergling";"Larva";175;1
"Unit";"Baneling";"Zergling";176;0
"Unit";"Baneling";"Zergling";176;0
"Unit";"Hydralisk";"Larva";176;2
"Unit";"Hydralisk";"Larva";178;2
"Unit";"Hydralisk";"Larva";180;2
"Unit";"Zergling";"Larva";182;1
"Unit";"Zergling";"Larva";183;1
"Unit";"Zergling";"Larva";184;1
"Unit";"Zergling";"Larva";185;1
"Unit";"Zergling";"Larva";186;1
"Unit";"Zergling";"Larva";187;1
"Unit";"Zergling";"Larva";188;1
"Unit";"Zergling";"Larva";189;1
"Unit";"Zergling";"Larva";190;1
"Unit";"Zergling";"Larva";191;1
"Unit";"Baneling";"Zergling";192;0
"Unit";"Baneling";"Zergling";192;0
"Unit";"Baneling";"Zergling";192;0
"Unit";"Baneling";"Zergling";192;0
"Unit";"Zergling";"Larva";192;1
"Unit";"Zergling";"Larva";193;1
"Unit";"Zergling";"Larva";194;1
"Unit";"Zergling";"Larva";195;1
"Unit";"Zergling";"Larva";196;1
"Unit";"Zergling";"Larva";197;1
"Building";"Hatchery";NA;198;0
"Building";"CreepTumor";NA;198;0
"Building";"CreepTumor";NA;198;0
"Building";"CreepTumor";NA;198;0
"Building";"CreepTumor";NA;198;0
"Unit";"Baneling";"Zergling";198;0
"Unit";"Baneling";"Zergling";198;0
"Unit";"Baneling";"Zergling";198;0
"Unit";"Baneling";"Zergling";198;0
"Unit";"Baneling";"Zergling";198;0
"Unit";"Zergling";"Larva";198;1
"Unit";"Zergling";"Larva";199;1
"Unit";"Zergling";"Larva";200;1
"Unit";"Zergling";"Larva";201;1
"Unit";"Zergling";"Larva";202;1
"Unit";"Zergling";"Larva";203;1
"Unit";"Overlord";"Larva";204;0
"Unit";"Baneling";"Zergling";204;0
"Unit";"Baneling";"Zergling";204;0
"Unit";"Baneling";"Zergling";204;0
"Unit";"Baneling";"Zergling";204;0
"Unit";"Baneling";"Zergling";204;0
"Unit";"Baneling";"Zergling";204;0
"Unit";"Baneling";"Zergling";204;0
"Unit";"Overlord";"Larva";204;0
"Unit";"Zergling";"Larva";204;1
"Unit";"Zergling";"Larva";205;1
"Unit";"Zergling";"Larva";206;1
"Unit";"Zergling";"Larva";207;1
"Unit";"Zergling";"Larva";208;1
"Unit";"Zergling";"Larva";209;1
"Unit";"Zergling";"Larva";210;1
"Unit";"Zergling";"Larva";211;1
"Unit";"Zergling";"Larva";212;1
"Unit";"Zergling";"Larva";213;1
"Unit";"Zergling";"Larva";214;1
"Unit";"Zergling";"Larva";215;1
"Unit";"Zergling";"Larva";216;1
"Unit";"Zergling";"Larva";217;1
"Unit";"Baneling";"Zergling";218;0
"Unit";"Baneling";"Zergling";218;0
"Unit";"Baneling";"Zergling";218;0
"Unit";"Baneling";"Zergling";218;0
"Unit";"Baneling";"Zergling";218;0
"Unit";"Baneling";"Zergling";218;0
"Unit";"Overlord";"Larva";218;0
"Unit";"Overlord";"Larva";218;0
"Building";"CreepTumorQueen";NA;218;0
"Building";"CreepTumorQueen";NA;218;0
"Building";"CreepTumorQueen";NA;218;0
"Building";"CreepTumorQueen";NA;218;0
"Unit";"Hydralisk";"Larva";218;2
"Unit";"Hydralisk";"Larva";220;2
"Unit";"Hydralisk";"Larva";222;2
"Unit";"Zergling";"Larva";224;1
"Unit";"Zergling";"Larva";225;1
"Unit";"Zergling";"Larva";226;1
"Unit";"Zergling";"Larva";227;1
"Unit";"Zergling";"Larva";228;1
"Unit";"Zergling";"Larva";229;1
"Unit";"Zergling";"Larva";230;1
"Unit";"Zergling";"Larva";231;1
"Building";"CreepTumor";NA;232;0
"Building";"CreepTumor";NA;232;0
"Building";"CreepTumor";NA;232;0
"Building";"CreepTumor";NA;232;0
"Unit";"Hydralisk";"Larva";232;2
"Unit";"Hydralisk";"Larva";234;2
"Unit";"Hydralisk";"Larva";236;2
"Unit";"Hydralisk";"Larva";238;2
"Unit";"Hydralisk";"Larva";240;2
"Unit";"Hydralisk";"Larva";242;2
"Unit";"Hydralisk";"Larva";244;2
"Unit";"Zergling";"Larva";246;1
"Unit";"Zergling";"Larva";247;1
"Unit";"Zergling";"Larva";248;1
"Unit";"Zergling";"Larva";249;1
"Unit";"Zergling";"Larva";250;1
"Unit";"Zergling";"Larva";251;1
"Unit";"Zergling";"Larva";252;1
"Unit";"Zergling";"Larva";253;1
"Unit";"Zergling";"Larva";254;1
"Unit";"Zergling";"Larva";255;1
"Unit";"Zergling";"Larva";256;1
"Unit";"Zergling";"Larva";257;1
"Unit";"Zergling";"Larva";258;1
"Unit";"Zergling";"Larva";259;1
"Building";"CreepTumor";NA;260;0
"Building";"CreepTumor";NA;260;0
"Building";"CreepTumor";NA;260;0
"Building";"CreepTumor";NA;265;0
"Building";"CreepTumor";NA;265;0
"Building";"CreepTumor";NA;265;0
"Unit";"Baneling";"Zergling";267;0
"Unit";"Baneling";"Zergling";267;0
"Unit";"Baneling";"Zergling";267;0
"Unit";"Baneling";"Zergling";267;0
"Unit";"Baneling";"Zergling";267;0
"Unit";"Baneling";"Zergling";267;0
"Unit";"Baneling";"Zergling";267;0
"Unit";"Baneling";"Zergling";267;0
"Unit";"Hydralisk";"Larva";267;2
"Unit";"Hydralisk";"Larva";269;2
"Unit";"Hydralisk";"Larva";271;2
"Unit";"Zergling";"Larva";273;1
"Unit";"Zergling";"Larva";274;1
"Unit";"Zergling";"Larva";275;1
"Unit";"Zergling";"Larva";276;1
"Unit";"Zergling";"Larva";277;1
"Unit";"Zergling";"Larva";278;1
"Unit";"Zergling";"Larva";279;1
"Unit";"Zergling";"Larva";280;1
"Unit";"Zergling";"Larva";281;1
"Unit";"Zergling";"Larva";282;1
"Unit";"Hydralisk";"Larva";283;2
"Unit";"Hydralisk";"Larva";285;2
"Unit";"Zergling";"Larva";287;1
"Unit";"Zergling";"Larva";288;1
"Unit";"Zergling";"Larva";289;1
"Unit";"Zergling";"Larva";290;1
"Unit";"Zergling";"Larva";291;1
"Unit";"Zergling";"Larva";292;1
"Unit";"Zergling";"Larva";293;1
"Unit";"Zergling";"Larva";294;1
"Unit";"Zergling";"Larva";295;1
"Unit";"Zergling";"Larva";296;1
"Unit";"Zergling";"Larva";297;1
"Unit";"Zergling";"Larva";298;1
"Unit";"Zergling";"Larva";299;1
"Unit";"Zergling";"Larva";300;1
"Unit";"Zergling";"Larva";301;1
"Unit";"Zergling";"Larva";302;1
"Unit";"Zergling";"Larva";303;1
"Unit";"Zergling";"Larva";304;1
"Unit";"Hydralisk";"Larva";305;2
"Unit";"Hydralisk";"Larva";307;2
"Unit";"Hydralisk";"Larva";309;2
"Unit";"Zergling";"Larva";311;1
"Unit";"Zergling";"Larva";312;1
"Unit";"Zergling";"Larva";313;1
"Unit";"Zergling";"Larva";314;1
"Unit";"Zergling";"Larva";315;1
"Unit";"Zergling";"Larva";316;1
"Unit";"Zergling";"Larva";317;1
"Unit";"Zergling";"Larva";318;1
"Unit";"Zergling";"Larva";319;1
"Unit";"Zergling";"Larva";320;1
"Building";"CreepTumor";NA;321;0
"Unit";"Baneling";"Zergling";321;0
"Unit";"Baneling";"Zergling";321;0
"Unit";"Baneling";"Zergling";321;0
"Unit";"Baneling";"Zergling";321;0
"Unit";"Baneling";"Zergling";321;0
"Unit";"Baneling";"Zergling";321;0
"Unit";"Baneling";"Zergling";321;0
"Unit";"Baneling";"Zergling";321;0
"Unit";"Baneling";"Zergling";321;0
"Unit";"Baneling";"Zergling";321;0
"Unit";"Baneling";"Zergling";321;0
"Unit";"Baneling";"Zergling";321;0
"Unit";"Baneling";"Zergling";321;0
"Unit";"Baneling";"Zergling";321;0
"Building";"CreepTumor";NA;321;0
"Building";"CreepTumor";NA;321;0
"Building";"CreepTumor";NA;321;0
"Unit";"Overlord";"Larva";321;0
"Unit";"Overlord";"Larva";321;0
"Building";"CreepTumor";NA;323;0
"Unit";"Hydralisk";"Larva";323;2
"Unit";"Hydralisk";"Larva";325;2
"Unit";"Zergling";"Larva";327;1
"Unit";"Zergling";"Larva";328;1
"Unit";"Zergling";"Larva";329;1
"Unit";"Zergling";"Larva";330;1
"Unit";"Zergling";"Larva";331;1
"Unit";"Zergling";"Larva";332;1
"Unit";"Zergling";"Larva";333;1
"Unit";"Zergling";"Larva";334;1
"Unit";"Zergling";"Larva";335;1
"Unit";"Zergling";"Larva";336;1
"Building";"Hatchery";NA;337;0
"Unit";"Overlord";"Larva";337;0
"Unit";"Overlord";"Larva";337;0
"Unit";"Hydralisk";"Larva";337;2
"Unit";"Hydralisk";"Larva";339;2
"Unit";"Hydralisk";"Larva";341;2
"Unit";"Zergling";"Larva";343;1
"Unit";"Zergling";"Larva";344;1
"Unit";"Zergling";"Larva";345;1
"Unit";"Zergling";"Larva";346;1
"Unit";"Hydralisk";"Larva";347;2
"Unit";"Hydralisk";"Larva";349;2
"Unit";"Hydralisk";"Larva";351;2
"Unit";"Zergling";"Larva";353;1
"Unit";"Zergling";"Larva";354;1
"Unit";"Zergling";"Larva";355;1
"Unit";"Zergling";"Larva";356;1
"Unit";"Zergling";"Larva";357;1
"Unit";"Zergling";"Larva";358;1
"Unit";"Zergling";"Larva";359;1
"Unit";"Zergling";"Larva";360;1
"Unit";"Zergling";"Larva";361;1
"Unit";"Zergling";"Larva";362;1
"Unit";"Zergling";"Larva";363;1
"Unit";"Zergling";"Larva";364;1
"Unit";"Zergling";"Larva";365;1
"Unit";"Zergling";"Larva";366;1
"Unit";"Zergling";"Larva";367;1
"Unit";"Zergling";"Larva";368;1
"Unit";"Zergling";"Larva";369;1
"Unit";"Zergling";"Larva";370;1
"Unit";"Zergling";"Larva";371;1
"Unit";"Zergling";"Larva";372;1
"Unit";"Zergling";"Larva";373;1
"Unit";"Zergling";"Larva";374;1
"Building";"CreepTumor";NA;377;0
"Building";"InfestationPit";NA;377;0
"Building";"CreepTumor";NA;377;0
"Building";"CreepTumor";NA;377;0
"Building";"CreepTumor";NA;377;0
"Building";"CreepTumor";NA;377;0
"Building";"CreepTumor";NA;377;0
"Unit";"Overlord";"Larva";377;0
"Unit";"Overlord";"Larva";377;0
"Building";"CreepTumor";NA;377;0
"Unit";"Baneling";"Zergling";377;0
"Unit";"Baneling";"Zergling";377;0
"Unit";"Baneling";"Zergling";377;0
"Unit";"Baneling";"Zergling";377;0
"Unit";"Baneling";"Zergling";377;0
"Unit";"Baneling";"Zergling";377;0
"Unit";"Baneling";"Zergling";377;0
"Unit";"Baneling";"Zergling";377;0
"Building";"CreepTumorQueen";NA;377;0
"Unit";"Zergling";"Larva";377;1
"Unit";"Zergling";"Larva";378;1
"Unit";"Zergling";"Larva";379;1
"Unit";"Zergling";"Larva";380;1
"Unit";"Zergling";"Larva";381;1
"Unit";"Zergling";"Larva";382;1
"Unit";"Zergling";"Larva";383;1
"Unit";"Zergling";"Larva";384;1
"Unit";"Baneling";"Zergling";385;0
"Unit";"Baneling";"Zergling";385;0
"Unit";"Baneling";"Zergling";385;0
"Unit";"Baneling";"Zergling";385;0
"Unit";"Baneling";"Zergling";385;0
"Unit";"Baneling";"Zergling";385;0
"Building";"CreepTumorQueen";NA;385;0
"Unit";"Baneling";"Zergling";385;0
"Unit";"Baneling";"Zergling";385;0
"Unit";"Baneling";"Zergling";385;0
"Unit";"Baneling";"Zergling";385;0
"Unit";"Baneling";"Zergling";385;0
"Unit";"Overlord";"Larva";385;0
"Unit";"Overlord";"Larva";385;0
"Unit";"Overlord";"Larva";385;0
"Unit";"Zergling";"Larva";385;1
"Unit";"Zergling";"Larva";386;1
"Unit";"Zergling";"Larva";387;1
"Unit";"Zergling";"Larva";388;1
"Unit";"Zergling";"Larva";389;1
"Unit";"Zergling";"Larva";390;1
"Unit";"Zergling";"Larva";391;1
"Unit";"Zergling";"Larva";392;1
"Unit";"Zergling";"Larva";393;1
"Unit";"Zergling";"Larva";394;1
"Unit";"Zergling";"Larva";395;1
"Unit";"Zergling";"Larva";396;1
"Unit";"Zergling";"Larva";397;1
"Unit";"Zergling";"Larva";398;1
"Unit";"Zergling";"Larva";399;1
"Unit";"Zergling";"Larva";400;1
"Unit";"Zergling";"Larva";401;1
"Unit";"Zergling";"Larva";402;1
"Unit";"Zergling";"Larva";403;1
"Unit";"Zergling";"Larva";404;1
"Unit";"Zergling";"Larva";405;1
"Unit";"Zergling";"Larva";406;1
"Unit";"Zergling";"Larva";407;1
"Unit";"Zergling";"Larva";408;1
"Unit";"Zergling";"Larva";409;1
"Unit";"Zergling";"Larva";410;1
"Unit";"Zergling";"Larva";411;1
"Unit";"Zergling";"Larva";412;1
"Unit";"Zergling";"Larva";413;1
"Unit";"Zergling";"Larva";414;1
"Unit";"Zergling";"Larva";415;1
"Unit";"Zergling";"Larva";416;1
"Unit";"Hydralisk";"Larva";417;2
"Unit";"Hydralisk";"Larva";419;2
"Unit";"Hydralisk";"Larva";421;2
"Unit";"Hydralisk";"Larva";423;2
"Unit";"Hydralisk";"Larva";425;2
"Building";"CreepTumor";NA;427;0
"Unit";"Zergling";"Larva";427;1
"Unit";"Zergling";"Larva";428;1
"Unit";"Zergling";"Larva";429;1
"Unit";"Zergling";"Larva";430;1
"Unit";"Zergling";"Larva";431;1
"Unit";"Zergling";"Larva";432;1
"Unit";"Zergling";"Larva";433;1
"Unit";"Zergling";"Larva";434;1
"Unit";"Zergling";"Larva";435;1
"Unit";"Zergling";"Larva";436;1
"Unit";"Zergling";"Larva";437;1
"Unit";"Zergling";"Larva";438;1
"Unit";"Zergling";"Larva";439;1
"Unit";"Zergling";"Larva";440;1
"Unit";"Zergling";"Larva";441;1
"Unit";"Zergling";"Larva";442;1
"Unit";"Baneling";"Zergling";443;0
"Unit";"Baneling";"Zergling";443;0
"Unit";"Baneling";"Zergling";443;0
"Unit";"Baneling";"Zergling";443;0
"Unit";"Baneling";"Zergling";443;0
"Unit";"Baneling";"Zergling";443;0
"Building";"CreepTumor";NA;443;0
"Building";"CreepTumor";NA;443;0
"Unit";"Baneling";"Zergling";443;0
"Unit";"Baneling";"Zergling";443;0
"Unit";"Baneling";"Zergling";443;0
"Unit";"Baneling";"Zergling";443;0
"Unit";"Baneling";"Zergling";443;0
"Unit";"Zergling";"Larva";443;1
"Unit";"Zergling";"Larva";444;1
"Unit";"Zergling";"Larva";445;1
"Unit";"Zergling";"Larva";446;1
"Unit";"Zergling";"Larva";447;1
"Unit";"Zergling";"Larva";448;1
"Unit";"Zergling";"Larva";449;1
"Unit";"Zergling";"Larva";450;1
"Building";"CreepTumor";NA;453;0
"Building";"CreepTumor";NA;453;0
"Building";"CreepTumor";NA;453;0
"Unit";"Baneling";"Zergling";453;0
"Unit";"Baneling";"Zergling";453;0
"Unit";"Baneling";"Zergling";453;0
"Unit";"Baneling";"Zergling";453;0
"Unit";"Baneling";"Zergling";453;0
"Unit";"Baneling";"Zergling";453;0
"Unit";"Baneling";"Zergling";453;0
"Building";"CreepTumor";NA;453;0
"Unit";"Zergling";"Larva";453;1
"Unit";"Zergling";"Larva";454;1
"Unit";"Zergling";"Larva";455;1
"Unit";"Zergling";"Larva";456;1
"Unit";"Zergling";"Larva";457;1
"Unit";"Zergling";"Larva";458;1
"Unit";"Zergling";"Larva";459;1
"Unit";"Zergling";"Larva";460;1
"Unit";"Zergling";"Larva";461;1
"Unit";"Zergling";"Larva";462;1
"Unit";"Zergling";"Larva";463;1
"Unit";"Zergling";"Larva";464;1
"Unit";"Zergling";"Larva";465;1
"Unit";"Zergling";"Larva";466;1
"Unit";"Zergling";"Larva";467;1
"Unit";"Zergling";"Larva";468;1
"Unit";"Zergling";"Larva";469;1
"Unit";"Zergling";"Larva";470;1
"Unit";"Zergling";"Larva";471;1
"Unit";"Zergling";"Larva";472;1
"Unit";"Zergling";"Larva";473;1
"Unit";"Zergling";"Larva";474;1
"Unit";"Zergling";"Larva";475;1
"Unit";"Zergling";"Larva";476;1
"Unit";"Zergling";"Larva";477;1
"Unit";"Zergling";"Larva";478;1
"Unit";"Zergling";"Larva";479;1
"Unit";"Zergling";"Larva";480;1
"Unit";"Baneling";"Zergling";481;0
"Unit";"Baneling";"Zergling";481;0
"Unit";"Baneling";"Zergling";481;0
"Unit";"Baneling";"Zergling";481;0
"Unit";"Baneling";"Zergling";481;0
"Unit";"Baneling";"Zergling";481;0
"Unit";"Zergling";"Larva";481;1
"Unit";"Zergling";"Larva";482;1
"Unit";"Zergling";"Larva";483;1
"Unit";"Zergling";"Larva";484;1
"Unit";"Zergling";"Larva";485;1
"Unit";"Zergling";"Larva";486;1
"Unit";"Zergling";"Larva";487;1
"Unit";"Zergling";"Larva";488;1
"Unit";"Zergling";"Larva";489;1
"Unit";"Zergling";"Larva";490;1
"Unit";"Zergling";"Larva";491;1
"Unit";"Zergling";"Larva";492;1
"Unit";"Zergling";"Larva";493;1
"Unit";"Zergling";"Larva";494;1
"Unit";"Zergling";"Larva";495;1
"Unit";"Zergling";"Larva";496;1
"Unit";"Baneling";"Zergling";497;0
"Unit";"Baneling";"Zergling";497;0
"Unit";"Baneling";"Zergling";497;0
"Unit";"Baneling";"Zergling";497;0
"Unit";"Baneling";"Zergling";497;0
"Unit";"Baneling";"Zergling";497;0
"Building";"CreepTumor";NA;497;0
"Building";"CreepTumor";NA;497;0
"Building";"CreepTumor";NA;497;0
"Building";"CreepTumor";NA;497;0
"Building";"CreepTumor";NA;497;0
"Building";"CreepTumor";NA;497;0
"Unit";"Zergling";"Larva";497;1
"Unit";"Zergling";"Larva";498;1
"Unit";"Zergling";"Larva";499;1
"Unit";"Zergling";"Larva";500;1
"Unit";"Zergling";"Larva";501;1
"Unit";"Zergling";"Larva";502;1
"Unit";"Zergling";"Larva";503;1
"Unit";"Zergling";"Larva";504;1
"Unit";"Zergling";"Larva";505;1
"Unit";"Zergling";"Larva";506;1
"Unit";"Zergling";"Larva";507;1
"Unit";"Zergling";"Larva";508;1
"Unit";"Zergling";"Larva";509;1
"Unit";"Zergling";"Larva";510;1
"Unit";"Zergling";"Larva";511;1
"Unit";"Zergling";"Larva";512;1
"Unit";"Zergling";"Larva";513;1
"Unit";"Zergling";"Larva";514;1
"Unit";"Zergling";"Larva";515;1
"Unit";"Zergling";"Larva";516;1
"Unit";"Zergling";"Larva";517;1
"Unit";"Zergling";"Larva";518;1
"Unit";"Zergling";"Larva";519;1
"Unit";"Zergling";"Larva";520;1
"Unit";"Zergling";"Larva";521;1
"Unit";"Zergling";"Larva";522;1
"Unit";"Zergling";"Larva";523;1
"Unit";"Zergling";"Larva";524;1
"Unit";"Zergling";"Larva";525;1
"Unit";"Zergling";"Larva";526;1
"Unit";"Zergling";"Larva";527;1
"Unit";"Zergling";"Larva";528;1
"Unit";"Hydralisk";"Larva";529;2
"Unit";"Hydralisk";"Larva";531;2
"Unit";"Zergling";"Larva";533;1
"Unit";"Zergling";"Larva";534;1
"Unit";"Zergling";"Larva";535;1
"Unit";"Zergling";"Larva";536;1
"Unit";"Zergling";"Larva";537;1
"Unit";"Zergling";"Larva";538;1
"Unit";"Zergling";"Larva";539;1
"Unit";"Zergling";"Larva";540;1
"Unit";"Zergling";"Larva";541;1
"Unit";"Zergling";"Larva";542;1
"Unit";"Zergling";"Larva";543;1
"Unit";"Zergling";"Larva";544;1
"Unit";"Zergling";"Larva";545;1
"Unit";"Zergling";"Larva";546;1
"Unit";"Zergling";"Larva";547;1
"Unit";"Zergling";"Larva";548;1
"Unit";"Zergling";"Larva";549;1
"Unit";"Zergling";"Larva";550;1
"Unit";"Zergling";"Larva";551;1
"Unit";"Zergling";"Larva";552;1
"Unit";"Zergling";"Larva";553;1
"Unit";"Zergling";"Larva";554;1
"Unit";"Zergling";"Larva";555;1
"Unit";"Zergling";"Larva";556;1
"Unit";"Zergling";"Larva";557;1
"Unit";"Zergling";"Larva";558;1
"Unit";"Zergling";"Larva";559;1
"Unit";"Zergling";"Larva";560;1
"Unit";"Zergling";"Larva";561;1
"Unit";"Zergling";"Larva";562;1
"Unit";"Zergling";"Larva";563;1
"Unit";"Zergling";"Larva";564;1
"Unit";"Zergling";"Larva";565;1
"Unit";"Zergling";"Larva";566;1
"Unit";"Hydralisk";"Larva";567;2
"Unit";"Hydralisk";"Larva";569;2
"Unit";"Hydralisk";"Larva";571;2
"Unit";"Zergling";"Larva";573;1
"Unit";"Zergling";"Larva";574;1
"Unit";"Zergling";"Larva";575;1
"Unit";"Zergling";"Larva";576;1
"Unit";"Hydralisk";"Larva";577;2
"Unit";"Hydralisk";"Larva";579;2
"Unit";"Hydralisk";"Larva";581;2
"Unit";"Hydralisk";"Larva";583;2
"Unit";"Baneling";"Zergling";585;0
"Unit";"Baneling";"Zergling";585;0
"Unit";"Baneling";"Zergling";585;0
"Unit";"Baneling";"Zergling";585;0
"Unit";"Baneling";"Zergling";585;0
"Unit";"Baneling";"Zergling";585;0
"Unit";"Baneling";"Zergling";585;0
"Unit";"Baneling";"Zergling";585;0
"Unit";"Baneling";"Zergling";585;0
"Unit";"Baneling";"Zergling";585;0
"Unit";"Baneling";"Zergling";585;0
"Unit";"Baneling";"Zergling";585;0
"Unit";"Baneling";"Zergling";585;0
"Unit";"Baneling";"Zergling";585;0
"Unit";"Baneling";"Zergling";585;0
"Unit";"Baneling";"Zergling";585;0
"Unit";"Baneling";"Zergling";585;0
"Unit";"Baneling";"Zergling";585;0
"Unit";"Hydralisk";"Larva";585;2
"Unit";"Zergling";"Larva";587;1
"Unit";"Zergling";"Larva";588;1
"Unit";"Zergling";"Larva";589;1
"Unit";"Zergling";"Larva";590;1
"Unit";"Zergling";"Larva";591;1
"Unit";"Zergling";"Larva";592;1
"Unit";"Zergling";"Larva";593;1
"Unit";"Zergling";"Larva";594;1
"Unit";"Zergling";"Larva";595;1
"Unit";"Zergling";"Larva";596;1
"Unit";"Zergling";"Larva";597;1
"Unit";"Zergling";"Larva";598;1
"Building";"CreepTumor";NA;599;0
"Unit";"Baneling";"Zergling";599;0
"Unit";"Baneling";"Zergling";599;0
"Unit";"Baneling";"Zergling";599;0
"Unit";"Baneling";"Zergling";599;0
"Unit";"Baneling";"Zergling";599;0
"Unit";"Baneling";"Zergling";599;0
"Unit";"Baneling";"Zergling";599;0
"Unit";"Baneling";"Zergling";599;0
"Unit";"Baneling";"Zergling";599;0
"Unit";"Baneling";"Zergling";599;0
"Unit";"Zergling";"Larva";599;1
"Unit";"Zergling";"Larva";600;1
"Unit";"Zergling";"Larva";601;1
"Unit";"Zergling";"Larva";602;1
"Unit";"Zergling";"Larva";603;1
"Unit";"Zergling";"Larva";604;1
"Unit";"Zergling";"Larva";605;1
"Unit";"Zergling";"Larva";606;1
"Unit";"Zergling";"Larva";607;1
"Unit";"Zergling";"Larva";608;1
"Unit";"Zergling";"Larva";609;1
"Unit";"Zergling";"Larva";610;1
"Unit";"Zergling";"Larva";611;1
"Unit";"Zergling";"Larva";612;1
"Upgrade";"SprayZerg";NA;613;0
"Upgrade";"SprayZerg";NA;613;0
"Upgrade";"SprayZerg";NA;613;0
"Upgrade";"zerglingmovementspeed";NA;613;0
"Upgrade";"SprayZerg";NA;613;0
"Upgrade";"SprayZerg";NA;613;0
"Upgrade";"EvolveMuscularAugments";NA;613;0
"Upgrade";"SprayZerg";NA;613;0
"Upgrade";"EvolveGroovedSpines";NA;613;0
"Upgrade";"ZergMissileWeaponsLevel1";NA;613;0
"Upgrade";"CentrificalHooks";NA;613;0
"Upgrade";"SprayZerg";NA;613;0
"Upgrade";"SprayZerg";NA;613;0
"Upgrade";"SprayZerg";NA;613;0
"Upgrade";"overlordspeed";NA;613;0
"Upgrade";"ZergMissileWeaponsLevel2";NA;613;0
"Upgrade";"SprayZerg";NA;613;0
