"type";"unit_name";"on_building";"total_supply";"supply"
"Unit";"Overlord";"Larva";13;0
"Building";"Extractor";NA;17;0
"Building";"SpawningPool";NA;19;0
"Building";"Hatchery";NA;17;0
"Unit";"Overlord";"Larva";22;0
"Unit";"Zergling";"Larva";23;1
"Unit";"Zergling";"Larva";23;1
"Unit";"Zergling";"Larva";23;1
"Unit";"Zergling";"Larva";23;1
"Unit";"Zergling";"Larva";23;1
"Unit";"Zergling";"Larva";23;1
"Unit";"Queen";"Hatchery";23;2
"Unit";"Queen";"Hatchery";23;2
"Unit";"Overlord";"Larva";36;0
"Unit";"Overlord";"Larva";43;0
"Unit";"Queen";"Hatchery";40;2
"Building";"CreepTumorQueen";NA;46;0
"Building";"CreepTumorQueen";NA;46;0
"Building";"SporeCrawler";NA;46;0
"Building";"SporeCrawler";NA;46;0
"Unit";"Overlord";"Larva";46;0
"Building";"CreepTumorQueen";NA;49;0
"Building";"Hatchery";NA;38;0
"Unit";"Zergling";"Larva";49;1
"Unit";"Zergling";"Larva";49;1
"Unit";"Zergling";"Larva";49;1
"Unit";"Zergling";"Larva";49;1
"Unit";"Zergling";"Larva";49;1
"Unit";"Zergling";"Larva";49;1
"Unit";"Zergling";"Larva";49;1
"Unit";"Zergling";"Larva";49;1
"Unit";"Zergling";"Larva";49;1
"Unit";"Zergling";"Larva";49;1
"Unit";"Zergling";"Larva";49;1
"Unit";"Zergling";"Larva";49;1
"Unit";"Zergling";"Larva";49;1
"Unit";"Zergling";"Larva";49;1
"Unit";"Zergling";"Larva";49;1
"Unit";"Zergling";"Larva";49;1
"Unit";"Zergling";"Larva";49;1
"Unit";"Zergling";"Larva";49;1
"Unit";"Queen";"Hatchery";49;2
"Building";"CreepTumor";NA;49;0
"Building";"CreepTumor";NA;49;0
"Building";"HydraliskDen";NA;67;0
"Building";"CreepTumor";NA;77;0
"Building";"CreepTumor";NA;77;0
"Unit";"Overlord";"Larva";69;0
"Unit";"Overlord";"Larva";69;0
"Unit";"Queen";"Hatchery";69;2
"Building";"CreepTumorQueen";NA;77;0
"Building";"BanelingNest";NA;69;0
"Building";"EvolutionChamber";NA;77;0
"Building";"EvolutionChamber";NA;77;0
"Building";"CreepTumorQueen";NA;89;0
"Building";"CreepTumor";NA;89;0
"Building";"CreepTumor";NA;91;0
"Building";"CreepTumorQueen";NA;93;0
"Building";"CreepTumor";NA;95;0
"Building";"Extractor";NA;95;0
"Building";"Extractor";NA;95;0
"Building";"SporeCrawler";NA;95;0
"Building";"CreepTumor";NA;101;0
"Upgrade";"EvolveGroovedSpines";"HydraliskDen";86;0
"Building";"CreepTumor";NA;101;0
"Building";"CreepTumor";NA;101;0
"Building";"CreepTumor";NA;101;0
"Building";"CreepTumorQueen";NA;101;0
"Building";"SpineCrawler";NA;98;0
"Unit";"Overlord";"Larva";101;0
"Unit";"Overlord";"Larva";101;0
"Unit";"Zergling";"Larva";101;1
"Unit";"Zergling";"Larva";101;1
"Unit";"Zergling";"Larva";101;1
"Unit";"Zergling";"Larva";101;1
"Unit";"Zergling";"Larva";101;1
"Unit";"Zergling";"Larva";101;1
"Unit";"Hydralisk";"Larva";101;2
"Unit";"Hydralisk";"Larva";101;2
"Unit";"Hydralisk";"Larva";101;2
"Unit";"Overlord";"Larva";101;0
"Unit";"Overlord";"Larva";101;0
"Unit";"Overlord";"Larva";101;0
"Unit";"Overlord";"Larva";101;0
"Unit";"Overlord";"Larva";101;0
"Unit";"Overlord";"Larva";101;0
"Unit";"Overlord";"Larva";101;0
"Building";"Extractor";NA;101;0
"Building";"Extractor";NA;101;0
"Building";"CreepTumor";NA;113;0
"Building";"CreepTumor";NA;113;0
"Building";"CreepTumorQueen";NA;113;0
"Building";"CreepTumor";NA;113;0
"Unit";"Hydralisk";"Larva";113;2
"Building";"CreepTumor";NA;113;0
"Building";"CreepTumor";NA;113;0
"Unit";"Hydralisk";"Larva";113;2
"Unit";"Hydralisk";"Larva";113;2
"Unit";"Hydralisk";"Larva";113;2
"Unit";"Hydralisk";"Larva";121;2
"Unit";"Hydralisk";"Larva";121;2
"Unit";"Hydralisk";"Larva";121;2
"Unit";"Hydralisk";"Larva";121;2
"Upgrade";"ZergMissileWeaponsLevel1";"EvolutionChamber";101;0
"Upgrade";"ZergGroundArmorsLevel1";"EvolutionChamber";101;0
"Unit";"Zergling";"Larva";127;1
"Unit";"Zergling";"Larva";127;1
"Unit";"Zergling";"Larva";127;1
"Unit";"Zergling";"Larva";127;1
"Building";"Extractor";NA;127;0
"Unit";"Zergling";"Larva";132;1
"Unit";"Zergling";"Larva";132;1
"Building";"CreepTumorQueen";NA;142;0
"Building";"CreepTumor";NA;142;0
"Building";"Extractor";NA;148;0
"Building";"InfestationPit";NA;142;0
"Building";"SporeCrawler";NA;148;0
"Building";"Extractor";NA;148;0
"Unit";"Overlord";"Larva";148;0
"Unit";"Overlord";"Larva";148;0
"Unit";"Hydralisk";"Larva";148;2
"Unit";"Hydralisk";"Larva";148;2
"Unit";"Hydralisk";"Larva";148;2
"Unit";"Hydralisk";"Larva";148;2
"Unit";"Hydralisk";"Larva";148;2
"Unit";"Hydralisk";"Larva";148;2
"Building";"CreepTumorQueen";NA;148;0
"Building";"CreepTumor";NA;148;0
"Building";"Hatchery";NA;121;0
"Building";"SpineCrawler";NA;148;0
"Building";"CreepTumor";NA;148;0
"Building";"CreepTumor";NA;148;0
"Building";"CreepTumor";NA;160;0
"Building";"CreepTumor";NA;160;0
"Building";"CreepTumor";NA;160;0
"Unit";"Queen";"Hatchery";148;2
"Unit";"Overlord";"Larva";160;0
"Unit";"Overlord";"Larva";160;0
"Building";"SpineCrawler";NA;148;0
"Building";"SpineCrawler";NA;148;0
"Upgrade";"EvolveMuscularAugments";"HydraliskDen";148;0
"Building";"CreepTumor";NA;180;0
"Building";"CreepTumor";NA;180;0
"Unit";"Baneling";"Zergling";180;0
"Unit";"Baneling";"Zergling";180;0
"Unit";"Baneling";"Zergling";180;0
"Building";"SpineCrawler";NA;180;0
"Unit";"Hydralisk";"Larva";180;2
"Unit";"Hydralisk";"Larva";180;2
"Unit";"Hydralisk";"Larva";180;2
"Unit";"Hydralisk";"Larva";180;2
"Unit";"Hydralisk";"Larva";180;2
"Unit";"Hydralisk";"Larva";180;2
"Unit";"Hydralisk";"Larva";180;2
"Unit";"Hydralisk";"Larva";180;2
"Unit";"Hydralisk";"Larva";180;2
"Unit";"Hydralisk";"Larva";180;2
"Building";"SpineCrawler";NA;180;0
"Building";"SpineCrawler";NA;180;0
"Building";"CreepTumor";NA;180;0
"Unit";"Hydralisk";"Larva";180;2
"Unit";"Hydralisk";"Larva";180;2
"Unit";"Hydralisk";"Larva";180;2
"Unit";"Hydralisk";"Larva";180;2
"Building";"CreepTumor";NA;200;0
"Unit";"Zergling";"Larva";200;1
"Unit";"Zergling";"Larva";200;1
"Unit";"Zergling";"Larva";200;1
"Unit";"Zergling";"Larva";200;1
"Unit";"Zergling";"Larva";200;1
"Unit";"Zergling";"Larva";200;1
"Unit";"Zergling";"Larva";200;1
"Unit";"Zergling";"Larva";200;1
"Building";"CreepTumor";NA;200;0
"Unit";"Zergling";"Larva";208;1
"Unit";"Zergling";"Larva";208;1
"Unit";"Zergling";"Larva";208;1
"Unit";"Zergling";"Larva";208;1
"Unit";"Hydralisk";"Larva";200;2
"Unit";"Hydralisk";"Larva";200;2
"Unit";"Zergling";"Larva";208;1
"Unit";"Zergling";"Larva";208;1
"Unit";"Zergling";"Larva";208;1
"Unit";"Zergling";"Larva";208;1
"Unit";"Zergling";"Larva";208;1
"Unit";"Zergling";"Larva";208;1
"Unit";"Zergling";"Larva";208;1
"Unit";"Zergling";"Larva";208;1
"Unit";"Overlord";"Larva";208;0
"Unit";"Overlord";"Larva";208;0
"Unit";"Overlord";"Larva";208;0
"Unit";"Baneling";"Zergling";216;0
"Unit";"Baneling";"Zergling";216;0
"Unit";"Baneling";"Zergling";216;0
"Unit";"Baneling";"Zergling";216;0
"Unit";"Baneling";"Zergling";216;0
"Unit";"Baneling";"Zergling";216;0
"Unit";"Hydralisk";"Larva";208;2
"Unit";"Hydralisk";"Larva";232;2
"Unit";"Hydralisk";"Larva";232;2
"Unit";"Hydralisk";"Larva";232;2
"Unit";"Hydralisk";"Larva";232;2
"Unit";"Hydralisk";"Larva";232;2
"Unit";"Hydralisk";"Larva";232;2
"Unit";"Hydralisk";"Larva";232;2
"Unit";"Hydralisk";"Larva";232;2
"Unit";"Hydralisk";"Larva";234;2
"Unit";"Hydralisk";"Larva";234;2
"Unit";"Hydralisk";"Larva";234;2
"Unit";"Hydralisk";"Larva";234;2
"Unit";"Hydralisk";"Larva";234;2
"Unit";"Hydralisk";"Larva";234;2
"Unit";"Hydralisk";"Larva";234;2
"Unit";"Hydralisk";"Larva";236;2
"Unit";"Hydralisk";"Larva";236;2
"Building";"CreepTumor";NA;275;0
"Building";"CreepTumor";NA;282;0
"Building";"CreepTumor";NA;282;0
"Upgrade";"ZergMissileWeaponsLevel2";"EvolutionChamber";216;0
"Upgrade";"ZergGroundArmorsLevel2";"EvolutionChamber";216;0
"Building";"CreepTumorQueen";NA;282;0
"Unit";"Hydralisk";"Larva";282;2
"Unit";"Hydralisk";"Larva";282;2
"Unit";"Hydralisk";"Larva";282;2
"Unit";"Hydralisk";"Larva";282;2
"Unit";"Hydralisk";"Larva";282;2
"Unit";"Hydralisk";"Larva";282;2
"Unit";"Hydralisk";"Larva";282;2
"Unit";"Hydralisk";"Larva";282;2
"Unit";"Hydralisk";"Larva";282;2
"Unit";"Hydralisk";"Larva";282;2
"Unit";"Hydralisk";"Larva";282;2
"Unit";"Hydralisk";"Larva";282;2
"Building";"CreepTumor";NA;282;0
"Building";"CreepTumor";NA;282;0
"Building";"CreepTumor";NA;302;0
"Building";"CreepTumor";NA;306;0
"Building";"CreepTumor";NA;306;0
"Building";"CreepTumor";NA;306;0
"Building";"SpineCrawler";NA;282;0
"Unit";"Queen";"Hatchery";282;2
"Building";"SpineCrawler";NA;282;0
"Unit";"Queen";"Hatchery";282;2
"Unit";"Hydralisk";"Larva";306;2
"Unit";"Hydralisk";"Larva";306;2
"Unit";"Hydralisk";"Larva";306;2
"Unit";"Hydralisk";"Larva";306;2
"Unit";"Hydralisk";"Larva";306;2
"Building";"Extractor";NA;306;0
"Unit";"Hydralisk";"Larva";306;2
"Building";"CreepTumor";NA;310;0
"Building";"CreepTumor";NA;312;0
"Building";"CreepTumor";NA;312;0
"Building";"CreepTumor";NA;320;0
"Building";"CreepTumor";NA;322;0
"Building";"CreepTumor";NA;322;0
"Unit";"Zergling";"Larva";322;1
"Unit";"Zergling";"Larva";322;1
"Unit";"Zergling";"Larva";322;1
"Unit";"Zergling";"Larva";322;1
"Unit";"Overlord";"Larva";322;0
"Unit";"Overlord";"Larva";322;0
"Unit";"Hydralisk";"Larva";322;2
"Unit";"Hydralisk";"Larva";322;2
"Unit";"Hydralisk";"Larva";322;2
"Unit";"Hydralisk";"Larva";322;2
"Unit";"Hydralisk";"Larva";322;2
"Building";"SpineCrawler";NA;322;0
"Building";"Hatchery";NA;322;0
"Building";"CreepTumor";NA;336;0
"Building";"CreepTumor";NA;336;0
"Building";"SporeCrawler";NA;336;0
"Building";"CreepTumor";NA;336;0
"Building";"CreepTumor";NA;336;0
"Unit";"Zergling";"Larva";336;1
"Unit";"Zergling";"Larva";336;1
"Unit";"Zergling";"Larva";336;1
"Unit";"Zergling";"Larva";336;1
"Unit";"Zergling";"Larva";336;1
"Unit";"Zergling";"Larva";336;1
"Unit";"Zergling";"Larva";336;1
"Unit";"Zergling";"Larva";336;1
"Unit";"Zergling";"Larva";336;1
"Unit";"Zergling";"Larva";336;1
"Unit";"Zergling";"Larva";336;1
"Unit";"Zergling";"Larva";336;1
"Unit";"Zergling";"Larva";336;1
"Unit";"Zergling";"Larva";336;1
"Unit";"Overlord";"Larva";336;0
"Unit";"Overlord";"Larva";336;0
"Building";"Spire";NA;336;0
"Unit";"Baneling";"Zergling";352;0
"Unit";"Baneling";"Zergling";352;0
"Unit";"Baneling";"Zergling";352;0
"Unit";"Baneling";"Zergling";352;0
"Unit";"Baneling";"Zergling";352;0
"Unit";"Baneling";"Zergling";352;0
"Unit";"Baneling";"Zergling";352;0
"Unit";"Baneling";"Zergling";352;0
"Unit";"Baneling";"Zergling";352;0
"Unit";"Baneling";"Zergling";352;0
"Unit";"Baneling";"Zergling";352;0
"Unit";"Baneling";"Zergling";352;0
"Unit";"Baneling";"Zergling";352;0
"Unit";"Baneling";"Zergling";352;0
"Unit";"Baneling";"Zergling";352;0
"Unit";"Baneling";"Zergling";352;0
"Unit";"Baneling";"Zergling";352;0
"Unit";"Baneling";"Zergling";352;0
"Unit";"Hydralisk";"Larva";352;2
"Unit";"Hydralisk";"Larva";352;2
"Unit";"Hydralisk";"Larva";352;2
"Unit";"Corruptor";"Larva";352;2
"Unit";"Corruptor";"Larva";352;2
"Unit";"Corruptor";"Larva";352;2
"Unit";"Corruptor";"Larva";352;2
"Unit";"Corruptor";"Larva";352;2
"Unit";"Corruptor";"Larva";352;2
"Unit";"Corruptor";"Larva";352;2
"Unit";"Corruptor";"Larva";352;2
"Unit";"Corruptor";"Larva";352;2
"Unit";"Corruptor";"Larva";352;2
"Unit";"Corruptor";"Larva";352;2
"Unit";"Corruptor";"Larva";352;2
"Unit";"Corruptor";"Larva";352;2
"Unit";"Corruptor";"Larva";352;2
"Unit";"Corruptor";"Larva";352;2
"Unit";"Corruptor";"Larva";352;2
"Unit";"Corruptor";"Larva";352;2
"Unit";"Zergling";"Larva";392;1
"Unit";"Zergling";"Larva";392;1
"Unit";"Zergling";"Larva";392;1
"Unit";"Zergling";"Larva";392;1
"Unit";"Zergling";"Larva";392;1
"Unit";"Zergling";"Larva";392;1
"Unit";"Zergling";"Larva";392;1
"Unit";"Zergling";"Larva";392;1
"Unit";"Hydralisk";"Larva";392;2
"Unit";"Hydralisk";"Larva";392;2
"Unit";"Hydralisk";"Larva";392;2
"Unit";"Hydralisk";"Larva";392;2
"Unit";"Hydralisk";"Larva";392;2
"Unit";"Hydralisk";"Larva";392;2
"Unit";"Hydralisk";"Larva";392;2
"Unit";"Hydralisk";"Larva";392;2
"Unit";"Hydralisk";"Larva";392;2
"Unit";"Queen";"Hatchery";392;2
"Unit";"Baneling";"Zergling";418;0
"Unit";"Baneling";"Zergling";418;0
"Unit";"Baneling";"Zergling";418;0
"Unit";"Baneling";"Zergling";418;0
"Unit";"Baneling";"Zergling";418;0
"Unit";"Baneling";"Zergling";418;0
"Unit";"Baneling";"Zergling";418;0
"Unit";"Baneling";"Zergling";418;0
"Unit";"Zergling";"Larva";418;1
"Unit";"Zergling";"Larva";418;1
"Unit";"Zergling";"Larva";418;1
"Unit";"Zergling";"Larva";418;1
"Unit";"Zergling";"Larva";418;1
"Unit";"Zergling";"Larva";418;1
"Unit";"Zergling";"Larva";418;1
"Unit";"Zergling";"Larva";418;1
"Building";"CreepTumor";NA;428;0
"Building";"CreepTumor";NA;428;0
"Building";"CreepTumor";NA;428;0
"Building";"Extractor";NA;439;0
"Building";"Extractor";NA;439;0
"Unit";"Hydralisk";"Larva";439;2
"Unit";"Hydralisk";"Larva";439;2
"Unit";"Hydralisk";"Larva";439;2
"Unit";"Hydralisk";"Larva";439;2
"Unit";"Hydralisk";"Larva";439;2
"Unit";"Hydralisk";"Larva";439;2
"Unit";"Hydralisk";"Larva";439;2
"Building";"SporeCrawler";NA;439;0
"Building";"CreepTumorQueen";NA;453;0
"Building";"CreepTumorQueen";NA;453;0
"Building";"CreepTumorQueen";NA;453;0
"Building";"SporeCrawler";NA;453;0
"Unit";"Queen";"Hatchery";453;2
"Building";"SpineCrawler";NA;453;0
"Building";"CreepTumor";NA;453;0
"Building";"SpineCrawler";NA;453;0
"Unit";"Zergling";"Larva";453;1
"Unit";"Zergling";"Larva";453;1
"Unit";"Zergling";"Larva";453;1
"Unit";"Zergling";"Larva";453;1
"Unit";"Zergling";"Larva";453;1
"Unit";"Zergling";"Larva";453;1
"Unit";"Zergling";"Larva";453;1
"Unit";"Zergling";"Larva";453;1
"Unit";"Zergling";"Larva";453;1
"Unit";"Zergling";"Larva";453;1
"Unit";"Zergling";"Larva";453;1
"Unit";"Zergling";"Larva";453;1
"Unit";"Zergling";"Larva";453;1
"Unit";"Zergling";"Larva";453;1
"Unit";"Zergling";"Larva";453;1
"Unit";"Zergling";"Larva";453;1
"Unit";"Zergling";"Larva";453;1
"Unit";"Zergling";"Larva";453;1
"Unit";"Zergling";"Larva";453;1
"Unit";"Zergling";"Larva";453;1
"Unit";"Hydralisk";"Larva";453;2
"Unit";"Hydralisk";"Larva";453;2
"Unit";"Hydralisk";"Larva";453;2
"Building";"Hatchery";NA;453;0
"Building";"CreepTumor";NA;481;0
"Building";"CreepTumor";NA;481;0
"Building";"CreepTumor";NA;481;0
"Building";"CreepTumor";NA;481;0
"Building";"CreepTumor";NA;481;0
"Upgrade";"ZergMissileWeaponsLevel3";"EvolutionChamber";481;0
"Upgrade";"ZergGroundArmorsLevel3";"EvolutionChamber";481;0
