"type";"unit_name";"on_building";"total_supply";"supply"
"Unit";"Overlord";"Larva";13;0
"Building";"Extractor";NA;16;0
"Unit";"Overlord";"Larva";21;0
"Building";"Hatchery";NA;16;0
"Building";"SpawningPool";NA;19;0
"Unit";"Zergling";"Larva";22;1
"Unit";"Zergling";"Larva";22;1
"Unit";"Zergling";"Larva";22;1
"Unit";"Zergling";"Larva";22;1
"Unit";"Queen";"Hatchery";22;2
"Unit";"Queen";"Hatchery";22;2
"Building";"CreepTumorQueen";NA;36;0
"Unit";"Overlord";"Larva";36;0
"Unit";"Overlord";"Larva";39;0
"Building";"CreepTumor";NA;40;0
"Building";"CreepTumorQueen";NA;40;0
"Unit";"Queen";"Hatchery";40;2
"Building";"Hatchery";NA;34;0
"Unit";"Overlord";"Larva";48;0
"Building";"Extractor";NA;48;0
"Building";"CreepTumor";NA;50;0
"Building";"CreepTumor";NA;50;0
"Building";"CreepTumorQueen";NA;50;0
"Unit";"Overlord";"Larva";50;0
"Building";"RoachWarren";NA;50;0
"Unit";"Zergling";"Larva";50;1
"Unit";"Zergling";"Larva";50;1
"Unit";"Zergling";"Larva";50;1
"Unit";"Zergling";"Larva";50;1
"Unit";"Zergling";"Larva";50;1
"Unit";"Zergling";"Larva";50;1
"Unit";"Zergling";"Larva";50;1
"Unit";"Zergling";"Larva";50;1
"Unit";"Zergling";"Larva";51;1
"Unit";"Zergling";"Larva";51;1
"Unit";"Queen";"Hatchery";50;2
"Building";"CreepTumorQueen";NA;66;0
"Building";"CreepTumor";NA;68;0
"Building";"CreepTumor";NA;68;0
"Unit";"Roach";"Larva";56;2
"Unit";"Overlord";"Larva";56;0
"Building";"CreepTumor";NA;68;0
"Unit";"Roach";"Larva";70;2
"Unit";"Roach";"Larva";70;2
"Unit";"Roach";"Larva";70;2
"Unit";"Roach";"Larva";70;2
"Building";"CreepTumor";NA;70;0
"Unit";"Overlord";"Larva";70;0
"Unit";"Overlord";"Larva";70;0
"Unit";"Overlord";"Larva";70;0
"Building";"CreepTumor";NA;70;0
"Unit";"Roach";"Larva";78;2
"Unit";"Roach";"Larva";78;2
"Unit";"Roach";"Larva";78;2
"Unit";"Roach";"Larva";78;2
"Building";"Extractor";NA;78;0
"Building";"CreepTumor";NA;78;0
"Unit";"Queen";"Hatchery";78;2
"Building";"CreepTumor";NA;81;0
"Building";"Extractor";NA;78;0
"Building";"CreepTumor";NA;98;0
"Building";"Extractor";NA;100;0
"Unit";"Overlord";"Larva";100;0
"Unit";"Overlord";"Larva";100;0
"Unit";"Overlord";"Larva";100;0
"Building";"Extractor";NA;100;0
"Building";"CreepTumorQueen";NA;107;0
"Building";"HydraliskDen";NA;100;0
"Building";"EvolutionChamber";NA;107;0
"Building";"CreepTumor";NA;117;0
"Unit";"Overlord";"Larva";121;0
"Unit";"Overlord";"Larva";121;0
"Unit";"Overlord";"Larva";121;0
"Unit";"Hydralisk";"Larva";121;2
"Unit";"Hydralisk";"Larva";121;2
"Unit";"Hydralisk";"Larva";121;2
"Unit";"Hydralisk";"Larva";121;2
"Unit";"Overlord";"Larva";127;0
"Unit";"Overlord";"Larva";127;0
"Unit";"Overlord";"Larva";127;0
"Unit";"Overlord";"Larva";127;0
"Building";"CreepTumorQueen";NA;127;0
"Building";"CreepTumorQueen";NA;127;0
"Upgrade";"GlialReconstitution";"RoachWarren";113;0
"Upgrade";"EvolveGroovedSpines";"HydraliskDen";121;0
"Building";"CreepTumor";NA;135;0
"Unit";"Hydralisk";"Larva";127;2
"Unit";"Hydralisk";"Larva";127;2
"Unit";"Hydralisk";"Larva";127;2
"Unit";"Hydralisk";"Larva";129;2
"Unit";"Hydralisk";"Larva";131;2
"Unit";"Hydralisk";"Larva";133;2
"Unit";"Hydralisk";"Larva";135;2
"Building";"CreepTumor";NA;135;0
"Building";"CreepTumor";NA;135;0
"Building";"LurkerDenMP";NA;113;0
"Building";"CreepTumor";NA;149;0
"Unit";"Hydralisk";"Larva";135;2
"Unit";"Hydralisk";"Larva";135;2
"Unit";"Hydralisk";"Larva";135;2
"Building";"CreepTumor";NA;149;0
"Unit";"Hydralisk";"Larva";135;2
"Unit";"Hydralisk";"Larva";135;2
"Unit";"Hydralisk";"Larva";135;2
"Unit";"Hydralisk";"Larva";135;2
"Building";"Hatchery";NA;121;0
"Building";"CreepTumor";NA;149;0
"Unit";"Zergling";"Larva";149;1
"Unit";"Zergling";"Larva";149;1
"Unit";"Zergling";"Larva";149;1
"Unit";"Zergling";"Larva";149;1
"Unit";"Zergling";"Larva";149;1
"Unit";"Zergling";"Larva";149;1
"Unit";"Zergling";"Larva";149;1
"Unit";"Zergling";"Larva";149;1
"Unit";"Zergling";"Larva";149;1
"Unit";"Zergling";"Larva";149;1
"Unit";"Zergling";"Larva";149;1
"Unit";"Zergling";"Larva";149;1
"Unit";"Zergling";"Larva";149;1
"Unit";"Zergling";"Larva";149;1
"Building";"Extractor";NA;177;0
"Building";"Extractor";NA;177;0
"Upgrade";"ZergMissileWeaponsLevel1";"EvolutionChamber";135;0
"Building";"SporeCrawler";NA;183;0
"Building";"CreepTumor";NA;183;0
"Upgrade";"EvolveMuscularAugments";"HydraliskDen";149;0
"Unit";"Overlord";"Larva";183;0
"Unit";"Overlord";"Larva";183;0
"Unit";"Overlord";"Larva";183;0
"Unit";"Hydralisk";"Larva";183;2
"Unit";"Hydralisk";"Larva";183;2
"Unit";"Hydralisk";"Larva";183;2
"Building";"CreepTumor";NA;189;0
"Building";"CreepTumor";NA;189;0
"Building";"CreepTumor";NA;189;0
"Building";"CreepTumor";NA;189;0
"Unit";"Hydralisk";"Larva";189;2
"Unit";"Hydralisk";"Larva";189;2
"Unit";"Hydralisk";"Larva";189;2
"Unit";"Hydralisk";"Larva";189;2
"Unit";"Hydralisk";"Larva";189;2
"Unit";"Hydralisk";"Larva";189;2
"Unit";"Hydralisk";"Larva";189;2
"Unit";"Hydralisk";"Larva";189;2
"Unit";"Hydralisk";"Larva";189;2
"Unit";"Hydralisk";"Larva";189;2
"Unit";"Hydralisk";"Larva";189;2
"Unit";"Hydralisk";"Larva";189;2
"Unit";"Hydralisk";"Larva";189;2
"Unit";"Hydralisk";"Larva";189;2
"Unit";"Hydralisk";"Larva";189;2
"Unit";"Hydralisk";"Larva";189;2
"Unit";"Roach";"Larva";213;2
"Unit";"Roach";"Larva";213;2
"Unit";"Roach";"Larva";213;2
"Building";"InfestationPit";NA;189;0
"Unit";"Hydralisk";"Larva";213;2
"Building";"CreepTumor";NA;229;0
"Building";"CreepTumor";NA;229;0
"Building";"Hatchery";NA;213;0
"Unit";"Hydralisk";"Larva";229;2
"Unit";"Hydralisk";"Larva";229;2
"Unit";"Hydralisk";"Larva";229;2
"Unit";"Hydralisk";"Larva";229;2
"Unit";"Hydralisk";"Larva";229;2
"Unit";"Hydralisk";"Larva";229;2
"Unit";"Hydralisk";"Larva";229;2
"Unit";"Hydralisk";"Larva";229;2
"Unit";"Hydralisk";"Larva";229;2
"Unit";"Hydralisk";"Larva";229;2
"Unit";"Hydralisk";"Larva";229;2
"Unit";"Roach";"Larva";229;2
"Unit";"Roach";"Larva";229;2
"Unit";"Roach";"Larva";229;2
"Unit";"Overlord";"Larva";229;0
"Unit";"Overlord";"Larva";229;0
"Building";"Spire";NA;229;0
"Unit";"Overlord";"Larva";257;0
"Unit";"Overlord";"Larva";257;0
"Unit";"Queen";"Hatchery";257;2
"Building";"Extractor";NA;257;0
"Building";"Extractor";NA;257;0
"Unit";"Corruptor";"Larva";257;2
"Unit";"Corruptor";"Larva";257;2
"Unit";"Corruptor";"Larva";257;2
"Unit";"Corruptor";"Larva";257;2
"Unit";"Corruptor";"Larva";257;2
"Unit";"Corruptor";"Larva";257;2
"Unit";"Corruptor";"Larva";257;2
"Unit";"Corruptor";"Larva";257;2
"Building";"CreepTumor";NA;259;0
"Building";"CreepTumor";NA;259;0
"Building";"CreepTumor";NA;259;0
"Unit";"Hydralisk";"Larva";259;2
"Unit";"Hydralisk";"Larva";259;2
"Unit";"Hydralisk";"Larva";259;2
"Unit";"Hydralisk";"Larva";259;2
"Unit";"Hydralisk";"Larva";259;2
"Unit";"Hydralisk";"Larva";259;2
"Building";"SpineCrawler";NA;275;0
"Building";"SpineCrawler";NA;275;0
"Building";"SpineCrawler";NA;275;0
"Building";"SpineCrawler";NA;275;0
"Building";"SpineCrawler";NA;275;0
"Building";"SporeCrawler";NA;287;0
"Unit";"Zergling";"Larva";287;1
"Unit";"Zergling";"Larva";287;1
"Unit";"Zergling";"Larva";287;1
"Unit";"Zergling";"Larva";287;1
"Unit";"Zergling";"Larva";287;1
"Unit";"Zergling";"Larva";287;1
"Unit";"Zergling";"Larva";287;1
"Unit";"Zergling";"Larva";287;1
"Unit";"Zergling";"Larva";287;1
"Unit";"Zergling";"Larva";287;1
"Unit";"Zergling";"Larva";287;1
"Unit";"Zergling";"Larva";287;1
"Unit";"Zergling";"Larva";287;1
"Unit";"Zergling";"Larva";287;1
"Unit";"Zergling";"Larva";287;1
"Unit";"Zergling";"Larva";287;1
"Unit";"Zergling";"Larva";287;1
"Unit";"Zergling";"Larva";287;1
"Unit";"Zergling";"Larva";287;1
"Unit";"Zergling";"Larva";287;1
"Unit";"Zergling";"Larva";287;1
"Unit";"Zergling";"Larva";287;1
"Unit";"Zergling";"Larva";287;1
"Unit";"Zergling";"Larva";287;1
"Unit";"Zergling";"Larva";287;1
"Unit";"Zergling";"Larva";287;1
"Unit";"Zergling";"Larva";287;1
"Unit";"Zergling";"Larva";287;1
"Building";"CreepTumor";NA;301;0
"Building";"CreepTumor";NA;299;0
"Upgrade";"NeuralParasite";"InfestationPit";299;0
"Building";"CreepTumor";NA;333;0
"Building";"CreepTumor";NA;333;0
"Building";"CreepTumor";NA;336;0
"Building";"CreepTumor";NA;339;0
"Unit";"Infestor";"Larva";339;2
"Unit";"Infestor";"Larva";339;2
"Unit";"Infestor";"Larva";339;2
"Unit";"Infestor";"Larva";339;2
"Unit";"Infestor";"Larva";339;2
"Unit";"Infestor";"Larva";339;2
"Unit";"Hydralisk";"Larva";339;2
"Unit";"Hydralisk";"Larva";339;2
"Unit";"Hydralisk";"Larva";339;2
"Unit";"Hydralisk";"Larva";339;2
"Unit";"Hydralisk";"Larva";339;2
"Unit";"Hydralisk";"Larva";339;2
"Unit";"Hydralisk";"Larva";339;2
"Unit";"Hydralisk";"Larva";339;2
"Unit";"Hydralisk";"Larva";339;2
"Unit";"Hydralisk";"Larva";339;2
"Unit";"Hydralisk";"Larva";339;2
"Unit";"Hydralisk";"Larva";339;2
"Unit";"Hydralisk";"Larva";339;2
"Unit";"Hydralisk";"Larva";339;2
"Unit";"Hydralisk";"Larva";341;2
"Unit";"Hydralisk";"Larva";343;2
"Unit";"Hydralisk";"Larva";345;2
"Unit";"Hydralisk";"Larva";347;2
"Unit";"Hydralisk";"Larva";349;2
"Unit";"Hydralisk";"Larva";351;2
"Building";"SpineCrawler";NA;339;0
"Building";"SpineCrawler";NA;339;0
"Building";"SpineCrawler";NA;339;0
"Building";"SpineCrawler";NA;339;0
"Building";"SpineCrawler";NA;339;0
"Building";"SpineCrawler";NA;339;0
"Building";"SpineCrawler";NA;339;0
"Building";"EvolutionChamber";NA;351;0
"Unit";"Hydralisk";"Larva";391;2
"Unit";"Hydralisk";"Larva";391;2
"Unit";"Hydralisk";"Larva";391;2
"Unit";"Hydralisk";"Larva";391;2
"Unit";"Hydralisk";"Larva";391;2
"Unit";"Hydralisk";"Larva";391;2
"Unit";"Corruptor";"Larva";391;2
"Unit";"Viper";"Larva";391;3
"Unit";"Viper";"Larva";391;3
"Unit";"Viper";"Larva";391;3
"Unit";"Hydralisk";"Larva";391;2
"Unit";"Hydralisk";"Larva";391;2
"Unit";"Hydralisk";"Larva";391;2
"Unit";"Hydralisk";"Larva";391;2
"Unit";"Hydralisk";"Larva";391;2
"Unit";"Hydralisk";"Larva";391;2
"Unit";"Hydralisk";"Larva";391;2
"Unit";"Hydralisk";"Larva";391;2
"Unit";"Hydralisk";"Larva";391;2
"Unit";"Hydralisk";"Larva";424;2
"Unit";"Hydralisk";"Larva";424;2
"Unit";"Hydralisk";"Larva";428;2
"Unit";"Hydralisk";"Larva";430;2
"Unit";"Hydralisk";"Larva";432;2
"Unit";"Hydralisk";"Larva";432;2
"Unit";"Hydralisk";"Larva";432;2
"Unit";"Hydralisk";"Larva";432;2
"Unit";"Hydralisk";"Larva";432;2
"Unit";"Hydralisk";"Larva";432;2
"Unit";"Hydralisk";"Larva";432;2
"Unit";"Hydralisk";"Larva";432;2
"Unit";"Hydralisk";"Larva";432;2
"Unit";"Hydralisk";"Larva";432;2
"Unit";"Hydralisk";"Larva";432;2
"Unit";"Infestor";"Larva";408;2
"Unit";"Infestor";"Larva";411;2
"Unit";"Infestor";"Larva";414;2
"Unit";"Infestor";"Larva";414;2
"Unit";"Corruptor";"Larva";432;2
"Upgrade";"ZergMissileWeaponsLevel2";"EvolutionChamber";391;0
"Building";"CreepTumor";NA;477;0
"Building";"CreepTumor";NA;477;0
"Building";"CreepTumor";NA;477;0
"Unit";"Hydralisk";"Larva";477;2
"Unit";"Hydralisk";"Larva";477;2
"Unit";"Hydralisk";"Larva";477;2
"Unit";"Hydralisk";"Larva";477;2
"Unit";"Hydralisk";"Larva";477;2
"Unit";"Hydralisk";"Larva";477;2
"Unit";"Hydralisk";"Larva";477;2
"Unit";"Hydralisk";"Larva";477;2
"Unit";"Hydralisk";"Larva";477;2
"Building";"CreepTumor";NA;477;0
"Unit";"Overlord";"Larva";477;0
"Unit";"Overlord";"Larva";477;0
"Unit";"Corruptor";"Larva";495;2
"Unit";"Corruptor";"Larva";495;2
"Unit";"Corruptor";"Larva";495;2
"Unit";"Corruptor";"Larva";495;2
"Unit";"Corruptor";"Larva";495;2
"Unit";"Corruptor";"Larva";495;2
"Unit";"Corruptor";"Larva";495;2
"Unit";"Corruptor";"Larva";495;2
"Building";"CreepTumor";NA;511;0
"Building";"Hatchery";NA;495;0
"Building";"CreepTumor";NA;511;0
"Building";"CreepTumor";NA;511;0
"Unit";"Overlord";"Larva";511;0
"Unit";"Overlord";"Larva";511;0
"Building";"Hatchery";NA;511;0
