"type";"unit_name";"on_building";"total_supply";"supply"
"Unit";"Overlord";"Larva";13;0
"Building";"Extractor";NA;18;0
"Building";"SpawningPool";NA;19;0
"Building";"Hatchery";NA;16;0
"Unit";"Overlord";"Larva";27;0
"Unit";"Queen";"Hatchery";24;2
"Unit";"Zergling";"Larva";27;1
"Unit";"Zergling";"Larva";27;1
"Unit";"Zergling";"Larva";27;1
"Unit";"Zergling";"Larva";27;1
"Building";"Hatchery";NA;22;0
"Unit";"Overlord";"Larva";34;0
"Unit";"Zergling";"Larva";37;1
"Unit";"Zergling";"Larva";37;1
"Unit";"Queen";"Hatchery";27;2
"Unit";"Zergling";"Larva";37;1
"Unit";"Zergling";"Larva";37;1
"Unit";"Zergling";"Larva";37;1
"Unit";"Zergling";"Larva";37;1
"Building";"CreepTumorQueen";NA;37;0
"Unit";"Zergling";"Larva";41;1
"Unit";"Zergling";"Larva";41;1
"Unit";"Zergling";"Larva";41;1
"Unit";"Zergling";"Larva";41;1
"Building";"BanelingNest";NA;37;0
"Unit";"Zergling";"Larva";45;1
"Unit";"Zergling";"Larva";45;1
"Unit";"Zergling";"Larva";45;1
"Unit";"Zergling";"Larva";45;1
"Unit";"Zergling";"Larva";45;1
"Unit";"Zergling";"Larva";45;1
"Unit";"Baneling";"Zergling";61;0
"Unit";"Baneling";"Zergling";61;0
"Unit";"Baneling";"Zergling";61;0
"Unit";"Baneling";"Zergling";61;0
"Unit";"Baneling";"Zergling";61;0
"Building";"CreepTumor";NA;61;0
"Building";"CreepTumorQueen";NA;61;0
"Unit";"Queen";"Hatchery";50;2
"Building";"SporeCrawler";NA;61;0
"Unit";"Queen";"Hatchery";54;2
"Building";"SporeCrawler";NA;61;0
"Unit";"Overlord";"Larva";61;0
"Unit";"Overlord";"Larva";67;0
"Building";"CreepTumor";NA;67;0
"Building";"EvolutionChamber";NA;67;0
"Building";"CreepTumor";NA;76;0
"Building";"CreepTumorQueen";NA;76;0
"Building";"Extractor";NA;76;0
"Building";"Extractor";NA;76;0
"Building";"SporeCrawler";NA;78;0
"Unit";"Overlord";"Larva";88;0
"Unit";"Overlord";"Larva";88;0
"Unit";"Zergling";"Larva";88;1
"Unit";"Zergling";"Larva";88;1
"Unit";"Zergling";"Larva";88;1
"Unit";"Zergling";"Larva";88;1
"Unit";"Zergling";"Larva";88;1
"Unit";"Zergling";"Larva";88;1
"Unit";"Zergling";"Larva";88;1
"Unit";"Zergling";"Larva";88;1
"Unit";"Overlord";"Larva";88;0
"Unit";"Overlord";"Larva";88;0
"Unit";"Overlord";"Larva";88;0
"Building";"CreepTumor";NA;88;0
"Building";"CreepTumor";NA;88;0
"Unit";"Zergling";"Larva";88;1
"Unit";"Zergling";"Larva";88;1
"Unit";"Zergling";"Larva";88;1
"Unit";"Zergling";"Larva";88;1
"Unit";"Zergling";"Larva";88;1
"Unit";"Zergling";"Larva";88;1
"Building";"CreepTumor";NA;96;0
"Unit";"Zergling";"Larva";102;1
"Unit";"Zergling";"Larva";102;1
"Unit";"Zergling";"Larva";102;1
"Unit";"Zergling";"Larva";102;1
"Unit";"Zergling";"Larva";102;1
"Unit";"Zergling";"Larva";102;1
"Unit";"Zergling";"Larva";102;1
"Unit";"Zergling";"Larva";102;1
"Unit";"Zergling";"Larva";102;1
"Unit";"Zergling";"Larva";102;1
"Building";"SporeCrawler";NA;102;0
"Unit";"Baneling";"Zergling";108;0
"Unit";"Overlord";"Larva";108;0
"Unit";"Baneling";"Zergling";108;0
"Unit";"Overlord";"Larva";108;0
"Unit";"Overlord";"Larva";108;0
"Building";"Extractor";NA;108;0
"Building";"CreepTumor";NA;118;0
"Building";"HydraliskDen";NA;108;0
"Building";"CreepTumor";NA;124;0
"Building";"Extractor";NA;124;0
"Unit";"Queen";"Hatchery";122;2
"Unit";"Zergling";"Larva";133;1
"Unit";"Zergling";"Larva";133;1
"Unit";"Zergling";"Larva";133;1
"Unit";"Zergling";"Larva";133;1
"Unit";"Zergling";"Larva";133;1
"Unit";"Zergling";"Larva";133;1
"Unit";"Zergling";"Larva";133;1
"Unit";"Zergling";"Larva";133;1
"Unit";"Zergling";"Larva";133;1
"Unit";"Zergling";"Larva";133;1
"Upgrade";"ZergMeleeWeaponsLevel1";"EvolutionChamber";102;0
"Unit";"Zergling";"Larva";133;1
"Unit";"Zergling";"Larva";133;1
"Unit";"Zergling";"Larva";133;1
"Unit";"Zergling";"Larva";133;1
"Unit";"Zergling";"Larva";133;1
"Unit";"Zergling";"Larva";133;1
"Unit";"Zergling";"Larva";133;1
"Unit";"Zergling";"Larva";133;1
"Unit";"Zergling";"Larva";137;1
"Unit";"Zergling";"Larva";137;1
"Unit";"Zergling";"Larva";137;1
"Unit";"Zergling";"Larva";137;1
"Building";"CreepTumor";NA;155;0
"Building";"CreepTumor";NA;159;0
"Unit";"Overlord";"Larva";155;0
"Unit";"Overlord";"Larva";155;0
"Unit";"Hydralisk";"Larva";147;2
"Unit";"Hydralisk";"Larva";147;2
"Unit";"Hydralisk";"Larva";147;2
"Unit";"Hydralisk";"Larva";147;2
"Unit";"Hydralisk";"Larva";147;2
"Building";"CreepTumorQueen";NA;159;0
"Unit";"Hydralisk";"Larva";159;2
"Unit";"Hydralisk";"Larva";159;2
"Unit";"Hydralisk";"Larva";159;2
"Unit";"Hydralisk";"Larva";159;2
"Unit";"Hydralisk";"Larva";159;2
"Building";"Hatchery";NA;131;0
"Upgrade";"EvolveGroovedSpines";"HydraliskDen";137;0
"Building";"CreepTumor";NA;169;0
"Unit";"Zergling";"Larva";169;1
"Unit";"Zergling";"Larva";169;1
"Unit";"Zergling";"Larva";169;1
"Unit";"Zergling";"Larva";169;1
"Unit";"Zergling";"Larva";169;1
"Unit";"Zergling";"Larva";169;1
"Unit";"Zergling";"Larva";169;1
"Unit";"Zergling";"Larva";169;1
"Unit";"Zergling";"Larva";169;1
"Unit";"Zergling";"Larva";169;1
"Building";"CreepTumor";NA;169;0
"Building";"CreepTumorQueen";NA;169;0
"Building";"CreepTumor";NA;169;0
"Unit";"Hydralisk";"Larva";169;2
"Unit";"Hydralisk";"Larva";169;2
"Unit";"Overlord";"Larva";171;0
"Unit";"Overlord";"Larva";173;0
"Unit";"Baneling";"Zergling";189;0
"Unit";"Baneling";"Zergling";189;0
"Unit";"Baneling";"Zergling";189;0
"Unit";"Baneling";"Zergling";189;0
"Unit";"Baneling";"Zergling";189;0
"Unit";"Baneling";"Zergling";191;0
"Unit";"Baneling";"Zergling";191;0
"Unit";"Baneling";"Zergling";193;0
"Unit";"Baneling";"Zergling";193;0
"Unit";"Baneling";"Zergling";193;0
"Unit";"Baneling";"Zergling";193;0
"Unit";"Queen";"Hatchery";179;2
"Building";"CreepTumor";NA;197;0
"Building";"CreepTumor";NA;197;0
"Building";"CreepTumor";NA;197;0
"Unit";"Zergling";"Larva";197;1
"Unit";"Zergling";"Larva";197;1
"Unit";"Zergling";"Larva";197;1
"Unit";"Zergling";"Larva";197;1
"Unit";"Zergling";"Larva";197;1
"Unit";"Zergling";"Larva";197;1
"Unit";"Zergling";"Larva";197;1
"Unit";"Zergling";"Larva";197;1
"Unit";"Zergling";"Larva";197;1
"Unit";"Zergling";"Larva";197;1
"Unit";"Zergling";"Larva";197;1
"Unit";"Zergling";"Larva";197;1
"Unit";"Zergling";"Larva";197;1
"Unit";"Zergling";"Larva";197;1
"Unit";"Zergling";"Larva";197;1
"Unit";"Zergling";"Larva";197;1
"Unit";"Zergling";"Larva";197;1
"Unit";"Zergling";"Larva";197;1
"Unit";"Zergling";"Larva";197;1
"Unit";"Zergling";"Larva";197;1
"Unit";"Overlord";"Larva";197;0
"Unit";"Overlord";"Larva";197;0
"Unit";"Overlord";"Larva";197;0
"Unit";"Overlord";"Larva";197;0
"Unit";"Hydralisk";"Larva";197;2
"Unit";"Hydralisk";"Larva";197;2
"Unit";"Hydralisk";"Larva";197;2
"Unit";"Hydralisk";"Larva";197;2
"Unit";"Hydralisk";"Larva";197;2
"Unit";"Hydralisk";"Larva";197;2
"Unit";"Hydralisk";"Larva";197;2
"Unit";"Overlord";"Larva";199;0
"Unit";"Overlord";"Larva";199;0
"Unit";"Overlord";"Larva";199;0
"Upgrade";"EvolveMuscularAugments";"HydraliskDen";197;0
"Building";"CreepTumor";NA;234;0
"Building";"CreepTumor";NA;234;0
"Building";"CreepTumor";NA;234;0
"Unit";"Zergling";"Larva";226;1
"Unit";"Zergling";"Larva";226;1
"Unit";"Zergling";"Larva";230;1
"Unit";"Zergling";"Larva";230;1
"Unit";"Zergling";"Larva";230;1
"Unit";"Zergling";"Larva";230;1
"Unit";"Zergling";"Larva";234;1
"Unit";"Zergling";"Larva";234;1
"Unit";"Zergling";"Larva";234;1
"Unit";"Zergling";"Larva";234;1
"Unit";"Zergling";"Larva";234;1
"Unit";"Zergling";"Larva";234;1
"Building";"InfestationPit";NA;199;0
"Unit";"Queen";"Hatchery";199;2
"Building";"SporeCrawler";NA;234;0
"Building";"SpineCrawler";NA;234;0
"Building";"CreepTumor";NA;250;0
"Building";"CreepTumor";NA;250;0
"Building";"CreepTumor";NA;250;0
"Unit";"Hydralisk";"Larva";250;2
"Unit";"Hydralisk";"Larva";250;2
"Unit";"Hydralisk";"Larva";250;2
"Unit";"Hydralisk";"Larva";250;2
"Unit";"Hydralisk";"Larva";250;2
"Unit";"Hydralisk";"Larva";250;2
"Unit";"Hydralisk";"Larva";250;2
"Unit";"Hydralisk";"Larva";250;2
"Unit";"Hydralisk";"Larva";250;2
"Unit";"Hydralisk";"Larva";250;2
"Upgrade";"ZergMeleeWeaponsLevel2";"EvolutionChamber";197;0
"Building";"CreepTumor";NA;252;0
"Unit";"Baneling";"Zergling";250;0
"Building";"Extractor";NA;250;0
"Unit";"Baneling";"Zergling";250;0
"Unit";"Baneling";"Zergling";250;0
"Unit";"Baneling";"Zergling";250;0
"Unit";"Baneling";"Zergling";250;0
"Unit";"Baneling";"Zergling";250;0
"Unit";"Baneling";"Zergling";250;0
"Unit";"Baneling";"Zergling";250;0
"Unit";"Baneling";"Zergling";250;0
"Unit";"Baneling";"Zergling";250;0
"Unit";"Baneling";"Zergling";250;0
"Unit";"Baneling";"Zergling";250;0
"Unit";"Baneling";"Zergling";250;0
"Unit";"Baneling";"Zergling";250;0
"Unit";"Baneling";"Zergling";250;0
"Unit";"Baneling";"Zergling";250;0
"Unit";"Baneling";"Zergling";250;0
"Building";"Extractor";NA;250;0
"Building";"CreepTumorQueen";NA;270;0
"Building";"CreepTumorQueen";NA;270;0
"Building";"CreepTumorQueen";NA;270;0
"Building";"CreepTumorQueen";NA;270;0
"Building";"CreepTumorQueen";NA;270;0
"Building";"CreepTumorQueen";NA;270;0
"Building";"CreepTumorQueen";NA;270;0
"Unit";"Zergling";"Larva";270;1
"Unit";"Zergling";"Larva";270;1
"Unit";"Zergling";"Larva";270;1
"Unit";"Zergling";"Larva";270;1
"Unit";"Zergling";"Larva";270;1
"Unit";"Zergling";"Larva";270;1
"Unit";"Zergling";"Larva";270;1
"Unit";"Zergling";"Larva";270;1
"Unit";"Zergling";"Larva";270;1
"Unit";"Zergling";"Larva";270;1
"Unit";"Zergling";"Larva";270;1
"Unit";"Zergling";"Larva";270;1
"Unit";"Zergling";"Larva";270;1
"Unit";"Zergling";"Larva";270;1
"Unit";"Zergling";"Larva";270;1
"Unit";"Zergling";"Larva";270;1
"Unit";"Zergling";"Larva";270;1
"Unit";"Zergling";"Larva";270;1
"Unit";"Zergling";"Larva";270;1
"Unit";"Zergling";"Larva";270;1
"Unit";"Zergling";"Larva";270;1
"Unit";"Zergling";"Larva";270;1
"Unit";"Zergling";"Larva";270;1
"Unit";"Zergling";"Larva";270;1
"Unit";"Zergling";"Larva";270;1
"Unit";"Zergling";"Larva";270;1
"Building";"Extractor";NA;270;0
"Unit";"Zergling";"Larva";270;1
"Unit";"Zergling";"Larva";270;1
"Unit";"Zergling";"Larva";270;1
"Unit";"Zergling";"Larva";270;1
"Unit";"Zergling";"Larva";270;1
"Unit";"Zergling";"Larva";270;1
"Unit";"Zergling";"Larva";270;1
"Unit";"Zergling";"Larva";270;1
"Unit";"Zergling";"Larva";270;1
"Unit";"Zergling";"Larva";270;1
"Unit";"Zergling";"Larva";273;1
"Unit";"Zergling";"Larva";273;1
"Unit";"Zergling";"Larva";273;1
"Unit";"Zergling";"Larva";273;1
"Unit";"Zergling";"Larva";273;1
"Unit";"Zergling";"Larva";273;1
"Unit";"Zergling";"Larva";273;1
"Unit";"Zergling";"Larva";273;1
"Unit";"Zergling";"Larva";273;1
"Unit";"Zergling";"Larva";273;1
"Unit";"Zergling";"Larva";273;1
"Unit";"Zergling";"Larva";273;1
"Unit";"Zergling";"Larva";273;1
"Unit";"Zergling";"Larva";273;1
"Unit";"Zergling";"Larva";273;1
"Unit";"Zergling";"Larva";273;1
"Unit";"Baneling";"Zergling";299;0
"Unit";"Baneling";"Zergling";299;0
"Unit";"Baneling";"Zergling";299;0
"Unit";"Baneling";"Zergling";299;0
"Unit";"Baneling";"Zergling";299;0
"Unit";"Baneling";"Zergling";299;0
"Unit";"Baneling";"Zergling";299;0
"Unit";"Baneling";"Zergling";299;0
"Unit";"Baneling";"Zergling";299;0
"Unit";"Baneling";"Zergling";299;0
"Unit";"Baneling";"Zergling";299;0
"Unit";"Baneling";"Zergling";299;0
"Unit";"Baneling";"Zergling";299;0
"Unit";"Baneling";"Zergling";299;0
"Unit";"Baneling";"Zergling";299;0
"Unit";"Baneling";"Zergling";299;0
"Unit";"Baneling";"Zergling";299;0
"Unit";"Baneling";"Zergling";299;0
"Unit";"Baneling";"Zergling";299;0
"Unit";"Baneling";"Zergling";299;0
"Unit";"Zergling";"Larva";309;1
"Unit";"Zergling";"Larva";309;1
"Unit";"Zergling";"Larva";309;1
"Unit";"Zergling";"Larva";309;1
"Unit";"Zergling";"Larva";309;1
"Unit";"Zergling";"Larva";309;1
"Unit";"Zergling";"Larva";309;1
"Unit";"Zergling";"Larva";309;1
"Unit";"Zergling";"Larva";325;1
"Unit";"Zergling";"Larva";325;1
"Unit";"Zergling";"Larva";325;1
"Unit";"Zergling";"Larva";325;1
"Unit";"Zergling";"Larva";325;1
"Unit";"Zergling";"Larva";325;1
"Unit";"Zergling";"Larva";325;1
"Unit";"Zergling";"Larva";325;1
"Unit";"Zergling";"Larva";325;1
"Unit";"Zergling";"Larva";325;1
"Unit";"Zergling";"Larva";325;1
"Unit";"Zergling";"Larva";325;1
"Unit";"Zergling";"Larva";325;1
"Unit";"Zergling";"Larva";325;1
"Unit";"Zergling";"Larva";325;1
"Unit";"Zergling";"Larva";325;1
"Unit";"Zergling";"Larva";325;1
"Unit";"Zergling";"Larva";325;1
"Building";"Spire";NA;270;0
"Unit";"Hydralisk";"Larva";333;2
"Unit";"Hydralisk";"Larva";333;2
"Unit";"Hydralisk";"Larva";333;2
"Unit";"Hydralisk";"Larva";333;2
"Building";"CreepTumor";NA;351;0
"Building";"CreepTumor";NA;351;0
"Unit";"Hydralisk";"Larva";351;2
"Unit";"Hydralisk";"Larva";351;2
"Unit";"Hydralisk";"Larva";351;2
"Unit";"Hydralisk";"Larva";351;2
"Unit";"Hydralisk";"Larva";351;2
"Unit";"Hydralisk";"Larva";351;2
"Unit";"Hydralisk";"Larva";351;2
"Unit";"Hydralisk";"Larva";351;2
"Unit";"Hydralisk";"Larva";351;2
"Unit";"Hydralisk";"Larva";351;2
"Unit";"Hydralisk";"Larva";351;2
"Unit";"Baneling";"Zergling";359;0
"Unit";"Baneling";"Zergling";359;0
"Unit";"Zergling";"Larva";351;1
"Unit";"Zergling";"Larva";351;1
"Unit";"Zergling";"Larva";351;1
"Unit";"Zergling";"Larva";351;1
"Unit";"Zergling";"Larva";351;1
"Unit";"Zergling";"Larva";351;1
"Unit";"Zergling";"Larva";351;1
"Unit";"Zergling";"Larva";351;1
"Unit";"Zergling";"Larva";351;1
"Unit";"Zergling";"Larva";351;1
"Unit";"Baneling";"Zergling";359;0
"Unit";"Baneling";"Zergling";359;0
"Unit";"Baneling";"Zergling";359;0
"Unit";"Baneling";"Zergling";359;0
"Unit";"Baneling";"Zergling";359;0
"Unit";"Baneling";"Zergling";359;0
"Unit";"Zergling";"Larva";359;1
"Unit";"Zergling";"Larva";359;1
"Unit";"Hydralisk";"Larva";391;2
"Unit";"Hydralisk";"Larva";391;2
"Unit";"Hydralisk";"Larva";391;2
"Unit";"Hydralisk";"Larva";391;2
"Unit";"Hydralisk";"Larva";391;2
"Unit";"Zergling";"Larva";393;1
"Unit";"Zergling";"Larva";393;1
"Unit";"Zergling";"Larva";393;1
"Unit";"Zergling";"Larva";393;1
"Unit";"Zergling";"Larva";393;1
"Unit";"Zergling";"Larva";393;1
"Unit";"Zergling";"Larva";393;1
"Unit";"Zergling";"Larva";393;1
"Unit";"Zergling";"Larva";393;1
"Unit";"Zergling";"Larva";393;1
"Unit";"Zergling";"Larva";393;1
"Unit";"Zergling";"Larva";393;1
"Unit";"Zergling";"Larva";393;1
"Unit";"Zergling";"Larva";393;1
"Unit";"Zergling";"Larva";393;1
"Unit";"Zergling";"Larva";393;1
"Unit";"Zergling";"Larva";393;1
"Unit";"Zergling";"Larva";393;1
"Unit";"Zergling";"Larva";393;1
"Unit";"Zergling";"Larva";393;1
"Unit";"Zergling";"Larva";393;1
"Unit";"Zergling";"Larva";393;1
"Unit";"Zergling";"Larva";393;1
"Unit";"Zergling";"Larva";393;1
"Unit";"Zergling";"Larva";393;1
"Unit";"Zergling";"Larva";393;1
"Unit";"Zergling";"Larva";393;1
"Unit";"Zergling";"Larva";393;1
"Building";"CreepTumor";NA;403;0
"Building";"CreepTumor";NA;403;0
"Building";"CreepTumor";NA;403;0
"Building";"CreepTumor";NA;403;0
"Building";"CreepTumor";NA;403;0
"Building";"CreepTumor";NA;403;0
"Upgrade";"ZergMissileWeaponsLevel1";"EvolutionChamber";351;0
"Unit";"Corruptor";"Larva";427;2
"Unit";"Corruptor";"Larva";427;2
"Unit";"Corruptor";"Larva";427;2
"Unit";"Corruptor";"Larva";427;2
"Unit";"Corruptor";"Larva";431;2
"Building";"CreepTumor";NA;443;0
"Unit";"Corruptor";"Larva";433;2
"Unit";"Corruptor";"Larva";433;2
"Unit";"Corruptor";"Larva";433;2
"Building";"CreepTumor";NA;443;0
"Building";"CreepTumor";NA;443;0
"Building";"CreepTumor";NA;443;0
"Building";"CreepTumor";NA;443;0
"Building";"CreepTumor";NA;443;0
"Building";"CreepTumor";NA;443;0
"Building";"CreepTumor";NA;443;0
"Building";"CreepTumorQueen";NA;449;0
"Unit";"Baneling";"Zergling";449;0
"Unit";"Baneling";"Zergling";449;0
"Unit";"Baneling";"Zergling";449;0
"Unit";"Baneling";"Zergling";449;0
"Unit";"Baneling";"Zergling";449;0
"Unit";"Zergling";"Larva";449;1
"Unit";"Zergling";"Larva";449;1
"Unit";"Zergling";"Larva";449;1
"Unit";"Zergling";"Larva";449;1
"Unit";"Zergling";"Larva";449;1
"Unit";"Zergling";"Larva";449;1
"Unit";"Zergling";"Larva";449;1
"Unit";"Zergling";"Larva";449;1
"Unit";"Zergling";"Larva";449;1
"Unit";"Zergling";"Larva";449;1
"Unit";"Zergling";"Larva";449;1
"Unit";"Zergling";"Larva";449;1
"Unit";"Zergling";"Larva";449;1
"Unit";"Zergling";"Larva";449;1
"Unit";"Zergling";"Larva";449;1
"Unit";"Zergling";"Larva";449;1
"Unit";"Zergling";"Larva";449;1
"Unit";"Zergling";"Larva";449;1
"Unit";"Zergling";"Larva";449;1
"Unit";"Zergling";"Larva";449;1
"Unit";"Zergling";"Larva";449;1
"Unit";"Zergling";"Larva";449;1
"Unit";"Zergling";"Larva";449;1
"Unit";"Zergling";"Larva";449;1
"Unit";"Zergling";"Larva";449;1
"Unit";"Zergling";"Larva";449;1
"Unit";"Zergling";"Larva";449;1
"Unit";"Zergling";"Larva";449;1
"Unit";"Zergling";"Larva";449;1
"Unit";"Zergling";"Larva";449;1
"Building";"CreepTumor";NA;449;0
"Unit";"Zergling";"Larva";449;1
"Unit";"Zergling";"Larva";449;1
"Unit";"Zergling";"Larva";449;1
"Unit";"Zergling";"Larva";449;1
"Unit";"Zergling";"Larva";449;1
"Unit";"Zergling";"Larva";449;1
"Unit";"Zergling";"Larva";449;1
"Unit";"Zergling";"Larva";449;1
"Unit";"Zergling";"Larva";449;1
"Unit";"Zergling";"Larva";449;1
"Unit";"Zergling";"Larva";449;1
"Unit";"Zergling";"Larva";449;1
"Unit";"Zergling";"Larva";449;1
"Unit";"Zergling";"Larva";449;1
"Unit";"Zergling";"Larva";449;1
"Unit";"Zergling";"Larva";449;1
"Unit";"Zergling";"Larva";449;1
"Unit";"Zergling";"Larva";449;1
"Unit";"Zergling";"Larva";449;1
"Unit";"Zergling";"Larva";449;1
"Unit";"Zergling";"Larva";449;1
"Unit";"Zergling";"Larva";449;1
"Unit";"Zergling";"Larva";449;1
"Unit";"Zergling";"Larva";449;1
"Building";"Hatchery";NA;449;0
"Unit";"Mutalisk";"Larva";479;2
"Unit";"Mutalisk";"Larva";479;2
"Unit";"Mutalisk";"Larva";479;2
"Building";"CreepTumorQueen";NA;506;0
"Unit";"Hydralisk";"Larva";506;2
"Unit";"Hydralisk";"Larva";506;2
"Unit";"Hydralisk";"Larva";506;2
"Unit";"Hydralisk";"Larva";506;2
"Unit";"Hydralisk";"Larva";506;2
"Unit";"Hydralisk";"Larva";512;2
"Unit";"Hydralisk";"Larva";512;2
"Unit";"Hydralisk";"Larva";512;2
"Unit";"Hydralisk";"Larva";512;2
