"type";"unit_name";"on_building";"total_supply";"supply"
"Unit";"Overlord";"Larva";12;0
"Building";"Extractor";NA;19;0
"Unit";"Overlord";"Larva";22;0
"Building";"Hatchery";NA;17;0
"Building";"SpawningPool";NA;19;0
"Unit";"Zergling";"Larva";22;1
"Unit";"Zergling";"Larva";22;1
"Unit";"Zergling";"Larva";22;1
"Unit";"Zergling";"Larva";22;1
"Unit";"Queen";"Hatchery";22;2
"Unit";"Queen";"Hatchery";22;2
"Unit";"Overlord";"Larva";30;0
"Unit";"Queen";"Hatchery";31;2
"Unit";"Zergling";"Larva";39;1
"Unit";"Zergling";"Larva";39;1
"Building";"CreepTumorQueen";NA;43;0
"Unit";"Zergling";"Larva";40;1
"Unit";"Zergling";"Larva";40;1
"Unit";"Overlord";"Larva";43;0
"Building";"SporeCrawler";NA;52;0
"Building";"SporeCrawler";NA;52;0
"Building";"Hatchery";NA;37;0
"Building";"CreepTumorQueen";NA;56;0
"Building";"CreepTumor";NA;56;0
"Unit";"Overlord";"Larva";56;0
"Unit";"Overlord";"Larva";62;0
"Unit";"Overlord";"Larva";62;0
"Unit";"Queen";"Hatchery";59;2
"Unit";"Zergling";"Larva";65;1
"Unit";"Zergling";"Larva";65;1
"Unit";"Zergling";"Larva";65;1
"Unit";"Zergling";"Larva";65;1
"Unit";"Zergling";"Larva";65;1
"Unit";"Zergling";"Larva";65;1
"Unit";"Zergling";"Larva";65;1
"Unit";"Zergling";"Larva";65;1
"Unit";"Zergling";"Larva";65;1
"Unit";"Zergling";"Larva";65;1
"Unit";"Queen";"Hatchery";59;2
"Building";"SporeCrawler";NA;65;0
"Building";"Extractor";NA;65;0
"Building";"EvolutionChamber";NA;65;0
"Building";"BanelingNest";NA;65;0
"Building";"Extractor";NA;87;0
"Building";"CreepTumorQueen";NA;87;0
"Building";"Extractor";NA;87;0
"Building";"CreepTumorQueen";NA;95;0
"Unit";"Overlord";"Larva";95;0
"Unit";"Zergling";"Larva";95;1
"Unit";"Zergling";"Larva";95;1
"Unit";"Zergling";"Larva";95;1
"Unit";"Zergling";"Larva";95;1
"Unit";"Zergling";"Larva";95;1
"Unit";"Zergling";"Larva";95;1
"Unit";"Zergling";"Larva";95;1
"Unit";"Zergling";"Larva";95;1
"Unit";"Zergling";"Larva";95;1
"Unit";"Zergling";"Larva";95;1
"Unit";"Zergling";"Larva";95;1
"Unit";"Zergling";"Larva";95;1
"Unit";"Zergling";"Larva";95;1
"Unit";"Zergling";"Larva";95;1
"Unit";"Zergling";"Larva";95;1
"Unit";"Zergling";"Larva";95;1
"Unit";"Zergling";"Larva";95;1
"Unit";"Zergling";"Larva";95;1
"Unit";"Zergling";"Larva";95;1
"Unit";"Zergling";"Larva";95;1
"Building";"HydraliskDen";NA;95;0
"Building";"SporeCrawler";NA;95;0
"Building";"SporeCrawler";NA;95;0
"Building";"SporeCrawler";NA;95;0
"Building";"CreepTumor";NA;121;0
"Building";"CreepTumorQueen";NA;122;0
"Building";"CreepTumor";NA;122;0
"Unit";"Overlord";"Larva";122;0
"Unit";"Overlord";"Larva";122;0
"Unit";"Baneling";"Zergling";124;0
"Unit";"Baneling";"Zergling";124;0
"Unit";"Baneling";"Zergling";124;0
"Unit";"Baneling";"Zergling";124;0
"Unit";"Baneling";"Zergling";124;0
"Unit";"Baneling";"Zergling";124;0
"Unit";"Zergling";"Larva";124;1
"Unit";"Zergling";"Larva";124;1
"Unit";"Zergling";"Larva";124;1
"Unit";"Zergling";"Larva";124;1
"Unit";"Zergling";"Larva";124;1
"Unit";"Zergling";"Larva";124;1
"Unit";"Zergling";"Larva";124;1
"Unit";"Zergling";"Larva";124;1
"Unit";"Zergling";"Larva";124;1
"Unit";"Zergling";"Larva";124;1
"Unit";"Zergling";"Larva";124;1
"Unit";"Zergling";"Larva";124;1
"Unit";"Zergling";"Larva";124;1
"Unit";"Zergling";"Larva";124;1
"Unit";"Zergling";"Larva";124;1
"Unit";"Zergling";"Larva";124;1
"Unit";"Zergling";"Larva";124;1
"Unit";"Zergling";"Larva";124;1
"Unit";"Zergling";"Larva";124;1
"Unit";"Zergling";"Larva";124;1
"Unit";"Zergling";"Larva";124;1
"Unit";"Zergling";"Larva";124;1
"Unit";"Zergling";"Larva";124;1
"Unit";"Zergling";"Larva";124;1
"Unit";"Zergling";"Larva";124;1
"Unit";"Zergling";"Larva";124;1
"Unit";"Zergling";"Larva";124;1
"Unit";"Zergling";"Larva";124;1
"Unit";"Baneling";"Zergling";136;0
"Unit";"Baneling";"Zergling";136;0
"Upgrade";"ZergMeleeWeaponsLevel1";"EvolutionChamber";95;0
"Unit";"Zergling";"Larva";152;1
"Unit";"Zergling";"Larva";152;1
"Unit";"Zergling";"Larva";152;1
"Unit";"Zergling";"Larva";152;1
"Unit";"Zergling";"Larva";152;1
"Unit";"Zergling";"Larva";152;1
"Unit";"Zergling";"Larva";152;1
"Unit";"Zergling";"Larva";152;1
"Unit";"Zergling";"Larva";152;1
"Unit";"Zergling";"Larva";152;1
"Unit";"Zergling";"Larva";152;1
"Unit";"Zergling";"Larva";152;1
"Unit";"Zergling";"Larva";152;1
"Unit";"Zergling";"Larva";152;1
"Unit";"Zergling";"Larva";152;1
"Unit";"Zergling";"Larva";152;1
"Unit";"Zergling";"Larva";152;1
"Unit";"Zergling";"Larva";152;1
"Unit";"Zergling";"Larva";152;1
"Unit";"Zergling";"Larva";152;1
"Unit";"Zergling";"Larva";152;1
"Unit";"Zergling";"Larva";152;1
"Unit";"Zergling";"Larva";152;1
"Unit";"Zergling";"Larva";152;1
"Unit";"Zergling";"Larva";152;1
"Unit";"Zergling";"Larva";152;1
"Building";"Hatchery";NA;124;0
"Unit";"Zergling";"Larva";164;1
"Unit";"Zergling";"Larva";164;1
"Unit";"Zergling";"Larva";168;1
"Unit";"Zergling";"Larva";168;1
"Unit";"Zergling";"Larva";168;1
"Unit";"Zergling";"Larva";168;1
"Unit";"Zergling";"Larva";180;1
"Unit";"Zergling";"Larva";180;1
"Unit";"Zergling";"Larva";180;1
"Unit";"Zergling";"Larva";180;1
"Unit";"Zergling";"Larva";180;1
"Unit";"Zergling";"Larva";180;1
"Unit";"Queen";"Hatchery";164;2
"Unit";"Queen";"Hatchery";164;2
"Unit";"Queen";"Hatchery";164;2
"Unit";"Zergling";"Larva";184;1
"Unit";"Zergling";"Larva";184;1
"Unit";"Zergling";"Larva";184;1
"Unit";"Zergling";"Larva";184;1
"Building";"CreepTumorQueen";NA;196;0
"Building";"CreepTumor";NA;200;0
"Building";"CreepTumor";NA;209;0
"Building";"CreepTumor";NA;212;0
"Building";"CreepTumor";NA;212;0
"Unit";"Zergling";"Larva";212;1
"Unit";"Zergling";"Larva";212;1
"Unit";"Zergling";"Larva";212;1
"Unit";"Zergling";"Larva";212;1
"Unit";"Zergling";"Larva";212;1
"Unit";"Zergling";"Larva";212;1
"Unit";"Overlord";"Larva";212;0
"Unit";"Overlord";"Larva";212;0
"Unit";"Baneling";"Zergling";213;0
"Unit";"Baneling";"Zergling";213;0
"Unit";"Baneling";"Zergling";219;0
"Unit";"Baneling";"Zergling";221;0
"Building";"SporeCrawler";NA;212;0
"Unit";"Zergling";"Larva";227;1
"Unit";"Zergling";"Larva";227;1
"Unit";"Zergling";"Larva";227;1
"Unit";"Zergling";"Larva";227;1
"Unit";"Zergling";"Larva";227;1
"Unit";"Zergling";"Larva";227;1
"Unit";"Zergling";"Larva";227;1
"Unit";"Zergling";"Larva";227;1
"Unit";"Zergling";"Larva";227;1
"Unit";"Zergling";"Larva";227;1
"Unit";"Zergling";"Larva";227;1
"Unit";"Zergling";"Larva";227;1
"Unit";"Zergling";"Larva";227;1
"Unit";"Zergling";"Larva";227;1
"Building";"CreepTumor";NA;227;0
"Building";"CreepTumor";NA;227;0
"Building";"CreepTumor";NA;230;0
"Building";"CreepTumor";NA;231;0
"Unit";"Overlord";"Larva";227;0
"Unit";"Overlord";"Larva";227;0
"Unit";"Hydralisk";"Larva";231;2
"Unit";"Hydralisk";"Larva";231;2
"Unit";"Hydralisk";"Larva";231;2
"Upgrade";"EvolveMuscularAugments";"HydraliskDen";212;0
"Unit";"Hydralisk";"Larva";245;2
"Unit";"Hydralisk";"Larva";245;2
"Unit";"Hydralisk";"Larva";245;2
"Unit";"Hydralisk";"Larva";245;2
"Unit";"Hydralisk";"Larva";245;2
"Unit";"Hydralisk";"Larva";245;2
"Unit";"Hydralisk";"Larva";245;2
"Building";"CreepTumor";NA;251;0
"Unit";"Hydralisk";"Larva";245;2
"Building";"CreepTumor";NA;251;0
"Building";"CreepTumor";NA;251;0
"Unit";"Overlord";"Larva";245;0
"Unit";"Overlord";"Larva";247;0
"Building";"Hatchery";NA;212;0
"Unit";"Hydralisk";"Larva";261;2
"Unit";"Hydralisk";"Larva";261;2
"Unit";"Hydralisk";"Larva";261;2
"Building";"Extractor";NA;268;0
"Building";"CreepTumor";NA;268;0
"Building";"Extractor";NA;268;0
"Upgrade";"ZergMeleeWeaponsLevel2";"EvolutionChamber";212;0
"Unit";"Hydralisk";"Larva";268;2
"Unit";"Hydralisk";"Larva";268;2
"Unit";"Overlord";"Larva";280;0
"Unit";"Overlord";"Larva";280;0
"Unit";"Hydralisk";"Larva";268;2
"Unit";"Hydralisk";"Larva";268;2
"Unit";"Hydralisk";"Larva";268;2
"Building";"CreepTumorQueen";NA;280;0
"Unit";"Zergling";"Larva";280;1
"Unit";"Zergling";"Larva";280;1
"Unit";"Zergling";"Larva";280;1
"Unit";"Zergling";"Larva";280;1
"Unit";"Zergling";"Larva";280;1
"Unit";"Zergling";"Larva";280;1
"Unit";"Zergling";"Larva";280;1
"Unit";"Zergling";"Larva";280;1
"Unit";"Zergling";"Larva";280;1
"Unit";"Zergling";"Larva";280;1
"Unit";"Zergling";"Larva";280;1
"Unit";"Zergling";"Larva";280;1
"Building";"CreepTumor";NA;280;0
"Unit";"Overlord";"Larva";290;0
"Building";"CreepTumor";NA;302;0
"Upgrade";"EvolveGroovedSpines";"HydraliskDen";280;0
"Building";"CreepTumor";NA;311;0
"Building";"CreepTumorQueen";NA;311;0
"Building";"CreepTumor";NA;311;0
"Building";"CreepTumor";NA;311;0
"Unit";"Hydralisk";"Larva";308;2
"Unit";"Hydralisk";"Larva";308;2
"Unit";"Hydralisk";"Larva";308;2
"Unit";"Baneling";"Zergling";311;0
"Unit";"Baneling";"Zergling";311;0
"Unit";"Baneling";"Zergling";311;0
"Unit";"Baneling";"Zergling";311;0
"Unit";"Baneling";"Zergling";311;0
"Unit";"Baneling";"Zergling";311;0
"Unit";"Baneling";"Zergling";311;0
"Unit";"Baneling";"Zergling";311;0
"Unit";"Baneling";"Zergling";311;0
"Unit";"Baneling";"Zergling";311;0
"Unit";"Baneling";"Zergling";311;0
"Unit";"Baneling";"Zergling";311;0
"Unit";"Baneling";"Zergling";311;0
"Unit";"Baneling";"Zergling";311;0
"Unit";"Baneling";"Zergling";311;0
"Unit";"Baneling";"Zergling";311;0
"Unit";"Baneling";"Zergling";311;0
"Unit";"Baneling";"Zergling";311;0
"Unit";"Baneling";"Zergling";311;0
"Unit";"Zergling";"Larva";311;1
"Unit";"Zergling";"Larva";311;1
"Unit";"Zergling";"Larva";311;1
"Unit";"Zergling";"Larva";311;1
"Unit";"Zergling";"Larva";311;1
"Unit";"Zergling";"Larva";311;1
"Unit";"Zergling";"Larva";311;1
"Unit";"Zergling";"Larva";311;1
"Unit";"Zergling";"Larva";311;1
"Unit";"Zergling";"Larva";311;1
"Unit";"Zergling";"Larva";317;1
"Unit";"Zergling";"Larva";317;1
"Unit";"Zergling";"Larva";317;1
"Unit";"Zergling";"Larva";317;1
"Unit";"Zergling";"Larva";317;1
"Unit";"Zergling";"Larva";317;1
"Unit";"Zergling";"Larva";317;1
"Unit";"Zergling";"Larva";317;1
"Unit";"Zergling";"Larva";317;1
"Unit";"Zergling";"Larva";317;1
"Unit";"Zergling";"Larva";317;1
"Unit";"Zergling";"Larva";317;1
"Unit";"Zergling";"Larva";317;1
"Unit";"Zergling";"Larva";317;1
"Unit";"Zergling";"Larva";317;1
"Unit";"Zergling";"Larva";317;1
"Unit";"Zergling";"Larva";317;1
"Unit";"Zergling";"Larva";317;1
"Unit";"Zergling";"Larva";317;1
"Unit";"Zergling";"Larva";317;1
"Unit";"Zergling";"Larva";317;1
"Unit";"Zergling";"Larva";317;1
"Unit";"Baneling";"Zergling";317;0
"Unit";"Zergling";"Larva";317;1
"Unit";"Zergling";"Larva";317;1
"Unit";"Baneling";"Zergling";317;0
"Unit";"Zergling";"Larva";317;1
"Unit";"Zergling";"Larva";317;1
"Unit";"Baneling";"Zergling";319;0
"Unit";"Baneling";"Zergling";319;0
"Unit";"Baneling";"Zergling";319;0
"Unit";"Baneling";"Zergling";319;0
"Unit";"Baneling";"Zergling";327;0
"Unit";"Baneling";"Zergling";327;0
"Unit";"Baneling";"Zergling";327;0
"Unit";"Baneling";"Zergling";327;0
"Unit";"Baneling";"Zergling";327;0
"Unit";"Baneling";"Zergling";327;0
"Unit";"Baneling";"Zergling";327;0
"Unit";"Baneling";"Zergling";327;0
"Unit";"Zergling";"Larva";353;1
"Unit";"Zergling";"Larva";353;1
"Unit";"Zergling";"Larva";353;1
"Unit";"Zergling";"Larva";353;1
"Unit";"Zergling";"Larva";353;1
"Unit";"Zergling";"Larva";353;1
"Unit";"Zergling";"Larva";353;1
"Unit";"Zergling";"Larva";353;1
"Unit";"Zergling";"Larva";353;1
"Unit";"Zergling";"Larva";353;1
"Unit";"Zergling";"Larva";353;1
"Unit";"Zergling";"Larva";353;1
"Unit";"Hydralisk";"Larva";353;2
"Unit";"Hydralisk";"Larva";353;2
"Unit";"Hydralisk";"Larva";353;2
"Unit";"Hydralisk";"Larva";353;2
"Building";"Hatchery";NA;311;0
"Unit";"Zergling";"Larva";353;1
"Unit";"Zergling";"Larva";353;1
"Unit";"Zergling";"Larva";353;1
"Unit";"Zergling";"Larva";353;1
"Unit";"Zergling";"Larva";353;1
"Unit";"Zergling";"Larva";353;1
"Unit";"Zergling";"Larva";353;1
"Unit";"Zergling";"Larva";353;1
"Unit";"Zergling";"Larva";353;1
"Unit";"Zergling";"Larva";353;1
"Unit";"Zergling";"Larva";353;1
"Unit";"Zergling";"Larva";353;1
"Unit";"Zergling";"Larva";353;1
"Unit";"Zergling";"Larva";353;1
"Unit";"Hydralisk";"Larva";353;2
"Unit";"Hydralisk";"Larva";353;2
"Unit";"Zergling";"Larva";353;1
"Unit";"Zergling";"Larva";353;1
"Building";"LurkerDenMP";NA;308;0
"Unit";"Hydralisk";"Larva";353;2
"Unit";"Zergling";"Larva";353;1
"Unit";"Zergling";"Larva";353;1
"Upgrade";"ZergMissileWeaponsLevel1";"EvolutionChamber";311;0
"Unit";"Hydralisk";"Larva";373;2
"Unit";"Hydralisk";"Larva";373;2
"Unit";"Hydralisk";"Larva";373;2
"Unit";"Hydralisk";"Larva";373;2
"Building";"Extractor";NA;373;0
"Building";"Extractor";NA;373;0
"Unit";"Baneling";"Zergling";403;0
"Unit";"Baneling";"Zergling";404;0
"Unit";"Baneling";"Zergling";404;0
"Unit";"Hydralisk";"Larva";413;2
"Unit";"Hydralisk";"Larva";413;2
"Unit";"Hydralisk";"Larva";413;2
"Unit";"Hydralisk";"Larva";413;2
"Unit";"Hydralisk";"Larva";413;2
"Unit";"Zergling";"Larva";413;1
"Unit";"Zergling";"Larva";413;1
"Unit";"Zergling";"Larva";413;1
"Unit";"Zergling";"Larva";413;1
"Unit";"Zergling";"Larva";413;1
"Unit";"Zergling";"Larva";413;1
"Unit";"Zergling";"Larva";413;1
"Unit";"Zergling";"Larva";413;1
"Unit";"Zergling";"Larva";413;1
"Unit";"Zergling";"Larva";413;1
"Unit";"Zergling";"Larva";413;1
"Unit";"Zergling";"Larva";413;1
"Unit";"Zergling";"Larva";413;1
"Unit";"Zergling";"Larva";413;1
"Building";"Extractor";NA;413;0
"Unit";"Zergling";"Larva";413;1
"Unit";"Zergling";"Larva";413;1
"Unit";"Zergling";"Larva";413;1
"Unit";"Zergling";"Larva";413;1
"Unit";"Zergling";"Larva";413;1
"Unit";"Zergling";"Larva";413;1
"Unit";"Zergling";"Larva";413;1
"Unit";"Zergling";"Larva";413;1
"Unit";"Zergling";"Larva";417;1
"Unit";"Zergling";"Larva";417;1
"Unit";"Zergling";"Larva";417;1
"Unit";"Zergling";"Larva";417;1
"Unit";"Zergling";"Larva";419;1
"Unit";"Zergling";"Larva";419;1
"Unit";"Zergling";"Larva";421;1
"Unit";"Zergling";"Larva";421;1
"Unit";"Zergling";"Larva";423;1
"Unit";"Zergling";"Larva";423;1
"Unit";"Hydralisk";"Larva";413;2
"Unit";"Hydralisk";"Larva";413;2
"Unit";"Hydralisk";"Larva";413;2
"Unit";"Baneling";"Zergling";445;0
"Unit";"Baneling";"Zergling";445;0
"Unit";"Baneling";"Zergling";445;0
"Unit";"Baneling";"Zergling";445;0
"Building";"SporeCrawler";NA;461;0
"Unit";"Hydralisk";"Larva";462;2
"Unit";"Hydralisk";"Larva";462;2
"Unit";"Hydralisk";"Larva";463;2
"Unit";"Hydralisk";"Larva";463;2
"Building";"SpineCrawler";NA;461;0
"Unit";"Zergling";"Larva";468;1
"Unit";"Zergling";"Larva";468;1
"Unit";"Zergling";"Larva";468;1
"Unit";"Zergling";"Larva";468;1
"Unit";"Zergling";"Larva";468;1
"Unit";"Zergling";"Larva";468;1
"Unit";"Zergling";"Larva";468;1
"Unit";"Zergling";"Larva";468;1
"Unit";"Zergling";"Larva";468;1
"Unit";"Zergling";"Larva";468;1
"Unit";"Zergling";"Larva";468;1
"Unit";"Zergling";"Larva";468;1
"Unit";"Zergling";"Larva";468;1
"Unit";"Zergling";"Larva";468;1
"Unit";"Zergling";"Larva";468;1
"Unit";"Zergling";"Larva";468;1
"Unit";"Queen";"Hatchery";462;2
"Unit";"Zergling";"Larva";468;1
"Unit";"Zergling";"Larva";468;1
"Unit";"Baneling";"Zergling";476;0
"Unit";"Baneling";"Zergling";476;0
"Unit";"Baneling";"Zergling";476;0
"Unit";"Baneling";"Zergling";476;0
"Unit";"Baneling";"Zergling";476;0
"Unit";"Baneling";"Zergling";476;0
"Unit";"Baneling";"Zergling";476;0
"Unit";"Baneling";"Zergling";476;0
"Unit";"Baneling";"Zergling";476;0
"Unit";"Baneling";"Zergling";476;0
"Unit";"Baneling";"Zergling";476;0
"Unit";"Baneling";"Zergling";476;0
"Unit";"Baneling";"Zergling";476;0
"Unit";"Baneling";"Zergling";476;0
"Building";"Extractor";NA;496;0
"Unit";"Hydralisk";"Larva";496;2
"Unit";"Hydralisk";"Larva";496;2
"Unit";"Hydralisk";"Larva";496;2
"Unit";"Hydralisk";"Larva";496;2
"Unit";"Hydralisk";"Larva";496;2
"Unit";"Hydralisk";"Larva";496;2
"Unit";"Hydralisk";"Larva";496;2
"Unit";"Hydralisk";"Larva";496;2
"Unit";"Zergling";"Larva";496;1
"Unit";"Zergling";"Larva";496;1
"Unit";"Zergling";"Larva";496;1
"Unit";"Zergling";"Larva";496;1
"Unit";"Zergling";"Larva";496;1
"Unit";"Zergling";"Larva";496;1
"Unit";"Zergling";"Larva";496;1
"Unit";"Zergling";"Larva";496;1
"Unit";"Zergling";"Larva";496;1
"Unit";"Zergling";"Larva";496;1
"Unit";"Zergling";"Larva";496;1
"Unit";"Zergling";"Larva";496;1
"Unit";"Zergling";"Larva";496;1
"Unit";"Zergling";"Larva";496;1
"Unit";"Zergling";"Larva";496;1
"Unit";"Zergling";"Larva";496;1
"Unit";"Zergling";"Larva";496;1
"Unit";"Zergling";"Larva";496;1
"Unit";"Zergling";"Larva";496;1
"Unit";"Zergling";"Larva";496;1
"Unit";"Hydralisk";"Larva";496;2
"Unit";"Hydralisk";"Larva";496;2
"Unit";"Hydralisk";"Larva";496;2
"Unit";"Hydralisk";"Larva";496;2
"Unit";"Hydralisk";"Larva";496;2
"Unit";"Hydralisk";"Larva";496;2
"Unit";"Hydralisk";"Larva";496;2
"Unit";"Hydralisk";"Larva";496;2
"Unit";"Baneling";"Zergling";534;0
"Unit";"Baneling";"Zergling";536;0
"Unit";"Baneling";"Zergling";540;0
"Unit";"Baneling";"Zergling";540;0
"Unit";"Baneling";"Zergling";540;0
"Unit";"Baneling";"Zergling";544;0
"Unit";"Baneling";"Zergling";548;0
"Upgrade";"ZergMissileWeaponsLevel2";"EvolutionChamber";476;0
"Unit";"Hydralisk";"Larva";548;2
"Unit";"Hydralisk";"Larva";548;2
"Unit";"Hydralisk";"Larva";548;2
"Unit";"Hydralisk";"Larva";548;2
"Unit";"Hydralisk";"Larva";548;2
"Unit";"Hydralisk";"Larva";548;2
"Unit";"Hydralisk";"Larva";548;2
"Unit";"Zergling";"Larva";548;1
"Unit";"Zergling";"Larva";548;1
"Unit";"Overlord";"Larva";548;0
"Unit";"Overlord";"Larva";548;0
"Unit";"Hydralisk";"Larva";548;2
"Unit";"Hydralisk";"Larva";548;2
"Unit";"Zergling";"Larva";562;1
"Unit";"Zergling";"Larva";562;1
"Unit";"Zergling";"Larva";562;1
"Unit";"Zergling";"Larva";562;1
"Unit";"Zergling";"Larva";562;1
"Unit";"Zergling";"Larva";562;1
"Building";"InfestationPit";NA;548;0
"Unit";"Hydralisk";"Larva";568;2
"Unit";"Hydralisk";"Larva";568;2
"Unit";"Hydralisk";"Larva";568;2
"Unit";"Hydralisk";"Larva";568;2
"Unit";"Hydralisk";"Larva";568;2
"Unit";"Hydralisk";"Larva";568;2
"Unit";"Hydralisk";"Larva";568;2
"Unit";"Hydralisk";"Larva";568;2
"Unit";"Hydralisk";"Larva";568;2
"Unit";"Hydralisk";"Larva";568;2
"Unit";"Hydralisk";"Larva";574;2
"Unit";"Hydralisk";"Larva";574;2
"Unit";"Hydralisk";"Larva";574;2
"Unit";"Hydralisk";"Larva";574;2
"Unit";"Hydralisk";"Larva";574;2
"Unit";"Hydralisk";"Larva";574;2
"Unit";"Hydralisk";"Larva";574;2
"Unit";"Hydralisk";"Larva";574;2
"Unit";"Hydralisk";"Larva";574;2
"Unit";"Hydralisk";"Larva";574;2
"Unit";"Hydralisk";"Larva";574;2
"Building";"CreepTumor";NA;594;0
"Unit";"Zergling";"Larva";594;1
"Unit";"Zergling";"Larva";594;1
"Unit";"Zergling";"Larva";594;1
"Unit";"Zergling";"Larva";594;1
"Unit";"Zergling";"Larva";594;1
"Unit";"Zergling";"Larva";594;1
"Unit";"Zergling";"Larva";594;1
"Unit";"Zergling";"Larva";594;1
"Unit";"Zergling";"Larva";594;1
"Unit";"Zergling";"Larva";594;1
"Unit";"Zergling";"Larva";594;1
"Unit";"Zergling";"Larva";594;1
"Unit";"Zergling";"Larva";594;1
"Unit";"Zergling";"Larva";594;1
"Unit";"Hydralisk";"Larva";594;2
"Unit";"Hydralisk";"Larva";594;2
"Unit";"Hydralisk";"Larva";594;2
"Unit";"Hydralisk";"Larva";594;2
"Building";"CreepTumor";NA;638;0
"Building";"CreepTumor";NA;638;0
"Unit";"Baneling";"Zergling";638;0
"Unit";"Baneling";"Zergling";638;0
"Unit";"Baneling";"Zergling";638;0
"Unit";"Baneling";"Zergling";638;0
"Unit";"Baneling";"Zergling";638;0
"Unit";"Baneling";"Zergling";638;0
"Unit";"Baneling";"Zergling";638;0
"Unit";"Baneling";"Zergling";638;0
"Unit";"Baneling";"Zergling";638;0
"Unit";"Zergling";"Larva";638;1
"Unit";"Zergling";"Larva";638;1
"Unit";"Zergling";"Larva";638;1
"Unit";"Zergling";"Larva";638;1
"Unit";"Zergling";"Larva";638;1
"Unit";"Zergling";"Larva";638;1
"Unit";"Zergling";"Larva";638;1
"Unit";"Zergling";"Larva";638;1
"Unit";"Zergling";"Larva";638;1
"Unit";"Zergling";"Larva";638;1
"Unit";"Zergling";"Larva";638;1
"Unit";"Zergling";"Larva";638;1
"Unit";"Zergling";"Larva";638;1
"Unit";"Zergling";"Larva";638;1
"Unit";"Zergling";"Larva";638;1
"Unit";"Zergling";"Larva";638;1
"Unit";"Zergling";"Larva";638;1
"Unit";"Zergling";"Larva";638;1
"Unit";"Zergling";"Larva";638;1
"Unit";"Zergling";"Larva";638;1
"Unit";"Zergling";"Larva";638;1
"Unit";"Zergling";"Larva";638;1
"Unit";"Zergling";"Larva";638;1
"Unit";"Zergling";"Larva";638;1
"Unit";"Zergling";"Larva";638;1
"Unit";"Zergling";"Larva";638;1
"Unit";"Zergling";"Larva";638;1
"Unit";"Zergling";"Larva";638;1
"Building";"Spire";NA;594;0
"Unit";"Hydralisk";"Larva";638;2
"Unit";"Hydralisk";"Larva";638;2
"Unit";"Hydralisk";"Larva";670;2
"Unit";"Hydralisk";"Larva";670;2
"Unit";"Hydralisk";"Larva";670;2
"Unit";"Hydralisk";"Larva";670;2
"Unit";"Hydralisk";"Larva";670;2
"Unit";"Hydralisk";"Larva";670;2
"Unit";"Hydralisk";"Larva";670;2
"Unit";"Hydralisk";"Larva";670;2
"Unit";"Hydralisk";"Larva";670;2
"Building";"Hatchery";NA;638;0
"Unit";"Corruptor";"Larva";670;2
"Unit";"Corruptor";"Larva";670;2
"Unit";"Corruptor";"Larva";670;2
"Unit";"Corruptor";"Larva";670;2
"Building";"Hatchery";NA;666;0
"Unit";"Corruptor";"Larva";688;2
"Unit";"Corruptor";"Larva";688;2
"Building";"CreepTumor";NA;696;0
"Unit";"Overlord";"Larva";696;0
"Unit";"Overlord";"Larva";696;0
"Unit";"Overlord";"Larva";696;0
"Building";"Extractor";NA;696;0
"Building";"Extractor";NA;696;0
"Unit";"Zergling";"Larva";700;1
"Unit";"Zergling";"Larva";700;1
"Unit";"Zergling";"Larva";700;1
"Unit";"Zergling";"Larva";700;1
"Unit";"Zergling";"Larva";700;1
"Unit";"Zergling";"Larva";700;1
"Unit";"Zergling";"Larva";700;1
"Unit";"Zergling";"Larva";700;1
"Unit";"Zergling";"Larva";700;1
"Unit";"Zergling";"Larva";700;1
"Unit";"Zergling";"Larva";700;1
"Unit";"Zergling";"Larva";700;1
"Unit";"Zergling";"Larva";700;1
"Unit";"Zergling";"Larva";700;1
"Unit";"Zergling";"Larva";700;1
"Unit";"Zergling";"Larva";700;1
"Unit";"Baneling";"Zergling";700;0
"Unit";"Baneling";"Zergling";700;0
"Unit";"Baneling";"Zergling";700;0
"Unit";"Baneling";"Zergling";700;0
"Unit";"Baneling";"Zergling";700;0
"Unit";"Baneling";"Zergling";700;0
"Unit";"Baneling";"Zergling";700;0
"Unit";"Baneling";"Zergling";700;0
"Unit";"Corruptor";"Larva";700;2
"Unit";"Corruptor";"Larva";700;2
"Unit";"Zergling";"Larva";723;1
"Unit";"Zergling";"Larva";723;1
"Unit";"Zergling";"Larva";723;1
"Unit";"Zergling";"Larva";723;1
"Unit";"Zergling";"Larva";723;1
"Unit";"Zergling";"Larva";723;1
"Unit";"Zergling";"Larva";723;1
"Unit";"Zergling";"Larva";723;1
"Unit";"Zergling";"Larva";723;1
"Unit";"Zergling";"Larva";723;1
"Unit";"Corruptor";"Larva";723;2
"Unit";"Corruptor";"Larva";723;2
"Unit";"Corruptor";"Larva";723;2
"Unit";"Corruptor";"Larva";723;2
"Unit";"Zergling";"Larva";723;1
"Unit";"Zergling";"Larva";723;1
"Unit";"Corruptor";"Larva";723;2
"Unit";"Corruptor";"Larva";723;2
"Unit";"Zergling";"Larva";745;1
"Unit";"Zergling";"Larva";745;1
"Unit";"Zergling";"Larva";745;1
"Unit";"Zergling";"Larva";745;1
"Unit";"Zergling";"Larva";745;1
"Unit";"Zergling";"Larva";745;1
"Unit";"Zergling";"Larva";745;1
"Unit";"Zergling";"Larva";745;1
"Unit";"Zergling";"Larva";745;1
"Unit";"Zergling";"Larva";745;1
"Unit";"Corruptor";"Larva";741;2
"Unit";"Corruptor";"Larva";741;2
"Unit";"Zergling";"Larva";761;1
"Unit";"Zergling";"Larva";761;1
"Unit";"Zergling";"Larva";761;1
"Unit";"Zergling";"Larva";761;1
"Unit";"Zergling";"Larva";761;1
"Unit";"Zergling";"Larva";761;1
"Unit";"Corruptor";"Larva";747;2
"Unit";"Hydralisk";"Larva";772;2
"Unit";"Hydralisk";"Larva";772;2
"Unit";"Hydralisk";"Larva";772;2
"Unit";"Hydralisk";"Larva";772;2
"Unit";"Zergling";"Larva";772;1
"Unit";"Zergling";"Larva";772;1
"Unit";"Zergling";"Larva";772;1
"Unit";"Zergling";"Larva";772;1
"Unit";"Zergling";"Larva";772;1
"Unit";"Zergling";"Larva";772;1
"Unit";"Zergling";"Larva";772;1
"Unit";"Zergling";"Larva";772;1
"Unit";"Zergling";"Larva";780;1
"Unit";"Zergling";"Larva";780;1
"Unit";"Zergling";"Larva";780;1
"Unit";"Zergling";"Larva";780;1
"Unit";"Zergling";"Larva";792;1
"Unit";"Zergling";"Larva";792;1
"Unit";"Zergling";"Larva";792;1
"Unit";"Zergling";"Larva";792;1
"Unit";"Zergling";"Larva";792;1
"Unit";"Zergling";"Larva";792;1
"Unit";"Zergling";"Larva";792;1
"Unit";"Zergling";"Larva";792;1
"Building";"Extractor";NA;805;0
"Building";"Extractor";NA;805;0
"Unit";"Zergling";"Larva";812;1
"Unit";"Zergling";"Larva";812;1
"Unit";"Zergling";"Larva";812;1
"Unit";"Zergling";"Larva";812;1
"Unit";"Zergling";"Larva";812;1
"Unit";"Zergling";"Larva";812;1
"Unit";"Zergling";"Larva";812;1
"Unit";"Zergling";"Larva";812;1
"Unit";"Zergling";"Larva";812;1
"Unit";"Zergling";"Larva";812;1
"Unit";"Zergling";"Larva";812;1
"Unit";"Zergling";"Larva";812;1
"Unit";"Hydralisk";"Larva";812;2
"Unit";"Hydralisk";"Larva";812;2
"Unit";"Hydralisk";"Larva";812;2
"Unit";"Hydralisk";"Larva";812;2
"Unit";"Zergling";"Larva";824;1
"Unit";"Zergling";"Larva";824;1
"Unit";"Overlord";"Larva";834;0
"Building";"SpawningPool";NA;824;0
"Building";"Hatchery";NA;812;0
"Unit";"Overlord";"Larva";834;0
"Unit";"Overlord";"Larva";834;0
"Unit";"Overlord";"Larva";834;0
"Unit";"Overlord";"Larva";834;0
"Unit";"Overlord";"Larva";839;0
"Unit";"Overlord";"Larva";839;0
"Building";"Hatchery";NA;834;0
"Building";"HydraliskDen";NA;839;0
"Unit";"Zergling";"Larva";839;1
"Unit";"Zergling";"Larva";839;1
"Unit";"Zergling";"Larva";839;1
"Unit";"Zergling";"Larva";839;1
"Unit";"Zergling";"Larva";839;1
"Unit";"Zergling";"Larva";839;1
