"type";"unit_name";"on_building";"total_supply";"supply"
"Unit";"Overlord";"Larva";13;0
"Building";"Extractor";NA;19;0
"Unit";"Overlord";"Larva";19;0
"Building";"Hatchery";NA;17;0
"Building";"SpawningPool";NA;19;0
"Unit";"Overlord";"Larva";22;0
"Unit";"Zergling";"Larva";22;1
"Unit";"Zergling";"Larva";22;1
"Unit";"Zergling";"Larva";25;1
"Unit";"Zergling";"Larva";25;1
"Unit";"Queen";"Hatchery";22;2
"Unit";"Queen";"Hatchery";22;2
"Unit";"Zergling";"Larva";28;1
"Unit";"Zergling";"Larva";28;1
"Unit";"Zergling";"Larva";28;1
"Unit";"Zergling";"Larva";28;1
"Building";"CreepTumorQueen";NA;34;0
"Unit";"Overlord";"Larva";38;0
"Unit";"Queen";"Hatchery";32;2
"Building";"CreepTumor";NA;46;0
"Unit";"Overlord";"Larva";50;0
"Building";"CreepTumorQueen";NA;50;0
"Building";"CreepTumorQueen";NA;50;0
"Building";"Extractor";NA;50;0
"Building";"Extractor";NA;50;0
"Building";"RoachWarren";NA;46;0
"Building";"SporeCrawler";NA;55;0
"Building";"SporeCrawler";NA;55;0
"Building";"CreepTumor";NA;55;0
"Building";"CreepTumor";NA;55;0
"Building";"CreepTumor";NA;61;0
"Building";"Hatchery";NA;50;0
"Building";"CreepTumor";NA;66;0
"Building";"CreepTumor";NA;66;0
"Building";"CreepTumor";NA;66;0
"Unit";"Roach";"Larva";66;2
"Unit";"Roach";"Larva";66;2
"Unit";"Roach";"Larva";66;2
"Unit";"Roach";"Larva";66;2
"Unit";"Roach";"Larva";66;2
"Unit";"Roach";"Larva";66;2
"Unit";"Roach";"Larva";66;2
"Unit";"Roach";"Larva";66;2
"Unit";"Overlord";"Larva";66;0
"Unit";"Overlord";"Larva";66;0
"Unit";"Overlord";"Larva";66;0
"Upgrade";"Burrow";"Hatchery";64;0
"Upgrade";"GlialReconstitution";"RoachWarren";62;0
"Unit";"Overlord";"Larva";82;0
"Unit";"Overlord";"Larva";82;0
"Building";"Extractor";NA;82;0
"Building";"CreepTumor";NA;82;0
"Building";"HydraliskDen";NA;82;0
"Building";"CreepTumor";NA;83;0
"Building";"CreepTumor";NA;86;0
"Building";"SporeCrawler";NA;86;0
"Building";"CreepTumor";NA;95;0
"Building";"CreepTumor";NA;97;0
"Building";"CreepTumor";NA;97;0
"Building";"Extractor";NA;98;0
"Unit";"Hydralisk";"Larva";98;2
"Unit";"Hydralisk";"Larva";98;2
"Building";"BanelingNest";NA;95;0
"Unit";"Hydralisk";"Larva";98;2
"Building";"CreepTumor";NA;106;0
"Unit";"Overlord";"Larva";106;0
"Building";"CreepTumor";NA;110;0
"Unit";"Overlord";"Larva";106;0
"Unit";"Overlord";"Larva";106;0
"Unit";"Overlord";"Larva";106;0
"Unit";"Overlord";"Larva";106;0
"Unit";"Overlord";"Larva";106;0
"Building";"CreepTumor";NA;112;0
"Upgrade";"EvolveGroovedSpines";"HydraliskDen";97;0
"Unit";"Hydralisk";"Larva";112;2
"Unit";"Hydralisk";"Larva";112;2
"Unit";"Hydralisk";"Larva";112;2
"Unit";"Hydralisk";"Larva";112;2
"Unit";"Hydralisk";"Larva";112;2
"Unit";"Hydralisk";"Larva";112;2
"Unit";"Hydralisk";"Larva";112;2
"Building";"CreepTumor";NA;112;0
"Unit";"Zergling";"Larva";112;1
"Unit";"Zergling";"Larva";112;1
"Unit";"Zergling";"Larva";112;1
"Unit";"Zergling";"Larva";112;1
"Unit";"Zergling";"Larva";112;1
"Unit";"Zergling";"Larva";112;1
"Building";"CreepTumor";NA;126;0
"Unit";"Hydralisk";"Larva";112;2
"Unit";"Hydralisk";"Larva";112;2
"Unit";"Hydralisk";"Larva";112;2
"Building";"CreepTumor";NA;126;0
"Unit";"Zergling";"Larva";126;1
"Unit";"Zergling";"Larva";126;1
"Unit";"Zergling";"Larva";126;1
"Unit";"Zergling";"Larva";126;1
"Unit";"Zergling";"Larva";126;1
"Unit";"Zergling";"Larva";126;1
"Unit";"Hydralisk";"Larva";126;2
"Unit";"Hydralisk";"Larva";126;2
"Unit";"Hydralisk";"Larva";126;2
"Unit";"Hydralisk";"Larva";126;2
"Unit";"Zergling";"Larva";138;1
"Unit";"Zergling";"Larva";138;1
"Unit";"Zergling";"Larva";138;1
"Unit";"Zergling";"Larva";138;1
"Unit";"Zergling";"Larva";138;1
"Unit";"Zergling";"Larva";138;1
"Unit";"Zergling";"Larva";138;1
"Unit";"Zergling";"Larva";138;1
"Unit";"Zergling";"Larva";138;1
"Unit";"Zergling";"Larva";138;1
"Unit";"Zergling";"Larva";138;1
"Unit";"Zergling";"Larva";138;1
"Unit";"Zergling";"Larva";138;1
"Unit";"Zergling";"Larva";138;1
"Unit";"Baneling";"Zergling";138;0
"Unit";"Baneling";"Zergling";138;0
"Unit";"Baneling";"Zergling";138;0
"Unit";"Baneling";"Zergling";138;0
"Unit";"Baneling";"Zergling";138;0
"Unit";"Baneling";"Zergling";138;0
"Unit";"Baneling";"Zergling";138;0
"Unit";"Baneling";"Zergling";138;0
"Unit";"Baneling";"Zergling";138;0
"Unit";"Baneling";"Zergling";140;0
"Building";"CreepTumor";NA;144;0
"Building";"CreepTumor";NA;152;0
"Building";"CreepTumor";NA;152;0
"Unit";"Zergling";"Larva";152;1
"Unit";"Zergling";"Larva";152;1
"Unit";"Zergling";"Larva";152;1
"Unit";"Zergling";"Larva";152;1
"Unit";"Zergling";"Larva";152;1
"Unit";"Zergling";"Larva";152;1
"Unit";"Zergling";"Larva";152;1
"Unit";"Zergling";"Larva";152;1
"Upgrade";"EvolveMuscularAugments";"HydraliskDen";126;0
"Unit";"Overlord";"Larva";160;0
"Unit";"Overlord";"Larva";166;0
"Unit";"Overlord";"Larva";166;0
"Unit";"Zergling";"Larva";174;1
"Unit";"Zergling";"Larva";174;1
"Unit";"Zergling";"Larva";174;1
"Unit";"Zergling";"Larva";174;1
"Unit";"Zergling";"Larva";174;1
"Unit";"Zergling";"Larva";174;1
"Unit";"Zergling";"Larva";174;1
"Unit";"Zergling";"Larva";174;1
"Unit";"Zergling";"Larva";174;1
"Unit";"Zergling";"Larva";174;1
"Unit";"Zergling";"Larva";174;1
"Unit";"Zergling";"Larva";174;1
"Unit";"Zergling";"Larva";174;1
"Unit";"Zergling";"Larva";174;1
"Unit";"Zergling";"Larva";174;1
"Unit";"Zergling";"Larva";174;1
"Unit";"Zergling";"Larva";174;1
"Unit";"Zergling";"Larva";174;1
"Unit";"Zergling";"Larva";174;1
"Unit";"Zergling";"Larva";174;1
"Unit";"Zergling";"Larva";174;1
"Unit";"Zergling";"Larva";174;1
"Unit";"Zergling";"Larva";174;1
"Unit";"Zergling";"Larva";174;1
"Unit";"Zergling";"Larva";174;1
"Unit";"Zergling";"Larva";174;1
"Unit";"Baneling";"Zergling";174;0
"Unit";"Baneling";"Zergling";174;0
"Unit";"Baneling";"Zergling";174;0
"Unit";"Baneling";"Zergling";174;0
"Unit";"Baneling";"Zergling";174;0
"Unit";"Baneling";"Zergling";174;0
"Unit";"Baneling";"Zergling";174;0
"Unit";"Baneling";"Zergling";174;0
"Unit";"Baneling";"Zergling";174;0
"Unit";"Zergling";"Larva";174;1
"Unit";"Zergling";"Larva";174;1
"Unit";"Zergling";"Larva";174;1
"Unit";"Zergling";"Larva";174;1
"Unit";"Zergling";"Larva";174;1
"Unit";"Zergling";"Larva";174;1
"Unit";"Zergling";"Larva";174;1
"Unit";"Zergling";"Larva";174;1
"Unit";"Roach";"Larva";200;2
"Unit";"Roach";"Larva";200;2
"Unit";"Roach";"Larva";200;2
"Unit";"Zergling";"Larva";214;1
"Unit";"Zergling";"Larva";214;1
"Unit";"Zergling";"Larva";214;1
"Unit";"Zergling";"Larva";214;1
"Unit";"Zergling";"Larva";214;1
"Unit";"Zergling";"Larva";214;1
"Unit";"Zergling";"Larva";214;1
"Unit";"Zergling";"Larva";214;1
"Unit";"Zergling";"Larva";214;1
"Unit";"Zergling";"Larva";214;1
"Unit";"Zergling";"Larva";214;1
"Unit";"Zergling";"Larva";214;1
"Unit";"Roach";"Larva";226;2
"Unit";"Roach";"Larva";226;2
"Unit";"Roach";"Larva";226;2
"Unit";"Roach";"Larva";226;2
"Unit";"Roach";"Larva";226;2
"Unit";"Roach";"Larva";226;2
"Unit";"Roach";"Larva";226;2
"Unit";"Roach";"Larva";226;2
"Unit";"Roach";"Larva";226;2
"Building";"Hatchery";NA;208;0
"Unit";"Hydralisk";"Larva";244;2
"Unit";"Hydralisk";"Larva";244;2
"Unit";"Hydralisk";"Larva";244;2
"Unit";"Hydralisk";"Larva";244;2
"Unit";"Hydralisk";"Larva";244;2
"Unit";"Hydralisk";"Larva";244;2
"Unit";"Hydralisk";"Larva";244;2
"Unit";"Hydralisk";"Larva";244;2
"Unit";"Hydralisk";"Larva";260;2
"Unit";"Hydralisk";"Larva";260;2
"Unit";"Hydralisk";"Larva";260;2
"Unit";"Hydralisk";"Larva";260;2
"Unit";"Hydralisk";"Larva";260;2
"Unit";"Hydralisk";"Larva";260;2
"Unit";"Hydralisk";"Larva";260;2
"Unit";"Hydralisk";"Larva";260;2
"Unit";"Hydralisk";"Larva";260;2
"Unit";"Hydralisk";"Larva";260;2
"Unit";"Roach";"Larva";260;2
"Unit";"Roach";"Larva";260;2
"Unit";"Roach";"Larva";260;2
"Unit";"Roach";"Larva";260;2
"Unit";"Roach";"Larva";260;2
"Unit";"Roach";"Larva";260;2
"Unit";"Roach";"Larva";260;2
"Unit";"Roach";"Larva";260;2
"Unit";"Roach";"Larva";260;2
"Building";"CreepTumor";NA;298;0
"Unit";"Hydralisk";"Larva";280;2
"Unit";"Hydralisk";"Larva";280;2
"Unit";"Hydralisk";"Larva";280;2
"Building";"CreepTumor";NA;298;0
"Building";"CreepTumor";NA;298;0
"Unit";"Queen";"Hatchery";280;2
"Unit";"Hydralisk";"Larva";316;2
"Unit";"Hydralisk";"Larva";316;2
"Unit";"Hydralisk";"Larva";316;2
"Unit";"Hydralisk";"Larva";316;2
"Unit";"Hydralisk";"Larva";316;2
"Unit";"Hydralisk";"Larva";316;2
"Unit";"Hydralisk";"Larva";316;2
"Unit";"Hydralisk";"Larva";316;2
"Unit";"Hydralisk";"Larva";316;2
"Unit";"Hydralisk";"Larva";316;2
"Unit";"Hydralisk";"Larva";316;2
"Unit";"Hydralisk";"Larva";316;2
"Unit";"Hydralisk";"Larva";316;2
"Unit";"Hydralisk";"Larva";316;2
"Unit";"Zergling";"Larva";344;1
"Unit";"Zergling";"Larva";344;1
"Unit";"Zergling";"Larva";344;1
"Unit";"Zergling";"Larva";344;1
"Unit";"Zergling";"Larva";344;1
"Unit";"Zergling";"Larva";344;1
"Unit";"Zergling";"Larva";344;1
"Unit";"Zergling";"Larva";344;1
"Unit";"Zergling";"Larva";344;1
"Unit";"Zergling";"Larva";344;1
"Unit";"Hydralisk";"Larva";344;2
"Unit";"Hydralisk";"Larva";344;2
"Unit";"Hydralisk";"Larva";344;2
"Unit";"Hydralisk";"Larva";344;2
"Unit";"Hydralisk";"Larva";344;2
"Unit";"Hydralisk";"Larva";344;2
"Unit";"Hydralisk";"Larva";344;2
"Unit";"Hydralisk";"Larva";344;2
"Unit";"Hydralisk";"Larva";344;2
"Unit";"Hydralisk";"Larva";344;2
"Unit";"Hydralisk";"Larva";344;2
"Unit";"Roach";"Larva";376;2
"Unit";"Roach";"Larva";376;2
"Unit";"Roach";"Larva";376;2
"Unit";"Roach";"Larva";376;2
"Unit";"Roach";"Larva";376;2
"Unit";"Roach";"Larva";376;2
"Unit";"Roach";"Larva";376;2
"Unit";"Roach";"Larva";376;2
