"type";"unit_name";"on_building";"total_supply";"supply"
"Unit";"Overlord";"Larva";13;0
"Building";"Extractor";NA;18;0
"Building";"Hatchery";NA;16;0
"Building";"SpawningPool";NA;19;0
"Unit";"Overlord";"Larva";24;0
"Unit";"Queen";"Hatchery";24;2
"Unit";"Zergling";"Larva";26;1
"Unit";"Zergling";"Larva";26;1
"Unit";"Zergling";"Larva";26;1
"Unit";"Zergling";"Larva";26;1
"Unit";"Zergling";"Larva";26;1
"Unit";"Zergling";"Larva";26;1
"Building";"CreepTumorQueen";NA;31;0
"Building";"Hatchery";NA;23;0
"Unit";"Queen";"Hatchery";29;2
"Unit";"Zergling";"Larva";39;1
"Unit";"Zergling";"Larva";39;1
"Unit";"Zergling";"Larva";39;1
"Unit";"Zergling";"Larva";39;1
"Unit";"Zergling";"Larva";40;1
"Unit";"Zergling";"Larva";40;1
"Building";"CreepTumor";NA;40;0
"Unit";"Overlord";"Larva";40;0
"Unit";"Queen";"Hatchery";39;2
"Unit";"Overlord";"Larva";48;0
"Unit";"Overlord";"Larva";48;0
"Building";"Extractor";NA;50;0
"Building";"Extractor";NA;50;0
"Building";"CreepTumorQueen";NA;52;0
"Building";"CreepTumor";NA;61;0
"Building";"CreepTumor";NA;63;0
"Building";"RoachWarren";NA;56;0
"Building";"CreepTumorQueen";NA;63;0
"Unit";"Roach";"Larva";68;2
"Building";"EvolutionChamber";NA;63;0
"Unit";"Roach";"Larva";68;2
"Unit";"Roach";"Larva";68;2
"Unit";"Roach";"Larva";68;2
"Unit";"Roach";"Larva";68;2
"Unit";"Roach";"Larva";68;2
"Unit";"Overlord";"Larva";68;0
"Unit";"Queen";"Hatchery";63;2
"Unit";"Overlord";"Larva";68;0
"Unit";"Roach";"Larva";80;2
"Unit";"Roach";"Larva";80;2
"Unit";"Roach";"Larva";80;2
"Unit";"Roach";"Larva";80;2
"Unit";"Roach";"Larva";80;2
"Unit";"Overlord";"Larva";82;0
"Unit";"Roach";"Larva";88;2
"Unit";"Queen";"Hatchery";80;2
"Building";"CreepTumor";NA;92;0
"Building";"CreepTumor";NA;92;0
"Building";"CreepTumor";NA;100;0
"Unit";"Overlord";"Larva";106;0
"Unit";"Roach";"Larva";106;2
"Unit";"Roach";"Larva";106;2
"Unit";"Roach";"Larva";106;2
"Unit";"Roach";"Larva";106;2
"Unit";"Roach";"Larva";106;2
"Building";"CreepTumor";NA;106;0
"Building";"CreepTumorQueen";NA;106;0
"Building";"CreepTumorQueen";NA;106;0
"Building";"CreepTumorQueen";NA;107;0
"Unit";"Overlord";"Larva";106;0
"Building";"HydraliskDen";NA;106;0
"Upgrade";"GlialReconstitution";"RoachWarren";96;0
"Building";"Extractor";NA;117;0
"Unit";"Overlord";"Larva";128;0
"Building";"CreepTumor";NA;131;0
"Building";"Extractor";NA;130;0
"Building";"CreepTumor";NA;135;0
"Building";"CreepTumor";NA;135;0
"Building";"CreepTumor";NA;135;0
"Building";"Extractor";NA;130;0
"Building";"CreepTumor";NA;135;0
"Building";"CreepTumor";NA;135;0
"Building";"CreepTumorQueen";NA;135;0
"Upgrade";"ZergMissileWeaponsLevel1";"EvolutionChamber";100;0
"Building";"CreepTumorQueen";NA;138;0
"Unit";"Overlord";"Larva";135;0
"Unit";"Zergling";"Larva";138;1
"Unit";"Zergling";"Larva";138;1
"Unit";"Zergling";"Larva";138;1
"Unit";"Zergling";"Larva";138;1
"Building";"Spire";NA;117;0
"Unit";"Overlord";"Larva";138;0
"Building";"CreepTumor";NA;146;0
"Building";"CreepTumor";NA;148;0
"Building";"CreepTumor";NA;148;0
"Building";"CreepTumor";NA;148;0
"Building";"CreepTumor";NA;148;0
"Building";"CreepTumorQueen";NA;148;0
"Building";"CreepTumor";NA;148;0
"Unit";"Mutalisk";"Larva";148;2
"Unit";"Mutalisk";"Larva";148;2
"Unit";"Mutalisk";"Larva";148;2
"Unit";"Mutalisk";"Larva";148;2
"Unit";"Mutalisk";"Larva";148;2
"Unit";"Zergling";"Larva";148;1
"Unit";"Zergling";"Larva";148;1
"Unit";"Zergling";"Larva";148;1
"Unit";"Zergling";"Larva";148;1
"Unit";"Zergling";"Larva";148;1
"Unit";"Zergling";"Larva";148;1
"Unit";"Zergling";"Larva";148;1
"Unit";"Zergling";"Larva";148;1
"Unit";"Mutalisk";"Larva";148;2
"Unit";"Zergling";"Larva";148;1
"Unit";"Zergling";"Larva";148;1
"Unit";"Overlord";"Larva";148;0
"Unit";"Overlord";"Larva";148;0
"Unit";"Overlord";"Larva";148;0
"Unit";"Overlord";"Larva";158;0
"Unit";"Overlord";"Larva";158;0
"Building";"Hatchery";NA;138;0
"Unit";"Overlord";"Larva";170;0
"Unit";"Mutalisk";"Larva";170;2
"Unit";"Overlord";"Larva";170;0
"Unit";"Mutalisk";"Larva";170;2
"Unit";"Mutalisk";"Larva";170;2
"Unit";"Overlord";"Larva";170;0
"Unit";"Overlord";"Larva";170;0
"Unit";"Mutalisk";"Larva";170;2
"Unit";"Mutalisk";"Larva";170;2
"Unit";"Mutalisk";"Larva";170;2
"Unit";"Mutalisk";"Larva";170;2
"Unit";"Mutalisk";"Larva";174;2
"Unit";"Mutalisk";"Larva";178;2
"Unit";"Mutalisk";"Larva";178;2
"Unit";"Mutalisk";"Larva";184;2
"Unit";"Mutalisk";"Larva";184;2
"Unit";"Zergling";"Larva";194;1
"Unit";"Zergling";"Larva";194;1
"Unit";"Zergling";"Larva";194;1
"Unit";"Zergling";"Larva";194;1
"Unit";"Zergling";"Larva";194;1
"Unit";"Zergling";"Larva";194;1
"Unit";"Zergling";"Larva";194;1
"Unit";"Zergling";"Larva";194;1
"Unit";"Zergling";"Larva";194;1
"Unit";"Zergling";"Larva";194;1
"Unit";"Zergling";"Larva";194;1
"Unit";"Zergling";"Larva";194;1
"Unit";"Zergling";"Larva";194;1
"Unit";"Zergling";"Larva";194;1
"Unit";"Zergling";"Larva";194;1
"Unit";"Zergling";"Larva";194;1
"Unit";"Zergling";"Larva";194;1
"Unit";"Zergling";"Larva";194;1
"Unit";"Zergling";"Larva";194;1
"Unit";"Zergling";"Larva";194;1
"Unit";"Mutalisk";"Larva";186;2
"Building";"CreepTumor";NA;200;0
"Unit";"Queen";"Hatchery";184;2
"Upgrade";"ZergMissileWeaponsLevel2";"EvolutionChamber";148;0
"Building";"Extractor";NA;198;0
"Building";"Extractor";NA;200;0
"Unit";"Mutalisk";"Larva";200;2
"Unit";"Mutalisk";"Larva";200;2
"Unit";"Zergling";"Larva";222;1
"Unit";"Zergling";"Larva";222;1
"Unit";"Zergling";"Larva";222;1
"Unit";"Zergling";"Larva";222;1
"Unit";"Mutalisk";"Larva";202;2
"Unit";"Mutalisk";"Larva";226;2
"Unit";"Overlord";"Larva";226;0
"Unit";"Zergling";"Larva";226;1
"Unit";"Zergling";"Larva";226;1
"Unit";"Zergling";"Larva";226;1
"Unit";"Zergling";"Larva";226;1
"Unit";"Zergling";"Larva";226;1
"Unit";"Zergling";"Larva";226;1
"Unit";"Zergling";"Larva";226;1
"Unit";"Zergling";"Larva";226;1
"Unit";"Zergling";"Larva";226;1
"Unit";"Zergling";"Larva";226;1
"Unit";"Zergling";"Larva";226;1
"Unit";"Zergling";"Larva";226;1
"Unit";"Zergling";"Larva";226;1
"Unit";"Zergling";"Larva";226;1
"Unit";"Zergling";"Larva";228;1
"Unit";"Zergling";"Larva";228;1
"Unit";"Mutalisk";"Larva";226;2
"Unit";"Mutalisk";"Larva";236;2
"Unit";"Mutalisk";"Larva";236;2
"Unit";"Mutalisk";"Larva";236;2
"Unit";"Mutalisk";"Larva";240;2
"Unit";"Mutalisk";"Larva";240;2
"Unit";"Mutalisk";"Larva";256;2
"Unit";"Zergling";"Larva";262;1
"Unit";"Zergling";"Larva";262;1
"Unit";"Zergling";"Larva";262;1
"Unit";"Zergling";"Larva";262;1
"Unit";"Zergling";"Larva";262;1
"Unit";"Zergling";"Larva";262;1
"Unit";"Zergling";"Larva";262;1
"Unit";"Zergling";"Larva";262;1
"Unit";"Zergling";"Larva";262;1
"Unit";"Zergling";"Larva";262;1
"Unit";"Zergling";"Larva";262;1
"Unit";"Zergling";"Larva";262;1
"Unit";"Zergling";"Larva";262;1
"Unit";"Zergling";"Larva";262;1
"Unit";"Zergling";"Larva";262;1
"Unit";"Zergling";"Larva";262;1
"Unit";"Zergling";"Larva";262;1
"Unit";"Zergling";"Larva";262;1
"Unit";"Zergling";"Larva";262;1
"Unit";"Zergling";"Larva";262;1
"Unit";"Zergling";"Larva";262;1
"Unit";"Zergling";"Larva";262;1
"Unit";"Zergling";"Larva";262;1
"Unit";"Zergling";"Larva";262;1
"Unit";"Zergling";"Larva";262;1
"Unit";"Zergling";"Larva";262;1
"Unit";"Zergling";"Larva";262;1
"Unit";"Zergling";"Larva";262;1
"Unit";"Zergling";"Larva";262;1
"Unit";"Zergling";"Larva";262;1
"Unit";"Mutalisk";"Larva";260;2
"Unit";"Mutalisk";"Larva";262;2
"Building";"Hatchery";NA;226;0
"Unit";"Mutalisk";"Larva";270;2
"Unit";"Mutalisk";"Larva";272;2
"Unit";"Mutalisk";"Larva";280;2
"Unit";"Mutalisk";"Larva";300;2
"Unit";"Mutalisk";"Larva";300;2
"Building";"Extractor";NA;314;0
"Building";"CreepTumor";NA;324;0
"Unit";"Mutalisk";"Larva";324;2
