"type";"unit_name";"on_building";"total_supply";"supply"
"Unit";"Overlord";"Larva";13;0
"Building";"Extractor";NA;17;0
"Building";"Hatchery";NA;16;0
"Building";"SpawningPool";NA;19;0
"Unit";"Overlord";"Larva";22;0
"Unit";"Queen";"Hatchery";23;2
"Unit";"Queen";"Hatchery";23;2
"Unit";"Overlord";"Larva";27;0
"Unit";"Queen";"Hatchery";32;2
"Unit";"Overlord";"Larva";34;0
"Unit";"Zergling";"Larva";36;1
"Unit";"Zergling";"Larva";36;1
"Unit";"Zergling";"Larva";38;1
"Unit";"Zergling";"Larva";38;1
"Building";"CreepTumorQueen";NA;40;0
"Unit";"Zergling";"Larva";40;1
"Unit";"Zergling";"Larva";40;1
"Unit";"Zergling";"Larva";40;1
"Unit";"Zergling";"Larva";40;1
"Building";"SporeCrawler";NA;49;0
"Building";"SporeCrawler";NA;49;0
"Unit";"Overlord";"Larva";53;0
"Building";"CreepTumor";NA;57;0
"Building";"CreepTumorQueen";NA;59;0
"Unit";"Overlord";"Larva";57;0
"Unit";"Queen";"Hatchery";53;2
"Building";"CreepTumor";NA;66;0
"Building";"Hatchery";NA;48;0
"Building";"SporeCrawler";NA;66;0
"Building";"RoachWarren";NA;60;0
"Unit";"Zergling";"Larva";71;1
"Unit";"Zergling";"Larva";71;1
"Unit";"Zergling";"Larva";71;1
"Unit";"Zergling";"Larva";71;1
"Unit";"Zergling";"Larva";71;1
"Unit";"Zergling";"Larva";71;1
"Unit";"Zergling";"Larva";71;1
"Unit";"Zergling";"Larva";71;1
"Unit";"Zergling";"Larva";71;1
"Unit";"Zergling";"Larva";71;1
"Unit";"Zergling";"Larva";71;1
"Unit";"Zergling";"Larva";71;1
"Unit";"Queen";"Hatchery";66;2
"Building";"CreepTumor";NA;83;0
"Unit";"Overlord";"Larva";85;0
"Unit";"Overlord";"Larva";85;0
"Unit";"Overlord";"Larva";85;0
"Unit";"Overlord";"Larva";85;0
"Unit";"Roach";"Larva";85;2
"Unit";"Roach";"Larva";85;2
"Building";"CreepTumor";NA;85;0
"Unit";"Queen";"Hatchery";83;2
"Unit";"Overlord";"Larva";85;0
"Unit";"Overlord";"Larva";85;0
"Building";"CreepTumorQueen";NA;85;0
"Unit";"Queen";"Hatchery";83;2
"Unit";"Overlord";"Larva";85;0
"Unit";"Queen";"Hatchery";85;2
"Unit";"Roach";"Larva";85;2
"Unit";"Roach";"Larva";85;2
"Unit";"Roach";"Larva";85;2
"Building";"CreepTumorQueen";NA;91;0
"Unit";"Roach";"Larva";91;2
"Unit";"Roach";"Larva";91;2
"Unit";"Roach";"Larva";91;2
"Building";"CreepTumor";NA;101;0
"Building";"Extractor";NA;101;0
"Building";"Extractor";NA;101;0
"Building";"CreepTumor";NA;108;0
"Unit";"Queen";"Hatchery";93;2
"Unit";"Queen";"Hatchery";93;2
"Building";"CreepTumor";NA;115;0
"Unit";"Roach";"Larva";109;2
"Unit";"Roach";"Larva";109;2
"Unit";"Zergling";"Larva";115;1
"Unit";"Zergling";"Larva";115;1
"Unit";"Zergling";"Larva";115;1
"Unit";"Zergling";"Larva";115;1
"Unit";"Zergling";"Larva";115;1
"Unit";"Zergling";"Larva";115;1
"Unit";"Roach";"Larva";110;2
"Building";"Extractor";NA;115;0
"Upgrade";"GlialReconstitution";"RoachWarren";91;0
"Building";"Extractor";NA;133;0
"Building";"CreepTumor";NA;139;0
"Building";"Extractor";NA;133;0
"Building";"CreepTumor";NA;139;0
"Building";"CreepTumorQueen";NA;139;0
"Unit";"Overlord";"Larva";147;0
"Unit";"Overlord";"Larva";147;0
"Unit";"Overlord";"Larva";148;0
"Unit";"Overlord";"Larva";149;0
"Unit";"Overlord";"Larva";150;0
"Building";"HydraliskDen";NA;139;0
"Building";"CreepTumor";NA;150;0
"Building";"EvolutionChamber";NA;150;0
"Building";"EvolutionChamber";NA;150;0
"Building";"CreepTumor";NA;151;0
"Unit";"Overlord";"Larva";150;0
"Unit";"Overlord";"Larva";150;0
"Unit";"Overlord";"Larva";150;0
"Unit";"Overlord";"Larva";150;0
"Building";"CreepTumor";NA;151;0
"Building";"CreepTumor";NA;151;0
"Building";"Hatchery";NA;129;0
"Unit";"Hydralisk";"Larva";152;2
"Unit";"Hydralisk";"Larva";152;2
"Building";"CreepTumorQueen";NA;152;0
"Unit";"Hydralisk";"Larva";152;2
"Unit";"Hydralisk";"Larva";152;2
"Unit";"Hydralisk";"Larva";152;2
"Unit";"Hydralisk";"Larva";152;2
"Unit";"Hydralisk";"Larva";152;2
"Unit";"Hydralisk";"Larva";152;2
"Unit";"Hydralisk";"Larva";152;2
"Unit";"Hydralisk";"Larva";152;2
"Building";"CreepTumor";NA;169;0
"Building";"CreepTumor";NA;180;0
"Building";"CreepTumor";NA;180;0
"Building";"CreepTumor";NA;180;0
"Unit";"Hydralisk";"Larva";172;2
"Building";"CreepTumor";NA;185;0
"Unit";"Hydralisk";"Larva";176;2
"Building";"Extractor";NA;180;0
"Building";"Extractor";NA;180;0
"Unit";"Zergling";"Larva";185;1
"Unit";"Zergling";"Larva";185;1
"Unit";"Zergling";"Larva";185;1
"Unit";"Zergling";"Larva";185;1
"Unit";"Zergling";"Larva";185;1
"Unit";"Zergling";"Larva";185;1
"Unit";"Zergling";"Larva";185;1
"Unit";"Zergling";"Larva";185;1
"Unit";"Zergling";"Larva";185;1
"Unit";"Zergling";"Larva";185;1
"Unit";"Zergling";"Larva";185;1
"Unit";"Zergling";"Larva";185;1
"Unit";"Zergling";"Larva";185;1
"Unit";"Zergling";"Larva";185;1
"Unit";"Zergling";"Larva";185;1
"Unit";"Zergling";"Larva";185;1
"Unit";"Zergling";"Larva";185;1
"Unit";"Zergling";"Larva";185;1
"Unit";"Zergling";"Larva";185;1
"Unit";"Zergling";"Larva";185;1
"Upgrade";"EvolveGroovedSpines";"HydraliskDen";152;0
"Building";"LurkerDenMP";NA;152;0
"Unit";"Zergling";"Larva";209;1
"Unit";"Zergling";"Larva";209;1
"Unit";"Zergling";"Larva";209;1
"Unit";"Zergling";"Larva";209;1
"Unit";"Zergling";"Larva";209;1
"Unit";"Zergling";"Larva";209;1
"Unit";"Zergling";"Larva";209;1
"Unit";"Zergling";"Larva";209;1
"Unit";"Overlord";"Larva";209;0
"Unit";"Overlord";"Larva";209;0
"Unit";"Overlord";"Larva";209;0
"Building";"CreepTumor";NA;209;0
"Building";"CreepTumor";NA;209;0
"Building";"CreepTumor";NA;220;0
"Unit";"Zergling";"Larva";220;1
"Unit";"Zergling";"Larva";220;1
"Unit";"Zergling";"Larva";220;1
"Unit";"Zergling";"Larva";220;1
"Unit";"Zergling";"Larva";220;1
"Unit";"Zergling";"Larva";220;1
"Unit";"Zergling";"Larva";220;1
"Unit";"Zergling";"Larva";220;1
"Unit";"Zergling";"Larva";220;1
"Unit";"Zergling";"Larva";220;1
"Unit";"Zergling";"Larva";220;1
"Unit";"Zergling";"Larva";220;1
"Unit";"Zergling";"Larva";220;1
"Unit";"Zergling";"Larva";220;1
"Unit";"Zergling";"Larva";220;1
"Unit";"Zergling";"Larva";220;1
"Unit";"Zergling";"Larva";220;1
"Unit";"Zergling";"Larva";220;1
"Unit";"Zergling";"Larva";220;1
"Unit";"Zergling";"Larva";220;1
"Unit";"Zergling";"Larva";220;1
"Unit";"Zergling";"Larva";220;1
"Unit";"Zergling";"Larva";220;1
"Unit";"Zergling";"Larva";220;1
"Unit";"Zergling";"Larva";220;1
"Unit";"Zergling";"Larva";220;1
"Unit";"Zergling";"Larva";220;1
"Unit";"Zergling";"Larva";220;1
"Unit";"Zergling";"Larva";248;1
"Unit";"Zergling";"Larva";248;1
"Unit";"Zergling";"Larva";248;1
"Unit";"Zergling";"Larva";248;1
"Unit";"Zergling";"Larva";248;1
"Unit";"Zergling";"Larva";248;1
"Unit";"Zergling";"Larva";248;1
"Unit";"Zergling";"Larva";248;1
"Unit";"Zergling";"Larva";248;1
"Unit";"Zergling";"Larva";248;1
"Upgrade";"ZergMissileWeaponsLevel1";"EvolutionChamber";185;0
"Upgrade";"ZergMeleeWeaponsLevel1";"EvolutionChamber";185;0
"Unit";"Hydralisk";"Larva";248;2
"Unit";"Hydralisk";"Larva";248;2
"Unit";"Hydralisk";"Larva";248;2
"Unit";"Hydralisk";"Larva";248;2
"Unit";"Hydralisk";"Larva";248;2
"Unit";"Zergling";"Larva";248;1
"Unit";"Zergling";"Larva";248;1
"Unit";"Hydralisk";"Larva";248;2
"Upgrade";"EvolveMuscularAugments";"HydraliskDen";220;0
"Building";"Hatchery";NA;209;0
"Unit";"Hydralisk";"Larva";272;2
"Unit";"Hydralisk";"Larva";272;2
"Unit";"Hydralisk";"Larva";272;2
"Unit";"Hydralisk";"Larva";272;2
"Unit";"Hydralisk";"Larva";272;2
"Unit";"Hydralisk";"Larva";272;2
"Unit";"Hydralisk";"Larva";272;2
"Unit";"Hydralisk";"Larva";272;2
"Unit";"Hydralisk";"Larva";272;2
"Unit";"Hydralisk";"Larva";272;2
"Unit";"Hydralisk";"Larva";272;2
"Unit";"Hydralisk";"Larva";272;2
"Unit";"Hydralisk";"Larva";272;2
"Unit";"Hydralisk";"Larva";272;2
"Unit";"Hydralisk";"Larva";272;2
"Unit";"Hydralisk";"Larva";272;2
"Unit";"Hydralisk";"Larva";272;2
"Unit";"Hydralisk";"Larva";272;2
"Unit";"Hydralisk";"Larva";272;2
"Unit";"Zergling";"Larva";272;1
"Unit";"Zergling";"Larva";272;1
"Unit";"Zergling";"Larva";272;1
"Unit";"Zergling";"Larva";272;1
"Unit";"Zergling";"Larva";272;1
"Unit";"Zergling";"Larva";272;1
"Unit";"Zergling";"Larva";272;1
"Unit";"Zergling";"Larva";272;1
"Unit";"Hydralisk";"Larva";272;2
"Unit";"Hydralisk";"Larva";272;2
"Unit";"Hydralisk";"Larva";272;2
"Unit";"Hydralisk";"Larva";272;2
"Unit";"Hydralisk";"Larva";272;2
"Unit";"Hydralisk";"Larva";272;2
"Unit";"Hydralisk";"Larva";272;2
"Unit";"Zergling";"Larva";272;1
"Unit";"Zergling";"Larva";272;1
"Unit";"Zergling";"Larva";272;1
"Unit";"Zergling";"Larva";272;1
"Unit";"Zergling";"Larva";272;1
"Unit";"Zergling";"Larva";272;1
"Unit";"Zergling";"Larva";272;1
"Unit";"Zergling";"Larva";272;1
"Unit";"Zergling";"Larva";272;1
"Unit";"Zergling";"Larva";272;1
"Unit";"Zergling";"Larva";272;1
"Unit";"Zergling";"Larva";272;1
"Unit";"Zergling";"Larva";272;1
"Unit";"Zergling";"Larva";272;1
"Unit";"Zergling";"Larva";272;1
"Unit";"Zergling";"Larva";272;1
"Unit";"Zergling";"Larva";272;1
"Unit";"Zergling";"Larva";272;1
"Unit";"Zergling";"Larva";272;1
"Unit";"Zergling";"Larva";272;1
"Unit";"Zergling";"Larva";272;1
"Unit";"Zergling";"Larva";272;1
"Unit";"Zergling";"Larva";272;1
"Unit";"Zergling";"Larva";272;1
"Unit";"Zergling";"Larva";318;1
"Unit";"Zergling";"Larva";318;1
"Unit";"Zergling";"Larva";318;1
"Unit";"Zergling";"Larva";318;1
"Unit";"Hydralisk";"Larva";272;2
"Unit";"Hydralisk";"Larva";272;2
"Unit";"Hydralisk";"Larva";272;2
"Unit";"Hydralisk";"Larva";272;2
"Building";"CreepTumorQueen";NA;338;0
"Building";"CreepTumorQueen";NA;338;0
"Building";"CreepTumorQueen";NA;338;0
"Unit";"Zergling";"Larva";338;1
"Unit";"Zergling";"Larva";338;1
"Unit";"Zergling";"Larva";338;1
"Unit";"Zergling";"Larva";338;1
"Unit";"Zergling";"Larva";338;1
"Unit";"Zergling";"Larva";338;1
"Building";"CreepTumor";NA;356;0
"Building";"CreepTumor";NA;368;0
"Building";"CreepTumor";NA;368;0
"Building";"CreepTumor";NA;368;0
"Building";"CreepTumor";NA;368;0
"Unit";"Zergling";"Larva";368;1
"Unit";"Zergling";"Larva";368;1
"Unit";"Zergling";"Larva";368;1
"Unit";"Zergling";"Larva";368;1
"Unit";"Zergling";"Larva";368;1
"Unit";"Zergling";"Larva";368;1
"Unit";"Zergling";"Larva";368;1
"Unit";"Zergling";"Larva";368;1
"Unit";"Zergling";"Larva";368;1
"Unit";"Zergling";"Larva";368;1
"Unit";"Zergling";"Larva";368;1
"Unit";"Zergling";"Larva";368;1
"Unit";"Zergling";"Larva";368;1
"Unit";"Zergling";"Larva";368;1
"Unit";"Zergling";"Larva";368;1
"Unit";"Zergling";"Larva";368;1
"Unit";"Zergling";"Larva";368;1
"Unit";"Zergling";"Larva";368;1
"Unit";"Zergling";"Larva";368;1
"Unit";"Zergling";"Larva";368;1
"Unit";"Zergling";"Larva";368;1
"Unit";"Zergling";"Larva";368;1
"Unit";"Zergling";"Larva";368;1
"Unit";"Zergling";"Larva";368;1
"Unit";"Zergling";"Larva";368;1
"Unit";"Zergling";"Larva";368;1
"Unit";"Zergling";"Larva";368;1
"Unit";"Zergling";"Larva";368;1
"Unit";"Zergling";"Larva";368;1
"Unit";"Zergling";"Larva";368;1
"Unit";"Zergling";"Larva";368;1
"Unit";"Zergling";"Larva";368;1
"Building";"Extractor";NA;368;0
"Building";"Extractor";NA;368;0
"Building";"CreepTumor";NA;406;0
"Unit";"Zergling";"Larva";406;1
"Unit";"Zergling";"Larva";406;1
"Unit";"Zergling";"Larva";406;1
"Unit";"Zergling";"Larva";406;1
"Unit";"Zergling";"Larva";406;1
"Unit";"Zergling";"Larva";406;1
"Unit";"Zergling";"Larva";406;1
"Unit";"Zergling";"Larva";406;1
"Unit";"Zergling";"Larva";406;1
"Unit";"Zergling";"Larva";406;1
"Unit";"Zergling";"Larva";406;1
"Unit";"Zergling";"Larva";406;1
"Unit";"Zergling";"Larva";406;1
"Unit";"Zergling";"Larva";406;1
"Unit";"Zergling";"Larva";406;1
"Unit";"Zergling";"Larva";406;1
"Unit";"Zergling";"Larva";406;1
"Unit";"Zergling";"Larva";406;1
"Unit";"Zergling";"Larva";406;1
"Unit";"Zergling";"Larva";406;1
"Unit";"Zergling";"Larva";406;1
"Unit";"Zergling";"Larva";406;1
"Unit";"Zergling";"Larva";406;1
"Unit";"Zergling";"Larva";406;1
"Unit";"Zergling";"Larva";406;1
"Unit";"Zergling";"Larva";406;1
"Unit";"Zergling";"Larva";406;1
"Unit";"Zergling";"Larva";406;1
"Unit";"Zergling";"Larva";406;1
"Unit";"Zergling";"Larva";406;1
"Unit";"Zergling";"Larva";406;1
"Unit";"Zergling";"Larva";406;1
"Unit";"Zergling";"Larva";406;1
"Unit";"Zergling";"Larva";406;1
"Unit";"Zergling";"Larva";406;1
"Unit";"Zergling";"Larva";406;1
"Unit";"Zergling";"Larva";406;1
"Unit";"Zergling";"Larva";406;1
"Unit";"Zergling";"Larva";406;1
"Unit";"Zergling";"Larva";406;1
"Unit";"Hydralisk";"Larva";406;2
"Unit";"Hydralisk";"Larva";406;2
"Unit";"Hydralisk";"Larva";406;2
"Unit";"Hydralisk";"Larva";406;2
"Unit";"Hydralisk";"Larva";406;2
"Unit";"Hydralisk";"Larva";406;2
"Unit";"Hydralisk";"Larva";406;2
"Unit";"Hydralisk";"Larva";406;2
"Building";"CreepTumor";NA;406;0
"Building";"CreepTumor";NA;446;0
"Building";"CreepTumor";NA;446;0
"Building";"CreepTumor";NA;446;0
"Building";"InfestationPit";NA;406;0
"Unit";"Overlord";"Larva";462;0
"Unit";"Overlord";"Larva";462;0
"Unit";"Overlord";"Larva";462;0
"Unit";"Overlord";"Larva";462;0
"Unit";"Overlord";"Larva";462;0
"Unit";"Zergling";"Larva";462;1
"Unit";"Zergling";"Larva";462;1
"Unit";"Zergling";"Larva";462;1
"Unit";"Zergling";"Larva";462;1
"Unit";"Zergling";"Larva";462;1
"Unit";"Zergling";"Larva";462;1
"Unit";"Zergling";"Larva";462;1
"Unit";"Zergling";"Larva";462;1
"Unit";"Zergling";"Larva";462;1
"Unit";"Zergling";"Larva";462;1
"Unit";"Zergling";"Larva";462;1
"Unit";"Zergling";"Larva";462;1
"Unit";"Zergling";"Larva";462;1
"Unit";"Zergling";"Larva";462;1
"Unit";"Zergling";"Larva";462;1
"Unit";"Zergling";"Larva";462;1
"Unit";"Zergling";"Larva";462;1
"Unit";"Zergling";"Larva";462;1
"Unit";"Hydralisk";"Larva";462;2
"Unit";"Hydralisk";"Larva";462;2
"Unit";"Hydralisk";"Larva";462;2
"Unit";"Hydralisk";"Larva";462;2
"Unit";"Hydralisk";"Larva";462;2
"Unit";"Hydralisk";"Larva";462;2
"Unit";"Hydralisk";"Larva";462;2
"Unit";"Hydralisk";"Larva";462;2
"Unit";"Hydralisk";"Larva";462;2
"Unit";"Hydralisk";"Larva";462;2
"Unit";"Hydralisk";"Larva";462;2
"Unit";"Hydralisk";"Larva";462;2
"Unit";"Zergling";"Larva";462;1
"Unit";"Zergling";"Larva";462;1
"Upgrade";"ZergGroundArmorsLevel1";"EvolutionChamber";406;0
"Unit";"Hydralisk";"Larva";462;2
"Unit";"Hydralisk";"Larva";462;2
"Unit";"Hydralisk";"Larva";462;2
"Unit";"Hydralisk";"Larva";462;2
"Building";"CreepTumor";NA;504;0
"Building";"CreepTumor";NA;504;0
"Unit";"Hydralisk";"Larva";480;2
"Unit";"Hydralisk";"Larva";480;2
"Unit";"Hydralisk";"Larva";480;2
"Unit";"Hydralisk";"Larva";480;2
"Upgrade";"ZergMissileWeaponsLevel2";"EvolutionChamber";406;0
"Unit";"Hydralisk";"Larva";514;2
"Unit";"Hydralisk";"Larva";514;2
"Unit";"Hydralisk";"Larva";514;2
"Unit";"Hydralisk";"Larva";514;2
"Unit";"Hydralisk";"Larva";514;2
"Unit";"Hydralisk";"Larva";514;2
"Unit";"Hydralisk";"Larva";514;2
"Unit";"Hydralisk";"Larva";514;2
"Unit";"Hydralisk";"Larva";514;2
"Unit";"Hydralisk";"Larva";514;2
"Building";"CreepTumor";NA;522;0
"Unit";"Zergling";"Larva";542;1
"Unit";"Zergling";"Larva";542;1
"Unit";"Zergling";"Larva";542;1
"Unit";"Zergling";"Larva";542;1
"Unit";"Zergling";"Larva";542;1
"Unit";"Zergling";"Larva";542;1
"Unit";"Zergling";"Larva";542;1
"Unit";"Zergling";"Larva";542;1
"Unit";"Zergling";"Larva";542;1
"Unit";"Zergling";"Larva";542;1
"Unit";"Zergling";"Larva";542;1
"Unit";"Zergling";"Larva";542;1
"Unit";"Zergling";"Larva";542;1
"Unit";"Zergling";"Larva";542;1
"Unit";"Zergling";"Larva";542;1
"Unit";"Zergling";"Larva";542;1
"Unit";"Zergling";"Larva";542;1
"Unit";"Zergling";"Larva";542;1
"Unit";"Zergling";"Larva";542;1
"Unit";"Zergling";"Larva";542;1
"Unit";"Zergling";"Larva";542;1
"Unit";"Zergling";"Larva";542;1
"Unit";"Zergling";"Larva";542;1
"Unit";"Zergling";"Larva";542;1
"Unit";"Zergling";"Larva";542;1
"Unit";"Zergling";"Larva";542;1
"Unit";"Zergling";"Larva";542;1
"Unit";"Zergling";"Larva";542;1
"Building";"Hatchery";NA;504;0
"Unit";"Zergling";"Larva";574;1
"Unit";"Zergling";"Larva";574;1
"Unit";"Viper";"Larva";572;3
"Building";"CreepTumor";NA;574;0
"Unit";"Viper";"Larva";573;3
"Unit";"Viper";"Larva";574;3
"Unit";"Viper";"Larva";574;3
"Unit";"Hydralisk";"Larva";574;2
"Unit";"Hydralisk";"Larva";574;2
"Unit";"Hydralisk";"Larva";574;2
"Unit";"Hydralisk";"Larva";574;2
"Unit";"Hydralisk";"Larva";574;2
"Unit";"Hydralisk";"Larva";574;2
"Unit";"Hydralisk";"Larva";574;2
"Building";"CreepTumor";NA;576;0
"Unit";"Hydralisk";"Larva";574;2
"Unit";"Hydralisk";"Larva";574;2
"Unit";"Hydralisk";"Larva";574;2
"Unit";"Hydralisk";"Larva";574;2
"Unit";"Hydralisk";"Larva";574;2
"Unit";"Zergling";"Larva";612;1
"Unit";"Zergling";"Larva";612;1
"Unit";"Zergling";"Larva";612;1
"Unit";"Zergling";"Larva";612;1
"Unit";"Zergling";"Larva";612;1
"Unit";"Zergling";"Larva";612;1
"Unit";"Zergling";"Larva";612;1
"Unit";"Zergling";"Larva";612;1
"Unit";"Zergling";"Larva";620;1
"Unit";"Zergling";"Larva";620;1
"Unit";"Zergling";"Larva";620;1
"Unit";"Zergling";"Larva";620;1
"Unit";"Zergling";"Larva";620;1
"Unit";"Zergling";"Larva";620;1
"Unit";"Zergling";"Larva";620;1
"Unit";"Zergling";"Larva";620;1
"Unit";"Zergling";"Larva";620;1
"Unit";"Zergling";"Larva";620;1
"Unit";"Zergling";"Larva";620;1
"Unit";"Zergling";"Larva";620;1
"Unit";"Zergling";"Larva";620;1
"Unit";"Zergling";"Larva";620;1
"Unit";"Zergling";"Larva";620;1
"Unit";"Zergling";"Larva";620;1
"Unit";"Zergling";"Larva";620;1
"Unit";"Zergling";"Larva";620;1
"Unit";"Zergling";"Larva";620;1
"Unit";"Zergling";"Larva";620;1
"Unit";"Zergling";"Larva";620;1
"Unit";"Zergling";"Larva";620;1
"Unit";"Zergling";"Larva";620;1
"Unit";"Zergling";"Larva";620;1
"Upgrade";"ZergGroundArmorsLevel2";"EvolutionChamber";574;0
"Building";"CreepTumor";NA;644;0
"Building";"CreepTumor";NA;644;0
"Building";"CreepTumor";NA;644;0
"Unit";"Hydralisk";"Larva";644;2
"Unit";"Hydralisk";"Larva";644;2
"Unit";"Hydralisk";"Larva";644;2
"Unit";"Hydralisk";"Larva";644;2
"Unit";"Hydralisk";"Larva";644;2
"Building";"CreepTumor";NA;654;0
"Upgrade";"ZergMissileWeaponsLevel3";"EvolutionChamber";644;0
"Unit";"Hydralisk";"Larva";654;2
"Unit";"Hydralisk";"Larva";654;2
"Unit";"Hydralisk";"Larva";654;2
"Unit";"Hydralisk";"Larva";654;2
"Unit";"Hydralisk";"Larva";654;2
"Unit";"Hydralisk";"Larva";654;2
"Unit";"Hydralisk";"Larva";654;2
"Unit";"Hydralisk";"Larva";654;2
"Unit";"Hydralisk";"Larva";654;2
"Unit";"Hydralisk";"Larva";654;2
"Unit";"Hydralisk";"Larva";654;2
"Unit";"Hydralisk";"Larva";654;2
"Unit";"Hydralisk";"Larva";654;2
"Building";"Hatchery";NA;654;0
"Unit";"Hydralisk";"Larva";654;2
"Unit";"Hydralisk";"Larva";654;2
"Unit";"Hydralisk";"Larva";654;2
"Unit";"Hydralisk";"Larva";654;2
"Unit";"Hydralisk";"Larva";654;2
"Unit";"Hydralisk";"Larva";654;2
"Unit";"Hydralisk";"Larva";654;2
"Unit";"Hydralisk";"Larva";654;2
"Unit";"Hydralisk";"Larva";654;2
"Unit";"Hydralisk";"Larva";654;2
"Unit";"Hydralisk";"Larva";654;2
"Unit";"Hydralisk";"Larva";654;2
"Building";"Hatchery";NA;654;0
"Unit";"Hydralisk";"Larva";680;2
"Unit";"Hydralisk";"Larva";680;2
"Unit";"Viper";"Larva";680;3
"Unit";"Viper";"Larva";680;3
"Unit";"Hydralisk";"Larva";704;2
"Unit";"Hydralisk";"Larva";704;2
"Unit";"Hydralisk";"Larva";704;2
"Unit";"Hydralisk";"Larva";704;2
"Upgrade";"ZergGroundArmorsLevel3";"EvolutionChamber";654;0
"Unit";"Hydralisk";"Larva";722;2
"Unit";"Hydralisk";"Larva";722;2
"Unit";"Hydralisk";"Larva";722;2
"Unit";"Hydralisk";"Larva";722;2
"Unit";"Hydralisk";"Larva";722;2
"Unit";"Hydralisk";"Larva";722;2
"Unit";"Hydralisk";"Larva";722;2
"Unit";"Hydralisk";"Larva";722;2
"Unit";"Hydralisk";"Larva";722;2
"Unit";"Hydralisk";"Larva";722;2
"Unit";"Hydralisk";"Larva";722;2
"Unit";"Hydralisk";"Larva";722;2
"Unit";"Hydralisk";"Larva";722;2
"Unit";"Hydralisk";"Larva";722;2
"Unit";"Hydralisk";"Larva";742;2
"Unit";"Hydralisk";"Larva";742;2
"Unit";"Hydralisk";"Larva";742;2
"Unit";"Hydralisk";"Larva";742;2
"Unit";"Hydralisk";"Larva";742;2
"Unit";"Hydralisk";"Larva";742;2
"Unit";"Hydralisk";"Larva";742;2
"Unit";"Hydralisk";"Larva";742;2
"Unit";"Hydralisk";"Larva";742;2
"Unit";"Hydralisk";"Larva";742;2
"Unit";"Hydralisk";"Larva";742;2
"Unit";"Hydralisk";"Larva";742;2
"Unit";"Hydralisk";"Larva";742;2
"Unit";"Hydralisk";"Larva";742;2
"Unit";"Hydralisk";"Larva";742;2
"Unit";"Hydralisk";"Larva";742;2
"Unit";"Hydralisk";"Larva";742;2
"Unit";"Hydralisk";"Larva";742;2
"Unit";"Hydralisk";"Larva";742;2
"Unit";"Hydralisk";"Larva";742;2
"Unit";"Hydralisk";"Larva";742;2
"Unit";"Viper";"Larva";742;3
"Unit";"Viper";"Larva";742;3
"Unit";"Viper";"Larva";742;3
"Unit";"Viper";"Larva";742;3
"Unit";"Viper";"Larva";742;3
"Building";"Extractor";NA;750;0
"Building";"Extractor";NA;750;0
"Upgrade";"ZergMeleeWeaponsLevel2";"EvolutionChamber";722;0
"Unit";"Hydralisk";"Larva";818;2
"Unit";"Hydralisk";"Larva";818;2
"Unit";"Hydralisk";"Larva";818;2
"Unit";"Hydralisk";"Larva";818;2
"Unit";"Hydralisk";"Larva";818;2
"Unit";"Hydralisk";"Larva";818;2
"Unit";"Hydralisk";"Larva";818;2
"Unit";"Hydralisk";"Larva";818;2
"Unit";"Hydralisk";"Larva";818;2
"Unit";"Hydralisk";"Larva";818;2
"Unit";"Hydralisk";"Larva";818;2
