"type";"unit_name";"on_building";"total_supply";"supply"
"Unit";"Overlord";"Larva";13;0
"Building";"Extractor";NA;14;0
"Building";"SpawningPool";NA;14;0
"Unit";"Zergling";"Larva";19;1
"Unit";"Zergling";"Larva";19;1
"Unit";"Zergling";"Larva";19;1
"Unit";"Zergling";"Larva";19;1
"Unit";"Zergling";"Larva";19;1
"Unit";"Zergling";"Larva";19;1
"Unit";"Zergling";"Larva";19;1
"Unit";"Zergling";"Larva";19;1
"Building";"Hatchery";NA;19;0
"Unit";"Overlord";"Larva";27;0
"Unit";"Queen";"Hatchery";29;2
"Building";"Hatchery";NA;27;0
"Unit";"Queen";"Hatchery";33;2
"Unit";"Overlord";"Larva";39;0
"Building";"Extractor";NA;46;0
"Unit";"Queen";"Hatchery";41;2
"Building";"BanelingNest";NA;47;0
"Building";"RoachWarren";NA;48;0
"Unit";"Overlord";"Larva";55;0
"Unit";"Overlord";"Larva";55;0
"Unit";"Overlord";"Larva";61;0
"Unit";"Overlord";"Larva";61;0
"Unit";"Roach";"Larva";61;2
"Unit";"Roach";"Larva";61;2
"Unit";"Roach";"Larva";61;2
"Unit";"Roach";"Larva";61;2
"Unit";"Roach";"Larva";61;2
"Unit";"Roach";"Larva";61;2
"Unit";"Baneling";"Zergling";67;0
"Unit";"Baneling";"Zergling";67;0
"Unit";"Baneling";"Zergling";67;0
"Unit";"Baneling";"Zergling";67;0
"Unit";"Roach";"Larva";61;2
"Unit";"Roach";"Larva";61;2
"Unit";"Roach";"Larva";61;2
"Unit";"Roach";"Larva";61;2
"Building";"CreepTumorQueen";NA;81;0
"Unit";"Overlord";"Larva";81;0
"Unit";"Overlord";"Larva";81;0
"Unit";"Overlord";"Larva";81;0
"Building";"Extractor";NA;81;0
"Building";"Extractor";NA;81;0
"Unit";"Roach";"Larva";81;2
"Unit";"Roach";"Larva";81;2
"Unit";"Roach";"Larva";81;2
"Unit";"Roach";"Larva";81;2
"Unit";"Roach";"Larva";82;2
"Building";"EvolutionChamber";NA;81;0
"Unit";"Roach";"Larva";87;2
"Unit";"Roach";"Larva";87;2
"Unit";"Roach";"Larva";87;2
"Unit";"Roach";"Larva";87;2
"Unit";"Roach";"Larva";87;2
"Unit";"Roach";"Larva";87;2
"Unit";"Overlord";"Larva";112;0
"Unit";"Overlord";"Larva";112;0
"Unit";"Roach";"Larva";112;2
"Building";"CreepTumor";NA;116;0
"Unit";"Zergling";"Larva";116;1
"Unit";"Zergling";"Larva";116;1
"Unit";"Zergling";"Larva";116;1
"Unit";"Zergling";"Larva";116;1
"Unit";"Zergling";"Larva";116;1
"Unit";"Zergling";"Larva";116;1
"Unit";"Zergling";"Larva";116;1
"Unit";"Zergling";"Larva";116;1
"Unit";"Zergling";"Larva";116;1
"Unit";"Zergling";"Larva";116;1
"Unit";"Zergling";"Larva";116;1
"Unit";"Zergling";"Larva";116;1
"Unit";"Roach";"Larva";118;2
"Unit";"Roach";"Larva";118;2
"Unit";"Roach";"Larva";118;2
"Unit";"Roach";"Larva";118;2
"Unit";"Overlord";"Larva";124;0
"Unit";"Baneling";"Zergling";130;0
"Unit";"Baneling";"Zergling";130;0
"Unit";"Overlord";"Larva";142;0
"Unit";"Overlord";"Larva";142;0
"Unit";"Overlord";"Larva";142;0
"Building";"CreepTumor";NA;142;0
"Building";"CreepTumorQueen";NA;142;0
"Upgrade";"GlialReconstitution";"RoachWarren";124;0
"Building";"Extractor";NA;142;0
"Building";"Extractor";NA;142;0
"Building";"HydraliskDen";NA;142;0
"Building";"Spire";NA;130;0
"Upgrade";"ZergMissileWeaponsLevel1";"EvolutionChamber";138;0
"Unit";"Mutalisk";"Larva";151;2
"Unit";"Mutalisk";"Larva";151;2
"Unit";"Mutalisk";"Larva";151;2
"Unit";"Mutalisk";"Larva";151;2
"Unit";"Mutalisk";"Larva";151;2
"Unit";"Mutalisk";"Larva";151;2
"Unit";"Mutalisk";"Larva";151;2
"Building";"Hatchery";NA;142;0
"Building";"CreepTumor";NA;157;0
"Unit";"Mutalisk";"Larva";159;2
"Unit";"Mutalisk";"Larva";159;2
"Unit";"Mutalisk";"Larva";159;2
"Unit";"Overlord";"Larva";171;0
"Unit";"Overlord";"Larva";171;0
"Unit";"Overlord";"Larva";171;0
"Unit";"Overlord";"Larva";171;0
"Unit";"Overlord";"Larva";171;0
"Unit";"Overlord";"Larva";171;0
"Unit";"Zergling";"Larva";171;1
"Unit";"Zergling";"Larva";171;1
"Unit";"Zergling";"Larva";171;1
"Unit";"Zergling";"Larva";171;1
"Unit";"Zergling";"Larva";171;1
"Unit";"Zergling";"Larva";171;1
"Unit";"Zergling";"Larva";171;1
"Unit";"Zergling";"Larva";171;1
"Unit";"Zergling";"Larva";171;1
"Unit";"Zergling";"Larva";171;1
"Unit";"Zergling";"Larva";171;1
"Unit";"Zergling";"Larva";171;1
"Unit";"Zergling";"Larva";171;1
"Unit";"Zergling";"Larva";171;1
"Unit";"Zergling";"Larva";171;1
"Unit";"Zergling";"Larva";171;1
"Unit";"Mutalisk";"Larva";171;2
"Unit";"Roach";"Larva";195;2
"Unit";"Roach";"Larva";195;2
"Unit";"Roach";"Larva";195;2
"Unit";"Roach";"Larva";195;2
"Unit";"Roach";"Larva";195;2
"Unit";"Roach";"Larva";195;2
"Unit";"Roach";"Larva";195;2
"Unit";"Roach";"Larva";195;2
"Unit";"Roach";"Larva";195;2
"Unit";"Roach";"Larva";195;2
"Unit";"Roach";"Larva";195;2
"Unit";"Roach";"Larva";195;2
"Building";"Hatchery";NA;157;0
"Unit";"Baneling";"Zergling";195;0
"Unit";"Baneling";"Zergling";195;0
"Unit";"Baneling";"Zergling";195;0
"Unit";"Baneling";"Zergling";195;0
"Unit";"Baneling";"Zergling";195;0
"Unit";"Baneling";"Zergling";195;0
"Unit";"Mutalisk";"Larva";195;2
"Unit";"Mutalisk";"Larva";195;2
"Unit";"Mutalisk";"Larva";195;2
"Unit";"Roach";"Larva";219;2
"Unit";"Roach";"Larva";219;2
"Unit";"Roach";"Larva";219;2
"Unit";"Roach";"Larva";219;2
"Unit";"Roach";"Larva";219;2
"Unit";"Roach";"Larva";219;2
"Unit";"Roach";"Larva";219;2
"Unit";"Roach";"Larva";219;2
"Unit";"Roach";"Larva";219;2
"Unit";"Roach";"Larva";219;2
"Unit";"Roach";"Larva";219;2
"Unit";"Roach";"Larva";219;2
"Unit";"Roach";"Larva";219;2
"Unit";"Roach";"Larva";219;2
"Unit";"Roach";"Larva";253;2
"Unit";"Roach";"Larva";253;2
"Unit";"Roach";"Larva";253;2
"Unit";"Roach";"Larva";253;2
"Unit";"Roach";"Larva";253;2
"Unit";"Roach";"Larva";253;2
"Unit";"Roach";"Larva";253;2
"Unit";"Roach";"Larva";253;2
"Unit";"Roach";"Larva";253;2
"Unit";"Roach";"Larva";253;2
"Unit";"Roach";"Larva";253;2
"Unit";"Zergling";"Larva";253;1
"Unit";"Zergling";"Larva";253;1
"Unit";"Zergling";"Larva";253;1
"Unit";"Zergling";"Larva";253;1
"Unit";"Zergling";"Larva";253;1
"Unit";"Zergling";"Larva";253;1
"Unit";"Roach";"Larva";275;2
"Unit";"Roach";"Larva";275;2
"Unit";"Roach";"Larva";275;2
"Unit";"Roach";"Larva";275;2
"Unit";"Roach";"Larva";275;2
"Unit";"Roach";"Larva";275;2
"Unit";"Roach";"Larva";275;2
"Unit";"Roach";"Larva";275;2
"Unit";"Roach";"Larva";275;2
"Upgrade";"ZergMissileWeaponsLevel2";"EvolutionChamber";195;0
"Unit";"Baneling";"Zergling";281;0
"Unit";"Baneling";"Zergling";281;0
"Unit";"Baneling";"Zergling";281;0
"Unit";"Baneling";"Zergling";281;0
"Unit";"Baneling";"Zergling";281;0
"Unit";"Baneling";"Zergling";281;0
"Unit";"Mutalisk";"Larva";299;2
"Unit";"Mutalisk";"Larva";299;2
"Unit";"Mutalisk";"Larva";299;2
"Unit";"Mutalisk";"Larva";299;2
"Unit";"Roach";"Larva";299;2
"Unit";"Roach";"Larva";299;2
"Unit";"Roach";"Larva";299;2
"Unit";"Roach";"Larva";299;2
"Unit";"Roach";"Larva";299;2
"Unit";"Roach";"Larva";299;2
"Unit";"Roach";"Larva";299;2
"Unit";"Roach";"Larva";299;2
"Unit";"Roach";"Larva";299;2
"Unit";"Roach";"Larva";299;2
"Building";"Extractor";NA;307;0
"Building";"Extractor";NA;307;0
"Unit";"Mutalisk";"Larva";307;2
"Unit";"Mutalisk";"Larva";327;2
"Building";"CreepTumor";NA;329;0
"Unit";"Mutalisk";"Larva";327;2
"Unit";"Mutalisk";"Larva";329;2
"Unit";"Mutalisk";"Larva";329;2
"Building";"Extractor";NA;329;0
"Unit";"Mutalisk";"Larva";333;2
"Unit";"Mutalisk";"Larva";333;2
"Building";"Hatchery";NA;307;0
"Building";"Hatchery";NA;307;0
"Unit";"Mutalisk";"Larva";337;2
"Unit";"Mutalisk";"Larva";337;2
"Unit";"Mutalisk";"Larva";337;2
"Building";"EvolutionChamber";NA;365;0
"Building";"InfestationPit";NA;365;0
