"type";"unit_name";"on_building";"total_supply";"supply"
"Unit";"Overlord";"Larva";13;0
"Building";"Extractor";NA;17;0
"Building";"SpawningPool";NA;19;0
"Unit";"Overlord";"Larva";21;0
"Building";"Hatchery";NA;17;0
"Unit";"Zergling";"Larva";22;1
"Unit";"Zergling";"Larva";22;1
"Unit";"Zergling";"Larva";22;1
"Unit";"Zergling";"Larva";22;1
"Unit";"Queen";"Hatchery";22;2
"Unit";"Queen";"Hatchery";22;2
"Unit";"Overlord";"Larva";35;0
"Building";"CreepTumorQueen";NA;40;0
"Unit";"Overlord";"Larva";40;0
"Building";"Hatchery";NA;33;0
"Building";"SporeCrawler";NA;44;0
"Building";"SporeCrawler";NA;48;0
"Building";"CreepTumor";NA;50;0
"Unit";"Overlord";"Larva";50;0
"Unit";"Zergling";"Larva";52;1
"Unit";"Zergling";"Larva";52;1
"Unit";"Zergling";"Larva";52;1
"Unit";"Zergling";"Larva";52;1
"Unit";"Zergling";"Larva";52;1
"Unit";"Zergling";"Larva";52;1
"Unit";"Overlord";"Larva";52;0
"Building";"EvolutionChamber";NA;52;0
"Building";"Extractor";NA;52;0
"Building";"Extractor";NA;52;0
"Unit";"Queen";"Hatchery";52;2
"Building";"RoachWarren";NA;51;0
"Building";"SporeCrawler";NA;63;0
"Unit";"Overlord";"Larva";73;0
"Unit";"Overlord";"Larva";73;0
"Unit";"Overlord";"Larva";73;0
"Building";"Extractor";NA;73;0
"Unit";"Overlord";"Larva";75;0
"Unit";"Overlord";"Larva";75;0
"Unit";"Overlord";"Larva";75;0
"Building";"CreepTumor";NA;81;0
"Unit";"Roach";"Larva";81;2
"Unit";"Roach";"Larva";81;2
"Unit";"Roach";"Larva";81;2
"Unit";"Roach";"Larva";81;2
"Unit";"Roach";"Larva";81;2
"Unit";"Roach";"Larva";81;2
"Unit";"Roach";"Larva";81;2
"Unit";"Roach";"Larva";81;2
"Unit";"Roach";"Larva";81;2
"Unit";"Roach";"Larva";81;2
"Unit";"Roach";"Larva";81;2
"Unit";"Overlord";"Larva";81;0
"Unit";"Roach";"Larva";109;2
"Unit";"Roach";"Larva";109;2
"Unit";"Roach";"Larva";109;2
"Unit";"Roach";"Larva";109;2
"Upgrade";"ZergMissileWeaponsLevel1";"EvolutionChamber";73;0
"Unit";"Roach";"Larva";110;2
"Unit";"Roach";"Larva";110;2
"Upgrade";"GlialReconstitution";"RoachWarren";81;0
"Unit";"Overlord";"Larva";111;0
"Unit";"Overlord";"Larva";111;0
"Unit";"Roach";"Larva";111;2
"Unit";"Roach";"Larva";111;2
"Unit";"Roach";"Larva";111;2
"Unit";"Roach";"Larva";129;2
"Unit";"Roach";"Larva";129;2
"Unit";"Roach";"Larva";129;2
"Unit";"Roach";"Larva";129;2
"Unit";"Roach";"Larva";129;2
"Unit";"Roach";"Larva";129;2
"Unit";"Roach";"Larva";129;2
"Building";"CreepTumor";NA;147;0
"Unit";"Overlord";"Larva";145;0
"Unit";"Overlord";"Larva";145;0
"Unit";"Roach";"Larva";162;2
"Unit";"Roach";"Larva";162;2
"Unit";"Roach";"Larva";162;2
"Unit";"Roach";"Larva";162;2
"Unit";"Roach";"Larva";162;2
"Building";"Extractor";NA;162;0
"Building";"Extractor";NA;162;0
"Unit";"Roach";"Larva";162;2
"Unit";"Roach";"Larva";162;2
"Unit";"Roach";"Larva";162;2
"Unit";"Roach";"Larva";162;2
"Unit";"Roach";"Larva";162;2
"Unit";"Roach";"Larva";162;2
"Unit";"Roach";"Larva";162;2
"Unit";"Roach";"Larva";172;2
"Unit";"Roach";"Larva";172;2
"Unit";"Roach";"Larva";172;2
"Unit";"Roach";"Larva";172;2
"Unit";"Roach";"Larva";172;2
"Unit";"Overlord";"Larva";182;0
"Unit";"Overlord";"Larva";182;0
"Upgrade";"ZergMissileWeaponsLevel2";"EvolutionChamber";145;0
"Unit";"Roach";"Larva";186;2
"Unit";"Roach";"Larva";196;2
"Unit";"Roach";"Larva";196;2
"Unit";"Roach";"Larva";196;2
"Unit";"Roach";"Larva";199;2
"Unit";"Roach";"Larva";199;2
"Unit";"Roach";"Larva";199;2
"Unit";"Roach";"Larva";199;2
"Building";"Spire";NA;162;0
"Building";"Extractor";NA;215;0
"Building";"Hatchery";NA;172;0
"Unit";"Overlord";"Larva";215;0
"Unit";"Mutalisk";"Larva";223;2
"Unit";"Mutalisk";"Larva";223;2
"Unit";"Mutalisk";"Larva";223;2
"Unit";"Mutalisk";"Larva";223;2
"Unit";"Mutalisk";"Larva";223;2
"Unit";"Mutalisk";"Larva";223;2
"Unit";"Queen";"Hatchery";223;2
"Unit";"Queen";"Hatchery";223;2
"Unit";"Roach";"Larva";241;2
"Unit";"Roach";"Larva";241;2
"Unit";"Roach";"Larva";241;2
"Unit";"Roach";"Larva";241;2
"Unit";"Roach";"Larva";241;2
"Unit";"Roach";"Larva";241;2
"Unit";"Roach";"Larva";241;2
"Unit";"Roach";"Larva";241;2
"Unit";"Roach";"Larva";241;2
"Unit";"Roach";"Larva";241;2
"Unit";"Roach";"Larva";241;2
"Unit";"Roach";"Larva";245;2
"Unit";"Roach";"Larva";245;2
"Unit";"Roach";"Larva";245;2
"Unit";"Roach";"Larva";245;2
"Unit";"Roach";"Larva";245;2
"Unit";"Roach";"Larva";245;2
"Unit";"Roach";"Larva";245;2
"Unit";"Roach";"Larva";245;2
"Building";"HydraliskDen";NA;245;0
"Unit";"Roach";"Larva";267;2
"Unit";"Roach";"Larva";267;2
"Unit";"Roach";"Larva";267;2
"Unit";"Queen";"Hatchery";245;2
"Unit";"Roach";"Larva";269;2
"Unit";"Roach";"Larva";275;2
"Unit";"Roach";"Larva";283;2
"Unit";"Roach";"Larva";283;2
"Unit";"Roach";"Larva";283;2
"Unit";"Roach";"Larva";289;2
"Unit";"Roach";"Larva";289;2
"Unit";"Roach";"Larva";289;2
"Unit";"Roach";"Larva";289;2
"Unit";"Overlord";"Larva";291;0
"Unit";"Overlord";"Larva";291;0
"Unit";"Overlord";"Larva";291;0
"Unit";"Overlord";"Larva";291;0
"Unit";"Overlord";"Larva";291;0
"Unit";"Overlord";"Larva";291;0
"Unit";"Roach";"Larva";309;2
"Unit";"Roach";"Larva";309;2
"Unit";"Roach";"Larva";309;2
"Unit";"Roach";"Larva";309;2
"Unit";"Roach";"Larva";309;2
"Unit";"Roach";"Larva";309;2
"Unit";"Roach";"Larva";309;2
"Unit";"Roach";"Larva";309;2
"Unit";"Roach";"Larva";309;2
"Unit";"Roach";"Larva";309;2
"Unit";"Roach";"Larva";309;2
"Unit";"Roach";"Larva";309;2
"Unit";"Roach";"Larva";309;2
"Unit";"Roach";"Larva";309;2
"Unit";"Roach";"Larva";309;2
"Unit";"Roach";"Larva";309;2
