"type";"unit_name";"on_building";"total_supply";"supply"
"Unit";"Overlord";"Larva";12;0
"Unit";"Overlord";"Larva";14;0
"Building";"Extractor";NA;16;0
"Building";"SpawningPool";NA;17;0
"Building";"Hatchery";NA;16;0
"Building";"Extractor";NA;19;0
"Building";"RoachWarren";NA;19;0
"Unit";"Roach";"Larva";24;2
"Unit";"Roach";"Larva";24;2
"Unit";"Roach";"Larva";24;2
"Unit";"Roach";"Larva";24;2
"Unit";"Overlord";"Larva";30;0
"Unit";"Overlord";"Larva";32;0
"Unit";"Roach";"Larva";32;2
"Unit";"Roach";"Larva";32;2
"Unit";"Roach";"Larva";36;2
"Unit";"Roach";"Larva";36;2
"Unit";"Roach";"Larva";36;2
"Unit";"Queen";"Hatchery";36;2
"Building";"Hatchery";NA;36;0
"Unit";"Roach";"Larva";44;2
"Unit";"Roach";"Larva";44;2
"Unit";"Roach";"Larva";44;2
"Unit";"Roach";"Larva";44;2
"Unit";"Roach";"Larva";44;2
"Unit";"Roach";"Larva";44;2
"Unit";"Queen";"Hatchery";56;2
"Unit";"Overlord";"Larva";64;0
"Building";"HydraliskDen";NA;66;0
"Unit";"Overlord";"Larva";71;0
"Building";"SporeCrawler";NA;71;0
"Building";"SporeCrawler";NA;71;0
"Unit";"Overlord";"Larva";71;0
"Unit";"Queen";"Hatchery";71;2
"Unit";"Queen";"Hatchery";71;2
"Unit";"Hydralisk";"Larva";75;2
"Unit";"Hydralisk";"Larva";75;2
"Unit";"Hydralisk";"Larva";75;2
"Unit";"Overlord";"Larva";79;0
"Unit";"Overlord";"Larva";79;0
"Unit";"Queen";"Hatchery";85;2
"Unit";"Queen";"Hatchery";85;2
"Building";"CreepTumorQueen";NA;94;0
"Building";"CreepTumorQueen";NA;94;0
"Unit";"Hydralisk";"Larva";92;2
"Building";"SporeCrawler";NA;94;0
"Unit";"Overlord";"Larva";94;0
"Unit";"Overlord";"Larva";94;0
"Unit";"Overlord";"Larva";94;0
"Unit";"Overlord";"Larva";96;0
"Unit";"Overlord";"Larva";96;0
"Unit";"Queen";"Hatchery";94;2
"Building";"CreepTumor";NA;96;0
"Building";"CreepTumor";NA;96;0
"Building";"CreepTumorQueen";NA;98;0
"Building";"CreepTumorQueen";NA;98;0
"Unit";"Queen";"Hatchery";96;2
"Building";"CreepTumor";NA;102;0
"Building";"CreepTumor";NA;102;0
"Building";"CreepTumorQueen";NA;104;0
"Building";"CreepTumorQueen";NA;104;0
"Building";"CreepTumor";NA;102;0
"Building";"EvolutionChamber";NA;104;0
"Unit";"Hydralisk";"Larva";104;2
"Unit";"Hydralisk";"Larva";104;2
"Unit";"Hydralisk";"Larva";104;2
"Unit";"Hydralisk";"Larva";104;2
"Unit";"Hydralisk";"Larva";104;2
"Building";"CreepTumor";NA;104;0
"Building";"CreepTumor";NA;104;0
"Building";"CreepTumor";NA;104;0
"Building";"CreepTumor";NA;104;0
"Building";"CreepTumor";NA;104;0
"Building";"CreepTumor";NA;104;0
"Unit";"Overlord";"Larva";104;0
"Unit";"Overlord";"Larva";104;0
"Building";"Hatchery";NA;96;0
"Unit";"Queen";"Hatchery";104;2
"Unit";"Queen";"Hatchery";104;2
"Building";"CreepTumorQueen";NA;104;0
"Building";"CreepTumorQueen";NA;104;0
"Building";"CreepTumor";NA;118;0
"Upgrade";"EvolveGroovedSpines";"HydraliskDen";104;0
"Building";"CreepTumor";NA;118;0
"Building";"CreepTumor";NA;118;0
"Building";"CreepTumor";NA;118;0
"Building";"CreepTumor";NA;118;0
"Building";"CreepTumor";NA;118;0
"Building";"CreepTumor";NA;118;0
"Unit";"Hydralisk";"Larva";118;2
"Unit";"Hydralisk";"Larva";118;2
"Unit";"Hydralisk";"Larva";118;2
"Unit";"Hydralisk";"Larva";118;2
"Unit";"Hydralisk";"Larva";118;2
"Unit";"Hydralisk";"Larva";118;2
"Building";"CreepTumor";NA;118;0
"Unit";"Overlord";"Larva";130;0
"Building";"CreepTumor";NA;138;0
"Building";"CreepTumor";NA;138;0
"Building";"CreepTumor";NA;138;0
"Building";"CreepTumor";NA;138;0
"Building";"CreepTumor";NA;138;0
"Building";"CreepTumor";NA;138;0
"Building";"CreepTumor";NA;138;0
"Building";"CreepTumorQueen";NA;142;0
"Building";"CreepTumorQueen";NA;142;0
"Building";"CreepTumorQueen";NA;142;0
"Building";"Extractor";NA;138;0
"Building";"CreepTumorQueen";NA;142;0
"Building";"CreepTumor";NA;142;0
"Building";"CreepTumor";NA;142;0
"Building";"CreepTumor";NA;142;0
"Building";"CreepTumor";NA;142;0
"Building";"CreepTumor";NA;142;0
"Building";"CreepTumor";NA;142;0
"Building";"CreepTumor";NA;142;0
"Unit";"Hydralisk";"Larva";142;2
"Unit";"Hydralisk";"Larva";142;2
"Unit";"Hydralisk";"Larva";142;2
"Unit";"Hydralisk";"Larva";142;2
"Unit";"Hydralisk";"Larva";142;2
"Unit";"Hydralisk";"Larva";142;2
"Unit";"Hydralisk";"Larva";142;2
"Unit";"Hydralisk";"Larva";142;2
"Building";"CreepTumorQueen";NA;145;0
"Upgrade";"ZergMissileWeaponsLevel1";"EvolutionChamber";130;0
"Building";"CreepTumor";NA;161;0
"Unit";"Queen";"Hatchery";142;2
"Unit";"Queen";"Hatchery";142;2
"Unit";"Queen";"Hatchery";142;2
"Building";"CreepTumor";NA;161;0
"Building";"CreepTumor";NA;161;0
"Building";"CreepTumor";NA;161;0
"Building";"CreepTumor";NA;161;0
"Building";"CreepTumor";NA;161;0
"Building";"CreepTumor";NA;161;0
"Building";"CreepTumor";NA;161;0
"Building";"CreepTumor";NA;161;0
"Building";"CreepTumor";NA;161;0
"Building";"Extractor";NA;161;0
"Building";"CreepTumorQueen";NA;161;0
"Building";"Extractor";NA;161;0
"Unit";"Overlord";"Larva";161;0
"Unit";"Hydralisk";"Larva";161;2
"Unit";"Hydralisk";"Larva";161;2
"Unit";"Hydralisk";"Larva";161;2
"Unit";"Hydralisk";"Larva";161;2
"Building";"CreepTumorQueen";NA;175;0
"Building";"CreepTumorQueen";NA;183;0
"Building";"CreepTumorQueen";NA;183;0
"Building";"Extractor";NA;175;0
"Building";"CreepTumor";NA;192;0
"Building";"CreepTumor";NA;192;0
"Building";"CreepTumor";NA;192;0
"Building";"CreepTumorQueen";NA;192;0
"Building";"CreepTumorQueen";NA;192;0
"Building";"CreepTumor";NA;192;0
"Building";"CreepTumor";NA;192;0
"Building";"CreepTumor";NA;192;0
"Building";"CreepTumor";NA;192;0
"Building";"CreepTumor";NA;192;0
"Building";"CreepTumor";NA;192;0
"Building";"CreepTumor";NA;192;0
"Building";"CreepTumor";NA;192;0
"Building";"CreepTumor";NA;192;0
"Building";"CreepTumorQueen";NA;192;0
"Building";"CreepTumor";NA;192;0
"Building";"CreepTumorQueen";NA;192;0
"Building";"CreepTumor";NA;192;0
"Building";"InfestationPit";NA;192;0
"Unit";"Overlord";"Larva";192;0
"Unit";"Overlord";"Larva";192;0
"Unit";"Overlord";"Larva";192;0
"Unit";"Overlord";"Larva";192;0
"Building";"CreepTumor";NA;192;0
"Unit";"Hydralisk";"Larva";192;2
"Unit";"Hydralisk";"Larva";192;2
"Unit";"Hydralisk";"Larva";192;2
"Unit";"Hydralisk";"Larva";192;2
"Unit";"Hydralisk";"Larva";192;2
"Building";"CreepTumor";NA;192;0
"Upgrade";"EvolveMuscularAugments";"HydraliskDen";190;0
"Building";"CreepTumorQueen";NA;192;0
"Building";"CreepTumorQueen";NA;192;0
"Building";"CreepTumor";NA;192;0
"Building";"CreepTumor";NA;192;0
"Building";"CreepTumor";NA;192;0
"Building";"CreepTumor";NA;192;0
"Building";"CreepTumor";NA;192;0
"Building";"CreepTumor";NA;192;0
"Building";"CreepTumor";NA;192;0
"Building";"CreepTumor";NA;192;0
"Building";"CreepTumorQueen";NA;192;0
"Building";"Hatchery";NA;183;0
"Unit";"Overlord";"Larva";202;0
"Unit";"Overlord";"Larva";202;0
"Unit";"Overlord";"Larva";202;0
"Unit";"Overlord";"Larva";202;0
"Unit";"Overlord";"Larva";202;0
"Upgrade";"GlialReconstitution";"RoachWarren";192;0
"Unit";"Roach";"Larva";202;2
"Building";"CreepTumor";NA;202;0
"Unit";"Roach";"Larva";202;2
"Unit";"Roach";"Larva";202;2
"Unit";"Roach";"Larva";202;2
"Unit";"Roach";"Larva";202;2
"Unit";"Roach";"Larva";202;2
"Unit";"Roach";"Larva";202;2
"Unit";"Roach";"Larva";202;2
"Unit";"Roach";"Larva";202;2
"Building";"CreepTumor";NA;202;0
"Building";"CreepTumor";NA;202;0
"Building";"CreepTumor";NA;202;0
"Building";"CreepTumor";NA;202;0
"Building";"CreepTumorQueen";NA;202;0
"Building";"CreepTumorQueen";NA;202;0
"Building";"CreepTumorQueen";NA;202;0
"Building";"CreepTumor";NA;202;0
"Building";"CreepTumor";NA;202;0
"Building";"CreepTumor";NA;220;0
"Building";"CreepTumor";NA;220;0
"Building";"CreepTumor";NA;220;0
"Building";"CreepTumor";NA;220;0
"Building";"CreepTumor";NA;220;0
"Building";"CreepTumor";NA;220;0
"Building";"CreepTumor";NA;220;0
"Building";"CreepTumor";NA;220;0
"Building";"Extractor";NA;220;0
"Building";"Extractor";NA;220;0
"Upgrade";"ZergMissileWeaponsLevel2";"EvolutionChamber";192;0
"Building";"CreepTumor";NA;220;0
"Building";"CreepTumor";NA;220;0
"Building";"CreepTumor";NA;220;0
"Building";"CreepTumor";NA;220;0
"Building";"CreepTumor";NA;220;0
"Building";"CreepTumor";NA;220;0
"Building";"CreepTumor";NA;220;0
"Building";"CreepTumor";NA;220;0
"Building";"CreepTumor";NA;220;0
"Building";"SporeCrawler";NA;220;0
"Building";"CreepTumor";NA;220;0
"Building";"CreepTumor";NA;220;0
"Building";"CreepTumor";NA;220;0
"Building";"CreepTumor";NA;220;0
"Building";"CreepTumor";NA;222;0
"Building";"LurkerDenMP";NA;192;0
"Building";"SporeCrawler";NA;220;0
"Unit";"Hydralisk";"Larva";226;2
"Building";"CreepTumorQueen";NA;226;0
"Unit";"Hydralisk";"Larva";226;2
"Unit";"Hydralisk";"Larva";226;2
"Building";"CreepTumorQueen";NA;226;0
"Unit";"Hydralisk";"Larva";226;2
"Unit";"Hydralisk";"Larva";226;2
"Unit";"Hydralisk";"Larva";226;2
"Unit";"Hydralisk";"Larva";226;2
"Unit";"Hydralisk";"Larva";226;2
"Unit";"Hydralisk";"Larva";226;2
"Unit";"Hydralisk";"Larva";226;2
"Unit";"Hydralisk";"Larva";226;2
"Unit";"Hydralisk";"Larva";226;2
"Unit";"Hydralisk";"Larva";226;2
"Unit";"Hydralisk";"Larva";226;2
"Building";"CreepTumorQueen";NA;226;0
"Building";"CreepTumorQueen";NA;226;0
"Building";"CreepTumorQueen";NA;226;0
"Building";"CreepTumorQueen";NA;226;0
"Building";"CreepTumor";NA;226;0
"Building";"CreepTumor";NA;226;0
"Building";"CreepTumor";NA;254;0
"Building";"CreepTumor";NA;254;0
"Building";"CreepTumor";NA;254;0
"Building";"CreepTumorQueen";NA;254;0
"Building";"CreepTumor";NA;254;0
"Building";"CreepTumorQueen";NA;254;0
"Building";"CreepTumorQueen";NA;254;0
"Building";"CreepTumorQueen";NA;254;0
"Building";"CreepTumorQueen";NA;254;0
"Building";"CreepTumorQueen";NA;254;0
"Building";"CreepTumorQueen";NA;254;0
"Building";"CreepTumor";NA;254;0
"Building";"CreepTumorQueen";NA;254;0
"Building";"CreepTumor";NA;254;0
"Building";"CreepTumor";NA;254;0
"Building";"CreepTumor";NA;254;0
"Building";"CreepTumor";NA;254;0
"Building";"CreepTumor";NA;254;0
"Building";"CreepTumorQueen";NA;254;0
"Building";"CreepTumorQueen";NA;254;0
"Building";"CreepTumor";NA;254;0
"Building";"CreepTumorQueen";NA;254;0
"Building";"CreepTumor";NA;254;0
"Building";"CreepTumor";NA;254;0
"Building";"CreepTumorQueen";NA;254;0
"Building";"Spire";NA;254;0
"Unit";"Hydralisk";"Larva";254;2
"Unit";"Hydralisk";"Larva";254;2
"Unit";"Hydralisk";"Larva";254;2
"Unit";"Hydralisk";"Larva";254;2
"Unit";"Hydralisk";"Larva";254;2
"Unit";"Hydralisk";"Larva";254;2
"Unit";"Hydralisk";"Larva";254;2
"Unit";"Hydralisk";"Larva";254;2
"Unit";"Hydralisk";"Larva";254;2
"Unit";"Hydralisk";"Larva";254;2
"Unit";"Hydralisk";"Larva";254;2
"Unit";"Hydralisk";"Larva";254;2
"Unit";"Hydralisk";"Larva";254;2
"Unit";"Hydralisk";"Larva";254;2
"Unit";"Hydralisk";"Larva";254;2
"Unit";"Hydralisk";"Larva";254;2
"Unit";"Hydralisk";"Larva";254;2
"Unit";"Hydralisk";"Larva";254;2
"Unit";"Hydralisk";"Larva";254;2
"Unit";"Hydralisk";"Larva";254;2
"Unit";"Hydralisk";"Larva";254;2
"Unit";"Hydralisk";"Larva";254;2
"Unit";"Hydralisk";"Larva";254;2
"Unit";"Roach";"Larva";254;2
"Unit";"Roach";"Larva";254;2
"Unit";"Roach";"Larva";254;2
"Unit";"Roach";"Larva";254;2
"Unit";"Roach";"Larva";254;2
"Unit";"Roach";"Larva";254;2
"Unit";"Roach";"Larva";254;2
"Unit";"Roach";"Larva";254;2
"Unit";"Roach";"Larva";254;2
"Building";"CreepTumor";NA;318;0
"Building";"CreepTumorQueen";NA;318;0
"Building";"CreepTumor";NA;318;0
"Unit";"Roach";"Larva";318;2
"Unit";"Roach";"Larva";318;2
"Unit";"Roach";"Larva";318;2
"Building";"CreepTumor";NA;318;0
"Unit";"Roach";"Larva";318;2
"Unit";"Roach";"Larva";318;2
"Unit";"Roach";"Larva";318;2
"Unit";"Roach";"Larva";318;2
"Unit";"Roach";"Larva";318;2
"Unit";"Roach";"Larva";318;2
"Building";"CreepTumor";NA;318;0
"Unit";"Roach";"Larva";318;2
"Unit";"Roach";"Larva";318;2
"Unit";"Roach";"Larva";318;2
"Unit";"Roach";"Larva";318;2
"Unit";"Roach";"Larva";318;2
"Building";"CreepTumor";NA;318;0
"Building";"CreepTumor";NA;318;0
"Building";"CreepTumor";NA;318;0
"Building";"CreepTumor";NA;318;0
"Building";"CreepTumor";NA;318;0
"Building";"CreepTumor";NA;318;0
"Building";"CreepTumor";NA;318;0
"Building";"CreepTumor";NA;318;0
"Upgrade";"ZergMissileWeaponsLevel3";"EvolutionChamber";254;0
"Unit";"Roach";"Larva";346;2
"Unit";"Roach";"Larva";346;2
"Unit";"Roach";"Larva";346;2
"Unit";"Roach";"Larva";346;2
"Unit";"Roach";"Larva";346;2
"Unit";"Roach";"Larva";346;2
"Unit";"Roach";"Larva";346;2
"Unit";"Roach";"Larva";346;2
