"type";"unit_name";"on_building";"total_supply";"supply"
"Unit";"Overlord";"Larva";13;0
"Building";"Extractor";NA;17;0
"Unit";"Overlord";"Larva";21;0
"Building";"Hatchery";NA;16;0
"Building";"SpawningPool";NA;18;0
"Unit";"Zergling";"Larva";22;1
"Unit";"Zergling";"Larva";22;1
"Unit";"Zergling";"Larva";22;1
"Unit";"Zergling";"Larva";22;1
"Unit";"Queen";"Hatchery";22;2
"Unit";"Queen";"Hatchery";22;2
"Unit";"Zergling";"Larva";27;1
"Unit";"Zergling";"Larva";27;1
"Unit";"Zergling";"Larva";27;1
"Unit";"Zergling";"Larva";27;1
"Unit";"Overlord";"Larva";37;0
"Unit";"Queen";"Hatchery";37;2
"Building";"EvolutionChamber";NA;39;0
"Unit";"Overlord";"Larva";39;0
"Unit";"Overlord";"Larva";39;0
"Building";"CreepTumorQueen";NA;44;0
"Building";"SporeCrawler";NA;50;0
"Building";"SporeCrawler";NA;50;0
"Unit";"Overlord";"Larva";55;0
"Unit";"Overlord";"Larva";55;0
"Building";"Extractor";NA;58;0
"Building";"Extractor";NA;58;0
"Building";"CreepTumor";NA;60;0
"Building";"CreepTumorQueen";NA;60;0
"Building";"CreepTumorQueen";NA;60;0
"Unit";"Zergling";"Larva";60;1
"Unit";"Zergling";"Larva";60;1
"Unit";"Zergling";"Larva";60;1
"Unit";"Zergling";"Larva";60;1
"Unit";"Zergling";"Larva";60;1
"Unit";"Zergling";"Larva";60;1
"Unit";"Zergling";"Larva";60;1
"Unit";"Zergling";"Larva";60;1
"Unit";"Zergling";"Larva";60;1
"Unit";"Zergling";"Larva";60;1
"Unit";"Zergling";"Larva";60;1
"Unit";"Zergling";"Larva";60;1
"Unit";"Zergling";"Larva";60;1
"Unit";"Zergling";"Larva";60;1
"Unit";"Zergling";"Larva";60;1
"Unit";"Zergling";"Larva";60;1
"Building";"BanelingNest";NA;58;0
"Unit";"Zergling";"Larva";60;1
"Unit";"Zergling";"Larva";60;1
"Unit";"Zergling";"Larva";66;1
"Unit";"Zergling";"Larva";66;1
"Unit";"Zergling";"Larva";66;1
"Unit";"Zergling";"Larva";66;1
"Building";"CreepTumorQueen";NA;76;0
"Building";"CreepTumor";NA;76;0
"Building";"CreepTumor";NA;76;0
"Building";"CreepTumor";NA;76;0
"Building";"CreepTumor";NA;88;0
"Building";"CreepTumor";NA;88;0
"Building";"CreepTumor";NA;88;0
"Building";"Hatchery";NA;60;0
"Building";"CreepTumor";NA;90;0
"Building";"HydraliskDen";NA;88;0
"Upgrade";"ZergMeleeWeaponsLevel1";"EvolutionChamber";60;0
"Unit";"Overlord";"Larva";92;0
"Unit";"Overlord";"Larva";92;0
"Unit";"Overlord";"Larva";92;0
"Unit";"Overlord";"Larva";92;0
"Unit";"Baneling";"Zergling";92;0
"Unit";"Baneling";"Zergling";92;0
"Unit";"Baneling";"Zergling";92;0
"Unit";"Baneling";"Zergling";92;0
"Unit";"Baneling";"Zergling";92;0
"Unit";"Baneling";"Zergling";92;0
"Unit";"Baneling";"Zergling";92;0
"Unit";"Baneling";"Zergling";92;0
"Unit";"Baneling";"Zergling";92;0
"Building";"CreepTumor";NA;92;0
"Building";"CreepTumor";NA;92;0
"Unit";"Zergling";"Larva";92;1
"Unit";"Zergling";"Larva";92;1
"Unit";"Zergling";"Larva";92;1
"Unit";"Zergling";"Larva";92;1
"Unit";"Zergling";"Larva";92;1
"Unit";"Zergling";"Larva";92;1
"Unit";"Zergling";"Larva";92;1
"Unit";"Zergling";"Larva";92;1
"Unit";"Zergling";"Larva";92;1
"Unit";"Zergling";"Larva";92;1
"Unit";"Zergling";"Larva";92;1
"Unit";"Zergling";"Larva";92;1
"Unit";"Zergling";"Larva";92;1
"Unit";"Zergling";"Larva";92;1
"Building";"CreepTumor";NA;106;0
"Building";"CreepTumor";NA;106;0
"Unit";"Hydralisk";"Larva";106;2
"Unit";"Hydralisk";"Larva";106;2
"Unit";"Hydralisk";"Larva";106;2
"Unit";"Hydralisk";"Larva";106;2
"Unit";"Baneling";"Zergling";106;0
"Unit";"Zergling";"Larva";106;1
"Unit";"Zergling";"Larva";106;1
"Unit";"Baneling";"Zergling";106;0
"Unit";"Zergling";"Larva";106;1
"Unit";"Zergling";"Larva";106;1
"Unit";"Zergling";"Larva";106;1
"Unit";"Zergling";"Larva";106;1
"Unit";"Baneling";"Zergling";106;0
"Unit";"Zergling";"Larva";106;1
"Unit";"Zergling";"Larva";106;1
"Unit";"Zergling";"Larva";106;1
"Unit";"Zergling";"Larva";106;1
"Unit";"Baneling";"Zergling";106;0
"Unit";"Baneling";"Zergling";106;0
"Unit";"Baneling";"Zergling";106;0
"Building";"CreepTumor";NA;111;0
"Building";"CreepTumor";NA;111;0
"Unit";"Zergling";"Larva";111;1
"Unit";"Zergling";"Larva";111;1
"Unit";"Zergling";"Larva";119;1
"Unit";"Zergling";"Larva";119;1
"Unit";"Zergling";"Larva";119;1
"Unit";"Zergling";"Larva";119;1
"Unit";"Hydralisk";"Larva";111;2
"Upgrade";"EvolveGroovedSpines";"HydraliskDen";106;0
"Unit";"Zergling";"Larva";129;1
"Unit";"Zergling";"Larva";129;1
"Unit";"Hydralisk";"Larva";129;2
"Unit";"Zergling";"Larva";129;1
"Unit";"Zergling";"Larva";129;1
"Unit";"Zergling";"Larva";131;1
"Unit";"Zergling";"Larva";131;1
"Unit";"Zergling";"Larva";131;1
"Unit";"Zergling";"Larva";131;1
"Unit";"Zergling";"Larva";147;1
"Unit";"Zergling";"Larva";147;1
"Unit";"Zergling";"Larva";147;1
"Unit";"Zergling";"Larva";147;1
"Unit";"Baneling";"Zergling";147;0
"Unit";"Baneling";"Zergling";147;0
"Unit";"Hydralisk";"Larva";147;2
"Unit";"Hydralisk";"Larva";147;2
"Unit";"Hydralisk";"Larva";147;2
"Unit";"Hydralisk";"Larva";147;2
"Unit";"Hydralisk";"Larva";147;2
"Unit";"Zergling";"Larva";161;1
"Unit";"Zergling";"Larva";161;1
"Unit";"Zergling";"Larva";161;1
"Unit";"Zergling";"Larva";161;1
"Unit";"Zergling";"Larva";161;1
"Unit";"Zergling";"Larva";161;1
"Unit";"Zergling";"Larva";161;1
"Unit";"Zergling";"Larva";161;1
"Unit";"Zergling";"Larva";161;1
"Unit";"Zergling";"Larva";161;1
"Unit";"Zergling";"Larva";161;1
"Unit";"Zergling";"Larva";161;1
"Unit";"Zergling";"Larva";161;1
"Unit";"Zergling";"Larva";161;1
"Unit";"Hydralisk";"Larva";161;2
"Unit";"Hydralisk";"Larva";161;2
"Unit";"Hydralisk";"Larva";161;2
"Unit";"Zergling";"Larva";161;1
"Unit";"Zergling";"Larva";161;1
"Unit";"Zergling";"Larva";161;1
"Unit";"Zergling";"Larva";161;1
"Unit";"Zergling";"Larva";161;1
"Unit";"Zergling";"Larva";161;1
"Unit";"Zergling";"Larva";161;1
"Unit";"Zergling";"Larva";161;1
"Unit";"Zergling";"Larva";161;1
"Unit";"Zergling";"Larva";161;1
"Unit";"Zergling";"Larva";161;1
"Unit";"Zergling";"Larva";161;1
"Unit";"Zergling";"Larva";161;1
"Unit";"Zergling";"Larva";161;1
"Unit";"Baneling";"Zergling";181;0
"Unit";"Baneling";"Zergling";181;0
"Unit";"Baneling";"Zergling";181;0
"Unit";"Baneling";"Zergling";181;0
"Unit";"Baneling";"Zergling";181;0
"Unit";"Baneling";"Zergling";181;0
"Unit";"Zergling";"Larva";181;1
"Unit";"Zergling";"Larva";181;1
"Unit";"Zergling";"Larva";181;1
"Unit";"Zergling";"Larva";181;1
"Unit";"Zergling";"Larva";181;1
"Unit";"Zergling";"Larva";181;1
"Unit";"Zergling";"Larva";181;1
"Unit";"Zergling";"Larva";181;1
"Unit";"Baneling";"Zergling";195;0
"Unit";"Baneling";"Zergling";195;0
"Unit";"Baneling";"Zergling";195;0
"Unit";"Baneling";"Zergling";195;0
"Unit";"Baneling";"Zergling";195;0
"Unit";"Queen";"Hatchery";161;2
"Unit";"Queen";"Hatchery";161;2
"Unit";"Zergling";"Larva";195;1
"Unit";"Zergling";"Larva";195;1
"Unit";"Hydralisk";"Larva";195;2
"Unit";"Zergling";"Larva";203;1
"Unit";"Zergling";"Larva";203;1
"Unit";"Zergling";"Larva";213;1
"Unit";"Zergling";"Larva";213;1
"Unit";"Zergling";"Larva";213;1
"Unit";"Zergling";"Larva";213;1
"Unit";"Zergling";"Larva";213;1
"Unit";"Zergling";"Larva";213;1
"Unit";"Zergling";"Larva";213;1
"Unit";"Zergling";"Larva";213;1
"Building";"Hatchery";NA;175;0
"Unit";"Queen";"Hatchery";207;2
"Unit";"Queen";"Hatchery";207;2
"Unit";"Baneling";"Zergling";225;0
"Unit";"Hydralisk";"Larva";221;2
"Unit";"Hydralisk";"Larva";221;2
"Unit";"Hydralisk";"Larva";221;2
"Unit";"Hydralisk";"Larva";221;2
"Unit";"Hydralisk";"Larva";221;2
"Unit";"Hydralisk";"Larva";221;2
"Unit";"Hydralisk";"Larva";221;2
"Unit";"Hydralisk";"Larva";221;2
"Unit";"Hydralisk";"Larva";221;2
"Unit";"Zergling";"Larva";225;1
"Unit";"Zergling";"Larva";225;1
"Unit";"Zergling";"Larva";225;1
"Unit";"Zergling";"Larva";225;1
"Unit";"Zergling";"Larva";225;1
"Unit";"Zergling";"Larva";225;1
"Unit";"Zergling";"Larva";225;1
"Unit";"Zergling";"Larva";225;1
"Unit";"Baneling";"Zergling";225;0
"Unit";"Baneling";"Zergling";225;0
"Unit";"Baneling";"Zergling";225;0
"Unit";"Zergling";"Larva";243;1
"Unit";"Zergling";"Larva";243;1
"Unit";"Zergling";"Larva";243;1
"Unit";"Zergling";"Larva";243;1
"Unit";"Zergling";"Larva";243;1
"Unit";"Zergling";"Larva";243;1
"Unit";"Queen";"Hatchery";225;2
"Unit";"Queen";"Hatchery";243;2
"Unit";"Zergling";"Larva";257;1
"Unit";"Zergling";"Larva";257;1
"Unit";"Zergling";"Larva";257;1
"Unit";"Zergling";"Larva";257;1
"Unit";"Zergling";"Larva";257;1
"Unit";"Zergling";"Larva";257;1
"Unit";"Zergling";"Larva";257;1
"Unit";"Zergling";"Larva";257;1
"Unit";"Zergling";"Larva";257;1
"Unit";"Zergling";"Larva";257;1
"Building";"CreepTumor";NA;259;0
"Building";"CreepTumor";NA;259;0
"Unit";"Hydralisk";"Larva";257;2
"Unit";"Hydralisk";"Larva";257;2
"Unit";"Hydralisk";"Larva";257;2
"Building";"CreepTumorQueen";NA;259;0
