"type";"unit_name";"on_building";"total_supply";"supply"
"Unit";"Overlord";"Larva";12;0
"Building";"Extractor";NA;18;0
"Unit";"Overlord";"Larva";21;0
"Building";"SpawningPool";NA;19;0
"Building";"Hatchery";NA;17;0
"Unit";"Zergling";"Larva";22;1
"Unit";"Zergling";"Larva";22;1
"Unit";"Queen";"Hatchery";22;2
"Unit";"Queen";"Hatchery";23;2
"Unit";"Zergling";"Larva";34;1
"Unit";"Zergling";"Larva";34;1
"Unit";"Zergling";"Larva";34;1
"Unit";"Zergling";"Larva";34;1
"Unit";"Zergling";"Larva";34;1
"Unit";"Zergling";"Larva";34;1
"Unit";"Overlord";"Larva";34;0
"Unit";"Queen";"Hatchery";34;2
"Building";"CreepTumorQueen";NA;45;0
"Unit";"Overlord";"Larva";45;0
"Building";"SporeCrawler";NA;51;0
"Building";"Hatchery";NA;34;0
"Unit";"Overlord";"Larva";51;0
"Building";"SporeCrawler";NA;51;0
"Building";"CreepTumor";NA;53;0
"Building";"CreepTumorQueen";NA;54;0
"Building";"Extractor";NA;61;0
"Unit";"Queen";"Hatchery";55;2
"Building";"SporeCrawler";NA;61;0
"Unit";"Overlord";"Larva";69;0
"Unit";"Overlord";"Larva";69;0
"Building";"CreepTumor";NA;74;0
"Building";"CreepTumor";NA;74;0
"Unit";"Overlord";"Larva";74;0
"Building";"CreepTumor";NA;83;0
"Building";"EvolutionChamber";NA;74;0
"Building";"EvolutionChamber";NA;74;0
"Unit";"Overlord";"Larva";83;0
"Building";"CreepTumorQueen";NA;90;0
"Unit";"Zergling";"Larva";88;1
"Unit";"Zergling";"Larva";88;1
"Unit";"Zergling";"Larva";88;1
"Unit";"Zergling";"Larva";88;1
"Unit";"Zergling";"Larva";88;1
"Unit";"Zergling";"Larva";88;1
"Building";"CreepTumor";NA;90;0
"Building";"Extractor";NA;88;0
"Building";"CreepTumorQueen";NA;90;0
"Building";"Extractor";NA;88;0
"Building";"BanelingNest";NA;74;0
"Unit";"Zergling";"Larva";90;1
"Unit";"Zergling";"Larva";90;1
"Unit";"Zergling";"Larva";90;1
"Unit";"Zergling";"Larva";90;1
"Unit";"Zergling";"Larva";90;1
"Unit";"Zergling";"Larva";90;1
"Unit";"Zergling";"Larva";90;1
"Unit";"Zergling";"Larva";90;1
"Unit";"Zergling";"Larva";90;1
"Unit";"Zergling";"Larva";90;1
"Unit";"Zergling";"Larva";90;1
"Unit";"Zergling";"Larva";90;1
"Unit";"Zergling";"Larva";90;1
"Unit";"Zergling";"Larva";90;1
"Unit";"Zergling";"Larva";90;1
"Unit";"Zergling";"Larva";90;1
"Unit";"Zergling";"Larva";90;1
"Unit";"Zergling";"Larva";90;1
"Unit";"Overlord";"Larva";114;0
"Unit";"Overlord";"Larva";114;0
"Building";"Extractor";NA;114;0
"Building";"HydraliskDen";NA;114;0
"Unit";"Zergling";"Larva";117;1
"Unit";"Zergling";"Larva";117;1
"Unit";"Zergling";"Larva";117;1
"Unit";"Zergling";"Larva";117;1
"Unit";"Zergling";"Larva";117;1
"Unit";"Zergling";"Larva";117;1
"Unit";"Zergling";"Larva";117;1
"Unit";"Zergling";"Larva";117;1
"Unit";"Zergling";"Larva";117;1
"Unit";"Zergling";"Larva";117;1
"Unit";"Zergling";"Larva";117;1
"Unit";"Zergling";"Larva";117;1
"Unit";"Zergling";"Larva";117;1
"Unit";"Zergling";"Larva";117;1
"Unit";"Zergling";"Larva";117;1
"Unit";"Zergling";"Larva";117;1
"Unit";"Zergling";"Larva";117;1
"Unit";"Zergling";"Larva";117;1
"Unit";"Zergling";"Larva";117;1
"Unit";"Zergling";"Larva";117;1
"Unit";"Zergling";"Larva";117;1
"Unit";"Zergling";"Larva";117;1
"Unit";"Zergling";"Larva";117;1
"Unit";"Zergling";"Larva";117;1
"Unit";"Zergling";"Larva";117;1
"Unit";"Zergling";"Larva";117;1
"Building";"Hatchery";NA;88;0
"Building";"CreepTumor";NA;117;0
"Building";"CreepTumor";NA;117;0
"Building";"CreepTumor";NA;117;0
"Building";"CreepTumor";NA;117;0
"Unit";"Overlord";"Larva";117;0
"Unit";"Overlord";"Larva";117;0
"Unit";"Overlord";"Larva";117;0
"Unit";"Overlord";"Larva";117;0
"Building";"CreepTumor";NA;144;0
"Building";"CreepTumor";NA;144;0
"Building";"CreepTumor";NA;144;0
"Building";"Extractor";NA;144;0
"Unit";"Hydralisk";"Larva";150;2
"Unit";"Hydralisk";"Larva";150;2
"Unit";"Hydralisk";"Larva";150;2
"Unit";"Hydralisk";"Larva";150;2
"Building";"Hatchery";NA;114;0
"Building";"CreepTumor";NA;150;0
"Unit";"Hydralisk";"Larva";150;2
"Unit";"Hydralisk";"Larva";150;2
"Unit";"Hydralisk";"Larva";150;2
"Unit";"Hydralisk";"Larva";150;2
"Unit";"Queen";"Hatchery";150;2
"Upgrade";"ZergMeleeWeaponsLevel1";"EvolutionChamber";117;0
"Upgrade";"ZergMissileWeaponsLevel1";"EvolutionChamber";117;0
"Upgrade";"EvolveGroovedSpines";"HydraliskDen";144;0
"Unit";"Baneling";"Zergling";180;0
"Unit";"Baneling";"Zergling";180;0
"Unit";"Baneling";"Zergling";180;0
"Unit";"Baneling";"Zergling";180;0
"Unit";"Baneling";"Zergling";180;0
"Unit";"Baneling";"Zergling";180;0
"Unit";"Baneling";"Zergling";180;0
"Unit";"Baneling";"Zergling";180;0
"Unit";"Zergling";"Larva";189;1
"Unit";"Zergling";"Larva";189;1
"Unit";"Zergling";"Larva";191;1
"Unit";"Zergling";"Larva";191;1
"Unit";"Zergling";"Larva";191;1
"Unit";"Zergling";"Larva";191;1
"Unit";"Zergling";"Larva";191;1
"Unit";"Zergling";"Larva";191;1
"Unit";"Zergling";"Larva";191;1
"Unit";"Zergling";"Larva";191;1
"Unit";"Zergling";"Larva";191;1
"Unit";"Zergling";"Larva";191;1
"Unit";"Zergling";"Larva";191;1
"Unit";"Zergling";"Larva";191;1
"Unit";"Zergling";"Larva";191;1
"Unit";"Zergling";"Larva";191;1
"Unit";"Overlord";"Larva";213;0
"Building";"Hatchery";NA;189;0
"Building";"CreepTumor";NA;213;0
"Building";"CreepTumor";NA;213;0
"Building";"CreepTumor";NA;213;0
"Building";"Extractor";NA;213;0
"Building";"Extractor";NA;213;0
"Unit";"Overlord";"Larva";213;0
"Unit";"Overlord";"Larva";213;0
"Unit";"Hydralisk";"Larva";213;2
"Unit";"Hydralisk";"Larva";213;2
"Unit";"Overlord";"Larva";213;0
"Unit";"Overlord";"Larva";213;0
"Unit";"Hydralisk";"Larva";213;2
"Unit";"Hydralisk";"Larva";213;2
"Unit";"Hydralisk";"Larva";213;2
"Unit";"Hydralisk";"Larva";213;2
"Unit";"Overlord";"Larva";213;0
"Unit";"Overlord";"Larva";213;0
"Unit";"Hydralisk";"Larva";213;2
"Unit";"Baneling";"Zergling";213;0
"Unit";"Baneling";"Zergling";213;0
"Unit";"Baneling";"Zergling";213;0
"Unit";"Baneling";"Zergling";213;0
"Unit";"Baneling";"Zergling";213;0
"Unit";"Baneling";"Zergling";213;0
"Unit";"Baneling";"Zergling";213;0
"Unit";"Baneling";"Zergling";213;0
"Unit";"Baneling";"Zergling";213;0
"Unit";"Baneling";"Zergling";213;0
"Unit";"Baneling";"Zergling";213;0
"Unit";"Baneling";"Zergling";213;0
"Unit";"Baneling";"Zergling";213;0
"Unit";"Baneling";"Zergling";213;0
"Unit";"Baneling";"Zergling";213;0
"Unit";"Baneling";"Zergling";213;0
"Unit";"Baneling";"Zergling";213;0
"Unit";"Baneling";"Zergling";213;0
"Unit";"Baneling";"Zergling";213;0
"Unit";"Baneling";"Zergling";213;0
"Building";"Hatchery";NA;191;0
"Unit";"Zergling";"Larva";213;1
"Unit";"Zergling";"Larva";213;1
"Unit";"Zergling";"Larva";213;1
"Unit";"Zergling";"Larva";213;1
"Unit";"Zergling";"Larva";213;1
"Unit";"Zergling";"Larva";213;1
"Unit";"Zergling";"Larva";213;1
"Unit";"Zergling";"Larva";213;1
"Unit";"Zergling";"Larva";213;1
"Unit";"Zergling";"Larva";213;1
"Building";"InfestationPit";NA;213;0
"Unit";"Zergling";"Larva";227;1
"Unit";"Zergling";"Larva";227;1
"Unit";"Zergling";"Larva";227;1
"Unit";"Zergling";"Larva";227;1
"Unit";"Zergling";"Larva";227;1
"Unit";"Zergling";"Larva";227;1
"Unit";"Zergling";"Larva";227;1
"Unit";"Zergling";"Larva";227;1
"Unit";"Zergling";"Larva";227;1
"Unit";"Zergling";"Larva";227;1
"Unit";"Zergling";"Larva";227;1
"Unit";"Zergling";"Larva";227;1
"Unit";"Zergling";"Larva";227;1
"Unit";"Zergling";"Larva";227;1
"Unit";"Zergling";"Larva";227;1
"Unit";"Zergling";"Larva";227;1
"Unit";"Zergling";"Larva";227;1
"Unit";"Zergling";"Larva";227;1
"Building";"CreepTumor";NA;227;0
"Upgrade";"ZergMeleeWeaponsLevel2";"EvolutionChamber";191;0
"Upgrade";"ZergMissileWeaponsLevel2";"EvolutionChamber";191;0
"Unit";"Zergling";"Larva";255;1
"Unit";"Zergling";"Larva";255;1
"Unit";"Zergling";"Larva";255;1
"Unit";"Zergling";"Larva";255;1
"Unit";"Zergling";"Larva";255;1
"Unit";"Zergling";"Larva";255;1
"Unit";"Zergling";"Larva";255;1
"Unit";"Zergling";"Larva";255;1
"Unit";"Zergling";"Larva";255;1
"Unit";"Zergling";"Larva";255;1
"Unit";"Zergling";"Larva";255;1
"Unit";"Zergling";"Larva";255;1
"Unit";"Zergling";"Larva";255;1
"Unit";"Zergling";"Larva";255;1
"Unit";"Zergling";"Larva";255;1
"Unit";"Zergling";"Larva";255;1
"Upgrade";"EvolveMuscularAugments";"HydraliskDen";213;0
