"type";"unit_name";"on_building";"total_supply";"supply"
"Unit";"Overlord";"Larva";14;0
"Building";"SpawningPool";NA;12;0
"Unit";"Zergling";"Larva";15;1
"Unit";"Zergling";"Larva";15;1
"Unit";"Zergling";"Larva";15;1
"Unit";"Zergling";"Larva";15;1
"Unit";"Zergling";"Larva";15;1
"Unit";"Zergling";"Larva";15;1
"Unit";"Zergling";"Larva";15;1
"Unit";"Zergling";"Larva";15;1
"Unit";"Queen";"Hatchery";15;2
"Building";"Extractor";NA;25;0
"Unit";"Overlord";"Larva";27;0
"Unit";"Queen";"Hatchery";26;2
"Building";"Hatchery";NA;23;0
"Building";"CreepTumorQueen";NA;36;0
"Unit";"Zergling";"Larva";41;1
"Unit";"Zergling";"Larva";41;1
"Unit";"Zergling";"Larva";41;1
"Unit";"Zergling";"Larva";41;1
"Unit";"Zergling";"Larva";41;1
"Unit";"Zergling";"Larva";41;1
"Unit";"Overlord";"Larva";41;0
"Building";"CreepTumor";NA;41;0
"Unit";"Overlord";"Larva";47;0
"Building";"SporeCrawler";NA;54;0
"Building";"SporeCrawler";NA;54;0
"Building";"CreepTumor";NA;54;0
"Building";"Hatchery";NA;38;0
"Building";"SporeCrawler";NA;54;0
"Building";"Extractor";NA;58;0
"Unit";"Overlord";"Larva";62;0
"Unit";"Overlord";"Larva";63;0
"Building";"CreepTumor";NA;65;0
"Unit";"Queen";"Hatchery";62;2
"Unit";"Queen";"Hatchery";62;2
"Building";"SporeCrawler";NA;65;0
"Building";"EvolutionChamber";NA;65;0
"Building";"Extractor";NA;69;0
"Building";"CreepTumor";NA;75;0
"Building";"RoachWarren";NA;65;0
"Building";"CreepTumorQueen";NA;83;0
"Building";"Extractor";NA;83;0
"Building";"CreepTumor";NA;93;0
"Unit";"Overlord";"Larva";93;0
"Unit";"Overlord";"Larva";93;0
"Unit";"Overlord";"Larva";93;0
"Building";"CreepTumor";NA;93;0
"Building";"CreepTumorQueen";NA;93;0
"Building";"SpineCrawler";NA;87;0
"Unit";"Roach";"Larva";93;2
"Unit";"Roach";"Larva";93;2
"Unit";"Roach";"Larva";93;2
"Unit";"Roach";"Larva";93;2
"Unit";"Roach";"Larva";93;2
"Unit";"Roach";"Larva";93;2
"Building";"HydraliskDen";NA;93;0
"Unit";"Roach";"Larva";105;2
"Unit";"Roach";"Larva";105;2
"Unit";"Roach";"Larva";105;2
"Unit";"Roach";"Larva";105;2
"Unit";"Roach";"Larva";105;2
"Unit";"Roach";"Larva";105;2
"Unit";"Roach";"Larva";105;2
"Building";"CreepTumor";NA;105;0
"Building";"CreepTumor";NA;119;0
"Unit";"Overlord";"Larva";119;0
"Unit";"Overlord";"Larva";119;0
"Unit";"Overlord";"Larva";119;0
"Unit";"Overlord";"Larva";119;0
"Unit";"Overlord";"Larva";119;0
"Upgrade";"ZergMissileWeaponsLevel1";"EvolutionChamber";93;0
"Upgrade";"GlialReconstitution";"RoachWarren";93;0
"Unit";"Roach";"Larva";119;2
"Unit";"Roach";"Larva";121;2
"Unit";"Roach";"Larva";121;2
"Unit";"Roach";"Larva";121;2
"Unit";"Roach";"Larva";123;2
"Unit";"Roach";"Larva";123;2
"Unit";"Roach";"Larva";123;2
"Unit";"Roach";"Larva";123;2
"Unit";"Roach";"Larva";123;2
"Unit";"Roach";"Larva";123;2
"Unit";"Roach";"Larva";123;2
"Unit";"Roach";"Larva";123;2
"Unit";"Roach";"Larva";123;2
"Unit";"Roach";"Larva";123;2
"Unit";"Roach";"Larva";123;2
"Unit";"Roach";"Larva";129;2
"Unit";"Roach";"Larva";129;2
"Unit";"Roach";"Larva";129;2
"Unit";"Roach";"Larva";129;2
"Building";"Hatchery";NA;119;0
"Building";"CreepTumor";NA;171;0
"Building";"CreepTumor";NA;171;0
"Unit";"Hydralisk";"Larva";171;2
"Unit";"Queen";"Hatchery";165;2
"Unit";"Queen";"Hatchery";167;2
"Unit";"Queen";"Hatchery";171;2
"Unit";"Hydralisk";"Larva";176;2
"Unit";"Hydralisk";"Larva";177;2
"Unit";"Hydralisk";"Larva";177;2
"Unit";"Zergling";"Larva";184;1
"Unit";"Zergling";"Larva";184;1
"Unit";"Zergling";"Larva";184;1
"Unit";"Zergling";"Larva";184;1
"Unit";"Zergling";"Larva";184;1
"Unit";"Zergling";"Larva";184;1
"Unit";"Zergling";"Larva";184;1
"Unit";"Zergling";"Larva";184;1
"Unit";"Zergling";"Larva";184;1
"Unit";"Zergling";"Larva";184;1
"Unit";"Zergling";"Larva";184;1
"Unit";"Zergling";"Larva";184;1
"Unit";"Zergling";"Larva";184;1
"Unit";"Zergling";"Larva";184;1
"Unit";"Hydralisk";"Larva";182;2
"Unit";"Hydralisk";"Larva";182;2
"Building";"Extractor";NA;184;0
"Building";"Extractor";NA;184;0
"Unit";"Zergling";"Larva";190;1
"Unit";"Zergling";"Larva";190;1
"Unit";"Zergling";"Larva";190;1
"Unit";"Zergling";"Larva";190;1
"Unit";"Zergling";"Larva";190;1
"Unit";"Zergling";"Larva";190;1
"Unit";"Hydralisk";"Larva";190;2
"Unit";"Hydralisk";"Larva";190;2
"Unit";"Overlord";"Larva";208;0
"Unit";"Overlord";"Larva";208;0
"Unit";"Overlord";"Larva";208;0
"Unit";"Overlord";"Larva";208;0
"Upgrade";"EvolveGroovedSpines";"HydraliskDen";182;0
"Unit";"Zergling";"Larva";218;1
"Unit";"Zergling";"Larva";218;1
"Unit";"Zergling";"Larva";218;1
"Unit";"Zergling";"Larva";218;1
"Unit";"Hydralisk";"Larva";218;2
"Unit";"Hydralisk";"Larva";218;2
"Unit";"Hydralisk";"Larva";218;2
"Unit";"Hydralisk";"Larva";218;2
"Unit";"Overlord";"Larva";218;0
"Unit";"Overlord";"Larva";218;0
"Unit";"Overlord";"Larva";218;0
"Building";"CreepTumor";NA;218;0
"Unit";"Zergling";"Larva";218;1
"Unit";"Zergling";"Larva";218;1
"Unit";"Zergling";"Larva";218;1
"Unit";"Zergling";"Larva";218;1
"Unit";"Zergling";"Larva";218;1
"Unit";"Zergling";"Larva";218;1
"Unit";"Zergling";"Larva";218;1
"Unit";"Zergling";"Larva";218;1
"Unit";"Hydralisk";"Larva";230;2
"Unit";"Hydralisk";"Larva";230;2
"Unit";"Hydralisk";"Larva";230;2
"Unit";"Hydralisk";"Larva";230;2
"Upgrade";"ZergMissileWeaponsLevel2";"EvolutionChamber";182;0
"Unit";"Hydralisk";"Larva";238;2
"Unit";"Hydralisk";"Larva";238;2
"Unit";"Hydralisk";"Larva";238;2
"Unit";"Hydralisk";"Larva";238;2
"Unit";"Hydralisk";"Larva";238;2
"Building";"RoachWarren";NA;230;0
"Building";"Hatchery";NA;218;0
"Building";"LurkerDenMP";NA;218;0
"Unit";"Queen";"Hatchery";246;2
"Unit";"Queen";"Hatchery";256;2
"Unit";"Roach";"Larva";272;2
"Unit";"Roach";"Larva";272;2
"Unit";"Roach";"Larva";272;2
"Unit";"Roach";"Larva";272;2
"Unit";"Roach";"Larva";272;2
"Unit";"Roach";"Larva";272;2
"Unit";"Roach";"Larva";272;2
