"type";"unit_name";"on_building";"total_supply_lag";"supply"
"Unit";"Overlord";"Larva";14;0
"Building";"Hatchery";NA;17;0
"Building";"Extractor";NA;19;0
"Building";"SpawningPool";NA;19;0
"Unit";"Overlord";"Larva";22;0
"Unit";"Zergling";"Larva";22;1
"Unit";"Zergling";"Larva";23;1
"Unit";"Zergling";"Larva";24;1
"Unit";"Zergling";"Larva";25;1
"Unit";"Queen";"Hatchery";26;2
"Unit";"Queen";"Hatchery";28;2
"Building";"Hatchery";NA;37;0
"Unit";"Zergling";"Larva";37;1
"Unit";"Zergling";"Larva";38;1
"Unit";"Overlord";"Larva";39;0
"Unit";"Queen";"Hatchery";41;2
"Unit";"Zergling";"Larva";45;1
"Unit";"Zergling";"Larva";46;1
"Unit";"Overlord";"Larva";49;0
"Building";"SporeCrawler";NA;55;0
"Building";"CreepTumorQueen";NA;55;0
"Unit";"Overlord";"Larva";55;0
"Unit";"Overlord";"Larva";58;0
"Building";"CreepTumor";NA;63;0
"Building";"SporeCrawler";NA;63;0
"Unit";"Queen";"Hatchery";63;2
"Building";"SporeCrawler";NA;67;0
"Building";"Extractor";NA;69;0
"Building";"Extractor";NA;69;0
"Unit";"Overlord";"Larva";71;0
"Building";"CreepTumorQueen";NA;76;0
"Building";"CreepTumor";NA;76;0
"Building";"Extractor";NA;83;0
"Unit";"Queen";"Hatchery";83;2
"Building";"HydraliskDen";NA;85;0
"Unit";"Overlord";"Larva";85;0
"Unit";"Zergling";"Larva";85;1
"Unit";"Zergling";"Larva";86;1
"Unit";"Zergling";"Larva";87;1
"Unit";"Zergling";"Larva";88;1
"Unit";"Zergling";"Larva";89;1
"Unit";"Zergling";"Larva";90;1
"Unit";"Zergling";"Larva";91;1
"Unit";"Zergling";"Larva";92;1
"Unit";"Zergling";"Larva";93;1
"Unit";"Zergling";"Larva";94;1
"Unit";"Queen";"Hatchery";95;2
"Building";"CreepTumor";NA;97;0
"Building";"CreepTumorQueen";NA;97;0
"Unit";"Queen";"Hatchery";97;2
"Building";"CreepTumor";NA;99;0
"Unit";"Zergling";"Larva";99;1
"Unit";"Zergling";"Larva";100;1
"Unit";"Zergling";"Larva";101;1
"Unit";"Zergling";"Larva";102;1
"Unit";"Zergling";"Larva";103;1
"Unit";"Zergling";"Larva";104;1
"Unit";"Overlord";"Larva";105;0
"Unit";"Overlord";"Larva";105;0
"Unit";"Hydralisk";"Larva";105;2
"Unit";"Hydralisk";"Larva";107;2
"Unit";"Hydralisk";"Larva";109;2
"Unit";"Hydralisk";"Larva";111;2
"Unit";"Hydralisk";"Larva";113;2
"Building";"CreepTumor";NA;115;0
"Unit";"Hydralisk";"Larva";115;2
"Unit";"Hydralisk";"Larva";117;2
"Unit";"Hydralisk";"Larva";119;2
"Building";"CreepTumor";NA;121;0
"Unit";"Hydralisk";"Larva";121;2
"Unit";"Hydralisk";"Larva";123;2
"Unit";"Hydralisk";"Larva";125;2
"Unit";"Overlord";"Larva";127;0
"Unit";"Overlord";"Larva";127;0
"Unit";"Overlord";"Larva";127;0
"Unit";"Overlord";"Larva";127;0
"Unit";"Overlord";"Larva";127;0
"Unit";"Hydralisk";"Larva";127;2
"Unit";"Hydralisk";"Larva";129;2
"Building";"CreepTumorQueen";NA;131;0
"Building";"CreepTumorQueen";NA;131;0
"Building";"CreepTumorQueen";NA;131;0
"Unit";"Queen";"Hatchery";131;2
"Building";"NydusNetwork";NA;133;0
"Building";"CreepTumor";NA;133;0
"Unit";"Queen";"Hatchery";133;2
"Unit";"Overlord";"Larva";135;0
"Unit";"Queen";"Hatchery";135;2
"Unit";"Hydralisk";"Larva";137;2
"Unit";"Hydralisk";"Larva";139;2
"Unit";"Hydralisk";"Larva";141;2
"Unit";"Hydralisk";"Larva";143;2
"Unit";"Hydralisk";"Larva";145;2
"Unit";"Zergling";"Larva";147;1
"Unit";"Zergling";"Larva";148;1
"Unit";"Zergling";"Larva";149;1
"Unit";"Zergling";"Larva";150;1
"Unit";"Zergling";"Larva";151;1
"Unit";"Zergling";"Larva";152;1
"Unit";"Zergling";"Larva";153;1
"Unit";"Zergling";"Larva";154;1
"Unit";"Zergling";"Larva";155;1
"Unit";"Zergling";"Larva";156;1
"Building";"CreepTumor";NA;157;0
"Building";"CreepTumor";NA;157;0
"Building";"CreepTumor";NA;157;0
"Unit";"Hydralisk";"Larva";157;2
"Building";"NydusCanal";NA;159;0
"Unit";"Hydralisk";"Larva";159;2
"Unit";"Zergling";"Larva";161;1
"Unit";"Zergling";"Larva";162;1
"Unit";"Hydralisk";"Larva";163;2
"Unit";"Zergling";"Larva";165;1
"Unit";"Zergling";"Larva";166;1
"Unit";"Hydralisk";"Larva";167;2
"Unit";"Overlord";"Larva";169;0
"Unit";"Zergling";"Larva";169;1
"Unit";"Zergling";"Larva";170;1
"Unit";"Zergling";"Larva";171;1
"Unit";"Zergling";"Larva";172;1
"Unit";"Hydralisk";"Larva";173;2
"Unit";"Zergling";"Larva";175;1
"Unit";"Zergling";"Larva";176;1
"Unit";"Hydralisk";"Larva";177;2
"Unit";"Hydralisk";"Larva";179;2
"Unit";"Zergling";"Larva";181;1
"Unit";"Zergling";"Larva";182;1
"Unit";"Hydralisk";"Larva";183;2
"Unit";"Hydralisk";"Larva";185;2
"Unit";"Zergling";"Larva";187;1
"Unit";"Zergling";"Larva";188;1
"Unit";"Hydralisk";"Larva";189;2
"Unit";"Zergling";"Larva";191;1
"Unit";"Zergling";"Larva";192;1
"Unit";"Zergling";"Larva";193;1
"Unit";"Zergling";"Larva";194;1
"Unit";"Hydralisk";"Larva";195;2
"Unit";"Zergling";"Larva";197;1
"Unit";"Zergling";"Larva";198;1
"Unit";"Zergling";"Larva";199;1
"Unit";"Zergling";"Larva";200;1
"Unit";"Zergling";"Larva";201;1
"Unit";"Zergling";"Larva";202;1
"Unit";"Hydralisk";"Larva";203;2
"Unit";"Zergling";"Larva";205;1
"Unit";"Zergling";"Larva";206;1
"Unit";"Zergling";"Larva";207;1
"Unit";"Zergling";"Larva";208;1
"Unit";"Zergling";"Larva";209;1
"Unit";"Zergling";"Larva";210;1
"Unit";"Zergling";"Larva";211;1
"Unit";"Zergling";"Larva";212;1
"Unit";"Zergling";"Larva";213;1
"Unit";"Zergling";"Larva";214;1
"Unit";"Zergling";"Larva";215;1
"Unit";"Zergling";"Larva";216;1
"Unit";"Zergling";"Larva";217;1
"Unit";"Zergling";"Larva";218;1
"Unit";"Zergling";"Larva";219;1
"Unit";"Zergling";"Larva";220;1
"Unit";"Hydralisk";"Larva";221;2
"Unit";"Hydralisk";"Larva";223;2
"Unit";"Zergling";"Larva";225;1
"Unit";"Zergling";"Larva";226;1
"Unit";"Zergling";"Larva";227;1
"Unit";"Zergling";"Larva";228;1
"Unit";"Zergling";"Larva";229;1
"Unit";"Zergling";"Larva";230;1
"Unit";"Zergling";"Larva";231;1
"Unit";"Zergling";"Larva";232;1
"Unit";"Zergling";"Larva";233;1
"Unit";"Zergling";"Larva";234;1
"Unit";"Zergling";"Larva";235;1
"Unit";"Zergling";"Larva";236;1
"Unit";"Zergling";"Larva";237;1
"Unit";"Zergling";"Larva";238;1
"Unit";"Hydralisk";"Larva";239;2
"Unit";"Zergling";"Larva";241;1
"Unit";"Zergling";"Larva";242;1
"Unit";"Overlord";"Larva";243;0
"Unit";"Hydralisk";"Larva";243;2
"Unit";"Hydralisk";"Larva";245;2
"Unit";"Zergling";"Larva";247;1
"Unit";"Zergling";"Larva";248;1
"Unit";"Hydralisk";"Larva";249;2
"Unit";"Zergling";"Larva";251;1
"Unit";"Zergling";"Larva";252;1
"Unit";"Zergling";"Larva";253;1
"Unit";"Zergling";"Larva";254;1
"Unit";"Zergling";"Larva";255;1
"Unit";"Zergling";"Larva";256;1
"Unit";"Zergling";"Larva";257;1
"Unit";"Zergling";"Larva";258;1
"Unit";"Zergling";"Larva";259;1
"Unit";"Zergling";"Larva";260;1
"Unit";"Zergling";"Larva";261;1
"Unit";"Zergling";"Larva";262;1
"Unit";"Zergling";"Larva";263;1
"Unit";"Zergling";"Larva";264;1
"Unit";"Zergling";"Larva";265;1
"Unit";"Zergling";"Larva";266;1
"Unit";"Hydralisk";"Larva";267;2
"Unit";"Hydralisk";"Larva";269;2
"Unit";"Hydralisk";"Larva";271;2
"Unit";"Zergling";"Larva";273;1
"Unit";"Zergling";"Larva";274;1
"Unit";"Zergling";"Larva";275;1
"Unit";"Zergling";"Larva";276;1
"Unit";"Zergling";"Larva";277;1
"Unit";"Zergling";"Larva";278;1
"Unit";"Zergling";"Larva";279;1
"Unit";"Zergling";"Larva";280;1
"Unit";"Zergling";"Larva";281;1
"Unit";"Zergling";"Larva";282;1
"Unit";"Zergling";"Larva";283;1
"Unit";"Zergling";"Larva";284;1
"Unit";"Zergling";"Larva";285;1
"Unit";"Zergling";"Larva";286;1
"Unit";"Hydralisk";"Larva";287;2
"Unit";"Zergling";"Larva";289;1
"Unit";"Zergling";"Larva";290;1
"Unit";"Zergling";"Larva";291;1
"Unit";"Zergling";"Larva";292;1
"Unit";"Zergling";"Larva";293;1
"Unit";"Zergling";"Larva";294;1
"Unit";"Zergling";"Larva";295;1
"Unit";"Zergling";"Larva";296;1
"Unit";"Hydralisk";"Larva";297;2
"Unit";"Hydralisk";"Larva";299;2
"Unit";"Hydralisk";"Larva";301;2
"Upgrade";"SprayZerg";NA;303;0
"Upgrade";"SprayZerg";NA;303;0
"Upgrade";"SprayZerg";NA;303;0
"Upgrade";"zerglingmovementspeed";NA;303;0
"Upgrade";"SprayZerg";NA;303;0
"Upgrade";"EvolveGroovedSpines";NA;303;0
