"type";"unit_name";"on_building";"total_supply";"supply"
"Unit";"Overlord";"Larva";12;0
"Building";"Extractor";NA;18;0
"Unit";"Overlord";"Larva";20;0
"Building";"SpawningPool";NA;19;0
"Unit";"Queen";"Hatchery";21;2
"Building";"Extractor";NA;24;0
"Building";"Hatchery";NA;21;0
"Unit";"Zergling";"Larva";30;1
"Unit";"Zergling";"Larva";30;1
"Unit";"Zergling";"Larva";30;1
"Unit";"Zergling";"Larva";30;1
"Unit";"Zergling";"Larva";30;1
"Unit";"Zergling";"Larva";30;1
"Unit";"Overlord";"Larva";30;0
"Unit";"Overlord";"Larva";31;0
"Unit";"Zergling";"Larva";38;1
"Unit";"Zergling";"Larva";38;1
"Unit";"Queen";"Hatchery";38;2
"Unit";"Zergling";"Larva";42;1
"Unit";"Zergling";"Larva";42;1
"Unit";"Zergling";"Larva";42;1
"Unit";"Zergling";"Larva";42;1
"Unit";"Zergling";"Larva";42;1
"Unit";"Zergling";"Larva";42;1
"Unit";"Zergling";"Larva";42;1
"Unit";"Zergling";"Larva";42;1
"Unit";"Zergling";"Larva";45;1
"Unit";"Zergling";"Larva";45;1
"Building";"NydusNetwork";NA;42;0
"Unit";"Queen";"Hatchery";42;2
"Unit";"Zergling";"Larva";56;1
"Unit";"Zergling";"Larva";56;1
"Unit";"Zergling";"Larva";56;1
"Unit";"Zergling";"Larva";56;1
"Building";"NydusCanal";NA;58;0
"Unit";"Zergling";"Larva";58;1
"Unit";"Zergling";"Larva";58;1
"Unit";"Zergling";"Larva";58;1
"Unit";"Zergling";"Larva";58;1
"Unit";"Zergling";"Larva";58;1
"Unit";"Zergling";"Larva";58;1
"Unit";"Zergling";"Larva";58;1
"Unit";"Zergling";"Larva";58;1
"Unit";"Zergling";"Larva";58;1
"Unit";"Zergling";"Larva";58;1
"Unit";"Zergling";"Larva";60;1
"Unit";"Zergling";"Larva";60;1
"Unit";"Zergling";"Larva";62;1
"Unit";"Zergling";"Larva";62;1
"Unit";"Zergling";"Larva";62;1
"Unit";"Zergling";"Larva";62;1
"Building";"CreepTumorQueen";NA;62;0
"Unit";"Queen";"Hatchery";62;2
"Building";"CreepTumor";NA;83;0
"Unit";"Queen";"Hatchery";83;2
"Building";"SporeCrawler";NA;83;0
"Building";"CreepTumor";NA;88;0
"Building";"HydraliskDen";NA;83;0
"Unit";"Queen";"Hatchery";83;2
"Unit";"Queen";"Hatchery";86;2
"Building";"CreepTumorQueen";NA;92;0
"Unit";"Overlord";"Larva";92;0
"Unit";"Overlord";"Larva";92;0
"Unit";"Overlord";"Larva";92;0
"Unit";"Hydralisk";"Larva";92;2
"Building";"Hatchery";NA;88;0
"Building";"CreepTumorQueen";NA;97;0
"Building";"CreepTumorQueen";NA;97;0
"Building";"CreepTumorQueen";NA;97;0
"Building";"CreepTumor";NA;97;0
"Unit";"Hydralisk";"Larva";97;2
"Unit";"Hydralisk";"Larva";97;2
"Unit";"Hydralisk";"Larva";97;2
"Building";"NydusCanal";NA;97;0
"Upgrade";"EvolveGroovedSpines";"HydraliskDen";95;0
"Building";"CreepTumor";NA;97;0
"Building";"CreepTumorQueen";NA;105;0
"Building";"CreepTumor";NA;105;0
"Building";"CreepTumor";NA;105;0
"Unit";"Hydralisk";"Larva";103;2
"Unit";"Queen";"Hatchery";97;2
"Unit";"Hydralisk";"Larva";105;2
"Unit";"Hydralisk";"Larva";105;2
"Building";"EvolutionChamber";NA;105;0
"Building";"CreepTumorQueen";NA;109;0
"Unit";"Overlord";"Larva";109;0
"Building";"CreepTumorQueen";NA;116;0
"Building";"Hatchery";NA;97;0
"Unit";"Overlord";"Larva";116;0
"Unit";"Overlord";"Larva";116;0
"Unit";"Overlord";"Larva";116;0
"Unit";"Overlord";"Larva";116;0
"Building";"CreepTumor";NA;116;0
"Unit";"Hydralisk";"Larva";110;2
"Unit";"Hydralisk";"Larva";111;2
"Unit";"Hydralisk";"Larva";111;2
"Upgrade";"EvolveMuscularAugments";"HydraliskDen";109;0
"Unit";"Hydralisk";"Larva";130;2
"Unit";"Hydralisk";"Larva";130;2
"Unit";"Hydralisk";"Larva";130;2
"Unit";"Hydralisk";"Larva";130;2
"Unit";"Hydralisk";"Larva";130;2
"Unit";"Hydralisk";"Larva";130;2
"Unit";"Hydralisk";"Larva";130;2
"Unit";"Hydralisk";"Larva";130;2
"Unit";"Hydralisk";"Larva";130;2
"Building";"CreepTumor";NA;130;0
"Building";"Hatchery";NA;116;0
"Building";"CreepTumor";NA;135;0
"Building";"CreepTumor";NA;153;0
"Building";"CreepTumor";NA;153;0
"Unit";"Hydralisk";"Larva";153;2
"Unit";"Hydralisk";"Larva";153;2
"Unit";"Hydralisk";"Larva";153;2
"Unit";"Hydralisk";"Larva";153;2
"Unit";"Hydralisk";"Larva";153;2
"Unit";"Hydralisk";"Larva";153;2
"Upgrade";"ZergMissileWeaponsLevel1";"EvolutionChamber";124;0
"Building";"CreepTumor";NA;166;0
"Building";"CreepTumor";NA;166;0
"Unit";"Zergling";"Larva";166;1
"Unit";"Zergling";"Larva";166;1
"Unit";"Zergling";"Larva";166;1
"Unit";"Zergling";"Larva";166;1
"Unit";"Zergling";"Larva";166;1
"Unit";"Zergling";"Larva";166;1
"Building";"BanelingNest";NA;153;0
"Building";"Hatchery";NA;130;0
"Unit";"Hydralisk";"Larva";166;2
"Unit";"Hydralisk";"Larva";166;2
"Unit";"Hydralisk";"Larva";166;2
"Unit";"Hydralisk";"Larva";166;2
"Unit";"Hydralisk";"Larva";166;2
"Unit";"Zergling";"Larva";166;1
"Unit";"Zergling";"Larva";166;1
"Unit";"Zergling";"Larva";170;1
"Unit";"Zergling";"Larva";170;1
"Unit";"Zergling";"Larva";172;1
"Unit";"Zergling";"Larva";172;1
"Unit";"Zergling";"Larva";172;1
"Unit";"Zergling";"Larva";172;1
"Unit";"Zergling";"Larva";172;1
"Unit";"Zergling";"Larva";172;1
"Unit";"Zergling";"Larva";172;1
"Unit";"Zergling";"Larva";172;1
"Unit";"Zergling";"Larva";172;1
"Unit";"Zergling";"Larva";172;1
"Unit";"Zergling";"Larva";172;1
"Unit";"Zergling";"Larva";172;1
"Unit";"Zergling";"Larva";172;1
"Unit";"Zergling";"Larva";172;1
"Unit";"Zergling";"Larva";172;1
"Unit";"Zergling";"Larva";172;1
"Unit";"Zergling";"Larva";172;1
"Unit";"Zergling";"Larva";172;1
"Unit";"Zergling";"Larva";172;1
"Unit";"Zergling";"Larva";172;1
"Unit";"Zergling";"Larva";172;1
"Unit";"Zergling";"Larva";172;1
"Unit";"Hydralisk";"Larva";166;2
"Unit";"Hydralisk";"Larva";166;2
"Unit";"Hydralisk";"Larva";186;2
"Unit";"Hydralisk";"Larva";186;2
"Building";"CreepTumor";NA;216;0
"Building";"CreepTumor";NA;216;0
"Unit";"Overlord";"Larva";216;0
"Unit";"Overlord";"Larva";216;0
"Unit";"Overlord";"Larva";216;0
"Building";"Extractor";NA;216;0
"Building";"CreepTumorQueen";NA;220;0
"Building";"Extractor";NA;216;0
"Building";"CreepTumorQueen";NA;220;0
"Building";"CreepTumorQueen";NA;220;0
