"type";"unit_name";"on_building";"total_supply";"supply"
"Unit";"Overlord";"Larva";12;0
"Building";"Extractor";NA;18;0
"Unit";"Overlord";"Larva";21;0
"Building";"SpawningPool";NA;19;0
"Building";"Hatchery";NA;17;0
"Unit";"Zergling";"Larva";23;1
"Unit";"Zergling";"Larva";23;1
"Unit";"Queen";"Hatchery";22;2
"Unit";"Queen";"Hatchery";23;2
"Unit";"Overlord";"Larva";28;0
"Building";"CreepTumorQueen";NA;34;0
"Unit";"Zergling";"Larva";34;1
"Unit";"Zergling";"Larva";34;1
"Unit";"Overlord";"Larva";34;0
"Unit";"Queen";"Hatchery";29;2
"Unit";"Queen";"Hatchery";34;2
"Building";"CreepTumor";NA;41;0
"Building";"CreepTumorQueen";NA;45;0
"Building";"CreepTumorQueen";NA;48;0
"Unit";"Overlord";"Larva";45;0
"Building";"CreepTumorQueen";NA;50;0
"Building";"Extractor";NA;49;0
"Building";"Extractor";NA;49;0
"Building";"CreepTumor";NA;52;0
"Building";"CreepTumor";NA;52;0
"Building";"CreepTumor";NA;54;0
"Unit";"Overlord";"Larva";54;0
"Building";"Extractor";NA;56;0
"Unit";"Overlord";"Larva";59;0
"Building";"CreepTumor";NA;59;0
"Building";"CreepTumor";NA;60;0
"Building";"CreepTumor";NA;60;0
"Building";"CreepTumor";NA;60;0
"Building";"HydraliskDen";NA;59;0
"Unit";"Overlord";"Larva";64;0
"Building";"Hatchery";NA;49;0
"Unit";"Overlord";"Larva";67;0
"Building";"CreepTumor";NA;67;0
"Building";"CreepTumor";NA;67;0
"Building";"CreepTumor";NA;67;0
"Unit";"Hydralisk";"Larva";67;2
"Unit";"Hydralisk";"Larva";67;2
"Unit";"Hydralisk";"Larva";67;2
"Unit";"Hydralisk";"Larva";67;2
"Unit";"Hydralisk";"Larva";67;2
"Building";"CreepTumor";NA;67;0
"Unit";"Hydralisk";"Larva";67;2
"Unit";"Hydralisk";"Larva";67;2
"Unit";"Hydralisk";"Larva";67;2
"Unit";"Hydralisk";"Larva";67;2
"Building";"CreepTumor";NA;77;0
"Building";"CreepTumor";NA;79;0
"Unit";"Hydralisk";"Larva";67;2
"Building";"CreepTumor";NA;83;0
"Unit";"Hydralisk";"Larva";77;2
"Unit";"Overlord";"Larva";83;0
"Building";"CreepTumor";NA;85;0
"Unit";"Hydralisk";"Larva";79;2
"Unit";"Hydralisk";"Larva";81;2
"Upgrade";"EvolveMuscularAugments";"HydraliskDen";67;0
"Building";"CreepTumor";NA;98;0
"Building";"CreepTumor";NA;104;0
"Unit";"Overlord";"Larva";98;0
"Unit";"Hydralisk";"Larva";98;2
"Building";"EvolutionChamber";NA;98;0
"Unit";"Overlord";"Larva";104;0
"Unit";"Hydralisk";"Larva";104;2
"Building";"CreepTumorQueen";NA;107;0
"Unit";"Overlord";"Larva";105;0
"Building";"CreepTumor";NA;109;0
"Unit";"Overlord";"Larva";107;0
"Building";"Extractor";NA;107;0
"Building";"Extractor";NA;107;0
"Building";"CreepTumor";NA;116;0
"Unit";"Hydralisk";"Larva";107;2
"Unit";"Overlord";"Larva";116;0
"Unit";"Hydralisk";"Larva";109;2
"Unit";"Hydralisk";"Larva";109;2
"Unit";"Hydralisk";"Larva";116;2
"Unit";"Overlord";"Larva";116;0
"Building";"CreepTumorQueen";NA;127;0
"Building";"CreepTumorQueen";NA;127;0
"Building";"CreepTumor";NA;127;0
"Building";"LurkerDenMP";NA;98;0
"Building";"CreepTumor";NA;132;0
"Unit";"Hydralisk";"Larva";127;2
"Unit";"Overlord";"Larva";133;0
"Building";"CreepTumor";NA;136;0
"Upgrade";"EvolveGroovedSpines";"HydraliskDen";118;0
"Unit";"Hydralisk";"Larva";133;2
"Unit";"Hydralisk";"Larva";133;2
"Building";"CreepTumorQueen";NA;141;0
"Building";"CreepTumor";NA;141;0
"Unit";"Hydralisk";"Larva";140;2
"Unit";"Hydralisk";"Larva";141;2
"Unit";"Hydralisk";"Larva";141;2
"Unit";"Hydralisk";"Larva";141;2
"Building";"CreepTumor";NA;145;0
"Building";"CreepTumor";NA;145;0
"Unit";"Overlord";"Larva";145;0
"Unit";"Hydralisk";"Larva";145;2
"Unit";"Hydralisk";"Larva";145;2
"Building";"Hatchery";NA;127;0
"Upgrade";"ZergMissileWeaponsLevel1";"EvolutionChamber";122;0
"Building";"CreepTumor";NA;153;0
"Unit";"Overlord";"Larva";153;0
"Building";"CreepTumor";NA;153;0
"Building";"CreepTumor";NA;153;0
"Unit";"Hydralisk";"Larva";153;2
"Unit";"Hydralisk";"Larva";153;2
"Unit";"Overlord";"Larva";153;0
"Unit";"Overlord";"Larva";153;0
"Unit";"Overlord";"Larva";155;0
"Unit";"Overlord";"Larva";157;0
"Building";"CreepTumor";NA;171;0
"Unit";"Zergling";"Larva";157;1
"Unit";"Zergling";"Larva";157;1
"Unit";"Zergling";"Larva";157;1
"Unit";"Zergling";"Larva";157;1
"Unit";"Zergling";"Larva";157;1
"Unit";"Zergling";"Larva";157;1
"Building";"InfestationPit";NA;153;0
"Building";"CreepTumor";NA;171;0
"Building";"CreepTumor";NA;171;0
"Unit";"Zergling";"Larva";171;1
"Unit";"Zergling";"Larva";171;1
"Unit";"Zergling";"Larva";171;1
"Unit";"Zergling";"Larva";171;1
"Unit";"Zergling";"Larva";171;1
"Unit";"Zergling";"Larva";171;1
"Unit";"Zergling";"Larva";171;1
"Unit";"Zergling";"Larva";171;1
"Building";"CreepTumor";NA;171;0
"Unit";"Zergling";"Larva";171;1
"Unit";"Zergling";"Larva";171;1
"Unit";"Zergling";"Larva";171;1
"Unit";"Zergling";"Larva";171;1
"Unit";"Zergling";"Larva";171;1
"Unit";"Zergling";"Larva";171;1
"Unit";"Zergling";"Larva";171;1
"Unit";"Zergling";"Larva";171;1
"Unit";"Zergling";"Larva";171;1
"Unit";"Zergling";"Larva";171;1
"Unit";"Zergling";"Larva";171;1
"Unit";"Zergling";"Larva";171;1
"Building";"Extractor";NA;197;0
"Building";"Extractor";NA;197;0
"Unit";"Zergling";"Larva";197;1
"Unit";"Zergling";"Larva";197;1
"Unit";"Zergling";"Larva";197;1
"Unit";"Zergling";"Larva";197;1
"Unit";"Zergling";"Larva";197;1
"Unit";"Zergling";"Larva";197;1
"Unit";"Zergling";"Larva";197;1
"Unit";"Zergling";"Larva";197;1
"Unit";"Zergling";"Larva";197;1
"Unit";"Zergling";"Larva";197;1
"Unit";"Zergling";"Larva";197;1
"Unit";"Zergling";"Larva";197;1
"Building";"CreepTumor";NA;197;0
"Unit";"Hydralisk";"Larva";197;2
"Unit";"Hydralisk";"Larva";197;2
"Unit";"Hydralisk";"Larva";197;2
"Unit";"Hydralisk";"Larva";197;2
"Unit";"Hydralisk";"Larva";197;2
"Unit";"Hydralisk";"Larva";197;2
"Unit";"Hydralisk";"Larva";197;2
"Unit";"Zergling";"Larva";197;1
"Unit";"Zergling";"Larva";197;1
"Building";"CreepTumor";NA;209;0
"Unit";"Zergling";"Larva";197;1
"Unit";"Zergling";"Larva";197;1
"Unit";"Zergling";"Larva";197;1
"Unit";"Zergling";"Larva";197;1
"Unit";"Zergling";"Larva";197;1
"Unit";"Zergling";"Larva";197;1
"Unit";"Zergling";"Larva";197;1
"Unit";"Zergling";"Larva";197;1
"Unit";"Zergling";"Larva";197;1
"Unit";"Zergling";"Larva";197;1
"Unit";"Zergling";"Larva";199;1
"Unit";"Zergling";"Larva";199;1
"Building";"CreepTumor";NA;209;0
"Unit";"Zergling";"Larva";223;1
"Unit";"Zergling";"Larva";223;1
"Unit";"Zergling";"Larva";223;1
"Unit";"Zergling";"Larva";223;1
"Unit";"Zergling";"Larva";223;1
"Unit";"Zergling";"Larva";223;1
"Unit";"Zergling";"Larva";223;1
"Unit";"Zergling";"Larva";223;1
"Unit";"Zergling";"Larva";223;1
"Unit";"Zergling";"Larva";223;1
"Building";"Spire";NA;197;0
"Building";"Hatchery";NA;197;0
"Unit";"Overlord";"Larva";247;0
"Unit";"Overlord";"Larva";247;0
"Unit";"Corruptor";"Larva";247;2
"Unit";"Corruptor";"Larva";247;2
"Unit";"Corruptor";"Larva";247;2
"Unit";"Corruptor";"Larva";247;2
"Building";"CreepTumor";NA;247;0
"Unit";"Corruptor";"Larva";247;2
"Unit";"Corruptor";"Larva";247;2
"Building";"EvolutionChamber";NA;255;0
"Upgrade";"ZergMissileWeaponsLevel2";"EvolutionChamber";209;0
"Unit";"Corruptor";"Larva";259;2
"Unit";"Corruptor";"Larva";259;2
"Unit";"Corruptor";"Larva";259;2
"Unit";"Corruptor";"Larva";259;2
"Unit";"Corruptor";"Larva";259;2
"Unit";"Corruptor";"Larva";259;2
"Unit";"Corruptor";"Larva";263;2
"Unit";"Corruptor";"Larva";263;2
"Unit";"Corruptor";"Larva";263;2
"Unit";"Corruptor";"Larva";263;2
"Unit";"Corruptor";"Larva";263;2
"Unit";"Zergling";"Larva";281;1
"Unit";"Zergling";"Larva";281;1
"Unit";"Zergling";"Larva";281;1
"Unit";"Zergling";"Larva";281;1
"Unit";"Zergling";"Larva";281;1
"Unit";"Zergling";"Larva";281;1
"Unit";"Zergling";"Larva";281;1
"Unit";"Zergling";"Larva";281;1
"Unit";"Zergling";"Larva";281;1
"Unit";"Zergling";"Larva";281;1
"Unit";"Zergling";"Larva";281;1
"Unit";"Zergling";"Larva";281;1
"Unit";"Zergling";"Larva";281;1
"Unit";"Zergling";"Larva";281;1
"Unit";"Zergling";"Larva";281;1
"Unit";"Zergling";"Larva";281;1
"Unit";"Zergling";"Larva";281;1
"Unit";"Zergling";"Larva";281;1
"Upgrade";"ZergMeleeWeaponsLevel1";"EvolutionChamber";259;0
"Unit";"Hydralisk";"Larva";299;2
"Unit";"Hydralisk";"Larva";299;2
"Unit";"Hydralisk";"Larva";299;2
"Unit";"Hydralisk";"Larva";299;2
"Upgrade";"ZergMissileWeaponsLevel3";"EvolutionChamber";263;0
"Building";"Hatchery";NA;281;0
"Building";"Hatchery";NA;281;0
"Unit";"Corruptor";"Larva";299;2
"Unit";"Corruptor";"Larva";299;2
"Unit";"Corruptor";"Larva";299;2
"Building";"Extractor";NA;313;0
"Building";"Extractor";NA;313;0
"Unit";"Zergling";"Larva";313;1
"Unit";"Zergling";"Larva";313;1
"Unit";"Zergling";"Larva";313;1
"Unit";"Zergling";"Larva";313;1
"Unit";"Zergling";"Larva";313;1
"Unit";"Zergling";"Larva";313;1
"Unit";"Zergling";"Larva";313;1
"Unit";"Zergling";"Larva";313;1
"Unit";"Zergling";"Larva";313;1
"Unit";"Zergling";"Larva";313;1
"Unit";"Zergling";"Larva";313;1
"Unit";"Zergling";"Larva";313;1
"Unit";"Zergling";"Larva";313;1
"Unit";"Zergling";"Larva";313;1
"Unit";"Zergling";"Larva";316;1
"Unit";"Zergling";"Larva";316;1
"Unit";"Zergling";"Larva";316;1
"Unit";"Zergling";"Larva";316;1
"Unit";"Zergling";"Larva";316;1
"Unit";"Zergling";"Larva";316;1
"Unit";"Zergling";"Larva";316;1
"Unit";"Zergling";"Larva";316;1
"Unit";"Zergling";"Larva";316;1
"Unit";"Zergling";"Larva";316;1
"Unit";"Zergling";"Larva";316;1
"Unit";"Zergling";"Larva";316;1
"Unit";"Corruptor";"Larva";330;2
"Unit";"Corruptor";"Larva";330;2
"Unit";"Corruptor";"Larva";330;2
"Unit";"Corruptor";"Larva";330;2
"Unit";"Corruptor";"Larva";330;2
"Unit";"Corruptor";"Larva";330;2
"Unit";"Corruptor";"Larva";330;2
"Unit";"Corruptor";"Larva";330;2
"Unit";"Corruptor";"Larva";330;2
"Unit";"Corruptor";"Larva";330;2
"Unit";"Overlord";"Larva";342;0
"Unit";"Overlord";"Larva";342;0
"Unit";"Corruptor";"Larva";367;2
"Unit";"Corruptor";"Larva";367;2
"Unit";"Corruptor";"Larva";367;2
"Unit";"Corruptor";"Larva";367;2
"Unit";"Corruptor";"Larva";367;2
"Building";"Hatchery";NA;342;0
"Unit";"Viper";"Larva";378;3
"Unit";"Zergling";"Larva";389;1
"Unit";"Zergling";"Larva";389;1
"Unit";"Zergling";"Larva";389;1
"Unit";"Zergling";"Larva";389;1
"Unit";"Zergling";"Larva";389;1
"Unit";"Zergling";"Larva";389;1
"Unit";"Viper";"Larva";389;3
"Building";"CreepTumorQueen";NA;406;0
"Building";"CreepTumorQueen";NA;406;0
"Unit";"Queen";"Hatchery";389;2
"Building";"CreepTumorQueen";NA;406;0
"Unit";"Viper";"Larva";403;3
"Building";"Extractor";NA;406;0
"Unit";"Corruptor";"Larva";411;2
"Unit";"Corruptor";"Larva";411;2
"Unit";"Corruptor";"Larva";411;2
"Unit";"Corruptor";"Larva";411;2
"Unit";"Overlord";"Larva";411;0
"Upgrade";"ZergMeleeWeaponsLevel2";"EvolutionChamber";389;0
