"type";"unit_name";"on_building";"total_supply";"supply"
"Unit";"Overlord";"Larva";12;0
"Building";"Extractor";NA;19;0
"Building";"Hatchery";NA;16;0
"Building";"SpawningPool";NA;19;0
"Unit";"Overlord";"Larva";26;0
"Unit";"Queen";"Hatchery";23;2
"Unit";"Zergling";"Larva";28;1
"Unit";"Zergling";"Larva";28;1
"Unit";"Zergling";"Larva";28;1
"Unit";"Zergling";"Larva";28;1
"Building";"Hatchery";NA;22;0
"Unit";"Overlord";"Larva";35;0
"Unit";"Queen";"Hatchery";28;2
"Unit";"Zergling";"Larva";38;1
"Unit";"Zergling";"Larva";38;1
"Unit";"Zergling";"Larva";38;1
"Unit";"Zergling";"Larva";38;1
"Unit";"Zergling";"Larva";38;1
"Unit";"Zergling";"Larva";38;1
"Unit";"Zergling";"Larva";38;1
"Unit";"Zergling";"Larva";38;1
"Unit";"Zergling";"Larva";38;1
"Unit";"Zergling";"Larva";38;1
"Building";"CreepTumorQueen";NA;43;0
"Unit";"Overlord";"Larva";43;0
"Unit";"Overlord";"Larva";43;0
"Building";"SporeCrawler";NA;53;0
"Building";"SporeCrawler";NA;53;0
"Building";"EvolutionChamber";NA;53;0
"Unit";"Queen";"Hatchery";43;2
"Unit";"Queen";"Hatchery";43;2
"Building";"CreepTumorQueen";NA;55;0
"Unit";"Overlord";"Larva";68;0
"Building";"CreepTumor";NA;70;0
"Building";"SporeCrawler";NA;70;0
"Building";"CreepTumor";NA;76;0
"Building";"Extractor";NA;76;0
"Unit";"Overlord";"Larva";78;0
"Unit";"Overlord";"Larva";84;0
"Building";"Extractor";NA;84;0
"Unit";"Zergling";"Larva";84;1
"Unit";"Zergling";"Larva";84;1
"Unit";"Zergling";"Larva";84;1
"Unit";"Zergling";"Larva";84;1
"Unit";"Zergling";"Larva";84;1
"Unit";"Zergling";"Larva";84;1
"Building";"BanelingNest";NA;76;0
"Building";"CreepTumor";NA;92;0
"Building";"CreepTumor";NA;92;0
"Building";"CreepTumorQueen";NA;92;0
"Building";"CreepTumorQueen";NA;98;0
"Unit";"Zergling";"Larva";92;1
"Unit";"Zergling";"Larva";92;1
"Unit";"Zergling";"Larva";92;1
"Unit";"Zergling";"Larva";92;1
"Unit";"Zergling";"Larva";92;1
"Unit";"Zergling";"Larva";92;1
"Unit";"Zergling";"Larva";92;1
"Unit";"Zergling";"Larva";92;1
"Unit";"Zergling";"Larva";92;1
"Unit";"Zergling";"Larva";92;1
"Unit";"Zergling";"Larva";92;1
"Unit";"Zergling";"Larva";92;1
"Unit";"Zergling";"Larva";92;1
"Unit";"Zergling";"Larva";92;1
"Unit";"Zergling";"Larva";98;1
"Unit";"Zergling";"Larva";98;1
"Unit";"Zergling";"Larva";98;1
"Unit";"Zergling";"Larva";98;1
"Unit";"Zergling";"Larva";98;1
"Unit";"Zergling";"Larva";98;1
"Unit";"Zergling";"Larva";98;1
"Unit";"Zergling";"Larva";98;1
"Unit";"Zergling";"Larva";98;1
"Unit";"Zergling";"Larva";98;1
"Unit";"Zergling";"Larva";98;1
"Unit";"Zergling";"Larva";98;1
"Unit";"Overlord";"Larva";112;0
"Unit";"Overlord";"Larva";112;0
"Upgrade";"ZergMeleeWeaponsLevel1";"EvolutionChamber";76;0
"Unit";"Queen";"Hatchery";98;2
"Unit";"Overlord";"Larva";112;0
"Unit";"Overlord";"Larva";124;0
"Unit";"Overlord";"Larva";126;0
"Unit";"Overlord";"Larva";126;0
"Building";"CreepTumor";NA;132;0
"Building";"CreepTumor";NA;132;0
"Building";"CreepTumor";NA;132;0
"Building";"CreepTumor";NA;137;0
"Building";"HydraliskDen";NA;132;0
"Building";"Extractor";NA;137;0
"Unit";"Zergling";"Larva";137;1
"Unit";"Zergling";"Larva";137;1
"Unit";"Hydralisk";"Larva";137;2
"Unit";"Zergling";"Larva";137;1
"Unit";"Zergling";"Larva";137;1
"Unit";"Zergling";"Larva";137;1
"Unit";"Zergling";"Larva";137;1
"Unit";"Zergling";"Larva";137;1
"Unit";"Zergling";"Larva";137;1
"Unit";"Zergling";"Larva";137;1
"Unit";"Zergling";"Larva";137;1
"Unit";"Zergling";"Larva";137;1
"Unit";"Zergling";"Larva";137;1
"Unit";"Zergling";"Larva";137;1
"Unit";"Zergling";"Larva";137;1
"Unit";"Zergling";"Larva";137;1
"Unit";"Zergling";"Larva";137;1
"Unit";"Zergling";"Larva";137;1
"Unit";"Zergling";"Larva";137;1
"Unit";"Zergling";"Larva";137;1
"Unit";"Zergling";"Larva";137;1
"Unit";"Zergling";"Larva";137;1
"Unit";"Zergling";"Larva";137;1
"Unit";"Hydralisk";"Larva";137;2
"Unit";"Queen";"Hatchery";137;2
"Unit";"Queen";"Hatchery";137;2
"Unit";"Hydralisk";"Larva";137;2
"Unit";"Hydralisk";"Larva";137;2
"Building";"Extractor";NA;137;0
"Unit";"Zergling";"Larva";137;1
"Unit";"Zergling";"Larva";137;1
"Unit";"Zergling";"Larva";137;1
"Unit";"Zergling";"Larva";137;1
"Unit";"Zergling";"Larva";137;1
"Unit";"Zergling";"Larva";137;1
"Unit";"Zergling";"Larva";137;1
"Unit";"Zergling";"Larva";137;1
"Unit";"Hydralisk";"Larva";137;2
"Unit";"Hydralisk";"Larva";137;2
"Unit";"Zergling";"Larva";165;1
"Unit";"Zergling";"Larva";165;1
"Unit";"Zergling";"Larva";165;1
"Unit";"Zergling";"Larva";165;1
"Unit";"Zergling";"Larva";165;1
"Unit";"Zergling";"Larva";165;1
"Unit";"Zergling";"Larva";167;1
"Unit";"Zergling";"Larva";167;1
"Building";"CreepTumor";NA;173;0
"Building";"CreepTumorQueen";NA;179;0
"Building";"CreepTumorQueen";NA;181;0
"Unit";"Hydralisk";"Larva";171;2
"Unit";"Hydralisk";"Larva";171;2
"Unit";"Hydralisk";"Larva";191;2
"Unit";"Hydralisk";"Larva";191;2
"Building";"CreepTumor";NA;195;0
"Building";"CreepTumor";NA;204;0
"Building";"CreepTumor";NA;204;0
"Building";"CreepTumorQueen";NA;204;0
"Building";"CreepTumorQueen";NA;204;0
"Building";"CreepTumor";NA;204;0
"Unit";"Baneling";"Zergling";197;0
"Building";"CreepTumorQueen";NA;204;0
"Unit";"Baneling";"Zergling";199;0
"Unit";"Baneling";"Zergling";199;0
"Unit";"Baneling";"Zergling";201;0
"Unit";"Baneling";"Zergling";203;0
"Unit";"Baneling";"Zergling";203;0
"Unit";"Baneling";"Zergling";204;0
"Building";"CreepTumor";NA;204;0
"Building";"CreepTumorQueen";NA;204;0
"Unit";"Overlord";"Larva";204;0
"Unit";"Overlord";"Larva";204;0
"Unit";"Zergling";"Larva";204;1
"Unit";"Zergling";"Larva";204;1
"Unit";"Zergling";"Larva";204;1
"Unit";"Zergling";"Larva";204;1
"Unit";"Zergling";"Larva";204;1
"Unit";"Zergling";"Larva";204;1
"Building";"CreepTumorQueen";NA;208;0
"Unit";"Zergling";"Larva";208;1
"Unit";"Zergling";"Larva";208;1
"Unit";"Zergling";"Larva";208;1
"Unit";"Zergling";"Larva";208;1
"Unit";"Zergling";"Larva";208;1
"Unit";"Zergling";"Larva";208;1
"Unit";"Zergling";"Larva";208;1
"Unit";"Zergling";"Larva";208;1
"Unit";"Zergling";"Larva";208;1
"Unit";"Zergling";"Larva";208;1
"Building";"CreepTumor";NA;214;0
"Unit";"Zergling";"Larva";208;1
"Unit";"Zergling";"Larva";208;1
"Unit";"Zergling";"Larva";208;1
"Unit";"Zergling";"Larva";208;1
"Unit";"Zergling";"Larva";208;1
"Unit";"Zergling";"Larva";208;1
"Unit";"Zergling";"Larva";208;1
"Unit";"Zergling";"Larva";208;1
"Building";"Extractor";NA;208;0
"Building";"CreepTumor";NA;214;0
"Upgrade";"ZergMeleeWeaponsLevel2";"EvolutionChamber";137;0
"Building";"CreepTumor";NA;214;0
"Building";"CreepTumorQueen";NA;214;0
"Building";"CreepTumorQueen";NA;214;0
"Unit";"Queen";"Hatchery";208;2
"Unit";"Queen";"Hatchery";208;2
"Unit";"Overlord";"Larva";214;0
"Unit";"Zergling";"Larva";214;1
"Unit";"Zergling";"Larva";214;1
"Unit";"Zergling";"Larva";214;1
"Unit";"Zergling";"Larva";214;1
"Building";"Hatchery";NA;191;0
"Building";"SpineCrawler";NA;208;0
"Building";"SpineCrawler";NA;208;0
"Building";"CreepTumor";NA;242;0
"Unit";"Hydralisk";"Larva";236;2
"Unit";"Hydralisk";"Larva";236;2
"Unit";"Hydralisk";"Larva";236;2
"Unit";"Hydralisk";"Larva";236;2
"Unit";"Zergling";"Larva";249;1
"Unit";"Zergling";"Larva";249;1
"Unit";"Zergling";"Larva";249;1
"Unit";"Zergling";"Larva";249;1
"Unit";"Zergling";"Larva";249;1
"Unit";"Zergling";"Larva";249;1
"Building";"Hatchery";NA;208;0
"Unit";"Zergling";"Larva";259;1
"Unit";"Zergling";"Larva";259;1
"Unit";"Zergling";"Larva";259;1
"Unit";"Zergling";"Larva";259;1
"Unit";"Zergling";"Larva";259;1
"Unit";"Zergling";"Larva";259;1
"Upgrade";"EvolveMuscularAugments";"HydraliskDen";242;0
"Unit";"Zergling";"Larva";259;1
"Unit";"Zergling";"Larva";259;1
"Unit";"Zergling";"Larva";259;1
"Unit";"Zergling";"Larva";259;1
"Unit";"Zergling";"Larva";259;1
"Unit";"Zergling";"Larva";259;1
"Unit";"Zergling";"Larva";259;1
"Unit";"Zergling";"Larva";259;1
"Unit";"Zergling";"Larva";259;1
"Unit";"Zergling";"Larva";259;1
"Unit";"Zergling";"Larva";259;1
"Unit";"Zergling";"Larva";259;1
"Unit";"Zergling";"Larva";259;1
"Unit";"Zergling";"Larva";259;1
"Upgrade";"Burrow";"Hatchery";242;0
"Unit";"Overlord";"Larva";265;0
"Unit";"Overlord";"Larva";265;0
"Unit";"Overlord";"Larva";265;0
"Building";"SporeCrawler";NA;265;0
"Unit";"Zergling";"Larva";285;1
"Unit";"Zergling";"Larva";285;1
"Unit";"Zergling";"Larva";285;1
"Unit";"Zergling";"Larva";285;1
"Unit";"Zergling";"Larva";285;1
"Unit";"Zergling";"Larva";285;1
"Unit";"Zergling";"Larva";285;1
"Unit";"Zergling";"Larva";285;1
"Unit";"Overlord";"Larva";285;0
"Unit";"Hydralisk";"Larva";265;2
"Unit";"Hydralisk";"Larva";265;2
"Unit";"Hydralisk";"Larva";265;2
"Building";"InfestationPit";NA;265;0
"Unit";"Zergling";"Larva";299;1
"Unit";"Zergling";"Larva";299;1
"Unit";"Zergling";"Larva";299;1
"Unit";"Zergling";"Larva";299;1
"Unit";"Zergling";"Larva";299;1
"Unit";"Zergling";"Larva";299;1
"Unit";"Zergling";"Larva";299;1
"Unit";"Zergling";"Larva";299;1
"Unit";"Zergling";"Larva";299;1
"Unit";"Zergling";"Larva";299;1
"Unit";"Zergling";"Larva";299;1
"Unit";"Zergling";"Larva";299;1
"Unit";"Zergling";"Larva";299;1
"Unit";"Zergling";"Larva";299;1
"Unit";"Zergling";"Larva";299;1
"Unit";"Zergling";"Larva";299;1
"Unit";"Zergling";"Larva";299;1
"Unit";"Zergling";"Larva";299;1
"Unit";"Zergling";"Larva";299;1
"Unit";"Zergling";"Larva";299;1
"Unit";"Zergling";"Larva";299;1
"Unit";"Zergling";"Larva";299;1
"Unit";"Zergling";"Larva";299;1
"Unit";"Zergling";"Larva";299;1
"Unit";"Zergling";"Larva";299;1
"Unit";"Zergling";"Larva";299;1
"Unit";"Zergling";"Larva";299;1
"Unit";"Zergling";"Larva";299;1
"Building";"CreepTumor";NA;299;0
"Building";"CreepTumor";NA;299;0
"Unit";"Baneling";"Zergling";327;0
"Unit";"Baneling";"Zergling";327;0
"Unit";"Baneling";"Zergling";327;0
"Unit";"Baneling";"Zergling";327;0
"Unit";"Baneling";"Zergling";327;0
"Unit";"Baneling";"Zergling";327;0
"Unit";"Baneling";"Zergling";327;0
"Unit";"Baneling";"Zergling";327;0
"Unit";"Baneling";"Zergling";327;0
"Unit";"Baneling";"Zergling";327;0
"Unit";"Baneling";"Zergling";327;0
"Unit";"Baneling";"Zergling";327;0
"Unit";"Baneling";"Zergling";327;0
"Unit";"Baneling";"Zergling";327;0
"Unit";"Baneling";"Zergling";327;0
"Unit";"Baneling";"Zergling";327;0
"Unit";"Baneling";"Zergling";327;0
"Unit";"Baneling";"Zergling";327;0
"Unit";"Baneling";"Zergling";327;0
"Unit";"Baneling";"Zergling";327;0
"Unit";"Baneling";"Zergling";327;0
"Unit";"Baneling";"Zergling";327;0
"Unit";"Baneling";"Zergling";327;0
"Unit";"Baneling";"Zergling";327;0
"Unit";"Baneling";"Zergling";327;0
"Unit";"Baneling";"Zergling";327;0
"Unit";"Baneling";"Zergling";327;0
"Unit";"Baneling";"Zergling";327;0
"Unit";"Baneling";"Zergling";327;0
"Unit";"Baneling";"Zergling";327;0
"Unit";"Baneling";"Zergling";327;0
"Unit";"Baneling";"Zergling";327;0
"Unit";"Baneling";"Zergling";327;0
"Unit";"Baneling";"Zergling";327;0
"Unit";"Baneling";"Zergling";327;0
"Unit";"Baneling";"Zergling";327;0
"Building";"CreepTumor";NA;327;0
"Building";"CreepTumor";NA;327;0
"Building";"CreepTumor";NA;327;0
"Building";"CreepTumor";NA;327;0
"Building";"CreepTumor";NA;327;0
"Unit";"Zergling";"Larva";327;1
"Unit";"Zergling";"Larva";327;1
"Unit";"Zergling";"Larva";327;1
"Unit";"Zergling";"Larva";327;1
"Unit";"Zergling";"Larva";327;1
"Unit";"Zergling";"Larva";327;1
"Unit";"Zergling";"Larva";327;1
"Unit";"Zergling";"Larva";327;1
"Unit";"Zergling";"Larva";327;1
"Unit";"Zergling";"Larva";327;1
"Building";"CreepTumor";NA;327;0
"Upgrade";"EvolveGroovedSpines";"HydraliskDen";293;0
"Upgrade";"ZergMissileWeaponsLevel1";"EvolutionChamber";265;0
"Building";"Hatchery";NA;285;0
"Building";"CreepTumor";NA;337;0
"Building";"CreepTumor";NA;337;0
"Building";"CreepTumorQueen";NA;337;0
"Building";"CreepTumorQueen";NA;337;0
"Building";"CreepTumorQueen";NA;337;0
"Building";"CreepTumorQueen";NA;337;0
"Building";"CreepTumorQueen";NA;337;0
"Building";"Extractor";NA;337;0
"Building";"CreepTumorQueen";NA;337;0
"Building";"CreepTumor";NA;337;0
"Building";"CreepTumor";NA;337;0
"Building";"Extractor";NA;337;0
"Unit";"Zergling";"Larva";337;1
"Unit";"Zergling";"Larva";337;1
"Unit";"Zergling";"Larva";337;1
"Unit";"Zergling";"Larva";337;1
"Unit";"Zergling";"Larva";337;1
"Unit";"Zergling";"Larva";337;1
"Unit";"Zergling";"Larva";337;1
"Unit";"Zergling";"Larva";337;1
"Unit";"Zergling";"Larva";337;1
"Unit";"Zergling";"Larva";337;1
"Unit";"Zergling";"Larva";337;1
"Unit";"Zergling";"Larva";337;1
"Unit";"Zergling";"Larva";337;1
"Unit";"Zergling";"Larva";337;1
"Unit";"Zergling";"Larva";337;1
"Unit";"Zergling";"Larva";337;1
"Unit";"Zergling";"Larva";337;1
"Unit";"Zergling";"Larva";337;1
"Unit";"Zergling";"Larva";337;1
"Unit";"Zergling";"Larva";337;1
"Unit";"Zergling";"Larva";337;1
"Unit";"Zergling";"Larva";337;1
"Unit";"Zergling";"Larva";337;1
"Unit";"Zergling";"Larva";337;1
"Unit";"Zergling";"Larva";337;1
"Unit";"Zergling";"Larva";337;1
"Building";"Spire";NA;327;0
"Unit";"Zergling";"Larva";337;1
"Unit";"Zergling";"Larva";337;1
"Unit";"Zergling";"Larva";337;1
"Unit";"Zergling";"Larva";337;1
"Unit";"Zergling";"Larva";337;1
"Unit";"Zergling";"Larva";337;1
"Unit";"Zergling";"Larva";337;1
"Unit";"Zergling";"Larva";337;1
"Unit";"Zergling";"Larva";337;1
"Unit";"Zergling";"Larva";337;1
"Unit";"Zergling";"Larva";337;1
"Unit";"Zergling";"Larva";337;1
"Unit";"Zergling";"Larva";337;1
"Unit";"Zergling";"Larva";337;1
"Unit";"Zergling";"Larva";337;1
"Unit";"Zergling";"Larva";337;1
"Unit";"Zergling";"Larva";337;1
"Unit";"Zergling";"Larva";337;1
"Unit";"Zergling";"Larva";337;1
"Unit";"Zergling";"Larva";337;1
"Unit";"Zergling";"Larva";337;1
"Unit";"Zergling";"Larva";337;1
"Unit";"Zergling";"Larva";337;1
"Unit";"Zergling";"Larva";337;1
"Unit";"Zergling";"Larva";337;1
"Unit";"Zergling";"Larva";337;1
"Unit";"Zergling";"Larva";337;1
"Unit";"Zergling";"Larva";337;1
"Unit";"Zergling";"Larva";337;1
"Unit";"Zergling";"Larva";337;1
"Unit";"Overlord";"Larva";363;0
"Unit";"Overlord";"Larva";363;0
"Unit";"Corruptor";"Larva";363;2
"Unit";"Corruptor";"Larva";363;2
"Unit";"Corruptor";"Larva";363;2
"Unit";"Corruptor";"Larva";363;2
"Unit";"Corruptor";"Larva";363;2
"Building";"CreepTumor";NA;393;0
"Building";"CreepTumor";NA;393;0
"Building";"CreepTumor";NA;393;0
"Building";"CreepTumor";NA;393;0
"Building";"CreepTumor";NA;393;0
"Building";"CreepTumor";NA;393;0
"Building";"CreepTumor";NA;393;0
"Building";"CreepTumor";NA;403;0
"Building";"CreepTumor";NA;403;0
"Unit";"Corruptor";"Larva";403;2
"Unit";"Corruptor";"Larva";403;2
"Unit";"Corruptor";"Larva";403;2
"Building";"CreepTumor";NA;403;0
"Building";"CreepTumor";NA;403;0
"Building";"Extractor";NA;403;0
"Building";"Extractor";NA;403;0
"Building";"SporeCrawler";NA;403;0
"Unit";"Baneling";"Zergling";409;0
"Unit";"Baneling";"Zergling";409;0
"Unit";"Baneling";"Zergling";409;0
"Unit";"Baneling";"Zergling";409;0
"Unit";"Baneling";"Zergling";409;0
"Unit";"Baneling";"Zergling";409;0
"Unit";"Baneling";"Zergling";409;0
"Building";"CreepTumor";NA;409;0
"Building";"CreepTumor";NA;409;0
"Building";"CreepTumor";NA;409;0
"Building";"SpineCrawler";NA;403;0
"Building";"CreepTumor";NA;418;0
"Building";"CreepTumor";NA;418;0
"Building";"SpineCrawler";NA;412;0
"Building";"SpineCrawler";NA;412;0
"Building";"CreepTumor";NA;418;0
"Building";"CreepTumor";NA;418;0
"Building";"CreepTumor";NA;418;0
"Unit";"Hydralisk";"Larva";418;2
"Unit";"Hydralisk";"Larva";418;2
"Unit";"Hydralisk";"Larva";418;2
"Unit";"Hydralisk";"Larva";418;2
"Unit";"Hydralisk";"Larva";418;2
"Unit";"Hydralisk";"Larva";418;2
"Unit";"Hydralisk";"Larva";418;2
"Unit";"Hydralisk";"Larva";418;2
"Unit";"Hydralisk";"Larva";418;2
"Upgrade";"ZergMeleeWeaponsLevel3";"EvolutionChamber";403;0
"Unit";"Zergling";"Larva";439;1
"Unit";"Zergling";"Larva";439;1
"Unit";"Zergling";"Larva";439;1
"Unit";"Zergling";"Larva";439;1
"Unit";"Zergling";"Larva";439;1
"Unit";"Zergling";"Larva";439;1
"Unit";"Zergling";"Larva";439;1
"Unit";"Zergling";"Larva";439;1
"Unit";"Zergling";"Larva";439;1
"Unit";"Zergling";"Larva";439;1
"Unit";"Zergling";"Larva";439;1
"Unit";"Zergling";"Larva";439;1
"Unit";"Zergling";"Larva";439;1
"Unit";"Zergling";"Larva";439;1
"Unit";"Hydralisk";"Larva";453;2
"Unit";"Hydralisk";"Larva";453;2
"Unit";"Hydralisk";"Larva";453;2
"Unit";"Hydralisk";"Larva";453;2
"Unit";"Hydralisk";"Larva";453;2
"Building";"UltraliskCavern";NA;445;0
