"type";"unit_name";"on_building";"total_supply";"supply"
"Unit";"Overlord";"Larva";13;0
"Building";"Extractor";NA;18;0
"Building";"SpawningPool";NA;19;0
"Building";"Hatchery";NA;17;0
"Unit";"Overlord";"Larva";22;0
"Unit";"Zergling";"Larva";23;1
"Unit";"Zergling";"Larva";23;1
"Unit";"Zergling";"Larva";23;1
"Unit";"Zergling";"Larva";23;1
"Unit";"Queen";"Hatchery";23;2
"Unit";"Queen";"Hatchery";23;2
"Unit";"Overlord";"Larva";37;0
"Unit";"Queen";"Hatchery";37;2
"Unit";"Overlord";"Larva";40;0
"Unit";"Zergling";"Larva";40;1
"Unit";"Zergling";"Larva";40;1
"Building";"CreepTumorQueen";NA;49;0
"Building";"Hatchery";NA;35;0
"Unit";"Overlord";"Larva";49;0
"Unit";"Queen";"Hatchery";40;2
"Unit";"Queen";"Hatchery";51;2
"Unit";"Overlord";"Larva";59;0
"Unit";"Overlord";"Larva";59;0
"Unit";"Queen";"Hatchery";57;2
"Building";"CreepTumorQueen";NA;59;0
"Unit";"Zergling";"Larva";59;1
"Unit";"Zergling";"Larva";59;1
"Building";"Extractor";NA;59;0
"Building";"Extractor";NA;59;0
"Building";"CreepTumorQueen";NA;64;0
"Building";"CreepTumorQueen";NA;68;0
"Building";"CreepTumorQueen";NA;68;0
"Building";"CreepTumor";NA;68;0
"Unit";"Zergling";"Larva";68;1
"Unit";"Zergling";"Larva";68;1
"Unit";"Zergling";"Larva";68;1
"Unit";"Zergling";"Larva";68;1
"Unit";"Zergling";"Larva";68;1
"Unit";"Zergling";"Larva";68;1
"Unit";"Zergling";"Larva";68;1
"Unit";"Zergling";"Larva";68;1
"Unit";"Zergling";"Larva";68;1
"Unit";"Zergling";"Larva";68;1
"Unit";"Zergling";"Larva";68;1
"Unit";"Zergling";"Larva";68;1
"Unit";"Zergling";"Larva";68;1
"Unit";"Zergling";"Larva";68;1
"Unit";"Zergling";"Larva";68;1
"Unit";"Zergling";"Larva";68;1
"Unit";"Zergling";"Larva";68;1
"Unit";"Zergling";"Larva";68;1
"Unit";"Zergling";"Larva";68;1
"Unit";"Zergling";"Larva";68;1
"Unit";"Zergling";"Larva";68;1
"Unit";"Zergling";"Larva";68;1
"Building";"CreepTumor";NA;68;0
"Building";"CreepTumorQueen";NA;90;0
"Building";"CreepTumor";NA;90;0
"Building";"CreepTumor";NA;90;0
"Building";"CreepTumor";NA;90;0
"Building";"CreepTumor";NA;90;0
"Building";"RoachWarren";NA;68;0
"Building";"CreepTumor";NA;93;0
"Building";"CreepTumor";NA;93;0
"Building";"CreepTumor";NA;93;0
"Unit";"Zergling";"Larva";93;1
"Unit";"Zergling";"Larva";93;1
"Building";"CreepTumor";NA;93;0
"Unit";"Zergling";"Larva";93;1
"Unit";"Zergling";"Larva";93;1
"Unit";"Zergling";"Larva";93;1
"Unit";"Zergling";"Larva";93;1
"Unit";"Zergling";"Larva";93;1
"Unit";"Zergling";"Larva";93;1
"Unit";"Zergling";"Larva";93;1
"Unit";"Zergling";"Larva";93;1
"Building";"CreepTumor";NA;93;0
"Unit";"Overlord";"Larva";93;0
"Unit";"Overlord";"Larva";93;0
"Unit";"Overlord";"Larva";93;0
"Unit";"Overlord";"Larva";93;0
"Unit";"Overlord";"Larva";93;0
"Unit";"Overlord";"Larva";93;0
"Building";"CreepTumorQueen";NA;93;0
"Building";"CreepTumorQueen";NA;93;0
"Building";"CreepTumorQueen";NA;103;0
"Building";"CreepTumorQueen";NA;103;0
"Building";"Extractor";NA;93;0
"Building";"CreepTumor";NA;110;0
"Building";"CreepTumor";NA;110;0
"Building";"CreepTumor";NA;110;0
"Unit";"Roach";"Larva";110;2
"Unit";"Roach";"Larva";110;2
"Unit";"Roach";"Larva";110;2
"Unit";"Roach";"Larva";110;2
"Unit";"Roach";"Larva";110;2
"Unit";"Roach";"Larva";110;2
"Unit";"Roach";"Larva";110;2
"Unit";"Roach";"Larva";110;2
"Unit";"Roach";"Larva";110;2
"Unit";"Roach";"Larva";110;2
"Unit";"Roach";"Larva";110;2
"Unit";"Overlord";"Larva";110;0
"Upgrade";"GlialReconstitution";"RoachWarren";103;0
"Unit";"Overlord";"Larva";132;0
"Unit";"Overlord";"Larva";132;0
"Building";"CreepTumor";NA;132;0
"Building";"CreepTumor";NA;132;0
"Unit";"Roach";"Larva";132;2
"Unit";"Roach";"Larva";132;2
"Unit";"Roach";"Larva";132;2
"Unit";"Roach";"Larva";132;2
"Unit";"Roach";"Larva";132;2
"Unit";"Roach";"Larva";132;2
"Unit";"Roach";"Larva";132;2
"Unit";"Roach";"Larva";132;2
"Unit";"Roach";"Larva";132;2
"Building";"CreepTumor";NA;132;0
"Building";"CreepTumor";NA;132;0
"Building";"CreepTumor";NA;132;0
"Building";"CreepTumor";NA;132;0
"Building";"CreepTumor";NA;132;0
"Building";"CreepTumor";NA;132;0
"Building";"CreepTumor";NA;132;0
"Building";"Hatchery";NA;103;0
"Unit";"Roach";"Larva";150;2
"Unit";"Roach";"Larva";150;2
"Unit";"Roach";"Larva";150;2
"Unit";"Roach";"Larva";150;2
"Unit";"Roach";"Larva";150;2
"Unit";"Roach";"Larva";150;2
"Unit";"Roach";"Larva";150;2
"Unit";"Roach";"Larva";150;2
"Unit";"Roach";"Larva";166;2
"Unit";"Roach";"Larva";166;2
"Unit";"Roach";"Larva";166;2
"Unit";"Roach";"Larva";166;2
"Unit";"Roach";"Larva";166;2
"Unit";"Roach";"Larva";166;2
"Unit";"Roach";"Larva";166;2
"Unit";"Roach";"Larva";166;2
"Unit";"Roach";"Larva";166;2
"Unit";"Roach";"Larva";166;2
"Building";"CreepTumor";NA;166;0
"Building";"Extractor";NA;166;0
"Building";"Extractor";NA;166;0
