"type";"unit_name";"on_building";"total_supply";"supply"
"Unit";"Overlord";"Larva";13;0
"Building";"Extractor";NA;17;0
"Unit";"Overlord";"Larva";21;0
"Building";"Hatchery";NA;16;0
"Building";"SpawningPool";NA;19;0
"Unit";"Zergling";"Larva";23;1
"Unit";"Zergling";"Larva";23;1
"Unit";"Zergling";"Larva";23;1
"Unit";"Zergling";"Larva";23;1
"Unit";"Queen";"Hatchery";23;2
"Unit";"Queen";"Hatchery";23;2
"Building";"CreepTumorQueen";NA;35;0
"Unit";"Overlord";"Larva";37;0
"Unit";"Overlord";"Larva";39;0
"Unit";"Queen";"Hatchery";37;2
"Building";"CreepTumorQueen";NA;40;0
"Building";"CreepTumor";NA;40;0
"Building";"Hatchery";NA;31;0
"Building";"SporeCrawler";NA;48;0
"Building";"SporeCrawler";NA;48;0
"Unit";"Overlord";"Larva";48;0
"Unit";"Overlord";"Larva";48;0
"Unit";"Zergling";"Larva";51;1
"Unit";"Zergling";"Larva";51;1
"Unit";"Zergling";"Larva";51;1
"Unit";"Zergling";"Larva";51;1
"Building";"CreepTumor";NA;51;0
"Building";"CreepTumor";NA;51;0
"Unit";"Zergling";"Larva";51;1
"Unit";"Zergling";"Larva";51;1
"Unit";"Queen";"Hatchery";48;2
"Building";"CreepTumorQueen";NA;51;0
"Building";"Extractor";NA;51;0
"Building";"Extractor";NA;51;0
"Unit";"Queen";"Hatchery";51;2
"Building";"EvolutionChamber";NA;51;0
"Building";"CreepTumorQueen";NA;59;0
"Unit";"Overlord";"Larva";71;0
"Unit";"Overlord";"Larva";71;0
"Building";"SporeCrawler";NA;72;0
"Building";"CreepTumor";NA;72;0
"Building";"CreepTumor";NA;77;0
"Building";"CreepTumor";NA;77;0
"Building";"CreepTumor";NA;77;0
"Unit";"Overlord";"Larva";80;0
"Unit";"Overlord";"Larva";80;0
"Building";"RoachWarren";NA;76;0
"Unit";"Overlord";"Larva";81;0
"Unit";"Overlord";"Larva";81;0
"Unit";"Overlord";"Larva";92;0
"Unit";"Overlord";"Larva";92;0
"Unit";"Overlord";"Larva";92;0
"Unit";"Overlord";"Larva";92;0
"Building";"CreepTumor";NA;94;0
"Unit";"Roach";"Larva";94;2
"Unit";"Roach";"Larva";94;2
"Unit";"Roach";"Larva";94;2
"Unit";"Roach";"Larva";94;2
"Building";"CreepTumor";NA;94;0
"Unit";"Roach";"Larva";94;2
"Unit";"Roach";"Larva";94;2
"Building";"CreepTumor";NA;94;0
"Building";"CreepTumorQueen";NA;100;0
"Building";"CreepTumorQueen";NA;100;0
"Building";"CreepTumor";NA;96;0
"Unit";"Roach";"Larva";94;2
"Unit";"Roach";"Larva";94;2
"Building";"Extractor";NA;94;0
"Building";"Extractor";NA;94;0
"Unit";"Roach";"Larva";100;2
"Unit";"Roach";"Larva";100;2
"Unit";"Roach";"Larva";100;2
"Unit";"Roach";"Larva";100;2
"Unit";"Roach";"Larva";100;2
"Unit";"Roach";"Larva";100;2
"Unit";"Roach";"Larva";100;2
"Building";"HydraliskDen";NA;94;0
"Building";"CreepTumor";NA;106;0
"Building";"CreepTumor";NA;110;0
"Upgrade";"ZergMissileWeaponsLevel1";"EvolutionChamber";81;0
"Building";"CreepTumor";NA;127;0
"Building";"Extractor";NA;127;0
"Upgrade";"GlialReconstitution";"RoachWarren";94;0
"Building";"CreepTumor";NA;133;0
"Building";"CreepTumor";NA;133;0
"Building";"CreepTumor";NA;133;0
"Building";"CreepTumor";NA;133;0
"Unit";"Overlord";"Larva";142;0
"Unit";"Overlord";"Larva";142;0
"Unit";"Overlord";"Larva";142;0
"Unit";"Overlord";"Larva";142;0
"Building";"Hatchery";NA;110;0
"Building";"CreepTumor";NA;148;0
"Building";"Hatchery";NA;127;0
"Unit";"Hydralisk";"Larva";142;2
"Unit";"Hydralisk";"Larva";142;2
"Unit";"Hydralisk";"Larva";142;2
"Unit";"Hydralisk";"Larva";142;2
"Building";"InfestationPit";NA;142;0
"Upgrade";"EvolveGroovedSpines";"HydraliskDen";133;0
"Unit";"Hydralisk";"Larva";148;2
"Unit";"Hydralisk";"Larva";148;2
"Unit";"Hydralisk";"Larva";148;2
"Unit";"Hydralisk";"Larva";148;2
"Unit";"Hydralisk";"Larva";148;2
"Unit";"Hydralisk";"Larva";148;2
"Unit";"Hydralisk";"Larva";148;2
"Unit";"Hydralisk";"Larva";148;2
"Unit";"Hydralisk";"Larva";148;2
"Building";"Extractor";NA;148;0
"Building";"Extractor";NA;148;0
"Unit";"Hydralisk";"Larva";148;2
"Unit";"Overlord";"Larva";156;0
"Unit";"Hydralisk";"Larva";148;2
"Unit";"Hydralisk";"Larva";148;2
"Unit";"Overlord";"Larva";156;0
"Unit";"Hydralisk";"Larva";174;2
"Building";"SpineCrawler";NA;156;0
"Building";"SpineCrawler";NA;156;0
"Unit";"Hydralisk";"Larva";180;2
"Unit";"Hydralisk";"Larva";180;2
"Building";"CreepTumor";NA;180;0
"Building";"CreepTumorQueen";NA;182;0
"Building";"CreepTumorQueen";NA;182;0
"Building";"CreepTumor";NA;186;0
"Unit";"Roach";"Larva";186;2
"Unit";"Roach";"Larva";186;2
"Unit";"Roach";"Larva";186;2
"Unit";"Roach";"Larva";186;2
"Unit";"Roach";"Larva";186;2
"Building";"CreepTumor";NA;192;0
"Building";"CreepTumor";NA;193;0
"Building";"CreepTumor";NA;194;0
"Building";"CreepTumorQueen";NA;194;0
"Unit";"Hydralisk";"Larva";186;2
"Unit";"Hydralisk";"Larva";186;2
"Unit";"Hydralisk";"Larva";186;2
"Unit";"Hydralisk";"Larva";186;2
"Unit";"Hydralisk";"Larva";186;2
"Unit";"Hydralisk";"Larva";186;2
"Building";"CreepTumor";NA;194;0
"Building";"CreepTumor";NA;194;0
"Building";"CreepTumorQueen";NA;194;0
"Building";"CreepTumorQueen";NA;194;0
"Building";"CreepTumorQueen";NA;194;0
"Building";"CreepTumor";NA;194;0
"Building";"CreepTumorQueen";NA;204;0
"Building";"CreepTumorQueen";NA;204;0
"Building";"SpineCrawler";NA;186;0
"Building";"SpineCrawler";NA;186;0
"Building";"Spire";NA;174;0
"Building";"CreepTumor";NA;216;0
"Upgrade";"EvolveMuscularAugments";"HydraliskDen";186;0
"Building";"CreepTumor";NA;216;0
"Building";"CreepTumor";NA;216;0
"Building";"CreepTumor";NA;216;0
"Unit";"Roach";"Larva";216;2
"Unit";"Roach";"Larva";216;2
"Unit";"Roach";"Larva";216;2
"Unit";"Roach";"Larva";216;2
"Unit";"Roach";"Larva";216;2
"Building";"CreepTumor";NA;216;0
"Unit";"Hydralisk";"Larva";216;2
"Unit";"Hydralisk";"Larva";216;2
"Unit";"Hydralisk";"Larva";216;2
"Unit";"Hydralisk";"Larva";216;2
"Unit";"Hydralisk";"Larva";216;2
"Unit";"Hydralisk";"Larva";216;2
"Unit";"Overlord";"Larva";216;0
"Building";"SpineCrawler";NA;216;0
"Building";"CreepTumor";NA;238;0
"Building";"CreepTumor";NA;238;0
"Building";"CreepTumor";NA;238;0
"Building";"SpineCrawler";NA;216;0
"Building";"CreepTumorQueen";NA;238;0
"Building";"CreepTumorQueen";NA;238;0
"Building";"CreepTumorQueen";NA;238;0
"Unit";"Roach";"Larva";238;2
"Unit";"Roach";"Larva";238;2
"Unit";"Roach";"Larva";238;2
"Unit";"Roach";"Larva";238;2
"Unit";"Roach";"Larva";238;2
"Unit";"Roach";"Larva";238;2
"Unit";"Roach";"Larva";238;2
"Unit";"Roach";"Larva";238;2
"Unit";"Roach";"Larva";238;2
"Unit";"Hydralisk";"Larva";238;2
"Unit";"Hydralisk";"Larva";238;2
"Unit";"Hydralisk";"Larva";238;2
"Unit";"Hydralisk";"Larva";238;2
"Building";"CreepTumor";NA;238;0
"Unit";"Hydralisk";"Larva";238;2
"Unit";"Hydralisk";"Larva";238;2
"Unit";"Hydralisk";"Larva";238;2
"Unit";"Hydralisk";"Larva";238;2
"Upgrade";"ZergMissileWeaponsLevel2";"EvolutionChamber";216;0
"Building";"CreepTumor";NA;238;0
"Building";"CreepTumor";NA;238;0
"Building";"CreepTumor";NA;238;0
"Building";"CreepTumor";NA;238;0
"Building";"CreepTumor";NA;238;0
"Building";"CreepTumor";NA;238;0
"Unit";"Corruptor";"Larva";238;2
"Unit";"Corruptor";"Larva";238;2
"Unit";"Corruptor";"Larva";238;2
"Unit";"Corruptor";"Larva";238;2
"Unit";"Corruptor";"Larva";238;2
"Building";"CreepTumor";NA;256;0
"Building";"CreepTumorQueen";NA;272;0
"Building";"CreepTumor";NA;282;0
"Building";"CreepTumor";NA;282;0
"Unit";"Hydralisk";"Larva";282;2
"Unit";"Hydralisk";"Larva";282;2
"Unit";"Hydralisk";"Larva";282;2
"Unit";"Hydralisk";"Larva";282;2
"Unit";"Hydralisk";"Larva";282;2
"Unit";"Hydralisk";"Larva";282;2
"Unit";"Hydralisk";"Larva";282;2
"Unit";"Hydralisk";"Larva";282;2
"Building";"CreepTumor";NA;298;0
"Unit";"Hydralisk";"Larva";282;2
"Unit";"Hydralisk";"Larva";282;2
"Unit";"Hydralisk";"Larva";282;2
"Unit";"Hydralisk";"Larva";282;2
"Unit";"Hydralisk";"Larva";282;2
"Unit";"Hydralisk";"Larva";282;2
"Unit";"Hydralisk";"Larva";282;2
"Building";"CreepTumorQueen";NA;298;0
"Building";"CreepTumor";NA;312;0
"Building";"CreepTumor";NA;312;0
"Building";"CreepTumor";NA;312;0
"Building";"Hatchery";NA;282;0
"Building";"CreepTumor";NA;312;0
"Building";"Extractor";NA;312;0
"Building";"CreepTumor";NA;312;0
"Building";"CreepTumorQueen";NA;315;0
"Building";"CreepTumor";NA;315;0
"Building";"CreepTumor";NA;315;0
"Building";"LurkerDenMP";NA;282;0
"Unit";"Zergling";"Larva";315;1
"Unit";"Zergling";"Larva";315;1
"Unit";"Zergling";"Larva";315;1
"Unit";"Zergling";"Larva";315;1
"Unit";"Zergling";"Larva";315;1
"Unit";"Zergling";"Larva";315;1
"Unit";"Zergling";"Larva";315;1
"Unit";"Zergling";"Larva";315;1
"Unit";"Zergling";"Larva";315;1
"Unit";"Zergling";"Larva";315;1
"Unit";"Zergling";"Larva";315;1
"Unit";"Zergling";"Larva";315;1
"Unit";"Zergling";"Larva";315;1
"Unit";"Zergling";"Larva";315;1
"Unit";"Zergling";"Larva";315;1
"Unit";"Zergling";"Larva";315;1
"Unit";"Zergling";"Larva";315;1
"Unit";"Zergling";"Larva";315;1
"Unit";"Zergling";"Larva";315;1
"Unit";"Zergling";"Larva";315;1
"Unit";"Zergling";"Larva";315;1
"Unit";"Zergling";"Larva";315;1
"Unit";"Zergling";"Larva";315;1
"Unit";"Zergling";"Larva";315;1
"Unit";"Zergling";"Larva";315;1
"Unit";"Zergling";"Larva";315;1
"Unit";"Zergling";"Larva";315;1
"Unit";"Zergling";"Larva";315;1
"Unit";"Zergling";"Larva";315;1
"Unit";"Zergling";"Larva";315;1
"Unit";"Zergling";"Larva";315;1
"Unit";"Zergling";"Larva";315;1
"Unit";"Hydralisk";"Larva";347;2
"Unit";"Hydralisk";"Larva";347;2
"Unit";"Hydralisk";"Larva";347;2
"Unit";"Hydralisk";"Larva";347;2
"Unit";"Hydralisk";"Larva";347;2
"Unit";"Hydralisk";"Larva";347;2
"Unit";"Hydralisk";"Larva";347;2
"Unit";"Hydralisk";"Larva";347;2
"Unit";"Hydralisk";"Larva";347;2
"Unit";"Hydralisk";"Larva";347;2
"Unit";"Hydralisk";"Larva";347;2
"Unit";"Hydralisk";"Larva";347;2
"Unit";"Hydralisk";"Larva";347;2
"Unit";"Hydralisk";"Larva";347;2
"Unit";"Hydralisk";"Larva";347;2
"Unit";"Hydralisk";"Larva";347;2
"Unit";"Hydralisk";"Larva";347;2
"Unit";"Hydralisk";"Larva";347;2
"Unit";"Hydralisk";"Larva";347;2
"Unit";"Hydralisk";"Larva";347;2
"Unit";"Hydralisk";"Larva";347;2
"Unit";"Hydralisk";"Larva";347;2
"Unit";"Hydralisk";"Larva";347;2
"Unit";"Hydralisk";"Larva";347;2
"Unit";"Hydralisk";"Larva";347;2
"Unit";"Hydralisk";"Larva";347;2
"Unit";"Hydralisk";"Larva";347;2
"Building";"CreepTumor";NA;347;0
"Building";"CreepTumor";NA;347;0
"Unit";"Hydralisk";"Larva";347;2
"Unit";"Hydralisk";"Larva";347;2
"Unit";"Hydralisk";"Larva";347;2
