"type";"unit_name";"on_building";"total_supply";"supply"
"Unit";"Overlord";"Larva";13;0
"Building";"Extractor";NA;18;0
"Building";"SpawningPool";NA;18;0
"Unit";"Overlord";"Larva";21;0
"Building";"Hatchery";NA;16;0
"Unit";"Zergling";"Larva";22;1
"Unit";"Zergling";"Larva";22;1
"Unit";"Zergling";"Larva";22;1
"Unit";"Zergling";"Larva";22;1
"Unit";"Queen";"Hatchery";22;2
"Unit";"Overlord";"Larva";34;0
"Unit";"Queen";"Hatchery";33;2
"Building";"Hatchery";NA;27;0
"Building";"Extractor";NA;40;0
"Unit";"Queen";"Hatchery";38;2
"Unit";"Overlord";"Larva";46;0
"Building";"SporeCrawler";NA;47;0
"Building";"SporeCrawler";NA;47;0
"Building";"SporeCrawler";NA;48;0
"Unit";"Overlord";"Larva";52;0
"Building";"CreepTumorQueen";NA;56;0
"Building";"CreepTumorQueen";NA;60;0
"Unit";"Queen";"Hatchery";52;2
"Building";"RoachWarren";NA;60;0
"Building";"CreepTumor";NA;72;0
"Building";"CreepTumor";NA;72;0
"Building";"CreepTumorQueen";NA;72;0
"Building";"Extractor";NA;62;0
"Unit";"Overlord";"Larva";72;0
"Unit";"Overlord";"Larva";72;0
"Unit";"Overlord";"Larva";72;0
"Building";"Extractor";NA;72;0
"Building";"CreepTumor";NA;75;0
"Building";"CreepTumor";NA;75;0
"Building";"CreepTumor";NA;76;0
"Building";"CreepTumorQueen";NA;81;0
"Unit";"Roach";"Larva";77;2
"Unit";"Roach";"Larva";77;2
"Unit";"Roach";"Larva";77;2
"Unit";"Roach";"Larva";77;2
"Unit";"Roach";"Larva";77;2
"Unit";"Roach";"Larva";86;2
"Unit";"Overlord";"Larva";86;0
"Unit";"Overlord";"Larva";86;0
"Unit";"Overlord";"Larva";86;0
"Building";"CreepTumor";NA;96;0
"Building";"CreepTumor";NA;98;0
"Unit";"Overlord";"Larva";98;0
"Unit";"Overlord";"Larva";98;0
"Building";"CreepTumor";NA;98;0
"Unit";"Roach";"Larva";98;2
"Unit";"Roach";"Larva";98;2
"Unit";"Roach";"Larva";98;2
"Unit";"Roach";"Larva";98;2
"Building";"CreepTumorQueen";NA;98;0
"Upgrade";"GlialReconstitution";"RoachWarren";80;0
"Unit";"Roach";"Larva";98;2
"Unit";"Roach";"Larva";98;2
"Unit";"Roach";"Larva";98;2
"Unit";"Roach";"Larva";98;2
"Unit";"Roach";"Larva";98;2
"Unit";"Roach";"Larva";98;2
"Unit";"Roach";"Larva";98;2
"Unit";"Roach";"Larva";98;2
"Unit";"Roach";"Larva";100;2
"Unit";"Roach";"Larva";100;2
"Unit";"Roach";"Larva";106;2
"Unit";"Roach";"Larva";106;2
"Unit";"Roach";"Larva";106;2
"Unit";"Roach";"Larva";106;2
"Unit";"Roach";"Larva";116;2
"Unit";"Roach";"Larva";116;2
"Unit";"Roach";"Larva";120;2
"Unit";"Roach";"Larva";120;2
"Unit";"Roach";"Larva";120;2
"Unit";"Roach";"Larva";128;2
"Unit";"Roach";"Larva";138;2
"Unit";"Roach";"Larva";138;2
"Unit";"Roach";"Larva";138;2
"Building";"Hatchery";NA;98;0
"Building";"CreepTumor";NA;146;0
"Unit";"Roach";"Larva";146;2
"Unit";"Roach";"Larva";146;2
"Unit";"Roach";"Larva";146;2
"Unit";"Roach";"Larva";146;2
"Unit";"Roach";"Larva";152;2
"Unit";"Roach";"Larva";152;2
"Unit";"Roach";"Larva";152;2
"Unit";"Roach";"Larva";152;2
"Unit";"Overlord";"Larva";160;0
"Unit";"Overlord";"Larva";160;0
"Unit";"Overlord";"Larva";160;0
"Unit";"Overlord";"Larva";168;0
"Unit";"Zergling";"Larva";168;1
"Unit";"Zergling";"Larva";168;1
"Building";"CreepTumorQueen";NA;168;0
"Unit";"Zergling";"Larva";168;1
"Unit";"Zergling";"Larva";168;1
"Unit";"Zergling";"Larva";168;1
"Unit";"Zergling";"Larva";168;1
"Unit";"Zergling";"Larva";168;1
"Unit";"Zergling";"Larva";168;1
"Unit";"Zergling";"Larva";168;1
"Unit";"Zergling";"Larva";168;1
"Unit";"Zergling";"Larva";168;1
"Unit";"Zergling";"Larva";168;1
"Unit";"Zergling";"Larva";168;1
"Unit";"Zergling";"Larva";168;1
"Unit";"Zergling";"Larva";168;1
"Unit";"Zergling";"Larva";168;1
"Unit";"Zergling";"Larva";168;1
"Unit";"Zergling";"Larva";168;1
"Unit";"Zergling";"Larva";168;1
"Unit";"Zergling";"Larva";168;1
"Unit";"Queen";"Hatchery";168;2
"Unit";"Zergling";"Larva";178;1
"Unit";"Zergling";"Larva";178;1
"Unit";"Zergling";"Larva";188;1
"Unit";"Zergling";"Larva";188;1
"Unit";"Zergling";"Larva";188;1
"Unit";"Zergling";"Larva";188;1
"Unit";"Zergling";"Larva";188;1
"Unit";"Zergling";"Larva";188;1
"Unit";"Zergling";"Larva";188;1
"Unit";"Zergling";"Larva";188;1
"Unit";"Zergling";"Larva";188;1
"Unit";"Zergling";"Larva";188;1
"Unit";"Zergling";"Larva";188;1
"Unit";"Zergling";"Larva";188;1
"Unit";"Zergling";"Larva";188;1
"Unit";"Zergling";"Larva";188;1
"Unit";"Overlord";"Larva";188;0
"Unit";"Overlord";"Larva";206;0
"Unit";"Overlord";"Larva";206;0
"Unit";"Zergling";"Larva";206;1
"Unit";"Zergling";"Larva";206;1
"Unit";"Zergling";"Larva";206;1
"Unit";"Zergling";"Larva";206;1
"Unit";"Zergling";"Larva";206;1
"Unit";"Zergling";"Larva";206;1
"Unit";"Zergling";"Larva";206;1
"Unit";"Zergling";"Larva";206;1
"Unit";"Zergling";"Larva";206;1
"Unit";"Zergling";"Larva";206;1
"Unit";"Zergling";"Larva";206;1
"Unit";"Zergling";"Larva";206;1
"Unit";"Zergling";"Larva";206;1
"Unit";"Zergling";"Larva";206;1
"Unit";"Zergling";"Larva";220;1
"Unit";"Zergling";"Larva";220;1
"Unit";"Zergling";"Larva";220;1
"Unit";"Zergling";"Larva";220;1
"Unit";"Zergling";"Larva";220;1
"Unit";"Zergling";"Larva";220;1
"Unit";"Zergling";"Larva";220;1
"Unit";"Zergling";"Larva";220;1
"Unit";"Zergling";"Larva";220;1
"Unit";"Zergling";"Larva";220;1
"Unit";"Zergling";"Larva";220;1
"Unit";"Zergling";"Larva";220;1
"Unit";"Zergling";"Larva";220;1
"Unit";"Zergling";"Larva";220;1
"Unit";"Zergling";"Larva";220;1
"Unit";"Zergling";"Larva";220;1
"Unit";"Zergling";"Larva";220;1
"Unit";"Zergling";"Larva";220;1
"Unit";"Zergling";"Larva";220;1
"Unit";"Zergling";"Larva";220;1
"Unit";"Zergling";"Larva";220;1
"Unit";"Zergling";"Larva";220;1
"Unit";"Zergling";"Larva";220;1
"Unit";"Zergling";"Larva";220;1
"Unit";"Zergling";"Larva";220;1
"Unit";"Zergling";"Larva";220;1
"Unit";"Zergling";"Larva";220;1
"Unit";"Zergling";"Larva";220;1
"Unit";"Zergling";"Larva";220;1
"Unit";"Zergling";"Larva";220;1
"Unit";"Zergling";"Larva";220;1
"Unit";"Zergling";"Larva";220;1
"Unit";"Zergling";"Larva";220;1
"Unit";"Zergling";"Larva";220;1
"Unit";"Zergling";"Larva";220;1
"Unit";"Zergling";"Larva";220;1
"Unit";"Zergling";"Larva";220;1
"Unit";"Zergling";"Larva";220;1
"Unit";"Zergling";"Larva";220;1
"Unit";"Zergling";"Larva";220;1
"Unit";"Zergling";"Larva";220;1
"Unit";"Zergling";"Larva";220;1
"Unit";"Zergling";"Larva";220;1
"Unit";"Zergling";"Larva";220;1
"Unit";"Zergling";"Larva";246;1
"Unit";"Zergling";"Larva";246;1
"Unit";"Zergling";"Larva";246;1
"Unit";"Zergling";"Larva";246;1
"Unit";"Zergling";"Larva";246;1
"Unit";"Zergling";"Larva";246;1
"Unit";"Zergling";"Larva";246;1
"Unit";"Zergling";"Larva";246;1
"Unit";"Zergling";"Larva";246;1
"Unit";"Zergling";"Larva";246;1
"Unit";"Zergling";"Larva";246;1
"Unit";"Zergling";"Larva";246;1
"Unit";"Zergling";"Larva";246;1
"Unit";"Zergling";"Larva";246;1
"Unit";"Zergling";"Larva";264;1
"Unit";"Zergling";"Larva";264;1
"Unit";"Zergling";"Larva";264;1
"Unit";"Zergling";"Larva";264;1
"Unit";"Zergling";"Larva";264;1
"Unit";"Zergling";"Larva";264;1
"Unit";"Zergling";"Larva";264;1
"Unit";"Zergling";"Larva";264;1
"Unit";"Zergling";"Larva";264;1
"Unit";"Zergling";"Larva";264;1
"Unit";"Zergling";"Larva";264;1
"Unit";"Zergling";"Larva";264;1
