"type";"unit_name";"on_building";"total_supply";"supply"
"Unit";"Overlord";"Larva";12;0
"Building";"Extractor";NA;18;0
"Unit";"Overlord";"Larva";21;0
"Building";"SpawningPool";NA;19;0
"Building";"Hatchery";NA;17;0
"Unit";"Zergling";"Larva";22;1
"Unit";"Zergling";"Larva";22;1
"Unit";"Zergling";"Larva";23;1
"Unit";"Zergling";"Larva";23;1
"Unit";"Zergling";"Larva";24;1
"Unit";"Zergling";"Larva";24;1
"Unit";"Queen";"Hatchery";22;2
"Unit";"Queen";"Hatchery";22;2
"Unit";"Overlord";"Larva";36;0
"Building";"CreepTumorQueen";NA;38;0
"Unit";"Queen";"Hatchery";36;2
"Unit";"Overlord";"Larva";40;0
"Building";"CreepTumor";NA;50;0
"Building";"SporeCrawler";NA;46;0
"Building";"SporeCrawler";NA;48;0
"Building";"Hatchery";NA;36;0
"Building";"CreepTumorQueen";NA;52;0
"Building";"SporeCrawler";NA;52;0
"Building";"CreepTumor";NA;52;0
"Building";"CreepTumorQueen";NA;52;0
"Unit";"Overlord";"Larva";52;0
"Unit";"Overlord";"Larva";52;0
"Unit";"Queen";"Hatchery";52;2
"Building";"Extractor";NA;61;0
"Building";"Extractor";NA;61;0
"Building";"CreepTumor";NA;63;0
"Building";"CreepTumor";NA;63;0
"Building";"CreepTumor";NA;63;0
"Building";"EvolutionChamber";NA;61;0
"Building";"EvolutionChamber";NA;61;0
"Building";"CreepTumorQueen";NA;69;0
"Building";"BanelingNest";NA;61;0
"Building";"HydraliskDen";NA;63;0
"Unit";"Queen";"Hatchery";63;2
"Unit";"Overlord";"Larva";74;0
"Building";"CreepTumorQueen";NA;79;0
"Unit";"Overlord";"Larva";74;0
"Unit";"Overlord";"Larva";74;0
"Building";"CreepTumor";NA;79;0
"Building";"CreepTumor";NA;79;0
"Building";"CreepTumor";NA;79;0
"Building";"CreepTumor";NA;81;0
"Unit";"Overlord";"Larva";81;0
"Unit";"Overlord";"Larva";81;0
"Unit";"Zergling";"Larva";81;1
"Unit";"Zergling";"Larva";81;1
"Unit";"Zergling";"Larva";81;1
"Unit";"Zergling";"Larva";81;1
"Unit";"Zergling";"Larva";81;1
"Unit";"Zergling";"Larva";81;1
"Unit";"Zergling";"Larva";81;1
"Unit";"Zergling";"Larva";81;1
"Unit";"Zergling";"Larva";81;1
"Unit";"Zergling";"Larva";81;1
"Unit";"Zergling";"Larva";81;1
"Unit";"Zergling";"Larva";81;1
"Building";"CreepTumor";NA;81;0
"Building";"CreepTumor";NA;81;0
"Building";"CreepTumor";NA;81;0
"Building";"CreepTumorQueen";NA;83;0
"Building";"CreepTumor";NA;81;0
"Building";"Extractor";NA;81;0
"Building";"CreepTumor";NA;94;0
"Building";"CreepTumor";NA;94;0
"Building";"CreepTumor";NA;94;0
"Building";"CreepTumor";NA;98;0
"Building";"CreepTumor";NA;102;0
"Building";"CreepTumor";NA;102;0
"Unit";"Zergling";"Larva";102;1
"Unit";"Zergling";"Larva";102;1
"Unit";"Zergling";"Larva";102;1
"Unit";"Zergling";"Larva";102;1
"Unit";"Zergling";"Larva";102;1
"Unit";"Zergling";"Larva";102;1
"Unit";"Zergling";"Larva";102;1
"Unit";"Zergling";"Larva";102;1
"Unit";"Zergling";"Larva";102;1
"Unit";"Zergling";"Larva";102;1
"Unit";"Zergling";"Larva";102;1
"Unit";"Zergling";"Larva";102;1
"Unit";"Zergling";"Larva";102;1
"Unit";"Zergling";"Larva";102;1
"Unit";"Zergling";"Larva";102;1
"Unit";"Zergling";"Larva";102;1
"Unit";"Zergling";"Larva";102;1
"Unit";"Zergling";"Larva";102;1
"Unit";"Zergling";"Larva";102;1
"Unit";"Zergling";"Larva";102;1
"Unit";"Hydralisk";"Larva";102;2
"Unit";"Hydralisk";"Larva";102;2
"Unit";"Overlord";"Larva";102;0
"Unit";"Overlord";"Larva";102;0
"Building";"CreepTumorQueen";NA;122;0
"Building";"CreepTumor";NA;122;0
"Building";"CreepTumor";NA;126;0
"Building";"CreepTumor";NA;126;0
"Building";"CreepTumor";NA;127;0
"Building";"CreepTumor";NA;127;0
"Upgrade";"EvolveMuscularAugments";"HydraliskDen";102;0
"Building";"CreepTumor";NA;127;0
"Unit";"Hydralisk";"Larva";127;2
"Unit";"Hydralisk";"Larva";127;2
"Unit";"Hydralisk";"Larva";127;2
"Unit";"Hydralisk";"Larva";127;2
"Unit";"Hydralisk";"Larva";127;2
"Unit";"Hydralisk";"Larva";127;2
"Unit";"Overlord";"Larva";127;0
"Unit";"Overlord";"Larva";127;0
"Unit";"Overlord";"Larva";127;0
"Unit";"Overlord";"Larva";127;0
"Unit";"Overlord";"Larva";127;0
"Upgrade";"ZergMissileWeaponsLevel1";"EvolutionChamber";94;0
"Upgrade";"ZergMeleeWeaponsLevel1";"EvolutionChamber";94;0
"Unit";"Hydralisk";"Larva";127;2
"Unit";"Hydralisk";"Larva";127;2
"Unit";"Hydralisk";"Larva";127;2
"Building";"CreepTumor";NA;139;0
"Building";"CreepTumor";NA;139;0
"Building";"CreepTumor";NA;139;0
"Building";"CreepTumor";NA;139;0
"Unit";"Zergling";"Larva";127;1
"Unit";"Zergling";"Larva";127;1
"Building";"CreepTumor";NA;139;0
"Unit";"Zergling";"Larva";127;1
"Unit";"Zergling";"Larva";127;1
"Building";"CreepTumorQueen";NA;139;0
"Building";"CreepTumor";NA;139;0
"Unit";"Hydralisk";"Larva";127;2
"Unit";"Hydralisk";"Larva";127;2
"Building";"CreepTumor";NA;139;0
"Building";"Extractor";NA;145;0
"Unit";"Hydralisk";"Larva";145;2
"Unit";"Hydralisk";"Larva";145;2
"Unit";"Hydralisk";"Larva";145;2
"Building";"Hatchery";NA;122;0
"Unit";"Zergling";"Larva";153;1
"Unit";"Zergling";"Larva";153;1
"Building";"Extractor";NA;149;0
"Unit";"Zergling";"Larva";153;1
"Unit";"Zergling";"Larva";153;1
"Unit";"Zergling";"Larva";153;1
"Unit";"Zergling";"Larva";153;1
"Unit";"Zergling";"Larva";153;1
"Unit";"Zergling";"Larva";153;1
"Unit";"Zergling";"Larva";153;1
"Unit";"Zergling";"Larva";153;1
"Unit";"Zergling";"Larva";153;1
"Unit";"Zergling";"Larva";153;1
"Building";"CreepTumor";NA;153;0
"Building";"CreepTumor";NA;153;0
"Unit";"Hydralisk";"Larva";149;2
"Unit";"Hydralisk";"Larva";149;2
"Unit";"Hydralisk";"Larva";151;2
"Building";"CreepTumor";NA;153;0
"Building";"CreepTumor";NA;153;0
"Building";"CreepTumor";NA;159;0
"Unit";"Zergling";"Larva";163;1
"Unit";"Zergling";"Larva";163;1
"Unit";"Zergling";"Larva";165;1
"Unit";"Zergling";"Larva";165;1
"Unit";"Zergling";"Larva";167;1
"Unit";"Zergling";"Larva";167;1
"Unit";"Baneling";"Zergling";171;0
"Unit";"Zergling";"Larva";169;1
"Unit";"Zergling";"Larva";169;1
"Unit";"Baneling";"Zergling";171;0
"Unit";"Baneling";"Zergling";171;0
"Unit";"Zergling";"Larva";171;1
"Unit";"Zergling";"Larva";171;1
"Unit";"Baneling";"Zergling";171;0
"Unit";"Zergling";"Larva";171;1
"Unit";"Zergling";"Larva";171;1
"Unit";"Zergling";"Larva";171;1
"Unit";"Zergling";"Larva";171;1
"Unit";"Baneling";"Zergling";171;0
"Unit";"Baneling";"Zergling";171;0
"Unit";"Baneling";"Zergling";171;0
"Unit";"Baneling";"Zergling";171;0
"Unit";"Baneling";"Zergling";171;0
"Upgrade";"EvolveGroovedSpines";"HydraliskDen";145;0
"Unit";"Hydralisk";"Larva";177;2
"Unit";"Zergling";"Larva";191;1
"Unit";"Zergling";"Larva";191;1
"Unit";"Zergling";"Larva";193;1
"Unit";"Zergling";"Larva";193;1
"Unit";"Zergling";"Larva";193;1
"Unit";"Zergling";"Larva";193;1
"Unit";"Zergling";"Larva";193;1
"Unit";"Zergling";"Larva";193;1
"Unit";"Zergling";"Larva";193;1
"Unit";"Zergling";"Larva";193;1
"Unit";"Zergling";"Larva";193;1
"Unit";"Zergling";"Larva";193;1
"Unit";"Zergling";"Larva";193;1
"Unit";"Zergling";"Larva";193;1
"Unit";"Zergling";"Larva";193;1
"Unit";"Zergling";"Larva";193;1
"Unit";"Zergling";"Larva";193;1
"Unit";"Zergling";"Larva";193;1
"Unit";"Hydralisk";"Larva";191;2
"Unit";"Hydralisk";"Larva";191;2
"Unit";"Hydralisk";"Larva";191;2
"Unit";"Hydralisk";"Larva";191;2
"Building";"CreepTumor";NA;193;0
"Unit";"Hydralisk";"Larva";191;2
"Building";"CreepTumor";NA;193;0
"Building";"CreepTumor";NA;193;0
"Building";"CreepTumor";NA;193;0
"Unit";"Zergling";"Larva";193;1
"Unit";"Zergling";"Larva";193;1
"Unit";"Zergling";"Larva";193;1
"Unit";"Zergling";"Larva";193;1
"Unit";"Zergling";"Larva";193;1
"Unit";"Zergling";"Larva";193;1
"Unit";"Zergling";"Larva";193;1
"Unit";"Zergling";"Larva";193;1
"Building";"CreepTumor";NA;221;0
"Building";"CreepTumor";NA;221;0
"Building";"CreepTumor";NA;221;0
"Unit";"Hydralisk";"Larva";193;2
"Unit";"Hydralisk";"Larva";193;2
"Unit";"Hydralisk";"Larva";193;2
"Unit";"Hydralisk";"Larva";193;2
"Building";"Extractor";NA;213;0
"Building";"CreepTumor";NA;229;0
"Unit";"Zergling";"Larva";221;1
"Unit";"Zergling";"Larva";221;1
"Unit";"Zergling";"Larva";221;1
"Unit";"Zergling";"Larva";221;1
"Unit";"Zergling";"Larva";221;1
"Unit";"Zergling";"Larva";221;1
"Unit";"Zergling";"Larva";221;1
"Unit";"Zergling";"Larva";221;1
"Unit";"Hydralisk";"Larva";221;2
"Unit";"Hydralisk";"Larva";221;2
"Unit";"Hydralisk";"Larva";221;2
"Unit";"Hydralisk";"Larva";221;2
"Unit";"Queen";"Hatchery";211;2
"Unit";"Baneling";"Zergling";237;0
"Unit";"Baneling";"Zergling";237;0
"Unit";"Baneling";"Zergling";237;0
"Unit";"Baneling";"Zergling";237;0
"Unit";"Baneling";"Zergling";237;0
"Unit";"Baneling";"Zergling";237;0
"Unit";"Baneling";"Zergling";237;0
"Unit";"Overlord";"Larva";247;0
"Unit";"Overlord";"Larva";249;0
"Unit";"Overlord";"Larva";251;0
"Unit";"Overlord";"Larva";253;0
"Unit";"Zergling";"Larva";255;1
"Unit";"Zergling";"Larva";255;1
"Unit";"Zergling";"Larva";255;1
"Unit";"Zergling";"Larva";255;1
"Unit";"Zergling";"Larva";255;1
"Unit";"Zergling";"Larva";255;1
"Unit";"Zergling";"Larva";255;1
"Unit";"Zergling";"Larva";255;1
"Unit";"Zergling";"Larva";255;1
"Unit";"Zergling";"Larva";255;1
"Unit";"Zergling";"Larva";255;1
"Unit";"Zergling";"Larva";255;1
"Unit";"Zergling";"Larva";255;1
"Unit";"Zergling";"Larva";255;1
