"type";"unit_name";"on_building";"total_supply";"supply"
"Unit";"Overlord";"Larva";14;0
"Building";"SpawningPool";NA;12;0
"Unit";"Zergling";"Larva";15;1
"Unit";"Zergling";"Larva";15;1
"Unit";"Zergling";"Larva";15;1
"Unit";"Zergling";"Larva";15;1
"Unit";"Zergling";"Larva";15;1
"Unit";"Zergling";"Larva";15;1
"Building";"Extractor";NA;22;0
"Unit";"Queen";"Hatchery";21;2
"Unit";"Overlord";"Larva";24;0
