"type";"unit_name";"on_building";"total_supply";"supply"
"Unit";"Overlord";"Larva";13;0
"Building";"Extractor";NA;18;0
"Building";"Hatchery";NA;16;0
"Building";"SpawningPool";NA;19;0
"Unit";"Overlord";"Larva";22;0
"Unit";"Zergling";"Larva";23;1
"Unit";"Zergling";"Larva";23;1
"Unit";"Zergling";"Larva";23;1
"Unit";"Zergling";"Larva";23;1
"Unit";"Queen";"Hatchery";23;2
"Unit";"Queen";"Hatchery";23;2
"Unit";"Overlord";"Larva";37;0
"Building";"CreepTumorQueen";NA;40;0
"Unit";"Overlord";"Larva";42;0
"Building";"CreepTumor";NA;47;0
"Unit";"Overlord";"Larva";44;0
"Building";"Hatchery";NA;35;0
"Unit";"Overlord";"Larva";47;0
"Building";"RoachWarren";NA;42;0
"Building";"Extractor";NA;47;0
"Building";"Extractor";NA;47;0
"Building";"CreepTumor";NA;56;0
"Unit";"Queen";"Hatchery";47;2
"Unit";"Roach";"Larva";57;2
"Unit";"Roach";"Larva";57;2
"Unit";"Roach";"Larva";57;2
"Unit";"Roach";"Larva";57;2
"Unit";"Roach";"Larva";57;2
"Unit";"Roach";"Larva";57;2
"Unit";"Roach";"Larva";57;2
"Building";"SporeCrawler";NA;57;0
"Unit";"Roach";"Larva";57;2
"Building";"SporeCrawler";NA;57;0
"Unit";"Overlord";"Larva";77;0
"Unit";"Overlord";"Larva";77;0
"Unit";"Overlord";"Larva";77;0
"Building";"Extractor";NA;77;0
"Unit";"Overlord";"Larva";77;0
"Unit";"Overlord";"Larva";77;0
"Building";"HydraliskDen";NA;77;0
"Building";"EvolutionChamber";NA;77;0
"Unit";"Roach";"Larva";77;2
"Unit";"Roach";"Larva";77;2
"Unit";"Roach";"Larva";77;2
"Unit";"Roach";"Larva";77;2
"Unit";"Roach";"Larva";77;2
"Unit";"Roach";"Larva";77;2
"Unit";"Roach";"Larva";77;2
"Unit";"Roach";"Larva";77;2
"Unit";"Roach";"Larva";97;2
"Unit";"Roach";"Larva";98;2
"Building";"SporeCrawler";NA;97;0
"Building";"CreepTumorQueen";NA;110;0
"Upgrade";"GlialReconstitution";"RoachWarren";77;0
"Unit";"Overlord";"Larva";110;0
"Unit";"Overlord";"Larva";110;0
"Building";"CreepTumor";NA;118;0
"Upgrade";"EvolveGroovedSpines";"HydraliskDen";100;0
"Building";"Extractor";NA;118;0
"Building";"Extractor";NA;118;0
"Unit";"Hydralisk";"Larva";121;2
"Unit";"Hydralisk";"Larva";121;2
"Unit";"Hydralisk";"Larva";121;2
"Unit";"Hydralisk";"Larva";121;2
"Unit";"Hydralisk";"Larva";121;2
"Unit";"Overlord";"Larva";121;0
"Unit";"Overlord";"Larva";121;0
"Building";"CreepTumor";NA;136;0
"Unit";"Hydralisk";"Larva";136;2
"Unit";"Hydralisk";"Larva";136;2
"Unit";"Hydralisk";"Larva";136;2
"Unit";"Hydralisk";"Larva";136;2
"Unit";"Hydralisk";"Larva";136;2
"Unit";"Hydralisk";"Larva";136;2
"Unit";"Hydralisk";"Larva";136;2
"Building";"CreepTumor";NA;136;0
"Unit";"Roach";"Larva";136;2
"Unit";"Roach";"Larva";136;2
"Unit";"Roach";"Larva";136;2
"Unit";"Roach";"Larva";136;2
"Unit";"Roach";"Larva";136;2
"Unit";"Overlord";"Larva";136;0
"Unit";"Overlord";"Larva";136;0
"Unit";"Overlord";"Larva";136;0
"Upgrade";"ZergMissileWeaponsLevel1";"EvolutionChamber";118;0
"Unit";"Overlord";"Larva";136;0
"Unit";"Overlord";"Larva";150;0
"Unit";"Overlord";"Larva";150;0
"Upgrade";"EvolveMuscularAugments";"HydraliskDen";136;0
"Unit";"Roach";"Larva";160;2
"Unit";"Roach";"Larva";160;2
"Unit";"Roach";"Larva";160;2
"Unit";"Roach";"Larva";160;2
"Unit";"Roach";"Larva";160;2
"Unit";"Roach";"Larva";160;2
"Unit";"Roach";"Larva";160;2
"Unit";"Roach";"Larva";160;2
"Unit";"Overlord";"Larva";160;0
"Unit";"Overlord";"Larva";160;0
"Unit";"Roach";"Larva";160;2
"Unit";"Roach";"Larva";160;2
"Unit";"Zergling";"Larva";176;1
"Unit";"Zergling";"Larva";176;1
"Unit";"Zergling";"Larva";176;1
"Unit";"Zergling";"Larva";176;1
"Unit";"Zergling";"Larva";176;1
"Unit";"Zergling";"Larva";176;1
"Unit";"Hydralisk";"Larva";176;2
"Unit";"Hydralisk";"Larva";176;2
"Unit";"Hydralisk";"Larva";176;2
"Unit";"Hydralisk";"Larva";176;2
"Unit";"Hydralisk";"Larva";176;2
"Unit";"Hydralisk";"Larva";176;2
"Building";"Hatchery";NA;150;0
"Unit";"Hydralisk";"Larva";180;2
"Unit";"Hydralisk";"Larva";180;2
"Unit";"Hydralisk";"Larva";180;2
"Unit";"Hydralisk";"Larva";198;2
"Unit";"Hydralisk";"Larva";198;2
"Unit";"Hydralisk";"Larva";198;2
"Unit";"Hydralisk";"Larva";198;2
"Building";"LurkerDenMP";NA;160;0
"Unit";"Zergling";"Larva";204;1
"Unit";"Zergling";"Larva";204;1
"Unit";"Zergling";"Larva";204;1
"Unit";"Zergling";"Larva";204;1
"Unit";"Zergling";"Larva";204;1
"Unit";"Zergling";"Larva";204;1
"Unit";"Hydralisk";"Larva";204;2
"Unit";"Hydralisk";"Larva";204;2
"Building";"SporeCrawler";NA;212;0
"Unit";"Queen";"Hatchery";204;2
"Unit";"Roach";"Larva";222;2
"Unit";"Roach";"Larva";222;2
"Unit";"Roach";"Larva";222;2
"Unit";"Roach";"Larva";222;2
"Unit";"Roach";"Larva";222;2
"Unit";"Roach";"Larva";222;2
"Unit";"Roach";"Larva";222;2
"Unit";"Roach";"Larva";222;2
"Unit";"Roach";"Larva";222;2
"Unit";"Roach";"Larva";222;2
"Unit";"Roach";"Larva";222;2
"Unit";"Roach";"Larva";222;2
"Unit";"Roach";"Larva";222;2
"Unit";"Roach";"Larva";222;2
"Unit";"Roach";"Larva";222;2
"Unit";"Roach";"Larva";222;2
"Unit";"Zergling";"Larva";222;1
"Unit";"Zergling";"Larva";222;1
"Unit";"Zergling";"Larva";222;1
"Unit";"Zergling";"Larva";222;1
"Unit";"Zergling";"Larva";222;1
"Unit";"Zergling";"Larva";222;1
"Unit";"Zergling";"Larva";222;1
"Unit";"Zergling";"Larva";222;1
"Unit";"Zergling";"Larva";222;1
"Unit";"Zergling";"Larva";222;1
"Unit";"Hydralisk";"Larva";256;2
"Unit";"Hydralisk";"Larva";256;2
"Unit";"Hydralisk";"Larva";256;2
"Unit";"Hydralisk";"Larva";256;2
"Unit";"Zergling";"Larva";266;1
"Unit";"Zergling";"Larva";266;1
"Unit";"Zergling";"Larva";266;1
"Unit";"Zergling";"Larva";266;1
"Unit";"Zergling";"Larva";266;1
"Unit";"Zergling";"Larva";266;1
"Unit";"Zergling";"Larva";266;1
"Unit";"Zergling";"Larva";266;1
"Unit";"Zergling";"Larva";266;1
"Unit";"Zergling";"Larva";266;1
"Unit";"Zergling";"Larva";266;1
"Unit";"Zergling";"Larva";266;1
"Unit";"Zergling";"Larva";266;1
"Unit";"Zergling";"Larva";266;1
"Unit";"Zergling";"Larva";266;1
"Unit";"Zergling";"Larva";266;1
"Unit";"Zergling";"Larva";266;1
"Unit";"Zergling";"Larva";266;1
"Unit";"Hydralisk";"Larva";266;2
"Unit";"Hydralisk";"Larva";266;2
"Unit";"Hydralisk";"Larva";266;2
"Unit";"Hydralisk";"Larva";266;2
"Unit";"Hydralisk";"Larva";300;2
"Unit";"Hydralisk";"Larva";300;2
"Unit";"Hydralisk";"Larva";300;2
"Unit";"Hydralisk";"Larva";300;2
"Unit";"Zergling";"Larva";300;1
"Unit";"Zergling";"Larva";300;1
"Unit";"Zergling";"Larva";300;1
"Unit";"Zergling";"Larva";300;1
"Unit";"Zergling";"Larva";300;1
"Unit";"Zergling";"Larva";300;1
"Unit";"Zergling";"Larva";300;1
"Unit";"Zergling";"Larva";300;1
"Unit";"Zergling";"Larva";300;1
"Unit";"Zergling";"Larva";300;1
"Unit";"Zergling";"Larva";300;1
"Unit";"Zergling";"Larva";300;1
"Unit";"Zergling";"Larva";300;1
"Unit";"Zergling";"Larva";300;1
"Unit";"Zergling";"Larva";300;1
"Unit";"Zergling";"Larva";300;1
"Unit";"Zergling";"Larva";300;1
"Unit";"Zergling";"Larva";300;1
"Unit";"Zergling";"Larva";300;1
"Unit";"Zergling";"Larva";300;1
"Unit";"Zergling";"Larva";300;1
"Unit";"Zergling";"Larva";300;1
"Unit";"Zergling";"Larva";300;1
"Unit";"Zergling";"Larva";300;1
"Unit";"Zergling";"Larva";300;1
"Unit";"Zergling";"Larva";300;1
"Unit";"Zergling";"Larva";300;1
"Unit";"Zergling";"Larva";300;1
"Unit";"Zergling";"Larva";300;1
"Unit";"Zergling";"Larva";300;1
"Unit";"Zergling";"Larva";300;1
"Unit";"Zergling";"Larva";300;1
"Unit";"Zergling";"Larva";300;1
"Unit";"Zergling";"Larva";300;1
"Unit";"Zergling";"Larva";300;1
"Unit";"Zergling";"Larva";300;1
"Upgrade";"ZergMissileWeaponsLevel2";"EvolutionChamber";222;0
