"type";"unit_name";"on_building";"total_supply";"supply"
"Unit";"Overlord";"Larva";12;0
"Building";"Extractor";NA;18;0
"Unit";"Overlord";"Larva";22;0
"Building";"SpawningPool";NA;19;0
"Building";"Hatchery";NA;17;0
"Unit";"Zergling";"Larva";22;1
"Unit";"Zergling";"Larva";22;1
"Unit";"Zergling";"Larva";23;1
"Unit";"Zergling";"Larva";23;1
"Unit";"Queen";"Hatchery";22;2
"Unit";"Queen";"Hatchery";23;2
"Unit";"Overlord";"Larva";29;0
"Building";"CreepTumorQueen";NA;34;0
"Unit";"Queen";"Hatchery";31;2
"Unit";"Zergling";"Larva";35;1
"Unit";"Zergling";"Larva";35;1
"Unit";"Zergling";"Larva";36;1
"Unit";"Zergling";"Larva";36;1
"Unit";"Zergling";"Larva";37;1
"Unit";"Zergling";"Larva";37;1
"Unit";"Zergling";"Larva";37;1
"Unit";"Zergling";"Larva";37;1
"Building";"CreepTumorQueen";NA;41;0
"Building";"CreepTumor";NA;41;0
"Unit";"Overlord";"Larva";39;0
"Building";"CreepTumorQueen";NA;54;0
"Building";"CreepTumor";NA;54;0
"Building";"Hatchery";NA;35;0
"Building";"EvolutionChamber";NA;54;0
"Unit";"Overlord";"Larva";56;0
"Unit";"Overlord";"Larva";56;0
"Building";"SporeCrawler";NA;63;0
"Building";"SporeCrawler";NA;63;0
"Building";"CreepTumor";NA;68;0
"Building";"CreepTumor";NA;68;0
"Building";"CreepTumor";NA;68;0
"Building";"Extractor";NA;67;0
"Building";"Extractor";NA;67;0
"Unit";"Overlord";"Larva";75;0
"Building";"CreepTumor";NA;82;0
"Unit";"Zergling";"Larva";81;1
"Unit";"Zergling";"Larva";81;1
"Unit";"Zergling";"Larva";81;1
"Unit";"Zergling";"Larva";81;1
"Unit";"Zergling";"Larva";81;1
"Unit";"Zergling";"Larva";81;1
"Unit";"Zergling";"Larva";81;1
"Unit";"Zergling";"Larva";81;1
"Unit";"Zergling";"Larva";81;1
"Unit";"Zergling";"Larva";81;1
"Building";"CreepTumor";NA;82;0
"Building";"CreepTumor";NA;82;0
"Unit";"Overlord";"Larva";81;0
"Unit";"Overlord";"Larva";81;0
"Building";"RoachWarren";NA;78;0
"Building";"Extractor";NA;96;0
"Building";"Extractor";NA;96;0
"Building";"CreepTumor";NA;101;0
"Building";"CreepTumor";NA;101;0
"Building";"CreepTumor";NA;101;0
"Building";"Extractor";NA;96;0
"Unit";"Overlord";"Larva";106;0
"Unit";"Overlord";"Larva";107;0
"Unit";"Overlord";"Larva";107;0
"Unit";"Overlord";"Larva";107;0
"Upgrade";"ZergMissileWeaponsLevel1";"EvolutionChamber";78;0
"Unit";"Roach";"Larva";110;2
"Unit";"Roach";"Larva";110;2
"Unit";"Roach";"Larva";110;2
"Unit";"Zergling";"Larva";110;1
"Unit";"Zergling";"Larva";110;1
"Unit";"Zergling";"Larva";110;1
"Unit";"Zergling";"Larva";110;1
"Unit";"Zergling";"Larva";110;1
"Unit";"Zergling";"Larva";110;1
"Unit";"Zergling";"Larva";110;1
"Unit";"Zergling";"Larva";110;1
"Unit";"Zergling";"Larva";110;1
"Unit";"Zergling";"Larva";110;1
"Unit";"Roach";"Larva";110;2
"Unit";"Roach";"Larva";110;2
"Unit";"Roach";"Larva";110;2
"Unit";"Roach";"Larva";110;2
"Unit";"Roach";"Larva";110;2
"Unit";"Roach";"Larva";110;2
"Building";"CreepTumor";NA;110;0
"Building";"CreepTumor";NA;110;0
"Building";"CreepTumor";NA;110;0
"Unit";"Overlord";"Larva";110;0
"Unit";"Overlord";"Larva";110;0
"Unit";"Roach";"Larva";116;2
"Building";"Spire";NA;110;0
"Building";"CreepTumor";NA;140;0
"Building";"CreepTumor";NA;142;0
"Building";"CreepTumor";NA;142;0
"Unit";"Queen";"Hatchery";138;2
"Unit";"Queen";"Hatchery";138;2
"Unit";"Overlord";"Larva";142;0
"Unit";"Overlord";"Larva";142;0
"Upgrade";"GlialReconstitution";"RoachWarren";126;0
"Unit";"Queen";"Hatchery";140;2
"Unit";"Mutalisk";"Larva";142;2
"Unit";"Mutalisk";"Larva";142;2
"Unit";"Mutalisk";"Larva";142;2
"Unit";"Mutalisk";"Larva";142;2
"Unit";"Mutalisk";"Larva";142;2
"Unit";"Mutalisk";"Larva";142;2
"Unit";"Mutalisk";"Larva";142;2
"Unit";"Mutalisk";"Larva";142;2
"Unit";"Mutalisk";"Larva";142;2
"Unit";"Overlord";"Larva";144;0
"Unit";"Overlord";"Larva";144;0
"Unit";"Overlord";"Larva";144;0
"Building";"CreepTumorQueen";NA;146;0
"Building";"Extractor";NA;146;0
"Building";"Hatchery";NA;126;0
"Building";"Extractor";NA;146;0
"Building";"CreepTumor";NA;166;0
"Building";"CreepTumor";NA;170;0
"Unit";"Zergling";"Larva";172;1
"Unit";"Zergling";"Larva";172;1
"Unit";"Zergling";"Larva";172;1
"Unit";"Zergling";"Larva";172;1
"Unit";"Zergling";"Larva";172;1
"Unit";"Zergling";"Larva";172;1
"Unit";"Zergling";"Larva";172;1
"Unit";"Zergling";"Larva";172;1
"Unit";"Zergling";"Larva";172;1
"Unit";"Zergling";"Larva";172;1
"Building";"HydraliskDen";NA;146;0
"Building";"EvolutionChamber";NA;166;0
"Unit";"Zergling";"Larva";172;1
"Unit";"Zergling";"Larva";172;1
"Building";"CreepTumorQueen";NA;172;0
"Unit";"Zergling";"Larva";172;1
"Unit";"Zergling";"Larva";172;1
"Unit";"Zergling";"Larva";172;1
"Unit";"Zergling";"Larva";172;1
"Unit";"Zergling";"Larva";172;1
"Unit";"Zergling";"Larva";172;1
"Unit";"Zergling";"Larva";172;1
"Unit";"Zergling";"Larva";172;1
"Unit";"Zergling";"Larva";172;1
"Unit";"Zergling";"Larva";172;1
"Unit";"Zergling";"Larva";172;1
"Unit";"Zergling";"Larva";172;1
"Unit";"Zergling";"Larva";172;1
"Unit";"Zergling";"Larva";172;1
"Unit";"Zergling";"Larva";172;1
"Unit";"Zergling";"Larva";172;1
"Unit";"Zergling";"Larva";172;1
"Unit";"Zergling";"Larva";172;1
"Unit";"Zergling";"Larva";172;1
"Unit";"Zergling";"Larva";172;1
"Unit";"Zergling";"Larva";172;1
"Unit";"Zergling";"Larva";172;1
"Unit";"Mutalisk";"Larva";184;2
"Unit";"Mutalisk";"Larva";186;2
"Unit";"Mutalisk";"Larva";186;2
"Unit";"Mutalisk";"Larva";188;2
"Unit";"Mutalisk";"Larva";188;2
"Unit";"Mutalisk";"Larva";190;2
"Building";"BanelingNest";NA;172;0
"Upgrade";"ZergMeleeWeaponsLevel1";"EvolutionChamber";146;0
"Unit";"Queen";"Hatchery";206;2
"Building";"CreepTumor";NA;218;0
"Unit";"Mutalisk";"Larva";218;2
"Unit";"Mutalisk";"Larva";218;2
"Unit";"Mutalisk";"Larva";218;2
"Unit";"Mutalisk";"Larva";218;2
"Unit";"Mutalisk";"Larva";218;2
"Unit";"Mutalisk";"Larva";218;2
"Unit";"Mutalisk";"Larva";218;2
"Unit";"Mutalisk";"Larva";218;2
"Unit";"Zergling";"Larva";218;1
"Unit";"Zergling";"Larva";218;1
"Unit";"Zergling";"Larva";218;1
"Unit";"Zergling";"Larva";218;1
"Unit";"Zergling";"Larva";218;1
"Unit";"Zergling";"Larva";218;1
"Unit";"Zergling";"Larva";218;1
"Unit";"Zergling";"Larva";218;1
"Unit";"Zergling";"Larva";218;1
"Unit";"Zergling";"Larva";218;1
"Unit";"Zergling";"Larva";220;1
"Unit";"Zergling";"Larva";220;1
"Unit";"Zergling";"Larva";220;1
"Unit";"Zergling";"Larva";220;1
"Unit";"Zergling";"Larva";220;1
"Unit";"Zergling";"Larva";220;1
"Unit";"Zergling";"Larva";220;1
"Unit";"Zergling";"Larva";220;1
"Unit";"Zergling";"Larva";220;1
"Unit";"Zergling";"Larva";220;1
"Unit";"Zergling";"Larva";220;1
"Unit";"Zergling";"Larva";220;1
"Unit";"Zergling";"Larva";220;1
"Unit";"Zergling";"Larva";220;1
"Unit";"Zergling";"Larva";220;1
"Unit";"Zergling";"Larva";220;1
"Unit";"Zergling";"Larva";220;1
"Unit";"Zergling";"Larva";220;1
"Unit";"Overlord";"Larva";220;0
"Unit";"Overlord";"Larva";220;0
"Unit";"Overlord";"Larva";220;0
"Unit";"Baneling";"Zergling";264;0
"Unit";"Baneling";"Zergling";264;0
"Unit";"Baneling";"Zergling";264;0
"Unit";"Baneling";"Zergling";264;0
"Unit";"Baneling";"Zergling";264;0
"Unit";"Baneling";"Zergling";264;0
"Unit";"Baneling";"Zergling";264;0
"Unit";"Baneling";"Zergling";264;0
"Unit";"Baneling";"Zergling";264;0
"Unit";"Baneling";"Zergling";264;0
"Unit";"Baneling";"Zergling";264;0
"Unit";"Baneling";"Zergling";264;0
"Unit";"Baneling";"Zergling";264;0
"Unit";"Baneling";"Zergling";264;0
"Unit";"Baneling";"Zergling";264;0
"Unit";"Baneling";"Zergling";264;0
"Unit";"Baneling";"Zergling";264;0
"Unit";"Baneling";"Zergling";264;0
"Unit";"Baneling";"Zergling";264;0
"Unit";"Baneling";"Zergling";264;0
"Unit";"Baneling";"Zergling";264;0
"Unit";"Baneling";"Zergling";264;0
"Unit";"Baneling";"Zergling";264;0
"Unit";"Baneling";"Zergling";264;0
"Building";"SpineCrawler";NA;264;0
"Unit";"Zergling";"Larva";264;1
"Unit";"Zergling";"Larva";264;1
"Unit";"Zergling";"Larva";264;1
"Unit";"Zergling";"Larva";264;1
"Unit";"Zergling";"Larva";264;1
"Unit";"Zergling";"Larva";264;1
"Unit";"Zergling";"Larva";264;1
"Unit";"Zergling";"Larva";264;1
"Unit";"Zergling";"Larva";264;1
"Unit";"Zergling";"Larva";264;1
"Unit";"Zergling";"Larva";264;1
"Unit";"Zergling";"Larva";264;1
"Unit";"Zergling";"Larva";264;1
"Unit";"Zergling";"Larva";264;1
"Unit";"Zergling";"Larva";264;1
"Unit";"Zergling";"Larva";264;1
"Unit";"Zergling";"Larva";264;1
"Unit";"Zergling";"Larva";264;1
"Unit";"Zergling";"Larva";264;1
"Unit";"Zergling";"Larva";264;1
"Unit";"Zergling";"Larva";264;1
"Unit";"Zergling";"Larva";264;1
"Unit";"Zergling";"Larva";264;1
"Unit";"Zergling";"Larva";264;1
"Unit";"Zergling";"Larva";264;1
"Unit";"Zergling";"Larva";264;1
"Unit";"Zergling";"Larva";264;1
"Unit";"Zergling";"Larva";264;1
"Unit";"Zergling";"Larva";288;1
"Unit";"Zergling";"Larva";288;1
"Unit";"Zergling";"Larva";288;1
"Unit";"Zergling";"Larva";288;1
"Unit";"Zergling";"Larva";288;1
"Unit";"Zergling";"Larva";288;1
"Unit";"Zergling";"Larva";288;1
"Unit";"Zergling";"Larva";288;1
"Unit";"Zergling";"Larva";292;1
"Unit";"Zergling";"Larva";292;1
"Unit";"Zergling";"Larva";292;1
"Unit";"Zergling";"Larva";292;1
"Building";"Hatchery";NA;304;0
"Building";"CreepTumor";NA;304;0
"Building";"Hatchery";NA;304;0
"Building";"CreepTumor";NA;304;0
"Building";"CreepTumorQueen";NA;304;0
"Building";"Hatchery";NA;304;0
"Building";"SpawningPool";NA;310;0
"Building";"CreepTumor";NA;314;0
"Building";"CreepTumor";NA;314;0
"Building";"CreepTumor";NA;314;0
"Building";"Hatchery";NA;314;0
