"type";"unit_name";"on_building";"total_supply";"supply"
"Unit";"Overlord";"Larva";13;0
"Building";"Extractor";NA;18;0
"Unit";"Overlord";"Larva";21;0
"Building";"SpawningPool";NA;19;0
"Building";"Hatchery";NA;17;0
"Unit";"Zergling";"Larva";22;1
"Unit";"Zergling";"Larva";22;1
"Unit";"Zergling";"Larva";22;1
"Unit";"Zergling";"Larva";22;1
"Unit";"Queen";"Hatchery";22;2
"Unit";"Queen";"Hatchery";22;2
"Unit";"Overlord";"Larva";30;0
"Unit";"Queen";"Hatchery";36;2
"Building";"CreepTumorQueen";NA;42;0
"Building";"SporeCrawler";NA;47;0
"Building";"SporeCrawler";NA;47;0
"Unit";"Overlord";"Larva";47;0
"Unit";"Queen";"Hatchery";42;2
"Building";"CreepTumorQueen";NA;50;0
"Unit";"Overlord";"Larva";49;0
"Building";"CreepTumor";NA;50;0
"Building";"Hatchery";NA;38;0
"Unit";"Overlord";"Larva";58;0
"Building";"CreepTumor";NA;62;0
"Building";"CreepTumorQueen";NA;62;0
"Building";"Extractor";NA;58;0
"Unit";"Overlord";"Larva";62;0
"Building";"Extractor";NA;58;0
"Building";"RoachWarren";NA;58;0
"Building";"SporeCrawler";NA;66;0
"Unit";"Queen";"Hatchery";62;2
"Building";"CreepTumorQueen";NA;74;0
"Building";"CreepTumor";NA;74;0
"Building";"CreepTumor";NA;74;0
"Building";"CreepTumorQueen";NA;76;0
"Unit";"Overlord";"Larva";74;0
"Unit";"Overlord";"Larva";85;0
"Unit";"Overlord";"Larva";87;0
"Unit";"Overlord";"Larva";87;0
"Unit";"Overlord";"Larva";87;0
"Unit";"Overlord";"Larva";88;0
"Unit";"Roach";"Larva";88;2
"Unit";"Roach";"Larva";88;2
"Unit";"Roach";"Larva";88;2
"Unit";"Roach";"Larva";88;2
"Unit";"Roach";"Larva";88;2
"Unit";"Roach";"Larva";88;2
"Building";"CreepTumor";NA;88;0
"Building";"CreepTumor";NA;88;0
"Building";"CreepTumor";NA;88;0
"Unit";"Roach";"Larva";88;2
"Unit";"Roach";"Larva";88;2
"Unit";"Roach";"Larva";88;2
"Unit";"Roach";"Larva";88;2
"Building";"CreepTumor";NA;88;0
"Building";"CreepTumorQueen";NA;88;0
"Building";"CreepTumorQueen";NA;88;0
"Building";"Extractor";NA;88;0
"Building";"Extractor";NA;88;0
"Building";"Extractor";NA;100;0
"Unit";"Roach";"Larva";108;2
"Unit";"Roach";"Larva";108;2
"Unit";"Roach";"Larva";108;2
"Unit";"Roach";"Larva";108;2
"Building";"CreepTumorQueen";NA;116;0
"Building";"CreepTumor";NA;116;0
"Building";"CreepTumor";NA;116;0
"Building";"CreepTumorQueen";NA;116;0
"Building";"HydraliskDen";NA;100;0
"Building";"CreepTumor";NA;116;0
"Building";"CreepTumor";NA;116;0
"Building";"CreepTumor";NA;116;0
"Unit";"Roach";"Larva";116;2
"Unit";"Roach";"Larva";116;2
"Unit";"Roach";"Larva";116;2
"Unit";"Roach";"Larva";116;2
"Unit";"Roach";"Larva";116;2
"Unit";"Roach";"Larva";116;2
"Unit";"Overlord";"Larva";118;0
"Unit";"Roach";"Larva";124;2
"Unit";"Roach";"Larva";124;2
"Unit";"Roach";"Larva";136;2
"Unit";"Overlord";"Larva";136;0
"Unit";"Overlord";"Larva";136;0
"Upgrade";"GlialReconstitution";"RoachWarren";116;0
"Unit";"Roach";"Larva";142;2
"Unit";"Hydralisk";"Larva";140;2
"Unit";"Hydralisk";"Larva";140;2
"Unit";"Hydralisk";"Larva";140;2
"Unit";"Hydralisk";"Larva";140;2
"Unit";"Hydralisk";"Larva";140;2
"Unit";"Hydralisk";"Larva";140;2
"Unit";"Hydralisk";"Larva";140;2
"Unit";"Hydralisk";"Larva";140;2
"Unit";"Roach";"Larva";142;2
"Unit";"Roach";"Larva";142;2
"Unit";"Roach";"Larva";142;2
"Unit";"Roach";"Larva";142;2
"Unit";"Hydralisk";"Larva";142;2
"Unit";"Hydralisk";"Larva";142;2
"Unit";"Hydralisk";"Larva";142;2
"Unit";"Hydralisk";"Larva";142;2
"Unit";"Roach";"Larva";142;2
"Unit";"Hydralisk";"Larva";160;2
"Unit";"Hydralisk";"Larva";160;2
"Unit";"Hydralisk";"Larva";160;2
"Unit";"Roach";"Larva";160;2
"Unit";"Roach";"Larva";160;2
"Unit";"Queen";"Hatchery";142;2
"Unit";"Queen";"Hatchery";142;2
"Unit";"Queen";"Hatchery";142;2
"Building";"CreepTumor";NA;178;0
"Building";"CreepTumor";NA;178;0
"Building";"CreepTumor";NA;178;0
"Building";"CreepTumor";NA;178;0
"Unit";"Hydralisk";"Larva";176;2
"Unit";"Hydralisk";"Larva";176;2
"Unit";"Hydralisk";"Larva";176;2
"Building";"CreepTumor";NA;180;0
"Building";"CreepTumor";NA;184;0
"Building";"CreepTumor";NA;184;0
"Building";"CreepTumor";NA;207;0
"Building";"CreepTumor";NA;207;0
"Building";"CreepTumor";NA;207;0
"Building";"CreepTumorQueen";NA;207;0
"Building";"CreepTumor";NA;207;0
"Building";"CreepTumor";NA;207;0
"Building";"CreepTumor";NA;207;0
"Unit";"Overlord";"Larva";207;0
"Unit";"Overlord";"Larva";207;0
"Building";"CreepTumorQueen";NA;221;0
"Unit";"Hydralisk";"Larva";210;2
"Unit";"Roach";"Larva";221;2
"Unit";"Roach";"Larva";221;2
"Unit";"Roach";"Larva";221;2
"Unit";"Roach";"Larva";221;2
"Unit";"Roach";"Larva";221;2
"Building";"CreepTumor";NA;222;0
"Unit";"Hydralisk";"Larva";222;2
"Building";"CreepTumorQueen";NA;232;0
"Unit";"Overlord";"Larva";222;0
"Building";"Hatchery";NA;201;0
"Upgrade";"EvolveMuscularAugments";"HydraliskDen";210;0
"Building";"EvolutionChamber";NA;224;0
"Building";"EvolutionChamber";NA;224;0
"Building";"CreepTumor";NA;240;0
"Building";"CreepTumor";NA;240;0
"Building";"CreepTumor";NA;240;0
"Building";"CreepTumor";NA;241;0
"Building";"Extractor";NA;239;0
"Building";"CreepTumorQueen";NA;242;0
"Building";"CreepTumor";NA;241;0
"Building";"Extractor";NA;239;0
"Unit";"Hydralisk";"Larva";241;2
"Unit";"Hydralisk";"Larva";241;2
"Unit";"Roach";"Larva";251;2
"Unit";"Roach";"Larva";251;2
"Unit";"Roach";"Larva";251;2
"Unit";"Roach";"Larva";251;2
"Unit";"Roach";"Larva";251;2
"Unit";"Overlord";"Larva";251;0
"Unit";"Overlord";"Larva";251;0
"Unit";"Hydralisk";"Larva";255;2
"Unit";"Hydralisk";"Larva";255;2
"Unit";"Hydralisk";"Larva";255;2
"Unit";"Hydralisk";"Larva";255;2
"Unit";"Roach";"Larva";265;2
"Unit";"Roach";"Larva";265;2
"Unit";"Roach";"Larva";265;2
"Unit";"Roach";"Larva";265;2
"Unit";"Roach";"Larva";265;2
"Unit";"Roach";"Larva";265;2
"Unit";"Roach";"Larva";265;2
"Unit";"Roach";"Larva";265;2
"Unit";"Roach";"Larva";273;2
"Unit";"Roach";"Larva";273;2
"Unit";"Roach";"Larva";273;2
"Unit";"Roach";"Larva";273;2
"Unit";"Roach";"Larva";273;2
"Unit";"Roach";"Larva";273;2
"Unit";"Roach";"Larva";273;2
"Unit";"Roach";"Larva";273;2
"Unit";"Roach";"Larva";273;2
"Upgrade";"EvolveGroovedSpines";"HydraliskDen";251;0
"Building";"LurkerDenMP";NA;234;0
"Unit";"Hydralisk";"Larva";289;2
"Unit";"Hydralisk";"Larva";289;2
"Unit";"Hydralisk";"Larva";289;2
"Unit";"Hydralisk";"Larva";307;2
"Unit";"Hydralisk";"Larva";307;2
"Unit";"Hydralisk";"Larva";307;2
"Unit";"Roach";"Larva";307;2
"Unit";"Roach";"Larva";307;2
"Unit";"Roach";"Larva";307;2
"Unit";"Roach";"Larva";307;2
"Unit";"Roach";"Larva";307;2
"Unit";"Roach";"Larva";307;2
"Unit";"Roach";"Larva";307;2
"Unit";"Roach";"Larva";307;2
"Building";"SpineCrawler";NA;335;0
"Building";"SpineCrawler";NA;335;0
"Building";"SpineCrawler";NA;335;0
"Upgrade";"ZergMissileWeaponsLevel1";"EvolutionChamber";307;0
"Upgrade";"ZergGroundArmorsLevel1";"EvolutionChamber";307;0
"Unit";"Hydralisk";"Larva";343;2
"Unit";"Hydralisk";"Larva";343;2
"Unit";"Hydralisk";"Larva";343;2
"Unit";"Hydralisk";"Larva";343;2
"Unit";"Hydralisk";"Larva";343;2
"Unit";"Hydralisk";"Larva";343;2
"Unit";"Hydralisk";"Larva";343;2
"Unit";"Hydralisk";"Larva";343;2
"Unit";"Hydralisk";"Larva";343;2
"Unit";"Hydralisk";"Larva";343;2
"Unit";"Hydralisk";"Larva";343;2
"Building";"Hatchery";NA;333;0
"Unit";"Hydralisk";"Larva";343;2
"Building";"Hatchery";NA;335;0
"Unit";"Roach";"Larva";369;2
"Unit";"Roach";"Larva";369;2
"Unit";"Roach";"Larva";369;2
"Building";"CreepTumorQueen";NA;370;0
"Unit";"Roach";"Larva";369;2
"Unit";"Roach";"Larva";369;2
"Unit";"Roach";"Larva";370;2
"Unit";"Roach";"Larva";370;2
"Building";"CreepTumorQueen";NA;370;0
"Building";"CreepTumor";NA;370;0
"Building";"CreepTumor";NA;370;0
"Building";"CreepTumor";NA;370;0
"Building";"CreepTumor";NA;370;0
"Building";"CreepTumor";NA;370;0
"Building";"CreepTumorQueen";NA;370;0
"Building";"CreepTumorQueen";NA;370;0
"Building";"CreepTumorQueen";NA;370;0
"Building";"LurkerDenMP";NA;343;0
"Building";"CreepTumorQueen";NA;384;0
"Unit";"Roach";"Larva";374;2
"Unit";"Roach";"Larva";378;2
"Unit";"Roach";"Larva";380;2
"Unit";"Roach";"Larva";382;2
"Unit";"Roach";"Larva";384;2
"Unit";"Roach";"Larva";384;2
"Unit";"Hydralisk";"Larva";384;2
"Unit";"Hydralisk";"Larva";384;2
"Unit";"Hydralisk";"Larva";384;2
"Unit";"Hydralisk";"Larva";384;2
"Unit";"Hydralisk";"Larva";396;2
"Unit";"Hydralisk";"Larva";396;2
"Unit";"Hydralisk";"Larva";396;2
"Unit";"Hydralisk";"Larva";396;2
"Unit";"Hydralisk";"Larva";396;2
"Unit";"Hydralisk";"Larva";396;2
"Building";"CreepTumorQueen";NA;404;0
"Unit";"Overlord";"Larva";406;0
"Unit";"Overlord";"Larva";406;0
"Unit";"Overlord";"Larva";406;0
"Unit";"Overlord";"Larva";406;0
"Building";"Extractor";NA;416;0
"Unit";"Overlord";"Larva";416;0
"Unit";"Overlord";"Larva";416;0
"Unit";"Overlord";"Larva";416;0
"Unit";"Overlord";"Larva";416;0
