"type";"unit_name";"on_building";"total_supply";"supply"
"Unit";"Overlord";"Larva";13;0
"Building";"Extractor";NA;18;0
"Building";"Hatchery";NA;14;0
"Building";"SpawningPool";NA;19;0
"Unit";"Overlord";"Larva";21;0
"Unit";"Zergling";"Larva";22;1
"Unit";"Zergling";"Larva";22;1
"Unit";"Zergling";"Larva";22;1
"Unit";"Zergling";"Larva";22;1
"Unit";"Queen";"Hatchery";22;2
"Unit";"Queen";"Hatchery";22;2
"Unit";"Overlord";"Larva";35;0
"Unit";"Zergling";"Larva";35;1
"Unit";"Zergling";"Larva";35;1
"Unit";"Zergling";"Larva";35;1
"Unit";"Zergling";"Larva";35;1
"Unit";"Zergling";"Larva";37;1
"Unit";"Zergling";"Larva";37;1
"Unit";"Queen";"Hatchery";35;2
"Unit";"Overlord";"Larva";37;0
"Building";"CreepTumorQueen";NA;45;0
"Building";"SporeCrawler";NA;43;0
"Unit";"Overlord";"Larva";45;0
"Unit";"Overlord";"Larva";45;0
"Building";"Hatchery";NA;35;0
"Building";"CreepTumorQueen";NA;50;0
"Building";"CreepTumor";NA;51;0
"Unit";"Queen";"Hatchery";49;2
"Unit";"Overlord";"Larva";55;0
"Building";"SporeCrawler";NA;55;0
"Building";"CreepTumor";NA;63;0
"Building";"CreepTumor";NA;63;0
"Building";"SporeCrawler";NA;63;0
"Building";"CreepTumorQueen";NA;70;0
"Building";"Extractor";NA;64;0
"Building";"Extractor";NA;65;0
"Unit";"Overlord";"Larva";73;0
"Unit";"Zergling";"Larva";73;1
"Unit";"Zergling";"Larva";73;1
"Unit";"Zergling";"Larva";76;1
"Unit";"Zergling";"Larva";76;1
"Unit";"Zergling";"Larva";76;1
"Unit";"Zergling";"Larva";76;1
"Unit";"Overlord";"Larva";77;0
"Unit";"Zergling";"Larva";77;1
"Unit";"Zergling";"Larva";77;1
"Unit";"Zergling";"Larva";77;1
"Unit";"Zergling";"Larva";77;1
"Unit";"Zergling";"Larva";77;1
"Unit";"Zergling";"Larva";77;1
"Unit";"Zergling";"Larva";77;1
"Unit";"Zergling";"Larva";77;1
"Unit";"Zergling";"Larva";77;1
"Unit";"Zergling";"Larva";77;1
"Unit";"Zergling";"Larva";79;1
"Unit";"Zergling";"Larva";79;1
"Building";"CreepTumor";NA;85;0
"Building";"HydraliskDen";NA;77;0
"Unit";"Zergling";"Larva";83;1
"Unit";"Zergling";"Larva";83;1
"Unit";"Hydralisk";"Larva";97;2
"Unit";"Hydralisk";"Larva";97;2
"Unit";"Hydralisk";"Larva";97;2
"Unit";"Hydralisk";"Larva";97;2
"Unit";"Hydralisk";"Larva";97;2
"Unit";"Hydralisk";"Larva";97;2
"Unit";"Hydralisk";"Larva";97;2
"Unit";"Zergling";"Larva";97;1
"Unit";"Zergling";"Larva";97;1
"Unit";"Zergling";"Larva";97;1
"Unit";"Zergling";"Larva";97;1
"Unit";"Zergling";"Larva";97;1
"Unit";"Zergling";"Larva";97;1
"Unit";"Zergling";"Larva";97;1
"Unit";"Zergling";"Larva";97;1
"Unit";"Hydralisk";"Larva";97;2
"Unit";"Zergling";"Larva";97;1
"Unit";"Zergling";"Larva";97;1
"Unit";"Hydralisk";"Larva";97;2
"Unit";"Overlord";"Larva";97;0
"Unit";"Overlord";"Larva";97;0
"Unit";"Hydralisk";"Larva";97;2
"Building";"CreepTumor";NA;127;0
"Building";"CreepTumor";NA;134;0
"Building";"Extractor";NA;125;0
"Building";"CreepTumorQueen";NA;135;0
"Building";"EvolutionChamber";NA;125;0
"Building";"CreepTumorQueen";NA;135;0
"Building";"Extractor";NA;135;0
"Building";"Extractor";NA;135;0
"Building";"BanelingNest";NA;125;0
"Building";"CreepTumor";NA;144;0
"Building";"CreepTumor";NA;144;0
"Building";"CreepTumor";NA;144;0
"Unit";"Hydralisk";"Larva";144;2
"Unit";"Hydralisk";"Larva";144;2
"Unit";"Hydralisk";"Larva";144;2
"Unit";"Overlord";"Larva";149;0
"Unit";"Overlord";"Larva";149;0
"Unit";"Overlord";"Larva";150;0
"Building";"CreepTumor";NA;150;0
"Upgrade";"EvolveGroovedSpines";"HydraliskDen";141;0
"Unit";"Overlord";"Larva";156;0
"Unit";"Overlord";"Larva";156;0
"Building";"CreepTumor";NA;156;0
"Unit";"Hydralisk";"Larva";156;2
"Unit";"Hydralisk";"Larva";156;2
"Unit";"Hydralisk";"Larva";156;2
"Building";"CreepTumor";NA;169;0
"Building";"Hatchery";NA;143;0
"Unit";"Zergling";"Larva";165;1
"Unit";"Zergling";"Larva";165;1
"Unit";"Zergling";"Larva";165;1
"Unit";"Zergling";"Larva";165;1
"Unit";"Zergling";"Larva";165;1
"Unit";"Zergling";"Larva";165;1
"Unit";"Baneling";"Zergling";172;0
"Unit";"Baneling";"Zergling";172;0
"Unit";"Baneling";"Zergling";172;0
"Unit";"Zergling";"Larva";171;1
"Unit";"Zergling";"Larva";171;1
"Unit";"Zergling";"Larva";171;1
"Unit";"Zergling";"Larva";171;1
"Unit";"Baneling";"Zergling";172;0
"Unit";"Zergling";"Larva";171;1
"Unit";"Zergling";"Larva";171;1
"Unit";"Baneling";"Zergling";172;0
"Building";"CreepTumor";NA;174;0
"Building";"CreepTumor";NA;174;0
"Building";"CreepTumor";NA;174;0
"Unit";"Hydralisk";"Larva";171;2
"Unit";"Baneling";"Zergling";174;0
"Unit";"Baneling";"Zergling";174;0
"Unit";"Baneling";"Zergling";174;0
"Unit";"Baneling";"Zergling";174;0
"Unit";"Baneling";"Zergling";174;0
"Unit";"Zergling";"Larva";174;1
"Unit";"Zergling";"Larva";174;1
"Unit";"Zergling";"Larva";180;1
"Unit";"Zergling";"Larva";180;1
"Unit";"Zergling";"Larva";180;1
"Unit";"Zergling";"Larva";180;1
"Unit";"Zergling";"Larva";180;1
"Unit";"Zergling";"Larva";180;1
"Unit";"Zergling";"Larva";180;1
"Unit";"Zergling";"Larva";180;1
"Unit";"Zergling";"Larva";180;1
"Unit";"Zergling";"Larva";180;1
"Unit";"Hydralisk";"Larva";174;2
"Building";"CreepTumor";NA;188;0
"Unit";"Zergling";"Larva";188;1
"Unit";"Zergling";"Larva";188;1
"Unit";"Zergling";"Larva";188;1
"Unit";"Zergling";"Larva";188;1
"Building";"CreepTumor";NA;192;0
"Unit";"Zergling";"Larva";191;1
"Unit";"Zergling";"Larva";191;1
"Unit";"Zergling";"Larva";191;1
"Unit";"Zergling";"Larva";191;1
"Unit";"Zergling";"Larva";191;1
"Unit";"Zergling";"Larva";191;1
"Unit";"Zergling";"Larva";191;1
"Unit";"Zergling";"Larva";191;1
"Unit";"Zergling";"Larva";191;1
"Unit";"Zergling";"Larva";191;1
"Unit";"Zergling";"Larva";191;1
"Unit";"Zergling";"Larva";191;1
"Unit";"Zergling";"Larva";191;1
"Unit";"Zergling";"Larva";191;1
"Upgrade";"ZergMissileWeaponsLevel1";"EvolutionChamber";150;0
"Unit";"Overlord";"Larva";204;0
"Upgrade";"EvolveMuscularAugments";"HydraliskDen";174;0
"Unit";"Zergling";"Larva";206;1
"Unit";"Zergling";"Larva";206;1
"Building";"CreepTumor";NA;210;0
"Unit";"Overlord";"Larva";206;0
"Unit";"Overlord";"Larva";206;0
"Unit";"Zergling";"Larva";210;1
"Unit";"Zergling";"Larva";210;1
"Unit";"Zergling";"Larva";210;1
"Unit";"Zergling";"Larva";210;1
"Unit";"Zergling";"Larva";210;1
"Unit";"Zergling";"Larva";210;1
"Unit";"Zergling";"Larva";210;1
"Unit";"Zergling";"Larva";210;1
"Building";"CreepTumor";NA;224;0
"Unit";"Zergling";"Larva";210;1
"Unit";"Zergling";"Larva";210;1
"Unit";"Zergling";"Larva";224;1
"Unit";"Zergling";"Larva";224;1
"Unit";"Zergling";"Larva";224;1
"Unit";"Zergling";"Larva";224;1
"Unit";"Zergling";"Larva";224;1
"Unit";"Zergling";"Larva";224;1
"Unit";"Baneling";"Zergling";226;0
"Unit";"Baneling";"Zergling";226;0
"Unit";"Baneling";"Zergling";226;0
"Unit";"Baneling";"Zergling";226;0
"Unit";"Baneling";"Zergling";226;0
"Unit";"Baneling";"Zergling";226;0
"Unit";"Baneling";"Zergling";226;0
"Unit";"Baneling";"Zergling";226;0
"Building";"CreepTumor";NA;236;0
"Building";"CreepTumor";NA;236;0
"Unit";"Zergling";"Larva";228;1
"Unit";"Zergling";"Larva";228;1
"Unit";"Zergling";"Larva";232;1
"Unit";"Zergling";"Larva";232;1
"Unit";"Zergling";"Larva";234;1
"Unit";"Zergling";"Larva";234;1
"Building";"Hatchery";NA;178;0
"Unit";"Zergling";"Larva";236;1
"Unit";"Zergling";"Larva";236;1
"Unit";"Zergling";"Larva";236;1
"Unit";"Zergling";"Larva";236;1
"Unit";"Zergling";"Larva";236;1
"Unit";"Zergling";"Larva";236;1
"Unit";"Hydralisk";"Larva";226;2
"Unit";"Hydralisk";"Larva";226;2
"Unit";"Hydralisk";"Larva";226;2
"Unit";"Hydralisk";"Larva";226;2
"Unit";"Zergling";"Larva";242;1
"Unit";"Zergling";"Larva";242;1
"Unit";"Hydralisk";"Larva";242;2
"Unit";"Hydralisk";"Larva";242;2
"Unit";"Baneling";"Zergling";262;0
"Unit";"Baneling";"Zergling";262;0
"Unit";"Baneling";"Zergling";262;0
"Unit";"Baneling";"Zergling";262;0
"Unit";"Baneling";"Zergling";262;0
"Unit";"Baneling";"Zergling";262;0
"Unit";"Baneling";"Zergling";262;0
"Unit";"Baneling";"Zergling";262;0
"Unit";"Baneling";"Zergling";262;0
"Unit";"Baneling";"Zergling";262;0
"Building";"CreepTumor";NA;264;0
"Unit";"Zergling";"Larva";264;1
"Unit";"Zergling";"Larva";264;1
"Unit";"Zergling";"Larva";264;1
"Unit";"Zergling";"Larva";264;1
"Unit";"Zergling";"Larva";264;1
"Unit";"Zergling";"Larva";264;1
"Unit";"Zergling";"Larva";264;1
"Unit";"Zergling";"Larva";264;1
"Unit";"Zergling";"Larva";264;1
"Unit";"Zergling";"Larva";264;1
"Unit";"Overlord";"Larva";264;0
"Unit";"Overlord";"Larva";264;0
"Unit";"Overlord";"Larva";264;0
"Unit";"Baneling";"Zergling";268;0
"Unit";"Baneling";"Zergling";268;0
"Unit";"Baneling";"Zergling";268;0
"Unit";"Baneling";"Zergling";268;0
"Unit";"Baneling";"Zergling";268;0
"Unit";"Baneling";"Zergling";268;0
"Unit";"Baneling";"Zergling";268;0
"Unit";"Baneling";"Zergling";268;0
"Unit";"Baneling";"Zergling";268;0
"Unit";"Baneling";"Zergling";268;0
"Unit";"Baneling";"Zergling";268;0
"Unit";"Baneling";"Zergling";268;0
"Unit";"Baneling";"Zergling";268;0
"Unit";"Baneling";"Zergling";268;0
"Unit";"Overlord";"Larva";268;0
"Building";"CreepTumor";NA;268;0
"Unit";"Zergling";"Larva";268;1
"Unit";"Zergling";"Larva";268;1
"Unit";"Zergling";"Larva";268;1
"Unit";"Zergling";"Larva";268;1
"Unit";"Zergling";"Larva";268;1
"Unit";"Zergling";"Larva";268;1
"Unit";"Zergling";"Larva";268;1
"Unit";"Zergling";"Larva";268;1
"Unit";"Zergling";"Larva";268;1
"Unit";"Zergling";"Larva";268;1
"Unit";"Zergling";"Larva";268;1
"Unit";"Zergling";"Larva";268;1
"Unit";"Zergling";"Larva";268;1
"Unit";"Zergling";"Larva";268;1
"Unit";"Zergling";"Larva";268;1
"Unit";"Zergling";"Larva";268;1
"Unit";"Overlord";"Larva";268;0
"Unit";"Zergling";"Larva";278;1
"Unit";"Zergling";"Larva";278;1
"Unit";"Zergling";"Larva";278;1
"Unit";"Zergling";"Larva";278;1
"Unit";"Zergling";"Larva";278;1
"Unit";"Zergling";"Larva";278;1
"Unit";"Zergling";"Larva";278;1
"Unit";"Zergling";"Larva";278;1
"Unit";"Zergling";"Larva";278;1
"Unit";"Zergling";"Larva";278;1
"Unit";"Zergling";"Larva";278;1
"Unit";"Zergling";"Larva";278;1
"Unit";"Zergling";"Larva";278;1
"Unit";"Zergling";"Larva";278;1
"Building";"SpineCrawler";NA;268;0
"Unit";"Zergling";"Larva";309;1
"Unit";"Zergling";"Larva";309;1
"Unit";"Zergling";"Larva";309;1
"Unit";"Zergling";"Larva";309;1
"Unit";"Zergling";"Larva";309;1
"Unit";"Zergling";"Larva";309;1
"Unit";"Zergling";"Larva";309;1
"Unit";"Zergling";"Larva";309;1
"Unit";"Zergling";"Larva";309;1
"Unit";"Zergling";"Larva";309;1
"Unit";"Zergling";"Larva";309;1
"Unit";"Zergling";"Larva";309;1
"Unit";"Zergling";"Larva";309;1
"Unit";"Zergling";"Larva";309;1
"Unit";"Zergling";"Larva";309;1
"Unit";"Zergling";"Larva";309;1
"Unit";"Zergling";"Larva";309;1
"Unit";"Zergling";"Larva";309;1
"Unit";"Zergling";"Larva";309;1
"Unit";"Zergling";"Larva";309;1
"Unit";"Zergling";"Larva";309;1
"Unit";"Zergling";"Larva";309;1
"Unit";"Zergling";"Larva";309;1
"Unit";"Zergling";"Larva";309;1
"Unit";"Zergling";"Larva";309;1
"Unit";"Zergling";"Larva";309;1
"Unit";"Zergling";"Larva";309;1
"Unit";"Zergling";"Larva";309;1
"Unit";"Zergling";"Larva";309;1
"Unit";"Zergling";"Larva";309;1
"Unit";"Zergling";"Larva";309;1
"Unit";"Zergling";"Larva";309;1
"Unit";"Zergling";"Larva";309;1
"Unit";"Zergling";"Larva";309;1
"Unit";"Zergling";"Larva";309;1
"Unit";"Zergling";"Larva";309;1
"Unit";"Zergling";"Larva";309;1
"Unit";"Zergling";"Larva";309;1
"Unit";"Zergling";"Larva";309;1
"Unit";"Zergling";"Larva";309;1
"Unit";"Zergling";"Larva";309;1
"Unit";"Zergling";"Larva";309;1
"Unit";"Zergling";"Larva";309;1
"Unit";"Zergling";"Larva";309;1
"Unit";"Zergling";"Larva";309;1
"Unit";"Zergling";"Larva";309;1
"Unit";"Zergling";"Larva";309;1
"Unit";"Zergling";"Larva";309;1
"Unit";"Zergling";"Larva";309;1
"Unit";"Zergling";"Larva";309;1
"Upgrade";"ZergMeleeWeaponsLevel1";"EvolutionChamber";248;0
"Unit";"Baneling";"Zergling";345;0
"Unit";"Baneling";"Zergling";345;0
"Unit";"Baneling";"Zergling";345;0
"Unit";"Baneling";"Zergling";345;0
"Unit";"Baneling";"Zergling";345;0
"Unit";"Baneling";"Zergling";345;0
"Unit";"Baneling";"Zergling";345;0
"Unit";"Baneling";"Zergling";345;0
"Unit";"Baneling";"Zergling";345;0
"Unit";"Baneling";"Zergling";345;0
"Unit";"Baneling";"Zergling";345;0
"Unit";"Baneling";"Zergling";345;0
"Unit";"Zergling";"Larva";345;1
"Unit";"Zergling";"Larva";345;1
"Unit";"Zergling";"Larva";345;1
"Unit";"Zergling";"Larva";345;1
"Unit";"Zergling";"Larva";345;1
"Unit";"Zergling";"Larva";345;1
"Unit";"Zergling";"Larva";345;1
"Unit";"Zergling";"Larva";345;1
"Unit";"Zergling";"Larva";345;1
"Unit";"Zergling";"Larva";345;1
"Building";"SpineCrawler";NA;309;0
"Unit";"Zergling";"Larva";361;1
"Unit";"Zergling";"Larva";361;1
"Unit";"Zergling";"Larva";361;1
"Unit";"Zergling";"Larva";361;1
"Unit";"Zergling";"Larva";361;1
"Unit";"Zergling";"Larva";361;1
"Unit";"Zergling";"Larva";361;1
"Unit";"Zergling";"Larva";361;1
"Unit";"Zergling";"Larva";361;1
"Unit";"Zergling";"Larva";361;1
"Unit";"Zergling";"Larva";361;1
"Unit";"Zergling";"Larva";361;1
"Unit";"Zergling";"Larva";361;1
"Unit";"Zergling";"Larva";361;1
"Unit";"Zergling";"Larva";361;1
"Unit";"Zergling";"Larva";361;1
"Unit";"Zergling";"Larva";361;1
"Unit";"Zergling";"Larva";361;1
"Unit";"Zergling";"Larva";361;1
"Unit";"Zergling";"Larva";361;1
"Unit";"Zergling";"Larva";361;1
"Unit";"Zergling";"Larva";361;1
"Unit";"Zergling";"Larva";361;1
"Unit";"Zergling";"Larva";361;1
"Unit";"Zergling";"Larva";361;1
"Unit";"Zergling";"Larva";361;1
"Building";"CreepTumor";NA;371;0
"Building";"CreepTumor";NA;371;0
"Unit";"Baneling";"Zergling";371;0
"Unit";"Baneling";"Zergling";371;0
"Unit";"Baneling";"Zergling";371;0
"Building";"CreepTumor";NA;371;0
"Unit";"Baneling";"Zergling";371;0
"Unit";"Baneling";"Zergling";371;0
"Unit";"Baneling";"Zergling";371;0
"Unit";"Baneling";"Zergling";371;0
"Unit";"Baneling";"Zergling";371;0
"Unit";"Baneling";"Zergling";371;0
"Unit";"Baneling";"Zergling";371;0
"Unit";"Zergling";"Larva";371;1
"Unit";"Zergling";"Larva";371;1
"Unit";"Baneling";"Zergling";371;0
"Unit";"Baneling";"Zergling";371;0
"Unit";"Baneling";"Zergling";371;0
"Unit";"Baneling";"Zergling";371;0
"Unit";"Baneling";"Zergling";371;0
"Unit";"Zergling";"Larva";371;1
"Unit";"Zergling";"Larva";371;1
"Unit";"Zergling";"Larva";371;1
"Unit";"Zergling";"Larva";371;1
"Unit";"Zergling";"Larva";371;1
"Unit";"Zergling";"Larva";371;1
"Unit";"Zergling";"Larva";371;1
"Unit";"Zergling";"Larva";371;1
"Unit";"Zergling";"Larva";371;1
"Unit";"Zergling";"Larva";371;1
"Unit";"Zergling";"Larva";371;1
"Unit";"Zergling";"Larva";371;1
"Unit";"Zergling";"Larva";397;1
"Unit";"Zergling";"Larva";397;1
"Unit";"Zergling";"Larva";397;1
"Unit";"Zergling";"Larva";397;1
"Unit";"Zergling";"Larva";397;1
"Unit";"Zergling";"Larva";397;1
"Unit";"Zergling";"Larva";397;1
"Unit";"Zergling";"Larva";397;1
"Unit";"Zergling";"Larva";405;1
"Unit";"Zergling";"Larva";405;1
"Unit";"Zergling";"Larva";405;1
"Unit";"Zergling";"Larva";405;1
"Unit";"Zergling";"Larva";407;1
"Unit";"Zergling";"Larva";407;1
"Unit";"Zergling";"Larva";407;1
"Unit";"Zergling";"Larva";407;1
"Unit";"Zergling";"Larva";407;1
"Unit";"Zergling";"Larva";407;1
"Unit";"Zergling";"Larva";407;1
"Unit";"Zergling";"Larva";407;1
"Unit";"Zergling";"Larva";419;1
"Unit";"Zergling";"Larva";419;1
"Unit";"Zergling";"Larva";419;1
"Unit";"Zergling";"Larva";419;1
"Unit";"Zergling";"Larva";419;1
"Unit";"Zergling";"Larva";419;1
"Unit";"Zergling";"Larva";419;1
"Unit";"Zergling";"Larva";419;1
"Unit";"Zergling";"Larva";419;1
"Unit";"Zergling";"Larva";419;1
"Unit";"Zergling";"Larva";419;1
"Unit";"Zergling";"Larva";419;1
"Unit";"Zergling";"Larva";419;1
"Unit";"Zergling";"Larva";419;1
"Unit";"Zergling";"Larva";419;1
"Unit";"Zergling";"Larva";419;1
"Unit";"Zergling";"Larva";419;1
"Unit";"Zergling";"Larva";419;1
"Unit";"Zergling";"Larva";419;1
"Unit";"Zergling";"Larva";419;1
"Unit";"Zergling";"Larva";419;1
"Unit";"Zergling";"Larva";419;1
"Unit";"Zergling";"Larva";419;1
"Unit";"Zergling";"Larva";419;1
"Unit";"Zergling";"Larva";419;1
"Unit";"Zergling";"Larva";419;1
"Building";"CreepTumor";NA;431;0
"Unit";"Zergling";"Larva";431;1
"Unit";"Zergling";"Larva";431;1
"Unit";"Hydralisk";"Larva";431;2
"Unit";"Baneling";"Zergling";431;0
"Building";"CreepTumor";NA;457;0
"Unit";"Baneling";"Zergling";431;0
"Unit";"Baneling";"Zergling";431;0
"Unit";"Baneling";"Zergling";431;0
"Unit";"Baneling";"Zergling";431;0
"Unit";"Baneling";"Zergling";431;0
"Unit";"Baneling";"Zergling";431;0
"Unit";"Baneling";"Zergling";431;0
"Unit";"Baneling";"Zergling";431;0
"Unit";"Baneling";"Zergling";431;0
"Unit";"Baneling";"Zergling";431;0
"Unit";"Baneling";"Zergling";431;0
"Unit";"Baneling";"Zergling";431;0
"Unit";"Baneling";"Zergling";431;0
"Unit";"Baneling";"Zergling";431;0
"Unit";"Baneling";"Zergling";431;0
"Unit";"Baneling";"Zergling";433;0
"Unit";"Baneling";"Zergling";433;0
"Unit";"Baneling";"Zergling";433;0
"Building";"CreepTumor";NA;457;0
"Unit";"Hydralisk";"Larva";431;2
"Unit";"Hydralisk";"Larva";431;2
"Unit";"Hydralisk";"Larva";431;2
"Unit";"Zergling";"Larva";457;1
"Unit";"Zergling";"Larva";457;1
"Unit";"Hydralisk";"Larva";431;2
"Unit";"Zergling";"Larva";457;1
"Unit";"Zergling";"Larva";457;1
"Unit";"Zergling";"Larva";457;1
"Unit";"Zergling";"Larva";457;1
"Unit";"Zergling";"Larva";457;1
"Unit";"Zergling";"Larva";457;1
"Unit";"Zergling";"Larva";457;1
"Unit";"Zergling";"Larva";457;1
"Unit";"Zergling";"Larva";459;1
"Unit";"Zergling";"Larva";459;1
"Unit";"Baneling";"Zergling";461;0
"Unit";"Baneling";"Zergling";461;0
"Unit";"Baneling";"Zergling";461;0
"Unit";"Baneling";"Zergling";461;0
"Unit";"Baneling";"Zergling";461;0
"Unit";"Baneling";"Zergling";461;0
"Unit";"Baneling";"Zergling";461;0
"Unit";"Baneling";"Zergling";461;0
"Unit";"Zergling";"Larva";461;1
"Unit";"Zergling";"Larva";461;1
"Unit";"Zergling";"Larva";461;1
"Unit";"Zergling";"Larva";461;1
"Unit";"Zergling";"Larva";467;1
"Unit";"Zergling";"Larva";467;1
"Building";"Hatchery";NA;405;0
"Unit";"Zergling";"Larva";471;1
"Unit";"Zergling";"Larva";471;1
"Unit";"Zergling";"Larva";471;1
"Unit";"Zergling";"Larva";471;1
"Unit";"Zergling";"Larva";471;1
"Unit";"Zergling";"Larva";471;1
"Unit";"Zergling";"Larva";473;1
"Unit";"Zergling";"Larva";473;1
"Building";"CreepTumor";NA;477;0
"Unit";"Zergling";"Larva";477;1
"Unit";"Zergling";"Larva";477;1
"Unit";"Zergling";"Larva";477;1
"Unit";"Zergling";"Larva";477;1
"Unit";"Zergling";"Larva";477;1
"Unit";"Zergling";"Larva";477;1
"Unit";"Zergling";"Larva";477;1
"Unit";"Zergling";"Larva";477;1
"Unit";"Queen";"Hatchery";457;2
"Unit";"Zergling";"Larva";477;1
"Unit";"Zergling";"Larva";477;1
"Unit";"Zergling";"Larva";477;1
"Unit";"Zergling";"Larva";477;1
"Unit";"Zergling";"Larva";477;1
"Unit";"Zergling";"Larva";477;1
"Unit";"Zergling";"Larva";477;1
"Unit";"Zergling";"Larva";477;1
"Unit";"Zergling";"Larva";477;1
"Unit";"Zergling";"Larva";477;1
"Unit";"Zergling";"Larva";477;1
"Unit";"Zergling";"Larva";477;1
"Unit";"Zergling";"Larva";477;1
"Unit";"Zergling";"Larva";477;1
"Building";"CreepTumor";NA;485;0
"Unit";"Zergling";"Larva";481;1
"Unit";"Zergling";"Larva";481;1
"Unit";"Baneling";"Zergling";487;0
"Unit";"Baneling";"Zergling";487;0
"Unit";"Baneling";"Zergling";487;0
"Unit";"Baneling";"Zergling";487;0
"Unit";"Zergling";"Larva";487;1
"Unit";"Zergling";"Larva";487;1
"Unit";"Zergling";"Larva";499;1
"Unit";"Zergling";"Larva";499;1
"Unit";"Zergling";"Larva";519;1
"Unit";"Zergling";"Larva";519;1
"Unit";"Zergling";"Larva";519;1
"Unit";"Zergling";"Larva";519;1
"Unit";"Zergling";"Larva";519;1
"Unit";"Zergling";"Larva";519;1
"Unit";"Zergling";"Larva";519;1
"Unit";"Zergling";"Larva";519;1
"Unit";"Zergling";"Larva";523;1
"Unit";"Zergling";"Larva";523;1
"Unit";"Zergling";"Larva";523;1
"Unit";"Zergling";"Larva";523;1
"Unit";"Hydralisk";"Larva";523;2
"Unit";"Hydralisk";"Larva";523;2
"Unit";"Hydralisk";"Larva";523;2
"Unit";"Zergling";"Larva";523;1
"Unit";"Zergling";"Larva";523;1
"Unit";"Zergling";"Larva";523;1
"Unit";"Zergling";"Larva";523;1
"Unit";"Zergling";"Larva";523;1
"Unit";"Zergling";"Larva";523;1
"Unit";"Zergling";"Larva";523;1
"Unit";"Zergling";"Larva";523;1
"Unit";"Zergling";"Larva";523;1
"Unit";"Zergling";"Larva";523;1
"Unit";"Zergling";"Larva";523;1
"Unit";"Zergling";"Larva";523;1
"Upgrade";"ZergMissileWeaponsLevel2";"EvolutionChamber";419;0
"Unit";"Zergling";"Larva";523;1
"Unit";"Zergling";"Larva";523;1
"Unit";"Zergling";"Larva";523;1
"Unit";"Zergling";"Larva";523;1
"Unit";"Zergling";"Larva";523;1
"Unit";"Zergling";"Larva";523;1
"Unit";"Hydralisk";"Larva";523;2
"Unit";"Hydralisk";"Larva";523;2
"Unit";"Hydralisk";"Larva";523;2
"Unit";"Hydralisk";"Larva";523;2
"Unit";"Hydralisk";"Larva";523;2
"Unit";"Hydralisk";"Larva";533;2
"Unit";"Hydralisk";"Larva";533;2
"Unit";"Hydralisk";"Larva";533;2
"Unit";"Hydralisk";"Larva";533;2
"Unit";"Hydralisk";"Larva";533;2
"Unit";"Zergling";"Larva";561;1
"Unit";"Zergling";"Larva";561;1
"Unit";"Zergling";"Larva";561;1
"Unit";"Zergling";"Larva";561;1
"Unit";"Zergling";"Larva";561;1
"Unit";"Zergling";"Larva";561;1
"Unit";"Zergling";"Larva";561;1
"Unit";"Zergling";"Larva";561;1
"Unit";"Zergling";"Larva";561;1
"Unit";"Zergling";"Larva";561;1
"Building";"CreepTumor";NA;577;0
"Unit";"Hydralisk";"Larva";561;2
"Unit";"Hydralisk";"Larva";561;2
"Unit";"Hydralisk";"Larva";561;2
"Unit";"Hydralisk";"Larva";561;2
"Unit";"Hydralisk";"Larva";561;2
"Unit";"Zergling";"Larva";577;1
"Unit";"Zergling";"Larva";577;1
"Unit";"Zergling";"Larva";577;1
"Unit";"Zergling";"Larva";577;1
"Unit";"Zergling";"Larva";577;1
"Unit";"Zergling";"Larva";577;1
"Unit";"Zergling";"Larva";577;1
"Unit";"Zergling";"Larva";577;1
"Unit";"Zergling";"Larva";577;1
"Unit";"Zergling";"Larva";577;1
"Unit";"Zergling";"Larva";577;1
"Unit";"Zergling";"Larva";577;1
"Unit";"Zergling";"Larva";577;1
"Unit";"Zergling";"Larva";577;1
"Unit";"Hydralisk";"Larva";571;2
"Unit";"Hydralisk";"Larva";571;2
"Unit";"Baneling";"Zergling";581;0
"Unit";"Baneling";"Zergling";581;0
"Unit";"Baneling";"Zergling";581;0
"Unit";"Baneling";"Zergling";581;0
"Unit";"Baneling";"Zergling";581;0
"Unit";"Baneling";"Zergling";583;0
"Unit";"Baneling";"Zergling";591;0
"Unit";"Hydralisk";"Larva";581;2
"Unit";"Hydralisk";"Larva";581;2
"Unit";"Hydralisk";"Larva";581;2
"Building";"CreepTumorQueen";NA;619;0
"Unit";"Hydralisk";"Larva";601;2
"Unit";"Hydralisk";"Larva";601;2
"Unit";"Hydralisk";"Larva";603;2
"Unit";"Hydralisk";"Larva";603;2
"Unit";"Hydralisk";"Larva";615;2
"Unit";"Hydralisk";"Larva";619;2
"Unit";"Baneling";"Zergling";625;0
"Unit";"Baneling";"Zergling";625;0
"Unit";"Baneling";"Zergling";625;0
"Unit";"Baneling";"Zergling";625;0
"Unit";"Baneling";"Zergling";625;0
"Unit";"Baneling";"Zergling";625;0
"Building";"CreepTumor";NA;641;0
"Unit";"Hydralisk";"Larva";631;2
"Unit";"Hydralisk";"Larva";631;2
"Unit";"Hydralisk";"Larva";631;2
"Unit";"Hydralisk";"Larva";631;2
"Unit";"Hydralisk";"Larva";637;2
"Unit";"Hydralisk";"Larva";637;2
"Unit";"Hydralisk";"Larva";641;2
"Unit";"Hydralisk";"Larva";641;2
"Building";"CreepTumor";NA;641;0
"Unit";"Baneling";"Zergling";650;0
"Unit";"Baneling";"Zergling";650;0
"Unit";"Baneling";"Zergling";650;0
"Unit";"Baneling";"Zergling";650;0
"Unit";"Baneling";"Zergling";650;0
"Unit";"Baneling";"Zergling";650;0
"Unit";"Baneling";"Zergling";650;0
"Unit";"Baneling";"Zergling";650;0
"Unit";"Baneling";"Zergling";650;0
"Unit";"Baneling";"Zergling";650;0
"Building";"CreepTumor";NA;654;0
"Unit";"Zergling";"Larva";641;1
"Unit";"Zergling";"Larva";641;1
"Unit";"Zergling";"Larva";641;1
"Unit";"Zergling";"Larva";641;1
"Unit";"Zergling";"Larva";641;1
"Unit";"Zergling";"Larva";641;1
"Unit";"Zergling";"Larva";643;1
"Unit";"Zergling";"Larva";643;1
"Unit";"Zergling";"Larva";643;1
"Unit";"Zergling";"Larva";643;1
"Unit";"Zergling";"Larva";644;1
"Unit";"Zergling";"Larva";644;1
"Building";"CreepTumor";NA;664;0
"Building";"InfestationPit";NA;641;0
"Building";"Extractor";NA;664;0
"Building";"Extractor";NA;664;0
"Building";"CreepTumor";NA;676;0
"Building";"Hatchery";NA;625;0
"Unit";"Baneling";"Zergling";676;0
"Unit";"Baneling";"Zergling";676;0
"Unit";"Baneling";"Zergling";676;0
"Unit";"Baneling";"Zergling";676;0
"Unit";"Baneling";"Zergling";676;0
"Unit";"Baneling";"Zergling";676;0
"Unit";"Baneling";"Zergling";676;0
"Unit";"Baneling";"Zergling";676;0
"Unit";"Baneling";"Zergling";676;0
"Unit";"Baneling";"Zergling";676;0
"Unit";"Zergling";"Larva";676;1
"Unit";"Zergling";"Larva";676;1
"Unit";"Zergling";"Larva";676;1
"Unit";"Zergling";"Larva";676;1
"Unit";"Zergling";"Larva";676;1
"Unit";"Zergling";"Larva";676;1
"Unit";"Zergling";"Larva";676;1
"Unit";"Zergling";"Larva";676;1
"Unit";"Zergling";"Larva";676;1
"Unit";"Zergling";"Larva";676;1
"Unit";"Zergling";"Larva";676;1
"Unit";"Zergling";"Larva";676;1
"Unit";"Zergling";"Larva";676;1
"Unit";"Zergling";"Larva";676;1
"Unit";"Zergling";"Larva";676;1
"Unit";"Zergling";"Larva";676;1
"Unit";"Zergling";"Larva";676;1
"Unit";"Zergling";"Larva";676;1
"Unit";"Zergling";"Larva";676;1
"Unit";"Zergling";"Larva";676;1
"Unit";"Zergling";"Larva";676;1
"Unit";"Zergling";"Larva";676;1
"Unit";"Zergling";"Larva";676;1
"Unit";"Zergling";"Larva";676;1
"Unit";"Zergling";"Larva";676;1
"Unit";"Zergling";"Larva";676;1
"Unit";"Zergling";"Larva";676;1
"Unit";"Zergling";"Larva";676;1
"Unit";"Zergling";"Larva";676;1
"Unit";"Zergling";"Larva";676;1
"Unit";"Zergling";"Larva";676;1
"Unit";"Zergling";"Larva";676;1
"Unit";"Zergling";"Larva";676;1
"Unit";"Zergling";"Larva";676;1
"Unit";"Zergling";"Larva";676;1
"Unit";"Zergling";"Larva";676;1
"Unit";"Zergling";"Larva";676;1
"Unit";"Zergling";"Larva";676;1
"Unit";"Zergling";"Larva";676;1
"Unit";"Zergling";"Larva";676;1
"Unit";"Zergling";"Larva";676;1
"Unit";"Zergling";"Larva";676;1
"Unit";"Zergling";"Larva";676;1
"Unit";"Zergling";"Larva";676;1
"Building";"CreepTumor";NA;676;0
"Upgrade";"ZergMeleeWeaponsLevel2";"EvolutionChamber";625;0
"Unit";"Zergling";"Larva";676;1
"Unit";"Zergling";"Larva";676;1
"Unit";"Zergling";"Larva";676;1
"Unit";"Zergling";"Larva";676;1
"Unit";"Zergling";"Larva";676;1
"Unit";"Zergling";"Larva";676;1
"Unit";"Zergling";"Larva";676;1
"Unit";"Zergling";"Larva";676;1
"Unit";"Zergling";"Larva";676;1
"Unit";"Zergling";"Larva";676;1
"Unit";"Zergling";"Larva";676;1
"Unit";"Zergling";"Larva";676;1
"Unit";"Zergling";"Larva";676;1
"Unit";"Zergling";"Larva";676;1
"Unit";"Zergling";"Larva";676;1
"Unit";"Zergling";"Larva";676;1
"Unit";"Zergling";"Larva";676;1
"Unit";"Zergling";"Larva";676;1
"Unit";"Zergling";"Larva";676;1
"Unit";"Zergling";"Larva";676;1
"Unit";"Zergling";"Larva";676;1
"Unit";"Zergling";"Larva";676;1
"Unit";"Zergling";"Larva";676;1
"Unit";"Zergling";"Larva";676;1
"Unit";"Zergling";"Larva";676;1
"Unit";"Zergling";"Larva";676;1
"Unit";"Zergling";"Larva";676;1
"Unit";"Zergling";"Larva";676;1
"Unit";"Zergling";"Larva";676;1
"Unit";"Zergling";"Larva";676;1
"Unit";"Zergling";"Larva";676;1
"Unit";"Zergling";"Larva";676;1
"Unit";"Baneling";"Zergling";720;0
"Unit";"Baneling";"Zergling";720;0
"Unit";"Baneling";"Zergling";720;0
"Unit";"Baneling";"Zergling";720;0
"Unit";"Baneling";"Zergling";720;0
"Unit";"Baneling";"Zergling";720;0
"Unit";"Baneling";"Zergling";720;0
"Unit";"Baneling";"Zergling";720;0
"Unit";"Baneling";"Zergling";720;0
"Unit";"Baneling";"Zergling";720;0
"Unit";"Zergling";"Larva";720;1
"Unit";"Zergling";"Larva";720;1
"Unit";"Zergling";"Larva";720;1
"Unit";"Zergling";"Larva";720;1
"Unit";"Zergling";"Larva";720;1
"Unit";"Zergling";"Larva";720;1
"Unit";"Zergling";"Larva";720;1
"Unit";"Zergling";"Larva";720;1
"Unit";"Zergling";"Larva";720;1
"Unit";"Zergling";"Larva";720;1
"Unit";"Zergling";"Larva";720;1
"Unit";"Zergling";"Larva";720;1
"Unit";"Zergling";"Larva";720;1
"Unit";"Zergling";"Larva";720;1
"Unit";"Zergling";"Larva";720;1
"Unit";"Zergling";"Larva";720;1
"Unit";"Zergling";"Larva";720;1
"Unit";"Zergling";"Larva";720;1
"Unit";"Zergling";"Larva";720;1
"Unit";"Zergling";"Larva";720;1
"Unit";"Zergling";"Larva";720;1
"Unit";"Zergling";"Larva";720;1
"Unit";"Zergling";"Larva";740;1
"Unit";"Zergling";"Larva";740;1
"Unit";"Zergling";"Larva";740;1
"Unit";"Zergling";"Larva";740;1
"Unit";"Baneling";"Zergling";752;0
"Unit";"Baneling";"Zergling";752;0
"Unit";"Baneling";"Zergling";752;0
"Unit";"Baneling";"Zergling";752;0
"Unit";"Baneling";"Zergling";752;0
"Unit";"Baneling";"Zergling";752;0
"Unit";"Baneling";"Zergling";752;0
"Unit";"Baneling";"Zergling";752;0
"Unit";"Zergling";"Larva";752;1
"Unit";"Zergling";"Larva";752;1
"Unit";"Zergling";"Larva";752;1
"Unit";"Zergling";"Larva";752;1
"Unit";"Hydralisk";"Larva";752;2
"Unit";"Hydralisk";"Larva";752;2
"Unit";"Hydralisk";"Larva";752;2
"Unit";"Hydralisk";"Larva";752;2
"Unit";"Zergling";"Larva";774;1
"Unit";"Zergling";"Larva";774;1
"Unit";"Zergling";"Larva";774;1
"Unit";"Zergling";"Larva";774;1
"Building";"CreepTumor";NA;778;0
"Building";"Hatchery";NA;676;0
"Unit";"Baneling";"Zergling";778;0
"Unit";"Zergling";"Larva";778;1
"Unit";"Zergling";"Larva";778;1
"Unit";"Baneling";"Zergling";778;0
"Unit";"Zergling";"Larva";778;1
"Unit";"Zergling";"Larva";778;1
"Unit";"Baneling";"Zergling";778;0
"Unit";"Baneling";"Zergling";778;0
"Unit";"Baneling";"Zergling";778;0
"Unit";"Baneling";"Zergling";778;0
"Unit";"Baneling";"Zergling";778;0
"Unit";"Baneling";"Zergling";778;0
"Unit";"Zergling";"Larva";782;1
"Unit";"Zergling";"Larva";782;1
"Unit";"Zergling";"Larva";782;1
"Unit";"Zergling";"Larva";782;1
"Unit";"Zergling";"Larva";782;1
"Unit";"Zergling";"Larva";782;1
"Unit";"Zergling";"Larva";782;1
"Unit";"Zergling";"Larva";782;1
"Unit";"Baneling";"Zergling";799;0
"Unit";"Baneling";"Zergling";799;0
"Unit";"Baneling";"Zergling";799;0
"Unit";"Baneling";"Zergling";799;0
"Unit";"Baneling";"Zergling";799;0
"Unit";"Baneling";"Zergling";799;0
"Unit";"Baneling";"Zergling";799;0
"Unit";"Baneling";"Zergling";799;0
"Unit";"Baneling";"Zergling";799;0
"Unit";"Baneling";"Zergling";801;0
"Unit";"Baneling";"Zergling";801;0
"Unit";"Baneling";"Zergling";801;0
"Unit";"Baneling";"Zergling";801;0
"Unit";"Baneling";"Zergling";801;0
"Unit";"Zergling";"Larva";799;1
"Unit";"Zergling";"Larva";799;1
"Unit";"Zergling";"Larva";799;1
"Unit";"Zergling";"Larva";799;1
"Unit";"Zergling";"Larva";799;1
"Unit";"Zergling";"Larva";799;1
"Unit";"Baneling";"Zergling";807;0
"Unit";"Baneling";"Zergling";807;0
"Unit";"Baneling";"Zergling";807;0
"Unit";"Baneling";"Zergling";807;0
"Unit";"Baneling";"Zergling";807;0
"Unit";"Baneling";"Zergling";807;0
"Unit";"Baneling";"Zergling";807;0
"Unit";"Baneling";"Zergling";807;0
"Unit";"Baneling";"Zergling";807;0
"Unit";"Baneling";"Zergling";807;0
"Unit";"Baneling";"Zergling";807;0
"Unit";"Zergling";"Larva";807;1
"Unit";"Zergling";"Larva";807;1
"Unit";"Zergling";"Larva";807;1
"Unit";"Zergling";"Larva";807;1
"Unit";"Zergling";"Larva";807;1
"Unit";"Zergling";"Larva";807;1
"Unit";"Zergling";"Larva";807;1
"Unit";"Zergling";"Larva";807;1
"Unit";"Zergling";"Larva";807;1
"Unit";"Zergling";"Larva";807;1
"Unit";"Zergling";"Larva";807;1
"Unit";"Zergling";"Larva";807;1
"Unit";"Zergling";"Larva";807;1
"Unit";"Zergling";"Larva";807;1
"Unit";"Zergling";"Larva";807;1
"Unit";"Zergling";"Larva";807;1
"Unit";"Zergling";"Larva";807;1
"Unit";"Zergling";"Larva";807;1
"Unit";"Zergling";"Larva";807;1
"Unit";"Zergling";"Larva";807;1
"Unit";"Zergling";"Larva";807;1
"Unit";"Zergling";"Larva";807;1
"Unit";"Zergling";"Larva";807;1
"Unit";"Zergling";"Larva";807;1
"Unit";"Zergling";"Larva";807;1
"Unit";"Zergling";"Larva";807;1
"Unit";"Zergling";"Larva";807;1
"Unit";"Zergling";"Larva";807;1
"Unit";"Zergling";"Larva";807;1
"Unit";"Zergling";"Larva";807;1
"Unit";"Zergling";"Larva";807;1
"Unit";"Zergling";"Larva";807;1
"Unit";"Baneling";"Zergling";815;0
"Unit";"Baneling";"Zergling";815;0
"Unit";"Baneling";"Zergling";815;0
"Unit";"Baneling";"Zergling";815;0
"Unit";"Baneling";"Zergling";815;0
"Unit";"Baneling";"Zergling";815;0
"Unit";"Baneling";"Zergling";815;0
"Unit";"Baneling";"Zergling";815;0
"Unit";"Baneling";"Zergling";815;0
"Unit";"Baneling";"Zergling";815;0
"Building";"CreepTumor";NA;815;0
"Unit";"Zergling";"Larva";815;1
"Unit";"Zergling";"Larva";815;1
"Unit";"Zergling";"Larva";815;1
"Unit";"Zergling";"Larva";815;1
"Unit";"Zergling";"Larva";815;1
"Unit";"Zergling";"Larva";815;1
"Unit";"Zergling";"Larva";815;1
"Unit";"Zergling";"Larva";815;1
"Unit";"Zergling";"Larva";815;1
"Unit";"Zergling";"Larva";815;1
"Unit";"Zergling";"Larva";815;1
"Unit";"Zergling";"Larva";815;1
"Unit";"Zergling";"Larva";815;1
"Unit";"Zergling";"Larva";815;1
"Unit";"Zergling";"Larva";815;1
"Unit";"Zergling";"Larva";815;1
"Unit";"Zergling";"Larva";815;1
"Unit";"Zergling";"Larva";815;1
"Building";"Spire";NA;778;0
"Unit";"Zergling";"Larva";845;1
"Unit";"Zergling";"Larva";845;1
"Unit";"Zergling";"Larva";845;1
"Unit";"Zergling";"Larva";845;1
"Unit";"Zergling";"Larva";845;1
"Unit";"Zergling";"Larva";845;1
"Unit";"Zergling";"Larva";865;1
"Unit";"Zergling";"Larva";865;1
"Unit";"Zergling";"Larva";865;1
"Unit";"Zergling";"Larva";865;1
"Unit";"Zergling";"Larva";865;1
"Unit";"Zergling";"Larva";865;1
"Unit";"Zergling";"Larva";865;1
"Unit";"Zergling";"Larva";865;1
"Unit";"Hydralisk";"Larva";865;2
"Unit";"Hydralisk";"Larva";865;2
"Unit";"Hydralisk";"Larva";865;2
"Unit";"Hydralisk";"Larva";865;2
"Unit";"Hydralisk";"Larva";865;2
"Unit";"Hydralisk";"Larva";865;2
"Unit";"Hydralisk";"Larva";865;2
"Building";"CreepTumor";NA;869;0
"Unit";"Baneling";"Zergling";869;0
"Unit";"Baneling";"Zergling";869;0
"Unit";"Baneling";"Zergling";869;0
"Unit";"Baneling";"Zergling";869;0
"Unit";"Baneling";"Zergling";869;0
"Unit";"Baneling";"Zergling";869;0
"Unit";"Baneling";"Zergling";869;0
"Unit";"Baneling";"Zergling";869;0
"Unit";"Baneling";"Zergling";869;0
"Unit";"Baneling";"Zergling";869;0
"Unit";"Baneling";"Zergling";869;0
"Unit";"Baneling";"Zergling";869;0
"Unit";"Baneling";"Zergling";869;0
"Unit";"Baneling";"Zergling";869;0
"Unit";"Zergling";"Larva";869;1
"Unit";"Zergling";"Larva";869;1
"Unit";"Zergling";"Larva";869;1
"Unit";"Zergling";"Larva";869;1
"Unit";"Zergling";"Larva";869;1
"Unit";"Zergling";"Larva";869;1
"Unit";"Zergling";"Larva";869;1
"Unit";"Zergling";"Larva";869;1
"Unit";"Zergling";"Larva";869;1
"Unit";"Zergling";"Larva";869;1
"Unit";"Zergling";"Larva";869;1
"Unit";"Zergling";"Larva";869;1
"Unit";"Zergling";"Larva";869;1
"Unit";"Zergling";"Larva";869;1
"Upgrade";"ZergGroundArmorsLevel1";"EvolutionChamber";807;0
"Unit";"Zergling";"Larva";877;1
"Unit";"Zergling";"Larva";877;1
"Unit";"Zergling";"Larva";877;1
"Unit";"Zergling";"Larva";877;1
"Building";"Hatchery";NA;845;0
"Building";"CreepTumor";NA;914;0
"Unit";"Corruptor";"Larva";910;2
"Unit";"Corruptor";"Larva";910;2
"Unit";"Corruptor";"Larva";910;2
"Unit";"Corruptor";"Larva";910;2
"Building";"CreepTumor";NA;918;0
"Unit";"Corruptor";"Larva";914;2
"Unit";"Corruptor";"Larva";914;2
"Building";"CreepTumorQueen";NA;930;0
"Building";"CreepTumor";NA;930;0
"Building";"CreepTumorQueen";NA;932;0
"Building";"CreepTumorQueen";NA;932;0
"Building";"CreepTumorQueen";NA;932;0
"Building";"CreepTumor";NA;932;0
"Unit";"Corruptor";"Larva";932;2
"Unit";"Corruptor";"Larva";932;2
"Building";"Extractor";NA;932;0
"Building";"Extractor";NA;932;0
"Building";"SporeCrawler";NA;932;0
"Building";"CreepTumor";NA;942;0
"Building";"CreepTumor";NA;942;0
"Building";"CreepTumorQueen";NA;942;0
"Building";"CreepTumor";NA;942;0
"Building";"CreepTumorQueen";NA;942;0
"Building";"CreepTumorQueen";NA;942;0
"Unit";"Corruptor";"Larva";932;2
"Building";"Hatchery";NA;918;0
"Building";"SporeCrawler";NA;944;0
"Unit";"Zergling";"Larva";944;1
"Unit";"Zergling";"Larva";944;1
"Unit";"Zergling";"Larva";944;1
"Unit";"Zergling";"Larva";944;1
"Unit";"Zergling";"Larva";944;1
"Unit";"Zergling";"Larva";944;1
"Unit";"Zergling";"Larva";944;1
"Unit";"Zergling";"Larva";944;1
"Unit";"Zergling";"Larva";944;1
"Unit";"Zergling";"Larva";944;1
"Building";"SporeCrawler";NA;944;0
"Building";"SpineCrawler";NA;942;0
"Building";"SpineCrawler";NA;944;0
"Building";"SpineCrawler";NA;944;0
"Building";"SpineCrawler";NA;944;0
"Building";"Extractor";NA;944;0
"Building";"Extractor";NA;944;0
"Unit";"Corruptor";"Larva";944;2
"Building";"SpineCrawler";NA;944;0
"Building";"SpineCrawler";NA;944;0
"Unit";"Zergling";"Larva";960;1
"Unit";"Zergling";"Larva";960;1
"Unit";"Zergling";"Larva";960;1
"Unit";"Zergling";"Larva";960;1
"Unit";"Zergling";"Larva";960;1
"Unit";"Zergling";"Larva";960;1
"Unit";"Zergling";"Larva";960;1
"Unit";"Zergling";"Larva";960;1
"Unit";"Zergling";"Larva";960;1
"Unit";"Zergling";"Larva";960;1
"Unit";"Zergling";"Larva";960;1
"Unit";"Zergling";"Larva";960;1
"Unit";"Zergling";"Larva";960;1
"Unit";"Zergling";"Larva";960;1
"Unit";"Zergling";"Larva";960;1
"Unit";"Zergling";"Larva";960;1
"Unit";"Zergling";"Larva";960;1
"Unit";"Zergling";"Larva";960;1
"Unit";"Zergling";"Larva";960;1
"Unit";"Zergling";"Larva";960;1
"Unit";"Zergling";"Larva";960;1
"Unit";"Zergling";"Larva";960;1
"Unit";"Zergling";"Larva";960;1
"Unit";"Zergling";"Larva";960;1
"Unit";"Zergling";"Larva";960;1
"Unit";"Zergling";"Larva";960;1
"Unit";"Zergling";"Larva";960;1
"Unit";"Zergling";"Larva";960;1
"Unit";"Zergling";"Larva";960;1
"Unit";"Zergling";"Larva";960;1
"Unit";"Zergling";"Larva";960;1
"Unit";"Zergling";"Larva";960;1
"Unit";"Zergling";"Larva";960;1
"Unit";"Zergling";"Larva";960;1
"Unit";"Zergling";"Larva";960;1
"Unit";"Zergling";"Larva";960;1
"Unit";"Zergling";"Larva";960;1
"Unit";"Zergling";"Larva";960;1
"Unit";"Zergling";"Larva";960;1
"Unit";"Zergling";"Larva";960;1
"Unit";"Zergling";"Larva";960;1
"Unit";"Zergling";"Larva";960;1
"Unit";"Zergling";"Larva";960;1
"Unit";"Zergling";"Larva";960;1
"Building";"SpineCrawler";NA;954;0
"Building";"SpineCrawler";NA;954;0
"Unit";"Zergling";"Larva";960;1
"Unit";"Zergling";"Larva";960;1
"Unit";"Zergling";"Larva";960;1
"Unit";"Zergling";"Larva";960;1
"Unit";"Zergling";"Larva";960;1
"Unit";"Zergling";"Larva";960;1
"Unit";"Zergling";"Larva";960;1
"Unit";"Zergling";"Larva";960;1
"Unit";"Zergling";"Larva";960;1
"Unit";"Zergling";"Larva";960;1
"Unit";"Zergling";"Larva";960;1
"Unit";"Zergling";"Larva";960;1
"Unit";"Zergling";"Larva";960;1
"Unit";"Zergling";"Larva";960;1
"Unit";"Zergling";"Larva";960;1
"Unit";"Zergling";"Larva";960;1
"Unit";"Zergling";"Larva";960;1
"Unit";"Zergling";"Larva";960;1
"Unit";"Zergling";"Larva";960;1
"Unit";"Zergling";"Larva";960;1
"Unit";"Zergling";"Larva";960;1
"Unit";"Zergling";"Larva";960;1
"Unit";"Zergling";"Larva";960;1
"Unit";"Zergling";"Larva";960;1
"Unit";"Zergling";"Larva";960;1
"Unit";"Zergling";"Larva";960;1
"Unit";"Zergling";"Larva";960;1
"Unit";"Zergling";"Larva";960;1
"Unit";"Zergling";"Larva";960;1
"Unit";"Zergling";"Larva";960;1
"Unit";"Zergling";"Larva";960;1
"Unit";"Zergling";"Larva";960;1
"Upgrade";"ZergMissileWeaponsLevel3";"EvolutionChamber";936;0
"Unit";"Zergling";"Larva";960;1
"Unit";"Zergling";"Larva";960;1
"Building";"CreepTumor";NA;1004;0
"Unit";"Zergling";"Larva";960;1
"Unit";"Zergling";"Larva";960;1
"Unit";"Zergling";"Larva";960;1
"Unit";"Zergling";"Larva";960;1
"Unit";"Zergling";"Larva";960;1
"Unit";"Zergling";"Larva";960;1
"Building";"CreepTumor";NA;1004;0
"Building";"CreepTumor";NA;1004;0
"Building";"CreepTumor";NA;1004;0
"Unit";"Hydralisk";"Larva";960;2
"Unit";"Corruptor";"Larva";960;2
"Unit";"Corruptor";"Larva";960;2
"Unit";"Corruptor";"Larva";960;2
"Unit";"Corruptor";"Larva";960;2
"Unit";"Corruptor";"Larva";960;2
"Unit";"Corruptor";"Larva";960;2
"Unit";"Corruptor";"Larva";960;2
"Unit";"Corruptor";"Larva";960;2
"Unit";"Baneling";"Zergling";1004;0
"Unit";"Baneling";"Zergling";1004;0
"Unit";"Baneling";"Zergling";1004;0
"Unit";"Baneling";"Zergling";1004;0
"Unit";"Baneling";"Zergling";1004;0
"Unit";"Baneling";"Zergling";1004;0
"Unit";"Baneling";"Zergling";1004;0
"Unit";"Baneling";"Zergling";1004;0
"Unit";"Baneling";"Zergling";1004;0
"Building";"Extractor";NA;1004;0
"Unit";"Baneling";"Zergling";1004;0
"Unit";"Baneling";"Zergling";1004;0
"Unit";"Baneling";"Zergling";1004;0
"Unit";"Baneling";"Zergling";1004;0
"Unit";"Baneling";"Zergling";1004;0
"Unit";"Zergling";"Larva";1004;1
"Unit";"Zergling";"Larva";1004;1
"Unit";"Baneling";"Zergling";1036;0
"Unit";"Baneling";"Zergling";1036;0
"Unit";"Baneling";"Zergling";1036;0
"Unit";"Baneling";"Zergling";1036;0
"Unit";"Baneling";"Zergling";1044;0
"Unit";"Baneling";"Zergling";1044;0
"Unit";"Baneling";"Zergling";1046;0
"Unit";"Baneling";"Zergling";1046;0
"Unit";"Baneling";"Zergling";1046;0
"Unit";"Baneling";"Zergling";1046;0
"Unit";"Baneling";"Zergling";1062;0
"Unit";"Baneling";"Zergling";1062;0
"Unit";"Baneling";"Zergling";1062;0
"Unit";"Baneling";"Zergling";1062;0
"Unit";"Zergling";"Larva";1064;1
"Unit";"Zergling";"Larva";1064;1
"Building";"CreepTumor";NA;1064;0
"Building";"CreepTumor";NA;1064;0
"Building";"CreepTumor";NA;1066;0
"Building";"Extractor";NA;1066;0
"Building";"CreepTumor";NA;1066;0
"Unit";"Zergling";"Larva";1066;1
"Unit";"Zergling";"Larva";1066;1
"Unit";"Zergling";"Larva";1066;1
"Unit";"Zergling";"Larva";1066;1
"Unit";"Zergling";"Larva";1066;1
"Unit";"Zergling";"Larva";1066;1
"Unit";"Zergling";"Larva";1066;1
"Unit";"Zergling";"Larva";1066;1
"Unit";"Zergling";"Larva";1066;1
"Unit";"Zergling";"Larva";1066;1
"Unit";"Zergling";"Larva";1066;1
"Unit";"Zergling";"Larva";1066;1
"Unit";"Zergling";"Larva";1066;1
"Unit";"Zergling";"Larva";1066;1
"Unit";"Zergling";"Larva";1066;1
"Unit";"Zergling";"Larva";1066;1
"Unit";"Zergling";"Larva";1066;1
"Unit";"Zergling";"Larva";1066;1
"Unit";"Zergling";"Larva";1066;1
"Unit";"Zergling";"Larva";1066;1
"Unit";"Zergling";"Larva";1066;1
"Unit";"Zergling";"Larva";1066;1
"Unit";"Zergling";"Larva";1066;1
"Unit";"Zergling";"Larva";1066;1
"Unit";"Zergling";"Larva";1066;1
"Unit";"Zergling";"Larva";1066;1
"Unit";"Zergling";"Larva";1066;1
"Unit";"Zergling";"Larva";1066;1
"Unit";"Zergling";"Larva";1066;1
"Unit";"Zergling";"Larva";1066;1
"Unit";"Zergling";"Larva";1066;1
"Unit";"Zergling";"Larva";1066;1
"Unit";"Zergling";"Larva";1066;1
"Unit";"Zergling";"Larva";1066;1
"Unit";"Zergling";"Larva";1066;1
"Unit";"Zergling";"Larva";1066;1
"Unit";"Zergling";"Larva";1066;1
"Unit";"Zergling";"Larva";1066;1
"Building";"SpineCrawler";NA;1066;0
"Building";"SpineCrawler";NA;1066;0
"Building";"SpineCrawler";NA;1066;0
"Building";"SpineCrawler";NA;1066;0
"Building";"SpineCrawler";NA;1066;0
"Building";"SpineCrawler";NA;1066;0
"Building";"SpineCrawler";NA;1066;0
"Building";"SpineCrawler";NA;1066;0
"Unit";"Baneling";"Zergling";1068;0
"Unit";"Baneling";"Zergling";1076;0
"Unit";"Baneling";"Zergling";1082;0
"Unit";"Zergling";"Larva";1066;1
"Unit";"Zergling";"Larva";1066;1
"Unit";"Zergling";"Larva";1066;1
"Unit";"Zergling";"Larva";1066;1
"Unit";"Zergling";"Larva";1066;1
"Unit";"Zergling";"Larva";1066;1
"Unit";"Zergling";"Larva";1066;1
"Unit";"Zergling";"Larva";1066;1
"Unit";"Zergling";"Larva";1066;1
"Unit";"Zergling";"Larva";1066;1
"Unit";"Zergling";"Larva";1066;1
"Unit";"Zergling";"Larva";1066;1
"Unit";"Zergling";"Larva";1066;1
"Unit";"Zergling";"Larva";1066;1
"Unit";"Zergling";"Larva";1066;1
"Unit";"Zergling";"Larva";1066;1
"Unit";"Zergling";"Larva";1066;1
"Unit";"Zergling";"Larva";1066;1
"Unit";"Zergling";"Larva";1066;1
"Unit";"Zergling";"Larva";1066;1
"Unit";"Zergling";"Larva";1066;1
"Unit";"Zergling";"Larva";1066;1
"Unit";"Zergling";"Larva";1066;1
"Unit";"Zergling";"Larva";1066;1
"Unit";"Zergling";"Larva";1066;1
"Unit";"Zergling";"Larva";1066;1
"Unit";"Baneling";"Zergling";1104;0
"Unit";"Baneling";"Zergling";1106;0
