"type";"unit_name";"on_building";"total_supply_lag";"supply"
"Unit";"Overlord";"Larva";13;0
"Building";"Hatchery";NA;17;0
"Building";"Extractor";NA;19;0
"Building";"SpawningPool";NA;19;0
"Building";"Hatchery";NA;23;0
"Unit";"Zergling";"Larva";25;1
"Unit";"Zergling";"Larva";26;1
"Unit";"Queen";"Hatchery";27;2
"Unit";"Overlord";"Larva";29;0
"Unit";"Zergling";"Larva";29;1
"Unit";"Zergling";"Larva";30;1
"Unit";"Zergling";"Larva";31;1
"Unit";"Zergling";"Larva";32;1
"Unit";"Queen";"Hatchery";36;2
"Unit";"Zergling";"Larva";38;1
"Unit";"Zergling";"Larva";39;1
"Unit";"Zergling";"Larva";40;1
"Unit";"Zergling";"Larva";41;1
"Unit";"Queen";"Hatchery";44;2
"Unit";"Overlord";"Larva";47;0
"Building";"SporeCrawler";NA;57;0
"Building";"SporeCrawler";NA;57;0
"Building";"SporeCrawler";NA;57;0
"Unit";"Overlord";"Larva";61;0
"Building";"Extractor";NA;65;0
"Building";"CreepTumorQueen";NA;69;0
"Unit";"Queen";"Hatchery";69;2
"Unit";"Overlord";"Larva";71;0
"Unit";"Overlord";"Larva";71;0
"Unit";"Zergling";"Larva";71;1
"Unit";"Zergling";"Larva";72;1
"Unit";"Zergling";"Larva";73;1
"Unit";"Zergling";"Larva";74;1
"Unit";"Zergling";"Larva";75;1
"Unit";"Zergling";"Larva";76;1
"Unit";"Zergling";"Larva";77;1
"Unit";"Zergling";"Larva";78;1
"Unit";"Zergling";"Larva";79;1
"Unit";"Zergling";"Larva";80;1
"Unit";"Zergling";"Larva";81;1
"Unit";"Zergling";"Larva";82;1
"Unit";"Overlord";"Larva";83;0
"Unit";"Zergling";"Larva";83;1
"Unit";"Zergling";"Larva";84;1
"Unit";"Zergling";"Larva";85;1
"Unit";"Zergling";"Larva";86;1
"Building";"CreepTumorQueen";NA;87;0
"Building";"CreepTumor";NA;88;0
"Building";"Extractor";NA;99;0
"Building";"RoachWarren";NA;100;0
"Building";"CreepTumor";NA;102;0
"Building";"EvolutionChamber";NA;103;0
"Building";"CreepTumor";NA;103;0
"Unit";"Overlord";"Larva";103;0
"Unit";"Overlord";"Larva";103;0
"Building";"CreepTumorQueen";NA;107;0
"Unit";"Overlord";"Larva";107;0
"Unit";"Overlord";"Larva";107;0
"Building";"Spire";NA;107;0
"Building";"Extractor";NA;108;0
"Building";"Extractor";NA;108;0
"Unit";"Zergling";"Larva";108;1
"Unit";"Zergling";"Larva";109;1
"Unit";"Zergling";"Larva";110;1
"Unit";"Zergling";"Larva";111;1
"Unit";"Zergling";"Larva";112;1
"Unit";"Zergling";"Larva";113;1
"Unit";"Zergling";"Larva";114;1
"Unit";"Zergling";"Larva";115;1
"Unit";"Zergling";"Larva";116;1
"Unit";"Zergling";"Larva";117;1
"Unit";"Zergling";"Larva";118;1
"Unit";"Zergling";"Larva";119;1
"Unit";"Zergling";"Larva";120;1
"Unit";"Zergling";"Larva";121;1
"Unit";"Zergling";"Larva";122;1
"Unit";"Zergling";"Larva";123;1
"Unit";"Zergling";"Larva";124;1
"Unit";"Zergling";"Larva";125;1
"Unit";"Roach";"Larva";126;2
"Unit";"Roach";"Larva";128;2
"Unit";"Roach";"Larva";130;2
"Unit";"Roach";"Larva";132;2
"Unit";"Roach";"Larva";134;2
"Unit";"Roach";"Larva";136;2
"Unit";"Roach";"Larva";138;2
"Upgrade";"GlialReconstitution";"RoachWarren";143;0
"Unit";"Zergling";"Larva";143;1
"Unit";"Zergling";"Larva";144;1
"Unit";"Zergling";"Larva";145;1
"Unit";"Zergling";"Larva";146;1
"Building";"Extractor";NA;152;0
"Unit";"Zergling";"Larva";152;1
"Unit";"Zergling";"Larva";153;1
"Building";"CreepTumor";NA;154;0
"Unit";"Overlord";"Larva";154;0
"Unit";"Overlord";"Larva";154;0
"Building";"Hatchery";NA;154;0
"Unit";"Mutalisk";"Larva";154;2
"Unit";"Mutalisk";"Larva";156;2
"Unit";"Mutalisk";"Larva";158;2
"Unit";"Mutalisk";"Larva";160;2
"Unit";"Queen";"Hatchery";162;2
"Unit";"Mutalisk";"Larva";164;2
"Building";"CreepTumor";NA;169;0
"Unit";"Mutalisk";"Larva";169;2
"Building";"BanelingNest";NA;171;0
"Unit";"Overlord";"Larva";177;0
"Unit";"Mutalisk";"Larva";177;2
"Unit";"Mutalisk";"Larva";179;2
"Building";"Extractor";NA;181;0
"Unit";"Zergling";"Larva";187;1
"Unit";"Zergling";"Larva";188;1
"Unit";"Zergling";"Larva";189;1
"Unit";"Zergling";"Larva";190;1
"Unit";"Zergling";"Larva";191;1
"Unit";"Zergling";"Larva";192;1
"Unit";"Zergling";"Larva";193;1
"Unit";"Zergling";"Larva";194;1
"Building";"HydraliskDen";NA;195;0
"Unit";"Roach";"Larva";195;2
"Unit";"Zergling";"Larva";197;1
"Unit";"Zergling";"Larva";198;1
"Unit";"Zergling";"Larva";199;1
"Unit";"Zergling";"Larva";200;1
"Unit";"Zergling";"Larva";201;1
"Unit";"Zergling";"Larva";202;1
"Unit";"Overlord";"Larva";203;0
"Unit";"Overlord";"Larva";203;0
"Unit";"Overlord";"Larva";203;0
"Unit";"Overlord";"Larva";203;0
"Unit";"Baneling";"Zergling";205;0
"Unit";"Baneling";"Zergling";205;0
"Unit";"Baneling";"Zergling";205;0
"Unit";"Baneling";"Zergling";205;0
"Unit";"Baneling";"Zergling";205;0
"Unit";"Baneling";"Zergling";205;0
"Unit";"Baneling";"Zergling";205;0
"Unit";"Baneling";"Zergling";205;0
"Unit";"Baneling";"Zergling";205;0
"Unit";"Baneling";"Zergling";205;0
"Unit";"Baneling";"Zergling";205;0
"Unit";"Baneling";"Zergling";205;0
"Unit";"Baneling";"Zergling";205;0
"Unit";"Baneling";"Zergling";205;0
"Unit";"Baneling";"Zergling";205;0
"Unit";"Hydralisk";"Larva";205;2
"Unit";"Hydralisk";"Larva";207;2
"Unit";"Zergling";"Larva";209;1
"Unit";"Zergling";"Larva";210;1
"Unit";"Zergling";"Larva";211;1
"Unit";"Zergling";"Larva";212;1
"Unit";"Zergling";"Larva";213;1
"Unit";"Zergling";"Larva";214;1
"Unit";"Zergling";"Larva";215;1
"Unit";"Zergling";"Larva";216;1
"Unit";"Zergling";"Larva";217;1
"Unit";"Zergling";"Larva";218;1
"Unit";"Zergling";"Larva";219;1
"Unit";"Zergling";"Larva";220;1
"Unit";"Hydralisk";"Larva";221;2
"Unit";"Zergling";"Larva";223;1
"Unit";"Zergling";"Larva";224;1
"Unit";"Zergling";"Larva";225;1
"Unit";"Zergling";"Larva";226;1
"Unit";"Hydralisk";"Larva";227;2
"Unit";"Zergling";"Larva";229;1
"Unit";"Zergling";"Larva";230;1
"Unit";"Zergling";"Larva";231;1
"Unit";"Zergling";"Larva";232;1
"Unit";"Zergling";"Larva";233;1
"Unit";"Zergling";"Larva";234;1
"Unit";"Hydralisk";"Larva";235;2
"Unit";"Hydralisk";"Larva";237;2
"Unit";"Hydralisk";"Larva";239;2
"Building";"CreepTumor";NA;241;0
"Unit";"Baneling";"Zergling";241;0
"Unit";"Baneling";"Zergling";241;0
"Unit";"Baneling";"Zergling";241;0
"Unit";"Zergling";"Larva";241;1
"Unit";"Zergling";"Larva";242;1
"Building";"CreepTumorQueen";NA;243;0
"Unit";"Zergling";"Larva";243;1
"Unit";"Zergling";"Larva";244;1
"Unit";"Hydralisk";"Larva";245;2
"Unit";"Overlord";"Larva";247;0
"Unit";"Overlord";"Larva";247;0
"Unit";"Hydralisk";"Larva";247;2
"Unit";"Hydralisk";"Larva";249;2
"Unit";"Zergling";"Larva";251;1
"Unit";"Zergling";"Larva";252;1
"Unit";"Zergling";"Larva";253;1
"Unit";"Zergling";"Larva";254;1
"Unit";"Zergling";"Larva";255;1
"Unit";"Zergling";"Larva";256;1
"Unit";"Hydralisk";"Larva";257;2
"Unit";"Zergling";"Larva";259;1
"Unit";"Zergling";"Larva";260;1
"Unit";"Zergling";"Larva";261;1
"Unit";"Zergling";"Larva";262;1
"Unit";"Zergling";"Larva";263;1
"Unit";"Zergling";"Larva";264;1
"Unit";"Baneling";"Zergling";270;0
"Unit";"Baneling";"Zergling";270;0
"Unit";"Baneling";"Zergling";270;0
"Unit";"Zergling";"Larva";270;1
"Unit";"Zergling";"Larva";271;1
"Unit";"Zergling";"Larva";272;1
"Unit";"Zergling";"Larva";273;1
"Unit";"Baneling";"Zergling";274;0
"Unit";"Baneling";"Zergling";274;0
"Unit";"Baneling";"Zergling";274;0
"Unit";"Baneling";"Zergling";274;0
"Unit";"Baneling";"Zergling";274;0
"Unit";"Baneling";"Zergling";274;0
"Unit";"Baneling";"Zergling";274;0
"Unit";"Baneling";"Zergling";274;0
"Unit";"Hydralisk";"Larva";274;2
"Unit";"Hydralisk";"Larva";276;2
"Unit";"Hydralisk";"Larva";278;2
"Unit";"Zergling";"Larva";280;1
"Unit";"Zergling";"Larva";281;1
"Unit";"Zergling";"Larva";282;1
"Unit";"Zergling";"Larva";283;1
"Unit";"Zergling";"Larva";284;1
"Unit";"Zergling";"Larva";285;1
"Unit";"Zergling";"Larva";286;1
"Unit";"Zergling";"Larva";287;1
"Unit";"Zergling";"Larva";288;1
"Unit";"Zergling";"Larva";289;1
"Unit";"Hydralisk";"Larva";290;2
"Unit";"Zergling";"Larva";292;1
"Unit";"Zergling";"Larva";293;1
"Unit";"Baneling";"Zergling";294;0
"Unit";"Baneling";"Zergling";294;0
"Unit";"Baneling";"Zergling";294;0
"Unit";"Baneling";"Zergling";294;0
"Unit";"Baneling";"Zergling";294;0
"Unit";"Baneling";"Zergling";294;0
"Unit";"Baneling";"Zergling";294;0
"Unit";"Hydralisk";"Larva";294;2
"Unit";"Zergling";"Larva";296;1
"Unit";"Zergling";"Larva";297;1
"Unit";"Zergling";"Larva";298;1
"Unit";"Zergling";"Larva";299;1
"Unit";"Hydralisk";"Larva";300;2
"Unit";"Zergling";"Larva";302;1
"Unit";"Zergling";"Larva";303;1
"Unit";"Zergling";"Larva";304;1
"Unit";"Zergling";"Larva";305;1
"Unit";"Hydralisk";"Larva";306;2
"Unit";"Zergling";"Larva";308;1
"Unit";"Zergling";"Larva";309;1
"Unit";"Hydralisk";"Larva";310;2
"Unit";"Zergling";"Larva";312;1
"Unit";"Zergling";"Larva";313;1
"Unit";"Hydralisk";"Larva";314;2
"Unit";"Hydralisk";"Larva";316;2
"Unit";"Hydralisk";"Larva";318;2
"Unit";"Baneling";"Zergling";320;0
"Unit";"Baneling";"Zergling";320;0
"Unit";"Baneling";"Zergling";320;0
"Unit";"Baneling";"Zergling";320;0
"Unit";"Baneling";"Zergling";320;0
"Unit";"Baneling";"Zergling";320;0
"Unit";"Baneling";"Zergling";320;0
"Unit";"Hydralisk";"Larva";320;2
"Unit";"Baneling";"Zergling";322;0
"Unit";"Baneling";"Zergling";322;0
"Unit";"Baneling";"Zergling";322;0
"Unit";"Baneling";"Zergling";322;0
"Unit";"Hydralisk";"Larva";322;2
"Unit";"Zergling";"Larva";324;1
"Unit";"Zergling";"Larva";325;1
"Unit";"Baneling";"Zergling";326;0
"Unit";"Zergling";"Larva";326;1
"Unit";"Zergling";"Larva";327;1
"Unit";"Zergling";"Larva";328;1
"Unit";"Zergling";"Larva";329;1
"Unit";"Baneling";"Zergling";330;0
"Unit";"Baneling";"Zergling";330;0
"Unit";"Baneling";"Zergling";330;0
"Unit";"Hydralisk";"Larva";330;2
"Unit";"Zergling";"Larva";332;1
"Unit";"Zergling";"Larva";333;1
"Unit";"Zergling";"Larva";334;1
"Unit";"Zergling";"Larva";335;1
"Upgrade";"SprayZerg";NA;336;0
"Upgrade";"SprayZerg";NA;336;0
"Upgrade";"SprayZerg";NA;336;0
"Upgrade";"SprayZerg";NA;336;0
"Upgrade";"zerglingmovementspeed";NA;336;0
"Upgrade";"SprayZerg";NA;336;0
"Upgrade";"ZergMissileWeaponsLevel1";NA;336;0
"Upgrade";"SprayZerg";NA;336;0
"Upgrade";"CentrificalHooks";NA;336;0
"Upgrade";"EvolveGroovedSpines";NA;336;0
"Upgrade";"EvolveMuscularAugments";NA;336;0
