"type";"unit_name";"on_building";"total_supply_lag";"supply"
"Unit";"Overlord";"Larva";14;0
"Building";"Hatchery";NA;15;0
"Building";"Extractor";NA;19;0
"Building";"SpawningPool";NA;19;0
"Unit";"Overlord";"Larva";22;0
"Unit";"Queen";"Hatchery";23;2
"Unit";"Queen";"Hatchery";25;2
"Unit";"Zergling";"Larva";27;1
"Unit";"Zergling";"Larva";28;1
"Unit";"Zergling";"Larva";29;1
"Unit";"Zergling";"Larva";30;1
"Building";"Hatchery";NA;36;0
"Unit";"Queen";"Hatchery";36;2
"Unit";"Overlord";"Larva";40;0
"Unit";"Overlord";"Larva";41;0
"Unit";"Zergling";"Larva";41;1
"Unit";"Zergling";"Larva";42;1
"Building";"CreepTumorQueen";NA;43;0
"Unit";"Zergling";"Larva";43;1
"Unit";"Zergling";"Larva";44;1
"Unit";"Zergling";"Larva";45;1
"Unit";"Zergling";"Larva";46;1
"Building";"SporeCrawler";NA;55;0
"Unit";"Queen";"Hatchery";55;2
"Building";"SporeCrawler";NA;58;0
"Building";"CreepTumor";NA;58;0
"Building";"CreepTumorQueen";NA;62;0
"Unit";"Queen";"Hatchery";63;2
"Unit";"Overlord";"Larva";70;0
"Unit";"Overlord";"Larva";70;0
"Unit";"Overlord";"Larva";70;0
"Building";"CreepTumor";NA;70;0
"Building";"CreepTumor";NA;70;0
"Unit";"Overlord";"Larva";70;0
"Building";"CreepTumorQueen";NA;70;0
"Building";"RoachWarren";NA;70;0
"Unit";"Overlord";"Larva";70;0
"Building";"CreepTumor";NA;81;0
"Building";"CreepTumor";NA;81;0
"Building";"Extractor";NA;81;0
"Building";"Extractor";NA;81;0
"Building";"Extractor";NA;85;0
"Building";"CreepTumor";NA;86;0
"Unit";"Overlord";"Larva";90;0
"Unit";"Roach";"Larva";90;2
"Unit";"Roach";"Larva";92;2
"Unit";"Roach";"Larva";94;2
"Building";"CreepTumor";NA;96;0
"Building";"CreepTumor";NA;96;0
"Unit";"Roach";"Larva";96;2
"Unit";"Roach";"Larva";98;2
"Unit";"Overlord";"Larva";100;0
"Unit";"Overlord";"Larva";100;0
"Building";"SporeCrawler";NA;100;0
"Unit";"Roach";"Larva";100;2
"Unit";"Roach";"Larva";102;2
"Building";"CreepTumor";NA;104;0
"Unit";"Roach";"Larva";104;2
"Unit";"Roach";"Larva";106;2
"Unit";"Overlord";"Larva";108;0
"Unit";"Overlord";"Larva";108;0
"Unit";"Overlord";"Larva";108;0
"Building";"EvolutionChamber";NA;108;0
"Unit";"Overlord";"Larva";109;0
"Building";"Extractor";NA;109;0
"Building";"CreepTumor";NA;109;0
"Unit";"Roach";"Larva";109;2
"Unit";"Roach";"Larva";111;2
"Unit";"Roach";"Larva";113;2
"Building";"CreepTumorQueen";NA;115;0
"Building";"CreepTumor";NA;118;0
"Unit";"Roach";"Larva";118;2
"Building";"CreepTumor";NA;120;0
"Unit";"Roach";"Larva";122;2
"Unit";"Roach";"Larva";124;2
"Building";"BanelingNest";NA;131;0
"Building";"Extractor";NA;131;0
"Upgrade";"GlialReconstitution";"RoachWarren";131;0
"Building";"CreepTumor";NA;134;0
"Building";"CreepTumor";NA;134;0
"Building";"CreepTumor";NA;136;0
"Building";"CreepTumor";NA;136;0
"Unit";"Roach";"Larva";136;2
"Unit";"Roach";"Larva";138;2
"Unit";"Roach";"Larva";140;2
"Unit";"Roach";"Larva";142;2
"Building";"Hatchery";NA;144;0
"Unit";"Roach";"Larva";144;2
"Unit";"Roach";"Larva";146;2
"Unit";"Overlord";"Larva";148;0
"Unit";"Overlord";"Larva";148;0
"Unit";"Zergling";"Larva";148;1
"Unit";"Zergling";"Larva";149;1
"Unit";"Overlord";"Larva";150;0
"Unit";"Overlord";"Larva";150;0
"Building";"CreepTumorQueen";NA;150;0
"Unit";"Overlord";"Larva";150;0
"Building";"CreepTumor";NA;150;0
"Building";"CreepTumor";NA;150;0
"Unit";"Overlord";"Larva";150;0
"Building";"CreepTumor";NA;159;0
"Building";"Hatchery";NA;159;0
"Unit";"Zergling";"Larva";159;1
"Unit";"Zergling";"Larva";160;1
"Unit";"Zergling";"Larva";161;1
"Unit";"Zergling";"Larva";162;1
"Unit";"Zergling";"Larva";163;1
"Unit";"Zergling";"Larva";164;1
"Unit";"Zergling";"Larva";165;1
"Unit";"Zergling";"Larva";166;1
"Unit";"Zergling";"Larva";167;1
"Unit";"Zergling";"Larva";168;1
"Unit";"Zergling";"Larva";169;1
"Unit";"Zergling";"Larva";170;1
"Unit";"Overlord";"Larva";171;0
"Unit";"Overlord";"Larva";171;0
"Unit";"Zergling";"Larva";171;1
"Unit";"Zergling";"Larva";172;1
"Unit";"Zergling";"Larva";173;1
"Unit";"Zergling";"Larva";174;1
"Unit";"Zergling";"Larva";175;1
"Unit";"Zergling";"Larva";176;1
"Unit";"Zergling";"Larva";177;1
"Unit";"Zergling";"Larva";178;1
"Building";"CreepTumor";NA;179;0
"Unit";"Zergling";"Larva";179;1
"Unit";"Zergling";"Larva";180;1
"Building";"CreepTumor";NA;181;0
"Unit";"Zergling";"Larva";181;1
"Unit";"Zergling";"Larva";182;1
"Unit";"Zergling";"Larva";183;1
"Unit";"Zergling";"Larva";184;1
"Building";"CreepTumor";NA;185;0
"Unit";"Zergling";"Larva";185;1
"Unit";"Zergling";"Larva";186;1
"Unit";"Zergling";"Larva";187;1
"Unit";"Zergling";"Larva";188;1
"Unit";"Zergling";"Larva";189;1
"Unit";"Zergling";"Larva";190;1
"Unit";"Zergling";"Larva";191;1
"Unit";"Zergling";"Larva";192;1
"Unit";"Zergling";"Larva";193;1
"Unit";"Zergling";"Larva";194;1
"Unit";"Baneling";"Zergling";195;0
"Unit";"Baneling";"Zergling";195;0
"Unit";"Baneling";"Zergling";195;0
"Unit";"Baneling";"Zergling";195;0
"Unit";"Baneling";"Zergling";195;0
"Unit";"Baneling";"Zergling";195;0
"Unit";"Baneling";"Zergling";195;0
"Unit";"Baneling";"Zergling";195;0
"Unit";"Zergling";"Larva";195;1
"Unit";"Zergling";"Larva";196;1
"Unit";"Zergling";"Larva";197;1
"Unit";"Zergling";"Larva";198;1
"Unit";"Roach";"Larva";199;2
"Unit";"Roach";"Larva";201;2
"Unit";"Roach";"Larva";203;2
"Unit";"Roach";"Larva";205;2
"Unit";"Zergling";"Larva";207;1
"Unit";"Zergling";"Larva";208;1
"Unit";"Zergling";"Larva";209;1
"Unit";"Zergling";"Larva";210;1
"Unit";"Zergling";"Larva";211;1
"Unit";"Zergling";"Larva";212;1
"Unit";"Zergling";"Larva";213;1
"Unit";"Zergling";"Larva";214;1
"Unit";"Zergling";"Larva";215;1
"Unit";"Zergling";"Larva";216;1
"Unit";"Zergling";"Larva";217;1
"Unit";"Zergling";"Larva";218;1
"Unit";"Zergling";"Larva";219;1
"Unit";"Zergling";"Larva";220;1
"Unit";"Roach";"Larva";221;2
"Unit";"Roach";"Larva";223;2
"Unit";"Zergling";"Larva";225;1
"Unit";"Zergling";"Larva";226;1
"Unit";"Zergling";"Larva";227;1
"Unit";"Zergling";"Larva";228;1
"Unit";"Zergling";"Larva";229;1
"Unit";"Zergling";"Larva";230;1
"Unit";"Zergling";"Larva";231;1
"Unit";"Zergling";"Larva";232;1
"Unit";"Zergling";"Larva";233;1
"Unit";"Zergling";"Larva";234;1
"Unit";"Roach";"Larva";235;2
"Unit";"Roach";"Larva";237;2
"Unit";"Roach";"Larva";239;2
"Unit";"Roach";"Larva";241;2
"Unit";"Roach";"Larva";243;2
"Unit";"Roach";"Larva";245;2
"Unit";"Roach";"Larva";247;2
"Building";"CreepTumor";NA;249;0
"Unit";"Zergling";"Larva";249;1
"Unit";"Zergling";"Larva";250;1
"Unit";"Zergling";"Larva";251;1
"Unit";"Zergling";"Larva";252;1
"Unit";"Queen";"Hatchery";253;2
"Unit";"Roach";"Larva";255;2
"Unit";"Roach";"Larva";257;2
"Unit";"Roach";"Larva";259;2
"Unit";"Zergling";"Larva";261;1
"Unit";"Zergling";"Larva";262;1
"Unit";"Baneling";"Zergling";263;0
"Unit";"Baneling";"Zergling";263;0
"Unit";"Baneling";"Zergling";263;0
"Unit";"Baneling";"Zergling";263;0
"Unit";"Baneling";"Zergling";263;0
"Unit";"Baneling";"Zergling";263;0
"Unit";"Baneling";"Zergling";263;0
"Unit";"Baneling";"Zergling";263;0
"Unit";"Baneling";"Zergling";263;0
"Unit";"Baneling";"Zergling";263;0
"Unit";"Baneling";"Zergling";263;0
"Unit";"Baneling";"Zergling";263;0
"Unit";"Baneling";"Zergling";263;0
"Unit";"Baneling";"Zergling";263;0
"Unit";"Baneling";"Zergling";263;0
"Unit";"Zergling";"Larva";263;1
"Unit";"Zergling";"Larva";264;1
"Unit";"Zergling";"Larva";265;1
"Unit";"Zergling";"Larva";266;1
"Unit";"Zergling";"Larva";267;1
"Unit";"Zergling";"Larva";268;1
"Unit";"Zergling";"Larva";269;1
"Unit";"Zergling";"Larva";270;1
"Unit";"Zergling";"Larva";271;1
"Unit";"Zergling";"Larva";272;1
"Building";"CreepTumor";NA;273;0
"Unit";"Zergling";"Larva";273;1
"Unit";"Zergling";"Larva";274;1
"Unit";"Zergling";"Larva";275;1
"Unit";"Zergling";"Larva";276;1
"Building";"CreepTumor";NA;277;0
"Unit";"Zergling";"Larva";277;1
"Unit";"Zergling";"Larva";278;1
"Unit";"Zergling";"Larva";279;1
"Unit";"Zergling";"Larva";280;1
"Unit";"Zergling";"Larva";281;1
"Unit";"Zergling";"Larva";282;1
"Unit";"Zergling";"Larva";283;1
"Unit";"Zergling";"Larva";284;1
"Unit";"Zergling";"Larva";285;1
"Unit";"Zergling";"Larva";286;1
"Unit";"Zergling";"Larva";287;1
"Unit";"Zergling";"Larva";288;1
"Unit";"Zergling";"Larva";289;1
"Unit";"Zergling";"Larva";290;1
"Unit";"Zergling";"Larva";291;1
"Unit";"Zergling";"Larva";292;1
"Unit";"Zergling";"Larva";293;1
"Unit";"Zergling";"Larva";294;1
"Unit";"Baneling";"Zergling";295;0
"Unit";"Baneling";"Zergling";295;0
"Unit";"Baneling";"Zergling";295;0
"Unit";"Baneling";"Zergling";295;0
"Unit";"Zergling";"Larva";295;1
"Unit";"Zergling";"Larva";296;1
"Unit";"Zergling";"Larva";297;1
"Unit";"Zergling";"Larva";298;1
"Unit";"Zergling";"Larva";299;1
"Unit";"Zergling";"Larva";300;1
"Unit";"Zergling";"Larva";301;1
"Unit";"Zergling";"Larva";302;1
"Unit";"Zergling";"Larva";303;1
"Unit";"Zergling";"Larva";304;1
"Unit";"Baneling";"Zergling";305;0
"Unit";"Baneling";"Zergling";305;0
"Unit";"Zergling";"Larva";305;1
"Unit";"Zergling";"Larva";306;1
"Unit";"Zergling";"Larva";307;1
"Unit";"Zergling";"Larva";308;1
"Unit";"Zergling";"Larva";309;1
"Unit";"Zergling";"Larva";310;1
"Unit";"Zergling";"Larva";311;1
"Unit";"Zergling";"Larva";312;1
"Unit";"Zergling";"Larva";313;1
"Unit";"Zergling";"Larva";314;1
"Unit";"Zergling";"Larva";315;1
"Unit";"Zergling";"Larva";316;1
"Unit";"Roach";"Larva";317;2
"Unit";"Roach";"Larva";319;2
"Unit";"Roach";"Larva";321;2
"Unit";"Zergling";"Larva";323;1
"Unit";"Zergling";"Larva";324;1
"Unit";"Zergling";"Larva";325;1
"Unit";"Zergling";"Larva";326;1
"Unit";"Zergling";"Larva";327;1
"Unit";"Zergling";"Larva";328;1
"Unit";"Baneling";"Zergling";329;0
"Unit";"Baneling";"Zergling";329;0
"Unit";"Baneling";"Zergling";329;0
"Unit";"Baneling";"Zergling";329;0
"Unit";"Zergling";"Larva";329;1
"Unit";"Zergling";"Larva";330;1
"Unit";"Zergling";"Larva";331;1
"Unit";"Zergling";"Larva";332;1
"Unit";"Zergling";"Larva";333;1
"Unit";"Zergling";"Larva";334;1
"Unit";"Zergling";"Larva";335;1
"Unit";"Zergling";"Larva";336;1
"Unit";"Zergling";"Larva";337;1
"Unit";"Zergling";"Larva";338;1
"Unit";"Zergling";"Larva";339;1
"Unit";"Zergling";"Larva";340;1
"Unit";"Zergling";"Larva";341;1
"Unit";"Zergling";"Larva";342;1
"Unit";"Zergling";"Larva";343;1
"Unit";"Zergling";"Larva";344;1
"Unit";"Zergling";"Larva";345;1
"Unit";"Zergling";"Larva";346;1
"Unit";"Zergling";"Larva";347;1
"Unit";"Zergling";"Larva";348;1
"Unit";"Zergling";"Larva";349;1
"Unit";"Zergling";"Larva";350;1
"Unit";"Zergling";"Larva";351;1
"Unit";"Zergling";"Larva";352;1
"Unit";"Zergling";"Larva";353;1
"Unit";"Zergling";"Larva";354;1
"Unit";"Zergling";"Larva";355;1
"Unit";"Zergling";"Larva";356;1
"Unit";"Zergling";"Larva";357;1
"Unit";"Zergling";"Larva";358;1
"Unit";"Zergling";"Larva";359;1
"Unit";"Zergling";"Larva";360;1
"Unit";"Roach";"Larva";361;2
"Unit";"Roach";"Larva";363;2
"Unit";"Roach";"Larva";365;2
"Unit";"Roach";"Larva";367;2
"Unit";"Roach";"Larva";369;2
"Unit";"Roach";"Larva";371;2
"Unit";"Roach";"Larva";373;2
"Unit";"Roach";"Larva";375;2
"Building";"CreepTumor";NA;377;0
"Building";"CreepTumor";NA;377;0
"Unit";"Zergling";"Larva";377;1
"Unit";"Zergling";"Larva";378;1
"Unit";"Zergling";"Larva";379;1
"Unit";"Zergling";"Larva";380;1
"Unit";"Baneling";"Zergling";381;0
"Unit";"Baneling";"Zergling";381;0
"Unit";"Baneling";"Zergling";381;0
"Unit";"Baneling";"Zergling";381;0
"Unit";"Baneling";"Zergling";381;0
"Unit";"Baneling";"Zergling";381;0
"Unit";"Baneling";"Zergling";381;0
"Unit";"Baneling";"Zergling";381;0
"Unit";"Baneling";"Zergling";381;0
"Unit";"Baneling";"Zergling";381;0
"Unit";"Baneling";"Zergling";381;0
"Unit";"Baneling";"Zergling";381;0
"Unit";"Baneling";"Zergling";381;0
"Unit";"Baneling";"Zergling";381;0
"Unit";"Zergling";"Larva";381;1
"Unit";"Zergling";"Larva";382;1
"Unit";"Zergling";"Larva";383;1
"Unit";"Zergling";"Larva";384;1
"Building";"CreepTumor";NA;385;0
"Unit";"Zergling";"Larva";385;1
"Unit";"Zergling";"Larva";386;1
"Building";"CreepTumor";NA;387;0
"Unit";"Zergling";"Larva";387;1
"Unit";"Zergling";"Larva";388;1
"Unit";"Zergling";"Larva";389;1
"Unit";"Zergling";"Larva";390;1
"Unit";"Baneling";"Zergling";391;0
"Unit";"Baneling";"Zergling";391;0
"Unit";"Baneling";"Zergling";391;0
"Unit";"Baneling";"Zergling";391;0
"Unit";"Baneling";"Zergling";391;0
"Unit";"Baneling";"Zergling";391;0
"Unit";"Zergling";"Larva";391;1
"Unit";"Zergling";"Larva";392;1
"Unit";"Zergling";"Larva";393;1
"Unit";"Zergling";"Larva";394;1
"Unit";"Zergling";"Larva";395;1
"Unit";"Zergling";"Larva";396;1
"Building";"CreepTumorQueen";NA;397;0
"Unit";"Zergling";"Larva";397;1
"Unit";"Zergling";"Larva";398;1
"Unit";"Zergling";"Larva";399;1
"Unit";"Zergling";"Larva";400;1
"Unit";"Zergling";"Larva";401;1
"Unit";"Zergling";"Larva";402;1
"Unit";"Zergling";"Larva";403;1
"Unit";"Zergling";"Larva";404;1
"Unit";"Zergling";"Larva";405;1
"Unit";"Zergling";"Larva";406;1
"Unit";"Zergling";"Larva";407;1
"Unit";"Zergling";"Larva";408;1
"Unit";"Zergling";"Larva";409;1
"Unit";"Zergling";"Larva";410;1
"Unit";"Zergling";"Larva";411;1
"Unit";"Zergling";"Larva";412;1
"Unit";"Zergling";"Larva";413;1
"Unit";"Zergling";"Larva";414;1
"Unit";"Zergling";"Larva";415;1
"Unit";"Zergling";"Larva";416;1
"Unit";"Zergling";"Larva";417;1
"Unit";"Zergling";"Larva";418;1
"Unit";"Zergling";"Larva";419;1
"Unit";"Zergling";"Larva";420;1
"Unit";"Baneling";"Zergling";421;0
"Unit";"Baneling";"Zergling";421;0
"Unit";"Baneling";"Zergling";421;0
"Unit";"Baneling";"Zergling";421;0
"Unit";"Baneling";"Zergling";421;0
"Unit";"Baneling";"Zergling";421;0
"Unit";"Baneling";"Zergling";421;0
"Unit";"Baneling";"Zergling";421;0
"Unit";"Baneling";"Zergling";421;0
"Unit";"Baneling";"Zergling";421;0
"Unit";"Zergling";"Larva";421;1
"Unit";"Zergling";"Larva";422;1
"Unit";"Zergling";"Larva";423;1
"Unit";"Zergling";"Larva";424;1
"Unit";"Zergling";"Larva";425;1
"Unit";"Zergling";"Larva";426;1
"Unit";"Zergling";"Larva";427;1
"Unit";"Zergling";"Larva";428;1
"Unit";"Zergling";"Larva";429;1
"Unit";"Zergling";"Larva";430;1
"Unit";"Zergling";"Larva";431;1
"Unit";"Zergling";"Larva";432;1
"Unit";"Zergling";"Larva";433;1
"Unit";"Zergling";"Larva";434;1
"Unit";"Zergling";"Larva";435;1
"Unit";"Zergling";"Larva";436;1
"Unit";"Zergling";"Larva";437;1
"Unit";"Zergling";"Larva";438;1
"Upgrade";"SprayZerg";NA;439;0
"Upgrade";"SprayZerg";NA;439;0
"Upgrade";"SprayZerg";NA;439;0
"Upgrade";"zerglingmovementspeed";NA;439;0
"Upgrade";"SprayZerg";NA;439;0
"Upgrade";"SprayZerg";NA;439;0
"Upgrade";"SprayZerg";NA;439;0
"Upgrade";"SprayZerg";NA;439;0
"Upgrade";"ZergMissileWeaponsLevel1";NA;439;0
"Upgrade";"CentrificalHooks";NA;439;0
"Upgrade";"SprayZerg";NA;439;0
