"type";"unit_name";"on_building";"total_supply_lag";"supply"
"Unit";"Overlord";"Larva";13;0
"Building";"Hatchery";NA;16;0
"Building";"Extractor";NA;19;0
"Building";"SpawningPool";NA;19;0
"Unit";"Overlord";"Larva";23;0
"Unit";"Queen";"Hatchery";23;2
"Unit";"Queen";"Hatchery";25;2
"Unit";"Zergling";"Larva";27;1
"Unit";"Zergling";"Larva";28;1
"Unit";"Zergling";"Larva";29;1
"Unit";"Zergling";"Larva";30;1
"Building";"Hatchery";NA;35;0
"Building";"CreepTumorQueen";NA;37;0
"Unit";"Queen";"Hatchery";37;2
"Unit";"Overlord";"Larva";39;0
"Building";"CreepTumor";NA;47;0
"Building";"CreepTumorQueen";NA;47;0
"Unit";"Overlord";"Larva";47;0
"Unit";"Queen";"Hatchery";47;2
"Unit";"Overlord";"Larva";49;0
"Building";"CreepTumor";NA;52;0
"Building";"CreepTumorQueen";NA;52;0
"Building";"CreepTumor";NA;55;0
"Unit";"Overlord";"Larva";55;0
"Building";"SporeCrawler";NA;56;0
"Unit";"Zergling";"Larva";57;1
"Unit";"Zergling";"Larva";58;1
"Unit";"Zergling";"Larva";59;1
"Unit";"Zergling";"Larva";60;1
"Building";"RoachWarren";NA;65;0
"Building";"Extractor";NA;65;0
"Building";"CreepTumor";NA;66;0
"Building";"SporeCrawler";NA;68;0
"Building";"Extractor";NA;72;0
"Unit";"Overlord";"Larva";72;0
"Unit";"Overlord";"Larva";74;0
"Unit";"Queen";"Hatchery";79;2
"Unit";"Roach";"Larva";81;2
"Unit";"Roach";"Larva";83;2
"Unit";"Overlord";"Larva";85;0
"Building";"CreepTumorQueen";NA;85;0
"Unit";"Roach";"Larva";85;2
"Unit";"Roach";"Larva";87;2
"Unit";"Roach";"Larva";89;2
"Unit";"Roach";"Larva";91;2
"Upgrade";"GlialReconstitution";"RoachWarren";93;0
"Unit";"Roach";"Larva";93;2
"Unit";"Roach";"Larva";95;2
"Building";"CreepTumor";NA;97;0
"Building";"CreepTumorQueen";NA;97;0
"Unit";"Overlord";"Larva";97;0
"Building";"CreepTumor";NA;97;0
"Unit";"Roach";"Larva";97;2
"Unit";"Roach";"Larva";99;2
"Unit";"Roach";"Larva";101;2
"Unit";"Roach";"Larva";103;2
"Unit";"Roach";"Larva";105;2
"Building";"CreepTumor";NA;107;0
"Unit";"Overlord";"Larva";107;0
"Unit";"Overlord";"Larva";107;0
"Unit";"Roach";"Larva";107;2
"Unit";"Roach";"Larva";109;2
"Unit";"Roach";"Larva";111;2
"Unit";"Roach";"Larva";113;2
"Building";"CreepTumor";NA;115;0
"Unit";"Overlord";"Larva";115;0
"Unit";"Overlord";"Larva";115;0
"Unit";"Roach";"Larva";115;2
"Unit";"Roach";"Larva";117;2
"Unit";"Roach";"Larva";119;2
"Unit";"Roach";"Larva";121;2
"Unit";"Overlord";"Larva";123;0
"Unit";"Roach";"Larva";123;2
"Unit";"Roach";"Larva";125;2
"Unit";"Roach";"Larva";127;2
"Unit";"Roach";"Larva";129;2
"Unit";"Overlord";"Larva";131;0
"Unit";"Roach";"Larva";131;2
"Unit";"Roach";"Larva";133;2
"Unit";"Roach";"Larva";135;2
"Unit";"Roach";"Larva";137;2
"Unit";"Zergling";"Larva";139;1
"Unit";"Zergling";"Larva";140;1
"Unit";"Zergling";"Larva";141;1
"Unit";"Zergling";"Larva";142;1
"Unit";"Zergling";"Larva";143;1
"Unit";"Zergling";"Larva";144;1
"Unit";"Overlord";"Larva";145;0
"Unit";"Zergling";"Larva";145;1
"Unit";"Zergling";"Larva";146;1
"Unit";"Zergling";"Larva";147;1
"Unit";"Zergling";"Larva";148;1
"Unit";"Zergling";"Larva";149;1
"Unit";"Zergling";"Larva";150;1
"Unit";"Zergling";"Larva";151;1
"Unit";"Zergling";"Larva";152;1
"Unit";"Zergling";"Larva";153;1
"Unit";"Zergling";"Larva";154;1
"Unit";"Zergling";"Larva";155;1
"Unit";"Zergling";"Larva";156;1
"Unit";"Zergling";"Larva";157;1
"Unit";"Zergling";"Larva";158;1
"Unit";"Zergling";"Larva";159;1
"Unit";"Zergling";"Larva";160;1
"Unit";"Zergling";"Larva";161;1
"Unit";"Zergling";"Larva";162;1
"Unit";"Zergling";"Larva";163;1
"Unit";"Zergling";"Larva";164;1
"Unit";"Overlord";"Larva";165;0
"Unit";"Zergling";"Larva";165;1
"Unit";"Zergling";"Larva";166;1
"Unit";"Zergling";"Larva";167;1
"Unit";"Zergling";"Larva";168;1
"Unit";"Zergling";"Larva";169;1
"Unit";"Zergling";"Larva";170;1
"Unit";"Roach";"Larva";171;2
"Unit";"Roach";"Larva";173;2
"Unit";"Roach";"Larva";175;2
"Unit";"Roach";"Larva";177;2
"Unit";"Roach";"Larva";179;2
"Unit";"Roach";"Larva";181;2
"Unit";"Roach";"Larva";183;2
"Unit";"Roach";"Larva";185;2
"Unit";"Roach";"Larva";187;2
"Unit";"Roach";"Larva";189;2
"Unit";"Roach";"Larva";191;2
"Unit";"Roach";"Larva";193;2
"Unit";"Roach";"Larva";195;2
"Unit";"Roach";"Larva";197;2
"Unit";"Roach";"Larva";199;2
"Unit";"Roach";"Larva";201;2
"Unit";"Roach";"Larva";203;2
"Unit";"Roach";"Larva";205;2
"Unit";"Roach";"Larva";207;2
"Unit";"Roach";"Larva";209;2
"Unit";"Roach";"Larva";211;2
"Unit";"Roach";"Larva";213;2
"Unit";"Roach";"Larva";215;2
"Unit";"Queen";"Hatchery";217;2
"Unit";"Queen";"Hatchery";219;2
"Unit";"Roach";"Larva";221;2
"Unit";"Roach";"Larva";223;2
"Unit";"Roach";"Larva";225;2
"Unit";"Roach";"Larva";227;2
"Building";"Hatchery";NA;229;0
"Building";"Extractor";NA;232;0
"Building";"EvolutionChamber";NA;238;0
"Unit";"Overlord";"Larva";241;0
"Upgrade";"Burrow";"Hatchery";241;0
"Building";"CreepTumor";NA;243;0
"Upgrade";"TunnelingClaws";"RoachWarren";245;0
"Building";"Extractor";NA;245;0
"Building";"Extractor";NA;246;0
"Unit";"Overlord";"Larva";246;0
"Unit";"Overlord";"Larva";250;0
"Unit";"Roach";"Larva";250;2
"Unit";"Roach";"Larva";252;2
"Unit";"Roach";"Larva";254;2
"Unit";"Roach";"Larva";256;2
"Unit";"Overlord";"Larva";258;0
"Building";"CreepTumor";NA;258;0
"Building";"CreepTumor";NA;258;0
"Unit";"Roach";"Larva";258;2
"Unit";"Roach";"Larva";260;2
"Unit";"Roach";"Larva";262;2
"Unit";"Roach";"Larva";264;2
"Unit";"Roach";"Larva";266;2
"Unit";"Roach";"Larva";268;2
"Unit";"Roach";"Larva";270;2
"Unit";"Roach";"Larva";272;2
"Unit";"Roach";"Larva";274;2
"Unit";"Overlord";"Larva";276;0
"Unit";"Overlord";"Larva";276;0
"Unit";"Overlord";"Larva";276;0
"Building";"HydraliskDen";NA;277;0
"Unit";"Overlord";"Larva";287;0
"Unit";"Roach";"Larva";287;2
"Unit";"Roach";"Larva";289;2
"Unit";"Roach";"Larva";291;2
"Unit";"Roach";"Larva";293;2
"Unit";"Queen";"Hatchery";295;2
"Unit";"Roach";"Larva";297;2
"Unit";"Roach";"Larva";299;2
"Unit";"Roach";"Larva";301;2
"Unit";"Roach";"Larva";303;2
"Building";"Hatchery";NA;305;0
"Unit";"Overlord";"Larva";305;0
"Unit";"Hydralisk";"Larva";305;2
"Unit";"Hydralisk";"Larva";307;2
"Unit";"Hydralisk";"Larva";309;2
"Unit";"Hydralisk";"Larva";311;2
"Unit";"Hydralisk";"Larva";313;2
"Unit";"Hydralisk";"Larva";315;2
"Unit";"Hydralisk";"Larva";317;2
"Unit";"Hydralisk";"Larva";319;2
"Unit";"Roach";"Larva";321;2
"Unit";"Roach";"Larva";323;2
"Unit";"Roach";"Larva";325;2
"Unit";"Roach";"Larva";327;2
"Unit";"Roach";"Larva";329;2
"Unit";"Roach";"Larva";331;2
"Unit";"Roach";"Larva";333;2
"Unit";"Roach";"Larva";335;2
"Unit";"Roach";"Larva";337;2
"Unit";"Roach";"Larva";339;2
"Unit";"Roach";"Larva";341;2
"Unit";"Roach";"Larva";343;2
"Unit";"Overlord";"Larva";345;0
"Unit";"Overlord";"Larva";345;0
"Unit";"Overlord";"Larva";345;0
"Unit";"Overlord";"Larva";345;0
"Unit";"Overlord";"Larva";345;0
"Unit";"Overlord";"Larva";345;0
"Unit";"Roach";"Larva";345;2
"Unit";"Roach";"Larva";347;2
"Unit";"Roach";"Larva";349;2
"Unit";"Roach";"Larva";351;2
"Unit";"Roach";"Larva";353;2
"Unit";"Roach";"Larva";355;2
"Unit";"Roach";"Larva";357;2
"Unit";"Roach";"Larva";359;2
"Unit";"Roach";"Larva";361;2
"Unit";"Roach";"Larva";363;2
"Unit";"Hydralisk";"Larva";365;2
"Unit";"Hydralisk";"Larva";367;2
"Unit";"Hydralisk";"Larva";369;2
"Upgrade";"SprayZerg";NA;371;0
"Upgrade";"SprayZerg";NA;371;0
"Upgrade";"SprayZerg";NA;371;0
"Upgrade";"zerglingmovementspeed";NA;371;0
"Upgrade";"SprayZerg";NA;371;0
"Upgrade";"SprayZerg";NA;371;0
"Upgrade";"SprayZerg";NA;371;0
"Upgrade";"SprayZerg";NA;371;0
"Upgrade";"ZergMissileWeaponsLevel1";NA;371;0
"Upgrade";"EvolveMuscularAugments";NA;371;0
"Upgrade";"SprayZerg";NA;371;0
