"type";"unit_name";"on_building";"total_supply";"supply"
"Unit";"Overlord";"Larva";12;0
"Building";"Extractor";NA;17;0
"Unit";"Overlord";"Larva";21;0
"Building";"Hatchery";NA;17;0
"Building";"SpawningPool";NA;19;0
"Unit";"Queen";"Hatchery";22;2
"Unit";"Zergling";"Larva";23;1
"Unit";"Zergling";"Larva";23;1
"Unit";"Queen";"Hatchery";22;2
"Unit";"Zergling";"Larva";23;1
"Unit";"Zergling";"Larva";23;1
"Unit";"Zergling";"Larva";23;1
"Unit";"Zergling";"Larva";23;1
"Unit";"Zergling";"Larva";24;1
"Unit";"Zergling";"Larva";24;1
"Unit";"Zergling";"Larva";35;1
"Unit";"Zergling";"Larva";35;1
"Unit";"Zergling";"Larva";35;1
"Unit";"Zergling";"Larva";35;1
"Unit";"Overlord";"Larva";38;0
"Unit";"Queen";"Hatchery";36;2
"Unit";"Overlord";"Larva";42;0
"Unit";"Overlord";"Larva";42;0
"Building";"CreepTumorQueen";NA;50;0
"Building";"Hatchery";NA;24;0
"Unit";"Overlord";"Larva";49;0
"Building";"Extractor";NA;63;0
"Building";"Extractor";NA;63;0
"Building";"SporeCrawler";NA;63;0
"Building";"SporeCrawler";NA;65;0
"Building";"SporeCrawler";NA;65;0
"Building";"CreepTumor";NA;68;0
"Unit";"Overlord";"Larva";68;0
"Unit";"Overlord";"Larva";70;0
"Unit";"Overlord";"Larva";70;0
"Unit";"Overlord";"Larva";73;0
"Building";"EvolutionChamber";NA;73;0
"Building";"CreepTumor";NA;82;0
"Unit";"Overlord";"Larva";82;0
"Building";"Extractor";NA;82;0
"Building";"HydraliskDen";NA;80;0
"Unit";"Overlord";"Larva";86;0
"Unit";"Hydralisk";"Larva";91;2
"Unit";"Hydralisk";"Larva";91;2
"Unit";"Hydralisk";"Larva";91;2
"Unit";"Hydralisk";"Larva";91;2
"Unit";"Hydralisk";"Larva";91;2
"Unit";"Hydralisk";"Larva";91;2
"Unit";"Hydralisk";"Larva";91;2
"Unit";"Hydralisk";"Larva";91;2
"Unit";"Hydralisk";"Larva";91;2
"Unit";"Overlord";"Larva";103;0
"Unit";"Overlord";"Larva";103;0
"Unit";"Overlord";"Larva";103;0
"Unit";"Overlord";"Larva";103;0
"Unit";"Hydralisk";"Larva";101;2
"Building";"CreepTumor";NA;107;0
"Building";"Extractor";NA;105;0
"Upgrade";"EvolveGroovedSpines";"HydraliskDen";91;0
"Unit";"Overlord";"Larva";113;0
"Unit";"Overlord";"Larva";113;0
"Unit";"Hydralisk";"Larva";111;2
"Unit";"Hydralisk";"Larva";111;2
"Unit";"Hydralisk";"Larva";111;2
"Unit";"Hydralisk";"Larva";111;2
"Unit";"Hydralisk";"Larva";111;2
"Unit";"Overlord";"Larva";115;0
"Unit";"Overlord";"Larva";115;0
"Unit";"Hydralisk";"Larva";114;2
"Unit";"Overlord";"Larva";115;0
"Unit";"Overlord";"Larva";115;0
"Building";"CreepTumor";NA;115;0
"Unit";"Queen";"Hatchery";113;2
"Unit";"Hydralisk";"Larva";115;2
"Unit";"Hydralisk";"Larva";115;2
"Unit";"Hydralisk";"Larva";115;2
"Unit";"Hydralisk";"Larva";125;2
"Unit";"Hydralisk";"Larva";125;2
"Unit";"Zergling";"Larva";127;1
"Unit";"Zergling";"Larva";127;1
"Unit";"Zergling";"Larva";127;1
"Unit";"Zergling";"Larva";127;1
"Unit";"Zergling";"Larva";127;1
"Unit";"Zergling";"Larva";127;1
"Unit";"Zergling";"Larva";127;1
"Unit";"Zergling";"Larva";127;1
"Unit";"Zergling";"Larva";127;1
"Unit";"Zergling";"Larva";127;1
"Unit";"Hydralisk";"Larva";127;2
"Unit";"Hydralisk";"Larva";127;2
"Unit";"Zergling";"Larva";129;1
"Unit";"Zergling";"Larva";129;1
"Unit";"Zergling";"Larva";129;1
"Unit";"Zergling";"Larva";129;1
"Upgrade";"ZergMissileWeaponsLevel1";"EvolutionChamber";103;0
"Unit";"Hydralisk";"Larva";127;2
"Unit";"Hydralisk";"Larva";129;2
"Building";"CreepTumor";NA;139;0
"Unit";"Hydralisk";"Larva";135;2
"Unit";"Hydralisk";"Larva";135;2
"Unit";"Hydralisk";"Larva";139;2
"Unit";"Queen";"Hatchery";127;2
"Unit";"Hydralisk";"Larva";161;2
"Upgrade";"EvolveMuscularAugments";"HydraliskDen";127;0
"Unit";"Hydralisk";"Larva";161;2
"Unit";"Hydralisk";"Larva";161;2
"Unit";"Hydralisk";"Larva";161;2
"Unit";"Hydralisk";"Larva";161;2
"Unit";"Hydralisk";"Larva";165;2
"Unit";"Hydralisk";"Larva";169;2
"Building";"Hatchery";NA;125;0
"Unit";"Overlord";"Larva";169;0
"Unit";"Overlord";"Larva";169;0
"Unit";"Zergling";"Larva";175;1
"Unit";"Zergling";"Larva";175;1
"Unit";"Hydralisk";"Larva";169;2
"Unit";"Zergling";"Larva";175;1
"Unit";"Zergling";"Larva";175;1
"Unit";"Zergling";"Larva";175;1
"Unit";"Zergling";"Larva";175;1
"Unit";"Zergling";"Larva";175;1
"Unit";"Zergling";"Larva";175;1
"Unit";"Zergling";"Larva";175;1
"Unit";"Zergling";"Larva";175;1
"Unit";"Zergling";"Larva";175;1
"Unit";"Zergling";"Larva";175;1
"Unit";"Hydralisk";"Larva";169;2
"Unit";"Hydralisk";"Larva";169;2
"Unit";"Overlord";"Larva";181;0
"Unit";"Hydralisk";"Larva";183;2
"Unit";"Hydralisk";"Larva";195;2
"Unit";"Hydralisk";"Larva";195;2
"Unit";"Hydralisk";"Larva";197;2
"Unit";"Hydralisk";"Larva";199;2
"Unit";"Hydralisk";"Larva";199;2
"Unit";"Hydralisk";"Larva";201;2
"Unit";"Hydralisk";"Larva";201;2
"Unit";"Zergling";"Larva";201;1
"Unit";"Zergling";"Larva";201;1
"Unit";"Zergling";"Larva";201;1
"Unit";"Zergling";"Larva";201;1
"Unit";"Zergling";"Larva";201;1
"Unit";"Zergling";"Larva";201;1
"Unit";"Zergling";"Larva";201;1
"Unit";"Zergling";"Larva";201;1
"Unit";"Zergling";"Larva";201;1
"Unit";"Zergling";"Larva";201;1
"Unit";"Zergling";"Larva";201;1
"Unit";"Zergling";"Larva";201;1
"Unit";"Zergling";"Larva";201;1
"Unit";"Zergling";"Larva";201;1
"Unit";"Zergling";"Larva";203;1
"Unit";"Zergling";"Larva";203;1
"Unit";"Hydralisk";"Larva";201;2
"Unit";"Hydralisk";"Larva";201;2
"Unit";"Hydralisk";"Larva";216;2
"Unit";"Hydralisk";"Larva";216;2
"Unit";"Hydralisk";"Larva";216;2
"Unit";"Hydralisk";"Larva";216;2
"Building";"Extractor";NA;226;0
