"type";"unit_name";"on_building";"total_supply";"supply"
"Unit";"Overlord";"Larva";13;0
"Building";"Extractor";NA;18;0
"Unit";"Overlord";"Larva";21;0
"Building";"SpawningPool";NA;19;0
"Building";"Hatchery";NA;16;0
"Unit";"Zergling";"Larva";22;1
"Unit";"Zergling";"Larva";22;1
"Unit";"Zergling";"Larva";22;1
"Unit";"Zergling";"Larva";22;1
"Unit";"Queen";"Hatchery";22;2
"Unit";"Queen";"Hatchery";22;2
"Building";"CreepTumorQueen";NA;35;0
"Unit";"Overlord";"Larva";35;0
"Unit";"Zergling";"Larva";35;1
"Unit";"Zergling";"Larva";35;1
"Unit";"Zergling";"Larva";35;1
"Unit";"Zergling";"Larva";35;1
"Building";"CreepTumor";NA;38;0
"Unit";"Overlord";"Larva";38;0
"Unit";"Queen";"Hatchery";38;2
"Building";"CreepTumorQueen";NA;42;0
"Building";"Hatchery";NA;35;0
"Building";"CreepTumorQueen";NA;52;0
"Building";"CreepTumor";NA;52;0
"Building";"SporeCrawler";NA;48;0
"Building";"SporeCrawler";NA;48;0
"Unit";"Queen";"Hatchery";48;2
"Building";"Extractor";NA;57;0
"Building";"Extractor";NA;57;0
"Unit";"Queen";"Hatchery";53;2
"Building";"CreepTumor";NA;62;0
"Building";"CreepTumor";NA;62;0
"Building";"EvolutionChamber";NA;57;0
"Building";"CreepTumorQueen";NA;68;0
"Building";"CreepTumor";NA;68;0
"Building";"SporeCrawler";NA;66;0
"Building";"CreepTumor";NA;71;0
"Building";"CreepTumor";NA;71;0
"Building";"CreepTumorQueen";NA;71;0
"Unit";"Overlord";"Larva";71;0
"Unit";"Overlord";"Larva";71;0
"Building";"CreepTumor";NA;78;0
"Building";"CreepTumor";NA;78;0
"Unit";"Queen";"Hatchery";71;2
"Building";"CreepTumor";NA;78;0
"Building";"CreepTumor";NA;78;0
"Unit";"Overlord";"Larva";78;0
"Unit";"Overlord";"Larva";78;0
"Unit";"Overlord";"Larva";78;0
"Unit";"Overlord";"Larva";78;0
"Building";"RoachWarren";NA;75;0
"Building";"CreepTumor";NA;84;0
"Building";"CreepTumorQueen";NA;84;0
"Building";"CreepTumor";NA;84;0
"Building";"CreepTumor";NA;84;0
"Building";"CreepTumor";NA;84;0
"Building";"CreepTumor";NA;92;0
"Unit";"Roach";"Larva";87;2
"Unit";"Roach";"Larva";87;2
"Unit";"Roach";"Larva";87;2
"Unit";"Roach";"Larva";87;2
"Unit";"Roach";"Larva";87;2
"Unit";"Roach";"Larva";92;2
"Unit";"Roach";"Larva";92;2
"Unit";"Roach";"Larva";92;2
"Building";"CreepTumor";NA;102;0
"Unit";"Roach";"Larva";92;2
"Unit";"Roach";"Larva";92;2
"Unit";"Roach";"Larva";92;2
"Unit";"Roach";"Larva";92;2
"Unit";"Zergling";"Larva";104;1
"Unit";"Zergling";"Larva";104;1
"Unit";"Overlord";"Larva";106;0
"Unit";"Overlord";"Larva";106;0
"Unit";"Overlord";"Larva";106;0
"Unit";"Overlord";"Larva";118;0
"Unit";"Overlord";"Larva";118;0
"Unit";"Overlord";"Larva";118;0
"Unit";"Zergling";"Larva";118;1
"Unit";"Zergling";"Larva";118;1
"Unit";"Zergling";"Larva";118;1
"Unit";"Zergling";"Larva";118;1
"Unit";"Roach";"Larva";118;2
"Unit";"Zergling";"Larva";118;1
"Unit";"Zergling";"Larva";118;1
"Unit";"Zergling";"Larva";118;1
"Unit";"Zergling";"Larva";118;1
"Unit";"Roach";"Larva";118;2
"Unit";"Roach";"Larva";118;2
"Unit";"Roach";"Larva";118;2
"Unit";"Roach";"Larva";118;2
"Unit";"Roach";"Larva";118;2
"Upgrade";"GlialReconstitution";"RoachWarren";102;0
"Building";"CreepTumor";NA;138;0
"Building";"CreepTumor";NA;138;0
"Building";"CreepTumor";NA;138;0
"Building";"CreepTumor";NA;138;0
"Building";"CreepTumor";NA;138;0
"Upgrade";"ZergMissileWeaponsLevel1";"EvolutionChamber";92;0
"Building";"CreepTumor";NA;153;0
"Building";"Extractor";NA;150;0
"Building";"Extractor";NA;150;0
"Unit";"Overlord";"Larva";164;0
"Building";"CreepTumor";NA;164;0
"Unit";"Overlord";"Larva";164;0
"Unit";"Overlord";"Larva";164;0
"Unit";"Overlord";"Larva";164;0
"Building";"HydraliskDen";NA;150;0
"Building";"CreepTumor";NA;164;0
"Building";"CreepTumor";NA;164;0
"Building";"Extractor";NA;164;0
"Building";"CreepTumorQueen";NA;164;0
"Unit";"Roach";"Larva";164;2
"Unit";"Roach";"Larva";164;2
"Unit";"Roach";"Larva";164;2
"Unit";"Roach";"Larva";164;2
"Building";"CreepTumor";NA;164;0
"Building";"CreepTumor";NA;164;0
"Building";"CreepTumorQueen";NA;164;0
"Building";"CreepTumorQueen";NA;164;0
"Building";"CreepTumorQueen";NA;164;0
"Building";"CreepTumorQueen";NA;164;0
"Building";"CreepTumorQueen";NA;164;0
"Building";"CreepTumor";NA;172;0
"Building";"CreepTumor";NA;182;0
"Building";"CreepTumor";NA;182;0
"Building";"CreepTumor";NA;182;0
"Building";"CreepTumor";NA;182;0
"Building";"CreepTumor";NA;182;0
"Building";"CreepTumor";NA;182;0
"Building";"CreepTumor";NA;182;0
"Building";"Hatchery";NA;164;0
"Building";"CreepTumor";NA;182;0
"Unit";"Hydralisk";"Larva";172;2
"Unit";"Hydralisk";"Larva";172;2
"Unit";"Hydralisk";"Larva";172;2
"Unit";"Hydralisk";"Larva";172;2
"Unit";"Hydralisk";"Larva";172;2
"Unit";"Hydralisk";"Larva";172;2
"Unit";"Hydralisk";"Larva";172;2
"Unit";"Hydralisk";"Larva";172;2
"Building";"Hatchery";NA;164;0
"Building";"Extractor";NA;182;0
"Building";"Extractor";NA;182;0
"Unit";"Overlord";"Larva";182;0
"Unit";"Overlord";"Larva";182;0
"Unit";"Overlord";"Larva";182;0
"Upgrade";"EvolveGroovedSpines";"HydraliskDen";172;0
"Building";"InfestationPit";NA;182;0
"Unit";"Roach";"Larva";219;2
"Unit";"Roach";"Larva";219;2
"Unit";"Roach";"Larva";219;2
"Unit";"Roach";"Larva";219;2
"Unit";"Roach";"Larva";219;2
"Unit";"Hydralisk";"Larva";219;2
"Unit";"Hydralisk";"Larva";219;2
"Unit";"Hydralisk";"Larva";219;2
"Unit";"Hydralisk";"Larva";219;2
"Building";"CreepTumor";NA;219;0
"Building";"CreepTumor";NA;219;0
"Unit";"Roach";"Larva";219;2
"Unit";"Roach";"Larva";219;2
"Unit";"Roach";"Larva";219;2
"Unit";"Roach";"Larva";219;2
"Unit";"Roach";"Larva";219;2
"Unit";"Hydralisk";"Larva";219;2
"Unit";"Hydralisk";"Larva";219;2
"Unit";"Hydralisk";"Larva";219;2
"Unit";"Hydralisk";"Larva";219;2
"Unit";"Hydralisk";"Larva";219;2
"Building";"LurkerDenMP";NA;182;0
"Unit";"Hydralisk";"Larva";237;2
"Unit";"Hydralisk";"Larva";237;2
"Unit";"Hydralisk";"Larva";237;2
"Unit";"Hydralisk";"Larva";237;2
"Unit";"Hydralisk";"Larva";237;2
"Unit";"Hydralisk";"Larva";237;2
"Unit";"Hydralisk";"Larva";237;2
"Unit";"Hydralisk";"Larva";237;2
"Building";"SporeCrawler";NA;247;0
"Building";"SporeCrawler";NA;247;0
"Building";"SporeCrawler";NA;257;0
"Building";"SporeCrawler";NA;257;0
"Building";"SporeCrawler";NA;257;0
"Building";"SporeCrawler";NA;257;0
"Upgrade";"ZergMissileWeaponsLevel2";"EvolutionChamber";198;0
"Upgrade";"EvolveMuscularAugments";"HydraliskDen";237;0
"Unit";"Roach";"Larva";279;2
"Unit";"Roach";"Larva";279;2
"Unit";"Roach";"Larva";279;2
"Unit";"Roach";"Larva";279;2
"Unit";"Roach";"Larva";279;2
"Unit";"Roach";"Larva";279;2
"Unit";"Hydralisk";"Larva";279;2
"Unit";"Hydralisk";"Larva";279;2
"Unit";"Hydralisk";"Larva";279;2
"Unit";"Hydralisk";"Larva";279;2
"Unit";"Hydralisk";"Larva";279;2
"Unit";"Hydralisk";"Larva";279;2
"Building";"CreepTumor";NA;279;0
"Building";"CreepTumor";NA;303;0
"Building";"CreepTumor";NA;303;0
"Unit";"Roach";"Larva";303;2
"Unit";"Queen";"Hatchery";279;2
"Unit";"Hydralisk";"Larva";303;2
"Unit";"Hydralisk";"Larva";303;2
"Unit";"Queen";"Hatchery";291;2
"Building";"CreepTumor";NA;313;0
"Unit";"Roach";"Larva";313;2
"Unit";"Roach";"Larva";313;2
"Unit";"Roach";"Larva";313;2
"Unit";"Hydralisk";"Larva";313;2
"Unit";"Hydralisk";"Larva";313;2
"Unit";"Hydralisk";"Larva";313;2
"Building";"Hatchery";NA;291;0
"Unit";"Roach";"Larva";325;2
"Unit";"Roach";"Larva";325;2
"Unit";"Roach";"Larva";325;2
"Unit";"Roach";"Larva";325;2
"Unit";"Roach";"Larva";325;2
"Unit";"Roach";"Larva";325;2
"Unit";"Hydralisk";"Larva";325;2
"Unit";"Hydralisk";"Larva";325;2
"Unit";"Hydralisk";"Larva";325;2
"Unit";"Hydralisk";"Larva";325;2
"Unit";"Hydralisk";"Larva";325;2
"Building";"CreepTumor";NA;367;0
"Unit";"Roach";"Larva";355;2
"Unit";"Hydralisk";"Larva";355;2
"Building";"Spire";NA;313;0
"Unit";"Roach";"Larva";369;2
"Unit";"Roach";"Larva";369;2
"Unit";"Roach";"Larva";369;2
"Unit";"Roach";"Larva";369;2
"Unit";"Roach";"Larva";369;2
"Unit";"Roach";"Larva";369;2
"Unit";"Roach";"Larva";369;2
"Unit";"Hydralisk";"Larva";369;2
"Unit";"Hydralisk";"Larva";369;2
"Unit";"Hydralisk";"Larva";369;2
"Unit";"Hydralisk";"Larva";369;2
"Unit";"Hydralisk";"Larva";369;2
"Unit";"Hydralisk";"Larva";369;2
"Unit";"Hydralisk";"Larva";369;2
"Building";"CreepTumor";NA;399;0
"Unit";"Roach";"Larva";399;2
"Unit";"Roach";"Larva";399;2
"Unit";"Roach";"Larva";399;2
"Unit";"Roach";"Larva";399;2
"Unit";"Roach";"Larva";399;2
"Building";"CreepTumor";NA;399;0
"Unit";"Hydralisk";"Larva";399;2
"Unit";"Hydralisk";"Larva";399;2
"Unit";"Hydralisk";"Larva";399;2
"Unit";"Hydralisk";"Larva";399;2
"Unit";"Hydralisk";"Larva";399;2
"Unit";"Roach";"Larva";419;2
"Unit";"Roach";"Larva";419;2
"Unit";"Roach";"Larva";419;2
"Unit";"Roach";"Larva";419;2
"Unit";"Hydralisk";"Larva";419;2
"Unit";"Hydralisk";"Larva";419;2
"Unit";"Hydralisk";"Larva";419;2
"Unit";"Hydralisk";"Larva";419;2
"Unit";"Hydralisk";"Larva";419;2
"Building";"Extractor";NA;437;0
"Unit";"Roach";"Larva";437;2
"Unit";"Roach";"Larva";437;2
"Unit";"Roach";"Larva";437;2
"Building";"Extractor";NA;437;0
"Unit";"Hydralisk";"Larva";437;2
"Unit";"Hydralisk";"Larva";437;2
"Unit";"Hydralisk";"Larva";437;2
"Unit";"Hydralisk";"Larva";437;2
"Unit";"Roach";"Larva";451;2
"Unit";"Roach";"Larva";451;2
"Unit";"Roach";"Larva";451;2
"Unit";"Roach";"Larva";451;2
"Unit";"Roach";"Larva";451;2
"Unit";"Roach";"Larva";451;2
"Unit";"Roach";"Larva";451;2
"Unit";"Overlord";"Larva";451;0
"Unit";"Overlord";"Larva";451;0
"Unit";"Overlord";"Larva";451;0
"Unit";"Overlord";"Larva";451;0
"Unit";"Hydralisk";"Larva";451;2
"Unit";"Hydralisk";"Larva";451;2
"Unit";"Hydralisk";"Larva";451;2
"Unit";"Hydralisk";"Larva";451;2
"Unit";"Hydralisk";"Larva";451;2
"Unit";"Hydralisk";"Larva";451;2
"Unit";"Hydralisk";"Larva";451;2
"Unit";"Corruptor";"Larva";451;2
"Unit";"Corruptor";"Larva";451;2
"Building";"Extractor";NA;451;0
"Unit";"Corruptor";"Larva";451;2
"Building";"Extractor";NA;451;0
"Unit";"Corruptor";"Larva";451;2
"Unit";"Corruptor";"Larva";451;2
"Unit";"Corruptor";"Larva";451;2
"Unit";"Corruptor";"Larva";451;2
"Unit";"Roach";"Larva";479;2
"Unit";"Roach";"Larva";479;2
"Unit";"Roach";"Larva";479;2
"Unit";"Roach";"Larva";479;2
"Unit";"Roach";"Larva";479;2
"Unit";"Roach";"Larva";479;2
"Unit";"Hydralisk";"Larva";479;2
"Unit";"Hydralisk";"Larva";479;2
"Unit";"Hydralisk";"Larva";479;2
"Unit";"Hydralisk";"Larva";479;2
"Unit";"Hydralisk";"Larva";479;2
"Unit";"Hydralisk";"Larva";479;2
"Unit";"Hydralisk";"Larva";479;2
"Unit";"Hydralisk";"Larva";493;2
"Unit";"Hydralisk";"Larva";493;2
"Unit";"Hydralisk";"Larva";493;2
"Unit";"Hydralisk";"Larva";493;2
"Unit";"Hydralisk";"Larva";493;2
"Unit";"Hydralisk";"Larva";493;2
"Unit";"Hydralisk";"Larva";493;2
"Unit";"Hydralisk";"Larva";493;2
"Unit";"Hydralisk";"Larva";493;2
"Unit";"Hydralisk";"Larva";493;2
"Unit";"Hydralisk";"Larva";493;2
"Unit";"Hydralisk";"Larva";493;2
"Unit";"Hydralisk";"Larva";493;2
"Unit";"Hydralisk";"Larva";493;2
"Unit";"Hydralisk";"Larva";493;2
"Unit";"Hydralisk";"Larva";493;2
"Unit";"Hydralisk";"Larva";493;2
"Unit";"Hydralisk";"Larva";493;2
"Unit";"Hydralisk";"Larva";493;2
"Unit";"Roach";"Larva";519;2
"Unit";"Roach";"Larva";519;2
"Unit";"Roach";"Larva";519;2
"Unit";"Hydralisk";"Larva";519;2
"Unit";"Hydralisk";"Larva";519;2
"Unit";"Hydralisk";"Larva";519;2
"Unit";"Hydralisk";"Larva";519;2
"Building";"CreepTumor";NA;563;0
"Building";"CreepTumor";NA;563;0
"Unit";"Hydralisk";"Larva";557;2
"Unit";"Hydralisk";"Larva";557;2
"Unit";"Hydralisk";"Larva";557;2
"Unit";"Hydralisk";"Larva";557;2
"Unit";"Hydralisk";"Larva";557;2
"Unit";"Hydralisk";"Larva";557;2
"Unit";"Hydralisk";"Larva";557;2
"Unit";"Hydralisk";"Larva";557;2
"Unit";"Hydralisk";"Larva";557;2
"Building";"CreepTumor";NA;571;0
"Unit";"Hydralisk";"Larva";571;2
"Unit";"Hydralisk";"Larva";571;2
"Unit";"Hydralisk";"Larva";571;2
"Unit";"Hydralisk";"Larva";571;2
"Unit";"Hydralisk";"Larva";571;2
"Unit";"Hydralisk";"Larva";571;2
"Unit";"Queen";"Hatchery";571;2
"Building";"Extractor";NA;592;0
"Unit";"Hydralisk";"Larva";592;2
"Unit";"Hydralisk";"Larva";592;2
"Unit";"Hydralisk";"Larva";592;2
"Unit";"Hydralisk";"Larva";592;2
"Unit";"Hydralisk";"Larva";592;2
"Unit";"Hydralisk";"Larva";592;2
"Unit";"Hydralisk";"Larva";592;2
