"type";"unit_name";"on_building";"total_supply_lag"
"Unit";"Overlord";"Larva";13
"Building";"Hatchery";NA;17
"Building";"Extractor";NA;19
"Building";"SpawningPool";NA;19
"Unit";"Overlord";"Larva";23
"Unit";"Queen";"Hatchery";23
"Unit";"Queen";"Hatchery";25
"Unit";"Zergling";"Larva";27
"Unit";"Zergling";"Larva";28
"Unit";"Zergling";"Larva";29
"Unit";"Zergling";"Larva";30
"Building";"Hatchery";NA;35
"Unit";"Queen";"Hatchery";39
"Unit";"Overlord";"Larva";41
"Unit";"Overlord";"Larva";42
"Building";"EvolutionChamber";NA;50
"Building";"SporeCrawler";NA;51
"Building";"CreepTumorQueen";NA;51
"Unit";"Zergling";"Larva";51
"Unit";"Zergling";"Larva";52
"Unit";"Zergling";"Larva";53
"Unit";"Zergling";"Larva";54
"Unit";"Zergling";"Larva";55
"Unit";"Zergling";"Larva";56
"Unit";"Zergling";"Larva";57
"Unit";"Zergling";"Larva";58
"Unit";"Overlord";"Larva";59
"Building";"SporeCrawler";NA;64
"Unit";"Overlord";"Larva";68
"Unit";"Queen";"Hatchery";68
"Building";"CreepTumor";NA;75
"Building";"SporeCrawler";NA;82
"Unit";"Overlord";"Larva";83
"Unit";"Queen";"Hatchery";83
"Unit";"Overlord";"Larva";89
"Unit";"Overlord";"Larva";89
"Building";"Extractor";NA;89
"Building";"Extractor";NA;89
"Unit";"Overlord";"Larva";89
"Unit";"Zergling";"Larva";89
"Unit";"Zergling";"Larva";90
"Unit";"Zergling";"Larva";91
"Unit";"Zergling";"Larva";92
"Unit";"Zergling";"Larva";93
"Unit";"Zergling";"Larva";94
"Unit";"Zergling";"Larva";95
"Unit";"Zergling";"Larva";96
"Unit";"Zergling";"Larva";97
"Unit";"Zergling";"Larva";98
"Unit";"Zergling";"Larva";99
"Unit";"Zergling";"Larva";100
"Unit";"Zergling";"Larva";101
"Unit";"Zergling";"Larva";102
"Unit";"Zergling";"Larva";103
"Unit";"Zergling";"Larva";104
"Unit";"Zergling";"Larva";105
"Unit";"Zergling";"Larva";106
"Unit";"Zergling";"Larva";107
"Unit";"Zergling";"Larva";108
"Unit";"Zergling";"Larva";109
"Unit";"Zergling";"Larva";110
"Unit";"Zergling";"Larva";111
"Unit";"Zergling";"Larva";112
"Unit";"Zergling";"Larva";113
"Unit";"Zergling";"Larva";114
"Unit";"Zergling";"Larva";115
"Unit";"Zergling";"Larva";116
"Unit";"Zergling";"Larva";117
"Unit";"Zergling";"Larva";118
"Building";"Extractor";NA;119
"Building";"HydraliskDen";NA;119
"Building";"Extractor";NA;119
"Building";"BanelingNest";NA;125
"Unit";"Overlord";"Larva";128
"Building";"EvolutionChamber";NA;139
"Unit";"Overlord";"Larva";140
"Building";"CreepTumor";NA;141
"Building";"Hatchery";NA;141
"Unit";"Hydralisk";"Larva";141
"Unit";"Hydralisk";"Larva";143
"Unit";"Hydralisk";"Larva";145
"Unit";"Hydralisk";"Larva";147
"Unit";"Hydralisk";"Larva";149
"Unit";"Hydralisk";"Larva";151
"Unit";"Zergling";"Larva";153
"Unit";"Zergling";"Larva";154
"Unit";"Zergling";"Larva";155
"Unit";"Zergling";"Larva";156
"Unit";"Zergling";"Larva";157
"Unit";"Zergling";"Larva";158
"Unit";"Zergling";"Larva";159
"Unit";"Zergling";"Larva";160
"Unit";"Zergling";"Larva";161
"Unit";"Zergling";"Larva";162
"Unit";"Zergling";"Larva";163
"Unit";"Zergling";"Larva";164
"Unit";"Zergling";"Larva";165
"Unit";"Zergling";"Larva";166
"Unit";"Zergling";"Larva";167
"Unit";"Zergling";"Larva";168
"Building";"CreepTumorQueen";NA;169
"Unit";"Overlord";"Larva";169
"Building";"CreepTumor";NA;169
"Unit";"Zergling";"Larva";169
"Unit";"Zergling";"Larva";170
"Unit";"Zergling";"Larva";171
"Unit";"Zergling";"Larva";172
"Unit";"Zergling";"Larva";173
"Unit";"Zergling";"Larva";174
"Unit";"Zergling";"Larva";175
"Unit";"Zergling";"Larva";176
"Unit";"Zergling";"Larva";177
"Unit";"Zergling";"Larva";178
"Unit";"Zergling";"Larva";179
"Unit";"Zergling";"Larva";180
"Building";"Hatchery";NA;181
"Unit";"Hydralisk";"Larva";181
"Unit";"Hydralisk";"Larva";183
"Unit";"Hydralisk";"Larva";185
"Unit";"Hydralisk";"Larva";187
"Unit";"Zergling";"Larva";189
"Unit";"Zergling";"Larva";190
"Unit";"Zergling";"Larva";191
"Unit";"Zergling";"Larva";192
"Unit";"Zergling";"Larva";193
"Unit";"Zergling";"Larva";194
"Unit";"Overlord";"Larva";195
"Unit";"Overlord";"Larva";195
"Unit";"Overlord";"Larva";195
"Unit";"Overlord";"Larva";195
"Unit";"Overlord";"Larva";195
"Unit";"Overlord";"Larva";195
"Building";"InfestationPit";NA;195
"Building";"Extractor";NA;208
"Unit";"Overlord";"Larva";208
"Unit";"Hydralisk";"Larva";210
"Unit";"Hydralisk";"Larva";212
"Unit";"Hydralisk";"Larva";214
"Unit";"Hydralisk";"Larva";216
"Unit";"Zergling";"Larva";218
"Unit";"Zergling";"Larva";219
"Unit";"Zergling";"Larva";220
"Unit";"Zergling";"Larva";221
"Unit";"Overlord";"Larva";222
"Unit";"Zergling";"Larva";222
"Unit";"Zergling";"Larva";223
"Unit";"Zergling";"Larva";224
"Unit";"Zergling";"Larva";225
"Unit";"Zergling";"Larva";226
"Unit";"Zergling";"Larva";227
"Unit";"Zergling";"Larva";228
"Unit";"Zergling";"Larva";229
"Unit";"Zergling";"Larva";230
"Unit";"Zergling";"Larva";231
"Unit";"Zergling";"Larva";232
"Unit";"Zergling";"Larva";233
"Unit";"Zergling";"Larva";234
"Unit";"Zergling";"Larva";235
"Unit";"Zergling";"Larva";236
"Unit";"Zergling";"Larva";237
"Unit";"Baneling";"Zergling";238
"Unit";"Baneling";"Zergling";238
"Unit";"Baneling";"Zergling";238
"Unit";"Baneling";"Zergling";238
"Unit";"Baneling";"Zergling";238
"Unit";"Baneling";"Zergling";238
"Unit";"Zergling";"Larva";238
"Unit";"Zergling";"Larva";239
"Building";"SporeCrawler";NA;240
"Unit";"Zergling";"Larva";240
"Unit";"Zergling";"Larva";241
"Unit";"Zergling";"Larva";242
"Unit";"Zergling";"Larva";243
"Unit";"Zergling";"Larva";244
"Unit";"Zergling";"Larva";245
"Unit";"Zergling";"Larva";246
"Unit";"Zergling";"Larva";247
"Unit";"Zergling";"Larva";248
"Unit";"Zergling";"Larva";249
"Unit";"Zergling";"Larva";250
"Unit";"Zergling";"Larva";251
"Unit";"Zergling";"Larva";252
"Unit";"Zergling";"Larva";253
"Unit";"Zergling";"Larva";254
"Unit";"Zergling";"Larva";255
"Unit";"Baneling";"Zergling";256
"Unit";"Baneling";"Zergling";256
"Unit";"Baneling";"Zergling";256
"Unit";"Baneling";"Zergling";256
"Unit";"Baneling";"Zergling";256
"Unit";"Baneling";"Zergling";256
"Building";"CreepTumorQueen";NA;256
"Building";"Spire";NA;256
"Unit";"Zergling";"Larva";256
"Unit";"Zergling";"Larva";257
"Unit";"Zergling";"Larva";258
"Unit";"Zergling";"Larva";259
"Unit";"Zergling";"Larva";260
"Unit";"Zergling";"Larva";261
"Unit";"Zergling";"Larva";262
"Unit";"Zergling";"Larva";263
"Unit";"Zergling";"Larva";264
"Unit";"Zergling";"Larva";265
"Unit";"Zergling";"Larva";266
"Unit";"Zergling";"Larva";267
"Unit";"Zergling";"Larva";268
"Unit";"Zergling";"Larva";269
"Unit";"Zergling";"Larva";270
"Unit";"Zergling";"Larva";271
"Unit";"Zergling";"Larva";272
"Unit";"Zergling";"Larva";273
"Unit";"Zergling";"Larva";274
"Unit";"Zergling";"Larva";275
"Unit";"Zergling";"Larva";276
"Unit";"Zergling";"Larva";277
"Building";"CreepTumorQueen";NA;278
"Unit";"Overlord";"Larva";278
"Unit";"Baneling";"Zergling";278
"Unit";"Baneling";"Zergling";278
"Unit";"Baneling";"Zergling";278
"Unit";"Baneling";"Zergling";278
"Unit";"Baneling";"Zergling";278
"Unit";"Baneling";"Zergling";278
"Unit";"Baneling";"Zergling";278
"Unit";"Baneling";"Zergling";278
"Unit";"Baneling";"Zergling";278
"Unit";"Zergling";"Larva";278
"Unit";"Zergling";"Larva";279
"Unit";"Zergling";"Larva";280
"Unit";"Zergling";"Larva";281
"Unit";"Zergling";"Larva";282
"Unit";"Zergling";"Larva";283
"Unit";"Zergling";"Larva";284
"Unit";"Zergling";"Larva";285
"Unit";"Zergling";"Larva";286
"Unit";"Zergling";"Larva";287
"Unit";"Zergling";"Larva";288
"Unit";"Zergling";"Larva";289
"Unit";"Zergling";"Larva";290
"Unit";"Zergling";"Larva";291
"Unit";"Zergling";"Larva";292
"Unit";"Zergling";"Larva";293
"Unit";"Zergling";"Larva";294
"Unit";"Zergling";"Larva";295
"Unit";"Zergling";"Larva";296
"Unit";"Zergling";"Larva";297
"Unit";"Zergling";"Larva";298
"Unit";"Zergling";"Larva";299
"Unit";"Overlord";"Larva";300
"Building";"CreepTumor";NA;300
"Building";"CreepTumor";NA;300
"Unit";"Queen";"Hatchery";300
"Unit";"Zergling";"Larva";302
"Unit";"Zergling";"Larva";303
"Unit";"Zergling";"Larva";304
"Unit";"Zergling";"Larva";305
"Unit";"Zergling";"Larva";306
"Unit";"Zergling";"Larva";307
"Unit";"Zergling";"Larva";308
"Unit";"Zergling";"Larva";309
"Unit";"Zergling";"Larva";310
"Unit";"Zergling";"Larva";311
"Unit";"Zergling";"Larva";312
"Unit";"Zergling";"Larva";313
"Unit";"Zergling";"Larva";314
"Unit";"Zergling";"Larva";315
"Unit";"Zergling";"Larva";316
"Unit";"Zergling";"Larva";317
"Building";"Hatchery";NA;318
"Unit";"Zergling";"Larva";318
"Unit";"Zergling";"Larva";319
"Unit";"Zergling";"Larva";320
"Unit";"Zergling";"Larva";321
"Unit";"Zergling";"Larva";322
"Unit";"Zergling";"Larva";323
"Unit";"Zergling";"Larva";324
"Unit";"Zergling";"Larva";325
"Unit";"Zergling";"Larva";326
"Unit";"Zergling";"Larva";327
"Unit";"Zergling";"Larva";328
"Unit";"Zergling";"Larva";329
"Unit";"Zergling";"Larva";330
"Unit";"Zergling";"Larva";331
"Unit";"Zergling";"Larva";332
"Unit";"Zergling";"Larva";333
"Unit";"Zergling";"Larva";334
"Unit";"Zergling";"Larva";335
"Unit";"Zergling";"Larva";336
"Unit";"Zergling";"Larva";337
"Unit";"Baneling";"Zergling";338
"Unit";"Baneling";"Zergling";338
"Unit";"Baneling";"Zergling";338
"Unit";"Baneling";"Zergling";338
"Unit";"Baneling";"Zergling";338
"Unit";"Baneling";"Zergling";338
"Unit";"Zergling";"Larva";338
"Unit";"Zergling";"Larva";339
"Unit";"Zergling";"Larva";340
"Unit";"Zergling";"Larva";341
"Unit";"Zergling";"Larva";342
"Unit";"Zergling";"Larva";343
"Unit";"Zergling";"Larva";344
"Unit";"Zergling";"Larva";345
"Unit";"Zergling";"Larva";346
"Unit";"Zergling";"Larva";347
"Unit";"Zergling";"Larva";348
"Unit";"Zergling";"Larva";349
"Unit";"Zergling";"Larva";350
"Unit";"Zergling";"Larva";351
"Unit";"Zergling";"Larva";352
"Unit";"Zergling";"Larva";353
"Unit";"Overlord";"Larva";354
"Unit";"Zergling";"Larva";354
"Unit";"Zergling";"Larva";355
"Unit";"Zergling";"Larva";356
"Unit";"Zergling";"Larva";357
"Unit";"Zergling";"Larva";358
"Unit";"Zergling";"Larva";359
"Unit";"Zergling";"Larva";360
"Unit";"Zergling";"Larva";361
"Unit";"Zergling";"Larva";362
"Unit";"Zergling";"Larva";363
"Unit";"Zergling";"Larva";364
"Unit";"Zergling";"Larva";365
"Unit";"Zergling";"Larva";366
"Unit";"Zergling";"Larva";367
"Unit";"Zergling";"Larva";368
"Unit";"Zergling";"Larva";369
"Unit";"Zergling";"Larva";370
"Unit";"Zergling";"Larva";371
"Unit";"Zergling";"Larva";372
"Unit";"Zergling";"Larva";373
"Unit";"Zergling";"Larva";374
"Unit";"Zergling";"Larva";375
"Unit";"Hydralisk";"Larva";376
"Unit";"Zergling";"Larva";378
"Unit";"Zergling";"Larva";379
"Unit";"Zergling";"Larva";380
"Unit";"Zergling";"Larva";381
"Unit";"Zergling";"Larva";382
"Unit";"Zergling";"Larva";383
"Unit";"Zergling";"Larva";384
"Unit";"Zergling";"Larva";385
"Unit";"Zergling";"Larva";386
"Unit";"Zergling";"Larva";387
"Unit";"Zergling";"Larva";388
"Unit";"Zergling";"Larva";389
"Building";"CreepTumor";NA;390
"Building";"CreepTumor";NA;390
"Unit";"Hydralisk";"Larva";390
"Unit";"Zergling";"Larva";392
"Unit";"Zergling";"Larva";393
"Building";"CreepTumor";NA;394
"Unit";"Hydralisk";"Larva";394
"Unit";"Zergling";"Larva";396
"Unit";"Zergling";"Larva";397
"Unit";"Zergling";"Larva";398
"Unit";"Zergling";"Larva";399
"Unit";"Zergling";"Larva";400
"Unit";"Zergling";"Larva";401
"Unit";"Zergling";"Larva";402
"Unit";"Zergling";"Larva";403
"Building";"CreepTumor";NA;404
"Unit";"Baneling";"Zergling";404
"Unit";"Baneling";"Zergling";404
"Unit";"Baneling";"Zergling";404
"Unit";"Baneling";"Zergling";404
"Unit";"Baneling";"Zergling";404
"Unit";"Baneling";"Zergling";404
"Unit";"Baneling";"Zergling";404
"Unit";"Baneling";"Zergling";404
"Unit";"Baneling";"Zergling";404
"Unit";"Baneling";"Zergling";404
"Unit";"Baneling";"Zergling";404
"Unit";"Baneling";"Zergling";404
"Unit";"Baneling";"Zergling";404
"Unit";"Baneling";"Zergling";404
"Unit";"Baneling";"Zergling";404
"Building";"Hatchery";NA;404
"Building";"CreepTumor";NA;404
"Building";"CreepTumor";NA;404
"Unit";"Zergling";"Larva";404
"Unit";"Zergling";"Larva";405
"Unit";"Zergling";"Larva";406
"Unit";"Zergling";"Larva";407
"Unit";"Zergling";"Larva";408
"Unit";"Zergling";"Larva";409
"Unit";"Zergling";"Larva";410
"Unit";"Zergling";"Larva";411
"Unit";"Zergling";"Larva";412
"Unit";"Zergling";"Larva";413
"Unit";"Zergling";"Larva";414
"Unit";"Zergling";"Larva";415
"Unit";"Zergling";"Larva";416
"Unit";"Zergling";"Larva";417
"Unit";"Zergling";"Larva";418
"Unit";"Zergling";"Larva";419
"Unit";"Overlord";"Larva";420
"Unit";"Corruptor";"Larva";420
"Unit";"Corruptor";"Larva";422
"Unit";"Corruptor";"Larva";424
"Unit";"Corruptor";"Larva";426
"Unit";"Corruptor";"Larva";428
"Unit";"Corruptor";"Larva";430
"Unit";"Corruptor";"Larva";432
"Unit";"Corruptor";"Larva";434
"Unit";"Corruptor";"Larva";436
"Unit";"Zergling";"Larva";438
"Unit";"Zergling";"Larva";439
"Unit";"Zergling";"Larva";440
"Unit";"Zergling";"Larva";441
"Unit";"Zergling";"Larva";442
"Unit";"Zergling";"Larva";443
"Unit";"Zergling";"Larva";444
"Unit";"Zergling";"Larva";445
"Unit";"Zergling";"Larva";446
"Unit";"Zergling";"Larva";447
"Unit";"Zergling";"Larva";448
"Unit";"Zergling";"Larva";449
"Unit";"Zergling";"Larva";450
"Unit";"Zergling";"Larva";451
"Unit";"Zergling";"Larva";452
"Unit";"Zergling";"Larva";453
"Unit";"Zergling";"Larva";454
"Unit";"Zergling";"Larva";455
"Unit";"Zergling";"Larva";456
"Unit";"Zergling";"Larva";457
"Unit";"Zergling";"Larva";458
"Unit";"Zergling";"Larva";459
"Unit";"Zergling";"Larva";460
"Unit";"Zergling";"Larva";461
"Unit";"Zergling";"Larva";462
"Unit";"Zergling";"Larva";463
"Unit";"Zergling";"Larva";464
"Unit";"Zergling";"Larva";465
"Unit";"Zergling";"Larva";466
"Unit";"Zergling";"Larva";467
"Unit";"Zergling";"Larva";468
"Unit";"Zergling";"Larva";469
"Unit";"Zergling";"Larva";470
"Unit";"Zergling";"Larva";471
"Unit";"Zergling";"Larva";472
"Unit";"Zergling";"Larva";473
"Unit";"Zergling";"Larva";474
"Unit";"Zergling";"Larva";475
"Unit";"Zergling";"Larva";476
"Unit";"Zergling";"Larva";477
"Unit";"Zergling";"Larva";478
"Unit";"Zergling";"Larva";479
"Unit";"Zergling";"Larva";480
"Unit";"Zergling";"Larva";481
"Unit";"Zergling";"Larva";482
"Unit";"Zergling";"Larva";483
"Unit";"Zergling";"Larva";484
"Unit";"Zergling";"Larva";485
"Unit";"Zergling";"Larva";486
"Unit";"Zergling";"Larva";487
"Unit";"Zergling";"Larva";488
"Unit";"Zergling";"Larva";489
"Building";"Extractor";NA;490
"Building";"Extractor";NA;490
"Unit";"Zergling";"Larva";490
"Unit";"Zergling";"Larva";491
"Unit";"Zergling";"Larva";492
"Unit";"Zergling";"Larva";493
"Unit";"Zergling";"Larva";494
"Unit";"Zergling";"Larva";495
"Unit";"Zergling";"Larva";496
"Unit";"Zergling";"Larva";497
"Unit";"Zergling";"Larva";498
"Unit";"Zergling";"Larva";499
"Unit";"Zergling";"Larva";500
"Unit";"Zergling";"Larva";501
"Unit";"Zergling";"Larva";502
"Unit";"Zergling";"Larva";503
"Unit";"Zergling";"Larva";504
"Unit";"Zergling";"Larva";505
"Unit";"Zergling";"Larva";506
"Unit";"Zergling";"Larva";507
"Unit";"Zergling";"Larva";508
"Unit";"Zergling";"Larva";509
"Unit";"Zergling";"Larva";510
"Unit";"Zergling";"Larva";511
"Unit";"Zergling";"Larva";512
"Unit";"Zergling";"Larva";513
"Unit";"Zergling";"Larva";514
"Unit";"Zergling";"Larva";515
"Unit";"Zergling";"Larva";516
"Unit";"Zergling";"Larva";517
"Unit";"Zergling";"Larva";518
"Unit";"Zergling";"Larva";519
"Unit";"Zergling";"Larva";520
"Unit";"Zergling";"Larva";521
"Unit";"Zergling";"Larva";522
"Unit";"Zergling";"Larva";523
"Upgrade";"SprayZerg";NA;524
"Upgrade";"SprayZerg";NA;524
"Upgrade";"SprayZerg";NA;524
"Upgrade";"zerglingmovementspeed";NA;524
"Upgrade";"SprayZerg";NA;524
"Upgrade";"ZergMeleeWeaponsLevel1";NA;524
"Upgrade";"SprayZerg";NA;524
"Upgrade";"SprayZerg";NA;524
"Upgrade";"SprayZerg";NA;524
"Upgrade";"EvolveMuscularAugments";NA;524
"Upgrade";"SprayZerg";NA;524
"Upgrade";"ZergMeleeWeaponsLevel2";NA;524
"Upgrade";"CentrificalHooks";NA;524
"Upgrade";"ZergMissileWeaponsLevel1";NA;524
"Upgrade";"SprayZerg";NA;524
"Upgrade";"SprayZerg";NA;524
"Upgrade";"SprayZerg";NA;524
"Upgrade";"ZergMissileWeaponsLevel2";NA;524
"Upgrade";"zerglingattackspeed";NA;524
"Upgrade";"SprayZerg";NA;524
