"type";"unit_name";"on_building";"total_supply";"supply"
"Unit";"Overlord";"Larva";12;0
"Building";"SpawningPool";NA;14;0
"Building";"Extractor";NA;18;0
"Unit";"Zergling";"Larva";19;1
"Unit";"Zergling";"Larva";19;1
"Unit";"Zergling";"Larva";19;1
"Unit";"Zergling";"Larva";19;1
"Unit";"Zergling";"Larva";19;1
"Unit";"Zergling";"Larva";19;1
"Unit";"Overlord";"Larva";19;0
"Unit";"Queen";"Hatchery";19;2
"Building";"Hatchery";NA;18;0
"Unit";"Queen";"Hatchery";26;2
"Building";"CreepTumorQueen";NA;34;0
"Unit";"Overlord";"Larva";39;0
"Unit";"Zergling";"Larva";39;1
"Unit";"Zergling";"Larva";39;1
"Building";"CreepTumorQueen";NA;42;0
"Building";"CreepTumor";NA;42;0
"Unit";"Overlord";"Larva";42;0
"Building";"SporeCrawler";NA;46;0
"Building";"SporeCrawler";NA;49;0
"Building";"CreepTumor";NA;50;0
"Unit";"Queen";"Hatchery";49;2
"Building";"Extractor";NA;50;0
"Building";"Hatchery";NA;41;0
"Unit";"Overlord";"Larva";53;0
"Building";"Extractor";NA;57;0
"Unit";"Overlord";"Larva";60;0
"Unit";"Zergling";"Larva";68;1
"Unit";"Zergling";"Larva";68;1
"Unit";"Zergling";"Larva";68;1
"Unit";"Zergling";"Larva";68;1
"Unit";"Zergling";"Larva";68;1
"Unit";"Zergling";"Larva";68;1
"Unit";"Zergling";"Larva";71;1
"Unit";"Zergling";"Larva";71;1
"Unit";"Zergling";"Larva";71;1
"Unit";"Zergling";"Larva";71;1
"Unit";"Zergling";"Larva";71;1
"Unit";"Zergling";"Larva";71;1
"Unit";"Zergling";"Larva";71;1
"Unit";"Zergling";"Larva";71;1
"Unit";"Zergling";"Larva";71;1
"Unit";"Zergling";"Larva";71;1
"Unit";"Zergling";"Larva";71;1
"Unit";"Zergling";"Larva";71;1
"Unit";"Zergling";"Larva";71;1
"Unit";"Zergling";"Larva";71;1
"Unit";"Zergling";"Larva";71;1
"Unit";"Zergling";"Larva";71;1
"Unit";"Zergling";"Larva";71;1
"Unit";"Zergling";"Larva";71;1
"Building";"HydraliskDen";NA;71;0
"Unit";"Zergling";"Larva";77;1
"Unit";"Zergling";"Larva";77;1
"Unit";"Zergling";"Larva";77;1
"Unit";"Zergling";"Larva";77;1
"Unit";"Overlord";"Larva";89;0
"Unit";"Overlord";"Larva";89;0
"Building";"SpineCrawler";NA;71;0
"Unit";"Hydralisk";"Larva";95;2
"Unit";"Hydralisk";"Larva";95;2
"Unit";"Hydralisk";"Larva";95;2
"Unit";"Hydralisk";"Larva";99;2
"Unit";"Hydralisk";"Larva";99;2
"Unit";"Hydralisk";"Larva";99;2
"Unit";"Zergling";"Larva";99;1
"Unit";"Zergling";"Larva";99;1
"Unit";"Zergling";"Larva";99;1
"Unit";"Zergling";"Larva";99;1
"Unit";"Zergling";"Larva";99;1
"Unit";"Zergling";"Larva";99;1
"Unit";"Hydralisk";"Larva";99;2
"Unit";"Hydralisk";"Larva";99;2
"Unit";"Zergling";"Larva";105;1
"Unit";"Zergling";"Larva";105;1
"Unit";"Zergling";"Larva";105;1
"Unit";"Zergling";"Larva";105;1
"Unit";"Zergling";"Larva";105;1
"Unit";"Zergling";"Larva";105;1
"Unit";"Zergling";"Larva";105;1
"Unit";"Zergling";"Larva";105;1
"Unit";"Zergling";"Larva";105;1
"Unit";"Zergling";"Larva";105;1
"Unit";"Zergling";"Larva";105;1
"Unit";"Zergling";"Larva";105;1
"Unit";"Zergling";"Larva";105;1
"Unit";"Zergling";"Larva";105;1
"Unit";"Zergling";"Larva";105;1
"Unit";"Zergling";"Larva";105;1
"Unit";"Overlord";"Larva";131;0
"Unit";"Overlord";"Larva";131;0
"Unit";"Hydralisk";"Larva";137;2
"Building";"Extractor";NA;137;0
"Unit";"Hydralisk";"Larva";137;2
"Unit";"Hydralisk";"Larva";137;2
"Unit";"Hydralisk";"Larva";137;2
"Unit";"Hydralisk";"Larva";137;2
"Unit";"Overlord";"Larva";139;0
"Unit";"Hydralisk";"Larva";139;2
"Unit";"Overlord";"Larva";147;0
"Unit";"Overlord";"Larva";147;0
"Upgrade";"EvolveMuscularAugments";"HydraliskDen";137;0
"Unit";"Zergling";"Larva";166;1
"Unit";"Zergling";"Larva";166;1
"Unit";"Zergling";"Larva";166;1
"Unit";"Zergling";"Larva";166;1
"Unit";"Zergling";"Larva";166;1
"Unit";"Zergling";"Larva";166;1
"Unit";"Zergling";"Larva";166;1
"Unit";"Zergling";"Larva";166;1
"Unit";"Zergling";"Larva";166;1
"Unit";"Zergling";"Larva";166;1
"Unit";"Zergling";"Larva";166;1
"Unit";"Zergling";"Larva";166;1
"Unit";"Zergling";"Larva";166;1
"Unit";"Zergling";"Larva";166;1
"Unit";"Zergling";"Larva";166;1
"Unit";"Zergling";"Larva";166;1
"Unit";"Hydralisk";"Larva";178;2
"Unit";"Hydralisk";"Larva";178;2
"Unit";"Hydralisk";"Larva";178;2
"Building";"EvolutionChamber";NA;178;0
"Unit";"Zergling";"Larva";184;1
"Unit";"Zergling";"Larva";184;1
"Unit";"Zergling";"Larva";184;1
"Unit";"Zergling";"Larva";184;1
"Unit";"Zergling";"Larva";184;1
"Unit";"Zergling";"Larva";184;1
"Unit";"Zergling";"Larva";184;1
"Unit";"Zergling";"Larva";184;1
"Unit";"Zergling";"Larva";184;1
"Unit";"Zergling";"Larva";184;1
"Unit";"Zergling";"Larva";184;1
"Unit";"Zergling";"Larva";184;1
"Building";"Extractor";NA;184;0
"Unit";"Overlord";"Larva";184;0
"Building";"CreepTumorQueen";NA;202;0
"Building";"Extractor";NA;190;0
"Unit";"Overlord";"Larva";205;0
"Upgrade";"EvolveGroovedSpines";"HydraliskDen";184;0
"Unit";"Queen";"Hatchery";202;2
"Unit";"Overlord";"Larva";210;0
"Unit";"Overlord";"Larva";210;0
"Building";"Spire";NA;184;0
"Unit";"Overlord";"Larva";210;0
"Building";"Hatchery";NA;184;0
"Unit";"Mutalisk";"Larva";218;2
"Unit";"Mutalisk";"Larva";218;2
"Unit";"Mutalisk";"Larva";218;2
"Unit";"Mutalisk";"Larva";218;2
"Unit";"Mutalisk";"Larva";218;2
"Unit";"Mutalisk";"Larva";218;2
"Unit";"Mutalisk";"Larva";218;2
"Unit";"Mutalisk";"Larva";218;2
"Unit";"Mutalisk";"Larva";218;2
"Unit";"Mutalisk";"Larva";218;2
"Unit";"Mutalisk";"Larva";218;2
"Unit";"Overlord";"Larva";218;0
"Unit";"Mutalisk";"Larva";218;2
"Unit";"Mutalisk";"Larva";218;2
"Unit";"Mutalisk";"Larva";218;2
"Building";"Extractor";NA;218;0
"Building";"Extractor";NA;234;0
"Unit";"Mutalisk";"Larva";234;2
"Unit";"Mutalisk";"Larva";234;2
"Unit";"Zergling";"Larva";245;1
"Unit";"Zergling";"Larva";245;1
"Unit";"Zergling";"Larva";245;1
"Unit";"Zergling";"Larva";245;1
"Unit";"Zergling";"Larva";245;1
"Unit";"Zergling";"Larva";245;1
"Unit";"Zergling";"Larva";245;1
"Unit";"Zergling";"Larva";245;1
"Unit";"Zergling";"Larva";245;1
"Unit";"Zergling";"Larva";245;1
"Unit";"Hydralisk";"Larva";245;2
"Unit";"Queen";"Hatchery";218;2
"Unit";"Hydralisk";"Larva";245;2
"Unit";"Zergling";"Larva";251;1
"Unit";"Zergling";"Larva";251;1
"Unit";"Zergling";"Larva";251;1
"Unit";"Zergling";"Larva";251;1
"Unit";"Zergling";"Larva";251;1
"Unit";"Zergling";"Larva";251;1
"Unit";"Zergling";"Larva";251;1
"Unit";"Zergling";"Larva";251;1
"Unit";"Zergling";"Larva";251;1
"Unit";"Zergling";"Larva";251;1
"Upgrade";"ZergMeleeWeaponsLevel1";"EvolutionChamber";210;0
"Building";"CreepTumorQueen";NA;281;0
"Unit";"Mutalisk";"Larva";257;2
"Unit";"Mutalisk";"Larva";259;2
"Unit";"Mutalisk";"Larva";263;2
"Unit";"Zergling";"Larva";281;1
"Unit";"Zergling";"Larva";281;1
"Unit";"Zergling";"Larva";281;1
"Unit";"Zergling";"Larva";281;1
"Unit";"Zergling";"Larva";281;1
"Unit";"Zergling";"Larva";281;1
"Unit";"Zergling";"Larva";281;1
"Unit";"Zergling";"Larva";281;1
"Unit";"Zergling";"Larva";281;1
"Unit";"Zergling";"Larva";281;1
"Unit";"Zergling";"Larva";281;1
"Unit";"Zergling";"Larva";281;1
"Unit";"Zergling";"Larva";281;1
"Unit";"Zergling";"Larva";281;1
"Unit";"Mutalisk";"Larva";301;2
"Unit";"Mutalisk";"Larva";301;2
"Unit";"Mutalisk";"Larva";301;2
"Unit";"Mutalisk";"Larva";301;2
"Unit";"Mutalisk";"Larva";301;2
"Unit";"Zergling";"Larva";301;1
"Unit";"Zergling";"Larva";301;1
"Unit";"Zergling";"Larva";301;1
"Unit";"Zergling";"Larva";301;1
"Unit";"Zergling";"Larva";301;1
"Unit";"Zergling";"Larva";301;1
"Unit";"Mutalisk";"Larva";301;2
"Unit";"Mutalisk";"Larva";301;2
"Unit";"Mutalisk";"Larva";317;2
"Unit";"Mutalisk";"Larva";317;2
"Unit";"Mutalisk";"Larva";317;2
"Unit";"Mutalisk";"Larva";317;2
"Unit";"Zergling";"Larva";321;1
"Unit";"Zergling";"Larva";321;1
"Unit";"Zergling";"Larva";321;1
"Unit";"Zergling";"Larva";321;1
"Unit";"Zergling";"Larva";321;1
"Unit";"Zergling";"Larva";321;1
"Unit";"Zergling";"Larva";321;1
"Unit";"Zergling";"Larva";321;1
"Unit";"Zergling";"Larva";321;1
"Unit";"Zergling";"Larva";321;1
"Unit";"Zergling";"Larva";321;1
"Unit";"Zergling";"Larva";321;1
"Unit";"Zergling";"Larva";321;1
"Unit";"Zergling";"Larva";321;1
"Unit";"Zergling";"Larva";321;1
"Unit";"Zergling";"Larva";321;1
"Unit";"Zergling";"Larva";321;1
"Unit";"Zergling";"Larva";321;1
"Unit";"Zergling";"Larva";321;1
"Unit";"Zergling";"Larva";321;1
