"type";"unit_name";"on_building";"total_supply";"supply"
"Building";"Pylon";NA;13;0
"Building";"Assimilator";NA;16;0
"Building";"Assimilator";NA;16;0
"Building";"Gateway";NA;15;0
"Building";"Pylon";NA;20;0
"Building";"Gateway";NA;18;0
"Unit";"Zealot";"Gateway";20;2
"Building";"CyberneticsCore";NA;19;0
"Unit";"Stalker";"Gateway";24;2
"Building";"Pylon";NA;24;0
"Building";"Pylon";NA;26;0
"Unit";"Stalker";"Gateway";26;2
