"type";"unit_name";"on_building";"total_supply";"supply"
"Building";"Pylon";NA;12;0
"Building";"Assimilator";NA;15;0
"Building";"Gateway";NA;14;0
"Building";"Pylon";NA;17;0
"Unit";"Zealot";"Gateway";17;2
"Unit";"Zealot";"Gateway";21;2
"Building";"CyberneticsCore";NA;21;0
"Building";"Pylon";NA;23;0
"Unit";"Stalker";"Gateway";23;2
"Building";"Assimilator";NA;23;0
"Unit";"Stalker";"Gateway";24;2
"Building";"ShieldBattery";NA;27;0
"Building";"Pylon";NA;27;0
