"type";"unit_name";"on_building";"total_supply";"supply"
"Building";"Pylon";NA;13;0
"Building";"Assimilator";NA;16;0
"Building";"Gateway";NA;15;0
"Building";"Assimilator";NA;18;0
"Building";"Gateway";NA;17;0
"Building";"Pylon";NA;20;0
"Building";"CyberneticsCore";NA;19;0
"Building";"Pylon";NA;23;0
"Unit";"Stalker";"Gateway";22;2
"Unit";"Stalker";"Gateway";22;2
"Building";"Pylon";NA;23;0
"Unit";"Stalker";"Gateway";28;2
"Unit";"Stalker";"Gateway";28;2
"Unit";"Stalker";"Gateway";28;2
"Unit";"Stalker";"Gateway";30;2
"Building";"Pylon";NA;36;0
"Building";"Pylon";NA;37;0
"Building";"ShieldBattery";NA;37;0
"Unit";"Stalker";"Gateway";38;2
"Unit";"Stalker";"Gateway";38;2
"Building";"Nexus";NA;37;0
"Building";"TwilightCouncil";NA;43;0
"Building";"RoboticsFacility";NA;43;0
"Building";"Forge";NA;47;0
"Building";"Pylon";NA;49;0
"Unit";"Immortal";"Robotics Facility";46;4
"Building";"TemplarArchive";NA;50;0
"Building";"HighTemplar";NA;61;0
"Building";"HighTemplar";NA;61;0
"Unit";"Immortal";"Robotics Facility";52;4
"Building";"Assimilator";NA;59;0
"Unit";"Archon";"High Templar";62;0
"Building";"Assimilator";NA;60;0
"Upgrade";"Charge";"TwilightCouncil";49;0
"Building";"Gateway";NA;59;0
"Building";"Gateway";NA;59;0
"Building";"Pylon";NA;68;0
"Building";"Pylon";NA;68;0
"Building";"Pylon";NA;69;0
"Building";"Pylon";NA;69;0
"Upgrade";"ProtossGroundWeaponsLevel1";"Forge";58;0
"Building";"HighTemplar";NA;69;0
"Building";"HighTemplar";NA;69;0
"Unit";"Zealot";"Gateway";69;2
"Unit";"Zealot";"Gateway";69;2
"Building";"Gateway";NA;68;0
"Building";"Pylon";NA;69;0
"Unit";"Archon";"High Templar";73;0
"Building";"Gateway";NA;69;0
"Building";"Gateway";NA;69;0
"Building";"Gateway";NA;69;0
"Building";"HighTemplar";NA;73;0
"Building";"HighTemplar";NA;73;0
"Unit";"Zealot";"Gateway";73;2
"Unit";"Zealot";"Gateway";73;2
"Unit";"Zealot";"Gateway";73;2
"Unit";"Zealot";"Gateway";73;2
"Unit";"Zealot";"Gateway";73;2
"Unit";"Archon";"High Templar";81;0
"Unit";"Zealot";"Gateway";83;2
"Unit";"Zealot";"Gateway";85;2
"Unit";"Zealot";"Gateway";85;2
"Unit";"Zealot";"Gateway";85;2
"Unit";"Zealot";"Gateway";85;2
"Unit";"Zealot";"Gateway";85;2
"Unit";"Zealot";"Gateway";85;2
"Unit";"Zealot";"Gateway";97;2
"Unit";"Zealot";"Gateway";97;2
"Unit";"Zealot";"Gateway";97;2
"Unit";"Zealot";"Gateway";97;2
"Unit";"Zealot";"Gateway";97;2
"Unit";"Zealot";"Gateway";97;2
"Unit";"Zealot";"Gateway";97;2
"Building";"HighTemplar";NA;112;0
"Building";"HighTemplar";NA;112;0
"Unit";"Sentry";"Gateway";112;2
"Unit";"Sentry";"Gateway";112;2
"Building";"Pylon";NA;112;0
"Unit";"Stalker";"Gateway";116;2
"Unit";"Zealot";"Gateway";116;2
"Unit";"Zealot";"Gateway";116;2
"Unit";"Zealot";"Gateway";116;2
"Unit";"Archon";"High Templar";116;0
"Building";"Pylon";NA;112;0
"Unit";"Stalker";"Gateway";124;2
"Unit";"Immortal";"Robotics Facility";112;4
"Unit";"Zealot";"Gateway";128;2
"Unit";"Zealot";"Gateway";128;2
"Unit";"Zealot";"Gateway";128;2
"Unit";"Zealot";"Gateway";132;2
"Unit";"Sentry";"Gateway";138;2
"Unit";"Adept";"Gateway";142;2
"Unit";"Adept";"Gateway";142;2
"Unit";"Adept";"Gateway";142;2
"Building";"Nexus";NA;111;0
"Building";"DarkShrine";NA;112;0
"Unit";"Immortal";"Robotics Facility";128;4
"Unit";"Zealot";"Gateway";152;2
"Unit";"Zealot";"Gateway";152;2
"Unit";"Zealot";"Gateway";152;2
"Unit";"Zealot";"Gateway";152;2
"Unit";"Adept";"Gateway";160;2
"Unit";"Adept";"Gateway";160;2
"Building";"HighTemplar";NA;160;0
"Building";"HighTemplar";NA;160;0
"Upgrade";"ProtossGroundWeaponsLevel2";"Forge";122;0
"Unit";"Archon";"High Templar";164;0
"Unit";"Immortal";"Robotics Facility";152;4
"Building";"DarkTemplar";NA;171;0
"Building";"DarkTemplar";NA;171;0
"Building";"DarkTemplar";NA;172;0
"Building";"Assimilator";NA;172;0
"Building";"Assimilator";NA;172;0
"Unit";"Zealot";"Gateway";177;2
"Unit";"Zealot";"Gateway";177;2
"Unit";"Zealot";"Gateway";177;2
"Unit";"Zealot";"Gateway";177;2
"Unit";"Zealot";"Gateway";177;2
"Unit";"Zealot";"Gateway";187;2
"Unit";"Zealot";"Gateway";187;2
"Unit";"Zealot";"Gateway";187;2
"Building";"Pylon";NA;193;0
"Building";"Pylon";NA;193;0
"Building";"Pylon";NA;193;0
"Unit";"Stalker";"Gateway";198;2
"Unit";"Stalker";"Gateway";198;2
"Unit";"Stalker";"Gateway";198;2
"Building";"Forge";NA;195;0
"Building";"Stargate";NA;195;0
"Unit";"Zealot";"Gateway";204;2
"Unit";"Immortal";"Robotics Facility";195;4
"Building";"Pylon";NA;204;0
"Building";"ShieldBattery";NA;195;0
"Building";"ShieldBattery";NA;198;0
"Building";"Pylon";NA;204;0
"Building";"Pylon";NA;204;0
"Building";"ShieldBattery";NA;198;0
"Unit";"Zealot";"Gateway";210;2
"Unit";"Zealot";"Gateway";210;2
"Unit";"Zealot";"Gateway";210;2
"Unit";"Zealot";"Gateway";210;2
"Building";"Pylon";NA;204;0
"Building";"HighTemplar";NA;218;0
"Building";"HighTemplar";NA;218;0
"Unit";"Zealot";"Gateway";218;2
"Unit";"Zealot";"Gateway";218;2
"Building";"Pylon";NA;218;0
"Unit";"Archon";"High Templar";222;0
"Unit";"Immortal";"Robotics Facility";214;4
"Building";"Pylon";NA;222;0
"Upgrade";"ProtossAirWeaponsLevel1";"CyberneticsCore";198;0
"Upgrade";"ProtossGroundWeaponsLevel3";"Forge";193;0
"Building";"PhotonCannon";NA;222;0
"Building";"PhotonCannon";NA;222;0
"Building";"DarkTemplar";NA;226;0
"Unit";"Immortal";"Robotics Facility";222;4
"Building";"DarkTemplar";NA;226;0
"Unit";"Stalker";"Gateway";230;2
"Unit";"Stalker";"Gateway";230;2
"Unit";"Stalker";"Gateway";230;2
"Upgrade";"ProtossShieldsLevel1";"Forge";222;0
"Unit";"Immortal";"Robotics Facility";226;4
"Unit";"Stalker";"Gateway";240;2
"Unit";"Stalker";"Gateway";240;2
"Unit";"Stalker";"Gateway";240;2
"Unit";"Stalker";"Gateway";240;2
"Unit";"Stalker";"Gateway";240;2
"Building";"Pylon";NA;236;0
"Building";"FleetBeacon";NA;230;0
"Building";"Pylon";NA;250;0
"Upgrade";"ProtossAirArmorsLevel1";"CyberneticsCore";230;0
"Building";"PhotonCannon";NA;250;0
"Building";"Nexus";NA;230;0
"Building";"PhotonCannon";NA;250;0
"Building";"ShieldBattery";NA;250;0
"Unit";"Zealot";"Gateway";250;2
"Unit";"Zealot";"Gateway";250;2
"Unit";"Zealot";"Gateway";250;2
"Unit";"Zealot";"Gateway";250;2
"Building";"DarkTemplar";NA;250;0
"Building";"DarkTemplar";NA;258;0
"Upgrade";"ProtossGroundArmorsLevel1";"Forge";250;0
"Building";"DarkTemplar";NA;258;0
"Unit";"Zealot";"Gateway";258;2
"Unit";"Zealot";"Gateway";258;2
"Unit";"Zealot";"Gateway";258;2
"Unit";"Zealot";"Gateway";258;2
"Unit";"Zealot";"Gateway";258;2
"Unit";"Zealot";"Gateway";258;2
"Upgrade";"ProtossShieldsLevel2";"Forge";250;0
"Building";"Nexus";NA;250;0
"Unit";"Mothership";"Mothership Core";250;6
"Unit";"Zealot";"Gateway";276;2
"Unit";"Zealot";"Gateway";276;2
"Unit";"Zealot";"Gateway";276;2
"Unit";"Zealot";"Gateway";276;2
"Unit";"Zealot";"Gateway";276;2
"Unit";"Zealot";"Gateway";276;2
"Unit";"Zealot";"Gateway";276;2
"Unit";"Zealot";"Gateway";276;2
"Unit";"Carrier";"Stargate";258;6
"Building";"PhotonCannon";NA;276;0
"Building";"PhotonCannon";NA;276;0
"Building";"Assimilator";NA;298;0
"Building";"Assimilator";NA;298;0
"Unit";"Zealot";"Gateway";298;2
"Unit";"Zealot";"Gateway";298;2
"Unit";"Zealot";"Gateway";298;2
"Unit";"Zealot";"Gateway";298;2
"Unit";"Zealot";"Gateway";298;2
"Unit";"Zealot";"Gateway";298;2
"Unit";"Zealot";"Gateway";298;2
"Unit";"Zealot";"Gateway";298;2
"Building";"Pylon";NA;298;0
"Building";"Pylon";NA;298;0
"Building";"Pylon";NA;302;0
"Building";"HighTemplar";NA;314;0
"Building";"HighTemplar";NA;314;0
"Building";"HighTemplar";NA;314;0
"Building";"HighTemplar";NA;314;0
"Unit";"Zealot";"Gateway";314;2
"Unit";"Zealot";"Gateway";314;2
"Unit";"Zealot";"Gateway";314;2
"Unit";"Zealot";"Gateway";314;2
"Unit";"Observer";"Robotics Facility";314;1
"Unit";"Archon";"High Templar";322;0
"Unit";"Archon";"High Templar";322;0
"Unit";"Observer";"Robotics Facility";322;1
"Unit";"Zealot";"Gateway";323;2
"Unit";"Zealot";"Gateway";323;2
"Unit";"Zealot";"Gateway";323;2
"Unit";"Zealot";"Gateway";323;2
"Unit";"Carrier";"Stargate";298;6
"Unit";"Zealot";"Gateway";338;2
"Unit";"Zealot";"Gateway";338;2
