"type";"unit_name";"on_building";"total_supply";"supply"
"Building";"Pylon";NA;13;0
"Building";"Assimilator";NA;15;0
"Building";"Pylon";NA;16;0
"Building";"Gateway";NA;15;0
"Building";"Pylon";NA;17;0
"Unit";"Zealot";"Gateway";18;2
"Unit";"Zealot";"Gateway";18;2
"Unit";"Zealot";"Gateway";22;2
"Building";"Pylon";NA;24;0
