"type";"unit_name";"on_building";"total_supply";"supply"
"Building";"Pylon";NA;13;0
"Building";"Assimilator";NA;15;0
"Building";"Gateway";NA;15;0
"Building";"Forge";NA;17;0
"Unit";"Zealot";"Gateway";19;2
"Building";"Pylon";NA;22;0
"Building";"PhotonCannon";NA;20;0
"Building";"PhotonCannon";NA;22;0
"Building";"PhotonCannon";NA;22;0
