"type";"unit_name";"on_building";"total_supply";"supply"
"Building";"Pylon";NA;13;0
"Building";"Assimilator";NA;16;0
"Building";"Assimilator";NA;16;0
"Building";"Gateway";NA;15;0
"Unit";"Zealot";"Gateway";19;2
"Building";"Pylon";NA;21;0
"Building";"CyberneticsCore";NA;20;0
"Unit";"Stalker";"Gateway";23;2
"Building";"Pylon";NA;25;0
"Building";"Gateway";NA;23;0
"Building";"Stargate";NA;29;0
"Unit";"Stalker";"Gateway";30;2
"Unit";"Stalker";"Gateway";30;2
"Building";"Pylon";NA;30;0
