"type";"unit_name";"on_building";"total_supply";"supply"
"Building";"Pylon";NA;13;0
"Building";"Assimilator";NA;16;0
"Building";"Assimilator";NA;17;0
"Building";"Gateway";NA;15;0
"Building";"Pylon";NA;20;0
"Building";"CyberneticsCore";NA;19;0
"Building";"Pylon";NA;21;0
"Building";"Assimilator";NA;21;0
"Building";"Pylon";NA;21;0
"Building";"Stargate";NA;21;0
"Building";"ShieldBattery";NA;21;0
