"type";"unit_name";"on_building";"total_supply";"supply"
"Building";"Pylon";NA;13;0
"Building";"Assimilator";NA;16;0
"Building";"Assimilator";NA;17;0
"Building";"Gateway";NA;15;0
"Building";"Gateway";NA;18;0
"Building";"Pylon";NA;21;0
"Building";"CyberneticsCore";NA;20;0
"Building";"Pylon";NA;23;0
"Unit";"Stalker";"Gateway";23;2
"Unit";"Stalker";"Gateway";23;2
"Building";"Stargate";NA;24;0
"Building";"Pylon";NA;28;0
"Building";"ShieldBattery";NA;28;0
"Unit";"Oracle";"Stargate";28;3
"Building";"ShieldBattery";NA;29;0
"Building";"Nexus";NA;28;0
"Unit";"Stalker";"Gateway";34;2
"Unit";"Oracle";"Stargate";29;3
"Unit";"Stalker";"Gateway";36;2
"Building";"RoboticsFacility";NA;33;0
"Unit";"Observer";"Robotics Facility";43;1
"Unit";"Adept";"Gateway";48;2
"Unit";"Adept";"Gateway";48;2
"Building";"Pylon";NA;49;0
"Unit";"Sentry";"Gateway";56;2
"Unit";"Sentry";"Gateway";56;2
"Building";"Assimilator";NA;55;0
"Building";"Assimilator";NA;55;0
"Building";"Forge";NA;49;0
"Unit";"Immortal";"Robotics Facility";56;4
"Building";"OracleStasisTrap";NA;69;0
"Unit";"Stalker";"Gateway";69;2
"Unit";"Stalker";"Gateway";69;2
"Building";"Pylon";NA;69;0
"Unit";"Immortal";"Robotics Facility";63;4
"Building";"Gateway";NA;63;0
"Building";"Gateway";NA;63;0
"Building";"Gateway";NA;63;0
"Building";"Gateway";NA;63;0
"Building";"TwilightCouncil";NA;69;0
"Building";"Pylon";NA;78;0
"Unit";"Stalker";"Gateway";78;2
"Unit";"Stalker";"Gateway";78;2
"Unit";"Stalker";"Gateway";82;2
"Unit";"Stalker";"Gateway";84;2
"Unit";"Immortal";"Robotics Facility";74;4
"Unit";"Stalker";"Gateway";90;2
"Unit";"Stalker";"Gateway";90;2
"Upgrade";"ProtossGroundWeaponsLevel1";"Forge";69;0
"Unit";"Stalker";"Gateway";90;2
"Unit";"Stalker";"Gateway";90;2
"Unit";"Stalker";"Gateway";98;2
"Unit";"Stalker";"Gateway";98;2
"Unit";"Stalker";"Gateway";102;2
"Unit";"Stalker";"Gateway";102;2
"Unit";"Stalker";"Gateway";102;2
"Unit";"Stalker";"Gateway";108;2
"Unit";"Stalker";"Gateway";108;2
"Upgrade";"Charge";"TwilightCouncil";90;0
"Building";"Pylon";NA;112;0
"Unit";"Zealot";"Gateway";114;2
"Unit";"Zealot";"Gateway";114;2
"Unit";"Zealot";"Gateway";114;2
"Unit";"Zealot";"Gateway";114;2
"Unit";"Zealot";"Gateway";114;2
"Unit";"Zealot";"Gateway";114;2
"Building";"TemplarArchive";NA;112;0
"Building";"HighTemplar";NA;128;0
"Building";"HighTemplar";NA;128;0
"Building";"HighTemplar";NA;128;0
"Building";"HighTemplar";NA;128;0
"Unit";"Zealot";"Gateway";128;2
"Building";"Nexus";NA;112;0
"Unit";"Archon";"High Templar";128;0
"Unit";"Archon";"High Templar";128;0
"Unit";"Stalker";"Gateway";130;2
"Unit";"Immortal";"Robotics Facility";127;4
"Building";"Pylon";NA;130;0
"Upgrade";"ProtossGroundWeaponsLevel2";"Forge";112;0
"Unit";"Zealot";"Gateway";136;2
"Building";"HighTemplar";NA;138;0
"Building";"HighTemplar";NA;138;0
"Unit";"Zealot";"Gateway";138;2
"Unit";"Zealot";"Gateway";138;2
"Unit";"Archon";"High Templar";142;0
"Building";"Pylon";NA;142;0
"Unit";"Zealot";"Gateway";145;2
"Unit";"Zealot";"Gateway";145;2
"Unit";"Zealot";"Gateway";145;2
"Unit";"Zealot";"Gateway";145;2
"Unit";"Zealot";"Gateway";153;2
"Unit";"Zealot";"Gateway";153;2
"Unit";"Zealot";"Gateway";158;2
"Unit";"Zealot";"Gateway";159;2
"Unit";"Zealot";"Gateway";159;2
"Unit";"Zealot";"Gateway";159;2
"Building";"HighTemplar";NA;171;0
"Building";"HighTemplar";NA;171;0
"Unit";"Zealot";"Gateway";171;2
"Unit";"Zealot";"Gateway";171;2
"Unit";"Zealot";"Gateway";171;2
"Unit";"Zealot";"Gateway";171;2
"Unit";"Immortal";"Robotics Facility";157;4
"Unit";"Archon";"High Templar";179;0
"Building";"Assimilator";NA;171;0
"Building";"Assimilator";NA;171;0
"Building";"Pylon";NA;179;0
"Building";"HighTemplar";NA;186;0
"Building";"HighTemplar";NA;186;0
"Building";"HighTemplar";NA;186;0
"Building";"HighTemplar";NA;186;0
"Unit";"Archon";"High Templar";186;0
"Unit";"Archon";"High Templar";186;0
"Building";"Pylon";NA;186;0
"Unit";"Immortal";"Robotics Facility";183;4
"Building";"Pylon";NA;186;0
"Building";"HighTemplar";NA;191;0
"Building";"HighTemplar";NA;191;0
"Unit";"Zealot";"Gateway";191;2
"Unit";"Zealot";"Gateway";191;2
"Unit";"Zealot";"Gateway";191;2
"Unit";"Zealot";"Gateway";191;2
"Unit";"Archon";"High Templar";191;0
"Building";"PhotonCannon";NA;186;0
"Building";"PhotonCannon";NA;186;0
"Building";"PhotonCannon";NA;186;0
"Unit";"Zealot";"Gateway";201;2
"Unit";"Zealot";"Gateway";201;2
"Upgrade";"ProtossGroundWeaponsLevel3";"Forge";168;0
"Unit";"Zealot";"Gateway";201;2
"Unit";"Zealot";"Gateway";201;2
"Unit";"Zealot";"Gateway";201;2
"Unit";"Zealot";"Gateway";201;2
"Unit";"Immortal";"Robotics Facility";199;4
"Building";"HighTemplar";NA;217;0
"Building";"HighTemplar";NA;217;0
"Building";"HighTemplar";NA;217;0
"Building";"HighTemplar";NA;217;0
"Building";"HighTemplar";NA;217;0
"Building";"HighTemplar";NA;217;0
"Unit";"Archon";"High Templar";217;0
"Unit";"Archon";"High Templar";217;0
"Unit";"Immortal";"Robotics Facility";213;4
"Unit";"Archon";"High Templar";217;0
"Building";"Pylon";NA;221;0
"Building";"Pylon";NA;221;0
"Building";"HighTemplar";NA;221;0
"Building";"HighTemplar";NA;221;0
"Building";"HighTemplar";NA;221;0
"Building";"HighTemplar";NA;221;0
"Unit";"Zealot";"Gateway";221;2
"Unit";"Zealot";"Gateway";221;2
"Unit";"Immortal";"Robotics Facility";217;4
"Unit";"Archon";"High Templar";221;0
"Unit";"Archon";"High Templar";221;0
"Building";"Pylon";NA;221;0
"Unit";"Zealot";"Gateway";229;2
"Unit";"Zealot";"Gateway";229;2
"Building";"Gateway";NA;221;0
"Unit";"Immortal";"Robotics Facility";221;4
"Building";"Gateway";NA;221;0
"Building";"ShieldBattery";NA;229;0
"Building";"Gateway";NA;221;0
"Building";"Gateway";NA;221;0
"Unit";"Zealot";"Gateway";237;2
"Unit";"Zealot";"Gateway";237;2
"Unit";"Zealot";"Gateway";237;2
"Unit";"Zealot";"Gateway";237;2
"Unit";"Zealot";"Gateway";237;2
"Unit";"Zealot";"Gateway";237;2
"Building";"ShieldBattery";NA;229;0
"Building";"Nexus";NA;217;0
"Building";"HighTemplar";NA;249;0
"Building";"HighTemplar";NA;249;0
"Building";"HighTemplar";NA;249;0
"Building";"HighTemplar";NA;249;0
"Unit";"Archon";"High Templar";249;0
"Unit";"Archon";"High Templar";249;0
"Building";"Assimilator";NA;249;0
"Building";"Assimilator";NA;249;0
"Unit";"Zealot";"Gateway";249;2
"Unit";"Zealot";"Gateway";249;2
"Unit";"Zealot";"Gateway";249;2
"Unit";"Zealot";"Gateway";249;2
"Unit";"Zealot";"Gateway";249;2
"Unit";"Zealot";"Gateway";249;2
"Building";"Pylon";NA;249;0
"Building";"Pylon";NA;249;0
"Unit";"Zealot";"Gateway";261;2
"Unit";"Zealot";"Gateway";261;2
"Unit";"Zealot";"Gateway";261;2
"Unit";"Zealot";"Gateway";261;2
"Unit";"Immortal";"Robotics Facility";249;4
"Unit";"Zealot";"Gateway";273;2
"Unit";"Zealot";"Gateway";273;2
"Unit";"Zealot";"Gateway";273;2
"Unit";"Zealot";"Gateway";273;2
"Building";"PhotonCannon";NA;261;0
"Unit";"Zealot";"Gateway";281;2
"Building";"PhotonCannon";NA;269;0
"Unit";"Zealot";"Gateway";283;2
