"type";"unit_name";"on_building";"total_supply";"supply"
"Building";"Pylon";NA;13;0
"Building";"Assimilator";NA;16;0
"Building";"Assimilator";NA;17;0
"Building";"Gateway";NA;14;0
"Building";"Pylon";NA;20;0
"Building";"Gateway";NA;18;0
"Building";"CyberneticsCore";NA;20;0
"Building";"Pylon";NA;23;0
"Unit";"Stalker";"Gateway";22;2
"Unit";"Stalker";"Gateway";23;2
"Building";"TwilightCouncil";NA;24;0
"Unit";"Stalker";"Gateway";29;2
"Unit";"Stalker";"Gateway";29;2
"Building";"Pylon";NA;35;0
"Building";"RoboticsFacility";NA;35;0
"Building";"ShieldBattery";NA;35;0
"Unit";"Sentry";"Gateway";35;2
"Unit";"Stalker";"Gateway";37;2
"Building";"Gateway";NA;35;0
"Building";"Pylon";NA;35;0
"Unit";"Observer";"Robotics Facility";37;1
"Unit";"Stalker";"Gateway";40;2
"Unit";"Stalker";"Gateway";43;2
"Building";"Pylon";NA;40;0
"Unit";"Stalker";"Gateway";45;2
"Unit";"Stalker";"Gateway";48;2
"Unit";"Observer";"Robotics Facility";45;1
"Building";"Nexus";NA;35;0
"Unit";"Phoenix";"Stargate";48;2
"Unit";"Immortal";"Robotics Facility";52;4
"Unit";"Zealot";"Gateway";64;2
"Unit";"Zealot";"Gateway";64;2
"Unit";"Zealot";"Gateway";64;2
"Building";"Assimilator";NA;64;0
"Building";"Forge";NA;64;0
"Unit";"Immortal";"Robotics Facility";64;4
"Building";"RoboticsFacility";NA;64;0
"Building";"Pylon";NA;74;0
"Building";"Pylon";NA;82;0
"Building";"Assimilator";NA;82;0
"Unit";"Immortal";"Robotics Facility";82;4
"Building";"TemplarArchive";NA;83;0
"Upgrade";"Charge";"TwilightCouncil";73;0
"Building";"HighTemplar";NA;90;0
"Building";"Pylon";NA;90;0
"Unit";"Immortal";"Robotics Facility";84;4
"Building";"Pylon";NA;90;0
"Building";"Pylon";NA;90;0
"Building";"Pylon";NA;90;0
"Building";"Pylon";NA;94;0
"Unit";"Immortal";"Robotics Facility";90;4
"Unit";"Zealot";"Gateway";94;2
"Unit";"Zealot";"Gateway";94;2
"Upgrade";"ProtossGroundWeaponsLevel1";"Forge";84;0
"Building";"Nexus";NA;84;0
"Building";"HighTemplar";NA;102;0
"Unit";"Zealot";"Gateway";102;2
"Unit";"Zealot";"Gateway";102;2
"Unit";"Archon";"High Templar";102;0
"Building";"Gateway";NA;94;0
"Building";"Gateway";NA;94;0
"Building";"Gateway";NA;94;0
"Building";"Gateway";NA;94;0
"Building";"ShieldBattery";NA;102;0
"Building";"HighTemplar";NA;106;0
"Building";"HighTemplar";NA;106;0
"Building";"ShieldBattery";NA;102;0
"Building";"HighTemplar";NA;106;0
"Building";"HighTemplar";NA;106;0
"Unit";"Zealot";"Gateway";106;2
"Unit";"Zealot";"Gateway";106;2
"Unit";"Zealot";"Gateway";106;2
"Unit";"Archon";"High Templar";106;0
"Unit";"Archon";"High Templar";106;0
"Unit";"Zealot";"Gateway";112;2
"Unit";"Zealot";"Gateway";113;2
"Unit";"Zealot";"Gateway";113;2
"Building";"Pylon";NA;112;0
"Unit";"Zealot";"Gateway";120;2
"Unit";"Zealot";"Gateway";120;2
"Unit";"Stalker";"Gateway";120;2
"Unit";"Zealot";"Gateway";124;2
"Building";"Pylon";NA;120;0
"Building";"PhotonCannon";NA;112;0
"Unit";"Observer";"Robotics Facility";120;1
"Unit";"Zealot";"Gateway";129;2
"Unit";"Zealot";"Gateway";129;2
"Unit";"Zealot";"Gateway";129;2
"Unit";"Zealot";"Gateway";129;2
"Unit";"Zealot";"Gateway";129;2
"Unit";"Immortal";"Robotics Facility";120;4
"Unit";"Zealot";"Gateway";143;2
"Unit";"Zealot";"Gateway";143;2
"Unit";"Zealot";"Gateway";147;2
"Unit";"Zealot";"Gateway";147;2
"Unit";"Zealot";"Gateway";151;2
"Unit";"Zealot";"Gateway";151;2
"Unit";"Zealot";"Gateway";151;2
"Building";"HighTemplar";NA;158;0
"Building";"HighTemplar";NA;158;0
"Building";"HighTemplar";NA;158;0
"Building";"HighTemplar";NA;158;0
"Upgrade";"ProtossGroundWeaponsLevel2";"Forge";112;0
"Unit";"Stalker";"Gateway";160;2
"Unit";"Stalker";"Gateway";160;2
"Unit";"Stalker";"Gateway";160;2
"Unit";"Archon";"High Templar";160;0
"Unit";"Archon";"High Templar";160;0
"Building";"Assimilator";NA;160;0
"Building";"Assimilator";NA;160;0
"Building";"HighTemplar";NA;171;0
"Building";"HighTemplar";NA;171;0
"Building";"Pylon";NA;169;0
"Unit";"Archon";"High Templar";172;0
"Building";"Gateway";NA;160;0
"Building";"Gateway";NA;160;0
"Unit";"Immortal";"Robotics Facility";169;4
"Building";"HighTemplar";NA;176;0
"Building";"HighTemplar";NA;176;0
"Building";"Forge";NA;172;0
"Unit";"Immortal";"Robotics Facility";172;4
"Unit";"Archon";"High Templar";178;0
"Building";"HighTemplar";NA;182;0
"Building";"HighTemplar";NA;182;0
"Unit";"Immortal";"Robotics Facility";172;4
"Building";"Pylon";NA;182;0
"Unit";"Archon";"High Templar";182;0
"Unit";"Observer";"Robotics Facility";182;1
"Unit";"Zealot";"Gateway";186;2
"Unit";"Zealot";"Gateway";186;2
"Unit";"Zealot";"Gateway";186;2
"Building";"Pylon";NA;186;0
"Building";"Pylon";NA;186;0
"Unit";"Zealot";"Gateway";193;2
"Upgrade";"ProtossGroundArmorsLevel1";"Forge";172;0
"Unit";"Zealot";"Gateway";195;2
"Unit";"Zealot";"Gateway";195;2
"Unit";"Zealot";"Gateway";195;2
"Unit";"Zealot";"Gateway";195;2
"Building";"Pylon";NA;195;0
"Building";"Pylon";NA;195;0
"Building";"Pylon";NA;203;0
"Building";"Pylon";NA;203;0
"Unit";"Zealot";"Gateway";203;2
"Unit";"Zealot";"Gateway";203;2
"Unit";"Zealot";"Gateway";203;2
"Unit";"Zealot";"Gateway";203;2
"Unit";"Zealot";"Gateway";203;2
"Building";"Pylon";NA;203;0
"Unit";"Observer";"Robotics Facility";203;1
"Building";"PhotonCannon";NA;203;0
"Building";"PhotonCannon";NA;203;0
"Building";"HighTemplar";NA;214;0
"Building";"HighTemplar";NA;214;0
"Building";"HighTemplar";NA;214;0
"Building";"HighTemplar";NA;214;0
"Building";"HighTemplar";NA;214;0
"Building";"HighTemplar";NA;214;0
"Building";"HighTemplar";NA;214;0
"Building";"HighTemplar";NA;214;0
"Building";"PhotonCannon";NA;203;0
"Building";"PhotonCannon";NA;203;0
"Unit";"Archon";"High Templar";214;0
"Unit";"Archon";"High Templar";214;0
"Unit";"Archon";"High Templar";214;0
"Building";"HighTemplar";NA;214;0
"Building";"HighTemplar";NA;214;0
"Building";"HighTemplar";NA;214;0
"Building";"PhotonCannon";NA;214;0
"Building";"PhotonCannon";NA;214;0
"Unit";"Zealot";"Gateway";214;2
"Unit";"Zealot";"Gateway";214;2
"Unit";"Zealot";"Gateway";214;2
"Building";"Pylon";NA;214;0
"Building";"PhotonCannon";NA;214;0
"Unit";"Archon";"High Templar";214;0
"Unit";"Archon";"High Templar";214;0
"Upgrade";"ProtossGroundWeaponsLevel3";"Forge";195;0
"Unit";"Zealot";"Gateway";220;2
"Unit";"Zealot";"Gateway";220;2
"Unit";"Zealot";"Gateway";220;2
"Unit";"Zealot";"Gateway";226;2
"Unit";"Zealot";"Gateway";226;2
"Unit";"Zealot";"Gateway";226;2
"Unit";"Zealot";"Gateway";226;2
"Unit";"Zealot";"Gateway";226;2
"Unit";"Zealot";"Gateway";226;2
"Unit";"Zealot";"Gateway";226;2
"Building";"HighTemplar";NA;240;0
"Building";"HighTemplar";NA;240;0
"Unit";"Observer";"Robotics Facility";240;1
"Building";"HighTemplar";NA;241;0
"Building";"HighTemplar";NA;241;0
"Building";"HighTemplar";NA;241;0
"Building";"HighTemplar";NA;241;0
"Building";"HighTemplar";NA;241;0
"Building";"HighTemplar";NA;241;0
"Building";"HighTemplar";NA;241;0
"Unit";"Observer";"Robotics Facility";240;1
"Unit";"Archon";"High Templar";241;0
"Unit";"Archon";"High Templar";241;0
"Unit";"Archon";"High Templar";241;0
"Unit";"Archon";"High Templar";242;0
"Building";"PhotonCannon";NA;240;0
"Building";"PhotonCannon";NA;240;0
"Building";"Pylon";NA;242;0
"Unit";"Zealot";"Gateway";242;2
"Unit";"Zealot";"Gateway";242;2
"Unit";"Zealot";"Gateway";242;2
"Unit";"Zealot";"Gateway";242;2
"Unit";"Zealot";"Gateway";242;2
"Unit";"Zealot";"Gateway";252;2
"Building";"Pylon";NA;242;0
"Unit";"Zealot";"Gateway";252;2
"Building";"ShieldBattery";NA;242;0
"Building";"Nexus";NA;240;0
"Unit";"Zealot";"Gateway";256;2
"Unit";"Zealot";"Gateway";256;2
"Unit";"Zealot";"Gateway";256;2
"Unit";"Zealot";"Gateway";256;2
"Building";"HighTemplar";NA;265;0
"Building";"HighTemplar";NA;265;0
"Building";"DarkShrine";NA;242;0
"Building";"HighTemplar";NA;265;0
"Building";"HighTemplar";NA;265;0
"Unit";"Zealot";"Gateway";265;2
"Unit";"Zealot";"Gateway";265;2
"Unit";"Zealot";"Gateway";265;2
"Unit";"Immortal";"Robotics Facility";256;4
"Unit";"Immortal";"Robotics Facility";256;4
"Unit";"Archon";"High Templar";265;0
"Unit";"Archon";"High Templar";265;0
"Building";"Pylon";NA;265;0
"Unit";"Zealot";"Gateway";279;2
"Unit";"Zealot";"Gateway";279;2
"Building";"Assimilator";NA;265;0
"Building";"PhotonCannon";NA;265;0
