"type";"unit_name";"on_building";"total_supply";"supply"
"Unit";"Overlord";"Larva";13;0
"Building";"Extractor";NA;18;0
"Unit";"Overlord";"Larva";21;0
"Building";"SpawningPool";NA;19;0
"Building";"Hatchery";NA;17;0
"Unit";"Zergling";"Larva";23;1
"Unit";"Zergling";"Larva";23;1
"Unit";"Zergling";"Larva";23;1
"Unit";"Zergling";"Larva";23;1
"Unit";"Queen";"Hatchery";22;2
"Unit";"Queen";"Hatchery";23;2
"Building";"CreepTumorQueen";NA;34;0
"Unit";"Overlord";"Larva";35;0
"Building";"CreepTumor";NA;36;0
"Unit";"Queen";"Hatchery";35;2
"Building";"CreepTumorQueen";NA;39;0
"Building";"Hatchery";NA;27;0
"Unit";"Overlord";"Larva";40;0
"Unit";"Overlord";"Larva";45;0
"Building";"CreepTumorQueen";NA;47;0
"Building";"CreepTumor";NA;47;0
"Building";"CreepTumor";NA;49;0
"Unit";"Queen";"Hatchery";42;2
"Unit";"Queen";"Hatchery";47;2
"Unit";"Overlord";"Larva";51;0
"Unit";"Overlord";"Larva";51;0
"Unit";"Overlord";"Larva";57;0
"Building";"CreepTumorQueen";NA;62;0
"Unit";"Queen";"Hatchery";53;2
"Building";"CreepTumor";NA;67;0
"Unit";"Zergling";"Larva";64;1
"Unit";"Zergling";"Larva";64;1
"Unit";"Zergling";"Larva";64;1
"Unit";"Zergling";"Larva";64;1
"Unit";"Zergling";"Larva";64;1
"Unit";"Zergling";"Larva";64;1
"Unit";"Zergling";"Larva";64;1
"Unit";"Zergling";"Larva";64;1
"Building";"CreepTumorQueen";NA;73;0
"Building";"CreepTumor";NA;73;0
"Building";"Extractor";NA;64;0
"Building";"Extractor";NA;64;0
"Building";"CreepTumor";NA;73;0
"Unit";"Zergling";"Larva";73;1
"Unit";"Zergling";"Larva";73;1
"Unit";"Zergling";"Larva";73;1
"Unit";"Zergling";"Larva";73;1
"Unit";"Zergling";"Larva";73;1
"Unit";"Zergling";"Larva";73;1
"Building";"CreepTumor";NA;81;0
"Building";"CreepTumorQueen";NA;81;0
"Unit";"Overlord";"Larva";90;0
"Unit";"Overlord";"Larva";90;0
"Unit";"Overlord";"Larva";90;0
"Building";"CreepTumor";NA;97;0
"Building";"EvolutionChamber";NA;81;0
"Building";"EvolutionChamber";NA;81;0
"Building";"Extractor";NA;90;0
"Building";"CreepTumor";NA;99;0
"Building";"Extractor";NA;90;0
"Building";"CreepTumor";NA;101;0
"Building";"CreepTumor";NA;101;0
"Building";"CreepTumor";NA;101;0
"Unit";"Overlord";"Larva";101;0
"Unit";"Overlord";"Larva";101;0
"Unit";"Overlord";"Larva";101;0
"Building";"BanelingNest";NA;97;0
"Unit";"Overlord";"Larva";101;0
"Unit";"Zergling";"Larva";104;1
"Unit";"Zergling";"Larva";104;1
"Unit";"Zergling";"Larva";105;1
"Unit";"Zergling";"Larva";105;1
"Unit";"Zergling";"Larva";106;1
"Unit";"Zergling";"Larva";106;1
"Unit";"Zergling";"Larva";108;1
"Unit";"Zergling";"Larva";108;1
"Unit";"Zergling";"Larva";108;1
"Unit";"Zergling";"Larva";108;1
"Unit";"Overlord";"Larva";108;0
"Building";"Extractor";NA;108;0
"Unit";"Zergling";"Larva";118;1
"Unit";"Zergling";"Larva";118;1
"Unit";"Zergling";"Larva";118;1
"Unit";"Zergling";"Larva";118;1
"Unit";"Zergling";"Larva";118;1
"Unit";"Zergling";"Larva";118;1
"Unit";"Zergling";"Larva";118;1
"Unit";"Zergling";"Larva";118;1
"Unit";"Zergling";"Larva";118;1
"Unit";"Zergling";"Larva";118;1
"Unit";"Zergling";"Larva";118;1
"Unit";"Zergling";"Larva";118;1
"Unit";"Zergling";"Larva";118;1
"Unit";"Zergling";"Larva";118;1
"Unit";"Zergling";"Larva";118;1
"Unit";"Zergling";"Larva";118;1
"Unit";"Zergling";"Larva";118;1
"Unit";"Zergling";"Larva";118;1
"Unit";"Zergling";"Larva";118;1
"Unit";"Zergling";"Larva";118;1
"Building";"CreepTumorQueen";NA;118;0
"Building";"CreepTumorQueen";NA;118;0
"Building";"Hatchery";NA;101;0
"Building";"CreepTumorQueen";NA;142;0
"Building";"HydraliskDen";NA;138;0
"Building";"CreepTumor";NA;149;0
"Building";"CreepTumor";NA;149;0
"Building";"CreepTumor";NA;149;0
"Unit";"Baneling";"Zergling";149;0
"Unit";"Baneling";"Zergling";149;0
"Unit";"Baneling";"Zergling";149;0
"Unit";"Baneling";"Zergling";149;0
"Unit";"Baneling";"Zergling";149;0
"Unit";"Baneling";"Zergling";149;0
"Unit";"Baneling";"Zergling";149;0
"Unit";"Baneling";"Zergling";149;0
"Building";"CreepTumor";NA;149;0
"Building";"CreepTumor";NA;149;0
"Building";"CreepTumor";NA;149;0
"Building";"Hatchery";NA;108;0
"Unit";"Overlord";"Larva";153;0
"Building";"CreepTumor";NA;161;0
"Building";"CreepTumor";NA;161;0
"Building";"CreepTumor";NA;161;0
"Unit";"Hydralisk";"Larva";153;2
"Unit";"Hydralisk";"Larva";153;2
"Unit";"Hydralisk";"Larva";153;2
"Upgrade";"ZergGroundArmorsLevel1";"EvolutionChamber";118;0
"Unit";"Overlord";"Larva";161;0
"Unit";"Hydralisk";"Larva";161;2
"Unit";"Hydralisk";"Larva";161;2
"Upgrade";"ZergMeleeWeaponsLevel1";"EvolutionChamber";118;0
"Building";"CreepTumor";NA;161;0
"Building";"CreepTumorQueen";NA;167;0
"Unit";"Zergling";"Larva";171;1
"Unit";"Zergling";"Larva";171;1
"Unit";"Zergling";"Larva";171;1
"Unit";"Zergling";"Larva";171;1
"Unit";"Zergling";"Larva";171;1
"Unit";"Zergling";"Larva";171;1
"Unit";"Zergling";"Larva";171;1
"Unit";"Zergling";"Larva";171;1
"Unit";"Zergling";"Larva";171;1
"Unit";"Zergling";"Larva";171;1
"Unit";"Zergling";"Larva";171;1
"Unit";"Zergling";"Larva";171;1
"Unit";"Zergling";"Larva";171;1
"Unit";"Zergling";"Larva";171;1
"Unit";"Zergling";"Larva";171;1
"Unit";"Zergling";"Larva";171;1
"Unit";"Zergling";"Larva";171;1
"Unit";"Zergling";"Larva";171;1
"Unit";"Zergling";"Larva";171;1
"Unit";"Zergling";"Larva";171;1
"Unit";"Zergling";"Larva";171;1
"Unit";"Zergling";"Larva";171;1
"Unit";"Zergling";"Larva";171;1
"Unit";"Zergling";"Larva";171;1
"Unit";"Zergling";"Larva";171;1
"Unit";"Zergling";"Larva";171;1
"Building";"CreepTumor";NA;200;0
"Building";"CreepTumor";NA;200;0
"Upgrade";"EvolveGroovedSpines";"HydraliskDen";161;0
"Building";"CreepTumor";NA;201;0
"Unit";"Overlord";"Larva";201;0
"Unit";"Overlord";"Larva";201;0
"Unit";"Hydralisk";"Larva";200;2
"Unit";"Hydralisk";"Larva";200;2
"Unit";"Hydralisk";"Larva";200;2
"Unit";"Hydralisk";"Larva";200;2
"Unit";"Hydralisk";"Larva";200;2
"Unit";"Hydralisk";"Larva";200;2
"Unit";"Hydralisk";"Larva";200;2
"Unit";"Hydralisk";"Larva";200;2
"Unit";"Hydralisk";"Larva";200;2
"Unit";"Hydralisk";"Larva";200;2
"Unit";"Hydralisk";"Larva";200;2
"Unit";"Hydralisk";"Larva";200;2
"Unit";"Hydralisk";"Larva";200;2
"Unit";"Hydralisk";"Larva";200;2
"Unit";"Hydralisk";"Larva";200;2
"Building";"SporeCrawler";NA;201;0
"Building";"CreepTumor";NA;201;0
"Building";"CreepTumor";NA;201;0
"Building";"CreepTumor";NA;201;0
"Building";"Extractor";NA;201;0
"Building";"InfestationPit";NA;200;0
"Building";"SpineCrawler";NA;201;0
"Building";"Hatchery";NA;171;0
"Unit";"Zergling";"Larva";233;1
"Unit";"Zergling";"Larva";233;1
"Unit";"Zergling";"Larva";233;1
"Unit";"Zergling";"Larva";233;1
"Unit";"Zergling";"Larva";233;1
"Unit";"Zergling";"Larva";233;1
"Unit";"Zergling";"Larva";233;1
"Unit";"Zergling";"Larva";233;1
"Unit";"Zergling";"Larva";233;1
"Unit";"Zergling";"Larva";233;1
"Unit";"Zergling";"Larva";233;1
"Unit";"Zergling";"Larva";233;1
"Unit";"Zergling";"Larva";233;1
"Unit";"Zergling";"Larva";233;1
"Unit";"Zergling";"Larva";233;1
"Unit";"Zergling";"Larva";233;1
"Unit";"Zergling";"Larva";233;1
"Unit";"Zergling";"Larva";233;1
"Unit";"Zergling";"Larva";233;1
"Unit";"Zergling";"Larva";233;1
"Unit";"Zergling";"Larva";233;1
"Unit";"Zergling";"Larva";233;1
"Unit";"Zergling";"Larva";233;1
"Unit";"Zergling";"Larva";233;1
"Unit";"Zergling";"Larva";233;1
"Unit";"Zergling";"Larva";233;1
"Unit";"Zergling";"Larva";233;1
"Unit";"Zergling";"Larva";233;1
"Building";"CreepTumor";NA;233;0
"Building";"CreepTumor";NA;233;0
"Building";"CreepTumor";NA;233;0
"Unit";"Zergling";"Larva";233;1
"Unit";"Zergling";"Larva";233;1
"Unit";"Zergling";"Larva";233;1
"Unit";"Zergling";"Larva";233;1
"Unit";"Zergling";"Larva";233;1
"Unit";"Zergling";"Larva";233;1
"Unit";"Zergling";"Larva";233;1
"Unit";"Zergling";"Larva";233;1
"Unit";"Zergling";"Larva";233;1
"Unit";"Zergling";"Larva";233;1
"Unit";"Zergling";"Larva";233;1
"Unit";"Zergling";"Larva";233;1
"Unit";"Zergling";"Larva";233;1
"Unit";"Zergling";"Larva";233;1
"Unit";"Zergling";"Larva";235;1
"Unit";"Zergling";"Larva";235;1
"Unit";"Zergling";"Larva";235;1
"Unit";"Zergling";"Larva";235;1
"Unit";"Zergling";"Larva";235;1
"Unit";"Zergling";"Larva";235;1
"Unit";"Zergling";"Larva";235;1
"Unit";"Zergling";"Larva";235;1
"Unit";"Zergling";"Larva";235;1
"Unit";"Zergling";"Larva";235;1
"Unit";"Zergling";"Larva";235;1
"Unit";"Zergling";"Larva";235;1
"Unit";"Baneling";"Zergling";261;0
"Building";"CreepTumor";NA;261;0
"Unit";"Baneling";"Zergling";261;0
"Unit";"Baneling";"Zergling";261;0
"Unit";"Baneling";"Zergling";261;0
"Unit";"Baneling";"Zergling";261;0
"Unit";"Baneling";"Zergling";261;0
"Unit";"Baneling";"Zergling";261;0
"Unit";"Baneling";"Zergling";261;0
"Unit";"Baneling";"Zergling";261;0
"Unit";"Baneling";"Zergling";261;0
"Upgrade";"EvolveMuscularAugments";"HydraliskDen";233;0
"Building";"CreepTumorQueen";NA;287;0
"Building";"EvolutionChamber";NA;261;0
"Building";"CreepTumor";NA;289;0
"Building";"Extractor";NA;287;0
"Unit";"Zergling";"Larva";289;1
"Unit";"Zergling";"Larva";289;1
"Unit";"Zergling";"Larva";289;1
"Unit";"Zergling";"Larva";289;1
"Unit";"Zergling";"Larva";289;1
"Unit";"Zergling";"Larva";289;1
"Unit";"Zergling";"Larva";289;1
"Unit";"Zergling";"Larva";289;1
"Unit";"Zergling";"Larva";289;1
"Unit";"Zergling";"Larva";289;1
"Unit";"Zergling";"Larva";289;1
"Unit";"Zergling";"Larva";289;1
"Unit";"Zergling";"Larva";289;1
"Unit";"Zergling";"Larva";289;1
"Unit";"Zergling";"Larva";289;1
"Unit";"Zergling";"Larva";289;1
"Unit";"Zergling";"Larva";289;1
"Unit";"Zergling";"Larva";289;1
"Unit";"Zergling";"Larva";289;1
"Unit";"Zergling";"Larva";289;1
"Unit";"Zergling";"Larva";289;1
"Unit";"Zergling";"Larva";289;1
"Unit";"Zergling";"Larva";289;1
"Unit";"Zergling";"Larva";289;1
"Unit";"Zergling";"Larva";289;1
"Unit";"Zergling";"Larva";289;1
"Unit";"Zergling";"Larva";289;1
"Unit";"Zergling";"Larva";289;1
"Unit";"Zergling";"Larva";289;1
"Unit";"Zergling";"Larva";289;1
"Unit";"Overlord";"Larva";289;0
"Unit";"Overlord";"Larva";289;0
"Unit";"Overlord";"Larva";289;0
"Unit";"Overlord";"Larva";289;0
"Building";"CreepTumor";NA;319;0
"Upgrade";"ZergMeleeWeaponsLevel2";"EvolutionChamber";233;0
"Building";"CreepTumor";NA;319;0
"Upgrade";"ZergGroundArmorsLevel2";"EvolutionChamber";233;0
"Building";"CreepTumor";NA;322;0
"Building";"CreepTumor";NA;322;0
"Building";"CreepTumor";NA;322;0
"Unit";"Viper";"Larva";319;3
"Unit";"Viper";"Larva";319;3
"Unit";"Baneling";"Zergling";322;0
"Unit";"Baneling";"Zergling";322;0
"Unit";"Baneling";"Zergling";322;0
"Unit";"Baneling";"Zergling";322;0
"Unit";"Baneling";"Zergling";322;0
"Unit";"Baneling";"Zergling";322;0
"Unit";"Baneling";"Zergling";322;0
"Unit";"Baneling";"Zergling";322;0
"Unit";"Baneling";"Zergling";322;0
"Unit";"Baneling";"Zergling";322;0
"Unit";"Baneling";"Zergling";322;0
"Unit";"Baneling";"Zergling";322;0
"Unit";"Baneling";"Zergling";322;0
"Unit";"Baneling";"Zergling";322;0
"Unit";"Baneling";"Zergling";322;0
"Unit";"Baneling";"Zergling";322;0
"Unit";"Baneling";"Zergling";322;0
"Unit";"Baneling";"Zergling";322;0
"Unit";"Baneling";"Zergling";322;0
"Unit";"Baneling";"Zergling";322;0
"Unit";"Baneling";"Zergling";322;0
"Unit";"Baneling";"Zergling";322;0
"Unit";"Baneling";"Zergling";322;0
"Unit";"Baneling";"Zergling";322;0
"Unit";"Baneling";"Zergling";322;0
"Unit";"Baneling";"Zergling";322;0
"Unit";"Baneling";"Zergling";322;0
"Unit";"Baneling";"Zergling";322;0
"Unit";"Baneling";"Zergling";322;0
"Unit";"Baneling";"Zergling";322;0
"Unit";"Baneling";"Zergling";322;0
"Unit";"Baneling";"Zergling";322;0
"Unit";"Baneling";"Zergling";322;0
"Unit";"Baneling";"Zergling";322;0
"Unit";"Baneling";"Zergling";322;0
"Unit";"Baneling";"Zergling";322;0
"Unit";"Baneling";"Zergling";322;0
"Unit";"Baneling";"Zergling";322;0
"Unit";"Baneling";"Zergling";322;0
"Unit";"Baneling";"Zergling";322;0
"Unit";"Baneling";"Zergling";322;0
"Unit";"Baneling";"Zergling";322;0
"Unit";"Baneling";"Zergling";322;0
"Unit";"Baneling";"Zergling";322;0
"Unit";"Baneling";"Zergling";322;0
"Unit";"Baneling";"Zergling";322;0
"Unit";"Baneling";"Zergling";322;0
"Unit";"Baneling";"Zergling";322;0
"Unit";"Baneling";"Zergling";322;0
"Unit";"Baneling";"Zergling";322;0
"Unit";"Baneling";"Zergling";322;0
"Unit";"Baneling";"Zergling";322;0
"Unit";"Baneling";"Zergling";322;0
"Unit";"Zergling";"Larva";322;1
"Unit";"Zergling";"Larva";322;1
"Unit";"Zergling";"Larva";322;1
"Unit";"Zergling";"Larva";322;1
"Building";"UltraliskCavern";NA;319;0
"Building";"SpineCrawler";NA;328;0
"Upgrade";"Burrow";"Hatchery";328;0
"Unit";"Baneling";"Zergling";332;0
"Unit";"Baneling";"Zergling";332;0
"Unit";"Baneling";"Zergling";332;0
"Unit";"Baneling";"Zergling";332;0
"Unit";"Baneling";"Zergling";332;0
"Unit";"Baneling";"Zergling";332;0
"Unit";"Baneling";"Zergling";332;0
"Unit";"Baneling";"Zergling";332;0
"Unit";"Baneling";"Zergling";332;0
"Unit";"Baneling";"Zergling";332;0
"Unit";"Baneling";"Zergling";332;0
"Unit";"Baneling";"Zergling";332;0
"Unit";"Zergling";"Larva";332;1
"Unit";"Zergling";"Larva";332;1
"Unit";"Zergling";"Larva";332;1
"Unit";"Zergling";"Larva";332;1
"Unit";"Zergling";"Larva";332;1
"Unit";"Zergling";"Larva";332;1
"Unit";"Zergling";"Larva";332;1
"Unit";"Zergling";"Larva";332;1
"Unit";"Zergling";"Larva";332;1
"Unit";"Zergling";"Larva";332;1
"Unit";"Zergling";"Larva";332;1
"Unit";"Zergling";"Larva";332;1
"Unit";"Zergling";"Larva";332;1
"Unit";"Zergling";"Larva";332;1
"Unit";"Zergling";"Larva";332;1
"Unit";"Zergling";"Larva";332;1
"Unit";"Zergling";"Larva";332;1
"Unit";"Zergling";"Larva";332;1
"Unit";"Zergling";"Larva";332;1
"Unit";"Zergling";"Larva";332;1
"Unit";"Zergling";"Larva";332;1
"Unit";"Zergling";"Larva";332;1
"Unit";"Zergling";"Larva";332;1
"Unit";"Zergling";"Larva";332;1
"Unit";"Zergling";"Larva";332;1
"Unit";"Zergling";"Larva";332;1
"Unit";"Zergling";"Larva";332;1
"Unit";"Zergling";"Larva";332;1
"Unit";"Zergling";"Larva";332;1
"Unit";"Zergling";"Larva";332;1
"Unit";"Zergling";"Larva";332;1
"Unit";"Zergling";"Larva";332;1
"Unit";"Zergling";"Larva";332;1
"Unit";"Zergling";"Larva";332;1
"Unit";"Zergling";"Larva";332;1
"Unit";"Zergling";"Larva";332;1
"Unit";"Zergling";"Larva";332;1
"Unit";"Zergling";"Larva";332;1
"Unit";"Zergling";"Larva";332;1
"Unit";"Zergling";"Larva";332;1
"Unit";"Zergling";"Larva";332;1
"Unit";"Zergling";"Larva";332;1
"Unit";"Zergling";"Larva";332;1
"Unit";"Zergling";"Larva";332;1
"Unit";"Zergling";"Larva";332;1
"Unit";"Zergling";"Larva";332;1
"Unit";"Zergling";"Larva";332;1
"Unit";"Zergling";"Larva";332;1
"Unit";"Zergling";"Larva";332;1
"Unit";"Zergling";"Larva";332;1
"Unit";"Zergling";"Larva";332;1
"Unit";"Zergling";"Larva";332;1
"Unit";"Zergling";"Larva";332;1
"Unit";"Zergling";"Larva";332;1
"Unit";"Zergling";"Larva";332;1
"Unit";"Zergling";"Larva";332;1
"Unit";"Zergling";"Larva";332;1
"Unit";"Zergling";"Larva";332;1
"Upgrade";"ZergMissileWeaponsLevel1";"EvolutionChamber";328;0
"Unit";"Ultralisk";"Larva";332;6
"Unit";"Ultralisk";"Larva";332;6
"Unit";"Ultralisk";"Larva";332;6
"Building";"CreepTumor";NA;390;0
"Building";"CreepTumor";NA;390;0
"Building";"CreepTumor";NA;390;0
"Building";"Hatchery";NA;332;0
