"type";"unit_name";"on_building";"total_supply_lag";"supply"
"Unit";"Overlord";"Larva";13;0
"Building";"Hatchery";NA;17;0
"Building";"Extractor";NA;19;0
"Building";"SpawningPool";NA;19;0
"Unit";"Overlord";"Larva";23;0
"Unit";"Queen";"Hatchery";23;2
"Unit";"Queen";"Hatchery";25;2
"Unit";"Zergling";"Larva";27;1
"Unit";"Zergling";"Larva";28;1
"Unit";"Zergling";"Larva";29;1
"Unit";"Zergling";"Larva";30;1
"Building";"Hatchery";NA;33;0
"Unit";"Queen";"Hatchery";37;2
"Unit";"Overlord";"Larva";40;0
"Unit";"Overlord";"Larva";42;0
"Building";"CreepTumorQueen";NA;50;0
"Unit";"Overlord";"Larva";50;0
"Unit";"Queen";"Hatchery";50;2
"Unit";"Queen";"Hatchery";52;2
"Unit";"Queen";"Hatchery";59;2
"Building";"CreepTumorQueen";NA;64;0
"Unit";"Overlord";"Larva";66;0
"Unit";"Overlord";"Larva";66;0
"Building";"CreepTumor";NA;66;0
"Unit";"Overlord";"Larva";67;0
"Building";"BanelingNest";NA;68;0
"Building";"CreepTumorQueen";NA;68;0
"Building";"Extractor";NA;72;0
"Building";"CreepTumorQueen";NA;72;0
"Unit";"Zergling";"Larva";72;1
"Unit";"Zergling";"Larva";73;1
"Building";"Extractor";NA;74;0
"Unit";"Zergling";"Larva";74;1
"Unit";"Zergling";"Larva";75;1
"Unit";"Zergling";"Larva";76;1
"Unit";"Zergling";"Larva";77;1
"Unit";"Zergling";"Larva";78;1
"Unit";"Zergling";"Larva";79;1
"Unit";"Zergling";"Larva";80;1
"Unit";"Zergling";"Larva";81;1
"Unit";"Zergling";"Larva";82;1
"Unit";"Zergling";"Larva";83;1
"Building";"CreepTumor";NA;84;0
"Unit";"Overlord";"Larva";86;0
"Building";"CreepTumor";NA;87;0
"Building";"CreepTumor";NA;87;0
"Building";"CreepTumorQueen";NA;90;0
"Building";"CreepTumor";NA;98;0
"Unit";"Overlord";"Larva";98;0
"Building";"CreepTumor";NA;98;0
"Building";"SporeCrawler";NA;101;0
"Building";"SporeCrawler";NA;101;0
"Building";"SporeCrawler";NA;101;0
"Building";"EvolutionChamber";NA;102;0
"Building";"EvolutionChamber";NA;102;0
"Unit";"Zergling";"Larva";104;1
"Unit";"Zergling";"Larva";105;1
"Unit";"Zergling";"Larva";106;1
"Unit";"Zergling";"Larva";107;1
"Unit";"Zergling";"Larva";108;1
"Unit";"Zergling";"Larva";109;1
"Unit";"Zergling";"Larva";110;1
"Unit";"Zergling";"Larva";111;1
"Unit";"Zergling";"Larva";112;1
"Unit";"Zergling";"Larva";113;1
"Unit";"Zergling";"Larva";114;1
"Unit";"Zergling";"Larva";115;1
"Unit";"Zergling";"Larva";116;1
"Unit";"Zergling";"Larva";117;1
"Unit";"Zergling";"Larva";118;1
"Unit";"Zergling";"Larva";119;1
"Unit";"Baneling";"Zergling";120;0
"Unit";"Baneling";"Zergling";120;0
"Unit";"Baneling";"Zergling";120;0
"Unit";"Baneling";"Zergling";120;0
"Unit";"Baneling";"Zergling";120;0
"Unit";"Overlord";"Larva";120;0
"Unit";"Baneling";"Zergling";120;0
"Unit";"Baneling";"Zergling";120;0
"Unit";"Zergling";"Larva";120;1
"Unit";"Zergling";"Larva";121;1
"Building";"Extractor";NA;122;0
"Building";"HydraliskDen";NA;122;0
"Building";"Extractor";NA;122;0
"Unit";"Overlord";"Larva";122;0
"Building";"Extractor";NA;142;0
"Building";"CreepTumorQueen";NA;145;0
"Building";"CreepTumorQueen";NA;145;0
"Building";"CreepTumorQueen";NA;145;0
"Building";"Hatchery";NA;145;0
"Unit";"Overlord";"Larva";145;0
"Building";"CreepTumorQueen";NA;145;0
"Unit";"Hydralisk";"Larva";145;2
"Unit";"Hydralisk";"Larva";147;2
"Unit";"Hydralisk";"Larva";149;2
"Unit";"Zergling";"Larva";151;1
"Unit";"Zergling";"Larva";152;1
"Unit";"Overlord";"Larva";153;0
"Unit";"Hydralisk";"Larva";153;2
"Building";"CreepTumorQueen";NA;155;0
"Unit";"Hydralisk";"Larva";155;2
"Unit";"Zergling";"Larva";157;1
"Unit";"Zergling";"Larva";158;1
"Unit";"Zergling";"Larva";159;1
"Unit";"Zergling";"Larva";160;1
"Unit";"Zergling";"Larva";161;1
"Unit";"Zergling";"Larva";162;1
"Building";"CreepTumorQueen";NA;163;0
"Building";"CreepTumor";NA;163;0
"Building";"CreepTumorQueen";NA;163;0
"Unit";"Overlord";"Larva";163;0
"Building";"CreepTumor";NA;163;0
"Building";"CreepTumor";NA;163;0
"Unit";"Hydralisk";"Larva";163;2
"Building";"InfestationPit";NA;165;0
"Unit";"Hydralisk";"Larva";165;2
"Unit";"Overlord";"Larva";167;0
"Building";"CreepTumor";NA;167;0
"Building";"CreepTumor";NA;167;0
"Unit";"Overlord";"Larva";167;0
"Building";"CreepTumorQueen";NA;167;0
"Unit";"Hydralisk";"Larva";167;2
"Unit";"Hydralisk";"Larva";169;2
"Unit";"Hydralisk";"Larva";171;2
"Unit";"Overlord";"Larva";173;0
"Building";"CreepTumorQueen";NA;173;0
"Unit";"Overlord";"Larva";173;0
"Unit";"Overlord";"Larva";173;0
"Unit";"Hydralisk";"Larva";173;2
"Unit";"Hydralisk";"Larva";175;2
"Building";"Extractor";NA;184;0
"Building";"Extractor";NA;184;0
"Building";"Spire";NA;194;0
"Unit";"Hydralisk";"Larva";195;2
"Unit";"Hydralisk";"Larva";197;2
"Unit";"Zergling";"Larva";199;1
"Unit";"Zergling";"Larva";200;1
"Unit";"Zergling";"Larva";201;1
"Unit";"Zergling";"Larva";202;1
"Building";"CreepTumor";NA;203;0
"Building";"CreepTumor";NA;203;0
"Building";"CreepTumor";NA;203;0
"Building";"CreepTumor";NA;203;0
"Building";"CreepTumor";NA;203;0
"Building";"CreepTumor";NA;203;0
"Building";"CreepTumor";NA;203;0
"Building";"CreepTumor";NA;203;0
"Unit";"Zergling";"Larva";203;1
"Unit";"Zergling";"Larva";204;1
"Unit";"Zergling";"Larva";205;1
"Unit";"Zergling";"Larva";206;1
"Unit";"Zergling";"Larva";207;1
"Unit";"Zergling";"Larva";208;1
"Unit";"Baneling";"Zergling";209;0
"Unit";"Baneling";"Zergling";209;0
"Unit";"Baneling";"Zergling";209;0
"Unit";"Hydralisk";"Larva";209;2
"Unit";"Hydralisk";"Larva";211;2
"Unit";"Zergling";"Larva";213;1
"Unit";"Zergling";"Larva";214;1
"Unit";"Zergling";"Larva";215;1
"Unit";"Zergling";"Larva";216;1
"Unit";"Zergling";"Larva";217;1
"Unit";"Zergling";"Larva";218;1
"Unit";"Hydralisk";"Larva";219;2
"Unit";"Zergling";"Larva";221;1
"Unit";"Zergling";"Larva";222;1
"Unit";"Zergling";"Larva";223;1
"Unit";"Zergling";"Larva";224;1
"Unit";"Zergling";"Larva";225;1
"Unit";"Zergling";"Larva";226;1
"Unit";"Zergling";"Larva";227;1
"Unit";"Zergling";"Larva";228;1
"Unit";"Zergling";"Larva";229;1
"Unit";"Zergling";"Larva";230;1
"Unit";"Zergling";"Larva";231;1
"Unit";"Zergling";"Larva";232;1
"Unit";"Zergling";"Larva";233;1
"Unit";"Zergling";"Larva";234;1
"Unit";"Zergling";"Larva";235;1
"Unit";"Zergling";"Larva";236;1
"Unit";"Zergling";"Larva";237;1
"Unit";"Zergling";"Larva";238;1
"Building";"CreepTumor";NA;239;0
"Building";"CreepTumor";NA;239;0
"Building";"CreepTumor";NA;239;0
"Building";"CreepTumor";NA;239;0
"Building";"CreepTumor";NA;239;0
"Building";"CreepTumor";NA;239;0
"Building";"CreepTumor";NA;239;0
"Building";"CreepTumor";NA;239;0
"Building";"CreepTumor";NA;239;0
"Building";"CreepTumor";NA;239;0
"Unit";"Overlord";"Larva";239;0
"Unit";"Hydralisk";"Larva";239;2
"Unit";"Hydralisk";"Larva";241;2
"Unit";"Zergling";"Larva";243;1
"Unit";"Zergling";"Larva";244;1
"Unit";"Hydralisk";"Larva";245;2
"Unit";"Hydralisk";"Larva";247;2
"Unit";"Zergling";"Larva";249;1
"Unit";"Zergling";"Larva";250;1
"Unit";"Zergling";"Larva";251;1
"Unit";"Zergling";"Larva";252;1
"Unit";"Zergling";"Larva";253;1
"Unit";"Zergling";"Larva";254;1
"Unit";"Zergling";"Larva";255;1
"Unit";"Zergling";"Larva";256;1
"Unit";"Zergling";"Larva";257;1
"Unit";"Zergling";"Larva";258;1
"Unit";"Zergling";"Larva";259;1
"Unit";"Zergling";"Larva";260;1
"Building";"Hatchery";NA;261;0
"Unit";"Overlord";"Larva";261;0
"Unit";"Overlord";"Larva";261;0
"Building";"CreepTumorQueen";NA;261;0
"Building";"CreepTumorQueen";NA;261;0
"Unit";"Zergling";"Larva";261;1
"Unit";"Zergling";"Larva";262;1
"Unit";"Zergling";"Larva";263;1
"Unit";"Zergling";"Larva";264;1
"Unit";"Zergling";"Larva";265;1
"Unit";"Zergling";"Larva";266;1
"Unit";"Zergling";"Larva";267;1
"Unit";"Zergling";"Larva";268;1
"Unit";"Zergling";"Larva";269;1
"Unit";"Zergling";"Larva";270;1
"Unit";"Zergling";"Larva";271;1
"Unit";"Zergling";"Larva";272;1
"Unit";"Zergling";"Larva";273;1
"Unit";"Zergling";"Larva";274;1
"Building";"Hatchery";NA;275;0
"Building";"CreepTumor";NA;275;0
"Building";"CreepTumor";NA;275;0
"Building";"CreepTumor";NA;275;0
"Unit";"Viper";"Larva";275;3
"Unit";"Viper";"Larva";278;3
"Unit";"Viper";"Larva";281;3
"Unit";"Baneling";"Zergling";284;0
"Unit";"Baneling";"Zergling";284;0
"Unit";"Baneling";"Zergling";284;0
"Unit";"Baneling";"Zergling";284;0
"Unit";"Baneling";"Zergling";284;0
"Unit";"Hydralisk";"Larva";284;2
"Unit";"Zergling";"Larva";286;1
"Unit";"Zergling";"Larva";287;1
"Unit";"Zergling";"Larva";288;1
"Unit";"Zergling";"Larva";289;1
"Unit";"Zergling";"Larva";290;1
"Unit";"Zergling";"Larva";291;1
"Unit";"Zergling";"Larva";292;1
"Unit";"Zergling";"Larva";293;1
"Unit";"Zergling";"Larva";294;1
"Unit";"Zergling";"Larva";295;1
"Unit";"Zergling";"Larva";296;1
"Unit";"Zergling";"Larva";297;1
"Unit";"Baneling";"Zergling";298;0
"Unit";"Baneling";"Zergling";298;0
"Unit";"Baneling";"Zergling";298;0
"Unit";"Hydralisk";"Larva";298;2
"Unit";"Zergling";"Larva";300;1
"Unit";"Zergling";"Larva";301;1
"Unit";"Zergling";"Larva";302;1
"Unit";"Zergling";"Larva";303;1
"Unit";"Zergling";"Larva";304;1
"Unit";"Zergling";"Larva";305;1
"Unit";"Zergling";"Larva";306;1
"Unit";"Zergling";"Larva";307;1
"Unit";"Zergling";"Larva";308;1
"Unit";"Zergling";"Larva";309;1
"Unit";"Zergling";"Larva";310;1
"Unit";"Zergling";"Larva";311;1
"Unit";"Hydralisk";"Larva";312;2
"Unit";"Zergling";"Larva";314;1
"Unit";"Zergling";"Larva";315;1
"Unit";"Hydralisk";"Larva";316;2
"Unit";"Hydralisk";"Larva";318;2
"Unit";"Hydralisk";"Larva";320;2
"Unit";"Hydralisk";"Larva";322;2
"Building";"CreepTumor";NA;324;0
"Building";"CreepTumor";NA;324;0
"Building";"CreepTumor";NA;324;0
"Building";"Hatchery";NA;324;0
"Building";"CreepTumorQueen";NA;324;0
"Unit";"Hydralisk";"Larva";324;2
"Unit";"Zergling";"Larva";326;1
"Unit";"Zergling";"Larva";327;1
"Unit";"Zergling";"Larva";328;1
"Unit";"Zergling";"Larva";329;1
"Unit";"Zergling";"Larva";330;1
"Unit";"Zergling";"Larva";331;1
"Unit";"Zergling";"Larva";332;1
"Unit";"Zergling";"Larva";333;1
"Unit";"Zergling";"Larva";334;1
"Unit";"Zergling";"Larva";335;1
"Unit";"Zergling";"Larva";336;1
"Unit";"Zergling";"Larva";337;1
"Unit";"Zergling";"Larva";338;1
"Unit";"Zergling";"Larva";339;1
"Unit";"Zergling";"Larva";340;1
"Unit";"Zergling";"Larva";341;1
"Unit";"Zergling";"Larva";342;1
"Unit";"Zergling";"Larva";343;1
"Building";"CreepTumorQueen";NA;344;0
"Building";"CreepTumorQueen";NA;344;0
"Unit";"Hydralisk";"Larva";344;2
"Unit";"Hydralisk";"Larva";346;2
"Unit";"Zergling";"Larva";348;1
"Unit";"Zergling";"Larva";349;1
"Unit";"Corruptor";"Larva";351;2
"Unit";"Corruptor";"Larva";353;2
"Unit";"Corruptor";"Larva";355;2
"Unit";"Corruptor";"Larva";357;2
"Unit";"Corruptor";"Larva";359;2
"Unit";"Corruptor";"Larva";361;2
"Unit";"Corruptor";"Larva";363;2
"Building";"CreepTumor";NA;365;0
"Building";"CreepTumor";NA;365;0
"Unit";"Baneling";"Zergling";365;0
"Unit";"Baneling";"Zergling";365;0
"Unit";"Baneling";"Zergling";365;0
"Unit";"Baneling";"Zergling";365;0
"Unit";"Zergling";"Larva";365;1
"Unit";"Zergling";"Larva";366;1
"Unit";"Zergling";"Larva";367;1
"Unit";"Zergling";"Larva";368;1
"Unit";"Zergling";"Larva";369;1
"Unit";"Zergling";"Larva";370;1
"Building";"Extractor";NA;371;0
"Building";"Extractor";NA;371;0
"Unit";"Zergling";"Larva";371;1
"Unit";"Zergling";"Larva";372;1
"Unit";"Zergling";"Larva";373;1
"Unit";"Zergling";"Larva";374;1
"Unit";"Zergling";"Larva";375;1
"Unit";"Zergling";"Larva";376;1
"Unit";"Zergling";"Larva";377;1
"Unit";"Zergling";"Larva";378;1
"Unit";"Zergling";"Larva";379;1
"Unit";"Zergling";"Larva";380;1
"Unit";"Zergling";"Larva";381;1
"Unit";"Zergling";"Larva";382;1
"Unit";"Zergling";"Larva";383;1
"Unit";"Zergling";"Larva";384;1
"Unit";"Zergling";"Larva";385;1
"Unit";"Zergling";"Larva";386;1
"Unit";"Zergling";"Larva";387;1
"Unit";"Zergling";"Larva";388;1
"Unit";"Zergling";"Larva";389;1
"Unit";"Zergling";"Larva";390;1
"Unit";"Zergling";"Larva";391;1
"Unit";"Zergling";"Larva";392;1
"Building";"CreepTumor";NA;393;0
"Building";"CreepTumor";NA;393;0
"Building";"CreepTumor";NA;393;0
"Building";"CreepTumorQueen";NA;393;0
"Building";"CreepTumorQueen";NA;399;0
"Building";"CreepTumorQueen";NA;403;0
"Building";"Extractor";NA;403;0
"Building";"CreepTumorQueen";NA;403;0
"Building";"Extractor";NA;403;0
"Building";"CreepTumorQueen";NA;403;0
"Building";"CreepTumorQueen";NA;403;0
"Building";"Hatchery";NA;403;0
"Building";"CreepTumor";NA;410;0
"Unit";"Baneling";"Zergling";410;0
"Unit";"Baneling";"Zergling";410;0
"Unit";"Baneling";"Zergling";410;0
"Unit";"Baneling";"Zergling";410;0
"Unit";"Baneling";"Zergling";410;0
"Unit";"Baneling";"Zergling";410;0
"Building";"CreepTumor";NA;410;0
"Building";"CreepTumor";NA;410;0
"Building";"CreepTumor";NA;410;0
"Unit";"Hydralisk";"Larva";410;2
"Unit";"Hydralisk";"Larva";412;2
"Unit";"Hydralisk";"Larva";414;2
"Unit";"Hydralisk";"Larva";416;2
"Unit";"Zergling";"Larva";418;1
"Unit";"Zergling";"Larva";419;1
"Building";"CreepTumor";NA;427;0
"Building";"CreepTumor";NA;427;0
"Unit";"Hydralisk";"Larva";444;2
"Unit";"Hydralisk";"Larva";446;2
"Unit";"Hydralisk";"Larva";448;2
"Building";"CreepTumor";NA;453;0
"Building";"CreepTumor";NA;453;0
"Building";"CreepTumor";NA;453;0
"Building";"CreepTumor";NA;453;0
"Building";"CreepTumorQueen";NA;453;0
"Building";"CreepTumorQueen";NA;453;0
"Building";"CreepTumor";NA;453;0
"Building";"CreepTumor";NA;453;0
"Building";"CreepTumor";NA;453;0
"Unit";"Hydralisk";"Larva";453;2
"Unit";"Hydralisk";"Larva";455;2
"Unit";"Hydralisk";"Larva";457;2
"Unit";"Hydralisk";"Larva";459;2
"Unit";"Hydralisk";"Larva";461;2
"Unit";"Zergling";"Larva";463;1
"Unit";"Zergling";"Larva";464;1
"Unit";"Zergling";"Larva";465;1
"Unit";"Zergling";"Larva";466;1
"Unit";"Zergling";"Larva";467;1
"Unit";"Zergling";"Larva";468;1
"Unit";"Zergling";"Larva";469;1
"Unit";"Zergling";"Larva";470;1
"Building";"CreepTumor";NA;472;0
"Building";"CreepTumor";NA;472;0
"Building";"CreepTumor";NA;472;0
"Building";"CreepTumorQueen";NA;472;0
"Building";"CreepTumorQueen";NA;472;0
"Building";"SporeCrawler";NA;472;0
"Building";"CreepTumor";NA;478;0
"Building";"CreepTumor";NA;478;0
"Building";"CreepTumor";NA;478;0
"Building";"SporeCrawler";NA;478;0
"Building";"CreepTumor";NA;478;0
"Building";"SporeCrawler";NA;478;0
"Building";"CreepTumor";NA;478;0
"Building";"SporeCrawler";NA;478;0
"Unit";"Hydralisk";"Larva";478;2
"Unit";"Zergling";"Larva";480;1
"Unit";"Zergling";"Larva";481;1
"Building";"CreepTumor";NA;482;0
"Building";"CreepTumor";NA;482;0
"Building";"CreepTumor";NA;482;0
"Building";"UltraliskCavern";NA;482;0
"Building";"SpineCrawler";NA;487;0
"Building";"CreepTumor";NA;487;0
"Building";"CreepTumor";NA;487;0
"Building";"CreepTumor";NA;487;0
"Building";"CreepTumor";NA;487;0
"Building";"CreepTumor";NA;487;0
"Building";"CreepTumor";NA;487;0
"Building";"SpineCrawler";NA;487;0
"Unit";"Hydralisk";"Larva";487;2
"Unit";"Hydralisk";"Larva";489;2
"Unit";"Hydralisk";"Larva";491;2
"Unit";"Hydralisk";"Larva";493;2
"Unit";"Hydralisk";"Larva";495;2
"Building";"CreepTumor";NA;497;0
"Building";"CreepTumor";NA;497;0
"Building";"CreepTumor";NA;497;0
"Building";"CreepTumorQueen";NA;497;0
"Building";"CreepTumorQueen";NA;497;0
"Building";"CreepTumor";NA;497;0
"Building";"CreepTumor";NA;497;0
"Building";"CreepTumor";NA;497;0
"Building";"Hatchery";NA;497;0
"Building";"SporeCrawler";NA;497;0
"Building";"SporeCrawler";NA;497;0
"Building";"Spire";NA;497;0
"Unit";"Viper";"Larva";497;3
"Unit";"Viper";"Larva";500;3
"Unit";"Viper";"Larva";503;3
"Unit";"Hydralisk";"Larva";506;2
"Unit";"Hydralisk";"Larva";508;2
"Unit";"Hydralisk";"Larva";510;2
"Unit";"Hydralisk";"Larva";512;2
"Unit";"Hydralisk";"Larva";514;2
"Unit";"Hydralisk";"Larva";516;2
"Unit";"Hydralisk";"Larva";518;2
"Unit";"Hydralisk";"Larva";520;2
"Unit";"Hydralisk";"Larva";522;2
"Unit";"Zergling";"Larva";524;1
"Unit";"Zergling";"Larva";525;1
"Unit";"Zergling";"Larva";526;1
"Unit";"Zergling";"Larva";527;1
"Unit";"Zergling";"Larva";528;1
"Unit";"Zergling";"Larva";529;1
"Unit";"Zergling";"Larva";530;1
"Unit";"Zergling";"Larva";531;1
"Unit";"Zergling";"Larva";532;1
"Unit";"Zergling";"Larva";533;1
"Unit";"Zergling";"Larva";534;1
"Unit";"Zergling";"Larva";535;1
"Unit";"Hydralisk";"Larva";536;2
"Unit";"Hydralisk";"Larva";538;2
"Upgrade";"ChitinousPlating";"UltraliskCavern";540;0
"Unit";"Hydralisk";"Larva";540;2
"Unit";"Hydralisk";"Larva";542;2
"Unit";"Hydralisk";"Larva";544;2
"Unit";"Hydralisk";"Larva";546;2
"Unit";"Hydralisk";"Larva";548;2
"Unit";"Hydralisk";"Larva";550;2
"Unit";"Hydralisk";"Larva";552;2
"Unit";"Hydralisk";"Larva";554;2
"Unit";"Hydralisk";"Larva";556;2
"Unit";"Hydralisk";"Larva";558;2
"Unit";"Hydralisk";"Larva";560;2
"Unit";"Baneling";"Zergling";562;0
"Unit";"Baneling";"Zergling";562;0
"Unit";"Baneling";"Zergling";562;0
"Unit";"Baneling";"Zergling";562;0
"Unit";"Baneling";"Zergling";562;0
"Unit";"Baneling";"Zergling";562;0
"Unit";"Baneling";"Zergling";562;0
"Unit";"Hydralisk";"Larva";562;2
"Unit";"Hydralisk";"Larva";564;2
"Unit";"Hydralisk";"Larva";566;2
"Unit";"Hydralisk";"Larva";568;2
"Unit";"Hydralisk";"Larva";570;2
"Unit";"Hydralisk";"Larva";572;2
"Unit";"Ultralisk";"Larva";577;6
"Unit";"Ultralisk";"Larva";583;6
"Unit";"Ultralisk";"Larva";589;6
"Unit";"Hydralisk";"Larva";595;2
"Unit";"Hydralisk";"Larva";597;2
"Unit";"Hydralisk";"Larva";599;2
"Unit";"Hydralisk";"Larva";601;2
"Unit";"Hydralisk";"Larva";603;2
"Unit";"Hydralisk";"Larva";605;2
"Unit";"Hydralisk";"Larva";607;2
"Unit";"Hydralisk";"Larva";609;2
"Unit";"Zergling";"Larva";611;1
"Unit";"Zergling";"Larva";612;1
"Building";"CreepTumor";NA;613;0
"Building";"CreepTumor";NA;613;0
"Building";"CreepTumor";NA;613;0
"Unit";"Zergling";"Larva";618;1
"Unit";"Zergling";"Larva";619;1
"Unit";"Zergling";"Larva";620;1
"Unit";"Zergling";"Larva";621;1
"Unit";"Zergling";"Larva";622;1
"Unit";"Zergling";"Larva";623;1
"Unit";"Zergling";"Larva";624;1
"Unit";"Zergling";"Larva";625;1
"Unit";"Zergling";"Larva";626;1
"Unit";"Zergling";"Larva";627;1
"Unit";"Zergling";"Larva";628;1
"Unit";"Zergling";"Larva";629;1
"Unit";"Zergling";"Larva";630;1
"Unit";"Zergling";"Larva";631;1
"Unit";"Zergling";"Larva";632;1
"Unit";"Zergling";"Larva";633;1
"Unit";"Zergling";"Larva";634;1
"Unit";"Zergling";"Larva";635;1
"Unit";"Zergling";"Larva";636;1
"Unit";"Zergling";"Larva";637;1
"Building";"CreepTumor";NA;638;0
"Building";"CreepTumor";NA;638;0
"Building";"CreepTumor";NA;654;0
"Building";"CreepTumor";NA;654;0
"Building";"CreepTumor";NA;654;0
"Unit";"Zergling";"Larva";654;1
"Unit";"Zergling";"Larva";655;1
"Unit";"Zergling";"Larva";656;1
"Unit";"Zergling";"Larva";657;1
"Unit";"Zergling";"Larva";658;1
"Unit";"Zergling";"Larva";659;1
"Unit";"Zergling";"Larva";660;1
"Unit";"Zergling";"Larva";661;1
"Unit";"Zergling";"Larva";662;1
"Unit";"Zergling";"Larva";663;1
"Unit";"Zergling";"Larva";664;1
"Unit";"Zergling";"Larva";665;1
"Unit";"Zergling";"Larva";666;1
"Unit";"Zergling";"Larva";667;1
"Unit";"Zergling";"Larva";668;1
"Unit";"Zergling";"Larva";669;1
"Unit";"Zergling";"Larva";670;1
"Unit";"Zergling";"Larva";671;1
"Unit";"Zergling";"Larva";672;1
"Unit";"Zergling";"Larva";673;1
"Unit";"Zergling";"Larva";674;1
"Unit";"Zergling";"Larva";675;1
"Unit";"Ultralisk";"Larva";676;6
"Unit";"Zergling";"Larva";682;1
"Unit";"Zergling";"Larva";683;1
"Unit";"Zergling";"Larva";684;1
"Unit";"Zergling";"Larva";685;1
"Unit";"Overlord";"Larva";686;0
"Unit";"Overlord";"Larva";686;0
"Unit";"Overlord";"Larva";686;0
"Unit";"Overlord";"Larva";686;0
"Unit";"Ultralisk";"Larva";686;6
"Unit";"Zergling";"Larva";692;1
"Unit";"Zergling";"Larva";693;1
"Unit";"Zergling";"Larva";694;1
"Unit";"Zergling";"Larva";695;1
"Unit";"Zergling";"Larva";696;1
"Unit";"Zergling";"Larva";697;1
"Unit";"Zergling";"Larva";698;1
"Unit";"Zergling";"Larva";699;1
"Unit";"Zergling";"Larva";700;1
"Unit";"Zergling";"Larva";701;1
"Unit";"Zergling";"Larva";702;1
"Unit";"Zergling";"Larva";703;1
"Unit";"Hydralisk";"Larva";704;2
"Unit";"Hydralisk";"Larva";706;2
"Unit";"Hydralisk";"Larva";708;2
"Unit";"Hydralisk";"Larva";710;2
"Unit";"Hydralisk";"Larva";712;2
"Unit";"Ultralisk";"Larva";714;6
"Unit";"Ultralisk";"Larva";720;6
"Unit";"Ultralisk";"Larva";726;6
"Unit";"Ultralisk";"Larva";732;6
"Unit";"Zergling";"Larva";738;1
"Unit";"Zergling";"Larva";739;1
"Unit";"Zergling";"Larva";740;1
"Unit";"Zergling";"Larva";741;1
"Unit";"Zergling";"Larva";742;1
"Unit";"Zergling";"Larva";743;1
"Unit";"Zergling";"Larva";744;1
"Unit";"Zergling";"Larva";745;1
"Unit";"Viper";"Larva";750;3
"Unit";"Viper";"Larva";753;3
"Unit";"Viper";"Larva";756;3
"Building";"BanelingNest";NA;759;0
"Building";"CreepTumorQueen";NA;759;0
"Building";"CreepTumorQueen";NA;759;0
"Unit";"Hydralisk";"Larva";759;2
"Unit";"Hydralisk";"Larva";761;2
"Unit";"Hydralisk";"Larva";763;2
"Unit";"Hydralisk";"Larva";765;2
"Unit";"Hydralisk";"Larva";767;2
"Unit";"Hydralisk";"Larva";769;2
"Unit";"Hydralisk";"Larva";771;2
"Building";"CreepTumorQueen";NA;773;0
"Building";"Hatchery";NA;773;0
"Unit";"Hydralisk";"Larva";778;2
"Unit";"Hydralisk";"Larva";780;2
"Unit";"Hydralisk";"Larva";782;2
"Unit";"Hydralisk";"Larva";784;2
"Unit";"Hydralisk";"Larva";786;2
"Unit";"Zergling";"Larva";788;1
"Unit";"Zergling";"Larva";789;1
"Unit";"Zergling";"Larva";790;1
"Unit";"Zergling";"Larva";791;1
"Unit";"Zergling";"Larva";792;1
"Unit";"Zergling";"Larva";793;1
"Building";"CreepTumor";NA;801;0
"Building";"CreepTumor";NA;801;0
"Building";"CreepTumor";NA;801;0
"Unit";"Zergling";"Larva";801;1
"Unit";"Zergling";"Larva";802;1
"Unit";"Zergling";"Larva";803;1
"Unit";"Zergling";"Larva";804;1
"Unit";"Zergling";"Larva";805;1
"Unit";"Zergling";"Larva";806;1
"Unit";"Zergling";"Larva";807;1
"Unit";"Zergling";"Larva";808;1
"Unit";"Overlord";"Larva";809;0
"Unit";"Overlord";"Larva";809;0
"Unit";"Overlord";"Larva";809;0
"Building";"SpineCrawler";NA;809;0
"Unit";"Baneling";"Zergling";809;0
"Unit";"Baneling";"Zergling";809;0
"Unit";"Zergling";"Larva";809;1
"Unit";"Zergling";"Larva";810;1
"Unit";"Overlord";"Larva";811;0
"Unit";"Zergling";"Larva";816;1
"Unit";"Zergling";"Larva";817;1
"Unit";"Zergling";"Larva";818;1
"Unit";"Zergling";"Larva";819;1
"Unit";"Zergling";"Larva";820;1
"Unit";"Zergling";"Larva";821;1
"Unit";"Zergling";"Larva";822;1
"Unit";"Zergling";"Larva";823;1
"Unit";"Zergling";"Larva";824;1
"Unit";"Zergling";"Larva";825;1
"Unit";"Zergling";"Larva";826;1
"Unit";"Zergling";"Larva";827;1
"Unit";"Zergling";"Larva";828;1
"Unit";"Zergling";"Larva";829;1
"Building";"CreepTumor";NA;830;0
"Building";"CreepTumor";NA;830;0
"Building";"CreepTumor";NA;830;0
"Building";"CreepTumor";NA;830;0
"Unit";"Hydralisk";"Larva";830;2
"Unit";"Hydralisk";"Larva";832;2
"Unit";"Hydralisk";"Larva";834;2
"Unit";"Hydralisk";"Larva";836;2
"Unit";"Hydralisk";"Larva";838;2
"Unit";"Hydralisk";"Larva";840;2
"Unit";"Hydralisk";"Larva";842;2
"Unit";"Zergling";"Larva";844;1
"Unit";"Zergling";"Larva";845;1
"Unit";"Zergling";"Larva";846;1
"Unit";"Zergling";"Larva";847;1
"Unit";"Hydralisk";"Larva";848;2
"Unit";"Hydralisk";"Larva";850;2
"Unit";"Hydralisk";"Larva";852;2
"Unit";"Hydralisk";"Larva";854;2
"Unit";"Hydralisk";"Larva";856;2
"Unit";"Hydralisk";"Larva";858;2
"Unit";"Hydralisk";"Larva";860;2
"Unit";"Zergling";"Larva";862;1
"Unit";"Zergling";"Larva";863;1
"Unit";"Viper";"Larva";864;3
"Unit";"Viper";"Larva";867;3
"Unit";"Viper";"Larva";870;3
"Unit";"Zergling";"Larva";873;1
"Unit";"Zergling";"Larva";874;1
"Unit";"Zergling";"Larva";875;1
"Unit";"Zergling";"Larva";876;1
"Unit";"Zergling";"Larva";877;1
"Unit";"Zergling";"Larva";878;1
"Unit";"Zergling";"Larva";879;1
"Unit";"Zergling";"Larva";880;1
"Unit";"Zergling";"Larva";881;1
"Unit";"Zergling";"Larva";882;1
"Unit";"Zergling";"Larva";883;1
"Unit";"Zergling";"Larva";884;1
"Unit";"Zergling";"Larva";885;1
"Unit";"Zergling";"Larva";886;1
"Unit";"Zergling";"Larva";887;1
"Unit";"Zergling";"Larva";888;1
"Unit";"Zergling";"Larva";889;1
"Unit";"Zergling";"Larva";890;1
"Building";"Extractor";NA;891;0
"Building";"SpineCrawler";NA;898;0
"Building";"CreepTumorQueen";NA;898;0
"Building";"CreepTumorQueen";NA;898;0
"Building";"CreepTumorQueen";NA;898;0
"Building";"CreepTumorQueen";NA;898;0
"Unit";"Zergling";"Larva";898;1
"Unit";"Zergling";"Larva";899;1
"Unit";"Zergling";"Larva";900;1
"Unit";"Zergling";"Larva";901;1
"Unit";"Zergling";"Larva";902;1
"Unit";"Zergling";"Larva";903;1
"Unit";"Zergling";"Larva";904;1
"Unit";"Zergling";"Larva";905;1
"Unit";"Zergling";"Larva";906;1
"Unit";"Zergling";"Larva";907;1
"Unit";"Zergling";"Larva";908;1
"Unit";"Zergling";"Larva";909;1
"Unit";"Baneling";"Zergling";910;0
"Unit";"Baneling";"Zergling";910;0
"Unit";"Baneling";"Zergling";910;0
"Unit";"Baneling";"Zergling";910;0
"Unit";"Baneling";"Zergling";910;0
"Unit";"Baneling";"Zergling";910;0
"Unit";"Baneling";"Zergling";910;0
"Unit";"Baneling";"Zergling";910;0
"Unit";"Baneling";"Zergling";910;0
"Unit";"Baneling";"Zergling";910;0
"Unit";"Baneling";"Zergling";910;0
"Unit";"Zergling";"Larva";910;1
"Unit";"Zergling";"Larva";911;1
"Unit";"Zergling";"Larva";912;1
"Unit";"Zergling";"Larva";913;1
"Unit";"Zergling";"Larva";914;1
"Unit";"Zergling";"Larva";915;1
"Building";"CreepTumor";NA;916;0
"Building";"CreepTumor";NA;916;0
"Building";"CreepTumor";NA;916;0
"Building";"SpineCrawler";NA;916;0
"Building";"Hatchery";NA;916;0
"Unit";"Zergling";"Larva";922;1
"Unit";"Zergling";"Larva";923;1
"Unit";"Zergling";"Larva";924;1
"Unit";"Zergling";"Larva";925;1
"Unit";"Zergling";"Larva";926;1
"Unit";"Zergling";"Larva";927;1
"Unit";"Zergling";"Larva";928;1
"Unit";"Zergling";"Larva";929;1
"Unit";"Zergling";"Larva";930;1
"Unit";"Zergling";"Larva";931;1
"Building";"Extractor";NA;932;0
"Building";"Extractor";NA;932;0
"Unit";"Zergling";"Larva";932;1
"Unit";"Zergling";"Larva";933;1
"Unit";"Zergling";"Larva";934;1
"Unit";"Zergling";"Larva";935;1
"Unit";"Zergling";"Larva";936;1
"Unit";"Zergling";"Larva";937;1
"Unit";"Zergling";"Larva";938;1
"Unit";"Zergling";"Larva";939;1
"Unit";"Zergling";"Larva";940;1
"Unit";"Zergling";"Larva";941;1
"Unit";"Zergling";"Larva";942;1
"Unit";"Zergling";"Larva";943;1
"Unit";"Zergling";"Larva";944;1
"Unit";"Zergling";"Larva";945;1
"Unit";"Zergling";"Larva";946;1
"Unit";"Zergling";"Larva";947;1
"Unit";"Zergling";"Larva";948;1
"Unit";"Zergling";"Larva";949;1
"Unit";"Zergling";"Larva";950;1
"Unit";"Zergling";"Larva";951;1
"Unit";"Zergling";"Larva";952;1
"Unit";"Zergling";"Larva";953;1
"Unit";"Zergling";"Larva";954;1
"Unit";"Zergling";"Larva";955;1
"Unit";"Zergling";"Larva";956;1
"Unit";"Zergling";"Larva";957;1
"Unit";"Zergling";"Larva";958;1
"Unit";"Zergling";"Larva";959;1
"Building";"CreepTumor";NA;963;0
"Building";"CreepTumor";NA;963;0
"Unit";"Ultralisk";"Larva";968;6
"Unit";"Ultralisk";"Larva";974;6
"Unit";"Ultralisk";"Larva";980;6
"Building";"Hatchery";NA;986;0
"Unit";"Ultralisk";"Larva";986;6
"Unit";"Zergling";"Larva";992;1
"Unit";"Zergling";"Larva";993;1
"Unit";"Zergling";"Larva";994;1
"Unit";"Zergling";"Larva";995;1
"Unit";"Zergling";"Larva";996;1
"Unit";"Zergling";"Larva";997;1
"Unit";"Zergling";"Larva";998;1
"Unit";"Zergling";"Larva";999;1
"Unit";"Zergling";"Larva";1000;1
"Unit";"Zergling";"Larva";1001;1
"Unit";"Zergling";"Larva";1002;1
"Unit";"Zergling";"Larva";1003;1
"Unit";"Zergling";"Larva";1004;1
"Unit";"Zergling";"Larva";1005;1
"Unit";"Baneling";"Zergling";1006;0
"Unit";"Baneling";"Zergling";1006;0
"Unit";"Baneling";"Zergling";1006;0
"Unit";"Baneling";"Zergling";1006;0
"Unit";"Baneling";"Zergling";1006;0
"Unit";"Baneling";"Zergling";1006;0
"Unit";"Baneling";"Zergling";1006;0
"Unit";"Baneling";"Zergling";1006;0
"Unit";"Baneling";"Zergling";1006;0
"Unit";"Baneling";"Zergling";1006;0
"Unit";"Baneling";"Zergling";1006;0
"Unit";"Baneling";"Zergling";1006;0
"Unit";"Ultralisk";"Larva";1008;6
"Unit";"Ultralisk";"Larva";1014;6
"Unit";"Hydralisk";"Larva";1020;2
"Unit";"Zergling";"Larva";1022;1
"Unit";"Zergling";"Larva";1023;1
"Unit";"Viper";"Larva";1024;3
"Unit";"Viper";"Larva";1027;3
"Unit";"Zergling";"Larva";1030;1
"Unit";"Zergling";"Larva";1031;1
"Unit";"Zergling";"Larva";1032;1
"Unit";"Zergling";"Larva";1033;1
"Unit";"Zergling";"Larva";1034;1
"Unit";"Zergling";"Larva";1035;1
"Unit";"Zergling";"Larva";1036;1
"Unit";"Zergling";"Larva";1037;1
"Unit";"Zergling";"Larva";1038;1
"Unit";"Zergling";"Larva";1039;1
"Unit";"Zergling";"Larva";1040;1
"Unit";"Zergling";"Larva";1041;1
"Unit";"Zergling";"Larva";1042;1
"Unit";"Zergling";"Larva";1043;1
"Unit";"Zergling";"Larva";1044;1
"Unit";"Zergling";"Larva";1045;1
"Unit";"Zergling";"Larva";1046;1
"Unit";"Zergling";"Larva";1047;1
"Unit";"Zergling";"Larva";1048;1
"Unit";"Zergling";"Larva";1049;1
"Unit";"Zergling";"Larva";1050;1
"Unit";"Zergling";"Larva";1051;1
"Unit";"Zergling";"Larva";1052;1
"Unit";"Zergling";"Larva";1053;1
"Unit";"Zergling";"Larva";1054;1
"Unit";"Zergling";"Larva";1055;1
"Unit";"Zergling";"Larva";1056;1
"Unit";"Zergling";"Larva";1057;1
"Unit";"Zergling";"Larva";1058;1
"Unit";"Zergling";"Larva";1059;1
"Unit";"Zergling";"Larva";1060;1
"Unit";"Zergling";"Larva";1061;1
"Unit";"Zergling";"Larva";1062;1
"Unit";"Zergling";"Larva";1063;1
"Unit";"Overlord";"Larva";1064;0
"Building";"Extractor";NA;1064;0
"Building";"Extractor";NA;1064;0
"Building";"Extractor";NA;1064;0
"Unit";"Baneling";"Zergling";1064;0
"Unit";"Baneling";"Zergling";1064;0
"Unit";"Baneling";"Zergling";1064;0
"Unit";"Baneling";"Zergling";1064;0
"Unit";"Baneling";"Zergling";1064;0
"Unit";"Baneling";"Zergling";1064;0
"Unit";"Baneling";"Zergling";1064;0
"Unit";"Baneling";"Zergling";1064;0
"Building";"Extractor";NA;1064;0
"Building";"CreepTumor";NA;1064;0
"Building";"CreepTumor";NA;1064;0
"Unit";"Viper";"Larva";1064;3
"Unit";"Zergling";"Larva";1070;1
"Unit";"Zergling";"Larva";1071;1
"Unit";"Zergling";"Larva";1072;1
"Unit";"Zergling";"Larva";1073;1
"Unit";"Zergling";"Larva";1074;1
"Unit";"Zergling";"Larva";1075;1
"Unit";"Zergling";"Larva";1076;1
"Unit";"Zergling";"Larva";1077;1
"Unit";"Zergling";"Larva";1078;1
"Unit";"Zergling";"Larva";1079;1
"Unit";"Zergling";"Larva";1080;1
"Unit";"Zergling";"Larva";1081;1
"Unit";"Zergling";"Larva";1082;1
"Unit";"Zergling";"Larva";1083;1
"Unit";"Zergling";"Larva";1084;1
"Unit";"Zergling";"Larva";1085;1
"Unit";"Zergling";"Larva";1086;1
"Unit";"Zergling";"Larva";1087;1
"Unit";"Zergling";"Larva";1088;1
"Unit";"Zergling";"Larva";1089;1
"Unit";"Zergling";"Larva";1090;1
"Unit";"Zergling";"Larva";1091;1
"Unit";"Zergling";"Larva";1092;1
"Unit";"Zergling";"Larva";1093;1
"Unit";"Zergling";"Larva";1094;1
"Unit";"Zergling";"Larva";1095;1
"Unit";"Zergling";"Larva";1096;1
"Unit";"Zergling";"Larva";1097;1
"Unit";"Zergling";"Larva";1098;1
"Unit";"Zergling";"Larva";1099;1
"Unit";"Zergling";"Larva";1100;1
"Unit";"Zergling";"Larva";1101;1
"Unit";"Hydralisk";"Larva";1102;2
"Building";"Hatchery";NA;1104;0
"Building";"Hatchery";NA;1104;0
"Building";"Hatchery";NA;1104;0
"Building";"CreepTumorQueen";NA;1104;0
"Building";"CreepTumor";NA;1104;0
"Unit";"Viper";"Larva";1104;3
"Unit";"Viper";"Larva";1107;3
"Building";"Extractor";NA;1119;0
"Unit";"Queen";"Hatchery";1119;2
"Building";"CreepTumor";NA;1137;0
"Building";"CreepTumor";NA;1137;0
"Building";"CreepTumor";NA;1137;0
"Building";"CreepTumor";NA;1137;0
"Building";"Extractor";NA;1149;0
"Building";"Extractor";NA;1149;0
"Building";"Extractor";NA;1153;0
"Building";"Extractor";NA;1153;0
"Building";"CreepTumor";NA;1153;0
"Building";"CreepTumor";NA;1153;0
"Upgrade";"SprayZerg";NA;1153;0
"Upgrade";"SprayZerg";NA;1153;0
"Upgrade";"SprayZerg";NA;1153;0
"Upgrade";"zerglingmovementspeed";NA;1153;0
"Upgrade";"SprayZerg";NA;1153;0
"Upgrade";"SprayZerg";NA;1153;0
"Upgrade";"SprayZerg";NA;1153;0
"Upgrade";"EvolveMuscularAugments";NA;1153;0
"Upgrade";"ZergGroundArmorsLevel1";NA;1153;0
"Upgrade";"SprayZerg";NA;1153;0
"Upgrade";"CentrificalHooks";NA;1153;0
"Upgrade";"ZergMeleeWeaponsLevel1";NA;1153;0
"Upgrade";"SprayZerg";NA;1153;0
"Upgrade";"SprayZerg";NA;1153;0
"Upgrade";"SprayZerg";NA;1153;0
"Upgrade";"ZergMissileWeaponsLevel1";NA;1153;0
"Upgrade";"SprayZerg";NA;1153;0
"Upgrade";"SprayZerg";NA;1153;0
"Upgrade";"SprayZerg";NA;1153;0
"Upgrade";"ZergMeleeWeaponsLevel2";NA;1153;0
"Upgrade";"SprayZerg";NA;1153;0
"Upgrade";"SprayZerg";NA;1153;0
"Upgrade";"ZergMissileWeaponsLevel2";NA;1153;0
"Upgrade";"SprayZerg";NA;1153;0
"Upgrade";"SprayZerg";NA;1153;0
"Upgrade";"ZergFlyerArmorsLevel1";NA;1153;0
"Upgrade";"ZergGroundArmorsLevel2";NA;1153;0
"Upgrade";"zerglingattackspeed";NA;1153;0
"Upgrade";"overlordspeed";NA;1153;0
"Upgrade";"ZergMeleeWeaponsLevel3";NA;1153;0
"Upgrade";"SprayZerg";NA;1153;0
"Upgrade";"ZergFlyerArmorsLevel2";NA;1153;0
"Upgrade";"ZergMissileWeaponsLevel3";NA;1153;0
"Upgrade";"SprayZerg";NA;1153;0
"Upgrade";"SprayZerg";NA;1153;0
"Upgrade";"SprayZerg";NA;1153;0
"Upgrade";"ZergGroundArmorsLevel3";NA;1153;0
"Upgrade";"SprayZerg";NA;1153;0
"Upgrade";"SprayZerg";NA;1153;0
"Upgrade";"ZergFlyerWeaponsLevel1";NA;1153;0
"Upgrade";"SprayZerg";NA;1153;0
"Upgrade";"ZergFlyerArmorsLevel3";NA;1153;0
"Upgrade";"SprayZerg";NA;1153;0
"Upgrade";"SprayZerg";NA;1153;0
"Upgrade";"SprayZerg";NA;1153;0
"Upgrade";"SprayZerg";NA;1153;0
"Upgrade";"SprayZerg";NA;1153;0
"Upgrade";"SprayZerg";NA;1153;0
"Upgrade";"SprayZerg";NA;1153;0
"Upgrade";"SprayZerg";NA;1153;0
