"type";"unit_name";"on_building";"total_supply";"supply"
"Unit";"Overlord";"Larva";12;0
"Building";"Extractor";NA;17;0
"Building";"SpawningPool";NA;19;0
"Building";"Hatchery";NA;17;0
"Unit";"Overlord";"Larva";22;0
"Unit";"Zergling";"Larva";23;1
"Unit";"Zergling";"Larva";23;1
"Unit";"Zergling";"Larva";24;1
"Unit";"Zergling";"Larva";24;1
"Unit";"Queen";"Hatchery";23;2
"Unit";"Zergling";"Larva";27;1
"Unit";"Zergling";"Larva";27;1
"Unit";"Queen";"Hatchery";23;2
"Unit";"Overlord";"Larva";35;0
"Unit";"Overlord";"Larva";41;0
"Unit";"Overlord";"Larva";41;0
"Unit";"Overlord";"Larva";41;0
"Building";"EvolutionChamber";NA;42;0
"Building";"EvolutionChamber";NA;42;0
"Building";"Hatchery";NA;41;0
"Unit";"Queen";"Hatchery";49;2
"Unit";"Zergling";"Larva";56;1
"Unit";"Zergling";"Larva";56;1
"Unit";"Zergling";"Larva";56;1
"Unit";"Zergling";"Larva";56;1
"Unit";"Zergling";"Larva";56;1
"Unit";"Zergling";"Larva";56;1
"Unit";"Zergling";"Larva";56;1
"Unit";"Zergling";"Larva";56;1
"Unit";"Queen";"Hatchery";54;2
"Building";"CreepTumorQueen";NA;72;0
"Unit";"Zergling";"Larva";72;1
"Unit";"Zergling";"Larva";72;1
"Unit";"Zergling";"Larva";72;1
"Unit";"Zergling";"Larva";72;1
"Unit";"Zergling";"Larva";74;1
"Unit";"Zergling";"Larva";74;1
"Unit";"Overlord";"Larva";79;0
"Unit";"Overlord";"Larva";79;0
"Unit";"Overlord";"Larva";79;0
"Building";"CreepTumorQueen";NA;83;0
"Unit";"Overlord";"Larva";79;0
"Building";"CreepTumor";NA;83;0
"Building";"Extractor";NA;85;0
"Building";"Extractor";NA;85;0
"Building";"Extractor";NA;85;0
"Upgrade";"ZergMeleeWeaponsLevel1";"EvolutionChamber";64;0
"Upgrade";"ZergGroundArmorsLevel1";"EvolutionChamber";64;0
"Building";"Extractor";NA;88;0
"Unit";"Overlord";"Larva";99;0
"Unit";"Zergling";"Larva";103;1
"Unit";"Zergling";"Larva";103;1
"Unit";"Zergling";"Larva";103;1
"Unit";"Zergling";"Larva";103;1
"Unit";"Zergling";"Larva";103;1
"Unit";"Zergling";"Larva";103;1
"Unit";"Zergling";"Larva";103;1
"Unit";"Zergling";"Larva";103;1
"Unit";"Zergling";"Larva";103;1
"Unit";"Zergling";"Larva";103;1
"Unit";"Zergling";"Larva";103;1
"Unit";"Zergling";"Larva";103;1
"Unit";"Zergling";"Larva";103;1
"Unit";"Zergling";"Larva";103;1
"Unit";"Zergling";"Larva";103;1
"Unit";"Zergling";"Larva";103;1
"Unit";"Zergling";"Larva";103;1
"Unit";"Zergling";"Larva";103;1
"Unit";"Zergling";"Larva";103;1
"Unit";"Zergling";"Larva";103;1
"Unit";"Zergling";"Larva";103;1
"Unit";"Zergling";"Larva";103;1
"Unit";"Zergling";"Larva";103;1
"Unit";"Zergling";"Larva";103;1
"Building";"BanelingNest";NA;99;0
"Unit";"Zergling";"Larva";103;1
"Unit";"Zergling";"Larva";103;1
"Unit";"Zergling";"Larva";103;1
"Unit";"Zergling";"Larva";103;1
"Unit";"Zergling";"Larva";125;1
"Unit";"Zergling";"Larva";125;1
"Unit";"Zergling";"Larva";125;1
"Unit";"Zergling";"Larva";125;1
"Unit";"Zergling";"Larva";125;1
"Unit";"Zergling";"Larva";125;1
"Unit";"Zergling";"Larva";125;1
"Unit";"Zergling";"Larva";125;1
"Unit";"Zergling";"Larva";125;1
"Unit";"Zergling";"Larva";125;1
"Building";"Hatchery";NA;85;0
"Unit";"Queen";"Hatchery";131;2
"Unit";"Queen";"Hatchery";131;2
"Building";"HydraliskDen";NA;148;0
"Unit";"Queen";"Hatchery";146;2
"Unit";"Zergling";"Larva";151;1
"Unit";"Zergling";"Larva";151;1
"Unit";"Zergling";"Larva";151;1
"Unit";"Zergling";"Larva";151;1
"Unit";"Zergling";"Larva";151;1
"Unit";"Zergling";"Larva";151;1
"Unit";"Zergling";"Larva";151;1
"Unit";"Zergling";"Larva";151;1
"Unit";"Zergling";"Larva";151;1
"Unit";"Zergling";"Larva";151;1
"Unit";"Zergling";"Larva";151;1
"Unit";"Zergling";"Larva";151;1
"Unit";"Zergling";"Larva";151;1
"Unit";"Zergling";"Larva";151;1
"Unit";"Zergling";"Larva";151;1
"Unit";"Zergling";"Larva";151;1
"Unit";"Zergling";"Larva";151;1
"Unit";"Zergling";"Larva";151;1
"Unit";"Zergling";"Larva";151;1
"Unit";"Zergling";"Larva";151;1
"Unit";"Zergling";"Larva";151;1
"Unit";"Zergling";"Larva";151;1
"Unit";"Zergling";"Larva";151;1
"Unit";"Zergling";"Larva";151;1
"Unit";"Zergling";"Larva";151;1
"Unit";"Zergling";"Larva";151;1
"Unit";"Zergling";"Larva";151;1
"Unit";"Zergling";"Larva";151;1
"Unit";"Zergling";"Larva";151;1
"Unit";"Zergling";"Larva";151;1
"Unit";"Baneling";"Zergling";155;0
"Unit";"Baneling";"Zergling";155;0
"Unit";"Baneling";"Zergling";155;0
"Unit";"Baneling";"Zergling";155;0
"Building";"CreepTumorQueen";NA;188;0
"Upgrade";"ZergMissileWeaponsLevel1";"EvolutionChamber";131;0
"Unit";"Hydralisk";"Larva";188;2
"Unit";"Hydralisk";"Larva";188;2
"Unit";"Baneling";"Zergling";188;0
"Unit";"Baneling";"Zergling";188;0
"Unit";"Baneling";"Zergling";188;0
"Unit";"Baneling";"Zergling";188;0
"Building";"CreepTumor";NA;192;0
"Building";"CreepTumorQueen";NA;192;0
"Building";"CreepTumor";NA;192;0
"Building";"CreepTumor";NA;192;0
"Building";"CreepTumorQueen";NA;192;0
"Unit";"Overlord";"Larva";192;0
"Unit";"Overlord";"Larva";192;0
"Unit";"Overlord";"Larva";192;0
"Unit";"Overlord";"Larva";192;0
"Unit";"Overlord";"Larva";192;0
"Unit";"Overlord";"Larva";192;0
"Unit";"Baneling";"Zergling";192;0
"Unit";"Baneling";"Zergling";192;0
"Unit";"Baneling";"Zergling";192;0
"Unit";"Baneling";"Zergling";192;0
"Unit";"Baneling";"Zergling";192;0
"Unit";"Baneling";"Zergling";192;0
"Unit";"Baneling";"Zergling";192;0
"Unit";"Baneling";"Zergling";192;0
"Unit";"Baneling";"Zergling";192;0
"Unit";"Baneling";"Zergling";192;0
"Unit";"Baneling";"Zergling";192;0
"Unit";"Baneling";"Zergling";192;0
"Unit";"Baneling";"Zergling";192;0
"Unit";"Baneling";"Zergling";192;0
"Unit";"Baneling";"Zergling";192;0
"Unit";"Baneling";"Zergling";192;0
"Unit";"Zergling";"Larva";192;1
"Unit";"Zergling";"Larva";192;1
"Unit";"Hydralisk";"Larva";192;2
"Unit";"Hydralisk";"Larva";192;2
"Unit";"Hydralisk";"Larva";192;2
"Unit";"Hydralisk";"Larva";192;2
"Unit";"Hydralisk";"Larva";192;2
"Unit";"Hydralisk";"Larva";192;2
"Unit";"Hydralisk";"Larva";192;2
"Unit";"Hydralisk";"Larva";192;2
"Unit";"Hydralisk";"Larva";192;2
"Unit";"Hydralisk";"Larva";192;2
"Unit";"Hydralisk";"Larva";192;2
"Upgrade";"ZergMeleeWeaponsLevel2";"EvolutionChamber";158;0
"Upgrade";"EvolveGroovedSpines";"HydraliskDen";192;0
"Unit";"Hydralisk";"Larva";216;2
"Unit";"Hydralisk";"Larva";216;2
"Unit";"Hydralisk";"Larva";216;2
"Unit";"Hydralisk";"Larva";216;2
"Unit";"Hydralisk";"Larva";216;2
"Unit";"Hydralisk";"Larva";216;2
"Unit";"Hydralisk";"Larva";216;2
"Unit";"Hydralisk";"Larva";216;2
"Unit";"Overlord";"Larva";216;0
"Unit";"Overlord";"Larva";216;0
"Unit";"Overlord";"Larva";216;0
"Unit";"Overlord";"Larva";216;0
"Unit";"Overlord";"Larva";216;0
"Unit";"Overlord";"Larva";216;0
"Unit";"Overlord";"Larva";216;0
"Unit";"Overlord";"Larva";216;0
"Unit";"Overlord";"Larva";216;0
"Unit";"Overlord";"Larva";216;0
"Building";"Extractor";NA;216;0
"Unit";"Baneling";"Zergling";216;0
"Unit";"Baneling";"Zergling";216;0
"Unit";"Baneling";"Zergling";216;0
"Unit";"Baneling";"Zergling";216;0
"Unit";"Baneling";"Zergling";216;0
"Unit";"Baneling";"Zergling";216;0
"Unit";"Zergling";"Larva";217;1
"Unit";"Zergling";"Larva";217;1
"Unit";"Zergling";"Larva";218;1
"Unit";"Zergling";"Larva";218;1
"Unit";"Zergling";"Larva";219;1
"Unit";"Zergling";"Larva";219;1
"Unit";"Zergling";"Larva";219;1
"Unit";"Zergling";"Larva";219;1
"Building";"LurkerDenMP";NA;192;0
"Building";"Extractor";NA;235;0
"Unit";"Baneling";"Zergling";243;0
"Building";"Extractor";NA;235;0
"Unit";"Zergling";"Larva";243;1
"Unit";"Zergling";"Larva";243;1
"Unit";"Zergling";"Larva";243;1
"Unit";"Zergling";"Larva";243;1
"Unit";"Zergling";"Larva";243;1
"Unit";"Zergling";"Larva";243;1
"Unit";"Zergling";"Larva";243;1
"Unit";"Zergling";"Larva";243;1
"Unit";"Zergling";"Larva";243;1
"Unit";"Zergling";"Larva";243;1
"Unit";"Zergling";"Larva";243;1
"Unit";"Zergling";"Larva";243;1
"Unit";"Zergling";"Larva";243;1
"Unit";"Zergling";"Larva";243;1
"Unit";"Zergling";"Larva";243;1
"Unit";"Zergling";"Larva";243;1
"Unit";"Zergling";"Larva";243;1
"Unit";"Zergling";"Larva";243;1
"Unit";"Zergling";"Larva";243;1
"Unit";"Zergling";"Larva";243;1
"Unit";"Zergling";"Larva";243;1
"Unit";"Zergling";"Larva";243;1
"Unit";"Zergling";"Larva";243;1
"Unit";"Zergling";"Larva";243;1
"Unit";"Zergling";"Larva";243;1
"Unit";"Zergling";"Larva";243;1
"Unit";"Zergling";"Larva";243;1
"Unit";"Zergling";"Larva";243;1
"Unit";"Zergling";"Larva";243;1
"Unit";"Zergling";"Larva";243;1
"Unit";"Zergling";"Larva";243;1
"Unit";"Zergling";"Larva";243;1
"Unit";"Zergling";"Larva";243;1
"Unit";"Zergling";"Larva";243;1
"Unit";"Zergling";"Larva";243;1
"Unit";"Zergling";"Larva";243;1
"Unit";"Zergling";"Larva";243;1
"Unit";"Zergling";"Larva";243;1
"Unit";"Zergling";"Larva";243;1
"Unit";"Zergling";"Larva";243;1
"Unit";"Zergling";"Larva";243;1
"Unit";"Zergling";"Larva";243;1
"Unit";"Zergling";"Larva";243;1
"Unit";"Zergling";"Larva";243;1
"Unit";"Zergling";"Larva";243;1
"Unit";"Zergling";"Larva";243;1
"Unit";"Zergling";"Larva";243;1
"Unit";"Zergling";"Larva";243;1
"Unit";"Zergling";"Larva";243;1
"Unit";"Zergling";"Larva";243;1
"Unit";"Zergling";"Larva";243;1
"Unit";"Zergling";"Larva";243;1
"Unit";"Zergling";"Larva";243;1
"Unit";"Zergling";"Larva";243;1
"Unit";"Zergling";"Larva";243;1
"Unit";"Zergling";"Larva";243;1
"Unit";"Zergling";"Larva";243;1
"Unit";"Zergling";"Larva";243;1
"Upgrade";"EvolveMuscularAugments";"HydraliskDen";243;0
"Unit";"Zergling";"Larva";243;1
"Unit";"Zergling";"Larva";243;1
"Unit";"Zergling";"Larva";243;1
"Unit";"Zergling";"Larva";243;1
"Unit";"Zergling";"Larva";243;1
"Unit";"Zergling";"Larva";243;1
"Unit";"Zergling";"Larva";243;1
"Unit";"Zergling";"Larva";243;1
"Unit";"Zergling";"Larva";243;1
"Unit";"Zergling";"Larva";243;1
"Unit";"Zergling";"Larva";243;1
"Unit";"Zergling";"Larva";243;1
"Unit";"Zergling";"Larva";243;1
"Unit";"Zergling";"Larva";243;1
"Unit";"Baneling";"Zergling";315;0
"Unit";"Baneling";"Zergling";315;0
"Unit";"Baneling";"Zergling";315;0
"Unit";"Baneling";"Zergling";315;0
"Unit";"Baneling";"Zergling";315;0
"Unit";"Baneling";"Zergling";315;0
"Unit";"Baneling";"Zergling";315;0
"Unit";"Baneling";"Zergling";315;0
"Unit";"Baneling";"Zergling";315;0
"Unit";"Baneling";"Zergling";315;0
"Unit";"Baneling";"Zergling";315;0
"Unit";"Baneling";"Zergling";315;0
"Unit";"Baneling";"Zergling";315;0
"Unit";"Baneling";"Zergling";315;0
"Unit";"Baneling";"Zergling";315;0
"Unit";"Zergling";"Larva";315;1
"Unit";"Zergling";"Larva";315;1
"Unit";"Baneling";"Zergling";315;0
"Unit";"Baneling";"Zergling";315;0
"Unit";"Baneling";"Zergling";315;0
"Unit";"Baneling";"Zergling";315;0
"Unit";"Baneling";"Zergling";315;0
"Unit";"Baneling";"Zergling";315;0
"Unit";"Baneling";"Zergling";315;0
"Unit";"Baneling";"Zergling";315;0
"Unit";"Zergling";"Larva";315;1
"Unit";"Zergling";"Larva";315;1
"Unit";"Baneling";"Zergling";315;0
"Unit";"Baneling";"Zergling";315;0
"Unit";"Zergling";"Larva";315;1
"Unit";"Zergling";"Larva";315;1
"Unit";"Zergling";"Larva";315;1
"Unit";"Zergling";"Larva";315;1
"Unit";"Zergling";"Larva";315;1
"Unit";"Zergling";"Larva";315;1
"Unit";"Zergling";"Larva";315;1
"Unit";"Zergling";"Larva";315;1
"Unit";"Baneling";"Zergling";315;0
"Unit";"Baneling";"Zergling";315;0
"Unit";"Zergling";"Larva";315;1
"Unit";"Zergling";"Larva";315;1
"Unit";"Zergling";"Larva";315;1
"Unit";"Zergling";"Larva";315;1
"Unit";"Zergling";"Larva";315;1
"Unit";"Zergling";"Larva";315;1
"Unit";"Zergling";"Larva";315;1
"Unit";"Zergling";"Larva";315;1
"Unit";"Zergling";"Larva";315;1
"Unit";"Zergling";"Larva";315;1
"Unit";"Zergling";"Larva";315;1
"Unit";"Zergling";"Larva";315;1
"Building";"InfestationPit";NA;301;0
"Unit";"Baneling";"Zergling";315;0
"Unit";"Baneling";"Zergling";315;0
"Unit";"Baneling";"Zergling";315;0
"Unit";"Zergling";"Larva";315;1
"Unit";"Zergling";"Larva";315;1
"Unit";"Zergling";"Larva";315;1
"Unit";"Zergling";"Larva";315;1
"Unit";"Zergling";"Larva";315;1
"Unit";"Zergling";"Larva";315;1
"Unit";"Zergling";"Larva";315;1
"Unit";"Zergling";"Larva";315;1
"Unit";"Zergling";"Larva";315;1
"Unit";"Zergling";"Larva";315;1
"Unit";"Hydralisk";"Larva";315;2
"Unit";"Hydralisk";"Larva";315;2
"Building";"CreepTumor";NA;353;0
"Building";"CreepTumorQueen";NA;353;0
"Building";"CreepTumor";NA;353;0
"Building";"CreepTumorQueen";NA;353;0
"Building";"CreepTumorQueen";NA;353;0
"Building";"Hatchery";NA;301;0
"Building";"CreepTumorQueen";NA;353;0
"Building";"CreepTumorQueen";NA;353;0
"Unit";"Zergling";"Larva";353;1
"Unit";"Zergling";"Larva";353;1
"Building";"CreepTumorQueen";NA;353;0
"Unit";"Zergling";"Larva";353;1
"Unit";"Zergling";"Larva";353;1
"Unit";"Zergling";"Larva";353;1
"Unit";"Zergling";"Larva";353;1
"Unit";"Zergling";"Larva";353;1
"Unit";"Zergling";"Larva";353;1
"Unit";"Zergling";"Larva";353;1
"Unit";"Zergling";"Larva";353;1
"Unit";"Zergling";"Larva";353;1
"Unit";"Zergling";"Larva";353;1
"Unit";"Zergling";"Larva";353;1
"Unit";"Zergling";"Larva";353;1
"Unit";"Zergling";"Larva";353;1
"Unit";"Zergling";"Larva";353;1
"Unit";"Zergling";"Larva";353;1
"Unit";"Zergling";"Larva";353;1
"Unit";"Zergling";"Larva";353;1
"Unit";"Zergling";"Larva";353;1
"Unit";"Zergling";"Larva";353;1
"Unit";"Zergling";"Larva";353;1
"Unit";"Zergling";"Larva";353;1
"Unit";"Zergling";"Larva";353;1
"Unit";"Zergling";"Larva";353;1
"Unit";"Zergling";"Larva";353;1
"Unit";"Zergling";"Larva";353;1
"Unit";"Zergling";"Larva";353;1
"Upgrade";"ZergMissileWeaponsLevel2";"EvolutionChamber";301;0
"Upgrade";"ZergGroundArmorsLevel2";"EvolutionChamber";301;0
"Unit";"Zergling";"Larva";381;1
"Unit";"Zergling";"Larva";381;1
"Unit";"Hydralisk";"Larva";381;2
"Unit";"Hydralisk";"Larva";381;2
"Unit";"Hydralisk";"Larva";381;2
"Unit";"Infestor";"Larva";381;2
"Unit";"Infestor";"Larva";381;2
"Unit";"Baneling";"Zergling";389;0
"Unit";"Baneling";"Zergling";389;0
"Unit";"Baneling";"Zergling";389;0
"Unit";"Baneling";"Zergling";389;0
"Unit";"Baneling";"Zergling";389;0
"Unit";"Baneling";"Zergling";389;0
"Unit";"Baneling";"Zergling";389;0
"Unit";"Baneling";"Zergling";389;0
"Unit";"Baneling";"Zergling";389;0
"Unit";"Baneling";"Zergling";389;0
"Unit";"Baneling";"Zergling";389;0
"Unit";"Baneling";"Zergling";389;0
"Unit";"Baneling";"Zergling";389;0
"Unit";"Baneling";"Zergling";389;0
