"type";"unit_name";"on_building";"total_supply";"supply"
"Unit";"Overlord";"Larva";13;0
"Building";"Extractor";NA;18;0
"Unit";"Overlord";"Larva";21;0
"Building";"SpawningPool";NA;19;0
"Building";"Hatchery";NA;17;0
"Unit";"Zergling";"Larva";23;1
"Unit";"Zergling";"Larva";23;1
"Unit";"Zergling";"Larva";23;1
"Unit";"Zergling";"Larva";23;1
"Unit";"Queen";"Hatchery";23;2
"Unit";"Queen";"Hatchery";23;2
"Building";"CreepTumorQueen";NA;35;0
"Unit";"Overlord";"Larva";35;0
"Unit";"Overlord";"Larva";38;0
"Building";"CreepTumor";NA;40;0
"Building";"Hatchery";NA;35;0
"Building";"CreepTumor";NA;48;0
"Unit";"Zergling";"Larva";48;1
"Unit";"Zergling";"Larva";48;1
"Unit";"Zergling";"Larva";48;1
"Unit";"Zergling";"Larva";48;1
"Unit";"Zergling";"Larva";48;1
"Unit";"Zergling";"Larva";48;1
"Unit";"Overlord";"Larva";48;0
"Unit";"Overlord";"Larva";50;0
"Unit";"Queen";"Hatchery";48;2
"Building";"Extractor";NA;52;0
"Building";"CreepTumorQueen";NA;60;0
"Building";"SporeCrawler";NA;60;0
"Building";"SporeCrawler";NA;60;0
"Building";"SporeCrawler";NA;62;0
"Unit";"Queen";"Hatchery";60;2
"Building";"CreepTumor";NA;68;0
"Building";"CreepTumor";NA;68;0
"Unit";"Overlord";"Larva";68;0
"Unit";"Queen";"Hatchery";62;2
"Building";"EvolutionChamber";NA;74;0
"Building";"EvolutionChamber";NA;74;0
"Unit";"Zergling";"Larva";77;1
"Unit";"Zergling";"Larva";77;1
"Unit";"Zergling";"Larva";77;1
"Unit";"Zergling";"Larva";77;1
"Unit";"Zergling";"Larva";77;1
"Unit";"Zergling";"Larva";77;1
"Unit";"Overlord";"Larva";77;0
"Unit";"Overlord";"Larva";77;0
"Unit";"Overlord";"Larva";77;0
"Building";"CreepTumor";NA;90;0
"Building";"CreepTumorQueen";NA;90;0
"Unit";"Overlord";"Larva";90;0
"Unit";"Overlord";"Larva";90;0
"Building";"Extractor";NA;90;0
"Building";"CreepTumorQueen";NA;90;0
"Building";"Extractor";NA;90;0
"Building";"CreepTumor";NA;90;0
"Building";"CreepTumorQueen";NA;99;0
"Unit";"Overlord";"Larva";90;0
"Building";"RoachWarren";NA;90;0
"Building";"CreepTumorQueen";NA;99;0
"Building";"Extractor";NA;90;0
"Unit";"Overlord";"Larva";99;0
"Unit";"Roach";"Larva";99;2
"Unit";"Roach";"Larva";99;2
"Unit";"Roach";"Larva";99;2
"Unit";"Roach";"Larva";99;2
"Unit";"Roach";"Larva";99;2
"Unit";"Roach";"Larva";99;2
"Unit";"Roach";"Larva";107;2
"Unit";"Roach";"Larva";107;2
"Unit";"Roach";"Larva";107;2
"Unit";"Roach";"Larva";107;2
"Unit";"Roach";"Larva";107;2
"Unit";"Overlord";"Larva";107;0
"Unit";"Roach";"Larva";129;2
"Unit";"Roach";"Larva";129;2
"Unit";"Roach";"Larva";129;2
"Unit";"Roach";"Larva";129;2
"Unit";"Roach";"Larva";129;2
"Unit";"Roach";"Larva";129;2
"Unit";"Roach";"Larva";129;2
"Unit";"Roach";"Larva";129;2
"Unit";"Roach";"Larva";129;2
"Unit";"Roach";"Larva";129;2
"Unit";"Roach";"Larva";129;2
"Upgrade";"Burrow";"Hatchery";99;0
"Unit";"Roach";"Larva";129;2
"Unit";"Roach";"Larva";129;2
"Unit";"Roach";"Larva";129;2
"Unit";"Roach";"Larva";129;2
"Upgrade";"ZergGroundArmorsLevel1";"EvolutionChamber";99;0
"Unit";"Roach";"Larva";129;2
"Unit";"Roach";"Larva";129;2
"Unit";"Roach";"Larva";129;2
"Unit";"Roach";"Larva";129;2
"Upgrade";"ZergMissileWeaponsLevel1";"EvolutionChamber";99;0
"Building";"Hatchery";NA;104;0
"Upgrade";"GlialReconstitution";"RoachWarren";119;0
"Unit";"Roach";"Larva";151;2
"Unit";"Roach";"Larva";151;2
"Unit";"Roach";"Larva";151;2
"Unit";"Roach";"Larva";151;2
"Unit";"Roach";"Larva";151;2
"Unit";"Roach";"Larva";151;2
"Building";"Extractor";NA;171;0
"Building";"CreepTumorQueen";NA;179;0
"Unit";"Queen";"Hatchery";179;2
"Building";"CreepTumor";NA;191;0
"Unit";"Overlord";"Larva";191;0
"Building";"CreepTumor";NA;194;0
"Unit";"Queen";"Hatchery";189;2
"Upgrade";"TunnelingClaws";"RoachWarren";189;0
"Unit";"Overlord";"Larva";194;0
"Building";"HydraliskDen";NA;191;0
"Unit";"Roach";"Larva";195;2
"Unit";"Roach";"Larva";195;2
"Unit";"Roach";"Larva";195;2
"Unit";"Roach";"Larva";195;2
"Unit";"Roach";"Larva";195;2
"Unit";"Overlord";"Larva";205;0
"Unit";"Overlord";"Larva";205;0
"Unit";"Queen";"Hatchery";194;2
"Unit";"Queen";"Hatchery";207;2
"Unit";"Hydralisk";"Larva";217;2
"Unit";"Hydralisk";"Larva";217;2
"Unit";"Hydralisk";"Larva";217;2
"Unit";"Hydralisk";"Larva";217;2
"Unit";"Hydralisk";"Larva";217;2
"Unit";"Hydralisk";"Larva";217;2
"Unit";"Hydralisk";"Larva";217;2
"Unit";"Hydralisk";"Larva";217;2
"Unit";"Hydralisk";"Larva";219;2
"Unit";"Hydralisk";"Larva";219;2
"Unit";"Hydralisk";"Larva";219;2
"Building";"CreepTumorQueen";NA;243;0
"Building";"CreepTumorQueen";NA;243;0
"Building";"Extractor";NA;237;0
"Building";"InfestationPit";NA;219;0
"Building";"CreepTumor";NA;248;0
"Unit";"Overlord";"Larva";243;0
"Unit";"Overlord";"Larva";243;0
"Unit";"Overlord";"Larva";243;0
"Upgrade";"EvolveGroovedSpines";"HydraliskDen";219;0
"Unit";"Hydralisk";"Larva";248;2
"Unit";"Hydralisk";"Larva";248;2
"Unit";"Hydralisk";"Larva";248;2
"Unit";"Hydralisk";"Larva";248;2
"Unit";"Hydralisk";"Larva";248;2
"Building";"CreepTumorQueen";NA;248;0
"Unit";"Overlord";"Larva";252;0
"Unit";"Overlord";"Larva";252;0
"Upgrade";"ZergMissileWeaponsLevel2";"EvolutionChamber";217;0
"Upgrade";"ZergGroundArmorsLevel2";"EvolutionChamber";217;0
"Unit";"Overlord";"Larva";262;0
"Unit";"Overlord";"Larva";262;0
"Building";"Extractor";NA;262;0
"Building";"CreepTumor";NA;262;0
"Building";"CreepTumor";NA;262;0
"Building";"Hatchery";NA;248;0
"Unit";"Overlord";"Larva";262;0
"Unit";"Overlord";"Larva";262;0
"Building";"CreepTumorQueen";NA;262;0
"Building";"CreepTumor";NA;262;0
"Unit";"Hydralisk";"Larva";262;2
"Unit";"Hydralisk";"Larva";262;2
"Unit";"Hydralisk";"Larva";262;2
"Unit";"Hydralisk";"Larva";262;2
"Unit";"Hydralisk";"Larva";262;2
"Unit";"Hydralisk";"Larva";262;2
"Unit";"Hydralisk";"Larva";262;2
"Unit";"Hydralisk";"Larva";262;2
"Upgrade";"EvolveMuscularAugments";"HydraliskDen";262;0
"Building";"SpineCrawler";NA;262;0
"Building";"SpineCrawler";NA;262;0
"Building";"SpineCrawler";NA;262;0
"Unit";"Overlord";"Larva";281;0
"Building";"Extractor";NA;281;0
"Unit";"Queen";"Hatchery";281;2
"Unit";"Hydralisk";"Larva";281;2
"Unit";"Hydralisk";"Larva";281;2
"Unit";"Hydralisk";"Larva";281;2
"Unit";"Hydralisk";"Larva";281;2
"Unit";"Hydralisk";"Larva";281;2
"Unit";"Hydralisk";"Larva";281;2
"Unit";"Hydralisk";"Larva";281;2
"Unit";"Hydralisk";"Larva";281;2
"Building";"Extractor";NA;281;0
"Unit";"Hydralisk";"Larva";299;2
"Unit";"Hydralisk";"Larva";299;2
"Unit";"Hydralisk";"Larva";299;2
"Unit";"Hydralisk";"Larva";299;2
"Unit";"Hydralisk";"Larva";299;2
"Unit";"Hydralisk";"Larva";299;2
"Unit";"Hydralisk";"Larva";299;2
"Unit";"Hydralisk";"Larva";299;2
"Unit";"Hydralisk";"Larva";299;2
"Unit";"Hydralisk";"Larva";299;2
"Unit";"Hydralisk";"Larva";299;2
"Building";"CreepTumor";NA;321;0
"Unit";"Infestor";"Larva";299;2
"Unit";"Infestor";"Larva";299;2
"Unit";"Infestor";"Larva";299;2
"Building";"CreepTumorQueen";NA;321;0
"Unit";"Infestor";"Larva";299;2
"Unit";"Infestor";"Larva";299;2
"Unit";"Infestor";"Larva";299;2
"Building";"CreepTumor";NA;321;0
"Unit";"Infestor";"Larva";299;2
"Building";"SpineCrawler";NA;321;0
"Building";"SpineCrawler";NA;321;0
"Unit";"Overlord";"Larva";321;0
"Unit";"Hydralisk";"Larva";324;2
"Unit";"Hydralisk";"Larva";324;2
"Unit";"Hydralisk";"Larva";324;2
"Unit";"Hydralisk";"Larva";324;2
"Unit";"Hydralisk";"Larva";324;2
"Unit";"Hydralisk";"Larva";324;2
"Unit";"Hydralisk";"Larva";324;2
"Unit";"Hydralisk";"Larva";324;2
"Unit";"Hydralisk";"Larva";324;2
"Unit";"Hydralisk";"Larva";356;2
"Unit";"Hydralisk";"Larva";356;2
"Unit";"Hydralisk";"Larva";356;2
"Unit";"Hydralisk";"Larva";356;2
"Unit";"Hydralisk";"Larva";356;2
"Unit";"Hydralisk";"Larva";356;2
"Unit";"Hydralisk";"Larva";356;2
"Unit";"Hydralisk";"Larva";356;2
"Unit";"Overlord";"Larva";356;0
"Upgrade";"ZergMissileWeaponsLevel3";"EvolutionChamber";321;0
"Upgrade";"ZergGroundArmorsLevel3";"EvolutionChamber";321;0
"Unit";"Hydralisk";"Larva";372;2
"Unit";"Hydralisk";"Larva";372;2
"Unit";"Hydralisk";"Larva";372;2
"Unit";"Hydralisk";"Larva";372;2
"Unit";"Hydralisk";"Larva";372;2
"Unit";"Hydralisk";"Larva";372;2
"Unit";"Hydralisk";"Larva";372;2
"Unit";"Hydralisk";"Larva";372;2
"Unit";"Hydralisk";"Larva";372;2
"Unit";"Hydralisk";"Larva";372;2
"Unit";"Hydralisk";"Larva";372;2
"Unit";"Hydralisk";"Larva";372;2
"Unit";"Hydralisk";"Larva";372;2
"Building";"CreepTumorQueen";NA;403;0
"Unit";"Hydralisk";"Larva";377;2
"Unit";"Hydralisk";"Larva";377;2
"Unit";"Hydralisk";"Larva";377;2
"Unit";"Hydralisk";"Larva";377;2
"Unit";"Hydralisk";"Larva";377;2
"Unit";"Hydralisk";"Larva";377;2
"Unit";"Hydralisk";"Larva";377;2
"Unit";"Hydralisk";"Larva";377;2
"Building";"CreepTumor";NA;403;0
"Building";"CreepTumorQueen";NA;403;0
"Building";"CreepTumorQueen";NA;403;0
"Building";"SporeCrawler";NA;403;0
"Unit";"Hydralisk";"Larva";419;2
"Unit";"Hydralisk";"Larva";419;2
"Building";"CreepTumor";NA;419;0
"Building";"SpineCrawler";NA;419;0
"Building";"SpineCrawler";NA;419;0
"Building";"Extractor";NA;419;0
"Building";"Extractor";NA;419;0
"Building";"Hatchery";NA;403;0
"Unit";"Hydralisk";"Larva";426;2
"Unit";"Hydralisk";"Larva";426;2
"Unit";"Hydralisk";"Larva";426;2
"Unit";"Hydralisk";"Larva";426;2
"Unit";"Hydralisk";"Larva";426;2
"Unit";"Hydralisk";"Larva";426;2
"Unit";"Hydralisk";"Larva";426;2
"Unit";"Hydralisk";"Larva";426;2
"Unit";"Hydralisk";"Larva";426;2
"Unit";"Hydralisk";"Larva";426;2
"Unit";"Hydralisk";"Larva";426;2
"Building";"CreepTumor";NA;426;0
