"type";"unit_name";"on_building";"total_supply";"supply"
"Unit";"Overlord";"Larva";13;0
"Building";"Extractor";NA;19;0
"Building";"SpawningPool";NA;19;0
"Unit";"Overlord";"Larva";22;0
"Building";"Hatchery";NA;18;0
"Unit";"Zergling";"Larva";23;1
"Unit";"Zergling";"Larva";23;1
"Unit";"Zergling";"Larva";23;1
"Unit";"Zergling";"Larva";23;1
"Unit";"Zergling";"Larva";23;1
"Unit";"Zergling";"Larva";23;1
"Unit";"Queen";"Hatchery";23;2
"Unit";"Queen";"Hatchery";23;2
"Unit";"Overlord";"Larva";39;0
"Unit";"Overlord";"Larva";40;0
"Building";"RoachWarren";NA;40;0
"Unit";"Zergling";"Larva";52;1
"Unit";"Zergling";"Larva";52;1
"Unit";"Zergling";"Larva";52;1
"Unit";"Zergling";"Larva";52;1
"Unit";"Zergling";"Larva";52;1
"Unit";"Zergling";"Larva";52;1
"Building";"Extractor";NA;52;0
"Building";"Extractor";NA;52;0
"Unit";"Overlord";"Larva";63;0
"Unit";"Overlord";"Larva";63;0
"Unit";"Queen";"Hatchery";52;2
"Unit";"Roach";"Larva";63;2
"Building";"EvolutionChamber";NA;63;0
"Building";"EvolutionChamber";NA;63;0
"Building";"Hatchery";NA;49;0
"Unit";"Overlord";"Larva";68;0
"Unit";"Overlord";"Larva";68;0
"Building";"SporeCrawler";NA;68;0
"Building";"SporeCrawler";NA;70;0
"Unit";"Roach";"Larva";72;2
"Unit";"Roach";"Larva";72;2
"Unit";"Queen";"Hatchery";70;2
"Building";"Extractor";NA;78;0
"Unit";"Roach";"Larva";84;2
"Unit";"Roach";"Larva";86;2
"Unit";"Roach";"Larva";86;2
"Unit";"Roach";"Larva";86;2
"Unit";"Roach";"Larva";86;2
"Unit";"Roach";"Larva";86;2
"Building";"HydraliskDen";NA;84;0
"Unit";"Roach";"Larva";86;2
"Unit";"Roach";"Larva";86;2
"Unit";"Roach";"Larva";86;2
"Unit";"Roach";"Larva";86;2
"Unit";"Roach";"Larva";98;2
"Unit";"Roach";"Larva";106;2
"Unit";"Roach";"Larva";106;2
"Unit";"Roach";"Larva";106;2
"Unit";"Queen";"Hatchery";88;2
"Upgrade";"GlialReconstitution";"RoachWarren";86;0
"Upgrade";"ZergMissileWeaponsLevel1";"EvolutionChamber";78;0
"Upgrade";"ZergGroundArmorsLevel1";"EvolutionChamber";78;0
"Unit";"Roach";"Larva";106;2
"Unit";"Roach";"Larva";106;2
"Unit";"Roach";"Larva";106;2
"Unit";"Roach";"Larva";106;2
"Unit";"Roach";"Larva";106;2
"Unit";"Queen";"Hatchery";106;2
"Unit";"Overlord";"Larva";116;0
"Unit";"Overlord";"Larva";116;0
"Building";"CreepTumorQueen";NA;129;0
"Unit";"Overlord";"Larva";129;0
"Unit";"Overlord";"Larva";129;0
"Upgrade";"EvolveGroovedSpines";"HydraliskDen";127;0
"Building";"CreepTumor";NA;137;0
"Unit";"Hydralisk";"Larva";137;2
"Unit";"Hydralisk";"Larva";137;2
"Unit";"Hydralisk";"Larva";137;2
"Unit";"Roach";"Larva";146;2
"Unit";"Roach";"Larva";146;2
"Unit";"Roach";"Larva";146;2
"Unit";"Roach";"Larva";146;2
"Unit";"Roach";"Larva";146;2
"Unit";"Roach";"Larva";146;2
"Unit";"Roach";"Larva";146;2
"Unit";"Roach";"Larva";146;2
"Unit";"Roach";"Larva";146;2
"Unit";"Roach";"Larva";146;2
"Unit";"Roach";"Larva";146;2
"Unit";"Roach";"Larva";146;2
"Unit";"Roach";"Larva";146;2
"Building";"CreepTumor";NA;146;0
"Unit";"Queen";"Hatchery";146;2
"Building";"CreepTumorQueen";NA;172;0
"Building";"SporeCrawler";NA;146;0
"Unit";"Hydralisk";"Larva";172;2
"Unit";"Hydralisk";"Larva";172;2
"Unit";"Hydralisk";"Larva";172;2
"Unit";"Hydralisk";"Larva";172;2
"Unit";"Hydralisk";"Larva";172;2
"Unit";"Overlord";"Larva";172;0
"Unit";"Overlord";"Larva";172;0
"Building";"CreepTumorQueen";NA;174;0
"Building";"CreepTumorQueen";NA;174;0
"Building";"CreepTumorQueen";NA;175;0
"Upgrade";"ZergMissileWeaponsLevel2";"EvolutionChamber";137;0
"Unit";"Hydralisk";"Larva";185;2
"Upgrade";"EvolveMuscularAugments";"HydraliskDen";172;0
"Building";"CreepTumor";NA;190;0
"Unit";"Hydralisk";"Larva";185;2
"Unit";"Hydralisk";"Larva";185;2
"Unit";"Hydralisk";"Larva";185;2
"Building";"CreepTumor";NA;190;0
"Unit";"Hydralisk";"Larva";185;2
"Unit";"Hydralisk";"Larva";185;2
"Unit";"Hydralisk";"Larva";185;2
"Building";"CreepTumor";NA;190;0
"Building";"CreepTumorQueen";NA;190;0
"Upgrade";"ZergGroundArmorsLevel2";"EvolutionChamber";146;0
"Building";"Extractor";NA;188;0
"Building";"InfestationPit";NA;185;0
"Unit";"Hydralisk";"Larva";204;2
"Unit";"Hydralisk";"Larva";204;2
"Unit";"Hydralisk";"Larva";204;2
"Unit";"Hydralisk";"Larva";204;2
"Unit";"Hydralisk";"Larva";204;2
"Unit";"Hydralisk";"Larva";204;2
"Unit";"Hydralisk";"Larva";204;2
"Unit";"Hydralisk";"Larva";204;2
"Unit";"Hydralisk";"Larva";204;2
"Unit";"Hydralisk";"Larva";204;2
"Unit";"Hydralisk";"Larva";204;2
"Building";"CreepTumor";NA;204;0
"Building";"CreepTumor";NA;204;0
"Building";"CreepTumor";NA;204;0
"Building";"CreepTumorQueen";NA;204;0
"Building";"CreepTumor";NA;204;0
"Unit";"Roach";"Larva";204;2
"Unit";"Roach";"Larva";204;2
"Unit";"Roach";"Larva";204;2
"Unit";"Roach";"Larva";204;2
"Unit";"Roach";"Larva";204;2
"Unit";"Roach";"Larva";204;2
"Building";"Hatchery";NA;192;0
"Building";"Extractor";NA;204;0
"Unit";"Overlord";"Larva";226;0
"Unit";"Overlord";"Larva";226;0
"Unit";"Overlord";"Larva";226;0
"Unit";"Overlord";"Larva";226;0
"Building";"CreepTumorQueen";NA;228;0
"Building";"CreepTumor";NA;228;0
"Building";"Extractor";NA;226;0
"Unit";"Queen";"Hatchery";206;2
"Unit";"Roach";"Larva";238;2
"Unit";"Roach";"Larva";238;2
"Building";"CreepTumor";NA;255;0
"Unit";"Roach";"Larva";255;2
"Building";"CreepTumor";NA;255;0
"Unit";"Roach";"Larva";255;2
"Unit";"Roach";"Larva";255;2
"Unit";"Roach";"Larva";255;2
"Unit";"Roach";"Larva";255;2
"Unit";"Roach";"Larva";255;2
"Unit";"Roach";"Larva";255;2
"Unit";"Roach";"Larva";255;2
"Unit";"Roach";"Larva";255;2
"Building";"CreepTumorQueen";NA;259;0
"Building";"CreepTumor";NA;259;0
"Unit";"Overlord";"Larva";259;0
"Building";"CreepTumor";NA;277;0
"Building";"CreepTumor";NA;277;0
"Building";"CreepTumor";NA;277;0
"Building";"CreepTumor";NA;277;0
"Building";"CreepTumorQueen";NA;277;0
"Building";"CreepTumorQueen";NA;277;0
"Building";"CreepTumorQueen";NA;277;0
"Unit";"Overlord";"Larva";277;0
"Unit";"Overlord";"Larva";277;0
"Unit";"Overlord";"Larva";277;0
"Unit";"Overlord";"Larva";277;0
"Unit";"Overlord";"Larva";277;0
"Building";"CreepTumor";NA;277;0
"Building";"CreepTumorQueen";NA;277;0
"Building";"CreepTumor";NA;277;0
"Building";"CreepTumor";NA;277;0
"Building";"CreepTumor";NA;277;0
"Building";"Extractor";NA;277;0
"Building";"CreepTumor";NA;277;0
"Building";"SporeCrawler";NA;277;0
"Unit";"Hydralisk";"Larva";279;2
"Unit";"Hydralisk";"Larva";279;2
"Unit";"Hydralisk";"Larva";279;2
"Unit";"Hydralisk";"Larva";279;2
"Unit";"Hydralisk";"Larva";279;2
"Unit";"Hydralisk";"Larva";279;2
"Unit";"Hydralisk";"Larva";279;2
"Unit";"Hydralisk";"Larva";279;2
"Unit";"Hydralisk";"Larva";279;2
"Unit";"Hydralisk";"Larva";279;2
"Unit";"Hydralisk";"Larva";279;2
"Unit";"Hydralisk";"Larva";279;2
"Unit";"Hydralisk";"Larva";279;2
"Unit";"Hydralisk";"Larva";279;2
"Unit";"Hydralisk";"Larva";279;2
"Unit";"Hydralisk";"Larva";279;2
"Unit";"Hydralisk";"Larva";279;2
"Unit";"Hydralisk";"Larva";279;2
"Unit";"Roach";"Larva";279;2
"Unit";"Roach";"Larva";279;2
"Unit";"Viper";"Larva";279;3
"Building";"LurkerDenMP";NA;277;0
"Unit";"Roach";"Larva";322;2
"Unit";"Roach";"Larva";322;2
"Unit";"Roach";"Larva";322;2
"Unit";"Roach";"Larva";322;2
"Unit";"Roach";"Larva";322;2
"Unit";"Viper";"Larva";322;3
"Unit";"Viper";"Larva";322;3
"Unit";"Roach";"Larva";338;2
"Unit";"Roach";"Larva";338;2
"Unit";"Roach";"Larva";338;2
"Unit";"Overlord";"Larva";338;0
"Unit";"Overlord";"Larva";338;0
"Unit";"Overlord";"Larva";338;0
"Upgrade";"ZergMissileWeaponsLevel3";"EvolutionChamber";279;0
"Upgrade";"ZergGroundArmorsLevel3";"EvolutionChamber";279;0
"Unit";"Roach";"Larva";344;2
"Unit";"Roach";"Larva";344;2
"Unit";"Roach";"Larva";344;2
"Unit";"Roach";"Larva";344;2
"Unit";"Roach";"Larva";344;2
"Unit";"Roach";"Larva";344;2
"Unit";"Roach";"Larva";344;2
"Unit";"Roach";"Larva";344;2
"Unit";"Roach";"Larva";344;2
"Unit";"Roach";"Larva";344;2
"Unit";"Roach";"Larva";344;2
"Unit";"Roach";"Larva";344;2
"Unit";"Roach";"Larva";344;2
"Unit";"Roach";"Larva";344;2
"Unit";"Roach";"Larva";344;2
"Unit";"Hydralisk";"Larva";374;2
"Unit";"Hydralisk";"Larva";374;2
"Unit";"Hydralisk";"Larva";374;2
"Unit";"Hydralisk";"Larva";374;2
"Unit";"Hydralisk";"Larva";374;2
"Unit";"Hydralisk";"Larva";374;2
"Unit";"Hydralisk";"Larva";374;2
"Building";"Hatchery";NA;338;0
"Building";"CreepTumor";NA;374;0
"Building";"CreepTumor";NA;374;0
"Building";"CreepTumor";NA;374;0
"Building";"CreepTumor";NA;374;0
"Building";"CreepTumor";NA;374;0
"Building";"CreepTumor";NA;374;0
"Building";"CreepTumorQueen";NA;388;0
"Building";"Extractor";NA;374;0
"Building";"Extractor";NA;374;0
"Building";"CreepTumorQueen";NA;388;0
"Building";"Hatchery";NA;344;0
"Building";"CreepTumorQueen";NA;388;0
"Building";"CreepTumorQueen";NA;388;0
"Building";"CreepTumorQueen";NA;388;0
"Unit";"Viper";"Larva";388;3
"Unit";"Viper";"Larva";388;3
"Unit";"Hydralisk";"Larva";402;2
"Unit";"Hydralisk";"Larva";402;2
"Unit";"Hydralisk";"Larva";402;2
"Unit";"Hydralisk";"Larva";402;2
"Unit";"Hydralisk";"Larva";422;2
"Unit";"Hydralisk";"Larva";422;2
"Unit";"Hydralisk";"Larva";422;2
"Unit";"Hydralisk";"Larva";422;2
"Unit";"Hydralisk";"Larva";422;2
"Unit";"Hydralisk";"Larva";422;2
"Unit";"Hydralisk";"Larva";422;2
"Unit";"Hydralisk";"Larva";422;2
"Unit";"Hydralisk";"Larva";422;2
"Unit";"Hydralisk";"Larva";422;2
"Unit";"Hydralisk";"Larva";422;2
"Unit";"Hydralisk";"Larva";422;2
"Unit";"Hydralisk";"Larva";422;2
"Unit";"Hydralisk";"Larva";422;2
"Unit";"Hydralisk";"Larva";422;2
"Unit";"Hydralisk";"Larva";422;2
"Unit";"Hydralisk";"Larva";422;2
"Unit";"Hydralisk";"Larva";422;2
"Building";"CreepTumor";NA;425;0
"Building";"CreepTumor";NA;425;0
"Building";"CreepTumor";NA;441;0
"Building";"CreepTumor";NA;449;0
"Building";"CreepTumor";NA;457;0
"Building";"CreepTumor";NA;461;0
"Building";"CreepTumor";NA;461;0
"Building";"CreepTumor";NA;461;0
"Building";"CreepTumor";NA;461;0
"Unit";"Overlord";"Larva";425;0
"Building";"CreepTumorQueen";NA;461;0
"Building";"SporeCrawler";NA;425;0
"Building";"SporeCrawler";NA;425;0
"Building";"CreepTumorQueen";NA;461;0
"Unit";"Queen";"Hatchery";422;2
"Building";"CreepTumorQueen";NA;461;0
"Building";"CreepTumorQueen";NA;461;0
"Building";"Extractor";NA;461;0
"Building";"CreepTumor";NA;463;0
"Unit";"Hydralisk";"Larva";461;2
"Unit";"Hydralisk";"Larva";461;2
"Unit";"Hydralisk";"Larva";461;2
"Unit";"Hydralisk";"Larva";461;2
"Unit";"Hydralisk";"Larva";461;2
"Unit";"Hydralisk";"Larva";461;2
"Unit";"Hydralisk";"Larva";461;2
"Unit";"Hydralisk";"Larva";461;2
"Unit";"Hydralisk";"Larva";461;2
"Unit";"Hydralisk";"Larva";461;2
"Unit";"Hydralisk";"Larva";461;2
"Unit";"Hydralisk";"Larva";461;2
"Unit";"Hydralisk";"Larva";461;2
"Unit";"Hydralisk";"Larva";461;2
"Unit";"Hydralisk";"Larva";461;2
"Building";"Spire";NA;461;0
"Building";"CreepTumor";NA;495;0
"Building";"CreepTumor";NA;495;0
"Building";"CreepTumor";NA;495;0
"Building";"CreepTumor";NA;495;0
"Building";"CreepTumor";NA;495;0
"Building";"CreepTumor";NA;495;0
"Building";"CreepTumor";NA;495;0
"Building";"CreepTumor";NA;495;0
"Building";"CreepTumor";NA;495;0
"Building";"CreepTumor";NA;495;0
"Building";"CreepTumor";NA;495;0
"Building";"CreepTumorQueen";NA;495;0
"Unit";"Hydralisk";"Larva";495;2
"Building";"CreepTumorQueen";NA;495;0
"Unit";"Hydralisk";"Larva";495;2
"Unit";"Hydralisk";"Larva";495;2
"Building";"CreepTumorQueen";NA;495;0
"Building";"CreepTumorQueen";NA;495;0
"Building";"Hatchery";NA;501;0
"Unit";"Hydralisk";"Larva";501;2
