"type";"unit_name";"on_building";"total_supply";"supply"
"Unit";"Overlord";"Larva";12;0
"Building";"Extractor";NA;18;0
"Unit";"Overlord";"Larva";21;0
"Building";"SpawningPool";NA;19;0
"Building";"Hatchery";NA;17;0
"Unit";"Zergling";"Larva";22;1
"Unit";"Zergling";"Larva";22;1
"Unit";"Zergling";"Larva";22;1
"Unit";"Zergling";"Larva";22;1
"Unit";"Queen";"Hatchery";22;2
"Unit";"Queen";"Hatchery";22;2
"Unit";"Overlord";"Larva";35;0
"Unit";"Queen";"Hatchery";35;2
"Building";"CreepTumorQueen";NA;40;0
"Unit";"Overlord";"Larva";38;0
"Unit";"Overlord";"Larva";44;0
"Building";"Hatchery";NA;33;0
"Unit";"Zergling";"Larva";44;1
"Unit";"Zergling";"Larva";44;1
"Unit";"Zergling";"Larva";44;1
"Unit";"Zergling";"Larva";44;1
"Unit";"Zergling";"Larva";44;1
"Unit";"Zergling";"Larva";44;1
"Building";"CreepTumor";NA;47;0
"Unit";"Queen";"Hatchery";40;2
"Unit";"Zergling";"Larva";47;1
"Unit";"Zergling";"Larva";47;1
"Building";"CreepTumorQueen";NA;56;0
"Building";"Extractor";NA;68;0
"Building";"Extractor";NA;68;0
"Unit";"Queen";"Hatchery";58;2
"Building";"SporeCrawler";NA;68;0
"Building";"SporeCrawler";NA;68;0
"Building";"CreepTumorQueen";NA;73;0
"Building";"CreepTumor";NA;73;0
"Building";"CreepTumorQueen";NA;73;0
"Building";"SporeCrawler";NA;70;0
"Building";"CreepTumor";NA;73;0
"Unit";"Queen";"Hatchery";68;2
"Building";"BanelingNest";NA;68;0
"Building";"CreepTumorQueen";NA;77;0
"Unit";"Overlord";"Larva";77;0
"Unit";"Overlord";"Larva";77;0
"Unit";"Overlord";"Larva";77;0
"Unit";"Overlord";"Larva";77;0
"Unit";"Overlord";"Larva";77;0
"Building";"CreepTumor";NA;80;0
"Building";"CreepTumor";NA;80;0
"Building";"CreepTumor";NA;80;0
"Building";"CreepTumorQueen";NA;80;0
"Unit";"Zergling";"Larva";90;1
"Unit";"Zergling";"Larva";90;1
"Unit";"Zergling";"Larva";90;1
"Unit";"Zergling";"Larva";90;1
"Unit";"Zergling";"Larva";90;1
"Unit";"Zergling";"Larva";90;1
"Unit";"Zergling";"Larva";90;1
"Unit";"Zergling";"Larva";90;1
"Building";"CreepTumorQueen";NA;96;0
"Building";"CreepTumor";NA;96;0
"Building";"CreepTumor";NA;96;0
"Building";"EvolutionChamber";NA;90;0
"Unit";"Zergling";"Larva";96;1
"Unit";"Zergling";"Larva";96;1
"Unit";"Zergling";"Larva";96;1
"Unit";"Zergling";"Larva";96;1
"Unit";"Zergling";"Larva";96;1
"Unit";"Zergling";"Larva";96;1
"Building";"EvolutionChamber";NA;90;0
"Building";"RoachWarren";NA;90;0
"Building";"Extractor";NA;111;0
"Building";"Extractor";NA;111;0
"Unit";"Overlord";"Larva";114;0
"Building";"CreepTumor";NA;114;0
"Building";"Extractor";NA;114;0
"Building";"InfestationPit";NA;111;0
"Unit";"Roach";"Larva";114;2
"Unit";"Roach";"Larva";114;2
"Unit";"Roach";"Larva";114;2
"Unit";"Roach";"Larva";114;2
"Unit";"Baneling";"Zergling";120;0
"Unit";"Baneling";"Zergling";120;0
"Unit";"Baneling";"Zergling";120;0
"Unit";"Baneling";"Zergling";120;0
"Unit";"Baneling";"Zergling";120;0
"Unit";"Baneling";"Zergling";120;0
"Building";"CreepTumorQueen";NA;120;0
"Unit";"Roach";"Larva";120;2
"Unit";"Roach";"Larva";120;2
"Unit";"Roach";"Larva";120;2
"Unit";"Roach";"Larva";120;2
"Unit";"Roach";"Larva";120;2
"Unit";"Roach";"Larva";120;2
"Building";"CreepTumorQueen";NA;128;0
"Unit";"Overlord";"Larva";128;0
"Unit";"Overlord";"Larva";128;0
"Unit";"Overlord";"Larva";128;0
"Unit";"Overlord";"Larva";128;0
"Building";"CreepTumorQueen";NA;140;0
"Building";"CreepTumorQueen";NA;140;0
"Building";"CreepTumorQueen";NA;140;0
"Building";"CreepTumor";NA;140;0
"Building";"Hatchery";NA;114;0
"Building";"CreepTumor";NA;154;0
"Building";"CreepTumor";NA;154;0
"Building";"CreepTumor";NA;154;0
"Unit";"Overlord";"Larva";151;0
"Building";"HydraliskDen";NA;140;0
"Building";"CreepTumor";NA;155;0
"Building";"CreepTumor";NA;155;0
"Building";"CreepTumor";NA;156;0
"Upgrade";"ZergGroundArmorsLevel1";"EvolutionChamber";120;0
"Upgrade";"ZergMissileWeaponsLevel1";"EvolutionChamber";120;0
"Building";"SporeCrawler";NA;156;0
"Unit";"Roach";"Larva";156;2
"Unit";"Roach";"Larva";156;2
"Unit";"Roach";"Larva";156;2
"Unit";"Roach";"Larva";156;2
"Unit";"Roach";"Larva";156;2
"Unit";"Roach";"Larva";156;2
"Unit";"Roach";"Larva";156;2
"Unit";"Roach";"Larva";156;2
"Unit";"Roach";"Larva";156;2
"Unit";"Roach";"Larva";156;2
"Building";"SpineCrawler";NA;156;0
"Building";"SpineCrawler";NA;156;0
"Building";"CreepTumor";NA;162;0
"Building";"SpineCrawler";NA;156;0
"Building";"CreepTumor";NA;182;0
"Building";"CreepTumor";NA;182;0
"Upgrade";"GlialReconstitution";"RoachWarren";155;0
"Building";"CreepTumor";NA;186;0
"Building";"CreepTumor";NA;186;0
"Building";"CreepTumor";NA;186;0
"Building";"CreepTumorQueen";NA;186;0
"Building";"CreepTumorQueen";NA;186;0
"Building";"CreepTumorQueen";NA;186;0
"Unit";"Hydralisk";"Larva";186;2
"Unit";"Hydralisk";"Larva";186;2
"Unit";"Hydralisk";"Larva";186;2
"Unit";"Hydralisk";"Larva";186;2
"Unit";"Hydralisk";"Larva";186;2
"Unit";"Hydralisk";"Larva";186;2
"Unit";"Hydralisk";"Larva";186;2
"Unit";"Hydralisk";"Larva";186;2
"Unit";"Hydralisk";"Larva";186;2
"Building";"CreepTumor";NA;186;0
"Unit";"Overlord";"Larva";186;0
"Unit";"Overlord";"Larva";186;0
"Unit";"Overlord";"Larva";186;0
"Unit";"Overlord";"Larva";186;0
"Unit";"Overlord";"Larva";186;0
"Building";"CreepTumor";NA;187;0
"Building";"CreepTumor";NA;187;0
"Building";"CreepTumor";NA;187;0
"Upgrade";"EvolveGroovedSpines";"HydraliskDen";162;0
"Building";"CreepTumor";NA;205;0
"Unit";"Viper";"Larva";205;3
"Unit";"Viper";"Larva";205;3
"Unit";"Viper";"Larva";205;3
"Building";"CreepTumor";NA;214;0
"Unit";"Hydralisk";"Larva";205;2
"Unit";"Hydralisk";"Larva";205;2
"Unit";"Hydralisk";"Larva";205;2
"Unit";"Hydralisk";"Larva";205;2
"Unit";"Hydralisk";"Larva";205;2
"Unit";"Hydralisk";"Larva";205;2
"Unit";"Hydralisk";"Larva";205;2
"Unit";"Hydralisk";"Larva";205;2
"Building";"CreepTumor";NA;220;0
"Building";"CreepTumor";NA;220;0
"Building";"CreepTumor";NA;220;0
"Building";"Extractor";NA;220;0
"Building";"Extractor";NA;220;0
"Unit";"Roach";"Larva";220;2
"Unit";"Roach";"Larva";220;2
"Unit";"Roach";"Larva";220;2
"Unit";"Roach";"Larva";220;2
"Unit";"Roach";"Larva";220;2
"Unit";"Roach";"Larva";220;2
"Unit";"Roach";"Larva";220;2
"Unit";"Roach";"Larva";220;2
"Unit";"Roach";"Larva";220;2
"Unit";"Roach";"Larva";220;2
"Building";"CreepTumor";NA;256;0
"Unit";"Roach";"Larva";256;2
"Unit";"Roach";"Larva";256;2
"Unit";"Roach";"Larva";256;2
"Unit";"Roach";"Larva";256;2
"Unit";"Roach";"Larva";256;2
"Unit";"Roach";"Larva";256;2
"Unit";"Roach";"Larva";256;2
"Unit";"Roach";"Larva";256;2
"Unit";"Roach";"Larva";256;2
"Unit";"Roach";"Larva";256;2
"Building";"Extractor";NA;256;0
"Building";"Extractor";NA;256;0
"Upgrade";"ZergGroundArmorsLevel2";"EvolutionChamber";205;0
"Upgrade";"ZergMissileWeaponsLevel2";"EvolutionChamber";205;0
"Building";"Extractor";NA;256;0
"Building";"Extractor";NA;256;0
"Unit";"Overlord";"Larva";256;0
"Unit";"Overlord";"Larva";256;0
"Unit";"Overlord";"Larva";256;0
"Unit";"Hydralisk";"Larva";256;2
"Unit";"Hydralisk";"Larva";256;2
"Building";"Hatchery";NA;220;0
"Upgrade";"EvolveMuscularAugments";"HydraliskDen";256;0
"Building";"Hatchery";NA;236;0
"Unit";"Roach";"Larva";280;2
"Unit";"Roach";"Larva";280;2
"Unit";"Roach";"Larva";280;2
"Unit";"Roach";"Larva";280;2
"Unit";"Hydralisk";"Larva";280;2
"Building";"CreepTumor";NA;280;0
"Unit";"Hydralisk";"Larva";280;2
"Unit";"Hydralisk";"Larva";280;2
"Unit";"Hydralisk";"Larva";280;2
"Unit";"Hydralisk";"Larva";280;2
"Building";"CreepTumor";NA;280;0
"Building";"CreepTumor";NA;280;0
"Building";"SpineCrawler";NA;288;0
"Building";"SpineCrawler";NA;288;0
"Building";"SpineCrawler";NA;298;0
"Building";"CreepTumor";NA;303;0
"Building";"CreepTumor";NA;303;0
"Building";"CreepTumor";NA;303;0
