"type";"unit_name";"on_building";"total_supply";"supply"
"Unit";"Overlord";"Larva";13;0
"Building";"Extractor";NA;19;0
"Unit";"Overlord";"Larva";22;0
"Building";"SpawningPool";NA;19;0
"Building";"Hatchery";NA;17;0
"Unit";"Zergling";"Larva";22;1
"Unit";"Zergling";"Larva";22;1
"Unit";"Zergling";"Larva";22;1
"Unit";"Zergling";"Larva";22;1
"Unit";"Queen";"Hatchery";22;2
"Unit";"Queen";"Hatchery";22;2
"Building";"CreepTumorQueen";NA;35;0
"Unit";"Zergling";"Larva";35;1
"Unit";"Zergling";"Larva";35;1
"Unit";"Zergling";"Larva";35;1
"Unit";"Zergling";"Larva";35;1
"Unit";"Overlord";"Larva";38;0
"Unit";"Overlord";"Larva";38;0
"Unit";"Queen";"Hatchery";35;2
"Building";"CreepTumor";NA;42;0
"Building";"CreepTumorQueen";NA;42;0
"Building";"Hatchery";NA;32;0
"Building";"CreepTumor";NA;51;0
"Building";"CreepTumor";NA;51;0
"Unit";"Overlord";"Larva";50;0
"Unit";"Queen";"Hatchery";44;2
"Unit";"Queen";"Hatchery";44;2
"Building";"CreepTumor";NA;64;0
"Building";"CreepTumor";NA;64;0
"Unit";"Queen";"Hatchery";52;2
"Unit";"Zergling";"Larva";67;1
"Unit";"Zergling";"Larva";67;1
"Unit";"Zergling";"Larva";67;1
"Unit";"Zergling";"Larva";67;1
"Unit";"Zergling";"Larva";69;1
"Unit";"Zergling";"Larva";69;1
"Unit";"Zergling";"Larva";69;1
"Unit";"Zergling";"Larva";69;1
"Unit";"Overlord";"Larva";69;0
"Unit";"Overlord";"Larva";69;0
"Unit";"Overlord";"Larva";69;0
"Unit";"Overlord";"Larva";69;0
"Building";"CreepTumorQueen";NA;75;0
"Building";"SporeCrawler";NA;71;0
"Building";"SporeCrawler";NA;71;0
"Building";"SporeCrawler";NA;71;0
"Unit";"Overlord";"Larva";79;0
"Unit";"Overlord";"Larva";79;0
"Building";"RoachWarren";NA;79;0
"Building";"CreepTumorQueen";NA;88;0
"Building";"CreepTumor";NA;88;0
"Building";"CreepTumorQueen";NA;88;0
"Building";"CreepTumor";NA;88;0
"Building";"CreepTumor";NA;88;0
"Building";"Extractor";NA;88;0
"Building";"Extractor";NA;94;0
"Building";"Extractor";NA;97;0
"Building";"EvolutionChamber";NA;97;0
"Building";"EvolutionChamber";NA;97;0
"Building";"CreepTumor";NA;106;0
"Building";"CreepTumor";NA;106;0
"Building";"Extractor";NA;103;0
"Building";"Extractor";NA;103;0
"Building";"CreepTumor";NA;107;0
"Unit";"Roach";"Larva";104;2
"Unit";"Roach";"Larva";104;2
"Unit";"Roach";"Larva";104;2
"Unit";"Overlord";"Larva";119;0
"Unit";"Roach";"Larva";119;2
"Unit";"Overlord";"Larva";119;0
"Unit";"Overlord";"Larva";119;0
"Unit";"Overlord";"Larva";119;0
"Unit";"Roach";"Larva";119;2
"Unit";"Roach";"Larva";119;2
"Unit";"Roach";"Larva";119;2
"Unit";"Roach";"Larva";119;2
"Unit";"Overlord";"Larva";127;0
"Unit";"Overlord";"Larva";127;0
"Unit";"Overlord";"Larva";127;0
"Building";"CreepTumorQueen";NA;127;0
"Building";"CreepTumor";NA;127;0
"Building";"CreepTumor";NA;127;0
"Building";"CreepTumorQueen";NA;127;0
"Unit";"Roach";"Larva";137;2
"Unit";"Roach";"Larva";137;2
"Unit";"Roach";"Larva";137;2
"Unit";"Roach";"Larva";137;2
"Unit";"Roach";"Larva";137;2
"Unit";"Roach";"Larva";137;2
"Unit";"Roach";"Larva";137;2
"Unit";"Roach";"Larva";137;2
"Building";"CreepTumor";NA;137;0
"Building";"CreepTumor";NA;137;0
"Building";"CreepTumorQueen";NA;137;0
"Building";"CreepTumorQueen";NA;137;0
"Unit";"Overlord";"Larva";137;0
"Unit";"Overlord";"Larva";137;0
"Upgrade";"GlialReconstitution";"RoachWarren";119;0
"Building";"CreepTumorQueen";NA;147;0
"Unit";"Roach";"Larva";137;2
"Building";"CreepTumor";NA;149;0
"Building";"CreepTumor";NA;149;0
"Unit";"Roach";"Larva";137;2
"Unit";"Roach";"Larva";137;2
"Unit";"Roach";"Larva";137;2
"Unit";"Roach";"Larva";147;2
"Unit";"Roach";"Larva";149;2
"Unit";"Roach";"Larva";149;2
"Unit";"Roach";"Larva";149;2
"Unit";"Roach";"Larva";149;2
"Unit";"Roach";"Larva";153;2
"Unit";"Roach";"Larva";153;2
"Unit";"Roach";"Larva";155;2
"Upgrade";"ZergMissileWeaponsLevel1";"EvolutionChamber";119;0
"Upgrade";"ZergGroundArmorsLevel1";"EvolutionChamber";119;0
"Unit";"Roach";"Larva";163;2
"Unit";"Roach";"Larva";163;2
"Unit";"Roach";"Larva";163;2
"Unit";"Roach";"Larva";163;2
"Unit";"Roach";"Larva";163;2
"Unit";"Roach";"Larva";167;2
"Unit";"Roach";"Larva";167;2
"Building";"Hatchery";NA;137;0
"Unit";"Roach";"Larva";175;2
"Unit";"Roach";"Larva";175;2
"Unit";"Roach";"Larva";175;2
"Building";"CreepTumorQueen";NA;194;0
"Unit";"Roach";"Larva";177;2
"Unit";"Roach";"Larva";177;2
"Unit";"Roach";"Larva";177;2
"Building";"CreepTumor";NA;194;0
"Building";"CreepTumor";NA;194;0
"Building";"CreepTumor";NA;194;0
"Unit";"Overlord";"Larva";200;0
"Unit";"Overlord";"Larva";200;0
"Unit";"Overlord";"Larva";200;0
"Unit";"Roach";"Larva";200;2
"Unit";"Roach";"Larva";200;2
"Unit";"Roach";"Larva";200;2
"Unit";"Roach";"Larva";206;2
"Unit";"Roach";"Larva";206;2
"Unit";"Roach";"Larva";206;2
"Unit";"Roach";"Larva";206;2
"Unit";"Roach";"Larva";206;2
"Unit";"Roach";"Larva";208;2
"Unit";"Roach";"Larva";212;2
"Unit";"Roach";"Larva";212;2
"Unit";"Roach";"Larva";212;2
"Unit";"Roach";"Larva";212;2
"Unit";"Roach";"Larva";212;2
"Unit";"Roach";"Larva";212;2
"Unit";"Roach";"Larva";212;2
"Unit";"Roach";"Larva";212;2
"Unit";"Roach";"Larva";212;2
"Unit";"Roach";"Larva";212;2
"Unit";"Roach";"Larva";212;2
"Unit";"Roach";"Larva";212;2
"Unit";"Roach";"Larva";212;2
"Unit";"Roach";"Larva";224;2
"Unit";"Roach";"Larva";224;2
"Unit";"Roach";"Larva";224;2
"Unit";"Roach";"Larva";226;2
"Unit";"Roach";"Larva";228;2
"Unit";"Roach";"Larva";240;2
"Unit";"Roach";"Larva";240;2
"Unit";"Roach";"Larva";248;2
"Unit";"Roach";"Larva";250;2
"Unit";"Roach";"Larva";250;2
"Unit";"Roach";"Larva";252;2
"Unit";"Roach";"Larva";260;2
