"type";"unit_name";"on_building";"total_supply";"supply"
"Unit";"Overlord";"Larva";12;0
"Building";"Extractor";NA;17;0
"Unit";"Overlord";"Larva";21;0
"Building";"SpawningPool";NA;19;0
"Building";"Hatchery";NA;17;0
"Unit";"Zergling";"Larva";23;1
"Unit";"Zergling";"Larva";23;1
"Unit";"Zergling";"Larva";24;1
"Unit";"Zergling";"Larva";24;1
"Unit";"Queen";"Hatchery";23;2
"Unit";"Queen";"Hatchery";23;2
"Unit";"Overlord";"Larva";30;0
"Unit";"Overlord";"Larva";36;0
"Unit";"Queen";"Hatchery";33;2
"Building";"CreepTumorQueen";NA;38;0
"Unit";"Queen";"Hatchery";35;2
"Building";"CreepTumorQueen";NA;39;0
"Unit";"Zergling";"Larva";50;1
"Unit";"Zergling";"Larva";50;1
"Unit";"Zergling";"Larva";50;1
"Unit";"Zergling";"Larva";50;1
"Building";"CreepTumor";NA;52;0
"Building";"CreepTumorQueen";NA;52;0
"Building";"CreepTumor";NA;52;0
"Building";"CreepTumorQueen";NA;56;0
"Unit";"Overlord";"Larva";56;0
"Unit";"Overlord";"Larva";56;0
"Building";"CreepTumor";NA;59;0
"Unit";"Overlord";"Larva";59;0
"Unit";"Zergling";"Larva";59;1
"Unit";"Zergling";"Larva";59;1
"Unit";"Overlord";"Larva";59;0
"Building";"CreepTumorQueen";NA;59;0
"Building";"CreepTumor";NA;59;0
"Building";"CreepTumor";NA;59;0
"Building";"CreepTumor";NA;59;0
"Unit";"Zergling";"Larva";59;1
"Unit";"Zergling";"Larva";59;1
"Unit";"Zergling";"Larva";59;1
"Unit";"Zergling";"Larva";59;1
"Unit";"Zergling";"Larva";59;1
"Unit";"Zergling";"Larva";59;1
"Building";"Extractor";NA;59;0
"Unit";"Queen";"Hatchery";59;2
"Building";"Hatchery";NA;52;0
"Building";"EvolutionChamber";NA;61;0
"Building";"EvolutionChamber";NA;61;0
"Building";"CreepTumor";NA;78;0
"Building";"CreepTumor";NA;78;0
"Building";"CreepTumor";NA;78;0
"Unit";"Overlord";"Larva";72;0
"Unit";"Overlord";"Larva";78;0
"Building";"CreepTumorQueen";NA;79;0
"Building";"CreepTumor";NA;79;0
"Building";"BanelingNest";NA;70;0
"Building";"CreepTumor";NA;79;0
"Building";"CreepTumor";NA;86;0
"Building";"CreepTumor";NA;88;0
"Building";"CreepTumor";NA;88;0
"Building";"CreepTumor";NA;88;0
"Building";"Hatchery";NA;70;0
"Building";"Extractor";NA;88;0
"Building";"CreepTumor";NA;91;0
"Building";"Extractor";NA;88;0
"Building";"CreepTumorQueen";NA;98;0
"Building";"CreepTumorQueen";NA;98;0
"Unit";"Zergling";"Larva";96;1
"Unit";"Zergling";"Larva";96;1
"Unit";"Zergling";"Larva";98;1
"Unit";"Zergling";"Larva";98;1
"Unit";"Zergling";"Larva";98;1
"Unit";"Zergling";"Larva";98;1
"Unit";"Zergling";"Larva";98;1
"Unit";"Zergling";"Larva";98;1
"Unit";"Zergling";"Larva";98;1
"Unit";"Zergling";"Larva";98;1
"Unit";"Zergling";"Larva";98;1
"Unit";"Zergling";"Larva";98;1
"Unit";"Zergling";"Larva";98;1
"Unit";"Zergling";"Larva";98;1
"Unit";"Zergling";"Larva";98;1
"Unit";"Zergling";"Larva";98;1
"Unit";"Zergling";"Larva";98;1
"Unit";"Zergling";"Larva";98;1
"Unit";"Zergling";"Larva";98;1
"Unit";"Zergling";"Larva";98;1
"Unit";"Zergling";"Larva";98;1
"Unit";"Zergling";"Larva";98;1
"Unit";"Zergling";"Larva";98;1
"Unit";"Zergling";"Larva";98;1
"Unit";"Zergling";"Larva";98;1
"Unit";"Zergling";"Larva";98;1
"Unit";"Zergling";"Larva";98;1
"Unit";"Zergling";"Larva";98;1
"Unit";"Zergling";"Larva";98;1
"Unit";"Zergling";"Larva";98;1
"Unit";"Zergling";"Larva";116;1
"Unit";"Zergling";"Larva";116;1
"Unit";"Zergling";"Larva";116;1
"Unit";"Zergling";"Larva";116;1
"Unit";"Zergling";"Larva";116;1
"Unit";"Zergling";"Larva";116;1
"Unit";"Zergling";"Larva";116;1
"Unit";"Zergling";"Larva";116;1
"Unit";"Zergling";"Larva";116;1
"Unit";"Zergling";"Larva";116;1
"Unit";"Overlord";"Larva";128;0
"Unit";"Overlord";"Larva";128;0
"Unit";"Overlord";"Larva";128;0
"Unit";"Overlord";"Larva";128;0
"Unit";"Baneling";"Zergling";138;0
"Unit";"Baneling";"Zergling";138;0
"Unit";"Baneling";"Zergling";138;0
"Unit";"Baneling";"Zergling";138;0
"Unit";"Baneling";"Zergling";138;0
"Unit";"Baneling";"Zergling";138;0
"Unit";"Baneling";"Zergling";138;0
"Unit";"Baneling";"Zergling";138;0
"Upgrade";"ZergGroundArmorsLevel1";"EvolutionChamber";88;0
"Unit";"Baneling";"Zergling";138;0
"Unit";"Baneling";"Zergling";138;0
"Unit";"Baneling";"Zergling";138;0
"Unit";"Baneling";"Zergling";138;0
"Unit";"Baneling";"Zergling";138;0
"Unit";"Baneling";"Zergling";138;0
"Unit";"Baneling";"Zergling";138;0
"Unit";"Baneling";"Zergling";138;0
"Upgrade";"ZergMeleeWeaponsLevel1";"EvolutionChamber";88;0
"Building";"CreepTumor";NA;138;0
"Building";"CreepTumor";NA;138;0
"Building";"CreepTumor";NA;138;0
"Building";"Extractor";NA;138;0
"Building";"CreepTumor";NA;138;0
"Building";"Extractor";NA;138;0
"Unit";"Zergling";"Larva";138;1
"Unit";"Zergling";"Larva";138;1
"Unit";"Zergling";"Larva";138;1
"Unit";"Zergling";"Larva";138;1
"Unit";"Zergling";"Larva";138;1
"Unit";"Zergling";"Larva";138;1
"Unit";"Zergling";"Larva";138;1
"Unit";"Zergling";"Larva";138;1
"Unit";"Zergling";"Larva";138;1
"Unit";"Zergling";"Larva";138;1
"Unit";"Zergling";"Larva";138;1
"Unit";"Zergling";"Larva";138;1
"Unit";"Zergling";"Larva";138;1
"Unit";"Zergling";"Larva";138;1
"Unit";"Zergling";"Larva";138;1
"Unit";"Zergling";"Larva";138;1
"Unit";"Zergling";"Larva";138;1
"Unit";"Zergling";"Larva";138;1
"Building";"CreepTumor";NA;138;0
"Unit";"Zergling";"Larva";138;1
"Unit";"Zergling";"Larva";138;1
"Unit";"Zergling";"Larva";138;1
"Unit";"Zergling";"Larva";138;1
"Unit";"Zergling";"Larva";138;1
"Unit";"Zergling";"Larva";138;1
"Unit";"Zergling";"Larva";138;1
"Unit";"Zergling";"Larva";138;1
"Building";"CreepTumor";NA;138;0
"Unit";"Zergling";"Larva";171;1
"Unit";"Zergling";"Larva";171;1
"Unit";"Zergling";"Larva";171;1
"Unit";"Zergling";"Larva";171;1
"Unit";"Zergling";"Larva";171;1
"Unit";"Zergling";"Larva";171;1
"Unit";"Zergling";"Larva";171;1
"Unit";"Zergling";"Larva";171;1
"Unit";"Zergling";"Larva";171;1
"Unit";"Zergling";"Larva";171;1
"Unit";"Zergling";"Larva";171;1
"Unit";"Zergling";"Larva";171;1
"Unit";"Zergling";"Larva";171;1
"Unit";"Zergling";"Larva";171;1
"Unit";"Zergling";"Larva";171;1
"Unit";"Zergling";"Larva";171;1
"Unit";"Zergling";"Larva";171;1
"Unit";"Zergling";"Larva";171;1
"Unit";"Zergling";"Larva";171;1
"Unit";"Zergling";"Larva";171;1
"Unit";"Zergling";"Larva";171;1
"Unit";"Zergling";"Larva";171;1
"Unit";"Zergling";"Larva";171;1
"Unit";"Zergling";"Larva";171;1
"Unit";"Zergling";"Larva";171;1
"Unit";"Zergling";"Larva";171;1
"Unit";"Zergling";"Larva";171;1
"Unit";"Zergling";"Larva";171;1
"Unit";"Zergling";"Larva";171;1
"Unit";"Zergling";"Larva";171;1
"Unit";"Zergling";"Larva";171;1
"Unit";"Zergling";"Larva";171;1
"Unit";"Zergling";"Larva";171;1
"Unit";"Zergling";"Larva";171;1
"Unit";"Zergling";"Larva";171;1
"Unit";"Zergling";"Larva";171;1
"Unit";"Zergling";"Larva";171;1
"Unit";"Zergling";"Larva";171;1
"Building";"CreepTumor";NA;171;0
"Unit";"Overlord";"Larva";171;0
"Unit";"Overlord";"Larva";171;0
"Unit";"Overlord";"Larva";171;0
"Building";"CreepTumor";NA;171;0
"Building";"CreepTumor";NA;171;0
"Building";"CreepTumor";NA;171;0
"Building";"CreepTumor";NA;171;0
"Building";"CreepTumor";NA;171;0
"Building";"CreepTumor";NA;171;0
"Unit";"Baneling";"Zergling";209;0
"Unit";"Baneling";"Zergling";209;0
"Unit";"Baneling";"Zergling";209;0
"Unit";"Baneling";"Zergling";209;0
"Unit";"Baneling";"Zergling";209;0
"Unit";"Baneling";"Zergling";209;0
"Unit";"Overlord";"Larva";179;0
"Unit";"Overlord";"Larva";185;0
"Building";"CreepTumorQueen";NA;209;0
"Building";"Hatchery";NA;171;0
"Building";"CreepTumor";NA;209;0
"Unit";"Baneling";"Zergling";209;0
"Unit";"Baneling";"Zergling";209;0
"Unit";"Baneling";"Zergling";209;0
"Unit";"Baneling";"Zergling";209;0
"Unit";"Baneling";"Zergling";209;0
"Unit";"Baneling";"Zergling";209;0
"Unit";"Baneling";"Zergling";209;0
"Unit";"Baneling";"Zergling";209;0
"Unit";"Zergling";"Larva";209;1
"Unit";"Zergling";"Larva";209;1
"Unit";"Zergling";"Larva";209;1
"Unit";"Zergling";"Larva";209;1
"Unit";"Zergling";"Larva";209;1
"Unit";"Zergling";"Larva";209;1
"Unit";"Zergling";"Larva";209;1
"Unit";"Zergling";"Larva";209;1
"Unit";"Zergling";"Larva";209;1
"Unit";"Zergling";"Larva";209;1
"Unit";"Zergling";"Larva";209;1
"Unit";"Zergling";"Larva";209;1
"Unit";"Zergling";"Larva";209;1
"Unit";"Zergling";"Larva";209;1
"Unit";"Zergling";"Larva";209;1
"Unit";"Zergling";"Larva";209;1
"Unit";"Zergling";"Larva";209;1
"Unit";"Zergling";"Larva";209;1
"Unit";"Zergling";"Larva";209;1
"Unit";"Zergling";"Larva";209;1
"Unit";"Zergling";"Larva";209;1
"Unit";"Zergling";"Larva";209;1
"Unit";"Zergling";"Larva";209;1
"Unit";"Zergling";"Larva";209;1
"Unit";"Zergling";"Larva";209;1
"Unit";"Zergling";"Larva";209;1
"Unit";"Zergling";"Larva";209;1
"Unit";"Zergling";"Larva";209;1
"Unit";"Zergling";"Larva";209;1
"Unit";"Zergling";"Larva";209;1
"Unit";"Zergling";"Larva";209;1
"Unit";"Zergling";"Larva";209;1
"Building";"CreepTumor";NA;209;0
"Building";"CreepTumor";NA;209;0
"Unit";"Overlord";"Larva";209;0
"Unit";"Overlord";"Larva";221;0
"Building";"Spire";NA;171;0
"Building";"CreepTumor";NA;245;0
"Building";"CreepTumor";NA;245;0
"Unit";"Queen";"Hatchery";241;2
"Building";"Extractor";NA;245;0
"Building";"Extractor";NA;245;0
"Unit";"Overlord";"Larva";245;0
"Unit";"Overlord";"Larva";245;0
"Upgrade";"ZergGroundArmorsLevel2";"EvolutionChamber";171;0
"Unit";"Overlord";"Larva";245;0
"Unit";"Overlord";"Larva";245;0
"Upgrade";"ZergMeleeWeaponsLevel2";"EvolutionChamber";171;0
"Unit";"Mutalisk";"Larva";245;2
"Unit";"Mutalisk";"Larva";245;2
"Unit";"Mutalisk";"Larva";245;2
"Unit";"Mutalisk";"Larva";245;2
"Unit";"Mutalisk";"Larva";245;2
"Unit";"Mutalisk";"Larva";245;2
"Unit";"Mutalisk";"Larva";245;2
"Unit";"Mutalisk";"Larva";245;2
"Unit";"Mutalisk";"Larva";245;2
"Unit";"Baneling";"Zergling";249;0
"Unit";"Baneling";"Zergling";249;0
"Unit";"Baneling";"Zergling";249;0
"Unit";"Baneling";"Zergling";249;0
"Unit";"Baneling";"Zergling";249;0
"Unit";"Baneling";"Zergling";249;0
"Unit";"Baneling";"Zergling";249;0
"Unit";"Baneling";"Zergling";249;0
"Unit";"Baneling";"Zergling";249;0
"Unit";"Baneling";"Zergling";249;0
"Unit";"Baneling";"Zergling";249;0
"Unit";"Baneling";"Zergling";249;0
"Unit";"Baneling";"Zergling";249;0
"Unit";"Baneling";"Zergling";249;0
"Unit";"Baneling";"Zergling";249;0
"Unit";"Overlord";"Larva";249;0
"Unit";"Overlord";"Larva";267;0
"Unit";"Mutalisk";"Larva";267;2
"Unit";"Mutalisk";"Larva";267;2
"Unit";"Mutalisk";"Larva";267;2
"Unit";"Mutalisk";"Larva";267;2
"Building";"CreepTumor";NA;267;0
"Unit";"Overlord";"Larva";267;0
"Building";"CreepTumor";NA;267;0
"Unit";"Zergling";"Larva";268;1
"Unit";"Zergling";"Larva";268;1
"Unit";"Zergling";"Larva";270;1
"Unit";"Zergling";"Larva";270;1
"Unit";"Zergling";"Larva";270;1
"Unit";"Zergling";"Larva";270;1
"Unit";"Zergling";"Larva";270;1
"Unit";"Zergling";"Larva";270;1
"Unit";"Zergling";"Larva";271;1
"Unit";"Zergling";"Larva";271;1
"Unit";"Zergling";"Larva";271;1
"Unit";"Zergling";"Larva";271;1
"Unit";"Zergling";"Larva";271;1
"Unit";"Zergling";"Larva";271;1
"Unit";"Zergling";"Larva";271;1
"Unit";"Zergling";"Larva";271;1
"Unit";"Zergling";"Larva";271;1
"Unit";"Zergling";"Larva";271;1
"Unit";"Zergling";"Larva";271;1
"Unit";"Zergling";"Larva";271;1
"Unit";"Baneling";"Zergling";282;0
"Unit";"Baneling";"Zergling";282;0
"Unit";"Baneling";"Zergling";282;0
"Unit";"Baneling";"Zergling";282;0
"Unit";"Mutalisk";"Larva";267;2
"Unit";"Mutalisk";"Larva";268;2
"Unit";"Mutalisk";"Larva";268;2
"Unit";"Zergling";"Larva";282;1
"Unit";"Zergling";"Larva";282;1
"Unit";"Zergling";"Larva";282;1
"Unit";"Zergling";"Larva";282;1
"Unit";"Zergling";"Larva";282;1
"Unit";"Zergling";"Larva";282;1
"Unit";"Zergling";"Larva";282;1
"Unit";"Zergling";"Larva";282;1
"Unit";"Zergling";"Larva";282;1
"Unit";"Zergling";"Larva";282;1
"Unit";"Zergling";"Larva";282;1
"Unit";"Zergling";"Larva";282;1
"Unit";"Zergling";"Larva";282;1
"Unit";"Zergling";"Larva";282;1
"Unit";"Zergling";"Larva";282;1
"Unit";"Zergling";"Larva";282;1
"Unit";"Zergling";"Larva";282;1
"Unit";"Zergling";"Larva";282;1
"Unit";"Zergling";"Larva";282;1
"Unit";"Zergling";"Larva";282;1
"Unit";"Zergling";"Larva";282;1
"Unit";"Zergling";"Larva";282;1
"Unit";"Zergling";"Larva";284;1
"Unit";"Zergling";"Larva";284;1
"Unit";"Zergling";"Larva";284;1
"Unit";"Zergling";"Larva";284;1
"Unit";"Zergling";"Larva";284;1
"Unit";"Zergling";"Larva";284;1
"Unit";"Baneling";"Zergling";322;0
"Unit";"Baneling";"Zergling";326;0
"Unit";"Baneling";"Zergling";326;0
"Unit";"Baneling";"Zergling";326;0
"Unit";"Baneling";"Zergling";328;0
"Unit";"Baneling";"Zergling";328;0
"Unit";"Baneling";"Zergling";328;0
"Unit";"Baneling";"Zergling";328;0
"Unit";"Baneling";"Zergling";330;0
"Unit";"Baneling";"Zergling";330;0
"Unit";"Baneling";"Zergling";336;0
"Unit";"Baneling";"Zergling";336;0
"Unit";"Baneling";"Zergling";336;0
"Unit";"Baneling";"Zergling";336;0
"Unit";"Baneling";"Zergling";336;0
"Unit";"Baneling";"Zergling";336;0
"Unit";"Baneling";"Zergling";336;0
"Unit";"Baneling";"Zergling";336;0
"Unit";"Baneling";"Zergling";336;0
"Unit";"Baneling";"Zergling";336;0
"Unit";"Baneling";"Zergling";336;0
"Unit";"Baneling";"Zergling";336;0
"Unit";"Baneling";"Zergling";336;0
"Unit";"Baneling";"Zergling";336;0
"Unit";"Baneling";"Zergling";336;0
"Unit";"Baneling";"Zergling";336;0
"Unit";"Baneling";"Zergling";336;0
"Unit";"Zergling";"Larva";336;1
"Unit";"Zergling";"Larva";336;1
"Unit";"Zergling";"Larva";336;1
"Unit";"Zergling";"Larva";336;1
"Unit";"Zergling";"Larva";336;1
"Unit";"Zergling";"Larva";336;1
"Unit";"Zergling";"Larva";336;1
"Unit";"Zergling";"Larva";336;1
"Unit";"Zergling";"Larva";336;1
"Unit";"Zergling";"Larva";336;1
"Unit";"Zergling";"Larva";336;1
"Unit";"Zergling";"Larva";336;1
"Unit";"Zergling";"Larva";336;1
"Unit";"Zergling";"Larva";336;1
"Unit";"Zergling";"Larva";336;1
"Unit";"Zergling";"Larva";336;1
"Unit";"Zergling";"Larva";336;1
"Unit";"Zergling";"Larva";336;1
"Unit";"Zergling";"Larva";336;1
"Unit";"Zergling";"Larva";336;1
"Unit";"Zergling";"Larva";336;1
"Unit";"Zergling";"Larva";336;1
"Unit";"Zergling";"Larva";336;1
"Unit";"Zergling";"Larva";336;1
"Unit";"Zergling";"Larva";336;1
"Unit";"Zergling";"Larva";336;1
"Unit";"Zergling";"Larva";336;1
"Unit";"Zergling";"Larva";336;1
"Unit";"Zergling";"Larva";336;1
"Unit";"Zergling";"Larva";336;1
"Unit";"Zergling";"Larva";336;1
"Unit";"Zergling";"Larva";336;1
"Unit";"Zergling";"Larva";336;1
"Unit";"Zergling";"Larva";336;1
"Unit";"Zergling";"Larva";336;1
"Unit";"Zergling";"Larva";336;1
"Unit";"Zergling";"Larva";336;1
"Unit";"Zergling";"Larva";336;1
"Unit";"Zergling";"Larva";336;1
"Unit";"Zergling";"Larva";336;1
"Building";"Hatchery";NA;267;0
"Building";"Extractor";NA;336;0
"Building";"Extractor";NA;336;0
"Building";"InfestationPit";NA;336;0
"Unit";"Zergling";"Larva";376;1
"Unit";"Zergling";"Larva";376;1
"Unit";"Zergling";"Larva";376;1
"Unit";"Zergling";"Larva";376;1
"Unit";"Zergling";"Larva";376;1
"Unit";"Zergling";"Larva";376;1
"Unit";"Zergling";"Larva";376;1
"Unit";"Zergling";"Larva";376;1
"Unit";"Zergling";"Larva";376;1
"Unit";"Zergling";"Larva";376;1
"Unit";"Zergling";"Larva";376;1
"Unit";"Zergling";"Larva";376;1
"Unit";"Zergling";"Larva";376;1
"Unit";"Zergling";"Larva";376;1
"Unit";"Zergling";"Larva";376;1
"Unit";"Zergling";"Larva";376;1
"Unit";"Zergling";"Larva";376;1
"Unit";"Zergling";"Larva";376;1
"Unit";"Mutalisk";"Larva";376;2
"Unit";"Mutalisk";"Larva";376;2
"Unit";"Mutalisk";"Larva";376;2
"Unit";"Mutalisk";"Larva";376;2
"Unit";"Mutalisk";"Larva";376;2
"Unit";"Mutalisk";"Larva";376;2
"Unit";"Mutalisk";"Larva";376;2
"Unit";"Zergling";"Larva";414;1
"Unit";"Zergling";"Larva";414;1
"Unit";"Zergling";"Larva";415;1
"Unit";"Zergling";"Larva";415;1
"Unit";"Zergling";"Larva";415;1
"Unit";"Zergling";"Larva";415;1
"Unit";"Zergling";"Larva";415;1
"Unit";"Zergling";"Larva";415;1
"Unit";"Zergling";"Larva";416;1
"Unit";"Zergling";"Larva";416;1
"Unit";"Zergling";"Larva";416;1
"Unit";"Zergling";"Larva";416;1
"Unit";"Zergling";"Larva";416;1
"Unit";"Zergling";"Larva";416;1
"Unit";"Zergling";"Larva";416;1
"Unit";"Zergling";"Larva";416;1
"Unit";"Zergling";"Larva";417;1
"Unit";"Zergling";"Larva";417;1
"Unit";"Zergling";"Larva";417;1
"Unit";"Zergling";"Larva";417;1
"Unit";"Zergling";"Larva";417;1
"Unit";"Zergling";"Larva";417;1
"Unit";"Zergling";"Larva";417;1
"Unit";"Zergling";"Larva";417;1
"Unit";"Zergling";"Larva";417;1
"Unit";"Zergling";"Larva";417;1
"Unit";"Zergling";"Larva";418;1
"Unit";"Zergling";"Larva";418;1
"Unit";"Zergling";"Larva";418;1
"Unit";"Zergling";"Larva";418;1
"Unit";"Zergling";"Larva";418;1
"Unit";"Zergling";"Larva";418;1
"Unit";"Zergling";"Larva";418;1
"Unit";"Zergling";"Larva";418;1
"Unit";"Mutalisk";"Larva";418;2
"Unit";"Zergling";"Larva";418;1
"Unit";"Zergling";"Larva";418;1
"Unit";"Mutalisk";"Larva";418;2
"Unit";"Zergling";"Larva";418;1
"Unit";"Zergling";"Larva";418;1
"Unit";"Zergling";"Larva";418;1
"Unit";"Zergling";"Larva";418;1
"Unit";"Mutalisk";"Larva";418;2
"Unit";"Zergling";"Larva";418;1
"Unit";"Zergling";"Larva";418;1
"Unit";"Baneling";"Zergling";452;0
"Unit";"Baneling";"Zergling";452;0
"Unit";"Baneling";"Zergling";452;0
"Unit";"Baneling";"Zergling";452;0
"Unit";"Baneling";"Zergling";452;0
"Unit";"Baneling";"Zergling";452;0
"Unit";"Baneling";"Zergling";452;0
"Unit";"Baneling";"Zergling";452;0
"Unit";"Baneling";"Zergling";452;0
"Unit";"Baneling";"Zergling";452;0
"Unit";"Baneling";"Zergling";452;0
"Unit";"Baneling";"Zergling";452;0
"Unit";"Baneling";"Zergling";452;0
"Unit";"Baneling";"Zergling";452;0
"Unit";"Baneling";"Zergling";452;0
"Unit";"Baneling";"Zergling";452;0
"Unit";"Baneling";"Zergling";452;0
"Unit";"Baneling";"Zergling";452;0
"Unit";"Baneling";"Zergling";452;0
"Unit";"Baneling";"Zergling";452;0
"Unit";"Baneling";"Zergling";452;0
"Unit";"Baneling";"Zergling";466;0
"Unit";"Baneling";"Zergling";466;0
"Unit";"Baneling";"Zergling";466;0
"Unit";"Baneling";"Zergling";466;0
"Unit";"Baneling";"Zergling";466;0
"Unit";"Zergling";"Larva";466;1
"Unit";"Zergling";"Larva";466;1
"Unit";"Zergling";"Larva";466;1
"Unit";"Zergling";"Larva";466;1
"Unit";"Zergling";"Larva";466;1
"Unit";"Zergling";"Larva";466;1
"Unit";"Zergling";"Larva";466;1
"Unit";"Zergling";"Larva";466;1
"Unit";"Zergling";"Larva";466;1
"Unit";"Zergling";"Larva";466;1
"Unit";"Baneling";"Zergling";466;0
"Unit";"Zergling";"Larva";466;1
"Unit";"Zergling";"Larva";466;1
"Unit";"Zergling";"Larva";466;1
"Unit";"Zergling";"Larva";466;1
"Unit";"Zergling";"Larva";466;1
"Unit";"Zergling";"Larva";466;1
"Unit";"Zergling";"Larva";466;1
"Unit";"Zergling";"Larva";466;1
"Unit";"Zergling";"Larva";466;1
"Unit";"Zergling";"Larva";466;1
"Unit";"Zergling";"Larva";466;1
"Unit";"Zergling";"Larva";466;1
"Unit";"Zergling";"Larva";466;1
"Unit";"Zergling";"Larva";466;1
"Unit";"Zergling";"Larva";466;1
"Unit";"Zergling";"Larva";466;1
"Unit";"Zergling";"Larva";466;1
"Unit";"Zergling";"Larva";466;1
"Unit";"Zergling";"Larva";466;1
"Unit";"Zergling";"Larva";466;1
"Unit";"Zergling";"Larva";466;1
"Unit";"Zergling";"Larva";466;1
"Unit";"Zergling";"Larva";466;1
"Unit";"Zergling";"Larva";466;1
"Unit";"Baneling";"Zergling";500;0
"Unit";"Baneling";"Zergling";500;0
"Unit";"Zergling";"Larva";500;1
"Unit";"Zergling";"Larva";500;1
"Unit";"Baneling";"Zergling";500;0
"Unit";"Zergling";"Larva";500;1
"Unit";"Zergling";"Larva";500;1
"Unit";"Zergling";"Larva";500;1
"Unit";"Zergling";"Larva";500;1
"Unit";"Zergling";"Larva";500;1
"Unit";"Zergling";"Larva";500;1
"Unit";"Zergling";"Larva";500;1
"Unit";"Zergling";"Larva";500;1
"Unit";"Zergling";"Larva";500;1
"Unit";"Zergling";"Larva";500;1
"Unit";"Zergling";"Larva";500;1
"Unit";"Zergling";"Larva";500;1
"Unit";"Zergling";"Larva";500;1
"Unit";"Zergling";"Larva";500;1
"Unit";"Zergling";"Larva";500;1
"Unit";"Zergling";"Larva";500;1
"Unit";"Zergling";"Larva";500;1
"Unit";"Zergling";"Larva";500;1
"Unit";"Zergling";"Larva";500;1
"Unit";"Zergling";"Larva";500;1
"Unit";"Zergling";"Larva";500;1
"Unit";"Zergling";"Larva";500;1
"Unit";"Zergling";"Larva";500;1
"Unit";"Zergling";"Larva";500;1
"Unit";"Zergling";"Larva";500;1
"Unit";"Zergling";"Larva";500;1
"Unit";"Zergling";"Larva";500;1
"Unit";"Zergling";"Larva";500;1
"Unit";"Zergling";"Larva";500;1
"Unit";"Zergling";"Larva";500;1
"Building";"UltraliskCavern";NA;466;0
"Building";"CreepTumorQueen";NA;500;0
"Building";"CreepTumorQueen";NA;500;0
"Building";"CreepTumorQueen";NA;500;0
"Building";"CreepTumorQueen";NA;532;0
"Building";"CreepTumorQueen";NA;532;0
"Building";"CreepTumorQueen";NA;532;0
"Unit";"Zergling";"Larva";532;1
"Unit";"Zergling";"Larva";532;1
"Unit";"Zergling";"Larva";532;1
"Unit";"Zergling";"Larva";532;1
"Unit";"Zergling";"Larva";532;1
"Unit";"Zergling";"Larva";532;1
"Unit";"Zergling";"Larva";532;1
"Unit";"Zergling";"Larva";532;1
"Building";"Hatchery";NA;466;0
"Building";"CreepTumor";NA;540;0
"Building";"CreepTumor";NA;540;0
"Building";"CreepTumor";NA;540;0
"Unit";"Ultralisk";"Larva";532;6
"Unit";"Ultralisk";"Larva";532;6
"Building";"CreepTumorQueen";NA;540;0
"Building";"CreepTumorQueen";NA;540;0
"Building";"CreepTumorQueen";NA;540;0
"Unit";"Ultralisk";"Larva";540;6
"Unit";"Ultralisk";"Larva";540;6
"Unit";"Ultralisk";"Larva";540;6
"Unit";"Ultralisk";"Larva";540;6
"Unit";"Zergling";"Larva";569;1
"Unit";"Zergling";"Larva";569;1
"Unit";"Zergling";"Larva";569;1
"Unit";"Zergling";"Larva";569;1
"Unit";"Zergling";"Larva";569;1
"Unit";"Zergling";"Larva";569;1
"Unit";"Zergling";"Larva";569;1
"Unit";"Zergling";"Larva";569;1
"Unit";"Infestor";"Larva";557;2
"Upgrade";"ChitinousPlating";"UltraliskCavern";540;0
"Building";"CreepTumor";NA;569;0
"Building";"CreepTumor";NA;569;0
"Building";"CreepTumor";NA;569;0
"Unit";"Ultralisk";"Larva";557;6
"Building";"CreepTumor";NA;569;0
"Building";"CreepTumor";NA;569;0
"Building";"CreepTumorQueen";NA;591;0
"Building";"CreepTumorQueen";NA;597;0
"Unit";"Ultralisk";"Larva";557;6
"Building";"CreepTumorQueen";NA;597;0
"Unit";"Ultralisk";"Larva";569;6
"Unit";"Baneling";"Zergling";597;0
"Unit";"Baneling";"Zergling";597;0
"Unit";"Baneling";"Zergling";597;0
"Unit";"Zergling";"Larva";597;1
"Unit";"Zergling";"Larva";597;1
"Unit";"Baneling";"Zergling";597;0
"Unit";"Baneling";"Zergling";597;0
"Unit";"Zergling";"Larva";597;1
"Unit";"Zergling";"Larva";597;1
"Unit";"Zergling";"Larva";597;1
"Unit";"Zergling";"Larva";597;1
"Unit";"Zergling";"Larva";597;1
"Unit";"Zergling";"Larva";597;1
"Unit";"Zergling";"Larva";597;1
"Unit";"Zergling";"Larva";597;1
"Unit";"Zergling";"Larva";597;1
"Unit";"Zergling";"Larva";597;1
"Unit";"Zergling";"Larva";597;1
"Unit";"Zergling";"Larva";597;1
"Unit";"Zergling";"Larva";597;1
"Unit";"Zergling";"Larva";597;1
"Upgrade";"ZergGroundArmorsLevel3";"EvolutionChamber";500;0
"Upgrade";"ZergMeleeWeaponsLevel3";"EvolutionChamber";500;0
"Unit";"Ultralisk";"Larva";569;6
"Unit";"Infestor";"Larva";569;2
"Unit";"Infestor";"Larva";569;2
"Unit";"Zergling";"Larva";609;1
"Unit";"Zergling";"Larva";609;1
"Unit";"Zergling";"Larva";609;1
"Unit";"Zergling";"Larva";609;1
"Unit";"Ultralisk";"Larva";589;6
"Unit";"Zergling";"Larva";625;1
"Unit";"Zergling";"Larva";625;1
"Unit";"Zergling";"Larva";625;1
"Unit";"Zergling";"Larva";625;1
"Unit";"Zergling";"Larva";625;1
"Unit";"Zergling";"Larva";625;1
"Unit";"Zergling";"Larva";625;1
"Unit";"Zergling";"Larva";625;1
"Unit";"Ultralisk";"Larva";609;6
"Unit";"Ultralisk";"Larva";609;6
"Building";"CreepTumor";NA;653;0
"Building";"CreepTumor";NA;653;0
"Building";"CreepTumor";NA;653;0
"Unit";"Ultralisk";"Larva";635;6
"Building";"CreepTumorQueen";NA;665;0
"Building";"CreepTumorQueen";NA;665;0
"Building";"CreepTumorQueen";NA;665;0
"Unit";"Baneling";"Zergling";665;0
"Unit";"Baneling";"Zergling";665;0
"Unit";"Baneling";"Zergling";665;0
"Unit";"Baneling";"Zergling";665;0
"Unit";"Baneling";"Zergling";665;0
"Unit";"Baneling";"Zergling";665;0
"Unit";"Baneling";"Zergling";665;0
"Unit";"Baneling";"Zergling";665;0
"Unit";"Baneling";"Zergling";665;0
"Unit";"Baneling";"Zergling";665;0
"Unit";"Baneling";"Zergling";665;0
"Unit";"Baneling";"Zergling";665;0
"Building";"CreepTumor";NA;671;0
"Building";"CreepTumor";NA;671;0
"Building";"CreepTumor";NA;671;0
"Building";"CreepTumor";NA;671;0
"Unit";"Ultralisk";"Larva";653;6
"Unit";"Ultralisk";"Larva";653;6
"Building";"CreepTumor";NA;671;0
"Building";"CreepTumor";NA;671;0
"Unit";"Ultralisk";"Larva";653;6
"Unit";"Ultralisk";"Larva";653;6
"Building";"CreepTumor";NA;683;0
"Building";"CreepTumor";NA;683;0
"Building";"CreepTumor";NA;683;0
"Building";"CreepTumorQueen";NA;696;0
"Building";"CreepTumorQueen";NA;696;0
"Unit";"Zergling";"Larva";696;1
"Unit";"Zergling";"Larva";696;1
"Unit";"Overlord";"Larva";696;0
"Unit";"Overlord";"Larva";696;0
"Unit";"Overlord";"Larva";696;0
"Building";"Extractor";NA;696;0
"Unit";"Corruptor";"Larva";696;2
"Unit";"Corruptor";"Larva";696;2
"Building";"SpineCrawler";NA;696;0
"Building";"SpineCrawler";NA;696;0
"Unit";"Corruptor";"Larva";698;2
"Unit";"Corruptor";"Larva";698;2
"Unit";"Corruptor";"Larva";698;2
"Unit";"Corruptor";"Larva";698;2
"Unit";"Corruptor";"Larva";698;2
"Unit";"Corruptor";"Larva";698;2
"Unit";"Corruptor";"Larva";698;2
"Unit";"Corruptor";"Larva";698;2
"Unit";"Corruptor";"Larva";698;2
"Unit";"Overlord";"Larva";708;0
"Unit";"Overlord";"Larva";708;0
"Building";"CreepTumor";NA;726;0
"Building";"Hatchery";NA;695;0
"Unit";"Ultralisk";"Larva";708;6
"Unit";"Zergling";"Larva";726;1
"Unit";"Zergling";"Larva";726;1
"Unit";"Zergling";"Larva";726;1
"Unit";"Zergling";"Larva";726;1
"Building";"CreepTumorQueen";NA;736;0
"Building";"CreepTumor";NA;736;0
"Building";"CreepTumorQueen";NA;736;0
"Building";"CreepTumor";NA;736;0
"Building";"CreepTumorQueen";NA;737;0
"Building";"CreepTumor";NA;736;0
"Building";"CreepTumor";NA;736;0
"Unit";"Infestor";"Larva";736;2
"Unit";"Infestor";"Larva";736;2
"Unit";"Infestor";"Larva";736;2
"Building";"CreepTumor";NA;760;0
"Building";"CreepTumor";NA;760;0
"Building";"CreepTumor";NA;760;0
"Unit";"Overlord";"Larva";754;0
"Unit";"Overlord";"Larva";754;0
"Unit";"Overlord";"Larva";754;0
"Building";"CreepTumor";NA;760;0
"Building";"CreepTumor";NA;760;0
"Building";"CreepTumor";NA;760;0
"Building";"CreepTumor";NA;760;0
"Building";"CreepTumor";NA;760;0
"Building";"Extractor";NA;760;0
"Building";"Extractor";NA;760;0
"Unit";"Zergling";"Larva";760;1
"Unit";"Zergling";"Larva";760;1
"Unit";"Zergling";"Larva";760;1
"Unit";"Zergling";"Larva";760;1
"Unit";"Zergling";"Larva";760;1
"Unit";"Zergling";"Larva";760;1
"Building";"SporeCrawler";NA;760;0
"Building";"SporeCrawler";NA;760;0
"Unit";"Ultralisk";"Larva";754;6
"Unit";"Ultralisk";"Larva";754;6
"Building";"Hatchery";NA;736;0
"Unit";"Ultralisk";"Larva";754;6
"Unit";"Ultralisk";"Larva";754;6
"Unit";"Ultralisk";"Larva";754;6
"Unit";"Ultralisk";"Larva";754;6
"Unit";"Zergling";"Larva";763;1
"Unit";"Zergling";"Larva";763;1
"Unit";"Zergling";"Larva";763;1
"Unit";"Zergling";"Larva";763;1
"Unit";"Zergling";"Larva";763;1
"Unit";"Zergling";"Larva";763;1
"Unit";"Zergling";"Larva";763;1
"Unit";"Zergling";"Larva";763;1
"Unit";"Zergling";"Larva";763;1
"Unit";"Zergling";"Larva";763;1
"Unit";"Zergling";"Larva";763;1
"Unit";"Zergling";"Larva";763;1
"Unit";"Zergling";"Larva";763;1
"Unit";"Zergling";"Larva";763;1
"Unit";"Zergling";"Larva";763;1
"Unit";"Zergling";"Larva";763;1
"Unit";"Zergling";"Larva";763;1
"Unit";"Zergling";"Larva";763;1
"Unit";"Zergling";"Larva";763;1
"Unit";"Zergling";"Larva";763;1
"Unit";"Zergling";"Larva";763;1
"Unit";"Zergling";"Larva";763;1
"Unit";"Zergling";"Larva";763;1
"Unit";"Zergling";"Larva";763;1
"Unit";"Zergling";"Larva";763;1
"Unit";"Zergling";"Larva";763;1
"Unit";"Zergling";"Larva";763;1
"Unit";"Zergling";"Larva";763;1
"Unit";"Zergling";"Larva";763;1
"Unit";"Zergling";"Larva";763;1
"Unit";"Zergling";"Larva";763;1
"Unit";"Zergling";"Larva";763;1
"Unit";"Zergling";"Larva";763;1
"Unit";"Zergling";"Larva";763;1
"Unit";"Zergling";"Larva";763;1
"Unit";"Zergling";"Larva";763;1
"Unit";"Overlord";"Larva";769;0
"Unit";"Ultralisk";"Larva";760;6
"Building";"CreepTumor";NA;841;0
"Building";"CreepTumor";NA;841;0
"Building";"CreepTumor";NA;841;0
"Building";"CreepTumor";NA;841;0
"Building";"CreepTumor";NA;841;0
"Unit";"Baneling";"Zergling";841;0
"Unit";"Baneling";"Zergling";841;0
"Unit";"Baneling";"Zergling";841;0
"Unit";"Baneling";"Zergling";841;0
"Unit";"Baneling";"Zergling";841;0
"Unit";"Baneling";"Zergling";841;0
"Unit";"Baneling";"Zergling";841;0
"Unit";"Baneling";"Zergling";841;0
"Unit";"Baneling";"Zergling";841;0
"Unit";"Baneling";"Zergling";841;0
"Unit";"Baneling";"Zergling";841;0
"Unit";"Baneling";"Zergling";841;0
"Unit";"Baneling";"Zergling";841;0
"Unit";"Baneling";"Zergling";841;0
"Unit";"Baneling";"Zergling";841;0
"Unit";"Baneling";"Zergling";841;0
"Building";"CreepTumor";NA;851;0
"Building";"CreepTumorQueen";NA;851;0
"Building";"CreepTumorQueen";NA;851;0
"Building";"CreepTumor";NA;851;0
"Building";"CreepTumor";NA;851;0
"Building";"CreepTumorQueen";NA;851;0
"Building";"CreepTumor";NA;851;0
"Building";"CreepTumor";NA;851;0
"Building";"SporeCrawler";NA;851;0
"Building";"SporeCrawler";NA;851;0
"Building";"SpineCrawler";NA;851;0
"Building";"SpineCrawler";NA;851;0
"Unit";"Zergling";"Larva";851;1
"Unit";"Zergling";"Larva";851;1
"Unit";"Zergling";"Larva";851;1
"Unit";"Zergling";"Larva";851;1
"Unit";"Zergling";"Larva";851;1
"Unit";"Zergling";"Larva";851;1
"Unit";"Zergling";"Larva";851;1
"Unit";"Zergling";"Larva";851;1
"Unit";"Zergling";"Larva";851;1
"Unit";"Zergling";"Larva";851;1
"Unit";"Zergling";"Larva";851;1
"Unit";"Zergling";"Larva";851;1
"Unit";"Zergling";"Larva";851;1
"Unit";"Zergling";"Larva";851;1
"Unit";"Zergling";"Larva";851;1
"Unit";"Zergling";"Larva";851;1
"Unit";"Zergling";"Larva";851;1
"Unit";"Zergling";"Larva";851;1
"Unit";"Corruptor";"Larva";851;2
"Unit";"Corruptor";"Larva";851;2
"Unit";"Corruptor";"Larva";851;2
"Building";"CreepTumor";NA;875;0
"Unit";"Infestor";"Larva";851;2
"Unit";"Infestor";"Larva";851;2
"Building";"CreepTumor";NA;875;0
"Unit";"Infestor";"Larva";851;2
"Unit";"Infestor";"Larva";851;2
"Building";"CreepTumor";NA;875;0
"Building";"CreepTumor";NA;875;0
"Unit";"Ultralisk";"Larva";851;6
"Unit";"Ultralisk";"Larva";851;6
"Unit";"Ultralisk";"Larva";851;6
"Unit";"Ultralisk";"Larva";851;6
"Unit";"Ultralisk";"Larva";851;6
"Unit";"Ultralisk";"Larva";851;6
"Unit";"Corruptor";"Larva";875;2
"Unit";"Corruptor";"Larva";875;2
"Building";"CreepTumor";NA;919;0
"Building";"CreepTumor";NA;919;0
"Unit";"Baneling";"Zergling";919;0
"Unit";"Baneling";"Zergling";919;0
"Unit";"Baneling";"Zergling";919;0
"Unit";"Baneling";"Zergling";919;0
"Unit";"Baneling";"Zergling";919;0
"Unit";"Baneling";"Zergling";919;0
"Unit";"Baneling";"Zergling";919;0
"Unit";"Zergling";"Larva";923;1
"Unit";"Zergling";"Larva";923;1
"Unit";"Zergling";"Larva";923;1
"Unit";"Zergling";"Larva";923;1
"Unit";"Zergling";"Larva";923;1
"Unit";"Zergling";"Larva";923;1
"Unit";"Zergling";"Larva";923;1
"Unit";"Zergling";"Larva";923;1
"Unit";"Infestor";"Larva";919;2
"Unit";"Infestor";"Larva";919;2
"Unit";"Ultralisk";"Larva";919;6
"Unit";"Ultralisk";"Larva";919;6
"Unit";"Ultralisk";"Larva";919;6
"Unit";"Ultralisk";"Larva";919;6
"Building";"CreepTumor";NA;959;0
"Building";"CreepTumor";NA;959;0
"Unit";"Corruptor";"Larva";935;2
"Unit";"Corruptor";"Larva";935;2
"Unit";"Corruptor";"Larva";935;2
"Unit";"Overlord";"Larva";959;0
"Building";"Hatchery";NA;919;0
"Building";"CreepTumor";NA;959;0
"Building";"CreepTumorQueen";NA;970;0
"Unit";"Ultralisk";"Larva";959;6
"Building";"CreepTumorQueen";NA;970;0
"Building";"CreepTumorQueen";NA;970;0
"Building";"Extractor";NA;970;0
"Building";"Extractor";NA;970;0
"Building";"CreepTumor";NA;976;0
"Building";"CreepTumor";NA;976;0
"Unit";"Zergling";"Larva";970;1
"Unit";"Zergling";"Larva";970;1
"Unit";"Zergling";"Larva";970;1
"Unit";"Zergling";"Larva";970;1
"Unit";"Zergling";"Larva";970;1
"Unit";"Zergling";"Larva";970;1
"Unit";"Zergling";"Larva";970;1
"Unit";"Zergling";"Larva";970;1
"Unit";"Zergling";"Larva";970;1
"Unit";"Zergling";"Larva";970;1
"Unit";"Zergling";"Larva";970;1
"Unit";"Zergling";"Larva";970;1
"Unit";"Zergling";"Larva";970;1
"Unit";"Zergling";"Larva";970;1
"Building";"CreepTumor";NA;976;0
"Unit";"Zergling";"Larva";970;1
"Unit";"Zergling";"Larva";970;1
"Unit";"Zergling";"Larva";970;1
"Unit";"Zergling";"Larva";970;1
"Unit";"Zergling";"Larva";970;1
"Unit";"Zergling";"Larva";970;1
"Unit";"Zergling";"Larva";970;1
"Unit";"Zergling";"Larva";970;1
"Unit";"Zergling";"Larva";970;1
"Unit";"Zergling";"Larva";970;1
"Unit";"Zergling";"Larva";970;1
"Unit";"Zergling";"Larva";970;1
"Unit";"Zergling";"Larva";970;1
"Unit";"Zergling";"Larva";970;1
"Unit";"Zergling";"Larva";970;1
"Unit";"Zergling";"Larva";970;1
"Unit";"Zergling";"Larva";970;1
"Unit";"Zergling";"Larva";970;1
"Unit";"Zergling";"Larva";970;1
"Unit";"Zergling";"Larva";970;1
"Unit";"Zergling";"Larva";970;1
"Unit";"Zergling";"Larva";970;1
"Unit";"Zergling";"Larva";970;1
"Unit";"Zergling";"Larva";970;1
"Unit";"Zergling";"Larva";970;1
"Unit";"Zergling";"Larva";970;1
"Unit";"Zergling";"Larva";970;1
"Unit";"Zergling";"Larva";970;1
"Unit";"Zergling";"Larva";970;1
"Unit";"Zergling";"Larva";970;1
"Unit";"Zergling";"Larva";970;1
"Unit";"Zergling";"Larva";970;1
"Building";"CreepTumor";NA;976;0
"Building";"CreepTumor";NA;976;0
"Building";"CreepTumor";NA;1022;0
"Unit";"Ultralisk";"Larva";970;6
"Unit";"Ultralisk";"Larva";970;6
"Unit";"Ultralisk";"Larva";970;6
"Building";"CreepTumorQueen";NA;1023;0
"Building";"CreepTumorQueen";NA;1023;0
"Unit";"Baneling";"Zergling";1023;0
"Unit";"Baneling";"Zergling";1023;0
"Unit";"Baneling";"Zergling";1023;0
"Unit";"Baneling";"Zergling";1023;0
"Unit";"Baneling";"Zergling";1023;0
"Building";"CreepTumorQueen";NA;1023;0
"Unit";"Baneling";"Zergling";1023;0
"Unit";"Baneling";"Zergling";1023;0
"Unit";"Baneling";"Zergling";1023;0
"Unit";"Baneling";"Zergling";1023;0
"Unit";"Baneling";"Zergling";1023;0
"Unit";"Baneling";"Zergling";1023;0
"Unit";"Baneling";"Zergling";1023;0
"Unit";"Baneling";"Zergling";1023;0
"Unit";"Baneling";"Zergling";1023;0
"Unit";"Zergling";"Larva";1023;1
"Unit";"Zergling";"Larva";1023;1
"Unit";"Zergling";"Larva";1023;1
"Unit";"Zergling";"Larva";1023;1
"Unit";"Zergling";"Larva";1023;1
"Unit";"Zergling";"Larva";1023;1
"Building";"CreepTumor";NA;1041;0
"Building";"CreepTumor";NA;1041;0
"Building";"CreepTumor";NA;1041;0
"Building";"Hatchery";NA;970;0
"Unit";"Ultralisk";"Larva";1023;6
