"type";"unit_name";"on_building";"total_supply";"supply"
"Unit";"Overlord";"Larva";13;0
"Building";"Extractor";NA;18;0
"Unit";"Overlord";"Larva";21;0
"Building";"SpawningPool";NA;19;0
"Building";"Hatchery";NA;17;0
"Unit";"Zergling";"Larva";22;1
"Unit";"Zergling";"Larva";22;1
"Unit";"Zergling";"Larva";22;1
"Unit";"Zergling";"Larva";22;1
"Unit";"Zergling";"Larva";22;1
"Unit";"Zergling";"Larva";22;1
"Unit";"Queen";"Hatchery";22;2
"Unit";"Queen";"Hatchery";22;2
"Unit";"Overlord";"Larva";33;0
"Unit";"Overlord";"Larva";38;0
"Unit";"Queen";"Hatchery";36;2
"Unit";"Queen";"Hatchery";37;2
"Building";"CreepTumorQueen";NA;40;0
"Building";"CreepTumorQueen";NA;40;0
"Building";"CreepTumor";NA;54;0
"Unit";"Overlord";"Larva";51;0
"Unit";"Overlord";"Larva";51;0
"Building";"Extractor";NA;54;0
"Unit";"Queen";"Hatchery";51;2
"Building";"CreepTumorQueen";NA;54;0
"Building";"CreepTumorQueen";NA;54;0
"Building";"CreepTumorQueen";NA;54;0
"Unit";"Zergling";"Larva";54;1
"Unit";"Zergling";"Larva";54;1
"Unit";"Zergling";"Larva";54;1
"Unit";"Zergling";"Larva";54;1
"Unit";"Zergling";"Larva";54;1
"Unit";"Zergling";"Larva";54;1
"Building";"CreepTumor";NA;67;0
"Building";"CreepTumorQueen";NA;67;0
"Building";"CreepTumorQueen";NA;67;0
"Building";"CreepTumor";NA;68;0
"Building";"CreepTumor";NA;68;0
"Unit";"Overlord";"Larva";67;0
"Building";"CreepTumor";NA;68;0
"Building";"Hatchery";NA;45;0
"Building";"SporeCrawler";NA;67;0
"Building";"SporeCrawler";NA;68;0
"Building";"CreepTumor";NA;69;0
"Building";"CreepTumor";NA;69;0
"Unit";"Zergling";"Larva";69;1
"Unit";"Zergling";"Larva";69;1
"Unit";"Zergling";"Larva";69;1
"Unit";"Zergling";"Larva";69;1
"Unit";"Zergling";"Larva";69;1
"Unit";"Zergling";"Larva";69;1
"Building";"EvolutionChamber";NA;69;0
"Unit";"Zergling";"Larva";69;1
"Unit";"Zergling";"Larva";69;1
"Building";"EvolutionChamber";NA;69;0
"Building";"CreepTumor";NA;74;0
"Building";"CreepTumor";NA;74;0
"Unit";"Overlord";"Larva";69;0
"Building";"CreepTumor";NA;74;0
"Unit";"Queen";"Hatchery";69;2
"Unit";"Zergling";"Larva";82;1
"Unit";"Zergling";"Larva";82;1
"Unit";"Zergling";"Larva";82;1
"Unit";"Zergling";"Larva";82;1
"Unit";"Zergling";"Larva";82;1
"Unit";"Zergling";"Larva";82;1
"Unit";"Zergling";"Larva";82;1
"Unit";"Zergling";"Larva";82;1
"Unit";"Zergling";"Larva";82;1
"Unit";"Zergling";"Larva";82;1
"Unit";"Zergling";"Larva";82;1
"Unit";"Zergling";"Larva";82;1
"Building";"CreepTumor";NA;86;0
"Building";"SporeCrawler";NA;82;0
"Building";"CreepTumor";NA;86;0
"Building";"CreepTumor";NA;86;0
"Building";"CreepTumor";NA;86;0
"Unit";"Overlord";"Larva";86;0
"Unit";"Zergling";"Larva";100;1
"Unit";"Zergling";"Larva";100;1
"Unit";"Zergling";"Larva";100;1
"Unit";"Zergling";"Larva";100;1
"Unit";"Zergling";"Larva";100;1
"Unit";"Zergling";"Larva";100;1
"Unit";"Zergling";"Larva";100;1
"Unit";"Zergling";"Larva";100;1
"Unit";"Zergling";"Larva";100;1
"Unit";"Zergling";"Larva";100;1
"Unit";"Zergling";"Larva";100;1
"Unit";"Zergling";"Larva";100;1
"Unit";"Overlord";"Larva";100;0
"Unit";"Zergling";"Larva";100;1
"Unit";"Zergling";"Larva";100;1
"Unit";"Zergling";"Larva";100;1
"Unit";"Zergling";"Larva";100;1
"Unit";"Zergling";"Larva";100;1
"Unit";"Zergling";"Larva";100;1
"Unit";"Zergling";"Larva";100;1
"Unit";"Zergling";"Larva";100;1
"Unit";"Zergling";"Larva";100;1
"Unit";"Zergling";"Larva";100;1
"Unit";"Zergling";"Larva";100;1
"Unit";"Zergling";"Larva";100;1
"Unit";"Zergling";"Larva";100;1
"Unit";"Zergling";"Larva";100;1
"Unit";"Zergling";"Larva";112;1
"Unit";"Zergling";"Larva";112;1
"Unit";"Zergling";"Larva";112;1
"Unit";"Zergling";"Larva";112;1
"Unit";"Zergling";"Larva";112;1
"Unit";"Zergling";"Larva";112;1
"Unit";"Zergling";"Larva";112;1
"Unit";"Zergling";"Larva";112;1
"Unit";"Zergling";"Larva";112;1
"Unit";"Zergling";"Larva";112;1
"Unit";"Zergling";"Larva";112;1
"Unit";"Zergling";"Larva";112;1
"Unit";"Queen";"Hatchery";112;2
"Unit";"Queen";"Hatchery";112;2
"Building";"CreepTumor";NA;138;0
"Building";"CreepTumor";NA;138;0
"Unit";"Queen";"Hatchery";126;2
"Building";"Extractor";NA;140;0
"Building";"Extractor";NA;144;0
"Unit";"Overlord";"Larva";144;0
"Unit";"Overlord";"Larva";144;0
"Building";"CreepTumor";NA;145;0
"Upgrade";"ZergMeleeWeaponsLevel1";"EvolutionChamber";100;0
"Upgrade";"ZergGroundArmorsLevel1";"EvolutionChamber";100;0
"Building";"Extractor";NA;145;0
"Building";"Extractor";NA;145;0
"Building";"CreepTumor";NA;147;0
"Building";"CreepTumor";NA;147;0
"Building";"CreepTumorQueen";NA;157;0
"Building";"RoachWarren";NA;147;0
"Building";"CreepTumor";NA;157;0
"Building";"CreepTumor";NA;157;0
"Building";"CreepTumor";NA;160;0
"Unit";"Overlord";"Larva";160;0
"Building";"CreepTumorQueen";NA;160;0
"Unit";"Overlord";"Larva";160;0
"Unit";"Overlord";"Larva";160;0
"Unit";"Overlord";"Larva";160;0
"Building";"CreepTumor";NA;160;0
"Building";"CreepTumorQueen";NA;160;0
"Building";"CreepTumorQueen";NA;160;0
"Building";"CreepTumor";NA;160;0
"Unit";"Roach";"Larva";160;2
"Unit";"Roach";"Larva";160;2
"Unit";"Roach";"Larva";160;2
"Unit";"Roach";"Larva";160;2
"Unit";"Roach";"Larva";160;2
"Unit";"Roach";"Larva";160;2
"Unit";"Roach";"Larva";160;2
"Unit";"Roach";"Larva";160;2
"Unit";"Roach";"Larva";160;2
"Unit";"Roach";"Larva";160;2
"Unit";"Roach";"Larva";160;2
"Unit";"Roach";"Larva";160;2
"Building";"Hatchery";NA;157;0
"Unit";"Roach";"Larva";184;2
"Unit";"Roach";"Larva";184;2
"Unit";"Roach";"Larva";184;2
"Unit";"Roach";"Larva";184;2
"Unit";"Roach";"Larva";184;2
"Unit";"Roach";"Larva";184;2
"Unit";"Roach";"Larva";184;2
"Unit";"Roach";"Larva";184;2
"Building";"CreepTumorQueen";NA;184;0
"Building";"CreepTumorQueen";NA;184;0
"Building";"CreepTumor";NA;184;0
"Building";"CreepTumor";NA;184;0
"Building";"CreepTumor";NA;203;0
"Unit";"Overlord";"Larva";203;0
"Unit";"Overlord";"Larva";203;0
"Upgrade";"ZergMissileWeaponsLevel1";"EvolutionChamber";160;0
"Building";"CreepTumor";NA;211;0
"Unit";"Roach";"Larva";211;2
"Unit";"Roach";"Larva";211;2
"Unit";"Roach";"Larva";211;2
"Unit";"Roach";"Larva";211;2
"Unit";"Roach";"Larva";211;2
"Upgrade";"GlialReconstitution";"RoachWarren";184;0
"Building";"Extractor";NA;211;0
"Building";"Extractor";NA;211;0
"Unit";"Roach";"Larva";228;2
"Unit";"Roach";"Larva";228;2
"Unit";"Roach";"Larva";228;2
"Unit";"Roach";"Larva";228;2
"Unit";"Roach";"Larva";228;2
"Unit";"Roach";"Larva";228;2
"Unit";"Roach";"Larva";228;2
"Unit";"Roach";"Larva";228;2
"Unit";"Roach";"Larva";228;2
"Unit";"Roach";"Larva";228;2
"Upgrade";"ZergGroundArmorsLevel2";"EvolutionChamber";184;0
"Unit";"Roach";"Larva";228;2
"Unit";"Roach";"Larva";228;2
"Unit";"Roach";"Larva";248;2
"Unit";"Roach";"Larva";248;2
"Unit";"Roach";"Larva";248;2
"Unit";"Roach";"Larva";248;2
"Unit";"Roach";"Larva";248;2
"Unit";"Roach";"Larva";248;2
"Unit";"Roach";"Larva";252;2
"Unit";"Queen";"Hatchery";252;2
"Building";"CreepTumor";NA;280;0
"Building";"CreepTumor";NA;280;0
"Unit";"Roach";"Larva";280;2
"Unit";"Roach";"Larva";280;2
"Unit";"Roach";"Larva";280;2
"Unit";"Roach";"Larva";280;2
"Unit";"Overlord";"Larva";280;0
"Unit";"Queen";"Hatchery";270;2
"Building";"CreepTumor";NA;284;0
"Building";"CreepTumor";NA;284;0
"Building";"CreepTumor";NA;292;0
"Building";"CreepTumor";NA;294;0
"Building";"InfestationPit";NA;280;0
"Unit";"Overlord";"Larva";302;0
"Unit";"Overlord";"Larva";302;0
"Unit";"Roach";"Larva";302;2
"Unit";"Roach";"Larva";302;2
"Unit";"Roach";"Larva";302;2
"Unit";"Roach";"Larva";302;2
"Unit";"Roach";"Larva";302;2
"Unit";"Roach";"Larva";302;2
"Unit";"Roach";"Larva";302;2
"Unit";"Roach";"Larva";302;2
"Unit";"Roach";"Larva";302;2
"Unit";"Roach";"Larva";302;2
"Unit";"Roach";"Larva";302;2
"Unit";"Roach";"Larva";304;2
"Unit";"Roach";"Larva";308;2
"Unit";"Roach";"Larva";308;2
"Unit";"Roach";"Larva";308;2
"Unit";"Roach";"Larva";308;2
"Unit";"Roach";"Larva";308;2
"Unit";"Roach";"Larva";308;2
"Unit";"Overlord";"Larva";330;0
"Building";"Hatchery";NA;302;0
"Unit";"Overlord";"Larva";338;0
"Unit";"Overlord";"Larva";338;0
"Unit";"Overlord";"Larva";338;0
"Building";"CreepTumor";NA;338;0
"Building";"CreepTumor";NA;338;0
"Unit";"Overlord";"Larva";338;0
"Unit";"Roach";"Larva";338;2
"Unit";"Roach";"Larva";338;2
"Unit";"Roach";"Larva";338;2
"Unit";"Roach";"Larva";338;2
"Unit";"Roach";"Larva";338;2
"Unit";"Roach";"Larva";338;2
"Unit";"Roach";"Larva";338;2
"Unit";"Roach";"Larva";338;2
"Unit";"Roach";"Larva";338;2
"Unit";"Roach";"Larva";338;2
"Unit";"Roach";"Larva";338;2
"Unit";"Roach";"Larva";338;2
"Unit";"Roach";"Larva";338;2
"Unit";"Roach";"Larva";338;2
"Unit";"Roach";"Larva";338;2
"Upgrade";"ZergMissileWeaponsLevel2";"EvolutionChamber";302;0
"Unit";"Roach";"Larva";338;2
"Unit";"Roach";"Larva";338;2
"Unit";"Overlord";"Larva";338;0
"Unit";"Overlord";"Larva";338;0
"Building";"Hatchery";NA;338;0
"Building";"Hatchery";NA;338;0
"Building";"Extractor";NA;372;0
"Building";"Extractor";NA;372;0
"Unit";"Roach";"Larva";372;2
"Unit";"Roach";"Larva";372;2
"Unit";"Roach";"Larva";372;2
"Unit";"Roach";"Larva";372;2
"Unit";"Roach";"Larva";372;2
"Unit";"Roach";"Larva";372;2
"Unit";"Roach";"Larva";372;2
"Unit";"Roach";"Larva";372;2
"Unit";"Roach";"Larva";372;2
"Unit";"Roach";"Larva";372;2
"Unit";"Roach";"Larva";372;2
"Unit";"Roach";"Larva";372;2
"Unit";"Roach";"Larva";372;2
"Unit";"Roach";"Larva";372;2
"Unit";"Roach";"Larva";400;2
"Unit";"Roach";"Larva";400;2
"Unit";"Roach";"Larva";400;2
"Unit";"Roach";"Larva";400;2
"Unit";"Roach";"Larva";400;2
"Unit";"Roach";"Larva";400;2
"Unit";"Roach";"Larva";400;2
"Unit";"Roach";"Larva";400;2
"Unit";"Roach";"Larva";400;2
"Unit";"Roach";"Larva";400;2
"Unit";"Roach";"Larva";400;2
"Unit";"Roach";"Larva";400;2
"Unit";"Roach";"Larva";400;2
"Unit";"Roach";"Larva";400;2
"Unit";"Roach";"Larva";400;2
"Unit";"Roach";"Larva";400;2
"Building";"RoachWarren";NA;432;0
"Building";"CreepTumor";NA;432;0
"Building";"EvolutionChamber";NA;432;0
"Unit";"Queen";"Hatchery";432;2
"Unit";"Queen";"Hatchery";432;2
"Unit";"Roach";"Larva";432;2
"Unit";"Roach";"Larva";432;2
"Unit";"Roach";"Larva";432;2
"Unit";"Roach";"Larva";432;2
"Unit";"Roach";"Larva";432;2
"Unit";"Roach";"Larva";432;2
"Unit";"Roach";"Larva";432;2
"Unit";"Roach";"Larva";432;2
"Unit";"Roach";"Larva";432;2
"Unit";"Roach";"Larva";432;2
"Unit";"Roach";"Larva";432;2
"Unit";"Roach";"Larva";432;2
"Unit";"Roach";"Larva";432;2
"Unit";"Roach";"Larva";432;2
"Unit";"Roach";"Larva";432;2
"Unit";"Roach";"Larva";432;2
"Unit";"Roach";"Larva";432;2
"Unit";"Roach";"Larva";432;2
"Unit";"Queen";"Hatchery";432;2
"Unit";"Queen";"Hatchery";432;2
"Unit";"Viper";"Larva";432;3
"Unit";"Viper";"Larva";432;3
"Unit";"Viper";"Larva";432;3
"Unit";"Viper";"Larva";432;3
"Unit";"Roach";"Larva";476;2
"Unit";"Roach";"Larva";476;2
"Unit";"Roach";"Larva";476;2
"Unit";"Roach";"Larva";476;2
"Unit";"Roach";"Larva";476;2
"Unit";"Viper";"Larva";432;3
"Unit";"Overlord";"Larva";476;0
"Unit";"Roach";"Larva";504;2
"Unit";"Roach";"Larva";504;2
"Unit";"Roach";"Larva";504;2
"Unit";"Roach";"Larva";504;2
"Unit";"Roach";"Larva";504;2
"Unit";"Roach";"Larva";504;2
"Unit";"Roach";"Larva";504;2
"Unit";"Roach";"Larva";504;2
"Unit";"Roach";"Larva";504;2
"Unit";"Roach";"Larva";504;2
"Unit";"Roach";"Larva";504;2
"Unit";"Roach";"Larva";504;2
"Unit";"Roach";"Larva";504;2
"Unit";"Roach";"Larva";504;2
"Unit";"Roach";"Larva";532;2
"Unit";"Roach";"Larva";532;2
"Unit";"Roach";"Larva";532;2
"Unit";"Roach";"Larva";532;2
"Unit";"Roach";"Larva";532;2
"Unit";"Roach";"Larva";532;2
"Unit";"Roach";"Larva";532;2
"Unit";"Roach";"Larva";532;2
"Unit";"Roach";"Larva";532;2
"Unit";"Roach";"Larva";532;2
"Building";"Hatchery";NA;501;0
"Building";"Extractor";NA;532;0
"Building";"Extractor";NA;532;0
"Unit";"Roach";"Larva";532;2
"Unit";"Roach";"Larva";532;2
"Upgrade";"ZergMissileWeaponsLevel3";"EvolutionChamber";476;0
"Unit";"Queen";"Hatchery";532;2
"Unit";"Roach";"Larva";556;2
"Unit";"Roach";"Larva";556;2
"Unit";"Roach";"Larva";556;2
"Unit";"Roach";"Larva";556;2
"Unit";"Roach";"Larva";556;2
"Unit";"Roach";"Larva";556;2
"Unit";"Roach";"Larva";556;2
"Unit";"Roach";"Larva";556;2
"Unit";"Roach";"Larva";556;2
"Unit";"Roach";"Larva";556;2
"Unit";"Roach";"Larva";556;2
"Unit";"Roach";"Larva";556;2
"Building";"Extractor";NA;556;0
"Unit";"Roach";"Larva";556;2
"Unit";"Roach";"Larva";556;2
"Unit";"Roach";"Larva";556;2
"Unit";"Roach";"Larva";556;2
"Unit";"Roach";"Larva";556;2
"Building";"CreepTumor";NA;582;0
"Unit";"Roach";"Larva";592;2
"Unit";"Roach";"Larva";592;2
"Unit";"Roach";"Larva";592;2
"Unit";"Roach";"Larva";592;2
"Unit";"Roach";"Larva";592;2
"Unit";"Roach";"Larva";592;2
"Unit";"Roach";"Larva";592;2
"Unit";"Roach";"Larva";592;2
"Unit";"Roach";"Larva";592;2
"Unit";"Roach";"Larva";592;2
"Unit";"Roach";"Larva";592;2
"Unit";"Roach";"Larva";592;2
"Building";"CreepTumorQueen";NA;592;0
"Unit";"Overlord";"Larva";592;0
"Building";"CreepTumorQueen";NA;592;0
"Building";"SpineCrawler";NA;592;0
"Building";"SpineCrawler";NA;592;0
"Unit";"Roach";"Larva";620;2
"Unit";"Roach";"Larva";620;2
"Unit";"Roach";"Larva";620;2
"Unit";"Roach";"Larva";620;2
"Unit";"Roach";"Larva";620;2
"Building";"SpineCrawler";NA;592;0
