"type";"unit_name";"on_building";"total_supply";"supply"
"Unit";"Overlord";"Larva";12;0
"Building";"Extractor";NA;18;0
"Building";"SpawningPool";NA;19;0
"Unit";"Overlord";"Larva";22;0
"Building";"Hatchery";NA;17;0
"Unit";"Zergling";"Larva";23;1
"Unit";"Zergling";"Larva";23;1
"Unit";"Queen";"Hatchery";23;2
"Unit";"Queen";"Hatchery";23;2
"Unit";"Overlord";"Larva";27;0
"Unit";"Overlord";"Larva";34;0
"Unit";"Queen";"Hatchery";31;2
"Unit";"Zergling";"Larva";34;1
"Unit";"Zergling";"Larva";34;1
"Building";"CreepTumorQueen";NA;36;0
"Unit";"Queen";"Hatchery";34;2
"Building";"CreepTumorQueen";NA;37;0
"Unit";"Overlord";"Larva";48;0
"Building";"EvolutionChamber";NA;48;0
"Building";"CreepTumor";NA;52;0
"Unit";"Zergling";"Larva";53;1
"Unit";"Zergling";"Larva";53;1
"Unit";"Zergling";"Larva";53;1
"Unit";"Zergling";"Larva";53;1
"Building";"Extractor";NA;53;0
"Unit";"Queen";"Hatchery";51;2
"Building";"SporeCrawler";NA;57;0
"Building";"CreepTumor";NA;61;0
"Building";"SporeCrawler";NA;57;0
"Unit";"Zergling";"Larva";63;1
"Unit";"Zergling";"Larva";63;1
"Unit";"Zergling";"Larva";63;1
"Unit";"Zergling";"Larva";63;1
"Unit";"Zergling";"Larva";63;1
"Unit";"Zergling";"Larva";63;1
"Building";"Hatchery";NA;50;0
"Unit";"Overlord";"Larva";65;0
"Building";"RoachWarren";NA;59;0
"Unit";"Overlord";"Larva";72;0
"Unit";"Roach";"Larva";72;2
"Unit";"Roach";"Larva";72;2
"Unit";"Queen";"Hatchery";66;2
"Unit";"Roach";"Larva";72;2
"Unit";"Roach";"Larva";72;2
"Unit";"Roach";"Larva";72;2
"Building";"EvolutionChamber";NA;72;0
"Unit";"Overlord";"Larva";72;0
"Unit";"Queen";"Hatchery";72;2
"Building";"Extractor";NA;83;0
"Unit";"Roach";"Larva";83;2
"Unit";"Roach";"Larva";83;2
"Building";"Extractor";NA;83;0
"Upgrade";"ZergGroundArmorsLevel1";"EvolutionChamber";66;0
"Unit";"Overlord";"Larva";104;0
"Building";"HydraliskDen";NA;100;0
"Unit";"Zergling";"Larva";106;1
"Unit";"Zergling";"Larva";106;1
"Building";"CreepTumorQueen";NA;109;0
"Unit";"Overlord";"Larva";106;0
"Unit";"Overlord";"Larva";108;0
"Building";"Extractor";NA;109;0
"Building";"BanelingNest";NA;104;0
"Building";"CreepTumorQueen";NA;114;0
"Unit";"Overlord";"Larva";114;0
"Building";"CreepTumorQueen";NA;115;0
"Building";"CreepTumor";NA;115;0
"Unit";"Overlord";"Larva";115;0
"Unit";"Overlord";"Larva";115;0
"Building";"CreepTumor";NA;123;0
"Building";"CreepTumor";NA;123;0
"Building";"CreepTumorQueen";NA;123;0
"Building";"Extractor";NA;123;0
"Unit";"Zergling";"Larva";123;1
"Unit";"Zergling";"Larva";123;1
"Unit";"Zergling";"Larva";123;1
"Unit";"Zergling";"Larva";123;1
"Unit";"Zergling";"Larva";123;1
"Unit";"Zergling";"Larva";123;1
"Unit";"Zergling";"Larva";123;1
"Unit";"Zergling";"Larva";123;1
"Unit";"Zergling";"Larva";123;1
"Unit";"Zergling";"Larva";123;1
"Unit";"Zergling";"Larva";123;1
"Unit";"Zergling";"Larva";123;1
"Building";"SporeCrawler";NA;123;0
"Upgrade";"ZergMissileWeaponsLevel1";"EvolutionChamber";106;0
"Building";"CreepTumor";NA;131;0
"Building";"CreepTumor";NA;131;0
"Building";"CreepTumor";NA;131;0
"Building";"CreepTumor";NA;131;0
"Unit";"Zergling";"Larva";123;1
"Unit";"Zergling";"Larva";123;1
"Unit";"Zergling";"Larva";125;1
"Unit";"Zergling";"Larva";125;1
"Unit";"Zergling";"Larva";127;1
"Unit";"Zergling";"Larva";127;1
"Unit";"Zergling";"Larva";129;1
"Unit";"Zergling";"Larva";129;1
"Unit";"Zergling";"Larva";131;1
"Unit";"Zergling";"Larva";131;1
"Building";"CreepTumorQueen";NA;135;0
"Unit";"Overlord";"Larva";131;0
"Unit";"Overlord";"Larva";131;0
"Unit";"Baneling";"Zergling";135;0
"Unit";"Baneling";"Zergling";135;0
"Unit";"Baneling";"Zergling";135;0
"Unit";"Baneling";"Zergling";135;0
"Building";"CreepTumorQueen";NA;143;0
"Building";"CreepTumorQueen";NA;143;0
"Building";"SpineCrawler";NA;123;0
"Unit";"Hydralisk";"Larva";135;2
"Unit";"Hydralisk";"Larva";135;2
"Unit";"Hydralisk";"Larva";135;2
"Upgrade";"ZergMeleeWeaponsLevel1";"EvolutionChamber";114;0
"Building";"CreepTumorQueen";NA;147;0
"Building";"CreepTumor";NA;147;0
"Unit";"Overlord";"Larva";145;0
"Building";"CreepTumor";NA;147;0
"Building";"CreepTumor";NA;147;0
"Building";"CreepTumor";NA;147;0
"Upgrade";"EvolveMuscularAugments";"HydraliskDen";123;0
"Building";"SpineCrawler";NA;145;0
"Unit";"Baneling";"Zergling";157;0
"Unit";"Baneling";"Zergling";157;0
"Unit";"Baneling";"Zergling";158;0
"Unit";"Zergling";"Larva";157;1
"Unit";"Zergling";"Larva";157;1
"Unit";"Zergling";"Larva";157;1
"Unit";"Zergling";"Larva";157;1
"Unit";"Zergling";"Larva";157;1
"Unit";"Zergling";"Larva";157;1
"Unit";"Overlord";"Larva";161;0
"Building";"SporeCrawler";NA;163;0
"Unit";"Zergling";"Larva";169;1
"Unit";"Zergling";"Larva";169;1
"Unit";"Zergling";"Larva";169;1
"Unit";"Zergling";"Larva";169;1
"Unit";"Zergling";"Larva";169;1
"Unit";"Zergling";"Larva";169;1
"Unit";"Zergling";"Larva";169;1
"Unit";"Zergling";"Larva";169;1
"Unit";"Baneling";"Zergling";169;0
"Unit";"Hydralisk";"Larva";169;2
"Unit";"Hydralisk";"Larva";169;2
"Unit";"Baneling";"Zergling";169;0
"Unit";"Baneling";"Zergling";169;0
"Unit";"Baneling";"Zergling";169;0
"Unit";"Baneling";"Zergling";169;0
"Unit";"Baneling";"Zergling";169;0
"Unit";"Baneling";"Zergling";169;0
"Unit";"Baneling";"Zergling";169;0
"Unit";"Baneling";"Zergling";169;0
"Building";"Hatchery";NA;143;0
"Unit";"Zergling";"Larva";169;1
"Unit";"Zergling";"Larva";169;1
"Unit";"Zergling";"Larva";169;1
"Unit";"Zergling";"Larva";169;1
"Unit";"Zergling";"Larva";169;1
"Unit";"Zergling";"Larva";169;1
"Unit";"Overlord";"Larva";169;0
"Building";"CreepTumor";NA;173;0
"Building";"CreepTumor";NA;175;0
"Building";"SpineCrawler";NA;163;0
"Unit";"Zergling";"Larva";181;1
"Unit";"Zergling";"Larva";181;1
"Unit";"Zergling";"Larva";183;1
"Unit";"Zergling";"Larva";183;1
"Unit";"Zergling";"Larva";185;1
"Unit";"Zergling";"Larva";185;1
"Unit";"Zergling";"Larva";187;1
"Unit";"Zergling";"Larva";187;1
"Unit";"Zergling";"Larva";187;1
"Unit";"Zergling";"Larva";187;1
"Unit";"Zergling";"Larva";187;1
"Unit";"Zergling";"Larva";187;1
"Unit";"Zergling";"Larva";187;1
"Unit";"Zergling";"Larva";187;1
"Building";"CreepTumorQueen";NA;187;0
"Unit";"Overlord";"Larva";187;0
"Unit";"Overlord";"Larva";187;0
"Unit";"Overlord";"Larva";187;0
"Unit";"Zergling";"Larva";187;1
"Unit";"Zergling";"Larva";187;1
"Unit";"Zergling";"Larva";187;1
"Unit";"Zergling";"Larva";187;1
"Unit";"Zergling";"Larva";187;1
"Unit";"Zergling";"Larva";187;1
"Upgrade";"EvolveGroovedSpines";"HydraliskDen";169;0
"Building";"CreepTumor";NA;201;0
"Unit";"Baneling";"Zergling";207;0
"Unit";"Baneling";"Zergling";207;0
"Unit";"Baneling";"Zergling";207;0
"Unit";"Baneling";"Zergling";207;0
"Unit";"Baneling";"Zergling";207;0
"Building";"CreepTumor";NA;207;0
"Building";"CreepTumor";NA;207;0
"Building";"InfestationPit";NA;201;0
"Unit";"Hydralisk";"Larva";216;2
"Unit";"Hydralisk";"Larva";216;2
"Building";"SpineCrawler";NA;201;0
"Building";"SpineCrawler";NA;201;0
"Building";"CreepTumor";NA;221;0
"Building";"CreepTumor";NA;221;0
"Building";"CreepTumor";NA;221;0
"Building";"CreepTumor";NA;225;0
"Building";"CreepTumor";NA;225;0
"Upgrade";"ZergMissileWeaponsLevel2";"EvolutionChamber";169;0
"Building";"CreepTumor";NA;225;0
"Building";"Extractor";NA;225;0
"Unit";"Baneling";"Zergling";225;0
"Unit";"Baneling";"Zergling";225;0
"Building";"EvolutionChamber";NA;225;0
"Unit";"Baneling";"Zergling";225;0
"Unit";"Baneling";"Zergling";225;0
"Unit";"Hydralisk";"Larva";225;2
"Unit";"Hydralisk";"Larva";225;2
"Unit";"Zergling";"Larva";225;1
"Unit";"Zergling";"Larva";225;1
"Building";"Extractor";NA;225;0
"Unit";"Zergling";"Larva";225;1
"Unit";"Zergling";"Larva";225;1
"Unit";"Zergling";"Larva";225;1
"Unit";"Zergling";"Larva";225;1
"Unit";"Zergling";"Larva";225;1
"Unit";"Zergling";"Larva";225;1
"Building";"EvolutionChamber";NA;225;0
"Building";"SporeCrawler";NA;225;0
"Unit";"Overlord";"Larva";225;0
"Unit";"Zergling";"Larva";225;1
"Unit";"Zergling";"Larva";225;1
"Unit";"Zergling";"Larva";225;1
"Unit";"Zergling";"Larva";225;1
"Building";"SpineCrawler";NA;225;0
"Unit";"Hydralisk";"Larva";225;2
"Unit";"Hydralisk";"Larva";225;2
"Unit";"Hydralisk";"Larva";225;2
"Unit";"Hydralisk";"Larva";225;2
"Building";"CreepTumor";NA;237;0
"Building";"CreepTumor";NA;237;0
"Building";"CreepTumor";NA;237;0
"Building";"CreepTumor";NA;259;0
"Unit";"Zergling";"Larva";252;1
"Unit";"Zergling";"Larva";252;1
"Building";"CreepTumorQueen";NA;265;0
"Building";"CreepTumorQueen";NA;265;0
"Building";"CreepTumorQueen";NA;265;0
"Building";"CreepTumorQueen";NA;265;0
"Building";"CreepTumorQueen";NA;265;0
"Unit";"Zergling";"Larva";265;1
"Unit";"Zergling";"Larva";265;1
"Unit";"Zergling";"Larva";265;1
"Unit";"Zergling";"Larva";265;1
"Unit";"Zergling";"Larva";265;1
"Unit";"Zergling";"Larva";265;1
"Unit";"Zergling";"Larva";265;1
"Unit";"Zergling";"Larva";265;1
"Unit";"Zergling";"Larva";265;1
"Unit";"Zergling";"Larva";265;1
"Unit";"Zergling";"Larva";265;1
"Unit";"Zergling";"Larva";265;1
"Unit";"Zergling";"Larva";265;1
"Unit";"Zergling";"Larva";265;1
"Unit";"Zergling";"Larva";265;1
"Unit";"Zergling";"Larva";265;1
"Unit";"Zergling";"Larva";265;1
"Unit";"Zergling";"Larva";265;1
"Unit";"Zergling";"Larva";265;1
"Unit";"Zergling";"Larva";265;1
"Unit";"Zergling";"Larva";265;1
"Unit";"Zergling";"Larva";265;1
"Unit";"Zergling";"Larva";265;1
"Unit";"Zergling";"Larva";265;1
"Unit";"Zergling";"Larva";267;1
"Unit";"Zergling";"Larva";267;1
"Building";"SpineCrawler";NA;265;0
"Upgrade";"ZergMeleeWeaponsLevel2";"EvolutionChamber";225;0
"Unit";"Zergling";"Larva";291;1
"Unit";"Zergling";"Larva";291;1
"Unit";"Zergling";"Larva";291;1
"Unit";"Zergling";"Larva";291;1
"Unit";"Zergling";"Larva";291;1
"Unit";"Zergling";"Larva";291;1
"Unit";"Zergling";"Larva";291;1
"Unit";"Zergling";"Larva";291;1
"Unit";"Zergling";"Larva";291;1
"Unit";"Zergling";"Larva";291;1
"Unit";"Zergling";"Larva";291;1
"Unit";"Zergling";"Larva";291;1
"Unit";"Zergling";"Larva";291;1
"Unit";"Zergling";"Larva";291;1
"Unit";"Zergling";"Larva";291;1
"Unit";"Zergling";"Larva";291;1
"Unit";"Zergling";"Larva";291;1
"Unit";"Zergling";"Larva";291;1
"Unit";"Overlord";"Larva";291;0
"Unit";"Overlord";"Larva";291;0
"Unit";"Zergling";"Larva";293;1
"Unit";"Zergling";"Larva";293;1
"Unit";"Zergling";"Larva";293;1
"Unit";"Zergling";"Larva";293;1
"Unit";"Zergling";"Larva";293;1
"Unit";"Zergling";"Larva";293;1
"Unit";"Overlord";"Larva";295;0
"Building";"CreepTumor";NA;311;0
"Unit";"Overlord";"Larva";295;0
"Unit";"Overlord";"Larva";295;0
"Building";"CreepTumor";NA;311;0
"Unit";"Overlord";"Larva";295;0
"Building";"CreepTumor";NA;311;0
"Building";"CreepTumor";NA;317;0
"Building";"CreepTumor";NA;317;0
"Unit";"Hydralisk";"Larva";311;2
"Unit";"Hydralisk";"Larva";311;2
"Unit";"Hydralisk";"Larva";311;2
"Unit";"Hydralisk";"Larva";311;2
"Unit";"Hydralisk";"Larva";311;2
"Unit";"Hydralisk";"Larva";311;2
"Unit";"Hydralisk";"Larva";311;2
"Building";"Hatchery";NA;267;0
"Building";"CreepTumor";NA;331;0
"Building";"CreepTumor";NA;331;0
"Building";"CreepTumor";NA;331;0
"Building";"CreepTumor";NA;331;0
"Building";"CreepTumor";NA;331;0
"Building";"CreepTumor";NA;331;0
"Unit";"Viper";"Larva";331;3
"Unit";"Viper";"Larva";331;3
"Unit";"Viper";"Larva";331;3
"Unit";"Viper";"Larva";331;3
"Unit";"Hydralisk";"Larva";331;2
"Unit";"Hydralisk";"Larva";331;2
"Building";"CreepTumor";NA;331;0
"Building";"CreepTumor";NA;331;0
"Unit";"Zergling";"Larva";331;1
"Unit";"Zergling";"Larva";331;1
"Unit";"Zergling";"Larva";331;1
"Unit";"Zergling";"Larva";331;1
"Unit";"Zergling";"Larva";331;1
"Unit";"Zergling";"Larva";331;1
"Unit";"Zergling";"Larva";331;1
"Unit";"Zergling";"Larva";331;1
"Building";"CreepTumor";NA;331;0
"Building";"CreepTumor";NA;331;0
"Unit";"Zergling";"Larva";331;1
"Unit";"Zergling";"Larva";331;1
"Building";"CreepTumor";NA;331;0
"Building";"CreepTumor";NA;331;0
"Building";"EvolutionChamber";NA;331;0
"Building";"UltraliskCavern";NA;323;0
"Building";"EvolutionChamber";NA;331;0
"Building";"EvolutionChamber";NA;331;0
"Building";"Hatchery";NA;317;0
"Unit";"Zergling";"Larva";357;1
"Unit";"Zergling";"Larva";357;1
"Unit";"Zergling";"Larva";357;1
"Unit";"Zergling";"Larva";357;1
"Unit";"Zergling";"Larva";357;1
"Unit";"Zergling";"Larva";357;1
"Unit";"Zergling";"Larva";357;1
"Unit";"Zergling";"Larva";357;1
"Unit";"Zergling";"Larva";357;1
"Unit";"Zergling";"Larva";357;1
"Unit";"Zergling";"Larva";357;1
"Unit";"Zergling";"Larva";357;1
"Unit";"Zergling";"Larva";357;1
"Unit";"Zergling";"Larva";357;1
"Unit";"Zergling";"Larva";357;1
"Unit";"Zergling";"Larva";357;1
"Unit";"Zergling";"Larva";357;1
"Unit";"Zergling";"Larva";357;1
"Unit";"Zergling";"Larva";357;1
"Unit";"Zergling";"Larva";357;1
"Unit";"Zergling";"Larva";357;1
"Unit";"Zergling";"Larva";357;1
"Unit";"Zergling";"Larva";357;1
"Unit";"Zergling";"Larva";357;1
"Unit";"Zergling";"Larva";357;1
"Unit";"Zergling";"Larva";357;1
"Unit";"Zergling";"Larva";357;1
"Unit";"Zergling";"Larva";357;1
"Unit";"Zergling";"Larva";357;1
"Unit";"Zergling";"Larva";357;1
"Unit";"Zergling";"Larva";357;1
"Unit";"Zergling";"Larva";357;1
"Unit";"Zergling";"Larva";357;1
"Unit";"Zergling";"Larva";357;1
"Unit";"Ultralisk";"Larva";357;6
"Unit";"Ultralisk";"Larva";357;6
"Unit";"Zergling";"Larva";407;1
"Unit";"Zergling";"Larva";407;1
"Unit";"Zergling";"Larva";407;1
"Unit";"Zergling";"Larva";407;1
"Unit";"Zergling";"Larva";407;1
"Unit";"Zergling";"Larva";407;1
"Unit";"Zergling";"Larva";407;1
"Unit";"Zergling";"Larva";407;1
"Unit";"Zergling";"Larva";407;1
"Unit";"Zergling";"Larva";407;1
"Unit";"Zergling";"Larva";407;1
"Unit";"Zergling";"Larva";407;1
"Unit";"Zergling";"Larva";407;1
"Unit";"Zergling";"Larva";407;1
"Unit";"Zergling";"Larva";407;1
"Unit";"Zergling";"Larva";407;1
"Unit";"Zergling";"Larva";407;1
"Unit";"Zergling";"Larva";407;1
"Unit";"Zergling";"Larva";407;1
"Unit";"Zergling";"Larva";407;1
"Unit";"Zergling";"Larva";407;1
"Unit";"Zergling";"Larva";407;1
"Unit";"Zergling";"Larva";407;1
"Unit";"Zergling";"Larva";407;1
"Building";"CreepTumor";NA;407;0
"Building";"CreepTumor";NA;407;0
"Building";"CreepTumor";NA;407;0
"Building";"CreepTumor";NA;407;0
"Building";"CreepTumor";NA;407;0
"Building";"CreepTumor";NA;407;0
"Building";"SporeCrawler";NA;407;0
"Upgrade";"ChitinousPlating";"UltraliskCavern";369;0
"Building";"SporeCrawler";NA;407;0
"Building";"Extractor";NA;431;0
"Upgrade";"ZergMeleeWeaponsLevel3";"EvolutionChamber";331;0
"Upgrade";"ZergMissileWeaponsLevel3";"EvolutionChamber";331;0
"Unit";"Hydralisk";"Larva";431;2
"Unit";"Hydralisk";"Larva";431;2
"Unit";"Zergling";"Larva";431;1
"Unit";"Zergling";"Larva";431;1
"Unit";"Zergling";"Larva";431;1
"Unit";"Zergling";"Larva";431;1
"Unit";"Zergling";"Larva";431;1
"Unit";"Zergling";"Larva";431;1
"Building";"CreepTumorQueen";NA;431;0
"Unit";"Ultralisk";"Larva";431;6
"Unit";"Ultralisk";"Larva";431;6
"Unit";"Zergling";"Larva";431;1
"Unit";"Zergling";"Larva";431;1
"Building";"CreepTumor";NA;439;0
"Unit";"Zergling";"Larva";431;1
"Unit";"Zergling";"Larva";431;1
"Unit";"Zergling";"Larva";431;1
"Unit";"Zergling";"Larva";431;1
"Building";"CreepTumor";NA;441;0
"Building";"CreepTumor";NA;441;0
"Building";"CreepTumorQueen";NA;441;0
"Building";"CreepTumor";NA;441;0
"Unit";"Zergling";"Larva";431;1
"Unit";"Zergling";"Larva";431;1
"Unit";"Zergling";"Larva";431;1
"Unit";"Zergling";"Larva";431;1
"Unit";"Zergling";"Larva";433;1
"Unit";"Zergling";"Larva";433;1
"Unit";"Zergling";"Larva";441;1
"Unit";"Zergling";"Larva";441;1
"Unit";"Zergling";"Larva";441;1
"Unit";"Zergling";"Larva";441;1
"Unit";"Zergling";"Larva";441;1
"Unit";"Zergling";"Larva";441;1
"Unit";"Zergling";"Larva";441;1
"Unit";"Zergling";"Larva";441;1
"Unit";"Zergling";"Larva";441;1
"Unit";"Zergling";"Larva";441;1
"Unit";"Zergling";"Larva";441;1
"Unit";"Zergling";"Larva";441;1
"Building";"CreepTumor";NA;463;0
"Building";"CreepTumor";NA;477;0
"Building";"CreepTumor";NA;477;0
"Building";"CreepTumor";NA;477;0
"Building";"Spire";NA;431;0
"Building";"Spire";NA;431;0
"Building";"Hatchery";NA;431;0
"Building";"Extractor";NA;477;0
"Building";"Extractor";NA;477;0
"Building";"CreepTumor";NA;485;0
"Building";"CreepTumor";NA;485;0
"Unit";"Corruptor";"Larva";477;2
"Unit";"Corruptor";"Larva";477;2
"Unit";"Corruptor";"Larva";477;2
"Unit";"Corruptor";"Larva";477;2
"Unit";"Corruptor";"Larva";477;2
"Unit";"Viper";"Larva";477;3
"Unit";"Viper";"Larva";477;3
"Unit";"Viper";"Larva";477;3
"Building";"SpineCrawler";NA;485;0
"Building";"CreepTumor";NA;510;0
"Building";"CreepTumor";NA;510;0
"Building";"CreepTumor";NA;510;0
"Building";"CreepTumor";NA;510;0
"Building";"CreepTumor";NA;510;0
"Building";"CreepTumor";NA;512;0
"Building";"SporeCrawler";NA;510;0
"Building";"Spire";NA;477;0
"Building";"CreepTumor";NA;514;0
"Building";"CreepTumor";NA;514;0
"Unit";"Overlord";"Larva";514;0
"Building";"SpineCrawler";NA;510;0
"Building";"SpineCrawler";NA;510;0
"Unit";"Corruptor";"Larva";514;2
"Unit";"Corruptor";"Larva";514;2
"Unit";"Corruptor";"Larva";514;2
"Unit";"Corruptor";"Larva";514;2
"Unit";"Corruptor";"Larva";514;2
"Unit";"Zergling";"Larva";514;1
"Unit";"Zergling";"Larva";514;1
"Unit";"Zergling";"Larva";514;1
"Unit";"Zergling";"Larva";514;1
"Unit";"Zergling";"Larva";514;1
"Unit";"Zergling";"Larva";514;1
"Unit";"Zergling";"Larva";514;1
"Unit";"Zergling";"Larva";514;1
"Unit";"Hydralisk";"Larva";514;2
"Unit";"Zergling";"Larva";514;1
"Unit";"Zergling";"Larva";514;1
"Unit";"Hydralisk";"Larva";514;2
"Unit";"Hydralisk";"Larva";514;2
"Unit";"Hydralisk";"Larva";514;2
"Unit";"Hydralisk";"Larva";514;2
"Unit";"Zergling";"Larva";514;1
"Unit";"Zergling";"Larva";514;1
"Unit";"Zergling";"Larva";514;1
"Unit";"Zergling";"Larva";514;1
"Unit";"Zergling";"Larva";514;1
"Unit";"Zergling";"Larva";514;1
"Unit";"Zergling";"Larva";514;1
"Unit";"Zergling";"Larva";514;1
"Unit";"Zergling";"Larva";514;1
"Unit";"Zergling";"Larva";514;1
"Unit";"Zergling";"Larva";514;1
"Unit";"Zergling";"Larva";514;1
"Unit";"Zergling";"Larva";514;1
"Unit";"Zergling";"Larva";514;1
"Unit";"Zergling";"Larva";514;1
"Unit";"Zergling";"Larva";514;1
"Unit";"Zergling";"Larva";514;1
"Unit";"Zergling";"Larva";514;1
"Upgrade";"ZergGroundArmorsLevel2";"EvolutionChamber";485;0
"Unit";"Zergling";"Larva";562;1
"Unit";"Zergling";"Larva";562;1
"Unit";"Zergling";"Larva";562;1
"Unit";"Zergling";"Larva";562;1
"Unit";"Zergling";"Larva";562;1
"Unit";"Zergling";"Larva";562;1
"Unit";"Zergling";"Larva";562;1
"Unit";"Zergling";"Larva";562;1
"Unit";"Zergling";"Larva";570;1
"Unit";"Zergling";"Larva";570;1
"Unit";"Zergling";"Larva";570;1
"Unit";"Zergling";"Larva";570;1
"Unit";"Zergling";"Larva";570;1
"Unit";"Zergling";"Larva";570;1
"Unit";"Zergling";"Larva";570;1
"Unit";"Zergling";"Larva";570;1
"Unit";"Zergling";"Larva";570;1
"Unit";"Zergling";"Larva";570;1
"Unit";"Zergling";"Larva";570;1
"Unit";"Zergling";"Larva";570;1
"Unit";"Zergling";"Larva";570;1
"Unit";"Zergling";"Larva";570;1
"Unit";"Zergling";"Larva";570;1
"Unit";"Zergling";"Larva";570;1
"Unit";"Zergling";"Larva";570;1
"Unit";"Zergling";"Larva";570;1
"Unit";"Zergling";"Larva";570;1
"Unit";"Zergling";"Larva";570;1
"Unit";"Zergling";"Larva";570;1
"Unit";"Zergling";"Larva";570;1
"Unit";"Zergling";"Larva";570;1
"Unit";"Zergling";"Larva";570;1
"Unit";"Zergling";"Larva";570;1
"Unit";"Zergling";"Larva";570;1
"Unit";"Zergling";"Larva";570;1
"Unit";"Zergling";"Larva";570;1
"Unit";"Zergling";"Larva";570;1
"Unit";"Zergling";"Larva";570;1
"Unit";"Zergling";"Larva";570;1
"Unit";"Zergling";"Larva";570;1
"Unit";"Zergling";"Larva";570;1
"Unit";"Zergling";"Larva";570;1
"Unit";"Zergling";"Larva";570;1
"Unit";"Zergling";"Larva";570;1
"Unit";"Zergling";"Larva";570;1
"Unit";"Zergling";"Larva";570;1
"Unit";"Zergling";"Larva";570;1
"Unit";"Zergling";"Larva";570;1
"Unit";"Zergling";"Larva";570;1
"Unit";"Zergling";"Larva";570;1
"Unit";"Zergling";"Larva";570;1
"Unit";"Zergling";"Larva";570;1
"Unit";"Zergling";"Larva";570;1
"Unit";"Zergling";"Larva";570;1
"Unit";"Zergling";"Larva";570;1
"Unit";"Zergling";"Larva";570;1
"Unit";"Zergling";"Larva";570;1
"Unit";"Zergling";"Larva";570;1
"Unit";"Zergling";"Larva";570;1
"Unit";"Zergling";"Larva";570;1
"Unit";"Zergling";"Larva";570;1
"Unit";"Zergling";"Larva";570;1
"Unit";"Zergling";"Larva";570;1
"Unit";"Zergling";"Larva";570;1
"Unit";"Zergling";"Larva";570;1
"Unit";"Zergling";"Larva";570;1
"Unit";"Zergling";"Larva";570;1
"Unit";"Zergling";"Larva";570;1
"Unit";"Zergling";"Larva";570;1
"Unit";"Zergling";"Larva";570;1
"Unit";"Zergling";"Larva";570;1
"Unit";"Zergling";"Larva";570;1
"Unit";"Zergling";"Larva";570;1
"Unit";"Zergling";"Larva";570;1
"Unit";"Zergling";"Larva";570;1
"Unit";"Zergling";"Larva";570;1
"Unit";"Zergling";"Larva";570;1
"Unit";"Zergling";"Larva";570;1
"Unit";"Zergling";"Larva";570;1
"Unit";"Zergling";"Larva";570;1
"Unit";"Zergling";"Larva";570;1
"Unit";"Zergling";"Larva";570;1
"Unit";"Zergling";"Larva";570;1
"Unit";"Zergling";"Larva";570;1
"Unit";"Zergling";"Larva";570;1
"Unit";"Zergling";"Larva";570;1
"Unit";"Zergling";"Larva";570;1
"Unit";"Zergling";"Larva";570;1
"Unit";"Zergling";"Larva";604;1
"Unit";"Zergling";"Larva";604;1
"Unit";"Zergling";"Larva";606;1
"Unit";"Zergling";"Larva";606;1
"Unit";"Zergling";"Larva";612;1
"Unit";"Zergling";"Larva";612;1
"Unit";"Zergling";"Larva";620;1
"Unit";"Zergling";"Larva";620;1
"Unit";"Zergling";"Larva";628;1
"Unit";"Zergling";"Larva";628;1
"Unit";"Zergling";"Larva";648;1
"Unit";"Zergling";"Larva";648;1
"Unit";"Zergling";"Larva";648;1
"Unit";"Zergling";"Larva";648;1
"Unit";"Zergling";"Larva";648;1
"Unit";"Zergling";"Larva";648;1
"Unit";"Zergling";"Larva";648;1
"Unit";"Zergling";"Larva";648;1
"Unit";"Zergling";"Larva";648;1
"Unit";"Zergling";"Larva";648;1
"Unit";"Zergling";"Larva";648;1
"Unit";"Zergling";"Larva";648;1
"Building";"CreepTumor";NA;660;0
"Unit";"Hydralisk";"Larva";670;2
"Building";"CreepTumorQueen";NA;672;0
"Building";"CreepTumorQueen";NA;672;0
"Building";"CreepTumorQueen";NA;672;0
"Unit";"Corruptor";"Larva";660;2
"Unit";"Corruptor";"Larva";660;2
"Unit";"Corruptor";"Larva";660;2
"Unit";"Corruptor";"Larva";662;2
"Unit";"Hydralisk";"Larva";672;2
"Unit";"Hydralisk";"Larva";672;2
"Unit";"Hydralisk";"Larva";672;2
"Unit";"Hydralisk";"Larva";672;2
"Unit";"Baneling";"Zergling";686;0
"Unit";"Hydralisk";"Larva";672;2
"Unit";"Baneling";"Zergling";686;0
"Unit";"Baneling";"Zergling";686;0
"Unit";"Baneling";"Zergling";686;0
"Unit";"Baneling";"Zergling";686;0
"Unit";"Baneling";"Zergling";686;0
"Unit";"Zergling";"Larva";686;1
"Unit";"Zergling";"Larva";686;1
"Unit";"Zergling";"Larva";686;1
"Unit";"Zergling";"Larva";686;1
"Unit";"Zergling";"Larva";686;1
"Unit";"Zergling";"Larva";686;1
"Unit";"Zergling";"Larva";686;1
"Unit";"Zergling";"Larva";686;1
"Unit";"Zergling";"Larva";686;1
"Unit";"Zergling";"Larva";686;1
"Unit";"Hydralisk";"Larva";686;2
"Unit";"Hydralisk";"Larva";686;2
"Unit";"Hydralisk";"Larva";686;2
"Unit";"Hydralisk";"Larva";686;2
"Unit";"Hydralisk";"Larva";686;2
"Unit";"Hydralisk";"Larva";686;2
"Unit";"Hydralisk";"Larva";692;2
"Unit";"Hydralisk";"Larva";692;2
"Unit";"Hydralisk";"Larva";692;2
"Unit";"Hydralisk";"Larva";698;2
"Unit";"Hydralisk";"Larva";698;2
"Unit";"Hydralisk";"Larva";698;2
"Unit";"Hydralisk";"Larva";702;2
"Unit";"Hydralisk";"Larva";716;2
