"type";"unit_name";"on_building";"total_supply";"supply"
"Unit";"Overlord";"Larva";13;0
"Building";"Extractor";NA;18;0
"Unit";"Overlord";"Larva";21;0
"Building";"SpawningPool";NA;19;0
"Building";"Hatchery";NA;17;0
"Unit";"Zergling";"Larva";23;1
"Unit";"Zergling";"Larva";23;1
"Unit";"Zergling";"Larva";23;1
"Unit";"Zergling";"Larva";23;1
"Unit";"Queen";"Hatchery";22;2
"Unit";"Queen";"Hatchery";23;2
"Unit";"Overlord";"Larva";33;0
"Unit";"Overlord";"Larva";37;0
"Building";"Hatchery";NA;29;0
"Unit";"Overlord";"Larva";47;0
"Building";"Extractor";NA;47;0
"Unit";"Queen";"Hatchery";39;2
"Unit";"Queen";"Hatchery";39;2
"Building";"CreepTumorQueen";NA;53;0
"Unit";"Zergling";"Larva";49;1
"Unit";"Zergling";"Larva";49;1
"Unit";"Zergling";"Larva";49;1
"Unit";"Zergling";"Larva";49;1
"Unit";"Zergling";"Larva";49;1
"Unit";"Zergling";"Larva";49;1
"Unit";"Zergling";"Larva";49;1
"Unit";"Zergling";"Larva";49;1
"Unit";"Zergling";"Larva";51;1
"Unit";"Zergling";"Larva";51;1
"Unit";"Zergling";"Larva";51;1
"Unit";"Zergling";"Larva";51;1
"Building";"CreepTumorQueen";NA;53;0
"Unit";"Zergling";"Larva";51;1
"Unit";"Zergling";"Larva";51;1
"Unit";"Zergling";"Larva";51;1
"Unit";"Zergling";"Larva";51;1
"Unit";"Zergling";"Larva";53;1
"Unit";"Zergling";"Larva";53;1
"Unit";"Overlord";"Larva";53;0
"Unit";"Queen";"Hatchery";49;2
"Building";"BanelingNest";NA;49;0
"Unit";"Overlord";"Larva";72;0
"Unit";"Overlord";"Larva";73;0
"Unit";"Overlord";"Larva";77;0
"Building";"CreepTumorQueen";NA;83;0
"Building";"CreepTumor";NA;80;0
"Building";"CreepTumorQueen";NA;83;0
"Unit";"Zergling";"Larva";83;1
"Unit";"Zergling";"Larva";83;1
"Building";"EvolutionChamber";NA;80;0
"Unit";"Zergling";"Larva";83;1
"Unit";"Zergling";"Larva";83;1
"Unit";"Zergling";"Larva";83;1
"Unit";"Zergling";"Larva";83;1
"Unit";"Zergling";"Larva";83;1
"Unit";"Zergling";"Larva";83;1
"Unit";"Zergling";"Larva";83;1
"Unit";"Zergling";"Larva";83;1
"Building";"EvolutionChamber";NA;83;0
"Building";"Extractor";NA;98;0
"Building";"Extractor";NA;98;0
"Building";"CreepTumor";NA;107;0
"Building";"CreepTumor";NA;107;0
"Building";"CreepTumorQueen";NA;107;0
"Building";"CreepTumorQueen";NA;107;0
"Building";"SporeCrawler";NA;98;0
"Building";"CreepTumor";NA;107;0
"Building";"SporeCrawler";NA;107;0
"Building";"SporeCrawler";NA;107;0
"Building";"Extractor";NA;107;0
"Building";"Extractor";NA;107;0
"Unit";"Overlord";"Larva";112;0
"Unit";"Overlord";"Larva";114;0
"Building";"Spire";NA;98;0
"Unit";"Overlord";"Larva";124;0
"Building";"CreepTumor";NA;124;0
"Unit";"Overlord";"Larva";124;0
"Unit";"Overlord";"Larva";124;0
"Building";"CreepTumor";NA;124;0
"Building";"CreepTumor";NA;124;0
"Building";"CreepTumor";NA;124;0
"Building";"CreepTumor";NA;124;0
"Building";"CreepTumorQueen";NA;124;0
"Building";"CreepTumorQueen";NA;124;0
"Unit";"Mutalisk";"Larva";124;2
"Unit";"Mutalisk";"Larva";124;2
"Unit";"Mutalisk";"Larva";124;2
"Unit";"Mutalisk";"Larva";124;2
"Unit";"Mutalisk";"Larva";124;2
"Unit";"Mutalisk";"Larva";124;2
"Unit";"Mutalisk";"Larva";124;2
"Unit";"Mutalisk";"Larva";124;2
"Unit";"Mutalisk";"Larva";124;2
"Unit";"Overlord";"Larva";124;0
"Unit";"Overlord";"Larva";124;0
"Building";"CreepTumor";NA;124;0
"Building";"CreepTumor";NA;142;0
"Building";"CreepTumor";NA;142;0
"Building";"CreepTumorQueen";NA;142;0
"Building";"CreepTumorQueen";NA;142;0
"Unit";"Zergling";"Larva";142;1
"Unit";"Zergling";"Larva";142;1
"Unit";"Zergling";"Larva";142;1
"Unit";"Zergling";"Larva";142;1
"Unit";"Zergling";"Larva";142;1
"Unit";"Zergling";"Larva";142;1
"Unit";"Zergling";"Larva";142;1
"Unit";"Zergling";"Larva";142;1
"Unit";"Zergling";"Larva";142;1
"Unit";"Zergling";"Larva";142;1
"Unit";"Zergling";"Larva";142;1
"Unit";"Zergling";"Larva";142;1
"Unit";"Zergling";"Larva";142;1
"Unit";"Zergling";"Larva";142;1
"Unit";"Zergling";"Larva";142;1
"Unit";"Zergling";"Larva";142;1
"Unit";"Zergling";"Larva";142;1
"Unit";"Zergling";"Larva";142;1
"Unit";"Zergling";"Larva";142;1
"Unit";"Zergling";"Larva";142;1
"Unit";"Zergling";"Larva";142;1
"Unit";"Zergling";"Larva";142;1
"Unit";"Zergling";"Larva";142;1
"Unit";"Zergling";"Larva";142;1
"Building";"InfestationPit";NA;142;0
"Building";"CreepTumor";NA;166;0
"Building";"CreepTumor";NA;166;0
"Building";"CreepTumor";NA;166;0
"Building";"CreepTumor";NA;166;0
"Building";"Hatchery";NA;142;0
"Building";"HydraliskDen";NA;166;0
"Building";"Hatchery";NA;142;0
"Upgrade";"ZergMeleeWeaponsLevel1";"EvolutionChamber";142;0
"Upgrade";"ZergGroundArmorsLevel1";"EvolutionChamber";142;0
"Unit";"Hydralisk";"Larva";166;2
"Unit";"Hydralisk";"Larva";166;2
"Unit";"Hydralisk";"Larva";166;2
"Unit";"Hydralisk";"Larva";166;2
"Unit";"Hydralisk";"Larva";166;2
"Unit";"Hydralisk";"Larva";166;2
"Unit";"Hydralisk";"Larva";166;2
"Unit";"Hydralisk";"Larva";166;2
"Unit";"Hydralisk";"Larva";166;2
"Unit";"Hydralisk";"Larva";166;2
"Unit";"Hydralisk";"Larva";166;2
"Unit";"Hydralisk";"Larva";166;2
"Unit";"Hydralisk";"Larva";166;2
"Unit";"Hydralisk";"Larva";166;2
"Unit";"Hydralisk";"Larva";166;2
"Unit";"Overlord";"Larva";171;0
"Unit";"Overlord";"Larva";171;0
"Unit";"Overlord";"Larva";171;0
"Unit";"Overlord";"Larva";171;0
"Unit";"Overlord";"Larva";171;0
"Unit";"Overlord";"Larva";171;0
"Unit";"Overlord";"Larva";173;0
"Unit";"Overlord";"Larva";173;0
"Unit";"Overlord";"Larva";179;0
"Unit";"Overlord";"Larva";201;0
"Building";"Extractor";NA;201;0
"Building";"Extractor";NA;201;0
"Building";"CreepTumor";NA;205;0
"Building";"CreepTumor";NA;205;0
"Building";"CreepTumor";NA;205;0
"Building";"CreepTumor";NA;205;0
"Unit";"Zergling";"Larva";205;1
"Unit";"Zergling";"Larva";205;1
"Unit";"Zergling";"Larva";205;1
"Unit";"Zergling";"Larva";205;1
"Unit";"Zergling";"Larva";205;1
"Unit";"Zergling";"Larva";205;1
"Unit";"Zergling";"Larva";205;1
"Unit";"Zergling";"Larva";205;1
"Unit";"Zergling";"Larva";205;1
"Unit";"Zergling";"Larva";205;1
"Unit";"Zergling";"Larva";205;1
"Unit";"Zergling";"Larva";205;1
"Unit";"Zergling";"Larva";205;1
"Unit";"Zergling";"Larva";205;1
"Unit";"Zergling";"Larva";205;1
"Unit";"Zergling";"Larva";205;1
"Unit";"Zergling";"Larva";205;1
"Unit";"Zergling";"Larva";205;1
"Unit";"Hydralisk";"Larva";205;2
"Unit";"Hydralisk";"Larva";205;2
"Unit";"Hydralisk";"Larva";205;2
"Unit";"Hydralisk";"Larva";205;2
"Unit";"Hydralisk";"Larva";205;2
"Unit";"Hydralisk";"Larva";205;2
"Unit";"Hydralisk";"Larva";205;2
"Unit";"Hydralisk";"Larva";205;2
"Unit";"Hydralisk";"Larva";205;2
"Unit";"Hydralisk";"Larva";205;2
"Unit";"Hydralisk";"Larva";205;2
"Building";"HydraliskDen";NA;245;0
"Building";"SporeCrawler";NA;245;0
"Building";"SporeCrawler";NA;257;0
"Building";"SpineCrawler";NA;245;0
"Building";"SpineCrawler";NA;245;0
"Building";"SpineCrawler";NA;246;0
"Building";"SpineCrawler";NA;249;0
"Unit";"Baneling";"Zergling";264;0
"Unit";"Baneling";"Zergling";264;0
"Unit";"Baneling";"Zergling";264;0
"Unit";"Baneling";"Zergling";264;0
"Unit";"Baneling";"Zergling";264;0
"Unit";"Baneling";"Zergling";264;0
"Unit";"Baneling";"Zergling";264;0
"Unit";"Baneling";"Zergling";264;0
"Unit";"Baneling";"Zergling";264;0
"Unit";"Baneling";"Zergling";264;0
"Unit";"Baneling";"Zergling";264;0
"Unit";"Baneling";"Zergling";264;0
"Unit";"Baneling";"Zergling";264;0
"Unit";"Baneling";"Zergling";264;0
"Unit";"Baneling";"Zergling";264;0
"Unit";"Baneling";"Zergling";264;0
"Unit";"Baneling";"Zergling";264;0
"Unit";"Baneling";"Zergling";264;0
"Unit";"Baneling";"Zergling";264;0
"Unit";"Baneling";"Zergling";264;0
"Unit";"Baneling";"Zergling";264;0
"Unit";"Baneling";"Zergling";264;0
"Unit";"Baneling";"Zergling";264;0
"Unit";"Baneling";"Zergling";264;0
"Unit";"Baneling";"Zergling";264;0
"Unit";"Baneling";"Zergling";264;0
"Unit";"Baneling";"Zergling";264;0
"Building";"SpineCrawler";NA;257;0
"Building";"SpineCrawler";NA;264;0
"Building";"SpineCrawler";NA;264;0
"Building";"SpineCrawler";NA;264;0
"Unit";"Zergling";"Larva";269;1
"Unit";"Zergling";"Larva";269;1
"Unit";"Zergling";"Larva";269;1
"Unit";"Zergling";"Larva";269;1
"Unit";"Zergling";"Larva";269;1
"Unit";"Zergling";"Larva";269;1
"Unit";"Zergling";"Larva";269;1
"Unit";"Zergling";"Larva";269;1
"Unit";"Zergling";"Larva";269;1
"Unit";"Zergling";"Larva";269;1
"Unit";"Zergling";"Larva";269;1
"Unit";"Zergling";"Larva";269;1
"Unit";"Zergling";"Larva";269;1
"Unit";"Zergling";"Larva";269;1
"Unit";"Zergling";"Larva";269;1
"Unit";"Zergling";"Larva";269;1
"Unit";"Zergling";"Larva";269;1
"Unit";"Zergling";"Larva";269;1
"Unit";"Zergling";"Larva";269;1
"Unit";"Zergling";"Larva";269;1
"Unit";"Zergling";"Larva";269;1
"Unit";"Zergling";"Larva";269;1
"Unit";"Zergling";"Larva";269;1
"Unit";"Zergling";"Larva";269;1
"Unit";"Zergling";"Larva";269;1
"Unit";"Zergling";"Larva";269;1
"Unit";"Zergling";"Larva";269;1
"Unit";"Zergling";"Larva";269;1
"Unit";"Zergling";"Larva";269;1
"Unit";"Zergling";"Larva";269;1
"Unit";"Zergling";"Larva";269;1
"Unit";"Zergling";"Larva";269;1
"Unit";"Zergling";"Larva";269;1
"Unit";"Zergling";"Larva";269;1
"Unit";"Zergling";"Larva";269;1
"Unit";"Zergling";"Larva";269;1
"Unit";"Zergling";"Larva";269;1
"Unit";"Zergling";"Larva";269;1
"Unit";"Zergling";"Larva";269;1
"Unit";"Zergling";"Larva";269;1
"Unit";"Zergling";"Larva";269;1
"Unit";"Zergling";"Larva";269;1
"Unit";"Zergling";"Larva";269;1
"Unit";"Zergling";"Larva";269;1
"Unit";"Zergling";"Larva";269;1
"Unit";"Zergling";"Larva";269;1
"Unit";"Zergling";"Larva";269;1
"Unit";"Zergling";"Larva";269;1
"Upgrade";"ZergMeleeWeaponsLevel2";"EvolutionChamber";245;0
"Upgrade";"ZergGroundArmorsLevel2";"EvolutionChamber";245;0
"Building";"Hatchery";NA;257;0
"Building";"CreepTumor";NA;269;0
"Building";"CreepTumor";NA;269;0
"Building";"CreepTumor";NA;317;0
"Building";"CreepTumor";NA;317;0
"Unit";"Queen";"Hatchery";269;2
"Building";"UltraliskCavern";NA;269;0
"Unit";"Baneling";"Zergling";317;0
"Unit";"Baneling";"Zergling";317;0
"Unit";"Baneling";"Zergling";317;0
"Unit";"Baneling";"Zergling";317;0
"Unit";"Baneling";"Zergling";317;0
"Unit";"Baneling";"Zergling";317;0
"Unit";"Baneling";"Zergling";317;0
"Unit";"Baneling";"Zergling";317;0
"Unit";"Baneling";"Zergling";317;0
"Unit";"Baneling";"Zergling";317;0
"Unit";"Baneling";"Zergling";317;0
"Unit";"Baneling";"Zergling";317;0
"Unit";"Baneling";"Zergling";317;0
"Unit";"Baneling";"Zergling";317;0
"Unit";"Baneling";"Zergling";317;0
"Unit";"Baneling";"Zergling";317;0
"Unit";"Baneling";"Zergling";317;0
"Unit";"Baneling";"Zergling";317;0
"Unit";"Baneling";"Zergling";317;0
"Unit";"Baneling";"Zergling";317;0
"Unit";"Baneling";"Zergling";317;0
"Unit";"Zergling";"Larva";319;1
"Unit";"Zergling";"Larva";319;1
"Unit";"Zergling";"Larva";319;1
"Unit";"Zergling";"Larva";319;1
"Unit";"Zergling";"Larva";319;1
"Unit";"Zergling";"Larva";319;1
"Unit";"Zergling";"Larva";319;1
"Unit";"Zergling";"Larva";319;1
"Unit";"Zergling";"Larva";319;1
"Unit";"Zergling";"Larva";319;1
"Unit";"Ultralisk";"Larva";319;6
"Unit";"Ultralisk";"Larva";319;6
"Unit";"Ultralisk";"Larva";319;6
"Unit";"Zergling";"Larva";329;1
"Unit";"Zergling";"Larva";329;1
"Unit";"Zergling";"Larva";329;1
"Unit";"Zergling";"Larva";329;1
"Unit";"Zergling";"Larva";329;1
"Unit";"Zergling";"Larva";329;1
"Unit";"Zergling";"Larva";329;1
"Unit";"Zergling";"Larva";329;1
"Unit";"Zergling";"Larva";329;1
"Unit";"Zergling";"Larva";329;1
"Unit";"Zergling";"Larva";329;1
"Unit";"Zergling";"Larva";329;1
"Unit";"Zergling";"Larva";329;1
"Unit";"Zergling";"Larva";329;1
"Unit";"Zergling";"Larva";329;1
"Unit";"Zergling";"Larva";329;1
"Unit";"Zergling";"Larva";329;1
"Unit";"Zergling";"Larva";329;1
"Unit";"Zergling";"Larva";329;1
"Unit";"Zergling";"Larva";329;1
"Unit";"Zergling";"Larva";329;1
"Unit";"Zergling";"Larva";329;1
"Unit";"Zergling";"Larva";329;1
"Unit";"Zergling";"Larva";329;1
"Unit";"Zergling";"Larva";329;1
"Unit";"Zergling";"Larva";329;1
"Unit";"Zergling";"Larva";329;1
"Unit";"Zergling";"Larva";329;1
"Unit";"Zergling";"Larva";329;1
"Unit";"Zergling";"Larva";329;1
"Unit";"Zergling";"Larva";329;1
"Unit";"Zergling";"Larva";329;1
"Unit";"Zergling";"Larva";329;1
"Unit";"Zergling";"Larva";329;1
"Unit";"Zergling";"Larva";329;1
"Unit";"Zergling";"Larva";329;1
"Unit";"Zergling";"Larva";329;1
"Unit";"Zergling";"Larva";329;1
"Unit";"Zergling";"Larva";329;1
"Unit";"Zergling";"Larva";329;1
"Unit";"Zergling";"Larva";329;1
"Unit";"Zergling";"Larva";329;1
"Unit";"Zergling";"Larva";329;1
"Unit";"Zergling";"Larva";329;1
"Unit";"Zergling";"Larva";329;1
"Unit";"Zergling";"Larva";329;1
"Unit";"Zergling";"Larva";329;1
"Unit";"Zergling";"Larva";329;1
"Building";"LurkerDenMP";NA;317;0
"Unit";"Baneling";"Zergling";347;0
"Unit";"Baneling";"Zergling";347;0
"Unit";"Baneling";"Zergling";347;0
"Unit";"Baneling";"Zergling";347;0
"Unit";"Baneling";"Zergling";347;0
"Unit";"Baneling";"Zergling";347;0
"Unit";"Baneling";"Zergling";347;0
"Unit";"Baneling";"Zergling";347;0
"Unit";"Baneling";"Zergling";347;0
"Upgrade";"ChitinousPlating";"UltraliskCavern";319;0
"Unit";"Hydralisk";"Larva";395;2
"Unit";"Hydralisk";"Larva";395;2
"Unit";"Hydralisk";"Larva";395;2
"Unit";"Queen";"Hatchery";407;2
"Upgrade";"ZergMeleeWeaponsLevel3";"EvolutionChamber";319;0
"Upgrade";"ZergGroundArmorsLevel3";"EvolutionChamber";319;0
"Unit";"Hydralisk";"Larva";407;2
"Unit";"Hydralisk";"Larva";407;2
"Unit";"Hydralisk";"Larva";407;2
"Unit";"Hydralisk";"Larva";407;2
"Unit";"Hydralisk";"Larva";407;2
"Unit";"Hydralisk";"Larva";407;2
"Unit";"Hydralisk";"Larva";407;2
"Unit";"Hydralisk";"Larva";407;2
"Unit";"Hydralisk";"Larva";407;2
"Unit";"Baneling";"Zergling";409;0
"Unit";"Baneling";"Zergling";409;0
"Unit";"Baneling";"Zergling";409;0
"Unit";"Baneling";"Zergling";409;0
"Unit";"Baneling";"Zergling";409;0
"Unit";"Baneling";"Zergling";409;0
"Unit";"Baneling";"Zergling";409;0
"Unit";"Baneling";"Zergling";409;0
"Unit";"Baneling";"Zergling";409;0
"Unit";"Baneling";"Zergling";409;0
"Unit";"Baneling";"Zergling";409;0
"Unit";"Baneling";"Zergling";409;0
"Unit";"Baneling";"Zergling";409;0
"Unit";"Baneling";"Zergling";409;0
"Unit";"Baneling";"Zergling";409;0
"Unit";"Baneling";"Zergling";409;0
"Building";"Extractor";NA;409;0
"Building";"CreepTumor";NA;427;0
"Building";"CreepTumor";NA;427;0
"Building";"Hatchery";NA;409;0
"Unit";"Overlord";"Larva";427;0
"Unit";"Overlord";"Larva";427;0
"Unit";"Overlord";"Larva";427;0
"Unit";"Overlord";"Larva";427;0
"Unit";"Overlord";"Larva";427;0
"Upgrade";"EvolveGroovedSpines";"HydraliskDen";427;0
"Unit";"Hydralisk";"Larva";446;2
"Unit";"Hydralisk";"Larva";446;2
"Unit";"Hydralisk";"Larva";446;2
"Unit";"Hydralisk";"Larva";446;2
"Unit";"Hydralisk";"Larva";446;2
"Unit";"Hydralisk";"Larva";446;2
"Unit";"Hydralisk";"Larva";446;2
"Upgrade";"ZergMissileWeaponsLevel1";"EvolutionChamber";427;0
"Building";"CreepTumor";NA;460;0
"Building";"CreepTumor";NA;460;0
"Unit";"Queen";"Hatchery";446;2
"Building";"Hatchery";NA;435;0
"Unit";"Zergling";"Larva";462;1
"Unit";"Zergling";"Larva";462;1
"Unit";"Zergling";"Larva";462;1
"Unit";"Zergling";"Larva";462;1
"Unit";"Zergling";"Larva";462;1
"Unit";"Zergling";"Larva";462;1
"Unit";"Zergling";"Larva";462;1
"Unit";"Zergling";"Larva";462;1
"Unit";"Zergling";"Larva";462;1
"Unit";"Zergling";"Larva";462;1
"Unit";"Zergling";"Larva";462;1
"Unit";"Zergling";"Larva";462;1
"Unit";"Zergling";"Larva";462;1
"Unit";"Zergling";"Larva";462;1
"Unit";"Zergling";"Larva";462;1
"Unit";"Zergling";"Larva";462;1
"Unit";"Zergling";"Larva";462;1
"Unit";"Zergling";"Larva";462;1
"Unit";"Zergling";"Larva";462;1
"Unit";"Zergling";"Larva";462;1
"Unit";"Zergling";"Larva";462;1
"Unit";"Zergling";"Larva";462;1
"Unit";"Zergling";"Larva";462;1
"Unit";"Zergling";"Larva";462;1
"Unit";"Zergling";"Larva";462;1
"Unit";"Zergling";"Larva";462;1
"Unit";"Zergling";"Larva";462;1
"Unit";"Zergling";"Larva";462;1
"Unit";"Zergling";"Larva";462;1
"Unit";"Zergling";"Larva";462;1
"Unit";"Zergling";"Larva";462;1
"Unit";"Zergling";"Larva";462;1
"Unit";"Zergling";"Larva";462;1
"Unit";"Zergling";"Larva";462;1
"Unit";"Baneling";"Zergling";496;0
"Upgrade";"EvolveMuscularAugments";"HydraliskDen";462;0
"Unit";"Baneling";"Zergling";496;0
"Unit";"Baneling";"Zergling";496;0
"Unit";"Baneling";"Zergling";496;0
"Unit";"Baneling";"Zergling";496;0
"Unit";"Baneling";"Zergling";496;0
"Unit";"Baneling";"Zergling";496;0
"Unit";"Baneling";"Zergling";496;0
"Unit";"Baneling";"Zergling";496;0
"Unit";"Baneling";"Zergling";496;0
"Unit";"Baneling";"Zergling";496;0
"Unit";"Baneling";"Zergling";496;0
"Unit";"Baneling";"Zergling";496;0
"Unit";"Baneling";"Zergling";496;0
"Unit";"Baneling";"Zergling";496;0
"Unit";"Baneling";"Zergling";496;0
"Unit";"Baneling";"Zergling";496;0
"Unit";"Baneling";"Zergling";496;0
"Unit";"Baneling";"Zergling";496;0
"Unit";"Baneling";"Zergling";496;0
"Unit";"Baneling";"Zergling";496;0
"Unit";"Baneling";"Zergling";496;0
"Unit";"Baneling";"Zergling";496;0
"Unit";"Baneling";"Zergling";496;0
"Unit";"Baneling";"Zergling";496;0
"Unit";"Baneling";"Zergling";496;0
"Unit";"Baneling";"Zergling";496;0
"Unit";"Baneling";"Zergling";496;0
"Unit";"Baneling";"Zergling";496;0
"Unit";"Baneling";"Zergling";496;0
"Unit";"Baneling";"Zergling";496;0
"Unit";"Baneling";"Zergling";496;0
"Unit";"Baneling";"Zergling";496;0
"Unit";"Baneling";"Zergling";496;0
"Unit";"Baneling";"Zergling";496;0
"Unit";"Baneling";"Zergling";496;0
"Unit";"Baneling";"Zergling";496;0
"Unit";"Hydralisk";"Larva";464;2
"Unit";"Hydralisk";"Larva";472;2
"Unit";"Hydralisk";"Larva";476;2
"Unit";"Hydralisk";"Larva";476;2
"Unit";"Hydralisk";"Larva";480;2
"Unit";"Hydralisk";"Larva";484;2
"Unit";"Hydralisk";"Larva";484;2
"Unit";"Hydralisk";"Larva";488;2
"Unit";"Hydralisk";"Larva";490;2
"Unit";"Hydralisk";"Larva";490;2
"Unit";"Zergling";"Larva";496;1
"Unit";"Zergling";"Larva";496;1
"Unit";"Zergling";"Larva";496;1
"Unit";"Zergling";"Larva";496;1
"Unit";"Zergling";"Larva";496;1
"Unit";"Zergling";"Larva";496;1
"Unit";"Zergling";"Larva";496;1
"Unit";"Zergling";"Larva";496;1
"Unit";"Zergling";"Larva";496;1
"Unit";"Zergling";"Larva";496;1
"Unit";"Zergling";"Larva";496;1
"Unit";"Zergling";"Larva";496;1
"Unit";"Zergling";"Larva";496;1
"Unit";"Zergling";"Larva";496;1
"Unit";"Zergling";"Larva";496;1
"Unit";"Zergling";"Larva";496;1
"Unit";"Zergling";"Larva";496;1
"Unit";"Zergling";"Larva";496;1
"Unit";"Zergling";"Larva";496;1
"Unit";"Zergling";"Larva";496;1
"Building";"Hatchery";NA;536;0
"Building";"CreepTumorQueen";NA;536;0
"Building";"CreepTumorQueen";NA;536;0
"Building";"CreepTumorQueen";NA;536;0
"Building";"HydraliskDen";NA;536;0
"Building";"CreepTumorQueen";NA;536;0
"Building";"CreepTumor";NA;536;0
"Building";"Hatchery";NA;536;0
"Building";"CreepTumor";NA;536;0
"Building";"Hatchery";NA;536;0
"Building";"CreepTumor";NA;536;0
"Building";"CreepTumor";NA;536;0
"Building";"CreepTumor";NA;536;0
"Building";"CreepTumor";NA;536;0
"Unit";"Queen";"Hatchery";536;2
"Unit";"Queen";"Hatchery";536;2
"Unit";"Queen";"Hatchery";536;2
"Unit";"Queen";"Hatchery";536;2
"Unit";"Queen";"Hatchery";536;2
"Unit";"Queen";"Hatchery";536;2
"Unit";"Hydralisk";"Larva";536;2
"Unit";"Hydralisk";"Larva";536;2
"Unit";"Hydralisk";"Larva";536;2
"Unit";"Hydralisk";"Larva";536;2
"Unit";"Hydralisk";"Larva";536;2
"Unit";"Hydralisk";"Larva";536;2
"Unit";"Hydralisk";"Larva";536;2
"Unit";"Hydralisk";"Larva";536;2
"Unit";"Hydralisk";"Larva";536;2
"Unit";"Hydralisk";"Larva";536;2
"Unit";"Hydralisk";"Larva";536;2
"Unit";"Hydralisk";"Larva";536;2
"Unit";"Hydralisk";"Larva";536;2
"Building";"Extractor";NA;536;0
"Building";"Extractor";NA;536;0
"Upgrade";"ZergMissileWeaponsLevel2";"EvolutionChamber";536;0
"Building";"CreepTumor";NA;574;0
"Building";"CreepTumor";NA;574;0
"Building";"CreepTumor";NA;574;0
"Building";"CreepTumor";NA;574;0
"Building";"CreepTumor";NA;574;0
"Building";"CreepTumorQueen";NA;574;0
"Building";"Extractor";NA;574;0
"Building";"CreepTumorQueen";NA;574;0
"Building";"CreepTumorQueen";NA;574;0
"Building";"CreepTumorQueen";NA;574;0
"Building";"CreepTumor";NA;574;0
"Building";"Extractor";NA;574;0
"Building";"Extractor";NA;574;0
"Building";"CreepTumorQueen";NA;574;0
"Building";"SporeCrawler";NA;574;0
"Building";"CreepTumorQueen";NA;574;0
"Building";"CreepTumorQueen";NA;574;0
"Unit";"Zergling";"Larva";574;1
"Unit";"Zergling";"Larva";574;1
"Unit";"Zergling";"Larva";574;1
"Unit";"Zergling";"Larva";574;1
"Unit";"Zergling";"Larva";574;1
"Unit";"Zergling";"Larva";574;1
"Unit";"Zergling";"Larva";574;1
"Unit";"Zergling";"Larva";574;1
"Unit";"Zergling";"Larva";574;1
"Unit";"Zergling";"Larva";574;1
"Unit";"Zergling";"Larva";574;1
"Unit";"Zergling";"Larva";574;1
"Unit";"Zergling";"Larva";574;1
"Unit";"Zergling";"Larva";574;1
"Unit";"Zergling";"Larva";574;1
"Unit";"Zergling";"Larva";574;1
"Unit";"Zergling";"Larva";574;1
"Unit";"Zergling";"Larva";574;1
"Unit";"Zergling";"Larva";574;1
"Unit";"Zergling";"Larva";574;1
"Unit";"Zergling";"Larva";574;1
"Unit";"Zergling";"Larva";574;1
"Unit";"Zergling";"Larva";574;1
"Unit";"Zergling";"Larva";574;1
"Unit";"Zergling";"Larva";574;1
"Unit";"Zergling";"Larva";574;1
"Unit";"Zergling";"Larva";574;1
"Unit";"Zergling";"Larva";574;1
"Unit";"Zergling";"Larva";574;1
"Unit";"Zergling";"Larva";574;1
"Unit";"Zergling";"Larva";574;1
"Unit";"Zergling";"Larva";574;1
"Unit";"Zergling";"Larva";574;1
"Unit";"Zergling";"Larva";574;1
"Unit";"Zergling";"Larva";574;1
"Unit";"Zergling";"Larva";574;1
"Unit";"Zergling";"Larva";574;1
"Unit";"Zergling";"Larva";574;1
"Unit";"Zergling";"Larva";574;1
"Unit";"Zergling";"Larva";574;1
"Unit";"Zergling";"Larva";574;1
"Unit";"Zergling";"Larva";574;1
"Unit";"Zergling";"Larva";574;1
"Unit";"Zergling";"Larva";574;1
"Unit";"Zergling";"Larva";574;1
"Unit";"Zergling";"Larva";574;1
"Unit";"Zergling";"Larva";574;1
"Unit";"Zergling";"Larva";574;1
"Unit";"Zergling";"Larva";574;1
"Unit";"Zergling";"Larva";574;1
"Unit";"Zergling";"Larva";574;1
"Unit";"Zergling";"Larva";574;1
"Unit";"Zergling";"Larva";574;1
"Unit";"Zergling";"Larva";574;1
"Unit";"Zergling";"Larva";574;1
"Unit";"Zergling";"Larva";574;1
"Unit";"Zergling";"Larva";574;1
"Unit";"Zergling";"Larva";574;1
"Unit";"Zergling";"Larva";574;1
"Unit";"Zergling";"Larva";574;1
"Unit";"Zergling";"Larva";574;1
"Unit";"Zergling";"Larva";574;1
"Unit";"Zergling";"Larva";574;1
"Unit";"Zergling";"Larva";574;1
"Unit";"Zergling";"Larva";574;1
"Unit";"Zergling";"Larva";574;1
"Unit";"Zergling";"Larva";574;1
"Unit";"Zergling";"Larva";574;1
"Building";"SpineCrawler";NA;574;0
"Building";"SpineCrawler";NA;574;0
"Building";"SporeCrawler";NA;642;0
"Building";"SpineCrawler";NA;642;0
"Building";"SpineCrawler";NA;642;0
"Upgrade";"ZergMissileWeaponsLevel3";"EvolutionChamber";574;0
"Unit";"Zergling";"Larva";654;1
"Unit";"Zergling";"Larva";654;1
"Unit";"Zergling";"Larva";654;1
"Unit";"Zergling";"Larva";654;1
"Unit";"Zergling";"Larva";654;1
"Unit";"Zergling";"Larva";654;1
"Unit";"Zergling";"Larva";654;1
"Unit";"Zergling";"Larva";654;1
"Unit";"Zergling";"Larva";654;1
"Unit";"Zergling";"Larva";654;1
"Unit";"Zergling";"Larva";654;1
"Unit";"Zergling";"Larva";654;1
"Unit";"Zergling";"Larva";654;1
"Unit";"Zergling";"Larva";654;1
"Unit";"Zergling";"Larva";654;1
"Unit";"Zergling";"Larva";654;1
"Unit";"Zergling";"Larva";654;1
"Unit";"Zergling";"Larva";654;1
"Unit";"Zergling";"Larva";654;1
"Unit";"Zergling";"Larva";654;1
"Unit";"Zergling";"Larva";654;1
"Unit";"Zergling";"Larva";654;1
"Unit";"Zergling";"Larva";654;1
"Unit";"Zergling";"Larva";654;1
"Unit";"Zergling";"Larva";654;1
"Unit";"Zergling";"Larva";654;1
"Unit";"Zergling";"Larva";654;1
"Unit";"Zergling";"Larva";654;1
"Unit";"Zergling";"Larva";654;1
"Unit";"Zergling";"Larva";654;1
"Unit";"Zergling";"Larva";654;1
"Unit";"Zergling";"Larva";654;1
"Unit";"Zergling";"Larva";654;1
"Unit";"Zergling";"Larva";654;1
"Unit";"Zergling";"Larva";654;1
"Unit";"Zergling";"Larva";654;1
"Unit";"Zergling";"Larva";654;1
"Unit";"Zergling";"Larva";654;1
"Unit";"Zergling";"Larva";654;1
"Unit";"Zergling";"Larva";654;1
"Unit";"Zergling";"Larva";654;1
"Unit";"Zergling";"Larva";654;1
"Unit";"Zergling";"Larva";654;1
"Unit";"Zergling";"Larva";654;1
"Unit";"Zergling";"Larva";654;1
"Unit";"Zergling";"Larva";654;1
"Unit";"Zergling";"Larva";654;1
"Unit";"Zergling";"Larva";654;1
"Unit";"Zergling";"Larva";654;1
"Unit";"Zergling";"Larva";654;1
"Unit";"Zergling";"Larva";654;1
"Unit";"Zergling";"Larva";654;1
"Unit";"Zergling";"Larva";654;1
"Unit";"Zergling";"Larva";654;1
"Unit";"Zergling";"Larva";654;1
"Unit";"Zergling";"Larva";654;1
"Unit";"Zergling";"Larva";654;1
"Unit";"Zergling";"Larva";654;1
"Unit";"Zergling";"Larva";654;1
"Unit";"Zergling";"Larva";654;1
"Unit";"Zergling";"Larva";654;1
"Unit";"Zergling";"Larva";654;1
"Unit";"Zergling";"Larva";654;1
"Unit";"Zergling";"Larva";654;1
"Unit";"Zergling";"Larva";654;1
"Unit";"Zergling";"Larva";654;1
"Unit";"Zergling";"Larva";654;1
"Unit";"Zergling";"Larva";654;1
"Unit";"Zergling";"Larva";654;1
"Unit";"Zergling";"Larva";654;1
"Unit";"Zergling";"Larva";654;1
"Unit";"Zergling";"Larva";654;1
"Unit";"Zergling";"Larva";654;1
"Unit";"Zergling";"Larva";654;1
"Unit";"Zergling";"Larva";654;1
"Unit";"Zergling";"Larva";654;1
"Unit";"Zergling";"Larva";654;1
"Unit";"Zergling";"Larva";654;1
"Unit";"Zergling";"Larva";654;1
"Unit";"Zergling";"Larva";654;1
"Unit";"Zergling";"Larva";654;1
"Unit";"Zergling";"Larva";654;1
"Unit";"Zergling";"Larva";654;1
"Unit";"Zergling";"Larva";654;1
"Unit";"Zergling";"Larva";654;1
"Unit";"Zergling";"Larva";654;1
"Unit";"Zergling";"Larva";654;1
"Unit";"Zergling";"Larva";654;1
"Unit";"Zergling";"Larva";654;1
"Unit";"Zergling";"Larva";654;1
"Unit";"Zergling";"Larva";654;1
"Unit";"Zergling";"Larva";654;1
"Unit";"Zergling";"Larva";654;1
"Unit";"Zergling";"Larva";654;1
"Unit";"Zergling";"Larva";654;1
"Unit";"Zergling";"Larva";654;1
"Unit";"Zergling";"Larva";654;1
"Unit";"Zergling";"Larva";654;1
"Building";"CreepTumor";NA;752;0
"Building";"CreepTumor";NA;752;0
"Building";"CreepTumor";NA;752;0
"Building";"CreepTumorQueen";NA;752;0
"Building";"CreepTumorQueen";NA;752;0
"Building";"CreepTumor";NA;752;0
"Building";"CreepTumor";NA;752;0
"Building";"CreepTumor";NA;752;0
"Building";"CreepTumor";NA;752;0
"Building";"CreepTumorQueen";NA;752;0
"Building";"CreepTumorQueen";NA;752;0
"Building";"Extractor";NA;752;0
"Building";"Extractor";NA;752;0
"Unit";"Baneling";"Zergling";752;0
"Unit";"Baneling";"Zergling";752;0
"Unit";"Baneling";"Zergling";752;0
"Unit";"Baneling";"Zergling";752;0
"Unit";"Baneling";"Zergling";752;0
"Unit";"Baneling";"Zergling";752;0
"Unit";"Baneling";"Zergling";752;0
"Unit";"Baneling";"Zergling";752;0
"Unit";"Baneling";"Zergling";752;0
"Unit";"Baneling";"Zergling";752;0
"Unit";"Baneling";"Zergling";752;0
"Unit";"Baneling";"Zergling";752;0
"Unit";"Baneling";"Zergling";752;0
"Unit";"Baneling";"Zergling";752;0
"Unit";"Baneling";"Zergling";752;0
"Unit";"Baneling";"Zergling";752;0
"Unit";"Baneling";"Zergling";752;0
"Unit";"Baneling";"Zergling";752;0
"Unit";"Baneling";"Zergling";752;0
"Unit";"Baneling";"Zergling";752;0
"Unit";"Baneling";"Zergling";752;0
"Unit";"Baneling";"Zergling";752;0
"Unit";"Baneling";"Zergling";752;0
"Unit";"Baneling";"Zergling";752;0
"Unit";"Baneling";"Zergling";752;0
"Unit";"Baneling";"Zergling";752;0
"Building";"CreepTumor";NA;752;0
"Building";"CreepTumor";NA;752;0
"Building";"Hatchery";NA;752;0
"Unit";"Zergling";"Larva";752;1
"Unit";"Zergling";"Larva";752;1
"Unit";"Zergling";"Larva";752;1
"Unit";"Zergling";"Larva";752;1
"Unit";"Zergling";"Larva";752;1
"Unit";"Zergling";"Larva";752;1
"Unit";"Zergling";"Larva";752;1
"Unit";"Zergling";"Larva";752;1
"Unit";"Zergling";"Larva";752;1
"Unit";"Zergling";"Larva";752;1
"Unit";"Zergling";"Larva";752;1
"Unit";"Zergling";"Larva";752;1
"Unit";"Zergling";"Larva";752;1
"Unit";"Zergling";"Larva";752;1
"Unit";"Zergling";"Larva";752;1
"Unit";"Zergling";"Larva";752;1
"Unit";"Zergling";"Larva";752;1
"Unit";"Zergling";"Larva";752;1
"Unit";"Zergling";"Larva";752;1
"Unit";"Zergling";"Larva";752;1
"Unit";"Zergling";"Larva";752;1
"Unit";"Zergling";"Larva";752;1
"Unit";"Zergling";"Larva";752;1
"Unit";"Zergling";"Larva";752;1
"Unit";"Zergling";"Larva";752;1
"Unit";"Zergling";"Larva";752;1
"Unit";"Zergling";"Larva";752;1
"Unit";"Zergling";"Larva";752;1
"Unit";"Zergling";"Larva";752;1
"Unit";"Zergling";"Larva";752;1
"Unit";"Zergling";"Larva";752;1
"Unit";"Zergling";"Larva";752;1
"Unit";"Zergling";"Larva";752;1
"Unit";"Zergling";"Larva";752;1
"Unit";"Zergling";"Larva";752;1
"Unit";"Zergling";"Larva";752;1
"Unit";"Zergling";"Larva";752;1
"Unit";"Zergling";"Larva";752;1
"Unit";"Zergling";"Larva";752;1
"Unit";"Zergling";"Larva";752;1
"Unit";"Zergling";"Larva";752;1
"Unit";"Zergling";"Larva";752;1
"Unit";"Zergling";"Larva";752;1
"Unit";"Zergling";"Larva";752;1
"Unit";"Zergling";"Larva";752;1
"Unit";"Zergling";"Larva";752;1
"Unit";"Zergling";"Larva";752;1
"Unit";"Zergling";"Larva";752;1
"Unit";"Zergling";"Larva";752;1
"Unit";"Zergling";"Larva";752;1
"Unit";"Zergling";"Larva";752;1
"Unit";"Zergling";"Larva";752;1
"Unit";"Zergling";"Larva";752;1
"Unit";"Zergling";"Larva";752;1
"Unit";"Zergling";"Larva";752;1
"Unit";"Zergling";"Larva";752;1
"Unit";"Zergling";"Larva";752;1
"Unit";"Zergling";"Larva";752;1
"Unit";"Zergling";"Larva";752;1
"Unit";"Zergling";"Larva";752;1
"Unit";"Zergling";"Larva";752;1
"Unit";"Zergling";"Larva";752;1
"Unit";"Zergling";"Larva";752;1
"Unit";"Zergling";"Larva";752;1
"Unit";"Zergling";"Larva";752;1
"Unit";"Zergling";"Larva";752;1
"Unit";"Zergling";"Larva";752;1
"Unit";"Zergling";"Larva";752;1
"Unit";"Zergling";"Larva";752;1
"Unit";"Zergling";"Larva";752;1
"Unit";"Zergling";"Larva";752;1
"Unit";"Zergling";"Larva";752;1
"Unit";"Zergling";"Larva";752;1
"Unit";"Zergling";"Larva";752;1
"Unit";"Zergling";"Larva";752;1
"Unit";"Zergling";"Larva";752;1
"Unit";"Zergling";"Larva";752;1
"Unit";"Zergling";"Larva";752;1
"Unit";"Zergling";"Larva";752;1
"Unit";"Zergling";"Larva";752;1
"Unit";"Zergling";"Larva";752;1
"Unit";"Zergling";"Larva";752;1
"Unit";"Zergling";"Larva";752;1
"Unit";"Zergling";"Larva";752;1
"Unit";"Zergling";"Larva";752;1
"Unit";"Zergling";"Larva";752;1
"Unit";"Zergling";"Larva";752;1
"Unit";"Zergling";"Larva";752;1
"Unit";"Zergling";"Larva";752;1
"Unit";"Zergling";"Larva";752;1
"Unit";"Zergling";"Larva";752;1
"Unit";"Zergling";"Larva";752;1
"Unit";"Zergling";"Larva";752;1
"Unit";"Zergling";"Larva";752;1
"Unit";"Zergling";"Larva";752;1
"Unit";"Zergling";"Larva";752;1
"Unit";"Zergling";"Larva";752;1
"Unit";"Zergling";"Larva";752;1
"Unit";"Zergling";"Larva";752;1
"Unit";"Zergling";"Larva";752;1
"Unit";"Zergling";"Larva";752;1
"Unit";"Zergling";"Larva";752;1
"Unit";"Zergling";"Larva";752;1
"Unit";"Zergling";"Larva";752;1
"Unit";"Zergling";"Larva";752;1
"Unit";"Zergling";"Larva";752;1
"Unit";"Zergling";"Larva";752;1
"Unit";"Zergling";"Larva";752;1
"Unit";"Zergling";"Larva";752;1
"Unit";"Zergling";"Larva";752;1
"Unit";"Zergling";"Larva";752;1
"Unit";"Zergling";"Larva";752;1
"Unit";"Zergling";"Larva";752;1
"Unit";"Zergling";"Larva";752;1
"Unit";"Zergling";"Larva";752;1
"Unit";"Zergling";"Larva";752;1
"Unit";"Zergling";"Larva";752;1
"Unit";"Zergling";"Larva";752;1
"Unit";"Zergling";"Larva";752;1
"Unit";"Zergling";"Larva";752;1
"Unit";"Zergling";"Larva";752;1
"Unit";"Zergling";"Larva";752;1
"Unit";"Zergling";"Larva";752;1
"Unit";"Zergling";"Larva";752;1
"Unit";"Zergling";"Larva";752;1
"Unit";"Zergling";"Larva";752;1
"Unit";"Zergling";"Larva";752;1
"Unit";"Zergling";"Larva";752;1
"Unit";"Zergling";"Larva";752;1
"Unit";"Zergling";"Larva";752;1
"Unit";"Zergling";"Larva";752;1
"Unit";"Zergling";"Larva";752;1
"Unit";"Zergling";"Larva";752;1
"Unit";"Zergling";"Larva";752;1
"Unit";"Corruptor";"Larva";752;2
"Unit";"Corruptor";"Larva";752;2
"Unit";"Corruptor";"Larva";752;2
"Unit";"Corruptor";"Larva";752;2
"Unit";"Corruptor";"Larva";752;2
"Unit";"Corruptor";"Larva";752;2
"Unit";"Corruptor";"Larva";752;2
"Unit";"Corruptor";"Larva";752;2
"Unit";"Corruptor";"Larva";752;2
"Unit";"Corruptor";"Larva";752;2
"Unit";"Corruptor";"Larva";752;2
"Unit";"Corruptor";"Larva";752;2
"Unit";"Corruptor";"Larva";752;2
"Unit";"Corruptor";"Larva";752;2
"Unit";"Corruptor";"Larva";752;2
"Unit";"Corruptor";"Larva";752;2
"Unit";"Corruptor";"Larva";752;2
"Unit";"Corruptor";"Larva";752;2
"Unit";"Corruptor";"Larva";752;2
"Unit";"Corruptor";"Larva";752;2
"Unit";"Corruptor";"Larva";752;2
"Building";"CreepTumor";NA;752;0
"Unit";"Baneling";"Zergling";928;0
"Unit";"Baneling";"Zergling";928;0
"Unit";"Baneling";"Zergling";928;0
"Unit";"Baneling";"Zergling";928;0
"Unit";"Baneling";"Zergling";928;0
"Unit";"Baneling";"Zergling";928;0
"Unit";"Baneling";"Zergling";928;0
"Unit";"Baneling";"Zergling";928;0
"Unit";"Baneling";"Zergling";928;0
"Unit";"Baneling";"Zergling";928;0
"Unit";"Baneling";"Zergling";928;0
"Unit";"Baneling";"Zergling";928;0
"Unit";"Baneling";"Zergling";928;0
"Unit";"Baneling";"Zergling";928;0
"Unit";"Baneling";"Zergling";928;0
"Unit";"Baneling";"Zergling";928;0
"Unit";"Baneling";"Zergling";928;0
"Unit";"Baneling";"Zergling";928;0
"Unit";"Baneling";"Zergling";928;0
"Unit";"Baneling";"Zergling";928;0
"Unit";"Baneling";"Zergling";928;0
"Unit";"Baneling";"Zergling";928;0
"Unit";"Baneling";"Zergling";928;0
"Unit";"Baneling";"Zergling";928;0
"Unit";"Baneling";"Zergling";928;0
"Unit";"Baneling";"Zergling";928;0
"Building";"CreepTumor";NA;928;0
"Building";"CreepTumorQueen";NA;928;0
"Building";"CreepTumorQueen";NA;928;0
"Building";"CreepTumorQueen";NA;928;0
"Unit";"Zergling";"Larva";928;1
"Unit";"Zergling";"Larva";928;1
"Unit";"Zergling";"Larva";928;1
"Unit";"Zergling";"Larva";928;1
"Unit";"Zergling";"Larva";928;1
"Unit";"Zergling";"Larva";928;1
"Unit";"Zergling";"Larva";928;1
"Unit";"Zergling";"Larva";928;1
"Unit";"Zergling";"Larva";928;1
"Unit";"Zergling";"Larva";928;1
"Unit";"Zergling";"Larva";928;1
"Unit";"Zergling";"Larva";928;1
"Unit";"Zergling";"Larva";928;1
"Unit";"Zergling";"Larva";928;1
"Unit";"Zergling";"Larva";928;1
"Unit";"Zergling";"Larva";928;1
"Unit";"Zergling";"Larva";928;1
"Unit";"Zergling";"Larva";928;1
"Unit";"Zergling";"Larva";928;1
"Unit";"Zergling";"Larva";928;1
"Unit";"Zergling";"Larva";928;1
"Unit";"Zergling";"Larva";928;1
"Unit";"Zergling";"Larva";928;1
"Unit";"Zergling";"Larva";928;1
"Unit";"Zergling";"Larva";928;1
"Unit";"Zergling";"Larva";928;1
"Unit";"Zergling";"Larva";928;1
"Unit";"Zergling";"Larva";928;1
"Unit";"Zergling";"Larva";928;1
"Unit";"Zergling";"Larva";928;1
"Unit";"Zergling";"Larva";928;1
"Unit";"Zergling";"Larva";928;1
"Unit";"Zergling";"Larva";928;1
"Unit";"Zergling";"Larva";928;1
"Unit";"Zergling";"Larva";928;1
"Unit";"Zergling";"Larva";928;1
"Unit";"Zergling";"Larva";928;1
"Unit";"Zergling";"Larva";928;1
"Unit";"Zergling";"Larva";928;1
"Unit";"Zergling";"Larva";928;1
"Unit";"Zergling";"Larva";928;1
"Unit";"Zergling";"Larva";928;1
"Unit";"Overlord";"Larva";928;0
"Unit";"Overlord";"Larva";928;0
"Unit";"Overlord";"Larva";928;0
"Unit";"Overlord";"Larva";928;0
"Unit";"Overlord";"Larva";928;0
"Unit";"Overlord";"Larva";928;0
"Unit";"Baneling";"Zergling";970;0
"Unit";"Baneling";"Zergling";970;0
"Unit";"Baneling";"Zergling";970;0
"Unit";"Baneling";"Zergling";970;0
"Unit";"Baneling";"Zergling";970;0
"Unit";"Baneling";"Zergling";970;0
"Unit";"Baneling";"Zergling";970;0
"Unit";"Baneling";"Zergling";970;0
"Unit";"Baneling";"Zergling";970;0
"Unit";"Baneling";"Zergling";970;0
"Unit";"Baneling";"Zergling";970;0
"Unit";"Baneling";"Zergling";970;0
"Unit";"Baneling";"Zergling";970;0
"Unit";"Baneling";"Zergling";970;0
"Unit";"Baneling";"Zergling";970;0
"Unit";"Baneling";"Zergling";970;0
"Unit";"Baneling";"Zergling";970;0
"Unit";"Baneling";"Zergling";970;0
"Unit";"Baneling";"Zergling";970;0
"Unit";"Baneling";"Zergling";970;0
"Unit";"Baneling";"Zergling";970;0
"Unit";"Baneling";"Zergling";970;0
"Unit";"Baneling";"Zergling";970;0
"Unit";"Baneling";"Zergling";970;0
"Unit";"Baneling";"Zergling";970;0
"Unit";"Baneling";"Zergling";970;0
"Unit";"Baneling";"Zergling";970;0
"Unit";"Baneling";"Zergling";970;0
"Unit";"Baneling";"Zergling";970;0
"Unit";"Baneling";"Zergling";970;0
"Unit";"Baneling";"Zergling";970;0
"Unit";"Baneling";"Zergling";970;0
"Unit";"Baneling";"Zergling";970;0
"Unit";"Baneling";"Zergling";970;0
"Unit";"Baneling";"Zergling";970;0
"Unit";"Baneling";"Zergling";970;0
"Unit";"Baneling";"Zergling";970;0
"Unit";"Baneling";"Zergling";970;0
"Unit";"Baneling";"Zergling";970;0
"Unit";"Baneling";"Zergling";970;0
"Unit";"Baneling";"Zergling";970;0
"Unit";"Baneling";"Zergling";970;0
"Building";"CreepTumor";NA;970;0
"Building";"CreepTumor";NA;970;0
"Building";"CreepTumor";NA;970;0
"Building";"CreepTumor";NA;970;0
"Unit";"Mutalisk";"Larva";970;2
"Unit";"Mutalisk";"Larva";970;2
"Unit";"Mutalisk";"Larva";970;2
"Unit";"Mutalisk";"Larva";970;2
"Unit";"Mutalisk";"Larva";970;2
"Unit";"Mutalisk";"Larva";970;2
"Unit";"Mutalisk";"Larva";970;2
"Unit";"Mutalisk";"Larva";970;2
"Unit";"Mutalisk";"Larva";970;2
"Unit";"Mutalisk";"Larva";970;2
"Unit";"Mutalisk";"Larva";970;2
"Unit";"Mutalisk";"Larva";970;2
"Unit";"Mutalisk";"Larva";970;2
"Unit";"Mutalisk";"Larva";970;2
"Unit";"Mutalisk";"Larva";970;2
"Unit";"Mutalisk";"Larva";970;2
"Unit";"Mutalisk";"Larva";970;2
"Unit";"Mutalisk";"Larva";970;2
"Unit";"Mutalisk";"Larva";970;2
"Unit";"Mutalisk";"Larva";970;2
"Unit";"Mutalisk";"Larva";970;2
"Unit";"Mutalisk";"Larva";970;2
"Unit";"Mutalisk";"Larva";970;2
"Unit";"Mutalisk";"Larva";970;2
