"type";"unit_name";"on_building";"total_supply";"supply"
"Unit";"Overlord";"Larva";12;0
"Building";"Extractor";NA;18;0
"Unit";"Overlord";"Larva";21;0
"Building";"SpawningPool";NA;19;0
"Building";"Hatchery";NA;17;0
"Unit";"Zergling";"Larva";23;1
"Unit";"Zergling";"Larva";23;1
"Unit";"Zergling";"Larva";23;1
"Unit";"Zergling";"Larva";23;1
"Unit";"Queen";"Hatchery";23;2
"Unit";"Queen";"Hatchery";23;2
"Unit";"Queen";"Hatchery";33;2
"Unit";"Overlord";"Larva";36;0
"Unit";"Queen";"Hatchery";36;2
"Building";"CreepTumorQueen";NA;42;0
"Unit";"Overlord";"Larva";40;0
"Building";"CreepTumorQueen";NA;42;0
"Building";"CreepTumorQueen";NA;54;0
"Building";"CreepTumor";NA;54;0
"Building";"CreepTumorQueen";NA;54;0
"Unit";"Overlord";"Larva";50;0
"Building";"Hatchery";NA;36;0
"Building";"CreepTumor";NA;56;0
"Unit";"Queen";"Hatchery";50;2
"Unit";"Overlord";"Larva";57;0
"Unit";"Zergling";"Larva";57;1
"Unit";"Zergling";"Larva";57;1
"Building";"CreepTumor";NA;65;0
"Unit";"Zergling";"Larva";57;1
"Unit";"Zergling";"Larva";57;1
"Building";"CreepTumor";NA;65;0
"Unit";"Zergling";"Larva";57;1
"Unit";"Zergling";"Larva";57;1
"Unit";"Zergling";"Larva";57;1
"Unit";"Zergling";"Larva";57;1
"Unit";"Zergling";"Larva";57;1
"Unit";"Zergling";"Larva";57;1
"Unit";"Zergling";"Larva";57;1
"Unit";"Zergling";"Larva";57;1
"Building";"CreepTumorQueen";NA;65;0
"Building";"CreepTumorQueen";NA;65;0
"Building";"CreepTumor";NA;65;0
"Unit";"Overlord";"Larva";65;0
"Building";"SporeCrawler";NA;65;0
"Building";"SporeCrawler";NA;65;0
"Building";"CreepTumorQueen";NA;79;0
"Unit";"Zergling";"Larva";79;1
"Unit";"Zergling";"Larva";79;1
"Unit";"Zergling";"Larva";79;1
"Unit";"Zergling";"Larva";79;1
"Unit";"Zergling";"Larva";79;1
"Unit";"Zergling";"Larva";79;1
"Unit";"Zergling";"Larva";79;1
"Unit";"Zergling";"Larva";79;1
"Building";"CreepTumor";NA;86;0
"Unit";"Queen";"Hatchery";77;2
"Building";"EvolutionChamber";NA;86;0
"Building";"SporeCrawler";NA;86;0
"Building";"CreepTumor";NA;96;0
"Building";"Extractor";NA;86;0
"Building";"Extractor";NA;86;0
"Building";"BanelingNest";NA;86;0
"Unit";"Overlord";"Larva";101;0
"Unit";"Overlord";"Larva";101;0
"Building";"CreepTumor";NA;104;0
"Building";"CreepTumorQueen";NA;104;0
"Building";"CreepTumorQueen";NA;105;0
"Building";"CreepTumorQueen";NA;107;0
"Unit";"Overlord";"Larva";104;0
"Unit";"Overlord";"Larva";104;0
"Building";"EvolutionChamber";NA;101;0
"Building";"Extractor";NA;104;0
"Building";"Extractor";NA;109;0
"Building";"Extractor";NA;109;0
"Unit";"Zergling";"Larva";109;1
"Unit";"Zergling";"Larva";109;1
"Unit";"Zergling";"Larva";109;1
"Unit";"Zergling";"Larva";109;1
"Unit";"Zergling";"Larva";109;1
"Unit";"Zergling";"Larva";109;1
"Unit";"Zergling";"Larva";109;1
"Unit";"Zergling";"Larva";109;1
"Building";"CreepTumorQueen";NA;115;0
"Building";"CreepTumorQueen";NA;115;0
"Unit";"Zergling";"Larva";123;1
"Unit";"Zergling";"Larva";123;1
"Unit";"Zergling";"Larva";123;1
"Unit";"Zergling";"Larva";123;1
"Unit";"Zergling";"Larva";123;1
"Unit";"Zergling";"Larva";123;1
"Unit";"Zergling";"Larva";123;1
"Unit";"Zergling";"Larva";123;1
"Unit";"Zergling";"Larva";123;1
"Unit";"Zergling";"Larva";123;1
"Unit";"Zergling";"Larva";123;1
"Unit";"Zergling";"Larva";123;1
"Building";"HydraliskDen";NA;123;0
"Building";"CreepTumor";NA;140;0
"Building";"CreepTumor";NA;140;0
"Building";"CreepTumor";NA;140;0
"Upgrade";"ZergGroundArmorsLevel1";"EvolutionChamber";109;0
"Unit";"Zergling";"Larva";140;1
"Unit";"Zergling";"Larva";140;1
"Unit";"Zergling";"Larva";140;1
"Unit";"Zergling";"Larva";140;1
"Unit";"Zergling";"Larva";140;1
"Unit";"Zergling";"Larva";140;1
"Unit";"Zergling";"Larva";140;1
"Unit";"Zergling";"Larva";140;1
"Building";"Hatchery";NA;121;0
"Unit";"Hydralisk";"Larva";140;2
"Unit";"Hydralisk";"Larva";140;2
"Unit";"Hydralisk";"Larva";140;2
"Unit";"Hydralisk";"Larva";140;2
"Unit";"Hydralisk";"Larva";140;2
"Unit";"Hydralisk";"Larva";140;2
"Unit";"Hydralisk";"Larva";140;2
"Unit";"Hydralisk";"Larva";140;2
"Unit";"Hydralisk";"Larva";140;2
"Unit";"Hydralisk";"Larva";140;2
"Building";"CreepTumor";NA;140;0
"Building";"CreepTumor";NA;140;0
"Unit";"Baneling";"Zergling";148;0
"Unit";"Baneling";"Zergling";148;0
"Unit";"Baneling";"Zergling";148;0
"Unit";"Baneling";"Zergling";148;0
"Unit";"Baneling";"Zergling";148;0
"Unit";"Baneling";"Zergling";148;0
"Unit";"Baneling";"Zergling";148;0
"Unit";"Baneling";"Zergling";156;0
"Unit";"Baneling";"Zergling";168;0
"Unit";"Baneling";"Zergling";168;0
"Building";"CreepTumorQueen";NA;168;0
"Unit";"Baneling";"Zergling";168;0
"Upgrade";"ZergMeleeWeaponsLevel1";"EvolutionChamber";124;0
"Unit";"Overlord";"Larva";168;0
"Unit";"Overlord";"Larva";168;0
"Unit";"Overlord";"Larva";168;0
"Unit";"Overlord";"Larva";168;0
"Unit";"Overlord";"Larva";168;0
"Building";"Hatchery";NA;140;0
"Upgrade";"EvolveGroovedSpines";"HydraliskDen";140;0
"Unit";"Baneling";"Zergling";168;0
"Unit";"Baneling";"Zergling";168;0
"Unit";"Baneling";"Zergling";168;0
"Unit";"Baneling";"Zergling";168;0
"Unit";"Baneling";"Zergling";168;0
"Unit";"Baneling";"Zergling";168;0
"Unit";"Baneling";"Zergling";168;0
"Unit";"Baneling";"Zergling";168;0
"Unit";"Queen";"Hatchery";168;2
"Unit";"Zergling";"Larva";168;1
"Unit";"Zergling";"Larva";168;1
"Building";"CreepTumor";NA;168;0
"Unit";"Zergling";"Larva";168;1
"Unit";"Zergling";"Larva";168;1
"Unit";"Zergling";"Larva";168;1
"Unit";"Zergling";"Larva";168;1
"Unit";"Zergling";"Larva";168;1
"Unit";"Zergling";"Larva";168;1
"Unit";"Zergling";"Larva";168;1
"Unit";"Zergling";"Larva";168;1
"Unit";"Zergling";"Larva";168;1
"Unit";"Zergling";"Larva";168;1
"Unit";"Zergling";"Larva";168;1
"Unit";"Zergling";"Larva";168;1
"Unit";"Zergling";"Larva";168;1
"Unit";"Zergling";"Larva";168;1
"Unit";"Zergling";"Larva";168;1
"Unit";"Zergling";"Larva";168;1
"Unit";"Zergling";"Larva";168;1
"Unit";"Zergling";"Larva";168;1
"Unit";"Zergling";"Larva";168;1
"Unit";"Zergling";"Larva";168;1
"Unit";"Zergling";"Larva";168;1
"Unit";"Zergling";"Larva";168;1
"Unit";"Zergling";"Larva";168;1
"Unit";"Zergling";"Larva";168;1
"Unit";"Zergling";"Larva";168;1
"Unit";"Zergling";"Larva";168;1
"Unit";"Zergling";"Larva";168;1
"Unit";"Zergling";"Larva";168;1
"Unit";"Zergling";"Larva";168;1
"Unit";"Zergling";"Larva";168;1
"Unit";"Zergling";"Larva";168;1
"Unit";"Zergling";"Larva";168;1
"Unit";"Zergling";"Larva";168;1
"Unit";"Zergling";"Larva";168;1
"Unit";"Zergling";"Larva";168;1
"Unit";"Zergling";"Larva";168;1
"Building";"CreepTumor";NA;168;0
"Building";"CreepTumor";NA;168;0
"Unit";"Zergling";"Larva";170;1
"Unit";"Zergling";"Larva";170;1
"Unit";"Zergling";"Larva";170;1
"Unit";"Zergling";"Larva";170;1
"Unit";"Zergling";"Larva";170;1
"Unit";"Zergling";"Larva";170;1
"Unit";"Zergling";"Larva";170;1
"Unit";"Zergling";"Larva";170;1
"Unit";"Zergling";"Larva";170;1
"Unit";"Zergling";"Larva";170;1
"Unit";"Zergling";"Larva";170;1
"Unit";"Zergling";"Larva";170;1
"Unit";"Zergling";"Larva";170;1
"Unit";"Zergling";"Larva";170;1
"Unit";"Zergling";"Larva";170;1
"Unit";"Zergling";"Larva";170;1
"Unit";"Zergling";"Larva";170;1
"Unit";"Zergling";"Larva";170;1
"Unit";"Zergling";"Larva";170;1
"Unit";"Zergling";"Larva";170;1
"Building";"CreepTumorQueen";NA;208;0
"Unit";"Queen";"Hatchery";168;2
"Building";"CreepTumor";NA;228;0
"Building";"CreepTumor";NA;228;0
"Building";"CreepTumor";NA;230;0
