"type";"unit_name";"on_building";"total_supply";"supply"
"Unit";"Overlord";"Larva";13;0
"Building";"Extractor";NA;18;0
"Unit";"Overlord";"Larva";21;0
"Building";"SpawningPool";NA;19;0
"Building";"Hatchery";NA;17;0
"Unit";"Zergling";"Larva";22;1
"Unit";"Zergling";"Larva";22;1
"Unit";"Zergling";"Larva";22;1
"Unit";"Zergling";"Larva";22;1
"Unit";"Queen";"Hatchery";22;2
"Unit";"Queen";"Hatchery";22;2
"Building";"CreepTumorQueen";NA;35;0
"Unit";"Overlord";"Larva";37;0
"Unit";"Overlord";"Larva";41;0
"Building";"CreepTumor";NA;42;0
"Building";"Hatchery";NA;32;0
"Building";"CreepTumorQueen";NA;47;0
"Building";"CreepTumorQueen";NA;48;0
"Unit";"Queen";"Hatchery";42;2
"Unit";"Queen";"Hatchery";46;2
"Building";"RoachWarren";NA;46;0
"Unit";"Overlord";"Larva";63;0
"Unit";"Queen";"Hatchery";57;2
"Building";"Extractor";NA;63;0
"Building";"CreepTumorQueen";NA;63;0
"Building";"CreepTumor";NA;63;0
"Building";"CreepTumor";NA;63;0
"Unit";"Overlord";"Larva";63;0
"Unit";"Overlord";"Larva";63;0
"Building";"CreepTumorQueen";NA;63;0
"Building";"SporeCrawler";NA;63;0
"Unit";"Zergling";"Larva";63;1
"Unit";"Zergling";"Larva";63;1
"Unit";"Zergling";"Larva";63;1
"Unit";"Zergling";"Larva";63;1
"Unit";"Zergling";"Larva";63;1
"Unit";"Zergling";"Larva";63;1
"Unit";"Zergling";"Larva";63;1
"Unit";"Zergling";"Larva";63;1
"Unit";"Zergling";"Larva";63;1
"Unit";"Zergling";"Larva";63;1
"Unit";"Zergling";"Larva";63;1
"Unit";"Zergling";"Larva";63;1
"Unit";"Zergling";"Larva";63;1
"Unit";"Zergling";"Larva";63;1
"Unit";"Queen";"Hatchery";63;2
"Building";"SporeCrawler";NA;65;0
"Building";"SporeCrawler";NA;65;0
"Building";"EvolutionChamber";NA;65;0
"Building";"EvolutionChamber";NA;65;0
"Building";"CreepTumorQueen";NA;82;0
"Building";"CreepTumorQueen";NA;82;0
"Building";"CreepTumor";NA;82;0
"Unit";"Queen";"Hatchery";82;2
"Building";"CreepTumor";NA;98;0
"Building";"CreepTumor";NA;98;0
"Building";"CreepTumorQueen";NA;98;0
"Building";"CreepTumorQueen";NA;98;0
"Building";"CreepTumorQueen";NA;100;0
"Building";"CreepTumor";NA;98;0
"Building";"CreepTumor";NA;98;0
"Building";"CreepTumor";NA;98;0
"Building";"CreepTumorQueen";NA;100;0
"Building";"Extractor";NA;106;0
"Building";"Extractor";NA;106;0
"Building";"BanelingNest";NA;98;0
"Unit";"Overlord";"Larva";112;0
"Unit";"Overlord";"Larva";112;0
"Building";"CreepTumor";NA;113;0
"Building";"CreepTumor";NA;113;0
"Building";"CreepTumor";NA;113;0
"Building";"Extractor";NA;113;0
"Unit";"Overlord";"Larva";113;0
"Unit";"Overlord";"Larva";113;0
"Unit";"Overlord";"Larva";113;0
"Unit";"Overlord";"Larva";113;0
"Unit";"Overlord";"Larva";113;0
"Unit";"Queen";"Hatchery";113;2
"Unit";"Overlord";"Larva";113;0
"Building";"Extractor";NA;113;0
"Unit";"Zergling";"Larva";122;1
"Unit";"Zergling";"Larva";122;1
"Unit";"Zergling";"Larva";122;1
"Unit";"Zergling";"Larva";122;1
"Unit";"Zergling";"Larva";122;1
"Unit";"Zergling";"Larva";122;1
"Unit";"Zergling";"Larva";122;1
"Unit";"Zergling";"Larva";122;1
"Unit";"Zergling";"Larva";122;1
"Unit";"Zergling";"Larva";122;1
"Unit";"Zergling";"Larva";122;1
"Unit";"Zergling";"Larva";122;1
"Building";"SporeCrawler";NA;122;0
"Unit";"Zergling";"Larva";124;1
"Unit";"Zergling";"Larva";124;1
"Building";"InfestationPit";NA;122;0
"Unit";"Zergling";"Larva";124;1
"Unit";"Zergling";"Larva";124;1
"Unit";"Zergling";"Larva";124;1
"Unit";"Zergling";"Larva";124;1
"Unit";"Zergling";"Larva";124;1
"Unit";"Zergling";"Larva";124;1
"Unit";"Zergling";"Larva";124;1
"Unit";"Zergling";"Larva";124;1
"Unit";"Zergling";"Larva";124;1
"Unit";"Zergling";"Larva";124;1
"Upgrade";"ZergMeleeWeaponsLevel1";"EvolutionChamber";112;0
"Upgrade";"ZergGroundArmorsLevel1";"EvolutionChamber";112;0
"Building";"CreepTumor";NA;136;0
"Unit";"Zergling";"Larva";136;1
"Unit";"Zergling";"Larva";136;1
"Unit";"Zergling";"Larva";136;1
"Unit";"Zergling";"Larva";136;1
"Unit";"Zergling";"Larva";136;1
"Unit";"Zergling";"Larva";136;1
"Unit";"Zergling";"Larva";136;1
"Unit";"Zergling";"Larva";136;1
"Building";"CreepTumor";NA;136;0
"Building";"CreepTumor";NA;136;0
"Building";"CreepTumor";NA;136;0
"Building";"CreepTumor";NA;136;0
"Building";"CreepTumorQueen";NA;148;0
"Building";"CreepTumorQueen";NA;148;0
"Building";"CreepTumorQueen";NA;160;0
"Building";"CreepTumorQueen";NA;160;0
"Building";"Hatchery";NA;119;0
"Unit";"Zergling";"Larva";160;1
"Unit";"Zergling";"Larva";160;1
"Unit";"Zergling";"Larva";160;1
"Unit";"Zergling";"Larva";160;1
"Unit";"Zergling";"Larva";160;1
"Unit";"Zergling";"Larva";160;1
"Unit";"Zergling";"Larva";160;1
"Unit";"Zergling";"Larva";160;1
"Unit";"Zergling";"Larva";160;1
"Unit";"Zergling";"Larva";160;1
"Unit";"Zergling";"Larva";160;1
"Unit";"Zergling";"Larva";160;1
"Unit";"Zergling";"Larva";160;1
"Unit";"Zergling";"Larva";160;1
"Unit";"Zergling";"Larva";160;1
"Unit";"Zergling";"Larva";160;1
"Unit";"Zergling";"Larva";160;1
"Unit";"Zergling";"Larva";160;1
"Unit";"Zergling";"Larva";160;1
"Unit";"Zergling";"Larva";160;1
"Unit";"Zergling";"Larva";160;1
"Unit";"Zergling";"Larva";160;1
"Unit";"Zergling";"Larva";160;1
"Unit";"Zergling";"Larva";160;1
"Unit";"Baneling";"Zergling";160;0
"Unit";"Baneling";"Zergling";160;0
"Unit";"Baneling";"Zergling";160;0
"Unit";"Baneling";"Zergling";160;0
"Unit";"Baneling";"Zergling";160;0
"Unit";"Baneling";"Zergling";160;0
"Unit";"Baneling";"Zergling";160;0
"Unit";"Baneling";"Zergling";160;0
"Unit";"Baneling";"Zergling";160;0
"Unit";"Baneling";"Zergling";160;0
"Unit";"Baneling";"Zergling";160;0
"Unit";"Baneling";"Zergling";160;0
"Building";"CreepTumor";NA;160;0
"Building";"CreepTumor";NA;160;0
"Building";"CreepTumor";NA;184;0
"Building";"CreepTumor";NA;184;0
"Building";"CreepTumor";NA;184;0
"Building";"CreepTumor";NA;184;0
"Building";"CreepTumorQueen";NA;184;0
"Building";"CreepTumorQueen";NA;184;0
"Building";"CreepTumor";NA;184;0
"Building";"CreepTumor";NA;184;0
"Building";"CreepTumorQueen";NA;184;0
"Building";"CreepTumor";NA;184;0
"Building";"CreepTumor";NA;184;0
"Building";"CreepTumor";NA;184;0
"Unit";"Queen";"Hatchery";184;2
"Unit";"Zergling";"Larva";197;1
"Unit";"Zergling";"Larva";197;1
"Unit";"Zergling";"Larva";197;1
"Unit";"Zergling";"Larva";197;1
"Unit";"Zergling";"Larva";197;1
"Unit";"Zergling";"Larva";197;1
"Unit";"Zergling";"Larva";197;1
"Unit";"Zergling";"Larva";197;1
"Unit";"Zergling";"Larva";197;1
"Unit";"Zergling";"Larva";197;1
"Unit";"Zergling";"Larva";197;1
"Unit";"Zergling";"Larva";197;1
"Unit";"Zergling";"Larva";197;1
"Unit";"Zergling";"Larva";197;1
"Unit";"Zergling";"Larva";197;1
"Unit";"Zergling";"Larva";197;1
"Building";"Hatchery";NA;160;0
"Unit";"Zergling";"Larva";197;1
"Unit";"Zergling";"Larva";197;1
"Unit";"Zergling";"Larva";197;1
"Unit";"Zergling";"Larva";197;1
"Unit";"Zergling";"Larva";197;1
"Unit";"Zergling";"Larva";197;1
"Building";"CreepTumor";NA;197;0
"Building";"CreepTumor";NA;197;0
"Building";"CreepTumor";NA;197;0
"Unit";"Baneling";"Zergling";197;0
"Unit";"Baneling";"Zergling";197;0
"Unit";"Baneling";"Zergling";197;0
"Unit";"Baneling";"Zergling";197;0
"Unit";"Baneling";"Zergling";197;0
"Unit";"Baneling";"Zergling";197;0
"Unit";"Baneling";"Zergling";197;0
"Unit";"Baneling";"Zergling";197;0
"Unit";"Baneling";"Zergling";197;0
"Unit";"Baneling";"Zergling";197;0
"Building";"CreepTumor";NA;199;0
"Building";"CreepTumor";NA;199;0
"Building";"CreepTumor";NA;199;0
"Building";"HydraliskDen";NA;197;0
"Unit";"Zergling";"Larva";197;1
"Unit";"Zergling";"Larva";197;1
"Unit";"Zergling";"Larva";197;1
"Unit";"Zergling";"Larva";197;1
"Unit";"Zergling";"Larva";197;1
"Unit";"Zergling";"Larva";197;1
"Unit";"Zergling";"Larva";197;1
"Unit";"Zergling";"Larva";197;1
"Unit";"Zergling";"Larva";197;1
"Unit";"Zergling";"Larva";197;1
"Unit";"Zergling";"Larva";197;1
"Unit";"Zergling";"Larva";197;1
"Unit";"Zergling";"Larva";197;1
"Unit";"Zergling";"Larva";197;1
"Unit";"Zergling";"Larva";197;1
"Unit";"Zergling";"Larva";197;1
"Unit";"Zergling";"Larva";197;1
"Unit";"Zergling";"Larva";197;1
"Building";"CreepTumor";NA;215;0
"Building";"CreepTumor";NA;215;0
"Building";"CreepTumor";NA;215;0
"Unit";"Zergling";"Larva";221;1
"Unit";"Zergling";"Larva";221;1
"Unit";"Zergling";"Larva";221;1
"Unit";"Zergling";"Larva";221;1
"Unit";"Zergling";"Larva";221;1
"Unit";"Zergling";"Larva";221;1
"Unit";"Zergling";"Larva";221;1
"Unit";"Zergling";"Larva";221;1
"Unit";"Zergling";"Larva";221;1
"Unit";"Zergling";"Larva";221;1
"Unit";"Zergling";"Larva";221;1
"Unit";"Zergling";"Larva";221;1
"Unit";"Zergling";"Larva";221;1
"Unit";"Zergling";"Larva";221;1
"Unit";"Zergling";"Larva";221;1
"Unit";"Zergling";"Larva";221;1
"Unit";"Zergling";"Larva";221;1
"Unit";"Zergling";"Larva";221;1
"Unit";"Hydralisk";"Larva";239;2
"Unit";"Hydralisk";"Larva";239;2
"Unit";"Hydralisk";"Larva";239;2
"Unit";"Hydralisk";"Larva";239;2
"Unit";"Overlord";"Larva";257;0
"Unit";"Overlord";"Larva";257;0
"Unit";"Overlord";"Larva";257;0
"Building";"CreepTumor";NA;257;0
"Building";"CreepTumor";NA;257;0
"Unit";"Overlord";"Larva";257;0
"Unit";"Overlord";"Larva";257;0
"Unit";"Overlord";"Larva";257;0
"Unit";"Hydralisk";"Larva";257;2
"Upgrade";"ZergMeleeWeaponsLevel2";"EvolutionChamber";184;0
"Upgrade";"ZergGroundArmorsLevel2";"EvolutionChamber";184;0
"Unit";"Zergling";"Larva";265;1
"Unit";"Zergling";"Larva";265;1
"Unit";"Zergling";"Larva";265;1
"Unit";"Zergling";"Larva";265;1
"Unit";"Zergling";"Larva";265;1
"Unit";"Zergling";"Larva";265;1
"Unit";"Zergling";"Larva";265;1
"Unit";"Zergling";"Larva";265;1
"Unit";"Zergling";"Larva";265;1
"Unit";"Zergling";"Larva";265;1
"Unit";"Zergling";"Larva";265;1
"Unit";"Zergling";"Larva";265;1
"Unit";"Zergling";"Larva";265;1
"Unit";"Zergling";"Larva";265;1
"Unit";"Zergling";"Larva";265;1
"Unit";"Zergling";"Larva";265;1
"Unit";"Zergling";"Larva";265;1
"Unit";"Zergling";"Larva";265;1
"Unit";"Zergling";"Larva";265;1
"Unit";"Zergling";"Larva";265;1
"Unit";"Zergling";"Larva";265;1
"Unit";"Zergling";"Larva";265;1
"Unit";"Zergling";"Larva";265;1
"Unit";"Zergling";"Larva";265;1
"Unit";"Zergling";"Larva";265;1
"Unit";"Zergling";"Larva";265;1
"Unit";"Zergling";"Larva";265;1
"Unit";"Zergling";"Larva";265;1
"Unit";"Zergling";"Larva";265;1
"Unit";"Zergling";"Larva";265;1
"Unit";"Zergling";"Larva";265;1
"Unit";"Zergling";"Larva";265;1
"Unit";"Zergling";"Larva";265;1
"Unit";"Zergling";"Larva";265;1
"Building";"CreepTumorQueen";NA;267;0
"Building";"Extractor";NA;267;0
"Unit";"Zergling";"Larva";267;1
"Unit";"Zergling";"Larva";267;1
"Unit";"Zergling";"Larva";267;1
"Unit";"Zergling";"Larva";267;1
"Unit";"Zergling";"Larva";267;1
"Unit";"Zergling";"Larva";267;1
"Unit";"Zergling";"Larva";267;1
"Unit";"Zergling";"Larva";267;1
"Unit";"Zergling";"Larva";267;1
"Unit";"Zergling";"Larva";267;1
"Unit";"Zergling";"Larva";267;1
"Unit";"Zergling";"Larva";267;1
"Unit";"Zergling";"Larva";267;1
"Unit";"Zergling";"Larva";267;1
"Unit";"Zergling";"Larva";267;1
"Unit";"Zergling";"Larva";267;1
"Unit";"Zergling";"Larva";267;1
"Unit";"Zergling";"Larva";267;1
"Building";"Extractor";NA;267;0
"Unit";"Baneling";"Zergling";301;0
"Unit";"Baneling";"Zergling";301;0
"Unit";"Baneling";"Zergling";301;0
"Unit";"Baneling";"Zergling";301;0
"Unit";"Baneling";"Zergling";301;0
"Unit";"Baneling";"Zergling";301;0
"Unit";"Baneling";"Zergling";301;0
"Unit";"Baneling";"Zergling";301;0
"Unit";"Baneling";"Zergling";301;0
"Unit";"Baneling";"Zergling";301;0
"Unit";"Baneling";"Zergling";301;0
"Unit";"Baneling";"Zergling";301;0
"Unit";"Baneling";"Zergling";301;0
"Unit";"Baneling";"Zergling";301;0
"Unit";"Baneling";"Zergling";301;0
"Unit";"Baneling";"Zergling";301;0
"Unit";"Baneling";"Zergling";301;0
"Building";"Spire";NA;257;0
"Unit";"Hydralisk";"Larva";301;2
"Unit";"Hydralisk";"Larva";301;2
"Unit";"Hydralisk";"Larva";301;2
"Unit";"Hydralisk";"Larva";301;2
"Unit";"Hydralisk";"Larva";301;2
"Unit";"Hydralisk";"Larva";301;2
"Unit";"Hydralisk";"Larva";301;2
"Unit";"Zergling";"Larva";319;1
"Unit";"Zergling";"Larva";319;1
"Unit";"Zergling";"Larva";319;1
"Unit";"Zergling";"Larva";319;1
"Unit";"Zergling";"Larva";319;1
"Unit";"Zergling";"Larva";319;1
"Unit";"Zergling";"Larva";319;1
"Unit";"Zergling";"Larva";319;1
"Unit";"Zergling";"Larva";319;1
"Unit";"Zergling";"Larva";319;1
"Unit";"Zergling";"Larva";319;1
"Unit";"Zergling";"Larva";319;1
"Unit";"Zergling";"Larva";319;1
"Unit";"Zergling";"Larva";319;1
"Unit";"Zergling";"Larva";319;1
"Unit";"Zergling";"Larva";319;1
"Unit";"Zergling";"Larva";319;1
"Unit";"Zergling";"Larva";319;1
"Unit";"Zergling";"Larva";319;1
"Unit";"Zergling";"Larva";319;1
"Unit";"Zergling";"Larva";319;1
"Unit";"Zergling";"Larva";319;1
"Unit";"Baneling";"Zergling";333;0
"Unit";"Zergling";"Larva";323;1
"Unit";"Zergling";"Larva";323;1
"Unit";"Baneling";"Zergling";333;0
"Unit";"Baneling";"Zergling";333;0
"Unit";"Baneling";"Zergling";333;0
"Unit";"Baneling";"Zergling";333;0
"Unit";"Baneling";"Zergling";333;0
"Unit";"Zergling";"Larva";323;1
"Unit";"Zergling";"Larva";323;1
"Unit";"Zergling";"Larva";323;1
"Unit";"Zergling";"Larva";323;1
"Unit";"Zergling";"Larva";323;1
"Unit";"Zergling";"Larva";323;1
"Unit";"Baneling";"Zergling";333;0
"Unit";"Baneling";"Zergling";333;0
"Unit";"Zergling";"Larva";323;1
"Unit";"Zergling";"Larva";323;1
"Unit";"Zergling";"Larva";323;1
"Unit";"Zergling";"Larva";323;1
"Unit";"Zergling";"Larva";323;1
"Unit";"Zergling";"Larva";323;1
"Unit";"Zergling";"Larva";323;1
"Unit";"Zergling";"Larva";323;1
"Unit";"Zergling";"Larva";323;1
"Unit";"Zergling";"Larva";323;1
"Building";"CreepTumor";NA;355;0
"Building";"CreepTumor";NA;355;0
"Building";"CreepTumor";NA;355;0
"Unit";"Zergling";"Larva";355;1
"Unit";"Zergling";"Larva";355;1
"Unit";"Zergling";"Larva";355;1
"Unit";"Zergling";"Larva";355;1
"Unit";"Zergling";"Larva";355;1
"Unit";"Zergling";"Larva";355;1
"Unit";"Zergling";"Larva";355;1
"Unit";"Zergling";"Larva";355;1
"Unit";"Zergling";"Larva";355;1
"Unit";"Zergling";"Larva";355;1
"Unit";"Zergling";"Larva";355;1
"Unit";"Zergling";"Larva";355;1
"Unit";"Zergling";"Larva";379;1
"Unit";"Zergling";"Larva";379;1
"Unit";"Zergling";"Larva";379;1
"Unit";"Zergling";"Larva";379;1
"Unit";"Zergling";"Larva";379;1
"Unit";"Zergling";"Larva";379;1
"Unit";"Zergling";"Larva";379;1
"Unit";"Zergling";"Larva";379;1
"Unit";"Zergling";"Larva";379;1
"Unit";"Zergling";"Larva";379;1
"Unit";"Zergling";"Larva";379;1
"Unit";"Zergling";"Larva";379;1
"Unit";"Zergling";"Larva";379;1
"Unit";"Zergling";"Larva";379;1
"Unit";"Zergling";"Larva";379;1
"Unit";"Zergling";"Larva";379;1
"Unit";"Zergling";"Larva";379;1
"Unit";"Zergling";"Larva";379;1
"Unit";"Zergling";"Larva";379;1
"Unit";"Zergling";"Larva";379;1
"Unit";"Zergling";"Larva";379;1
"Unit";"Zergling";"Larva";379;1
"Unit";"Zergling";"Larva";379;1
"Unit";"Zergling";"Larva";379;1
"Unit";"Zergling";"Larva";379;1
"Unit";"Zergling";"Larva";379;1
"Unit";"Zergling";"Larva";379;1
"Unit";"Zergling";"Larva";379;1
"Unit";"Zergling";"Larva";379;1
"Unit";"Zergling";"Larva";379;1
"Unit";"Zergling";"Larva";379;1
"Unit";"Zergling";"Larva";379;1
"Unit";"Zergling";"Larva";379;1
"Unit";"Zergling";"Larva";379;1
"Unit";"Zergling";"Larva";379;1
"Unit";"Zergling";"Larva";379;1
"Unit";"Zergling";"Larva";379;1
"Unit";"Zergling";"Larva";379;1
"Unit";"Zergling";"Larva";379;1
"Unit";"Zergling";"Larva";379;1
"Building";"CreepTumor";NA;385;0
"Building";"CreepTumor";NA;385;0
"Building";"CreepTumorQueen";NA;385;0
"Building";"CreepTumorQueen";NA;385;0
"Building";"CreepTumorQueen";NA;385;0
"Building";"CreepTumorQueen";NA;385;0
"Building";"CreepTumorQueen";NA;385;0
"Building";"CreepTumorQueen";NA;385;0
"Building";"CreepTumorQueen";NA;425;0
"Building";"CreepTumorQueen";NA;425;0
"Building";"CreepTumor";NA;425;0
"Building";"CreepTumorQueen";NA;425;0
"Unit";"Baneling";"Zergling";425;0
"Building";"CreepTumor";NA;425;0
"Unit";"Baneling";"Zergling";425;0
"Unit";"Baneling";"Zergling";425;0
"Unit";"Baneling";"Zergling";425;0
"Unit";"Baneling";"Zergling";425;0
"Unit";"Baneling";"Zergling";425;0
"Unit";"Baneling";"Zergling";425;0
"Unit";"Baneling";"Zergling";425;0
"Building";"CreepTumor";NA;425;0
"Building";"CreepTumor";NA;425;0
"Building";"CreepTumorQueen";NA;425;0
"Building";"CreepTumor";NA;425;0
"Building";"CreepTumorQueen";NA;425;0
"Building";"CreepTumor";NA;425;0
"Unit";"Zergling";"Larva";425;1
"Unit";"Zergling";"Larva";425;1
"Unit";"Zergling";"Larva";425;1
"Unit";"Zergling";"Larva";425;1
"Unit";"Zergling";"Larva";425;1
"Unit";"Zergling";"Larva";425;1
"Unit";"Zergling";"Larva";425;1
"Unit";"Zergling";"Larva";425;1
"Unit";"Zergling";"Larva";425;1
"Unit";"Zergling";"Larva";425;1
"Unit";"Zergling";"Larva";425;1
"Unit";"Zergling";"Larva";425;1
"Unit";"Zergling";"Larva";425;1
"Unit";"Zergling";"Larva";425;1
"Unit";"Zergling";"Larva";425;1
"Unit";"Zergling";"Larva";425;1
"Unit";"Zergling";"Larva";425;1
"Unit";"Zergling";"Larva";425;1
"Unit";"Zergling";"Larva";425;1
"Unit";"Zergling";"Larva";425;1
"Unit";"Zergling";"Larva";425;1
"Unit";"Zergling";"Larva";425;1
"Unit";"Zergling";"Larva";425;1
"Unit";"Zergling";"Larva";425;1
"Unit";"Zergling";"Larva";425;1
"Unit";"Zergling";"Larva";425;1
"Upgrade";"EvolveMuscularAugments";"HydraliskDen";379;0
"Building";"CreepTumor";NA;425;0
"Building";"CreepTumor";NA;425;0
"Building";"CreepTumor";NA;425;0
"Building";"CreepTumor";NA;425;0
"Building";"CreepTumor";NA;425;0
"Building";"CreepTumor";NA;425;0
"Building";"CreepTumor";NA;425;0
"Building";"CreepTumor";NA;425;0
"Unit";"Zergling";"Larva";451;1
"Unit";"Zergling";"Larva";451;1
"Unit";"Zergling";"Larva";451;1
"Unit";"Zergling";"Larva";451;1
"Unit";"Zergling";"Larva";451;1
"Unit";"Zergling";"Larva";451;1
"Unit";"Zergling";"Larva";451;1
"Unit";"Zergling";"Larva";451;1
"Unit";"Zergling";"Larva";451;1
"Unit";"Zergling";"Larva";451;1
"Unit";"Zergling";"Larva";451;1
"Unit";"Zergling";"Larva";451;1
"Unit";"Zergling";"Larva";451;1
"Unit";"Zergling";"Larva";451;1
"Unit";"Zergling";"Larva";451;1
"Unit";"Zergling";"Larva";451;1
"Unit";"Zergling";"Larva";451;1
"Unit";"Zergling";"Larva";451;1
"Unit";"Zergling";"Larva";451;1
"Unit";"Zergling";"Larva";451;1
"Unit";"Zergling";"Larva";451;1
"Unit";"Zergling";"Larva";451;1
"Unit";"Zergling";"Larva";451;1
"Unit";"Zergling";"Larva";451;1
"Unit";"Zergling";"Larva";451;1
"Unit";"Zergling";"Larva";451;1
"Unit";"Zergling";"Larva";451;1
"Unit";"Zergling";"Larva";451;1
"Unit";"Zergling";"Larva";451;1
"Unit";"Zergling";"Larva";451;1
"Unit";"Hydralisk";"Larva";451;2
"Unit";"Hydralisk";"Larva";451;2
"Unit";"Hydralisk";"Larva";451;2
"Unit";"Hydralisk";"Larva";451;2
"Unit";"Hydralisk";"Larva";451;2
"Unit";"Hydralisk";"Larva";451;2
"Upgrade";"ZergMeleeWeaponsLevel3";"EvolutionChamber";333;0
"Upgrade";"ZergGroundArmorsLevel3";"EvolutionChamber";333;0
"Building";"CreepTumor";NA;493;0
"Building";"CreepTumor";NA;493;0
"Building";"CreepTumor";NA;493;0
"Building";"CreepTumor";NA;493;0
"Building";"CreepTumor";NA;493;0
"Building";"CreepTumor";NA;493;0
"Building";"CreepTumor";NA;493;0
"Building";"CreepTumor";NA;493;0
"Building";"CreepTumor";NA;493;0
"Building";"CreepTumor";NA;493;0
"Building";"CreepTumor";NA;493;0
"Unit";"Corruptor";"Larva";493;2
"Unit";"Corruptor";"Larva";493;2
"Unit";"Corruptor";"Larva";493;2
"Unit";"Corruptor";"Larva";493;2
"Unit";"Corruptor";"Larva";493;2
"Unit";"Corruptor";"Larva";493;2
"Unit";"Corruptor";"Larva";493;2
"Unit";"Corruptor";"Larva";493;2
"Unit";"Baneling";"Zergling";493;0
"Unit";"Baneling";"Zergling";493;0
"Unit";"Baneling";"Zergling";493;0
"Unit";"Baneling";"Zergling";493;0
"Unit";"Baneling";"Zergling";493;0
"Unit";"Baneling";"Zergling";493;0
"Unit";"Baneling";"Zergling";493;0
"Unit";"Baneling";"Zergling";493;0
"Unit";"Zergling";"Larva";493;1
"Unit";"Zergling";"Larva";493;1
"Unit";"Zergling";"Larva";493;1
"Unit";"Zergling";"Larva";493;1
"Unit";"Zergling";"Larva";493;1
"Unit";"Zergling";"Larva";493;1
"Unit";"Zergling";"Larva";493;1
"Unit";"Zergling";"Larva";493;1
"Unit";"Zergling";"Larva";493;1
"Unit";"Zergling";"Larva";493;1
"Unit";"Zergling";"Larva";493;1
"Unit";"Zergling";"Larva";493;1
"Unit";"Zergling";"Larva";493;1
"Unit";"Zergling";"Larva";493;1
"Unit";"Zergling";"Larva";493;1
"Unit";"Zergling";"Larva";493;1
"Unit";"Zergling";"Larva";493;1
"Unit";"Zergling";"Larva";493;1
"Unit";"Zergling";"Larva";493;1
"Unit";"Zergling";"Larva";493;1
"Unit";"Zergling";"Larva";493;1
"Unit";"Zergling";"Larva";493;1
"Unit";"Zergling";"Larva";493;1
"Unit";"Zergling";"Larva";493;1
"Unit";"Zergling";"Larva";493;1
"Unit";"Zergling";"Larva";493;1
"Unit";"Zergling";"Larva";493;1
"Unit";"Zergling";"Larva";493;1
"Unit";"Zergling";"Larva";493;1
"Unit";"Zergling";"Larva";493;1
"Unit";"Zergling";"Larva";493;1
"Unit";"Zergling";"Larva";493;1
"Unit";"Zergling";"Larva";493;1
"Unit";"Zergling";"Larva";493;1
"Unit";"Zergling";"Larva";493;1
"Unit";"Zergling";"Larva";493;1
"Upgrade";"EvolveGroovedSpines";"HydraliskDen";481;0
"Building";"CreepTumor";NA;509;0
"Building";"CreepTumor";NA;509;0
"Building";"CreepTumor";NA;509;0
"Building";"CreepTumor";NA;509;0
"Building";"CreepTumor";NA;509;0
"Building";"CreepTumor";NA;509;0
"Building";"CreepTumor";NA;509;0
"Building";"CreepTumor";NA;545;0
"Building";"CreepTumor";NA;545;0
"Unit";"Baneling";"Zergling";545;0
"Unit";"Baneling";"Zergling";545;0
"Unit";"Baneling";"Zergling";545;0
"Unit";"Baneling";"Zergling";545;0
"Unit";"Baneling";"Zergling";545;0
"Unit";"Baneling";"Zergling";545;0
"Unit";"Baneling";"Zergling";545;0
"Unit";"Baneling";"Zergling";545;0
"Unit";"Baneling";"Zergling";545;0
"Unit";"Baneling";"Zergling";545;0
"Unit";"Baneling";"Zergling";545;0
"Building";"CreepTumor";NA;545;0
"Building";"CreepTumor";NA;545;0
"Building";"CreepTumor";NA;545;0
"Building";"CreepTumor";NA;545;0
"Building";"CreepTumor";NA;545;0
"Building";"CreepTumor";NA;545;0
"Building";"Hatchery";NA;493;0
"Building";"CreepTumor";NA;545;0
"Unit";"Zergling";"Larva";545;1
"Unit";"Zergling";"Larva";545;1
"Unit";"Zergling";"Larva";545;1
"Unit";"Zergling";"Larva";545;1
"Building";"CreepTumor";NA;545;0
"Building";"CreepTumor";NA;545;0
"Building";"CreepTumor";NA;545;0
"Building";"CreepTumor";NA;545;0
"Building";"CreepTumor";NA;545;0
"Building";"CreepTumor";NA;545;0
"Building";"CreepTumor";NA;549;0
"Building";"CreepTumor";NA;549;0
"Unit";"Zergling";"Larva";549;1
"Unit";"Zergling";"Larva";549;1
"Unit";"Zergling";"Larva";549;1
"Unit";"Zergling";"Larva";549;1
"Building";"CreepTumor";NA;549;0
"Unit";"Overlord";"Larva";553;0
"Unit";"Overlord";"Larva";553;0
"Unit";"Overlord";"Larva";553;0
"Unit";"Overlord";"Larva";553;0
"Unit";"Zergling";"Larva";553;1
"Unit";"Zergling";"Larva";553;1
"Unit";"Zergling";"Larva";553;1
"Unit";"Zergling";"Larva";553;1
"Unit";"Zergling";"Larva";553;1
"Unit";"Zergling";"Larva";553;1
"Unit";"Zergling";"Larva";553;1
"Unit";"Zergling";"Larva";553;1
"Unit";"Zergling";"Larva";553;1
"Unit";"Zergling";"Larva";553;1
"Unit";"Zergling";"Larva";553;1
"Unit";"Zergling";"Larva";553;1
"Unit";"Zergling";"Larva";553;1
"Unit";"Zergling";"Larva";553;1
"Unit";"Zergling";"Larva";553;1
"Unit";"Zergling";"Larva";553;1
"Unit";"Zergling";"Larva";553;1
"Unit";"Zergling";"Larva";553;1
"Unit";"Zergling";"Larva";553;1
"Unit";"Zergling";"Larva";553;1
"Unit";"Zergling";"Larva";553;1
"Unit";"Zergling";"Larva";553;1
"Unit";"Zergling";"Larva";553;1
"Unit";"Zergling";"Larva";553;1
"Unit";"Zergling";"Larva";553;1
"Unit";"Zergling";"Larva";553;1
"Unit";"Zergling";"Larva";553;1
"Unit";"Zergling";"Larva";553;1
"Unit";"Zergling";"Larva";553;1
"Unit";"Zergling";"Larva";553;1
"Unit";"Zergling";"Larva";553;1
"Unit";"Zergling";"Larva";553;1
"Unit";"Zergling";"Larva";553;1
"Unit";"Zergling";"Larva";553;1
"Unit";"Zergling";"Larva";553;1
"Unit";"Zergling";"Larva";553;1
"Unit";"Zergling";"Larva";553;1
"Unit";"Zergling";"Larva";553;1
"Unit";"Zergling";"Larva";553;1
"Unit";"Zergling";"Larva";553;1
"Unit";"Zergling";"Larva";553;1
"Unit";"Zergling";"Larva";553;1
"Unit";"Zergling";"Larva";553;1
"Unit";"Zergling";"Larva";553;1
"Unit";"Zergling";"Larva";553;1
"Unit";"Zergling";"Larva";553;1
"Unit";"Zergling";"Larva";553;1
"Unit";"Zergling";"Larva";553;1
"Unit";"Zergling";"Larva";553;1
"Unit";"Zergling";"Larva";553;1
"Unit";"Zergling";"Larva";553;1
"Unit";"Zergling";"Larva";553;1
"Building";"CreepTumor";NA;556;0
"Building";"CreepTumor";NA;556;0
"Unit";"Zergling";"Larva";556;1
"Unit";"Zergling";"Larva";556;1
"Building";"CreepTumor";NA;610;0
"Building";"CreepTumor";NA;610;0
"Building";"SporeCrawler";NA;610;0
"Building";"SporeCrawler";NA;610;0
"Building";"SporeCrawler";NA;610;0
"Building";"SporeCrawler";NA;610;0
"Building";"SporeCrawler";NA;610;0
"Building";"SporeCrawler";NA;610;0
"Building";"CreepTumor";NA;610;0
"Building";"CreepTumor";NA;610;0
"Unit";"Zergling";"Larva";610;1
"Unit";"Zergling";"Larva";610;1
"Unit";"Zergling";"Larva";610;1
"Unit";"Zergling";"Larva";610;1
"Unit";"Zergling";"Larva";610;1
"Unit";"Zergling";"Larva";610;1
"Unit";"Zergling";"Larva";610;1
"Unit";"Zergling";"Larva";610;1
"Unit";"Zergling";"Larva";610;1
"Unit";"Zergling";"Larva";610;1
"Unit";"Zergling";"Larva";610;1
"Unit";"Zergling";"Larva";610;1
"Unit";"Zergling";"Larva";610;1
"Unit";"Zergling";"Larva";610;1
"Unit";"Zergling";"Larva";610;1
"Unit";"Zergling";"Larva";610;1
"Unit";"Zergling";"Larva";610;1
"Unit";"Zergling";"Larva";610;1
"Unit";"Zergling";"Larva";610;1
"Unit";"Zergling";"Larva";610;1
"Unit";"Zergling";"Larva";610;1
"Unit";"Zergling";"Larva";610;1
"Unit";"Zergling";"Larva";610;1
"Unit";"Zergling";"Larva";610;1
"Unit";"Zergling";"Larva";610;1
"Unit";"Zergling";"Larva";610;1
"Unit";"Zergling";"Larva";610;1
"Unit";"Zergling";"Larva";610;1
"Unit";"Zergling";"Larva";610;1
"Unit";"Zergling";"Larva";610;1
"Unit";"Zergling";"Larva";610;1
"Unit";"Zergling";"Larva";610;1
"Unit";"Zergling";"Larva";610;1
"Unit";"Zergling";"Larva";610;1
"Unit";"Zergling";"Larva";610;1
"Unit";"Zergling";"Larva";610;1
"Unit";"Zergling";"Larva";610;1
"Unit";"Zergling";"Larva";610;1
"Unit";"Zergling";"Larva";610;1
"Unit";"Zergling";"Larva";610;1
"Building";"CreepTumor";NA;610;0
"Unit";"Corruptor";"Larva";650;2
"Unit";"Corruptor";"Larva";650;2
"Unit";"Corruptor";"Larva";650;2
"Unit";"Corruptor";"Larva";650;2
"Unit";"Corruptor";"Larva";650;2
"Unit";"Corruptor";"Larva";650;2
"Unit";"Corruptor";"Larva";650;2
"Unit";"Corruptor";"Larva";650;2
"Unit";"Corruptor";"Larva";650;2
"Unit";"Corruptor";"Larva";650;2
"Unit";"Corruptor";"Larva";650;2
"Unit";"Corruptor";"Larva";650;2
"Unit";"Zergling";"Larva";650;1
"Unit";"Zergling";"Larva";650;1
"Unit";"Zergling";"Larva";650;1
"Unit";"Zergling";"Larva";650;1
"Unit";"Zergling";"Larva";650;1
"Unit";"Zergling";"Larva";650;1
"Unit";"Zergling";"Larva";650;1
"Unit";"Zergling";"Larva";650;1
"Unit";"Zergling";"Larva";650;1
"Unit";"Zergling";"Larva";650;1
"Unit";"Zergling";"Larva";650;1
"Unit";"Zergling";"Larva";650;1
"Unit";"Zergling";"Larva";650;1
"Unit";"Zergling";"Larva";650;1
"Building";"CreepTumor";NA;650;0
"Building";"CreepTumor";NA;650;0
"Unit";"Zergling";"Larva";688;1
"Unit";"Zergling";"Larva";688;1
"Unit";"Zergling";"Larva";688;1
"Unit";"Zergling";"Larva";688;1
"Unit";"Zergling";"Larva";688;1
"Unit";"Zergling";"Larva";688;1
"Unit";"Zergling";"Larva";688;1
"Unit";"Zergling";"Larva";688;1
"Unit";"Zergling";"Larva";688;1
"Unit";"Zergling";"Larva";688;1
"Unit";"Zergling";"Larva";688;1
"Unit";"Zergling";"Larva";688;1
"Unit";"Zergling";"Larva";688;1
"Unit";"Zergling";"Larva";688;1
"Unit";"Zergling";"Larva";688;1
"Unit";"Zergling";"Larva";688;1
"Unit";"Hydralisk";"Larva";688;2
"Unit";"Hydralisk";"Larva";688;2
"Unit";"Hydralisk";"Larva";688;2
"Unit";"Hydralisk";"Larva";688;2
"Building";"Hatchery";NA;650;0
"Unit";"Zergling";"Larva";712;1
"Unit";"Zergling";"Larva";712;1
"Unit";"Zergling";"Larva";712;1
"Unit";"Zergling";"Larva";712;1
"Unit";"Corruptor";"Larva";704;2
"Unit";"Corruptor";"Larva";704;2
"Unit";"Corruptor";"Larva";704;2
"Unit";"Corruptor";"Larva";704;2
"Unit";"Corruptor";"Larva";706;2
"Unit";"Corruptor";"Larva";706;2
"Unit";"Corruptor";"Larva";706;2
"Unit";"Corruptor";"Larva";706;2
