"type";"unit_name";"on_building";"total_supply";"supply"
"Unit";"Overlord";"Larva";13;0
"Building";"Extractor";NA;18;0
"Unit";"Overlord";"Larva";21;0
"Building";"SpawningPool";NA;19;0
"Building";"Hatchery";NA;17;0
"Unit";"Zergling";"Larva";22;1
"Unit";"Zergling";"Larva";22;1
"Unit";"Zergling";"Larva";22;1
"Unit";"Zergling";"Larva";22;1
"Unit";"Queen";"Hatchery";22;2
"Unit";"Queen";"Hatchery";22;2
"Unit";"Overlord";"Larva";36;0
"Unit";"Queen";"Hatchery";35;2
"Building";"CreepTumorQueen";NA;38;0
"Unit";"Overlord";"Larva";49;0
"Unit";"Overlord";"Larva";49;0
"Building";"CreepTumor";NA;49;0
"Building";"CreepTumorQueen";NA;49;0
"Unit";"Queen";"Hatchery";49;2
"Building";"Extractor";NA;49;0
"Unit";"Zergling";"Larva";49;1
"Unit";"Zergling";"Larva";49;1
"Unit";"Zergling";"Larva";49;1
"Unit";"Zergling";"Larva";49;1
"Unit";"Zergling";"Larva";49;1
"Unit";"Zergling";"Larva";49;1
"Building";"EvolutionChamber";NA;49;0
"Building";"EvolutionChamber";NA;49;0
"Building";"CreepTumor";NA;49;0
"Building";"Hatchery";NA;38;0
"Unit";"Overlord";"Larva";49;0
"Building";"CreepTumorQueen";NA;60;0
"Building";"SporeCrawler";NA;60;0
"Building";"SporeCrawler";NA;60;0
"Building";"CreepTumor";NA;64;0
"Building";"CreepTumor";NA;64;0
"Unit";"Zergling";"Larva";68;1
"Unit";"Zergling";"Larva";68;1
"Unit";"Zergling";"Larva";68;1
"Unit";"Zergling";"Larva";68;1
"Unit";"Zergling";"Larva";68;1
"Unit";"Zergling";"Larva";68;1
"Unit";"Overlord";"Larva";68;0
"Building";"CreepTumor";NA;68;0
"Building";"SporeCrawler";NA;68;0
"Unit";"Overlord";"Larva";71;0
"Unit";"Overlord";"Larva";71;0
"Building";"CreepTumor";NA;77;0
"Unit";"Overlord";"Larva";77;0
"Unit";"Queen";"Hatchery";77;2
"Building";"Extractor";NA;83;0
"Building";"CreepTumor";NA;85;0
"Building";"CreepTumor";NA;85;0
"Building";"RoachWarren";NA;77;0
"Building";"CreepTumorQueen";NA;90;0
"Building";"Extractor";NA;83;0
"Building";"CreepTumorQueen";NA;90;0
"Unit";"Roach";"Larva";90;2
"Unit";"Roach";"Larva";90;2
"Building";"Hatchery";NA;83;0
"Unit";"Roach";"Larva";102;2
"Unit";"Roach";"Larva";102;2
"Building";"Hatchery";NA;85;0
"Building";"CreepTumor";NA;106;0
"Building";"Extractor";NA;106;0
"Unit";"Roach";"Larva";116;2
"Unit";"Roach";"Larva";116;2
"Building";"Extractor";NA;116;0
"Unit";"Queen";"Hatchery";106;2
"Upgrade";"ZergMissileWeaponsLevel1";"EvolutionChamber";94;0
"Building";"Extractor";NA;116;0
"Upgrade";"ZergGroundArmorsLevel1";"EvolutionChamber";98;0
"Unit";"Roach";"Larva";116;2
"Unit";"Roach";"Larva";116;2
"Building";"CreepTumor";NA;122;0
"Building";"Extractor";NA;122;0
"Building";"CreepTumorQueen";NA;126;0
"Building";"CreepTumorQueen";NA;126;0
"Building";"CreepTumor";NA;126;0
"Building";"CreepTumor";NA;126;0
"Building";"CreepTumor";NA;126;0
"Building";"Hatchery";NA;106;0
"Building";"CreepTumor";NA;130;0
"Building";"InfestationPit";NA;126;0
"Unit";"Roach";"Larva";130;2
"Unit";"Roach";"Larva";130;2
"Unit";"Roach";"Larva";130;2
"Unit";"Roach";"Larva";130;2
"Unit";"Roach";"Larva";130;2
"Unit";"Overlord";"Larva";130;0
"Unit";"Overlord";"Larva";130;0
"Unit";"Overlord";"Larva";130;0
"Unit";"Queen";"Hatchery";130;2
"Unit";"Queen";"Hatchery";130;2
"Unit";"Overlord";"Larva";140;0
"Unit";"Overlord";"Larva";140;0
"Unit";"Overlord";"Larva";142;0
"Unit";"Overlord";"Larva";142;0
"Unit";"Overlord";"Larva";144;0
"Building";"CreepTumor";NA;144;0
"Unit";"Overlord";"Larva";144;0
"Unit";"Queen";"Hatchery";140;2
"Unit";"Overlord";"Larva";144;0
"Unit";"Overlord";"Larva";144;0
"Unit";"Overlord";"Larva";144;0
"Unit";"Roach";"Larva";144;2
"Unit";"Roach";"Larva";144;2
"Unit";"Roach";"Larva";144;2
"Unit";"Roach";"Larva";144;2
"Unit";"Roach";"Larva";144;2
"Unit";"Roach";"Larva";144;2
"Unit";"Roach";"Larva";144;2
"Unit";"Roach";"Larva";144;2
"Building";"CreepTumor";NA;144;0
"Building";"CreepTumor";NA;146;0
"Building";"CreepTumor";NA;146;0
"Unit";"Queen";"Hatchery";144;2
"Upgrade";"ZergMissileWeaponsLevel2";"EvolutionChamber";130;0
"Upgrade";"ZergGroundArmorsLevel2";"EvolutionChamber";130;0
"Building";"HydraliskDen";NA;144;0
"Building";"Hatchery";NA;140;0
"Building";"SporeCrawler";NA;162;0
"Building";"CreepTumor";NA;167;0
"Building";"CreepTumor";NA;167;0
"Building";"CreepTumor";NA;167;0
"Unit";"Roach";"Larva";164;2
"Unit";"Roach";"Larva";164;2
"Unit";"Roach";"Larva";164;2
"Unit";"Roach";"Larva";164;2
"Unit";"Roach";"Larva";164;2
"Unit";"Roach";"Larva";164;2
"Unit";"Roach";"Larva";164;2
"Unit";"Roach";"Larva";164;2
"Unit";"Roach";"Larva";164;2
"Unit";"Roach";"Larva";164;2
"Unit";"Roach";"Larva";164;2
"Unit";"Roach";"Larva";164;2
"Unit";"Roach";"Larva";164;2
"Unit";"Roach";"Larva";164;2
"Unit";"Roach";"Larva";164;2
"Building";"Extractor";NA;162;0
"Building";"Extractor";NA;164;0
"Building";"CreepTumor";NA;167;0
"Building";"CreepTumor";NA;167;0
"Building";"CreepTumorQueen";NA;167;0
"Building";"CreepTumorQueen";NA;167;0
"Building";"CreepTumorQueen";NA;197;0
"Unit";"Overlord";"Larva";167;0
"Unit";"Overlord";"Larva";167;0
"Unit";"Overlord";"Larva";167;0
"Upgrade";"GlialReconstitution";"RoachWarren";146;0
"Building";"CreepTumorQueen";NA;197;0
"Building";"Hatchery";NA;146;0
"Building";"CreepTumor";NA;197;0
"Building";"SporeCrawler";NA;197;0
"Building";"SpineCrawler";NA;197;0
"Building";"SpineCrawler";NA;197;0
"Upgrade";"EvolveGroovedSpines";"HydraliskDen";197;0
"Unit";"Viper";"Larva";208;3
"Unit";"Viper";"Larva";208;3
"Unit";"Viper";"Larva";208;3
"Unit";"Viper";"Larva";208;3
"Unit";"Hydralisk";"Larva";208;2
"Unit";"Hydralisk";"Larva";208;2
"Unit";"Hydralisk";"Larva";208;2
"Unit";"Hydralisk";"Larva";208;2
"Unit";"Hydralisk";"Larva";208;2
"Unit";"Hydralisk";"Larva";208;2
"Unit";"Hydralisk";"Larva";208;2
"Unit";"Hydralisk";"Larva";208;2
"Unit";"Hydralisk";"Larva";208;2
"Unit";"Hydralisk";"Larva";208;2
"Unit";"Hydralisk";"Larva";208;2
"Unit";"Hydralisk";"Larva";208;2
"Unit";"Hydralisk";"Larva";208;2
"Unit";"Hydralisk";"Larva";208;2
"Unit";"Hydralisk";"Larva";208;2
"Unit";"Hydralisk";"Larva";208;2
"Unit";"Hydralisk";"Larva";208;2
"Building";"CreepTumor";NA;208;0
"Building";"CreepTumor";NA;208;0
"Building";"CreepTumor";NA;208;0
"Building";"CreepTumor";NA;222;0
"Building";"CreepTumor";NA;254;0
"Building";"CreepTumor";NA;254;0
"Building";"CreepTumor";NA;254;0
"Building";"CreepTumor";NA;254;0
"Building";"CreepTumor";NA;254;0
"Unit";"Roach";"Larva";254;2
"Unit";"Roach";"Larva";254;2
"Unit";"Roach";"Larva";254;2
"Unit";"Roach";"Larva";254;2
"Unit";"Roach";"Larva";254;2
"Unit";"Roach";"Larva";254;2
"Unit";"Roach";"Larva";254;2
"Unit";"Roach";"Larva";254;2
"Unit";"Roach";"Larva";254;2
"Unit";"Roach";"Larva";254;2
"Unit";"Roach";"Larva";254;2
"Unit";"Roach";"Larva";254;2
"Unit";"Roach";"Larva";254;2
"Unit";"Roach";"Larva";254;2
"Unit";"Roach";"Larva";254;2
"Building";"Extractor";NA;254;0
"Building";"Extractor";NA;254;0
"Upgrade";"EvolveMuscularAugments";"HydraliskDen";254;0
"Unit";"Overlord";"Larva";254;0
"Building";"Hatchery";NA;220;0
"Building";"CreepTumor";NA;288;0
"Building";"CreepTumor";NA;289;0
"Building";"CreepTumorQueen";NA;293;0
"Building";"CreepTumorQueen";NA;293;0
"Building";"CreepTumorQueen";NA;293;0
"Building";"SporeCrawler";NA;293;0
"Building";"SporeCrawler";NA;293;0
"Building";"CreepTumor";NA;293;0
"Building";"CreepTumor";NA;293;0
"Building";"CreepTumor";NA;293;0
"Building";"Spire";NA;284;0
"Building";"CreepTumor";NA;302;0
"Building";"CreepTumor";NA;302;0
"Upgrade";"ZergMissileWeaponsLevel3";"EvolutionChamber";282;0
"Upgrade";"ZergGroundArmorsLevel3";"EvolutionChamber";284;0
"Building";"SporeCrawler";NA;312;0
"Building";"SporeCrawler";NA;312;0
"Building";"SporeCrawler";NA;312;0
"Building";"SporeCrawler";NA;312;0
"Building";"SporeCrawler";NA;312;0
"Unit";"Overlord";"Larva";315;0
"Building";"EvolutionChamber";NA;315;0
"Building";"Spire";NA;308;0
"Building";"CreepTumor";NA;315;0
"Building";"CreepTumor";NA;315;0
"Building";"CreepTumor";NA;318;0
"Building";"CreepTumor";NA;318;0
"Building";"SpineCrawler";NA;315;0
"Building";"Hatchery";NA;312;0
"Building";"CreepTumorQueen";NA;318;0
"Building";"CreepTumorQueen";NA;318;0
"Building";"CreepTumor";NA;318;0
"Building";"CreepTumor";NA;318;0
"Building";"SporeCrawler";NA;318;0
"Building";"SporeCrawler";NA;318;0
"Building";"SporeCrawler";NA;318;0
"Building";"SporeCrawler";NA;318;0
"Unit";"Corruptor";"Larva";318;2
"Unit";"Corruptor";"Larva";318;2
"Unit";"Corruptor";"Larva";318;2
"Unit";"Corruptor";"Larva";318;2
"Unit";"Corruptor";"Larva";318;2
"Unit";"Corruptor";"Larva";318;2
"Unit";"Corruptor";"Larva";318;2
"Building";"CreepTumorQueen";NA;322;0
"Building";"CreepTumorQueen";NA;322;0
"Building";"SpineCrawler";NA;318;0
"Building";"CreepTumor";NA;322;0
"Building";"CreepTumor";NA;322;0
"Building";"SporeCrawler";NA;322;0
"Building";"SporeCrawler";NA;322;0
"Building";"SporeCrawler";NA;322;0
"Building";"Hatchery";NA;318;0
"Building";"SporeCrawler";NA;322;0
"Building";"SporeCrawler";NA;322;0
"Building";"SporeCrawler";NA;322;0
"Building";"SporeCrawler";NA;322;0
"Unit";"Hydralisk";"Larva";339;2
"Unit";"Hydralisk";"Larva";339;2
"Unit";"Hydralisk";"Larva";339;2
"Unit";"Hydralisk";"Larva";339;2
"Unit";"Hydralisk";"Larva";339;2
"Unit";"Hydralisk";"Larva";339;2
"Building";"CreepTumorQueen";NA;339;0
"Building";"CreepTumorQueen";NA;339;0
"Unit";"Overlord";"Larva";339;0
"Unit";"Corruptor";"Larva";339;2
"Unit";"Corruptor";"Larva";339;2
"Unit";"Corruptor";"Larva";339;2
"Unit";"Corruptor";"Larva";339;2
"Unit";"Corruptor";"Larva";339;2
"Unit";"Corruptor";"Larva";339;2
"Building";"CreepTumor";NA;351;0
"Building";"CreepTumor";NA;351;0
"Building";"CreepTumorQueen";NA;351;0
"Building";"SporeCrawler";NA;372;0
"Building";"SporeCrawler";NA;372;0
"Building";"SporeCrawler";NA;372;0
"Building";"SporeCrawler";NA;372;0
"Building";"SporeCrawler";NA;372;0
"Building";"SporeCrawler";NA;372;0
"Building";"SporeCrawler";NA;372;0
"Building";"SporeCrawler";NA;372;0
"Building";"SporeCrawler";NA;372;0
"Building";"CreepTumor";NA;372;0
"Building";"CreepTumor";NA;372;0
"Building";"CreepTumor";NA;372;0
"Building";"CreepTumor";NA;372;0
"Building";"CreepTumor";NA;372;0
"Building";"CreepTumor";NA;372;0
"Building";"CreepTumor";NA;372;0
"Building";"Hatchery";NA;362;0
"Building";"CreepTumorQueen";NA;376;0
"Unit";"Infestor";"Larva";372;2
"Unit";"Infestor";"Larva";372;2
"Unit";"Infestor";"Larva";372;2
"Unit";"Corruptor";"Larva";382;2
"Unit";"Corruptor";"Larva";382;2
"Unit";"Corruptor";"Larva";382;2
"Unit";"Corruptor";"Larva";382;2
"Unit";"Corruptor";"Larva";382;2
"Unit";"Corruptor";"Larva";382;2
"Unit";"Corruptor";"Larva";382;2
"Unit";"Corruptor";"Larva";382;2
"Unit";"Corruptor";"Larva";382;2
"Unit";"Corruptor";"Larva";386;2
"Unit";"Corruptor";"Larva";386;2
"Unit";"Corruptor";"Larva";386;2
"Unit";"Corruptor";"Larva";386;2
"Unit";"Corruptor";"Larva";408;2
"Unit";"Corruptor";"Larva";408;2
"Unit";"Corruptor";"Larva";408;2
"Unit";"Corruptor";"Larva";408;2
"Unit";"Corruptor";"Larva";408;2
"Unit";"Corruptor";"Larva";408;2
"Unit";"Corruptor";"Larva";408;2
"Unit";"Corruptor";"Larva";408;2
"Unit";"Corruptor";"Larva";408;2
"Unit";"Corruptor";"Larva";408;2
"Unit";"Corruptor";"Larva";414;2
"Unit";"Corruptor";"Larva";414;2
"Unit";"Corruptor";"Larva";414;2
"Unit";"Corruptor";"Larva";414;2
"Unit";"Corruptor";"Larva";414;2
"Unit";"Corruptor";"Larva";414;2
"Building";"InfestationPit";NA;455;0
"Building";"Hatchery";NA;455;0
"Unit";"Infestor";"Larva";455;2
"Unit";"Infestor";"Larva";455;2
"Unit";"Infestor";"Larva";455;2
"Unit";"Corruptor";"Larva";455;2
"Unit";"Corruptor";"Larva";455;2
"Unit";"Corruptor";"Larva";455;2
"Unit";"Corruptor";"Larva";455;2
"Unit";"Corruptor";"Larva";455;2
"Unit";"Corruptor";"Larva";461;2
"Unit";"Corruptor";"Larva";461;2
"Unit";"Corruptor";"Larva";461;2
"Unit";"Corruptor";"Larva";461;2
"Unit";"Corruptor";"Larva";461;2
"Unit";"Corruptor";"Larva";461;2
"Unit";"Corruptor";"Larva";461;2
"Unit";"Infestor";"Larva";471;2
"Unit";"Infestor";"Larva";471;2
"Unit";"Infestor";"Larva";471;2
"Unit";"Infestor";"Larva";471;2
"Unit";"Corruptor";"Larva";471;2
"Unit";"Corruptor";"Larva";471;2
"Unit";"Corruptor";"Larva";471;2
"Unit";"Corruptor";"Larva";471;2
