"type";"unit_name";"on_building";"total_supply";"supply"
"Unit";"Overlord";"Larva";12;0
"Building";"Hatchery";NA;16;0
"Building";"Extractor";NA;21;0
"Building";"SpawningPool";NA;19;0
"Unit";"Zergling";"Larva";24;1
"Unit";"Zergling";"Larva";24;1
"Unit";"Zergling";"Larva";24;1
"Unit";"Zergling";"Larva";24;1
"Unit";"Overlord";"Larva";24;0
"Unit";"Queen";"Hatchery";24;2
"Unit";"Queen";"Hatchery";24;2
"Building";"Hatchery";NA;21;0
"Unit";"Zergling";"Larva";34;1
"Unit";"Zergling";"Larva";34;1
"Unit";"Zergling";"Larva";34;1
"Unit";"Zergling";"Larva";34;1
"Unit";"Overlord";"Larva";34;0
"Unit";"Queen";"Hatchery";34;2
"Building";"CreepTumorQueen";NA;40;0
"Unit";"Queen";"Hatchery";34;2
"Building";"CreepTumorQueen";NA;42;0
"Building";"CreepTumorQueen";NA;44;0
"Building";"CreepTumor";NA;50;0
"Building";"CreepTumorQueen";NA;50;0
"Building";"CreepTumor";NA;50;0
"Unit";"Queen";"Hatchery";44;2
"Building";"CreepTumor";NA;55;0
"Unit";"Overlord";"Larva";57;0
"Unit";"Overlord";"Larva";57;0
"Unit";"Overlord";"Larva";57;0
"Building";"CreepTumor";NA;57;0
"Building";"CreepTumor";NA;59;0
"Unit";"Overlord";"Larva";59;0
"Unit";"Overlord";"Larva";59;0
"Unit";"Zergling";"Larva";59;1
"Unit";"Zergling";"Larva";59;1
"Building";"CreepTumor";NA;59;0
"Building";"BanelingNest";NA;57;0
"Unit";"Zergling";"Larva";59;1
"Unit";"Zergling";"Larva";59;1
"Unit";"Zergling";"Larva";59;1
"Unit";"Zergling";"Larva";59;1
"Unit";"Zergling";"Larva";59;1
"Unit";"Zergling";"Larva";59;1
"Unit";"Zergling";"Larva";59;1
"Unit";"Zergling";"Larva";59;1
"Unit";"Zergling";"Larva";59;1
"Unit";"Zergling";"Larva";59;1
"Unit";"Zergling";"Larva";59;1
"Unit";"Zergling";"Larva";59;1
"Unit";"Zergling";"Larva";59;1
"Unit";"Zergling";"Larva";59;1
"Unit";"Zergling";"Larva";59;1
"Unit";"Zergling";"Larva";59;1
"Building";"CreepTumor";NA;61;0
"Building";"CreepTumor";NA;61;0
"Unit";"Baneling";"Zergling";61;0
"Unit";"Baneling";"Zergling";61;0
"Unit";"Baneling";"Zergling";61;0
"Unit";"Baneling";"Zergling";61;0
"Unit";"Baneling";"Zergling";61;0
"Unit";"Baneling";"Zergling";61;0
"Unit";"Baneling";"Zergling";61;0
"Unit";"Overlord";"Larva";77;0
"Unit";"Overlord";"Larva";77;0
"Building";"CreepTumorQueen";NA;77;0
"Building";"CreepTumorQueen";NA;77;0
"Building";"CreepTumorQueen";NA;77;0
"Building";"CreepTumorQueen";NA;77;0
"Building";"CreepTumor";NA;77;0
"Building";"CreepTumor";NA;77;0
"Building";"CreepTumorQueen";NA;77;0
"Building";"CreepTumorQueen";NA;80;0
"Building";"CreepTumorQueen";NA;80;0
"Unit";"Queen";"Hatchery";77;2
"Unit";"Queen";"Hatchery";77;2
"Unit";"Queen";"Hatchery";77;2
"Building";"CreepTumor";NA;80;0
"Building";"CreepTumor";NA;94;0
"Building";"CreepTumor";NA;94;0
"Building";"CreepTumor";NA;94;0
"Building";"CreepTumorQueen";NA;97;0
"Building";"CreepTumorQueen";NA;97;0
"Building";"CreepTumorQueen";NA;97;0
"Building";"CreepTumorQueen";NA;97;0
"Building";"CreepTumorQueen";NA;97;0
"Building";"Extractor";NA;94;0
"Unit";"Zergling";"Larva";97;1
"Unit";"Zergling";"Larva";97;1
"Unit";"Zergling";"Larva";97;1
"Unit";"Zergling";"Larva";97;1
"Unit";"Zergling";"Larva";97;1
"Unit";"Zergling";"Larva";97;1
"Unit";"Zergling";"Larva";97;1
"Unit";"Zergling";"Larva";97;1
"Unit";"Zergling";"Larva";97;1
"Unit";"Zergling";"Larva";97;1
"Unit";"Zergling";"Larva";97;1
"Unit";"Zergling";"Larva";97;1
"Unit";"Zergling";"Larva";97;1
"Unit";"Zergling";"Larva";97;1
"Unit";"Zergling";"Larva";97;1
"Unit";"Zergling";"Larva";97;1
"Unit";"Baneling";"Zergling";97;0
"Unit";"Baneling";"Zergling";97;0
"Unit";"Baneling";"Zergling";97;0
"Unit";"Baneling";"Zergling";97;0
"Unit";"Baneling";"Zergling";97;0
"Unit";"Baneling";"Zergling";113;0
"Unit";"Baneling";"Zergling";113;0
"Unit";"Queen";"Hatchery";97;2
"Unit";"Queen";"Hatchery";97;2
"Building";"CreepTumor";NA;123;0
"Building";"CreepTumor";NA;123;0
"Unit";"Zergling";"Larva";123;1
"Unit";"Zergling";"Larva";123;1
"Unit";"Zergling";"Larva";123;1
"Unit";"Zergling";"Larva";123;1
"Unit";"Zergling";"Larva";123;1
"Unit";"Zergling";"Larva";123;1
"Unit";"Zergling";"Larva";123;1
"Unit";"Zergling";"Larva";123;1
"Unit";"Zergling";"Larva";123;1
"Unit";"Zergling";"Larva";123;1
"Unit";"Zergling";"Larva";123;1
"Unit";"Zergling";"Larva";123;1
"Unit";"Zergling";"Larva";123;1
"Unit";"Zergling";"Larva";123;1
"Unit";"Zergling";"Larva";123;1
"Unit";"Zergling";"Larva";123;1
"Unit";"Zergling";"Larva";123;1
"Unit";"Zergling";"Larva";123;1
"Unit";"Zergling";"Larva";123;1
"Unit";"Zergling";"Larva";123;1
"Unit";"Zergling";"Larva";123;1
"Unit";"Zergling";"Larva";123;1
"Building";"Hatchery";NA;97;0
"Building";"CreepTumor";NA;145;0
"Building";"CreepTumor";NA;145;0
"Building";"CreepTumor";NA;145;0
"Building";"CreepTumor";NA;145;0
"Building";"Extractor";NA;123;0
"Building";"CreepTumor";NA;145;0
"Building";"CreepTumor";NA;145;0
"Building";"EvolutionChamber";NA;123;0
"Building";"EvolutionChamber";NA;123;0
"Building";"Extractor";NA;149;0
"Building";"CreepTumorQueen";NA;149;0
"Building";"Extractor";NA;149;0
"Building";"CreepTumorQueen";NA;156;0
"Building";"SporeCrawler";NA;149;0
"Building";"CreepTumorQueen";NA;156;0
"Building";"CreepTumorQueen";NA;156;0
"Unit";"Queen";"Hatchery";145;2
"Building";"SporeCrawler";NA;149;0
"Building";"CreepTumorQueen";NA;156;0
"Building";"CreepTumorQueen";NA;156;0
"Building";"CreepTumorQueen";NA;156;0
"Building";"CreepTumor";NA;156;0
"Unit";"Overlord";"Larva";166;0
"Unit";"Overlord";"Larva";166;0
"Unit";"Zergling";"Larva";166;1
"Unit";"Zergling";"Larva";166;1
"Unit";"Zergling";"Larva";166;1
"Unit";"Zergling";"Larva";166;1
"Unit";"Zergling";"Larva";166;1
"Unit";"Zergling";"Larva";166;1
"Building";"CreepTumor";NA;166;0
"Unit";"Overlord";"Larva";166;0
"Unit";"Zergling";"Larva";166;1
"Unit";"Zergling";"Larva";166;1
"Unit";"Zergling";"Larva";166;1
"Unit";"Zergling";"Larva";166;1
"Building";"CreepTumor";NA;166;0
"Building";"CreepTumor";NA;166;0
"Building";"CreepTumor";NA;166;0
"Building";"Extractor";NA;166;0
"Building";"CreepTumor";NA;169;0
"Building";"CreepTumor";NA;169;0
"Building";"CreepTumor";NA;169;0
"Building";"CreepTumor";NA;177;0
"Unit";"Overlord";"Larva";166;0
"Building";"CreepTumor";NA;177;0
"Unit";"Overlord";"Larva";166;0
"Building";"CreepTumor";NA;177;0
"Building";"CreepTumor";NA;177;0
"Unit";"Zergling";"Larva";177;1
"Unit";"Zergling";"Larva";177;1
"Unit";"Zergling";"Larva";177;1
"Unit";"Zergling";"Larva";177;1
"Unit";"Zergling";"Larva";177;1
"Unit";"Zergling";"Larva";177;1
"Unit";"Zergling";"Larva";177;1
"Unit";"Zergling";"Larva";177;1
"Unit";"Zergling";"Larva";177;1
"Unit";"Zergling";"Larva";177;1
"Unit";"Zergling";"Larva";177;1
"Unit";"Zergling";"Larva";177;1
"Unit";"Zergling";"Larva";177;1
"Unit";"Zergling";"Larva";177;1
"Unit";"Zergling";"Larva";177;1
"Unit";"Zergling";"Larva";177;1
"Building";"HydraliskDen";NA;166;0
"Building";"CreepTumor";NA;177;0
"Unit";"Baneling";"Zergling";193;0
"Unit";"Baneling";"Zergling";193;0
"Unit";"Baneling";"Zergling";193;0
"Unit";"Baneling";"Zergling";193;0
"Unit";"Baneling";"Zergling";193;0
"Unit";"Baneling";"Zergling";193;0
"Unit";"Baneling";"Zergling";193;0
"Unit";"Baneling";"Zergling";193;0
"Unit";"Baneling";"Zergling";193;0
"Unit";"Baneling";"Zergling";193;0
"Unit";"Baneling";"Zergling";193;0
"Unit";"Baneling";"Zergling";193;0
"Unit";"Baneling";"Zergling";193;0
"Unit";"Zergling";"Larva";193;1
"Unit";"Zergling";"Larva";193;1
"Unit";"Zergling";"Larva";193;1
"Unit";"Zergling";"Larva";193;1
"Unit";"Zergling";"Larva";193;1
"Unit";"Zergling";"Larva";193;1
"Unit";"Zergling";"Larva";193;1
"Unit";"Zergling";"Larva";193;1
"Unit";"Zergling";"Larva";193;1
"Unit";"Zergling";"Larva";193;1
"Unit";"Zergling";"Larva";193;1
"Unit";"Zergling";"Larva";193;1
"Building";"CreepTumor";NA;200;0
"Building";"Hatchery";NA;156;0
"Building";"CreepTumorQueen";NA;200;0
"Building";"CreepTumorQueen";NA;212;0
"Building";"CreepTumorQueen";NA;212;0
"Building";"CreepTumorQueen";NA;212;0
"Building";"CreepTumorQueen";NA;212;0
"Building";"CreepTumorQueen";NA;212;0
"Building";"Extractor";NA;212;0
"Building";"Extractor";NA;212;0
"Unit";"Overlord";"Larva";212;0
"Unit";"Zergling";"Larva";212;1
"Unit";"Zergling";"Larva";212;1
"Unit";"Zergling";"Larva";212;1
"Unit";"Zergling";"Larva";212;1
"Unit";"Zergling";"Larva";212;1
"Unit";"Zergling";"Larva";212;1
"Unit";"Zergling";"Larva";212;1
"Unit";"Zergling";"Larva";212;1
"Building";"InfestationPit";NA;200;0
"Unit";"Queen";"Hatchery";212;2
"Building";"CreepTumor";NA;233;0
"Building";"CreepTumor";NA;233;0
"Building";"CreepTumor";NA;233;0
"Building";"CreepTumor";NA;233;0
"Building";"CreepTumor";NA;233;0
"Building";"CreepTumor";NA;233;0
"Upgrade";"ZergGroundArmorsLevel1";"EvolutionChamber";177;0
"Upgrade";"EvolveGroovedSpines";"HydraliskDen";212;0
"Building";"CreepTumor";NA;235;0
"Unit";"Overlord";"Larva";235;0
"Unit";"Overlord";"Larva";235;0
"Unit";"Overlord";"Larva";235;0
"Unit";"Overlord";"Larva";235;0
"Unit";"Overlord";"Larva";235;0
"Unit";"Overlord";"Larva";235;0
"Building";"CreepTumor";NA;235;0
"Building";"SporeCrawler";NA;235;0
"Upgrade";"ZergMeleeWeaponsLevel1";"EvolutionChamber";200;0
"Building";"CreepTumor";NA;235;0
"Unit";"Overlord";"Larva";235;0
"Unit";"Overlord";"Larva";235;0
"Unit";"Overlord";"Larva";235;0
"Unit";"Overlord";"Larva";235;0
"Building";"SporeCrawler";NA;235;0
"Building";"CreepTumor";NA;235;0
"Building";"CreepTumor";NA;235;0
"Building";"CreepTumor";NA;235;0
"Building";"CreepTumor";NA;235;0
"Building";"CreepTumor";NA;235;0
"Building";"SporeCrawler";NA;235;0
"Building";"CreepTumor";NA;235;0
"Unit";"Zergling";"Larva";246;1
"Unit";"Zergling";"Larva";246;1
"Unit";"Zergling";"Larva";246;1
"Unit";"Zergling";"Larva";246;1
"Unit";"Zergling";"Larva";246;1
"Unit";"Zergling";"Larva";246;1
"Unit";"Zergling";"Larva";246;1
"Unit";"Zergling";"Larva";246;1
"Unit";"Zergling";"Larva";246;1
"Unit";"Zergling";"Larva";246;1
"Unit";"Zergling";"Larva";246;1
"Unit";"Zergling";"Larva";246;1
"Unit";"Zergling";"Larva";246;1
"Unit";"Zergling";"Larva";246;1
"Unit";"Zergling";"Larva";246;1
"Unit";"Zergling";"Larva";246;1
"Unit";"Zergling";"Larva";246;1
"Unit";"Zergling";"Larva";246;1
"Unit";"Zergling";"Larva";246;1
"Unit";"Zergling";"Larva";246;1
"Unit";"Zergling";"Larva";246;1
"Unit";"Zergling";"Larva";246;1
"Unit";"Zergling";"Larva";246;1
"Unit";"Zergling";"Larva";246;1
"Unit";"Zergling";"Larva";246;1
"Unit";"Zergling";"Larva";246;1
"Unit";"Zergling";"Larva";246;1
"Unit";"Zergling";"Larva";246;1
"Building";"SpineCrawler";NA;235;0
"Unit";"Zergling";"Larva";246;1
"Unit";"Zergling";"Larva";246;1
"Unit";"Zergling";"Larva";246;1
"Unit";"Zergling";"Larva";246;1
"Unit";"Zergling";"Larva";246;1
"Unit";"Zergling";"Larva";246;1
"Unit";"Zergling";"Larva";246;1
"Unit";"Zergling";"Larva";246;1
"Unit";"Zergling";"Larva";246;1
"Unit";"Zergling";"Larva";246;1
"Unit";"Zergling";"Larva";246;1
"Unit";"Zergling";"Larva";246;1
"Unit";"Zergling";"Larva";246;1
"Unit";"Zergling";"Larva";246;1
"Building";"SpineCrawler";NA;235;0
"Building";"SpineCrawler";NA;235;0
"Building";"CreepTumor";NA;288;0
"Unit";"Overlord";"Larva";288;0
"Unit";"Overlord";"Larva";288;0
"Unit";"Zergling";"Larva";288;1
"Unit";"Zergling";"Larva";288;1
"Unit";"Zergling";"Larva";288;1
"Unit";"Zergling";"Larva";288;1
"Unit";"Zergling";"Larva";288;1
"Unit";"Zergling";"Larva";288;1
"Unit";"Zergling";"Larva";288;1
"Unit";"Zergling";"Larva";288;1
"Unit";"Zergling";"Larva";288;1
"Unit";"Zergling";"Larva";288;1
"Unit";"Zergling";"Larva";288;1
"Unit";"Zergling";"Larva";288;1
"Unit";"Zergling";"Larva";288;1
"Unit";"Zergling";"Larva";288;1
"Unit";"Zergling";"Larva";288;1
"Unit";"Zergling";"Larva";288;1
"Unit";"Zergling";"Larva";288;1
"Unit";"Zergling";"Larva";288;1
"Unit";"Zergling";"Larva";288;1
"Unit";"Zergling";"Larva";288;1
"Unit";"Zergling";"Larva";288;1
"Unit";"Zergling";"Larva";288;1
"Unit";"Zergling";"Larva";288;1
"Unit";"Zergling";"Larva";288;1
"Unit";"Zergling";"Larva";288;1
"Unit";"Zergling";"Larva";288;1
"Unit";"Zergling";"Larva";288;1
"Unit";"Zergling";"Larva";288;1
"Unit";"Zergling";"Larva";288;1
"Unit";"Zergling";"Larva";288;1
"Building";"Spire";NA;235;0
"Upgrade";"EvolveMuscularAugments";"HydraliskDen";246;0
"Building";"SporeCrawler";NA;288;0
"Building";"CreepTumorQueen";NA;318;0
"Unit";"Queen";"Hatchery";288;2
"Building";"CreepTumorQueen";NA;318;0
"Unit";"Corruptor";"Larva";318;2
"Unit";"Corruptor";"Larva";318;2
"Unit";"Corruptor";"Larva";318;2
"Unit";"Corruptor";"Larva";318;2
"Unit";"Corruptor";"Larva";318;2
"Unit";"Corruptor";"Larva";318;2
"Unit";"Zergling";"Larva";318;1
"Unit";"Zergling";"Larva";318;1
"Unit";"Zergling";"Larva";318;1
"Unit";"Zergling";"Larva";318;1
"Unit";"Zergling";"Larva";318;1
"Unit";"Zergling";"Larva";318;1
"Unit";"Zergling";"Larva";318;1
"Unit";"Zergling";"Larva";318;1
"Unit";"Zergling";"Larva";318;1
"Unit";"Zergling";"Larva";318;1
"Unit";"Zergling";"Larva";318;1
"Unit";"Zergling";"Larva";318;1
"Unit";"Zergling";"Larva";318;1
"Unit";"Zergling";"Larva";318;1
"Unit";"Zergling";"Larva";318;1
"Unit";"Zergling";"Larva";318;1
"Unit";"Zergling";"Larva";318;1
"Unit";"Zergling";"Larva";318;1
"Unit";"Zergling";"Larva";318;1
"Unit";"Zergling";"Larva";318;1
"Unit";"Zergling";"Larva";318;1
"Unit";"Zergling";"Larva";318;1
"Unit";"Zergling";"Larva";318;1
"Unit";"Zergling";"Larva";318;1
"Unit";"Zergling";"Larva";320;1
"Unit";"Zergling";"Larva";320;1
"Unit";"Zergling";"Larva";320;1
"Unit";"Zergling";"Larva";320;1
"Unit";"Zergling";"Larva";320;1
"Unit";"Zergling";"Larva";320;1
"Unit";"Zergling";"Larva";320;1
"Unit";"Zergling";"Larva";320;1
"Unit";"Zergling";"Larva";320;1
"Unit";"Zergling";"Larva";320;1
"Unit";"Zergling";"Larva";320;1
"Unit";"Zergling";"Larva";320;1
"Unit";"Zergling";"Larva";320;1
"Unit";"Zergling";"Larva";320;1
"Unit";"Baneling";"Zergling";332;0
"Unit";"Baneling";"Zergling";332;0
"Unit";"Baneling";"Zergling";332;0
"Unit";"Baneling";"Zergling";332;0
"Unit";"Baneling";"Zergling";332;0
"Unit";"Baneling";"Zergling";332;0
"Unit";"Baneling";"Zergling";332;0
"Unit";"Baneling";"Zergling";332;0
"Unit";"Baneling";"Zergling";332;0
"Unit";"Baneling";"Zergling";332;0
"Unit";"Baneling";"Zergling";332;0
"Unit";"Baneling";"Zergling";332;0
"Unit";"Baneling";"Zergling";332;0
"Unit";"Baneling";"Zergling";332;0
"Unit";"Baneling";"Zergling";332;0
"Unit";"Baneling";"Zergling";356;0
"Unit";"Baneling";"Zergling";356;0
"Unit";"Baneling";"Zergling";356;0
"Unit";"Baneling";"Zergling";356;0
"Unit";"Baneling";"Zergling";356;0
"Unit";"Baneling";"Zergling";356;0
"Unit";"Zergling";"Larva";334;1
"Unit";"Zergling";"Larva";334;1
"Unit";"Zergling";"Larva";342;1
"Unit";"Zergling";"Larva";342;1
"Unit";"Zergling";"Larva";342;1
"Unit";"Zergling";"Larva";342;1
"Unit";"Zergling";"Larva";346;1
"Unit";"Zergling";"Larva";346;1
"Unit";"Hydralisk";"Larva";332;2
"Unit";"Hydralisk";"Larva";332;2
"Unit";"Hydralisk";"Larva";332;2
"Unit";"Hydralisk";"Larva";332;2
"Building";"CreepTumor";NA;386;0
"Unit";"Zergling";"Larva";386;1
"Unit";"Zergling";"Larva";386;1
"Unit";"Zergling";"Larva";386;1
"Unit";"Zergling";"Larva";386;1
"Unit";"Zergling";"Larva";386;1
"Unit";"Zergling";"Larva";386;1
"Unit";"Zergling";"Larva";386;1
"Unit";"Zergling";"Larva";386;1
"Unit";"Zergling";"Larva";386;1
"Unit";"Zergling";"Larva";386;1
"Unit";"Zergling";"Larva";386;1
"Unit";"Zergling";"Larva";386;1
"Unit";"Zergling";"Larva";386;1
"Unit";"Zergling";"Larva";386;1
"Unit";"Zergling";"Larva";386;1
"Unit";"Zergling";"Larva";386;1
"Unit";"Zergling";"Larva";386;1
"Unit";"Zergling";"Larva";386;1
"Unit";"Zergling";"Larva";386;1
"Unit";"Zergling";"Larva";386;1
"Unit";"Zergling";"Larva";386;1
"Unit";"Zergling";"Larva";386;1
"Unit";"Zergling";"Larva";386;1
"Unit";"Zergling";"Larva";386;1
"Upgrade";"ZergGroundArmorsLevel2";"EvolutionChamber";288;0
"Upgrade";"ZergMeleeWeaponsLevel2";"EvolutionChamber";288;0
"Building";"CreepTumor";NA;386;0
"Building";"CreepTumor";NA;386;0
"Building";"CreepTumorQueen";NA;410;0
"Building";"Spire";NA;318;0
"Building";"CreepTumorQueen";NA;410;0
"Building";"CreepTumorQueen";NA;410;0
"Building";"CreepTumorQueen";NA;410;0
"Building";"CreepTumorQueen";NA;410;0
"Building";"CreepTumorQueen";NA;410;0
"Building";"CreepTumorQueen";NA;410;0
"Building";"CreepTumorQueen";NA;410;0
"Building";"CreepTumorQueen";NA;410;0
"Unit";"Baneling";"Zergling";410;0
"Unit";"Baneling";"Zergling";410;0
"Unit";"Baneling";"Zergling";410;0
"Unit";"Baneling";"Zergling";410;0
"Unit";"Baneling";"Zergling";410;0
"Unit";"Baneling";"Zergling";410;0
"Unit";"Baneling";"Zergling";410;0
"Unit";"Baneling";"Zergling";410;0
"Unit";"Baneling";"Zergling";410;0
"Unit";"Baneling";"Zergling";410;0
"Unit";"Baneling";"Zergling";410;0
"Unit";"Baneling";"Zergling";410;0
"Unit";"Baneling";"Zergling";410;0
"Unit";"Baneling";"Zergling";410;0
"Unit";"Baneling";"Zergling";410;0
"Unit";"Baneling";"Zergling";410;0
"Unit";"Baneling";"Zergling";410;0
"Unit";"Hydralisk";"Larva";410;2
"Unit";"Hydralisk";"Larva";410;2
"Unit";"Hydralisk";"Larva";410;2
"Unit";"Hydralisk";"Larva";410;2
"Unit";"Hydralisk";"Larva";410;2
"Unit";"Hydralisk";"Larva";410;2
"Unit";"Hydralisk";"Larva";410;2
"Unit";"Hydralisk";"Larva";410;2
"Unit";"Hydralisk";"Larva";410;2
"Unit";"Hydralisk";"Larva";410;2
"Unit";"Hydralisk";"Larva";410;2
"Unit";"Hydralisk";"Larva";410;2
"Building";"CreepTumor";NA;410;0
"Building";"CreepTumor";NA;410;0
"Unit";"Zergling";"Larva";410;1
"Unit";"Zergling";"Larva";410;1
"Unit";"Zergling";"Larva";410;1
"Unit";"Zergling";"Larva";410;1
"Unit";"Zergling";"Larva";410;1
"Unit";"Zergling";"Larva";410;1
"Unit";"Baneling";"Zergling";440;0
"Unit";"Baneling";"Zergling";440;0
"Unit";"Baneling";"Zergling";440;0
"Unit";"Baneling";"Zergling";440;0
"Unit";"Baneling";"Zergling";440;0
"Building";"Hatchery";NA;410;0
"Unit";"Zergling";"Larva";440;1
"Unit";"Zergling";"Larva";440;1
"Unit";"Zergling";"Larva";440;1
"Unit";"Zergling";"Larva";440;1
"Unit";"Zergling";"Larva";440;1
"Unit";"Zergling";"Larva";440;1
"Unit";"Zergling";"Larva";440;1
"Unit";"Zergling";"Larva";440;1
"Unit";"Zergling";"Larva";440;1
"Unit";"Zergling";"Larva";440;1
"Unit";"Zergling";"Larva";440;1
"Unit";"Zergling";"Larva";440;1
"Unit";"Zergling";"Larva";440;1
"Unit";"Zergling";"Larva";440;1
"Unit";"Zergling";"Larva";440;1
"Unit";"Zergling";"Larva";440;1
"Unit";"Zergling";"Larva";440;1
"Unit";"Zergling";"Larva";440;1
"Unit";"Zergling";"Larva";440;1
"Unit";"Zergling";"Larva";440;1
"Unit";"Zergling";"Larva";440;1
"Unit";"Zergling";"Larva";440;1
"Unit";"Zergling";"Larva";440;1
"Unit";"Zergling";"Larva";440;1
"Unit";"Zergling";"Larva";440;1
"Unit";"Zergling";"Larva";440;1
"Unit";"Zergling";"Larva";440;1
"Unit";"Zergling";"Larva";440;1
"Unit";"Zergling";"Larva";440;1
"Unit";"Zergling";"Larva";440;1
"Unit";"Zergling";"Larva";440;1
"Unit";"Zergling";"Larva";440;1
"Unit";"Zergling";"Larva";440;1
"Unit";"Zergling";"Larva";440;1
"Unit";"Zergling";"Larva";440;1
"Unit";"Zergling";"Larva";440;1
"Unit";"Zergling";"Larva";440;1
"Unit";"Zergling";"Larva";440;1
"Unit";"Zergling";"Larva";440;1
"Unit";"Zergling";"Larva";440;1
"Unit";"Zergling";"Larva";440;1
"Unit";"Zergling";"Larva";440;1
"Unit";"Zergling";"Larva";440;1
"Unit";"Zergling";"Larva";440;1
"Unit";"Zergling";"Larva";440;1
"Unit";"Zergling";"Larva";440;1
"Unit";"Zergling";"Larva";440;1
"Unit";"Zergling";"Larva";440;1
"Unit";"Zergling";"Larva";440;1
"Unit";"Zergling";"Larva";440;1
"Building";"CreepTumor";NA;440;0
"Building";"CreepTumor";NA;482;0
"Building";"CreepTumor";NA;482;0
"Unit";"Zergling";"Larva";468;1
"Unit";"Zergling";"Larva";468;1
"Unit";"Zergling";"Larva";482;1
"Unit";"Zergling";"Larva";482;1
"Unit";"Zergling";"Larva";482;1
"Unit";"Zergling";"Larva";482;1
"Unit";"Zergling";"Larva";496;1
"Unit";"Zergling";"Larva";496;1
"Unit";"Zergling";"Larva";496;1
"Unit";"Zergling";"Larva";496;1
"Unit";"Zergling";"Larva";496;1
"Unit";"Zergling";"Larva";496;1
"Unit";"Zergling";"Larva";496;1
"Unit";"Zergling";"Larva";496;1
"Unit";"Zergling";"Larva";496;1
"Unit";"Zergling";"Larva";496;1
"Unit";"Zergling";"Larva";496;1
"Unit";"Zergling";"Larva";496;1
"Unit";"Zergling";"Larva";496;1
"Unit";"Zergling";"Larva";496;1
"Unit";"Zergling";"Larva";496;1
"Unit";"Zergling";"Larva";496;1
"Unit";"Zergling";"Larva";496;1
"Unit";"Zergling";"Larva";496;1
"Unit";"Zergling";"Larva";498;1
"Unit";"Zergling";"Larva";498;1
"Building";"CreepTumorQueen";NA;502;0
"Building";"CreepTumorQueen";NA;502;0
"Unit";"Overlord";"Larva";502;0
"Unit";"Overlord";"Larva";502;0
"Unit";"Overlord";"Larva";502;0
"Unit";"Overlord";"Larva";502;0
"Unit";"Overlord";"Larva";502;0
"Building";"CreepTumor";NA;522;0
"Building";"CreepTumor";NA;522;0
"Building";"CreepTumor";NA;522;0
"Building";"CreepTumor";NA;522;0
"Building";"CreepTumor";NA;522;0
"Building";"CreepTumor";NA;522;0
"Building";"CreepTumor";NA;522;0
"Building";"CreepTumor";NA;522;0
"Building";"CreepTumor";NA;522;0
"Unit";"Zergling";"Larva";522;1
"Unit";"Zergling";"Larva";522;1
"Building";"CreepTumor";NA;522;0
"Unit";"Baneling";"Zergling";522;0
"Unit";"Zergling";"Larva";522;1
"Unit";"Zergling";"Larva";522;1
"Unit";"Baneling";"Zergling";522;0
"Unit";"Baneling";"Zergling";522;0
"Unit";"Zergling";"Larva";522;1
"Unit";"Zergling";"Larva";522;1
"Unit";"Zergling";"Larva";522;1
"Unit";"Zergling";"Larva";522;1
"Unit";"Zergling";"Larva";522;1
"Unit";"Zergling";"Larva";522;1
"Unit";"Baneling";"Zergling";522;0
"Unit";"Baneling";"Zergling";522;0
"Unit";"Baneling";"Zergling";522;0
"Unit";"Baneling";"Zergling";522;0
"Unit";"Zergling";"Larva";522;1
"Unit";"Zergling";"Larva";522;1
"Unit";"Zergling";"Larva";522;1
"Unit";"Zergling";"Larva";522;1
"Unit";"Zergling";"Larva";522;1
"Unit";"Zergling";"Larva";522;1
"Unit";"Zergling";"Larva";522;1
"Unit";"Zergling";"Larva";522;1
"Unit";"Baneling";"Zergling";522;0
"Unit";"Baneling";"Zergling";522;0
"Unit";"Baneling";"Zergling";522;0
"Unit";"Zergling";"Larva";522;1
"Unit";"Zergling";"Larva";522;1
"Unit";"Zergling";"Larva";522;1
"Unit";"Zergling";"Larva";522;1
"Unit";"Zergling";"Larva";522;1
"Unit";"Zergling";"Larva";522;1
"Unit";"Zergling";"Larva";522;1
"Unit";"Zergling";"Larva";522;1
"Unit";"Baneling";"Zergling";522;0
"Unit";"Baneling";"Zergling";522;0
"Unit";"Baneling";"Zergling";522;0
"Unit";"Baneling";"Zergling";522;0
"Building";"CreepTumor";NA;522;0
"Building";"CreepTumor";NA;548;0
"Unit";"Baneling";"Zergling";548;0
"Unit";"Baneling";"Zergling";548;0
"Unit";"Baneling";"Zergling";548;0
"Unit";"Baneling";"Zergling";548;0
"Unit";"Baneling";"Zergling";548;0
"Unit";"Baneling";"Zergling";548;0
"Unit";"Zergling";"Larva";548;1
"Unit";"Zergling";"Larva";548;1
"Unit";"Zergling";"Larva";548;1
"Unit";"Zergling";"Larva";548;1
"Unit";"Zergling";"Larva";548;1
"Unit";"Zergling";"Larva";548;1
"Unit";"Zergling";"Larva";548;1
"Unit";"Zergling";"Larva";548;1
"Unit";"Zergling";"Larva";548;1
"Unit";"Zergling";"Larva";548;1
"Unit";"Zergling";"Larva";548;1
"Unit";"Zergling";"Larva";548;1
"Unit";"Zergling";"Larva";548;1
"Unit";"Zergling";"Larva";548;1
"Unit";"Zergling";"Larva";548;1
"Unit";"Zergling";"Larva";548;1
"Unit";"Zergling";"Larva";548;1
"Unit";"Zergling";"Larva";548;1
"Unit";"Zergling";"Larva";548;1
"Unit";"Zergling";"Larva";548;1
"Building";"Hatchery";NA;502;0
"Unit";"Hydralisk";"Larva";548;2
"Unit";"Hydralisk";"Larva";548;2
"Unit";"Hydralisk";"Larva";548;2
"Unit";"Hydralisk";"Larva";548;2
"Unit";"Hydralisk";"Larva";548;2
"Unit";"Zergling";"Larva";573;1
"Unit";"Zergling";"Larva";573;1
"Unit";"Zergling";"Larva";573;1
"Unit";"Zergling";"Larva";573;1
"Unit";"Zergling";"Larva";573;1
"Unit";"Zergling";"Larva";573;1
"Unit";"Zergling";"Larva";573;1
"Unit";"Zergling";"Larva";573;1
"Unit";"Zergling";"Larva";573;1
"Unit";"Zergling";"Larva";573;1
"Unit";"Baneling";"Zergling";593;0
"Unit";"Baneling";"Zergling";593;0
"Unit";"Baneling";"Zergling";593;0
"Unit";"Baneling";"Zergling";593;0
"Unit";"Baneling";"Zergling";593;0
"Unit";"Baneling";"Zergling";593;0
"Unit";"Baneling";"Zergling";593;0
"Unit";"Baneling";"Zergling";593;0
"Unit";"Zergling";"Larva";593;1
"Unit";"Zergling";"Larva";593;1
"Unit";"Zergling";"Larva";593;1
"Unit";"Zergling";"Larva";593;1
"Unit";"Zergling";"Larva";593;1
"Unit";"Zergling";"Larva";593;1
"Unit";"Zergling";"Larva";593;1
"Unit";"Zergling";"Larva";593;1
"Unit";"Zergling";"Larva";593;1
"Unit";"Zergling";"Larva";593;1
"Unit";"Zergling";"Larva";593;1
"Unit";"Zergling";"Larva";593;1
"Unit";"Zergling";"Larva";593;1
"Unit";"Zergling";"Larva";593;1
"Unit";"Zergling";"Larva";593;1
"Unit";"Zergling";"Larva";593;1
"Building";"CreepTumorQueen";NA;593;0
"Building";"CreepTumorQueen";NA;593;0
"Building";"CreepTumorQueen";NA;593;0
"Building";"CreepTumorQueen";NA;593;0
"Building";"CreepTumor";NA;593;0
"Upgrade";"ZergMeleeWeaponsLevel3";"EvolutionChamber";522;0
"Upgrade";"ZergGroundArmorsLevel3";"EvolutionChamber";522;0
"Unit";"Zergling";"Larva";607;1
"Unit";"Zergling";"Larva";607;1
"Unit";"Zergling";"Larva";609;1
"Unit";"Zergling";"Larva";609;1
"Unit";"Zergling";"Larva";609;1
"Unit";"Zergling";"Larva";609;1
"Unit";"Zergling";"Larva";609;1
"Unit";"Zergling";"Larva";609;1
"Unit";"Zergling";"Larva";609;1
"Unit";"Zergling";"Larva";609;1
"Unit";"Zergling";"Larva";609;1
"Unit";"Zergling";"Larva";609;1
"Unit";"Zergling";"Larva";609;1
"Unit";"Zergling";"Larva";609;1
"Unit";"Zergling";"Larva";609;1
"Unit";"Zergling";"Larva";609;1
"Unit";"Zergling";"Larva";609;1
"Unit";"Zergling";"Larva";609;1
"Unit";"Zergling";"Larva";609;1
"Unit";"Zergling";"Larva";609;1
"Unit";"Zergling";"Larva";609;1
"Unit";"Zergling";"Larva";609;1
"Unit";"Zergling";"Larva";609;1
"Unit";"Zergling";"Larva";609;1
"Unit";"Zergling";"Larva";609;1
"Unit";"Zergling";"Larva";609;1
"Building";"CreepTumorQueen";NA;609;0
"Building";"CreepTumorQueen";NA;609;0
"Building";"CreepTumor";NA;609;0
"Building";"CreepTumor";NA;609;0
"Unit";"Zergling";"Larva";609;1
"Unit";"Zergling";"Larva";609;1
"Unit";"Zergling";"Larva";609;1
"Unit";"Zergling";"Larva";609;1
"Unit";"Zergling";"Larva";609;1
"Unit";"Zergling";"Larva";609;1
"Unit";"Zergling";"Larva";609;1
"Unit";"Zergling";"Larva";609;1
"Unit";"Zergling";"Larva";609;1
"Unit";"Zergling";"Larva";609;1
"Unit";"Zergling";"Larva";609;1
"Unit";"Zergling";"Larva";609;1
"Unit";"Zergling";"Larva";609;1
"Unit";"Zergling";"Larva";609;1
"Unit";"Zergling";"Larva";609;1
"Unit";"Zergling";"Larva";609;1
"Unit";"Zergling";"Larva";609;1
"Unit";"Zergling";"Larva";609;1
"Building";"Extractor";NA;609;0
"Building";"Extractor";NA;609;0
"Building";"CreepTumor";NA;653;0
"Building";"CreepTumor";NA;653;0
"Building";"CreepTumor";NA;653;0
"Building";"CreepTumor";NA;653;0
"Building";"CreepTumor";NA;653;0
"Building";"CreepTumor";NA;653;0
"Building";"CreepTumor";NA;653;0
"Building";"InfestationPit";NA;635;0
"Building";"CreepTumor";NA;653;0
"Building";"CreepTumor";NA;653;0
"Building";"CreepTumor";NA;653;0
"Building";"CreepTumor";NA;653;0
"Building";"CreepTumor";NA;653;0
"Building";"Hatchery";NA;609;0
"Unit";"Zergling";"Larva";653;1
"Unit";"Zergling";"Larva";653;1
"Unit";"Zergling";"Larva";653;1
"Unit";"Zergling";"Larva";653;1
"Unit";"Zergling";"Larva";653;1
"Unit";"Zergling";"Larva";653;1
"Unit";"Zergling";"Larva";653;1
"Unit";"Zergling";"Larva";653;1
"Unit";"Zergling";"Larva";653;1
"Unit";"Zergling";"Larva";653;1
"Unit";"Zergling";"Larva";653;1
"Unit";"Zergling";"Larva";653;1
"Unit";"Zergling";"Larva";653;1
"Unit";"Zergling";"Larva";653;1
"Unit";"Zergling";"Larva";653;1
"Unit";"Zergling";"Larva";653;1
"Unit";"Zergling";"Larva";653;1
"Unit";"Zergling";"Larva";653;1
"Unit";"Zergling";"Larva";653;1
"Unit";"Zergling";"Larva";653;1
"Unit";"Zergling";"Larva";653;1
"Unit";"Zergling";"Larva";653;1
"Unit";"Zergling";"Larva";653;1
"Unit";"Zergling";"Larva";653;1
"Unit";"Zergling";"Larva";653;1
"Unit";"Zergling";"Larva";653;1
"Unit";"Zergling";"Larva";653;1
"Unit";"Zergling";"Larva";653;1
"Unit";"Zergling";"Larva";653;1
"Unit";"Zergling";"Larva";653;1
"Unit";"Zergling";"Larva";653;1
"Unit";"Zergling";"Larva";653;1
"Unit";"Zergling";"Larva";653;1
"Unit";"Zergling";"Larva";653;1
"Unit";"Zergling";"Larva";653;1
"Unit";"Zergling";"Larva";653;1
"Unit";"Zergling";"Larva";653;1
"Unit";"Zergling";"Larva";653;1
"Unit";"Zergling";"Larva";653;1
"Unit";"Zergling";"Larva";653;1
"Unit";"Zergling";"Larva";653;1
"Unit";"Zergling";"Larva";653;1
"Building";"CreepTumor";NA;653;0
"Building";"CreepTumor";NA;653;0
"Building";"CreepTumor";NA;653;0
"Building";"CreepTumor";NA;653;0
"Building";"CreepTumor";NA;653;0
"Building";"CreepTumor";NA;665;0
"Building";"CreepTumor";NA;695;0
"Building";"CreepTumor";NA;695;0
"Building";"CreepTumor";NA;695;0
"Unit";"Zergling";"Larva";695;1
"Unit";"Zergling";"Larva";695;1
"Unit";"Zergling";"Larva";695;1
"Unit";"Zergling";"Larva";695;1
"Unit";"Zergling";"Larva";695;1
"Unit";"Zergling";"Larva";695;1
"Unit";"Zergling";"Larva";695;1
"Unit";"Zergling";"Larva";695;1
"Unit";"Zergling";"Larva";695;1
"Unit";"Zergling";"Larva";695;1
"Unit";"Zergling";"Larva";695;1
"Unit";"Zergling";"Larva";695;1
"Unit";"Zergling";"Larva";695;1
"Unit";"Zergling";"Larva";695;1
"Unit";"Zergling";"Larva";695;1
"Unit";"Zergling";"Larva";695;1
"Unit";"Zergling";"Larva";695;1
"Unit";"Zergling";"Larva";695;1
"Unit";"Zergling";"Larva";695;1
"Unit";"Zergling";"Larva";695;1
"Unit";"Zergling";"Larva";695;1
"Unit";"Zergling";"Larva";695;1
"Unit";"Zergling";"Larva";695;1
"Unit";"Zergling";"Larva";695;1
"Unit";"Zergling";"Larva";695;1
"Unit";"Zergling";"Larva";695;1
"Unit";"Zergling";"Larva";695;1
"Unit";"Zergling";"Larva";695;1
"Unit";"Zergling";"Larva";695;1
"Unit";"Zergling";"Larva";695;1
"Upgrade";"ZergMissileWeaponsLevel1";"EvolutionChamber";653;0
"Building";"Extractor";NA;695;0
"Building";"Extractor";NA;695;0
"Building";"CreepTumor";NA;697;0
"Building";"CreepTumor";NA;707;0
"Building";"SporeCrawler";NA;695;0
"Building";"CreepTumor";NA;697;0
"Unit";"Zergling";"Larva";695;1
"Unit";"Zergling";"Larva";695;1
"Unit";"Zergling";"Larva";695;1
"Unit";"Zergling";"Larva";695;1
"Unit";"Zergling";"Larva";695;1
"Unit";"Zergling";"Larva";695;1
"Unit";"Zergling";"Larva";695;1
"Unit";"Zergling";"Larva";695;1
"Unit";"Zergling";"Larva";695;1
"Unit";"Zergling";"Larva";695;1
"Unit";"Zergling";"Larva";695;1
"Unit";"Zergling";"Larva";695;1
"Building";"CreepTumor";NA;725;0
"Building";"SpineCrawler";NA;695;0
"Building";"SpineCrawler";NA;695;0
"Building";"SpineCrawler";NA;695;0
"Building";"CreepTumor";NA;737;0
"Building";"CreepTumor";NA;737;0
"Building";"CreepTumor";NA;737;0
"Building";"CreepTumor";NA;737;0
"Building";"CreepTumor";NA;737;0
"Building";"CreepTumor";NA;737;0
"Building";"CreepTumorQueen";NA;737;0
"Building";"CreepTumorQueen";NA;737;0
"Building";"CreepTumorQueen";NA;737;0
"Building";"CreepTumorQueen";NA;737;0
"Building";"CreepTumorQueen";NA;737;0
"Building";"CreepTumorQueen";NA;737;0
"Unit";"Zergling";"Larva";737;1
"Unit";"Zergling";"Larva";737;1
"Unit";"Zergling";"Larva";737;1
"Unit";"Zergling";"Larva";737;1
"Unit";"Zergling";"Larva";737;1
"Unit";"Zergling";"Larva";737;1
"Unit";"Zergling";"Larva";737;1
"Unit";"Zergling";"Larva";737;1
"Unit";"Zergling";"Larva";737;1
"Unit";"Zergling";"Larva";737;1
"Unit";"Zergling";"Larva";737;1
"Unit";"Zergling";"Larva";737;1
"Unit";"Zergling";"Larva";737;1
"Unit";"Zergling";"Larva";737;1
"Unit";"Zergling";"Larva";737;1
"Unit";"Zergling";"Larva";737;1
"Unit";"Zergling";"Larva";737;1
"Unit";"Zergling";"Larva";737;1
"Unit";"Zergling";"Larva";737;1
"Unit";"Zergling";"Larva";737;1
"Unit";"Zergling";"Larva";737;1
"Unit";"Zergling";"Larva";737;1
"Unit";"Zergling";"Larva";737;1
"Unit";"Zergling";"Larva";737;1
"Unit";"Zergling";"Larva";737;1
"Unit";"Zergling";"Larva";737;1
"Unit";"Zergling";"Larva";737;1
"Unit";"Zergling";"Larva";737;1
"Unit";"Zergling";"Larva";737;1
"Unit";"Zergling";"Larva";737;1
"Unit";"Zergling";"Larva";737;1
"Unit";"Zergling";"Larva";737;1
"Building";"CreepTumorQueen";NA;737;0
"Building";"CreepTumorQueen";NA;737;0
"Building";"CreepTumorQueen";NA;737;0
"Building";"CreepTumor";NA;769;0
"Building";"CreepTumor";NA;769;0
"Building";"CreepTumor";NA;769;0
"Building";"CreepTumor";NA;769;0
"Building";"CreepTumorQueen";NA;769;0
"Building";"CreepTumorQueen";NA;769;0
"Building";"CreepTumorQueen";NA;769;0
"Building";"CreepTumor";NA;769;0
"Building";"Extractor";NA;769;0
"Building";"Extractor";NA;769;0
"Building";"CreepTumor";NA;769;0
"Building";"CreepTumor";NA;769;0
"Building";"CreepTumor";NA;769;0
"Unit";"Corruptor";"Larva";769;2
"Building";"CreepTumor";NA;769;0
"Building";"CreepTumor";NA;769;0
"Building";"CreepTumor";NA;769;0
"Building";"CreepTumor";NA;769;0
"Building";"CreepTumor";NA;769;0
"Building";"CreepTumorQueen";NA;771;0
"Building";"CreepTumorQueen";NA;771;0
"Building";"CreepTumorQueen";NA;771;0
"Building";"CreepTumorQueen";NA;771;0
"Building";"CreepTumor";NA;771;0
"Building";"CreepTumor";NA;771;0
"Unit";"Corruptor";"Larva";771;2
"Unit";"Corruptor";"Larva";771;2
"Unit";"Corruptor";"Larva";771;2
"Unit";"Corruptor";"Larva";771;2
"Building";"CreepTumor";NA;779;0
"Building";"CreepTumor";NA;779;0
"Building";"CreepTumor";NA;779;0
"Unit";"Corruptor";"Larva";771;2
"Building";"CreepTumor";NA;779;0
"Building";"CreepTumor";NA;779;0
"Unit";"Zergling";"Larva";779;1
"Unit";"Zergling";"Larva";779;1
"Unit";"Zergling";"Larva";779;1
"Unit";"Zergling";"Larva";779;1
"Unit";"Zergling";"Larva";779;1
"Unit";"Zergling";"Larva";779;1
"Unit";"Zergling";"Larva";779;1
"Unit";"Zergling";"Larva";779;1
"Unit";"Zergling";"Larva";779;1
"Unit";"Zergling";"Larva";779;1
"Unit";"Zergling";"Larva";779;1
"Unit";"Zergling";"Larva";779;1
"Unit";"Zergling";"Larva";779;1
"Unit";"Zergling";"Larva";779;1
"Unit";"Zergling";"Larva";779;1
"Unit";"Zergling";"Larva";779;1
"Unit";"Zergling";"Larva";779;1
"Unit";"Zergling";"Larva";779;1
"Unit";"Zergling";"Larva";779;1
"Unit";"Zergling";"Larva";779;1
"Unit";"Zergling";"Larva";779;1
"Unit";"Zergling";"Larva";779;1
"Unit";"Zergling";"Larva";779;1
"Unit";"Zergling";"Larva";779;1
"Unit";"Zergling";"Larva";779;1
"Unit";"Zergling";"Larva";779;1
"Unit";"Zergling";"Larva";779;1
"Unit";"Zergling";"Larva";779;1
"Unit";"Zergling";"Larva";779;1
"Unit";"Zergling";"Larva";779;1
"Building";"CreepTumor";NA;811;0
"Building";"CreepTumorQueen";NA;811;0
"Building";"CreepTumorQueen";NA;811;0
"Building";"CreepTumorQueen";NA;811;0
