"type";"unit_name";"on_building";"total_supply";"supply"
"Unit";"Overlord";"Larva";12;0
"Building";"SpawningPool";NA;19;0
"Building";"Hatchery";NA;17;0
"Unit";"Overlord";"Larva";21;0
"Unit";"Zergling";"Larva";23;1
"Unit";"Zergling";"Larva";23;1
"Unit";"Zergling";"Larva";23;1
"Unit";"Zergling";"Larva";23;1
"Unit";"Queen";"Hatchery";23;2
"Building";"Hatchery";NA;21;0
"Unit";"Overlord";"Larva";29;0
"Unit";"Queen";"Hatchery";23;2
"Unit";"Queen";"Hatchery";33;2
"Building";"Extractor";NA;38;0
"Building";"Extractor";NA;38;0
"Unit";"Queen";"Hatchery";33;2
"Building";"CreepTumorQueen";NA;45;0
"Unit";"Overlord";"Larva";43;0
"Building";"CreepTumorQueen";NA;49;0
"Unit";"Overlord";"Larva";51;0
"Unit";"Overlord";"Larva";51;0
"Building";"CreepTumor";NA;57;0
"Building";"CreepTumor";NA;57;0
"Building";"EvolutionChamber";NA;57;0
"Building";"RoachWarren";NA;57;0
"Building";"Extractor";NA;57;0
"Building";"Extractor";NA;57;0
"Unit";"Queen";"Hatchery";57;2
"Unit";"Roach";"Larva";67;2
"Unit";"Roach";"Larva";67;2
"Building";"CreepTumorQueen";NA;67;0
"Building";"CreepTumor";NA;67;0
"Building";"CreepTumor";NA;67;0
"Building";"CreepTumorQueen";NA;67;0
"Building";"CreepTumorQueen";NA;67;0
"Unit";"Roach";"Larva";67;2
"Unit";"Roach";"Larva";67;2
"Unit";"Roach";"Larva";67;2
"Unit";"Roach";"Larva";67;2
"Unit";"Roach";"Larva";67;2
"Unit";"Overlord";"Larva";67;0
"Unit";"Overlord";"Larva";67;0
"Unit";"Roach";"Larva";67;2
"Unit";"Overlord";"Larva";71;0
"Unit";"Overlord";"Larva";71;0
"Building";"CreepTumor";NA;99;0
"Building";"CreepTumor";NA;99;0
"Building";"CreepTumor";NA;99;0
"Building";"CreepTumor";NA;99;0
"Building";"InfestationPit";NA;85;0
"Upgrade";"ZergGroundArmorsLevel1";"EvolutionChamber";71;0
"Building";"CreepTumor";NA;101;0
"Building";"CreepTumor";NA;101;0
"Building";"CreepTumor";NA;101;0
"Building";"CreepTumor";NA;101;0
"Unit";"Overlord";"Larva";101;0
"Unit";"Overlord";"Larva";101;0
"Unit";"Queen";"Hatchery";107;2
"Building";"EvolutionChamber";NA;111;0
"Building";"CreepTumor";NA;114;0
"Building";"CreepTumor";NA;114;0
"Building";"CreepTumor";NA;125;0
"Building";"CreepTumor";NA;131;0
"Building";"CreepTumor";NA;131;0
"Building";"Extractor";NA;125;0
"Building";"Extractor";NA;125;0
"Building";"HydraliskDen";NA;122;0
"Unit";"Overlord";"Larva";131;0
"Unit";"Overlord";"Larva";131;0
"Building";"CreepTumorQueen";NA;131;0
"Upgrade";"ZergMissileWeaponsLevel1";"EvolutionChamber";114;0
"Building";"CreepTumorQueen";NA;131;0
"Building";"CreepTumorQueen";NA;131;0
"Building";"CreepTumor";NA;134;0
"Building";"CreepTumor";NA;138;0
"Building";"CreepTumor";NA;141;0
"Unit";"Overlord";"Larva";141;0
"Unit";"Overlord";"Larva";141;0
"Building";"Hatchery";NA;131;0
"Unit";"Overlord";"Larva";147;0
"Unit";"Overlord";"Larva";147;0
"Upgrade";"GlialReconstitution";"RoachWarren";131;0
"Unit";"Hydralisk";"Larva";147;2
"Unit";"Hydralisk";"Larva";147;2
"Unit";"Hydralisk";"Larva";147;2
"Unit";"Hydralisk";"Larva";147;2
"Unit";"Hydralisk";"Larva";147;2
"Upgrade";"EvolveGroovedSpines";"HydraliskDen";147;0
"Building";"CreepTumor";NA;166;0
"Building";"CreepTumor";NA;166;0
"Building";"CreepTumor";NA;166;0
"Building";"CreepTumor";NA;166;0
"Unit";"Overlord";"Larva";166;0
"Unit";"Overlord";"Larva";166;0
"Building";"CreepTumor";NA;166;0
"Building";"Extractor";NA;166;0
"Building";"CreepTumor";NA;166;0
"Building";"CreepTumor";NA;166;0
"Building";"Extractor";NA;166;0
"Unit";"Hydralisk";"Larva";166;2
"Unit";"Hydralisk";"Larva";166;2
"Unit";"Hydralisk";"Larva";166;2
"Unit";"Hydralisk";"Larva";166;2
"Upgrade";"ZergGroundArmorsLevel2";"EvolutionChamber";131;0
"Unit";"Queen";"Hatchery";166;2
"Unit";"Hydralisk";"Larva";170;2
"Unit";"Hydralisk";"Larva";170;2
"Unit";"Hydralisk";"Larva";170;2
"Unit";"Hydralisk";"Larva";170;2
"Unit";"Hydralisk";"Larva";170;2
"Unit";"Hydralisk";"Larva";170;2
"Unit";"Hydralisk";"Larva";170;2
"Unit";"Hydralisk";"Larva";170;2
"Building";"CreepTumor";NA;180;0
"Unit";"Overlord";"Larva";180;0
"Unit";"Overlord";"Larva";180;0
"Unit";"Overlord";"Larva";180;0
"Building";"Hatchery";NA;166;0
"Unit";"Roach";"Larva";196;2
"Unit";"Roach";"Larva";196;2
"Unit";"Roach";"Larva";196;2
"Unit";"Roach";"Larva";196;2
"Unit";"Roach";"Larva";196;2
"Unit";"Roach";"Larva";196;2
"Unit";"Roach";"Larva";196;2
"Unit";"Roach";"Larva";196;2
"Unit";"Roach";"Larva";196;2
"Unit";"Roach";"Larva";196;2
"Unit";"Roach";"Larva";196;2
"Unit";"Roach";"Larva";196;2
"Unit";"Roach";"Larva";196;2
"Unit";"Roach";"Larva";196;2
"Unit";"Roach";"Larva";196;2
"Unit";"Overlord";"Larva";196;0
"Upgrade";"EvolveMuscularAugments";"HydraliskDen";196;0
"Building";"CreepTumor";NA;232;0
"Upgrade";"ZergMissileWeaponsLevel2";"EvolutionChamber";166;0
"Unit";"Queen";"Hatchery";232;2
"Building";"Hatchery";NA;232;0
"Unit";"Roach";"Larva";240;2
"Unit";"Roach";"Larva";240;2
"Unit";"Roach";"Larva";240;2
"Unit";"Roach";"Larva";240;2
"Unit";"Roach";"Larva";240;2
"Unit";"Roach";"Larva";240;2
"Unit";"Roach";"Larva";240;2
"Building";"Spire";NA;232;0
"Building";"Spire";NA;232;0
"Unit";"Hydralisk";"Larva";240;2
"Unit";"Hydralisk";"Larva";240;2
"Unit";"Hydralisk";"Larva";240;2
"Unit";"Hydralisk";"Larva";240;2
"Unit";"Hydralisk";"Larva";240;2
"Unit";"Hydralisk";"Larva";240;2
"Unit";"Hydralisk";"Larva";240;2
"Unit";"Hydralisk";"Larva";240;2
"Unit";"Hydralisk";"Larva";240;2
"Unit";"Hydralisk";"Larva";240;2
"Unit";"Hydralisk";"Larva";240;2
"Unit";"Hydralisk";"Larva";240;2
"Unit";"Hydralisk";"Larva";240;2
"Unit";"Hydralisk";"Larva";240;2
"Unit";"Hydralisk";"Larva";240;2
"Unit";"Hydralisk";"Larva";240;2
"Unit";"Hydralisk";"Larva";240;2
"Unit";"Hydralisk";"Larva";240;2
"Unit";"Hydralisk";"Larva";240;2
"Unit";"Hydralisk";"Larva";240;2
"Unit";"Viper";"Larva";240;3
"Unit";"Viper";"Larva";297;3
"Unit";"Viper";"Larva";297;3
"Unit";"Viper";"Larva";297;3
"Unit";"Viper";"Larva";297;3
"Unit";"Viper";"Larva";297;3
"Building";"Hatchery";NA;254;0
"Upgrade";"ZergMissileWeaponsLevel3";"EvolutionChamber";240;0
"Building";"Hatchery";NA;297;0
"Upgrade";"ZergGroundArmorsLevel3";"EvolutionChamber";240;0
"Unit";"Roach";"Larva";312;2
"Unit";"Roach";"Larva";312;2
"Unit";"Roach";"Larva";312;2
"Unit";"Roach";"Larva";312;2
"Unit";"Roach";"Larva";312;2
"Unit";"Roach";"Larva";312;2
"Unit";"Roach";"Larva";312;2
"Unit";"Roach";"Larva";312;2
"Unit";"Roach";"Larva";312;2
"Unit";"Roach";"Larva";312;2
"Unit";"Roach";"Larva";312;2
"Unit";"Hydralisk";"Larva";312;2
"Unit";"Hydralisk";"Larva";312;2
"Unit";"Hydralisk";"Larva";312;2
"Unit";"Hydralisk";"Larva";312;2
"Unit";"Hydralisk";"Larva";312;2
"Unit";"Hydralisk";"Larva";312;2
"Unit";"Hydralisk";"Larva";312;2
"Unit";"Hydralisk";"Larva";312;2
"Unit";"Hydralisk";"Larva";312;2
"Unit";"Hydralisk";"Larva";312;2
"Unit";"Hydralisk";"Larva";312;2
"Unit";"Hydralisk";"Larva";312;2
"Unit";"Hydralisk";"Larva";312;2
"Unit";"Hydralisk";"Larva";312;2
"Unit";"Hydralisk";"Larva";312;2
"Unit";"Hydralisk";"Larva";312;2
"Unit";"Hydralisk";"Larva";312;2
"Unit";"Hydralisk";"Larva";312;2
"Building";"CreepTumor";NA;370;0
"Building";"NydusNetwork";NA;312;0
"Unit";"Hydralisk";"Larva";370;2
"Unit";"Hydralisk";"Larva";370;2
"Unit";"Hydralisk";"Larva";370;2
"Unit";"Hydralisk";"Larva";370;2
"Building";"NydusCanal";NA;378;0
"Upgrade";"ZergMeleeWeaponsLevel1";"EvolutionChamber";312;0
"Unit";"Roach";"Larva";378;2
"Unit";"Roach";"Larva";378;2
"Unit";"Roach";"Larva";378;2
"Unit";"Roach";"Larva";378;2
"Unit";"Roach";"Larva";378;2
"Unit";"Roach";"Larva";378;2
"Unit";"Roach";"Larva";378;2
"Unit";"Roach";"Larva";378;2
"Unit";"Roach";"Larva";378;2
"Unit";"Roach";"Larva";378;2
"Unit";"Roach";"Larva";378;2
"Unit";"Roach";"Larva";378;2
"Unit";"Roach";"Larva";378;2
"Unit";"Roach";"Larva";378;2
"Unit";"Roach";"Larva";378;2
"Unit";"Roach";"Larva";378;2
"Unit";"Roach";"Larva";378;2
"Unit";"Roach";"Larva";378;2
"Building";"NydusCanal";NA;378;0
"Unit";"Hydralisk";"Larva";378;2
"Unit";"Hydralisk";"Larva";378;2
"Unit";"Hydralisk";"Larva";378;2
"Building";"NydusCanal";NA;420;0
"Unit";"Queen";"Hatchery";378;2
"Unit";"Queen";"Hatchery";378;2
"Unit";"Hydralisk";"Larva";420;2
"Unit";"Hydralisk";"Larva";420;2
"Unit";"Hydralisk";"Larva";420;2
"Unit";"Hydralisk";"Larva";420;2
"Unit";"Hydralisk";"Larva";420;2
"Unit";"Hydralisk";"Larva";420;2
"Unit";"Hydralisk";"Larva";420;2
"Unit";"Hydralisk";"Larva";420;2
"Unit";"Hydralisk";"Larva";420;2
"Unit";"Hydralisk";"Larva";420;2
"Unit";"Hydralisk";"Larva";420;2
"Unit";"Hydralisk";"Larva";420;2
"Unit";"Hydralisk";"Larva";420;2
"Unit";"Hydralisk";"Larva";420;2
"Unit";"Hydralisk";"Larva";420;2
"Unit";"Hydralisk";"Larva";420;2
"Unit";"Hydralisk";"Larva";420;2
"Building";"CreepTumor";NA;424;0
"Building";"Extractor";NA;458;0
"Building";"CreepTumor";NA;473;0
"Building";"Hatchery";NA;420;0
"Unit";"Queen";"Hatchery";473;2
"Upgrade";"ZergMeleeWeaponsLevel2";"EvolutionChamber";424;0
"Unit";"Overlord";"Larva";473;0
"Building";"NydusCanal";NA;473;0
"Building";"CreepTumor";NA;475;0
"Unit";"Hydralisk";"Larva";473;2
"Unit";"Hydralisk";"Larva";473;2
"Unit";"Hydralisk";"Larva";473;2
"Unit";"Hydralisk";"Larva";473;2
"Unit";"Hydralisk";"Larva";473;2
"Unit";"Hydralisk";"Larva";473;2
"Unit";"Hydralisk";"Larva";473;2
"Unit";"Hydralisk";"Larva";473;2
"Unit";"Hydralisk";"Larva";473;2
"Unit";"Hydralisk";"Larva";473;2
"Unit";"Hydralisk";"Larva";473;2
"Unit";"Hydralisk";"Larva";473;2
"Unit";"Hydralisk";"Larva";473;2
"Unit";"Hydralisk";"Larva";473;2
"Unit";"Hydralisk";"Larva";473;2
"Unit";"Hydralisk";"Larva";473;2
"Unit";"Hydralisk";"Larva";473;2
"Building";"NydusCanal";NA;475;0
"Building";"Extractor";NA;477;0
