"type";"unit_name";"on_building";"total_supply";"supply"
"Unit";"Overlord";"Larva";12;0
"Building";"SpawningPool";NA;19;0
"Building";"Hatchery";NA;17;0
"Building";"Extractor";NA;23;0
"Unit";"Overlord";"Larva";23;0
"Unit";"Zergling";"Larva";24;1
"Unit";"Zergling";"Larva";24;1
"Unit";"Zergling";"Larva";24;1
"Unit";"Zergling";"Larva";24;1
"Unit";"Queen";"Hatchery";24;2
"Unit";"Queen";"Hatchery";24;2
"Unit";"Overlord";"Larva";36;0
"Unit";"Overlord";"Larva";39;0
"Building";"Hatchery";NA;26;0
"Unit";"Overlord";"Larva";43;0
"Unit";"Queen";"Hatchery";39;2
"Building";"CreepTumorQueen";NA;49;0
"Unit";"Overlord";"Larva";46;0
"Building";"CreepTumorQueen";NA;51;0
"Unit";"Queen";"Hatchery";46;2
"Building";"CreepTumor";NA;51;0
"Unit";"Queen";"Hatchery";49;2
"Unit";"Queen";"Hatchery";51;2
"Unit";"Zergling";"Larva";61;1
"Unit";"Zergling";"Larva";61;1
"Unit";"Zergling";"Larva";61;1
"Unit";"Zergling";"Larva";61;1
"Unit";"Zergling";"Larva";61;1
"Unit";"Zergling";"Larva";61;1
"Unit";"Zergling";"Larva";61;1
"Unit";"Zergling";"Larva";61;1
"Unit";"Zergling";"Larva";61;1
"Unit";"Zergling";"Larva";61;1
"Unit";"Zergling";"Larva";61;1
"Unit";"Zergling";"Larva";61;1
"Unit";"Zergling";"Larva";61;1
"Unit";"Zergling";"Larva";61;1
"Unit";"Zergling";"Larva";61;1
"Unit";"Zergling";"Larva";61;1
"Building";"BanelingNest";NA;51;0
"Unit";"Zergling";"Larva";63;1
"Unit";"Zergling";"Larva";63;1
"Unit";"Zergling";"Larva";63;1
"Unit";"Zergling";"Larva";63;1
"Unit";"Zergling";"Larva";63;1
"Unit";"Zergling";"Larva";63;1
"Unit";"Zergling";"Larva";63;1
"Unit";"Zergling";"Larva";63;1
"Unit";"Zergling";"Larva";63;1
"Unit";"Zergling";"Larva";63;1
"Unit";"Queen";"Hatchery";63;2
"Building";"CreepTumorQueen";NA;91;0
"Building";"CreepTumorQueen";NA;91;0
"Building";"CreepTumorQueen";NA;99;0
"Building";"CreepTumor";NA;99;0
"Building";"CreepTumorQueen";NA;99;0
"Building";"SporeCrawler";NA;99;0
"Building";"SporeCrawler";NA;99;0
"Building";"CreepTumorQueen";NA;99;0
"Building";"CreepTumorQueen";NA;99;0
"Building";"CreepTumorQueen";NA;99;0
"Unit";"Queen";"Hatchery";99;2
"Building";"CreepTumor";NA;99;0
"Building";"CreepTumor";NA;99;0
"Building";"CreepTumor";NA;99;0
"Unit";"Overlord";"Larva";99;0
"Unit";"Overlord";"Larva";99;0
"Building";"Extractor";NA;99;0
"Building";"Extractor";NA;99;0
"Building";"CreepTumor";NA;100;0
"Building";"CreepTumorQueen";NA;102;0
"Building";"SporeCrawler";NA;99;0
"Unit";"Overlord";"Larva";102;0
"Building";"SporeCrawler";NA;104;0
"Unit";"Baneling";"Zergling";105;0
"Unit";"Baneling";"Zergling";105;0
"Unit";"Baneling";"Zergling";105;0
"Building";"Hatchery";NA;99;0
"Building";"Extractor";NA;112;0
"Building";"Extractor";NA;118;0
"Building";"Extractor";NA;118;0
"Building";"CreepTumor";NA;127;0
"Building";"CreepTumor";NA;127;0
"Building";"CreepTumorQueen";NA;127;0
"Building";"CreepTumor";NA;127;0
"Building";"CreepTumorQueen";NA;127;0
"Building";"CreepTumor";NA;127;0
"Building";"CreepTumor";NA;127;0
"Building";"HydraliskDen";NA;123;0
"Building";"CreepTumorQueen";NA;127;0
"Building";"CreepTumorQueen";NA;127;0
"Building";"CreepTumorQueen";NA;127;0
"Building";"CreepTumorQueen";NA;127;0
"Unit";"Queen";"Hatchery";127;2
"Building";"EvolutionChamber";NA;129;0
"Building";"EvolutionChamber";NA;129;0
"Building";"CreepTumor";NA;132;0
"Unit";"Overlord";"Larva";129;0
"Unit";"Overlord";"Larva";129;0
"Unit";"Zergling";"Larva";129;1
"Unit";"Zergling";"Larva";129;1
"Unit";"Overlord";"Larva";129;0
"Unit";"Overlord";"Larva";129;0
"Unit";"Zergling";"Larva";129;1
"Unit";"Zergling";"Larva";129;1
"Unit";"Zergling";"Larva";129;1
"Unit";"Zergling";"Larva";129;1
"Unit";"Overlord";"Larva";129;0
"Unit";"Zergling";"Larva";129;1
"Unit";"Zergling";"Larva";129;1
"Unit";"Zergling";"Larva";129;1
"Unit";"Zergling";"Larva";129;1
"Unit";"Zergling";"Larva";129;1
"Unit";"Zergling";"Larva";129;1
"Building";"CreepTumor";NA;138;0
"Building";"CreepTumor";NA;138;0
"Building";"CreepTumor";NA;138;0
"Building";"CreepTumor";NA;138;0
"Building";"InfestationPit";NA;129;0
"Building";"CreepTumor";NA;138;0
"Building";"CreepTumor";NA;138;0
"Building";"CreepTumor";NA;138;0
"Building";"CreepTumorQueen";NA;144;0
"Building";"CreepTumorQueen";NA;150;0
"Building";"CreepTumorQueen";NA;150;0
"Unit";"Zergling";"Larva";138;1
"Unit";"Zergling";"Larva";138;1
"Unit";"Zergling";"Larva";138;1
"Unit";"Zergling";"Larva";138;1
"Building";"SporeCrawler";NA;138;0
"Building";"SporeCrawler";NA;138;0
"Building";"CreepTumorQueen";NA;154;0
"Building";"CreepTumorQueen";NA;154;0
"Building";"CreepTumorQueen";NA;154;0
"Building";"CreepTumorQueen";NA;154;0
"Building";"CreepTumorQueen";NA;154;0
"Building";"CreepTumor";NA;154;0
"Building";"CreepTumor";NA;154;0
"Building";"CreepTumor";NA;160;0
"Building";"CreepTumor";NA;169;0
"Building";"Hatchery";NA;129;0
"Building";"CreepTumor";NA;169;0
"Upgrade";"EvolveGroovedSpines";"HydraliskDen";134;0
"Building";"CreepTumor";NA;169;0
"Building";"CreepTumor";NA;169;0
"Building";"CreepTumor";NA;169;0
"Building";"CreepTumorQueen";NA;171;0
"Unit";"Zergling";"Larva";169;1
"Unit";"Zergling";"Larva";169;1
"Unit";"Zergling";"Larva";169;1
"Unit";"Zergling";"Larva";169;1
"Unit";"Zergling";"Larva";169;1
"Unit";"Zergling";"Larva";169;1
"Unit";"Zergling";"Larva";169;1
"Unit";"Zergling";"Larva";169;1
"Unit";"Zergling";"Larva";169;1
"Unit";"Zergling";"Larva";169;1
"Unit";"Zergling";"Larva";169;1
"Unit";"Zergling";"Larva";169;1
"Unit";"Zergling";"Larva";169;1
"Unit";"Zergling";"Larva";169;1
"Unit";"Zergling";"Larva";169;1
"Unit";"Zergling";"Larva";169;1
"Unit";"Zergling";"Larva";169;1
"Unit";"Zergling";"Larva";169;1
"Unit";"Zergling";"Larva";169;1
"Unit";"Zergling";"Larva";169;1
"Building";"CreepTumor";NA;171;0
"Building";"CreepTumor";NA;171;0
"Building";"CreepTumorQueen";NA;171;0
"Building";"CreepTumor";NA;171;0
"Building";"CreepTumor";NA;171;0
"Building";"CreepTumor";NA;171;0
"Building";"CreepTumor";NA;171;0
"Building";"CreepTumor";NA;171;0
"Building";"CreepTumor";NA;171;0
"Building";"CreepTumor";NA;171;0
"Building";"CreepTumor";NA;171;0
"Unit";"Overlord";"Larva";177;0
"Unit";"Overlord";"Larva";189;0
"Unit";"Hydralisk";"Larva";171;2
"Building";"CreepTumor";NA;191;0
"Unit";"Hydralisk";"Larva";171;2
"Unit";"Hydralisk";"Larva";171;2
"Unit";"Hydralisk";"Larva";171;2
"Unit";"Hydralisk";"Larva";171;2
"Unit";"Hydralisk";"Larva";171;2
"Building";"CreepTumor";NA;191;0
"Building";"CreepTumor";NA;191;0
"Building";"CreepTumor";NA;191;0
"Building";"CreepTumor";NA;191;0
"Building";"SporeCrawler";NA;191;0
"Building";"CreepTumor";NA;191;0
"Building";"CreepTumor";NA;191;0
"Building";"CreepTumor";NA;191;0
"Building";"CreepTumor";NA;191;0
"Building";"CreepTumorQueen";NA;191;0
"Building";"CreepTumor";NA;191;0
"Building";"CreepTumor";NA;191;0
"Building";"CreepTumor";NA;191;0
"Unit";"Overlord";"Larva";191;0
"Unit";"Overlord";"Larva";191;0
"Unit";"Overlord";"Larva";191;0
"Building";"CreepTumor";NA;203;0
"Unit";"Zergling";"Larva";191;1
"Unit";"Zergling";"Larva";191;1
"Unit";"Zergling";"Larva";193;1
"Unit";"Zergling";"Larva";193;1
"Unit";"Zergling";"Larva";193;1
"Unit";"Zergling";"Larva";193;1
"Unit";"Zergling";"Larva";197;1
"Unit";"Zergling";"Larva";197;1
"Unit";"Zergling";"Larva";201;1
"Unit";"Zergling";"Larva";201;1
"Unit";"Zergling";"Larva";201;1
"Unit";"Zergling";"Larva";201;1
"Unit";"Zergling";"Larva";201;1
"Unit";"Zergling";"Larva";201;1
"Unit";"Zergling";"Larva";203;1
"Unit";"Zergling";"Larva";203;1
"Unit";"Zergling";"Larva";203;1
"Unit";"Zergling";"Larva";203;1
"Unit";"Zergling";"Larva";203;1
"Unit";"Zergling";"Larva";203;1
"Unit";"Zergling";"Larva";203;1
"Unit";"Zergling";"Larva";203;1
"Unit";"Zergling";"Larva";203;1
"Unit";"Zergling";"Larva";203;1
"Unit";"Baneling";"Zergling";203;0
"Unit";"Baneling";"Zergling";203;0
"Unit";"Baneling";"Zergling";203;0
"Unit";"Baneling";"Zergling";203;0
"Unit";"Baneling";"Zergling";203;0
"Unit";"Baneling";"Zergling";203;0
"Unit";"Baneling";"Zergling";203;0
"Unit";"Baneling";"Zergling";203;0
"Unit";"Baneling";"Zergling";203;0
"Unit";"Baneling";"Zergling";203;0
"Building";"CreepTumorQueen";NA;203;0
"Building";"CreepTumorQueen";NA;203;0
"Unit";"Queen";"Hatchery";191;2
"Unit";"Zergling";"Larva";227;1
"Unit";"Zergling";"Larva";227;1
"Unit";"Zergling";"Larva";227;1
"Unit";"Zergling";"Larva";227;1
"Unit";"Zergling";"Larva";227;1
"Unit";"Zergling";"Larva";227;1
"Unit";"Zergling";"Larva";227;1
"Unit";"Zergling";"Larva";227;1
"Unit";"Zergling";"Larva";227;1
"Unit";"Zergling";"Larva";227;1
"Unit";"Zergling";"Larva";227;1
"Unit";"Zergling";"Larva";227;1
"Unit";"Zergling";"Larva";227;1
"Unit";"Zergling";"Larva";227;1
"Unit";"Zergling";"Larva";227;1
"Unit";"Zergling";"Larva";227;1
"Unit";"Zergling";"Larva";227;1
"Unit";"Zergling";"Larva";227;1
"Unit";"Baneling";"Zergling";227;0
"Unit";"Baneling";"Zergling";227;0
"Unit";"Baneling";"Zergling";227;0
"Unit";"Baneling";"Zergling";227;0
"Unit";"Baneling";"Zergling";227;0
"Unit";"Baneling";"Zergling";227;0
"Unit";"Baneling";"Zergling";227;0
"Unit";"Baneling";"Zergling";227;0
"Unit";"Hydralisk";"Larva";227;2
"Unit";"Hydralisk";"Larva";227;2
"Unit";"Hydralisk";"Larva";227;2
"Unit";"Hydralisk";"Larva";227;2
"Unit";"Hydralisk";"Larva";227;2
"Upgrade";"ZergGroundArmorsLevel1";"EvolutionChamber";171;0
"Upgrade";"ZergMeleeWeaponsLevel1";"EvolutionChamber";171;0
"Unit";"Viper";"Larva";227;3
"Unit";"Viper";"Larva";227;3
"Unit";"Overlord";"Larva";247;0
"Unit";"Overlord";"Larva";247;0
"Unit";"Overlord";"Larva";247;0
"Unit";"Viper";"Larva";247;3
"Unit";"Zergling";"Larva";266;1
"Unit";"Zergling";"Larva";266;1
"Unit";"Zergling";"Larva";266;1
"Unit";"Zergling";"Larva";266;1
"Unit";"Zergling";"Larva";266;1
"Unit";"Zergling";"Larva";266;1
"Unit";"Zergling";"Larva";266;1
"Unit";"Zergling";"Larva";266;1
"Unit";"Zergling";"Larva";266;1
"Unit";"Zergling";"Larva";266;1
"Unit";"Zergling";"Larva";266;1
"Unit";"Zergling";"Larva";266;1
"Unit";"Zergling";"Larva";266;1
"Unit";"Zergling";"Larva";266;1
"Unit";"Zergling";"Larva";266;1
"Unit";"Zergling";"Larva";266;1
"Unit";"Zergling";"Larva";266;1
"Unit";"Zergling";"Larva";266;1
"Unit";"Zergling";"Larva";266;1
"Unit";"Zergling";"Larva";266;1
"Unit";"Zergling";"Larva";266;1
"Unit";"Zergling";"Larva";266;1
"Unit";"Zergling";"Larva";266;1
"Unit";"Zergling";"Larva";266;1
"Unit";"Zergling";"Larva";266;1
"Unit";"Zergling";"Larva";266;1
"Unit";"Zergling";"Larva";266;1
"Unit";"Zergling";"Larva";266;1
"Unit";"Zergling";"Larva";266;1
"Unit";"Zergling";"Larva";266;1
"Unit";"Viper";"Larva";266;3
