"type";"unit_name";"on_building";"total_supply_lag";"supply"
"Unit";"Overlord";"Larva";13;0
"Building";"Hatchery";NA;17;0
"Building";"Extractor";NA;19;0
"Building";"SpawningPool";NA;19;0
"Unit";"Overlord";"Larva";23;0
"Unit";"Queen";"Hatchery";23;2
"Unit";"Queen";"Hatchery";25;2
"Unit";"Zergling";"Larva";27;1
"Unit";"Zergling";"Larva";28;1
"Building";"Hatchery";NA;32;0
"Unit";"Queen";"Hatchery";33;2
"Unit";"Overlord";"Larva";36;0
"Unit";"Zergling";"Larva";40;1
"Unit";"Zergling";"Larva";41;1
"Unit";"Zergling";"Larva";42;1
"Unit";"Zergling";"Larva";43;1
"Building";"CreepTumorQueen";NA;47;0
"Unit";"Overlord";"Larva";49;0
"Unit";"Queen";"Hatchery";51;2
"Building";"CreepTumor";NA;53;0
"Unit";"Queen";"Hatchery";59;2
"Building";"CreepTumorQueen";NA;61;0
"Unit";"Zergling";"Larva";61;1
"Unit";"Zergling";"Larva";62;1
"Unit";"Overlord";"Larva";63;0
"Unit";"Overlord";"Larva";66;0
"Building";"CreepTumor";NA;66;0
"Unit";"Overlord";"Larva";66;0
"Building";"CreepTumorQueen";NA;66;0
"Unit";"Queen";"Hatchery";70;2
"Building";"EvolutionChamber";NA;77;0
"Building";"CreepTumor";NA;77;0
"Building";"EvolutionChamber";NA;77;0
"Building";"CreepTumor";NA;77;0
"Building";"CreepTumorQueen";NA;77;0
"Building";"SporeCrawler";NA;77;0
"Building";"CreepTumor";NA;77;0
"Building";"SporeCrawler";NA;81;0
"Unit";"Zergling";"Larva";81;1
"Unit";"Zergling";"Larva";82;1
"Unit";"Zergling";"Larva";83;1
"Unit";"Zergling";"Larva";84;1
"Building";"Extractor";NA;86;0
"Building";"CreepTumor";NA;93;0
"Building";"CreepTumor";NA;93;0
"Building";"CreepTumorQueen";NA;93;0
"Building";"CreepTumorQueen";NA;93;0
"Building";"Hatchery";NA;93;0
"Unit";"Overlord";"Larva";93;0
"Unit";"Overlord";"Larva";93;0
"Building";"CreepTumor";NA;94;0
"Building";"BanelingNest";NA;94;0
"Building";"CreepTumor";NA;94;0
"Unit";"Overlord";"Larva";94;0
"Building";"Extractor";NA;94;0
"Building";"Extractor";NA;94;0
"Building";"CreepTumor";NA;94;0
"Building";"CreepTumor";NA;94;0
"Building";"CreepTumorQueen";NA;94;0
"Building";"CreepTumor";NA;96;0
"Building";"CreepTumor";NA;96;0
"Building";"Hatchery";NA;108;0
"Building";"CreepTumor";NA;112;0
"Building";"Extractor";NA;112;0
"Building";"Extractor";NA;112;0
"Unit";"Zergling";"Larva";112;1
"Unit";"Zergling";"Larva";113;1
"Unit";"Zergling";"Larva";114;1
"Unit";"Zergling";"Larva";115;1
"Unit";"Zergling";"Larva";116;1
"Unit";"Zergling";"Larva";117;1
"Unit";"Zergling";"Larva";118;1
"Unit";"Zergling";"Larva";119;1
"Unit";"Zergling";"Larva";120;1
"Unit";"Zergling";"Larva";121;1
"Unit";"Zergling";"Larva";122;1
"Unit";"Zergling";"Larva";123;1
"Building";"CreepTumorQueen";NA;124;0
"Building";"CreepTumorQueen";NA;124;0
"Building";"CreepTumor";NA;124;0
"Building";"CreepTumorQueen";NA;124;0
"Unit";"Zergling";"Larva";126;1
"Unit";"Zergling";"Larva";127;1
"Unit";"Zergling";"Larva";128;1
"Unit";"Zergling";"Larva";129;1
"Unit";"Zergling";"Larva";130;1
"Unit";"Zergling";"Larva";131;1
"Unit";"Zergling";"Larva";132;1
"Unit";"Zergling";"Larva";133;1
"Unit";"Zergling";"Larva";134;1
"Unit";"Zergling";"Larva";135;1
"Unit";"Zergling";"Larva";136;1
"Unit";"Zergling";"Larva";137;1
"Building";"CreepTumor";NA;138;0
"Building";"CreepTumor";NA;138;0
"Unit";"Zergling";"Larva";138;1
"Unit";"Zergling";"Larva";139;1
"Building";"Spire";NA;140;0
"Unit";"Zergling";"Larva";140;1
"Unit";"Zergling";"Larva";141;1
"Unit";"Zergling";"Larva";142;1
"Unit";"Zergling";"Larva";143;1
"Unit";"Baneling";"Zergling";144;0
"Unit";"Baneling";"Zergling";144;0
"Unit";"Baneling";"Zergling";144;0
"Unit";"Baneling";"Zergling";144;0
"Unit";"Baneling";"Zergling";144;0
"Unit";"Overlord";"Larva";144;0
"Unit";"Overlord";"Larva";144;0
"Unit";"Overlord";"Larva";144;0
"Unit";"Baneling";"Zergling";144;0
"Unit";"Baneling";"Zergling";144;0
"Unit";"Baneling";"Zergling";144;0
"Unit";"Baneling";"Zergling";144;0
"Unit";"Baneling";"Zergling";144;0
"Building";"CreepTumor";NA;144;0
"Building";"CreepTumorQueen";NA;144;0
"Building";"CreepTumor";NA;144;0
"Building";"CreepTumor";NA;144;0
"Building";"CreepTumor";NA;144;0
"Building";"CreepTumor";NA;144;0
"Unit";"Overlord";"Larva";144;0
"Unit";"Zergling";"Larva";144;1
"Unit";"Zergling";"Larva";145;1
"Unit";"Zergling";"Larva";146;1
"Unit";"Zergling";"Larva";147;1
"Unit";"Zergling";"Larva";148;1
"Unit";"Zergling";"Larva";149;1
"Unit";"Zergling";"Larva";150;1
"Unit";"Zergling";"Larva";151;1
"Unit";"Zergling";"Larva";152;1
"Unit";"Zergling";"Larva";153;1
"Unit";"Zergling";"Larva";154;1
"Unit";"Zergling";"Larva";155;1
"Unit";"Zergling";"Larva";156;1
"Unit";"Zergling";"Larva";157;1
"Unit";"Zergling";"Larva";158;1
"Unit";"Zergling";"Larva";159;1
"Unit";"Zergling";"Larva";160;1
"Unit";"Zergling";"Larva";161;1
"Unit";"Zergling";"Larva";162;1
"Unit";"Zergling";"Larva";163;1
"Unit";"Zergling";"Larva";164;1
"Unit";"Zergling";"Larva";165;1
"Unit";"Zergling";"Larva";166;1
"Unit";"Zergling";"Larva";167;1
"Unit";"Zergling";"Larva";168;1
"Unit";"Zergling";"Larva";169;1
"Unit";"Zergling";"Larva";170;1
"Unit";"Zergling";"Larva";171;1
"Unit";"Zergling";"Larva";172;1
"Unit";"Zergling";"Larva";173;1
"Unit";"Zergling";"Larva";174;1
"Unit";"Zergling";"Larva";175;1
"Unit";"Zergling";"Larva";176;1
"Unit";"Zergling";"Larva";177;1
"Unit";"Zergling";"Larva";178;1
"Unit";"Zergling";"Larva";179;1
"Unit";"Zergling";"Larva";180;1
"Unit";"Zergling";"Larva";181;1
"Unit";"Zergling";"Larva";182;1
"Unit";"Zergling";"Larva";183;1
"Unit";"Baneling";"Zergling";184;0
"Unit";"Baneling";"Zergling";184;0
"Unit";"Baneling";"Zergling";184;0
"Unit";"Baneling";"Zergling";184;0
"Unit";"Baneling";"Zergling";184;0
"Unit";"Baneling";"Zergling";184;0
"Unit";"Baneling";"Zergling";184;0
"Unit";"Baneling";"Zergling";184;0
"Unit";"Baneling";"Zergling";184;0
"Unit";"Zergling";"Larva";184;1
"Unit";"Zergling";"Larva";185;1
"Unit";"Zergling";"Larva";186;1
"Unit";"Zergling";"Larva";187;1
"Unit";"Zergling";"Larva";188;1
"Unit";"Zergling";"Larva";189;1
"Unit";"Zergling";"Larva";190;1
"Unit";"Zergling";"Larva";191;1
"Unit";"Zergling";"Larva";192;1
"Unit";"Zergling";"Larva";193;1
"Unit";"Zergling";"Larva";194;1
"Unit";"Zergling";"Larva";195;1
"Unit";"Zergling";"Larva";196;1
"Unit";"Zergling";"Larva";197;1
"Unit";"Zergling";"Larva";198;1
"Unit";"Zergling";"Larva";199;1
"Unit";"Zergling";"Larva";200;1
"Unit";"Zergling";"Larva";201;1
"Unit";"Zergling";"Larva";202;1
"Unit";"Zergling";"Larva";203;1
"Unit";"Zergling";"Larva";204;1
"Unit";"Zergling";"Larva";205;1
"Unit";"Zergling";"Larva";206;1
"Unit";"Zergling";"Larva";207;1
"Unit";"Zergling";"Larva";208;1
"Unit";"Zergling";"Larva";209;1
"Unit";"Zergling";"Larva";210;1
"Unit";"Zergling";"Larva";211;1
"Unit";"Zergling";"Larva";212;1
"Unit";"Zergling";"Larva";213;1
"Unit";"Zergling";"Larva";214;1
"Unit";"Zergling";"Larva";215;1
"Unit";"Zergling";"Larva";216;1
"Unit";"Zergling";"Larva";217;1
"Unit";"Zergling";"Larva";218;1
"Unit";"Zergling";"Larva";219;1
"Unit";"Zergling";"Larva";220;1
"Unit";"Zergling";"Larva";221;1
"Unit";"Zergling";"Larva";222;1
"Unit";"Zergling";"Larva";223;1
"Building";"CreepTumor";NA;233;0
"Unit";"Mutalisk";"Larva";233;2
"Unit";"Mutalisk";"Larva";235;2
"Building";"InfestationPit";NA;237;0
"Unit";"Mutalisk";"Larva";237;2
"Unit";"Mutalisk";"Larva";239;2
"Building";"Hatchery";NA;241;0
"Building";"CreepTumorQueen";NA;241;0
"Building";"Hatchery";NA;241;0
"Unit";"Mutalisk";"Larva";250;2
"Unit";"Mutalisk";"Larva";252;2
"Unit";"Overlord";"Larva";254;0
"Unit";"Overlord";"Larva";254;0
"Building";"CreepTumorQueen";NA;254;0
"Building";"CreepTumorQueen";NA;254;0
"Unit";"Overlord";"Larva";254;0
"Unit";"Mutalisk";"Larva";254;2
"Building";"CreepTumor";NA;256;0
"Building";"CreepTumor";NA;256;0
"Building";"CreepTumor";NA;256;0
"Building";"CreepTumor";NA;256;0
"Unit";"Mutalisk";"Larva";256;2
"Unit";"Mutalisk";"Larva";258;2
"Unit";"Mutalisk";"Larva";260;2
"Unit";"Mutalisk";"Larva";262;2
"Building";"CreepTumor";NA;264;0
"Building";"CreepTumor";NA;264;0
"Unit";"Mutalisk";"Larva";264;2
"Unit";"Mutalisk";"Larva";266;2
"Unit";"Zergling";"Larva";268;1
"Unit";"Zergling";"Larva";269;1
"Unit";"Zergling";"Larva";270;1
"Unit";"Zergling";"Larva";271;1
"Unit";"Zergling";"Larva";272;1
"Unit";"Zergling";"Larva";273;1
"Unit";"Zergling";"Larva";274;1
"Unit";"Zergling";"Larva";275;1
"Unit";"Zergling";"Larva";276;1
"Unit";"Zergling";"Larva";277;1
"Unit";"Zergling";"Larva";278;1
"Unit";"Zergling";"Larva";279;1
"Unit";"Zergling";"Larva";280;1
"Unit";"Zergling";"Larva";281;1
"Unit";"Zergling";"Larva";282;1
"Unit";"Zergling";"Larva";283;1
"Building";"CreepTumor";NA;284;0
"Unit";"Mutalisk";"Larva";284;2
"Unit";"Overlord";"Larva";286;0
"Unit";"Overlord";"Larva";286;0
"Unit";"Overlord";"Larva";286;0
"Unit";"Overlord";"Larva";286;0
"Building";"CreepTumor";NA;286;0
"Unit";"Baneling";"Zergling";286;0
"Unit";"Baneling";"Zergling";286;0
"Unit";"Baneling";"Zergling";286;0
"Unit";"Baneling";"Zergling";286;0
"Unit";"Baneling";"Zergling";286;0
"Unit";"Baneling";"Zergling";286;0
"Unit";"Baneling";"Zergling";286;0
"Unit";"Baneling";"Zergling";286;0
"Unit";"Baneling";"Zergling";286;0
"Unit";"Baneling";"Zergling";286;0
"Unit";"Baneling";"Zergling";286;0
"Unit";"Baneling";"Zergling";286;0
"Building";"Extractor";NA;287;0
"Building";"CreepTumorQueen";NA;287;0
"Building";"Extractor";NA;289;0
"Building";"CreepTumorQueen";NA;289;0
"Unit";"Baneling";"Zergling";289;0
"Unit";"Baneling";"Zergling";289;0
"Unit";"Baneling";"Zergling";289;0
"Unit";"Baneling";"Zergling";289;0
"Unit";"Baneling";"Zergling";289;0
"Unit";"Baneling";"Zergling";289;0
"Unit";"Baneling";"Zergling";289;0
"Unit";"Zergling";"Larva";289;1
"Unit";"Zergling";"Larva";290;1
"Unit";"Zergling";"Larva";291;1
"Unit";"Zergling";"Larva";292;1
"Unit";"Zergling";"Larva";293;1
"Unit";"Zergling";"Larva";294;1
"Unit";"Zergling";"Larva";295;1
"Unit";"Zergling";"Larva";296;1
"Unit";"Zergling";"Larva";297;1
"Unit";"Zergling";"Larva";298;1
"Unit";"Zergling";"Larva";299;1
"Unit";"Zergling";"Larva";300;1
"Unit";"Zergling";"Larva";301;1
"Unit";"Zergling";"Larva";302;1
"Unit";"Zergling";"Larva";303;1
"Unit";"Zergling";"Larva";304;1
"Unit";"Zergling";"Larva";305;1
"Unit";"Zergling";"Larva";306;1
"Unit";"Zergling";"Larva";307;1
"Unit";"Zergling";"Larva";308;1
"Unit";"Zergling";"Larva";309;1
"Unit";"Zergling";"Larva";310;1
"Unit";"Zergling";"Larva";311;1
"Unit";"Zergling";"Larva";312;1
"Unit";"Zergling";"Larva";313;1
"Unit";"Zergling";"Larva";314;1
"Unit";"Zergling";"Larva";315;1
"Unit";"Zergling";"Larva";316;1
"Building";"CreepTumorQueen";NA;317;0
"Unit";"Zergling";"Larva";317;1
"Unit";"Zergling";"Larva";318;1
"Unit";"Zergling";"Larva";319;1
"Unit";"Zergling";"Larva";320;1
"Unit";"Zergling";"Larva";321;1
"Unit";"Zergling";"Larva";322;1
"Unit";"Zergling";"Larva";323;1
"Unit";"Zergling";"Larva";324;1
"Unit";"Zergling";"Larva";325;1
"Unit";"Zergling";"Larva";326;1
"Unit";"Zergling";"Larva";327;1
"Unit";"Zergling";"Larva";328;1
"Unit";"Zergling";"Larva";329;1
"Unit";"Zergling";"Larva";330;1
"Unit";"Zergling";"Larva";331;1
"Unit";"Zergling";"Larva";332;1
"Unit";"Zergling";"Larva";333;1
"Unit";"Zergling";"Larva";334;1
"Unit";"Zergling";"Larva";335;1
"Unit";"Zergling";"Larva";336;1
"Unit";"Zergling";"Larva";337;1
"Unit";"Zergling";"Larva";338;1
"Unit";"Zergling";"Larva";339;1
"Unit";"Zergling";"Larva";340;1
"Unit";"Zergling";"Larva";341;1
"Unit";"Zergling";"Larva";342;1
"Unit";"Zergling";"Larva";343;1
"Unit";"Zergling";"Larva";344;1
"Unit";"Zergling";"Larva";345;1
"Unit";"Zergling";"Larva";346;1
"Unit";"Zergling";"Larva";347;1
"Unit";"Zergling";"Larva";348;1
"Unit";"Zergling";"Larva";349;1
"Unit";"Zergling";"Larva";350;1
"Unit";"Zergling";"Larva";351;1
"Unit";"Zergling";"Larva";352;1
"Unit";"Zergling";"Larva";353;1
"Unit";"Zergling";"Larva";354;1
"Unit";"Zergling";"Larva";355;1
"Unit";"Zergling";"Larva";356;1
"Unit";"Zergling";"Larva";357;1
"Unit";"Zergling";"Larva";358;1
"Unit";"Zergling";"Larva";359;1
"Unit";"Zergling";"Larva";360;1
"Unit";"Zergling";"Larva";361;1
"Unit";"Zergling";"Larva";362;1
"Unit";"Zergling";"Larva";363;1
"Unit";"Zergling";"Larva";364;1
"Unit";"Zergling";"Larva";365;1
"Unit";"Zergling";"Larva";366;1
"Unit";"Zergling";"Larva";367;1
"Unit";"Zergling";"Larva";368;1
"Unit";"Zergling";"Larva";369;1
"Unit";"Zergling";"Larva";370;1
"Unit";"Zergling";"Larva";371;1
"Unit";"Zergling";"Larva";372;1
"Unit";"Zergling";"Larva";373;1
"Unit";"Zergling";"Larva";374;1
"Unit";"Zergling";"Larva";375;1
"Unit";"Zergling";"Larva";376;1
"Unit";"Zergling";"Larva";377;1
"Unit";"Zergling";"Larva";378;1
"Unit";"Zergling";"Larva";379;1
"Unit";"Zergling";"Larva";380;1
"Unit";"Zergling";"Larva";381;1
"Unit";"Zergling";"Larva";382;1
"Unit";"Baneling";"Zergling";383;0
"Unit";"Baneling";"Zergling";383;0
"Unit";"Baneling";"Zergling";383;0
"Unit";"Baneling";"Zergling";383;0
"Unit";"Baneling";"Zergling";383;0
"Unit";"Baneling";"Zergling";383;0
"Unit";"Baneling";"Zergling";383;0
"Unit";"Baneling";"Zergling";383;0
"Unit";"Baneling";"Zergling";383;0
"Unit";"Baneling";"Zergling";383;0
"Building";"CreepTumor";NA;383;0
"Building";"CreepTumor";NA;383;0
"Building";"CreepTumor";NA;383;0
"Building";"CreepTumor";NA;383;0
"Building";"CreepTumor";NA;383;0
"Building";"CreepTumor";NA;383;0
"Unit";"Baneling";"Zergling";383;0
"Unit";"Baneling";"Zergling";383;0
"Unit";"Baneling";"Zergling";383;0
"Unit";"Baneling";"Zergling";383;0
"Unit";"Baneling";"Zergling";383;0
"Unit";"Baneling";"Zergling";383;0
"Unit";"Baneling";"Zergling";383;0
"Unit";"Baneling";"Zergling";383;0
"Unit";"Baneling";"Zergling";383;0
"Building";"CreepTumorQueen";NA;383;0
"Unit";"Zergling";"Larva";383;1
"Unit";"Zergling";"Larva";384;1
"Unit";"Zergling";"Larva";385;1
"Unit";"Zergling";"Larva";386;1
"Unit";"Zergling";"Larva";387;1
"Unit";"Zergling";"Larva";388;1
"Unit";"Zergling";"Larva";389;1
"Unit";"Zergling";"Larva";390;1
"Unit";"Zergling";"Larva";391;1
"Unit";"Zergling";"Larva";392;1
"Unit";"Zergling";"Larva";393;1
"Unit";"Zergling";"Larva";394;1
"Unit";"Zergling";"Larva";395;1
"Unit";"Zergling";"Larva";396;1
"Unit";"Zergling";"Larva";397;1
"Unit";"Zergling";"Larva";398;1
"Unit";"Zergling";"Larva";399;1
"Unit";"Zergling";"Larva";400;1
"Unit";"Zergling";"Larva";401;1
"Unit";"Zergling";"Larva";402;1
"Unit";"Zergling";"Larva";403;1
"Unit";"Zergling";"Larva";404;1
"Unit";"Zergling";"Larva";405;1
"Unit";"Zergling";"Larva";406;1
"Unit";"Zergling";"Larva";407;1
"Unit";"Zergling";"Larva";408;1
"Building";"CreepTumorQueen";NA;409;0
"Unit";"Baneling";"Zergling";409;0
"Unit";"Baneling";"Zergling";409;0
"Unit";"Baneling";"Zergling";409;0
"Unit";"Baneling";"Zergling";409;0
"Unit";"Baneling";"Zergling";409;0
"Unit";"Baneling";"Zergling";409;0
"Unit";"Baneling";"Zergling";409;0
"Unit";"Baneling";"Zergling";409;0
"Unit";"Baneling";"Zergling";409;0
"Unit";"Baneling";"Zergling";409;0
"Building";"CreepTumor";NA;409;0
"Building";"CreepTumor";NA;409;0
"Building";"Extractor";NA;409;0
"Building";"SpineCrawler";NA;409;0
"Building";"SporeCrawler";NA;409;0
"Building";"CreepTumor";NA;409;0
"Building";"CreepTumor";NA;409;0
"Unit";"Zergling";"Larva";409;1
"Unit";"Zergling";"Larva";410;1
"Unit";"Zergling";"Larva";411;1
"Unit";"Zergling";"Larva";412;1
"Unit";"Zergling";"Larva";413;1
"Unit";"Zergling";"Larva";414;1
"Unit";"Zergling";"Larva";415;1
"Unit";"Zergling";"Larva";416;1
"Unit";"Zergling";"Larva";417;1
"Unit";"Zergling";"Larva";418;1
"Unit";"Zergling";"Larva";419;1
"Unit";"Zergling";"Larva";420;1
"Unit";"Zergling";"Larva";421;1
"Unit";"Zergling";"Larva";422;1
"Unit";"Zergling";"Larva";423;1
"Unit";"Zergling";"Larva";424;1
"Unit";"Zergling";"Larva";425;1
"Unit";"Zergling";"Larva";426;1
"Unit";"Zergling";"Larva";427;1
"Unit";"Zergling";"Larva";428;1
"Unit";"Zergling";"Larva";429;1
"Unit";"Zergling";"Larva";430;1
"Unit";"Zergling";"Larva";431;1
"Unit";"Zergling";"Larva";432;1
"Unit";"Zergling";"Larva";433;1
"Unit";"Zergling";"Larva";434;1
"Unit";"Zergling";"Larva";435;1
"Unit";"Zergling";"Larva";436;1
"Unit";"Zergling";"Larva";437;1
"Unit";"Zergling";"Larva";438;1
"Unit";"Zergling";"Larva";439;1
"Unit";"Zergling";"Larva";440;1
"Unit";"Zergling";"Larva";441;1
"Unit";"Zergling";"Larva";442;1
"Building";"UltraliskCavern";NA;443;0
"Unit";"Baneling";"Zergling";443;0
"Unit";"Baneling";"Zergling";443;0
"Unit";"Baneling";"Zergling";443;0
"Unit";"Baneling";"Zergling";443;0
"Unit";"Baneling";"Zergling";443;0
"Unit";"Baneling";"Zergling";443;0
"Unit";"Baneling";"Zergling";443;0
"Unit";"Baneling";"Zergling";443;0
"Unit";"Baneling";"Zergling";443;0
"Unit";"Baneling";"Zergling";443;0
"Unit";"Baneling";"Zergling";443;0
"Unit";"Baneling";"Zergling";443;0
"Unit";"Baneling";"Zergling";443;0
"Building";"CreepTumor";NA;443;0
"Unit";"Overlord";"Larva";443;0
"Unit";"Overlord";"Larva";443;0
"Unit";"Overlord";"Larva";443;0
"Building";"SporeCrawler";NA;443;0
"Building";"Hatchery";NA;443;0
"Building";"CreepTumor";NA;443;0
"Building";"CreepTumor";NA;443;0
"Building";"CreepTumor";NA;443;0
"Building";"CreepTumor";NA;443;0
"Building";"CreepTumor";NA;448;0
"Building";"CreepTumor";NA;448;0
"Building";"CreepTumor";NA;448;0
"Unit";"Ultralisk";"Larva";448;6
"Unit";"Ultralisk";"Larva";454;6
"Unit";"Ultralisk";"Larva";460;6
"Upgrade";"ChitinousPlating";"UltraliskCavern";466;0
"Building";"CreepTumor";NA;466;0
"Building";"CreepTumor";NA;466;0
"Building";"Hatchery";NA;466;0
"Upgrade";"Burrow";"Hatchery";466;0
"Building";"Hatchery";NA;466;0
"Building";"Extractor";NA;466;0
"Unit";"Infestor";"Larva";466;2
"Unit";"Infestor";"Larva";468;2
"Unit";"Infestor";"Larva";470;2
"Unit";"Infestor";"Larva";472;2
"Unit";"Infestor";"Larva";474;2
"Unit";"Infestor";"Larva";476;2
"Unit";"Corruptor";"Larva";478;2
"Unit";"Corruptor";"Larva";480;2
"Unit";"Corruptor";"Larva";482;2
"Building";"CreepTumor";NA;484;0
"Building";"CreepTumor";NA;484;0
"Building";"CreepTumor";NA;484;0
"Building";"CreepTumor";NA;484;0
"Unit";"Corruptor";"Larva";484;2
"Unit";"Corruptor";"Larva";486;2
"Unit";"Corruptor";"Larva";488;2
"Unit";"Corruptor";"Larva";490;2
"Unit";"Corruptor";"Larva";492;2
"Unit";"Corruptor";"Larva";494;2
"Building";"CreepTumorQueen";NA;496;0
"Unit";"Overlord";"Larva";496;0
"Building";"CreepTumor";NA;496;0
"Building";"CreepTumor";NA;496;0
"Building";"CreepTumorQueen";NA;496;0
"Building";"CreepTumor";NA;496;0
"Building";"SpineCrawler";NA;496;0
"Building";"CreepTumor";NA;496;0
"Building";"CreepTumorQueen";NA;496;0
"Building";"CreepTumor";NA;496;0
"Building";"CreepTumor";NA;496;0
"Building";"SpineCrawler";NA;496;0
"Building";"SporeCrawler";NA;496;0
"Building";"CreepTumor";NA;496;0
"Unit";"Zergling";"Larva";496;1
"Unit";"Zergling";"Larva";497;1
"Unit";"Zergling";"Larva";498;1
"Unit";"Zergling";"Larva";499;1
"Unit";"Zergling";"Larva";500;1
"Unit";"Zergling";"Larva";501;1
"Unit";"Zergling";"Larva";502;1
"Unit";"Zergling";"Larva";503;1
"Unit";"Zergling";"Larva";504;1
"Unit";"Zergling";"Larva";505;1
"Unit";"Zergling";"Larva";506;1
"Unit";"Zergling";"Larva";507;1
"Unit";"Zergling";"Larva";508;1
"Unit";"Zergling";"Larva";509;1
"Unit";"Zergling";"Larva";510;1
"Unit";"Zergling";"Larva";511;1
"Unit";"Zergling";"Larva";512;1
"Unit";"Zergling";"Larva";513;1
"Building";"CreepTumorQueen";NA;514;0
"Building";"CreepTumor";NA;514;0
"Building";"SporeCrawler";NA;514;0
"Building";"SporeCrawler";NA;514;0
"Building";"SporeCrawler";NA;514;0
"Building";"SporeCrawler";NA;514;0
"Unit";"Corruptor";"Larva";514;2
"Unit";"Corruptor";"Larva";516;2
"Unit";"Corruptor";"Larva";518;2
"Unit";"Corruptor";"Larva";520;2
"Unit";"Corruptor";"Larva";522;2
"Unit";"Corruptor";"Larva";524;2
"Unit";"Corruptor";"Larva";526;2
"Unit";"Corruptor";"Larva";528;2
"Building";"SporeCrawler";NA;530;0
"Unit";"Overlord";"Larva";530;0
"Building";"CreepTumor";NA;530;0
"Building";"CreepTumor";NA;530;0
"Building";"Extractor";NA;536;0
"Building";"CreepTumorQueen";NA;540;0
"Building";"CreepTumorQueen";NA;540;0
"Unit";"Viper";"Larva";540;3
"Building";"CreepTumorQueen";NA;543;0
"Building";"CreepTumorQueen";NA;543;0
"Unit";"Viper";"Larva";543;3
"Upgrade";"NeuralParasite";"InfestationPit";546;0
"Unit";"Baneling";"Zergling";546;0
"Unit";"Baneling";"Zergling";546;0
"Unit";"Baneling";"Zergling";546;0
"Unit";"Baneling";"Zergling";546;0
"Unit";"Baneling";"Zergling";546;0
"Unit";"Baneling";"Zergling";546;0
"Unit";"Baneling";"Zergling";546;0
"Unit";"Baneling";"Zergling";546;0
"Unit";"Baneling";"Zergling";546;0
"Unit";"Baneling";"Zergling";546;0
"Unit";"Baneling";"Zergling";546;0
"Unit";"Baneling";"Zergling";546;0
"Unit";"Baneling";"Zergling";546;0
"Unit";"Baneling";"Zergling";546;0
"Unit";"Baneling";"Zergling";546;0
"Unit";"Baneling";"Zergling";546;0
"Unit";"Zergling";"Larva";546;1
"Unit";"Zergling";"Larva";547;1
"Unit";"Zergling";"Larva";548;1
"Unit";"Zergling";"Larva";549;1
"Unit";"Zergling";"Larva";550;1
"Unit";"Zergling";"Larva";551;1
"Unit";"Zergling";"Larva";552;1
"Unit";"Zergling";"Larva";553;1
"Unit";"Zergling";"Larva";554;1
"Unit";"Zergling";"Larva";555;1
"Unit";"Zergling";"Larva";556;1
"Unit";"Zergling";"Larva";557;1
"Building";"CreepTumorQueen";NA;558;0
"Building";"CreepTumorQueen";NA;558;0
"Building";"CreepTumorQueen";NA;558;0
"Upgrade";"SprayZerg";NA;558;0
"Upgrade";"SprayZerg";NA;558;0
"Upgrade";"SprayZerg";NA;558;0
"Upgrade";"zerglingmovementspeed";NA;558;0
"Upgrade";"SprayZerg";NA;558;0
"Upgrade";"SprayZerg";NA;558;0
"Upgrade";"SprayZerg";NA;558;0
"Upgrade";"SprayZerg";NA;558;0
"Upgrade";"ZergMeleeWeaponsLevel1";NA;558;0
"Upgrade";"ZergGroundArmorsLevel1";NA;558;0
"Upgrade";"SprayZerg";NA;558;0
"Upgrade";"CentrificalHooks";NA;558;0
"Upgrade";"SprayZerg";NA;558;0
"Upgrade";"SprayZerg";NA;558;0
"Upgrade";"overlordspeed";NA;558;0
"Upgrade";"ZergGroundArmorsLevel2";NA;558;0
"Upgrade";"ZergMeleeWeaponsLevel2";NA;558;0
"Upgrade";"SprayZerg";NA;558;0
"Upgrade";"SprayZerg";NA;558;0
"Upgrade";"ZergFlyerWeaponsLevel1";NA;558;0
"Upgrade";"zerglingattackspeed";NA;558;0
"Upgrade";"SprayZerg";NA;558;0
"Upgrade";"ZergMeleeWeaponsLevel3";NA;558;0
"Upgrade";"SprayZerg";NA;558;0
"Upgrade";"ZergGroundArmorsLevel3";NA;558;0
"Upgrade";"SprayZerg";NA;558;0
"Upgrade";"InfestorEnergyUpgrade";NA;558;0
"Upgrade";"SprayZerg";NA;558;0
"Upgrade";"SprayZerg";NA;558;0
"Upgrade";"SprayZerg";NA;558;0
"Upgrade";"ZergFlyerArmorsLevel1";NA;558;0
"Upgrade";"ZergMissileWeaponsLevel1";NA;558;0
"Upgrade";"ZergFlyerWeaponsLevel2";NA;558;0
