"type";"unit_name";"on_building";"total_supply";"supply"
"Unit";"Overlord";"Larva";12;0
"Building";"Extractor";NA;18;0
"Building";"SpawningPool";NA;19;0
"Building";"Hatchery";NA;17;0
"Unit";"Overlord";"Larva";23;0
"Unit";"Zergling";"Larva";23;1
"Unit";"Zergling";"Larva";23;1
"Unit";"Zergling";"Larva";23;1
"Unit";"Zergling";"Larva";23;1
"Unit";"Queen";"Hatchery";23;2
"Unit";"Queen";"Hatchery";23;2
"Building";"CreepTumorQueen";NA;33;0
"Unit";"Overlord";"Larva";33;0
"Unit";"Queen";"Hatchery";33;2
"Building";"CreepTumor";NA;39;0
"Unit";"Overlord";"Larva";37;0
"Unit";"Overlord";"Larva";41;0
"Unit";"Queen";"Hatchery";41;2
"Unit";"Overlord";"Larva";51;0
"Unit";"Overlord";"Larva";51;0
"Unit";"Overlord";"Larva";51;0
"Building";"CreepTumor";NA;58;0
"Building";"CreepTumorQueen";NA;58;0
"Unit";"Overlord";"Larva";58;0
"Building";"CreepTumorQueen";NA;58;0
"Unit";"Zergling";"Larva";58;1
"Unit";"Zergling";"Larva";58;1
"Building";"Extractor";NA;58;0
"Building";"CreepTumorQueen";NA;58;0
"Building";"CreepTumorQueen";NA;58;0
"Unit";"Queen";"Hatchery";51;2
"Building";"CreepTumorQueen";NA;58;0
"Unit";"Zergling";"Larva";58;1
"Unit";"Zergling";"Larva";58;1
"Unit";"Zergling";"Larva";58;1
"Unit";"Zergling";"Larva";58;1
"Unit";"Zergling";"Larva";58;1
"Unit";"Zergling";"Larva";58;1
"Unit";"Zergling";"Larva";58;1
"Unit";"Zergling";"Larva";58;1
"Unit";"Zergling";"Larva";58;1
"Unit";"Zergling";"Larva";58;1
"Building";"CreepTumor";NA;60;0
"Unit";"Overlord";"Larva";60;0
"Building";"Hatchery";NA;47;0
"Unit";"Zergling";"Larva";60;1
"Unit";"Zergling";"Larva";60;1
"Unit";"Zergling";"Larva";60;1
"Unit";"Zergling";"Larva";60;1
"Unit";"Zergling";"Larva";60;1
"Unit";"Zergling";"Larva";60;1
"Building";"CreepTumor";NA;72;0
"Building";"BanelingNest";NA;58;0
"Unit";"Overlord";"Larva";72;0
"Unit";"Overlord";"Larva";72;0
"Unit";"Zergling";"Larva";72;1
"Unit";"Zergling";"Larva";72;1
"Unit";"Zergling";"Larva";72;1
"Unit";"Zergling";"Larva";72;1
"Unit";"Zergling";"Larva";72;1
"Unit";"Zergling";"Larva";72;1
"Unit";"Zergling";"Larva";72;1
"Unit";"Zergling";"Larva";72;1
"Unit";"Zergling";"Larva";72;1
"Unit";"Zergling";"Larva";72;1
"Unit";"Zergling";"Larva";78;1
"Unit";"Zergling";"Larva";78;1
"Unit";"Zergling";"Larva";78;1
"Unit";"Zergling";"Larva";78;1
"Unit";"Zergling";"Larva";78;1
"Unit";"Zergling";"Larva";78;1
"Unit";"Zergling";"Larva";78;1
"Unit";"Zergling";"Larva";78;1
"Unit";"Zergling";"Larva";78;1
"Unit";"Zergling";"Larva";78;1
"Building";"CreepTumor";NA;88;0
"Building";"CreepTumor";NA;88;0
"Unit";"Queen";"Hatchery";78;2
"Unit";"Queen";"Hatchery";78;2
"Building";"CreepTumorQueen";NA;98;0
"Building";"SporeCrawler";NA;103;0
"Unit";"Overlord";"Larva";108;0
"Building";"CreepTumor";NA;114;0
"Building";"Extractor";NA;114;0
"Unit";"Queen";"Hatchery";108;2
"Building";"CreepTumor";NA;117;0
"Building";"CreepTumor";NA;117;0
"Building";"CreepTumor";NA;117;0
"Building";"CreepTumorQueen";NA;120;0
"Building";"CreepTumorQueen";NA;120;0
"Unit";"Overlord";"Larva";117;0
"Building";"CreepTumor";NA;120;0
"Building";"CreepTumor";NA;120;0
"Building";"CreepTumorQueen";NA;120;0
"Building";"CreepTumorQueen";NA;120;0
"Building";"CreepTumor";NA;122;0
"Building";"CreepTumorQueen";NA;128;0
"Building";"CreepTumorQueen";NA;128;0
"Building";"CreepTumor";NA;128;0
"Building";"CreepTumorQueen";NA;128;0
"Building";"CreepTumor";NA;129;0
"Building";"CreepTumor";NA;129;0
"Unit";"Overlord";"Larva";129;0
"Building";"CreepTumor";NA;131;0
"Building";"CreepTumorQueen";NA;131;0
"Building";"CreepTumorQueen";NA;131;0
"Unit";"Baneling";"Zergling";131;0
"Building";"SpineCrawler";NA;122;0
"Unit";"Baneling";"Zergling";131;0
"Building";"Extractor";NA;131;0
"Unit";"Baneling";"Zergling";131;0
"Unit";"Baneling";"Zergling";131;0
"Unit";"Baneling";"Zergling";131;0
"Unit";"Baneling";"Zergling";131;0
"Unit";"Baneling";"Zergling";131;0
"Unit";"Baneling";"Zergling";131;0
"Unit";"Zergling";"Larva";131;1
"Unit";"Zergling";"Larva";131;1
"Unit";"Zergling";"Larva";131;1
"Unit";"Zergling";"Larva";131;1
"Building";"Spire";NA;114;0
"Building";"Extractor";NA;131;0
"Building";"SporeCrawler";NA;131;0
"Building";"CreepTumor";NA;136;0
"Building";"CreepTumor";NA;136;0
"Building";"CreepTumor";NA;136;0
"Unit";"Overlord";"Larva";136;0
"Unit";"Overlord";"Larva";136;0
"Unit";"Overlord";"Larva";136;0
"Building";"CreepTumor";NA;136;0
"Building";"CreepTumor";NA;136;0
"Building";"CreepTumor";NA;136;0
"Building";"CreepTumor";NA;136;0
"Building";"Extractor";NA;136;0
"Building";"CreepTumorQueen";NA;144;0
"Building";"CreepTumorQueen";NA;144;0
"Building";"SpineCrawler";NA;131;0
"Building";"CreepTumorQueen";NA;144;0
"Building";"CreepTumor";NA;144;0
"Unit";"Zergling";"Larva";144;1
"Unit";"Zergling";"Larva";144;1
"Building";"CreepTumor";NA;144;0
"Building";"CreepTumor";NA;144;0
"Unit";"Zergling";"Larva";144;1
"Unit";"Zergling";"Larva";144;1
"Unit";"Zergling";"Larva";144;1
"Unit";"Zergling";"Larva";144;1
"Building";"CreepTumorQueen";NA;144;0
"Building";"CreepTumorQueen";NA;144;0
"Building";"CreepTumor";NA;144;0
"Building";"CreepTumor";NA;144;0
"Unit";"Mutalisk";"Larva";144;2
"Unit";"Mutalisk";"Larva";144;2
"Unit";"Mutalisk";"Larva";144;2
"Building";"CreepTumorQueen";NA;144;0
"Building";"CreepTumorQueen";NA;144;0
"Building";"CreepTumor";NA;144;0
"Building";"CreepTumor";NA;144;0
"Building";"CreepTumor";NA;144;0
"Building";"CreepTumor";NA;144;0
"Building";"CreepTumor";NA;146;0
"Building";"CreepTumorQueen";NA;150;0
"Unit";"Zergling";"Larva";150;1
"Unit";"Zergling";"Larva";150;1
"Unit";"Zergling";"Larva";150;1
"Unit";"Zergling";"Larva";150;1
"Unit";"Zergling";"Larva";150;1
"Unit";"Zergling";"Larva";150;1
"Unit";"Zergling";"Larva";150;1
"Unit";"Zergling";"Larva";150;1
"Unit";"Zergling";"Larva";150;1
"Unit";"Zergling";"Larva";150;1
"Unit";"Zergling";"Larva";150;1
"Unit";"Zergling";"Larva";150;1
"Unit";"Zergling";"Larva";150;1
"Unit";"Zergling";"Larva";150;1
"Unit";"Zergling";"Larva";150;1
"Unit";"Zergling";"Larva";150;1
"Unit";"Zergling";"Larva";150;1
"Unit";"Zergling";"Larva";150;1
"Unit";"Zergling";"Larva";150;1
"Unit";"Zergling";"Larva";150;1
"Unit";"Baneling";"Zergling";156;0
"Unit";"Baneling";"Zergling";156;0
"Unit";"Mutalisk";"Larva";156;2
"Unit";"Mutalisk";"Larva";156;2
"Unit";"Zergling";"Larva";156;1
"Unit";"Zergling";"Larva";156;1
"Unit";"Zergling";"Larva";156;1
"Unit";"Zergling";"Larva";156;1
"Unit";"Zergling";"Larva";156;1
"Unit";"Zergling";"Larva";156;1
"Unit";"Mutalisk";"Larva";156;2
"Building";"CreepTumor";NA;158;0
"Building";"CreepTumor";NA;158;0
"Building";"CreepTumor";NA;168;0
"Building";"CreepTumor";NA;172;0
"Building";"CreepTumor";NA;176;0
"Building";"CreepTumor";NA;176;0
"Building";"CreepTumor";NA;176;0
"Building";"CreepTumor";NA;176;0
"Building";"CreepTumor";NA;176;0
"Building";"CreepTumor";NA;176;0
"Building";"CreepTumor";NA;176;0
"Building";"CreepTumor";NA;176;0
"Building";"CreepTumor";NA;176;0
"Unit";"Baneling";"Zergling";176;0
"Unit";"Baneling";"Zergling";176;0
"Unit";"Baneling";"Zergling";176;0
"Unit";"Baneling";"Zergling";176;0
"Unit";"Baneling";"Zergling";176;0
"Unit";"Baneling";"Zergling";176;0
"Unit";"Baneling";"Zergling";176;0
"Unit";"Baneling";"Zergling";176;0
"Unit";"Zergling";"Larva";176;1
"Unit";"Zergling";"Larva";176;1
"Building";"CreepTumor";NA;176;0
"Unit";"Zergling";"Larva";176;1
"Unit";"Zergling";"Larva";176;1
"Unit";"Zergling";"Larva";176;1
"Unit";"Zergling";"Larva";176;1
"Building";"CreepTumor";NA;188;0
"Building";"CreepTumor";NA;188;0
"Building";"CreepTumorQueen";NA;194;0
"Building";"CreepTumorQueen";NA;194;0
"Unit";"Zergling";"Larva";188;1
"Unit";"Zergling";"Larva";188;1
"Unit";"Zergling";"Larva";188;1
"Unit";"Zergling";"Larva";188;1
"Unit";"Zergling";"Larva";188;1
"Unit";"Zergling";"Larva";188;1
"Unit";"Zergling";"Larva";188;1
"Unit";"Zergling";"Larva";188;1
"Building";"CreepTumor";NA;194;0
"Building";"CreepTumor";NA;194;0
"Building";"CreepTumor";NA;194;0
"Building";"CreepTumor";NA;194;0
"Unit";"Mutalisk";"Larva";188;2
"Building";"CreepTumor";NA;194;0
"Building";"CreepTumor";NA;194;0
"Building";"CreepTumor";NA;194;0
"Building";"CreepTumor";NA;194;0
"Building";"CreepTumor";NA;202;0
"Building";"CreepTumor";NA;202;0
"Unit";"Zergling";"Larva";194;1
"Unit";"Zergling";"Larva";194;1
"Unit";"Zergling";"Larva";194;1
"Unit";"Zergling";"Larva";194;1
"Unit";"Zergling";"Larva";194;1
"Unit";"Zergling";"Larva";194;1
"Unit";"Zergling";"Larva";194;1
"Unit";"Zergling";"Larva";194;1
"Unit";"Zergling";"Larva";194;1
"Unit";"Zergling";"Larva";194;1
"Unit";"Zergling";"Larva";194;1
"Unit";"Zergling";"Larva";194;1
"Unit";"Zergling";"Larva";194;1
"Unit";"Zergling";"Larva";194;1
"Unit";"Zergling";"Larva";194;1
"Unit";"Zergling";"Larva";194;1
"Unit";"Mutalisk";"Larva";194;2
"Building";"CreepTumor";NA;204;0
"Unit";"Mutalisk";"Larva";194;2
"Building";"CreepTumor";NA;204;0
"Building";"CreepTumor";NA;204;0
"Building";"CreepTumorQueen";NA;204;0
"Building";"CreepTumor";NA;204;0
"Building";"CreepTumorQueen";NA;204;0
"Unit";"Mutalisk";"Larva";204;2
"Building";"CreepTumor";NA;220;0
"Building";"CreepTumor";NA;220;0
"Unit";"Zergling";"Larva";224;1
"Unit";"Zergling";"Larva";224;1
"Unit";"Zergling";"Larva";224;1
"Unit";"Zergling";"Larva";224;1
"Unit";"Zergling";"Larva";224;1
"Unit";"Zergling";"Larva";224;1
"Unit";"Zergling";"Larva";224;1
"Unit";"Zergling";"Larva";224;1
"Unit";"Zergling";"Larva";224;1
"Unit";"Zergling";"Larva";224;1
"Unit";"Zergling";"Larva";224;1
"Unit";"Zergling";"Larva";224;1
"Building";"CreepTumor";NA;226;0
"Unit";"Mutalisk";"Larva";224;2
"Unit";"Mutalisk";"Larva";224;2
"Unit";"Mutalisk";"Larva";224;2
"Unit";"Overlord";"Larva";224;0
"Unit";"Overlord";"Larva";224;0
"Unit";"Overlord";"Larva";238;0
"Unit";"Overlord";"Larva";238;0
"Building";"CreepTumor";NA;244;0
"Building";"CreepTumor";NA;244;0
"Unit";"Mutalisk";"Larva";244;2
"Unit";"Mutalisk";"Larva";244;2
"Unit";"Mutalisk";"Larva";244;2
"Unit";"Zergling";"Larva";244;1
"Unit";"Zergling";"Larva";244;1
"Unit";"Mutalisk";"Larva";244;2
"Unit";"Zergling";"Larva";244;1
"Unit";"Zergling";"Larva";244;1
"Unit";"Zergling";"Larva";244;1
"Unit";"Zergling";"Larva";244;1
"Unit";"Zergling";"Larva";244;1
"Unit";"Zergling";"Larva";244;1
"Unit";"Zergling";"Larva";244;1
"Unit";"Zergling";"Larva";244;1
"Unit";"Zergling";"Larva";244;1
"Unit";"Zergling";"Larva";244;1
"Unit";"Zergling";"Larva";244;1
"Unit";"Zergling";"Larva";244;1
"Unit";"Zergling";"Larva";244;1
"Unit";"Zergling";"Larva";244;1
"Unit";"Zergling";"Larva";244;1
"Unit";"Zergling";"Larva";244;1
"Unit";"Zergling";"Larva";244;1
"Unit";"Zergling";"Larva";244;1
"Building";"Extractor";NA;244;0
"Building";"Extractor";NA;244;0
"Unit";"Zergling";"Larva";244;1
"Unit";"Zergling";"Larva";244;1
"Unit";"Zergling";"Larva";244;1
"Unit";"Zergling";"Larva";244;1
"Unit";"Zergling";"Larva";244;1
"Unit";"Zergling";"Larva";244;1
"Building";"EvolutionChamber";NA;244;0
"Building";"EvolutionChamber";NA;244;0
"Unit";"Overlord";"Larva";274;0
"Unit";"Overlord";"Larva";274;0
"Building";"InfestationPit";NA;244;0
"Unit";"Baneling";"Zergling";280;0
"Unit";"Baneling";"Zergling";280;0
"Unit";"Baneling";"Zergling";280;0
"Unit";"Zergling";"Larva";280;1
"Unit";"Zergling";"Larva";280;1
"Unit";"Baneling";"Zergling";280;0
"Unit";"Baneling";"Zergling";280;0
"Unit";"Baneling";"Zergling";280;0
"Unit";"Baneling";"Zergling";280;0
"Unit";"Baneling";"Zergling";280;0
"Unit";"Baneling";"Zergling";280;0
"Unit";"Zergling";"Larva";280;1
"Unit";"Zergling";"Larva";280;1
"Unit";"Zergling";"Larva";280;1
"Unit";"Zergling";"Larva";280;1
"Unit";"Zergling";"Larva";280;1
"Unit";"Zergling";"Larva";280;1
"Building";"CreepTumor";NA;280;0
"Unit";"Mutalisk";"Larva";276;2
"Building";"CreepTumor";NA;280;0
"Unit";"Mutalisk";"Larva";280;2
"Unit";"Mutalisk";"Larva";280;2
"Building";"CreepTumor";NA;280;0
"Building";"CreepTumor";NA;280;0
"Building";"CreepTumor";NA;280;0
"Unit";"Overlord";"Larva";280;0
"Unit";"Overlord";"Larva";280;0
"Unit";"Zergling";"Larva";280;1
"Unit";"Zergling";"Larva";280;1
"Building";"CreepTumorQueen";NA;288;0
"Unit";"Zergling";"Larva";280;1
"Unit";"Zergling";"Larva";280;1
"Unit";"Zergling";"Larva";280;1
"Unit";"Zergling";"Larva";280;1
"Unit";"Zergling";"Larva";280;1
"Unit";"Zergling";"Larva";280;1
"Unit";"Zergling";"Larva";280;1
"Unit";"Zergling";"Larva";280;1
"Unit";"Zergling";"Larva";280;1
"Unit";"Zergling";"Larva";280;1
"Building";"CreepTumorQueen";NA;294;0
"Building";"CreepTumorQueen";NA;294;0
"Building";"CreepTumorQueen";NA;294;0
"Building";"CreepTumorQueen";NA;294;0
"Building";"CreepTumorQueen";NA;294;0
"Building";"Hatchery";NA;244;0
