"type";"unit_name";"on_building";"total_supply";"supply"
"Unit";"Overlord";"Larva";12;0
"Building";"Extractor";NA;19;0
"Unit";"Overlord";"Larva";22;0
"Building";"SpawningPool";NA;19;0
"Building";"Hatchery";NA;17;0
"Unit";"Zergling";"Larva";22;1
"Unit";"Zergling";"Larva";22;1
"Unit";"Zergling";"Larva";22;1
"Unit";"Zergling";"Larva";22;1
"Unit";"Queen";"Hatchery";22;2
"Unit";"Queen";"Hatchery";22;2
"Unit";"Overlord";"Larva";34;0
"Unit";"Overlord";"Larva";37;0
"Building";"CreepTumorQueen";NA;39;0
"Unit";"Queen";"Hatchery";36;2
"Building";"CreepTumor";NA;52;0
"Building";"CreepTumorQueen";NA;54;0
"Building";"CreepTumorQueen";NA;58;0
"Building";"EvolutionChamber";NA;52;0
"Unit";"Overlord";"Larva";58;0
"Building";"Hatchery";NA;39;0
"Unit";"Overlord";"Larva";58;0
"Unit";"Overlord";"Larva";58;0
"Building";"CreepTumorQueen";NA;58;0
"Unit";"Queen";"Hatchery";52;2
"Building";"EvolutionChamber";NA;58;0
"Building";"CreepTumor";NA;59;0
"Building";"CreepTumor";NA;59;0
"Unit";"Zergling";"Larva";59;1
"Unit";"Zergling";"Larva";59;1
"Unit";"Zergling";"Larva";59;1
"Unit";"Zergling";"Larva";59;1
"Unit";"Zergling";"Larva";59;1
"Unit";"Zergling";"Larva";59;1
"Unit";"Zergling";"Larva";59;1
"Unit";"Zergling";"Larva";59;1
"Unit";"Zergling";"Larva";59;1
"Unit";"Zergling";"Larva";59;1
"Unit";"Zergling";"Larva";59;1
"Unit";"Zergling";"Larva";59;1
"Unit";"Zergling";"Larva";59;1
"Unit";"Zergling";"Larva";59;1
"Unit";"Zergling";"Larva";61;1
"Unit";"Zergling";"Larva";61;1
"Building";"CreepTumor";NA;75;0
"Unit";"Zergling";"Larva";61;1
"Unit";"Zergling";"Larva";61;1
"Unit";"Zergling";"Larva";61;1
"Unit";"Zergling";"Larva";61;1
"Unit";"Zergling";"Larva";61;1
"Unit";"Zergling";"Larva";61;1
"Unit";"Zergling";"Larva";61;1
"Unit";"Zergling";"Larva";61;1
"Unit";"Queen";"Hatchery";59;2
"Building";"CreepTumor";NA;75;0
"Building";"CreepTumor";NA;75;0
"Building";"CreepTumorQueen";NA;75;0
"Building";"CreepTumorQueen";NA;75;0
"Unit";"Queen";"Hatchery";59;2
"Building";"CreepTumorQueen";NA;75;0
"Unit";"Queen";"Hatchery";61;2
"Unit";"Zergling";"Larva";87;1
"Unit";"Zergling";"Larva";87;1
"Unit";"Zergling";"Larva";87;1
"Unit";"Zergling";"Larva";87;1
"Building";"Extractor";NA;77;0
"Building";"Extractor";NA;87;0
"Building";"CreepTumor";NA;98;0
"Unit";"Zergling";"Larva";95;1
"Unit";"Zergling";"Larva";95;1
"Unit";"Zergling";"Larva";95;1
"Unit";"Zergling";"Larva";95;1
"Unit";"Zergling";"Larva";95;1
"Unit";"Zergling";"Larva";95;1
"Building";"CreepTumorQueen";NA;102;0
"Unit";"Overlord";"Larva";102;0
"Unit";"Overlord";"Larva";102;0
"Unit";"Overlord";"Larva";102;0
"Building";"CreepTumorQueen";NA;111;0
"Building";"CreepTumorQueen";NA;111;0
"Building";"CreepTumor";NA;111;0
"Building";"CreepTumor";NA;111;0
"Building";"CreepTumor";NA;111;0
"Building";"CreepTumor";NA;111;0
"Building";"BanelingNest";NA;95;0
"Unit";"Overlord";"Larva";111;0
"Unit";"Overlord";"Larva";111;0
"Unit";"Overlord";"Larva";111;0
"Unit";"Overlord";"Larva";111;0
"Building";"CreepTumor";NA;111;0
"Building";"CreepTumor";NA;111;0
"Unit";"Zergling";"Larva";111;1
"Unit";"Zergling";"Larva";111;1
"Unit";"Zergling";"Larva";111;1
"Unit";"Zergling";"Larva";111;1
"Unit";"Zergling";"Larva";111;1
"Unit";"Zergling";"Larva";111;1
"Unit";"Zergling";"Larva";111;1
"Unit";"Zergling";"Larva";111;1
"Unit";"Zergling";"Larva";111;1
"Unit";"Zergling";"Larva";111;1
"Unit";"Zergling";"Larva";111;1
"Unit";"Zergling";"Larva";111;1
"Unit";"Zergling";"Larva";111;1
"Unit";"Zergling";"Larva";111;1
"Unit";"Zergling";"Larva";111;1
"Unit";"Zergling";"Larva";111;1
"Unit";"Zergling";"Larva";111;1
"Unit";"Zergling";"Larva";111;1
"Unit";"Zergling";"Larva";111;1
"Unit";"Zergling";"Larva";111;1
"Unit";"Baneling";"Zergling";111;0
"Unit";"Baneling";"Zergling";111;0
"Building";"CreepTumor";NA;111;0
"Unit";"Baneling";"Zergling";111;0
"Building";"CreepTumor";NA;111;0
"Building";"CreepTumor";NA;111;0
"Unit";"Zergling";"Larva";111;1
"Unit";"Zergling";"Larva";111;1
"Unit";"Zergling";"Larva";111;1
"Unit";"Zergling";"Larva";111;1
"Unit";"Zergling";"Larva";111;1
"Unit";"Zergling";"Larva";111;1
"Upgrade";"ZergGroundArmorsLevel1";"EvolutionChamber";87;0
"Building";"CreepTumorQueen";NA;137;0
"Building";"CreepTumorQueen";NA;137;0
"Unit";"Overlord";"Larva";137;0
"Unit";"Overlord";"Larva";137;0
"Unit";"Zergling";"Larva";145;1
"Unit";"Zergling";"Larva";145;1
"Unit";"Overlord";"Larva";147;0
"Upgrade";"ZergMeleeWeaponsLevel1";"EvolutionChamber";111;0
"Building";"CreepTumor";NA;149;0
"Building";"CreepTumor";NA;149;0
"Unit";"Queen";"Hatchery";146;2
"Unit";"Zergling";"Larva";149;1
"Unit";"Zergling";"Larva";149;1
"Unit";"Zergling";"Larva";149;1
"Unit";"Zergling";"Larva";149;1
"Unit";"Zergling";"Larva";149;1
"Unit";"Zergling";"Larva";149;1
"Unit";"Zergling";"Larva";149;1
"Unit";"Zergling";"Larva";149;1
"Unit";"Zergling";"Larva";149;1
"Unit";"Zergling";"Larva";149;1
"Unit";"Zergling";"Larva";149;1
"Unit";"Zergling";"Larva";149;1
"Unit";"Zergling";"Larva";149;1
"Unit";"Zergling";"Larva";149;1
"Unit";"Zergling";"Larva";149;1
"Unit";"Zergling";"Larva";149;1
"Unit";"Zergling";"Larva";149;1
"Unit";"Zergling";"Larva";149;1
"Unit";"Zergling";"Larva";149;1
"Unit";"Zergling";"Larva";149;1
"Unit";"Zergling";"Larva";149;1
"Unit";"Zergling";"Larva";149;1
"Unit";"Zergling";"Larva";149;1
"Unit";"Zergling";"Larva";149;1
"Unit";"Zergling";"Larva";149;1
"Unit";"Zergling";"Larva";149;1
"Unit";"Zergling";"Larva";149;1
"Unit";"Zergling";"Larva";149;1
"Unit";"Zergling";"Larva";149;1
"Unit";"Zergling";"Larva";149;1
"Unit";"Zergling";"Larva";149;1
"Unit";"Zergling";"Larva";149;1
"Unit";"Zergling";"Larva";149;1
"Unit";"Zergling";"Larva";149;1
"Building";"Extractor";NA;149;0
"Building";"HydraliskDen";NA;149;0
"Building";"CreepTumorQueen";NA;173;0
"Building";"CreepTumor";NA;173;0
"Unit";"Zergling";"Larva";173;1
"Unit";"Zergling";"Larva";173;1
"Building";"CreepTumorQueen";NA;185;0
"Unit";"Zergling";"Larva";173;1
"Unit";"Zergling";"Larva";173;1
"Unit";"Zergling";"Larva";173;1
"Unit";"Zergling";"Larva";173;1
"Unit";"Zergling";"Larva";173;1
"Unit";"Zergling";"Larva";173;1
"Unit";"Zergling";"Larva";173;1
"Unit";"Zergling";"Larva";173;1
"Unit";"Zergling";"Larva";173;1
"Unit";"Zergling";"Larva";173;1
"Unit";"Zergling";"Larva";173;1
"Unit";"Zergling";"Larva";173;1
"Building";"CreepTumorQueen";NA;185;0
"Building";"CreepTumorQueen";NA;185;0
"Unit";"Overlord";"Larva";185;0
"Unit";"Overlord";"Larva";185;0
"Building";"Hatchery";NA;147;0
"Unit";"Hydralisk";"Larva";185;2
"Unit";"Hydralisk";"Larva";187;2
"Unit";"Hydralisk";"Larva";187;2
"Unit";"Hydralisk";"Larva";187;2
"Unit";"Hydralisk";"Larva";187;2
"Building";"CreepTumorQueen";NA;199;0
"Building";"CreepTumor";NA;199;0
"Building";"CreepTumor";NA;199;0
"Building";"CreepTumorQueen";NA;199;0
"Building";"CreepTumor";NA;199;0
"Building";"CreepTumor";NA;199;0
"Building";"CreepTumor";NA;199;0
"Building";"CreepTumor";NA;199;0
"Building";"Hatchery";NA;149;0
"Building";"CreepTumor";NA;209;0
"Building";"CreepTumor";NA;209;0
"Unit";"Zergling";"Larva";209;1
"Unit";"Zergling";"Larva";209;1
"Unit";"Zergling";"Larva";209;1
"Unit";"Zergling";"Larva";209;1
"Unit";"Zergling";"Larva";209;1
"Unit";"Zergling";"Larva";209;1
"Unit";"Zergling";"Larva";209;1
"Unit";"Zergling";"Larva";209;1
"Unit";"Zergling";"Larva";209;1
"Unit";"Zergling";"Larva";209;1
"Unit";"Zergling";"Larva";209;1
"Unit";"Zergling";"Larva";209;1
"Unit";"Zergling";"Larva";209;1
"Unit";"Zergling";"Larva";209;1
"Unit";"Zergling";"Larva";209;1
"Unit";"Zergling";"Larva";209;1
"Unit";"Zergling";"Larva";209;1
"Unit";"Zergling";"Larva";209;1
"Unit";"Zergling";"Larva";209;1
"Unit";"Zergling";"Larva";209;1
"Unit";"Hydralisk";"Larva";209;2
"Unit";"Hydralisk";"Larva";209;2
"Unit";"Hydralisk";"Larva";209;2
"Building";"CreepTumor";NA;239;0
"Building";"Extractor";NA;209;0
"Building";"CreepTumorQueen";NA;243;0
"Building";"Extractor";NA;232;0
"Building";"CreepTumor";NA;243;0
"Building";"CreepTumorQueen";NA;243;0
"Upgrade";"EvolveMuscularAugments";"HydraliskDen";199;0
"Building";"CreepTumorQueen";NA;243;0
"Building";"CreepTumor";NA;243;0
"Building";"CreepTumor";NA;243;0
"Upgrade";"Burrow";"Hatchery";209;0
"Building";"InfestationPit";NA;236;0
"Building";"CreepTumorQueen";NA;243;0
"Unit";"Baneling";"Zergling";243;0
"Unit";"Baneling";"Zergling";243;0
"Unit";"Baneling";"Zergling";243;0
"Unit";"Baneling";"Zergling";243;0
"Unit";"Baneling";"Zergling";243;0
"Unit";"Baneling";"Zergling";243;0
"Unit";"Baneling";"Zergling";243;0
"Unit";"Baneling";"Zergling";243;0
"Unit";"Baneling";"Zergling";243;0
"Unit";"Baneling";"Zergling";243;0
"Unit";"Baneling";"Zergling";243;0
"Unit";"Baneling";"Zergling";243;0
"Unit";"Baneling";"Zergling";243;0
"Building";"CreepTumor";NA;243;0
"Building";"CreepTumor";NA;243;0
"Building";"CreepTumor";NA;243;0
"Upgrade";"ZergGroundArmorsLevel2";"EvolutionChamber";199;0
"Upgrade";"ZergMeleeWeaponsLevel2";"EvolutionChamber";199;0
"Building";"CreepTumor";NA;243;0
"Unit";"Zergling";"Larva";243;1
"Unit";"Zergling";"Larva";243;1
"Unit";"Zergling";"Larva";243;1
"Unit";"Zergling";"Larva";243;1
"Unit";"Zergling";"Larva";243;1
"Unit";"Zergling";"Larva";243;1
"Unit";"Zergling";"Larva";243;1
"Unit";"Zergling";"Larva";243;1
"Unit";"Zergling";"Larva";243;1
"Unit";"Zergling";"Larva";243;1
"Unit";"Zergling";"Larva";243;1
"Unit";"Zergling";"Larva";243;1
"Unit";"Zergling";"Larva";243;1
"Unit";"Zergling";"Larva";243;1
"Unit";"Zergling";"Larva";243;1
"Unit";"Zergling";"Larva";243;1
"Unit";"Zergling";"Larva";243;1
"Unit";"Zergling";"Larva";243;1
"Unit";"Zergling";"Larva";243;1
"Unit";"Zergling";"Larva";243;1
"Unit";"Zergling";"Larva";243;1
"Unit";"Zergling";"Larva";243;1
"Unit";"Zergling";"Larva";243;1
"Unit";"Zergling";"Larva";243;1
"Unit";"Zergling";"Larva";243;1
"Unit";"Zergling";"Larva";243;1
"Unit";"Zergling";"Larva";243;1
"Unit";"Zergling";"Larva";243;1
"Unit";"Zergling";"Larva";243;1
"Unit";"Zergling";"Larva";243;1
"Unit";"Zergling";"Larva";243;1
"Unit";"Zergling";"Larva";243;1
"Unit";"Zergling";"Larva";243;1
"Unit";"Zergling";"Larva";243;1
"Unit";"Zergling";"Larva";243;1
"Unit";"Zergling";"Larva";243;1
"Unit";"Zergling";"Larva";243;1
"Unit";"Zergling";"Larva";243;1
"Building";"CreepTumor";NA;243;0
"Unit";"Baneling";"Zergling";243;0
"Unit";"Baneling";"Zergling";243;0
"Unit";"Baneling";"Zergling";243;0
"Unit";"Baneling";"Zergling";243;0
"Unit";"Baneling";"Zergling";243;0
"Unit";"Baneling";"Zergling";243;0
"Unit";"Baneling";"Zergling";243;0
"Unit";"Baneling";"Zergling";243;0
"Unit";"Baneling";"Zergling";243;0
"Unit";"Baneling";"Zergling";243;0
"Unit";"Baneling";"Zergling";243;0
"Unit";"Baneling";"Zergling";243;0
"Unit";"Baneling";"Zergling";246;0
"Unit";"Baneling";"Zergling";246;0
"Unit";"Baneling";"Zergling";246;0
"Unit";"Baneling";"Zergling";246;0
"Unit";"Baneling";"Zergling";246;0
"Unit";"Zergling";"Larva";284;1
"Unit";"Zergling";"Larva";284;1
"Unit";"Overlord";"Larva";266;0
"Unit";"Zergling";"Larva";284;1
"Unit";"Zergling";"Larva";284;1
"Unit";"Zergling";"Larva";284;1
"Unit";"Zergling";"Larva";284;1
"Unit";"Zergling";"Larva";284;1
"Unit";"Zergling";"Larva";284;1
"Unit";"Zergling";"Larva";284;1
"Unit";"Zergling";"Larva";284;1
"Unit";"Zergling";"Larva";298;1
"Unit";"Zergling";"Larva";298;1
"Unit";"Zergling";"Larva";298;1
"Unit";"Zergling";"Larva";298;1
"Unit";"Zergling";"Larva";298;1
"Unit";"Zergling";"Larva";298;1
"Unit";"Zergling";"Larva";298;1
"Unit";"Zergling";"Larva";298;1
"Unit";"Zergling";"Larva";298;1
"Unit";"Zergling";"Larva";298;1
"Unit";"Zergling";"Larva";298;1
"Unit";"Zergling";"Larva";298;1
"Unit";"Zergling";"Larva";298;1
"Unit";"Zergling";"Larva";298;1
"Unit";"Zergling";"Larva";298;1
"Unit";"Zergling";"Larva";298;1
"Unit";"Zergling";"Larva";298;1
"Unit";"Zergling";"Larva";298;1
"Unit";"Zergling";"Larva";298;1
"Unit";"Zergling";"Larva";298;1
"Unit";"Zergling";"Larva";298;1
"Unit";"Zergling";"Larva";298;1
"Unit";"Zergling";"Larva";298;1
"Unit";"Zergling";"Larva";298;1
"Unit";"Zergling";"Larva";298;1
"Unit";"Zergling";"Larva";298;1
"Unit";"Zergling";"Larva";298;1
"Unit";"Zergling";"Larva";298;1
"Unit";"Zergling";"Larva";298;1
"Unit";"Zergling";"Larva";298;1
"Unit";"Zergling";"Larva";298;1
"Unit";"Zergling";"Larva";298;1
"Unit";"Zergling";"Larva";298;1
"Unit";"Zergling";"Larva";298;1
"Unit";"Zergling";"Larva";298;1
"Unit";"Zergling";"Larva";298;1
"Building";"CreepTumor";NA;298;0
"Building";"CreepTumor";NA;298;0
"Building";"CreepTumor";NA;298;0
"Building";"CreepTumor";NA;298;0
"Building";"CreepTumor";NA;298;0
"Building";"CreepTumorQueen";NA;298;0
"Unit";"Hydralisk";"Larva";298;2
"Unit";"Hydralisk";"Larva";298;2
"Building";"CreepTumor";NA;334;0
"Building";"CreepTumor";NA;334;0
"Unit";"Baneling";"Zergling";334;0
"Unit";"Hydralisk";"Larva";334;2
"Unit";"Baneling";"Zergling";334;0
"Unit";"Baneling";"Zergling";334;0
"Unit";"Baneling";"Zergling";334;0
"Unit";"Baneling";"Zergling";334;0
"Unit";"Hydralisk";"Larva";334;2
"Unit";"Baneling";"Zergling";334;0
"Unit";"Baneling";"Zergling";334;0
"Unit";"Baneling";"Zergling";336;0
"Unit";"Baneling";"Zergling";336;0
"Unit";"Hydralisk";"Larva";334;2
"Unit";"Hydralisk";"Larva";334;2
"Unit";"Hydralisk";"Larva";334;2
"Unit";"Hydralisk";"Larva";334;2
"Unit";"Baneling";"Zergling";336;0
"Unit";"Baneling";"Zergling";336;0
"Unit";"Hydralisk";"Larva";334;2
"Unit";"Hydralisk";"Larva";334;2
"Building";"CreepTumor";NA;338;0
"Building";"CreepTumor";NA;338;0
"Building";"CreepTumor";NA;338;0
"Building";"CreepTumor";NA;338;0
"Unit";"Zergling";"Larva";338;1
"Unit";"Zergling";"Larva";338;1
"Unit";"Zergling";"Larva";338;1
"Unit";"Zergling";"Larva";338;1
"Unit";"Zergling";"Larva";338;1
"Unit";"Zergling";"Larva";338;1
"Unit";"Zergling";"Larva";338;1
"Unit";"Zergling";"Larva";338;1
"Unit";"Zergling";"Larva";338;1
"Unit";"Zergling";"Larva";338;1
"Unit";"Zergling";"Larva";338;1
"Unit";"Zergling";"Larva";338;1
"Unit";"Zergling";"Larva";338;1
"Unit";"Zergling";"Larva";338;1
"Unit";"Zergling";"Larva";338;1
"Unit";"Zergling";"Larva";338;1
"Unit";"Zergling";"Larva";338;1
"Unit";"Zergling";"Larva";338;1
"Unit";"Baneling";"Zergling";338;0
"Unit";"Baneling";"Zergling";338;0
"Unit";"Baneling";"Zergling";338;0
"Unit";"Baneling";"Zergling";338;0
"Unit";"Baneling";"Zergling";338;0
"Unit";"Baneling";"Zergling";338;0
"Unit";"Baneling";"Zergling";338;0
"Unit";"Baneling";"Zergling";338;0
"Unit";"Zergling";"Larva";364;1
"Unit";"Zergling";"Larva";364;1
"Unit";"Zergling";"Larva";364;1
"Unit";"Zergling";"Larva";364;1
"Unit";"Zergling";"Larva";364;1
"Unit";"Zergling";"Larva";364;1
"Unit";"Zergling";"Larva";364;1
"Unit";"Zergling";"Larva";364;1
"Unit";"Zergling";"Larva";364;1
"Unit";"Zergling";"Larva";364;1
"Unit";"Zergling";"Larva";364;1
"Unit";"Zergling";"Larva";364;1
"Unit";"Zergling";"Larva";364;1
"Unit";"Zergling";"Larva";364;1
"Unit";"Zergling";"Larva";364;1
"Unit";"Zergling";"Larva";364;1
"Unit";"Zergling";"Larva";364;1
"Unit";"Zergling";"Larva";364;1
"Unit";"Zergling";"Larva";364;1
"Unit";"Zergling";"Larva";364;1
"Unit";"Zergling";"Larva";364;1
"Unit";"Zergling";"Larva";364;1
"Unit";"Baneling";"Zergling";372;0
"Unit";"Baneling";"Zergling";372;0
"Unit";"Baneling";"Zergling";372;0
"Unit";"Baneling";"Zergling";372;0
"Unit";"Baneling";"Zergling";372;0
"Unit";"Baneling";"Zergling";372;0
"Unit";"Zergling";"Larva";372;1
"Unit";"Zergling";"Larva";372;1
"Unit";"Baneling";"Zergling";394;0
"Unit";"Baneling";"Zergling";394;0
"Unit";"Baneling";"Zergling";394;0
"Unit";"Baneling";"Zergling";394;0
"Unit";"Baneling";"Zergling";394;0
"Unit";"Baneling";"Zergling";394;0
"Unit";"Baneling";"Zergling";394;0
"Unit";"Baneling";"Zergling";394;0
"Unit";"Baneling";"Zergling";394;0
"Unit";"Baneling";"Zergling";394;0
"Unit";"Baneling";"Zergling";394;0
"Unit";"Hydralisk";"Larva";372;2
"Unit";"Zergling";"Larva";394;1
"Unit";"Zergling";"Larva";394;1
"Unit";"Zergling";"Larva";394;1
"Unit";"Zergling";"Larva";394;1
"Unit";"Zergling";"Larva";394;1
"Unit";"Zergling";"Larva";394;1
"Unit";"Zergling";"Larva";394;1
"Unit";"Zergling";"Larva";394;1
"Unit";"Zergling";"Larva";394;1
"Unit";"Zergling";"Larva";394;1
"Unit";"Zergling";"Larva";394;1
"Unit";"Zergling";"Larva";394;1
"Unit";"Zergling";"Larva";394;1
"Unit";"Zergling";"Larva";394;1
"Unit";"Zergling";"Larva";394;1
"Unit";"Zergling";"Larva";394;1
"Unit";"Zergling";"Larva";394;1
"Unit";"Zergling";"Larva";394;1
"Unit";"Zergling";"Larva";394;1
"Unit";"Zergling";"Larva";394;1
"Unit";"Zergling";"Larva";394;1
"Unit";"Zergling";"Larva";394;1
"Unit";"Zergling";"Larva";394;1
"Unit";"Zergling";"Larva";394;1
"Unit";"Zergling";"Larva";394;1
"Unit";"Zergling";"Larva";394;1
"Unit";"Zergling";"Larva";396;1
"Unit";"Zergling";"Larva";396;1
"Unit";"Zergling";"Larva";396;1
"Unit";"Zergling";"Larva";396;1
"Unit";"Zergling";"Larva";396;1
"Unit";"Zergling";"Larva";396;1
"Unit";"Zergling";"Larva";396;1
"Unit";"Zergling";"Larva";396;1
"Unit";"Zergling";"Larva";396;1
"Unit";"Zergling";"Larva";396;1
"Unit";"Zergling";"Larva";396;1
"Unit";"Zergling";"Larva";396;1
"Unit";"Zergling";"Larva";396;1
"Unit";"Zergling";"Larva";396;1
"Unit";"Zergling";"Larva";396;1
"Unit";"Zergling";"Larva";396;1
"Unit";"Zergling";"Larva";396;1
"Unit";"Zergling";"Larva";396;1
"Building";"Hatchery";NA;354;0
"Unit";"Hydralisk";"Larva";424;2
"Unit";"Hydralisk";"Larva";424;2
"Unit";"Hydralisk";"Larva";424;2
"Unit";"Hydralisk";"Larva";424;2
"Unit";"Hydralisk";"Larva";424;2
"Unit";"Hydralisk";"Larva";424;2
"Unit";"Hydralisk";"Larva";424;2
"Unit";"Hydralisk";"Larva";424;2
"Unit";"Hydralisk";"Larva";424;2
"Unit";"Zergling";"Larva";442;1
"Unit";"Zergling";"Larva";442;1
"Unit";"Zergling";"Larva";442;1
"Unit";"Zergling";"Larva";442;1
"Unit";"Zergling";"Larva";442;1
"Unit";"Zergling";"Larva";442;1
"Unit";"Zergling";"Larva";442;1
"Unit";"Zergling";"Larva";442;1
"Unit";"Zergling";"Larva";442;1
"Unit";"Zergling";"Larva";442;1
"Unit";"Baneling";"Zergling";460;0
"Unit";"Baneling";"Zergling";460;0
"Unit";"Baneling";"Zergling";460;0
"Unit";"Baneling";"Zergling";460;0
"Unit";"Hydralisk";"Larva";442;2
"Unit";"Hydralisk";"Larva";442;2
"Unit";"Hydralisk";"Larva";442;2
"Unit";"Hydralisk";"Larva";442;2
"Unit";"Zergling";"Larva";460;1
"Unit";"Zergling";"Larva";460;1
"Unit";"Zergling";"Larva";460;1
"Unit";"Zergling";"Larva";460;1
"Unit";"Zergling";"Larva";460;1
"Unit";"Zergling";"Larva";460;1
"Unit";"Zergling";"Larva";460;1
"Unit";"Zergling";"Larva";460;1
"Unit";"Hydralisk";"Larva";442;2
"Unit";"Hydralisk";"Larva";442;2
"Unit";"Hydralisk";"Larva";442;2
"Building";"Extractor";NA;470;0
"Building";"Extractor";NA;470;0
"Building";"CreepTumor";NA;492;0
"Building";"CreepTumor";NA;492;0
"Building";"CreepTumor";NA;492;0
"Unit";"Hydralisk";"Larva";492;2
"Unit";"Hydralisk";"Larva";492;2
"Unit";"Hydralisk";"Larva";492;2
"Unit";"Hydralisk";"Larva";492;2
"Unit";"Hydralisk";"Larva";492;2
"Unit";"Hydralisk";"Larva";492;2
"Unit";"Hydralisk";"Larva";492;2
"Unit";"Hydralisk";"Larva";492;2
"Building";"CreepTumorQueen";NA;513;0
"Building";"CreepTumorQueen";NA;513;0
"Building";"CreepTumorQueen";NA;513;0
"Building";"CreepTumor";NA;513;0
"Building";"CreepTumorQueen";NA;513;0
"Building";"CreepTumorQueen";NA;513;0
"Building";"CreepTumorQueen";NA;513;0
"Unit";"Overlord";"Larva";513;0
"Unit";"Overlord";"Larva";513;0
"Unit";"Overlord";"Larva";513;0
"Building";"CreepTumorQueen";NA;513;0
"Building";"CreepTumorQueen";NA;513;0
"Unit";"Zergling";"Larva";513;1
"Unit";"Zergling";"Larva";513;1
"Building";"CreepTumor";NA;513;0
"Building";"CreepTumor";NA;513;0
"Building";"CreepTumor";NA;513;0
"Building";"CreepTumor";NA;513;0
"Building";"CreepTumor";NA;513;0
"Building";"CreepTumor";NA;513;0
"Building";"CreepTumor";NA;513;0
"Building";"Hatchery";NA;492;0
"Unit";"Overlord";"Larva";513;0
"Unit";"Overlord";"Larva";513;0
"Unit";"Baneling";"Zergling";515;0
"Unit";"Baneling";"Zergling";515;0
"Unit";"Baneling";"Zergling";515;0
"Unit";"Baneling";"Zergling";515;0
"Unit";"Baneling";"Zergling";515;0
"Unit";"Baneling";"Zergling";515;0
"Unit";"Baneling";"Zergling";515;0
"Unit";"Baneling";"Zergling";515;0
"Unit";"Baneling";"Zergling";515;0
"Unit";"Baneling";"Zergling";515;0
"Building";"UltraliskCavern";NA;513;0
"Unit";"Zergling";"Larva";515;1
"Unit";"Zergling";"Larva";515;1
"Unit";"Zergling";"Larva";515;1
"Unit";"Zergling";"Larva";515;1
"Unit";"Zergling";"Larva";515;1
"Unit";"Zergling";"Larva";515;1
"Unit";"Zergling";"Larva";515;1
"Unit";"Zergling";"Larva";515;1
"Unit";"Zergling";"Larva";515;1
"Unit";"Zergling";"Larva";515;1
"Unit";"Zergling";"Larva";515;1
"Unit";"Zergling";"Larva";515;1
"Unit";"Zergling";"Larva";515;1
"Unit";"Zergling";"Larva";515;1
"Unit";"Zergling";"Larva";515;1
"Unit";"Zergling";"Larva";515;1
"Unit";"Zergling";"Larva";515;1
"Unit";"Zergling";"Larva";515;1
"Unit";"Zergling";"Larva";515;1
"Unit";"Zergling";"Larva";515;1
"Unit";"Zergling";"Larva";515;1
"Unit";"Zergling";"Larva";515;1
"Unit";"Zergling";"Larva";515;1
"Unit";"Zergling";"Larva";515;1
"Unit";"Zergling";"Larva";515;1
"Unit";"Zergling";"Larva";515;1
"Unit";"Zergling";"Larva";515;1
"Unit";"Zergling";"Larva";515;1
"Unit";"Zergling";"Larva";515;1
"Unit";"Zergling";"Larva";515;1
"Building";"CreepTumor";NA;515;0
"Building";"CreepTumor";NA;515;0
"Building";"CreepTumor";NA;515;0
"Building";"CreepTumorQueen";NA;545;0
"Building";"Extractor";NA;515;0
"Building";"CreepTumorQueen";NA;545;0
"Building";"CreepTumor";NA;545;0
"Building";"CreepTumor";NA;545;0
"Building";"CreepTumor";NA;545;0
"Building";"CreepTumor";NA;545;0
"Building";"CreepTumor";NA;545;0
"Building";"Extractor";NA;515;0
"Building";"CreepTumorQueen";NA;549;0
"Building";"CreepTumorQueen";NA;549;0
"Unit";"Overlord";"Larva";549;0
"Building";"CreepTumor";NA;549;0
"Building";"CreepTumor";NA;549;0
"Building";"CreepTumor";NA;549;0
"Building";"CreepTumor";NA;549;0
"Building";"CreepTumor";NA;549;0
"Building";"CreepTumor";NA;549;0
"Building";"CreepTumor";NA;549;0
"Building";"CreepTumor";NA;549;0
"Unit";"Ultralisk";"Larva";549;6
"Unit";"Ultralisk";"Larva";549;6
"Unit";"Ultralisk";"Larva";549;6
"Building";"Spire";NA;515;0
"Building";"CreepTumorQueen";NA;549;0
"Building";"CreepTumorQueen";NA;549;0
"Unit";"Zergling";"Larva";549;1
"Unit";"Zergling";"Larva";549;1
"Unit";"Zergling";"Larva";549;1
"Unit";"Zergling";"Larva";549;1
"Unit";"Zergling";"Larva";549;1
"Unit";"Zergling";"Larva";549;1
"Unit";"Zergling";"Larva";549;1
"Unit";"Zergling";"Larva";549;1
"Unit";"Ultralisk";"Larva";549;6
"Unit";"Zergling";"Larva";575;1
"Unit";"Zergling";"Larva";575;1
"Unit";"Zergling";"Larva";575;1
"Unit";"Zergling";"Larva";575;1
"Unit";"Ultralisk";"Larva";549;6
"Upgrade";"ChitinousPlating";"UltraliskCavern";549;0
"Upgrade";"ZergGroundArmorsLevel3";"EvolutionChamber";515;0
"Unit";"Queen";"Hatchery";581;2
"Unit";"Overlord";"Larva";591;0
"Upgrade";"ZergMeleeWeaponsLevel3";"EvolutionChamber";549;0
"Building";"CreepTumorQueen";NA;593;0
"Building";"CreepTumorQueen";NA;593;0
"Building";"CreepTumor";NA;593;0
"Building";"CreepTumorQueen";NA;593;0
"Building";"CreepTumor";NA;593;0
"Building";"CreepTumor";NA;593;0
"Unit";"Viper";"Larva";593;3
"Unit";"Viper";"Larva";593;3
"Unit";"Viper";"Larva";593;3
"Unit";"Viper";"Larva";593;3
"Building";"CreepTumor";NA;593;0
"Building";"CreepTumor";NA;593;0
"Building";"CreepTumor";NA;593;0
"Unit";"Corruptor";"Larva";593;2
"Unit";"Corruptor";"Larva";593;2
"Unit";"Corruptor";"Larva";593;2
"Unit";"Corruptor";"Larva";593;2
"Unit";"Corruptor";"Larva";593;2
"Unit";"Corruptor";"Larva";593;2
"Unit";"Corruptor";"Larva";593;2
"Unit";"Corruptor";"Larva";593;2
"Unit";"Corruptor";"Larva";593;2
"Unit";"Zergling";"Larva";605;1
"Unit";"Zergling";"Larva";605;1
"Unit";"Zergling";"Larva";605;1
"Unit";"Zergling";"Larva";605;1
"Unit";"Zergling";"Larva";605;1
"Unit";"Zergling";"Larva";605;1
"Building";"CreepTumor";NA;605;0
"Building";"CreepTumor";NA;605;0
"Building";"CreepTumor";NA;605;0
"Building";"CreepTumor";NA;623;0
"Building";"CreepTumor";NA;629;0
"Building";"Hatchery";NA;593;0
"Building";"CreepTumor";NA;629;0
"Building";"CreepTumor";NA;629;0
"Building";"CreepTumor";NA;629;0
"Building";"CreepTumor";NA;629;0
"Building";"CreepTumor";NA;629;0
"Building";"Hatchery";NA;605;0
"Building";"Hatchery";NA;605;0
"Building";"CreepTumorQueen";NA;629;0
"Building";"CreepTumorQueen";NA;629;0
"Building";"CreepTumor";NA;629;0
"Building";"CreepTumor";NA;629;0
"Building";"CreepTumor";NA;629;0
"Building";"CreepTumor";NA;629;0
"Unit";"Zergling";"Larva";629;1
"Unit";"Zergling";"Larva";629;1
"Unit";"Zergling";"Larva";629;1
"Unit";"Zergling";"Larva";629;1
"Unit";"Zergling";"Larva";629;1
"Unit";"Zergling";"Larva";629;1
"Unit";"Zergling";"Larva";629;1
"Unit";"Zergling";"Larva";629;1
"Unit";"Zergling";"Larva";629;1
"Unit";"Zergling";"Larva";629;1
"Unit";"Zergling";"Larva";629;1
"Unit";"Zergling";"Larva";629;1
"Unit";"Zergling";"Larva";629;1
"Unit";"Zergling";"Larva";629;1
"Unit";"Zergling";"Larva";629;1
"Unit";"Zergling";"Larva";629;1
"Unit";"Zergling";"Larva";629;1
"Unit";"Zergling";"Larva";629;1
"Unit";"Zergling";"Larva";629;1
"Unit";"Zergling";"Larva";629;1
"Unit";"Zergling";"Larva";629;1
"Unit";"Zergling";"Larva";629;1
"Unit";"Zergling";"Larva";629;1
"Unit";"Zergling";"Larva";629;1
"Unit";"Zergling";"Larva";629;1
"Unit";"Zergling";"Larva";629;1
"Unit";"Zergling";"Larva";629;1
"Unit";"Zergling";"Larva";629;1
"Unit";"Zergling";"Larva";629;1
"Unit";"Zergling";"Larva";629;1
"Unit";"Zergling";"Larva";629;1
"Unit";"Zergling";"Larva";629;1
"Unit";"Zergling";"Larva";629;1
"Unit";"Zergling";"Larva";629;1
"Unit";"Zergling";"Larva";629;1
"Unit";"Zergling";"Larva";629;1
"Unit";"Zergling";"Larva";629;1
"Unit";"Zergling";"Larva";629;1
"Unit";"Zergling";"Larva";629;1
"Unit";"Zergling";"Larva";629;1
"Unit";"Zergling";"Larva";629;1
"Unit";"Zergling";"Larva";629;1
"Unit";"Zergling";"Larva";629;1
"Unit";"Zergling";"Larva";629;1
"Unit";"Zergling";"Larva";629;1
"Unit";"Zergling";"Larva";629;1
"Unit";"Zergling";"Larva";629;1
"Unit";"Zergling";"Larva";629;1
"Unit";"Zergling";"Larva";629;1
"Unit";"Zergling";"Larva";629;1
"Unit";"Zergling";"Larva";629;1
"Unit";"Zergling";"Larva";629;1
"Unit";"Zergling";"Larva";629;1
"Unit";"Zergling";"Larva";629;1
"Unit";"Zergling";"Larva";629;1
"Unit";"Zergling";"Larva";629;1
"Unit";"Zergling";"Larva";629;1
"Unit";"Zergling";"Larva";629;1
"Unit";"Zergling";"Larva";629;1
"Unit";"Zergling";"Larva";629;1
"Unit";"Zergling";"Larva";629;1
"Unit";"Zergling";"Larva";629;1
"Unit";"Zergling";"Larva";629;1
"Unit";"Zergling";"Larva";629;1
"Unit";"Zergling";"Larva";629;1
"Unit";"Zergling";"Larva";629;1
"Unit";"Zergling";"Larva";629;1
"Unit";"Zergling";"Larva";629;1
"Unit";"Zergling";"Larva";629;1
"Unit";"Zergling";"Larva";629;1
"Unit";"Zergling";"Larva";629;1
"Unit";"Zergling";"Larva";629;1
"Unit";"Zergling";"Larva";629;1
"Unit";"Zergling";"Larva";629;1
"Unit";"Zergling";"Larva";629;1
"Unit";"Zergling";"Larva";629;1
"Unit";"Zergling";"Larva";629;1
"Unit";"Zergling";"Larva";629;1
"Unit";"Zergling";"Larva";629;1
"Unit";"Zergling";"Larva";629;1
"Unit";"Zergling";"Larva";629;1
"Unit";"Zergling";"Larva";629;1
"Unit";"Zergling";"Larva";629;1
"Unit";"Zergling";"Larva";629;1
"Unit";"Ultralisk";"Larva";629;6
"Unit";"Ultralisk";"Larva";629;6
"Unit";"Ultralisk";"Larva";629;6
"Upgrade";"ZergMissileWeaponsLevel1";"EvolutionChamber";629;0
"Unit";"Overlord";"Larva";629;0
"Unit";"Corruptor";"Larva";629;2
"Unit";"Corruptor";"Larva";629;2
"Unit";"Corruptor";"Larva";629;2
"Unit";"Corruptor";"Larva";699;2
"Unit";"Corruptor";"Larva";699;2
"Building";"CreepTumor";NA;735;0
"Unit";"Zergling";"Larva";745;1
"Unit";"Zergling";"Larva";745;1
"Unit";"Zergling";"Larva";745;1
"Unit";"Zergling";"Larva";745;1
"Unit";"Zergling";"Larva";745;1
"Unit";"Zergling";"Larva";745;1
"Unit";"Zergling";"Larva";745;1
"Unit";"Zergling";"Larva";745;1
"Unit";"Zergling";"Larva";745;1
"Unit";"Zergling";"Larva";745;1
"Unit";"Zergling";"Larva";745;1
"Unit";"Zergling";"Larva";745;1
"Unit";"Zergling";"Larva";745;1
"Unit";"Zergling";"Larva";745;1
"Unit";"Zergling";"Larva";745;1
"Unit";"Zergling";"Larva";745;1
"Unit";"Zergling";"Larva";745;1
"Unit";"Zergling";"Larva";745;1
"Unit";"Zergling";"Larva";745;1
"Unit";"Zergling";"Larva";745;1
"Unit";"Zergling";"Larva";745;1
"Unit";"Zergling";"Larva";745;1
"Unit";"Zergling";"Larva";745;1
"Unit";"Zergling";"Larva";745;1
"Unit";"Zergling";"Larva";745;1
"Unit";"Zergling";"Larva";745;1
"Unit";"Zergling";"Larva";745;1
"Unit";"Zergling";"Larva";745;1
"Unit";"Zergling";"Larva";745;1
"Unit";"Zergling";"Larva";745;1
"Unit";"Zergling";"Larva";745;1
"Unit";"Zergling";"Larva";745;1
"Unit";"Zergling";"Larva";745;1
"Unit";"Zergling";"Larva";745;1
"Unit";"Zergling";"Larva";745;1
"Unit";"Zergling";"Larva";745;1
"Unit";"Zergling";"Larva";745;1
"Unit";"Zergling";"Larva";745;1
"Unit";"Zergling";"Larva";745;1
"Unit";"Zergling";"Larva";745;1
"Unit";"Zergling";"Larva";745;1
"Unit";"Zergling";"Larva";745;1
"Unit";"Zergling";"Larva";745;1
"Unit";"Zergling";"Larva";745;1
"Unit";"Zergling";"Larva";745;1
"Unit";"Zergling";"Larva";745;1
"Unit";"Zergling";"Larva";745;1
"Unit";"Zergling";"Larva";745;1
"Unit";"Zergling";"Larva";745;1
"Unit";"Zergling";"Larva";745;1
"Unit";"Zergling";"Larva";745;1
"Unit";"Zergling";"Larva";745;1
"Unit";"Baneling";"Zergling";777;0
"Unit";"Baneling";"Zergling";777;0
"Unit";"Baneling";"Zergling";777;0
"Unit";"Baneling";"Zergling";777;0
"Unit";"Baneling";"Zergling";777;0
"Unit";"Baneling";"Zergling";777;0
"Unit";"Baneling";"Zergling";777;0
"Unit";"Baneling";"Zergling";777;0
"Unit";"Baneling";"Zergling";777;0
"Unit";"Baneling";"Zergling";777;0
"Unit";"Baneling";"Zergling";777;0
"Unit";"Baneling";"Zergling";777;0
"Unit";"Baneling";"Zergling";777;0
"Unit";"Baneling";"Zergling";777;0
"Unit";"Baneling";"Zergling";777;0
"Unit";"Baneling";"Zergling";777;0
"Unit";"Baneling";"Zergling";777;0
"Unit";"Baneling";"Zergling";777;0
"Unit";"Baneling";"Zergling";777;0
"Unit";"Baneling";"Zergling";777;0
"Unit";"Baneling";"Zergling";777;0
"Unit";"Baneling";"Zergling";777;0
"Unit";"Baneling";"Zergling";777;0
"Unit";"Baneling";"Zergling";777;0
"Unit";"Baneling";"Zergling";777;0
"Unit";"Baneling";"Zergling";777;0
"Unit";"Baneling";"Zergling";777;0
"Unit";"Baneling";"Zergling";777;0
"Unit";"Baneling";"Zergling";777;0
"Unit";"Baneling";"Zergling";777;0
"Unit";"Baneling";"Zergling";777;0
"Unit";"Baneling";"Zergling";777;0
"Unit";"Baneling";"Zergling";777;0
"Unit";"Baneling";"Zergling";777;0
"Unit";"Baneling";"Zergling";777;0
"Unit";"Baneling";"Zergling";777;0
"Unit";"Baneling";"Zergling";777;0
"Unit";"Baneling";"Zergling";777;0
"Unit";"Baneling";"Zergling";777;0
"Unit";"Baneling";"Zergling";777;0
"Unit";"Baneling";"Zergling";777;0
"Unit";"Baneling";"Zergling";777;0
"Unit";"Baneling";"Zergling";777;0
"Unit";"Baneling";"Zergling";777;0
"Unit";"Zergling";"Larva";797;1
"Unit";"Zergling";"Larva";797;1
"Unit";"Zergling";"Larva";797;1
"Unit";"Zergling";"Larva";797;1
"Unit";"Zergling";"Larva";797;1
"Unit";"Zergling";"Larva";797;1
"Unit";"Zergling";"Larva";797;1
"Unit";"Zergling";"Larva";797;1
"Unit";"Zergling";"Larva";797;1
"Unit";"Zergling";"Larva";797;1
"Unit";"Zergling";"Larva";797;1
"Unit";"Zergling";"Larva";797;1
"Unit";"Zergling";"Larva";797;1
"Unit";"Zergling";"Larva";797;1
"Unit";"Zergling";"Larva";797;1
"Unit";"Zergling";"Larva";797;1
"Unit";"Zergling";"Larva";797;1
"Unit";"Zergling";"Larva";797;1
"Unit";"Zergling";"Larva";797;1
"Unit";"Zergling";"Larva";797;1
"Unit";"Zergling";"Larva";797;1
"Unit";"Zergling";"Larva";797;1
"Unit";"Zergling";"Larva";797;1
"Unit";"Zergling";"Larva";797;1
"Unit";"Zergling";"Larva";797;1
"Unit";"Zergling";"Larva";797;1
"Unit";"Zergling";"Larva";797;1
"Unit";"Zergling";"Larva";797;1
"Unit";"Zergling";"Larva";797;1
"Unit";"Zergling";"Larva";797;1
"Unit";"Zergling";"Larva";797;1
"Unit";"Zergling";"Larva";797;1
"Unit";"Zergling";"Larva";797;1
"Unit";"Zergling";"Larva";797;1
"Unit";"Zergling";"Larva";797;1
"Unit";"Zergling";"Larva";797;1
"Unit";"Zergling";"Larva";797;1
"Unit";"Zergling";"Larva";797;1
"Unit";"Zergling";"Larva";797;1
"Unit";"Zergling";"Larva";797;1
"Unit";"Zergling";"Larva";797;1
"Unit";"Zergling";"Larva";797;1
"Unit";"Hydralisk";"Larva";797;2
"Unit";"Hydralisk";"Larva";797;2
"Unit";"Hydralisk";"Larva";797;2
"Unit";"Hydralisk";"Larva";797;2
"Unit";"Hydralisk";"Larva";797;2
"Unit";"Hydralisk";"Larva";797;2
"Unit";"Hydralisk";"Larva";797;2
"Unit";"Hydralisk";"Larva";797;2
"Unit";"Hydralisk";"Larva";797;2
"Unit";"Hydralisk";"Larva";797;2
"Unit";"Hydralisk";"Larva";797;2
"Unit";"Hydralisk";"Larva";797;2
"Unit";"Hydralisk";"Larva";797;2
"Building";"CreepTumor";NA;837;0
"Building";"CreepTumor";NA;837;0
"Building";"CreepTumor";NA;837;0
"Building";"CreepTumor";NA;837;0
"Building";"CreepTumor";NA;837;0
"Building";"CreepTumor";NA;837;0
"Unit";"Baneling";"Zergling";865;0
"Unit";"Baneling";"Zergling";865;0
"Unit";"Baneling";"Zergling";865;0
"Unit";"Baneling";"Zergling";865;0
"Building";"CreepTumor";NA;865;0
"Building";"CreepTumor";NA;865;0
"Building";"CreepTumorQueen";NA;865;0
"Building";"CreepTumorQueen";NA;865;0
"Unit";"Ultralisk";"Larva";839;6
"Unit";"Ultralisk";"Larva";839;6
"Unit";"Ultralisk";"Larva";839;6
"Unit";"Ultralisk";"Larva";839;6
"Unit";"Ultralisk";"Larva";839;6
"Building";"CreepTumor";NA;865;0
"Unit";"Zergling";"Larva";865;1
"Unit";"Zergling";"Larva";865;1
"Unit";"Zergling";"Larva";865;1
"Unit";"Zergling";"Larva";865;1
"Unit";"Zergling";"Larva";865;1
"Unit";"Zergling";"Larva";865;1
"Unit";"Zergling";"Larva";865;1
"Unit";"Zergling";"Larva";865;1
"Unit";"Zergling";"Larva";865;1
"Unit";"Zergling";"Larva";865;1
"Unit";"Zergling";"Larva";865;1
"Unit";"Zergling";"Larva";865;1
"Unit";"Zergling";"Larva";865;1
"Unit";"Zergling";"Larva";865;1
"Unit";"Zergling";"Larva";865;1
"Unit";"Zergling";"Larva";865;1
"Unit";"Zergling";"Larva";865;1
"Unit";"Zergling";"Larva";865;1
"Unit";"Zergling";"Larva";865;1
"Unit";"Zergling";"Larva";865;1
"Unit";"Zergling";"Larva";865;1
"Unit";"Zergling";"Larva";865;1
"Unit";"Zergling";"Larva";865;1
"Unit";"Zergling";"Larva";865;1
"Unit";"Zergling";"Larva";865;1
"Unit";"Zergling";"Larva";865;1
"Unit";"Zergling";"Larva";865;1
"Unit";"Zergling";"Larva";865;1
"Unit";"Zergling";"Larva";865;1
"Unit";"Zergling";"Larva";865;1
"Unit";"Zergling";"Larva";865;1
"Unit";"Zergling";"Larva";865;1
"Unit";"Zergling";"Larva";865;1
"Unit";"Zergling";"Larva";865;1
"Unit";"Zergling";"Larva";865;1
"Unit";"Zergling";"Larva";865;1
"Unit";"Zergling";"Larva";865;1
"Unit";"Zergling";"Larva";865;1
"Unit";"Zergling";"Larva";933;1
"Unit";"Zergling";"Larva";933;1
"Unit";"Zergling";"Larva";933;1
"Unit";"Zergling";"Larva";933;1
"Unit";"Zergling";"Larva";933;1
"Unit";"Zergling";"Larva";933;1
"Unit";"Zergling";"Larva";933;1
"Unit";"Zergling";"Larva";933;1
"Unit";"Zergling";"Larva";933;1
"Unit";"Zergling";"Larva";933;1
"Unit";"Zergling";"Larva";933;1
"Unit";"Zergling";"Larva";933;1
"Unit";"Zergling";"Larva";933;1
"Unit";"Zergling";"Larva";933;1
"Unit";"Zergling";"Larva";933;1
"Unit";"Zergling";"Larva";933;1
"Unit";"Zergling";"Larva";933;1
"Unit";"Zergling";"Larva";933;1
"Unit";"Zergling";"Larva";933;1
"Unit";"Zergling";"Larva";933;1
"Unit";"Zergling";"Larva";933;1
"Unit";"Zergling";"Larva";933;1
"Unit";"Zergling";"Larva";933;1
"Unit";"Zergling";"Larva";933;1
"Unit";"Ultralisk";"Larva";865;6
"Unit";"Ultralisk";"Larva";865;6
"Building";"Hatchery";NA;865;0
"Unit";"Zergling";"Larva";957;1
"Unit";"Zergling";"Larva";957;1
"Unit";"Zergling";"Larva";957;1
"Unit";"Zergling";"Larva";957;1
"Unit";"Zergling";"Larva";957;1
"Unit";"Zergling";"Larva";957;1
"Unit";"Zergling";"Larva";957;1
"Unit";"Zergling";"Larva";957;1
"Unit";"Zergling";"Larva";957;1
"Unit";"Zergling";"Larva";957;1
"Unit";"Zergling";"Larva";957;1
"Unit";"Zergling";"Larva";957;1
"Unit";"Zergling";"Larva";957;1
"Unit";"Zergling";"Larva";957;1
"Unit";"Zergling";"Larva";957;1
"Unit";"Zergling";"Larva";957;1
"Unit";"Zergling";"Larva";957;1
"Unit";"Zergling";"Larva";957;1
"Unit";"Zergling";"Larva";957;1
"Unit";"Zergling";"Larva";957;1
"Unit";"Zergling";"Larva";957;1
"Unit";"Zergling";"Larva";957;1
"Unit";"Zergling";"Larva";957;1
"Unit";"Zergling";"Larva";957;1
"Unit";"Zergling";"Larva";957;1
"Unit";"Zergling";"Larva";957;1
"Unit";"Zergling";"Larva";957;1
"Unit";"Zergling";"Larva";957;1
"Unit";"Zergling";"Larva";957;1
"Unit";"Zergling";"Larva";957;1
"Unit";"Zergling";"Larva";957;1
"Unit";"Zergling";"Larva";957;1
"Unit";"Zergling";"Larva";957;1
"Unit";"Zergling";"Larva";957;1
"Unit";"Zergling";"Larva";957;1
"Unit";"Zergling";"Larva";957;1
"Unit";"Zergling";"Larva";957;1
"Unit";"Zergling";"Larva";957;1
"Unit";"Zergling";"Larva";957;1
"Unit";"Zergling";"Larva";957;1
"Unit";"Zergling";"Larva";957;1
"Unit";"Zergling";"Larva";957;1
"Unit";"Zergling";"Larva";957;1
"Unit";"Zergling";"Larva";957;1
