"type";"unit_name";"on_building";"total_supply";"supply"
"Unit";"Overlord";"Larva";13;0
"Building";"Extractor";NA;17;0
"Unit";"Overlord";"Larva";22;0
"Building";"SpawningPool";NA;19;0
"Building";"Hatchery";NA;17;0
"Unit";"Zergling";"Larva";22;1
"Unit";"Zergling";"Larva";22;1
"Unit";"Zergling";"Larva";23;1
"Unit";"Zergling";"Larva";23;1
"Unit";"Queen";"Hatchery";22;2
"Unit";"Queen";"Hatchery";23;2
"Unit";"Overlord";"Larva";29;0
"Unit";"Queen";"Hatchery";34;2
"Unit";"Queen";"Hatchery";35;2
"Building";"CreepTumorQueen";NA;39;0
"Building";"CreepTumorQueen";NA;39;0
"Unit";"Overlord";"Larva";39;0
"Unit";"Overlord";"Larva";47;0
"Building";"CreepTumor";NA;50;0
"Building";"CreepTumor";NA;50;0
"Building";"CreepTumorQueen";NA;51;0
"Building";"CreepTumorQueen";NA;55;0
"Unit";"Zergling";"Larva";51;1
"Unit";"Zergling";"Larva";51;1
"Unit";"Zergling";"Larva";51;1
"Unit";"Zergling";"Larva";51;1
"Unit";"Zergling";"Larva";51;1
"Unit";"Zergling";"Larva";51;1
"Unit";"Zergling";"Larva";51;1
"Unit";"Zergling";"Larva";51;1
"Unit";"Zergling";"Larva";51;1
"Unit";"Zergling";"Larva";51;1
"Unit";"Zergling";"Larva";55;1
"Unit";"Zergling";"Larva";55;1
"Unit";"Zergling";"Larva";55;1
"Unit";"Zergling";"Larva";55;1
"Unit";"Zergling";"Larva";55;1
"Unit";"Zergling";"Larva";55;1
"Building";"Hatchery";NA;38;0
"Unit";"Overlord";"Larva";55;0
"Building";"CreepTumor";NA;65;0
"Building";"CreepTumor";NA;65;0
"Building";"CreepTumor";NA;65;0
"Building";"CreepTumorQueen";NA;71;0
"Building";"Extractor";NA;55;0
"Unit";"Queen";"Hatchery";55;2
"Unit";"Overlord";"Larva";72;0
"Building";"CreepTumor";NA;75;0
"Unit";"Overlord";"Larva";75;0
"Building";"CreepTumorQueen";NA;81;0
"Unit";"Zergling";"Larva";77;1
"Unit";"Zergling";"Larva";77;1
"Building";"CreepTumor";NA;81;0
"Unit";"Zergling";"Larva";77;1
"Unit";"Zergling";"Larva";77;1
"Unit";"Zergling";"Larva";77;1
"Unit";"Zergling";"Larva";77;1
"Building";"CreepTumor";NA;81;0
"Building";"CreepTumor";NA;81;0
"Unit";"Queen";"Hatchery";72;2
"Unit";"Overlord";"Larva";81;0
"Building";"CreepTumorQueen";NA;87;0
"Building";"CreepTumor";NA;87;0
"Building";"SporeCrawler";NA;81;0
"Building";"SporeCrawler";NA;81;0
"Unit";"Overlord";"Larva";89;0
"Building";"CreepTumor";NA;90;0
"Building";"EvolutionChamber";NA;81;0
"Building";"EvolutionChamber";NA;83;0
"Building";"CreepTumor";NA;94;0
"Building";"CreepTumor";NA;94;0
"Building";"CreepTumorQueen";NA;99;0
"Building";"CreepTumorQueen";NA;99;0
"Unit";"Overlord";"Larva";94;0
"Building";"CreepTumor";NA;99;0
"Building";"CreepTumor";NA;99;0
"Building";"CreepTumor";NA;99;0
"Building";"Extractor";NA;95;0
"Building";"Extractor";NA;99;0
"Building";"CreepTumor";NA;102;0
"Building";"CreepTumorQueen";NA;102;0
"Building";"Extractor";NA;101;0
"Building";"CreepTumor";NA;106;0
"Building";"CreepTumor";NA;106;0
"Unit";"Overlord";"Larva";106;0
"Building";"HydraliskDen";NA;102;0
"Building";"RoachWarren";NA;99;0
"Building";"CreepTumor";NA;111;0
"Building";"CreepTumorQueen";NA;111;0
"Unit";"Overlord";"Larva";106;0
"Building";"CreepTumor";NA;111;0
"Building";"CreepTumor";NA;111;0
"Building";"CreepTumor";NA;111;0
"Building";"CreepTumor";NA;111;0
"Building";"CreepTumor";NA;111;0
"Unit";"Overlord";"Larva";111;0
"Building";"Extractor";NA;111;0
"Building";"CreepTumor";NA;118;0
"Unit";"Overlord";"Larva";111;0
"Unit";"Roach";"Larva";119;2
"Unit";"Roach";"Larva";119;2
"Unit";"Roach";"Larva";119;2
"Unit";"Roach";"Larva";119;2
"Unit";"Roach";"Larva";119;2
"Unit";"Roach";"Larva";119;2
"Unit";"Roach";"Larva";119;2
"Unit";"Roach";"Larva";119;2
"Unit";"Roach";"Larva";119;2
"Unit";"Roach";"Larva";119;2
"Unit";"Roach";"Larva";119;2
"Unit";"Roach";"Larva";141;2
"Unit";"Roach";"Larva";141;2
"Unit";"Roach";"Larva";141;2
"Unit";"Roach";"Larva";141;2
"Unit";"Roach";"Larva";141;2
"Unit";"Roach";"Larva";141;2
"Unit";"Roach";"Larva";141;2
"Unit";"Roach";"Larva";141;2
"Upgrade";"EvolveMuscularAugments";"HydraliskDen";119;0
"Upgrade";"ZergMeleeWeaponsLevel1";"EvolutionChamber";111;0
"Building";"SporeCrawler";NA;141;0
"Upgrade";"ZergGroundArmorsLevel1";"EvolutionChamber";111;0
"Unit";"Hydralisk";"Larva";141;2
"Unit";"Hydralisk";"Larva";141;2
"Unit";"Hydralisk";"Larva";141;2
"Unit";"Hydralisk";"Larva";141;2
"Upgrade";"GlialReconstitution";"RoachWarren";119;0
"Unit";"Queen";"Hatchery";141;2
"Unit";"Hydralisk";"Larva";157;2
"Unit";"Hydralisk";"Larva";157;2
"Unit";"Hydralisk";"Larva";157;2
"Unit";"Hydralisk";"Larva";157;2
"Unit";"Queen";"Hatchery";141;2
"Building";"CreepTumor";NA;181;0
"Building";"CreepTumor";NA;181;0
"Building";"CreepTumor";NA;181;0
"Building";"CreepTumor";NA;184;0
"Unit";"Overlord";"Larva";185;0
"Unit";"Queen";"Hatchery";185;2
"Building";"CreepTumor";NA;187;0
"Unit";"Hydralisk";"Larva";185;2
"Unit";"Hydralisk";"Larva";185;2
"Unit";"Hydralisk";"Larva";185;2
"Unit";"Hydralisk";"Larva";185;2
"Unit";"Hydralisk";"Larva";185;2
"Unit";"Hydralisk";"Larva";185;2
"Unit";"Hydralisk";"Larva";185;2
"Unit";"Hydralisk";"Larva";185;2
"Unit";"Hydralisk";"Larva";185;2
"Unit";"Hydralisk";"Larva";185;2
"Unit";"Hydralisk";"Larva";185;2
"Unit";"Hydralisk";"Larva";185;2
"Building";"CreepTumor";NA;187;0
"Building";"CreepTumor";NA;187;0
"Building";"CreepTumor";NA;187;0
"Unit";"Overlord";"Larva";187;0
"Unit";"Overlord";"Larva";187;0
"Unit";"Overlord";"Larva";187;0
"Building";"CreepTumor";NA;211;0
"Building";"CreepTumor";NA;211;0
"Unit";"Overlord";"Larva";211;0
"Building";"CreepTumor";NA;211;0
"Upgrade";"EvolveGroovedSpines";"HydraliskDen";185;0
"Building";"CreepTumor";NA;211;0
"Building";"CreepTumor";NA;212;0
"Building";"Hatchery";NA;185;0
"Building";"CreepTumor";NA;218;0
"Unit";"Overlord";"Larva";218;0
"Building";"CreepTumor";NA;220;0
"Building";"CreepTumorQueen";NA;223;0
"Building";"CreepTumor";NA;223;0
"Upgrade";"ZergMissileWeaponsLevel1";"EvolutionChamber";185;0
"Building";"CreepTumorQueen";NA;225;0
"Unit";"Overlord";"Larva";225;0
"Building";"Extractor";NA;225;0
"Building";"Extractor";NA;225;0
"Upgrade";"ZergGroundArmorsLevel2";"EvolutionChamber";185;0
"Unit";"Hydralisk";"Larva";225;2
"Unit";"Hydralisk";"Larva";225;2
"Unit";"Hydralisk";"Larva";225;2
"Unit";"Hydralisk";"Larva";225;2
"Unit";"Hydralisk";"Larva";225;2
"Unit";"Hydralisk";"Larva";225;2
"Unit";"Hydralisk";"Larva";225;2
"Unit";"Zergling";"Larva";225;1
"Unit";"Zergling";"Larva";225;1
"Unit";"Zergling";"Larva";225;1
"Unit";"Zergling";"Larva";225;1
"Unit";"Zergling";"Larva";225;1
"Unit";"Zergling";"Larva";225;1
"Unit";"Zergling";"Larva";225;1
"Unit";"Zergling";"Larva";225;1
"Unit";"Zergling";"Larva";225;1
"Unit";"Zergling";"Larva";225;1
"Unit";"Zergling";"Larva";225;1
"Unit";"Zergling";"Larva";225;1
"Unit";"Zergling";"Larva";225;1
"Unit";"Zergling";"Larva";225;1
"Unit";"Zergling";"Larva";225;1
"Unit";"Zergling";"Larva";225;1
"Unit";"Zergling";"Larva";225;1
"Unit";"Zergling";"Larva";225;1
"Unit";"Zergling";"Larva";225;1
"Unit";"Zergling";"Larva";225;1
"Unit";"Zergling";"Larva";225;1
"Unit";"Zergling";"Larva";225;1
"Unit";"Roach";"Larva";225;2
"Building";"InfestationPit";NA;225;0
"Building";"CreepTumor";NA;263;0
"Building";"CreepTumor";NA;263;0
"Unit";"Hydralisk";"Larva";239;2
"Unit";"Hydralisk";"Larva";243;2
"Unit";"Hydralisk";"Larva";247;2
"Unit";"Hydralisk";"Larva";251;2
"Unit";"Hydralisk";"Larva";251;2
"Building";"CreepTumor";NA;263;0
"Building";"CreepTumor";NA;263;0
"Building";"CreepTumor";NA;263;0
"Building";"CreepTumor";NA;263;0
"Building";"CreepTumor";NA;263;0
"Building";"CreepTumor";NA;263;0
"Unit";"Zergling";"Larva";273;1
"Unit";"Zergling";"Larva";273;1
"Unit";"Zergling";"Larva";273;1
"Unit";"Zergling";"Larva";273;1
"Unit";"Zergling";"Larva";273;1
"Unit";"Zergling";"Larva";273;1
"Unit";"Zergling";"Larva";273;1
"Unit";"Zergling";"Larva";273;1
"Unit";"Zergling";"Larva";273;1
"Unit";"Zergling";"Larva";273;1
"Unit";"Zergling";"Larva";273;1
"Unit";"Zergling";"Larva";273;1
"Unit";"Zergling";"Larva";273;1
"Unit";"Zergling";"Larva";273;1
"Unit";"Zergling";"Larva";273;1
"Unit";"Zergling";"Larva";273;1
"Unit";"Zergling";"Larva";273;1
"Unit";"Zergling";"Larva";273;1
"Unit";"Zergling";"Larva";273;1
"Unit";"Zergling";"Larva";273;1
"Unit";"Zergling";"Larva";273;1
"Unit";"Zergling";"Larva";273;1
"Unit";"Zergling";"Larva";273;1
"Unit";"Zergling";"Larva";273;1
"Unit";"Zergling";"Larva";273;1
"Unit";"Zergling";"Larva";273;1
"Unit";"Zergling";"Larva";273;1
"Unit";"Zergling";"Larva";273;1
"Unit";"Zergling";"Larva";273;1
"Unit";"Zergling";"Larva";273;1
"Unit";"Zergling";"Larva";273;1
"Unit";"Zergling";"Larva";273;1
"Unit";"Zergling";"Larva";273;1
"Unit";"Zergling";"Larva";273;1
"Unit";"Zergling";"Larva";273;1
"Unit";"Zergling";"Larva";273;1
"Unit";"Zergling";"Larva";273;1
"Unit";"Zergling";"Larva";273;1
"Unit";"Zergling";"Larva";273;1
"Unit";"Zergling";"Larva";273;1
"Unit";"Zergling";"Larva";273;1
"Unit";"Zergling";"Larva";273;1
"Unit";"Zergling";"Larva";273;1
"Unit";"Zergling";"Larva";273;1
"Unit";"Zergling";"Larva";305;1
"Unit";"Zergling";"Larva";305;1
"Unit";"Zergling";"Larva";305;1
"Unit";"Zergling";"Larva";305;1
"Unit";"Zergling";"Larva";305;1
"Unit";"Zergling";"Larva";305;1
"Unit";"Zergling";"Larva";305;1
"Unit";"Zergling";"Larva";305;1
"Upgrade";"Burrow";"Hatchery";273;0
"Unit";"Zergling";"Larva";317;1
"Unit";"Zergling";"Larva";317;1
"Unit";"Zergling";"Larva";317;1
"Unit";"Zergling";"Larva";317;1
"Unit";"Zergling";"Larva";317;1
"Unit";"Zergling";"Larva";317;1
"Unit";"Zergling";"Larva";317;1
"Unit";"Zergling";"Larva";317;1
"Building";"Hatchery";NA;263;0
