"type";"unit_name";"on_building";"total_supply";"supply"
"Building";"Extractor";NA;13;0
"Unit";"Overlord";"Larva";16;0
"Building";"SpawningPool";NA;15;0
"Unit";"Zergling";"Larva";17;1
"Unit";"Zergling";"Larva";17;1
"Unit";"Zergling";"Larva";17;1
"Unit";"Zergling";"Larva";17;1
"Unit";"Zergling";"Larva";17;1
"Unit";"Zergling";"Larva";17;1
"Unit";"Zergling";"Larva";17;1
"Unit";"Zergling";"Larva";17;1
"Unit";"Zergling";"Larva";23;1
"Unit";"Zergling";"Larva";23;1
"Unit";"Queen";"Hatchery";17;2
"Unit";"Overlord";"Larva";29;0
"Unit";"Zergling";"Larva";29;1
"Unit";"Zergling";"Larva";29;1
"Unit";"Zergling";"Larva";31;1
"Unit";"Zergling";"Larva";31;1
"Unit";"Zergling";"Larva";31;1
"Unit";"Zergling";"Larva";31;1
"Unit";"Zergling";"Larva";31;1
"Unit";"Zergling";"Larva";31;1
"Unit";"Zergling";"Larva";31;1
"Unit";"Zergling";"Larva";31;1
"Unit";"Zergling";"Larva";31;1
"Unit";"Zergling";"Larva";31;1
"Unit";"Zergling";"Larva";31;1
"Unit";"Zergling";"Larva";31;1
"Building";"Hatchery";NA;25;0
"Unit";"Queen";"Hatchery";39;2
"Unit";"Overlord";"Larva";45;0
"Unit";"Queen";"Hatchery";44;2
"Building";"CreepTumorQueen";NA;51;0
"Unit";"Overlord";"Larva";54;0
"Unit";"Overlord";"Larva";64;0
"Building";"Hatchery";NA;51;0
"Building";"CreepTumorQueen";NA;69;0
"Building";"CreepTumorQueen";NA;69;0
"Unit";"Overlord";"Larva";69;0
"Unit";"Zergling";"Larva";69;1
"Unit";"Zergling";"Larva";69;1
"Unit";"Zergling";"Larva";69;1
"Unit";"Zergling";"Larva";69;1
"Unit";"Zergling";"Larva";69;1
"Unit";"Zergling";"Larva";69;1
"Unit";"Zergling";"Larva";69;1
"Unit";"Zergling";"Larva";69;1
"Building";"CreepTumor";NA;77;0
"Building";"CreepTumor";NA;77;0
"Building";"BanelingNest";NA;69;0
"Unit";"Queen";"Hatchery";69;2
"Building";"CreepTumorQueen";NA;79;0
"Unit";"Queen";"Hatchery";69;2
"Building";"Extractor";NA;79;0
"Building";"CreepTumorQueen";NA;94;0
"Building";"CreepTumor";NA;94;0
"Building";"CreepTumor";NA;94;0
"Unit";"Baneling";"Zergling";94;0
"Unit";"Baneling";"Zergling";94;0
"Unit";"Baneling";"Zergling";94;0
"Unit";"Baneling";"Zergling";94;0
"Unit";"Queen";"Hatchery";89;2
"Unit";"Overlord";"Larva";94;0
"Building";"CreepTumor";NA;94;0
"Building";"CreepTumorQueen";NA;94;0
"Unit";"Queen";"Hatchery";94;2
"Building";"CreepTumor";NA;98;0
"Unit";"Overlord";"Larva";96;0
"Unit";"Overlord";"Larva";96;0
"Building";"CreepTumor";NA;98;0
"Building";"CreepTumor";NA;98;0
"Building";"CreepTumor";NA;100;0
"Unit";"Zergling";"Larva";100;1
"Unit";"Zergling";"Larva";100;1
"Unit";"Zergling";"Larva";100;1
"Unit";"Zergling";"Larva";100;1
"Unit";"Zergling";"Larva";101;1
"Unit";"Zergling";"Larva";101;1
"Unit";"Zergling";"Larva";101;1
"Unit";"Zergling";"Larva";101;1
"Unit";"Zergling";"Larva";101;1
"Unit";"Zergling";"Larva";101;1
"Unit";"Zergling";"Larva";101;1
"Unit";"Zergling";"Larva";101;1
"Unit";"Overlord";"Larva";101;0
"Building";"CreepTumorQueen";NA;101;0
"Building";"CreepTumorQueen";NA;101;0
"Building";"CreepTumorQueen";NA;101;0
"Building";"CreepTumorQueen";NA;113;0
"Unit";"Overlord";"Larva";101;0
"Unit";"Baneling";"Zergling";121;0
"Unit";"Baneling";"Zergling";121;0
"Unit";"Baneling";"Zergling";121;0
"Unit";"Baneling";"Zergling";121;0
"Unit";"Baneling";"Zergling";121;0
"Building";"EvolutionChamber";NA;101;0
"Building";"EvolutionChamber";NA;101;0
"Building";"CreepTumor";NA;121;0
"Unit";"Zergling";"Larva";121;1
"Unit";"Zergling";"Larva";121;1
"Unit";"Zergling";"Larva";121;1
"Unit";"Zergling";"Larva";121;1
"Unit";"Zergling";"Larva";121;1
"Unit";"Zergling";"Larva";121;1
"Unit";"Zergling";"Larva";121;1
"Unit";"Zergling";"Larva";121;1
"Unit";"Zergling";"Larva";121;1
"Unit";"Zergling";"Larva";121;1
"Unit";"Zergling";"Larva";121;1
"Unit";"Zergling";"Larva";121;1
"Unit";"Zergling";"Larva";121;1
"Unit";"Zergling";"Larva";121;1
"Building";"CreepTumor";NA;121;0
"Building";"CreepTumor";NA;121;0
"Building";"CreepTumor";NA;121;0
"Building";"SporeCrawler";NA;121;0
"Building";"CreepTumor";NA;121;0
"Building";"CreepTumor";NA;121;0
"Building";"CreepTumor";NA;121;0
"Unit";"Zergling";"Larva";121;1
"Unit";"Zergling";"Larva";121;1
"Unit";"Zergling";"Larva";121;1
"Unit";"Zergling";"Larva";121;1
"Unit";"Zergling";"Larva";121;1
"Unit";"Zergling";"Larva";121;1
"Unit";"Zergling";"Larva";121;1
"Unit";"Zergling";"Larva";121;1
"Unit";"Zergling";"Larva";121;1
"Unit";"Zergling";"Larva";121;1
"Unit";"Zergling";"Larva";121;1
"Unit";"Zergling";"Larva";121;1
"Unit";"Baneling";"Zergling";135;0
"Unit";"Baneling";"Zergling";135;0
"Unit";"Overlord";"Larva";135;0
"Unit";"Queen";"Hatchery";121;2
"Unit";"Zergling";"Larva";147;1
"Unit";"Zergling";"Larva";147;1
"Unit";"Zergling";"Larva";147;1
"Unit";"Zergling";"Larva";147;1
"Unit";"Zergling";"Larva";147;1
"Unit";"Zergling";"Larva";147;1
"Unit";"Zergling";"Larva";147;1
"Unit";"Zergling";"Larva";147;1
"Unit";"Zergling";"Larva";147;1
"Unit";"Zergling";"Larva";147;1
"Unit";"Zergling";"Larva";147;1
"Unit";"Zergling";"Larva";147;1
"Unit";"Zergling";"Larva";147;1
"Unit";"Zergling";"Larva";147;1
"Unit";"Zergling";"Larva";147;1
"Unit";"Zergling";"Larva";147;1
"Unit";"Zergling";"Larva";147;1
"Unit";"Zergling";"Larva";147;1
"Unit";"Zergling";"Larva";147;1
"Unit";"Zergling";"Larva";147;1
"Unit";"Zergling";"Larva";147;1
"Unit";"Zergling";"Larva";147;1
"Unit";"Zergling";"Larva";147;1
"Unit";"Zergling";"Larva";147;1
"Unit";"Zergling";"Larva";149;1
"Unit";"Zergling";"Larva";149;1
"Unit";"Zergling";"Larva";149;1
"Unit";"Zergling";"Larva";149;1
"Building";"CreepTumor";NA;149;0
"Building";"CreepTumor";NA;169;0
"Building";"CreepTumor";NA;169;0
"Building";"CreepTumor";NA;169;0
"Building";"Extractor";NA;169;0
"Building";"Extractor";NA;169;0
"Building";"Extractor";NA;171;0
"Building";"Extractor";NA;177;0
"Building";"SporeCrawler";NA;177;0
"Building";"InfestationPit";NA;169;0
"Building";"CreepTumor";NA;188;0
"Building";"CreepTumor";NA;188;0
"Building";"CreepTumor";NA;188;0
"Building";"SporeCrawler";NA;186;0
"Unit";"Zergling";"Larva";193;1
"Unit";"Zergling";"Larva";193;1
"Unit";"Zergling";"Larva";193;1
"Unit";"Zergling";"Larva";193;1
"Unit";"Zergling";"Larva";193;1
"Unit";"Zergling";"Larva";193;1
"Unit";"Queen";"Hatchery";185;2
"Upgrade";"ZergGroundArmorsLevel1";"EvolutionChamber";147;0
"Building";"CreepTumorQueen";NA;204;0
"Building";"CreepTumorQueen";NA;204;0
"Building";"CreepTumorQueen";NA;204;0
"Building";"Hatchery";NA;169;0
"Building";"CreepTumor";NA;204;0
"Building";"SporeCrawler";NA;204;0
"Building";"Hatchery";NA;169;0
"Building";"CreepTumor";NA;211;0
"Unit";"Overlord";"Larva";209;0
"Unit";"Overlord";"Larva";210;0
"Building";"CreepTumor";NA;211;0
"Building";"CreepTumor";NA;211;0
"Building";"CreepTumorQueen";NA;212;0
"Building";"CreepTumorQueen";NA;212;0
"Unit";"Overlord";"Larva";211;0
"Unit";"Overlord";"Larva";211;0
"Building";"CreepTumorQueen";NA;212;0
"Building";"CreepTumorQueen";NA;214;0
"Unit";"Queen";"Hatchery";204;2
"Building";"CreepTumor";NA;214;0
"Building";"CreepTumor";NA;214;0
"Building";"CreepTumorQueen";NA;214;0
"Building";"CreepTumorQueen";NA;214;0
"Building";"CreepTumorQueen";NA;214;0
"Upgrade";"ZergMeleeWeaponsLevel1";"EvolutionChamber";186;0
"Building";"CreepTumor";NA;216;0
"Building";"CreepTumor";NA;216;0
"Building";"CreepTumor";NA;216;0
"Building";"CreepTumor";NA;216;0
"Building";"CreepTumor";NA;237;0
"Building";"CreepTumor";NA;237;0
"Building";"CreepTumor";NA;237;0
"Building";"CreepTumor";NA;237;0
"Building";"CreepTumor";NA;237;0
"Building";"SporeCrawler";NA;231;0
"Building";"Extractor";NA;231;0
"Building";"SporeCrawler";NA;231;0
"Building";"Extractor";NA;231;0
"Unit";"Queen";"Hatchery";216;2
"Unit";"Zergling";"Larva";237;1
"Unit";"Zergling";"Larva";237;1
"Unit";"Zergling";"Larva";237;1
"Unit";"Zergling";"Larva";237;1
"Unit";"Zergling";"Larva";237;1
"Unit";"Zergling";"Larva";237;1
"Unit";"Zergling";"Larva";237;1
"Unit";"Zergling";"Larva";237;1
"Unit";"Zergling";"Larva";237;1
"Unit";"Zergling";"Larva";237;1
"Unit";"Zergling";"Larva";237;1
"Unit";"Zergling";"Larva";237;1
"Unit";"Zergling";"Larva";237;1
"Unit";"Zergling";"Larva";237;1
"Unit";"Zergling";"Larva";237;1
"Unit";"Zergling";"Larva";237;1
"Unit";"Zergling";"Larva";237;1
"Unit";"Zergling";"Larva";237;1
"Unit";"Zergling";"Larva";237;1
"Unit";"Zergling";"Larva";237;1
"Unit";"Zergling";"Larva";237;1
"Unit";"Zergling";"Larva";237;1
"Unit";"Zergling";"Larva";237;1
"Unit";"Zergling";"Larva";237;1
"Building";"SpineCrawler";NA;231;0
"Unit";"Baneling";"Zergling";237;0
"Unit";"Baneling";"Zergling";237;0
"Unit";"Baneling";"Zergling";237;0
"Unit";"Baneling";"Zergling";237;0
"Unit";"Baneling";"Zergling";237;0
"Unit";"Baneling";"Zergling";237;0
"Unit";"Baneling";"Zergling";237;0
"Unit";"Baneling";"Zergling";237;0
"Unit";"Baneling";"Zergling";237;0
"Unit";"Baneling";"Zergling";237;0
"Unit";"Baneling";"Zergling";237;0
"Unit";"Baneling";"Zergling";237;0
"Unit";"Baneling";"Zergling";237;0
"Unit";"Baneling";"Zergling";237;0
"Unit";"Baneling";"Zergling";237;0
"Unit";"Baneling";"Zergling";237;0
"Unit";"Baneling";"Zergling";237;0
"Unit";"Baneling";"Zergling";237;0
"Unit";"Zergling";"Larva";237;1
"Unit";"Zergling";"Larva";237;1
"Building";"SpineCrawler";NA;231;0
"Unit";"Zergling";"Larva";237;1
"Unit";"Zergling";"Larva";237;1
"Unit";"Zergling";"Larva";237;1
"Unit";"Zergling";"Larva";237;1
"Unit";"Zergling";"Larva";237;1
"Unit";"Zergling";"Larva";237;1
"Unit";"Zergling";"Larva";237;1
"Unit";"Zergling";"Larva";237;1
"Unit";"Zergling";"Larva";237;1
"Unit";"Zergling";"Larva";237;1
"Unit";"Zergling";"Larva";239;1
"Unit";"Zergling";"Larva";239;1
"Unit";"Zergling";"Larva";239;1
"Unit";"Zergling";"Larva";239;1
"Unit";"Zergling";"Larva";239;1
"Unit";"Zergling";"Larva";239;1
"Unit";"Zergling";"Larva";239;1
"Unit";"Zergling";"Larva";239;1
"Unit";"Zergling";"Larva";241;1
"Unit";"Zergling";"Larva";241;1
"Unit";"Zergling";"Larva";241;1
"Unit";"Zergling";"Larva";241;1
"Unit";"Zergling";"Larva";241;1
"Unit";"Zergling";"Larva";241;1
"Building";"UltraliskCavern";NA;237;0
"Unit";"Zergling";"Larva";275;1
"Unit";"Zergling";"Larva";275;1
"Unit";"Zergling";"Larva";275;1
"Unit";"Zergling";"Larva";275;1
"Unit";"Zergling";"Larva";275;1
"Unit";"Zergling";"Larva";275;1
"Unit";"Zergling";"Larva";275;1
"Unit";"Zergling";"Larva";275;1
"Unit";"Zergling";"Larva";275;1
"Unit";"Zergling";"Larva";275;1
"Unit";"Zergling";"Larva";275;1
"Unit";"Zergling";"Larva";275;1
"Unit";"Zergling";"Larva";275;1
"Unit";"Zergling";"Larva";275;1
"Unit";"Zergling";"Larva";275;1
"Unit";"Zergling";"Larva";275;1
"Unit";"Zergling";"Larva";275;1
"Unit";"Zergling";"Larva";275;1
"Unit";"Zergling";"Larva";275;1
"Unit";"Zergling";"Larva";275;1
"Unit";"Zergling";"Larva";275;1
"Unit";"Zergling";"Larva";275;1
"Unit";"Zergling";"Larva";289;1
"Unit";"Zergling";"Larva";289;1
"Unit";"Zergling";"Larva";289;1
"Unit";"Zergling";"Larva";289;1
"Unit";"Zergling";"Larva";289;1
"Unit";"Zergling";"Larva";289;1
"Unit";"Zergling";"Larva";289;1
"Unit";"Zergling";"Larva";289;1
"Unit";"Zergling";"Larva";311;1
"Unit";"Zergling";"Larva";311;1
"Unit";"Zergling";"Larva";311;1
"Unit";"Zergling";"Larva";311;1
"Unit";"Zergling";"Larva";311;1
"Unit";"Zergling";"Larva";311;1
"Unit";"Zergling";"Larva";311;1
"Unit";"Zergling";"Larva";311;1
"Unit";"Zergling";"Larva";311;1
"Unit";"Zergling";"Larva";311;1
"Unit";"Zergling";"Larva";311;1
"Unit";"Zergling";"Larva";311;1
"Unit";"Zergling";"Larva";311;1
"Unit";"Zergling";"Larva";311;1
"Unit";"Zergling";"Larva";311;1
"Unit";"Zergling";"Larva";311;1
"Unit";"Zergling";"Larva";311;1
"Unit";"Zergling";"Larva";311;1
"Unit";"Zergling";"Larva";311;1
"Unit";"Zergling";"Larva";311;1
"Unit";"Zergling";"Larva";311;1
"Unit";"Zergling";"Larva";311;1
"Unit";"Zergling";"Larva";311;1
"Unit";"Zergling";"Larva";311;1
"Unit";"Zergling";"Larva";311;1
"Unit";"Zergling";"Larva";311;1
"Unit";"Zergling";"Larva";311;1
"Unit";"Zergling";"Larva";311;1
"Unit";"Zergling";"Larva";311;1
"Unit";"Zergling";"Larva";311;1
"Unit";"Zergling";"Larva";319;1
"Unit";"Zergling";"Larva";319;1
"Unit";"Zergling";"Larva";319;1
"Unit";"Zergling";"Larva";319;1
"Unit";"Zergling";"Larva";319;1
"Unit";"Zergling";"Larva";319;1
"Unit";"Zergling";"Larva";355;1
"Unit";"Zergling";"Larva";355;1
"Unit";"Zergling";"Larva";355;1
"Unit";"Zergling";"Larva";355;1
"Unit";"Zergling";"Larva";355;1
"Unit";"Zergling";"Larva";355;1
"Unit";"Zergling";"Larva";355;1
"Unit";"Zergling";"Larva";355;1
"Unit";"Zergling";"Larva";355;1
"Unit";"Zergling";"Larva";355;1
"Unit";"Zergling";"Larva";355;1
"Unit";"Zergling";"Larva";355;1
"Unit";"Zergling";"Larva";355;1
"Unit";"Zergling";"Larva";355;1
"Unit";"Zergling";"Larva";355;1
"Unit";"Zergling";"Larva";355;1
"Upgrade";"ZergGroundArmorsLevel2";"EvolutionChamber";237;0
"Unit";"Zergling";"Larva";355;1
"Unit";"Zergling";"Larva";355;1
"Unit";"Zergling";"Larva";355;1
"Unit";"Zergling";"Larva";355;1
"Unit";"Zergling";"Larva";355;1
"Unit";"Zergling";"Larva";355;1
"Unit";"Ultralisk";"Larva";319;6
"Unit";"Zergling";"Larva";355;1
"Unit";"Zergling";"Larva";355;1
"Unit";"Ultralisk";"Larva";319;6
"Unit";"Ultralisk";"Larva";319;6
"Upgrade";"ZergMeleeWeaponsLevel2";"EvolutionChamber";275;0
"Unit";"Ultralisk";"Larva";355;6
"Unit";"Ultralisk";"Larva";355;6
"Building";"CreepTumor";NA;397;0
"Unit";"Zergling";"Larva";397;1
"Unit";"Zergling";"Larva";397;1
"Unit";"Zergling";"Larva";397;1
"Unit";"Zergling";"Larva";397;1
"Unit";"Zergling";"Larva";397;1
"Unit";"Zergling";"Larva";397;1
"Unit";"Zergling";"Larva";397;1
"Unit";"Zergling";"Larva";397;1
"Unit";"Zergling";"Larva";397;1
"Unit";"Zergling";"Larva";397;1
"Unit";"Zergling";"Larva";397;1
"Unit";"Zergling";"Larva";397;1
"Unit";"Zergling";"Larva";397;1
"Unit";"Zergling";"Larva";397;1
"Unit";"Zergling";"Larva";397;1
"Unit";"Zergling";"Larva";397;1
"Unit";"Zergling";"Larva";397;1
"Unit";"Zergling";"Larva";397;1
"Unit";"Zergling";"Larva";397;1
"Unit";"Zergling";"Larva";397;1
"Unit";"Zergling";"Larva";397;1
"Unit";"Zergling";"Larva";397;1
"Unit";"Zergling";"Larva";397;1
"Unit";"Zergling";"Larva";397;1
"Unit";"Zergling";"Larva";397;1
"Unit";"Zergling";"Larva";397;1
"Unit";"Zergling";"Larva";397;1
"Unit";"Zergling";"Larva";397;1
"Unit";"Zergling";"Larva";397;1
"Unit";"Zergling";"Larva";397;1
"Building";"CreepTumor";NA;397;0
"Building";"CreepTumor";NA;397;0
