"Type";"UnitName";"OnBuilding";"TotalSupply";"Supply"
"Unit";"SCV";"Command Center";12;1
"Unit";"SCV";"Command Center";12;1
"Unit";"SCV";"Command Center";13;1
"Building";"SupplyDepot";NA;13;0
"Building";"Refinery";NA;14;0
"Unit";"SCV";"Command Center";15;1
"Unit";"SCV";"Command Center";16;1
"Unit";"SCV";"Command Center";16;1
"Unit";"SCV";"Command Center";17;1
"Building";"Barracks";NA;15;0
"Building";"Refinery";NA;17;0
"Unit";"Marine";"Barracks";19;1
"Building";"SupplyDepot";NA;19;0
"Unit";"SCV";"Command Center";20;1
"Building";"Factory";NA;19;0
"Unit";"SCV";"Command Center";20;1
"Building";"BarracksReactor";NA;20;0
"Unit";"SCV";"Command Center";22;1
"Unit";"SCV";"Command Center";22;1
"Unit";"Marine";"Barracks";22;1
"Building";"SupplyDepot";NA;22;0
"Unit";"Cyclone";"Factory";23;3
"Unit";"Cyclone";"Factory";23;3
"Unit";"SCV";"Command Center";31;1
"Unit";"Cyclone";"Factory";31;3
"Unit";"Marine";"Barracks";31;1
"Unit";"Cyclone";"Factory";31;3
"Unit";"SCV";"Command Center";32;1
"Unit";"SCV";"Command Center";39;1
"Building";"CommandCenter";NA;25;0
"Unit";"SCV";"Command Center";41;1
"Building";"SupplyDepot";NA;41;0
"Building";"SupplyDepot";NA;41;0
"Building";"BarracksTechLab";NA;41;0
"Unit";"SCV";"Command Center";42;1
"Unit";"Cyclone";"Factory";41;3
"Unit";"Cyclone";"Factory";41;3
"Building";"Starport";NA;41;0
"Unit";"SCV";"Command Center";42;1
"Unit";"SCV";"Command Center";50;1
"Unit";"SCV";"Command Center";50;1
"Building";"SupplyDepot";NA;50;0
"Building";"SupplyDepot";NA;50;0
"Building";"BarracksReactor";NA;50;0
"Unit";"SCV";"Command Center";52;1
"Unit";"SCV";"Command Center";52;1
"Unit";"Banshee";"Starport";50;3
"Building";"FactoryTechLab";NA;52;0
"Unit";"SCV";"Command Center";53;1
"Unit";"Marine";"Barracks";52;1
"Building";"SupplyDepot";NA;52;0
"Unit";"Marine";"Barracks";52;1
"Unit";"SCV";"Command Center";54;1
"Unit";"SCV";"Command Center";60;1
"Unit";"SCV";"Command Center";61;1
"Unit";"Marine";"Barracks";61;1
"Unit";"Marine";"Barracks";61;1
"Unit";"Banshee";"Starport";60;3
"Unit";"SCV";"Command Center";65;1
"Unit";"Marine";"Barracks";65;1
"Unit";"Marine";"Barracks";65;1
"Unit";"SCV";"Command Center";68;1
"Unit";"SCV";"Command Center";69;1
"Unit";"SCV";"Command Center";71;1
"Unit";"SCV";"Command Center";72;1
"Unit";"Marine";"Barracks";71;1
"Unit";"Marine";"Barracks";71;1
"Unit";"SCV";"Command Center";73;1
"Unit";"SCV";"Command Center";74;1
"Unit";"Marine";"Barracks";75;1
"Unit";"Marine";"Barracks";76;1
"Building";"Refinery";NA;75;0
"Unit";"SCV";"Command Center";77;1
"Building";"Refinery";NA;75;0
"Building";"Barracks";NA;69;0
"Unit";"SCV";"Command Center";78;1
"Building";"Barracks";NA;69;0
"Unit";"SCV";"Command Center";81;1
"Unit";"SCV";"Command Center";82;1
"Building";"SupplyDepot";NA;79;0
"Building";"SupplyDepot";NA;79;0
"Unit";"Marine";"Barracks";79;1
"Unit";"Marine";"Barracks";80;1
"Building";"SupplyDepot";NA;82;0
"Building";"SupplyDepot";NA;82;0
"Building";"SupplyDepot";NA;83;0
"Unit";"SCV";"Command Center";85;1
"Unit";"SCV";"Command Center";85;1
"Unit";"Marine";"Barracks";84;1
"Unit";"Marine";"Barracks";84;1
"Unit";"Marine";"Barracks";84;1
"Unit";"Marine";"Barracks";85;1
"Building";"StarportReactor";NA;82;0
"Unit";"SCV";"Command Center";87;1
"Unit";"SCV";"Command Center";88;1
"Unit";"Marine";"Barracks";87;1
"Unit";"Marine";"Barracks";89;1
"Building";"EngineeringBay";NA;87;0
"Unit";"SCV";"Command Center";93;1
"Unit";"SCV";"Command Center";94;1
"Unit";"SCV";"Command Center";99;1
"Unit";"SCV";"Command Center";99;1
"Unit";"Marine";"Barracks";97;1
"Unit";"Marine";"Barracks";98;1
"Unit";"Marine";"Barracks";99;1
"Building";"Barracks";NA;93;0
"Building";"Barracks";NA;93;0
"Building";"SupplyDepot";NA;99;0
"Unit";"Marine";"Barracks";99;1
"Unit";"Marine";"Barracks";99;1
"Unit";"SCV";"Command Center";104;1
"Unit";"SCV";"Command Center";104;1
"Building";"SupplyDepot";NA;104;0
"Unit";"SCV";"Command Center";106;1
"Unit";"SCV";"Command Center";107;1
"Building";"SupplyDepot";NA;104;0
"Unit";"Marine";"Barracks";108;1
"Unit";"Marine";"Barracks";108;1
"Unit";"Marine";"Barracks";108;1
"Unit";"Marine";"Barracks";108;1
"Unit";"Marine";"Barracks";108;1
"Unit";"Marine";"Barracks";108;1
"Unit";"Marine";"Barracks";110;1
"Unit";"Marine";"Barracks";111;1
"Unit";"Marine";"Barracks";112;1
"Unit";"SCV";"Command Center";116;1
"Unit";"Marine";"Barracks";116;1
"Building";"SupplyDepot";NA;116;0
"Unit";"Marine";"Barracks";116;1
"Unit";"Marine";"Barracks";116;1
"Building";"SupplyDepot";NA;116;0
"Upgrade";"Stimpack";"TechLab";99;0
"Unit";"Marine";"Barracks";119;1
"Unit";"Marine";"Barracks";119;1
"Unit";"Marine";"Barracks";125;1
"Unit";"Marine";"Barracks";125;1
"Unit";"Marine";"Barracks";125;1
"Unit";"Marine";"Barracks";125;1
"Unit";"Marine";"Barracks";125;1
"Unit";"Marine";"Barracks";125;1
"Upgrade";"TerranInfantryWeaponsLevel1";"EngineeringBay";108;0
"Building";"CommandCenter";NA;116;0
"Unit";"Medivac";"Starport";125;2
"Unit";"Marine";"Barracks";131;1
"Unit";"Marine";"Barracks";131;1
"Unit";"Marine";"Barracks";135;1
"Unit";"Marine";"Barracks";135;1
"Unit";"SCV";"Command Center";137;1
"Unit";"SCV";"Command Center";137;1
"Unit";"SCV";"Command Center";138;1
"Unit";"Marine";"Barracks";138;1
"Unit";"SCV";"Command Center";139;1
"Unit";"SCV";"Command Center";139;1
"Unit";"Liberator";"Starport";137;3
"Unit";"SCV";"Command Center";141;1
"Unit";"SCV";"Command Center";142;1
"Unit";"Marine";"Barracks";142;1
"Unit";"Marine";"Barracks";142;1
"Unit";"Marine";"Barracks";142;1
"Unit";"SCV";"Command Center";146;1
"Unit";"SCV";"Command Center";147;1
"Building";"StarportTechLab";NA;146;0
"Unit";"SCV";"Command Center";148;1
"Unit";"SCV";"Command Center";154;1
"Unit";"SCV";"Command Center";154;1
"Unit";"Marine";"Barracks";154;1
"Unit";"Marine";"Barracks";154;1
"Unit";"Marine";"Barracks";154;1
"Unit";"SCV";"Command Center";159;1
"Unit";"SCV";"Command Center";159;1
"Unit";"Marine";"Barracks";159;1
"Unit";"SCV";"Command Center";159;1
"Unit";"Marine";"Barracks";159;1
"Unit";"Banshee";"Starport";154;3
"Unit";"SCV";"Command Center";161;1
"Building";"Factory";NA;154;0
"Unit";"SCV";"Command Center";167;1
"Unit";"SCV";"Command Center";169;1
"Unit";"Marine";"Barracks";168;1
"Building";"FactoryTechLab";NA;168;0
"Unit";"Marine";"Barracks";168;1
"Unit";"SCV";"Command Center";169;1
"Unit";"SCV";"Command Center";169;1
"Unit";"SCV";"Command Center";170;1
"Unit";"SCV";"Command Center";174;1
"Building";"BarracksReactor";NA;169;0
"Unit";"Marine";"Barracks";172;1
"Unit";"Marine";"Barracks";172;1
"Unit";"SCV";"Command Center";174;1
"Unit";"SCV";"Command Center";176;1
"Unit";"SCV";"Command Center";176;1
"Building";"Factory";NA;169;0
"Unit";"Banshee";"Starport";169;3
"Building";"Refinery";NA;175;0
"Building";"Barracks";NA;169;0
"Unit";"Marine";"Barracks";179;1
"Unit";"Marine";"Barracks";179;1
"Unit";"SCV";"Command Center";184;1
"Unit";"Marine";"Barracks";181;1
"Unit";"Marine";"Barracks";184;1
"Unit";"SCV";"Command Center";184;1
"Unit";"Marine";"Barracks";184;1
"Unit";"Marine";"Barracks";185;1
"Unit";"SCV";"Command Center";189;1
"Unit";"SCV";"Command Center";190;1
"Unit";"Marine";"Barracks";187;1
"Unit";"Marine";"Barracks";188;1
"Building";"FactoryTechLab";NA;190;0
"Unit";"Marine";"Barracks";190;1
"Unit";"Marine";"Barracks";191;1
"Unit";"SCV";"Command Center";193;1
"Unit";"Marine";"Barracks";199;1
"Unit";"Marine";"Barracks";199;1
"Unit";"Marine";"Barracks";199;1
"Unit";"Marine";"Barracks";199;1
"Unit";"SCV";"Command Center";199;1
"Unit";"SCV";"Command Center";199;1
