"Type";"UnitName";"OnBuilding";"TotalSupply";"Supply"
"Unit";"SCV";"Command Center";12;1
"Unit";"SCV";"Command Center";12;1
"Unit";"SCV";"Command Center";13;1
"Building";"SupplyDepot";NA;13;0
"Unit";"SCV";"Command Center";15;1
"Building";"Refinery";NA;14;0
"Unit";"SCV";"Command Center";15;1
"Unit";"SCV";"Command Center";16;1
"Building";"Refinery";NA;16;0
"Unit";"SCV";"Command Center";17;1
"Building";"Barracks";NA;15;0
"Building";"SupplyDepot";NA;19;0
"Unit";"Reaper";"Barracks";19;1
"Unit";"SCV";"Command Center";19;1
"Building";"Factory";NA;19;0
"Unit";"SCV";"Command Center";21;1
"Unit";"SCV";"Command Center";22;1
"Unit";"Reaper";"Barracks";21;1
"Building";"SupplyDepot";NA;22;0
"Unit";"SCV";"Command Center";22;1
"Unit";"Cyclone";"Factory";22;3
"Unit";"SCV";"Command Center";28;1
"Building";"BarracksReactor";NA;24;0
"Unit";"Cyclone";"Factory";28;3
"Unit";"SCV";"Command Center";29;1
"Building";"SupplyDepot";NA;28;0
"Unit";"SCV";"Command Center";32;1
"Building";"Starport";NA;28;0
"Unit";"SCV";"Command Center";33;1
"Unit";"SCV";"Command Center";34;1
"Building";"CommandCenter";NA;28;0
"Unit";"SCV";"Command Center";35;1
"Unit";"Hellion";"Factory";35;2
"Unit";"Medivac";"Starport";34;2
"Building";"SupplyDepot";NA;35;0
"Unit";"Cyclone";"Factory";36;3
"Unit";"SCV";"Command Center";36;1
"Building";"BarracksTechLab";NA;36;0
"Unit";"SCV";"Command Center";44;1
"Unit";"SCV";"Command Center";45;1
"Unit";"Cyclone";"Factory";41;3
"Unit";"Hellion";"Factory";45;2
"Unit";"SCV";"Command Center";45;1
"Unit";"SCV";"Command Center";46;1
"Unit";"SCV";"Command Center";52;1
"Unit";"SCV";"Command Center";55;1
"Unit";"SCV";"Command Center";55;1
"Unit";"SCV";"Command Center";55;1
"Unit";"SCV";"Command Center";56;1
"Building";"FactoryTechLab";NA;57;0
"Unit";"Marine";"Barracks";57;1
"Unit";"Marine";"Barracks";57;1
"Unit";"SCV";"Command Center";57;1
"Unit";"SCV";"Command Center";58;1
"Unit";"SCV";"Command Center";61;1
"Unit";"SCV";"Command Center";62;1
"Unit";"Marine";"Barracks";61;1
"Unit";"Marine";"Barracks";61;1
"Building";"Refinery";NA;63;0
"Unit";"SCV";"Command Center";63;1
"Unit";"SCV";"Command Center";64;1
"Building";"Refinery";NA;59;0
"Building";"EngineeringBay";NA;63;0
"Building";"SupplyDepot";NA;63;0
"Building";"SupplyDepot";NA;63;0
"Building";"EngineeringBay";NA;63;0
"Building";"SupplyDepot";NA;63;0
"Unit";"Raven";"Starport";59;2
"Unit";"SCV";"Command Center";67;1
"Unit";"SCV";"Command Center";68;1
"Unit";"Marine";"Barracks";67;1
"Unit";"Marine";"Barracks";67;1
"Unit";"SCV";"Command Center";71;1
"Unit";"SCV";"Command Center";72;1
"Building";"CommandCenter";NA;57;0
"Unit";"SCV";"Command Center";75;1
"Unit";"SCV";"Command Center";77;1
"Unit";"Marine";"Barracks";77;1
"Unit";"SCV";"Command Center";77;1
"Unit";"SCV";"Command Center";78;1
"Building";"FactoryReactor";NA;75;0
"Building";"StarportReactor";NA;75;0
"Unit";"SCV";"Command Center";80;1
"Unit";"Marine";"Barracks";79;1
"Unit";"SCV";"Command Center";81;1
"Building";"Barracks";NA;75;0
"Unit";"SCV";"Command Center";82;1
"Building";"Barracks";NA;77;0
"Building";"Barracks";NA;77;0
"Unit";"SCV";"Command Center";86;1
"Unit";"SCV";"Command Center";86;1
"Unit";"SCV";"Command Center";86;1
"Unit";"Marine";"Barracks";86;1
"Unit";"Marine";"Barracks";86;1
"Unit";"Marine";"Barracks";86;1
"Unit";"SCV";"Command Center";86;1
"Unit";"SCV";"Command Center";87;1
"Unit";"Marine";"Barracks";86;1
"Building";"Barracks";NA;82;0
"Unit";"Marine";"Barracks";86;1
"Unit";"SCV";"Command Center";92;1
"Unit";"SCV";"Command Center";93;1
"Unit";"Marine";"Barracks";89;1
"Unit";"Marine";"Barracks";89;1
"Unit";"Marine";"Barracks";89;1
"Unit";"Marine";"Barracks";90;1
"Unit";"Marine";"Barracks";91;1
"Unit";"Marine";"Barracks";94;1
"Unit";"SCV";"Command Center";96;1
"Unit";"SCV";"Command Center";97;1
"Upgrade";"TerranInfantryWeaponsLevel1";"EngineeringBay";79;0
"Upgrade";"TerranInfantryArmorsLevel1";"EngineeringBay";79;0
"Building";"StarportReactor";NA;89;0
"Building";"SupplyDepot";NA;96;0
"Unit";"Marine";"Barracks";96;1
"Unit";"SCV";"Command Center";104;1
"Unit";"SCV";"Command Center";104;1
"Unit";"SCV";"Command Center";105;1
"Building";"SupplyDepot";NA;98;0
"Building";"Armory";NA;89;0
"Building";"SupplyDepot";NA;98;0
"Building";"SupplyDepot";NA;101;0
"Unit";"Marine";"Barracks";104;1
"Unit";"Marine";"Barracks";104;1
"Unit";"Marine";"Barracks";104;1
"Unit";"Marine";"Barracks";104;1
"Unit";"Marine";"Barracks";104;1
"Unit";"Marine";"Barracks";106;1
"Unit";"SCV";"Command Center";107;1
"Unit";"SCV";"Command Center";108;1
"Unit";"SCV";"Command Center";109;1
"Upgrade";"Stimpack";"TechLab";83;0
"Unit";"Marine";"Barracks";110;1
"Unit";"SCV";"Command Center";116;1
"Unit";"Marine";"Barracks";110;1
"Building";"BarracksReactor";NA;106;0
"Unit";"SCV";"Command Center";117;1
"Unit";"SCV";"Command Center";118;1
"Unit";"Marine";"Barracks";116;1
"Unit";"Marine";"Barracks";116;1
"Unit";"Marine";"Barracks";117;1
"Building";"Refinery";NA;116;0
"Building";"Refinery";NA;117;0
"Unit";"SCV";"Command Center";122;1
"Unit";"SCV";"Command Center";122;1
"Unit";"Marine";"Barracks";119;1
"Unit";"Marine";"Barracks";119;1
"Unit";"Marine";"Barracks";119;1
"Unit";"Marine";"Barracks";125;1
"Unit";"Marine";"Barracks";125;1
"Unit";"Marine";"Barracks";125;1
"Unit";"Marine";"Barracks";126;1
"Unit";"Marine";"Barracks";126;1
"Unit";"Medivac";"Starport";121;2
"Unit";"Medivac";"Starport";121;2
"Unit";"Marine";"Barracks";131;1
"Unit";"Marine";"Barracks";131;1
"Unit";"Marine";"Barracks";132;1
"Unit";"Marine";"Barracks";132;1
"Unit";"Marine";"Barracks";137;1
"Unit";"Marine";"Barracks";137;1
"Unit";"Marine";"Barracks";139;1
"Unit";"Marine";"Barracks";141;1
"Unit";"Marine";"Barracks";141;1
"Building";"Factory";NA;127;0
"Unit";"Marine";"Barracks";141;1
"Unit";"Marine";"Barracks";142;1
"Unit";"Medivac";"Starport";141;2
"Unit";"Marine";"Barracks";145;1
"Unit";"Marine";"Barracks";145;1
"Building";"SupplyDepot";NA;145;0
"Unit";"Marine";"Barracks";145;1
"Unit";"Marine";"Barracks";146;1
"Unit";"Marine";"Barracks";147;1
"Unit";"Marine";"Barracks";148;1
"Building";"SupplyDepot";NA;145;0
"Building";"SupplyDepot";NA;145;0
"Building";"SupplyDepot";NA;145;0
"Building";"FactoryTechLab";NA;152;0
"Unit";"Medivac";"Starport";150;2
"Unit";"Marine";"Barracks";156;1
"Unit";"Marine";"Barracks";156;1
"Unit";"Marine";"Barracks";156;1
"Unit";"Marine";"Barracks";160;1
"Unit";"Marine";"Barracks";160;1
"Unit";"Marine";"Barracks";160;1
"Unit";"Marine";"Barracks";160;1
"Unit";"Medivac";"Starport";156;2
"Unit";"Marine";"Barracks";165;1
"Unit";"Marine";"Barracks";168;1
"Unit";"Marine";"Barracks";168;1
"Unit";"Marine";"Barracks";168;1
"Unit";"Marauder";"Barracks";168;2
"Unit";"Marine";"Barracks";168;1
"Unit";"Medivac";"Starport";160;2
"Unit";"Marine";"Barracks";168;1
"Upgrade";"TerranInfantryWeaponsLevel2";"EngineeringBay";132;0
"Upgrade";"TerranInfantryArmorsLevel2";"EngineeringBay";132;0
"Unit";"Marine";"Barracks";172;1
"Unit";"Marine";"Barracks";172;1
"Unit";"Marine";"Barracks";174;1
"Upgrade";"TerranVehicleWeaponsLevel1";"Armory";149;0
"Unit";"Marine";"Barracks";181;1
"Unit";"Marine";"Barracks";181;1
"Unit";"Marine";"Barracks";181;1
"Unit";"Marine";"Barracks";181;1
"Unit";"Marine";"Barracks";181;1
"Unit";"Marine";"Barracks";181;1
"Unit";"Marine";"Barracks";181;1
"Building";"CommandCenter";NA;160;0
"Unit";"Marine";"Barracks";184;1
"Unit";"Marine";"Barracks";184;1
"Unit";"Marine";"Barracks";184;1
"Unit";"Medivac";"Starport";184;2
"Unit";"Medivac";"Starport";184;2
"Unit";"Marine";"Barracks";190;1
"Unit";"Marine";"Barracks";190;1
"Unit";"Marine";"Barracks";190;1
"Unit";"Marine";"Barracks";190;1
"Unit";"Marine";"Barracks";190;1
"Unit";"Marine";"Barracks";191;1
"Unit";"Marine";"Barracks";192;1
"Unit";"Marine";"Barracks";193;1
"Unit";"Marine";"Barracks";203;1
"Unit";"Marine";"Barracks";204;1
"Unit";"Marine";"Barracks";204;1
"Unit";"Marine";"Barracks";204;1
"Unit";"Marine";"Barracks";204;1
"Unit";"Marine";"Barracks";204;1
"Unit";"Marine";"Barracks";204;1
"Unit";"Marine";"Barracks";204;1
"Unit";"Marine";"Barracks";205;1
"Building";"Refinery";NA;205;0
"Unit";"Marine";"Barracks";206;1
"Building";"Refinery";NA;206;0
"Unit";"Marine";"Barracks";216;1
"Unit";"Marine";"Barracks";216;1
"Unit";"Marine";"Barracks";216;1
"Unit";"Marine";"Barracks";216;1
"Unit";"Marine";"Barracks";216;1
"Unit";"Marine";"Barracks";216;1
"Unit";"Marine";"Barracks";216;1
"Unit";"Marine";"Barracks";216;1
"Unit";"Marine";"Barracks";216;1
"Unit";"Marine";"Barracks";216;1
"Unit";"Marine";"Barracks";226;1
"Unit";"Marine";"Barracks";226;1
"Unit";"Marine";"Barracks";226;1
"Unit";"Marine";"Barracks";226;1
"Unit";"Marine";"Barracks";226;1
"Unit";"Marine";"Barracks";226;1
"Unit";"Marine";"Barracks";226;1
"Unit";"Marine";"Barracks";226;1
"Unit";"Marine";"Barracks";226;1
"Unit";"Marine";"Barracks";226;1
"Unit";"Marine";"Barracks";227;1
"Unit";"Marine";"Barracks";228;1
"Unit";"Marine";"Barracks";229;1
"Unit";"Marine";"Barracks";229;1
"Unit";"Marine";"Barracks";231;1
"Unit";"Marine";"Barracks";231;1
"Unit";"Marine";"Barracks";233;1
"Unit";"Marine";"Barracks";235;1
"Unit";"Marine";"Barracks";235;1
"Unit";"Marine";"Barracks";236;1
"Unit";"Marauder";"Barracks";242;2
"Unit";"Medivac";"Starport";236;2
"Unit";"Medivac";"Starport";236;2
"Upgrade";"TerranInfantryWeaponsLevel3";"EngineeringBay";216;0
"Upgrade";"TerranInfantryArmorsLevel3";"EngineeringBay";216;0
"Upgrade";"TerranVehicleWeaponsLevel2";"Armory";225;0
"Unit";"Marine";"Barracks";252;1
"Unit";"Marine";"Barracks";252;1
"Unit";"Marine";"Barracks";252;1
"Building";"CommandCenter";NA;235;0
"Unit";"Marine";"Barracks";254;1
"Unit";"Marine";"Barracks";255;1
"Unit";"Marine";"Barracks";255;1
"Unit";"Marine";"Barracks";255;1
"Unit";"Marine";"Barracks";255;1
"Unit";"Marine";"Barracks";255;1
"Unit";"Marine";"Barracks";255;1
"Unit";"Marine";"Barracks";255;1
"Unit";"Marine";"Barracks";255;1
"Unit";"Marine";"Barracks";255;1
"Building";"Starport";NA;255;0
"Building";"Starport";NA;255;0
"Building";"Starport";NA;255;0
"Building";"Starport";NA;256;0
"Building";"Starport";NA;256;0
"Building";"Starport";NA;264;0
"Building";"Starport";NA;264;0
"Building";"FusionCore";NA;256;0
"Building";"StarportTechLab";NA;265;0
"Building";"StarportTechLab";NA;265;0
"Building";"StarportTechLab";NA;265;0
"Building";"StarportTechLab";NA;265;0
"Building";"StarportTechLab";NA;265;0
"Building";"StarportTechLab";NA;265;0
"Building";"StarportTechLab";NA;265;0
