"type";"unit_name";"on_building";"total_supply";"supply"
"Building";"Refinery";NA;14;0
"Building";"Barracks";NA;15;0
"Unit";"Reaper";"Barracks";19;1
"Building";"Refinery";NA;19;0
"Building";"Factory";NA;19;0
"Building";"BarracksReactor";NA;20;0
"Building";"CommandCenter";NA;19;0
"Building";"Refinery";NA;24;0
"Unit";"Cyclone";"Factory";24;3
"Unit";"Cyclone";"Factory";24;3
"Building";"Starport";NA;24;0
"Unit";"Hellion";"Factory";32;2
"Building";"BarracksTechLab";NA;33;0
"Unit";"Hellion";"Factory";33;2
"Unit";"Hellion";"Factory";42;2
"Unit";"Hellion";"Factory";42;2
"Unit";"Medivac";"Starport";42;2
"Unit";"Cyclone";"Factory";52;3
"Building";"BarracksReactor";NA;44;0
"Unit";"Cyclone";"Factory";54;3
"Unit";"Banshee";"Starport";54;3
"Unit";"Cyclone";"Factory";67;3
"Building";"Refinery";NA;67;0
"Unit";"Cyclone";"Factory";67;3
"Building";"BarracksTechLab";NA;68;0
"Unit";"Hellion";"Factory";69;2
"Unit";"Banshee";"Starport";67;3
"Unit";"Hellion";"Factory";76;2
"Building";"Factory";NA;68;0
"Building";"Factory";NA;68;0
"Unit";"Raven";"Starport";91;2
"Unit";"Hellion";"Factory";94;2
"Unit";"Hellion";"Factory";94;2
"Building";"EngineeringBay";NA;94;0
"Building";"Armory";NA;94;0
"Building";"Armory";NA;94;0
"Building";"CommandCenter";NA;92;0
"Unit";"Hellion";"Factory";103;2
"Unit";"Hellion";"Factory";103;2
"Unit";"Hellion";"Factory";115;2
"Unit";"Hellion";"Factory";115;2
"Building";"Factory";NA;113;0
"Building";"Factory";NA;113;0
"Building";"FactoryTechLab";NA;121;0
"Unit";"Hellion";"Factory";121;2
"Unit";"Hellion";"Factory";121;2
"Building";"FactoryReactor";NA;121;0
"Unit";"Hellion";"Factory";123;2
"Unit";"Hellion";"Factory";123;2
"Unit";"Hellion";"Factory";123;2
"Unit";"Hellion";"Factory";125;2
"Building";"SensorTower";NA;127;0
"Unit";"Hellion";"Factory";127;2
"Building";"Refinery";NA;127;0
"Unit";"Hellion";"Factory";127;2
"Unit";"Hellion";"Factory";127;2
"Unit";"Hellion";"Factory";129;2
"Upgrade";"TerranVehicleWeaponsLevel1";"Armory";117;0
"Unit";"Hellion";"Factory";141;2
"Unit";"Hellion";"Factory";141;2
"Building";"Refinery";NA;143;0
"Building";"CommandCenter";NA;122;0
"Unit";"Hellion";"Factory";143;2
"Unit";"Hellion";"Factory";143;2
"Unit";"Hellion";"Factory";143;2
"Unit";"Hellion";"Factory";143;2
"Unit";"Hellion";"Factory";145;2
"Unit";"Hellion";"Factory";156;2
"Unit";"Hellion";"Factory";162;2
"Unit";"Hellion";"Factory";164;2
"Unit";"Hellion";"Factory";164;2
"Unit";"Hellion";"Factory";164;2
"Unit";"Hellion";"Factory";172;2
"Unit";"Hellion";"Factory";172;2
"Unit";"Hellion";"Factory";172;2
"Unit";"Hellion";"Factory";172;2
"Unit";"Thor";"Factory";172;6
"Unit";"Thor";"Factory";172;6
"Unit";"Hellion";"Factory";195;2
"Building";"MissileTurret";NA;197;0
