"Type";"UnitName";"OnBuilding";"TotalSupply";"Supply"
"Unit";"SCV";"Command Center";12;1
"Unit";"SCV";"Command Center";12;1
"Unit";"SCV";"Command Center";13;1
"Building";"SupplyDepot";NA;13;0
"Building";"Refinery";NA;14;0
"Unit";"SCV";"Command Center";15;1
"Unit";"SCV";"Command Center";15;1
"Unit";"SCV";"Command Center";16;1
"Building";"Refinery";NA;16;0
"Unit";"SCV";"Command Center";17;1
"Building";"Barracks";NA;15;0
"Unit";"Reaper";"Barracks";19;1
"Unit";"SCV";"Command Center";19;1
"Building";"SupplyDepot";NA;19;0
"Building";"Factory";NA;19;0
"Unit";"SCV";"Command Center";21;1
"Unit";"Reaper";"Barracks";20;1
"Unit";"SCV";"Command Center";22;1
"Unit";"Cyclone";"Factory";22;3
"Unit";"SCV";"Command Center";24;1
"Unit";"SCV";"Command Center";28;1
"Building";"BarracksReactor";NA;24;0
"Unit";"Cyclone";"Factory";28;3
"Building";"SupplyDepot";NA;28;0
"Unit";"SCV";"Command Center";32;1
"Unit";"Marine";"Barracks";32;1
"Unit";"Marine";"Barracks";32;1
"Unit";"SCV";"Command Center";32;1
"Building";"CommandCenter";NA;24;0
"Building";"SupplyDepot";NA;32;0
"Building";"Starport";NA;29;0
"Building";"FactoryTechLab";NA;33;0
"Building";"EngineeringBay";NA;32;0
"Unit";"SCV";"Command Center";36;1
"Unit";"Marine";"Barracks";35;1
"Unit";"Marine";"Barracks";35;1
"Unit";"SCV";"Command Center";37;1
"Building";"MissileTurret";NA;37;0
"Building";"MissileTurret";NA;39;0
"Unit";"Marine";"Barracks";39;1
"Unit";"Marine";"Barracks";39;1
"Unit";"SCV";"Command Center";40;1
"Unit";"SCV";"Command Center";40;1
"Unit";"SCV";"Command Center";42;1
"Unit";"SCV";"Command Center";44;1
"Unit";"SCV";"Command Center";46;1
"Unit";"SCV";"Command Center";46;1
"Unit";"SCV";"Command Center";46;1
"Unit";"SCV";"Command Center";47;1
"Building";"BarracksTechLab";NA;46;0
"Unit";"SCV";"Command Center";50;1
"Unit";"SCV";"Command Center";50;1
"Building";"Barracks";NA;45;0
"Unit";"Marine";"Barracks";50;1
"Building";"Barracks";NA;46;0
"Unit";"SCV";"Command Center";50;1
"Unit";"SCV";"Command Center";52;1
"Building";"Refinery";NA;50;0
"Building";"SupplyDepot";NA;50;0
"Building";"SupplyDepot";NA;50;0
"Building";"StarportReactor";NA;50;0
"Unit";"Marine";"Barracks";54;1
"Unit";"Marine";"Barracks";55;1
"Unit";"Marine";"Barracks";55;1
"Unit";"SCV";"Command Center";55;1
"Unit";"SCV";"Command Center";55;1
"Building";"SupplyDepot";NA;55;0
"Building";"SupplyDepot";NA;55;0
"Unit";"Marine";"Barracks";55;1
"Unit";"Marine";"Barracks";58;1
"Unit";"Marine";"Barracks";58;1
"Unit";"Marine";"Barracks";58;1
"Unit";"Marine";"Barracks";58;1
"Unit";"SCV";"Command Center";60;1
"Unit";"SCV";"Command Center";60;1
"Building";"StarportReactor";NA;55;0
"Unit";"Marine";"Barracks";60;1
"Unit";"SCV";"Command Center";65;1
"Unit";"Marine";"Barracks";61;1
"Unit";"Marine";"Barracks";62;1
"Unit";"Marine";"Barracks";63;1
"Unit";"SCV";"Command Center";67;1
"Building";"SupplyDepot";NA;61;0
"Building";"SupplyDepot";NA;65;0
"Unit";"SCV";"Command Center";69;1
"Building";"Refinery";NA;67;0
"Unit";"Marine";"Barracks";69;1
"Unit";"Marine";"Barracks";69;1
"Unit";"Marine";"Barracks";69;1
"Unit";"SCV";"Command Center";73;1
"Unit";"SCV";"Command Center";73;1
"Unit";"Medivac";"Starport";69;2
"Unit";"Marine";"Barracks";73;1
"Unit";"Medivac";"Starport";69;2
"Unit";"Marine";"Barracks";73;1
"Unit";"Marine";"Barracks";74;1
"Unit";"SCV";"Command Center";77;1
"Building";"SupplyDepot";NA;76;0
"Unit";"Marine";"Barracks";77;1
"Unit";"Marine";"Barracks";77;1
"Building";"SupplyDepot";NA;76;0
"Upgrade";"Stimpack";"TechLab";55;0
"Unit";"Marine";"Barracks";85;1
"Unit";"Marine";"Barracks";85;1
"Unit";"SCV";"Command Center";89;1
"Unit";"SCV";"Command Center";89;1
"Building";"SensorTower";NA;89;0
"Unit";"Marine";"Barracks";91;1
"Unit";"Marine";"Barracks";91;1
"Unit";"Marine";"Barracks";91;1
"Unit";"SCV";"Command Center";91;1
"Unit";"Marine";"Barracks";93;1
"Unit";"Marine";"Barracks";93;1
"Unit";"Marine";"Barracks";93;1
"Unit";"SCV";"Command Center";97;1
"Unit";"Marine";"Barracks";97;1
"Unit";"Marine";"Barracks";97;1
"Unit";"SCV";"Command Center";97;1
"Upgrade";"TerranInfantryWeaponsLevel1";"EngineeringBay";74;0
"Unit";"SCV";"Command Center";100;1
"Unit";"Marine";"Barracks";97;1
"Unit";"Marine";"Barracks";99;1
"Building";"Armory";NA;93;0
"Building";"CommandCenter";NA;89;0
"Unit";"Marine";"Barracks";106;1
"Unit";"Marine";"Barracks";106;1
"Unit";"Marine";"Barracks";106;1
"Unit";"SCV";"Command Center";107;1
"Unit";"Marine";"Barracks";107;1
"Unit";"Marine";"Barracks";107;1
"Unit";"SCV";"Command Center";107;1
"Building";"Barracks";NA;103;0
"Unit";"Marine";"Barracks";107;1
"Building";"Barracks";NA;103;0
"Unit";"SCV";"Command Center";114;1
"Unit";"SCV";"Command Center";114;1
"Unit";"Marine";"Barracks";111;1
"Unit";"Marine";"Barracks";111;1
"Unit";"Marine";"Barracks";111;1
"Unit";"Marine";"Barracks";114;1
"Unit";"SCV";"Command Center";117;1
"Unit";"SCV";"Command Center";117;1
"Building";"Barracks";NA;107;0
"Building";"Barracks";NA;107;0
"Unit";"Marine";"Barracks";123;1
"Unit";"Marine";"Barracks";123;1
"Building";"BarracksReactor";NA;115;0
"Building";"BarracksReactor";NA;115;0
"Unit";"Marine";"Barracks";123;1
"Unit";"Marine";"Barracks";126;1
"Unit";"Marine";"Barracks";126;1
"Unit";"Marine";"Barracks";126;1
"Unit";"Marine";"Barracks";126;1
"Unit";"Marine";"Barracks";126;1
"Unit";"Marine";"Barracks";126;1
"Unit";"Marine";"Barracks";126;1
"Unit";"Marine";"Barracks";133;1
"Unit";"Marine";"Barracks";133;1
"Unit";"Marine";"Barracks";133;1
"Unit";"Marine";"Barracks";133;1
"Unit";"SCV";"Command Center";135;1
"Unit";"Marine";"Barracks";133;1
"Unit";"Marine";"Barracks";133;1
"Building";"Refinery";NA;135;0
"Unit";"Marine";"Barracks";137;1
"Unit";"Marine";"Barracks";137;1
"Unit";"Marine";"Barracks";137;1
"Unit";"Marine";"Barracks";137;1
"Upgrade";"TerranInfantryArmorsLevel1";"EngineeringBay";126;0
"Unit";"Liberator";"Starport";133;3
"Unit";"Liberator";"Starport";133;3
"Unit";"SCV";"Command Center";140;1
"Unit";"SCV";"Command Center";140;1
"Unit";"SCV";"Command Center";140;1
"Building";"BarracksReactor";NA;137;0
"Building";"BarracksReactor";NA;137;0
"Unit";"Marine";"Barracks";144;1
"Unit";"Marine";"Barracks";144;1
"Unit";"Marine";"Barracks";144;1
"Unit";"Marine";"Barracks";144;1
"Unit";"Marine";"Barracks";144;1
"Unit";"Marine";"Barracks";144;1
"Unit";"SCV";"Command Center";153;1
"Unit";"Marine";"Barracks";150;1
"Unit";"Marine";"Barracks";150;1
