"type";"unit_name";"on_building";"total_supply";"supply"
"Building";"Refinery";NA;14;0
"Building";"Refinery";NA;16;0
"Building";"Barracks";NA;15;0
"Unit";"Reaper";"Barracks";19;1
"Building";"Factory";NA;19;0
"Unit";"Reaper";"Barracks";19;1
"Unit";"Hellion";"Factory";21;2
"Unit";"Cyclone";"Factory";26;3
"Building";"BarracksReactor";NA;26;0
"Building";"Starport";NA;26;0
"Unit";"Marine";"Barracks";31;1
"Unit";"Marine";"Barracks";31;1
"Unit";"Medivac";"Starport";35;2
"Unit";"Cyclone";"Factory";35;3
"Unit";"Marine";"Barracks";36;1
"Unit";"Marine";"Barracks";36;1
"Building";"CommandCenter";NA;22;0
"Building";"EngineeringBay";NA;36;0
"Building";"Bunker";NA;36;0
"Unit";"Marine";"Barracks";42;1
"Unit";"Marine";"Barracks";42;1
"Unit";"Cyclone";"Factory";44;3
"Unit";"Marine";"Barracks";44;1
"Building";"MissileTurret";NA;46;0
"Building";"MissileTurret";NA;46;0
"Unit";"Marine";"Barracks";50;1
"Unit";"Marine";"Barracks";50;1
"Building";"FactoryTechLab";NA;50;0
"Unit";"Marine";"Barracks";51;1
"Unit";"Marine";"Barracks";52;1
"Unit";"Marine";"Barracks";54;1
"Building";"FactoryTechLab";NA;61;0
"Unit";"Marine";"Barracks";62;1
