"type";"unit_name";"on_building";"total_supply";"supply"
"Building";"Refinery";NA;15;0
"Building";"Barracks";NA;15;0
"Building";"Refinery";NA;15;0
"Building";"Barracks";NA;15;0
"Unit";"Reaper";"Barracks";17;1
"Unit";"Reaper";"Barracks";18;1
"Unit";"Reaper";"Barracks";19;1
"Unit";"Reaper";"Barracks";20;1
"Unit";"Reaper";"Barracks";20;1
"Building";"Factory";NA;21;0
"Unit";"Reaper";"Barracks";22;1
"Unit";"Cyclone";"Factory";27;3
"Building";"Starport";NA;27;0
"Unit";"Cyclone";"Factory";33;3
"Unit";"Medivac";"Starport";33;2
"Unit";"Cyclone";"Factory";39;3
"Building";"BarracksTechLab";NA;41;0
"Building";"BarracksTechLab";NA;42;0
"Building";"CommandCenter";NA;33;0
"Unit";"Cyclone";"Factory";46;3
"Building";"FactoryTechLab";NA;52;0
"Building";"EngineeringBay";NA;53;0
"Building";"StarportReactor";NA;53;0
"Building";"MissileTurret";NA;55;0
"Building";"EngineeringBay";NA;55;0
"Building";"MissileTurret";NA;56;0
"Unit";"Marine";"Barracks";56;1
"Unit";"Marine";"Barracks";56;1
"Unit";"Marine";"Barracks";59;1
"Unit";"Marine";"Barracks";60;1
"Building";"Refinery";NA;62;0
"Unit";"Marine";"Barracks";64;1
"Unit";"Marine";"Barracks";65;1
"Unit";"Marine";"Barracks";69;1
"Unit";"Marine";"Barracks";70;1
"Building";"Refinery";NA;62;0
"Unit";"Marine";"Barracks";73;1
"Unit";"Marine";"Barracks";74;1
"Unit";"Medivac";"Starport";77;2
"Upgrade";"TerranInfantryWeaponsLevel1";"EngineeringBay";67;0
"Building";"CommandCenter";NA;68;0
"Upgrade";"Stimpack";"TechLab";66;0
"Upgrade";"TerranInfantryArmorsLevel1";"EngineeringBay";67;0
"Unit";"Marine";"Barracks";84;1
"Unit";"Marine";"Barracks";84;1
"Unit";"Medivac";"Starport";84;2
"Building";"Barracks";NA;81;0
"Unit";"Marine";"Barracks";86;1
"Unit";"Marine";"Barracks";86;1
"Building";"SensorTower";NA;89;0
"Unit";"Marine";"Barracks";92;1
"Unit";"Marine";"Barracks";92;1
"Building";"Armory";NA;88;0
"Unit";"Marine";"Barracks";98;1
"Unit";"Marine";"Barracks";98;1
"Unit";"Marine";"Barracks";102;1
"Unit";"Marine";"Barracks";102;1
"Building";"BarracksReactor";NA;102;0
"Unit";"Marine";"Barracks";107;1
"Unit";"Marine";"Barracks";107;1
"Building";"Refinery";NA;109;0
"Building";"Refinery";NA;109;0
"Building";"Barracks";NA;102;0
"Unit";"Marine";"Barracks";109;1
"Unit";"Marine";"Barracks";109;1
"Unit";"Marine";"Barracks";109;1
"Unit";"Marine";"Barracks";109;1
"Building";"Barracks";NA;106;0
"Unit";"Medivac";"Starport";109;2
"Unit";"Marine";"Barracks";111;1
"Building";"Barracks";NA;107;0
"Unit";"Marine";"Barracks";111;1
"Unit";"Marine";"Barracks";113;1
"Unit";"Marine";"Barracks";114;1
"Unit";"Marine";"Barracks";114;1
"Unit";"Marine";"Barracks";116;1
"Unit";"Marine";"Barracks";118;1
"Unit";"Marine";"Barracks";119;1
"Unit";"Marine";"Barracks";119;1
"Unit";"Marine";"Barracks";120;1
"Unit";"Marine";"Barracks";121;1
"Unit";"Marine";"Barracks";121;1
"Unit";"Marine";"Barracks";123;1
"Unit";"Marine";"Barracks";124;1
"Unit";"Marine";"Barracks";125;1
"Unit";"Marine";"Barracks";126;1
"Unit";"Marine";"Barracks";127;1
"Unit";"Marine";"Barracks";128;1
"Unit";"Marine";"Barracks";130;1
"Unit";"Marauder";"Barracks";128;2
"Unit";"Marine";"Barracks";131;1
"Unit";"Marine";"Barracks";132;1
"Unit";"Marine";"Barracks";133;1
"Unit";"Marine";"Barracks";134;1
"Unit";"Marine";"Barracks";137;1
"Unit";"Marine";"Barracks";139;1
"Unit";"Marine";"Barracks";140;1
"Unit";"Marine";"Barracks";142;1
"Unit";"Marine";"Barracks";143;1
"Unit";"Marine";"Barracks";146;1
"Unit";"Marine";"Barracks";147;1
"Unit";"Marine";"Barracks";148;1
"Upgrade";"TerranVehicleWeaponsLevel1";"Armory";118;0
"Unit";"Marine";"Barracks";149;1
"Upgrade";"TerranInfantryWeaponsLevel2";"EngineeringBay";111;0
"Upgrade";"TerranInfantryArmorsLevel2";"EngineeringBay";111;0
"Unit";"Marine";"Barracks";150;1
"Unit";"Marine";"Barracks";151;1
"Unit";"Marine";"Barracks";152;1
"Unit";"Marine";"Barracks";153;1
"Unit";"Marine";"Barracks";154;1
"Unit";"Marine";"Barracks";155;1
"Unit";"Marine";"Barracks";156;1
"Unit";"Marine";"Barracks";157;1
"Unit";"Marine";"Barracks";158;1
"Unit";"Marine";"Barracks";159;1
"Unit";"Marine";"Barracks";160;1
"Unit";"Marine";"Barracks";161;1
"Unit";"Medivac";"Starport";158;2
"Unit";"Marine";"Barracks";162;1
"Unit";"Medivac";"Starport";158;2
"Unit";"Marine";"Barracks";163;1
"Unit";"Marine";"Barracks";164;1
"Unit";"Marine";"Barracks";168;1
"Unit";"Marine";"Barracks";169;1
"Unit";"Marine";"Barracks";170;1
"Unit";"Marine";"Barracks";171;1
"Unit";"Marine";"Barracks";175;1
"Unit";"Marine";"Barracks";179;1
"Unit";"Marine";"Barracks";181;1
"Unit";"Marine";"Barracks";182;1
"Unit";"Marine";"Barracks";185;1
"Unit";"Marine";"Barracks";185;1
"Unit";"Marine";"Barracks";186;1
"Unit";"Marine";"Barracks";187;1
"Unit";"Marine";"Barracks";188;1
"Unit";"Marine";"Barracks";189;1
"Unit";"Marine";"Barracks";190;1
"Unit";"Marine";"Barracks";191;1
"Unit";"Marine";"Barracks";192;1
"Unit";"Marine";"Barracks";193;1
"Unit";"Marine";"Barracks";197;1
"Unit";"Marine";"Barracks";198;1
"Unit";"Marine";"Barracks";198;1
"Unit";"Marine";"Barracks";198;1
"Unit";"Marine";"Barracks";199;1
"Unit";"Marine";"Barracks";199;1
"Unit";"Marine";"Barracks";201;1
"Unit";"Marine";"Barracks";201;1
"Unit";"Marine";"Barracks";202;1
"Unit";"Marine";"Barracks";204;1
"Unit";"Marine";"Barracks";210;1
"Unit";"Marine";"Barracks";211;1
"Unit";"Marine";"Barracks";212;1
"Unit";"Marine";"Barracks";212;1
"Unit";"Marine";"Barracks";214;1
"Unit";"Marine";"Barracks";217;1
"Unit";"Marine";"Barracks";217;1
"Unit";"Marine";"Barracks";217;1
"Unit";"Marine";"Barracks";220;1
"Unit";"Marine";"Barracks";225;1
"Unit";"Marine";"Barracks";225;1
"Unit";"Marauder";"Barracks";225;2
"Unit";"Marine";"Barracks";227;1
"Unit";"Marine";"Barracks";229;1
"Unit";"Marine";"Barracks";229;1
"Unit";"Marine";"Barracks";230;1
"Unit";"Marine";"Barracks";231;1
"Unit";"Marine";"Barracks";232;1
"Unit";"Marine";"Barracks";239;1
"Unit";"Marine";"Barracks";239;1
"Unit";"Marine";"Barracks";239;1
"Unit";"Marine";"Barracks";239;1
"Unit";"Marine";"Barracks";242;1
"Unit";"Marine";"Barracks";242;1
"Unit";"Marine";"Barracks";242;1
"Unit";"Medivac";"Starport";239;2
"Unit";"Marine";"Barracks";242;1
"Unit";"Marauder";"Barracks";245;2
"Unit";"Marine";"Barracks";248;1
"Unit";"Marine";"Barracks";254;1
"Unit";"Marine";"Barracks";255;1
