"Type";"UnitName";"OnBuilding";"TotalSupply";"Supply"
"Unit";"SCV";"Command Center";12;1
"Unit";"SCV";"Command Center";12;1
"Unit";"SCV";"Command Center";13;1
"Building";"SupplyDepot";NA;13;0
"Building";"Refinery";NA;14;0
"Unit";"SCV";"Command Center";15;1
"Unit";"SCV";"Command Center";15;1
"Unit";"SCV";"Command Center";16;1
"Building";"Refinery";NA;16;0
"Unit";"SCV";"Command Center";18;1
"Building";"Barracks";NA;15;0
"Unit";"Reaper";"Barracks";19;1
"Building";"Factory";NA;19;0
"Unit";"SCV";"Command Center";19;1
"Building";"SupplyDepot";NA;19;0
"Unit";"SCV";"Command Center";21;1
"Unit";"Reaper";"Barracks";19;1
"Unit";"SCV";"Command Center";21;1
"Unit";"Hellion";"Factory";21;2
"Unit";"SCV";"Command Center";26;1
"Unit";"Cyclone";"Factory";26;3
"Building";"Starport";NA;26;0
"Building";"BarracksReactor";NA;26;0
"Unit";"SCV";"Command Center";27;1
"Unit";"SCV";"Command Center";30;1
"Building";"CommandCenter";NA;22;0
"Unit";"SCV";"Command Center";32;1
"Building";"SupplyDepot";NA;31;0
"Unit";"Cyclone";"Factory";31;3
"Unit";"Marine";"Barracks";32;1
"Unit";"Marine";"Barracks";32;1
"Unit";"SCV";"Command Center";32;1
"Unit";"SCV";"Command Center";38;1
"Building";"FactoryTechLab";NA;38;0
"Unit";"Marine";"Barracks";38;1
"Unit";"Marine";"Barracks";38;1
"Unit";"SCV";"Command Center";39;1
"Unit";"Medivac";"Starport";38;2
"Unit";"SCV";"Command Center";42;1
"Unit";"SCV";"Command Center";45;1
"Unit";"SCV";"Command Center";46;1
"Unit";"Marine";"Barracks";45;1
"Unit";"SCV";"Command Center";46;1
"Unit";"SCV";"Command Center";47;1
"Building";"Barracks";NA;40;0
"Building";"Barracks";NA;42;0
"Unit";"SCV";"Command Center";49;1
"Building";"StarportReactor";NA;46;0
"Unit";"SCV";"Command Center";50;1
"Unit";"Marine";"Barracks";50;1
"Building";"FactoryTechLab";NA;50;0
"Unit";"SCV";"Command Center";51;1
"Building";"SupplyDepot";NA;51;0
"Unit";"SCV";"Command Center";52;1
"Building";"EngineeringBay";NA;50;0
"Unit";"SCV";"Command Center";54;1
"Unit";"Marine";"Barracks";55;1
"Unit";"Marine";"Barracks";55;1
"Unit";"SCV";"Command Center";55;1
"Building";"Refinery";NA;55;0
"Unit";"Marine";"Barracks";55;1
"Unit";"Marine";"Barracks";55;1
"Unit";"Marine";"Barracks";55;1
"Unit";"SCV";"Command Center";56;1
"Unit";"SCV";"Command Center";59;1
"Unit";"SCV";"Command Center";63;1
"Building";"StarportReactor";NA;55;0
"Building";"SupplyDepot";NA;57;0
"Unit";"SCV";"Command Center";64;1
"Unit";"SCV";"Command Center";65;1
"Unit";"Marine";"Barracks";66;1
"Unit";"Marine";"Barracks";66;1
"Unit";"Marine";"Barracks";66;1
"Unit";"Marine";"Barracks";66;1
"Unit";"SCV";"Command Center";66;1
"Unit";"Marine";"Barracks";66;1
"Building";"SupplyDepot";NA;66;0
"Building";"SupplyDepot";NA;67;0
"Unit";"Medivac";"Starport";66;2
"Unit";"Medivac";"Starport";66;2
"Unit";"SCV";"Command Center";74;1
"Upgrade";"Stimpack";"TechLab";52;0
"Unit";"Marine";"Barracks";74;1
"Unit";"Marine";"Barracks";74;1
"Unit";"Marine";"Barracks";74;1
"Unit";"Marine";"Barracks";74;1
"Unit";"Marine";"Barracks";74;1
"Building";"SupplyDepot";NA;74;0
"Unit";"SCV";"Command Center";79;1
"Building";"SupplyDepot";NA;78;0
"Building";"SupplyDepot";NA;78;0
"Unit";"Marine";"Barracks";84;1
"Unit";"Marine";"Barracks";84;1
"Unit";"Marine";"Barracks";84;1
"Unit";"SCV";"Command Center";85;1
"Building";"MissileTurret";NA;85;0
"Building";"SupplyDepot";NA;85;0
"Building";"MissileTurret";NA;85;0
"Unit";"Marine";"Barracks";85;1
"Unit";"Marine";"Barracks";85;1
"Unit";"SCV";"Command Center";89;1
"Unit";"SCV";"Command Center";89;1
"Building";"Refinery";NA;89;0
"Unit";"Marine";"Barracks";89;1
"Unit";"Marine";"Barracks";89;1
"Unit";"Marine";"Barracks";89;1
"Upgrade";"TerranInfantryWeaponsLevel1";"EngineeringBay";67;0
"Building";"CommandCenter";NA;74;0
"Unit";"Marine";"Barracks";89;1
"Unit";"Marine";"Barracks";93;1
"Building";"SupplyDepot";NA;89;0
"Building";"SupplyDepot";NA;90;0
"Unit";"Medivac";"Starport";89;2
"Unit";"Medivac";"Starport";89;2
"Unit";"Marine";"Barracks";93;1
"Unit";"Marine";"Barracks";98;1
"Unit";"Marine";"Barracks";98;1
"Unit";"Marauder";"Barracks";98;2
"Unit";"Marine";"Barracks";102;1
"Unit";"Marine";"Barracks";102;1
"Unit";"Marine";"Barracks";103;1
"Unit";"Marine";"Barracks";104;1
"Unit";"Marine";"Barracks";105;1
"Unit";"Marine";"Barracks";109;1
"Unit";"Marine";"Barracks";109;1
"Unit";"Medivac";"Starport";103;2
"Unit";"Medivac";"Starport";103;2
"Unit";"SCV";"Command Center";111;1
"Unit";"SCV";"Command Center";112;1
"Unit";"Marine";"Barracks";109;1
"Unit";"Marine";"Barracks";110;1
"Unit";"Marine";"Barracks";111;1
"Unit";"SCV";"Command Center";119;1
"Unit";"SCV";"Command Center";119;1
"Building";"EngineeringBay";NA;112;0
"Unit";"Marine";"Barracks";118;1
"Unit";"Marine";"Barracks";118;1
"Unit";"SCV";"Command Center";123;1
"Unit";"Marine";"Barracks";122;1
"Unit";"Marine";"Barracks";122;1
"Unit";"SCV";"Command Center";123;1
"Unit";"SCV";"Command Center";124;1
"Building";"Armory";NA;111;0
"Unit";"SCV";"Command Center";127;1
"Unit";"SCV";"Command Center";130;1
"Building";"Barracks";NA;112;0
"Unit";"SCV";"Command Center";131;1
"Building";"Barracks";NA;112;0
"Unit";"Marine";"Barracks";127;1
"Unit";"Marine";"Barracks";127;1
"Unit";"Marine";"Barracks";132;1
"Unit";"Marine";"Barracks";132;1
"Unit";"Marine";"Barracks";132;1
"Unit";"SCV";"Command Center";132;1
"Unit";"SCV";"Command Center";133;1
"Building";"Refinery";NA;132;0
"Building";"Refinery";NA;132;0
"Unit";"Medivac";"Starport";132;2
"Unit";"Medivac";"Starport";132;2
"Unit";"Marine";"Barracks";140;1
"Unit";"Marine";"Barracks";140;1
"Unit";"Marine";"Barracks";142;1
"Unit";"Marine";"Barracks";142;1
"Building";"BarracksReactor";NA;137;0
"Unit";"Marine";"Barracks";148;1
"Unit";"Marine";"Barracks";148;1
"Unit";"Marine";"Barracks";148;1
"Unit";"Marine";"Barracks";148;1
"Unit";"Marine";"Barracks";149;1
"Building";"BarracksReactor";NA;142;0
"Upgrade";"TerranInfantryArmorsLevel1";"EngineeringBay";125;0
"Unit";"Marine";"Barracks";150;1
"Unit";"Marine";"Barracks";151;1
"Unit";"Marine";"Barracks";152;1
"Unit";"Marine";"Barracks";152;1
"Unit";"Marine";"Barracks";153;1
"Unit";"Marine";"Barracks";153;1
"Unit";"Marine";"Barracks";154;1
"Unit";"Marine";"Barracks";155;1
"Unit";"Marine";"Barracks";155;1
"Unit";"Medivac";"Starport";155;2
"Unit";"Marine";"Barracks";164;1
"Unit";"Marine";"Barracks";164;1
"Unit";"Marine";"Barracks";164;1
"Unit";"Marine";"Barracks";164;1
"Unit";"Marine";"Barracks";164;1
"Unit";"Marine";"Barracks";164;1
"Unit";"Marine";"Barracks";164;1
"Unit";"Marine";"Barracks";164;1
"Unit";"Medivac";"Starport";164;2
"Unit";"Marine";"Barracks";166;1
"Unit";"Marine";"Barracks";167;1
"Unit";"Marine";"Barracks";167;1
