"Type";"UnitName";"OnBuilding";"TotalSupply";"Supply"
"Unit";"SCV";"Command Center";12;1
"Unit";"SCV";"Command Center";12;1
"Unit";"SCV";"Command Center";13;1
"Building";"SupplyDepot";NA;13;0
"Unit";"SCV";"Command Center";15;1
"Unit";"SCV";"Command Center";15;1
"Building";"Refinery";NA;15;0
"Unit";"SCV";"Command Center";16;1
"Unit";"SCV";"Command Center";17;1
"Building";"Barracks";NA;15;0
"Unit";"SCV";"Command Center";19;1
"Building";"BarracksReactor";NA;19;0
"Building";"SupplyDepot";NA;19;0
"Building";"Bunker";NA;19;0
"Unit";"SCV";"Command Center";20;1
"Building";"Refinery";NA;19;0
"Unit";"Marine";"Barracks";20;1
"Unit";"Marine";"Barracks";20;1
"Unit";"SCV";"Command Center";20;1
"Unit";"SCV";"Command Center";24;1
"Unit";"Marine";"Barracks";24;1
"Unit";"Marine";"Barracks";24;1
"Building";"Bunker";NA;20;0
"Unit";"SCV";"Command Center";24;1
"Unit";"Marine";"Barracks";25;1
"Unit";"Marine";"Barracks";26;1
"Unit";"SCV";"Command Center";27;1
"Unit";"SCV";"Command Center";30;1
"Unit";"Marine";"Barracks";28;1
"Unit";"Marine";"Barracks";29;1
"Building";"EngineeringBay";NA;28;0
"Unit";"SCV";"Command Center";31;1
"Building";"SupplyDepot";NA;31;0
"Building";"Factory";NA;28;0
"Unit";"SCV";"Command Center";35;1
"Building";"SupplyDepot";NA;35;0
"Unit";"SCV";"Command Center";36;1
"Unit";"Hellion";"Factory";36;2
"Building";"BarracksReactor";NA;35;0
"Building";"SupplyDepot";NA;36;0
"Unit";"SCV";"Command Center";36;1
"Building";"Starport";NA;36;0
"Unit";"SCV";"Command Center";39;1
"Unit";"Marine";"Barracks";39;1
"Unit";"Marine";"Barracks";39;1
"Building";"FactoryTechLab";NA;40;0
"Unit";"SCV";"Command Center";40;1
"Building";"SupplyDepot";NA;40;0
"Unit";"Marine";"Barracks";43;1
"Unit";"Marine";"Barracks";43;1
"Unit";"SCV";"Command Center";43;1
"Building";"SupplyDepot";NA;44;0
"Building";"FactoryTechLab";NA;46;0
"Unit";"Marine";"Barracks";47;1
"Unit";"Marine";"Barracks";47;1
"Unit";"SCV";"Command Center";47;1
"Building";"CommandCenter";NA;37;0
"Unit";"SCV";"Command Center";50;1
"Unit";"Raven";"Starport";44;2
"Unit";"SCV";"Command Center";51;1
"Building";"Barracks";NA;47;0
"Unit";"SCV";"Command Center";54;1
"Building";"BarracksTechLab";NA;53;0
"Unit";"SCV";"Command Center";55;1
"Unit";"SCV";"Command Center";55;1
"Unit";"SCV";"Command Center";55;1
"Unit";"SCV";"Command Center";56;1
"Unit";"SCV";"Command Center";58;1
"Unit";"Marine";"Barracks";58;1
"Unit";"SCV";"Command Center";58;1
"Unit";"Marine";"Barracks";58;1
"Unit";"SCV";"Command Center";59;1
"Unit";"SCV";"Command Center";62;1
"Unit";"SCV";"Command Center";63;1
"Unit";"SCV";"Command Center";65;1
"Unit";"SCV";"Command Center";66;1
"Unit";"Marine";"Barracks";67;1
"Unit";"Marine";"Barracks";67;1
"Unit";"SCV";"Command Center";67;1
"Unit";"SCV";"Command Center";70;1
"Unit";"Medivac";"Starport";67;2
"Upgrade";"Stimpack";"TechLab";58;0
"Unit";"Medivac";"Starport";67;2
"Unit";"Marine";"Barracks";68;1
"Unit";"Marine";"Barracks";69;1
"Unit";"SCV";"Command Center";71;1
"Unit";"Marine";"Barracks";76;1
"Building";"Barracks";NA;67;0
"Unit";"SCV";"Command Center";78;1
"Unit";"Marine";"Barracks";77;1
"Unit";"SCV";"Command Center";78;1
"Unit";"SCV";"Command Center";80;1
"Building";"Barracks";NA;71;0
"Unit";"Marine";"Barracks";79;1
"Building";"Barracks";NA;71;0
"Unit";"Marine";"Barracks";81;1
"Unit";"Marine";"Barracks";82;1
"Unit";"Marine";"Barracks";82;1
"Building";"SupplyDepot";NA;83;0
"Building";"SupplyDepot";NA;84;0
"Unit";"Marine";"Barracks";84;1
"Building";"Refinery";NA;84;0
"Building";"Refinery";NA;84;0
"Unit";"SCV";"Command Center";88;1
"Unit";"Marine";"Barracks";88;1
"Unit";"Marine";"Barracks";88;1
"Building";"BarracksReactor";NA;88;0
"Building";"BarracksReactor";NA;88;0
"Unit";"Marine";"Barracks";89;1
"Unit";"Marine";"Barracks";89;1
"Unit";"Medivac";"Starport";88;2
"Unit";"Marine";"Barracks";92;1
"Unit";"Marine";"Barracks";92;1
"Building";"SupplyDepot";NA;92;0
"Building";"SupplyDepot";NA;92;0
"Building";"SupplyDepot";NA;92;0
"Unit";"Marine";"Barracks";92;1
"Unit";"Marine";"Barracks";93;1
"Unit";"Marine";"Barracks";96;1
"Unit";"Marine";"Barracks";96;1
"Unit";"Marine";"Barracks";98;1
"Unit";"Marine";"Barracks";98;1
"Unit";"Marine";"Barracks";98;1
"Unit";"Marine";"Barracks";98;1
"Unit";"Marine";"Barracks";98;1
"Unit";"Marine";"Barracks";99;1
"Unit";"Marine";"Barracks";100;1
"Building";"Factory";NA;92;0
"Building";"CommandCenter";NA;88;0
"Building";"SupplyDepot";NA;100;0
"Building";"SupplyDepot";NA;102;0
"Building";"SupplyDepot";NA;102;0
"Upgrade";"TerranInfantryWeaponsLevel1";"EngineeringBay";89;0
"Unit";"Marine";"Barracks";109;1
"Unit";"Marine";"Barracks";109;1
"Unit";"Marine";"Barracks";109;1
"Unit";"Marine";"Barracks";109;1
"Unit";"Marine";"Barracks";109;1
"Unit";"Marine";"Barracks";109;1
"Unit";"Marine";"Barracks";109;1
"Unit";"Medivac";"Starport";109;2
"Unit";"Marine";"Barracks";109;1
"Unit";"Marine";"Barracks";110;1
"Unit";"Marine";"Barracks";111;1
"Unit";"Marine";"Barracks";111;1
"Unit";"Marine";"Barracks";113;1
"Unit";"Marine";"Barracks";116;1
"Unit";"Marine";"Barracks";116;1
"Unit";"Marine";"Barracks";118;1
"Unit";"Marine";"Barracks";119;1
"Unit";"Marine";"Barracks";120;1
"Unit";"Marine";"Barracks";123;1
"Unit";"Marine";"Barracks";123;1
"Unit";"Marine";"Barracks";123;1
"Unit";"Marine";"Barracks";124;1
"Unit";"Marine";"Barracks";125;1
"Unit";"Marine";"Barracks";126;1
"Unit";"Marine";"Barracks";127;1
"Building";"BarracksReactor";NA;123;0
"Unit";"Marine";"Barracks";128;1
"Unit";"Marine";"Barracks";129;1
"Unit";"Marine";"Barracks";130;1
"Unit";"Marine";"Barracks";131;1
"Unit";"Marine";"Barracks";132;1
"Unit";"Marine";"Barracks";133;1
"Unit";"Marine";"Barracks";134;1
"Unit";"Marine";"Barracks";135;1
"Unit";"Marine";"Barracks";136;1
"Unit";"Marine";"Barracks";137;1
"Unit";"Marine";"Barracks";138;1
"Unit";"SCV";"Command Center";139;1
"Unit";"Medivac";"Starport";135;2
"Unit";"Marine";"Barracks";139;1
"Unit";"Marine";"Barracks";140;1
"Unit";"Marine";"Barracks";142;1
"Unit";"Marine";"Barracks";142;1
"Unit";"Marine";"Barracks";142;1
"Unit";"Marine";"Barracks";142;1
"Unit";"Marine";"Barracks";143;1
"Unit";"Marine";"Barracks";147;1
"Unit";"Marine";"Barracks";147;1
"Unit";"Marine";"Barracks";149;1
"Unit";"Marine";"Barracks";154;1
"Unit";"Marine";"Barracks";154;1
"Unit";"Marine";"Barracks";154;1
"Unit";"Marine";"Barracks";154;1
"Unit";"SCV";"Command Center";159;1
"Unit";"SCV";"Command Center";159;1
"Unit";"SCV";"Command Center";159;1
"Unit";"Marine";"Barracks";158;1
"Unit";"Marine";"Barracks";158;1
"Unit";"Marine";"Barracks";162;1
"Unit";"Marine";"Barracks";162;1
"Unit";"SCV";"Command Center";163;1
"Unit";"SCV";"Command Center";164;1
"Unit";"Marine";"Barracks";172;1
"Unit";"Marine";"Barracks";172;1
"Unit";"Marine";"Barracks";172;1
"Unit";"Marine";"Barracks";172;1
"Unit";"Marine";"Barracks";172;1
"Building";"EngineeringBay";NA;177;0
"Unit";"Marine";"Barracks";177;1
"Unit";"Marine";"Barracks";177;1
"Unit";"Marine";"Barracks";177;1
"Unit";"Marine";"Barracks";177;1
"Building";"SupplyDepot";NA;177;0
"Building";"SupplyDepot";NA;177;0
"Building";"Armory";NA;177;0
"Unit";"Marine";"Barracks";177;1
"Unit";"Marine";"Barracks";177;1
"Unit";"Marine";"Barracks";177;1
"Unit";"Marine";"Barracks";177;1
"Upgrade";"TerranInfantryArmorsLevel1";"EngineeringBay";172;0
"Unit";"Marine";"Barracks";185;1
"Unit";"Marine";"Barracks";185;1
"Unit";"Marine";"Barracks";185;1
"Unit";"Marine";"Barracks";185;1
"Unit";"Marine";"Barracks";185;1
"Unit";"Marine";"Barracks";185;1
"Unit";"Marine";"Barracks";185;1
"Unit";"Marine";"Barracks";185;1
"Unit";"Marine";"Barracks";185;1
"Unit";"Marine";"Barracks";185;1
"Unit";"Medivac";"Starport";185;2
"Unit";"Marine";"Barracks";186;1
"Unit";"Marine";"Barracks";187;1
"Unit";"Marine";"Barracks";187;1
"Unit";"Medivac";"Starport";185;2
"Unit";"Marine";"Barracks";189;1
"Unit";"Marine";"Barracks";189;1
"Unit";"Marine";"Barracks";191;1
"Unit";"Marine";"Barracks";192;1
"Unit";"Marine";"Barracks";192;1
