"type";"unit_name";"on_building";"total_supply";"supply"
"Building";"Refinery";NA;14;0
"Building";"Refinery";NA;16;0
"Building";"Barracks";NA;15;0
"Unit";"Reaper";"Barracks";19;1
"Building";"Factory";NA;19;0
"Unit";"Reaper";"Barracks";20;1
"Unit";"Hellion";"Factory";21;2
"Unit";"Cyclone";"Factory";28;3
"Building";"BarracksReactor";NA;27;0
"Building";"Starport";NA;27;0
