"Type";"UnitName";"OnBuilding";"TotalSupply";"Supply"
"Unit";"SCV";"Command Center";12;1
"Unit";"SCV";"Command Center";12;1
"Unit";"SCV";"Command Center";13;1
"Building";"SupplyDepot";NA;13;0
"Unit";"SCV";"Command Center";15;1
"Unit";"SCV";"Command Center";15;1
"Building";"Refinery";NA;15;0
"Unit";"SCV";"Command Center";16;1
"Building";"Barracks";NA;15;0
"Unit";"SCV";"Command Center";17;1
"Unit";"Reaper";"Barracks";19;1
"Unit";"SCV";"Command Center";19;1
"Unit";"SCV";"Command Center";21;1
"Building";"SupplyDepot";NA;20;0
"Unit";"SCV";"Command Center";21;1
"Building";"Refinery";NA;21;0
"Building";"BarracksReactor";NA;20;0
"Unit";"SCV";"Command Center";22;1
"Unit";"Marine";"Barracks";23;1
"Unit";"Marine";"Barracks";23;1
"Unit";"SCV";"Command Center";24;1
"Building";"CommandCenter";NA;19;0
"Unit";"SCV";"Command Center";26;1
"Unit";"Marine";"Barracks";24;1
"Unit";"Marine";"Barracks";25;1
"Building";"Bunker";NA;24;0
"Building";"Factory";NA;23;0
"Unit";"SCV";"Command Center";27;1
"Unit";"Marine";"Barracks";28;1
"Unit";"Marine";"Barracks";29;1
"Unit";"SCV";"Command Center";30;1
"Unit";"SCV";"Command Center";31;1
"Unit";"SCV";"Command Center";33;1
"Unit";"Marine";"Barracks";31;1
"Unit";"Marine";"Barracks";32;1
"Unit";"SCV";"Command Center";34;1
"Unit";"Cyclone";"Factory";33;3
"Building";"Starport";NA;30;0
"Unit";"SCV";"Command Center";35;1
"Building";"SupplyDepot";NA;35;0
"Unit";"SCV";"Command Center";39;1
"Unit";"Marine";"Barracks";36;1
"Unit";"Marine";"Barracks";37;1
"Unit";"SCV";"Command Center";44;1
"Unit";"SCV";"Command Center";44;1
"Unit";"Marine";"Barracks";46;1
"Unit";"Marine";"Barracks";46;1
"Building";"FactoryTechLab";NA;46;0
"Unit";"SCV";"Command Center";48;1
"Unit";"SCV";"Command Center";48;1
"Unit";"Marine";"Barracks";50;1
"Unit";"Marine";"Barracks";50;1
"Unit";"SCV";"Command Center";52;1
"Building";"SupplyDepot";NA;52;0
"Building";"EngineeringBay";NA;52;0
"Building";"EngineeringBay";NA;52;0
"Unit";"SCV";"Command Center";55;1
"Unit";"SCV";"Command Center";55;1
"Unit";"Marine";"Barracks";55;1
"Unit";"Marine";"Barracks";55;1
"Building";"SupplyDepot";NA;55;0
"Unit";"SCV";"Command Center";55;1
"Building";"SupplyDepot";NA;55;0
"Unit";"SCV";"Command Center";59;1
"Unit";"SCV";"Command Center";59;1
"Building";"CommandCenter";NA;48;0
"Building";"Refinery";NA;57;0
"Unit";"Marine";"Barracks";59;1
"Unit";"Marine";"Barracks";59;1
"Building";"StarportReactor";NA;55;0
"Building";"Refinery";NA;59;0
"Unit";"SCV";"Command Center";60;1
"Building";"SupplyDepot";NA;60;0
"Unit";"SCV";"Command Center";61;1
"Unit";"SCV";"Command Center";64;1
"Unit";"Marine";"Barracks";64;1
"Unit";"SCV";"Command Center";65;1
"Unit";"Marine";"Barracks";64;1
"Unit";"Marine";"Barracks";67;1
"Unit";"Marine";"Barracks";69;1
"Unit";"SCV";"Command Center";70;1
"Unit";"SCV";"Command Center";70;1
"Unit";"Marine";"Barracks";70;1
"Unit";"Marine";"Barracks";71;1
"Building";"Barracks";NA;66;0
"Unit";"SCV";"Command Center";72;1
"Unit";"SCV";"Command Center";73;1
"Building";"Barracks";NA;66;0
"Unit";"SCV";"Command Center";78;1
"Unit";"SCV";"Command Center";78;1
"Unit";"Marine";"Barracks";76;1
"Unit";"Marine";"Barracks";76;1
"Unit";"Medivac";"Starport";74;2
"Unit";"Medivac";"Starport";74;2
"Building";"Barracks";NA;72;0
"Upgrade";"TerranInfantryArmorsLevel1";"EngineeringBay";65;0
"Upgrade";"TerranInfantryWeaponsLevel1";"EngineeringBay";65;0
"Building";"Barracks";NA;72;0
"Building";"BarracksTechLab";NA;78;0
"Building";"BarracksTechLab";NA;78;0
"Unit";"SCV";"Command Center";86;1
"Unit";"SCV";"Command Center";86;1
"Unit";"Marine";"Barracks";80;1
"Unit";"SCV";"Command Center";86;1
"Building";"Armory";NA;74;0
"Unit";"SCV";"Command Center";86;1
"Unit";"SCV";"Command Center";89;1
"Unit";"SCV";"Command Center";90;1
"Building";"SupplyDepot";NA;89;0
"Unit";"SCV";"Command Center";90;1
"Unit";"Medivac";"Starport";89;2
"Unit";"Medivac";"Starport";89;2
"Building";"BarracksReactor";NA;86;0
"Unit";"SCV";"Command Center";93;1
"Unit";"SCV";"Command Center";93;1
"Unit";"SCV";"Command Center";94;1
"Building";"Barracks";NA;86;0
"Building";"Barracks";NA;86;0
"Unit";"Marine";"Barracks";94;1
"Unit";"Marine";"Barracks";94;1
"Unit";"SCV";"Command Center";98;1
"Building";"Refinery";NA;94;0
"Building";"Refinery";NA;94;0
"Unit";"SCV";"Command Center";99;1
"Unit";"SCV";"Command Center";100;1
"Unit";"Marine";"Barracks";103;1
"Building";"SupplyDepot";NA;105;0
"Building";"SupplyDepot";NA;105;0
"Building";"BarracksReactor";NA;101;0
"Building";"BarracksReactor";NA;101;0
"Building";"SupplyDepot";NA;106;0
"Building";"SupplyDepot";NA;106;0
"Building";"BarracksReactor";NA;101;0
"Unit";"SCV";"Command Center";107;1
"Unit";"SCV";"Command Center";107;1
"Unit";"SCV";"Command Center";107;1
"Unit";"Marine";"Barracks";107;1
"Unit";"Marine";"Barracks";107;1
"Unit";"Marine";"Barracks";107;1
"Unit";"Marine";"Barracks";107;1
"Unit";"Marine";"Barracks";107;1
"Unit";"Marine";"Barracks";107;1
"Unit";"Marine";"Barracks";107;1
"Unit";"Marine";"Barracks";107;1
"Building";"SupplyDepot";NA;107;0
"Unit";"Marine";"Barracks";109;1
"Building";"SupplyDepot";NA;107;0
"Unit";"Medivac";"Starport";107;2
"Unit";"Marine";"Barracks";110;1
"Unit";"Marine";"Barracks";110;1
"Unit";"Marine";"Barracks";110;1
"Unit";"Marine";"Barracks";110;1
"Unit";"Marine";"Barracks";112;1
"Building";"Factory";NA;107;0
"Unit";"SCV";"Command Center";116;1
"Unit";"SCV";"Command Center";116;1
"Unit";"SCV";"Command Center";118;1
"Unit";"Marine";"Barracks";116;1
"Unit";"Marine";"Barracks";116;1
"Unit";"Marine";"Barracks";119;1
"Unit";"Marine";"Barracks";119;1
"Unit";"Marine";"Barracks";119;1
"Upgrade";"Stimpack";"TechLab";101;0
"Building";"SupplyDepot";NA;126;0
"Building";"SupplyDepot";NA;126;0
"Building";"SupplyDepot";NA;128;0
"Unit";"Medivac";"Starport";121;2
"Unit";"Medivac";"Starport";121;2
"Building";"FactoryTechLab";NA;134;0
"Unit";"SCV";"Command Center";134;1
"Unit";"SCV";"Command Center";134;1
"Unit";"Marine";"Barracks";134;1
"Unit";"Marine";"Barracks";134;1
"Unit";"Marine";"Barracks";134;1
"Unit";"Marine";"Barracks";134;1
"Unit";"Marine";"Barracks";134;1
"Unit";"Marine";"Barracks";134;1
"Unit";"Marine";"Barracks";134;1
"Unit";"Marine";"Barracks";134;1
"Unit";"Marine";"Barracks";134;1
"Building";"CommandCenter";NA;107;0
"Unit";"Marine";"Barracks";134;1
"Unit";"Marine";"Barracks";134;1
"Unit";"Marine";"Barracks";134;1
"Upgrade";"TerranInfantryWeaponsLevel2";"EngineeringBay";106;0
"Unit";"Marine";"Barracks";149;1
"Unit";"Marine";"Barracks";149;1
"Unit";"Marine";"Barracks";149;1
"Upgrade";"TerranInfantryArmorsLevel2";"EngineeringBay";107;0
"Unit";"Marine";"Barracks";152;1
"Unit";"Marine";"Barracks";152;1
"Unit";"Marine";"Barracks";152;1
"Unit";"Marine";"Barracks";152;1
"Unit";"Marine";"Barracks";152;1
"Unit";"Marine";"Barracks";152;1
"Unit";"Marine";"Barracks";152;1
"Unit";"Marine";"Barracks";152;1
"Unit";"Marine";"Barracks";152;1
"Unit";"Marine";"Barracks";152;1
"Unit";"Marine";"Barracks";155;1
"Unit";"Marine";"Barracks";155;1
"Unit";"Marine";"Barracks";155;1
"Unit";"Marine";"Barracks";165;1
"Unit";"Marine";"Barracks";165;1
"Unit";"Marine";"Barracks";165;1
"Unit";"Marine";"Barracks";165;1
"Unit";"Marine";"Barracks";165;1
"Unit";"Marine";"Barracks";165;1
"Unit";"Marine";"Barracks";165;1
"Unit";"Marine";"Barracks";167;1
"Unit";"Marine";"Barracks";167;1
"Unit";"Marine";"Barracks";167;1
"Unit";"Marine";"Barracks";167;1
"Upgrade";"TerranVehicleWeaponsLevel1";"Armory";134;0
"Unit";"Marine";"Barracks";167;1
"Unit";"Marine";"Barracks";168;1
"Unit";"Marine";"Barracks";169;1
"Unit";"Marine";"Barracks";170;1
"Unit";"Marine";"Barracks";170;1
"Unit";"Marine";"Barracks";175;1
"Unit";"SCV";"Command Center";175;1
"Unit";"SCV";"Command Center";175;1
"Unit";"SCV";"Command Center";175;1
"Unit";"Marine";"Barracks";179;1
"Unit";"Marine";"Barracks";179;1
"Unit";"Marine";"Barracks";179;1
"Unit";"Marine";"Barracks";179;1
"Unit";"Marine";"Barracks";179;1
"Unit";"Marine";"Barracks";179;1
"Unit";"Marine";"Barracks";179;1
