"Type";"UnitName";"OnBuilding";"TotalSupply";"Supply"
"Unit";"SCV";"Command Center";12;1
"Unit";"SCV";"Command Center";12;1
"Unit";"SCV";"Command Center";13;1
"Building";"SupplyDepot";NA;13;0
"Unit";"SCV";"Command Center";15;1
"Building";"Refinery";NA;14;0
"Unit";"SCV";"Command Center";15;1
"Unit";"SCV";"Command Center";16;1
"Unit";"SCV";"Command Center";17;1
"Building";"Barracks";NA;15;0
"Unit";"Reaper";"Barracks";19;1
"Unit";"SCV";"Command Center";19;1
"Unit";"SCV";"Command Center";21;1
"Building";"Refinery";NA;20;0
"Building";"Factory";NA;19;0
"Building";"SupplyDepot";NA;21;0
"Unit";"SCV";"Command Center";22;1
"Building";"CommandCenter";NA;19;0
"Unit";"SCV";"Command Center";22;1
"Building";"FactoryTechLab";NA;23;0
"Unit";"SCV";"Command Center";23;1
"Building";"BarracksReactor";NA;22;0
"Building";"Starport";NA;22;0
"Unit";"SCV";"Command Center";24;1
"Unit";"Marine";"Barracks";25;1
"Unit";"Marine";"Barracks";25;1
"Unit";"SCV";"Command Center";25;1
"Unit";"SCV";"Command Center";26;1
"Unit";"SCV";"Command Center";28;1
"Unit";"SCV";"Command Center";30;1
"Building";"FactoryTechLab";NA;30;0
"Unit";"Marine";"Barracks";30;1
"Unit";"Marine";"Barracks";30;1
"Unit";"SCV";"Command Center";31;1
"Building";"SupplyDepot";NA;30;0
"Unit";"SCV";"Command Center";32;1
"Unit";"Banshee";"Starport";26;3
"Unit";"SCV";"Command Center";35;1
"Unit";"Marine";"Barracks";35;1
"Unit";"Marine";"Barracks";35;1
"Unit";"SCV";"Command Center";39;1
"Unit";"SCV";"Command Center";40;1
"Unit";"SCV";"Command Center";43;1
"Building";"SupplyDepot";NA;43;0
"Unit";"SCV";"Command Center";45;1
"Unit";"SCV";"Command Center";45;1
"Unit";"Banshee";"Starport";40;3
"Building";"SupplyDepot";NA;44;0
"Building";"BarracksTechLab";NA;45;0
"Building";"EngineeringBay";NA;45;0
"Building";"Refinery";NA;45;0
"Unit";"SCV";"Command Center";50;1
"Building";"CommandCenter";NA;36;0
"Unit";"SCV";"Command Center";51;1
"Unit";"SCV";"Command Center";51;1
"Unit";"Marine";"Barracks";50;1
"Building";"Barracks";NA;45;0
"Unit";"SCV";"Command Center";51;1
"Unit";"SCV";"Command Center";52;1
"Building";"EngineeringBay";NA;51;0
"Unit";"Banshee";"Starport";50;3
"Unit";"SCV";"Command Center";54;1
"Unit";"SCV";"Command Center";55;1
"Building";"SupplyDepot";NA;54;0
"Unit";"SCV";"Command Center";59;1
"Unit";"SCV";"Command Center";61;1
"Building";"Barracks";NA;51;0
"Unit";"Marine";"Barracks";61;1
"Unit";"Marine";"Barracks";61;1
"Unit";"Marine";"Barracks";61;1
"Unit";"SCV";"Command Center";61;1
"Unit";"SCV";"Command Center";61;1
"Unit";"Marine";"Barracks";63;1
"Unit";"SCV";"Command Center";68;1
"Building";"SupplyDepot";NA;63;0
"Unit";"Marine";"Barracks";63;1
"Unit";"Marine";"Barracks";64;1
"Unit";"Marine";"Barracks";65;1
"Building";"SupplyDepot";NA;63;0
"Building";"Bunker";NA;63;0
"Unit";"SCV";"Command Center";70;1
"Unit";"SCV";"Command Center";70;1
"Unit";"SCV";"Command Center";70;1
"Building";"BarracksTechLab";NA;73;0
"Unit";"SCV";"Command Center";73;1
"Unit";"Marine";"Barracks";73;1
"Unit";"Marine";"Barracks";73;1
"Unit";"Marine";"Barracks";73;1
"Building";"Refinery";NA;73;0
"Building";"StarportReactor";NA;68;0
"Unit";"SCV";"Command Center";80;1
"Unit";"SCV";"Command Center";80;1
"Building";"MissileTurret";NA;80;0
"Upgrade";"Stimpack";"TechLab";56;0
"Building";"Barracks";NA;70;0
"Building";"Barracks";NA;73;0
"Unit";"SCV";"Command Center";80;1
"Building";"MissileTurret";NA;80;0
"Unit";"Marine";"Barracks";80;1
"Unit";"Marine";"Barracks";80;1
"Unit";"SCV";"Command Center";82;1
"Unit";"Marine";"Barracks";80;1
"Unit";"Marine";"Barracks";80;1
"Unit";"SCV";"Command Center";82;1
"Unit";"SCV";"Command Center";85;1
"Unit";"SCV";"Command Center";88;1
"Upgrade";"TerranInfantryWeaponsLevel1";"EngineeringBay";68;0
"Unit";"Marine";"Barracks";83;1
"Unit";"SCV";"Command Center";88;1
"Unit";"SCV";"Command Center";89;1
"Unit";"Marine";"Barracks";88;1
"Unit";"Marine";"Barracks";88;1
"Unit";"Marine";"Barracks";88;1
"Unit";"Marine";"Barracks";88;1
"Building";"Armory";NA;80;0
"Unit";"SCV";"Command Center";90;1
"Building";"Starport";NA;82;0
"Building";"Starport";NA;82;0
"Unit";"SCV";"Command Center";92;1
"Building";"BarracksReactor";NA;88;0
"Building";"SupplyDepot";NA;92;0
"Building";"SupplyDepot";NA;92;0
"Unit";"Marine";"Barracks";99;1
"Unit";"Marine";"Barracks";99;1
"Unit";"Marine";"Barracks";99;1
"Unit";"Marine";"Barracks";100;1
"Unit";"Marine";"Barracks";100;1
"Unit";"Marine";"Barracks";103;1
"Unit";"SCV";"Command Center";103;1
"Unit";"Marine";"Barracks";103;1
"Unit";"SCV";"Command Center";103;1
"Unit";"Marine";"Barracks";103;1
"Unit";"Marine";"Barracks";103;1
"Unit";"Marine";"Barracks";103;1
"Unit";"SCV";"Command Center";103;1
"Unit";"SCV";"Command Center";106;1
"Unit";"SCV";"Command Center";110;1
"Unit";"Marine";"Barracks";103;1
"Unit";"Marine";"Barracks";104;1
"Unit";"Medivac";"Starport";103;2
"Building";"StarportTechLab";NA;105;0
"Unit";"Medivac";"Starport";103;2
"Unit";"SCV";"Command Center";112;1
"Unit";"Marine";"Barracks";105;1
"Upgrade";"TerranInfantryArmorsLevel1";"EngineeringBay";88;0
"Unit";"SCV";"Command Center";113;1
"Unit";"SCV";"Command Center";114;1
"Unit";"SCV";"Command Center";121;1
"Unit";"Marine";"Barracks";114;1
"Unit";"Marine";"Barracks";114;1
"Unit";"Marine";"Barracks";114;1
"Building";"StarportReactor";NA;105;0
"Unit";"Marauder";"Barracks";114;2
"Building";"Refinery";NA;123;0
"Building";"Refinery";NA;123;0
"Unit";"SCV";"Command Center";131;1
"Unit";"SCV";"Command Center";131;1
"Unit";"SCV";"Command Center";131;1
"Building";"FusionCore";NA;113;0
"Unit";"Marine";"Barracks";131;1
"Unit";"Marine";"Barracks";131;1
"Unit";"Marine";"Barracks";131;1
"Unit";"Marine";"Barracks";131;1
"Unit";"Marine";"Barracks";131;1
"Unit";"Marine";"Barracks";131;1
"Unit";"Marine";"Barracks";131;1
"Unit";"SCV";"Command Center";131;1
"Building";"MissileTurret";NA;134;0
"Unit";"SCV";"Command Center";141;1
"Unit";"SCV";"Command Center";141;1
"Building";"MissileTurret";NA;134;0
"Unit";"Marine";"Barracks";134;1
"Unit";"Marine";"Barracks";135;1
"Unit";"Marine";"Barracks";136;1
"Unit";"Marine";"Barracks";142;1
"Unit";"Marine";"Barracks";142;1
"Unit";"Marine";"Barracks";142;1
"Unit";"Marine";"Barracks";142;1
"Unit";"Marine";"Barracks";144;1
"Unit";"Marine";"Barracks";147;1
"Unit";"Marine";"Barracks";151;1
"Building";"SupplyDepot";NA;152;0
"Building";"SupplyDepot";NA;152;0
"Unit";"Liberator";"Starport";147;3
"Building";"SupplyDepot";NA;152;0
"Unit";"Liberator";"Starport";151;3
"Unit";"Marine";"Barracks";154;1
"Unit";"Marine";"Barracks";154;1
"Unit";"Marine";"Barracks";154;1
"Building";"SupplyDepot";NA;154;0
"Building";"SupplyDepot";NA;154;0
"Unit";"Marauder";"Barracks";154;2
"Unit";"Marine";"Barracks";163;1
"Unit";"Marine";"Barracks";163;1
"Unit";"Marine";"Barracks";163;1
"Unit";"Marauder";"Barracks";163;2
"Unit";"Liberator";"Starport";154;3
"Unit";"Liberator";"Starport";154;3
"Unit";"Marauder";"Barracks";163;2
"Unit";"Liberator";"Starport";157;3
"Building";"CommandCenter";NA;154;0
"Unit";"Liberator";"Starport";160;3
"Unit";"Liberator";"Starport";160;3
"Unit";"SCV";"Command Center";178;1
"Building";"SensorTower";NA;188;0
"Unit";"Medivac";"Starport";181;2
"Upgrade";"TerranShipWeaponsLevel1";"Armory";160;0
"Building";"Starport";NA;188;0
"Unit";"Marine";"Barracks";190;1
"Unit";"Marine";"Barracks";190;1
"Unit";"Marine";"Barracks";190;1
"Unit";"Marine";"Barracks";190;1
"Unit";"Marine";"Barracks";190;1
"Unit";"Marine";"Barracks";190;1
"Building";"Barracks";NA;188;0
"Unit";"Marauder";"Barracks";190;2
"Building";"Barracks";NA;188;0
"Building";"Armory";NA;188;0
"Unit";"Marine";"Barracks";190;1
"Unit";"Marine";"Barracks";191;1
"Unit";"Marauder";"Barracks";194;2
"Unit";"Marauder";"Barracks";195;2
"Unit";"Marine";"Barracks";198;1
"Unit";"Marine";"Barracks";198;1
"Unit";"Marauder";"Barracks";196;2
"Unit";"Marine";"Barracks";198;1
"Unit";"Marine";"Barracks";199;1
"Building";"SupplyDepot";NA;198;0
"Building";"SupplyDepot";NA;200;0
"Building";"SupplyDepot";NA;200;0
"Building";"SupplyDepot";NA;200;0
"Building";"Refinery";NA;200;0
"Unit";"Marine";"Barracks";204;1
"Unit";"Marine";"Barracks";205;1
"Building";"Refinery";NA;200;0
"Unit";"Marauder";"Barracks";200;2
"Unit";"Marauder";"Barracks";202;2
"Unit";"Marauder";"Barracks";206;2
"Unit";"Marine";"Barracks";208;1
"Unit";"Marine";"Barracks";209;1
"Building";"BarracksTechLab";NA;210;0
"Building";"BarracksTechLab";NA;210;0
"Unit";"Marine";"Barracks";210;1
"Unit";"Marine";"Barracks";211;1
"Unit";"Marauder";"Barracks";212;2
"Unit";"Liberator";"Starport";208;3
"Unit";"Marine";"Barracks";224;1
"Unit";"Marine";"Barracks";224;1
"Unit";"Marine";"Barracks";224;1
"Unit";"Marine";"Barracks";224;1
"Unit";"Marine";"Barracks";224;1
"Unit";"Marauder";"Barracks";224;2
"Unit";"Marauder";"Barracks";224;2
"Unit";"Marauder";"Barracks";224;2
"Unit";"Marauder";"Barracks";224;2
