"Type";"UnitName";"OnBuilding";"TotalSupply";"Supply"
"Unit";"SCV";"Command Center";12;1
"Unit";"SCV";"Command Center";12;1
"Unit";"SCV";"Command Center";13;1
"Building";"SupplyDepot";NA;13;0
"Building";"Refinery";NA;14;0
"Unit";"SCV";"Command Center";15;1
"Unit";"SCV";"Command Center";15;1
"Unit";"SCV";"Command Center";16;1
"Unit";"SCV";"Command Center";17;1
"Building";"Barracks";NA;15;0
"Unit";"Reaper";"Barracks";19;1
"Unit";"SCV";"Command Center";19;1
"Unit";"SCV";"Command Center";21;1
"Building";"SupplyDepot";NA;20;0
"Unit";"Reaper";"Barracks";20;1
"Building";"Factory";NA;19;0
"Building";"Refinery";NA;21;0
"Unit";"SCV";"Command Center";22;1
"Unit";"Marine";"Barracks";22;1
"Unit";"SCV";"Command Center";23;1
"Building";"CommandCenter";NA;19;0
"Unit";"Hellion";"Factory";23;2
"Unit";"SCV";"Command Center";25;1
"Building";"Starport";NA;23;0
"Unit";"SCV";"Command Center";28;1
"Building";"BarracksReactor";NA;25;0
"Unit";"SCV";"Command Center";29;1
"Unit";"SCV";"Command Center";30;1
"Unit";"SCV";"Command Center";30;1
"Unit";"Cyclone";"Factory";30;3
"Unit";"SCV";"Command Center";31;1
"Unit";"Marine";"Barracks";30;1
"Unit";"Marine";"Barracks";31;1
"Unit";"SCV";"Command Center";32;1
"Unit";"SCV";"Command Center";36;1
"Unit";"Medivac";"Starport";31;2
"Building";"SupplyDepot";NA;33;0
"Unit";"SCV";"Command Center";39;1
"Unit";"Marine";"Barracks";39;1
"Unit";"Marine";"Barracks";39;1
"Unit";"SCV";"Command Center";40;1
"Building";"StarportTechLab";NA;43;0
"Unit";"SCV";"Command Center";46;1
"Building";"SupplyDepot";NA;43;0
"Unit";"SCV";"Command Center";47;1
"Unit";"Marine";"Barracks";47;1
"Unit";"Marine";"Barracks";47;1
"Unit";"SCV";"Command Center";47;1
"Unit";"Cyclone";"Factory";47;3
"Unit";"SCV";"Command Center";48;1
"Unit";"SCV";"Command Center";51;1
"Unit";"Marine";"Barracks";51;1
"Unit";"Marine";"Barracks";51;1
"Unit";"SCV";"Command Center";55;1
"Building";"SupplyDepot";NA;52;0
"Unit";"SCV";"Command Center";56;1
"Unit";"SCV";"Command Center";60;1
"Unit";"SCV";"Command Center";60;1
"Unit";"Raven";"Starport";49;2
"Unit";"Marine";"Barracks";60;1
"Unit";"Marine";"Barracks";60;1
"Building";"FactoryTechLab";NA;61;0
"Unit";"SCV";"Command Center";61;1
"Unit";"SCV";"Command Center";62;1
"Building";"CommandCenter";NA;47;0
"Unit";"SCV";"Command Center";67;1
"Unit";"SCV";"Command Center";68;1
"Building";"Refinery";NA;67;0
"Building";"Refinery";NA;68;0
"Unit";"SCV";"Command Center";69;1
"Unit";"SCV";"Command Center";70;1
"Unit";"Marine";"Barracks";71;1
"Unit";"SCV";"Command Center";71;1
"Unit";"SCV";"Command Center";73;1
"Building";"StarportReactor";NA;69;0
"Building";"Barracks";NA;68;0
"Building";"SupplyDepot";NA;73;0
"Unit";"SCV";"Command Center";74;1
"Building";"Barracks";NA;69;0
"Building";"Barracks";NA;69;0
"Building";"Barracks";NA;69;0
"Building";"EngineeringBay";NA;72;0
"Unit";"SCV";"Command Center";75;1
"Unit";"SCV";"Command Center";75;1
"Building";"EngineeringBay";NA;73;0
"Unit";"Marine";"Barracks";76;1
"Unit";"SCV";"Command Center";76;1
"Unit";"SCV";"Command Center";77;1
"Building";"SupplyDepot";NA;76;0
"Unit";"Marine";"Barracks";79;1
"Unit";"Marine";"Barracks";79;1
"Unit";"Marine";"Barracks";79;1
"Unit";"SCV";"Command Center";82;1
"Unit";"SCV";"Command Center";82;1
"Unit";"SCV";"Command Center";82;1
"Unit";"Marine";"Barracks";82;1
"Building";"BarracksReactor";NA;79;0
"Building";"BarracksReactor";NA;79;0
"Building";"BarracksReactor";NA;79;0
"Unit";"Marine";"Barracks";84;1
"Unit";"Marine";"Barracks";88;1
"Unit";"Marine";"Barracks";89;1
"Unit";"Marine";"Barracks";89;1
"Unit";"Marine";"Barracks";89;1
"Unit";"Marine";"Barracks";89;1
"Building";"SupplyDepot";NA;84;0
"Unit";"SCV";"Command Center";91;1
"Unit";"SCV";"Command Center";91;1
"Building";"SupplyDepot";NA;82;0
"Unit";"Medivac";"Starport";89;2
"Unit";"Marine";"Barracks";91;1
"Unit";"Marine";"Barracks";91;1
"Upgrade";"Stimpack";"TechLab";76;0
"Unit";"SCV";"Command Center";97;1
"Unit";"Marine";"Barracks";95;1
"Unit";"Marine";"Barracks";95;1
"Unit";"Marine";"Barracks";95;1
"Unit";"Marine";"Barracks";95;1
"Unit";"SCV";"Command Center";97;1
"Unit";"Marine";"Barracks";97;1
"Unit";"Marine";"Barracks";97;1
"Unit";"Marine";"Barracks";97;1
"Unit";"SCV";"Command Center";101;1
"Unit";"Marine";"Barracks";107;1
"Unit";"Marine";"Barracks";107;1
"Unit";"Medivac";"Starport";101;2
"Unit";"Medivac";"Starport";101;2
"Unit";"Marine";"Barracks";110;1
"Unit";"Marine";"Barracks";110;1
"Building";"SupplyDepot";NA;110;0
"Building";"EngineeringBay";NA;107;0
"Building";"EngineeringBay";NA;107;0
"Unit";"SCV";"Command Center";119;1
"Unit";"SCV";"Command Center";119;1
"Building";"SupplyDepot";NA;111;0
"Unit";"SCV";"Command Center";119;1
"Unit";"Marine";"Barracks";119;1
"Unit";"Marine";"Barracks";119;1
"Unit";"Marine";"Barracks";119;1
"Unit";"Marine";"Barracks";119;1
"Unit";"Marine";"Barracks";119;1
"Unit";"Marine";"Barracks";119;1
"Building";"SupplyDepot";NA;119;0
"Unit";"Marine";"Barracks";122;1
"Unit";"Marine";"Barracks";123;1
"Unit";"Marine";"Barracks";124;1
"Unit";"Marine";"Barracks";124;1
"Unit";"Marine";"Barracks";128;1
"Unit";"Marine";"Barracks";128;1
"Unit";"Marine";"Barracks";128;1
"Unit";"Marine";"Barracks";128;1
"Unit";"Marine";"Barracks";128;1
"Unit";"Marine";"Barracks";128;1
"Unit";"Marine";"Barracks";129;1
"Unit";"Marine";"Barracks";130;1
"Unit";"Marine";"Barracks";131;1
"Building";"Refinery";NA;132;0
"Unit";"Marine";"Barracks";134;1
"Unit";"Medivac";"Starport";128;2
"Unit";"SCV";"Command Center";141;1
"Unit";"SCV";"Command Center";141;1
"Unit";"Medivac";"Starport";134;2
"Unit";"SCV";"Command Center";141;1
"Building";"SupplyDepot";NA;137;0
"Building";"SupplyDepot";NA;137;0
"Building";"SupplyDepot";NA;139;0
"Building";"SensorTower";NA;141;0
"Building";"MissileTurret";NA;141;0
"Unit";"Marine";"Barracks";141;1
"Unit";"Marine";"Barracks";141;1
"Building";"Refinery";NA;141;0
"Unit";"Marine";"Barracks";144;1
"Unit";"Marine";"Barracks";144;1
"Unit";"SCV";"Command Center";149;1
"Unit";"Marine";"Barracks";144;1
"Unit";"SCV";"Command Center";149;1
"Unit";"SCV";"Command Center";151;1
"Unit";"Marine";"Barracks";149;1
"Unit";"Marine";"Barracks";149;1
"Building";"SensorTower";NA;151;0
"Unit";"Marine";"Barracks";151;1
"Unit";"Marine";"Barracks";151;1
"Unit";"Marine";"Barracks";151;1
"Unit";"Marine";"Barracks";151;1
"Building";"SupplyDepot";NA;149;0
"Unit";"SCV";"Command Center";153;1
"Unit";"Marine";"Barracks";151;1
"Unit";"Marine";"Barracks";152;1
"Unit";"Marine";"Barracks";157;1
"Unit";"Marine";"Barracks";157;1
"Unit";"Marine";"Barracks";157;1
"Unit";"Marine";"Barracks";159;1
"Building";"Factory";NA;149;0
"Unit";"Marine";"Barracks";164;1
"Unit";"Marine";"Barracks";164;1
"Unit";"Marine";"Barracks";164;1
"Unit";"Marine";"Barracks";164;1
"Unit";"Marine";"Barracks";166;1
"Unit";"Marine";"Barracks";166;1
"Unit";"Marine";"Barracks";167;1
"Unit";"Marine";"Barracks";167;1
"Unit";"Marine";"Barracks";169;1
"Unit";"Marine";"Barracks";170;1
"Building";"SupplyDepot";NA;170;0
"Building";"FactoryTechLab";NA;174;0
"Unit";"Medivac";"Starport";169;2
"Unit";"Medivac";"Starport";169;2
"Building";"Barracks";NA;162;0
"Building";"Barracks";NA;164;0
"Building";"Barracks";NA;164;0
"Building";"MissileTurret";NA;178;0
"Upgrade";"TerranInfantryWeaponsLevel1";"EngineeringBay";145;0
"Upgrade";"TerranInfantryArmorsLevel1";"EngineeringBay";146;0
"Building";"MissileTurret";NA;179;0
"Building";"MissileTurret";NA;179;0
"Unit";"Marine";"Barracks";179;1
"Unit";"Marine";"Barracks";179;1
"Unit";"Marine";"Barracks";180;1
"Unit";"Marine";"Barracks";180;1
"Building";"Armory";NA;170;0
"Building";"BarracksReactor";NA;184;0
"Building";"BarracksReactor";NA;184;0
"Building";"BarracksReactor";NA;184;0
"Unit";"Marine";"Barracks";188;1
"Unit";"Marine";"Barracks";188;1
"Unit";"Marine";"Barracks";188;1
"Unit";"Marine";"Barracks";188;1
"Unit";"Marine";"Barracks";188;1
"Unit";"Marine";"Barracks";188;1
"Building";"CommandCenter";NA;176;0
"Building";"SupplyDepot";NA;188;0
"Unit";"Marine";"Barracks";188;1
"Building";"SupplyDepot";NA;188;0
"Building";"SupplyDepot";NA;188;0
"Unit";"Marine";"Barracks";188;1
"Unit";"Marine";"Barracks";194;1
"Unit";"Marine";"Barracks";194;1
"Unit";"Marine";"Barracks";194;1
"Unit";"Marine";"Barracks";196;1
"Unit";"Marine";"Barracks";196;1
"Unit";"Medivac";"Starport";194;2
"Unit";"Medivac";"Starport";194;2
"Unit";"Marine";"Barracks";196;1
"Unit";"Marine";"Barracks";196;1
"Unit";"Marine";"Barracks";199;1
"Unit";"Marine";"Barracks";199;1
"Unit";"Marine";"Barracks";199;1
"Unit";"Marine";"Barracks";199;1
"Unit";"Marine";"Barracks";199;1
"Unit";"Marine";"Barracks";199;1
"Unit";"Marine";"Barracks";201;1
"Unit";"Marine";"Barracks";201;1
"Unit";"Marine";"Barracks";201;1
"Unit";"Marine";"Barracks";201;1
"Unit";"Marine";"Barracks";207;1
"Unit";"Marine";"Barracks";207;1
"Unit";"Marine";"Barracks";207;1
"Unit";"Marine";"Barracks";207;1
"Unit";"Marine";"Barracks";213;1
"Unit";"Marine";"Barracks";213;1
"Unit";"Marine";"Barracks";213;1
"Unit";"Marine";"Barracks";217;1
"Unit";"Marine";"Barracks";217;1
"Unit";"Marine";"Barracks";217;1
"Unit";"Marine";"Barracks";221;1
"Unit";"Marine";"Barracks";221;1
"Unit";"Marine";"Barracks";221;1
"Unit";"Marine";"Barracks";221;1
"Unit";"Marine";"Barracks";222;1
"Unit";"Marine";"Barracks";223;1
"Unit";"Marine";"Barracks";224;1
"Upgrade";"TerranVehicleWeaponsLevel1";"Armory";196;0
"Unit";"Marine";"Barracks";234;1
"Upgrade";"TerranInfantryArmorsLevel2";"EngineeringBay";195;0
"Upgrade";"TerranInfantryWeaponsLevel2";"EngineeringBay";195;0
