"type";"unit_name";"on_building";"total_supply";"supply"
"Building";"Refinery";NA;14;0
"Building";"Barracks";NA;15;0
"Unit";"Reaper";"Barracks";19;1
"Unit";"Reaper";"Barracks";20;1
"Building";"Factory";NA;19;0
"Building";"Refinery";NA;21;0
"Unit";"Marine";"Barracks";22;1
"Building";"CommandCenter";NA;19;0
"Unit";"Hellion";"Factory";23;2
"Building";"Starport";NA;23;0
"Building";"BarracksReactor";NA;25;0
"Unit";"Cyclone";"Factory";30;3
"Unit";"Marine";"Barracks";30;1
"Unit";"Marine";"Barracks";31;1
"Unit";"Medivac";"Starport";31;2
"Unit";"Marine";"Barracks";39;1
"Unit";"Marine";"Barracks";39;1
"Building";"StarportTechLab";NA;43;0
"Unit";"Marine";"Barracks";47;1
"Unit";"Marine";"Barracks";47;1
"Unit";"Cyclone";"Factory";47;3
"Unit";"Marine";"Barracks";51;1
"Unit";"Marine";"Barracks";51;1
"Unit";"Raven";"Starport";49;2
"Unit";"Marine";"Barracks";60;1
"Unit";"Marine";"Barracks";60;1
"Building";"FactoryTechLab";NA;61;0
"Building";"CommandCenter";NA;47;0
"Building";"Refinery";NA;67;0
"Building";"Refinery";NA;68;0
"Unit";"Marine";"Barracks";71;1
"Building";"StarportReactor";NA;69;0
"Building";"Barracks";NA;68;0
"Building";"Barracks";NA;69;0
"Building";"Barracks";NA;69;0
"Building";"Barracks";NA;69;0
"Building";"EngineeringBay";NA;72;0
"Building";"EngineeringBay";NA;73;0
"Unit";"Marine";"Barracks";76;1
"Unit";"Marine";"Barracks";79;1
"Unit";"Marine";"Barracks";79;1
"Unit";"Marine";"Barracks";79;1
"Unit";"Marine";"Barracks";82;1
"Building";"BarracksReactor";NA;79;0
"Building";"BarracksReactor";NA;79;0
"Building";"BarracksReactor";NA;79;0
"Unit";"Marine";"Barracks";84;1
"Unit";"Marine";"Barracks";88;1
"Unit";"Marine";"Barracks";89;1
"Unit";"Marine";"Barracks";89;1
"Unit";"Marine";"Barracks";89;1
"Unit";"Marine";"Barracks";89;1
"Unit";"Medivac";"Starport";89;2
"Unit";"Marine";"Barracks";91;1
"Unit";"Marine";"Barracks";91;1
"Upgrade";"Stimpack";"TechLab";76;0
"Unit";"Marine";"Barracks";95;1
"Unit";"Marine";"Barracks";95;1
"Unit";"Marine";"Barracks";95;1
"Unit";"Marine";"Barracks";95;1
"Unit";"Marine";"Barracks";97;1
"Unit";"Marine";"Barracks";97;1
"Unit";"Marine";"Barracks";97;1
"Unit";"Marine";"Barracks";107;1
"Unit";"Marine";"Barracks";107;1
"Unit";"Medivac";"Starport";101;2
"Unit";"Medivac";"Starport";101;2
"Unit";"Marine";"Barracks";110;1
"Unit";"Marine";"Barracks";110;1
"Building";"EngineeringBay";NA;107;0
"Building";"EngineeringBay";NA;107;0
"Unit";"Marine";"Barracks";119;1
"Unit";"Marine";"Barracks";119;1
"Unit";"Marine";"Barracks";119;1
"Unit";"Marine";"Barracks";119;1
"Unit";"Marine";"Barracks";119;1
"Unit";"Marine";"Barracks";119;1
"Unit";"Marine";"Barracks";122;1
"Unit";"Marine";"Barracks";123;1
"Unit";"Marine";"Barracks";124;1
"Unit";"Marine";"Barracks";124;1
"Unit";"Marine";"Barracks";128;1
"Unit";"Marine";"Barracks";128;1
"Unit";"Marine";"Barracks";128;1
"Unit";"Marine";"Barracks";128;1
"Unit";"Marine";"Barracks";128;1
"Unit";"Marine";"Barracks";128;1
"Unit";"Marine";"Barracks";129;1
"Unit";"Marine";"Barracks";130;1
"Unit";"Marine";"Barracks";131;1
"Building";"Refinery";NA;132;0
"Unit";"Marine";"Barracks";134;1
"Unit";"Medivac";"Starport";128;2
"Unit";"Medivac";"Starport";134;2
"Building";"SensorTower";NA;141;0
"Building";"MissileTurret";NA;141;0
"Unit";"Marine";"Barracks";141;1
"Unit";"Marine";"Barracks";141;1
"Building";"Refinery";NA;141;0
"Unit";"Marine";"Barracks";144;1
"Unit";"Marine";"Barracks";144;1
"Unit";"Marine";"Barracks";144;1
"Unit";"Marine";"Barracks";149;1
"Unit";"Marine";"Barracks";149;1
"Building";"SensorTower";NA;151;0
"Unit";"Marine";"Barracks";151;1
"Unit";"Marine";"Barracks";151;1
"Unit";"Marine";"Barracks";151;1
"Unit";"Marine";"Barracks";151;1
"Unit";"Marine";"Barracks";151;1
"Unit";"Marine";"Barracks";152;1
"Unit";"Marine";"Barracks";157;1
"Unit";"Marine";"Barracks";157;1
"Unit";"Marine";"Barracks";157;1
"Unit";"Marine";"Barracks";159;1
"Building";"Factory";NA;149;0
"Unit";"Marine";"Barracks";164;1
"Unit";"Marine";"Barracks";164;1
"Unit";"Marine";"Barracks";164;1
"Unit";"Marine";"Barracks";164;1
"Unit";"Marine";"Barracks";166;1
"Unit";"Marine";"Barracks";166;1
"Unit";"Marine";"Barracks";167;1
"Unit";"Marine";"Barracks";167;1
"Unit";"Marine";"Barracks";169;1
"Unit";"Marine";"Barracks";170;1
"Building";"FactoryTechLab";NA;174;0
"Unit";"Medivac";"Starport";169;2
"Unit";"Medivac";"Starport";169;2
"Building";"Barracks";NA;162;0
"Building";"Barracks";NA;164;0
"Building";"Barracks";NA;164;0
"Building";"MissileTurret";NA;178;0
"Upgrade";"TerranInfantryWeaponsLevel1";"EngineeringBay";145;0
"Upgrade";"TerranInfantryArmorsLevel1";"EngineeringBay";146;0
"Building";"MissileTurret";NA;179;0
"Building";"MissileTurret";NA;179;0
"Unit";"Marine";"Barracks";179;1
"Unit";"Marine";"Barracks";179;1
"Unit";"Marine";"Barracks";180;1
"Unit";"Marine";"Barracks";180;1
"Building";"Armory";NA;170;0
"Building";"BarracksReactor";NA;184;0
"Building";"BarracksReactor";NA;184;0
"Building";"BarracksReactor";NA;184;0
"Unit";"Marine";"Barracks";188;1
"Unit";"Marine";"Barracks";188;1
"Unit";"Marine";"Barracks";188;1
"Unit";"Marine";"Barracks";188;1
"Unit";"Marine";"Barracks";188;1
"Unit";"Marine";"Barracks";188;1
"Building";"CommandCenter";NA;176;0
"Unit";"Marine";"Barracks";188;1
"Unit";"Marine";"Barracks";188;1
"Unit";"Marine";"Barracks";194;1
"Unit";"Marine";"Barracks";194;1
"Unit";"Marine";"Barracks";194;1
"Unit";"Marine";"Barracks";196;1
"Unit";"Marine";"Barracks";196;1
"Unit";"Medivac";"Starport";194;2
"Unit";"Medivac";"Starport";194;2
"Unit";"Marine";"Barracks";196;1
"Unit";"Marine";"Barracks";196;1
"Unit";"Marine";"Barracks";199;1
"Unit";"Marine";"Barracks";199;1
"Unit";"Marine";"Barracks";199;1
"Unit";"Marine";"Barracks";199;1
"Unit";"Marine";"Barracks";199;1
"Unit";"Marine";"Barracks";199;1
"Unit";"Marine";"Barracks";201;1
"Unit";"Marine";"Barracks";201;1
"Unit";"Marine";"Barracks";201;1
"Unit";"Marine";"Barracks";201;1
"Unit";"Marine";"Barracks";207;1
"Unit";"Marine";"Barracks";207;1
"Unit";"Marine";"Barracks";207;1
"Unit";"Marine";"Barracks";207;1
"Unit";"Marine";"Barracks";213;1
"Unit";"Marine";"Barracks";213;1
"Unit";"Marine";"Barracks";213;1
"Unit";"Marine";"Barracks";217;1
"Unit";"Marine";"Barracks";217;1
"Unit";"Marine";"Barracks";217;1
"Unit";"Marine";"Barracks";221;1
"Unit";"Marine";"Barracks";221;1
"Unit";"Marine";"Barracks";221;1
"Unit";"Marine";"Barracks";221;1
"Unit";"Marine";"Barracks";222;1
"Unit";"Marine";"Barracks";223;1
"Unit";"Marine";"Barracks";224;1
"Upgrade";"TerranVehicleWeaponsLevel1";"Armory";196;0
"Unit";"Marine";"Barracks";234;1
"Upgrade";"TerranInfantryArmorsLevel2";"EngineeringBay";195;0
"Upgrade";"TerranInfantryWeaponsLevel2";"EngineeringBay";195;0
