"type";"unit_name";"on_building";"total_supply";"supply"
"Building";"Refinery";NA;14;0
"Building";"Barracks";NA;15;0
"Building";"Refinery";NA;16;0
"Building";"Barracks";NA;16;0
"Unit";"Reaper";"Barracks";18;1
"Unit";"Reaper";"Barracks";18;1
"Unit";"Reaper";"Barracks";18;1
"Unit";"Reaper";"Barracks";19;1
"Unit";"Reaper";"Barracks";20;1
"Building";"Factory";NA;20;0
