"type";"unit_name";"on_building";"total_supply";"supply"
"Building";"Refinery";NA;14;0
"Building";"Barracks";NA;15;0
"Unit";"Reaper";"Barracks";19;1
"Unit";"Reaper";"Barracks";19;1
"Building";"Factory";NA;19;0
"Building";"CommandCenter";NA;19;0
"Building";"Refinery";NA;24;0
"Unit";"Cyclone";"Factory";24;3
"Building";"BarracksReactor";NA;25;0
"Building";"Refinery";NA;25;0
"Unit";"Cyclone";"Factory";30;3
"Building";"EngineeringBay";NA;34;0
"Building";"MissileTurret";NA;41;0
"Unit";"Cyclone";"Factory";40;3
"Building";"MissileTurret";NA;41;0
"Unit";"Cyclone";"Factory";41;3
"Building";"CommandCenter";NA;32;0
"Building";"FactoryTechLab";NA;49;0
"Building";"Starport";NA;49;0
"Building";"BarracksReactor";NA;49;0
"Building";"Factory";NA;49;0
"Building";"Factory";NA;49;0
"Building";"Refinery";NA;53;0
"Unit";"Hellion";"Factory";58;2
"Unit";"Hellion";"Factory";58;2
"Unit";"Hellion";"Factory";59;2
"Building";"BarracksReactor";NA;59;0
"Unit";"Hellion";"Factory";70;2
"Unit";"Hellion";"Factory";70;2
"Unit";"Hellion";"Factory";73;2
"Unit";"Hellion";"Factory";73;2
"Unit";"Hellion";"Factory";77;2
"Unit";"Hellion";"Factory";77;2
"Building";"SensorTower";NA;77;0
"Unit";"Hellion";"Factory";87;2
"Unit";"Hellion";"Factory";87;2
"Unit";"Hellion";"Factory";87;2
"Unit";"Hellion";"Factory";87;2
"Unit";"Medivac";"Starport";87;2
"Unit";"Medivac";"Starport";87;2
"Unit";"Hellion";"Factory";87;2
"Unit";"Hellion";"Factory";89;2
"Unit";"Hellion";"Factory";91;2
"Unit";"Hellion";"Factory";93;2
"Building";"MissileTurret";NA;99;0
"Building";"MissileTurret";NA;99;0
"Building";"MissileTurret";NA;99;0
"Building";"MissileTurret";NA;99;0
"Building";"Armory";NA;99;0
"Building";"Armory";NA;99;0
"Unit";"Medivac";"Starport";107;2
"Unit";"Medivac";"Starport";107;2
"Unit";"Hellion";"Factory";107;2
"Unit";"Hellion";"Factory";107;2
"Unit";"Hellion";"Factory";107;2
"Unit";"Hellion";"Factory";107;2
"Unit";"Hellion";"Factory";119;2
"Unit";"Hellion";"Factory";119;2
"Unit";"Hellion";"Factory";119;2
"Unit";"Hellion";"Factory";125;2
"Building";"SensorTower";NA;129;0
"Building";"Refinery";NA;130;0
"Building";"Refinery";NA;131;0
"Unit";"Hellion";"Factory";133;2
"Unit";"Hellion";"Factory";133;2
"Unit";"Hellion";"Factory";133;2
"Building";"Factory";NA;134;0
"Building";"Factory";NA;134;0
"Unit";"Hellion";"Factory";140;2
"Unit";"Hellion";"Factory";140;2
"Unit";"Hellion";"Factory";140;2
"Unit";"Hellion";"Factory";140;2
"Upgrade";"TerranVehicleWeaponsLevel1";"Armory";125;0
"Building";"FactoryTechLab";NA;148;0
"Building";"FactoryTechLab";NA;148;0
"Unit";"Hellion";"Factory";148;2
"Unit";"Hellion";"Factory";148;2
"Unit";"Hellion";"Factory";148;2
"Unit";"Hellion";"Factory";148;2
