"Type";"UnitName";"OnBuilding";"TotalSupply";"Supply"
"Unit";"SCV";"Command Center";12;1
"Unit";"SCV";"Command Center";12;1
"Unit";"SCV";"Command Center";13;1
"Building";"SupplyDepot";NA;13;0
"Building";"Refinery";NA;14;0
"Unit";"SCV";"Command Center";15;1
"Unit";"SCV";"Command Center";15;1
"Unit";"SCV";"Command Center";16;1
"Building";"Refinery";NA;16;0
"Unit";"SCV";"Command Center";18;1
"Building";"Barracks";NA;15;0
"Unit";"Reaper";"Barracks";19;1
"Building";"SupplyDepot";NA;19;0
"Unit";"SCV";"Command Center";19;1
"Building";"Factory";NA;19;0
"Unit";"SCV";"Command Center";21;1
"Unit";"Reaper";"Barracks";20;1
"Unit";"SCV";"Command Center";21;1
"Unit";"SCV";"Command Center";23;1
"Building";"SupplyDepot";NA;22;0
"Building";"BarracksTechLab";NA;24;0
"Unit";"Cyclone";"Factory";22;3
"Unit";"SCV";"Command Center";24;1
"Building";"Starport";NA;22;0
"Building";"SupplyDepot";NA;25;0
"Unit";"SCV";"Command Center";29;1
"Unit";"Hellion";"Factory";28;2
"Unit";"SCV";"Command Center";29;1
"Unit";"SCV";"Command Center";33;1
"Building";"SupplyDepot";NA;32;0
"Unit";"Cyclone";"Factory";33;3
"Unit";"SCV";"Command Center";33;1
"Unit";"Banshee";"Starport";32;3
"Unit";"SCV";"Command Center";37;1
"Unit";"SCV";"Command Center";41;1
"Unit";"SCV";"Command Center";42;1
"Building";"FactoryTechLab";NA;42;0
"Unit";"SCV";"Command Center";43;1
"Unit";"Banshee";"Starport";38;3
"Building";"BarracksReactor";NA;42;0
"Unit";"SCV";"Command Center";44;1
"Building";"CommandCenter";NA;34;0
"Unit";"SCV";"Command Center";48;1
"Unit";"SCV";"Command Center";49;1
"Unit";"Marine";"Barracks";50;1
"Unit";"Marine";"Barracks";50;1
"Unit";"SCV";"Command Center";50;1
"Unit";"SCV";"Command Center";53;1
"Unit";"Marine";"Barracks";51;1
"Unit";"Marine";"Barracks";52;1
"Unit";"Raven";"Starport";50;2
"Unit";"SCV";"Command Center";54;1
"Unit";"SCV";"Command Center";55;1
"Unit";"Marine";"Barracks";55;1
"Unit";"Marine";"Barracks";56;1
"Unit";"SCV";"Command Center";59;1
"Unit";"SCV";"Command Center";60;1
"Building";"Refinery";NA;57;0
"Unit";"SCV";"Command Center";63;1
"Unit";"SCV";"Command Center";64;1
"Unit";"Marine";"Barracks";61;1
"Unit";"Marine";"Barracks";62;1
"Building";"EngineeringBay";NA;61;0
"Building";"EngineeringBay";NA;62;0
"Building";"Refinery";NA;65;0
"Building";"StarportReactor";NA;61;0
"Unit";"SCV";"Command Center";69;1
"Unit";"SCV";"Command Center";69;1
"Building";"Barracks";NA;61;0
"Building";"Barracks";NA;61;0
"Building";"MissileTurret";NA;69;0
"Building";"MissileTurret";NA;69;0
"Building";"BarracksReactor";NA;69;0
"Unit";"SCV";"Command Center";71;1
"Building";"CommandCenter";NA;61;0
"Building";"SupplyDepot";NA;71;0
"Building";"SupplyDepot";NA;71;0
"Unit";"SCV";"Command Center";72;1
"Unit";"SCV";"Command Center";72;1
"Unit";"Marine";"Barracks";72;1
"Building";"SupplyDepot";NA;72;0
"Unit";"SCV";"Command Center";72;1
"Unit";"SCV";"Command Center";72;1
"Unit";"SCV";"Command Center";75;1
"Unit";"SCV";"Command Center";77;1
"Building";"Barracks";NA;72;0
"Building";"Barracks";NA;72;0
"Unit";"Marine";"Barracks";77;1
"Unit";"Marine";"Barracks";77;1
"Unit";"Marine";"Barracks";77;1
"Unit";"Marine";"Barracks";77;1
"Unit";"Marine";"Barracks";77;1
"Unit";"SCV";"Command Center";79;1
"Unit";"SCV";"Command Center";79;1
"Upgrade";"TerranInfantryWeaponsLevel1";"EngineeringBay";71;0
"Unit";"SCV";"Command Center";84;1
"Unit";"Marine";"Barracks";84;1
"Unit";"Marine";"Barracks";85;1
"Unit";"Marine";"Barracks";86;1
"Unit";"Marine";"Barracks";86;1
"Unit";"Marine";"Barracks";86;1
"Unit";"SCV";"Command Center";92;1
"Unit";"SCV";"Command Center";92;1
"Unit";"Marine";"Barracks";92;1
"Unit";"Marine";"Barracks";92;1
"Unit";"Marine";"Barracks";92;1
"Unit";"Marine";"Barracks";92;1
"Unit";"Marine";"Barracks";92;1
"Building";"BarracksReactor";NA;86;0
"Building";"BarracksReactor";NA;86;0
"Building";"Refinery";NA;92;0
"Building";"SupplyDepot";NA;92;0
"Building";"SupplyDepot";NA;92;0
"Building";"SupplyDepot";NA;92;0
"Upgrade";"Stimpack";"TechLab";77;0
"Unit";"Marine";"Barracks";94;1
"Unit";"Marine";"Barracks";95;1
"Unit";"Marine";"Barracks";96;1
"Unit";"SCV";"Command Center";99;1
"Unit";"SCV";"Command Center";99;1
"Unit";"SCV";"Command Center";99;1
"Building";"SupplyDepot";NA;99;0
"Building";"SupplyDepot";NA;99;0
"Unit";"SCV";"Command Center";102;1
"Unit";"SCV";"Command Center";103;1
"Unit";"SCV";"Command Center";104;1
"Building";"Armory";NA;92;0
"Building";"MissileTurret";NA;105;0
"Building";"MissileTurret";NA;105;0
"Unit";"Medivac";"Starport";99;2
"Unit";"Marine";"Barracks";105;1
"Unit";"Marine";"Barracks";105;1
"Unit";"Marine";"Barracks";105;1
"Unit";"Marine";"Barracks";105;1
"Unit";"Marine";"Barracks";105;1
"Unit";"Marine";"Barracks";105;1
"Unit";"Marine";"Barracks";105;1
"Unit";"Marine";"Barracks";105;1
"Unit";"Medivac";"Starport";99;2
"Building";"SupplyDepot";NA;105;0
"Building";"SupplyDepot";NA;105;0
"Unit";"SCV";"Command Center";108;1
"Unit";"SCV";"Command Center";108;1
"Unit";"SCV";"Command Center";121;1
"Unit";"Marine";"Barracks";120;1
"Unit";"Marine";"Barracks";120;1
"Unit";"Marine";"Barracks";120;1
"Unit";"Marine";"Barracks";120;1
"Unit";"Marine";"Barracks";120;1
"Unit";"Marine";"Barracks";120;1
"Unit";"SCV";"Command Center";122;1
"Upgrade";"TerranInfantryArmorsLevel1";"EngineeringBay";99;0
"Unit";"SCV";"Command Center";130;1
"Unit";"SCV";"Command Center";130;1
"Unit";"Marine";"Barracks";130;1
"Unit";"Marine";"Barracks";130;1
"Unit";"SCV";"Command Center";130;1
"Unit";"SCV";"Command Center";130;1
"Unit";"SCV";"Command Center";131;1
"Unit";"Marine";"Barracks";130;1
"Unit";"Marine";"Barracks";130;1
"Unit";"Marine";"Barracks";130;1
"Unit";"Marine";"Barracks";130;1
"Unit";"Marine";"Barracks";130;1
"Unit";"SCV";"Command Center";134;1
"Building";"Refinery";NA;130;0
"Building";"Refinery";NA;130;0
"Unit";"Marine";"Barracks";134;1
"Unit";"Marine";"Barracks";134;1
"Unit";"Marine";"Barracks";134;1
"Unit";"SCV";"Command Center";135;1
"Unit";"Medivac";"Starport";130;2
"Unit";"Medivac";"Starport";130;2
"Unit";"SCV";"Command Center";142;1
"Unit";"SCV";"Command Center";142;1
"Building";"MissileTurret";NA;137;0
"Building";"MissileTurret";NA;138;0
"Building";"MissileTurret";NA;140;0
"Building";"MissileTurret";NA;143;0
"Unit";"Marine";"Barracks";143;1
"Unit";"Marine";"Barracks";147;1
"Unit";"Marine";"Barracks";147;1
"Unit";"Marine";"Barracks";147;1
"Unit";"Marine";"Barracks";147;1
"Unit";"Marine";"Barracks";147;1
"Unit";"Marine";"Barracks";147;1
"Unit";"Marine";"Barracks";153;1
"Unit";"Marine";"Barracks";153;1
"Unit";"SCV";"Command Center";154;1
"Unit";"SCV";"Command Center";155;1
"Unit";"SCV";"Command Center";155;1
"Unit";"Marine";"Barracks";154;1
"Building";"SensorTower";NA;154;0
"Unit";"Marine";"Barracks";154;1
"Unit";"Marine";"Barracks";155;1
"Unit";"Marine";"Barracks";155;1
"Building";"SensorTower";NA;162;0
"Unit";"Marine";"Barracks";162;1
"Unit";"Marine";"Barracks";162;1
"Unit";"Marine";"Barracks";162;1
"Unit";"Marine";"Barracks";162;1
"Unit";"Marine";"Barracks";162;1
"Unit";"Marine";"Barracks";165;1
"Unit";"Marine";"Barracks";166;1
"Unit";"Marine";"Barracks";167;1
"Unit";"Marine";"Barracks";169;1
"Upgrade";"TerranInfantryWeaponsLevel2";"EngineeringBay";130;0
"Building";"SupplyDepot";NA;169;0
"Unit";"Marine";"Barracks";169;1
"Unit";"Marine";"Barracks";170;1
"Unit";"Marine";"Barracks";170;1
"Unit";"Marine";"Barracks";172;1
"Unit";"Marine";"Barracks";172;1
"Unit";"Marine";"Barracks";174;1
"Unit";"Marine";"Barracks";175;1
"Unit";"Marine";"Barracks";176;1
"Unit";"Marine";"Barracks";177;1
"Unit";"Medivac";"Starport";175;2
"Building";"SensorTower";NA;178;0
"Unit";"Medivac";"Starport";175;2
"Unit";"Marine";"Barracks";178;1
"Unit";"SCV";"Command Center";186;1
"Unit";"SCV";"Command Center";187;1
"Upgrade";"TerranVehicleWeaponsLevel1";"Armory";153;0
"Unit";"Marine";"Barracks";187;1
"Unit";"Marine";"Barracks";187;1
"Unit";"Marine";"Barracks";187;1
"Unit";"Marine";"Barracks";187;1
"Unit";"Marine";"Barracks";187;1
"Unit";"Marine";"Barracks";187;1
"Unit";"Marine";"Barracks";187;1
"Unit";"Marine";"Barracks";192;1
"Unit";"Marine";"Barracks";192;1
"Unit";"SCV";"Command Center";194;1
"Building";"SupplyDepot";NA;192;0
"Building";"MissileTurret";NA;194;0
"Upgrade";"TerranInfantryArmorsLevel2";"EngineeringBay";153;0
"Building";"CommandCenter";NA;177;0
"Building";"Factory";NA;201;0
"Unit";"Marine";"Barracks";204;1
"Unit";"Marine";"Barracks";204;1
"Unit";"Marine";"Barracks";204;1
"Unit";"Marine";"Barracks";204;1
"Unit";"Marine";"Barracks";204;1
"Unit";"Marine";"Barracks";204;1
"Unit";"Marine";"Barracks";204;1
"Unit";"Liberator";"Starport";204;3
"Unit";"Liberator";"Starport";204;3
"Unit";"Marine";"Barracks";204;1
"Unit";"Marine";"Barracks";205;1
"Unit";"Marine";"Barracks";207;1
"Unit";"Marine";"Barracks";207;1
"Unit";"Marine";"Barracks";209;1
"Building";"FactoryTechLab";NA;210;0
