"Type";"UnitName";"OnBuilding";"TotalSupply";"Supply"
"Unit";"SCV";"Command Center";12;1
"Unit";"SCV";"Command Center";12;1
"Building";"SupplyDepot";NA;13;0
"Unit";"SCV";"Command Center";14;1
"Building";"Refinery";NA;14;0
"Unit";"SCV";"Command Center";14;1
"Unit";"SCV";"Command Center";16;1
"Unit";"SCV";"Command Center";16;1
"Unit";"SCV";"Command Center";17;1
"Building";"Refinery";NA;17;0
"Building";"Barracks";NA;15;0
"Unit";"SCV";"Command Center";19;1
"Unit";"Reaper";"Barracks";19;1
"Building";"SupplyDepot";NA;19;0
"Building";"Factory";NA;19;0
"Unit";"SCV";"Command Center";19;1
"Unit";"SCV";"Command Center";21;1
"Unit";"SCV";"Command Center";22;1
"Unit";"Reaper";"Barracks";21;1
"Unit";"Hellion";"Factory";22;2
"Unit";"SCV";"Command Center";23;1
"Unit";"Hellion";"Factory";25;2
"Unit";"Reaper";"Barracks";24;1
"Unit";"SCV";"Command Center";30;1
"Unit";"Hellion";"Factory";30;2
"Unit";"SCV";"Command Center";31;1
"Unit";"SCV";"Command Center";35;1
"Unit";"Reaper";"Barracks";30;1
"Unit";"Hellion";"Factory";35;2
"Unit";"SCV";"Command Center";35;1
"Building";"Starport";NA;32;0
"Unit";"SCV";"Command Center";40;1
"Unit";"Reaper";"Barracks";37;1
"Building";"CommandCenter";NA;31;0
"Building";"SupplyDepot";NA;40;0
"Unit";"SCV";"Command Center";40;1
"Unit";"Cyclone";"Factory";40;3
"Unit";"SCV";"Command Center";42;1
"Unit";"Liberator";"Starport";40;3
"Unit";"SCV";"Command Center";46;1
"Unit";"SCV";"Command Center";50;1
"Unit";"SCV";"Command Center";51;1
"Unit";"SCV";"Command Center";52;1
"Building";"FactoryTechLab";NA;53;0
"Building";"StarportTechLab";NA;53;0
"Unit";"SCV";"Command Center";53;1
"Unit";"SCV";"Command Center";54;1
"Unit";"SCV";"Command Center";54;1
"Building";"BarracksReactor";NA;53;0
"Unit";"SCV";"Command Center";55;1
"Unit";"SCV";"Command Center";56;1
"Building";"Bunker";NA;54;0
"Unit";"SCV";"Command Center";57;1
"Building";"Barracks";NA;53;0
"Building";"Barracks";NA;53;0
"Unit";"SCV";"Command Center";58;1
"Unit";"SCV";"Command Center";59;1
"Unit";"Banshee";"Starport";54;3
"Unit";"Marine";"Barracks";59;1
"Unit";"Marine";"Barracks";59;1
"Unit";"SCV";"Command Center";60;1
"Unit";"SCV";"Command Center";61;1
"Building";"BarracksTechLab";NA;61;0
"Building";"BarracksTechLab";NA;61;0
"Unit";"SCV";"Command Center";67;1
"Building";"SupplyDepot";NA;62;0
"Building";"SupplyDepot";NA;67;0
"Unit";"SCV";"Command Center";68;1
"Unit";"Marine";"Barracks";68;1
"Unit";"Marine";"Barracks";68;1
"Building";"EngineeringBay";NA;67;0
"Building";"EngineeringBay";NA;67;0
"Unit";"SCV";"Command Center";69;1
"Unit";"SCV";"Command Center";70;1
"Unit";"SCV";"Command Center";73;1
"Unit";"Banshee";"Starport";67;3
"Unit";"SCV";"Command Center";74;1
"Unit";"SCV";"Command Center";75;1
"Unit";"Marine";"Barracks";75;1
"Unit";"Marine";"Barracks";75;1
"Unit";"SCV";"Command Center";79;1
"Unit";"Marauder";"Barracks";75;2
"Unit";"Marauder";"Barracks";75;2
"Unit";"SCV";"Command Center";80;1
"Building";"CommandCenter";NA;61;0
"Unit";"SCV";"Command Center";83;1
"Unit";"SCV";"Command Center";88;1
"Unit";"SCV";"Command Center";89;1
"Unit";"Marine";"Barracks";89;1
"Unit";"Marine";"Barracks";89;1
"Building";"Refinery";NA;88;0
"Unit";"Marauder";"Barracks";89;2
"Unit";"Marauder";"Barracks";89;2
"Building";"Refinery";NA;89;0
"Unit";"SCV";"Command Center";90;1
"Building";"SupplyDepot";NA;90;0
"Building";"SupplyDepot";NA;90;0
"Unit";"SCV";"Command Center";94;1
"Unit";"Marine";"Barracks";94;1
"Unit";"Marine";"Barracks";94;1
"Unit";"SCV";"Command Center";99;1
"Unit";"Marauder";"Barracks";94;2
"Unit";"Marauder";"Barracks";96;2
"Unit";"SCV";"Command Center";99;1
"Building";"StarportReactor";NA;90;0
"Unit";"SCV";"Command Center";102;1
"Building";"Barracks";NA;90;0
"Unit";"SCV";"Command Center";107;1
"Unit";"Marine";"Barracks";102;1
"Unit";"Marine";"Barracks";102;1
"Unit";"Marauder";"Barracks";103;2
"Unit";"Marauder";"Barracks";105;2
"Unit";"SCV";"Command Center";108;1
"Upgrade";"Stimpack";"TechLab";80;0
"Unit";"Medivac";"Starport";108;2
"Unit";"Medivac";"Starport";108;2
"Unit";"SCV";"Command Center";119;1
"Unit";"SCV";"Command Center";119;1
"Unit";"Marauder";"Barracks";117;2
"Unit";"Marauder";"Barracks";117;2
"Unit";"Marauder";"Barracks";117;2
"Unit";"SCV";"Command Center";121;1
"Unit";"Marine";"Barracks";121;1
"Unit";"Marine";"Barracks";121;1
"Unit";"SCV";"Command Center";121;1
"Unit";"SCV";"Command Center";122;1
"Unit";"SCV";"Command Center";129;1
"Unit";"Marauder";"Barracks";123;2
"Unit";"Marauder";"Barracks";125;2
"Unit";"Marauder";"Barracks";127;2
"Unit";"SCV";"Command Center";132;1
"Unit";"Marine";"Barracks";130;1
"Upgrade";"TerranInfantryWeaponsLevel1";"EngineeringBay";102;0
"Unit";"SCV";"Command Center";143;1
"Unit";"SCV";"Command Center";143;1
"Unit";"Marine";"Barracks";141;1
"Unit";"Marine";"Barracks";142;1
"Unit";"SCV";"Command Center";143;1
"Unit";"Marauder";"Barracks";135;2
"Unit";"Marauder";"Barracks";137;2
"Unit";"Marauder";"Barracks";139;2
"Unit";"SCV";"Command Center";143;1
"Unit";"Marauder";"Barracks";148;2
"Unit";"Marauder";"Barracks";150;2
"Unit";"Marine";"Barracks";155;1
"Unit";"Marine";"Barracks";155;1
"Unit";"SCV";"Command Center";159;1
"Unit";"SCV";"Command Center";159;1
"Unit";"SCV";"Command Center";159;1
"Unit";"Marauder";"Barracks";155;2
"Unit";"Marauder";"Barracks";155;2
"Unit";"Marauder";"Barracks";157;2
"Unit";"Medivac";"Starport";155;2
"Building";"Refinery";NA;159;0
"Building";"Refinery";NA;159;0
"Unit";"Marine";"Barracks";159;1
"Unit";"Marine";"Barracks";160;1
"Unit";"Marauder";"Barracks";164;2
"Building";"Armory";NA;109;0
"Unit";"Marine";"Barracks";176;1
"Unit";"Marine";"Barracks";176;1
"Unit";"SCV";"Command Center";176;1
"Unit";"SCV";"Command Center";176;1
"Unit";"SCV";"Command Center";176;1
"Unit";"Marauder";"Barracks";176;2
"Unit";"Marauder";"Barracks";176;2
"Unit";"Marauder";"Barracks";176;2
"Unit";"SCV";"Command Center";178;1
"Unit";"SCV";"Command Center";181;1
"Unit";"SCV";"Command Center";181;1
"Unit";"Medivac";"Starport";176;2
"Unit";"Medivac";"Starport";176;2
"Upgrade";"TerranInfantryArmorsLevel1";"EngineeringBay";159;0
"Unit";"Marine";"Barracks";187;1
"Unit";"Marine";"Barracks";187;1
"Unit";"Marauder";"Barracks";181;2
"Unit";"Marauder";"Barracks";183;2
"Unit";"Marauder";"Barracks";185;2
"Unit";"Marine";"Barracks";194;1
"Unit";"Marine";"Barracks";195;1
"Unit";"Marauder";"Barracks";196;2
"Unit";"Marauder";"Barracks";198;2
"Unit";"Marauder";"Barracks";200;2
"Building";"Barracks";NA;187;0
"Building";"Barracks";NA;187;0
"Unit";"Marine";"Barracks";202;1
"Unit";"Marine";"Barracks";203;1
"Unit";"SCV";"Command Center";210;1
"Unit";"SCV";"Command Center";210;1
"Unit";"SCV";"Command Center";210;1
"Unit";"Marauder";"Barracks";204;2
"Unit";"Marauder";"Barracks";206;2
"Unit";"Marauder";"Barracks";208;2
"Unit";"SCV";"Command Center";212;1
"Unit";"Medivac";"Starport";204;2
"Unit";"Medivac";"Starport";204;2
"Building";"BarracksTechLab";NA;210;0
"Unit";"Marine";"Barracks";210;1
"Building";"BarracksTechLab";NA;212;0
"Building";"SupplyDepot";NA;210;0
"Unit";"Marine";"Barracks";219;1
"Unit";"Marauder";"Barracks";215;2
"Unit";"Marauder";"Barracks";217;2
"Unit";"Marauder";"Barracks";219;2
"Unit";"Marine";"Barracks";226;1
"Unit";"Marine";"Barracks";228;1
"Unit";"Marauder";"Barracks";228;2
"Unit";"Marauder";"Barracks";228;2
"Unit";"Marauder";"Barracks";228;2
"Unit";"Marauder";"Barracks";230;2
"Unit";"Marauder";"Barracks";232;2
"Unit";"Marine";"Barracks";234;1
"Unit";"Marine";"Barracks";236;1
"Building";"CommandCenter";NA;210;0
"Unit";"Marine";"Barracks";244;1
"Unit";"Marauder";"Barracks";236;2
"Unit";"Marauder";"Barracks";238;2
"Unit";"Marauder";"Barracks";240;2
"Unit";"Marauder";"Barracks";242;2
"Unit";"Marine";"Barracks";247;1
"Unit";"Marine";"Barracks";248;1
"Upgrade";"TerranInfantryWeaponsLevel2";"EngineeringBay";210;0
"Unit";"Marauder";"Barracks";248;2
"Unit";"Marauder";"Barracks";249;2
"Unit";"Marauder";"Barracks";251;2
"Unit";"Marauder";"Barracks";253;2
"Unit";"Marauder";"Barracks";255;2
"Unit";"Marine";"Barracks";257;1
"Unit";"SCV";"Command Center";259;1
"Unit";"SCV";"Command Center";259;1
"Unit";"SCV";"Command Center";259;1
"Unit";"SCV";"Command Center";270;1
"Unit";"Marauder";"Barracks";259;2
"Unit";"SCV";"Command Center";271;1
"Unit";"SCV";"Command Center";272;1
"Unit";"Marauder";"Barracks";261;2
"Unit";"Marauder";"Barracks";263;2
"Unit";"Marauder";"Barracks";265;2
"Unit";"Marauder";"Barracks";267;2
"Unit";"SCV";"Command Center";273;1
"Unit";"SCV";"Command Center";276;1
"Unit";"SCV";"Command Center";277;1
"Unit";"Marine";"Barracks";273;1
"Unit";"Marine";"Barracks";273;1
"Unit";"Marine";"Barracks";274;1
"Unit";"Marauder";"Barracks";277;2
"Upgrade";"TerranInfantryArmorsLevel2";"EngineeringBay";235;0
