"Type";"UnitName";"OnBuilding";"TotalSupply";"Supply"
"Unit";"SCV";"Command Center";12;1
"Unit";"SCV";"Command Center";12;1
"Unit";"SCV";"Command Center";13;1
"Building";"SupplyDepot";NA;13;0
"Unit";"SCV";"Command Center";15;1
"Building";"Refinery";NA;14;0
"Unit";"SCV";"Command Center";16;1
"Unit";"SCV";"Command Center";16;1
"Unit";"SCV";"Command Center";17;1
"Building";"Barracks";NA;15;0
"Unit";"Reaper";"Barracks";19;1
"Unit";"SCV";"Command Center";19;1
"Unit";"SCV";"Command Center";21;1
"Unit";"SCV";"Command Center";21;1
"Building";"BarracksReactor";NA;20;0
"Unit";"SCV";"Command Center";22;1
"Building";"Factory";NA;20;0
"Building";"SupplyDepot";NA;22;0
"Unit";"SCV";"Command Center";23;1
"Unit";"Marine";"Barracks";24;1
"Unit";"Marine";"Barracks";24;1
"Unit";"SCV";"Command Center";24;1
"Unit";"SCV";"Command Center";27;1
"Building";"Refinery";NA;27;0
"Unit";"Marine";"Barracks";28;1
"Unit";"Marine";"Barracks";28;1
"Unit";"Cyclone";"Factory";27;3
"Unit";"SCV";"Command Center";34;1
"Unit";"Marine";"Barracks";34;1
"Unit";"SCV";"Command Center";34;1
"Unit";"Cyclone";"Factory";34;3
"Unit";"Marine";"Barracks";36;1
"Unit";"Marine";"Barracks";36;1
"Building";"CommandCenter";NA;19;0
"Unit";"SCV";"Command Center";36;1
"Unit";"SCV";"Command Center";42;1
"Building";"EngineeringBay";NA;37;0
"Building";"Starport";NA;36;0
"Building";"FactoryTechLab";NA;43;0
"Unit";"SCV";"Command Center";44;1
"Unit";"Marine";"Barracks";44;1
"Unit";"SCV";"Command Center";45;1
"Building";"MissileTurret";NA;44;0
"Unit";"SCV";"Command Center";46;1
"Unit";"SCV";"Command Center";47;1
"Building";"FactoryTechLab";NA;47;0
"Unit";"SCV";"Command Center";47;1
"Unit";"SCV";"Command Center";48;1
"Unit";"SCV";"Command Center";49;1
"Unit";"Marine";"Barracks";49;1
"Unit";"Raven";"Starport";46;2
"Unit";"SCV";"Command Center";50;1
"Unit";"SCV";"Command Center";51;1
"Building";"MissileTurret";NA;51;0
"Unit";"SCV";"Command Center";55;1
"Unit";"SCV";"Command Center";58;1
"Unit";"SCV";"Command Center";58;1
"Building";"SupplyDepot";NA;57;0
"Building";"SupplyDepot";NA;57;0
"Unit";"SCV";"Command Center";58;1
"Unit";"SCV";"Command Center";60;1
"Unit";"SCV";"Command Center";60;1
"Unit";"Medivac";"Starport";58;2
"Unit";"SCV";"Command Center";61;1
"Unit";"SCV";"Command Center";62;1
"Building";"SupplyDepot";NA;62;0
"Unit";"SCV";"Command Center";65;1
"Unit";"Marine";"Barracks";65;1
"Building";"Barracks";NA;58;0
"Unit";"SCV";"Command Center";66;1
"Unit";"SCV";"Command Center";67;1
"Unit";"SCV";"Command Center";69;1
"Building";"Barracks";NA;62;0
"Unit";"SCV";"Command Center";70;1
"Building";"Refinery";NA;68;0
"Building";"Refinery";NA;68;0
"Building";"SupplyDepot";NA;68;0
"Unit";"Marine";"Barracks";70;1
"Unit";"Marine";"Barracks";70;1
"Unit";"Marine";"Barracks";70;1
"Unit";"SCV";"Command Center";71;1
"Unit";"SCV";"Command Center";72;1
"Unit";"Marine";"Barracks";73;1
"Unit";"Marine";"Barracks";74;1
"Unit";"Marine";"Barracks";75;1
"Building";"SupplyDepot";NA;73;0
"Building";"SupplyDepot";NA;73;0
"Unit";"SCV";"Command Center";78;1
"Unit";"SCV";"Command Center";78;1
"Building";"MissileTurret";NA;81;0
"Unit";"SCV";"Command Center";83;1
"Unit";"SCV";"Command Center";83;1
"Unit";"Marine";"Barracks";81;1
"Unit";"Marine";"Barracks";81;1
"Unit";"SCV";"Command Center";83;1
"Unit";"Marine";"Barracks";83;1
"Unit";"SCV";"Command Center";87;1
"Unit";"Marine";"Barracks";85;1
"Unit";"Marine";"Barracks";86;1
"Building";"BarracksReactor";NA;81;0
"Upgrade";"Stimpack";"TechLab";69;0
"Building";"MissileTurret";NA;87;0
"Upgrade";"TerranInfantryWeaponsLevel1";"EngineeringBay";70;0
"Building";"MissileTurret";NA;87;0
"Unit";"SCV";"Command Center";87;1
"Building";"MissileTurret";NA;87;0
"Building";"SupplyDepot";NA;87;0
"Unit";"SCV";"Command Center";89;1
"Unit";"SCV";"Command Center";94;1
"Unit";"SCV";"Command Center";94;1
"Unit";"Marine";"Barracks";94;1
"Unit";"Marine";"Barracks";94;1
"Unit";"Marine";"Barracks";94;1
"Unit";"Marine";"Barracks";94;1
"Unit";"Marine";"Barracks";94;1
"Unit";"SCV";"Command Center";96;1
"Unit";"SCV";"Command Center";96;1
"Unit";"Medivac";"Starport";94;2
"Unit";"Marine";"Barracks";96;1
"Unit";"Marine";"Barracks";97;1
"Unit";"Marine";"Barracks";98;1
"Unit";"Marine";"Barracks";99;1
"Unit";"Marine";"Barracks";100;1
"Building";"SupplyDepot";NA;101;0
"Unit";"Marine";"Barracks";105;1
"Unit";"Marine";"Barracks";106;1
"Unit";"Marine";"Barracks";107;1
"Unit";"Marine";"Barracks";110;1
"Unit";"Marine";"Barracks";110;1
"Building";"Barracks";NA;101;0
"Building";"Barracks";NA;101;0
"Unit";"Marine";"Barracks";110;1
"Unit";"Marine";"Barracks";111;1
"Unit";"Marine";"Barracks";112;1
"Building";"CommandCenter";NA;96;0
"Unit";"Marine";"Barracks";113;1
"Unit";"Marine";"Barracks";114;1
"Unit";"Marine";"Barracks";115;1
"Unit";"Marine";"Barracks";116;1
"Unit";"Marine";"Barracks";118;1
"Unit";"Marine";"Barracks";118;1
"Unit";"Marine";"Barracks";119;1
"Unit";"Marine";"Barracks";120;1
"Unit";"Marine";"Barracks";121;1
"Unit";"Marine";"Barracks";122;1
"Unit";"Medivac";"Starport";120;2
"Unit";"Marine";"Barracks";123;1
"Unit";"Marine";"Barracks";124;1
"Unit";"Marine";"Barracks";125;1
"Unit";"Marine";"Barracks";126;1
"Unit";"Marine";"Barracks";127;1
"Building";"BarracksReactor";NA;123;0
"Building";"BarracksReactor";NA;123;0
"Upgrade";"TerranInfantryArmorsLevel1";"EngineeringBay";113;0
"Unit";"Marine";"Barracks";130;1
"Unit";"Marine";"Barracks";131;1
"Unit";"Marine";"Barracks";132;1
"Unit";"Marine";"Barracks";133;1
"Unit";"Marine";"Barracks";134;1
"Unit";"SCV";"Command Center";135;1
"Unit";"SCV";"Command Center";135;1
"Unit";"Marine";"Barracks";135;1
"Unit";"Marine";"Barracks";135;1
"Unit";"Marine";"Barracks";135;1
"Unit";"Marine";"Barracks";135;1
"Unit";"Marine";"Barracks";136;1
"Unit";"Marine";"Barracks";137;1
"Unit";"Marine";"Barracks";138;1
"Building";"SupplyDepot";NA;137;0
"Unit";"Medivac";"Starport";135;2
"Unit";"Marine";"Barracks";140;1
"Unit";"Marine";"Barracks";140;1
"Unit";"Marine";"Barracks";142;1
"Unit";"Marine";"Barracks";143;1
"Unit";"Marine";"Barracks";144;1
"Building";"CommandCenter";NA;128;0
"Unit";"Medivac";"Starport";149;2
"Unit";"Marine";"Barracks";156;1
"Unit";"Marine";"Barracks";156;1
"Unit";"Marine";"Barracks";156;1
"Unit";"Marine";"Barracks";156;1
"Unit";"Marine";"Barracks";156;1
"Unit";"Marine";"Barracks";156;1
"Unit";"Marine";"Barracks";156;1
"Unit";"Marine";"Barracks";156;1
"Unit";"Marine";"Barracks";156;1
"Unit";"Marine";"Barracks";158;1
"Unit";"Marine";"Barracks";159;1
"Unit";"Marine";"Barracks";160;1
"Unit";"Medivac";"Starport";156;2
"Unit";"Marine";"Barracks";167;1
"Unit";"Marine";"Barracks";167;1
"Unit";"Marine";"Barracks";167;1
"Unit";"Marine";"Barracks";167;1
"Unit";"Marine";"Barracks";167;1
"Unit";"Marine";"Barracks";167;1
"Unit";"Marine";"Barracks";167;1
"Unit";"Marine";"Barracks";168;1
"Unit";"Marine";"Barracks";169;1
"Unit";"Marine";"Barracks";172;1
"Unit";"Marine";"Barracks";173;1
"Unit";"Marine";"Barracks";174;1
"Unit";"Marine";"Barracks";175;1
"Unit";"Marine";"Barracks";176;1
"Unit";"Marine";"Barracks";178;1
"Unit";"Marine";"Barracks";178;1
"Unit";"Marine";"Barracks";179;1
"Unit";"Marine";"Barracks";180;1
"Unit";"SCV";"Command Center";181;1
"Unit";"SCV";"Command Center";181;1
"Unit";"SCV";"Command Center";181;1
"Unit";"Medivac";"Starport";170;2
"Unit";"Marine";"Barracks";181;1
"Unit";"Marine";"Barracks";182;1
"Unit";"Marine";"Barracks";183;1
"Unit";"Marine";"Barracks";184;1
"Unit";"Marine";"Barracks";185;1
"Unit";"SCV";"Command Center";190;1
"Unit";"SCV";"Command Center";191;1
"Unit";"SCV";"Command Center";192;1
"Unit";"Marine";"Barracks";186;1
"Unit";"Marine";"Barracks";187;1
"Unit";"Marine";"Barracks";188;1
"Building";"EngineeringBay";NA;186;0
"Unit";"Marine";"Barracks";195;1
"Unit";"Marine";"Barracks";195;1
"Unit";"Marine";"Barracks";196;1
"Unit";"Marine";"Barracks";197;1
"Unit";"Marine";"Barracks";198;1
"Unit";"Medivac";"Starport";193;2
"Unit";"Marine";"Barracks";207;1
"Unit";"Marine";"Barracks";207;1
"Unit";"Marine";"Barracks";207;1
"Building";"Armory";NA;187;0
"Building";"Refinery";NA;213;0
"Building";"Refinery";NA;213;0
"Building";"SupplyDepot";NA;216;0
"Building";"SupplyDepot";NA;216;0
"Building";"SupplyDepot";NA;216;0
"Unit";"SCV";"Command Center";216;1
"Unit";"SCV";"Command Center";216;1
"Unit";"Marine";"Barracks";216;1
"Unit";"Marine";"Barracks";216;1
"Unit";"Marine";"Barracks";216;1
"Unit";"Marine";"Barracks";216;1
"Unit";"Marine";"Barracks";216;1
"Unit";"Marine";"Barracks";216;1
"Unit";"Marine";"Barracks";216;1
"Unit";"Marine";"Barracks";216;1
"Unit";"Marine";"Barracks";216;1
"Building";"SupplyDepot";NA;216;0
"Building";"SupplyDepot";NA;216;0
"Building";"SupplyDepot";NA;216;0
"Unit";"Medivac";"Starport";216;2
"Unit";"Marine";"Barracks";218;1
"Unit";"Marine";"Barracks";218;1
"Unit";"Marine";"Barracks";218;1
"Unit";"Marine";"Barracks";221;1
"Unit";"Marine";"Barracks";227;1
"Unit";"Marine";"Barracks";227;1
"Unit";"Marine";"Barracks";227;1
"Unit";"Marine";"Barracks";227;1
"Unit";"Marine";"Barracks";227;1
"Unit";"Marine";"Barracks";229;1
"Building";"Factory";NA;216;0
"Unit";"Medivac";"Starport";227;2
"Unit";"Marine";"Barracks";238;1
"Unit";"Marine";"Barracks";238;1
"Unit";"Marine";"Barracks";238;1
"Unit";"Marine";"Barracks";238;1
"Unit";"Marine";"Barracks";238;1
"Unit";"Marine";"Barracks";238;1
"Unit";"Marine";"Barracks";239;1
"Unit";"Marine";"Barracks";239;1
"Unit";"Marine";"Barracks";239;1
"Unit";"Marine";"Barracks";241;1
"Unit";"Marine";"Barracks";242;1
"Unit";"Marine";"Barracks";243;1
"Unit";"Marine";"Barracks";244;1
"Unit";"Marine";"Barracks";254;1
"Unit";"Marine";"Barracks";254;1
"Unit";"Marine";"Barracks";254;1
"Unit";"Marine";"Barracks";254;1
"Unit";"Marine";"Barracks";254;1
"Unit";"Marine";"Barracks";254;1
"Unit";"Marine";"Barracks";254;1
"Unit";"Marine";"Barracks";254;1
"Unit";"Marine";"Barracks";254;1
"Unit";"Medivac";"Starport";254;2
"Unit";"Marine";"Barracks";254;1
"Unit";"Marine";"Barracks";255;1
"Unit";"Marine";"Barracks";256;1
"Unit";"Marine";"Barracks";257;1
"Unit";"Marine";"Barracks";258;1
"Unit";"Marine";"Barracks";259;1
"Unit";"Marine";"Barracks";260;1
"Unit";"Marine";"Barracks";261;1
"Unit";"Marine";"Barracks";262;1
"Unit";"Marine";"Barracks";265;1
"Unit";"Marine";"Barracks";266;1
"Unit";"Marine";"Barracks";267;1
"Unit";"Marine";"Barracks";274;1
"Unit";"Marine";"Barracks";274;1
"Unit";"Marine";"Barracks";274;1
"Unit";"Marine";"Barracks";274;1
"Building";"StarportTechLab";NA;274;0
"Unit";"Marine";"Barracks";281;1
"Unit";"Marine";"Barracks";281;1
"Unit";"Marine";"Barracks";281;1
"Unit";"Marine";"Barracks";281;1
"Unit";"Marine";"Barracks";281;1
"Unit";"Marine";"Barracks";281;1
"Unit";"Marine";"Barracks";281;1
"Unit";"Marine";"Barracks";281;1
"Unit";"Marine";"Barracks";281;1
"Unit";"Marine";"Barracks";281;1
"Unit";"Marine";"Barracks";282;1
"Unit";"Marine";"Barracks";283;1
"Unit";"Marine";"Barracks";284;1
"Unit";"Marine";"Barracks";285;1
"Unit";"Marine";"Barracks";286;1
"Unit";"Marine";"Barracks";287;1
"Unit";"Marine";"Barracks";288;1
"Unit";"Marine";"Barracks";289;1
"Unit";"Marine";"Barracks";290;1
"Unit";"Marine";"Barracks";291;1
"Unit";"Marine";"Barracks";292;1
"Unit";"Marine";"Barracks";293;1
"Unit";"Marine";"Barracks";294;1
"Unit";"Marine";"Barracks";295;1
"Unit";"Marine";"Barracks";296;1
"Unit";"Marine";"Barracks";297;1
"Unit";"Marine";"Barracks";298;1
"Unit";"Medivac";"Starport";290;2
"Upgrade";"TerranInfantryWeaponsLevel2";"EngineeringBay";263;0
"Upgrade";"TerranInfantryArmorsLevel2";"EngineeringBay";263;0
"Unit";"Marine";"Barracks";299;1
"Unit";"Marine";"Barracks";300;1
"Unit";"Marine";"Barracks";301;1
"Unit";"Marine";"Barracks";302;1
"Unit";"Marine";"Barracks";303;1
"Unit";"Marine";"Barracks";304;1
"Unit";"Marine";"Barracks";305;1
"Unit";"Marine";"Barracks";307;1
"Unit";"Marine";"Barracks";307;1
"Unit";"Marine";"Barracks";310;1
"Unit";"Marine";"Barracks";311;1
"Unit";"Medivac";"Starport";308;2
"Unit";"Marine";"Barracks";312;1
"Upgrade";"TerranVehicleWeaponsLevel1";"Armory";281;0
"Building";"Refinery";NA;319;0
"Unit";"Marine";"Barracks";319;1
"Unit";"Marine";"Barracks";319;1
"Unit";"Marine";"Barracks";319;1
"Unit";"Marine";"Barracks";319;1
"Unit";"Marine";"Barracks";319;1
"Building";"Refinery";NA;319;0
"Unit";"Marine";"Barracks";319;1
"Building";"FactoryTechLab";NA;319;0
"Unit";"Marine";"Barracks";319;1
"Unit";"Marine";"Barracks";320;1
"Building";"BarracksReactor";NA;332;0
"Building";"SensorTower";NA;332;0
"Building";"SensorTower";NA;332;0
"Building";"SensorTower";NA;332;0
"Building";"SensorTower";NA;332;0
"Building";"SensorTower";NA;332;0
"Building";"SensorTower";NA;332;0
"Building";"SensorTower";NA;332;0
"Building";"SensorTower";NA;332;0
"Building";"SensorTower";NA;332;0
"Building";"SensorTower";NA;332;0
"Building";"Refinery";NA;332;0
"Building";"Refinery";NA;332;0
"Building";"SensorTower";NA;332;0
"Building";"SensorTower";NA;332;0
"Building";"CommandCenter";NA;332;0
"Building";"SensorTower";NA;332;0
"Building";"CommandCenter";NA;332;0
"Building";"CommandCenter";NA;332;0
"Building";"CommandCenter";NA;332;0
"Building";"CommandCenter";NA;332;0
"Building";"CommandCenter";NA;332;0
"Building";"CommandCenter";NA;332;0
"Building";"CommandCenter";NA;332;0
"Building";"CommandCenter";NA;332;0
"Building";"CommandCenter";NA;332;0
"Building";"CommandCenter";NA;332;0
"Building";"CommandCenter";NA;332;0
"Building";"CommandCenter";NA;332;0
"Building";"CommandCenter";NA;332;0
"Building";"CommandCenter";NA;332;0
"Building";"CommandCenter";NA;332;0
"Building";"CommandCenter";NA;332;0
"Building";"CommandCenter";NA;332;0
"Upgrade";"TerranShipWeaponsLevel1";"Armory";332;0
