"Type";"UnitName";"OnBuilding";"TotalSupply";"Supply"
"Unit";"SCV";"Command Center";12;1
"Unit";"SCV";"Command Center";12;1
"Unit";"SCV";"Command Center";13;1
"Building";"SupplyDepot";NA;13;0
"Unit";"SCV";"Command Center";15;1
"Unit";"SCV";"Command Center";15;1
"Building";"Refinery";NA;15;0
"Unit";"SCV";"Command Center";16;1
"Building";"Barracks";NA;15;0
"Unit";"SCV";"Command Center";17;1
"Building";"BarracksReactor";NA;19;0
"Unit";"SCV";"Command Center";19;1
"Building";"SupplyDepot";NA;19;0
"Unit";"Marine";"Barracks";19;1
"Unit";"Marine";"Barracks";19;1
"Unit";"SCV";"Command Center";20;1
"Unit";"Marine";"Barracks";21;1
"Unit";"Marine";"Barracks";22;1
"Unit";"SCV";"Command Center";22;1
"Building";"Refinery";NA;22;0
"Unit";"SCV";"Command Center";25;1
"Building";"CommandCenter";NA;19;0
"Building";"Factory";NA;20;0
"Unit";"Marine";"Barracks";23;1
"Unit";"Marine";"Barracks";24;1
"Unit";"SCV";"Command Center";26;1
"Building";"FactoryTechLab";NA;29;0
"Unit";"Marine";"Barracks";29;1
"Unit";"Marine";"Barracks";29;1
"Unit";"SCV";"Command Center";30;1
"Unit";"SCV";"Command Center";33;1
"Unit";"Marine";"Barracks";33;1
"Unit";"Marine";"Barracks";33;1
"Building";"Starport";NA;29;0
"Unit";"SCV";"Command Center";33;1
"Unit";"SCV";"Command Center";37;1
"Unit";"SCV";"Command Center";37;1
"Building";"SupplyDepot";NA;37;0
"Unit";"SCV";"Command Center";39;1
"Unit";"SCV";"Command Center";39;1
"Unit";"Medivac";"Starport";37;2
"Unit";"Medivac";"Starport";37;2
"Building";"EngineeringBay";NA;39;0
"Unit";"Marine";"Barracks";41;1
"Unit";"SCV";"Command Center";45;1
"Unit";"SCV";"Command Center";45;1
"Building";"FactoryReactor";NA;39;0
"Building";"SupplyDepot";NA;41;0
"Unit";"SCV";"Command Center";46;1
"Unit";"SCV";"Command Center";47;1
"Building";"Barracks";NA;39;0
"Building";"Barracks";NA;39;0
"Unit";"Marine";"Barracks";45;1
"Building";"Refinery";NA;46;0
"Unit";"SCV";"Command Center";48;1
"Building";"SupplyDepot";NA;48;0
"Unit";"SCV";"Command Center";51;1
"Unit";"Marine";"Barracks";50;1
"Building";"StarportReactor";NA;46;0
"Unit";"SCV";"Command Center";51;1
"Unit";"Marine";"Barracks";52;1
"Unit";"Marine";"Barracks";52;1
"Unit";"Marine";"Barracks";52;1
"Unit";"Marine";"Barracks";52;1
"Unit";"SCV";"Command Center";55;1
"Unit";"Marine";"Barracks";53;1
"Building";"SupplyDepot";NA;55;0
"Unit";"SCV";"Command Center";59;1
"Unit";"SCV";"Command Center";59;1
"Unit";"Medivac";"Starport";54;2
"Unit";"Medivac";"Starport";54;2
"Unit";"Marine";"Barracks";60;1
"Unit";"Marine";"Barracks";61;1
"Unit";"Marine";"Barracks";61;1
"Unit";"Marine";"Barracks";61;1
"Unit";"Marine";"Barracks";61;1
"Unit";"SCV";"Command Center";61;1
"Unit";"SCV";"Command Center";62;1
"Building";"SupplyDepot";NA;61;0
"Unit";"SCV";"Command Center";74;1
"Unit";"SCV";"Command Center";74;1
"Upgrade";"Stimpack";"TechLab";48;0
"Unit";"Marine";"Barracks";74;1
"Unit";"Marine";"Barracks";74;1
"Unit";"Marine";"Barracks";74;1
"Unit";"Marine";"Barracks";74;1
"Unit";"Marine";"Barracks";74;1
"Building";"SupplyDepot";NA;74;0
"Upgrade";"TerranInfantryWeaponsLevel1";"EngineeringBay";54;0
"Building";"Barracks";NA;68;0
"Building";"Barracks";NA;68;0
"Unit";"Medivac";"Starport";76;2
"Unit";"Medivac";"Starport";76;2
"Unit";"Marine";"Barracks";76;1
"Unit";"Marine";"Barracks";77;1
"Unit";"Marine";"Barracks";78;1
"Building";"FactoryReactor";NA;74;0
"Unit";"Marine";"Barracks";81;1
"Unit";"Marine";"Barracks";81;1
"Building";"SupplyDepot";NA;81;0
"Building";"SupplyDepot";NA;81;0
"Unit";"Marine";"Barracks";85;1
"Unit";"Marine";"Barracks";90;1
"Unit";"Marine";"Barracks";90;1
"Unit";"Marine";"Barracks";90;1
"Unit";"Marine";"Barracks";90;1
"Unit";"Marine";"Barracks";90;1
"Unit";"Marine";"Barracks";90;1
"Building";"BarracksReactor";NA;88;0
"Unit";"Marine";"Barracks";91;1
"Unit";"Marine";"Barracks";91;1
"Unit";"Marine";"Barracks";92;1
"Unit";"Marine";"Barracks";93;1
"Unit";"Medivac";"Starport";90;2
"Unit";"Medivac";"Starport";90;2
"Unit";"Marine";"Barracks";95;1
"Unit";"Marine";"Barracks";95;1
"Building";"SupplyDepot";NA;97;0
"Building";"SupplyDepot";NA;97;0
"Unit";"Marine";"Barracks";105;1
"Unit";"Marine";"Barracks";105;1
"Unit";"Marine";"Barracks";105;1
"Unit";"Marine";"Barracks";105;1
"Unit";"Marine";"Barracks";105;1
"Unit";"Marine";"Barracks";105;1
"Unit";"Marine";"Barracks";107;1
"Unit";"Marine";"Barracks";107;1
"Unit";"Marine";"Barracks";107;1
"Unit";"SCV";"Command Center";113;1
"Unit";"SCV";"Command Center";113;1
"Unit";"Marine";"Barracks";107;1
"Unit";"Marine";"Barracks";115;1
"Unit";"Marine";"Barracks";115;1
"Unit";"Marine";"Barracks";116;1
"Unit";"SCV";"Command Center";116;1
"Unit";"Marine";"Barracks";116;1
"Unit";"SCV";"Command Center";117;1
"Unit";"Marine";"Barracks";116;1
"Unit";"Marine";"Barracks";116;1
"Unit";"SCV";"Command Center";122;1
"Unit";"SCV";"Command Center";124;1
"Unit";"SCV";"Command Center";127;1
"Unit";"SCV";"Command Center";128;1
"Upgrade";"TerranInfantryArmorsLevel1";"EngineeringBay";97;0
"Unit";"Marine";"Barracks";129;1
"Unit";"Marine";"Barracks";129;1
"Unit";"Marine";"Barracks";129;1
"Unit";"SCV";"Command Center";131;1
"Unit";"SCV";"Command Center";131;1
"Building";"SensorTower";NA;129;0
"Unit";"Marine";"Barracks";129;1
"Unit";"Marine";"Barracks";129;1
"Unit";"Marine";"Barracks";129;1
"Building";"EngineeringBay";NA;129;0
"Unit";"Marine";"Barracks";129;1
"Unit";"Marine";"Barracks";140;1
"Unit";"Marine";"Barracks";140;1
"Unit";"Marine";"Barracks";140;1
"Unit";"Marine";"Barracks";140;1
"Unit";"Marine";"Barracks";140;1
"Unit";"Marine";"Barracks";140;1
"Unit";"Marine";"Barracks";140;1
"Unit";"Marine";"Barracks";140;1
"Unit";"Marine";"Barracks";140;1
"Building";"Armory";NA;129;0
"Unit";"Marine";"Barracks";140;1
"Unit";"Marine";"Barracks";141;1
"Unit";"Marine";"Barracks";142;1
"Unit";"Marine";"Barracks";143;1
"Unit";"Marine";"Barracks";144;1
"Unit";"Marine";"Barracks";145;1
"Unit";"Marine";"Barracks";146;1
"Unit";"Marine";"Barracks";147;1
"Unit";"Marine";"Barracks";149;1
"Unit";"Medivac";"Starport";149;2
"Unit";"Medivac";"Starport";149;2
"Building";"CommandCenter";NA;129;0
"Unit";"Marine";"Barracks";149;1
"Unit";"Marine";"Barracks";150;1
"Unit";"Marine";"Barracks";151;1
"Unit";"Marine";"Barracks";152;1
"Unit";"Marine";"Barracks";153;1
"Unit";"Marine";"Barracks";167;1
"Unit";"Marine";"Barracks";167;1
