"type";"unit_name";"on_building";"total_supply";"supply"
"Building";"Refinery";NA;14;0
"Building";"Refinery";NA;16;0
"Building";"Barracks";NA;15;0
"Unit";"Reaper";"Barracks";19;1
"Building";"Factory";NA;19;0
"Unit";"Marine";"Barracks";19;1
"Unit";"Cyclone";"Factory";23;3
"Building";"Starport";NA;21;0
"Unit";"Medivac";"Starport";28;2
"Unit";"Cyclone";"Factory";28;3
"Building";"BarracksTechLab";NA;29;0
"Unit";"Cyclone";"Factory";35;3
