"Type";"UnitName";"OnBuilding";"TotalSupply";"Supply"
"Unit";"SCV";"Command Center";12;1
"Unit";"SCV";"Command Center";12;1
"Unit";"SCV";"Command Center";13;1
"Building";"SupplyDepot";NA;13;0
"Building";"Refinery";NA;14;0
"Unit";"SCV";"Command Center";15;1
"Unit";"SCV";"Command Center";15;1
"Unit";"SCV";"Command Center";16;1
"Unit";"SCV";"Command Center";17;1
"Building";"Barracks";NA;15;0
"Unit";"Reaper";"Barracks";19;1
"Unit";"SCV";"Command Center";19;1
"Unit";"Marine";"Barracks";20;1
"Unit";"SCV";"Command Center";21;1
"Building";"SupplyDepot";NA;20;0
"Building";"Factory";NA;19;0
"Unit";"SCV";"Command Center";23;1
"Building";"Refinery";NA;22;0
"Unit";"SCV";"Command Center";23;1
"Building";"CommandCenter";NA;19;0
"Unit";"SCV";"Command Center";24;1
"Building";"BarracksReactor";NA;23;0
"Unit";"Cyclone";"Factory";24;3
"Unit";"SCV";"Command Center";25;1
"Unit";"SCV";"Command Center";30;1
"Unit";"SCV";"Command Center";30;1
"Building";"Starport";NA;26;0
"Building";"Bunker";NA;25;0
"Unit";"Marine";"Barracks";30;1
"Unit";"Marine";"Barracks";30;1
"Unit";"SCV";"Command Center";30;1
"Unit";"SCV";"Command Center";31;1
"Unit";"Cyclone";"Factory";30;3
"Building";"SupplyDepot";NA;32;0
"Unit";"SCV";"Command Center";34;1
"Unit";"SCV";"Command Center";36;1
"Unit";"Marine";"Barracks";32;1
"Unit";"Marine";"Barracks";33;1
"Unit";"SCV";"Command Center";39;1
"Unit";"Medivac";"Starport";32;2
"Unit";"SCV";"Command Center";40;1
"Building";"FactoryTechLab";NA;39;0
"Building";"SupplyDepot";NA;39;0
"Unit";"SCV";"Command Center";43;1
"Unit";"SCV";"Command Center";46;1
"Unit";"Marine";"Barracks";43;1
"Unit";"Marine";"Barracks";43;1
"Unit";"SCV";"Command Center";47;1
"Unit";"SCV";"Command Center";48;1
"Building";"FactoryTechLab";NA;50;0
"Unit";"SCV";"Command Center";51;1
"Unit";"SCV";"Command Center";52;1
"Unit";"Marine";"Barracks";51;1
"Unit";"Marine";"Barracks";51;1
"Building";"StarportReactor";NA;47;0
"Building";"SupplyDepot";NA;52;0
"Building";"Barracks";NA;47;0
"Building";"Barracks";NA;48;0
"Unit";"Marine";"Barracks";57;1
"Unit";"Marine";"Barracks";57;1
"Unit";"Marine";"Barracks";57;1
"Unit";"SCV";"Command Center";57;1
"Unit";"SCV";"Command Center";57;1
"Building";"StarportReactor";NA;57;0
"Unit";"Marine";"Barracks";57;1
"Unit";"SCV";"Command Center";60;1
"Unit";"SCV";"Command Center";61;1
"Unit";"Marine";"Barracks";57;1
"Unit";"Marine";"Barracks";58;1
"Unit";"Marine";"Barracks";59;1
"Unit";"SCV";"Command Center";63;1
"Unit";"SCV";"Command Center";64;1
"Unit";"Marine";"Barracks";62;1
"Unit";"Marine";"Barracks";65;1
"Unit";"Marine";"Barracks";66;1
"Unit";"Marine";"Barracks";67;1
"Building";"Barracks";NA;57;0
"Building";"Barracks";NA;57;0
"Unit";"SCV";"Command Center";68;1
"Unit";"SCV";"Command Center";69;1
"Building";"Refinery";NA;68;0
"Building";"Refinery";NA;68;0
"Unit";"Medivac";"Starport";65;2
"Unit";"Medivac";"Starport";65;2
"Unit";"SCV";"Command Center";74;1
"Unit";"SCV";"Command Center";75;1
"Unit";"Marine";"Barracks";71;1
"Unit";"Marine";"Barracks";72;1
"Building";"SupplyDepot";NA;76;0
"Building";"SupplyDepot";NA;76;0
"Unit";"SCV";"Command Center";84;1
"Unit";"SCV";"Command Center";84;1
"Building";"BarracksReactor";NA;71;0
"Unit";"Marine";"Barracks";84;1
"Unit";"Marine";"Barracks";84;1
"Unit";"Marine";"Barracks";84;1
"Unit";"SCV";"Command Center";89;1
"Unit";"SCV";"Command Center";89;1
"Unit";"Marine";"Barracks";86;1
"Unit";"Marine";"Barracks";86;1
"Unit";"Marine";"Barracks";86;1
"Unit";"Marine";"Barracks";86;1
"Unit";"Marine";"Barracks";86;1
"Building";"BarracksReactor";NA;84;0
"Unit";"SCV";"Command Center";89;1
"Building";"EngineeringBay";NA;89;0
"Building";"EngineeringBay";NA;89;0
"Unit";"Marine";"Barracks";96;1
"Unit";"Marine";"Barracks";96;1
"Unit";"Marine";"Barracks";96;1
"Unit";"Marine";"Barracks";96;1
"Unit";"Marine";"Barracks";96;1
"Unit";"Marine";"Barracks";96;1
"Unit";"Marine";"Barracks";96;1
"Unit";"Marine";"Barracks";97;1
"Unit";"Marine";"Barracks";97;1
"Building";"SupplyDepot";NA;97;0
"Unit";"Medivac";"Starport";97;2
"Unit";"Marine";"Barracks";104;1
"Unit";"Marine";"Barracks";104;1
"Unit";"Marine";"Barracks";104;1
"Unit";"Marine";"Barracks";106;1
"Unit";"Marine";"Barracks";106;1
"Unit";"Marine";"Barracks";106;1
"Unit";"Marine";"Barracks";108;1
"Unit";"Marine";"Barracks";108;1
"Unit";"Marine";"Barracks";110;1
"Unit";"Marine";"Barracks";111;1
"Unit";"Marine";"Barracks";114;1
"Unit";"Marine";"Barracks";114;1
"Unit";"Marine";"Barracks";114;1
"Unit";"Marine";"Barracks";114;1
"Building";"SupplyDepot";NA;111;0
"Upgrade";"Stimpack";"TechLab";96;0
"Unit";"Marine";"Barracks";118;1
"Unit";"Marine";"Barracks";122;1
"Unit";"Marine";"Barracks";122;1
"Unit";"Marine";"Barracks";122;1
"Unit";"Marine";"Barracks";122;1
"Unit";"Marine";"Barracks";122;1
"Unit";"Marine";"Barracks";122;1
"Unit";"Marine";"Barracks";122;1
"Unit";"Marine";"Barracks";122;1
"Unit";"Marine";"Barracks";122;1
"Unit";"Marine";"Barracks";126;1
"Upgrade";"TerranInfantryWeaponsLevel1";"EngineeringBay";111;0
"Unit";"Marine";"Barracks";132;1
"Upgrade";"TerranInfantryArmorsLevel1";"EngineeringBay";111;0
"Unit";"Marine";"Barracks";133;1
"Unit";"Marine";"Barracks";133;1
"Unit";"Marine";"Barracks";133;1
"Unit";"Marine";"Barracks";133;1
"Unit";"Marine";"Barracks";133;1
"Building";"SupplyDepot";NA;134;0
"Building";"SupplyDepot";NA;134;0
"Building";"SupplyDepot";NA;134;0
"Building";"CommandCenter";NA;122;0
"Unit";"Marine";"Barracks";139;1
"Unit";"Marine";"Barracks";139;1
"Unit";"Marine";"Barracks";139;1
"Unit";"Marine";"Barracks";139;1
"Unit";"Marine";"Barracks";139;1
"Unit";"Marine";"Barracks";139;1
"Unit";"Marine";"Barracks";140;1
"Unit";"Marine";"Barracks";141;1
"Unit";"Marine";"Barracks";147;1
"Unit";"Marine";"Barracks";147;1
"Building";"Factory";NA;144;0
"Unit";"Marine";"Barracks";147;1
"Unit";"Marine";"Barracks";148;1
"Building";"FactoryTechLab";NA;151;0
"Building";"Starport";NA;151;0
"Building";"Barracks";NA;151;0
"Building";"Barracks";NA;151;0
"Building";"BarracksTechLab";NA;151;0
"Unit";"Marine";"Barracks";151;1
"Unit";"Marine";"Barracks";151;1
"Unit";"SCV";"Command Center";153;1
"Unit";"SCV";"Command Center";153;1
"Unit";"Marine";"Barracks";153;1
"Unit";"Marine";"Barracks";153;1
"Unit";"SCV";"Command Center";157;1
"Unit";"SCV";"Command Center";157;1
"Unit";"Marine";"Barracks";157;1
"Building";"StarportTechLab";NA;159;0
"Unit";"Marine";"Barracks";160;1
"Unit";"Marine";"Barracks";160;1
"Unit";"SCV";"Command Center";162;1
"Unit";"Marine";"Barracks";160;1
"Unit";"Marine";"Barracks";161;1
"Unit";"SCV";"Command Center";162;1
"Unit";"Marine";"Barracks";163;1
"Unit";"Marine";"Barracks";164;1
"Unit";"SCV";"Command Center";166;1
"Unit";"Raven";"Starport";160;2
"Unit";"SCV";"Command Center";166;1
"Unit";"Marine";"Barracks";167;1
"Unit";"Marine";"Barracks";172;1
"Building";"BarracksReactor";NA;168;0
"Unit";"SCV";"Command Center";173;1
"Unit";"SCV";"Command Center";173;1
"Building";"Barracks";NA;168;0
"Unit";"Marine";"Barracks";173;1
"Unit";"Raven";"Starport";172;2
"Unit";"SCV";"Command Center";174;1
"Unit";"SCV";"Command Center";175;1
"Building";"Refinery";NA;174;0
"Unit";"Marine";"Barracks";176;1
"Unit";"Marine";"Barracks";176;1
"Unit";"Marine";"Barracks";176;1
"Unit";"SCV";"Command Center";181;1
"Unit";"SCV";"Command Center";181;1
"Unit";"Marine";"Barracks";183;1
"Unit";"Marine";"Barracks";183;1
"Unit";"Marine";"Barracks";183;1
"Unit";"Marine";"Barracks";183;1
"Unit";"SCV";"Command Center";186;1
"Unit";"Raven";"Starport";177;2
"Unit";"Marine";"Barracks";188;1
"Unit";"Marine";"Barracks";189;1
"Unit";"SCV";"Command Center";191;1
"Unit";"SCV";"Command Center";191;1
"Unit";"Marine";"Barracks";193;1
"Unit";"SCV";"Command Center";197;1
"Unit";"SCV";"Command Center";197;1
"Unit";"Raven";"Starport";191;2
"Unit";"SCV";"Command Center";200;1
"Unit";"SCV";"Command Center";200;1
"Unit";"SCV";"Command Center";202;1
"Unit";"SCV";"Command Center";203;1
"Unit";"Marine";"Barracks";203;1
"Unit";"Marine";"Barracks";203;1
"Unit";"Marine";"Barracks";203;1
"Unit";"SCV";"Command Center";204;1
"Unit";"SCV";"Command Center";206;1
"Unit";"SCV";"Command Center";209;1
"Building";"Refinery";NA;209;0
"Unit";"SCV";"Command Center";211;1
"Unit";"SCV";"Command Center";211;1
"Unit";"SCV";"Command Center";212;1
"Unit";"Raven";"Starport";206;2
"Unit";"SCV";"Command Center";213;1
"Unit";"Marine";"Barracks";214;1
"Unit";"Marine";"Barracks";214;1
"Unit";"Marine";"Barracks";214;1
"Unit";"Marine";"Barracks";214;1
"Unit";"Marine";"Barracks";218;1
"Unit";"SCV";"Command Center";222;1
"Unit";"Marine";"Barracks";222;1
"Unit";"Marine";"Barracks";222;1
"Unit";"Marine";"Barracks";222;1
"Unit";"SCV";"Command Center";222;1
"Unit";"SCV";"Command Center";223;1
"Unit";"Marine";"Barracks";222;1
"Building";"EngineeringBay";NA;222;0
"Unit";"Marine";"Barracks";224;1
"Unit";"Marine";"Barracks";226;1
"Unit";"Marine";"Barracks";229;1
"Unit";"SCV";"Command Center";232;1
"Unit";"SCV";"Command Center";232;1
"Building";"Barracks";NA;222;0
"Unit";"Marine";"Barracks";230;1
"Building";"Armory";NA;222;0
"Building";"Barracks";NA;222;0
"Unit";"Marine";"Barracks";232;1
"Building";"BarracksReactor";NA;228;0
"Unit";"Raven";"Starport";228;2
"Unit";"Marine";"Barracks";232;1
"Unit";"Marine";"Barracks";235;1
"Unit";"Marine";"Barracks";236;1
"Unit";"Marine";"Barracks";237;1
"Unit";"Marine";"Barracks";237;1
"Unit";"Marine";"Barracks";242;1
"Unit";"Marine";"Barracks";242;1
"Unit";"Marine";"Barracks";242;1
"Building";"SupplyDepot";NA;244;0
"Building";"SupplyDepot";NA;244;0
"Unit";"Raven";"Starport";237;2
"Unit";"Marine";"Barracks";247;1
"Unit";"Marine";"Barracks";247;1
"Unit";"Marine";"Barracks";247;1
"Unit";"Marine";"Barracks";247;1
"Unit";"Marine";"Barracks";247;1
"Unit";"Marine";"Barracks";247;1
"Unit";"Marine";"Barracks";247;1
"Unit";"Marine";"Barracks";249;1
"Unit";"Marine";"Barracks";250;1
"Unit";"Marine";"Barracks";250;1
"Unit";"Marine";"Barracks";250;1
"Unit";"Marine";"Barracks";250;1
"Unit";"Marine";"Barracks";250;1
"Unit";"Marine";"Barracks";250;1
"Building";"CommandCenter";NA;242;0
"Unit";"Marine";"Barracks";256;1
"Unit";"Marine";"Barracks";257;1
"Building";"SupplyDepot";NA;256;0
"Building";"SupplyDepot";NA;257;0
"Building";"SupplyDepot";NA;257;0
"Unit";"Marine";"Barracks";263;1
"Unit";"Marine";"Barracks";263;1
"Unit";"Marine";"Barracks";263;1
"Unit";"Marine";"Barracks";263;1
"Unit";"Marine";"Barracks";263;1
"Unit";"Marine";"Barracks";263;1
"Unit";"Marine";"Barracks";264;1
"Unit";"Raven";"Starport";256;2
"Unit";"Marine";"Barracks";265;1
"Unit";"Marine";"Barracks";265;1
"Unit";"Marine";"Barracks";270;1
"Unit";"Marine";"Barracks";270;1
"Unit";"Marine";"Barracks";270;1
"Unit";"Marine";"Barracks";270;1
"Unit";"Marine";"Barracks";271;1
"Unit";"SCV";"Command Center";274;1
"Unit";"SCV";"Command Center";274;1
"Unit";"SCV";"Command Center";274;1
"Unit";"Marine";"Barracks";274;1
"Unit";"Marine";"Barracks";274;1
"Unit";"Marine";"Barracks";280;1
"Unit";"Marine";"Barracks";280;1
"Unit";"Marine";"Barracks";280;1
"Unit";"Marine";"Barracks";280;1
"Unit";"Marine";"Barracks";280;1
"Unit";"Raven";"Starport";272;2
"Unit";"Marine";"Barracks";293;1
"Unit";"Marine";"Barracks";293;1
"Unit";"Marine";"Barracks";293;1
"Unit";"Marine";"Barracks";293;1
"Unit";"Marine";"Barracks";293;1
"Unit";"Marine";"Barracks";293;1
"Unit";"Marine";"Barracks";293;1
"Unit";"Raven";"Starport";291;2
"Unit";"Marine";"Barracks";293;1
"Unit";"Marine";"Barracks";294;1
"Unit";"Marine";"Barracks";294;1
"Unit";"Marine";"Barracks";298;1
"Unit";"Marine";"Barracks";300;1
"Unit";"Marine";"Barracks";300;1
"Unit";"Marine";"Barracks";300;1
"Unit";"Medivac";"Starport";300;2
"Building";"Refinery";NA;309;0
"Building";"Starport";NA;309;0
