"type";"unit_name";"on_building";"total_supply";"supply"
"Building";"Barracks";NA;15;0
"Unit";"Marine";"Barracks";18;1
"Unit";"Marine";"Barracks";20;1
"Building";"Bunker";NA;19;0
"Building";"Refinery";NA;20;0
"Unit";"Marine";"Barracks";21;1
"Building";"Refinery";NA;20;0
"Building";"CommandCenter";NA;17;0
"Unit";"Marine";"Barracks";24;1
"Building";"Refinery";NA;24;0
"Building";"Refinery";NA;25;0
"Building";"Factory";NA;26;0
"Building";"BarracksReactor";NA;27;0
"Building";"Factory";NA;29;0
"Building";"Starport";NA;33;0
"Building";"FactoryTechLab";NA;36;0
"Unit";"Cyclone";"Factory";35;3
"Building";"BarracksReactor";NA;34;0
"Unit";"Cyclone";"Factory";39;3
"Unit";"Raven";"Starport";42;2
"Unit";"Cyclone";"Factory";47;3
"Unit";"Cyclone";"Factory";47;3
"Unit";"Cyclone";"Factory";51;3
"Unit";"Cyclone";"Factory";62;3
"Unit";"Cyclone";"Factory";62;3
"Building";"FactoryTechLab";NA;62;0
"Unit";"Raven";"Starport";62;2
"Unit";"Cyclone";"Factory";72;3
"Unit";"Cyclone";"Factory";72;3
"Unit";"Raven";"Starport";74;2
"Unit";"Hellion";"Factory";82;2
"Unit";"Hellion";"Factory";82;2
"Building";"CommandCenter";NA;67;0
"Building";"EngineeringBay";NA;82;0
"Building";"Factory";NA;84;0
"Building";"Factory";NA;84;0
"Building";"Factory";NA;84;0
"Building";"MissileTurret";NA;94;0
"Building";"MissileTurret";NA;94;0
"Building";"MissileTurret";NA;94;0
"Building";"Refinery";NA;94;0
"Building";"Refinery";NA;94;0
"Building";"FactoryTechLab";NA;98;0
"Building";"FactoryTechLab";NA;98;0
"Building";"FactoryTechLab";NA;98;0
"Building";"CommandCenter";NA;94;0
"Building";"CommandCenter";NA;94;0
"Building";"Starport";NA;99;0
"Building";"Starport";NA;99;0
"Building";"Armory";NA;99;0
"Building";"Armory";NA;99;0
"Building";"Refinery";NA;105;0
"Building";"StarportReactor";NA;102;0
"Building";"StarportReactor";NA;102;0
"Building";"Refinery";NA;105;0
"Building";"Refinery";NA;105;0
"Building";"Refinery";NA;108;0
"Unit";"Hellion";"Factory";109;2
"Building";"SensorTower";NA;117;0
"Unit";"Liberator";"Starport";131;3
"Unit";"Liberator";"Starport";131;3
"Building";"MissileTurret";NA;133;0
"Building";"MissileTurret";NA;133;0
"Building";"Refinery";NA;133;0
"Building";"MissileTurret";NA;141;0
"Building";"MissileTurret";NA;141;0
"Building";"Bunker";NA;141;0
"Building";"SensorTower";NA;141;0
"Building";"MissileTurret";NA;141;0
"Building";"MissileTurret";NA;141;0
"Building";"MissileTurret";NA;141;0
