"type";"unit_name";"on_building";"total_supply";"supply"
"Building";"Refinery";NA;15;0
"Building";"Barracks";NA;15;0
"Unit";"Reaper";"Barracks";19;1
"Building";"BarracksTechLab";NA;20;0
"Building";"Refinery";NA;21;0
"Unit";"Marine";"Barracks";21;1
"Building";"Factory";NA;21;0
"Unit";"Marine";"Barracks";24;1
"Building";"CommandCenter";NA;20;0
"Unit";"Hellion";"Factory";26;2
"Unit";"Marauder";"Barracks";26;2
"Building";"Barracks";NA;24;0
"Unit";"Marine";"Barracks";32;1
"Building";"FactoryTechLab";NA;32;0
"Unit";"Marine";"Barracks";33;1
"Unit";"Marauder";"Barracks";35;2
"Unit";"Marine";"Barracks";35;1
"Building";"Starport";NA;33;0
"Upgrade";"Stimpack";"TechLab";28;0
"Unit";"Medivac";"Starport";44;2
"Building";"BarracksReactor";NA;44;0
"Unit";"Marauder";"Barracks";46;2
"Building";"EngineeringBay";NA;46;0
"Building";"Barracks";NA;44;0
"Unit";"Marine";"Barracks";52;1
"Unit";"Marine";"Barracks";52;1
"Unit";"Marine";"Barracks";52;1
"Unit";"Medivac";"Starport";50;2
"Building";"Refinery";NA;54;0
"Building";"Refinery";NA;54;0
"Unit";"Marine";"Barracks";59;1
"Unit";"Marine";"Barracks";59;1
"Unit";"Marine";"Barracks";59;1
"Building";"BarracksReactor";NA;59;0
"Unit";"Marine";"Barracks";66;1
"Unit";"Marine";"Barracks";66;1
"Unit";"Marauder";"Barracks";66;2
"Building";"Barracks";NA;59;0
"Building";"Barracks";NA;59;0
"Unit";"Marine";"Barracks";71;1
"Unit";"Marine";"Barracks";71;1
"Unit";"Marine";"Barracks";72;1
"Building";"CommandCenter";NA;54;0
"Unit";"Marauder";"Barracks";71;2
"Building";"BarracksReactor";NA;73;0
"Building";"BarracksReactor";NA;73;0
"Unit";"Marine";"Barracks";79;1
"Unit";"Marine";"Barracks";79;1
"Unit";"Marine";"Barracks";79;1
"Unit";"Marine";"Barracks";79;1
"Unit";"Marauder";"Barracks";79;2
"Unit";"Medivac";"Starport";79;2
"Building";"SensorTower";NA;79;0
"Unit";"Marine";"Barracks";85;1
"Unit";"Marine";"Barracks";85;1
"Unit";"Marine";"Barracks";85;1
"Unit";"Marine";"Barracks";85;1
"Unit";"Marine";"Barracks";85;1
"Unit";"Marine";"Barracks";85;1
"Unit";"Marauder";"Barracks";85;2
"Building";"EngineeringBay";NA;89;0
"Unit";"Marine";"Barracks";97;1
"Unit";"Marine";"Barracks";97;1
"Unit";"Marauder";"Barracks";97;2
"Unit";"Marine";"Barracks";102;1
"Unit";"Marine";"Barracks";102;1
"Unit";"Marine";"Barracks";102;1
"Unit";"Marine";"Barracks";102;1
"Building";"Armory";NA;89;0
"Unit";"Marine";"Barracks";104;1
"Unit";"Marine";"Barracks";104;1
"Unit";"Medivac";"Starport";104;2
"Unit";"Medivac";"Starport";104;2
"Unit";"Marauder";"Barracks";106;2
"Building";"BarracksReactor";NA;102;0
"Unit";"Marine";"Barracks";114;1
"Unit";"Marine";"Barracks";114;1
"Unit";"Marine";"Barracks";114;1
"Unit";"Marine";"Barracks";114;1
"Unit";"Marine";"Barracks";114;1
"Unit";"Marine";"Barracks";114;1
"Upgrade";"TerranInfantryWeaponsLevel1";"EngineeringBay";89;0
"Unit";"Marauder";"Barracks";118;2
"Unit";"Medivac";"Starport";120;2
"Unit";"Marine";"Barracks";120;1
"Unit";"Medivac";"Starport";120;2
"Unit";"Marine";"Barracks";134;1
"Unit";"Marine";"Barracks";134;1
"Unit";"Marine";"Barracks";134;1
"Unit";"Marine";"Barracks";134;1
"Unit";"Marine";"Barracks";134;1
"Unit";"Marine";"Barracks";134;1
"Unit";"Marauder";"Barracks";134;2
"Unit";"Marine";"Barracks";140;1
"Unit";"Marine";"Barracks";140;1
"Unit";"Marine";"Barracks";140;1
"Unit";"Marine";"Barracks";140;1
"Unit";"Marine";"Barracks";140;1
"Unit";"Marine";"Barracks";140;1
"Unit";"Marine";"Barracks";140;1
"Unit";"Marauder";"Barracks";140;2
"Upgrade";"TerranInfantryArmorsLevel1";"EngineeringBay";120;0
"Unit";"Marine";"Barracks";151;1
"Unit";"Marauder";"Barracks";149;2
"Unit";"Marine";"Barracks";151;1
"Unit";"Marine";"Barracks";151;1
"Unit";"Marine";"Barracks";151;1
"Unit";"Marine";"Barracks";151;1
"Unit";"Marine";"Barracks";151;1
"Unit";"Marine";"Barracks";151;1
"Unit";"Marine";"Barracks";151;1
"Unit";"Marine";"Barracks";151;1
"Unit";"Marine";"Barracks";152;1
"Unit";"Marine";"Barracks";154;1
