"type";"unit_name";"on_building";"total_supply";"supply"
"Building";"Barracks";NA;15;0
"Unit";"Marine";"Barracks";18;1
"Unit";"Marine";"Barracks";18;1
"Building";"Bunker";NA;18;0
"Building";"Refinery";NA;18;0
"Building";"Refinery";NA;19;0
"Unit";"Marine";"Barracks";19;1
"Building";"CommandCenter";NA;18;0
"Unit";"Marine";"Barracks";23;1
"Building";"Factory";NA;23;0
"Building";"BarracksReactor";NA;27;0
"Building";"Refinery";NA;29;0
"Building";"Refinery";NA;29;0
"Unit";"Cyclone";"Factory";31;3
"Building";"Starport";NA;29;0
"Building";"StarportTechLab";NA;38;0
"Building";"BarracksReactor";NA;39;0
"Building";"Factory";NA;38;0
"Unit";"Cyclone";"Factory";43;3
"Unit";"Raven";"Starport";41;2
"Unit";"Cyclone";"Factory";44;3
"Unit";"Cyclone";"Factory";50;3
"Unit";"Cyclone";"Factory";50;3
"Unit";"Hellion";"Factory";56;2
"Unit";"Hellion";"Factory";56;2
"Unit";"Raven";"Starport";56;2
"Unit";"Cyclone";"Factory";68;3
"Unit";"Cyclone";"Factory";68;3
"Unit";"Cyclone";"Factory";70;3
"Unit";"Cyclone";"Factory";70;3
"Unit";"Hellion";"Factory";82;2
"Unit";"Hellion";"Factory";82;2
"Unit";"Cyclone";"Factory";82;3
"Unit";"Cyclone";"Factory";82;3
"Unit";"Hellion";"Factory";88;2
"Unit";"Hellion";"Factory";94;2
"Unit";"Hellion";"Factory";96;2
"Unit";"Raven";"Starport";84;2
"Unit";"Cyclone";"Factory";96;3
"Unit";"Cyclone";"Factory";111;3
"Unit";"Cyclone";"Factory";111;3
"Unit";"Cyclone";"Factory";111;3
"Building";"CommandCenter";NA;96;0
"Unit";"Cyclone";"Factory";112;3
