"Type";"UnitName";"OnBuilding";"TotalSupply";"Supply"
"Unit";"SCV";"Command Center";12;1
"Unit";"SCV";"Command Center";12;1
"Unit";"SCV";"Command Center";13;1
"Building";"SupplyDepot";NA;13;0
"Building";"Refinery";NA;14;0
"Unit";"SCV";"Command Center";15;1
"Unit";"SCV";"Command Center";15;1
"Unit";"SCV";"Command Center";16;1
"Unit";"SCV";"Command Center";17;1
"Building";"Barracks";NA;15;0
"Unit";"Reaper";"Barracks";19;1
"Unit";"SCV";"Command Center";19;1
"Building";"Refinery";NA;20;0
"Unit";"SCV";"Command Center";21;1
"Building";"Factory";NA;19;0
"Unit";"Reaper";"Barracks";20;1
"Building";"SupplyDepot";NA;21;0
"Unit";"SCV";"Command Center";22;1
"Unit";"SCV";"Command Center";24;1
"Building";"CommandCenter";NA;19;0
"Unit";"Cyclone";"Factory";24;3
"Unit";"SCV";"Command Center";25;1
"Unit";"Marine";"Barracks";25;1
"Unit";"SCV";"Command Center";28;1
"Unit";"SCV";"Command Center";30;1
"Unit";"Marine";"Barracks";31;1
"Unit";"SCV";"Command Center";31;1
"Unit";"Hellion";"Factory";31;2
"Unit";"SCV";"Command Center";31;1
"Unit";"SCV";"Command Center";33;1
"Unit";"SCV";"Command Center";36;1
"Building";"BarracksTechLab";NA;33;0
"Building";"Starport";NA;31;0
"Unit";"SCV";"Command Center";37;1
"Unit";"SCV";"Command Center";39;1
"Unit";"SCV";"Command Center";40;1
"Building";"SupplyDepot";NA;39;0
"Unit";"Cyclone";"Factory";39;3
"Unit";"SCV";"Command Center";40;1
"Unit";"SCV";"Command Center";41;1
"Unit";"Marine";"Barracks";41;1
"Building";"Barracks";NA;37;0
"Building";"Barracks";NA;37;0
"Unit";"SCV";"Command Center";47;1
"Unit";"SCV";"Command Center";47;1
"Unit";"Liberator";"Starport";40;3
"Unit";"SCV";"Command Center";48;1
"Unit";"SCV";"Command Center";49;1
"Unit";"Marine";"Barracks";48;1
"Unit";"Marine";"Barracks";48;1
"Unit";"Marine";"Barracks";48;1
"Unit";"SCV";"Command Center";53;1
"Unit";"SCV";"Command Center";54;1
"Building";"Refinery";NA;50;0
"Unit";"Marine";"Barracks";55;1
"Unit";"Marine";"Barracks";56;1
"Unit";"Marine";"Barracks";57;1
"Unit";"SCV";"Command Center";58;1
"Unit";"Marine";"Barracks";60;1
"Unit";"SCV";"Command Center";64;1
"Unit";"SCV";"Command Center";64;1
"Unit";"Marine";"Barracks";63;1
"Unit";"Marine";"Barracks";63;1
"Unit";"SCV";"Command Center";69;1
"Unit";"SCV";"Command Center";69;1
"Unit";"Marine";"Barracks";64;1
"Unit";"Marine";"Barracks";69;1
"Building";"StarportReactor";NA;63;0
"Building";"FactoryReactor";NA;63;0
"Unit";"SCV";"Command Center";69;1
"Unit";"SCV";"Command Center";70;1
"Unit";"SCV";"Command Center";73;1
"Unit";"SCV";"Command Center";74;1
"Upgrade";"Stimpack";"TechLab";50;0
"Building";"SupplyDepot";NA;73;0
"Building";"SupplyDepot";NA;73;0
"Building";"EngineeringBay";NA;73;0
"Building";"FactoryTechLab";NA;77;0
"Unit";"SCV";"Command Center";77;1
"Unit";"SCV";"Command Center";77;1
"Unit";"Marine";"Barracks";77;1
"Unit";"SCV";"Command Center";77;1
"Unit";"SCV";"Command Center";77;1
"Building";"StarportReactor";NA;75;0
"Unit";"Marine";"Barracks";77;1
"Unit";"Marine";"Barracks";77;1
"Unit";"Marine";"Barracks";77;1
"Unit";"Marine";"Barracks";77;1
"Building";"SupplyDepot";NA;77;0
"Unit";"SCV";"Command Center";80;1
"Unit";"SCV";"Command Center";80;1
"Unit";"SCV";"Command Center";86;1
"Unit";"SCV";"Command Center";86;1
"Unit";"Medivac";"Starport";82;2
"Building";"SupplyDepot";NA;86;0
"Building";"SupplyDepot";NA;86;0
"Unit";"SCV";"Command Center";88;1
"Unit";"SCV";"Command Center";88;1
"Unit";"Marine";"Barracks";90;1
"Unit";"SCV";"Command Center";92;1
"Unit";"SCV";"Command Center";92;1
"Unit";"Marine";"Barracks";94;1
"Unit";"Marine";"Barracks";94;1
"Unit";"Marine";"Barracks";94;1
"Unit";"Marine";"Barracks";94;1
"Unit";"SCV";"Command Center";95;1
"Unit";"SCV";"Command Center";95;1
"Unit";"Marine";"Barracks";94;1
"Unit";"SCV";"Command Center";101;1
"Unit";"SCV";"Command Center";101;1
"Unit";"Marine";"Barracks";97;1
"Unit";"Marine";"Barracks";98;1
"Unit";"Marine";"Barracks";101;1
"Unit";"Marine";"Barracks";101;1
"Unit";"Medivac";"Starport";97;2
"Unit";"Medivac";"Starport";97;2
"Building";"SupplyDepot";NA;101;0
"Unit";"Marine";"Barracks";103;1
"Unit";"SCV";"Command Center";104;1
"Unit";"SCV";"Command Center";104;1
"Building";"SupplyDepot";NA;104;0
"Building";"MissileTurret";NA;108;0
"Building";"MissileTurret";NA;110;0
"Unit";"SCV";"Command Center";115;1
"Unit";"SCV";"Command Center";117;1
"Building";"CommandCenter";NA;90;0
"Upgrade";"TerranInfantryWeaponsLevel1";"EngineeringBay";88;0
"Unit";"SCV";"Command Center";117;1
"Unit";"Marine";"Barracks";117;1
"Unit";"SCV";"Command Center";118;1
"Unit";"Marine";"Barracks";117;1
"Unit";"Marine";"Barracks";117;1
"Unit";"Marine";"Barracks";117;1
"Unit";"Marine";"Barracks";117;1
"Building";"SupplyDepot";NA;119;0
"Unit";"Medivac";"Starport";117;2
"Unit";"Medivac";"Starport";117;2
"Building";"SupplyDepot";NA;119;0
"Unit";"Marine";"Barracks";120;1
"Building";"Refinery";NA;119;0
"Unit";"Marine";"Barracks";126;1
"Unit";"Marine";"Barracks";126;1
"Unit";"Marine";"Barracks";126;1
"Unit";"Marine";"Barracks";126;1
"Unit";"Marine";"Barracks";130;1
"Unit";"SCV";"Command Center";135;1
"Unit";"SCV";"Command Center";135;1
"Unit";"Medivac";"Starport";130;2
"Unit";"Marine";"Barracks";135;1
"Unit";"Marine";"Barracks";135;1
"Unit";"Marine";"Barracks";135;1
"Unit";"Marine";"Barracks";135;1
"Unit";"Marine";"Barracks";135;1
"Building";"EngineeringBay";NA;136;0
"Unit";"Marine";"Barracks";140;1
"Unit";"Marine";"Barracks";141;1
"Unit";"Marine";"Barracks";142;1
"Unit";"SCV";"Command Center";145;1
"Unit";"SCV";"Command Center";145;1
"Unit";"Marine";"Barracks";145;1
"Unit";"Marine";"Barracks";145;1
"Unit";"Medivac";"Starport";140;2
"Unit";"SCV";"Command Center";148;1
"Unit";"SCV";"Command Center";149;1
"Unit";"Marine";"Barracks";145;1
"Unit";"Marine";"Barracks";146;1
"Building";"Armory";NA;136;0
"Unit";"SCV";"Command Center";152;1
"Unit";"SCV";"Command Center";154;1
"Building";"SupplyDepot";NA;152;0
"Unit";"Marine";"Barracks";154;1
"Unit";"Marine";"Barracks";154;1
"Unit";"Marine";"Barracks";154;1
"Building";"SupplyDepot";NA;152;0
"Unit";"Marine";"Barracks";156;1
"Unit";"Marine";"Barracks";157;1
"Unit";"SCV";"Command Center";159;1
"Unit";"SCV";"Command Center";159;1
"Unit";"SCV";"Command Center";159;1
"Upgrade";"TerranInfantryArmorsLevel1";"EngineeringBay";131;0
"Building";"Barracks";NA;145;0
"Building";"Barracks";NA;145;0
"Unit";"SCV";"Command Center";165;1
"Unit";"SCV";"Command Center";166;1
"Unit";"Marine";"Barracks";168;1
"Unit";"Marine";"Barracks";168;1
"Building";"SupplyDepot";NA;167;0
"Building";"SupplyDepot";NA;167;0
"Unit";"Marine";"Barracks";170;1
"Unit";"Marine";"Barracks";170;1
"Unit";"Marine";"Barracks";170;1
"Building";"Refinery";NA;170;0
"Building";"Refinery";NA;170;0
"Unit";"Marine";"Barracks";170;1
"Unit";"Marine";"Barracks";171;1
"Building";"BarracksReactor";NA;168;0
"Building";"BarracksReactor";NA;168;0
"Unit";"Medivac";"Starport";170;2
"Unit";"Medivac";"Starport";170;2
"Building";"Barracks";NA;168;0
"Building";"Barracks";NA;168;0
"Unit";"SCV";"Command Center";177;1
"Unit";"SCV";"Command Center";177;1
"Unit";"Marine";"Barracks";177;1
"Unit";"Marine";"Barracks";177;1
"Unit";"Marine";"Barracks";177;1
"Unit";"Marine";"Barracks";177;1
"Unit";"Marine";"Barracks";177;1
"Unit";"Marine";"Barracks";177;1
"Unit";"Marine";"Barracks";177;1
"Unit";"Marine";"Barracks";177;1
"Unit";"Marine";"Barracks";177;1
"Building";"SupplyDepot";NA;181;0
"Building";"SupplyDepot";NA;181;0
"Unit";"SCV";"Command Center";192;1
"Unit";"SCV";"Command Center";192;1
"Unit";"Marine";"Barracks";183;1
"Unit";"Marine";"Barracks";186;1
"Unit";"Marine";"Barracks";187;1
"Unit";"Marine";"Barracks";188;1
"Unit";"Marine";"Barracks";192;1
"Unit";"Marine";"Barracks";192;1
"Unit";"Marine";"Barracks";192;1
"Unit";"Marine";"Barracks";192;1
"Unit";"Marine";"Barracks";192;1
"Building";"Factory";NA;177;0
"Unit";"Marine";"Barracks";201;1
"Unit";"Marine";"Barracks";201;1
"Unit";"Marine";"Barracks";201;1
"Unit";"Marine";"Barracks";201;1
"Unit";"SCV";"Command Center";203;1
"Building";"FactoryTechLab";NA;203;0
"Unit";"Marine";"Barracks";207;1
"Unit";"Marine";"Barracks";207;1
"Unit";"Marine";"Barracks";207;1
"Unit";"Marine";"Barracks";207;1
"Unit";"Marine";"Barracks";207;1
"Unit";"Marine";"Barracks";207;1
"Unit";"Marine";"Barracks";207;1
"Unit";"Marine";"Barracks";207;1
"Unit";"Marine";"Barracks";207;1
"Building";"SupplyDepot";NA;205;0
"Building";"SupplyDepot";NA;207;0
"Upgrade";"TerranInfantryWeaponsLevel2";"EngineeringBay";172;0
"Building";"BarracksReactor";NA;203;0
"Building";"BarracksReactor";NA;203;0
"Unit";"Marine";"Barracks";208;1
"Unit";"Marine";"Barracks";209;1
"Unit";"Marine";"Barracks";210;1
"Unit";"Marine";"Barracks";210;1
"Unit";"Marine";"Barracks";212;1
"Unit";"Marine";"Barracks";212;1
"Unit";"Marine";"Barracks";214;1
"Unit";"Marine";"Barracks";217;1
"Unit";"Marine";"Barracks";217;1
"Building";"CommandCenter";NA;192;0
"Unit";"Marine";"Barracks";217;1
"Unit";"Marine";"Barracks";217;1
"Unit";"Marine";"Barracks";217;1
"Unit";"Marine";"Barracks";217;1
"Unit";"Marine";"Barracks";217;1
"Unit";"Marine";"Barracks";218;1
"Unit";"Marine";"Barracks";219;1
"Unit";"Marine";"Barracks";219;1
"Unit";"Medivac";"Starport";217;2
"Unit";"Medivac";"Starport";217;2
"Upgrade";"TerranInfantryArmorsLevel2";"EngineeringBay";192;0
"Unit";"Marine";"Barracks";230;1
"Unit";"Marine";"Barracks";230;1
"Unit";"Marine";"Barracks";230;1
"Unit";"Marine";"Barracks";230;1
"Unit";"Marine";"Barracks";230;1
"Unit";"Marine";"Barracks";230;1
"Unit";"Marine";"Barracks";230;1
"Unit";"Marine";"Barracks";230;1
"Building";"SensorTower";NA;230;0
"Unit";"Marine";"Barracks";230;1
"Unit";"Marine";"Barracks";247;1
"Unit";"Marine";"Barracks";247;1
"Unit";"Marine";"Barracks";247;1
"Unit";"Marine";"Barracks";247;1
"Unit";"Marine";"Barracks";247;1
"Unit";"Marine";"Barracks";247;1
"Unit";"Marine";"Barracks";247;1
"Unit";"Marine";"Barracks";247;1
"Unit";"Marine";"Barracks";247;1
"Unit";"Marine";"Barracks";247;1
"Unit";"Marine";"Barracks";247;1
"Unit";"Marine";"Barracks";247;1
"Unit";"Marine";"Barracks";247;1
"Upgrade";"TerranVehicleWeaponsLevel1";"Armory";217;0
"Unit";"Marine";"Barracks";247;1
"Unit";"Medivac";"Starport";247;2
"Unit";"Marine";"Barracks";248;1
"Unit";"Marine";"Barracks";249;1
"Unit";"Marine";"Barracks";250;1
"Unit";"Marine";"Barracks";250;1
"Unit";"Marine";"Barracks";252;1
"Unit";"Marine";"Barracks";252;1
"Unit";"Marine";"Barracks";254;1
"Unit";"Marine";"Barracks";255;1
"Unit";"Marine";"Barracks";255;1
"Unit";"Marine";"Barracks";255;1
"Unit";"Marine";"Barracks";258;1
"Unit";"Marine";"Barracks";258;1
"Unit";"Marine";"Barracks";260;1
"Unit";"Marine";"Barracks";263;1
"Unit";"Marine";"Barracks";264;1
"Unit";"Marine";"Barracks";265;1
"Unit";"Marine";"Barracks";265;1
"Unit";"Marine";"Barracks";267;1
"Unit";"Marine";"Barracks";267;1
"Unit";"Medivac";"Starport";275;2
"Unit";"Medivac";"Starport";275;2
"Unit";"Marine";"Barracks";282;1
"Unit";"Marine";"Barracks";282;1
"Unit";"Marine";"Barracks";282;1
"Unit";"Marine";"Barracks";282;1
"Unit";"Marine";"Barracks";282;1
"Unit";"Marine";"Barracks";282;1
"Unit";"Marine";"Barracks";282;1
"Unit";"Marine";"Barracks";282;1
"Unit";"Marine";"Barracks";282;1
"Unit";"Marine";"Barracks";282;1
"Unit";"Marine";"Barracks";282;1
"Unit";"Marine";"Barracks";282;1
"Unit";"Marine";"Barracks";282;1
"Unit";"Marine";"Barracks";286;1
"Unit";"Marine";"Barracks";296;1
"Unit";"Marine";"Barracks";296;1
"Unit";"Marine";"Barracks";296;1
"Unit";"Marine";"Barracks";296;1
"Unit";"Marine";"Barracks";296;1
"Unit";"Marine";"Barracks";296;1
"Unit";"Marine";"Barracks";296;1
"Unit";"Marine";"Barracks";296;1
"Unit";"Marine";"Barracks";296;1
