"Type";"UnitName";"OnBuilding";"TotalSupply";"Supply"
"Unit";"SCV";"Command Center";12;1
"Unit";"SCV";"Command Center";12;1
"Unit";"SCV";"Command Center";13;1
"Building";"SupplyDepot";NA;13;0
"Building";"Refinery";NA;14;0
"Unit";"SCV";"Command Center";15;1
"Unit";"SCV";"Command Center";15;1
"Unit";"SCV";"Command Center";16;1
"Unit";"SCV";"Command Center";17;1
"Building";"Barracks";NA;15;0
"Unit";"Reaper";"Barracks";19;1
"Unit";"SCV";"Command Center";19;1
"Unit";"SCV";"Command Center";21;1
"Building";"SupplyDepot";NA;20;0
"Building";"Factory";NA;19;0
"Building";"Refinery";NA;21;0
"Unit";"Reaper";"Barracks";20;1
"Unit";"SCV";"Command Center";22;1
"Building";"CommandCenter";NA;19;0
"Unit";"SCV";"Command Center";24;1
"Unit";"Marine";"Barracks";24;1
"Unit";"Hellion";"Factory";24;2
"Unit";"SCV";"Command Center";24;1
"Unit";"Marine";"Barracks";26;1
"Building";"Starport";NA;24;0
"Unit";"SCV";"Command Center";28;1
"Unit";"Marine";"Barracks";30;1
"Unit";"Cyclone";"Factory";29;3
"Unit";"SCV";"Command Center";35;1
"Unit";"SCV";"Command Center";35;1
"Unit";"SCV";"Command Center";35;1
"Building";"FactoryTechLab";NA;35;0
"Unit";"SCV";"Command Center";37;1
"Unit";"Liberator";"Starport";31;3
"Unit";"SCV";"Command Center";38;1
"Building";"SupplyDepot";NA;37;0
"Building";"SupplyDepot";NA;37;0
"Building";"Bunker";NA;36;0
"Building";"BarracksReactor";NA;35;0
"Unit";"SCV";"Command Center";43;1
"Unit";"SCV";"Command Center";43;1
"Unit";"Marine";"Barracks";43;1
"Unit";"Marine";"Barracks";43;1
"Unit";"SCV";"Command Center";43;1
"Unit";"SCV";"Command Center";44;1
"Building";"StarportTechLab";NA;43;0
"Unit";"SCV";"Command Center";47;1
"Unit";"SCV";"Command Center";48;1
"Unit";"Marine";"Barracks";49;1
"Unit";"Marine";"Barracks";49;1
"Unit";"SCV";"Command Center";52;1
"Unit";"SCV";"Command Center";53;1
"Unit";"Marine";"Barracks";51;1
"Unit";"SCV";"Command Center";53;1
"Unit";"SCV";"Command Center";55;1
"Unit";"Marine";"Barracks";53;1
"Building";"Refinery";NA;53;0
"Building";"Refinery";NA;55;0
"Unit";"Marine";"Barracks";56;1
"Unit";"SCV";"Command Center";56;1
"Building";"EngineeringBay";NA;53;0
"Building";"EngineeringBay";NA;53;0
"Unit";"SCV";"Command Center";57;1
"Unit";"Marine";"Barracks";59;1
"Unit";"SCV";"Command Center";60;1
"Unit";"Raven";"Starport";53;2
"Building";"CommandCenter";NA;45;0
"Unit";"SCV";"Command Center";62;1
"Unit";"SCV";"Command Center";66;1
"Building";"SupplyDepot";NA;62;0
"Unit";"SCV";"Command Center";67;1
"Unit";"Marine";"Barracks";66;1
"Unit";"Marine";"Barracks";66;1
"Building";"SupplyDepot";NA;63;0
"Unit";"SCV";"Command Center";69;1
"Unit";"SCV";"Command Center";71;1
"Unit";"SCV";"Command Center";71;1
"Unit";"SCV";"Command Center";72;1
"Unit";"SCV";"Command Center";73;1
"Unit";"Marine";"Barracks";71;1
"Unit";"Marine";"Barracks";71;1
"Building";"StarportReactor";NA;68;0
"Unit";"SCV";"Command Center";74;1
"Unit";"SCV";"Command Center";74;1
"Building";"Barracks";NA;67;0
"Building";"Barracks";NA;68;0
"Unit";"Marine";"Barracks";78;1
"Unit";"Marine";"Barracks";78;1
"Unit";"Marine";"Barracks";80;1
"Unit";"Marauder";"Barracks";80;2
"Building";"Barracks";NA;73;0
"Building";"Barracks";NA;73;0
"Unit";"Marine";"Barracks";82;1
"Unit";"Marine";"Barracks";82;1
"Building";"Armory";NA;78;0
"Unit";"Marine";"Barracks";85;1
"Unit";"Marine";"Barracks";85;1
"Unit";"Marine";"Barracks";85;1
"Upgrade";"TerranInfantryWeaponsLevel1";"EngineeringBay";71;0
"Unit";"Marine";"Barracks";85;1
"Unit";"Marine";"Barracks";86;1
"Unit";"Marine";"Barracks";87;1
"Upgrade";"TerranInfantryArmorsLevel1";"EngineeringBay";73;0
"Unit";"Marine";"Barracks";87;1
"Unit";"Marine";"Barracks";88;1
"Unit";"Marine";"Barracks";89;1
"Unit";"Marine";"Barracks";90;1
"Unit";"SCV";"Command Center";93;1
"Unit";"SCV";"Command Center";93;1
"Unit";"SCV";"Command Center";93;1
"Unit";"Medivac";"Starport";89;2
"Unit";"Medivac";"Starport";89;2
"Unit";"Marine";"Barracks";93;1
"Unit";"Marine";"Barracks";94;1
"Building";"BarracksTechLab";NA;96;0
"Unit";"SCV";"Command Center";97;1
"Unit";"SCV";"Command Center";98;1
"Unit";"SCV";"Command Center";99;1
"Unit";"Marine";"Barracks";104;1
"Unit";"SCV";"Command Center";106;1
"Unit";"Marine";"Barracks";104;1
"Unit";"SCV";"Command Center";109;1
"Unit";"SCV";"Command Center";109;1
"Building";"BarracksReactor";NA;96;0
"Unit";"Marauder";"Barracks";105;2
"Building";"BarracksReactor";NA;96;0
"Unit";"Marauder";"Barracks";106;2
"Unit";"Medivac";"Starport";100;2
"Unit";"SCV";"Command Center";112;1
"Unit";"SCV";"Command Center";112;1
"Unit";"Marine";"Barracks";109;1
"Unit";"Marine";"Barracks";111;1
"Unit";"Medivac";"Starport";109;2
"Unit";"SCV";"Command Center";120;1
"Unit";"Marauder";"Barracks";114;2
"Unit";"Marine";"Barracks";120;1
"Building";"SupplyDepot";NA;123;0
"Building";"SupplyDepot";NA;123;0
"Building";"SupplyDepot";NA;124;0
"Unit";"SCV";"Command Center";130;1
"Unit";"SCV";"Command Center";130;1
"Unit";"SCV";"Command Center";130;1
"Unit";"Marine";"Barracks";130;1
"Unit";"Marine";"Barracks";130;1
"Unit";"Marine";"Barracks";130;1
"Unit";"Marine";"Barracks";130;1
"Unit";"Marine";"Barracks";130;1
"Unit";"Marine";"Barracks";130;1
"Unit";"Marine";"Barracks";130;1
"Unit";"Marauder";"Barracks";130;2
"Building";"SupplyDepot";NA;130;0
"Unit";"SCV";"Command Center";130;1
"Unit";"SCV";"Command Center";131;1
"Unit";"SCV";"Command Center";132;1
"Building";"SupplyDepot";NA;130;0
"Upgrade";"Stimpack";"TechLab";104;0
"Building";"SupplyDepot";NA;130;0
"Unit";"Marine";"Barracks";134;1
"Unit";"Marine";"Barracks";134;1
"Unit";"SCV";"Command Center";142;1
"Unit";"SCV";"Command Center";143;1
"Unit";"Marine";"Barracks";140;1
"Unit";"Marine";"Barracks";140;1
"Unit";"Marine";"Barracks";140;1
"Unit";"Marauder";"Barracks";133;2
"Unit";"Marine";"Barracks";142;1
"Building";"Starport";NA;130;0
"Unit";"SCV";"Command Center";149;1
"Unit";"SCV";"Command Center";149;1
"Unit";"SCV";"Command Center";149;1
"Unit";"SCV";"Command Center";155;1
"Unit";"Marine";"Barracks";155;1
"Unit";"Marine";"Barracks";155;1
"Unit";"Marine";"Barracks";155;1
"Unit";"Marine";"Barracks";155;1
"Unit";"Marine";"Barracks";155;1
"Unit";"Marine";"Barracks";155;1
"Unit";"Marine";"Barracks";155;1
"Unit";"Marine";"Barracks";155;1
"Unit";"SCV";"Command Center";158;1
"Unit";"SCV";"Command Center";158;1
"Unit";"Medivac";"Starport";155;2
"Unit";"Medivac";"Starport";155;2
"Unit";"Marine";"Barracks";159;1
"Unit";"Marine";"Barracks";160;1
"Unit";"Marine";"Barracks";161;1
"Unit";"Marine";"Barracks";166;1
"Unit";"Marine";"Barracks";166;1
"Unit";"Marine";"Barracks";166;1
"Unit";"Marine";"Barracks";166;1
"Unit";"Marine";"Barracks";166;1
"Building";"StarportReactor";NA;158;0
"Unit";"Marine";"Barracks";181;1
"Upgrade";"TerranInfantryWeaponsLevel2";"EngineeringBay";133;0
"Unit";"Marine";"Barracks";181;1
"Unit";"Marine";"Barracks";181;1
"Unit";"Marine";"Barracks";181;1
"Unit";"Marine";"Barracks";181;1
"Unit";"Marine";"Barracks";181;1
"Unit";"Marine";"Barracks";181;1
"Unit";"Marine";"Barracks";181;1
"Upgrade";"TerranInfantryArmorsLevel2";"EngineeringBay";140;0
