"type";"unit_name";"on_building";"total_supply";"supply"
"Building";"Refinery";NA;14;0
"Building";"Barracks";NA;15;0
"Unit";"Reaper";"Barracks";19;1
"Unit";"Marine";"Barracks";19;1
"Building";"Factory";NA;19;0
"Unit";"Marine";"Barracks";21;1
"Building";"CommandCenter";NA;19;0
"Unit";"Marine";"Barracks";21;1
"Unit";"Hellion";"Factory";21;2
"Unit";"Marine";"Barracks";23;1
"Unit";"Hellion";"Factory";24;2
"Building";"Starport";NA;26;0
"Building";"BarracksReactor";NA;28;0
"Building";"StarportTechLab";NA;30;0
"Building";"Refinery";NA;30;0
"Unit";"Cyclone";"Factory";30;3
"Unit";"Marine";"Barracks";31;1
"Unit";"Marine";"Barracks";31;1
"Unit";"Hellion";"Factory";34;2
"Unit";"Marine";"Barracks";39;1
"Unit";"Marine";"Barracks";39;1
"Unit";"Marine";"Barracks";47;1
"Unit";"Marine";"Barracks";47;1
"Unit";"Hellion";"Factory";48;2
"Unit";"Marine";"Barracks";51;1
"Unit";"Marine";"Barracks";51;1
"Building";"FactoryTechLab";NA;53;0
"Unit";"Raven";"Starport";48;2
"Building";"EngineeringBay";NA;54;0
"Unit";"Marine";"Barracks";57;1
"Unit";"Marine";"Barracks";57;1
"Building";"MissileTurret";NA;63;0
"Building";"MissileTurret";NA;63;0
"Unit";"Marine";"Barracks";63;1
"Unit";"Marine";"Barracks";63;1
"Unit";"Raven";"Starport";63;2
"Building";"Refinery";NA;69;0
"Building";"Refinery";NA;69;0
"Unit";"Marine";"Barracks";78;1
"Unit";"Marine";"Barracks";78;1
"Unit";"Marine";"Barracks";83;1
"Building";"Barracks";NA;79;0
"Building";"Barracks";NA;79;0
"Building";"CommandCenter";NA;79;0
"Unit";"Marine";"Barracks";87;1
"Building";"BarracksReactor";NA;87;0
"Building";"BarracksReactor";NA;87;0
"Unit";"Marine";"Barracks";90;1
"Building";"Barracks";NA;87;0
"Upgrade";"TerranInfantryWeaponsLevel1";"EngineeringBay";83;0
"Upgrade";"Stimpack";"TechLab";82;0
"Building";"Barracks";NA;87;0
"Unit";"Marine";"Barracks";92;1
"Unit";"Marine";"Barracks";92;1
"Unit";"Marine";"Barracks";92;1
"Unit";"Marine";"Barracks";92;1
"Unit";"Marine";"Barracks";92;1
"Unit";"Marine";"Barracks";93;1
"Unit";"Marine";"Barracks";100;1
"Unit";"Marine";"Barracks";100;1
"Building";"BarracksReactor";NA;100;0
"Building";"BarracksReactor";NA;100;0
"Unit";"Marine";"Barracks";103;1
"Unit";"Marine";"Barracks";103;1
"Unit";"Marine";"Barracks";103;1
"Unit";"Marine";"Barracks";103;1
"Unit";"Marine";"Barracks";103;1
"Unit";"Medivac";"Starport";103;2
"Unit";"Marine";"Barracks";103;1
"Unit";"Marine";"Barracks";110;1
"Unit";"Marine";"Barracks";110;1
"Unit";"Marine";"Barracks";110;1
"Unit";"Marine";"Barracks";111;1
"Unit";"Marine";"Barracks";111;1
"Unit";"Marine";"Barracks";111;1
"Unit";"Marine";"Barracks";111;1
"Upgrade";"TerranInfantryArmorsLevel1";"EngineeringBay";103;0
"Unit";"Marine";"Barracks";118;1
"Unit";"Marine";"Barracks";118;1
"Unit";"Marine";"Barracks";118;1
"Unit";"Marine";"Barracks";118;1
"Unit";"Liberator";"Starport";111;3
"Unit";"Marine";"Barracks";118;1
"Unit";"Marine";"Barracks";118;1
"Unit";"Marine";"Barracks";118;1
"Unit";"Marine";"Barracks";118;1
"Unit";"Marine";"Barracks";118;1
"Unit";"Marine";"Barracks";118;1
"Unit";"Marine";"Barracks";127;1
"Unit";"Marine";"Barracks";127;1
"Unit";"Marine";"Barracks";127;1
"Unit";"Medivac";"Starport";121;2
"Building";"CommandCenter";NA;111;0
"Unit";"Marine";"Barracks";130;1
"Unit";"Marine";"Barracks";131;1
"Unit";"Marine";"Barracks";131;1
"Unit";"Medivac";"Starport";122;2
"Unit";"Marine";"Barracks";131;1
"Building";"Armory";NA;118;0
"Unit";"Marine";"Barracks";134;1
"Unit";"Marine";"Barracks";142;1
"Unit";"Marine";"Barracks";142;1
"Unit";"Marine";"Barracks";142;1
"Unit";"Marine";"Barracks";142;1
"Unit";"Marine";"Barracks";142;1
"Unit";"Marine";"Barracks";142;1
"Unit";"Marine";"Barracks";143;1
"Unit";"Marine";"Barracks";150;1
"Unit";"Marine";"Barracks";150;1
"Unit";"Marine";"Barracks";150;1
"Unit";"Marine";"Barracks";150;1
"Unit";"Marine";"Barracks";150;1
"Unit";"Marine";"Barracks";150;1
"Unit";"Marine";"Barracks";150;1
"Unit";"Marine";"Barracks";153;1
"Unit";"Marine";"Barracks";154;1
"Unit";"Marine";"Barracks";155;1
"Unit";"Marine";"Barracks";155;1
"Unit";"Marine";"Barracks";156;1
"Unit";"Marine";"Barracks";156;1
"Unit";"Marine";"Barracks";156;1
"Unit";"Marine";"Barracks";156;1
"Unit";"Marine";"Barracks";157;1
"Unit";"Marine";"Barracks";157;1
"Unit";"Marine";"Barracks";158;1
"Unit";"Marine";"Barracks";159;1
"Unit";"Marine";"Barracks";160;1
"Unit";"Marine";"Barracks";166;1
"Unit";"Marine";"Barracks";166;1
"Unit";"Marine";"Barracks";166;1
"Unit";"Marine";"Barracks";173;1
"Unit";"Marine";"Barracks";173;1
"Unit";"Marine";"Barracks";173;1
"Unit";"Marine";"Barracks";173;1
"Unit";"Marine";"Barracks";173;1
"Unit";"Marine";"Barracks";173;1
"Unit";"Marine";"Barracks";173;1
"Unit";"Marine";"Barracks";173;1
"Unit";"Marine";"Barracks";173;1
"Unit";"Marine";"Barracks";173;1
"Unit";"Marine";"Barracks";174;1
"Unit";"Marine";"Barracks";175;1
"Unit";"Marine";"Barracks";176;1
"Unit";"Medivac";"Starport";173;2
