"type";"unit_name";"on_building";"total_supply";"supply"
"Building";"Refinery";NA;14;0
"Building";"Barracks";NA;15;0
"Unit";"Reaper";"Barracks";19;1
"Building";"Refinery";NA;19;0
"Building";"Factory";NA;19;0
"Unit";"Reaper";"Barracks";21;1
"Unit";"Hellion";"Factory";23;2
"Building";"Starport";NA;23;0
"Unit";"Reaper";"Barracks";25;1
"Unit";"Hellion";"Factory";27;2
"Building";"StarportTechLab";NA;29;0
