"type";"unit_name";"on_building";"total_supply";"supply"
"Building";"Refinery";NA;15;0
"Building";"Barracks";NA;15;0
"Building";"Barracks";NA;17;0
"Unit";"Reaper";"Barracks";19;1
"Unit";"Reaper";"Barracks";19;1
"Unit";"Reaper";"Barracks";20;1
"Building";"Refinery";NA;21;0
"Unit";"Reaper";"Barracks";22;1
"Unit";"Reaper";"Barracks";24;1
"Building";"Barracks";NA;23;0
"Building";"CommandCenter";NA;21;0
"Unit";"Reaper";"Barracks";24;1
"Unit";"Reaper";"Barracks";27;1
