"type";"unit_name";"on_building";"total_supply";"supply"
"Building";"Refinery";NA;14;0
"Building";"Barracks";NA;15;0
"Unit";"Reaper";"Barracks";19;1
"Building";"Refinery";NA;20;0
"Unit";"Reaper";"Barracks";20;1
"Building";"Factory";NA;20;0
"Building";"CommandCenter";NA;19;0
"Unit";"Marine";"Barracks";24;1
"Unit";"Hellion";"Factory";24;2
"Building";"Starport";NA;24;0
"Unit";"Marine";"Barracks";29;1
"Unit";"Cyclone";"Factory";30;3
"Unit";"Marine";"Barracks";31;1
"Unit";"Liberator";"Starport";30;3
"Unit";"Cyclone";"Factory";39;3
"Building";"StarportTechLab";NA;44;0
"Building";"Refinery";NA;44;0
"Building";"Refinery";NA;44;0
"Building";"BarracksReactor";NA;39;0
"Building";"FactoryTechLab";NA;49;0
"Building";"EngineeringBay";NA;51;0
"Building";"EngineeringBay";NA;53;0
"Building";"CommandCenter";NA;39;0
"Unit";"Raven";"Starport";51;2
"Unit";"Marine";"Barracks";55;1
"Unit";"Marine";"Barracks";55;1
"Building";"Bunker";NA;55;0
"Unit";"Marine";"Barracks";60;1
"Unit";"Marine";"Barracks";60;1
"Unit";"Marine";"Barracks";65;1
"Unit";"Marine";"Barracks";65;1
"Unit";"Raven";"Starport";58;2
"Building";"Barracks";NA;61;0
"Building";"Barracks";NA;61;0
"Unit";"Marine";"Barracks";74;1
"Unit";"Marine";"Barracks";74;1
"Unit";"Marine";"Barracks";80;1
"Unit";"Marine";"Barracks";80;1
"Building";"FactoryTechLab";NA;80;0
"Building";"StarportReactor";NA;76;0
"Unit";"Marine";"Barracks";81;1
"Unit";"Marine";"Barracks";81;1
"Unit";"Marine";"Barracks";85;1
"Unit";"Marine";"Barracks";85;1
"Building";"Barracks";NA;80;0
"Upgrade";"TerranInfantryWeaponsLevel1";"EngineeringBay";67;0
"Upgrade";"TerranInfantryArmorsLevel1";"EngineeringBay";67;0
"Building";"Barracks";NA;80;0
"Unit";"Marauder";"Barracks";86;2
"Unit";"Medivac";"Starport";85;2
"Unit";"Medivac";"Starport";85;2
"Unit";"Marauder";"Barracks";87;2
"Unit";"Marine";"Barracks";90;1
"Unit";"Marine";"Barracks";90;1
"Building";"BarracksTechLab";NA;90;0
"Building";"Armory";NA;83;0
"Unit";"Marauder";"Barracks";92;2
"Building";"BarracksReactor";NA;90;0
"Unit";"Marauder";"Barracks";97;2
"Unit";"Marauder";"Barracks";101;2
"Unit";"Medivac";"Starport";97;2
"Unit";"Medivac";"Starport";97;2
"Unit";"Marine";"Barracks";101;1
"Unit";"Marine";"Barracks";101;1
"Unit";"Marauder";"Barracks";101;2
"Unit";"Marauder";"Barracks";103;2
"Building";"Refinery";NA;106;0
"Unit";"Marine";"Barracks";116;1
"Unit";"Marine";"Barracks";116;1
"Unit";"Marine";"Barracks";116;1
"Unit";"Marine";"Barracks";116;1
"Unit";"Marauder";"Barracks";116;2
"Unit";"Marauder";"Barracks";116;2
"Upgrade";"Stimpack";"TechLab";87;0
"Unit";"Marine";"Barracks";118;1
"Unit";"Marine";"Barracks";119;1
"Unit";"Marine";"Barracks";120;1
"Unit";"Marine";"Barracks";121;1
"Unit";"Marauder";"Barracks";126;2
"Unit";"Marauder";"Barracks";128;2
"Unit";"Marauder";"Barracks";128;2
"Unit";"Marine";"Barracks";131;1
"Unit";"Medivac";"Starport";128;2
"Unit";"Marine";"Barracks";137;1
"Unit";"Marine";"Barracks";137;1
"Unit";"Medivac";"Starport";131;2
"Unit";"Marine";"Barracks";137;1
"Building";"Refinery";NA;137;0
