"type";"unit_name";"on_building";"total_supply";"supply"
"Building";"Refinery";NA;15;0
"Building";"Barracks";NA;15;0
"Unit";"Reaper";"Barracks";19;1
"Building";"Refinery";NA;19;0
"Building";"Factory";NA;19;0
"Building";"BarracksReactor";NA;21;0
"Building";"CommandCenter";NA;19;0
"Unit";"Marine";"Barracks";23;1
"Unit";"Marine";"Barracks";23;1
"Unit";"Cyclone";"Factory";24;3
"Building";"Refinery";NA;32;0
"Building";"BarracksTechLab";NA;33;0
"Unit";"Cyclone";"Factory";33;3
"Unit";"Cyclone";"Factory";33;3
"Building";"Starport";NA;33;0
"Building";"FactoryTechLab";NA;44;0
"Unit";"Marine";"Barracks";45;1
"Unit";"Marine";"Barracks";45;1
"Unit";"Marine";"Barracks";48;1
"Unit";"Marine";"Barracks";49;1
"Building";"EngineeringBay";NA;47;0
"Unit";"Raven";"Starport";45;2
"Building";"Barracks";NA;55;0
"Building";"Barracks";NA;55;0
"Building";"MissileTurret";NA;62;0
"Unit";"Marine";"Barracks";63;1
"Building";"StarportReactor";NA;62;0
"Building";"Refinery";NA;67;0
"Unit";"Marine";"Barracks";69;1
"Unit";"Marine";"Barracks";69;1
"Building";"BarracksReactor";NA;67;0
"Unit";"Marine";"Barracks";69;1
"Unit";"Marine";"Barracks";72;1
"Unit";"Marine";"Barracks";72;1
"Unit";"Marine";"Barracks";74;1
"Unit";"Marine";"Barracks";74;1
"Building";"CommandCenter";NA;64;0
"Unit";"Medivac";"Starport";72;2
"Unit";"Medivac";"Starport";72;2
"Unit";"Marine";"Barracks";74;1
"Unit";"Marine";"Barracks";74;1
"Upgrade";"TerranInfantryWeaponsLevel1";"EngineeringBay";67;0
"Building";"EngineeringBay";NA;76;0
"Building";"Armory";NA;78;0
"Unit";"Marine";"Barracks";87;1
"Unit";"Marine";"Barracks";87;1
"Unit";"Marine";"Barracks";87;1
"Unit";"Marine";"Barracks";87;1
"Unit";"Marine";"Barracks";87;1
"Building";"Barracks";NA;85;0
"Building";"Barracks";NA;85;0
"Unit";"Medivac";"Starport";89;2
"Unit";"Medivac";"Starport";89;2
"Upgrade";"Stimpack";"TechLab";73;0
"Unit";"Marine";"Barracks";89;1
"Unit";"Marine";"Barracks";100;1
"Unit";"Marine";"Barracks";100;1
"Unit";"Marine";"Barracks";100;1
"Unit";"Marine";"Barracks";100;1
"Unit";"Marine";"Barracks";100;1
"Unit";"Medivac";"Starport";100;2
"Unit";"Medivac";"Starport";100;2
"Unit";"Marine";"Barracks";107;1
"Unit";"Marine";"Barracks";107;1
"Unit";"Marine";"Barracks";107;1
"Unit";"Marine";"Barracks";107;1
"Building";"MissileTurret";NA;107;0
"Building";"BarracksReactor";NA;100;0
"Building";"BarracksReactor";NA;100;0
"Building";"SensorTower";NA;107;0
"Unit";"Marine";"Barracks";113;1
"Unit";"Marine";"Barracks";113;1
"Building";"Refinery";NA;113;0
"Building";"Refinery";NA;116;0
"Unit";"Marine";"Barracks";120;1
"Unit";"Marine";"Barracks";120;1
"Unit";"Marine";"Barracks";121;1
"Unit";"Marine";"Barracks";121;1
"Unit";"Marine";"Barracks";121;1
"Unit";"Marine";"Barracks";121;1
"Unit";"Marine";"Barracks";121;1
"Upgrade";"TerranInfantryArmorsLevel1";"EngineeringBay";100;0
"Unit";"Marine";"Barracks";131;1
"Unit";"Marine";"Barracks";131;1
"Unit";"Marine";"Barracks";131;1
"Unit";"Marine";"Barracks";133;1
"Unit";"Marine";"Barracks";134;1
"Unit";"Marine";"Barracks";134;1
"Unit";"Marine";"Barracks";140;1
"Unit";"Marine";"Barracks";140;1
"Unit";"Marine";"Barracks";140;1
"Unit";"Marine";"Barracks";140;1
"Unit";"Marine";"Barracks";140;1
