"type";"unit_name";"on_building";"total_supply";"supply"
"Building";"Refinery";NA;15;0
"Building";"Barracks";NA;15;0
"Unit";"Reaper";"Barracks";19;1
"Unit";"Marine";"Barracks";19;1
"Building";"Refinery";NA;19;0
"Building";"Factory";NA;21;0
"Building";"Bunker";NA;22;0
"Unit";"Marine";"Barracks";23;1
"Building";"CommandCenter";NA;19;0
"Unit";"Marine";"Barracks";24;1
"Unit";"Cyclone";"Factory";25;3
"Unit";"Marine";"Barracks";27;1
"Building";"Starport";NA;25;0
"Unit";"Marine";"Barracks";32;1
"Unit";"Cyclone";"Factory";32;3
"Building";"FactoryTechLab";NA;38;0
"Building";"BarracksReactor";NA;38;0
"Unit";"Marine";"Barracks";44;1
"Unit";"Marine";"Barracks";45;1
"Unit";"Marine";"Barracks";51;1
"Unit";"Marine";"Barracks";51;1
"Unit";"Marine";"Barracks";56;1
"Unit";"Marine";"Barracks";56;1
"Unit";"Liberator";"Starport";52;3
"Unit";"Marine";"Barracks";61;1
"Unit";"Marine";"Barracks";61;1
"Building";"Refinery";NA;66;0
"Unit";"Marine";"Barracks";66;1
"Building";"Refinery";NA;66;0
"Building";"Refinery";NA;66;0
"Building";"EngineeringBay";NA;66;0
"Building";"EngineeringBay";NA;66;0
"Building";"CommandCenter";NA;58;0
"Unit";"Marine";"Barracks";66;1
"Unit";"Marine";"Barracks";68;1
"Building";"Barracks";NA;66;0
"Building";"StarportReactor";NA;66;0
"Building";"Barracks";NA;66;0
"Building";"Barracks";NA;66;0
"Building";"Barracks";NA;66;0
"Unit";"Marine";"Barracks";69;1
"Unit";"Marine";"Barracks";70;1
"Building";"BarracksTechLab";NA;71;0
"Building";"BarracksTechLab";NA;71;0
"Unit";"Marine";"Barracks";71;1
"Unit";"Marine";"Barracks";72;1
"Building";"MissileTurret";NA;73;0
"Unit";"Medivac";"Starport";72;2
"Building";"MissileTurret";NA;73;0
"Unit";"Marine";"Barracks";73;1
"Building";"BarracksReactor";NA;72;0
"Building";"BarracksReactor";NA;72;0
"Unit";"Marine";"Barracks";74;1
"Unit";"Marine";"Barracks";77;1
"Unit";"Marine";"Barracks";77;1
"Unit";"Marine";"Barracks";77;1
"Unit";"Marine";"Barracks";79;1
"Unit";"Marine";"Barracks";79;1
"Unit";"Marine";"Barracks";79;1
"Unit";"Marine";"Barracks";79;1
"Unit";"Marine";"Barracks";79;1
"Unit";"Marine";"Barracks";81;1
"Unit";"Marine";"Barracks";82;1
"Unit";"Marine";"Barracks";91;1
"Unit";"Marine";"Barracks";91;1
"Unit";"Marine";"Barracks";91;1
"Unit";"Marine";"Barracks";91;1
"Unit";"Marine";"Barracks";91;1
"Unit";"Marine";"Barracks";91;1
"Unit";"Marine";"Barracks";91;1
"Unit";"Marine";"Barracks";91;1
"Unit";"Medivac";"Starport";91;2
"Unit";"Medivac";"Starport";91;2
"Unit";"Marine";"Barracks";91;1
"Unit";"Marine";"Barracks";92;1
"Unit";"Marine";"Barracks";94;1
"Unit";"Marine";"Barracks";99;1
"Unit";"Marine";"Barracks";99;1
"Unit";"Marine";"Barracks";99;1
"Unit";"Marine";"Barracks";99;1
"Unit";"Marine";"Barracks";99;1
"Unit";"Marine";"Barracks";103;1
"Upgrade";"TerranInfantryWeaponsLevel1";"EngineeringBay";81;0
"Upgrade";"TerranInfantryArmorsLevel1";"EngineeringBay";84;0
"Unit";"Marine";"Barracks";111;1
"Unit";"Marine";"Barracks";111;1
"Unit";"Marine";"Barracks";111;1
"Unit";"Marine";"Barracks";111;1
"Unit";"Marine";"Barracks";111;1
"Unit";"Marine";"Barracks";111;1
"Building";"Armory";NA;99;0
"Unit";"Medivac";"Starport";112;2
"Unit";"Medivac";"Starport";112;2
"Unit";"Marine";"Barracks";118;1
"Unit";"Marine";"Barracks";118;1
"Unit";"Marine";"Barracks";118;1
"Unit";"Marine";"Barracks";120;1
"Unit";"Marine";"Barracks";120;1
"Unit";"Marine";"Barracks";120;1
"Unit";"Marine";"Barracks";120;1
"Unit";"Marine";"Barracks";120;1
"Unit";"Marine";"Barracks";124;1
"Unit";"Marine";"Barracks";136;1
"Unit";"Marine";"Barracks";136;1
"Unit";"Marine";"Barracks";136;1
"Unit";"Marine";"Barracks";136;1
"Unit";"Marine";"Barracks";136;1
"Upgrade";"Stimpack";"TechLab";107;0
"Unit";"Marine";"Barracks";136;1
"Unit";"Marine";"Barracks";136;1
"Unit";"Marine";"Barracks";136;1
"Unit";"Marine";"Barracks";136;1
"Unit";"Marine";"Barracks";137;1
"Unit";"Marine";"Barracks";138;1
"Unit";"Marine";"Barracks";139;1
"Unit";"Marine";"Barracks";140;1
"Unit";"Marine";"Barracks";144;1
"Unit";"Marine";"Barracks";144;1
"Unit";"Marine";"Barracks";144;1
"Building";"Factory";NA;136;0
"Unit";"Marine";"Barracks";149;1
"Unit";"Marine";"Barracks";149;1
"Unit";"Marine";"Barracks";152;1
"Unit";"Marine";"Barracks";152;1
"Unit";"Marine";"Barracks";152;1
"Unit";"Marine";"Barracks";152;1
"Unit";"Marine";"Barracks";154;1
"Unit";"Marine";"Barracks";154;1
"Unit";"Marine";"Barracks";154;1
"Unit";"Marine";"Barracks";154;1
"Upgrade";"TerranVehicleWeaponsLevel1";"Armory";136;0
"Building";"Refinery";NA;158;0
"Building";"Refinery";NA;158;0
"Unit";"Marine";"Barracks";165;1
"Unit";"Marine";"Barracks";165;1
"Unit";"Marine";"Barracks";165;1
"Unit";"Marine";"Barracks";165;1
"Unit";"Marine";"Barracks";165;1
"Unit";"Marine";"Barracks";165;1
"Unit";"Marine";"Barracks";165;1
"Unit";"Marine";"Barracks";165;1
"Upgrade";"TerranInfantryWeaponsLevel2";"EngineeringBay";144;0
"Upgrade";"TerranInfantryArmorsLevel2";"EngineeringBay";144;0
"Unit";"Marine";"Barracks";168;1
"Unit";"Marine";"Barracks";179;1
"Unit";"Marine";"Barracks";179;1
