"type";"unit_name";"on_building";"total_supply";"supply"
"Building";"Refinery";NA;14;0
"Building";"Refinery";NA;16;0
"Building";"Barracks";NA;15;0
"Unit";"Reaper";"Barracks";19;1
"Building";"Factory";NA;19;0
"Unit";"Hellion";"Factory";21;2
"Unit";"Reaper";"Barracks";19;1
"Unit";"Cyclone";"Factory";26;3
"Building";"BarracksReactor";NA;25;0
"Building";"FactoryTechLab";NA;31;0
"Unit";"Marine";"Barracks";31;1
"Unit";"Marine";"Barracks";31;1
"Building";"CommandCenter";NA;22;0
"Building";"Starport";NA;31;0
"Unit";"Marine";"Barracks";35;1
"Building";"FactoryTechLab";NA;35;0
"Unit";"Marine";"Barracks";36;1
"Building";"Bunker";NA;35;0
"Unit";"Marine";"Barracks";38;1
"Unit";"Marine";"Barracks";38;1
"Unit";"Raven";"Starport";37;2
"Unit";"Marine";"Barracks";44;1
"Unit";"Marine";"Barracks";44;1
"Unit";"Marine";"Barracks";54;1
"Building";"StarportReactor";NA;52;0
"Building";"Refinery";NA;54;0
"Building";"Refinery";NA;54;0
"Building";"CommandCenter";NA;44;0
"Unit";"Marine";"Barracks";57;1
"Building";"Barracks";NA;54;0
"Building";"Barracks";NA;54;0
"Building";"EngineeringBay";NA;59;0
"Building";"EngineeringBay";NA;59;0
"Unit";"Marine";"Barracks";64;1
"Building";"StarportReactor";NA;59;0
"Unit";"Marine";"Barracks";66;1
"Unit";"Marine";"Barracks";66;1
"Unit";"Marine";"Barracks";66;1
"Unit";"Marine";"Barracks";66;1
"Unit";"Marine";"Barracks";66;1
"Unit";"Marine";"Barracks";71;1
"Unit";"Marine";"Barracks";71;1
"Unit";"Marine";"Barracks";71;1
"Unit";"Marine";"Barracks";71;1
"Unit";"Marine";"Barracks";71;1
"Unit";"Medivac";"Starport";67;2
"Unit";"Medivac";"Starport";67;2
"Unit";"Marine";"Barracks";75;1
"Upgrade";"Stimpack";"TechLab";61;0
"Unit";"Marine";"Barracks";86;1
"Unit";"Marine";"Barracks";86;1
"Unit";"Marine";"Barracks";86;1
"Unit";"Marine";"Barracks";86;1
"Unit";"Marine";"Barracks";86;1
"Unit";"Marine";"Barracks";90;1
"Unit";"Marine";"Barracks";90;1
"Unit";"Medivac";"Starport";87;2
"Unit";"Medivac";"Starport";87;2
"Unit";"Marine";"Barracks";94;1
"Unit";"Marine";"Barracks";94;1
"Unit";"Marine";"Barracks";94;1
"Unit";"Marine";"Barracks";95;1
"Unit";"Marine";"Barracks";104;1
"Upgrade";"TerranInfantryWeaponsLevel1";"EngineeringBay";74;0
"Upgrade";"TerranInfantryArmorsLevel1";"EngineeringBay";75;0
"Unit";"Marine";"Barracks";108;1
"Unit";"Marine";"Barracks";108;1
"Unit";"Marine";"Barracks";108;1
"Unit";"Marine";"Barracks";108;1
"Building";"Barracks";NA;95;0
"Building";"Barracks";NA;95;0
"Building";"Armory";NA;95;0
"Unit";"Marine";"Barracks";112;1
"Unit";"Marine";"Barracks";112;1
"Unit";"Marine";"Barracks";113;1
"Unit";"Marine";"Barracks";114;1
"Unit";"Medivac";"Starport";112;2
"Unit";"Medivac";"Starport";112;2
"Building";"Refinery";NA;117;0
"Building";"Refinery";NA;117;0
"Unit";"Marine";"Barracks";118;1
"Unit";"Marine";"Barracks";118;1
"Unit";"Marine";"Barracks";118;1
"Unit";"Marine";"Barracks";119;1
"Building";"BarracksReactor";NA;117;0
"Building";"BarracksReactor";NA;117;0
"Unit";"Marine";"Barracks";123;1
"Unit";"Marine";"Barracks";127;1
"Unit";"Marine";"Barracks";128;1
"Unit";"Marine";"Barracks";134;1
"Unit";"Marine";"Barracks";134;1
