"type";"unit_name";"on_building";"total_supply";"supply"
"Building";"Refinery";NA;15;0
"Building";"Barracks";NA;15;0
"Building";"Refinery";NA;15;0
"Building";"Barracks";NA;15;0
"Building";"Barracks";NA;15;0
"Unit";"Reaper";"Barracks";15;1
"Unit";"Reaper";"Barracks";15;1
"Unit";"Reaper";"Barracks";15;1
"Unit";"Reaper";"Barracks";17;1
"Unit";"Reaper";"Barracks";18;1
"Unit";"Reaper";"Barracks";19;1
"Unit";"Reaper";"Barracks";20;1
"Unit";"Reaper";"Barracks";22;1
"Unit";"Reaper";"Barracks";22;1
"Unit";"Reaper";"Barracks";23;1
"Unit";"Reaper";"Barracks";24;1
