"Type";"UnitName";"OnBuilding";"TotalSupply";"Supply"
"Unit";"SCV";"Command Center";12;1
"Unit";"SCV";"Command Center";12;1
"Unit";"SCV";"Command Center";13;1
"Building";"SupplyDepot";NA;13;0
"Building";"Refinery";NA;14;0
"Unit";"SCV";"Command Center";15;1
"Unit";"SCV";"Command Center";15;1
"Unit";"SCV";"Command Center";16;1
"Unit";"SCV";"Command Center";17;1
"Building";"Barracks";NA;15;0
"Unit";"Reaper";"Barracks";19;1
"Unit";"SCV";"Command Center";19;1
"Unit";"SCV";"Command Center";21;1
"Building";"SupplyDepot";NA;20;0
"Unit";"Reaper";"Barracks";20;1
"Building";"Factory";NA;19;0
"Building";"Refinery";NA;21;0
"Unit";"SCV";"Command Center";22;1
"Building";"CommandCenter";NA;19;0
"Unit";"Marine";"Barracks";23;1
"Unit";"SCV";"Command Center";23;1
"Unit";"Hellion";"Factory";23;2
"Unit";"SCV";"Command Center";26;1
"Building";"Starport";NA;24;0
"Unit";"SCV";"Command Center";28;1
"Unit";"Marine";"Barracks";29;1
"Unit";"SCV";"Command Center";29;1
"Unit";"SCV";"Command Center";30;1
"Unit";"Cyclone";"Factory";29;3
"Unit";"SCV";"Command Center";33;1
"Unit";"SCV";"Command Center";33;1
"Unit";"Marine";"Barracks";36;1
"Unit";"SCV";"Command Center";36;1
"Unit";"SCV";"Command Center";38;1
"Building";"SupplyDepot";NA;38;0
"Unit";"Cyclone";"Factory";39;3
"Unit";"Liberator";"Starport";36;3
"Unit";"SCV";"Command Center";41;1
"Unit";"SCV";"Command Center";41;1
"Unit";"Marine";"Barracks";41;1
"Building";"Refinery";NA;47;0
"Building";"SupplyDepot";NA;47;0
"Building";"Refinery";NA;48;0
"Unit";"SCV";"Command Center";50;1
"Unit";"SCV";"Command Center";50;1
"Building";"StarportTechLab";NA;50;0
"Unit";"Cyclone";"Factory";49;3
"Unit";"SCV";"Command Center";50;1
"Unit";"SCV";"Command Center";51;1
"Building";"BarracksReactor";NA;50;0
"Unit";"SCV";"Command Center";55;1
"Unit";"SCV";"Command Center";56;1
"Building";"FactoryTechLab";NA;55;0
"Building";"EngineeringBay";NA;55;0
"Building";"EngineeringBay";NA;55;0
"Unit";"SCV";"Command Center";57;1
"Unit";"SCV";"Command Center";58;1
"Unit";"Marine";"Barracks";58;1
"Unit";"Marine";"Barracks";58;1
"Building";"CommandCenter";NA;47;0
"Unit";"SCV";"Command Center";59;1
"Unit";"SCV";"Command Center";61;1
"Unit";"Raven";"Starport";55;2
"Unit";"SCV";"Command Center";63;1
"Unit";"SCV";"Command Center";65;1
"Unit";"Marine";"Barracks";63;1
"Unit";"Marine";"Barracks";63;1
"Unit";"SCV";"Command Center";68;1
"Unit";"SCV";"Command Center";71;1
"Building";"Barracks";NA;59;0
"Building";"Barracks";NA;59;0
"Unit";"SCV";"Command Center";71;1
"Unit";"SCV";"Command Center";73;1
"Unit";"Marine";"Barracks";71;1
"Unit";"SCV";"Command Center";73;1
"Unit";"Marine";"Barracks";71;1
"Building";"FactoryTechLab";NA;73;0
"Unit";"SCV";"Command Center";73;1
"Unit";"Raven";"Starport";67;2
"Unit";"SCV";"Command Center";74;1
"Unit";"Marine";"Barracks";74;1
"Unit";"SCV";"Command Center";78;1
"Unit";"Marine";"Barracks";78;1
"Unit";"Marine";"Barracks";78;1
"Unit";"SCV";"Command Center";82;1
"Unit";"SCV";"Command Center";82;1
"Building";"Barracks";NA;71;0
"Building";"Barracks";NA;71;0
"Building";"SupplyDepot";NA;78;0
"Building";"SupplyDepot";NA;78;0
"Unit";"Marine";"Barracks";83;1
"Unit";"SCV";"Command Center";88;1
"Unit";"SCV";"Command Center";88;1
"Unit";"Marine";"Barracks";88;1
"Unit";"Marine";"Barracks";88;1
"Unit";"Marine";"Barracks";88;1
"Building";"SupplyDepot";NA;88;0
"Unit";"Marine";"Barracks";89;1
"Building";"StarportReactor";NA;84;0
"Unit";"Marine";"Barracks";91;1
"Building";"BarracksReactor";NA;88;0
"Building";"BarracksReactor";NA;88;0
"Unit";"Marine";"Barracks";94;1
"Unit";"Marine";"Barracks";94;1
"Unit";"SCV";"Command Center";95;1
"Building";"SensorTower";NA;94;0
"Building";"Armory";NA;86;0
"Upgrade";"TerranInfantryWeaponsLevel1";"EngineeringBay";73;0
"Upgrade";"TerranInfantryArmorsLevel1";"EngineeringBay";73;0
"Building";"SupplyDepot";NA;94;0
"Unit";"SCV";"Command Center";95;1
"Building";"SupplyDepot";NA;94;0
"Unit";"Marine";"Barracks";95;1
"Unit";"SCV";"Command Center";99;1
"Unit";"SCV";"Command Center";99;1
"Unit";"SCV";"Command Center";100;1
"Building";"SensorTower";NA;99;0
"Unit";"Medivac";"Starport";95;2
"Unit";"Medivac";"Starport";95;2
"Building";"SupplyDepot";NA;100;0
"Unit";"SCV";"Command Center";101;1
"Unit";"Marine";"Barracks";101;1
"Unit";"Marine";"Barracks";101;1
"Unit";"Marine";"Barracks";101;1
"Unit";"Marine";"Barracks";101;1
"Unit";"SCV";"Command Center";104;1
"Unit";"Marine";"Barracks";104;1
"Unit";"Marine";"Barracks";104;1
"Unit";"Marine";"Barracks";104;1
"Unit";"Marine";"Barracks";104;1
"Unit";"SCV";"Command Center";108;1
"Unit";"Marine";"Barracks";109;1
"Building";"Refinery";NA;108;0
"Building";"Refinery";NA;108;0
"Upgrade";"Stimpack";"TechLab";88;0
"Unit";"Marine";"Barracks";120;1
"Unit";"Marine";"Barracks";120;1
"Unit";"Marine";"Barracks";120;1
"Unit";"Marine";"Barracks";120;1
"Unit";"Marine";"Barracks";120;1
"Unit";"Marine";"Barracks";120;1
"Unit";"Marine";"Barracks";120;1
"Unit";"Marine";"Barracks";120;1
"Unit";"SCV";"Command Center";120;1
"Unit";"SCV";"Command Center";120;1
"Unit";"SCV";"Command Center";120;1
"Unit";"Marine";"Barracks";120;1
"Unit";"Marine";"Barracks";121;1
"Unit";"Marine";"Barracks";122;1
"Unit";"Marine";"Barracks";123;1
"Unit";"Marine";"Barracks";124;1
"Unit";"Marine";"Barracks";125;1
"Unit";"Marine";"Barracks";126;1
"Unit";"SCV";"Command Center";128;1
"Unit";"Marine";"Barracks";127;1
"Unit";"SCV";"Command Center";129;1
"Unit";"SCV";"Command Center";130;1
"Building";"SupplyDepot";NA;131;0
"Building";"SupplyDepot";NA;131;0
"Unit";"Marine";"Barracks";131;1
"Building";"SupplyDepot";NA;131;0
"Unit";"Marine";"Barracks";132;1
"Unit";"Marine";"Barracks";133;1
"Unit";"Marine";"Barracks";134;1
"Unit";"Marine";"Barracks";135;1
"Unit";"Marine";"Barracks";136;1
"Unit";"Marine";"Barracks";137;1
"Building";"MissileTurret";NA;142;0
"Building";"MissileTurret";NA;142;0
"Unit";"Medivac";"Starport";131;2
"Unit";"Medivac";"Starport";131;2
"Building";"MissileTurret";NA;142;0
"Building";"MissileTurret";NA;142;0
"Unit";"Marine";"Barracks";142;1
"Unit";"Marine";"Barracks";142;1
"Unit";"Marine";"Barracks";143;1
"Building";"Factory";NA;131;0
"Unit";"Marine";"Barracks";149;1
"Building";"MissileTurret";NA;149;0
"Unit";"Marine";"Barracks";149;1
"Building";"Barracks";NA;131;0
"Building";"Barracks";NA;131;0
"Unit";"Marine";"Barracks";149;1
"Unit";"Marine";"Barracks";149;1
"Unit";"Marine";"Barracks";149;1
"Unit";"Marine";"Barracks";156;1
"Unit";"Marine";"Barracks";156;1
"Unit";"Marine";"Barracks";157;1
"Unit";"Marine";"Barracks";158;1
"Unit";"Marine";"Barracks";158;1
"Building";"FactoryTechLab";NA;158;0
"Unit";"Medivac";"Starport";153;2
"Unit";"Marine";"Barracks";161;1
"Unit";"Marine";"Barracks";161;1
"Unit";"Marine";"Barracks";161;1
"Building";"BarracksReactor";NA;158;0
"Building";"SupplyDepot";NA;166;0
"Building";"BarracksReactor";NA;161;0
"Unit";"Marine";"Barracks";168;1
"Unit";"Marine";"Barracks";168;1
"Unit";"Marine";"Barracks";168;1
"Unit";"Marine";"Barracks";170;1
"Unit";"Marine";"Barracks";171;1
"Unit";"Marine";"Barracks";171;1
"Unit";"Marine";"Barracks";172;1
"Unit";"Marine";"Barracks";172;1
"Unit";"Marine";"Barracks";173;1
"Unit";"Marine";"Barracks";173;1
"Upgrade";"TerranVehicleWeaponsLevel1";"Armory";149;0
"Unit";"SCV";"Command Center";175;1
"Unit";"SCV";"Command Center";175;1
"Unit";"SCV";"Command Center";175;1
"Unit";"Marine";"Barracks";175;1
"Unit";"Marine";"Barracks";175;1
"Upgrade";"TerranInfantryWeaponsLevel2";"EngineeringBay";142;0
"Upgrade";"TerranInfantryArmorsLevel2";"EngineeringBay";142;0
"Unit";"Marine";"Barracks";175;1
"Unit";"Marine";"Barracks";176;1
"Unit";"SCV";"Command Center";181;1
"Unit";"Marine";"Barracks";181;1
"Unit";"Marine";"Barracks";181;1
"Unit";"Marine";"Barracks";181;1
"Building";"CommandCenter";NA;161;0
"Unit";"SCV";"Command Center";192;1
"Unit";"SCV";"Command Center";192;1
"Unit";"Marine";"Barracks";188;1
"Unit";"Marine";"Barracks";189;1
"Unit";"Marine";"Barracks";189;1
"Unit";"Marine";"Barracks";189;1
"Unit";"Marine";"Barracks";191;1
"Building";"MissileTurret";NA;192;0
"Building";"SensorTower";NA;192;0
"Building";"MissileTurret";NA;192;0
"Building";"MissileTurret";NA;192;0
"Unit";"Marine";"Barracks";192;1
"Unit";"Marine";"Barracks";192;1
"Building";"Barracks";NA;181;0
"Building";"Factory";NA;184;0
"Building";"Barracks";NA;181;0
"Unit";"Marine";"Barracks";199;1
"Unit";"Marine";"Barracks";199;1
"Unit";"Marine";"Barracks";199;1
"Unit";"Marine";"Barracks";199;1
"Unit";"Marine";"Barracks";199;1
"Unit";"Marine";"Barracks";201;1
"Unit";"Marine";"Barracks";201;1
"Unit";"Marine";"Barracks";201;1
"Building";"FactoryTechLab";NA;205;0
