"type";"unit_name";"on_building";"total_supply";"supply"
"Building";"Refinery";NA;14;0
"Building";"Barracks";NA;15;0
"Unit";"Reaper";"Barracks";19;1
"Building";"Refinery";NA;20;0
"Building";"Factory";NA;19;0
"Unit";"Reaper";"Barracks";21;1
"Building";"CommandCenter";NA;19;0
"Unit";"Hellion";"Factory";22;2
"Unit";"Marine";"Barracks";23;1
"Building";"Starport";NA;22;0
"Unit";"Marine";"Barracks";28;1
"Unit";"Cyclone";"Factory";29;3
"Unit";"Medivac";"Starport";29;2
"Unit";"Marine";"Barracks";37;1
"Unit";"Cyclone";"Factory";37;3
"Building";"FactoryTechLab";NA;47;0
"Building";"BarracksReactor";NA;44;0
"Building";"FactoryTechLab";NA;51;0
"Unit";"Marine";"Barracks";53;1
"Unit";"Marine";"Barracks";54;1
"Building";"Refinery";NA;55;0
"Building";"Refinery";NA;55;0
"Building";"EngineeringBay";NA;55;0
"Building";"EngineeringBay";NA;55;0
"Unit";"Marine";"Barracks";59;1
"Unit";"Marine";"Barracks";59;1
"Building";"CommandCenter";NA;49;0
"Unit";"Raven";"Starport";55;2
"Building";"Bunker";NA;59;0
"Unit";"Marine";"Barracks";69;1
"Unit";"Marine";"Barracks";71;1
"Building";"StarportReactor";NA;69;0
"Building";"Barracks";NA;69;0
"Building";"Barracks";NA;69;0
"Unit";"Marine";"Barracks";76;1
"Unit";"Marine";"Barracks";79;1
"Building";"Barracks";NA;74;0
"Building";"Barracks";NA;74;0
"Unit";"Marine";"Barracks";80;1
"Unit";"Marine";"Barracks";84;1
"Unit";"Marine";"Barracks";84;1
"Unit";"Marine";"Barracks";84;1
"Unit";"Marine";"Barracks";84;1
"Upgrade";"TerranInfantryWeaponsLevel1";"EngineeringBay";71;0
"Unit";"Marine";"Barracks";88;1
"Building";"StarportReactor";NA;83;0
"Building";"Armory";NA;80;0
"Unit";"Marine";"Barracks";89;1
"Building";"BarracksReactor";NA;84;0
"Unit";"Marine";"Barracks";95;1
"Building";"BarracksReactor";NA;84;0
"Unit";"Marine";"Barracks";95;1
"Unit";"Marine";"Barracks";95;1
"Unit";"Marine";"Barracks";97;1
"Upgrade";"Stimpack";"TechLab";76;0
"Upgrade";"TerranInfantryArmorsLevel1";"EngineeringBay";77;0
"Unit";"Marine";"Barracks";106;1
"Unit";"Marine";"Barracks";106;1
"Unit";"Marine";"Barracks";106;1
"Unit";"Marine";"Barracks";106;1
"Unit";"Marine";"Barracks";106;1
"Unit";"Marine";"Barracks";106;1
"Unit";"Marine";"Barracks";106;1
"Unit";"Marine";"Barracks";106;1
"Unit";"Marine";"Barracks";106;1
"Unit";"Medivac";"Starport";106;2
"Unit";"Medivac";"Starport";106;2
"Unit";"Marine";"Barracks";112;1
"Unit";"Marine";"Barracks";113;1
"Unit";"Marine";"Barracks";114;1
"Unit";"Marine";"Barracks";121;1
"Unit";"Marine";"Barracks";121;1
"Unit";"Marine";"Barracks";121;1
"Unit";"Marine";"Barracks";121;1
"Unit";"Marine";"Barracks";121;1
"Unit";"Marine";"Barracks";121;1
"Building";"Refinery";NA;121;0
"Building";"Refinery";NA;121;0
"Unit";"Marine";"Barracks";128;1
"Unit";"Marine";"Barracks";129;1
"Unit";"Marine";"Barracks";130;1
"Unit";"Marine";"Barracks";131;1
"Unit";"Marine";"Barracks";132;1
"Unit";"Marine";"Barracks";133;1
"Unit";"Marine";"Barracks";133;1
"Unit";"Marine";"Barracks";138;1
"Unit";"Marine";"Barracks";138;1
"Unit";"Marine";"Barracks";139;1
"Unit";"Marine";"Barracks";140;1
"Unit";"Marine";"Barracks";141;1
"Unit";"Medivac";"Starport";138;2
"Unit";"Medivac";"Starport";138;2
"Unit";"Marine";"Barracks";142;1
"Unit";"Marine";"Barracks";143;1
"Unit";"Marine";"Barracks";148;1
"Unit";"Marine";"Barracks";148;1
"Unit";"Marine";"Barracks";148;1
"Unit";"Marine";"Barracks";148;1
"Unit";"Marine";"Barracks";148;1
"Unit";"Marine";"Barracks";149;1
"Unit";"Marine";"Barracks";150;1
"Unit";"Marine";"Barracks";163;1
"Unit";"Marine";"Barracks";164;1
"Upgrade";"TerranVehicleWeaponsLevel1";"Armory";131;0
"Unit";"Marine";"Barracks";164;1
"Unit";"Marine";"Barracks";164;1
"Unit";"Marine";"Barracks";164;1
"Unit";"Marine";"Barracks";164;1
"Unit";"Marine";"Barracks";164;1
"Unit";"Marine";"Barracks";164;1
"Unit";"Marine";"Barracks";164;1
"Unit";"Marine";"Barracks";164;1
"Unit";"Marine";"Barracks";165;1
"Unit";"Marine";"Barracks";166;1
"Unit";"Marine";"Barracks";167;1
"Unit";"Marine";"Barracks";168;1
"Unit";"Marine";"Barracks";168;1
"Unit";"Marine";"Barracks";170;1
"Upgrade";"TerranInfantryWeaponsLevel2";"EngineeringBay";131;0
"Upgrade";"TerranInfantryArmorsLevel2";"EngineeringBay";131;0
"Unit";"Medivac";"Starport";166;2
"Unit";"Medivac";"Starport";166;2
"Unit";"Marine";"Barracks";175;1
"Unit";"Marine";"Barracks";175;1
"Unit";"Marine";"Barracks";175;1
"Unit";"Marine";"Barracks";175;1
"Building";"Factory";NA;166;0
"Building";"Barracks";NA;166;0
"Unit";"Marine";"Barracks";175;1
"Unit";"Marine";"Barracks";176;1
"Unit";"Marine";"Barracks";177;1
"Unit";"Marine";"Barracks";177;1
"Building";"Barracks";NA;166;0
"Building";"Barracks";NA;166;0
"Unit";"Marine";"Barracks";184;1
"Unit";"Marine";"Barracks";188;1
"Unit";"Marine";"Barracks";188;1
"Unit";"Marine";"Barracks";188;1
"Unit";"Marine";"Barracks";188;1
"Unit";"Marine";"Barracks";188;1
"Unit";"Marine";"Barracks";189;1
"Unit";"Marine";"Barracks";192;1
"Building";"FactoryTechLab";NA;192;0
"Building";"CommandCenter";NA;166;0
"Building";"BarracksReactor";NA;192;0
"Building";"BarracksReactor";NA;192;0
"Building";"BarracksReactor";NA;192;0
"Unit";"Marine";"Barracks";200;1
"Unit";"Marine";"Barracks";200;1
"Unit";"Marine";"Barracks";200;1
"Unit";"Marine";"Barracks";200;1
"Unit";"Marine";"Barracks";200;1
"Unit";"Marine";"Barracks";200;1
"Unit";"Marine";"Barracks";200;1
"Unit";"Marine";"Barracks";200;1
"Unit";"Marine";"Barracks";207;1
"Unit";"Marine";"Barracks";207;1
"Unit";"Marine";"Barracks";208;1
"Unit";"Marine";"Barracks";208;1
"Unit";"Marine";"Barracks";208;1
"Unit";"Marine";"Barracks";208;1
"Unit";"Marine";"Barracks";208;1
"Unit";"Marine";"Barracks";208;1
"Unit";"Marine";"Barracks";208;1
"Unit";"Marine";"Barracks";208;1
"Unit";"Marine";"Barracks";208;1
"Unit";"Marine";"Barracks";208;1
"Unit";"Marine";"Barracks";208;1
"Unit";"Marine";"Barracks";208;1
"Unit";"Marine";"Barracks";208;1
"Unit";"Medivac";"Starport";208;2
"Unit";"Medivac";"Starport";208;2
"Building";"Refinery";NA;227;0
"Unit";"Marine";"Barracks";227;1
"Building";"Refinery";NA;227;0
"Unit";"Marine";"Barracks";227;1
"Unit";"Marine";"Barracks";227;1
"Unit";"Marine";"Barracks";227;1
"Unit";"Marine";"Barracks";227;1
"Unit";"Marine";"Barracks";227;1
"Unit";"Marine";"Barracks";227;1
"Unit";"Marine";"Barracks";227;1
"Unit";"Marine";"Barracks";227;1
"Unit";"Marine";"Barracks";227;1
"Unit";"Marine";"Barracks";227;1
"Unit";"Marine";"Barracks";227;1
"Unit";"Marine";"Barracks";227;1
"Building";"Factory";NA;223;0
"Unit";"Marine";"Barracks";227;1
"Unit";"Marine";"Barracks";227;1
"Unit";"Marine";"Barracks";240;1
"Unit";"Marine";"Barracks";242;1
"Unit";"Marine";"Barracks";242;1
"Unit";"Marine";"Barracks";242;1
"Unit";"Marine";"Barracks";242;1
"Unit";"Marine";"Barracks";242;1
"Unit";"Marine";"Barracks";242;1
"Unit";"Marine";"Barracks";242;1
"Unit";"Marine";"Barracks";242;1
"Unit";"Marine";"Barracks";242;1
"Unit";"Marine";"Barracks";242;1
"Unit";"Marine";"Barracks";242;1
"Unit";"Marine";"Barracks";242;1
"Unit";"Marine";"Barracks";255;1
"Unit";"Marine";"Barracks";255;1
"Building";"FactoryTechLab";NA;255;0
"Unit";"Marine";"Barracks";255;1
"Unit";"Marine";"Barracks";255;1
"Unit";"Marine";"Barracks";255;1
"Building";"Bunker";NA;260;0
"Building";"Factory";NA;260;0
"Building";"Factory";NA;260;0
