"type";"unit_name";"on_building";"total_supply";"supply"
"Building";"Refinery";NA;14;0
"Building";"Refinery";NA;16;0
"Building";"Barracks";NA;15;0
"Building";"BarracksReactor";NA;19;0
"Building";"Factory";NA;19;0
"Unit";"Cyclone";"Factory";20;3
"Unit";"Cyclone";"Factory";20;3
"Unit";"Cyclone";"Factory";26;3
"Unit";"Cyclone";"Factory";26;3
"Unit";"Marine";"Barracks";32;1
"Unit";"Cyclone";"Factory";32;3
"Unit";"Cyclone";"Factory";33;3
"Unit";"Marine";"Barracks";37;1
