"type";"unit_name";"on_building";"total_supply";"supply"
"Building";"Refinery";NA;14;0
"Building";"Refinery";NA;16;0
"Building";"Barracks";NA;15;0
"Unit";"Reaper";"Barracks";19;1
"Building";"Factory";NA;19;0
"Unit";"Reaper";"Barracks";20;1
"Unit";"Cyclone";"Factory";21;3
"Building";"Starport";NA;21;0
"Building";"BarracksTechLab";NA;28;0
"Unit";"Cyclone";"Factory";27;3
"Unit";"Medivac";"Starport";27;2
