"Type";"UnitName";"OnBuilding";"TotalSupply";"Supply"
"Unit";"SCV";"Command Center";12;1
"Unit";"SCV";"Command Center";12;1
"Unit";"SCV";"Command Center";13;1
"Building";"SupplyDepot";NA;13;0
"Building";"Refinery";NA;14;0
"Unit";"SCV";"Command Center";15;1
"Unit";"SCV";"Command Center";16;1
"Unit";"SCV";"Command Center";16;1
"Unit";"SCV";"Command Center";17;1
"Building";"Barracks";NA;15;0
"Building";"Refinery";NA;19;0
"Unit";"Reaper";"Barracks";19;1
"Unit";"SCV";"Command Center";19;1
"Building";"SupplyDepot";NA;19;0
"Unit";"SCV";"Command Center";21;1
"Building";"Factory";NA;19;0
"Unit";"SCV";"Command Center";22;1
"Unit";"Reaper";"Barracks";20;1
"Unit";"SCV";"Command Center";22;1
"Unit";"SCV";"Command Center";24;1
"Unit";"SCV";"Command Center";25;1
"Building";"BarracksReactor";NA;24;0
"Unit";"Cyclone";"Factory";25;3
"Unit";"SCV";"Command Center";26;1
"Building";"SupplyDepot";NA;26;0
"Unit";"SCV";"Command Center";30;1
"Unit";"SCV";"Command Center";32;1
"Unit";"SCV";"Command Center";32;1
"Unit";"Cyclone";"Factory";32;3
"Unit";"Cyclone";"Factory";32;3
"Building";"BarracksTechLab";NA;32;0
"Unit";"SCV";"Command Center";33;1
"Building";"Starport";NA;32;0
"Unit";"Hellion";"Factory";40;2
"Building";"CommandCenter";NA;25;0
"Unit";"SCV";"Command Center";41;1
"Building";"SupplyDepot";NA;40;0
"Building";"SupplyDepot";NA;40;0
"Building";"EngineeringBay";NA;40;0
"Unit";"Hellion";"Factory";43;2
"Unit";"SCV";"Command Center";44;1
"Building";"BarracksReactor";NA;41;0
"Unit";"SCV";"Command Center";47;1
"Building";"MissileTurret";NA;46;0
"Unit";"SCV";"Command Center";47;1
"Unit";"Marine";"Barracks";47;1
"Unit";"Marine";"Barracks";47;1
"Unit";"SCV";"Command Center";48;1
"Building";"FactoryTechLab";NA;48;0
"Building";"MissileTurret";NA;48;0
"Unit";"Banshee";"Starport";44;3
"Unit";"SCV";"Command Center";48;1
"Unit";"Marine";"Barracks";51;1
"Unit";"Marine";"Barracks";51;1
"Unit";"SCV";"Command Center";52;1
"Unit";"SCV";"Command Center";56;1
"Unit";"SCV";"Command Center";59;1
"Unit";"SCV";"Command Center";59;1
"Unit";"Marine";"Barracks";59;1
"Unit";"Marine";"Barracks";59;1
"Building";"SupplyDepot";NA;60;0
"Unit";"SCV";"Command Center";62;1
"Unit";"SCV";"Command Center";62;1
"Building";"Refinery";NA;61;0
"Unit";"Banshee";"Starport";56;3
"Building";"Refinery";NA;61;0
"Unit";"SCV";"Command Center";64;1
"Unit";"SCV";"Command Center";66;1
"Unit";"SCV";"Command Center";69;1
"Unit";"SCV";"Command Center";70;1
"Building";"SupplyDepot";NA;70;0
"Unit";"SCV";"Command Center";72;1
"Unit";"SCV";"Command Center";72;1
"Building";"SensorTower";NA;73;0
"Unit";"SCV";"Command Center";73;1
"Unit";"SCV";"Command Center";74;1
"Building";"StarportReactor";NA;71;0
"Unit";"Marine";"Barracks";75;1
"Building";"SupplyDepot";NA;74;0
"Building";"Barracks";NA;71;0
"Unit";"SCV";"Command Center";78;1
"Unit";"SCV";"Command Center";78;1
"Unit";"Marine";"Barracks";77;1
"Building";"Barracks";NA;73;0
"Building";"CommandCenter";NA;69;0
"Unit";"SCV";"Command Center";78;1
"Unit";"SCV";"Command Center";81;1
"Unit";"Marine";"Barracks";81;1
"Unit";"Marine";"Barracks";81;1
"Unit";"Marine";"Barracks";81;1
"Unit";"Marine";"Barracks";81;1
"Unit";"Marine";"Barracks";81;1
"Unit";"Medivac";"Starport";78;2
"Unit";"Medivac";"Starport";78;2
"Unit";"SCV";"Command Center";82;1
"Unit";"SCV";"Command Center";92;1
"Unit";"Marine";"Barracks";83;1
"Unit";"Marine";"Barracks";84;1
"Unit";"Marine";"Barracks";88;1
"Unit";"Marine";"Barracks";88;1
"Unit";"Marine";"Barracks";88;1
"Unit";"SCV";"Command Center";93;1
"Unit";"SCV";"Command Center";93;1
"Unit";"SCV";"Command Center";93;1
"Building";"SupplyDepot";NA;93;0
"Building";"SupplyDepot";NA;93;0
"Building";"SupplyDepot";NA;93;0
"Unit";"Marine";"Barracks";94;1
"Unit";"Marine";"Barracks";95;1
"Unit";"Marine";"Barracks";96;1
"Building";"Barracks";NA;82;0
"Building";"Barracks";NA;82;0
"Unit";"SCV";"Command Center";102;1
"Unit";"Marine";"Barracks";102;1
"Unit";"Marine";"Barracks";102;1
"Unit";"Marine";"Barracks";102;1
"Unit";"Medivac";"Starport";102;2
"Unit";"Medivac";"Starport";102;2
"Unit";"Marine";"Barracks";105;1
"Unit";"Marine";"Barracks";105;1
"Upgrade";"Stimpack";"TechLab";81;0
"Building";"Factory";NA;101;0
"Upgrade";"TerranInfantryWeaponsLevel1";"EngineeringBay";82;0
"Unit";"Marine";"Barracks";115;1
"Unit";"Marine";"Barracks";115;1
"Building";"SensorTower";NA;106;0
"Unit";"Marine";"Barracks";115;1
"Unit";"Marine";"Barracks";115;1
"Unit";"Marine";"Barracks";115;1
"Building";"FactoryTechLab";NA;115;0
"Unit";"Marine";"Barracks";115;1
"Unit";"Marine";"Barracks";116;1
"Unit";"Marine";"Barracks";117;1
"Unit";"Marine";"Barracks";118;1
"Building";"BarracksReactor";NA;115;0
"Building";"BarracksReactor";NA;115;0
"Building";"SupplyDepot";NA;117;0
"Unit";"SCV";"Command Center";120;1
"Unit";"SCV";"Command Center";120;1
"Unit";"Marine";"Barracks";119;1
"Building";"EngineeringBay";NA;119;0
"Unit";"Marine";"Barracks";120;1
"Unit";"Marine";"Barracks";121;1
"Unit";"Marine";"Barracks";122;1
"Unit";"Marine";"Barracks";125;1
"Unit";"Marine";"Barracks";126;1
"Unit";"Marine";"Barracks";126;1
"Unit";"Marine";"Barracks";127;1
"Unit";"Marine";"Barracks";127;1
"Unit";"Marine";"Barracks";127;1
"Building";"Armory";NA;119;0
"Unit";"Marine";"Barracks";127;1
"Unit";"Marine";"Barracks";130;1
"Unit";"Marine";"Barracks";130;1
"Unit";"Medivac";"Starport";127;2
"Building";"SupplyDepot";NA;141;0
"Building";"SupplyDepot";NA;141;0
"Upgrade";"TerranInfantryArmorsLevel1";"EngineeringBay";127;0
"Unit";"Marine";"Barracks";141;1
"Unit";"Marine";"Barracks";141;1
"Unit";"Marine";"Barracks";141;1
"Unit";"Marine";"Barracks";141;1
"Unit";"Marine";"Barracks";141;1
"Unit";"Marine";"Barracks";141;1
"Building";"SupplyDepot";NA;141;0
"Building";"SupplyDepot";NA;141;0
"Building";"SupplyDepot";NA;141;0
"Unit";"Marine";"Barracks";141;1
"Building";"SupplyDepot";NA;141;0
"Building";"SupplyDepot";NA;141;0
"Building";"CommandCenter";NA;141;0
"Building";"SupplyDepot";NA;141;0
"Building";"SupplyDepot";NA;141;0
"Unit";"Marine";"Barracks";147;1
"Unit";"Marine";"Barracks";147;1
"Unit";"Marine";"Barracks";147;1
"Unit";"Marine";"Barracks";147;1
"Unit";"Marine";"Barracks";147;1
"Unit";"Marine";"Barracks";147;1
"Unit";"Marine";"Barracks";147;1
"Unit";"Marine";"Barracks";155;1
"Unit";"Marine";"Barracks";155;1
"Unit";"Marine";"Barracks";155;1
"Unit";"Marine";"Barracks";155;1
"Unit";"Marine";"Barracks";155;1
"Unit";"Marine";"Barracks";155;1
"Unit";"Marine";"Barracks";155;1
"Unit";"Marine";"Barracks";155;1
"Unit";"Marine";"Barracks";159;1
"Unit";"Marine";"Barracks";159;1
"Unit";"Marine";"Barracks";161;1
"Unit";"Marine";"Barracks";161;1
"Unit";"Marine";"Barracks";165;1
"Unit";"Marine";"Barracks";165;1
"Unit";"Marine";"Barracks";165;1
