"Type";"UnitName";"OnBuilding";"TotalSupply";"Supply"
"Unit";"SCV";"Command Center";12;1
"Unit";"SCV";"Command Center";12;1
"Unit";"SCV";"Command Center";13;1
"Building";"SupplyDepot";NA;13;0
"Building";"Refinery";NA;14;0
"Unit";"SCV";"Command Center";15;1
"Unit";"SCV";"Command Center";15;1
"Unit";"SCV";"Command Center";16;1
"Unit";"SCV";"Command Center";17;1
"Building";"Barracks";NA;15;0
"Building";"Refinery";NA;17;0
"Unit";"Reaper";"Barracks";19;1
"Building";"SupplyDepot";NA;19;0
"Unit";"SCV";"Command Center";20;1
"Building";"Factory";NA;19;0
"Unit";"SCV";"Command Center";21;1
"Unit";"Reaper";"Barracks";19;1
"Unit";"SCV";"Command Center";21;1
"Unit";"Hellion";"Factory";21;2
"Unit";"SCV";"Command Center";24;1
"Building";"Starport";NA;21;0
"Building";"SupplyDepot";NA;24;0
"Unit";"SCV";"Command Center";26;1
"Building";"BarracksReactor";NA;24;0
"Unit";"SCV";"Command Center";27;1
"Unit";"Cyclone";"Factory";27;3
"Unit";"SCV";"Command Center";28;1
"Unit";"Medivac";"Starport";28;2
"Unit";"Marine";"Barracks";33;1
"Unit";"Cyclone";"Factory";33;3
"Building";"SupplyDepot";NA;33;0
"Unit";"SCV";"Command Center";39;1
"Building";"SupplyDepot";NA;35;0
"Unit";"Marine";"Barracks";39;1
"Building";"FactoryTechLab";NA;39;0
"Building";"CommandCenter";NA;32;0
"Unit";"SCV";"Command Center";41;1
"Building";"EngineeringBay";NA;39;0
"Unit";"Liberator";"Starport";39;3
"Building";"SupplyDepot";NA;41;0
"Unit";"SCV";"Command Center";42;1
"Unit";"Marine";"Barracks";41;1
"Unit";"Marine";"Barracks";42;1
"Building";"Barracks";NA;39;0
"Building";"FactoryTechLab";NA;45;0
"Building";"Barracks";NA;41;0
"Unit";"Marine";"Barracks";47;1
"Unit";"SCV";"Command Center";48;1
"Unit";"SCV";"Command Center";50;1
"Unit";"Marine";"Barracks";48;1
"Unit";"Marine";"Barracks";49;1
"Building";"Bunker";NA;48;0
"Unit";"SCV";"Command Center";51;1
"Unit";"SCV";"Command Center";52;1
"Building";"StarportReactor";NA;48;0
"Unit";"Marine";"Barracks";50;1
"Unit";"Marine";"Barracks";53;1
"Unit";"Marine";"Barracks";53;1
"Building";"BarracksReactor";NA;50;0
"Unit";"SCV";"Command Center";56;1
"Unit";"Marine";"Barracks";56;1
"Unit";"Marine";"Barracks";56;1
"Unit";"Marine";"Barracks";57;1
"Unit";"SCV";"Command Center";60;1
"Unit";"Medivac";"Starport";56;2
"Unit";"Medivac";"Starport";56;2
"Unit";"Marine";"Barracks";58;1
"Unit";"Marine";"Barracks";63;1
"Unit";"Marine";"Barracks";63;1
"Unit";"Marine";"Barracks";65;1
"Unit";"Marine";"Barracks";67;1
"Unit";"SCV";"Command Center";69;1
"Unit";"SCV";"Command Center";70;1
"Unit";"Marine";"Barracks";68;1
"Unit";"Marine";"Barracks";68;1
"Unit";"Marine";"Barracks";72;1
"Unit";"SCV";"Command Center";75;1
"Unit";"SCV";"Command Center";75;1
"Unit";"Medivac";"Starport";68;2
"Unit";"Medivac";"Starport";68;2
"Unit";"Marine";"Barracks";73;1
"Unit";"Marine";"Barracks";74;1
"Building";"Bunker";NA;72;0
"Building";"Refinery";NA;75;0
"Upgrade";"Stimpack";"TechLab";56;0
"Unit";"Marine";"Barracks";76;1
"Unit";"Marine";"Barracks";77;1
"Unit";"Marine";"Barracks";77;1
"Building";"SupplyDepot";NA;85;0
"Unit";"Marine";"Barracks";88;1
"Unit";"Marine";"Barracks";88;1
"Unit";"Marine";"Barracks";88;1
"Unit";"SCV";"Command Center";88;1
"Unit";"Marine";"Barracks";88;1
"Unit";"Marine";"Barracks";88;1
"Unit";"Marine";"Barracks";88;1
"Unit";"Marine";"Barracks";91;1
"Building";"SupplyDepot";NA;91;0
"Building";"SupplyDepot";NA;91;0
"Building";"SupplyDepot";NA;91;0
"Building";"EngineeringBay";NA;91;0
"Unit";"Marine";"Barracks";96;1
"Unit";"Marine";"Barracks";96;1
"Unit";"Marine";"Barracks";96;1
"Upgrade";"TerranInfantryWeaponsLevel1";"EngineeringBay";85;0
"Unit";"SCV";"Command Center";96;1
"Unit";"Marine";"Barracks";96;1
"Unit";"SCV";"Command Center";96;1
"Unit";"Marine";"Barracks";96;1
"Building";"Refinery";NA;96;0
"Unit";"Marine";"Barracks";96;1
"Unit";"SCV";"Command Center";99;1
"Unit";"Marine";"Barracks";99;1
"Unit";"Marine";"Barracks";99;1
"Building";"Barracks";NA;95;0
"Building";"Barracks";NA;95;0
"Unit";"Marine";"Barracks";99;1
"Unit";"SCV";"Command Center";103;1
"Building";"CommandCenter";NA;88;0
"Unit";"Medivac";"Starport";103;2
"Unit";"SCV";"Command Center";109;1
"Unit";"Marine";"Barracks";107;1
"Unit";"Marine";"Barracks";107;1
"Unit";"Marine";"Barracks";107;1
"Unit";"Medivac";"Starport";103;2
"Unit";"Marine";"Barracks";109;1
"Building";"BarracksReactor";NA;108;0
"Building";"BarracksReactor";NA;108;0
"Unit";"Marine";"Barracks";117;1
"Unit";"Marine";"Barracks";117;1
"Unit";"Marine";"Barracks";118;1
"Unit";"Marine";"Barracks";118;1
"Unit";"Marine";"Barracks";120;1
"Unit";"Marine";"Barracks";120;1
"Unit";"Marine";"Barracks";120;1
"Unit";"Marine";"Barracks";120;1
"Unit";"Marine";"Barracks";120;1
"Unit";"Marine";"Barracks";120;1
"Unit";"Marine";"Barracks";122;1
"Unit";"Marine";"Barracks";122;1
"Unit";"Marine";"Barracks";122;1
"Unit";"SCV";"Command Center";128;1
"Unit";"SCV";"Command Center";128;1
"Unit";"Marine";"Barracks";122;1
"Unit";"Marine";"Barracks";123;1
"Unit";"Marine";"Barracks";124;1
"Unit";"Marine";"Barracks";128;1
"Unit";"Marine";"Barracks";128;1
"Unit";"SCV";"Command Center";131;1
"Unit";"Medivac";"Starport";133;2
"Unit";"Marine";"Barracks";139;1
"Unit";"Medivac";"Starport";136;2
"Unit";"Marine";"Barracks";139;1
"Unit";"Marine";"Barracks";139;1
"Unit";"Marine";"Barracks";139;1
"Building";"Armory";NA;133;0
"Unit";"Marine";"Barracks";146;1
"Unit";"Marine";"Barracks";148;1
"Unit";"Marine";"Barracks";148;1
"Unit";"Marine";"Barracks";148;1
"Unit";"Marine";"Barracks";148;1
"Unit";"Marine";"Barracks";148;1
"Unit";"Marine";"Barracks";148;1
"Unit";"Marine";"Barracks";148;1
"Building";"SensorTower";NA;148;0
"Unit";"SCV";"Command Center";148;1
"Unit";"SCV";"Command Center";148;1
"Unit";"SCV";"Command Center";148;1
"Unit";"Marine";"Barracks";148;1
"Unit";"Marine";"Barracks";148;1
"Unit";"SCV";"Command Center";155;1
"Unit";"SCV";"Command Center";156;1
"Unit";"SCV";"Command Center";157;1
"Unit";"Marine";"Barracks";148;1
"Unit";"Marine";"Barracks";148;1
"Unit";"Marine";"Barracks";148;1
"Unit";"Marine";"Barracks";156;1
"Unit";"Marine";"Barracks";157;1
"Unit";"Marine";"Barracks";158;1
"Unit";"Marine";"Barracks";158;1
"Upgrade";"TerranInfantryArmorsLevel1";"EngineeringBay";139;0
"Unit";"Marine";"Barracks";160;1
"Unit";"Marine";"Barracks";160;1
"Unit";"Marine";"Barracks";170;1
"Building";"Factory";NA;152;0
"Unit";"Marine";"Barracks";170;1
"Building";"Barracks";NA;155;0
"Building";"Barracks";NA;155;0
"Unit";"SCV";"Command Center";172;1
"Unit";"Marine";"Barracks";172;1
"Unit";"Marine";"Barracks";172;1
"Unit";"Marine";"Barracks";172;1
"Unit";"SCV";"Command Center";174;1
"Unit";"Marine";"Barracks";172;1
"Unit";"Medivac";"Starport";170;2
"Unit";"Medivac";"Starport";170;2
"Unit";"Marine";"Barracks";174;1
"Unit";"Marine";"Barracks";174;1
"Unit";"SCV";"Command Center";178;1
"Unit";"Marine";"Barracks";174;1
"Unit";"Marine";"Barracks";174;1
"Unit";"SCV";"Command Center";184;1
"Unit";"SCV";"Command Center";184;1
"Unit";"Marine";"Barracks";182;1
"Unit";"Marine";"Barracks";182;1
"Unit";"Marine";"Barracks";182;1
"Building";"FactoryTechLab";NA;184;0
"Unit";"Marine";"Barracks";187;1
"Unit";"Marine";"Barracks";187;1
"Unit";"Marine";"Barracks";187;1
"Unit";"SCV";"Command Center";189;1
"Building";"Refinery";NA;184;0
"Building";"Refinery";NA;186;0
"Building";"BarracksReactor";NA;178;0
"Building";"BarracksReactor";NA;178;0
"Unit";"Marine";"Barracks";189;1
"Unit";"Marine";"Barracks";189;1
"Unit";"Marine";"Barracks";189;1
"Upgrade";"TerranVehicleWeaponsLevel1";"Armory";160;0
"Unit";"Marine";"Barracks";194;1
"Unit";"Marine";"Barracks";194;1
"Unit";"Marine";"Barracks";194;1
"Building";"MissileTurret";NA;194;0
"Unit";"Marine";"Barracks";194;1
"Unit";"Marine";"Barracks";201;1
"Unit";"Marine";"Barracks";201;1
"Unit";"Marine";"Barracks";201;1
"Unit";"Marine";"Barracks";201;1
"Unit";"Medivac";"Starport";194;2
"Unit";"Marine";"Barracks";201;1
"Upgrade";"TerranInfantryWeaponsLevel2";"EngineeringBay";166;0
"Unit";"Marine";"Barracks";206;1
"Unit";"Marine";"Barracks";209;1
"Unit";"Marine";"Barracks";211;1
"Unit";"Marine";"Barracks";211;1
"Unit";"Marine";"Barracks";211;1
"Unit";"Marine";"Barracks";211;1
"Unit";"Marine";"Barracks";211;1
"Unit";"Marine";"Barracks";214;1
"Unit";"Marine";"Barracks";214;1
"Unit";"Marine";"Barracks";215;1
"Unit";"Marine";"Barracks";215;1
"Unit";"Marine";"Barracks";216;1
"Unit";"Marine";"Barracks";216;1
"Unit";"Marine";"Barracks";216;1
"Unit";"Marine";"Barracks";218;1
"Unit";"Marine";"Barracks";218;1
"Unit";"Marine";"Barracks";219;1
"Unit";"Marine";"Barracks";219;1
"Unit";"Marine";"Barracks";228;1
"Unit";"Marine";"Barracks";228;1
"Unit";"Marine";"Barracks";228;1
"Unit";"Marine";"Barracks";228;1
"Building";"StarportTechLab";NA;231;0
"Unit";"SCV";"Command Center";234;1
"Unit";"SCV";"Command Center";234;1
"Unit";"Banshee";"Starport";234;3
"Unit";"Marine";"Barracks";234;1
"Unit";"Marine";"Barracks";234;1
"Unit";"Marine";"Barracks";241;1
"Unit";"Marine";"Barracks";241;1
"Unit";"Marine";"Barracks";241;1
"Unit";"SCV";"Command Center";241;1
"Unit";"SCV";"Command Center";241;1
"Unit";"Marine";"Barracks";241;1
"Unit";"Marine";"Barracks";241;1
"Unit";"Marine";"Barracks";241;1
"Unit";"Banshee";"Starport";241;3
"Unit";"Marine";"Barracks";248;1
"Unit";"Marine";"Barracks";248;1
"Unit";"SCV";"Command Center";252;1
"Unit";"Marine";"Barracks";252;1
"Unit";"Marine";"Barracks";252;1
"Unit";"Marine";"Barracks";252;1
