"Type";"UnitName";"OnBuilding";"TotalSupply";"Supply"
"Unit";"SCV";"Command Center";12;1
"Unit";"SCV";"Command Center";12;1
"Unit";"SCV";"Command Center";13;1
"Building";"SupplyDepot";NA;13;0
"Unit";"SCV";"Command Center";15;1
"Unit";"SCV";"Command Center";15;1
"Building";"Refinery";NA;15;0
"Unit";"SCV";"Command Center";16;1
"Building";"Barracks";NA;15;0
"Unit";"SCV";"Command Center";17;1
"Unit";"Reaper";"Barracks";19;1
"Unit";"SCV";"Command Center";19;1
"Building";"SupplyDepot";NA;19;0
"Unit";"Marine";"Barracks";20;1
"Unit";"SCV";"Command Center";21;1
"Unit";"Marine";"Barracks";22;1
"Unit";"SCV";"Command Center";23;1
"Building";"Factory";NA;21;0
"Building";"CommandCenter";NA;19;0
"Unit";"Marine";"Barracks";23;1
"Building";"Refinery";NA;23;0
"Unit";"SCV";"Command Center";24;1
"Unit";"SCV";"Command Center";26;1
"Unit";"Marine";"Barracks";25;1
"Unit";"SCV";"Command Center";27;1
"Unit";"Cyclone";"Factory";27;3
"Unit";"SCV";"Command Center";29;1
"Unit";"SCV";"Command Center";30;1
"Unit";"Marine";"Barracks";30;1
"Unit";"SCV";"Command Center";33;1
"Building";"Starport";NA;28;0
"Building";"SupplyDepot";NA;30;0
"Unit";"SCV";"Command Center";34;1
"Unit";"Marine";"Barracks";35;1
"Unit";"SCV";"Command Center";36;1
"Unit";"SCV";"Command Center";37;1
"Building";"SupplyDepot";NA;36;0
"Unit";"SCV";"Command Center";39;1
"Unit";"Cyclone";"Factory";37;3
"Unit";"SCV";"Command Center";40;1
"Unit";"Marine";"Barracks";38;1
"Unit";"SCV";"Command Center";41;1
"Unit";"Medivac";"Starport";38;2
"Unit";"SCV";"Command Center";46;1
"Unit";"SCV";"Command Center";47;1
"Building";"BarracksTechLab";NA;47;0
"Unit";"SCV";"Command Center";51;1
"Unit";"SCV";"Command Center";51;1
"Unit";"SCV";"Command Center";52;1
"Unit";"Marine";"Barracks";52;1
"Building";"FactoryTechLab";NA;52;0
"Unit";"SCV";"Command Center";53;1
"Building";"SupplyDepot";NA;53;0
"Unit";"SCV";"Command Center";54;1
"Building";"Refinery";NA;53;0
"Building";"Refinery";NA;53;0
"Building";"Barracks";NA;50;0
"Unit";"SCV";"Command Center";56;1
"Unit";"Marine";"Barracks";55;1
"Building";"SupplyDepot";NA;55;0
"Unit";"SCV";"Command Center";57;1
"Unit";"SCV";"Command Center";58;1
"Building";"CommandCenter";NA;46;0
"Building";"Barracks";NA;52;0
"Unit";"Marine";"Barracks";59;1
"Building";"StarportReactor";NA;54;0
"Unit";"Marine";"Barracks";59;1
"Unit";"SCV";"Command Center";62;1
"Unit";"SCV";"Command Center";62;1
"Building";"SupplyDepot";NA;62;0
"Unit";"Marine";"Barracks";63;1
"Unit";"SCV";"Command Center";66;1
"Unit";"SCV";"Command Center";66;1
"Building";"EngineeringBay";NA;64;0
"Unit";"SCV";"Command Center";67;1
"Unit";"SCV";"Command Center";68;1
"Building";"BarracksReactor";NA;63;0
"Building";"BarracksReactor";NA;63;0
"Building";"EngineeringBay";NA;66;0
"Unit";"Marine";"Barracks";69;1
"Building";"EngineeringBay";NA;66;0
"Building";"Barracks";NA;64;0
"Unit";"SCV";"Command Center";71;1
"Unit";"SCV";"Command Center";71;1
"Unit";"Marine";"Barracks";71;1
"Unit";"Marine";"Barracks";71;1
"Unit";"Marine";"Barracks";71;1
"Unit";"Marine";"Barracks";71;1
"Unit";"Marine";"Barracks";72;1
"Unit";"SCV";"Command Center";72;1
"Unit";"SCV";"Command Center";73;1
"Building";"MissileTurret";NA;72;0
"Upgrade";"Stimpack";"TechLab";59;0
"Unit";"SCV";"Command Center";78;1
"Unit";"Marine";"Barracks";74;1
"Unit";"Marine";"Barracks";75;1
"Unit";"SCV";"Command Center";79;1
"Unit";"Medivac";"Starport";72;2
"Unit";"Medivac";"Starport";72;2
"Unit";"Marine";"Barracks";79;1
"Unit";"Marine";"Barracks";79;1
"Unit";"Marine";"Barracks";79;1
"Building";"MissileTurret";NA;79;0
"Unit";"SCV";"Command Center";81;1
"Building";"MissileTurret";NA;81;0
"Unit";"SCV";"Command Center";81;1
"Unit";"SCV";"Command Center";84;1
"Unit";"Marine";"Barracks";82;1
"Unit";"Marine";"Barracks";85;1
"Building";"BarracksReactor";NA;78;0
"Building";"MissileTurret";NA;92;0
"Building";"MissileTurret";NA;93;0
"Unit";"SCV";"Command Center";97;1
"Building";"Barracks";NA;81;0
"Building";"Barracks";NA;81;0
"Unit";"SCV";"Command Center";97;1
"Unit";"SCV";"Command Center";97;1
"Building";"SupplyDepot";NA;97;0
"Building";"SupplyDepot";NA;97;0
"Unit";"Marine";"Barracks";97;1
"Unit";"Marine";"Barracks";97;1
"Unit";"Marine";"Barracks";97;1
"Unit";"Marine";"Barracks";97;1
"Unit";"Marine";"Barracks";97;1
"Unit";"Marine";"Barracks";97;1
"Unit";"Marine";"Barracks";97;1
"Unit";"Marine";"Barracks";100;1
"Unit";"Marine";"Barracks";100;1
"Unit";"Marine";"Barracks";102;1
"Unit";"Marine";"Barracks";102;1
"Unit";"Marine";"Barracks";104;1
"Unit";"Marine";"Barracks";105;1
"Unit";"Marine";"Barracks";105;1
"Unit";"Medivac";"Starport";98;2
"Upgrade";"TerranInfantryWeaponsLevel1";"EngineeringBay";85;0
"Upgrade";"TerranInfantryArmorsLevel1";"EngineeringBay";85;0
"Unit";"SCV";"Command Center";116;1
"Unit";"Marine";"Barracks";107;1
"Unit";"Marine";"Barracks";107;1
"Unit";"Marine";"Barracks";109;1
"Unit";"Marine";"Barracks";112;1
"Unit";"Marine";"Barracks";112;1
"Unit";"Marine";"Barracks";114;1
"Unit";"Marine";"Barracks";116;1
"Building";"SensorTower";NA;116;0
"Building";"BarracksReactor";NA;107;0
"Building";"BarracksReactor";NA;116;0
"Unit";"Medivac";"Starport";116;2
"Building";"Barracks";NA;109;0
"Unit";"Medivac";"Starport";117;2
"Building";"SupplyDepot";NA;123;0
"Building";"SupplyDepot";NA;124;0
"Unit";"Marine";"Barracks";124;1
"Unit";"Marine";"Barracks";124;1
"Unit";"Marine";"Barracks";124;1
"Building";"Armory";NA;116;0
"Unit";"SCV";"Command Center";128;1
"Unit";"SCV";"Command Center";128;1
"Unit";"SCV";"Command Center";128;1
"Unit";"Marine";"Barracks";124;1
"Unit";"Marine";"Barracks";128;1
"Unit";"Marine";"Barracks";128;1
"Unit";"Marine";"Barracks";128;1
"Unit";"SCV";"Command Center";131;1
"Unit";"SCV";"Command Center";132;1
"Unit";"Marauder";"Barracks";128;2
"Building";"SupplyDepot";NA;131;0
"Unit";"Marine";"Barracks";131;1
"Unit";"Marine";"Barracks";131;1
"Unit";"Marine";"Barracks";131;1
"Unit";"SCV";"Command Center";142;1
"Unit";"SCV";"Command Center";142;1
"Unit";"SCV";"Command Center";142;1
"Unit";"Marine";"Barracks";142;1
"Unit";"Marine";"Barracks";142;1
"Unit";"Marine";"Barracks";142;1
"Unit";"Marauder";"Barracks";142;2
"Unit";"Marine";"Barracks";145;1
"Unit";"Marine";"Barracks";148;1
"Unit";"Marine";"Barracks";150;1
"Unit";"SCV";"Command Center";153;1
"Unit";"Marine";"Barracks";153;1
"Unit";"Marine";"Barracks";154;1
"Unit";"Marine";"Barracks";154;1
"Unit";"Marine";"Barracks";154;1
"Unit";"Marine";"Barracks";154;1
"Unit";"Marine";"Barracks";154;1
"Unit";"Marine";"Barracks";155;1
"Unit";"Marine";"Barracks";156;1
"Unit";"Marine";"Barracks";156;1
"Unit";"Marine";"Barracks";157;1
"Unit";"Marine";"Barracks";157;1
"Unit";"Marine";"Barracks";158;1
"Unit";"Marine";"Barracks";158;1
"Unit";"Marine";"Barracks";159;1
"Unit";"Marine";"Barracks";160;1
"Unit";"Marine";"Barracks";161;1
"Unit";"Marine";"Barracks";161;1
"Unit";"Marine";"Barracks";168;1
"Unit";"Marine";"Barracks";168;1
"Unit";"Marine";"Barracks";174;1
"Unit";"Marine";"Barracks";174;1
"Unit";"Marine";"Barracks";174;1
"Unit";"Marine";"Barracks";174;1
"Unit";"Marine";"Barracks";174;1
"Unit";"Marine";"Barracks";174;1
"Unit";"Marine";"Barracks";174;1
"Unit";"Marine";"Barracks";174;1
"Unit";"SCV";"Command Center";176;1
"Unit";"Marine";"Barracks";174;1
"Unit";"SCV";"Command Center";176;1
"Unit";"SCV";"Command Center";176;1
"Unit";"Marine";"Barracks";174;1
"Unit";"Marine";"Barracks";175;1
"Unit";"SCV";"Command Center";184;1
"Unit";"Marine";"Barracks";176;1
"Unit";"Marine";"Barracks";177;1
"Unit";"Marine";"Barracks";178;1
"Unit";"Marine";"Barracks";179;1
"Unit";"Marine";"Barracks";180;1
"Unit";"Marine";"Barracks";181;1
"Unit";"Marine";"Barracks";182;1
"Unit";"Marine";"Barracks";183;1
"Unit";"Marine";"Barracks";185;1
"Unit";"Marine";"Barracks";188;1
"Upgrade";"TerranInfantryWeaponsLevel2";"EngineeringBay";153;0
"Building";"SupplyDepot";NA;190;0
"Building";"SupplyDepot";NA;190;0
"Building";"SupplyDepot";NA;190;0
"Building";"SensorTower";NA;201;0
"Building";"SupplyDepot";NA;201;0
"Building";"SupplyDepot";NA;201;0
"Unit";"Marine";"Barracks";201;1
"Unit";"Marine";"Barracks";201;1
"Unit";"Marine";"Barracks";201;1
"Unit";"Marine";"Barracks";201;1
"Unit";"Marine";"Barracks";201;1
"Unit";"Marine";"Barracks";201;1
"Unit";"Marine";"Barracks";201;1
"Unit";"Marine";"Barracks";201;1
"Unit";"Marine";"Barracks";201;1
"Unit";"Marine";"Barracks";201;1
"Unit";"Marine";"Barracks";201;1
