"Type";"UnitName";"OnBuilding";"TotalSupply";"Supply"
"Unit";"SCV";"Command Center";12;1
"Unit";"SCV";"Command Center";12;1
"Unit";"SCV";"Command Center";13;1
"Building";"SupplyDepot";NA;13;0
"Unit";"SCV";"Command Center";15;1
"Building";"Refinery";NA;14;0
"Unit";"SCV";"Command Center";15;1
"Unit";"SCV";"Command Center";16;1
"Unit";"SCV";"Command Center";17;1
"Building";"Barracks";NA;15;0
"Unit";"Reaper";"Barracks";19;1
"Unit";"SCV";"Command Center";19;1
"Unit";"SCV";"Command Center";20;1
"Building";"Refinery";NA;20;0
"Unit";"SCV";"Command Center";21;1
"Building";"Factory";NA;19;0
"Building";"SupplyDepot";NA;21;0
"Building";"BarracksReactor";NA;20;0
"Unit";"SCV";"Command Center";22;1
"Building";"CommandCenter";NA;19;0
"Unit";"SCV";"Command Center";23;1
"Unit";"Marine";"Barracks";23;1
"Unit";"Marine";"Barracks";24;1
"Unit";"SCV";"Command Center";24;1
"Unit";"Cyclone";"Factory";24;3
"Building";"Bunker";NA;24;0
"Unit";"Marine";"Barracks";25;1
"Unit";"Marine";"Barracks";26;1
"Unit";"SCV";"Command Center";31;1
"Unit";"SCV";"Command Center";34;1
"Unit";"SCV";"Command Center";34;1
"Unit";"Marine";"Barracks";34;1
"Unit";"Marine";"Barracks";34;1
"Unit";"SCV";"Command Center";35;1
"Building";"FactoryTechLab";NA;34;0
"Building";"Starport";NA;34;0
"Building";"SupplyDepot";NA;35;0
"Unit";"SCV";"Command Center";39;1
"Unit";"SCV";"Command Center";39;1
"Unit";"Marine";"Barracks";39;1
"Unit";"Marine";"Barracks";39;1
"Building";"EngineeringBay";NA;39;0
"Unit";"SCV";"Command Center";41;1
"Unit";"SCV";"Command Center";41;1
"Unit";"SCV";"Command Center";45;1
"Unit";"SCV";"Command Center";45;1
"Building";"SupplyDepot";NA;45;0
"Unit";"Marine";"Barracks";45;1
"Unit";"Marine";"Barracks";45;1
"Unit";"Liberator";"Starport";41;3
"Unit";"SCV";"Command Center";47;1
"Unit";"SCV";"Command Center";47;1
"Building";"Barracks";NA;41;0
"Building";"SupplyDepot";NA;47;0
"Unit";"SCV";"Command Center";54;1
"Unit";"SCV";"Command Center";54;1
"Building";"StarportTechLab";NA;52;0
"Unit";"Marine";"Barracks";52;1
"Unit";"Marine";"Barracks";52;1
"Building";"SupplyDepot";NA;54;0
"Unit";"SCV";"Command Center";54;1
"Unit";"SCV";"Command Center";55;1
"Building";"Barracks";NA;45;0
"Unit";"Marine";"Barracks";58;1
"Unit";"Marine";"Barracks";58;1
"Building";"SupplyDepot";NA;58;0
"Unit";"SCV";"Command Center";60;1
"Unit";"SCV";"Command Center";60;1
"Unit";"Marine";"Barracks";59;1
"Building";"StarportReactor";NA;58;0
"Unit";"Marine";"Barracks";62;1
"Unit";"Marine";"Barracks";62;1
"Unit";"SCV";"Command Center";65;1
"Unit";"Marine";"Barracks";65;1
"Unit";"SCV";"Command Center";65;1
"Building";"BarracksReactor";NA;60;0
"Upgrade";"TerranInfantryWeaponsLevel1";"EngineeringBay";49;0
"Building";"Refinery";NA;65;0
"Building";"Refinery";NA;65;0
"Unit";"SCV";"Command Center";70;1
"Unit";"SCV";"Command Center";70;1
"Building";"SupplyDepot";NA;70;0
"Unit";"Marine";"Barracks";70;1
"Unit";"SCV";"Command Center";70;1
"Unit";"SCV";"Command Center";71;1
"Unit";"Marine";"Barracks";70;1
"Unit";"Marine";"Barracks";72;1
"Unit";"Marine";"Barracks";72;1
"Unit";"Marine";"Barracks";72;1
"Building";"CommandCenter";NA;60;0
"Building";"Barracks";NA;68;0
"Building";"EngineeringBay";NA;72;0
"Building";"Barracks";NA;70;0
"Unit";"SCV";"Command Center";79;1
"Unit";"SCV";"Command Center";79;1
"Unit";"Marine";"Barracks";76;1
"Unit";"Marine";"Barracks";76;1
"Building";"Armory";NA;70;0
"Unit";"Marine";"Barracks";79;1
"Unit";"Marine";"Barracks";79;1
"Building";"SupplyDepot";NA;79;0
"Unit";"Medivac";"Starport";76;2
"Unit";"Medivac";"Starport";79;2
"Unit";"Marine";"Barracks";83;1
"Unit";"Marine";"Barracks";83;1
"Unit";"Marine";"Barracks";83;1
"Unit";"SCV";"Command Center";87;1
"Building";"BarracksReactor";NA;79;0
"Upgrade";"Stimpack";"TechLab";68;0
"Unit";"Marine";"Barracks";87;1
"Unit";"Marine";"Barracks";87;1
"Building";"BarracksReactor";NA;79;0
"Unit";"Marine";"Barracks";89;1
"Unit";"Marine";"Barracks";92;1
"Unit";"Marine";"Barracks";93;1
"Unit";"Marine";"Barracks";94;1
"Unit";"Medivac";"Starport";92;2
"Unit";"Marine";"Barracks";96;1
"Unit";"Marine";"Barracks";96;1
"Unit";"Marine";"Barracks";96;1
"Unit";"Marine";"Barracks";96;1
"Unit";"Marine";"Barracks";97;1
"Unit";"Marine";"Barracks";97;1
"Unit";"Marine";"Barracks";97;1
"Unit";"Marine";"Barracks";97;1
"Unit";"Medivac";"Starport";96;2
"Unit";"Marine";"Barracks";99;1
"Upgrade";"TerranInfantryArmorsLevel1";"EngineeringBay";83;0
"Building";"SupplyDepot";NA;112;0
"Building";"SupplyDepot";NA;112;0
"Building";"SupplyDepot";NA;112;0
"Unit";"Marine";"Barracks";112;1
"Unit";"Marine";"Barracks";112;1
"Unit";"Marine";"Barracks";112;1
"Unit";"SCV";"Command Center";112;1
"Unit";"Marine";"Barracks";112;1
"Unit";"Marine";"Barracks";112;1
"Unit";"Marine";"Barracks";112;1
"Unit";"Marine";"Barracks";112;1
"Unit";"Marine";"Barracks";112;1
"Unit";"Marine";"Barracks";112;1
"Unit";"Marine";"Barracks";112;1
"Unit";"Marine";"Barracks";118;1
"Unit";"Marine";"Barracks";118;1
"Unit";"Marine";"Barracks";118;1
"Unit";"Marine";"Barracks";118;1
"Unit";"Marine";"Barracks";118;1
"Unit";"Marine";"Barracks";118;1
"Unit";"Marine";"Barracks";122;1
"Unit";"Marine";"Barracks";122;1
"Unit";"Marine";"Barracks";122;1
"Unit";"Marine";"Barracks";125;1
"Unit";"Marine";"Barracks";127;1
"Unit";"Marine";"Barracks";127;1
"Unit";"Marine";"Barracks";127;1
"Unit";"Marine";"Barracks";127;1
"Unit";"Marine";"Barracks";127;1
"Unit";"Marine";"Barracks";129;1
"Unit";"Marine";"Barracks";130;1
"Unit";"Marine";"Barracks";131;1
"Unit";"Marine";"Barracks";132;1
"Unit";"Marine";"Barracks";133;1
"Unit";"Marine";"Barracks";134;1
"Unit";"Marine";"Barracks";134;1
"Unit";"Marine";"Barracks";136;1
"Unit";"Marine";"Barracks";136;1
"Unit";"Marine";"Barracks";138;1
"Unit";"Marine";"Barracks";139;1
"Unit";"SCV";"Command Center";141;1
"Unit";"SCV";"Command Center";141;1
"Unit";"SCV";"Command Center";141;1
"Unit";"Marine";"Barracks";140;1
"Unit";"Marine";"Barracks";141;1
"Unit";"Marine";"Barracks";142;1
"Unit";"Marine";"Barracks";143;1
"Unit";"Marine";"Barracks";143;1
"Unit";"SCV";"Command Center";149;1
"Unit";"SCV";"Command Center";150;1
"Unit";"SCV";"Command Center";151;1
"Unit";"Marine";"Barracks";145;1
"Unit";"Marine";"Barracks";145;1
"Unit";"Marine";"Barracks";147;1
"Unit";"Marine";"Barracks";149;1
"Upgrade";"TerranInfantryWeaponsLevel2";"EngineeringBay";112;0
"Unit";"Marine";"Barracks";153;1
"Unit";"SCV";"Command Center";165;1
"Unit";"SCV";"Command Center";165;1
"Unit";"SCV";"Command Center";165;1
"Unit";"Marine";"Barracks";165;1
"Unit";"Marine";"Barracks";165;1
"Unit";"Marine";"Barracks";165;1
"Unit";"Marine";"Barracks";165;1
"Unit";"Marine";"Barracks";165;1
"Unit";"Marine";"Barracks";165;1
"Unit";"Marine";"Barracks";165;1
"Unit";"Marine";"Barracks";165;1
"Unit";"Marine";"Barracks";165;1
"Unit";"SCV";"Command Center";165;1
"Unit";"SCV";"Command Center";166;1
"Unit";"SCV";"Command Center";167;1
"Unit";"Marine";"Barracks";168;1
"Unit";"Marine";"Barracks";169;1
"Unit";"Marine";"Barracks";169;1
"Unit";"Marine";"Barracks";171;1
"Unit";"Marine";"Barracks";171;1
"Unit";"Marine";"Barracks";173;1
"Unit";"Marine";"Barracks";173;1
"Unit";"Marine";"Barracks";175;1
"Unit";"SCV";"Command Center";177;1
"Unit";"Marine";"Barracks";177;1
"Unit";"Marine";"Barracks";180;1
"Unit";"Medivac";"Starport";177;2
"Unit";"Medivac";"Starport";177;2
"Unit";"Marine";"Barracks";181;1
"Unit";"Marine";"Barracks";181;1
"Unit";"Marine";"Barracks";183;1
"Unit";"Marine";"Barracks";183;1
"Unit";"Marine";"Barracks";185;1
"Unit";"Marine";"Barracks";200;1
"Unit";"Marine";"Barracks";200;1
"Unit";"Marine";"Barracks";200;1
"Unit";"Marine";"Barracks";200;1
"Unit";"Marine";"Barracks";200;1
"Unit";"SCV";"Command Center";200;1
"Unit";"SCV";"Command Center";200;1
"Unit";"Medivac";"Starport";190;2
"Unit";"Medivac";"Starport";193;2
"Unit";"Marine";"Barracks";200;1
"Unit";"Marine";"Barracks";200;1
"Unit";"Marine";"Barracks";200;1
"Unit";"Marine";"Barracks";200;1
"Unit";"SCV";"Command Center";205;1
"Unit";"Marine";"Barracks";200;1
"Unit";"Marine";"Barracks";201;1
"Unit";"Marine";"Barracks";202;1
"Unit";"Marine";"Barracks";205;1
"Unit";"Marine";"Barracks";205;1
"Unit";"Marine";"Barracks";216;1
"Unit";"Marine";"Barracks";216;1
"Unit";"Marine";"Barracks";216;1
"Unit";"Marine";"Barracks";216;1
"Unit";"Marine";"Barracks";217;1
"Unit";"Marine";"Barracks";218;1
"Unit";"Marine";"Barracks";219;1
"Unit";"Marine";"Barracks";220;1
"Unit";"SCV";"Command Center";224;1
"Unit";"SCV";"Command Center";224;1
"Unit";"SCV";"Command Center";224;1
"Unit";"Marine";"Barracks";221;1
"Unit";"Marine";"Barracks";222;1
"Unit";"Marine";"Barracks";223;1
"Unit";"SCV";"Command Center";229;1
"Unit";"Marine";"Barracks";229;1
"Unit";"Marine";"Barracks";229;1
"Unit";"Marine";"Barracks";229;1
"Unit";"Marine";"Barracks";229;1
"Unit";"Marine";"Barracks";229;1
"Unit";"SCV";"Command Center";235;1
"Unit";"Marine";"Barracks";235;1
"Unit";"SCV";"Command Center";235;1
"Unit";"Marine";"Barracks";235;1
"Unit";"Marine";"Barracks";241;1
"Unit";"Marine";"Barracks";242;1
"Unit";"Marine";"Barracks";242;1
"Unit";"Marine";"Barracks";242;1
"Unit";"Marine";"Barracks";242;1
"Unit";"Marine";"Barracks";242;1
"Building";"Factory";NA;229;0
"Building";"Barracks";NA;229;0
"Building";"Barracks";NA;229;0
"Unit";"Marine";"Barracks";245;1
"Unit";"Marine";"Barracks";245;1
"Upgrade";"TerranInfantryArmorsLevel2";"EngineeringBay";200;0
"Unit";"Medivac";"Starport";245;2
"Unit";"Medivac";"Starport";245;2
"Unit";"SCV";"Command Center";253;1
"Unit";"SCV";"Command Center";253;1
"Unit";"SCV";"Command Center";253;1
"Unit";"Marine";"Barracks";253;1
"Unit";"Marine";"Barracks";253;1
"Unit";"Marine";"Barracks";253;1
"Unit";"Marine";"Barracks";253;1
"Unit";"Marine";"Barracks";253;1
"Unit";"Marine";"Barracks";253;1
"Unit";"Marine";"Barracks";253;1
"Unit";"Marine";"Barracks";253;1
"Unit";"Marine";"Barracks";253;1
"Unit";"SCV";"Command Center";257;1
"Unit";"SCV";"Command Center";258;1
"Unit";"SCV";"Command Center";260;1
"Unit";"SCV";"Command Center";269;1
"Unit";"Marine";"Barracks";260;1
"Unit";"Marine";"Barracks";261;1
"Unit";"Marine";"Barracks";262;1
"Unit";"Marine";"Barracks";262;1
"Unit";"Marine";"Barracks";264;1
"Unit";"Marine";"Barracks";269;1
"Unit";"Marine";"Barracks";269;1
"Unit";"Marine";"Barracks";269;1
"Building";"FactoryTechLab";NA;271;0
"Upgrade";"TerranVehicleWeaponsLevel1";"Armory";238;0
"Upgrade";"TerranInfantryWeaponsLevel3";"EngineeringBay";231;0
"Building";"BarracksReactor";NA;270;0
"Building";"BarracksReactor";NA;271;0
"Unit";"Marine";"Barracks";281;1
"Unit";"Marine";"Barracks";281;1
"Unit";"Marine";"Barracks";281;1
"Unit";"Marine";"Barracks";281;1
"Unit";"Marine";"Barracks";281;1
"Unit";"Marine";"Barracks";281;1
"Unit";"Marine";"Barracks";281;1
"Unit";"Marine";"Barracks";281;1
"Unit";"Marine";"Barracks";281;1
"Unit";"SCV";"Command Center";281;1
"Unit";"SCV";"Command Center";291;1
"Unit";"Marine";"Barracks";291;1
"Unit";"Marine";"Barracks";291;1
"Unit";"Marine";"Barracks";291;1
"Unit";"Marine";"Barracks";291;1
"Unit";"Marine";"Barracks";291;1
"Unit";"Marine";"Barracks";291;1
"Unit";"Marine";"Barracks";291;1
"Unit";"Marine";"Barracks";291;1
"Unit";"Marine";"Barracks";291;1
"Unit";"Marine";"Barracks";292;1
"Unit";"Marine";"Barracks";292;1
"Unit";"Marine";"Barracks";292;1
"Unit";"Marine";"Barracks";298;1
"Unit";"Marine";"Barracks";298;1
"Unit";"Medivac";"Starport";292;2
"Unit";"Medivac";"Starport";298;2
"Unit";"SCV";"Command Center";310;1
"Unit";"Marine";"Barracks";311;1
"Unit";"Marine";"Barracks";311;1
"Unit";"Marine";"Barracks";311;1
"Unit";"Marine";"Barracks";311;1
"Unit";"Marine";"Barracks";311;1
"Unit";"Marine";"Barracks";311;1
"Unit";"Marine";"Barracks";311;1
"Unit";"SCV";"Command Center";311;1
"Unit";"Marine";"Barracks";319;1
"Unit";"Marine";"Barracks";319;1
"Unit";"Marine";"Barracks";319;1
"Unit";"Marine";"Barracks";319;1
"Unit";"Marine";"Barracks";319;1
"Unit";"Marine";"Barracks";319;1
"Unit";"Marine";"Barracks";324;1
"Unit";"Marine";"Barracks";324;1
"Unit";"SCV";"Command Center";325;1
