"type";"unit_name";"on_building";"total_supply_lag";"supply"
"Building";"Barracks";NA;15;0
"Building";"Refinery";NA;15;0
"Building";"Barracks";NA;15;0
"Building";"Refinery";NA;17;0
"Unit";"Reaper";"Barracks";17;1
"Unit";"Reaper";"Barracks";18;1
"Unit";"Reaper";"Barracks";20;1
"Building";"Factory";NA;21;0
"Unit";"Reaper";"Barracks";22;1
