"type";"unit_name";"on_building";"total_supply";"supply"
"Building";"Refinery";NA;15;0
"Building";"Barracks";NA;15;0
"Building";"Refinery";NA;17;0
"Building";"Barracks";NA;16;0
"Unit";"Reaper";"Barracks";19;1
"Unit";"Reaper";"Barracks";19;1
"Unit";"Reaper";"Barracks";19;1
"Building";"Factory";NA;20;0
"Unit";"Reaper";"Barracks";21;1
"Unit";"Reaper";"Barracks";23;1
"Unit";"Reaper";"Barracks";27;1
"Unit";"Cyclone";"Factory";31;3
"Building";"BarracksTechLab";NA;33;0
