"Type";"UnitName";"OnBuilding";"TotalSupply";"Supply"
"Unit";"SCV";"Command Center";12;1
"Unit";"SCV";"Command Center";12;1
"Unit";"SCV";"Command Center";13;1
"Building";"SupplyDepot";NA;13;0
"Building";"Refinery";NA;14;0
"Unit";"SCV";"Command Center";15;1
"Unit";"SCV";"Command Center";15;1
"Unit";"SCV";"Command Center";16;1
"Building";"Refinery";NA;17;0
"Unit";"SCV";"Command Center";17;1
"Building";"Barracks";NA;15;0
"Unit";"Reaper";"Barracks";19;1
"Unit";"SCV";"Command Center";19;1
"Building";"SupplyDepot";NA;19;0
"Unit";"SCV";"Command Center";20;1
"Building";"Factory";NA;19;0
"Unit";"SCV";"Command Center";21;1
"Unit";"Reaper";"Barracks";19;1
"Unit";"SCV";"Command Center";22;1
"Unit";"SCV";"Command Center";24;1
"Building";"BarracksTechLab";NA;24;0
"Building";"Starport";NA;22;0
"Unit";"Cyclone";"Factory";24;3
"Unit";"SCV";"Command Center";25;1
"Building";"SupplyDepot";NA;25;0
"Unit";"SCV";"Command Center";30;1
"Unit";"Marine";"Barracks";30;1
"Unit";"SCV";"Command Center";30;1
"Building";"SupplyDepot";NA;30;0
"Unit";"SCV";"Command Center";32;1
"Unit";"Liberator";"Starport";30;3
"Unit";"SCV";"Command Center";33;1
"Unit";"Marine";"Barracks";33;1
"Building";"SupplyDepot";NA;33;0
"Unit";"SCV";"Command Center";37;1
"Unit";"SCV";"Command Center";39;1
"Building";"EngineeringBay";NA;39;0
"Unit";"SCV";"Command Center";40;1
"Building";"CommandCenter";NA;31;0
"Building";"SupplyDepot";NA;40;0
"Unit";"Marine";"Barracks";41;1
"Unit";"SCV";"Command Center";41;1
"Unit";"Raven";"Starport";40;2
"Building";"MissileTurret";NA;42;0
"Building";"SupplyDepot";NA;42;0
"Unit";"Cyclone";"Factory";42;3
"Unit";"SCV";"Command Center";44;1
"Unit";"SCV";"Command Center";49;1
"Building";"FactoryTechLab";NA;50;0
"Unit";"SCV";"Command Center";50;1
"Unit";"SCV";"Command Center";51;1
"Unit";"Marine";"Barracks";52;1
"Building";"Barracks";NA;46;0
"Unit";"SCV";"Command Center";52;1
"Building";"SupplyDepot";NA;52;0
"Building";"SupplyDepot";NA;52;0
"Unit";"SCV";"Command Center";54;1
"Unit";"SCV";"Command Center";55;1
"Unit";"Marine";"Barracks";54;1
"Unit";"SCV";"Command Center";55;1
"Unit";"SCV";"Command Center";56;1
"Unit";"Marine";"Barracks";57;1
"Building";"BarracksReactor";NA;54;0
"Unit";"SCV";"Command Center";58;1
"Building";"Bunker";NA;55;0
"Unit";"SCV";"Command Center";60;1
"Unit";"SCV";"Command Center";61;1
"Unit";"Marine";"Barracks";60;1
"Unit";"SCV";"Command Center";62;1
"Unit";"Marine";"Barracks";62;1
"Unit";"Marine";"Barracks";62;1
"Unit";"SCV";"Command Center";63;1
"Building";"StarportReactor";NA;59;0
"Building";"Barracks";NA;58;0
"Unit";"SCV";"Command Center";65;1
"Building";"Refinery";NA;63;0
"Unit";"SCV";"Command Center";68;1
"Building";"Refinery";NA;65;0
"Unit";"Marine";"Barracks";68;1
"Unit";"Marine";"Barracks";68;1
"Unit";"SCV";"Command Center";69;1
"Unit";"Marine";"Barracks";68;1
"Unit";"SCV";"Command Center";70;1
"Unit";"SCV";"Command Center";73;1
"Unit";"Marine";"Barracks";71;1
"Unit";"Marine";"Barracks";72;1
"Unit";"Marine";"Barracks";74;1
"Building";"SupplyDepot";NA;69;0
"Unit";"SCV";"Command Center";75;1
"Upgrade";"Stimpack";"TechLab";56;0
"Building";"EngineeringBay";NA;68;0
"Building";"BarracksReactor";NA;70;0
"Unit";"SCV";"Command Center";76;1
"Unit";"Medivac";"Starport";71;2
"Unit";"Medivac";"Starport";75;2
"Unit";"SCV";"Command Center";80;1
"Unit";"SCV";"Command Center";81;1
"Unit";"Marine";"Barracks";80;1
"Unit";"Marine";"Barracks";81;1
"Unit";"Marine";"Barracks";81;1
"Building";"CommandCenter";NA;63;0
"Unit";"SCV";"Command Center";86;1
"Unit";"SCV";"Command Center";87;1
"Unit";"Marine";"Barracks";87;1
"Unit";"Marine";"Barracks";87;1
"Unit";"SCV";"Command Center";91;1
"Unit";"SCV";"Command Center";92;1
"Unit";"Marine";"Barracks";92;1
"Unit";"Marine";"Barracks";92;1
"Unit";"Marine";"Barracks";92;1
"Unit";"SCV";"Command Center";95;1
"Unit";"Marine";"Barracks";95;1
"Unit";"Marine";"Barracks";95;1
"Unit";"SCV";"Command Center";96;1
"Unit";"SCV";"Command Center";100;1
"Unit";"SCV";"Command Center";103;1
"Building";"SupplyDepot";NA;97;0
"Building";"SupplyDepot";NA;97;0
"Unit";"SCV";"Command Center";104;1
"Unit";"SCV";"Command Center";105;1
"Building";"Barracks";NA;95;0
"Building";"Barracks";NA;95;0
"Unit";"Marine";"Barracks";105;1
"Unit";"Marine";"Barracks";105;1
"Unit";"Marine";"Barracks";105;1
"Unit";"Marine";"Barracks";105;1
"Unit";"Marine";"Barracks";105;1
"Unit";"SCV";"Command Center";106;1
"Building";"SupplyDepot";NA;106;0
"Building";"SupplyDepot";NA;106;0
"Unit";"SCV";"Command Center";108;1
"Unit";"Medivac";"Starport";106;2
"Unit";"Marine";"Barracks";108;1
"Unit";"Marine";"Barracks";109;1
"Unit";"Marine";"Barracks";110;1
"Unit";"Marine";"Barracks";111;1
"Unit";"Marine";"Barracks";112;1
"Unit";"Medivac";"Starport";107;2
"Unit";"SCV";"Command Center";117;1
"Building";"Refinery";NA;114;0
"Building";"Refinery";NA;114;0
"Unit";"SCV";"Command Center";122;1
"Building";"Armory";NA;106;0
"Building";"SupplyDepot";NA;115;0
"Building";"SupplyDepot";NA;117;0
"Unit";"SCV";"Command Center";124;1
"Unit";"SCV";"Command Center";125;1
"Unit";"Marine";"Barracks";126;1
"Unit";"Marine";"Barracks";126;1
"Unit";"SCV";"Command Center";126;1
"Unit";"Marine";"Barracks";126;1
"Building";"BarracksTechLab";NA;126;0
"Unit";"Marine";"Barracks";126;1
"Unit";"Marine";"Barracks";126;1
"Unit";"Marauder";"Barracks";126;2
"Unit";"SCV";"Command Center";127;1
"Unit";"SCV";"Command Center";130;1
"Unit";"Marine";"Barracks";134;1
"Unit";"Marine";"Barracks";134;1
"Unit";"Marine";"Barracks";134;1
"Unit";"Marine";"Barracks";134;1
"Unit";"Marine";"Barracks";137;1
"Unit";"Marine";"Barracks";138;1
"Unit";"Medivac";"Starport";137;2
"Unit";"Marine";"Barracks";138;1
"Unit";"Marine";"Barracks";139;1
"Building";"BarracksReactor";NA;137;0
"Upgrade";"TerranInfantryWeaponsLevel1";"EngineeringBay";117;0
"Upgrade";"TerranInfantryArmorsLevel1";"EngineeringBay";117;0
"Unit";"Marine";"Barracks";144;1
"Unit";"Marine";"Barracks";144;1
"Unit";"Marine";"Barracks";144;1
"Unit";"Marine";"Barracks";144;1
"Unit";"Marine";"Barracks";146;1
"Unit";"Marine";"Barracks";147;1
"Unit";"Medivac";"Starport";144;2
"Building";"Barracks";NA;138;0
"Building";"Barracks";NA;138;0
"Building";"Barracks";NA;138;0
"Unit";"Medivac";"Starport";144;2
"Unit";"Marine";"Barracks";148;1
"Unit";"Marine";"Barracks";149;1
"Unit";"Marine";"Barracks";150;1
"Unit";"Marine";"Barracks";151;1
"Building";"SupplyDepot";NA;148;0
"Building";"SupplyDepot";NA;148;0
"Building";"SupplyDepot";NA;148;0
"Unit";"Marine";"Barracks";152;1
"Unit";"Marine";"Barracks";153;1
"Unit";"Marine";"Barracks";156;1
"Unit";"Marine";"Barracks";156;1
"Unit";"Marine";"Barracks";158;1
"Unit";"Marine";"Barracks";159;1
"Unit";"Marine";"Barracks";160;1
"Unit";"Medivac";"Starport";154;2
"Building";"BarracksTechLab";NA;164;0
"Building";"BarracksTechLab";NA;164;0
"Unit";"Marine";"Barracks";164;1
"Unit";"Marine";"Barracks";164;1
"Unit";"Medivac";"Starport";156;2
"Building";"CommandCenter";NA;142;0
"Unit";"Marauder";"Barracks";164;2
"Unit";"Marauder";"Barracks";168;2
"Building";"BarracksReactor";NA;164;0
"Unit";"Medivac";"Starport";169;2
"Unit";"Marine";"Barracks";177;1
"Unit";"Marine";"Barracks";177;1
"Unit";"Marine";"Barracks";177;1
"Unit";"Marine";"Barracks";177;1
"Unit";"Marine";"Barracks";177;1
"Unit";"Marine";"Barracks";177;1
"Unit";"Marine";"Barracks";177;1
"Unit";"Marauder";"Barracks";177;2
"Unit";"Marauder";"Barracks";177;2
"Unit";"Medivac";"Starport";173;2
"Unit";"Marauder";"Barracks";177;2
"Unit";"Marine";"Barracks";179;1
"Unit";"Marine";"Barracks";179;1
"Unit";"Marine";"Barracks";181;1
"Unit";"Marine";"Barracks";182;1
"Unit";"Marine";"Barracks";182;1
"Unit";"Marauder";"Barracks";186;2
"Unit";"Marauder";"Barracks";188;2
"Unit";"Marauder";"Barracks";190;2
"Unit";"Marine";"Barracks";196;1
"Unit";"Medivac";"Starport";179;2
"Unit";"Marauder";"Barracks";194;2
