"Type";"UnitName";"OnBuilding";"TotalSupply";"Supply"
"Unit";"SCV";"Command Center";12;1
"Unit";"SCV";"Command Center";12;1
"Unit";"SCV";"Command Center";13;1
"Building";"SupplyDepot";NA;13;0
"Unit";"SCV";"Command Center";15;1
"Building";"Refinery";NA;14;0
"Unit";"SCV";"Command Center";16;1
"Unit";"SCV";"Command Center";16;1
"Unit";"SCV";"Command Center";17;1
"Building";"Barracks";NA;15;0
"Unit";"Reaper";"Barracks";19;1
"Unit";"SCV";"Command Center";19;1
"Unit";"SCV";"Command Center";20;1
"Building";"Refinery";NA;19;0
"Building";"SupplyDepot";NA;21;0
"Building";"Factory";NA;19;0
"Unit";"SCV";"Command Center";22;1
"Unit";"Reaper";"Barracks";21;1
"Unit";"SCV";"Command Center";23;1
"Unit";"Hellion";"Factory";22;2
"Unit";"Marine";"Barracks";24;1
"Unit";"SCV";"Command Center";24;1
"Building";"Starport";NA;22;0
"Building";"CommandCenter";NA;19;0
"Unit";"Cyclone";"Factory";29;3
"Unit";"SCV";"Command Center";29;1
"Unit";"Marine";"Barracks";29;1
"Unit";"SCV";"Command Center";33;1
"Unit";"SCV";"Command Center";34;1
"Building";"SupplyDepot";NA;33;0
"Unit";"Liberator";"Starport";29;3
"Unit";"SCV";"Command Center";35;1
"Unit";"Cyclone";"Factory";35;3
"Unit";"SCV";"Command Center";35;1
"Unit";"Marine";"Barracks";36;1
"Building";"SupplyDepot";NA;36;0
"Unit";"Marine";"Barracks";45;1
"Unit";"Marine";"Barracks";45;1
"Unit";"SCV";"Command Center";46;1
"Unit";"Cyclone";"Factory";46;3
"Unit";"SCV";"Command Center";51;1
"Unit";"SCV";"Command Center";51;1
"Unit";"SCV";"Command Center";51;1
"Unit";"Liberator";"Starport";46;3
"Unit";"SCV";"Command Center";53;1
"Unit";"SCV";"Command Center";53;1
"Unit";"Cyclone";"Factory";54;3
"Building";"SupplyDepot";NA;57;0
"Building";"SupplyDepot";NA;57;0
"Unit";"Marine";"Barracks";57;1
"Unit";"SCV";"Command Center";59;1
"Unit";"SCV";"Command Center";62;1
"Building";"EngineeringBay";NA;59;0
"Building";"FactoryTechLab";NA;62;0
"Unit";"SCV";"Command Center";63;1
"Building";"BarracksTechLab";NA;63;0
"Unit";"SCV";"Command Center";64;1
"Unit";"SCV";"Command Center";65;1
"Building";"StarportReactor";NA;59;0
"Building";"Barracks";NA;59;0
"Unit";"SCV";"Command Center";66;1
"Building";"Barracks";NA;59;0
"Building";"Barracks";NA;59;0
"Building";"Barracks";NA;59;0
"Unit";"Marine";"Barracks";66;1
"Unit";"SCV";"Command Center";67;1
"Building";"Refinery";NA;67;0
"Unit";"SCV";"Command Center";68;1
"Building";"Refinery";NA;67;0
"Unit";"SCV";"Command Center";70;1
"Unit";"Marine";"Barracks";69;1
"Unit";"Marine";"Barracks";69;1
"Unit";"Marine";"Barracks";70;1
"Unit";"Marine";"Barracks";70;1
"Unit";"SCV";"Command Center";72;1
"Building";"SupplyDepot";NA;72;0
"Unit";"SCV";"Command Center";77;1
"Building";"SupplyDepot";NA;72;0
"Building";"BarracksReactor";NA;69;0
"Unit";"Marine";"Barracks";77;1
"Unit";"Marine";"Barracks";77;1
"Unit";"SCV";"Command Center";78;1
"Unit";"SCV";"Command Center";78;1
"Unit";"Marine";"Barracks";79;1
"Building";"SupplyDepot";NA;79;0
"Unit";"SCV";"Command Center";81;1
"Unit";"Marine";"Barracks";79;1
"Building";"SupplyDepot";NA;79;0
"Unit";"Marine";"Barracks";79;1
"Unit";"SCV";"Command Center";83;1
"Building";"BarracksReactor";NA;77;0
"Unit";"Medivac";"Starport";79;2
"Building";"SupplyDepot";NA;85;0
"Building";"BarracksReactor";NA;81;0
"Building";"SupplyDepot";NA;87;0
"Building";"BarracksReactor";NA;81;0
"Upgrade";"TerranInfantryWeaponsLevel1";"EngineeringBay";72;0
"Unit";"Marine";"Barracks";90;1
"Unit";"Marine";"Barracks";90;1
"Unit";"Marine";"Barracks";90;1
"Unit";"Marine";"Barracks";90;1
"Unit";"Marine";"Barracks";90;1
"Unit";"SCV";"Command Center";90;1
"Unit";"Marine";"Barracks";90;1
"Unit";"Marine";"Barracks";90;1
"Unit";"Marine";"Barracks";90;1
"Unit";"Marine";"Barracks";90;1
"Upgrade";"Stimpack";"TechLab";78;0
"Unit";"SCV";"Command Center";95;1
"Unit";"SCV";"Command Center";95;1
"Unit";"Marine";"Barracks";95;1
"Unit";"Marine";"Barracks";95;1
"Unit";"Marine";"Barracks";95;1
"Unit";"Marine";"Barracks";95;1
"Unit";"Marine";"Barracks";95;1
"Building";"EngineeringBay";NA;95;0
"Unit";"Marine";"Barracks";100;1
"Unit";"Marine";"Barracks";100;1
"Unit";"SCV";"Command Center";107;1
"Unit";"Marine";"Barracks";100;1
"Unit";"Marine";"Barracks";100;1
"Unit";"Medivac";"Starport";95;2
"Unit";"Medivac";"Starport";95;2
"Unit";"SCV";"Command Center";107;1
"Unit";"Marine";"Barracks";107;1
"Unit";"Marine";"Barracks";107;1
"Unit";"Marine";"Barracks";107;1
"Unit";"Marine";"Barracks";107;1
"Building";"Armory";NA;95;0
"Unit";"Marine";"Barracks";112;1
"Unit";"Marine";"Barracks";116;1
"Unit";"Marine";"Barracks";116;1
"Unit";"Marine";"Barracks";118;1
"Unit";"Marine";"Barracks";121;1
"Unit";"Marine";"Barracks";121;1
"Unit";"Marine";"Barracks";121;1
"Building";"CommandCenter";NA;95;0
"Building";"SupplyDepot";NA;121;0
"Unit";"Medivac";"Starport";118;2
"Unit";"Medivac";"Starport";118;2
"Unit";"SCV";"Command Center";132;1
"Unit";"Marine";"Barracks";132;1
"Unit";"Marine";"Barracks";132;1
"Unit";"Marine";"Barracks";132;1
"Unit";"Marine";"Barracks";132;1
"Unit";"Marine";"Barracks";132;1
"Unit";"Marine";"Barracks";132;1
"Unit";"Marine";"Barracks";132;1
"Unit";"Marine";"Barracks";132;1
"Unit";"Marine";"Barracks";132;1
"Unit";"SCV";"Command Center";133;1
"Unit";"SCV";"Command Center";133;1
"Unit";"Medivac";"Starport";132;2
"Upgrade";"TerranInfantryArmorsLevel1";"EngineeringBay";109;0
"Unit";"Marine";"Barracks";133;1
"Unit";"Marine";"Barracks";134;1
"Unit";"Marine";"Barracks";135;1
"Unit";"SCV";"Command Center";144;1
"Unit";"SCV";"Command Center";144;1
"Unit";"Marine";"Barracks";142;1
"Unit";"Marine";"Barracks";142;1
"Unit";"Marine";"Barracks";151;1
"Unit";"Marine";"Barracks";153;1
"Unit";"SCV";"Command Center";153;1
"Unit";"Marine";"Barracks";153;1
"Unit";"Marine";"Barracks";153;1
"Unit";"Marine";"Barracks";153;1
"Unit";"Marine";"Barracks";153;1
"Unit";"Marine";"Barracks";153;1
"Unit";"Marine";"Barracks";155;1
"Unit";"Marine";"Barracks";155;1
"Unit";"Marine";"Barracks";155;1
"Unit";"Marine";"Barracks";161;1
"Unit";"Marine";"Barracks";161;1
"Unit";"Marine";"Barracks";161;1
"Unit";"Marine";"Barracks";161;1
"Unit";"Marine";"Barracks";161;1
"Unit";"Marine";"Barracks";161;1
"Unit";"Marine";"Barracks";161;1
"Unit";"Marine";"Barracks";162;1
"Unit";"SCV";"Command Center";164;1
"Unit";"SCV";"Command Center";164;1
"Unit";"Marine";"Barracks";164;1
"Unit";"Marine";"Barracks";164;1
"Unit";"SCV";"Command Center";172;1
"Building";"SupplyDepot";NA;177;0
"Building";"SupplyDepot";NA;177;0
"Building";"SupplyDepot";NA;177;0
