"Type";"UnitName";"OnBuilding";"TotalSupply";"Supply"
"Unit";"SCV";"Command Center";12;1
"Unit";"SCV";"Command Center";12;1
"Unit";"SCV";"Command Center";13;1
"Building";"SupplyDepot";NA;13;0
"Unit";"SCV";"Command Center";15;1
"Unit";"SCV";"Command Center";15;1
"Building";"Refinery";NA;15;0
"Unit";"SCV";"Command Center";16;1
"Building";"Barracks";NA;15;0
"Unit";"SCV";"Command Center";17;1
"Unit";"Reaper";"Barracks";19;1
"Unit";"SCV";"Command Center";19;1
"Building";"Refinery";NA;19;0
"Unit";"SCV";"Command Center";20;1
"Building";"SupplyDepot";NA;19;0
"Unit";"SCV";"Command Center";21;1
"Unit";"SCV";"Command Center";22;1
"Building";"BarracksReactor";NA;22;0
"Unit";"SCV";"Command Center";24;1
"Building";"CommandCenter";NA;19;0
"Unit";"SCV";"Command Center";24;1
"Building";"Factory";NA;21;0
"Unit";"Marine";"Barracks";25;1
"Unit";"Marine";"Barracks";25;1
"Unit";"SCV";"Command Center";26;1
"Unit";"Marine";"Barracks";28;1
"Unit";"Marine";"Barracks";28;1
"Unit";"SCV";"Command Center";29;1
"Unit";"SCV";"Command Center";29;1
"Unit";"Cyclone";"Factory";29;3
"Unit";"Marine";"Barracks";29;1
"Unit";"Marine";"Barracks";30;1
"Unit";"SCV";"Command Center";36;1
"Unit";"SCV";"Command Center";36;1
"Unit";"SCV";"Command Center";38;1
"Unit";"Cyclone";"Factory";37;3
"Unit";"SCV";"Command Center";44;1
"Unit";"SCV";"Command Center";44;1
"Unit";"SCV";"Command Center";44;1
"Unit";"SCV";"Command Center";45;1
"Building";"SupplyDepot";NA;44;0
"Building";"Refinery";NA;46;0
"Building";"Factory";NA;40;0
"Unit";"Cyclone";"Factory";46;3
"Unit";"Cyclone";"Factory";46;3
"Unit";"SCV";"Command Center";46;1
"Unit";"SCV";"Command Center";47;1
"Building";"BarracksReactor";NA;44;0
"Unit";"SCV";"Command Center";56;1
"Unit";"SCV";"Command Center";56;1
"Building";"CommandCenter";NA;38;0
"Building";"Refinery";NA;48;0
"Building";"SupplyDepot";NA;48;0
"Unit";"SCV";"Command Center";56;1
"Unit";"SCV";"Command Center";57;1
"Building";"Armory";NA;48;0
"Unit";"Cyclone";"Factory";58;3
"Unit";"Cyclone";"Factory";60;3
"Unit";"SCV";"Command Center";60;1
"Unit";"SCV";"Command Center";60;1
"Unit";"Cyclone";"Factory";60;3
"Unit";"Cyclone";"Factory";60;3
"Unit";"SCV";"Command Center";66;1
"Unit";"SCV";"Command Center";67;1
"Unit";"SCV";"Command Center";76;1
"Unit";"SCV";"Command Center";76;1
"Unit";"SCV";"Command Center";76;1
"Building";"SupplyDepot";NA;74;0
"Building";"SupplyDepot";NA;76;0
"Unit";"Cyclone";"Factory";76;3
"Unit";"Cyclone";"Factory";76;3
"Unit";"SCV";"Command Center";79;1
"Unit";"SCV";"Command Center";79;1
"Unit";"SCV";"Command Center";85;1
"Unit";"Cyclone";"Factory";79;3
"Building";"SupplyDepot";NA;85;0
"Unit";"Cyclone";"Factory";85;3
"Building";"Factory";NA;79;0
"Building";"FactoryTechLab";NA;94;0
"Building";"EngineeringBay";NA;94;0
"Unit";"SCV";"Command Center";94;1
"Unit";"SCV";"Command Center";94;1
"Unit";"SCV";"Command Center";94;1
"Unit";"Cyclone";"Factory";94;3
"Unit";"Cyclone";"Factory";94;3
"Unit";"Cyclone";"Factory";94;3
"Unit";"Cyclone";"Factory";94;3
"Unit";"SCV";"Command Center";94;1
"Unit";"SCV";"Command Center";95;1
"Unit";"SCV";"Command Center";109;1
"Building";"Factory";NA;94;0
"Unit";"Hellion";"Factory";106;2
"Building";"Refinery";NA;111;0
"Building";"Refinery";NA;111;0
"Building";"MissileTurret";NA;111;0
"Upgrade";"TerranVehicleWeaponsLevel1";"Armory";91;0
"Building";"MissileTurret";NA;112;0
"Building";"MissileTurret";NA;112;0
"Building";"CommandCenter";NA;94;0
"Building";"SupplyDepot";NA;114;0
"Building";"SupplyDepot";NA;114;0
"Building";"SupplyDepot";NA;114;0
"Unit";"SCV";"Command Center";114;1
"Building";"FactoryReactor";NA;114;0
"Unit";"Hellion";"Factory";114;2
"Unit";"Hellion";"Factory";114;2
"Unit";"Hellion";"Factory";114;2
"Unit";"Hellion";"Factory";114;2
"Unit";"Hellion";"Factory";114;2
"Building";"MissileTurret";NA;114;0
"Building";"MissileTurret";NA;114;0
"Unit";"Hellion";"Factory";125;2
"Unit";"Hellion";"Factory";125;2
"Unit";"Hellion";"Factory";125;2
"Unit";"Hellion";"Factory";125;2
"Unit";"Hellion";"Factory";125;2
"Unit";"Hellion";"Factory";125;2
"Unit";"Hellion";"Factory";125;2
"Unit";"SCV";"Command Center";125;1
"Unit";"SCV";"Command Center";125;1
"Unit";"SCV";"Command Center";125;1
"Building";"SupplyDepot";NA;125;0
"Building";"SupplyDepot";NA;125;0
"Unit";"SCV";"Command Center";142;1
"Unit";"SCV";"Command Center";142;1
"Unit";"SCV";"Command Center";142;1
"Unit";"Cyclone";"Factory";142;3
"Unit";"Cyclone";"Factory";142;3
"Unit";"Cyclone";"Factory";142;3
"Unit";"Thor";"Factory";142;6
"Building";"Factory";NA;142;0
"Building";"Factory";NA;142;0
"Unit";"SCV";"Command Center";145;1
"Unit";"Cyclone";"Factory";142;3
"Unit";"Cyclone";"Factory";142;3
"Building";"SupplyDepot";NA;142;0
"Unit";"Cyclone";"Factory";142;3
"Building";"SupplyDepot";NA;142;0
"Building";"SupplyDepot";NA;142;0
"Unit";"SCV";"Command Center";154;1
"Unit";"SCV";"Command Center";154;1
"Unit";"SCV";"Command Center";154;1
"Unit";"Cyclone";"Factory";154;3
"Unit";"Cyclone";"Factory";154;3
"Building";"FactoryTechLab";NA;170;0
"Unit";"SCV";"Command Center";173;1
"Unit";"SCV";"Command Center";173;1
"Unit";"SCV";"Command Center";173;1
"Unit";"SCV";"Command Center";173;1
"Unit";"Hellion";"Factory";170;2
"Unit";"Hellion";"Factory";170;2
"Unit";"Hellion";"Factory";170;2
"Unit";"Cyclone";"Factory";170;3
"Unit";"SCV";"Command Center";179;1
"Building";"FactoryReactor";NA;170;0
"Unit";"Hellion";"Factory";192;2
"Unit";"Hellion";"Factory";192;2
"Unit";"Hellion";"Factory";192;2
"Unit";"Hellion";"Factory";192;2
"Building";"Refinery";NA;192;0
"Unit";"Cyclone";"Factory";193;3
"Unit";"Cyclone";"Factory";193;3
"Building";"Refinery";NA;193;0
"Unit";"Cyclone";"Factory";193;3
"Unit";"Cyclone";"Factory";193;3
"Unit";"Hellion";"Factory";193;2
"Upgrade";"TerranVehicleWeaponsLevel2";"Armory";142;0
"Unit";"SCV";"Command Center";213;1
"Unit";"Cyclone";"Factory";201;3
"Unit";"SCV";"Command Center";213;1
"Unit";"SCV";"Command Center";213;1
"Unit";"Cyclone";"Factory";201;3
"Unit";"Cyclone";"Factory";201;3
"Unit";"Cyclone";"Factory";210;3
"Unit";"Cyclone";"Factory";210;3
"Unit";"Cyclone";"Factory";221;3
"Unit";"Cyclone";"Factory";227;3
"Unit";"Hellion";"Factory";227;2
"Unit";"SCV";"Command Center";233;1
"Unit";"SCV";"Command Center";233;1
"Unit";"SCV";"Command Center";233;1
"Unit";"Cyclone";"Factory";233;3
"Unit";"Cyclone";"Factory";233;3
"Unit";"Cyclone";"Factory";236;3
"Building";"SupplyDepot";NA;241;0
"Unit";"Hellion";"Factory";253;2
"Unit";"Hellion";"Factory";253;2
"Unit";"Cyclone";"Factory";253;3
"Unit";"Cyclone";"Factory";253;3
"Unit";"Cyclone";"Factory";253;3
"Unit";"Cyclone";"Factory";253;3
"Unit";"Cyclone";"Factory";253;3
"Unit";"Hellion";"Factory";253;2
"Unit";"Cyclone";"Factory";257;3
"Unit";"Cyclone";"Factory";257;3
"Unit";"Hellion";"Factory";257;2
"Unit";"Cyclone";"Factory";272;3
"Unit";"Cyclone";"Factory";272;3
"Unit";"SCV";"Command Center";280;1
"Unit";"SCV";"Command Center";280;1
"Unit";"SCV";"Command Center";282;1
"Unit";"SCV";"Command Center";282;1
"Unit";"Cyclone";"Factory";274;3
"Unit";"Cyclone";"Factory";274;3
"Building";"CommandCenter";NA;253;0
"Unit";"Cyclone";"Factory";282;3
