"type";"unit_name";"on_building";"total_supply";"supply"
"Building";"Refinery";NA;14;0
"Building";"Barracks";NA;15;0
"Unit";"Reaper";"Barracks";19;1
"Unit";"Reaper";"Barracks";19;1
"Building";"Refinery";NA;22;0
"Unit";"Marine";"Barracks";24;1
"Building";"CommandCenter";NA;19;0
"Building";"Bunker";NA;22;0
"Building";"Factory";NA;21;0
"Unit";"Marine";"Barracks";26;1
"Unit";"Cyclone";"Factory";29;3
"Building";"BarracksReactor";NA;30;0
"Unit";"Cyclone";"Factory";36;3
"Building";"Refinery";NA;37;0
"Building";"EngineeringBay";NA;38;0
"Building";"Starport";NA;36;0
"Building";"BarracksTechLab";NA;43;0
"Building";"Refinery";NA;45;0
"Unit";"Cyclone";"Factory";46;3
"Unit";"Cyclone";"Factory";46;3
"Unit";"Cyclone";"Factory";57;3
"Unit";"Raven";"Starport";52;2
"Building";"BarracksTechLab";NA;68;0
"Building";"CommandCenter";NA;61;0
"Building";"Armory";NA;70;0
"Building";"BarracksTechLab";NA;74;0
"Building";"Factory";NA;72;0
"Building";"MissileTurret";NA;76;0
"Building";"BarracksTechLab";NA;77;0
"Building";"MissileTurret";NA;77;0
"Building";"Factory";NA;77;0
"Building";"MissileTurret";NA;78;0
"Building";"Factory";NA;78;0
"Unit";"Hellion";"Factory";79;2
"Unit";"Hellion";"Factory";79;2
"Building";"FactoryTechLab";NA;83;0
"Unit";"Hellion";"Factory";83;2
"Unit";"Hellion";"Factory";83;2
"Upgrade";"TerranVehicleWeaponsLevel1";"Armory";78;0
"Unit";"Hellion";"Factory";83;2
"Unit";"Hellion";"Factory";83;2
"Unit";"Hellion";"Factory";85;2
"Unit";"Hellion";"Factory";87;2
"Unit";"Hellion";"Factory";89;2
"Unit";"Hellion";"Factory";91;2
"Building";"MissileTurret";NA;93;0
"Building";"SensorTower";NA;93;0
"Building";"MissileTurret";NA;93;0
"Building";"MissileTurret";NA;93;0
"Unit";"Liberator";"Starport";87;3
"Unit";"Hellion";"Factory";93;2
"Unit";"Hellion";"Factory";93;2
"Unit";"Hellion";"Factory";97;2
"Building";"SensorTower";NA;103;0
"Building";"Refinery";NA;103;0
"Unit";"Hellion";"Factory";103;2
"Building";"MissileTurret";NA;109;0
"Building";"Refinery";NA;109;0
"Building";"MissileTurret";NA;116;0
"Building";"Factory";NA;112;0
"Building";"BarracksReactor";NA;116;0
"Building";"BarracksTechLab";NA;118;0
"Unit";"Hellion";"Factory";118;2
"Unit";"Hellion";"Factory";118;2
"Unit";"Hellion";"Factory";118;2
"Building";"Starport";NA;118;0
"Unit";"Hellion";"Factory";118;2
"Unit";"Hellion";"Factory";118;2
"Building";"CommandCenter";NA;118;0
"Unit";"Hellion";"Factory";126;2
"Unit";"Hellion";"Factory";128;2
"Building";"SensorTower";NA;130;0
"Building";"Factory";NA;128;0
"Unit";"Hellion";"Factory";130;2
"Unit";"Hellion";"Factory";130;2
"Unit";"Hellion";"Factory";130;2
"Unit";"Hellion";"Factory";136;2
"Building";"Refinery";NA;138;0
"Building";"Refinery";NA;138;0
"Building";"SensorTower";NA;139;0
"Unit";"Thor";"Factory";132;6
"Unit";"Hellion";"Factory";142;2
"Unit";"Hellion";"Factory";142;2
"Unit";"Hellion";"Factory";148;2
"Unit";"Hellion";"Factory";150;2
"Unit";"Thor";"Factory";142;6
"Unit";"Hellion";"Factory";150;2
"Unit";"Hellion";"Factory";152;2
"Unit";"Hellion";"Factory";152;2
"Unit";"Hellion";"Factory";154;2
"Unit";"Hellion";"Factory";156;2
"Unit";"Hellion";"Factory";162;2
"Unit";"Hellion";"Factory";164;2
"Building";"MissileTurret";NA;168;0
"Unit";"Hellion";"Factory";166;2
"Building";"MissileTurret";NA;172;0
"Building";"MissileTurret";NA;172;0
"Unit";"Hellion";"Factory";168;2
"Unit";"Hellion";"Factory";172;2
"Unit";"Hellion";"Factory";172;2
