"Type";"UnitName";"OnBuilding";"TotalSupply";"Supply"
"Unit";"SCV";"Command Center";12;1
"Unit";"SCV";"Command Center";12;1
"Unit";"SCV";"Command Center";13;1
"Building";"SupplyDepot";NA;13;0
"Building";"Refinery";NA;14;0
"Unit";"SCV";"Command Center";15;1
"Unit";"SCV";"Command Center";15;1
"Unit";"SCV";"Command Center";16;1
"Building";"Refinery";NA;16;0
"Unit";"SCV";"Command Center";18;1
"Building";"Barracks";NA;15;0
"Unit";"SCV";"Command Center";18;1
"Unit";"Reaper";"Barracks";19;1
"Building";"SupplyDepot";NA;20;0
"Building";"Factory";NA;19;0
"Unit";"SCV";"Command Center";21;1
"Unit";"SCV";"Command Center";22;1
"Building";"BarracksReactor";NA;21;0
"Building";"SupplyDepot";NA;22;0
"Unit";"SCV";"Command Center";22;1
"Unit";"Cyclone";"Factory";22;3
"Unit";"SCV";"Command Center";23;1
"Unit";"SCV";"Command Center";28;1
"Unit";"SCV";"Command Center";28;1
"Building";"SupplyDepot";NA;28;0
"Unit";"Cyclone";"Factory";28;3
"Unit";"Cyclone";"Factory";28;3
"Unit";"SCV";"Command Center";29;1
"Unit";"SCV";"Command Center";37;1
"Unit";"Cyclone";"Factory";36;3
"Unit";"Cyclone";"Factory";36;3
"Unit";"SCV";"Command Center";37;1
"Building";"SupplyDepot";NA;37;0
"Unit";"SCV";"Command Center";44;1
"Unit";"SCV";"Command Center";45;1
"Unit";"SCV";"Command Center";46;1
"Unit";"Cyclone";"Factory";46;3
"Unit";"Cyclone";"Factory";46;3
"Building";"BarracksTechLab";NA;47;0
"Building";"SupplyDepot";NA;47;0
"Unit";"SCV";"Command Center";47;1
"Unit";"SCV";"Command Center";55;1
"Building";"CommandCenter";NA;37;0
"Unit";"SCV";"Command Center";56;1
"Unit";"Marine";"Barracks";55;1
"Building";"Barracks";NA;47;0
"Building";"Barracks";NA;47;0
"Unit";"SCV";"Command Center";57;1
"Building";"FactoryReactor";NA;55;0
"Building";"Starport";NA;55;0
"Unit";"SCV";"Command Center";58;1
"Unit";"Marine";"Barracks";59;1
"Unit";"Marine";"Barracks";59;1
"Building";"SupplyDepot";NA;59;0
"Unit";"SCV";"Command Center";59;1
"Unit";"Marine";"Barracks";59;1
"Building";"EngineeringBay";NA;59;0
"Building";"FactoryTechLab";NA;59;0
"Building";"BarracksReactor";NA;58;0
"Unit";"SCV";"Command Center";60;1
"Unit";"SCV";"Command Center";62;1
"Unit";"Marine";"Barracks";60;1
"Unit";"Marine";"Barracks";61;1
"Unit";"Marine";"Barracks";63;1
"Unit";"SCV";"Command Center";64;1
"Building";"SupplyDepot";NA;64;0
"Building";"EngineeringBay";NA;64;0
"Unit";"Marine";"Barracks";65;1
"Unit";"Marine";"Barracks";65;1
"Unit";"Medivac";"Starport";64;2
"Unit";"SCV";"Command Center";69;1
"Unit";"Marine";"Barracks";69;1
"Unit";"Marine";"Barracks";69;1
"Unit";"Medivac";"Starport";64;2
"Unit";"Marine";"Barracks";69;1
"Unit";"SCV";"Command Center";70;1
"Unit";"SCV";"Command Center";74;1
"Building";"SupplyDepot";NA;70;0
"Upgrade";"Stimpack";"TechLab";58;0
"Unit";"Marine";"Barracks";80;1
"Building";"Refinery";NA;80;0
"Building";"Refinery";NA;80;0
"Unit";"Marine";"Barracks";81;1
"Unit";"Marine";"Barracks";82;1
"Unit";"SCV";"Command Center";82;1
"Unit";"SCV";"Command Center";82;1
"Unit";"Medivac";"Starport";81;2
"Unit";"Marine";"Barracks";83;1
"Unit";"Marine";"Barracks";83;1
"Unit";"Marine";"Barracks";83;1
"Unit";"Marine";"Barracks";83;1
"Unit";"Medivac";"Starport";85;2
"Building";"SupplyDepot";NA;92;0
"Unit";"SCV";"Command Center";93;1
"Unit";"SCV";"Command Center";93;1
"Unit";"Marine";"Barracks";93;1
"Unit";"Marine";"Barracks";93;1
"Unit";"Marine";"Barracks";93;1
"Unit";"Marine";"Barracks";95;1
"Unit";"Marine";"Barracks";95;1
"Unit";"SCV";"Command Center";95;1
"Unit";"SCV";"Command Center";97;1
"Building";"SupplyDepot";NA;95;0
"Building";"SupplyDepot";NA;95;0
"Unit";"SCV";"Command Center";102;1
"Unit";"SCV";"Command Center";103;1
"Unit";"Marine";"Barracks";97;1
"Unit";"Marine";"Barracks";98;1
"Building";"SupplyDepot";NA;97;0
"Unit";"Medivac";"Starport";97;2
"Unit";"Marine";"Barracks";104;1
"Unit";"SCV";"Command Center";105;1
"Unit";"SCV";"Command Center";105;1
"Unit";"Marine";"Barracks";108;1
"Building";"SensorTower";NA;108;0
"Building";"SupplyDepot";NA;105;0
"Unit";"SCV";"Command Center";111;1
"Unit";"SCV";"Command Center";112;1
"Unit";"Marine";"Barracks";111;1
"Unit";"Marine";"Barracks";111;1
"Unit";"Marine";"Barracks";113;1
"Unit";"SCV";"Command Center";114;1
"Unit";"SCV";"Command Center";115;1
"Building";"CommandCenter";NA;95;0
"Unit";"SCV";"Command Center";119;1
"Unit";"Marine";"Barracks";121;1
"Unit";"Marine";"Barracks";121;1
"Unit";"Marine";"Barracks";121;1
"Unit";"Marine";"Barracks";121;1
"Unit";"Marine";"Barracks";121;1
"Unit";"SCV";"Command Center";121;1
"Building";"Armory";NA;111;0
"Unit";"SCV";"Command Center";122;1
"Upgrade";"TerranInfantryWeaponsLevel1";"EngineeringBay";97;0
"Unit";"SCV";"Command Center";128;1
"Unit";"Marine";"Barracks";122;1
"Unit";"Marine";"Barracks";123;1
"Unit";"Marine";"Barracks";124;1
"Unit";"Marine";"Barracks";124;1
"Unit";"Marine";"Barracks";128;1
"Building";"SensorTower";NA;128;0
"Upgrade";"TerranInfantryArmorsLevel1";"EngineeringBay";105;0
"Unit";"SCV";"Command Center";134;1
"Unit";"Marine";"Barracks";130;1
"Unit";"Marine";"Barracks";131;1
"Unit";"Marine";"Barracks";132;1
"Unit";"SCV";"Command Center";135;1
"Unit";"Marine";"Barracks";135;1
"Unit";"Marine";"Barracks";135;1
"Building";"Factory";NA;122;0
"Building";"Refinery";NA;135;0
"Unit";"SCV";"Command Center";136;1
"Unit";"Marine";"Barracks";136;1
"Unit";"SCV";"Command Center";142;1
"Unit";"SCV";"Command Center";142;1
"Unit";"Marine";"Barracks";140;1
"Unit";"Marine";"Barracks";140;1
"Unit";"Marine";"Barracks";140;1
"Unit";"Marine";"Barracks";141;1
"Unit";"SCV";"Command Center";143;1
"Building";"FactoryTechLab";NA;143;0
"Building";"Refinery";NA;142;0
"Unit";"Marine";"Barracks";143;1
"Unit";"Marine";"Barracks";146;1
"Unit";"SCV";"Command Center";151;1
"Unit";"Marine";"Barracks";147;1
"Building";"Barracks";NA;135;0
"Unit";"Marine";"Barracks";148;1
"Unit";"Marine";"Barracks";149;1
"Building";"Barracks";NA;135;0
