"type";"unit_name";"on_building";"total_supply";"supply"
"Building";"Refinery";NA;14;0
"Building";"Refinery";NA;16;0
"Building";"Barracks";NA;15;0
"Unit";"Reaper";"Barracks";19;1
"Building";"Factory";NA;19;0
"Unit";"Reaper";"Barracks";20;1
"Unit";"Hellion";"Factory";21;2
"Building";"Starport";NA;21;0
"Building";"BarracksTechLab";NA;26;0
"Unit";"Cyclone";"Factory";27;3
"Unit";"Liberator";"Starport";27;3
"Building";"BarracksReactor";NA;31;0
"Unit";"Cyclone";"Factory";35;3
"Unit";"Marine";"Barracks";35;1
"Unit";"Marine";"Barracks";35;1
"Unit";"Marine";"Barracks";41;1
"Unit";"Marine";"Barracks";41;1
"Building";"CommandCenter";NA;32;0
"Unit";"Cyclone";"Factory";42;3
"Unit";"Marine";"Barracks";45;1
"Unit";"Marine";"Barracks";45;1
"Building";"FactoryTechLab";NA;49;0
"Unit";"Raven";"Starport";42;2
"Unit";"Marine";"Barracks";52;1
"Unit";"Marine";"Barracks";52;1
"Unit";"Marine";"Barracks";60;1
"Unit";"Marine";"Barracks";64;1
"Building";"CommandCenter";NA;59;0
"Building";"EngineeringBay";NA;66;0
"Building";"EngineeringBay";NA;66;0
"Building";"Refinery";NA;69;0
"Building";"Refinery";NA;69;0
"Building";"StarportReactor";NA;66;0
"Building";"Barracks";NA;66;0
"Building";"Barracks";NA;66;0
"Unit";"Marine";"Barracks";73;1
"Unit";"Marine";"Barracks";76;1
"Unit";"Marine";"Barracks";77;1
"Unit";"Marine";"Barracks";77;1
"Unit";"Marine";"Barracks";77;1
"Unit";"Marine";"Barracks";77;1
"Upgrade";"Stimpack";"TechLab";66;0
"Building";"StarportReactor";NA;75;0
"Unit";"Marine";"Barracks";84;1
"Unit";"Marine";"Barracks";84;1
"Unit";"Marine";"Barracks";84;1
"Unit";"Marine";"Barracks";84;1
"Unit";"Marine";"Barracks";84;1
"Unit";"Marine";"Barracks";88;1
"Unit";"Marine";"Barracks";89;1
"Unit";"Marine";"Barracks";90;1
"Unit";"Marine";"Barracks";91;1
"Unit";"Marine";"Barracks";92;1
"Building";"SensorTower";NA;94;0
"Building";"SensorTower";NA;96;0
"Unit";"Marine";"Barracks";104;1
"Unit";"Marine";"Barracks";104;1
"Unit";"Marine";"Barracks";104;1
"Unit";"Marine";"Barracks";104;1
"Unit";"Marine";"Barracks";104;1
"Upgrade";"TerranInfantryWeaponsLevel1";"EngineeringBay";80;0
"Upgrade";"TerranInfantryArmorsLevel1";"EngineeringBay";80;0
"Unit";"Marine";"Barracks";113;1
"Unit";"Marine";"Barracks";113;1
"Unit";"Marine";"Barracks";113;1
"Unit";"Marine";"Barracks";113;1
"Unit";"Marine";"Barracks";113;1
"Unit";"Medivac";"Starport";106;2
"Unit";"Medivac";"Starport";106;2
"Building";"Refinery";NA;114;0
"Building";"Refinery";NA;114;0
"Unit";"Marine";"Barracks";122;1
"Unit";"Marine";"Barracks";122;1
"Unit";"Marine";"Barracks";122;1
"Unit";"Marine";"Barracks";122;1
"Unit";"Marine";"Barracks";122;1
"Building";"Armory";NA;106;0
"Unit";"Marine";"Barracks";126;1
"Unit";"Marine";"Barracks";127;1
"Unit";"Marine";"Barracks";128;1
"Unit";"Marine";"Barracks";129;1
"Unit";"Marine";"Barracks";134;1
"Unit";"Marine";"Barracks";134;1
"Unit";"Marine";"Barracks";135;1
"Unit";"Marine";"Barracks";136;1
"Unit";"Marine";"Barracks";137;1
"Building";"Barracks";NA;131;0
"Unit";"Medivac";"Starport";138;2
"Building";"Barracks";NA;131;0
"Building";"Factory";NA;131;0
"Unit";"Marine";"Barracks";146;1
"Unit";"Marine";"Barracks";146;1
"Unit";"Marine";"Barracks";146;1
"Unit";"Marine";"Barracks";146;1
"Unit";"Medivac";"Starport";141;2
"Unit";"Marine";"Barracks";146;1
"Building";"FactoryTechLab";NA;151;0
"Unit";"Marine";"Barracks";154;1
"Unit";"Marine";"Barracks";157;1
"Unit";"Marine";"Barracks";158;1
"Unit";"Marine";"Barracks";158;1
"Unit";"Marine";"Barracks";158;1
"Unit";"Medivac";"Starport";146;2
"Building";"BarracksReactor";NA;151;0
"Building";"BarracksReactor";NA;151;0
"Unit";"Medivac";"Starport";155;2
"Unit";"Marine";"Barracks";163;1
"Unit";"Marine";"Barracks";163;1
"Unit";"Marine";"Barracks";163;1
"Unit";"Marine";"Barracks";163;1
"Unit";"Marine";"Barracks";163;1
"Unit";"Marine";"Barracks";167;1
"Unit";"Marine";"Barracks";167;1
"Unit";"Marine";"Barracks";167;1
"Unit";"Marine";"Barracks";167;1
"Building";"CommandCenter";NA;146;0
"Unit";"Marine";"Barracks";167;1
"Unit";"Marine";"Barracks";168;1
"Unit";"Marine";"Barracks";172;1
"Upgrade";"TerranVehicleWeaponsLevel1";"Armory";146;0
"Unit";"Marine";"Barracks";173;1
"Unit";"Marine";"Barracks";174;1
"Unit";"Marine";"Barracks";177;1
"Unit";"Marine";"Barracks";177;1
"Building";"FactoryTechLab";NA;179;0
"Upgrade";"TerranInfantryArmorsLevel2";"EngineeringBay";146;0
"Upgrade";"TerranInfantryWeaponsLevel2";"EngineeringBay";146;0
"Unit";"Marine";"Barracks";183;1
"Unit";"Marine";"Barracks";183;1
"Unit";"Marine";"Barracks";183;1
"Unit";"Marine";"Barracks";184;1
"Unit";"Marine";"Barracks";188;1
"Unit";"Marine";"Barracks";188;1
"Unit";"Marine";"Barracks";188;1
"Unit";"Marine";"Barracks";188;1
"Building";"Factory";NA;184;0
"Building";"Barracks";NA;184;0
"Building";"Barracks";NA;184;0
"Building";"StarportReactor";NA;188;0
"Building";"BarracksReactor";NA;188;0
"Building";"BarracksReactor";NA;188;0
"Unit";"Marine";"Barracks";194;1
"Unit";"Marine";"Barracks";194;1
"Unit";"Marine";"Barracks";194;1
"Unit";"Marine";"Barracks";194;1
"Building";"FactoryTechLab";NA;194;0
"Building";"SensorTower";NA;194;0
"Unit";"Marine";"Barracks";196;1
"Unit";"Marine";"Barracks";200;1
"Unit";"Marine";"Barracks";200;1
"Unit";"Marine";"Barracks";200;1
"Unit";"Marine";"Barracks";200;1
"Unit";"Marine";"Barracks";200;1
"Unit";"Marine";"Barracks";200;1
"Unit";"Marine";"Barracks";200;1
"Building";"BarracksReactor";NA;194;0
"Building";"BarracksReactor";NA;194;0
"Unit";"Medivac";"Starport";200;2
"Unit";"Medivac";"Starport";200;2
"Building";"CommandCenter";NA;190;0
"Unit";"Marine";"Barracks";212;1
"Unit";"Marine";"Barracks";212;1
"Unit";"Marine";"Barracks";212;1
"Unit";"Marine";"Barracks";212;1
"Unit";"Marine";"Barracks";212;1
"Unit";"Marine";"Barracks";212;1
"Unit";"Marine";"Barracks";212;1
"Unit";"Marine";"Barracks";212;1
"Unit";"Marine";"Barracks";212;1
"Unit";"Marine";"Barracks";212;1
"Unit";"Marine";"Barracks";212;1
"Unit";"Marine";"Barracks";212;1
"Unit";"Marine";"Barracks";217;1
"Unit";"Marine";"Barracks";229;1
"Unit";"Marine";"Barracks";229;1
"Unit";"Marine";"Barracks";229;1
"Unit";"Marine";"Barracks";229;1
"Unit";"Marine";"Barracks";229;1
"Unit";"Marine";"Barracks";229;1
"Unit";"Marine";"Barracks";229;1
"Unit";"Marine";"Barracks";229;1
"Unit";"Marine";"Barracks";238;1
"Unit";"Marine";"Barracks";238;1
"Unit";"Marine";"Barracks";238;1
"Unit";"Marine";"Barracks";238;1
"Unit";"Marine";"Barracks";238;1
"Unit";"Marine";"Barracks";238;1
"Unit";"Marine";"Barracks";238;1
"Building";"CommandCenter";NA;205;0
"Upgrade";"TerranInfantryWeaponsLevel3";"EngineeringBay";194;0
"Upgrade";"TerranInfantryArmorsLevel3";"EngineeringBay";194;0
"Unit";"Marine";"Barracks";245;1
"Unit";"Marine";"Barracks";245;1
"Unit";"Marine";"Barracks";245;1
"Unit";"Marine";"Barracks";245;1
"Unit";"Marine";"Barracks";245;1
"Unit";"Marine";"Barracks";245;1
"Unit";"Marine";"Barracks";245;1
"Unit";"Marine";"Barracks";245;1
