"Type";"UnitName";"OnBuilding";"TotalSupply";"Supply"
"Unit";"SCV";"Command Center";12;1
"Unit";"SCV";"Command Center";12;1
"Unit";"SCV";"Command Center";13;1
"Building";"SupplyDepot";NA;13;0
"Building";"Refinery";NA;14;0
"Unit";"SCV";"Command Center";15;1
"Unit";"SCV";"Command Center";16;1
"Unit";"SCV";"Command Center";16;1
"Building";"Refinery";NA;16;0
"Unit";"SCV";"Command Center";17;1
"Building";"Barracks";NA;15;0
"Unit";"Reaper";"Barracks";19;1
"Unit";"SCV";"Command Center";19;1
"Building";"SupplyDepot";NA;19;0
"Building";"Factory";NA;19;0
"Building";"SupplyDepot";NA;20;0
"Unit";"SCV";"Command Center";21;1
"Unit";"Reaper";"Barracks";20;1
"Unit";"Hellion";"Factory";21;2
"Unit";"SCV";"Command Center";25;1
"Unit";"SCV";"Command Center";25;1
"Unit";"Cyclone";"Factory";25;3
"Building";"SupplyDepot";NA;25;0
"Building";"BarracksReactor";NA;25;0
"Unit";"SCV";"Command Center";26;1
"Unit";"SCV";"Command Center";30;1
"Unit";"Marine";"Barracks";31;1
"Unit";"Marine";"Barracks";31;1
"Unit";"SCV";"Command Center";31;1
"Unit";"SCV";"Command Center";34;1
"Unit";"Marine";"Barracks";35;1
"Unit";"Marine";"Barracks";35;1
"Unit";"Cyclone";"Factory";35;3
"Unit";"SCV";"Command Center";35;1
"Building";"CommandCenter";NA;22;0
"Unit";"SCV";"Command Center";41;1
"Unit";"Marine";"Barracks";36;1
"Unit";"Marine";"Barracks";37;1
"Building";"FactoryTechLab";NA;41;0
"Building";"Starport";NA;35;0
"Unit";"SCV";"Command Center";42;1
"Unit";"Marine";"Barracks";43;1
"Unit";"Marine";"Barracks";44;1
"Unit";"SCV";"Command Center";45;1
"Unit";"SCV";"Command Center";48;1
"Unit";"SCV";"Command Center";48;1
"Unit";"Medivac";"Starport";45;2
"Unit";"SCV";"Command Center";53;1
"Unit";"SCV";"Command Center";53;1
"Unit";"SCV";"Command Center";53;1
"Unit";"SCV";"Command Center";54;1
"Unit";"SCV";"Command Center";55;1
"Unit";"SCV";"Command Center";57;1
"Building";"Refinery";NA;57;0
"Building";"Refinery";NA;57;0
"Unit";"SCV";"Command Center";58;1
"Building";"FactoryTechLab";NA;58;0
"Unit";"SCV";"Command Center";59;1
"Unit";"SCV";"Command Center";59;1
"Unit";"Liberator";"Starport";57;3
"Building";"EngineeringBay";NA;59;0
"Building";"EngineeringBay";NA;59;0
"Unit";"SCV";"Command Center";60;1
"Unit";"Marine";"Barracks";60;1
"Unit";"SCV";"Command Center";61;1
"Unit";"SCV";"Command Center";65;1
"Building";"Barracks";NA;58;0
"Building";"Barracks";NA;59;0
"Unit";"SCV";"Command Center";68;1
"Unit";"Marine";"Barracks";67;1
"Building";"CommandCenter";NA;55;0
"Unit";"SCV";"Command Center";68;1
"Unit";"SCV";"Command Center";69;1
"Building";"StarportReactor";NA;65;0
"Unit";"Marine";"Barracks";70;1
"Unit";"Marine";"Barracks";70;1
"Unit";"SCV";"Command Center";71;1
"Unit";"Marine";"Barracks";71;1
"Unit";"SCV";"Command Center";72;1
"Unit";"SCV";"Command Center";75;1
"Building";"BarracksReactor";NA;69;0
"Unit";"SCV";"Command Center";78;1
"Unit";"Marine";"Barracks";78;1
"Unit";"Marine";"Barracks";78;1
"Unit";"Marine";"Barracks";78;1
"Building";"SupplyDepot";NA;78;0
"Building";"SupplyDepot";NA;78;0
"Building";"SupplyDepot";NA;79;0
"Unit";"SCV";"Command Center";83;1
"Unit";"Marine";"Barracks";83;1
"Unit";"SCV";"Command Center";83;1
"Unit";"Marine";"Barracks";83;1
"Unit";"Marine";"Barracks";83;1
"Unit";"Marine";"Barracks";83;1
"Unit";"Marine";"Barracks";83;1
"Upgrade";"Stimpack";"TechLab";68;0
"Building";"SupplyDepot";NA;83;0
"Unit";"SCV";"Command Center";83;1
"Unit";"Medivac";"Starport";83;2
"Unit";"Medivac";"Starport";83;2
"Unit";"SCV";"Command Center";85;1
"Unit";"SCV";"Command Center";90;1
"Unit";"Marine";"Barracks";90;1
"Unit";"Marine";"Barracks";90;1
"Unit";"Marine";"Barracks";90;1
"Unit";"Marine";"Barracks";90;1
"Unit";"Marine";"Barracks";90;1
"Unit";"SCV";"Command Center";102;1
"Unit";"SCV";"Command Center";102;1
"Unit";"SCV";"Command Center";102;1
"Building";"SupplyDepot";NA;96;0
"Upgrade";"TerranInfantryArmorsLevel1";"EngineeringBay";78;0
"Upgrade";"TerranInfantryWeaponsLevel1";"EngineeringBay";78;0
"Unit";"Marine";"Barracks";97;1
"Unit";"SCV";"Command Center";102;1
"Unit";"Marine";"Barracks";102;1
"Unit";"Marine";"Barracks";102;1
"Unit";"Marine";"Barracks";102;1
"Unit";"Medivac";"Starport";100;2
"Building";"Barracks";NA;91;0
"Building";"Barracks";NA;91;0
"Unit";"Marine";"Barracks";106;1
"Unit";"Marine";"Barracks";106;1
"Unit";"SCV";"Command Center";107;1
"Unit";"SCV";"Command Center";107;1
"Unit";"SCV";"Command Center";107;1
"Building";"SupplyDepot";NA;106;0
"Unit";"SCV";"Command Center";114;1
"Unit";"Marine";"Barracks";112;1
"Unit";"Medivac";"Starport";107;2
"Unit";"Marine";"Barracks";117;1
"Unit";"Marine";"Barracks";117;1
"Unit";"Marine";"Barracks";117;1
"Unit";"Marine";"Barracks";117;1
"Unit";"Marine";"Barracks";118;1
"Building";"Armory";NA;106;0
"Building";"BarracksReactor";NA;112;0
"Building";"BarracksReactor";NA;112;0
"Unit";"Marine";"Barracks";121;1
"Unit";"Marine";"Barracks";122;1
"Unit";"Marine";"Barracks";123;1
"Unit";"Marine";"Barracks";124;1
"Unit";"SCV";"Command Center";126;1
"Unit";"Marine";"Barracks";125;1
"Unit";"SCV";"Command Center";126;1
"Unit";"Marine";"Barracks";126;1
"Unit";"SCV";"Command Center";130;1
