"type";"unit_name";"on_building";"total_supply_lag";"supply"
"Unit";"Overlord";"Larva";13;0
"Building";"Extractor";NA;17;0
"Building";"SpawningPool";NA;18;0
"Building";"Hatchery";NA;20;0
"Unit";"Queen";"Hatchery";22;2
"Unit";"Zergling";"Larva";24;1
"Unit";"Zergling";"Larva";25;1
"Unit";"Overlord";"Larva";26;0
"Building";"BanelingNest";NA;26;0
"Unit";"Queen";"Hatchery";27;2
"Unit";"Zergling";"Larva";30;1
"Unit";"Zergling";"Larva";31;1
"Unit";"Zergling";"Larva";32;1
"Unit";"Zergling";"Larva";33;1
"Unit";"Zergling";"Larva";34;1
"Unit";"Zergling";"Larva";35;1
"Unit";"Zergling";"Larva";36;1
"Unit";"Zergling";"Larva";37;1
"Unit";"Zergling";"Larva";38;1
"Unit";"Zergling";"Larva";39;1
"Unit";"Zergling";"Larva";40;1
"Unit";"Zergling";"Larva";41;1
"Unit";"Zergling";"Larva";42;1
"Unit";"Zergling";"Larva";43;1
"Unit";"Zergling";"Larva";44;1
"Unit";"Zergling";"Larva";45;1
"Unit";"Baneling";"Zergling";46;0
"Unit";"Baneling";"Zergling";46;0
"Unit";"Zergling";"Larva";46;1
"Unit";"Zergling";"Larva";47;1
"Unit";"Zergling";"Larva";48;1
"Unit";"Zergling";"Larva";49;1
"Unit";"Overlord";"Larva";50;0
"Unit";"Overlord";"Larva";52;0
"Unit";"Overlord";"Larva";58;0
"Unit";"Baneling";"Zergling";60;0
"Unit";"Baneling";"Zergling";60;0
"Unit";"Baneling";"Zergling";62;0
"Building";"Hatchery";NA;62;0
"Unit";"Zergling";"Larva";62;1
"Unit";"Zergling";"Larva";63;1
"Unit";"Zergling";"Larva";64;1
"Unit";"Zergling";"Larva";65;1
"Unit";"Zergling";"Larva";66;1
"Unit";"Zergling";"Larva";67;1
"Unit";"Zergling";"Larva";68;1
"Unit";"Zergling";"Larva";69;1
"Unit";"Zergling";"Larva";70;1
"Unit";"Zergling";"Larva";71;1
"Unit";"Zergling";"Larva";72;1
"Unit";"Zergling";"Larva";73;1
"Unit";"Zergling";"Larva";74;1
"Unit";"Zergling";"Larva";75;1
"Unit";"Zergling";"Larva";76;1
"Unit";"Zergling";"Larva";77;1
"Unit";"Zergling";"Larva";78;1
"Unit";"Zergling";"Larva";79;1
"Unit";"Zergling";"Larva";80;1
"Unit";"Zergling";"Larva";81;1
"Building";"RoachWarren";NA;88;0
"Unit";"Queen";"Hatchery";88;2
"Building";"Extractor";NA;91;0
"Building";"Extractor";NA;92;0
"Unit";"Zergling";"Larva";92;1
"Unit";"Zergling";"Larva";93;1
"Unit";"Baneling";"Zergling";94;0
"Unit";"Baneling";"Zergling";94;0
"Unit";"Overlord";"Larva";94;0
"Unit";"Zergling";"Larva";96;1
"Unit";"Zergling";"Larva";97;1
"Unit";"Zergling";"Larva";98;1
"Unit";"Zergling";"Larva";99;1
"Building";"CreepTumorQueen";NA;100;0
"Unit";"Zergling";"Larva";100;1
"Unit";"Zergling";"Larva";101;1
"Unit";"Zergling";"Larva";102;1
"Unit";"Zergling";"Larva";103;1
"Unit";"Zergling";"Larva";104;1
"Unit";"Zergling";"Larva";105;1
"Unit";"Zergling";"Larva";106;1
"Unit";"Zergling";"Larva";107;1
"Unit";"Zergling";"Larva";108;1
"Unit";"Zergling";"Larva";109;1
"Unit";"Zergling";"Larva";110;1
"Unit";"Zergling";"Larva";111;1
"Unit";"Zergling";"Larva";112;1
"Unit";"Zergling";"Larva";113;1
"Unit";"Baneling";"Zergling";114;0
"Unit";"Baneling";"Zergling";114;0
"Unit";"Roach";"Larva";114;2
"Unit";"Roach";"Larva";116;2
"Unit";"Roach";"Larva";118;2
"Unit";"Roach";"Larva";120;2
"Unit";"Roach";"Larva";122;2
"Unit";"Roach";"Larva";124;2
"Unit";"Roach";"Larva";126;2
"Unit";"Baneling";"Zergling";128;0
"Unit";"Baneling";"Zergling";128;0
"Building";"CreepTumor";NA;128;0
"Unit";"Overlord";"Larva";128;0
"Unit";"Roach";"Larva";128;2
"Unit";"Roach";"Larva";130;2
"Unit";"Overlord";"Larva";132;0
"Unit";"Overlord";"Larva";132;0
"Unit";"Overlord";"Larva";133;0
"Unit";"Roach";"Larva";133;2
"Unit";"Roach";"Larva";135;2
"Unit";"Roach";"Larva";137;2
"Unit";"Roach";"Larva";139;2
"Unit";"Roach";"Larva";141;2
"Unit";"Roach";"Larva";143;2
"Unit";"Roach";"Larva";145;2
"Unit";"Roach";"Larva";147;2
"Unit";"Roach";"Larva";149;2
"Unit";"Roach";"Larva";156;2
"Unit";"Roach";"Larva";158;2
"Unit";"Roach";"Larva";160;2
"Unit";"Roach";"Larva";162;2
"Unit";"Zergling";"Larva";164;1
"Unit";"Zergling";"Larva";165;1
"Unit";"Zergling";"Larva";166;1
"Unit";"Zergling";"Larva";167;1
"Unit";"Zergling";"Larva";168;1
"Unit";"Zergling";"Larva";169;1
"Unit";"Roach";"Larva";170;2
"Unit";"Roach";"Larva";172;2
"Unit";"Roach";"Larva";174;2
"Unit";"Zergling";"Larva";176;1
"Unit";"Zergling";"Larva";177;1
"Unit";"Zergling";"Larva";178;1
"Unit";"Zergling";"Larva";179;1
"Unit";"Overlord";"Larva";180;0
"Unit";"Roach";"Larva";180;2
"Unit";"Roach";"Larva";182;2
"Unit";"Roach";"Larva";184;2
"Unit";"Roach";"Larva";186;2
"Unit";"Roach";"Larva";188;2
"Unit";"Roach";"Larva";190;2
"Unit";"Roach";"Larva";192;2
"Unit";"Roach";"Larva";194;2
"Unit";"Roach";"Larva";196;2
"Unit";"Roach";"Larva";198;2
"Unit";"Roach";"Larva";200;2
"Unit";"Roach";"Larva";202;2
"Unit";"Roach";"Larva";204;2
"Unit";"Roach";"Larva";206;2
"Unit";"Overlord";"Larva";208;0
"Unit";"Overlord";"Larva";208;0
"Unit";"Overlord";"Larva";208;0
"Unit";"Zergling";"Larva";208;1
"Unit";"Zergling";"Larva";209;1
"Unit";"Zergling";"Larva";210;1
"Unit";"Zergling";"Larva";211;1
"Unit";"Zergling";"Larva";212;1
"Unit";"Zergling";"Larva";213;1
"Unit";"Zergling";"Larva";214;1
"Unit";"Zergling";"Larva";215;1
"Unit";"Roach";"Larva";216;2
"Unit";"Zergling";"Larva";218;1
"Unit";"Zergling";"Larva";219;1
"Unit";"Zergling";"Larva";220;1
"Unit";"Zergling";"Larva";221;1
"Unit";"Zergling";"Larva";222;1
"Unit";"Zergling";"Larva";223;1
"Unit";"Zergling";"Larva";224;1
"Unit";"Zergling";"Larva";225;1
"Upgrade";"SprayZerg";NA;226;0
"Upgrade";"SprayZerg";NA;226;0
"Upgrade";"zerglingmovementspeed";NA;226;0
"Upgrade";"SprayZerg";NA;226;0
"Upgrade";"SprayZerg";NA;226;0
