"type";"unit_name";"on_building";"total_supply_lag";"supply"
"Unit";"Overlord";"Larva";13;0
"Building";"Extractor";NA;17;0
"Building";"SpawningPool";NA;18;0
"Building";"Hatchery";NA;20;0
"Unit";"Queen";"Hatchery";21;2
"Unit";"Zergling";"Larva";23;1
"Unit";"Zergling";"Larva";24;1
"Unit";"Overlord";"Larva";25;0
"Building";"BanelingNest";NA;26;0
"Unit";"Zergling";"Larva";26;1
"Unit";"Zergling";"Larva";27;1
"Unit";"Queen";"Hatchery";28;2
"Unit";"Zergling";"Larva";30;1
"Unit";"Zergling";"Larva";31;1
"Unit";"Zergling";"Larva";33;1
"Unit";"Zergling";"Larva";34;1
"Unit";"Zergling";"Larva";35;1
"Unit";"Zergling";"Larva";36;1
"Unit";"Zergling";"Larva";37;1
"Unit";"Zergling";"Larva";38;1
"Unit";"Zergling";"Larva";39;1
"Unit";"Zergling";"Larva";40;1
"Unit";"Zergling";"Larva";41;1
"Unit";"Zergling";"Larva";42;1
"Unit";"Zergling";"Larva";43;1
"Unit";"Zergling";"Larva";44;1
"Unit";"Zergling";"Larva";45;1
"Unit";"Zergling";"Larva";46;1
"Unit";"Baneling";"Zergling";47;0
"Unit";"Baneling";"Zergling";47;0
"Unit";"Zergling";"Larva";47;1
"Unit";"Zergling";"Larva";48;1
"Unit";"Overlord";"Larva";49;0
"Unit";"Zergling";"Larva";51;1
"Unit";"Zergling";"Larva";52;1
"Unit";"Baneling";"Zergling";62;0
"Unit";"Baneling";"Zergling";62;0
"Unit";"Overlord";"Larva";67;0
"Unit";"Overlord";"Larva";67;0
"Unit";"Baneling";"Zergling";67;0
"Unit";"Baneling";"Zergling";67;0
"Unit";"Baneling";"Zergling";67;0
"Unit";"Queen";"Hatchery";67;2
"Unit";"Zergling";"Larva";74;1
"Unit";"Zergling";"Larva";75;1
"Unit";"Zergling";"Larva";76;1
"Unit";"Zergling";"Larva";77;1
"Unit";"Zergling";"Larva";78;1
"Unit";"Zergling";"Larva";79;1
"Unit";"Overlord";"Larva";80;0
"Unit";"Zergling";"Larva";80;1
"Unit";"Zergling";"Larva";81;1
"Unit";"Zergling";"Larva";82;1
"Unit";"Zergling";"Larva";83;1
"Unit";"Zergling";"Larva";84;1
"Unit";"Zergling";"Larva";85;1
"Unit";"Overlord";"Larva";86;0
"Building";"Hatchery";NA;86;0
"Unit";"Zergling";"Larva";86;1
"Unit";"Zergling";"Larva";87;1
"Unit";"Zergling";"Larva";88;1
"Unit";"Zergling";"Larva";89;1
"Unit";"Baneling";"Zergling";90;0
"Unit";"Baneling";"Zergling";90;0
"Building";"Extractor";NA;90;0
"Unit";"Baneling";"Zergling";90;0
"Unit";"Baneling";"Zergling";90;0
"Building";"RoachWarren";NA;90;0
"Building";"CreepTumorQueen";NA;90;0
"Unit";"Zergling";"Larva";90;1
"Unit";"Zergling";"Larva";91;1
"Unit";"Zergling";"Larva";92;1
"Unit";"Zergling";"Larva";93;1
"Unit";"Zergling";"Larva";94;1
"Unit";"Zergling";"Larva";95;1
"Unit";"Zergling";"Larva";96;1
"Unit";"Zergling";"Larva";97;1
"Unit";"Zergling";"Larva";98;1
"Unit";"Zergling";"Larva";99;1
"Unit";"Zergling";"Larva";100;1
"Unit";"Zergling";"Larva";101;1
"Unit";"Zergling";"Larva";102;1
"Unit";"Zergling";"Larva";103;1
"Unit";"Zergling";"Larva";104;1
"Unit";"Zergling";"Larva";105;1
"Unit";"Zergling";"Larva";106;1
"Unit";"Zergling";"Larva";107;1
"Unit";"Zergling";"Larva";108;1
"Unit";"Zergling";"Larva";109;1
"Unit";"Zergling";"Larva";110;1
"Unit";"Zergling";"Larva";111;1
"Building";"EvolutionChamber";NA;112;0
"Unit";"Overlord";"Larva";112;0
"Unit";"Roach";"Larva";112;2
"Unit";"Roach";"Larva";114;2
"Unit";"Roach";"Larva";116;2
"Unit";"Roach";"Larva";118;2
"Unit";"Roach";"Larva";120;2
"Unit";"Overlord";"Larva";122;0
"Unit";"Roach";"Larva";122;2
"Unit";"Roach";"Larva";124;2
"Building";"Extractor";NA;126;0
"Unit";"Roach";"Larva";126;2
"Unit";"Roach";"Larva";128;2
"Unit";"Roach";"Larva";132;2
"Unit";"Roach";"Larva";134;2
"Unit";"Roach";"Larva";136;2
"Unit";"Zergling";"Larva";138;1
"Unit";"Zergling";"Larva";139;1
"Unit";"Zergling";"Larva";140;1
"Unit";"Zergling";"Larva";141;1
"Unit";"Zergling";"Larva";142;1
"Unit";"Zergling";"Larva";143;1
"Unit";"Zergling";"Larva";144;1
"Unit";"Zergling";"Larva";145;1
"Unit";"Zergling";"Larva";146;1
"Unit";"Zergling";"Larva";147;1
"Unit";"Roach";"Larva";148;2
"Unit";"Roach";"Larva";150;2
"Unit";"Roach";"Larva";152;2
"Unit";"Zergling";"Larva";158;1
"Unit";"Zergling";"Larva";159;1
"Unit";"Zergling";"Larva";160;1
"Unit";"Zergling";"Larva";161;1
"Unit";"Zergling";"Larva";162;1
"Unit";"Zergling";"Larva";163;1
"Unit";"Zergling";"Larva";164;1
"Unit";"Zergling";"Larva";165;1
"Unit";"Zergling";"Larva";166;1
"Unit";"Zergling";"Larva";167;1
"Unit";"Zergling";"Larva";168;1
"Unit";"Zergling";"Larva";169;1
"Unit";"Overlord";"Larva";173;0
"Unit";"Overlord";"Larva";173;0
"Unit";"Roach";"Larva";175;2
"Unit";"Roach";"Larva";177;2
"Unit";"Roach";"Larva";179;2
"Unit";"Roach";"Larva";181;2
"Unit";"Roach";"Larva";183;2
"Unit";"Roach";"Larva";185;2
"Unit";"Overlord";"Larva";187;0
"Unit";"Overlord";"Larva";187;0
"Unit";"Roach";"Larva";187;2
"Building";"Extractor";NA;191;0
"Upgrade";"GlialReconstitution";"RoachWarren";193;0
"Unit";"Roach";"Larva";195;2
"Unit";"Roach";"Larva";197;2
"Unit";"Zergling";"Larva";199;1
"Unit";"Zergling";"Larva";200;1
"Unit";"Zergling";"Larva";201;1
"Unit";"Zergling";"Larva";202;1
"Unit";"Zergling";"Larva";203;1
"Unit";"Zergling";"Larva";204;1
"Unit";"Zergling";"Larva";205;1
"Unit";"Zergling";"Larva";206;1
"Unit";"Zergling";"Larva";207;1
"Unit";"Zergling";"Larva";208;1
"Unit";"Zergling";"Larva";209;1
"Unit";"Zergling";"Larva";210;1
"Unit";"Zergling";"Larva";211;1
"Unit";"Zergling";"Larva";212;1
"Unit";"Zergling";"Larva";213;1
"Unit";"Zergling";"Larva";214;1
"Unit";"Roach";"Larva";215;2
"Unit";"Roach";"Larva";217;2
"Unit";"Overlord";"Larva";221;0
"Unit";"Overlord";"Larva";221;0
"Unit";"Roach";"Larva";221;2
"Unit";"Roach";"Larva";223;2
"Unit";"Roach";"Larva";225;2
"Unit";"Roach";"Larva";227;2
"Unit";"Roach";"Larva";229;2
"Unit";"Roach";"Larva";231;2
"Unit";"Roach";"Larva";233;2
"Unit";"Roach";"Larva";235;2
"Unit";"Roach";"Larva";237;2
"Unit";"Roach";"Larva";239;2
"Unit";"Roach";"Larva";241;2
"Unit";"Roach";"Larva";243;2
"Unit";"Roach";"Larva";245;2
"Unit";"Roach";"Larva";247;2
"Unit";"Roach";"Larva";249;2
"Unit";"Roach";"Larva";251;2
"Unit";"Queen";"Hatchery";253;2
"Unit";"Roach";"Larva";255;2
"Unit";"Roach";"Larva";257;2
"Unit";"Roach";"Larva";260;2
"Unit";"Roach";"Larva";262;2
"Unit";"Roach";"Larva";264;2
"Unit";"Roach";"Larva";266;2
"Unit";"Roach";"Larva";268;2
"Unit";"Roach";"Larva";270;2
"Unit";"Roach";"Larva";272;2
"Unit";"Baneling";"Zergling";275;0
"Unit";"Baneling";"Zergling";275;0
"Unit";"Roach";"Larva";275;2
"Unit";"Overlord";"Larva";277;0
"Unit";"Overlord";"Larva";277;0
"Unit";"Overlord";"Larva";277;0
"Upgrade";"SprayZerg";NA;277;0
"Upgrade";"SprayZerg";NA;277;0
"Upgrade";"zerglingmovementspeed";NA;277;0
"Upgrade";"SprayZerg";NA;277;0
"Upgrade";"SprayZerg";NA;277;0
"Upgrade";"ZergMissileWeaponsLevel1";NA;277;0
"Upgrade";"SprayZerg";NA;277;0
