"type";"unit_name";"on_building";"total_supply";"supply"
"Unit";"Overlord";"Larva";12;0
"Building";"Extractor";NA;18;0
"Unit";"Overlord";"Larva";21;0
"Building";"SpawningPool";NA;19;0
"Building";"Hatchery";NA;17;0
"Unit";"Queen";"Hatchery";22;2
"Unit";"Queen";"Hatchery";22;2
"Unit";"Zergling";"Larva";33;1
"Unit";"Zergling";"Larva";33;1
"Unit";"Overlord";"Larva";35;0
"Building";"BanelingNest";NA;33;0
"Unit";"Overlord";"Larva";38;0
"Unit";"Zergling";"Larva";38;1
"Unit";"Zergling";"Larva";38;1
"Unit";"Zergling";"Larva";38;1
"Unit";"Zergling";"Larva";38;1
"Unit";"Overlord";"Larva";42;0
"Building";"Hatchery";NA;33;0
"Unit";"Zergling";"Larva";44;1
"Unit";"Zergling";"Larva";44;1
"Unit";"Zergling";"Larva";44;1
"Unit";"Zergling";"Larva";44;1
"Building";"EvolutionChamber";NA;52;0
"Building";"RoachWarren";NA;48;0
"Building";"Extractor";NA;59;0
"Building";"Extractor";NA;59;0
"Unit";"Overlord";"Larva";59;0
"Unit";"Roach";"Larva";63;2
"Unit";"Roach";"Larva";63;2
"Unit";"Roach";"Larva";63;2
"Unit";"Roach";"Larva";63;2
"Unit";"Roach";"Larva";63;2
"Unit";"Roach";"Larva";63;2
"Unit";"Baneling";"Zergling";63;0
"Unit";"Baneling";"Zergling";63;0
"Unit";"Roach";"Larva";63;2
"Unit";"Roach";"Larva";63;2
"Unit";"Queen";"Hatchery";59;2
"Unit";"Zergling";"Larva";63;1
"Unit";"Zergling";"Larva";63;1
"Unit";"Zergling";"Larva";63;1
"Unit";"Zergling";"Larva";63;1
"Unit";"Zergling";"Larva";63;1
"Unit";"Zergling";"Larva";63;1
"Unit";"Zergling";"Larva";63;1
"Unit";"Zergling";"Larva";63;1
"Unit";"Zergling";"Larva";63;1
"Unit";"Zergling";"Larva";63;1
"Unit";"Roach";"Larva";63;2
"Unit";"Zergling";"Larva";73;1
"Unit";"Zergling";"Larva";73;1
"Unit";"Overlord";"Larva";81;0
"Unit";"Overlord";"Larva";81;0
"Unit";"Overlord";"Larva";95;0
"Unit";"Overlord";"Larva";96;0
"Unit";"Roach";"Larva";107;2
"Unit";"Roach";"Larva";107;2
"Unit";"Roach";"Larva";107;2
"Unit";"Roach";"Larva";107;2
"Unit";"Roach";"Larva";107;2
"Unit";"Roach";"Larva";107;2
"Unit";"Roach";"Larva";107;2
"Building";"Extractor";NA;107;0
"Unit";"Roach";"Larva";107;2
"Unit";"Roach";"Larva";107;2
"Upgrade";"GlialReconstitution";"RoachWarren";96;0
"Unit";"Roach";"Larva";121;2
"Unit";"Roach";"Larva";121;2
"Unit";"Roach";"Larva";121;2
"Unit";"Overlord";"Larva";121;0
"Unit";"Overlord";"Larva";123;0
"Unit";"Overlord";"Larva";128;0
"Unit";"Overlord";"Larva";131;0
"Unit";"Overlord";"Larva";137;0
"Upgrade";"ZergMissileWeaponsLevel1";"EvolutionChamber";96;0
"Unit";"Roach";"Larva";137;2
"Unit";"Roach";"Larva";137;2
"Unit";"Roach";"Larva";137;2
"Unit";"Roach";"Larva";137;2
"Unit";"Roach";"Larva";137;2
"Unit";"Roach";"Larva";137;2
"Unit";"Roach";"Larva";137;2
"Unit";"Roach";"Larva";137;2
"Unit";"Roach";"Larva";137;2
"Unit";"Roach";"Larva";137;2
"Unit";"Roach";"Larva";137;2
"Unit";"Roach";"Larva";137;2
"Unit";"Roach";"Larva";137;2
"Unit";"Roach";"Larva";137;2
"Unit";"Roach";"Larva";157;2
"Unit";"Roach";"Larva";157;2
"Unit";"Roach";"Larva";157;2
"Unit";"Overlord";"Larva";157;0
"Unit";"Roach";"Larva";171;2
"Unit";"Overlord";"Larva";171;0
"Unit";"Roach";"Larva";171;2
"Unit";"Roach";"Larva";171;2
"Unit";"Roach";"Larva";171;2
"Unit";"Roach";"Larva";171;2
"Unit";"Overlord";"Larva";171;0
"Unit";"Overlord";"Larva";171;0
"Unit";"Overlord";"Larva";171;0
"Unit";"Roach";"Larva";175;2
"Unit";"Roach";"Larva";175;2
"Unit";"Overlord";"Larva";175;0
"Unit";"Roach";"Larva";177;2
"Unit";"Roach";"Larva";185;2
"Unit";"Roach";"Larva";185;2
"Unit";"Roach";"Larva";185;2
"Unit";"Roach";"Larva";185;2
"Unit";"Roach";"Larva";185;2
"Unit";"Roach";"Larva";185;2
"Unit";"Roach";"Larva";185;2
"Unit";"Roach";"Larva";185;2
"Unit";"Roach";"Larva";185;2
"Unit";"Roach";"Larva";185;2
"Unit";"Roach";"Larva";185;2
"Unit";"Roach";"Larva";185;2
"Unit";"Roach";"Larva";189;2
"Unit";"Roach";"Larva";189;2
"Unit";"Roach";"Larva";215;2
"Unit";"Roach";"Larva";215;2
"Unit";"Roach";"Larva";215;2
"Unit";"Roach";"Larva";215;2
"Unit";"Overlord";"Larva";215;0
"Building";"Hatchery";NA;175;0
"Unit";"Roach";"Larva";219;2
"Unit";"Roach";"Larva";219;2
"Unit";"Roach";"Larva";219;2
"Unit";"Roach";"Larva";219;2
"Unit";"Roach";"Larva";219;2
"Unit";"Roach";"Larva";219;2
"Unit";"Roach";"Larva";227;2
"Unit";"Roach";"Larva";227;2
"Unit";"Roach";"Larva";227;2
"Unit";"Roach";"Larva";227;2
"Unit";"Roach";"Larva";227;2
"Unit";"Roach";"Larva";227;2
"Unit";"Roach";"Larva";227;2
"Upgrade";"ZergMissileWeaponsLevel2";"EvolutionChamber";174;0
"Unit";"Roach";"Larva";253;2
"Unit";"Roach";"Larva";253;2
"Unit";"Roach";"Larva";253;2
"Unit";"Roach";"Larva";253;2
"Unit";"Roach";"Larva";253;2
"Unit";"Roach";"Larva";253;2
"Unit";"Roach";"Larva";253;2
"Unit";"Roach";"Larva";253;2
"Unit";"Roach";"Larva";253;2
"Unit";"Roach";"Larva";253;2
"Unit";"Roach";"Larva";253;2
"Unit";"Roach";"Larva";253;2
"Unit";"Roach";"Larva";253;2
"Unit";"Roach";"Larva";279;2
"Unit";"Roach";"Larva";279;2
"Unit";"Roach";"Larva";279;2
"Unit";"Roach";"Larva";279;2
"Unit";"Roach";"Larva";279;2
"Unit";"Roach";"Larva";279;2
"Unit";"Roach";"Larva";279;2
"Unit";"Roach";"Larva";279;2
"Unit";"Roach";"Larva";279;2
"Unit";"Roach";"Larva";279;2
"Unit";"Roach";"Larva";299;2
"Unit";"Roach";"Larva";299;2
"Unit";"Roach";"Larva";299;2
"Unit";"Roach";"Larva";299;2
"Unit";"Roach";"Larva";299;2
"Unit";"Roach";"Larva";299;2
"Unit";"Roach";"Larva";299;2
"Unit";"Roach";"Larva";299;2
"Unit";"Overlord";"Larva";299;0
"Unit";"Roach";"Larva";299;2
"Unit";"Roach";"Larva";299;2
"Unit";"Roach";"Larva";299;2
"Unit";"Roach";"Larva";299;2
"Unit";"Roach";"Larva";299;2
"Unit";"Roach";"Larva";299;2
"Unit";"Roach";"Larva";299;2
"Unit";"Roach";"Larva";315;2
"Unit";"Roach";"Larva";315;2
"Unit";"Roach";"Larva";315;2
"Unit";"Roach";"Larva";315;2
"Unit";"Roach";"Larva";329;2
"Unit";"Roach";"Larva";329;2
"Unit";"Roach";"Larva";329;2
"Unit";"Queen";"Hatchery";315;2
"Unit";"Roach";"Larva";340;2
"Unit";"Roach";"Larva";340;2
"Unit";"Roach";"Larva";340;2
"Unit";"Roach";"Larva";340;2
"Unit";"Roach";"Larva";340;2
"Unit";"Roach";"Larva";340;2
"Unit";"Roach";"Larva";340;2
"Unit";"Roach";"Larva";340;2
"Unit";"Roach";"Larva";340;2
"Unit";"Overlord";"Larva";342;0
"Building";"Extractor";NA;346;0
"Building";"Extractor";NA;348;0
"Unit";"Roach";"Larva";348;2
"Unit";"Roach";"Larva";348;2
"Unit";"Roach";"Larva";348;2
"Unit";"Roach";"Larva";348;2
"Unit";"Roach";"Larva";348;2
"Unit";"Roach";"Larva";348;2
"Unit";"Roach";"Larva";348;2
"Unit";"Roach";"Larva";348;2
"Unit";"Overlord";"Larva";366;0
"Unit";"Roach";"Larva";366;2
"Unit";"Roach";"Larva";366;2
"Unit";"Roach";"Larva";366;2
"Unit";"Roach";"Larva";366;2
"Unit";"Roach";"Larva";366;2
"Unit";"Roach";"Larva";366;2
"Building";"Hatchery";NA;332;0
"Unit";"Roach";"Larva";382;2
"Unit";"Roach";"Larva";382;2
"Unit";"Roach";"Larva";382;2
"Unit";"Roach";"Larva";382;2
"Unit";"Roach";"Larva";382;2
"Unit";"Roach";"Larva";382;2
"Unit";"Roach";"Larva";382;2
"Unit";"Roach";"Larva";382;2
"Unit";"Roach";"Larva";382;2
"Unit";"Roach";"Larva";382;2
"Unit";"Roach";"Larva";384;2
"Unit";"Roach";"Larva";416;2
"Unit";"Roach";"Larva";416;2
"Unit";"Roach";"Larva";416;2
"Unit";"Roach";"Larva";416;2
"Unit";"Roach";"Larva";416;2
"Unit";"Roach";"Larva";416;2
"Unit";"Roach";"Larva";416;2
"Unit";"Roach";"Larva";416;2
"Unit";"Roach";"Larva";416;2
"Unit";"Roach";"Larva";416;2
"Unit";"Roach";"Larva";416;2
"Unit";"Roach";"Larva";416;2
"Unit";"Roach";"Larva";440;2
"Unit";"Roach";"Larva";440;2
"Unit";"Roach";"Larva";440;2
"Unit";"Roach";"Larva";440;2
"Unit";"Roach";"Larva";440;2
"Unit";"Roach";"Larva";440;2
"Unit";"Roach";"Larva";440;2
"Unit";"Roach";"Larva";440;2
"Unit";"Roach";"Larva";440;2
"Unit";"Roach";"Larva";440;2
