"type";"unit_name";"on_building";"total_supply";"supply"
"Unit";"Overlord";"Larva";13;0
"Building";"Extractor";NA;17;0
"Unit";"Overlord";"Larva";21;0
"Building";"Hatchery";NA;17;0
"Building";"SpawningPool";NA;19;0
"Unit";"Zergling";"Larva";22;1
"Unit";"Zergling";"Larva";22;1
"Unit";"Zergling";"Larva";22;1
"Unit";"Zergling";"Larva";22;1
"Unit";"Zergling";"Larva";22;1
"Unit";"Zergling";"Larva";22;1
"Unit";"Queen";"Hatchery";22;2
"Unit";"Queen";"Hatchery";22;2
"Building";"BanelingNest";NA;31;0
"Building";"SpineCrawler";NA;37;0
"Unit";"Overlord";"Larva";40;0
"Building";"Extractor";NA;42;0
"Building";"Extractor";NA;42;0
"Building";"Extractor";NA;44;0
"Unit";"Overlord";"Larva";49;0
"Unit";"Overlord";"Larva";49;0
"Unit";"Zergling";"Larva";53;1
"Unit";"Zergling";"Larva";53;1
"Unit";"Zergling";"Larva";53;1
"Unit";"Zergling";"Larva";53;1
"Unit";"Baneling";"Zergling";57;0
"Unit";"Baneling";"Zergling";57;0
"Unit";"Baneling";"Zergling";57;0
"Unit";"Baneling";"Zergling";59;0
"Unit";"Zergling";"Larva";62;1
"Unit";"Zergling";"Larva";62;1
"Unit";"Zergling";"Larva";62;1
"Unit";"Zergling";"Larva";62;1
"Unit";"Zergling";"Larva";62;1
"Unit";"Zergling";"Larva";62;1
"Unit";"Zergling";"Larva";62;1
"Unit";"Zergling";"Larva";62;1
"Unit";"Zergling";"Larva";62;1
"Unit";"Zergling";"Larva";62;1
"Unit";"Zergling";"Larva";62;1
"Unit";"Zergling";"Larva";62;1
"Unit";"Zergling";"Larva";62;1
"Unit";"Zergling";"Larva";62;1
"Unit";"Baneling";"Zergling";64;0
"Unit";"Baneling";"Zergling";64;0
"Unit";"Baneling";"Zergling";64;0
"Building";"Spire";NA;57;0
"Unit";"Overlord";"Larva";79;0
"Unit";"Overlord";"Larva";79;0
"Unit";"Overlord";"Larva";79;0
"Unit";"Overlord";"Larva";79;0
"Unit";"Mutalisk";"Larva";83;2
"Unit";"Mutalisk";"Larva";83;2
"Unit";"Mutalisk";"Larva";83;2
"Unit";"Mutalisk";"Larva";84;2
"Unit";"Mutalisk";"Larva";84;2
"Unit";"Mutalisk";"Larva";92;2
"Unit";"Mutalisk";"Larva";92;2
"Unit";"Mutalisk";"Larva";92;2
"Unit";"Mutalisk";"Larva";92;2
"Unit";"Mutalisk";"Larva";94;2
"Building";"Hatchery";NA;83;0
"Building";"EvolutionChamber";NA;96;0
"Building";"EvolutionChamber";NA;96;0
"Unit";"Overlord";"Larva";112;0
"Building";"RoachWarren";NA;96;0
"Unit";"Queen";"Hatchery";112;2
"Unit";"Queen";"Hatchery";112;2
"Unit";"Overlord";"Larva";119;0
"Unit";"Overlord";"Larva";119;0
"Unit";"Overlord";"Larva";119;0
"Unit";"Overlord";"Larva";120;0
"Unit";"Roach";"Larva";129;2
"Unit";"Roach";"Larva";129;2
"Unit";"Roach";"Larva";129;2
"Building";"Hatchery";NA;112;0
"Building";"SporeCrawler";NA;135;0
"Building";"HydraliskDen";NA;135;0
"Upgrade";"GlialReconstitution";"RoachWarren";129;0
"Building";"SporeCrawler";NA;135;0
"Building";"SporeCrawler";NA;136;0
"Unit";"Queen";"Hatchery";135;2
"Unit";"Queen";"Hatchery";135;2
"Unit";"Queen";"Hatchery";135;2
"Unit";"Hydralisk";"Larva";136;2
"Unit";"Hydralisk";"Larva";136;2
"Unit";"Hydralisk";"Larva";136;2
"Unit";"Hydralisk";"Larva";136;2
"Upgrade";"ZergMissileWeaponsLevel1";"EvolutionChamber";129;0
"Unit";"Hydralisk";"Larva";136;2
"Unit";"Hydralisk";"Larva";136;2
"Unit";"Hydralisk";"Larva";136;2
"Unit";"Hydralisk";"Larva";136;2
"Unit";"Hydralisk";"Larva";136;2
"Unit";"Hydralisk";"Larva";136;2
"Unit";"Hydralisk";"Larva";136;2
"Unit";"Hydralisk";"Larva";136;2
"Unit";"Hydralisk";"Larva";136;2
"Building";"SporeCrawler";NA;136;0
"Unit";"Overlord";"Larva";136;0
"Unit";"Overlord";"Larva";136;0
"Unit";"Overlord";"Larva";136;0
"Building";"SporeCrawler";NA;136;0
"Building";"Extractor";NA;138;0
"Building";"Extractor";NA;142;0
"Unit";"Hydralisk";"Larva";168;2
"Unit";"Hydralisk";"Larva";168;2
"Unit";"Hydralisk";"Larva";168;2
"Unit";"Hydralisk";"Larva";168;2
"Unit";"Hydralisk";"Larva";168;2
"Unit";"Hydralisk";"Larva";168;2
"Unit";"Hydralisk";"Larva";168;2
"Building";"SporeCrawler";NA;168;0
"Building";"SporeCrawler";NA;168;0
"Upgrade";"EvolveGroovedSpines";"HydraliskDen";168;0
"Building";"InfestationPit";NA;168;0
"Upgrade";"ZergGroundArmorsLevel1";"EvolutionChamber";142;0
"Unit";"Hydralisk";"Larva";195;2
"Unit";"Hydralisk";"Larva";195;2
"Unit";"Hydralisk";"Larva";195;2
"Unit";"Hydralisk";"Larva";195;2
"Unit";"Hydralisk";"Larva";195;2
"Unit";"Hydralisk";"Larva";195;2
"Unit";"Hydralisk";"Larva";195;2
"Unit";"Hydralisk";"Larva";195;2
"Unit";"Hydralisk";"Larva";195;2
"Building";"SpawningPool";NA;194;0
"Building";"LurkerDenMP";NA;168;0
"Unit";"Hydralisk";"Larva";195;2
"Unit";"Hydralisk";"Larva";195;2
"Unit";"Hydralisk";"Larva";195;2
"Unit";"Hydralisk";"Larva";195;2
"Unit";"Hydralisk";"Larva";213;2
"Unit";"Hydralisk";"Larva";213;2
"Unit";"Hydralisk";"Larva";213;2
"Unit";"Hydralisk";"Larva";213;2
"Unit";"Hydralisk";"Larva";213;2
"Unit";"Hydralisk";"Larva";213;2
"Upgrade";"EvolveMuscularAugments";"HydraliskDen";195;0
"Unit";"Overlord";"Larva";221;0
"Unit";"Overlord";"Larva";221;0
"Building";"Extractor";NA;235;0
"Unit";"Queen";"Hatchery";235;2
"Unit";"Hydralisk";"Larva";235;2
"Unit";"Hydralisk";"Larva";235;2
"Unit";"Hydralisk";"Larva";235;2
"Unit";"Hydralisk";"Larva";235;2
"Unit";"Hydralisk";"Larva";235;2
"Unit";"Hydralisk";"Larva";235;2
"Unit";"Hydralisk";"Larva";235;2
"Unit";"Overlord";"Larva";235;0
"Unit";"Overlord";"Larva";235;0
"Unit";"Overlord";"Larva";235;0
"Unit";"Overlord";"Larva";235;0
"Unit";"Viper";"Larva";235;3
"Unit";"Roach";"Larva";254;2
"Unit";"Viper";"Larva";251;3
"Unit";"Viper";"Larva";251;3
"Unit";"Hydralisk";"Larva";251;2
"Unit";"Viper";"Larva";251;3
"Unit";"Hydralisk";"Larva";254;2
"Unit";"Hydralisk";"Larva";254;2
"Unit";"Hydralisk";"Larva";254;2
"Unit";"Hydralisk";"Larva";254;2
"Unit";"Hydralisk";"Larva";254;2
"Building";"Hatchery";NA;235;0
"Unit";"Roach";"Larva";292;2
"Unit";"Roach";"Larva";292;2
"Unit";"Roach";"Larva";292;2
"Building";"Extractor";NA;296;0
"Unit";"Overlord";"Larva";298;0
"Unit";"Overlord";"Larva";298;0
"Unit";"Overlord";"Larva";298;0
"Unit";"Overlord";"Larva";298;0
"Building";"Extractor";NA;298;0
"Building";"Extractor";NA;298;0
"Unit";"Overlord";"Larva";306;0
"Unit";"Overlord";"Larva";306;0
"Building";"SporeCrawler";NA;306;0
"Building";"SporeCrawler";NA;306;0
"Building";"SporeCrawler";NA;306;0
"Building";"SporeCrawler";NA;306;0
"Building";"SporeCrawler";NA;306;0
"Unit";"Queen";"Hatchery";306;2
"Unit";"Queen";"Hatchery";306;2
"Unit";"Queen";"Hatchery";306;2
"Unit";"Hydralisk";"Larva";306;2
"Unit";"Hydralisk";"Larva";306;2
"Unit";"Hydralisk";"Larva";306;2
"Unit";"Hydralisk";"Larva";306;2
"Unit";"Hydralisk";"Larva";306;2
"Unit";"Hydralisk";"Larva";306;2
"Unit";"Hydralisk";"Larva";306;2
"Unit";"Hydralisk";"Larva";306;2
"Unit";"Hydralisk";"Larva";306;2
"Unit";"Hydralisk";"Larva";306;2
"Unit";"Hydralisk";"Larva";306;2
"Unit";"Hydralisk";"Larva";306;2
"Unit";"Hydralisk";"Larva";306;2
"Unit";"Hydralisk";"Larva";306;2
"Unit";"Hydralisk";"Larva";340;2
"Unit";"Hydralisk";"Larva";340;2
"Unit";"Hydralisk";"Larva";340;2
"Unit";"Hydralisk";"Larva";340;2
"Unit";"Hydralisk";"Larva";340;2
"Unit";"Hydralisk";"Larva";340;2
"Upgrade";"ZergMissileWeaponsLevel2";"EvolutionChamber";306;0
"Upgrade";"ZergGroundArmorsLevel2";"EvolutionChamber";306;0
"Unit";"Hydralisk";"Larva";352;2
"Unit";"Hydralisk";"Larva";352;2
"Unit";"Hydralisk";"Larva";352;2
"Unit";"Hydralisk";"Larva";352;2
"Unit";"Hydralisk";"Larva";352;2
"Unit";"Hydralisk";"Larva";352;2
"Unit";"Roach";"Larva";364;2
"Unit";"Roach";"Larva";364;2
"Building";"Hatchery";NA;364;0
"Unit";"Hydralisk";"Larva";368;2
"Unit";"Hydralisk";"Larva";368;2
"Unit";"Hydralisk";"Larva";368;2
"Unit";"Hydralisk";"Larva";368;2
"Unit";"Hydralisk";"Larva";368;2
"Building";"Extractor";NA;378;0
"Unit";"Hydralisk";"Larva";378;2
"Unit";"Hydralisk";"Larva";378;2
"Unit";"Hydralisk";"Larva";378;2
"Unit";"Hydralisk";"Larva";378;2
"Unit";"Hydralisk";"Larva";378;2
"Unit";"Hydralisk";"Larva";378;2
"Unit";"Hydralisk";"Larva";378;2
"Unit";"Hydralisk";"Larva";378;2
"Unit";"Hydralisk";"Larva";378;2
"Unit";"Hydralisk";"Larva";378;2
"Unit";"Hydralisk";"Larva";378;2
"Unit";"Hydralisk";"Larva";378;2
"Unit";"Hydralisk";"Larva";378;2
"Building";"Extractor";NA;394;0
"Unit";"Viper";"Larva";394;3
"Unit";"Viper";"Larva";394;3
"Building";"Extractor";NA;404;0
"Unit";"Viper";"Larva";410;3
"Unit";"Overlord";"Larva";410;0
"Unit";"Overlord";"Larva";410;0
"Building";"Hatchery";NA;394;0
"Unit";"Hydralisk";"Larva";419;2
"Unit";"Hydralisk";"Larva";419;2
"Unit";"Hydralisk";"Larva";419;2
"Unit";"Hydralisk";"Larva";419;2
"Unit";"Hydralisk";"Larva";419;2
"Unit";"Hydralisk";"Larva";419;2
"Unit";"Hydralisk";"Larva";419;2
"Unit";"Hydralisk";"Larva";419;2
"Unit";"Hydralisk";"Larva";419;2
"Building";"Hatchery";NA;416;0
"Unit";"Overlord";"Larva";437;0
"Unit";"Overlord";"Larva";437;0
"Unit";"Viper";"Larva";437;3
"Unit";"Viper";"Larva";437;3
"Unit";"Viper";"Larva";437;3
"Unit";"Viper";"Larva";437;3
"Building";"EvolutionChamber";NA;439;0
"Building";"EvolutionChamber";NA;439;0
"Building";"EvolutionChamber";NA;439;0
"Building";"EvolutionChamber";NA;439;0
"Building";"Extractor";NA;461;0
"Building";"Extractor";NA;461;0
"Unit";"Hydralisk";"Larva";467;2
"Building";"Hatchery";NA;461;0
"Upgrade";"Burrow";"Hatchery";467;0
"Upgrade";"TunnelingClaws";"RoachWarren";467;0
