"type";"unit_name";"on_building";"total_supply";"supply"
"Unit";"Overlord";"Larva";13;0
"Building";"Extractor";NA;17;0
"Building";"SpawningPool";NA;19;0
"Building";"Hatchery";NA;17;0
"Unit";"Overlord";"Larva";22;0
"Unit";"Zergling";"Larva";22;1
"Unit";"Zergling";"Larva";22;1
"Unit";"Zergling";"Larva";22;1
"Unit";"Zergling";"Larva";22;1
"Unit";"Queen";"Hatchery";22;2
"Unit";"Queen";"Hatchery";22;2
"Unit";"Overlord";"Larva";36;0
"Unit";"Overlord";"Larva";38;0
"Building";"BanelingNest";NA;35;0
"Unit";"Overlord";"Larva";38;0
"Unit";"Zergling";"Larva";42;1
"Unit";"Zergling";"Larva";42;1
"Unit";"Zergling";"Larva";42;1
"Unit";"Zergling";"Larva";42;1
"Unit";"Zergling";"Larva";42;1
"Unit";"Zergling";"Larva";42;1
"Building";"Hatchery";NA;33;0
"Unit";"Zergling";"Larva";42;1
"Unit";"Zergling";"Larva";42;1
"Unit";"Zergling";"Larva";42;1
"Unit";"Zergling";"Larva";42;1
"Unit";"Zergling";"Larva";42;1
"Unit";"Zergling";"Larva";42;1
"Unit";"Baneling";"Zergling";42;0
"Unit";"Baneling";"Zergling";42;0
"Unit";"Zergling";"Larva";42;1
"Unit";"Zergling";"Larva";42;1
"Unit";"Baneling";"Zergling";48;0
"Unit";"Baneling";"Zergling";48;0
"Unit";"Zergling";"Larva";42;1
"Unit";"Zergling";"Larva";42;1
"Unit";"Zergling";"Larva";42;1
"Unit";"Zergling";"Larva";42;1
"Unit";"Zergling";"Larva";42;1
"Unit";"Zergling";"Larva";42;1
"Unit";"Baneling";"Zergling";56;0
"Unit";"Baneling";"Zergling";56;0
"Unit";"Zergling";"Larva";54;1
"Unit";"Zergling";"Larva";54;1
"Unit";"Queen";"Hatchery";54;2
"Unit";"Zergling";"Larva";64;1
"Unit";"Zergling";"Larva";64;1
"Unit";"Zergling";"Larva";64;1
"Unit";"Zergling";"Larva";64;1
"Unit";"Zergling";"Larva";64;1
"Unit";"Zergling";"Larva";64;1
"Unit";"Zergling";"Larva";64;1
"Unit";"Zergling";"Larva";64;1
"Unit";"Zergling";"Larva";64;1
"Unit";"Zergling";"Larva";64;1
"Unit";"Zergling";"Larva";64;1
"Unit";"Zergling";"Larva";64;1
"Unit";"Queen";"Hatchery";62;2
"Building";"Extractor";NA;66;0
"Building";"Extractor";NA;66;0
"Building";"EvolutionChamber";NA;68;0
"Building";"CreepTumorQueen";NA;85;0
"Unit";"Baneling";"Zergling";101;0
"Unit";"Baneling";"Zergling";102;0
"Building";"CreepTumor";NA;103;0
"Building";"CreepTumorQueen";NA;105;0
"Unit";"Overlord";"Larva";107;0
"Unit";"Overlord";"Larva";107;0
"Unit";"Overlord";"Larva";107;0
"Building";"RoachWarren";NA;101;0
"Building";"Extractor";NA;107;0
"Building";"Extractor";NA;107;0
"Unit";"Overlord";"Larva";114;0
"Unit";"Overlord";"Larva";114;0
"Building";"CreepTumor";NA;126;0
"Unit";"Roach";"Larva";114;2
"Unit";"Roach";"Larva";126;2
"Unit";"Roach";"Larva";126;2
"Building";"CreepTumor";NA;126;0
"Building";"CreepTumorQueen";NA;126;0
"Unit";"Roach";"Larva";126;2
"Building";"Extractor";NA;126;0
"Unit";"Roach";"Larva";128;2
"Unit";"Roach";"Larva";128;2
"Unit";"Roach";"Larva";128;2
"Unit";"Roach";"Larva";128;2
"Unit";"Roach";"Larva";128;2
"Unit";"Roach";"Larva";128;2
"Unit";"Roach";"Larva";128;2
"Unit";"Roach";"Larva";132;2
"Upgrade";"ZergMissileWeaponsLevel1";"EvolutionChamber";109;0
"Unit";"Roach";"Larva";134;2
"Unit";"Roach";"Larva";134;2
"Unit";"Overlord";"Larva";148;0
"Unit";"Overlord";"Larva";148;0
"Unit";"Overlord";"Larva";148;0
"Unit";"Overlord";"Larva";148;0
"Building";"CreepTumor";NA;150;0
"Unit";"Overlord";"Larva";148;0
"Upgrade";"GlialReconstitution";"RoachWarren";126;0
"Building";"CreepTumor";NA;154;0
"Building";"CreepTumor";NA;154;0
"Unit";"Overlord";"Larva";154;0
"Unit";"Overlord";"Larva";154;0
"Unit";"Overlord";"Larva";154;0
"Building";"HydraliskDen";NA;154;0
"Building";"Hatchery";NA;126;0
"Building";"CreepTumor";NA;154;0
"Unit";"Roach";"Larva";154;2
"Unit";"Roach";"Larva";154;2
"Unit";"Roach";"Larva";154;2
"Unit";"Roach";"Larva";154;2
"Unit";"Roach";"Larva";154;2
"Unit";"Roach";"Larva";154;2
"Unit";"Roach";"Larva";154;2
"Unit";"Roach";"Larva";154;2
"Unit";"Roach";"Larva";154;2
"Unit";"Roach";"Larva";154;2
"Unit";"Roach";"Larva";154;2
"Unit";"Roach";"Larva";154;2
"Unit";"Roach";"Larva";154;2
"Unit";"Roach";"Larva";154;2
"Unit";"Roach";"Larva";154;2
"Unit";"Roach";"Larva";154;2
"Unit";"Roach";"Larva";154;2
"Unit";"Roach";"Larva";154;2
"Unit";"Roach";"Larva";154;2
"Unit";"Roach";"Larva";154;2
"Building";"CreepTumor";NA;172;0
"Building";"CreepTumor";NA;172;0
"Building";"CreepTumor";NA;204;0
"Unit";"Overlord";"Larva";194;0
"Unit";"Roach";"Larva";194;2
"Unit";"Overlord";"Larva";194;0
"Unit";"Overlord";"Larva";194;0
"Unit";"Overlord";"Larva";194;0
"Unit";"Roach";"Larva";194;2
"Unit";"Overlord";"Larva";194;0
"Building";"Extractor";NA;204;0
"Building";"Extractor";NA;204;0
"Unit";"Roach";"Larva";208;2
"Unit";"Roach";"Larva";208;2
"Unit";"Roach";"Larva";208;2
"Unit";"Roach";"Larva";208;2
"Unit";"Roach";"Larva";208;2
"Unit";"Roach";"Larva";208;2
"Unit";"Roach";"Larva";208;2
"Unit";"Roach";"Larva";208;2
"Unit";"Roach";"Larva";208;2
"Unit";"Roach";"Larva";208;2
"Unit";"Roach";"Larva";208;2
"Unit";"Roach";"Larva";208;2
"Unit";"Roach";"Larva";208;2
"Unit";"Roach";"Larva";234;2
"Building";"LurkerDenMP";NA;172;0
"Upgrade";"ZergMissileWeaponsLevel2";"EvolutionChamber";154;0
"Unit";"Roach";"Larva";234;2
"Unit";"Roach";"Larva";234;2
"Unit";"Roach";"Larva";234;2
"Unit";"Roach";"Larva";234;2
"Unit";"Roach";"Larva";234;2
"Unit";"Roach";"Larva";234;2
"Unit";"Roach";"Larva";234;2
"Unit";"Roach";"Larva";234;2
"Unit";"Roach";"Larva";234;2
"Unit";"Roach";"Larva";234;2
"Building";"CreepTumor";NA;260;0
"Building";"CreepTumor";NA;260;0
"Unit";"Hydralisk";"Larva";260;2
"Unit";"Hydralisk";"Larva";260;2
"Unit";"Hydralisk";"Larva";260;2
"Unit";"Hydralisk";"Larva";260;2
"Building";"InfestationPit";NA;234;0
"Building";"EvolutionChamber";NA;260;0
"Building";"CreepTumor";NA;268;0
"Unit";"Hydralisk";"Larva";260;2
"Unit";"Hydralisk";"Larva";260;2
"Unit";"Hydralisk";"Larva";260;2
"Unit";"Hydralisk";"Larva";260;2
"Upgrade";"EvolveGroovedSpines";"HydraliskDen";260;0
"Unit";"Overlord";"Larva";268;0
"Unit";"Overlord";"Larva";268;0
"Unit";"Overlord";"Larva";268;0
"Building";"Hatchery";NA;260;0
"Unit";"Roach";"Larva";276;2
"Unit";"Roach";"Larva";276;2
"Unit";"Roach";"Larva";276;2
"Unit";"Roach";"Larva";276;2
"Unit";"Roach";"Larva";276;2
"Unit";"Roach";"Larva";276;2
"Unit";"Roach";"Larva";276;2
"Unit";"Roach";"Larva";276;2
"Unit";"Roach";"Larva";276;2
"Unit";"Roach";"Larva";276;2
"Unit";"Roach";"Larva";276;2
"Upgrade";"ZergGroundArmorsLevel1";"EvolutionChamber";268;0
"Unit";"Hydralisk";"Larva";276;2
"Unit";"Hydralisk";"Larva";276;2
"Unit";"Hydralisk";"Larva";276;2
"Unit";"Hydralisk";"Larva";276;2
"Unit";"Hydralisk";"Larva";276;2
"Unit";"Hydralisk";"Larva";276;2
"Unit";"Hydralisk";"Larva";276;2
"Unit";"Hydralisk";"Larva";276;2
"Unit";"Hydralisk";"Larva";276;2
"Unit";"Hydralisk";"Larva";276;2
"Unit";"Hydralisk";"Larva";276;2
"Unit";"Hydralisk";"Larva";276;2
"Building";"CreepTumor";NA;298;0
"Building";"Hatchery";NA;276;0
"Unit";"Hydralisk";"Larva";298;2
"Unit";"Hydralisk";"Larva";298;2
"Unit";"Hydralisk";"Larva";298;2
"Unit";"Hydralisk";"Larva";298;2
"Unit";"Hydralisk";"Larva";298;2
"Unit";"Hydralisk";"Larva";298;2
"Building";"CreepTumor";NA;334;0
"Building";"CreepTumor";NA;336;0
"Building";"CreepTumor";NA;336;0
"Building";"CreepTumorQueen";NA;336;0
"Upgrade";"EvolveMuscularAugments";"HydraliskDen";298;0
"Building";"Extractor";NA;336;0
"Building";"Extractor";NA;336;0
"Building";"SporeCrawler";NA;336;0
"Building";"CreepTumor";NA;336;0
"Building";"SpineCrawler";NA;336;0
"Building";"SpineCrawler";NA;336;0
"Building";"SpineCrawler";NA;336;0
"Building";"SpineCrawler";NA;336;0
"Unit";"Viper";"Larva";336;3
"Unit";"Viper";"Larva";336;3
"Unit";"Viper";"Larva";336;3
"Unit";"Viper";"Larva";336;3
"Unit";"Viper";"Larva";336;3
"Building";"CreepTumor";NA;342;0
"Unit";"Hydralisk";"Larva";336;2
"Unit";"Hydralisk";"Larva";336;2
"Unit";"Hydralisk";"Larva";336;2
"Unit";"Hydralisk";"Larva";336;2
"Unit";"Hydralisk";"Larva";336;2
"Unit";"Hydralisk";"Larva";336;2
"Unit";"Hydralisk";"Larva";336;2
"Unit";"Hydralisk";"Larva";336;2
"Unit";"Hydralisk";"Larva";336;2
"Unit";"Hydralisk";"Larva";336;2
"Unit";"Hydralisk";"Larva";336;2
"Unit";"Hydralisk";"Larva";336;2
"Unit";"Zergling";"Larva";375;1
"Unit";"Zergling";"Larva";375;1
"Unit";"Zergling";"Larva";375;1
"Unit";"Zergling";"Larva";375;1
"Unit";"Zergling";"Larva";375;1
"Unit";"Zergling";"Larva";375;1
"Unit";"Zergling";"Larva";375;1
"Unit";"Zergling";"Larva";375;1
"Unit";"Zergling";"Larva";375;1
"Unit";"Zergling";"Larva";375;1
"Unit";"Zergling";"Larva";375;1
"Unit";"Zergling";"Larva";375;1
"Unit";"Zergling";"Larva";375;1
"Unit";"Zergling";"Larva";375;1
"Unit";"Zergling";"Larva";375;1
"Unit";"Zergling";"Larva";375;1
"Unit";"Zergling";"Larva";375;1
"Unit";"Zergling";"Larva";375;1
"Unit";"Zergling";"Larva";375;1
"Unit";"Zergling";"Larva";375;1
"Unit";"Zergling";"Larva";375;1
"Unit";"Zergling";"Larva";375;1
"Unit";"Zergling";"Larva";375;1
"Unit";"Zergling";"Larva";375;1
"Unit";"Zergling";"Larva";375;1
"Unit";"Zergling";"Larva";375;1
"Unit";"Zergling";"Larva";375;1
"Unit";"Zergling";"Larva";375;1
"Unit";"Zergling";"Larva";375;1
"Unit";"Zergling";"Larva";375;1
"Unit";"Zergling";"Larva";375;1
"Unit";"Zergling";"Larva";375;1
"Unit";"Zergling";"Larva";375;1
"Unit";"Zergling";"Larva";375;1
"Unit";"Zergling";"Larva";375;1
"Unit";"Zergling";"Larva";375;1
"Unit";"Zergling";"Larva";375;1
"Unit";"Zergling";"Larva";375;1
"Building";"SpineCrawler";NA;351;0
"Upgrade";"ZergGroundArmorsLevel2";"EvolutionChamber";336;0
"Unit";"Hydralisk";"Larva";375;2
"Unit";"Hydralisk";"Larva";377;2
"Unit";"Hydralisk";"Larva";377;2
"Unit";"Overlord";"Larva";413;0
"Unit";"Overlord";"Larva";413;0
"Unit";"Overlord";"Larva";413;0
"Upgrade";"ZergMissileWeaponsLevel3";"EvolutionChamber";336;0
"Unit";"Hydralisk";"Larva";425;2
"Unit";"Hydralisk";"Larva";425;2
"Unit";"Hydralisk";"Larva";425;2
"Unit";"Hydralisk";"Larva";425;2
"Unit";"Hydralisk";"Larva";425;2
"Unit";"Hydralisk";"Larva";425;2
"Unit";"Hydralisk";"Larva";425;2
"Unit";"Hydralisk";"Larva";425;2
"Unit";"Hydralisk";"Larva";425;2
"Unit";"Hydralisk";"Larva";425;2
"Unit";"Hydralisk";"Larva";425;2
"Unit";"Hydralisk";"Larva";425;2
"Unit";"Hydralisk";"Larva";425;2
"Unit";"Hydralisk";"Larva";425;2
"Unit";"Hydralisk";"Larva";425;2
"Unit";"Hydralisk";"Larva";455;2
"Unit";"Hydralisk";"Larva";455;2
"Unit";"Hydralisk";"Larva";455;2
"Unit";"Hydralisk";"Larva";455;2
"Unit";"Hydralisk";"Larva";455;2
"Unit";"Hydralisk";"Larva";455;2
"Unit";"Hydralisk";"Larva";455;2
"Unit";"Hydralisk";"Larva";455;2
"Unit";"Hydralisk";"Larva";455;2
"Unit";"Hydralisk";"Larva";455;2
"Building";"CreepTumor";NA;475;0
"Unit";"Hydralisk";"Larva";475;2
"Unit";"Hydralisk";"Larva";475;2
"Unit";"Hydralisk";"Larva";475;2
"Unit";"Hydralisk";"Larva";475;2
"Unit";"Hydralisk";"Larva";475;2
"Unit";"Hydralisk";"Larva";475;2
"Unit";"Hydralisk";"Larva";475;2
"Unit";"Hydralisk";"Larva";475;2
"Unit";"Hydralisk";"Larva";475;2
"Unit";"Hydralisk";"Larva";475;2
