"type";"unit_name";"on_building";"total_supply";"supply"
"Unit";"Overlord";"Larva";13;0
"Building";"Extractor";NA;17;0
"Unit";"Overlord";"Larva";21;0
"Building";"SpawningPool";NA;19;0
"Building";"Hatchery";NA;17;0
"Unit";"Queen";"Hatchery";23;2
"Unit";"Zergling";"Larva";24;1
"Unit";"Zergling";"Larva";24;1
"Unit";"Queen";"Hatchery";23;2
"Unit";"Zergling";"Larva";26;1
"Unit";"Zergling";"Larva";26;1
"Unit";"Zergling";"Larva";27;1
"Unit";"Zergling";"Larva";27;1
"Unit";"Zergling";"Larva";31;1
"Unit";"Zergling";"Larva";31;1
"Unit";"Zergling";"Larva";33;1
"Unit";"Zergling";"Larva";33;1
"Building";"BanelingNest";NA;26;0
"Unit";"Zergling";"Larva";41;1
"Unit";"Zergling";"Larva";41;1
"Unit";"Zergling";"Larva";41;1
"Unit";"Zergling";"Larva";41;1
"Unit";"Zergling";"Larva";41;1
"Unit";"Zergling";"Larva";41;1
"Unit";"Overlord";"Larva";41;0
"Unit";"Zergling";"Larva";41;1
"Unit";"Zergling";"Larva";41;1
"Unit";"Zergling";"Larva";41;1
"Unit";"Zergling";"Larva";41;1
"Unit";"Baneling";"Zergling";45;0
"Unit";"Baneling";"Zergling";45;0
"Unit";"Baneling";"Zergling";45;0
"Unit";"Baneling";"Zergling";45;0
"Unit";"Overlord";"Larva";47;0
"Building";"Hatchery";NA;37;0
"Unit";"Zergling";"Larva";55;1
"Unit";"Zergling";"Larva";55;1
"Unit";"Zergling";"Larva";55;1
"Unit";"Zergling";"Larva";55;1
"Unit";"Zergling";"Larva";55;1
"Unit";"Zergling";"Larva";55;1
"Unit";"Zergling";"Larva";62;1
"Unit";"Zergling";"Larva";62;1
"Unit";"Zergling";"Larva";62;1
"Unit";"Zergling";"Larva";62;1
"Unit";"Baneling";"Zergling";68;0
"Unit";"Baneling";"Zergling";68;0
"Unit";"Baneling";"Zergling";68;0
"Unit";"Baneling";"Zergling";68;0
"Unit";"Zergling";"Larva";68;1
"Unit";"Zergling";"Larva";68;1
"Unit";"Zergling";"Larva";68;1
"Unit";"Zergling";"Larva";68;1
"Unit";"Queen";"Hatchery";62;2
"Unit";"Zergling";"Larva";68;1
"Unit";"Zergling";"Larva";68;1
"Unit";"Zergling";"Larva";68;1
"Unit";"Zergling";"Larva";68;1
"Unit";"Queen";"Hatchery";68;2
"Unit";"Baneling";"Zergling";72;0
"Unit";"Baneling";"Zergling";72;0
"Unit";"Baneling";"Zergling";72;0
"Building";"CreepTumorQueen";NA;82;0
"Unit";"Zergling";"Larva";74;1
"Unit";"Zergling";"Larva";74;1
"Unit";"Zergling";"Larva";74;1
"Unit";"Zergling";"Larva";74;1
"Unit";"Zergling";"Larva";76;1
"Unit";"Zergling";"Larva";76;1
"Unit";"Zergling";"Larva";76;1
"Unit";"Zergling";"Larva";76;1
"Unit";"Overlord";"Larva";92;0
"Unit";"Overlord";"Larva";92;0
"Unit";"Overlord";"Larva";92;0
"Unit";"Overlord";"Larva";92;0
"Building";"CreepTumor";NA;97;0
"Building";"Extractor";NA;97;0
"Building";"Extractor";NA;97;0
"Building";"EvolutionChamber";NA;97;0
"Building";"RoachWarren";NA;97;0
"Building";"CreepTumor";NA;110;0
"Building";"CreepTumorQueen";NA;110;0
"Building";"CreepTumorQueen";NA;110;0
"Building";"Extractor";NA;120;0
"Building";"Extractor";NA;120;0
"Unit";"Overlord";"Larva";126;0
"Unit";"Overlord";"Larva";126;0
"Building";"Extractor";NA;126;0
"Unit";"Overlord";"Larva";126;0
"Building";"EvolutionChamber";NA;126;0
"Unit";"Roach";"Larva";131;2
"Unit";"Roach";"Larva";131;2
"Unit";"Roach";"Larva";131;2
"Unit";"Roach";"Larva";131;2
"Unit";"Roach";"Larva";131;2
"Unit";"Roach";"Larva";131;2
"Unit";"Roach";"Larva";131;2
"Building";"HydraliskDen";NA;131;0
"Unit";"Roach";"Larva";131;2
"Unit";"Roach";"Larva";131;2
"Unit";"Roach";"Larva";131;2
"Unit";"Roach";"Larva";137;2
"Unit";"Roach";"Larva";137;2
"Unit";"Roach";"Larva";137;2
"Unit";"Roach";"Larva";137;2
"Unit";"Roach";"Larva";137;2
"Unit";"Roach";"Larva";145;2
"Unit";"Roach";"Larva";145;2
"Building";"CreepTumorQueen";NA;157;0
"Building";"CreepTumor";NA;157;0
"Building";"CreepTumor";NA;157;0
"Building";"CreepTumor";NA;157;0
"Building";"CreepTumorQueen";NA;157;0
"Unit";"Roach";"Larva";151;2
"Unit";"Overlord";"Larva";151;0
"Unit";"Overlord";"Larva";151;0
"Unit";"Overlord";"Larva";151;0
"Building";"CreepTumorQueen";NA;161;0
"Upgrade";"ZergMissileWeaponsLevel1";"EvolutionChamber";120;0
"Unit";"Roach";"Larva";167;2
"Unit";"Roach";"Larva";167;2
"Unit";"Roach";"Larva";167;2
"Upgrade";"GlialReconstitution";"RoachWarren";137;0
"Unit";"Roach";"Larva";167;2
"Unit";"Roach";"Larva";167;2
"Unit";"Roach";"Larva";167;2
"Unit";"Zergling";"Larva";167;1
"Unit";"Zergling";"Larva";167;1
"Unit";"Zergling";"Larva";167;1
"Unit";"Zergling";"Larva";167;1
"Unit";"Zergling";"Larva";167;1
"Unit";"Zergling";"Larva";167;1
"Unit";"Roach";"Larva";167;2
"Unit";"Roach";"Larva";167;2
"Unit";"Roach";"Larva";167;2
"Building";"CreepTumor";NA;173;0
"Building";"CreepTumor";NA;173;0
"Building";"CreepTumor";NA;173;0
"Building";"CreepTumor";NA;173;0
"Building";"CreepTumor";NA;173;0
"Building";"CreepTumor";NA;173;0
"Unit";"Roach";"Larva";173;2
"Unit";"Roach";"Larva";191;2
"Unit";"Roach";"Larva";191;2
"Unit";"Queen";"Hatchery";173;2
"Building";"CreepTumorQueen";NA;193;0
"Unit";"Overlord";"Larva";191;0
"Unit";"Overlord";"Larva";191;0
"Unit";"Overlord";"Larva";191;0
"Unit";"Overlord";"Larva";191;0
"Building";"CreepTumorQueen";NA;193;0
"Building";"CreepTumorQueen";NA;193;0
"Building";"CreepTumor";NA;193;0
"Building";"CreepTumor";NA;193;0
"Building";"CreepTumor";NA;193;0
"Building";"CreepTumor";NA;193;0
"Building";"CreepTumor";NA;193;0
"Building";"CreepTumor";NA;193;0
"Building";"LurkerDenMP";NA;165;0
"Building";"Hatchery";NA;167;0
"Unit";"Roach";"Larva";199;2
"Unit";"Roach";"Larva";199;2
"Unit";"Roach";"Larva";199;2
"Unit";"Roach";"Larva";199;2
"Unit";"Roach";"Larva";199;2
"Unit";"Roach";"Larva";199;2
"Unit";"Roach";"Larva";199;2
"Unit";"Roach";"Larva";199;2
"Unit";"Roach";"Larva";199;2
"Unit";"Roach";"Larva";199;2
"Unit";"Roach";"Larva";199;2
"Unit";"Roach";"Larva";199;2
"Unit";"Roach";"Larva";199;2
"Unit";"Roach";"Larva";199;2
"Unit";"Roach";"Larva";199;2
"Unit";"Roach";"Larva";199;2
"Unit";"Roach";"Larva";199;2
"Unit";"Roach";"Larva";199;2
"Unit";"Roach";"Larva";199;2
"Unit";"Roach";"Larva";199;2
"Unit";"Roach";"Larva";199;2
"Upgrade";"ZergGroundArmorsLevel1";"EvolutionChamber";173;0
"Unit";"Hydralisk";"Larva";227;2
"Unit";"Hydralisk";"Larva";227;2
"Unit";"Roach";"Larva";227;2
"Unit";"Roach";"Larva";227;2
"Building";"CreepTumor";NA;241;0
"Building";"CreepTumor";NA;241;0
"Unit";"Roach";"Larva";241;2
"Unit";"Roach";"Larva";241;2
"Unit";"Roach";"Larva";241;2
"Unit";"Roach";"Larva";241;2
"Building";"Extractor";NA;242;0
"Unit";"Roach";"Larva";260;2
"Unit";"Overlord";"Larva";260;0
"Unit";"Overlord";"Larva";260;0
"Unit";"Roach";"Larva";260;2
"Unit";"Overlord";"Larva";260;0
"Unit";"Roach";"Larva";260;2
"Unit";"Roach";"Larva";260;2
"Unit";"Roach";"Larva";260;2
"Unit";"Roach";"Larva";260;2
"Unit";"Roach";"Larva";260;2
"Unit";"Roach";"Larva";264;2
"Unit";"Roach";"Larva";264;2
"Unit";"Roach";"Larva";264;2
"Unit";"Roach";"Larva";264;2
"Unit";"Roach";"Larva";264;2
"Unit";"Roach";"Larva";264;2
"Unit";"Roach";"Larva";264;2
"Unit";"Roach";"Larva";264;2
"Unit";"Roach";"Larva";264;2
"Unit";"Roach";"Larva";264;2
"Unit";"Roach";"Larva";264;2
"Unit";"Roach";"Larva";264;2
"Unit";"Hydralisk";"Larva";298;2
"Unit";"Hydralisk";"Larva";298;2
"Unit";"Hydralisk";"Larva";298;2
"Unit";"Hydralisk";"Larva";298;2
"Unit";"Hydralisk";"Larva";298;2
"Unit";"Hydralisk";"Larva";298;2
"Unit";"Hydralisk";"Larva";298;2
"Unit";"Hydralisk";"Larva";298;2
"Unit";"Hydralisk";"Larva";298;2
"Building";"SpineCrawler";NA;292;0
"Building";"SpineCrawler";NA;298;0
"Building";"CreepTumor";NA;321;0
"Building";"CreepTumor";NA;321;0
"Building";"CreepTumor";NA;321;0
"Unit";"Roach";"Larva";321;2
"Unit";"Roach";"Larva";321;2
"Unit";"Roach";"Larva";321;2
"Unit";"Overlord";"Larva";321;0
"Unit";"Overlord";"Larva";321;0
"Unit";"Overlord";"Larva";321;0
"Unit";"Overlord";"Larva";321;0
"Unit";"Overlord";"Larva";321;0
"Unit";"Overlord";"Larva";321;0
"Building";"Extractor";NA;321;0
"Unit";"Roach";"Larva";327;2
"Unit";"Roach";"Larva";327;2
"Unit";"Roach";"Larva";327;2
"Unit";"Roach";"Larva";327;2
"Unit";"Roach";"Larva";327;2
"Upgrade";"ZergMissileWeaponsLevel2";"EvolutionChamber";298;0
"Unit";"Roach";"Larva";327;2
"Unit";"Roach";"Larva";327;2
"Unit";"Roach";"Larva";327;2
"Unit";"Roach";"Larva";327;2
"Unit";"Roach";"Larva";327;2
"Unit";"Roach";"Larva";327;2
"Unit";"Roach";"Larva";327;2
"Unit";"Hydralisk";"Larva";337;2
"Unit";"Hydralisk";"Larva";337;2
"Unit";"Roach";"Larva";337;2
"Unit";"Roach";"Larva";337;2
"Unit";"Roach";"Larva";337;2
"Unit";"Roach";"Larva";337;2
"Unit";"Roach";"Larva";337;2
"Unit";"Roach";"Larva";339;2
"Unit";"Hydralisk";"Larva";351;2
"Unit";"Hydralisk";"Larva";351;2
"Building";"CreepTumor";NA;367;0
"Building";"CreepTumor";NA;367;0
"Building";"CreepTumor";NA;367;0
"Unit";"Hydralisk";"Larva";371;2
