"type";"unit_name";"on_building";"total_supply";"supply"
"Unit";"Overlord";"Larva";13;0
"Building";"Extractor";NA;17;0
"Unit";"Overlord";"Larva";21;0
"Building";"SpawningPool";NA;19;0
"Building";"Hatchery";NA;17;0
"Unit";"Zergling";"Larva";22;1
"Unit";"Zergling";"Larva";22;1
"Unit";"Zergling";"Larva";22;1
"Unit";"Zergling";"Larva";22;1
"Unit";"Zergling";"Larva";22;1
"Unit";"Zergling";"Larva";22;1
"Unit";"Queen";"Hatchery";22;2
"Unit";"Queen";"Hatchery";22;2
"Building";"BanelingNest";NA;31;0
"Unit";"Overlord";"Larva";39;0
"Unit";"Zergling";"Larva";39;1
"Unit";"Zergling";"Larva";39;1
"Unit";"Zergling";"Larva";39;1
"Unit";"Zergling";"Larva";39;1
"Unit";"Zergling";"Larva";39;1
"Unit";"Zergling";"Larva";39;1
"Unit";"Zergling";"Larva";39;1
"Unit";"Zergling";"Larva";39;1
"Unit";"Zergling";"Larva";40;1
"Unit";"Zergling";"Larva";40;1
"Unit";"Zergling";"Larva";40;1
"Unit";"Zergling";"Larva";40;1
"Unit";"Zergling";"Larva";42;1
"Unit";"Zergling";"Larva";42;1
"Unit";"Zergling";"Larva";48;1
"Unit";"Zergling";"Larva";48;1
"Unit";"Baneling";"Zergling";48;0
"Unit";"Baneling";"Zergling";48;0
"Unit";"Zergling";"Larva";48;1
"Unit";"Zergling";"Larva";48;1
"Unit";"Zergling";"Larva";54;1
"Unit";"Zergling";"Larva";54;1
"Unit";"Zergling";"Larva";54;1
"Unit";"Zergling";"Larva";54;1
"Building";"Hatchery";NA;39;0
"Unit";"Baneling";"Zergling";59;0
"Unit";"Baneling";"Zergling";59;0
"Unit";"Baneling";"Zergling";65;0
"Unit";"Baneling";"Zergling";65;0
"Unit";"Baneling";"Zergling";65;0
"Unit";"Overlord";"Larva";65;0
"Unit";"Overlord";"Larva";65;0
"Unit";"Overlord";"Larva";65;0
"Unit";"Overlord";"Larva";65;0
"Building";"Extractor";NA;74;0
"Building";"Extractor";NA;74;0
"Unit";"Zergling";"Larva";80;1
"Unit";"Zergling";"Larva";80;1
"Unit";"Zergling";"Larva";80;1
"Unit";"Zergling";"Larva";80;1
"Unit";"Zergling";"Larva";80;1
"Unit";"Zergling";"Larva";80;1
"Unit";"Zergling";"Larva";80;1
"Unit";"Zergling";"Larva";80;1
"Building";"RoachWarren";NA;74;0
"Unit";"Overlord";"Larva";80;0
"Unit";"Overlord";"Larva";80;0
"Unit";"Baneling";"Zergling";80;0
"Unit";"Baneling";"Zergling";80;0
"Unit";"Baneling";"Zergling";80;0
"Unit";"Queen";"Hatchery";80;2
"Unit";"Roach";"Larva";94;2
"Unit";"Roach";"Larva";94;2
"Unit";"Roach";"Larva";94;2
"Unit";"Roach";"Larva";94;2
"Unit";"Roach";"Larva";94;2
"Unit";"Roach";"Larva";94;2
"Building";"EvolutionChamber";NA;94;0
"Unit";"Overlord";"Larva";102;0
"Unit";"Overlord";"Larva";102;0
"Unit";"Overlord";"Larva";118;0
"Building";"Extractor";NA;118;0
"Building";"Extractor";NA;118;0
"Unit";"Roach";"Larva";118;2
"Unit";"Roach";"Larva";118;2
"Upgrade";"GlialReconstitution";"RoachWarren";99;0
"Unit";"Overlord";"Larva";126;0
"Unit";"Overlord";"Larva";126;0
"Unit";"Roach";"Larva";130;2
"Unit";"Roach";"Larva";130;2
"Unit";"Roach";"Larva";130;2
"Unit";"Roach";"Larva";130;2
"Unit";"Roach";"Larva";130;2
"Unit";"Roach";"Larva";130;2
"Unit";"Roach";"Larva";130;2
"Unit";"Roach";"Larva";130;2
"Unit";"Roach";"Larva";130;2
"Unit";"Overlord";"Larva";130;0
"Unit";"Baneling";"Zergling";130;0
"Unit";"Baneling";"Zergling";130;0
"Unit";"Baneling";"Zergling";130;0
"Unit";"Baneling";"Zergling";130;0
"Unit";"Baneling";"Zergling";130;0
"Unit";"Overlord";"Larva";130;0
"Unit";"Roach";"Larva";130;2
"Unit";"Roach";"Larva";130;2
"Building";"Hatchery";NA;118;0
"Upgrade";"ZergMissileWeaponsLevel1";"EvolutionChamber";126;0
"Building";"SporeCrawler";NA;152;0
"Building";"SporeCrawler";NA;152;0
"Unit";"Roach";"Larva";152;2
"Unit";"Roach";"Larva";152;2
"Unit";"Roach";"Larva";152;2
"Unit";"Roach";"Larva";152;2
"Unit";"Roach";"Larva";152;2
"Unit";"Roach";"Larva";152;2
"Unit";"Roach";"Larva";152;2
"Unit";"Roach";"Larva";152;2
"Unit";"Roach";"Larva";152;2
"Unit";"Roach";"Larva";152;2
"Unit";"Roach";"Larva";152;2
"Unit";"Roach";"Larva";152;2
"Building";"SporeCrawler";NA;152;0
"Building";"SporeCrawler";NA;152;0
"Unit";"Queen";"Hatchery";152;2
"Unit";"Queen";"Hatchery";152;2
"Unit";"Queen";"Hatchery";152;2
"Unit";"Queen";"Hatchery";152;2
"Building";"SporeCrawler";NA;176;0
"Building";"HydraliskDen";NA;152;0
"Building";"SporeCrawler";NA;176;0
"Unit";"Hydralisk";"Larva";187;2
"Unit";"Hydralisk";"Larva";187;2
"Unit";"Hydralisk";"Larva";187;2
"Unit";"Hydralisk";"Larva";187;2
"Unit";"Hydralisk";"Larva";187;2
"Unit";"Hydralisk";"Larva";187;2
"Unit";"Hydralisk";"Larva";187;2
"Unit";"Hydralisk";"Larva";187;2
"Unit";"Hydralisk";"Larva";187;2
"Unit";"Overlord";"Larva";187;0
"Unit";"Overlord";"Larva";187;0
"Unit";"Overlord";"Larva";187;0
"Unit";"Overlord";"Larva";187;0
"Unit";"Overlord";"Larva";187;0
"Unit";"Queen";"Hatchery";187;2
"Unit";"Queen";"Hatchery";187;2
"Unit";"Queen";"Hatchery";187;2
"Unit";"Queen";"Hatchery";187;2
"Unit";"Hydralisk";"Larva";187;2
"Unit";"Hydralisk";"Larva";187;2
"Unit";"Hydralisk";"Larva";187;2
"Unit";"Hydralisk";"Larva";187;2
"Unit";"Hydralisk";"Larva";187;2
"Building";"SporeCrawler";NA;205;0
"Unit";"Hydralisk";"Larva";221;2
"Unit";"Hydralisk";"Larva";223;2
"Unit";"Hydralisk";"Larva";223;2
"Unit";"Hydralisk";"Larva";223;2
"Unit";"Hydralisk";"Larva";223;2
"Unit";"Hydralisk";"Larva";223;2
"Unit";"Hydralisk";"Larva";223;2
"Unit";"Hydralisk";"Larva";223;2
"Unit";"Hydralisk";"Larva";223;2
"Building";"Extractor";NA;223;0
"Unit";"Hydralisk";"Larva";237;2
"Unit";"Hydralisk";"Larva";237;2
"Unit";"Hydralisk";"Larva";237;2
"Unit";"Hydralisk";"Larva";237;2
"Unit";"Hydralisk";"Larva";237;2
"Unit";"Hydralisk";"Larva";254;2
"Upgrade";"ZergMissileWeaponsLevel2";"EvolutionChamber";205;0
"Unit";"Hydralisk";"Larva";254;2
"Unit";"Hydralisk";"Larva";254;2
"Unit";"Hydralisk";"Larva";254;2
"Unit";"Hydralisk";"Larva";254;2
"Unit";"Overlord";"Larva";260;0
"Unit";"Overlord";"Larva";260;0
"Unit";"Overlord";"Larva";260;0
"Unit";"Overlord";"Larva";260;0
"Unit";"Overlord";"Larva";260;0
"Upgrade";"EvolveGroovedSpines";"HydraliskDen";254;0
"Building";"Hatchery";NA;254;0
"Building";"Hatchery";NA;254;0
"Unit";"Hydralisk";"Larva";264;2
"Unit";"Hydralisk";"Larva";264;2
"Unit";"Hydralisk";"Larva";264;2
"Unit";"Hydralisk";"Larva";264;2
"Unit";"Hydralisk";"Larva";264;2
"Unit";"Hydralisk";"Larva";264;2
"Unit";"Hydralisk";"Larva";264;2
"Unit";"Hydralisk";"Larva";264;2
"Unit";"Hydralisk";"Larva";264;2
"Unit";"Hydralisk";"Larva";264;2
"Unit";"Roach";"Larva";264;2
"Unit";"Roach";"Larva";264;2
"Unit";"Roach";"Larva";264;2
"Unit";"Roach";"Larva";264;2
"Building";"LurkerDenMP";NA;254;0
"Unit";"Roach";"Larva";292;2
"Unit";"Roach";"Larva";292;2
"Unit";"Roach";"Larva";292;2
"Unit";"Roach";"Larva";292;2
"Unit";"Roach";"Larva";292;2
"Unit";"Roach";"Larva";292;2
"Unit";"Roach";"Larva";292;2
"Unit";"Roach";"Larva";292;2
"Unit";"Roach";"Larva";292;2
"Unit";"Roach";"Larva";292;2
"Unit";"Hydralisk";"Larva";292;2
"Unit";"Hydralisk";"Larva";292;2
"Unit";"Hydralisk";"Larva";292;2
"Unit";"Hydralisk";"Larva";292;2
"Upgrade";"ZergGroundArmorsLevel1";"EvolutionChamber";264;0
"Unit";"Overlord";"Larva";320;0
"Unit";"Overlord";"Larva";320;0
"Unit";"Overlord";"Larva";329;0
"Unit";"Overlord";"Larva";329;0
"Building";"SporeCrawler";NA;329;0
"Unit";"Overlord";"Larva";329;0
"Unit";"Overlord";"Larva";329;0
"Building";"SporeCrawler";NA;329;0
"Upgrade";"EvolveMuscularAugments";"HydraliskDen";329;0
"Unit";"Hydralisk";"Larva";337;2
"Unit";"Hydralisk";"Larva";337;2
"Unit";"Hydralisk";"Larva";337;2
"Unit";"Hydralisk";"Larva";337;2
"Unit";"Hydralisk";"Larva";337;2
"Unit";"Hydralisk";"Larva";337;2
"Unit";"Hydralisk";"Larva";337;2
"Unit";"Hydralisk";"Larva";337;2
"Unit";"Hydralisk";"Larva";337;2
"Unit";"Hydralisk";"Larva";337;2
"Unit";"Overlord";"Larva";357;0
"Unit";"Overlord";"Larva";357;0
"Unit";"Overlord";"Larva";357;0
"Unit";"Overlord";"Larva";357;0
"Unit";"Overlord";"Larva";357;0
"Unit";"Overlord";"Larva";357;0
"Unit";"Overlord";"Larva";357;0
"Unit";"Overlord";"Larva";357;0
"Unit";"Overlord";"Larva";357;0
"Unit";"Overlord";"Larva";357;0
"Unit";"Overlord";"Larva";357;0
"Unit";"Overlord";"Larva";357;0
"Unit";"Overlord";"Larva";357;0
"Unit";"Overlord";"Larva";357;0
"Unit";"Overlord";"Larva";357;0
"Building";"InfestationPit";NA;357;0
"Unit";"Roach";"Larva";357;2
"Unit";"Roach";"Larva";357;2
"Unit";"Roach";"Larva";357;2
"Unit";"Roach";"Larva";357;2
"Upgrade";"ZergGroundArmorsLevel2";"EvolutionChamber";343;0
"Unit";"Hydralisk";"Larva";357;2
"Unit";"Hydralisk";"Larva";357;2
"Unit";"Hydralisk";"Larva";357;2
"Unit";"Hydralisk";"Larva";357;2
"Unit";"Hydralisk";"Larva";357;2
"Unit";"Hydralisk";"Larva";357;2
"Unit";"Hydralisk";"Larva";357;2
"Unit";"Hydralisk";"Larva";357;2
"Unit";"Hydralisk";"Larva";357;2
"Unit";"Hydralisk";"Larva";357;2
"Unit";"Hydralisk";"Larva";357;2
"Unit";"Hydralisk";"Larva";357;2
"Unit";"Hydralisk";"Larva";357;2
"Unit";"Hydralisk";"Larva";357;2
"Upgrade";"TunnelingClaws";"RoachWarren";357;0
"Unit";"Hydralisk";"Larva";393;2
"Unit";"Hydralisk";"Larva";393;2
"Unit";"Hydralisk";"Larva";393;2
"Unit";"Hydralisk";"Larva";393;2
"Unit";"Hydralisk";"Larva";393;2
"Unit";"Hydralisk";"Larva";393;2
"Unit";"Hydralisk";"Larva";393;2
"Unit";"Hydralisk";"Larva";393;2
"Unit";"Hydralisk";"Larva";393;2
"Unit";"Hydralisk";"Larva";393;2
"Unit";"Hydralisk";"Larva";393;2
"Unit";"Hydralisk";"Larva";393;2
"Unit";"Hydralisk";"Larva";393;2
"Unit";"Hydralisk";"Larva";393;2
"Unit";"Hydralisk";"Larva";393;2
"Unit";"Hydralisk";"Larva";393;2
"Unit";"Hydralisk";"Larva";393;2
"Unit";"Hydralisk";"Larva";393;2
"Unit";"Hydralisk";"Larva";393;2
"Unit";"Hydralisk";"Larva";393;2
"Unit";"Hydralisk";"Larva";393;2
"Unit";"Hydralisk";"Larva";393;2
"Unit";"Hydralisk";"Larva";393;2
"Unit";"Roach";"Larva";393;2
"Unit";"Roach";"Larva";393;2
"Unit";"Roach";"Larva";443;2
"Unit";"Roach";"Larva";443;2
"Unit";"Roach";"Larva";443;2
"Unit";"Roach";"Larva";443;2
"Unit";"Roach";"Larva";443;2
"Unit";"Roach";"Larva";443;2
"Unit";"Roach";"Larva";443;2
"Unit";"Roach";"Larva";443;2
"Unit";"Roach";"Larva";443;2
"Unit";"Roach";"Larva";443;2
"Unit";"Roach";"Larva";443;2
"Unit";"Roach";"Larva";443;2
"Unit";"Roach";"Larva";443;2
