"type";"unit_name";"on_building";"total_supply";"supply"
"Unit";"Overlord";"Larva";13;0
"Building";"Extractor";NA;18;0
"Unit";"Overlord";"Larva";22;0
"Building";"SpawningPool";NA;19;0
"Building";"Hatchery";NA;17;0
"Unit";"Zergling";"Larva";22;1
"Unit";"Zergling";"Larva";22;1
"Unit";"Zergling";"Larva";22;1
"Unit";"Zergling";"Larva";22;1
"Unit";"Queen";"Hatchery";22;2
"Unit";"Queen";"Hatchery";22;2
"Unit";"Overlord";"Larva";35;0
"Building";"BanelingNest";NA;32;0
"Building";"EvolutionChamber";NA;49;0
"Unit";"Overlord";"Larva";51;0
"Building";"Extractor";NA;49;0
"Unit";"Overlord";"Larva";51;0
"Unit";"Overlord";"Larva";51;0
"Building";"Extractor";NA;53;0
"Building";"Hatchery";NA;39;0
"Unit";"Zergling";"Larva";56;1
"Unit";"Zergling";"Larva";56;1
"Unit";"Zergling";"Larva";56;1
"Unit";"Zergling";"Larva";56;1
"Building";"RoachWarren";NA;54;0
"Unit";"Queen";"Hatchery";59;2
"Building";"Extractor";NA;68;0
"Unit";"Roach";"Larva";70;2
"Unit";"Roach";"Larva";70;2
"Unit";"Roach";"Larva";78;2
"Unit";"Roach";"Larva";78;2
"Unit";"Roach";"Larva";78;2
"Unit";"Roach";"Larva";78;2
"Unit";"Overlord";"Larva";82;0
"Unit";"Overlord";"Larva";82;0
"Unit";"Overlord";"Larva";82;0
"Unit";"Overlord";"Larva";82;0
"Unit";"Overlord";"Larva";82;0
"Unit";"Overlord";"Larva";82;0
"Unit";"Roach";"Larva";90;2
"Unit";"Roach";"Larva";90;2
"Unit";"Roach";"Larva";90;2
"Unit";"Roach";"Larva";90;2
"Unit";"Roach";"Larva";90;2
"Unit";"Roach";"Larva";90;2
"Unit";"Overlord";"Larva";90;0
"Unit";"Roach";"Larva";90;2
"Upgrade";"ZergMissileWeaponsLevel1";"EvolutionChamber";67;0
"Unit";"Roach";"Larva";90;2
"Unit";"Roach";"Larva";90;2
"Unit";"Roach";"Larva";90;2
"Upgrade";"GlialReconstitution";"RoachWarren";78;0
"Unit";"Roach";"Larva";90;2
"Unit";"Roach";"Larva";90;2
"Unit";"Overlord";"Larva";102;0
"Unit";"Overlord";"Larva";102;0
"Unit";"Overlord";"Larva";102;0
"Unit";"Overlord";"Larva";102;0
"Unit";"Roach";"Larva";102;2
"Unit";"Roach";"Larva";102;2
"Unit";"Roach";"Larva";112;2
"Unit";"Overlord";"Larva";114;0
"Unit";"Overlord";"Larva";114;0
"Unit";"Roach";"Larva";118;2
"Unit";"Roach";"Larva";118;2
"Unit";"Roach";"Larva";118;2
"Unit";"Roach";"Larva";118;2
"Unit";"Roach";"Larva";118;2
"Unit";"Roach";"Larva";118;2
"Unit";"Queen";"Hatchery";114;2
"Building";"Extractor";NA;120;0
"Building";"HydraliskDen";NA;137;0
"Unit";"Roach";"Larva";142;2
"Unit";"Roach";"Larva";142;2
"Unit";"Roach";"Larva";142;2
"Unit";"Roach";"Larva";142;2
"Unit";"Roach";"Larva";142;2
"Unit";"Roach";"Larva";142;2
"Unit";"Roach";"Larva";142;2
"Unit";"Roach";"Larva";142;2
"Unit";"Roach";"Larva";142;2
"Building";"Extractor";NA;142;0
"Unit";"Roach";"Larva";142;2
"Unit";"Roach";"Larva";142;2
"Unit";"Roach";"Larva";142;2
"Unit";"Roach";"Larva";158;2
"Unit";"Roach";"Larva";158;2
"Unit";"Roach";"Larva";158;2
"Unit";"Roach";"Larva";158;2
"Unit";"Roach";"Larva";158;2
"Unit";"Overlord";"Larva";166;0
"Unit";"Overlord";"Larva";166;0
"Unit";"Roach";"Larva";166;2
"Unit";"Roach";"Larva";166;2
"Unit";"Roach";"Larva";166;2
"Unit";"Roach";"Larva";166;2
"Unit";"Roach";"Larva";176;2
"Unit";"Roach";"Larva";176;2
"Unit";"Roach";"Larva";176;2
"Unit";"Roach";"Larva";176;2
"Unit";"Roach";"Larva";176;2
"Unit";"Roach";"Larva";180;2
"Unit";"Roach";"Larva";182;2
"Unit";"Roach";"Larva";184;2
"Unit";"Roach";"Larva";184;2
"Unit";"Roach";"Larva";194;2
"Unit";"Roach";"Larva";194;2
"Unit";"Roach";"Larva";194;2
"Unit";"Hydralisk";"Larva";194;2
"Unit";"Hydralisk";"Larva";194;2
"Unit";"Hydralisk";"Larva";198;2
"Upgrade";"ZergMissileWeaponsLevel2";"EvolutionChamber";142;0
"Unit";"Hydralisk";"Larva";208;2
"Unit";"Hydralisk";"Larva";208;2
"Unit";"Hydralisk";"Larva";208;2
"Unit";"Hydralisk";"Larva";208;2
"Building";"Hatchery";NA;176;0
"Building";"LurkerDenMP";NA;160;0
"Upgrade";"EvolveGroovedSpines";"HydraliskDen";202;0
"Building";"Extractor";NA;233;0
"Unit";"Roach";"Larva";233;2
"Building";"Extractor";NA;233;0
"Unit";"Roach";"Larva";233;2
"Unit";"Overlord";"Larva";236;0
"Unit";"Overlord";"Larva";236;0
"Building";"EvolutionChamber";NA;233;0
"Unit";"Queen";"Hatchery";233;2
"Building";"InfestationPit";NA;233;0
"Unit";"Hydralisk";"Larva";240;2
"Unit";"Hydralisk";"Larva";240;2
"Unit";"Hydralisk";"Larva";240;2
"Unit";"Hydralisk";"Larva";240;2
"Unit";"Hydralisk";"Larva";240;2
"Unit";"Hydralisk";"Larva";240;2
"Unit";"Overlord";"Larva";254;0
"Unit";"Overlord";"Larva";254;0
"Upgrade";"EvolveMuscularAugments";"HydraliskDen";240;0
"Unit";"Hydralisk";"Larva";254;2
"Unit";"Hydralisk";"Larva";254;2
"Unit";"Hydralisk";"Larva";254;2
"Unit";"Overlord";"Larva";254;0
"Unit";"Overlord";"Larva";254;0
"Upgrade";"ZergGroundArmorsLevel1";"EvolutionChamber";236;0
"Unit";"Roach";"Larva";260;2
"Unit";"Roach";"Larva";260;2
"Unit";"Roach";"Larva";260;2
"Unit";"Roach";"Larva";260;2
"Unit";"Roach";"Larva";260;2
"Unit";"Roach";"Larva";260;2
"Unit";"Roach";"Larva";260;2
"Unit";"Roach";"Larva";260;2
"Unit";"Roach";"Larva";260;2
"Unit";"Roach";"Larva";260;2
"Unit";"Roach";"Larva";260;2
"Unit";"Roach";"Larva";260;2
"Unit";"Roach";"Larva";260;2
"Unit";"Roach";"Larva";260;2
"Unit";"Roach";"Larva";260;2
"Unit";"Roach";"Larva";260;2
"Unit";"Roach";"Larva";260;2
"Unit";"Roach";"Larva";260;2
"Unit";"Roach";"Larva";260;2
