"type";"unit_name";"on_building";"total_supply";"supply"
"Unit";"Overlord";"Larva";12;0
"Building";"Extractor";NA;17;0
"Unit";"Overlord";"Larva";20;0
"Building";"Hatchery";NA;16;0
"Building";"SpawningPool";NA;19;0
"Unit";"Zergling";"Larva";21;1
"Unit";"Zergling";"Larva";21;1
"Unit";"Queen";"Hatchery";21;2
"Unit";"Queen";"Hatchery";21;2
"Unit";"Overlord";"Larva";35;0
"Building";"CreepTumorQueen";NA;37;0
"Unit";"Queen";"Hatchery";35;2
"Unit";"Overlord";"Larva";39;0
"Building";"Extractor";NA;48;0
"Building";"Hatchery";NA;34;0
"Unit";"Overlord";"Larva";49;0
"Building";"CreepTumor";NA;49;0
"Building";"Extractor";NA;51;0
"Building";"Extractor";NA;51;0
"Unit";"Zergling";"Larva";55;1
"Unit";"Zergling";"Larva";55;1
"Unit";"Zergling";"Larva";55;1
"Unit";"Zergling";"Larva";55;1
"Unit";"Zergling";"Larva";55;1
"Unit";"Zergling";"Larva";55;1
"Unit";"Queen";"Hatchery";52;2
"Unit";"Overlord";"Larva";66;0
"Unit";"Overlord";"Larva";66;0
"Unit";"Overlord";"Larva";67;0
"Unit";"Overlord";"Larva";67;0
"Building";"CreepTumorQueen";NA;71;0
"Building";"Spire";NA;55;0
"Unit";"Zergling";"Larva";71;1
"Unit";"Zergling";"Larva";71;1
"Unit";"Zergling";"Larva";71;1
"Unit";"Zergling";"Larva";71;1
"Unit";"Zergling";"Larva";71;1
"Unit";"Zergling";"Larva";71;1
"Unit";"Zergling";"Larva";71;1
"Unit";"Zergling";"Larva";71;1
"Unit";"Zergling";"Larva";71;1
"Unit";"Zergling";"Larva";71;1
"Unit";"Zergling";"Larva";71;1
"Unit";"Zergling";"Larva";71;1
"Unit";"Zergling";"Larva";71;1
"Unit";"Zergling";"Larva";71;1
"Unit";"Zergling";"Larva";71;1
"Unit";"Zergling";"Larva";71;1
"Unit";"Zergling";"Larva";71;1
"Unit";"Zergling";"Larva";71;1
"Unit";"Zergling";"Larva";71;1
"Unit";"Zergling";"Larva";71;1
"Unit";"Zergling";"Larva";71;1
"Unit";"Zergling";"Larva";71;1
"Unit";"Zergling";"Larva";71;1
"Unit";"Zergling";"Larva";71;1
"Unit";"Mutalisk";"Larva";71;2
"Unit";"Mutalisk";"Larva";71;2
"Unit";"Mutalisk";"Larva";71;2
"Unit";"Mutalisk";"Larva";71;2
"Unit";"Mutalisk";"Larva";71;2
"Unit";"Mutalisk";"Larva";71;2
"Unit";"Mutalisk";"Larva";71;2
"Building";"CreepTumor";NA;71;0
"Building";"EvolutionChamber";NA;71;0
"Building";"EvolutionChamber";NA;71;0
"Unit";"Mutalisk";"Larva";71;2
"Unit";"Mutalisk";"Larva";71;2
"Unit";"Overlord";"Larva";110;0
"Unit";"Overlord";"Larva";110;0
"Building";"HydraliskDen";NA;110;0
"Unit";"Mutalisk";"Larva";123;2
"Unit";"Mutalisk";"Larva";123;2
"Unit";"Mutalisk";"Larva";123;2
"Building";"Extractor";NA;123;0
"Building";"Extractor";NA;123;0
"Building";"CreepTumor";NA;136;0
"Unit";"Overlord";"Larva";136;0
"Unit";"Overlord";"Larva";136;0
"Unit";"Hydralisk";"Larva";142;2
"Unit";"Hydralisk";"Larva";142;2
"Unit";"Hydralisk";"Larva";142;2
"Unit";"Hydralisk";"Larva";142;2
"Unit";"Hydralisk";"Larva";142;2
"Unit";"Hydralisk";"Larva";142;2
"Unit";"Hydralisk";"Larva";142;2
"Unit";"Hydralisk";"Larva";142;2
"Building";"SpineCrawler";NA;142;0
"Building";"SpineCrawler";NA;142;0
"Building";"Hatchery";NA;136;0
"Unit";"Overlord";"Larva";158;0
"Unit";"Overlord";"Larva";158;0
"Building";"LurkerDenMP";NA;136;0
"Upgrade";"ZergMissileWeaponsLevel1";"EvolutionChamber";142;0
"Unit";"Overlord";"Larva";170;0
"Unit";"Overlord";"Larva";170;0
"Unit";"Overlord";"Larva";170;0
"Unit";"Hydralisk";"Larva";170;2
"Unit";"Hydralisk";"Larva";170;2
"Unit";"Queen";"Hatchery";158;2
"Building";"SporeCrawler";NA;170;0
"Upgrade";"EvolveGroovedSpines";"HydraliskDen";158;0
"Unit";"Hydralisk";"Larva";176;2
"Unit";"Hydralisk";"Larva";176;2
"Unit";"Hydralisk";"Larva";176;2
"Unit";"Hydralisk";"Larva";176;2
"Unit";"Hydralisk";"Larva";176;2
"Unit";"Hydralisk";"Larva";176;2
"Unit";"Hydralisk";"Larva";176;2
"Unit";"Hydralisk";"Larva";176;2
"Unit";"Hydralisk";"Larva";176;2
"Unit";"Hydralisk";"Larva";176;2
"Unit";"Hydralisk";"Larva";176;2
"Unit";"Hydralisk";"Larva";176;2
"Unit";"Hydralisk";"Larva";176;2
"Building";"Extractor";NA;176;0
"Building";"CreepTumor";NA;178;0
"Building";"Extractor";NA;176;0
"Building";"InfestationPit";NA;176;0
"Unit";"Overlord";"Larva";204;0
"Unit";"Overlord";"Larva";204;0
"Building";"CreepTumor";NA;204;0
"Building";"SporeCrawler";NA;204;0
"Upgrade";"ZergGroundArmorsLevel1";"EvolutionChamber";174;0
"Upgrade";"EvolveMuscularAugments";"HydraliskDen";204;0
"Building";"Hatchery";NA;204;0
"Unit";"Hydralisk";"Larva";206;2
"Unit";"Hydralisk";"Larva";206;2
"Unit";"Hydralisk";"Larva";206;2
"Unit";"Hydralisk";"Larva";206;2
"Unit";"Hydralisk";"Larva";206;2
"Unit";"Hydralisk";"Larva";206;2
"Unit";"Hydralisk";"Larva";206;2
"Unit";"Hydralisk";"Larva";220;2
"Unit";"Hydralisk";"Larva";220;2
"Unit";"Hydralisk";"Larva";220;2
"Unit";"Hydralisk";"Larva";220;2
"Unit";"Hydralisk";"Larva";220;2
"Unit";"Hydralisk";"Larva";220;2
"Unit";"Hydralisk";"Larva";232;2
"Unit";"Hydralisk";"Larva";232;2
"Unit";"Hydralisk";"Larva";232;2
"Unit";"Hydralisk";"Larva";232;2
"Unit";"Hydralisk";"Larva";232;2
"Unit";"Hydralisk";"Larva";232;2
"Unit";"Hydralisk";"Larva";232;2
"Unit";"Hydralisk";"Larva";232;2
"Unit";"Hydralisk";"Larva";232;2
"Unit";"Hydralisk";"Larva";232;2
"Unit";"Hydralisk";"Larva";232;2
"Unit";"Hydralisk";"Larva";232;2
"Unit";"Hydralisk";"Larva";232;2
"Unit";"Hydralisk";"Larva";232;2
"Unit";"Hydralisk";"Larva";232;2
"Unit";"Hydralisk";"Larva";232;2
"Unit";"Hydralisk";"Larva";232;2
