"type";"unit_name";"on_building";"total_supply_lag";"supply"
"Building";"Refinery";NA;15;0
"Building";"Barracks";NA;16;0
"Unit";"Reaper";"Barracks";19;1
"Building";"CommandCenter";NA;20;0
"Building";"Factory";NA;20;0
"Building";"Refinery";NA;21;0
"Building";"BarracksReactor";NA;21;0
"Building";"Starport";NA;24;0
"Unit";"Hellion";"Factory";24;2
"Unit";"Marine";"Barracks";26;1
"Unit";"Marine";"Barracks";27;1
"Unit";"Marine";"Barracks";30;1
"Unit";"Marine";"Barracks";31;1
"Building";"FactoryTechLab";NA;33;0
"Unit";"Marine";"Barracks";33;1
"Unit";"Marine";"Barracks";34;1
"Unit";"Marine";"Barracks";38;1
"Unit";"Marine";"Barracks";39;1
"Unit";"Raven";"Starport";40;2
"Building";"Refinery";NA;43;0
"Unit";"Cyclone";"Factory";43;3
"Unit";"Marine";"Barracks";47;1
"Unit";"Marine";"Barracks";48;1
"Unit";"Cyclone";"Factory";53;3
"Unit";"Marine";"Barracks";58;1
"Unit";"Marine";"Barracks";59;1
"Unit";"Raven";"Starport";60;2
"Building";"FactoryTechLab";NA;64;0
"Unit";"Marine";"Barracks";65;1
"Unit";"Marine";"Barracks";66;1
"Building";"CommandCenter";NA;70;0
"Unit";"Marine";"Barracks";74;1
"Building";"Barracks";NA;75;0
"Building";"Barracks";NA;75;0
"Unit";"Marine";"Barracks";77;1
"Building";"Refinery";NA;78;0
"Upgrade";"Stimpack";"TechLab";80;0
"Building";"EngineeringBay";NA;81;0
"Building";"EngineeringBay";NA;81;0
"Unit";"Marine";"Barracks";81;1
"Building";"Barracks";NA;83;0
"Building";"BarracksReactor";NA;83;0
"Building";"BarracksReactor";NA;83;0
"Building";"Barracks";NA;83;0
"Building";"MissileTurret";NA;85;0
"Unit";"Marine";"Barracks";88;1
"Unit";"Medivac";"Starport";91;2
"Unit";"Medivac";"Starport";93;2
"Unit";"Marine";"Barracks";95;1
"Unit";"Marine";"Barracks";96;1
"Building";"Refinery";NA;97;0
"Unit";"Marine";"Barracks";97;1
"Building";"Refinery";NA;99;0
"Building";"BarracksReactor";NA;99;0
"Building";"MissileTurret";NA;99;0
"Building";"BarracksReactor";NA;99;0
"Upgrade";"TerranInfantryWeaponsLevel1";"EngineeringBay";100;0
"Unit";"Marine";"Barracks";102;1
"Unit";"Marine";"Barracks";103;1
"Unit";"Marine";"Barracks";104;1
"Unit";"Marine";"Barracks";105;1
"Unit";"Marine";"Barracks";106;1
"Unit";"Marine";"Barracks";109;1
"Unit";"Marine";"Barracks";110;1
"Unit";"Marine";"Barracks";111;1
"Unit";"Marine";"Barracks";112;1
"Unit";"Marine";"Barracks";113;1
"Unit";"Marine";"Barracks";114;1
"Unit";"Marine";"Barracks";115;1
"Unit";"Marine";"Barracks";116;1
"Unit";"Medivac";"Starport";120;2
"Unit";"Marine";"Barracks";122;1
"Unit";"Marine";"Barracks";123;1
"Unit";"Marine";"Barracks";124;1
"Unit";"Marine";"Barracks";125;1
"Building";"Armory";NA;128;0
"Unit";"Marine";"Barracks";128;1
"Unit";"Marine";"Barracks";129;1
"Unit";"Marine";"Barracks";130;1
"Unit";"Medivac";"Starport";131;2
"Unit";"Marine";"Barracks";133;1
"Unit";"Marine";"Barracks";134;1
"Unit";"Marine";"Barracks";135;1
"Unit";"Marine";"Barracks";136;1
"Unit";"Marine";"Barracks";137;1
"Unit";"Marine";"Barracks";138;1
"Unit";"Marine";"Barracks";139;1
"Unit";"Marine";"Barracks";140;1
"Unit";"Marine";"Barracks";141;1
"Unit";"Marine";"Barracks";142;1
"Unit";"Marine";"Barracks";143;1
"Unit";"Marine";"Barracks";144;1
"Unit";"Marine";"Barracks";145;1
"Unit";"Marine";"Barracks";146;1
"Unit";"Marine";"Barracks";147;1
"Unit";"Marine";"Barracks";148;1
"Unit";"Marine";"Barracks";149;1
"Unit";"Marine";"Barracks";150;1
"Unit";"Marine";"Barracks";151;1
"Unit";"Medivac";"Starport";152;2
"Unit";"Medivac";"Starport";154;2
"Building";"Factory";NA;156;0
"Unit";"Marine";"Barracks";156;1
"Unit";"Marine";"Barracks";157;1
"Unit";"Marine";"Barracks";158;1
"Unit";"Marine";"Barracks";159;1
"Unit";"Marine";"Barracks";160;1
"Building";"BarracksReactor";NA;161;0
"Unit";"Marine";"Barracks";161;1
"Unit";"Marine";"Barracks";162;1
"Unit";"Marine";"Barracks";163;1
"Unit";"Medivac";"Starport";164;2
"Unit";"Medivac";"Starport";166;2
"Unit";"Marine";"Barracks";168;1
"Unit";"Marine";"Barracks";169;1
"Unit";"Marine";"Barracks";170;1
"Unit";"Marine";"Barracks";171;1
"Unit";"Marine";"Barracks";172;1
"Unit";"Marine";"Barracks";173;1
"Unit";"Marine";"Barracks";174;1
"Unit";"Marine";"Barracks";175;1
"Unit";"Marine";"Barracks";176;1
"Upgrade";"TerranInfantryWeaponsLevel2";"EngineeringBay";177;0
"Unit";"Marine";"Barracks";177;1
"Unit";"Marine";"Barracks";178;1
"Unit";"Marine";"Barracks";179;1
"Unit";"Marine";"Barracks";180;1
"Unit";"Marine";"Barracks";181;1
"Unit";"Marine";"Barracks";182;1
"Unit";"Marine";"Barracks";183;1
"Unit";"Medivac";"Starport";184;2
"Unit";"Marine";"Barracks";186;1
"Unit";"Marine";"Barracks";187;1
"Unit";"Marine";"Barracks";188;1
"Unit";"Marine";"Barracks";189;1
"Unit";"Marine";"Barracks";190;1
"Unit";"Marine";"Barracks";191;1
"Unit";"Marine";"Barracks";192;1
"Unit";"Marine";"Barracks";193;1
"Unit";"Marine";"Barracks";194;1
"Unit";"Marine";"Barracks";195;1
"Upgrade";"TerranVehicleWeaponsLevel1";"Armory";196;0
"Unit";"Medivac";"Starport";196;2
"Unit";"Marine";"Barracks";198;1
"Unit";"Marine";"Barracks";199;1
"Unit";"Marine";"Barracks";200;1
"Unit";"Marine";"Barracks";201;1
"Unit";"Marine";"Barracks";202;1
"Unit";"Marine";"Barracks";203;1
"Unit";"Marine";"Barracks";204;1
"Unit";"Medivac";"Starport";205;2
"Unit";"Marine";"Barracks";207;1
"Unit";"Marine";"Barracks";208;1
"Unit";"Marine";"Barracks";209;1
"Unit";"Marine";"Barracks";210;1
"Unit";"Marine";"Barracks";211;1
"Unit";"Marine";"Barracks";212;1
"Unit";"Marine";"Barracks";213;1
"Unit";"Marine";"Barracks";214;1
"Unit";"Marine";"Barracks";215;1
"Unit";"Medivac";"Starport";216;2
"Unit";"Medivac";"Starport";218;2
"Unit";"Marine";"Barracks";220;1
"Unit";"Marine";"Barracks";221;1
"Unit";"Marine";"Barracks";222;1
"Unit";"Marine";"Barracks";223;1
"Unit";"Marine";"Barracks";224;1
"Unit";"Marine";"Barracks";225;1
"Unit";"Marine";"Barracks";226;1
"Unit";"Medivac";"Starport";227;2
"Building";"CommandCenter";NA;229;0
"Unit";"Marine";"Barracks";229;1
"Unit";"Marine";"Barracks";230;1
"Unit";"Marine";"Barracks";231;1
"Unit";"Marine";"Barracks";232;1
"Unit";"Marine";"Barracks";233;1
"Unit";"Marine";"Barracks";234;1
"Unit";"Marine";"Barracks";235;1
"Unit";"Marine";"Barracks";236;1
"Unit";"Marine";"Barracks";237;1
"Unit";"Marine";"Barracks";238;1
"Unit";"Marine";"Barracks";239;1
"Unit";"Marine";"Barracks";240;1
"Unit";"Marine";"Barracks";241;1
"Unit";"Marine";"Barracks";242;1
"Unit";"Marine";"Barracks";243;1
"Unit";"Marine";"Barracks";244;1
"Unit";"Marine";"Barracks";245;1
"Unit";"Marine";"Barracks";246;1
"Unit";"Marine";"Barracks";247;1
"Unit";"Marine";"Barracks";248;1
"Upgrade";"SprayTerran";NA;249;0
"Upgrade";"SprayTerran";NA;249;0
"Upgrade";"SprayTerran";NA;249;0
"Upgrade";"SprayTerran";NA;249;0
"Upgrade";"TerranInfantryArmorsLevel1";NA;249;0
"Upgrade";"ShieldWall";NA;249;0
"Upgrade";"TerranInfantryArmorsLevel2";NA;249;0
"Upgrade";"SprayTerran";NA;249;0
"Upgrade";"SprayTerran";NA;249;0
