"type";"unit_name";"on_building";"total_supply_lag"
"Building";"Refinery";NA;15
"Building";"Barracks";NA;16
"Unit";"Reaper";"Barracks";19
"Building";"CommandCenter";NA;20
"Building";"Factory";NA;20
"Building";"Refinery";NA;21
"Building";"BarracksReactor";NA;21
"Building";"Starport";NA;24
"Unit";"Hellion";"Factory";24
"Unit";"Marine";"Barracks";26
"Unit";"Marine";"Barracks";27
"Unit";"Marine";"Barracks";30
"Unit";"Marine";"Barracks";31
"Building";"FactoryTechLab";NA;33
"Unit";"Marine";"Barracks";33
"Unit";"Marine";"Barracks";34
"Unit";"Marine";"Barracks";38
"Unit";"Marine";"Barracks";39
"Unit";"Raven";"Starport";40
"Building";"Refinery";NA;43
"Unit";"Cyclone";"Factory";43
"Unit";"Marine";"Barracks";47
"Unit";"Marine";"Barracks";48
"Unit";"Cyclone";"Factory";53
"Unit";"Marine";"Barracks";58
"Unit";"Marine";"Barracks";59
"Unit";"Raven";"Starport";60
"Building";"FactoryTechLab";NA;64
"Unit";"Marine";"Barracks";65
"Unit";"Marine";"Barracks";66
"Building";"CommandCenter";NA;70
"Unit";"Marine";"Barracks";74
"Building";"Barracks";NA;75
"Building";"Barracks";NA;75
"Unit";"Marine";"Barracks";77
"Building";"Refinery";NA;78
"Upgrade";"Stimpack";"TechLab";80
"Building";"EngineeringBay";NA;81
"Building";"EngineeringBay";NA;81
"Unit";"Marine";"Barracks";81
"Building";"Barracks";NA;83
"Building";"BarracksReactor";NA;83
"Building";"BarracksReactor";NA;83
"Building";"Barracks";NA;83
"Building";"MissileTurret";NA;85
"Unit";"Marine";"Barracks";88
"Unit";"Medivac";"Starport";91
"Unit";"Medivac";"Starport";93
"Unit";"Marine";"Barracks";95
"Unit";"Marine";"Barracks";96
"Building";"Refinery";NA;97
"Unit";"Marine";"Barracks";97
"Building";"Refinery";NA;99
"Building";"BarracksReactor";NA;99
"Building";"MissileTurret";NA;99
"Building";"BarracksReactor";NA;99
"Upgrade";"TerranInfantryWeaponsLevel1";"EngineeringBay";100
"Unit";"Marine";"Barracks";102
"Unit";"Marine";"Barracks";103
"Unit";"Marine";"Barracks";104
"Unit";"Marine";"Barracks";105
"Unit";"Marine";"Barracks";106
"Unit";"Marine";"Barracks";109
"Unit";"Marine";"Barracks";110
"Unit";"Marine";"Barracks";111
"Unit";"Marine";"Barracks";112
"Unit";"Marine";"Barracks";113
"Unit";"Marine";"Barracks";114
"Unit";"Marine";"Barracks";115
"Unit";"Marine";"Barracks";116
"Unit";"Medivac";"Starport";120
"Unit";"Marine";"Barracks";122
"Unit";"Marine";"Barracks";123
"Unit";"Marine";"Barracks";124
"Unit";"Marine";"Barracks";125
"Building";"Armory";NA;128
"Unit";"Marine";"Barracks";128
"Unit";"Marine";"Barracks";129
"Unit";"Marine";"Barracks";130
"Unit";"Medivac";"Starport";131
"Unit";"Marine";"Barracks";133
"Unit";"Marine";"Barracks";134
"Unit";"Marine";"Barracks";135
"Unit";"Marine";"Barracks";136
"Unit";"Marine";"Barracks";137
"Unit";"Marine";"Barracks";138
"Unit";"Marine";"Barracks";139
"Unit";"Marine";"Barracks";140
"Unit";"Marine";"Barracks";141
"Unit";"Marine";"Barracks";142
"Unit";"Marine";"Barracks";143
"Unit";"Marine";"Barracks";144
"Unit";"Marine";"Barracks";145
"Unit";"Marine";"Barracks";146
"Unit";"Marine";"Barracks";147
"Unit";"Marine";"Barracks";148
"Unit";"Marine";"Barracks";149
"Unit";"Marine";"Barracks";150
"Unit";"Marine";"Barracks";151
"Unit";"Medivac";"Starport";152
"Unit";"Medivac";"Starport";154
"Building";"Factory";NA;156
"Unit";"Marine";"Barracks";156
"Unit";"Marine";"Barracks";157
"Unit";"Marine";"Barracks";158
"Unit";"Marine";"Barracks";159
"Unit";"Marine";"Barracks";160
"Building";"BarracksReactor";NA;161
"Unit";"Marine";"Barracks";161
"Unit";"Marine";"Barracks";162
"Unit";"Marine";"Barracks";163
"Unit";"Medivac";"Starport";164
"Unit";"Medivac";"Starport";166
"Unit";"Marine";"Barracks";168
"Unit";"Marine";"Barracks";169
"Unit";"Marine";"Barracks";170
"Unit";"Marine";"Barracks";171
"Unit";"Marine";"Barracks";172
"Unit";"Marine";"Barracks";173
"Unit";"Marine";"Barracks";174
"Unit";"Marine";"Barracks";175
"Unit";"Marine";"Barracks";176
"Upgrade";"TerranInfantryWeaponsLevel2";"EngineeringBay";177
"Unit";"Marine";"Barracks";177
"Unit";"Marine";"Barracks";178
"Unit";"Marine";"Barracks";179
"Unit";"Marine";"Barracks";180
"Unit";"Marine";"Barracks";181
"Unit";"Marine";"Barracks";182
"Unit";"Marine";"Barracks";183
"Unit";"Medivac";"Starport";184
"Unit";"Marine";"Barracks";186
"Unit";"Marine";"Barracks";187
"Unit";"Marine";"Barracks";188
"Unit";"Marine";"Barracks";189
"Unit";"Marine";"Barracks";190
"Unit";"Marine";"Barracks";191
"Unit";"Marine";"Barracks";192
"Unit";"Marine";"Barracks";193
"Unit";"Marine";"Barracks";194
"Unit";"Marine";"Barracks";195
"Upgrade";"TerranVehicleWeaponsLevel1";"Armory";196
"Unit";"Medivac";"Starport";196
"Unit";"Marine";"Barracks";198
"Unit";"Marine";"Barracks";199
"Unit";"Marine";"Barracks";200
"Unit";"Marine";"Barracks";201
"Unit";"Marine";"Barracks";202
"Unit";"Marine";"Barracks";203
"Unit";"Marine";"Barracks";204
"Unit";"Medivac";"Starport";205
"Unit";"Marine";"Barracks";207
"Unit";"Marine";"Barracks";208
"Unit";"Marine";"Barracks";209
"Unit";"Marine";"Barracks";210
"Unit";"Marine";"Barracks";211
"Unit";"Marine";"Barracks";212
"Unit";"Marine";"Barracks";213
"Unit";"Marine";"Barracks";214
"Unit";"Marine";"Barracks";215
"Unit";"Medivac";"Starport";216
"Unit";"Medivac";"Starport";218
"Unit";"Marine";"Barracks";220
"Unit";"Marine";"Barracks";221
"Unit";"Marine";"Barracks";222
"Unit";"Marine";"Barracks";223
"Unit";"Marine";"Barracks";224
"Unit";"Marine";"Barracks";225
"Unit";"Marine";"Barracks";226
"Unit";"Medivac";"Starport";227
"Building";"CommandCenter";NA;229
"Unit";"Marine";"Barracks";229
"Unit";"Marine";"Barracks";230
"Unit";"Marine";"Barracks";231
"Unit";"Marine";"Barracks";232
"Unit";"Marine";"Barracks";233
"Unit";"Marine";"Barracks";234
"Unit";"Marine";"Barracks";235
"Unit";"Marine";"Barracks";236
"Unit";"Marine";"Barracks";237
"Unit";"Marine";"Barracks";238
"Unit";"Marine";"Barracks";239
"Unit";"Marine";"Barracks";240
"Unit";"Marine";"Barracks";241
"Unit";"Marine";"Barracks";242
"Unit";"Marine";"Barracks";243
"Unit";"Marine";"Barracks";244
"Unit";"Marine";"Barracks";245
"Unit";"Marine";"Barracks";246
"Unit";"Marine";"Barracks";247
"Unit";"Marine";"Barracks";248
"Upgrade";"SprayTerran";NA;249
"Upgrade";"SprayTerran";NA;249
"Upgrade";"SprayTerran";NA;249
"Upgrade";"SprayTerran";NA;249
"Upgrade";"TerranInfantryArmorsLevel1";NA;249
"Upgrade";"ShieldWall";NA;249
"Upgrade";"TerranInfantryArmorsLevel2";NA;249
"Upgrade";"SprayTerran";NA;249
"Upgrade";"SprayTerran";NA;249
