"type";"unit_name";"on_building";"total_supply";"supply"
"Building";"Extractor";NA;13;0
"Unit";"Overlord";"Larva";16;0
"Building";"SpawningPool";NA;15;0
"Unit";"Zergling";"Larva";17;1
"Unit";"Zergling";"Larva";17;1
"Unit";"Zergling";"Larva";17;1
"Unit";"Zergling";"Larva";17;1
"Unit";"Zergling";"Larva";17;1
"Unit";"Zergling";"Larva";17;1
"Unit";"Zergling";"Larva";17;1
"Unit";"Zergling";"Larva";17;1
"Unit";"Queen";"Hatchery";17;2
"Unit";"Overlord";"Larva";28;0
"Building";"BanelingNest";NA;28;0
"Unit";"Zergling";"Larva";29;1
"Unit";"Zergling";"Larva";29;1
"Unit";"Zergling";"Larva";29;1
"Unit";"Zergling";"Larva";29;1
"Unit";"Zergling";"Larva";29;1
"Unit";"Zergling";"Larva";29;1
"Unit";"Zergling";"Larva";29;1
"Unit";"Zergling";"Larva";29;1
"Unit";"Zergling";"Larva";29;1
"Unit";"Zergling";"Larva";29;1
"Unit";"Zergling";"Larva";29;1
"Unit";"Zergling";"Larva";29;1
"Unit";"Baneling";"Zergling";29;0
"Unit";"Baneling";"Zergling";29;0
"Unit";"Baneling";"Zergling";29;0
"Unit";"Baneling";"Zergling";29;0
"Unit";"Baneling";"Zergling";29;0
"Unit";"Zergling";"Larva";41;1
"Unit";"Zergling";"Larva";41;1
"Unit";"Zergling";"Larva";41;1
"Unit";"Zergling";"Larva";41;1
"Unit";"Queen";"Hatchery";29;2
"Unit";"Zergling";"Larva";41;1
"Unit";"Zergling";"Larva";41;1
"Unit";"Zergling";"Larva";41;1
"Unit";"Zergling";"Larva";41;1
"Unit";"Zergling";"Larva";41;1
"Unit";"Zergling";"Larva";41;1
"Unit";"Baneling";"Zergling";45;0
"Unit";"Baneling";"Zergling";45;0
"Unit";"Zergling";"Larva";47;1
"Unit";"Zergling";"Larva";47;1
"Unit";"Zergling";"Larva";53;1
"Unit";"Zergling";"Larva";53;1
"Building";"EvolutionChamber";NA;57;0
"Unit";"Overlord";"Larva";62;0
"Unit";"Baneling";"Zergling";62;0
"Unit";"Zergling";"Larva";62;1
"Unit";"Zergling";"Larva";62;1
"Unit";"Baneling";"Zergling";62;0
"Unit";"Baneling";"Zergling";62;0
"Unit";"Zergling";"Larva";62;1
"Unit";"Zergling";"Larva";62;1
"Unit";"Queen";"Hatchery";62;2
"Building";"Hatchery";NA;57;0
"Unit";"Zergling";"Larva";68;1
"Unit";"Zergling";"Larva";68;1
"Building";"CreepTumorQueen";NA;68;0
"Unit";"Zergling";"Larva";68;1
"Unit";"Zergling";"Larva";68;1
"Unit";"Zergling";"Larva";68;1
"Unit";"Zergling";"Larva";68;1
"Unit";"Zergling";"Larva";68;1
"Unit";"Zergling";"Larva";68;1
"Unit";"Zergling";"Larva";68;1
"Unit";"Zergling";"Larva";68;1
"Unit";"Zergling";"Larva";68;1
"Unit";"Zergling";"Larva";68;1
"Unit";"Overlord";"Larva";84;0
"Unit";"Zergling";"Larva";86;1
"Unit";"Zergling";"Larva";86;1
"Unit";"Zergling";"Larva";86;1
"Unit";"Zergling";"Larva";86;1
"Unit";"Zergling";"Larva";86;1
"Unit";"Zergling";"Larva";86;1
"Unit";"Zergling";"Larva";86;1
"Unit";"Zergling";"Larva";86;1
"Unit";"Zergling";"Larva";86;1
"Unit";"Zergling";"Larva";86;1
"Unit";"Zergling";"Larva";86;1
"Unit";"Zergling";"Larva";86;1
"Unit";"Zergling";"Larva";86;1
"Unit";"Zergling";"Larva";86;1
"Unit";"Zergling";"Larva";86;1
"Unit";"Zergling";"Larva";86;1
"Unit";"Zergling";"Larva";86;1
"Unit";"Zergling";"Larva";86;1
"Building";"CreepTumor";NA;96;0
"Upgrade";"ZergGroundArmorsLevel1";"EvolutionChamber";72;0
"Building";"RoachWarren";NA;96;0
"Unit";"Overlord";"Larva";108;0
"Unit";"Overlord";"Larva";108;0
"Unit";"Overlord";"Larva";108;0
"Unit";"Roach";"Larva";108;2
"Unit";"Roach";"Larva";108;2
"Unit";"Roach";"Larva";108;2
"Unit";"Roach";"Larva";108;2
"Unit";"Roach";"Larva";111;2
"Unit";"Roach";"Larva";111;2
"Unit";"Roach";"Larva";111;2
"Unit";"Roach";"Larva";119;2
"Unit";"Roach";"Larva";121;2
"Unit";"Roach";"Larva";121;2
"Unit";"Roach";"Larva";121;2
"Unit";"Overlord";"Larva";129;0
"Unit";"Roach";"Larva";129;2
"Unit";"Roach";"Larva";130;2
"Unit";"Roach";"Larva";130;2
"Unit";"Roach";"Larva";136;2
"Unit";"Roach";"Larva";136;2
"Building";"Hatchery";NA;119;0
"Building";"Extractor";NA;147;0
"Building";"Extractor";NA;147;0
"Unit";"Overlord";"Larva";153;0
"Unit";"Zergling";"Larva";153;1
"Unit";"Zergling";"Larva";153;1
"Unit";"Zergling";"Larva";153;1
"Unit";"Zergling";"Larva";153;1
"Unit";"Zergling";"Larva";153;1
"Unit";"Zergling";"Larva";153;1
"Unit";"Zergling";"Larva";153;1
"Unit";"Zergling";"Larva";153;1
"Unit";"Zergling";"Larva";153;1
"Unit";"Zergling";"Larva";153;1
"Unit";"Roach";"Larva";155;2
"Unit";"Roach";"Larva";155;2
"Unit";"Roach";"Larva";155;2
"Unit";"Overlord";"Larva";155;0
"Building";"CreepTumor";NA;167;0
"Building";"Extractor";NA;167;0
"Unit";"Queen";"Hatchery";155;2
"Unit";"Overlord";"Larva";167;0
"Unit";"Roach";"Larva";167;2
"Unit";"Roach";"Larva";167;2
"Unit";"Roach";"Larva";167;2
"Upgrade";"ZergMissileWeaponsLevel1";"EvolutionChamber";142;0
"Unit";"Roach";"Larva";176;2
"Unit";"Roach";"Larva";176;2
"Unit";"Overlord";"Larva";179;0
"Unit";"Overlord";"Larva";182;0
"Building";"Extractor";NA;187;0
"Unit";"Roach";"Larva";191;2
"Unit";"Roach";"Larva";191;2
"Unit";"Roach";"Larva";191;2
"Unit";"Roach";"Larva";194;2
"Unit";"Roach";"Larva";195;2
"Unit";"Roach";"Larva";199;2
"Unit";"Roach";"Larva";199;2
"Unit";"Roach";"Larva";199;2
"Unit";"Roach";"Larva";199;2
"Unit";"Roach";"Larva";199;2
"Unit";"Roach";"Larva";199;2
