"type";"unit_name";"on_building";"total_supply_lag";"supply"
"Unit";"Overlord";"Larva";13;0
"Building";"SpawningPool";NA;17;0
"Building";"Extractor";NA;18;0
"Building";"Hatchery";NA;19;0
"Unit";"Zergling";"Larva";19;1
"Unit";"Zergling";"Larva";20;1
"Unit";"Queen";"Hatchery";21;2
"Unit";"Zergling";"Larva";23;1
"Unit";"Zergling";"Larva";24;1
"Unit";"Zergling";"Larva";25;1
"Unit";"Zergling";"Larva";26;1
"Unit";"Zergling";"Larva";27;1
"Unit";"Zergling";"Larva";28;1
"Unit";"Overlord";"Larva";29;0
"Unit";"Zergling";"Larva";29;1
"Unit";"Zergling";"Larva";30;1
"Unit";"Zergling";"Larva";31;1
"Unit";"Zergling";"Larva";32;1
"Unit";"Zergling";"Larva";33;1
"Unit";"Zergling";"Larva";34;1
"Unit";"Queen";"Hatchery";38;2
"Unit";"Overlord";"Larva";45;0
"Unit";"Queen";"Hatchery";46;2
"Unit";"Overlord";"Larva";49;0
"Building";"Hatchery";NA;57;0
"Building";"CreepTumorQueen";NA;62;0
"Building";"Extractor";NA;62;0
"Unit";"Overlord";"Larva";63;0
"Building";"EvolutionChamber";NA;67;0
"Building";"Extractor";NA;67;0
"Building";"CreepTumor";NA;72;0
"Building";"RoachWarren";NA;72;0
"Unit";"Queen";"Hatchery";72;2
"Unit";"Overlord";"Larva";74;0
"Unit";"Overlord";"Larva";78;0
"Building";"CreepTumor";NA;84;0
"Unit";"Overlord";"Larva";84;0
"Unit";"Roach";"Larva";84;2
"Unit";"Roach";"Larva";86;2
"Unit";"Roach";"Larva";88;2
"Unit";"Roach";"Larva";90;2
"Unit";"Roach";"Larva";92;2
"Unit";"Roach";"Larva";94;2
"Unit";"Roach";"Larva";96;2
"Unit";"Overlord";"Larva";98;0
"Unit";"Roach";"Larva";98;2
"Unit";"Roach";"Larva";100;2
"Unit";"Overlord";"Larva";102;0
"Building";"CreepTumorQueen";NA;103;0
"Building";"Extractor";NA;103;0
"Unit";"Overlord";"Larva";103;0
"Unit";"Roach";"Larva";103;2
"Unit";"Roach";"Larva";105;2
"Unit";"Roach";"Larva";107;2
"Unit";"Overlord";"Larva";109;0
"Unit";"Roach";"Larva";109;2
"Building";"CreepTumor";NA;112;0
"Unit";"Roach";"Larva";112;2
"Unit";"Roach";"Larva";114;2
"Unit";"Roach";"Larva";116;2
"Unit";"Roach";"Larva";118;2
"Unit";"Roach";"Larva";120;2
"Unit";"Overlord";"Larva";122;0
"Unit";"Roach";"Larva";122;2
"Unit";"Roach";"Larva";124;2
"Unit";"Roach";"Larva";126;2
"Unit";"Roach";"Larva";128;2
"Unit";"Roach";"Larva";130;2
"Unit";"Roach";"Larva";132;2
"Unit";"Roach";"Larva";134;2
"Building";"Extractor";NA;136;0
"Building";"CreepTumor";NA;136;0
"Building";"CreepTumor";NA;136;0
"Unit";"Overlord";"Larva";136;0
"Upgrade";"GlialReconstitution";"RoachWarren";142;0
"Unit";"Overlord";"Larva";142;0
"Unit";"Roach";"Larva";142;2
"Unit";"Roach";"Larva";144;2
"Unit";"Roach";"Larva";146;2
"Unit";"Roach";"Larva";148;2
"Unit";"Roach";"Larva";150;2
"Unit";"Overlord";"Larva";152;0
"Unit";"Roach";"Larva";152;2
"Unit";"Roach";"Larva";154;2
"Unit";"Roach";"Larva";156;2
"Unit";"Roach";"Larva";158;2
"Unit";"Overlord";"Larva";160;0
"Unit";"Overlord";"Larva";160;0
"Unit";"Roach";"Larva";160;2
"Unit";"Roach";"Larva";162;2
"Unit";"Roach";"Larva";164;2
"Unit";"Roach";"Larva";166;2
"Unit";"Roach";"Larva";168;2
"Unit";"Roach";"Larva";170;2
"Unit";"Roach";"Larva";172;2
"Unit";"Roach";"Larva";174;2
"Unit";"Roach";"Larva";176;2
"Unit";"Roach";"Larva";178;2
"Unit";"Roach";"Larva";180;2
"Unit";"Roach";"Larva";182;2
"Unit";"Roach";"Larva";184;2
"Unit";"Roach";"Larva";186;2
"Unit";"Roach";"Larva";188;2
"Unit";"Roach";"Larva";190;2
"Unit";"Roach";"Larva";192;2
"Unit";"Roach";"Larva";194;2
"Unit";"Roach";"Larva";196;2
"Unit";"Roach";"Larva";198;2
"Unit";"Roach";"Larva";200;2
"Unit";"Overlord";"Larva";202;0
"Unit";"Overlord";"Larva";202;0
"Unit";"Overlord";"Larva";202;0
"Building";"Hatchery";NA;202;0
"Building";"EvolutionChamber";NA;202;0
"Unit";"Roach";"Larva";206;2
"Unit";"Roach";"Larva";208;2
"Unit";"Roach";"Larva";210;2
"Unit";"Roach";"Larva";212;2
"Unit";"Roach";"Larva";214;2
"Unit";"Roach";"Larva";216;2
"Unit";"Roach";"Larva";218;2
"Unit";"Roach";"Larva";220;2
"Unit";"Overlord";"Larva";222;0
"Unit";"Overlord";"Larva";222;0
"Unit";"Roach";"Larva";222;2
"Upgrade";"Burrow";"Hatchery";224;0
"Unit";"Roach";"Larva";224;2
"Upgrade";"TunnelingClaws";"RoachWarren";226;0
"Unit";"Roach";"Larva";226;2
"Unit";"Overlord";"Larva";228;0
"Unit";"Overlord";"Larva";228;0
"Unit";"Overlord";"Larva";228;0
"Unit";"Overlord";"Larva";228;0
"Unit";"Roach";"Larva";228;2
"Unit";"Roach";"Larva";230;2
"Unit";"Roach";"Larva";232;2
"Unit";"Roach";"Larva";234;2
"Unit";"Roach";"Larva";236;2
"Unit";"Overlord";"Larva";238;0
"Unit";"Roach";"Larva";238;2
"Unit";"Roach";"Larva";240;2
"Unit";"Roach";"Larva";242;2
"Unit";"Overlord";"Larva";244;0
"Unit";"Roach";"Larva";244;2
"Unit";"Roach";"Larva";246;2
"Unit";"Roach";"Larva";248;2
"Unit";"Roach";"Larva";250;2
"Unit";"Roach";"Larva";252;2
"Unit";"Roach";"Larva";254;2
"Unit";"Roach";"Larva";256;2
"Unit";"Roach";"Larva";258;2
"Unit";"Roach";"Larva";260;2
"Unit";"Roach";"Larva";262;2
"Unit";"Roach";"Larva";264;2
"Unit";"Roach";"Larva";266;2
"Unit";"Roach";"Larva";268;2
"Unit";"Roach";"Larva";270;2
"Unit";"Roach";"Larva";272;2
"Unit";"Roach";"Larva";274;2
"Unit";"Roach";"Larva";276;2
"Unit";"Roach";"Larva";278;2
"Unit";"Roach";"Larva";280;2
"Unit";"Roach";"Larva";282;2
"Unit";"Roach";"Larva";284;2
"Unit";"Roach";"Larva";286;2
"Unit";"Roach";"Larva";288;2
"Building";"Extractor";NA;290;0
"Building";"Extractor";NA;290;0
"Upgrade";"SprayZerg";NA;290;0
"Upgrade";"SprayZerg";NA;290;0
"Upgrade";"zerglingmovementspeed";NA;290;0
"Upgrade";"SprayZerg";NA;290;0
"Upgrade";"SprayZerg";NA;290;0
"Upgrade";"ZergMissileWeaponsLevel1";NA;290;0
"Upgrade";"SprayZerg";NA;290;0
"Upgrade";"ZergMissileWeaponsLevel2";NA;290;0
"Upgrade";"SprayZerg";NA;290;0
