"type";"unit_name";"on_building";"total_supply";"supply"
"Unit";"Overlord";"Larva";13;0
"Building";"Extractor";NA;17;0
"Building";"SpawningPool";NA;16;0
"Unit";"Overlord";"Larva";19;0
"Unit";"Zergling";"Larva";20;1
"Unit";"Zergling";"Larva";20;1
"Unit";"Zergling";"Larva";20;1
"Unit";"Zergling";"Larva";20;1
"Unit";"Zergling";"Larva";24;1
"Unit";"Zergling";"Larva";24;1
"Unit";"Queen";"Hatchery";20;2
"Unit";"Zergling";"Larva";24;1
"Unit";"Zergling";"Larva";24;1
"Unit";"Zergling";"Larva";24;1
"Unit";"Zergling";"Larva";24;1
"Unit";"Zergling";"Larva";30;1
"Unit";"Zergling";"Larva";30;1
"Unit";"Zergling";"Larva";32;1
"Unit";"Zergling";"Larva";32;1
"Building";"BanelingNest";NA;24;0
"Building";"Hatchery";NA;20;0
"Unit";"Baneling";"Zergling";36;0
"Unit";"Zergling";"Larva";36;1
"Unit";"Zergling";"Larva";36;1
"Unit";"Baneling";"Zergling";36;0
"Unit";"Baneling";"Zergling";36;0
"Unit";"Zergling";"Larva";36;1
"Unit";"Zergling";"Larva";36;1
"Unit";"Zergling";"Larva";36;1
"Unit";"Zergling";"Larva";36;1
"Unit";"Zergling";"Larva";36;1
"Unit";"Zergling";"Larva";36;1
"Unit";"Baneling";"Zergling";36;0
"Unit";"Baneling";"Zergling";36;0
"Unit";"Baneling";"Zergling";36;0
"Unit";"Zergling";"Larva";36;1
"Unit";"Zergling";"Larva";36;1
"Unit";"Zergling";"Larva";44;1
"Unit";"Zergling";"Larva";44;1
"Unit";"Zergling";"Larva";44;1
"Unit";"Zergling";"Larva";44;1
"Unit";"Zergling";"Larva";46;1
"Unit";"Zergling";"Larva";46;1
"Unit";"Zergling";"Larva";46;1
"Unit";"Zergling";"Larva";46;1
"Unit";"Zergling";"Larva";46;1
"Unit";"Zergling";"Larva";46;1
"Unit";"Queen";"Hatchery";36;2
"Unit";"Baneling";"Zergling";46;0
"Unit";"Baneling";"Zergling";48;0
"Unit";"Baneling";"Zergling";48;0
"Unit";"Overlord";"Larva";58;0
"Unit";"Overlord";"Larva";60;0
"Unit";"Baneling";"Zergling";67;0
"Building";"EvolutionChamber";NA;62;0
"Unit";"Zergling";"Larva";73;1
"Unit";"Zergling";"Larva";73;1
"Unit";"Zergling";"Larva";73;1
"Unit";"Zergling";"Larva";73;1
"Unit";"Zergling";"Larva";73;1
"Unit";"Zergling";"Larva";73;1
"Unit";"Zergling";"Larva";73;1
"Unit";"Zergling";"Larva";73;1
"Unit";"Zergling";"Larva";73;1
"Unit";"Zergling";"Larva";73;1
"Unit";"Zergling";"Larva";73;1
"Unit";"Zergling";"Larva";73;1
"Unit";"Zergling";"Larva";73;1
"Unit";"Zergling";"Larva";73;1
"Building";"Extractor";NA;73;0
"Unit";"Overlord";"Larva";73;0
"Building";"Hatchery";NA;68;0
"Unit";"Overlord";"Larva";87;0
"Building";"RoachWarren";NA;87;0
"Unit";"Queen";"Hatchery";89;2
"Unit";"Roach";"Larva";93;2
"Unit";"Roach";"Larva";93;2
"Unit";"Roach";"Larva";93;2
"Unit";"Roach";"Larva";93;2
"Unit";"Roach";"Larva";93;2
"Unit";"Roach";"Larva";93;2
"Unit";"Roach";"Larva";93;2
"Unit";"Roach";"Larva";93;2
"Unit";"Roach";"Larva";93;2
"Unit";"Roach";"Larva";95;2
"Unit";"Roach";"Larva";111;2
"Unit";"Zergling";"Larva";111;1
"Unit";"Zergling";"Larva";111;1
"Unit";"Zergling";"Larva";111;1
"Unit";"Zergling";"Larva";111;1
"Unit";"Zergling";"Larva";111;1
"Unit";"Zergling";"Larva";111;1
"Unit";"Zergling";"Larva";111;1
"Unit";"Zergling";"Larva";111;1
"Unit";"Zergling";"Larva";111;1
"Unit";"Zergling";"Larva";111;1
"Unit";"Zergling";"Larva";111;1
"Unit";"Zergling";"Larva";111;1
"Unit";"Zergling";"Larva";111;1
"Unit";"Zergling";"Larva";111;1
"Unit";"Overlord";"Larva";113;0
"Unit";"Overlord";"Larva";113;0
"Upgrade";"ZergGroundArmorsLevel1";"EvolutionChamber";89;0
"Building";"Extractor";NA;131;0
"Building";"Extractor";NA;131;0
"Unit";"Roach";"Larva";131;2
"Unit";"Roach";"Larva";131;2
"Unit";"Roach";"Larva";131;2
"Unit";"Roach";"Larva";146;2
"Unit";"Roach";"Larva";146;2
"Unit";"Roach";"Larva";146;2
"Unit";"Roach";"Larva";146;2
"Unit";"Roach";"Larva";146;2
"Upgrade";"GlialReconstitution";"RoachWarren";134;0
"Unit";"Roach";"Larva";152;2
"Unit";"Roach";"Larva";156;2
"Unit";"Roach";"Larva";156;2
"Unit";"Overlord";"Larva";156;0
"Unit";"Overlord";"Larva";156;0
"Unit";"Overlord";"Larva";156;0
"Unit";"Queen";"Hatchery";152;2
"Unit";"Roach";"Larva";158;2
"Unit";"Roach";"Larva";162;2
"Unit";"Roach";"Larva";162;2
"Unit";"Roach";"Larva";162;2
"Unit";"Roach";"Larva";162;2
"Unit";"Roach";"Larva";162;2
"Unit";"Roach";"Larva";162;2
"Unit";"Roach";"Larva";162;2
"Unit";"Roach";"Larva";162;2
"Unit";"Roach";"Larva";168;2
"Unit";"Roach";"Larva";176;2
"Unit";"Roach";"Larva";176;2
"Unit";"Roach";"Larva";180;2
"Upgrade";"ZergMissileWeaponsLevel1";"EvolutionChamber";152;0
"Unit";"Roach";"Larva";182;2
"Unit";"Roach";"Larva";182;2
"Unit";"Roach";"Larva";182;2
"Unit";"Roach";"Larva";182;2
"Unit";"Roach";"Larva";198;2
"Unit";"Roach";"Larva";198;2
"Unit";"Roach";"Larva";198;2
"Unit";"Roach";"Larva";198;2
"Unit";"Roach";"Larva";198;2
"Unit";"Roach";"Larva";198;2
"Unit";"Roach";"Larva";198;2
"Unit";"Roach";"Larva";198;2
"Unit";"Roach";"Larva";198;2
"Unit";"Roach";"Larva";198;2
"Unit";"Roach";"Larva";198;2
"Unit";"Roach";"Larva";200;2
"Unit";"Roach";"Larva";218;2
"Unit";"Roach";"Larva";218;2
"Unit";"Roach";"Larva";218;2
"Unit";"Roach";"Larva";218;2
"Unit";"Roach";"Larva";226;2
"Unit";"Roach";"Larva";226;2
"Unit";"Roach";"Larva";226;2
"Unit";"Roach";"Larva";236;2
"Unit";"Roach";"Larva";236;2
"Unit";"Roach";"Larva";236;2
"Unit";"Roach";"Larva";236;2
"Unit";"Roach";"Larva";236;2
"Unit";"Roach";"Larva";236;2
"Unit";"Roach";"Larva";236;2
"Unit";"Roach";"Larva";244;2
"Unit";"Roach";"Larva";244;2
"Unit";"Roach";"Larva";244;2
"Unit";"Roach";"Larva";244;2
"Unit";"Roach";"Larva";258;2
"Unit";"Roach";"Larva";258;2
"Unit";"Roach";"Larva";258;2
"Unit";"Roach";"Larva";258;2
"Unit";"Roach";"Larva";266;2
"Unit";"Roach";"Larva";266;2
"Unit";"Roach";"Larva";266;2
"Unit";"Roach";"Larva";272;2
"Unit";"Roach";"Larva";272;2
"Unit";"Roach";"Larva";272;2
"Unit";"Roach";"Larva";272;2
"Unit";"Roach";"Larva";272;2
"Unit";"Roach";"Larva";272;2
"Unit";"Roach";"Larva";276;2
"Unit";"Roach";"Larva";276;2
"Unit";"Roach";"Larva";288;2
"Unit";"Roach";"Larva";288;2
