"type";"unit_name";"on_building";"total_supply";"supply"
"Unit";"Overlord";"Larva";12;0
"Building";"SpawningPool";NA;17;0
"Building";"Extractor";NA;18;0
"Unit";"Overlord";"Larva";22;0
"Unit";"Queen";"Hatchery";21;2
"Building";"Hatchery";NA;18;0
"Unit";"Zergling";"Larva";26;1
"Unit";"Zergling";"Larva";26;1
"Unit";"Queen";"Hatchery";22;2
"Unit";"Overlord";"Larva";28;0
"Unit";"Queen";"Hatchery";26;2
"Unit";"Zergling";"Larva";36;1
"Unit";"Zergling";"Larva";36;1
"Unit";"Zergling";"Larva";36;1
"Unit";"Zergling";"Larva";36;1
"Unit";"Zergling";"Larva";36;1
"Unit";"Zergling";"Larva";36;1
"Unit";"Zergling";"Larva";36;1
"Unit";"Zergling";"Larva";36;1
"Building";"BanelingNest";NA;30;0
"Unit";"Zergling";"Larva";38;1
"Unit";"Zergling";"Larva";38;1
"Unit";"Zergling";"Larva";38;1
"Unit";"Zergling";"Larva";38;1
"Unit";"Zergling";"Larva";38;1
"Unit";"Zergling";"Larva";38;1
"Unit";"Zergling";"Larva";38;1
"Unit";"Zergling";"Larva";38;1
"Unit";"Zergling";"Larva";38;1
"Unit";"Zergling";"Larva";38;1
"Unit";"Baneling";"Zergling";44;0
"Unit";"Baneling";"Zergling";44;0
"Unit";"Overlord";"Larva";44;0
"Unit";"Overlord";"Larva";54;0
"Building";"Hatchery";NA;36;0
"Building";"CreepTumorQueen";NA;61;0
"Building";"CreepTumor";NA;73;0
"Building";"Extractor";NA;66;0
"Building";"Extractor";NA;66;0
"Building";"EvolutionChamber";NA;66;0
"Unit";"Overlord";"Larva";74;0
"Building";"RoachWarren";NA;74;0
"Building";"CreepTumor";NA;79;0
"Unit";"Overlord";"Larva";79;0
"Unit";"Overlord";"Larva";79;0
"Unit";"Overlord";"Larva";79;0
"Unit";"Overlord";"Larva";79;0
"Unit";"Roach";"Larva";79;2
"Unit";"Roach";"Larva";79;2
"Unit";"Roach";"Larva";79;2
"Unit";"Roach";"Larva";79;2
"Unit";"Roach";"Larva";79;2
"Unit";"Roach";"Larva";79;2
"Unit";"Roach";"Larva";79;2
"Unit";"Baneling";"Zergling";79;0
"Unit";"Baneling";"Zergling";79;0
"Unit";"Baneling";"Zergling";79;0
"Unit";"Roach";"Larva";93;2
"Unit";"Roach";"Larva";93;2
"Unit";"Roach";"Larva";93;2
"Building";"SpineCrawler";NA;79;0
"Unit";"Baneling";"Zergling";93;0
"Unit";"Zergling";"Larva";93;1
"Unit";"Zergling";"Larva";93;1
"Unit";"Zergling";"Larva";93;1
"Unit";"Zergling";"Larva";93;1
"Unit";"Zergling";"Larva";93;1
"Unit";"Zergling";"Larva";93;1
"Unit";"Baneling";"Zergling";99;0
"Unit";"Roach";"Larva";93;2
"Unit";"Roach";"Larva";93;2
"Unit";"Roach";"Larva";93;2
"Unit";"Roach";"Larva";93;2
"Unit";"Overlord";"Larva";99;0
"Unit";"Roach";"Larva";99;2
"Unit";"Roach";"Larva";99;2
"Unit";"Roach";"Larva";99;2
"Unit";"Roach";"Larva";99;2
"Upgrade";"GlialReconstitution";"RoachWarren";93;0
"Unit";"Roach";"Larva";113;2
"Unit";"Roach";"Larva";113;2
"Unit";"Roach";"Larva";113;2
"Unit";"Roach";"Larva";113;2
"Unit";"Roach";"Larva";113;2
"Unit";"Roach";"Larva";113;2
"Upgrade";"ZergMissileWeaponsLevel1";"EvolutionChamber";79;0
"Unit";"Overlord";"Larva";121;0
"Unit";"Overlord";"Larva";121;0
"Unit";"Overlord";"Larva";121;0
"Unit";"Overlord";"Larva";121;0
"Unit";"Overlord";"Larva";121;0
"Unit";"Roach";"Larva";131;2
"Unit";"Roach";"Larva";133;2
"Unit";"Roach";"Larva";133;2
"Unit";"Roach";"Larva";133;2
"Unit";"Roach";"Larva";133;2
"Unit";"Roach";"Larva";133;2
"Unit";"Roach";"Larva";133;2
"Unit";"Zergling";"Larva";133;1
"Unit";"Zergling";"Larva";133;1
"Unit";"Roach";"Larva";133;2
"Unit";"Zergling";"Larva";133;1
"Unit";"Zergling";"Larva";133;1
"Unit";"Zergling";"Larva";133;1
"Unit";"Zergling";"Larva";133;1
"Unit";"Zergling";"Larva";133;1
"Unit";"Zergling";"Larva";133;1
"Unit";"Zergling";"Larva";133;1
"Unit";"Zergling";"Larva";133;1
"Unit";"Zergling";"Larva";133;1
"Unit";"Zergling";"Larva";133;1
"Unit";"Zergling";"Larva";133;1
"Unit";"Zergling";"Larva";133;1
"Unit";"Overlord";"Larva";163;0
"Unit";"Overlord";"Larva";163;0
"Unit";"Queen";"Hatchery";163;2
"Unit";"Roach";"Larva";172;2
"Unit";"Roach";"Larva";172;2
"Unit";"Roach";"Larva";172;2
"Unit";"Roach";"Larva";172;2
"Unit";"Roach";"Larva";172;2
"Unit";"Roach";"Larva";172;2
"Unit";"Roach";"Larva";172;2
"Unit";"Roach";"Larva";172;2
"Unit";"Roach";"Larva";172;2
"Unit";"Roach";"Larva";172;2
"Unit";"Roach";"Larva";174;2
"Unit";"Roach";"Larva";174;2
"Unit";"Roach";"Larva";174;2
"Unit";"Roach";"Larva";174;2
"Building";"Extractor";NA;192;0
"Building";"Extractor";NA;194;0
"Building";"Extractor";NA;194;0
"Unit";"Roach";"Larva";194;2
"Unit";"Roach";"Larva";194;2
"Unit";"Roach";"Larva";194;2
"Unit";"Overlord";"Larva";207;0
"Unit";"Overlord";"Larva";207;0
"Unit";"Overlord";"Larva";207;0
"Unit";"Overlord";"Larva";207;0
"Unit";"Roach";"Larva";213;2
"Unit";"Roach";"Larva";213;2
"Unit";"Roach";"Larva";213;2
"Unit";"Roach";"Larva";213;2
"Unit";"Roach";"Larva";213;2
"Unit";"Roach";"Larva";213;2
"Unit";"Roach";"Larva";213;2
"Unit";"Roach";"Larva";213;2
"Unit";"Roach";"Larva";213;2
"Unit";"Roach";"Larva";213;2
"Unit";"Roach";"Larva";213;2
"Unit";"Roach";"Larva";213;2
"Unit";"Roach";"Larva";213;2
"Unit";"Roach";"Larva";213;2
"Unit";"Roach";"Larva";213;2
"Unit";"Roach";"Larva";213;2
"Upgrade";"ZergMissileWeaponsLevel2";"EvolutionChamber";172;0
"Unit";"Roach";"Larva";235;2
"Unit";"Roach";"Larva";235;2
"Unit";"Roach";"Larva";235;2
"Unit";"Roach";"Larva";235;2
"Unit";"Roach";"Larva";235;2
"Unit";"Roach";"Larva";235;2
"Unit";"Roach";"Larva";235;2
"Unit";"Roach";"Larva";253;2
"Unit";"Roach";"Larva";253;2
"Unit";"Roach";"Larva";253;2
"Unit";"Roach";"Larva";253;2
"Unit";"Roach";"Larva";253;2
"Unit";"Roach";"Larva";253;2
"Unit";"Roach";"Larva";253;2
"Unit";"Roach";"Larva";259;2
"Unit";"Roach";"Larva";259;2
"Unit";"Roach";"Larva";259;2
"Unit";"Roach";"Larva";259;2
"Unit";"Roach";"Larva";259;2
"Unit";"Roach";"Larva";259;2
"Unit";"Overlord";"Larva";273;0
"Unit";"Roach";"Larva";273;2
"Unit";"Roach";"Larva";273;2
"Unit";"Roach";"Larva";273;2
"Unit";"Roach";"Larva";273;2
"Unit";"Roach";"Larva";273;2
"Unit";"Roach";"Larva";273;2
"Unit";"Roach";"Larva";273;2
"Unit";"Roach";"Larva";285;2
"Unit";"Roach";"Larva";285;2
"Unit";"Roach";"Larva";285;2
"Unit";"Roach";"Larva";285;2
"Unit";"Roach";"Larva";285;2
"Unit";"Roach";"Larva";285;2
"Unit";"Roach";"Larva";285;2
"Building";"CreepTumor";NA;299;0
"Unit";"Roach";"Larva";299;2
"Unit";"Roach";"Larva";299;2
"Unit";"Roach";"Larva";299;2
"Unit";"Roach";"Larva";313;2
"Unit";"Roach";"Larva";313;2
"Unit";"Roach";"Larva";313;2
"Unit";"Roach";"Larva";313;2
"Unit";"Roach";"Larva";313;2
"Building";"HydraliskDen";NA;313;0
"Unit";"Roach";"Larva";319;2
"Unit";"Roach";"Larva";319;2
"Unit";"Roach";"Larva";319;2
