"type";"unit_name";"on_building";"total_supply";"supply"
"Unit";"Overlord";"Larva";13;0
"Building";"Extractor";NA;18;0
"Building";"SpawningPool";NA;19;0
"Building";"Hatchery";NA;17;0
"Unit";"Overlord";"Larva";22;0
"Unit";"Queen";"Hatchery";23;2
"Unit";"Queen";"Hatchery";23;2
"Unit";"Overlord";"Larva";32;0
"Unit";"Zergling";"Larva";33;1
"Unit";"Zergling";"Larva";33;1
"Unit";"Zergling";"Larva";33;1
"Unit";"Zergling";"Larva";33;1
"Unit";"Zergling";"Larva";33;1
"Unit";"Zergling";"Larva";33;1
"Unit";"Zergling";"Larva";34;1
"Unit";"Zergling";"Larva";34;1
"Building";"BanelingNest";NA;32;0
"Unit";"Overlord";"Larva";36;0
"Unit";"Overlord";"Larva";36;0
"Unit";"Zergling";"Larva";36;1
"Unit";"Zergling";"Larva";36;1
"Unit";"Zergling";"Larva";38;1
"Unit";"Zergling";"Larva";38;1
"Unit";"Zergling";"Larva";38;1
"Unit";"Zergling";"Larva";38;1
"Unit";"Zergling";"Larva";40;1
"Unit";"Zergling";"Larva";40;1
"Unit";"Zergling";"Larva";42;1
"Unit";"Zergling";"Larva";42;1
"Unit";"Baneling";"Zergling";42;0
"Unit";"Baneling";"Zergling";42;0
"Unit";"Zergling";"Larva";42;1
"Unit";"Zergling";"Larva";42;1
"Unit";"Zergling";"Larva";42;1
"Unit";"Zergling";"Larva";42;1
"Unit";"Zergling";"Larva";42;1
"Unit";"Zergling";"Larva";42;1
"Building";"Hatchery";NA;27;0
"Unit";"Zergling";"Larva";48;1
"Unit";"Zergling";"Larva";48;1
"Unit";"Zergling";"Larva";50;1
"Unit";"Zergling";"Larva";50;1
"Unit";"Baneling";"Zergling";56;0
"Unit";"Baneling";"Zergling";56;0
"Unit";"Baneling";"Zergling";56;0
"Unit";"Zergling";"Larva";56;1
"Unit";"Zergling";"Larva";56;1
"Unit";"Zergling";"Larva";58;1
"Unit";"Zergling";"Larva";58;1
"Unit";"Zergling";"Larva";58;1
"Unit";"Zergling";"Larva";58;1
"Unit";"Zergling";"Larva";58;1
"Unit";"Zergling";"Larva";58;1
"Unit";"Zergling";"Larva";58;1
"Unit";"Zergling";"Larva";58;1
"Unit";"Zergling";"Larva";58;1
"Unit";"Zergling";"Larva";58;1
"Unit";"Zergling";"Larva";74;1
"Unit";"Zergling";"Larva";74;1
"Unit";"Zergling";"Larva";76;1
"Unit";"Zergling";"Larva";76;1
"Unit";"Zergling";"Larva";76;1
"Unit";"Zergling";"Larva";76;1
"Unit";"Zergling";"Larva";78;1
"Unit";"Zergling";"Larva";78;1
"Unit";"Baneling";"Zergling";78;0
"Unit";"Zergling";"Larva";78;1
"Unit";"Zergling";"Larva";78;1
"Unit";"Zergling";"Larva";78;1
"Unit";"Zergling";"Larva";78;1
"Unit";"Zergling";"Larva";78;1
"Unit";"Zergling";"Larva";78;1
"Unit";"Zergling";"Larva";78;1
"Unit";"Zergling";"Larva";78;1
"Unit";"Zergling";"Larva";78;1
"Unit";"Zergling";"Larva";78;1
"Unit";"Zergling";"Larva";78;1
"Unit";"Zergling";"Larva";78;1
"Unit";"Zergling";"Larva";85;1
"Unit";"Zergling";"Larva";85;1
"Unit";"Zergling";"Larva";87;1
"Unit";"Zergling";"Larva";87;1
"Unit";"Overlord";"Larva";91;0
"Unit";"Zergling";"Larva";102;1
"Unit";"Zergling";"Larva";102;1
"Unit";"Zergling";"Larva";102;1
"Unit";"Zergling";"Larva";102;1
"Unit";"Queen";"Hatchery";92;2
"Unit";"Overlord";"Larva";118;0
"Unit";"Zergling";"Larva";125;1
"Unit";"Zergling";"Larva";125;1
"Unit";"Baneling";"Zergling";125;0
"Unit";"Baneling";"Zergling";125;0
"Unit";"Zergling";"Larva";125;1
"Unit";"Zergling";"Larva";125;1
"Unit";"Zergling";"Larva";127;1
"Unit";"Zergling";"Larva";127;1
"Unit";"Zergling";"Larva";127;1
"Unit";"Zergling";"Larva";127;1
"Building";"Extractor";NA;127;0
"Building";"Extractor";NA;127;0
"Building";"EvolutionChamber";NA;127;0
"Unit";"Zergling";"Larva";136;1
"Unit";"Zergling";"Larva";136;1
"Unit";"Zergling";"Larva";141;1
"Unit";"Zergling";"Larva";141;1
"Unit";"Overlord";"Larva";143;0
"Unit";"Baneling";"Zergling";143;0
"Unit";"Baneling";"Zergling";143;0
"Building";"RoachWarren";NA;127;0
"Unit";"Baneling";"Zergling";143;0
"Unit";"Baneling";"Zergling";145;0
"Unit";"Overlord";"Larva";145;0
"Unit";"Overlord";"Larva";145;0
"Unit";"Overlord";"Larva";145;0
"Unit";"Overlord";"Larva";145;0
"Unit";"Overlord";"Larva";145;0
"Unit";"Roach";"Larva";147;2
"Unit";"Roach";"Larva";147;2
"Unit";"Roach";"Larva";147;2
"Unit";"Roach";"Larva";147;2
"Unit";"Roach";"Larva";147;2
"Unit";"Roach";"Larva";147;2
"Unit";"Roach";"Larva";147;2
"Unit";"Roach";"Larva";147;2
"Unit";"Roach";"Larva";147;2
"Unit";"Roach";"Larva";147;2
"Unit";"Roach";"Larva";147;2
"Unit";"Roach";"Larva";147;2
"Unit";"Roach";"Larva";147;2
"Unit";"Roach";"Larva";147;2
"Unit";"Roach";"Larva";147;2
"Unit";"Zergling";"Larva";159;1
"Unit";"Zergling";"Larva";159;1
"Unit";"Zergling";"Larva";159;1
"Unit";"Zergling";"Larva";159;1
"Unit";"Zergling";"Larva";159;1
"Unit";"Zergling";"Larva";159;1
"Unit";"Zergling";"Larva";159;1
"Unit";"Zergling";"Larva";159;1
"Unit";"Zergling";"Larva";159;1
"Unit";"Zergling";"Larva";159;1
"Unit";"Roach";"Larva";149;2
"Unit";"Zergling";"Larva";163;1
"Unit";"Zergling";"Larva";163;1
"Unit";"Zergling";"Larva";165;1
"Unit";"Zergling";"Larva";165;1
"Unit";"Zergling";"Larva";167;1
"Unit";"Zergling";"Larva";167;1
"Unit";"Zergling";"Larva";175;1
"Unit";"Zergling";"Larva";175;1
"Unit";"Baneling";"Zergling";191;0
"Unit";"Baneling";"Zergling";191;0
"Unit";"Baneling";"Zergling";191;0
"Unit";"Baneling";"Zergling";191;0
"Unit";"Baneling";"Zergling";191;0
"Unit";"Baneling";"Zergling";191;0
"Unit";"Baneling";"Zergling";191;0
"Unit";"Baneling";"Zergling";193;0
"Unit";"Zergling";"Larva";191;1
"Unit";"Zergling";"Larva";191;1
"Unit";"Zergling";"Larva";191;1
"Unit";"Zergling";"Larva";191;1
"Unit";"Zergling";"Larva";191;1
"Unit";"Zergling";"Larva";191;1
"Unit";"Zergling";"Larva";191;1
"Unit";"Zergling";"Larva";191;1
"Unit";"Zergling";"Larva";191;1
"Unit";"Zergling";"Larva";191;1
"Unit";"Zergling";"Larva";191;1
"Unit";"Zergling";"Larva";191;1
"Unit";"Zergling";"Larva";191;1
"Unit";"Zergling";"Larva";191;1
"Unit";"Zergling";"Larva";191;1
"Unit";"Zergling";"Larva";191;1
"Unit";"Zergling";"Larva";191;1
"Unit";"Zergling";"Larva";191;1
"Unit";"Zergling";"Larva";191;1
"Unit";"Zergling";"Larva";191;1
"Unit";"Zergling";"Larva";197;1
"Unit";"Zergling";"Larva";197;1
"Unit";"Zergling";"Larva";197;1
"Unit";"Zergling";"Larva";197;1
"Unit";"Zergling";"Larva";197;1
"Unit";"Zergling";"Larva";197;1
"Building";"Extractor";NA;197;0
"Building";"Extractor";NA;197;0
"Unit";"Zergling";"Larva";197;1
"Unit";"Zergling";"Larva";197;1
