"type";"unit_name";"on_building";"total_supply_lag";"supply"
"Unit";"Overlord";"Larva";13;0
"Building";"SpawningPool";NA;17;0
"Building";"Hatchery";NA;18;0
"Building";"Extractor";NA;18;0
"Unit";"Queen";"Hatchery";21;2
"Unit";"Zergling";"Larva";23;1
"Unit";"Zergling";"Larva";24;1
"Unit";"Overlord";"Larva";25;0
"Unit";"Queen";"Hatchery";27;2
"Unit";"Queen";"Hatchery";31;2
"Unit";"Zergling";"Larva";34;1
"Unit";"Zergling";"Larva";35;1
"Unit";"Zergling";"Larva";36;1
"Unit";"Zergling";"Larva";37;1
"Unit";"Overlord";"Larva";38;0
"Unit";"Overlord";"Larva";40;0
"Building";"CreepTumorQueen";NA;40;0
"Unit";"Zergling";"Larva";40;1
"Unit";"Zergling";"Larva";41;1
"Unit";"Zergling";"Larva";42;1
"Unit";"Zergling";"Larva";43;1
"Unit";"Overlord";"Larva";44;0
"Unit";"Zergling";"Larva";45;1
"Unit";"Zergling";"Larva";46;1
"Unit";"Zergling";"Larva";47;1
"Unit";"Zergling";"Larva";48;1
"Unit";"Zergling";"Larva";49;1
"Unit";"Zergling";"Larva";50;1
"Building";"EvolutionChamber";NA;53;0
"Building";"CreepTumor";NA;53;0
"Building";"CreepTumorQueen";NA;53;0
"Building";"RoachWarren";NA;56;0
"Building";"EvolutionChamber";NA;59;0
"Unit";"Zergling";"Larva";59;1
"Unit";"Zergling";"Larva";60;1
"Unit";"Zergling";"Larva";61;1
"Unit";"Zergling";"Larva";62;1
"Unit";"Zergling";"Larva";63;1
"Unit";"Zergling";"Larva";64;1
"Unit";"Zergling";"Larva";65;1
"Unit";"Zergling";"Larva";66;1
"Unit";"Zergling";"Larva";67;1
"Unit";"Zergling";"Larva";68;1
"Building";"Extractor";NA;71;0
"Unit";"Overlord";"Larva";72;0
"Building";"Extractor";NA;72;0
"Unit";"Overlord";"Larva";77;0
"Building";"CreepTumor";NA;82;0
"Building";"CreepTumor";NA;82;0
"Unit";"Overlord";"Larva";82;0
"Unit";"Overlord";"Larva";82;0
"Unit";"Roach";"Larva";82;2
"Unit";"Roach";"Larva";84;2
"Unit";"Roach";"Larva";86;2
"Unit";"Roach";"Larva";88;2
"Unit";"Roach";"Larva";90;2
"Unit";"Roach";"Larva";92;2
"Building";"CreepTumor";NA;94;0
"Unit";"Roach";"Larva";94;2
"Unit";"Roach";"Larva";96;2
"Unit";"Roach";"Larva";98;2
"Upgrade";"GlialReconstitution";"RoachWarren";100;0
"Building";"Hatchery";NA;100;0
"Unit";"Roach";"Larva";100;2
"Unit";"Roach";"Larva";102;2
"Unit";"Roach";"Larva";104;2
"Unit";"Roach";"Larva";106;2
"Unit";"Overlord";"Larva";114;0
"Unit";"Overlord";"Larva";114;0
"Unit";"Roach";"Larva";121;2
"Unit";"Roach";"Larva";123;2
"Unit";"Roach";"Larva";125;2
"Unit";"Roach";"Larva";127;2
"Unit";"Roach";"Larva";129;2
"Unit";"Roach";"Larva";131;2
"Unit";"Roach";"Larva";133;2
"Building";"Extractor";NA;135;0
"Unit";"Roach";"Larva";135;2
"Unit";"Roach";"Larva";137;2
"Unit";"Roach";"Larva";139;2
"Unit";"Overlord";"Larva";141;0
"Unit";"Roach";"Larva";141;2
"Unit";"Roach";"Larva";143;2
"Unit";"Roach";"Larva";145;2
"Unit";"Roach";"Larva";147;2
"Unit";"Roach";"Larva";149;2
"Unit";"Overlord";"Larva";151;0
"Unit";"Overlord";"Larva";151;0
"Unit";"Overlord";"Larva";151;0
"Unit";"Overlord";"Larva";151;0
"Unit";"Roach";"Larva";151;2
"Unit";"Roach";"Larva";153;2
"Unit";"Roach";"Larva";155;2
"Unit";"Roach";"Larva";157;2
"Unit";"Roach";"Larva";159;2
"Building";"CreepTumor";NA;161;0
"Unit";"Roach";"Larva";161;2
"Unit";"Roach";"Larva";163;2
"Unit";"Roach";"Larva";165;2
"Unit";"Roach";"Larva";167;2
"Unit";"Overlord";"Larva";169;0
"Unit";"Roach";"Larva";169;2
"Unit";"Roach";"Larva";171;2
"Unit";"Roach";"Larva";173;2
"Unit";"Roach";"Larva";175;2
"Unit";"Roach";"Larva";177;2
"Unit";"Roach";"Larva";179;2
"Unit";"Roach";"Larva";181;2
"Unit";"Roach";"Larva";183;2
"Unit";"Roach";"Larva";185;2
"Unit";"Roach";"Larva";187;2
"Unit";"Roach";"Larva";189;2
"Unit";"Roach";"Larva";191;2
"Unit";"Roach";"Larva";193;2
"Unit";"Roach";"Larva";195;2
"Building";"Extractor";NA;197;0
"Unit";"Roach";"Larva";197;2
"Unit";"Overlord";"Larva";199;0
"Unit";"Roach";"Larva";199;2
"Unit";"Roach";"Larva";201;2
"Unit";"Roach";"Larva";203;2
"Unit";"Roach";"Larva";205;2
"Unit";"Roach";"Larva";207;2
"Unit";"Roach";"Larva";209;2
"Unit";"Roach";"Larva";211;2
"Unit";"Roach";"Larva";213;2
"Unit";"Roach";"Larva";215;2
"Unit";"Roach";"Larva";217;2
"Unit";"Overlord";"Larva";219;0
"Unit";"Overlord";"Larva";219;0
"Unit";"Roach";"Larva";219;2
"Unit";"Roach";"Larva";221;2
"Unit";"Roach";"Larva";223;2
"Unit";"Roach";"Larva";225;2
"Unit";"Roach";"Larva";227;2
"Unit";"Roach";"Larva";229;2
"Unit";"Roach";"Larva";231;2
"Unit";"Roach";"Larva";233;2
"Unit";"Roach";"Larva";235;2
"Unit";"Roach";"Larva";237;2
"Unit";"Roach";"Larva";239;2
"Unit";"Roach";"Larva";241;2
"Unit";"Roach";"Larva";243;2
"Unit";"Roach";"Larva";245;2
"Unit";"Roach";"Larva";247;2
"Unit";"Roach";"Larva";249;2
"Unit";"Roach";"Larva";251;2
"Unit";"Roach";"Larva";253;2
"Unit";"Roach";"Larva";255;2
"Unit";"Roach";"Larva";257;2
"Unit";"Roach";"Larva";259;2
"Unit";"Roach";"Larva";261;2
"Unit";"Roach";"Larva";263;2
"Unit";"Roach";"Larva";265;2
"Unit";"Roach";"Larva";267;2
"Unit";"Roach";"Larva";269;2
"Unit";"Roach";"Larva";271;2
"Unit";"Roach";"Larva";273;2
"Building";"Extractor";NA;275;0
"Unit";"Roach";"Larva";275;2
"Unit";"Roach";"Larva";277;2
"Unit";"Roach";"Larva";279;2
"Unit";"Roach";"Larva";281;2
"Unit";"Roach";"Larva";288;2
"Unit";"Roach";"Larva";290;2
"Unit";"Roach";"Larva";292;2
"Unit";"Overlord";"Larva";294;0
"Unit";"Overlord";"Larva";294;0
"Unit";"Roach";"Larva";294;2
"Unit";"Roach";"Larva";296;2
"Unit";"Roach";"Larva";298;2
"Unit";"Roach";"Larva";300;2
"Unit";"Roach";"Larva";302;2
"Unit";"Roach";"Larva";304;2
"Unit";"Roach";"Larva";306;2
"Unit";"Roach";"Larva";308;2
"Unit";"Roach";"Larva";310;2
"Unit";"Roach";"Larva";312;2
"Unit";"Roach";"Larva";314;2
"Unit";"Roach";"Larva";316;2
"Unit";"Roach";"Larva";318;2
"Unit";"Roach";"Larva";320;2
"Unit";"Roach";"Larva";322;2
"Unit";"Roach";"Larva";324;2
"Unit";"Roach";"Larva";326;2
"Unit";"Roach";"Larva";328;2
"Unit";"Roach";"Larva";330;2
"Unit";"Roach";"Larva";332;2
"Unit";"Roach";"Larva";334;2
"Unit";"Roach";"Larva";336;2
"Unit";"Roach";"Larva";338;2
"Unit";"Roach";"Larva";340;2
"Unit";"Roach";"Larva";342;2
"Unit";"Roach";"Larva";344;2
"Unit";"Roach";"Larva";346;2
"Unit";"Roach";"Larva";348;2
"Unit";"Roach";"Larva";350;2
"Unit";"Roach";"Larva";352;2
"Unit";"Roach";"Larva";354;2
"Unit";"Roach";"Larva";356;2
"Unit";"Roach";"Larva";358;2
"Unit";"Roach";"Larva";360;2
"Unit";"Roach";"Larva";362;2
"Unit";"Roach";"Larva";364;2
"Unit";"Roach";"Larva";366;2
"Building";"Hatchery";NA;368;0
"Unit";"Roach";"Larva";368;2
"Unit";"Roach";"Larva";370;2
"Unit";"Roach";"Larva";372;2
"Unit";"Roach";"Larva";374;2
"Unit";"Roach";"Larva";376;2
"Unit";"Roach";"Larva";378;2
"Unit";"Roach";"Larva";380;2
"Unit";"Roach";"Larva";382;2
"Unit";"Roach";"Larva";384;2
"Unit";"Roach";"Larva";386;2
"Unit";"Roach";"Larva";388;2
"Unit";"Roach";"Larva";390;2
"Unit";"Roach";"Larva";392;2
"Unit";"Roach";"Larva";394;2
"Unit";"Roach";"Larva";396;2
"Unit";"Roach";"Larva";398;2
"Unit";"Roach";"Larva";400;2
"Unit";"Roach";"Larva";402;2
"Unit";"Roach";"Larva";404;2
"Unit";"Roach";"Larva";406;2
"Unit";"Roach";"Larva";408;2
"Unit";"Roach";"Larva";410;2
"Unit";"Roach";"Larva";412;2
"Unit";"Roach";"Larva";414;2
"Unit";"Roach";"Larva";416;2
"Unit";"Roach";"Larva";418;2
"Unit";"Roach";"Larva";420;2
"Unit";"Roach";"Larva";422;2
"Unit";"Roach";"Larva";424;2
"Unit";"Roach";"Larva";426;2
"Unit";"Roach";"Larva";428;2
"Unit";"Roach";"Larva";430;2
"Unit";"Roach";"Larva";432;2
"Unit";"Roach";"Larva";434;2
"Unit";"Roach";"Larva";436;2
"Unit";"Roach";"Larva";438;2
"Unit";"Roach";"Larva";440;2
"Unit";"Roach";"Larva";442;2
"Unit";"Roach";"Larva";444;2
"Unit";"Roach";"Larva";446;2
"Unit";"Roach";"Larva";448;2
"Unit";"Roach";"Larva";450;2
"Unit";"Roach";"Larva";452;2
"Unit";"Roach";"Larva";454;2
"Unit";"Roach";"Larva";456;2
"Unit";"Roach";"Larva";458;2
"Unit";"Roach";"Larva";460;2
"Unit";"Roach";"Larva";462;2
"Unit";"Roach";"Larva";464;2
"Unit";"Roach";"Larva";466;2
"Unit";"Roach";"Larva";468;2
"Unit";"Roach";"Larva";470;2
"Unit";"Roach";"Larva";472;2
"Unit";"Roach";"Larva";474;2
"Unit";"Roach";"Larva";476;2
"Unit";"Roach";"Larva";478;2
"Unit";"Roach";"Larva";480;2
"Unit";"Roach";"Larva";482;2
"Unit";"Roach";"Larva";484;2
"Unit";"Roach";"Larva";486;2
"Unit";"Roach";"Larva";488;2
"Unit";"Roach";"Larva";490;2
"Unit";"Overlord";"Larva";492;0
"Unit";"Roach";"Larva";492;2
"Unit";"Roach";"Larva";494;2
"Unit";"Roach";"Larva";498;2
"Unit";"Roach";"Larva";500;2
"Unit";"Overlord";"Larva";502;0
"Unit";"Roach";"Larva";502;2
"Unit";"Roach";"Larva";504;2
"Unit";"Roach";"Larva";506;2
"Unit";"Roach";"Larva";508;2
"Unit";"Roach";"Larva";510;2
"Unit";"Roach";"Larva";512;2
"Unit";"Roach";"Larva";514;2
"Unit";"Roach";"Larva";516;2
"Unit";"Overlord";"Larva";520;0
"Unit";"Overlord";"Larva";520;0
"Unit";"Roach";"Larva";520;2
"Unit";"Roach";"Larva";522;2
"Unit";"Roach";"Larva";524;2
"Unit";"Roach";"Larva";526;2
"Unit";"Roach";"Larva";528;2
"Unit";"Roach";"Larva";530;2
"Unit";"Roach";"Larva";532;2
"Unit";"Roach";"Larva";534;2
"Unit";"Roach";"Larva";536;2
"Unit";"Roach";"Larva";538;2
"Unit";"Roach";"Larva";540;2
"Unit";"Roach";"Larva";542;2
"Building";"Spire";NA;544;0
"Unit";"Overlord";"Larva";544;0
"Unit";"Overlord";"Larva";544;0
"Building";"Extractor";NA;544;0
"Unit";"Overlord";"Larva";544;0
"Unit";"Mutalisk";"Larva";544;2
"Unit";"Mutalisk";"Larva";546;2
"Unit";"Mutalisk";"Larva";548;2
"Unit";"Mutalisk";"Larva";550;2
"Unit";"Mutalisk";"Larva";552;2
"Unit";"Mutalisk";"Larva";554;2
"Unit";"Mutalisk";"Larva";556;2
"Unit";"Mutalisk";"Larva";558;2
"Unit";"Mutalisk";"Larva";560;2
"Unit";"Mutalisk";"Larva";562;2
"Unit";"Mutalisk";"Larva";564;2
"Unit";"Mutalisk";"Larva";566;2
"Unit";"Mutalisk";"Larva";568;2
"Unit";"Mutalisk";"Larva";570;2
"Unit";"Mutalisk";"Larva";572;2
"Unit";"Roach";"Larva";574;2
"Unit";"Roach";"Larva";576;2
"Unit";"Roach";"Larva";578;2
"Unit";"Roach";"Larva";580;2
"Unit";"Roach";"Larva";582;2
"Unit";"Roach";"Larva";584;2
"Unit";"Roach";"Larva";586;2
"Unit";"Roach";"Larva";588;2
"Unit";"Roach";"Larva";590;2
"Unit";"Roach";"Larva";592;2
"Unit";"Roach";"Larva";594;2
"Unit";"Roach";"Larva";596;2
"Upgrade";"SprayZerg";NA;598;0
"Upgrade";"SprayZerg";NA;598;0
"Upgrade";"zerglingmovementspeed";NA;598;0
"Upgrade";"SprayZerg";NA;598;0
"Upgrade";"ZergMissileWeaponsLevel1";NA;598;0
"Upgrade";"ZergGroundArmorsLevel1";NA;598;0
"Upgrade";"SprayZerg";NA;598;0
"Upgrade";"ZergMissileWeaponsLevel2";NA;598;0
"Upgrade";"ZergGroundArmorsLevel2";NA;598;0
"Upgrade";"SprayZerg";NA;598;0
"Upgrade";"SprayZerg";NA;598;0
