"type";"unit_name";"on_building";"total_supply";"supply"
"Unit";"Overlord";"Larva";14;0
"Building";"SpawningPool";NA;12;0
"Unit";"Zergling";"Larva";15;1
"Unit";"Zergling";"Larva";15;1
"Unit";"Zergling";"Larva";15;1
"Unit";"Zergling";"Larva";15;1
"Unit";"Zergling";"Larva";15;1
"Unit";"Zergling";"Larva";15;1
"Unit";"Zergling";"Larva";15;1
"Unit";"Zergling";"Larva";15;1
"Unit";"Zergling";"Larva";21;1
"Unit";"Zergling";"Larva";21;1
"Unit";"Zergling";"Larva";23;1
"Unit";"Zergling";"Larva";23;1
"Unit";"Overlord";"Larva";25;0
"Unit";"Queen";"Hatchery";23;2
"Unit";"Zergling";"Larva";27;1
"Unit";"Zergling";"Larva";27;1
"Building";"Hatchery";NA;15;0
"Unit";"Overlord";"Larva";32;0
"Unit";"Queen";"Hatchery";29;2
"Unit";"Queen";"Hatchery";32;2
"Unit";"Zergling";"Larva";45;1
"Unit";"Zergling";"Larva";45;1
"Unit";"Zergling";"Larva";45;1
"Unit";"Zergling";"Larva";45;1
"Unit";"Zergling";"Larva";45;1
"Unit";"Zergling";"Larva";45;1
"Unit";"Queen";"Hatchery";42;2
"Building";"SpineCrawler";NA;45;0
"Building";"Extractor";NA;45;0
"Building";"Extractor";NA;45;0
"Building";"EvolutionChamber";NA;51;0
"Building";"RoachWarren";NA;51;0
"Building";"CreepTumorQueen";NA;61;0
"Building";"CreepTumorQueen";NA;61;0
"Unit";"Overlord";"Larva";61;0
"Unit";"Overlord";"Larva";61;0
"Building";"CreepTumor";NA;70;0
"Building";"CreepTumor";NA;70;0
"Building";"EvolutionChamber";NA;70;0
"Unit";"Overlord";"Larva";70;0
"Unit";"Overlord";"Larva";70;0
"Building";"Extractor";NA;70;0
"Unit";"Overlord";"Larva";77;0
"Building";"CreepTumorQueen";NA;77;0
"Building";"CreepTumorQueen";NA;77;0
"Building";"CreepTumorQueen";NA;77;0
"Unit";"Roach";"Larva";77;2
"Unit";"Roach";"Larva";77;2
"Unit";"Roach";"Larva";77;2
"Unit";"Roach";"Larva";77;2
"Unit";"Roach";"Larva";77;2
"Unit";"Roach";"Larva";77;2
"Unit";"Roach";"Larva";77;2
"Unit";"Roach";"Larva";77;2
"Building";"CreepTumor";NA;87;0
"Building";"CreepTumor";NA;87;0
"Unit";"Roach";"Larva";87;2
"Unit";"Roach";"Larva";87;2
"Unit";"Roach";"Larva";87;2
"Building";"CreepTumorQueen";NA;87;0
"Building";"CreepTumorQueen";NA;93;0
"Upgrade";"ZergMissileWeaponsLevel1";"EvolutionChamber";70;0
"Upgrade";"GlialReconstitution";"RoachWarren";77;0
"Building";"Extractor";NA;99;0
"Building";"CreepTumorQueen";NA;104;0
"Building";"CreepTumorQueen";NA;104;0
"Unit";"Overlord";"Larva";104;0
"Building";"Hatchery";NA;77;0
"Unit";"Overlord";"Larva";106;0
"Unit";"Overlord";"Larva";106;0
"Unit";"Roach";"Larva";110;2
"Unit";"Roach";"Larva";110;2
"Unit";"Roach";"Larva";110;2
"Unit";"Roach";"Larva";110;2
"Building";"CreepTumor";NA;118;0
"Building";"CreepTumor";NA;118;0
"Unit";"Roach";"Larva";110;2
"Unit";"Roach";"Larva";110;2
"Unit";"Roach";"Larva";110;2
"Unit";"Roach";"Larva";110;2
"Unit";"Roach";"Larva";110;2
"Building";"CreepTumor";NA;118;0
"Building";"CreepTumor";NA;118;0
"Building";"CreepTumor";NA;118;0
"Unit";"Overlord";"Larva";118;0
"Unit";"Overlord";"Larva";118;0
"Unit";"Overlord";"Larva";118;0
"Unit";"Overlord";"Larva";118;0
"Building";"CreepTumor";NA;131;0
"Building";"CreepTumor";NA;131;0
"Building";"CreepTumor";NA;131;0
"Unit";"Roach";"Larva";131;2
"Building";"Extractor";NA;131;0
"Building";"Extractor";NA;131;0
"Building";"CreepTumor";NA;135;0
"Building";"CreepTumor";NA;135;0
"Building";"CreepTumor";NA;135;0
"Building";"HydraliskDen";NA;131;0
"Building";"SpineCrawler";NA;128;0
"Unit";"Roach";"Larva";137;2
"Unit";"Roach";"Larva";137;2
"Unit";"Roach";"Larva";137;2
"Unit";"Roach";"Larva";137;2
"Unit";"Roach";"Larva";137;2
"Unit";"Roach";"Larva";137;2
"Unit";"Roach";"Larva";137;2
"Building";"CreepTumor";NA;157;0
"Upgrade";"ZergMissileWeaponsLevel2";"EvolutionChamber";110;0
"Building";"CreepTumor";NA;157;0
"Building";"CreepTumor";NA;157;0
"Building";"CreepTumor";NA;157;0
"Building";"SpineCrawler";NA;156;0
"Unit";"Hydralisk";"Larva";164;2
"Unit";"Hydralisk";"Larva";164;2
"Unit";"Hydralisk";"Larva";164;2
"Unit";"Hydralisk";"Larva";164;2
"Unit";"Hydralisk";"Larva";164;2
"Unit";"Hydralisk";"Larva";164;2
"Unit";"Roach";"Larva";164;2
"Unit";"Roach";"Larva";164;2
"Building";"CreepTumor";NA;164;0
"Unit";"Overlord";"Larva";164;0
"Unit";"Overlord";"Larva";164;0
"Unit";"Overlord";"Larva";164;0
"Unit";"Overlord";"Larva";164;0
"Upgrade";"ZergGroundArmorsLevel1";"EvolutionChamber";135;0
"Building";"CreepTumor";NA;176;0
"Building";"CreepTumor";NA;176;0
"Unit";"Overlord";"Larva";180;0
"Unit";"Overlord";"Larva";180;0
"Building";"SpineCrawler";NA;164;0
"Unit";"Hydralisk";"Larva";180;2
"Building";"Extractor";NA;180;0
"Unit";"Hydralisk";"Larva";180;2
"Building";"Extractor";NA;180;0
"Building";"Hatchery";NA;164;0
"Building";"CreepTumor";NA;184;0
"Building";"CreepTumor";NA;184;0
"Building";"CreepTumor";NA;185;0
"Building";"CreepTumorQueen";NA;186;0
"Building";"CreepTumorQueen";NA;186;0
"Unit";"Hydralisk";"Larva";180;2
"Unit";"Hydralisk";"Larva";180;2
"Unit";"Hydralisk";"Larva";180;2
"Building";"CreepTumorQueen";NA;186;0
"Building";"LurkerDenMP";NA;164;0
"Building";"CreepTumorQueen";NA;186;0
"Unit";"Hydralisk";"Larva";186;2
"Unit";"Hydralisk";"Larva";186;2
"Unit";"Hydralisk";"Larva";186;2
"Unit";"Hydralisk";"Larva";186;2
"Unit";"Roach";"Larva";198;2
"Building";"CreepTumor";NA;206;0
"Unit";"Roach";"Larva";206;2
"Unit";"Roach";"Larva";206;2
"Unit";"Roach";"Larva";206;2
"Unit";"Roach";"Larva";206;2
"Unit";"Roach";"Larva";206;2
"Unit";"Roach";"Larva";208;2
"Unit";"Roach";"Larva";208;2
"Unit";"Roach";"Larva";208;2
"Unit";"Roach";"Larva";208;2
"Unit";"Roach";"Larva";208;2
"Unit";"Roach";"Larva";208;2
"Unit";"Roach";"Larva";208;2
"Upgrade";"EvolveGroovedSpines";"HydraliskDen";206;0
"Unit";"Hydralisk";"Larva";220;2
"Unit";"Hydralisk";"Larva";220;2
"Unit";"Roach";"Larva";238;2
"Unit";"Overlord";"Larva";238;0
"Unit";"Overlord";"Larva";238;0
"Unit";"Overlord";"Larva";238;0
"Unit";"Overlord";"Larva";238;0
"Unit";"Roach";"Larva";242;2
"Unit";"Roach";"Larva";242;2
"Unit";"Roach";"Larva";242;2
"Unit";"Roach";"Larva";242;2
"Unit";"Roach";"Larva";242;2
"Unit";"Roach";"Larva";242;2
"Unit";"Roach";"Larva";242;2
"Building";"InfestationPit";NA;238;0
"Upgrade";"EvolveMuscularAugments";"HydraliskDen";238;0
"Unit";"Roach";"Larva";256;2
"Unit";"Roach";"Larva";256;2
"Unit";"Roach";"Larva";256;2
"Unit";"Roach";"Larva";256;2
"Unit";"Roach";"Larva";256;2
"Unit";"Roach";"Larva";256;2
"Unit";"Roach";"Larva";256;2
"Unit";"Roach";"Larva";256;2
"Unit";"Roach";"Larva";256;2
"Unit";"Roach";"Larva";256;2
"Unit";"Roach";"Larva";256;2
