"type";"unit_name";"on_building";"total_supply_lag";"supply"
"Building";"Refinery";NA;15;0
"Building";"Barracks";NA;16;0
"Unit";"Reaper";"Barracks";19;1
"Building";"CommandCenter";NA;20;0
"Building";"Factory";NA;20;0
"Building";"BarracksReactor";NA;21;0
"Building";"Refinery";NA;22;0
"Unit";"Marine";"Barracks";24;1
"Unit";"Marine";"Barracks";25;1
"Unit";"Cyclone";"Factory";27;3
"Unit";"Marine";"Barracks";31;1
"Unit";"Marine";"Barracks";32;1
"Building";"Starport";NA;33;0
"Building";"FactoryTechLab";NA;34;0
"Unit";"Marine";"Barracks";34;1
"Unit";"Marine";"Barracks";35;1
"Unit";"Marine";"Barracks";40;1
"Unit";"Marine";"Barracks";41;1
"Unit";"Raven";"Starport";44;2
"Building";"CommandCenter";NA;46;0
"Unit";"Marine";"Barracks";47;1
"Unit";"Marine";"Barracks";48;1
"Building";"FactoryTechLab";NA;49;0
"Unit";"Marine";"Barracks";51;1
"Building";"Bunker";NA;53;0
"Unit";"Marine";"Barracks";58;1
"Unit";"Marine";"Barracks";62;1
"Building";"Barracks";NA;65;0
"Building";"Barracks";NA;65;0
"Unit";"Marine";"Barracks";66;1
"Building";"StarportReactor";NA;69;0
"Upgrade";"Stimpack";"TechLab";70;0
"Unit";"Marine";"Barracks";71;1
"Building";"Refinery";NA;72;0
"Building";"EngineeringBay";NA;72;0
"Building";"EngineeringBay";NA;72;0
"Building";"Refinery";NA;72;0
"Unit";"Marine";"Barracks";77;1
"Building";"StarportReactor";NA;79;0
"Unit";"Marine";"Barracks";79;1
"Unit";"Marine";"Barracks";80;1
"Unit";"Marine";"Barracks";81;1
"Building";"MissileTurret";NA;83;0
"Building";"Barracks";NA;84;0
"Building";"Barracks";NA;84;0
"Unit";"Marine";"Barracks";87;1
"Unit";"Marine";"Barracks";88;1
"Unit";"Marine";"Barracks";89;1
"Unit";"Marine";"Barracks";90;1
"Unit";"Marine";"Barracks";91;1
"Upgrade";"TerranInfantryWeaponsLevel1";"EngineeringBay";92;0
"Unit";"Medivac";"Starport";95;2
"Unit";"Medivac";"Starport";97;2
"Unit";"Marine";"Barracks";99;1
"Unit";"Marauder";"Barracks";100;2
"Building";"Refinery";NA;102;0
"Unit";"Marine";"Barracks";105;1
"Unit";"Marine";"Barracks";106;1
"Unit";"Marine";"Barracks";107;1
"Unit";"Marine";"Barracks";109;1
"Unit";"Marine";"Barracks";112;1
"Building";"BarracksTechLab";NA;113;0
"Unit";"Medivac";"Starport";113;2
"Unit";"Medivac";"Starport";115;2
"Unit";"Marine";"Barracks";117;1
"Unit";"Marine";"Barracks";118;1
"Unit";"Marine";"Barracks";119;1
"Building";"Refinery";NA;120;0
"Unit";"Marauder";"Barracks";120;2
"Unit";"Marine";"Barracks";122;1
"Unit";"Marine";"Barracks";123;1
"Unit";"Marine";"Barracks";124;1
"Building";"Armory";NA;125;0
"Building";"CommandCenter";NA;125;0
"Unit";"Marauder";"Barracks";125;2
"Unit";"Marauder";"Barracks";127;2
"Unit";"Marine";"Barracks";129;1
"Unit";"Marine";"Barracks";130;1
"Unit";"Marine";"Barracks";131;1
"Unit";"Marine";"Barracks";132;1
"Unit";"Medivac";"Starport";133;2
"Unit";"Marauder";"Barracks";135;2
"Unit";"Marine";"Barracks";140;1
"Unit";"Marine";"Barracks";141;1
"Unit";"Marine";"Barracks";142;1
"Unit";"Marine";"Barracks";143;1
"Unit";"Marauder";"Barracks";144;2
"Unit";"Marauder";"Barracks";146;2
"Unit";"Medivac";"Starport";148;2
"Unit";"Marine";"Barracks";150;1
"Unit";"Medivac";"Starport";151;2
"Unit";"Marine";"Barracks";155;1
"Unit";"Marauder";"Barracks";156;2
"Unit";"Marauder";"Barracks";158;2
"Unit";"Marine";"Barracks";160;1
"Unit";"Marine";"Barracks";161;1
"Unit";"Marauder";"Barracks";163;2
"Building";"FactoryReactor";NA;165;0
"Building";"Starport";NA;166;0
"Unit";"Marine";"Barracks";167;1
"Unit";"Marine";"Barracks";168;1
"Unit";"Marine";"Barracks";169;1
"Upgrade";"TerranInfantryWeaponsLevel2";"EngineeringBay";172;0
"Unit";"Marauder";"Barracks";172;2
"Unit";"Marauder";"Barracks";174;2
"Unit";"Marine";"Barracks";176;1
"Unit";"Marine";"Barracks";177;1
"Building";"Refinery";NA;181;0
"Building";"Refinery";NA;181;0
"Building";"Starport";NA;181;0
"Building";"Starport";NA;184;0
"Building";"CommandCenter";NA;186;0
"Building";"StarportTechLab";NA;186;0
"Building";"Starport";NA;186;0
"Unit";"Liberator";"Starport";186;3
"Unit";"Liberator";"Starport";189;3
"Building";"StarportTechLab";NA;192;0
"Building";"SensorTower";NA;192;0
"Unit";"Raven";"Starport";192;2
"Unit";"Marine";"Barracks";197;1
"Building";"StarportTechLab";NA;199;0
"Building";"CommandCenter";NA;203;0
"Building";"CommandCenter";NA;203;0
"Unit";"Raven";"Starport";210;2
"Unit";"Raven";"Starport";212;2
"Unit";"Raven";"Starport";214;2
"Unit";"Liberator";"Starport";216;3
"Unit";"Liberator";"Starport";219;3
"Building";"Barracks";NA;222;0
"Building";"Barracks";NA;222;0
"Building";"Refinery";NA;222;0
"Building";"Refinery";NA;222;0
"Building";"FusionCore";NA;222;0
"Building";"CommandCenter";NA;222;0
"Building";"CommandCenter";NA;222;0
"Unit";"Raven";"Starport";225;2
"Unit";"Raven";"Starport";227;2
"Upgrade";"TerranShipWeaponsLevel1";"Armory";229;0
"Unit";"Raven";"Starport";229;2
"Upgrade";"TerranInfantryWeaponsLevel3";"EngineeringBay";231;0
"Building";"CommandCenter";NA;231;0
"Building";"Refinery";NA;231;0
"Building";"BarracksTechLab";NA;231;0
"Building";"BarracksTechLab";NA;231;0
"Unit";"Raven";"Starport";231;2
"Unit";"Raven";"Starport";233;2
"Building";"Refinery";NA;235;0
"Unit";"Raven";"Starport";242;2
"Building";"Armory";NA;247;0
"Upgrade";"TerranShipWeaponsLevel2";"Armory";248;0
"Unit";"Raven";"Starport";248;2
"Unit";"Raven";"Starport";250;2
"Unit";"Raven";"Starport";252;2
"Unit";"Marauder";"Barracks";254;2
"Unit";"Marauder";"Barracks";256;2
"Unit";"Marine";"Barracks";258;1
"Unit";"Marine";"Barracks";259;1
"Unit";"Marine";"Barracks";260;1
"Unit";"Marine";"Barracks";261;1
"Unit";"Marine";"Barracks";262;1
"Unit";"Marine";"Barracks";263;1
"Unit";"Marine";"Barracks";264;1
"Unit";"Marine";"Barracks";271;1
"Unit";"Liberator";"Starport";272;3
"Unit";"Liberator";"Starport";275;3
"Unit";"Liberator";"Starport";278;3
"Unit";"Liberator";"Starport";281;3
"Unit";"Marine";"Barracks";284;1
"Unit";"Marine";"Barracks";285;1
"Unit";"Raven";"Starport";288;2
"Unit";"Raven";"Starport";290;2
"Unit";"Marauder";"Barracks";292;2
"Unit";"Marauder";"Barracks";294;2
"Unit";"Marine";"Barracks";296;1
"Unit";"Marine";"Barracks";297;1
"Unit";"Marine";"Barracks";298;1
"Unit";"Marine";"Barracks";299;1
"Unit";"Marine";"Barracks";300;1
"Unit";"Marine";"Barracks";301;1
"Unit";"Marine";"Barracks";302;1
"Unit";"Raven";"Starport";305;2
"Unit";"Marine";"Barracks";313;1
"Unit";"Marine";"Barracks";314;1
"Unit";"Marine";"Barracks";315;1
"Unit";"Marine";"Barracks";316;1
"Unit";"Marine";"Barracks";317;1
"Unit";"Marine";"Barracks";318;1
"Unit";"Marine";"Barracks";319;1
"Unit";"Marine";"Barracks";320;1
"Unit";"Marine";"Barracks";321;1
"Unit";"Marine";"Barracks";322;1
"Unit";"Marine";"Barracks";323;1
"Unit";"Marine";"Barracks";324;1
"Unit";"Marine";"Barracks";325;1
"Upgrade";"SprayTerran";NA;328;0
"Upgrade";"SprayTerran";NA;328;0
"Upgrade";"SprayTerran";NA;328;0
"Upgrade";"SprayTerran";NA;328;0
"Upgrade";"SprayTerran";NA;328;0
"Upgrade";"ShieldWall";NA;328;0
"Upgrade";"PunisherGrenades";NA;328;0
"Upgrade";"SprayTerran";NA;328;0
"Upgrade";"TerranInfantryArmorsLevel1";NA;328;0
"Upgrade";"SprayTerran";NA;328;0
"Upgrade";"SprayTerran";NA;328;0
"Upgrade";"SprayTerran";NA;328;0
"Upgrade";"SprayTerran";NA;328;0
"Upgrade";"TerranInfantryArmorsLevel2";NA;328;0
"Upgrade";"RavenCorvidReactor";NA;328;0
"Upgrade";"SprayTerran";NA;328;0
"Upgrade";"SprayTerran";NA;328;0
"Upgrade";"SprayTerran";NA;328;0
"Upgrade";"SprayTerran";NA;328;0
"Upgrade";"SprayTerran";NA;328;0
"Upgrade";"SprayTerran";NA;328;0
"Upgrade";"SprayTerran";NA;328;0
"Upgrade";"LiberatorAGRangeUpgrade";NA;328;0
"Upgrade";"SprayTerran";NA;328;0
"Upgrade";"TerranInfantryArmorsLevel3";NA;328;0
