"Type";"UnitName";"OnBuilding";"TotalSupply";"Supply"
"Building";"SupplyDepot";NA;12;0
"Building";"Refinery";NA;12;0
"Building";"Barracks";NA;12;0
"Building";"Barracks";NA;12;0
"Unit";"Reaper";"Barracks";12;1
"Building";"Barracks";NA;12;0
"Unit";"Reaper";"Barracks";12;1
"Building";"Bunker";NA;13;0
"Unit";"Reaper";"Barracks";12;1
"Building";"Refinery";NA;14;0
"Unit";"Reaper";"Barracks";13;1
