"type";"unit_name";"on_building";"total_supply";"supply"
"Building";"Refinery";NA;15;0
"Building";"Barracks";NA;15;0
"Unit";"Reaper";"Barracks";19;1
"Unit";"Marine";"Barracks";21;1
"Building";"Refinery";NA;21;0
"Building";"Factory";NA;21;0
"Building";"BarracksReactor";NA;23;0
"Building";"CommandCenter";NA;19;0
"Unit";"Cyclone";"Factory";25;3
"Unit";"Marine";"Barracks";26;1
"Unit";"Marine";"Barracks";26;1
"Building";"FactoryTechLab";NA;32;0
"Building";"Bunker";NA;27;0
"Unit";"Marine";"Barracks";33;1
"Unit";"Marine";"Barracks";33;1
"Building";"Starport";NA;32;0
"Unit";"Marine";"Barracks";35;1
"Unit";"Marine";"Barracks";36;1
"Unit";"Marine";"Barracks";43;1
"Unit";"Marine";"Barracks";43;1
"Building";"FactoryTechLab";NA;45;0
"Building";"Barracks";NA;40;0
"Building";"EngineeringBay";NA;45;0
"Building";"EngineeringBay";NA;45;0
"Unit";"Marine";"Barracks";49;1
"Unit";"Marine";"Barracks";49;1
"Building";"Refinery";NA;53;0
"Building";"Refinery";NA;53;0
"Unit";"Marine";"Barracks";54;1
"Unit";"Marine";"Barracks";54;1
"Unit";"Marine";"Barracks";54;1
"Building";"StarportReactor";NA;58;0
"Unit";"Marine";"Barracks";63;1
"Unit";"Marine";"Barracks";63;1
"Unit";"Marine";"Barracks";63;1
"Upgrade";"TerranInfantryWeaponsLevel1";"EngineeringBay";56;0
"Upgrade";"TerranInfantryArmorsLevel1";"EngineeringBay";56;0
"Building";"CommandCenter";NA;61;0
"Unit";"Marine";"Barracks";69;1
"Unit";"Marine";"Barracks";69;1
"Unit";"Marine";"Barracks";69;1
"Unit";"Marine";"Barracks";70;1
"Building";"Barracks";NA;69;0
"Building";"Barracks";NA;69;0
"Unit";"Marine";"Barracks";73;1
"Unit";"Marine";"Barracks";75;1
"Unit";"Marine";"Barracks";79;1
"Unit";"Marine";"Barracks";79;1
"Upgrade";"Stimpack";"TechLab";64;0
"Unit";"Marine";"Barracks";81;1
"Unit";"Marine";"Barracks";81;1
"Building";"BarracksReactor";NA;79;0
"Building";"BarracksReactor";NA;79;0
"Unit";"Marine";"Barracks";84;1
"Building";"Armory";NA;76;0
"Building";"Barracks";NA;79;0
"Unit";"Medivac";"Starport";85;2
"Unit";"Medivac";"Starport";85;2
"Unit";"Marine";"Barracks";90;1
"Unit";"Marine";"Barracks";90;1
"Unit";"Marine";"Barracks";90;1
"Unit";"Marine";"Barracks";90;1
"Unit";"Marine";"Barracks";90;1
"Unit";"Marine";"Barracks";90;1
"Unit";"Marine";"Barracks";90;1
"Unit";"Marine";"Barracks";103;1
"Unit";"Marine";"Barracks";103;1
"Unit";"Marine";"Barracks";103;1
"Building";"BarracksReactor";NA;94;0
"Unit";"Marine";"Barracks";103;1
"Unit";"Marine";"Barracks";103;1
"Unit";"Marine";"Barracks";103;1
"Unit";"Marine";"Barracks";105;1
"Unit";"Medivac";"Starport";103;2
"Unit";"Medivac";"Starport";103;2
"Unit";"Marine";"Barracks";113;1
"Unit";"Marine";"Barracks";113;1
"Unit";"Marine";"Barracks";113;1
"Unit";"Marine";"Barracks";113;1
"Building";"Refinery";NA;119;0
"Unit";"Marine";"Barracks";119;1
"Unit";"Marine";"Barracks";119;1
"Building";"Refinery";NA;123;0
"Unit";"Medivac";"Starport";123;2
"Unit";"Medivac";"Starport";123;2
"Unit";"Marine";"Barracks";126;1
"Unit";"Marine";"Barracks";126;1
"Unit";"Marine";"Barracks";126;1
"Unit";"Marine";"Barracks";126;1
"Unit";"Marine";"Barracks";126;1
"Unit";"Marine";"Barracks";133;1
"Unit";"Marine";"Barracks";133;1
"Unit";"Marine";"Barracks";133;1
"Unit";"Marine";"Barracks";133;1
"Unit";"Marine";"Barracks";133;1
"Upgrade";"TerranInfantryWeaponsLevel2";"EngineeringBay";107;0
"Upgrade";"TerranInfantryArmorsLevel2";"EngineeringBay";107;0
"Unit";"Marine";"Barracks";146;1
"Unit";"Marine";"Barracks";146;1
"Unit";"Marine";"Barracks";146;1
"Unit";"Marine";"Barracks";146;1
"Unit";"Marine";"Barracks";146;1
"Unit";"Marine";"Barracks";146;1
"Building";"CommandCenter";NA;125;0
"Unit";"Liberator";"Starport";138;3
"Building";"Starport";NA;141;0
"Unit";"Marine";"Barracks";150;1
"Unit";"Marine";"Barracks";150;1
"Unit";"Marine";"Barracks";150;1
"Unit";"Marine";"Barracks";150;1
"Unit";"Marine";"Barracks";150;1
"Unit";"Marine";"Barracks";150;1
"Unit";"Marine";"Barracks";150;1
"Unit";"Marine";"Barracks";150;1
"Unit";"Marine";"Barracks";150;1
"Unit";"Liberator";"Starport";146;3
"Unit";"Marine";"Barracks";169;1
"Unit";"Marine";"Barracks";169;1
"Unit";"Marine";"Barracks";169;1
"Unit";"Marine";"Barracks";169;1
"Unit";"Marine";"Barracks";169;1
"Unit";"Marine";"Barracks";169;1
"Unit";"Marine";"Barracks";169;1
"Unit";"Marine";"Barracks";169;1
"Unit";"Marine";"Barracks";169;1
"Building";"StarportTechLab";NA;169;0
"Unit";"Marine";"Barracks";169;1
"Unit";"Marine";"Barracks";170;1
"Unit";"Marine";"Barracks";171;1
"Unit";"Marine";"Barracks";172;1
"Unit";"Marine";"Barracks";173;1
"Unit";"Marine";"Barracks";174;1
"Unit";"Marine";"Barracks";175;1
"Unit";"Marine";"Barracks";176;1
"Unit";"Marine";"Barracks";177;1
"Unit";"Liberator";"Starport";169;3
"Unit";"Liberator";"Starport";169;3
"Unit";"Marine";"Barracks";183;1
"Unit";"Marine";"Barracks";183;1
"Unit";"Marine";"Barracks";183;1
"Unit";"Marine";"Barracks";185;1
"Unit";"Marine";"Barracks";185;1
"Unit";"Marine";"Barracks";187;1
"Unit";"Marine";"Barracks";187;1
"Unit";"Marine";"Barracks";187;1
"Building";"FusionCore";NA;169;0
