"type";"unit_name";"on_building";"total_supply";"supply"
"Building";"Refinery";NA;15;0
"Building";"Barracks";NA;15;0
"Unit";"Reaper";"Barracks";19;1
"Unit";"Marine";"Barracks";19;1
"Building";"Refinery";NA;21;0
"Building";"Factory";NA;19;0
"Building";"CommandCenter";NA;19;0
"Building";"BarracksReactor";NA;23;0
"Unit";"Hellion";"Factory";23;2
"Unit";"Marine";"Barracks";24;1
"Unit";"Marine";"Barracks";24;1
"Building";"Starport";NA;24;0
"Unit";"Marine";"Barracks";29;1
"Unit";"Marine";"Barracks";29;1
"Unit";"Cyclone";"Factory";29;3
"Unit";"Medivac";"Starport";30;2
"Unit";"Marine";"Barracks";37;1
"Unit";"Marine";"Barracks";37;1
"Unit";"Marine";"Barracks";45;1
"Unit";"Marine";"Barracks";45;1
"Unit";"Cyclone";"Factory";45;3
"Unit";"Marine";"Barracks";48;1
"Unit";"Marine";"Barracks";48;1
"Building";"StarportTechLab";NA;48;0
"Building";"FactoryTechLab";NA;54;0
"Unit";"Marine";"Barracks";57;1
"Unit";"Marine";"Barracks";57;1
"Building";"Refinery";NA;58;0
"Building";"Refinery";NA;58;0
"Unit";"Raven";"Starport";57;2
"Building";"BarracksTechLab";NA;62;0
"Building";"CommandCenter";NA;53;0
"Building";"Barracks";NA;62;0
"Building";"Barracks";NA;62;0
"Building";"EngineeringBay";NA;65;0
"Building";"EngineeringBay";NA;65;0
"Unit";"Marine";"Barracks";66;1
"Unit";"Marine";"Barracks";72;1
"Building";"BarracksReactor";NA;68;0
"Building";"BarracksReactor";NA;68;0
"Unit";"Marine";"Barracks";73;1
"Unit";"Marine";"Barracks";74;1
"Unit";"Marine";"Barracks";74;1
"Building";"Barracks";NA;71;0
"Unit";"Marine";"Barracks";76;1
"Unit";"Marine";"Barracks";76;1
"Building";"Barracks";NA;73;0
"Unit";"Marine";"Barracks";76;1
"Building";"MissileTurret";NA;79;0
"Building";"MissileTurret";NA;79;0
"Building";"MissileTurret";NA;79;0
"Unit";"Marine";"Barracks";81;1
"Unit";"Marine";"Barracks";81;1
"Unit";"Marine";"Barracks";82;1
"Unit";"Marine";"Barracks";82;1
"Unit";"Marine";"Barracks";82;1
"Building";"BarracksReactor";NA;79;0
"Upgrade";"Stimpack";"TechLab";71;0
"Building";"BarracksReactor";NA;81;0
"Unit";"Marine";"Barracks";87;1
"Unit";"Medivac";"Starport";82;2
"Unit";"Marine";"Barracks";89;1
"Unit";"Marine";"Barracks";89;1
"Unit";"Marine";"Barracks";89;1
"Unit";"Marine";"Barracks";89;1
"Upgrade";"TerranInfantryWeaponsLevel1";"EngineeringBay";74;0
"Upgrade";"TerranInfantryArmorsLevel1";"EngineeringBay";74;0
"Unit";"Marine";"Barracks";91;1
"Unit";"Marine";"Barracks";94;1
"Unit";"Medivac";"Starport";91;2
"Unit";"Marine";"Barracks";100;1
"Unit";"Medivac";"Starport";99;2
"Unit";"Marine";"Barracks";101;1
"Unit";"Marine";"Barracks";102;1
"Unit";"Marine";"Barracks";103;1
"Unit";"Marine";"Barracks";103;1
"Unit";"Marine";"Barracks";103;1
"Unit";"Marine";"Barracks";107;1
"Unit";"Marine";"Barracks";110;1
"Unit";"Marine";"Barracks";110;1
"Unit";"Marine";"Barracks";110;1
"Unit";"Medivac";"Starport";105;2
"Unit";"Marine";"Barracks";112;1
"Unit";"Marine";"Barracks";113;1
"Unit";"Marine";"Barracks";117;1
"Unit";"Marine";"Barracks";117;1
"Unit";"Marine";"Barracks";117;1
"Building";"SensorTower";NA;117;0
"Unit";"Marine";"Barracks";117;1
"Building";"Refinery";NA;118;0
"Building";"Refinery";NA;118;0
"Unit";"Marine";"Barracks";118;1
"Unit";"Marine";"Barracks";119;1
"Unit";"Marine";"Barracks";121;1
"Building";"Armory";NA;104;0
"Unit";"Medivac";"Starport";118;2
"Unit";"Marine";"Barracks";129;1
"Unit";"Marine";"Barracks";129;1
"Unit";"Marine";"Barracks";129;1
"Unit";"Marine";"Barracks";129;1
"Unit";"Marine";"Barracks";129;1
"Unit";"Medivac";"Starport";121;2
"Unit";"Marine";"Barracks";132;1
"Unit";"Marine";"Barracks";134;1
"Unit";"Marine";"Barracks";134;1
"Unit";"Marine";"Barracks";134;1
"Unit";"Marine";"Barracks";141;1
"Unit";"Marine";"Barracks";141;1
"Unit";"Marine";"Barracks";141;1
"Unit";"Marine";"Barracks";141;1
"Unit";"Medivac";"Starport";132;2
"Unit";"Marine";"Barracks";141;1
"Unit";"Marine";"Barracks";144;1
"Unit";"Marine";"Barracks";144;1
"Unit";"Marine";"Barracks";144;1
"Building";"Factory";NA;141;0
"Unit";"Marine";"Barracks";152;1
"Unit";"Marine";"Barracks";152;1
"Unit";"Marine";"Barracks";155;1
"Unit";"Marine";"Barracks";155;1
"Unit";"Marine";"Barracks";155;1
"Unit";"Marine";"Barracks";155;1
"Unit";"Marine";"Barracks";155;1
"Unit";"Marine";"Barracks";155;1
"Unit";"Marine";"Barracks";155;1
"Unit";"Marine";"Barracks";155;1
"Unit";"Marine";"Barracks";156;1
"Unit";"Marine";"Barracks";157;1
"Unit";"Marine";"Barracks";158;1
"Unit";"Medivac";"Starport";155;2
"Unit";"Medivac";"Starport";155;2
"Unit";"Marine";"Barracks";172;1
"Unit";"Marine";"Barracks";172;1
"Unit";"Marine";"Barracks";172;1
"Unit";"Marine";"Barracks";172;1
"Unit";"Marine";"Barracks";172;1
"Unit";"Marine";"Barracks";172;1
"Unit";"Marine";"Barracks";172;1
"Unit";"Marine";"Barracks";172;1
"Unit";"Marine";"Barracks";172;1
"Unit";"Marine";"Barracks";172;1
"Unit";"Marine";"Barracks";178;1
"Unit";"Marine";"Barracks";178;1
"Unit";"Marine";"Barracks";178;1
"Unit";"Marine";"Barracks";178;1
"Unit";"Marine";"Barracks";178;1
"Upgrade";"TerranInfantryWeaponsLevel2";"EngineeringBay";155;0
"Unit";"Marine";"Barracks";187;1
"Unit";"Marine";"Barracks";187;1
"Upgrade";"TerranInfantryArmorsLevel2";"EngineeringBay";157;0
