"Type";"UnitName";"OnBuilding";"TotalSupply";"Supply"
"Unit";"SCV";"Command Center";12;1
"Unit";"SCV";"Command Center";12;1
"Unit";"SCV";"Command Center";13;1
"Building";"SupplyDepot";NA;13;0
"Building";"Refinery";NA;14;0
"Unit";"SCV";"Command Center";15;1
"Unit";"SCV";"Command Center";15;1
"Unit";"SCV";"Command Center";16;1
"Building";"Barracks";NA;15;0
"Unit";"SCV";"Command Center";17;1
"Building";"Refinery";NA;17;0
"Building";"BarracksTechLab";NA;18;0
"Building";"SupplyDepot";NA;19;0
"Unit";"Marauder";"Barracks";19;2
"Unit";"SCV";"Command Center";19;1
"Building";"Factory";NA;19;0
"Unit";"Marauder";"Barracks";19;2
"Unit";"SCV";"Command Center";21;1
"Unit";"SCV";"Command Center";24;1
"Unit";"Marauder";"Barracks";25;2
"Unit";"SCV";"Command Center";25;1
"Building";"SupplyDepot";NA;25;0
"Building";"Starport";NA;22;0
"Building";"FactoryReactor";NA;25;0
"Unit";"SCV";"Command Center";29;1
"Unit";"Marauder";"Barracks";26;2
"Unit";"SCV";"Command Center";29;1
"Unit";"Marauder";"Barracks";30;2
"Unit";"Medivac";"Starport";29;2
"Building";"StarportTechLab";NA;37;0
"Unit";"Marine";"Barracks";37;1
"Building";"SupplyDepot";NA;37;0
"Building";"FusionCore";NA;37;0
"Unit";"Marine";"Barracks";37;1
"Building";"SupplyDepot";NA;38;0
"Building";"CommandCenter";NA;33;0
"Unit";"SCV";"Command Center";39;1
"Unit";"SCV";"Command Center";39;1
"Building";"Refinery";NA;40;0
"Unit";"SCV";"Command Center";40;1
"Unit";"Battlecruiser";"Starport";39;6
"Unit";"SCV";"Command Center";41;1
"Unit";"SCV";"Command Center";41;1
"Unit";"Marine";"Barracks";41;1
"Unit";"SCV";"Command Center";48;1
"Unit";"SCV";"Command Center";49;1
"Building";"Refinery";NA;48;0
"Unit";"Marine";"Barracks";50;1
"Unit";"SCV";"Command Center";51;1
"Building";"CommandCenter";NA;39;0
"Unit";"SCV";"Command Center";55;1
"Unit";"SCV";"Command Center";55;1
"Unit";"SCV";"Command Center";55;1
"Unit";"SCV";"Command Center";56;1
"Building";"SupplyDepot";NA;55;0
"Unit";"SCV";"Command Center";57;1
"Building";"SupplyDepot";NA;57;0
"Unit";"SCV";"Command Center";57;1
"Unit";"SCV";"Command Center";58;1
"Unit";"SCV";"Command Center";59;1
"Building";"EngineeringBay";NA;57;0
"Unit";"SCV";"Command Center";60;1
"Unit";"SCV";"Command Center";61;1
"Building";"Armory";NA;55;0
"Unit";"Battlecruiser";"Starport";53;6
"Building";"Armory";NA;55;0
"Unit";"Marine";"Barracks";62;1
"Unit";"SCV";"Command Center";63;1
"Unit";"SCV";"Command Center";64;1
"Building";"Starport";NA;60;0
"Unit";"SCV";"Command Center";72;1
"Unit";"SCV";"Command Center";73;1
"Building";"Refinery";NA;71;0
"Unit";"SCV";"Command Center";75;1
"Building";"StarportTechLab";NA;76;0
"Unit";"Marine";"Barracks";76;1
"Unit";"SCV";"Command Center";76;1
"Unit";"SCV";"Command Center";77;1
"Building";"SupplyDepot";NA;76;0
"Unit";"SCV";"Command Center";77;1
"Unit";"SCV";"Command Center";78;1
"Unit";"SCV";"Command Center";79;1
"Unit";"Marine";"Barracks";77;1
"Unit";"SCV";"Command Center";80;1
"Unit";"SCV";"Command Center";81;1
"Unit";"Battlecruiser";"Starport";72;6
"Unit";"SCV";"Command Center";82;1
"Building";"SupplyDepot";NA;80;0
"Building";"Refinery";NA;80;0
"Unit";"SCV";"Command Center";84;1
"Unit";"SCV";"Command Center";85;1
"Unit";"SCV";"Command Center";92;1
"Unit";"SCV";"Command Center";95;1
"Unit";"SCV";"Command Center";96;1
"Upgrade";"TerranVehicleAndShipArmorsLevel1";"Armory";79;0
"Building";"SupplyDepot";NA;97;0
"Unit";"Battlecruiser";"Starport";84;6
"Unit";"Marine";"Barracks";98;1
"Unit";"Hellion";"Factory";98;2
"Unit";"Hellion";"Factory";98;2
"Upgrade";"TerranShipWeaponsLevel1";"Armory";82;0
"Unit";"Battlecruiser";"Starport";95;6
"Unit";"Hellion";"Factory";105;2
"Unit";"Hellion";"Factory";107;2
"Building";"Starport";NA;98;0
"Building";"CommandCenter";NA;97;0
"Building";"StarportTechLab";NA;119;0
"Building";"SupplyDepot";NA;119;0
"Unit";"Battlecruiser";"Starport";98;6
"Building";"Starport";NA;119;0
"Building";"Bunker";NA;119;0
"Building";"SupplyDepot";NA;125;0
"Building";"StarportTechLab";NA;125;0
"Building";"SensorTower";NA;125;0
"Building";"MissileTurret";NA;125;0
"Unit";"Battlecruiser";"Starport";119;6
"Unit";"Battlecruiser";"Starport";125;6
"Unit";"SCV";"Command Center";137;1
"Upgrade";"TerranShipWeaponsLevel2";"Armory";119;0
"Upgrade";"TerranVehicleAndShipArmorsLevel2";"Armory";119;0
"Unit";"SCV";"Command Center";137;1
"Building";"MissileTurret";NA;137;0
"Building";"Refinery";NA;137;0
"Building";"Refinery";NA;137;0
"Unit";"SCV";"Command Center";138;1
"Unit";"Battlecruiser";"Starport";125;6
"Unit";"Battlecruiser";"Starport";125;6
"Unit";"SCV";"Command Center";139;1
"Unit";"Battlecruiser";"Starport";131;6
"Unit";"SCV";"Command Center";152;1
"Building";"CommandCenter";NA;137;0
"Unit";"Battlecruiser";"Starport";138;6
"Building";"Refinery";NA;160;0
"Building";"Refinery";NA;166;0
"Unit";"Battlecruiser";"Starport";153;6
"Unit";"Battlecruiser";"Starport";153;6
"Unit";"Battlecruiser";"Starport";160;6
"Building";"MissileTurret";NA;166;0
"Unit";"Hellion";"Factory";184;2
"Unit";"Hellion";"Factory";184;2
"Unit";"SCV";"Command Center";184;1
"Unit";"Battlecruiser";"Starport";166;6
"Unit";"SCV";"Command Center";188;1
"Unit";"Hellion";"Factory";184;2
"Unit";"Hellion";"Factory";186;2
"Unit";"SCV";"Command Center";195;1
"Building";"SupplyDepot";NA;195;0
"Building";"SupplyDepot";NA;195;0
"Unit";"Battlecruiser";"Starport";178;6
"Unit";"SCV";"Command Center";200;1
"Unit";"Battlecruiser";"Starport";184;6
"Unit";"SCV";"Command Center";207;1
"Unit";"Hellion";"Factory";201;2
"Unit";"Hellion";"Factory";201;2
"Building";"CommandCenter";NA;188;0
"Unit";"Hellion";"Factory";215;2
"Unit";"Hellion";"Factory";217;2
"Unit";"Battlecruiser";"Starport";201;6
"Upgrade";"TerranShipWeaponsLevel3";"Armory";184;0
"Upgrade";"TerranVehicleAndShipArmorsLevel3";"Armory";188;0
"Unit";"Raven";"Starport";219;2
"Unit";"Battlecruiser";"Starport";208;6
"Unit";"Battlecruiser";"Starport";208;6
