"type";"unit_name";"on_building";"total_supply";"supply"
"Building";"Refinery";NA;14;0
"Building";"Barracks";NA;15;0
"Unit";"Reaper";"Barracks";19;1
"Building";"Refinery";NA;20;0
"Building";"Factory";NA;19;0
"Unit";"Reaper";"Barracks";21;1
"Building";"CommandCenter";NA;19;0
"Unit";"Hellion";"Factory";22;2
"Building";"Starport";NA;22;0
"Building";"BarracksReactor";NA;24;0
"Building";"FactoryTechLab";NA;29;0
"Unit";"Marine";"Barracks";29;1
"Unit";"Marine";"Barracks";29;1
"Unit";"Medivac";"Starport";29;2
"Unit";"Marine";"Barracks";33;1
"Unit";"Marine";"Barracks";33;1
"Unit";"Marine";"Barracks";40;1
"Unit";"Marine";"Barracks";40;1
"Unit";"Marine";"Barracks";44;1
"Unit";"Marine";"Barracks";44;1
"Unit";"Liberator";"Starport";40;3
"Unit";"Marine";"Barracks";50;1
"Unit";"Marine";"Barracks";50;1
"Building";"Refinery";NA;56;0
"Building";"Refinery";NA;56;0
"Building";"FactoryTechLab";NA;58;0
"Unit";"Marine";"Barracks";58;1
"Building";"EngineeringBay";NA;58;0
"Building";"StarportReactor";NA;58;0
"Unit";"Marine";"Barracks";63;1
"Building";"Barracks";NA;58;0
"Building";"CommandCenter";NA;54;0
"Unit";"Marine";"Barracks";65;1
"Unit";"Marine";"Barracks";66;1
"Unit";"Marine";"Barracks";66;1
"Unit";"Marine";"Barracks";68;1
"Unit";"Marine";"Barracks";69;1
"Unit";"Marine";"Barracks";73;1
"Unit";"Marine";"Barracks";74;1
"Building";"Barracks";NA;66;0
"Building";"EngineeringBay";NA;73;0
"Unit";"Marine";"Barracks";77;1
"Unit";"Marine";"Barracks";79;1
"Upgrade";"Stimpack";"TechLab";64;0
"Building";"Armory";NA;73;0
"Unit";"Marine";"Barracks";81;1
"Unit";"Marine";"Barracks";81;1
"Unit";"Marine";"Barracks";82;1
"Unit";"Marine";"Barracks";83;1
"Unit";"Marine";"Barracks";84;1
"Unit";"Marine";"Barracks";85;1
"Building";"BarracksReactor";NA;83;0
"Unit";"Medivac";"Starport";83;2
"Unit";"Medivac";"Starport";83;2
"Unit";"Marine";"Barracks";86;1
"Unit";"Marine";"Barracks";87;1
"Upgrade";"TerranInfantryWeaponsLevel1";"EngineeringBay";76;0
"Unit";"Marine";"Barracks";88;1
"Unit";"Marine";"Barracks";94;1
"Unit";"Marine";"Barracks";94;1
"Unit";"Marine";"Barracks";95;1
"Unit";"Marine";"Barracks";97;1
"Unit";"Medivac";"Starport";90;2
"Unit";"Medivac";"Starport";92;2
"Unit";"Marine";"Barracks";97;1
"Unit";"Marine";"Barracks";99;1
"Building";"CommandCenter";NA;83;0
"Unit";"Marine";"Barracks";102;1
"Unit";"Marine";"Barracks";102;1
"Unit";"Marine";"Barracks";104;1
"Unit";"Marine";"Barracks";109;1
"Unit";"Marine";"Barracks";110;1
"Building";"Barracks";NA;95;0
"Building";"Barracks";NA;95;0
"Unit";"Marine";"Barracks";111;1
"Unit";"Medivac";"Starport";111;2
"Unit";"Medivac";"Starport";111;2
"Building";"MissileTurret";NA;117;0
"Building";"MissileTurret";NA;117;0
"Building";"MissileTurret";NA;117;0
"Building";"MissileTurret";NA;118;0
"Unit";"Marine";"Barracks";118;1
"Unit";"Marine";"Barracks";118;1
"Building";"SensorTower";NA;119;0
"Unit";"Marine";"Barracks";119;1
"Unit";"Marine";"Barracks";119;1
"Unit";"Marine";"Barracks";123;1
"Unit";"Marine";"Barracks";123;1
"Unit";"Marine";"Barracks";124;1
"Upgrade";"TerranInfantryArmorsLevel1";"EngineeringBay";99;0
"Building";"BarracksReactor";NA;119;0
"Upgrade";"TerranVehicleWeaponsLevel1";"Armory";99;0
"Building";"BarracksReactor";NA;119;0
"Unit";"Marine";"Barracks";128;1
"Unit";"Marine";"Barracks";131;1
"Unit";"Marine";"Barracks";131;1
"Unit";"Medivac";"Starport";126;2
"Unit";"Marine";"Barracks";131;1
"Unit";"Medivac";"Starport";128;2
"Unit";"Marine";"Barracks";133;1
"Unit";"Marine";"Barracks";133;1
"Building";"Refinery";NA;134;0
"Building";"Refinery";NA;134;0
"Unit";"Marine";"Barracks";145;1
"Unit";"Marine";"Barracks";145;1
"Unit";"Marine";"Barracks";145;1
"Unit";"Marine";"Barracks";145;1
"Unit";"Marine";"Barracks";145;1
"Unit";"Marine";"Barracks";145;1
"Unit";"Marine";"Barracks";145;1
"Unit";"Marine";"Barracks";145;1
"Unit";"Marine";"Barracks";149;1
"Unit";"Marine";"Barracks";149;1
"Unit";"Medivac";"Starport";145;2
"Unit";"Medivac";"Starport";145;2
"Unit";"Marine";"Barracks";155;1
"Unit";"Marine";"Barracks";155;1
"Unit";"Marine";"Barracks";155;1
"Unit";"Marine";"Barracks";155;1
"Unit";"Marine";"Barracks";155;1
"Unit";"Marine";"Barracks";155;1
"Unit";"Medivac";"Starport";157;2
"Unit";"Marine";"Barracks";169;1
"Unit";"Marine";"Barracks";169;1
"Unit";"Marine";"Barracks";169;1
"Unit";"Marine";"Barracks";169;1
"Unit";"Marine";"Barracks";169;1
"Unit";"Marine";"Barracks";169;1
"Unit";"Marine";"Barracks";169;1
"Unit";"Marine";"Barracks";169;1
"Unit";"Marine";"Barracks";169;1
"Building";"Factory";NA;161;0
"Unit";"Marine";"Barracks";171;1
"Building";"Barracks";NA;161;0
"Building";"Barracks";NA;161;0
"Upgrade";"TerranInfantryWeaponsLevel2";"EngineeringBay";145;0
"Upgrade";"TerranInfantryArmorsLevel2";"EngineeringBay";149;0
"Unit";"Marine";"Barracks";181;1
"Unit";"Marine";"Barracks";181;1
"Unit";"Marine";"Barracks";181;1
"Building";"CommandCenter";NA;161;0
"Unit";"Marine";"Barracks";181;1
"Unit";"Marine";"Barracks";181;1
"Building";"FactoryTechLab";NA;181;0
"Unit";"Marine";"Barracks";181;1
"Unit";"Marine";"Barracks";181;1
"Unit";"Marine";"Barracks";181;1
"Unit";"Marine";"Barracks";181;1
"Unit";"Marine";"Barracks";186;1
"Unit";"Marine";"Barracks";186;1
"Unit";"Marine";"Barracks";186;1
"Unit";"Marine";"Barracks";186;1
"Unit";"Marine";"Barracks";186;1
"Upgrade";"TerranVehicleWeaponsLevel2";"Armory";161;0
"Building";"Barracks";NA;195;0
"Building";"Barracks";NA;195;0
"Building";"Barracks";NA;195;0
"Building";"CommandCenter";NA;195;0
"Building";"StarportTechLab";NA;195;0
"Building";"CommandCenter";NA;195;0
"Unit";"Marine";"Barracks";195;1
"Unit";"Marine";"Barracks";195;1
"Unit";"Marine";"Barracks";195;1
"Unit";"Banshee";"Starport";195;3
