"Type";"UnitName";"OnBuilding";"TotalSupply";"Supply"
"Building";"SupplyDepot";NA;12;0
"Building";"Refinery";NA;12;0
"Building";"Barracks";NA;12;0
"Building";"Barracks";NA;12;0
"Unit";"Reaper";"Barracks";12;1
"Building";"Barracks";NA;12;0
"Unit";"Reaper";"Barracks";12;1
"Unit";"Reaper";"Barracks";12;1
"Unit";"Reaper";"Barracks";13;1
"Unit";"Reaper";"Barracks";14;1
"Unit";"Reaper";"Barracks";15;1
"Building";"Refinery";NA;16;0
