"type";"unit_name";"on_building";"total_supply";"supply"
"Building";"Refinery";NA;14;0
"Building";"Barracks";NA;15;0
"Unit";"Reaper";"Barracks";19;1
"Unit";"Marine";"Barracks";21;1
"Building";"Refinery";NA;22;0
"Building";"Factory";NA;19;0
"Building";"CommandCenter";NA;19;0
"Building";"BarracksReactor";NA;23;0
"Unit";"Hellion";"Factory";24;2
"Unit";"Marine";"Barracks";25;1
"Unit";"Marine";"Barracks";25;1
"Building";"Starport";NA;24;0
"Unit";"Marine";"Barracks";31;1
"Unit";"Marine";"Barracks";31;1
"Unit";"Cyclone";"Factory";31;3
"Unit";"Medivac";"Starport";31;2
"Building";"EngineeringBay";NA;41;0
"Unit";"Cyclone";"Factory";42;3
"Building";"BarracksTechLab";NA;47;0
"Building";"FactoryTechLab";NA;50;0
"Unit";"Marine";"Barracks";53;1
"Building";"Barracks";NA;46;0
"Building";"Barracks";NA;46;0
"Unit";"Marine";"Barracks";58;1
"Unit";"Marine";"Barracks";58;1
"Unit";"Marine";"Barracks";58;1
"Building";"MissileTurret";NA;62;0
"Building";"Refinery";NA;60;0
"Building";"Refinery";NA;60;0
"Building";"MissileTurret";NA;65;0
"Unit";"Marine";"Barracks";67;1
"Unit";"Marine";"Barracks";67;1
"Unit";"Marine";"Barracks";67;1
"Building";"StarportReactor";NA;65;0
"Building";"BarracksReactor";NA;65;0
"Building";"Bunker";NA;67;0
"Unit";"Marine";"Barracks";69;1
"Unit";"Marine";"Barracks";74;1
"Unit";"Marine";"Barracks";74;1
"Unit";"Marine";"Barracks";74;1
"Unit";"Marine";"Barracks";74;1
"Upgrade";"Stimpack";"TechLab";58;0
"Unit";"Marine";"Barracks";74;1
"Unit";"Medivac";"Starport";74;2
"Unit";"Medivac";"Starport";74;2
"Unit";"Marine";"Barracks";75;1
"Unit";"Marine";"Barracks";76;1
"Unit";"Marine";"Barracks";77;1
"Unit";"Marine";"Barracks";78;1
"Unit";"Marine";"Barracks";79;1
"Unit";"Marine";"Barracks";90;1
"Unit";"Marine";"Barracks";90;1
"Unit";"Marine";"Barracks";90;1
"Unit";"Marine";"Barracks";90;1
"Unit";"Medivac";"Starport";88;2
"Unit";"Medivac";"Starport";88;2
"Unit";"Marine";"Barracks";91;1
"Unit";"Marine";"Barracks";91;1
"Unit";"Marine";"Barracks";92;1
"Upgrade";"TerranInfantryWeaponsLevel1";"EngineeringBay";74;0
"Unit";"Marine";"Barracks";102;1
"Unit";"Marine";"Barracks";102;1
"Unit";"Marine";"Barracks";104;1
"Unit";"Marine";"Barracks";104;1
"Unit";"Marine";"Barracks";104;1
"Building";"CommandCenter";NA;88;0
"Unit";"Marine";"Barracks";104;1
"Unit";"Marine";"Barracks";105;1
"Building";"EngineeringBay";NA;104;0
"Unit";"Marine";"Barracks";106;1
"Unit";"Marine";"Barracks";107;1
"Unit";"Marine";"Barracks";108;1
"Unit";"Medivac";"Starport";106;2
"Building";"Barracks";NA;104;0
"Unit";"Marine";"Barracks";109;1
"Building";"Barracks";NA;104;0
"Unit";"Marine";"Barracks";110;1
"Unit";"Marine";"Barracks";111;1
"Unit";"Marine";"Barracks";112;1
"Unit";"Marine";"Barracks";113;1
"Unit";"Medivac";"Starport";109;2
"Unit";"Marine";"Barracks";116;1
"Unit";"Marine";"Barracks";117;1
"Unit";"Marine";"Barracks";118;1
"Unit";"Marine";"Barracks";127;1
"Unit";"Marine";"Barracks";127;1
"Unit";"Marine";"Barracks";127;1
"Unit";"Marine";"Barracks";127;1
"Unit";"Marine";"Barracks";127;1
"Building";"BarracksReactor";NA;121;0
"Unit";"Medivac";"Starport";127;2
"Unit";"Medivac";"Starport";127;2
"Building";"BarracksReactor";NA;125;0
"Building";"Refinery";NA;128;0
"Unit";"Marine";"Barracks";128;1
"Building";"Refinery";NA;128;0
"Unit";"Marine";"Barracks";132;1
"Unit";"Marine";"Barracks";132;1
"Unit";"Marauder";"Barracks";131;2
"Unit";"Marine";"Barracks";134;1
"Building";"MissileTurret";NA;140;0
"Unit";"Marine";"Barracks";140;1
"Building";"MissileTurret";NA;142;0
"Building";"SensorTower";NA;143;0
"Unit";"Marine";"Barracks";144;1
"Unit";"Marine";"Barracks";145;1
"Unit";"Marine";"Barracks";146;1
"Upgrade";"TerranInfantryArmorsLevel1";"EngineeringBay";114;0
"Building";"MissileTurret";NA;149;0
"Unit";"Marine";"Barracks";149;1
"Unit";"Marine";"Barracks";149;1
"Unit";"Marine";"Barracks";149;1
"Unit";"Marine";"Barracks";149;1
"Unit";"Marine";"Barracks";149;1
"Building";"MissileTurret";NA;149;0
"Building";"Factory";NA;136;0
"Unit";"Marine";"Barracks";150;1
"Unit";"Marine";"Barracks";151;1
"Unit";"Marine";"Barracks";152;1
"Unit";"Marine";"Barracks";153;1
"Unit";"Marine";"Barracks";154;1
"Unit";"Marine";"Barracks";155;1
"Unit";"Marine";"Barracks";156;1
"Unit";"Marine";"Barracks";157;1
"Unit";"Marine";"Barracks";157;1
"Unit";"Marine";"Barracks";159;1
"Building";"Armory";NA;149;0
"Unit";"Marine";"Barracks";160;1
"Unit";"Marine";"Barracks";161;1
"Unit";"Marine";"Barracks";162;1
"Unit";"Marine";"Barracks";163;1
"Unit";"Marine";"Barracks";168;1
"Unit";"Marine";"Barracks";168;1
"Unit";"Marine";"Barracks";171;1
"Unit";"Marine";"Barracks";172;1
"Unit";"Marine";"Barracks";172;1
"Unit";"Marine";"Barracks";172;1
"Unit";"Marine";"Barracks";172;1
"Unit";"Marine";"Barracks";172;1
"Unit";"Marine";"Barracks";172;1
"Unit";"Marine";"Barracks";173;1
"Unit";"Marine";"Barracks";174;1
"Unit";"Medivac";"Starport";172;2
"Unit";"Medivac";"Starport";172;2
"Unit";"Marine";"Barracks";181;1
"Unit";"Marine";"Barracks";181;1
"Unit";"Marine";"Barracks";181;1
"Unit";"Marine";"Barracks";181;1
"Unit";"Marine";"Barracks";181;1
"Unit";"Marine";"Barracks";181;1
"Unit";"Marine";"Barracks";181;1
"Building";"FactoryTechLab";NA;182;0
"Unit";"Marine";"Barracks";182;1
"Building";"MissileTurret";NA;184;0
"Unit";"Marine";"Barracks";189;1
"Unit";"Marine";"Barracks";195;1
"Unit";"Marine";"Barracks";195;1
"Unit";"Marine";"Barracks";195;1
"Unit";"Marine";"Barracks";195;1
"Unit";"Marine";"Barracks";195;1
"Building";"MissileTurret";NA;195;0
"Unit";"Marine";"Barracks";196;1
"Unit";"Marine";"Barracks";196;1
"Unit";"Marine";"Barracks";196;1
"Unit";"Marine";"Barracks";196;1
"Unit";"Marine";"Barracks";202;1
"Unit";"Marine";"Barracks";202;1
"Unit";"Marine";"Barracks";202;1
"Unit";"Marine";"Barracks";202;1
"Unit";"Marine";"Barracks";202;1
"Unit";"Marine";"Barracks";202;1
"Unit";"Marine";"Barracks";203;1
"Unit";"Marine";"Barracks";204;1
