"Type";"UnitName";"OnBuilding";"TotalSupply";"Supply"
"Unit";"SCV";"Command Center";12;1
"Unit";"SCV";"Command Center";12;1
"Unit";"SCV";"Command Center";13;1
"Building";"SupplyDepot";NA;13;0
"Building";"Refinery";NA;14;0
"Unit";"SCV";"Command Center";15;1
"Unit";"SCV";"Command Center";15;1
"Unit";"SCV";"Command Center";16;1
"Unit";"SCV";"Command Center";18;1
"Building";"Barracks";NA;15;0
"Unit";"Reaper";"Barracks";19;1
"Unit";"SCV";"Command Center";19;1
"Unit";"SCV";"Command Center";21;1
"Building";"BarracksReactor";NA;20;0
"Unit";"SCV";"Command Center";22;1
"Building";"SupplyDepot";NA;21;0
"Building";"Refinery";NA;21;0
"Building";"Factory";NA;20;0
"Unit";"SCV";"Command Center";23;1
"Unit";"Marine";"Barracks";23;1
"Unit";"Marine";"Barracks";23;1
"Unit";"SCV";"Command Center";23;1
"Building";"CommandCenter";NA;19;0
"Unit";"SCV";"Command Center";26;1
"Unit";"Marine";"Barracks";26;1
"Unit";"Marine";"Barracks";26;1
"Building";"Starport";NA;23;0
"Unit";"SCV";"Command Center";30;1
"Unit";"Marine";"Barracks";28;1
"Unit";"Marine";"Barracks";29;1
"Unit";"Cyclone";"Factory";30;3
"Unit";"SCV";"Command Center";30;1
"Unit";"SCV";"Command Center";33;1
"Unit";"Marine";"Barracks";31;1
"Unit";"Marine";"Barracks";32;1
"Unit";"SCV";"Command Center";36;1
"Unit";"Medivac";"Starport";30;2
"Unit";"SCV";"Command Center";40;1
"Building";"SupplyDepot";NA;38;0
"Unit";"Cyclone";"Factory";38;3
"Unit";"SCV";"Command Center";44;1
"Unit";"SCV";"Command Center";44;1
"Building";"EngineeringBay";NA;43;0
"Unit";"Marine";"Barracks";44;1
"Unit";"Marine";"Barracks";44;1
"Unit";"SCV";"Command Center";47;1
"Unit";"SCV";"Command Center";47;1
"Building";"SupplyDepot";NA;47;0
"Building";"FactoryTechLab";NA;49;0
"Building";"SupplyDepot";NA;49;0
"Unit";"SCV";"Command Center";51;1
"Unit";"SCV";"Command Center";51;1
"Unit";"SCV";"Command Center";53;1
"Unit";"SCV";"Command Center";53;1
"Building";"BarracksTechLab";NA;55;0
"Unit";"SCV";"Command Center";55;1
"Unit";"SCV";"Command Center";55;1
"Unit";"SCV";"Command Center";57;1
"Unit";"SCV";"Command Center";57;1
"Building";"StarportReactor";NA;55;0
"Unit";"Marine";"Barracks";57;1
"Building";"Barracks";NA;53;0
"Building";"Barracks";NA;53;0
"Building";"Refinery";NA;57;0
"Building";"Refinery";NA;57;0
"Unit";"SCV";"Command Center";59;1
"Unit";"SCV";"Command Center";59;1
"Building";"SupplyDepot";NA;59;0
"Unit";"Marine";"Barracks";62;1
"Unit";"Marine";"Barracks";62;1
"Unit";"Marine";"Barracks";62;1
"Unit";"SCV";"Command Center";62;1
"Unit";"SCV";"Command Center";62;1
"Building";"SupplyDepot";NA;62;0
"Unit";"Marine";"Barracks";64;1
"Unit";"Marine";"Barracks";64;1
"Unit";"SCV";"Command Center";67;1
"Unit";"SCV";"Command Center";69;1
"Unit";"SCV";"Command Center";73;1
"Building";"StarportReactor";NA;64;0
"Unit";"Marine";"Barracks";72;1
"Unit";"Marine";"Barracks";72;1
"Unit";"Marine";"Barracks";72;1
"Unit";"Marine";"Barracks";73;1
"Unit";"Marine";"Barracks";73;1
"Unit";"SCV";"Command Center";73;1
"Unit";"SCV";"Command Center";73;1
"Unit";"SCV";"Command Center";79;1
"Unit";"SCV";"Command Center";80;1
"Unit";"Marine";"Barracks";80;1
"Unit";"Marine";"Barracks";81;1
"Unit";"SCV";"Command Center";81;1
"Unit";"SCV";"Command Center";82;1
"Upgrade";"TerranInfantryWeaponsLevel1";"EngineeringBay";62;0
"Building";"SupplyDepot";NA;82;0
"Unit";"Marine";"Barracks";83;1
"Unit";"Marine";"Barracks";83;1
"Unit";"Marine";"Barracks";83;1
"Unit";"Medivac";"Starport";82;2
"Unit";"Medivac";"Starport";82;2
"Upgrade";"Stimpack";"TechLab";64;0
"Unit";"Marine";"Barracks";87;1
"Unit";"Marine";"Barracks";87;1
"Building";"SupplyDepot";NA;87;0
"Building";"SupplyDepot";NA;87;0
"Unit";"Marine";"Barracks";94;1
"Unit";"Marine";"Barracks";94;1
"Unit";"Marine";"Barracks";94;1
"Unit";"Marine";"Barracks";96;1
"Unit";"Marine";"Barracks";96;1
"Building";"SupplyDepot";NA;96;0
"Unit";"Marine";"Barracks";96;1
"Building";"SupplyDepot";NA;96;0
"Unit";"Marine";"Barracks";99;1
"Unit";"Marine";"Barracks";99;1
"Unit";"SCV";"Command Center";101;1
"Unit";"SCV";"Command Center";101;1
"Unit";"Marine";"Barracks";101;1
"Unit";"Marine";"Barracks";101;1
"Unit";"Medivac";"Starport";96;2
"Unit";"Medivac";"Starport";96;2
"Unit";"Marine";"Barracks";101;1
"Unit";"SCV";"Command Center";104;1
"Unit";"SCV";"Command Center";105;1
"Building";"SupplyDepot";NA;102;0
"Unit";"Marine";"Barracks";106;1
"Unit";"Marine";"Barracks";106;1
"Unit";"Marine";"Barracks";107;1
"Unit";"SCV";"Command Center";115;1
"Unit";"Marine";"Barracks";115;1
"Unit";"Marine";"Barracks";115;1
"Unit";"Marine";"Barracks";115;1
"Unit";"Medivac";"Starport";115;2
"Unit";"Medivac";"Starport";115;2
"Building";"Barracks";NA;104;0
"Unit";"Marine";"Barracks";118;1
"Unit";"Marine";"Barracks";118;1
"Building";"Barracks";NA;106;0
"Building";"CommandCenter";NA;99;0
"Unit";"SCV";"Command Center";122;1
"Unit";"SCV";"Command Center";122;1
"Unit";"Marine";"Barracks";119;1
"Upgrade";"TerranInfantryArmorsLevel1";"EngineeringBay";96;0
"Unit";"Marine";"Barracks";122;1
"Unit";"Marine";"Barracks";122;1
