"type";"unit_name";"on_building";"total_supply";"supply"
"Building";"Refinery";NA;15;0
"Building";"Barracks";NA;15;0
"Unit";"Reaper";"Barracks";19;1
"Building";"Refinery";NA;19;0
"Building";"BarracksReactor";NA;20;0
"Building";"CommandCenter";NA;19;0
"Building";"Bunker";NA;22;0
"Unit";"Marine";"Barracks";24;1
"Unit";"Marine";"Barracks";24;1
"Building";"Factory";NA;22;0
"Unit";"Marine";"Barracks";25;1
"Unit";"Marine";"Barracks";26;1
"Unit";"Marine";"Barracks";28;1
"Unit";"Marine";"Barracks";30;1
"Unit";"Cyclone";"Factory";31;3
"Building";"Starport";NA;28;0
"Building";"FactoryTechLab";NA;39;0
"Unit";"Marine";"Barracks";39;1
"Unit";"Marine";"Barracks";39;1
"Building";"Bunker";NA;39;0
"Unit";"Marine";"Barracks";45;1
"Unit";"Marine";"Barracks";45;1
"Building";"Barracks";NA;41;0
"Building";"EngineeringBay";NA;47;0
"Building";"Barracks";NA;41;0
"Building";"StarportTechLab";NA;47;0
"Unit";"Marine";"Barracks";51;1
"Unit";"Marine";"Barracks";51;1
"Building";"MissileTurret";NA;52;0
"Building";"MissileTurret";NA;52;0
"Building";"MissileTurret";NA;52;0
"Building";"BarracksTechLab";NA;52;0
"Building";"BarracksTechLab";NA;52;0
"Unit";"Marine";"Barracks";54;1
"Unit";"Marine";"Barracks";54;1
"Unit";"Marine";"Barracks";54;1
"Unit";"Marine";"Barracks";54;1
"Building";"Refinery";NA;55;0
"Unit";"Raven";"Starport";54;2
"Unit";"Marine";"Barracks";59;1
"Unit";"Marine";"Barracks";59;1
"Unit";"Marine";"Barracks";59;1
"Unit";"Marine";"Barracks";61;1
"Unit";"Marine";"Barracks";64;1
"Unit";"Marine";"Barracks";65;1
"Unit";"Marine";"Barracks";66;1
"Unit";"Marine";"Barracks";73;1
"Unit";"Marine";"Barracks";73;1
"Unit";"Marine";"Barracks";73;1
"Unit";"Marine";"Barracks";73;1
"Unit";"Marine";"Barracks";75;1
"Unit";"Marine";"Barracks";76;1
"Unit";"Marine";"Barracks";77;1
"Unit";"Marine";"Barracks";78;1
"Unit";"Marine";"Barracks";79;1
"Unit";"Marine";"Barracks";80;1
"Unit";"Marine";"Barracks";81;1
"Upgrade";"Stimpack";"TechLab";62;0
"Unit";"Marine";"Barracks";85;1
"Unit";"Marine";"Barracks";85;1
"Unit";"Marine";"Barracks";86;1
"Unit";"Marine";"Barracks";87;1
"Building";"CommandCenter";NA;75;0
"Building";"Refinery";NA;88;0
"Building";"Barracks";NA;85;0
"Building";"Barracks";NA;85;0
"Unit";"Marine";"Barracks";89;1
"Unit";"Marine";"Barracks";90;1
"Upgrade";"TerranInfantryWeaponsLevel1";"EngineeringBay";75;0
"Building";"Factory";NA;88;0
"Unit";"Marine";"Barracks";94;1
"Unit";"Marine";"Barracks";94;1
"Unit";"Marine";"Barracks";94;1
"Unit";"Marine";"Barracks";96;1
"Building";"StarportReactor";NA;92;0
"Building";"BarracksTechLab";NA;96;0
"Building";"EngineeringBay";NA;96;0
"Building";"BarracksReactor";NA;96;0
"Building";"Refinery";NA;99;0
"Unit";"Marine";"Barracks";102;1
"Unit";"Marine";"Barracks";102;1
"Unit";"Marine";"Barracks";102;1
"Unit";"Marine";"Barracks";102;1
"Building";"Armory";NA;96;0
"Unit";"Marine";"Barracks";102;1
"Unit";"Marine";"Barracks";102;1
"Unit";"Marine";"Barracks";106;1
"Unit";"Marine";"Barracks";106;1
"Unit";"Marine";"Barracks";106;1
"Unit";"Marine";"Barracks";106;1
"Unit";"Marauder";"Barracks";106;2
"Unit";"Marine";"Barracks";106;1
"Unit";"Marine";"Barracks";107;1
"Unit";"Marine";"Barracks";112;1
"Unit";"Marine";"Barracks";112;1
"Unit";"Marine";"Barracks";114;1
"Unit";"Marine";"Barracks";116;1
"Unit";"Marine";"Barracks";116;1
"Unit";"Marine";"Barracks";116;1
"Unit";"Marauder";"Barracks";116;2
"Unit";"Marine";"Barracks";116;1
"Unit";"Marine";"Barracks";117;1
"Unit";"Marine";"Barracks";118;1
"Unit";"Marine";"Barracks";119;1
"Unit";"Marine";"Barracks";120;1
"Unit";"Marine";"Barracks";124;1
"Unit";"Marine";"Barracks";124;1
"Building";"Refinery";NA;124;0
"Unit";"Marine";"Barracks";124;1
"Building";"Starport";NA;138;0
"Building";"Starport";NA;138;0
"Building";"CommandCenter";NA;129;0
"Building";"StarportTechLab";NA;142;0
"Building";"StarportTechLab";NA;142;0
"Building";"Refinery";NA;142;0
"Upgrade";"TerranInfantryArmorsLevel1";"EngineeringBay";138;0
"Building";"StarportReactor";NA;142;0
"Building";"Refinery";NA;142;0
"Building";"FusionCore";NA;142;0
"Unit";"Marine";"Barracks";142;1
"Unit";"Marine";"Barracks";142;1
"Unit";"Marine";"Barracks";142;1
"Unit";"Marine";"Barracks";142;1
"Unit";"Marine";"Barracks";142;1
"Unit";"Marine";"Barracks";142;1
"Unit";"Marine";"Barracks";142;1
"Building";"CommandCenter";NA;142;0
"Upgrade";"TerranInfantryWeaponsLevel2";"EngineeringBay";139;0
"Unit";"Raven";"Starport";142;2
"Unit";"Raven";"Starport";142;2
"Unit";"Marine";"Barracks";142;1
"Unit";"Marine";"Barracks";143;1
"Unit";"Marine";"Barracks";144;1
"Unit";"Marine";"Barracks";144;1
"Building";"Refinery";NA;149;0
"Building";"Refinery";NA;149;0
"Building";"Barracks";NA;142;0
"Building";"Barracks";NA;142;0
"Unit";"Marine";"Barracks";157;1
"Unit";"Marine";"Barracks";157;1
"Unit";"Marine";"Barracks";157;1
"Unit";"Marine";"Barracks";157;1
"Unit";"Raven";"Starport";161;2
"Unit";"Raven";"Starport";161;2
"Building";"Armory";NA;166;0
"Building";"Starport";NA;166;0
"Building";"Starport";NA;166;0
"Unit";"Battlecruiser";"Starport";162;6
"Unit";"Battlecruiser";"Starport";164;6
"Building";"StarportTechLab";NA;178;0
"Upgrade";"TerranShipWeaponsLevel1";"Armory";166;0
"Upgrade";"TerranInfantryArmorsLevel2";"EngineeringBay";166;0
"Upgrade";"TerranInfantryWeaponsLevel3";"EngineeringBay";166;0
"Unit";"Battlecruiser";"Starport";178;6
