"type";"unit_name";"on_building";"total_supply";"supply"
"Building";"Refinery";NA;14;0
"Building";"Barracks";NA;15;0
"Unit";"Marine";"Barracks";20;1
"Unit";"Marine";"Barracks";21;1
"Building";"Factory";NA;20;0
"Building";"CommandCenter";NA;19;0
"Building";"Refinery";NA;23;0
"Unit";"Cyclone";"Factory";23;3
"Unit";"Cyclone";"Factory";28;3
"Building";"BarracksReactor";NA;28;0
"Building";"Refinery";NA;32;0
"Building";"Starport";NA;30;0
"Building";"BarracksTechLab";NA;37;0
"Unit";"Cyclone";"Factory";39;3
"Unit";"Cyclone";"Factory";39;3
"Unit";"Hellion";"Factory";43;2
"Building";"Refinery";NA;55;0
"Unit";"Hellion";"Factory";58;2
"Unit";"Hellion";"Factory";58;2
"Building";"Factory";NA;58;0
"Building";"CommandCenter";NA;54;0
"Building";"Factory";NA;58;0
"Building";"Armory";NA;62;0
"Building";"FactoryTechLab";NA;70;0
"Building";"FactoryTechLab";NA;70;0
"Building";"Armory";NA;62;0
"Building";"EngineeringBay";NA;72;0
"Building";"BarracksReactor";NA;72;0
"Unit";"Hellion";"Factory";74;2
"Unit";"Hellion";"Factory";74;2
"Unit";"Raven";"Starport";72;2
"Unit";"Hellion";"Factory";77;2
"Unit";"Hellion";"Factory";83;2
"Building";"MissileTurret";NA;83;0
"Building";"MissileTurret";NA;85;0
"Building";"MissileTurret";NA;91;0
"Building";"MissileTurret";NA;93;0
"Building";"Refinery";NA;96;0
"Building";"MissileTurret";NA;96;0
"Building";"Refinery";NA;96;0
"Upgrade";"TerranVehicleWeaponsLevel1";"Armory";83;0
"Building";"MissileTurret";NA;98;0
"Building";"MissileTurret";NA;101;0
"Building";"Starport";NA;98;0
"Building";"Factory";NA;98;0
"Unit";"Hellion";"Factory";105;2
"Unit";"Hellion";"Factory";105;2
"Unit";"Hellion";"Factory";105;2
"Unit";"Hellion";"Factory";109;2
"Building";"FactoryTechLab";NA;109;0
"Upgrade";"TerranShipWeaponsLevel1";"Armory";105;0
"Unit";"Hellion";"Factory";123;2
"Building";"MissileTurret";NA;126;0
"Building";"MissileTurret";NA;126;0
"Building";"MissileTurret";NA;127;0
"Building";"MissileTurret";NA;127;0
"Building";"CommandCenter";NA;123;0
"Unit";"Hellion";"Factory";134;2
"Unit";"Hellion";"Factory";134;2
"Unit";"Hellion";"Factory";138;2
"Unit";"Hellion";"Factory";140;2
"Building";"MissileTurret";NA;146;0
"Building";"MissileTurret";NA;146;0
"Building";"MissileTurret";NA;146;0
"Unit";"Hellion";"Factory";146;2
"Building";"CommandCenter";NA;137;0
"Building";"MissileTurret";NA;154;0
"Building";"Refinery";NA;154;0
"Upgrade";"TerranVehicleWeaponsLevel2";"Armory";137;0
"Unit";"Hellion";"Factory";154;2
"Unit";"Hellion";"Factory";154;2
"Building";"Refinery";NA;154;0
"Unit";"Hellion";"Factory";157;2
"Unit";"Raven";"Starport";154;2
"Building";"Refinery";NA;161;0
"Building";"Refinery";NA;161;0
"Building";"Factory";NA;154;0
"Unit";"Hellion";"Factory";165;2
"Building";"FactoryTechLab";NA;165;0
"Building";"MissileTurret";NA;165;0
"Unit";"Raven";"Starport";163;2
"Building";"MissileTurret";NA;167;0
"Unit";"Thor";"Factory";165;6
"Unit";"Hellion";"Factory";167;2
"Unit";"Hellion";"Factory";177;2
"Unit";"Hellion";"Factory";177;2
"Upgrade";"TerranShipWeaponsLevel2";"Armory";165;0
"Unit";"Hellion";"Factory";177;2
"Unit";"Hellion";"Factory";179;2
"Building";"FactoryReactor";NA;181;0
"Unit";"Hellion";"Factory";193;2
"Unit";"Hellion";"Factory";204;2
