"type";"unit_name";"on_building";"total_supply_lag";"supply"
"Building";"Refinery";NA;15;0
"Building";"Barracks";NA;16;0
"Unit";"Reaper";"Barracks";19;1
"Building";"CommandCenter";NA;20;0
"Building";"Factory";NA;20;0
"Building";"BarracksReactor";NA;21;0
"Building";"Refinery";NA;22;0
"Unit";"Hellion";"Factory";24;2
"Building";"Starport";NA;26;0
"Unit";"Marine";"Barracks";26;1
"Unit";"Marine";"Barracks";27;1
"Building";"FactoryTechLab";NA;29;0
"Unit";"Marine";"Barracks";30;1
"Unit";"Marine";"Barracks";31;1
"Unit";"Banshee";"Starport";34;3
"Unit";"Marine";"Barracks";37;1
"Unit";"Marine";"Barracks";38;1
"Building";"FactoryTechLab";NA;39;0
"Building";"CommandCenter";NA;49;0
"Unit";"Raven";"Starport";49;2
"Unit";"Marine";"Barracks";51;1
"Unit";"Marine";"Barracks";52;1
"Building";"Refinery";NA;55;0
"Building";"Refinery";NA;57;0
"Building";"Barracks";NA;60;0
"Building";"Barracks";NA;61;0
"Unit";"Banshee";"Starport";61;3
"Unit";"Marine";"Barracks";65;1
"Building";"EngineeringBay";NA;66;0
"Unit";"Marine";"Barracks";67;1
"Building";"EngineeringBay";NA;68;0
"Unit";"Marine";"Barracks";69;1
"Unit";"Marine";"Barracks";71;1
"Building";"BarracksTechLab";NA;73;0
"Building";"BarracksReactor";NA;73;0
"Building";"Barracks";NA;73;0
"Building";"Barracks";NA;73;0
"Unit";"Marine";"Barracks";73;1
"Unit";"Marine";"Barracks";74;1
"Unit";"Marine";"Barracks";75;1
"Unit";"Marine";"Barracks";76;1
"Building";"StarportReactor";NA;77;0
"Upgrade";"TerranInfantryWeaponsLevel1";"EngineeringBay";79;0
"Unit";"Marine";"Barracks";79;1
"Unit";"Marine";"Barracks";80;1
"Unit";"Marine";"Barracks";81;1
"Unit";"Marine";"Barracks";82;1
"Unit";"Marine";"Barracks";83;1
"Building";"BarracksReactor";NA;84;0
"Building";"BarracksReactor";NA;84;0
"Unit";"Marine";"Barracks";84;1
"Upgrade";"Stimpack";"TechLab";85;0
"Unit";"Marine";"Barracks";85;1
"Unit";"Medivac";"Starport";89;2
"Unit";"Marine";"Barracks";91;1
"Unit";"Marine";"Barracks";92;1
"Unit";"Medivac";"Starport";93;2
"Building";"Refinery";NA;96;0
"Building";"Refinery";NA;97;0
"Building";"SensorTower";NA;97;0
"Unit";"Marine";"Barracks";98;1
"Unit";"Marine";"Barracks";99;1
"Building";"Armory";NA;103;0
"Building";"MissileTurret";NA;103;0
"Unit";"Marine";"Barracks";103;1
"Building";"MissileTurret";NA;104;0
"Unit";"Medivac";"Starport";106;2
"Unit";"Medivac";"Starport";108;2
"Unit";"Marine";"Barracks";110;1
"Unit";"Marine";"Barracks";111;1
"Unit";"Marine";"Barracks";116;1
"Unit";"Marine";"Barracks";118;1
"Unit";"Medivac";"Starport";123;2
"Unit";"Medivac";"Starport";126;2
"Unit";"Marine";"Barracks";130;1
"Unit";"Marine";"Barracks";131;1
"Unit";"Marine";"Barracks";132;1
"Unit";"Marine";"Barracks";133;1
"Unit";"Marine";"Barracks";134;1
"Unit";"Marine";"Barracks";135;1
"Unit";"Marine";"Barracks";137;1
"Building";"Factory";NA;139;0
"Unit";"Marine";"Barracks";141;1
"Unit";"Marine";"Barracks";142;1
"Unit";"Marine";"Barracks";143;1
"Unit";"Marine";"Barracks";144;1
"Unit";"Marine";"Barracks";145;1
"Unit";"Marine";"Barracks";146;1
"Unit";"Marine";"Barracks";147;1
"Unit";"Marine";"Barracks";148;1
"Unit";"Marine";"Barracks";149;1
"Unit";"Marine";"Barracks";150;1
"Unit";"Marine";"Barracks";151;1
"Unit";"Marine";"Barracks";152;1
"Unit";"Marine";"Barracks";153;1
"Unit";"Marine";"Barracks";154;1
"Building";"CommandCenter";NA;155;0
"Unit";"Marine";"Barracks";155;1
"Unit";"Marine";"Barracks";156;1
"Unit";"Marine";"Barracks";157;1
"Unit";"Marine";"Barracks";158;1
"Unit";"Liberator";"Starport";159;3
"Unit";"Liberator";"Starport";162;3
"Unit";"Marine";"Barracks";165;1
"Unit";"Marine";"Barracks";166;1
"Unit";"Marine";"Barracks";167;1
"Unit";"Marine";"Barracks";168;1
"Unit";"Marine";"Barracks";169;1
"Unit";"Marine";"Barracks";170;1
"Unit";"Marine";"Barracks";171;1
"Unit";"Marine";"Barracks";172;1
"Unit";"Marine";"Barracks";173;1
"Unit";"Marine";"Barracks";174;1
"Unit";"Marine";"Barracks";175;1
"Unit";"Marine";"Barracks";176;1
"Unit";"Marine";"Barracks";177;1
"Unit";"Marine";"Barracks";178;1
"Unit";"Liberator";"Starport";179;3
"Unit";"Liberator";"Starport";182;3
"Upgrade";"TerranInfantryWeaponsLevel2";"EngineeringBay";185;0
"Unit";"Marine";"Barracks";185;1
"Unit";"Marine";"Barracks";186;1
"Upgrade";"TerranVehicleWeaponsLevel1";"Armory";187;0
"Unit";"Marine";"Barracks";187;1
"Unit";"Marine";"Barracks";188;1
"Building";"Barracks";NA;189;0
"Building";"Barracks";NA;189;0
"Unit";"Marine";"Barracks";189;1
"Unit";"Marine";"Barracks";190;1
"Unit";"Marine";"Barracks";191;1
"Unit";"Marine";"Barracks";192;1
"Unit";"Marine";"Barracks";193;1
"Unit";"Marine";"Barracks";194;1
"Unit";"Marine";"Barracks";195;1
"Unit";"Marine";"Barracks";196;1
"Unit";"Marine";"Barracks";197;1
"Building";"MissileTurret";NA;198;0
"Unit";"Marine";"Barracks";198;1
"Unit";"Marine";"Barracks";199;1
"Unit";"Marine";"Barracks";200;1
"Unit";"Marine";"Barracks";201;1
"Unit";"Marine";"Barracks";202;1
"Unit";"Marine";"Barracks";203;1
"Unit";"Marine";"Barracks";204;1
"Unit";"Marine";"Barracks";205;1
"Unit";"Marine";"Barracks";206;1
"Unit";"Liberator";"Starport";207;3
"Unit";"Liberator";"Starport";210;3
"Unit";"Marine";"Barracks";213;1
"Unit";"Marine";"Barracks";214;1
"Unit";"Marine";"Barracks";215;1
"Unit";"Marine";"Barracks";216;1
"Unit";"Marine";"Barracks";217;1
"Unit";"Marine";"Barracks";218;1
"Unit";"Marine";"Barracks";219;1
"Building";"BarracksReactor";NA;220;0
"Building";"BarracksReactor";NA;220;0
"Unit";"Marine";"Barracks";220;1
"Unit";"Marine";"Barracks";221;1
"Unit";"Marine";"Barracks";222;1
"Unit";"Marine";"Barracks";223;1
"Unit";"Marine";"Barracks";224;1
"Building";"Refinery";NA;225;0
"Building";"Refinery";NA;225;0
"Building";"CommandCenter";NA;225;0
"Unit";"Marine";"Barracks";225;1
"Unit";"Marine";"Barracks";226;1
"Unit";"Marine";"Barracks";227;1
"Unit";"Marine";"Barracks";228;1
"Unit";"Marine";"Barracks";229;1
"Unit";"Marine";"Barracks";230;1
"Unit";"Marine";"Barracks";231;1
"Unit";"Marine";"Barracks";232;1
"Unit";"Marine";"Barracks";233;1
"Unit";"Marine";"Barracks";234;1
"Unit";"Marine";"Barracks";235;1
"Unit";"Marine";"Barracks";236;1
"Unit";"Marine";"Barracks";237;1
"Unit";"Marine";"Barracks";238;1
"Unit";"Marine";"Barracks";239;1
"Unit";"Marine";"Barracks";240;1
"Unit";"Marine";"Barracks";241;1
"Unit";"Marine";"Barracks";242;1
"Unit";"Marine";"Barracks";243;1
"Upgrade";"TerranInfantryWeaponsLevel3";"EngineeringBay";244;0
"Building";"CommandCenter";NA;244;0
"Unit";"Marine";"Barracks";244;1
"Unit";"Marine";"Barracks";245;1
"Unit";"Marine";"Barracks";246;1
"Unit";"Marine";"Barracks";247;1
"Unit";"Marine";"Barracks";248;1
"Unit";"Marine";"Barracks";249;1
"Unit";"Marine";"Barracks";250;1
"Unit";"Marine";"Barracks";251;1
"Unit";"Marine";"Barracks";255;1
"Unit";"Marine";"Barracks";256;1
"Unit";"Marine";"Barracks";257;1
"Unit";"Marine";"Barracks";258;1
"Unit";"Marine";"Barracks";260;1
"Unit";"Marine";"Barracks";261;1
"Unit";"Marine";"Barracks";262;1
"Unit";"Marine";"Barracks";263;1
"Unit";"Marine";"Barracks";264;1
"Unit";"Marine";"Barracks";265;1
"Unit";"Marine";"Barracks";266;1
"Unit";"Marine";"Barracks";267;1
"Unit";"Marine";"Barracks";268;1
"Unit";"Marine";"Barracks";269;1
"Unit";"Marine";"Barracks";270;1
"Unit";"Marine";"Barracks";271;1
"Unit";"Marine";"Barracks";272;1
"Unit";"Marine";"Barracks";273;1
"Unit";"Liberator";"Starport";274;3
"Unit";"Marine";"Barracks";277;1
"Unit";"Marine";"Barracks";278;1
"Unit";"Marine";"Barracks";279;1
"Unit";"Marine";"Barracks";280;1
"Unit";"Marine";"Barracks";281;1
"Unit";"Marine";"Barracks";282;1
"Unit";"Marine";"Barracks";283;1
"Unit";"Marine";"Barracks";284;1
"Unit";"Marine";"Barracks";285;1
"Unit";"Marine";"Barracks";286;1
"Unit";"Marine";"Barracks";287;1
"Unit";"Marine";"Barracks";288;1
"Unit";"Marine";"Barracks";289;1
"Unit";"Marine";"Barracks";290;1
"Unit";"Marine";"Barracks";291;1
"Unit";"Marine";"Barracks";292;1
"Unit";"Marine";"Barracks";293;1
"Unit";"Marine";"Barracks";294;1
"Unit";"Marine";"Barracks";295;1
"Unit";"Marine";"Barracks";296;1
"Unit";"Marine";"Barracks";297;1
"Unit";"Marine";"Barracks";298;1
"Unit";"Marine";"Barracks";299;1
"Unit";"Marine";"Barracks";300;1
"Unit";"Marine";"Barracks";301;1
"Upgrade";"SprayTerran";NA;302;0
"Upgrade";"SprayTerran";NA;302;0
"Upgrade";"SprayTerran";NA;302;0
"Upgrade";"BansheeCloak";NA;302;0
"Upgrade";"SprayTerran";NA;302;0
"Upgrade";"TerranInfantryArmorsLevel1";NA;302;0
"Upgrade";"SprayTerran";NA;302;0
"Upgrade";"ShieldWall";NA;302;0
"Upgrade";"SprayTerran";NA;302;0
"Upgrade";"SprayTerran";NA;302;0
"Upgrade";"TerranInfantryArmorsLevel2";NA;302;0
"Upgrade";"SprayTerran";NA;302;0
"Upgrade";"SprayTerran";NA;302;0
"Upgrade";"SprayTerran";NA;302;0
"Upgrade";"TerranInfantryArmorsLevel3";NA;302;0
