"type";"unit_name";"on_building";"total_supply";"supply"
"Building";"Refinery";NA;14;0
"Building";"Barracks";NA;15;0
"Unit";"Reaper";"Barracks";19;1
"Building";"Refinery";NA;21;0
"Building";"Factory";NA;20;0
"Unit";"Reaper";"Barracks";21;1
"Building";"CommandCenter";NA;20;0
"Unit";"Hellion";"Factory";23;2
"Building";"BarracksReactor";NA;23;0
"Building";"Starport";NA;24;0
"Unit";"Cyclone";"Factory";28;3
"Unit";"Marine";"Barracks";29;1
"Unit";"Marine";"Barracks";29;1
"Building";"FactoryTechLab";NA;32;0
"Unit";"Medivac";"Starport";29;2
"Building";"BarracksTechLab";NA;41;0
"Unit";"Marine";"Barracks";44;1
"Unit";"Marine";"Barracks";47;1
"Building";"CommandCenter";NA;37;0
"Building";"Refinery";NA;50;0
"Building";"Refinery";NA;50;0
"Unit";"Marine";"Barracks";51;1
"Building";"StarportReactor";NA;49;0
"Building";"Barracks";NA;47;0
"Building";"Barracks";NA;48;0
"Building";"EngineeringBay";NA;54;0
"Unit";"Marine";"Barracks";58;1
"Unit";"Marine";"Barracks";58;1
"Unit";"Medivac";"Starport";59;2
"Unit";"Marine";"Barracks";61;1
"Unit";"Medivac";"Starport";59;2
"Unit";"Marine";"Barracks";65;1
"Unit";"Marine";"Barracks";65;1
"Building";"BarracksReactor";NA;58;0
"Unit";"Marine";"Barracks";71;1
"Unit";"Marine";"Barracks";73;1
"Upgrade";"Stimpack";"TechLab";52;0
"Unit";"Marine";"Barracks";77;1
"Unit";"Marine";"Barracks";77;1
"Unit";"Marine";"Barracks";77;1
"Unit";"Marine";"Barracks";77;1
"Unit";"Marine";"Barracks";79;1
"Unit";"Marine";"Barracks";81;1
"Unit";"Marine";"Barracks";82;1
"Unit";"Marine";"Barracks";83;1
"Unit";"Marine";"Barracks";84;1
"Building";"Barracks";NA;77;0
"Building";"Barracks";NA;77;0
"Building";"Refinery";NA;88;0
"Building";"Refinery";NA;88;0
"Unit";"Marine";"Barracks";95;1
"Unit";"Marine";"Barracks";95;1
"Unit";"Marine";"Barracks";95;1
"Unit";"Marine";"Barracks";95;1
"Unit";"Marine";"Barracks";95;1
"Upgrade";"TerranInfantryWeaponsLevel1";"EngineeringBay";79;0
"Unit";"Marine";"Barracks";98;1
"Unit";"Marine";"Barracks";98;1
"Unit";"Marine";"Barracks";98;1
"Building";"BarracksReactor";NA;95;0
"Building";"BarracksReactor";NA;95;0
"Unit";"Marine";"Barracks";106;1
"Unit";"Marine";"Barracks";106;1
"Unit";"Marine";"Barracks";106;1
"Unit";"Marine";"Barracks";106;1
"Unit";"Marine";"Barracks";106;1
"Unit";"Medivac";"Starport";106;2
"Unit";"Medivac";"Starport";106;2
"Unit";"Marine";"Barracks";112;1
"Unit";"Marine";"Barracks";113;1
"Unit";"Marine";"Barracks";114;1
"Unit";"Marine";"Barracks";114;1
"Unit";"Marine";"Barracks";114;1
"Unit";"Marine";"Barracks";115;1
"Unit";"Marine";"Barracks";115;1
"Unit";"Marine";"Barracks";120;1
"Unit";"Marine";"Barracks";120;1
"Building";"EngineeringBay";NA;120;0
"Unit";"Marine";"Barracks";125;1
"Unit";"Marine";"Barracks";126;1
"Unit";"Marine";"Barracks";127;1
"Unit";"Marine";"Barracks";131;1
"Unit";"Marine";"Barracks";131;1
"Unit";"Marine";"Barracks";131;1
"Unit";"Marine";"Barracks";135;1
"Unit";"Marine";"Barracks";135;1
"Unit";"Marine";"Barracks";135;1
"Building";"Factory";NA;118;0
"Unit";"Marine";"Barracks";136;1
"Unit";"Marine";"Barracks";137;1
"Building";"SensorTower";NA;141;0
"Unit";"Marine";"Barracks";141;1
"Unit";"Marine";"Barracks";141;1
"Building";"Armory";NA;120;0
"Unit";"Medivac";"Starport";135;2
"Unit";"Medivac";"Starport";135;2
"Unit";"Marine";"Barracks";147;1
"Unit";"Marine";"Barracks";158;1
"Unit";"Marine";"Barracks";158;1
"Unit";"Marine";"Barracks";158;1
"Unit";"Marine";"Barracks";158;1
"Unit";"Marine";"Barracks";158;1
"Building";"FactoryTechLab";NA;159;0
"Unit";"Marine";"Barracks";159;1
"Unit";"Marine";"Barracks";159;1
"Unit";"Marine";"Barracks";159;1
"Unit";"Marine";"Barracks";159;1
"Unit";"Marine";"Barracks";162;1
"Unit";"Marine";"Barracks";163;1
"Unit";"Marine";"Barracks";167;1
"Unit";"Marine";"Barracks";167;1
"Unit";"Marine";"Barracks";174;1
"Upgrade";"TerranInfantryArmorsLevel1";"EngineeringBay";141;0
"Unit";"Medivac";"Starport";171;2
"Unit";"Medivac";"Starport";171;2
"Unit";"Marine";"Barracks";181;1
"Unit";"Marine";"Barracks";181;1
"Unit";"Marine";"Barracks";181;1
"Unit";"Marine";"Barracks";181;1
"Unit";"Marine";"Barracks";181;1
"Unit";"Marine";"Barracks";181;1
"Unit";"Marine";"Barracks";181;1
"Unit";"Marine";"Barracks";183;1
"Unit";"Marine";"Barracks";183;1
"Unit";"Marine";"Barracks";189;1
"Unit";"Marine";"Barracks";196;1
"Unit";"Marine";"Barracks";196;1
"Unit";"Marine";"Barracks";196;1
"Unit";"Marine";"Barracks";196;1
"Unit";"Marine";"Barracks";196;1
"Unit";"Marine";"Barracks";196;1
"Unit";"Marine";"Barracks";198;1
"Unit";"Marine";"Barracks";199;1
"Unit";"Marine";"Barracks";199;1
"Unit";"Medivac";"Starport";197;2
"Unit";"Marine";"Barracks";199;1
"Unit";"Marine";"Barracks";200;1
"Unit";"Medivac";"Starport";198;2
"Unit";"Marine";"Barracks";201;1
"Unit";"Marine";"Barracks";206;1
"Unit";"Marine";"Barracks";206;1
"Unit";"Marine";"Barracks";208;1
"Unit";"Marine";"Barracks";208;1
"Unit";"Marine";"Barracks";210;1
"Unit";"Marine";"Barracks";215;1
"Unit";"Marine";"Barracks";215;1
"Unit";"Marine";"Barracks";215;1
"Unit";"Marine";"Barracks";215;1
"Unit";"Medivac";"Starport";208;2
"Unit";"Marine";"Barracks";217;1
"Unit";"Marine";"Barracks";217;1
"Unit";"Medivac";"Starport";215;2
"Unit";"Marine";"Barracks";217;1
"Unit";"Marine";"Barracks";218;1
"Unit";"Marine";"Barracks";219;1
"Unit";"Marine";"Barracks";220;1
"Upgrade";"TerranInfantryWeaponsLevel2";"EngineeringBay";181;0
"Unit";"Marine";"Barracks";221;1
"Unit";"Marine";"Barracks";222;1
"Unit";"Marine";"Barracks";223;1
"Unit";"Marine";"Barracks";226;1
"Unit";"Marine";"Barracks";227;1
"Unit";"Marine";"Barracks";230;1
"Unit";"Marine";"Barracks";231;1
"Unit";"Marine";"Barracks";232;1
"Unit";"Marine";"Barracks";233;1
"Unit";"Medivac";"Starport";224;2
"Building";"SensorTower";NA;237;0
"Unit";"Marine";"Barracks";237;1
"Unit";"Marine";"Barracks";237;1
"Unit";"Marine";"Barracks";237;1
"Unit";"Marine";"Barracks";237;1
"Unit";"Marine";"Barracks";238;1
"Unit";"Marine";"Barracks";239;1
"Unit";"Marine";"Barracks";242;1
"Unit";"Marine";"Barracks";242;1
"Unit";"Marine";"Barracks";245;1
"Upgrade";"TerranInfantryArmorsLevel2";"EngineeringBay";208;0
"Unit";"Medivac";"Starport";253;2
"Unit";"Medivac";"Starport";253;2
"Unit";"Marine";"Barracks";256;1
"Unit";"Marine";"Barracks";256;1
"Unit";"Marine";"Barracks";257;1
"Unit";"Marine";"Barracks";257;1
"Unit";"Marine";"Barracks";257;1
"Unit";"Marine";"Barracks";257;1
"Unit";"Marine";"Barracks";257;1
"Building";"CommandCenter";NA;237;0
"Unit";"Marine";"Barracks";257;1
"Unit";"Marine";"Barracks";270;1
"Unit";"Marine";"Barracks";270;1
"Unit";"Marine";"Barracks";270;1
"Unit";"Marine";"Barracks";270;1
"Unit";"Marine";"Barracks";270;1
"Unit";"Marine";"Barracks";270;1
"Unit";"Marine";"Barracks";270;1
"Unit";"Marine";"Barracks";270;1
"Unit";"Marine";"Barracks";270;1
