"Type";"UnitName";"OnBuilding";"TotalSupply";"Supply"
"Unit";"SCV";"Command Center";12;1
"Unit";"SCV";"Command Center";12;1
"Unit";"SCV";"Command Center";14;1
"Building";"SupplyDepot";NA;13;0
"Unit";"SCV";"Command Center";15;1
"Building";"Refinery";NA;14;0
"Unit";"SCV";"Command Center";15;1
"Unit";"SCV";"Command Center";16;1
"Unit";"SCV";"Command Center";17;1
"Building";"Barracks";NA;15;0
"Unit";"SCV";"Command Center";19;1
"Unit";"Reaper";"Barracks";19;1
"Unit";"SCV";"Command Center";20;1
"Building";"Refinery";NA;21;0
"Building";"SupplyDepot";NA;22;0
"Building";"Factory";NA;20;0
"Unit";"Reaper";"Barracks";21;1
"Unit";"SCV";"Command Center";22;1
"Building";"CommandCenter";NA;20;0
"Unit";"SCV";"Command Center";23;1
"Unit";"Hellion";"Factory";23;2
"Building";"BarracksReactor";NA;23;0
"Unit";"SCV";"Command Center";27;1
"Building";"Starport";NA;24;0
"Unit";"SCV";"Command Center";27;1
"Unit";"Cyclone";"Factory";28;3
"Unit";"SCV";"Command Center";29;1
"Unit";"SCV";"Command Center";29;1
"Unit";"Marine";"Barracks";29;1
"Unit";"Marine";"Barracks";29;1
"Unit";"SCV";"Command Center";32;1
"Building";"FactoryTechLab";NA;32;0
"Unit";"SCV";"Command Center";33;1
"Unit";"Medivac";"Starport";29;2
"Unit";"SCV";"Command Center";36;1
"Building";"SupplyDepot";NA;33;0
"Unit";"SCV";"Command Center";37;1
"Unit";"SCV";"Command Center";40;1
"Unit";"SCV";"Command Center";41;1
"Building";"BarracksTechLab";NA;41;0
"Unit";"SCV";"Command Center";42;1
"Unit";"SCV";"Command Center";44;1
"Unit";"SCV";"Command Center";44;1
"Unit";"Marine";"Barracks";44;1
"Unit";"SCV";"Command Center";45;1
"Unit";"SCV";"Command Center";46;1
"Unit";"SCV";"Command Center";48;1
"Unit";"Marine";"Barracks";47;1
"Unit";"SCV";"Command Center";49;1
"Building";"CommandCenter";NA;37;0
"Unit";"SCV";"Command Center";50;1
"Unit";"SCV";"Command Center";52;1
"Building";"Refinery";NA;50;0
"Building";"Refinery";NA;50;0
"Building";"SupplyDepot";NA;50;0
"Unit";"Marine";"Barracks";51;1
"Unit";"SCV";"Command Center";53;1
"Building";"StarportReactor";NA;49;0
"Building";"Barracks";NA;47;0
"Unit";"SCV";"Command Center";54;1
"Building";"Barracks";NA;48;0
"Unit";"SCV";"Command Center";56;1
"Building";"EngineeringBay";NA;54;0
"Unit";"SCV";"Command Center";57;1
"Unit";"SCV";"Command Center";58;1
"Unit";"SCV";"Command Center";59;1
"Unit";"Marine";"Barracks";58;1
"Unit";"Marine";"Barracks";58;1
"Unit";"SCV";"Command Center";59;1
"Unit";"SCV";"Command Center";60;1
"Unit";"SCV";"Command Center";61;1
"Unit";"SCV";"Command Center";64;1
"Unit";"Medivac";"Starport";59;2
"Unit";"Marine";"Barracks";61;1
"Building";"SupplyDepot";NA;61;0
"Unit";"Medivac";"Starport";59;2
"Unit";"Marine";"Barracks";65;1
"Unit";"Marine";"Barracks";65;1
"Building";"BarracksReactor";NA;58;0
"Unit";"SCV";"Command Center";67;1
"Unit";"SCV";"Command Center";67;1
"Building";"SupplyDepot";NA;67;0
"Unit";"Marine";"Barracks";71;1
"Unit";"Marine";"Barracks";73;1
"Upgrade";"Stimpack";"TechLab";52;0
"Unit";"SCV";"Command Center";77;1
"Unit";"SCV";"Command Center";77;1
"Unit";"Marine";"Barracks";77;1
"Unit";"Marine";"Barracks";77;1
"Building";"SupplyDepot";NA;76;0
"Unit";"Marine";"Barracks";77;1
"Unit";"Marine";"Barracks";77;1
"Unit";"SCV";"Command Center";79;1
"Unit";"SCV";"Command Center";80;1
"Unit";"Marine";"Barracks";79;1
"Unit";"Marine";"Barracks";81;1
"Unit";"Marine";"Barracks";82;1
"Unit";"SCV";"Command Center";83;1
"Unit";"SCV";"Command Center";85;1
"Unit";"SCV";"Command Center";86;1
"Unit";"Marine";"Barracks";83;1
"Unit";"Marine";"Barracks";84;1
"Building";"Barracks";NA;77;0
"Building";"Barracks";NA;77;0
"Building";"Refinery";NA;88;0
"Building";"Refinery";NA;88;0
"Building";"SupplyDepot";NA;91;0
"Building";"SupplyDepot";NA;93;0
"Building";"SupplyDepot";NA;94;0
"Unit";"SCV";"Command Center";95;1
"Unit";"SCV";"Command Center";95;1
"Unit";"SCV";"Command Center";95;1
"Unit";"Marine";"Barracks";95;1
"Unit";"Marine";"Barracks";95;1
"Unit";"Marine";"Barracks";95;1
"Unit";"Marine";"Barracks";95;1
"Unit";"Marine";"Barracks";95;1
"Unit";"SCV";"Command Center";95;1
"Unit";"SCV";"Command Center";96;1
"Unit";"SCV";"Command Center";96;1
"Building";"SupplyDepot";NA;95;0
"Building";"SupplyDepot";NA;95;0
"Upgrade";"TerranInfantryWeaponsLevel1";"EngineeringBay";79;0
"Unit";"Marine";"Barracks";98;1
"Unit";"Marine";"Barracks";98;1
"Unit";"Marine";"Barracks";98;1
"Unit";"SCV";"Command Center";103;1
"Unit";"SCV";"Command Center";104;1
"Unit";"SCV";"Command Center";104;1
"Building";"BarracksReactor";NA;95;0
"Building";"BarracksReactor";NA;95;0
"Unit";"Marine";"Barracks";106;1
"Unit";"Marine";"Barracks";106;1
"Unit";"SCV";"Command Center";109;1
"Unit";"Marine";"Barracks";106;1
"Unit";"Marine";"Barracks";106;1
"Unit";"Marine";"Barracks";106;1
"Unit";"SCV";"Command Center";112;1
"Unit";"SCV";"Command Center";112;1
"Unit";"SCV";"Command Center";114;1
"Unit";"Medivac";"Starport";106;2
"Unit";"Medivac";"Starport";106;2
"Unit";"Marine";"Barracks";112;1
"Unit";"Marine";"Barracks";113;1
"Unit";"Marine";"Barracks";114;1
"Unit";"Marine";"Barracks";114;1
"Unit";"Marine";"Barracks";114;1
"Unit";"SCV";"Command Center";118;1
"Unit";"Marine";"Barracks";115;1
"Unit";"Marine";"Barracks";115;1
"Unit";"Marine";"Barracks";120;1
"Unit";"Marine";"Barracks";120;1
"Unit";"SCV";"Command Center";126;1
"Building";"EngineeringBay";NA;120;0
"Unit";"Marine";"Barracks";125;1
"Unit";"Marine";"Barracks";126;1
"Unit";"Marine";"Barracks";127;1
"Unit";"SCV";"Command Center";133;1
"Unit";"SCV";"Command Center";133;1
"Unit";"Marine";"Barracks";131;1
"Unit";"Marine";"Barracks";131;1
"Unit";"Marine";"Barracks";131;1
"Unit";"Marine";"Barracks";135;1
"Unit";"Marine";"Barracks";135;1
"Unit";"Marine";"Barracks";135;1
"Building";"Factory";NA;118;0
"Unit";"Marine";"Barracks";136;1
"Unit";"Marine";"Barracks";137;1
"Unit";"SCV";"Command Center";144;1
"Unit";"SCV";"Command Center";144;1
"Unit";"SCV";"Command Center";144;1
"Building";"SensorTower";NA;141;0
"Unit";"Marine";"Barracks";141;1
"Unit";"Marine";"Barracks";141;1
"Building";"Armory";NA;120;0
"Unit";"Medivac";"Starport";135;2
"Unit";"Medivac";"Starport";135;2
"Unit";"Marine";"Barracks";147;1
"Unit";"SCV";"Command Center";158;1
"Unit";"SCV";"Command Center";158;1
"Unit";"SCV";"Command Center";158;1
"Unit";"Marine";"Barracks";158;1
"Unit";"Marine";"Barracks";158;1
"Unit";"Marine";"Barracks";158;1
"Unit";"Marine";"Barracks";158;1
"Unit";"Marine";"Barracks";158;1
"Building";"FactoryTechLab";NA;159;0
"Unit";"SCV";"Command Center";159;1
"Unit";"SCV";"Command Center";160;1
"Unit";"SCV";"Command Center";161;1
"Unit";"Marine";"Barracks";159;1
"Unit";"Marine";"Barracks";159;1
"Unit";"Marine";"Barracks";159;1
"Unit";"Marine";"Barracks";159;1
"Unit";"Marine";"Barracks";162;1
"Unit";"Marine";"Barracks";163;1
"Unit";"SCV";"Command Center";167;1
"Unit";"SCV";"Command Center";168;1
"Unit";"SCV";"Command Center";169;1
"Unit";"Marine";"Barracks";167;1
"Unit";"Marine";"Barracks";167;1
"Unit";"SCV";"Command Center";176;1
"Unit";"Marine";"Barracks";174;1
"Upgrade";"TerranInfantryArmorsLevel1";"EngineeringBay";141;0
"Unit";"SCV";"Command Center";181;1
"Unit";"SCV";"Command Center";181;1
"Unit";"Medivac";"Starport";171;2
"Unit";"Medivac";"Starport";171;2
"Unit";"Marine";"Barracks";181;1
"Unit";"Marine";"Barracks";181;1
"Unit";"Marine";"Barracks";181;1
"Unit";"Marine";"Barracks";181;1
"Unit";"Marine";"Barracks";181;1
"Unit";"Marine";"Barracks";181;1
"Unit";"Marine";"Barracks";181;1
"Unit";"Marine";"Barracks";183;1
"Unit";"Marine";"Barracks";183;1
"Unit";"Marine";"Barracks";189;1
"Unit";"Marine";"Barracks";196;1
"Unit";"Marine";"Barracks";196;1
"Unit";"Marine";"Barracks";196;1
"Unit";"Marine";"Barracks";196;1
"Unit";"Marine";"Barracks";196;1
"Unit";"Marine";"Barracks";196;1
"Unit";"Marine";"Barracks";198;1
"Unit";"Marine";"Barracks";199;1
"Unit";"Marine";"Barracks";199;1
"Unit";"Medivac";"Starport";197;2
"Unit";"Marine";"Barracks";199;1
"Unit";"Marine";"Barracks";200;1
"Unit";"Medivac";"Starport";198;2
"Unit";"Marine";"Barracks";201;1
"Building";"SupplyDepot";NA;201;0
"Building";"SupplyDepot";NA;201;0
"Building";"SupplyDepot";NA;201;0
"Unit";"Marine";"Barracks";206;1
"Unit";"Marine";"Barracks";206;1
"Unit";"Marine";"Barracks";208;1
"Unit";"Marine";"Barracks";208;1
"Unit";"Marine";"Barracks";210;1
"Unit";"Marine";"Barracks";215;1
"Unit";"Marine";"Barracks";215;1
"Unit";"Marine";"Barracks";215;1
"Unit";"Marine";"Barracks";215;1
"Unit";"Medivac";"Starport";208;2
"Unit";"Marine";"Barracks";217;1
"Unit";"Marine";"Barracks";217;1
"Unit";"Medivac";"Starport";215;2
"Unit";"Marine";"Barracks";217;1
"Unit";"Marine";"Barracks";218;1
"Unit";"Marine";"Barracks";219;1
"Unit";"Marine";"Barracks";220;1
"Upgrade";"TerranInfantryWeaponsLevel2";"EngineeringBay";181;0
"Unit";"Marine";"Barracks";221;1
"Unit";"Marine";"Barracks";222;1
"Unit";"Marine";"Barracks";223;1
"Unit";"Marine";"Barracks";226;1
"Unit";"Marine";"Barracks";227;1
"Unit";"Marine";"Barracks";230;1
"Unit";"Marine";"Barracks";231;1
"Unit";"Marine";"Barracks";232;1
"Unit";"Marine";"Barracks";233;1
"Unit";"Medivac";"Starport";224;2
"Building";"SensorTower";NA;237;0
"Unit";"Marine";"Barracks";237;1
"Unit";"Marine";"Barracks";237;1
"Unit";"Marine";"Barracks";237;1
"Unit";"Marine";"Barracks";237;1
"Unit";"Marine";"Barracks";238;1
"Unit";"Marine";"Barracks";239;1
"Unit";"Marine";"Barracks";242;1
"Unit";"Marine";"Barracks";242;1
"Unit";"Marine";"Barracks";245;1
"Unit";"SCV";"Command Center";253;1
"Unit";"SCV";"Command Center";253;1
"Unit";"SCV";"Command Center";253;1
"Upgrade";"TerranInfantryArmorsLevel2";"EngineeringBay";208;0
"Unit";"SCV";"Command Center";254;1
"Unit";"Medivac";"Starport";253;2
"Unit";"Medivac";"Starport";253;2
"Unit";"Marine";"Barracks";256;1
"Unit";"Marine";"Barracks";256;1
"Unit";"Marine";"Barracks";257;1
"Unit";"Marine";"Barracks";257;1
"Unit";"Marine";"Barracks";257;1
"Unit";"Marine";"Barracks";257;1
"Unit";"Marine";"Barracks";257;1
"Building";"CommandCenter";NA;237;0
"Unit";"Marine";"Barracks";257;1
"Unit";"Marine";"Barracks";270;1
"Unit";"Marine";"Barracks";270;1
"Unit";"Marine";"Barracks";270;1
"Unit";"Marine";"Barracks";270;1
"Unit";"Marine";"Barracks";270;1
"Unit";"Marine";"Barracks";270;1
"Unit";"Marine";"Barracks";270;1
"Unit";"Marine";"Barracks";270;1
"Unit";"Marine";"Barracks";270;1
