"Type";"UnitName";"OnBuilding";"TotalSupply";"Supply"
"Unit";"SCV";"Command Center";12;1
"Unit";"SCV";"Command Center";13;1
"Building";"SupplyDepot";NA;13;0
"Unit";"SCV";"Command Center";14;1
"Building";"Refinery";NA;14;0
"Unit";"SCV";"Command Center";15;1
"Unit";"SCV";"Command Center";15;1
"Unit";"SCV";"Command Center";16;1
"Unit";"SCV";"Command Center";17;1
"Building";"Refinery";NA;17;0
"Building";"Barracks";NA;15;0
"Unit";"SCV";"Command Center";18;1
"Unit";"Reaper";"Barracks";19;1
"Building";"SupplyDepot";NA;20;0
"Unit";"SCV";"Command Center";21;1
"Building";"Factory";NA;20;0
"Unit";"Reaper";"Barracks";20;1
"Unit";"SCV";"Command Center";22;1
"Unit";"Hellion";"Factory";22;2
"Building";"SupplyDepot";NA;22;0
"Unit";"SCV";"Command Center";24;1
"Building";"Starport";NA;22;0
"Unit";"Hellion";"Factory";24;2
"Building";"BarracksReactor";NA;23;0
"Unit";"SCV";"Command Center";29;1
"Building";"SupplyDepot";NA;29;0
"Unit";"Liberator";"Starport";29;3
"Unit";"Cyclone";"Factory";30;3
"Unit";"Cyclone";"Factory";30;3
"Building";"BarracksTechLab";NA;30;0
"Building";"StarportTechLab";NA;33;0
"Building";"EngineeringBay";NA;30;0
"Building";"CommandCenter";NA;29;0
"Building";"Barracks";NA;33;0
"Building";"Barracks";NA;33;0
"Unit";"Marine";"Barracks";39;1
"Unit";"Banshee";"Starport";39;3
"Unit";"Marine";"Barracks";40;1
"Unit";"SCV";"Command Center";44;1
"Unit";"SCV";"Command Center";44;1
"Unit";"SCV";"Command Center";44;1
"Unit";"Banshee";"Starport";44;3
"Unit";"SCV";"Command Center";46;1
"Unit";"SCV";"Command Center";50;1
"Building";"FactoryTechLab";NA;47;0
"Building";"MissileTurret";NA;51;0
"Unit";"SCV";"Command Center";51;1
"Unit";"Marine";"Barracks";51;1
"Building";"BarracksReactor";NA;47;0
"Unit";"Marine";"Barracks";51;1
"Unit";"Marine";"Barracks";51;1
"Unit";"SCV";"Command Center";52;1
"Unit";"SCV";"Command Center";52;1
"Upgrade";"Stimpack";"TechLab";40;0
"Unit";"Marine";"Barracks";52;1
"Unit";"Marine";"Barracks";54;1
"Unit";"SCV";"Command Center";60;1
"Building";"CommandCenter";NA;47;0
"Unit";"Marine";"Barracks";60;1
"Unit";"SCV";"Command Center";61;1
"Building";"Refinery";NA;61;0
"Unit";"SCV";"Command Center";62;1
"Building";"Refinery";NA;61;0
"Unit";"Marine";"Barracks";62;1
"Unit";"Marine";"Barracks";62;1
"Unit";"Marine";"Barracks";62;1
"Unit";"Marine";"Barracks";62;1
"Unit";"Marine";"Barracks";62;1
"Unit";"SCV";"Command Center";63;1
"Unit";"SCV";"Command Center";63;1
"Building";"Barracks";NA;60;0
"Building";"Refinery";NA;63;0
"Building";"Refinery";NA;63;0
"Building";"EngineeringBay";NA;63;0
"Building";"Barracks";NA;61;0
"Unit";"Marine";"Barracks";70;1
"Unit";"Marine";"Barracks";70;1
"Unit";"SCV";"Command Center";70;1
"Unit";"SCV";"Command Center";71;1
"Unit";"SCV";"Command Center";71;1
"Unit";"SCV";"Command Center";73;1
"Unit";"SCV";"Command Center";75;1
"Unit";"Marine";"Barracks";76;1
"Unit";"Marine";"Barracks";76;1
"Unit";"Marine";"Barracks";76;1
"Unit";"Marine";"Barracks";76;1
"Unit";"Marine";"Barracks";76;1
"Building";"CommandCenter";NA;61;0
"Building";"SupplyDepot";NA;77;0
"Building";"SupplyDepot";NA;77;0
"Unit";"SCV";"Command Center";83;1
"Unit";"SCV";"Command Center";83;1
"Unit";"Marine";"Barracks";83;1
"Unit";"Marine";"Barracks";83;1
"Unit";"Marine";"Barracks";83;1
"Unit";"Marine";"Barracks";83;1
"Unit";"Marine";"Barracks";83;1
"Unit";"SCV";"Command Center";83;1
"Unit";"SCV";"Command Center";83;1
"Unit";"SCV";"Command Center";85;1
"Unit";"Marine";"Barracks";83;1
"Unit";"Marine";"Barracks";85;1
"Unit";"Marine";"Barracks";85;1
"Unit";"Marine";"Barracks";85;1
"Unit";"Marine";"Barracks";85;1
"Unit";"Marine";"Barracks";85;1
"Unit";"Marine";"Barracks";85;1
"Unit";"SCV";"Command Center";90;1
"Building";"StarportReactor";NA;83;0
"Unit";"SCV";"Command Center";92;1
"Unit";"Marine";"Barracks";93;1
"Unit";"Marine";"Barracks";94;1
"Unit";"SCV";"Command Center";101;1
"Unit";"Marine";"Barracks";95;1
"Unit";"Marine";"Barracks";95;1
"Unit";"Marine";"Barracks";95;1
"Building";"MissileTurret";NA;102;0
"Unit";"Marine";"Barracks";102;1
"Unit";"Marine";"Barracks";102;1
"Building";"SupplyDepot";NA;108;0
"Building";"SupplyDepot";NA;108;0
"Building";"SupplyDepot";NA;108;0
"Unit";"Marine";"Barracks";110;1
"Unit";"SCV";"Command Center";110;1
"Unit";"Marine";"Barracks";110;1
"Unit";"Marine";"Barracks";110;1
"Unit";"Marine";"Barracks";110;1
"Unit";"Marine";"Barracks";110;1
"Unit";"Marauder";"Barracks";110;2
"Unit";"Medivac";"Starport";110;2
"Unit";"Medivac";"Starport";110;2
"Unit";"SCV";"Command Center";111;1
"Unit";"SCV";"Command Center";111;1
"Building";"BarracksReactor";NA;110;0
"Unit";"SCV";"Command Center";116;1
"Unit";"SCV";"Command Center";122;1
"Unit";"SCV";"Command Center";124;1
"Unit";"Marauder";"Barracks";116;2
"Unit";"SCV";"Command Center";124;1
"Unit";"SCV";"Command Center";125;1
"Building";"BarracksReactor";NA;112;0
"Unit";"Medivac";"Starport";118;2
"Unit";"Medivac";"Starport";120;2
"Unit";"Marine";"Barracks";126;1
"Unit";"Marine";"Barracks";126;1
"Unit";"Marine";"Barracks";127;1
"Unit";"Marine";"Barracks";127;1
"Unit";"SCV";"Command Center";130;1
"Building";"SupplyDepot";NA;126;0
"Unit";"Marine";"Barracks";131;1
"Unit";"Marine";"Barracks";131;1
"Unit";"Marine";"Barracks";131;1
"Unit";"Marine";"Barracks";131;1
"Unit";"Marine";"Barracks";131;1
"Unit";"SCV";"Command Center";139;1
"Building";"Armory";NA;124;0
"Unit";"Marine";"Barracks";135;1
"Unit";"Marine";"Barracks";136;1
"Unit";"Marine";"Barracks";137;1
"Unit";"Marine";"Barracks";138;1
"Building";"MissileTurret";NA;140;0
"Unit";"Medivac";"Starport";131;2
"Unit";"Medivac";"Starport";133;2
"Upgrade";"TerranInfantryArmorsLevel1";"EngineeringBay";111;0
"Upgrade";"TerranInfantryWeaponsLevel1";"EngineeringBay";111;0
"Building";"Refinery";NA;146;0
"Building";"Refinery";NA;146;0
"Unit";"Marine";"Barracks";154;1
"Unit";"Marine";"Barracks";154;1
"Unit";"Marine";"Barracks";154;1
"Unit";"Marine";"Barracks";154;1
"Unit";"Marine";"Barracks";154;1
"Unit";"Marine";"Barracks";154;1
"Unit";"Marine";"Barracks";154;1
"Unit";"Marine";"Barracks";154;1
"Unit";"Marine";"Barracks";154;1
"Unit";"Marine";"Barracks";154;1
"Unit";"Marine";"Barracks";155;1
"Unit";"Marine";"Barracks";155;1
"Unit";"Marine";"Barracks";157;1
"Unit";"Marine";"Barracks";158;1
"Unit";"Marine";"Barracks";158;1
"Unit";"Marine";"Barracks";160;1
"Unit";"Marine";"Barracks";160;1
"Unit";"Marine";"Barracks";162;1
