"Type";"UnitName";"OnBuilding";"TotalSupply";"Supply"
"Unit";"SCV";"Command Center";12;1
"Unit";"SCV";"Command Center";12;1
"Unit";"SCV";"Command Center";13;1
"Building";"SupplyDepot";NA;13;0
"Building";"Refinery";NA;14;0
"Unit";"SCV";"Command Center";15;1
"Unit";"SCV";"Command Center";16;1
"Unit";"SCV";"Command Center";16;1
"Building";"Refinery";NA;16;0
"Unit";"SCV";"Command Center";18;1
"Building";"Barracks";NA;15;0
"Unit";"SCV";"Command Center";18;1
"Unit";"Reaper";"Barracks";19;1
"Building";"SupplyDepot";NA;20;0
"Unit";"SCV";"Command Center";20;1
"Building";"Factory";NA;19;0
"Unit";"SCV";"Command Center";21;1
"Unit";"Reaper";"Barracks";20;1
"Unit";"SCV";"Command Center";23;1
"Unit";"Cyclone";"Factory";23;3
"Building";"Starport";NA;22;0
"Unit";"SCV";"Command Center";24;1
"Building";"SupplyDepot";NA;24;0
"Unit";"SCV";"Command Center";28;1
"Building";"BarracksReactor";NA;24;0
"Unit";"Cyclone";"Factory";29;3
"Unit";"Marine";"Barracks";30;1
"Unit";"Marine";"Barracks";30;1
"Unit";"SCV";"Command Center";35;1
"Unit";"Cyclone";"Factory";35;3
"Building";"SupplyDepot";NA;35;0
"Building";"SupplyDepot";NA;35;0
"Unit";"SCV";"Command Center";39;1
"Unit";"Marine";"Barracks";39;1
"Unit";"Marine";"Barracks";39;1
"Unit";"Liberator";"Starport";35;3
"Building";"FactoryTechLab";NA;39;0
"Unit";"SCV";"Command Center";42;1
"Building";"CommandCenter";NA;30;0
"Building";"Barracks";NA;36;0
"Unit";"Marine";"Barracks";45;1
"Unit";"Marine";"Barracks";45;1
"Unit";"SCV";"Command Center";46;1
"Unit";"SCV";"Command Center";48;1
"Building";"StarportReactor";NA;45;0
"Building";"BarracksTechLab";NA;48;0
"Unit";"Marine";"Barracks";49;1
"Unit";"SCV";"Command Center";49;1
"Building";"Barracks";NA;42;0
"Unit";"SCV";"Command Center";52;1
"Unit";"SCV";"Command Center";52;1
"Unit";"Marine";"Barracks";52;1
"Unit";"Marine";"Barracks";52;1
"Building";"SupplyDepot";NA;52;0
"Unit";"SCV";"Command Center";54;1
"Unit";"SCV";"Command Center";54;1
"Unit";"Marine";"Barracks";54;1
"Unit";"Medivac";"Starport";52;2
"Building";"BarracksReactor";NA;52;0
"Unit";"Marine";"Barracks";56;1
"Unit";"Marine";"Barracks";56;1
"Unit";"SCV";"Command Center";58;1
"Unit";"SCV";"Command Center";58;1
"Unit";"Marine";"Barracks";61;1
"Unit";"Marine";"Barracks";61;1
"Building";"Barracks";NA;52;0
"Building";"EngineeringBay";NA;58;0
"Unit";"Marine";"Barracks";65;1
"Unit";"Marine";"Barracks";65;1
"Unit";"Medivac";"Starport";59;2
"Unit";"SCV";"Command Center";67;1
"Unit";"SCV";"Command Center";67;1
"Unit";"Marine";"Barracks";67;1
"Unit";"Marine";"Barracks";67;1
"Unit";"Marine";"Barracks";67;1
"Unit";"SCV";"Command Center";76;1
"Unit";"SCV";"Command Center";76;1
"Unit";"Marine";"Barracks";76;1
"Unit";"Marine";"Barracks";76;1
"Unit";"Marine";"Barracks";76;1
"Unit";"Marine";"Barracks";76;1
"Building";"BarracksReactor";NA;73;0
"Unit";"Marine";"Barracks";78;1
"Unit";"Marine";"Barracks";78;1
"Unit";"Marine";"Barracks";79;1
"Unit";"Marine";"Barracks";81;1
"Upgrade";"Stimpack";"TechLab";61;0
"Building";"SupplyDepot";NA;81;0
"Unit";"Marine";"Barracks";81;1
"Building";"SupplyDepot";NA;81;0
"Building";"Refinery";NA;81;0
"Building";"Refinery";NA;82;0
"Unit";"Marine";"Barracks";85;1
"Unit";"Marine";"Barracks";88;1
"Unit";"Marine";"Barracks";88;1
"Unit";"Marine";"Barracks";88;1
"Unit";"Marine";"Barracks";88;1
"Unit";"Marine";"Barracks";88;1
"Unit";"Marine";"Barracks";88;1
"Unit";"Marauder";"Barracks";88;2
"Unit";"SCV";"Command Center";88;1
"Unit";"SCV";"Command Center";88;1
"Unit";"Medivac";"Starport";88;2
"Unit";"Medivac";"Starport";88;2
"Unit";"Marine";"Barracks";88;1
"Unit";"Marine";"Barracks";89;1
"Unit";"SCV";"Command Center";98;1
"Unit";"Marauder";"Barracks";94;2
"Building";"CommandCenter";NA;81;0
"Unit";"Marine";"Barracks";104;1
"Unit";"Marine";"Barracks";104;1
"Unit";"Marine";"Barracks";104;1
"Unit";"Marine";"Barracks";104;1
"Unit";"Medivac";"Starport";98;2
"Unit";"Marine";"Barracks";107;1
"Unit";"Marine";"Barracks";107;1
"Unit";"Marine";"Barracks";107;1
"Unit";"SCV";"Command Center";109;1
"Unit";"SCV";"Command Center";109;1
"Unit";"Marine";"Barracks";111;1
"Unit";"Marine";"Barracks";111;1
"Unit";"Marine";"Barracks";111;1
"Unit";"Marine";"Barracks";111;1
"Building";"EngineeringBay";NA;107;0
"Building";"Barracks";NA;102;0
"Unit";"SCV";"Command Center";116;1
"Unit";"SCV";"Command Center";117;1
"Unit";"Marine";"Barracks";113;1
"Building";"Barracks";NA;102;0
"Building";"Barracks";NA;102;0
"Building";"SupplyDepot";NA;115;0
"Building";"SupplyDepot";NA;115;0
"Unit";"Marine";"Barracks";118;1
"Unit";"Marine";"Barracks";118;1
"Unit";"SCV";"Command Center";125;1
"Unit";"SCV";"Command Center";125;1
"Unit";"Marine";"Barracks";122;1
"Unit";"Marine";"Barracks";127;1
"Unit";"Marine";"Barracks";127;1
"Unit";"Marine";"Barracks";127;1
"Unit";"Marauder";"Barracks";127;2
"Unit";"Marine";"Barracks";130;1
"Unit";"Marine";"Barracks";130;1
"Unit";"Marine";"Barracks";130;1
"Unit";"Marine";"Barracks";130;1
"Building";"BarracksReactor";NA;127;0
"Building";"BarracksReactor";NA;127;0
"Building";"BarracksReactor";NA;129;0
"Unit";"Marine";"Barracks";135;1
"Unit";"Marine";"Barracks";135;1
"Unit";"Marine";"Barracks";135;1
"Unit";"Marine";"Barracks";138;1
"Unit";"Marine";"Barracks";138;1
"Unit";"Marine";"Barracks";138;1
"Unit";"Marine";"Barracks";138;1
"Unit";"SCV";"Command Center";142;1
"Unit";"SCV";"Command Center";142;1
"Unit";"SCV";"Command Center";142;1
"Unit";"Marine";"Barracks";139;1
"Unit";"Marine";"Barracks";139;1
"Unit";"Marine";"Barracks";139;1
