"Type";"UnitName";"OnBuilding";"TotalSupply";"Supply"
"Unit";"SCV";"Command Center";12;1
"Unit";"SCV";"Command Center";12;1
"Unit";"SCV";"Command Center";13;1
"Building";"SupplyDepot";NA;13;0
"Unit";"SCV";"Command Center";15;1
"Building";"Refinery";NA;14;0
"Unit";"SCV";"Command Center";15;1
"Unit";"SCV";"Command Center";16;1
"Building";"Refinery";NA;16;0
"Unit";"SCV";"Command Center";17;1
"Building";"Barracks";NA;15;0
"Unit";"SCV";"Command Center";18;1
"Unit";"Reaper";"Barracks";19;1
"Building";"SupplyDepot";NA;20;0
"Unit";"SCV";"Command Center";21;1
"Building";"Factory";NA;19;0
"Unit";"SCV";"Command Center";21;1
"Building";"BarracksReactor";NA;21;0
"Unit";"SCV";"Command Center";22;1
"Building";"SupplyDepot";NA;22;0
"Unit";"Cyclone";"Factory";22;3
"Unit";"SCV";"Command Center";23;1
"Unit";"SCV";"Command Center";28;1
"Building";"Starport";NA;23;0
"Building";"SupplyDepot";NA;28;0
"Unit";"Marine";"Barracks";29;1
"Unit";"Marine";"Barracks";29;1
"Unit";"SCV";"Command Center";29;1
"Unit";"Cyclone";"Factory";29;3
"Unit";"Marine";"Barracks";29;1
"Unit";"SCV";"Command Center";32;1
"Unit";"Medivac";"Starport";29;2
"Unit";"SCV";"Command Center";36;1
"Unit";"Marine";"Barracks";37;1
"Unit";"Marine";"Barracks";37;1
"Building";"CommandCenter";NA;28;0
"Unit";"Cyclone";"Factory";37;3
"Unit";"SCV";"Command Center";39;1
"Building";"StarportTechLab";NA;40;0
"Unit";"SCV";"Command Center";45;1
"Unit";"Marine";"Barracks";40;1
"Unit";"Marine";"Barracks";41;1
"Building";"FactoryTechLab";NA;46;0
"Unit";"SCV";"Command Center";46;1
"Unit";"SCV";"Command Center";49;1
"Unit";"SCV";"Command Center";50;1
"Unit";"SCV";"Command Center";50;1
"Unit";"SCV";"Command Center";51;1
"Unit";"Marine";"Barracks";52;1
"Unit";"Marine";"Barracks";52;1
"Unit";"Raven";"Starport";49;2
"Unit";"SCV";"Command Center";52;1
"Unit";"SCV";"Command Center";53;1
"Building";"Refinery";NA;52;0
"Building";"Refinery";NA;53;0
"Building";"SupplyDepot";NA;54;0
"Unit";"SCV";"Command Center";60;1
"Unit";"SCV";"Command Center";60;1
"Building";"CommandCenter";NA;49;0
"Unit";"Marine";"Barracks";60;1
"Unit";"SCV";"Command Center";60;1
"Unit";"SCV";"Command Center";61;1
"Building";"Barracks";NA;52;0
"Building";"Barracks";NA;54;0
"Unit";"SCV";"Command Center";63;1
"Building";"EngineeringBay";NA;62;0
"Building";"StarportReactor";NA;60;0
"Building";"EngineeringBay";NA;62;0
"Unit";"Marine";"Barracks";62;1
"Unit";"SCV";"Command Center";65;1
"Unit";"SCV";"Command Center";65;1
"Unit";"Marine";"Barracks";66;1
"Building";"SupplyDepot";NA;66;0
"Unit";"Marine";"Barracks";66;1
"Unit";"SCV";"Command Center";69;1
"Unit";"SCV";"Command Center";69;1
"Building";"BarracksReactor";NA;65;0
"Unit";"Marine";"Barracks";69;1
"Unit";"Marine";"Barracks";69;1
"Unit";"SCV";"Command Center";71;1
"Unit";"SCV";"Command Center";72;1
"Unit";"Medivac";"Starport";69;2
"Unit";"SCV";"Command Center";74;1
"Unit";"Marine";"Barracks";73;1
"Unit";"Marine";"Barracks";73;1
"Unit";"Marine";"Barracks";73;1
"Unit";"SCV";"Command Center";75;1
"Unit";"SCV";"Command Center";76;1
"Unit";"Marine";"Barracks";73;1
"Unit";"SCV";"Command Center";79;1
"Building";"SupplyDepot";NA;77;0
"Unit";"Marine";"Barracks";80;1
"Unit";"SCV";"Command Center";86;1
"Unit";"SCV";"Command Center";86;1
"Building";"SupplyDepot";NA;79;0
"Unit";"SCV";"Command Center";87;1
"Building";"Barracks";NA;73;0
"Building";"Barracks";NA;73;0
"Unit";"Marine";"Barracks";87;1
"Unit";"SCV";"Command Center";90;1
"Unit";"Marine";"Barracks";87;1
"Unit";"Marine";"Barracks";87;1
"Unit";"Marine";"Barracks";87;1
"Unit";"Marine";"Barracks";90;1
"Unit";"SCV";"Command Center";91;1
"Unit";"SCV";"Command Center";91;1
"Building";"SensorTower";NA;90;0
"Unit";"Medivac";"Starport";87;2
"Unit";"Medivac";"Starport";87;2
"Unit";"Marine";"Barracks";91;1
"Unit";"Marine";"Barracks";92;1
"Unit";"Marine";"Barracks";92;1
"Unit";"Marine";"Barracks";92;1
"Upgrade";"Stimpack";"TechLab";69;0
"Unit";"Marine";"Barracks";103;1
"Upgrade";"TerranInfantryWeaponsLevel1";"EngineeringBay";73;0
"Upgrade";"TerranInfantryArmorsLevel1";"EngineeringBay";73;0
"Unit";"Marine";"Barracks";103;1
"Building";"SupplyDepot";NA;103;0
"Building";"SupplyDepot";NA;103;0
"Building";"SupplyDepot";NA;104;0
"Building";"BarracksReactor";NA;99;0
"Building";"BarracksReactor";NA;99;0
"Unit";"SCV";"Command Center";109;1
"Unit";"SCV";"Command Center";109;1
"Unit";"SCV";"Command Center";109;1
"Unit";"Marine";"Barracks";109;1
"Unit";"Marine";"Barracks";109;1
"Unit";"Marine";"Barracks";109;1
"Unit";"Marine";"Barracks";109;1
"Unit";"Marine";"Barracks";109;1
"Unit";"SCV";"Command Center";109;1
"Unit";"SCV";"Command Center";110;1
"Unit";"Marine";"Barracks";109;1
"Unit";"Marine";"Barracks";109;1
"Building";"Armory";NA;104;0
"Building";"Refinery";NA;109;0
"Building";"Refinery";NA;109;0
"Unit";"SCV";"Command Center";111;1
"Unit";"Medivac";"Starport";109;2
"Unit";"Marine";"Barracks";111;1
"Unit";"Marine";"Barracks";111;1
"Unit";"SCV";"Command Center";117;1
"Unit";"SCV";"Command Center";118;1
"Unit";"Marine";"Barracks";112;1
"Unit";"Marine";"Barracks";113;1
"Unit";"SCV";"Command Center";121;1
"Unit";"Marine";"Barracks";119;1
"Unit";"Marine";"Barracks";119;1
"Unit";"Marine";"Barracks";119;1
"Unit";"SCV";"Command Center";126;1
"Unit";"SCV";"Command Center";127;1
"Unit";"Medivac";"Starport";118;2
"Unit";"SCV";"Command Center";130;1
"Unit";"SCV";"Command Center";136;1
"Unit";"SCV";"Command Center";136;1
"Unit";"Marine";"Barracks";135;1
"Unit";"Marine";"Barracks";136;1
"Unit";"SCV";"Command Center";138;1
"Unit";"Marine";"Barracks";136;1
"Unit";"Marine";"Barracks";136;1
"Unit";"Marine";"Barracks";136;1
"Unit";"Marine";"Barracks";136;1
"Unit";"Marine";"Barracks";136;1
"Unit";"Marine";"Barracks";136;1
"Unit";"Marine";"Barracks";136;1
"Building";"SupplyDepot";NA;139;0
"Building";"SupplyDepot";NA;139;0
"Unit";"Marine";"Barracks";141;1
"Unit";"Marine";"Barracks";142;1
"Unit";"Marine";"Barracks";145;1
"Unit";"Marine";"Barracks";145;1
"Unit";"Marine";"Barracks";151;1
"Unit";"Marine";"Barracks";151;1
"Unit";"Marine";"Barracks";151;1
"Building";"SupplyDepot";NA;145;0
"Building";"SupplyDepot";NA;151;0
"Building";"SupplyDepot";NA;151;0
"Unit";"Marine";"Barracks";151;1
"Unit";"Marine";"Barracks";151;1
"Unit";"Marine";"Barracks";151;1
"Unit";"Marine";"Barracks";152;1
"Unit";"Marine";"Barracks";153;1
"Unit";"Marine";"Barracks";154;1
"Unit";"Marine";"Barracks";155;1
"Building";"SupplyDepot";NA;151;0
"Unit";"Marine";"Barracks";156;1
"Unit";"Marine";"Barracks";157;1
"Building";"SupplyDepot";NA;154;0
"Building";"MissileTurret";NA;158;0
"Unit";"Medivac";"Starport";151;2
"Building";"MissileTurret";NA;158;0
"Unit";"Marine";"Barracks";158;1
"Unit";"Marine";"Barracks";160;1
"Unit";"Marine";"Barracks";160;1
"Unit";"Marine";"Barracks";161;1
"Unit";"Marine";"Barracks";162;1
"Unit";"Marine";"Barracks";163;1
"Unit";"Marine";"Barracks";164;1
"Unit";"Marine";"Barracks";165;1
"Unit";"Marine";"Barracks";166;1
"Unit";"Marine";"Barracks";169;1
"Unit";"Marine";"Barracks";170;1
"Unit";"Marine";"Barracks";171;1
"Unit";"Marine";"Barracks";172;1
"Unit";"Marine";"Barracks";173;1
"Unit";"Marine";"Barracks";178;1
"Unit";"Marine";"Barracks";178;1
"Unit";"Marine";"Barracks";178;1
"Unit";"Marine";"Barracks";178;1
"Unit";"Medivac";"Starport";174;2
"Unit";"Medivac";"Starport";175;2
"Unit";"Marine";"Barracks";178;1
"Unit";"Marine";"Barracks";179;1
"Unit";"Marine";"Barracks";180;1
"Unit";"Marine";"Barracks";181;1
"Unit";"Marine";"Barracks";182;1
"Building";"MissileTurret";NA;183;0
"Building";"MissileTurret";NA;183;0
"Unit";"Marine";"Barracks";187;1
"Unit";"Marine";"Barracks";187;1
"Unit";"Marine";"Barracks";187;1
"Unit";"Marine";"Barracks";187;1
"Building";"Factory";NA;178;0
"Unit";"Marine";"Barracks";191;1
"Unit";"Marine";"Barracks";193;1
"Unit";"Marine";"Barracks";193;1
"Unit";"Marine";"Barracks";194;1
"Upgrade";"TerranInfantryWeaponsLevel2";"EngineeringBay";151;0
"Unit";"Marine";"Barracks";204;1
"Unit";"Marine";"Barracks";204;1
"Unit";"Marine";"Barracks";204;1
"Upgrade";"TerranInfantryArmorsLevel2";"EngineeringBay";160;0
"Unit";"Marine";"Barracks";204;1
"Unit";"Marine";"Barracks";204;1
"Unit";"Marine";"Barracks";204;1
"Unit";"Marine";"Barracks";204;1
"Unit";"Marine";"Barracks";204;1
"Unit";"Marine";"Barracks";204;1
"Unit";"Marine";"Barracks";204;1
"Unit";"Marine";"Barracks";205;1
"Unit";"Marine";"Barracks";207;1
"Building";"CommandCenter";NA;180;0
"Unit";"Marine";"Barracks";207;1
"Unit";"Marine";"Barracks";208;1
"Unit";"Marine";"Barracks";209;1
"Unit";"Marine";"Barracks";210;1
"Unit";"Marine";"Barracks";212;1
"Unit";"Marine";"Barracks";212;1
"Unit";"Marine";"Barracks";213;1
"Unit";"Marine";"Barracks";214;1
"Unit";"SCV";"Command Center";216;1
"Unit";"SCV";"Command Center";216;1
"Unit";"SCV";"Command Center";216;1
"Building";"FactoryTechLab";NA;216;0
"Unit";"Medivac";"Starport";212;2
"Unit";"Medivac";"Starport";213;2
"Unit";"SCV";"Command Center";224;1
"Unit";"Marine";"Barracks";222;1
"Unit";"Marine";"Barracks";222;1
"Unit";"Marine";"Barracks";222;1
"Unit";"Marine";"Barracks";222;1
"Building";"SensorTower";NA;222;0
"Unit";"Marine";"Barracks";222;1
"Unit";"Marine";"Barracks";222;1
"Unit";"Marine";"Barracks";222;1
"Unit";"Marine";"Barracks";222;1
"Unit";"Marine";"Barracks";223;1
"Unit";"Marine";"Barracks";232;1
"Unit";"Marine";"Barracks";233;1
"Unit";"Marine";"Barracks";234;1
"Unit";"Marine";"Barracks";234;1
"Unit";"Marine";"Barracks";236;1
"Unit";"Marine";"Barracks";237;1
"Unit";"Marine";"Barracks";237;1
"Unit";"Marine";"Barracks";239;1
"Unit";"Marine";"Barracks";240;1
"Unit";"Medivac";"Starport";231;2
"Unit";"Medivac";"Starport";232;2
"Building";"MissileTurret";NA;241;0
"Unit";"Marine";"Barracks";248;1
"Unit";"Marine";"Barracks";248;1
