"type";"unit_name";"on_building";"total_supply";"supply"
"Building";"Refinery";NA;14;0
"Building";"Barracks";NA;15;0
"Unit";"Marine";"Barracks";19;1
"Unit";"Marine";"Barracks";20;1
"Building";"Factory";NA;19;0
"Unit";"Marine";"Barracks";21;1
"Unit";"Hellion";"Factory";23;2
"Building";"BarracksReactor";NA;24;0
"Building";"Refinery";NA;28;0
"Unit";"Cyclone";"Factory";28;3
"Building";"CommandCenter";NA;24;0
"Unit";"Cyclone";"Factory";35;3
"Unit";"Cyclone";"Factory";35;3
"Building";"Refinery";NA;36;0
"Building";"Refinery";NA;36;0
"Building";"CommandCenter";NA;30;0
"Unit";"Cyclone";"Factory";44;3
"Building";"Armory";NA;37;0
"Unit";"Cyclone";"Factory";46;3
"Building";"BarracksTechLab";NA;46;0
"Building";"Factory";NA;47;0
"Building";"BarracksTechLab";NA;57;0
"Building";"EngineeringBay";NA;60;0
"Building";"Factory";NA;57;0
"Unit";"Hellion";"Factory";65;2
"Unit";"Hellion";"Factory";65;2
"Building";"MissileTurret";NA;68;0
"Building";"MissileTurret";NA;73;0
"Building";"MissileTurret";NA;73;0
"Building";"MissileTurret";NA;73;0
"Unit";"Hellion";"Factory";78;2
"Unit";"Hellion";"Factory";78;2
"Upgrade";"TerranVehicleWeaponsLevel1";"Armory";63;0
"Building";"Refinery";NA;78;0
"Building";"Refinery";NA;78;0
"Building";"BarracksReactor";NA;78;0
"Building";"Starport";NA;78;0
"Unit";"Hellion";"Factory";85;2
"Unit";"Hellion";"Factory";85;2
"Building";"Armory";NA;78;0
"Unit";"Hellion";"Factory";94;2
"Building";"Factory";NA;94;0
"Building";"BarracksReactor";NA;95;0
"Unit";"Hellion";"Factory";99;2
"Unit";"Hellion";"Factory";99;2
"Building";"BarracksTechLab";NA;101;0
"Unit";"Hellion";"Factory";104;2
"Building";"Starport";NA;100;0
"Unit";"Hellion";"Factory";107;2
"Building";"Factory";NA;100;0
"Building";"Starport";NA;107;0
"Building";"Starport";NA;108;0
"Unit";"Hellion";"Factory";112;2
"Unit";"Hellion";"Factory";112;2
"Building";"StarportReactor";NA;110;0
"Upgrade";"TerranVehicleWeaponsLevel2";"Armory";97;0
"Building";"Refinery";NA;112;0
"Building";"CommandCenter";NA;108;0
"Unit";"Hellion";"Factory";116;2
"Unit";"Hellion";"Factory";116;2
"Building";"StarportTechLab";NA;116;0
"Building";"StarportTechLab";NA;116;0
"Unit";"Hellion";"Factory";116;2
"Building";"CommandCenter";NA;112;0
"Unit";"Hellion";"Factory";122;2
"Building";"Refinery";NA;122;0
"Unit";"Hellion";"Factory";122;2
"Unit";"Hellion";"Factory";122;2
"Unit";"Liberator";"Starport";120;3
"Unit";"Liberator";"Starport";120;3
"Unit";"Hellion";"Factory";122;2
"Unit";"Hellion";"Factory";122;2
"Unit";"Liberator";"Starport";120;3
"Unit";"Liberator";"Starport";120;3
"Unit";"Hellion";"Factory";122;2
"Unit";"Liberator";"Starport";124;3
"Building";"CommandCenter";NA;124;0
"Unit";"Hellion";"Factory";151;2
"Upgrade";"TerranShipWeaponsLevel1";"Armory";148;0
"Unit";"Hellion";"Factory";151;2
"Unit";"Hellion";"Factory";153;2
"Unit";"Hellion";"Factory";153;2
"Unit";"Hellion";"Factory";153;2
"Building";"Refinery";NA;153;0
"Building";"Refinery";NA;153;0
"Unit";"Hellion";"Factory";161;2
"Unit";"Hellion";"Factory";161;2
"Unit";"Hellion";"Factory";161;2
"Unit";"Hellion";"Factory";161;2
"Unit";"Hellion";"Factory";161;2
"Unit";"Liberator";"Starport";159;3
"Unit";"Hellion";"Factory";161;2
"Unit";"Hellion";"Factory";161;2
"Unit";"Hellion";"Factory";161;2
"Unit";"Hellion";"Factory";169;2
"Unit";"Hellion";"Factory";169;2
"Unit";"Hellion";"Factory";176;2
"Unit";"Hellion";"Factory";182;2
"Unit";"Hellion";"Factory";184;2
"Unit";"Hellion";"Factory";184;2
"Unit";"Hellion";"Factory";184;2
"Unit";"Hellion";"Factory";184;2
"Unit";"Hellion";"Factory";186;2
"Unit";"Hellion";"Factory";198;2
"Unit";"Hellion";"Factory";198;2
"Unit";"Hellion";"Factory";198;2
"Unit";"Hellion";"Factory";198;2
"Unit";"Hellion";"Factory";198;2
"Unit";"Hellion";"Factory";198;2
"Unit";"Hellion";"Factory";200;2
"Unit";"Hellion";"Factory";202;2
