"type";"unit_name";"on_building";"total_supply";"supply"
"Building";"Refinery";NA;15;0
"Building";"Barracks";NA;15;0
"Unit";"Reaper";"Barracks";19;1
"Unit";"Reaper";"Barracks";19;1
"Building";"CommandCenter";NA;19;0
"Building";"BarracksReactor";NA;23;0
"Building";"Barracks";NA;22;0
"Building";"Barracks";NA;23;0
"Unit";"Marine";"Barracks";24;1
"Unit";"Marine";"Barracks";24;1
"Building";"CommandCenter";NA;22;0
"Building";"Bunker";NA;23;0
"Building";"BarracksTechLab";NA;24;0
"Unit";"Marine";"Barracks";25;1
"Unit";"Marine";"Barracks";26;1
"Unit";"Marine";"Barracks";27;1
"Unit";"Marine";"Barracks";29;1
"Unit";"Marine";"Barracks";29;1
"Building";"Refinery";NA;32;0
"Unit";"Marine";"Barracks";36;1
"Unit";"Marine";"Barracks";36;1
"Unit";"Marine";"Barracks";36;1
"Unit";"Marine";"Barracks";36;1
"Building";"EngineeringBay";NA;37;0
"Building";"Factory";NA;33;0
"Unit";"Marine";"Barracks";46;1
"Unit";"Marine";"Barracks";46;1
"Unit";"Marine";"Barracks";46;1
"Unit";"Marine";"Barracks";46;1
"Unit";"Marine";"Barracks";53;1
"Unit";"Marine";"Barracks";53;1
"Unit";"Marine";"Barracks";53;1
"Unit";"Marine";"Barracks";53;1
"Building";"Starport";NA;47;0
"Building";"FactoryReactor";NA;49;0
"Unit";"Marine";"Barracks";56;1
"Unit";"Marine";"Barracks";57;1
"Unit";"Marine";"Barracks";58;1
"Unit";"Marine";"Barracks";59;1
"Upgrade";"Stimpack";"TechLab";36;0
"Unit";"Marine";"Barracks";63;1
"Unit";"Marine";"Barracks";64;1
"Unit";"Marine";"Barracks";65;1
"Unit";"Marine";"Barracks";66;1
"Unit";"Medivac";"Starport";63;2
"Unit";"Medivac";"Starport";63;2
"Building";"Refinery";NA;67;0
"Building";"Refinery";NA;67;0
"Building";"FactoryTechLab";NA;78;0
"Upgrade";"TerranInfantryWeaponsLevel1";"EngineeringBay";56;0
"Building";"BarracksReactor";NA;74;0
"Unit";"Marine";"Barracks";81;1
"Unit";"Marine";"Barracks";81;1
"Unit";"Marine";"Barracks";81;1
"Building";"Barracks";NA;78;0
"Building";"Barracks";NA;78;0
"Unit";"Medivac";"Starport";81;2
"Unit";"Marine";"Barracks";89;1
"Unit";"Marine";"Barracks";89;1
"Unit";"Marine";"Barracks";89;1
"Unit";"Marine";"Barracks";89;1
"Unit";"Marine";"Barracks";91;1
"Unit";"Marine";"Barracks";91;1
"Unit";"Marine";"Barracks";95;1
"Unit";"Marine";"Barracks";95;1
"Unit";"Marine";"Barracks";95;1
"Building";"BarracksReactor";NA;91;0
"Building";"BarracksReactor";NA;91;0
"Unit";"Marine";"Barracks";95;1
"Unit";"Marine";"Barracks";97;1
"Unit";"Marine";"Barracks";97;1
"Unit";"Marine";"Barracks";98;1
"Unit";"Marine";"Barracks";104;1
"Unit";"Marine";"Barracks";104;1
"Unit";"Marine";"Barracks";104;1
"Unit";"Marine";"Barracks";104;1
"Unit";"Marine";"Barracks";104;1
"Unit";"Marine";"Barracks";104;1
"Unit";"Medivac";"Starport";97;2
"Unit";"Medivac";"Starport";97;2
"Unit";"Marine";"Barracks";104;1
"Unit";"Marine";"Barracks";105;1
"Unit";"Marine";"Barracks";106;1
"Unit";"Marine";"Barracks";115;1
"Unit";"Marine";"Barracks";115;1
"Unit";"Marine";"Barracks";117;1
"Unit";"Marine";"Barracks";125;1
"Unit";"Marine";"Barracks";125;1
"Unit";"Marine";"Barracks";125;1
"Unit";"Marine";"Barracks";125;1
"Unit";"Marine";"Barracks";125;1
"Unit";"Marine";"Barracks";125;1
"Unit";"Marine";"Barracks";126;1
"Upgrade";"TerranInfantryArmorsLevel1";"EngineeringBay";97;0
"Building";"EngineeringBay";NA;129;0
"Unit";"Marine";"Barracks";142;1
"Unit";"Marine";"Barracks";142;1
"Unit";"Medivac";"Starport";139;2
"Unit";"Marine";"Barracks";142;1
"Unit";"Medivac";"Starport";139;2
"Building";"Armory";NA;129;0
"Unit";"Marine";"Barracks";142;1
"Unit";"Marine";"Barracks";142;1
"Unit";"Marine";"Barracks";142;1
"Unit";"Marine";"Barracks";142;1
"Unit";"Marine";"Barracks";142;1
"Unit";"Marine";"Barracks";142;1
"Unit";"Marine";"Barracks";142;1
"Unit";"Marine";"Barracks";143;1
"Unit";"Marine";"Barracks";146;1
"Unit";"Marine";"Barracks";149;1
"Unit";"Marine";"Barracks";150;1
"Unit";"Marine";"Barracks";155;1
"Unit";"Marine";"Barracks";155;1
"Unit";"Marine";"Barracks";158;1
"Unit";"Marine";"Barracks";158;1
"Unit";"Marine";"Barracks";158;1
"Unit";"Marine";"Barracks";158;1
"Unit";"Marine";"Barracks";158;1
"Unit";"Marine";"Barracks";158;1
"Unit";"Marine";"Barracks";162;1
"Unit";"Marine";"Barracks";162;1
"Unit";"Marine";"Barracks";162;1
"Unit";"Marine";"Barracks";162;1
"Unit";"Marine";"Barracks";163;1
"Unit";"Marauder";"Barracks";168;2
"Building";"SensorTower";NA;177;0
"Unit";"Marine";"Barracks";177;1
"Unit";"Marine";"Barracks";179;1
"Unit";"Marine";"Barracks";179;1
"Unit";"Medivac";"Starport";177;2
"Unit";"Medivac";"Starport";177;2
"Unit";"Marine";"Barracks";180;1
"Unit";"Marine";"Barracks";180;1
"Unit";"Marine";"Barracks";180;1
"Unit";"Marine";"Barracks";180;1
"Unit";"Marine";"Barracks";180;1
"Unit";"Marine";"Barracks";180;1
"Unit";"Marine";"Barracks";180;1
"Unit";"Marine";"Barracks";182;1
"Unit";"Marine";"Barracks";185;1
"Unit";"Marine";"Barracks";190;1
"Unit";"Marine";"Barracks";191;1
"Unit";"Marine";"Barracks";193;1
"Unit";"Marine";"Barracks";194;1
"Unit";"Marine";"Barracks";194;1
"Unit";"Marine";"Barracks";195;1
"Unit";"Marine";"Barracks";198;1
"Unit";"Marine";"Barracks";198;1
"Unit";"Marine";"Barracks";198;1
"Unit";"Marine";"Barracks";199;1
"Unit";"Marine";"Barracks";200;1
"Unit";"Marine";"Barracks";201;1
"Unit";"Marine";"Barracks";202;1
"Unit";"Medivac";"Starport";198;2
"Unit";"Medivac";"Starport";198;2
"Unit";"Marine";"Barracks";210;1
"Unit";"Marine";"Barracks";210;1
"Unit";"Marine";"Barracks";210;1
"Unit";"Marine";"Barracks";211;1
"Unit";"Marine";"Barracks";211;1
"Unit";"Marine";"Barracks";211;1
"Unit";"Marine";"Barracks";212;1
"Unit";"Marine";"Barracks";213;1
"Unit";"Marine";"Barracks";214;1
"Unit";"Marine";"Barracks";219;1
"Unit";"Marine";"Barracks";220;1
"Unit";"Marine";"Barracks";221;1
"Unit";"Marine";"Barracks";222;1
"Unit";"Marine";"Barracks";223;1
"Unit";"Marine";"Barracks";224;1
"Unit";"Marine";"Barracks";228;1
"Unit";"Marine";"Barracks";228;1
"Unit";"Marine";"Barracks";228;1
"Upgrade";"TerranInfantryWeaponsLevel2";"EngineeringBay";180;0
"Upgrade";"TerranInfantryArmorsLevel2";"EngineeringBay";180;0
"Unit";"Marine";"Barracks";228;1
"Unit";"Marine";"Barracks";229;1
"Unit";"Marine";"Barracks";230;1
"Unit";"Marine";"Barracks";231;1
"Unit";"Marine";"Barracks";232;1
"Unit";"Marine";"Barracks";233;1
"Unit";"Marine";"Barracks";234;1
"Unit";"Marine";"Barracks";235;1
"Unit";"Marine";"Barracks";236;1
"Unit";"Marine";"Barracks";237;1
"Unit";"Marine";"Barracks";238;1
"Unit";"Marine";"Barracks";239;1
"Unit";"Marine";"Barracks";240;1
"Unit";"Marine";"Barracks";241;1
"Unit";"Marine";"Barracks";242;1
"Unit";"Marine";"Barracks";243;1
"Unit";"Marine";"Barracks";244;1
"Unit";"Marine";"Barracks";245;1
"Unit";"Marine";"Barracks";246;1
"Unit";"Marine";"Barracks";249;1
"Unit";"Marine";"Barracks";249;1
"Unit";"Marine";"Barracks";249;1
"Unit";"Marine";"Barracks";250;1
"Unit";"Marine";"Barracks";251;1
"Unit";"Marine";"Barracks";255;1
"Unit";"Marine";"Barracks";255;1
"Unit";"Marine";"Barracks";255;1
"Unit";"Marine";"Barracks";255;1
"Unit";"Marine";"Barracks";256;1
"Unit";"Marine";"Barracks";260;1
"Unit";"Marine";"Barracks";260;1
"Unit";"Marine";"Barracks";260;1
"Unit";"Marine";"Barracks";271;1
"Unit";"Marine";"Barracks";271;1
"Unit";"Marine";"Barracks";271;1
"Unit";"Marine";"Barracks";271;1
"Unit";"Marine";"Barracks";274;1
"Unit";"Marine";"Barracks";274;1
"Unit";"Marine";"Barracks";274;1
"Unit";"Marine";"Barracks";276;1
"Unit";"Marine";"Barracks";276;1
"Unit";"Marine";"Barracks";277;1
"Unit";"Marine";"Barracks";278;1
"Unit";"Marine";"Barracks";279;1
"Unit";"Marine";"Barracks";287;1
"Unit";"Marine";"Barracks";287;1
"Unit";"Marine";"Barracks";287;1
"Unit";"Marine";"Barracks";290;1
"Unit";"Marine";"Barracks";291;1
"Unit";"Marine";"Barracks";292;1
"Unit";"Marine";"Barracks";292;1
"Unit";"Marine";"Barracks";299;1
"Unit";"Marine";"Barracks";299;1
"Unit";"Marine";"Barracks";299;1
"Unit";"Marine";"Barracks";299;1
"Unit";"Marine";"Barracks";299;1
"Unit";"Marine";"Barracks";299;1
"Unit";"Marine";"Barracks";299;1
"Unit";"Marine";"Barracks";299;1
"Unit";"Marine";"Barracks";299;1
"Unit";"Marine";"Barracks";299;1
"Unit";"Marine";"Barracks";300;1
"Unit";"Marine";"Barracks";301;1
"Unit";"Marine";"Barracks";303;1
"Unit";"Marine";"Barracks";303;1
"Unit";"Marine";"Barracks";304;1
"Unit";"Marine";"Barracks";308;1
"Unit";"Marine";"Barracks";308;1
"Unit";"Marine";"Barracks";308;1
"Unit";"Marine";"Barracks";308;1
"Unit";"Marine";"Barracks";309;1
"Unit";"Marine";"Barracks";310;1
"Unit";"Marine";"Barracks";311;1
"Unit";"Marine";"Barracks";312;1
"Unit";"Marine";"Barracks";317;1
"Unit";"Marine";"Barracks";317;1
"Unit";"Marine";"Barracks";317;1
"Unit";"Marine";"Barracks";317;1
"Upgrade";"TerranInfantryWeaponsLevel3";"EngineeringBay";286;0
"Unit";"Marine";"Barracks";317;1
"Unit";"Marine";"Barracks";318;1
"Unit";"Medivac";"Starport";316;2
"Unit";"Medivac";"Starport";317;2
"Unit";"Marine";"Barracks";320;1
"Unit";"Marine";"Barracks";321;1
"Upgrade";"TerranInfantryArmorsLevel3";"EngineeringBay";291;0
"Unit";"Marine";"Barracks";322;1
"Unit";"Marine";"Barracks";323;1
"Unit";"Marine";"Barracks";323;1
"Unit";"Marine";"Barracks";325;1
"Unit";"Marine";"Barracks";326;1
"Unit";"Marine";"Barracks";327;1
"Unit";"Marine";"Barracks";332;1
"Unit";"Marine";"Barracks";333;1
"Unit";"Marine";"Barracks";334;1
"Unit";"Marine";"Barracks";342;1
"Unit";"Marine";"Barracks";342;1
"Unit";"Marine";"Barracks";342;1
"Unit";"Marine";"Barracks";342;1
"Unit";"Marine";"Barracks";342;1
"Unit";"Marine";"Barracks";343;1
"Unit";"Marine";"Barracks";343;1
"Unit";"Marine";"Barracks";343;1
"Unit";"Marine";"Barracks";343;1
"Unit";"Marine";"Barracks";344;1
"Unit";"Marine";"Barracks";345;1
"Unit";"Marine";"Barracks";345;1
"Unit";"Marine";"Barracks";347;1
"Unit";"Marine";"Barracks";348;1
