"type";"unit_name";"on_building";"total_supply";"supply"
"Building";"Refinery";NA;14;0
"Building";"Barracks";NA;15;0
"Unit";"Marine";"Barracks";19;1
"Unit";"Marine";"Barracks";19;1
"Building";"Bunker";NA;19;0
"Building";"Bunker";NA;19;0
"Unit";"Marine";"Barracks";20;1
"Unit";"Marine";"Barracks";22;1
"Unit";"Marine";"Barracks";26;1
"Building";"Factory";NA;24;0
"Unit";"Marine";"Barracks";27;1
"Unit";"Hellion";"Factory";28;2
"Unit";"Marine";"Barracks";29;1
