"Type";"UnitName";"OnBuilding";"TotalSupply";"Supply"
"Unit";"SCV";"Command Center";12;1
"Unit";"SCV";"Command Center";13;1
"Building";"SupplyDepot";NA;13;0
"Unit";"SCV";"Command Center";14;1
"Building";"Refinery";NA;13;0
"Unit";"SCV";"Command Center";14;1
"Unit";"SCV";"Command Center";16;1
"Unit";"SCV";"Command Center";17;1
"Building";"Refinery";NA;16;0
"Unit";"SCV";"Command Center";17;1
"Building";"Barracks";NA;15;0
"Unit";"Reaper";"Barracks";19;1
"Building";"SupplyDepot";NA;19;0
"Unit";"SCV";"Command Center";19;1
"Building";"Factory";NA;19;0
"Unit";"SCV";"Command Center";20;1
"Unit";"SCV";"Command Center";22;1
"Unit";"Reaper";"Barracks";19;1
"Unit";"Hellion";"Factory";21;2
"Unit";"SCV";"Command Center";22;1
"Unit";"SCV";"Command Center";26;1
"Building";"BarracksTechLab";NA;24;0
"Building";"Starport";NA;24;0
"Building";"SupplyDepot";NA;28;0
"Unit";"Cyclone";"Factory";28;3
"Unit";"SCV";"Command Center";28;1
"Building";"CommandCenter";NA;22;0
"Unit";"SCV";"Command Center";31;1
"Unit";"Cyclone";"Factory";32;3
"Unit";"SCV";"Command Center";33;1
"Unit";"SCV";"Command Center";36;1
"Unit";"Banshee";"Starport";31;3
"Unit";"SCV";"Command Center";37;1
"Unit";"SCV";"Command Center";38;1
"Building";"BarracksReactor";NA;33;0
"Building";"FactoryTechLab";NA;38;0
"Unit";"SCV";"Command Center";41;1
"Unit";"SCV";"Command Center";43;1
"Building";"Refinery";NA;41;0
"Building";"EngineeringBay";NA;41;0
"Unit";"Marine";"Barracks";43;1
"Unit";"SCV";"Command Center";45;1
"Building";"SupplyDepot";NA;43;0
"Unit";"Marine";"Barracks";43;1
"Unit";"SCV";"Command Center";45;1
"Unit";"Banshee";"Starport";38;3
"Building";"FactoryTechLab";NA;45;0
"Unit";"SCV";"Command Center";46;1
"Unit";"SCV";"Command Center";48;1
"Building";"Barracks";NA;41;0
"Building";"Barracks";NA;41;0
"Unit";"Marine";"Barracks";45;1
"Unit";"SCV";"Command Center";52;1
"Unit";"Marine";"Barracks";52;1
"Unit";"SCV";"Command Center";55;1
"Unit";"Marine";"Barracks";55;1
"Unit";"SCV";"Command Center";56;1
"Unit";"SCV";"Command Center";57;1
"Unit";"SCV";"Command Center";59;1
"Unit";"Marine";"Barracks";58;1
"Unit";"Marine";"Barracks";58;1
"Unit";"SCV";"Command Center";60;1
"Building";"SupplyDepot";NA;58;0
"Building";"BarracksReactor";NA;55;0
"Unit";"Marine";"Barracks";60;1
"Unit";"SCV";"Command Center";62;1
"Unit";"Marine";"Barracks";62;1
"Unit";"Marine";"Barracks";63;1
"Unit";"SCV";"Command Center";66;1
"Building";"SupplyDepot";NA;64;0
"Unit";"Marine";"Barracks";65;1
"Unit";"Marine";"Barracks";65;1
"Unit";"Marine";"Barracks";65;1
"Building";"Barracks";NA;58;0
"Building";"Barracks";NA;58;0
"Unit";"SCV";"Command Center";67;1
"Building";"StarportReactor";NA;61;0
"Unit";"Marine";"Barracks";67;1
"Unit";"Marine";"Barracks";68;1
"Unit";"Marine";"Barracks";70;1
"Unit";"Marine";"Barracks";74;1
"Unit";"Marine";"Barracks";74;1
"Building";"SupplyDepot";NA;74;0
"Building";"Refinery";NA;74;0
"Unit";"Marine";"Barracks";74;1
"Unit";"Marine";"Barracks";76;1
"Unit";"SCV";"Command Center";79;1
"Unit";"Marine";"Barracks";79;1
"Unit";"Marine";"Barracks";79;1
"Unit";"Marine";"Barracks";79;1
"Unit";"Medivac";"Starport";76;2
"Unit";"Medivac";"Starport";76;2
"Building";"BarracksReactor";NA;76;0
"Building";"BarracksReactor";NA;76;0
"Unit";"Marine";"Barracks";80;1
"Unit";"Marine";"Barracks";80;1
"Building";"SupplyDepot";NA;81;0
"Unit";"Marine";"Barracks";82;1
"Unit";"Marine";"Barracks";83;1
"Upgrade";"TerranInfantryWeaponsLevel1";"EngineeringBay";65;0
"Unit";"Marine";"Barracks";87;1
"Unit";"Marine";"Barracks";90;1
"Unit";"Marine";"Barracks";91;1
"Unit";"Marine";"Barracks";91;1
"Unit";"Marine";"Barracks";91;1
"Unit";"Marine";"Barracks";91;1
"Unit";"Marine";"Barracks";91;1
"Unit";"Marine";"Barracks";91;1
"Unit";"Marine";"Barracks";92;1
"Unit";"Marine";"Barracks";93;1
"Upgrade";"Stimpack";"TechLab";70;0
"Unit";"Marine";"Barracks";94;1
"Unit";"Marine";"Barracks";95;1
"Unit";"Marine";"Barracks";96;1
"Unit";"Marine";"Barracks";97;1
"Unit";"Marine";"Barracks";98;1
"Unit";"Marine";"Barracks";99;1
"Unit";"Marine";"Barracks";100;1
"Unit";"Marine";"Barracks";101;1
"Unit";"Marine";"Barracks";102;1
"Unit";"Marine";"Barracks";109;1
"Building";"CommandCenter";NA;85;0
"Building";"SupplyDepot";NA;109;0
"Building";"SupplyDepot";NA;109;0
"Building";"SupplyDepot";NA;110;0
"Unit";"Marine";"Barracks";112;1
"Building";"SupplyDepot";NA;112;0
"Unit";"Marine";"Barracks";113;1
"Unit";"Marine";"Barracks";113;1
"Unit";"Marine";"Barracks";113;1
"Unit";"Marine";"Barracks";113;1
"Unit";"Marine";"Barracks";113;1
"Unit";"Marine";"Barracks";113;1
"Unit";"Marine";"Barracks";113;1
"Unit";"Marine";"Barracks";113;1
"Unit";"Medivac";"Starport";113;2
"Unit";"Medivac";"Starport";113;2
"Unit";"Marine";"Barracks";113;1
"Unit";"Marine";"Barracks";114;1
"Unit";"Marine";"Barracks";120;1
"Unit";"Marine";"Barracks";120;1
"Unit";"Marine";"Barracks";121;1
"Unit";"Marine";"Barracks";121;1
"Unit";"Marine";"Barracks";121;1
"Unit";"Marine";"Barracks";122;1
"Unit";"Marine";"Barracks";122;1
"Building";"SupplyDepot";NA;122;0
"Unit";"Marine";"Barracks";127;1
"Unit";"Marine";"Barracks";127;1
"Unit";"Marine";"Barracks";133;1
"Unit";"Marine";"Barracks";133;1
"Unit";"Medivac";"Starport";122;2
"Unit";"Marine";"Barracks";135;1
"Unit";"Marine";"Barracks";135;1
"Unit";"Marine";"Barracks";135;1
"Unit";"Marine";"Barracks";135;1
"Unit";"Marine";"Barracks";135;1
"Upgrade";"TerranInfantryArmorsLevel1";"EngineeringBay";112;0
"Unit";"Marine";"Barracks";136;1
"Unit";"Marine";"Barracks";141;1
"Unit";"Marine";"Barracks";141;1
"Unit";"Marine";"Barracks";143;1
"Unit";"Marine";"Barracks";147;1
"Unit";"Marine";"Barracks";147;1
"Unit";"Marine";"Barracks";147;1
"Unit";"Marine";"Barracks";147;1
"Unit";"Medivac";"Starport";146;2
"Unit";"Marine";"Barracks";147;1
"Unit";"Marine";"Barracks";149;1
"Unit";"Marine";"Barracks";150;1
"Unit";"Marine";"Barracks";150;1
"Unit";"Marine";"Barracks";150;1
"Building";"Armory";NA;141;0
"Unit";"Marine";"Barracks";153;1
"Unit";"Marine";"Barracks";153;1
"Unit";"Marine";"Barracks";153;1
"Unit";"Marine";"Barracks";154;1
"Unit";"Marine";"Barracks";158;1
"Unit";"Marine";"Barracks";158;1
"Unit";"Marine";"Barracks";159;1
"Unit";"Marine";"Barracks";163;1
"Unit";"Marine";"Barracks";164;1
"Unit";"Marine";"Barracks";170;1
"Unit";"Marine";"Barracks";170;1
"Unit";"Marine";"Barracks";170;1
"Unit";"Marine";"Barracks";173;1
"Building";"SupplyDepot";NA;173;0
"Building";"SupplyDepot";NA;173;0
"Unit";"Medivac";"Starport";173;2
"Unit";"Medivac";"Starport";173;2
"Building";"SupplyDepot";NA;174;0
"Building";"SupplyDepot";NA;176;0
"Building";"SupplyDepot";NA;178;0
"Building";"SupplyDepot";NA;178;0
"Building";"SupplyDepot";NA;178;0
"Building";"SupplyDepot";NA;178;0
