"type";"unit_name";"on_building";"total_supply";"supply"
"Building";"Refinery";NA;14;0
"Building";"Barracks";NA;15;0
"Unit";"Reaper";"Barracks";19;1
"Building";"Refinery";NA;21;0
"Building";"Factory";NA;19;0
"Unit";"Reaper";"Barracks";21;1
"Building";"CommandCenter";NA;19;0
"Unit";"Hellion";"Factory";22;2
"Building";"Starport";NA;22;0
"Building";"BarracksReactor";NA;24;0
"Building";"EngineeringBay";NA;27;0
"Unit";"Cyclone";"Factory";27;3
"Unit";"Marine";"Barracks";28;1
"Unit";"Marine";"Barracks";28;1
"Unit";"Medivac";"Starport";28;2
"Unit";"Marine";"Barracks";33;1
"Unit";"Marine";"Barracks";34;1
"Building";"FactoryTechLab";NA;35;0
"Unit";"Marine";"Barracks";41;1
"Unit";"Marine";"Barracks";41;1
"Building";"Barracks";NA;37;0
"Building";"Barracks";NA;37;0
"Building";"BarracksTechLab";NA;47;0
"Building";"Refinery";NA;49;0
"Unit";"Marine";"Barracks";51;1
"Unit";"Marine";"Barracks";51;1
"Building";"StarportReactor";NA;47;0
"Unit";"Marine";"Barracks";51;1
"Building";"BarracksReactor";NA;51;0
"Unit";"Marine";"Barracks";56;1
"Unit";"Marine";"Barracks";56;1
"Unit";"Marine";"Barracks";58;1
"Unit";"Marine";"Barracks";60;1
"Unit";"Marine";"Barracks";61;1
"Unit";"Marine";"Barracks";65;1
"Unit";"Marine";"Barracks";65;1
"Unit";"Marine";"Barracks";67;1
"Unit";"Marine";"Barracks";67;1
"Upgrade";"TerranInfantryWeaponsLevel1";"EngineeringBay";51;0
"Building";"CommandCenter";NA;55;0
"Unit";"Medivac";"Starport";69;2
"Unit";"Medivac";"Starport";69;2
"Building";"Barracks";NA;62;0
"Building";"Barracks";NA;64;0
"Building";"Refinery";NA;73;0
"Unit";"Marine";"Barracks";75;1
"Unit";"Marine";"Barracks";75;1
"Unit";"Marine";"Barracks";77;1
"Unit";"Marine";"Barracks";77;1
"Unit";"Marine";"Barracks";77;1
"Upgrade";"Stimpack";"TechLab";62;0
"Unit";"Marine";"Barracks";87;1
"Unit";"Marine";"Barracks";87;1
"Unit";"Marine";"Barracks";87;1
"Building";"BarracksReactor";NA;81;0
"Unit";"Marine";"Barracks";88;1
"Unit";"Marine";"Barracks";89;1
"Building";"BarracksReactor";NA;81;0
"Unit";"Marine";"Barracks";96;1
"Unit";"Marine";"Barracks";96;1
"Unit";"Marine";"Barracks";96;1
"Unit";"Marine";"Barracks";96;1
"Unit";"Marine";"Barracks";96;1
"Unit";"Marine";"Barracks";96;1
"Unit";"Marine";"Barracks";96;1
"Unit";"Marine";"Barracks";96;1
"Unit";"Medivac";"Starport";96;2
"Unit";"Marine";"Barracks";98;1
"Building";"Factory";NA;89;0
"Unit";"Marine";"Barracks";100;1
"Unit";"Marine";"Barracks";108;1
"Unit";"Marine";"Barracks";109;1
"Unit";"Marine";"Barracks";109;1
"Unit";"Marine";"Barracks";109;1
"Building";"Refinery";NA;99;0
"Building";"Refinery";NA;100;0
"Unit";"Marine";"Barracks";109;1
"Unit";"Marine";"Barracks";109;1
"Unit";"Marine";"Barracks";109;1
"Unit";"Marine";"Barracks";121;1
"Unit";"Marine";"Barracks";121;1
"Unit";"Marine";"Barracks";121;1
"Unit";"Marine";"Barracks";121;1
"Unit";"Marine";"Barracks";121;1
"Unit";"Marine";"Barracks";121;1
"Unit";"Marine";"Barracks";121;1
"Building";"FactoryTechLab";NA;123;0
"Unit";"Marine";"Barracks";125;1
"Unit";"Marine";"Barracks";125;1
"Building";"EngineeringBay";NA;125;0
"Unit";"Marine";"Barracks";135;1
"Unit";"Marine";"Barracks";135;1
"Unit";"Marine";"Barracks";135;1
"Unit";"Marine";"Barracks";137;1
"Unit";"Marine";"Barracks";137;1
"Building";"Armory";NA;125;0
"Unit";"Marine";"Barracks";140;1
"Unit";"Marine";"Barracks";140;1
"Unit";"Marauder";"Barracks";140;2
"Unit";"Marine";"Barracks";145;1
"Unit";"Marine";"Barracks";145;1
"Unit";"Marine";"Barracks";145;1
"Unit";"Medivac";"Starport";145;2
"Unit";"Medivac";"Starport";145;2
"Unit";"Marine";"Barracks";149;1
"Unit";"Marine";"Barracks";149;1
"Unit";"Marine";"Barracks";149;1
"Unit";"Marine";"Barracks";149;1
"Unit";"Marauder";"Barracks";149;2
"Upgrade";"TerranInfantryArmorsLevel1";"EngineeringBay";132;0
"Unit";"Medivac";"Starport";159;2
"Unit";"Medivac";"Starport";159;2
"Building";"CommandCenter";NA;140;0
"Unit";"Marine";"Barracks";162;1
"Unit";"Marine";"Barracks";162;1
"Unit";"Marine";"Barracks";162;1
"Unit";"Marauder";"Barracks";162;2
"Unit";"Marine";"Barracks";162;1
"Unit";"Marine";"Barracks";162;1
"Unit";"Marine";"Barracks";162;1
"Unit";"Marine";"Barracks";162;1
"Building";"Starport";NA;162;0
"Building";"Starport";NA;162;0
"Building";"Starport";NA;162;0
"Unit";"Medivac";"Starport";162;2
"Unit";"Medivac";"Starport";164;2
"Unit";"Marine";"Barracks";175;1
"Building";"Refinery";NA;174;0
"Unit";"Marine";"Barracks";175;1
"Unit";"Marine";"Barracks";175;1
"Building";"Refinery";NA;175;0
"Unit";"Marauder";"Barracks";175;2
"Unit";"Marine";"Barracks";175;1
"Unit";"Marine";"Barracks";175;1
"Unit";"Marine";"Barracks";175;1
"Unit";"Marine";"Barracks";175;1
"Unit";"Marine";"Barracks";188;1
"Unit";"Marauder";"Barracks";188;2
"Building";"StarportReactor";NA;186;0
"Building";"StarportReactor";NA;186;0
"Building";"StarportReactor";NA;186;0
"Upgrade";"TerranInfantryWeaponsLevel2";"EngineeringBay";162;0
"Unit";"Marauder";"Barracks";192;2
"Upgrade";"TerranVehicleWeaponsLevel1";"Armory";180;0
"Unit";"Marine";"Barracks";198;1
"Unit";"Marine";"Barracks";198;1
"Unit";"Marine";"Barracks";198;1
"Unit";"Marine";"Barracks";198;1
"Unit";"Marine";"Barracks";198;1
"Unit";"Marine";"Barracks";198;1
"Unit";"Marauder";"Barracks";198;2
"Upgrade";"TerranInfantryArmorsLevel2";"EngineeringBay";188;0
"Building";"CommandCenter";NA;194;0
