"type";"unit_name";"on_building";"total_supply";"supply"
"Building";"Refinery";NA;15;0
"Building";"Refinery";NA;15;0
"Building";"Barracks";NA;14;0
"Building";"Factory";NA;18;0
"Building";"BarracksReactor";NA;18;0
"Unit";"Cyclone";"Factory";19;3
"Unit";"Cyclone";"Factory";19;3
"Unit";"Cyclone";"Factory";26;3
"Unit";"Cyclone";"Factory";26;3
