"type";"unit_name";"on_building";"total_supply";"supply"
"Building";"Refinery";NA;14;0
"Building";"Refinery";NA;17;0
"Building";"Barracks";NA;15;0
"Unit";"Reaper";"Barracks";19;1
"Building";"Factory";NA;19;0
"Building";"FactoryTechLab";NA;20;0
"Unit";"Reaper";"Barracks";19;1
"Unit";"Marine";"Barracks";22;1
"Building";"Armory";NA;21;0
"Unit";"Cyclone";"Factory";23;3
"Unit";"Thor";"Factory";26;6
"Unit";"Marine";"Barracks";30;1
"Unit";"Thor";"Factory";30;6
