"Type";"UnitName";"OnBuilding";"TotalSupply";"Supply"
"Unit";"SCV";"Command Center";12;1
"Unit";"SCV";"Command Center";12;1
"Unit";"SCV";"Command Center";13;1
"Building";"SupplyDepot";NA;13;0
"Unit";"SCV";"Command Center";15;1
"Unit";"SCV";"Command Center";15;1
"Building";"Refinery";NA;15;0
"Unit";"SCV";"Command Center";16;1
"Unit";"SCV";"Command Center";17;1
"Building";"Barracks";NA;15;0
"Unit";"Reaper";"Barracks";19;1
"Unit";"SCV";"Command Center";19;1
"Unit";"SCV";"Command Center";20;1
"Building";"SupplyDepot";NA;19;0
"Unit";"SCV";"Command Center";21;1
"Unit";"SCV";"Command Center";22;1
"Building";"BarracksReactor";NA;21;0
"Building";"CommandCenter";NA;19;0
"Unit";"SCV";"Command Center";23;1
"Unit";"Marine";"Barracks";24;1
"Unit";"Marine";"Barracks";24;1
"Unit";"SCV";"Command Center";25;1
"Building";"Bunker";NA;24;0
"Building";"Refinery";NA;24;0
"Unit";"SCV";"Command Center";28;1
"Unit";"SCV";"Command Center";28;1
"Unit";"Marine";"Barracks";28;1
"Unit";"Marine";"Barracks";28;1
"Building";"Factory";NA;24;0
"Unit";"SCV";"Command Center";29;1
"Building";"CommandCenter";NA;22;0
"Unit";"SCV";"Command Center";29;1
"Unit";"SCV";"Command Center";32;1
"Building";"FactoryTechLab";NA;32;0
"Unit";"SCV";"Command Center";34;1
"Building";"EngineeringBay";NA;30;0
"Building";"EngineeringBay";NA;32;0
"Building";"BarracksTechLab";NA;33;0
"Unit";"SCV";"Command Center";35;1
"Unit";"SCV";"Command Center";36;1
"Unit";"SCV";"Command Center";37;1
"Unit";"SCV";"Command Center";37;1
"Unit";"SCV";"Command Center";38;1
"Unit";"SCV";"Command Center";38;1
"Unit";"SCV";"Command Center";39;1
"Unit";"SCV";"Command Center";40;1
"Building";"Barracks";NA;36;0
"Unit";"SCV";"Command Center";43;1
"Unit";"SCV";"Command Center";43;1
"Unit";"Marine";"Barracks";41;1
"Unit";"SCV";"Command Center";44;1
"Unit";"SCV";"Command Center";44;1
"Unit";"SCV";"Command Center";47;1
"Building";"Refinery";NA;44;0
"Unit";"SCV";"Command Center";47;1
"Building";"Refinery";NA;44;0
"Unit";"SCV";"Command Center";48;1
"Unit";"Marine";"Barracks";48;1
"Unit";"Marine";"Barracks";48;1
"Unit";"Marine";"Barracks";48;1
"Unit";"SCV";"Command Center";51;1
"Unit";"SCV";"Command Center";51;1
"Building";"Barracks";NA;43;0
"Unit";"SCV";"Command Center";51;1
"Building";"Barracks";NA;43;0
"Building";"SupplyDepot";NA;51;0
"Building";"Starport";NA;47;0
"Unit";"Marine";"Barracks";55;1
"Unit";"SCV";"Command Center";58;1
"Unit";"SCV";"Command Center";58;1
"Unit";"SCV";"Command Center";58;1
"Unit";"Marine";"Barracks";57;1
"Unit";"Marine";"Barracks";57;1
"Building";"Armory";NA;49;0
"Unit";"Marine";"Barracks";59;1
"Building";"SupplyDepot";NA;59;0
"Unit";"Marine";"Barracks";62;1
"Building";"SupplyDepot";NA;59;0
"Upgrade";"TerranInfantryWeaponsLevel1";"EngineeringBay";43;0
"Building";"BarracksReactor";NA;58;0
"Upgrade";"TerranInfantryArmorsLevel1";"EngineeringBay";43;0
"Building";"BarracksReactor";NA;58;0
"Building";"StarportReactor";NA;58;0
"Unit";"Marine";"Barracks";65;1
"Unit";"Marine";"Barracks";65;1
"Upgrade";"Stimpack";"TechLab";48;0
"Unit";"Marine";"Barracks";66;1
"Unit";"Marine";"Barracks";66;1
"Unit";"Marine";"Barracks";66;1
"Unit";"Marine";"Barracks";66;1
"Unit";"Marine";"Barracks";66;1
"Unit";"Marine";"Barracks";68;1
"Unit";"Marine";"Barracks";68;1
"Unit";"Medivac";"Starport";66;2
"Unit";"Medivac";"Starport";66;2
"Unit";"Marine";"Barracks";68;1
"Unit";"Marine";"Barracks";69;1
"Building";"MissileTurret";NA;71;0
"Building";"MissileTurret";NA;73;0
"Building";"MissileTurret";NA;73;0
"Building";"Barracks";NA;66;0
"Building";"Barracks";NA;68;0
"Unit";"Marine";"Barracks";80;1
"Building";"Barracks";NA;68;0
"Unit";"Marine";"Barracks";81;1
"Unit";"Marine";"Barracks";81;1
"Unit";"Marine";"Barracks";81;1
"Unit";"SCV";"Command Center";85;1
"Unit";"SCV";"Command Center";85;1
"Unit";"SCV";"Command Center";85;1
"Unit";"Marine";"Barracks";85;1
"Unit";"Marine";"Barracks";85;1
"Unit";"SCV";"Command Center";85;1
"Unit";"SCV";"Command Center";85;1
"Unit";"SCV";"Command Center";85;1
"Building";"BarracksReactor";NA;82;0
"Building";"Refinery";NA;85;0
"Building";"BarracksReactor";NA;82;0
"Building";"BarracksReactor";NA;82;0
"Building";"Refinery";NA;85;0
"Unit";"Marine";"Barracks";90;1
"Unit";"Marine";"Barracks";90;1
"Unit";"Marine";"Barracks";90;1
"Building";"MissileTurret";NA;93;0
"Unit";"Medivac";"Starport";90;2
"Building";"SupplyDepot";NA;93;0
"Building";"SupplyDepot";NA;93;0
"Unit";"SCV";"Command Center";98;1
"Building";"SensorTower";NA;98;0
"Unit";"Marine";"Barracks";98;1
"Unit";"Marine";"Barracks";98;1
"Unit";"Marine";"Barracks";98;1
"Building";"Factory";NA;96;0
"Unit";"Marine";"Barracks";102;1
"Unit";"Marine";"Barracks";102;1
"Unit";"Marine";"Barracks";102;1
"Unit";"Marine";"Barracks";102;1
"Unit";"Marine";"Barracks";102;1
"Unit";"Marine";"Barracks";102;1
"Unit";"Marine";"Barracks";102;1
"Unit";"Marine";"Barracks";102;1
"Unit";"Marine";"Barracks";102;1
"Unit";"Marine";"Barracks";102;1
"Unit";"Marine";"Barracks";102;1
"Building";"FactoryTechLab";NA;111;0
"Unit";"Marine";"Barracks";111;1
"Unit";"Marine";"Barracks";113;1
"Unit";"Marine";"Barracks";113;1
"Unit";"Marine";"Barracks";113;1
"Unit";"Marine";"Barracks";113;1
"Unit";"Marine";"Barracks";113;1
"Unit";"Marine";"Barracks";113;1
"Unit";"Marine";"Barracks";113;1
"Unit";"Marine";"Barracks";113;1
"Unit";"Marine";"Barracks";113;1
"Unit";"Marine";"Barracks";113;1
"Unit";"Marine";"Barracks";113;1
"Unit";"Marine";"Barracks";113;1
"Unit";"Marine";"Barracks";113;1
"Upgrade";"TerranInfantryWeaponsLevel2";"EngineeringBay";93;0
"Building";"SupplyDepot";NA;113;0
"Building";"SupplyDepot";NA;113;0
"Building";"SupplyDepot";NA;113;0
"Building";"SupplyDepot";NA;114;0
"Upgrade";"TerranVehicleWeaponsLevel1";"Armory";98;0
"Upgrade";"TerranInfantryArmorsLevel2";"EngineeringBay";96;0
"Unit";"Marine";"Barracks";121;1
"Building";"CommandCenter";NA;113;0
"Unit";"Marine";"Barracks";128;1
"Unit";"Marine";"Barracks";128;1
"Unit";"Marine";"Barracks";128;1
"Unit";"Marine";"Barracks";128;1
"Unit";"Marine";"Barracks";128;1
"Unit";"Marine";"Barracks";128;1
"Unit";"Marine";"Barracks";128;1
"Unit";"Marine";"Barracks";128;1
"Unit";"Marine";"Barracks";128;1
"Unit";"Marine";"Barracks";128;1
"Unit";"Marine";"Barracks";128;1
"Unit";"Marine";"Barracks";128;1
"Unit";"Marine";"Barracks";128;1
"Building";"SensorTower";NA;128;0
"Unit";"Marine";"Barracks";128;1
"Unit";"Marine";"Barracks";141;1
"Unit";"Marine";"Barracks";141;1
"Unit";"Marine";"Barracks";141;1
"Unit";"SCV";"Command Center";142;1
"Unit";"SCV";"Command Center";142;1
"Unit";"SCV";"Command Center";142;1
"Unit";"SCV";"Command Center";142;1
"Building";"SensorTower";NA;141;0
"Unit";"SCV";"Command Center";145;1
"Unit";"SCV";"Command Center";146;1
"Unit";"SCV";"Command Center";147;1
"Unit";"Medivac";"Starport";141;2
"Unit";"Medivac";"Starport";141;2
"Unit";"SCV";"Command Center";149;1
"Unit";"SCV";"Command Center";156;1
"Unit";"SCV";"Command Center";156;1
"Unit";"Marine";"Barracks";149;1
"Unit";"Marine";"Barracks";149;1
"Unit";"Marine";"Barracks";149;1
"Unit";"Marine";"Barracks";149;1
"Unit";"Marine";"Barracks";149;1
"Unit";"Marine";"Barracks";149;1
"Unit";"Marine";"Barracks";149;1
"Unit";"Marine";"Barracks";149;1
"Unit";"Marine";"Barracks";149;1
"Unit";"Marine";"Barracks";149;1
"Unit";"Marine";"Barracks";149;1
"Unit";"SCV";"Command Center";156;1
"Unit";"Marine";"Barracks";149;1
"Unit";"Marine";"Barracks";149;1
"Unit";"SCV";"Command Center";156;1
"Unit";"SCV";"Command Center";159;1
"Unit";"SCV";"Command Center";160;1
"Unit";"SCV";"Command Center";170;1
"Unit";"Medivac";"Starport";152;2
"Unit";"Medivac";"Starport";154;2
"Building";"SupplyDepot";NA;157;0
"Building";"SupplyDepot";NA;173;0
"Building";"SupplyDepot";NA;173;0
"Unit";"Marine";"Barracks";181;1
"Unit";"SCV";"Command Center";181;1
"Unit";"SCV";"Command Center";181;1
"Unit";"SCV";"Command Center";181;1
"Unit";"SCV";"Command Center";181;1
"Unit";"SCV";"Command Center";182;1
"Unit";"SCV";"Command Center";183;1
"Unit";"SCV";"Command Center";184;1
"Unit";"SCV";"Command Center";185;1
"Building";"SupplyDepot";NA;186;0
"Unit";"Marine";"Barracks";190;1
"Unit";"Marine";"Barracks";190;1
"Unit";"SCV";"Command Center";190;1
"Unit";"SCV";"Command Center";190;1
"Unit";"SCV";"Command Center";190;1
"Unit";"SCV";"Command Center";190;1
"Upgrade";"TerranInfantryWeaponsLevel3";"EngineeringBay";145;0
"Upgrade";"TerranInfantryArmorsLevel3";"EngineeringBay";145;0
"Unit";"Marine";"Barracks";190;1
"Unit";"Marine";"Barracks";190;1
"Unit";"Marine";"Barracks";190;1
"Unit";"Marine";"Barracks";190;1
"Unit";"Marine";"Barracks";190;1
"Unit";"Marine";"Barracks";190;1
"Unit";"Marine";"Barracks";190;1
"Unit";"Marine";"Barracks";190;1
"Unit";"Marine";"Barracks";190;1
"Unit";"Marine";"Barracks";190;1
"Unit";"Marine";"Barracks";190;1
"Upgrade";"TerranVehicleWeaponsLevel2";"Armory";181;0
"Unit";"Marine";"Barracks";207;1
"Unit";"Marine";"Barracks";207;1
"Unit";"Marine";"Barracks";207;1
"Unit";"Marine";"Barracks";207;1
"Unit";"Marine";"Barracks";207;1
"Unit";"Marine";"Barracks";207;1
"Unit";"Marine";"Barracks";207;1
"Unit";"Marine";"Barracks";207;1
"Unit";"Marine";"Barracks";207;1
"Unit";"Marine";"Barracks";207;1
"Unit";"Marine";"Barracks";207;1
"Unit";"Marine";"Barracks";207;1
"Unit";"Marine";"Barracks";207;1
"Building";"Barracks";NA;207;0
"Building";"Barracks";NA;207;0
"Building";"Barracks";NA;207;0
"Unit";"Marine";"Barracks";207;1
"Unit";"Marine";"Barracks";208;1
"Unit";"Marine";"Barracks";209;1
"Unit";"Marine";"Barracks";209;1
"Unit";"Marine";"Barracks";211;1
"Unit";"Marine";"Barracks";211;1
"Unit";"Marine";"Barracks";213;1
"Unit";"Marine";"Barracks";213;1
"Unit";"Marine";"Barracks";215;1
"Unit";"Marine";"Barracks";215;1
"Unit";"Marine";"Barracks";217;1
"Unit";"Marine";"Barracks";217;1
"Unit";"Marine";"Barracks";219;1
"Building";"CommandCenter";NA;207;0
"Unit";"Marine";"Barracks";220;1
"Unit";"Marine";"Barracks";221;1
"Building";"CommandCenter";NA;207;0
"Building";"BarracksReactor";NA;220;0
"Building";"BarracksReactor";NA;220;0
"Building";"BarracksReactor";NA;220;0
"Building";"CommandCenter";NA;207;0
"Unit";"Marine";"Barracks";235;1
"Unit";"Marine";"Barracks";235;1
"Unit";"Marine";"Barracks";235;1
"Unit";"Marine";"Barracks";235;1
"Unit";"Marine";"Barracks";235;1
"Unit";"Marine";"Barracks";235;1
"Unit";"Marine";"Barracks";235;1
"Unit";"Marine";"Barracks";235;1
"Unit";"Marine";"Barracks";235;1
"Building";"Refinery";NA;235;0
"Building";"SupplyDepot";NA;235;0
"Building";"Starport";NA;235;0
"Building";"Starport";NA;235;0
"Unit";"Medivac";"Starport";244;2
"Building";"Armory";NA;244;0
"Building";"StarportTechLab";NA;246;0
"Building";"MissileTurret";NA;246;0
"Building";"StarportReactor";NA;246;0
"Building";"Refinery";NA;246;0
"Building";"Refinery";NA;246;0
"Building";"SensorTower";NA;246;0
"Building";"FusionCore";NA;246;0
"Unit";"Marine";"Barracks";246;1
"Unit";"Marine";"Barracks";246;1
"Unit";"Marine";"Barracks";246;1
"Unit";"Marine";"Barracks";246;1
"Unit";"Marine";"Barracks";246;1
"Unit";"Marine";"Barracks";246;1
"Unit";"Marine";"Barracks";246;1
"Unit";"Marine";"Barracks";246;1
"Unit";"Marine";"Barracks";246;1
"Unit";"Marine";"Barracks";246;1
"Unit";"Marine";"Barracks";246;1
"Unit";"Marine";"Barracks";246;1
"Unit";"Marine";"Barracks";246;1
"Unit";"Marine";"Barracks";246;1
"Unit";"Marine";"Barracks";246;1
"Unit";"Marine";"Barracks";246;1
"Building";"Refinery";NA;246;0
"Building";"Refinery";NA;246;0
