"type";"unit_name";"on_building";"total_supply";"supply"
"Building";"Refinery";NA;14;0
"Building";"Refinery";NA;16;0
"Building";"Barracks";NA;15;0
"Building";"BarracksReactor";NA;19;0
"Building";"Factory";NA;19;0
"Unit";"Marine";"Barracks";21;1
"Unit";"Cyclone";"Factory";21;3
"Unit";"Cyclone";"Factory";21;3
"Unit";"Cyclone";"Factory";31;3
"Unit";"Cyclone";"Factory";32;3
"Building";"BarracksTechLab";NA;35;0
"Building";"CommandCenter";NA;30;0
"Building";"Starport";NA;32;0
"Building";"BarracksReactor";NA;40;0
"Building";"EngineeringBay";NA;41;0
"Building";"FactoryTechLab";NA;42;0
"Unit";"Marine";"Barracks";43;1
"Unit";"Marine";"Barracks";43;1
"Unit";"Banshee";"Starport";41;3
"Unit";"Marine";"Barracks";46;1
"Unit";"Marine";"Barracks";46;1
"Building";"BarracksTechLab";NA;55;0
"Unit";"Liberator";"Starport";48;3
"Building";"Bunker";NA;55;0
"Unit";"Marine";"Barracks";62;1
"Unit";"Marine";"Barracks";63;1
"Building";"Refinery";NA;64;0
"Building";"Refinery";NA;64;0
"Building";"CommandCenter";NA;57;0
"Unit";"Marine";"Barracks";67;1
"Building";"StarportReactor";NA;64;0
"Building";"Barracks";NA;64;0
"Building";"Barracks";NA;64;0
"Building";"Barracks";NA;64;0
"Building";"Barracks";NA;64;0
"Unit";"Marine";"Barracks";70;1
"Unit";"Marine";"Barracks";71;1
"Unit";"Marine";"Barracks";73;1
"Unit";"Marine";"Barracks";74;1
"Unit";"Marine";"Barracks";74;1
"Unit";"Marine";"Barracks";74;1
"Unit";"Marine";"Barracks";82;1
"Unit";"Marine";"Barracks";82;1
"Unit";"Marine";"Barracks";82;1
"Unit";"Marine";"Barracks";82;1
"Unit";"Marine";"Barracks";82;1
"Unit";"Medivac";"Starport";82;2
"Unit";"Marine";"Barracks";82;1
"Building";"BarracksReactor";NA;76;0
"Unit";"Marine";"Barracks";83;1
"Upgrade";"Stimpack";"TechLab";70;0
"Unit";"Marine";"Barracks";91;1
"Unit";"Marine";"Barracks";91;1
"Unit";"Marine";"Barracks";91;1
"Unit";"Marine";"Barracks";91;1
"Unit";"Marine";"Barracks";91;1
"Unit";"Marine";"Barracks";92;1
"Unit";"Marine";"Barracks";92;1
"Unit";"Marine";"Barracks";92;1
"Unit";"Medivac";"Starport";91;2
"Unit";"Marine";"Barracks";92;1
"Unit";"Marine";"Barracks";93;1
"Unit";"Marine";"Barracks";94;1
"Unit";"Medivac";"Starport";92;2
"Building";"CommandCenter";NA;82;0
"Unit";"Marine";"Barracks";108;1
"Unit";"Marine";"Barracks";108;1
"Unit";"Marine";"Barracks";108;1
"Unit";"Marine";"Barracks";108;1
"Unit";"Marine";"Barracks";108;1
"Unit";"Marine";"Barracks";111;1
"Unit";"Marine";"Barracks";111;1
"Unit";"Marine";"Barracks";111;1
"Unit";"Marine";"Barracks";111;1
"Unit";"Medivac";"Starport";111;2
"Unit";"Marine";"Barracks";116;1
"Unit";"Marine";"Barracks";116;1
"Unit";"Marine";"Barracks";117;1
"Unit";"Marine";"Barracks";117;1
"Unit";"Marine";"Barracks";132;1
"Unit";"Marine";"Barracks";132;1
"Building";"EngineeringBay";NA;132;0
"Unit";"Marine";"Barracks";132;1
"Unit";"Marine";"Barracks";132;1
"Unit";"Marine";"Barracks";134;1
"Unit";"Marine";"Barracks";134;1
"Unit";"Marine";"Barracks";134;1
"Unit";"Marine";"Barracks";134;1
"Unit";"Marine";"Barracks";134;1
"Building";"Armory";NA;132;0
"Unit";"Marine";"Barracks";137;1
"Unit";"Marine";"Barracks";137;1
"Unit";"Marine";"Barracks";137;1
"Unit";"Marine";"Barracks";137;1
"Unit";"Marine";"Barracks";137;1
"Unit";"Marine";"Barracks";140;1
"Unit";"Marine";"Barracks";140;1
"Building";"Refinery";NA;140;0
"Building";"Refinery";NA;140;0
"Unit";"Marine";"Barracks";141;1
"Unit";"Marine";"Barracks";141;1
"Unit";"Marine";"Barracks";142;1
"Unit";"Marine";"Barracks";143;1
"Unit";"Marine";"Barracks";150;1
"Unit";"Marine";"Barracks";150;1
"Unit";"Marine";"Barracks";150;1
"Building";"Factory";NA;140;0
"Unit";"Marine";"Barracks";153;1
"Unit";"Marine";"Barracks";153;1
"Building";"Barracks";NA;140;0
"Building";"Barracks";NA;140;0
"Unit";"Marine";"Barracks";153;1
"Unit";"Marine";"Barracks";157;1
"Unit";"Marine";"Barracks";157;1
"Unit";"Marine";"Barracks";157;1
"Unit";"Marine";"Barracks";158;1
"Unit";"Marine";"Barracks";159;1
"Unit";"Marine";"Barracks";160;1
"Unit";"Marine";"Barracks";161;1
"Unit";"Marine";"Barracks";162;1
"Unit";"Marine";"Barracks";163;1
"Unit";"Marine";"Barracks";164;1
"Upgrade";"TerranInfantryWeaponsLevel1";"EngineeringBay";135;0
"Unit";"Marine";"Barracks";165;1
"Unit";"Marine";"Barracks";166;1
"Unit";"Marine";"Barracks";167;1
"Unit";"Marine";"Barracks";168;1
"Unit";"Marine";"Barracks";168;1
"Building";"MissileTurret";NA;168;0
"Unit";"Marine";"Barracks";168;1
"Unit";"Marine";"Barracks";169;1
"Unit";"Marine";"Barracks";170;1
"Unit";"Marine";"Barracks";171;1
"Unit";"Marine";"Barracks";172;1
"Unit";"Marine";"Barracks";173;1
"Unit";"Marine";"Barracks";174;1
"Unit";"Marine";"Barracks";175;1
"Unit";"Marine";"Barracks";176;1
"Unit";"Marine";"Barracks";177;1
"Unit";"Marine";"Barracks";178;1
"Unit";"Marine";"Barracks";179;1
"Building";"MissileTurret";NA;168;0
"Building";"MissileTurret";NA;168;0
"Unit";"Marine";"Barracks";180;1
"Unit";"Marine";"Barracks";181;1
"Unit";"Marine";"Barracks";182;1
"Unit";"Marine";"Barracks";183;1
"Unit";"Marine";"Barracks";184;1
"Unit";"Marine";"Barracks";185;1
"Unit";"Marine";"Barracks";186;1
"Unit";"Marine";"Barracks";187;1
"Unit";"Marine";"Barracks";188;1
"Unit";"Marine";"Barracks";192;1
"Unit";"Marine";"Barracks";193;1
"Unit";"Marine";"Barracks";193;1
"Unit";"Marine";"Barracks";193;1
"Unit";"Marine";"Barracks";197;1
"Unit";"Marine";"Barracks";202;1
"Unit";"Marine";"Barracks";202;1
"Unit";"Marine";"Barracks";202;1
"Unit";"Marine";"Barracks";202;1
"Unit";"Marine";"Barracks";202;1
"Unit";"Marine";"Barracks";204;1
"Unit";"Marine";"Barracks";205;1
"Unit";"Marine";"Barracks";209;1
"Unit";"Marine";"Barracks";209;1
"Upgrade";"TerranInfantryArmorsLevel1";"EngineeringBay";173;0
"Unit";"Marine";"Barracks";220;1
"Unit";"Marine";"Barracks";220;1
"Unit";"Marine";"Barracks";220;1
"Unit";"Marine";"Barracks";220;1
"Unit";"Medivac";"Starport";214;2
"Unit";"Medivac";"Starport";214;2
"Unit";"Marine";"Barracks";220;1
"Unit";"Marine";"Barracks";220;1
"Unit";"Marine";"Barracks";221;1
"Unit";"Marine";"Barracks";221;1
"Building";"FactoryTechLab";NA;221;0
"Building";"BarracksReactor";NA;220;0
"Building";"BarracksReactor";NA;220;0
"Unit";"Marine";"Barracks";221;1
"Unit";"Marine";"Barracks";222;1
"Unit";"Marine";"Barracks";233;1
"Unit";"Marine";"Barracks";233;1
"Unit";"Marine";"Barracks";233;1
"Unit";"Marine";"Barracks";233;1
"Unit";"Marine";"Barracks";235;1
"Unit";"Marine";"Barracks";235;1
"Unit";"Marine";"Barracks";235;1
"Unit";"Marine";"Barracks";235;1
"Unit";"Marine";"Barracks";235;1
"Unit";"Marine";"Barracks";235;1
"Unit";"Marine";"Barracks";242;1
"Unit";"Marine";"Barracks";242;1
"Unit";"Marine";"Barracks";242;1
"Unit";"Marine";"Barracks";242;1
"Unit";"Marine";"Barracks";242;1
"Unit";"Marine";"Barracks";242;1
"Building";"MissileTurret";NA;245;0
"Building";"MissileTurret";NA;245;0
"Building";"MissileTurret";NA;245;0
"Unit";"Marine";"Barracks";245;1
"Unit";"Marine";"Barracks";245;1
"Building";"MissileTurret";NA;245;0
"Building";"MissileTurret";NA;245;0
"Building";"Starport";NA;239;0
"Unit";"Marine";"Barracks";246;1
"Unit";"Marine";"Barracks";247;1
"Unit";"Marine";"Barracks";248;1
"Unit";"Marine";"Barracks";251;1
"Unit";"Marine";"Barracks";251;1
"Unit";"Marine";"Barracks";251;1
"Unit";"Marine";"Barracks";251;1
"Unit";"Marine";"Barracks";251;1
"Unit";"Marine";"Barracks";251;1
"Unit";"Marine";"Barracks";252;1
"Unit";"Marine";"Barracks";253;1
"Unit";"Marine";"Barracks";254;1
"Unit";"Marine";"Barracks";254;1
"Unit";"Marine";"Barracks";255;1
"Unit";"Marine";"Barracks";256;1
"Unit";"Marine";"Barracks";257;1
"Unit";"Marine";"Barracks";258;1
"Upgrade";"TerranInfantryWeaponsLevel2";"EngineeringBay";231;0
"Unit";"Marine";"Barracks";266;1
"Unit";"Marine";"Barracks";269;1
"Unit";"Marine";"Barracks";269;1
"Unit";"Marine";"Barracks";269;1
"Unit";"Marine";"Barracks";269;1
"Unit";"Marine";"Barracks";269;1
"Unit";"Marine";"Barracks";271;1
"Unit";"Marine";"Barracks";271;1
"Unit";"Marine";"Barracks";271;1
"Unit";"Marine";"Barracks";271;1
"Unit";"Marine";"Barracks";271;1
"Unit";"Marine";"Barracks";271;1
"Unit";"Marine";"Barracks";271;1
"Unit";"Marine";"Barracks";272;1
"Unit";"Marine";"Barracks";274;1
"Unit";"Medivac";"Starport";271;2
"Unit";"Marine";"Barracks";275;1
"Unit";"Marine";"Barracks";276;1
"Unit";"Marine";"Barracks";280;1
"Unit";"Marine";"Barracks";280;1
"Unit";"Marine";"Barracks";280;1
"Building";"Refinery";NA;294;0
"Building";"Refinery";NA;294;0
"Unit";"Marine";"Barracks";294;1
"Unit";"Marine";"Barracks";294;1
"Unit";"Marine";"Barracks";294;1
"Unit";"Marine";"Barracks";295;1
"Unit";"Marine";"Barracks";301;1
"Unit";"Marine";"Barracks";301;1
"Unit";"Marine";"Barracks";301;1
"Unit";"Marine";"Barracks";301;1
"Building";"BarracksReactor";NA;294;0
"Unit";"Thor";"Factory";294;6
"Unit";"Thor";"Factory";294;6
"Unit";"Marine";"Barracks";309;1
"Unit";"Marine";"Barracks";309;1
"Unit";"Marine";"Barracks";309;1
"Unit";"Marine";"Barracks";313;1
"Unit";"Marine";"Barracks";313;1
"Unit";"Marine";"Barracks";313;1
"Unit";"Marine";"Barracks";313;1
"Unit";"Marine";"Barracks";313;1
"Unit";"Marine";"Barracks";313;1
"Unit";"Marine";"Barracks";313;1
"Unit";"Marine";"Barracks";313;1
"Unit";"Marine";"Barracks";313;1
"Unit";"Marine";"Barracks";325;1
"Unit";"Marine";"Barracks";326;1
"Unit";"Marine";"Barracks";328;1
"Unit";"Marine";"Barracks";328;1
"Unit";"Marine";"Barracks";331;1
"Unit";"Marine";"Barracks";337;1
"Unit";"Marine";"Barracks";337;1
"Unit";"Marine";"Barracks";337;1
"Unit";"Marine";"Barracks";337;1
"Unit";"Marine";"Barracks";337;1
"Unit";"Marine";"Barracks";337;1
"Unit";"Marine";"Barracks";337;1
"Unit";"Marine";"Barracks";349;1
"Unit";"Marine";"Barracks";349;1
"Unit";"Marine";"Barracks";349;1
"Unit";"Marine";"Barracks";349;1
"Unit";"Marine";"Barracks";349;1
"Unit";"Marine";"Barracks";349;1
"Unit";"Thor";"Factory";349;6
"Upgrade";"TerranShipWeaponsLevel1";"Armory";331;0
"Unit";"Marine";"Barracks";355;1
"Unit";"Marine";"Barracks";355;1
"Building";"CommandCenter";NA;343;0
"Unit";"Marine";"Barracks";361;1
"Unit";"Marine";"Barracks";361;1
"Unit";"Marine";"Barracks";361;1
"Unit";"Marine";"Barracks";361;1
"Unit";"Marine";"Barracks";361;1
"Unit";"Marine";"Barracks";361;1
"Unit";"Marine";"Barracks";361;1
"Unit";"Marine";"Barracks";361;1
"Unit";"Marine";"Barracks";361;1
"Unit";"Marine";"Barracks";361;1
"Upgrade";"TerranInfantryArmorsLevel2";"EngineeringBay";339;0
"Unit";"Marine";"Barracks";363;1
"Unit";"Marine";"Barracks";363;1
