"type";"unit_name";"on_building";"total_supply";"supply"
"Building";"Refinery";NA;13;0
"Building";"Barracks";NA;15;0
"Building";"BarracksTechLab";NA;18;0
"Building";"Barracks";NA;17;0
"Unit";"Marauder";"Barracks";19;2
"Building";"BarracksTechLab";NA;19;0
"Unit";"Marauder";"Barracks";21;2
"Unit";"Marauder";"Barracks";22;2
"Unit";"Marauder";"Barracks";25;2
"Unit";"Marauder";"Barracks";30;2
"Unit";"Marauder";"Barracks";30;2
"Unit";"Marauder";"Barracks";31;2
"Unit";"Marauder";"Barracks";33;2
