"type";"unit_name";"on_building";"total_supply";"supply"
"Building";"Refinery";NA;14;0
"Building";"Refinery";NA;16;0
"Building";"Barracks";NA;15;0
"Unit";"Reaper";"Barracks";18;1
"Building";"Factory";NA;19;0
"Unit";"Reaper";"Barracks";20;1
"Unit";"Hellion";"Factory";21;2
"Building";"Starport";NA;21;0
"Building";"BarracksReactor";NA;24;0
"Unit";"Cyclone";"Factory";27;3
"Unit";"Liberator";"Starport";29;3
"Building";"FactoryReactor";NA;33;0
"Unit";"Marine";"Barracks";37;1
"Unit";"Marine";"Barracks";37;1
"Building";"CommandCenter";NA;29;0
"Unit";"Marine";"Barracks";40;1
"Unit";"Marine";"Barracks";40;1
"Unit";"Medivac";"Starport";40;2
"Unit";"Cyclone";"Factory";40;3
"Unit";"Cyclone";"Factory";40;3
"Unit";"Marine";"Barracks";42;1
"Unit";"Marine";"Barracks";42;1
"Building";"CommandCenter";NA;34;0
"Unit";"Marine";"Barracks";54;1
"Unit";"Marine";"Barracks";54;1
"Unit";"Cyclone";"Factory";54;3
"Unit";"Cyclone";"Factory";55;3
"Unit";"Marine";"Barracks";57;1
"Unit";"Marine";"Barracks";57;1
"Unit";"Cyclone";"Factory";67;3
"Unit";"Marine";"Barracks";72;1
"Unit";"Marine";"Barracks";73;1
"Building";"Refinery";NA;76;0
"Building";"Refinery";NA;76;0
"Unit";"Cyclone";"Factory";76;3
"Unit";"Marine";"Barracks";81;1
"Unit";"Marine";"Barracks";81;1
"Unit";"Cyclone";"Factory";81;3
"Building";"Refinery";NA;81;0
"Building";"Refinery";NA;81;0
"Building";"Barracks";NA;76;0
"Building";"Barracks";NA;76;0
"Building";"Barracks";NA;79;0
"Unit";"Marine";"Barracks";92;1
"Unit";"Marine";"Barracks";92;1
"Building";"Barracks";NA;79;0
"Unit";"Cyclone";"Factory";93;3
"Unit";"Cyclone";"Factory";93;3
"Building";"BarracksTechLab";NA;95;0
"Building";"BarracksTechLab";NA;95;0
"Building";"EngineeringBay";NA;97;0
"Building";"EngineeringBay";NA;97;0
"Building";"BarracksReactor";NA;97;0
"Building";"BarracksReactor";NA;97;0
"Unit";"Marine";"Barracks";109;1
"Unit";"Marine";"Barracks";109;1
"Unit";"Marine";"Barracks";109;1
"Unit";"Marine";"Barracks";109;1
"Unit";"Marine";"Barracks";109;1
"Unit";"Medivac";"Starport";109;2
"Unit";"Marine";"Barracks";110;1
"Unit";"Marine";"Barracks";112;1
"Unit";"Marine";"Barracks";112;1
"Unit";"Marine";"Barracks";114;1
"Unit";"Marine";"Barracks";114;1
"Unit";"Marine";"Barracks";114;1
"Unit";"Marine";"Barracks";114;1
"Unit";"Marine";"Barracks";114;1
"Building";"FactoryTechLab";NA;117;0
"Unit";"Marine";"Barracks";124;1
"Unit";"Marine";"Barracks";124;1
"Unit";"Marine";"Barracks";124;1
"Unit";"Marine";"Barracks";124;1
"Unit";"Marine";"Barracks";124;1
"Unit";"Marine";"Barracks";124;1
"Unit";"Marine";"Barracks";124;1
"Building";"Factory";NA;117;0
"Unit";"Marine";"Barracks";128;1
"Unit";"Marine";"Barracks";129;1
"Unit";"Medivac";"Starport";128;2
"Unit";"Marine";"Barracks";138;1
"Building";"Armory";NA;124;0
"Unit";"Marine";"Barracks";138;1
"Unit";"Marine";"Barracks";138;1
"Unit";"Marine";"Barracks";138;1
"Unit";"Marine";"Barracks";138;1
"Unit";"Marine";"Barracks";138;1
"Unit";"Medivac";"Starport";128;2
"Building";"FactoryTechLab";NA;142;0
"Building";"MissileTurret";NA;145;0
"Building";"MissileTurret";NA;145;0
"Building";"MissileTurret";NA;153;0
"Unit";"Marine";"Barracks";153;1
"Building";"MissileTurret";NA;153;0
"Unit";"Marine";"Barracks";153;1
"Unit";"Marine";"Barracks";153;1
"Unit";"Marine";"Barracks";153;1
"Unit";"Marine";"Barracks";153;1
"Unit";"Marine";"Barracks";153;1
"Unit";"Marine";"Barracks";153;1
"Upgrade";"TerranInfantryWeaponsLevel1";"EngineeringBay";118;0
"Upgrade";"TerranInfantryArmorsLevel1";"EngineeringBay";124;0
"Upgrade";"Stimpack";"TechLab";120;0
"Unit";"Marine";"Barracks";160;1
"Unit";"Marine";"Barracks";160;1
"Unit";"Marine";"Barracks";160;1
"Unit";"Marine";"Barracks";160;1
"Unit";"Marine";"Barracks";160;1
"Unit";"Marine";"Barracks";160;1
"Unit";"Marine";"Barracks";160;1
"Unit";"Marine";"Barracks";160;1
"Unit";"Liberator";"Starport";153;3
"Unit";"Marine";"Barracks";160;1
"Unit";"Marine";"Barracks";167;1
"Unit";"Marine";"Barracks";167;1
"Unit";"Marine";"Barracks";167;1
"Unit";"Marine";"Barracks";167;1
"Unit";"Marine";"Barracks";167;1
"Unit";"Marine";"Barracks";168;1
"Unit";"Marine";"Barracks";168;1
"Unit";"Liberator";"Starport";172;3
"Unit";"Liberator";"Starport";172;3
"Unit";"Marine";"Barracks";183;1
"Unit";"Marine";"Barracks";183;1
"Unit";"Marine";"Barracks";183;1
"Unit";"Marine";"Barracks";183;1
"Unit";"Marine";"Barracks";183;1
"Unit";"Marine";"Barracks";183;1
"Unit";"Marine";"Barracks";183;1
"Unit";"Marine";"Barracks";184;1
"Unit";"Marine";"Barracks";190;1
"Unit";"Marine";"Barracks";190;1
"Unit";"Marine";"Barracks";192;1
"Building";"Starport";NA;197;0
"Building";"Starport";NA;198;0
"Unit";"Marine";"Barracks";203;1
"Unit";"Marine";"Barracks";203;1
"Unit";"Marine";"Barracks";203;1
"Unit";"Marine";"Barracks";203;1
"Unit";"Marine";"Barracks";203;1
"Unit";"Marine";"Barracks";203;1
"Unit";"Marine";"Barracks";203;1
"Unit";"Marine";"Barracks";203;1
"Upgrade";"TerranInfantryWeaponsLevel2";"EngineeringBay";182;0
