"type";"unit_name";"on_building";"total_supply";"supply"
"Building";"Refinery";NA;14;0
"Building";"Barracks";NA;16;0
"Building";"Barracks";NA;17;0
"Unit";"Reaper";"Barracks";19;1
"Unit";"Reaper";"Barracks";19;1
"Unit";"Reaper";"Barracks";19;1
"Building";"Refinery";NA;21;0
"Unit";"Reaper";"Barracks";21;1
"Unit";"Reaper";"Barracks";23;1
"Building";"Factory";NA;25;0
"Building";"CommandCenter";NA;23;0
"Building";"Bunker";NA;30;0
"Building";"FactoryReactor";NA;30;0
"Building";"Starport";NA;30;0
"Building";"CommandCenter";NA;30;0
"Building";"StarportTechLab";NA;33;0
"Unit";"Cyclone";"Factory";34;3
"Unit";"Cyclone";"Factory";34;3
"Unit";"Marine";"Barracks";43;1
"Unit";"Marine";"Barracks";43;1
"Unit";"Raven";"Starport";36;2
"Building";"BarracksTechLab";NA;48;0
"Unit";"Cyclone";"Factory";48;3
"Unit";"Cyclone";"Factory";50;3
"Building";"Refinery";NA;51;0
"Building";"Refinery";NA;51;0
"Building";"EngineeringBay";NA;57;0
"Building";"BarracksReactor";NA;51;0
"Building";"StarportReactor";NA;56;0
"Building";"MissileTurret";NA;65;0
"Building";"MissileTurret";NA;65;0
"Unit";"Hellion";"Factory";69;2
"Unit";"Hellion";"Factory";69;2
"Unit";"Hellion";"Factory";71;2
"Unit";"Hellion";"Factory";73;2
"Building";"Factory";NA;69;0
"Building";"Factory";NA;69;0
"Building";"Armory";NA;76;0
"Building";"Armory";NA;76;0
"Building";"Factory";NA;79;0
"Unit";"Hellion";"Factory";87;2
"Unit";"Hellion";"Factory";87;2
"Unit";"Hellion";"Factory";87;2
"Building";"Refinery";NA;88;0
"Building";"Refinery";NA;88;0
"Unit";"Hellion";"Factory";95;2
"Unit";"Hellion";"Factory";95;2
"Unit";"Hellion";"Factory";110;2
"Unit";"Hellion";"Factory";110;2
"Unit";"Hellion";"Factory";117;2
"Unit";"Hellion";"Factory";117;2
"Unit";"Hellion";"Factory";117;2
"Unit";"Hellion";"Factory";117;2
"Unit";"Liberator";"Starport";117;3
"Unit";"Liberator";"Starport";117;3
"Upgrade";"TerranVehicleWeaponsLevel1";"Armory";110;0
"Unit";"Cyclone";"Factory";127;3
"Unit";"Cyclone";"Factory";127;3
"Unit";"Cyclone";"Factory";127;3
"Unit";"Hellion";"Factory";133;2
"Unit";"Hellion";"Factory";133;2
"Unit";"Hellion";"Factory";142;2
"Building";"CommandCenter";NA;127;0
"Unit";"Hellion";"Factory";148;2
"Unit";"Hellion";"Factory";148;2
"Unit";"Hellion";"Factory";148;2
"Unit";"Hellion";"Factory";150;2
"Unit";"Hellion";"Factory";154;2
"Unit";"Hellion";"Factory";154;2
"Unit";"Liberator";"Starport";154;3
"Unit";"Hellion";"Factory";163;2
"Unit";"Hellion";"Factory";163;2
"Unit";"Medivac";"Starport";163;2
"Building";"Refinery";NA;166;0
"Unit";"Hellion";"Factory";166;2
"Unit";"Hellion";"Factory";166;2
"Building";"Refinery";NA;166;0
"Building";"Factory";NA;163;0
"Unit";"Medivac";"Starport";166;2
"Unit";"Hellion";"Factory";167;2
"Unit";"Hellion";"Factory";169;2
"Building";"FactoryTechLab";NA;178;0
"Upgrade";"TerranVehicleWeaponsLevel2";"Armory";154;0
"Unit";"Liberator";"Starport";178;3
"Unit";"Hellion";"Factory";184;2
"Unit";"Hellion";"Factory";184;2
"Unit";"Hellion";"Factory";184;2
"Unit";"Hellion";"Factory";184;2
"Unit";"Liberator";"Starport";178;3
"Unit";"Thor";"Factory";184;6
"Unit";"Thor";"Factory";184;6
"Unit";"Hellion";"Factory";189;2
"Unit";"Hellion";"Factory";191;2
"Unit";"Hellion";"Factory";193;2
"Building";"MissileTurret";NA;200;0
"Building";"MissileTurret";NA;219;0
"Building";"SensorTower";NA;219;0
"Unit";"Hellion";"Factory";219;2
"Building";"CommandCenter";NA;184;0
"Unit";"Hellion";"Factory";220;2
"Unit";"Hellion";"Factory";220;2
"Building";"MissileTurret";NA;222;0
"Building";"Starport";NA;222;0
"Building";"Starport";NA;222;0
"Unit";"Hellion";"Factory";227;2
"Unit";"Hellion";"Factory";227;2
"Unit";"Hellion";"Factory";227;2
"Unit";"Hellion";"Factory";227;2
"Building";"StarportTechLab";NA;236;0
"Unit";"Hellion";"Factory";236;2
"Unit";"Hellion";"Factory";236;2
"Unit";"Hellion";"Factory";236;2
"Building";"StarportReactor";NA;236;0
"Unit";"Hellion";"Factory";236;2
"Unit";"Hellion";"Factory";238;2
"Unit";"Liberator";"Starport";236;3
"Unit";"Liberator";"Starport";236;3
"Unit";"Hellion";"Factory";242;2
"Upgrade";"TerranVehicleWeaponsLevel3";"Armory";220;0
"Unit";"Hellion";"Factory";242;2
"Unit";"Hellion";"Factory";242;2
"Unit";"Hellion";"Factory";246;2
"Unit";"Hellion";"Factory";256;2
"Unit";"Raven";"Starport";242;2
"Unit";"Hellion";"Factory";260;2
"Unit";"Hellion";"Factory";264;2
