"type";"unit_name";"on_building";"total_supply";"supply"
"Building";"Refinery";NA;14;0
"Building";"Refinery";NA;16;0
"Building";"Barracks";NA;15;0
"Unit";"Reaper";"Barracks";19;1
"Building";"Factory";NA;19;0
"Unit";"Reaper";"Barracks";19;1
"Unit";"Cyclone";"Factory";24;3
"Building";"Starport";NA;24;0
"Building";"BarracksReactor";NA;24;0
"Building";"FactoryTechLab";NA;28;0
"Building";"CommandCenter";NA;22;0
"Unit";"Hellion";"Factory";31;2
"Unit";"Hellion";"Factory";31;2
"Unit";"Hellion";"Factory";34;2
"Unit";"Raven";"Starport";31;2
"Unit";"Cyclone";"Factory";37;3
"Building";"BarracksReactor";NA;37;0
"Building";"Factory";NA;38;0
"Unit";"Hellion";"Factory";47;2
"Unit";"Hellion";"Factory";47;2
"Unit";"Hellion";"Factory";53;2
"Unit";"Hellion";"Factory";53;2
"Unit";"Hellion";"Factory";56;2
"Unit";"Hellion";"Factory";56;2
"Unit";"Hellion";"Factory";58;2
"Unit";"Hellion";"Factory";64;2
"Unit";"Hellion";"Factory";64;2
"Unit";"Hellion";"Factory";68;2
"Unit";"Hellion";"Factory";72;2
"Unit";"Hellion";"Factory";76;2
"Building";"Refinery";NA;78;0
"Building";"Refinery";NA;78;0
"Unit";"Hellion";"Factory";84;2
"Unit";"Hellion";"Factory";84;2
"Unit";"Hellion";"Factory";84;2
"Building";"BarracksTechLab";NA;86;0
"Building";"CommandCenter";NA;78;0
"Unit";"Hellion";"Factory";94;2
"Building";"Factory";NA;86;0
"Unit";"Hellion";"Factory";100;2
"Unit";"Hellion";"Factory";100;2
"Building";"Refinery";NA;105;0
"Unit";"Hellion";"Factory";105;2
"Building";"Refinery";NA;105;0
"Unit";"Medivac";"Starport";105;2
"Unit";"Medivac";"Starport";105;2
"Unit";"Hellion";"Factory";106;2
"Unit";"Hellion";"Factory";110;2
"Building";"Armory";NA;106;0
"Building";"EngineeringBay";NA;117;0
"Unit";"Hellion";"Factory";125;2
"Unit";"Hellion";"Factory";125;2
"Building";"MissileTurret";NA;130;0
"Building";"MissileTurret";NA;135;0
"Building";"MissileTurret";NA;135;0
"Building";"Factory";NA;127;0
"Building";"SensorTower";NA;138;0
"Building";"Factory";NA;127;0
"Unit";"Hellion";"Factory";137;2
"Unit";"Hellion";"Factory";137;2
"Building";"MissileTurret";NA;138;0
"Unit";"Medivac";"Starport";140;2
"Unit";"Medivac";"Starport";140;2
"Building";"MissileTurret";NA;147;0
"Building";"FactoryTechLab";NA;147;0
"Building";"Armory";NA;141;0
"Building";"FactoryReactor";NA;147;0
"Unit";"Hellion";"Factory";151;2
"Unit";"Hellion";"Factory";151;2
"Unit";"Hellion";"Factory";151;2
"Building";"MissileTurret";NA;154;0
"Building";"MissileTurret";NA;154;0
"Upgrade";"TerranVehicleWeaponsLevel1";"Armory";140;0
"Building";"MissileTurret";NA;156;0
"Unit";"Medivac";"Starport";154;2
"Unit";"Medivac";"Starport";154;2
"Building";"MissileTurret";NA;162;0
"Building";"MissileTurret";NA;162;0
"Building";"MissileTurret";NA;162;0
"Unit";"Hellion";"Factory";162;2
"Unit";"Hellion";"Factory";162;2
"Unit";"Hellion";"Factory";162;2
"Unit";"Hellion";"Factory";162;2
"Building";"CommandCenter";NA;151;0
"Unit";"Hellion";"Factory";174;2
"Unit";"Hellion";"Factory";174;2
"Unit";"Hellion";"Factory";174;2
"Unit";"Thor";"Factory";174;6
"Unit";"Hellion";"Factory";174;2
"Unit";"Hellion";"Factory";174;2
"Building";"MissileTurret";NA;186;0
"Building";"SensorTower";NA;186;0
"Building";"Refinery";NA;186;0
"Building";"Refinery";NA;186;0
"Building";"Starport";NA;186;0
"Building";"Starport";NA;186;0
"Unit";"Hellion";"Factory";190;2
"Unit";"Hellion";"Factory";190;2
"Unit";"Hellion";"Factory";190;2
"Unit";"Hellion";"Factory";190;2
"Unit";"Thor";"Factory";188;6
"Building";"MissileTurret";NA;194;0
"Building";"MissileTurret";NA;194;0
"Unit";"Hellion";"Factory";198;2
"Unit";"Hellion";"Factory";198;2
"Unit";"Hellion";"Factory";198;2
"Unit";"Hellion";"Factory";210;2
"Unit";"Hellion";"Factory";210;2
"Unit";"Hellion";"Factory";210;2
"Unit";"Hellion";"Factory";210;2
"Unit";"Hellion";"Factory";210;2
"Unit";"Hellion";"Factory";210;2
"Unit";"Hellion";"Factory";212;2
"Upgrade";"TerranVehicleWeaponsLevel2";"Armory";190;0
"Unit";"Hellion";"Factory";222;2
"Unit";"Hellion";"Factory";222;2
"Unit";"Hellion";"Factory";222;2
"Unit";"Hellion";"Factory";228;2
"Unit";"Hellion";"Factory";228;2
"Unit";"Hellion";"Factory";228;2
"Unit";"Hellion";"Factory";230;2
"Unit";"Hellion";"Factory";242;2
"Unit";"Hellion";"Factory";242;2
"Unit";"Hellion";"Factory";242;2
"Unit";"Liberator";"Starport";234;3
"Unit";"Liberator";"Starport";234;3
"Unit";"Liberator";"Starport";234;3
"Unit";"Liberator";"Starport";234;3
"Unit";"Hellion";"Factory";248;2
"Unit";"Hellion";"Factory";248;2
"Unit";"Hellion";"Factory";248;2
"Unit";"Hellion";"Factory";248;2
"Unit";"Thor";"Factory";248;6
"Building";"CommandCenter";NA;242;0
"Unit";"Liberator";"Starport";260;3
"Unit";"Liberator";"Starport";260;3
"Unit";"Thor";"Factory";274;6
"Unit";"Thor";"Factory";274;6
"Building";"MissileTurret";NA;292;0
"Building";"Refinery";NA;292;0
"Building";"Refinery";NA;292;0
"Unit";"Thor";"Factory";280;6
"Unit";"Thor";"Factory";280;6
"Unit";"Hellion";"Factory";292;2
"Unit";"Hellion";"Factory";292;2
