"type";"unit_name";"on_building";"total_supply";"supply"
"Building";"Refinery";NA;14;0
"Building";"Barracks";NA;15;0
"Unit";"Reaper";"Barracks";19;1
"Building";"Bunker";NA;19;0
"Unit";"Marine";"Barracks";20;1
"Building";"Factory";NA;20;0
"Unit";"Marine";"Barracks";23;1
"Unit";"Cyclone";"Factory";25;3
"Unit";"Marine";"Barracks";25;1
"Building";"FactoryTechLab";NA;31;0
"Building";"Refinery";NA;32;0
"Building";"CommandCenter";NA;23;0
"Building";"BarracksReactor";NA;33;0
"Unit";"Marine";"Barracks";36;1
"Unit";"Marine";"Barracks";36;1
"Building";"Starport";NA;36;0
"Unit";"Marine";"Barracks";41;1
"Unit";"Marine";"Barracks";41;1
"Unit";"Marine";"Barracks";47;1
"Unit";"Marine";"Barracks";47;1
"Unit";"Marine";"Barracks";49;1
"Unit";"Marine";"Barracks";50;1
"Building";"EngineeringBay";NA;53;0
"Building";"Refinery";NA;56;0
"Building";"Refinery";NA;56;0
"Building";"Starport";NA;56;0
"Unit";"Marine";"Barracks";59;1
"Unit";"Marine";"Barracks";59;1
"Building";"MissileTurret";NA;61;0
"Building";"MissileTurret";NA;61;0
"Building";"Bunker";NA;61;0
"Building";"BarracksTechLab";NA;68;0
"Building";"StarportReactor";NA;68;0
"Building";"Barracks";NA;68;0
"Building";"Barracks";NA;68;0
"Building";"MissileTurret";NA;74;0
"Building";"MissileTurret";NA;74;0
"Unit";"Marine";"Barracks";76;1
"Unit";"Marine";"Barracks";76;1
"Unit";"Marine";"Barracks";76;1
"Building";"BarracksReactor";NA;76;0
"Building";"CommandCenter";NA;72;0
"Unit";"Medivac";"Starport";83;2
"Unit";"Marine";"Barracks";85;1
"Unit";"Marine";"Barracks";85;1
"Unit";"Marine";"Barracks";85;1
"Unit";"Marine";"Barracks";85;1
"Unit";"Marine";"Barracks";85;1
"Building";"Refinery";NA;87;0
"Building";"Refinery";NA;87;0
"Unit";"Marine";"Barracks";97;1
"Unit";"Marine";"Barracks";97;1
"Unit";"Marine";"Barracks";97;1
"Unit";"Marine";"Barracks";97;1
"Unit";"Marine";"Barracks";97;1
"Building";"Barracks";NA;86;0
"Building";"Barracks";NA;86;0
"Building";"StarportReactor";NA;95;0
"Unit";"Marine";"Barracks";99;1
"Unit";"Marine";"Barracks";101;1
"Unit";"Marine";"Barracks";102;1
"Unit";"Marine";"Barracks";103;1
"Unit";"Marauder";"Barracks";104;2
"Upgrade";"TerranInfantryWeaponsLevel1";"EngineeringBay";85;0
"Unit";"Marine";"Barracks";107;1
"Unit";"Marine";"Barracks";108;1
"Unit";"Marine";"Barracks";109;1
"Unit";"Marine";"Barracks";110;1
"Upgrade";"Stimpack";"TechLab";85;0
"Unit";"Marauder";"Barracks";111;2
"Unit";"Marine";"Barracks";113;1
"Unit";"Marine";"Barracks";114;1
"Unit";"Marine";"Barracks";115;1
"Unit";"Marine";"Barracks";116;1
"Building";"EngineeringBay";NA;117;0
"Unit";"Marauder";"Barracks";117;2
"Building";"BarracksTechLab";NA;121;0
"Building";"BarracksTechLab";NA;121;0
"Unit";"Marine";"Barracks";121;1
"Unit";"Marine";"Barracks";122;1
"Unit";"Marine";"Barracks";123;1
"Unit";"Marine";"Barracks";124;1
"Building";"CommandCenter";NA;106;0
"Unit";"Marauder";"Barracks";125;2
"Building";"Armory";NA;117;0
"Unit";"Marauder";"Barracks";127;2
"Unit";"Marauder";"Barracks";127;2
"Unit";"Marauder";"Barracks";133;2
"Unit";"Liberator";"Starport";133;3
"Unit";"Liberator";"Starport";133;3
"Unit";"Liberator";"Starport";133;3
"Unit";"Marine";"Barracks";143;1
"Unit";"Marine";"Barracks";143;1
"Unit";"Marine";"Barracks";143;1
"Unit";"Marine";"Barracks";143;1
"Unit";"Marauder";"Barracks";143;2
"Unit";"Marine";"Barracks";158;1
"Unit";"Marine";"Barracks";158;1
"Unit";"Marine";"Barracks";158;1
"Unit";"Marine";"Barracks";160;1
"Building";"Refinery";NA;158;0
"Building";"Refinery";NA;158;0
