"type";"unit_name";"on_building";"total_supply";"supply"
"Building";"Refinery";NA;14;0
"Building";"Barracks";NA;16;0
"Unit";"Reaper";"Barracks";19;1
"Building";"Refinery";NA;21;0
"Building";"Factory";NA;20;0
"Unit";"Reaper";"Barracks";21;1
"Building";"CommandCenter";NA;20;0
"Unit";"Cyclone";"Factory";24;3
