"type";"unit_name";"on_building";"total_supply_lag";"supply"
"Building";"Barracks";NA;14;0
"Building";"Refinery";NA;14;0
"Building";"Barracks";NA;14;0
"Building";"Refinery";NA;16;0
"Unit";"Reaper";"Barracks";17;1
"Unit";"Reaper";"Barracks";19;1
"Unit";"Reaper";"Barracks";20;1
"Unit";"Reaper";"Barracks";21;1
"Unit";"Reaper";"Barracks";24;1
