"Type";"UnitName";"OnBuilding";"TotalSupply";"Supply"
"Unit";"SCV";"Command Center";12;1
"Unit";"SCV";"Command Center";12;1
"Unit";"SCV";"Command Center";13;1
"Building";"SupplyDepot";NA;13;0
"Unit";"SCV";"Command Center";15;1
"Building";"Refinery";NA;14;0
"Unit";"SCV";"Command Center";15;1
"Unit";"SCV";"Command Center";16;1
"Unit";"SCV";"Command Center";17;1
"Building";"Barracks";NA;15;0
"Unit";"Reaper";"Barracks";19;1
"Unit";"SCV";"Command Center";19;1
"Unit";"SCV";"Command Center";20;1
"Building";"SupplyDepot";NA;20;0
"Building";"Factory";NA;19;0
"Unit";"Reaper";"Barracks";20;1
"Unit";"SCV";"Command Center";22;1
"Building";"Refinery";NA;21;0
"Unit";"SCV";"Command Center";23;1
"Unit";"Hellion";"Factory";22;2
"Unit";"Marine";"Barracks";23;1
"Building";"CommandCenter";NA;19;0
"Unit";"SCV";"Command Center";24;1
"Unit";"SCV";"Command Center";28;1
"Building";"Starport";NA;24;0
"Unit";"SCV";"Command Center";30;1
"Unit";"Marine";"Barracks";30;1
"Unit";"SCV";"Command Center";30;1
"Unit";"SCV";"Command Center";31;1
"Unit";"Cyclone";"Factory";30;3
"Building";"SupplyDepot";NA;30;0
"Unit";"SCV";"Command Center";33;1
"Unit";"SCV";"Command Center";34;1
"Unit";"SCV";"Command Center";38;1
"Unit";"SCV";"Command Center";39;1
"Unit";"Liberator";"Starport";31;3
"Unit";"SCV";"Command Center";39;1
"Unit";"Cyclone";"Factory";39;3
"Unit";"SCV";"Command Center";44;1
"Unit";"SCV";"Command Center";44;1
"Building";"StarportTechLab";NA;44;0
"Unit";"SCV";"Command Center";49;1
"Building";"BarracksReactor";NA;40;0
"Building";"SupplyDepot";NA;49;0
"Unit";"Cyclone";"Factory";49;3
"Unit";"SCV";"Command Center";51;1
"Building";"Refinery";NA;50;0
"Building";"Refinery";NA;50;0
"Unit";"SCV";"Command Center";51;1
"Unit";"SCV";"Command Center";54;1
"Unit";"Marine";"Barracks";51;1
"Unit";"Marine";"Barracks";51;1
"Unit";"SCV";"Command Center";56;1
"Unit";"SCV";"Command Center";56;1
"Building";"FactoryTechLab";NA;56;0
"Unit";"SCV";"Command Center";59;1
"Unit";"SCV";"Command Center";60;1
"Building";"CommandCenter";NA;48;0
"Unit";"Marine";"Barracks";60;1
"Unit";"Marine";"Barracks";60;1
"Unit";"SCV";"Command Center";62;1
"Unit";"Raven";"Starport";56;2
"Building";"EngineeringBay";NA;61;0
"Building";"EngineeringBay";NA;62;0
"Building";"Barracks";NA;57;0
"Building";"Barracks";NA;59;0
"Unit";"SCV";"Command Center";68;1
"Unit";"SCV";"Command Center";68;1
"Unit";"Marine";"Barracks";68;1
"Unit";"Marine";"Barracks";68;1
"Unit";"SCV";"Command Center";70;1
"Unit";"SCV";"Command Center";71;1
"Unit";"SCV";"Command Center";72;1
"Building";"BarracksTechLab";NA;68;0
"Unit";"SCV";"Command Center";74;1
"Unit";"SCV";"Command Center";74;1
"Unit";"Marine";"Barracks";72;1
"Unit";"Marine";"Barracks";72;1
"Unit";"Raven";"Starport";68;2
"Unit";"Marine";"Barracks";75;1
"Building";"BarracksReactor";NA;71;0
"Unit";"Marine";"Barracks";81;1
"Building";"SupplyDepot";NA;78;0
"Unit";"Marine";"Barracks";81;1
"Building";"SupplyDepot";NA;81;0
"Unit";"SCV";"Command Center";82;1
"Unit";"SCV";"Command Center";83;1
"Unit";"Marine";"Barracks";82;1
"Unit";"Marine";"Barracks";83;1
"Unit";"SCV";"Command Center";84;1
"Unit";"SCV";"Command Center";85;1
"Unit";"Marine";"Barracks";85;1
"Unit";"Marine";"Barracks";85;1
"Unit";"Medivac";"Starport";83;2
"Unit";"Medivac";"Starport";83;2
"Unit";"Marine";"Barracks";86;1
"Building";"Barracks";NA;81;0
"Building";"Barracks";NA;77;0
"Unit";"SCV";"Command Center";97;1
"Unit";"SCV";"Command Center";97;1
"Unit";"Marine";"Barracks";97;1
"Unit";"Marine";"Barracks";97;1
"Unit";"Marine";"Barracks";97;1
"Unit";"Marine";"Barracks";97;1
"Upgrade";"TerranInfantryWeaponsLevel1";"EngineeringBay";77;0
"Unit";"Medivac";"Starport";92;2
"Upgrade";"TerranInfantryArmorsLevel1";"EngineeringBay";81;0
"Unit";"SCV";"Command Center";97;1
"Unit";"Marine";"Barracks";97;1
"Unit";"Marine";"Barracks";97;1
"Unit";"SCV";"Command Center";97;1
"Building";"SupplyDepot";NA;89;0
"Unit";"SCV";"Command Center";103;1
"Building";"SupplyDepot";NA;85;0
"Unit";"Marine";"Barracks";99;1
"Unit";"Marine";"Barracks";100;1
"Unit";"SCV";"Command Center";105;1
"Unit";"Marine";"Barracks";102;1
"Unit";"SCV";"Command Center";108;1
"Unit";"SCV";"Command Center";109;1
"Unit";"SCV";"Command Center";112;1
"Upgrade";"Stimpack";"TechLab";84;0
"Unit";"SCV";"Command Center";115;1
"Unit";"Marine";"Barracks";115;1
"Unit";"Marine";"Barracks";115;1
"Unit";"Marine";"Barracks";115;1
"Unit";"SCV";"Command Center";116;1
"Unit";"SCV";"Command Center";116;1
"Building";"MissileTurret";NA;116;0
"Unit";"SCV";"Command Center";118;1
"Building";"BarracksReactor";NA;110;0
"Unit";"SCV";"Command Center";121;1
"Building";"BarracksReactor";NA;111;0
"Unit";"SCV";"Command Center";122;1
"Unit";"Marine";"Barracks";118;1
"Unit";"Marine";"Barracks";123;1
"Unit";"Marine";"Barracks";123;1
"Unit";"SCV";"Command Center";123;1
"Unit";"SCV";"Command Center";124;1
"Building";"SupplyDepot";NA;123;0
"Unit";"Marine";"Barracks";126;1
"Unit";"Marine";"Barracks";126;1
"Unit";"Medivac";"Starport";123;2
"Unit";"Marine";"Barracks";127;1
"Unit";"Marine";"Barracks";129;1
"Unit";"Marine";"Barracks";129;1
"Unit";"Marine";"Barracks";129;1
"Unit";"Marine";"Barracks";129;1
"Building";"Factory";NA;122;0
"Building";"Armory";NA;118;0
"Building";"BarracksReactor";NA;123;0
"Unit";"Marine";"Barracks";131;1
"Unit";"Marine";"Barracks";132;1
"Unit";"SCV";"Command Center";140;1
"Unit";"Marine";"Barracks";135;1
"Unit";"Marine";"Barracks";136;1
"Unit";"Marine";"Barracks";136;1
"Unit";"Marine";"Barracks";140;1
"Unit";"Marine";"Barracks";140;1
"Unit";"SCV";"Command Center";140;1
"Building";"SupplyDepot";NA;140;0
"Unit";"Marine";"Barracks";142;1
"Unit";"Marine";"Barracks";142;1
"Building";"SupplyDepot";NA;140;0
"Building";"SupplyDepot";NA;140;0
"Unit";"Medivac";"Starport";140;2
"Unit";"Medivac";"Starport";140;2
"Unit";"Marine";"Barracks";143;1
"Unit";"Marine";"Barracks";148;1
"Unit";"Marine";"Barracks";148;1
"Unit";"Marine";"Barracks";148;1
"Unit";"Marine";"Barracks";149;1
"Unit";"Marine";"Barracks";149;1
"Unit";"Marine";"Barracks";149;1
"Unit";"Marine";"Barracks";149;1
"Unit";"Marine";"Barracks";149;1
"Unit";"Marine";"Barracks";155;1
"Unit";"Marine";"Barracks";156;1
"Unit";"Marine";"Barracks";157;1
"Unit";"Marine";"Barracks";158;1
"Unit";"Marine";"Barracks";159;1
"Unit";"Marine";"Barracks";160;1
"Unit";"Marine";"Barracks";161;1
