"Type";"UnitName";"OnBuilding";"TotalSupply";"Supply"
"Unit";"SCV";"Command Center";12;1
"Unit";"SCV";"Command Center";12;1
"Unit";"SCV";"Command Center";13;1
"Building";"SupplyDepot";NA;13;0
"Unit";"SCV";"Command Center";15;1
"Unit";"SCV";"Command Center";15;1
"Building";"Refinery";NA;15;0
"Unit";"SCV";"Command Center";16;1
"Building";"Barracks";NA;15;0
"Unit";"SCV";"Command Center";17;1
"Unit";"Reaper";"Barracks";19;1
"Building";"SupplyDepot";NA;19;0
"Unit";"SCV";"Command Center";19;1
"Unit";"Marine";"Barracks";20;1
"Unit";"SCV";"Command Center";21;1
"Unit";"SCV";"Command Center";22;1
"Building";"Refinery";NA;23;0
"Unit";"SCV";"Command Center";23;1
"Building";"Factory";NA;20;0
"Building";"CommandCenter";NA;19;0
"Building";"BarracksReactor";NA;22;0
"Unit";"SCV";"Command Center";25;1
"Unit";"Hellion";"Factory";25;2
"Unit";"SCV";"Command Center";25;1
"Unit";"Marine";"Barracks";26;1
"Unit";"Marine";"Barracks";26;1
"Unit";"SCV";"Command Center";29;1
"Unit";"SCV";"Command Center";31;1
"Unit";"SCV";"Command Center";32;1
"Unit";"Marine";"Barracks";31;1
"Unit";"Cyclone";"Factory";29;3
"Unit";"Marine";"Barracks";32;1
"Unit";"SCV";"Command Center";33;1
"Building";"Bunker";NA;29;0
"Unit";"SCV";"Command Center";34;1
"Unit";"SCV";"Command Center";39;1
"Unit";"SCV";"Command Center";41;1
"Building";"CommandCenter";NA;25;0
"Building";"Starport";NA;33;0
"Building";"BarracksTechLab";NA;41;0
"Building";"SupplyDepot";NA;40;0
"Unit";"SCV";"Command Center";43;1
"Unit";"SCV";"Command Center";43;1
"Building";"EngineeringBay";NA;41;0
"Unit";"Cyclone";"Factory";43;3
"Unit";"SCV";"Command Center";45;1
"Unit";"SCV";"Command Center";45;1
"Unit";"Cyclone";"Factory";43;3
"Building";"MissileTurret";NA;45;0
"Unit";"SCV";"Command Center";50;1
"Unit";"SCV";"Command Center";50;1
"Building";"BarracksTechLab";NA;50;0
"Building";"SupplyDepot";NA;50;0
"Unit";"SCV";"Command Center";53;1
"Unit";"SCV";"Command Center";54;1
"Unit";"SCV";"Command Center";55;1
"Unit";"Raven";"Starport";45;2
"Unit";"SCV";"Command Center";56;1
"Building";"Refinery";NA;55;0
"Building";"Refinery";NA;55;0
"Unit";"SCV";"Command Center";58;1
"Building";"SupplyDepot";NA;56;0
"Building";"MissileTurret";NA;57;0
"Unit";"SCV";"Command Center";60;1
"Unit";"Marine";"Barracks";58;1
"Unit";"SCV";"Command Center";61;1
"Building";"SupplyDepot";NA;57;0
"Building";"FactoryReactor";NA;55;0
"Unit";"SCV";"Command Center";61;1
"Unit";"SCV";"Command Center";65;1
"Building";"Barracks";NA;55;0
"Building";"Barracks";NA;55;0
"Unit";"SCV";"Command Center";65;1
"Unit";"Marine";"Barracks";65;1
"Building";"SupplyDepot";NA;65;0
"Unit";"SCV";"Command Center";67;1
"Building";"StarportReactor";NA;61;0
"Unit";"Marine";"Barracks";67;1
"Unit";"Marine";"Barracks";67;1
"Unit";"SCV";"Command Center";69;1
"Unit";"SCV";"Command Center";69;1
"Building";"SupplyDepot";NA;70;0
"Unit";"Marine";"Barracks";73;1
"Unit";"Marine";"Barracks";73;1
"Unit";"Marine";"Barracks";73;1
"Unit";"Marine";"Barracks";73;1
"Unit";"Marine";"Barracks";73;1
"Building";"Barracks";NA;66;0
"Building";"Barracks";NA;67;0
"Unit";"Marine";"Barracks";74;1
"Unit";"Marine";"Barracks";75;1
"Unit";"Marine";"Barracks";76;1
"Unit";"Marine";"Barracks";76;1
"Building";"BarracksTechLab";NA;79;0
"Unit";"SCV";"Command Center";79;1
"Unit";"SCV";"Command Center";79;1
"Unit";"SCV";"Command Center";83;1
"Unit";"SCV";"Command Center";85;1
"Unit";"Marine";"Barracks";83;1
"Unit";"Marine";"Barracks";83;1
"Unit";"Marine";"Barracks";83;1
"Unit";"Marine";"Barracks";83;1
"Unit";"Marine";"Barracks";83;1
"Building";"BarracksTechLab";NA;85;0
"Unit";"SCV";"Command Center";85;1
"Unit";"SCV";"Command Center";86;1
"Building";"BarracksReactor";NA;79;0
"Building";"EngineeringBay";NA;85;0
"Unit";"SCV";"Command Center";92;1
"Building";"StarportReactor";NA;83;0
"Unit";"Marine";"Barracks";92;1
"Unit";"Marine";"Barracks";92;1
"Unit";"Marine";"Barracks";92;1
"Unit";"SCV";"Command Center";92;1
"Building";"SupplyDepot";NA;92;0
"Unit";"SCV";"Command Center";93;1
"Unit";"Marine";"Barracks";94;1
"Unit";"Marine";"Barracks";94;1
"Unit";"Marine";"Barracks";94;1
"Unit";"Marine";"Barracks";95;1
"Unit";"SCV";"Command Center";100;1
"Unit";"SCV";"Command Center";100;1
"Building";"Armory";NA;85;0
"Unit";"Marine";"Barracks";100;1
"Unit";"Marine";"Barracks";100;1
"Unit";"Marine";"Barracks";100;1
"Unit";"Marine";"Barracks";100;1
"Upgrade";"TerranInfantryWeaponsLevel1";"EngineeringBay";79;0
"Unit";"SCV";"Command Center";103;1
"Unit";"SCV";"Command Center";106;1
"Unit";"Marine";"Barracks";100;1
"Unit";"SCV";"Command Center";106;1
"Unit";"Marine";"Barracks";103;1
"Unit";"Marine";"Barracks";103;1
"Unit";"Marine";"Barracks";103;1
"Building";"SupplyDepot";NA;100;0
"Building";"SupplyDepot";NA;106;0
"Unit";"SCV";"Command Center";110;1
"Unit";"Marine";"Barracks";106;1
"Unit";"SCV";"Command Center";111;1
"Unit";"Marine";"Barracks";107;1
"Unit";"Marine";"Barracks";108;1
"Building";"StarportReactor";NA;100;0
"Unit";"SCV";"Command Center";115;1
"Unit";"Marine";"Barracks";112;1
"Unit";"Marine";"Barracks";112;1
"Unit";"Marine";"Barracks";114;1
"Unit";"Marine";"Barracks";122;1
"Unit";"SCV";"Command Center";124;1
"Unit";"Marine";"Barracks";122;1
"Unit";"Marine";"Barracks";122;1
"Unit";"Marine";"Barracks";122;1
"Unit";"SCV";"Command Center";124;1
"Building";"Refinery";NA;122;0
"Unit";"SCV";"Command Center";126;1
"Building";"MissileTurret";NA;123;0
"Building";"Refinery";NA;122;0
"Unit";"Marine";"Barracks";126;1
"Unit";"Marine";"Barracks";126;1
"Building";"Factory";NA;111;0
"Unit";"Marine";"Barracks";126;1
"Unit";"Marine";"Barracks";126;1
"Unit";"Medivac";"Starport";123;2
"Building";"SupplyDepot";NA;126;0
"Unit";"Medivac";"Starport";123;2
"Unit";"Marine";"Barracks";132;1
"Unit";"Marine";"Barracks";132;1
"Building";"SupplyDepot";NA;128;0
"Unit";"Marine";"Barracks";133;1
"Unit";"Marine";"Barracks";133;1
"Upgrade";"Stimpack";"TechLab";98;0
"Unit";"Marine";"Barracks";133;1
"Building";"MissileTurret";NA;139;0
"Unit";"Marine";"Barracks";141;1
"Building";"FactoryTechLab";NA;141;0
"Unit";"Marine";"Barracks";141;1
"Unit";"Marine";"Barracks";141;1
"Unit";"Marine";"Barracks";141;1
"Unit";"Marine";"Barracks";145;1
"Unit";"Marine";"Barracks";145;1
"Unit";"Medivac";"Starport";141;2
"Unit";"Medivac";"Starport";141;2
"Building";"SupplyDepot";NA;146;0
"Building";"SupplyDepot";NA;146;0
"Unit";"Marine";"Barracks";149;1
"Unit";"Marine";"Barracks";149;1
"Unit";"Marine";"Barracks";149;1
"Unit";"Marine";"Barracks";149;1
"Unit";"Marine";"Barracks";149;1
"Upgrade";"TerranInfantryArmorsLevel1";"EngineeringBay";117;0
"Building";"SupplyDepot";NA;150;0
"Building";"MissileTurret";NA;152;0
"Unit";"Marine";"Barracks";152;1
"Unit";"Marine";"Barracks";156;1
"Unit";"Marine";"Barracks";156;1
"Unit";"Marine";"Barracks";156;1
"Building";"SupplyDepot";NA;156;0
"Upgrade";"TerranVehicleWeaponsLevel1";"Armory";126;0
"Unit";"Marine";"Barracks";161;1
"Unit";"Marine";"Barracks";161;1
"Unit";"Marine";"Barracks";161;1
"Unit";"Marine";"Barracks";161;1
"Unit";"Medivac";"Starport";156;2
"Unit";"Marine";"Barracks";161;1
"Unit";"Marine";"Barracks";162;1
"Unit";"Marine";"Barracks";165;1
"Unit";"Marine";"Barracks";165;1
"Unit";"Marine";"Barracks";165;1
"Unit";"Marine";"Barracks";166;1
"Unit";"Marine";"Barracks";167;1
"Unit";"Marine";"Barracks";167;1
"Unit";"Marine";"Barracks";172;1
"Unit";"Marine";"Barracks";173;1
"Unit";"Marine";"Barracks";173;1
"Upgrade";"TerranInfantryWeaponsLevel2";"EngineeringBay";139;0
"Building";"SupplyDepot";NA;179;0
"Unit";"Medivac";"Starport";173;2
"Unit";"Medivac";"Starport";173;2
"Unit";"Marine";"Barracks";180;1
"Unit";"Marine";"Barracks";181;1
"Unit";"Marine";"Barracks";182;1
"Building";"SupplyDepot";NA;182;0
"Unit";"Marine";"Barracks";182;1
"Unit";"Marine";"Barracks";182;1
"Building";"CommandCenter";NA;172;0
"Unit";"Marine";"Barracks";191;1
"Unit";"SCV";"Command Center";191;1
"Unit";"Marine";"Barracks";191;1
"Unit";"Marine";"Barracks";191;1
"Unit";"Marine";"Barracks";191;1
"Unit";"Marine";"Barracks";191;1
"Unit";"Marine";"Barracks";191;1
"Unit";"Marine";"Barracks";191;1
"Unit";"Marine";"Barracks";191;1
"Unit";"Marine";"Barracks";191;1
"Unit";"Marine";"Barracks";192;1
"Unit";"Marine";"Barracks";192;1
"Unit";"Marine";"Barracks";200;1
"Unit";"Marine";"Barracks";200;1
"Unit";"Marine";"Barracks";200;1
"Unit";"Marine";"Barracks";200;1
"Unit";"Marine";"Barracks";200;1
"Unit";"Medivac";"Starport";200;2
"Unit";"Medivac";"Starport";200;2
"Unit";"Marine";"Barracks";208;1
"Unit";"Marine";"Barracks";208;1
"Unit";"Marine";"Barracks";208;1
"Unit";"Marine";"Barracks";208;1
"Unit";"Marine";"Barracks";208;1
"Unit";"Marine";"Barracks";208;1
"Unit";"Marauder";"Barracks";208;2
