"type";"unit_name";"on_building";"total_supply";"supply"
"Building";"Refinery";NA;15;0
"Building";"Barracks";NA;15;0
"Unit";"Reaper";"Barracks";19;1
"Building";"Refinery";NA;20;0
"Building";"Factory";NA;19;0
"Unit";"Reaper";"Barracks";21;1
"Building";"CommandCenter";NA;19;0
"Unit";"Hellion";"Factory";23;2
"Building";"Starport";NA;23;0
"Building";"BarracksReactor";NA;25;0
"Unit";"Cyclone";"Factory";29;3
"Unit";"Marine";"Barracks";30;1
"Unit";"Marine";"Barracks";31;1
"Unit";"Marine";"Barracks";36;1
"Building";"FactoryTechLab";NA;36;0
"Unit";"Medivac";"Starport";31;2
"Building";"EngineeringBay";NA;36;0
"Unit";"Marine";"Barracks";39;1
"Unit";"Marine";"Barracks";39;1
"Building";"BarracksTechLab";NA;47;0
"Building";"Barracks";NA;47;0
"Unit";"Marine";"Barracks";49;1
"Unit";"Marine";"Barracks";51;1
"Building";"Barracks";NA;47;0
"Unit";"Marine";"Barracks";52;1
"Unit";"Marine";"Barracks";53;1
"Unit";"Marine";"Barracks";57;1
"Unit";"Marine";"Barracks";60;1
"Unit";"Marine";"Barracks";60;1
"Unit";"Marine";"Barracks";62;1
"Unit";"Marine";"Barracks";66;1
"Unit";"Marine";"Barracks";66;1
"Building";"BarracksReactor";NA;63;0
"Unit";"Marine";"Barracks";69;1
"Upgrade";"Stimpack";"TechLab";52;0
"Unit";"Marine";"Barracks";73;1
"Building";"StarportReactor";NA;69;0
"Unit";"Marine";"Barracks";74;1
"Unit";"Marine";"Barracks";79;1
"Unit";"Marine";"Barracks";79;1
"Unit";"Marine";"Barracks";81;1
"Unit";"Marine";"Barracks";81;1
"Unit";"Medivac";"Starport";80;2
"Unit";"Marine";"Barracks";85;1
"Unit";"Marine";"Barracks";85;1
"Unit";"Marine";"Barracks";85;1
"Unit";"Medivac";"Starport";82;2
"Unit";"Marine";"Barracks";88;1
"Unit";"Marine";"Barracks";88;1
"Unit";"Marine";"Barracks";100;1
"Unit";"Marine";"Barracks";100;1
"Unit";"Marine";"Barracks";101;1
"Unit";"Marine";"Barracks";106;1
"Unit";"Marine";"Barracks";106;1
"Unit";"Marine";"Barracks";106;1
"Unit";"Marauder";"Barracks";106;2
"Building";"Refinery";NA;106;0
"Unit";"Marine";"Barracks";114;1
"Unit";"Marine";"Barracks";114;1
"Unit";"Marine";"Barracks";114;1
"Unit";"Marine";"Barracks";114;1
"Building";"CommandCenter";NA;100;0
"Unit";"Marauder";"Barracks";114;2
"Unit";"Marine";"Barracks";118;1
"Unit";"Marine";"Barracks";120;1
"Unit";"Marine";"Barracks";120;1
"Unit";"Marauder";"Barracks";121;2
"Upgrade";"TerranInfantryWeaponsLevel1";"EngineeringBay";102;0
"Unit";"Marine";"Barracks";124;1
"Unit";"Marine";"Barracks";124;1
"Unit";"Marine";"Barracks";128;1
"Unit";"Marine";"Barracks";128;1
"Building";"Barracks";NA;115;0
"Building";"Barracks";NA;115;0
"Unit";"Marine";"Barracks";128;1
"Unit";"Marine";"Barracks";130;1
"Unit";"Marine";"Barracks";132;1
"Unit";"Marine";"Barracks";136;1
"Unit";"Marine";"Barracks";136;1
"Building";"BarracksTechLab";NA;137;0
"Unit";"Medivac";"Starport";132;2
"Building";"BarracksTechLab";NA;137;0
"Unit";"Medivac";"Starport";132;2
"Unit";"Marine";"Barracks";139;1
"Unit";"Marine";"Barracks";139;1
"Unit";"Marine";"Barracks";141;1
"Unit";"Marine";"Barracks";147;1
"Unit";"Marine";"Barracks";147;1
"Unit";"Marine";"Barracks";147;1
"Unit";"Marauder";"Barracks";149;2
"Unit";"Medivac";"Starport";143;2
"Unit";"Medivac";"Starport";145;2
"Building";"SensorTower";NA;151;0
"Unit";"Marine";"Barracks";152;1
"Unit";"Marine";"Barracks";152;1
"Unit";"Marine";"Barracks";152;1
"Building";"Refinery";NA;164;0
"Unit";"Medivac";"Starport";157;2
"Unit";"Marine";"Barracks";169;1
"Unit";"Marine";"Barracks";169;1
"Unit";"Marauder";"Barracks";169;2
"Unit";"Marine";"Barracks";169;1
"Building";"Factory";NA;162;0
"Building";"Refinery";NA;169;0
"Unit";"Marine";"Barracks";169;1
"Building";"Refinery";NA;169;0
"Unit";"Marine";"Barracks";173;1
"Unit";"Marine";"Barracks";179;1
"Unit";"Marine";"Barracks";179;1
"Unit";"Marine";"Barracks";179;1
"Unit";"Marauder";"Barracks";179;2
"Building";"FactoryTechLab";NA;182;0
"Unit";"Marine";"Barracks";188;1
"Unit";"Marine";"Barracks";188;1
"Unit";"Marine";"Barracks";188;1
"Unit";"Marine";"Barracks";188;1
"Unit";"Marine";"Barracks";188;1
"Unit";"Marine";"Barracks";188;1
"Unit";"Marauder";"Barracks";189;2
"Unit";"Medivac";"Starport";192;2
"Unit";"Medivac";"Starport";192;2
"Unit";"Marauder";"Barracks";200;2
"Unit";"Marauder";"Barracks";200;2
"Building";"Starport";NA;198;0
"Building";"Starport";NA;198;0
"Upgrade";"TerranInfantryArmorsLevel1";"EngineeringBay";198;0
"Building";"StarportReactor";NA;208;0
"Building";"StarportReactor";NA;208;0
"Building";"SensorTower";NA;208;0
"Building";"SensorTower";NA;208;0
"Building";"Refinery";NA;208;0
"Building";"Refinery";NA;208;0
"Building";"CommandCenter";NA;208;0
"Unit";"Marine";"Barracks";208;1
"Unit";"Marine";"Barracks";208;1
"Unit";"Marauder";"Barracks";208;2
"Unit";"Marine";"Barracks";208;1
"Unit";"Marine";"Barracks";208;1
"Unit";"Marauder";"Barracks";208;2
"Unit";"Marine";"Barracks";216;1
"Unit";"Marine";"Barracks";216;1
"Unit";"Marine";"Barracks";216;1
"Unit";"Marine";"Barracks";216;1
"Unit";"Liberator";"Starport";208;3
"Unit";"Liberator";"Starport";208;3
"Unit";"Marine";"Barracks";226;1
"Unit";"Liberator";"Starport";216;3
"Unit";"Marine";"Barracks";226;1
"Unit";"Marine";"Barracks";226;1
"Unit";"Marauder";"Barracks";226;2
"Unit";"Liberator";"Starport";226;3
"Unit";"Liberator";"Starport";226;3
"Unit";"Marine";"Barracks";232;1
"Unit";"Marine";"Barracks";232;1
"Unit";"Liberator";"Starport";226;3
"Unit";"Marauder";"Barracks";232;2
"Unit";"Marauder";"Barracks";232;2
"Unit";"Marine";"Barracks";234;1
"Unit";"Liberator";"Starport";226;3
"Unit";"Liberator";"Starport";226;3
"Unit";"Marine";"Barracks";249;1
"Unit";"Liberator";"Starport";232;3
"Unit";"Marine";"Barracks";249;1
"Unit";"Marine";"Barracks";249;1
"Unit";"Marine";"Barracks";249;1
