"type";"unit_name";"on_building";"total_supply";"supply"
"Building";"Refinery";NA;14;0
"Building";"Barracks";NA;15;0
"Unit";"Reaper";"Barracks";19;1
"Building";"Refinery";NA;20;0
"Building";"Factory";NA;19;0
"Building";"BarracksReactor";NA;20;0
"Building";"CommandCenter";NA;19;0
"Unit";"Hellion";"Factory";24;2
"Building";"Starport";NA;23;0
"Building";"BarracksTechLab";NA;24;0
"Unit";"Cyclone";"Factory";25;3
"Unit";"Marine";"Barracks";34;1
"Unit";"Marine";"Barracks";34;1
"Building";"FactoryTechLab";NA;36;0
"Unit";"Raven";"Starport";33;2
"Unit";"Marine";"Barracks";38;1
"Unit";"Marine";"Barracks";38;1
"Unit";"Marine";"Barracks";48;1
"Building";"StarportReactor";NA;46;0
"Building";"Barracks";NA;45;0
"Building";"Barracks";NA;46;0
"Building";"EngineeringBay";NA;50;0
"Building";"Refinery";NA;50;0
"Building";"EngineeringBay";NA;50;0
"Building";"Refinery";NA;50;0
"Building";"CommandCenter";NA;38;0
"Unit";"Marine";"Barracks";55;1
"Unit";"Marine";"Barracks";55;1
"Unit";"Marine";"Barracks";55;1
"Unit";"Marine";"Barracks";56;1
"Unit";"Marine";"Barracks";57;1
"Unit";"Marine";"Barracks";62;1
"Unit";"Marine";"Barracks";62;1
"Unit";"Marine";"Barracks";62;1
"Unit";"Marine";"Barracks";62;1
"Building";"StarportReactor";NA;57;0
"Unit";"Marine";"Barracks";64;1
"Unit";"Marine";"Barracks";66;1
"Unit";"Marine";"Barracks";67;1
"Unit";"Marine";"Barracks";72;1
"Unit";"Marine";"Barracks";72;1
"Unit";"Marine";"Barracks";72;1
"Upgrade";"Stimpack";"TechLab";53;0
"Unit";"Marine";"Barracks";72;1
"Unit";"Marine";"Barracks";76;1
"Unit";"Medivac";"Starport";72;2
"Unit";"Medivac";"Starport";72;2
"Unit";"Marine";"Barracks";82;1
"Unit";"Marine";"Barracks";82;1
"Unit";"Marine";"Barracks";82;1
"Unit";"Marine";"Barracks";82;1
"Unit";"Marine";"Barracks";92;1
"Unit";"Marine";"Barracks";92;1
"Building";"SensorTower";NA;92;0
"Building";"Armory";NA;76;0
"Unit";"Marine";"Barracks";92;1
"Unit";"Marine";"Barracks";92;1
"Unit";"Marine";"Barracks";92;1
"Upgrade";"TerranInfantryArmorsLevel1";"EngineeringBay";70;0
"Upgrade";"TerranInfantryWeaponsLevel1";"EngineeringBay";70;0
"Building";"SensorTower";NA;94;0
"Unit";"Marine";"Barracks";94;1
"Unit";"Marine";"Barracks";101;1
"Unit";"Marine";"Barracks";101;1
"Unit";"Marine";"Barracks";101;1
"Unit";"Marine";"Barracks";101;1
"Unit";"Marine";"Barracks";102;1
"Building";"Barracks";NA;92;0
"Unit";"Marine";"Barracks";108;1
"Unit";"Marine";"Barracks";108;1
"Unit";"Marine";"Barracks";108;1
"Unit";"Marine";"Barracks";108;1
"Unit";"Medivac";"Starport";108;2
"Unit";"Medivac";"Starport";108;2
"Building";"Refinery";NA;115;0
"Unit";"Marine";"Barracks";115;1
"Unit";"Marine";"Barracks";115;1
"Building";"Refinery";NA;115;0
"Unit";"Marine";"Barracks";115;1
"Unit";"Marine";"Barracks";115;1
"Building";"Barracks";NA;109;0
"Unit";"Marine";"Barracks";132;1
"Unit";"Marine";"Barracks";132;1
"Unit";"Marine";"Barracks";132;1
"Unit";"Marine";"Barracks";132;1
"Building";"BarracksReactor";NA;129;0
"Building";"Factory";NA;129;0
"Building";"BarracksReactor";NA;132;0
"Unit";"Medivac";"Starport";132;2
"Unit";"Marine";"Barracks";138;1
"Unit";"Marine";"Barracks";138;1
"Unit";"Marine";"Barracks";138;1
"Unit";"Marine";"Barracks";138;1
"Unit";"Marine";"Barracks";138;1
"Unit";"Marine";"Barracks";138;1
"Unit";"Marine";"Barracks";138;1
"Unit";"Medivac";"Starport";138;2
"Unit";"Marine";"Barracks";140;1
"Unit";"Marine";"Barracks";141;1
"Unit";"Marine";"Barracks";142;1
"Unit";"Medivac";"Starport";138;2
"Unit";"Marine";"Barracks";147;1
"Unit";"Marine";"Barracks";147;1
"Unit";"Marine";"Barracks";147;1
"Unit";"Marine";"Barracks";147;1
"Unit";"Marine";"Barracks";147;1
"Unit";"Marine";"Barracks";147;1
"Unit";"Marine";"Barracks";149;1
"Unit";"Marine";"Barracks";150;1
"Upgrade";"TerranInfantryArmorsLevel2";"EngineeringBay";129;0
"Unit";"Marine";"Barracks";154;1
"Unit";"Marine";"Barracks";154;1
"Building";"FactoryTechLab";NA;155;0
"Unit";"Marine";"Barracks";155;1
"Unit";"Marine";"Barracks";156;1
"Unit";"Marine";"Barracks";156;1
"Upgrade";"TerranInfantryWeaponsLevel2";"EngineeringBay";132;0
"Building";"MissileTurret";NA;162;0
"Building";"MissileTurret";NA;162;0
"Unit";"Marine";"Barracks";162;1
"Unit";"Marine";"Barracks";162;1
"Unit";"Marine";"Barracks";162;1
"Unit";"Marine";"Barracks";162;1
"Building";"MissileTurret";NA;162;0
"Building";"MissileTurret";NA;162;0
"Unit";"Marine";"Barracks";162;1
"Unit";"Marine";"Barracks";163;1
"Unit";"Marine";"Barracks";167;1
"Unit";"Marine";"Barracks";167;1
"Unit";"Marine";"Barracks";167;1
"Unit";"Marine";"Barracks";167;1
"Unit";"Marine";"Barracks";168;1
"Unit";"Marine";"Barracks";169;1
"Unit";"Marine";"Barracks";169;1
"Building";"Barracks";NA;160;0
"Building";"Barracks";NA;160;0
"Unit";"Marine";"Barracks";171;1
"Building";"SensorTower";NA;172;0
"Unit";"Marine";"Barracks";172;1
"Unit";"Marine";"Barracks";173;1
"Unit";"Marine";"Barracks";174;1
"Unit";"Marine";"Barracks";174;1
"Unit";"Medivac";"Starport";171;2
"Unit";"Marine";"Barracks";176;1
"Unit";"Marine";"Barracks";177;1
"Unit";"Marine";"Barracks";178;1
"Unit";"Marine";"Barracks";178;1
"Unit";"Marine";"Barracks";180;1
"Unit";"Marine";"Barracks";181;1
"Unit";"Marine";"Barracks";182;1
"Unit";"Marine";"Barracks";183;1
"Unit";"Marine";"Barracks";183;1
"Unit";"Marine";"Barracks";187;1
"Unit";"Marine";"Barracks";188;1
"Unit";"Marine";"Barracks";189;1
"Unit";"Marine";"Barracks";189;1
"Building";"CommandCenter";NA;162;0
"Unit";"Marine";"Barracks";191;1
"Unit";"Marine";"Barracks";192;1
"Unit";"Marine";"Barracks";193;1
"Unit";"Marine";"Barracks";194;1
"Unit";"Marine";"Barracks";194;1
"Building";"BarracksReactor";NA;185;0
"Building";"BarracksReactor";NA;185;0
"Building";"Barracks";NA;180;0
"Unit";"Marine";"Barracks";196;1
"Unit";"Marine";"Barracks";197;1
"Unit";"Marine";"Barracks";198;1
"Unit";"Marine";"Barracks";198;1
"Unit";"Marine";"Barracks";200;1
"Unit";"Marine";"Barracks";201;1
"Unit";"Marine";"Barracks";202;1
"Unit";"Marine";"Barracks";203;1
"Unit";"Marine";"Barracks";203;1
"Unit";"Marine";"Barracks";205;1
"Upgrade";"TerranVehicleWeaponsLevel1";"Armory";173;0
"Unit";"Marine";"Barracks";209;1
"Unit";"Marine";"Barracks";209;1
"Unit";"Marine";"Barracks";209;1
"Unit";"Marine";"Barracks";209;1
"Unit";"Marine";"Barracks";209;1
"Unit";"Marine";"Barracks";209;1
"Unit";"Medivac";"Starport";211;2
"Unit";"Medivac";"Starport";211;2
"Building";"BarracksReactor";NA;210;0
"Unit";"Marine";"Barracks";221;1
"Unit";"Marine";"Barracks";221;1
"Unit";"Marine";"Barracks";221;1
"Unit";"Marine";"Barracks";221;1
"Unit";"Marine";"Barracks";221;1
"Unit";"Marine";"Barracks";221;1
"Unit";"Marine";"Barracks";225;1
"Unit";"Marine";"Barracks";225;1
"Unit";"Marine";"Barracks";225;1
"Unit";"Marine";"Barracks";225;1
"Unit";"Marine";"Barracks";225;1
"Unit";"Marine";"Barracks";225;1
"Unit";"Marine";"Barracks";225;1
"Unit";"Marine";"Barracks";225;1
"Unit";"Marine";"Barracks";225;1
"Unit";"Marine";"Barracks";225;1
"Unit";"Marine";"Barracks";226;1
"Unit";"Marine";"Barracks";240;1
"Unit";"Marine";"Barracks";240;1
"Unit";"Marine";"Barracks";240;1
"Unit";"Marine";"Barracks";240;1
"Unit";"Marine";"Barracks";240;1
"Unit";"Marine";"Barracks";240;1
"Unit";"Marine";"Barracks";240;1
"Unit";"Marine";"Barracks";240;1
"Unit";"Marine";"Barracks";240;1
"Unit";"Marine";"Barracks";240;1
"Unit";"Marine";"Barracks";242;1
"Unit";"Medivac";"Starport";242;2
"Unit";"Medivac";"Starport";242;2
"Unit";"Marine";"Barracks";253;1
"Unit";"Marine";"Barracks";253;1
"Unit";"Marine";"Barracks";253;1
"Unit";"Marine";"Barracks";253;1
"Unit";"Marine";"Barracks";253;1
"Unit";"Marine";"Barracks";253;1
"Unit";"Marine";"Barracks";253;1
"Unit";"Marine";"Barracks";253;1
"Unit";"Marine";"Barracks";253;1
"Unit";"Marine";"Barracks";253;1
"Unit";"Marine";"Barracks";253;1
"Unit";"Marine";"Barracks";253;1
"Building";"Starport";NA;253;0
"Building";"Starport";NA;253;0
"Unit";"Marine";"Barracks";269;1
"Unit";"Medivac";"Starport";269;2
"Upgrade";"TerranInfantryArmorsLevel3";"EngineeringBay";231;0
"Upgrade";"TerranInfantryWeaponsLevel3";"EngineeringBay";241;0
"Unit";"Marine";"Barracks";272;1
"Unit";"Marine";"Barracks";272;1
"Unit";"Marine";"Barracks";272;1
"Unit";"Marine";"Barracks";272;1
"Unit";"Marine";"Barracks";272;1
"Unit";"Marine";"Barracks";272;1
"Unit";"Marine";"Barracks";272;1
"Unit";"Marine";"Barracks";272;1
"Unit";"Marine";"Barracks";272;1
"Unit";"Marine";"Barracks";272;1
"Unit";"Marine";"Barracks";272;1
"Unit";"Marine";"Barracks";272;1
"Unit";"Marine";"Barracks";272;1
"Unit";"Marine";"Barracks";272;1
"Unit";"Medivac";"Starport";272;2
"Unit";"Medivac";"Starport";272;2
"Unit";"Marine";"Barracks";272;1
"Unit";"Marine";"Barracks";272;1
"Unit";"Marine";"Barracks";273;1
"Unit";"Marine";"Barracks";273;1
"Unit";"Marine";"Barracks";275;1
"Unit";"Marine";"Barracks";275;1
"Unit";"Marine";"Barracks";277;1
"Unit";"Marine";"Barracks";277;1
"Unit";"Marine";"Barracks";279;1
"Building";"StarportTechLab";NA;284;0
"Building";"StarportReactor";NA;284;0
"Unit";"Marine";"Barracks";299;1
"Unit";"Marine";"Barracks";299;1
"Unit";"Marine";"Barracks";299;1
"Unit";"Marine";"Barracks";299;1
"Unit";"Marine";"Barracks";299;1
"Unit";"Marine";"Barracks";299;1
"Unit";"Marine";"Barracks";299;1
"Unit";"Marine";"Barracks";299;1
"Unit";"Marine";"Barracks";299;1
"Unit";"Marine";"Barracks";299;1
"Unit";"Marine";"Barracks";299;1
"Unit";"Marine";"Barracks";299;1
"Unit";"Marine";"Barracks";311;1
"Building";"CommandCenter";NA;284;0
"Unit";"Marine";"Barracks";312;1
"Unit";"Marine";"Barracks";312;1
"Unit";"Marine";"Barracks";312;1
"Unit";"Marine";"Barracks";312;1
"Unit";"Marine";"Barracks";312;1
"Unit";"Marine";"Barracks";312;1
"Unit";"Marine";"Barracks";317;1
