"type";"unit_name";"on_building";"total_supply_lag";"supply"
"Unit";"Overlord";"Larva";13;0
"Building";"Hatchery";NA;18;0
"Building";"Extractor";NA;19;0
"Building";"SpawningPool";NA;19;0
"Unit";"Overlord";"Larva";21;0
"Unit";"Queen";"Hatchery";23;2
"Unit";"Zergling";"Larva";25;1
"Unit";"Zergling";"Larva";26;1
"Unit";"Queen";"Hatchery";27;2
"Unit";"Zergling";"Larva";29;1
"Unit";"Zergling";"Larva";30;1
"Building";"Hatchery";NA;35;0
"Building";"CreepTumorQueen";NA;38;0
"Unit";"Queen";"Hatchery";39;2
"Unit";"Overlord";"Larva";41;0
"Unit";"Overlord";"Larva";42;0
"Building";"CreepTumor";NA;42;0
"Building";"CreepTumorQueen";NA;49;0
"Building";"RoachWarren";NA;49;0
"Building";"Extractor";NA;49;0
"Building";"Extractor";NA;52;0
"Building";"CreepTumor";NA;56;0
"Unit";"Overlord";"Larva";56;0
"Unit";"Overlord";"Larva";62;0
"Unit";"Overlord";"Larva";62;0
"Building";"SporeCrawler";NA;62;0
"Unit";"Roach";"Larva";66;2
"Unit";"Overlord";"Larva";68;0
"Unit";"Overlord";"Larva";68;0
"Unit";"Roach";"Larva";68;2
"Unit";"Roach";"Larva";70;2
"Unit";"Roach";"Larva";72;2
"Unit";"Roach";"Larva";74;2
"Unit";"Roach";"Larva";76;2
"Unit";"Roach";"Larva";78;2
"Building";"CreepTumor";NA;80;0
"Building";"CreepTumor";NA;80;0
"Unit";"Roach";"Larva";80;2
"Unit";"Roach";"Larva";82;2
"Unit";"Overlord";"Larva";84;0
"Unit";"Roach";"Larva";84;2
"Unit";"Roach";"Larva";86;2
"Upgrade";"GlialReconstitution";"RoachWarren";88;0
"Unit";"Roach";"Larva";89;2
"Unit";"Roach";"Larva";91;2
"Unit";"Roach";"Larva";93;2
"Unit";"Roach";"Larva";95;2
"Unit";"Overlord";"Larva";98;0
"Building";"CreepTumor";NA;98;0
"Unit";"Overlord";"Larva";98;0
"Unit";"Roach";"Larva";98;2
"Unit";"Roach";"Larva";100;2
"Unit";"Roach";"Larva";102;2
"Building";"EvolutionChamber";NA;106;0
"Building";"Extractor";NA;112;0
"Building";"HydraliskDen";NA;116;0
"Unit";"Zergling";"Larva";116;1
"Unit";"Zergling";"Larva";117;1
"Building";"CreepTumor";NA;118;0
"Unit";"Overlord";"Larva";118;0
"Unit";"Roach";"Larva";118;2
"Unit";"Roach";"Larva";120;2
"Unit";"Roach";"Larva";122;2
"Unit";"Roach";"Larva";124;2
"Unit";"Roach";"Larva";126;2
"Building";"CreepTumor";NA;128;0
"Unit";"Overlord";"Larva";128;0
"Unit";"Roach";"Larva";128;2
"Building";"Extractor";NA;130;0
"Building";"Extractor";NA;130;0
"Unit";"Overlord";"Larva";136;0
"Unit";"Roach";"Larva";136;2
"Unit";"Overlord";"Larva";138;0
"Building";"Hatchery";NA;138;0
"Unit";"Queen";"Hatchery";138;2
"Unit";"Overlord";"Larva";140;0
"Unit";"Hydralisk";"Larva";140;2
"Unit";"Hydralisk";"Larva";142;2
"Unit";"Hydralisk";"Larva";144;2
"Unit";"Hydralisk";"Larva";146;2
"Unit";"Hydralisk";"Larva";148;2
"Unit";"Hydralisk";"Larva";152;2
"Unit";"Hydralisk";"Larva";154;2
"Unit";"Hydralisk";"Larva";156;2
"Unit";"Hydralisk";"Larva";158;2
"Unit";"Zergling";"Larva";160;1
"Unit";"Zergling";"Larva";161;1
"Unit";"Hydralisk";"Larva";168;2
"Unit";"Hydralisk";"Larva";170;2
"Unit";"Hydralisk";"Larva";172;2
"Unit";"Hydralisk";"Larva";174;2
"Unit";"Overlord";"Larva";176;0
"Unit";"Overlord";"Larva";176;0
"Unit";"Zergling";"Larva";176;1
"Unit";"Zergling";"Larva";177;1
"Unit";"Overlord";"Larva";178;0
"Unit";"Hydralisk";"Larva";178;2
"Building";"CreepTumorQueen";NA;180;0
"Unit";"Overlord";"Larva";180;0
"Unit";"Overlord";"Larva";180;0
"Building";"CreepTumor";NA;180;0
"Unit";"Hydralisk";"Larva";180;2
"Unit";"Hydralisk";"Larva";182;2
"Unit";"Hydralisk";"Larva";184;2
"Unit";"Hydralisk";"Larva";186;2
"Unit";"Hydralisk";"Larva";188;2
"Unit";"Hydralisk";"Larva";190;2
"Unit";"Hydralisk";"Larva";192;2
"Unit";"Hydralisk";"Larva";194;2
"Unit";"Hydralisk";"Larva";196;2
"Unit";"Hydralisk";"Larva";198;2
"Unit";"Hydralisk";"Larva";200;2
"Building";"CreepTumor";NA;202;0
"Unit";"Hydralisk";"Larva";202;2
"Unit";"Hydralisk";"Larva";204;2
"Unit";"Hydralisk";"Larva";206;2
"Unit";"Hydralisk";"Larva";208;2
"Unit";"Hydralisk";"Larva";210;2
"Unit";"Hydralisk";"Larva";212;2
"Unit";"Hydralisk";"Larva";214;2
"Building";"CreepTumor";NA;216;0
"Unit";"Roach";"Larva";216;2
"Unit";"Roach";"Larva";218;2
"Unit";"Roach";"Larva";220;2
"Unit";"Roach";"Larva";222;2
"Unit";"Zergling";"Larva";224;1
"Unit";"Zergling";"Larva";225;1
"Building";"BanelingNest";NA;226;0
"Unit";"Zergling";"Larva";226;1
"Unit";"Zergling";"Larva";227;1
"Unit";"Zergling";"Larva";228;1
"Unit";"Zergling";"Larva";229;1
"Unit";"Zergling";"Larva";230;1
"Unit";"Zergling";"Larva";231;1
"Unit";"Zergling";"Larva";232;1
"Unit";"Zergling";"Larva";233;1
"Unit";"Hydralisk";"Larva";234;2
"Unit";"Hydralisk";"Larva";236;2
"Unit";"Hydralisk";"Larva";238;2
"Unit";"Hydralisk";"Larva";240;2
"Unit";"Hydralisk";"Larva";242;2
"Unit";"Hydralisk";"Larva";244;2
"Unit";"Hydralisk";"Larva";246;2
"Unit";"Zergling";"Larva";248;1
"Unit";"Zergling";"Larva";249;1
"Unit";"Zergling";"Larva";250;1
"Unit";"Zergling";"Larva";251;1
"Unit";"Hydralisk";"Larva";252;2
"Upgrade";"SprayZerg";NA;254;0
"Upgrade";"SprayZerg";NA;254;0
"Upgrade";"SprayZerg";NA;254;0
"Upgrade";"zerglingmovementspeed";NA;254;0
"Upgrade";"SprayZerg";NA;254;0
"Upgrade";"SprayZerg";NA;254;0
"Upgrade";"SprayZerg";NA;254;0
"Upgrade";"EvolveMuscularAugments";NA;254;0
"Upgrade";"ZergMissileWeaponsLevel1";NA;254;0
