"type";"unit_name";"on_building";"total_supply_lag";"supply"
"Unit";"Overlord";"Larva";13;0
"Building";"Extractor";NA;18;0
"Building";"SpawningPool";NA;18;0
"Building";"Hatchery";NA;19;0
"Unit";"Queen";"Hatchery";22;2
"Unit";"Overlord";"Larva";24;0
"Unit";"Zergling";"Larva";24;1
"Unit";"Zergling";"Larva";25;1
"Unit";"Queen";"Hatchery";28;2
"Unit";"Zergling";"Larva";30;1
"Unit";"Zergling";"Larva";31;1
"Building";"Hatchery";NA;36;0
"Unit";"Overlord";"Larva";40;0
"Unit";"Queen";"Hatchery";40;2
"Unit";"Overlord";"Larva";47;0
"Unit";"Overlord";"Larva";51;0
"Building";"RoachWarren";NA;51;0
"Building";"CreepTumorQueen";NA;53;0
"Unit";"Zergling";"Larva";54;1
"Unit";"Zergling";"Larva";55;1
"Unit";"Zergling";"Larva";56;1
"Unit";"Zergling";"Larva";57;1
"Unit";"Zergling";"Larva";58;1
"Unit";"Zergling";"Larva";59;1
"Unit";"Zergling";"Larva";60;1
"Unit";"Zergling";"Larva";61;1
"Unit";"Zergling";"Larva";62;1
"Unit";"Zergling";"Larva";63;1
"Building";"Extractor";NA;65;0
"Building";"SporeCrawler";NA;65;0
"Building";"SporeCrawler";NA;65;0
"Building";"CreepTumor";NA;68;0
"Unit";"Overlord";"Larva";68;0
"Building";"Extractor";NA;68;0
"Unit";"Overlord";"Larva";71;0
"Unit";"Roach";"Larva";71;2
"Unit";"Roach";"Larva";73;2
"Unit";"Roach";"Larva";75;2
"Unit";"Roach";"Larva";77;2
"Unit";"Roach";"Larva";79;2
"Unit";"Roach";"Larva";90;2
"Unit";"Roach";"Larva";92;2
"Upgrade";"GlialReconstitution";"RoachWarren";94;0
"Unit";"Overlord";"Larva";94;0
"Unit";"Overlord";"Larva";94;0
"Unit";"Roach";"Larva";94;2
"Unit";"Roach";"Larva";96;2
"Unit";"Roach";"Larva";98;2
"Unit";"Overlord";"Larva";100;0
"Unit";"Roach";"Larva";100;2
"Unit";"Roach";"Larva";102;2
"Unit";"Roach";"Larva";104;2
"Unit";"Roach";"Larva";106;2
"Unit";"Roach";"Larva";108;2
"Unit";"Roach";"Larva";110;2
"Unit";"Roach";"Larva";112;2
"Unit";"Overlord";"Larva";114;0
"Unit";"Overlord";"Larva";114;0
"Building";"Extractor";NA;125;0
"Building";"Spire";NA;129;0
"Building";"EvolutionChamber";NA;129;0
"Building";"Extractor";NA;130;0
"Building";"Extractor";NA;130;0
"Building";"SporeCrawler";NA;131;0
"Unit";"Overlord";"Larva";138;0
"Building";"Hatchery";NA;138;0
"Building";"Hatchery";NA;140;0
"Unit";"Roach";"Larva";145;2
"Unit";"Roach";"Larva";147;2
"Unit";"Roach";"Larva";149;2
"Unit";"Roach";"Larva";151;2
"Unit";"Roach";"Larva";153;2
"Unit";"Roach";"Larva";155;2
"Unit";"Roach";"Larva";157;2
"Unit";"Roach";"Larva";159;2
"Unit";"Overlord";"Larva";164;0
"Unit";"Overlord";"Larva";164;0
"Unit";"Overlord";"Larva";164;0
"Building";"Extractor";NA;164;0
"Building";"SporeCrawler";NA;171;0
"Building";"BanelingNest";NA;171;0
"Unit";"Corruptor";"Larva";176;2
"Unit";"Corruptor";"Larva";178;2
"Unit";"Corruptor";"Larva";180;2
"Unit";"Corruptor";"Larva";182;2
"Unit";"Corruptor";"Larva";184;2
"Unit";"Corruptor";"Larva";186;2
"Unit";"Corruptor";"Larva";188;2
"Unit";"Corruptor";"Larva";190;2
"Unit";"Corruptor";"Larva";192;2
"Unit";"Corruptor";"Larva";194;2
"Unit";"Corruptor";"Larva";196;2
"Unit";"Corruptor";"Larva";198;2
"Unit";"Overlord";"Larva";201;0
"Unit";"Overlord";"Larva";201;0
"Building";"Spire";NA;201;0
"Building";"CreepTumor";NA;201;0
"Building";"SpineCrawler";NA;201;0
"Building";"SpineCrawler";NA;201;0
"Unit";"Corruptor";"Larva";201;2
"Unit";"Corruptor";"Larva";203;2
"Unit";"Corruptor";"Larva";205;2
"Building";"Hatchery";NA;207;0
"Upgrade";"Burrow";"Hatchery";207;0
"Unit";"Corruptor";"Larva";212;2
"Unit";"Corruptor";"Larva";214;2
"Unit";"Corruptor";"Larva";216;2
"Unit";"Overlord";"Larva";218;0
"Unit";"Overlord";"Larva";218;0
"Unit";"Overlord";"Larva";218;0
"Unit";"Roach";"Larva";220;2
"Unit";"Roach";"Larva";222;2
"Unit";"Roach";"Larva";224;2
"Unit";"Roach";"Larva";226;2
"Unit";"Overlord";"Larva";228;0
"Unit";"Zergling";"Larva";228;1
"Unit";"Zergling";"Larva";229;1
"Unit";"Zergling";"Larva";230;1
"Unit";"Zergling";"Larva";231;1
"Unit";"Zergling";"Larva";232;1
"Unit";"Zergling";"Larva";233;1
"Unit";"Zergling";"Larva";234;1
"Unit";"Zergling";"Larva";235;1
"Unit";"Zergling";"Larva";236;1
"Unit";"Zergling";"Larva";237;1
"Unit";"Zergling";"Larva";238;1
"Unit";"Zergling";"Larva";239;1
"Unit";"Zergling";"Larva";240;1
"Unit";"Zergling";"Larva";241;1
"Unit";"Zergling";"Larva";242;1
"Unit";"Zergling";"Larva";243;1
"Unit";"Zergling";"Larva";244;1
"Unit";"Zergling";"Larva";245;1
"Unit";"Zergling";"Larva";246;1
"Unit";"Zergling";"Larva";247;1
"Unit";"Zergling";"Larva";248;1
"Unit";"Zergling";"Larva";249;1
"Unit";"Zergling";"Larva";250;1
"Unit";"Zergling";"Larva";251;1
"Unit";"Corruptor";"Larva";252;2
"Unit";"Corruptor";"Larva";254;2
"Unit";"Corruptor";"Larva";256;2
"Unit";"Corruptor";"Larva";258;2
"Unit";"Corruptor";"Larva";260;2
"Unit";"Baneling";"Zergling";267;0
"Unit";"Baneling";"Zergling";267;0
"Unit";"Baneling";"Zergling";267;0
"Unit";"Baneling";"Zergling";267;0
"Unit";"Baneling";"Zergling";267;0
"Unit";"Baneling";"Zergling";267;0
"Unit";"Baneling";"Zergling";267;0
"Unit";"Baneling";"Zergling";267;0
"Building";"Extractor";NA;267;0
"Unit";"Zergling";"Larva";267;1
"Unit";"Zergling";"Larva";268;1
"Unit";"Zergling";"Larva";269;1
"Unit";"Zergling";"Larva";270;1
"Unit";"Zergling";"Larva";271;1
"Unit";"Zergling";"Larva";272;1
"Unit";"Zergling";"Larva";273;1
"Unit";"Zergling";"Larva";274;1
"Unit";"Zergling";"Larva";275;1
"Unit";"Zergling";"Larva";276;1
"Unit";"Zergling";"Larva";277;1
"Unit";"Zergling";"Larva";278;1
"Unit";"Zergling";"Larva";279;1
"Unit";"Zergling";"Larva";280;1
"Unit";"Zergling";"Larva";281;1
"Unit";"Zergling";"Larva";282;1
"Unit";"Zergling";"Larva";283;1
"Unit";"Zergling";"Larva";284;1
"Unit";"Zergling";"Larva";285;1
"Unit";"Zergling";"Larva";286;1
"Unit";"Zergling";"Larva";287;1
"Unit";"Zergling";"Larva";288;1
"Unit";"Zergling";"Larva";289;1
"Unit";"Zergling";"Larva";290;1
"Unit";"Zergling";"Larva";291;1
"Unit";"Zergling";"Larva";292;1
"Building";"Extractor";NA;293;0
"Unit";"Zergling";"Larva";293;1
"Unit";"Zergling";"Larva";294;1
"Unit";"Zergling";"Larva";295;1
"Unit";"Zergling";"Larva";296;1
"Unit";"Zergling";"Larva";297;1
"Unit";"Zergling";"Larva";298;1
"Unit";"Zergling";"Larva";299;1
"Unit";"Zergling";"Larva";300;1
"Unit";"Zergling";"Larva";301;1
"Unit";"Zergling";"Larva";302;1
"Unit";"Zergling";"Larva";303;1
"Unit";"Zergling";"Larva";304;1
"Unit";"Zergling";"Larva";305;1
"Unit";"Zergling";"Larva";306;1
"Unit";"Zergling";"Larva";307;1
"Unit";"Zergling";"Larva";308;1
"Unit";"Zergling";"Larva";309;1
"Unit";"Zergling";"Larva";310;1
"Unit";"Zergling";"Larva";311;1
"Unit";"Zergling";"Larva";312;1
"Unit";"Zergling";"Larva";313;1
"Unit";"Zergling";"Larva";314;1
"Unit";"Zergling";"Larva";315;1
"Unit";"Zergling";"Larva";316;1
"Unit";"Queen";"Hatchery";317;2
"Unit";"Overlord";"Larva";325;0
"Unit";"Overlord";"Larva";325;0
"Unit";"Overlord";"Larva";325;0
"Building";"InfestationPit";NA;326;0
"Unit";"Corruptor";"Larva";326;2
"Unit";"Corruptor";"Larva";328;2
"Unit";"Zergling";"Larva";330;1
"Unit";"Zergling";"Larva";331;1
"Unit";"Zergling";"Larva";332;1
"Unit";"Zergling";"Larva";333;1
"Unit";"Zergling";"Larva";334;1
"Unit";"Zergling";"Larva";335;1
"Unit";"Zergling";"Larva";336;1
"Unit";"Zergling";"Larva";337;1
"Unit";"Baneling";"Zergling";338;0
"Unit";"Baneling";"Zergling";338;0
"Unit";"Baneling";"Zergling";338;0
"Unit";"Baneling";"Zergling";338;0
"Unit";"Baneling";"Zergling";338;0
"Unit";"Baneling";"Zergling";338;0
"Unit";"Baneling";"Zergling";338;0
"Unit";"Baneling";"Zergling";338;0
"Unit";"Baneling";"Zergling";338;0
"Building";"SporeCrawler";NA;338;0
"Building";"SpineCrawler";NA;341;0
"Building";"SpineCrawler";NA;342;0
"Building";"Hatchery";NA;342;0
"Unit";"Zergling";"Larva";342;1
"Unit";"Zergling";"Larva";343;1
"Unit";"Zergling";"Larva";344;1
"Unit";"Zergling";"Larva";345;1
"Unit";"Zergling";"Larva";346;1
"Unit";"Zergling";"Larva";347;1
"Unit";"Zergling";"Larva";348;1
"Unit";"Zergling";"Larva";349;1
"Unit";"Zergling";"Larva";350;1
"Unit";"Zergling";"Larva";351;1
"Unit";"Zergling";"Larva";352;1
"Unit";"Zergling";"Larva";353;1
"Unit";"Zergling";"Larva";354;1
"Unit";"Zergling";"Larva";355;1
"Unit";"Zergling";"Larva";356;1
"Unit";"Zergling";"Larva";357;1
"Unit";"Zergling";"Larva";358;1
"Unit";"Zergling";"Larva";359;1
"Unit";"Zergling";"Larva";360;1
"Unit";"Zergling";"Larva";361;1
"Unit";"Zergling";"Larva";362;1
"Unit";"Zergling";"Larva";363;1
"Unit";"Zergling";"Larva";364;1
"Unit";"Zergling";"Larva";365;1
"Unit";"Zergling";"Larva";366;1
"Unit";"Zergling";"Larva";367;1
"Unit";"Zergling";"Larva";368;1
"Unit";"Zergling";"Larva";369;1
"Unit";"Zergling";"Larva";370;1
"Unit";"Zergling";"Larva";371;1
"Unit";"Zergling";"Larva";372;1
"Unit";"Zergling";"Larva";373;1
"Unit";"Zergling";"Larva";374;1
"Unit";"Zergling";"Larva";375;1
"Unit";"Zergling";"Larva";376;1
"Unit";"Zergling";"Larva";377;1
"Unit";"Zergling";"Larva";378;1
"Unit";"Zergling";"Larva";379;1
"Building";"SporeCrawler";NA;390;0
"Building";"SpineCrawler";NA;390;0
"Building";"SpineCrawler";NA;390;0
"Building";"SpineCrawler";NA;394;0
"Building";"SporeCrawler";NA;394;0
"Building";"SpineCrawler";NA;394;0
"Unit";"Zergling";"Larva";394;1
"Unit";"Zergling";"Larva";395;1
"Unit";"Zergling";"Larva";396;1
"Unit";"Zergling";"Larva";397;1
"Unit";"Zergling";"Larva";398;1
"Unit";"Zergling";"Larva";399;1
"Unit";"Zergling";"Larva";400;1
"Unit";"Zergling";"Larva";401;1
"Unit";"Zergling";"Larva";402;1
"Unit";"Zergling";"Larva";403;1
"Unit";"Zergling";"Larva";404;1
"Unit";"Zergling";"Larva";405;1
"Unit";"Zergling";"Larva";406;1
"Unit";"Zergling";"Larva";407;1
"Unit";"Zergling";"Larva";408;1
"Unit";"Zergling";"Larva";409;1
"Unit";"Baneling";"Zergling";410;0
"Unit";"Baneling";"Zergling";410;0
"Unit";"Baneling";"Zergling";410;0
"Unit";"Baneling";"Zergling";410;0
"Unit";"Baneling";"Zergling";410;0
"Unit";"Baneling";"Zergling";410;0
"Unit";"Baneling";"Zergling";410;0
"Unit";"Baneling";"Zergling";410;0
"Unit";"Baneling";"Zergling";410;0
"Unit";"Baneling";"Zergling";410;0
"Unit";"Baneling";"Zergling";410;0
"Unit";"Baneling";"Zergling";410;0
"Unit";"Baneling";"Zergling";410;0
"Unit";"Baneling";"Zergling";410;0
"Unit";"Baneling";"Zergling";410;0
"Unit";"Baneling";"Zergling";410;0
"Unit";"Baneling";"Zergling";410;0
"Unit";"Baneling";"Zergling";410;0
"Unit";"Baneling";"Zergling";410;0
"Unit";"Baneling";"Zergling";410;0
"Unit";"Baneling";"Zergling";410;0
"Unit";"Baneling";"Zergling";410;0
"Unit";"Baneling";"Zergling";410;0
"Unit";"Baneling";"Zergling";410;0
"Unit";"Baneling";"Zergling";410;0
"Unit";"Baneling";"Zergling";410;0
"Unit";"Baneling";"Zergling";410;0
"Unit";"Baneling";"Zergling";410;0
"Unit";"Baneling";"Zergling";410;0
"Unit";"Baneling";"Zergling";410;0
"Unit";"Baneling";"Zergling";410;0
"Unit";"Baneling";"Zergling";410;0
"Unit";"Baneling";"Zergling";410;0
"Unit";"Baneling";"Zergling";410;0
"Unit";"Baneling";"Zergling";410;0
"Unit";"Baneling";"Zergling";410;0
"Unit";"Baneling";"Zergling";410;0
"Unit";"Baneling";"Zergling";410;0
"Unit";"Baneling";"Zergling";410;0
"Unit";"Baneling";"Zergling";410;0
"Unit";"Baneling";"Zergling";410;0
"Unit";"Baneling";"Zergling";410;0
"Unit";"Baneling";"Zergling";410;0
"Upgrade";"SprayZerg";NA;410;0
"Upgrade";"SprayZerg";NA;410;0
"Upgrade";"SprayZerg";NA;410;0
"Upgrade";"zerglingmovementspeed";NA;410;0
"Upgrade";"SprayZerg";NA;410;0
"Upgrade";"SprayZerg";NA;410;0
"Upgrade";"SprayZerg";NA;410;0
"Upgrade";"SprayZerg";NA;410;0
"Upgrade";"SprayZerg";NA;410;0
"Upgrade";"SprayZerg";NA;410;0
"Upgrade";"ZergMeleeWeaponsLevel1";NA;410;0
"Upgrade";"ZergFlyerArmorsLevel1";NA;410;0
"Upgrade";"overlordspeed";NA;410;0
"Upgrade";"SprayZerg";NA;410;0
"Upgrade";"ZergFlyerWeaponsLevel1";NA;410;0
"Upgrade";"ZergMeleeWeaponsLevel2";NA;410;0
"Upgrade";"SprayZerg";NA;410;0
"Upgrade";"CentrificalHooks";NA;410;0
"Upgrade";"ZergFlyerArmorsLevel2";NA;410;0
"Upgrade";"SprayZerg";NA;410;0
