"type";"unit_name";"on_building";"total_supply_lag";"supply"
"Unit";"Overlord";"Larva";13;0
"Building";"Extractor";NA;17;0
"Building";"SpawningPool";NA;17;0
"Building";"Hatchery";NA;19;0
"Unit";"Queen";"Hatchery";21;2
"Unit";"Overlord";"Larva";23;0
"Unit";"Zergling";"Larva";23;1
"Unit";"Zergling";"Larva";24;1
"Unit";"Zergling";"Larva";25;1
"Unit";"Zergling";"Larva";26;1
"Unit";"Zergling";"Larva";27;1
"Unit";"Zergling";"Larva";28;1
"Unit";"Queen";"Hatchery";29;2
"Unit";"Overlord";"Larva";32;0
"Building";"Extractor";NA;44;0
"Building";"SporeCrawler";NA;50;0
"Building";"SporeCrawler";NA;52;0
"Building";"Hatchery";NA;52;0
"Building";"Spire";NA;56;0
"Unit";"Overlord";"Larva";58;0
"Unit";"Overlord";"Larva";58;0
"Unit";"Overlord";"Larva";58;0
"Unit";"Overlord";"Larva";58;0
"Building";"Extractor";NA;58;0
"Building";"Extractor";NA;59;0
"Unit";"Overlord";"Larva";65;0
"Building";"HydraliskDen";NA;65;0
"Building";"EvolutionChamber";NA;65;0
"Unit";"Queen";"Hatchery";74;2
"Building";"SporeCrawler";NA;76;0
"Unit";"Mutalisk";"Larva";76;2
"Unit";"Mutalisk";"Larva";78;2
"Unit";"Mutalisk";"Larva";80;2
"Unit";"Mutalisk";"Larva";82;2
"Unit";"Mutalisk";"Larva";89;2
"Unit";"Overlord";"Larva";91;0
"Unit";"Mutalisk";"Larva";91;2
"Unit";"Mutalisk";"Larva";93;2
"Building";"Extractor";NA;97;0
"Building";"Extractor";NA;97;0
"Unit";"Mutalisk";"Larva";104;2
"Unit";"Overlord";"Larva";106;0
"Unit";"Overlord";"Larva";106;0
"Unit";"Overlord";"Larva";106;0
"Unit";"Overlord";"Larva";106;0
"Unit";"Overlord";"Larva";106;0
"Unit";"Overlord";"Larva";106;0
"Unit";"Corruptor";"Larva";106;2
"Unit";"Corruptor";"Larva";108;2
"Unit";"Corruptor";"Larva";110;2
"Unit";"Corruptor";"Larva";112;2
"Unit";"Corruptor";"Larva";114;2
"Unit";"Corruptor";"Larva";116;2
"Unit";"Corruptor";"Larva";118;2
"Unit";"Mutalisk";"Larva";126;2
"Unit";"Overlord";"Larva";128;0
"Unit";"Mutalisk";"Larva";128;2
"Unit";"Mutalisk";"Larva";137;2
"Unit";"Mutalisk";"Larva";139;2
"Unit";"Mutalisk";"Larva";141;2
"Building";"Hatchery";NA;143;0
"Unit";"Overlord";"Larva";143;0
"Building";"BanelingNest";NA;143;0
"Unit";"Zergling";"Larva";143;1
"Unit";"Zergling";"Larva";144;1
"Unit";"Zergling";"Larva";145;1
"Unit";"Zergling";"Larva";146;1
"Unit";"Zergling";"Larva";147;1
"Unit";"Zergling";"Larva";148;1
"Unit";"Zergling";"Larva";149;1
"Unit";"Zergling";"Larva";150;1
"Unit";"Zergling";"Larva";151;1
"Unit";"Zergling";"Larva";152;1
"Unit";"Zergling";"Larva";153;1
"Unit";"Zergling";"Larva";154;1
"Unit";"Zergling";"Larva";155;1
"Unit";"Zergling";"Larva";156;1
"Unit";"Mutalisk";"Larva";157;2
"Unit";"Mutalisk";"Larva";159;2
"Unit";"Mutalisk";"Larva";161;2
"Unit";"Mutalisk";"Larva";163;2
"Unit";"Mutalisk";"Larva";165;2
"Unit";"Mutalisk";"Larva";167;2
"Unit";"Mutalisk";"Larva";169;2
"Unit";"Mutalisk";"Larva";171;2
"Unit";"Zergling";"Larva";173;1
"Unit";"Zergling";"Larva";174;1
"Unit";"Zergling";"Larva";175;1
"Unit";"Zergling";"Larva";176;1
"Unit";"Zergling";"Larva";177;1
"Unit";"Zergling";"Larva";178;1
"Unit";"Zergling";"Larva";179;1
"Unit";"Zergling";"Larva";180;1
"Unit";"Zergling";"Larva";181;1
"Unit";"Zergling";"Larva";182;1
"Unit";"Zergling";"Larva";183;1
"Unit";"Zergling";"Larva";184;1
"Unit";"Overlord";"Larva";185;0
"Unit";"Mutalisk";"Larva";185;2
"Unit";"Mutalisk";"Larva";187;2
"Unit";"Mutalisk";"Larva";189;2
"Unit";"Zergling";"Larva";191;1
"Unit";"Zergling";"Larva";192;1
"Unit";"Zergling";"Larva";193;1
"Unit";"Zergling";"Larva";194;1
"Unit";"Zergling";"Larva";195;1
"Unit";"Zergling";"Larva";196;1
"Unit";"Zergling";"Larva";197;1
"Unit";"Zergling";"Larva";198;1
"Unit";"Zergling";"Larva";199;1
"Unit";"Zergling";"Larva";200;1
"Unit";"Zergling";"Larva";201;1
"Unit";"Zergling";"Larva";202;1
"Unit";"Zergling";"Larva";203;1
"Unit";"Zergling";"Larva";204;1
"Unit";"Overlord";"Larva";207;0
"Building";"Extractor";NA;207;0
"Building";"Hatchery";NA;207;0
"Building";"SporeCrawler";NA;207;0
"Building";"SporeCrawler";NA;207;0
"Unit";"Queen";"Hatchery";207;2
"Unit";"Zergling";"Larva";209;1
"Unit";"Zergling";"Larva";210;1
"Unit";"Zergling";"Larva";211;1
"Unit";"Zergling";"Larva";212;1
"Unit";"Zergling";"Larva";213;1
"Unit";"Zergling";"Larva";214;1
"Building";"InfestationPit";NA;215;0
"Building";"Hatchery";NA;215;0
"Unit";"Mutalisk";"Larva";215;2
"Unit";"Mutalisk";"Larva";217;2
"Unit";"Mutalisk";"Larva";219;2
"Unit";"Mutalisk";"Larva";221;2
"Unit";"Mutalisk";"Larva";223;2
"Unit";"Mutalisk";"Larva";225;2
"Unit";"Mutalisk";"Larva";227;2
"Unit";"Mutalisk";"Larva";229;2
"Unit";"Overlord";"Larva";231;0
"Unit";"Overlord";"Larva";231;0
"Unit";"Mutalisk";"Larva";238;2
"Unit";"Mutalisk";"Larva";240;2
"Building";"Extractor";NA;242;0
"Building";"Extractor";NA;242;0
"Unit";"Zergling";"Larva";242;1
"Unit";"Zergling";"Larva";243;1
"Unit";"Zergling";"Larva";244;1
"Unit";"Zergling";"Larva";245;1
"Unit";"Zergling";"Larva";246;1
"Unit";"Zergling";"Larva";247;1
"Unit";"Zergling";"Larva";248;1
"Unit";"Zergling";"Larva";249;1
"Unit";"Zergling";"Larva";250;1
"Unit";"Zergling";"Larva";251;1
"Unit";"Zergling";"Larva";252;1
"Unit";"Zergling";"Larva";253;1
"Unit";"Zergling";"Larva";254;1
"Unit";"Zergling";"Larva";255;1
"Unit";"Zergling";"Larva";256;1
"Unit";"Zergling";"Larva";257;1
"Unit";"Zergling";"Larva";258;1
"Unit";"Zergling";"Larva";259;1
"Building";"Hatchery";NA;260;0
"Unit";"Mutalisk";"Larva";260;2
"Unit";"Mutalisk";"Larva";263;2
"Unit";"Mutalisk";"Larva";265;2
"Unit";"Mutalisk";"Larva";267;2
"Unit";"Mutalisk";"Larva";269;2
"Unit";"Zergling";"Larva";271;1
"Unit";"Zergling";"Larva";272;1
"Unit";"Zergling";"Larva";273;1
"Unit";"Zergling";"Larva";274;1
"Unit";"Zergling";"Larva";275;1
"Unit";"Zergling";"Larva";276;1
"Unit";"Zergling";"Larva";277;1
"Unit";"Zergling";"Larva";278;1
"Unit";"Zergling";"Larva";279;1
"Unit";"Zergling";"Larva";280;1
"Unit";"Zergling";"Larva";281;1
"Unit";"Zergling";"Larva";282;1
"Unit";"Zergling";"Larva";283;1
"Unit";"Zergling";"Larva";284;1
"Unit";"Overlord";"Larva";299;0
"Unit";"Overlord";"Larva";299;0
"Unit";"Corruptor";"Larva";299;2
"Unit";"Corruptor";"Larva";301;2
"Unit";"Corruptor";"Larva";303;2
"Unit";"Overlord";"Larva";305;0
"Unit";"Zergling";"Larva";305;1
"Unit";"Zergling";"Larva";306;1
"Unit";"Zergling";"Larva";307;1
"Unit";"Zergling";"Larva";308;1
"Unit";"Zergling";"Larva";309;1
"Unit";"Zergling";"Larva";310;1
"Unit";"Zergling";"Larva";311;1
"Unit";"Zergling";"Larva";312;1
"Unit";"Zergling";"Larva";313;1
"Unit";"Zergling";"Larva";314;1
"Unit";"Zergling";"Larva";315;1
"Unit";"Zergling";"Larva";316;1
"Unit";"Zergling";"Larva";317;1
"Unit";"Zergling";"Larva";318;1
"Unit";"Overlord";"Larva";319;0
"Unit";"Zergling";"Larva";319;1
"Unit";"Zergling";"Larva";320;1
"Unit";"Zergling";"Larva";321;1
"Unit";"Zergling";"Larva";322;1
"Unit";"Zergling";"Larva";323;1
"Unit";"Zergling";"Larva";324;1
"Unit";"Zergling";"Larva";325;1
"Unit";"Zergling";"Larva";326;1
"Unit";"Zergling";"Larva";327;1
"Unit";"Zergling";"Larva";328;1
"Unit";"Zergling";"Larva";329;1
"Unit";"Zergling";"Larva";330;1
"Unit";"Zergling";"Larva";331;1
"Unit";"Zergling";"Larva";332;1
"Unit";"Zergling";"Larva";333;1
"Unit";"Zergling";"Larva";334;1
"Unit";"Zergling";"Larva";335;1
"Unit";"Zergling";"Larva";336;1
"Unit";"Zergling";"Larva";337;1
"Unit";"Zergling";"Larva";338;1
"Unit";"Zergling";"Larva";339;1
"Unit";"Zergling";"Larva";340;1
"Unit";"Zergling";"Larva";341;1
"Unit";"Zergling";"Larva";342;1
"Unit";"Zergling";"Larva";343;1
"Unit";"Zergling";"Larva";344;1
"Unit";"Zergling";"Larva";345;1
"Unit";"Zergling";"Larva";346;1
"Unit";"Zergling";"Larva";347;1
"Unit";"Zergling";"Larva";348;1
"Unit";"Zergling";"Larva";349;1
"Unit";"Zergling";"Larva";350;1
"Unit";"Zergling";"Larva";351;1
"Unit";"Zergling";"Larva";352;1
"Unit";"Zergling";"Larva";353;1
"Unit";"Zergling";"Larva";354;1
"Unit";"Zergling";"Larva";355;1
"Unit";"Zergling";"Larva";356;1
"Upgrade";"SprayZerg";NA;357;0
"Upgrade";"SprayZerg";NA;357;0
"Upgrade";"zerglingmovementspeed";NA;357;0
"Upgrade";"SprayZerg";NA;357;0
"Upgrade";"SprayZerg";NA;357;0
"Upgrade";"ZergFlyerWeaponsLevel1";NA;357;0
"Upgrade";"SprayZerg";NA;357;0
"Upgrade";"SprayZerg";NA;357;0
"Upgrade";"SprayZerg";NA;357;0
"Upgrade";"ZergFlyerArmorsLevel1";NA;357;0
"Upgrade";"SprayZerg";NA;357;0
"Upgrade";"SprayZerg";NA;357;0
"Upgrade";"SprayZerg";NA;357;0
"Upgrade";"SprayZerg";NA;357;0
"Upgrade";"ZergFlyerWeaponsLevel2";NA;357;0
"Upgrade";"SprayZerg";NA;357;0
