"type";"unit_name";"on_building";"total_supply_lag";"supply"
"Building";"SpawningPool";NA;12;0
"Unit";"Overlord";"Larva";15;0
"Unit";"Zergling";"Larva";15;1
"Unit";"Zergling";"Larva";16;1
"Unit";"Zergling";"Larva";17;1
"Unit";"Zergling";"Larva";18;1
"Unit";"Zergling";"Larva";19;1
"Unit";"Zergling";"Larva";20;1
"Unit";"Zergling";"Larva";21;1
"Unit";"Zergling";"Larva";22;1
"Building";"Hatchery";NA;23;0
"Unit";"Zergling";"Larva";23;1
"Unit";"Zergling";"Larva";24;1
"Unit";"Queen";"Hatchery";25;2
"Unit";"Zergling";"Larva";27;1
"Unit";"Zergling";"Larva";28;1
"Unit";"Overlord";"Larva";29;0
"Building";"Extractor";NA;30;0
"Unit";"Queen";"Hatchery";31;2
"Unit";"Queen";"Hatchery";44;2
"Unit";"Zergling";"Larva";46;1
"Unit";"Zergling";"Larva";47;1
"Unit";"Zergling";"Larva";48;1
"Unit";"Zergling";"Larva";49;1
"Unit";"Zergling";"Larva";50;1
"Unit";"Zergling";"Larva";51;1
"Unit";"Zergling";"Larva";52;1
"Unit";"Zergling";"Larva";53;1
"Unit";"Zergling";"Larva";54;1
"Unit";"Zergling";"Larva";55;1
"Unit";"Overlord";"Larva";56;0
"Building";"Hatchery";NA;56;0
"Building";"CreepTumorQueen";NA;56;0
"Unit";"Overlord";"Larva";59;0
"Unit";"Zergling";"Larva";61;1
"Unit";"Zergling";"Larva";62;1
"Unit";"Zergling";"Larva";63;1
"Unit";"Zergling";"Larva";64;1
"Unit";"Zergling";"Larva";65;1
"Unit";"Zergling";"Larva";66;1
"Building";"SporeCrawler";NA;67;0
"Unit";"Zergling";"Larva";67;1
"Unit";"Zergling";"Larva";68;1
"Building";"SporeCrawler";NA;69;0
"Unit";"Zergling";"Larva";69;1
"Unit";"Zergling";"Larva";70;1
"Building";"CreepTumor";NA;71;0
"Unit";"Zergling";"Larva";71;1
"Unit";"Zergling";"Larva";72;1
"Unit";"Zergling";"Larva";73;1
"Unit";"Zergling";"Larva";74;1
"Unit";"Zergling";"Larva";75;1
"Unit";"Zergling";"Larva";76;1
"Building";"CreepTumorQueen";NA;77;0
"Unit";"Queen";"Hatchery";91;2
"Building";"Extractor";NA;93;0
"Building";"BanelingNest";NA;93;0
"Unit";"Zergling";"Larva";93;1
"Unit";"Zergling";"Larva";94;1
"Unit";"Zergling";"Larva";95;1
"Unit";"Zergling";"Larva";96;1
"Unit";"Zergling";"Larva";97;1
"Unit";"Zergling";"Larva";98;1
"Building";"CreepTumor";NA;99;0
"Building";"CreepTumor";NA;99;0
"Building";"CreepTumorQueen";NA;102;0
"Unit";"Overlord";"Larva";103;0
"Unit";"Overlord";"Larva";103;0
"Unit";"Overlord";"Larva";105;0
"Building";"EvolutionChamber";NA;105;0
"Unit";"Overlord";"Larva";105;0
"Building";"Extractor";NA;108;0
"Unit";"Zergling";"Larva";112;1
"Unit";"Zergling";"Larva";113;1
"Unit";"Zergling";"Larva";114;1
"Unit";"Zergling";"Larva";115;1
"Unit";"Zergling";"Larva";116;1
"Unit";"Zergling";"Larva";117;1
"Unit";"Zergling";"Larva";118;1
"Unit";"Zergling";"Larva";119;1
"Unit";"Zergling";"Larva";120;1
"Unit";"Zergling";"Larva";121;1
"Building";"HydraliskDen";NA;123;0
"Building";"Extractor";NA;125;0
"Building";"CreepTumor";NA;130;0
"Building";"CreepTumor";NA;130;0
"Building";"CreepTumor";NA;130;0
"Building";"CreepTumorQueen";NA;130;0
"Unit";"Baneling";"Zergling";130;0
"Unit";"Baneling";"Zergling";130;0
"Unit";"Baneling";"Zergling";130;0
"Unit";"Baneling";"Zergling";130;0
"Unit";"Baneling";"Zergling";130;0
"Unit";"Baneling";"Zergling";130;0
"Unit";"Baneling";"Zergling";130;0
"Unit";"Baneling";"Zergling";130;0
"Unit";"Baneling";"Zergling";130;0
"Unit";"Zergling";"Larva";130;1
"Unit";"Zergling";"Larva";131;1
"Unit";"Zergling";"Larva";132;1
"Unit";"Zergling";"Larva";133;1
"Unit";"Zergling";"Larva";134;1
"Unit";"Zergling";"Larva";135;1
"Unit";"Zergling";"Larva";136;1
"Unit";"Zergling";"Larva";137;1
"Unit";"Zergling";"Larva";138;1
"Unit";"Zergling";"Larva";139;1
"Unit";"Zergling";"Larva";140;1
"Unit";"Zergling";"Larva";141;1
"Unit";"Zergling";"Larva";142;1
"Unit";"Zergling";"Larva";143;1
"Unit";"Zergling";"Larva";147;1
"Unit";"Zergling";"Larva";148;1
"Unit";"Hydralisk";"Larva";149;2
"Unit";"Hydralisk";"Larva";151;2
"Unit";"Hydralisk";"Larva";153;2
"Unit";"Hydralisk";"Larva";155;2
"Unit";"Overlord";"Larva";157;0
"Unit";"Overlord";"Larva";157;0
"Unit";"Overlord";"Larva";157;0
"Building";"Hatchery";NA;157;0
"Unit";"Zergling";"Larva";157;1
"Unit";"Zergling";"Larva";158;1
"Unit";"Overlord";"Larva";159;0
"Unit";"Overlord";"Larva";159;0
"Unit";"Overlord";"Larva";159;0
"Unit";"Hydralisk";"Larva";159;2
"Unit";"Hydralisk";"Larva";161;2
"Unit";"Zergling";"Larva";163;1
"Unit";"Zergling";"Larva";164;1
"Unit";"Zergling";"Larva";165;1
"Unit";"Zergling";"Larva";166;1
"Unit";"Zergling";"Larva";167;1
"Unit";"Zergling";"Larva";168;1
"Unit";"Zergling";"Larva";169;1
"Unit";"Zergling";"Larva";170;1
"Building";"CreepTumor";NA;173;0
"Building";"CreepTumorQueen";NA;173;0
"Building";"CreepTumorQueen";NA;173;0
"Unit";"Hydralisk";"Larva";173;2
"Unit";"Hydralisk";"Larva";175;2
"Unit";"Overlord";"Larva";177;0
"Unit";"Overlord";"Larva";177;0
"Building";"CreepTumor";NA;177;0
"Building";"CreepTumor";NA;177;0
"Building";"CreepTumor";NA;177;0
"Unit";"Hydralisk";"Larva";177;2
"Unit";"Hydralisk";"Larva";179;2
"Building";"CreepTumor";NA;186;0
"Building";"CreepTumor";NA;186;0
"Building";"CreepTumor";NA;186;0
"Unit";"Hydralisk";"Larva";186;2
"Unit";"Hydralisk";"Larva";188;2
"Unit";"Hydralisk";"Larva";190;2
"Building";"CreepTumor";NA;192;0
"Building";"CreepTumor";NA;192;0
"Building";"CreepTumor";NA;192;0
"Unit";"Baneling";"Zergling";192;0
"Unit";"Baneling";"Zergling";192;0
"Unit";"Baneling";"Zergling";192;0
"Unit";"Baneling";"Zergling";192;0
"Unit";"Baneling";"Zergling";192;0
"Unit";"Baneling";"Zergling";192;0
"Unit";"Baneling";"Zergling";192;0
"Unit";"Baneling";"Zergling";192;0
"Unit";"Baneling";"Zergling";192;0
"Unit";"Baneling";"Zergling";192;0
"Unit";"Baneling";"Zergling";192;0
"Unit";"Zergling";"Larva";192;1
"Unit";"Zergling";"Larva";193;1
"Unit";"Zergling";"Larva";194;1
"Unit";"Zergling";"Larva";195;1
"Unit";"Zergling";"Larva";196;1
"Unit";"Zergling";"Larva";197;1
"Unit";"Zergling";"Larva";198;1
"Unit";"Zergling";"Larva";199;1
"Unit";"Zergling";"Larva";200;1
"Unit";"Zergling";"Larva";201;1
"Unit";"Zergling";"Larva";202;1
"Unit";"Zergling";"Larva";203;1
"Unit";"Zergling";"Larva";204;1
"Unit";"Zergling";"Larva";205;1
"Unit";"Zergling";"Larva";206;1
"Unit";"Zergling";"Larva";207;1
"Unit";"Zergling";"Larva";208;1
"Unit";"Zergling";"Larva";209;1
"Unit";"Zergling";"Larva";210;1
"Unit";"Zergling";"Larva";211;1
"Unit";"Zergling";"Larva";212;1
"Unit";"Zergling";"Larva";213;1
"Unit";"Zergling";"Larva";214;1
"Unit";"Zergling";"Larva";215;1
"Unit";"Zergling";"Larva";216;1
"Unit";"Zergling";"Larva";217;1
"Unit";"Zergling";"Larva";218;1
"Unit";"Zergling";"Larva";219;1
"Unit";"Zergling";"Larva";220;1
"Unit";"Zergling";"Larva";221;1
"Unit";"Zergling";"Larva";222;1
"Unit";"Zergling";"Larva";223;1
"Unit";"Zergling";"Larva";224;1
"Unit";"Zergling";"Larva";225;1
"Unit";"Zergling";"Larva";226;1
"Unit";"Zergling";"Larva";227;1
"Unit";"Zergling";"Larva";228;1
"Unit";"Zergling";"Larva";229;1
"Unit";"Zergling";"Larva";230;1
"Unit";"Zergling";"Larva";231;1
"Unit";"Zergling";"Larva";232;1
"Unit";"Zergling";"Larva";233;1
"Unit";"Hydralisk";"Larva";234;2
"Unit";"Hydralisk";"Larva";236;2
"Unit";"Hydralisk";"Larva";238;2
"Unit";"Hydralisk";"Larva";240;2
"Unit";"Hydralisk";"Larva";242;2
"Unit";"Hydralisk";"Larva";244;2
"Unit";"Hydralisk";"Larva";246;2
"Unit";"Hydralisk";"Larva";248;2
"Unit";"Hydralisk";"Larva";250;2
"Unit";"Hydralisk";"Larva";252;2
"Unit";"Hydralisk";"Larva";254;2
"Unit";"Hydralisk";"Larva";256;2
"Unit";"Hydralisk";"Larva";258;2
"Unit";"Zergling";"Larva";260;1
"Unit";"Zergling";"Larva";261;1
"Unit";"Zergling";"Larva";262;1
"Unit";"Zergling";"Larva";263;1
"Unit";"Zergling";"Larva";264;1
"Unit";"Zergling";"Larva";265;1
"Unit";"Queen";"Hatchery";266;2
"Unit";"Queen";"Hatchery";268;2
"Unit";"Zergling";"Larva";270;1
"Unit";"Zergling";"Larva";271;1
"Unit";"Zergling";"Larva";272;1
"Unit";"Zergling";"Larva";273;1
"Unit";"Zergling";"Larva";274;1
"Unit";"Zergling";"Larva";275;1
"Unit";"Zergling";"Larva";276;1
"Unit";"Zergling";"Larva";277;1
"Unit";"Baneling";"Zergling";278;0
"Unit";"Baneling";"Zergling";278;0
"Unit";"Baneling";"Zergling";278;0
"Unit";"Hydralisk";"Larva";278;2
"Unit";"Hydralisk";"Larva";280;2
"Unit";"Zergling";"Larva";282;1
"Unit";"Zergling";"Larva";283;1
"Unit";"Zergling";"Larva";284;1
"Unit";"Zergling";"Larva";285;1
"Building";"Extractor";NA;288;0
"Unit";"Queen";"Hatchery";288;2
"Building";"CreepTumor";NA;290;0
"Building";"CreepTumor";NA;290;0
"Building";"Hatchery";NA;290;0
"Building";"CreepTumor";NA;290;0
"Unit";"Zergling";"Larva";290;1
"Unit";"Zergling";"Larva";291;1
"Unit";"Zergling";"Larva";292;1
"Unit";"Zergling";"Larva";293;1
"Unit";"Zergling";"Larva";294;1
"Unit";"Zergling";"Larva";295;1
"Unit";"Zergling";"Larva";296;1
"Unit";"Zergling";"Larva";297;1
"Unit";"Zergling";"Larva";298;1
"Unit";"Zergling";"Larva";299;1
"Unit";"Baneling";"Zergling";300;0
"Unit";"Baneling";"Zergling";300;0
"Unit";"Baneling";"Zergling";300;0
"Unit";"Baneling";"Zergling";300;0
"Unit";"Baneling";"Zergling";300;0
"Unit";"Baneling";"Zergling";300;0
"Unit";"Baneling";"Zergling";300;0
"Unit";"Baneling";"Zergling";300;0
"Unit";"Baneling";"Zergling";300;0
"Unit";"Baneling";"Zergling";300;0
"Unit";"Zergling";"Larva";300;1
"Unit";"Zergling";"Larva";301;1
"Unit";"Zergling";"Larva";302;1
"Unit";"Zergling";"Larva";303;1
"Unit";"Zergling";"Larva";304;1
"Unit";"Zergling";"Larva";305;1
"Unit";"Zergling";"Larva";306;1
"Unit";"Zergling";"Larva";307;1
"Unit";"Hydralisk";"Larva";308;2
"Unit";"Hydralisk";"Larva";310;2
"Unit";"Hydralisk";"Larva";312;2
"Unit";"Hydralisk";"Larva";314;2
"Unit";"Hydralisk";"Larva";316;2
"Unit";"Hydralisk";"Larva";318;2
"Unit";"Hydralisk";"Larva";320;2
"Unit";"Hydralisk";"Larva";322;2
"Unit";"Hydralisk";"Larva";324;2
"Unit";"Baneling";"Zergling";326;0
"Unit";"Baneling";"Zergling";326;0
"Unit";"Baneling";"Zergling";326;0
"Unit";"Baneling";"Zergling";326;0
"Unit";"Baneling";"Zergling";326;0
"Unit";"Baneling";"Zergling";326;0
"Unit";"Baneling";"Zergling";326;0
"Unit";"Zergling";"Larva";326;1
"Unit";"Zergling";"Larva";327;1
"Unit";"Zergling";"Larva";328;1
"Unit";"Zergling";"Larva";329;1
"Unit";"Zergling";"Larva";330;1
"Unit";"Zergling";"Larva";331;1
"Building";"CreepTumor";NA;332;0
"Unit";"Zergling";"Larva";332;1
"Unit";"Zergling";"Larva";333;1
"Unit";"Zergling";"Larva";334;1
"Unit";"Zergling";"Larva";335;1
"Unit";"Zergling";"Larva";336;1
"Unit";"Zergling";"Larva";337;1
"Unit";"Zergling";"Larva";338;1
"Unit";"Zergling";"Larva";339;1
"Unit";"Zergling";"Larva";340;1
"Unit";"Zergling";"Larva";341;1
"Unit";"Zergling";"Larva";342;1
"Unit";"Zergling";"Larva";343;1
"Unit";"Zergling";"Larva";344;1
"Unit";"Zergling";"Larva";345;1
"Unit";"Zergling";"Larva";346;1
"Unit";"Zergling";"Larva";347;1
"Unit";"Zergling";"Larva";348;1
"Unit";"Zergling";"Larva";349;1
"Unit";"Overlord";"Larva";350;0
"Unit";"Overlord";"Larva";350;0
"Unit";"Overlord";"Larva";350;0
"Unit";"Baneling";"Zergling";350;0
"Unit";"Baneling";"Zergling";350;0
"Unit";"Baneling";"Zergling";350;0
"Unit";"Baneling";"Zergling";350;0
"Unit";"Baneling";"Zergling";350;0
"Unit";"Baneling";"Zergling";350;0
"Unit";"Baneling";"Zergling";350;0
"Unit";"Baneling";"Zergling";350;0
"Unit";"Overlord";"Larva";350;0
"Unit";"Queen";"Hatchery";350;2
"Unit";"Hydralisk";"Larva";352;2
"Unit";"Hydralisk";"Larva";354;2
"Unit";"Hydralisk";"Larva";356;2
"Unit";"Hydralisk";"Larva";358;2
"Unit";"Hydralisk";"Larva";360;2
"Unit";"Hydralisk";"Larva";362;2
"Unit";"Hydralisk";"Larva";364;2
"Unit";"Hydralisk";"Larva";366;2
"Unit";"Hydralisk";"Larva";368;2
"Unit";"Hydralisk";"Larva";370;2
"Unit";"Hydralisk";"Larva";372;2
"Unit";"Hydralisk";"Larva";374;2
"Unit";"Zergling";"Larva";376;1
"Unit";"Zergling";"Larva";377;1
"Unit";"Zergling";"Larva";378;1
"Unit";"Zergling";"Larva";379;1
"Unit";"Zergling";"Larva";380;1
"Unit";"Zergling";"Larva";381;1
"Unit";"Zergling";"Larva";382;1
"Unit";"Zergling";"Larva";383;1
"Unit";"Zergling";"Larva";384;1
"Unit";"Zergling";"Larva";385;1
"Unit";"Zergling";"Larva";386;1
"Unit";"Zergling";"Larva";387;1
"Unit";"Zergling";"Larva";388;1
"Unit";"Zergling";"Larva";389;1
"Unit";"Zergling";"Larva";390;1
"Unit";"Zergling";"Larva";391;1
"Unit";"Zergling";"Larva";392;1
"Unit";"Zergling";"Larva";393;1
"Unit";"Zergling";"Larva";394;1
"Unit";"Zergling";"Larva";395;1
"Unit";"Zergling";"Larva";396;1
"Unit";"Zergling";"Larva";397;1
"Unit";"Zergling";"Larva";398;1
"Unit";"Zergling";"Larva";399;1
"Unit";"Zergling";"Larva";400;1
"Unit";"Zergling";"Larva";401;1
"Unit";"Zergling";"Larva";402;1
"Unit";"Zergling";"Larva";403;1
"Unit";"Zergling";"Larva";404;1
"Unit";"Zergling";"Larva";405;1
"Unit";"Zergling";"Larva";406;1
"Unit";"Zergling";"Larva";407;1
"Unit";"Hydralisk";"Larva";408;2
"Unit";"Hydralisk";"Larva";410;2
"Unit";"Zergling";"Larva";412;1
"Unit";"Zergling";"Larva";413;1
"Unit";"Zergling";"Larva";414;1
"Unit";"Zergling";"Larva";415;1
"Unit";"Zergling";"Larva";416;1
"Unit";"Zergling";"Larva";417;1
"Unit";"Zergling";"Larva";418;1
"Unit";"Zergling";"Larva";419;1
"Unit";"Baneling";"Zergling";420;0
"Unit";"Baneling";"Zergling";420;0
"Unit";"Baneling";"Zergling";420;0
"Unit";"Baneling";"Zergling";420;0
"Unit";"Baneling";"Zergling";420;0
"Unit";"Baneling";"Zergling";420;0
"Unit";"Baneling";"Zergling";420;0
"Unit";"Baneling";"Zergling";420;0
"Unit";"Baneling";"Zergling";420;0
"Unit";"Baneling";"Zergling";420;0
"Unit";"Baneling";"Zergling";420;0
"Unit";"Zergling";"Larva";420;1
"Unit";"Zergling";"Larva";421;1
"Unit";"Zergling";"Larva";422;1
"Unit";"Zergling";"Larva";423;1
"Unit";"Zergling";"Larva";424;1
"Unit";"Zergling";"Larva";425;1
"Unit";"Zergling";"Larva";426;1
"Unit";"Zergling";"Larva";427;1
"Unit";"Zergling";"Larva";428;1
"Unit";"Zergling";"Larva";429;1
"Unit";"Zergling";"Larva";430;1
"Unit";"Zergling";"Larva";431;1
"Unit";"Zergling";"Larva";432;1
"Unit";"Zergling";"Larva";433;1
"Unit";"Zergling";"Larva";434;1
"Unit";"Zergling";"Larva";435;1
"Unit";"Zergling";"Larva";436;1
"Unit";"Zergling";"Larva";437;1
"Unit";"Zergling";"Larva";438;1
"Unit";"Zergling";"Larva";439;1
"Unit";"Zergling";"Larva";440;1
"Unit";"Zergling";"Larva";441;1
"Unit";"Hydralisk";"Larva";442;2
"Unit";"Hydralisk";"Larva";444;2
"Unit";"Zergling";"Larva";446;1
"Unit";"Zergling";"Larva";447;1
"Unit";"Zergling";"Larva";448;1
"Unit";"Zergling";"Larva";449;1
"Unit";"Zergling";"Larva";450;1
"Unit";"Zergling";"Larva";451;1
"Unit";"Zergling";"Larva";452;1
"Unit";"Zergling";"Larva";453;1
"Unit";"Zergling";"Larva";454;1
"Unit";"Zergling";"Larva";455;1
"Unit";"Zergling";"Larva";456;1
"Unit";"Zergling";"Larva";457;1
"Unit";"Zergling";"Larva";458;1
"Unit";"Zergling";"Larva";459;1
"Unit";"Zergling";"Larva";460;1
"Unit";"Zergling";"Larva";461;1
"Upgrade";"SprayZerg";NA;469;0
"Upgrade";"SprayZerg";NA;469;0
"Upgrade";"SprayZerg";NA;469;0
"Upgrade";"zerglingmovementspeed";NA;469;0
"Upgrade";"SprayZerg";NA;469;0
"Upgrade";"SprayZerg";NA;469;0
"Upgrade";"SprayZerg";NA;469;0
"Upgrade";"ZergMeleeWeaponsLevel1";NA;469;0
"Upgrade";"CentrificalHooks";NA;469;0
"Upgrade";"EvolveMuscularAugments";NA;469;0
"Upgrade";"SprayZerg";NA;469;0
"Upgrade";"SprayZerg";NA;469;0
"Upgrade";"ZergMissileWeaponsLevel1";NA;469;0
