"type";"unit_name";"on_building";"total_supply_lag";"supply"
"Unit";"Overlord";"Larva";13;0
"Building";"Hatchery";NA;18;0
"Building";"Extractor";NA;19;0
"Building";"SpawningPool";NA;20;0
"Unit";"Overlord";"Larva";22;0
"Unit";"Zergling";"Larva";23;1
"Unit";"Zergling";"Larva";24;1
"Unit";"Queen";"Hatchery";25;2
"Unit";"Queen";"Hatchery";27;2
"Unit";"Zergling";"Larva";29;1
"Unit";"Zergling";"Larva";30;1
"Unit";"Overlord";"Larva";34;0
"Unit";"Zergling";"Larva";35;1
"Unit";"Zergling";"Larva";36;1
"Unit";"Zergling";"Larva";37;1
"Unit";"Zergling";"Larva";38;1
"Building";"EvolutionChamber";NA;39;0
"Unit";"Zergling";"Larva";39;1
"Unit";"Zergling";"Larva";40;1
"Unit";"Zergling";"Larva";41;1
"Unit";"Zergling";"Larva";42;1
"Unit";"Zergling";"Larva";43;1
"Unit";"Zergling";"Larva";44;1
"Unit";"Zergling";"Larva";45;1
"Unit";"Zergling";"Larva";46;1
"Unit";"Queen";"Hatchery";47;2
"Unit";"Zergling";"Larva";49;1
"Unit";"Zergling";"Larva";50;1
"Unit";"Zergling";"Larva";51;1
"Unit";"Zergling";"Larva";52;1
"Unit";"Zergling";"Larva";53;1
"Unit";"Zergling";"Larva";54;1
"Unit";"Zergling";"Larva";55;1
"Unit";"Zergling";"Larva";56;1
"Unit";"Zergling";"Larva";57;1
"Unit";"Zergling";"Larva";58;1
"Unit";"Zergling";"Larva";59;1
"Unit";"Zergling";"Larva";60;1
"Unit";"Zergling";"Larva";61;1
"Unit";"Zergling";"Larva";62;1
"Unit";"Zergling";"Larva";63;1
"Unit";"Zergling";"Larva";64;1
"Unit";"Zergling";"Larva";65;1
"Unit";"Zergling";"Larva";66;1
"Unit";"Zergling";"Larva";67;1
"Unit";"Zergling";"Larva";68;1
"Unit";"Zergling";"Larva";69;1
"Unit";"Zergling";"Larva";70;1
"Unit";"Zergling";"Larva";71;1
"Unit";"Zergling";"Larva";72;1
"Unit";"Zergling";"Larva";73;1
"Unit";"Zergling";"Larva";74;1
"Unit";"Zergling";"Larva";75;1
"Unit";"Zergling";"Larva";76;1
"Unit";"Zergling";"Larva";77;1
"Unit";"Zergling";"Larva";78;1
"Unit";"Zergling";"Larva";79;1
"Unit";"Zergling";"Larva";80;1
"Unit";"Zergling";"Larva";81;1
"Unit";"Zergling";"Larva";82;1
"Unit";"Zergling";"Larva";83;1
"Unit";"Zergling";"Larva";84;1
"Unit";"Zergling";"Larva";85;1
"Unit";"Zergling";"Larva";86;1
"Unit";"Zergling";"Larva";87;1
"Unit";"Zergling";"Larva";88;1
"Unit";"Zergling";"Larva";89;1
"Unit";"Zergling";"Larva";90;1
"Unit";"Zergling";"Larva";91;1
"Unit";"Zergling";"Larva";92;1
"Building";"SporeCrawler";NA;101;0
"Unit";"Overlord";"Larva";101;0
"Unit";"Overlord";"Larva";102;0
"Building";"SporeCrawler";NA;102;0
"Unit";"Overlord";"Larva";102;0
"Unit";"Zergling";"Larva";102;1
"Unit";"Zergling";"Larva";103;1
"Unit";"Zergling";"Larva";104;1
"Unit";"Zergling";"Larva";105;1
"Unit";"Zergling";"Larva";106;1
"Unit";"Zergling";"Larva";107;1
"Unit";"Queen";"Hatchery";108;2
"Unit";"Zergling";"Larva";110;1
"Unit";"Zergling";"Larva";111;1
"Unit";"Zergling";"Larva";112;1
"Unit";"Zergling";"Larva";113;1
"Building";"Hatchery";NA;114;0
"Unit";"Zergling";"Larva";114;1
"Unit";"Zergling";"Larva";115;1
"Unit";"Zergling";"Larva";116;1
"Unit";"Zergling";"Larva";117;1
"Unit";"Zergling";"Larva";118;1
"Unit";"Zergling";"Larva";119;1
"Unit";"Zergling";"Larva";120;1
"Unit";"Zergling";"Larva";121;1
"Unit";"Zergling";"Larva";122;1
"Unit";"Zergling";"Larva";123;1
"Unit";"Zergling";"Larva";124;1
"Unit";"Zergling";"Larva";125;1
"Unit";"Zergling";"Larva";126;1
"Unit";"Zergling";"Larva";127;1
"Unit";"Queen";"Hatchery";128;2
"Unit";"Zergling";"Larva";130;1
"Unit";"Zergling";"Larva";131;1
"Unit";"Zergling";"Larva";132;1
"Unit";"Zergling";"Larva";133;1
"Building";"Extractor";NA;139;0
"Unit";"Zergling";"Larva";140;1
"Unit";"Zergling";"Larva";141;1
"Unit";"Zergling";"Larva";142;1
"Unit";"Zergling";"Larva";143;1
"Unit";"Zergling";"Larva";144;1
"Unit";"Zergling";"Larva";145;1
"Unit";"Zergling";"Larva";146;1
"Unit";"Zergling";"Larva";147;1
"Building";"BanelingNest";NA;152;0
"Building";"CreepTumorQueen";NA;152;0
"Unit";"Overlord";"Larva";155;0
"Unit";"Overlord";"Larva";157;0
"Unit";"Overlord";"Larva";157;0
"Building";"SporeCrawler";NA;162;0
"Unit";"Zergling";"Larva";162;1
"Unit";"Zergling";"Larva";163;1
"Unit";"Zergling";"Larva";164;1
"Unit";"Zergling";"Larva";165;1
"Unit";"Zergling";"Larva";166;1
"Unit";"Zergling";"Larva";167;1
"Unit";"Zergling";"Larva";168;1
"Unit";"Zergling";"Larva";169;1
"Unit";"Zergling";"Larva";170;1
"Unit";"Zergling";"Larva";171;1
"Unit";"Zergling";"Larva";172;1
"Unit";"Zergling";"Larva";173;1
"Building";"CreepTumorQueen";NA;174;0
"Unit";"Zergling";"Larva";174;1
"Unit";"Zergling";"Larva";175;1
"Unit";"Zergling";"Larva";177;1
"Unit";"Zergling";"Larva";178;1
"Building";"CreepTumorQueen";NA;179;0
"Unit";"Zergling";"Larva";179;1
"Unit";"Zergling";"Larva";180;1
"Unit";"Zergling";"Larva";181;1
"Unit";"Zergling";"Larva";182;1
"Building";"HydraliskDen";NA;183;0
"Unit";"Zergling";"Larva";183;1
"Unit";"Zergling";"Larva";184;1
"Building";"Extractor";NA;188;0
"Building";"Extractor";NA;188;0
"Unit";"Zergling";"Larva";188;1
"Unit";"Zergling";"Larva";189;1
"Unit";"Zergling";"Larva";190;1
"Unit";"Zergling";"Larva";191;1
"Unit";"Zergling";"Larva";192;1
"Unit";"Zergling";"Larva";193;1
"Unit";"Zergling";"Larva";194;1
"Unit";"Zergling";"Larva";195;1
"Unit";"Zergling";"Larva";196;1
"Unit";"Zergling";"Larva";197;1
"Unit";"Zergling";"Larva";198;1
"Unit";"Zergling";"Larva";199;1
"Unit";"Zergling";"Larva";200;1
"Unit";"Zergling";"Larva";201;1
"Unit";"Zergling";"Larva";202;1
"Unit";"Zergling";"Larva";203;1
"Unit";"Zergling";"Larva";204;1
"Unit";"Zergling";"Larva";205;1
"Unit";"Zergling";"Larva";206;1
"Unit";"Zergling";"Larva";207;1
"Unit";"Zergling";"Larva";208;1
"Unit";"Zergling";"Larva";209;1
"Unit";"Zergling";"Larva";210;1
"Unit";"Zergling";"Larva";211;1
"Unit";"Baneling";"Zergling";212;0
"Unit";"Baneling";"Zergling";212;0
"Unit";"Baneling";"Zergling";212;0
"Unit";"Baneling";"Zergling";212;0
"Unit";"Baneling";"Zergling";212;0
"Unit";"Baneling";"Zergling";212;0
"Unit";"Zergling";"Larva";212;1
"Unit";"Zergling";"Larva";213;1
"Unit";"Zergling";"Larva";214;1
"Unit";"Zergling";"Larva";215;1
"Unit";"Zergling";"Larva";216;1
"Unit";"Zergling";"Larva";217;1
"Unit";"Hydralisk";"Larva";218;2
"Unit";"Hydralisk";"Larva";220;2
"Unit";"Zergling";"Larva";222;1
"Unit";"Zergling";"Larva";223;1
"Unit";"Zergling";"Larva";224;1
"Unit";"Zergling";"Larva";225;1
"Unit";"Zergling";"Larva";226;1
"Unit";"Zergling";"Larva";227;1
"Unit";"Zergling";"Larva";228;1
"Unit";"Zergling";"Larva";229;1
"Unit";"Hydralisk";"Larva";230;2
"Unit";"Zergling";"Larva";232;1
"Unit";"Zergling";"Larva";233;1
"Unit";"Zergling";"Larva";234;1
"Unit";"Zergling";"Larva";235;1
"Unit";"Zergling";"Larva";236;1
"Unit";"Zergling";"Larva";237;1
"Unit";"Zergling";"Larva";238;1
"Unit";"Zergling";"Larva";239;1
"Unit";"Zergling";"Larva";240;1
"Unit";"Zergling";"Larva";241;1
"Unit";"Zergling";"Larva";242;1
"Unit";"Zergling";"Larva";243;1
"Unit";"Zergling";"Larva";244;1
"Unit";"Zergling";"Larva";245;1
"Upgrade";"SprayZerg";NA;246;0
"Upgrade";"SprayZerg";NA;246;0
"Upgrade";"zerglingmovementspeed";NA;246;0
"Upgrade";"SprayZerg";NA;246;0
"Upgrade";"SprayZerg";NA;246;0
"Upgrade";"SprayZerg";NA;246;0
