"type";"unit_name";"on_building";"total_supply";"supply"
"Building";"Pylon";NA;13;0
"Building";"Assimilator";NA;16;0
"Building";"Gateway";NA;15;0
"Building";"Forge";NA;18;0
"Unit";"Zealot";"Gateway";20;2
"Building";"Pylon";NA;21;0
"Building";"PhotonCannon";NA;21;0
"Building";"PhotonCannon";NA;21;0
"Building";"Assimilator";NA;23;0
"Building";"CyberneticsCore";NA;23;0
