"type";"unit_name";"on_building";"total_supply";"supply"
"Building";"Pylon";NA;14;0
"Building";"Pylon";NA;16;0
"Building";"Gateway";NA;15;0
"Building";"Assimilator";NA;18;0
"Unit";"Zealot";"Gateway";18;2
"Building";"Gateway";NA;19;0
"Unit";"Zealot";"Gateway";22;2
"Unit";"Zealot";"Gateway";23;2
"Unit";"Zealot";"Gateway";26;2
"Unit";"Zealot";"Gateway";26;2
"Building";"Pylon";NA;32;0
"Unit";"Zealot";"Gateway";30;2
"Building";"Nexus";NA;26;0
