"type";"unit_name";"on_building";"total_supply";"supply"
"Building";"Pylon";NA;13;0
"Building";"Forge";NA;15;0
"Building";"Pylon";NA;17;0
"Building";"Pylon";NA;18;0
"Building";"PhotonCannon";NA;18;0
"Building";"PhotonCannon";NA;18;0
"Building";"Gateway";NA;18;0
"Building";"PhotonCannon";NA;19;0
"Building";"Gateway";NA;19;0
"Building";"Assimilator";NA;21;0
"Building";"Assimilator";NA;21;0
"Building";"CyberneticsCore";NA;24;0
"Building";"Pylon";NA;25;0
"Building";"Gateway";NA;24;0
