"type";"unit_name";"on_building";"total_supply";"supply"
"Unit";"Overlord";"Larva";13;0
"Building";"Extractor";NA;18;0
"Unit";"Overlord";"Larva";21;0
"Building";"SpawningPool";NA;19;0
"Building";"Hatchery";NA;17;0
"Unit";"Zergling";"Larva";22;1
"Unit";"Zergling";"Larva";22;1
"Unit";"Queen";"Hatchery";22;2
"Unit";"Queen";"Hatchery";23;2
"Building";"CreepTumorQueen";NA;33;0
"Unit";"Zergling";"Larva";33;1
"Unit";"Zergling";"Larva";33;1
"Unit";"Overlord";"Larva";33;0
"Building";"CreepTumor";NA;38;0
"Unit";"Overlord";"Larva";41;0
"Building";"Hatchery";NA;31;0
"Unit";"Zergling";"Larva";45;1
"Unit";"Zergling";"Larva";45;1
"Unit";"Zergling";"Larva";45;1
"Unit";"Zergling";"Larva";45;1
"Unit";"Queen";"Hatchery";43;2
"Unit";"Overlord";"Larva";47;0
"Unit";"Zergling";"Larva";56;1
"Unit";"Zergling";"Larva";56;1
"Unit";"Zergling";"Larva";56;1
"Unit";"Zergling";"Larva";56;1
"Building";"SporeCrawler";NA;56;0
"Building";"Extractor";NA;56;0
"Building";"SporeCrawler";NA;62;0
"Building";"SporeCrawler";NA;64;0
"Building";"Extractor";NA;65;0
"Unit";"Overlord";"Larva";74;0
"Unit";"Zergling";"Larva";74;1
"Unit";"Zergling";"Larva";74;1
"Unit";"Zergling";"Larva";74;1
"Unit";"Zergling";"Larva";74;1
"Unit";"Zergling";"Larva";74;1
"Unit";"Zergling";"Larva";74;1
"Unit";"Overlord";"Larva";74;0
"Unit";"Queen";"Hatchery";64;2
"Building";"CreepTumor";NA;74;0
"Building";"Extractor";NA;74;0
"Building";"RoachWarren";NA;74;0
"Unit";"Zergling";"Larva";80;1
"Unit";"Zergling";"Larva";80;1
"Unit";"Zergling";"Larva";80;1
"Unit";"Zergling";"Larva";80;1
"Unit";"Zergling";"Larva";80;1
"Unit";"Zergling";"Larva";80;1
"Unit";"Zergling";"Larva";80;1
"Unit";"Zergling";"Larva";80;1
"Unit";"Zergling";"Larva";80;1
"Unit";"Zergling";"Larva";80;1
"Unit";"Overlord";"Larva";82;0
"Building";"HydraliskDen";NA;74;0
"Unit";"Overlord";"Larva";82;0
"Unit";"Overlord";"Larva";82;0
"Unit";"Hydralisk";"Larva";98;2
"Unit";"Hydralisk";"Larva";98;2
"Unit";"Hydralisk";"Larva";98;2
"Unit";"Hydralisk";"Larva";98;2
"Unit";"Hydralisk";"Larva";98;2
"Unit";"Overlord";"Larva";98;0
"Building";"CreepTumorQueen";NA;108;0
"Building";"CreepTumorQueen";NA;108;0
"Unit";"Hydralisk";"Larva";98;2
"Unit";"Hydralisk";"Larva";98;2
"Unit";"Hydralisk";"Larva";98;2
"Building";"CreepTumorQueen";NA;108;0
"Building";"SporeCrawler";NA;120;0
"Building";"SporeCrawler";NA;120;0
"Building";"SporeCrawler";NA;120;0
"Building";"CreepTumor";NA;122;0
"Building";"CreepTumor";NA;122;0
"Building";"CreepTumor";NA;122;0
"Upgrade";"EvolveMuscularAugments";"HydraliskDen";108;0
"Building";"CreepTumor";NA;131;0
"Building";"BanelingNest";NA;120;0
"Building";"Extractor";NA;131;0
"Building";"Extractor";NA;131;0
"Unit";"Overlord";"Larva";131;0
"Unit";"Overlord";"Larva";131;0
"Building";"CreepTumor";NA;137;0
"Building";"CreepTumor";NA;137;0
"Unit";"Overlord";"Larva";131;0
"Building";"CreepTumor";NA;137;0
"Unit";"Hydralisk";"Larva";131;2
"Unit";"Hydralisk";"Larva";131;2
"Unit";"Hydralisk";"Larva";131;2
"Unit";"Hydralisk";"Larva";131;2
"Unit";"Hydralisk";"Larva";131;2
"Building";"CreepTumorQueen";NA;137;0
"Unit";"Overlord";"Larva";137;0
"Unit";"Overlord";"Larva";137;0
"Unit";"Overlord";"Larva";137;0
"Building";"CreepTumor";NA;147;0
"Building";"Hatchery";NA;131;0
"Building";"CreepTumor";NA;147;0
"Unit";"Hydralisk";"Larva";147;2
"Unit";"Hydralisk";"Larva";147;2
"Unit";"Hydralisk";"Larva";147;2
"Unit";"Hydralisk";"Larva";147;2
"Unit";"Hydralisk";"Larva";147;2
"Unit";"Hydralisk";"Larva";147;2
"Unit";"Hydralisk";"Larva";147;2
"Unit";"Hydralisk";"Larva";147;2
"Unit";"Hydralisk";"Larva";147;2
"Unit";"Hydralisk";"Larva";147;2
"Unit";"Hydralisk";"Larva";147;2
"Unit";"Hydralisk";"Larva";147;2
"Unit";"Hydralisk";"Larva";147;2
"Building";"CreepTumor";NA;152;0
"Unit";"Overlord";"Larva";147;0
"Unit";"Zergling";"Larva";176;1
"Unit";"Zergling";"Larva";176;1
"Unit";"Zergling";"Larva";178;1
"Unit";"Zergling";"Larva";178;1
"Unit";"Zergling";"Larva";178;1
"Unit";"Zergling";"Larva";178;1
"Unit";"Zergling";"Larva";178;1
"Unit";"Zergling";"Larva";178;1
"Unit";"Zergling";"Larva";178;1
"Unit";"Zergling";"Larva";178;1
"Unit";"Zergling";"Larva";178;1
"Unit";"Zergling";"Larva";178;1
"Unit";"Zergling";"Larva";178;1
"Unit";"Zergling";"Larva";178;1
"Unit";"Zergling";"Larva";178;1
"Unit";"Zergling";"Larva";178;1
"Unit";"Zergling";"Larva";178;1
"Unit";"Zergling";"Larva";178;1
"Unit";"Zergling";"Larva";178;1
"Unit";"Zergling";"Larva";178;1
"Unit";"Zergling";"Larva";178;1
"Unit";"Zergling";"Larva";178;1
"Upgrade";"EvolveGroovedSpines";"HydraliskDen";147;0
"Building";"EvolutionChamber";NA;152;0
"Building";"Hatchery";NA;147;0
"Unit";"Zergling";"Larva";200;1
"Unit";"Zergling";"Larva";200;1
"Unit";"Zergling";"Larva";200;1
"Unit";"Zergling";"Larva";200;1
"Unit";"Zergling";"Larva";200;1
"Unit";"Zergling";"Larva";200;1
"Unit";"Zergling";"Larva";200;1
"Unit";"Zergling";"Larva";200;1
"Unit";"Zergling";"Larva";200;1
"Unit";"Zergling";"Larva";200;1
"Unit";"Zergling";"Larva";200;1
"Unit";"Zergling";"Larva";200;1
"Unit";"Zergling";"Larva";200;1
"Unit";"Zergling";"Larva";200;1
"Unit";"Zergling";"Larva";200;1
"Unit";"Zergling";"Larva";200;1
"Unit";"Zergling";"Larva";200;1
"Unit";"Zergling";"Larva";200;1
"Unit";"Zergling";"Larva";200;1
"Unit";"Zergling";"Larva";200;1
"Unit";"Zergling";"Larva";200;1
"Unit";"Zergling";"Larva";200;1
"Unit";"Baneling";"Zergling";200;0
"Unit";"Baneling";"Zergling";200;0
"Unit";"Baneling";"Zergling";200;0
"Unit";"Baneling";"Zergling";200;0
"Unit";"Baneling";"Zergling";200;0
"Unit";"Baneling";"Zergling";200;0
"Unit";"Baneling";"Zergling";200;0
"Unit";"Baneling";"Zergling";200;0
"Unit";"Baneling";"Zergling";200;0
"Unit";"Zergling";"Larva";200;1
"Unit";"Zergling";"Larva";200;1
"Unit";"Zergling";"Larva";200;1
"Unit";"Zergling";"Larva";200;1
"Unit";"Zergling";"Larva";200;1
"Unit";"Zergling";"Larva";200;1
"Unit";"Zergling";"Larva";200;1
"Unit";"Zergling";"Larva";200;1
"Unit";"Zergling";"Larva";200;1
"Unit";"Zergling";"Larva";200;1
"Unit";"Zergling";"Larva";200;1
"Unit";"Zergling";"Larva";200;1
"Unit";"Baneling";"Zergling";200;0
"Unit";"Baneling";"Zergling";200;0
"Unit";"Baneling";"Zergling";200;0
"Unit";"Baneling";"Zergling";200;0
"Unit";"Baneling";"Zergling";239;0
"Unit";"Baneling";"Zergling";239;0
"Unit";"Baneling";"Zergling";239;0
"Unit";"Baneling";"Zergling";239;0
"Unit";"Baneling";"Zergling";239;0
"Unit";"Baneling";"Zergling";239;0
"Unit";"Baneling";"Zergling";239;0
"Unit";"Baneling";"Zergling";239;0
"Unit";"Baneling";"Zergling";239;0
"Unit";"Baneling";"Zergling";239;0
"Unit";"Baneling";"Zergling";239;0
"Unit";"Baneling";"Zergling";239;0
"Unit";"Baneling";"Zergling";239;0
"Unit";"Baneling";"Zergling";239;0
"Unit";"Baneling";"Zergling";239;0
"Unit";"Baneling";"Zergling";239;0
"Unit";"Baneling";"Zergling";239;0
"Unit";"Baneling";"Zergling";239;0
"Unit";"Baneling";"Zergling";239;0
"Unit";"Baneling";"Zergling";239;0
"Unit";"Baneling";"Zergling";239;0
"Unit";"Baneling";"Zergling";239;0
"Unit";"Baneling";"Zergling";239;0
"Unit";"Baneling";"Zergling";239;0
"Unit";"Baneling";"Zergling";239;0
"Unit";"Baneling";"Zergling";239;0
"Unit";"Baneling";"Zergling";239;0
"Unit";"Overlord";"Larva";239;0
