"type";"unit_name";"on_building";"total_supply";"supply"
"Unit";"Overlord";"Larva";13;0
"Building";"Extractor";NA;17;0
"Unit";"Overlord";"Larva";21;0
"Building";"SpawningPool";NA;19;0
"Building";"Hatchery";NA;17;0
"Unit";"Zergling";"Larva";23;1
"Unit";"Zergling";"Larva";23;1
"Unit";"Zergling";"Larva";23;1
"Unit";"Zergling";"Larva";23;1
"Unit";"Queen";"Hatchery";22;2
"Unit";"Queen";"Hatchery";23;2
"Building";"CreepTumorQueen";NA;35;0
"Unit";"Overlord";"Larva";36;0
"Building";"CreepTumor";NA;39;0
"Unit";"Queen";"Hatchery";37;2
"Unit";"Overlord";"Larva";40;0
"Building";"CreepTumorQueen";NA;46;0
"Unit";"Overlord";"Larva";46;0
"Building";"Hatchery";NA;35;0
"Building";"CreepTumor";NA;49;0
"Building";"SporeCrawler";NA;48;0
"Building";"SporeCrawler";NA;48;0
"Unit";"Overlord";"Larva";48;0
"Unit";"Queen";"Hatchery";44;2
"Building";"Extractor";NA;61;0
"Building";"SporeCrawler";NA;63;0
"Unit";"Overlord";"Larva";63;0
"Building";"CreepTumor";NA;71;0
"Building";"Extractor";NA;69;0
"Building";"EvolutionChamber";NA;69;0
"Building";"Extractor";NA;69;0
"Unit";"Overlord";"Larva";71;0
"Building";"CreepTumorQueen";NA;72;0
"Building";"CreepTumorQueen";NA;73;0
"Unit";"Queen";"Hatchery";69;2
"Building";"BanelingNest";NA;69;0
"Unit";"Zergling";"Larva";76;1
"Unit";"Zergling";"Larva";76;1
"Unit";"Zergling";"Larva";76;1
"Unit";"Zergling";"Larva";76;1
"Unit";"Zergling";"Larva";76;1
"Unit";"Zergling";"Larva";76;1
"Unit";"Zergling";"Larva";76;1
"Unit";"Zergling";"Larva";76;1
"Unit";"Zergling";"Larva";77;1
"Unit";"Zergling";"Larva";77;1
"Unit";"Zergling";"Larva";79;1
"Unit";"Zergling";"Larva";79;1
"Unit";"Zergling";"Larva";79;1
"Unit";"Zergling";"Larva";79;1
"Unit";"Overlord";"Larva";79;0
"Unit";"Zergling";"Larva";79;1
"Unit";"Zergling";"Larva";79;1
"Unit";"Zergling";"Larva";79;1
"Unit";"Zergling";"Larva";79;1
"Building";"CreepTumorQueen";NA;83;0
"Unit";"Queen";"Hatchery";73;2
"Building";"CreepTumor";NA;89;0
"Building";"CreepTumor";NA;95;0
"Unit";"Zergling";"Larva";81;1
"Unit";"Zergling";"Larva";81;1
"Unit";"Zergling";"Larva";81;1
"Unit";"Zergling";"Larva";81;1
"Unit";"Overlord";"Larva";95;0
"Building";"HydraliskDen";NA;81;0
"Unit";"Zergling";"Larva";95;1
"Unit";"Zergling";"Larva";95;1
"Unit";"Zergling";"Larva";95;1
"Unit";"Zergling";"Larva";95;1
"Unit";"Zergling";"Larva";95;1
"Unit";"Zergling";"Larva";95;1
"Unit";"Zergling";"Larva";95;1
"Unit";"Zergling";"Larva";95;1
"Unit";"Overlord";"Larva";105;0
"Unit";"Overlord";"Larva";113;0
"Unit";"Overlord";"Larva";121;0
"Unit";"Hydralisk";"Larva";122;2
"Unit";"Hydralisk";"Larva";122;2
"Unit";"Hydralisk";"Larva";122;2
"Unit";"Hydralisk";"Larva";122;2
"Unit";"Hydralisk";"Larva";122;2
"Unit";"Hydralisk";"Larva";122;2
"Unit";"Hydralisk";"Larva";122;2
"Unit";"Hydralisk";"Larva";122;2
"Unit";"Hydralisk";"Larva";122;2
"Upgrade";"ZergMeleeWeaponsLevel1";"EvolutionChamber";101;0
"Unit";"Overlord";"Larva";136;0
"Unit";"Overlord";"Larva";136;0
"Unit";"Hydralisk";"Larva";132;2
"Unit";"Hydralisk";"Larva";132;2
"Unit";"Zergling";"Larva";140;1
"Unit";"Zergling";"Larva";140;1
"Unit";"Zergling";"Larva";140;1
"Unit";"Zergling";"Larva";140;1
"Unit";"Zergling";"Larva";140;1
"Unit";"Zergling";"Larva";140;1
"Unit";"Zergling";"Larva";140;1
"Unit";"Zergling";"Larva";140;1
"Unit";"Zergling";"Larva";140;1
"Unit";"Zergling";"Larva";140;1
"Unit";"Zergling";"Larva";140;1
"Unit";"Zergling";"Larva";140;1
"Unit";"Zergling";"Larva";140;1
"Unit";"Zergling";"Larva";140;1
"Upgrade";"EvolveGroovedSpines";"HydraliskDen";122;0
"Building";"CreepTumorQueen";NA;140;0
"Building";"CreepTumorQueen";NA;140;0
"Building";"CreepTumor";NA;144;0
"Unit";"Zergling";"Larva";144;1
"Unit";"Zergling";"Larva";144;1
"Unit";"Zergling";"Larva";144;1
"Unit";"Zergling";"Larva";144;1
"Unit";"Zergling";"Larva";144;1
"Unit";"Zergling";"Larva";144;1
"Unit";"Zergling";"Larva";158;1
"Unit";"Zergling";"Larva";158;1
"Unit";"Zergling";"Larva";158;1
"Unit";"Zergling";"Larva";158;1
"Unit";"Hydralisk";"Larva";158;2
"Unit";"Hydralisk";"Larva";158;2
"Unit";"Hydralisk";"Larva";158;2
"Unit";"Hydralisk";"Larva";158;2
"Unit";"Zergling";"Larva";164;1
"Unit";"Zergling";"Larva";164;1
"Unit";"Zergling";"Larva";164;1
"Unit";"Zergling";"Larva";164;1
"Unit";"Zergling";"Larva";164;1
"Unit";"Zergling";"Larva";164;1
"Unit";"Baneling";"Zergling";176;0
"Unit";"Baneling";"Zergling";176;0
"Unit";"Baneling";"Zergling";176;0
"Unit";"Baneling";"Zergling";176;0
"Unit";"Baneling";"Zergling";176;0
"Unit";"Baneling";"Zergling";176;0
"Unit";"Baneling";"Zergling";176;0
"Unit";"Baneling";"Zergling";176;0
"Unit";"Queen";"Hatchery";164;2
"Unit";"Queen";"Hatchery";164;2
"Unit";"Baneling";"Zergling";176;0
"Unit";"Queen";"Hatchery";164;2
"Unit";"Zergling";"Larva";176;1
"Unit";"Zergling";"Larva";176;1
"Unit";"Zergling";"Larva";176;1
"Unit";"Zergling";"Larva";176;1
"Unit";"Zergling";"Larva";176;1
"Unit";"Zergling";"Larva";176;1
"Unit";"Zergling";"Larva";176;1
"Unit";"Zergling";"Larva";176;1
"Unit";"Zergling";"Larva";176;1
"Unit";"Zergling";"Larva";176;1
"Unit";"Zergling";"Larva";176;1
"Unit";"Zergling";"Larva";176;1
"Building";"Hatchery";NA;140;0
"Unit";"Zergling";"Larva";188;1
"Unit";"Zergling";"Larva";188;1
"Unit";"Zergling";"Larva";188;1
"Unit";"Zergling";"Larva";188;1
"Unit";"Zergling";"Larva";188;1
"Unit";"Zergling";"Larva";188;1
"Unit";"Zergling";"Larva";206;1
"Unit";"Zergling";"Larva";206;1
"Unit";"Zergling";"Larva";207;1
"Unit";"Zergling";"Larva";207;1
"Unit";"Zergling";"Larva";207;1
"Unit";"Zergling";"Larva";207;1
"Unit";"Zergling";"Larva";207;1
"Unit";"Zergling";"Larva";207;1
"Upgrade";"EvolveMuscularAugments";"HydraliskDen";182;0
"Unit";"Zergling";"Larva";214;1
"Unit";"Zergling";"Larva";214;1
"Unit";"Zergling";"Larva";214;1
"Unit";"Zergling";"Larva";214;1
"Unit";"Hydralisk";"Larva";224;2
"Unit";"Hydralisk";"Larva";224;2
"Unit";"Hydralisk";"Larva";224;2
"Unit";"Hydralisk";"Larva";224;2
"Unit";"Hydralisk";"Larva";224;2
"Unit";"Hydralisk";"Larva";224;2
"Unit";"Hydralisk";"Larva";224;2
"Unit";"Hydralisk";"Larva";224;2
"Building";"CreepTumor";NA;230;0
"Unit";"Hydralisk";"Larva";230;2
"Unit";"Hydralisk";"Larva";230;2
"Unit";"Hydralisk";"Larva";230;2
"Unit";"Hydralisk";"Larva";230;2
"Unit";"Hydralisk";"Larva";230;2
"Unit";"Baneling";"Zergling";246;0
"Unit";"Baneling";"Zergling";246;0
"Unit";"Baneling";"Zergling";246;0
"Unit";"Baneling";"Zergling";246;0
"Unit";"Baneling";"Zergling";246;0
"Building";"Extractor";NA;230;0
"Upgrade";"ZergMeleeWeaponsLevel2";"EvolutionChamber";176;0
"Building";"Extractor";NA;230;0
"Unit";"Overlord";"Larva";246;0
"Unit";"Overlord";"Larva";246;0
"Unit";"Overlord";"Larva";246;0
"Building";"Hatchery";NA;200;0
"Unit";"Overlord";"Larva";261;0
"Unit";"Overlord";"Larva";261;0
"Unit";"Baneling";"Zergling";261;0
"Unit";"Baneling";"Zergling";261;0
"Unit";"Baneling";"Zergling";261;0
"Unit";"Baneling";"Zergling";261;0
"Unit";"Baneling";"Zergling";261;0
"Unit";"Baneling";"Zergling";261;0
"Building";"CreepTumor";NA;261;0
"Unit";"Zergling";"Larva";261;1
"Unit";"Zergling";"Larva";261;1
"Unit";"Zergling";"Larva";261;1
"Unit";"Zergling";"Larva";261;1
"Unit";"Zergling";"Larva";261;1
"Unit";"Zergling";"Larva";261;1
"Unit";"Zergling";"Larva";261;1
"Unit";"Zergling";"Larva";261;1
"Unit";"Zergling";"Larva";261;1
"Unit";"Zergling";"Larva";261;1
"Unit";"Zergling";"Larva";261;1
"Unit";"Zergling";"Larva";261;1
"Unit";"Zergling";"Larva";261;1
"Unit";"Zergling";"Larva";261;1
"Unit";"Zergling";"Larva";261;1
"Unit";"Zergling";"Larva";261;1
"Unit";"Zergling";"Larva";261;1
"Unit";"Zergling";"Larva";261;1
"Unit";"Zergling";"Larva";261;1
"Unit";"Zergling";"Larva";261;1
"Unit";"Zergling";"Larva";261;1
"Unit";"Zergling";"Larva";261;1
"Unit";"Zergling";"Larva";261;1
"Unit";"Zergling";"Larva";261;1
"Unit";"Zergling";"Larva";261;1
"Unit";"Zergling";"Larva";261;1
"Unit";"Zergling";"Larva";261;1
"Unit";"Zergling";"Larva";261;1
"Unit";"Zergling";"Larva";261;1
"Unit";"Zergling";"Larva";261;1
"Unit";"Zergling";"Larva";261;1
"Unit";"Zergling";"Larva";261;1
"Unit";"Baneling";"Zergling";261;0
"Unit";"Baneling";"Zergling";261;0
"Unit";"Baneling";"Zergling";261;0
"Building";"SpineCrawler";NA;261;0
"Unit";"Hydralisk";"Larva";261;2
"Unit";"Hydralisk";"Larva";261;2
"Unit";"Hydralisk";"Larva";261;2
"Unit";"Zergling";"Larva";293;1
"Unit";"Zergling";"Larva";293;1
"Unit";"Zergling";"Larva";293;1
"Unit";"Zergling";"Larva";293;1
"Unit";"Zergling";"Larva";293;1
"Unit";"Zergling";"Larva";293;1
"Unit";"Zergling";"Larva";293;1
"Unit";"Zergling";"Larva";293;1
"Unit";"Zergling";"Larva";293;1
"Unit";"Zergling";"Larva";293;1
"Unit";"Zergling";"Larva";293;1
"Unit";"Zergling";"Larva";293;1
"Unit";"Zergling";"Larva";293;1
"Unit";"Zergling";"Larva";293;1
"Unit";"Zergling";"Larva";293;1
"Unit";"Zergling";"Larva";293;1
"Unit";"Zergling";"Larva";293;1
"Unit";"Zergling";"Larva";293;1
"Unit";"Zergling";"Larva";293;1
"Unit";"Zergling";"Larva";293;1
"Unit";"Zergling";"Larva";293;1
"Unit";"Zergling";"Larva";293;1
"Unit";"Zergling";"Larva";293;1
"Unit";"Zergling";"Larva";293;1
"Unit";"Zergling";"Larva";293;1
"Unit";"Zergling";"Larva";293;1
"Unit";"Zergling";"Larva";293;1
"Unit";"Zergling";"Larva";293;1
"Unit";"Zergling";"Larva";293;1
"Unit";"Zergling";"Larva";293;1
"Unit";"Baneling";"Zergling";329;0
"Unit";"Baneling";"Zergling";329;0
"Unit";"Baneling";"Zergling";329;0
"Unit";"Baneling";"Zergling";329;0
"Unit";"Baneling";"Zergling";329;0
"Unit";"Baneling";"Zergling";329;0
"Unit";"Baneling";"Zergling";329;0
"Unit";"Hydralisk";"Larva";299;2
"Unit";"Baneling";"Zergling";329;0
"Unit";"Hydralisk";"Larva";299;2
"Unit";"Hydralisk";"Larva";299;2
"Unit";"Hydralisk";"Larva";299;2
"Unit";"Hydralisk";"Larva";299;2
"Unit";"Baneling";"Zergling";329;0
"Building";"CreepTumor";NA;329;0
"Unit";"Zergling";"Larva";329;1
"Unit";"Zergling";"Larva";329;1
"Unit";"Zergling";"Larva";329;1
"Unit";"Zergling";"Larva";329;1
"Unit";"Zergling";"Larva";329;1
"Unit";"Zergling";"Larva";329;1
"Unit";"Zergling";"Larva";329;1
"Unit";"Zergling";"Larva";329;1
"Unit";"Zergling";"Larva";329;1
"Unit";"Zergling";"Larva";329;1
"Unit";"Zergling";"Larva";329;1
"Unit";"Zergling";"Larva";329;1
"Unit";"Zergling";"Larva";329;1
"Unit";"Zergling";"Larva";329;1
"Unit";"Zergling";"Larva";329;1
"Unit";"Zergling";"Larva";329;1
"Unit";"Zergling";"Larva";329;1
"Unit";"Zergling";"Larva";329;1
"Unit";"Zergling";"Larva";329;1
"Unit";"Zergling";"Larva";329;1
"Unit";"Zergling";"Larva";329;1
"Unit";"Zergling";"Larva";329;1
"Unit";"Hydralisk";"Larva";329;2
"Building";"CreepTumorQueen";NA;363;0
"Unit";"Hydralisk";"Larva";339;2
"Unit";"Hydralisk";"Larva";339;2
"Unit";"Hydralisk";"Larva";339;2
"Unit";"Hydralisk";"Larva";339;2
"Building";"CreepTumorQueen";NA;363;0
"Unit";"Hydralisk";"Larva";339;2
"Unit";"Hydralisk";"Larva";339;2
"Unit";"Zergling";"Larva";363;1
"Unit";"Zergling";"Larva";363;1
"Unit";"Zergling";"Larva";363;1
"Unit";"Zergling";"Larva";363;1
"Unit";"Zergling";"Larva";363;1
"Unit";"Zergling";"Larva";363;1
"Unit";"Zergling";"Larva";363;1
"Unit";"Zergling";"Larva";363;1
"Unit";"Zergling";"Larva";363;1
"Unit";"Zergling";"Larva";363;1
"Unit";"Zergling";"Larva";363;1
"Unit";"Zergling";"Larva";363;1
"Unit";"Zergling";"Larva";363;1
"Unit";"Zergling";"Larva";363;1
"Unit";"Zergling";"Larva";363;1
"Unit";"Zergling";"Larva";363;1
"Unit";"Zergling";"Larva";363;1
"Unit";"Zergling";"Larva";363;1
"Unit";"Baneling";"Zergling";363;0
"Unit";"Baneling";"Zergling";363;0
"Unit";"Baneling";"Zergling";363;0
"Unit";"Baneling";"Zergling";363;0
"Unit";"Baneling";"Zergling";363;0
"Unit";"Baneling";"Zergling";363;0
"Unit";"Baneling";"Zergling";363;0
"Unit";"Baneling";"Zergling";363;0
"Unit";"Baneling";"Zergling";363;0
"Unit";"Baneling";"Zergling";363;0
"Unit";"Baneling";"Zergling";363;0
"Building";"CreepTumorQueen";NA;393;0
"Unit";"Zergling";"Larva";393;1
"Unit";"Zergling";"Larva";393;1
"Unit";"Zergling";"Larva";393;1
"Unit";"Zergling";"Larva";393;1
"Unit";"Zergling";"Larva";393;1
"Unit";"Zergling";"Larva";393;1
"Unit";"Zergling";"Larva";393;1
"Unit";"Zergling";"Larva";393;1
"Unit";"Zergling";"Larva";393;1
"Unit";"Zergling";"Larva";393;1
"Unit";"Zergling";"Larva";393;1
"Unit";"Zergling";"Larva";393;1
"Unit";"Zergling";"Larva";393;1
"Unit";"Zergling";"Larva";393;1
"Unit";"Zergling";"Larva";393;1
"Unit";"Zergling";"Larva";393;1
"Unit";"Zergling";"Larva";393;1
"Unit";"Zergling";"Larva";393;1
"Unit";"Zergling";"Larva";393;1
"Unit";"Zergling";"Larva";393;1
"Unit";"Zergling";"Larva";393;1
"Unit";"Zergling";"Larva";393;1
"Unit";"Zergling";"Larva";393;1
"Unit";"Zergling";"Larva";393;1
"Unit";"Zergling";"Larva";393;1
"Unit";"Zergling";"Larva";393;1
"Unit";"Zergling";"Larva";393;1
"Unit";"Zergling";"Larva";393;1
"Unit";"Zergling";"Larva";393;1
"Unit";"Zergling";"Larva";393;1
"Unit";"Zergling";"Larva";393;1
"Unit";"Zergling";"Larva";393;1
"Unit";"Zergling";"Larva";393;1
"Unit";"Zergling";"Larva";393;1
"Unit";"Zergling";"Larva";393;1
"Unit";"Zergling";"Larva";393;1
"Unit";"Zergling";"Larva";393;1
"Unit";"Zergling";"Larva";393;1
"Unit";"Zergling";"Larva";393;1
"Unit";"Zergling";"Larva";393;1
"Unit";"Zergling";"Larva";393;1
"Unit";"Zergling";"Larva";393;1
"Unit";"Zergling";"Larva";393;1
"Unit";"Zergling";"Larva";393;1
"Unit";"Zergling";"Larva";393;1
"Unit";"Zergling";"Larva";393;1
"Unit";"Zergling";"Larva";393;1
"Unit";"Zergling";"Larva";393;1
"Unit";"Zergling";"Larva";393;1
"Unit";"Zergling";"Larva";393;1
"Unit";"Zergling";"Larva";393;1
"Unit";"Zergling";"Larva";393;1
"Unit";"Zergling";"Larva";395;1
"Unit";"Zergling";"Larva";395;1
"Unit";"Zergling";"Larva";395;1
"Unit";"Zergling";"Larva";395;1
"Unit";"Zergling";"Larva";395;1
"Unit";"Zergling";"Larva";395;1
"Unit";"Zergling";"Larva";395;1
"Unit";"Zergling";"Larva";395;1
"Unit";"Zergling";"Larva";395;1
"Unit";"Zergling";"Larva";395;1
"Unit";"Zergling";"Larva";399;1
"Unit";"Zergling";"Larva";399;1
"Unit";"Hydralisk";"Larva";425;2
"Unit";"Baneling";"Zergling";443;0
"Unit";"Baneling";"Zergling";443;0
"Unit";"Baneling";"Zergling";443;0
"Unit";"Baneling";"Zergling";443;0
"Unit";"Baneling";"Zergling";443;0
"Unit";"Baneling";"Zergling";443;0
"Unit";"Baneling";"Zergling";443;0
"Unit";"Baneling";"Zergling";443;0
"Unit";"Baneling";"Zergling";443;0
"Unit";"Baneling";"Zergling";443;0
"Unit";"Baneling";"Zergling";443;0
"Unit";"Baneling";"Zergling";443;0
"Unit";"Baneling";"Zergling";443;0
"Unit";"Baneling";"Zergling";443;0
"Unit";"Baneling";"Zergling";443;0
"Unit";"Hydralisk";"Larva";433;2
"Unit";"Hydralisk";"Larva";433;2
"Unit";"Hydralisk";"Larva";433;2
"Unit";"Zergling";"Larva";457;1
"Unit";"Zergling";"Larva";457;1
"Unit";"Zergling";"Larva";457;1
"Unit";"Zergling";"Larva";457;1
"Unit";"Zergling";"Larva";457;1
"Unit";"Zergling";"Larva";457;1
"Unit";"Zergling";"Larva";457;1
"Unit";"Zergling";"Larva";457;1
"Unit";"Zergling";"Larva";457;1
"Unit";"Zergling";"Larva";457;1
