"type";"unit_name";"on_building";"total_supply";"supply"
"Unit";"Overlord";"Larva";12;0
"Building";"Extractor";NA;18;0
"Unit";"Overlord";"Larva";21;0
"Building";"SpawningPool";NA;19;0
"Building";"Hatchery";NA;17;0
"Unit";"Queen";"Hatchery";22;2
"Unit";"Queen";"Hatchery";22;2
"Unit";"Zergling";"Larva";27;1
"Unit";"Zergling";"Larva";27;1
"Unit";"Overlord";"Larva";33;0
"Unit";"Queen";"Hatchery";33;2
"Unit";"Zergling";"Larva";37;1
"Unit";"Zergling";"Larva";37;1
"Building";"CreepTumorQueen";NA;37;0
"Unit";"Overlord";"Larva";37;0
"Unit";"Overlord";"Larva";49;0
"Unit";"Overlord";"Larva";49;0
"Unit";"Overlord";"Larva";49;0
"Building";"CreepTumorQueen";NA;49;0
"Building";"CreepTumor";NA;49;0
"Building";"Extractor";NA;49;0
"Building";"Hatchery";NA;36;0
"Unit";"Queen";"Hatchery";49;2
"Unit";"Overlord";"Larva";51;0
"Building";"RoachWarren";NA;49;0
"Unit";"Zergling";"Larva";51;1
"Unit";"Zergling";"Larva";51;1
"Unit";"Zergling";"Larva";51;1
"Unit";"Zergling";"Larva";51;1
"Unit";"Zergling";"Larva";51;1
"Unit";"Zergling";"Larva";51;1
"Building";"SporeCrawler";NA;56;0
"Unit";"Overlord";"Larva";56;0
"Building";"SporeCrawler";NA;56;0
"Building";"CreepTumorQueen";NA;62;0
"Unit";"Queen";"Hatchery";51;2
"Unit";"Roach";"Larva";62;2
"Unit";"Roach";"Larva";62;2
"Unit";"Roach";"Larva";62;2
"Unit";"Roach";"Larva";62;2
"Building";"CreepTumor";NA;62;0
"Building";"CreepTumor";NA;62;0
"Unit";"Roach";"Larva";65;2
"Unit";"Roach";"Larva";65;2
"Unit";"Roach";"Larva";78;2
"Unit";"Roach";"Larva";78;2
"Unit";"Roach";"Larva";87;2
"Unit";"Roach";"Larva";87;2
"Building";"SpineCrawler";NA;87;0
"Building";"SpineCrawler";NA;87;0
"Building";"SpineCrawler";NA;87;0
"Unit";"Roach";"Larva";91;2
"Unit";"Roach";"Larva";91;2
"Unit";"Roach";"Larva";91;2
"Unit";"Roach";"Larva";91;2
"Unit";"Roach";"Larva";95;2
"Unit";"Roach";"Larva";95;2
"Unit";"Roach";"Larva";95;2
"Unit";"Roach";"Larva";95;2
"Unit";"Roach";"Larva";95;2
"Unit";"Overlord";"Larva";95;0
"Unit";"Overlord";"Larva";95;0
"Unit";"Roach";"Larva";103;2
"Building";"Extractor";NA;103;0
"Building";"Extractor";NA;111;0
"Building";"CreepTumor";NA;113;0
"Unit";"Roach";"Larva";111;2
"Building";"CreepTumor";NA;118;0
"Building";"CreepTumor";NA;118;0
"Unit";"Queen";"Hatchery";111;2
"Unit";"Queen";"Hatchery";111;2
"Building";"CreepTumor";NA;137;0
"Building";"CreepTumor";NA;137;0
"Unit";"Queen";"Hatchery";126;2
"Building";"HydraliskDen";NA;130;0
"Building";"EvolutionChamber";NA;134;0
"Building";"CreepTumor";NA;142;0
"Building";"Extractor";NA;139;0
"Building";"Extractor";NA;142;0
"Unit";"Overlord";"Larva";145;0
"Building";"CreepTumor";NA;146;0
"Building";"CreepTumor";NA;148;0
"Upgrade";"GlialReconstitution";"RoachWarren";134;0
"Unit";"Hydralisk";"Larva";153;2
"Unit";"Hydralisk";"Larva";153;2
"Unit";"Hydralisk";"Larva";153;2
"Unit";"Hydralisk";"Larva";155;2
"Unit";"Hydralisk";"Larva";155;2
"Unit";"Hydralisk";"Larva";155;2
"Unit";"Hydralisk";"Larva";155;2
"Unit";"Hydralisk";"Larva";155;2
"Unit";"Hydralisk";"Larva";155;2
"Unit";"Hydralisk";"Larva";155;2
"Upgrade";"EvolveGroovedSpines";"HydraliskDen";150;0
"Unit";"Overlord";"Larva";161;0
"Unit";"Overlord";"Larva";161;0
"Unit";"Overlord";"Larva";161;0
"Building";"Hatchery";NA;145;0
"Building";"CreepTumor";NA;161;0
"Building";"CreepTumor";NA;161;0
"Building";"CreepTumor";NA;175;0
"Unit";"Overlord";"Larva";161;0
"Unit";"Overlord";"Larva";161;0
"Unit";"Queen";"Hatchery";161;2
"Building";"SpineCrawler";NA;161;0
"Unit";"Hydralisk";"Larva";175;2
"Unit";"Hydralisk";"Larva";175;2
"Unit";"Hydralisk";"Larva";175;2
"Unit";"Hydralisk";"Larva";175;2
"Unit";"Hydralisk";"Larva";175;2
"Building";"CreepTumor";NA;182;0
"Building";"CreepTumor";NA;182;0
"Unit";"Hydralisk";"Larva";177;2
"Unit";"Hydralisk";"Larva";177;2
"Unit";"Hydralisk";"Larva";177;2
"Unit";"Hydralisk";"Larva";177;2
"Building";"CreepTumor";NA;182;0
"Building";"Extractor";NA;182;0
"Upgrade";"ZergMissileWeaponsLevel1";"EvolutionChamber";155;0
"Unit";"Hydralisk";"Larva";182;2
"Unit";"Hydralisk";"Larva";182;2
"Unit";"Hydralisk";"Larva";182;2
"Unit";"Overlord";"Larva";200;0
"Unit";"Hydralisk";"Larva";200;2
"Unit";"Hydralisk";"Larva";200;2
"Unit";"Hydralisk";"Larva";200;2
"Unit";"Hydralisk";"Larva";200;2
"Unit";"Hydralisk";"Larva";200;2
"Unit";"Hydralisk";"Larva";200;2
"Unit";"Hydralisk";"Larva";200;2
"Unit";"Overlord";"Larva";200;0
"Upgrade";"EvolveMuscularAugments";"HydraliskDen";182;0
"Unit";"Roach";"Larva";206;2
"Unit";"Roach";"Larva";206;2
"Unit";"Roach";"Larva";206;2
"Unit";"Roach";"Larva";206;2
"Unit";"Roach";"Larva";206;2
"Unit";"Roach";"Larva";206;2
"Unit";"Overlord";"Larva";206;0
"Unit";"Hydralisk";"Larva";220;2
"Unit";"Hydralisk";"Larva";220;2
"Unit";"Hydralisk";"Larva";220;2
"Building";"SpineCrawler";NA;206;0
"Unit";"Hydralisk";"Larva";234;2
"Unit";"Hydralisk";"Larva";234;2
"Unit";"Hydralisk";"Larva";234;2
"Unit";"Hydralisk";"Larva";234;2
"Unit";"Hydralisk";"Larva";234;2
"Unit";"Hydralisk";"Larva";234;2
"Building";"LurkerDenMP";NA;182;0
"Building";"Extractor";NA;240;0
"Unit";"Queen";"Hatchery";234;2
"Unit";"Overlord";"Larva";256;0
"Unit";"Overlord";"Larva";256;0
"Unit";"Overlord";"Larva";256;0
"Building";"SpineCrawler";NA;256;0
"Building";"SpineCrawler";NA;256;0
"Unit";"Overlord";"Larva";258;0
"Unit";"Overlord";"Larva";258;0
"Unit";"Hydralisk";"Larva";258;2
"Unit";"Hydralisk";"Larva";258;2
"Unit";"Roach";"Larva";262;2
"Unit";"Roach";"Larva";262;2
"Unit";"Roach";"Larva";262;2
"Unit";"Roach";"Larva";262;2
"Unit";"Roach";"Larva";262;2
"Unit";"Roach";"Larva";262;2
"Unit";"Roach";"Larva";262;2
"Building";"SpineCrawler";NA;262;0
"Building";"InfestationPit";NA;262;0
"Unit";"Hydralisk";"Larva";277;2
"Unit";"Hydralisk";"Larva";277;2
"Unit";"Hydralisk";"Larva";277;2
"Unit";"Hydralisk";"Larva";277;2
"Unit";"Hydralisk";"Larva";277;2
"Unit";"Hydralisk";"Larva";277;2
"Unit";"Hydralisk";"Larva";277;2
"Unit";"Roach";"Larva";277;2
"Unit";"Roach";"Larva";277;2
"Unit";"Roach";"Larva";277;2
"Unit";"Roach";"Larva";277;2
"Unit";"Roach";"Larva";277;2
"Unit";"Roach";"Larva";277;2
"Unit";"Roach";"Larva";277;2
"Unit";"Roach";"Larva";277;2
"Unit";"Roach";"Larva";277;2
"Unit";"Roach";"Larva";277;2
"Unit";"Roach";"Larva";277;2
"Unit";"Roach";"Larva";277;2
"Unit";"Roach";"Larva";277;2
"Unit";"Hydralisk";"Larva";277;2
"Upgrade";"ZergMissileWeaponsLevel2";"EvolutionChamber";258;0
"Building";"Hatchery";NA;262;0
"Unit";"Hydralisk";"Larva";322;2
"Unit";"Hydralisk";"Larva";322;2
"Unit";"Hydralisk";"Larva";322;2
"Unit";"Hydralisk";"Larva";322;2
"Unit";"Hydralisk";"Larva";330;2
"Unit";"Hydralisk";"Larva";330;2
"Unit";"Hydralisk";"Larva";330;2
"Unit";"Hydralisk";"Larva";330;2
"Unit";"Hydralisk";"Larva";330;2
"Unit";"Hydralisk";"Larva";330;2
"Unit";"Hydralisk";"Larva";330;2
"Unit";"Hydralisk";"Larva";330;2
"Unit";"Hydralisk";"Larva";330;2
"Unit";"Hydralisk";"Larva";330;2
"Unit";"Hydralisk";"Larva";330;2
"Unit";"Hydralisk";"Larva";330;2
"Unit";"Hydralisk";"Larva";330;2
"Unit";"Hydralisk";"Larva";330;2
"Unit";"Hydralisk";"Larva";342;2
"Unit";"Hydralisk";"Larva";342;2
"Unit";"Hydralisk";"Larva";342;2
"Unit";"Hydralisk";"Larva";342;2
"Unit";"Hydralisk";"Larva";342;2
"Unit";"Hydralisk";"Larva";342;2
"Unit";"Hydralisk";"Larva";342;2
"Unit";"Hydralisk";"Larva";342;2
"Unit";"Hydralisk";"Larva";342;2
"Unit";"Hydralisk";"Larva";342;2
"Unit";"Hydralisk";"Larva";342;2
"Unit";"Hydralisk";"Larva";342;2
"Unit";"Hydralisk";"Larva";342;2
"Unit";"Hydralisk";"Larva";342;2
