"type";"unit_name";"on_building";"total_supply";"supply"
"Unit";"Overlord";"Larva";13;0
"Building";"SpawningPool";NA;17;0
"Building";"Extractor";NA;18;0
"Unit";"Zergling";"Larva";21;1
"Unit";"Zergling";"Larva";21;1
"Unit";"Overlord";"Larva";21;0
"Unit";"Queen";"Hatchery";21;2
"Building";"Hatchery";NA;18;0
"Unit";"Queen";"Hatchery";24;2
"Unit";"Overlord";"Larva";28;0
"Unit";"Queen";"Hatchery";27;2
"Building";"CreepTumorQueen";NA;38;0
"Unit";"Zergling";"Larva";38;1
"Unit";"Zergling";"Larva";38;1
"Unit";"Zergling";"Larva";38;1
"Unit";"Zergling";"Larva";38;1
"Unit";"Overlord";"Larva";40;0
"Building";"CreepTumor";NA;50;0
"Unit";"Zergling";"Larva";51;1
"Unit";"Zergling";"Larva";51;1
"Unit";"Zergling";"Larva";51;1
"Unit";"Zergling";"Larva";51;1
"Unit";"Zergling";"Larva";51;1
"Unit";"Zergling";"Larva";51;1
"Unit";"Overlord";"Larva";59;0
"Building";"SporeCrawler";NA;59;0
"Building";"CreepTumorQueen";NA;63;0
"Building";"CreepTumorQueen";NA;63;0
"Building";"CreepTumor";NA;63;0
"Building";"SporeCrawler";NA;63;0
"Unit";"Queen";"Hatchery";59;2
"Unit";"Overlord";"Larva";65;0
"Building";"Hatchery";NA;51;0
"Building";"RoachWarren";NA;63;0
"Building";"SporeCrawler";NA;68;0
"Building";"CreepTumorQueen";NA;74;0
"Building";"CreepTumor";NA;75;0
"Building";"CreepTumor";NA;75;0
"Building";"CreepTumor";NA;75;0
"Unit";"Overlord";"Larva";75;0
"Unit";"Roach";"Larva";75;2
"Unit";"Roach";"Larva";75;2
"Unit";"Roach";"Larva";75;2
"Unit";"Roach";"Larva";75;2
"Unit";"Roach";"Larva";75;2
"Unit";"Roach";"Larva";75;2
"Unit";"Overlord";"Larva";75;0
"Building";"CreepTumorQueen";NA;75;0
"Unit";"Queen";"Hatchery";74;2
"Building";"CreepTumorQueen";NA;75;0
"Unit";"Overlord";"Larva";75;0
"Unit";"Overlord";"Larva";75;0
"Unit";"Overlord";"Larva";75;0
"Unit";"Queen";"Hatchery";75;2
"Building";"CreepTumor";NA;89;0
"Building";"CreepTumor";NA;89;0
"Building";"CreepTumor";NA;89;0
"Building";"CreepTumor";NA;89;0
"Building";"CreepTumor";NA;89;0
"Unit";"Queen";"Hatchery";87;2
"Building";"Extractor";NA;93;0
"Building";"Extractor";NA;94;0
"Building";"Extractor";NA;97;0
"Building";"Extractor";NA;97;0
"Building";"EvolutionChamber";NA;97;0
"Building";"Extractor";NA;113;0
"Building";"CreepTumor";NA;116;0
"Building";"CreepTumor";NA;116;0
"Building";"CreepTumor";NA;117;0
"Upgrade";"GlialReconstitution";"RoachWarren";89;0
"Building";"HydraliskDen";NA;113;0
"Building";"CreepTumor";NA;120;0
"Building";"CreepTumor";NA;120;0
"Unit";"Roach";"Larva";117;2
"Unit";"Roach";"Larva";117;2
"Unit";"Roach";"Larva";117;2
"Unit";"Roach";"Larva";117;2
"Unit";"Overlord";"Larva";120;0
"Unit";"Overlord";"Larva";120;0
"Unit";"Overlord";"Larva";120;0
"Unit";"Overlord";"Larva";120;0
"Building";"CreepTumor";NA;120;0
"Building";"CreepTumor";NA;128;0
"Building";"CreepTumor";NA;128;0
"Unit";"Overlord";"Larva";128;0
"Unit";"Overlord";"Larva";128;0
"Building";"CreepTumor";NA;128;0
"Unit";"Roach";"Larva";128;2
"Unit";"Roach";"Larva";128;2
"Unit";"Hydralisk";"Larva";128;2
"Unit";"Hydralisk";"Larva";128;2
"Unit";"Hydralisk";"Larva";128;2
"Unit";"Roach";"Larva";128;2
"Building";"CreepTumor";NA;128;0
"Building";"CreepTumor";NA;128;0
"Unit";"Roach";"Larva";128;2
"Unit";"Roach";"Larva";128;2
"Unit";"Roach";"Larva";128;2
"Unit";"Roach";"Larva";128;2
"Unit";"Roach";"Larva";128;2
"Unit";"Roach";"Larva";128;2
"Unit";"Roach";"Larva";128;2
"Unit";"Roach";"Larva";128;2
"Building";"Hatchery";NA;116;0
"Upgrade";"EvolveGroovedSpines";"HydraliskDen";128;0
"Building";"Extractor";NA;167;0
"Unit";"Hydralisk";"Larva";167;2
"Unit";"Hydralisk";"Larva";167;2
"Unit";"Hydralisk";"Larva";167;2
"Unit";"Hydralisk";"Larva";167;2
"Unit";"Hydralisk";"Larva";167;2
"Unit";"Hydralisk";"Larva";167;2
"Building";"CreepTumor";NA;170;0
"Building";"CreepTumor";NA;170;0
"Upgrade";"ZergMissileWeaponsLevel1";"EvolutionChamber";128;0
"Unit";"Overlord";"Larva";182;0
"Unit";"Overlord";"Larva";182;0
"Unit";"Overlord";"Larva";182;0
"Unit";"Overlord";"Larva";182;0
"Unit";"Overlord";"Larva";182;0
"Unit";"Hydralisk";"Larva";170;2
"Unit";"Hydralisk";"Larva";170;2
"Unit";"Hydralisk";"Larva";170;2
"Unit";"Hydralisk";"Larva";170;2
"Unit";"Hydralisk";"Larva";170;2
"Unit";"Hydralisk";"Larva";170;2
"Unit";"Hydralisk";"Larva";170;2
"Building";"CreepTumor";NA;182;0
"Building";"CreepTumor";NA;182;0
"Building";"CreepTumor";NA;182;0
"Building";"CreepTumor";NA;182;0
"Building";"CreepTumor";NA;182;0
"Unit";"Roach";"Larva";196;2
"Unit";"Roach";"Larva";196;2
"Unit";"Roach";"Larva";196;2
"Unit";"Hydralisk";"Larva";182;2
"Unit";"Hydralisk";"Larva";182;2
"Unit";"Hydralisk";"Larva";182;2
"Unit";"Hydralisk";"Larva";182;2
"Unit";"Hydralisk";"Larva";182;2
"Unit";"Hydralisk";"Larva";182;2
"Building";"CreepTumor";NA;214;0
"Building";"CreepTumor";NA;214;0
"Building";"CreepTumor";NA;214;0
"Unit";"Roach";"Larva";196;2
"Unit";"Roach";"Larva";196;2
"Unit";"Hydralisk";"Larva";196;2
"Unit";"Hydralisk";"Larva";196;2
"Unit";"Hydralisk";"Larva";196;2
"Unit";"Roach";"Larva";202;2
"Unit";"Hydralisk";"Larva";196;2
"Unit";"Hydralisk";"Larva";196;2
"Unit";"Hydralisk";"Larva";196;2
"Building";"CreepTumor";NA;214;0
"Building";"CreepTumor";NA;214;0
"Building";"Hatchery";NA;182;0
"Unit";"Zergling";"Larva";232;1
"Unit";"Zergling";"Larva";232;1
"Building";"CreepTumor";NA;234;0
"Upgrade";"EvolveMuscularAugments";"HydraliskDen";214;0
"Unit";"Roach";"Larva";234;2
"Unit";"Roach";"Larva";234;2
"Unit";"Roach";"Larva";234;2
"Unit";"Roach";"Larva";234;2
"Unit";"Roach";"Larva";234;2
"Unit";"Roach";"Larva";234;2
"Unit";"Roach";"Larva";234;2
"Unit";"Roach";"Larva";234;2
"Unit";"Roach";"Larva";234;2
"Unit";"Roach";"Larva";234;2
"Unit";"Roach";"Larva";234;2
"Unit";"Roach";"Larva";234;2
"Unit";"Roach";"Larva";234;2
"Unit";"Roach";"Larva";234;2
"Unit";"Roach";"Larva";234;2
"Unit";"Roach";"Larva";234;2
"Unit";"Roach";"Larva";234;2
"Unit";"Roach";"Larva";234;2
"Unit";"Roach";"Larva";234;2
"Unit";"Roach";"Larva";234;2
"Unit";"Roach";"Larva";234;2
"Unit";"Roach";"Larva";234;2
"Unit";"Roach";"Larva";234;2
"Unit";"Roach";"Larva";234;2
"Unit";"Hydralisk";"Larva";234;2
"Upgrade";"ZergMissileWeaponsLevel2";"EvolutionChamber";214;0
"Unit";"Hydralisk";"Larva";234;2
"Unit";"Hydralisk";"Larva";234;2
"Unit";"Hydralisk";"Larva";234;2
"Unit";"Hydralisk";"Larva";234;2
"Unit";"Hydralisk";"Larva";234;2
"Unit";"Hydralisk";"Larva";234;2
"Unit";"Hydralisk";"Larva";234;2
"Unit";"Hydralisk";"Larva";234;2
"Building";"CreepTumor";NA;300;0
"Unit";"Hydralisk";"Larva";280;2
"Unit";"Hydralisk";"Larva";280;2
"Unit";"Hydralisk";"Larva";280;2
"Unit";"Hydralisk";"Larva";280;2
"Unit";"Hydralisk";"Larva";280;2
"Unit";"Hydralisk";"Larva";280;2
"Unit";"Hydralisk";"Larva";280;2
"Unit";"Hydralisk";"Larva";280;2
"Unit";"Hydralisk";"Larva";280;2
"Building";"CreepTumor";NA;300;0
"Building";"CreepTumor";NA;300;0
"Building";"CreepTumor";NA;300;0
"Building";"InfestationPit";NA;300;0
"Unit";"Roach";"Larva";318;2
"Unit";"Roach";"Larva";318;2
"Unit";"Roach";"Larva";318;2
"Unit";"Roach";"Larva";318;2
"Unit";"Roach";"Larva";318;2
"Unit";"Roach";"Larva";318;2
"Unit";"Roach";"Larva";318;2
"Unit";"Roach";"Larva";318;2
"Unit";"Hydralisk";"Larva";318;2
"Unit";"Hydralisk";"Larva";318;2
"Unit";"Hydralisk";"Larva";318;2
"Unit";"Hydralisk";"Larva";318;2
"Unit";"Hydralisk";"Larva";318;2
"Unit";"Hydralisk";"Larva";318;2
"Unit";"Hydralisk";"Larva";318;2
"Unit";"Hydralisk";"Larva";318;2
"Unit";"Hydralisk";"Larva";318;2
"Unit";"Hydralisk";"Larva";318;2
"Unit";"Hydralisk";"Larva";318;2
"Unit";"Hydralisk";"Larva";318;2
"Unit";"Hydralisk";"Larva";318;2
"Unit";"Hydralisk";"Larva";318;2
"Unit";"Hydralisk";"Larva";318;2
"Unit";"Hydralisk";"Larva";318;2
"Unit";"Hydralisk";"Larva";318;2
"Unit";"Hydralisk";"Larva";318;2
"Unit";"Hydralisk";"Larva";318;2
"Unit";"Hydralisk";"Larva";318;2
"Unit";"Hydralisk";"Larva";318;2
"Building";"CreepTumor";NA;376;0
"Unit";"Overlord";"Larva";340;0
"Unit";"Overlord";"Larva";342;0
"Unit";"Overlord";"Larva";350;0
"Unit";"Overlord";"Larva";358;0
"Unit";"Overlord";"Larva";366;0
"Building";"Hatchery";NA;318;0
"Building";"CreepTumorQueen";NA;376;0
"Building";"Extractor";NA;334;0
"Building";"CreepTumor";NA;376;0
"Unit";"Roach";"Larva";376;2
"Unit";"Roach";"Larva";376;2
"Unit";"Roach";"Larva";376;2
"Unit";"Roach";"Larva";376;2
"Building";"CreepTumor";NA;376;0
"Unit";"Roach";"Larva";376;2
"Building";"CreepTumorQueen";NA;380;0
"Unit";"Overlord";"Larva";376;0
"Upgrade";"ZergGroundArmorsLevel1";"EvolutionChamber";318;0
"Unit";"Hydralisk";"Larva";390;2
"Unit";"Hydralisk";"Larva";390;2
"Unit";"Hydralisk";"Larva";390;2
"Unit";"Hydralisk";"Larva";390;2
"Unit";"Hydralisk";"Larva";390;2
"Building";"Extractor";NA;390;0
"Building";"Extractor";NA;390;0
"Building";"LurkerDenMP";NA;318;0
"Unit";"Roach";"Larva";390;2
"Unit";"Roach";"Larva";390;2
"Unit";"Roach";"Larva";390;2
"Unit";"Roach";"Larva";390;2
"Unit";"Roach";"Larva";390;2
"Unit";"Roach";"Larva";390;2
"Unit";"Roach";"Larva";390;2
"Unit";"Roach";"Larva";390;2
"Unit";"Roach";"Larva";392;2
"Unit";"Roach";"Larva";392;2
"Unit";"Roach";"Larva";392;2
"Unit";"Roach";"Larva";392;2
"Unit";"Roach";"Larva";392;2
"Unit";"Roach";"Larva";392;2
"Unit";"Roach";"Larva";392;2
"Unit";"Roach";"Larva";396;2
"Unit";"Roach";"Larva";396;2
"Unit";"Roach";"Larva";400;2
"Unit";"Roach";"Larva";400;2
"Unit";"Roach";"Larva";400;2
"Unit";"Roach";"Larva";400;2
"Unit";"Roach";"Larva";400;2
"Unit";"Roach";"Larva";400;2
"Unit";"Roach";"Larva";400;2
"Unit";"Roach";"Larva";400;2
"Unit";"Roach";"Larva";400;2
"Unit";"Zergling";"Larva";402;1
"Unit";"Zergling";"Larva";402;1
"Unit";"Roach";"Larva";402;2
"Unit";"Roach";"Larva";402;2
"Unit";"Roach";"Larva";402;2
"Unit";"Roach";"Larva";402;2
"Unit";"Roach";"Larva";402;2
"Unit";"Hydralisk";"Larva";464;2
"Unit";"Hydralisk";"Larva";464;2
"Unit";"Hydralisk";"Larva";464;2
"Building";"CreepTumor";NA;472;0
"Building";"CreepTumor";NA;472;0
"Unit";"Hydralisk";"Larva";466;2
"Unit";"Hydralisk";"Larva";468;2
"Unit";"Hydralisk";"Larva";468;2
"Unit";"Hydralisk";"Larva";472;2
"Building";"EvolutionChamber";NA;480;0
"Unit";"Hydralisk";"Larva";480;2
"Unit";"Hydralisk";"Larva";480;2
"Unit";"Hydralisk";"Larva";480;2
"Unit";"Hydralisk";"Larva";480;2
"Unit";"Hydralisk";"Larva";480;2
"Unit";"Hydralisk";"Larva";480;2
"Unit";"Hydralisk";"Larva";480;2
"Unit";"Hydralisk";"Larva";480;2
"Unit";"Hydralisk";"Larva";480;2
"Unit";"Hydralisk";"Larva";480;2
"Building";"Hatchery";NA;480;0
"Unit";"Hydralisk";"Larva";490;2
"Unit";"Hydralisk";"Larva";490;2
"Unit";"Hydralisk";"Larva";490;2
"Unit";"Hydralisk";"Larva";490;2
"Unit";"Hydralisk";"Larva";490;2
"Unit";"Hydralisk";"Larva";490;2
"Unit";"Hydralisk";"Larva";490;2
"Unit";"Hydralisk";"Larva";500;2
"Unit";"Hydralisk";"Larva";500;2
"Unit";"Hydralisk";"Larva";500;2
"Building";"Extractor";NA;500;0
"Upgrade";"ZergMissileWeaponsLevel3";"EvolutionChamber";472;0
"Building";"Extractor";NA;500;0
"Unit";"Hydralisk";"Larva";526;2
"Unit";"Hydralisk";"Larva";526;2
"Unit";"Hydralisk";"Larva";526;2
"Unit";"Hydralisk";"Larva";526;2
"Unit";"Hydralisk";"Larva";526;2
"Unit";"Zergling";"Larva";526;1
"Unit";"Zergling";"Larva";526;1
"Unit";"Zergling";"Larva";526;1
"Unit";"Zergling";"Larva";526;1
"Unit";"Zergling";"Larva";526;1
"Unit";"Zergling";"Larva";526;1
"Unit";"Zergling";"Larva";526;1
"Unit";"Zergling";"Larva";526;1
"Unit";"Zergling";"Larva";526;1
"Unit";"Zergling";"Larva";526;1
"Unit";"Zergling";"Larva";526;1
"Unit";"Zergling";"Larva";526;1
"Unit";"Zergling";"Larva";526;1
"Unit";"Zergling";"Larva";526;1
"Unit";"Zergling";"Larva";526;1
"Unit";"Zergling";"Larva";526;1
"Unit";"Zergling";"Larva";526;1
"Unit";"Zergling";"Larva";526;1
"Unit";"Zergling";"Larva";526;1
"Unit";"Zergling";"Larva";526;1
"Unit";"Zergling";"Larva";526;1
"Unit";"Zergling";"Larva";526;1
"Unit";"Hydralisk";"Larva";526;2
"Unit";"Hydralisk";"Larva";526;2
"Unit";"Hydralisk";"Larva";526;2
"Unit";"Hydralisk";"Larva";526;2
"Unit";"Hydralisk";"Larva";526;2
"Unit";"Hydralisk";"Larva";526;2
"Unit";"Hydralisk";"Larva";526;2
"Unit";"Hydralisk";"Larva";526;2
"Unit";"Hydralisk";"Larva";526;2
"Unit";"Hydralisk";"Larva";526;2
"Unit";"Hydralisk";"Larva";526;2
"Unit";"Hydralisk";"Larva";526;2
"Unit";"Hydralisk";"Larva";526;2
"Unit";"Hydralisk";"Larva";526;2
"Upgrade";"ZergGroundArmorsLevel2";"EvolutionChamber";500;0
"Unit";"Hydralisk";"Larva";586;2
"Unit";"Hydralisk";"Larva";586;2
"Unit";"Hydralisk";"Larva";586;2
"Unit";"Hydralisk";"Larva";586;2
"Unit";"Hydralisk";"Larva";586;2
"Unit";"Hydralisk";"Larva";586;2
"Unit";"Hydralisk";"Larva";586;2
"Unit";"Hydralisk";"Larva";586;2
"Unit";"Hydralisk";"Larva";586;2
"Unit";"Hydralisk";"Larva";586;2
"Unit";"Hydralisk";"Larva";586;2
"Unit";"Hydralisk";"Larva";586;2
"Unit";"Hydralisk";"Larva";586;2
"Unit";"Hydralisk";"Larva";586;2
"Unit";"Hydralisk";"Larva";586;2
"Unit";"Hydralisk";"Larva";586;2
"Unit";"Hydralisk";"Larva";586;2
"Unit";"Hydralisk";"Larva";586;2
"Unit";"Hydralisk";"Larva";586;2
"Unit";"Hydralisk";"Larva";586;2
"Unit";"Hydralisk";"Larva";586;2
"Unit";"Overlord";"Larva";598;0
"Unit";"Overlord";"Larva";598;0
"Unit";"Overlord";"Larva";598;0
"Unit";"Zergling";"Larva";598;1
"Unit";"Zergling";"Larva";598;1
"Unit";"Zergling";"Larva";598;1
"Unit";"Zergling";"Larva";598;1
"Unit";"Zergling";"Larva";598;1
"Unit";"Zergling";"Larva";598;1
"Unit";"Zergling";"Larva";598;1
"Unit";"Zergling";"Larva";598;1
"Unit";"Zergling";"Larva";598;1
"Unit";"Zergling";"Larva";598;1
"Unit";"Hydralisk";"Larva";598;2
"Unit";"Hydralisk";"Larva";598;2
"Unit";"Hydralisk";"Larva";598;2
"Unit";"Hydralisk";"Larva";598;2
"Unit";"Hydralisk";"Larva";598;2
"Unit";"Hydralisk";"Larva";598;2
"Unit";"Hydralisk";"Larva";598;2
"Unit";"Hydralisk";"Larva";598;2
"Building";"CreepTumor";NA;628;0
"Building";"CreepTumor";NA;628;0
"Building";"CreepTumor";NA;628;0
"Building";"CreepTumor";NA;636;0
"Upgrade";"ZergMeleeWeaponsLevel1";"EvolutionChamber";586;0
"Unit";"Hydralisk";"Larva";654;2
"Unit";"Hydralisk";"Larva";654;2
"Unit";"Hydralisk";"Larva";654;2
"Unit";"Hydralisk";"Larva";654;2
"Unit";"Zergling";"Larva";654;1
"Unit";"Zergling";"Larva";654;1
"Unit";"Zergling";"Larva";654;1
"Unit";"Zergling";"Larva";654;1
"Unit";"Zergling";"Larva";654;1
"Unit";"Zergling";"Larva";654;1
"Unit";"Zergling";"Larva";654;1
"Unit";"Zergling";"Larva";654;1
"Unit";"Zergling";"Larva";654;1
"Unit";"Zergling";"Larva";654;1
"Unit";"Zergling";"Larva";654;1
"Unit";"Zergling";"Larva";654;1
"Unit";"Zergling";"Larva";654;1
"Unit";"Zergling";"Larva";654;1
"Unit";"Zergling";"Larva";654;1
"Unit";"Zergling";"Larva";654;1
"Unit";"Zergling";"Larva";654;1
"Unit";"Zergling";"Larva";654;1
"Unit";"Zergling";"Larva";654;1
"Unit";"Zergling";"Larva";654;1
"Unit";"Zergling";"Larva";654;1
"Unit";"Zergling";"Larva";654;1
"Unit";"Zergling";"Larva";654;1
"Unit";"Zergling";"Larva";654;1
"Unit";"Zergling";"Larva";654;1
"Unit";"Zergling";"Larva";654;1
"Unit";"Zergling";"Larva";654;1
"Unit";"Zergling";"Larva";654;1
"Unit";"Zergling";"Larva";654;1
"Unit";"Zergling";"Larva";654;1
"Unit";"Zergling";"Larva";654;1
"Unit";"Zergling";"Larva";654;1
"Unit";"Zergling";"Larva";654;1
"Unit";"Zergling";"Larva";654;1
"Unit";"Hydralisk";"Larva";654;2
"Unit";"Hydralisk";"Larva";654;2
"Unit";"Hydralisk";"Larva";654;2
"Unit";"Hydralisk";"Larva";654;2
"Unit";"Hydralisk";"Larva";654;2
"Unit";"Hydralisk";"Larva";654;2
"Unit";"Hydralisk";"Larva";654;2
"Unit";"Hydralisk";"Larva";654;2
"Unit";"Hydralisk";"Larva";654;2
"Unit";"Hydralisk";"Larva";654;2
"Unit";"Hydralisk";"Larva";654;2
"Unit";"Hydralisk";"Larva";654;2
"Unit";"Hydralisk";"Larva";654;2
"Unit";"Hydralisk";"Larva";654;2
"Unit";"Hydralisk";"Larva";654;2
"Unit";"Hydralisk";"Larva";654;2
"Unit";"Hydralisk";"Larva";654;2
"Unit";"Hydralisk";"Larva";654;2
"Unit";"Hydralisk";"Larva";654;2
"Unit";"Hydralisk";"Larva";654;2
"Unit";"Hydralisk";"Larva";654;2
"Unit";"Hydralisk";"Larva";654;2
"Unit";"Hydralisk";"Larva";654;2
"Unit";"Hydralisk";"Larva";654;2
"Unit";"Zergling";"Larva";696;1
"Unit";"Zergling";"Larva";696;1
"Unit";"Zergling";"Larva";696;1
"Unit";"Zergling";"Larva";696;1
"Unit";"Zergling";"Larva";696;1
"Unit";"Zergling";"Larva";696;1
"Unit";"Zergling";"Larva";696;1
"Unit";"Zergling";"Larva";696;1
"Unit";"Zergling";"Larva";696;1
"Unit";"Zergling";"Larva";696;1
"Unit";"Zergling";"Larva";696;1
"Unit";"Zergling";"Larva";696;1
"Unit";"Zergling";"Larva";696;1
"Unit";"Zergling";"Larva";696;1
"Unit";"Zergling";"Larva";696;1
"Unit";"Zergling";"Larva";696;1
"Unit";"Zergling";"Larva";696;1
"Unit";"Zergling";"Larva";696;1
"Unit";"Hydralisk";"Larva";664;2
"Unit";"Hydralisk";"Larva";666;2
"Unit";"Hydralisk";"Larva";666;2
"Unit";"Hydralisk";"Larva";666;2
"Unit";"Hydralisk";"Larva";670;2
"Building";"Extractor";NA;730;0
"Building";"Extractor";NA;762;0
"Unit";"Viper";"Larva";777;3
"Unit";"Overlord";"Larva";777;0
"Unit";"Overlord";"Larva";777;0
"Unit";"Overlord";"Larva";777;0
"Unit";"Overlord";"Larva";777;0
"Unit";"Overlord";"Larva";777;0
"Unit";"Overlord";"Larva";777;0
"Unit";"Overlord";"Larva";777;0
"Unit";"Overlord";"Larva";777;0
"Unit";"Overlord";"Larva";777;0
"Unit";"Hydralisk";"Larva";777;2
"Unit";"Hydralisk";"Larva";777;2
"Unit";"Hydralisk";"Larva";777;2
"Unit";"Hydralisk";"Larva";780;2
"Unit";"Hydralisk";"Larva";780;2
"Unit";"Hydralisk";"Larva";780;2
"Unit";"Hydralisk";"Larva";780;2
"Unit";"Hydralisk";"Larva";780;2
"Unit";"Hydralisk";"Larva";780;2
"Unit";"Hydralisk";"Larva";780;2
"Unit";"Hydralisk";"Larva";780;2
"Unit";"Hydralisk";"Larva";780;2
"Unit";"Hydralisk";"Larva";780;2
"Unit";"Hydralisk";"Larva";782;2
"Unit";"Viper";"Larva";780;3
"Unit";"Viper";"Larva";780;3
"Unit";"Viper";"Larva";780;3
"Unit";"Hydralisk";"Larva";786;2
"Unit";"Hydralisk";"Larva";786;2
"Unit";"Hydralisk";"Larva";786;2
"Unit";"Hydralisk";"Larva";786;2
"Unit";"Hydralisk";"Larva";786;2
"Unit";"Hydralisk";"Larva";786;2
"Unit";"Hydralisk";"Larva";786;2
"Unit";"Hydralisk";"Larva";786;2
"Unit";"Hydralisk";"Larva";786;2
"Unit";"Zergling";"Larva";817;1
"Unit";"Zergling";"Larva";817;1
"Unit";"Hydralisk";"Larva";817;2
"Unit";"Hydralisk";"Larva";817;2
"Upgrade";"ZergMeleeWeaponsLevel2";"EvolutionChamber";777;0
"Upgrade";"ZergGroundArmorsLevel3";"EvolutionChamber";777;0
"Unit";"Zergling";"Larva";841;1
"Unit";"Zergling";"Larva";841;1
"Unit";"Hydralisk";"Larva";841;2
"Unit";"Hydralisk";"Larva";841;2
"Unit";"Hydralisk";"Larva";841;2
"Unit";"Hydralisk";"Larva";841;2
"Unit";"Hydralisk";"Larva";841;2
"Unit";"Hydralisk";"Larva";841;2
"Unit";"Hydralisk";"Larva";841;2
"Unit";"Hydralisk";"Larva";841;2
"Unit";"Hydralisk";"Larva";841;2
"Unit";"Hydralisk";"Larva";841;2
"Unit";"Hydralisk";"Larva";841;2
"Unit";"Hydralisk";"Larva";841;2
"Unit";"Hydralisk";"Larva";841;2
"Unit";"Hydralisk";"Larva";841;2
"Unit";"Hydralisk";"Larva";841;2
"Unit";"Hydralisk";"Larva";841;2
"Unit";"Hydralisk";"Larva";841;2
"Unit";"Hydralisk";"Larva";841;2
"Unit";"Hydralisk";"Larva";841;2
"Unit";"Hydralisk";"Larva";841;2
"Unit";"Hydralisk";"Larva";841;2
"Unit";"Hydralisk";"Larva";841;2
"Unit";"Hydralisk";"Larva";841;2
"Unit";"Hydralisk";"Larva";841;2
"Unit";"Hydralisk";"Larva";841;2
"Unit";"Hydralisk";"Larva";841;2
"Unit";"Hydralisk";"Larva";841;2
"Unit";"Zergling";"Larva";843;1
"Unit";"Zergling";"Larva";843;1
"Unit";"Zergling";"Larva";843;1
"Unit";"Zergling";"Larva";843;1
"Unit";"Zergling";"Larva";843;1
"Unit";"Zergling";"Larva";843;1
"Unit";"Zergling";"Larva";843;1
"Unit";"Zergling";"Larva";843;1
"Unit";"Zergling";"Larva";843;1
"Unit";"Zergling";"Larva";843;1
"Unit";"Zergling";"Larva";843;1
"Unit";"Zergling";"Larva";843;1
"Unit";"Zergling";"Larva";843;1
"Unit";"Zergling";"Larva";843;1
"Unit";"Zergling";"Larva";843;1
"Unit";"Zergling";"Larva";843;1
"Unit";"Zergling";"Larva";843;1
"Unit";"Zergling";"Larva";843;1
"Unit";"Zergling";"Larva";843;1
"Unit";"Zergling";"Larva";843;1
"Unit";"Zergling";"Larva";843;1
"Unit";"Zergling";"Larva";843;1
"Unit";"Zergling";"Larva";843;1
"Unit";"Zergling";"Larva";843;1
"Unit";"Zergling";"Larva";843;1
"Unit";"Zergling";"Larva";843;1
"Unit";"Zergling";"Larva";843;1
"Unit";"Zergling";"Larva";843;1
"Unit";"Zergling";"Larva";843;1
"Unit";"Zergling";"Larva";843;1
"Unit";"Zergling";"Larva";843;1
"Unit";"Zergling";"Larva";843;1
"Unit";"Zergling";"Larva";843;1
"Unit";"Zergling";"Larva";843;1
"Unit";"Zergling";"Larva";843;1
"Unit";"Zergling";"Larva";843;1
"Unit";"Zergling";"Larva";843;1
"Unit";"Zergling";"Larva";843;1
"Unit";"Zergling";"Larva";843;1
"Unit";"Zergling";"Larva";843;1
"Unit";"Zergling";"Larva";843;1
"Unit";"Zergling";"Larva";843;1
"Unit";"Hydralisk";"Larva";843;2
"Unit";"Hydralisk";"Larva";843;2
"Unit";"Hydralisk";"Larva";843;2
"Unit";"Hydralisk";"Larva";843;2
"Building";"Hatchery";NA;841;0
"Building";"Extractor";NA;947;0
"Building";"Extractor";NA;947;0
"Unit";"Viper";"Larva";947;3
"Unit";"Viper";"Larva";947;3
"Unit";"Viper";"Larva";947;3
"Building";"SporeCrawler";NA;956;0
"Building";"SporeCrawler";NA;956;0
"Building";"SporeCrawler";NA;956;0
"Building";"SpineCrawler";NA;956;0
"Building";"SpineCrawler";NA;956;0
"Upgrade";"Burrow";"Hatchery";956;0
"Unit";"Hydralisk";"Larva";956;2
"Unit";"Hydralisk";"Larva";956;2
"Unit";"Hydralisk";"Larva";956;2
"Unit";"Hydralisk";"Larva";956;2
"Unit";"Hydralisk";"Larva";956;2
"Unit";"Hydralisk";"Larva";956;2
"Unit";"Hydralisk";"Larva";956;2
"Unit";"Hydralisk";"Larva";956;2
"Unit";"Hydralisk";"Larva";956;2
"Unit";"Hydralisk";"Larva";956;2
"Unit";"Hydralisk";"Larva";956;2
"Unit";"Zergling";"Larva";956;1
"Unit";"Zergling";"Larva";956;1
"Unit";"Zergling";"Larva";956;1
"Unit";"Zergling";"Larva";956;1
"Unit";"Zergling";"Larva";956;1
"Unit";"Zergling";"Larva";956;1
"Unit";"Zergling";"Larva";956;1
"Unit";"Zergling";"Larva";956;1
"Unit";"Zergling";"Larva";956;1
"Unit";"Zergling";"Larva";956;1
"Unit";"Zergling";"Larva";956;1
"Unit";"Zergling";"Larva";956;1
"Unit";"Zergling";"Larva";956;1
"Unit";"Zergling";"Larva";956;1
"Unit";"Zergling";"Larva";956;1
"Unit";"Zergling";"Larva";956;1
"Unit";"Zergling";"Larva";956;1
"Unit";"Zergling";"Larva";956;1
"Unit";"Zergling";"Larva";956;1
"Unit";"Zergling";"Larva";956;1
"Unit";"Zergling";"Larva";956;1
"Unit";"Zergling";"Larva";956;1
"Unit";"Zergling";"Larva";956;1
"Unit";"Zergling";"Larva";956;1
"Unit";"Zergling";"Larva";956;1
"Unit";"Zergling";"Larva";956;1
"Unit";"Zergling";"Larva";956;1
"Unit";"Zergling";"Larva";956;1
"Unit";"Zergling";"Larva";956;1
"Unit";"Zergling";"Larva";956;1
"Unit";"Zergling";"Larva";956;1
"Unit";"Zergling";"Larva";956;1
"Unit";"Zergling";"Larva";956;1
"Unit";"Zergling";"Larva";956;1
"Unit";"Zergling";"Larva";956;1
"Unit";"Zergling";"Larva";956;1
"Unit";"Zergling";"Larva";956;1
"Unit";"Zergling";"Larva";956;1
"Unit";"Zergling";"Larva";956;1
"Unit";"Zergling";"Larva";956;1
"Unit";"Zergling";"Larva";956;1
"Unit";"Zergling";"Larva";956;1
"Unit";"Hydralisk";"Larva";956;2
"Unit";"Hydralisk";"Larva";956;2
"Unit";"Hydralisk";"Larva";956;2
"Unit";"Hydralisk";"Larva";956;2
"Unit";"Hydralisk";"Larva";956;2
"Unit";"Zergling";"Larva";958;1
"Unit";"Zergling";"Larva";958;1
"Unit";"Hydralisk";"Larva";956;2
"Unit";"Hydralisk";"Larva";956;2
"Unit";"Hydralisk";"Larva";956;2
"Unit";"Hydralisk";"Larva";992;2
"Unit";"Hydralisk";"Larva";992;2
"Unit";"Hydralisk";"Larva";1032;2
"Unit";"Hydralisk";"Larva";1032;2
"Unit";"Hydralisk";"Larva";1032;2
"Unit";"Zergling";"Larva";1042;1
"Unit";"Zergling";"Larva";1042;1
"Unit";"Hydralisk";"Larva";1042;2
"Unit";"Hydralisk";"Larva";1042;2
"Unit";"Hydralisk";"Larva";1042;2
"Unit";"Hydralisk";"Larva";1042;2
