"type";"unit_name";"on_building";"total_supply";"supply"
"Unit";"Overlord";"Larva";12;0
"Building";"Extractor";NA;18;0
"Building";"SpawningPool";NA;19;0
"Building";"Hatchery";NA;17;0
"Unit";"Zergling";"Larva";25;1
"Unit";"Zergling";"Larva";25;1
"Unit";"Queen";"Hatchery";24;2
"Unit";"Overlord";"Larva";25;0
"Unit";"Queen";"Hatchery";25;2
"Unit";"Overlord";"Larva";25;0
"Building";"Hatchery";NA;22;0
"Building";"CreepTumorQueen";NA;33;0
"Unit";"Zergling";"Larva";31;1
"Unit";"Zergling";"Larva";31;1
"Unit";"Zergling";"Larva";31;1
"Unit";"Zergling";"Larva";31;1
"Unit";"Zergling";"Larva";31;1
"Unit";"Zergling";"Larva";31;1
"Unit";"Overlord";"Larva";41;0
"Unit";"Queen";"Hatchery";33;2
"Unit";"Queen";"Hatchery";39;2
"Building";"CreepTumor";NA;42;0
"Unit";"Zergling";"Larva";42;1
"Unit";"Zergling";"Larva";42;1
"Building";"CreepTumorQueen";NA;58;0
"Unit";"Overlord";"Larva";58;0
"Unit";"Overlord";"Larva";64;0
"Unit";"Zergling";"Larva";64;1
"Unit";"Zergling";"Larva";64;1
"Building";"Extractor";NA;64;0
"Building";"Extractor";NA;64;0
"Unit";"Overlord";"Larva";65;0
"Unit";"Zergling";"Larva";68;1
"Unit";"Zergling";"Larva";68;1
"Unit";"Zergling";"Larva";71;1
"Unit";"Zergling";"Larva";71;1
"Unit";"Zergling";"Larva";71;1
"Unit";"Zergling";"Larva";71;1
"Unit";"Zergling";"Larva";71;1
"Unit";"Zergling";"Larva";71;1
"Building";"CreepTumorQueen";NA;76;0
"Unit";"Zergling";"Larva";73;1
"Unit";"Zergling";"Larva";73;1
"Unit";"Zergling";"Larva";74;1
"Unit";"Zergling";"Larva";74;1
"Unit";"Zergling";"Larva";74;1
"Unit";"Zergling";"Larva";74;1
"Unit";"Zergling";"Larva";74;1
"Unit";"Zergling";"Larva";74;1
"Unit";"Overlord";"Larva";74;0
"Building";"CreepTumor";NA;78;0
"Building";"CreepTumor";NA;82;0
"Unit";"Overlord";"Larva";76;0
"Building";"CreepTumorQueen";NA;84;0
"Building";"RoachWarren";NA;69;0
"Unit";"Zergling";"Larva";84;1
"Unit";"Zergling";"Larva";84;1
"Unit";"Zergling";"Larva";84;1
"Unit";"Zergling";"Larva";84;1
"Unit";"Zergling";"Larva";84;1
"Unit";"Zergling";"Larva";84;1
"Unit";"Zergling";"Larva";84;1
"Unit";"Zergling";"Larva";84;1
"Unit";"Overlord";"Larva";93;0
"Unit";"Roach";"Larva";93;2
"Unit";"Roach";"Larva";93;2
"Unit";"Roach";"Larva";93;2
"Unit";"Roach";"Larva";93;2
"Unit";"Roach";"Larva";93;2
"Unit";"Roach";"Larva";93;2
"Unit";"Roach";"Larva";101;2
"Unit";"Roach";"Larva";101;2
"Unit";"Roach";"Larva";101;2
"Unit";"Roach";"Larva";101;2
"Unit";"Roach";"Larva";101;2
"Unit";"Roach";"Larva";101;2
"Unit";"Roach";"Larva";103;2
"Unit";"Roach";"Larva";121;2
"Unit";"Roach";"Larva";121;2
"Unit";"Roach";"Larva";121;2
"Unit";"Roach";"Larva";121;2
"Unit";"Roach";"Larva";121;2
"Unit";"Queen";"Hatchery";101;2
"Unit";"Roach";"Larva";121;2
"Unit";"Roach";"Larva";121;2
"Unit";"Roach";"Larva";127;2
"Unit";"Roach";"Larva";127;2
"Unit";"Overlord";"Larva";127;0
"Unit";"Overlord";"Larva";127;0
"Unit";"Overlord";"Larva";137;0
"Unit";"Roach";"Larva";139;2
"Unit";"Roach";"Larva";139;2
"Unit";"Overlord";"Larva";143;0
"Upgrade";"GlialReconstitution";"RoachWarren";147;0
"Building";"Extractor";NA;173;0
"Unit";"Roach";"Larva";173;2
"Unit";"Roach";"Larva";173;2
"Unit";"Roach";"Larva";173;2
"Unit";"Roach";"Larva";173;2
"Unit";"Roach";"Larva";183;2
"Unit";"Overlord";"Larva";183;0
"Unit";"Roach";"Larva";183;2
"Unit";"Roach";"Larva";191;2
"Unit";"Roach";"Larva";191;2
"Unit";"Roach";"Larva";191;2
"Unit";"Roach";"Larva";191;2
"Unit";"Roach";"Larva";191;2
"Building";"SporeCrawler";NA;193;0
"Unit";"Queen";"Hatchery";183;2
"Building";"EvolutionChamber";NA;193;0
"Unit";"Roach";"Larva";205;2
"Unit";"Roach";"Larva";205;2
"Unit";"Roach";"Larva";205;2
"Unit";"Roach";"Larva";210;2
"Unit";"Roach";"Larva";210;2
"Unit";"Roach";"Larva";210;2
"Unit";"Roach";"Larva";210;2
"Building";"CreepTumor";NA;216;0
"Unit";"Overlord";"Larva";210;0
"Unit";"Roach";"Larva";216;2
"Unit";"Roach";"Larva";216;2
"Building";"SporeCrawler";NA;216;0
"Building";"HydraliskDen";NA;216;0
"Unit";"Roach";"Larva";224;2
"Unit";"Roach";"Larva";224;2
"Unit";"Roach";"Larva";224;2
"Unit";"Roach";"Larva";225;2
"Building";"Hatchery";NA;195;0
"Unit";"Overlord";"Larva";229;0
"Building";"SpineCrawler";NA;216;0
"Unit";"Overlord";"Larva";230;0
"Unit";"Overlord";"Larva";230;0
"Unit";"Overlord";"Larva";230;0
"Unit";"Roach";"Larva";238;2
"Unit";"Roach";"Larva";238;2
"Unit";"Roach";"Larva";238;2
"Unit";"Roach";"Larva";238;2
"Unit";"Roach";"Larva";238;2
"Unit";"Roach";"Larva";238;2
"Unit";"Roach";"Larva";238;2
"Unit";"Roach";"Larva";238;2
"Unit";"Roach";"Larva";238;2
"Unit";"Roach";"Larva";238;2
"Unit";"Roach";"Larva";238;2
"Unit";"Hydralisk";"Larva";238;2
"Unit";"Roach";"Larva";238;2
"Unit";"Roach";"Larva";238;2
"Unit";"Roach";"Larva";238;2
"Unit";"Roach";"Larva";238;2
"Unit";"Roach";"Larva";238;2
"Unit";"Roach";"Larva";238;2
"Unit";"Hydralisk";"Larva";250;2
"Unit";"Hydralisk";"Larva";250;2
"Unit";"Hydralisk";"Larva";250;2
"Unit";"Hydralisk";"Larva";250;2
"Unit";"Hydralisk";"Larva";250;2
"Unit";"Hydralisk";"Larva";260;2
"Building";"Extractor";NA;274;0
"Building";"Extractor";NA;274;0
"Unit";"Queen";"Hatchery";260;2
"Unit";"Roach";"Larva";284;2
"Unit";"Roach";"Larva";284;2
"Unit";"Roach";"Larva";284;2
"Unit";"Roach";"Larva";293;2
"Unit";"Roach";"Larva";294;2
"Unit";"Overlord";"Larva";294;0
"Unit";"Roach";"Larva";294;2
"Unit";"Roach";"Larva";294;2
"Building";"Extractor";NA;310;0
"Building";"Extractor";NA;310;0
"Unit";"Hydralisk";"Larva";310;2
"Unit";"Hydralisk";"Larva";310;2
"Unit";"Hydralisk";"Larva";310;2
"Unit";"Hydralisk";"Larva";310;2
"Unit";"Overlord";"Larva";318;0
"Upgrade";"ZergMissileWeaponsLevel1";"EvolutionChamber";274;0
"Building";"InfestationPit";NA;310;0
"Upgrade";"EvolveGroovedSpines";"HydraliskDen";310;0
"Unit";"Hydralisk";"Larva";322;2
