"type";"unit_name";"on_building";"total_supply";"supply"
"Unit";"Overlord";"Larva";13;0
"Building";"Extractor";NA;17;0
"Unit";"Overlord";"Larva";21;0
"Building";"Hatchery";NA;17;0
"Building";"SpawningPool";NA;19;0
"Unit";"Zergling";"Larva";23;1
"Unit";"Zergling";"Larva";23;1
"Unit";"Zergling";"Larva";23;1
"Unit";"Zergling";"Larva";23;1
"Unit";"Queen";"Hatchery";23;2
"Unit";"Queen";"Hatchery";23;2
"Building";"CreepTumorQueen";NA;36;0
"Unit";"Overlord";"Larva";37;0
"Unit";"Queen";"Hatchery";36;2
"Unit";"Overlord";"Larva";40;0
"Building";"CreepTumor";NA;47;0
"Building";"CreepTumorQueen";NA;47;0
"Building";"Hatchery";NA;34;0
"Building";"SporeCrawler";NA;47;0
"Unit";"Zergling";"Larva";47;1
"Unit";"Zergling";"Larva";47;1
"Unit";"Zergling";"Larva";47;1
"Unit";"Zergling";"Larva";47;1
"Building";"SporeCrawler";NA;47;0
"Unit";"Queen";"Hatchery";47;2
"Building";"CreepTumorQueen";NA;60;0
"Building";"CreepTumor";NA;60;0
"Building";"Extractor";NA;49;0
"Unit";"Overlord";"Larva";62;0
"Unit";"Overlord";"Larva";62;0
"Unit";"Overlord";"Larva";62;0
"Building";"CreepTumorQueen";NA;68;0
"Building";"CreepTumor";NA;68;0
"Unit";"Queen";"Hatchery";62;2
"Unit";"Overlord";"Larva";68;0
"Building";"CreepTumorQueen";NA;70;0
"Building";"CreepTumor";NA;70;0
"Unit";"Zergling";"Larva";70;1
"Unit";"Zergling";"Larva";70;1
"Unit";"Zergling";"Larva";70;1
"Unit";"Zergling";"Larva";70;1
"Unit";"Zergling";"Larva";70;1
"Unit";"Zergling";"Larva";70;1
"Unit";"Zergling";"Larva";70;1
"Unit";"Zergling";"Larva";70;1
"Unit";"Zergling";"Larva";70;1
"Unit";"Zergling";"Larva";70;1
"Unit";"Queen";"Hatchery";68;2
"Building";"CreepTumor";NA;70;0
"Building";"RoachWarren";NA;68;0
"Building";"CreepTumorQueen";NA;80;0
"Unit";"Overlord";"Larva";80;0
"Unit";"Overlord";"Larva";80;0
"Unit";"Overlord";"Larva";80;0
"Unit";"Overlord";"Larva";80;0
"Building";"CreepTumor";NA;87;0
"Building";"CreepTumor";NA;87;0
"Building";"CreepTumorQueen";NA;87;0
"Unit";"Roach";"Larva";87;2
"Unit";"Roach";"Larva";87;2
"Unit";"Roach";"Larva";87;2
"Unit";"Roach";"Larva";87;2
"Unit";"Roach";"Larva";87;2
"Unit";"Roach";"Larva";87;2
"Unit";"Roach";"Larva";87;2
"Building";"CreepTumor";NA;87;0
"Building";"CreepTumor";NA;87;0
"Building";"CreepTumor";NA;101;0
"Building";"Extractor";NA;101;0
"Building";"Extractor";NA;101;0
"Building";"CreepTumor";NA;101;0
"Building";"CreepTumor";NA;101;0
"Building";"HydraliskDen";NA;101;0
"Building";"CreepTumor";NA;113;0
"Building";"Extractor";NA;113;0
"Building";"Extractor";NA;113;0
"Building";"CreepTumorQueen";NA;117;0
"Building";"CreepTumorQueen";NA;117;0
"Building";"CreepTumorQueen";NA;117;0
"Building";"CreepTumorQueen";NA;117;0
"Building";"EvolutionChamber";NA;117;0
"Unit";"Overlord";"Larva";117;0
"Unit";"Overlord";"Larva";117;0
"Building";"CreepTumor";NA;117;0
"Building";"CreepTumor";NA;117;0
"Building";"CreepTumor";NA;117;0
"Building";"CreepTumorQueen";NA;117;0
"Building";"CreepTumor";NA;117;0
"Building";"CreepTumor";NA;117;0
"Building";"CreepTumor";NA;126;0
"Building";"CreepTumor";NA;126;0
"Building";"CreepTumor";NA;126;0
"Unit";"Overlord";"Larva";126;0
"Unit";"Hydralisk";"Larva";126;2
"Unit";"Hydralisk";"Larva";126;2
"Unit";"Hydralisk";"Larva";126;2
"Unit";"Hydralisk";"Larva";126;2
"Unit";"Hydralisk";"Larva";126;2
"Unit";"Hydralisk";"Larva";126;2
"Building";"CreepTumor";NA;126;0
"Building";"CreepTumor";NA;126;0
"Building";"CreepTumor";NA;126;0
"Upgrade";"GlialReconstitution";"RoachWarren";117;0
"Upgrade";"EvolveGroovedSpines";"HydraliskDen";117;0
"Building";"CreepTumor";NA;141;0
"Building";"CreepTumor";NA;141;0
"Building";"CreepTumor";NA;141;0
"Building";"Hatchery";NA;117;0
"Building";"CreepTumor";NA;153;0
"Unit";"Overlord";"Larva";153;0
"Building";"CreepTumor";NA;153;0
"Building";"CreepTumor";NA;153;0
"Building";"CreepTumor";NA;153;0
"Building";"CreepTumor";NA;153;0
"Building";"Hatchery";NA;126;0
"Building";"Extractor";NA;153;0
"Building";"CreepTumorQueen";NA;155;0
"Building";"Extractor";NA;155;0
"Unit";"Hydralisk";"Larva";155;2
"Unit";"Hydralisk";"Larva";155;2
"Unit";"Hydralisk";"Larva";155;2
"Unit";"Hydralisk";"Larva";155;2
"Unit";"Hydralisk";"Larva";155;2
"Unit";"Hydralisk";"Larva";155;2
"Unit";"Hydralisk";"Larva";155;2
"Unit";"Hydralisk";"Larva";155;2
"Building";"CreepTumorQueen";NA;155;0
"Building";"LurkerDenMP";NA;126;0
"Building";"CreepTumor";NA;155;0
"Building";"CreepTumor";NA;155;0
"Building";"CreepTumorQueen";NA;155;0
"Building";"CreepTumor";NA;155;0
"Building";"CreepTumor";NA;155;0
"Building";"CreepTumor";NA;155;0
"Unit";"Overlord";"Larva";171;0
"Unit";"Overlord";"Larva";171;0
"Unit";"Overlord";"Larva";171;0
"Upgrade";"ZergMissileWeaponsLevel1";"EvolutionChamber";126;0
"Upgrade";"EvolveMuscularAugments";"HydraliskDen";155;0
"Building";"CreepTumor";NA;171;0
"Building";"CreepTumor";NA;171;0
"Building";"CreepTumor";NA;171;0
"Building";"CreepTumorQueen";NA;171;0
"Building";"CreepTumorQueen";NA;181;0
"Building";"CreepTumor";NA;181;0
"Building";"CreepTumor";NA;181;0
"Building";"CreepTumor";NA;181;0
"Building";"SpineCrawler";NA;171;0
"Building";"SpineCrawler";NA;171;0
"Building";"SpineCrawler";NA;171;0
"Building";"SpineCrawler";NA;171;0
"Building";"SpineCrawler";NA;171;0
"Building";"SpineCrawler";NA;171;0
"Building";"EvolutionChamber";NA;181;0
"Building";"SpineCrawler";NA;171;0
"Building";"CreepTumor";NA;181;0
"Building";"CreepTumor";NA;181;0
"Building";"CreepTumor";NA;181;0
"Building";"CreepTumor";NA;181;0
"Unit";"Hydralisk";"Larva";181;2
"Unit";"Hydralisk";"Larva";181;2
"Unit";"Hydralisk";"Larva";181;2
"Unit";"Hydralisk";"Larva";181;2
"Unit";"Hydralisk";"Larva";181;2
"Unit";"Hydralisk";"Larva";181;2
"Unit";"Hydralisk";"Larva";181;2
"Unit";"Hydralisk";"Larva";181;2
"Unit";"Overlord";"Larva";181;0
"Unit";"Overlord";"Larva";181;0
"Building";"Hatchery";NA;171;0
"Building";"InfestationPit";NA;181;0
"Unit";"Hydralisk";"Larva";197;2
"Unit";"Hydralisk";"Larva";197;2
"Building";"CreepTumor";NA;197;0
"Building";"CreepTumor";NA;197;0
"Building";"CreepTumor";NA;201;0
"Building";"Hatchery";NA;181;0
"Building";"CreepTumor";NA;201;0
"Building";"CreepTumor";NA;201;0
"Building";"CreepTumor";NA;201;0
"Building";"Hatchery";NA;181;0
"Building";"Hatchery";NA;181;0
"Unit";"Overlord";"Larva";201;0
"Building";"Spire";NA;197;0
"Building";"CreepTumor";NA;213;0
"Building";"Spire";NA;197;0
"Building";"CreepTumor";NA;213;0
"Building";"CreepTumor";NA;213;0
"Building";"CreepTumor";NA;213;0
"Building";"CreepTumor";NA;213;0
"Building";"CreepTumor";NA;213;0
"Upgrade";"ZergMissileWeaponsLevel2";"EvolutionChamber";181;0
"Building";"SporeCrawler";NA;213;0
"Building";"SporeCrawler";NA;213;0
"Building";"SporeCrawler";NA;213;0
"Building";"SporeCrawler";NA;213;0
"Building";"SporeCrawler";NA;213;0
"Building";"SporeCrawler";NA;213;0
"Building";"SporeCrawler";NA;213;0
"Building";"SporeCrawler";NA;213;0
"Building";"SporeCrawler";NA;213;0
"Building";"SporeCrawler";NA;213;0
"Building";"SporeCrawler";NA;213;0
"Upgrade";"ZergGroundArmorsLevel1";"EvolutionChamber";197;0
"Building";"SporeCrawler";NA;213;0
"Building";"SporeCrawler";NA;213;0
"Building";"SporeCrawler";NA;213;0
"Building";"SporeCrawler";NA;213;0
"Building";"SporeCrawler";NA;213;0
"Building";"SporeCrawler";NA;213;0
"Building";"SporeCrawler";NA;213;0
"Building";"CreepTumorQueen";NA;213;0
"Building";"CreepTumorQueen";NA;213;0
"Building";"CreepTumorQueen";NA;213;0
"Unit";"Corruptor";"Larva";213;2
"Unit";"Corruptor";"Larva";213;2
"Unit";"Corruptor";"Larva";213;2
"Unit";"Corruptor";"Larva";213;2
"Unit";"Corruptor";"Larva";213;2
"Unit";"Corruptor";"Larva";213;2
"Unit";"Corruptor";"Larva";213;2
"Unit";"Corruptor";"Larva";213;2
"Unit";"Corruptor";"Larva";213;2
"Unit";"Corruptor";"Larva";213;2
"Unit";"Corruptor";"Larva";213;2
"Building";"Extractor";NA;213;0
"Building";"Extractor";NA;213;0
"Building";"CreepTumorQueen";NA;242;0
"Building";"CreepTumorQueen";NA;242;0
"Building";"CreepTumor";NA;242;0
"Building";"CreepTumor";NA;242;0
"Building";"CreepTumor";NA;242;0
"Building";"CreepTumor";NA;242;0
"Building";"SporeCrawler";NA;213;0
"Building";"SporeCrawler";NA;213;0
"Building";"SporeCrawler";NA;213;0
"Building";"CreepTumorQueen";NA;242;0
"Building";"Extractor";NA;242;0
"Building";"Extractor";NA;242;0
"Building";"CreepTumor";NA;256;0
"Building";"CreepTumor";NA;256;0
"Building";"CreepTumor";NA;256;0
"Building";"CreepTumor";NA;256;0
"Building";"CreepTumor";NA;256;0
"Building";"SpineCrawler";NA;242;0
"Building";"SpineCrawler";NA;242;0
"Building";"SpineCrawler";NA;242;0
"Building";"CreepTumorQueen";NA;256;0
"Building";"SpineCrawler";NA;242;0
"Building";"CreepTumor";NA;256;0
"Building";"CreepTumorQueen";NA;256;0
"Building";"SporeCrawler";NA;256;0
"Building";"SporeCrawler";NA;256;0
"Building";"SporeCrawler";NA;256;0
"Building";"SporeCrawler";NA;256;0
"Building";"CreepTumor";NA;256;0
"Building";"SporeCrawler";NA;256;0
"Building";"CreepTumor";NA;256;0
"Building";"SporeCrawler";NA;256;0
"Building";"SporeCrawler";NA;256;0
"Unit";"Corruptor";"Larva";256;2
"Unit";"Corruptor";"Larva";256;2
"Building";"CreepTumor";NA;260;0
"Unit";"Corruptor";"Larva";260;2
"Unit";"Corruptor";"Larva";260;2
"Unit";"Corruptor";"Larva";260;2
"Unit";"Corruptor";"Larva";260;2
"Unit";"Corruptor";"Larva";260;2
"Unit";"Infestor";"Larva";260;2
"Unit";"Infestor";"Larva";260;2
"Unit";"Infestor";"Larva";260;2
"Unit";"Infestor";"Larva";260;2
"Unit";"Infestor";"Larva";260;2
"Unit";"Infestor";"Larva";260;2
"Unit";"Infestor";"Larva";260;2
"Unit";"Infestor";"Larva";260;2
"Unit";"Infestor";"Larva";260;2
"Building";"CreepTumorQueen";NA;292;0
"Building";"CreepTumor";NA;292;0
"Building";"CreepTumor";NA;292;0
"Building";"CreepTumor";NA;292;0
"Building";"CreepTumor";NA;292;0
"Building";"CreepTumorQueen";NA;301;0
"Building";"CreepTumorQueen";NA;301;0
"Building";"CreepTumor";NA;292;0
"Building";"SpineCrawler";NA;274;0
"Building";"SpineCrawler";NA;274;0
"Building";"SpineCrawler";NA;274;0
"Building";"SpineCrawler";NA;276;0
"Upgrade";"NeuralParasite";"InfestationPit";260;0
"Building";"Hatchery";NA;260;0
"Building";"CreepTumorQueen";NA;301;0
"Building";"CreepTumorQueen";NA;301;0
"Building";"CreepTumorQueen";NA;301;0
"Building";"CreepTumorQueen";NA;301;0
"Building";"Extractor";NA;301;0
"Building";"Extractor";NA;301;0
"Building";"CreepTumorQueen";NA;307;0
"Unit";"Corruptor";"Larva";301;2
"Unit";"Corruptor";"Larva";301;2
"Unit";"Corruptor";"Larva";301;2
"Unit";"Corruptor";"Larva";301;2
"Unit";"Corruptor";"Larva";301;2
"Unit";"Corruptor";"Larva";301;2
"Unit";"Corruptor";"Larva";301;2
"Unit";"Overlord";"Larva";321;0
"Building";"CreepTumor";NA;328;0
"Building";"CreepTumor";NA;328;0
"Building";"CreepTumor";NA;328;0
"Building";"CreepTumor";NA;328;0
"Building";"SpineCrawler";NA;321;0
"Building";"SpineCrawler";NA;321;0
"Building";"SpineCrawler";NA;321;0
"Building";"SpineCrawler";NA;321;0
"Building";"SpineCrawler";NA;321;0
"Building";"SpineCrawler";NA;321;0
"Building";"SpineCrawler";NA;321;0
"Unit";"Queen";"Hatchery";321;2
"Unit";"Zergling";"Larva";330;1
"Unit";"Zergling";"Larva";330;1
"Unit";"Zergling";"Larva";330;1
"Unit";"Zergling";"Larva";330;1
"Unit";"Zergling";"Larva";330;1
"Unit";"Zergling";"Larva";330;1
"Unit";"Zergling";"Larva";330;1
"Unit";"Zergling";"Larva";330;1
"Unit";"Zergling";"Larva";330;1
"Unit";"Zergling";"Larva";330;1
"Unit";"Corruptor";"Larva";330;2
"Unit";"Corruptor";"Larva";330;2
"Unit";"Corruptor";"Larva";330;2
"Unit";"Corruptor";"Larva";330;2
"Unit";"Corruptor";"Larva";330;2
"Unit";"Corruptor";"Larva";330;2
"Unit";"Corruptor";"Larva";330;2
"Unit";"Corruptor";"Larva";330;2
"Unit";"Corruptor";"Larva";330;2
"Unit";"Corruptor";"Larva";330;2
"Unit";"Corruptor";"Larva";330;2
"Building";"CreepTumor";NA;364;0
"Building";"CreepTumor";NA;364;0
"Building";"CreepTumor";NA;364;0
"Building";"CreepTumor";NA;364;0
"Upgrade";"ZergGroundArmorsLevel2";"EvolutionChamber";328;0
"Unit";"Infestor";"Larva";364;2
"Unit";"Infestor";"Larva";364;2
"Unit";"Infestor";"Larva";364;2
"Building";"SporeCrawler";NA;364;0
"Unit";"Infestor";"Larva";364;2
"Unit";"Infestor";"Larva";364;2
"Unit";"Infestor";"Larva";364;2
"Building";"CreepTumorQueen";NA;370;0
"Building";"CreepTumorQueen";NA;370;0
"Upgrade";"ZergMissileWeaponsLevel3";"EvolutionChamber";328;0
"Building";"CreepTumor";NA;370;0
"Building";"CreepTumorQueen";NA;370;0
"Building";"Extractor";NA;370;0
"Building";"CreepTumorQueen";NA;376;0
"Building";"Extractor";NA;370;0
"Building";"CreepTumorQueen";NA;376;0
"Building";"SpineCrawler";NA;364;0
"Building";"CreepTumorQueen";NA;376;0
"Building";"CreepTumorQueen";NA;376;0
"Building";"Hatchery";NA;364;0
"Unit";"Corruptor";"Larva";370;2
"Unit";"Corruptor";"Larva";370;2
"Unit";"Corruptor";"Larva";370;2
"Unit";"Corruptor";"Larva";370;2
"Unit";"Corruptor";"Larva";370;2
"Unit";"Corruptor";"Larva";370;2
"Building";"CreepTumor";NA;388;0
"Building";"CreepTumor";NA;388;0
"Building";"CreepTumor";NA;388;0
"Building";"CreepTumor";NA;388;0
"Building";"CreepTumor";NA;388;0
"Building";"CreepTumor";NA;388;0
"Building";"CreepTumor";NA;388;0
"Building";"Hatchery";NA;376;0
"Unit";"Zergling";"Larva";388;1
"Unit";"Zergling";"Larva";388;1
"Unit";"Zergling";"Larva";388;1
"Unit";"Zergling";"Larva";388;1
"Unit";"Zergling";"Larva";388;1
"Unit";"Zergling";"Larva";388;1
"Unit";"Zergling";"Larva";388;1
"Unit";"Zergling";"Larva";388;1
"Building";"SporeCrawler";NA;388;0
"Building";"SporeCrawler";NA;388;0
"Unit";"Corruptor";"Larva";388;2
"Unit";"Corruptor";"Larva";388;2
"Unit";"Corruptor";"Larva";388;2
"Building";"SporeCrawler";NA;388;0
"Building";"CreepTumor";NA;402;0
"Building";"CreepTumor";NA;402;0
"Building";"CreepTumor";NA;402;0
"Building";"SporeCrawler";NA;402;0
"Building";"SporeCrawler";NA;402;0
