"type";"unit_name";"on_building";"total_supply_lag";"supply"
"Unit";"Overlord";"Larva";13;0
"Building";"Hatchery";NA;17;0
"Building";"Extractor";NA;19;0
"Building";"SpawningPool";NA;19;0
"Unit";"Overlord";"Larva";23;0
"Unit";"Queen";"Hatchery";23;2
"Unit";"Queen";"Hatchery";25;2
"Unit";"Zergling";"Larva";27;1
"Unit";"Zergling";"Larva";28;1
"Unit";"Zergling";"Larva";29;1
"Unit";"Zergling";"Larva";30;1
"Building";"Hatchery";NA;37;0
"Unit";"Queen";"Hatchery";37;2
"Unit";"Overlord";"Larva";40;0
"Unit";"Zergling";"Larva";40;1
"Unit";"Zergling";"Larva";41;1
"Unit";"Zergling";"Larva";42;1
"Unit";"Zergling";"Larva";43;1
"Unit";"Overlord";"Larva";44;0
"Unit";"Overlord";"Larva";44;0
"Building";"CreepTumorQueen";NA;51;0
"Building";"EvolutionChamber";NA;53;0
"Unit";"Overlord";"Larva";53;0
"Unit";"Overlord";"Larva";53;0
"Building";"SporeCrawler";NA;53;0
"Building";"SporeCrawler";NA;53;0
"Building";"CreepTumor";NA;53;0
"Building";"CreepTumorQueen";NA;53;0
"Unit";"Zergling";"Larva";56;1
"Unit";"Zergling";"Larva";57;1
"Unit";"Zergling";"Larva";58;1
"Unit";"Zergling";"Larva";59;1
"Building";"SporeCrawler";NA;67;0
"Building";"CreepTumor";NA;67;0
"Building";"CreepTumor";NA;69;0
"Building";"CreepTumorQueen";NA;71;0
"Unit";"Queen";"Hatchery";71;2
"Unit";"Queen";"Hatchery";73;2
"Unit";"Overlord";"Larva";81;0
"Unit";"Overlord";"Larva";81;0
"Unit";"Overlord";"Larva";81;0
"Unit";"Zergling";"Larva";81;1
"Unit";"Zergling";"Larva";82;1
"Unit";"Zergling";"Larva";83;1
"Unit";"Zergling";"Larva";84;1
"Unit";"Zergling";"Larva";85;1
"Unit";"Zergling";"Larva";86;1
"Unit";"Zergling";"Larva";87;1
"Unit";"Zergling";"Larva";88;1
"Unit";"Zergling";"Larva";89;1
"Unit";"Zergling";"Larva";90;1
"Unit";"Zergling";"Larva";91;1
"Unit";"Zergling";"Larva";92;1
"Unit";"Zergling";"Larva";93;1
"Unit";"Zergling";"Larva";94;1
"Unit";"Zergling";"Larva";95;1
"Unit";"Zergling";"Larva";96;1
"Unit";"Zergling";"Larva";97;1
"Unit";"Zergling";"Larva";98;1
"Unit";"Zergling";"Larva";99;1
"Unit";"Zergling";"Larva";100;1
"Unit";"Zergling";"Larva";101;1
"Unit";"Zergling";"Larva";102;1
"Building";"Extractor";NA;107;0
"Building";"Extractor";NA;107;0
"Building";"CreepTumorQueen";NA;110;0
"Building";"Hatchery";NA;110;0
"Building";"BanelingNest";NA;110;0
"Building";"CreepTumor";NA;112;0
"Building";"CreepTumorQueen";NA;112;0
"Building";"HydraliskDen";NA;122;0
"Unit";"Overlord";"Larva";125;0
"Building";"CreepTumorQueen";NA;125;0
"Building";"CreepTumorQueen";NA;125;0
"Unit";"Zergling";"Larva";125;1
"Unit";"Zergling";"Larva";126;1
"Building";"EvolutionChamber";NA;135;0
"Building";"Extractor";NA;140;0
"Unit";"Overlord";"Larva";140;0
"Building";"CreepTumor";NA;140;0
"Building";"CreepTumor";NA;140;0
"Unit";"Zergling";"Larva";140;1
"Unit";"Zergling";"Larva";141;1
"Unit";"Zergling";"Larva";142;1
"Unit";"Zergling";"Larva";143;1
"Building";"Hatchery";NA;144;0
"Building";"Extractor";NA;144;0
"Unit";"Overlord";"Larva";144;0
"Unit";"Zergling";"Larva";144;1
"Unit";"Zergling";"Larva";145;1
"Unit";"Zergling";"Larva";146;1
"Unit";"Zergling";"Larva";147;1
"Unit";"Zergling";"Larva";148;1
"Unit";"Zergling";"Larva";149;1
"Building";"CreepTumor";NA;150;0
"Building";"CreepTumor";NA;150;0
"Unit";"Zergling";"Larva";150;1
"Unit";"Zergling";"Larva";151;1
"Unit";"Zergling";"Larva";152;1
"Unit";"Zergling";"Larva";153;1
"Unit";"Zergling";"Larva";154;1
"Unit";"Zergling";"Larva";155;1
"Unit";"Zergling";"Larva";156;1
"Unit";"Zergling";"Larva";157;1
"Unit";"Zergling";"Larva";158;1
"Unit";"Zergling";"Larva";159;1
"Unit";"Zergling";"Larva";160;1
"Unit";"Zergling";"Larva";161;1
"Unit";"Zergling";"Larva";162;1
"Unit";"Zergling";"Larva";163;1
"Unit";"Zergling";"Larva";164;1
"Unit";"Zergling";"Larva";165;1
"Unit";"Overlord";"Larva";166;0
"Building";"SporeCrawler";NA;173;0
"Building";"Extractor";NA;175;0
"Building";"CreepTumor";NA;181;0
"Building";"CreepTumor";NA;182;0
"Building";"CreepTumor";NA;182;0
"Unit";"Overlord";"Larva";182;0
"Building";"InfestationPit";NA;182;0
"Building";"CreepTumorQueen";NA;182;0
"Unit";"Hydralisk";"Larva";182;2
"Unit";"Hydralisk";"Larva";184;2
"Unit";"Hydralisk";"Larva";186;2
"Unit";"Hydralisk";"Larva";188;2
"Unit";"Hydralisk";"Larva";190;2
"Unit";"Hydralisk";"Larva";192;2
"Building";"CreepTumorQueen";NA;194;0
"Unit";"Zergling";"Larva";194;1
"Unit";"Zergling";"Larva";195;1
"Unit";"Overlord";"Larva";196;0
"Building";"CreepTumorQueen";NA;196;0
"Unit";"Overlord";"Larva";196;0
"Unit";"Overlord";"Larva";196;0
"Unit";"Overlord";"Larva";196;0
"Unit";"Hydralisk";"Larva";196;2
"Unit";"Hydralisk";"Larva";198;2
"Unit";"Hydralisk";"Larva";200;2
"Unit";"Hydralisk";"Larva";202;2
"Unit";"Hydralisk";"Larva";204;2
"Unit";"Zergling";"Larva";206;1
"Unit";"Zergling";"Larva";207;1
"Unit";"Zergling";"Larva";208;1
"Unit";"Zergling";"Larva";209;1
"Unit";"Zergling";"Larva";210;1
"Unit";"Zergling";"Larva";211;1
"Unit";"Zergling";"Larva";212;1
"Unit";"Zergling";"Larva";213;1
"Unit";"Zergling";"Larva";214;1
"Unit";"Zergling";"Larva";215;1
"Unit";"Zergling";"Larva";216;1
"Unit";"Zergling";"Larva";217;1
"Unit";"Zergling";"Larva";218;1
"Unit";"Zergling";"Larva";219;1
"Unit";"Zergling";"Larva";220;1
"Unit";"Zergling";"Larva";221;1
"Unit";"Zergling";"Larva";222;1
"Unit";"Zergling";"Larva";223;1
"Unit";"Zergling";"Larva";224;1
"Unit";"Zergling";"Larva";225;1
"Building";"CreepTumor";NA;226;0
"Building";"CreepTumor";NA;226;0
"Building";"CreepTumor";NA;226;0
"Building";"CreepTumor";NA;226;0
"Building";"CreepTumor";NA;226;0
"Unit";"Zergling";"Larva";226;1
"Unit";"Zergling";"Larva";227;1
"Unit";"Zergling";"Larva";228;1
"Unit";"Zergling";"Larva";229;1
"Unit";"Zergling";"Larva";230;1
"Unit";"Zergling";"Larva";231;1
"Unit";"Zergling";"Larva";232;1
"Unit";"Zergling";"Larva";233;1
"Unit";"Zergling";"Larva";234;1
"Unit";"Zergling";"Larva";235;1
"Building";"CreepTumorQueen";NA;236;0
"Unit";"Overlord";"Larva";236;0
"Building";"Spire";NA;236;0
"Unit";"Hydralisk";"Larva";236;2
"Unit";"Hydralisk";"Larva";238;2
"Unit";"Hydralisk";"Larva";240;2
"Unit";"Zergling";"Larva";242;1
"Unit";"Zergling";"Larva";243;1
"Unit";"Zergling";"Larva";244;1
"Unit";"Zergling";"Larva";245;1
"Unit";"Zergling";"Larva";246;1
"Unit";"Zergling";"Larva";247;1
"Building";"CreepTumor";NA;248;0
"Unit";"Overlord";"Larva";248;0
"Building";"CreepTumor";NA;248;0
"Building";"CreepTumor";NA;248;0
"Building";"Extractor";NA;253;0
"Building";"Extractor";NA;253;0
"Building";"CreepTumor";NA;259;0
"Building";"CreepTumor";NA;259;0
"Building";"CreepTumor";NA;259;0
"Building";"CreepTumor";NA;259;0
"Building";"SporeCrawler";NA;259;0
"Unit";"Hydralisk";"Larva";259;2
"Unit";"Hydralisk";"Larva";261;2
"Unit";"Zergling";"Larva";263;1
"Unit";"Zergling";"Larva";264;1
"Unit";"Zergling";"Larva";265;1
"Unit";"Zergling";"Larva";266;1
"Unit";"Zergling";"Larva";267;1
"Unit";"Zergling";"Larva";268;1
"Unit";"Zergling";"Larva";269;1
"Unit";"Zergling";"Larva";270;1
"Unit";"Zergling";"Larva";271;1
"Unit";"Zergling";"Larva";272;1
"Unit";"Zergling";"Larva";273;1
"Unit";"Zergling";"Larva";274;1
"Unit";"Zergling";"Larva";275;1
"Unit";"Zergling";"Larva";276;1
"Unit";"Zergling";"Larva";277;1
"Unit";"Zergling";"Larva";278;1
"Unit";"Zergling";"Larva";279;1
"Unit";"Zergling";"Larva";280;1
"Unit";"Baneling";"Zergling";281;0
"Unit";"Baneling";"Zergling";281;0
"Unit";"Baneling";"Zergling";281;0
"Unit";"Baneling";"Zergling";281;0
"Unit";"Baneling";"Zergling";281;0
"Unit";"Baneling";"Zergling";281;0
"Unit";"Baneling";"Zergling";281;0
"Unit";"Baneling";"Zergling";281;0
"Unit";"Baneling";"Zergling";281;0
"Unit";"Baneling";"Zergling";281;0
"Unit";"Baneling";"Zergling";281;0
"Unit";"Baneling";"Zergling";281;0
"Unit";"Baneling";"Zergling";281;0
"Unit";"Baneling";"Zergling";281;0
"Unit";"Overlord";"Larva";281;0
"Building";"CreepTumor";NA;281;0
"Building";"CreepTumor";NA;281;0
"Building";"CreepTumorQueen";NA;281;0
"Building";"CreepTumorQueen";NA;281;0
"Unit";"Hydralisk";"Larva";281;2
"Unit";"Hydralisk";"Larva";283;2
"Unit";"Zergling";"Larva";285;1
"Unit";"Zergling";"Larva";286;1
"Unit";"Zergling";"Larva";287;1
"Unit";"Zergling";"Larva";288;1
"Unit";"Zergling";"Larva";289;1
"Unit";"Zergling";"Larva";290;1
"Unit";"Zergling";"Larva";291;1
"Unit";"Zergling";"Larva";292;1
"Unit";"Zergling";"Larva";293;1
"Unit";"Zergling";"Larva";294;1
"Unit";"Overlord";"Larva";295;0
"Unit";"Zergling";"Larva";295;1
"Unit";"Zergling";"Larva";296;1
"Unit";"Zergling";"Larva";297;1
"Unit";"Zergling";"Larva";298;1
"Unit";"Zergling";"Larva";299;1
"Unit";"Zergling";"Larva";300;1
"Unit";"Zergling";"Larva";301;1
"Unit";"Zergling";"Larva";302;1
"Unit";"Zergling";"Larva";303;1
"Unit";"Zergling";"Larva";304;1
"Unit";"Zergling";"Larva";305;1
"Unit";"Zergling";"Larva";306;1
"Unit";"Zergling";"Larva";307;1
"Unit";"Zergling";"Larva";308;1
"Unit";"Zergling";"Larva";309;1
"Unit";"Zergling";"Larva";310;1
"Unit";"Overlord";"Larva";311;0
"Unit";"Zergling";"Larva";311;1
"Unit";"Zergling";"Larva";312;1
"Unit";"Zergling";"Larva";313;1
"Unit";"Zergling";"Larva";314;1
"Unit";"Zergling";"Larva";315;1
"Unit";"Zergling";"Larva";316;1
"Unit";"Zergling";"Larva";317;1
"Unit";"Zergling";"Larva";318;1
"Unit";"Zergling";"Larva";319;1
"Unit";"Zergling";"Larva";320;1
"Unit";"Zergling";"Larva";321;1
"Unit";"Zergling";"Larva";322;1
"Unit";"Zergling";"Larva";323;1
"Unit";"Zergling";"Larva";324;1
"Unit";"Zergling";"Larva";325;1
"Unit";"Zergling";"Larva";326;1
"Unit";"Zergling";"Larva";327;1
"Unit";"Zergling";"Larva";328;1
"Unit";"Zergling";"Larva";329;1
"Unit";"Zergling";"Larva";330;1
"Unit";"Zergling";"Larva";331;1
"Unit";"Zergling";"Larva";332;1
"Unit";"Zergling";"Larva";333;1
"Unit";"Zergling";"Larva";334;1
"Unit";"Zergling";"Larva";335;1
"Unit";"Zergling";"Larva";336;1
"Unit";"Zergling";"Larva";337;1
"Unit";"Zergling";"Larva";338;1
"Unit";"Zergling";"Larva";339;1
"Unit";"Zergling";"Larva";340;1
"Unit";"Zergling";"Larva";341;1
"Unit";"Zergling";"Larva";342;1
"Unit";"Zergling";"Larva";343;1
"Unit";"Zergling";"Larva";344;1
"Unit";"Zergling";"Larva";345;1
"Unit";"Zergling";"Larva";346;1
"Unit";"Zergling";"Larva";347;1
"Unit";"Zergling";"Larva";348;1
"Unit";"Zergling";"Larva";349;1
"Unit";"Zergling";"Larva";350;1
"Unit";"Zergling";"Larva";351;1
"Unit";"Zergling";"Larva";352;1
"Unit";"Overlord";"Larva";353;0
"Unit";"Zergling";"Larva";353;1
"Unit";"Zergling";"Larva";354;1
"Unit";"Zergling";"Larva";355;1
"Unit";"Zergling";"Larva";356;1
"Unit";"Zergling";"Larva";357;1
"Unit";"Zergling";"Larva";358;1
"Unit";"Zergling";"Larva";359;1
"Unit";"Zergling";"Larva";360;1
"Unit";"Baneling";"Zergling";361;0
"Unit";"Baneling";"Zergling";361;0
"Unit";"Baneling";"Zergling";361;0
"Unit";"Baneling";"Zergling";361;0
"Unit";"Baneling";"Zergling";361;0
"Unit";"Baneling";"Zergling";361;0
"Unit";"Baneling";"Zergling";361;0
"Unit";"Baneling";"Zergling";361;0
"Unit";"Baneling";"Zergling";361;0
"Unit";"Baneling";"Zergling";361;0
"Unit";"Zergling";"Larva";361;1
"Unit";"Zergling";"Larva";362;1
"Unit";"Zergling";"Larva";363;1
"Unit";"Zergling";"Larva";364;1
"Unit";"Zergling";"Larva";365;1
"Unit";"Zergling";"Larva";366;1
"Unit";"Zergling";"Larva";367;1
"Unit";"Zergling";"Larva";368;1
"Unit";"Zergling";"Larva";369;1
"Unit";"Zergling";"Larva";370;1
"Unit";"Zergling";"Larva";371;1
"Unit";"Zergling";"Larva";372;1
"Unit";"Baneling";"Zergling";373;0
"Unit";"Baneling";"Zergling";373;0
"Unit";"Baneling";"Zergling";373;0
"Unit";"Baneling";"Zergling";373;0
"Unit";"Hydralisk";"Larva";373;2
"Unit";"Zergling";"Larva";375;1
"Unit";"Zergling";"Larva";376;1
"Unit";"Zergling";"Larva";377;1
"Unit";"Zergling";"Larva";378;1
"Unit";"Zergling";"Larva";379;1
"Unit";"Zergling";"Larva";380;1
"Unit";"Zergling";"Larva";381;1
"Unit";"Zergling";"Larva";382;1
"Unit";"Zergling";"Larva";383;1
"Unit";"Zergling";"Larva";384;1
"Unit";"Zergling";"Larva";385;1
"Unit";"Zergling";"Larva";386;1
"Unit";"Baneling";"Zergling";387;0
"Unit";"Baneling";"Zergling";387;0
"Unit";"Baneling";"Zergling";387;0
"Unit";"Baneling";"Zergling";387;0
"Unit";"Baneling";"Zergling";387;0
"Unit";"Zergling";"Larva";387;1
"Unit";"Zergling";"Larva";388;1
"Unit";"Zergling";"Larva";389;1
"Unit";"Zergling";"Larva";390;1
"Unit";"Zergling";"Larva";391;1
"Unit";"Zergling";"Larva";392;1
"Unit";"Zergling";"Larva";393;1
"Unit";"Zergling";"Larva";394;1
"Unit";"Zergling";"Larva";395;1
"Unit";"Zergling";"Larva";396;1
"Unit";"Zergling";"Larva";397;1
"Unit";"Zergling";"Larva";398;1
"Unit";"Zergling";"Larva";399;1
"Unit";"Zergling";"Larva";400;1
"Unit";"Zergling";"Larva";401;1
"Unit";"Zergling";"Larva";402;1
"Building";"Hatchery";NA;403;0
"Building";"CreepTumor";NA;408;0
"Building";"Hatchery";NA;408;0
"Building";"CreepTumor";NA;408;0
"Building";"CreepTumor";NA;408;0
"Unit";"Corruptor";"Larva";408;2
"Unit";"Corruptor";"Larva";410;2
"Unit";"Corruptor";"Larva";412;2
"Unit";"Corruptor";"Larva";414;2
"Unit";"Corruptor";"Larva";416;2
"Unit";"Corruptor";"Larva";418;2
"Unit";"Corruptor";"Larva";420;2
"Unit";"Corruptor";"Larva";422;2
"Building";"CreepTumor";NA;424;0
"Building";"CreepTumor";NA;424;0
"Unit";"Zergling";"Larva";424;1
"Unit";"Zergling";"Larva";425;1
"Unit";"Zergling";"Larva";426;1
"Unit";"Zergling";"Larva";427;1
"Unit";"Zergling";"Larva";428;1
"Unit";"Zergling";"Larva";429;1
"Unit";"Zergling";"Larva";430;1
"Unit";"Zergling";"Larva";431;1
"Unit";"Zergling";"Larva";432;1
"Unit";"Zergling";"Larva";433;1
"Unit";"Zergling";"Larva";434;1
"Unit";"Zergling";"Larva";435;1
"Unit";"Zergling";"Larva";436;1
"Unit";"Zergling";"Larva";437;1
"Unit";"Zergling";"Larva";438;1
"Unit";"Zergling";"Larva";439;1
"Unit";"Zergling";"Larva";440;1
"Unit";"Zergling";"Larva";441;1
"Unit";"Queen";"Hatchery";442;2
"Unit";"Zergling";"Larva";452;1
"Unit";"Zergling";"Larva";453;1
"Unit";"Zergling";"Larva";454;1
"Unit";"Zergling";"Larva";455;1
"Unit";"Zergling";"Larva";456;1
"Unit";"Zergling";"Larva";457;1
"Unit";"Zergling";"Larva";458;1
"Unit";"Zergling";"Larva";459;1
"Unit";"Zergling";"Larva";460;1
"Unit";"Zergling";"Larva";461;1
"Unit";"Zergling";"Larva";462;1
"Unit";"Zergling";"Larva";463;1
"Unit";"Zergling";"Larva";464;1
"Unit";"Zergling";"Larva";465;1
"Unit";"Zergling";"Larva";466;1
"Unit";"Zergling";"Larva";467;1
"Unit";"Zergling";"Larva";468;1
"Unit";"Zergling";"Larva";469;1
"Unit";"Zergling";"Larva";470;1
"Unit";"Zergling";"Larva";471;1
"Unit";"Zergling";"Larva";472;1
"Unit";"Zergling";"Larva";473;1
"Unit";"Zergling";"Larva";474;1
"Unit";"Zergling";"Larva";475;1
"Unit";"Zergling";"Larva";476;1
"Unit";"Zergling";"Larva";477;1
"Unit";"Zergling";"Larva";478;1
"Unit";"Zergling";"Larva";479;1
"Unit";"Zergling";"Larva";480;1
"Unit";"Zergling";"Larva";481;1
"Unit";"Zergling";"Larva";482;1
"Unit";"Zergling";"Larva";483;1
"Unit";"Zergling";"Larva";484;1
"Unit";"Zergling";"Larva";485;1
"Unit";"Zergling";"Larva";486;1
"Unit";"Zergling";"Larva";487;1
"Unit";"Zergling";"Larva";488;1
"Unit";"Zergling";"Larva";489;1
"Unit";"Zergling";"Larva";490;1
"Unit";"Zergling";"Larva";491;1
"Unit";"Zergling";"Larva";492;1
"Unit";"Zergling";"Larva";493;1
"Unit";"Zergling";"Larva";494;1
"Unit";"Zergling";"Larva";495;1
"Unit";"Zergling";"Larva";496;1
"Unit";"Zergling";"Larva";497;1
"Unit";"Zergling";"Larva";498;1
"Unit";"Zergling";"Larva";499;1
"Unit";"Zergling";"Larva";500;1
"Unit";"Zergling";"Larva";501;1
"Unit";"Zergling";"Larva";502;1
"Unit";"Zergling";"Larva";503;1
"Unit";"Zergling";"Larva";504;1
"Unit";"Zergling";"Larva";505;1
"Unit";"Zergling";"Larva";506;1
"Unit";"Zergling";"Larva";507;1
"Unit";"Zergling";"Larva";508;1
"Unit";"Zergling";"Larva";509;1
"Unit";"Zergling";"Larva";510;1
"Unit";"Zergling";"Larva";511;1
"Unit";"Zergling";"Larva";512;1
"Unit";"Zergling";"Larva";513;1
"Unit";"Zergling";"Larva";514;1
"Unit";"Zergling";"Larva";515;1
"Unit";"Corruptor";"Larva";516;2
"Unit";"Corruptor";"Larva";518;2
"Unit";"Corruptor";"Larva";520;2
"Unit";"Corruptor";"Larva";522;2
"Unit";"Corruptor";"Larva";524;2
"Unit";"Corruptor";"Larva";526;2
"Building";"CreepTumor";NA;528;0
"Building";"CreepTumor";NA;528;0
"Building";"CreepTumor";NA;528;0
"Unit";"Corruptor";"Larva";528;2
"Unit";"Baneling";"Zergling";530;0
"Unit";"Baneling";"Zergling";530;0
"Unit";"Baneling";"Zergling";530;0
"Unit";"Baneling";"Zergling";530;0
"Unit";"Baneling";"Zergling";530;0
"Unit";"Baneling";"Zergling";530;0
"Unit";"Baneling";"Zergling";530;0
"Unit";"Baneling";"Zergling";530;0
"Unit";"Baneling";"Zergling";530;0
"Unit";"Baneling";"Zergling";530;0
"Building";"CreepTumor";NA;530;0
"Unit";"Corruptor";"Larva";530;2
"Unit";"Corruptor";"Larva";532;2
"Building";"CreepTumor";NA;534;0
"Building";"CreepTumor";NA;534;0
"Building";"CreepTumorQueen";NA;534;0
"Unit";"Zergling";"Larva";534;1
"Unit";"Zergling";"Larva";535;1
"Unit";"Zergling";"Larva";536;1
"Unit";"Zergling";"Larva";537;1
"Unit";"Zergling";"Larva";538;1
"Unit";"Zergling";"Larva";539;1
"Unit";"Zergling";"Larva";540;1
"Unit";"Zergling";"Larva";541;1
"Unit";"Zergling";"Larva";542;1
"Unit";"Zergling";"Larva";543;1
"Unit";"Zergling";"Larva";544;1
"Unit";"Zergling";"Larva";545;1
"Unit";"Zergling";"Larva";546;1
"Unit";"Zergling";"Larva";547;1
"Unit";"Zergling";"Larva";548;1
"Unit";"Zergling";"Larva";549;1
"Unit";"Zergling";"Larva";550;1
"Unit";"Zergling";"Larva";551;1
"Unit";"Zergling";"Larva";552;1
"Unit";"Zergling";"Larva";553;1
"Unit";"Zergling";"Larva";554;1
"Unit";"Zergling";"Larva";555;1
"Unit";"Zergling";"Larva";556;1
"Unit";"Zergling";"Larva";557;1
"Unit";"Zergling";"Larva";558;1
"Unit";"Zergling";"Larva";559;1
"Unit";"Zergling";"Larva";560;1
"Unit";"Zergling";"Larva";561;1
"Unit";"Zergling";"Larva";562;1
"Unit";"Zergling";"Larva";563;1
"Unit";"Zergling";"Larva";564;1
"Unit";"Zergling";"Larva";565;1
"Unit";"Zergling";"Larva";566;1
"Unit";"Zergling";"Larva";567;1
"Unit";"Zergling";"Larva";568;1
"Unit";"Zergling";"Larva";569;1
"Unit";"Zergling";"Larva";570;1
"Unit";"Zergling";"Larva";571;1
"Unit";"Zergling";"Larva";572;1
"Unit";"Zergling";"Larva";573;1
"Unit";"Zergling";"Larva";574;1
"Unit";"Zergling";"Larva";575;1
"Unit";"Zergling";"Larva";576;1
"Unit";"Zergling";"Larva";577;1
"Unit";"Zergling";"Larva";578;1
"Unit";"Zergling";"Larva";579;1
"Unit";"Corruptor";"Larva";580;2
"Unit";"Corruptor";"Larva";582;2
"Unit";"Zergling";"Larva";584;1
"Unit";"Zergling";"Larva";585;1
"Unit";"Zergling";"Larva";586;1
"Unit";"Zergling";"Larva";587;1
"Unit";"Zergling";"Larva";588;1
"Unit";"Zergling";"Larva";589;1
"Unit";"Zergling";"Larva";590;1
"Unit";"Zergling";"Larva";591;1
"Unit";"Zergling";"Larva";592;1
"Unit";"Zergling";"Larva";593;1
"Unit";"Zergling";"Larva";594;1
"Unit";"Zergling";"Larva";595;1
"Unit";"Zergling";"Larva";596;1
"Unit";"Zergling";"Larva";597;1
"Unit";"Zergling";"Larva";598;1
"Unit";"Zergling";"Larva";599;1
"Unit";"Zergling";"Larva";600;1
"Unit";"Zergling";"Larva";601;1
"Building";"Extractor";NA;602;0
"Building";"Extractor";NA;602;0
"Unit";"Queen";"Hatchery";602;2
"Building";"SpineCrawler";NA;604;0
"Building";"SpineCrawler";NA;604;0
"Unit";"Baneling";"Zergling";604;0
"Unit";"Baneling";"Zergling";604;0
"Unit";"Baneling";"Zergling";604;0
"Unit";"Baneling";"Zergling";604;0
"Unit";"Baneling";"Zergling";604;0
"Unit";"Baneling";"Zergling";604;0
"Unit";"Baneling";"Zergling";604;0
"Unit";"Baneling";"Zergling";604;0
"Unit";"Baneling";"Zergling";604;0
"Unit";"Baneling";"Zergling";604;0
"Building";"SpineCrawler";NA;606;0
"Building";"SpineCrawler";NA;606;0
"Building";"Spire";NA;606;0
"Unit";"Zergling";"Larva";606;1
"Unit";"Zergling";"Larva";607;1
"Unit";"Zergling";"Larva";608;1
"Unit";"Zergling";"Larva";609;1
"Unit";"Zergling";"Larva";610;1
"Unit";"Zergling";"Larva";611;1
"Unit";"Zergling";"Larva";612;1
"Unit";"Zergling";"Larva";613;1
"Unit";"Zergling";"Larva";614;1
"Unit";"Zergling";"Larva";615;1
"Unit";"Zergling";"Larva";616;1
"Unit";"Zergling";"Larva";617;1
"Unit";"Zergling";"Larva";618;1
"Unit";"Zergling";"Larva";619;1
"Unit";"Zergling";"Larva";620;1
"Unit";"Zergling";"Larva";621;1
"Unit";"Zergling";"Larva";622;1
"Unit";"Zergling";"Larva";623;1
"Unit";"Zergling";"Larva";624;1
"Unit";"Zergling";"Larva";625;1
"Unit";"Zergling";"Larva";626;1
"Unit";"Zergling";"Larva";627;1
"Unit";"Zergling";"Larva";628;1
"Unit";"Zergling";"Larva";629;1
"Unit";"Zergling";"Larva";630;1
"Unit";"Zergling";"Larva";631;1
"Building";"Hatchery";NA;632;0
"Unit";"Zergling";"Larva";632;1
"Unit";"Zergling";"Larva";633;1
"Unit";"Zergling";"Larva";634;1
"Unit";"Zergling";"Larva";635;1
"Unit";"Zergling";"Larva";636;1
"Unit";"Zergling";"Larva";637;1
"Unit";"Zergling";"Larva";638;1
"Unit";"Zergling";"Larva";639;1
"Unit";"Zergling";"Larva";640;1
"Unit";"Zergling";"Larva";641;1
"Unit";"Zergling";"Larva";642;1
"Unit";"Zergling";"Larva";643;1
"Unit";"Zergling";"Larva";644;1
"Unit";"Zergling";"Larva";645;1
"Unit";"Zergling";"Larva";646;1
"Unit";"Zergling";"Larva";647;1
"Unit";"Zergling";"Larva";648;1
"Unit";"Zergling";"Larva";649;1
"Building";"Extractor";NA;650;0
"Unit";"Zergling";"Larva";650;1
"Unit";"Zergling";"Larva";651;1
"Unit";"Zergling";"Larva";652;1
"Unit";"Zergling";"Larva";653;1
"Unit";"Zergling";"Larva";654;1
"Unit";"Zergling";"Larva";655;1
"Unit";"Zergling";"Larva";656;1
"Unit";"Zergling";"Larva";657;1
"Unit";"Zergling";"Larva";658;1
"Unit";"Zergling";"Larva";659;1
"Unit";"Overlord";"Larva";660;0
"Unit";"Overlord";"Larva";660;0
"Unit";"Overlord";"Larva";660;0
"Unit";"Overlord";"Larva";660;0
"Unit";"Overlord";"Larva";660;0
"Unit";"Baneling";"Zergling";660;0
"Unit";"Baneling";"Zergling";660;0
"Unit";"Baneling";"Zergling";660;0
"Unit";"Baneling";"Zergling";660;0
"Unit";"Baneling";"Zergling";660;0
"Unit";"Zergling";"Larva";660;1
"Unit";"Zergling";"Larva";661;1
"Unit";"Zergling";"Larva";662;1
"Unit";"Zergling";"Larva";663;1
"Building";"CreepTumor";NA;664;0
"Building";"CreepTumorQueen";NA;664;0
"Building";"CreepTumor";NA;664;0
"Building";"CreepTumorQueen";NA;664;0
"Building";"CreepTumorQueen";NA;664;0
"Unit";"Zergling";"Larva";664;1
"Unit";"Zergling";"Larva";665;1
"Unit";"Zergling";"Larva";666;1
"Unit";"Zergling";"Larva";667;1
"Unit";"Zergling";"Larva";668;1
"Unit";"Zergling";"Larva";669;1
"Unit";"Zergling";"Larva";670;1
"Unit";"Zergling";"Larva";671;1
"Unit";"Zergling";"Larva";672;1
"Unit";"Zergling";"Larva";673;1
"Unit";"Zergling";"Larva";674;1
"Unit";"Zergling";"Larva";675;1
"Unit";"Zergling";"Larva";676;1
"Unit";"Zergling";"Larva";677;1
"Unit";"Zergling";"Larva";678;1
"Unit";"Zergling";"Larva";679;1
"Unit";"Zergling";"Larva";680;1
"Unit";"Zergling";"Larva";681;1
"Unit";"Zergling";"Larva";682;1
"Unit";"Zergling";"Larva";683;1
"Unit";"Zergling";"Larva";684;1
"Unit";"Zergling";"Larva";685;1
"Unit";"Zergling";"Larva";686;1
"Unit";"Zergling";"Larva";687;1
"Building";"CreepTumorQueen";NA;688;0
"Unit";"Hydralisk";"Larva";688;2
"Unit";"Hydralisk";"Larva";690;2
"Building";"CreepTumorQueen";NA;692;0
"Unit";"Overlord";"Larva";692;0
"Building";"CreepTumorQueen";NA;692;0
"Building";"CreepTumor";NA;692;0
"Building";"CreepTumor";NA;692;0
"Building";"CreepTumor";NA;692;0
"Building";"CreepTumor";NA;692;0
"Building";"CreepTumor";NA;692;0
"Building";"SporeCrawler";NA;692;0
"Building";"SporeCrawler";NA;692;0
"Building";"SporeCrawler";NA;692;0
"Building";"SporeCrawler";NA;692;0
"Building";"SporeCrawler";NA;692;0
"Building";"SporeCrawler";NA;692;0
"Building";"SporeCrawler";NA;692;0
"Building";"SporeCrawler";NA;692;0
"Unit";"Zergling";"Larva";692;1
"Unit";"Zergling";"Larva";693;1
"Unit";"Zergling";"Larva";694;1
"Unit";"Zergling";"Larva";695;1
"Unit";"Zergling";"Larva";696;1
"Unit";"Zergling";"Larva";697;1
"Unit";"Zergling";"Larva";698;1
"Unit";"Zergling";"Larva";699;1
"Unit";"Zergling";"Larva";700;1
"Unit";"Zergling";"Larva";701;1
"Unit";"Zergling";"Larva";702;1
"Unit";"Zergling";"Larva";703;1
"Unit";"Zergling";"Larva";704;1
"Unit";"Zergling";"Larva";705;1
"Unit";"Zergling";"Larva";706;1
"Unit";"Zergling";"Larva";707;1
"Unit";"Zergling";"Larva";708;1
"Unit";"Zergling";"Larva";709;1
"Unit";"Zergling";"Larva";710;1
"Unit";"Zergling";"Larva";711;1
"Unit";"Zergling";"Larva";712;1
"Unit";"Zergling";"Larva";713;1
"Unit";"Zergling";"Larva";714;1
"Unit";"Zergling";"Larva";715;1
"Unit";"Zergling";"Larva";716;1
"Unit";"Zergling";"Larva";717;1
"Unit";"Zergling";"Larva";718;1
"Unit";"Zergling";"Larva";719;1
"Unit";"Zergling";"Larva";720;1
"Unit";"Zergling";"Larva";721;1
"Unit";"Zergling";"Larva";722;1
"Unit";"Zergling";"Larva";723;1
"Unit";"Zergling";"Larva";724;1
"Unit";"Zergling";"Larva";725;1
"Unit";"Zergling";"Larva";726;1
"Unit";"Zergling";"Larva";727;1
"Unit";"Zergling";"Larva";728;1
"Unit";"Zergling";"Larva";729;1
"Unit";"Zergling";"Larva";730;1
"Unit";"Zergling";"Larva";731;1
"Unit";"Zergling";"Larva";732;1
"Unit";"Zergling";"Larva";733;1
"Unit";"Zergling";"Larva";734;1
"Unit";"Zergling";"Larva";735;1
"Unit";"Zergling";"Larva";736;1
"Unit";"Zergling";"Larva";737;1
"Unit";"Zergling";"Larva";738;1
"Unit";"Zergling";"Larva";739;1
"Unit";"Zergling";"Larva";740;1
"Unit";"Zergling";"Larva";741;1
"Unit";"Zergling";"Larva";742;1
"Unit";"Zergling";"Larva";743;1
"Unit";"Zergling";"Larva";744;1
"Unit";"Zergling";"Larva";745;1
"Unit";"Hydralisk";"Larva";746;2
"Unit";"Hydralisk";"Larva";748;2
"Unit";"Hydralisk";"Larva";750;2
"Unit";"Zergling";"Larva";752;1
"Unit";"Zergling";"Larva";753;1
"Building";"UltraliskCavern";NA;754;0
"Building";"SporeCrawler";NA;755;0
"Unit";"Hydralisk";"Larva";755;2
"Unit";"Hydralisk";"Larva";757;2
"Unit";"Hydralisk";"Larva";759;2
"Unit";"Hydralisk";"Larva";761;2
"Unit";"Hydralisk";"Larva";763;2
"Unit";"Hydralisk";"Larva";765;2
"Unit";"Zergling";"Larva";767;1
"Unit";"Zergling";"Larva";768;1
"Unit";"Zergling";"Larva";769;1
"Unit";"Zergling";"Larva";770;1
"Unit";"Zergling";"Larva";771;1
"Unit";"Zergling";"Larva";772;1
"Unit";"Zergling";"Larva";773;1
"Unit";"Zergling";"Larva";774;1
"Unit";"Zergling";"Larva";775;1
"Unit";"Zergling";"Larva";776;1
"Unit";"Zergling";"Larva";777;1
"Unit";"Zergling";"Larva";778;1
"Unit";"Zergling";"Larva";779;1
"Unit";"Zergling";"Larva";780;1
"Unit";"Zergling";"Larva";781;1
"Unit";"Zergling";"Larva";782;1
"Unit";"Zergling";"Larva";783;1
"Unit";"Zergling";"Larva";784;1
"Unit";"Zergling";"Larva";785;1
"Unit";"Zergling";"Larva";786;1
"Unit";"Corruptor";"Larva";787;2
"Unit";"Corruptor";"Larva";789;2
"Unit";"Corruptor";"Larva";791;2
"Unit";"Corruptor";"Larva";793;2
"Unit";"Corruptor";"Larva";795;2
"Unit";"Corruptor";"Larva";797;2
"Unit";"Corruptor";"Larva";799;2
"Unit";"Corruptor";"Larva";801;2
"Unit";"Corruptor";"Larva";803;2
"Unit";"Corruptor";"Larva";805;2
"Building";"CreepTumor";NA;807;0
"Building";"CreepTumorQueen";NA;807;0
"Building";"CreepTumor";NA;807;0
"Building";"CreepTumor";NA;807;0
"Building";"CreepTumorQueen";NA;807;0
"Building";"CreepTumor";NA;807;0
"Building";"CreepTumor";NA;807;0
"Building";"CreepTumor";NA;807;0
"Building";"CreepTumor";NA;807;0
"Unit";"Zergling";"Larva";807;1
"Unit";"Zergling";"Larva";808;1
"Upgrade";"ChitinousPlating";"UltraliskCavern";809;0
"Building";"SporeCrawler";NA;812;0
"Building";"SporeCrawler";NA;812;0
"Building";"SporeCrawler";NA;812;0
"Building";"SporeCrawler";NA;812;0
"Building";"CreepTumor";NA;812;0
"Building";"CreepTumor";NA;812;0
"Building";"CreepTumorQueen";NA;812;0
"Building";"CreepTumorQueen";NA;812;0
"Unit";"Viper";"Larva";812;3
"Building";"CreepTumor";NA;815;0
"Building";"CreepTumor";NA;815;0
"Unit";"Overlord";"Larva";815;0
"Building";"SporeCrawler";NA;815;0
"Unit";"Overlord";"Larva";815;0
"Unit";"Overlord";"Larva";815;0
"Building";"SporeCrawler";NA;815;0
"Building";"SporeCrawler";NA;815;0
"Building";"SporeCrawler";NA;815;0
"Building";"SporeCrawler";NA;815;0
"Unit";"Overlord";"Larva";815;0
"Unit";"Zergling";"Larva";815;1
"Unit";"Zergling";"Larva";816;1
"Unit";"Zergling";"Larva";817;1
"Unit";"Zergling";"Larva";818;1
"Unit";"Zergling";"Larva";819;1
"Unit";"Zergling";"Larva";820;1
"Unit";"Zergling";"Larva";821;1
"Unit";"Zergling";"Larva";822;1
"Unit";"Zergling";"Larva";823;1
"Unit";"Zergling";"Larva";824;1
"Unit";"Zergling";"Larva";825;1
"Unit";"Zergling";"Larva";826;1
"Unit";"Zergling";"Larva";827;1
"Unit";"Zergling";"Larva";828;1
"Unit";"Zergling";"Larva";829;1
"Unit";"Zergling";"Larva";830;1
"Unit";"Zergling";"Larva";831;1
"Unit";"Zergling";"Larva";832;1
"Unit";"Zergling";"Larva";833;1
"Unit";"Zergling";"Larva";834;1
"Unit";"Zergling";"Larva";835;1
"Unit";"Zergling";"Larva";836;1
"Unit";"Zergling";"Larva";837;1
"Unit";"Zergling";"Larva";838;1
"Unit";"Zergling";"Larva";839;1
"Unit";"Zergling";"Larva";840;1
"Unit";"Zergling";"Larva";841;1
"Unit";"Zergling";"Larva";842;1
"Unit";"Zergling";"Larva";843;1
"Unit";"Zergling";"Larva";844;1
"Unit";"Zergling";"Larva";845;1
"Unit";"Zergling";"Larva";846;1
"Unit";"Zergling";"Larva";847;1
"Unit";"Zergling";"Larva";848;1
"Unit";"Zergling";"Larva";849;1
"Unit";"Zergling";"Larva";850;1
"Unit";"Zergling";"Larva";851;1
"Unit";"Zergling";"Larva";852;1
"Building";"CreepTumor";NA;853;0
"Building";"CreepTumor";NA;853;0
"Building";"CreepTumor";NA;853;0
"Building";"CreepTumor";NA;853;0
"Building";"CreepTumorQueen";NA;853;0
"Building";"CreepTumor";NA;853;0
"Building";"CreepTumor";NA;853;0
"Building";"CreepTumor";NA;853;0
"Building";"CreepTumor";NA;853;0
"Building";"CreepTumor";NA;853;0
"Unit";"Viper";"Larva";853;3
"Building";"CreepTumor";NA;856;0
"Building";"CreepTumorQueen";NA;856;0
"Unit";"Zergling";"Larva";856;1
"Unit";"Zergling";"Larva";857;1
"Unit";"Zergling";"Larva";858;1
"Unit";"Zergling";"Larva";859;1
"Unit";"Zergling";"Larva";860;1
"Unit";"Zergling";"Larva";861;1
"Unit";"Zergling";"Larva";862;1
"Unit";"Zergling";"Larva";863;1
"Unit";"Zergling";"Larva";864;1
"Unit";"Zergling";"Larva";865;1
"Unit";"Zergling";"Larva";866;1
"Unit";"Zergling";"Larva";867;1
"Unit";"Zergling";"Larva";868;1
"Unit";"Zergling";"Larva";869;1
"Unit";"Zergling";"Larva";870;1
"Unit";"Zergling";"Larva";871;1
"Unit";"Zergling";"Larva";872;1
"Unit";"Zergling";"Larva";873;1
"Unit";"Zergling";"Larva";874;1
"Unit";"Zergling";"Larva";875;1
"Unit";"Zergling";"Larva";876;1
"Unit";"Zergling";"Larva";877;1
"Unit";"Zergling";"Larva";878;1
"Unit";"Zergling";"Larva";879;1
"Unit";"Zergling";"Larva";880;1
"Unit";"Zergling";"Larva";881;1
"Unit";"Corruptor";"Larva";882;2
"Unit";"Corruptor";"Larva";884;2
"Unit";"Corruptor";"Larva";886;2
"Unit";"Corruptor";"Larva";888;2
"Unit";"Corruptor";"Larva";890;2
"Unit";"Corruptor";"Larva";892;2
"Unit";"Corruptor";"Larva";894;2
"Unit";"Hydralisk";"Larva";896;2
"Unit";"Hydralisk";"Larva";898;2
"Unit";"Hydralisk";"Larva";900;2
"Unit";"Hydralisk";"Larva";902;2
"Unit";"Hydralisk";"Larva";904;2
"Unit";"Hydralisk";"Larva";906;2
"Unit";"Hydralisk";"Larva";908;2
"Unit";"Hydralisk";"Larva";910;2
"Unit";"Hydralisk";"Larva";912;2
"Unit";"Hydralisk";"Larva";914;2
"Unit";"Hydralisk";"Larva";916;2
"Unit";"Hydralisk";"Larva";918;2
"Unit";"Hydralisk";"Larva";920;2
"Unit";"Hydralisk";"Larva";922;2
"Unit";"Hydralisk";"Larva";924;2
"Unit";"Hydralisk";"Larva";926;2
"Unit";"Hydralisk";"Larva";928;2
"Unit";"Hydralisk";"Larva";930;2
"Unit";"Hydralisk";"Larva";932;2
"Unit";"Hydralisk";"Larva";934;2
"Unit";"Hydralisk";"Larva";936;2
"Unit";"Hydralisk";"Larva";938;2
"Unit";"Hydralisk";"Larva";940;2
"Unit";"Hydralisk";"Larva";942;2
"Unit";"Hydralisk";"Larva";944;2
"Unit";"Zergling";"Larva";946;1
"Unit";"Zergling";"Larva";947;1
"Unit";"Zergling";"Larva";948;1
"Unit";"Zergling";"Larva";949;1
"Unit";"Zergling";"Larva";950;1
"Unit";"Zergling";"Larva";951;1
"Unit";"Zergling";"Larva";952;1
"Unit";"Zergling";"Larva";953;1
"Unit";"Zergling";"Larva";954;1
"Unit";"Zergling";"Larva";955;1
"Unit";"Zergling";"Larva";956;1
"Unit";"Zergling";"Larva";957;1
"Unit";"Zergling";"Larva";958;1
"Unit";"Zergling";"Larva";959;1
"Unit";"Zergling";"Larva";960;1
"Unit";"Zergling";"Larva";961;1
"Unit";"Zergling";"Larva";962;1
"Unit";"Zergling";"Larva";963;1
"Unit";"Zergling";"Larva";964;1
"Unit";"Zergling";"Larva";965;1
"Unit";"Zergling";"Larva";966;1
"Unit";"Zergling";"Larva";967;1
"Unit";"Hydralisk";"Larva";968;2
"Unit";"Hydralisk";"Larva";970;2
"Unit";"Hydralisk";"Larva";972;2
"Unit";"Hydralisk";"Larva";974;2
"Unit";"Hydralisk";"Larva";976;2
"Unit";"Hydralisk";"Larva";978;2
"Unit";"Hydralisk";"Larva";980;2
"Unit";"Zergling";"Larva";982;1
"Unit";"Zergling";"Larva";983;1
"Unit";"Zergling";"Larva";984;1
"Unit";"Zergling";"Larva";985;1
"Unit";"Zergling";"Larva";986;1
"Unit";"Zergling";"Larva";987;1
"Unit";"Zergling";"Larva";988;1
"Unit";"Zergling";"Larva";989;1
"Unit";"Zergling";"Larva";990;1
"Unit";"Zergling";"Larva";991;1
"Unit";"Zergling";"Larva";992;1
"Unit";"Zergling";"Larva";993;1
"Unit";"Zergling";"Larva";994;1
"Unit";"Zergling";"Larva";995;1
"Unit";"Zergling";"Larva";996;1
"Unit";"Zergling";"Larva";997;1
"Unit";"Zergling";"Larva";998;1
"Unit";"Zergling";"Larva";999;1
"Upgrade";"SprayZerg";NA;1000;0
"Upgrade";"SprayZerg";NA;1000;0
"Upgrade";"SprayZerg";NA;1000;0
"Upgrade";"zerglingmovementspeed";NA;1000;0
"Upgrade";"SprayZerg";NA;1000;0
"Upgrade";"SprayZerg";NA;1000;0
"Upgrade";"ZergMeleeWeaponsLevel1";NA;1000;0
"Upgrade";"SprayZerg";NA;1000;0
"Upgrade";"SprayZerg";NA;1000;0
"Upgrade";"EvolveMuscularAugments";NA;1000;0
"Upgrade";"SprayZerg";NA;1000;0
"Upgrade";"ZergMeleeWeaponsLevel2";NA;1000;0
"Upgrade";"ZergMissileWeaponsLevel1";NA;1000;0
"Upgrade";"overlordspeed";NA;1000;0
"Upgrade";"CentrificalHooks";NA;1000;0
"Upgrade";"SprayZerg";NA;1000;0
"Upgrade";"SprayZerg";NA;1000;0
"Upgrade";"zerglingattackspeed";NA;1000;0
"Upgrade";"ZergGroundArmorsLevel1";NA;1000;0
"Upgrade";"SprayZerg";NA;1000;0
"Upgrade";"ZergMeleeWeaponsLevel3";NA;1000;0
"Upgrade";"SprayZerg";NA;1000;0
"Upgrade";"ZergGroundArmorsLevel2";NA;1000;0
"Upgrade";"ZergFlyerWeaponsLevel1";NA;1000;0
"Upgrade";"SprayZerg";NA;1000;0
"Upgrade";"ZergMissileWeaponsLevel2";NA;1000;0
"Upgrade";"SprayZerg";NA;1000;0
"Upgrade";"ZergFlyerArmorsLevel1";NA;1000;0
"Upgrade";"ZergGroundArmorsLevel3";NA;1000;0
"Upgrade";"ZergFlyerWeaponsLevel2";NA;1000;0
"Upgrade";"ZergMissileWeaponsLevel3";NA;1000;0
"Upgrade";"InfestorEnergyUpgrade";NA;1000;0
"Upgrade";"ZergFlyerArmorsLevel2";NA;1000;0
