"type";"unit_name";"on_building";"total_supply";"supply"
"Unit";"Overlord";"Larva";13;0
"Building";"Extractor";NA;18;0
"Building";"SpawningPool";NA;19;0
"Building";"Hatchery";NA;17;0
"Unit";"Zergling";"Larva";25;1
"Unit";"Zergling";"Larva";25;1
"Unit";"Zergling";"Larva";25;1
"Unit";"Zergling";"Larva";25;1
"Unit";"Queen";"Hatchery";24;2
"Unit";"Overlord";"Larva";26;0
"Unit";"Overlord";"Larva";30;0
"Building";"Hatchery";NA;22;0
"Unit";"Zergling";"Larva";34;1
"Unit";"Zergling";"Larva";34;1
"Unit";"Queen";"Hatchery";33;2
"Building";"CreepTumorQueen";NA;37;0
"Unit";"Queen";"Hatchery";34;2
"Unit";"Overlord";"Larva";43;0
"Building";"CreepTumorQueen";NA;51;0
"Unit";"Queen";"Hatchery";45;2
"Building";"CreepTumor";NA;52;0
"Unit";"Overlord";"Larva";52;0
"Unit";"Overlord";"Larva";57;0
"Unit";"Overlord";"Larva";60;0
"Building";"Extractor";NA;58;0
"Building";"Extractor";NA;58;0
"Building";"CreepTumorQueen";NA;62;0
"Building";"EvolutionChamber";NA;62;0
"Building";"CreepTumor";NA;62;0
"Building";"CreepTumor";NA;72;0
"Building";"Extractor";NA;71;0
"Building";"Extractor";NA;78;0
"Building";"Extractor";NA;78;0
"Building";"CreepTumor";NA;84;0
"Building";"SporeCrawler";NA;84;0
"Building";"CreepTumor";NA;85;0
"Unit";"Zergling";"Larva";84;1
"Unit";"Zergling";"Larva";84;1
"Unit";"Zergling";"Larva";84;1
"Unit";"Zergling";"Larva";84;1
"Unit";"Zergling";"Larva";84;1
"Unit";"Zergling";"Larva";84;1
"Unit";"Zergling";"Larva";84;1
"Unit";"Zergling";"Larva";84;1
"Unit";"Zergling";"Larva";84;1
"Unit";"Zergling";"Larva";84;1
"Building";"SporeCrawler";NA;84;0
"Unit";"Overlord";"Larva";85;0
"Building";"CreepTumorQueen";NA;90;0
"Building";"CreepTumorQueen";NA;90;0
"Unit";"Overlord";"Larva";90;0
"Unit";"Overlord";"Larva";90;0
"Unit";"Overlord";"Larva";90;0
"Building";"Spire";NA;73;0
"Building";"SporeCrawler";NA;100;0
"Building";"CreepTumor";NA;104;0
"Unit";"Overlord";"Larva";100;0
"Building";"CreepTumor";NA;106;0
"Unit";"Overlord";"Larva";104;0
"Building";"CreepTumor";NA;106;0
"Building";"Hatchery";NA;84;0
"Unit";"Mutalisk";"Larva";106;2
"Unit";"Mutalisk";"Larva";106;2
"Unit";"Mutalisk";"Larva";106;2
"Unit";"Mutalisk";"Larva";106;2
"Unit";"Mutalisk";"Larva";106;2
"Unit";"Mutalisk";"Larva";106;2
"Unit";"Mutalisk";"Larva";106;2
"Building";"CreepTumorQueen";NA;110;0
"Building";"CreepTumor";NA;110;0
"Building";"Hatchery";NA;88;0
"Building";"CreepTumor";NA;110;0
"Building";"CreepTumor";NA;110;0
"Unit";"Overlord";"Larva";112;0
"Building";"InfestationPit";NA;106;0
"Building";"SporeCrawler";NA;128;0
"Building";"SporeCrawler";NA;129;0
"Unit";"Overlord";"Larva";132;0
"Building";"Extractor";NA;132;0
"Building";"Extractor";NA;132;0
"Unit";"Zergling";"Larva";137;1
"Unit";"Zergling";"Larva";137;1
"Unit";"Zergling";"Larva";137;1
"Unit";"Zergling";"Larva";137;1
"Building";"SporeCrawler";NA;140;0
"Upgrade";"ZergMeleeWeaponsLevel1";"EvolutionChamber";106;0
"Unit";"Corruptor";"Larva";144;2
"Unit";"Corruptor";"Larva";144;2
"Unit";"Corruptor";"Larva";144;2
"Unit";"Corruptor";"Larva";144;2
"Unit";"Corruptor";"Larva";144;2
"Unit";"Corruptor";"Larva";144;2
"Unit";"Corruptor";"Larva";144;2
"Unit";"Corruptor";"Larva";144;2
"Unit";"Corruptor";"Larva";144;2
"Unit";"Zergling";"Larva";144;1
"Unit";"Zergling";"Larva";144;1
"Unit";"Zergling";"Larva";144;1
"Unit";"Zergling";"Larva";144;1
"Unit";"Overlord";"Larva";144;0
"Building";"CreepTumorQueen";NA;171;0
"Building";"CreepTumor";NA;171;0
"Building";"CreepTumor";NA;173;0
"Unit";"Overlord";"Larva";153;0
"Unit";"Overlord";"Larva";173;0
"Unit";"Corruptor";"Larva";153;2
"Unit";"Corruptor";"Larva";153;2
"Unit";"Corruptor";"Larva";153;2
"Unit";"Overlord";"Larva";177;0
"Unit";"Zergling";"Larva";177;1
"Unit";"Zergling";"Larva";177;1
"Building";"Extractor";NA;177;0
"Building";"Extractor";NA;177;0
"Unit";"Zergling";"Larva";177;1
"Unit";"Zergling";"Larva";177;1
"Unit";"Zergling";"Larva";177;1
"Unit";"Zergling";"Larva";177;1
"Unit";"Zergling";"Larva";177;1
"Unit";"Zergling";"Larva";177;1
"Unit";"Zergling";"Larva";177;1
"Unit";"Zergling";"Larva";177;1
"Unit";"Zergling";"Larva";177;1
"Unit";"Zergling";"Larva";177;1
"Building";"CreepTumor";NA;177;0
"Building";"CreepTumor";NA;197;0
"Unit";"Zergling";"Larva";197;1
"Unit";"Zergling";"Larva";197;1
"Unit";"Overlord";"Larva";197;0
"Building";"CreepTumor";NA;199;0
"Building";"CreepTumor";NA;200;0
"Unit";"Zergling";"Larva";197;1
"Unit";"Zergling";"Larva";197;1
"Unit";"Zergling";"Larva";197;1
"Unit";"Zergling";"Larva";197;1
"Unit";"Zergling";"Larva";197;1
"Unit";"Zergling";"Larva";197;1
"Unit";"Zergling";"Larva";197;1
"Unit";"Zergling";"Larva";197;1
"Building";"CreepTumorQueen";NA;200;0
"Unit";"Overlord";"Larva";199;0
"Unit";"Overlord";"Larva";199;0
"Building";"CreepTumorQueen";NA;200;0
"Building";"CreepTumor";NA;200;0
"Upgrade";"Burrow";"Hatchery";185;0
"Unit";"Mutalisk";"Larva";200;2
"Unit";"Mutalisk";"Larva";200;2
"Unit";"Mutalisk";"Larva";200;2
"Unit";"Mutalisk";"Larva";200;2
"Unit";"Mutalisk";"Larva";200;2
"Unit";"Mutalisk";"Larva";200;2
"Unit";"Mutalisk";"Larva";200;2
"Unit";"Zergling";"Larva";204;1
"Unit";"Zergling";"Larva";204;1
"Unit";"Zergling";"Larva";204;1
"Unit";"Zergling";"Larva";204;1
"Unit";"Zergling";"Larva";204;1
"Unit";"Zergling";"Larva";204;1
"Building";"CreepTumor";NA;212;0
"Unit";"Overlord";"Larva";204;0
"Building";"CreepTumor";NA;212;0
"Upgrade";"NeuralParasite";"InfestationPit";195;0
"Unit";"Overlord";"Larva";212;0
"Building";"CreepTumor";NA;212;0
"Building";"CreepTumor";NA;212;0
"Unit";"Zergling";"Larva";212;1
"Unit";"Zergling";"Larva";212;1
"Building";"CreepTumor";NA;212;0
"Unit";"Zergling";"Larva";232;1
"Unit";"Zergling";"Larva";232;1
"Unit";"Zergling";"Larva";232;1
"Unit";"Zergling";"Larva";232;1
"Building";"Spire";NA;197;0
"Unit";"Infestor";"Larva";212;2
"Unit";"Infestor";"Larva";212;2
"Unit";"Infestor";"Larva";212;2
"Unit";"Corruptor";"Larva";232;2
"Unit";"Corruptor";"Larva";232;2
"Unit";"Zergling";"Larva";234;1
"Unit";"Zergling";"Larva";234;1
"Unit";"Zergling";"Larva";234;1
"Unit";"Zergling";"Larva";234;1
"Unit";"Zergling";"Larva";236;1
"Unit";"Zergling";"Larva";236;1
"Unit";"Zergling";"Larva";238;1
"Unit";"Zergling";"Larva";238;1
"Building";"CreepTumorQueen";NA;244;0
"Building";"CreepTumorQueen";NA;248;0
"Building";"Hatchery";NA;200;0
"Unit";"Corruptor";"Larva";234;2
"Unit";"Corruptor";"Larva";234;2
"Unit";"Corruptor";"Larva";234;2
"Unit";"Corruptor";"Larva";234;2
"Building";"BanelingNest";NA;234;0
"Unit";"Zergling";"Larva";256;1
"Unit";"Zergling";"Larva";256;1
"Unit";"Zergling";"Larva";256;1
"Unit";"Zergling";"Larva";256;1
"Unit";"Zergling";"Larva";256;1
"Unit";"Zergling";"Larva";256;1
"Unit";"Zergling";"Larva";256;1
"Unit";"Zergling";"Larva";256;1
"Unit";"Zergling";"Larva";256;1
"Unit";"Zergling";"Larva";256;1
"Building";"Hatchery";NA;212;0
"Upgrade";"ZergMeleeWeaponsLevel2";"EvolutionChamber";200;0
"Unit";"Corruptor";"Larva";256;2
"Unit";"Corruptor";"Larva";256;2
"Unit";"Corruptor";"Larva";256;2
"Unit";"Corruptor";"Larva";256;2
"Unit";"Corruptor";"Larva";256;2
"Unit";"Zergling";"Larva";264;1
"Unit";"Zergling";"Larva";264;1
"Unit";"Zergling";"Larva";264;1
"Unit";"Zergling";"Larva";264;1
"Unit";"Zergling";"Larva";264;1
"Unit";"Zergling";"Larva";264;1
"Unit";"Zergling";"Larva";264;1
"Unit";"Zergling";"Larva";264;1
"Unit";"Zergling";"Larva";264;1
"Unit";"Zergling";"Larva";264;1
"Unit";"Zergling";"Larva";264;1
"Unit";"Zergling";"Larva";264;1
"Unit";"Baneling";"Zergling";274;0
"Unit";"Baneling";"Zergling";274;0
"Unit";"Baneling";"Zergling";274;0
"Unit";"Baneling";"Zergling";274;0
"Unit";"Baneling";"Zergling";274;0
"Unit";"Baneling";"Zergling";274;0
"Unit";"Baneling";"Zergling";274;0
"Unit";"Baneling";"Zergling";274;0
"Unit";"Baneling";"Zergling";274;0
"Unit";"Baneling";"Zergling";274;0
"Unit";"Baneling";"Zergling";274;0
"Unit";"Zergling";"Larva";274;1
"Unit";"Zergling";"Larva";274;1
"Unit";"Zergling";"Larva";274;1
"Unit";"Zergling";"Larva";274;1
"Unit";"Zergling";"Larva";274;1
"Unit";"Zergling";"Larva";274;1
"Unit";"Zergling";"Larva";274;1
"Unit";"Zergling";"Larva";274;1
"Unit";"Zergling";"Larva";304;1
"Unit";"Zergling";"Larva";304;1
"Unit";"Zergling";"Larva";304;1
"Unit";"Zergling";"Larva";304;1
"Unit";"Zergling";"Larva";304;1
"Unit";"Zergling";"Larva";304;1
"Unit";"Zergling";"Larva";304;1
"Unit";"Zergling";"Larva";304;1
"Unit";"Zergling";"Larva";304;1
"Unit";"Zergling";"Larva";304;1
"Unit";"Zergling";"Larva";304;1
"Unit";"Zergling";"Larva";304;1
"Unit";"Zergling";"Larva";304;1
"Unit";"Zergling";"Larva";304;1
"Unit";"Zergling";"Larva";304;1
"Unit";"Zergling";"Larva";304;1
"Unit";"Zergling";"Larva";304;1
"Unit";"Zergling";"Larva";304;1
"Unit";"Zergling";"Larva";304;1
"Unit";"Zergling";"Larva";304;1
"Unit";"Zergling";"Larva";304;1
"Unit";"Zergling";"Larva";304;1
"Unit";"Zergling";"Larva";304;1
"Unit";"Zergling";"Larva";304;1
"Unit";"Zergling";"Larva";304;1
"Unit";"Zergling";"Larva";304;1
"Unit";"Zergling";"Larva";304;1
"Unit";"Zergling";"Larva";304;1
"Unit";"Zergling";"Larva";304;1
"Unit";"Zergling";"Larva";304;1
"Unit";"Zergling";"Larva";304;1
"Unit";"Zergling";"Larva";304;1
"Unit";"Zergling";"Larva";304;1
"Unit";"Zergling";"Larva";304;1
"Unit";"Zergling";"Larva";304;1
"Unit";"Zergling";"Larva";304;1
"Unit";"Zergling";"Larva";304;1
"Unit";"Zergling";"Larva";304;1
"Unit";"Zergling";"Larva";304;1
"Unit";"Zergling";"Larva";304;1
"Unit";"Zergling";"Larva";304;1
"Unit";"Zergling";"Larva";304;1
