"type";"unit_name";"on_building";"total_supply";"supply"
"Unit";"Overlord";"Larva";13;0
"Building";"Extractor";NA;17;0
"Unit";"Overlord";"Larva";21;0
"Building";"SpawningPool";NA;19;0
"Building";"Hatchery";NA;17;0
"Unit";"Zergling";"Larva";22;1
"Unit";"Zergling";"Larva";22;1
"Unit";"Zergling";"Larva";23;1
"Unit";"Zergling";"Larva";23;1
"Unit";"Queen";"Hatchery";22;2
"Unit";"Queen";"Hatchery";23;2
"Unit";"Overlord";"Larva";34;0
"Unit";"Overlord";"Larva";37;0
"Unit";"Queen";"Hatchery";37;2
"Building";"Hatchery";NA;29;0
"Building";"CreepTumorQueen";NA;49;0
"Building";"Extractor";NA;49;0
"Unit";"Overlord";"Larva";49;0
"Unit";"Queen";"Hatchery";44;2
"Building";"CreepTumorQueen";NA;54;0
"Unit";"Queen";"Hatchery";51;2
"Building";"RoachWarren";NA;51;0
"Building";"CreepTumorQueen";NA;66;0
"Building";"CreepTumor";NA;66;0
"Unit";"Overlord";"Larva";66;0
"Unit";"Overlord";"Larva";66;0
"Unit";"Overlord";"Larva";66;0
"Unit";"Overlord";"Larva";66;0
"Building";"Extractor";NA;66;0
"Unit";"Overlord";"Larva";66;0
"Building";"CreepTumor";NA;67;0
"Building";"CreepTumorQueen";NA;67;0
"Building";"CreepTumorQueen";NA;67;0
"Building";"CreepTumor";NA;67;0
"Building";"EvolutionChamber";NA;67;0
"Unit";"Roach";"Larva";67;2
"Unit";"Roach";"Larva";67;2
"Unit";"Roach";"Larva";67;2
"Unit";"Roach";"Larva";67;2
"Unit";"Roach";"Larva";67;2
"Unit";"Roach";"Larva";67;2
"Unit";"Roach";"Larva";67;2
"Unit";"Roach";"Larva";67;2
"Unit";"Roach";"Larva";67;2
"Unit";"Overlord";"Larva";67;0
"Unit";"Overlord";"Larva";67;0
"Unit";"Roach";"Larva";67;2
"Unit";"Roach";"Larva";67;2
"Unit";"Roach";"Larva";67;2
"Unit";"Roach";"Larva";67;2
"Unit";"Overlord";"Larva";67;0
"Unit";"Roach";"Larva";67;2
"Unit";"Roach";"Larva";67;2
"Building";"CreepTumor";NA;85;0
"Unit";"Overlord";"Larva";85;0
"Building";"CreepTumor";NA;85;0
"Building";"CreepTumor";NA;85;0
"Unit";"Overlord";"Larva";85;0
"Building";"CreepTumor";NA;93;0
"Building";"CreepTumor";NA;93;0
"Unit";"Roach";"Larva";93;2
"Unit";"Roach";"Larva";93;2
"Unit";"Roach";"Larva";93;2
"Unit";"Roach";"Larva";93;2
"Building";"CreepTumorQueen";NA;97;0
"Building";"CreepTumorQueen";NA;97;0
"Unit";"Overlord";"Larva";97;0
"Unit";"Roach";"Larva";97;2
"Building";"CreepTumor";NA;105;0
"Unit";"Roach";"Larva";97;2
"Building";"CreepTumor";NA;105;0
"Building";"CreepTumor";NA;105;0
"Building";"HydraliskDen";NA;97;0
"Building";"SporeCrawler";NA;105;0
"Building";"SporeCrawler";NA;105;0
"Building";"SporeCrawler";NA;105;0
"Building";"CreepTumor";NA;105;0
"Building";"CreepTumor";NA;109;0
"Building";"CreepTumor";NA;109;0
"Building";"CreepTumor";NA;109;0
"Unit";"Queen";"Hatchery";109;2
"Unit";"Queen";"Hatchery";109;2
"Unit";"Roach";"Larva";119;2
"Unit";"Roach";"Larva";119;2
"Unit";"Roach";"Larva";119;2
"Unit";"Roach";"Larva";119;2
"Unit";"Roach";"Larva";119;2
"Unit";"Hydralisk";"Larva";121;2
"Unit";"Hydralisk";"Larva";123;2
"Unit";"Hydralisk";"Larva";125;2
"Building";"CreepTumor";NA;135;0
"Building";"CreepTumor";NA;135;0
"Building";"CreepTumor";NA;135;0
"Upgrade";"GlialReconstitution";"RoachWarren";119;0
"Unit";"Overlord";"Larva";139;0
"Unit";"Overlord";"Larva";139;0
"Unit";"Overlord";"Larva";139;0
"Unit";"Overlord";"Larva";139;0
"Unit";"Overlord";"Larva";139;0
"Unit";"Hydralisk";"Larva";139;2
"Unit";"Hydralisk";"Larva";139;2
"Unit";"Hydralisk";"Larva";139;2
"Building";"CreepTumor";NA;139;0
"Building";"CreepTumor";NA;139;0
"Building";"CreepTumor";NA;139;0
"Building";"Hatchery";NA;121;0
"Building";"Extractor";NA;139;0
"Upgrade";"ZergMissileWeaponsLevel1";"EvolutionChamber";123;0
"Building";"Extractor";NA;145;0
"Building";"Hatchery";NA;139;0
"Unit";"Hydralisk";"Larva";151;2
"Unit";"Hydralisk";"Larva";151;2
"Unit";"Hydralisk";"Larva";151;2
"Unit";"Hydralisk";"Larva";151;2
"Unit";"Roach";"Larva";151;2
"Unit";"Roach";"Larva";151;2
"Unit";"Roach";"Larva";151;2
"Unit";"Roach";"Larva";151;2
"Unit";"Roach";"Larva";151;2
"Unit";"Roach";"Larva";151;2
"Unit";"Roach";"Larva";151;2
"Upgrade";"EvolveGroovedSpines";"HydraliskDen";151;0
"Building";"Hatchery";NA;145;0
"Building";"Extractor";NA;185;0
"Building";"Extractor";NA;185;0
"Upgrade";"EvolveMuscularAugments";"HydraliskDen";185;0
"Building";"InfestationPit";NA;185;0
"Unit";"Queen";"Hatchery";185;2
"Unit";"Hydralisk";"Larva";185;2
"Unit";"Hydralisk";"Larva";185;2
"Unit";"Hydralisk";"Larva";185;2
"Unit";"Hydralisk";"Larva";185;2
"Unit";"Hydralisk";"Larva";185;2
"Unit";"Hydralisk";"Larva";185;2
"Unit";"Hydralisk";"Larva";185;2
"Unit";"Hydralisk";"Larva";185;2
"Unit";"Hydralisk";"Larva";185;2
"Unit";"Roach";"Larva";185;2
"Unit";"Roach";"Larva";185;2
"Unit";"Roach";"Larva";185;2
"Unit";"Roach";"Larva";185;2
"Unit";"Roach";"Larva";185;2
"Unit";"Roach";"Larva";185;2
"Unit";"Roach";"Larva";185;2
"Unit";"Roach";"Larva";185;2
"Unit";"Roach";"Larva";185;2
"Unit";"Roach";"Larva";185;2
"Unit";"Overlord";"Larva";187;0
"Unit";"Hydralisk";"Larva";205;2
"Unit";"Hydralisk";"Larva";205;2
"Unit";"Hydralisk";"Larva";205;2
"Unit";"Hydralisk";"Larva";205;2
"Unit";"Queen";"Hatchery";185;2
"Unit";"Queen";"Hatchery";185;2
"Unit";"Queen";"Hatchery";185;2
"Unit";"Queen";"Hatchery";185;2
"Unit";"Roach";"Larva";225;2
"Unit";"Roach";"Larva";225;2
"Unit";"Roach";"Larva";225;2
"Unit";"Roach";"Larva";225;2
"Unit";"Roach";"Larva";225;2
"Building";"LurkerDenMP";NA;185;0
"Unit";"Roach";"Larva";233;2
"Unit";"Roach";"Larva";233;2
"Unit";"Roach";"Larva";233;2
"Unit";"Roach";"Larva";233;2
"Unit";"Roach";"Larva";233;2
"Unit";"Roach";"Larva";233;2
"Unit";"Overlord";"Larva";241;0
"Upgrade";"ZergMissileWeaponsLevel2";"EvolutionChamber";185;0
"Building";"CreepTumorQueen";NA;251;0
"Building";"CreepTumorQueen";NA;263;0
"Unit";"Overlord";"Larva";251;0
"Unit";"Overlord";"Larva";251;0
"Building";"CreepTumorQueen";NA;263;0
"Building";"CreepTumorQueen";NA;263;0
"Unit";"Hydralisk";"Larva";263;2
"Unit";"Hydralisk";"Larva";263;2
"Unit";"Hydralisk";"Larva";263;2
"Unit";"Hydralisk";"Larva";263;2
"Unit";"Hydralisk";"Larva";263;2
"Unit";"Hydralisk";"Larva";263;2
"Unit";"Hydralisk";"Larva";263;2
"Unit";"Hydralisk";"Larva";263;2
"Unit";"Hydralisk";"Larva";263;2
"Unit";"Hydralisk";"Larva";263;2
"Unit";"Hydralisk";"Larva";263;2
"Building";"Extractor";NA;285;0
"Unit";"Roach";"Larva";285;2
"Unit";"Roach";"Larva";285;2
"Unit";"Roach";"Larva";285;2
"Unit";"Roach";"Larva";285;2
"Unit";"Roach";"Larva";285;2
"Unit";"Roach";"Larva";285;2
"Unit";"Roach";"Larva";285;2
"Unit";"Roach";"Larva";285;2
"Unit";"Roach";"Larva";285;2
"Unit";"Roach";"Larva";285;2
"Unit";"Roach";"Larva";285;2
"Building";"Spire";NA;285;0
"Building";"CreepTumor";NA;310;0
"Building";"CreepTumor";NA;310;0
"Building";"CreepTumor";NA;310;0
"Building";"CreepTumor";NA;310;0
"Building";"CreepTumorQueen";NA;310;0
"Building";"CreepTumorQueen";NA;310;0
"Building";"CreepTumorQueen";NA;310;0
"Building";"CreepTumorQueen";NA;310;0
"Building";"CreepTumorQueen";NA;310;0
"Building";"Extractor";NA;310;0
"Building";"Extractor";NA;310;0
"Building";"CreepTumorQueen";NA;310;0
"Building";"CreepTumorQueen";NA;310;0
"Building";"CreepTumorQueen";NA;310;0
"Building";"CreepTumorQueen";NA;310;0
"Building";"CreepTumorQueen";NA;310;0
"Building";"CreepTumor";NA;310;0
"Building";"CreepTumor";NA;310;0
"Building";"CreepTumor";NA;310;0
"Building";"CreepTumor";NA;310;0
"Building";"CreepTumor";NA;310;0
"Building";"CreepTumor";NA;310;0
"Unit";"Hydralisk";"Larva";310;2
"Unit";"Hydralisk";"Larva";310;2
"Unit";"Viper";"Larva";310;3
"Unit";"Viper";"Larva";310;3
"Unit";"Viper";"Larva";310;3
"Unit";"Viper";"Larva";310;3
"Building";"Spire";NA;310;0
"Upgrade";"ZergMissileWeaponsLevel3";"EvolutionChamber";310;0
"Unit";"Mutalisk";"Larva";326;2
"Unit";"Mutalisk";"Larva";326;2
"Unit";"Mutalisk";"Larva";326;2
"Unit";"Mutalisk";"Larva";326;2
"Unit";"Mutalisk";"Larva";326;2
"Unit";"Mutalisk";"Larva";326;2
"Unit";"Mutalisk";"Larva";326;2
"Unit";"Mutalisk";"Larva";326;2
"Unit";"Mutalisk";"Larva";326;2
"Unit";"Mutalisk";"Larva";326;2
"Unit";"Mutalisk";"Larva";326;2
"Unit";"Mutalisk";"Larva";326;2
"Unit";"Mutalisk";"Larva";326;2
"Unit";"Mutalisk";"Larva";326;2
"Unit";"Mutalisk";"Larva";326;2
"Unit";"Mutalisk";"Larva";326;2
"Unit";"Roach";"Larva";326;2
"Unit";"Roach";"Larva";328;2
"Unit";"Roach";"Larva";328;2
"Unit";"Roach";"Larva";328;2
"Unit";"Roach";"Larva";328;2
"Unit";"Roach";"Larva";328;2
"Unit";"Roach";"Larva";328;2
"Unit";"Roach";"Larva";330;2
"Unit";"Roach";"Larva";332;2
"Unit";"Roach";"Larva";332;2
"Unit";"Roach";"Larva";336;2
"Unit";"Roach";"Larva";336;2
"Unit";"Roach";"Larva";340;2
"Unit";"Roach";"Larva";344;2
"Unit";"Roach";"Larva";344;2
"Unit";"Roach";"Larva";344;2
"Unit";"Roach";"Larva";348;2
"Unit";"Roach";"Larva";352;2
"Unit";"Roach";"Larva";352;2
"Unit";"Roach";"Larva";356;2
"Unit";"Roach";"Larva";356;2
"Building";"CreepTumor";NA;400;0
"Building";"CreepTumor";NA;400;0
"Building";"CreepTumor";NA;400;0
"Building";"CreepTumor";NA;400;0
"Building";"CreepTumor";NA;400;0
"Building";"CreepTumor";NA;400;0
