"type";"unit_name";"on_building";"total_supply";"supply"
"Unit";"Overlord";"Larva";13;0
"Building";"Extractor";NA;18;0
"Unit";"Overlord";"Larva";21;0
"Building";"SpawningPool";NA;19;0
"Building";"Hatchery";NA;17;0
"Unit";"Zergling";"Larva";23;1
"Unit";"Zergling";"Larva";23;1
"Unit";"Zergling";"Larva";23;1
"Unit";"Zergling";"Larva";23;1
"Unit";"Queen";"Hatchery";23;2
"Unit";"Queen";"Hatchery";23;2
"Building";"CreepTumorQueen";NA;35;0
"Unit";"Overlord";"Larva";35;0
"Unit";"Overlord";"Larva";40;0
"Unit";"Queen";"Hatchery";37;2
"Building";"SporeCrawler";NA;42;0
"Building";"SporeCrawler";NA;42;0
"Building";"Hatchery";NA;31;0
"Building";"Extractor";NA;42;0
"Building";"CreepTumor";NA;48;0
"Building";"CreepTumorQueen";NA;48;0
"Unit";"Overlord";"Larva";48;0
"Building";"SporeCrawler";NA;48;0
"Building";"CreepTumorQueen";NA;55;0
"Unit";"Overlord";"Larva";55;0
"Building";"CreepTumor";NA;55;0
"Unit";"Overlord";"Larva";55;0
"Building";"Extractor";NA;60;0
"Building";"CreepTumor";NA;64;0
"Building";"Extractor";NA;60;0
"Building";"CreepTumor";NA;68;0
"Unit";"Zergling";"Larva";67;1
"Unit";"Zergling";"Larva";67;1
"Unit";"Zergling";"Larva";67;1
"Unit";"Zergling";"Larva";67;1
"Building";"BanelingNest";NA;55;0
"Building";"HydraliskDen";NA;60;0
"Building";"CreepTumorQueen";NA;68;0
"Unit";"Overlord";"Larva";68;0
"Unit";"Overlord";"Larva";68;0
"Building";"EvolutionChamber";NA;68;0
"Building";"CreepTumorQueen";NA;78;0
"Building";"CreepTumor";NA;78;0
"Unit";"Queen";"Hatchery";72;2
"Building";"CreepTumor";NA;78;0
"Unit";"Hydralisk";"Larva";78;2
"Unit";"Hydralisk";"Larva";78;2
"Unit";"Hydralisk";"Larva";78;2
"Unit";"Hydralisk";"Larva";78;2
"Unit";"Hydralisk";"Larva";78;2
"Unit";"Hydralisk";"Larva";84;2
"Unit";"Hydralisk";"Larva";84;2
"Unit";"Hydralisk";"Larva";84;2
"Unit";"Hydralisk";"Larva";84;2
"Building";"CreepTumor";NA;95;0
"Building";"CreepTumor";NA;103;0
"Building";"CreepTumor";NA;103;0
"Building";"Extractor";NA;103;0
"Unit";"Overlord";"Larva";103;0
"Building";"Extractor";NA;103;0
"Upgrade";"EvolveGroovedSpines";"HydraliskDen";87;0
"Unit";"Queen";"Hatchery";103;2
"Unit";"Overlord";"Larva";112;0
"Unit";"Overlord";"Larva";112;0
"Building";"CreepTumor";NA;112;0
"Building";"CreepTumor";NA;112;0
"Unit";"Overlord";"Larva";120;0
"Unit";"Overlord";"Larva";120;0
"Unit";"Hydralisk";"Larva";120;2
"Unit";"Hydralisk";"Larva";120;2
"Unit";"Hydralisk";"Larva";120;2
"Unit";"Hydralisk";"Larva";120;2
"Unit";"Hydralisk";"Larva";120;2
"Unit";"Hydralisk";"Larva";120;2
"Unit";"Overlord";"Larva";120;0
"Unit";"Overlord";"Larva";120;0
"Unit";"Overlord";"Larva";120;0
"Building";"Hatchery";NA;112;0
"Upgrade";"ZergMissileWeaponsLevel1";"EvolutionChamber";103;0
"Upgrade";"EvolveMuscularAugments";"HydraliskDen";120;0
"Unit";"Overlord";"Larva";132;0
"Building";"CreepTumor";NA;132;0
"Building";"CreepTumor";NA;140;0
"Building";"Extractor";NA;145;0
"Building";"InfestationPit";NA;132;0
"Building";"SporeCrawler";NA;145;0
"Unit";"Zergling";"Larva";145;1
"Unit";"Zergling";"Larva";145;1
"Building";"Extractor";NA;145;0
"Building";"CreepTumorQueen";NA;153;0
"Building";"CreepTumorQueen";NA;153;0
"Building";"CreepTumorQueen";NA;153;0
"Building";"CreepTumor";NA;153;0
"Building";"SpineCrawler";NA;145;0
"Building";"LurkerDenMP";NA;120;0
"Unit";"Overlord";"Larva";155;0
"Unit";"Overlord";"Larva";155;0
"Unit";"Overlord";"Larva";155;0
"Unit";"Hydralisk";"Larva";155;2
"Unit";"Hydralisk";"Larva";155;2
"Unit";"Hydralisk";"Larva";155;2
"Unit";"Hydralisk";"Larva";155;2
"Unit";"Hydralisk";"Larva";155;2
"Unit";"Hydralisk";"Larva";155;2
"Unit";"Hydralisk";"Larva";155;2
"Unit";"Hydralisk";"Larva";155;2
"Unit";"Hydralisk";"Larva";155;2
"Unit";"Hydralisk";"Larva";155;2
"Unit";"Hydralisk";"Larva";155;2
"Unit";"Hydralisk";"Larva";155;2
"Unit";"Overlord";"Larva";155;0
"Unit";"Overlord";"Larva";155;0
"Unit";"Overlord";"Larva";155;0
"Unit";"Hydralisk";"Larva";155;2
"Unit";"Hydralisk";"Larva";155;2
"Unit";"Hydralisk";"Larva";155;2
"Unit";"Hydralisk";"Larva";155;2
"Unit";"Overlord";"Larva";179;0
"Unit";"Overlord";"Larva";179;0
"Unit";"Overlord";"Larva";179;0
"Unit";"Hydralisk";"Larva";179;2
"Unit";"Hydralisk";"Larva";179;2
"Unit";"Hydralisk";"Larva";179;2
"Unit";"Hydralisk";"Larva";179;2
"Unit";"Hydralisk";"Larva";179;2
"Unit";"Hydralisk";"Larva";179;2
"Unit";"Hydralisk";"Larva";179;2
"Unit";"Hydralisk";"Larva";201;2
"Unit";"Hydralisk";"Larva";201;2
"Unit";"Hydralisk";"Larva";201;2
"Unit";"Hydralisk";"Larva";201;2
"Unit";"Hydralisk";"Larva";201;2
"Unit";"Hydralisk";"Larva";201;2
"Unit";"Hydralisk";"Larva";201;2
"Unit";"Hydralisk";"Larva";201;2
"Unit";"Hydralisk";"Larva";201;2
"Unit";"Hydralisk";"Larva";201;2
"Unit";"Hydralisk";"Larva";201;2
"Unit";"Hydralisk";"Larva";201;2
"Unit";"Hydralisk";"Larva";201;2
"Unit";"Hydralisk";"Larva";201;2
"Unit";"Hydralisk";"Larva";201;2
"Building";"Hatchery";NA;187;0
"Unit";"Hydralisk";"Larva";231;2
"Unit";"Hydralisk";"Larva";231;2
"Unit";"Hydralisk";"Larva";231;2
"Unit";"Hydralisk";"Larva";231;2
"Unit";"Hydralisk";"Larva";231;2
"Unit";"Hydralisk";"Larva";231;2
"Unit";"Hydralisk";"Larva";231;2
"Unit";"Hydralisk";"Larva";231;2
"Building";"Extractor";NA;231;0
"Building";"Extractor";NA;231;0
"Unit";"Zergling";"Larva";231;1
"Unit";"Zergling";"Larva";231;1
"Unit";"Zergling";"Larva";231;1
"Unit";"Zergling";"Larva";231;1
"Unit";"Zergling";"Larva";231;1
"Unit";"Zergling";"Larva";231;1
"Unit";"Zergling";"Larva";231;1
"Unit";"Zergling";"Larva";231;1
"Unit";"Zergling";"Larva";231;1
"Unit";"Zergling";"Larva";231;1
"Unit";"Zergling";"Larva";231;1
"Unit";"Zergling";"Larva";231;1
"Unit";"Zergling";"Larva";231;1
"Unit";"Zergling";"Larva";231;1
"Unit";"Zergling";"Larva";231;1
"Unit";"Zergling";"Larva";231;1
"Unit";"Zergling";"Larva";231;1
"Unit";"Zergling";"Larva";231;1
"Unit";"Zergling";"Larva";231;1
"Unit";"Zergling";"Larva";231;1
"Unit";"Zergling";"Larva";231;1
"Unit";"Zergling";"Larva";231;1
"Unit";"Zergling";"Larva";231;1
"Unit";"Zergling";"Larva";231;1
"Unit";"Zergling";"Larva";231;1
"Unit";"Zergling";"Larva";231;1
"Unit";"Zergling";"Larva";231;1
"Unit";"Zergling";"Larva";231;1
"Building";"CreepTumor";NA;281;0
"Unit";"Hydralisk";"Larva";253;2
"Unit";"Hydralisk";"Larva";253;2
"Unit";"Hydralisk";"Larva";253;2
"Upgrade";"ZergMissileWeaponsLevel2";"EvolutionChamber";201;0
"Unit";"Viper";"Larva";281;3
"Building";"SporeCrawler";NA;287;0
"Building";"SpineCrawler";NA;287;0
"Unit";"Hydralisk";"Larva";295;2
"Unit";"Hydralisk";"Larva";295;2
"Unit";"Hydralisk";"Larva";295;2
"Unit";"Hydralisk";"Larva";295;2
"Unit";"Hydralisk";"Larva";295;2
"Unit";"Hydralisk";"Larva";295;2
"Unit";"Hydralisk";"Larva";295;2
"Unit";"Hydralisk";"Larva";295;2
"Unit";"Hydralisk";"Larva";295;2
"Unit";"Hydralisk";"Larva";295;2
"Unit";"Hydralisk";"Larva";295;2
"Unit";"Hydralisk";"Larva";295;2
"Unit";"Hydralisk";"Larva";295;2
"Unit";"Hydralisk";"Larva";295;2
"Unit";"Hydralisk";"Larva";295;2
"Unit";"Hydralisk";"Larva";295;2
"Unit";"Hydralisk";"Larva";295;2
"Unit";"Hydralisk";"Larva";295;2
"Unit";"Hydralisk";"Larva";295;2
"Unit";"Hydralisk";"Larva";295;2
"Unit";"Hydralisk";"Larva";295;2
"Unit";"Hydralisk";"Larva";295;2
"Unit";"Hydralisk";"Larva";295;2
"Unit";"Hydralisk";"Larva";295;2
"Unit";"Hydralisk";"Larva";295;2
"Unit";"Hydralisk";"Larva";295;2
"Unit";"Hydralisk";"Larva";295;2
"Unit";"Hydralisk";"Larva";295;2
"Building";"Hatchery";NA;292;0
"Unit";"Zergling";"Larva";351;1
"Unit";"Zergling";"Larva";351;1
"Unit";"Zergling";"Larva";351;1
"Unit";"Zergling";"Larva";351;1
"Unit";"Zergling";"Larva";351;1
"Unit";"Zergling";"Larva";351;1
"Unit";"Zergling";"Larva";351;1
"Unit";"Zergling";"Larva";351;1
"Unit";"Zergling";"Larva";351;1
"Unit";"Zergling";"Larva";351;1
"Unit";"Zergling";"Larva";351;1
"Unit";"Zergling";"Larva";351;1
"Unit";"Zergling";"Larva";351;1
"Unit";"Zergling";"Larva";351;1
"Unit";"Zergling";"Larva";351;1
"Unit";"Zergling";"Larva";351;1
"Unit";"Zergling";"Larva";351;1
"Unit";"Zergling";"Larva";351;1
"Unit";"Zergling";"Larva";351;1
"Unit";"Zergling";"Larva";351;1
"Unit";"Zergling";"Larva";351;1
"Unit";"Zergling";"Larva";351;1
"Unit";"Zergling";"Larva";351;1
"Unit";"Zergling";"Larva";351;1
"Unit";"Zergling";"Larva";351;1
"Unit";"Zergling";"Larva";351;1
"Unit";"Zergling";"Larva";351;1
"Unit";"Zergling";"Larva";351;1
"Unit";"Zergling";"Larva";351;1
"Unit";"Zergling";"Larva";351;1
"Building";"CreepTumor";NA;351;0
"Building";"Extractor";NA;390;0
"Building";"Extractor";NA;390;0
"Unit";"Zergling";"Larva";390;1
"Unit";"Zergling";"Larva";390;1
"Unit";"Zergling";"Larva";390;1
"Unit";"Zergling";"Larva";390;1
"Unit";"Zergling";"Larva";390;1
"Unit";"Zergling";"Larva";390;1
"Building";"CreepTumor";NA;390;0
"Unit";"Baneling";"Zergling";390;0
"Unit";"Baneling";"Zergling";390;0
"Unit";"Baneling";"Zergling";390;0
"Unit";"Baneling";"Zergling";390;0
"Building";"CreepTumor";NA;390;0
"Unit";"Hydralisk";"Larva";390;2
"Unit";"Hydralisk";"Larva";390;2
"Building";"SporeCrawler";NA;390;0
"Building";"SpineCrawler";NA;390;0
"Building";"SpineCrawler";NA;390;0
"Building";"SpineCrawler";NA;390;0
"Building";"SpineCrawler";NA;404;0
"Building";"SpineCrawler";NA;404;0
"Unit";"Hydralisk";"Larva";404;2
"Unit";"Hydralisk";"Larva";404;2
"Unit";"Hydralisk";"Larva";404;2
"Unit";"Hydralisk";"Larva";404;2
"Unit";"Hydralisk";"Larva";404;2
"Unit";"Hydralisk";"Larva";404;2
"Unit";"Hydralisk";"Larva";404;2
"Unit";"Hydralisk";"Larva";404;2
"Unit";"Hydralisk";"Larva";404;2
"Unit";"Hydralisk";"Larva";404;2
"Unit";"Hydralisk";"Larva";404;2
"Unit";"Hydralisk";"Larva";404;2
"Unit";"Hydralisk";"Larva";404;2
"Building";"Spire";NA;400;0
"Building";"Spire";NA;400;0
"Building";"CreepTumor";NA;430;0
"Building";"CreepTumor";NA;430;0
"Unit";"Hydralisk";"Larva";430;2
"Unit";"Hydralisk";"Larva";430;2
"Unit";"Hydralisk";"Larva";430;2
"Unit";"Hydralisk";"Larva";430;2
"Unit";"Hydralisk";"Larva";430;2
"Unit";"Hydralisk";"Larva";430;2
"Unit";"Hydralisk";"Larva";430;2
"Unit";"Hydralisk";"Larva";430;2
"Unit";"Hydralisk";"Larva";430;2
"Unit";"Hydralisk";"Larva";430;2
"Unit";"Hydralisk";"Larva";430;2
"Unit";"Hydralisk";"Larva";430;2
"Unit";"Hydralisk";"Larva";430;2
"Unit";"Hydralisk";"Larva";430;2
"Unit";"Hydralisk";"Larva";430;2
"Unit";"Hydralisk";"Larva";430;2
"Unit";"Hydralisk";"Larva";430;2
"Unit";"Hydralisk";"Larva";430;2
"Unit";"Hydralisk";"Larva";430;2
"Unit";"Hydralisk";"Larva";430;2
"Unit";"Hydralisk";"Larva";430;2
"Unit";"Hydralisk";"Larva";430;2
"Unit";"Hydralisk";"Larva";430;2
"Unit";"Hydralisk";"Larva";430;2
"Unit";"Overlord";"Larva";430;0
"Unit";"Overlord";"Larva";430;0
"Upgrade";"ZergMissileWeaponsLevel3";"EvolutionChamber";396;0
"Unit";"Overlord";"Larva";478;0
"Unit";"Overlord";"Larva";478;0
"Unit";"Overlord";"Larva";478;0
"Unit";"Overlord";"Larva";478;0
"Unit";"Overlord";"Larva";478;0
"Unit";"Overlord";"Larva";478;0
"Unit";"Overlord";"Larva";478;0
"Unit";"Overlord";"Larva";478;0
"Unit";"Overlord";"Larva";478;0
"Unit";"Hydralisk";"Larva";478;2
"Unit";"Hydralisk";"Larva";478;2
"Unit";"Hydralisk";"Larva";478;2
"Unit";"Hydralisk";"Larva";478;2
"Unit";"Hydralisk";"Larva";478;2
"Unit";"Hydralisk";"Larva";478;2
"Unit";"Hydralisk";"Larva";478;2
"Unit";"Hydralisk";"Larva";478;2
"Unit";"Hydralisk";"Larva";478;2
"Unit";"Hydralisk";"Larva";478;2
"Unit";"Hydralisk";"Larva";478;2
"Unit";"Hydralisk";"Larva";478;2
"Unit";"Hydralisk";"Larva";478;2
"Unit";"Hydralisk";"Larva";478;2
"Unit";"Hydralisk";"Larva";478;2
"Unit";"Hydralisk";"Larva";478;2
"Unit";"Hydralisk";"Larva";478;2
"Unit";"Hydralisk";"Larva";478;2
"Unit";"Hydralisk";"Larva";478;2
"Unit";"Hydralisk";"Larva";478;2
"Unit";"Hydralisk";"Larva";478;2
"Unit";"Hydralisk";"Larva";478;2
"Unit";"Hydralisk";"Larva";478;2
"Building";"Extractor";NA;524;0
"Building";"Extractor";NA;524;0
"Upgrade";"ZergMeleeWeaponsLevel1";"EvolutionChamber";478;0
"Unit";"Hydralisk";"Larva";524;2
"Unit";"Hydralisk";"Larva";524;2
"Unit";"Hydralisk";"Larva";524;2
"Unit";"Hydralisk";"Larva";524;2
"Unit";"Hydralisk";"Larva";524;2
"Unit";"Hydralisk";"Larva";524;2
"Unit";"Hydralisk";"Larva";524;2
"Unit";"Hydralisk";"Larva";524;2
"Unit";"Hydralisk";"Larva";524;2
"Unit";"Hydralisk";"Larva";524;2
"Unit";"Hydralisk";"Larva";524;2
"Building";"Hatchery";NA;478;0
"Unit";"Corruptor";"Larva";524;2
"Unit";"Corruptor";"Larva";524;2
"Unit";"Corruptor";"Larva";524;2
"Unit";"Corruptor";"Larva";524;2
"Unit";"Corruptor";"Larva";524;2
"Unit";"Corruptor";"Larva";524;2
"Unit";"Corruptor";"Larva";524;2
"Unit";"Corruptor";"Larva";524;2
"Unit";"Corruptor";"Larva";524;2
"Unit";"Corruptor";"Larva";524;2
"Unit";"Corruptor";"Larva";524;2
"Unit";"Corruptor";"Larva";524;2
"Unit";"Corruptor";"Larva";526;2
"Unit";"Corruptor";"Larva";526;2
"Unit";"Corruptor";"Larva";526;2
"Building";"CreepTumor";NA;582;0
"Building";"CreepTumorQueen";NA;582;0
"Building";"CreepTumorQueen";NA;582;0
"Building";"CreepTumorQueen";NA;582;0
"Building";"CreepTumorQueen";NA;582;0
"Building";"SporeCrawler";NA;582;0
"Building";"CreepTumorQueen";NA;582;0
"Building";"CreepTumor";NA;582;0
"Building";"SporeCrawler";NA;582;0
"Building";"SpineCrawler";NA;582;0
"Building";"SpineCrawler";NA;582;0
"Building";"SpineCrawler";NA;582;0
"Unit";"Viper";"Larva";582;3
"Unit";"Viper";"Larva";582;3
"Unit";"Viper";"Larva";582;3
"Building";"SpineCrawler";NA;582;0
"Building";"SpineCrawler";NA;582;0
"Building";"SpineCrawler";NA;582;0
"Building";"SpineCrawler";NA;582;0
"Unit";"Hydralisk";"Larva";591;2
"Unit";"Hydralisk";"Larva";591;2
"Unit";"Hydralisk";"Larva";591;2
"Unit";"Hydralisk";"Larva";591;2
"Unit";"Hydralisk";"Larva";591;2
"Building";"Hatchery";NA;582;0
"Upgrade";"ZergMeleeWeaponsLevel2";"EvolutionChamber";582;0
"Unit";"Hydralisk";"Larva";601;2
"Unit";"Hydralisk";"Larva";601;2
"Unit";"Hydralisk";"Larva";601;2
"Unit";"Hydralisk";"Larva";601;2
"Unit";"Hydralisk";"Larva";601;2
"Unit";"Hydralisk";"Larva";601;2
"Unit";"Hydralisk";"Larva";601;2
"Unit";"Hydralisk";"Larva";601;2
"Unit";"Hydralisk";"Larva";601;2
"Unit";"Hydralisk";"Larva";601;2
"Unit";"Hydralisk";"Larva";601;2
"Unit";"Hydralisk";"Larva";601;2
"Unit";"Hydralisk";"Larva";601;2
"Unit";"Hydralisk";"Larva";601;2
"Unit";"Hydralisk";"Larva";601;2
"Unit";"Hydralisk";"Larva";601;2
"Unit";"Hydralisk";"Larva";601;2
"Unit";"Hydralisk";"Larva";601;2
"Unit";"Hydralisk";"Larva";601;2
"Unit";"Hydralisk";"Larva";601;2
"Unit";"Hydralisk";"Larva";601;2
"Unit";"Hydralisk";"Larva";601;2
"Unit";"Hydralisk";"Larva";601;2
"Unit";"Hydralisk";"Larva";601;2
"Unit";"Hydralisk";"Larva";601;2
"Unit";"Hydralisk";"Larva";601;2
"Unit";"Hydralisk";"Larva";601;2
"Unit";"Hydralisk";"Larva";601;2
"Unit";"Hydralisk";"Larva";601;2
"Unit";"Hydralisk";"Larva";601;2
"Unit";"Hydralisk";"Larva";601;2
"Building";"CreepTumor";NA;601;0
"Building";"CreepTumor";NA;601;0
"Building";"CreepTumor";NA;601;0
"Building";"CreepTumor";NA;601;0
"Building";"CreepTumor";NA;601;0
"Unit";"Corruptor";"Larva";601;2
"Unit";"Corruptor";"Larva";601;2
"Unit";"Corruptor";"Larva";601;2
"Unit";"Corruptor";"Larva";601;2
"Unit";"Corruptor";"Larva";601;2
"Unit";"Corruptor";"Larva";601;2
"Unit";"Corruptor";"Larva";663;2
"Building";"CreepTumor";NA;677;0
"Building";"CreepTumor";NA;677;0
"Building";"CreepTumor";NA;677;0
"Building";"CreepTumor";NA;677;0
"Building";"CreepTumor";NA;677;0
"Building";"CreepTumor";NA;677;0
"Building";"CreepTumor";NA;677;0
"Unit";"Hydralisk";"Larva";677;2
"Unit";"Hydralisk";"Larva";677;2
"Unit";"Hydralisk";"Larva";677;2
"Building";"SporeCrawler";NA;683;0
"Building";"SporeCrawler";NA;683;0
"Building";"SporeCrawler";NA;683;0
"Building";"SpineCrawler";NA;683;0
"Building";"SpineCrawler";NA;683;0
"Building";"SpineCrawler";NA;683;0
