"type";"unit_name";"on_building";"total_supply";"supply"
"Unit";"Overlord";"Larva";13;0
"Building";"Extractor";NA;18;0
"Building";"SpawningPool";NA;19;0
"Building";"Hatchery";NA;17;0
"Unit";"Overlord";"Larva";25;0
"Unit";"Queen";"Hatchery";24;2
"Building";"Hatchery";NA;22;0
"Unit";"Zergling";"Larva";30;1
"Unit";"Zergling";"Larva";30;1
"Unit";"Zergling";"Larva";30;1
"Unit";"Zergling";"Larva";30;1
"Unit";"Overlord";"Larva";30;0
"Unit";"Queen";"Hatchery";27;2
"Building";"CreepTumorQueen";NA;41;0
"Unit";"Zergling";"Larva";40;1
"Unit";"Zergling";"Larva";40;1
"Unit";"Queen";"Hatchery";30;2
"Unit";"Zergling";"Larva";41;1
"Unit";"Zergling";"Larva";41;1
"Unit";"Overlord";"Larva";42;0
"Unit";"Overlord";"Larva";42;0
"Building";"CreepTumor";NA;51;0
"Unit";"Overlord";"Larva";53;0
"Unit";"Overlord";"Larva";53;0
"Unit";"Queen";"Hatchery";51;2
"Unit";"Overlord";"Larva";57;0
"Building";"CreepTumor";NA;57;0
"Building";"Extractor";NA;57;0
"Building";"Extractor";NA;57;0
"Building";"Extractor";NA;57;0
"Building";"CreepTumorQueen";NA;63;0
"Building";"SporeCrawler";NA;66;0
"Unit";"Overlord";"Larva";73;0
"Building";"CreepTumor";NA;79;0
"Unit";"Overlord";"Larva";74;0
"Building";"CreepTumor";NA;79;0
"Building";"CreepTumorQueen";NA;79;0
"Building";"HydraliskDen";NA;79;0
"Building";"SporeCrawler";NA;79;0
"Unit";"Overlord";"Larva";81;0
"Unit";"Overlord";"Larva";81;0
"Unit";"Zergling";"Larva";81;1
"Unit";"Zergling";"Larva";81;1
"Unit";"Zergling";"Larva";81;1
"Unit";"Zergling";"Larva";81;1
"Unit";"Zergling";"Larva";81;1
"Unit";"Zergling";"Larva";81;1
"Unit";"Zergling";"Larva";81;1
"Unit";"Zergling";"Larva";81;1
"Building";"CreepTumor";NA;81;0
"Unit";"Overlord";"Larva";81;0
"Building";"CreepTumor";NA;89;0
"Unit";"Hydralisk";"Larva";81;2
"Unit";"Hydralisk";"Larva";81;2
"Unit";"Hydralisk";"Larva";81;2
"Unit";"Hydralisk";"Larva";81;2
"Unit";"Hydralisk";"Larva";81;2
"Unit";"Hydralisk";"Larva";81;2
"Unit";"Hydralisk";"Larva";81;2
"Unit";"Hydralisk";"Larva";81;2
"Building";"CreepTumor";NA;89;0
"Unit";"Hydralisk";"Larva";89;2
"Unit";"Hydralisk";"Larva";89;2
"Unit";"Hydralisk";"Larva";89;2
"Building";"CreepTumor";NA;89;0
"Unit";"Overlord";"Larva";89;0
"Unit";"Hydralisk";"Larva";89;2
"Unit";"Hydralisk";"Larva";89;2
"Unit";"Hydralisk";"Larva";89;2
"Unit";"Zergling";"Larva";105;1
"Unit";"Zergling";"Larva";105;1
"Unit";"Zergling";"Larva";105;1
"Unit";"Zergling";"Larva";105;1
"Unit";"Zergling";"Larva";105;1
"Unit";"Zergling";"Larva";105;1
"Unit";"Zergling";"Larva";105;1
"Unit";"Zergling";"Larva";105;1
"Unit";"Zergling";"Larva";105;1
"Unit";"Zergling";"Larva";105;1
"Building";"CreepTumorQueen";NA;111;0
"Unit";"Hydralisk";"Larva";105;2
"Unit";"Hydralisk";"Larva";111;2
"Unit";"Hydralisk";"Larva";111;2
"Unit";"Zergling";"Larva";127;1
"Unit";"Zergling";"Larva";127;1
"Unit";"Zergling";"Larva";127;1
"Unit";"Zergling";"Larva";127;1
"Unit";"Zergling";"Larva";127;1
"Unit";"Zergling";"Larva";127;1
"Unit";"Zergling";"Larva";127;1
"Unit";"Zergling";"Larva";127;1
"Unit";"Zergling";"Larva";127;1
"Unit";"Zergling";"Larva";127;1
"Unit";"Zergling";"Larva";127;1
"Unit";"Zergling";"Larva";127;1
"Building";"CreepTumor";NA;129;0
"Building";"CreepTumor";NA;129;0
"Unit";"Hydralisk";"Larva";115;2
"Unit";"Hydralisk";"Larva";115;2
"Upgrade";"EvolveMuscularAugments";"HydraliskDen";89;0
"Building";"CreepTumor";NA;133;0
"Unit";"Zergling";"Larva";129;1
"Unit";"Zergling";"Larva";129;1
"Unit";"Zergling";"Larva";131;1
"Unit";"Zergling";"Larva";131;1
"Unit";"Zergling";"Larva";131;1
"Unit";"Zergling";"Larva";131;1
"Unit";"Zergling";"Larva";131;1
"Unit";"Zergling";"Larva";131;1
"Unit";"Zergling";"Larva";133;1
"Unit";"Zergling";"Larva";133;1
"Unit";"Hydralisk";"Larva";129;2
"Unit";"Hydralisk";"Larva";129;2
"Unit";"Hydralisk";"Larva";145;2
"Unit";"Hydralisk";"Larva";149;2
"Building";"CreepTumor";NA;163;0
"Unit";"Overlord";"Larva";163;0
"Unit";"Overlord";"Larva";163;0
"Unit";"Overlord";"Larva";163;0
"Unit";"Overlord";"Larva";163;0
"Unit";"Zergling";"Larva";163;1
"Unit";"Zergling";"Larva";163;1
"Unit";"Zergling";"Larva";163;1
"Unit";"Zergling";"Larva";163;1
"Building";"CreepTumor";NA;167;0
"Building";"CreepTumor";NA;167;0
"Unit";"Zergling";"Larva";167;1
"Unit";"Zergling";"Larva";167;1
"Unit";"Zergling";"Larva";169;1
"Unit";"Zergling";"Larva";169;1
"Unit";"Zergling";"Larva";169;1
"Unit";"Zergling";"Larva";169;1
"Unit";"Zergling";"Larva";169;1
"Unit";"Zergling";"Larva";169;1
"Unit";"Zergling";"Larva";169;1
"Unit";"Zergling";"Larva";169;1
"Unit";"Zergling";"Larva";169;1
"Unit";"Zergling";"Larva";169;1
"Unit";"Hydralisk";"Larva";167;2
"Unit";"Hydralisk";"Larva";167;2
"Unit";"Hydralisk";"Larva";167;2
"Unit";"Zergling";"Larva";171;1
"Unit";"Zergling";"Larva";171;1
"Unit";"Zergling";"Larva";171;1
"Unit";"Zergling";"Larva";171;1
"Unit";"Zergling";"Larva";171;1
"Unit";"Zergling";"Larva";171;1
"Unit";"Zergling";"Larva";171;1
"Unit";"Zergling";"Larva";171;1
"Unit";"Zergling";"Larva";171;1
"Unit";"Zergling";"Larva";171;1
"Unit";"Zergling";"Larva";171;1
"Unit";"Zergling";"Larva";171;1
"Unit";"Hydralisk";"Larva";171;2
"Unit";"Hydralisk";"Larva";171;2
"Unit";"Zergling";"Larva";183;1
"Unit";"Zergling";"Larva";183;1
"Unit";"Zergling";"Larva";183;1
"Unit";"Zergling";"Larva";183;1
"Unit";"Zergling";"Larva";183;1
"Unit";"Zergling";"Larva";183;1
"Unit";"Hydralisk";"Larva";171;2
"Unit";"Hydralisk";"Larva";171;2
"Unit";"Hydralisk";"Larva";201;2
"Unit";"Hydralisk";"Larva";201;2
"Upgrade";"EvolveGroovedSpines";"HydraliskDen";171;0
"Unit";"Zergling";"Larva";215;1
"Unit";"Zergling";"Larva";215;1
"Unit";"Hydralisk";"Larva";215;2
"Unit";"Hydralisk";"Larva";215;2
"Unit";"Hydralisk";"Larva";215;2
"Unit";"Hydralisk";"Larva";215;2
"Unit";"Overlord";"Larva";215;0
"Unit";"Overlord";"Larva";215;0
"Unit";"Overlord";"Larva";215;0
"Unit";"Zergling";"Larva";229;1
"Unit";"Zergling";"Larva";229;1
"Unit";"Zergling";"Larva";229;1
"Unit";"Zergling";"Larva";229;1
"Unit";"Zergling";"Larva";229;1
"Unit";"Zergling";"Larva";229;1
"Unit";"Hydralisk";"Larva";221;2
"Unit";"Hydralisk";"Larva";221;2
"Unit";"Hydralisk";"Larva";221;2
"Unit";"Hydralisk";"Larva";221;2
"Unit";"Hydralisk";"Larva";221;2
"Unit";"Zergling";"Larva";231;1
"Unit";"Zergling";"Larva";231;1
"Unit";"Zergling";"Larva";235;1
"Unit";"Zergling";"Larva";235;1
"Unit";"Zergling";"Larva";235;1
"Unit";"Zergling";"Larva";235;1
"Unit";"Zergling";"Larva";235;1
"Unit";"Zergling";"Larva";235;1
"Unit";"Zergling";"Larva";235;1
"Unit";"Zergling";"Larva";235;1
"Unit";"Zergling";"Larva";235;1
"Unit";"Zergling";"Larva";235;1
"Unit";"Zergling";"Larva";235;1
"Unit";"Zergling";"Larva";235;1
"Unit";"Hydralisk";"Larva";229;2
"Unit";"Hydralisk";"Larva";229;2
"Unit";"Hydralisk";"Larva";229;2
"Unit";"Hydralisk";"Larva";229;2
