"type";"unit_name";"on_building";"total_supply";"supply"
"Unit";"Overlord";"Larva";12;0
"Building";"SpawningPool";NA;19;0
"Building";"Hatchery";NA;17;0
"Unit";"Overlord";"Larva";20;0
"Unit";"Zergling";"Larva";23;1
"Unit";"Zergling";"Larva";23;1
"Unit";"Zergling";"Larva";23;1
"Unit";"Zergling";"Larva";23;1
"Unit";"Queen";"Hatchery";22;2
"Building";"Hatchery";NA;20;0
"Unit";"Queen";"Hatchery";23;2
"Unit";"Zergling";"Larva";30;1
"Unit";"Zergling";"Larva";30;1
"Unit";"Queen";"Hatchery";33;2
"Unit";"Overlord";"Larva";38;0
"Unit";"Queen";"Hatchery";36;2
"Building";"Extractor";NA;40;0
"Building";"Extractor";NA;40;0
"Unit";"Overlord";"Larva";50;0
"Building";"CreepTumorQueen";NA;58;0
"Unit";"Overlord";"Larva";58;0
"Unit";"Queen";"Hatchery";50;2
"Building";"RoachWarren";NA;58;0
"Building";"CreepTumorQueen";NA;65;0
"Building";"CreepTumor";NA;65;0
"Building";"Extractor";NA;59;0
"Building";"CreepTumorQueen";NA;67;0
"Unit";"Overlord";"Larva";70;0
"Unit";"Overlord";"Larva";72;0
"Unit";"Roach";"Larva";72;2
"Unit";"Roach";"Larva";72;2
"Building";"CreepTumorQueen";NA;72;0
"Building";"SporeCrawler";NA;72;0
"Building";"SporeCrawler";NA;72;0
"Building";"SporeCrawler";NA;72;0
"Building";"CreepTumor";NA;72;0
"Unit";"Queen";"Hatchery";72;2
"Unit";"Roach";"Larva";76;2
"Unit";"Roach";"Larva";76;2
"Unit";"Roach";"Larva";76;2
"Unit";"Roach";"Larva";76;2
"Unit";"Roach";"Larva";76;2
"Unit";"Roach";"Larva";76;2
"Unit";"Roach";"Larva";76;2
"Building";"CreepTumorQueen";NA;76;0
"Unit";"Overlord";"Larva";76;0
"Building";"CreepTumor";NA;81;0
"Building";"CreepTumor";NA;81;0
"Unit";"Overlord";"Larva";95;0
"Building";"Extractor";NA;95;0
"Unit";"Overlord";"Larva";97;0
"Building";"CreepTumor";NA;100;0
"Unit";"Overlord";"Larva";100;0
"Building";"CreepTumor";NA;100;0
"Unit";"Roach";"Larva";100;2
"Building";"CreepTumor";NA;100;0
"Unit";"Roach";"Larva";100;2
"Unit";"Roach";"Larva";100;2
"Unit";"Roach";"Larva";100;2
"Unit";"Overlord";"Larva";105;0
"Unit";"Overlord";"Larva";105;0
"Unit";"Roach";"Larva";105;2
"Unit";"Roach";"Larva";105;2
"Unit";"Roach";"Larva";105;2
"Unit";"Roach";"Larva";105;2
"Unit";"Roach";"Larva";105;2
"Unit";"Roach";"Larva";105;2
"Unit";"Overlord";"Larva";113;0
"Unit";"Roach";"Larva";113;2
"Unit";"Roach";"Larva";113;2
"Unit";"Roach";"Larva";113;2
"Unit";"Roach";"Larva";113;2
"Building";"EvolutionChamber";NA;113;0
"Building";"CreepTumor";NA;133;0
"Unit";"Roach";"Larva";133;2
"Unit";"Roach";"Larva";133;2
"Unit";"Roach";"Larva";133;2
"Unit";"Roach";"Larva";133;2
"Unit";"Roach";"Larva";133;2
"Unit";"Roach";"Larva";133;2
"Unit";"Roach";"Larva";133;2
"Unit";"Roach";"Larva";133;2
"Unit";"Roach";"Larva";133;2
"Unit";"Roach";"Larva";133;2
"Unit";"Roach";"Larva";133;2
"Unit";"Roach";"Larva";133;2
"Unit";"Roach";"Larva";133;2
"Unit";"Roach";"Larva";133;2
"Unit";"Roach";"Larva";133;2
"Unit";"Overlord";"Larva";133;0
"Unit";"Overlord";"Larva";133;0
"Building";"CreepTumor";NA;161;0
"Upgrade";"GlialReconstitution";"RoachWarren";127;0
"Building";"SpineCrawler";NA;133;0
"Building";"SpineCrawler";NA;133;0
"Unit";"Overlord";"Larva";161;0
"Unit";"Overlord";"Larva";161;0
"Unit";"Roach";"Larva";163;2
"Unit";"Roach";"Larva";163;2
"Unit";"Roach";"Larva";163;2
"Unit";"Roach";"Larva";163;2
"Unit";"Roach";"Larva";163;2
"Unit";"Roach";"Larva";163;2
"Unit";"Roach";"Larva";163;2
"Unit";"Roach";"Larva";163;2
"Unit";"Overlord";"Larva";163;0
"Building";"Extractor";NA;179;0
"Building";"Extractor";NA;179;0
"Building";"CreepTumor";NA;185;0
"Building";"CreepTumor";NA;185;0
"Building";"CreepTumorQueen";NA;185;0
"Building";"CreepTumorQueen";NA;187;0
"Building";"CreepTumorQueen";NA;188;0
"Building";"CreepTumor";NA;189;0
"Upgrade";"ZergMissileWeaponsLevel1";"EvolutionChamber";161;0
"Building";"HydraliskDen";NA;187;0
"Unit";"Overlord";"Larva";188;0
"Building";"SporeCrawler";NA;196;0
"Building";"CreepTumor";NA;196;0
"Building";"CreepTumor";NA;196;0
"Building";"CreepTumor";NA;196;0
"Building";"CreepTumor";NA;196;0
"Building";"CreepTumor";NA;196;0
"Building";"Hatchery";NA;185;0
"Unit";"Overlord";"Larva";196;0
"Unit";"Overlord";"Larva";196;0
"Unit";"Zergling";"Larva";197;1
"Unit";"Zergling";"Larva";197;1
"Unit";"Zergling";"Larva";197;1
"Unit";"Zergling";"Larva";197;1
"Building";"CreepTumorQueen";NA;201;0
"Unit";"Hydralisk";"Larva";197;2
"Unit";"Hydralisk";"Larva";197;2
"Unit";"Hydralisk";"Larva";197;2
"Unit";"Hydralisk";"Larva";197;2
"Unit";"Hydralisk";"Larva";197;2
"Unit";"Hydralisk";"Larva";197;2
"Unit";"Hydralisk";"Larva";197;2
"Unit";"Hydralisk";"Larva";197;2
"Unit";"Hydralisk";"Larva";197;2
"Unit";"Hydralisk";"Larva";197;2
"Unit";"Hydralisk";"Larva";197;2
"Unit";"Hydralisk";"Larva";197;2
"Unit";"Hydralisk";"Larva";197;2
"Building";"CreepTumor";NA;203;0
"Building";"CreepTumor";NA;227;0
"Building";"CreepTumor";NA;227;0
"Building";"CreepTumor";NA;227;0
"Unit";"Queen";"Hatchery";197;2
"Upgrade";"EvolveMuscularAugments";"HydraliskDen";197;0
"Building";"LurkerDenMP";NA;196;0
"Building";"Hatchery";NA;197;0
"Unit";"Hydralisk";"Larva";229;2
"Unit";"Hydralisk";"Larva";229;2
"Unit";"Hydralisk";"Larva";229;2
"Unit";"Hydralisk";"Larva";229;2
"Unit";"Hydralisk";"Larva";229;2
"Unit";"Hydralisk";"Larva";229;2
"Unit";"Hydralisk";"Larva";229;2
"Unit";"Hydralisk";"Larva";229;2
"Unit";"Hydralisk";"Larva";229;2
"Building";"CreepTumorQueen";NA;247;0
"Building";"CreepTumor";NA;247;0
"Building";"CreepTumorQueen";NA;247;0
"Building";"CreepTumor";NA;247;0
"Building";"CreepTumor";NA;247;0
"Building";"CreepTumor";NA;247;0
"Building";"CreepTumor";NA;247;0
"Upgrade";"ZergMissileWeaponsLevel2";"EvolutionChamber";201;0
"Upgrade";"EvolveGroovedSpines";"HydraliskDen";229;0
"Building";"SpineCrawler";NA;247;0
"Building";"SpineCrawler";NA;247;0
"Building";"SpineCrawler";NA;247;0
"Building";"InfestationPit";NA;247;0
"Unit";"Zergling";"Larva";247;1
"Unit";"Zergling";"Larva";247;1
"Unit";"Roach";"Larva";247;2
"Unit";"Roach";"Larva";247;2
"Unit";"Roach";"Larva";247;2
"Unit";"Roach";"Larva";247;2
"Unit";"Roach";"Larva";247;2
"Unit";"Roach";"Larva";247;2
"Unit";"Roach";"Larva";247;2
"Unit";"Roach";"Larva";247;2
"Unit";"Roach";"Larva";247;2
"Unit";"Roach";"Larva";247;2
"Unit";"Overlord";"Larva";251;0
"Unit";"Overlord";"Larva";251;0
"Unit";"Overlord";"Larva";251;0
"Unit";"Overlord";"Larva";251;0
"Unit";"Overlord";"Larva";251;0
"Building";"Extractor";NA;251;0
"Building";"Extractor";NA;269;0
"Unit";"Overlord";"Larva";269;0
"Unit";"Roach";"Larva";269;2
"Unit";"Roach";"Larva";269;2
"Unit";"Roach";"Larva";269;2
"Unit";"Roach";"Larva";269;2
"Unit";"Roach";"Larva";269;2
"Unit";"Roach";"Larva";269;2
"Building";"Extractor";NA;269;0
"Upgrade";"ZergGroundArmorsLevel1";"EvolutionChamber";247;0
"Building";"CreepTumor";NA;282;0
"Building";"CreepTumorQueen";NA;282;0
"Building";"CreepTumorQueen";NA;282;0
"Building";"CreepTumorQueen";NA;282;0
"Building";"Spire";NA;269;0
"Building";"Spire";NA;269;0
"Unit";"Overlord";"Larva";282;0
"Unit";"Overlord";"Larva";282;0
"Unit";"Hydralisk";"Larva";282;2
"Unit";"Hydralisk";"Larva";282;2
"Building";"Hatchery";NA;282;0
"Building";"CreepTumor";NA;286;0
"Unit";"Corruptor";"Larva";286;2
"Unit";"Corruptor";"Larva";286;2
"Unit";"Corruptor";"Larva";286;2
"Unit";"Corruptor";"Larva";286;2
"Unit";"Corruptor";"Larva";286;2
"Unit";"Corruptor";"Larva";286;2
"Unit";"Corruptor";"Larva";286;2
"Unit";"Corruptor";"Larva";286;2
"Unit";"Corruptor";"Larva";286;2
"Unit";"Corruptor";"Larva";286;2
"Unit";"Corruptor";"Larva";286;2
"Unit";"Corruptor";"Larva";286;2
"Unit";"Corruptor";"Larva";286;2
"Unit";"Corruptor";"Larva";286;2
"Building";"Extractor";NA;286;0
"Building";"Extractor";NA;286;0
"Building";"CreepTumorQueen";NA;286;0
"Building";"CreepTumorQueen";NA;286;0
"Building";"CreepTumor";NA;286;0
"Building";"SporeCrawler";NA;286;0
"Building";"SporeCrawler";NA;286;0
"Building";"SpineCrawler";NA;286;0
"Building";"SpineCrawler";NA;286;0
"Building";"CreepTumor";NA;314;0
"Building";"SpineCrawler";NA;286;0
"Building";"SpineCrawler";NA;286;0
"Building";"SpineCrawler";NA;294;0
"Building";"CreepTumor";NA;314;0
"Building";"SporeCrawler";NA;314;0
"Building";"SporeCrawler";NA;314;0
"Unit";"Corruptor";"Larva";314;2
"Unit";"Corruptor";"Larva";314;2
"Unit";"Corruptor";"Larva";314;2
"Unit";"Corruptor";"Larva";314;2
"Unit";"Corruptor";"Larva";314;2
"Building";"Hatchery";NA;314;0
"Building";"CreepTumorQueen";NA;324;0
"Building";"SporeCrawler";NA;314;0
"Unit";"Corruptor";"Larva";324;2
"Unit";"Corruptor";"Larva";324;2
"Unit";"Corruptor";"Larva";324;2
"Unit";"Corruptor";"Larva";324;2
"Unit";"Corruptor";"Larva";324;2
"Building";"SpineCrawler";NA;324;0
"Building";"SpineCrawler";NA;324;0
"Building";"SpineCrawler";NA;324;0
"Unit";"Corruptor";"Larva";334;2
"Unit";"Corruptor";"Larva";334;2
"Unit";"Corruptor";"Larva";334;2
"Unit";"Corruptor";"Larva";334;2
"Unit";"Corruptor";"Larva";334;2
"Unit";"Corruptor";"Larva";344;2
"Unit";"Corruptor";"Larva";344;2
"Unit";"Corruptor";"Larva";344;2
"Unit";"Corruptor";"Larva";344;2
"Unit";"Corruptor";"Larva";344;2
"Unit";"Corruptor";"Larva";344;2
"Unit";"Corruptor";"Larva";344;2
"Unit";"Corruptor";"Larva";344;2
"Unit";"Roach";"Larva";360;2
"Unit";"Roach";"Larva";360;2
"Unit";"Roach";"Larva";360;2
"Unit";"Roach";"Larva";360;2
"Unit";"Roach";"Larva";360;2
"Unit";"Hydralisk";"Larva";360;2
"Unit";"Hydralisk";"Larva";360;2
"Unit";"Hydralisk";"Larva";360;2
"Unit";"Hydralisk";"Larva";360;2
"Unit";"Hydralisk";"Larva";360;2
"Unit";"Hydralisk";"Larva";360;2
"Unit";"Hydralisk";"Larva";360;2
"Unit";"Roach";"Larva";360;2
"Unit";"Roach";"Larva";360;2
"Unit";"Roach";"Larva";360;2
"Unit";"Roach";"Larva";360;2
"Unit";"Roach";"Larva";360;2
"Unit";"Roach";"Larva";360;2
"Unit";"Roach";"Larva";360;2
"Building";"CreepTumor";NA;398;0
