"type";"unit_name";"on_building";"total_supply";"supply"
"Unit";"Overlord";"Larva";13;0
"Building";"Extractor";NA;18;0
"Unit";"Overlord";"Larva";21;0
"Building";"SpawningPool";NA;19;0
"Building";"Hatchery";NA;17;0
"Unit";"Zergling";"Larva";22;1
"Unit";"Zergling";"Larva";22;1
"Unit";"Zergling";"Larva";22;1
"Unit";"Zergling";"Larva";22;1
"Unit";"Queen";"Hatchery";22;2
"Unit";"Queen";"Hatchery";22;2
"Unit";"Overlord";"Larva";36;0
"Building";"CreepTumorQueen";NA;37;0
"Unit";"Queen";"Hatchery";34;2
"Unit";"Zergling";"Larva";39;1
"Unit";"Zergling";"Larva";39;1
"Unit";"Zergling";"Larva";39;1
"Unit";"Zergling";"Larva";39;1
"Unit";"Zergling";"Larva";39;1
"Unit";"Zergling";"Larva";39;1
"Unit";"Overlord";"Larva";40;0
"Building";"Hatchery";NA;29;0
"Building";"SporeCrawler";NA;42;0
"Building";"CreepTumor";NA;53;0
"Building";"SporeCrawler";NA;51;0
"Building";"CreepTumorQueen";NA;53;0
"Unit";"Overlord";"Larva";53;0
"Unit";"Queen";"Hatchery";53;2
"Building";"Extractor";NA;61;0
"Building";"Extractor";NA;63;0
"Unit";"Overlord";"Larva";71;0
"Building";"CreepTumor";NA;78;0
"Building";"CreepTumorQueen";NA;78;0
"Building";"EvolutionChamber";NA;75;0
"Building";"SporeCrawler";NA;78;0
"Building";"Extractor";NA;78;0
"Unit";"Overlord";"Larva";81;0
"Building";"CreepTumor";NA;88;0
"Building";"CreepTumor";NA;90;0
"Building";"CreepTumorQueen";NA;92;0
"Building";"Extractor";NA;92;0
"Building";"Extractor";NA;92;0
"Building";"HydraliskDen";NA;88;0
"Unit";"Zergling";"Larva";96;1
"Unit";"Zergling";"Larva";96;1
"Unit";"Zergling";"Larva";96;1
"Unit";"Zergling";"Larva";96;1
"Building";"CreepTumor";NA;108;0
"Unit";"Overlord";"Larva";108;0
"Unit";"Overlord";"Larva";108;0
"Unit";"Overlord";"Larva";108;0
"Unit";"Overlord";"Larva";108;0
"Unit";"Hydralisk";"Larva";104;2
"Unit";"Hydralisk";"Larva";104;2
"Unit";"Overlord";"Larva";108;0
"Unit";"Overlord";"Larva";108;0
"Unit";"Hydralisk";"Larva";108;2
"Building";"NydusNetwork";NA;104;0
"Building";"CreepTumorQueen";NA;112;0
"Building";"CreepTumor";NA;112;0
"Unit";"Hydralisk";"Larva";112;2
"Unit";"Hydralisk";"Larva";112;2
"Unit";"Hydralisk";"Larva";112;2
"Unit";"Hydralisk";"Larva";112;2
"Unit";"Hydralisk";"Larva";112;2
"Unit";"Hydralisk";"Larva";112;2
"Unit";"Hydralisk";"Larva";112;2
"Unit";"Hydralisk";"Larva";112;2
"Unit";"Hydralisk";"Larva";112;2
"Unit";"Hydralisk";"Larva";112;2
"Building";"NydusCanal";NA;114;0
"Unit";"Hydralisk";"Larva";114;2
"Unit";"Hydralisk";"Larva";114;2
"Upgrade";"EvolveGroovedSpines";"HydraliskDen";108;0
"Unit";"Hydralisk";"Larva";116;2
"Unit";"Hydralisk";"Larva";116;2
"Unit";"Hydralisk";"Larva";116;2
"Unit";"Hydralisk";"Larva";120;2
"Unit";"Overlord";"Larva";134;0
"Unit";"Overlord";"Larva";136;0
"Upgrade";"ZergMissileWeaponsLevel1";"EvolutionChamber";104;0
"Unit";"Hydralisk";"Larva";138;2
"Unit";"Queen";"Hatchery";130;2
"Unit";"Queen";"Hatchery";130;2
"Unit";"Hydralisk";"Larva";138;2
"Unit";"Hydralisk";"Larva";138;2
"Unit";"Hydralisk";"Larva";138;2
"Unit";"Hydralisk";"Larva";138;2
"Unit";"Hydralisk";"Larva";146;2
"Unit";"Hydralisk";"Larva";146;2
"Unit";"Hydralisk";"Larva";146;2
"Unit";"Hydralisk";"Larva";146;2
"Unit";"Hydralisk";"Larva";160;2
"Unit";"Hydralisk";"Larva";160;2
"Unit";"Hydralisk";"Larva";160;2
"Unit";"Hydralisk";"Larva";160;2
"Unit";"Hydralisk";"Larva";168;2
"Unit";"Hydralisk";"Larva";168;2
"Unit";"Hydralisk";"Larva";168;2
"Unit";"Hydralisk";"Larva";168;2
"Unit";"Hydralisk";"Larva";168;2
"Unit";"Hydralisk";"Larva";168;2
"Unit";"Overlord";"Larva";176;0
"Unit";"Hydralisk";"Larva";176;2
"Unit";"Hydralisk";"Larva";176;2
"Unit";"Hydralisk";"Larva";176;2
"Unit";"Hydralisk";"Larva";176;2
"Unit";"Hydralisk";"Larva";176;2
"Unit";"Hydralisk";"Larva";176;2
"Unit";"Hydralisk";"Larva";176;2
"Building";"Hatchery";NA;160;0
"Building";"CreepTumorQueen";NA;207;0
"Building";"CreepTumor";NA;220;0
"Building";"Extractor";NA;209;0
"Building";"Extractor";NA;209;0
"Unit";"Queen";"Hatchery";207;2
"Building";"InfestationPit";NA;209;0
"Building";"CreepTumor";NA;226;0
"Building";"CreepTumor";NA;226;0
"Unit";"Overlord";"Larva";226;0
"Unit";"Overlord";"Larva";226;0
"Building";"CreepTumorQueen";NA;226;0
"Upgrade";"EvolveMuscularAugments";"HydraliskDen";218;0
"Unit";"Hydralisk";"Larva";226;2
"Unit";"Hydralisk";"Larva";226;2
"Unit";"Hydralisk";"Larva";226;2
"Unit";"Hydralisk";"Larva";226;2
"Unit";"Hydralisk";"Larva";226;2
"Unit";"Hydralisk";"Larva";226;2
"Unit";"Hydralisk";"Larva";226;2
"Unit";"Hydralisk";"Larva";226;2
"Unit";"Hydralisk";"Larva";226;2
"Unit";"Hydralisk";"Larva";226;2
"Unit";"Hydralisk";"Larva";226;2
"Unit";"Queen";"Hatchery";226;2
"Building";"Spire";NA;209;0
"Building";"CreepTumor";NA;226;0
"Building";"CreepTumorQueen";NA;228;0
"Building";"CreepTumor";NA;228;0
"Building";"CreepTumor";NA;248;0
"Building";"CreepTumor";NA;248;0
"Unit";"Overlord";"Larva";266;0
"Unit";"Overlord";"Larva";266;0
"Unit";"Overlord";"Larva";266;0
"Unit";"Overlord";"Larva";266;0
"Building";"Hatchery";NA;226;0
"Unit";"Infestor";"Larva";250;2
"Building";"Extractor";NA;266;0
"Unit";"Infestor";"Larva";250;2
"Building";"Extractor";NA;266;0
"Building";"CreepTumor";NA;266;0
"Building";"SporeCrawler";NA;266;0
"Building";"SporeCrawler";NA;266;0
"Unit";"Infestor";"Larva";266;2
"Building";"SporeCrawler";NA;266;0
"Building";"EvolutionChamber";NA;270;0
"Upgrade";"Burrow";"Hatchery";266;0
"Unit";"Infestor";"Larva";266;2
"Unit";"Infestor";"Larva";266;2
"Building";"CreepTumor";NA;277;0
"Upgrade";"ZergMissileWeaponsLevel2";"EvolutionChamber";226;0
"Building";"SporeCrawler";NA;279;0
"Unit";"Infestor";"Larva";272;2
"Unit";"Infestor";"Larva";272;2
"Building";"SporeCrawler";NA;281;0
"Building";"SporeCrawler";NA;281;0
"Building";"SporeCrawler";NA;281;0
"Building";"SporeCrawler";NA;281;0
"Building";"SporeCrawler";NA;281;0
"Building";"SporeCrawler";NA;281;0
"Building";"SporeCrawler";NA;281;0
"Building";"SporeCrawler";NA;281;0
"Building";"SporeCrawler";NA;281;0
"Unit";"Infestor";"Larva";277;2
"Upgrade";"NeuralParasite";"InfestationPit";270;0
"Building";"Spire";NA;270;0
"Building";"Hatchery";NA;272;0
"Building";"CreepTumor";NA;296;0
"Unit";"Hydralisk";"Larva";296;2
"Unit";"Hydralisk";"Larva";296;2
"Unit";"Hydralisk";"Larva";296;2
"Unit";"Hydralisk";"Larva";296;2
"Unit";"Hydralisk";"Larva";296;2
"Unit";"Hydralisk";"Larva";296;2
"Unit";"Hydralisk";"Larva";296;2
"Unit";"Infestor";"Larva";296;2
"Unit";"Hydralisk";"Larva";296;2
"Building";"CreepTumor";NA;296;0
"Unit";"Hydralisk";"Larva";296;2
"Unit";"Hydralisk";"Larva";296;2
"Unit";"Infestor";"Larva";296;2
"Unit";"Infestor";"Larva";296;2
"Unit";"Infestor";"Larva";296;2
"Unit";"Infestor";"Larva";296;2
"Unit";"Hydralisk";"Larva";296;2
"Unit";"Infestor";"Larva";296;2
"Unit";"Infestor";"Larva";296;2
"Building";"CreepTumor";NA;296;0
"Building";"CreepTumorQueen";NA;296;0
"Unit";"Hydralisk";"Larva";296;2
"Unit";"Hydralisk";"Larva";296;2
"Unit";"Hydralisk";"Larva";296;2
"Building";"CreepTumor";NA;310;0
"Building";"CreepTumor";NA;312;0
"Building";"SporeCrawler";NA;296;0
"Building";"SporeCrawler";NA;296;0
"Unit";"Hydralisk";"Larva";296;2
"Unit";"Hydralisk";"Larva";296;2
"Unit";"Hydralisk";"Larva";296;2
"Unit";"Hydralisk";"Larva";296;2
"Unit";"Hydralisk";"Larva";296;2
"Building";"Extractor";NA;310;0
"Building";"Extractor";NA;310;0
"Building";"CreepTumor";NA;340;0
"Unit";"Hydralisk";"Larva";312;2
"Unit";"Hydralisk";"Larva";312;2
"Unit";"Hydralisk";"Larva";312;2
"Unit";"Hydralisk";"Larva";312;2
"Building";"CreepTumorQueen";NA;350;0
"Unit";"Zergling";"Larva";350;1
"Unit";"Zergling";"Larva";350;1
"Unit";"Zergling";"Larva";350;1
"Unit";"Zergling";"Larva";350;1
"Unit";"Zergling";"Larva";350;1
"Unit";"Zergling";"Larva";350;1
"Unit";"Zergling";"Larva";350;1
"Unit";"Zergling";"Larva";350;1
"Unit";"Zergling";"Larva";350;1
"Unit";"Zergling";"Larva";350;1
"Unit";"Zergling";"Larva";350;1
"Unit";"Zergling";"Larva";350;1
"Unit";"Zergling";"Larva";350;1
"Unit";"Zergling";"Larva";350;1
"Unit";"Zergling";"Larva";350;1
"Unit";"Zergling";"Larva";350;1
"Unit";"Zergling";"Larva";350;1
"Unit";"Zergling";"Larva";350;1
"Unit";"Zergling";"Larva";350;1
"Unit";"Zergling";"Larva";350;1
"Unit";"Zergling";"Larva";350;1
"Unit";"Zergling";"Larva";350;1
"Unit";"Zergling";"Larva";350;1
"Unit";"Zergling";"Larva";350;1
"Unit";"Zergling";"Larva";350;1
"Unit";"Zergling";"Larva";350;1
"Unit";"Zergling";"Larva";350;1
"Unit";"Zergling";"Larva";350;1
"Building";"CreepTumorQueen";NA;386;0
"Unit";"Queen";"Hatchery";340;2
"Unit";"Queen";"Hatchery";340;2
"Building";"CreepTumorQueen";NA;386;0
"Unit";"Overlord";"Larva";386;0
"Unit";"Overlord";"Larva";386;0
"Unit";"Overlord";"Larva";386;0
"Unit";"Overlord";"Larva";386;0
