"type";"unit_name";"on_building";"total_supply";"supply"
"Unit";"Overlord";"Larva";13;0
"Building";"Extractor";NA;18;0
"Building";"SpawningPool";NA;19;0
"Building";"Hatchery";NA;17;0
"Unit";"Overlord";"Larva";22;0
"Unit";"Queen";"Hatchery";23;2
"Unit";"Queen";"Hatchery";23;2
"Unit";"Zergling";"Larva";27;1
"Unit";"Zergling";"Larva";27;1
"Unit";"Zergling";"Larva";27;1
"Unit";"Zergling";"Larva";27;1
"Unit";"Overlord";"Larva";31;0
"Building";"CreepTumorQueen";NA;40;0
"Unit";"Overlord";"Larva";40;0
"Unit";"Overlord";"Larva";42;0
"Building";"Hatchery";NA;27;0
"Unit";"Queen";"Hatchery";40;2
"Building";"CreepTumor";NA;48;0
"Building";"SporeCrawler";NA;47;0
"Building";"SporeCrawler";NA;47;0
"Unit";"Overlord";"Larva";59;0
"Building";"Extractor";NA;55;0
"Building";"Extractor";NA;56;0
"Building";"SporeCrawler";NA;60;0
"Unit";"Zergling";"Larva";60;1
"Unit";"Zergling";"Larva";60;1
"Unit";"Zergling";"Larva";60;1
"Unit";"Zergling";"Larva";60;1
"Unit";"Zergling";"Larva";60;1
"Unit";"Zergling";"Larva";60;1
"Unit";"Zergling";"Larva";60;1
"Unit";"Zergling";"Larva";60;1
"Unit";"Zergling";"Larva";63;1
"Unit";"Zergling";"Larva";63;1
"Unit";"Zergling";"Larva";63;1
"Unit";"Zergling";"Larva";63;1
"Building";"Extractor";NA;63;0
"Building";"HydraliskDen";NA;67;0
"Building";"CreepTumor";NA;80;0
"Unit";"Overlord";"Larva";80;0
"Unit";"Overlord";"Larva";80;0
"Unit";"Overlord";"Larva";80;0
"Unit";"Hydralisk";"Larva";82;2
"Unit";"Hydralisk";"Larva";82;2
"Unit";"Hydralisk";"Larva";82;2
"Unit";"Hydralisk";"Larva";82;2
"Unit";"Hydralisk";"Larva";82;2
"Unit";"Hydralisk";"Larva";82;2
"Unit";"Hydralisk";"Larva";82;2
"Unit";"Hydralisk";"Larva";82;2
"Unit";"Overlord";"Larva";87;0
"Building";"CreepTumor";NA;101;0
"Unit";"Hydralisk";"Larva";101;2
"Unit";"Hydralisk";"Larva";101;2
"Unit";"Overlord";"Larva";104;0
"Unit";"Overlord";"Larva";104;0
"Building";"EvolutionChamber";NA;104;0
"Building";"Extractor";NA;115;0
"Building";"Extractor";NA;115;0
"Building";"CreepTumor";NA;125;0
"Upgrade";"EvolveGroovedSpines";"HydraliskDen";104;0
"Unit";"Hydralisk";"Larva";123;2
"Unit";"Hydralisk";"Larva";123;2
"Unit";"Hydralisk";"Larva";130;2
"Unit";"Hydralisk";"Larva";130;2
"Unit";"Hydralisk";"Larva";130;2
"Unit";"Hydralisk";"Larva";130;2
"Unit";"Hydralisk";"Larva";130;2
"Unit";"Hydralisk";"Larva";130;2
"Building";"Hatchery";NA;108;0
"Unit";"Overlord";"Larva";130;0
"Unit";"Overlord";"Larva";130;0
"Unit";"Overlord";"Larva";130;0
"Building";"CreepTumor";NA;145;0
"Building";"LurkerDenMP";NA;115;0
"Unit";"Hydralisk";"Larva";145;2
"Unit";"Hydralisk";"Larva";145;2
"Unit";"Hydralisk";"Larva";145;2
"Unit";"Hydralisk";"Larva";145;2
"Unit";"Hydralisk";"Larva";145;2
"Unit";"Hydralisk";"Larva";145;2
"Unit";"Hydralisk";"Larva";145;2
"Unit";"Queen";"Hatchery";145;2
"Building";"Extractor";NA;152;0
"Upgrade";"ZergMissileWeaponsLevel1";"EvolutionChamber";128;0
"Building";"Extractor";NA;166;0
"Upgrade";"EvolveMuscularAugments";"HydraliskDen";145;0
"Unit";"Overlord";"Larva";168;0
"Unit";"Overlord";"Larva";168;0
"Unit";"Overlord";"Larva";168;0
"Unit";"Overlord";"Larva";168;0
"Unit";"Overlord";"Larva";168;0
"Unit";"Overlord";"Larva";168;0
"Unit";"Overlord";"Larva";168;0
"Unit";"Overlord";"Larva";168;0
"Building";"EvolutionChamber";NA;168;0
"Building";"InfestationPit";NA;168;0
"Unit";"Hydralisk";"Larva";171;2
"Unit";"Hydralisk";"Larva";171;2
"Unit";"Hydralisk";"Larva";171;2
"Unit";"Hydralisk";"Larva";171;2
"Unit";"Hydralisk";"Larva";171;2
"Unit";"Hydralisk";"Larva";171;2
"Unit";"Hydralisk";"Larva";171;2
"Unit";"Hydralisk";"Larva";171;2
"Unit";"Hydralisk";"Larva";184;2
"Unit";"Hydralisk";"Larva";184;2
"Unit";"Hydralisk";"Larva";184;2
"Unit";"Hydralisk";"Larva";184;2
"Unit";"Hydralisk";"Larva";184;2
"Unit";"Hydralisk";"Larva";184;2
"Building";"Hatchery";NA;169;0
"Unit";"Zergling";"Larva";213;1
"Unit";"Zergling";"Larva";213;1
"Unit";"Zergling";"Larva";213;1
"Unit";"Zergling";"Larva";213;1
"Unit";"Zergling";"Larva";213;1
"Unit";"Zergling";"Larva";213;1
"Unit";"Zergling";"Larva";213;1
"Unit";"Zergling";"Larva";213;1
"Unit";"Zergling";"Larva";213;1
"Unit";"Zergling";"Larva";213;1
"Unit";"Zergling";"Larva";213;1
"Unit";"Zergling";"Larva";213;1
"Unit";"Zergling";"Larva";213;1
"Unit";"Zergling";"Larva";213;1
"Unit";"Zergling";"Larva";213;1
"Unit";"Zergling";"Larva";213;1
"Unit";"Zergling";"Larva";213;1
"Unit";"Zergling";"Larva";213;1
"Unit";"Zergling";"Larva";213;1
"Unit";"Zergling";"Larva";213;1
"Unit";"Zergling";"Larva";213;1
"Unit";"Zergling";"Larva";213;1
"Unit";"Zergling";"Larva";213;1
"Unit";"Zergling";"Larva";213;1
"Unit";"Zergling";"Larva";213;1
"Unit";"Zergling";"Larva";213;1
"Building";"SporeCrawler";NA;239;0
"Upgrade";"ZergMissileWeaponsLevel2";"EvolutionChamber";182;0
"Building";"SpineCrawler";NA;239;0
"Building";"SpineCrawler";NA;239;0
"Building";"SpineCrawler";NA;239;0
"Building";"SporeCrawler";NA;242;0
"Building";"SporeCrawler";NA;242;0
"Building";"Spire";NA;213;0
"Unit";"Hydralisk";"Larva";242;2
"Unit";"Hydralisk";"Larva";242;2
"Unit";"Hydralisk";"Larva";242;2
"Unit";"Hydralisk";"Larva";242;2
"Unit";"Hydralisk";"Larva";242;2
"Building";"SporeCrawler";NA;252;0
"Upgrade";"ZergGroundArmorsLevel1";"EvolutionChamber";242;0
"Building";"Extractor";NA;260;0
"Building";"SporeCrawler";NA;260;0
"Building";"Extractor";NA;260;0
"Building";"SpineCrawler";NA;260;0
"Building";"SpineCrawler";NA;260;0
"Unit";"Queen";"Hatchery";260;2
"Building";"SpineCrawler";NA;260;0
"Building";"SpineCrawler";NA;260;0
"Unit";"Corruptor";"Larva";267;2
"Unit";"Corruptor";"Larva";267;2
"Unit";"Corruptor";"Larva";267;2
"Unit";"Corruptor";"Larva";267;2
"Unit";"Corruptor";"Larva";267;2
"Unit";"Corruptor";"Larva";267;2
"Unit";"Corruptor";"Larva";267;2
"Unit";"Corruptor";"Larva";267;2
"Upgrade";"ZergMeleeWeaponsLevel1";"EvolutionChamber";242;0
"Building";"SpineCrawler";NA;267;0
"Unit";"Overlord";"Larva";285;0
"Unit";"Overlord";"Larva";285;0
"Unit";"Overlord";"Larva";285;0
"Building";"SpineCrawler";NA;285;0
"Building";"SpineCrawler";NA;285;0
"Building";"SpineCrawler";NA;285;0
"Upgrade";"Burrow";"Hatchery";269;0
"Unit";"Hydralisk";"Larva";285;2
"Unit";"Hydralisk";"Larva";285;2
"Unit";"Hydralisk";"Larva";285;2
"Unit";"Hydralisk";"Larva";285;2
"Unit";"Hydralisk";"Larva";285;2
"Unit";"Hydralisk";"Larva";285;2
"Unit";"Hydralisk";"Larva";285;2
"Unit";"Hydralisk";"Larva";285;2
"Unit";"Hydralisk";"Larva";285;2
"Unit";"Zergling";"Larva";303;1
"Unit";"Zergling";"Larva";303;1
"Unit";"Zergling";"Larva";303;1
"Unit";"Zergling";"Larva";303;1
"Unit";"Zergling";"Larva";303;1
"Unit";"Zergling";"Larva";303;1
"Unit";"Zergling";"Larva";303;1
"Unit";"Zergling";"Larva";303;1
"Unit";"Zergling";"Larva";303;1
"Unit";"Zergling";"Larva";303;1
"Unit";"Zergling";"Larva";303;1
"Unit";"Zergling";"Larva";303;1
"Unit";"Zergling";"Larva";303;1
"Unit";"Zergling";"Larva";303;1
"Unit";"Zergling";"Larva";303;1
"Unit";"Zergling";"Larva";303;1
"Unit";"Zergling";"Larva";303;1
"Unit";"Zergling";"Larva";303;1
"Unit";"Zergling";"Larva";303;1
"Unit";"Zergling";"Larva";303;1
"Unit";"Zergling";"Larva";323;1
"Unit";"Zergling";"Larva";323;1
"Unit";"Zergling";"Larva";323;1
"Unit";"Zergling";"Larva";323;1
"Unit";"Zergling";"Larva";323;1
"Unit";"Zergling";"Larva";323;1
