"type";"unit_name";"on_building";"total_supply";"supply"
"Unit";"Overlord";"Larva";13;0
"Building";"Extractor";NA;18;0
"Unit";"Overlord";"Larva";21;0
"Building";"SpawningPool";NA;19;0
"Building";"Hatchery";NA;17;0
"Unit";"Zergling";"Larva";22;1
"Unit";"Zergling";"Larva";22;1
"Unit";"Zergling";"Larva";22;1
"Unit";"Zergling";"Larva";22;1
"Unit";"Queen";"Hatchery";22;2
"Unit";"Queen";"Hatchery";22;2
"Unit";"Zergling";"Larva";28;1
"Unit";"Zergling";"Larva";28;1
"Unit";"Zergling";"Larva";28;1
"Unit";"Zergling";"Larva";28;1
"Building";"CreepTumorQueen";NA;37;0
"Building";"SpineCrawler";NA;28;0
"Unit";"Overlord";"Larva";38;0
"Unit";"Queen";"Hatchery";33;2
"Unit";"Zergling";"Larva";48;1
"Unit";"Zergling";"Larva";48;1
"Unit";"Zergling";"Larva";48;1
"Unit";"Zergling";"Larva";48;1
"Unit";"Zergling";"Larva";49;1
"Unit";"Zergling";"Larva";49;1
"Unit";"Zergling";"Larva";49;1
"Unit";"Zergling";"Larva";49;1
"Unit";"Zergling";"Larva";53;1
"Unit";"Zergling";"Larva";53;1
"Unit";"Zergling";"Larva";53;1
"Unit";"Zergling";"Larva";53;1
"Building";"CreepTumorQueen";NA;57;0
"Unit";"Overlord";"Larva";57;0
"Building";"CreepTumor";NA;57;0
"Unit";"Overlord";"Larva";57;0
"Building";"CreepTumorQueen";NA;63;0
"Building";"SporeCrawler";NA;57;0
"Unit";"Overlord";"Larva";63;0
"Unit";"Overlord";"Larva";63;0
"Building";"SporeCrawler";NA;63;0
"Building";"Hatchery";NA;49;0
"Building";"CreepTumor";NA;69;0
"Building";"CreepTumor";NA;69;0
"Building";"CreepTumorQueen";NA;70;0
"Building";"Extractor";NA;74;0
"Building";"Extractor";NA;74;0
"Building";"RoachWarren";NA;69;0
"Building";"EvolutionChamber";NA;74;0
"Unit";"Queen";"Hatchery";78;2
"Unit";"Roach";"Larva";82;2
"Unit";"Roach";"Larva";82;2
"Building";"SporeCrawler";NA;85;0
"Building";"Extractor";NA;89;0
"Unit";"Overlord";"Larva";96;0
"Unit";"Overlord";"Larva";96;0
"Unit";"Queen";"Hatchery";96;2
"Building";"Extractor";NA;104;0
"Building";"HydraliskDen";NA;104;0
"Building";"CreepTumor";NA;114;0
"Building";"CreepTumor";NA;114;0
"Building";"CreepTumor";NA;114;0
"Unit";"Roach";"Larva";113;2
"Unit";"Roach";"Larva";113;2
"Unit";"Roach";"Larva";114;2
"Unit";"Roach";"Larva";114;2
"Building";"CreepTumor";NA;120;0
"Unit";"Overlord";"Larva";120;0
"Unit";"Roach";"Larva";120;2
"Unit";"Overlord";"Larva";120;0
"Building";"CreepTumor";NA;128;0
"Unit";"Overlord";"Larva";128;0
"Unit";"Overlord";"Larva";128;0
"Building";"Extractor";NA;124;0
"Unit";"Overlord";"Larva";128;0
"Unit";"Overlord";"Larva";130;0
"Upgrade";"ZergMissileWeaponsLevel1";"EvolutionChamber";99;0
"Unit";"Hydralisk";"Larva";128;2
"Unit";"Hydralisk";"Larva";128;2
"Unit";"Hydralisk";"Larva";128;2
"Unit";"Queen";"Hatchery";128;2
"Upgrade";"GlialReconstitution";"RoachWarren";120;0
"Unit";"Hydralisk";"Larva";139;2
"Unit";"Roach";"Larva";143;2
"Upgrade";"EvolveGroovedSpines";"HydraliskDen";130;0
"Unit";"Hydralisk";"Larva";141;2
"Unit";"Hydralisk";"Larva";141;2
"Unit";"Hydralisk";"Larva";141;2
"Unit";"Hydralisk";"Larva";141;2
"Unit";"Hydralisk";"Larva";141;2
"Unit";"Hydralisk";"Larva";141;2
"Unit";"Hydralisk";"Larva";141;2
"Unit";"Roach";"Larva";147;2
"Unit";"Roach";"Larva";147;2
"Unit";"Roach";"Larva";147;2
"Unit";"Roach";"Larva";147;2
"Unit";"Roach";"Larva";147;2
"Unit";"Roach";"Larva";147;2
"Unit";"Roach";"Larva";147;2
"Unit";"Roach";"Larva";147;2
"Unit";"Roach";"Larva";147;2
"Unit";"Roach";"Larva";149;2
"Unit";"Roach";"Larva";149;2
"Building";"CreepTumor";NA;186;0
"Building";"Hatchery";NA;139;0
"Building";"CreepTumor";NA;187;0
"Building";"SporeCrawler";NA;186;0
"Unit";"Hydralisk";"Larva";182;2
"Unit";"Overlord";"Larva";187;0
"Unit";"Queen";"Hatchery";163;2
"Unit";"Hydralisk";"Larva";187;2
"Unit";"Hydralisk";"Larva";187;2
"Unit";"Hydralisk";"Larva";187;2
"Unit";"Hydralisk";"Larva";187;2
"Unit";"Hydralisk";"Larva";187;2
"Unit";"Overlord";"Larva";187;0
"Unit";"Queen";"Hatchery";165;2
"Unit";"Zergling";"Larva";189;1
"Unit";"Zergling";"Larva";189;1
"Unit";"Zergling";"Larva";189;1
"Unit";"Zergling";"Larva";189;1
"Unit";"Zergling";"Larva";189;1
"Unit";"Zergling";"Larva";189;1
"Building";"CreepTumorQueen";NA;203;0
"Unit";"Hydralisk";"Larva";187;2
"Building";"CreepTumorQueen";NA;203;0
"Building";"Extractor";NA;203;0
"Building";"Extractor";NA;203;0
"Unit";"Hydralisk";"Larva";203;2
"Unit";"Hydralisk";"Larva";203;2
"Unit";"Hydralisk";"Larva";203;2
"Unit";"Hydralisk";"Larva";203;2
"Unit";"Hydralisk";"Larva";203;2
"Unit";"Roach";"Larva";209;2
"Unit";"Roach";"Larva";211;2
"Unit";"Roach";"Larva";211;2
"Unit";"Roach";"Larva";211;2
"Unit";"Roach";"Larva";211;2
"Unit";"Roach";"Larva";211;2
"Unit";"Roach";"Larva";211;2
"Upgrade";"EvolveMuscularAugments";"HydraliskDen";187;0
"Unit";"Hydralisk";"Larva";211;2
"Unit";"Hydralisk";"Larva";213;2
"Unit";"Hydralisk";"Larva";241;2
"Upgrade";"ZergMissileWeaponsLevel2";"EvolutionChamber";186;0
"Unit";"Roach";"Larva";241;2
"Unit";"Roach";"Larva";241;2
"Unit";"Hydralisk";"Larva";241;2
"Unit";"Hydralisk";"Larva";241;2
"Unit";"Hydralisk";"Larva";241;2
"Unit";"Hydralisk";"Larva";241;2
"Unit";"Hydralisk";"Larva";241;2
"Unit";"Hydralisk";"Larva";241;2
"Unit";"Roach";"Larva";245;2
"Unit";"Roach";"Larva";245;2
"Unit";"Roach";"Larva";245;2
"Unit";"Roach";"Larva";245;2
"Unit";"Roach";"Larva";245;2
"Unit";"Roach";"Larva";245;2
"Unit";"Hydralisk";"Larva";263;2
"Unit";"Hydralisk";"Larva";263;2
"Unit";"Hydralisk";"Larva";263;2
"Unit";"Hydralisk";"Larva";263;2
"Unit";"Hydralisk";"Larva";263;2
"Unit";"Hydralisk";"Larva";263;2
"Unit";"Hydralisk";"Larva";263;2
"Building";"CreepTumorQueen";NA;275;0
"Unit";"Hydralisk";"Larva";275;2
"Unit";"Hydralisk";"Larva";275;2
"Unit";"Hydralisk";"Larva";275;2
"Unit";"Roach";"Larva";285;2
"Unit";"Roach";"Larva";285;2
"Unit";"Roach";"Larva";285;2
"Unit";"Roach";"Larva";285;2
"Unit";"Roach";"Larva";285;2
"Unit";"Roach";"Larva";285;2
"Unit";"Roach";"Larva";285;2
"Unit";"Roach";"Larva";285;2
"Unit";"Roach";"Larva";285;2
"Unit";"Roach";"Larva";285;2
"Unit";"Roach";"Larva";289;2
"Unit";"Roach";"Larva";289;2
"Unit";"Roach";"Larva";289;2
"Unit";"Roach";"Larva";289;2
"Unit";"Overlord";"Larva";289;0
"Unit";"Roach";"Larva";315;2
"Unit";"Roach";"Larva";317;2
"Unit";"Roach";"Larva";317;2
"Unit";"Roach";"Larva";319;2
"Unit";"Roach";"Larva";319;2
"Unit";"Roach";"Larva";321;2
"Unit";"Roach";"Larva";323;2
"Unit";"Hydralisk";"Larva";323;2
"Unit";"Hydralisk";"Larva";323;2
"Unit";"Overlord";"Larva";335;0
"Unit";"Overlord";"Larva";335;0
"Unit";"Hydralisk";"Larva";335;2
"Unit";"Hydralisk";"Larva";335;2
"Unit";"Hydralisk";"Larva";335;2
"Unit";"Hydralisk";"Larva";335;2
"Unit";"Hydralisk";"Larva";335;2
"Unit";"Hydralisk";"Larva";335;2
"Unit";"Hydralisk";"Larva";335;2
"Unit";"Hydralisk";"Larva";360;2
"Unit";"Hydralisk";"Larva";361;2
"Unit";"Hydralisk";"Larva";362;2
"Unit";"Hydralisk";"Larva";362;2
"Unit";"Hydralisk";"Larva";362;2
"Unit";"Hydralisk";"Larva";363;2
"Building";"CreepTumor";NA;382;0
"Building";"CreepTumor";NA;382;0
"Unit";"Roach";"Larva";382;2
"Unit";"Hydralisk";"Larva";382;2
"Unit";"Roach";"Larva";382;2
"Unit";"Hydralisk";"Larva";382;2
"Unit";"Roach";"Larva";382;2
"Unit";"Roach";"Larva";382;2
"Unit";"Roach";"Larva";384;2
"Unit";"Roach";"Larva";384;2
"Unit";"Roach";"Larva";384;2
"Unit";"Roach";"Larva";384;2
"Unit";"Roach";"Larva";384;2
"Unit";"Roach";"Larva";384;2
"Building";"CreepTumor";NA;386;0
"Unit";"Roach";"Larva";386;2
"Building";"CreepTumorQueen";NA;398;0
"Unit";"Roach";"Larva";392;2
"Unit";"Roach";"Larva";392;2
"Unit";"Roach";"Larva";392;2
"Unit";"Roach";"Larva";394;2
"Building";"CreepTumorQueen";NA;408;0
"Unit";"Roach";"Larva";396;2
"Building";"CreepTumor";NA;410;0
"Building";"CreepTumor";NA;414;0
"Unit";"Zergling";"Larva";420;1
"Unit";"Zergling";"Larva";420;1
"Unit";"Zergling";"Larva";420;1
"Unit";"Zergling";"Larva";420;1
"Unit";"Roach";"Larva";420;2
"Unit";"Roach";"Larva";420;2
"Building";"Hatchery";NA;382;0
"Unit";"Hydralisk";"Larva";420;2
"Unit";"Hydralisk";"Larva";420;2
"Unit";"Overlord";"Larva";420;0
"Unit";"Overlord";"Larva";420;0
"Unit";"Overlord";"Larva";420;0
"Unit";"Hydralisk";"Larva";420;2
"Building";"InfestationPit";NA;420;0
"Unit";"Hydralisk";"Larva";436;2
"Unit";"Hydralisk";"Larva";436;2
"Unit";"Hydralisk";"Larva";436;2
"Unit";"Hydralisk";"Larva";436;2
"Unit";"Hydralisk";"Larva";436;2
"Unit";"Hydralisk";"Larva";436;2
"Unit";"Hydralisk";"Larva";436;2
"Unit";"Hydralisk";"Larva";436;2
"Unit";"Hydralisk";"Larva";436;2
"Unit";"Roach";"Larva";436;2
"Unit";"Roach";"Larva";436;2
"Unit";"Roach";"Larva";436;2
"Unit";"Roach";"Larva";436;2
"Unit";"Hydralisk";"Larva";436;2
"Building";"Hatchery";NA;420;0
"Unit";"Hydralisk";"Larva";436;2
"Unit";"Hydralisk";"Larva";436;2
"Unit";"Hydralisk";"Larva";436;2
"Building";"LurkerDenMP";NA;420;0
"Unit";"Hydralisk";"Larva";462;2
"Unit";"Zergling";"Larva";462;1
"Unit";"Zergling";"Larva";462;1
"Unit";"Zergling";"Larva";464;1
"Unit";"Zergling";"Larva";464;1
"Unit";"Zergling";"Larva";464;1
"Unit";"Zergling";"Larva";464;1
"Unit";"Zergling";"Larva";464;1
"Unit";"Zergling";"Larva";464;1
"Upgrade";"ZergGroundArmorsLevel1";"EvolutionChamber";436;0
"Building";"Extractor";NA;482;0
"Building";"Extractor";NA;482;0
"Building";"Spire";NA;464;0
"Unit";"Hydralisk";"Larva";482;2
"Unit";"Hydralisk";"Larva";482;2
"Unit";"Hydralisk";"Larva";482;2
"Unit";"Hydralisk";"Larva";482;2
"Unit";"Hydralisk";"Larva";482;2
"Unit";"Hydralisk";"Larva";482;2
"Unit";"Hydralisk";"Larva";482;2
"Unit";"Hydralisk";"Larva";482;2
"Unit";"Hydralisk";"Larva";482;2
"Unit";"Overlord";"Larva";482;0
"Unit";"Hydralisk";"Larva";482;2
"Unit";"Hydralisk";"Larva";482;2
"Unit";"Hydralisk";"Larva";482;2
"Unit";"Hydralisk";"Larva";482;2
"Unit";"Hydralisk";"Larva";482;2
"Unit";"Hydralisk";"Larva";482;2
"Unit";"Hydralisk";"Larva";482;2
"Unit";"Hydralisk";"Larva";482;2
"Unit";"Hydralisk";"Larva";482;2
"Unit";"Overlord";"Larva";500;0
"Building";"Hatchery";NA;482;0
"Unit";"Overlord";"Larva";500;0
"Unit";"Overlord";"Larva";500;0
"Unit";"Overlord";"Larva";500;0
"Unit";"Overlord";"Larva";500;0
"Unit";"Overlord";"Larva";500;0
"Unit";"Corruptor";"Larva";482;2
"Unit";"Corruptor";"Larva";484;2
"Unit";"Overlord";"Larva";518;0
"Unit";"Corruptor";"Larva";518;2
"Unit";"Corruptor";"Larva";518;2
"Unit";"Corruptor";"Larva";518;2
"Unit";"Zergling";"Larva";522;1
"Unit";"Zergling";"Larva";522;1
"Unit";"Zergling";"Larva";522;1
"Unit";"Zergling";"Larva";522;1
"Unit";"Zergling";"Larva";522;1
"Unit";"Zergling";"Larva";522;1
"Unit";"Zergling";"Larva";522;1
"Unit";"Zergling";"Larva";522;1
"Unit";"Zergling";"Larva";522;1
"Unit";"Zergling";"Larva";522;1
"Unit";"Corruptor";"Larva";522;2
"Unit";"Corruptor";"Larva";522;2
"Unit";"Corruptor";"Larva";522;2
"Unit";"Corruptor";"Larva";522;2
"Unit";"Corruptor";"Larva";522;2
"Unit";"Corruptor";"Larva";522;2
"Unit";"Corruptor";"Larva";522;2
"Unit";"Corruptor";"Larva";522;2
"Unit";"Corruptor";"Larva";522;2
"Unit";"Corruptor";"Larva";522;2
"Unit";"Zergling";"Larva";522;1
"Unit";"Zergling";"Larva";522;1
"Unit";"Zergling";"Larva";522;1
"Unit";"Zergling";"Larva";522;1
"Unit";"Zergling";"Larva";524;1
"Unit";"Zergling";"Larva";524;1
"Unit";"Zergling";"Larva";524;1
"Unit";"Zergling";"Larva";524;1
"Unit";"Zergling";"Larva";528;1
"Unit";"Zergling";"Larva";528;1
"Unit";"Zergling";"Larva";528;1
"Unit";"Zergling";"Larva";528;1
"Building";"EvolutionChamber";NA;522;0
"Unit";"Hydralisk";"Larva";538;2
"Unit";"Hydralisk";"Larva";538;2
"Unit";"Hydralisk";"Larva";538;2
"Unit";"Hydralisk";"Larva";538;2
"Unit";"Hydralisk";"Larva";538;2
"Unit";"Hydralisk";"Larva";558;2
"Unit";"Hydralisk";"Larva";558;2
"Unit";"Hydralisk";"Larva";586;2
"Unit";"Hydralisk";"Larva";590;2
"Unit";"Hydralisk";"Larva";590;2
"Unit";"Hydralisk";"Larva";590;2
"Unit";"Hydralisk";"Larva";590;2
"Unit";"Hydralisk";"Larva";590;2
"Unit";"Hydralisk";"Larva";590;2
"Unit";"Hydralisk";"Larva";590;2
"Unit";"Hydralisk";"Larva";590;2
"Unit";"Hydralisk";"Larva";590;2
"Unit";"Hydralisk";"Larva";590;2
"Unit";"Hydralisk";"Larva";590;2
"Unit";"Hydralisk";"Larva";590;2
"Unit";"Hydralisk";"Larva";590;2
"Unit";"Hydralisk";"Larva";590;2
"Unit";"Hydralisk";"Larva";590;2
"Unit";"Hydralisk";"Larva";590;2
"Unit";"Hydralisk";"Larva";590;2
"Unit";"Hydralisk";"Larva";590;2
"Unit";"Hydralisk";"Larva";590;2
"Upgrade";"ZergMeleeWeaponsLevel1";"EvolutionChamber";570;0
"Unit";"Hydralisk";"Larva";616;2
"Unit";"Hydralisk";"Larva";630;2
"Unit";"Hydralisk";"Larva";630;2
"Unit";"Hydralisk";"Larva";630;2
"Unit";"Hydralisk";"Larva";630;2
"Unit";"Hydralisk";"Larva";630;2
"Unit";"Corruptor";"Larva";642;2
"Unit";"Corruptor";"Larva";642;2
"Unit";"Corruptor";"Larva";642;2
"Unit";"Corruptor";"Larva";642;2
"Building";"CreepTumor";NA;644;0
"Unit";"Corruptor";"Larva";644;2
"Unit";"Corruptor";"Larva";644;2
"Unit";"Corruptor";"Larva";650;2
"Unit";"Hydralisk";"Larva";652;2
"Unit";"Hydralisk";"Larva";652;2
"Unit";"Hydralisk";"Larva";652;2
"Unit";"Hydralisk";"Larva";652;2
"Building";"Hatchery";NA;642;0
"Unit";"Hydralisk";"Larva";654;2
"Unit";"Hydralisk";"Larva";654;2
"Unit";"Hydralisk";"Larva";654;2
"Unit";"Hydralisk";"Larva";654;2
"Building";"Hatchery";NA;644;0
