"type";"unit_name";"on_building";"total_supply_lag";"supply"
"Unit";"Overlord";"Larva";13;0
"Building";"Hatchery";NA;16;0
"Building";"Extractor";NA;19;0
"Building";"SpawningPool";NA;19;0
"Unit";"Overlord";"Larva";23;0
"Unit";"Queen";"Hatchery";23;2
"Unit";"Queen";"Hatchery";25;2
"Unit";"Zergling";"Larva";27;1
"Unit";"Zergling";"Larva";28;1
"Unit";"Zergling";"Larva";29;1
"Unit";"Zergling";"Larva";30;1
"Building";"Hatchery";NA;37;0
"Unit";"Overlord";"Larva";39;0
"Building";"SporeCrawler";NA;50;0
"Building";"SporeCrawler";NA;50;0
"Unit";"Queen";"Hatchery";50;2
"Building";"CreepTumorQueen";NA;52;0
"Unit";"Overlord";"Larva";52;0
"Building";"CreepTumorQueen";NA;52;0
"Building";"Extractor";NA;52;0
"Unit";"Overlord";"Larva";53;0
"Building";"Extractor";NA;62;0
"Building";"CreepTumor";NA;62;0
"Unit";"Queen";"Hatchery";62;2
"Building";"SporeCrawler";NA;64;0
"Unit";"Zergling";"Larva";68;1
"Unit";"Zergling";"Larva";69;1
"Unit";"Zergling";"Larva";70;1
"Unit";"Zergling";"Larva";71;1
"Unit";"Overlord";"Larva";72;0
"Building";"Extractor";NA;72;0
"Unit";"Overlord";"Larva";72;0
"Building";"HydraliskDen";NA;73;0
"Building";"CreepTumor";NA;73;0
"Building";"EvolutionChamber";NA;73;0
"Unit";"Overlord";"Larva";86;0
"Building";"CreepTumorQueen";NA;86;0
"Unit";"Overlord";"Larva";86;0
"Building";"Extractor";NA;86;0
"Building";"CreepTumorQueen";NA;86;0
"Unit";"Hydralisk";"Larva";86;2
"Unit";"Hydralisk";"Larva";88;2
"Unit";"Hydralisk";"Larva";90;2
"Building";"CreepTumor";NA;92;0
"Unit";"Hydralisk";"Larva";92;2
"Unit";"Hydralisk";"Larva";94;2
"Building";"CreepTumor";NA;96;0
"Unit";"Hydralisk";"Larva";96;2
"Unit";"Hydralisk";"Larva";98;2
"Unit";"Hydralisk";"Larva";100;2
"Building";"CreepTumor";NA;106;0
"Unit";"Overlord";"Larva";106;0
"Building";"CreepTumor";NA;106;0
"Unit";"Hydralisk";"Larva";106;2
"Building";"CreepTumorQueen";NA;108;0
"Unit";"Overlord";"Larva";108;0
"Unit";"Overlord";"Larva";108;0
"Building";"Extractor";NA;115;0
"Building";"CreepTumor";NA;115;0
"Building";"CreepTumor";NA;115;0
"Unit";"Overlord";"Larva";123;0
"Unit";"Hydralisk";"Larva";123;2
"Unit";"Overlord";"Larva";125;0
"Unit";"Overlord";"Larva";125;0
"Building";"CreepTumor";NA;125;0
"Building";"CreepTumor";NA;125;0
"Building";"Hatchery";NA;125;0
"Unit";"Hydralisk";"Larva";125;2
"Unit";"Hydralisk";"Larva";127;2
"Unit";"Hydralisk";"Larva";129;2
"Unit";"Hydralisk";"Larva";131;2
"Building";"BanelingNest";NA;133;0
"Unit";"Zergling";"Larva";133;1
"Unit";"Zergling";"Larva";134;1
"Unit";"Zergling";"Larva";135;1
"Unit";"Zergling";"Larva";136;1
"Unit";"Zergling";"Larva";137;1
"Unit";"Zergling";"Larva";138;1
"Unit";"Zergling";"Larva";139;1
"Unit";"Zergling";"Larva";140;1
"Unit";"Zergling";"Larva";141;1
"Unit";"Zergling";"Larva";142;1
"Unit";"Zergling";"Larva";143;1
"Unit";"Zergling";"Larva";144;1
"Unit";"Zergling";"Larva";145;1
"Unit";"Zergling";"Larva";146;1
"Unit";"Zergling";"Larva";147;1
"Unit";"Zergling";"Larva";148;1
"Unit";"Zergling";"Larva";149;1
"Unit";"Zergling";"Larva";150;1
"Unit";"Zergling";"Larva";151;1
"Unit";"Zergling";"Larva";152;1
"Unit";"Zergling";"Larva";153;1
"Unit";"Zergling";"Larva";154;1
"Unit";"Hydralisk";"Larva";155;2
"Unit";"Hydralisk";"Larva";157;2
"Unit";"Hydralisk";"Larva";159;2
"Unit";"Hydralisk";"Larva";161;2
"Unit";"Hydralisk";"Larva";163;2
"Unit";"Hydralisk";"Larva";165;2
"Unit";"Hydralisk";"Larva";167;2
"Unit";"Queen";"Hatchery";169;2
"Unit";"Zergling";"Larva";172;1
"Unit";"Zergling";"Larva";173;1
"Unit";"Zergling";"Larva";174;1
"Unit";"Zergling";"Larva";175;1
"Unit";"Zergling";"Larva";176;1
"Unit";"Zergling";"Larva";177;1
"Unit";"Hydralisk";"Larva";178;2
"Unit";"Hydralisk";"Larva";180;2
"Unit";"Queen";"Hatchery";182;2
"Building";"CreepTumor";NA;191;0
"Building";"CreepTumor";NA;191;0
"Building";"EvolutionChamber";NA;196;0
"Unit";"Queen";"Hatchery";196;2
"Unit";"Hydralisk";"Larva";198;2
"Unit";"Hydralisk";"Larva";200;2
"Unit";"Hydralisk";"Larva";202;2
"Building";"CreepTumor";NA;204;0
"Unit";"Hydralisk";"Larva";204;2
"Unit";"Hydralisk";"Larva";206;2
"Unit";"Hydralisk";"Larva";208;2
"Unit";"Hydralisk";"Larva";210;2
"Building";"CreepTumor";NA;212;0
"Unit";"Overlord";"Larva";212;0
"Unit";"Overlord";"Larva";212;0
"Unit";"Overlord";"Larva";212;0
"Unit";"Hydralisk";"Larva";215;2
"Unit";"Hydralisk";"Larva";217;2
"Unit";"Hydralisk";"Larva";219;2
"Unit";"Baneling";"Zergling";221;0
"Unit";"Baneling";"Zergling";221;0
"Unit";"Baneling";"Zergling";221;0
"Unit";"Baneling";"Zergling";221;0
"Unit";"Baneling";"Zergling";221;0
"Unit";"Overlord";"Larva";221;0
"Unit";"Zergling";"Larva";221;1
"Unit";"Zergling";"Larva";222;1
"Unit";"Zergling";"Larva";223;1
"Unit";"Zergling";"Larva";224;1
"Unit";"Zergling";"Larva";225;1
"Unit";"Zergling";"Larva";226;1
"Unit";"Zergling";"Larva";227;1
"Unit";"Zergling";"Larva";228;1
"Unit";"Zergling";"Larva";229;1
"Unit";"Zergling";"Larva";230;1
"Unit";"Zergling";"Larva";231;1
"Unit";"Zergling";"Larva";232;1
"Unit";"Zergling";"Larva";233;1
"Unit";"Zergling";"Larva";234;1
"Unit";"Zergling";"Larva";235;1
"Unit";"Zergling";"Larva";236;1
"Unit";"Zergling";"Larva";237;1
"Unit";"Zergling";"Larva";238;1
"Unit";"Zergling";"Larva";239;1
"Unit";"Zergling";"Larva";240;1
"Unit";"Zergling";"Larva";241;1
"Unit";"Zergling";"Larva";242;1
"Unit";"Zergling";"Larva";243;1
"Unit";"Zergling";"Larva";244;1
"Unit";"Baneling";"Zergling";245;0
"Unit";"Baneling";"Zergling";245;0
"Unit";"Baneling";"Zergling";245;0
"Unit";"Baneling";"Zergling";245;0
"Unit";"Baneling";"Zergling";245;0
"Unit";"Zergling";"Larva";245;1
"Unit";"Zergling";"Larva";246;1
"Unit";"Zergling";"Larva";247;1
"Unit";"Zergling";"Larva";248;1
"Unit";"Zergling";"Larva";249;1
"Unit";"Zergling";"Larva";250;1
"Building";"SpineCrawler";NA;251;0
"Building";"SpineCrawler";NA;251;0
"Unit";"Baneling";"Zergling";251;0
"Unit";"Baneling";"Zergling";251;0
"Unit";"Baneling";"Zergling";251;0
"Unit";"Baneling";"Zergling";251;0
"Unit";"Baneling";"Zergling";251;0
"Unit";"Baneling";"Zergling";251;0
"Unit";"Baneling";"Zergling";251;0
"Unit";"Baneling";"Zergling";251;0
"Unit";"Baneling";"Zergling";251;0
"Unit";"Baneling";"Zergling";251;0
"Unit";"Baneling";"Zergling";251;0
"Unit";"Baneling";"Zergling";251;0
"Unit";"Baneling";"Zergling";251;0
"Unit";"Baneling";"Zergling";251;0
"Unit";"Baneling";"Zergling";251;0
"Unit";"Baneling";"Zergling";251;0
"Unit";"Baneling";"Zergling";251;0
"Unit";"Baneling";"Zergling";251;0
"Unit";"Baneling";"Zergling";251;0
"Unit";"Baneling";"Zergling";251;0
"Unit";"Baneling";"Zergling";251;0
"Unit";"Baneling";"Zergling";251;0
"Unit";"Zergling";"Larva";251;1
"Unit";"Zergling";"Larva";252;1
"Unit";"Zergling";"Larva";253;1
"Unit";"Zergling";"Larva";254;1
"Unit";"Zergling";"Larva";255;1
"Unit";"Zergling";"Larva";256;1
"Unit";"Zergling";"Larva";257;1
"Unit";"Zergling";"Larva";258;1
"Unit";"Zergling";"Larva";259;1
"Unit";"Zergling";"Larva";260;1
"Unit";"Zergling";"Larva";261;1
"Unit";"Zergling";"Larva";262;1
"Unit";"Zergling";"Larva";263;1
"Unit";"Zergling";"Larva";264;1
"Unit";"Baneling";"Zergling";265;0
"Unit";"Baneling";"Zergling";265;0
"Unit";"Overlord";"Larva";265;0
"Unit";"Zergling";"Larva";265;1
"Unit";"Zergling";"Larva";266;1
"Unit";"Zergling";"Larva";267;1
"Unit";"Zergling";"Larva";268;1
"Unit";"Zergling";"Larva";269;1
"Unit";"Zergling";"Larva";270;1
"Unit";"Zergling";"Larva";271;1
"Unit";"Zergling";"Larva";272;1
"Unit";"Zergling";"Larva";273;1
"Unit";"Zergling";"Larva";274;1
"Building";"InfestationPit";NA;275;0
"Unit";"Zergling";"Larva";275;1
"Unit";"Zergling";"Larva";276;1
"Unit";"Overlord";"Larva";277;0
"Unit";"Zergling";"Larva";277;1
"Unit";"Zergling";"Larva";278;1
"Unit";"Zergling";"Larva";279;1
"Unit";"Zergling";"Larva";280;1
"Unit";"Zergling";"Larva";281;1
"Unit";"Zergling";"Larva";282;1
"Unit";"Zergling";"Larva";283;1
"Unit";"Zergling";"Larva";284;1
"Unit";"Zergling";"Larva";285;1
"Unit";"Zergling";"Larva";286;1
"Unit";"Zergling";"Larva";287;1
"Unit";"Zergling";"Larva";288;1
"Unit";"Zergling";"Larva";289;1
"Unit";"Zergling";"Larva";290;1
"Unit";"Zergling";"Larva";291;1
"Unit";"Zergling";"Larva";292;1
"Unit";"Zergling";"Larva";293;1
"Unit";"Zergling";"Larva";294;1
"Unit";"Zergling";"Larva";295;1
"Unit";"Zergling";"Larva";296;1
"Unit";"Baneling";"Zergling";297;0
"Unit";"Baneling";"Zergling";297;0
"Unit";"Baneling";"Zergling";297;0
"Unit";"Baneling";"Zergling";297;0
"Unit";"Baneling";"Zergling";297;0
"Unit";"Baneling";"Zergling";297;0
"Unit";"Baneling";"Zergling";297;0
"Unit";"Baneling";"Zergling";297;0
"Unit";"Baneling";"Zergling";297;0
"Unit";"Baneling";"Zergling";297;0
"Unit";"Queen";"Hatchery";300;2
"Building";"Hatchery";NA;302;0
"Building";"Spire";NA;302;0
"Building";"CreepTumor";NA;302;0
"Building";"Extractor";NA;305;0
"Building";"CreepTumorQueen";NA;305;0
"Building";"Hatchery";NA;305;0
"Unit";"Zergling";"Larva";305;1
"Unit";"Zergling";"Larva";306;1
"Unit";"Hydralisk";"Larva";307;2
"Unit";"Hydralisk";"Larva";309;2
"Unit";"Hydralisk";"Larva";311;2
"Building";"CreepTumor";NA;313;0
"Unit";"Zergling";"Larva";313;1
"Unit";"Zergling";"Larva";314;1
"Unit";"Zergling";"Larva";315;1
"Unit";"Zergling";"Larva";316;1
"Unit";"Zergling";"Larva";317;1
"Unit";"Zergling";"Larva";318;1
"Unit";"Zergling";"Larva";319;1
"Unit";"Zergling";"Larva";320;1
"Unit";"Zergling";"Larva";321;1
"Unit";"Zergling";"Larva";322;1
"Unit";"Zergling";"Larva";323;1
"Unit";"Zergling";"Larva";324;1
"Unit";"Zergling";"Larva";325;1
"Unit";"Zergling";"Larva";326;1
"Unit";"Zergling";"Larva";327;1
"Unit";"Zergling";"Larva";328;1
"Unit";"Zergling";"Larva";329;1
"Unit";"Zergling";"Larva";330;1
"Unit";"Zergling";"Larva";331;1
"Unit";"Zergling";"Larva";332;1
"Unit";"Zergling";"Larva";333;1
"Unit";"Zergling";"Larva";334;1
"Unit";"Zergling";"Larva";335;1
"Unit";"Zergling";"Larva";336;1
"Unit";"Zergling";"Larva";337;1
"Unit";"Zergling";"Larva";338;1
"Unit";"Zergling";"Larva";339;1
"Unit";"Zergling";"Larva";340;1
"Unit";"Zergling";"Larva";341;1
"Unit";"Zergling";"Larva";342;1
"Unit";"Baneling";"Zergling";343;0
"Unit";"Baneling";"Zergling";343;0
"Unit";"Baneling";"Zergling";343;0
"Unit";"Baneling";"Zergling";343;0
"Unit";"Baneling";"Zergling";343;0
"Unit";"Baneling";"Zergling";343;0
"Unit";"Baneling";"Zergling";343;0
"Unit";"Baneling";"Zergling";343;0
"Unit";"Baneling";"Zergling";343;0
"Unit";"Baneling";"Zergling";343;0
"Unit";"Baneling";"Zergling";343;0
"Unit";"Baneling";"Zergling";343;0
"Unit";"Baneling";"Zergling";343;0
"Unit";"Baneling";"Zergling";343;0
"Unit";"Baneling";"Zergling";343;0
"Unit";"Baneling";"Zergling";343;0
"Unit";"Baneling";"Zergling";343;0
"Unit";"Baneling";"Zergling";343;0
"Unit";"Zergling";"Larva";343;1
"Unit";"Zergling";"Larva";344;1
"Unit";"Zergling";"Larva";345;1
"Unit";"Zergling";"Larva";346;1
"Unit";"Zergling";"Larva";347;1
"Unit";"Zergling";"Larva";348;1
"Unit";"Zergling";"Larva";349;1
"Unit";"Zergling";"Larva";350;1
"Unit";"Zergling";"Larva";351;1
"Unit";"Zergling";"Larva";352;1
"Unit";"Zergling";"Larva";353;1
"Unit";"Zergling";"Larva";354;1
"Unit";"Zergling";"Larva";355;1
"Unit";"Zergling";"Larva";356;1
"Unit";"Zergling";"Larva";357;1
"Unit";"Zergling";"Larva";358;1
"Unit";"Overlord";"Larva";359;0
"Unit";"Overlord";"Larva";359;0
"Building";"CreepTumor";NA;365;0
"Unit";"Overlord";"Larva";365;0
"Building";"CreepTumor";NA;365;0
"Unit";"Overlord";"Larva";365;0
"Unit";"Zergling";"Larva";365;1
"Unit";"Zergling";"Larva";366;1
"Unit";"Zergling";"Larva";367;1
"Unit";"Zergling";"Larva";368;1
"Unit";"Zergling";"Larva";369;1
"Unit";"Zergling";"Larva";370;1
"Unit";"Zergling";"Larva";371;1
"Unit";"Zergling";"Larva";372;1
"Unit";"Zergling";"Larva";373;1
"Unit";"Zergling";"Larva";374;1
"Unit";"Zergling";"Larva";375;1
"Unit";"Zergling";"Larva";376;1
"Unit";"Zergling";"Larva";377;1
"Unit";"Zergling";"Larva";378;1
"Unit";"Zergling";"Larva";379;1
"Unit";"Zergling";"Larva";380;1
"Unit";"Zergling";"Larva";381;1
"Unit";"Zergling";"Larva";382;1
"Unit";"Baneling";"Zergling";383;0
"Unit";"Baneling";"Zergling";383;0
"Unit";"Baneling";"Zergling";383;0
"Unit";"Baneling";"Zergling";383;0
"Unit";"Baneling";"Zergling";383;0
"Unit";"Baneling";"Zergling";383;0
"Unit";"Baneling";"Zergling";383;0
"Unit";"Baneling";"Zergling";383;0
"Unit";"Baneling";"Zergling";383;0
"Unit";"Baneling";"Zergling";383;0
"Unit";"Baneling";"Zergling";383;0
"Unit";"Baneling";"Zergling";383;0
"Unit";"Baneling";"Zergling";383;0
"Unit";"Baneling";"Zergling";383;0
"Unit";"Baneling";"Zergling";383;0
"Unit";"Baneling";"Zergling";383;0
"Unit";"Baneling";"Zergling";383;0
"Unit";"Zergling";"Larva";383;1
"Unit";"Zergling";"Larva";384;1
"Unit";"Zergling";"Larva";385;1
"Unit";"Zergling";"Larva";386;1
"Unit";"Zergling";"Larva";387;1
"Unit";"Zergling";"Larva";388;1
"Unit";"Zergling";"Larva";389;1
"Unit";"Zergling";"Larva";390;1
"Unit";"Zergling";"Larva";391;1
"Unit";"Zergling";"Larva";392;1
"Unit";"Zergling";"Larva";393;1
"Unit";"Zergling";"Larva";394;1
"Unit";"Zergling";"Larva";395;1
"Unit";"Zergling";"Larva";396;1
"Unit";"Zergling";"Larva";397;1
"Unit";"Zergling";"Larva";398;1
"Unit";"Zergling";"Larva";399;1
"Unit";"Zergling";"Larva";400;1
"Unit";"Zergling";"Larva";401;1
"Unit";"Zergling";"Larva";402;1
"Unit";"Zergling";"Larva";403;1
"Unit";"Zergling";"Larva";404;1
"Unit";"Zergling";"Larva";405;1
"Unit";"Zergling";"Larva";406;1
"Building";"CreepTumorQueen";NA;407;0
"Unit";"Zergling";"Larva";407;1
"Unit";"Zergling";"Larva";408;1
"Unit";"Zergling";"Larva";409;1
"Unit";"Zergling";"Larva";410;1
"Unit";"Zergling";"Larva";411;1
"Unit";"Zergling";"Larva";412;1
"Unit";"Zergling";"Larva";413;1
"Unit";"Zergling";"Larva";414;1
"Unit";"Zergling";"Larva";415;1
"Unit";"Zergling";"Larva";416;1
"Unit";"Zergling";"Larva";417;1
"Unit";"Zergling";"Larva";418;1
"Unit";"Zergling";"Larva";419;1
"Unit";"Zergling";"Larva";420;1
"Unit";"Zergling";"Larva";421;1
"Unit";"Zergling";"Larva";422;1
"Building";"CreepTumorQueen";NA;423;0
"Unit";"Zergling";"Larva";423;1
"Unit";"Zergling";"Larva";424;1
"Unit";"Hydralisk";"Larva";425;2
"Unit";"Baneling";"Zergling";427;0
"Unit";"Baneling";"Zergling";427;0
"Unit";"Baneling";"Zergling";427;0
"Unit";"Baneling";"Zergling";427;0
"Unit";"Baneling";"Zergling";427;0
"Unit";"Baneling";"Zergling";427;0
"Unit";"Hydralisk";"Larva";427;2
"Unit";"Hydralisk";"Larva";429;2
"Unit";"Hydralisk";"Larva";431;2
"Unit";"Hydralisk";"Larva";433;2
"Unit";"Zergling";"Larva";435;1
"Unit";"Zergling";"Larva";436;1
"Unit";"Zergling";"Larva";437;1
"Unit";"Zergling";"Larva";438;1
"Unit";"Zergling";"Larva";439;1
"Unit";"Zergling";"Larva";440;1
"Unit";"Zergling";"Larva";441;1
"Unit";"Zergling";"Larva";442;1
"Unit";"Zergling";"Larva";443;1
"Unit";"Zergling";"Larva";444;1
"Unit";"Hydralisk";"Larva";445;2
"Unit";"Hydralisk";"Larva";447;2
"Unit";"Queen";"Hatchery";449;2
"Unit";"Baneling";"Zergling";451;0
"Unit";"Baneling";"Zergling";451;0
"Unit";"Baneling";"Zergling";451;0
"Unit";"Baneling";"Zergling";451;0
"Unit";"Baneling";"Zergling";451;0
"Unit";"Baneling";"Zergling";451;0
"Unit";"Baneling";"Zergling";451;0
"Unit";"Baneling";"Zergling";451;0
"Unit";"Baneling";"Zergling";451;0
"Unit";"Baneling";"Zergling";451;0
"Unit";"Baneling";"Zergling";451;0
"Unit";"Baneling";"Zergling";451;0
"Unit";"Baneling";"Zergling";451;0
"Unit";"Baneling";"Zergling";451;0
"Unit";"Baneling";"Zergling";451;0
"Unit";"Baneling";"Zergling";451;0
"Unit";"Baneling";"Zergling";451;0
"Unit";"Baneling";"Zergling";451;0
"Unit";"Zergling";"Larva";451;1
"Unit";"Zergling";"Larva";452;1
"Building";"Hatchery";NA;454;0
"Building";"CreepTumor";NA;454;0
"Building";"CreepTumorQueen";NA;454;0
"Building";"CreepTumorQueen";NA;454;0
"Building";"CreepTumor";NA;455;0
"Unit";"Overlord";"Larva";456;0
"Building";"CreepTumor";NA;456;0
"Building";"CreepTumor";NA;456;0
"Unit";"Corruptor";"Larva";456;2
"Unit";"Corruptor";"Larva";458;2
"Unit";"Corruptor";"Larva";460;2
"Unit";"Corruptor";"Larva";462;2
"Unit";"Corruptor";"Larva";464;2
"Unit";"Overlord";"Larva";466;0
"Building";"Hatchery";NA;466;0
"Unit";"Zergling";"Larva";466;1
"Unit";"Zergling";"Larva";467;1
"Unit";"Zergling";"Larva";468;1
"Unit";"Zergling";"Larva";469;1
"Unit";"Zergling";"Larva";470;1
"Unit";"Zergling";"Larva";471;1
"Unit";"Zergling";"Larva";472;1
"Unit";"Zergling";"Larva";473;1
"Unit";"Zergling";"Larva";474;1
"Unit";"Zergling";"Larva";475;1
"Unit";"Zergling";"Larva";476;1
"Unit";"Zergling";"Larva";477;1
"Unit";"Zergling";"Larva";478;1
"Unit";"Zergling";"Larva";479;1
"Unit";"Zergling";"Larva";480;1
"Unit";"Zergling";"Larva";481;1
"Unit";"Zergling";"Larva";482;1
"Unit";"Zergling";"Larva";483;1
"Unit";"Zergling";"Larva";484;1
"Unit";"Zergling";"Larva";485;1
"Unit";"Zergling";"Larva";486;1
"Unit";"Zergling";"Larva";487;1
"Unit";"Zergling";"Larva";488;1
"Unit";"Zergling";"Larva";489;1
"Unit";"Zergling";"Larva";490;1
"Unit";"Zergling";"Larva";491;1
"Unit";"Zergling";"Larva";492;1
"Unit";"Zergling";"Larva";493;1
"Unit";"Zergling";"Larva";494;1
"Unit";"Zergling";"Larva";495;1
"Unit";"Zergling";"Larva";496;1
"Unit";"Zergling";"Larva";497;1
"Unit";"Zergling";"Larva";498;1
"Unit";"Zergling";"Larva";499;1
"Unit";"Zergling";"Larva";500;1
"Unit";"Zergling";"Larva";501;1
"Unit";"Zergling";"Larva";502;1
"Unit";"Zergling";"Larva";503;1
"Unit";"Zergling";"Larva";504;1
"Unit";"Zergling";"Larva";505;1
"Building";"CreepTumor";NA;506;0
"Building";"CreepTumorQueen";NA;506;0
"Building";"CreepTumorQueen";NA;514;0
"Building";"CreepTumor";NA;515;0
"Building";"CreepTumor";NA;515;0
"Building";"SporeCrawler";NA;515;0
"Unit";"Corruptor";"Larva";515;2
"Unit";"Corruptor";"Larva";517;2
"Unit";"Corruptor";"Larva";519;2
"Building";"SporeCrawler";NA;521;0
"Unit";"Overlord";"Larva";521;0
"Building";"SporeCrawler";NA;521;0
"Building";"CreepTumor";NA;521;0
"Building";"SporeCrawler";NA;521;0
"Building";"CreepTumor";NA;521;0
"Unit";"Overlord";"Larva";521;0
"Building";"SporeCrawler";NA;521;0
"Building";"SporeCrawler";NA;521;0
"Building";"SporeCrawler";NA;521;0
"Building";"SporeCrawler";NA;521;0
"Building";"CreepTumor";NA;521;0
"Unit";"Viper";"Larva";521;3
"Building";"Extractor";NA;524;0
"Building";"SporeCrawler";NA;524;0
"Building";"SporeCrawler";NA;526;0
"Building";"SporeCrawler";NA;526;0
"Building";"SporeCrawler";NA;528;0
"Building";"SporeCrawler";NA;528;0
"Building";"CreepTumor";NA;528;0
"Building";"CreepTumor";NA;528;0
"Building";"CreepTumor";NA;528;0
"Building";"Hatchery";NA;528;0
"Building";"SporeCrawler";NA;529;0
"Building";"SporeCrawler";NA;529;0
"Building";"SporeCrawler";NA;531;0
"Building";"SporeCrawler";NA;531;0
"Unit";"Corruptor";"Larva";531;2
"Building";"CreepTumor";NA;533;0
"Building";"CreepTumor";NA;533;0
"Building";"CreepTumor";NA;533;0
"Building";"SpineCrawler";NA;533;0
"Building";"SpineCrawler";NA;533;0
"Unit";"Corruptor";"Larva";533;2
"Building";"SpineCrawler";NA;535;0
"Building";"SporeCrawler";NA;536;0
"Building";"SporeCrawler";NA;536;0
"Unit";"Corruptor";"Larva";536;2
"Unit";"Corruptor";"Larva";538;2
"Building";"SporeCrawler";NA;556;0
"Building";"SporeCrawler";NA;556;0
"Building";"SporeCrawler";NA;556;0
"Building";"SporeCrawler";NA;556;0
"Building";"SporeCrawler";NA;556;0
"Building";"UltraliskCavern";NA;556;0
"Building";"Spire";NA;556;0
"Building";"SporeCrawler";NA;556;0
"Building";"CreepTumor";NA;556;0
"Building";"SporeCrawler";NA;556;0
"Building";"SporeCrawler";NA;556;0
"Building";"SporeCrawler";NA;556;0
"Building";"SporeCrawler";NA;556;0
"Unit";"Zergling";"Larva";556;1
"Unit";"Zergling";"Larva";557;1
"Unit";"Zergling";"Larva";558;1
"Unit";"Zergling";"Larva";559;1
"Unit";"Zergling";"Larva";560;1
"Unit";"Zergling";"Larva";561;1
"Unit";"Zergling";"Larva";562;1
"Unit";"Zergling";"Larva";563;1
"Unit";"Zergling";"Larva";564;1
"Unit";"Zergling";"Larva";565;1
"Unit";"Zergling";"Larva";566;1
"Unit";"Zergling";"Larva";567;1
"Unit";"Zergling";"Larva";568;1
"Unit";"Zergling";"Larva";569;1
"Unit";"Zergling";"Larva";570;1
"Unit";"Zergling";"Larva";571;1
"Unit";"Zergling";"Larva";572;1
"Unit";"Zergling";"Larva";573;1
"Building";"SporeCrawler";NA;574;0
"Building";"Extractor";NA;574;0
"Building";"Extractor";NA;574;0
"Unit";"Corruptor";"Larva";574;2
"Unit";"Corruptor";"Larva";576;2
"Unit";"Corruptor";"Larva";578;2
"Building";"SporeCrawler";NA;580;0
"Building";"SpineCrawler";NA;580;0
"Building";"SpineCrawler";NA;581;0
"Building";"SporeCrawler";NA;583;0
"Unit";"Zergling";"Larva";583;1
"Unit";"Zergling";"Larva";584;1
"Unit";"Zergling";"Larva";585;1
"Unit";"Zergling";"Larva";586;1
"Unit";"Zergling";"Larva";587;1
"Unit";"Zergling";"Larva";588;1
"Unit";"Zergling";"Larva";589;1
"Unit";"Zergling";"Larva";590;1
"Unit";"Zergling";"Larva";591;1
"Unit";"Zergling";"Larva";592;1
"Unit";"Corruptor";"Larva";593;2
"Unit";"Corruptor";"Larva";595;2
"Unit";"Zergling";"Larva";597;1
"Unit";"Zergling";"Larva";598;1
"Building";"SporeCrawler";NA;599;0
"Building";"SporeCrawler";NA;599;0
"Building";"SporeCrawler";NA;599;0
"Building";"SporeCrawler";NA;599;0
"Building";"SporeCrawler";NA;599;0
"Building";"SporeCrawler";NA;599;0
"Unit";"Viper";"Larva";599;3
"Unit";"Viper";"Larva";602;3
"Unit";"Corruptor";"Larva";605;2
"Unit";"Corruptor";"Larva";607;2
"Building";"CreepTumor";NA;609;0
"Building";"CreepTumor";NA;609;0
"Unit";"Overlord";"Larva";609;0
"Unit";"Zergling";"Larva";609;1
"Unit";"Zergling";"Larva";610;1
"Unit";"Zergling";"Larva";611;1
"Unit";"Zergling";"Larva";612;1
"Unit";"Zergling";"Larva";613;1
"Unit";"Zergling";"Larva";614;1
"Unit";"Zergling";"Larva";615;1
"Unit";"Zergling";"Larva";616;1
"Unit";"Zergling";"Larva";617;1
"Unit";"Zergling";"Larva";618;1
"Unit";"Zergling";"Larva";619;1
"Unit";"Zergling";"Larva";620;1
"Unit";"Zergling";"Larva";621;1
"Unit";"Zergling";"Larva";622;1
"Unit";"Zergling";"Larva";623;1
"Unit";"Zergling";"Larva";624;1
"Unit";"Zergling";"Larva";625;1
"Unit";"Zergling";"Larva";626;1
"Unit";"Zergling";"Larva";627;1
"Unit";"Zergling";"Larva";628;1
"Unit";"Zergling";"Larva";629;1
"Unit";"Zergling";"Larva";630;1
"Unit";"Zergling";"Larva";631;1
"Unit";"Zergling";"Larva";632;1
"Unit";"Zergling";"Larva";633;1
"Unit";"Zergling";"Larva";634;1
"Unit";"Zergling";"Larva";635;1
"Unit";"Zergling";"Larva";636;1
"Unit";"Zergling";"Larva";637;1
"Unit";"Zergling";"Larva";638;1
"Building";"SporeCrawler";NA;645;0
"Building";"SporeCrawler";NA;645;0
"Building";"SporeCrawler";NA;645;0
"Building";"SporeCrawler";NA;645;0
"Building";"SporeCrawler";NA;645;0
"Building";"SporeCrawler";NA;645;0
"Building";"SporeCrawler";NA;645;0
"Upgrade";"ChitinousPlating";"UltraliskCavern";645;0
"Unit";"Zergling";"Larva";645;1
"Unit";"Zergling";"Larva";646;1
"Unit";"Zergling";"Larva";647;1
"Unit";"Zergling";"Larva";648;1
"Unit";"Zergling";"Larva";649;1
"Unit";"Zergling";"Larva";650;1
"Unit";"Zergling";"Larva";651;1
"Unit";"Zergling";"Larva";652;1
"Unit";"Corruptor";"Larva";653;2
"Unit";"Corruptor";"Larva";655;2
"Unit";"Corruptor";"Larva";657;2
"Building";"CreepTumor";NA;659;0
"Building";"EvolutionChamber";NA;659;0
"Building";"EvolutionChamber";NA;659;0
"Building";"SpineCrawler";NA;659;0
"Building";"SpineCrawler";NA;659;0
"Building";"SpineCrawler";NA;659;0
"Unit";"Zergling";"Larva";659;1
"Unit";"Zergling";"Larva";660;1
"Unit";"Zergling";"Larva";661;1
"Unit";"Zergling";"Larva";662;1
"Unit";"Zergling";"Larva";663;1
"Unit";"Zergling";"Larva";664;1
"Unit";"Zergling";"Larva";665;1
"Unit";"Zergling";"Larva";666;1
"Unit";"Zergling";"Larva";667;1
"Unit";"Zergling";"Larva";668;1
"Unit";"Zergling";"Larva";669;1
"Unit";"Zergling";"Larva";670;1
"Unit";"Baneling";"Zergling";671;0
"Unit";"Baneling";"Zergling";671;0
"Unit";"Baneling";"Zergling";671;0
"Unit";"Baneling";"Zergling";671;0
"Building";"Hatchery";NA;671;0
"Building";"CreepTumor";NA;671;0
"Building";"CreepTumor";NA;671;0
"Upgrade";"Burrow";"Hatchery";672;0
"Building";"CreepTumor";NA;672;0
"Building";"CreepTumor";NA;672;0
"Building";"CreepTumor";NA;672;0
"Building";"CreepTumorQueen";NA;672;0
"Building";"SporeCrawler";NA;675;0
"Building";"SporeCrawler";NA;677;0
"Unit";"Baneling";"Zergling";677;0
"Unit";"Baneling";"Zergling";677;0
"Unit";"Baneling";"Zergling";677;0
"Unit";"Baneling";"Zergling";677;0
"Unit";"Baneling";"Zergling";677;0
"Unit";"Baneling";"Zergling";677;0
"Unit";"Baneling";"Zergling";677;0
"Unit";"Baneling";"Zergling";677;0
"Building";"CreepTumor";NA;678;0
"Building";"CreepTumor";NA;678;0
"Building";"SporeCrawler";NA;678;0
"Building";"SporeCrawler";NA;678;0
"Building";"SporeCrawler";NA;678;0
"Building";"CreepTumorQueen";NA;678;0
"Building";"CreepTumorQueen";NA;685;0
"Building";"CreepTumor";NA;685;0
"Unit";"Corruptor";"Larva";685;2
"Unit";"Corruptor";"Larva";687;2
"Unit";"Corruptor";"Larva";689;2
"Unit";"Corruptor";"Larva";691;2
"Unit";"Corruptor";"Larva";693;2
"Unit";"Corruptor";"Larva";695;2
"Unit";"Corruptor";"Larva";697;2
"Unit";"Corruptor";"Larva";699;2
"Unit";"Corruptor";"Larva";701;2
"Building";"CreepTumorQueen";NA;703;0
"Unit";"Corruptor";"Larva";703;2
"Unit";"Corruptor";"Larva";705;2
"Unit";"Corruptor";"Larva";707;2
"Unit";"Corruptor";"Larva";709;2
"Unit";"Corruptor";"Larva";711;2
"Unit";"Corruptor";"Larva";713;2
"Unit";"Corruptor";"Larva";715;2
"Unit";"Corruptor";"Larva";717;2
"Unit";"Corruptor";"Larva";719;2
"Unit";"Corruptor";"Larva";721;2
"Unit";"Zergling";"Larva";723;1
"Unit";"Zergling";"Larva";724;1
"Unit";"Zergling";"Larva";725;1
"Unit";"Zergling";"Larva";726;1
"Unit";"Zergling";"Larva";727;1
"Unit";"Zergling";"Larva";728;1
"Unit";"Zergling";"Larva";729;1
"Unit";"Zergling";"Larva";730;1
"Unit";"Zergling";"Larva";731;1
"Unit";"Zergling";"Larva";732;1
"Unit";"Zergling";"Larva";733;1
"Unit";"Zergling";"Larva";734;1
"Unit";"Zergling";"Larva";735;1
"Unit";"Zergling";"Larva";736;1
"Unit";"Zergling";"Larva";737;1
"Unit";"Zergling";"Larva";738;1
"Unit";"Zergling";"Larva";739;1
"Unit";"Zergling";"Larva";740;1
"Unit";"Zergling";"Larva";741;1
"Unit";"Zergling";"Larva";742;1
"Unit";"Zergling";"Larva";743;1
"Unit";"Zergling";"Larva";744;1
"Unit";"Zergling";"Larva";745;1
"Unit";"Zergling";"Larva";746;1
"Unit";"Zergling";"Larva";747;1
"Unit";"Zergling";"Larva";748;1
"Unit";"Zergling";"Larva";749;1
"Unit";"Zergling";"Larva";750;1
"Unit";"Zergling";"Larva";751;1
"Unit";"Zergling";"Larva";752;1
"Unit";"Zergling";"Larva";753;1
"Unit";"Zergling";"Larva";754;1
"Unit";"Zergling";"Larva";755;1
"Unit";"Zergling";"Larva";756;1
"Unit";"Zergling";"Larva";757;1
"Unit";"Zergling";"Larva";758;1
"Unit";"Zergling";"Larva";759;1
"Unit";"Zergling";"Larva";760;1
"Building";"Extractor";NA;761;0
"Building";"Extractor";NA;761;0
"Building";"Extractor";NA;763;0
"Building";"Extractor";NA;763;0
"Building";"Hatchery";NA;765;0
"Unit";"Zergling";"Larva";765;1
"Unit";"Zergling";"Larva";766;1
"Building";"CreepTumor";NA;767;0
"Building";"CreepTumor";NA;767;0
"Building";"CreepTumor";NA;767;0
"Building";"SpineCrawler";NA;767;0
"Building";"SporeCrawler";NA;767;0
"Unit";"Zergling";"Larva";767;1
"Unit";"Zergling";"Larva";768;1
"Unit";"Zergling";"Larva";769;1
"Unit";"Zergling";"Larva";770;1
"Unit";"Zergling";"Larva";771;1
"Unit";"Zergling";"Larva";772;1
"Unit";"Zergling";"Larva";773;1
"Unit";"Zergling";"Larva";774;1
"Unit";"Zergling";"Larva";775;1
"Unit";"Zergling";"Larva";776;1
"Building";"CreepTumor";NA;777;0
"Building";"CreepTumor";NA;777;0
"Unit";"Zergling";"Larva";782;1
"Unit";"Zergling";"Larva";783;1
"Unit";"Zergling";"Larva";784;1
"Unit";"Zergling";"Larva";785;1
"Building";"CreepTumor";NA;786;0
"Unit";"Baneling";"Zergling";786;0
"Unit";"Baneling";"Zergling";786;0
"Unit";"Baneling";"Zergling";786;0
"Unit";"Baneling";"Zergling";786;0
"Unit";"Baneling";"Zergling";786;0
"Unit";"Baneling";"Zergling";786;0
"Unit";"Ultralisk";"Larva";786;6
"Unit";"Viper";"Larva";792;3
"Unit";"Viper";"Larva";795;3
"Unit";"Viper";"Larva";798;3
"Unit";"Zergling";"Larva";801;1
"Unit";"Zergling";"Larva";802;1
"Unit";"Zergling";"Larva";803;1
"Unit";"Zergling";"Larva";804;1
"Unit";"Zergling";"Larva";805;1
"Unit";"Zergling";"Larva";806;1
"Unit";"Zergling";"Larva";807;1
"Unit";"Zergling";"Larva";808;1
"Unit";"Zergling";"Larva";809;1
"Unit";"Zergling";"Larva";810;1
"Unit";"Zergling";"Larva";811;1
"Unit";"Zergling";"Larva";812;1
"Building";"CreepTumor";NA;813;0
"Building";"CreepTumor";NA;813;0
"Building";"CreepTumor";NA;813;0
"Unit";"Zergling";"Larva";813;1
"Unit";"Zergling";"Larva";814;1
"Unit";"Zergling";"Larva";815;1
"Unit";"Zergling";"Larva";816;1
"Unit";"Zergling";"Larva";817;1
"Unit";"Zergling";"Larva";818;1
"Unit";"Zergling";"Larva";819;1
"Unit";"Zergling";"Larva";820;1
"Unit";"Zergling";"Larva";821;1
"Unit";"Zergling";"Larva";822;1
"Unit";"Zergling";"Larva";823;1
"Unit";"Zergling";"Larva";824;1
"Unit";"Overlord";"Larva";825;0
"Unit";"Overlord";"Larva";825;0
"Unit";"Overlord";"Larva";825;0
"Unit";"Overlord";"Larva";825;0
"Unit";"Overlord";"Larva";825;0
"Unit";"Zergling";"Larva";825;1
"Unit";"Zergling";"Larva";826;1
"Unit";"Zergling";"Larva";827;1
"Unit";"Zergling";"Larva";828;1
"Unit";"Zergling";"Larva";829;1
"Unit";"Zergling";"Larva";830;1
"Unit";"Zergling";"Larva";831;1
"Unit";"Zergling";"Larva";832;1
"Unit";"Zergling";"Larva";833;1
"Unit";"Zergling";"Larva";834;1
"Unit";"Zergling";"Larva";835;1
"Unit";"Zergling";"Larva";836;1
"Unit";"Zergling";"Larva";837;1
"Unit";"Zergling";"Larva";838;1
"Unit";"Zergling";"Larva";839;1
"Unit";"Zergling";"Larva";840;1
"Unit";"Zergling";"Larva";841;1
"Unit";"Zergling";"Larva";842;1
"Unit";"Zergling";"Larva";843;1
"Unit";"Zergling";"Larva";844;1
"Unit";"Zergling";"Larva";845;1
"Unit";"Zergling";"Larva";846;1
"Unit";"Zergling";"Larva";847;1
"Unit";"Zergling";"Larva";848;1
"Unit";"Zergling";"Larva";849;1
"Unit";"Zergling";"Larva";850;1
"Unit";"Zergling";"Larva";851;1
"Unit";"Zergling";"Larva";852;1
"Unit";"Zergling";"Larva";853;1
"Unit";"Zergling";"Larva";854;1
"Building";"SporeCrawler";NA;855;0
"Building";"SporeCrawler";NA;855;0
"Building";"SporeCrawler";NA;855;0
"Building";"SporeCrawler";NA;855;0
"Unit";"Zergling";"Larva";855;1
"Unit";"Zergling";"Larva";856;1
"Unit";"Zergling";"Larva";857;1
"Unit";"Zergling";"Larva";858;1
"Unit";"Zergling";"Larva";859;1
"Unit";"Zergling";"Larva";860;1
"Unit";"Zergling";"Larva";861;1
"Unit";"Zergling";"Larva";862;1
"Unit";"Zergling";"Larva";863;1
"Unit";"Zergling";"Larva";864;1
"Building";"SporeCrawler";NA;865;0
"Upgrade";"SprayZerg";NA;865;0
"Upgrade";"SprayZerg";NA;865;0
"Upgrade";"SprayZerg";NA;865;0
"Upgrade";"zerglingmovementspeed";NA;865;0
"Upgrade";"SprayZerg";NA;865;0
"Upgrade";"EvolveGroovedSpines";NA;865;0
"Upgrade";"SprayZerg";NA;865;0
"Upgrade";"ZergMissileWeaponsLevel1";NA;865;0
"Upgrade";"SprayZerg";NA;865;0
"Upgrade";"EvolveMuscularAugments";NA;865;0
"Upgrade";"CentrificalHooks";NA;865;0
"Upgrade";"ZergMeleeWeaponsLevel1";NA;865;0
"Upgrade";"SprayZerg";NA;865;0
"Upgrade";"SprayZerg";NA;865;0
"Upgrade";"overlordspeed";NA;865;0
"Upgrade";"ZergGroundArmorsLevel1";NA;865;0
"Upgrade";"SprayZerg";NA;865;0
"Upgrade";"SprayZerg";NA;865;0
"Upgrade";"ZergMeleeWeaponsLevel2";NA;865;0
"Upgrade";"SprayZerg";NA;865;0
"Upgrade";"SprayZerg";NA;865;0
"Upgrade";"SprayZerg";NA;865;0
"Upgrade";"SprayZerg";NA;865;0
"Upgrade";"SprayZerg";NA;865;0
"Upgrade";"SprayZerg";NA;865;0
"Upgrade";"zerglingattackspeed";NA;865;0
"Upgrade";"ZergFlyerWeaponsLevel1";NA;865;0
"Upgrade";"ZergGroundArmorsLevel2";NA;865;0
"Upgrade";"SprayZerg";NA;865;0
"Upgrade";"ZergMeleeWeaponsLevel3";NA;865;0
"Upgrade";"ZergFlyerWeaponsLevel2";NA;865;0
"Upgrade";"ZergMissileWeaponsLevel2";NA;865;0
"Upgrade";"ZergGroundArmorsLevel3";NA;865;0
"Upgrade";"SprayZerg";NA;865;0
"Upgrade";"ZergFlyerArmorsLevel1";NA;865;0
"Upgrade";"SprayZerg";NA;865;0
"Upgrade";"ZergFlyerArmorsLevel2";NA;865;0
"Upgrade";"ZergMissileWeaponsLevel3";NA;865;0
"Upgrade";"ZergFlyerWeaponsLevel3";NA;865;0
"Upgrade";"SprayZerg";NA;865;0
"Upgrade";"SprayZerg";NA;865;0
"Upgrade";"ZergFlyerArmorsLevel3";NA;865;0
"Upgrade";"SprayZerg";NA;865;0
