"Type";"UnitName";"OnBuilding";"TotalSupply";"Supply"
"Unit";"SCV";"Command Center";12;1
"Unit";"SCV";"Command Center";12;1
"Unit";"SCV";"Command Center";13;1
"Building";"SupplyDepot";NA;13;0
"Unit";"SCV";"Command Center";15;1
"Unit";"SCV";"Command Center";15;1
"Building";"Refinery";NA;15;0
"Unit";"SCV";"Command Center";16;1
"Building";"Barracks";NA;15;0
"Unit";"SCV";"Command Center";17;1
"Unit";"Reaper";"Barracks";18;1
"Unit";"SCV";"Command Center";19;1
"Unit";"SCV";"Command Center";20;1
"Unit";"Marine";"Barracks";20;1
"Building";"SupplyDepot";NA;20;0
"Unit";"SCV";"Command Center";23;1
"Unit";"Marine";"Barracks";23;1
"Unit";"SCV";"Command Center";24;1
"Building";"CommandCenter";NA;19;0
"Unit";"Marine";"Barracks";25;1
"Building";"Factory";NA;21;0
"Unit";"SCV";"Command Center";25;1
"Building";"Refinery";NA;25;0
"Unit";"SCV";"Command Center";27;1
"Building";"Barracks";NA;23;0
"Unit";"SCV";"Command Center";28;1
"Unit";"SCV";"Command Center";29;1
"Building";"BarracksTechLab";NA;29;0
"Building";"BarracksReactor";NA;27;0
"Unit";"SCV";"Command Center";29;1
"Unit";"Cyclone";"Factory";29;3
"Unit";"SCV";"Command Center";30;1
"Unit";"SCV";"Command Center";32;1
"Unit";"Marine";"Barracks";31;1
"Building";"EngineeringBay";NA;30;0
"Unit";"Marine";"Barracks";31;1
"Unit";"SCV";"Command Center";35;1
"Unit";"Marine";"Barracks";35;1
"Building";"SupplyDepot";NA;35;0
"Unit";"SCV";"Command Center";37;1
"Unit";"SCV";"Command Center";39;1
"Unit";"Marine";"Barracks";38;1
"Unit";"SCV";"Command Center";41;1
"Unit";"Marine";"Barracks";41;1
"Unit";"SCV";"Command Center";44;1
"Unit";"Marine";"Barracks";42;1
"Unit";"SCV";"Command Center";44;1
"Building";"SupplyDepot";NA;42;0
"Unit";"Marine";"Barracks";44;1
"Unit";"SCV";"Command Center";46;1
"Unit";"Marine";"Barracks";45;1
"Building";"Starport";NA;41;0
"Unit";"SCV";"Command Center";48;1
"Unit";"Marine";"Barracks";47;1
"Building";"FactoryReactor";NA;44;0
"Unit";"SCV";"Command Center";50;1
"Building";"SupplyDepot";NA;48;0
"Unit";"SCV";"Command Center";52;1
"Unit";"Marine";"Barracks";50;1
"Unit";"Marine";"Barracks";51;1
"Unit";"Marine";"Barracks";53;1
"Unit";"SCV";"Command Center";54;1
"Building";"SupplyDepot";NA;52;0
"Unit";"SCV";"Command Center";57;1
"Unit";"Marine";"Barracks";57;1
"Unit";"SCV";"Command Center";60;1
"Unit";"Marine";"Barracks";58;1
"Unit";"SCV";"Command Center";61;1
"Unit";"Marine";"Barracks";60;1
"Unit";"Medivac";"Starport";55;2
"Unit";"Medivac";"Starport";55;2
"Building";"SupplyDepot";NA;60;0
"Building";"Refinery";NA;60;0
"Unit";"SCV";"Command Center";63;1
"Unit";"Marine";"Barracks";64;1
"Unit";"Marine";"Barracks";64;1
"Upgrade";"Stimpack";"TechLab";42;0
"Unit";"Marine";"Barracks";65;1
"Building";"SupplyDepot";NA;64;0
"Building";"Barracks";NA;57;0
"Unit";"SCV";"Command Center";71;1
"Unit";"SCV";"Command Center";71;1
"Upgrade";"TerranInfantryWeaponsLevel1";"EngineeringBay";48;0
"Unit";"Marine";"Barracks";71;1
"Unit";"Marine";"Barracks";72;1
"Unit";"Marine";"Barracks";73;1
"Unit";"SCV";"Command Center";74;1
"Building";"Barracks";NA;63;0
"Unit";"SCV";"Command Center";76;1
"Building";"Barracks";NA;65;0
"Unit";"Marine";"Barracks";76;1
"Unit";"Marine";"Barracks";77;1
"Building";"EngineeringBay";NA;76;0
"Unit";"SCV";"Command Center";81;1
"Unit";"Marine";"Barracks";80;1
"Building";"SupplyDepot";NA;78;0
"Building";"BarracksReactor";NA;76;0
"Building";"SupplyDepot";NA;81;0
"Building";"Armory";NA;76;0
"Building";"Refinery";NA;85;0
"Building";"BarracksReactor";NA;81;0
"Unit";"Medivac";"Starport";85;2
"Building";"BarracksReactor";NA;83;0
"Unit";"Marine";"Barracks";85;1
"Unit";"Marine";"Barracks";85;1
"Unit";"Marine";"Barracks";85;1
"Unit";"Marine";"Barracks";85;1
"Unit";"Marine";"Barracks";85;1
"Unit";"SCV";"Command Center";85;1
"Unit";"SCV";"Command Center";85;1
"Unit";"Marine";"Barracks";87;1
"Unit";"Marine";"Barracks";87;1
"Unit";"Marine";"Barracks";87;1
"Unit";"Marine";"Barracks";87;1
"Unit";"Marine";"Barracks";87;1
"Unit";"Marine";"Barracks";91;1
"Building";"SupplyDepot";NA;91;0
"Unit";"Marine";"Barracks";93;1
"Unit";"Marine";"Barracks";94;1
"Unit";"Marine";"Barracks";94;1
"Unit";"Marine";"Barracks";98;1
"Unit";"Marine";"Barracks";98;1
"Unit";"Marine";"Barracks";98;1
"Building";"SupplyDepot";NA;96;0
"Unit";"Medivac";"Starport";94;2
"Building";"SupplyDepot";NA;100;0
"Unit";"Medivac";"Starport";94;2
"Unit";"Marine";"Barracks";103;1
"Unit";"Marine";"Barracks";103;1
"Unit";"Marine";"Barracks";103;1
"Unit";"Marine";"Barracks";103;1
"Unit";"Marine";"Barracks";103;1
"Building";"CommandCenter";NA;85;0
"Upgrade";"TerranInfantryArmorsLevel1";"EngineeringBay";85;0
"Unit";"Marine";"Barracks";106;1
"Building";"SupplyDepot";NA;106;0
"Unit";"SCV";"Command Center";116;1
"Unit";"SCV";"Command Center";116;1
"Unit";"Marine";"Barracks";116;1
"Building";"Barracks";NA;106;0
"Building";"Barracks";NA;110;0
"Building";"Barracks";NA;110;0
"Unit";"Marine";"Barracks";119;1
"Unit";"Marine";"Barracks";119;1
"Unit";"Marine";"Barracks";119;1
"Unit";"Marine";"Barracks";119;1
"Unit";"Marine";"Barracks";119;1
"Unit";"Marine";"Barracks";119;1
"Unit";"Marine";"Barracks";119;1
"Unit";"Marine";"Barracks";119;1
"Unit";"Marine";"Barracks";119;1
"Unit";"SCV";"Command Center";119;1
"Unit";"SCV";"Command Center";122;1
"Unit";"SCV";"Command Center";123;1
"Unit";"Marine";"Barracks";119;1
"Unit";"Marine";"Barracks";120;1
"Unit";"Marine";"Barracks";121;1
"Unit";"SCV";"Command Center";131;1
"Unit";"SCV";"Command Center";131;1
"Unit";"SCV";"Command Center";131;1
"Unit";"Marine";"Barracks";129;1
"Unit";"Marine";"Barracks";131;1
"Unit";"Marine";"Barracks";131;1
"Unit";"Medivac";"Starport";128;2
"Unit";"Medivac";"Starport";128;2
"Unit";"Marine";"Barracks";134;1
"Unit";"Marine";"Barracks";134;1
"Unit";"Marine";"Barracks";134;1
"Building";"BarracksReactor";NA;126;0
"Building";"BarracksReactor";NA;126;0
"Building";"BarracksReactor";NA;127;0
"Upgrade";"TerranInfantryWeaponsLevel2";"EngineeringBay";103;0
"Unit";"Marine";"Barracks";134;1
"Building";"SupplyDepot";NA;134;0
"Unit";"SCV";"Command Center";134;1
"Building";"SupplyDepot";NA;134;0
"Unit";"Marine";"Barracks";140;1
"Unit";"Marine";"Barracks";140;1
"Unit";"Marine";"Barracks";149;1
"Unit";"Marine";"Barracks";149;1
"Unit";"Marine";"Barracks";149;1
"Unit";"Marine";"Barracks";149;1
"Unit";"Marine";"Barracks";149;1
"Unit";"Marine";"Barracks";149;1
"Unit";"Marine";"Barracks";149;1
"Unit";"Marine";"Barracks";149;1
"Unit";"Marine";"Barracks";149;1
"Unit";"Marine";"Barracks";149;1
"Unit";"Marine";"Barracks";149;1
"Unit";"Marine";"Barracks";149;1
"Unit";"Marine";"Barracks";149;1
"Unit";"Marine";"Barracks";149;1
"Unit";"Marine";"Barracks";150;1
"Building";"SupplyDepot";NA;151;0
"Unit";"Marine";"Barracks";151;1
"Unit";"Marine";"Barracks";166;1
"Unit";"Marine";"Barracks";166;1
"Unit";"Marine";"Barracks";166;1
"Unit";"Marine";"Barracks";166;1
"Unit";"Marine";"Barracks";166;1
"Unit";"Marine";"Barracks";166;1
"Unit";"Marine";"Barracks";166;1
"Unit";"Marine";"Barracks";166;1
"Unit";"Marine";"Barracks";166;1
"Unit";"Marine";"Barracks";166;1
"Unit";"Marine";"Barracks";166;1
"Unit";"Marine";"Barracks";166;1
"Unit";"Marine";"Barracks";166;1
"Unit";"Marine";"Barracks";180;1
"Unit";"Marine";"Barracks";180;1
"Unit";"Marine";"Barracks";180;1
"Unit";"Marine";"Barracks";180;1
"Unit";"Marine";"Barracks";180;1
"Unit";"Marine";"Barracks";180;1
"Unit";"Marine";"Barracks";180;1
"Unit";"Marine";"Barracks";180;1
"Unit";"Marine";"Barracks";180;1
"Unit";"Marine";"Barracks";180;1
"Unit";"Medivac";"Starport";180;2
"Unit";"Medivac";"Starport";180;2
"Upgrade";"TerranInfantryArmorsLevel2";"EngineeringBay";144;0
"Unit";"Marine";"Barracks";194;1
"Unit";"Marine";"Barracks";194;1
"Unit";"Marine";"Barracks";194;1
"Unit";"Marine";"Barracks";194;1
"Unit";"Marine";"Barracks";194;1
"Unit";"Marine";"Barracks";194;1
"Unit";"Marine";"Barracks";194;1
"Unit";"Marine";"Barracks";194;1
"Unit";"Marine";"Barracks";194;1
"Unit";"Marine";"Barracks";194;1
"Unit";"Marine";"Barracks";194;1
"Building";"Barracks";NA;180;0
"Building";"Barracks";NA;180;0
"Unit";"Marine";"Barracks";194;1
"Unit";"Marine";"Barracks";194;1
"Unit";"Marine";"Barracks";194;1
"Unit";"Marine";"Barracks";194;1
"Building";"CommandCenter";NA;167;0
"Unit";"Marine";"Barracks";194;1
"Unit";"Marine";"Barracks";195;1
"Unit";"Marine";"Barracks";196;1
"Unit";"Marine";"Barracks";196;1
"Unit";"Marine";"Barracks";196;1
"Unit";"Marine";"Barracks";205;1
"Unit";"Marine";"Barracks";205;1
"Unit";"Marine";"Barracks";205;1
"Unit";"Marine";"Barracks";205;1
"Unit";"Marine";"Barracks";205;1
"Unit";"Marine";"Barracks";205;1
"Unit";"Marine";"Barracks";205;1
"Unit";"Marine";"Barracks";206;1
"Unit";"Marine";"Barracks";207;1
"Unit";"Marine";"Barracks";207;1
"Unit";"Marine";"Barracks";209;1
"Unit";"Medivac";"Starport";205;2
"Unit";"Marine";"Barracks";214;1
"Unit";"Medivac";"Starport";205;2
"Unit";"Marine";"Barracks";214;1
"Unit";"Marine";"Barracks";214;1
"Unit";"Marine";"Barracks";214;1
