"Type";"UnitName";"OnBuilding";"TotalSupply";"Supply"
"Unit";"SCV";"Command Center";12;1
"Unit";"SCV";"Command Center";12;1
"Unit";"SCV";"Command Center";13;1
"Building";"SupplyDepot";NA;13;0
"Unit";"SCV";"Command Center";15;1
"Unit";"SCV";"Command Center";15;1
"Building";"Refinery";NA;15;0
"Unit";"SCV";"Command Center";16;1
"Building";"Barracks";NA;15;0
"Unit";"SCV";"Command Center";18;1
"Unit";"Reaper";"Barracks";18;1
"Unit";"SCV";"Command Center";19;1
"Building";"Refinery";NA;19;0
"Unit";"SCV";"Command Center";20;1
"Building";"SupplyDepot";NA;19;0
"Unit";"SCV";"Command Center";22;1
"Unit";"Reaper";"Barracks";20;1
"Unit";"SCV";"Command Center";22;1
"Building";"CommandCenter";NA;19;0
"Unit";"SCV";"Command Center";24;1
"Building";"Factory";NA;22;0
"Unit";"SCV";"Command Center";25;1
"Building";"BarracksReactor";NA;24;0
"Unit";"SCV";"Command Center";26;1
"Building";"FactoryTechLab";NA;27;0
"Unit";"SCV";"Command Center";27;1
"Unit";"Marine";"Barracks";27;1
"Unit";"Marine";"Barracks";27;1
"Unit";"SCV";"Command Center";28;1
"Unit";"SCV";"Command Center";28;1
"Building";"Starport";NA;27;0
"Unit";"SCV";"Command Center";31;1
"Unit";"Marine";"Barracks";29;1
"Unit";"Marine";"Barracks";30;1
"Unit";"SCV";"Command Center";32;1
"Building";"EngineeringBay";NA;29;0
"Building";"FactoryTechLab";NA;32;0
"Unit";"SCV";"Command Center";33;1
"Unit";"SCV";"Command Center";36;1
"Building";"SupplyDepot";NA;34;0
"Unit";"SCV";"Command Center";37;1
"Unit";"SCV";"Command Center";38;1
"Building";"MissileTurret";NA;38;0
"Unit";"SCV";"Command Center";39;1
"Building";"MissileTurret";NA;39;0
"Building";"SupplyDepot";NA;39;0
"Unit";"SCV";"Command Center";40;1
"Unit";"SCV";"Command Center";41;1
"Unit";"Banshee";"Starport";37;3
"Unit";"SCV";"Command Center";42;1
"Unit";"Marine";"Barracks";42;1
"Unit";"Marine";"Barracks";42;1
"Unit";"SCV";"Command Center";43;1
"Unit";"SCV";"Command Center";50;1
"Unit";"SCV";"Command Center";51;1
"Unit";"Marine";"Barracks";51;1
"Unit";"Marine";"Barracks";51;1
"Unit";"SCV";"Command Center";51;1
"Unit";"SCV";"Command Center";53;1
"Unit";"Marine";"Barracks";55;1
"Unit";"Marine";"Barracks";55;1
"Unit";"SCV";"Command Center";57;1
"Building";"CommandCenter";NA;48;0
"Unit";"SCV";"Command Center";60;1
"Unit";"SCV";"Command Center";60;1
"Unit";"Marine";"Barracks";60;1
"Unit";"Marine";"Barracks";60;1
"Unit";"SCV";"Command Center";60;1
"Unit";"SCV";"Command Center";61;1
"Building";"EngineeringBay";NA;60;0
"Building";"EngineeringBay";NA;60;0
"Upgrade";"TerranInfantryWeaponsLevel1";"EngineeringBay";53;0
"Building";"Refinery";NA;62;0
"Building";"Refinery";NA;62;0
"Unit";"SCV";"Command Center";64;1
"Unit";"SCV";"Command Center";66;1
"Unit";"SCV";"Command Center";66;1
"Unit";"Marine";"Barracks";64;1
"Unit";"Marine";"Barracks";64;1
"Unit";"Banshee";"Starport";60;3
"Unit";"SCV";"Command Center";66;1
"Unit";"SCV";"Command Center";67;1
"Building";"Barracks";NA;60;0
"Building";"Barracks";NA;62;0
"Unit";"SCV";"Command Center";74;1
"Building";"Refinery";NA;76;0
"Unit";"SCV";"Command Center";77;1
"Building";"Refinery";NA;76;0
"Unit";"SCV";"Command Center";77;1
"Unit";"Marine";"Barracks";77;1
"Building";"SupplyDepot";NA;76;0
"Building";"Armory";NA;67;0
"Building";"SupplyDepot";NA;77;0
"Building";"BarracksReactor";NA;77;0
"Unit";"SCV";"Command Center";80;1
"Unit";"SCV";"Command Center";80;1
"Building";"BarracksReactor";NA;77;0
"Unit";"Marine";"Barracks";80;1
"Unit";"SCV";"Command Center";80;1
"Building";"Barracks";NA;60;0
"Building";"Barracks";NA;60;0
"Unit";"SCV";"Command Center";80;1
"Building";"SupplyDepot";NA;80;0
"Building";"SupplyDepot";NA;80;0
"Unit";"Marine";"Barracks";82;1
"Unit";"Marine";"Barracks";84;1
"Unit";"Marine";"Barracks";84;1
"Building";"SupplyDepot";NA;84;0
"Unit";"Marine";"Barracks";84;1
"Unit";"Marine";"Barracks";84;1
"Building";"SupplyDepot";NA;84;0
"Unit";"Medivac";"Starport";84;2
"Unit";"Marine";"Barracks";90;1
"Building";"BarracksReactor";NA;84;0
"Unit";"Marine";"Barracks";90;1
"Upgrade";"TerranInfantryArmorsLevel1";"EngineeringBay";77;0
"Building";"BarracksReactor";NA;84;0
"Unit";"Marine";"Barracks";90;1
"Unit";"SCV";"Command Center";92;1
"Building";"CommandCenter";NA;80;0
"Unit";"Marine";"Barracks";92;1
"Unit";"Marine";"Barracks";92;1
"Unit";"SCV";"Command Center";94;1
"Unit";"Marine";"Barracks";95;1
"Unit";"Marine";"Barracks";95;1
"Unit";"Marine";"Barracks";95;1
"Unit";"Marine";"Barracks";95;1
"Unit";"Marine";"Barracks";95;1
"Building";"Refinery";NA;95;0
"Upgrade";"Stimpack";"TechLab";80;0
"Building";"SupplyDepot";NA;96;0
"Unit";"Marine";"Barracks";99;1
"Unit";"Marine";"Barracks";99;1
"Unit";"Marine";"Barracks";99;1
"Unit";"Marine";"Barracks";99;1
"Unit";"Marine";"Barracks";99;1
"Unit";"Marine";"Barracks";102;1
"Unit";"Marine";"Barracks";102;1
"Unit";"Marine";"Barracks";103;1
"Unit";"Marine";"Barracks";104;1
"Building";"SupplyDepot";NA;104;0
"Unit";"Medivac";"Starport";99;2
"Building";"SupplyDepot";NA;104;0
"Unit";"Marine";"Barracks";104;1
"Unit";"Marine";"Barracks";105;1
"Unit";"Marine";"Barracks";106;1
"Unit";"Marine";"Barracks";107;1
"Unit";"Medivac";"Starport";99;2
"Unit";"Marine";"Barracks";108;1
"Unit";"Marine";"Barracks";113;1
"Unit";"Marine";"Barracks";113;1
"Unit";"Marine";"Barracks";113;1
"Unit";"Marine";"Barracks";115;1
"Unit";"Marine";"Barracks";115;1
"Unit";"Marine";"Barracks";121;1
"Unit";"Marine";"Barracks";121;1
"Unit";"Marine";"Barracks";125;1
"Unit";"Marine";"Barracks";125;1
"Unit";"Marine";"Barracks";125;1
"Upgrade";"TerranInfantryWeaponsLevel2";"EngineeringBay";90;0
"Unit";"Marine";"Barracks";125;1
"Upgrade";"TerranVehicleWeaponsLevel1";"Armory";95;0
"Unit";"Marine";"Barracks";126;1
"Unit";"Marine";"Barracks";126;1
"Unit";"Marine";"Barracks";127;1
"Unit";"Marine";"Barracks";127;1
"Unit";"Marine";"Barracks";128;1
"Unit";"Marine";"Barracks";129;1
"Unit";"Marine";"Barracks";130;1
"Unit";"Marine";"Barracks";131;1
"Unit";"Marine";"Barracks";132;1
"Unit";"Marine";"Barracks";133;1
"Unit";"Marine";"Barracks";134;1
"Unit";"Marine";"Barracks";135;1
"Unit";"Marine";"Barracks";136;1
"Unit";"Marine";"Barracks";137;1
"Unit";"Marine";"Barracks";138;1
"Unit";"Marine";"Barracks";139;1
"Unit";"Marine";"Barracks";140;1
"Unit";"Marine";"Barracks";144;1
"Unit";"Marine";"Barracks";144;1
"Unit";"Marine";"Barracks";144;1
"Unit";"Marine";"Barracks";145;1
"Unit";"Medivac";"Starport";138;2
"Unit";"Marine";"Barracks";147;1
"Unit";"Marine";"Barracks";147;1
"Unit";"Marine";"Barracks";147;1
"Unit";"Marine";"Barracks";148;1
"Unit";"Marine";"Barracks";149;1
"Unit";"Marine";"Barracks";150;1
"Unit";"Marine";"Barracks";151;1
"Unit";"Marine";"Barracks";152;1
"Unit";"Marine";"Barracks";153;1
"Unit";"Marine";"Barracks";156;1
"Unit";"Marine";"Barracks";157;1
"Unit";"Marine";"Barracks";158;1
"Unit";"Marine";"Barracks";159;1
"Unit";"Marine";"Barracks";161;1
"Unit";"Marine";"Barracks";161;1
"Unit";"Marine";"Barracks";162;1
"Unit";"Marine";"Barracks";163;1
"Unit";"Marine";"Barracks";164;1
"Unit";"Marine";"Barracks";165;1
"Unit";"Marine";"Barracks";166;1
"Unit";"Marine";"Barracks";167;1
"Unit";"Marine";"Barracks";168;1
"Unit";"Marine";"Barracks";169;1
"Upgrade";"TerranInfantryArmorsLevel2";"EngineeringBay";129;0
"Unit";"Marine";"Barracks";170;1
"Unit";"Marine";"Barracks";171;1
"Unit";"Marine";"Barracks";172;1
"Unit";"Medivac";"Starport";167;2
"Unit";"Marine";"Barracks";173;1
"Unit";"Marine";"Barracks";174;1
"Unit";"Marine";"Barracks";175;1
"Unit";"Marine";"Barracks";176;1
"Unit";"Marine";"Barracks";177;1
"Unit";"Marine";"Barracks";178;1
"Unit";"Marine";"Barracks";179;1
"Unit";"Marine";"Barracks";180;1
"Unit";"Marine";"Barracks";181;1
"Unit";"Marine";"Barracks";184;1
"Unit";"Marine";"Barracks";185;1
"Unit";"Marine";"Barracks";186;1
"Unit";"Marine";"Barracks";187;1
"Unit";"Marine";"Barracks";188;1
"Unit";"Marine";"Barracks";189;1
"Unit";"Marine";"Barracks";190;1
"Unit";"Marine";"Barracks";191;1
"Unit";"Marine";"Barracks";192;1
"Unit";"Marine";"Barracks";193;1
"Unit";"Marine";"Barracks";196;1
"Unit";"Marine";"Barracks";196;1
"Unit";"Marine";"Barracks";196;1
"Unit";"Marine";"Barracks";197;1
"Unit";"Marine";"Barracks";198;1
"Unit";"SCV";"Command Center";203;1
"Unit";"SCV";"Command Center";203;1
"Unit";"SCV";"Command Center";203;1
"Unit";"Liberator";"Starport";189;3
"Unit";"Liberator";"Starport";189;3
"Unit";"Marine";"Barracks";202;1
"Unit";"Marine";"Barracks";202;1
"Unit";"Marine";"Barracks";202;1
"Unit";"Marine";"Barracks";205;1
"Unit";"Marine";"Barracks";205;1
"Unit";"Marine";"Barracks";207;1
"Unit";"Marine";"Barracks";207;1
"Unit";"Marine";"Barracks";207;1
"Unit";"Marine";"Barracks";208;1
"Unit";"Marine";"Barracks";217;1
"Upgrade";"TerranInfantryWeaponsLevel3";"EngineeringBay";165;0
"Unit";"Marine";"Barracks";222;1
"Unit";"Medivac";"Starport";211;2
"Unit";"Medivac";"Starport";214;2
"Building";"CommandCenter";NA;174;0
"Unit";"Marine";"Barracks";225;1
"Unit";"Marine";"Barracks";226;1
"Unit";"Marine";"Barracks";226;1
"Unit";"Marine";"Barracks";227;1
"Unit";"Marine";"Barracks";227;1
"Unit";"Marine";"Barracks";227;1
"Unit";"Marine";"Barracks";227;1
"Unit";"Marine";"Barracks";227;1
"Unit";"Marine";"Barracks";227;1
"Unit";"Marine";"Barracks";232;1
"Unit";"Marine";"Barracks";233;1
"Unit";"Marine";"Barracks";234;1
"Unit";"Marine";"Barracks";235;1
"Unit";"Marine";"Barracks";236;1
"Unit";"Marine";"Barracks";237;1
"Unit";"Marine";"Barracks";238;1
"Building";"MissileTurret";NA;239;0
"Unit";"Marine";"Barracks";239;1
"Unit";"Marine";"Barracks";240;1
"Unit";"Marine";"Barracks";241;1
"Unit";"Marine";"Barracks";242;1
"Unit";"Marine";"Barracks";243;1
"Unit";"Medivac";"Starport";239;2
"Unit";"Marine";"Barracks";244;1
"Unit";"Marine";"Barracks";245;1
"Unit";"Marine";"Barracks";246;1
"Unit";"Marine";"Barracks";247;1
"Unit";"Marine";"Barracks";248;1
"Unit";"Marine";"Barracks";249;1
"Unit";"Marine";"Barracks";250;1
"Unit";"Marine";"Barracks";251;1
"Unit";"Marine";"Barracks";252;1
"Unit";"Marine";"Barracks";255;1
"Unit";"Marine";"Barracks";256;1
"Unit";"Marine";"Barracks";257;1
"Unit";"Marine";"Barracks";258;1
"Unit";"Marine";"Barracks";259;1
"Unit";"Marine";"Barracks";260;1
"Unit";"Marine";"Barracks";261;1
"Unit";"Marine";"Barracks";262;1
"Unit";"Marine";"Barracks";263;1
"Unit";"Marine";"Barracks";264;1
"Unit";"Medivac";"Starport";259;2
"Unit";"Marine";"Barracks";265;1
"Unit";"Marine";"Barracks";266;1
"Unit";"Marine";"Barracks";267;1
"Unit";"Marine";"Barracks";268;1
"Unit";"Marine";"Barracks";270;1
"Unit";"Marine";"Barracks";270;1
"Unit";"Marine";"Barracks";271;1
"Unit";"Marine";"Barracks";273;1
"Unit";"Marine";"Barracks";273;1
"Upgrade";"TerranInfantryArmorsLevel3";"EngineeringBay";226;0
"Unit";"Marine";"Barracks";276;1
"Unit";"Marine";"Barracks";277;1
"Unit";"Marine";"Barracks";278;1
"Unit";"Marine";"Barracks";279;1
"Unit";"Marine";"Barracks";280;1
"Unit";"Marine";"Barracks";281;1
"Unit";"Medivac";"Starport";276;2
"Unit";"Marine";"Barracks";284;1
"Unit";"Marine";"Barracks";284;1
"Unit";"Marine";"Barracks";284;1
"Unit";"Marine";"Barracks";285;1
"Unit";"Marine";"Barracks";288;1
"Unit";"Marine";"Barracks";288;1
"Unit";"Marine";"Barracks";288;1
"Unit";"Marine";"Barracks";289;1
"Unit";"Marine";"Barracks";290;1
"Unit";"Marine";"Barracks";293;1
"Unit";"Marine";"Barracks";294;1
"Unit";"Marine";"Barracks";295;1
"Unit";"Marine";"Barracks";296;1
"Unit";"Marine";"Barracks";297;1
"Unit";"Marine";"Barracks";298;1
"Building";"Refinery";NA;295;0
"Building";"Refinery";NA;296;0
"Unit";"Marine";"Barracks";299;1
"Unit";"Marine";"Barracks";300;1
"Unit";"Marine";"Barracks";301;1
"Unit";"Marine";"Barracks";302;1
"Unit";"Marine";"Barracks";303;1
"Unit";"Marine";"Barracks";304;1
"Unit";"Marine";"Barracks";305;1
"Unit";"Marine";"Barracks";306;1
"Unit";"Marine";"Barracks";307;1
"Upgrade";"TerranVehicleWeaponsLevel2";"Armory";264;0
"Unit";"Marine";"Barracks";308;1
"Building";"Barracks";NA;295;0
"Unit";"Marine";"Barracks";309;1
"Building";"Barracks";NA;295;0
"Unit";"Marine";"Barracks";310;1
"Unit";"Marine";"Barracks";311;1
"Unit";"Marine";"Barracks";312;1
"Unit";"Marine";"Barracks";313;1
"Unit";"Marine";"Barracks";314;1
"Unit";"Marine";"Barracks";315;1
"Unit";"Marine";"Barracks";316;1
"Unit";"Marine";"Barracks";317;1
"Unit";"Marine";"Barracks";318;1
"Unit";"Marine";"Barracks";319;1
"Unit";"Marine";"Barracks";320;1
"Unit";"Marine";"Barracks";321;1
"Unit";"Marine";"Barracks";322;1
"Unit";"Marine";"Barracks";323;1
"Unit";"Marine";"Barracks";324;1
"Unit";"Marine";"Barracks";325;1
"Unit";"Marine";"Barracks";326;1
"Unit";"Marine";"Barracks";327;1
"Unit";"Marine";"Barracks";328;1
"Unit";"Marine";"Barracks";329;1
"Unit";"Marine";"Barracks";330;1
"Building";"BarracksReactor";NA;322;0
"Building";"BarracksReactor";NA;322;0
"Unit";"Marine";"Barracks";331;1
"Unit";"Marine";"Barracks";332;1
"Unit";"Marine";"Barracks";333;1
"Unit";"Marine";"Barracks";334;1
"Unit";"Marine";"Barracks";335;1
"Unit";"Marine";"Barracks";336;1
"Unit";"Marine";"Barracks";337;1
"Unit";"Marine";"Barracks";338;1
"Unit";"Marine";"Barracks";339;1
"Unit";"Marine";"Barracks";340;1
"Unit";"Marine";"Barracks";341;1
"Unit";"Marine";"Barracks";342;1
"Unit";"Marine";"Barracks";344;1
"Unit";"Marine";"Barracks";344;1
"Unit";"Marine";"Barracks";346;1
"Unit";"Marine";"Barracks";347;1
"Unit";"Marine";"Barracks";347;1
"Unit";"Marine";"Barracks";347;1
"Unit";"Marine";"Barracks";347;1
"Unit";"Marine";"Barracks";353;1
"Unit";"Marine";"Barracks";353;1
"Unit";"Marine";"Barracks";353;1
"Unit";"Marine";"Barracks";354;1
"Unit";"Marine";"Barracks";354;1
"Unit";"Marine";"Barracks";354;1
"Unit";"Marine";"Barracks";358;1
"Unit";"Marine";"Barracks";359;1
"Unit";"Marine";"Barracks";359;1
"Unit";"Marine";"Barracks";359;1
"Unit";"Marine";"Barracks";359;1
"Unit";"Marine";"Barracks";370;1
"Unit";"Marine";"Barracks";370;1
"Unit";"Marine";"Barracks";370;1
"Unit";"Marine";"Barracks";370;1
"Unit";"Marine";"Barracks";370;1
"Unit";"Marine";"Barracks";370;1
"Unit";"Marine";"Barracks";370;1
"Unit";"Marine";"Barracks";370;1
"Unit";"Marine";"Barracks";370;1
"Unit";"Marine";"Barracks";370;1
"Unit";"Marine";"Barracks";370;1
"Unit";"Marine";"Barracks";370;1
"Unit";"Marine";"Barracks";370;1
"Unit";"Marine";"Barracks";370;1
"Unit";"Marine";"Barracks";376;1
"Unit";"Marine";"Barracks";376;1
"Unit";"Marine";"Barracks";378;1
"Unit";"Marine";"Barracks";378;1
"Unit";"Marine";"Barracks";380;1
"Unit";"Marine";"Barracks";380;1
"Unit";"Marine";"Barracks";381;1
"Unit";"Marine";"Barracks";381;1
"Unit";"Marine";"Barracks";381;1
"Unit";"Marine";"Barracks";390;1
"Unit";"Marine";"Barracks";390;1
"Unit";"Marine";"Barracks";390;1
"Unit";"Marine";"Barracks";390;1
"Unit";"Marine";"Barracks";390;1
"Building";"MissileTurret";NA;390;0
"Unit";"Marine";"Barracks";390;1
"Building";"MissileTurret";NA;390;0
"Unit";"Marine";"Barracks";393;1
"Unit";"Marine";"Barracks";397;1
"Unit";"Marine";"Barracks";397;1
"Unit";"Marine";"Barracks";398;1
"Upgrade";"TerranVehicleWeaponsLevel3";"Armory";362;0
"Unit";"Marine";"Barracks";398;1
"Unit";"Marine";"Barracks";399;1
"Unit";"Marine";"Barracks";399;1
"Unit";"Marine";"Barracks";399;1
"Unit";"Marine";"Barracks";399;1
"Unit";"Marine";"Barracks";399;1
"Unit";"Marine";"Barracks";402;1
"Unit";"Medivac";"Starport";403;2
"Unit";"Marine";"Barracks";410;1
"Unit";"Marine";"Barracks";410;1
"Unit";"Marine";"Barracks";410;1
"Unit";"Marine";"Barracks";410;1
"Unit";"Marine";"Barracks";410;1
"Unit";"Marine";"Barracks";410;1
"Unit";"Marine";"Barracks";417;1
"Unit";"Medivac";"Starport";410;2
"Unit";"Marine";"Barracks";417;1
"Unit";"Marine";"Barracks";418;1
"Unit";"Marine";"Barracks";418;1
"Unit";"Marine";"Barracks";424;1
"Unit";"Marine";"Barracks";424;1
"Unit";"Marine";"Barracks";424;1
"Unit";"Marine";"Barracks";424;1
"Unit";"Marine";"Barracks";424;1
"Unit";"Marine";"Barracks";424;1
"Unit";"Marine";"Barracks";424;1
"Unit";"Marine";"Barracks";424;1
"Unit";"Marine";"Barracks";424;1
"Unit";"Marine";"Barracks";424;1
"Unit";"Marine";"Barracks";425;1
"Unit";"Marine";"Barracks";425;1
"Unit";"Marine";"Barracks";427;1
"Unit";"Marine";"Barracks";433;1
"Unit";"Marine";"Barracks";433;1
"Unit";"Marine";"Barracks";433;1
"Unit";"Medivac";"Starport";424;2
"Unit";"Marine";"Barracks";433;1
"Unit";"Medivac";"Starport";424;2
"Unit";"Marine";"Barracks";433;1
"Unit";"Marine";"Barracks";433;1
"Unit";"Marine";"Barracks";434;1
"Unit";"Marine";"Barracks";434;1
"Unit";"Marine";"Barracks";436;1
"Unit";"Marine";"Barracks";437;1
"Unit";"Marine";"Barracks";438;1
"Unit";"Marine";"Barracks";439;1
"Unit";"Marine";"Barracks";442;1
"Unit";"Marine";"Barracks";445;1
"Unit";"Marine";"Barracks";446;1
"Unit";"Marine";"Barracks";447;1
"Unit";"Marine";"Barracks";447;1
"Unit";"Marine";"Barracks";449;1
"Unit";"Marine";"Barracks";450;1
"Unit";"Marine";"Barracks";451;1
"Unit";"Marine";"Barracks";455;1
"Unit";"Marine";"Barracks";455;1
"Unit";"Marine";"Barracks";455;1
"Unit";"Marine";"Barracks";455;1
"Unit";"Marine";"Barracks";464;1
"Unit";"Marine";"Barracks";464;1
"Unit";"Marine";"Barracks";464;1
"Unit";"Marine";"Barracks";465;1
"Unit";"Marine";"Barracks";465;1
"Unit";"Marine";"Barracks";465;1
"Unit";"Marine";"Barracks";465;1
"Unit";"Marine";"Barracks";468;1
"Unit";"Marine";"Barracks";468;1
"Unit";"Marine";"Barracks";468;1
"Unit";"Marine";"Barracks";468;1
"Unit";"Marine";"Barracks";471;1
"Unit";"Marine";"Barracks";472;1
"Unit";"Marine";"Barracks";472;1
"Unit";"Liberator";"Starport";465;3
"Unit";"Liberator";"Starport";465;3
"Unit";"Marine";"Barracks";472;1
"Unit";"Marine";"Barracks";477;1
"Unit";"Marine";"Barracks";477;1
"Unit";"Marine";"Barracks";477;1
"Unit";"Marine";"Barracks";478;1
"Unit";"Marine";"Barracks";479;1
"Unit";"SCV";"Command Center";488;1
"Unit";"Marine";"Barracks";486;1
"Unit";"SCV";"Command Center";488;1
"Unit";"Marine";"Barracks";486;1
"Unit";"Marine";"Barracks";486;1
"Unit";"SCV";"Command Center";489;1
"Unit";"Marine";"Barracks";486;1
"Unit";"Marine";"Barracks";486;1
"Unit";"Marine";"Barracks";487;1
"Unit";"Marine";"Barracks";488;1
"Unit";"SCV";"Command Center";491;1
"Unit";"Marine";"Barracks";491;1
"Unit";"Marine";"Barracks";491;1
"Unit";"Marine";"Barracks";492;1
"Unit";"Marine";"Barracks";498;1
"Unit";"Medivac";"Starport";491;2
"Unit";"Medivac";"Starport";491;2
"Unit";"Marine";"Barracks";501;1
"Unit";"Marine";"Barracks";501;1
"Unit";"Marine";"Barracks";501;1
"Unit";"Marine";"Barracks";501;1
"Unit";"Marine";"Barracks";502;1
"Unit";"Marine";"Barracks";504;1
"Unit";"Marine";"Barracks";505;1
"Unit";"Marine";"Barracks";510;1
"Unit";"Marine";"Barracks";510;1
"Unit";"Marine";"Barracks";515;1
"Unit";"Marine";"Barracks";515;1
"Unit";"Marine";"Barracks";515;1
"Unit";"Marine";"Barracks";517;1
"Unit";"Marine";"Barracks";519;1
"Unit";"Marine";"Barracks";522;1
"Unit";"Marine";"Barracks";522;1
"Unit";"Marine";"Barracks";522;1
"Unit";"Marine";"Barracks";522;1
"Unit";"Marine";"Barracks";522;1
"Unit";"Marine";"Barracks";523;1
"Unit";"Marine";"Barracks";523;1
"Unit";"Marine";"Barracks";523;1
"Unit";"Marine";"Barracks";526;1
"Unit";"Marine";"Barracks";530;1
"Unit";"Marine";"Barracks";530;1
"Unit";"Marine";"Barracks";530;1
"Unit";"Marine";"Barracks";530;1
"Unit";"Marine";"Barracks";533;1
"Unit";"Marine";"Barracks";533;1
"Unit";"Marine";"Barracks";537;1
"Unit";"Marine";"Barracks";537;1
"Unit";"Marine";"Barracks";537;1
"Unit";"Marine";"Barracks";537;1
"Unit";"Marine";"Barracks";537;1
"Unit";"Marine";"Barracks";537;1
"Unit";"Marine";"Barracks";537;1
"Unit";"Marine";"Barracks";537;1
"Unit";"Marine";"Barracks";539;1
"Unit";"Marine";"Barracks";541;1
"Unit";"Marine";"Barracks";547;1
"Unit";"Marine";"Barracks";547;1
"Unit";"Marine";"Barracks";547;1
"Unit";"Marine";"Barracks";548;1
"Unit";"Marine";"Barracks";548;1
"Unit";"Marine";"Barracks";549;1
"Unit";"Marine";"Barracks";549;1
"Unit";"Marine";"Barracks";549;1
"Unit";"Marine";"Barracks";549;1
"Unit";"Marine";"Barracks";549;1
"Unit";"Marine";"Barracks";550;1
