"type";"unit_name";"on_building";"total_supply";"supply"
"Building";"Refinery";NA;14;0
"Building";"Refinery";NA;16;0
"Building";"Barracks";NA;15;0
"Unit";"Reaper";"Barracks";19;1
"Building";"Factory";NA;19;0
"Unit";"Reaper";"Barracks";19;1
"Unit";"Hellion";"Factory";21;2
"Building";"BarracksReactor";NA;23;0
"Unit";"Cyclone";"Factory";26;3
"Unit";"Marine";"Barracks";29;1
"Unit";"Marine";"Barracks";29;1
"Building";"FactoryTechLab";NA;29;0
"Building";"Starport";NA;26;0
"Unit";"Marine";"Barracks";29;1
"Unit";"Marine";"Barracks";30;1
"Building";"FactoryTechLab";NA;32;0
"Building";"CommandCenter";NA;26;0
"Unit";"Marine";"Barracks";32;1
"Unit";"Marine";"Barracks";33;1
"Unit";"Banshee";"Starport";32;3
"Unit";"Marine";"Barracks";37;1
"Unit";"Marine";"Barracks";37;1
"Unit";"Marine";"Barracks";41;1
"Unit";"Marine";"Barracks";42;1
"Unit";"Marine";"Barracks";44;1
"Unit";"Marine";"Barracks";45;1
"Unit";"Banshee";"Starport";41;3
"Building";"EngineeringBay";NA;48;0
"Unit";"Marine";"Barracks";55;1
"Building";"Refinery";NA;55;0
"Building";"StarportReactor";NA;55;0
"Unit";"Marine";"Barracks";57;1
"Building";"Barracks";NA;55;0
"Building";"Barracks";NA;55;0
"Unit";"Marine";"Barracks";62;1
"Unit";"Marine";"Barracks";63;1
"Unit";"Marine";"Barracks";63;1
"Unit";"Marine";"Barracks";65;1
"Unit";"Marine";"Barracks";68;1
"Unit";"Marine";"Barracks";69;1
"Unit";"Medivac";"Starport";65;2
"Unit";"Medivac";"Starport";65;2
"Building";"BarracksReactor";NA;63;0
"Unit";"Marine";"Barracks";71;1
"Building";"Refinery";NA;71;0
"Unit";"Marine";"Barracks";79;1
"Unit";"Marine";"Barracks";79;1
"Unit";"Marine";"Barracks";81;1
"Unit";"Marine";"Barracks";81;1
"Upgrade";"Stimpack";"TechLab";63;0
"Unit";"Marine";"Barracks";89;1
"Building";"CommandCenter";NA;68;0
"Unit";"Marine";"Barracks";91;1
"Unit";"Marine";"Barracks";91;1
"Unit";"Marine";"Barracks";91;1
"Building";"MissileTurret";NA;94;0
"Unit";"Medivac";"Starport";91;2
"Unit";"Medivac";"Starport";91;2
"Unit";"Marine";"Barracks";94;1
"Unit";"Marine";"Barracks";94;1
"Unit";"Marine";"Barracks";98;1
"Unit";"Marine";"Barracks";98;1
"Unit";"Marine";"Barracks";98;1
"Unit";"Marine";"Barracks";104;1
"Upgrade";"TerranInfantryWeaponsLevel1";"EngineeringBay";83;0
"Unit";"Marine";"Barracks";106;1
"Unit";"Medivac";"Starport";104;2
"Unit";"Medivac";"Starport";104;2
"Unit";"Marine";"Barracks";111;1
"Unit";"Marine";"Barracks";111;1
"Unit";"Marine";"Barracks";111;1
"Unit";"Marine";"Barracks";118;1
"Unit";"Marine";"Barracks";118;1
"Unit";"Marine";"Barracks";118;1
"Building";"Barracks";NA;82;0
"Building";"Barracks";NA;121;0
"Building";"Barracks";NA;121;0
"Unit";"Marine";"Barracks";127;1
"Unit";"Marine";"Barracks";127;1
"Unit";"Marine";"Barracks";127;1
"Unit";"Marine";"Barracks";127;1
"Unit";"Marine";"Barracks";127;1
"Unit";"Medivac";"Starport";127;2
"Unit";"Marine";"Barracks";127;1
"Unit";"Marine";"Barracks";128;1
"Unit";"Marine";"Barracks";128;1
"Unit";"Marine";"Barracks";130;1
"Building";"MissileTurret";NA;134;0
"Unit";"Marine";"Barracks";134;1
"Building";"MissileTurret";NA;134;0
"Building";"BarracksReactor";NA;127;0
"Building";"BarracksReactor";NA;127;0
"Building";"Factory";NA;127;0
"Unit";"Marine";"Barracks";136;1
"Unit";"Marine";"Barracks";137;1
"Unit";"Marine";"Barracks";137;1
"Unit";"Marine";"Barracks";139;1
"Building";"BarracksReactor";NA;132;0
"Unit";"Marine";"Barracks";144;1
"Unit";"Marine";"Barracks";144;1
"Unit";"Marine";"Barracks";144;1
"Unit";"Marine";"Barracks";145;1
"Unit";"Marine";"Barracks";145;1
"Unit";"Marine";"Barracks";147;1
"Building";"EngineeringBay";NA;144;0
"Unit";"Marine";"Barracks";148;1
"Unit";"Marine";"Barracks";148;1
"Unit";"Marine";"Barracks";149;1
"Building";"FactoryTechLab";NA;149;0
"Unit";"Marine";"Barracks";150;1
"Unit";"Marine";"Barracks";150;1
"Unit";"Marine";"Barracks";150;1
"Unit";"Marine";"Barracks";151;1
"Unit";"Marine";"Barracks";151;1
"Unit";"Marine";"Barracks";153;1
"Unit";"Marine";"Barracks";154;1
"Building";"Armory";NA;144;0
"Unit";"Marine";"Barracks";157;1
"Unit";"Marine";"Barracks";157;1
"Unit";"Marine";"Barracks";157;1
"Unit";"Marine";"Barracks";158;1
"Unit";"Marine";"Barracks";159;1
"Unit";"Marine";"Barracks";160;1
"Unit";"Marine";"Barracks";160;1
"Unit";"Marine";"Barracks";162;1
"Unit";"Marine";"Barracks";163;1
"Building";"BarracksReactor";NA;157;0
"Unit";"Marine";"Barracks";164;1
"Unit";"Marine";"Barracks";165;1
"Building";"CommandCenter";NA;144;0
"Unit";"Marine";"Barracks";166;1
"Unit";"Marine";"Barracks";168;1
"Unit";"Marine";"Barracks";168;1
"Unit";"Marine";"Barracks";169;1
"Unit";"Marine";"Barracks";169;1
"Unit";"Marine";"Barracks";171;1
"Unit";"Marine";"Barracks";172;1
"Unit";"Marine";"Barracks";173;1
"Unit";"Marine";"Barracks";174;1
"Unit";"Marine";"Barracks";176;1
"Unit";"Marine";"Barracks";177;1
"Unit";"Marine";"Barracks";177;1
"Unit";"Marine";"Barracks";178;1
"Unit";"Marine";"Barracks";178;1
"Unit";"Marine";"Barracks";181;1
"Unit";"Marine";"Barracks";182;1
"Unit";"Marine";"Barracks";183;1
"Unit";"Marine";"Barracks";184;1
"Unit";"Marine";"Barracks";185;1
"Unit";"Marine";"Barracks";186;1
"Unit";"Marine";"Barracks";187;1
"Unit";"Marine";"Barracks";188;1
"Unit";"Marine";"Barracks";193;1
"Unit";"Marine";"Barracks";193;1
"Unit";"Marine";"Barracks";196;1
"Unit";"Marine";"Barracks";196;1
"Unit";"Marine";"Barracks";196;1
"Unit";"Marine";"Barracks";196;1
"Building";"BarracksReactor";NA;187;0
"Building";"Refinery";NA;198;0
"Building";"Refinery";NA;199;0
"Unit";"Marine";"Barracks";200;1
"Unit";"Marine";"Barracks";200;1
"Unit";"Marine";"Barracks";201;1
"Unit";"Marine";"Barracks";202;1
"Unit";"Marine";"Barracks";210;1
"Unit";"Marine";"Barracks";210;1
"Unit";"Marine";"Barracks";210;1
"Unit";"Marine";"Barracks";210;1
"Unit";"Marine";"Barracks";210;1
"Unit";"Marine";"Barracks";210;1
"Unit";"Marine";"Barracks";210;1
"Unit";"Marine";"Barracks";210;1
"Unit";"Marine";"Barracks";210;1
"Unit";"Marine";"Barracks";210;1
"Unit";"Marine";"Barracks";210;1
"Unit";"Marine";"Barracks";210;1
"Unit";"Marine";"Barracks";211;1
"Unit";"Marine";"Barracks";212;1
"Unit";"Marine";"Barracks";213;1
"Unit";"Marine";"Barracks";214;1
"Unit";"Marine";"Barracks";221;1
"Unit";"Marine";"Barracks";221;1
"Unit";"Marine";"Barracks";221;1
"Unit";"Marine";"Barracks";221;1
"Upgrade";"TerranInfantryArmorsLevel1";"EngineeringBay";194;0
"Unit";"Medivac";"Starport";210;2
"Unit";"Medivac";"Starport";210;2
"Unit";"Marine";"Barracks";221;1
"Unit";"Marine";"Barracks";221;1
"Unit";"Marine";"Barracks";221;1
"Unit";"Marine";"Barracks";222;1
"Unit";"Marine";"Barracks";223;1
"Unit";"Marine";"Barracks";230;1
"Unit";"Marine";"Barracks";230;1
"Unit";"Marine";"Barracks";230;1
"Unit";"Marine";"Barracks";230;1
"Unit";"Marine";"Barracks";230;1
"Unit";"Marine";"Barracks";230;1
"Upgrade";"TerranInfantryWeaponsLevel2";"EngineeringBay";196;0
"Unit";"Marine";"Barracks";234;1
"Unit";"Marine";"Barracks";235;1
"Upgrade";"TerranVehicleWeaponsLevel1";"Armory";206;0
"Unit";"Marine";"Barracks";236;1
"Unit";"Marine";"Barracks";237;1
"Unit";"Marine";"Barracks";238;1
"Unit";"Medivac";"Starport";230;2
"Unit";"Marine";"Barracks";239;1
"Unit";"Marine";"Barracks";247;1
"Unit";"Marine";"Barracks";247;1
"Unit";"Marine";"Barracks";247;1
"Unit";"Marine";"Barracks";247;1
"Unit";"Marine";"Barracks";247;1
"Unit";"Marine";"Barracks";252;1
"Unit";"Marine";"Barracks";252;1
"Unit";"Marine";"Barracks";252;1
"Unit";"Marine";"Barracks";253;1
"Unit";"Marine";"Barracks";253;1
"Unit";"Marine";"Barracks";253;1
"Unit";"Marine";"Barracks";267;1
"Unit";"Marine";"Barracks";267;1
"Unit";"Marine";"Barracks";267;1
"Unit";"Marine";"Barracks";267;1
"Unit";"Marine";"Barracks";267;1
"Unit";"Marine";"Barracks";267;1
"Unit";"Marine";"Barracks";267;1
"Unit";"Marine";"Barracks";267;1
"Unit";"Marine";"Barracks";267;1
"Unit";"Marine";"Barracks";267;1
"Unit";"Marine";"Barracks";269;1
"Unit";"Marine";"Barracks";270;1
"Unit";"Marine";"Barracks";271;1
"Unit";"Marine";"Barracks";271;1
"Unit";"Marine";"Barracks";273;1
"Unit";"Marine";"Barracks";274;1
"Unit";"Marine";"Barracks";275;1
"Unit";"Marine";"Barracks";276;1
"Unit";"Marine";"Barracks";284;1
"Unit";"Marine";"Barracks";284;1
"Unit";"Marine";"Barracks";286;1
"Unit";"Marine";"Barracks";286;1
"Unit";"Marine";"Barracks";286;1
"Unit";"Marine";"Barracks";290;1
"Unit";"Marine";"Barracks";290;1
"Unit";"Marine";"Barracks";290;1
"Unit";"Marine";"Barracks";298;1
"Unit";"Marine";"Barracks";298;1
"Unit";"Marine";"Barracks";298;1
"Unit";"Marine";"Barracks";301;1
"Unit";"Marine";"Barracks";301;1
"Unit";"Marine";"Barracks";301;1
"Unit";"Marine";"Barracks";301;1
"Unit";"Marine";"Barracks";301;1
"Unit";"Marine";"Barracks";301;1
"Unit";"Marine";"Barracks";301;1
"Unit";"Marine";"Barracks";301;1
"Unit";"Marine";"Barracks";301;1
"Unit";"Marine";"Barracks";302;1
"Unit";"Marine";"Barracks";303;1
"Unit";"Marine";"Barracks";304;1
"Unit";"Marine";"Barracks";305;1
"Unit";"Marine";"Barracks";306;1
"Unit";"Marine";"Barracks";306;1
"Unit";"Marine";"Barracks";308;1
"Unit";"Marine";"Barracks";312;1
"Unit";"Marine";"Barracks";312;1
"Unit";"Marine";"Barracks";312;1
"Unit";"Marine";"Barracks";315;1
"Unit";"Marine";"Barracks";315;1
"Unit";"Marine";"Barracks";315;1
