"type";"unit_name";"on_building";"total_supply_lag";"supply"
"Building";"Refinery";NA;15;0
"Building";"Barracks";NA;16;0
"Unit";"Reaper";"Barracks";19;1
"Building";"CommandCenter";NA;20;0
"Building";"Factory";NA;21;0
"Building";"Refinery";NA;21;0
"Building";"BarracksReactor";NA;21;0
"Unit";"Hellion";"Factory";24;2
"Building";"Starport";NA;26;0
"Unit";"Marine";"Barracks";26;1
"Unit";"Marine";"Barracks";27;1
"Building";"FactoryTechLab";NA;29;0
"Unit";"Marine";"Barracks";30;1
"Building";"Bunker";NA;31;0
"Unit";"Marine";"Barracks";31;1
"Unit";"Banshee";"Starport";35;3
"Building";"FactoryTechLab";NA;38;0
"Unit";"Marine";"Barracks";40;1
"Unit";"Marine";"Barracks";41;1
"Unit";"Marine";"Barracks";45;1
"Unit";"Banshee";"Starport";47;3
"Unit";"Marine";"Barracks";50;1
"Building";"Barracks";NA;53;0
"Building";"Barracks";NA;53;0
"Building";"FactoryTechLab";NA;54;0
"Building";"EngineeringBay";NA;55;0
"Unit";"Marine";"Barracks";55;1
"Building";"Refinery";NA;57;0
"Unit";"Marine";"Barracks";60;1
"Building";"StarportReactor";NA;61;0
"Upgrade";"Stimpack";"TechLab";62;0
"Unit";"Marine";"Barracks";63;1
"Unit";"Marauder";"Barracks";64;2
"Unit";"Marine";"Barracks";67;1
"Unit";"Marine";"Barracks";70;1
"Unit";"Marine";"Barracks";72;1
"Unit";"Marauder";"Barracks";73;2
"Building";"Refinery";NA;75;0
"Unit";"Medivac";"Starport";75;2
"Unit";"Medivac";"Starport";77;2
"Upgrade";"TerranInfantryWeaponsLevel1";"EngineeringBay";79;0
"Building";"CommandCenter";NA;79;0
"Unit";"Marine";"Barracks";81;1
"Unit";"Marine";"Barracks";84;1
"Building";"Barracks";NA;85;0
"Building";"Barracks";NA;85;0
"Unit";"Marine";"Barracks";87;1
"Unit";"Medivac";"Starport";88;2
"Unit";"Marauder";"Barracks";90;2
"Unit";"Marauder";"Barracks";92;2
"Unit";"Marine";"Barracks";95;1
"Unit";"Medivac";"Starport";96;2
"Unit";"Marauder";"Barracks";100;2
"Unit";"Marine";"Barracks";102;1
"Unit";"Marauder";"Barracks";103;2
"Unit";"Marine";"Barracks";105;1
"Building";"BarracksTechLab";NA;107;0
"Building";"BarracksReactor";NA;107;0
"Unit";"Marine";"Barracks";109;1
"Unit";"Marauder";"Barracks";110;2
"Unit";"Medivac";"Starport";113;2
"Unit";"Marine";"Barracks";115;1
"Unit";"Marine";"Barracks";116;1
"Unit";"Marauder";"Barracks";117;2
"Unit";"Marine";"Barracks";120;1
"Unit";"Marauder";"Barracks";121;2
"Unit";"Marine";"Barracks";123;1
"Unit";"Marauder";"Barracks";124;2
"Unit";"Marine";"Barracks";126;1
"Unit";"Marine";"Barracks";127;1
"Unit";"Marine";"Barracks";128;1
"Unit";"Marine";"Barracks";129;1
"Unit";"Liberator";"Starport";130;3
"Unit";"Marine";"Barracks";133;1
"Unit";"Marine";"Barracks";134;1
"Unit";"Marauder";"Barracks";135;2
"Unit";"Marine";"Barracks";137;1
"Unit";"Marauder";"Barracks";138;2
"Unit";"Marauder";"Barracks";140;2
"Unit";"Marine";"Barracks";142;1
"Unit";"Liberator";"Starport";143;3
"Unit";"Marine";"Barracks";146;1
"Unit";"Marine";"Barracks";147;1
"Building";"Refinery";NA;148;0
"Unit";"Marine";"Barracks";148;1
"Building";"Refinery";NA;149;0
"Unit";"Marauder";"Barracks";150;2
"Building";"Armory";NA;152;0
"Building";"EngineeringBay";NA;153;0
"Building";"CommandCenter";NA;153;0
"Unit";"Marauder";"Barracks";153;2
"Unit";"Marine";"Barracks";155;1
"Building";"Starport";NA;159;0
"Unit";"Marauder";"Barracks";159;2
"Unit";"Marine";"Barracks";161;1
"Unit";"Marine";"Barracks";162;1
"Unit";"Marauder";"Barracks";163;2
"Unit";"Marine";"Barracks";165;1
"Unit";"Marauder";"Barracks";167;2
"Building";"Barracks";NA;171;0
"Building";"Barracks";NA;171;0
"Unit";"Marauder";"Barracks";172;2
"Unit";"Marine";"Barracks";174;1
"Unit";"Marine";"Barracks";177;1
"Unit";"Marine";"Barracks";179;1
"Unit";"Marauder";"Barracks";180;2
"Unit";"Marine";"Barracks";182;1
"Unit";"Marine";"Barracks";183;1
"Unit";"Marine";"Barracks";184;1
"Unit";"Marauder";"Barracks";185;2
"Unit";"Medivac";"Starport";187;2
"Unit";"Medivac";"Starport";189;2
"Building";"StarportReactor";NA;191;0
"Unit";"Marine";"Barracks";191;1
"Unit";"Marine";"Barracks";192;1
"Unit";"Marine";"Barracks";193;1
"Unit";"Marauder";"Barracks";194;2
"Unit";"Marauder";"Barracks";196;2
"Unit";"Marine";"Barracks";198;1
"Unit";"Marauder";"Barracks";199;2
"Unit";"Marine";"Barracks";201;1
"Unit";"Marine";"Barracks";202;1
"Building";"BarracksTechLab";NA;203;0
"Building";"BarracksTechLab";NA;203;0
"Unit";"Marauder";"Barracks";203;2
"Unit";"Marine";"Barracks";205;1
"Unit";"Marauder";"Barracks";206;2
"Unit";"Marine";"Barracks";208;1
"Unit";"Marauder";"Barracks";209;2
"Unit";"Marine";"Barracks";211;1
"Unit";"Marine";"Barracks";212;1
"Unit";"Marine";"Barracks";213;1
"Unit";"Marine";"Barracks";214;1
"Unit";"Marauder";"Barracks";215;2
"Unit";"Marine";"Barracks";217;1
"Unit";"Marine";"Barracks";218;1
"Unit";"Marine";"Barracks";219;1
"Unit";"Marine";"Barracks";220;1
"Unit";"Marauder";"Barracks";221;2
"Unit";"Marine";"Barracks";223;1
"Upgrade";"SprayTerran";NA;224;0
"Upgrade";"SprayTerran";NA;224;0
"Upgrade";"BansheeCloak";NA;224;0
"Upgrade";"SprayTerran";NA;224;0
"Upgrade";"SprayTerran";NA;224;0
"Upgrade";"ShieldWall";NA;224;0
"Upgrade";"PunisherGrenades";NA;224;0
"Upgrade";"SprayTerran";NA;224;0
"Upgrade";"TerranInfantryArmorsLevel1";NA;224;0
"Upgrade";"SprayTerran";NA;224;0
"Upgrade";"SprayTerran";NA;224;0
"Upgrade";"SprayTerran";NA;224;0
