"type";"unit_name";"on_building";"total_supply_lag";"supply"
"Building";"Barracks";NA;16;0
"Building";"Refinery";NA;16;0
"Unit";"Reaper";"Barracks";19;1
"Building";"CommandCenter";NA;20;0
"Unit";"Marine";"Barracks";21;1
"Building";"Factory";NA;23;0
"Building";"Refinery";NA;24;0
"Building";"BarracksTechLab";NA;24;0
"Unit";"Hellion";"Factory";27;2
"Building";"Starport";NA;29;0
"Building";"BarracksReactor";NA;29;0
"Unit";"Hellion";"Factory";30;2
"Building";"Bunker";NA;32;0
"Unit";"Banshee";"Starport";35;3
"Unit";"Marine";"Barracks";38;1
"Unit";"Marine";"Barracks";39;1
"Building";"FactoryTechLab";NA;41;0
"Unit";"Marine";"Barracks";43;1
"Unit";"Marine";"Barracks";44;1
"Unit";"Marine";"Barracks";47;1
"Unit";"Marine";"Barracks";49;1
"Building";"EngineeringBay";NA;50;0
"Unit";"Banshee";"Starport";51;3
"Building";"CommandCenter";NA;57;0
"Unit";"Marine";"Barracks";58;1
"Unit";"Marine";"Barracks";59;1
"Building";"Barracks";NA;62;0
"Building";"Barracks";NA;64;0
"Unit";"Marine";"Barracks";64;1
"Building";"Refinery";NA;66;0
"Building";"Refinery";NA;66;0
"Building";"StarportReactor";NA;67;0
"Unit";"Marine";"Barracks";68;1
"Upgrade";"TerranInfantryWeaponsLevel1";"EngineeringBay";71;0
"Building";"Barracks";NA;72;0
"Upgrade";"Stimpack";"TechLab";72;0
"Building";"Barracks";NA;72;0
"Unit";"Marine";"Barracks";74;1
"Unit";"Marine";"Barracks";75;1
"Unit";"Marine";"Barracks";76;1
"Unit";"Marine";"Barracks";79;1
"Unit";"Marine";"Barracks";80;1
"Building";"StarportReactor";NA;81;0
"Unit";"Marine";"Barracks";81;1
"Building";"Refinery";NA;85;0
"Building";"Refinery";NA;85;0
"Unit";"Marine";"Barracks";85;1
"Unit";"Marine";"Barracks";86;1
"Unit";"Marine";"Barracks";87;1
"Unit";"Marine";"Barracks";88;1
"Unit";"Marine";"Barracks";92;1
"Building";"BarracksTechLab";NA;93;0
"Building";"BarracksTechLab";NA;93;0
"Unit";"Marine";"Barracks";93;1
"Unit";"Marine";"Barracks";94;1
"Unit";"Medivac";"Starport";98;2
"Unit";"Medivac";"Starport";100;2
"Unit";"Marine";"Barracks";102;1
"Unit";"Marine";"Barracks";103;1
"Building";"CommandCenter";NA;104;0
"Unit";"Marine";"Barracks";104;1
"Unit";"Marauder";"Barracks";105;2
"Unit";"Marine";"Barracks";107;1
"Unit";"Marine";"Barracks";108;1
"Unit";"Marine";"Barracks";109;1
"Unit";"Marine";"Barracks";110;1
"Unit";"Marine";"Barracks";111;1
"Unit";"Medivac";"Starport";112;2
"Unit";"Medivac";"Starport";114;2
"Unit";"Marauder";"Barracks";116;2
"Unit";"Marine";"Barracks";118;1
"Unit";"Marauder";"Barracks";119;2
"Unit";"Marine";"Barracks";121;1
"Unit";"Marine";"Barracks";122;1
"Unit";"Marauder";"Barracks";123;2
"Unit";"Marine";"Barracks";125;1
"Unit";"Marine";"Barracks";129;1
"Unit";"Marauder";"Barracks";130;2
"Building";"Starport";NA;132;0
"Unit";"Marine";"Barracks";132;1
"Building";"FusionCore";NA;133;0
"Building";"Starport";NA;133;0
"Unit";"Marine";"Barracks";133;1
"Unit";"Marauder";"Barracks";134;2
"Unit";"Medivac";"Starport";136;2
"Unit";"Medivac";"Starport";138;2
"Unit";"Marine";"Barracks";143;1
"Unit";"Marauder";"Barracks";144;2
"Unit";"Marine";"Barracks";146;1
"Unit";"Marauder";"Barracks";147;2
"Building";"Refinery";NA;149;0
"Building";"Armory";NA;149;0
"Building";"Refinery";NA;150;0
"Building";"StarportTechLab";NA;150;0
"Building";"StarportReactor";NA;150;0
"Unit";"Marine";"Barracks";150;1
"Unit";"Marine";"Barracks";151;1
"Unit";"Marauder";"Barracks";152;2
"Unit";"Marine";"Barracks";154;1
"Unit";"Marauder";"Barracks";155;2
"Unit";"Medivac";"Starport";157;2
"Unit";"Marine";"Barracks";159;1
"Unit";"Marauder";"Barracks";160;2
"Unit";"Marine";"Barracks";162;1
"Unit";"Marauder";"Barracks";163;2
"Unit";"Marine";"Barracks";165;1
"Unit";"Marauder";"Barracks";166;2
"Unit";"Marine";"Barracks";168;1
"Unit";"Marauder";"Barracks";173;2
"Unit";"Marine";"Barracks";175;1
"Unit";"Marine";"Barracks";176;1
"Building";"Armory";NA;177;0
"Unit";"Marine";"Barracks";181;1
"Unit";"Marauder";"Barracks";182;2
"Unit";"Marauder";"Barracks";184;2
"Unit";"Marine";"Barracks";186;1
"Unit";"Marine";"Barracks";187;1
"Unit";"Marine";"Barracks";188;1
"Unit";"Marine";"Barracks";189;1
"Building";"MissileTurret";NA;190;0
"Unit";"Marine";"Barracks";190;1
"Unit";"Marauder";"Barracks";191;2
"Unit";"Marine";"Barracks";193;1
"Unit";"Marine";"Barracks";194;1
"Upgrade";"TerranInfantryWeaponsLevel2";"EngineeringBay";195;0
"Unit";"Marine";"Barracks";195;1
"Unit";"Marine";"Barracks";196;1
"Building";"CommandCenter";NA;197;0
"Unit";"Liberator";"Starport";197;3
"Unit";"Liberator";"Starport";200;3
"Unit";"Liberator";"Starport";203;3
"Unit";"Marine";"Barracks";206;1
"Unit";"Marauder";"Barracks";207;2
"Unit";"Marine";"Barracks";209;1
"Unit";"Marauder";"Barracks";210;2
"Unit";"Marine";"Barracks";212;1
"Unit";"Marauder";"Barracks";213;2
"Unit";"Marine";"Barracks";219;1
"Unit";"Marine";"Barracks";220;1
"Unit";"Liberator";"Starport";221;3
"Unit";"Liberator";"Starport";224;3
"Upgrade";"TerranShipWeaponsLevel1";"Armory";227;0
"Building";"Starport";NA;227;0
"Unit";"Marine";"Barracks";227;1
"Unit";"Marauder";"Barracks";228;2
"Unit";"Marine";"Barracks";230;1
"Unit";"Marauder";"Barracks";231;2
"Unit";"Marine";"Barracks";233;1
"Building";"Starport";NA;234;0
"Unit";"Liberator";"Starport";234;3
"Unit";"Liberator";"Starport";237;3
"Unit";"Liberator";"Starport";240;3
"Unit";"Liberator";"Starport";243;3
"Unit";"Marine";"Barracks";246;1
"Unit";"Marauder";"Barracks";247;2
"Unit";"Marine";"Barracks";249;1
"Unit";"Marauder";"Barracks";250;2
"Unit";"Liberator";"Starport";252;3
"Unit";"Marine";"Barracks";255;1
"Unit";"Marauder";"Barracks";256;2
"Unit";"Marine";"Barracks";258;1
"Unit";"Marine";"Barracks";259;1
"Unit";"Marine";"Barracks";260;1
"Unit";"Liberator";"Starport";261;3
"Unit";"Marauder";"Barracks";264;2
"Unit";"Liberator";"Starport";266;3
"Unit";"Marine";"Barracks";269;1
"Building";"SensorTower";NA;270;0
"Unit";"Liberator";"Starport";270;3
"Unit";"Liberator";"Starport";273;3
"Unit";"Marine";"Barracks";276;1
"Unit";"Marauder";"Barracks";277;2
"Unit";"Marine";"Barracks";279;1
"Unit";"Marauder";"Barracks";280;2
"Unit";"Marine";"Barracks";282;1
"Unit";"Liberator";"Starport";283;3
"Unit";"Liberator";"Starport";286;3
"Unit";"Liberator";"Starport";289;3
"Building";"CommandCenter";NA;292;0
"Unit";"Marine";"Barracks";292;1
"Unit";"Marauder";"Barracks";293;2
"Upgrade";"TerranShipWeaponsLevel2";"Armory";295;0
"Unit";"Liberator";"Starport";295;3
"Unit";"Marine";"Barracks";298;1
"Unit";"Marine";"Barracks";299;1
"Unit";"Marauder";"Barracks";300;2
"Unit";"Marine";"Barracks";302;1
"Unit";"Marauder";"Barracks";303;2
"Unit";"Liberator";"Starport";305;3
"Building";"Refinery";NA;312;0
"Building";"Refinery";NA;312;0
"Unit";"Marine";"Barracks";313;1
"Unit";"Marine";"Barracks";314;1
"Unit";"Liberator";"Starport";319;3
"Unit";"Marine";"Barracks";322;1
"Unit";"Marine";"Barracks";323;1
"Unit";"Marauder";"Barracks";324;2
"Unit";"Marine";"Barracks";326;1
"Unit";"Marine";"Barracks";327;1
"Unit";"Marauder";"Barracks";328;2
"Unit";"Marine";"Barracks";330;1
"Unit";"Marauder";"Barracks";331;2
"Unit";"Marine";"Barracks";333;1
"Unit";"Marauder";"Barracks";334;2
"Unit";"Marine";"Barracks";336;1
"Unit";"Marauder";"Barracks";337;2
"Unit";"Marine";"Barracks";339;1
"Unit";"Liberator";"Starport";340;3
"Unit";"Liberator";"Starport";343;3
"Unit";"Liberator";"Starport";346;3
"Unit";"Liberator";"Starport";349;3
"Unit";"Marine";"Barracks";352;1
"Unit";"Marine";"Barracks";353;1
"Unit";"Marauder";"Barracks";354;2
"Unit";"Marauder";"Barracks";356;2
"Unit";"Liberator";"Starport";358;3
"Unit";"Liberator";"Starport";361;3
"Unit";"Marine";"Barracks";364;1
"Unit";"Marauder";"Barracks";365;2
"Unit";"Marine";"Barracks";367;1
"Building";"Refinery";NA;368;0
"Unit";"Marauder";"Barracks";368;2
"Building";"Refinery";NA;370;0
"Unit";"Marine";"Barracks";370;1
"Unit";"Liberator";"Starport";371;3
"Unit";"Marine";"Barracks";374;1
"Unit";"Marauder";"Barracks";375;2
"Building";"CommandCenter";NA;377;0
"Unit";"Marine";"Barracks";377;1
"Unit";"Marauder";"Barracks";378;2
"Unit";"Liberator";"Starport";380;3
"Unit";"Liberator";"Starport";383;3
"Unit";"Liberator";"Starport";386;3
"Unit";"Marine";"Barracks";389;1
"Building";"CommandCenter";NA;390;0
"Upgrade";"TerranShipWeaponsLevel3";"Armory";390;0
"Unit";"Marine";"Barracks";390;1
"Upgrade";"TerranInfantryWeaponsLevel3";"EngineeringBay";391;0
"Building";"Starport";NA;391;0
"Building";"Starport";NA;391;0
"Unit";"Marine";"Barracks";391;1
"Building";"Refinery";NA;392;0
"Building";"Refinery";NA;392;0
"Unit";"Marine";"Barracks";392;1
"Building";"StarportReactor";NA;393;0
"Building";"StarportReactor";NA;393;0
"Unit";"Marine";"Barracks";393;1
"Unit";"Marauder";"Barracks";394;2
"Unit";"Marine";"Barracks";396;1
"Unit";"Marauder";"Barracks";397;2
"Unit";"Marine";"Barracks";399;1
"Unit";"Marauder";"Barracks";400;2
"Unit";"Marine";"Barracks";402;1
"Unit";"Liberator";"Starport";403;3
"Unit";"Liberator";"Starport";406;3
"Unit";"Liberator";"Starport";409;3
"Unit";"Liberator";"Starport";412;3
"Unit";"Liberator";"Starport";415;3
"Unit";"Liberator";"Starport";418;3
"Unit";"Liberator";"Starport";421;3
"Unit";"Liberator";"Starport";424;3
"Building";"Barracks";NA;427;0
"Building";"Barracks";NA;427;0
"Building";"Barracks";NA;427;0
"Unit";"Marine";"Barracks";427;1
"Unit";"Marine";"Barracks";428;1
"Unit";"Marine";"Barracks";429;1
"Unit";"Marine";"Barracks";430;1
"Unit";"Marauder";"Barracks";431;2
"Unit";"Marauder";"Barracks";433;2
"Unit";"Marauder";"Barracks";435;2
"Building";"SensorTower";NA;437;0
"Building";"MissileTurret";NA;437;0
"Building";"SensorTower";NA;437;0
"Unit";"Marine";"Barracks";437;1
"Unit";"Marine";"Barracks";438;1
"Unit";"Liberator";"Starport";439;3
"Building";"CommandCenter";NA;442;0
"Unit";"Liberator";"Starport";442;3
"Unit";"Marauder";"Barracks";445;2
"Unit";"Liberator";"Starport";447;3
"Unit";"Liberator";"Starport";450;3
"Unit";"Liberator";"Starport";453;3
"Unit";"Liberator";"Starport";456;3
"Unit";"Liberator";"Starport";459;3
"Unit";"Liberator";"Starport";462;3
"Unit";"Marine";"Barracks";465;1
"Unit";"Marine";"Barracks";466;1
"Building";"BarracksTechLab";NA;467;0
"Building";"BarracksReactor";NA;467;0
"Unit";"Marine";"Barracks";467;1
"Unit";"Marauder";"Barracks";468;2
"Unit";"Marine";"Barracks";470;1
"Unit";"Liberator";"Starport";471;3
"Unit";"Marine";"Barracks";474;1
"Unit";"Marauder";"Barracks";475;2
"Unit";"Liberator";"Starport";477;3
"Unit";"Liberator";"Starport";480;3
"Unit";"Marine";"Barracks";483;1
"Unit";"Marine";"Barracks";484;1
"Unit";"Liberator";"Starport";485;3
"Upgrade";"TerranVehicleWeaponsLevel1";"Armory";488;0
"Unit";"Liberator";"Starport";488;3
"Unit";"Liberator";"Starport";491;3
"Unit";"Marine";"Barracks";494;1
"Unit";"Marauder";"Barracks";495;2
"Unit";"Marine";"Barracks";497;1
"Unit";"Marauder";"Barracks";498;2
"Unit";"Marine";"Barracks";500;1
"Unit";"Marauder";"Barracks";501;2
"Unit";"Marine";"Barracks";503;1
"Unit";"Marauder";"Barracks";504;2
"Unit";"Marine";"Barracks";506;1
"Unit";"Marine";"Barracks";507;1
"Unit";"Marine";"Barracks";508;1
"Unit";"Marine";"Barracks";509;1
"Unit";"Marine";"Barracks";510;1
"Unit";"Marauder";"Barracks";511;2
"Unit";"Marauder";"Barracks";513;2
"Unit";"Marine";"Barracks";515;1
"Unit";"Marine";"Barracks";516;1
"Unit";"Marine";"Barracks";517;1
"Unit";"Marine";"Barracks";518;1
"Unit";"Marine";"Barracks";519;1
"Unit";"Marine";"Barracks";520;1
"Unit";"Marine";"Barracks";521;1
"Unit";"Marauder";"Barracks";522;2
"Unit";"Marauder";"Barracks";524;2
"Unit";"Marauder";"Barracks";526;2
"Unit";"Marauder";"Barracks";528;2
"Unit";"Hellion";"Factory";530;2
"Unit";"Marine";"Barracks";532;1
"Unit";"Marauder";"Barracks";533;2
"Unit";"Marine";"Barracks";535;1
"Unit";"Marauder";"Barracks";536;2
"Unit";"Marine";"Barracks";538;1
"Unit";"Marauder";"Barracks";539;2
"Unit";"Marine";"Barracks";541;1
"Unit";"Marauder";"Barracks";542;2
"Unit";"Marine";"Barracks";544;1
"Unit";"Marauder";"Barracks";545;2
"Unit";"Marine";"Barracks";547;1
"Unit";"Marauder";"Barracks";548;2
"Unit";"Marine";"Barracks";550;1
"Unit";"Marauder";"Barracks";551;2
"Unit";"Marine";"Barracks";553;1
"Upgrade";"SprayTerran";NA;554;0
"Upgrade";"SprayTerran";NA;554;0
"Upgrade";"SprayTerran";NA;554;0
"Upgrade";"BansheeCloak";NA;554;0
"Upgrade";"SprayTerran";NA;554;0
"Upgrade";"SprayTerran";NA;554;0
"Upgrade";"PunisherGrenades";NA;554;0
"Upgrade";"SprayTerran";NA;554;0
"Upgrade";"ShieldWall";NA;554;0
"Upgrade";"TerranInfantryArmorsLevel1";NA;554;0
"Upgrade";"SprayTerran";NA;554;0
"Upgrade";"LiberatorAGRangeUpgrade";NA;554;0
"Upgrade";"SprayTerran";NA;554;0
"Upgrade";"TerranVehicleAndShipArmorsLevel1";NA;554;0
"Upgrade";"SprayTerran";NA;554;0
"Upgrade";"SprayTerran";NA;554;0
"Upgrade";"TerranVehicleAndShipArmorsLevel2";NA;554;0
"Upgrade";"SprayTerran";NA;554;0
"Upgrade";"SprayTerran";NA;554;0
"Upgrade";"SprayTerran";NA;554;0
"Upgrade";"SprayTerran";NA;554;0
"Upgrade";"SprayTerran";NA;554;0
"Upgrade";"TerranVehicleAndShipArmorsLevel3";NA;554;0
"Upgrade";"SprayTerran";NA;554;0
"Upgrade";"TerranInfantryArmorsLevel2";NA;554;0
"Upgrade";"SmartServos";NA;554;0
