"Type";"UnitName";"OnBuilding";"TotalSupply";"Supply"
"Unit";"SCV";"Command Center";12;1
"Unit";"SCV";"Command Center";12;1
"Unit";"SCV";"Command Center";13;1
"Building";"SupplyDepot";NA;13;0
"Building";"Refinery";NA;14;0
"Unit";"SCV";"Command Center";15;1
"Unit";"SCV";"Command Center";15;1
"Unit";"SCV";"Command Center";16;1
"Unit";"SCV";"Command Center";17;1
"Building";"Barracks";NA;15;0
"Unit";"Reaper";"Barracks";19;1
"Unit";"SCV";"Command Center";19;1
"Unit";"SCV";"Command Center";21;1
"Building";"SupplyDepot";NA;20;0
"Building";"Factory";NA;19;0
"Unit";"SCV";"Command Center";22;1
"Building";"Refinery";NA;21;0
"Unit";"Reaper";"Barracks";20;1
"Unit";"SCV";"Command Center";22;1
"Building";"CommandCenter";NA;19;0
"Unit";"Hellion";"Factory";22;2
"Unit";"SCV";"Command Center";24;1
"Unit";"SCV";"Command Center";28;1
"Building";"Starport";NA;23;0
"Building";"BarracksReactor";NA;24;0
"Unit";"SCV";"Command Center";28;1
"Building";"SupplyDepot";NA;28;0
"Unit";"SCV";"Command Center";29;1
"Unit";"Cyclone";"Factory";29;3
"Unit";"SCV";"Command Center";31;1
"Unit";"SCV";"Command Center";31;1
"Unit";"Marine";"Barracks";31;1
"Unit";"Marine";"Barracks";31;1
"Unit";"SCV";"Command Center";34;1
"Unit";"SCV";"Command Center";36;1
"Unit";"Medivac";"Starport";31;2
"Building";"EngineeringBay";NA;31;0
"Unit";"SCV";"Command Center";38;1
"Unit";"Marine";"Barracks";38;1
"Unit";"Marine";"Barracks";38;1
"Unit";"Cyclone";"Factory";38;3
"Unit";"SCV";"Command Center";42;1
"Unit";"SCV";"Command Center";43;1
"Building";"MissileTurret";NA;43;0
"Unit";"SCV";"Command Center";48;1
"Unit";"Marine";"Barracks";45;1
"Unit";"Marine";"Barracks";45;1
"Unit";"SCV";"Command Center";49;1
"Building";"SupplyDepot";NA;48;0
"Building";"FactoryTechLab";NA;49;0
"Unit";"SCV";"Command Center";54;1
"Unit";"SCV";"Command Center";54;1
"Unit";"SCV";"Command Center";54;1
"Unit";"SCV";"Command Center";57;1
"Unit";"Marine";"Barracks";57;1
"Unit";"Marine";"Barracks";57;1
"Unit";"SCV";"Command Center";57;1
"Unit";"SCV";"Command Center";57;1
"Unit";"SCV";"Command Center";61;1
"Unit";"SCV";"Command Center";62;1
"Unit";"SCV";"Command Center";62;1
"Building";"BarracksTechLab";NA;62;0
"Building";"MissileTurret";NA;62;0
"Unit";"SCV";"Command Center";64;1
"Unit";"SCV";"Command Center";64;1
"Building";"Refinery";NA;65;0
"Unit";"SCV";"Command Center";67;1
"Unit";"Marine";"Barracks";67;1
"Building";"CommandCenter";NA;61;0
"Unit";"SCV";"Command Center";69;1
"Unit";"Marine";"Barracks";68;1
"Unit";"SCV";"Command Center";69;1
"Unit";"SCV";"Command Center";69;1
"Building";"Barracks";NA;67;0
"Unit";"Marine";"Barracks";70;1
"Building";"SupplyDepot";NA;69;0
"Building";"Barracks";NA;67;0
"Building";"SupplyDepot";NA;71;0
"Building";"StarportReactor";NA;69;0
"Building";"Refinery";NA;71;0
"Unit";"SCV";"Command Center";74;1
"Unit";"Marine";"Barracks";73;1
"Unit";"Marine";"Barracks";74;1
"Unit";"Marine";"Barracks";74;1
"Unit";"SCV";"Command Center";74;1
"Unit";"SCV";"Command Center";74;1
"Unit";"Marine";"Barracks";75;1
"Unit";"Marine";"Barracks";76;1
"Unit";"SCV";"Command Center";80;1
"Unit";"SCV";"Command Center";80;1
"Unit";"Marine";"Barracks";78;1
"Unit";"SCV";"Command Center";80;1
"Unit";"SCV";"Command Center";82;1
"Building";"BarracksTechLab";NA;82;0
"Unit";"SCV";"Command Center";86;1
"Unit";"SCV";"Command Center";86;1
"Building";"StarportReactor";NA;78;0
"Building";"Refinery";NA;86;0
"Building";"Refinery";NA;86;0
"Upgrade";"Stimpack";"TechLab";71;0
"Unit";"Marine";"Barracks";86;1
"Unit";"SCV";"Command Center";89;1
"Unit";"SCV";"Command Center";89;1
"Unit";"SCV";"Command Center";89;1
"Building";"EngineeringBay";NA;86;0
"Unit";"Marine";"Barracks";89;1
"Unit";"SCV";"Command Center";90;1
"Unit";"Marine";"Barracks";89;1
"Unit";"Marine";"Barracks";89;1
"Unit";"SCV";"Command Center";91;1
"Unit";"SCV";"Command Center";92;1
"Upgrade";"TerranInfantryWeaponsLevel1";"EngineeringBay";74;0
"Unit";"SCV";"Command Center";97;1
"Building";"Armory";NA;86;0
"Unit";"Marine";"Barracks";94;1
"Unit";"Medivac";"Starport";94;2
"Unit";"Medivac";"Starport";94;2
"Unit";"SCV";"Command Center";100;1
"Unit";"Marine";"Barracks";99;1
"Unit";"Marine";"Barracks";99;1
"Building";"CommandCenter";NA;82;0
"Unit";"Marauder";"Barracks";99;2
"Building";"SupplyDepot";NA;101;0
"Building";"SupplyDepot";NA;101;0
"Unit";"Marauder";"Barracks";107;2
"Unit";"Marine";"Barracks";110;1
"Unit";"Marauder";"Barracks";110;2
"Unit";"Marine";"Barracks";110;1
"Unit";"SCV";"Command Center";115;1
"Unit";"Marine";"Barracks";112;1
"Unit";"SCV";"Command Center";115;1
"Unit";"SCV";"Command Center";116;1
"Unit";"Marauder";"Barracks";110;2
"Unit";"Marine";"Barracks";113;1
"Unit";"Marine";"Barracks";115;1
"Unit";"SCV";"Command Center";116;1
"Unit";"SCV";"Command Center";118;1
"Unit";"SCV";"Command Center";123;1
"Unit";"Marine";"Barracks";117;1
"Unit";"Marine";"Barracks";122;1
"Unit";"SCV";"Command Center";124;1
"Unit";"Marauder";"Barracks";120;2
"Unit";"SCV";"Command Center";127;1
"Unit";"SCV";"Command Center";127;1
"Unit";"SCV";"Command Center";129;1
"Unit";"Marine";"Barracks";128;1
"Unit";"Marine";"Barracks";128;1
"Unit";"Medivac";"Starport";124;2
"Unit";"Medivac";"Starport";124;2
"Unit";"SCV";"Command Center";132;1
"Unit";"SCV";"Command Center";133;1
"Unit";"SCV";"Command Center";134;1
"Unit";"SCV";"Command Center";141;1
"Unit";"Marine";"Barracks";141;1
"Building";"SupplyDepot";NA;135;0
"Unit";"Marauder";"Barracks";141;2
"Unit";"Marauder";"Barracks";141;2
"Unit";"SCV";"Command Center";144;1
"Unit";"SCV";"Command Center";144;1
"Unit";"SCV";"Command Center";144;1
"Unit";"SCV";"Command Center";145;1
"Building";"SupplyDepot";NA;143;0
"Unit";"Marine";"Barracks";144;1
"Unit";"Medivac";"Starport";143;2
"Unit";"Marine";"Barracks";145;1
"Building";"SupplyDepot";NA;148;0
"Unit";"SCV";"Command Center";155;1
"Unit";"SCV";"Command Center";155;1
"Unit";"SCV";"Command Center";155;1
"Unit";"Marine";"Barracks";154;1
"Unit";"Marine";"Barracks";154;1
"Unit";"Marauder";"Barracks";154;2
"Unit";"Marine";"Barracks";158;1
"Unit";"Marauder";"Barracks";161;2
"Building";"Barracks";NA;153;0
"Building";"Barracks";NA;154;0
"Unit";"Medivac";"Starport";165;2
"Unit";"Medivac";"Starport";165;2
"Unit";"Marine";"Barracks";168;1
"Unit";"Marauder";"Barracks";168;2
"Unit";"Marine";"Barracks";168;1
"Unit";"Marine";"Barracks";168;1
"Building";"BarracksTechLab";NA;168;0
"Unit";"Marine";"Barracks";168;1
"Building";"Starport";NA;166;0
"Building";"Starport";NA;166;0
"Unit";"SCV";"Command Center";178;1
"Unit";"SCV";"Command Center";178;1
"Unit";"SCV";"Command Center";178;1
"Unit";"Marine";"Barracks";177;1
"Unit";"Marine";"Barracks";177;1
"Unit";"Marauder";"Barracks";173;2
"Unit";"Marine";"Barracks";177;1
"Unit";"Marauder";"Barracks";177;2
"Unit";"Marauder";"Barracks";177;2
"Upgrade";"TerranInfantryWeaponsLevel2";"EngineeringBay";152;0
"Unit";"Marine";"Barracks";186;1
"Unit";"Marine";"Barracks";186;1
"Unit";"SCV";"Command Center";190;1
"Unit";"SCV";"Command Center";190;1
"Unit";"SCV";"Command Center";190;1
"Building";"StarportReactor";NA;178;0
"Building";"StarportReactor";NA;178;0
"Unit";"Marauder";"Barracks";186;2
"Unit";"Marauder";"Barracks";186;2
"Unit";"Marauder";"Barracks";188;2
"Building";"Refinery";NA;193;0
"Building";"Refinery";NA;195;0
"Building";"SupplyDepot";NA;201;0
"Building";"SupplyDepot";NA;201;0
"Building";"SupplyDepot";NA;201;0
"Unit";"Marine";"Barracks";201;1
"Unit";"Marine";"Barracks";201;1
"Unit";"Marine";"Barracks";201;1
"Unit";"Marine";"Barracks";201;1
"Unit";"SCV";"Command Center";201;1
"Unit";"SCV";"Command Center";201;1
"Unit";"SCV";"Command Center";203;1
"Unit";"Marauder";"Barracks";201;2
"Unit";"Marauder";"Barracks";201;2
"Unit";"Marine";"Barracks";212;1
"Unit";"Marine";"Barracks";212;1
"Unit";"Marauder";"Barracks";212;2
"Unit";"Marauder";"Barracks";212;2
"Unit";"Marauder";"Barracks";212;2
"Unit";"Marine";"Barracks";220;1
"Unit";"Marine";"Barracks";220;1
"Unit";"Marauder";"Barracks";220;2
"Unit";"Marauder";"Barracks";220;2
"Unit";"Marine";"Barracks";220;1
"Unit";"Marauder";"Barracks";220;2
"Unit";"SCV";"Command Center";226;1
"Unit";"SCV";"Command Center";226;1
