"type";"unit_name";"on_building";"total_supply";"supply"
"Building";"Refinery";NA;14;0
"Building";"Barracks";NA;15;0
"Unit";"Reaper";"Barracks";19;1
"Building";"Factory";NA;19;0
"Building";"Refinery";NA;21;0
"Unit";"Reaper";"Barracks";20;1
"Building";"CommandCenter";NA;19;0
"Unit";"Hellion";"Factory";22;2
"Building";"BarracksReactor";NA;24;0
"Building";"Starport";NA;25;0
"Unit";"Marine";"Barracks";29;1
"Unit";"Marine";"Barracks";29;1
"Unit";"Cyclone";"Factory";30;3
"Unit";"Marine";"Barracks";33;1
"Unit";"Marine";"Barracks";33;1
"Building";"EngineeringBay";NA;33;0
"Unit";"Medivac";"Starport";33;2
"Building";"FactoryTechLab";NA;37;0
"Unit";"Marine";"Barracks";39;1
"Unit";"Marine";"Barracks";39;1
"Building";"MissileTurret";NA;41;0
"Building";"MissileTurret";NA;45;0
"Unit";"Marine";"Barracks";46;1
"Unit";"Marine";"Barracks";46;1
"Unit";"Marine";"Barracks";50;1
"Unit";"Marine";"Barracks";50;1
"Unit";"Liberator";"Starport";52;3
"Building";"BarracksTechLab";NA;56;0
"Building";"Refinery";NA;56;0
"Building";"Refinery";NA;56;0
"Unit";"Marine";"Barracks";63;1
"Unit";"Marine";"Barracks";65;1
"Building";"CommandCenter";NA;56;0
"Unit";"Marine";"Barracks";69;1
"Building";"StarportReactor";NA;66;0
"Building";"Barracks";NA;65;0
"Building";"Barracks";NA;65;0
"Upgrade";"TerranInfantryWeaponsLevel1";"EngineeringBay";58;0
"Building";"Barracks";NA;66;0
"Building";"EngineeringBay";NA;70;0
"Building";"Barracks";NA;66;0
"Unit";"Marine";"Barracks";73;1
"Unit";"Marine";"Barracks";73;1
"Unit";"Marine";"Barracks";73;1
"Building";"Armory";NA;70;0
"Unit";"Medivac";"Starport";73;2
"Unit";"Medivac";"Starport";73;2
"Building";"SensorTower";NA;74;0
"Unit";"Marine";"Barracks";74;1
"Building";"BarracksReactor";NA;73;0
"Building";"SensorTower";NA;79;0
"Building";"BarracksReactor";NA;74;0
"Building";"BarracksReactor";NA;74;0
"Upgrade";"Stimpack";"TechLab";70;0
"Unit";"Marine";"Barracks";88;1
"Unit";"Marine";"Barracks";88;1
"Unit";"Marine";"Barracks";88;1
"Unit";"Marine";"Barracks";88;1
"Unit";"Marine";"Barracks";89;1
"Unit";"Marine";"Barracks";89;1
"Unit";"Marine";"Barracks";91;1
"Unit";"Marine";"Barracks";91;1
"Unit";"Marine";"Barracks";91;1
"Unit";"Marine";"Barracks";91;1
"Unit";"Marine";"Barracks";95;1
"Building";"Refinery";NA;100;0
"Unit";"Marine";"Barracks";102;1
"Unit";"Marine";"Barracks";102;1
"Building";"Refinery";NA;100;0
"Unit";"Marine";"Barracks";102;1
"Unit";"Marine";"Barracks";102;1
"Unit";"Marine";"Barracks";106;1
"Unit";"Marine";"Barracks";106;1
"Unit";"Marine";"Barracks";112;1
"Unit";"Marine";"Barracks";112;1
"Unit";"Marine";"Barracks";114;1
"Unit";"Marine";"Barracks";114;1
"Unit";"Marine";"Barracks";114;1
"Unit";"Marine";"Barracks";114;1
"Building";"SensorTower";NA;114;0
"Unit";"Marine";"Barracks";116;1
"Unit";"Marine";"Barracks";116;1
"Unit";"Marine";"Barracks";116;1
"Unit";"Marine";"Barracks";116;1
"Unit";"Marine";"Barracks";116;1
"Upgrade";"TerranInfantryArmorsLevel1";"EngineeringBay";89;0
"Unit";"Marine";"Barracks";116;1
"Unit";"Marine";"Barracks";117;1
"Unit";"Marine";"Barracks";118;1
"Unit";"Marine";"Barracks";120;1
"Building";"MissileTurret";NA;123;0
"Unit";"Marine";"Barracks";123;1
"Building";"MissileTurret";NA;124;0
"Building";"Factory";NA;116;0
"Unit";"Marine";"Barracks";135;1
"Unit";"Marine";"Barracks";135;1
"Unit";"Marine";"Barracks";135;1
"Unit";"Marine";"Barracks";135;1
"Unit";"Marine";"Barracks";135;1
"Upgrade";"TerranInfantryWeaponsLevel2";"EngineeringBay";102;0
"Unit";"Marine";"Barracks";142;1
"Unit";"Marine";"Barracks";144;1
"Unit";"Marine";"Barracks";144;1
"Unit";"Marine";"Barracks";144;1
"Unit";"Marine";"Barracks";144;1
"Unit";"Marine";"Barracks";144;1
"Unit";"Marine";"Barracks";144;1
"Building";"CommandCenter";NA;123;0
"Unit";"Marine";"Barracks";151;1
"Unit";"Marine";"Barracks";151;1
"Unit";"Marine";"Barracks";151;1
"Building";"MissileTurret";NA;151;0
"Building";"MissileTurret";NA;151;0
"Upgrade";"TerranVehicleWeaponsLevel1";"Armory";134;0
"Building";"Refinery";NA;153;0
"Building";"Refinery";NA;153;0
"Unit";"Medivac";"Starport";153;2
"Unit";"Marine";"Barracks";156;1
"Unit";"Marine";"Barracks";156;1
"Unit";"Marine";"Barracks";157;1
"Unit";"Marine";"Barracks";157;1
"Unit";"Marine";"Barracks";157;1
"Building";"SensorTower";NA;161;0
"Unit";"Marine";"Barracks";161;1
"Unit";"Marine";"Barracks";161;1
"Unit";"Marine";"Barracks";161;1
"Unit";"Liberator";"Starport";153;3
"Unit";"Marine";"Barracks";161;1
"Unit";"Marine";"Barracks";161;1
"Unit";"Marine";"Barracks";161;1
"Unit";"Marine";"Barracks";163;1
"Unit";"Marine";"Barracks";164;1
"Unit";"Marine";"Barracks";164;1
"Building";"FactoryTechLab";NA;164;0
"Unit";"Marine";"Barracks";164;1
"Unit";"Marine";"Barracks";165;1
"Unit";"Liberator";"Starport";157;3
"Upgrade";"TerranInfantryArmorsLevel2";"EngineeringBay";144;0
"Unit";"Marine";"Barracks";181;1
"Unit";"Marine";"Barracks";181;1
"Unit";"Marine";"Barracks";184;1
"Unit";"Marine";"Barracks";184;1
"Unit";"Marine";"Barracks";185;1
"Unit";"Marine";"Barracks";185;1
"Building";"Refinery";NA;185;0
"Building";"MissileTurret";NA;185;0
"Building";"MissileTurret";NA;185;0
"Unit";"Marine";"Barracks";190;1
"Unit";"Marine";"Barracks";191;1
"Unit";"Marine";"Barracks";191;1
"Unit";"Marine";"Barracks";191;1
"Unit";"Marine";"Barracks";191;1
"Unit";"Marine";"Barracks";196;1
"Unit";"Marine";"Barracks";196;1
"Unit";"Marine";"Barracks";196;1
"Unit";"Marine";"Barracks";196;1
"Unit";"Marine";"Barracks";196;1
"Unit";"Marine";"Barracks";196;1
"Unit";"Marine";"Barracks";196;1
"Unit";"Marine";"Barracks";196;1
"Unit";"Marine";"Barracks";198;1
"Unit";"Marine";"Barracks";198;1
"Unit";"Medivac";"Starport";198;2
"Unit";"Medivac";"Starport";198;2
"Upgrade";"TerranInfantryWeaponsLevel3";"EngineeringBay";191;0
"Unit";"Marine";"Barracks";210;1
"Unit";"Marine";"Barracks";210;1
"Unit";"Marine";"Barracks";210;1
"Unit";"Marine";"Barracks";210;1
"Unit";"Liberator";"Starport";210;3
"Unit";"Liberator";"Starport";210;3
"Unit";"Marine";"Barracks";214;1
"Unit";"Marine";"Barracks";215;1
"Unit";"Marine";"Barracks";216;1
"Unit";"Marine";"Barracks";216;1
"Unit";"Marine";"Barracks";216;1
"Unit";"Marine";"Barracks";222;1
"Unit";"Medivac";"Starport";216;2
"Unit";"Medivac";"Starport";219;2
"Unit";"Marine";"Barracks";227;1
"Unit";"Marine";"Barracks";227;1
"Unit";"Marine";"Barracks";227;1
"Unit";"Marine";"Barracks";227;1
"Unit";"Marine";"Barracks";227;1
"Unit";"Medivac";"Starport";240;2
"Unit";"Marine";"Barracks";241;1
"Unit";"Marine";"Barracks";241;1
"Unit";"Marine";"Barracks";241;1
"Unit";"Marine";"Barracks";241;1
"Unit";"Marine";"Barracks";241;1
"Unit";"Marine";"Barracks";241;1
"Unit";"Marine";"Barracks";241;1
"Unit";"Marine";"Barracks";241;1
"Unit";"Marine";"Barracks";241;1
"Building";"CommandCenter";NA;237;0
"Unit";"Marine";"Barracks";243;1
"Unit";"Medivac";"Starport";252;2
"Unit";"Medivac";"Starport";252;2
"Unit";"Marine";"Barracks";253;1
"Unit";"Marine";"Barracks";255;1
"Unit";"Marine";"Barracks";257;1
"Unit";"Marine";"Barracks";257;1
"Unit";"Marine";"Barracks";257;1
"Unit";"Marine";"Barracks";257;1
"Unit";"Marine";"Barracks";257;1
"Unit";"Medivac";"Starport";257;2
"Unit";"Medivac";"Starport";257;2
"Unit";"Marine";"Barracks";259;1
"Unit";"Marine";"Barracks";259;1
"Unit";"Marine";"Barracks";259;1
"Unit";"Marine";"Barracks";262;1
"Unit";"Marine";"Barracks";262;1
"Unit";"Marine";"Barracks";262;1
"Unit";"Marine";"Barracks";262;1
"Unit";"Marine";"Barracks";264;1
"Unit";"Marine";"Barracks";264;1
"Unit";"Marine";"Barracks";275;1
"Unit";"Marine";"Barracks";275;1
"Unit";"Medivac";"Starport";264;2
