"type";"unit_name";"on_building";"total_supply_lag";"supply"
"Building";"Refinery";NA;15;0
"Building";"Barracks";NA;16;0
"Unit";"Reaper";"Barracks";19;1
"Building";"CommandCenter";NA;20;0
"Building";"Factory";NA;21;0
"Building";"BarracksReactor";NA;21;0
"Building";"Refinery";NA;22;0
"Unit";"Marine";"Barracks";24;1
"Unit";"Marine";"Barracks";25;1
"Building";"Starport";NA;26;0
"Unit";"Marine";"Barracks";27;1
"Unit";"Marine";"Barracks";28;1
"Unit";"Marine";"Barracks";30;1
"Unit";"Marine";"Barracks";31;1
"Unit";"Cyclone";"Factory";32;3
"Unit";"Marine";"Barracks";35;1
"Building";"Barracks";NA;36;0
"Building";"Barracks";NA;37;0
"Building";"EngineeringBay";NA;37;0
"Unit";"Marine";"Barracks";42;1
"Unit";"Marine";"Barracks";43;1
"Building";"BarracksTechLab";NA;45;0
"Building";"BarracksTechLab";NA;45;0
"Unit";"Marine";"Barracks";47;1
"Unit";"Marine";"Barracks";48;1
"Upgrade";"TerranInfantryWeaponsLevel1";"EngineeringBay";49;0
"Unit";"Marine";"Barracks";51;1
"Unit";"Marauder";"Barracks";54;2
"Unit";"Marauder";"Barracks";57;2
"Unit";"Marine";"Barracks";61;1
"Unit";"Marine";"Barracks";62;1
"Upgrade";"Stimpack";"TechLab";63;0
"Building";"StarportReactor";NA;63;0
"Building";"FactoryReactor";NA;63;0
"Unit";"Marauder";"Barracks";64;2
"Unit";"Marine";"Barracks";67;1
"Unit";"Marine";"Barracks";68;1
"Unit";"Marauder";"Barracks";70;2
"Unit";"Marauder";"Barracks";73;2
"Unit";"Marine";"Barracks";75;1
"Unit";"Marine";"Barracks";76;1
"Unit";"Medivac";"Starport";77;2
"Unit";"Medivac";"Starport";79;2
"Unit";"Marauder";"Barracks";81;2
"Unit";"Marauder";"Barracks";83;2
"Building";"CommandCenter";NA;85;0
"Building";"Refinery";NA;85;0
"Building";"Refinery";NA;85;0
"Unit";"Marine";"Barracks";86;1
"Building";"Barracks";NA;87;0
"Building";"Barracks";NA;87;0
"Unit";"Marine";"Barracks";87;1
"Unit";"Marine";"Barracks";88;1
"Unit";"Marine";"Barracks";89;1
"Unit";"Medivac";"Starport";92;2
"Unit";"Medivac";"Starport";94;2
"Unit";"Marauder";"Barracks";96;2
"Unit";"Marauder";"Barracks";98;2
"Unit";"Marine";"Barracks";100;1
"Unit";"Marine";"Barracks";101;1
"Unit";"Medivac";"Starport";104;2
"Building";"Starport";NA;106;0
"Unit";"Marine";"Barracks";106;1
"Unit";"Marine";"Barracks";107;1
"Building";"BarracksTechLab";NA;108;0
"Building";"BarracksTechLab";NA;108;0
"Unit";"Marauder";"Barracks";110;2
"Unit";"Marauder";"Barracks";112;2
"Unit";"Marauder";"Barracks";116;2
"Unit";"Marauder";"Barracks";118;2
"Unit";"Marauder";"Barracks";120;2
"Unit";"Marauder";"Barracks";122;2
"Unit";"Marauder";"Barracks";124;2
"Unit";"Marauder";"Barracks";126;2
"Unit";"Marine";"Barracks";128;1
"Unit";"Marine";"Barracks";129;1
"Unit";"Marine";"Barracks";130;1
"Unit";"Marine";"Barracks";131;1
"Unit";"Marine";"Barracks";132;1
"Unit";"Marine";"Barracks";133;1
"Unit";"Marine";"Barracks";134;1
"Unit";"Marine";"Barracks";135;1
"Unit";"Marauder";"Barracks";136;2
"Unit";"Marauder";"Barracks";138;2
"Unit";"Marine";"Barracks";140;1
"Unit";"Marauder";"Barracks";141;2
"Unit";"Marine";"Barracks";143;1
"Unit";"Marine";"Barracks";144;1
"Unit";"Marauder";"Barracks";147;2
"Unit";"Marine";"Barracks";149;1
"Unit";"Marine";"Barracks";152;1
"Unit";"Marine";"Barracks";153;1
"Unit";"Marine";"Barracks";154;1
"Unit";"Marine";"Barracks";155;1
"Unit";"Marine";"Barracks";157;1
"Unit";"Marauder";"Barracks";160;2
"Building";"GhostAcademy";NA;162;0
"Unit";"Marauder";"Barracks";162;2
"Unit";"Marauder";"Barracks";164;2
"Unit";"Liberator";"Starport";166;3
"Unit";"Marauder";"Barracks";169;2
"Unit";"Marine";"Barracks";171;1
"Unit";"Marine";"Barracks";172;1
"Unit";"Marauder";"Barracks";173;2
"Unit";"Liberator";"Starport";175;3
"Unit";"Marine";"Barracks";178;1
"Unit";"Liberator";"Starport";179;3
"Unit";"Liberator";"Starport";182;3
"Unit";"Marine";"Barracks";185;1
"Unit";"Marine";"Barracks";186;1
"Unit";"Marine";"Barracks";187;1
"Unit";"Marine";"Barracks";188;1
"Unit";"Ghost";"Barracks";189;2
"Unit";"Ghost";"Barracks";191;2
"Unit";"Marine";"Barracks";193;1
"Unit";"Marine";"Barracks";194;1
"Building";"Refinery";NA;195;0
"Unit";"Ghost";"Barracks";195;2
"Unit";"Liberator";"Starport";197;3
"Unit";"Ghost";"Barracks";200;2
"Unit";"Ghost";"Barracks";202;2
"Unit";"Marauder";"Barracks";204;2
"Unit";"Marine";"Barracks";206;1
"Unit";"Marine";"Barracks";207;1
"Unit";"Marine";"Barracks";208;1
"Building";"Armory";NA;209;0
"Building";"EngineeringBay";NA;209;0
"Unit";"Ghost";"Barracks";209;2
"Unit";"Ghost";"Barracks";211;2
"Unit";"Marine";"Barracks";213;1
"Unit";"Marine";"Barracks";214;1
"Unit";"Marine";"Barracks";215;1
"Unit";"Marauder";"Barracks";216;2
"Unit";"Liberator";"Starport";218;3
"Unit";"Ghost";"Barracks";221;2
"Unit";"Ghost";"Barracks";223;2
"Unit";"Ghost";"Barracks";225;2
"Unit";"Marine";"Barracks";227;1
"Unit";"Marine";"Barracks";228;1
"Unit";"Marine";"Barracks";229;1
"Upgrade";"SprayTerran";NA;230;0
"Upgrade";"SprayTerran";NA;230;0
"Upgrade";"ShieldWall";NA;230;0
"Upgrade";"SprayTerran";NA;230;0
"Upgrade";"SprayTerran";NA;230;0
"Upgrade";"TerranInfantryArmorsLevel1";NA;230;0
"Upgrade";"PunisherGrenades";NA;230;0
