"type";"unit_name";"on_building";"total_supply";"supply"
"Building";"Refinery";NA;18;0
"Building";"Barracks";NA;18;0
"Building";"CommandCenter";NA;16;0
"Building";"Barracks";NA;20;0
"Building";"BarracksReactor";NA;21;0
"Building";"Barracks";NA;21;0
"Building";"BarracksTechLab";NA;22;0
"Building";"Refinery";NA;22;0
"Unit";"Marine";"Barracks";22;1
"Unit";"Marine";"Barracks";22;1
"Unit";"Marine";"Barracks";23;1
"Unit";"Marine";"Barracks";23;1
"Unit";"Marine";"Barracks";26;1
"Unit";"Marine";"Barracks";26;1
"Unit";"Marine";"Barracks";27;1
"Building";"BarracksReactor";NA;29;0
"Unit";"Marine";"Barracks";34;1
"Unit";"Marine";"Barracks";34;1
"Unit";"Marine";"Barracks";34;1
"Unit";"Marine";"Barracks";36;1
"Unit";"Marine";"Barracks";36;1
"Building";"Factory";NA;30;0
"Unit";"Marine";"Barracks";41;1
"Unit";"Marine";"Barracks";41;1
"Unit";"Marine";"Barracks";41;1
"Unit";"Marine";"Barracks";48;1
"Unit";"Marine";"Barracks";48;1
"Unit";"Marine";"Barracks";48;1
"Unit";"Marine";"Barracks";48;1
"Unit";"Marine";"Barracks";48;1
"Building";"Starport";NA;48;0
"Building";"Refinery";NA;48;0
"Building";"FactoryReactor";NA;48;0
"Unit";"Marine";"Barracks";55;1
"Unit";"Marine";"Barracks";55;1
"Unit";"Marine";"Barracks";55;1
"Unit";"Marine";"Barracks";55;1
"Unit";"Marine";"Barracks";55;1
"Upgrade";"Stimpack";"TechLab";34;0
"Unit";"Marine";"Barracks";64;1
"Unit";"Marine";"Barracks";64;1
"Unit";"Marine";"Barracks";64;1
"Unit";"Medivac";"Starport";64;2
"Unit";"Medivac";"Starport";64;2
"Unit";"Marauder";"Barracks";66;2
"Unit";"Marine";"Barracks";75;1
"Unit";"Marine";"Barracks";75;1
"Unit";"Marine";"Barracks";75;1
"Unit";"Marine";"Barracks";75;1
"Unit";"Marauder";"Barracks";75;2
"Building";"Refinery";NA;77;0
"Unit";"Medivac";"Starport";75;2
"Unit";"Medivac";"Starport";75;2
"Unit";"Marine";"Barracks";77;1
"Building";"FactoryReactor";NA;77;0
"Building";"Barracks";NA;77;0
"Building";"Barracks";NA;81;0
"Unit";"Marine";"Barracks";88;1
"Unit";"Marine";"Barracks";88;1
"Unit";"Marine";"Barracks";88;1
"Unit";"Marine";"Barracks";88;1
"Unit";"Marauder";"Barracks";88;2
"Unit";"Medivac";"Starport";88;2
"Unit";"Medivac";"Starport";88;2
"Unit";"Marine";"Barracks";90;1
"Building";"EngineeringBay";NA;94;0
"Building";"EngineeringBay";NA;94;0
"Unit";"Marine";"Barracks";98;1
"Unit";"Marine";"Barracks";98;1
"Unit";"Marine";"Barracks";98;1
"Unit";"Marine";"Barracks";98;1
"Unit";"Marine";"Barracks";98;1
"Unit";"Marine";"Barracks";98;1
"Building";"BarracksReactor";NA;94;0
"Unit";"Medivac";"Starport";98;2
"Unit";"Marine";"Barracks";112;1
"Unit";"Marine";"Barracks";112;1
"Unit";"Marine";"Barracks";112;1
"Unit";"Marine";"Barracks";112;1
"Unit";"Marine";"Barracks";112;1
"Unit";"Marine";"Barracks";112;1
"Unit";"Marauder";"Barracks";112;2
"Building";"Barracks";NA;98;0
"Building";"Barracks";NA;102;0
"Building";"Barracks";NA;102;0
"Unit";"Marine";"Barracks";116;1
"Unit";"Medivac";"Starport";112;2
"Unit";"Marine";"Barracks";123;1
"Building";"CommandCenter";NA;90;0
"Unit";"Marine";"Barracks";123;1
"Unit";"Marine";"Barracks";125;1
"Unit";"Marine";"Barracks";130;1
"Unit";"Marine";"Barracks";130;1
"Unit";"Marine";"Barracks";130;1
"Building";"BarracksTechLab";NA;130;0
"Unit";"Marauder";"Barracks";130;2
"Building";"BarracksReactor";NA;130;0
"Building";"BarracksReactor";NA;130;0
"Unit";"Marine";"Barracks";134;1
"Unit";"Marine";"Barracks";134;1
"Unit";"Marine";"Barracks";134;1
"Unit";"Marine";"Barracks";134;1
"Unit";"Marine";"Barracks";136;1
"Unit";"Marine";"Barracks";136;1
"Unit";"Marauder";"Barracks";134;2
"Unit";"Marauder";"Barracks";136;2
"Building";"Refinery";NA;136;0
"Unit";"Medivac";"Starport";136;2
"Unit";"Medivac";"Starport";136;2
"Building";"Armory";NA;131;0
"Building";"Starport";NA;136;0
"Upgrade";"TerranInfantryWeaponsLevel1";"EngineeringBay";125;0
"Upgrade";"TerranInfantryArmorsLevel1";"EngineeringBay";126;0
"Unit";"Marine";"Barracks";152;1
"Unit";"Marine";"Barracks";152;1
"Unit";"Marine";"Barracks";152;1
"Unit";"Marine";"Barracks";152;1
"Unit";"Marine";"Barracks";152;1
"Unit";"Marine";"Barracks";152;1
"Unit";"Marine";"Barracks";152;1
"Unit";"Marine";"Barracks";152;1
"Unit";"Marine";"Barracks";152;1
"Unit";"Marine";"Barracks";152;1
"Building";"FusionCore";NA;136;0
"Unit";"Marauder";"Barracks";152;2
"Unit";"Marauder";"Barracks";152;2
"Unit";"Marine";"Barracks";152;1
"Unit";"Marine";"Barracks";152;1
"Building";"StarportTechLab";NA;152;0
"Unit";"Marine";"Barracks";154;1
"Unit";"Marine";"Barracks";155;1
"Unit";"Marine";"Barracks";158;1
"Unit";"Marine";"Barracks";159;1
"Unit";"Marine";"Barracks";160;1
"Unit";"Marauder";"Barracks";164;2
"Unit";"Marauder";"Barracks";166;2
"Unit";"Medivac";"Starport";152;2
"Unit";"Medivac";"Starport";153;2
"Unit";"Marine";"Barracks";175;1
"Unit";"Marine";"Barracks";175;1
"Unit";"Marine";"Barracks";175;1
"Unit";"Marine";"Barracks";175;1
"Unit";"Marine";"Barracks";175;1
"Unit";"Marine";"Barracks";175;1
"Unit";"Marine";"Barracks";175;1
"Unit";"Marine";"Barracks";177;1
"Unit";"Marauder";"Barracks";175;2
"Unit";"Marine";"Barracks";193;1
"Unit";"Marauder";"Barracks";195;2
"Building";"Refinery";NA;195;0
"Unit";"Marine";"Barracks";195;1
"Unit";"Marine";"Barracks";196;1
"Unit";"Marine";"Barracks";196;1
"Unit";"Marine";"Barracks";196;1
"Unit";"Marauder";"Barracks";198;2
"Unit";"Marauder";"Barracks";198;2
"Unit";"Marine";"Barracks";202;1
"Unit";"Marine";"Barracks";202;1
"Unit";"Marine";"Barracks";202;1
"Unit";"Marine";"Barracks";202;1
"Unit";"Marine";"Barracks";202;1
"Unit";"Marine";"Barracks";202;1
"Unit";"Marine";"Barracks";206;1
"Unit";"Marine";"Barracks";206;1
"Unit";"Marine";"Barracks";206;1
"Unit";"Marine";"Barracks";206;1
"Unit";"Marauder";"Barracks";202;2
"Unit";"Marauder";"Barracks";202;2
"Unit";"Liberator";"Starport";198;3
"Unit";"Liberator";"Starport";198;3
"Unit";"Marine";"Barracks";212;1
"Unit";"Marine";"Barracks";212;1
"Building";"CommandCenter";NA;195;0
"Upgrade";"TerranInfantryWeaponsLevel2";"EngineeringBay";193;0
"Upgrade";"TerranInfantryArmorsLevel2";"EngineeringBay";193;0
"Unit";"Marauder";"Barracks";216;2
"Unit";"Marauder";"Barracks";216;2
"Unit";"Marine";"Barracks";232;1
"Unit";"Marine";"Barracks";232;1
"Unit";"Marine";"Barracks";232;1
"Unit";"Marine";"Barracks";232;1
"Unit";"Marine";"Barracks";232;1
"Unit";"Marine";"Barracks";232;1
"Unit";"Marine";"Barracks";232;1
"Unit";"Marine";"Barracks";232;1
"Unit";"Marine";"Barracks";232;1
"Unit";"Marine";"Barracks";232;1
"Unit";"Marine";"Barracks";232;1
"Unit";"Marine";"Barracks";232;1
"Unit";"Marauder";"Barracks";228;2
"Unit";"Marauder";"Barracks";232;2
"Upgrade";"TerranShipWeaponsLevel1";"Armory";202;0
"Unit";"Marine";"Barracks";232;1
"Building";"CommandCenter";NA;212;0
"Unit";"Marine";"Barracks";233;1
"Unit";"Marauder";"Barracks";244;2
"Unit";"Marauder";"Barracks";246;2
"Unit";"Marine";"Barracks";248;1
"Unit";"Marine";"Barracks";248;1
"Unit";"Marine";"Barracks";248;1
"Unit";"Marine";"Barracks";248;1
"Unit";"Marine";"Barracks";248;1
"Unit";"Marine";"Barracks";248;1
"Unit";"Marauder";"Barracks";250;2
"Unit";"Marauder";"Barracks";252;2
"Unit";"Marine";"Barracks";257;1
"Unit";"Marine";"Barracks";258;1
"Unit";"Marine";"Barracks";259;1
"Unit";"Marine";"Barracks";260;1
"Unit";"Marine";"Barracks";260;1
"Unit";"Marine";"Barracks";260;1
"Unit";"Marine";"Barracks";260;1
"Unit";"Marine";"Barracks";260;1
"Unit";"Marine";"Barracks";260;1
"Unit";"Liberator";"Starport";248;3
"Unit";"Marauder";"Barracks";260;2
"Unit";"Marauder";"Barracks";262;2
"Unit";"Marine";"Barracks";280;1
"Unit";"Marine";"Barracks";280;1
"Unit";"Marine";"Barracks";280;1
"Unit";"Marine";"Barracks";280;1
"Unit";"Marine";"Barracks";280;1
"Unit";"Marine";"Barracks";280;1
"Unit";"Marauder";"Barracks";276;2
"Unit";"Marauder";"Barracks";278;2
