"Type";"UnitName";"OnBuilding";"TotalSupply";"Supply"
"Unit";"SCV";"Command Center";12;1
"Unit";"SCV";"Command Center";12;1
"Unit";"SCV";"Command Center";13;1
"Building";"SupplyDepot";NA;13;0
"Unit";"SCV";"Command Center";15;1
"Unit";"SCV";"Command Center";15;1
"Building";"Refinery";NA;15;0
"Unit";"SCV";"Command Center";16;1
"Unit";"SCV";"Command Center";17;1
"Building";"Barracks";NA;15;0
"Unit";"Reaper";"Barracks";19;1
"Unit";"SCV";"Command Center";19;1
"Building";"SupplyDepot";NA;19;0
"Unit";"Marine";"Barracks";20;1
"Unit";"SCV";"Command Center";21;1
"Unit";"SCV";"Command Center";22;1
"Unit";"Marine";"Barracks";21;1
"Unit";"SCV";"Command Center";23;1
"Building";"Refinery";NA;23;0
"Building";"CommandCenter";NA;19;0
"Unit";"SCV";"Command Center";25;1
"Building";"Factory";NA;21;0
"Unit";"SCV";"Command Center";26;1
"Unit";"SCV";"Command Center";27;1
"Unit";"Hellion";"Factory";27;2
"Building";"BarracksReactor";NA;26;0
"Unit";"SCV";"Command Center";28;1
"Unit";"SCV";"Command Center";31;1
"Building";"SupplyDepot";NA;28;0
"Unit";"SCV";"Command Center";31;1
"Building";"Starport";NA;28;0
"Unit";"SCV";"Command Center";33;1
"Building";"BarracksTechLab";NA;32;0
"Unit";"Hellion";"Factory";32;2
"Unit";"Hellion";"Factory";32;2
"Unit";"SCV";"Command Center";34;1
"Building";"SupplyDepot";NA;33;0
"Unit";"SCV";"Command Center";35;1
"Unit";"SCV";"Command Center";39;1
"Unit";"Hellion";"Factory";35;2
"Unit";"Hellion";"Factory";37;2
"Unit";"SCV";"Command Center";41;1
"Unit";"SCV";"Command Center";42;1
"Building";"BarracksTechLab";NA;42;0
"Unit";"SCV";"Command Center";46;1
"Unit";"SCV";"Command Center";48;1
"Unit";"Banshee";"Starport";39;3
"Unit";"SCV";"Command Center";49;1
"Building";"SupplyDepot";NA;48;0
"Unit";"SCV";"Command Center";53;1
"Unit";"SCV";"Command Center";54;1
"Unit";"SCV";"Command Center";55;1
"Unit";"Marine";"Barracks";55;1
"Unit";"SCV";"Command Center";55;1
"Building";"FactoryReactor";NA;53;0
"Unit";"SCV";"Command Center";57;1
"Building";"Refinery";NA;55;0
"Building";"EngineeringBay";NA;55;0
"Building";"Barracks";NA;50;0
"Building";"EngineeringBay";NA;55;0
"Building";"Barracks";NA;53;0
"Unit";"Banshee";"Starport";54;3
"Unit";"Marine";"Barracks";58;1
"Building";"Refinery";NA;58;0
"Building";"CommandCenter";NA;48;0
"Unit";"SCV";"Command Center";64;1
"Unit";"Marine";"Barracks";63;1
"Unit";"Marine";"Barracks";63;1
"Unit";"SCV";"Command Center";64;1
"Unit";"Marine";"Barracks";64;1
"Unit";"Marine";"Barracks";64;1
"Unit";"Marine";"Barracks";64;1
"Unit";"SCV";"Command Center";65;1
"Building";"Barracks";NA;59;0
"Building";"Barracks";NA;59;0
"Building";"SupplyDepot";NA;64;0
"Unit";"Marine";"Barracks";65;1
"Unit";"SCV";"Command Center";68;1
"Unit";"Marine";"Barracks";66;1
"Unit";"SCV";"Command Center";72;1
"Unit";"Marine";"Barracks";68;1
"Unit";"Marine";"Barracks";69;1
"Unit";"Marine";"Barracks";72;1
"Building";"StarportReactor";NA;65;0
"Unit";"SCV";"Command Center";75;1
"Unit";"Marine";"Barracks";72;1
"Unit";"SCV";"Command Center";75;1
"Unit";"Marine";"Barracks";74;1
"Upgrade";"Stimpack";"TechLab";57;0
"Unit";"SCV";"Command Center";80;1
"Unit";"SCV";"Command Center";81;1
"Unit";"Marine";"Barracks";79;1
"Unit";"Marine";"Barracks";79;1
"Unit";"Marine";"Barracks";79;1
"Unit";"Marine";"Barracks";83;1
"Unit";"Marine";"Barracks";83;1
"Unit";"SCV";"Command Center";83;1
"Unit";"SCV";"Command Center";84;1
"Building";"BarracksReactor";NA;78;0
"Building";"BarracksReactor";NA;78;0
"Unit";"Marine";"Barracks";85;1
"Unit";"Marine";"Barracks";86;1
"Unit";"Marine";"Barracks";87;1
"Unit";"SCV";"Command Center";90;1
"Unit";"Marine";"Barracks";88;1
"Unit";"Marine";"Barracks";90;1
"Building";"SupplyDepot";NA;92;0
"Building";"SupplyDepot";NA;92;0
"Unit";"Marine";"Barracks";92;1
"Unit";"Marine";"Barracks";93;1
"Unit";"Medivac";"Starport";92;2
"Unit";"Medivac";"Starport";95;2
"Building";"SupplyDepot";NA;98;0
"Unit";"SCV";"Command Center";100;1
"Upgrade";"TerranInfantryWeaponsLevel1";"EngineeringBay";78;0
"Unit";"SCV";"Command Center";102;1
"Unit";"SCV";"Command Center";102;1
"Unit";"Marine";"Barracks";100;1
"Unit";"Marine";"Barracks";100;1
"Unit";"Marine";"Barracks";100;1
"Unit";"Marine";"Barracks";100;1
"Unit";"Marine";"Barracks";100;1
"Unit";"Marine";"Barracks";100;1
"Unit";"Marine";"Barracks";100;1
"Building";"SupplyDepot";NA;104;0
"Building";"SupplyDepot";NA;104;0
"Building";"SupplyDepot";NA;104;0
"Unit";"SCV";"Command Center";114;1
"Unit";"SCV";"Command Center";114;1
"Unit";"SCV";"Command Center";114;1
"Unit";"Marine";"Barracks";114;1
"Unit";"Marine";"Barracks";114;1
"Unit";"Marine";"Barracks";114;1
"Unit";"Marine";"Barracks";114;1
"Unit";"Marine";"Barracks";114;1
"Unit";"Marine";"Barracks";114;1
"Unit";"Marine";"Barracks";114;1
"Unit";"Marine";"Barracks";114;1
"Building";"Armory";NA;100;0
"Unit";"Medivac";"Starport";104;2
"Unit";"Medivac";"Starport";104;2
"Unit";"SCV";"Command Center";114;1
"Unit";"SCV";"Command Center";115;1
"Unit";"Marine";"Barracks";114;1
"Unit";"Marine";"Barracks";117;1
"Unit";"Marine";"Barracks";118;1
"Unit";"Marine";"Barracks";119;1
"Building";"Refinery";NA;117;0
"Building";"Refinery";NA;117;0
"Unit";"Marine";"Barracks";125;1
"Unit";"Marine";"Barracks";125;1
"Unit";"Marine";"Barracks";125;1
"Building";"SupplyDepot";NA;118;0
"Building";"SupplyDepot";NA;125;0
"Building";"SupplyDepot";NA;125;0
"Unit";"Marine";"Barracks";138;1
"Unit";"Marine";"Barracks";138;1
"Unit";"Marine";"Barracks";138;1
"Unit";"Marine";"Barracks";138;1
"Unit";"Marine";"Barracks";138;1
"Unit";"Marine";"Barracks";138;1
"Unit";"Marine";"Barracks";138;1
"Unit";"Marine";"Barracks";138;1
"Unit";"Marine";"Barracks";138;1
"Unit";"Marine";"Barracks";138;1
"Unit";"SCV";"Command Center";144;1
"Unit";"SCV";"Command Center";144;1
"Unit";"SCV";"Command Center";144;1
"Unit";"Marine";"Barracks";147;1
"Unit";"Marine";"Barracks";147;1
"Unit";"Marine";"Barracks";147;1
"Unit";"Marine";"Barracks";147;1
"Unit";"Marine";"Barracks";147;1
"Building";"SupplyDepot";NA;151;0
"Building";"SupplyDepot";NA;151;0
"Building";"SupplyDepot";NA;151;0
"Building";"SupplyDepot";NA;156;0
"Building";"SupplyDepot";NA;156;0
"Unit";"Marine";"Barracks";156;1
"Unit";"Marine";"Barracks";156;1
"Unit";"Marine";"Barracks";156;1
"Unit";"Marine";"Barracks";156;1
"Unit";"Marine";"Barracks";156;1
"Unit";"Marine";"Barracks";156;1
"Unit";"Marine";"Barracks";156;1
"Unit";"Marine";"Barracks";156;1
"Unit";"Marine";"Barracks";156;1
"Unit";"Marine";"Barracks";156;1
"Unit";"Marine";"Barracks";157;1
"Unit";"Marine";"Barracks";158;1
"Unit";"Marine";"Barracks";159;1
"Unit";"Marine";"Barracks";160;1
"Unit";"Marine";"Barracks";161;1
"Unit";"Marine";"Barracks";162;1
"Unit";"Marine";"Barracks";162;1
"Unit";"Marine";"Barracks";162;1
"Unit";"Marine";"Barracks";165;1
"Unit";"Marine";"Barracks";166;1
"Unit";"Marine";"Barracks";167;1
"Unit";"Marine";"Barracks";168;1
"Unit";"Marine";"Barracks";169;1
"Unit";"Medivac";"Starport";162;2
"Unit";"Medivac";"Starport";162;2
"Unit";"Marine";"Barracks";171;1
"Unit";"Marine";"Barracks";171;1
"Unit";"Marine";"Barracks";171;1
"Unit";"Marine";"Barracks";171;1
"Unit";"Marine";"Barracks";174;1
"Unit";"Marine";"Barracks";175;1
"Unit";"Marine";"Barracks";176;1
"Unit";"Marine";"Barracks";177;1
"Unit";"Marine";"Barracks";178;1
"Building";"Barracks";NA;165;0
"Unit";"Marine";"Barracks";184;1
"Unit";"Marine";"Barracks";184;1
"Unit";"Marine";"Barracks";184;1
"Unit";"Marine";"Barracks";184;1
"Unit";"Marine";"Barracks";187;1
"Unit";"Marine";"Barracks";188;1
"Unit";"Marine";"Barracks";192;1
"Unit";"Marine";"Barracks";192;1
"Unit";"Marine";"Barracks";192;1
"Unit";"Marine";"Barracks";192;1
"Unit";"Marine";"Barracks";193;1
"Unit";"Medivac";"Starport";192;2
"Unit";"Medivac";"Starport";192;2
"Building";"CommandCenter";NA;171;0
"Unit";"Marine";"Barracks";203;1
"Unit";"Marine";"Barracks";203;1
"Unit";"Marine";"Barracks";203;1
"Unit";"Marine";"Barracks";203;1
"Unit";"Marine";"Barracks";203;1
"Unit";"Marine";"Barracks";205;1
"Unit";"Marine";"Barracks";205;1
"Unit";"Marine";"Barracks";205;1
"Unit";"Marine";"Barracks";205;1
"Unit";"Marine";"Barracks";207;1
"Unit";"Marine";"Barracks";208;1
"Unit";"Marine";"Barracks";209;1
"Unit";"Marine";"Barracks";209;1
"Unit";"Marine";"Barracks";209;1
"Unit";"Marine";"Barracks";212;1
"Unit";"Marine";"Barracks";212;1
"Unit";"Marine";"Barracks";214;1
"Unit";"Marine";"Barracks";214;1
