"Type";"UnitName";"OnBuilding";"TotalSupply";"Supply"
"Unit";"SCV";"Command Center";12;1
"Unit";"SCV";"Command Center";12;1
"Unit";"SCV";"Command Center";13;1
"Building";"SupplyDepot";NA;13;0
"Unit";"SCV";"Command Center";15;1
"Unit";"SCV";"Command Center";15;1
"Building";"Refinery";NA;15;0
"Unit";"SCV";"Command Center";16;1
"Building";"Barracks";NA;15;0
"Unit";"SCV";"Command Center";17;1
"Unit";"Reaper";"Barracks";19;1
"Unit";"SCV";"Command Center";19;1
"Building";"SupplyDepot";NA;19;0
"Unit";"Marine";"Barracks";19;1
"Unit";"SCV";"Command Center";20;1
"Unit";"SCV";"Command Center";22;1
"Unit";"SCV";"Command Center";23;1
"Building";"CommandCenter";NA;19;0
"Unit";"SCV";"Command Center";24;1
"Building";"Factory";NA;21;0
"Building";"BarracksReactor";NA;23;0
"Unit";"SCV";"Command Center";26;1
"Building";"Refinery";NA;25;0
"Unit";"SCV";"Command Center";27;1
"Unit";"Hellion";"Factory";26;2
"Unit";"Hellion";"Factory";26;2
"Unit";"SCV";"Command Center";27;1
"Unit";"SCV";"Command Center";27;1
"Unit";"SCV";"Command Center";32;1
"Unit";"SCV";"Command Center";33;1
"Unit";"Hellion";"Factory";33;2
"Unit";"Hellion";"Factory";33;2
"Unit";"SCV";"Command Center";34;1
"Unit";"SCV";"Command Center";36;1
"Building";"SupplyDepot";NA;34;0
"Unit";"SCV";"Command Center";40;1
"Building";"CommandCenter";NA;26;0
"Unit";"SCV";"Command Center";42;1
"Unit";"Hellion";"Factory";36;2
"Unit";"Hellion";"Factory";38;2
"Unit";"SCV";"Command Center";42;1
"Building";"SupplyDepot";NA;42;0
"Unit";"SCV";"Command Center";43;1
"Unit";"SCV";"Command Center";48;1
"Unit";"SCV";"Command Center";49;1
"Unit";"Hellion";"Factory";48;2
"Unit";"Hellion";"Factory";48;2
"Building";"Refinery";NA;49;0
"Unit";"SCV";"Command Center";50;1
"Building";"Refinery";NA;49;0
"Unit";"SCV";"Command Center";51;1
"Unit";"SCV";"Command Center";56;1
"Unit";"SCV";"Command Center";57;1
"Unit";"SCV";"Command Center";57;1
"Unit";"SCV";"Command Center";58;1
"Unit";"SCV";"Command Center";59;1
"Unit";"SCV";"Command Center";60;1
"Building";"Armory";NA;50;0
"Building";"Armory";NA;50;0
"Unit";"SCV";"Command Center";61;1
"Unit";"SCV";"Command Center";62;1
"Unit";"Hellion";"Factory";61;2
"Unit";"Hellion";"Factory";61;2
"Unit";"SCV";"Command Center";64;1
"Building";"BarracksReactor";NA;58;0
"Building";"Factory";NA;57;0
"Building";"Starport";NA;58;0
"Building";"Factory";NA;58;0
"Unit";"SCV";"Command Center";70;1
"Unit";"SCV";"Command Center";70;1
"Unit";"SCV";"Command Center";71;1
"Building";"SupplyDepot";NA;70;0
"Building";"SupplyDepot";NA;71;0
"Building";"FactoryTechLab";NA;71;0
"Building";"FactoryTechLab";NA;71;0
"Unit";"SCV";"Command Center";73;1
"Unit";"SCV";"Command Center";73;1
"Unit";"SCV";"Command Center";73;1
"Unit";"SCV";"Command Center";74;1
"Building";"Refinery";NA;73;0
"Building";"Refinery";NA;73;0
"Unit";"Medivac";"Starport";77;2
"Building";"CommandCenter";NA;65;0
"Unit";"Thor";"Factory";74;6
"Unit";"Thor";"Factory";76;6
"Unit";"Liberator";"Starport";78;3
"Unit";"SCV";"Command Center";92;1
"Unit";"SCV";"Command Center";92;1
"Unit";"SCV";"Command Center";92;1
"Unit";"SCV";"Command Center";95;1
"Unit";"SCV";"Command Center";96;1
"Unit";"SCV";"Command Center";97;1
"Upgrade";"TerranVehicleWeaponsLevel1";"Armory";77;0
"Upgrade";"TerranVehicleAndShipArmorsLevel1";"Armory";77;0
"Unit";"SCV";"Command Center";98;1
"Unit";"SCV";"Command Center";99;1
"Unit";"SCV";"Command Center";100;1
"Unit";"SCV";"Command Center";101;1
"Unit";"SCV";"Command Center";102;1
"Unit";"SCV";"Command Center";103;1
"Unit";"SCV";"Command Center";104;1
"Unit";"SCV";"Command Center";105;1
"Unit";"SCV";"Command Center";106;1
"Unit";"SCV";"Command Center";107;1
"Unit";"SCV";"Command Center";107;1
"Unit";"SCV";"Command Center";108;1
"Unit";"SCV";"Command Center";109;1
"Unit";"SCV";"Command Center";110;1
"Unit";"Liberator";"Starport";101;3
"Unit";"SCV";"Command Center";111;1
"Unit";"SCV";"Command Center";118;1
"Unit";"SCV";"Command Center";119;1
"Unit";"SCV";"Command Center";119;1
"Unit";"SCV";"Command Center";119;1
"Building";"Refinery";NA;119;0
"Unit";"SCV";"Command Center";119;1
"Building";"SupplyDepot";NA;119;0
"Unit";"SCV";"Command Center";120;1
"Unit";"SCV";"Command Center";123;1
"Unit";"SCV";"Command Center";123;1
"Unit";"SCV";"Command Center";124;1
"Unit";"SCV";"Command Center";124;1
"Building";"SupplyDepot";NA;124;0
"Building";"FactoryTechLab";NA;127;0
"Building";"SupplyDepot";NA;127;0
"Building";"EngineeringBay";NA;129;0
"Building";"FactoryReactor";NA;127;0
"Unit";"Medivac";"Starport";129;2
"Unit";"Medivac";"Starport";129;2
"Unit";"SCV";"Command Center";129;1
"Unit";"SCV";"Command Center";129;1
"Building";"MissileTurret";NA;129;0
"Building";"MissileTurret";NA;133;0
"Building";"MissileTurret";NA;133;0
"Building";"MissileTurret";NA;133;0
"Building";"Starport";NA;133;0
"Building";"Starport";NA;133;0
"Building";"Starport";NA;135;0
"Building";"Factory";NA;133;0
"Building";"SupplyDepot";NA;135;0
"Building";"SupplyDepot";NA;135;0
"Building";"SupplyDepot";NA;135;0
"Unit";"Liberator";"Starport";135;3
"Unit";"Liberator";"Starport";135;3
"Unit";"Hellion";"Factory";135;2
"Building";"StarportTechLab";NA;135;0
"Building";"StarportTechLab";NA;135;0
"Building";"StarportTechLab";NA;135;0
"Upgrade";"TerranVehicleWeaponsLevel2";"Armory";129;0
"Building";"FactoryTechLab";NA;141;0
"Building";"CommandCenter";NA;135;0
"Upgrade";"TerranVehicleAndShipArmorsLevel2";"Armory";129;0
"Unit";"Liberator";"Starport";141;3
"Unit";"Liberator";"Starport";141;3
"Building";"SensorTower";NA;143;0
"Building";"MissileTurret";NA;143;0
"Building";"MissileTurret";NA;143;0
"Building";"MissileTurret";NA;143;0
"Building";"Refinery";NA;143;0
"Building";"Refinery";NA;143;0
"Building";"SupplyDepot";NA;149;0
"Unit";"SCV";"Command Center";149;1
"Unit";"SCV";"Command Center";149;1
"Building";"MissileTurret";NA;149;0
"Unit";"Raven";"Starport";149;2
"Unit";"Raven";"Starport";149;2
"Unit";"Raven";"Starport";149;2
"Unit";"Hellion";"Factory";149;2
"Unit";"Hellion";"Factory";149;2
"Unit";"Hellion";"Factory";149;2
"Unit";"SCV";"Command Center";151;1
"Unit";"SCV";"Command Center";151;1
"Unit";"SCV";"Command Center";151;1
"Building";"CommandCenter";NA;149;0
"Unit";"Thor";"Factory";149;6
"Building";"FactoryTechLab";NA;166;0
"Unit";"Banshee";"Starport";166;3
"Unit";"Banshee";"Starport";166;3
"Building";"FactoryReactor";NA;166;0
"Building";"StarportReactor";NA;172;0
"Unit";"Raven";"Starport";172;2
"Unit";"Banshee";"Starport";178;3
"Unit";"Banshee";"Starport";178;3
"Building";"CommandCenter";NA;178;0
"Building";"FactoryReactor";NA;186;0
"Unit";"Raven";"Starport";186;2
"Unit";"Raven";"Starport";186;2
"Unit";"Raven";"Starport";186;2
"Building";"Factory";NA;186;0
"Building";"Factory";NA;186;0
"Unit";"Hellion";"Factory";192;2
"Unit";"Hellion";"Factory";192;2
"Building";"FactoryTechLab";NA;192;0
"Building";"FactoryTechLab";NA;196;0
"Building";"FactoryTechLab";NA;196;0
"Unit";"SCV";"Command Center";196;1
"Unit";"SCV";"Command Center";196;1
"Unit";"SCV";"Command Center";196;1
"Building";"Refinery";NA;196;0
"Building";"Refinery";NA;196;0
"Unit";"Raven";"Starport";196;2
"Unit";"Raven";"Starport";196;2
"Building";"FactoryTechLab";NA;199;0
"Unit";"SCV";"Command Center";203;1
"Unit";"SCV";"Command Center";203;1
"Unit";"SCV";"Command Center";203;1
"Building";"SensorTower";NA;203;0
"Upgrade";"TerranVehicleWeaponsLevel3";"Armory";192;0
"Upgrade";"TerranVehicleAndShipArmorsLevel3";"Armory";192;0
"Building";"MissileTurret";NA;206;0
"Building";"MissileTurret";NA;206;0
"Unit";"Raven";"Starport";203;2
"Unit";"Raven";"Starport";203;2
"Unit";"Raven";"Starport";203;2
"Building";"SensorTower";NA;206;0
"Building";"MissileTurret";NA;206;0
"Building";"MissileTurret";NA;212;0
"Building";"MissileTurret";NA;212;0
"Building";"FactoryReactor";NA;212;0
"Building";"CommandCenter";NA;206;0
"Unit";"Banshee";"Starport";206;3
"Unit";"Hellion";"Factory";215;2
"Unit";"Hellion";"Factory";215;2
"Unit";"Raven";"Starport";212;2
"Unit";"Raven";"Starport";212;2
"Building";"MissileTurret";NA;215;0
"Unit";"Raven";"Starport";212;2
"Unit";"Hellion";"Factory";215;2
"Unit";"Hellion";"Factory";217;2
"Unit";"Hellion";"Factory";219;2
"Unit";"Hellion";"Factory";219;2
"Unit";"SCV";"Command Center";223;1
"Unit";"SCV";"Command Center";223;1
"Unit";"SCV";"Command Center";223;1
"Unit";"SCV";"Command Center";223;1
"Unit";"SCV";"Command Center";229;1
"Unit";"SCV";"Command Center";229;1
"Unit";"SCV";"Command Center";233;1
"Unit";"SCV";"Command Center";234;1
"Unit";"SCV";"Command Center";235;1
"Unit";"Raven";"Starport";219;2
"Unit";"Raven";"Starport";221;2
"Unit";"SCV";"Command Center";239;1
"Unit";"SCV";"Command Center";239;1
"Building";"Refinery";NA;239;0
"Unit";"Raven";"Starport";223;2
"Unit";"Hellion";"Factory";242;2
"Unit";"Hellion";"Factory";242;2
"Unit";"Hellion";"Factory";242;2
"Building";"Refinery";NA;242;0
"Unit";"Raven";"Starport";248;2
"Building";"CommandCenter";NA;242;0
"Unit";"Raven";"Starport";256;2
"Unit";"Raven";"Starport";256;2
"Building";"CommandCenter";NA;246;0
"Building";"GhostAcademy";NA;256;0
"Unit";"Hellion";"Factory";258;2
"Unit";"Hellion";"Factory";258;2
"Unit";"Hellion";"Factory";258;2
"Building";"CommandCenter";NA;248;0
"Unit";"Hellion";"Factory";258;2
"Unit";"Hellion";"Factory";258;2
"Building";"Barracks";NA;256;0
"Building";"Barracks";NA;256;0
"Building";"Barracks";NA;256;0
"Building";"BarracksTechLab";NA;272;0
"Building";"BarracksTechLab";NA;272;0
"Building";"BarracksTechLab";NA;272;0
"Unit";"Thor";"Factory";262;6
"Unit";"Raven";"Starport";262;2
"Unit";"Raven";"Starport";262;2
"Unit";"Raven";"Starport";262;2
"Building";"BarracksTechLab";NA;272;0
"Unit";"Thor";"Factory";272;6
"Unit";"Thor";"Factory";272;6
"Unit";"Raven";"Starport";278;2
"Unit";"Raven";"Starport";280;2
"Upgrade";"PersonalCloaking";"GhostAcademy";284;0
"Unit";"Ghost";"Barracks";284;2
"Unit";"Ghost";"Barracks";284;2
"Unit";"Reaper";"Barracks";284;1
"Unit";"Reaper";"Barracks";284;1
"Building";"SensorTower";NA;300;0
"Building";"MissileTurret";NA;300;0
"Unit";"Raven";"Starport";284;2
"Unit";"Raven";"Starport";296;2
"Building";"Refinery";NA;304;0
"Building";"Refinery";NA;306;0
"Unit";"Ghost";"Barracks";300;2
"Unit";"Ghost";"Barracks";302;2
"Upgrade";"TerranShipWeaponsLevel1";"Armory";284;0
"Unit";"Ghost";"Barracks";304;2
"Unit";"Ghost";"Barracks";305;2
"Unit";"Hellion";"Factory";318;2
"Unit";"Hellion";"Factory";318;2
"Unit";"Hellion";"Factory";318;2
"Unit";"Raven";"Starport";318;2
"Unit";"Raven";"Starport";324;2
"Unit";"Raven";"Starport";324;2
"Building";"CommandCenter";NA;318;0
"Unit";"Ghost";"Barracks";326;2
"Unit";"Ghost";"Barracks";326;2
"Unit";"Ghost";"Barracks";326;2
"Building";"MissileTurret";NA;336;0
"Unit";"Raven";"Starport";330;2
"Building";"MissileTurret";NA;336;0
"Building";"SensorTower";NA;336;0
"Unit";"SCV";"Command Center";338;1
"Unit";"SCV";"Command Center";338;1
"Unit";"SCV";"Command Center";338;1
"Unit";"SCV";"Command Center";338;1
"Unit";"SCV";"Command Center";338;1
"Unit";"Ghost";"Barracks";336;2
"Unit";"Ghost";"Barracks";336;2
"Unit";"Ghost";"Barracks";336;2
"Unit";"Ghost";"Barracks";336;2
"Building";"CommandCenter";NA;326;0
"Unit";"Hellion";"Factory";351;2
"Unit";"Hellion";"Factory";351;2
"Unit";"Hellion";"Factory";351;2
"Unit";"SCV";"Command Center";351;1
"Unit";"SCV";"Command Center";351;1
"Unit";"SCV";"Command Center";351;1
"Unit";"SCV";"Command Center";351;1
"Unit";"SCV";"Command Center";351;1
"Unit";"SCV";"Command Center";351;1
"Unit";"SCV";"Command Center";351;1
"Building";"Refinery";NA;360;0
"Building";"Refinery";NA;360;0
"Unit";"Hellion";"Factory";364;2
"Unit";"Hellion";"Factory";364;2
"Unit";"Hellion";"Factory";364;2
"Unit";"Hellion";"Factory";364;2
"Unit";"Hellion";"Factory";364;2
"Unit";"Hellion";"Factory";364;2
"Building";"SensorTower";NA;364;0
"Unit";"Ghost";"Barracks";364;2
"Building";"MissileTurret";NA;364;0
"Unit";"Raven";"Starport";364;2
"Unit";"Raven";"Starport";364;2
"Unit";"Raven";"Starport";364;2
"Unit";"Hellion";"Factory";364;2
"Unit";"Hellion";"Factory";366;2
"Building";"SensorTower";NA;376;0
"Building";"CommandCenter";NA;364;0
"Unit";"Raven";"Starport";378;2
"Unit";"Ghost";"Barracks";388;2
"Building";"MissileTurret";NA;388;0
"Building";"MissileTurret";NA;388;0
"Unit";"Banshee";"Starport";388;3
"Unit";"Banshee";"Starport";388;3
"Building";"CommandCenter";NA;378;0
"Unit";"Raven";"Starport";388;2
"Building";"Refinery";NA;400;0
"Building";"Refinery";NA;400;0
"Unit";"Raven";"Starport";400;2
"Unit";"Raven";"Starport";400;2
"Unit";"Raven";"Starport";400;2
"Unit";"Raven";"Starport";400;2
"Unit";"Raven";"Starport";402;2
"Building";"CommandCenter";NA;400;0
"Building";"CommandCenter";NA;400;0
"Building";"CommandCenter";NA;400;0
"Building";"CommandCenter";NA;400;0
"Building";"MissileTurret";NA;410;0
"Building";"CommandCenter";NA;406;0
"Building";"CommandCenter";NA;406;0
"Building";"CommandCenter";NA;406;0
"Building";"MissileTurret";NA;410;0
"Building";"CommandCenter";NA;406;0
"Building";"MissileTurret";NA;410;0
"Building";"CommandCenter";NA;406;0
"Building";"EngineeringBay";NA;410;0
"Building";"MissileTurret";NA;410;0
"Building";"MissileTurret";NA;410;0
"Building";"MissileTurret";NA;410;0
"Building";"FusionCore";NA;410;0
"Building";"MissileTurret";NA;410;0
"Building";"MissileTurret";NA;410;0
"Upgrade";"TerranShipWeaponsLevel2";"Armory";410;0
"Building";"MissileTurret";NA;410;0
"Building";"MissileTurret";NA;410;0
"Building";"CommandCenter";NA;410;0
"Building";"CommandCenter";NA;410;0
"Building";"CommandCenter";NA;410;0
"Building";"CommandCenter";NA;410;0
"Building";"CommandCenter";NA;410;0
"Building";"CommandCenter";NA;410;0
"Building";"GhostAcademy";NA;410;0
"Unit";"Medivac";"Starport";410;2
"Building";"GhostAcademy";NA;410;0
"Building";"GhostAcademy";NA;410;0
"Building";"GhostAcademy";NA;410;0
"Building";"Starport";NA;410;0
"Building";"Starport";NA;410;0
"Building";"SensorTower";NA;412;0
"Building";"MissileTurret";NA;412;0
"Building";"MissileTurret";NA;412;0
"Building";"StarportTechLab";NA;412;0
"Building";"StarportTechLab";NA;412;0
"Upgrade";"TerranInfantryWeaponsLevel1";"EngineeringBay";410;0
"Upgrade";"TerranInfantryArmorsLevel1";"EngineeringBay";410;0
"Building";"MissileTurret";NA;412;0
"Building";"MissileTurret";NA;412;0
"Unit";"Ghost";"Barracks";412;2
"Building";"MissileTurret";NA;412;0
"Unit";"Liberator";"Starport";412;3
"Building";"MissileTurret";NA;412;0
"Building";"CommandCenter";NA;412;0
"Unit";"Liberator";"Starport";412;3
"Unit";"Liberator";"Starport";412;3
"Unit";"Liberator";"Starport";417;3
"Unit";"Liberator";"Starport";417;3
"Unit";"Liberator";"Starport";417;3
"Unit";"Liberator";"Starport";417;3
"Unit";"Liberator";"Starport";417;3
"Building";"SensorTower";NA;423;0
"Building";"MissileTurret";NA;438;0
"Building";"MissileTurret";NA;438;0
"Building";"MissileTurret";NA;438;0
"Unit";"Liberator";"Starport";417;3
"Building";"Refinery";NA;438;0
"Building";"Refinery";NA;438;0
"Building";"MissileTurret";NA;441;0
"Unit";"Liberator";"Starport";441;3
"Unit";"Liberator";"Starport";441;3
"Unit";"Liberator";"Starport";441;3
"Unit";"Liberator";"Starport";441;3
"Unit";"Liberator";"Starport";441;3
"Unit";"Liberator";"Starport";441;3
"Unit";"Liberator";"Starport";441;3
"Building";"CommandCenter";NA;441;0
"Unit";"Liberator";"Starport";441;3
"Upgrade";"Stimpack";"TechLab";465;0
"Upgrade";"TerranInfantryWeaponsLevel2";"EngineeringBay";465;0
"Upgrade";"TerranInfantryArmorsLevel2";"EngineeringBay";465;0
