"type";"unit_name";"on_building";"total_supply_lag";"supply"
"Building";"Refinery";NA;15;0
"Building";"Barracks";NA;16;0
"Unit";"Reaper";"Barracks";19;1
"Building";"CommandCenter";NA;20;0
"Building";"Factory";NA;20;0
"Building";"BarracksReactor";NA;21;0
"Building";"Refinery";NA;23;0
"Building";"Starport";NA;24;0
"Unit";"Hellion";"Factory";25;2
"Unit";"Hellion";"Factory";27;2
"Unit";"Hellion";"Factory";30;2
"Unit";"Hellion";"Factory";32;2
"Unit";"Marine";"Barracks";34;1
"Unit";"Medivac";"Starport";36;2
"Unit";"Hellion";"Factory";42;2
"Unit";"Hellion";"Factory";44;2
"Unit";"Liberator";"Starport";47;3
"Building";"Armory";NA;52;0
"Unit";"Hellion";"Factory";54;2
"Unit";"Hellion";"Factory";56;2
"Unit";"Hellion";"Factory";63;2
"Unit";"Hellion";"Factory";65;2
"Unit";"Hellion";"Factory";70;2
"Unit";"Hellion";"Factory";72;2
"Building";"CommandCenter";NA;75;0
"Building";"BarracksReactor";NA;77;0
"Building";"Factory";NA;78;0
"Unit";"Hellion";"Factory";78;2
"Unit";"Hellion";"Factory";80;2
"Unit";"Liberator";"Starport";84;3
"Building";"Refinery";NA;87;0
"Building";"Refinery";NA;87;0
"Unit";"Hellion";"Factory";88;2
"Unit";"Hellion";"Factory";90;2
"Upgrade";"TerranVehicleWeaponsLevel1";"Armory";94;0
"Unit";"Cyclone";"Factory";98;3
"Unit";"Cyclone";"Factory";101;3
"Building";"Refinery";NA;104;0
"Building";"Refinery";NA;104;0
"Unit";"Cyclone";"Factory";104;3
"Unit";"Cyclone";"Factory";107;3
"Unit";"Liberator";"Starport";110;3
"Building";"Factory";NA;115;0
"Building";"Factory";NA;117;0
"Unit";"Hellion";"Factory";117;2
"Unit";"Hellion";"Factory";119;2
"Unit";"Hellion";"Factory";122;2
"Building";"Factory";NA;125;0
"Unit";"Hellion";"Factory";126;2
"Unit";"Hellion";"Factory";131;2
"Unit";"Hellion";"Factory";133;2
"Unit";"Hellion";"Factory";137;2
"Unit";"Hellion";"Factory";140;2
"Unit";"Hellion";"Factory";144;2
"Building";"FactoryTechLab";NA;146;0
"Building";"FactoryTechLab";NA;146;0
"Unit";"Hellion";"Factory";149;2
"Unit";"Hellion";"Factory";151;2
"Unit";"Hellion";"Factory";156;2
"Unit";"Hellion";"Factory";158;2
"Building";"FactoryTechLab";NA;160;0
"Unit";"Liberator";"Starport";161;3
"Building";"CommandCenter";NA;167;0
"Unit";"Hellion";"Factory";167;2
"Unit";"Hellion";"Factory";169;2
"Unit";"Hellion";"Factory";171;2
"Unit";"Hellion";"Factory";174;2
"Unit";"Hellion";"Factory";177;2
"Unit";"Hellion";"Factory";180;2
"Building";"GhostAcademy";NA;182;0
"Building";"Barracks";NA;182;0
"Unit";"Hellion";"Factory";182;2
"Unit";"Hellion";"Factory";184;2
"Unit";"Hellion";"Factory";186;2
"Upgrade";"TerranVehicleWeaponsLevel2";"Armory";188;0
"Building";"BarracksTechLab";NA;188;0
"Unit";"Hellion";"Factory";188;2
"Building";"Armory";NA;190;0
"Unit";"Ghost";"Barracks";192;2
"Unit";"Liberator";"Starport";194;3
"Unit";"Hellion";"Factory";197;2
"Unit";"Hellion";"Factory";199;2
"Unit";"Hellion";"Factory";201;2
"Unit";"Hellion";"Factory";203;2
"Unit";"Ghost";"Barracks";205;2
"Unit";"Hellion";"Factory";207;2
"Building";"BarracksTechLab";NA;209;0
"Unit";"Hellion";"Factory";209;2
"Unit";"Hellion";"Factory";211;2
"Unit";"Hellion";"Factory";213;2
"Unit";"Liberator";"Starport";216;3
"Unit";"Hellion";"Factory";219;2
"Unit";"Hellion";"Factory";221;2
"Unit";"Ghost";"Barracks";223;2
"Unit";"Ghost";"Barracks";225;2
"Unit";"Hellion";"Factory";227;2
"Unit";"Hellion";"Factory";229;2
"Unit";"Hellion";"Factory";231;2
"Building";"Refinery";NA;233;0
"Building";"Refinery";NA;233;0
"Building";"EngineeringBay";NA;233;0
"Unit";"Hellion";"Factory";233;2
"Unit";"Hellion";"Factory";235;2
"Unit";"Ghost";"Barracks";237;2
"Unit";"Ghost";"Barracks";239;2
"Building";"CommandCenter";NA;241;0
"Unit";"Hellion";"Factory";241;2
"Unit";"Hellion";"Factory";243;2
"Unit";"Liberator";"Starport";245;3
"Unit";"Ghost";"Barracks";248;2
"Unit";"Ghost";"Barracks";250;2
"Unit";"Hellion";"Factory";252;2
"Unit";"Hellion";"Factory";254;2
"Unit";"Hellion";"Factory";256;2
"Building";"Factory";NA;258;0
"Unit";"Hellion";"Factory";258;2
"Unit";"Hellion";"Factory";260;2
"Unit";"Hellion";"Factory";262;2
"Unit";"Hellion";"Factory";264;2
"Unit";"Hellion";"Factory";266;2
"Unit";"Hellion";"Factory";268;2
"Unit";"Hellion";"Factory";270;2
"Unit";"Hellion";"Factory";272;2
"Unit";"Hellion";"Factory";274;2
"Unit";"Hellion";"Factory";276;2
"Unit";"Hellion";"Factory";281;2
"Unit";"Liberator";"Starport";283;3
"Building";"Refinery";NA;286;0
"Unit";"Hellion";"Factory";286;2
"Unit";"Hellion";"Factory";288;2
"Unit";"Hellion";"Factory";290;2
"Building";"CommandCenter";NA;292;0
"Building";"CommandCenter";NA;292;0
"Building";"CommandCenter";NA;292;0
"Building";"Refinery";NA;292;0
"Unit";"Hellion";"Factory";292;2
"Unit";"Hellion";"Factory";294;2
"Unit";"Hellion";"Factory";296;2
"Unit";"Hellion";"Factory";298;2
"Unit";"Hellion";"Factory";300;2
"Unit";"Hellion";"Factory";302;2
"Unit";"Hellion";"Factory";304;2
"Unit";"Ghost";"Barracks";306;2
"Unit";"Ghost";"Barracks";308;2
"Building";"CommandCenter";NA;310;0
"Unit";"Hellion";"Factory";310;2
"Unit";"Hellion";"Factory";312;2
"Building";"FactoryTechLab";NA;314;0
"Building";"Barracks";NA;314;0
"Unit";"Ghost";"Barracks";314;2
"Unit";"Ghost";"Barracks";316;2
"Unit";"Hellion";"Factory";318;2
"Unit";"Hellion";"Factory";320;2
"Unit";"Hellion";"Factory";322;2
"Unit";"Hellion";"Factory";324;2
"Unit";"Hellion";"Factory";326;2
"Upgrade";"TerranVehicleWeaponsLevel3";"Armory";328;0
"Unit";"Hellion";"Factory";328;2
"Unit";"Hellion";"Factory";330;2
"Unit";"Hellion";"Factory";332;2
"Unit";"Hellion";"Factory";334;2
"Unit";"Liberator";"Starport";336;3
"Unit";"Ghost";"Barracks";339;2
"Unit";"Ghost";"Barracks";341;2
"Building";"Refinery";NA;343;0
"Building";"Refinery";NA;343;0
"Unit";"Hellion";"Factory";343;2
"Unit";"Hellion";"Factory";345;2
"Unit";"Hellion";"Factory";347;2
"Unit";"Hellion";"Factory";349;2
"Building";"BarracksTechLab";NA;351;0
"Building";"CommandCenter";NA;351;0
"Unit";"Ghost";"Barracks";351;2
"Unit";"Hellion";"Factory";353;2
"Unit";"Hellion";"Factory";355;2
"Unit";"Ghost";"Barracks";357;2
"Unit";"Ghost";"Barracks";359;2
"Unit";"Hellion";"Factory";361;2
"Building";"MissileTurret";NA;363;0
"Building";"CommandCenter";NA;363;0
"Building";"SensorTower";NA;363;0
"Building";"MissileTurret";NA;363;0
"Building";"MissileTurret";NA;363;0
"Unit";"Ghost";"Barracks";363;2
"Unit";"Hellion";"Factory";365;2
"Unit";"Hellion";"Factory";367;2
"Unit";"Hellion";"Factory";369;2
"Unit";"Ghost";"Barracks";371;2
"Building";"StarportReactor";NA;373;0
"Unit";"Hellion";"Factory";373;2
"Unit";"Hellion";"Factory";375;2
"Unit";"Ghost";"Barracks";377;2
"Unit";"Ghost";"Barracks";379;2
"Unit";"Ghost";"Barracks";381;2
"Unit";"Hellion";"Factory";383;2
"Unit";"Hellion";"Factory";385;2
"Unit";"Hellion";"Factory";387;2
"Unit";"Hellion";"Factory";389;2
"Unit";"Hellion";"Factory";391;2
"Unit";"Hellion";"Factory";393;2
"Unit";"Hellion";"Factory";395;2
"Unit";"Hellion";"Factory";397;2
"Unit";"Liberator";"Starport";399;3
"Unit";"Liberator";"Starport";402;3
"Unit";"Hellion";"Factory";405;2
"Unit";"Hellion";"Factory";407;2
"Unit";"Hellion";"Factory";409;2
"Unit";"Hellion";"Factory";411;2
"Unit";"Ghost";"Barracks";413;2
"Unit";"Ghost";"Barracks";415;2
"Unit";"Ghost";"Barracks";417;2
"Unit";"Hellion";"Factory";419;2
"Unit";"Hellion";"Factory";421;2
"Unit";"Hellion";"Factory";423;2
"Unit";"Hellion";"Factory";425;2
"Unit";"Hellion";"Factory";427;2
"Unit";"Ghost";"Barracks";429;2
"Unit";"Ghost";"Barracks";431;2
"Unit";"Hellion";"Factory";433;2
"Unit";"Hellion";"Factory";435;2
"Unit";"Hellion";"Factory";437;2
"Unit";"Hellion";"Factory";439;2
"Unit";"Hellion";"Factory";441;2
"Upgrade";"SprayTerran";NA;443;0
"Upgrade";"SprayTerran";NA;443;0
"Upgrade";"SprayTerran";NA;443;0
"Upgrade";"SprayTerran";NA;443;0
"Upgrade";"SprayTerran";NA;443;0
"Upgrade";"SprayTerran";NA;443;0
"Upgrade";"HighCapacityBarrels";NA;443;0
"Upgrade";"GhostMoebiusReactor";NA;443;0
"Upgrade";"SprayTerran";NA;443;0
"Upgrade";"SprayTerran";NA;443;0
"Upgrade";"SmartServos";NA;443;0
"Upgrade";"SprayTerran";NA;443;0
"Upgrade";"SprayTerran";NA;443;0
"Upgrade";"SprayTerran";NA;443;0
"Upgrade";"SprayTerran";NA;443;0
"Upgrade";"SprayTerran";NA;443;0
"Upgrade";"SprayTerran";NA;443;0
"Upgrade";"SprayTerran";NA;443;0
"Upgrade";"SprayTerran";NA;443;0
"Upgrade";"TerranVehicleAndShipArmorsLevel1";NA;443;0
"Upgrade";"SprayTerran";NA;443;0
"Upgrade";"SprayTerran";NA;443;0
"Upgrade";"SprayTerran";NA;443;0
"Upgrade";"SprayTerran";NA;443;0
"Upgrade";"TerranInfantryArmorsLevel1";NA;443;0
"Upgrade";"TerranVehicleAndShipArmorsLevel2";NA;443;0
