"type";"unit_name";"on_building";"total_supply";"supply"
"Building";"Refinery";NA;14;0
"Building";"Barracks";NA;15;0
"Unit";"Reaper";"Barracks";19;1
"Building";"Factory";NA;19;0
"Building";"Refinery";NA;21;0
"Building";"BarracksReactor";NA;20;0
"Building";"CommandCenter";NA;19;0
"Unit";"Hellion";"Factory";24;2
"Unit";"Hellion";"Factory";24;2
"Building";"BarracksTechLab";NA;25;0
"Building";"Starport";NA;23;0
"Unit";"Hellion";"Factory";26;2
"Unit";"Hellion";"Factory";30;2
"Unit";"Hellion";"Factory";38;2
"Unit";"Hellion";"Factory";38;2
"Building";"BarracksReactor";NA;39;0
"Building";"FactoryTechLab";NA;46;0
"Unit";"Liberator";"Starport";42;3
"Building";"BarracksTechLab";NA;50;0
"Building";"EngineeringBay";NA;54;0
"Building";"EngineeringBay";NA;54;0
"Building";"Refinery";NA;56;0
"Unit";"Marine";"Barracks";57;1
"Building";"CommandCenter";NA;46;0
"Building";"StarportReactor";NA;55;0
"Building";"Barracks";NA;55;0
"Building";"Barracks";NA;55;0
"Unit";"Marine";"Barracks";61;1
"Unit";"Marine";"Barracks";62;1
"Unit";"Marine";"Barracks";62;1
"Building";"Refinery";NA;62;0
"Unit";"Marine";"Barracks";64;1
"Unit";"Marine";"Barracks";65;1
"Unit";"Marine";"Barracks";67;1
"Unit";"Marine";"Barracks";67;1
"Unit";"Marine";"Barracks";67;1
"Unit";"Marine";"Barracks";70;1
"Building";"Armory";NA;65;0
"Unit";"Medivac";"Starport";70;2
"Unit";"Medivac";"Starport";70;2
"Unit";"Marine";"Barracks";76;1
"Unit";"Marine";"Barracks";77;1
"Unit";"Marine";"Barracks";77;1
"Unit";"Marine";"Barracks";77;1
"Unit";"Marine";"Barracks";77;1
"Unit";"Marine";"Barracks";81;1
"Unit";"Marine";"Barracks";82;1
"Unit";"Marine";"Barracks";83;1
"Upgrade";"Stimpack";"TechLab";62;0
"Unit";"Marine";"Barracks";85;1
"Unit";"Marine";"Barracks";86;1
"Upgrade";"TerranInfantryWeaponsLevel1";"EngineeringBay";64;0
"Unit";"Medivac";"Starport";84;2
"Building";"MissileTurret";NA;93;0
"Building";"Barracks";NA;85;0
"Building";"Barracks";NA;85;0
"Unit";"Marine";"Barracks";97;1
"Unit";"Marine";"Barracks";99;1
"Unit";"Marine";"Barracks";99;1
"Unit";"Marine";"Barracks";99;1
"Unit";"Marine";"Barracks";99;1
"Unit";"Marine";"Barracks";100;1
"Unit";"Marine";"Barracks";103;1
"Unit";"Marine";"Barracks";104;1
"Unit";"Marine";"Barracks";105;1
"Unit";"Marine";"Barracks";109;1
"Unit";"Marine";"Barracks";109;1
"Building";"Refinery";NA;109;0
"Building";"Refinery";NA;109;0
"Building";"BarracksReactor";NA;103;0
"Building";"BarracksReactor";NA;103;0
"Unit";"Marine";"Barracks";112;1
"Unit";"Marine";"Barracks";113;1
"Unit";"Marine";"Barracks";114;1
"Building";"Factory";NA;109;0
"Unit";"Medivac";"Starport";115;2
"Upgrade";"TerranVehicleWeaponsLevel1";"Armory";97;0
"Unit";"Marine";"Barracks";122;1
"Unit";"Marine";"Barracks";122;1
"Unit";"Marine";"Barracks";122;1
"Unit";"Marine";"Barracks";122;1
"Unit";"Marine";"Barracks";122;1
"Upgrade";"TerranInfantryArmorsLevel1";"EngineeringBay";99;0
"Unit";"Marine";"Barracks";122;1
"Unit";"Marine";"Barracks";122;1
"Unit";"Marine";"Barracks";122;1
"Unit";"Marine";"Barracks";123;1
"Unit";"Marine";"Barracks";130;1
"Unit";"Marine";"Barracks";130;1
"Unit";"Marine";"Barracks";130;1
"Unit";"Marine";"Barracks";130;1
"Unit";"Marine";"Barracks";138;1
"Unit";"Marine";"Barracks";138;1
"Unit";"Marine";"Barracks";138;1
"Unit";"Marine";"Barracks";138;1
"Upgrade";"TerranInfantryWeaponsLevel2";"EngineeringBay";103;0
"Unit";"Marine";"Barracks";138;1
"Unit";"Marine";"Barracks";138;1
"Unit";"Marine";"Barracks";138;1
"Unit";"Marine";"Barracks";138;1
"Unit";"Marine";"Barracks";138;1
"Unit";"Medivac";"Starport";138;2
"Unit";"Medivac";"Starport";138;2
"Unit";"Marine";"Barracks";138;1
"Unit";"Marine";"Barracks";152;1
"Unit";"Marine";"Barracks";152;1
"Unit";"Marine";"Barracks";152;1
"Unit";"Marine";"Barracks";152;1
"Unit";"Marine";"Barracks";152;1
"Unit";"Marine";"Barracks";152;1
"Unit";"Marine";"Barracks";152;1
"Unit";"Marine";"Barracks";153;1
"Unit";"Marine";"Barracks";153;1
"Unit";"Medivac";"Starport";147;2
"Building";"Barracks";NA;142;0
"Building";"Barracks";NA;142;0
"Building";"Barracks";NA;144;0
"Unit";"Marine";"Barracks";153;1
"Unit";"Marine";"Barracks";154;1
"Unit";"Medivac";"Starport";153;2
"Unit";"Marine";"Barracks";160;1
"Unit";"Marine";"Barracks";160;1
"Unit";"Marine";"Barracks";160;1
"Building";"CommandCenter";NA;138;0
"Building";"BarracksTechLab";NA;164;0
"Building";"BarracksTechLab";NA;164;0
"Building";"BarracksTechLab";NA;164;0
"Unit";"Medivac";"Starport";162;2
"Building";"GhostAcademy";NA;164;0
"Unit";"Marine";"Barracks";171;1
"Unit";"Marine";"Barracks";171;1
"Unit";"Marine";"Barracks";171;1
"Unit";"Marine";"Barracks";171;1
"Unit";"Marine";"Barracks";171;1
"Unit";"Marauder";"Barracks";171;2
"Unit";"Marauder";"Barracks";178;2
