"Type";"UnitName";"OnBuilding";"TotalSupply";"Supply"
"Unit";"SCV";"Command Center";12;1
"Unit";"SCV";"Command Center";12;1
"Unit";"SCV";"Command Center";13;1
"Building";"SupplyDepot";NA;13;0
"Unit";"SCV";"Command Center";15;1
"Unit";"SCV";"Command Center";15;1
"Building";"Refinery";NA;15;0
"Unit";"SCV";"Command Center";16;1
"Building";"Barracks";NA;15;0
"Unit";"SCV";"Command Center";17;1
"Unit";"Reaper";"Barracks";19;1
"Unit";"SCV";"Command Center";19;1
"Building";"SupplyDepot";NA;19;0
"Unit";"Marine";"Barracks";19;1
"Unit";"SCV";"Command Center";21;1
"Building";"Refinery";NA;21;0
"Unit";"SCV";"Command Center";23;1
"Unit";"SCV";"Command Center";23;1
"Building";"Factory";NA;21;0
"Building";"CommandCenter";NA;19;0
"Building";"BarracksReactor";NA;22;0
"Unit";"SCV";"Command Center";24;1
"Unit";"SCV";"Command Center";26;1
"Building";"BarracksTechLab";NA;26;0
"Unit";"SCV";"Command Center";26;1
"Unit";"Hellion";"Factory";26;2
"Unit";"Hellion";"Factory";26;2
"Building";"Starport";NA;26;0
"Building";"SupplyDepot";NA;27;0
"Unit";"Hellion";"Factory";28;2
"Unit";"Hellion";"Factory";30;2
"Unit";"SCV";"Command Center";32;1
"Unit";"SCV";"Command Center";32;1
"Unit";"SCV";"Command Center";36;1
"Unit";"Hellion";"Factory";36;2
"Unit";"Hellion";"Factory";36;2
"Unit";"SCV";"Command Center";38;1
"Building";"SupplyDepot";NA;38;0
"Unit";"SCV";"Command Center";38;1
"Unit";"SCV";"Command Center";43;1
"Unit";"SCV";"Command Center";45;1
"Unit";"Hellion";"Factory";44;2
"Unit";"Hellion";"Factory";44;2
"Unit";"SCV";"Command Center";46;1
"Unit";"SCV";"Command Center";46;1
"Unit";"SCV";"Command Center";52;1
"Building";"SupplyDepot";NA;47;0
"Unit";"Liberator";"Starport";44;3
"Unit";"SCV";"Command Center";53;1
"Unit";"Hellion";"Factory";53;2
"Unit";"Hellion";"Factory";54;2
"Building";"Refinery";NA;58;0
"Building";"Refinery";NA;58;0
"Unit";"SCV";"Command Center";62;1
"Unit";"SCV";"Command Center";62;1
"Building";"SupplyDepot";NA;62;0
"Building";"BarracksTechLab";NA;62;0
"Unit";"Hellion";"Factory";62;2
"Unit";"Hellion";"Factory";62;2
"Building";"SupplyDepot";NA;62;0
"Building";"CommandCenter";NA;51;0
"Unit";"SCV";"Command Center";62;1
"Unit";"SCV";"Command Center";63;1
"Unit";"SCV";"Command Center";70;1
"Unit";"SCV";"Command Center";70;1
"Building";"Factory";NA;62;0
"Building";"Factory";NA;62;0
"Unit";"Hellion";"Factory";68;2
"Unit";"Hellion";"Factory";68;2
"Building";"StarportReactor";NA;62;0
"Building";"Armory";NA;62;0
"Building";"Armory";NA;62;0
"Unit";"SCV";"Command Center";70;1
"Unit";"SCV";"Command Center";71;1
"Unit";"SCV";"Command Center";76;1
"Unit";"SCV";"Command Center";77;1
"Unit";"SCV";"Command Center";78;1
"Unit";"Hellion";"Factory";78;2
"Unit";"Hellion";"Factory";78;2
"Unit";"SCV";"Command Center";80;1
"Unit";"SCV";"Command Center";85;1
"Unit";"SCV";"Command Center";85;1
"Building";"SupplyDepot";NA;80;0
"Building";"SupplyDepot";NA;80;0
"Unit";"SCV";"Command Center";85;1
"Building";"Refinery";NA;81;0
"Building";"Refinery";NA;85;0
"Unit";"SCV";"Command Center";86;1
"Unit";"SCV";"Command Center";88;1
"Unit";"Hellion";"Factory";86;2
"Unit";"Hellion";"Factory";86;2
"Unit";"SCV";"Command Center";89;1
"Unit";"SCV";"Command Center";96;1
"Unit";"SCV";"Command Center";96;1
"Building";"SupplyDepot";NA;91;0
"Unit";"SCV";"Command Center";96;1
"Building";"SupplyDepot";NA;91;0
"Unit";"SCV";"Command Center";96;1
"Building";"SupplyDepot";NA;96;0
"Unit";"SCV";"Command Center";99;1
"Unit";"Hellion";"Factory";99;2
"Unit";"Hellion";"Factory";99;2
"Unit";"SCV";"Command Center";101;1
"Upgrade";"TerranVehicleWeaponsLevel1";"Armory";85;0
"Unit";"Hellion";"Factory";101;2
"Unit";"SCV";"Command Center";106;1
"Unit";"SCV";"Command Center";106;1
"Unit";"Hellion";"Factory";105;2
"Building";"Factory";NA;99;0
"Building";"Factory";NA;99;0
"Unit";"SCV";"Command Center";106;1
"Unit";"SCV";"Command Center";112;1
"Unit";"SCV";"Command Center";113;1
"Unit";"SCV";"Command Center";113;1
"Building";"FactoryTechLab";NA;113;0
"Unit";"SCV";"Command Center";115;1
"Unit";"SCV";"Command Center";116;1
"Building";"FactoryReactor";NA;113;0
"Unit";"Hellion";"Factory";115;2
"Unit";"Hellion";"Factory";115;2
"Unit";"Liberator";"Starport";114;3
"Unit";"Liberator";"Starport";114;3
"Unit";"Hellion";"Factory";122;2
"Building";"SupplyDepot";NA;122;0
"Building";"SupplyDepot";NA;122;0
"Building";"SupplyDepot";NA;122;0
"Building";"SupplyDepot";NA;122;0
"Unit";"SCV";"Command Center";130;1
"Unit";"SCV";"Command Center";130;1
"Unit";"SCV";"Command Center";130;1
"Building";"SupplyDepot";NA;130;0
"Building";"SupplyDepot";NA;130;0
"Building";"SupplyDepot";NA;130;0
"Unit";"Hellion";"Factory";130;2
"Unit";"Hellion";"Factory";130;2
"Building";"CommandCenter";NA;116;0
"Unit";"SCV";"Command Center";130;1
"Upgrade";"TerranVehicleAndShipArmorsLevel1";"Armory";115;0
"Unit";"SCV";"Command Center";137;1
"Unit";"Hellion";"Factory";135;2
"Unit";"Hellion";"Factory";137;2
"Unit";"Hellion";"Factory";137;2
"Unit";"Hellion";"Factory";137;2
"Unit";"SCV";"Command Center";139;1
"Unit";"SCV";"Command Center";139;1
"Unit";"SCV";"Command Center";139;1
"Building";"Factory";NA;130;0
"Building";"Factory";NA;133;0
"Building";"Refinery";NA;139;0
"Upgrade";"TerranVehicleWeaponsLevel2";"Armory";117;0
"Building";"Factory";NA;133;0
"Building";"Refinery";NA;139;0
"Unit";"Hellion";"Factory";147;2
"Unit";"Hellion";"Factory";147;2
"Building";"FactoryTechLab";NA;154;0
"Building";"FactoryTechLab";NA;154;0
"Unit";"Hellion";"Factory";154;2
"Unit";"Hellion";"Factory";154;2
"Unit";"Hellion";"Factory";154;2
"Unit";"Hellion";"Factory";154;2
"Unit";"SCV";"Command Center";154;1
"Building";"FactoryReactor";NA;154;0
"Unit";"Hellion";"Factory";154;2
"Unit";"SCV";"Command Center";163;1
"Unit";"Hellion";"Factory";162;2
"Unit";"Hellion";"Factory";162;2
"Unit";"Hellion";"Factory";162;2
"Unit";"Hellion";"Factory";162;2
"Unit";"Liberator";"Starport";154;3
"Unit";"Hellion";"Factory";163;2
"Unit";"Hellion";"Factory";163;2
"Unit";"Hellion";"Factory";166;2
"Unit";"Hellion";"Factory";177;2
"Unit";"Hellion";"Factory";177;2
"Unit";"Hellion";"Factory";177;2
"Unit";"Hellion";"Factory";177;2
"Unit";"Hellion";"Factory";179;2
"Building";"EngineeringBay";NA;179;0
