"type";"unit_name";"on_building";"total_supply";"supply"
"Building";"Refinery";NA;14;0
"Building";"Barracks";NA;15;0
"Unit";"Reaper";"Barracks";19;1
"Building";"Refinery";NA;21;0
"Building";"Factory";NA;19;0
"Building";"BarracksReactor";NA;21;0
"Building";"CommandCenter";NA;19;0
"Building";"BarracksTechLab";NA;23;0
"Unit";"Hellion";"Factory";23;2
"Unit";"Hellion";"Factory";23;2
"Building";"Starport";NA;23;0
"Unit";"Hellion";"Factory";29;2
"Unit";"Hellion";"Factory";29;2
"Unit";"Hellion";"Factory";36;2
"Unit";"Hellion";"Factory";36;2
"Building";"BarracksReactor";NA;30;0
"Unit";"Liberator";"Starport";43;3
"Building";"FactoryTechLab";NA;46;0
"Building";"BarracksTechLab";NA;46;0
"Unit";"Marine";"Barracks";52;1
"Building";"StarportReactor";NA;52;0
"Unit";"Marine";"Barracks";56;1
"Building";"EngineeringBay";NA;54;0
"Building";"EngineeringBay";NA;54;0
"Building";"Refinery";NA;56;0
"Building";"Refinery";NA;56;0
"Building";"Barracks";NA;53;0
"Building";"Barracks";NA;53;0
"Unit";"Marine";"Barracks";60;1
"Building";"CommandCenter";NA;51;0
"Unit";"Marine";"Barracks";62;1
"Unit";"Marine";"Barracks";62;1
"Unit";"Marine";"Barracks";62;1
"Unit";"Marine";"Barracks";62;1
"Unit";"Marine";"Barracks";62;1
"Building";"StarportReactor";NA;61;0
"Unit";"Marine";"Barracks";63;1
"Unit";"Marine";"Barracks";64;1
"Unit";"Marine";"Barracks";65;1
"Unit";"Marine";"Barracks";68;1
"Unit";"Marine";"Barracks";68;1
"Building";"Barracks";NA;60;0
"Building";"Barracks";NA;61;0
"Unit";"Marine";"Barracks";70;1
"Unit";"Marine";"Barracks";74;1
"Upgrade";"Stimpack";"TechLab";58;0
"Unit";"Marine";"Barracks";81;1
"Unit";"Marine";"Barracks";81;1
"Unit";"Marine";"Barracks";81;1
"Unit";"Marine";"Barracks";81;1
"Unit";"Marine";"Barracks";81;1
"Building";"Factory";NA;70;0
"Building";"Armory";NA;76;0
"Unit";"Marine";"Barracks";85;1
"Building";"BarracksReactor";NA;81;0
"Unit";"Marine";"Barracks";85;1
"Unit";"Medivac";"Starport";82;2
"Unit";"Marine";"Barracks";90;1
"Unit";"Marine";"Barracks";90;1
"Unit";"Marine";"Barracks";90;1
"Unit";"Marine";"Barracks";90;1
"Unit";"Marine";"Barracks";90;1
"Upgrade";"TerranInfantryWeaponsLevel1";"EngineeringBay";77;0
"Building";"MissileTurret";NA;103;0
"Unit";"Marine";"Barracks";103;1
"Building";"MissileTurret";NA;103;0
"Unit";"Marine";"Barracks";103;1
"Building";"MissileTurret";NA;103;0
"Unit";"Marine";"Barracks";103;1
"Unit";"Marine";"Barracks";103;1
"Unit";"Marine";"Barracks";103;1
"Unit";"Medivac";"Starport";105;2
"Unit";"Marine";"Barracks";110;1
"Unit";"Marine";"Barracks";110;1
"Unit";"Marine";"Barracks";110;1
"Unit";"Marine";"Barracks";110;1
"Unit";"Marine";"Barracks";110;1
"Unit";"Marine";"Barracks";110;1
"Unit";"Marine";"Barracks";110;1
"Building";"Refinery";NA;110;0
"Building";"Refinery";NA;110;0
"Unit";"Marine";"Barracks";115;1
"Unit";"Marine";"Barracks";115;1
"Unit";"Marine";"Barracks";115;1
"Unit";"Marine";"Barracks";119;1
"Unit";"Marine";"Barracks";119;1
"Unit";"Marine";"Barracks";119;1
"Unit";"Marine";"Barracks";125;1
"Upgrade";"TerranVehicleWeaponsLevel1";"Armory";105;0
"Unit";"Marine";"Barracks";130;1
"Unit";"Marine";"Barracks";130;1
"Unit";"Marine";"Barracks";130;1
"Building";"CommandCenter";NA;110;0
"Unit";"Marine";"Barracks";131;1
"Unit";"Marine";"Barracks";131;1
"Unit";"Marine";"Barracks";131;1
"Unit";"Medivac";"Starport";130;2
"Unit";"Medivac";"Starport";131;2
"Unit";"Marine";"Barracks";131;1
"Unit";"Marine";"Barracks";131;1
"Unit";"Marine";"Barracks";131;1
"Unit";"Marine";"Barracks";131;1
"Unit";"Marine";"Barracks";132;1
"Unit";"Marine";"Barracks";133;1
"Unit";"Marine";"Barracks";134;1
"Unit";"Marine";"Barracks";135;1
"Unit";"Marine";"Barracks";146;1
"Unit";"Marine";"Barracks";146;1
"Unit";"Marine";"Barracks";146;1
"Unit";"Marine";"Barracks";146;1
"Unit";"Medivac";"Starport";137;2
"Unit";"Marine";"Barracks";149;1
"Unit";"Marine";"Barracks";149;1
"Unit";"Marine";"Barracks";149;1
"Unit";"Marine";"Barracks";149;1
"Unit";"Marine";"Barracks";149;1
"Upgrade";"TerranInfantryArmorsLevel1";"EngineeringBay";126;0
"Unit";"Marine";"Barracks";149;1
"Unit";"Marine";"Barracks";153;1
"Unit";"Marine";"Barracks";153;1
"Building";"Barracks";NA;137;0
"Building";"Barracks";NA;137;0
"Building";"Barracks";NA;137;0
"Unit";"Marine";"Barracks";159;1
"Unit";"Marine";"Barracks";159;1
"Unit";"Marine";"Barracks";160;1
"Unit";"Marine";"Barracks";160;1
"Upgrade";"TerranInfantryWeaponsLevel2";"EngineeringBay";128;0
"Unit";"Marine";"Barracks";163;1
"Unit";"Marine";"Barracks";163;1
"Unit";"Marine";"Barracks";163;1
"Unit";"Marine";"Barracks";163;1
"Unit";"Medivac";"Starport";160;2
"Unit";"Medivac";"Starport";160;2
"Unit";"Marine";"Barracks";165;1
"Building";"BarracksTechLab";NA;167;0
"Building";"BarracksTechLab";NA;167;0
"Unit";"Marine";"Barracks";171;1
"Unit";"Marine";"Barracks";171;1
"Unit";"Marine";"Barracks";171;1
"Unit";"Marine";"Barracks";171;1
"Building";"BarracksTechLab";NA;171;0
"Unit";"Marine";"Barracks";176;1
"Unit";"Marine";"Barracks";176;1
"Unit";"Marine";"Barracks";176;1
"Building";"GhostAcademy";NA;175;0
"Building";"Starport";NA;176;0
"Building";"Refinery";NA;180;0
"Unit";"Marine";"Barracks";183;1
"Unit";"Marine";"Barracks";183;1
"Unit";"Marine";"Barracks";183;1
"Unit";"Marine";"Barracks";183;1
"Unit";"Marine";"Barracks";183;1
"Building";"Refinery";NA;180;0
"Unit";"Marine";"Barracks";183;1
"Building";"FusionCore";NA;176;0
"Unit";"Marine";"Barracks";192;1
"Unit";"Marine";"Barracks";192;1
"Unit";"Marine";"Barracks";192;1
"Unit";"Marine";"Barracks";192;1
"Upgrade";"TerranVehicleWeaponsLevel2";"Armory";160;0
"Unit";"Marine";"Barracks";192;1
"Unit";"Marine";"Barracks";192;1
"Unit";"Ghost";"Barracks";192;2
"Unit";"Ghost";"Barracks";192;2
"Unit";"Ghost";"Barracks";192;2
"Unit";"Marine";"Barracks";192;1
"Unit";"Marine";"Barracks";192;1
"Unit";"Marine";"Barracks";206;1
"Unit";"Marine";"Barracks";206;1
"Unit";"Marine";"Barracks";206;1
"Unit";"Marine";"Barracks";206;1
"Unit";"Marine";"Barracks";208;1
"Unit";"Marine";"Barracks";208;1
"Unit";"Marine";"Barracks";208;1
"Unit";"Ghost";"Barracks";206;2
"Unit";"Ghost";"Barracks";206;2
"Unit";"Ghost";"Barracks";206;2
"Unit";"Marine";"Barracks";216;1
"Unit";"Marine";"Barracks";217;1
"Unit";"Marine";"Barracks";217;1
"Unit";"Marine";"Barracks";223;1
"Unit";"Marine";"Barracks";223;1
"Unit";"Ghost";"Barracks";217;2
"Unit";"Ghost";"Barracks";217;2
"Unit";"Marine";"Barracks";230;1
"Unit";"Marine";"Barracks";230;1
"Unit";"Marine";"Barracks";232;1
"Unit";"Medivac";"Starport";227;2
"Unit";"Medivac";"Starport";228;2
"Unit";"Ghost";"Barracks";232;2
"Unit";"Ghost";"Barracks";232;2
"Unit";"Marine";"Barracks";232;1
"Unit";"Marine";"Barracks";232;1
"Unit";"Marine";"Barracks";232;1
"Unit";"Marine";"Barracks";232;1
"Unit";"Marine";"Barracks";235;1
"Unit";"Marine";"Barracks";235;1
"Unit";"Marine";"Barracks";237;1
"Unit";"Marine";"Barracks";239;1
"Unit";"Marauder";"Barracks";235;2
"Unit";"Marauder";"Barracks";237;2
"Unit";"Marine";"Barracks";245;1
"Unit";"Marine";"Barracks";245;1
"Unit";"Marauder";"Barracks";239;2
"Unit";"Medivac";"Starport";239;2
"Unit";"Marauder";"Barracks";245;2
"Unit";"Marine";"Barracks";245;1
"Unit";"Marine";"Barracks";246;1
"Unit";"Marine";"Barracks";247;1
"Building";"StarportTechLab";NA;251;0
"Unit";"Marauder";"Barracks";251;2
"Unit";"Marauder";"Barracks";253;2
"Unit";"Marine";"Barracks";257;1
"Unit";"Marine";"Barracks";257;1
"Unit";"Marine";"Barracks";261;1
"Unit";"Marine";"Barracks";261;1
"Unit";"Marauder";"Barracks";257;2
"Upgrade";"TerranInfantryWeaponsLevel3";"EngineeringBay";214;0
"Unit";"Marine";"Barracks";266;1
"Unit";"Marine";"Barracks";266;1
"Unit";"Marine";"Barracks";266;1
"Unit";"Liberator";"Starport";251;3
"Unit";"Marine";"Barracks";279;1
"Unit";"Marine";"Barracks";279;1
"Unit";"Marine";"Barracks";282;1
"Unit";"Marine";"Barracks";282;1
"Unit";"Marine";"Barracks";282;1
"Unit";"Marauder";"Barracks";279;2
"Unit";"Marauder";"Barracks";279;2
"Unit";"Marine";"Barracks";282;1
"Unit";"Marine";"Barracks";282;1
"Unit";"Marine";"Barracks";282;1
"Unit";"Marauder";"Barracks";282;2
"Unit";"Marauder";"Barracks";282;2
"Unit";"Marine";"Barracks";282;1
"Unit";"Marine";"Barracks";283;1
"Unit";"Marine";"Barracks";284;1
"Unit";"Marine";"Barracks";291;1
"Unit";"Marauder";"Barracks";287;2
"Unit";"Marine";"Barracks";298;1
"Unit";"Marine";"Barracks";298;1
"Unit";"Marauder";"Barracks";291;2
"Unit";"Marauder";"Barracks";298;2
"Unit";"Marine";"Barracks";298;1
"Unit";"Marine";"Barracks";298;1
"Unit";"Marauder";"Barracks";298;2
"Unit";"Marine";"Barracks";301;1
"Unit";"Marine";"Barracks";301;1
"Upgrade";"PersonalCloaking";"GhostAcademy";279;0
"Unit";"Liberator";"Starport";298;3
"Unit";"Liberator";"Starport";298;3
"Unit";"Liberator";"Starport";298;3
"Unit";"Ghost";"Barracks";302;2
"Unit";"Marine";"Barracks";314;1
"Unit";"Marine";"Barracks";316;1
"Unit";"Marine";"Barracks";316;1
"Unit";"Marine";"Barracks";316;1
"Building";"CommandCenter";NA;282;0
"Unit";"Marine";"Barracks";316;1
"Unit";"Ghost";"Barracks";316;2
"Unit";"Marauder";"Barracks";316;2
"Unit";"Marine";"Barracks";328;1
"Unit";"Marine";"Barracks";328;1
"Unit";"Marine";"Barracks";331;1
"Unit";"Marine";"Barracks";331;1
"Unit";"Marauder";"Barracks";331;2
"Unit";"Marauder";"Barracks";331;2
"Unit";"Liberator";"Starport";316;3
"Unit";"Ghost";"Barracks";334;2
"Unit";"Marine";"Barracks";344;1
"Unit";"Marine";"Barracks";344;1
"Unit";"Marine";"Barracks";344;1
"Unit";"Marauder";"Barracks";344;2
"Unit";"Marauder";"Barracks";344;2
"Unit";"Liberator";"Starport";331;3
"Unit";"Marauder";"Barracks";344;2
"Unit";"Liberator";"Starport";331;3
"Unit";"Marine";"Barracks";347;1
"Unit";"Marine";"Barracks";347;1
"Unit";"Marauder";"Barracks";347;2
