"type";"unit_name";"on_building";"total_supply";"supply"
"Building";"Refinery";NA;14;0
"Building";"Barracks";NA;15;0
"Unit";"Reaper";"Barracks";19;1
"Building";"Refinery";NA;19;0
"Building";"Factory";NA;19;0
"Building";"BarracksReactor";NA;20;0
"Building";"CommandCenter";NA;19;0
"Unit";"Hellion";"Factory";24;2
"Building";"Starport";NA;23;0
"Unit";"Hellion";"Factory";24;2
"Building";"BarracksTechLab";NA;25;0
"Unit";"Hellion";"Factory";26;2
"Unit";"Hellion";"Factory";28;2
"Unit";"Hellion";"Factory";37;2
"Unit";"Hellion";"Factory";37;2
"Unit";"Hellion";"Factory";45;2
"Unit";"Hellion";"Factory";45;2
"Unit";"Banshee";"Starport";43;3
"Unit";"Hellion";"Factory";53;2
"Unit";"Hellion";"Factory";55;2
"Building";"BarracksTechLab";NA;65;0
"Building";"Refinery";NA;64;0
"Building";"Refinery";NA;64;0
"Unit";"Banshee";"Starport";55;3
"Building";"CommandCenter";NA;49;0
"Unit";"Hellion";"Factory";66;2
"Unit";"Hellion";"Factory";66;2
"Building";"Factory";NA;65;0
"Building";"Factory";NA;65;0
"Unit";"Hellion";"Factory";77;2
"Unit";"Hellion";"Factory";77;2
"Building";"Armory";NA;66;0
"Building";"Armory";NA;66;0
"Unit";"Hellion";"Factory";79;2
"Unit";"Hellion";"Factory";81;2
"Building";"Refinery";NA;86;0
"Building";"Factory";NA;79;0
"Building";"Factory";NA;79;0
"Building";"BarracksReactor";NA;85;0
"Unit";"Liberator";"Starport";85;3
"Building";"Refinery";NA;93;0
"Building";"FactoryTechLab";NA;96;0
"Building";"FactoryReactor";NA;96;0
"Unit";"Hellion";"Factory";103;2
"Unit";"Hellion";"Factory";103;2
"Building";"EngineeringBay";NA;106;0
"Unit";"Hellion";"Factory";111;2
"Unit";"Hellion";"Factory";111;2
"Unit";"Hellion";"Factory";111;2
"Unit";"Hellion";"Factory";113;2
"Unit";"Hellion";"Factory";115;2
"Unit";"Hellion";"Factory";117;2
"Unit";"Hellion";"Factory";121;2
"Upgrade";"TerranVehicleWeaponsLevel1";"Armory";102;0
"Building";"CommandCenter";NA;106;0
"Building";"Refinery";NA;123;0
"Building";"Refinery";NA;127;0
"Unit";"Hellion";"Factory";131;2
"Unit";"Hellion";"Factory";131;2
"Unit";"Hellion";"Factory";131;2
"Unit";"Hellion";"Factory";131;2
"Unit";"Hellion";"Factory";139;2
"Unit";"Hellion";"Factory";139;2
"Building";"Factory";NA;131;0
"Building";"Factory";NA;131;0
"Unit";"Hellion";"Factory";145;2
"Unit";"Hellion";"Factory";145;2
"Unit";"Hellion";"Factory";146;2
"Unit";"Hellion";"Factory";146;2
"Unit";"Hellion";"Factory";150;2
"Unit";"Hellion";"Factory";154;2
"Unit";"Hellion";"Factory";154;2
"Unit";"Hellion";"Factory";154;2
"Unit";"Hellion";"Factory";154;2
"Unit";"Hellion";"Factory";156;2
"Unit";"Hellion";"Factory";156;2
"Upgrade";"TerranVehicleWeaponsLevel2";"Armory";141;0
"Unit";"Hellion";"Factory";164;2
"Unit";"Hellion";"Factory";164;2
"Unit";"Hellion";"Factory";164;2
"Unit";"Hellion";"Factory";166;2
"Unit";"Hellion";"Factory";168;2
"Unit";"Hellion";"Factory";168;2
"Unit";"Hellion";"Factory";168;2
"Unit";"Hellion";"Factory";170;2
"Unit";"Hellion";"Factory";176;2
"Unit";"Hellion";"Factory";180;2
