"Type";"UnitName";"OnBuilding";"TotalSupply";"Supply"
"Unit";"SCV";"Command Center";12;1
"Unit";"SCV";"Command Center";12;1
"Unit";"SCV";"Command Center";13;1
"Building";"SupplyDepot";NA;13;0
"Unit";"SCV";"Command Center";15;1
"Unit";"SCV";"Command Center";15;1
"Unit";"SCV";"Command Center";16;1
"Building";"Barracks";NA;15;0
"Unit";"SCV";"Command Center";17;1
"Unit";"SCV";"Command Center";19;1
"Unit";"SCV";"Command Center";20;1
"Building";"CommandCenter";NA;18;0
"Unit";"Marine";"Barracks";20;1
"Unit";"SCV";"Command Center";21;1
"Building";"SupplyDepot";NA;21;0
"Unit";"SCV";"Command Center";23;1
"Unit";"Marine";"Barracks";23;1
"Unit";"SCV";"Command Center";24;1
"Building";"Bunker";NA;23;0
"Building";"Barracks";NA;21;0
"Unit";"SCV";"Command Center";24;1
"Building";"CommandCenter";NA;19;0
"Unit";"SCV";"Command Center";26;1
"Unit";"SCV";"Command Center";27;1
"Unit";"Marine";"Barracks";26;1
"Unit";"Marine";"Barracks";27;1
"Unit";"SCV";"Command Center";28;1
"Unit";"SCV";"Command Center";29;1
"Building";"Barracks";NA;24;0
"Unit";"Marine";"Barracks";30;1
"Unit";"SCV";"Command Center";32;1
"Unit";"SCV";"Command Center";33;1
"Unit";"Marine";"Barracks";32;1
"Building";"Barracks";NA;26;0
"Unit";"SCV";"Command Center";33;1
"Building";"Refinery";NA;33;0
"Unit";"SCV";"Command Center";37;1
"Unit";"Marine";"Barracks";35;1
"Building";"Refinery";NA;33;0
"Unit";"SCV";"Command Center";37;1
"Unit";"Marine";"Barracks";35;1
"Building";"Refinery";NA;35;0
"Unit";"Marine";"Barracks";37;1
"Unit";"SCV";"Command Center";38;1
"Unit";"SCV";"Command Center";38;1
"Unit";"Marine";"Barracks";38;1
"Building";"Barracks";NA;31;0
"Unit";"Marine";"Barracks";39;1
"Unit";"SCV";"Command Center";44;1
"Unit";"SCV";"Command Center";44;1
"Unit";"SCV";"Command Center";45;1
"Unit";"Marine";"Barracks";44;1
"Unit";"Marine";"Barracks";44;1
"Unit";"SCV";"Command Center";49;1
"Unit";"SCV";"Command Center";49;1
"Unit";"Marine";"Barracks";47;1
"Unit";"Marine";"Barracks";47;1
"Unit";"Marine";"Barracks";47;1
"Unit";"SCV";"Command Center";52;1
"Unit";"Marine";"Barracks";50;1
"Unit";"SCV";"Command Center";52;1
"Unit";"SCV";"Command Center";54;1
"Building";"SupplyDepot";NA;52;0
"Building";"SupplyDepot";NA;52;0
"Unit";"Marine";"Barracks";52;1
"Building";"Refinery";NA;57;0
"Unit";"SCV";"Command Center";61;1
"Building";"Factory";NA;47;0
"Building";"SupplyDepot";NA;58;0
"Unit";"SCV";"Command Center";62;1
"Unit";"Marine";"Barracks";61;1
"Unit";"Marine";"Barracks";61;1
"Unit";"Marine";"Barracks";61;1
"Unit";"Marine";"Barracks";61;1
"Building";"BarracksTechLab";NA;62;0
"Unit";"SCV";"Command Center";68;1
"Unit";"SCV";"Command Center";68;1
"Unit";"SCV";"Command Center";68;1
"Unit";"Marine";"Barracks";68;1
"Building";"BarracksTechLab";NA;68;0
"Unit";"SCV";"Command Center";71;1
"Unit";"SCV";"Command Center";71;1
"Unit";"Marine";"Barracks";68;1
"Unit";"SCV";"Command Center";72;1
"Unit";"Marine";"Barracks";70;1
"Unit";"Marine";"Barracks";70;1
"Building";"Starport";NA;68;0
"Building";"EngineeringBay";NA;68;0
"Building";"FactoryReactor";NA;68;0
"Building";"EngineeringBay";NA;68;0
"Unit";"Marine";"Barracks";72;1
"Unit";"Marine";"Barracks";72;1
"Building";"Barracks";NA;63;0
"Unit";"SCV";"Command Center";72;1
"Unit";"SCV";"Command Center";73;1
"Building";"Barracks";NA;68;0
"Unit";"SCV";"Command Center";75;1
"Building";"Barracks";NA;68;0
"Unit";"Marine";"Barracks";78;1
"Unit";"Marine";"Barracks";78;1
"Unit";"Marine";"Barracks";78;1
"Unit";"SCV";"Command Center";86;1
"Unit";"SCV";"Command Center";86;1
"Unit";"SCV";"Command Center";86;1
"Unit";"Marine";"Barracks";86;1
"Unit";"Marine";"Barracks";86;1
"Unit";"Marine";"Barracks";86;1
"Unit";"Marine";"Barracks";86;1
"Unit";"Marine";"Barracks";86;1
"Unit";"Marine";"Barracks";86;1
"Building";"SupplyDepot";NA;86;0
"Building";"SupplyDepot";NA;86;0
"Building";"FactoryTechLab";NA;86;0
"Building";"SupplyDepot";NA;86;0
"Building";"SupplyDepot";NA;86;0
"Building";"Factory";NA;80;0
"Unit";"Marauder";"Barracks";86;2
"Unit";"Marauder";"Barracks";86;2
"Unit";"SCV";"Command Center";89;1
"Unit";"SCV";"Command Center";89;1
"Unit";"SCV";"Command Center";89;1
"Unit";"Medivac";"Starport";86;2
"Unit";"Marine";"Barracks";95;1
"Unit";"Marine";"Barracks";95;1
"Unit";"Marine";"Barracks";95;1
"Unit";"Marine";"Barracks";95;1
"Unit";"Marine";"Barracks";99;1
"Unit";"Medivac";"Starport";89;2
"Unit";"Marine";"Barracks";102;1
"Building";"SupplyDepot";NA;99;0
"Building";"SupplyDepot";NA;99;0
"Unit";"SCV";"Command Center";102;1
"Unit";"SCV";"Command Center";102;1
"Unit";"Marauder";"Barracks";102;2
"Unit";"Marauder";"Barracks";102;2
"Building";"FactoryTechLab";NA;104;0
"Unit";"Marine";"Barracks";108;1
"Unit";"Marine";"Barracks";111;1
"Unit";"Marine";"Barracks";114;1
"Unit";"Marine";"Barracks";114;1
"Unit";"Marine";"Barracks";114;1
"Unit";"Marine";"Barracks";114;1
"Upgrade";"Stimpack";"TechLab";83;0
"Unit";"Marine";"Barracks";119;1
"Unit";"Medivac";"Starport";114;2
"Unit";"Marauder";"Barracks";120;2
"Unit";"Marauder";"Barracks";120;2
"Unit";"Medivac";"Starport";120;2
"Upgrade";"TerranInfantryWeaponsLevel1";"EngineeringBay";89;0
"Upgrade";"TerranInfantryArmorsLevel1";"EngineeringBay";89;0
"Unit";"Marine";"Barracks";127;1
"Unit";"Marine";"Barracks";127;1
"Unit";"Marine";"Barracks";127;1
"Unit";"Marine";"Barracks";127;1
"Unit";"Marine";"Barracks";133;1
"Unit";"Marine";"Barracks";133;1
"Unit";"Marauder";"Barracks";133;2
"Unit";"Marauder";"Barracks";133;2
"Unit";"Marine";"Barracks";143;1
"Unit";"Marine";"Barracks";143;1
"Unit";"Marine";"Barracks";143;1
"Unit";"SCV";"Command Center";143;1
"Unit";"SCV";"Command Center";143;1
"Unit";"SCV";"Command Center";143;1
"Unit";"Marine";"Barracks";143;1
"Unit";"Marine";"Barracks";143;1
"Unit";"Marine";"Barracks";143;1
"Building";"Armory";NA;133;0
"Unit";"Marauder";"Barracks";143;2
"Unit";"Marauder";"Barracks";143;2
"Building";"CommandCenter";NA;127;0
"Unit";"Medivac";"Starport";143;2
"Unit";"Medivac";"Starport";143;2
"Unit";"Marine";"Barracks";152;1
"Unit";"Marine";"Barracks";152;1
"Unit";"Marine";"Barracks";152;1
"Unit";"Marine";"Barracks";152;1
"Unit";"Marine";"Barracks";152;1
"Unit";"Marine";"Barracks";152;1
"Unit";"Marauder";"Barracks";152;2
"Unit";"Marauder";"Barracks";154;2
"Unit";"SCV";"Command Center";166;1
"Unit";"SCV";"Command Center";166;1
"Unit";"SCV";"Command Center";166;1
"Unit";"Marine";"Barracks";170;1
"Unit";"Marine";"Barracks";170;1
"Unit";"Marine";"Barracks";170;1
"Unit";"Marine";"Barracks";170;1
"Unit";"Marine";"Barracks";170;1
"Unit";"Marine";"Barracks";170;1
"Unit";"Marauder";"Barracks";170;2
"Unit";"Marauder";"Barracks";170;2
"Unit";"Liberator";"Starport";170;3
"Unit";"Liberator";"Starport";170;3
"Unit";"Marine";"Barracks";183;1
"Unit";"Marine";"Barracks";183;1
"Unit";"Marine";"Barracks";183;1
"Unit";"Marine";"Barracks";183;1
"Unit";"Marine";"Barracks";183;1
"Unit";"Marine";"Barracks";183;1
"Unit";"Marine";"Barracks";183;1
"Unit";"Marine";"Barracks";183;1
"Unit";"SCV";"Command Center";193;1
"Unit";"SCV";"Command Center";193;1
"Unit";"SCV";"Command Center";193;1
"Unit";"SCV";"Command Center";193;1
"Unit";"Marine";"Barracks";189;1
"Unit";"Marine";"Barracks";190;1
"Unit";"Marine";"Barracks";190;1
"Unit";"Marine";"Barracks";192;1
"Unit";"Marine";"Barracks";193;1
"Unit";"Marine";"Barracks";194;1
"Unit";"Marauder";"Barracks";195;2
"Unit";"SCV";"Command Center";197;1
"Unit";"SCV";"Command Center";198;1
"Unit";"SCV";"Command Center";199;1
"Unit";"SCV";"Command Center";200;1
"Building";"Refinery";NA;204;0
"Building";"Refinery";NA;205;0
"Unit";"SCV";"Command Center";213;1
"Unit";"SCV";"Command Center";213;1
"Unit";"SCV";"Command Center";213;1
"Unit";"SCV";"Command Center";213;1
"Unit";"Marine";"Barracks";207;1
"Unit";"Marine";"Barracks";207;1
"Unit";"Marine";"Barracks";207;1
"Unit";"Medivac";"Starport";197;2
"Unit";"Medivac";"Starport";197;2
"Unit";"SCV";"Command Center";214;1
"Unit";"Marine";"Barracks";213;1
"Unit";"Marine";"Barracks";213;1
"Unit";"Marine";"Barracks";213;1
"Unit";"Marauder";"Barracks";213;2
"Unit";"Marauder";"Barracks";213;2
"Unit";"Marine";"Barracks";224;1
"Unit";"Marine";"Barracks";224;1
"Unit";"Marine";"Barracks";224;1
"Unit";"SCV";"Command Center";224;1
"Unit";"SCV";"Command Center";224;1
"Unit";"Marine";"Barracks";225;1
"Unit";"Marine";"Barracks";228;1
"Unit";"Marine";"Barracks";228;1
"Unit";"SCV";"Command Center";235;1
"Unit";"Hellion";"Factory";232;2
"Unit";"Marauder";"Barracks";232;2
"Unit";"Marine";"Barracks";237;1
"Unit";"Marauder";"Barracks";232;2
"Unit";"Marine";"Barracks";237;1
"Unit";"Marine";"Barracks";237;1
"Unit";"Marine";"Barracks";241;1
"Unit";"Marine";"Barracks";241;1
"Unit";"Marine";"Barracks";241;1
"Unit";"Marine";"Barracks";250;1
"Unit";"Marine";"Barracks";250;1
"Unit";"Marine";"Barracks";250;1
"Unit";"SCV";"Command Center";250;1
"Unit";"SCV";"Command Center";250;1
"Unit";"SCV";"Command Center";250;1
"Unit";"SCV";"Command Center";250;1
"Unit";"Marauder";"Barracks";250;2
"Unit";"Marauder";"Barracks";250;2
"Unit";"Marine";"Barracks";260;1
"Unit";"Marine";"Barracks";260;1
"Unit";"Marine";"Barracks";260;1
"Unit";"Marine";"Barracks";260;1
"Unit";"Marine";"Barracks";260;1
"Building";"SupplyDepot";NA;253;0
"Unit";"Marine";"Barracks";260;1
"Building";"SupplyDepot";NA;253;0
"Unit";"Liberator";"Starport";241;3
"Unit";"Liberator";"Starport";241;3
"Unit";"Marauder";"Barracks";264;2
"Unit";"Marauder";"Barracks";264;2
"Unit";"SCV";"Command Center";280;1
"Unit";"SCV";"Command Center";280;1
"Unit";"SCV";"Command Center";280;1
"Unit";"SCV";"Command Center";280;1
"Unit";"Marine";"Barracks";280;1
"Unit";"Marine";"Barracks";280;1
"Unit";"Marine";"Barracks";280;1
"Unit";"Marine";"Barracks";280;1
"Unit";"Marine";"Barracks";280;1
"Unit";"Marine";"Barracks";280;1
"Unit";"SCV";"Command Center";284;1
"Unit";"SCV";"Command Center";284;1
"Unit";"SCV";"Command Center";284;1
"Unit";"SCV";"Command Center";284;1
"Unit";"Marauder";"Barracks";280;2
"Unit";"Marauder";"Barracks";280;2
"Upgrade";"TerranInfantryWeaponsLevel2";"EngineeringBay";241;0
"Unit";"SCV";"Command Center";290;1
"Unit";"SCV";"Command Center";291;1
"Unit";"SCV";"Command Center";292;1
"Unit";"SCV";"Command Center";293;1
"Upgrade";"TerranInfantryArmorsLevel2";"EngineeringBay";250;0
"Unit";"Medivac";"Starport";284;2
"Unit";"Medivac";"Starport";284;2
"Unit";"Marine";"Barracks";298;1
"Unit";"Marine";"Barracks";298;1
"Unit";"Marine";"Barracks";298;1
"Unit";"Marine";"Barracks";298;1
"Unit";"Marine";"Barracks";298;1
"Unit";"Marine";"Barracks";298;1
"Unit";"SCV";"Command Center";302;1
"Unit";"SCV";"Command Center";304;1
"Unit";"SCV";"Command Center";306;1
"Unit";"SCV";"Command Center";306;1
"Unit";"Marauder";"Barracks";298;2
"Unit";"Marauder";"Barracks";298;2
"Building";"GhostAcademy";NA;302;0
"Unit";"Marine";"Barracks";312;1
"Unit";"Marine";"Barracks";313;1
"Building";"Refinery";NA;306;0
"Unit";"Marine";"Barracks";316;1
"Building";"Refinery";NA;306;0
"Unit";"Marine";"Barracks";320;1
"Unit";"Marine";"Barracks";320;1
"Unit";"Marine";"Barracks";320;1
"Upgrade";"TerranVehicleWeaponsLevel1";"Armory";280;0
"Unit";"SCV";"Command Center";323;1
"Unit";"SCV";"Command Center";323;1
"Unit";"SCV";"Command Center";323;1
"Unit";"SCV";"Command Center";323;1
"Unit";"Marauder";"Barracks";320;2
"Unit";"Marauder";"Barracks";320;2
"Unit";"Marine";"Barracks";323;1
"Unit";"Marine";"Barracks";323;1
"Unit";"Marine";"Barracks";323;1
"Building";"BarracksTechLab";NA;326;0
"Building";"BarracksTechLab";NA;326;0
"Unit";"Marine";"Barracks";326;1
"Unit";"Ghost";"Barracks";330;2
"Unit";"Ghost";"Barracks";332;2
"Unit";"SCV";"Command Center";338;1
"Unit";"SCV";"Command Center";338;1
"Unit";"SCV";"Command Center";338;1
"Unit";"SCV";"Command Center";338;1
"Building";"SupplyDepot";NA;338;0
"Unit";"Marine";"Barracks";338;1
"Unit";"Marine";"Barracks";338;1
"Unit";"Marine";"Barracks";338;1
"Unit";"Marine";"Barracks";338;1
"Unit";"Marauder";"Barracks";338;2
"Unit";"Marauder";"Barracks";338;2
"Unit";"Ghost";"Barracks";346;2
"Unit";"Ghost";"Barracks";346;2
"Unit";"Marine";"Barracks";354;1
"Unit";"Marine";"Barracks";354;1
"Unit";"Marine";"Barracks";354;1
"Unit";"Marine";"Barracks";354;1
"Unit";"Liberator";"Starport";338;3
"Unit";"Liberator";"Starport";338;3
"Unit";"Marauder";"Barracks";354;2
"Unit";"Marauder";"Barracks";354;2
"Unit";"Marine";"Barracks";372;1
"Unit";"Marine";"Barracks";372;1
"Unit";"Marine";"Barracks";372;1
"Unit";"Marine";"Barracks";372;1
"Unit";"Marauder";"Barracks";372;2
"Unit";"Marauder";"Barracks";372;2
"Unit";"Marauder";"Barracks";372;2
"Unit";"Marauder";"Barracks";372;2
"Upgrade";"TerranInfantryWeaponsLevel3";"EngineeringBay";325;0
"Upgrade";"TerranInfantryArmorsLevel3";"EngineeringBay";330;0
"Unit";"Marine";"Barracks";384;1
"Unit";"Marine";"Barracks";384;1
"Unit";"Marine";"Barracks";384;1
"Unit";"Marine";"Barracks";384;1
"Unit";"Ghost";"Barracks";384;2
"Unit";"Ghost";"Barracks";384;2
"Unit";"Ghost";"Barracks";384;2
"Unit";"Ghost";"Barracks";384;2
"Unit";"Marine";"Barracks";388;1
"Unit";"Marine";"Barracks";388;1
"Unit";"Marine";"Barracks";388;1
"Unit";"Marine";"Barracks";388;1
"Unit";"Liberator";"Starport";384;3
"Unit";"Liberator";"Starport";384;3
"Unit";"SCV";"Command Center";400;1
"Unit";"SCV";"Command Center";400;1
"Unit";"SCV";"Command Center";400;1
"Unit";"SCV";"Command Center";400;1
"Unit";"Marine";"Barracks";403;1
"Unit";"Marine";"Barracks";406;1
"Unit";"Marine";"Barracks";406;1
"Unit";"Marine";"Barracks";406;1
"Upgrade";"TerranVehicleWeaponsLevel2";"Armory";372;0
"Unit";"Ghost";"Barracks";406;2
"Unit";"Ghost";"Barracks";406;2
"Unit";"Ghost";"Barracks";406;2
"Unit";"Ghost";"Barracks";406;2
"Unit";"Marine";"Barracks";414;1
"Unit";"Marine";"Barracks";414;1
"Unit";"Marine";"Barracks";414;1
"Unit";"Marine";"Barracks";414;1
