"type";"unit_name";"on_building";"total_supply";"supply"
"Building";"Refinery";NA;14;0
"Building";"Barracks";NA;15;0
"Unit";"Reaper";"Barracks";19;1
"Building";"Refinery";NA;21;0
"Building";"Factory";NA;19;0
"Building";"BarracksReactor";NA;20;0
"Building";"CommandCenter";NA;19;0
"Building";"BarracksTechLab";NA;24;0
"Unit";"Hellion";"Factory";24;2
"Unit";"Hellion";"Factory";24;2
"Building";"Starport";NA;23;0
"Unit";"Hellion";"Factory";25;2
"Unit";"Hellion";"Factory";27;2
"Unit";"Hellion";"Factory";37;2
"Unit";"Hellion";"Factory";37;2
"Unit";"Hellion";"Factory";44;2
"Unit";"Hellion";"Factory";44;2
"Unit";"Banshee";"Starport";44;3
"Unit";"Hellion";"Factory";52;2
"Unit";"Hellion";"Factory";52;2
"Unit";"Banshee";"Starport";57;3
"Unit";"Cyclone";"Factory";65;3
"Unit";"Cyclone";"Factory";65;3
"Building";"Refinery";NA;67;0
"Building";"Refinery";NA;67;0
"Building";"BarracksTechLab";NA;67;0
"Building";"CommandCenter";NA;52;0
"Building";"Armory";NA;65;0
"Unit";"Hellion";"Factory";78;2
"Unit";"Hellion";"Factory";78;2
"Building";"Factory";NA;67;0
"Building";"Factory";NA;67;0
"Unit";"Hellion";"Factory";88;2
"Unit";"Hellion";"Factory";88;2
"Building";"StarportReactor";NA;82;0
"Building";"Refinery";NA;88;0
"Building";"Refinery";NA;90;0
"Unit";"Hellion";"Factory";94;2
"Unit";"Hellion";"Factory";94;2
"Building";"EngineeringBay";NA;94;0
"Unit";"Thor";"Factory";90;6
"Unit";"Thor";"Factory";90;6
"Unit";"Medivac";"Starport";94;2
"Unit";"Medivac";"Starport";94;2
"Unit";"Hellion";"Factory";100;2
"Unit";"Hellion";"Factory";100;2
"Building";"BarracksTechLab";NA;128;0
"Unit";"Hellion";"Factory";128;2
"Unit";"Hellion";"Factory";128;2
"Building";"Armory";NA;104;0
"Building";"Factory";NA;125;0
"Building";"StarportReactor";NA;128;0
"Building";"Factory";NA;128;0
"Unit";"Hellion";"Factory";138;2
"Unit";"Hellion";"Factory";138;2
"Building";"MissileTurret";NA;142;0
"Upgrade";"TerranVehicleWeaponsLevel1";"Armory";117;0
"Unit";"Hellion";"Factory";149;2
"Unit";"Hellion";"Factory";149;2
"Unit";"Hellion";"Factory";149;2
"Unit";"Hellion";"Factory";149;2
"Building";"MissileTurret";NA;157;0
"Building";"MissileTurret";NA;157;0
"Unit";"Hellion";"Factory";157;2
"Unit";"Hellion";"Factory";157;2
"Unit";"Hellion";"Factory";157;2
"Unit";"Hellion";"Factory";157;2
"Building";"CommandCenter";NA;142;0
"Building";"Refinery";NA;165;0
"Unit";"Hellion";"Factory";168;2
"Unit";"Hellion";"Factory";168;2
"Unit";"Hellion";"Factory";168;2
"Unit";"Hellion";"Factory";168;2
"Building";"Refinery";NA;168;0
"Building";"MissileTurret";NA;168;0
"Unit";"Hellion";"Factory";168;2
"Unit";"Hellion";"Factory";170;2
"Unit";"Hellion";"Factory";176;2
"Unit";"Hellion";"Factory";176;2
"Unit";"Hellion";"Factory";176;2
"Building";"MissileTurret";NA;180;0
"Building";"MissileTurret";NA;180;0
"Unit";"Hellion";"Factory";184;2
"Building";"CommandCenter";NA;168;0
"Upgrade";"TerranVehicleWeaponsLevel2";"Armory";157;0
"Unit";"Hellion";"Factory";186;2
"Unit";"Hellion";"Factory";186;2
"Unit";"Hellion";"Factory";186;2
"Unit";"Hellion";"Factory";188;2
"Building";"Starport";NA;186;0
"Building";"Starport";NA;186;0
"Building";"Starport";NA;186;0
"Unit";"Hellion";"Factory";188;2
"Building";"Refinery";NA;194;0
"Unit";"Hellion";"Factory";194;2
"Unit";"Hellion";"Factory";194;2
"Building";"Refinery";NA;196;0
"Unit";"Hellion";"Factory";202;2
"Unit";"Hellion";"Factory";202;2
"Unit";"Hellion";"Factory";202;2
"Unit";"Hellion";"Factory";202;2
"Building";"SensorTower";NA;202;0
"Unit";"Thor";"Factory";202;6
"Unit";"Thor";"Factory";202;6
"Unit";"Hellion";"Factory";210;2
"Unit";"Hellion";"Factory";210;2
"Unit";"Hellion";"Factory";210;2
"Unit";"Hellion";"Factory";210;2
"Building";"StarportReactor";NA;230;0
"Building";"Factory";NA;230;0
"Building";"Factory";NA;230;0
"Building";"Factory";NA;230;0
"Unit";"Hellion";"Factory";230;2
"Unit";"Hellion";"Factory";230;2
"Unit";"Hellion";"Factory";230;2
"Unit";"Hellion";"Factory";230;2
"Unit";"Hellion";"Factory";238;2
"Unit";"Hellion";"Factory";238;2
"Unit";"Hellion";"Factory";238;2
"Building";"CommandCenter";NA;230;0
