"Type";"UnitName";"OnBuilding";"TotalSupply";"Supply"
"Unit";"SCV";"Command Center";12;1
"Unit";"SCV";"Command Center";12;1
"Unit";"SCV";"Command Center";13;1
"Building";"SupplyDepot";NA;13;0
"Unit";"SCV";"Command Center";15;1
"Building";"Refinery";NA;14;0
"Unit";"SCV";"Command Center";15;1
"Unit";"SCV";"Command Center";16;1
"Unit";"SCV";"Command Center";17;1
"Building";"Barracks";NA;15;0
"Unit";"Reaper";"Barracks";19;1
"Unit";"SCV";"Command Center";19;1
"Unit";"SCV";"Command Center";20;1
"Unit";"SCV";"Command Center";21;1
"Building";"SupplyDepot";NA;21;0
"Building";"Refinery";NA;21;0
"Building";"Factory";NA;19;0
"Building";"BarracksReactor";NA;20;0
"Unit";"SCV";"Command Center";23;1
"Building";"CommandCenter";NA;19;0
"Unit";"SCV";"Command Center";24;1
"Building";"BarracksTechLab";NA;24;0
"Unit";"Hellion";"Factory";24;2
"Unit";"Hellion";"Factory";24;2
"Unit";"SCV";"Command Center";24;1
"Building";"Starport";NA;23;0
"Unit";"SCV";"Command Center";29;1
"Unit";"SCV";"Command Center";29;1
"Unit";"Hellion";"Factory";25;2
"Unit";"Hellion";"Factory";27;2
"Unit";"SCV";"Command Center";30;1
"Unit";"SCV";"Command Center";31;1
"Unit";"SCV";"Command Center";36;1
"Unit";"SCV";"Command Center";37;1
"Unit";"Hellion";"Factory";37;2
"Unit";"Hellion";"Factory";37;2
"Building";"SupplyDepot";NA;38;0
"Unit";"SCV";"Command Center";44;1
"Unit";"SCV";"Command Center";44;1
"Building";"SupplyDepot";NA;44;0
"Unit";"SCV";"Command Center";46;1
"Unit";"SCV";"Command Center";46;1
"Unit";"Hellion";"Factory";44;2
"Unit";"Hellion";"Factory";44;2
"Unit";"SCV";"Command Center";46;1
"Unit";"SCV";"Command Center";47;1
"Unit";"Banshee";"Starport";44;3
"Building";"SupplyDepot";NA;46;0
"Unit";"SCV";"Command Center";52;1
"Unit";"SCV";"Command Center";53;1
"Unit";"Hellion";"Factory";52;2
"Unit";"Hellion";"Factory";52;2
"Unit";"SCV";"Command Center";57;1
"Unit";"SCV";"Command Center";58;1
"Building";"SupplyDepot";NA;57;0
"Unit";"SCV";"Command Center";65;1
"Unit";"SCV";"Command Center";65;1
"Building";"SupplyDepot";NA;65;0
"Unit";"SCV";"Command Center";65;1
"Unit";"SCV";"Command Center";66;1
"Unit";"Banshee";"Starport";57;3
"Unit";"Cyclone";"Factory";65;3
"Unit";"Cyclone";"Factory";65;3
"Building";"Refinery";NA;67;0
"Building";"Refinery";NA;67;0
"Unit";"SCV";"Command Center";67;1
"Unit";"SCV";"Command Center";68;1
"Building";"BarracksTechLab";NA;67;0
"Building";"CommandCenter";NA;52;0
"Unit";"SCV";"Command Center";78;1
"Unit";"SCV";"Command Center";79;1
"Building";"Armory";NA;65;0
"Unit";"Hellion";"Factory";78;2
"Unit";"Hellion";"Factory";78;2
"Unit";"SCV";"Command Center";82;1
"Unit";"SCV";"Command Center";82;1
"Building";"Factory";NA;67;0
"Building";"Factory";NA;67;0
"Unit";"SCV";"Command Center";88;1
"Unit";"SCV";"Command Center";88;1
"Unit";"Hellion";"Factory";88;2
"Unit";"Hellion";"Factory";88;2
"Building";"StarportReactor";NA;82;0
"Building";"Refinery";NA;88;0
"Building";"Refinery";NA;90;0
"Unit";"SCV";"Command Center";94;1
"Unit";"SCV";"Command Center";94;1
"Unit";"Hellion";"Factory";94;2
"Unit";"Hellion";"Factory";94;2
"Unit";"SCV";"Command Center";96;1
"Unit";"SCV";"Command Center";96;1
"Building";"EngineeringBay";NA;94;0
"Unit";"SCV";"Command Center";100;1
"Unit";"SCV";"Command Center";101;1
"Unit";"SCV";"Command Center";102;1
"Unit";"Thor";"Factory";90;6
"Unit";"Thor";"Factory";90;6
"Unit";"Medivac";"Starport";94;2
"Unit";"Medivac";"Starport";94;2
"Unit";"Hellion";"Factory";100;2
"Unit";"Hellion";"Factory";100;2
"Unit";"SCV";"Command Center";102;1
"Unit";"SCV";"Command Center";103;1
"Unit";"SCV";"Command Center";104;1
"Building";"SupplyDepot";NA;102;0
"Building";"SupplyDepot";NA;102;0
"Building";"SupplyDepot";NA;102;0
"Unit";"SCV";"Command Center";125;1
"Unit";"SCV";"Command Center";126;1
"Unit";"SCV";"Command Center";127;1
"Building";"BarracksTechLab";NA;128;0
"Unit";"SCV";"Command Center";128;1
"Unit";"SCV";"Command Center";131;1
"Unit";"Hellion";"Factory";128;2
"Unit";"SCV";"Command Center";131;1
"Unit";"Hellion";"Factory";128;2
"Building";"Armory";NA;104;0
"Unit";"SCV";"Command Center";131;1
"Building";"Factory";NA;125;0
"Building";"SupplyDepot";NA;131;0
"Building";"SupplyDepot";NA;131;0
"Unit";"SCV";"Command Center";136;1
"Unit";"SCV";"Command Center";136;1
"Building";"StarportReactor";NA;128;0
"Building";"Factory";NA;128;0
"Unit";"SCV";"Command Center";138;1
"Unit";"Hellion";"Factory";138;2
"Unit";"Hellion";"Factory";138;2
"Unit";"SCV";"Command Center";139;1
"Unit";"SCV";"Command Center";140;1
"Unit";"SCV";"Command Center";141;1
"Building";"MissileTurret";NA;142;0
"Building";"SupplyDepot";NA;142;0
"Upgrade";"TerranVehicleWeaponsLevel1";"Armory";117;0
"Building";"SupplyDepot";NA;142;0
"Unit";"Hellion";"Factory";149;2
"Unit";"Hellion";"Factory";149;2
"Unit";"Hellion";"Factory";149;2
"Unit";"Hellion";"Factory";149;2
"Building";"SupplyDepot";NA;149;0
"Building";"MissileTurret";NA;157;0
"Building";"MissileTurret";NA;157;0
"Building";"SupplyDepot";NA;157;0
"Building";"SupplyDepot";NA;157;0
"Unit";"Hellion";"Factory";157;2
"Unit";"Hellion";"Factory";157;2
"Unit";"Hellion";"Factory";157;2
"Unit";"Hellion";"Factory";157;2
"Building";"SupplyDepot";NA;157;0
"Building";"SupplyDepot";NA;157;0
"Building";"CommandCenter";NA;142;0
"Unit";"SCV";"Command Center";157;1
"Unit";"SCV";"Command Center";157;1
"Unit";"SCV";"Command Center";157;1
"Building";"Refinery";NA;165;0
"Unit";"Hellion";"Factory";168;2
"Unit";"Hellion";"Factory";168;2
"Unit";"Hellion";"Factory";168;2
"Unit";"Hellion";"Factory";168;2
"Building";"Refinery";NA;168;0
"Building";"MissileTurret";NA;168;0
"Unit";"Hellion";"Factory";168;2
"Unit";"Hellion";"Factory";170;2
"Unit";"Hellion";"Factory";176;2
"Unit";"Hellion";"Factory";176;2
"Upgrade";"TerranVehicleAndShipArmorsLevel1";"Armory";157;0
"Unit";"Hellion";"Factory";176;2
"Building";"MissileTurret";NA;180;0
"Building";"MissileTurret";NA;180;0
"Unit";"Hellion";"Factory";184;2
"Building";"CommandCenter";NA;168;0
"Upgrade";"TerranVehicleWeaponsLevel2";"Armory";157;0
"Unit";"Hellion";"Factory";186;2
"Unit";"Hellion";"Factory";186;2
"Unit";"Hellion";"Factory";186;2
"Unit";"Hellion";"Factory";188;2
"Building";"Starport";NA;186;0
"Building";"Starport";NA;186;0
"Building";"Starport";NA;186;0
"Unit";"Hellion";"Factory";188;2
"Building";"Refinery";NA;194;0
"Unit";"Hellion";"Factory";194;2
"Unit";"Hellion";"Factory";194;2
"Building";"Refinery";NA;196;0
"Unit";"Hellion";"Factory";202;2
"Unit";"Hellion";"Factory";202;2
"Unit";"Hellion";"Factory";202;2
"Unit";"Hellion";"Factory";202;2
"Building";"SensorTower";NA;202;0
"Unit";"Thor";"Factory";202;6
"Unit";"Thor";"Factory";202;6
"Unit";"Hellion";"Factory";210;2
"Unit";"Hellion";"Factory";210;2
"Unit";"Hellion";"Factory";210;2
"Unit";"Hellion";"Factory";210;2
"Building";"StarportReactor";NA;230;0
"Building";"Factory";NA;230;0
"Building";"Factory";NA;230;0
"Building";"Factory";NA;230;0
"Unit";"Hellion";"Factory";230;2
"Unit";"Hellion";"Factory";230;2
"Unit";"Hellion";"Factory";230;2
"Unit";"Hellion";"Factory";230;2
"Upgrade";"TerranVehicleAndShipArmorsLevel2";"Armory";222;0
"Unit";"Hellion";"Factory";238;2
"Unit";"Hellion";"Factory";238;2
"Unit";"Hellion";"Factory";238;2
"Building";"CommandCenter";NA;230;0
