"Type";"UnitName";"OnBuilding";"TotalSupply";"Supply"
"Unit";"SCV";"Command Center";12;1
"Unit";"SCV";"Command Center";12;1
"Unit";"SCV";"Command Center";13;1
"Building";"SupplyDepot";NA;13;0
"Unit";"SCV";"Command Center";15;1
"Building";"Refinery";NA;14;0
"Unit";"SCV";"Command Center";15;1
"Unit";"SCV";"Command Center";16;1
"Unit";"SCV";"Command Center";17;1
"Building";"Barracks";NA;15;0
"Unit";"Reaper";"Barracks";19;1
"Unit";"SCV";"Command Center";19;1
"Unit";"SCV";"Command Center";21;1
"Building";"Factory";NA;19;0
"Building";"SupplyDepot";NA;21;0
"Unit";"SCV";"Command Center";22;1
"Building";"BarracksReactor";NA;21;0
"Building";"CommandCenter";NA;19;0
"Unit";"SCV";"Command Center";23;1
"Building";"Refinery";NA;23;0
"Unit";"Hellion";"Factory";23;2
"Unit";"Hellion";"Factory";24;2
"Unit";"SCV";"Command Center";26;1
"Building";"BarracksTechLab";NA;26;0
"Unit";"SCV";"Command Center";28;1
"Unit";"SCV";"Command Center";29;1
"Unit";"Hellion";"Factory";28;2
"Unit";"Hellion";"Factory";28;2
"Building";"CommandCenter";NA;22;0
"Unit";"SCV";"Command Center";29;1
"Unit";"Marine";"Barracks";29;1
"Unit";"SCV";"Command Center";31;1
"Unit";"SCV";"Command Center";35;1
"Unit";"Marine";"Barracks";38;1
"Unit";"Hellion";"Factory";38;2
"Unit";"SCV";"Command Center";39;1
"Unit";"SCV";"Command Center";39;1
"Unit";"Hellion";"Factory";38;2
"Unit";"Marine";"Barracks";39;1
"Unit";"SCV";"Command Center";46;1
"Building";"EngineeringBay";NA;39;0
"Unit";"SCV";"Command Center";46;1
"Building";"EngineeringBay";NA;40;0
"Unit";"SCV";"Command Center";46;1
"Unit";"SCV";"Command Center";49;1
"Unit";"SCV";"Command Center";49;1
"Unit";"Cyclone";"Factory";48;3
"Unit";"Cyclone";"Factory";48;3
"Unit";"SCV";"Command Center";50;1
"Unit";"SCV";"Command Center";50;1
"Building";"SupplyDepot";NA;50;0
"Building";"SupplyDepot";NA;52;0
"Unit";"SCV";"Command Center";59;1
"Unit";"SCV";"Command Center";59;1
"Unit";"SCV";"Command Center";60;1
"Unit";"SCV";"Command Center";60;1
"Unit";"SCV";"Command Center";62;1
"Building";"Refinery";NA;60;0
"Building";"Refinery";NA;60;0
"Unit";"Marine";"Barracks";62;1
"Unit";"SCV";"Command Center";62;1
"Upgrade";"Stimpack";"TechLab";39;0
"Building";"FactoryTechLab";NA;62;0
"Unit";"SCV";"Command Center";64;1
"Building";"Barracks";NA;59;0
"Unit";"SCV";"Command Center";65;1
"Building";"Barracks";NA;59;0
"Unit";"SCV";"Command Center";66;1
"Building";"SupplyDepot";NA;65;0
"Unit";"SCV";"Command Center";69;1
"Building";"SupplyDepot";NA;67;0
"Unit";"Marine";"Barracks";68;1
"Building";"Barracks";NA;62;0
"Building";"Barracks";NA;62;0
"Unit";"SCV";"Command Center";70;1
"Unit";"SCV";"Command Center";71;1
"Unit";"Marine";"Barracks";71;1
"Building";"SupplyDepot";NA;71;0
"Building";"SupplyDepot";NA;71;0
"Unit";"Marine";"Barracks";73;1
"Building";"BarracksReactor";NA;70;0
"Building";"BarracksReactor";NA;70;0
"Building";"Starport";NA;70;0
"Upgrade";"TerranInfantryWeaponsLevel1";"EngineeringBay";60;0
"Upgrade";"TerranInfantryArmorsLevel1";"EngineeringBay";60;0
"Unit";"SCV";"Command Center";76;1
"Building";"BarracksReactor";NA;73;0
"Unit";"SCV";"Command Center";76;1
"Unit";"SCV";"Command Center";76;1
"Unit";"Marine";"Barracks";76;1
"Unit";"Marine";"Barracks";76;1
"Unit";"Marine";"Barracks";76;1
"Unit";"Marine";"Barracks";76;1
"Unit";"Marine";"Barracks";76;1
"Unit";"Marine";"Barracks";76;1
"Unit";"Marine";"Barracks";76;1
"Building";"Armory";NA;72;0
"Building";"Refinery";NA;76;0
"Unit";"SCV";"Command Center";79;1
"Unit";"Marine";"Barracks";79;1
"Unit";"Marine";"Barracks";80;1
"Unit";"Marine";"Barracks";83;1
"Unit";"Marine";"Barracks";85;1
"Unit";"Marine";"Barracks";86;1
"Unit";"Marine";"Barracks";86;1
"Unit";"Marine";"Barracks";86;1
"Building";"StarportReactor";NA;76;0
"Unit";"Marine";"Barracks";86;1
"Unit";"SCV";"Command Center";87;1
"Unit";"SCV";"Command Center";87;1
"Building";"SupplyDepot";NA;86;0
"Building";"SupplyDepot";NA;86;0
"Unit";"Marauder";"Barracks";86;2
"Unit";"Marine";"Barracks";87;1
"Unit";"Marine";"Barracks";94;1
"Unit";"Marine";"Barracks";94;1
"Unit";"Marine";"Barracks";94;1
"Unit";"Marine";"Barracks";94;1
"Unit";"Marine";"Barracks";94;1
"Unit";"Medivac";"Starport";94;2
"Unit";"Medivac";"Starport";96;2
"Building";"SupplyDepot";NA;100;0
"Building";"SupplyDepot";NA;100;0
"Unit";"Marine";"Barracks";105;1
"Unit";"Marine";"Barracks";105;1
"Unit";"Marine";"Barracks";105;1
"Unit";"Marine";"Barracks";105;1
"Unit";"Marine";"Barracks";105;1
"Unit";"Marine";"Barracks";105;1
"Building";"SupplyDepot";NA;105;0
"Unit";"Marauder";"Barracks";105;2
"Unit";"Marine";"Barracks";105;1
"Building";"CommandCenter";NA;77;0
"Unit";"Medivac";"Starport";114;2
"Unit";"Medivac";"Starport";114;2
"Unit";"Marine";"Barracks";118;1
"Unit";"Marine";"Barracks";118;1
"Unit";"Marine";"Barracks";118;1
"Unit";"Marine";"Barracks";118;1
"Unit";"Marine";"Barracks";118;1
"Unit";"Marine";"Barracks";118;1
"Unit";"Marine";"Barracks";118;1
"Unit";"Marine";"Barracks";118;1
"Unit";"Marauder";"Barracks";118;2
"Building";"Factory";NA;105;0
"Building";"SupplyDepot";NA;118;0
"Unit";"Marine";"Barracks";122;1
"Unit";"Marine";"Barracks";123;1
"Unit";"Marine";"Barracks";124;1
"Building";"SupplyDepot";NA;118;0
"Building";"SupplyDepot";NA;118;0
"Building";"SupplyDepot";NA;118;0
"Unit";"Marine";"Barracks";132;1
"Unit";"Marine";"Barracks";132;1
"Unit";"Marine";"Barracks";132;1
"Unit";"Marine";"Barracks";132;1
"Unit";"Marauder";"Barracks";132;2
"Building";"FactoryTechLab";NA;132;0
"Unit";"Medivac";"Starport";135;2
"Unit";"Medivac";"Starport";135;2
"Unit";"Marine";"Barracks";141;1
"Unit";"SCV";"Command Center";141;1
"Unit";"Marine";"Barracks";141;1
"Unit";"Marine";"Barracks";141;1
"Unit";"Marine";"Barracks";141;1
"Unit";"SCV";"Command Center";141;1
"Unit";"SCV";"Command Center";141;1
"Unit";"SCV";"Command Center";141;1
"Upgrade";"TerranInfantryWeaponsLevel2";"EngineeringBay";107;0
"Upgrade";"TerranInfantryArmorsLevel2";"EngineeringBay";107;0
"Unit";"Marauder";"Barracks";141;2
"Unit";"Marine";"Barracks";145;1
"Unit";"Marine";"Barracks";145;1
"Unit";"Marine";"Barracks";145;1
"Building";"Barracks";NA;141;0
"Building";"Barracks";NA;141;0
"Building";"Barracks";NA;141;0
"Unit";"Marine";"Barracks";155;1
"Unit";"Marine";"Barracks";155;1
"Unit";"Marine";"Barracks";155;1
"Unit";"Marine";"Barracks";155;1
"Unit";"Marine";"Barracks";155;1
"Unit";"Marine";"Barracks";155;1
"Building";"Refinery";NA;155;0
"Unit";"Marine";"Barracks";155;1
"Building";"BarracksTechLab";NA;165;0
"Building";"BarracksTechLab";NA;165;0
"Building";"BarracksTechLab";NA;165;0
"Unit";"Marine";"Barracks";165;1
"Unit";"Marine";"Barracks";165;1
"Unit";"Marauder";"Barracks";165;2
"Unit";"Marine";"Barracks";165;1
"Unit";"Marine";"Barracks";165;1
"Unit";"Marine";"Barracks";165;1
"Unit";"Marine";"Barracks";165;1
"Unit";"Marine";"Barracks";165;1
"Unit";"Marine";"Barracks";165;1
"Unit";"Marine";"Barracks";165;1
"Unit";"Marine";"Barracks";166;1
"Unit";"Marauder";"Barracks";167;2
"Upgrade";"TerranVehicleWeaponsLevel1";"Armory";145;0
"Unit";"Medivac";"Starport";165;2
"Unit";"Medivac";"Starport";165;2
"Unit";"Marine";"Barracks";171;1
"Unit";"Marine";"Barracks";174;1
"Unit";"Marine";"Barracks";175;1
"Unit";"Marauder";"Barracks";170;2
"Unit";"Marine";"Barracks";185;1
"Unit";"Marine";"Barracks";186;1
"Unit";"Marine";"Barracks";186;1
"Unit";"Marine";"Barracks";186;1
"Unit";"Marine";"Barracks";186;1
"Unit";"Marine";"Barracks";186;1
"Unit";"Marine";"Barracks";186;1
"Unit";"Marine";"Barracks";186;1
"Unit";"Marine";"Barracks";186;1
"Unit";"Marauder";"Barracks";183;2
"Unit";"Marauder";"Barracks";183;2
"Unit";"Marauder";"Barracks";184;2
"Unit";"Medivac";"Starport";186;2
"Unit";"Medivac";"Starport";186;2
"Unit";"Marine";"Barracks";188;1
"Unit";"Marine";"Barracks";189;1
"Unit";"Marine";"Barracks";190;1
"Unit";"Marine";"Barracks";190;1
"Unit";"Marine";"Barracks";192;1
"Unit";"Marine";"Barracks";193;1
"Unit";"Marauder";"Barracks";196;2
"Unit";"Marauder";"Barracks";197;2
"Unit";"Marine";"Barracks";203;1
"Unit";"Marine";"Barracks";203;1
"Unit";"Marauder";"Barracks";203;2
"Unit";"Marauder";"Barracks";203;2
