"type";"unit_name";"on_building";"total_supply";"supply"
"Building";"Refinery";NA;14;0
"Building";"Barracks";NA;15;0
"Unit";"Reaper";"Barracks";19;1
"Building";"Refinery";NA;19;0
"Building";"Factory";NA;19;0
"Building";"BarracksReactor";NA;20;0
"Building";"CommandCenter";NA;19;0
"Unit";"Marine";"Barracks";23;1
"Unit";"Marine";"Barracks";23;1
"Building";"FactoryTechLab";NA;23;0
"Building";"Starport";NA;23;0
"Unit";"Hellion";"Factory";28;2
"Unit";"Hellion";"Factory";28;2
"Unit";"Hellion";"Factory";34;2
"Unit";"Hellion";"Factory";34;2
"Unit";"Banshee";"Starport";29;3
"Unit";"Hellion";"Factory";42;2
"Unit";"Hellion";"Factory";42;2
"Unit";"Medivac";"Starport";46;2
"Building";"Armory";NA;42;0
"Unit";"Hellion";"Factory";54;2
"Unit";"Hellion";"Factory";54;2
"Building";"BarracksTechLab";NA;60;0
"Unit";"Marauder";"Barracks";66;2
"Building";"EngineeringBay";NA;67;0
"Building";"EngineeringBay";NA;67;0
"Building";"Refinery";NA;69;0
"Building";"Barracks";NA;67;0
"Building";"Barracks";NA;67;0
"Building";"CommandCenter";NA;64;0
"Unit";"Marauder";"Barracks";74;2
"Building";"Refinery";NA;75;0
"Unit";"Marine";"Barracks";76;1
"Unit";"Marine";"Barracks";76;1
"Building";"Barracks";NA;74;0
"Unit";"Marauder";"Barracks";80;2
"Building";"Barracks";NA;75;0
"Building";"BarracksReactor";NA;76;0
"Building";"StarportReactor";NA;76;0
"Unit";"Marine";"Barracks";84;1
"Unit";"Marine";"Barracks";84;1
"Unit";"Marauder";"Barracks";85;2
"Unit";"Marine";"Barracks";91;1
"Unit";"Marine";"Barracks";91;1
"Unit";"Marine";"Barracks";91;1
"Unit";"Marine";"Barracks";91;1
"Upgrade";"Stimpack";"TechLab";73;0
"Unit";"Marauder";"Barracks";94;2
"Building";"BarracksReactor";NA;92;0
"Building";"BarracksReactor";NA;92;0
"Unit";"Medivac";"Starport";94;2
"Unit";"Medivac";"Starport";94;2
"Unit";"Marine";"Barracks";100;1
"Unit";"Marine";"Barracks";100;1
"Unit";"Marine";"Barracks";100;1
"Unit";"Marine";"Barracks";100;1
"Upgrade";"TerranInfantryWeaponsLevel1";"EngineeringBay";82;0
"Upgrade";"TerranInfantryArmorsLevel1";"EngineeringBay";82;0
"Unit";"Marine";"Barracks";110;1
"Unit";"Marine";"Barracks";110;1
"Building";"Refinery";NA;105;0
"Unit";"Marine";"Barracks";110;1
"Unit";"Marine";"Barracks";110;1
"Building";"Refinery";NA;105;0
"Unit";"Marine";"Barracks";114;1
"Unit";"Marauder";"Barracks";110;2
"Unit";"Marine";"Barracks";114;1
"Unit";"Marine";"Barracks";114;1
"Unit";"Marine";"Barracks";114;1
"Unit";"Medivac";"Starport";115;2
"Unit";"Medivac";"Starport";115;2
"Unit";"Marine";"Barracks";123;1
"Unit";"Marine";"Barracks";123;1
"Unit";"Marine";"Barracks";123;1
"Unit";"Marine";"Barracks";123;1
"Building";"Factory";NA;105;0
"Unit";"Marine";"Barracks";130;1
"Unit";"Marine";"Barracks";130;1
"Unit";"Marine";"Barracks";130;1
"Unit";"Marine";"Barracks";130;1
"Unit";"Marauder";"Barracks";130;2
"Building";"FactoryTechLab";NA;139;0
"Unit";"Marauder";"Barracks";143;2
"Unit";"Marine";"Barracks";145;1
"Unit";"Marine";"Barracks";145;1
"Unit";"Marine";"Barracks";145;1
"Unit";"Marine";"Barracks";145;1
"Unit";"Marauder";"Barracks";145;2
"Unit";"Marine";"Barracks";147;1
"Unit";"Marine";"Barracks";147;1
"Unit";"Marine";"Barracks";152;1
"Unit";"Marine";"Barracks";152;1
"Unit";"Marine";"Barracks";152;1
"Unit";"Marine";"Barracks";152;1
"Unit";"Marine";"Barracks";152;1
"Unit";"Medivac";"Starport";147;2
"Unit";"Medivac";"Starport";147;2
"Unit";"Marauder";"Barracks";152;2
"Unit";"Marine";"Barracks";165;1
"Unit";"Marine";"Barracks";165;1
"Unit";"Marine";"Barracks";165;1
"Unit";"Marine";"Barracks";165;1
"Unit";"Marine";"Barracks";165;1
"Unit";"Marine";"Barracks";165;1
"Unit";"Marine";"Barracks";165;1
"Unit";"Marauder";"Barracks";165;2
