"type";"unit_name";"on_building";"total_supply";"supply"
"Building";"Refinery";NA;15;0
"Building";"Barracks";NA;15;0
"Unit";"Reaper";"Barracks";19;1
"Unit";"Marine";"Barracks";20;1
"Building";"Refinery";NA;21;0
"Building";"CommandCenter";NA;19;0
"Building";"BarracksReactor";NA;23;0
"Building";"Factory";NA;23;0
"Building";"BarracksTechLab";NA;26;0
"Unit";"Hellion";"Factory";26;2
"Unit";"Hellion";"Factory";26;2
"Building";"Starport";NA;26;0
"Unit";"Hellion";"Factory";28;2
"Unit";"Hellion";"Factory";30;2
"Unit";"Hellion";"Factory";39;2
"Unit";"Hellion";"Factory";40;2
"Unit";"Banshee";"Starport";34;3
"Unit";"Cyclone";"Factory";47;3
"Unit";"Cyclone";"Factory";51;3
"Unit";"Banshee";"Starport";51;3
"Unit";"Hellion";"Factory";63;2
"Unit";"Hellion";"Factory";63;2
"Building";"Armory";NA;61;0
"Building";"Refinery";NA;68;0
"Building";"Refinery";NA;68;0
"Building";"CommandCenter";NA;56;0
"Unit";"Banshee";"Starport";68;3
"Unit";"Hellion";"Factory";74;2
"Unit";"Hellion";"Factory";74;2
"Building";"Refinery";NA;84;0
"Unit";"Hellion";"Factory";84;2
"Building";"Factory";NA;76;0
"Building";"Factory";NA;76;0
"Building";"StarportReactor";NA;85;0
"Unit";"Hellion";"Factory";89;2
"Unit";"Hellion";"Factory";89;2
"Building";"Refinery";NA;91;0
"Building";"FactoryTechLab";NA;93;0
"Unit";"Hellion";"Factory";98;2
"Unit";"Hellion";"Factory";98;2
"Building";"Factory";NA;91;0
"Building";"Factory";NA;91;0
"Unit";"Medivac";"Starport";99;2
"Unit";"Medivac";"Starport";101;2
"Unit";"Thor";"Factory";98;6
"Unit";"Hellion";"Factory";108;2
"Unit";"Hellion";"Factory";108;2
"Unit";"Thor";"Factory";101;6
"Upgrade";"TerranVehicleWeaponsLevel1";"Armory";87;0
"Building";"FactoryTechLab";NA;120;0
"Unit";"Hellion";"Factory";132;2
"Unit";"Hellion";"Factory";132;2
"Building";"FactoryReactor";NA;120;0
"Unit";"Hellion";"Factory";138;2
"Unit";"Hellion";"Factory";138;2
"Building";"Armory";NA;132;0
"Unit";"Hellion";"Factory";138;2
"Building";"CommandCenter";NA;133;0
"Unit";"Hellion";"Factory";147;2
"Unit";"Hellion";"Factory";147;2
"Unit";"Hellion";"Factory";147;2
"Building";"Refinery";NA;147;0
"Building";"Refinery";NA;147;0
"Unit";"Hellion";"Factory";148;2
"Unit";"Hellion";"Factory";148;2
"Unit";"Hellion";"Factory";154;2
"Unit";"Hellion";"Factory";154;2
"Unit";"Hellion";"Factory";154;2
"Unit";"Hellion";"Factory";156;2
"Building";"EngineeringBay";NA;154;0
"Unit";"Hellion";"Factory";162;2
"Unit";"Hellion";"Factory";162;2
"Upgrade";"TerranVehicleWeaponsLevel2";"Armory";139;0
"Unit";"Hellion";"Factory";166;2
"Unit";"Hellion";"Factory";166;2
"Unit";"Hellion";"Factory";173;2
"Unit";"Hellion";"Factory";178;2
"Building";"Starport";NA;177;0
"Building";"Starport";NA;177;0
"Unit";"Hellion";"Factory";182;2
"Unit";"Hellion";"Factory";182;2
"Unit";"Hellion";"Factory";182;2
"Unit";"Hellion";"Factory";182;2
"Building";"CommandCenter";NA;180;0
"Unit";"Hellion";"Factory";190;2
"Unit";"Hellion";"Factory";190;2
"Unit";"Hellion";"Factory";190;2
"Unit";"Hellion";"Factory";190;2
"Unit";"Hellion";"Factory";198;2
"Unit";"Thor";"Factory";190;6
"Unit";"Thor";"Factory";192;6
"Unit";"Hellion";"Factory";198;2
"Unit";"Hellion";"Factory";198;2
"Unit";"Hellion";"Factory";198;2
"Unit";"Thor";"Factory";198;6
"Unit";"Thor";"Factory";200;6
"Unit";"Thor";"Factory";206;6
