"type";"unit_name";"on_building";"total_supply";"supply"
"Building";"Refinery";NA;15;0
"Building";"Barracks";NA;15;0
"Unit";"Marine";"Barracks";19;1
"Unit";"Marine";"Barracks";20;1
"Unit";"Marine";"Barracks";22;1
"Building";"Bunker";NA;22;0
"Building";"CommandCenter";NA;19;0
"Unit";"Marine";"Barracks";23;1
"Building";"Bunker";NA;23;0
"Building";"Factory";NA;23;0
"Unit";"Marine";"Barracks";24;1
"Building";"CommandCenter";NA;22;0
"Building";"Bunker";NA;25;0
"Unit";"Marine";"Barracks";26;1
"Building";"Refinery";NA;26;0
"Building";"FactoryTechLab";NA;27;0
"Unit";"Marine";"Barracks";30;1
"Unit";"Marine";"Barracks";34;1
"Unit";"Marine";"Barracks";40;1
"Building";"Starport";NA;37;0
"Unit";"Marine";"Barracks";43;1
"Unit";"Cyclone";"Factory";45;3
"Unit";"Marine";"Barracks";46;1
"Building";"StarportTechLab";NA;52;0
"Unit";"Marine";"Barracks";52;1
"Building";"Refinery";NA;61;0
"Building";"Refinery";NA;61;0
"Building";"Refinery";NA;61;0
"Building";"Refinery";NA;61;0
"Building";"EngineeringBay";NA;62;0
"Unit";"Banshee";"Starport";59;3
"Building";"BarracksReactor";NA;62;0
"Building";"Armory";NA;62;0
"Building";"CommandCenter";NA;63;0
"Building";"CommandCenter";NA;64;0
"Building";"Refinery";NA;77;0
"Building";"Refinery";NA;77;0
"Building";"Refinery";NA;77;0
"Building";"Armory";NA;72;0
"Building";"Refinery";NA;78;0
"Building";"MissileTurret";NA;80;0
"Building";"MissileTurret";NA;81;0
"Unit";"Thor";"Factory";77;6
"Building";"MissileTurret";NA;86;0
"Unit";"Liberator";"Starport";93;3
"Building";"Factory";NA;93;0
"Building";"Factory";NA;93;0
"Building";"SensorTower";NA;102;0
"Unit";"Hellion";"Factory";102;2
"Building";"MissileTurret";NA;102;0
"Building";"FactoryTechLab";NA;114;0
"Unit";"Hellion";"Factory";111;2
"Upgrade";"TerranVehicleWeaponsLevel1";"Armory";86;0
"Building";"SensorTower";NA;118;0
"Building";"FactoryReactor";NA;114;0
"Unit";"Raven";"Starport";114;2
"Unit";"Hellion";"Factory";120;2
"Unit";"Hellion";"Factory";120;2
"Building";"Factory";NA;115;0
"Building";"Factory";NA;118;0
"Building";"Factory";NA;118;0
"Building";"FusionCore";NA;118;0
"Building";"Starport";NA;121;0
"Building";"Starport";NA;122;0
"Unit";"Hellion";"Factory";129;2
"Unit";"Hellion";"Factory";129;2
"Unit";"Hellion";"Factory";129;2
"Unit";"Hellion";"Factory";129;2
"Unit";"Hellion";"Factory";129;2
"Unit";"Hellion";"Factory";131;2
"Unit";"Hellion";"Factory";133;2
"Unit";"Raven";"Starport";129;2
"Building";"CommandCenter";NA;122;0
"Building";"FactoryTechLab";NA;160;0
"Unit";"Thor";"Factory";142;6
"Building";"FactoryTechLab";NA;160;0
"Building";"FactoryTechLab";NA;160;0
"Building";"MissileTurret";NA;160;0
"Building";"MissileTurret";NA;160;0
"Building";"StarportTechLab";NA;160;0
"Unit";"Hellion";"Factory";160;2
"Unit";"Hellion";"Factory";160;2
"Unit";"Hellion";"Factory";160;2
"Building";"StarportReactor";NA;160;0
"Unit";"Hellion";"Factory";160;2
"Building";"MissileTurret";NA;167;0
"Building";"MissileTurret";NA;174;0
"Building";"Refinery";NA;167;0
"Unit";"Raven";"Starport";160;2
"Unit";"Hellion";"Factory";168;2
"Unit";"Hellion";"Factory";170;2
"Unit";"Hellion";"Factory";172;2
"Building";"MissileTurret";NA;174;0
"Upgrade";"TerranVehicleWeaponsLevel2";"Armory";137;0
"Unit";"Hellion";"Factory";174;2
"Unit";"Thor";"Factory";167;6
"Unit";"Thor";"Factory";167;6
"Unit";"Liberator";"Starport";174;3
"Unit";"Liberator";"Starport";185;3
"Unit";"Thor";"Factory";185;6
"Unit";"Thor";"Factory";187;6
"Building";"Refinery";NA;202;0
"Unit";"Liberator";"Starport";199;3
"Unit";"Liberator";"Starport";199;3
"Unit";"Cyclone";"Factory";202;3
"Unit";"Cyclone";"Factory";202;3
"Unit";"Liberator";"Starport";202;3
"Building";"SensorTower";NA;236;0
"Unit";"Banshee";"Starport";228;3
"Unit";"Banshee";"Starport";236;3
"Building";"SensorTower";NA;250;0
"Unit";"Liberator";"Starport";247;3
"Unit";"Liberator";"Starport";250;3
"Unit";"Liberator";"Starport";250;3
"Unit";"Liberator";"Starport";252;3
"Unit";"Liberator";"Starport";259;3
"Building";"CommandCenter";NA;256;0
"Building";"FactoryTechLab";NA;283;0
"Unit";"Raven";"Starport";279;2
"Unit";"Raven";"Starport";279;2
"Unit";"Hellion";"Factory";287;2
"Unit";"Hellion";"Factory";287;2
"Building";"FactoryTechLab";NA;287;0
"Upgrade";"TerranShipWeaponsLevel1";"Armory";268;0
"Unit";"Raven";"Starport";289;2
"Unit";"Raven";"Starport";291;2
"Building";"SensorTower";NA;299;0
"Unit";"Liberator";"Starport";304;3
"Unit";"Liberator";"Starport";304;3
"Upgrade";"TerranInfantryArmorsLevel1";"EngineeringBay";297;0
"Unit";"Raven";"Starport";304;2
"Unit";"Raven";"Starport";307;2
"Building";"CommandCenter";NA;305;0
"Building";"CommandCenter";NA;305;0
"Building";"CommandCenter";NA;306;0
"Building";"CommandCenter";NA;307;0
"Unit";"Banshee";"Starport";315;3
"Building";"CommandCenter";NA;315;0
"Unit";"Thor";"Factory";320;6
"Unit";"Thor";"Factory";320;6
"Building";"MissileTurret";NA;320;0
"Building";"MissileTurret";NA;320;0
"Unit";"Thor";"Factory";320;6
"Building";"MissileTurret";NA;332;0
"Upgrade";"TerranShipWeaponsLevel2";"Armory";317;0
"Building";"SensorTower";NA;338;0
"Building";"MissileTurret";NA;338;0
"Building";"MissileTurret";NA;338;0
"Upgrade";"TerranVehicleWeaponsLevel3";"Armory";317;0
"Building";"MissileTurret";NA;338;0
"Building";"Starport";NA;338;0
"Building";"Starport";NA;338;0
"Building";"Starport";NA;338;0
"Building";"Refinery";NA;339;0
"Building";"StarportTechLab";NA;339;0
"Building";"StarportTechLab";NA;339;0
"Building";"StarportTechLab";NA;339;0
"Building";"Refinery";NA;339;0
"Building";"Refinery";NA;339;0
"Building";"SensorTower";NA;339;0
"Building";"MissileTurret";NA;339;0
"Building";"MissileTurret";NA;339;0
"Building";"MissileTurret";NA;339;0
"Building";"CommandCenter";NA;339;0
"Building";"CommandCenter";NA;339;0
"Building";"CommandCenter";NA;339;0
"Unit";"Raven";"Starport";339;2
"Unit";"Raven";"Starport";339;2
"Unit";"Raven";"Starport";339;2
"Unit";"Raven";"Starport";339;2
"Unit";"Raven";"Starport";339;2
"Unit";"Thor";"Factory";339;6
"Unit";"Thor";"Factory";339;6
"Unit";"Thor";"Factory";339;6
"Building";"Refinery";NA;340;0
"Unit";"Raven";"Starport";340;2
"Building";"MissileTurret";NA;370;0
"Building";"MissileTurret";NA;370;0
"Unit";"Raven";"Starport";368;2
"Unit";"Raven";"Starport";368;2
"Unit";"Hellion";"Factory";372;2
"Unit";"Hellion";"Factory";372;2
"Unit";"Raven";"Starport";368;2
