"Type";"UnitName";"OnBuilding";"TotalSupply";"Supply"
"Unit";"SCV";"Command Center";12;1
"Unit";"SCV";"Command Center";12;1
"Unit";"SCV";"Command Center";13;1
"Building";"SupplyDepot";NA;13;0
"Unit";"SCV";"Command Center";15;1
"Unit";"SCV";"Command Center";15;1
"Building";"Refinery";NA;15;0
"Unit";"SCV";"Command Center";16;1
"Building";"Barracks";NA;15;0
"Unit";"SCV";"Command Center";17;1
"Unit";"Reaper";"Barracks";19;1
"Unit";"SCV";"Command Center";19;1
"Building";"SupplyDepot";NA;19;0
"Unit";"Marine";"Barracks";19;1
"Unit";"SCV";"Command Center";20;1
"Unit";"SCV";"Command Center";22;1
"Unit";"SCV";"Command Center";23;1
"Building";"CommandCenter";NA;19;0
"Unit";"SCV";"Command Center";24;1
"Building";"Factory";NA;21;0
"Building";"BarracksReactor";NA;23;0
"Unit";"SCV";"Command Center";25;1
"Building";"Refinery";NA;25;0
"Unit";"SCV";"Command Center";26;1
"Unit";"SCV";"Command Center";28;1
"Unit";"Hellion";"Factory";27;2
"Unit";"SCV";"Command Center";28;1
"Unit";"Hellion";"Factory";27;2
"Building";"Starport";NA;26;0
"Unit";"SCV";"Command Center";28;1
"Building";"BarracksTechLab";NA;28;0
"Unit";"SCV";"Command Center";34;1
"Building";"CommandCenter";NA;25;0
"Unit";"SCV";"Command Center";34;1
"Unit";"Hellion";"Factory";31;2
"Unit";"Hellion";"Factory";32;2
"Unit";"SCV";"Command Center";35;1
"Unit";"SCV";"Command Center";36;1
"Unit";"SCV";"Command Center";42;1
"Unit";"SCV";"Command Center";42;1
"Building";"BarracksTechLab";NA;42;0
"Unit";"SCV";"Command Center";44;1
"Unit";"SCV";"Command Center";44;1
"Unit";"Banshee";"Starport";36;3
"Unit";"SCV";"Command Center";46;1
"Unit";"SCV";"Command Center";46;1
"Unit";"SCV";"Command Center";47;1
"Building";"SupplyDepot";NA;45;0
"Unit";"Marine";"Barracks";47;1
"Unit";"SCV";"Command Center";50;1
"Unit";"SCV";"Command Center";51;1
"Building";"FactoryReactor";NA;45;0
"Unit";"SCV";"Command Center";52;1
"Building";"Barracks";NA;43;0
"Building";"Barracks";NA;44;0
"Unit";"SCV";"Command Center";54;1
"Unit";"SCV";"Command Center";56;1
"Unit";"SCV";"Command Center";56;1
"Unit";"Marine";"Barracks";53;1
"Building";"EngineeringBay";NA;53;0
"Building";"EngineeringBay";NA;53;0
"Building";"SupplyDepot";NA;55;0
"Unit";"SCV";"Command Center";57;1
"Unit";"SCV";"Command Center";59;1
"Unit";"SCV";"Command Center";59;1
"Unit";"Banshee";"Starport";52;3
"Building";"Refinery";NA;57;0
"Unit";"Marine";"Barracks";60;1
"Unit";"Marine";"Barracks";60;1
"Building";"Refinery";NA;58;0
"Unit";"SCV";"Command Center";61;1
"Unit";"Marine";"Barracks";61;1
"Unit";"Marine";"Barracks";61;1
"Unit";"Marine";"Barracks";61;1
"Unit";"SCV";"Command Center";69;1
"Unit";"SCV";"Command Center";69;1
"Building";"SupplyDepot";NA;63;0
"Unit";"Marine";"Barracks";73;1
"Unit";"Marine";"Barracks";73;1
"Unit";"Marine";"Barracks";73;1
"Unit";"SCV";"Command Center";75;1
"Unit";"SCV";"Command Center";75;1
"Unit";"Marine";"Barracks";75;1
"Building";"SupplyDepot";NA;74;0
"Unit";"SCV";"Command Center";78;1
"Building";"StarportReactor";NA;70;0
"Unit";"SCV";"Command Center";81;1
"Unit";"Marine";"Barracks";79;1
"Building";"SupplyDepot";NA;78;0
"Unit";"SCV";"Command Center";81;1
"Unit";"Marine";"Barracks";81;1
"Unit";"Marine";"Barracks";81;1
"Unit";"Marine";"Barracks";81;1
"Unit";"SCV";"Command Center";82;1
"Building";"Barracks";NA;73;0
"Building";"Barracks";NA;73;0
"Unit";"SCV";"Command Center";82;1
"Upgrade";"Stimpack";"TechLab";57;0
"Building";"SupplyDepot";NA;82;0
"Unit";"SCV";"Command Center";84;1
"Building";"SupplyDepot";NA;82;0
"Unit";"SCV";"Command Center";88;1
"Unit";"SCV";"Command Center";89;1
"Unit";"SCV";"Command Center";90;1
"Unit";"SCV";"Command Center";91;1
"Unit";"Medivac";"Starport";84;2
"Unit";"Medivac";"Starport";84;2
"Unit";"Marine";"Barracks";91;1
"Unit";"Marine";"Barracks";91;1
"Unit";"Marine";"Barracks";91;1
"Unit";"Marine";"Barracks";91;1
"Unit";"SCV";"Command Center";92;1
"Unit";"Marine";"Barracks";91;1
"Unit";"SCV";"Command Center";94;1
"Unit";"SCV";"Command Center";94;1
"Building";"Refinery";NA;92;0
"Building";"Refinery";NA;93;0
"Unit";"Marine";"Barracks";99;1
"Unit";"Marine";"Barracks";100;1
"Unit";"Marine";"Barracks";101;1
"Building";"BarracksReactor";NA;91;0
"Building";"BarracksReactor";NA;91;0
"Unit";"Marine";"Barracks";102;1
"Unit";"Marine";"Barracks";104;1
"Upgrade";"TerranInfantryWeaponsLevel1";"EngineeringBay";75;0
"Upgrade";"TerranInfantryArmorsLevel1";"EngineeringBay";75;0
"Building";"Armory";NA;92;0
"Building";"SupplyDepot";NA;107;0
"Building";"Factory";NA;93;0
"Unit";"Marine";"Barracks";107;1
"Unit";"Marine";"Barracks";108;1
"Unit";"Marine";"Barracks";109;1
"Building";"SupplyDepot";NA;107;0
"Unit";"Marine";"Barracks";111;1
"Unit";"Marine";"Barracks";112;1
"Unit";"Marine";"Barracks";112;1
"Unit";"Marine";"Barracks";112;1
"Unit";"Marine";"Barracks";112;1
"Unit";"Marine";"Barracks";112;1
"Unit";"Medivac";"Starport";107;2
"Unit";"Medivac";"Starport";112;2
"Unit";"Marine";"Barracks";112;1
"Unit";"Marine";"Barracks";114;1
"Unit";"Marine";"Barracks";115;1
"Unit";"Marine";"Barracks";116;1
"Unit";"Marine";"Barracks";120;1
"Unit";"Marine";"Barracks";120;1
"Unit";"Marine";"Barracks";120;1
"Unit";"Marine";"Barracks";123;1
"Building";"FactoryTechLab";NA;123;0
"Unit";"Marine";"Barracks";125;1
"Unit";"Marine";"Barracks";126;1
"Unit";"Marine";"Barracks";127;1
"Unit";"Marine";"Barracks";129;1
"Unit";"Marine";"Barracks";129;1
"Unit";"Marine";"Barracks";130;1
"Unit";"Marine";"Barracks";132;1
"Building";"BarracksTechLab";NA;133;0
"Unit";"Marine";"Barracks";133;1
"Unit";"Marine";"Barracks";134;1
"Unit";"Marine";"Barracks";135;1
"Unit";"Medivac";"Starport";133;2
"Unit";"Marine";"Barracks";136;1
"Unit";"Marine";"Barracks";137;1
"Unit";"Marine";"Barracks";138;1
"Unit";"Marine";"Barracks";139;1
"Unit";"Marine";"Barracks";140;1
"Unit";"Marine";"Barracks";142;1
"Unit";"Marine";"Barracks";143;1
"Building";"FactoryTechLab";NA;148;0
"Unit";"Marine";"Barracks";148;1
"Unit";"Marine";"Barracks";148;1
"Unit";"Marine";"Barracks";148;1
"Unit";"Marine";"Barracks";148;1
"Unit";"Marine";"Barracks";148;1
"Building";"SupplyDepot";NA;149;0
"Unit";"Marine";"Barracks";149;1
"Unit";"Marine";"Barracks";152;1
"Unit";"Marine";"Barracks";152;1
"Unit";"Marine";"Barracks";152;1
"Unit";"Marine";"Barracks";152;1
"Unit";"Marine";"Barracks";152;1
"Unit";"Marine";"Barracks";152;1
"Building";"Refinery";NA;152;0
"Building";"Refinery";NA;152;0
"Unit";"Marine";"Barracks";157;1
"Unit";"Marine";"Barracks";157;1
"Building";"StarportReactor";NA;150;0
"Unit";"Marine";"Barracks";158;1
"Unit";"Marine";"Barracks";159;1
"Unit";"Marine";"Barracks";160;1
"Unit";"Marine";"Barracks";160;1
"Unit";"Marine";"Barracks";160;1
"Unit";"Marine";"Barracks";160;1
"Building";"SupplyDepot";NA;168;0
"Building";"SupplyDepot";NA;168;0
"Building";"SupplyDepot";NA;168;0
"Upgrade";"TerranInfantryWeaponsLevel2";"EngineeringBay";140;0
"Unit";"Marine";"Barracks";172;1
"Unit";"Marine";"Barracks";172;1
"Unit";"Marine";"Barracks";172;1
"Unit";"Marine";"Barracks";172;1
"Unit";"Marine";"Barracks";172;1
"Unit";"Marine";"Barracks";172;1
"Unit";"Marine";"Barracks";172;1
"Unit";"Marine";"Barracks";172;1
"Upgrade";"TerranInfantryArmorsLevel2";"EngineeringBay";149;0
"Unit";"Medivac";"Starport";172;2
"Unit";"Medivac";"Starport";172;2
"Unit";"Marine";"Barracks";172;1
"Unit";"Marine";"Barracks";172;1
"Unit";"Marine";"Barracks";172;1
"Unit";"Marine";"Barracks";172;1
"Unit";"Marine";"Barracks";172;1
"Unit";"Marine";"Barracks";177;1
"Unit";"Marine";"Barracks";180;1
"Building";"SupplyDepot";NA;180;0
"Building";"SupplyDepot";NA;180;0
"Unit";"Marine";"Barracks";190;1
"Unit";"Marine";"Barracks";190;1
"Unit";"Marine";"Barracks";191;1
"Unit";"Marine";"Barracks";191;1
"Unit";"Marine";"Barracks";191;1
"Unit";"Marine";"Barracks";191;1
"Unit";"Marine";"Barracks";191;1
"Unit";"Marine";"Barracks";191;1
"Unit";"Marine";"Barracks";191;1
"Unit";"Medivac";"Starport";191;2
"Unit";"Marine";"Barracks";192;1
"Unit";"Medivac";"Starport";191;2
"Unit";"Marine";"Barracks";193;1
"Unit";"Marine";"Barracks";194;1
"Unit";"Marine";"Barracks";195;1
"Unit";"Marine";"Barracks";196;1
"Unit";"Marine";"Barracks";197;1
"Unit";"Marine";"Barracks";197;1
"Unit";"Marine";"Barracks";199;1
"Unit";"Marine";"Barracks";202;1
"Unit";"Marine";"Barracks";205;1
"Unit";"Marine";"Barracks";206;1
"Unit";"Marine";"Barracks";207;1
"Unit";"Marine";"Barracks";208;1
"Unit";"Marine";"Barracks";209;1
"Unit";"Marine";"Barracks";209;1
