"type";"unit_name";"on_building";"total_supply_lag";"supply"
"Building";"Refinery";NA;15;0
"Building";"Barracks";NA;16;0
"Unit";"Reaper";"Barracks";19;1
"Building";"CommandCenter";NA;20;0
"Building";"Factory";NA;20;0
"Building";"BarracksReactor";NA;21;0
"Building";"Refinery";NA;22;0
"Building";"Starport";NA;24;0
"Unit";"Hellion";"Factory";25;2
"Unit";"Hellion";"Factory";27;2
"Building";"BarracksTechLab";NA;29;0
"Unit";"Hellion";"Factory";31;2
"Unit";"Hellion";"Factory";33;2
"Building";"BarracksTechLab";NA;37;0
"Unit";"Hellion";"Factory";39;2
"Unit";"Hellion";"Factory";41;2
"Unit";"Banshee";"Starport";44;3
"Building";"CommandCenter";NA;51;0
"Unit";"Hellion";"Factory";55;2
"Building";"Refinery";NA;57;0
"Building";"Refinery";NA;57;0
"Unit";"Hellion";"Factory";57;2
"Unit";"Banshee";"Starport";59;3
"Building";"Armory";NA;64;0
"Building";"Armory";NA;64;0
"Building";"Factory";NA;68;0
"Building";"Factory";NA;68;0
"Unit";"Hellion";"Factory";70;2
"Unit";"Hellion";"Factory";72;2
"Building";"StarportReactor";NA;76;0
"Building";"Refinery";NA;79;0
"Building";"Refinery";NA;79;0
"Unit";"Thor";"Factory";79;6
"Unit";"Thor";"Factory";85;6
"Upgrade";"TerranVehicleWeaponsLevel1";"Armory";91;0
"Unit";"Medivac";"Starport";94;2
"Unit";"Medivac";"Starport";96;2
"Unit";"Hellion";"Factory";100;2
"Unit";"Hellion";"Factory";102;2
"Building";"BarracksReactor";NA;111;0
"Building";"Factory";NA;111;0
"Building";"Factory";NA;111;0
"Building";"CommandCenter";NA;113;0
"Unit";"Hellion";"Factory";114;2
"Unit";"Hellion";"Factory";116;2
"Unit";"Hellion";"Factory";121;2
"Unit";"Hellion";"Factory";123;2
"Building";"FactoryTechLab";NA;125;0
"Building";"EngineeringBay";NA;125;0
"Upgrade";"TerranVehicleWeaponsLevel2";"Armory";125;0
"Building";"Refinery";NA;125;0
"Building";"Refinery";NA;125;0
"Building";"MissileTurret";NA;128;0
"Building";"MissileTurret";NA;130;0
"Building";"CommandCenter";NA;130;0
"Unit";"Hellion";"Factory";130;2
"Unit";"Hellion";"Factory";132;2
"Unit";"Hellion";"Factory";134;2
"Unit";"Hellion";"Factory";136;2
"Building";"Starport";NA;138;0
"Building";"Starport";NA;138;0
"Building";"Starport";NA;138;0
"Building";"CommandCenter";NA;138;0
"Building";"SensorTower";NA;138;0
"Building";"Starport";NA;138;0
"Building";"Refinery";NA;138;0
"Building";"Refinery";NA;138;0
"Building";"CommandCenter";NA;138;0
"Unit";"Hellion";"Factory";138;2
"Unit";"Hellion";"Factory";140;2
"Unit";"Hellion";"Factory";142;2
"Unit";"Hellion";"Factory";151;2
"Unit";"Hellion";"Factory";153;2
"Unit";"Hellion";"Factory";158;2
"Unit";"Hellion";"Factory";160;2
"Unit";"Hellion";"Factory";162;2
"Upgrade";"SprayTerran";NA;167;0
"Upgrade";"SprayTerran";NA;167;0
"Upgrade";"SprayTerran";NA;167;0
"Upgrade";"BansheeCloak";NA;167;0
"Upgrade";"SprayTerran";NA;167;0
"Upgrade";"SprayTerran";NA;167;0
"Upgrade";"TerranVehicleAndShipArmorsLevel1";NA;167;0
"Upgrade";"SprayTerran";NA;167;0
"Upgrade";"SprayTerran";NA;167;0
"Upgrade";"HighCapacityBarrels";NA;167;0
"Upgrade";"SprayTerran";NA;167;0
"Upgrade";"TerranVehicleAndShipArmorsLevel2";NA;167;0
"Upgrade";"SprayTerran";NA;167;0
"Upgrade";"SprayTerran";NA;167;0
"Upgrade";"SprayTerran";NA;167;0
"Upgrade";"SprayTerran";NA;167;0
