"type";"unit_name";"on_building";"total_supply_lag";"supply"
"Building";"Barracks";NA;16;0
"Building";"Refinery";NA;16;0
"Unit";"Reaper";"Barracks";19;1
"Building";"CommandCenter";NA;20;0
"Building";"Factory";NA;21;0
"Building";"Refinery";NA;22;0
"Building";"BarracksReactor";NA;23;0
"Building";"Starport";NA;26;0
"Unit";"Hellion";"Factory";26;2
"Unit";"Hellion";"Factory";28;2
"Building";"BarracksTechLab";NA;30;0
"Unit";"Hellion";"Factory";33;2
"Unit";"Hellion";"Factory";35;2
"Unit";"Hellion";"Factory";40;2
"Unit";"Hellion";"Factory";42;2
"Unit";"Banshee";"Starport";47;3
"Unit";"Hellion";"Factory";51;2
"Unit";"Hellion";"Factory";53;2
"Building";"BarracksTechLab";NA;55;0
"Building";"CommandCenter";NA;58;0
"Unit";"Hellion";"Factory";59;2
"Unit";"Hellion";"Factory";61;2
"Unit";"Banshee";"Starport";65;3
"Unit";"Hellion";"Factory";69;2
"Unit";"Hellion";"Factory";71;2
"Unit";"Marine";"Barracks";73;1
"Building";"Barracks";NA;76;0
"Building";"Barracks";NA;76;0
"Unit";"Marine";"Barracks";77;1
"Building";"EngineeringBay";NA;78;0
"Building";"EngineeringBay";NA;78;0
"Building";"Refinery";NA;79;0
"Building";"Refinery";NA;79;0
"Unit";"Marine";"Barracks";79;1
"Upgrade";"Stimpack";"TechLab";80;0
"Building";"StarportReactor";NA;81;0
"Building";"Barracks";NA;83;0
"Building";"Barracks";NA;83;0
"Unit";"Marine";"Barracks";83;1
"Building";"BarracksReactor";NA;85;0
"Unit";"Marine";"Barracks";87;1
"Unit";"Marine";"Barracks";88;1
"Unit";"Medivac";"Starport";90;2
"Unit";"Medivac";"Starport";92;2
"Unit";"Marine";"Barracks";95;1
"Unit";"Marine";"Barracks";98;1
"Building";"BarracksReactor";NA;99;0
"Building";"BarracksReactor";NA;99;0
"Upgrade";"TerranInfantryWeaponsLevel1";"EngineeringBay";99;0
"Unit";"Marine";"Barracks";100;1
"Unit";"Marine";"Barracks";101;1
"Unit";"Marine";"Barracks";102;1
"Unit";"Marine";"Barracks";103;1
"Unit";"Marine";"Barracks";107;1
"Unit";"Marine";"Barracks";110;1
"Unit";"Marine";"Barracks";111;1
"Unit";"Marine";"Barracks";113;1
"Unit";"Marine";"Barracks";114;1
"Unit";"Marine";"Barracks";115;1
"Building";"Armory";NA;117;0
"Unit";"Medivac";"Starport";117;2
"Unit";"Medivac";"Starport";119;2
"Unit";"Marine";"Barracks";121;1
"Unit";"Marine";"Barracks";122;1
"Building";"Refinery";NA;126;0
"Building";"Refinery";NA;126;0
"Building";"Factory";NA;126;0
"Unit";"Marine";"Barracks";126;1
"Unit";"Marine";"Barracks";127;1
"Unit";"Marine";"Barracks";128;1
"Unit";"Marine";"Barracks";129;1
"Unit";"Marine";"Barracks";130;1
"Unit";"Marine";"Barracks";131;1
"Unit";"Marine";"Barracks";132;1
"Unit";"Marine";"Barracks";133;1
"Unit";"Marine";"Barracks";134;1
"Unit";"Marine";"Barracks";137;1
"Unit";"Marine";"Barracks";138;1
"Unit";"Marine";"Barracks";139;1
"Unit";"Marine";"Barracks";140;1
"Unit";"Marine";"Barracks";141;1
"Unit";"Marine";"Barracks";142;1
"Unit";"Medivac";"Starport";143;2
"Unit";"Medivac";"Starport";145;2
"Unit";"Marine";"Barracks";147;1
"Unit";"Marine";"Barracks";148;1
"Unit";"Marine";"Barracks";149;1
"Unit";"Marine";"Barracks";150;1
"Unit";"Marine";"Barracks";151;1
"Unit";"Marine";"Barracks";152;1
"Unit";"Marine";"Barracks";153;1
"Unit";"Marine";"Barracks";154;1
"Unit";"Marine";"Barracks";155;1
"Building";"FactoryTechLab";NA;156;0
"Unit";"Marine";"Barracks";156;1
"Unit";"Marine";"Barracks";157;1
"Unit";"Marine";"Barracks";158;1
"Unit";"Marine";"Barracks";159;1
"Unit";"Marine";"Barracks";160;1
"Unit";"Marine";"Barracks";161;1
"Upgrade";"TerranInfantryWeaponsLevel2";"EngineeringBay";162;0
"Unit";"Marine";"Barracks";162;1
"Unit";"Marine";"Barracks";163;1
"Unit";"Marine";"Barracks";164;1
"Unit";"Marine";"Barracks";165;1
"Unit";"Marine";"Barracks";166;1
"Unit";"Marine";"Barracks";167;1
"Unit";"Marine";"Barracks";168;1
"Unit";"Marine";"Barracks";169;1
"Unit";"Marine";"Barracks";170;1
"Building";"CommandCenter";NA;171;0
"Unit";"Marine";"Barracks";171;1
"Unit";"Marine";"Barracks";172;1
"Unit";"Marine";"Barracks";173;1
"Unit";"Marine";"Barracks";174;1
"Building";"Barracks";NA;175;0
"Unit";"Marine";"Barracks";175;1
"Building";"Barracks";NA;176;0
"Unit";"Marine";"Barracks";176;1
"Building";"Barracks";NA;177;0
"Unit";"Marine";"Barracks";177;1
"Unit";"Marine";"Barracks";178;1
"Unit";"Marine";"Barracks";179;1
"Unit";"Marine";"Barracks";180;1
"Unit";"Marine";"Barracks";181;1
"Unit";"Marine";"Barracks";182;1
"Unit";"Marine";"Barracks";183;1
"Unit";"Marine";"Barracks";184;1
"Unit";"Marine";"Barracks";185;1
"Unit";"Marine";"Barracks";186;1
"Unit";"Marine";"Barracks";187;1
"Unit";"Marine";"Barracks";188;1
"Unit";"Marine";"Barracks";189;1
"Upgrade";"TerranVehicleWeaponsLevel1";"Armory";190;0
"Unit";"Marine";"Barracks";190;1
"Unit";"Marine";"Barracks";191;1
"Unit";"Marine";"Barracks";192;1
"Unit";"Marine";"Barracks";193;1
"Unit";"Marine";"Barracks";194;1
"Unit";"Marine";"Barracks";195;1
"Unit";"Marine";"Barracks";196;1
"Unit";"Marine";"Barracks";197;1
"Unit";"Marine";"Barracks";198;1
"Unit";"Marine";"Barracks";199;1
"Unit";"Marine";"Barracks";200;1
"Unit";"Marine";"Barracks";201;1
"Unit";"Marine";"Barracks";202;1
"Building";"BarracksTechLab";NA;203;0
"Building";"BarracksTechLab";NA;203;0
"Building";"BarracksTechLab";NA;203;0
"Unit";"Marine";"Barracks";205;1
"Building";"CommandCenter";NA;206;0
"Unit";"Marine";"Barracks";206;1
"Unit";"Marine";"Barracks";207;1
"Unit";"Marine";"Barracks";208;1
"Unit";"Medivac";"Starport";209;2
"Unit";"Medivac";"Starport";211;2
"Unit";"Marauder";"Barracks";213;2
"Unit";"Marine";"Barracks";215;1
"Unit";"Marine";"Barracks";216;1
"Unit";"Marine";"Barracks";217;1
"Unit";"Marine";"Barracks";218;1
"Unit";"Marine";"Barracks";219;1
"Unit";"Marine";"Barracks";220;1
"Unit";"Marine";"Barracks";221;1
"Unit";"Marine";"Barracks";222;1
"Unit";"Marine";"Barracks";223;1
"Unit";"Marine";"Barracks";224;1
"Unit";"Marine";"Barracks";225;1
"Unit";"Marine";"Barracks";226;1
"Unit";"Marine";"Barracks";227;1
"Unit";"Marine";"Barracks";228;1
"Unit";"Marine";"Barracks";229;1
"Unit";"Marine";"Barracks";230;1
"Unit";"Marine";"Barracks";231;1
"Unit";"Marine";"Barracks";232;1
"Unit";"Marine";"Barracks";233;1
"Unit";"Marine";"Barracks";234;1
"Unit";"Marine";"Barracks";235;1
"Unit";"Marine";"Barracks";236;1
"Unit";"Marine";"Barracks";237;1
"Unit";"Marine";"Barracks";238;1
"Unit";"Marine";"Barracks";239;1
"Unit";"Marine";"Barracks";240;1
"Unit";"Marine";"Barracks";241;1
"Unit";"Marauder";"Barracks";242;2
"Unit";"Marauder";"Barracks";244;2
"Unit";"Marine";"Barracks";246;1
"Unit";"Marine";"Barracks";247;1
"Unit";"Marine";"Barracks";248;1
"Unit";"Marine";"Barracks";249;1
"Unit";"Marine";"Barracks";250;1
"Unit";"Marine";"Barracks";251;1
"Unit";"Liberator";"Starport";252;3
"Unit";"Liberator";"Starport";255;3
"Unit";"Marine";"Barracks";258;1
"Unit";"Marine";"Barracks";259;1
"Unit";"Marine";"Barracks";260;1
"Unit";"Marine";"Barracks";261;1
"Unit";"Marine";"Barracks";262;1
"Unit";"Marauder";"Barracks";263;2
"Unit";"Marine";"Barracks";265;1
"Unit";"Marine";"Barracks";266;1
"Unit";"Marine";"Barracks";267;1
"Unit";"Marine";"Barracks";268;1
"Unit";"Marine";"Barracks";269;1
"Unit";"Marine";"Barracks";270;1
"Unit";"Marine";"Barracks";271;1
"Unit";"Marine";"Barracks";272;1
"Unit";"Marine";"Barracks";273;1
"Upgrade";"SprayTerran";NA;274;0
"Upgrade";"SprayTerran";NA;274;0
"Upgrade";"SprayTerran";NA;274;0
"Upgrade";"BansheeCloak";NA;274;0
"Upgrade";"SprayTerran";NA;274;0
"Upgrade";"TerranInfantryArmorsLevel1";NA;274;0
"Upgrade";"ShieldWall";NA;274;0
"Upgrade";"SprayTerran";NA;274;0
"Upgrade";"SprayTerran";NA;274;0
"Upgrade";"SprayTerran";NA;274;0
"Upgrade";"TerranInfantryArmorsLevel2";NA;274;0
"Upgrade";"SprayTerran";NA;274;0
