"type";"unit_name";"on_building";"total_supply_lag";"supply"
"Building";"Barracks";NA;16;0
"Building";"Refinery";NA;16;0
"Unit";"Reaper";"Barracks";19;1
"Building";"CommandCenter";NA;20;0
"Unit";"Marine";"Barracks";21;1
"Building";"Factory";NA;23;0
"Building";"Refinery";NA;23;0
"Building";"BarracksReactor";NA;24;0
"Building";"Starport";NA;26;0
"Unit";"Marine";"Barracks";27;1
"Unit";"Marine";"Barracks";28;1
"Unit";"Marine";"Barracks";30;1
"Unit";"Marine";"Barracks";31;1
"Unit";"Medivac";"Starport";34;2
"Unit";"Marine";"Barracks";36;1
"Unit";"Marine";"Barracks";37;1
"Unit";"Hellion";"Factory";41;2
"Unit";"Hellion";"Factory";43;2
"Unit";"Liberator";"Starport";45;3
"Building";"Armory";NA;50;0
"Building";"BarracksTechLab";NA;50;0
"Unit";"Hellion";"Factory";51;2
"Unit";"Hellion";"Factory";53;2
"Building";"CommandCenter";NA;56;0
"Unit";"Hellion";"Factory";57;2
"Unit";"Hellion";"Factory";59;2
"Unit";"Marine";"Barracks";61;1
"Unit";"Marine";"Barracks";66;1
"Unit";"Hellion";"Factory";67;2
"Unit";"Hellion";"Factory";69;2
"Building";"EngineeringBay";NA;71;0
"Building";"EngineeringBay";NA;71;0
"Unit";"Marine";"Barracks";73;1
"Building";"StarportReactor";NA;75;0
"Upgrade";"Stimpack";"TechLab";75;0
"Unit";"Marine";"Barracks";75;1
"Building";"Barracks";NA;76;0
"Building";"Barracks";NA;76;0
"Building";"FactoryReactor";NA;77;0
"Unit";"Marine";"Barracks";78;1
"Building";"Refinery";NA;80;0
"Building";"Refinery";NA;80;0
"Building";"Barracks";NA;80;0
"Building";"Barracks";NA;80;0
"Unit";"Marine";"Barracks";81;1
"Unit";"Medivac";"Starport";82;2
"Unit";"Liberator";"Starport";84;3
"Unit";"Marine";"Barracks";88;1
"Unit";"Marine";"Barracks";89;1
"Upgrade";"TerranInfantryWeaponsLevel1";"EngineeringBay";90;0
"Building";"FactoryReactor";NA;90;0
"Unit";"Marine";"Barracks";92;1
"Unit";"Marine";"Barracks";93;1
"Unit";"Marine";"Barracks";94;1
"Unit";"Marine";"Barracks";97;1
"Unit";"Marine";"Barracks";98;1
"Unit";"Medivac";"Starport";99;2
"Unit";"Marine";"Barracks";101;1
"Building";"BarracksReactor";NA;102;0
"Building";"BarracksReactor";NA;102;0
"Unit";"Marine";"Barracks";105;1
"Unit";"Marine";"Barracks";106;1
"Unit";"Marine";"Barracks";107;1
"Unit";"Medivac";"Starport";110;2
"Unit";"Marine";"Barracks";112;1
"Unit";"Marine";"Barracks";113;1
"Building";"Barracks";NA;115;0
"Building";"Barracks";NA;115;0
"Unit";"Marine";"Barracks";116;1
"Building";"Barracks";NA;118;0
"Unit";"Medivac";"Starport";118;2
"Unit";"Marine";"Barracks";120;1
"Unit";"Marine";"Barracks";121;1
"Unit";"Marine";"Barracks";122;1
"Unit";"Marine";"Barracks";125;1
"Unit";"Marine";"Barracks";126;1
"Unit";"Marine";"Barracks";127;1
"Unit";"Marine";"Barracks";128;1
"Unit";"Marine";"Barracks";129;1
"Unit";"Marine";"Barracks";130;1
"Unit";"Marine";"Barracks";132;1
"Unit";"Marine";"Barracks";133;1
"Unit";"Marine";"Barracks";134;1
"Building";"MissileTurret";NA;137;0
"Unit";"Marine";"Barracks";137;1
"Unit";"Marine";"Barracks";138;1
"Unit";"Marine";"Barracks";139;1
"Unit";"Marine";"Barracks";140;1
"Unit";"Marine";"Barracks";141;1
"Unit";"Marine";"Barracks";142;1
"Building";"BarracksTechLab";NA;143;0
"Building";"BarracksTechLab";NA;143;0
"Unit";"Marine";"Barracks";143;1
"Unit";"Marine";"Barracks";144;1
"Unit";"Marine";"Barracks";145;1
"Unit";"Marauder";"Barracks";146;2
"Unit";"Marine";"Barracks";148;1
"Unit";"Marine";"Barracks";149;1
"Unit";"Marine";"Barracks";150;1
"Unit";"Marine";"Barracks";151;1
"Unit";"Marine";"Barracks";152;1
"Unit";"Marine";"Barracks";153;1
"Unit";"Marauder";"Barracks";154;2
"Unit";"Marine";"Barracks";156;1
"Unit";"Medivac";"Starport";157;2
"Unit";"Medivac";"Starport";159;2
"Upgrade";"TerranInfantryWeaponsLevel2";"EngineeringBay";161;0
"Unit";"Marine";"Barracks";161;1
"Unit";"Marine";"Barracks";162;1
"Unit";"Marine";"Barracks";163;1
"Unit";"Marine";"Barracks";164;1
"Unit";"Marine";"Barracks";165;1
"Unit";"Marine";"Barracks";166;1
"Unit";"Marine";"Barracks";167;1
"Unit";"Marine";"Barracks";168;1
"Unit";"Marine";"Barracks";169;1
"Unit";"Marauder";"Barracks";170;2
"Unit";"Marine";"Barracks";172;1
"Unit";"Marine";"Barracks";173;1
"Building";"MissileTurret";NA;174;0
"Building";"CommandCenter";NA;174;0
"Building";"MissileTurret";NA;174;0
"Building";"MissileTurret";NA;174;0
"Unit";"Marine";"Barracks";174;1
"Unit";"Marine";"Barracks";175;1
"Unit";"Marine";"Barracks";176;1
"Unit";"Marine";"Barracks";177;1
"Unit";"Marine";"Barracks";178;1
"Unit";"Marine";"Barracks";179;1
"Unit";"Marine";"Barracks";180;1
"Unit";"Marine";"Barracks";181;1
"Unit";"Marine";"Barracks";182;1
"Unit";"Marauder";"Barracks";183;2
"Unit";"Marine";"Barracks";185;1
"Building";"MissileTurret";NA;186;0
"Unit";"Marine";"Barracks";186;1
"Unit";"Marine";"Barracks";187;1
"Unit";"Marine";"Barracks";188;1
"Unit";"Marine";"Barracks";189;1
"Unit";"Marine";"Barracks";190;1
"Unit";"Marine";"Barracks";191;1
"Unit";"Marine";"Barracks";192;1
"Unit";"Marine";"Barracks";193;1
"Unit";"Marine";"Barracks";194;1
"Unit";"Medivac";"Starport";195;2
"Unit";"Marine";"Barracks";197;1
"Unit";"Marine";"Barracks";198;1
"Unit";"Marine";"Barracks";199;1
"Unit";"Marine";"Barracks";200;1
"Unit";"Marine";"Barracks";201;1
"Unit";"Marine";"Barracks";202;1
"Unit";"Marine";"Barracks";203;1
"Unit";"Marine";"Barracks";204;1
"Unit";"Marine";"Barracks";205;1
"Unit";"Marine";"Barracks";206;1
"Unit";"Marine";"Barracks";207;1
"Unit";"Marine";"Barracks";208;1
"Unit";"Marine";"Barracks";209;1
"Unit";"Marine";"Barracks";210;1
"Unit";"Marine";"Barracks";211;1
"Unit";"Marine";"Barracks";212;1
"Unit";"Marine";"Barracks";213;1
"Unit";"Marine";"Barracks";214;1
"Unit";"Marine";"Barracks";215;1
"Unit";"Marine";"Barracks";216;1
"Unit";"Marine";"Barracks";217;1
"Unit";"Marine";"Barracks";218;1
"Unit";"Marine";"Barracks";219;1
"Unit";"Marine";"Barracks";220;1
"Unit";"Medivac";"Starport";221;2
"Unit";"Marine";"Barracks";223;1
"Unit";"Marine";"Barracks";224;1
"Unit";"Marine";"Barracks";225;1
"Unit";"Marine";"Barracks";226;1
"Unit";"Marine";"Barracks";227;1
"Unit";"Medivac";"Starport";228;2
"Unit";"Marine";"Barracks";232;1
"Unit";"Marine";"Barracks";233;1
"Unit";"Marine";"Barracks";234;1
"Unit";"Marine";"Barracks";235;1
"Unit";"Marine";"Barracks";236;1
"Unit";"Medivac";"Starport";237;2
"Unit";"Marine";"Barracks";239;1
"Unit";"Marine";"Barracks";240;1
"Unit";"Marine";"Barracks";241;1
"Unit";"Marine";"Barracks";242;1
"Unit";"Marine";"Barracks";243;1
"Unit";"Marine";"Barracks";244;1
"Unit";"Marine";"Barracks";245;1
"Unit";"Marine";"Barracks";246;1
"Unit";"Marine";"Barracks";247;1
"Unit";"Marine";"Barracks";248;1
"Unit";"Marine";"Barracks";252;1
"Unit";"Marine";"Barracks";253;1
"Unit";"Marine";"Barracks";254;1
"Unit";"Medivac";"Starport";255;2
"Unit";"Marine";"Barracks";257;1
"Unit";"Marine";"Barracks";258;1
"Unit";"Marine";"Barracks";259;1
"Unit";"Marine";"Barracks";260;1
"Unit";"Marine";"Barracks";261;1
"Unit";"Marine";"Barracks";265;1
"Unit";"Medivac";"Starport";266;2
"Unit";"Marine";"Barracks";268;1
"Unit";"Marine";"Barracks";272;1
"Unit";"Marine";"Barracks";273;1
"Unit";"Marine";"Barracks";274;1
"Unit";"Marine";"Barracks";275;1
"Unit";"Marine";"Barracks";276;1
"Unit";"Marine";"Barracks";277;1
"Unit";"Medivac";"Starport";278;2
"Building";"MissileTurret";NA;280;0
"Unit";"Marine";"Barracks";282;1
"Unit";"Marauder";"Barracks";283;2
"Unit";"Medivac";"Starport";285;2
"Unit";"Marine";"Barracks";287;1
"Unit";"Marine";"Barracks";288;1
"Unit";"Marine";"Barracks";289;1
"Unit";"Marine";"Barracks";290;1
"Unit";"Marine";"Barracks";291;1
"Unit";"Marine";"Barracks";292;1
"Building";"BarracksTechLab";NA;293;0
"Unit";"Marine";"Barracks";293;1
"Unit";"Marine";"Barracks";294;1
"Unit";"Marine";"Barracks";295;1
"Unit";"Marine";"Barracks";298;1
"Unit";"Medivac";"Starport";301;2
"Unit";"Marine";"Barracks";303;1
"Unit";"Marine";"Barracks";304;1
"Unit";"Marine";"Barracks";305;1
"Unit";"Medivac";"Starport";306;2
"Building";"SensorTower";NA;308;0
"Building";"MissileTurret";NA;308;0
"Unit";"Marauder";"Barracks";308;2
"Unit";"Marine";"Barracks";310;1
"Unit";"Marine";"Barracks";311;1
"Unit";"Marine";"Barracks";312;1
"Unit";"Marine";"Barracks";313;1
"Unit";"Marine";"Barracks";314;1
"Unit";"Marine";"Barracks";315;1
"Unit";"Marine";"Barracks";316;1
"Unit";"Marine";"Barracks";317;1
"Unit";"Marine";"Barracks";318;1
"Unit";"Marine";"Barracks";319;1
"Unit";"Marine";"Barracks";320;1
"Unit";"Medivac";"Starport";321;2
"Unit";"Marine";"Barracks";323;1
"Unit";"Marine";"Barracks";324;1
"Unit";"Marine";"Barracks";325;1
"Unit";"Marine";"Barracks";326;1
"Unit";"Marine";"Barracks";327;1
"Unit";"Marine";"Barracks";328;1
"Unit";"Marine";"Barracks";329;1
"Unit";"Marine";"Barracks";330;1
"Unit";"Marine";"Barracks";331;1
"Unit";"Marine";"Barracks";332;1
"Unit";"Marine";"Barracks";333;1
"Unit";"Marine";"Barracks";334;1
"Unit";"Marine";"Barracks";335;1
"Unit";"Marine";"Barracks";336;1
"Unit";"Marine";"Barracks";337;1
"Unit";"Marine";"Barracks";338;1
"Unit";"Marine";"Barracks";339;1
"Unit";"Marine";"Barracks";340;1
"Unit";"Marine";"Barracks";341;1
"Unit";"Marine";"Barracks";342;1
"Unit";"Marine";"Barracks";343;1
"Unit";"Marine";"Barracks";344;1
"Unit";"Marine";"Barracks";345;1
"Unit";"Marine";"Barracks";346;1
"Unit";"Marine";"Barracks";347;1
"Unit";"Marine";"Barracks";348;1
"Unit";"Marine";"Barracks";349;1
"Unit";"Marine";"Barracks";350;1
"Unit";"Marine";"Barracks";351;1
"Unit";"Marine";"Barracks";352;1
"Building";"CommandCenter";NA;353;0
"Unit";"Marine";"Barracks";353;1
"Unit";"Marine";"Barracks";354;1
"Unit";"Marine";"Barracks";355;1
"Unit";"Marine";"Barracks";356;1
"Unit";"Marauder";"Barracks";357;2
"Unit";"Marine";"Barracks";359;1
"Unit";"Marine";"Barracks";360;1
"Unit";"Marine";"Barracks";361;1
"Unit";"Marine";"Barracks";362;1
"Unit";"Marine";"Barracks";363;1
"Unit";"Marine";"Barracks";364;1
"Unit";"Marine";"Barracks";365;1
"Unit";"Marine";"Barracks";366;1
"Unit";"Marine";"Barracks";367;1
"Unit";"Marine";"Barracks";368;1
"Unit";"Marine";"Barracks";369;1
"Unit";"Marine";"Barracks";370;1
"Unit";"Marine";"Barracks";371;1
"Unit";"Marine";"Barracks";372;1
"Unit";"Marine";"Barracks";373;1
"Unit";"Marine";"Barracks";374;1
"Unit";"Marine";"Barracks";375;1
"Unit";"Marine";"Barracks";376;1
"Unit";"Marine";"Barracks";377;1
"Unit";"Marine";"Barracks";378;1
"Unit";"Marauder";"Barracks";379;2
"Unit";"Marine";"Barracks";381;1
"Unit";"Marine";"Barracks";382;1
"Unit";"Marine";"Barracks";383;1
"Unit";"Marine";"Barracks";384;1
"Unit";"Marine";"Barracks";385;1
"Unit";"Marine";"Barracks";386;1
"Unit";"Marine";"Barracks";387;1
"Unit";"Marine";"Barracks";388;1
"Unit";"Marauder";"Barracks";389;2
"Unit";"Marine";"Barracks";391;1
"Upgrade";"SprayTerran";NA;392;0
"Upgrade";"SprayTerran";NA;392;0
"Upgrade";"SprayTerran";NA;392;0
"Upgrade";"SprayTerran";NA;392;0
"Upgrade";"TerranInfantryArmorsLevel1";NA;392;0
"Upgrade";"ShieldWall";NA;392;0
"Upgrade";"SprayTerran";NA;392;0
"Upgrade";"TerranInfantryArmorsLevel2";NA;392;0
"Upgrade";"SprayTerran";NA;392;0
"Upgrade";"SprayTerran";NA;392;0
"Upgrade";"SprayTerran";NA;392;0
