"type";"unit_name";"on_building";"total_supply_lag"
"Unit";"Overlord";"Larva";13
"Building";"Hatchery";NA;17
"Building";"Extractor";NA;19
"Building";"SpawningPool";NA;19
"Unit";"Overlord";"Larva";22
"Unit";"Queen";"Hatchery";23
"Unit";"Queen";"Hatchery";25
"Unit";"Zergling";"Larva";27
"Unit";"Zergling";"Larva";28
"Unit";"Zergling";"Larva";29
"Unit";"Zergling";"Larva";30
"Building";"Hatchery";NA;35
"Unit";"Queen";"Hatchery";35
"Unit";"Overlord";"Larva";40
"Unit";"Overlord";"Larva";42
"Building";"CreepTumorQueen";NA;50
"Unit";"Queen";"Hatchery";50
"Unit";"Overlord";"Larva";52
"Building";"BanelingNest";NA;54
"Building";"SporeCrawler";NA;55
"Building";"CreepTumorQueen";NA;58
"Building";"CreepTumor";NA;58
"Building";"CreepTumorQueen";NA;58
"Unit";"Overlord";"Larva";60
"Building";"SporeCrawler";NA;66
"Building";"EvolutionChamber";NA;67
"Unit";"Overlord";"Larva";67
"Building";"CreepTumor";NA;71
"Building";"Extractor";NA;72
"Building";"CreepTumorQueen";NA;72
"Building";"CreepTumor";NA;72
"Unit";"Overlord";"Larva";72
"Building";"SporeCrawler";NA;72
"Unit";"Zergling";"Larva";72
"Unit";"Zergling";"Larva";73
"Unit";"Zergling";"Larva";74
"Unit";"Zergling";"Larva";75
"Unit";"Zergling";"Larva";76
"Unit";"Zergling";"Larva";77
"Unit";"Zergling";"Larva";78
"Unit";"Zergling";"Larva";79
"Unit";"Zergling";"Larva";80
"Unit";"Zergling";"Larva";81
"Unit";"Zergling";"Larva";82
"Unit";"Zergling";"Larva";83
"Unit";"Zergling";"Larva";84
"Unit";"Zergling";"Larva";85
"Unit";"Zergling";"Larva";86
"Unit";"Zergling";"Larva";87
"Building";"CreepTumor";NA;93
"Building";"CreepTumor";NA;93
"Building";"CreepTumorQueen";NA;96
"Building";"CreepTumor";NA;96
"Building";"Extractor";NA;103
"Building";"Extractor";NA;109
"Building";"HydraliskDen";NA;109
"Building";"Extractor";NA;109
"Building";"Extractor";NA;109
"Building";"CreepTumor";NA;109
"Unit";"Overlord";"Larva";114
"Building";"Hatchery";NA;114
"Unit";"Queen";"Hatchery";114
"Unit";"Overlord";"Larva";118
"Building";"HydraliskDen";NA;118
"Unit";"Overlord";"Larva";118
"Unit";"Overlord";"Larva";122
"Unit";"Overlord";"Larva";122
"Unit";"Overlord";"Larva";122
"Unit";"Hydralisk";"Larva";122
"Unit";"Hydralisk";"Larva";124
"Unit";"Zergling";"Larva";126
"Unit";"Zergling";"Larva";127
"Unit";"Zergling";"Larva";128
"Unit";"Zergling";"Larva";129
"Unit";"Zergling";"Larva";130
"Unit";"Zergling";"Larva";131
"Building";"CreepTumor";NA;132
"Unit";"Hydralisk";"Larva";132
"Unit";"Hydralisk";"Larva";134
"Unit";"Zergling";"Larva";136
"Unit";"Zergling";"Larva";137
"Unit";"Hydralisk";"Larva";138
"Unit";"Hydralisk";"Larva";140
"Unit";"Hydralisk";"Larva";142
"Building";"CreepTumorQueen";NA;144
"Building";"CreepTumorQueen";NA;144
"Building";"CreepTumor";NA;144
"Building";"CreepTumor";NA;144
"Building";"CreepTumor";NA;144
"Building";"CreepTumorQueen";NA;144
"Unit";"Zergling";"Larva";144
"Unit";"Zergling";"Larva";145
"Unit";"Zergling";"Larva";146
"Unit";"Zergling";"Larva";147
"Unit";"Zergling";"Larva";148
"Unit";"Zergling";"Larva";149
"Unit";"Zergling";"Larva";150
"Unit";"Zergling";"Larva";151
"Unit";"Zergling";"Larva";152
"Unit";"Zergling";"Larva";153
"Unit";"Zergling";"Larva";154
"Unit";"Zergling";"Larva";155
"Unit";"Queen";"Hatchery";156
"Unit";"Zergling";"Larva";159
"Unit";"Zergling";"Larva";160
"Unit";"Zergling";"Larva";161
"Unit";"Zergling";"Larva";162
"Unit";"Zergling";"Larva";163
"Unit";"Zergling";"Larva";164
"Unit";"Zergling";"Larva";165
"Unit";"Zergling";"Larva";166
"Unit";"Zergling";"Larva";167
"Unit";"Zergling";"Larva";168
"Unit";"Zergling";"Larva";169
"Unit";"Zergling";"Larva";170
"Building";"CreepTumor";NA;171
"Unit";"Overlord";"Larva";171
"Unit";"Overlord";"Larva";171
"Building";"Extractor";NA;171
"Building";"SporeCrawler";NA;171
"Building";"CreepTumor";NA;171
"Building";"CreepTumor";NA;171
"Unit";"Zergling";"Larva";171
"Unit";"Zergling";"Larva";172
"Unit";"Zergling";"Larva";173
"Unit";"Zergling";"Larva";174
"Unit";"Zergling";"Larva";178
"Unit";"Zergling";"Larva";179
"Unit";"Zergling";"Larva";180
"Unit";"Zergling";"Larva";181
"Building";"CreepTumor";NA;182
"Building";"CreepTumor";NA;182
"Building";"CreepTumor";NA;182
"Unit";"Zergling";"Larva";182
"Unit";"Zergling";"Larva";183
"Unit";"Zergling";"Larva";184
"Unit";"Zergling";"Larva";185
"Unit";"Zergling";"Larva";186
"Unit";"Zergling";"Larva";187
"Unit";"Zergling";"Larva";188
"Unit";"Zergling";"Larva";189
"Unit";"Queen";"Hatchery";190
"Building";"CreepTumor";NA;192
"Building";"SpineCrawler";NA;194
"Unit";"Hydralisk";"Larva";194
"Building";"SpineCrawler";NA;196
"Unit";"Hydralisk";"Larva";196
"Unit";"Hydralisk";"Larva";198
"Unit";"Zergling";"Larva";200
"Unit";"Zergling";"Larva";201
"Unit";"Zergling";"Larva";202
"Unit";"Zergling";"Larva";203
"Unit";"Zergling";"Larva";204
"Unit";"Zergling";"Larva";205
"Unit";"Baneling";"Zergling";206
"Unit";"Baneling";"Zergling";206
"Unit";"Baneling";"Zergling";206
"Unit";"Baneling";"Zergling";206
"Unit";"Overlord";"Larva";206
"Unit";"Overlord";"Larva";206
"Building";"CreepTumor";NA;206
"Building";"CreepTumor";NA;206
"Building";"CreepTumor";NA;206
"Unit";"Zergling";"Larva";206
"Unit";"Zergling";"Larva";207
"Unit";"Zergling";"Larva";208
"Unit";"Zergling";"Larva";209
"Unit";"Overlord";"Larva";214
"Unit";"Overlord";"Larva";214
"Building";"CreepTumorQueen";NA;220
"Building";"CreepTumorQueen";NA;220
"Building";"CreepTumor";NA;220
"Unit";"Hydralisk";"Larva";220
"Unit";"Hydralisk";"Larva";222
"Building";"CreepTumor";NA;224
"Building";"CreepTumor";NA;224
"Building";"CreepTumor";NA;224
"Unit";"Overlord";"Larva";224
"Unit";"Hydralisk";"Larva";224
"Unit";"Hydralisk";"Larva";226
"Unit";"Overlord";"Larva";228
"Unit";"Hydralisk";"Larva";228
"Unit";"Hydralisk";"Larva";230
"Unit";"Zergling";"Larva";232
"Unit";"Zergling";"Larva";233
"Unit";"Zergling";"Larva";234
"Unit";"Zergling";"Larva";235
"Unit";"Zergling";"Larva";236
"Unit";"Zergling";"Larva";237
"Unit";"Overlord";"Larva";238
"Building";"CreepTumor";NA;238
"Building";"CreepTumor";NA;238
"Unit";"Zergling";"Larva";238
"Unit";"Zergling";"Larva";239
"Unit";"Zergling";"Larva";240
"Unit";"Zergling";"Larva";241
"Unit";"Zergling";"Larva";242
"Unit";"Zergling";"Larva";243
"Unit";"Zergling";"Larva";244
"Unit";"Zergling";"Larva";245
"Unit";"Zergling";"Larva";246
"Unit";"Zergling";"Larva";247
"Unit";"Zergling";"Larva";248
"Unit";"Zergling";"Larva";249
"Unit";"Zergling";"Larva";250
"Unit";"Zergling";"Larva";251
"Unit";"Zergling";"Larva";252
"Unit";"Zergling";"Larva";253
"Unit";"Zergling";"Larva";254
"Unit";"Zergling";"Larva";255
"Unit";"Zergling";"Larva";256
"Unit";"Zergling";"Larva";257
"Unit";"Zergling";"Larva";258
"Unit";"Zergling";"Larva";259
"Unit";"Zergling";"Larva";260
"Unit";"Zergling";"Larva";261
"Unit";"Overlord";"Larva";262
"Building";"CreepTumor";NA;262
"Building";"CreepTumor";NA;262
"Unit";"Overlord";"Larva";262
"Building";"SpineCrawler";NA;262
"Unit";"Zergling";"Larva";262
"Unit";"Zergling";"Larva";263
"Unit";"Zergling";"Larva";264
"Unit";"Zergling";"Larva";265
"Unit";"Zergling";"Larva";266
"Unit";"Zergling";"Larva";267
"Unit";"Zergling";"Larva";268
"Unit";"Zergling";"Larva";269
"Unit";"Zergling";"Larva";270
"Unit";"Zergling";"Larva";271
"Unit";"Zergling";"Larva";272
"Unit";"Zergling";"Larva";273
"Building";"Hatchery";NA;274
"Unit";"Zergling";"Larva";274
"Unit";"Zergling";"Larva";275
"Unit";"Zergling";"Larva";276
"Unit";"Zergling";"Larva";277
"Unit";"Zergling";"Larva";278
"Unit";"Zergling";"Larva";279
"Unit";"Zergling";"Larva";280
"Unit";"Zergling";"Larva";281
"Unit";"Zergling";"Larva";282
"Unit";"Zergling";"Larva";283
"Unit";"Zergling";"Larva";284
"Unit";"Zergling";"Larva";285
"Unit";"Zergling";"Larva";286
"Unit";"Zergling";"Larva";287
"Unit";"Zergling";"Larva";288
"Unit";"Zergling";"Larva";289
"Unit";"Zergling";"Larva";290
"Unit";"Zergling";"Larva";291
"Building";"InfestationPit";NA;292
"Unit";"Baneling";"Zergling";292
"Unit";"Baneling";"Zergling";292
"Unit";"Baneling";"Zergling";292
"Unit";"Baneling";"Zergling";292
"Unit";"Baneling";"Zergling";292
"Unit";"Baneling";"Zergling";292
"Unit";"Baneling";"Zergling";292
"Unit";"Baneling";"Zergling";292
"Unit";"Baneling";"Zergling";292
"Building";"CreepTumor";NA;292
"Building";"CreepTumor";NA;292
"Unit";"Zergling";"Larva";292
"Unit";"Zergling";"Larva";293
"Unit";"Zergling";"Larva";294
"Unit";"Zergling";"Larva";295
"Unit";"Zergling";"Larva";296
"Unit";"Zergling";"Larva";297
"Unit";"Zergling";"Larva";298
"Unit";"Zergling";"Larva";299
"Unit";"Zergling";"Larva";300
"Unit";"Zergling";"Larva";301
"Unit";"Zergling";"Larva";302
"Unit";"Zergling";"Larva";303
"Unit";"Zergling";"Larva";304
"Unit";"Zergling";"Larva";305
"Unit";"Zergling";"Larva";306
"Unit";"Zergling";"Larva";307
"Unit";"Zergling";"Larva";308
"Unit";"Zergling";"Larva";309
"Unit";"Zergling";"Larva";310
"Unit";"Zergling";"Larva";311
"Unit";"Zergling";"Larva";312
"Unit";"Zergling";"Larva";313
"Unit";"Baneling";"Zergling";314
"Unit";"Baneling";"Zergling";314
"Unit";"Baneling";"Zergling";314
"Unit";"Baneling";"Zergling";314
"Unit";"Baneling";"Zergling";314
"Unit";"Baneling";"Zergling";314
"Unit";"Baneling";"Zergling";314
"Unit";"Baneling";"Zergling";314
"Unit";"Baneling";"Zergling";314
"Unit";"Baneling";"Zergling";314
"Unit";"Baneling";"Zergling";314
"Unit";"Baneling";"Zergling";314
"Unit";"Zergling";"Larva";314
"Unit";"Zergling";"Larva";315
"Unit";"Baneling";"Zergling";316
"Unit";"Baneling";"Zergling";316
"Unit";"Baneling";"Zergling";316
"Unit";"Baneling";"Zergling";316
"Unit";"Baneling";"Zergling";316
"Unit";"Baneling";"Zergling";316
"Unit";"Baneling";"Zergling";316
"Unit";"Baneling";"Zergling";316
"Unit";"Baneling";"Zergling";316
"Unit";"Baneling";"Zergling";316
"Unit";"Baneling";"Zergling";316
"Unit";"Baneling";"Zergling";316
"Unit";"Baneling";"Zergling";316
"Unit";"Baneling";"Zergling";316
"Unit";"Baneling";"Zergling";316
"Unit";"Baneling";"Zergling";316
"Unit";"Baneling";"Zergling";316
"Unit";"Baneling";"Zergling";316
"Unit";"Baneling";"Zergling";316
"Unit";"Overlord";"Larva";316
"Unit";"Baneling";"Zergling";316
"Unit";"Baneling";"Zergling";316
"Unit";"Baneling";"Zergling";316
"Unit";"Baneling";"Zergling";316
"Unit";"Baneling";"Zergling";316
"Unit";"Baneling";"Zergling";316
"Unit";"Baneling";"Zergling";316
"Unit";"Zergling";"Larva";316
"Unit";"Zergling";"Larva";317
"Unit";"Zergling";"Larva";318
"Unit";"Zergling";"Larva";319
"Unit";"Zergling";"Larva";320
"Unit";"Zergling";"Larva";321
"Unit";"Zergling";"Larva";322
"Unit";"Zergling";"Larva";323
"Unit";"Zergling";"Larva";324
"Unit";"Zergling";"Larva";325
"Unit";"Zergling";"Larva";326
"Unit";"Zergling";"Larva";327
"Unit";"Zergling";"Larva";328
"Unit";"Zergling";"Larva";329
"Unit";"Zergling";"Larva";330
"Unit";"Zergling";"Larva";331
"Unit";"Zergling";"Larva";332
"Unit";"Zergling";"Larva";333
"Unit";"Baneling";"Zergling";334
"Unit";"Baneling";"Zergling";334
"Unit";"Baneling";"Zergling";334
"Unit";"Baneling";"Zergling";334
"Unit";"Baneling";"Zergling";334
"Unit";"Baneling";"Zergling";334
"Unit";"Baneling";"Zergling";334
"Unit";"Zergling";"Larva";334
"Unit";"Zergling";"Larva";335
"Unit";"Zergling";"Larva";336
"Unit";"Zergling";"Larva";337
"Unit";"Zergling";"Larva";338
"Unit";"Zergling";"Larva";339
"Unit";"Zergling";"Larva";340
"Unit";"Zergling";"Larva";341
"Unit";"Zergling";"Larva";342
"Unit";"Zergling";"Larva";343
"Unit";"Zergling";"Larva";344
"Unit";"Zergling";"Larva";345
"Unit";"Zergling";"Larva";346
"Unit";"Zergling";"Larva";347
"Unit";"Zergling";"Larva";348
"Unit";"Zergling";"Larva";349
"Unit";"Zergling";"Larva";350
"Unit";"Zergling";"Larva";351
"Unit";"Zergling";"Larva";352
"Unit";"Zergling";"Larva";353
"Unit";"Zergling";"Larva";354
"Unit";"Zergling";"Larva";355
"Unit";"Zergling";"Larva";356
"Unit";"Zergling";"Larva";357
"Unit";"Zergling";"Larva";358
"Unit";"Zergling";"Larva";359
"Unit";"Zergling";"Larva";360
"Unit";"Zergling";"Larva";361
"Unit";"Zergling";"Larva";362
"Unit";"Zergling";"Larva";363
"Unit";"Hydralisk";"Larva";364
"Unit";"Hydralisk";"Larva";366
"Unit";"Hydralisk";"Larva";368
"Unit";"Hydralisk";"Larva";370
"Unit";"Hydralisk";"Larva";372
"Unit";"Hydralisk";"Larva";374
"Unit";"Hydralisk";"Larva";376
"Unit";"Hydralisk";"Larva";378
"Unit";"Hydralisk";"Larva";380
"Unit";"Zergling";"Larva";382
"Unit";"Zergling";"Larva";383
"Unit";"Zergling";"Larva";384
"Unit";"Zergling";"Larva";385
"Unit";"Hydralisk";"Larva";386
"Unit";"Hydralisk";"Larva";388
"Unit";"Hydralisk";"Larva";390
"Unit";"Hydralisk";"Larva";392
"Unit";"Hydralisk";"Larva";394
"Unit";"Hydralisk";"Larva";396
"Unit";"Hydralisk";"Larva";398
"Unit";"Zergling";"Larva";400
"Unit";"Zergling";"Larva";401
"Unit";"Hydralisk";"Larva";402
"Unit";"Hydralisk";"Larva";404
"Unit";"Zergling";"Larva";406
"Unit";"Zergling";"Larva";407
"Unit";"Zergling";"Larva";408
"Unit";"Zergling";"Larva";409
"Unit";"Hydralisk";"Larva";410
"Unit";"Hydralisk";"Larva";412
"Unit";"Hydralisk";"Larva";414
"Unit";"Hydralisk";"Larva";416
"Unit";"Zergling";"Larva";418
"Unit";"Zergling";"Larva";419
"Unit";"Zergling";"Larva";420
"Unit";"Zergling";"Larva";421
"Unit";"Hydralisk";"Larva";422
"Unit";"Hydralisk";"Larva";424
"Unit";"Hydralisk";"Larva";426
"Unit";"Zergling";"Larva";428
"Unit";"Zergling";"Larva";429
"Unit";"Zergling";"Larva";430
"Unit";"Zergling";"Larva";431
"Unit";"Zergling";"Larva";432
"Unit";"Zergling";"Larva";433
"Unit";"Zergling";"Larva";434
"Unit";"Zergling";"Larva";435
"Unit";"Zergling";"Larva";436
"Unit";"Zergling";"Larva";437
"Unit";"Zergling";"Larva";438
"Unit";"Zergling";"Larva";439
"Unit";"Zergling";"Larva";440
"Unit";"Zergling";"Larva";441
"Unit";"Zergling";"Larva";442
"Unit";"Zergling";"Larva";443
"Unit";"Viper";"Larva";444
"Building";"CreepTumor";NA;447
"Unit";"Viper";"Larva";447
"Unit";"Zergling";"Larva";450
"Unit";"Zergling";"Larva";451
"Unit";"Zergling";"Larva";452
"Unit";"Zergling";"Larva";453
"Unit";"Zergling";"Larva";454
"Unit";"Zergling";"Larva";455
"Unit";"Zergling";"Larva";456
"Unit";"Zergling";"Larva";457
"Unit";"Zergling";"Larva";458
"Unit";"Zergling";"Larva";459
"Unit";"Zergling";"Larva";460
"Unit";"Zergling";"Larva";461
"Unit";"Zergling";"Larva";462
"Unit";"Zergling";"Larva";463
"Unit";"Zergling";"Larva";464
"Unit";"Zergling";"Larva";465
"Unit";"Zergling";"Larva";466
"Unit";"Zergling";"Larva";467
"Unit";"Zergling";"Larva";468
"Unit";"Zergling";"Larva";469
"Building";"CreepTumor";NA;470
"Building";"CreepTumor";NA;470
"Building";"CreepTumor";NA;470
"Unit";"Baneling";"Zergling";470
"Unit";"Baneling";"Zergling";470
"Unit";"Baneling";"Zergling";470
"Unit";"Baneling";"Zergling";470
"Unit";"Baneling";"Zergling";470
"Unit";"Baneling";"Zergling";470
"Unit";"Baneling";"Zergling";470
"Unit";"Baneling";"Zergling";470
"Unit";"Zergling";"Larva";470
"Unit";"Zergling";"Larva";471
"Unit";"Zergling";"Larva";472
"Unit";"Zergling";"Larva";473
"Unit";"Zergling";"Larva";474
"Unit";"Zergling";"Larva";475
"Unit";"Zergling";"Larva";476
"Unit";"Zergling";"Larva";477
"Unit";"Zergling";"Larva";478
"Unit";"Zergling";"Larva";479
"Unit";"Zergling";"Larva";480
"Unit";"Zergling";"Larva";481
"Unit";"Hydralisk";"Larva";482
"Building";"CreepTumor";NA;484
"Unit";"Zergling";"Larva";484
"Unit";"Zergling";"Larva";485
"Unit";"Zergling";"Larva";486
"Unit";"Zergling";"Larva";487
"Unit";"Zergling";"Larva";488
"Unit";"Zergling";"Larva";489
"Unit";"Zergling";"Larva";490
"Unit";"Zergling";"Larva";491
"Unit";"Zergling";"Larva";492
"Unit";"Zergling";"Larva";493
"Unit";"Zergling";"Larva";494
"Unit";"Zergling";"Larva";495
"Unit";"Zergling";"Larva";496
"Unit";"Zergling";"Larva";497
"Unit";"Zergling";"Larva";498
"Unit";"Zergling";"Larva";499
"Unit";"Zergling";"Larva";500
"Unit";"Zergling";"Larva";501
"Unit";"Zergling";"Larva";502
"Unit";"Zergling";"Larva";503
"Unit";"Zergling";"Larva";504
"Unit";"Zergling";"Larva";505
"Unit";"Baneling";"Zergling";506
"Unit";"Baneling";"Zergling";506
"Unit";"Baneling";"Zergling";506
"Unit";"Baneling";"Zergling";506
"Unit";"Baneling";"Zergling";506
"Unit";"Baneling";"Zergling";506
"Unit";"Baneling";"Zergling";506
"Building";"SpineCrawler";NA;506
"Building";"SporeCrawler";NA;506
"Building";"CreepTumor";NA;506
"Unit";"Zergling";"Larva";506
"Unit";"Zergling";"Larva";507
"Unit";"Zergling";"Larva";508
"Unit";"Zergling";"Larva";509
"Unit";"Zergling";"Larva";510
"Unit";"Zergling";"Larva";511
"Unit";"Zergling";"Larva";512
"Unit";"Zergling";"Larva";513
"Unit";"Zergling";"Larva";514
"Unit";"Zergling";"Larva";515
"Unit";"Zergling";"Larva";516
"Unit";"Zergling";"Larva";517
"Unit";"Zergling";"Larva";518
"Unit";"Zergling";"Larva";519
"Unit";"Hydralisk";"Larva";520
"Unit";"Hydralisk";"Larva";522
"Unit";"Zergling";"Larva";524
"Unit";"Zergling";"Larva";525
"Unit";"Zergling";"Larva";526
"Unit";"Zergling";"Larva";527
"Unit";"Zergling";"Larva";528
"Unit";"Zergling";"Larva";529
"Unit";"Zergling";"Larva";530
"Unit";"Zergling";"Larva";531
"Unit";"Hydralisk";"Larva";532
"Unit";"Hydralisk";"Larva";534
"Unit";"Zergling";"Larva";536
"Unit";"Zergling";"Larva";537
"Unit";"Zergling";"Larva";538
"Unit";"Zergling";"Larva";539
"Unit";"Zergling";"Larva";540
"Unit";"Zergling";"Larva";541
"Unit";"Zergling";"Larva";542
"Unit";"Zergling";"Larva";543
"Unit";"Hydralisk";"Larva";544
"Unit";"Hydralisk";"Larva";546
"Unit";"Zergling";"Larva";548
"Unit";"Zergling";"Larva";549
"Unit";"Zergling";"Larva";550
"Unit";"Zergling";"Larva";551
"Unit";"Zergling";"Larva";552
"Unit";"Zergling";"Larva";553
"Unit";"Zergling";"Larva";554
"Unit";"Zergling";"Larva";555
"Unit";"Zergling";"Larva";556
"Unit";"Zergling";"Larva";557
"Unit";"Zergling";"Larva";558
"Unit";"Zergling";"Larva";559
"Unit";"Zergling";"Larva";560
"Unit";"Zergling";"Larva";561
"Unit";"Zergling";"Larva";562
"Unit";"Zergling";"Larva";563
"Unit";"Zergling";"Larva";564
"Unit";"Zergling";"Larva";565
"Unit";"Zergling";"Larva";566
"Unit";"Zergling";"Larva";567
"Unit";"Zergling";"Larva";568
"Unit";"Zergling";"Larva";569
"Unit";"Baneling";"Zergling";570
"Unit";"Baneling";"Zergling";570
"Unit";"Baneling";"Zergling";570
"Unit";"Baneling";"Zergling";570
"Unit";"Baneling";"Zergling";570
"Unit";"Baneling";"Zergling";570
"Unit";"Baneling";"Zergling";570
"Unit";"Baneling";"Zergling";570
"Unit";"Baneling";"Zergling";570
"Unit";"Baneling";"Zergling";570
"Building";"CreepTumor";NA;570
"Unit";"Zergling";"Larva";570
"Unit";"Zergling";"Larva";571
"Unit";"Zergling";"Larva";572
"Unit";"Zergling";"Larva";573
"Unit";"Zergling";"Larva";574
"Unit";"Zergling";"Larva";575
"Building";"CreepTumor";NA;576
"Building";"CreepTumor";NA;576
"Unit";"Zergling";"Larva";576
"Unit";"Zergling";"Larva";577
"Unit";"Zergling";"Larva";578
"Unit";"Zergling";"Larva";579
"Unit";"Zergling";"Larva";580
"Unit";"Zergling";"Larva";581
"Unit";"Zergling";"Larva";582
"Unit";"Zergling";"Larva";583
"Unit";"Zergling";"Larva";584
"Unit";"Zergling";"Larva";585
"Unit";"Baneling";"Zergling";586
"Unit";"Baneling";"Zergling";586
"Unit";"Zergling";"Larva";586
"Unit";"Zergling";"Larva";587
"Unit";"Zergling";"Larva";588
"Unit";"Zergling";"Larva";589
"Unit";"Baneling";"Zergling";590
"Unit";"Baneling";"Zergling";590
"Unit";"Baneling";"Zergling";590
"Unit";"Baneling";"Zergling";590
"Unit";"Zergling";"Larva";590
"Unit";"Zergling";"Larva";591
"Unit";"Zergling";"Larva";592
"Unit";"Zergling";"Larva";593
"Unit";"Zergling";"Larva";594
"Unit";"Zergling";"Larva";595
"Unit";"Zergling";"Larva";596
"Unit";"Zergling";"Larva";597
"Unit";"Zergling";"Larva";598
"Unit";"Zergling";"Larva";599
"Unit";"Zergling";"Larva";600
"Unit";"Zergling";"Larva";601
"Unit";"Zergling";"Larva";602
"Unit";"Zergling";"Larva";603
"Unit";"Zergling";"Larva";604
"Unit";"Zergling";"Larva";605
"Unit";"Zergling";"Larva";606
"Unit";"Zergling";"Larva";607
"Unit";"Zergling";"Larva";608
"Unit";"Zergling";"Larva";609
"Unit";"Zergling";"Larva";610
"Unit";"Zergling";"Larva";611
"Unit";"Zergling";"Larva";612
"Unit";"Zergling";"Larva";613
"Unit";"Zergling";"Larva";614
"Unit";"Zergling";"Larva";615
"Unit";"Zergling";"Larva";616
"Unit";"Zergling";"Larva";617
"Unit";"Hydralisk";"Larva";618
"Unit";"Hydralisk";"Larva";620
"Unit";"Hydralisk";"Larva";622
"Unit";"Hydralisk";"Larva";624
"Unit";"Zergling";"Larva";626
"Unit";"Zergling";"Larva";627
"Unit";"Zergling";"Larva";628
"Unit";"Zergling";"Larva";629
"Unit";"Zergling";"Larva";630
"Unit";"Zergling";"Larva";631
"Unit";"Zergling";"Larva";632
"Unit";"Zergling";"Larva";633
"Unit";"Hydralisk";"Larva";634
"Unit";"Viper";"Larva";636
"Unit";"Viper";"Larva";639
"Unit";"Hydralisk";"Larva";642
"Unit";"Zergling";"Larva";644
"Unit";"Zergling";"Larva";645
"Unit";"Zergling";"Larva";646
"Unit";"Zergling";"Larva";647
"Unit";"Zergling";"Larva";648
"Unit";"Zergling";"Larva";649
"Unit";"Zergling";"Larva";650
"Unit";"Zergling";"Larva";651
"Unit";"Zergling";"Larva";652
"Unit";"Zergling";"Larva";653
"Unit";"Baneling";"Zergling";654
"Unit";"Baneling";"Zergling";654
"Unit";"Baneling";"Zergling";654
"Unit";"Baneling";"Zergling";654
"Unit";"Baneling";"Zergling";654
"Unit";"Baneling";"Zergling";654
"Unit";"Baneling";"Zergling";654
"Unit";"Baneling";"Zergling";654
"Unit";"Zergling";"Larva";654
"Unit";"Zergling";"Larva";655
"Unit";"Zergling";"Larva";656
"Unit";"Zergling";"Larva";657
"Unit";"Zergling";"Larva";658
"Unit";"Zergling";"Larva";659
"Unit";"Zergling";"Larva";660
"Unit";"Zergling";"Larva";661
"Unit";"Zergling";"Larva";662
"Unit";"Zergling";"Larva";663
"Unit";"Zergling";"Larva";664
"Unit";"Zergling";"Larva";665
"Unit";"Hydralisk";"Larva";666
"Unit";"Hydralisk";"Larva";668
"Unit";"Hydralisk";"Larva";670
"Building";"CreepTumor";NA;672
"Unit";"Zergling";"Larva";672
"Unit";"Zergling";"Larva";673
"Unit";"Zergling";"Larva";674
"Unit";"Zergling";"Larva";675
"Unit";"Zergling";"Larva";676
"Unit";"Zergling";"Larva";677
"Unit";"Zergling";"Larva";678
"Unit";"Zergling";"Larva";679
"Unit";"Baneling";"Zergling";680
"Unit";"Baneling";"Zergling";680
"Unit";"Baneling";"Zergling";680
"Unit";"Baneling";"Zergling";680
"Unit";"Baneling";"Zergling";680
"Unit";"Baneling";"Zergling";680
"Unit";"Baneling";"Zergling";680
"Unit";"Baneling";"Zergling";680
"Unit";"Baneling";"Zergling";680
"Unit";"Baneling";"Zergling";680
"Unit";"Zergling";"Larva";680
"Unit";"Zergling";"Larva";681
"Unit";"Zergling";"Larva";682
"Unit";"Zergling";"Larva";683
"Unit";"Zergling";"Larva";684
"Unit";"Zergling";"Larva";685
"Unit";"Zergling";"Larva";686
"Unit";"Zergling";"Larva";687
"Unit";"Baneling";"Zergling";688
"Unit";"Baneling";"Zergling";688
"Unit";"Baneling";"Zergling";688
"Unit";"Baneling";"Zergling";688
"Building";"CreepTumor";NA;688
"Unit";"Baneling";"Zergling";688
"Unit";"Baneling";"Zergling";688
"Unit";"Baneling";"Zergling";688
"Unit";"Baneling";"Zergling";688
"Unit";"Baneling";"Zergling";688
"Unit";"Zergling";"Larva";688
"Unit";"Zergling";"Larva";689
"Unit";"Zergling";"Larva";690
"Unit";"Zergling";"Larva";691
"Unit";"Zergling";"Larva";692
"Unit";"Zergling";"Larva";693
"Unit";"Hydralisk";"Larva";694
"Unit";"Zergling";"Larva";696
"Unit";"Zergling";"Larva";697
"Unit";"Zergling";"Larva";698
"Unit";"Zergling";"Larva";699
"Unit";"Zergling";"Larva";700
"Unit";"Zergling";"Larva";701
"Unit";"Zergling";"Larva";702
"Unit";"Zergling";"Larva";703
"Unit";"Zergling";"Larva";704
"Unit";"Zergling";"Larva";705
"Unit";"Zergling";"Larva";706
"Unit";"Zergling";"Larva";707
"Unit";"Zergling";"Larva";708
"Unit";"Zergling";"Larva";709
"Unit";"Zergling";"Larva";710
"Unit";"Zergling";"Larva";711
"Unit";"Zergling";"Larva";712
"Unit";"Zergling";"Larva";713
"Unit";"Zergling";"Larva";714
"Unit";"Zergling";"Larva";715
"Unit";"Zergling";"Larva";716
"Unit";"Zergling";"Larva";717
"Unit";"Zergling";"Larva";718
"Unit";"Zergling";"Larva";719
"Unit";"Zergling";"Larva";720
"Unit";"Zergling";"Larva";721
"Unit";"Zergling";"Larva";722
"Unit";"Zergling";"Larva";723
"Unit";"Zergling";"Larva";724
"Unit";"Zergling";"Larva";725
"Unit";"Zergling";"Larva";726
"Unit";"Zergling";"Larva";727
"Unit";"Zergling";"Larva";728
"Unit";"Zergling";"Larva";729
"Unit";"Zergling";"Larva";730
"Unit";"Zergling";"Larva";731
"Upgrade";"SprayZerg";NA;732
"Upgrade";"SprayZerg";NA;732
"Upgrade";"SprayZerg";NA;732
"Upgrade";"SprayZerg";NA;732
"Upgrade";"zerglingmovementspeed";NA;732
"Upgrade";"SprayZerg";NA;732
"Upgrade";"ZergMeleeWeaponsLevel1";NA;732
"Upgrade";"SprayZerg";NA;732
"Upgrade";"CentrificalHooks";NA;732
"Upgrade";"EvolveMuscularAugments";NA;732
"Upgrade";"SprayZerg";NA;732
"Upgrade";"ZergMeleeWeaponsLevel2";NA;732
"Upgrade";"overlordspeed";NA;732
"Upgrade";"SprayZerg";NA;732
"Upgrade";"ZergMissileWeaponsLevel1";NA;732
"Upgrade";"zerglingattackspeed";NA;732
"Upgrade";"ZergMeleeWeaponsLevel3";NA;732
