"type";"unit_name";"on_building";"total_supply_lag";"supply"
"Unit";"Overlord";"Larva";13;0
"Building";"Hatchery";NA;16;0
"Building";"Extractor";NA;19;0
"Building";"SpawningPool";NA;19;0
"Building";"Hatchery";NA;23;0
"Unit";"Zergling";"Larva";24;1
"Unit";"Zergling";"Larva";25;1
"Unit";"Queen";"Hatchery";26;2
"Unit";"Queen";"Hatchery";30;2
"Unit";"Overlord";"Larva";32;0
"Unit";"Zergling";"Larva";33;1
"Unit";"Zergling";"Larva";34;1
"Unit";"Zergling";"Larva";35;1
"Unit";"Zergling";"Larva";36;1
"Unit";"Queen";"Hatchery";40;2
"Unit";"Queen";"Hatchery";47;2
"Building";"CreepTumorQueen";NA;49;0
"Unit";"Overlord";"Larva";49;0
"Building";"RoachWarren";NA;49;0
"Building";"Extractor";NA;57;0
"Building";"Extractor";NA;57;0
"Building";"CreepTumor";NA;57;0
"Unit";"Overlord";"Larva";60;0
"Unit";"Overlord";"Larva";60;0
"Unit";"Overlord";"Larva";60;0
"Building";"CreepTumor";NA;60;0
"Unit";"Roach";"Larva";62;2
"Unit";"Roach";"Larva";64;2
"Unit";"Roach";"Larva";66;2
"Unit";"Roach";"Larva";68;2
"Unit";"Roach";"Larva";70;2
"Building";"CreepTumorQueen";NA;72;0
"Unit";"Roach";"Larva";72;2
"Unit";"Roach";"Larva";74;2
"Unit";"Roach";"Larva";79;2
"Unit";"Overlord";"Larva";83;0
"Unit";"Overlord";"Larva";84;0
"Upgrade";"GlialReconstitution";"RoachWarren";84;0
"Unit";"Overlord";"Larva";84;0
"Building";"CreepTumor";NA;84;0
"Unit";"Overlord";"Larva";84;0
"Unit";"Overlord";"Larva";84;0
"Building";"EvolutionChamber";NA;84;0
"Building";"CreepTumorQueen";NA;84;0
"Unit";"Overlord";"Larva";84;0
"Building";"CreepTumorQueen";NA;84;0
"Unit";"Roach";"Larva";92;2
"Unit";"Roach";"Larva";94;2
"Building";"Extractor";NA;96;0
"Unit";"Overlord";"Larva";96;0
"Building";"CreepTumor";NA;96;0
"Unit";"Roach";"Larva";96;2
"Unit";"Roach";"Larva";98;2
"Building";"Extractor";NA;104;0
"Building";"CreepTumor";NA;104;0
"Building";"CreepTumor";NA;104;0
"Building";"Extractor";NA;104;0
"Building";"CreepTumor";NA;104;0
"Building";"CreepTumorQueen";NA;107;0
"Unit";"Overlord";"Larva";107;0
"Unit";"Roach";"Larva";107;2
"Unit";"Roach";"Larva";109;2
"Unit";"Roach";"Larva";111;2
"Unit";"Roach";"Larva";113;2
"Unit";"Overlord";"Larva";115;0
"Building";"InfestationPit";NA;121;0
"Building";"CreepTumor";NA;123;0
"Building";"CreepTumor";NA;123;0
"Unit";"Overlord";"Larva";123;0
"Unit";"Roach";"Larva";123;2
"Unit";"Roach";"Larva";125;2
"Unit";"Roach";"Larva";127;2
"Building";"Hatchery";NA;129;0
"Building";"CreepTumorQueen";NA;129;0
"Unit";"Overlord";"Larva";131;0
"Building";"HydraliskDen";NA;132;0
"Building";"CreepTumor";NA;132;0
"Building";"CreepTumor";NA;132;0
"Building";"CreepTumorQueen";NA;132;0
"Building";"CreepTumor";NA;132;0
"Building";"SporeCrawler";NA;132;0
"Unit";"Overlord";"Larva";132;0
"Building";"CreepTumor";NA;132;0
"Unit";"Hydralisk";"Larva";132;2
"Unit";"Hydralisk";"Larva";134;2
"Unit";"Hydralisk";"Larva";136;2
"Unit";"Hydralisk";"Larva";138;2
"Unit";"Hydralisk";"Larva";140;2
"Unit";"Hydralisk";"Larva";142;2
"Building";"CreepTumor";NA;144;0
"Building";"CreepTumor";NA;144;0
"Building";"CreepTumor";NA;144;0
"Unit";"Hydralisk";"Larva";144;2
"Unit";"Hydralisk";"Larva";146;2
"Unit";"Hydralisk";"Larva";148;2
"Unit";"Overlord";"Larva";150;0
"Unit";"Hydralisk";"Larva";150;2
"Unit";"Hydralisk";"Larva";152;2
"Building";"CreepTumor";NA;161;0
"Unit";"Hydralisk";"Larva";161;2
"Unit";"Hydralisk";"Larva";163;2
"Unit";"Hydralisk";"Larva";165;2
"Unit";"Hydralisk";"Larva";167;2
"Unit";"Hydralisk";"Larva";169;2
"Unit";"Hydralisk";"Larva";171;2
"Unit";"Hydralisk";"Larva";173;2
"Unit";"Hydralisk";"Larva";175;2
"Unit";"Hydralisk";"Larva";177;2
"Unit";"Hydralisk";"Larva";179;2
"Unit";"Hydralisk";"Larva";181;2
"Unit";"Hydralisk";"Larva";183;2
"Unit";"Hydralisk";"Larva";185;2
"Unit";"Zergling";"Larva";187;1
"Unit";"Zergling";"Larva";188;1
"Unit";"Zergling";"Larva";189;1
"Unit";"Zergling";"Larva";190;1
"Unit";"Zergling";"Larva";191;1
"Unit";"Zergling";"Larva";192;1
"Unit";"Zergling";"Larva";193;1
"Unit";"Zergling";"Larva";194;1
"Unit";"Zergling";"Larva";195;1
"Unit";"Zergling";"Larva";196;1
"Unit";"Zergling";"Larva";197;1
"Unit";"Zergling";"Larva";198;1
"Unit";"Zergling";"Larva";199;1
"Unit";"Zergling";"Larva";200;1
"Unit";"Zergling";"Larva";201;1
"Unit";"Zergling";"Larva";202;1
"Unit";"Zergling";"Larva";203;1
"Unit";"Zergling";"Larva";204;1
"Unit";"Hydralisk";"Larva";205;2
"Unit";"Hydralisk";"Larva";207;2
"Unit";"Hydralisk";"Larva";209;2
"Unit";"Hydralisk";"Larva";211;2
"Unit";"Hydralisk";"Larva";213;2
"Unit";"Hydralisk";"Larva";215;2
"Unit";"Hydralisk";"Larva";217;2
"Unit";"Hydralisk";"Larva";219;2
"Building";"CreepTumor";NA;221;0
"Unit";"Hydralisk";"Larva";221;2
"Unit";"Hydralisk";"Larva";223;2
"Unit";"Hydralisk";"Larva";225;2
"Unit";"Hydralisk";"Larva";227;2
"Unit";"Hydralisk";"Larva";229;2
"Unit";"Zergling";"Larva";231;1
"Unit";"Zergling";"Larva";232;1
"Unit";"Zergling";"Larva";233;1
"Unit";"Zergling";"Larva";234;1
"Unit";"Zergling";"Larva";235;1
"Unit";"Zergling";"Larva";236;1
"Unit";"Zergling";"Larva";237;1
"Unit";"Zergling";"Larva";238;1
"Unit";"Zergling";"Larva";239;1
"Unit";"Zergling";"Larva";240;1
"Unit";"Zergling";"Larva";241;1
"Unit";"Zergling";"Larva";242;1
"Unit";"Hydralisk";"Larva";243;2
"Unit";"Hydralisk";"Larva";245;2
"Unit";"Hydralisk";"Larva";247;2
"Unit";"Hydralisk";"Larva";249;2
"Unit";"Hydralisk";"Larva";251;2
"Unit";"Hydralisk";"Larva";253;2
"Unit";"Hydralisk";"Larva";255;2
"Unit";"Roach";"Larva";257;2
"Unit";"Roach";"Larva";259;2
"Unit";"Roach";"Larva";261;2
"Unit";"Roach";"Larva";263;2
"Unit";"Roach";"Larva";265;2
"Unit";"Roach";"Larva";267;2
"Unit";"Hydralisk";"Larva";273;2
"Unit";"Hydralisk";"Larva";275;2
"Unit";"Hydralisk";"Larva";277;2
"Building";"SporeCrawler";NA;279;0
"Unit";"Roach";"Larva";279;2
"Building";"SpineCrawler";NA;281;0
"Unit";"Zergling";"Larva";281;1
"Unit";"Zergling";"Larva";282;1
"Unit";"Zergling";"Larva";283;1
"Unit";"Zergling";"Larva";284;1
"Unit";"Zergling";"Larva";285;1
"Unit";"Zergling";"Larva";286;1
"Unit";"Zergling";"Larva";287;1
"Unit";"Zergling";"Larva";288;1
"Unit";"Zergling";"Larva";289;1
"Unit";"Zergling";"Larva";290;1
"Unit";"Zergling";"Larva";291;1
"Unit";"Zergling";"Larva";292;1
"Unit";"Zergling";"Larva";293;1
"Unit";"Zergling";"Larva";294;1
"Unit";"Zergling";"Larva";295;1
"Unit";"Zergling";"Larva";296;1
"Building";"SpineCrawler";NA;297;0
"Building";"CreepTumor";NA;297;0
"Building";"CreepTumor";NA;297;0
"Unit";"Hydralisk";"Larva";297;2
"Unit";"Hydralisk";"Larva";299;2
"Unit";"Hydralisk";"Larva";301;2
"Unit";"Hydralisk";"Larva";303;2
"Building";"CreepTumor";NA;305;0
"Unit";"Roach";"Larva";305;2
"Unit";"Roach";"Larva";307;2
"Unit";"Roach";"Larva";309;2
"Unit";"Roach";"Larva";311;2
"Unit";"Hydralisk";"Larva";313;2
"Unit";"Hydralisk";"Larva";315;2
"Unit";"Hydralisk";"Larva";317;2
"Unit";"Zergling";"Larva";319;1
"Unit";"Zergling";"Larva";320;1
"Unit";"Zergling";"Larva";321;1
"Unit";"Zergling";"Larva";322;1
"Unit";"Zergling";"Larva";323;1
"Unit";"Zergling";"Larva";324;1
"Unit";"Zergling";"Larva";325;1
"Unit";"Zergling";"Larva";326;1
"Unit";"Zergling";"Larva";327;1
"Unit";"Zergling";"Larva";328;1
"Unit";"Zergling";"Larva";329;1
"Unit";"Zergling";"Larva";330;1
"Unit";"Zergling";"Larva";331;1
"Unit";"Zergling";"Larva";332;1
"Unit";"Zergling";"Larva";333;1
"Unit";"Zergling";"Larva";334;1
"Unit";"Zergling";"Larva";335;1
"Unit";"Zergling";"Larva";336;1
"Unit";"Zergling";"Larva";337;1
"Unit";"Zergling";"Larva";338;1
"Unit";"Zergling";"Larva";339;1
"Unit";"Zergling";"Larva";340;1
"Unit";"Hydralisk";"Larva";341;2
"Unit";"Hydralisk";"Larva";343;2
"Unit";"Hydralisk";"Larva";345;2
"Unit";"Hydralisk";"Larva";347;2
"Unit";"Hydralisk";"Larva";349;2
"Unit";"Hydralisk";"Larva";351;2
"Unit";"Zergling";"Larva";353;1
"Unit";"Zergling";"Larva";354;1
"Unit";"Zergling";"Larva";355;1
"Unit";"Zergling";"Larva";356;1
"Unit";"Zergling";"Larva";357;1
"Unit";"Zergling";"Larva";358;1
"Unit";"Zergling";"Larva";359;1
"Unit";"Zergling";"Larva";360;1
"Unit";"Hydralisk";"Larva";361;2
"Unit";"Hydralisk";"Larva";363;2
"Unit";"Queen";"Hatchery";365;2
"Building";"CreepTumor";NA;367;0
"Building";"CreepTumor";NA;367;0
"Unit";"Roach";"Larva";367;2
"Unit";"Roach";"Larva";369;2
"Unit";"Roach";"Larva";371;2
"Unit";"Roach";"Larva";373;2
"Unit";"Roach";"Larva";375;2
"Unit";"Roach";"Larva";377;2
"Building";"Extractor";NA;379;0
"Building";"CreepTumorQueen";NA;379;0
"Unit";"Hydralisk";"Larva";379;2
"Building";"CreepTumorQueen";NA;381;0
"Unit";"Hydralisk";"Larva";381;2
"Unit";"Zergling";"Larva";383;1
"Unit";"Zergling";"Larva";384;1
"Unit";"Zergling";"Larva";385;1
"Unit";"Zergling";"Larva";386;1
"Unit";"Zergling";"Larva";387;1
"Unit";"Zergling";"Larva";388;1
"Unit";"Zergling";"Larva";389;1
"Unit";"Zergling";"Larva";390;1
"Unit";"Zergling";"Larva";391;1
"Unit";"Zergling";"Larva";392;1
"Unit";"Zergling";"Larva";393;1
"Unit";"Zergling";"Larva";394;1
"Building";"CreepTumor";NA;395;0
"Building";"CreepTumor";NA;395;0
"Unit";"Hydralisk";"Larva";395;2
"Unit";"Hydralisk";"Larva";397;2
"Unit";"Hydralisk";"Larva";399;2
"Unit";"Hydralisk";"Larva";401;2
"Unit";"Hydralisk";"Larva";403;2
"Unit";"Hydralisk";"Larva";405;2
"Unit";"Hydralisk";"Larva";407;2
"Unit";"Hydralisk";"Larva";409;2
"Unit";"Zergling";"Larva";411;1
"Unit";"Zergling";"Larva";412;1
"Unit";"Zergling";"Larva";413;1
"Unit";"Zergling";"Larva";414;1
"Unit";"Zergling";"Larva";415;1
"Unit";"Zergling";"Larva";416;1
"Unit";"Zergling";"Larva";417;1
"Unit";"Zergling";"Larva";418;1
"Unit";"Zergling";"Larva";419;1
"Unit";"Zergling";"Larva";420;1
"Unit";"Zergling";"Larva";421;1
"Unit";"Zergling";"Larva";422;1
"Unit";"Zergling";"Larva";423;1
"Unit";"Zergling";"Larva";424;1
"Unit";"Zergling";"Larva";425;1
"Unit";"Zergling";"Larva";426;1
"Building";"BanelingNest";NA;427;0
"Unit";"Hydralisk";"Larva";427;2
"Unit";"Overlord";"Larva";429;0
"Unit";"Hydralisk";"Larva";429;2
"Unit";"Hydralisk";"Larva";431;2
"Unit";"Hydralisk";"Larva";433;2
"Unit";"Overlord";"Larva";435;0
"Unit";"Overlord";"Larva";435;0
"Unit";"Overlord";"Larva";435;0
"Unit";"Hydralisk";"Larva";435;2
"Unit";"Hydralisk";"Larva";437;2
"Unit";"Hydralisk";"Larva";439;2
"Unit";"Hydralisk";"Larva";441;2
"Unit";"Hydralisk";"Larva";443;2
"Unit";"Hydralisk";"Larva";445;2
"Unit";"Hydralisk";"Larva";447;2
"Unit";"Hydralisk";"Larva";449;2
"Unit";"Hydralisk";"Larva";451;2
"Unit";"Hydralisk";"Larva";453;2
"Unit";"Hydralisk";"Larva";455;2
"Unit";"Hydralisk";"Larva";457;2
"Unit";"Zergling";"Larva";459;1
"Unit";"Zergling";"Larva";460;1
"Unit";"Zergling";"Larva";461;1
"Unit";"Zergling";"Larva";462;1
"Unit";"Zergling";"Larva";463;1
"Unit";"Zergling";"Larva";464;1
"Unit";"Zergling";"Larva";465;1
"Unit";"Zergling";"Larva";466;1
"Unit";"Zergling";"Larva";467;1
"Unit";"Zergling";"Larva";468;1
"Unit";"Zergling";"Larva";469;1
"Unit";"Zergling";"Larva";470;1
"Unit";"Roach";"Larva";471;2
"Unit";"Roach";"Larva";473;2
"Unit";"Roach";"Larva";475;2
"Unit";"Roach";"Larva";477;2
"Unit";"Hydralisk";"Larva";479;2
"Unit";"Hydralisk";"Larva";481;2
"Unit";"Zergling";"Larva";483;1
"Unit";"Zergling";"Larva";484;1
"Unit";"Zergling";"Larva";485;1
"Unit";"Zergling";"Larva";486;1
"Unit";"Zergling";"Larva";487;1
"Unit";"Zergling";"Larva";488;1
"Unit";"Hydralisk";"Larva";489;2
"Unit";"Hydralisk";"Larva";491;2
"Unit";"Hydralisk";"Larva";493;2
"Unit";"Hydralisk";"Larva";495;2
"Unit";"Hydralisk";"Larva";497;2
"Unit";"Hydralisk";"Larva";499;2
"Unit";"Hydralisk";"Larva";501;2
"Unit";"Hydralisk";"Larva";503;2
"Unit";"Hydralisk";"Larva";505;2
"Unit";"Zergling";"Larva";507;1
"Unit";"Zergling";"Larva";508;1
"Unit";"Zergling";"Larva";509;1
"Unit";"Zergling";"Larva";510;1
"Unit";"Zergling";"Larva";511;1
"Unit";"Zergling";"Larva";512;1
"Unit";"Roach";"Larva";513;2
"Unit";"Roach";"Larva";515;2
"Unit";"Roach";"Larva";517;2
"Unit";"Roach";"Larva";519;2
"Unit";"Hydralisk";"Larva";521;2
"Unit";"Hydralisk";"Larva";523;2
"Unit";"Hydralisk";"Larva";525;2
"Unit";"Hydralisk";"Larva";527;2
"Unit";"Hydralisk";"Larva";529;2
"Upgrade";"SprayZerg";NA;531;0
"Upgrade";"SprayZerg";NA;531;0
"Upgrade";"SprayZerg";NA;531;0
"Upgrade";"SprayZerg";NA;531;0
"Upgrade";"SprayZerg";NA;531;0
"Upgrade";"overlordspeed";NA;531;0
"Upgrade";"ZergMissileWeaponsLevel1";NA;531;0
"Upgrade";"SprayZerg";NA;531;0
"Upgrade";"zerglingmovementspeed";NA;531;0
"Upgrade";"EvolveMuscularAugments";NA;531;0
"Upgrade";"ZergMissileWeaponsLevel2";NA;531;0
"Upgrade";"ZergMeleeWeaponsLevel1";NA;531;0
"Upgrade";"SprayZerg";NA;531;0
