"type";"unit_name";"on_building";"total_supply";"supply"
"Building";"Pylon";NA;12;0
"Building";"Assimilator";NA;15;0
"Building";"Gateway";NA;14;0
"Building";"CyberneticsCore";NA;19;0
"Building";"Pylon";NA;21;0
"Building";"Assimilator";NA;21;0
"Unit";"Adept";"Gateway";21;2
"Building";"Nexus";NA;20;0
"Building";"TwilightCouncil";NA;24;0
"Unit";"Adept";"Gateway";27;2
"Building";"Gateway";NA;25;0
"Building";"ShieldBattery";NA;30;0
"Building";"Pylon";NA;36;0
"Building";"RoboticsFacility";NA;31;0
"Building";"Pylon";NA;39;0
"Unit";"Adept";"Gateway";42;2
"Unit";"Adept";"Gateway";42;2
"Building";"Pylon";NA;41;0
"Unit";"Immortal";"Robotics Facility";39;4
"Building";"ShieldBattery";NA;41;0
"Unit";"Stalker";"Gateway";51;2
"Unit";"Stalker";"Gateway";51;2
"Building";"Assimilator";NA;55;0
"Building";"Assimilator";NA;55;0
"Unit";"Adept";"Gateway";57;2
"Unit";"Adept";"Gateway";57;2
"Building";"Gateway";NA;51;0
"Building";"Gateway";NA;51;0
"Unit";"Observer";"Robotics Facility";55;1
"Building";"Gateway";NA;51;0
"Building";"Gateway";NA;51;0
"Building";"Pylon";NA;66;0
"Building";"Pylon";NA;68;0
"Unit";"Adept";"Gateway";69;2
"Unit";"Adept";"Gateway";69;2
"Unit";"Adept";"Gateway";69;2
"Unit";"Adept";"Gateway";69;2
"Unit";"Adept";"Gateway";69;2
"Unit";"Adept";"Gateway";69;2
"Building";"Pylon";NA;68;0
"Unit";"Stalker";"Gateway";81;2
"Unit";"Stalker";"Gateway";81;2
"Unit";"Adept";"Gateway";81;2
"Unit";"Adept";"Gateway";81;2
"Unit";"Immortal";"Robotics Facility";81;4
"Upgrade";"Charge";"TwilightCouncil";69;0
"Unit";"Adept";"Gateway";97;2
"Unit";"Adept";"Gateway";97;2
"Unit";"Adept";"Gateway";97;2
"Building";"Pylon";NA;97;0
"Unit";"Adept";"Gateway";103;2
"Unit";"Adept";"Gateway";103;2
"Unit";"Adept";"Gateway";103;2
"Building";"TemplarArchive";NA;97;0
"Unit";"Zealot";"Gateway";109;2
"Unit";"Zealot";"Gateway";109;2
"Unit";"Zealot";"Gateway";109;2
"Unit";"Zealot";"Gateway";109;2
"Unit";"Zealot";"Gateway";109;2
"Unit";"Zealot";"Gateway";109;2
"Building";"Nexus";NA;95;0
"Building";"HighTemplar";NA;121;0
"Building";"HighTemplar";NA;121;0
"Building";"HighTemplar";NA;121;0
"Building";"HighTemplar";NA;121;0
"Building";"HighTemplar";NA;123;0
"Building";"HighTemplar";NA;123;0
"Unit";"Archon";"High Templar";123;0
"Unit";"Archon";"High Templar";123;0
"Unit";"Immortal";"Robotics Facility";121;4
"Unit";"Zealot";"Gateway";127;2
"Unit";"Zealot";"Gateway";127;2
"Unit";"Zealot";"Gateway";127;2
"Unit";"Zealot";"Gateway";129;2
"Unit";"Zealot";"Gateway";129;2
"Unit";"Zealot";"Gateway";129;2
"Unit";"Stalker";"Gateway";141;2
"Unit";"Zealot";"Gateway";145;2
"Unit";"Zealot";"Gateway";145;2
"Unit";"Zealot";"Gateway";145;2
"Unit";"Zealot";"Gateway";145;2
"Building";"HighTemplar";NA;161;0
"Building";"Forge";NA;159;0
"Building";"Forge";NA;159;0
"Building";"Pylon";NA;161;0
"Building";"Assimilator";NA;161;0
"Building";"Pylon";NA;161;0
"Building";"Pylon";NA;161;0
"Building";"Pylon";NA;161;0
"Building";"Pylon";NA;161;0
"Building";"Pylon";NA;161;0
"Unit";"Stalker";"Gateway";163;2
"Unit";"Stalker";"Gateway";163;2
"Unit";"Stalker";"Gateway";163;2
"Unit";"Stalker";"Gateway";163;2
"Unit";"Stalker";"Gateway";163;2
"Unit";"Zealot";"Gateway";173;2
"Unit";"Zealot";"Gateway";173;2
"Unit";"Zealot";"Gateway";173;2
"Unit";"Zealot";"Gateway";173;2
"Unit";"Zealot";"Gateway";181;2
"Unit";"Zealot";"Gateway";181;2
"Unit";"Zealot";"Gateway";181;2
"Unit";"Zealot";"Gateway";181;2
"Unit";"Zealot";"Gateway";181;2
"Unit";"Zealot";"Gateway";181;2
"Building";"Assimilator";NA;193;0
"Unit";"Zealot";"Gateway";197;2
"Unit";"Zealot";"Gateway";197;2
"Unit";"Zealot";"Gateway";197;2
"Unit";"Zealot";"Gateway";197;2
"Unit";"Zealot";"Gateway";197;2
"Unit";"Zealot";"Gateway";197;2
"Building";"Pylon";NA;196;0
"Unit";"Immortal";"Robotics Facility";193;4
"Unit";"Zealot";"Gateway";213;2
"Unit";"Zealot";"Gateway";213;2
"Unit";"Zealot";"Gateway";213;2
"Unit";"Zealot";"Gateway";213;2
"Unit";"Zealot";"Gateway";213;2
"Unit";"Zealot";"Gateway";213;2
"Building";"Nexus";NA;193;0
"Unit";"Immortal";"Robotics Facility";213;4
"Unit";"Zealot";"Gateway";225;2
"Unit";"Zealot";"Gateway";225;2
"Unit";"Zealot";"Gateway";225;2
"Unit";"Zealot";"Gateway";225;2
"Unit";"Zealot";"Gateway";225;2
"Unit";"Zealot";"Gateway";225;2
"Upgrade";"ProtossGroundWeaponsLevel1";"Forge";197;0
"Upgrade";"ProtossGroundArmorsLevel1";"Forge";197;0
"Building";"Pylon";NA;241;0
"Building";"RoboticsFacility";NA;225;0
"Building";"RoboticsFacility";NA;225;0
"Unit";"Stalker";"Gateway";241;2
"Unit";"Stalker";"Gateway";241;2
"Unit";"Stalker";"Gateway";241;2
"Unit";"Stalker";"Gateway";241;2
"Unit";"Stalker";"Gateway";241;2
"Unit";"Stalker";"Gateway";241;2
"Building";"RoboticsBay";NA;241;0
"Unit";"Immortal";"Robotics Facility";241;4
"Unit";"Zealot";"Gateway";253;2
"Unit";"Zealot";"Gateway";253;2
"Unit";"Zealot";"Gateway";253;2
"Unit";"Zealot";"Gateway";253;2
"Unit";"Zealot";"Gateway";253;2
"Unit";"Zealot";"Gateway";253;2
"Building";"Gateway";NA;241;0
"Building";"Gateway";NA;241;0
"Building";"ShieldBattery";NA;253;0
"Building";"Gateway";NA;241;0
"Building";"HighTemplar";NA;269;0
"Building";"HighTemplar";NA;269;0
"Building";"HighTemplar";NA;269;0
"Building";"HighTemplar";NA;269;0
"Unit";"Zealot";"Gateway";269;2
"Unit";"Zealot";"Gateway";269;2
"Unit";"Archon";"High Templar";273;0
"Unit";"Archon";"High Templar";273;0
"Unit";"Zealot";"Gateway";273;2
"Unit";"Zealot";"Gateway";273;2
"Unit";"Zealot";"Gateway";273;2
"Unit";"Zealot";"Gateway";273;2
"Unit";"Zealot";"Gateway";273;2
"Building";"ShieldBattery";NA;273;0
"Unit";"Colossus";"Robotics Facility";273;6
"Unit";"Colossus";"Robotics Facility";273;6
"Unit";"Colossus";"Robotics Facility";273;6
"Building";"HighTemplar";NA;287;0
"Building";"HighTemplar";NA;287;0
"Building";"HighTemplar";NA;287;0
"Building";"HighTemplar";NA;287;0
