"type";"unit_name";"on_building";"total_supply";"supply"
"Building";"Pylon";NA;13;0
"Building";"Assimilator";NA;15;0
"Building";"Gateway";NA;15;0
"Building";"CyberneticsCore";NA;20;0
"Building";"Assimilator";NA;21;0
"Building";"Pylon";NA;21;0
"Unit";"Stalker";"Gateway";22;2
"Building";"Nexus";NA;19;0
"Unit";"Stalker";"Gateway";24;2
"Building";"TwilightCouncil";NA;24;0
"Unit";"Stalker";"Gateway";31;2
"Building";"Pylon";NA;40;0
"Building";"Gateway";NA;34;0
"Building";"Gateway";NA;36;0
"Building";"Assimilator";NA;42;0
"Unit";"Stalker";"Gateway";46;2
"Unit";"Stalker";"Gateway";46;2
"Unit";"Stalker";"Gateway";46;2
"Building";"Pylon";NA;44;0
"Building";"RoboticsFacility";NA;42;0
"Building";"Pylon";NA;54;0
"Unit";"Stalker";"Gateway";56;2
"Unit";"Stalker";"Gateway";56;2
"Unit";"Stalker";"Gateway";56;2
"Unit";"Observer";"Robotics Facility";62;1
"Building";"Pylon";NA;64;0
"Building";"Pylon";NA;66;0
"Unit";"Observer";"Robotics Facility";67;1
"Unit";"Stalker";"Gateway";69;2
"Unit";"Stalker";"Gateway";69;2
"Unit";"Stalker";"Gateway";70;2
"Building";"Forge";NA;67;0
"Building";"Forge";NA;67;0
"Unit";"Sentry";"Gateway";81;2
"Unit";"Sentry";"Gateway";81;2
"Building";"Nexus";NA;66;0
"Unit";"Stalker";"Gateway";85;2
"Upgrade";"Charge";"TwilightCouncil";67;0
"Unit";"Stalker";"Gateway";89;2
"Unit";"Stalker";"Gateway";89;2
"Unit";"Stalker";"Gateway";89;2
"Unit";"Observer";"Robotics Facility";88;1
"Building";"Gateway";NA;81;0
"Building";"Gateway";NA;81;0
"Building";"Gateway";NA;85;0
"Unit";"Zealot";"Gateway";100;2
"Unit";"Zealot";"Gateway";100;2
"Unit";"Zealot";"Gateway";100;2
"Unit";"Zealot";"Gateway";100;2
"Building";"Gateway";NA;88;0
"Building";"Gateway";NA;88;0
"Unit";"Zealot";"Gateway";109;2
"Unit";"Immortal";"Robotics Facility";97;4
"Unit";"Zealot";"Gateway";115;2
"Upgrade";"ProtossGroundWeaponsLevel1";"Forge";81;0
"Upgrade";"ProtossGroundArmorsLevel1";"Forge";81;0
"Unit";"Zealot";"Gateway";117;2
"Unit";"Zealot";"Gateway";117;2
"Unit";"Zealot";"Gateway";117;2
"Unit";"Zealot";"Gateway";117;2
"Unit";"Zealot";"Gateway";125;2
"Building";"Pylon";NA;117;0
"Unit";"Zealot";"Gateway";127;2
"Unit";"Zealot";"Gateway";127;2
"Unit";"Zealot";"Gateway";127;2
"Building";"Pylon";NA;117;0
"Building";"Pylon";NA;117;0
"Building";"Pylon";NA;117;0
"Unit";"Zealot";"Gateway";133;2
"Unit";"Zealot";"Gateway";133;2
"Unit";"Zealot";"Gateway";133;2
"Unit";"Zealot";"Gateway";133;2
"Unit";"Zealot";"Gateway";139;2
"Unit";"Zealot";"Gateway";139;2
"Unit";"Zealot";"Gateway";139;2
"Unit";"Zealot";"Gateway";149;2
"Unit";"Zealot";"Gateway";149;2
"Unit";"Zealot";"Gateway";149;2
"Unit";"Zealot";"Gateway";149;2
"Unit";"Zealot";"Gateway";149;2
"Unit";"Zealot";"Gateway";159;2
"Unit";"Zealot";"Gateway";159;2
"Unit";"Zealot";"Gateway";159;2
"Unit";"Sentry";"Gateway";170;2
"Unit";"Sentry";"Gateway";170;2
"Building";"Assimilator";NA;167;0
"Building";"Assimilator";NA;167;0
"Building";"Assimilator";NA;167;0
"Building";"TemplarArchive";NA;165;0
"Unit";"Stalker";"Gateway";178;2
"Unit";"Stalker";"Gateway";178;2
"Unit";"Stalker";"Gateway";180;2
"Unit";"Zealot";"Gateway";187;2
"Unit";"Zealot";"Gateway";187;2
"Unit";"Zealot";"Gateway";193;2
"Unit";"Zealot";"Gateway";193;2
"Unit";"Zealot";"Gateway";193;2
"Unit";"Zealot";"Gateway";193;2
"Unit";"Stalker";"Gateway";201;2
"Unit";"Stalker";"Gateway";201;2
"Unit";"Stalker";"Gateway";201;2
"Unit";"Zealot";"Gateway";209;2
"Unit";"Zealot";"Gateway";209;2
"Unit";"Zealot";"Gateway";209;2
"Unit";"Zealot";"Gateway";209;2
"Unit";"Zealot";"Gateway";209;2
"Unit";"Zealot";"Gateway";209;2
"Unit";"Zealot";"Gateway";209;2
"Building";"Pylon";NA;207;0
"Upgrade";"ProtossGroundWeaponsLevel2";"Forge";167;0
"Upgrade";"ProtossGroundArmorsLevel2";"Forge";167;0
"Unit";"Zealot";"Gateway";223;2
"Unit";"Zealot";"Gateway";223;2
"Unit";"Zealot";"Gateway";227;2
"Unit";"Zealot";"Gateway";227;2
"Unit";"Zealot";"Gateway";227;2
"Unit";"Zealot";"Gateway";227;2
"Unit";"Zealot";"Gateway";227;2
"Unit";"Zealot";"Gateway";227;2
"Building";"HighTemplar";NA;239;0
"Building";"HighTemplar";NA;239;0
"Building";"HighTemplar";NA;239;0
"Building";"HighTemplar";NA;239;0
"Building";"HighTemplar";NA;239;0
"Building";"HighTemplar";NA;239;0
"Building";"HighTemplar";NA;239;0
"Building";"HighTemplar";NA;239;0
"Unit";"Archon";"High Templar";239;0
"Building";"Pylon";NA;239;0
"Unit";"Stalker";"Gateway";239;2
"Unit";"Stalker";"Gateway";239;2
"Unit";"Stalker";"Gateway";239;2
"Unit";"Stalker";"Gateway";239;2
"Unit";"Stalker";"Gateway";239;2
"Unit";"Stalker";"Gateway";247;2
"Unit";"Observer";"Robotics Facility";239;1
"Building";"Gateway";NA;239;0
"Building";"Gateway";NA;239;0
"Building";"HighTemplar";NA;252;0
"Building";"HighTemplar";NA;252;0
"Building";"HighTemplar";NA;252;0
"Building";"HighTemplar";NA;252;0
"Building";"HighTemplar";NA;252;0
"Building";"HighTemplar";NA;252;0
"Unit";"Zealot";"Gateway";252;2
"Unit";"Zealot";"Gateway";252;2
"Unit";"Archon";"High Templar";252;0
"Unit";"Archon";"High Templar";252;0
"Unit";"Archon";"High Templar";252;0
"Unit";"Zealot";"Gateway";256;2
"Unit";"Zealot";"Gateway";256;2
"Building";"Nexus";NA;239;0
"Building";"Pylon";NA;260;0
"Building";"Pylon";NA;260;0
"Upgrade";"ProtossGroundArmorsLevel3";"Forge";239;0
"Upgrade";"ProtossGroundWeaponsLevel3";"Forge";239;0
"Unit";"Immortal";"Robotics Facility";252;4
"Building";"Pylon";NA;260;0
"Building";"Pylon";NA;260;0
"Building";"Pylon";NA;260;0
"Unit";"Zealot";"Gateway";264;2
"Unit";"Zealot";"Gateway";264;2
"Unit";"Zealot";"Gateway";264;2
"Unit";"Zealot";"Gateway";264;2
"Unit";"Zealot";"Gateway";264;2
"Unit";"Zealot";"Gateway";264;2
"Unit";"Zealot";"Gateway";264;2
