"type";"unit_name";"on_building";"total_supply";"supply"
"Building";"Pylon";NA;13;0
"Building";"Assimilator";NA;15;0
"Building";"Pylon";NA;17;0
"Building";"Gateway";NA;14;0
"Unit";"Zealot";"Gateway";19;2
"Building";"CyberneticsCore";NA;18;0
"Building";"Gateway";NA;18;0
"Unit";"Stalker";"Gateway";20;2
"Unit";"Stalker";"Gateway";22;2
"Building";"Assimilator";NA;23;0
"Building";"Pylon";NA;28;0
