"type";"unit_name";"on_building";"total_supply";"supply"
"Building";"Pylon";NA;13;0
"Building";"Assimilator";NA;16;0
"Building";"Gateway";NA;15;0
"Building";"Assimilator";NA;20;0
"Building";"Pylon";NA;21;0
"Building";"CyberneticsCore";NA;20;0
"Building";"Nexus";NA;19;0
"Unit";"Stalker";"Gateway";22;2
"Unit";"Stalker";"Gateway";31;2
"Building";"Pylon";NA;36;0
"Unit";"Stalker";"Gateway";36;2
"Unit";"Stalker";"Gateway";51;2
"Building";"Gateway";NA;41;0
"Building";"Gateway";NA;41;0
"Building";"Pylon";NA;53;0
"Building";"Assimilator";NA;53;0
"Building";"TwilightCouncil";NA;49;0
"Unit";"Stalker";"Gateway";57;2
"Unit";"Stalker";"Gateway";57;2
"Building";"Pylon";NA;55;0
"Unit";"Stalker";"Gateway";61;2
"Unit";"Stalker";"Gateway";67;2
"Unit";"Stalker";"Gateway";67;2
"Building";"Nexus";NA;49;0
"Building";"Pylon";NA;65;0
"Building";"Pylon";NA;67;0
"Unit";"Stalker";"Gateway";74;2
"Unit";"Stalker";"Gateway";78;2
"Unit";"Stalker";"Gateway";78;2
"Building";"Forge";NA;73;0
"Building";"Forge";NA;73;0
"Unit";"Sentry";"Gateway";86;2
"Unit";"Sentry";"Gateway";86;2
"Unit";"Sentry";"Gateway";86;2
"Building";"Pylon";NA;85;0
"Building";"RoboticsFacility";NA;83;0
"Unit";"Zealot";"Gateway";92;2
"Unit";"Zealot";"Gateway";92;2
"Unit";"Zealot";"Gateway";92;2
"Building";"ShieldBattery";NA;92;0
"Building";"Pylon";NA;92;0
"Unit";"Observer";"Robotics Facility";92;1
"Building";"Pylon";NA;92;0
"Building";"Pylon";NA;98;0
"Unit";"Zealot";"Gateway";99;2
"Unit";"Zealot";"Gateway";99;2
"Unit";"Zealot";"Gateway";99;2
"Building";"Gateway";NA;92;0
"Building";"Gateway";NA;92;0
"Building";"Pylon";NA;98;0
"Building";"Gateway";NA;92;0
"Building";"Gateway";NA;92;0
"Building";"Gateway";NA;92;0
"Building";"Pylon";NA;105;0
"Unit";"Stalker";"Gateway";108;2
"Unit";"Stalker";"Gateway";108;2
"Unit";"Stalker";"Gateway";108;2
"Building";"Pylon";NA;105;0
"Building";"Assimilator";NA;105;0
"Building";"Assimilator";NA;105;0
"Building";"Assimilator";NA;105;0
"Unit";"Zealot";"Gateway";117;2
"Unit";"Zealot";"Gateway";117;2
"Unit";"Zealot";"Gateway";117;2
"Unit";"Zealot";"Gateway";117;2
"Unit";"Zealot";"Gateway";127;2
"Upgrade";"ProtossGroundWeaponsLevel1";"Forge";92;0
"Upgrade";"ProtossGroundArmorsLevel1";"Forge";92;0
"Upgrade";"Charge";"TwilightCouncil";98;0
"Unit";"Zealot";"Gateway";132;2
"Unit";"Zealot";"Gateway";132;2
"Unit";"Zealot";"Gateway";132;2
"Building";"Pylon";NA;130;0
"Unit";"Zealot";"Gateway";138;2
"Unit";"Zealot";"Gateway";138;2
"Unit";"Zealot";"Gateway";138;2
"Unit";"Immortal";"Robotics Facility";115;4
"Building";"RoboticsBay";NA;115;0
"Building";"Nexus";NA;105;0
"Building";"RoboticsFacility";NA;116;0
"Unit";"Zealot";"Gateway";148;2
"Unit";"Zealot";"Gateway";148;2
"Unit";"Zealot";"Gateway";148;2
"Unit";"Zealot";"Gateway";148;2
"Unit";"Zealot";"Gateway";148;2
"Unit";"Zealot";"Gateway";162;2
"Unit";"Zealot";"Gateway";162;2
"Unit";"Zealot";"Gateway";162;2
"Unit";"Zealot";"Gateway";162;2
"Unit";"Zealot";"Gateway";162;2
"Unit";"Zealot";"Gateway";173;2
"Unit";"Colossus";"Robotics Facility";148;6
"Unit";"Colossus";"Robotics Facility";148;6
"Unit";"Zealot";"Gateway";189;2
"Unit";"Zealot";"Gateway";189;2
"Unit";"Stalker";"Gateway";193;2
"Unit";"Stalker";"Gateway";193;2
"Unit";"Stalker";"Gateway";193;2
"Unit";"Stalker";"Gateway";193;2
"Unit";"Stalker";"Gateway";193;2
"Unit";"Stalker";"Gateway";193;2
"Unit";"Stalker";"Gateway";193;2
"Unit";"Stalker";"Gateway";193;2
"Upgrade";"ProtossGroundWeaponsLevel2";"Forge";144;0
"Upgrade";"ProtossGroundArmorsLevel2";"Forge";144;0
"Unit";"Colossus";"Robotics Facility";162;6
"Unit";"Colossus";"Robotics Facility";162;6
"Building";"DarkShrine";NA;158;0
"Building";"Assimilator";NA;209;0
"Upgrade";"ExtendedThermalLance";"RoboticsBay";162;0
"Building";"Assimilator";NA;209;0
"Building";"Pylon";NA;221;0
"Unit";"Observer";"Robotics Facility";221;1
"Building";"TemplarArchive";NA;209;0
"Building";"Pylon";NA;221;0
"Building";"Pylon";NA;221;0
"Building";"Pylon";NA;221;0
"Unit";"Phoenix";"Stargate";221;2
"Unit";"Immortal";"Robotics Facility";221;4
"Building";"Pylon";NA;222;0
"Building";"PhotonCannon";NA;222;0
"Building";"PhotonCannon";NA;222;0
"Building";"ShieldBattery";NA;222;0
"Building";"Nexus";NA;221;0
"Unit";"Immortal";"Robotics Facility";222;4
"Building";"Stargate";NA;222;0
"Unit";"Immortal";"Robotics Facility";228;4
"Unit";"Zealot";"Gateway";237;2
"Unit";"Zealot";"Gateway";237;2
"Unit";"Zealot";"Gateway";237;2
"Unit";"Zealot";"Gateway";237;2
"Building";"Gateway";NA;233;0
"Building";"Gateway";NA;233;0
"Upgrade";"ProtossGroundWeaponsLevel3";"Forge";221;0
"Building";"Gateway";NA;233;0
"Building";"Gateway";NA;233;0
"Building";"Gateway";NA;237;0
"Building";"Gateway";NA;237;0
"Building";"Gateway";NA;237;0
"Building";"Gateway";NA;237;0
"Upgrade";"ProtossGroundArmorsLevel3";"Forge";221;0
"Building";"HighTemplar";NA;246;0
"Building";"HighTemplar";NA;246;0
"Upgrade";"ProtossAirWeaponsLevel1";"CyberneticsCore";229;0
"Unit";"Zealot";"Gateway";246;2
"Unit";"Zealot";"Gateway";246;2
"Unit";"Zealot";"Gateway";246;2
"Building";"Pylon";NA;246;0
"Unit";"Zealot";"Gateway";246;2
"Unit";"Zealot";"Gateway";246;2
"Unit";"Zealot";"Gateway";246;2
"Unit";"Zealot";"Gateway";246;2
"Unit";"Zealot";"Gateway";246;2
"Unit";"Zealot";"Gateway";246;2
"Unit";"Zealot";"Gateway";246;2
"Unit";"Zealot";"Gateway";246;2
"Unit";"Zealot";"Gateway";246;2
"Unit";"Zealot";"Gateway";246;2
"Unit";"Zealot";"Gateway";246;2
"Building";"FleetBeacon";NA;246;0
"Unit";"Archon";"High Templar";274;0
"Upgrade";"ProtossShieldsLevel1";"Forge";246;0
"Building";"Gateway";NA;246;0
"Building";"Gateway";NA;246;0
"Building";"Gateway";NA;246;0
"Building";"Gateway";NA;246;0
"Unit";"Zealot";"Gateway";274;2
"Unit";"Zealot";"Gateway";274;2
"Unit";"Zealot";"Gateway";274;2
"Unit";"Zealot";"Gateway";274;2
"Unit";"Zealot";"Gateway";274;2
"Unit";"Zealot";"Gateway";274;2
"Unit";"Zealot";"Gateway";274;2
"Unit";"Zealot";"Gateway";274;2
"Building";"Gateway";NA;246;0
"Unit";"Zealot";"Gateway";274;2
"Unit";"Zealot";"Gateway";274;2
"Unit";"Zealot";"Gateway";274;2
"Unit";"Zealot";"Gateway";274;2
"Unit";"Zealot";"Gateway";274;2
"Unit";"Zealot";"Gateway";274;2
"Unit";"Zealot";"Gateway";274;2
"Building";"Gateway";NA;246;0
"Building";"Gateway";NA;246;0
"Unit";"Zealot";"Gateway";304;2
