"type";"unit_name";"on_building";"total_supply";"supply"
"Building";"Pylon";NA;13;0
"Building";"Assimilator";NA;16;0
"Building";"Pylon";NA;17;0
"Building";"Gateway";NA;15;0
"Building";"CyberneticsCore";NA;19;0
"Building";"Gateway";NA;19;0
"Unit";"Stalker";"Gateway";20;2
"Unit";"Stalker";"Gateway";20;2
"Unit";"Stalker";"Gateway";22;2
"Building";"Assimilator";NA;24;0
"Unit";"Stalker";"Gateway";24;2
"Building";"Pylon";NA;25;0
