"type";"unit_name";"on_building";"total_supply";"supply"
"Building";"Pylon";NA;13;0
"Building";"Assimilator";NA;15;0
"Building";"Gateway";NA;15;0
"Building";"Assimilator";NA;20;0
"Building";"CyberneticsCore";NA;20;0
"Building";"Pylon";NA;21;0
"Building";"Nexus";NA;19;0
"Unit";"Stalker";"Gateway";23;2
"Unit";"Stalker";"Gateway";28;2
"Building";"Pylon";NA;36;0
"Building";"Gateway";NA;31;0
"Building";"Gateway";NA;31;0
"Unit";"Stalker";"Gateway";34;2
"Building";"Pylon";NA;47;0
"Building";"TwilightCouncil";NA;44;0
"Building";"Assimilator";NA;47;0
"Unit";"Stalker";"Gateway";50;2
"Unit";"Stalker";"Gateway";51;2
"Unit";"Stalker";"Gateway";51;2
"Building";"ShieldBattery";NA;47;0
"Building";"Nexus";NA;42;0
"Unit";"Stalker";"Gateway";62;2
"Unit";"Stalker";"Gateway";62;2
"Unit";"Stalker";"Gateway";62;2
"Building";"Pylon";NA;61;0
"Building";"Pylon";NA;62;0
"Unit";"Stalker";"Gateway";74;2
"Unit";"Stalker";"Gateway";74;2
"Unit";"Stalker";"Gateway";74;2
"Building";"Pylon";NA;71;0
"Building";"Forge";NA;72;0
"Building";"Pylon";NA;81;0
"Building";"Forge";NA;74;0
"Unit";"Stalker";"Gateway";83;2
"Unit";"Stalker";"Gateway";83;2
"Unit";"Stalker";"Gateway";83;2
"Building";"RoboticsFacility";NA;81;0
"Building";"Pylon";NA;83;0
"Building";"Pylon";NA;89;0
"Building";"Gateway";NA;83;0
"Unit";"Sentry";"Gateway";94;2
"Building";"Gateway";NA;83;0
"Unit";"Sentry";"Gateway";94;2
"Unit";"Sentry";"Gateway";94;2
"Building";"Gateway";NA;83;0
"Building";"Gateway";NA;83;0
"Building";"Gateway";NA;83;0
"Building";"Pylon";NA;92;0
"Unit";"Zealot";"Gateway";100;2
"Unit";"Zealot";"Gateway";100;2
"Unit";"Zealot";"Gateway";100;2
"Unit";"Immortal";"Robotics Facility";89;4
"Building";"ShieldBattery";NA;92;0
"Building";"ShieldBattery";NA;94;0
"Unit";"Zealot";"Gateway";110;2
"Unit";"Zealot";"Gateway";110;2
"Unit";"Zealot";"Gateway";110;2
"Unit";"Zealot";"Gateway";110;2
"Unit";"Zealot";"Gateway";110;2
"Unit";"Zealot";"Gateway";118;2
"Unit";"Zealot";"Gateway";120;2
"Building";"Pylon";NA;110;0
"Building";"Pylon";NA;110;0
"Upgrade";"Charge";"TwilightCouncil";83;0
"Upgrade";"ProtossGroundWeaponsLevel1";"Forge";83;0
"Unit";"Zealot";"Gateway";124;2
"Upgrade";"ProtossGroundArmorsLevel1";"Forge";83;0
"Building";"Pylon";NA;120;0
"Unit";"Immortal";"Robotics Facility";100;4
"Unit";"Zealot";"Gateway";126;2
"Unit";"Zealot";"Gateway";126;2
"Unit";"Zealot";"Gateway";126;2
"Unit";"Zealot";"Gateway";126;2
"Unit";"Zealot";"Gateway";126;2
"Unit";"Zealot";"Gateway";140;2
"Unit";"Zealot";"Gateway";140;2
"Unit";"Zealot";"Gateway";140;2
"Unit";"Zealot";"Gateway";146;2
"Unit";"Zealot";"Gateway";146;2
"Unit";"Zealot";"Gateway";146;2
"Unit";"Zealot";"Gateway";146;2
"Unit";"Zealot";"Gateway";146;2
"Building";"Assimilator";NA;156;0
"Building";"Pylon";NA;156;0
"Building";"Pylon";NA;156;0
"Building";"Assimilator";NA;156;0
"Building";"Assimilator";NA;156;0
"Building";"Nexus";NA;126;0
"Unit";"Zealot";"Gateway";158;2
"Unit";"Zealot";"Gateway";158;2
"Unit";"Zealot";"Gateway";158;2
"Unit";"Zealot";"Gateway";158;2
"Unit";"Zealot";"Gateway";158;2
"Unit";"Zealot";"Gateway";158;2
"Unit";"Zealot";"Gateway";160;2
"Building";"Pylon";NA;158;0
"Unit";"Zealot";"Gateway";174;2
"Building";"Pylon";NA;158;0
"Unit";"Immortal";"Robotics Facility";158;4
"Upgrade";"ProtossGroundWeaponsLevel2";"Forge";140;0
"Unit";"Zealot";"Gateway";180;2
"Unit";"Zealot";"Gateway";180;2
"Unit";"Zealot";"Gateway";180;2
"Unit";"Zealot";"Gateway";180;2
"Unit";"Zealot";"Gateway";180;2
"Unit";"Zealot";"Gateway";180;2
"Building";"RoboticsBay";NA;176;0
"Upgrade";"ProtossGroundArmorsLevel2";"Forge";156;0
"Unit";"Zealot";"Gateway";192;2
"Unit";"Zealot";"Gateway";192;2
"Unit";"Zealot";"Gateway";194;2
"Unit";"Zealot";"Gateway";195;2
"Unit";"Zealot";"Gateway";195;2
"Unit";"Zealot";"Gateway";195;2
"Unit";"Zealot";"Gateway";195;2
"Unit";"Zealot";"Gateway";195;2
"Unit";"Immortal";"Robotics Facility";180;4
"Unit";"Zealot";"Gateway";216;2
"Unit";"Zealot";"Gateway";216;2
"Unit";"Zealot";"Gateway";216;2
"Unit";"Zealot";"Gateway";216;2
"Unit";"Zealot";"Gateway";216;2
"Unit";"Zealot";"Gateway";216;2
"Unit";"Zealot";"Gateway";216;2
"Unit";"Zealot";"Gateway";216;2
"Building";"RoboticsFacility";NA;192;0
"Unit";"Zealot";"Gateway";234;2
"Unit";"Zealot";"Gateway";234;2
"Unit";"Zealot";"Gateway";234;2
"Unit";"Zealot";"Gateway";234;2
"Unit";"Zealot";"Gateway";234;2
"Unit";"Zealot";"Gateway";234;2
"Unit";"Zealot";"Gateway";234;2
"Unit";"Zealot";"Gateway";234;2
"Unit";"Colossus";"Robotics Facility";204;6
"Unit";"Zealot";"Gateway";256;2
"Unit";"Zealot";"Gateway";256;2
"Unit";"Zealot";"Gateway";256;2
"Unit";"Zealot";"Gateway";256;2
"Unit";"Sentry";"Gateway";268;2
"Unit";"Zealot";"Gateway";274;2
"Unit";"Colossus";"Robotics Facility";236;6
"Unit";"Zealot";"Gateway";274;2
"Unit";"Zealot";"Gateway";274;2
"Unit";"Zealot";"Gateway";274;2
"Upgrade";"ProtossGroundWeaponsLevel3";"Forge";208;0
"Unit";"Colossus";"Robotics Facility";256;6
"Building";"TemplarArchive";NA;271;0
"Upgrade";"ExtendedThermalLance";"RoboticsBay";250;0
"Unit";"Zealot";"Gateway";294;2
"Unit";"Zealot";"Gateway";294;2
"Unit";"Zealot";"Gateway";294;2
"Unit";"Zealot";"Gateway";294;2
"Unit";"Zealot";"Gateway";294;2
"Unit";"Zealot";"Gateway";294;2
"Unit";"Zealot";"Gateway";294;2
"Unit";"Zealot";"Gateway";294;2
"Building";"Assimilator";NA;288;0
"Building";"Pylon";NA;294;0
"Building";"Assimilator";NA;288;0
"Unit";"Colossus";"Robotics Facility";271;6
"Building";"ShieldBattery";NA;294;0
"Upgrade";"ProtossGroundArmorsLevel3";"Forge";234;0
"Building";"HighTemplar";NA;316;0
"Building";"HighTemplar";NA;316;0
"Building";"HighTemplar";NA;316;0
"Building";"HighTemplar";NA;316;0
"Building";"HighTemplar";NA;316;0
"Building";"HighTemplar";NA;316;0
"Unit";"Colossus";"Robotics Facility";288;6
"Unit";"Zealot";"Gateway";316;2
"Unit";"Zealot";"Gateway";316;2
"Unit";"Archon";"High Templar";326;0
"Unit";"Archon";"High Templar";326;0
"Unit";"Colossus";"Robotics Facility";316;6
"Unit";"Immortal";"Robotics Facility";316;4
"Unit";"Zealot";"Gateway";336;2
"Unit";"Zealot";"Gateway";336;2
"Unit";"Zealot";"Gateway";336;2
"Building";"Pylon";NA;336;0
"Unit";"Zealot";"Gateway";342;2
"Unit";"Zealot";"Gateway";342;2
"Unit";"Zealot";"Gateway";342;2
"Unit";"Zealot";"Gateway";342;2
"Building";"Pylon";NA;336;0
"Upgrade";"ProtossShieldsLevel1";"Forge";316;0
"Building";"Gateway";NA;326;0
"Unit";"Immortal";"Robotics Facility";326;4
"Building";"Gateway";NA;326;0
"Building";"Gateway";NA;326;0
"Building";"Gateway";NA;326;0
"Unit";"Archon";"High Templar";350;0
"Building";"Gateway";NA;326;0
"Unit";"Stalker";"Gateway";354;2
"Unit";"Stalker";"Gateway";354;2
"Unit";"Stalker";"Gateway";354;2
"Unit";"Stalker";"Gateway";354;2
"Building";"HighTemplar";NA;354;0
"Building";"HighTemplar";NA;354;0
"Building";"HighTemplar";NA;354;0
"Building";"HighTemplar";NA;354;0
"Building";"Gateway";NA;332;0
"Building";"Stargate";NA;332;0
"Unit";"Archon";"High Templar";362;0
"Unit";"Archon";"High Templar";362;0
"Unit";"Zealot";"Gateway";362;2
"Unit";"Zealot";"Gateway";362;2
"Unit";"Zealot";"Gateway";362;2
"Unit";"Zealot";"Gateway";362;2
"Unit";"Zealot";"Gateway";362;2
"Unit";"Zealot";"Gateway";362;2
"Unit";"Zealot";"Gateway";362;2
"Unit";"Zealot";"Gateway";362;2
"Building";"Nexus";NA;332;0
"Unit";"Zealot";"Gateway";378;2
"Unit";"Zealot";"Gateway";378;2
"Unit";"Zealot";"Gateway";378;2
"Unit";"Zealot";"Gateway";378;2
"Unit";"Zealot";"Gateway";386;2
"Unit";"Zealot";"Gateway";386;2
"Unit";"Zealot";"Gateway";386;2
"Unit";"Zealot";"Gateway";386;2
"Unit";"Colossus";"Robotics Facility";362;6
"Unit";"Zealot";"Gateway";394;2
"Unit";"Zealot";"Gateway";394;2
"Unit";"Zealot";"Gateway";394;2
"Unit";"Zealot";"Gateway";394;2
"Unit";"Zealot";"Gateway";394;2
"Building";"HighTemplar";NA;410;0
"Building";"HighTemplar";NA;410;0
"Building";"HighTemplar";NA;410;0
"Building";"HighTemplar";NA;410;0
"Building";"HighTemplar";NA;410;0
"Building";"HighTemplar";NA;410;0
"Building";"HighTemplar";NA;410;0
"Building";"HighTemplar";NA;410;0
"Unit";"Archon";"High Templar";411;0
"Unit";"Archon";"High Templar";411;0
"Unit";"Archon";"High Templar";411;0
