"type";"unit_name";"on_building";"total_supply";"supply"
"Building";"Pylon";NA;14;0
"Building";"Assimilator";NA;15;0
"Building";"Assimilator";NA;16;0
"Building";"Gateway";NA;15;0
"Building";"Assimilator";NA;17;0
"Building";"Pylon";NA;20;0
"Building";"CyberneticsCore";NA;19;0
"Unit";"Adept";"Gateway";22;2
"Building";"RoboticsFacility";NA;23;0
"Unit";"Adept";"Gateway";26;2
"Building";"Pylon";NA;26;0
"Unit";"Observer";"Robotics Facility";26;1
"Building";"Stargate";NA;26;0
"Unit";"Immortal";"Robotics Facility";29;4
"Unit";"Phoenix";"Stargate";30;2
"Building";"Pylon";NA;30;0
"Unit";"Phoenix";"Stargate";37;2
"Unit";"Observer";"Robotics Facility";37;1
"Building";"Nexus";NA;30;0
"Unit";"Observer";"Robotics Facility";38;1
"Building";"ShieldBattery";NA;41;0
"Unit";"Phoenix";"Stargate";42;2
"Building";"Pylon";NA;43;0
"Unit";"Immortal";"Robotics Facility";46;4
"Unit";"Phoenix";"Stargate";53;2
"Building";"Assimilator";NA;54;0
"Building";"Assimilator";NA;54;0
"Building";"Pylon";NA;64;0
"Building";"RoboticsFacility";NA;60;0
"Building";"Forge";NA;64;0
"Building";"RoboticsBay";NA;66;0
"Building";"Pylon";NA;68;0
"Building";"Pylon";NA;70;0
"Building";"PhotonCannon";NA;70;0
"Building";"PhotonCannon";NA;70;0
"Building";"ShieldBattery";NA;70;0
"Unit";"Disruptor";"Robotics Facility";68;3
"Unit";"Disruptor";"Robotics Facility";68;3
"Unit";"Disruptor";"Robotics Facility";70;3
"Unit";"Disruptor";"Robotics Facility";70;3
"Building";"Pylon";NA;78;0
"Building";"PhotonCannon";NA;78;0
"Building";"ShieldBattery";NA;78;0
"Building";"Nexus";NA;70;0
"Building";"PhotonCannon";NA;78;0
"Building";"ShieldBattery";NA;78;0
"Building";"ShieldBattery";NA;78;0
"Unit";"Observer";"Robotics Facility";84;1
"Unit";"Phoenix";"Stargate";84;2
"Unit";"Observer";"Robotics Facility";84;1
"Unit";"Phoenix";"Stargate";86;2
"Building";"Assimilator";NA;90;0
"Building";"Assimilator";NA;92;0
"Building";"FleetBeacon";NA;90;0
"Building";"Stargate";NA;90;0
"Building";"PhotonCannon";NA;92;0
"Building";"PhotonCannon";NA;95;0
"Building";"PhotonCannon";NA;95;0
"Building";"Pylon";NA;97;0
"Building";"Pylon";NA;97;0
"Upgrade";"ProtossGroundWeaponsLevel1";"Forge";86;0
"Unit";"Colossus";"Robotics Facility";95;6
"Unit";"Colossus";"Robotics Facility";95;6
"Unit";"Phoenix";"Stargate";100;2
"Unit";"Phoenix";"Stargate";100;2
"Unit";"Phoenix";"Stargate";116;2
"Unit";"Phoenix";"Stargate";116;2
"Unit";"Disruptor";"Robotics Facility";116;3
"Unit";"Disruptor";"Robotics Facility";116;3
"Building";"Pylon";NA;120;0
"Building";"Pylon";NA;120;0
"Building";"Pylon";NA;120;0
"Building";"Pylon";NA;120;0
"Building";"Stargate";NA;116;0
"Building";"Pylon";NA;126;0
"Building";"TwilightCouncil";NA;120;0
"Building";"Stargate";NA;120;0
"Building";"Assimilator";NA;126;0
"Building";"Assimilator";NA;126;0
"Unit";"Observer";"Robotics Facility";126;1
"Unit";"Observer";"Robotics Facility";126;1
"Unit";"Phoenix";"Stargate";126;2
"Unit";"Phoenix";"Stargate";126;2
"Unit";"Observer";"Robotics Facility";131;1
"Building";"PhotonCannon";NA;129;0
"Building";"PhotonCannon";NA;129;0
"Building";"PhotonCannon";NA;130;0
"Building";"PhotonCannon";NA;131;0
"Building";"ShieldBattery";NA;131;0
"Building";"Nexus";NA;120;0
"Building";"ShieldBattery";NA;135;0
"Building";"ShieldBattery";NA;135;0
"Unit";"Phoenix";"Stargate";135;2
"Unit";"Phoenix";"Stargate";135;2
"Building";"Gateway";NA;129;0
"Building";"Gateway";NA;130;0
"Building";"Gateway";NA;131;0
"Building";"Gateway";NA;131;0
"Building";"Gateway";NA;131;0
"Building";"Gateway";NA;135;0
"Unit";"Colossus";"Robotics Facility";130;6
"Upgrade";"ProtossAirWeaponsLevel1";"CyberneticsCore";126;0
"Unit";"Phoenix";"Stargate";141;2
"Unit";"Phoenix";"Stargate";141;2
"Unit";"Phoenix";"Stargate";141;2
"Unit";"Phoenix";"Stargate";149;2
"Building";"Pylon";NA;155;0
"Building";"Pylon";NA;155;0
"Building";"Pylon";NA;155;0
"Upgrade";"ProtossGroundWeaponsLevel2";"Forge";135;0
"Unit";"Phoenix";"Stargate";155;2
"Building";"Assimilator";NA;155;0
"Unit";"Phoenix";"Stargate";155;2
"Unit";"Phoenix";"Stargate";155;2
"Building";"Assimilator";NA;155;0
"Unit";"Stalker";"Gateway";163;2
"Unit";"Stalker";"Gateway";163;2
"Unit";"Stalker";"Gateway";163;2
"Unit";"Stalker";"Gateway";163;2
"Unit";"Stalker";"Gateway";163;2
"Unit";"Stalker";"Gateway";163;2
"Unit";"Stalker";"Gateway";163;2
"Building";"Pylon";NA;157;0
"Building";"Pylon";NA;157;0
"Building";"CyberneticsCore";NA;155;0
"Building";"TemplarArchive";NA;163;0
"Building";"Nexus";NA;155;0
"Building";"HighTemplar";NA;177;0
"Building";"HighTemplar";NA;177;0
"Building";"HighTemplar";NA;177;0
"Building";"HighTemplar";NA;177;0
"Building";"HighTemplar";NA;177;0
"Building";"PhotonCannon";NA;177;0
"Building";"PhotonCannon";NA;177;0
"Upgrade";"ProtossAirWeaponsLevel2";"CyberneticsCore";149;0
"Building";"HighTemplar";NA;177;0
"Building";"PhotonCannon";NA;177;0
"Unit";"Observer";"Robotics Facility";177;1
"Unit";"Observer";"Robotics Facility";177;1
"Unit";"Archon";"High Templar";177;0
"Unit";"Archon";"High Templar";177;0
"Building";"ShieldBattery";NA;177;0
"Building";"ShieldBattery";NA;177;0
"Unit";"Archon";"High Templar";178;0
"Unit";"Stalker";"Gateway";179;2
"Unit";"Stalker";"Gateway";179;2
"Unit";"Stalker";"Gateway";179;2
"Unit";"Stalker";"Gateway";179;2
"Unit";"Stalker";"Gateway";179;2
"Unit";"Stalker";"Gateway";179;2
"Unit";"Stalker";"Gateway";191;2
"Unit";"Stalker";"Gateway";191;2
"Unit";"Stalker";"Gateway";191;2
"Unit";"Stalker";"Gateway";191;2
"Unit";"Stalker";"Gateway";191;2
"Upgrade";"ProtossGroundWeaponsLevel3";"Forge";177;0
"Upgrade";"ProtossAirArmorsLevel1";"CyberneticsCore";179;0
"Unit";"Zealot";"Gateway";201;2
"Unit";"Zealot";"Gateway";201;2
"Unit";"Zealot";"Gateway";201;2
"Unit";"Zealot";"Gateway";201;2
"Unit";"Zealot";"Gateway";201;2
"Unit";"Zealot";"Gateway";201;2
"Unit";"Zealot";"Gateway";201;2
"Unit";"Phoenix";"Stargate";215;2
"Upgrade";"ProtossAirWeaponsLevel3";"CyberneticsCore";191;0
"Unit";"Phoenix";"Stargate";215;2
"Unit";"Phoenix";"Stargate";215;2
"Unit";"Phoenix";"Stargate";215;2
"Unit";"Zealot";"Gateway";223;2
"Unit";"Zealot";"Gateway";223;2
"Unit";"Zealot";"Gateway";223;2
"Unit";"Zealot";"Gateway";223;2
"Unit";"Zealot";"Gateway";223;2
"Unit";"Zealot";"Gateway";223;2
"Unit";"Zealot";"Gateway";223;2
"Unit";"Phoenix";"Stargate";215;2
"Unit";"Phoenix";"Stargate";217;2
"Unit";"Phoenix";"Stargate";219;2
"Unit";"Phoenix";"Stargate";219;2
"Unit";"Stalker";"Gateway";245;2
"Unit";"Stalker";"Gateway";245;2
"Unit";"Stalker";"Gateway";245;2
"Unit";"Stalker";"Gateway";245;2
"Unit";"Stalker";"Gateway";245;2
"Unit";"Stalker";"Gateway";245;2
"Unit";"Phoenix";"Stargate";245;2
"Unit";"Phoenix";"Stargate";245;2
"Unit";"Phoenix";"Stargate";245;2
"Unit";"Phoenix";"Stargate";245;2
"Building";"HighTemplar";NA;265;0
"Building";"HighTemplar";NA;265;0
"Building";"HighTemplar";NA;265;0
"Building";"HighTemplar";NA;265;0
"Building";"HighTemplar";NA;265;0
"Building";"HighTemplar";NA;265;0
"Building";"HighTemplar";NA;265;0
"Unit";"Archon";"High Templar";265;0
"Unit";"Archon";"High Templar";265;0
"Unit";"Archon";"High Templar";265;0
"Upgrade";"Charge";"TwilightCouncil";245;0
"Unit";"Phoenix";"Stargate";265;2
"Unit";"Phoenix";"Stargate";265;2
"Unit";"Phoenix";"Stargate";265;2
"Unit";"Phoenix";"Stargate";265;2
"Building";"HighTemplar";NA;273;0
"Building";"HighTemplar";NA;273;0
"Building";"HighTemplar";NA;273;0
"Building";"HighTemplar";NA;273;0
"Building";"HighTemplar";NA;273;0
"Building";"HighTemplar";NA;273;0
"Building";"HighTemplar";NA;273;0
"Unit";"Archon";"High Templar";273;0
"Unit";"Archon";"High Templar";273;0
"Unit";"Archon";"High Templar";273;0
"Unit";"Archon";"High Templar";273;0
"Unit";"Phoenix";"Stargate";265;2
"Unit";"Phoenix";"Stargate";267;2
"Unit";"Phoenix";"Stargate";269;2
"Unit";"Phoenix";"Stargate";271;2
"Unit";"Zealot";"Gateway";285;2
"Unit";"Zealot";"Gateway";285;2
"Unit";"Zealot";"Gateway";285;2
"Unit";"Stalker";"Gateway";291;2
"Unit";"Stalker";"Gateway";291;2
"Unit";"Stalker";"Gateway";291;2
"Unit";"Stalker";"Gateway";291;2
"Unit";"Phoenix";"Stargate";277;2
"Unit";"Zealot";"Gateway";301;2
"Unit";"Zealot";"Gateway";301;2
"Unit";"Zealot";"Gateway";301;2
"Unit";"Zealot";"Gateway";301;2
"Building";"Pylon";NA;309;0
"Building";"Pylon";NA;309;0
"Unit";"Phoenix";"Stargate";309;2
"Unit";"Phoenix";"Stargate";309;2
"Unit";"Phoenix";"Stargate";309;2
"Unit";"Phoenix";"Stargate";309;2
"Building";"Nexus";NA;309;0
"Unit";"Phoenix";"Stargate";321;2
"Unit";"Phoenix";"Stargate";321;2
"Unit";"Phoenix";"Stargate";321;2
"Unit";"Phoenix";"Stargate";321;2
"Unit";"Stalker";"Gateway";332;2
"Unit";"Stalker";"Gateway";332;2
"Unit";"Stalker";"Gateway";332;2
"Unit";"Stalker";"Gateway";332;2
"Unit";"Stalker";"Gateway";332;2
"Unit";"Stalker";"Gateway";332;2
"Unit";"Stalker";"Gateway";332;2
"Unit";"Phoenix";"Stargate";332;2
"Unit";"Phoenix";"Stargate";332;2
"Unit";"Phoenix";"Stargate";332;2
"Unit";"Phoenix";"Stargate";332;2
"Unit";"Phoenix";"Stargate";346;2
"Unit";"Phoenix";"Stargate";346;2
"Unit";"Phoenix";"Stargate";346;2
"Unit";"Phoenix";"Stargate";346;2
"Unit";"Zealot";"Gateway";367;2
"Unit";"Zealot";"Gateway";367;2
"Unit";"Zealot";"Gateway";367;2
"Unit";"Zealot";"Gateway";367;2
"Unit";"Zealot";"Gateway";367;2
"Unit";"Zealot";"Gateway";367;2
"Upgrade";"ProtossShieldsLevel1";"Forge";321;0
"Unit";"Phoenix";"Stargate";362;2
"Unit";"Phoenix";"Stargate";362;2
"Unit";"Phoenix";"Stargate";362;2
"Unit";"Phoenix";"Stargate";362;2
"Upgrade";"ProtossAirArmorsLevel2";"CyberneticsCore";321;0
