"type";"unit_name";"on_building";"total_supply";"supply"
"Building";"Pylon";NA;13;0
"Building";"Assimilator";NA;15;0
"Building";"Gateway";NA;15;0
"Building";"Assimilator";NA;20;0
"Building";"Pylon";NA;20;0
"Building";"CyberneticsCore";NA;20;0
"Unit";"Stalker";"Gateway";21;2
"Building";"Nexus";NA;20;0
"Unit";"Stalker";"Gateway";26;2
"Building";"RoboticsFacility";NA;23;0
"Unit";"Immortal";"Robotics Facility";30;4
"Building";"Pylon";NA;36;0
"Unit";"Observer";"Robotics Facility";40;1
"Building";"Assimilator";NA;44;0
"Building";"Assimilator";NA;44;0
"Building";"TwilightCouncil";NA;44;0
"Building";"Pylon";NA;48;0
"Unit";"Stalker";"Gateway";52;2
"Building";"Gateway";NA;46;0
"Building";"Gateway";NA;46;0
"Building";"Pylon";NA;55;0
"Building";"ShieldBattery";NA;51;0
"Unit";"Stalker";"Gateway";59;2
"Unit";"Observer";"Robotics Facility";56;1
"Building";"TemplarArchive";NA;56;0
"Building";"HighTemplar";NA;63;0
"Building";"ShieldBattery";NA;62;0
"Unit";"Observer";"Robotics Facility";63;1
"Building";"Pylon";NA;63;0
"Building";"HighTemplar";NA;64;0
"Unit";"Stalker";"Gateway";65;2
"Building";"Pylon";NA;64;0
"Building";"HighTemplar";NA;67;0
"Building";"Gateway";NA;63;0
"Building";"Gateway";NA;63;0
"Building";"Forge";NA;65;0
"Building";"Pylon";NA;67;0
"Unit";"Stalker";"Gateway";69;2
"Unit";"Stalker";"Gateway";69;2
"Building";"Pylon";NA;69;0
"Building";"HighTemplar";NA;73;0
"Building";"Pylon";NA;73;0
"Building";"Pylon";NA;73;0
"Unit";"Stalker";"Gateway";74;2
"Unit";"Stalker";"Gateway";74;2
"Building";"Assimilator";NA;73;0
"Building";"Assimilator";NA;73;0
"Building";"Pylon";NA;73;0
"Unit";"Zealot";"Gateway";79;2
"Unit";"Observer";"Robotics Facility";74;1
"Unit";"Stalker";"Gateway";83;2
"Unit";"Stalker";"Gateway";83;2
"Unit";"Stalker";"Gateway";89;2
"Unit";"Stalker";"Gateway";89;2
"Building";"Pylon";NA;84;0
"Building";"Gateway";NA;74;0
"Building";"Gateway";NA;74;0
"Building";"HighTemplar";NA;94;0
"Building";"Nexus";NA;73;0
"Unit";"Stalker";"Gateway";94;2
"Unit";"Stalker";"Gateway";94;2
"Unit";"Stalker";"Gateway";94;2
"Upgrade";"ProtossGroundWeaponsLevel1";"Forge";73;0
"Unit";"Zealot";"Gateway";106;2
"Unit";"Zealot";"Gateway";106;2
"Unit";"Zealot";"Gateway";106;2
"Upgrade";"Charge";"TwilightCouncil";83;0
"Building";"Pylon";NA;105;0
"Unit";"Observer";"Robotics Facility";103;1
"Unit";"Zealot";"Gateway";106;2
"Unit";"Stalker";"Gateway";120;2
"Unit";"Stalker";"Gateway";120;2
"Unit";"Stalker";"Gateway";131;2
"Unit";"Zealot";"Gateway";136;2
"Unit";"Zealot";"Gateway";136;2
"Unit";"Zealot";"Gateway";136;2
"Unit";"Zealot";"Gateway";136;2
"Unit";"Zealot";"Gateway";136;2
"Building";"Pylon";NA;140;0
"Building";"Pylon";NA;149;0
"Unit";"Zealot";"Gateway";152;2
"Building";"RoboticsBay";NA;130;0
"Building";"Gateway";NA;131;0
"Unit";"Observer";"Robotics Facility";149;1
"Building";"Pylon";NA;151;0
"Upgrade";"ProtossGroundArmorsLevel1";"Forge";120;0
"Unit";"Stalker";"Gateway";156;2
"Unit";"Stalker";"Gateway";156;2
"Unit";"Stalker";"Gateway";156;2
"Building";"Assimilator";NA;155;0
"Building";"Assimilator";NA;155;0
"Unit";"Zealot";"Gateway";162;2
"Unit";"Zealot";"Gateway";162;2
"Unit";"Zealot";"Gateway";162;2
"Unit";"Zealot";"Gateway";162;2
"Building";"HighTemplar";NA;162;0
"Unit";"Colossus";"Robotics Facility";151;6
"Building";"Forge";NA;156;0
"Building";"RoboticsFacility";NA;155;0
"Building";"Nexus";NA;151;0
"Building";"Pylon";NA;176;0
"Building";"PhotonCannon";NA;176;0
"Building";"PhotonCannon";NA;176;0
"Unit";"Zealot";"Gateway";182;2
"Building";"Pylon";NA;182;0
"Unit";"Colossus";"Robotics Facility";176;6
"Upgrade";"ExtendedThermalLance";"RoboticsBay";162;0
"Building";"Pylon";NA;185;0
"Building";"HighTemplar";NA;194;0
"Building";"HighTemplar";NA;194;0
"Building";"HighTemplar";NA;194;0
"Building";"HighTemplar";NA;194;0
"Unit";"Colossus";"Robotics Facility";176;6
"Unit";"Observer";"Robotics Facility";185;1
"Unit";"Archon";"High Templar";195;0
"Unit";"Archon";"High Templar";201;0
"Upgrade";"ProtossGroundWeaponsLevel2";"Forge";162;0
"Building";"Pylon";NA;201;0
"Unit";"Observer";"Robotics Facility";195;1
"Building";"HighTemplar";NA;202;0
"Building";"HighTemplar";NA;202;0
"Building";"PhotonCannon";NA;194;0
"Unit";"Zealot";"Gateway";203;2
"Unit";"Zealot";"Gateway";203;2
"Unit";"Zealot";"Gateway";203;2
"Unit";"Zealot";"Gateway";203;2
"Unit";"Archon";"High Templar";203;0
"Building";"Pylon";NA;202;0
"Building";"DarkShrine";NA;185;0
"Building";"Stargate";NA;202;0
"Building";"HighTemplar";NA;211;0
"Building";"HighTemplar";NA;211;0
"Building";"HighTemplar";NA;211;0
"Building";"HighTemplar";NA;211;0
"Unit";"Stalker";"Gateway";211;2
"Unit";"Stalker";"Gateway";211;2
"Unit";"Stalker";"Gateway";211;2
"Unit";"Stalker";"Gateway";211;2
"Building";"Gateway";NA;202;0
"Building";"Gateway";NA;202;0
"Upgrade";"ProtossGroundArmorsLevel2";"Forge";182;0
"Building";"Gateway";NA;203;0
"Building";"Gateway";NA;203;0
"Unit";"Zealot";"Gateway";220;2
"Unit";"Zealot";"Gateway";220;2
"Unit";"Zealot";"Gateway";220;2
"Unit";"Zealot";"Gateway";220;2
"Unit";"Zealot";"Gateway";220;2
"Unit";"Zealot";"Gateway";220;2
"Unit";"Zealot";"Gateway";220;2
"Unit";"Zealot";"Gateway";220;2
"Building";"Nexus";NA;202;0
"Unit";"Colossus";"Robotics Facility";219;6
"Unit";"Colossus";"Robotics Facility";219;6
"Unit";"Zealot";"Gateway";250;2
"Unit";"Zealot";"Gateway";250;2
"Unit";"Zealot";"Gateway";250;2
"Unit";"Zealot";"Gateway";250;2
"Unit";"Zealot";"Gateway";250;2
"Unit";"Zealot";"Gateway";250;2
"Unit";"Zealot";"Gateway";250;2
"Unit";"Zealot";"Gateway";250;2
"Unit";"Zealot";"Gateway";250;2
"Unit";"Zealot";"Gateway";250;2
"Unit";"Zealot";"Gateway";270;2
"Unit";"Zealot";"Gateway";270;2
"Unit";"Stalker";"Gateway";274;2
"Unit";"Stalker";"Gateway";274;2
"Unit";"Stalker";"Gateway";274;2
"Unit";"Stalker";"Gateway";274;2
"Unit";"Zealot";"Gateway";284;2
"Unit";"Zealot";"Gateway";284;2
"Building";"DarkTemplar";NA;290;0
"Building";"DarkTemplar";NA;290;0
"Building";"DarkTemplar";NA;290;0
"Building";"DarkTemplar";NA;290;0
"Unit";"Zealot";"Gateway";284;2
"Unit";"Colossus";"Robotics Facility";250;6
"Unit";"Colossus";"Robotics Facility";250;6
"Unit";"Stalker";"Gateway";298;2
"Unit";"Stalker";"Gateway";298;2
"Unit";"Stalker";"Gateway";298;2
"Unit";"Stalker";"Gateway";298;2
"Unit";"Stalker";"Gateway";298;2
"Building";"HighTemplar";NA;298;0
"Building";"HighTemplar";NA;298;0
"Building";"HighTemplar";NA;298;0
"Upgrade";"ProtossGroundWeaponsLevel3";"Forge";222;0
"Building";"DarkTemplar";NA;315;0
"Building";"DarkTemplar";NA;315;0
"Unit";"Archon";"High Templar";314;0
"Unit";"Archon";"High Templar";314;0
"Building";"Assimilator";NA;314;0
"Building";"HighTemplar";NA;315;0
"Building";"HighTemplar";NA;315;0
"Unit";"Zealot";"Gateway";315;2
"Unit";"Zealot";"Gateway";315;2
"Unit";"Zealot";"Gateway";315;2
"Unit";"Zealot";"Gateway";315;2
"Unit";"Zealot";"Gateway";315;2
"Unit";"Zealot";"Gateway";315;2
"Unit";"Zealot";"Gateway";315;2
"Unit";"Zealot";"Gateway";315;2
"Building";"PhotonCannon";NA;314;0
"Building";"Assimilator";NA;315;0
"Unit";"Immortal";"Robotics Facility";314;4
"Unit";"Immortal";"Robotics Facility";314;4
"Building";"HighTemplar";NA;340;0
"Unit";"Stalker";"Gateway";340;2
"Unit";"Stalker";"Gateway";340;2
"Unit";"Stalker";"Gateway";340;2
"Unit";"Stalker";"Gateway";346;2
"Unit";"Stalker";"Gateway";346;2
"Unit";"Stalker";"Gateway";346;2
"Upgrade";"ProtossGroundArmorsLevel3";"Forge";284;0
"Unit";"Stalker";"Gateway";346;2
"Building";"HighTemplar";NA;346;0
"Building";"HighTemplar";NA;346;0
"Unit";"Archon";"High Templar";354;0
"Unit";"Archon";"High Templar";354;0
"Unit";"Zealot";"Gateway";354;2
"Unit";"Zealot";"Gateway";354;2
"Unit";"Zealot";"Gateway";354;2
"Unit";"Zealot";"Gateway";354;2
"Unit";"Zealot";"Gateway";354;2
"Unit";"Zealot";"Gateway";354;2
"Unit";"Zealot";"Gateway";354;2
"Unit";"Zealot";"Gateway";354;2
"Unit";"Zealot";"Gateway";354;2
"Unit";"Zealot";"Gateway";354;2
"Building";"Nexus";NA;346;0
"Building";"HighTemplar";NA;376;0
"Building";"HighTemplar";NA;376;0
"Building";"HighTemplar";NA;376;0
"Building";"HighTemplar";NA;376;0
"Unit";"Stalker";"Gateway";376;2
"Unit";"Stalker";"Gateway";376;2
"Unit";"Stalker";"Gateway";376;2
"Building";"Pylon";NA;374;0
"Unit";"Stalker";"Gateway";376;2
"Unit";"Stalker";"Gateway";376;2
"Unit";"Stalker";"Gateway";376;2
"Unit";"Stalker";"Gateway";376;2
"Unit";"Archon";"High Templar";380;0
"Unit";"Archon";"High Templar";382;0
"Unit";"Archon";"High Templar";384;0
"Building";"HighTemplar";NA;390;0
"Building";"HighTemplar";NA;390;0
"Unit";"Zealot";"Gateway";390;2
"Unit";"Zealot";"Gateway";390;2
"Building";"Assimilator";NA;390;0
"Building";"Assimilator";NA;390;0
"Unit";"Stalker";"Gateway";394;2
"Unit";"Stalker";"Gateway";394;2
"Unit";"Stalker";"Gateway";394;2
"Unit";"Stalker";"Gateway";394;2
"Unit";"Stalker";"Gateway";394;2
"Unit";"Stalker";"Gateway";394;2
"Unit";"Stalker";"Gateway";394;2
"Unit";"Stalker";"Gateway";394;2
"Unit";"Stalker";"Gateway";394;2
"Unit";"Stalker";"Gateway";394;2
"Unit";"Stalker";"Gateway";394;2
"Unit";"Stalker";"Gateway";394;2
"Building";"Gateway";NA;390;0
"Building";"Gateway";NA;390;0
"Upgrade";"ProtossShieldsLevel1";"Forge";376;0
"Unit";"Stalker";"Gateway";418;2
"Unit";"Stalker";"Gateway";418;2
"Unit";"Stalker";"Gateway";418;2
"Building";"HighTemplar";NA;418;0
"Building";"HighTemplar";NA;418;0
"Unit";"Zealot";"Gateway";418;2
"Unit";"Zealot";"Gateway";418;2
"Unit";"Zealot";"Gateway";418;2
"Unit";"Zealot";"Gateway";418;2
"Unit";"Zealot";"Gateway";418;2
"Unit";"Zealot";"Gateway";418;2
"Unit";"Zealot";"Gateway";418;2
"Building";"Pylon";NA;418;0
