"type";"unit_name";"on_building";"total_supply_lag";"supply"
"Building";"Pylon";NA;14;0
"Building";"Gateway";NA;16;0
"Building";"Assimilator";NA;17;0
"Building";"Nexus";NA;20;0
"Building";"CyberneticsCore";NA;20;0
"Building";"Assimilator";NA;21;0
"Building";"Pylon";NA;22;0
"Unit";"Stalker";"Gateway";22;2
"Building";"Stargate";NA;26;0
"Unit";"Stalker";"Gateway";29;2
"Unit";"Oracle";"Stargate";35;3
"Building";"Pylon";NA;40;0
"Unit";"Oracle";"Stargate";42;3
"Building";"Gateway";NA;45;0
"Building";"Gateway";NA;47;0
"Building";"Assimilator";NA;49;0
"Building";"Nexus";NA;51;0
"Building";"Pylon";NA;51;0
"Unit";"Phoenix";"Stargate";51;2
"Building";"Assimilator";NA;57;0
"Building";"Forge";NA;59;0
"Building";"TwilightCouncil";NA;59;0
"Building";"Pylon";NA;59;0
"Building";"OracleStasisTrap";NA;63;0
"Unit";"Sentry";"Gateway";63;2
"Unit";"Sentry";"Gateway";65;2
"Unit";"Sentry";"Gateway";67;2
"Building";"Gateway";NA;69;0
"Building";"Gateway";NA;69;0
"Building";"Gateway";NA;71;0
"Upgrade";"ProtossGroundWeaponsLevel1";"Forge";71;0
"Building";"Gateway";NA;71;0
"Building";"Gateway";NA;71;0
"Building";"OracleStasisTrap";NA;74;0
"Unit";"Stalker";"Gateway";74;2
"Unit";"Stalker";"Gateway";76;2
"Unit";"Stalker";"Gateway";78;2
"Building";"Pylon";NA;83;0
"Building";"Pylon";NA;83;0
"Building";"OracleStasisTrap";NA;83;0
"Building";"RoboticsFacility";NA;83;0
"Building";"PhotonCannon";NA;87;0
"Unit";"Stalker";"Gateway";89;2
"Building";"Assimilator";NA;91;0
"Building";"Assimilator";NA;91;0
"Unit";"Stalker";"Gateway";91;2
"Unit";"Stalker";"Gateway";93;2
"Building";"ShieldBattery";NA;95;0
"Building";"Pylon";NA;98;0
"Building";"Pylon";NA;98;0
"Unit";"Stalker";"Gateway";98;2
"Unit";"Stalker";"Gateway";100;2
"Unit";"Observer";"Robotics Facility";102;1
"Building";"Pylon";NA;103;0
"Unit";"Zealot";"Gateway";103;2
"Unit";"Zealot";"Gateway";105;2
"Unit";"Zealot";"Gateway";107;2
"Unit";"Zealot";"Gateway";109;2
"Unit";"Zealot";"Gateway";111;2
"Unit";"Stalker";"Gateway";113;2
"Building";"Pylon";NA;115;0
"Building";"Pylon";NA;115;0
"Upgrade";"Charge";"TwilightCouncil";115;0
"Unit";"Immortal";"Robotics Facility";115;4
"Building";"TemplarArchive";NA;119;0
"Unit";"Zealot";"Gateway";119;2
"Unit";"Zealot";"Gateway";121;2
"Unit";"Zealot";"Gateway";123;2
"Unit";"Zealot";"Gateway";125;2
"Unit";"Zealot";"Gateway";127;2
"Unit";"Zealot";"Gateway";129;2
"Unit";"Zealot";"Gateway";131;2
"Unit";"Zealot";"Gateway";133;2
"Unit";"Immortal";"Robotics Facility";135;4
"Unit";"Zealot";"Gateway";139;2
"Unit";"Zealot";"Gateway";141;2
"Unit";"Zealot";"Gateway";143;2
"Unit";"Zealot";"Gateway";145;2
"Unit";"Zealot";"Gateway";147;2
"Unit";"Zealot";"Gateway";149;2
"Unit";"Zealot";"Gateway";151;2
"Unit";"Zealot";"Gateway";153;2
"Building";"HighTemplar";NA;155;0
"Building";"HighTemplar";NA;155;0
"Building";"HighTemplar";NA;155;0
"Building";"HighTemplar";NA;155;0
"Building";"HighTemplar";NA;155;0
"Building";"HighTemplar";NA;155;0
"Unit";"Zealot";"Gateway";155;2
"Unit";"Zealot";"Gateway";157;2
"Unit";"Immortal";"Robotics Facility";159;4
"Unit";"Archon";"High Templar";163;0
"Unit";"Archon";"High Templar";163;0
"Unit";"Archon";"High Templar";163;0
"Unit";"Zealot";"Gateway";163;2
"Unit";"Zealot";"Gateway";165;2
"Unit";"Zealot";"Gateway";167;2
"Unit";"Zealot";"Gateway";169;2
"Unit";"Zealot";"Gateway";171;2
"Unit";"Zealot";"Gateway";173;2
"Unit";"Zealot";"Gateway";175;2
"Unit";"Zealot";"Gateway";177;2
"Building";"Pylon";NA;179;0
"Building";"HighTemplar";NA;179;0
"Building";"HighTemplar";NA;179;0
"Building";"HighTemplar";NA;179;0
"Building";"HighTemplar";NA;179;0
"Unit";"Zealot";"Gateway";179;2
"Unit";"Zealot";"Gateway";181;2
"Unit";"Zealot";"Gateway";183;2
"Unit";"Zealot";"Gateway";185;2
"Building";"Pylon";NA;187;0
"Building";"Pylon";NA;187;0
"Building";"Nexus";NA;187;0
"Unit";"Zealot";"Gateway";187;2
"Unit";"Zealot";"Gateway";189;2
"Unit";"Zealot";"Gateway";191;2
"Building";"HighTemplar";NA;193;0
"Building";"HighTemplar";NA;193;0
"Unit";"Stalker";"Gateway";193;2
"Unit";"Stalker";"Gateway";195;2
"Unit";"Archon";"High Templar";197;0
"Unit";"Zealot";"Gateway";199;2
"Unit";"Zealot";"Gateway";201;2
"Unit";"Zealot";"Gateway";203;2
"Unit";"Zealot";"Gateway";205;2
"Building";"PhotonCannon";NA;207;0
"Unit";"Archon";"High Templar";208;0
"Building";"HighTemplar";NA;208;0
"Building";"HighTemplar";NA;208;0
"Building";"HighTemplar";NA;208;0
"Unit";"Zealot";"Gateway";208;2
"Unit";"Zealot";"Gateway";210;2
"Unit";"Zealot";"Gateway";212;2
"Unit";"Zealot";"Gateway";214;2
"Unit";"Zealot";"Gateway";216;2
"Building";"Pylon";NA;220;0
"Unit";"Zealot";"Gateway";220;2
"Unit";"Zealot";"Gateway";222;2
"Unit";"Zealot";"Gateway";224;2
"Unit";"Zealot";"Gateway";226;2
"Unit";"Zealot";"Gateway";228;2
"Building";"HighTemplar";NA;230;0
"Building";"HighTemplar";NA;230;0
"Unit";"Zealot";"Gateway";230;2
"Unit";"Archon";"High Templar";232;0
"Unit";"Zealot";"Gateway";232;2
"Unit";"Zealot";"Gateway";234;2
"Unit";"Zealot";"Gateway";236;2
"Unit";"Zealot";"Gateway";238;2
"Unit";"Zealot";"Gateway";240;2
"Unit";"Zealot";"Gateway";242;2
"Upgrade";"SprayProtoss";NA;244;0
"Upgrade";"SprayProtoss";NA;244;0
"Upgrade";"SprayProtoss";NA;244;0
"Upgrade";"WarpGateResearch";NA;244;0
"Upgrade";"SprayProtoss";NA;244;0
"Upgrade";"BlinkTech";NA;244;0
"Upgrade";"ProtossGroundArmorsLevel1";NA;244;0
"Upgrade";"SprayProtoss";NA;244;0
"Upgrade";"PsiStormTech";NA;244;0
"Upgrade";"SprayProtoss";NA;244;0
"Upgrade";"ProtossGroundArmorsLevel2";NA;244;0
"Upgrade";"SprayProtoss";NA;244;0
