"type";"unit_name";"on_building";"total_supply";"supply"
"Building";"Pylon";NA;13;0
"Building";"Assimilator";NA;16;0
"Building";"Gateway";NA;14;0
"Building";"Pylon";NA;20;0
"Building";"CyberneticsCore";NA;19;0
"Building";"Assimilator";NA;21;0
"Unit";"Stalker";"Gateway";21;2
"Building";"Nexus";NA;18;0
"Unit";"Stalker";"Gateway";26;2
"Building";"TwilightCouncil";NA;26;0
"Unit";"Stalker";"Gateway";34;2
"Building";"Gateway";NA;30;0
"Building";"Gateway";NA;33;0
"Building";"Pylon";NA;38;0
"Building";"ShieldBattery";NA;38;0
"Unit";"Stalker";"Gateway";44;2
"Unit";"Stalker";"Gateway";44;2
"Unit";"Stalker";"Gateway";44;2
"Building";"Pylon";NA;52;0
"Building";"RoboticsFacility";NA;42;0
"Building";"Assimilator";NA;52;0
"Building";"Pylon";NA;54;0
"Unit";"Observer";"Robotics Facility";54;1
"Unit";"Stalker";"Gateway";56;2
"Unit";"Stalker";"Gateway";56;2
"Unit";"Stalker";"Gateway";56;2
"Building";"Pylon";NA;55;0
"Unit";"Observer";"Robotics Facility";64;1
"Unit";"Stalker";"Gateway";69;2
"Unit";"Stalker";"Gateway";69;2
"Building";"Pylon";NA;66;0
"Unit";"Stalker";"Gateway";73;2
"Building";"Nexus";NA;55;0
"Building";"Forge";NA;66;0
"Building";"Forge";NA;66;0
"Unit";"Stalker";"Gateway";75;2
"Unit";"Zealot";"Gateway";83;2
"Unit";"Zealot";"Gateway";83;2
"Unit";"Zealot";"Gateway";83;2
"Upgrade";"Charge";"TwilightCouncil";75;0
"Building";"Pylon";NA;91;0
"Building";"Gateway";NA;79;0
"Building";"Pylon";NA;91;0
"Building";"Gateway";NA;79;0
"Building";"Gateway";NA;79;0
"Building";"Pylon";NA;91;0
"Building";"Gateway";NA;79;0
"Building";"Gateway";NA;80;0
"Building";"Pylon";NA;93;0
"Unit";"Zealot";"Gateway";96;2
"Unit";"Zealot";"Gateway";96;2
"Unit";"Zealot";"Gateway";96;2
"Unit";"Zealot";"Gateway";96;2
"Unit";"Zealot";"Gateway";96;2
"Unit";"Zealot";"Gateway";96;2
"Unit";"Zealot";"Gateway";96;2
"Unit";"Zealot";"Gateway";96;2
"Unit";"Immortal";"Robotics Facility";92;4
"Building";"Pylon";NA;113;0
"Unit";"Zealot";"Gateway";118;2
"Unit";"Zealot";"Gateway";118;2
"Unit";"Zealot";"Gateway";118;2
"Unit";"Zealot";"Gateway";118;2
"Unit";"Zealot";"Gateway";118;2
"Unit";"Zealot";"Gateway";118;2
"Unit";"Zealot";"Gateway";118;2
"Unit";"Zealot";"Gateway";118;2
"Upgrade";"ProtossGroundWeaponsLevel1";"Forge";81;0
"Upgrade";"ProtossGroundArmorsLevel1";"Forge";81;0
"Building";"TemplarArchive";NA;96;0
"Building";"Pylon";NA;134;0
"Unit";"Zealot";"Gateway";134;2
"Unit";"Zealot";"Gateway";134;2
"Unit";"Zealot";"Gateway";134;2
"Unit";"Zealot";"Gateway";134;2
"Unit";"Zealot";"Gateway";134;2
"Unit";"Zealot";"Gateway";134;2
"Unit";"Zealot";"Gateway";134;2
"Unit";"Zealot";"Gateway";134;2
"Unit";"Stalker";"Gateway";150;2
"Unit";"Stalker";"Gateway";150;2
"Unit";"Stalker";"Gateway";150;2
"Unit";"Stalker";"Gateway";150;2
"Unit";"Stalker";"Gateway";150;2
"Unit";"Stalker";"Gateway";150;2
"Unit";"Stalker";"Gateway";150;2
"Unit";"Stalker";"Gateway";150;2
"Unit";"Zealot";"Gateway";167;2
"Unit";"Zealot";"Gateway";167;2
"Unit";"Zealot";"Gateway";167;2
"Unit";"Zealot";"Gateway";167;2
"Unit";"Zealot";"Gateway";167;2
"Unit";"Zealot";"Gateway";167;2
"Unit";"Zealot";"Gateway";167;2
"Unit";"Zealot";"Gateway";167;2
"Unit";"Zealot";"Gateway";184;2
"Unit";"Zealot";"Gateway";184;2
"Unit";"Zealot";"Gateway";184;2
"Unit";"Zealot";"Gateway";184;2
"Unit";"Zealot";"Gateway";184;2
"Unit";"Zealot";"Gateway";184;2
"Unit";"Zealot";"Gateway";184;2
"Unit";"Zealot";"Gateway";184;2
"Building";"Pylon";NA;183;0
"Unit";"Zealot";"Gateway";200;2
"Unit";"Zealot";"Gateway";200;2
"Unit";"Zealot";"Gateway";200;2
"Unit";"Zealot";"Gateway";200;2
"Unit";"Zealot";"Gateway";200;2
"Unit";"Zealot";"Gateway";200;2
"Unit";"Zealot";"Gateway";200;2
"Building";"HighTemplar";NA;214;0
"Building";"Pylon";NA;214;0
"Building";"Pylon";NA;214;0
"Upgrade";"ProtossGroundWeaponsLevel2";"Forge";167;0
"Building";"Nexus";NA;183;0
"Upgrade";"ProtossGroundArmorsLevel2";"Forge";167;0
"Building";"HighTemplar";NA;218;0
"Building";"HighTemplar";NA;218;0
"Building";"HighTemplar";NA;218;0
"Building";"HighTemplar";NA;218;0
"Unit";"Zealot";"Gateway";218;2
"Unit";"Zealot";"Gateway";218;2
"Unit";"Zealot";"Gateway";218;2
"Unit";"Zealot";"Gateway";228;2
"Unit";"Zealot";"Gateway";228;2
"Unit";"Zealot";"Gateway";228;2
"Unit";"Zealot";"Gateway";228;2
"Building";"Assimilator";NA;224;0
"Building";"Assimilator";NA;224;0
"Building";"Assimilator";NA;224;0
"Building";"Assimilator";NA;224;0
"Building";"Pylon";NA;228;0
"Unit";"Zealot";"Gateway";236;2
"Unit";"Zealot";"Gateway";236;2
"Unit";"Zealot";"Gateway";236;2
"Unit";"Zealot";"Gateway";236;2
"Building";"PhotonCannon";NA;224;0
"Building";"PhotonCannon";NA;224;0
"Building";"PhotonCannon";NA;226;0
"Building";"ShieldBattery";NA;228;0
"Building";"PhotonCannon";NA;228;0
"Unit";"Zealot";"Gateway";244;2
"Unit";"Zealot";"Gateway";244;2
"Unit";"Zealot";"Gateway";244;2
"Unit";"Zealot";"Gateway";244;2
"Unit";"Zealot";"Gateway";244;2
"Unit";"Zealot";"Gateway";244;2
"Unit";"Zealot";"Gateway";244;2
"Unit";"Zealot";"Gateway";244;2
"Unit";"Immortal";"Robotics Facility";244;4
"Unit";"Zealot";"Gateway";264;2
"Unit";"Zealot";"Gateway";264;2
"Unit";"Zealot";"Gateway";264;2
"Unit";"Zealot";"Gateway";264;2
"Unit";"Zealot";"Gateway";264;2
"Unit";"Zealot";"Gateway";264;2
"Unit";"Zealot";"Gateway";264;2
"Unit";"Zealot";"Gateway";264;2
"Building";"HighTemplar";NA;280;0
"Building";"HighTemplar";NA;280;0
"Building";"HighTemplar";NA;280;0
"Building";"HighTemplar";NA;280;0
"Building";"HighTemplar";NA;280;0
"Building";"HighTemplar";NA;280;0
"Building";"HighTemplar";NA;280;0
"Unit";"Immortal";"Robotics Facility";260;4
"Building";"Nexus";NA;260;0
"Upgrade";"ProtossGroundWeaponsLevel3";"Forge";244;0
"Building";"Gateway";NA;280;0
"Building";"Gateway";NA;280;0
"Building";"Gateway";NA;280;0
"Building";"Gateway";NA;280;0
"Building";"Gateway";NA;280;0
"Unit";"Zealot";"Gateway";285;2
"Unit";"Zealot";"Gateway";285;2
"Unit";"Zealot";"Gateway";285;2
"Unit";"Zealot";"Gateway";285;2
"Unit";"Zealot";"Gateway";285;2
"Unit";"Zealot";"Gateway";285;2
"Unit";"Zealot";"Gateway";285;2
"Unit";"Zealot";"Gateway";285;2
"Building";"Pylon";NA;284;0
"Building";"Pylon";NA;285;0
"Unit";"Zealot";"Gateway";301;2
"Unit";"Zealot";"Gateway";301;2
"Building";"RoboticsBay";NA;284;0
"Unit";"Zealot";"Gateway";301;2
"Unit";"Zealot";"Gateway";301;2
"Unit";"Zealot";"Gateway";301;2
"Unit";"Zealot";"Gateway";301;2
"Unit";"Zealot";"Gateway";301;2
"Unit";"Zealot";"Gateway";301;2
"Unit";"Zealot";"Gateway";301;2
"Unit";"Zealot";"Gateway";301;2
"Unit";"Zealot";"Gateway";301;2
"Unit";"Zealot";"Gateway";301;2
"Unit";"Zealot";"Gateway";301;2
"Building";"RoboticsFacility";NA;284;0
"Building";"Nexus";NA;285;0
"Building";"HighTemplar";NA;327;0
"Building";"HighTemplar";NA;327;0
"Building";"HighTemplar";NA;327;0
"Building";"HighTemplar";NA;327;0
"Unit";"Zealot";"Gateway";327;2
"Unit";"Zealot";"Gateway";327;2
"Unit";"Zealot";"Gateway";327;2
"Unit";"Zealot";"Gateway";327;2
"Unit";"Zealot";"Gateway";327;2
"Unit";"Zealot";"Gateway";327;2
"Unit";"Zealot";"Gateway";327;2
"Unit";"Zealot";"Gateway";327;2
"Unit";"Zealot";"Gateway";327;2
"Building";"HighTemplar";NA;345;0
"Building";"HighTemplar";NA;345;0
"Building";"HighTemplar";NA;345;0
"Building";"HighTemplar";NA;345;0
"Building";"HighTemplar";NA;345;0
"Building";"HighTemplar";NA;345;0
"Building";"Pylon";NA;345;0
"Unit";"Archon";"High Templar";345;0
"Unit";"Archon";"High Templar";345;0
"Unit";"Zealot";"Gateway";345;2
"Unit";"Zealot";"Gateway";345;2
"Unit";"Zealot";"Gateway";345;2
"Unit";"Zealot";"Gateway";345;2
"Unit";"Zealot";"Gateway";345;2
"Unit";"Zealot";"Gateway";345;2
"Unit";"Zealot";"Gateway";345;2
"Unit";"Archon";"High Templar";345;0
"Unit";"Colossus";"Robotics Facility";327;6
"Unit";"Colossus";"Robotics Facility";327;6
"Unit";"Zealot";"Gateway";371;2
"Unit";"Zealot";"Gateway";371;2
"Unit";"Zealot";"Gateway";371;2
"Unit";"Zealot";"Gateway";371;2
"Unit";"Zealot";"Gateway";371;2
"Unit";"Zealot";"Gateway";371;2
"Building";"Gateway";NA;345;0
"Unit";"Zealot";"Gateway";383;2
"Unit";"Zealot";"Gateway";383;2
"Unit";"Zealot";"Gateway";383;2
"Unit";"Zealot";"Gateway";383;2
"Unit";"Zealot";"Gateway";383;2
"Unit";"Zealot";"Gateway";383;2
"Unit";"Zealot";"Gateway";383;2
"Unit";"Zealot";"Gateway";383;2
"Unit";"Archon";"High Templar";383;0
"Unit";"Archon";"High Templar";383;0
"Building";"HighTemplar";NA;399;0
"Building";"HighTemplar";NA;399;0
"Building";"HighTemplar";NA;399;0
"Building";"HighTemplar";NA;399;0
"Building";"HighTemplar";NA;399;0
"Building";"HighTemplar";NA;399;0
"Building";"HighTemplar";NA;399;0
"Building";"HighTemplar";NA;399;0
"Unit";"Colossus";"Robotics Facility";365;6
"Unit";"Stalker";"Gateway";405;2
"Unit";"Stalker";"Gateway";405;2
"Unit";"Stalker";"Gateway";405;2
"Unit";"Stalker";"Gateway";405;2
"Unit";"Stalker";"Gateway";405;2
"Unit";"Stalker";"Gateway";405;2
"Unit";"Stalker";"Gateway";405;2
"Unit";"Stalker";"Gateway";405;2
"Building";"Pylon";NA;421;0
"Unit";"Zealot";"Gateway";421;2
"Unit";"Zealot";"Gateway";421;2
"Unit";"Zealot";"Gateway";421;2
"Unit";"Zealot";"Gateway";421;2
"Unit";"Zealot";"Gateway";421;2
"Unit";"Zealot";"Gateway";421;2
"Unit";"Zealot";"Gateway";421;2
"Unit";"Zealot";"Gateway";421;2
"Unit";"Zealot";"Gateway";437;2
"Unit";"Zealot";"Gateway";437;2
"Unit";"Zealot";"Gateway";437;2
"Unit";"Zealot";"Gateway";437;2
"Unit";"Zealot";"Gateway";437;2
"Unit";"Zealot";"Gateway";437;2
"Building";"Nexus";NA;421;0
"Building";"HighTemplar";NA;449;0
"Building";"HighTemplar";NA;449;0
"Building";"HighTemplar";NA;449;0
"Building";"HighTemplar";NA;449;0
"Building";"HighTemplar";NA;449;0
"Building";"HighTemplar";NA;449;0
"Unit";"Archon";"High Templar";449;0
"Unit";"Archon";"High Templar";449;0
"Unit";"Archon";"High Templar";449;0
"Upgrade";"ProtossGroundArmorsLevel3";"Forge";421;0
