"type";"unit_name";"on_building";"total_supply_lag";"supply"
"Building";"Pylon";NA;14;0
"Building";"Gateway";NA;16;0
"Building";"Assimilator";NA;17;0
"Building";"Nexus";NA;20;0
"Building";"CyberneticsCore";NA;21;0
"Building";"Pylon";NA;22;0
"Building";"Assimilator";NA;22;0
"Unit";"Stalker";"Gateway";24;2
"Building";"TwilightCouncil";NA;28;0
"Unit";"Stalker";"Gateway";28;2
"Unit";"Stalker";"Gateway";37;2
"Building";"Pylon";NA;41;0
"Unit";"Stalker";"Gateway";43;2
"Building";"Gateway";NA;46;0
"Building";"Gateway";NA;47;0
"Building";"RoboticsFacility";NA;47;0
"Building";"Pylon";NA;49;0
"Building";"Assimilator";NA;49;0
"Unit";"Stalker";"Gateway";51;2
"Building";"Pylon";NA;54;0
"Building";"Nexus";NA;54;0
"Unit";"Observer";"Robotics Facility";54;1
"Unit";"Stalker";"Gateway";55;2
"Unit";"Stalker";"Gateway";57;2
"Unit";"Stalker";"Gateway";59;2
"Unit";"Observer";"Robotics Facility";61;1
"Building";"Pylon";NA;62;0
"Unit";"Stalker";"Gateway";64;2
"Unit";"Stalker";"Gateway";66;2
"Upgrade";"Charge";"TwilightCouncil";71;0
"Building";"Forge";NA;71;0
"Unit";"Observer";"Robotics Facility";74;1
"Unit";"Stalker";"Gateway";75;2
"Unit";"Stalker";"Gateway";77;2
"Unit";"Stalker";"Gateway";83;2
"Unit";"Observer";"Robotics Facility";85;1
"Building";"Gateway";NA;89;0
"Building";"Gateway";NA;89;0
"Building";"Gateway";NA;89;0
"Unit";"Stalker";"Gateway";92;2
"Unit";"Stalker";"Gateway";94;2
"Unit";"Stalker";"Gateway";96;2
"Building";"Pylon";NA;98;0
"Building";"Forge";NA;103;0
"Unit";"Stalker";"Gateway";103;2
"Unit";"Stalker";"Gateway";105;2
"Unit";"Stalker";"Gateway";107;2
"Building";"Pylon";NA;115;0
"Building";"Pylon";NA;117;0
"Upgrade";"ProtossGroundWeaponsLevel1";"Forge";117;0
"Unit";"Stalker";"Gateway";118;2
"Unit";"Stalker";"Gateway";120;2
"Unit";"Stalker";"Gateway";122;2
"Unit";"Stalker";"Gateway";124;2
"Unit";"Stalker";"Gateway";126;2
"Unit";"Stalker";"Gateway";128;2
"Unit";"Zealot";"Gateway";137;2
"Unit";"Zealot";"Gateway";139;2
"Unit";"Zealot";"Gateway";141;2
"Unit";"Zealot";"Gateway";143;2
"Unit";"Zealot";"Gateway";145;2
"Unit";"Zealot";"Gateway";147;2
"Unit";"Zealot";"Gateway";157;2
"Unit";"Zealot";"Gateway";159;2
"Unit";"Zealot";"Gateway";161;2
"Unit";"Zealot";"Gateway";163;2
"Unit";"Zealot";"Gateway";165;2
"Unit";"Zealot";"Gateway";167;2
"Building";"Nexus";NA;172;0
"Building";"RoboticsFacility";NA;174;0
"Building";"RoboticsBay";NA;175;0
"Unit";"Zealot";"Gateway";176;2
"Unit";"Zealot";"Gateway";178;2
"Unit";"Zealot";"Gateway";180;2
"Unit";"Zealot";"Gateway";182;2
"Unit";"Zealot";"Gateway";184;2
"Unit";"Zealot";"Gateway";186;2
"Unit";"Colossus";"Robotics Facility";190;6
"Unit";"Colossus";"Robotics Facility";196;6
"Unit";"Zealot";"Gateway";202;2
"Unit";"Zealot";"Gateway";204;2
"Unit";"Zealot";"Gateway";206;2
"Unit";"Zealot";"Gateway";208;2
"Unit";"Zealot";"Gateway";210;2
"Unit";"Zealot";"Gateway";212;2
"Building";"Gateway";NA;217;0
"Building";"Gateway";NA;217;0
"Upgrade";"ExtendedThermalLance";"RoboticsBay";217;0
"Building";"Gateway";NA;217;0
"Unit";"Sentry";"Gateway";217;2
"Unit";"Sentry";"Gateway";219;2
"Unit";"Stalker";"Gateway";221;2
"Unit";"Stalker";"Gateway";223;2
"Unit";"Stalker";"Gateway";225;2
"Unit";"Stalker";"Gateway";227;2
"Unit";"Stalker";"Gateway";236;2
"Unit";"Stalker";"Gateway";238;2
"Unit";"Stalker";"Gateway";240;2
"Unit";"Zealot";"Gateway";246;2
"Unit";"Zealot";"Gateway";248;2
"Unit";"Zealot";"Gateway";250;2
"Unit";"Zealot";"Gateway";256;2
"Unit";"Zealot";"Gateway";259;2
"Unit";"Zealot";"Gateway";261;2
"Unit";"Stalker";"Gateway";263;2
"Unit";"Stalker";"Gateway";265;2
"Unit";"Stalker";"Gateway";267;2
"Unit";"Stalker";"Gateway";269;2
"Unit";"Stalker";"Gateway";271;2
"Unit";"Stalker";"Gateway";273;2
"Unit";"Stalker";"Gateway";277;2
"Building";"Pylon";NA;279;0
"Building";"Pylon";NA;280;0
"Building";"Pylon";NA;280;0
"Building";"Pylon";NA;280;0
"Unit";"Zealot";"Gateway";280;2
"Unit";"Zealot";"Gateway";282;2
"Unit";"Zealot";"Gateway";284;2
"Unit";"Zealot";"Gateway";286;2
"Unit";"Zealot";"Gateway";288;2
"Unit";"Zealot";"Gateway";290;2
"Unit";"Zealot";"Gateway";292;2
"Unit";"Zealot";"Gateway";294;2
"Unit";"Zealot";"Gateway";296;2
"Unit";"Colossus";"Robotics Facility";300;6
"Building";"Assimilator";NA;307;0
"Upgrade";"ProtossGroundWeaponsLevel2";"Forge";307;0
"Unit";"Colossus";"Robotics Facility";307;6
"Unit";"Zealot";"Gateway";313;2
"Unit";"Zealot";"Gateway";315;2
"Unit";"Zealot";"Gateway";317;2
"Unit";"Zealot";"Gateway";319;2
"Unit";"Zealot";"Gateway";321;2
"Unit";"Zealot";"Gateway";323;2
"Unit";"Zealot";"Gateway";325;2
"Unit";"Zealot";"Gateway";327;2
"Unit";"Zealot";"Gateway";329;2
"Unit";"Zealot";"Gateway";331;2
"Unit";"Zealot";"Gateway";333;2
"Unit";"Zealot";"Gateway";335;2
"Unit";"Zealot";"Gateway";337;2
"Unit";"Zealot";"Gateway";339;2
"Unit";"Zealot";"Gateway";341;2
"Unit";"Colossus";"Robotics Facility";347;6
"Unit";"Colossus";"Robotics Facility";353;6
"Unit";"Stalker";"Gateway";359;2
"Unit";"Stalker";"Gateway";361;2
"Building";"Assimilator";NA;363;0
"Unit";"Zealot";"Gateway";363;2
"Unit";"Zealot";"Gateway";365;2
"Unit";"Zealot";"Gateway";367;2
"Building";"Assimilator";NA;369;0
"Building";"Pylon";NA;369;0
"Building";"Pylon";NA;369;0
"Building";"Pylon";NA;369;0
"Building";"Pylon";NA;369;0
"Unit";"Zealot";"Gateway";371;2
"Unit";"Zealot";"Gateway";373;2
"Unit";"Zealot";"Gateway";375;2
"Unit";"Zealot";"Gateway";377;2
"Unit";"Zealot";"Gateway";379;2
"Unit";"Zealot";"Gateway";381;2
"Unit";"Zealot";"Gateway";383;2
"Unit";"Zealot";"Gateway";385;2
"Unit";"Zealot";"Gateway";387;2
"Upgrade";"SprayProtoss";NA;389;0
"Upgrade";"SprayProtoss";NA;389;0
"Upgrade";"WarpGateResearch";NA;389;0
"Upgrade";"SprayProtoss";NA;389;0
"Upgrade";"BlinkTech";NA;389;0
"Upgrade";"SprayProtoss";NA;389;0
"Upgrade";"ProtossGroundArmorsLevel1";NA;389;0
"Upgrade";"SprayProtoss";NA;389;0
"Upgrade";"ProtossGroundArmorsLevel2";NA;389;0
"Upgrade";"SprayProtoss";NA;389;0
"Upgrade";"ProtossGroundArmorsLevel3";NA;389;0
