"type";"unit_name";"on_building";"total_supply";"supply"
"Building";"Pylon";NA;13;0
"Building";"Assimilator";NA;15;0
"Building";"Gateway";NA;15;0
"Building";"Assimilator";NA;20;0
"Building";"CyberneticsCore";NA;20;0
"Building";"Pylon";NA;21;0
"Unit";"Stalker";"Gateway";22;2
"Building";"Nexus";NA;19;0
"Unit";"Stalker";"Gateway";24;2
"Unit";"Stalker";"Gateway";31;2
"Building";"Gateway";NA;27;0
"Building";"Gateway";NA;27;0
"Building";"Pylon";NA;34;0
"Building";"Pylon";NA;39;0
"Building";"Assimilator";NA;41;0
"Building";"TwilightCouncil";NA;39;0
"Unit";"Stalker";"Gateway";43;2
"Unit";"Stalker";"Gateway";43;2
"Unit";"Stalker";"Gateway";43;2
"Unit";"Stalker";"Gateway";52;2
"Unit";"Stalker";"Gateway";52;2
"Unit";"Stalker";"Gateway";52;2
"Building";"RoboticsFacility";NA;43;0
"Building";"Pylon";NA;58;0
"Unit";"Stalker";"Gateway";60;2
"Unit";"Stalker";"Gateway";60;2
"Unit";"Stalker";"Gateway";60;2
"Building";"Pylon";NA;60;0
"Unit";"Observer";"Robotics Facility";60;1
"Unit";"Stalker";"Gateway";67;2
"Unit";"Stalker";"Gateway";67;2
"Unit";"Stalker";"Gateway";67;2
"Building";"Pylon";NA;74;0
"Building";"Pylon";NA;74;0
"Unit";"Stalker";"Gateway";74;2
"Unit";"Stalker";"Gateway";74;2
"Building";"Gateway";NA;68;0
"Unit";"Stalker";"Gateway";74;2
"Building";"Nexus";NA;61;0
"Building";"Gateway";NA;68;0
"Unit";"Immortal";"Robotics Facility";74;4
"Building";"Gateway";NA;74;0
"Unit";"Observer";"Robotics Facility";82;1
"Building";"Forge";NA;82;0
"Unit";"Zealot";"Gateway";93;2
"Unit";"Sentry";"Gateway";96;2
"Unit";"Sentry";"Gateway";96;2
"Unit";"Sentry";"Gateway";96;2
"Unit";"Sentry";"Gateway";96;2
"Unit";"Stalker";"Gateway";97;2
"Building";"Pylon";NA;93;0
"Upgrade";"Charge";"TwilightCouncil";74;0
"Building";"Gateway";NA;88;0
"Building";"Gateway";NA;88;0
"Unit";"Stalker";"Gateway";108;2
"Unit";"Observer";"Robotics Facility";108;1
"Unit";"Stalker";"Gateway";111;2
"Unit";"Stalker";"Gateway";111;2
"Unit";"Stalker";"Gateway";111;2
"Unit";"Stalker";"Gateway";111;2
"Unit";"Stalker";"Gateway";111;2
"Unit";"Zealot";"Gateway";111;2
"Unit";"Zealot";"Gateway";121;2
"Unit";"Zealot";"Gateway";125;2
"Unit";"Zealot";"Gateway";125;2
"Unit";"Zealot";"Gateway";125;2
"Unit";"Zealot";"Gateway";125;2
"Unit";"Zealot";"Gateway";125;2
"Unit";"Zealot";"Gateway";125;2
"Unit";"Zealot";"Gateway";125;2
"Unit";"Zealot";"Gateway";125;2
"Building";"Assimilator";NA;125;0
"Building";"Pylon";NA;125;0
"Building";"Assimilator";NA;125;0
"Unit";"Zealot";"Gateway";144;2
"Unit";"Zealot";"Gateway";144;2
"Unit";"Zealot";"Gateway";144;2
"Unit";"Zealot";"Gateway";144;2
"Unit";"Zealot";"Gateway";144;2
"Unit";"Zealot";"Gateway";144;2
"Unit";"Zealot";"Gateway";144;2
"Unit";"Zealot";"Gateway";144;2
"Unit";"Immortal";"Robotics Facility";144;4
"Unit";"Sentry";"Gateway";164;2
"Unit";"Sentry";"Gateway";164;2
"Unit";"Zealot";"Gateway";164;2
"Unit";"Zealot";"Gateway";164;2
"Unit";"Zealot";"Gateway";164;2
"Unit";"Zealot";"Gateway";164;2
"Unit";"Zealot";"Gateway";164;2
"Unit";"Zealot";"Gateway";164;2
"Unit";"Sentry";"Gateway";181;2
"Unit";"Zealot";"Gateway";185;2
"Unit";"Zealot";"Gateway";185;2
"Unit";"Zealot";"Gateway";185;2
"Upgrade";"ProtossGroundArmorsLevel1";"Forge";139;0
"Building";"Pylon";NA;180;0
"Unit";"Zealot";"Gateway";191;2
"Unit";"Immortal";"Robotics Facility";180;4
"Building";"Pylon";NA;191;0
"Building";"Pylon";NA;191;0
"Building";"Pylon";NA;191;0
"Unit";"Zealot";"Gateway";200;2
"Unit";"Zealot";"Gateway";200;2
"Unit";"Zealot";"Gateway";200;2
"Unit";"Immortal";"Robotics Facility";191;4
"Unit";"Zealot";"Gateway";200;2
"Unit";"Zealot";"Gateway";200;2
"Unit";"Zealot";"Gateway";200;2
"Unit";"Zealot";"Gateway";200;2
"Building";"Nexus";NA;180;0
"Unit";"Stalker";"Gateway";219;2
"Building";"DarkShrine";NA;185;0
"Unit";"Stalker";"Gateway";221;2
"Unit";"Stalker";"Gateway";221;2
"Unit";"Stalker";"Gateway";221;2
"Unit";"Stalker";"Gateway";221;2
"Unit";"Stalker";"Gateway";221;2
"Unit";"Stalker";"Gateway";221;2
"Unit";"Stalker";"Gateway";221;2
"Unit";"Immortal";"Robotics Facility";221;4
"Building";"DarkTemplar";NA;241;0
"Building";"DarkTemplar";NA;241;0
"Building";"DarkTemplar";NA;241;0
"Building";"DarkTemplar";NA;241;0
"Building";"DarkTemplar";NA;241;0
"Unit";"Stalker";"Gateway";241;2
"Unit";"Stalker";"Gateway";241;2
"Unit";"Stalker";"Gateway";241;2
"Upgrade";"ProtossGroundWeaponsLevel1";"Forge";200;0
"Unit";"Observer";"Robotics Facility";237;1
"Building";"DarkTemplar";NA;248;0
"Unit";"Zealot";"Gateway";248;2
"Unit";"Zealot";"Gateway";248;2
"Unit";"Zealot";"Gateway";248;2
"Unit";"Zealot";"Gateway";248;2
"Unit";"Zealot";"Gateway";248;2
"Building";"Gateway";NA;247;0
"Building";"Gateway";NA;248;0
"Building";"Gateway";NA;248;0
