"type";"unit_name";"on_building";"total_supply";"supply"
"Building";"Pylon";NA;13;0
"Building";"Assimilator";NA;16;0
"Building";"Gateway";NA;15;0
"Building";"Assimilator";NA;21;0
"Building";"CyberneticsCore";NA;20;0
"Building";"Pylon";NA;22;0
"Unit";"Adept";"Gateway";23;2
"Building";"Nexus";NA;19;0
"Unit";"Stalker";"Gateway";27;2
"Building";"RoboticsFacility";NA;25;0
"Unit";"Observer";"Robotics Facility";36;1
"Building";"Gateway";NA;31;0
"Building";"Pylon";NA;38;0
"Building";"ShieldBattery";NA;37;0
"Building";"Gateway";NA;35;0
"Unit";"Observer";"Robotics Facility";39;1
"Building";"Pylon";NA;42;0
"Unit";"Stalker";"Gateway";46;2
"Unit";"Stalker";"Gateway";46;2
"Unit";"Stalker";"Gateway";46;2
"Building";"TwilightCouncil";NA;42;0
"Building";"Assimilator";NA;53;0
"Building";"Assimilator";NA;54;0
"Unit";"Sentry";"Gateway";57;2
"Unit";"Sentry";"Gateway";57;2
"Building";"Pylon";NA;62;0
"Building";"Pylon";NA;63;0
"Unit";"Stalker";"Gateway";63;2
"Unit";"Stalker";"Gateway";63;2
"Unit";"Stalker";"Gateway";63;2
"Building";"Nexus";NA;56;0
"Unit";"Stalker";"Gateway";70;2
"Unit";"Stalker";"Gateway";70;2
"Unit";"Stalker";"Gateway";70;2
"Building";"Forge";NA;79;0
"Building";"Forge";NA;79;0
"Unit";"Stalker";"Gateway";83;2
"Unit";"Stalker";"Gateway";83;2
"Unit";"Stalker";"Gateway";83;2
"Unit";"Observer";"Robotics Facility";82;1
"Building";"TemplarArchive";NA;82;0
"Building";"Gateway";NA;79;0
"Building";"Pylon";NA;83;0
"Building";"Gateway";NA;79;0
"Unit";"Stalker";"Gateway";90;2
"Unit";"Stalker";"Gateway";90;2
"Unit";"Stalker";"Gateway";90;2
"Upgrade";"Charge";"TwilightCouncil";83;0
"Unit";"Zealot";"Gateway";96;2
"Unit";"Zealot";"Gateway";96;2
"Unit";"Zealot";"Gateway";96;2
"Unit";"Adept";"Gateway";107;2
"Unit";"Adept";"Gateway";107;2
"Unit";"Adept";"Gateway";107;2
"Unit";"Sentry";"Gateway";111;2
"Unit";"Zealot";"Gateway";113;2
"Unit";"Immortal";"Robotics Facility";96;4
"Building";"Assimilator";NA;105;0
"Building";"Assimilator";NA;105;0
"Building";"Pylon";NA;113;0
"Unit";"Adept";"Gateway";124;2
"Unit";"Adept";"Gateway";124;2
"Unit";"Adept";"Gateway";124;2
"Building";"Pylon";NA;117;0
"Building";"Gateway";NA;102;0
"Building";"Gateway";NA;102;0
"Building";"Gateway";NA;102;0
"Building";"Gateway";NA;102;0
"Building";"Gateway";NA;103;0
"Building";"Gateway";NA;105;0
"Unit";"Immortal";"Robotics Facility";105;4
"Building";"Gateway";NA;105;0
"Building";"ShieldBattery";NA;124;0
"Building";"ShieldBattery";NA;131;0
"Unit";"Stalker";"Gateway";138;2
"Unit";"Zealot";"Gateway";140;2
"Unit";"Zealot";"Gateway";140;2
"Unit";"Zealot";"Gateway";140;2
"Unit";"Zealot";"Gateway";140;2
"Unit";"Zealot";"Gateway";140;2
"Unit";"Zealot";"Gateway";140;2
"Unit";"Zealot";"Gateway";140;2
"Unit";"Zealot";"Gateway";140;2
"Unit";"Immortal";"Robotics Facility";131;4
"Building";"Nexus";NA;107;0
"Upgrade";"ProtossGroundWeaponsLevel1";"Forge";107;0
"Upgrade";"ProtossGroundArmorsLevel1";"Forge";107;0
"Unit";"Zealot";"Gateway";160;2
"Unit";"Zealot";"Gateway";160;2
"Unit";"Zealot";"Gateway";160;2
"Unit";"Zealot";"Gateway";160;2
"Unit";"Zealot";"Gateway";160;2
"Unit";"Sentry";"Gateway";170;2
"Building";"Assimilator";NA;160;0
"Building";"Assimilator";NA;160;0
"Building";"Pylon";NA;168;0
"Building";"Pylon";NA;170;0
"Building";"Pylon";NA;170;0
"Building";"HighTemplar";NA;172;0
"Building";"HighTemplar";NA;172;0
"Building";"HighTemplar";NA;172;0
"Building";"HighTemplar";NA;172;0
"Building";"HighTemplar";NA;172;0
"Unit";"Immortal";"Robotics Facility";160;4
"Building";"HighTemplar";NA;176;0
"Unit";"Archon";"High Templar";172;0
"Unit";"Archon";"High Templar";172;0
"Unit";"Zealot";"Gateway";176;2
"Unit";"Zealot";"Gateway";176;2
"Unit";"Zealot";"Gateway";176;2
"Unit";"Zealot";"Gateway";176;2
"Building";"Pylon";NA;172;0
"Building";"Pylon";NA;172;0
"Building";"HighTemplar";NA;185;0
"Unit";"Zealot";"Gateway";185;2
"Building";"HighTemplar";NA;190;0
"Unit";"Zealot";"Gateway";190;2
"Unit";"Zealot";"Gateway";190;2
"Building";"HighTemplar";NA;196;0
"Building";"HighTemplar";NA;196;0
"Building";"HighTemplar";NA;196;0
"Building";"HighTemplar";NA;196;0
"Unit";"Zealot";"Gateway";196;2
"Unit";"Zealot";"Gateway";196;2
"Unit";"Zealot";"Gateway";196;2
"Unit";"Zealot";"Gateway";196;2
"Unit";"Zealot";"Gateway";196;2
"Unit";"Zealot";"Gateway";196;2
"Unit";"Zealot";"Gateway";196;2
"Unit";"Zealot";"Gateway";196;2
"Unit";"Archon";"High Templar";212;0
"Unit";"Archon";"High Templar";212;0
"Building";"HighTemplar";NA;212;0
"Building";"HighTemplar";NA;212;0
"Unit";"Zealot";"Gateway";212;2
"Unit";"Zealot";"Gateway";212;2
"Unit";"Zealot";"Gateway";212;2
"Unit";"Zealot";"Gateway";212;2
"Unit";"Zealot";"Gateway";212;2
"Unit";"Zealot";"Gateway";212;2
"Unit";"Zealot";"Gateway";224;2
"Unit";"Zealot";"Gateway";224;2
"Unit";"Zealot";"Gateway";224;2
"Unit";"Zealot";"Gateway";224;2
"Building";"HighTemplar";NA;232;0
"Building";"HighTemplar";NA;232;0
"Building";"HighTemplar";NA;232;0
"Building";"HighTemplar";NA;232;0
"Unit";"Zealot";"Gateway";232;2
"Unit";"Zealot";"Gateway";232;2
"Unit";"Zealot";"Gateway";232;2
"Unit";"Zealot";"Gateway";232;2
"Unit";"Zealot";"Gateway";232;2
"Unit";"Zealot";"Gateway";232;2
"Unit";"Zealot";"Gateway";232;2
"Unit";"Zealot";"Gateway";232;2
"Upgrade";"ProtossGroundArmorsLevel2";"Forge";196;0
"Building";"HighTemplar";NA;248;0
"Building";"HighTemplar";NA;248;0
"Building";"HighTemplar";NA;248;0
"Building";"HighTemplar";NA;248;0
"Building";"Pylon";NA;248;0
"Unit";"Zealot";"Gateway";248;2
"Unit";"Zealot";"Gateway";248;2
"Unit";"Archon";"High Templar";252;0
"Unit";"Archon";"High Templar";252;0
"Unit";"Archon";"High Templar";252;0
"Unit";"Archon";"High Templar";252;0
"Building";"Pylon";NA;252;0
"Unit";"Zealot";"Gateway";252;2
"Unit";"Zealot";"Gateway";252;2
"Unit";"Zealot";"Gateway";252;2
"Unit";"Zealot";"Gateway";252;2
"Unit";"Zealot";"Gateway";252;2
"Unit";"Zealot";"Gateway";252;2
"Unit";"Zealot";"Gateway";252;2
"Unit";"Zealot";"Gateway";252;2
"Building";"HighTemplar";NA;252;0
"Building";"HighTemplar";NA;252;0
"Building";"HighTemplar";NA;252;0
"Building";"HighTemplar";NA;268;0
"Unit";"Archon";"High Templar";268;0
"Unit";"Archon";"High Templar";268;0
"Building";"Nexus";NA;248;0
"Building";"Assimilator";NA;268;0
"Building";"Pylon";NA;268;0
"Building";"Assimilator";NA;268;0
"Unit";"Zealot";"Gateway";268;2
"Unit";"Zealot";"Gateway";268;2
"Unit";"Zealot";"Gateway";268;2
"Unit";"Zealot";"Gateway";268;2
"Building";"HighTemplar";NA;276;0
"Building";"HighTemplar";NA;276;0
"Building";"HighTemplar";NA;276;0
"Building";"HighTemplar";NA;276;0
"Unit";"Zealot";"Gateway";276;2
"Unit";"Zealot";"Gateway";276;2
"Unit";"Zealot";"Gateway";276;2
"Unit";"Archon";"High Templar";276;0
"Unit";"Archon";"High Templar";278;0
"Building";"HighTemplar";NA;282;0
"Building";"HighTemplar";NA;282;0
"Building";"HighTemplar";NA;282;0
"Unit";"Zealot";"Gateway";282;2
"Unit";"Zealot";"Gateway";282;2
"Unit";"Zealot";"Gateway";282;2
"Unit";"Zealot";"Gateway";282;2
"Unit";"Zealot";"Gateway";282;2
"Building";"HighTemplar";NA;292;0
"Building";"HighTemplar";NA;292;0
"Building";"HighTemplar";NA;292;0
"Unit";"Zealot";"Gateway";292;2
"Unit";"Zealot";"Gateway";292;2
"Unit";"Zealot";"Gateway";292;2
"Unit";"Zealot";"Gateway";292;2
"Unit";"Zealot";"Gateway";292;2
"Unit";"Zealot";"Gateway";292;2
"Unit";"Zealot";"Gateway";304;2
"Unit";"Zealot";"Gateway";304;2
"Unit";"Zealot";"Gateway";304;2
"Unit";"Archon";"High Templar";312;0
"Upgrade";"ProtossGroundArmorsLevel3";"Forge";268;0
"Unit";"Archon";"High Templar";312;0
"Unit";"Zealot";"Gateway";312;2
"Unit";"Zealot";"Gateway";312;2
"Unit";"Zealot";"Gateway";312;2
"Unit";"Zealot";"Gateway";312;2
"Unit";"Zealot";"Gateway";312;2
"Unit";"Zealot";"Gateway";312;2
"Unit";"Zealot";"Gateway";312;2
"Unit";"Zealot";"Gateway";312;2
"Unit";"Zealot";"Gateway";312;2
"Unit";"Zealot";"Gateway";312;2
"Building";"HighTemplar";NA;332;0
"Building";"HighTemplar";NA;332;0
"Building";"HighTemplar";NA;332;0
"Building";"HighTemplar";NA;332;0
"Building";"HighTemplar";NA;332;0
"Building";"HighTemplar";NA;332;0
"Building";"HighTemplar";NA;332;0
"Building";"HighTemplar";NA;332;0
"Unit";"Zealot";"Gateway";332;2
"Unit";"Zealot";"Gateway";332;2
"Unit";"Zealot";"Gateway";332;2
"Unit";"Zealot";"Gateway";332;2
"Unit";"Archon";"High Templar";340;0
"Unit";"Archon";"High Templar";340;0
"Unit";"Archon";"High Templar";340;0
"Unit";"Archon";"High Templar";340;0
"Unit";"Stalker";"Gateway";340;2
"Unit";"Stalker";"Gateway";340;2
"Unit";"Stalker";"Gateway";340;2
"Unit";"Stalker";"Gateway";340;2
"Unit";"Immortal";"Robotics Facility";332;4
"Unit";"Zealot";"Gateway";352;2
"Unit";"Zealot";"Gateway";352;2
"Unit";"Zealot";"Gateway";352;2
"Unit";"Zealot";"Gateway";352;2
"Unit";"Zealot";"Gateway";352;2
"Unit";"Zealot";"Gateway";352;2
"Unit";"Zealot";"Gateway";352;2
"Unit";"Zealot";"Gateway";352;2
"Building";"Pylon";NA;368;0
"Building";"HighTemplar";NA;368;0
"Building";"HighTemplar";NA;368;0
"Building";"HighTemplar";NA;368;0
"Building";"HighTemplar";NA;368;0
"Unit";"Zealot";"Gateway";368;2
"Unit";"Zealot";"Gateway";368;2
"Unit";"Zealot";"Gateway";368;2
"Unit";"Zealot";"Gateway";368;2
"Unit";"Zealot";"Gateway";368;2
"Unit";"Zealot";"Gateway";368;2
"Unit";"Zealot";"Gateway";368;2
"Unit";"Zealot";"Gateway";368;2
"Unit";"Archon";"High Templar";368;0
"Unit";"Archon";"High Templar";368;0
"Building";"HighTemplar";NA;384;0
"Building";"HighTemplar";NA;384;0
"Unit";"Zealot";"Gateway";384;2
"Unit";"Zealot";"Gateway";384;2
"Unit";"Zealot";"Gateway";384;2
"Unit";"Zealot";"Gateway";384;2
"Unit";"Zealot";"Gateway";384;2
"Unit";"Zealot";"Gateway";384;2
