"type";"unit_name";"on_building";"total_supply";"supply"
"Building";"Pylon";NA;13;0
"Building";"Assimilator";NA;16;0
"Building";"Gateway";NA;15;0
"Building";"Assimilator";NA;19;0
"Building";"CyberneticsCore";NA;19;0
"Building";"Pylon";NA;20;0
"Unit";"Adept";"Gateway";21;2
"Building";"Nexus";NA;19;0
"Building";"TwilightCouncil";NA;23;0
"Building";"ShieldBattery";NA;32;0
"Building";"Pylon";NA;35;0
"Building";"Gateway";NA;31;0
"Building";"Gateway";NA;32;0
"Unit";"Stalker";"Gateway";34;2
"Building";"Assimilator";NA;37;0
"Unit";"Stalker";"Gateway";42;2
"Unit";"Stalker";"Gateway";42;2
"Unit";"Stalker";"Gateway";42;2
"Building";"Pylon";NA;49;0
"Unit";"Stalker";"Gateway";52;2
"Unit";"Stalker";"Gateway";54;2
"Unit";"Stalker";"Gateway";58;2
"Building";"Pylon";NA;52;0
"Unit";"Sentry";"Gateway";62;2
"Unit";"Sentry";"Gateway";64;2
"Building";"Pylon";NA;62;0
"Unit";"Sentry";"Gateway";66;2
"Building";"Assimilator";NA;62;0
"Building";"Nexus";NA;52;0
"Building";"RoboticsFacility";NA;64;0
"Unit";"Adept";"Gateway";80;2
"Building";"Pylon";NA;76;0
"Unit";"Adept";"Gateway";80;2
"Unit";"Observer";"Robotics Facility";76;1
"Building";"Forge";NA;74;0
"Unit";"Adept";"Gateway";87;2
"Building";"Gateway";NA;72;0
"Building";"TemplarArchive";NA;74;0
"Building";"Gateway";NA;72;0
"Building";"ShieldBattery";NA;77;0
"Building";"ShieldBattery";NA;79;0
"Unit";"Stalker";"Gateway";93;2
"Unit";"Stalker";"Gateway";93;2
"Unit";"Stalker";"Gateway";93;2
"Unit";"Stalker";"Gateway";93;2
"Unit";"Stalker";"Gateway";93;2
"Unit";"Observer";"Robotics Facility";90;1
"Building";"Pylon";NA;103;0
"Unit";"Phoenix";"Stargate";101;2
"Building";"Assimilator";NA;104;0
"Building";"Assimilator";NA;104;0
"Building";"Pylon";NA;105;0
"Building";"Pylon";NA;106;0
"Unit";"Stalker";"Gateway";111;2
"Unit";"Stalker";"Gateway";111;2
"Building";"Pylon";NA;106;0
"Unit";"Adept";"Gateway";111;2
"Unit";"Adept";"Gateway";111;2
"Unit";"Adept";"Gateway";111;2
"Unit";"Observer";"Robotics Facility";106;1
"Building";"Pylon";NA;106;0
"Unit";"Adept";"Gateway";125;2
"Unit";"Adept";"Gateway";125;2
"Unit";"Adept";"Gateway";125;2
"Building";"HighTemplar";NA;131;0
"Building";"HighTemplar";NA;131;0
"Unit";"Zealot";"Gateway";131;2
"Unit";"Zealot";"Gateway";131;2
"Unit";"Zealot";"Gateway";131;2
"Building";"Pylon";NA;140;0
"Building";"Pylon";NA;140;0
"Upgrade";"ProtossGroundWeaponsLevel1";"Forge";108;0
"Unit";"Immortal";"Robotics Facility";131;4
"Building";"HighTemplar";NA;140;0
"Building";"HighTemplar";NA;140;0
"Building";"HighTemplar";NA;140;0
"Unit";"Adept";"Gateway";140;2
"Unit";"Adept";"Gateway";140;2
"Building";"Gateway";NA;131;0
"Building";"Gateway";NA;131;0
"Building";"RoboticsFacility";NA;131;0
"Building";"Gateway";NA;131;0
"Building";"Gateway";NA;131;0
"Building";"Pylon";NA;140;0
"Unit";"Adept";"Gateway";148;2
"Unit";"Adept";"Gateway";148;2
"Unit";"Adept";"Gateway";148;2
"Building";"Forge";NA;140;0
"Building";"Assimilator";NA;148;0
"Building";"Assimilator";NA;148;0
"Building";"Pylon";NA;148;0
"Unit";"Adept";"Gateway";154;2
"Unit";"Adept";"Gateway";154;2
"Unit";"Adept";"Gateway";154;2
"Unit";"Adept";"Gateway";154;2
"Unit";"Adept";"Gateway";154;2
"Unit";"Adept";"Gateway";154;2
"Unit";"Immortal";"Robotics Facility";140;4
"Unit";"Immortal";"Robotics Facility";140;4
"Building";"Nexus";NA;140;0
"Building";"HighTemplar";NA;178;0
"Building";"HighTemplar";NA;178;0
"Building";"HighTemplar";NA;181;0
"Unit";"Sentry";"Gateway";181;2
"Unit";"Sentry";"Gateway";181;2
"Unit";"Zealot";"Gateway";181;2
"Unit";"Zealot";"Gateway";181;2
"Unit";"Immortal";"Robotics Facility";174;4
"Unit";"Zealot";"Gateway";181;2
"Unit";"Immortal";"Robotics Facility";174;4
"Building";"ShieldBattery";NA;181;0
"Building";"PhotonCannon";NA;181;0
"Building";"PhotonCannon";NA;181;0
"Upgrade";"ProtossGroundArmorsLevel1";"Forge";154;0
"Building";"Pylon";NA;199;0
"Building";"Pylon";NA;199;0
"Building";"HighTemplar";NA;199;0
"Unit";"Zealot";"Gateway";199;2
"Unit";"Zealot";"Gateway";199;2
"Unit";"Zealot";"Gateway";199;2
"Unit";"Stalker";"Gateway";199;2
"Unit";"Stalker";"Gateway";199;2
"Unit";"Stalker";"Gateway";199;2
"Unit";"Zealot";"Gateway";211;2
"Unit";"Zealot";"Gateway";211;2
"Unit";"Immortal";"Robotics Facility";199;4
"Unit";"Stalker";"Gateway";219;2
"Unit";"Stalker";"Gateway";219;2
"Unit";"Stalker";"Gateway";219;2
"Unit";"Stalker";"Gateway";219;2
"Upgrade";"ProtossGroundWeaponsLevel2";"Forge";177;0
"Building";"RoboticsBay";NA;199;0
"Unit";"Zealot";"Gateway";227;2
"Unit";"Zealot";"Gateway";227;2
"Building";"Pylon";NA;219;0
"Unit";"Zealot";"Gateway";227;2
"Building";"Pylon";NA;219;0
"Upgrade";"Charge";"TwilightCouncil";199;0
"Unit";"Zealot";"Gateway";233;2
"Unit";"Zealot";"Gateway";233;2
"Unit";"Zealot";"Gateway";233;2
"Unit";"Zealot";"Gateway";233;2
"Unit";"Phoenix";"Stargate";233;2
"Unit";"Zealot";"Gateway";243;2
"Unit";"Zealot";"Gateway";243;2
"Unit";"Zealot";"Gateway";243;2
"Building";"Nexus";NA;219;0
"Building";"HighTemplar";NA;249;0
"Building";"HighTemplar";NA;249;0
"Building";"HighTemplar";NA;249;0
"Building";"HighTemplar";NA;249;0
"Building";"HighTemplar";NA;249;0
"Building";"HighTemplar";NA;249;0
"Unit";"Stalker";"Gateway";249;2
"Unit";"Stalker";"Gateway";249;2
"Unit";"Stalker";"Gateway";249;2
"Unit";"Archon";"High Templar";249;0
"Unit";"Archon";"High Templar";249;0
"Unit";"Archon";"High Templar";249;0
"Upgrade";"ProtossGroundArmorsLevel2";"Forge";219;0
"Unit";"Colossus";"Robotics Facility";233;6
"Unit";"Colossus";"Robotics Facility";233;6
"Upgrade";"ExtendedThermalLance";"RoboticsBay";233;0
"Building";"DarkShrine";NA;241;0
"Building";"Assimilator";NA;255;0
"Building";"Assimilator";NA;255;0
"Building";"ShieldBattery";NA;267;0
"Building";"PhotonCannon";NA;267;0
"Building";"PhotonCannon";NA;267;0
"Building";"ShieldBattery";NA;267;0
"Unit";"Archon";"High Templar";267;0
"Unit";"Zealot";"Gateway";267;2
"Unit";"Zealot";"Gateway";267;2
"Unit";"Zealot";"Gateway";267;2
"Unit";"Zealot";"Gateway";267;2
"Unit";"Zealot";"Gateway";267;2
"Unit";"Zealot";"Gateway";267;2
"Unit";"Zealot";"Gateway";267;2
"Unit";"Zealot";"Gateway";267;2
"Unit";"Zealot";"Gateway";267;2
"Upgrade";"ProtossGroundWeaponsLevel3";"Forge";241;0
