"type";"unit_name";"on_building";"total_supply";"supply"
"Building";"Pylon";NA;13;0
"Building";"Assimilator";NA;16;0
"Building";"Gateway";NA;15;0
"Building";"Assimilator";NA;20;0
"Building";"CyberneticsCore";NA;20;0
"Building";"Pylon";NA;21;0
"Unit";"Adept";"Gateway";22;2
"Building";"Nexus";NA;19;0
"Unit";"Adept";"Gateway";24;2
"Building";"TwilightCouncil";NA;23;0
"Building";"ShieldBattery";NA;33;0
"Unit";"Adept";"Gateway";33;2
"Building";"Gateway";NA;35;0
"Building";"Pylon";NA;44;0
"Building";"DarkShrine";NA;33;0
"Building";"Gateway";NA;37;0
"Building";"DarkTemplar";NA;46;0
"Building";"DarkTemplar";NA;46;0
"Building";"Pylon";NA;46;0
"Building";"DarkTemplar";NA;49;0
"Building";"Pylon";NA;50;0
"Building";"Pylon";NA;52;0
"Building";"Assimilator";NA;51;0
"Building";"Nexus";NA;46;0
"Building";"Assimilator";NA;52;0
"Building";"Pylon";NA;52;0
"Unit";"Stalker";"Gateway";54;2
"Unit";"Stalker";"Gateway";54;2
"Unit";"Stalker";"Gateway";54;2
"Building";"Forge";NA;51;0
"Building";"Forge";NA;51;0
"Building";"Pylon";NA;52;0
"Building";"DarkTemplar";NA;66;0
"Unit";"Sentry";"Gateway";66;2
"Unit";"Stalker";"Gateway";71;2
"Building";"Pylon";NA;78;0
"Building";"Gateway";NA;73;0
"Building";"Gateway";NA;73;0
"Unit";"Stalker";"Gateway";82;2
"Unit";"Stalker";"Gateway";82;2
"Unit";"Stalker";"Gateway";82;2
"Building";"Gateway";NA;73;0
"Building";"RoboticsFacility";NA;76;0
"Upgrade";"ProtossGroundWeaponsLevel1";"Forge";68;0
"Building";"DarkTemplar";NA;95;0
"Upgrade";"ProtossGroundArmorsLevel1";"Forge";71;0
"Unit";"Observer";"Robotics Facility";94;1
"Building";"Pylon";NA;98;0
"Building";"Pylon";NA;98;0
"Building";"RoboticsBay";NA;94;0
"Upgrade";"Charge";"TwilightCouncil";82;0
"Building";"Pylon";NA;105;0
"Unit";"Stalker";"Gateway";110;2
"Unit";"Stalker";"Gateway";110;2
"Unit";"Stalker";"Gateway";110;2
"Building";"Assimilator";NA;108;0
"Building";"Assimilator";NA;109;0
"Building";"Pylon";NA;118;0
"Unit";"Stalker";"Gateway";118;2
"Unit";"Stalker";"Gateway";118;2
"Unit";"Stalker";"Gateway";118;2
"Unit";"Stalker";"Gateway";118;2
"Unit";"Stalker";"Gateway";118;2
"Building";"Pylon";NA;118;0
"Unit";"Stalker";"Gateway";118;2
"Unit";"Disruptor";"Robotics Facility";118;3
"Building";"Pylon";NA;118;0
"Unit";"Zealot";"Gateway";133;2
"Unit";"Zealot";"Gateway";133;2
"Unit";"Zealot";"Gateway";133;2
"Unit";"Zealot";"Gateway";133;2
"Unit";"Zealot";"Gateway";133;2
"Unit";"Zealot";"Gateway";133;2
"Building";"Gateway";NA;128;0
"Unit";"Stalker";"Gateway";145;2
"Unit";"Stalker";"Gateway";145;2
"Unit";"Stalker";"Gateway";145;2
"Unit";"Stalker";"Gateway";145;2
"Unit";"Stalker";"Gateway";145;2
"Unit";"Stalker";"Gateway";145;2
"Building";"Gateway";NA;130;0
"Upgrade";"ProtossGroundWeaponsLevel2";"Forge";110;0
"Unit";"Disruptor";"Robotics Facility";133;3
"Building";"Pylon";NA;157;0
"Upgrade";"ProtossGroundArmorsLevel2";"Forge";118;0
"Building";"Pylon";NA;157;0
"Unit";"Stalker";"Gateway";160;2
"Unit";"Stalker";"Gateway";160;2
"Unit";"Stalker";"Gateway";160;2
"Unit";"Stalker";"Gateway";160;2
"Unit";"Stalker";"Gateway";160;2
"Unit";"Zealot";"Gateway";160;2
"Building";"RoboticsFacility";NA;145;0
"Unit";"Disruptor";"Robotics Facility";157;3
"Unit";"Stalker";"Gateway";170;2
"Building";"DarkTemplar";NA;177;0
"Building";"Nexus";NA;157;0
"Building";"Pylon";NA;177;0
"Building";"DarkTemplar";NA;177;0
"Building";"Pylon";NA;177;0
"Unit";"Stalker";"Gateway";177;2
"Unit";"Stalker";"Gateway";177;2
"Unit";"Stalker";"Gateway";177;2
"Unit";"Stalker";"Gateway";177;2
"Unit";"Stalker";"Gateway";189;2
"Unit";"Stalker";"Gateway";189;2
"Building";"PhotonCannon";NA;177;0
"Building";"ShieldBattery";NA;177;0
"Building";"DarkTemplar";NA;193;0
"Building";"DarkTemplar";NA;193;0
"Unit";"Disruptor";"Robotics Facility";177;3
"Unit";"Stalker";"Gateway";193;2
"Unit";"Stalker";"Gateway";193;2
"Unit";"Stalker";"Gateway";193;2
"Building";"RoboticsFacility";NA;177;0
"Unit";"Stalker";"Gateway";202;2
"Unit";"Stalker";"Gateway";202;2
"Unit";"Disruptor";"Robotics Facility";193;3
"Building";"Pylon";NA;202;0
"Upgrade";"ProtossGroundWeaponsLevel3";"Forge";177;0
"Upgrade";"ProtossGroundArmorsLevel3";"Forge";177;0
"Building";"DarkTemplar";NA;212;0
"Building";"DarkTemplar";NA;212;0
"Unit";"Zealot";"Gateway";212;2
"Unit";"Zealot";"Gateway";212;2
"Unit";"Zealot";"Gateway";212;2
"Unit";"Zealot";"Gateway";212;2
"Unit";"Zealot";"Gateway";212;2
"Building";"Assimilator";NA;209;0
"Building";"Assimilator";NA;209;0
"Unit";"Disruptor";"Robotics Facility";206;3
"Unit";"Disruptor";"Robotics Facility";206;3
"Unit";"Stalker";"Gateway";230;2
"Unit";"Stalker";"Gateway";230;2
"Unit";"Stalker";"Gateway";230;2
"Unit";"Stalker";"Gateway";230;2
"Unit";"Stalker";"Gateway";230;2
"Unit";"Stalker";"Gateway";230;2
"Unit";"Zealot";"Gateway";248;2
"Unit";"Disruptor";"Robotics Facility";242;3
"Unit";"Disruptor";"Robotics Facility";242;3
"Building";"Assimilator";NA;245;0
"Building";"Gateway";NA;242;0
"Building";"Pylon";NA;256;0
"Building";"Gateway";NA;242;0
"Building";"DarkTemplar";NA;256;0
"Building";"Pylon";NA;256;0
"Building";"Pylon";NA;256;0
"Building";"Pylon";NA;256;0
"Building";"DarkTemplar";NA;256;0
"Building";"DarkTemplar";NA;256;0
"Unit";"Colossus";"Robotics Facility";256;6
"Unit";"Colossus";"Robotics Facility";256;6
"Building";"Nexus";NA;256;0
"Building";"Pylon";NA;266;0
"Unit";"Disruptor";"Robotics Facility";258;3
"Upgrade";"ExtendedThermalLance";"RoboticsBay";256;0
"Building";"DarkTemplar";NA;278;0
"Unit";"Disruptor";"Robotics Facility";266;3
"Building";"DarkTemplar";NA;278;0
"Building";"DarkTemplar";NA;278;0
"Building";"DarkTemplar";NA;278;0
"Building";"DarkTemplar";NA;278;0
"Building";"DarkTemplar";NA;278;0
"Building";"DarkTemplar";NA;278;0
"Unit";"Disruptor";"Robotics Facility";275;3
"Unit";"Zealot";"Gateway";281;2
"Unit";"Zealot";"Gateway";281;2
"Unit";"Disruptor";"Robotics Facility";278;3
"Building";"DarkTemplar";NA;288;0
"Unit";"Stalker";"Gateway";291;2
"Unit";"Stalker";"Gateway";291;2
"Unit";"Stalker";"Gateway";291;2
"Unit";"Stalker";"Gateway";291;2
"Unit";"Stalker";"Gateway";291;2
"Unit";"Stalker";"Gateway";291;2
"Building";"Assimilator";NA;288;0
"Building";"Assimilator";NA;291;0
"Building";"Pylon";NA;303;0
"Building";"Pylon";NA;303;0
"Unit";"Zealot";"Gateway";303;2
"Unit";"Zealot";"Gateway";303;2
"Unit";"Zealot";"Gateway";303;2
"Unit";"Zealot";"Gateway";303;2
"Unit";"Zealot";"Gateway";303;2
"Unit";"Zealot";"Gateway";303;2
"Unit";"Zealot";"Gateway";303;2
"Unit";"Zealot";"Gateway";303;2
"Building";"DarkTemplar";NA;303;0
"Building";"DarkTemplar";NA;319;0
"Building";"DarkTemplar";NA;319;0
"Building";"DarkTemplar";NA;319;0
"Unit";"Zealot";"Gateway";319;2
"Unit";"Zealot";"Gateway";319;2
"Unit";"Zealot";"Gateway";319;2
"Building";"PhotonCannon";NA;319;0
"Unit";"Zealot";"Gateway";319;2
"Unit";"Zealot";"Gateway";319;2
"Unit";"Zealot";"Gateway";319;2
"Building";"Pylon";NA;319;0
"Building";"PhotonCannon";NA;319;0
"Building";"ShieldBattery";NA;319;0
"Unit";"Colossus";"Robotics Facility";303;6
"Unit";"Colossus";"Robotics Facility";303;6
"Building";"PhotonCannon";NA;319;0
"Building";"ShieldBattery";NA;319;0
"Building";"PhotonCannon";NA;319;0
"Building";"Pylon";NA;343;0
"Building";"Pylon";NA;343;0
"Unit";"Archon";"High Templar";343;0
"Unit";"Archon";"High Templar";343;0
"Unit";"Archon";"High Templar";343;0
"Building";"Gateway";NA;343;0
"Unit";"Archon";"High Templar";343;0
"Unit";"Archon";"High Templar";343;0
"Unit";"Archon";"High Templar";343;0
"Building";"Pylon";NA;343;0
"Building";"Gateway";NA;343;0
"Building";"Gateway";NA;343;0
"Building";"Pylon";NA;343;0
