"type";"unit_name";"on_building";"total_supply";"supply"
"Building";"Pylon";NA;14;0
"Building";"Assimilator";NA;15;0
"Building";"Gateway";NA;15;0
"Building";"Assimilator";NA;20;0
"Building";"Pylon";NA;21;0
"Building";"CyberneticsCore";NA;20;0
"Unit";"Adept";"Gateway";21;2
"Building";"Nexus";NA;19;0
"Unit";"Adept";"Gateway";22;2
"Building";"Stargate";NA;22;0
"Building";"Pylon";NA;26;0
"Unit";"Oracle";"Stargate";27;3
"Building";"Gateway";NA;31;0
"Building";"Pylon";NA;40;0
"Building";"Gateway";NA;32;0
"Unit";"Oracle";"Stargate";34;3
"Unit";"Stalker";"Gateway";41;2
"Building";"Assimilator";NA;47;0
"Building";"Pylon";NA;48;0
"Unit";"Phoenix";"Stargate";48;2
"Unit";"Stalker";"Gateway";52;2
"Building";"Assimilator";NA;52;0
"Building";"TwilightCouncil";NA;48;0
"Unit";"Stalker";"Gateway";61;2
"Unit";"Stalker";"Gateway";61;2
"Building";"Forge";NA;58;0
"Building";"Nexus";NA;48;0
"Unit";"Stalker";"Gateway";67;2
"Unit";"Stalker";"Gateway";71;2
"Unit";"Stalker";"Gateway";71;2
"Building";"ShieldBattery";NA;67;0
"Building";"ShieldBattery";NA;67;0
"Unit";"Stalker";"Gateway";75;2
"Unit";"Sentry";"Gateway";85;2
"Unit";"Oracle";"Stargate";83;3
"Building";"Pylon";NA;84;0
"Building";"Forge";NA;83;0
"Building";"Pylon";NA;87;0
"Unit";"Zealot";"Gateway";96;2
"Unit";"Zealot";"Gateway";96;2
"Unit";"Zealot";"Gateway";96;2
"Building";"RoboticsFacility";NA;83;0
"Building";"Assimilator";NA;98;0
"Building";"Pylon";NA;102;0
"Unit";"Zealot";"Gateway";106;2
"Unit";"Zealot";"Gateway";106;2
"Building";"Pylon";NA;103;0
"Unit";"Zealot";"Gateway";106;2
"Building";"Gateway";NA;93;0
"Building";"Gateway";NA;93;0
"Upgrade";"ProtossGroundWeaponsLevel1";"Forge";83;0
"Unit";"Observer";"Robotics Facility";107;1
"Building";"Pylon";NA;116;0
"Building";"Assimilator";NA;115;0
"Unit";"Zealot";"Gateway";118;2
"Unit";"Zealot";"Gateway";118;2
"Unit";"Zealot";"Gateway";118;2
"Unit";"Zealot";"Gateway";118;2
"Unit";"Zealot";"Gateway";118;2
"Building";"Gateway";NA;115;0
"Building";"Pylon";NA;128;0
"Unit";"Stalker";"Gateway";130;2
"Building";"RoboticsBay";NA;115;0
"Unit";"Stalker";"Gateway";130;2
"Unit";"Stalker";"Gateway";130;2
"Building";"Pylon";NA;130;0
"Upgrade";"Charge";"TwilightCouncil";104;0
"Unit";"Stalker";"Gateway";137;2
"Unit";"Stalker";"Gateway";137;2
"Unit";"Stalker";"Gateway";137;2
"Building";"Pylon";NA;137;0
"Upgrade";"ProtossGroundArmorsLevel1";"Forge";106;0
"Unit";"Immortal";"Robotics Facility";130;4
"Unit";"Zealot";"Gateway";143;2
"Unit";"Zealot";"Gateway";143;2
"Unit";"Zealot";"Gateway";143;2
"Building";"RoboticsFacility";NA;128;0
"Unit";"Stalker";"Gateway";153;2
"Unit";"Stalker";"Gateway";153;2
"Unit";"Stalker";"Gateway";153;2
"Unit";"Zealot";"Gateway";159;2
"Building";"Pylon";NA;153;0
"Building";"Pylon";NA;159;0
"Building";"Pylon";NA;159;0
"Unit";"Colossus";"Robotics Facility";137;6
"Unit";"Sentry";"Gateway";167;2
"Unit";"Sentry";"Gateway";167;2
"Unit";"Zealot";"Gateway";167;2
"Unit";"Zealot";"Gateway";167;2
"Unit";"Zealot";"Gateway";167;2
"Building";"Gateway";NA;153;0
"Building";"Gateway";NA;153;0
"Upgrade";"ProtossGroundWeaponsLevel2";"Forge";130;0
"Unit";"Zealot";"Gateway";177;2
"Upgrade";"ExtendedThermalLance";"RoboticsBay";143;0
"Building";"Pylon";NA;177;0
"Unit";"Stalker";"Gateway";179;2
"Unit";"Stalker";"Gateway";179;2
"Unit";"Stalker";"Gateway";179;2
"Unit";"Stalker";"Gateway";179;2
"Unit";"Colossus";"Robotics Facility";159;6
"Unit";"Stalker";"Gateway";193;2
"Unit";"Stalker";"Gateway";193;2
"Building";"Pylon";NA;187;0
"Unit";"Sentry";"Gateway";193;2
"Unit";"Sentry";"Gateway";193;2
"Unit";"Stalker";"Gateway";197;2
"Building";"Assimilator";NA;193;0
"Unit";"Stalker";"Gateway";203;2
"Unit";"Stalker";"Gateway";203;2
"Building";"TemplarArchive";NA;187;0
"Building";"Assimilator";NA;193;0
"Unit";"Colossus";"Robotics Facility";179;6
"Building";"Nexus";NA;177;0
"Upgrade";"ProtossGroundArmorsLevel2";"Forge";161;0
"Unit";"Stalker";"Gateway";213;2
"Unit";"Stalker";"Gateway";213;2
"Unit";"Stalker";"Gateway";213;2
"Unit";"Stalker";"Gateway";213;2
"Unit";"Stalker";"Gateway";213;2
"Unit";"Stalker";"Gateway";213;2
"Building";"HighTemplar";NA;225;0
"Building";"HighTemplar";NA;225;0
"Unit";"Zealot";"Gateway";227;2
"Unit";"Zealot";"Gateway";227;2
"Unit";"Zealot";"Gateway";227;2
"Unit";"Zealot";"Gateway";227;2
"Unit";"Zealot";"Gateway";227;2
"Building";"Pylon";NA;226;0
"Building";"Pylon";NA;226;0
"Unit";"Stalker";"Gateway";237;2
"Building";"PhotonCannon";NA;226;0
"Upgrade";"ProtossGroundWeaponsLevel3";"Forge";187;0
"Unit";"Stalker";"Gateway";239;2
"Unit";"Stalker";"Gateway";239;2
"Building";"ShieldBattery";NA;227;0
"Unit";"Stalker";"Gateway";243;2
"Unit";"Stalker";"Gateway";243;2
"Unit";"Stalker";"Gateway";243;2
"Unit";"Stalker";"Gateway";243;2
"Unit";"Zealot";"Gateway";251;2
"Unit";"Zealot";"Gateway";251;2
"Unit";"Zealot";"Gateway";251;2
"Unit";"Zealot";"Gateway";251;2
"Building";"HighTemplar";NA;262;0
"Building";"HighTemplar";NA;262;0
"Building";"HighTemplar";NA;262;0
"Building";"HighTemplar";NA;262;0
"Building";"Pylon";NA;259;0
"Building";"Pylon";NA;259;0
"Unit";"Zealot";"Gateway";262;2
"Unit";"Zealot";"Gateway";262;2
"Unit";"Sentry";"Gateway";262;2
"Unit";"Sentry";"Gateway";262;2
"Building";"Nexus";NA;243;0
"Unit";"Zealot";"Gateway";276;2
"Unit";"Zealot";"Gateway";276;2
"Unit";"Zealot";"Gateway";276;2
"Unit";"Zealot";"Gateway";276;2
"Unit";"Zealot";"Gateway";276;2
"Upgrade";"ProtossGroundArmorsLevel3";"Forge";239;0
"Unit";"Zealot";"Gateway";289;2
"Unit";"Zealot";"Gateway";289;2
"Unit";"Stalker";"Gateway";289;2
"Unit";"Stalker";"Gateway";289;2
"Unit";"Stalker";"Gateway";289;2
"Upgrade";"ProtossShieldsLevel1";"Forge";259;0
"Unit";"Zealot";"Gateway";299;2
"Unit";"Zealot";"Gateway";299;2
"Unit";"Zealot";"Gateway";299;2
"Building";"HighTemplar";NA;305;0
"Building";"HighTemplar";NA;305;0
"Building";"HighTemplar";NA;305;0
"Building";"HighTemplar";NA;305;0
"Unit";"Zealot";"Gateway";305;2
"Unit";"Zealot";"Gateway";305;2
"Unit";"Zealot";"Gateway";305;2
"Unit";"Zealot";"Gateway";305;2
"Unit";"Zealot";"Gateway";313;2
"Unit";"Archon";"High Templar";313;0
"Unit";"Archon";"High Templar";313;0
"Unit";"Zealot";"Gateway";315;2
"Unit";"Zealot";"Gateway";315;2
"Unit";"Zealot";"Gateway";315;2
"Unit";"Zealot";"Gateway";315;2
"Unit";"Zealot";"Gateway";315;2
"Unit";"Zealot";"Gateway";315;2
"Unit";"Zealot";"Gateway";327;2
"Unit";"Zealot";"Gateway";327;2
"Unit";"Zealot";"Gateway";327;2
"Building";"HighTemplar";NA;333;0
"Building";"HighTemplar";NA;333;0
"Building";"HighTemplar";NA;333;0
"Building";"HighTemplar";NA;333;0
"Building";"HighTemplar";NA;333;0
"Unit";"Colossus";"Robotics Facility";315;6
"Unit";"Archon";"High Templar";333;0
"Unit";"Archon";"High Templar";333;0
"Unit";"Colossus";"Robotics Facility";315;6
"Building";"HighTemplar";NA;339;0
"Building";"HighTemplar";NA;339;0
"Building";"HighTemplar";NA;339;0
"Unit";"Archon";"High Templar";345;0
"Unit";"Stalker";"Gateway";345;2
"Unit";"Stalker";"Gateway";345;2
"Unit";"Stalker";"Gateway";345;2
"Unit";"Stalker";"Gateway";345;2
"Unit";"Zealot";"Gateway";353;2
"Building";"Nexus";NA;327;0
"Unit";"Zealot";"Gateway";355;2
"Unit";"Zealot";"Gateway";355;2
"Unit";"Zealot";"Gateway";355;2
"Unit";"Zealot";"Gateway";355;2
"Unit";"Zealot";"Gateway";355;2
"Unit";"Zealot";"Gateway";355;2
"Upgrade";"ProtossShieldsLevel2";"Forge";315;0
"Building";"Gateway";NA;345;0
"Building";"Gateway";NA;345;0
"Building";"Gateway";NA;345;0
"Building";"Gateway";NA;347;0
"Unit";"Stalker";"Gateway";367;2
"Unit";"Stalker";"Gateway";367;2
"Building";"HighTemplar";NA;372;0
"Building";"HighTemplar";NA;372;0
"Building";"HighTemplar";NA;372;0
"Building";"HighTemplar";NA;372;0
"Building";"Pylon";NA;367;0
"Unit";"Sentry";"Gateway";373;2
"Unit";"Sentry";"Gateway";373;2
"Unit";"Archon";"High Templar";373;0
"Unit";"Archon";"High Templar";373;0
"Building";"Assimilator";NA;368;0
"Building";"Assimilator";NA;368;0
"Unit";"Zealot";"Gateway";377;2
"Unit";"Zealot";"Gateway";377;2
"Unit";"Oracle";"Stargate";367;3
"Unit";"Zealot";"Gateway";387;2
"Unit";"Zealot";"Gateway";387;2
"Unit";"Zealot";"Gateway";387;2
"Unit";"Zealot";"Gateway";387;2
"Unit";"Zealot";"Gateway";387;2
"Building";"FleetBeacon";NA;368;0
"Unit";"Zealot";"Gateway";387;2
"Unit";"Zealot";"Gateway";387;2
"Unit";"Zealot";"Gateway";387;2
"Building";"Pylon";NA;384;0
"Building";"Pylon";NA;387;0
"Unit";"Stalker";"Gateway";403;2
"Unit";"Stalker";"Gateway";403;2
"Unit";"Stalker";"Gateway";403;2
"Unit";"Zealot";"Gateway";409;2
"Unit";"Zealot";"Gateway";409;2
"Unit";"Stalker";"Gateway";413;2
"Unit";"Zealot";"Gateway";413;2
"Unit";"Zealot";"Gateway";415;2
"Unit";"Stalker";"Gateway";419;2
"Unit";"Stalker";"Gateway";419;2
"Unit";"Stalker";"Gateway";419;2
"Unit";"Zealot";"Gateway";419;2
"Unit";"Zealot";"Gateway";419;2
"Unit";"Zealot";"Gateway";419;2
"Unit";"Zealot";"Gateway";419;2
"Building";"HighTemplar";NA;433;0
"Building";"HighTemplar";NA;433;0
"Building";"HighTemplar";NA;433;0
"Building";"HighTemplar";NA;433;0
"Unit";"Sentry";"Gateway";433;2
"Unit";"Archon";"High Templar";433;0
"Unit";"Archon";"High Templar";433;0
"Unit";"Stalker";"Gateway";435;2
"Unit";"Stalker";"Gateway";435;2
"Unit";"Stalker";"Gateway";435;2
"Unit";"Stalker";"Gateway";435;2
"Unit";"Stalker";"Gateway";435;2
"Building";"HighTemplar";NA;445;0
"Building";"HighTemplar";NA;445;0
"Building";"HighTemplar";NA;445;0
"Building";"HighTemplar";NA;445;0
"Unit";"Zealot";"Gateway";445;2
"Unit";"Zealot";"Gateway";445;2
"Unit";"Zealot";"Gateway";445;2
"Unit";"Zealot";"Gateway";445;2
"Unit";"Zealot";"Gateway";445;2
"Unit";"Zealot";"Gateway";445;2
"Unit";"Observer";"Robotics Facility";445;1
"Unit";"Observer";"Robotics Facility";445;1
"Unit";"Archon";"High Templar";453;0
"Unit";"Archon";"High Templar";455;0
"Building";"HighTemplar";NA;458;0
"Unit";"Zealot";"Gateway";459;2
"Unit";"Zealot";"Gateway";459;2
