"type";"unit_name";"on_building";"total_supply";"supply"
"Building";"Pylon";NA;13;0
"Building";"Assimilator";NA;15;0
"Building";"Gateway";NA;15;0
"Unit";"Zealot";"Gateway";20;2
"Building";"Pylon";NA;21;0
"Building";"CyberneticsCore";NA;20;0
"Building";"Assimilator";NA;23;0
"Building";"Nexus";NA;19;0
"Unit";"Stalker";"Gateway";23;2
