"type";"unit_name";"on_building";"total_supply";"supply"
"Building";"Pylon";NA;13;0
"Building";"Assimilator";NA;16;0
"Building";"Gateway";NA;15;0
"Building";"Assimilator";NA;20;0
"Building";"Pylon";NA;21;0
"Building";"CyberneticsCore";NA;20;0
"Unit";"Adept";"Gateway";22;2
"Building";"Nexus";NA;19;0
"Unit";"Stalker";"Gateway";26;2
"Building";"RoboticsFacility";NA;23;0
"Unit";"Observer";"Robotics Facility";35;1
"Building";"Pylon";NA;37;0
"Unit";"Immortal";"Robotics Facility";41;4
"Building";"Assimilator";NA;45;0
"Building";"Assimilator";NA;45;0
"Building";"Pylon";NA;45;0
"Building";"ShieldBattery";NA;44;0
"Building";"Pylon";NA;47;0
"Unit";"Sentry";"Gateway";54;2
"Building";"Gateway";NA;43;0
"Building";"Gateway";NA;43;0
"Unit";"Observer";"Robotics Facility";52;1
"Unit";"Zealot";"Gateway";60;2
"Unit";"Zealot";"Gateway";60;2
"Building";"RoboticsBay";NA;47;0
"Building";"Pylon";NA;58;0
"Unit";"Observer";"Robotics Facility";58;1
"Building";"Pylon";NA;66;0
"Unit";"Sentry";"Gateway";68;2
"Unit";"Stalker";"Gateway";68;2
"Unit";"Stalker";"Gateway";68;2
"Unit";"Colossus";"Robotics Facility";60;6
"Building";"Forge";NA;66;0
"Building";"TwilightCouncil";NA;66;0
"Building";"Pylon";NA;74;0
"Unit";"Zealot";"Gateway";84;2
"Unit";"Zealot";"Gateway";84;2
"Building";"ShieldBattery";NA;74;0
"Building";"Nexus";NA;66;0
"Building";"Pylon";NA;89;0
"Upgrade";"ExtendedThermalLance";"RoboticsBay";66;0
"Unit";"Stalker";"Gateway";90;2
"Unit";"Stalker";"Gateway";90;2
"Unit";"Stalker";"Gateway";90;2
"Unit";"Colossus";"Robotics Facility";82;6
"Building";"PhotonCannon";NA;107;0
"Building";"Pylon";NA;111;0
"Building";"Gateway";NA;99;0
"Building";"Gateway";NA;99;0
"Building";"Pylon";NA;111;0
"Building";"Assimilator";NA;111;0
"Building";"Assimilator";NA;111;0
"Building";"Gateway";NA;99;0
"Building";"ShieldBattery";NA;111;0
"Upgrade";"Charge";"TwilightCouncil";90;0
"Unit";"Stalker";"Gateway";112;2
"Unit";"Stalker";"Gateway";112;2
"Unit";"Stalker";"Gateway";112;2
"Unit";"Colossus";"Robotics Facility";99;6
"Upgrade";"ProtossGroundArmorsLevel1";"Forge";90;0
"Building";"Pylon";NA;112;0
"Unit";"Stalker";"Gateway";125;2
"Unit";"Stalker";"Gateway";125;2
"Unit";"Stalker";"Gateway";125;2
"Building";"Forge";NA;112;0
"Building";"Pylon";NA;125;0
"Unit";"Stalker";"Gateway";131;2
"Unit";"Stalker";"Gateway";131;2
"Unit";"Stalker";"Gateway";131;2
"Unit";"Stalker";"Gateway";131;2
"Unit";"Stalker";"Gateway";131;2
"Unit";"Stalker";"Gateway";131;2
"Unit";"Zealot";"Gateway";145;2
"Unit";"Zealot";"Gateway";145;2
"Unit";"Zealot";"Gateway";145;2
"Unit";"Zealot";"Gateway";145;2
"Unit";"Zealot";"Gateway";145;2
"Unit";"Zealot";"Gateway";145;2
"Building";"Pylon";NA;157;0
"Building";"Pylon";NA;157;0
"Unit";"Zealot";"Gateway";157;2
"Unit";"Zealot";"Gateway";157;2
"Unit";"Zealot";"Gateway";157;2
"Unit";"Zealot";"Gateway";157;2
"Unit";"Zealot";"Gateway";158;2
"Unit";"Zealot";"Gateway";158;2
"Upgrade";"ProtossGroundWeaponsLevel1";"Forge";131;0
"Building";"TemplarArchive";NA;157;0
"Unit";"Immortal";"Robotics Facility";157;4
"Building";"HighTemplar";NA;175;0
"Building";"HighTemplar";NA;175;0
"Building";"HighTemplar";NA;175;0
"Building";"HighTemplar";NA;175;0
"Building";"HighTemplar";NA;175;0
"Building";"HighTemplar";NA;175;0
"Building";"Nexus";NA;157;0
"Building";"ShieldBattery";NA;171;0
"Building";"PhotonCannon";NA;171;0
"Building";"PhotonCannon";NA;171;0
"Building";"ShieldBattery";NA;175;0
"Unit";"Immortal";"Robotics Facility";171;4
"Building";"Assimilator";NA;175;0
"Building";"Assimilator";NA;175;0
"Unit";"Zealot";"Gateway";179;2
"Unit";"Zealot";"Gateway";179;2
"Unit";"Zealot";"Gateway";179;2
"Unit";"Zealot";"Gateway";179;2
"Upgrade";"ProtossGroundArmorsLevel2";"Forge";157;0
"Unit";"Zealot";"Gateway";188;2
"Unit";"Zealot";"Gateway";188;2
"Unit";"Stalker";"Gateway";196;2
"Unit";"Stalker";"Gateway";196;2
"Building";"Pylon";NA;201;0
"Building";"Pylon";NA;201;0
"Upgrade";"ProtossGroundWeaponsLevel2";"Forge";175;0
"Building";"Pylon";NA;201;0
"Unit";"Zealot";"Gateway";201;2
"Unit";"Zealot";"Gateway";203;2
"Unit";"Zealot";"Gateway";203;2
"Unit";"Zealot";"Gateway";203;2
"Unit";"Zealot";"Gateway";203;2
"Unit";"Zealot";"Gateway";203;2
"Building";"Assimilator";NA;201;0
"Building";"HighTemplar";NA;216;0
"Building";"HighTemplar";NA;216;0
"Building";"HighTemplar";NA;216;0
"Unit";"Stalker";"Gateway";216;2
"Unit";"Stalker";"Gateway";216;2
"Unit";"Stalker";"Gateway";216;2
"Unit";"Immortal";"Robotics Facility";201;4
"Unit";"Archon";"High Templar";223;0
"Unit";"Stalker";"Gateway";230;2
"Unit";"Stalker";"Gateway";230;2
"Unit";"Zealot";"Gateway";234;2
"Unit";"Zealot";"Gateway";234;2
"Unit";"Zealot";"Gateway";234;2
"Unit";"Zealot";"Gateway";234;2
"Unit";"Zealot";"Gateway";234;2
"Building";"Pylon";NA;244;0
"Building";"Pylon";NA;244;0
"Upgrade";"ProtossGroundArmorsLevel3";"Forge";201;0
"Building";"PhotonCannon";NA;244;0
"Building";"ShieldBattery";NA;244;0
"Building";"HighTemplar";NA;244;0
"Building";"HighTemplar";NA;244;0
"Building";"HighTemplar";NA;244;0
"Building";"HighTemplar";NA;244;0
"Building";"HighTemplar";NA;244;0
"Building";"HighTemplar";NA;244;0
"Building";"Gateway";NA;244;0
"Building";"Gateway";NA;244;0
"Unit";"Archon";"High Templar";244;0
"Unit";"Archon";"High Templar";244;0
"Unit";"Archon";"High Templar";244;0
"Building";"Gateway";NA;244;0
"Building";"Gateway";NA;244;0
"Building";"Gateway";NA;244;0
"Building";"Gateway";NA;244;0
"Building";"Nexus";NA;244;0
"Building";"Gateway";NA;244;0
"Building";"Gateway";NA;244;0
"Building";"ShieldBattery";NA;244;0
"Building";"ShieldBattery";NA;244;0
"Building";"PhotonCannon";NA;244;0
"Building";"PhotonCannon";NA;244;0
"Unit";"Stalker";"Gateway";244;2
"Unit";"Stalker";"Gateway";244;2
"Unit";"Stalker";"Gateway";244;2
"Unit";"Stalker";"Gateway";244;2
"Unit";"Stalker";"Gateway";244;2
"Unit";"Stalker";"Gateway";244;2
"Unit";"Stalker";"Gateway";244;2
"Unit";"Stalker";"Gateway";244;2
"Unit";"Stalker";"Gateway";244;2
"Unit";"Stalker";"Gateway";244;2
"Unit";"Stalker";"Gateway";244;2
"Building";"PhotonCannon";NA;244;0
"Upgrade";"ProtossGroundWeaponsLevel3";"Forge";234;0
"Unit";"Archon";"High Templar";266;0
"Unit";"Archon";"High Templar";266;0
"Unit";"Archon";"High Templar";266;0
"Unit";"Zealot";"Gateway";266;2
"Unit";"Zealot";"Gateway";266;2
"Unit";"Zealot";"Gateway";266;2
"Unit";"Zealot";"Gateway";266;2
"Unit";"Zealot";"Gateway";266;2
"Unit";"Zealot";"Gateway";266;2
"Unit";"Zealot";"Gateway";266;2
"Unit";"Zealot";"Gateway";266;2
"Unit";"Zealot";"Gateway";266;2
"Unit";"Zealot";"Gateway";266;2
"Unit";"Zealot";"Gateway";266;2
"Unit";"Zealot";"Gateway";266;2
"Unit";"Zealot";"Gateway";266;2
"Unit";"Zealot";"Gateway";266;2
"Upgrade";"ProtossShieldsLevel1";"Forge";244;0
"Unit";"Zealot";"Gateway";294;2
"Unit";"Zealot";"Gateway";294;2
"Unit";"Zealot";"Gateway";294;2
"Unit";"Zealot";"Gateway";294;2
"Unit";"Zealot";"Gateway";294;2
"Unit";"Zealot";"Gateway";294;2
"Unit";"Zealot";"Gateway";294;2
"Unit";"Zealot";"Gateway";294;2
"Unit";"Zealot";"Gateway";294;2
"Unit";"Zealot";"Gateway";312;2
"Unit";"Zealot";"Gateway";312;2
"Building";"HighTemplar";NA;316;0
"Building";"HighTemplar";NA;316;0
"Building";"HighTemplar";NA;316;0
"Building";"HighTemplar";NA;316;0
"Building";"HighTemplar";NA;316;0
"Building";"HighTemplar";NA;316;0
"Building";"HighTemplar";NA;316;0
"Building";"HighTemplar";NA;316;0
"Building";"HighTemplar";NA;316;0
"Building";"HighTemplar";NA;316;0
"Unit";"Zealot";"Gateway";316;2
"Unit";"Zealot";"Gateway";316;2
"Unit";"Zealot";"Gateway";316;2
"Unit";"Colossus";"Robotics Facility";294;6
"Unit";"Archon";"High Templar";316;0
"Unit";"Archon";"High Templar";316;0
"Unit";"Archon";"High Templar";316;0
"Unit";"Archon";"High Templar";316;0
"Unit";"Archon";"High Templar";316;0
