"type";"unit_name";"on_building";"total_supply";"supply"
"Building";"Pylon";NA;13;0
"Building";"Assimilator";NA;16;0
"Building";"Gateway";NA;15;0
"Building";"Assimilator";NA;20;0
"Building";"CyberneticsCore";NA;20;0
"Building";"Pylon";NA;21;0
"Unit";"Stalker";"Gateway";21;2
"Building";"Nexus";NA;20;0
"Building";"TwilightCouncil";NA;26;0
"Unit";"Stalker";"Gateway";27;2
"Building";"ShieldBattery";NA;35;0
"Building";"Pylon";NA;37;0
"Building";"Gateway";NA;31;0
"Building";"Gateway";NA;31;0
"Building";"Assimilator";NA;39;0
"Building";"Pylon";NA;40;0
"Building";"DarkShrine";NA;32;0
"Building";"Pylon";NA;44;0
"Building";"DarkTemplar";NA;46;0
"Building";"RoboticsFacility";NA;40;0
"Unit";"Sentry";"Gateway";49;2
"Unit";"Zealot";"Gateway";51;2
"Unit";"Zealot";"Gateway";53;2
"Unit";"Immortal";"Robotics Facility";48;4
"Building";"Pylon";NA;51;0
"Building";"Assimilator";NA;49;0
"Building";"Pylon";NA;51;0
"Building";"Nexus";NA;44;0
"Unit";"Sentry";"Gateway";59;2
"Unit";"Sentry";"Gateway";59;2
"Building";"Pylon";NA;53;0
"Building";"Pylon";NA;59;0
"Building";"Pylon";NA;59;0
"Unit";"Sentry";"Gateway";63;2
"Upgrade";"Charge";"TwilightCouncil";47;0
"Unit";"Zealot";"Gateway";69;2
"Unit";"Zealot";"Gateway";69;2
"Building";"ShieldBattery";NA;63;0
"Unit";"Immortal";"Robotics Facility";59;4
"Building";"ShieldBattery";NA;63;0
"Unit";"Immortal";"Robotics Facility";69;4
"Unit";"Zealot";"Gateway";86;2
"Unit";"Zealot";"Gateway";87;2
"Unit";"Observer";"Robotics Facility";85;1
"Unit";"Stalker";"Gateway";94;2
"Unit";"Stalker";"Gateway";100;2
"Unit";"Stalker";"Gateway";100;2
"Building";"Forge";NA;85;0
"Building";"Forge";NA;85;0
"Building";"Pylon";NA;96;0
"Building";"Gateway";NA;79;0
"Building";"Gateway";NA;83;0
"Building";"Gateway";NA;83;0
"Building";"Gateway";NA;84;0
"Unit";"Zealot";"Gateway";106;2
"Building";"Assimilator";NA;106;0
"Building";"Pylon";NA;108;0
"Building";"Assimilator";NA;108;0
"Building";"Pylon";NA;111;0
"Unit";"Zealot";"Gateway";114;2
"Unit";"Zealot";"Gateway";114;2
"Unit";"Zealot";"Gateway";114;2
"Unit";"Zealot";"Gateway";114;2
"Unit";"Zealot";"Gateway";114;2
"Unit";"Zealot";"Gateway";114;2
"Unit";"Zealot";"Gateway";114;2
"Unit";"Immortal";"Robotics Facility";106;4
"Building";"TemplarArchive";NA;111;0
"Building";"HighTemplar";NA;138;0
"Building";"HighTemplar";NA;138;0
"Building";"HighTemplar";NA;138;0
"Building";"HighTemplar";NA;140;0
"Unit";"Immortal";"Robotics Facility";135;4
"Upgrade";"ProtossGroundArmorsLevel1";"Forge";111;0
"Building";"Pylon";NA;140;0
"Building";"Pylon";NA;140;0
"Upgrade";"ProtossGroundWeaponsLevel1";"Forge";114;0
"Building";"Pylon";NA;144;0
"Building";"Pylon";NA;144;0
"Building";"Pylon";NA;144;0
"Building";"Pylon";NA;144;0
"Unit";"Observer";"Robotics Facility";144;1
"Building";"Assimilator";NA;144;0
"Unit";"Stalker";"Gateway";144;2
"Building";"Pylon";NA;144;0
"Unit";"Stalker";"Gateway";144;2
"Unit";"Stalker";"Gateway";144;2
"Building";"Assimilator";NA;144;0
"Building";"Nexus";NA;138;0
"Building";"Pylon";NA;144;0
"Unit";"Archon";"High Templar";151;0
"Unit";"Archon";"High Templar";151;0
"Building";"PhotonCannon";NA;144;0
"Building";"PhotonCannon";NA;144;0
"Building";"PhotonCannon";NA;144;0
"Building";"Pylon";NA;151;0
"Building";"Pylon";NA;151;0
"Building";"Pylon";NA;151;0
"Building";"HighTemplar";NA;157;0
"Building";"HighTemplar";NA;157;0
"Building";"HighTemplar";NA;157;0
"Building";"HighTemplar";NA;157;0
"Building";"HighTemplar";NA;157;0
"Building";"HighTemplar";NA;157;0
"Building";"HighTemplar";NA;157;0
"Building";"PhotonCannon";NA;151;0
"Building";"PhotonCannon";NA;152;0
"Building";"PhotonCannon";NA;154;0
"Building";"PhotonCannon";NA;154;0
"Building";"ShieldBattery";NA;154;0
"Unit";"Phoenix";"Stargate";157;2
"Unit";"Phoenix";"Stargate";157;2
"Unit";"Archon";"High Templar";160;0
"Building";"PhotonCannon";NA;157;0
"Building";"PhotonCannon";NA;160;0
"Unit";"Stalker";"Gateway";164;2
"Unit";"Stalker";"Gateway";164;2
"Unit";"Stalker";"Gateway";164;2
"Unit";"Stalker";"Gateway";164;2
"Unit";"Stalker";"Gateway";164;2
"Unit";"Stalker";"Gateway";164;2
"Unit";"Phoenix";"Stargate";160;2
"Building";"HighTemplar";NA;178;0
"Unit";"Stalker";"Gateway";178;2
"Unit";"Stalker";"Gateway";178;2
"Unit";"Stalker";"Gateway";178;2
"Unit";"Stalker";"Gateway";178;2
"Unit";"Stalker";"Gateway";178;2
"Unit";"Stalker";"Gateway";178;2
"Unit";"Immortal";"Robotics Facility";178;4
"Unit";"Zealot";"Gateway";194;2
"Building";"Pylon";NA;196;0
"Unit";"Zealot";"Gateway";196;2
"Unit";"Zealot";"Gateway";196;2
"Unit";"Zealot";"Gateway";196;2
"Unit";"Zealot";"Gateway";196;2
"Unit";"Zealot";"Gateway";196;2
"Unit";"Zealot";"Gateway";196;2
"Unit";"Zealot";"Gateway";196;2
"Unit";"Immortal";"Robotics Facility";194;4
"Unit";"Zealot";"Gateway";214;2
"Unit";"Zealot";"Gateway";214;2
"Unit";"Zealot";"Gateway";214;2
"Unit";"Zealot";"Gateway";214;2
"Unit";"Zealot";"Gateway";214;2
"Unit";"Zealot";"Gateway";214;2
"Upgrade";"ProtossGroundArmorsLevel2";"Forge";178;0
"Upgrade";"ProtossGroundWeaponsLevel2";"Forge";178;0
"Building";"Assimilator";NA;214;0
"Building";"Nexus";NA;196;0
"Building";"Pylon";NA;226;0
"Building";"Pylon";NA;226;0
"Building";"RoboticsBay";NA;214;0
"Unit";"Immortal";"Robotics Facility";214;4
"Building";"Assimilator";NA;226;0
"Building";"RoboticsFacility";NA;214;0
"Building";"HighTemplar";NA;230;0
"Building";"HighTemplar";NA;230;0
"Building";"HighTemplar";NA;230;0
"Building";"HighTemplar";NA;230;0
"Building";"HighTemplar";NA;230;0
"Building";"HighTemplar";NA;230;0
"Building";"HighTemplar";NA;230;0
"Building";"Nexus";NA;226;0
"Building";"Nexus";NA;226;0
"Unit";"Disruptor";"Robotics Facility";230;3
"Unit";"Disruptor";"Robotics Facility";230;3
"Unit";"Zealot";"Gateway";233;2
"Unit";"Zealot";"Gateway";236;2
"Unit";"Zealot";"Gateway";236;2
"Unit";"Zealot";"Gateway";236;2
"Unit";"Zealot";"Gateway";236;2
"Unit";"Zealot";"Gateway";236;2
"Unit";"Zealot";"Gateway";236;2
"Building";"Assimilator";NA;230;0
"Building";"Assimilator";NA;230;0
"Building";"Assimilator";NA;230;0
"Building";"Assimilator";NA;236;0
"Building";"Pylon";NA;250;0
"Unit";"Stalker";"Gateway";250;2
"Unit";"Stalker";"Gateway";250;2
"Unit";"Stalker";"Gateway";250;2
"Unit";"Stalker";"Gateway";250;2
"Unit";"Stalker";"Gateway";250;2
"Building";"Pylon";NA;250;0
"Unit";"Stalker";"Gateway";250;2
"Unit";"Stalker";"Gateway";250;2
"Building";"Gateway";NA;230;0
"Building";"Gateway";NA;230;0
"Building";"Gateway";NA;230;0
"Building";"Gateway";NA;230;0
"Unit";"Disruptor";"Robotics Facility";230;3
"Building";"Gateway";NA;230;0
"Building";"Gateway";NA;230;0
"Unit";"Disruptor";"Robotics Facility";250;3
"Unit";"Stalker";"Gateway";270;2
"Unit";"Stalker";"Gateway";270;2
"Unit";"Stalker";"Gateway";270;2
"Unit";"Stalker";"Gateway";270;2
"Unit";"Stalker";"Gateway";270;2
"Unit";"Stalker";"Gateway";270;2
"Unit";"Stalker";"Gateway";270;2
"Building";"PhotonCannon";NA;267;0
"Building";"PhotonCannon";NA;270;0
"Building";"Stargate";NA;264;0
"Building";"Stargate";NA;267;0
"Building";"Stargate";NA;267;0
"Unit";"Observer";"Robotics Facility";284;1
"Unit";"Observer";"Robotics Facility";284;1
"Unit";"Zealot";"Gateway";285;2
"Unit";"Zealot";"Gateway";285;2
"Unit";"Zealot";"Gateway";285;2
"Upgrade";"ProtossGroundWeaponsLevel3";"Forge";230;0
"Upgrade";"ProtossGroundArmorsLevel3";"Forge";230;0
"Unit";"Stalker";"Gateway";292;2
"Unit";"Stalker";"Gateway";292;2
"Unit";"Stalker";"Gateway";292;2
"Unit";"Stalker";"Gateway";292;2
"Unit";"Stalker";"Gateway";292;2
"Unit";"Stalker";"Gateway";292;2
"Unit";"Stalker";"Gateway";292;2
"Unit";"Stalker";"Gateway";292;2
"Unit";"Stalker";"Gateway";292;2
"Unit";"Stalker";"Gateway";292;2
"Unit";"Stalker";"Gateway";292;2
"Unit";"Stalker";"Gateway";292;2
"Unit";"Stalker";"Gateway";292;2
"Upgrade";"ProtossAirWeaponsLevel1";"CyberneticsCore";284;0
"Building";"Pylon";NA;318;0
"Unit";"Stalker";"Gateway";318;2
"Unit";"Stalker";"Gateway";318;2
"Unit";"Stalker";"Gateway";318;2
"Unit";"Stalker";"Gateway";318;2
"Unit";"Stalker";"Gateway";318;2
"Unit";"Stalker";"Gateway";318;2
"Unit";"Stalker";"Gateway";318;2
"Unit";"Stalker";"Gateway";318;2
"Unit";"Stalker";"Gateway";318;2
"Unit";"Stalker";"Gateway";318;2
"Unit";"Stalker";"Gateway";318;2
"Unit";"Stalker";"Gateway";318;2
"Unit";"Stalker";"Gateway";318;2
