"type";"unit_name";"on_building";"total_supply";"supply"
"Building";"Pylon";NA;13;0
"Building";"Assimilator";NA;15;0
"Building";"Gateway";NA;15;0
"Building";"Assimilator";NA;21;0
"Building";"Pylon";NA;21;0
"Building";"CyberneticsCore";NA;21;0
"Unit";"Stalker";"Gateway";22;2
"Building";"Nexus";NA;21;0
"Building";"TwilightCouncil";NA;23;0
"Unit";"Stalker";"Gateway";24;2
"Building";"ShieldBattery";NA;24;0
"Unit";"Stalker";"Gateway";27;2
"Unit";"Stalker";"Gateway";34;2
"Building";"Pylon";NA;38;0
"Building";"Gateway";NA;38;0
"Building";"Gateway";NA;38;0
"Unit";"Stalker";"Gateway";48;2
"Unit";"Stalker";"Gateway";48;2
"Unit";"Stalker";"Gateway";48;2
"Building";"Assimilator";NA;46;0
"Building";"Pylon";NA;46;0
"Building";"Assimilator";NA;46;0
"Building";"RoboticsFacility";NA;44;0
"Unit";"Observer";"Robotics Facility";54;1
"Building";"Pylon";NA;54;0
"Unit";"Stalker";"Gateway";59;2
"Unit";"Stalker";"Gateway";59;2
"Unit";"Stalker";"Gateway";59;2
"Unit";"Stalker";"Gateway";70;2
"Unit";"Stalker";"Gateway";70;2
"Unit";"Stalker";"Gateway";70;2
"Building";"Nexus";NA;54;0
"Unit";"Sentry";"Gateway";82;2
"Unit";"Sentry";"Gateway";82;2
"Unit";"Sentry";"Gateway";82;2
"Building";"Pylon";NA;80;0
"Building";"RoboticsBay";NA;70;0
"Building";"Gateway";NA;82;0
"Building";"Gateway";NA;82;0
"Unit";"Stalker";"Gateway";100;2
"Unit";"Stalker";"Gateway";100;2
"Unit";"Stalker";"Gateway";100;2
"Unit";"Colossus";"Robotics Facility";91;6
"Building";"Pylon";NA;106;0
"Building";"Pylon";NA;107;0
"Building";"Pylon";NA;107;0
"Upgrade";"Charge";"TwilightCouncil";89;0
"Unit";"Stalker";"Gateway";115;2
"Unit";"Stalker";"Gateway";115;2
"Unit";"Stalker";"Gateway";115;2
"Unit";"Stalker";"Gateway";115;2
"Unit";"Stalker";"Gateway";115;2
"Building";"Assimilator";NA;115;0
"Building";"Assimilator";NA;115;0
"Building";"Pylon";NA;115;0
"Unit";"Zealot";"Gateway";125;2
"Unit";"Zealot";"Gateway";125;2
"Unit";"Zealot";"Gateway";125;2
"Unit";"Zealot";"Gateway";125;2
"Unit";"Zealot";"Gateway";125;2
"Upgrade";"ExtendedThermalLance";"RoboticsBay";97;0
"Unit";"Colossus";"Robotics Facility";115;6
"Building";"TemplarArchive";NA;125;0
"Building";"Forge";NA;138;0
"Building";"Forge";NA;138;0
"Building";"Pylon";NA;148;0
"Building";"Pylon";NA;148;0
"Building";"HighTemplar";NA;148;0
"Building";"HighTemplar";NA;148;0
"Building";"HighTemplar";NA;148;0
"Building";"HighTemplar";NA;148;0
"Unit";"Zealot";"Gateway";148;2
"Unit";"Archon";"High Templar";152;0
"Unit";"Archon";"High Templar";152;0
"Building";"Pylon";NA;152;0
"Building";"Pylon";NA;152;0
"Building";"HighTemplar";NA;152;0
"Building";"HighTemplar";NA;152;0
"Building";"HighTemplar";NA;152;0
"Building";"HighTemplar";NA;152;0
"Building";"HighTemplar";NA;152;0
"Building";"Gateway";NA;150;0
"Building";"Gateway";NA;152;0
"Building";"PhotonCannon";NA;152;0
"Building";"PhotonCannon";NA;152;0
"Building";"PhotonCannon";NA;152;0
"Unit";"Zealot";"Gateway";152;2
"Unit";"Zealot";"Gateway";152;2
"Unit";"Zealot";"Gateway";152;2
"Unit";"Zealot";"Gateway";152;2
"Unit";"Zealot";"Gateway";152;2
"Unit";"Zealot";"Gateway";152;2
"Unit";"Zealot";"Gateway";152;2
"Building";"Pylon";NA;152;0
"Building";"Pylon";NA;152;0
"Building";"Nexus";NA;152;0
"Upgrade";"ProtossGroundWeaponsLevel1";"Forge";148;0
"Upgrade";"ProtossGroundArmorsLevel1";"Forge";148;0
"Building";"Pylon";NA;166;0
"Unit";"Zealot";"Gateway";166;2
"Unit";"Zealot";"Gateway";166;2
"Unit";"Zealot";"Gateway";166;2
"Unit";"Zealot";"Gateway";166;2
"Unit";"Zealot";"Gateway";166;2
"Unit";"Zealot";"Gateway";166;2
"Unit";"Zealot";"Gateway";166;2
"Building";"Gateway";NA;152;0
"Building";"Gateway";NA;152;0
"Unit";"Archon";"High Templar";180;0
"Unit";"Archon";"High Templar";180;0
"Building";"Gateway";NA;166;0
"Building";"Gateway";NA;166;0
"Unit";"Stalker";"Gateway";180;2
"Unit";"Stalker";"Gateway";180;2
"Unit";"Stalker";"Gateway";180;2
"Unit";"Stalker";"Gateway";180;2
"Unit";"Stalker";"Gateway";180;2
"Unit";"Stalker";"Gateway";180;2
"Unit";"Stalker";"Gateway";180;2
"Building";"HighTemplar";NA;194;0
"Building";"HighTemplar";NA;194;0
"Building";"HighTemplar";NA;194;0
"Building";"HighTemplar";NA;194;0
"Building";"HighTemplar";NA;194;0
"Building";"HighTemplar";NA;194;0
"Unit";"Zealot";"Gateway";194;2
"Unit";"Zealot";"Gateway";194;2
"Unit";"Zealot";"Gateway";194;2
"Unit";"Archon";"High Templar";194;0
"Unit";"Archon";"High Templar";194;0
"Unit";"Stalker";"Gateway";200;2
"Unit";"Stalker";"Gateway";200;2
"Unit";"Stalker";"Gateway";200;2
"Unit";"Colossus";"Robotics Facility";194;6
"Building";"Assimilator";NA;200;0
"Building";"Pylon";NA;200;0
"Building";"Assimilator";NA;200;0
"Unit";"Stalker";"Gateway";216;2
"Building";"Stargate";NA;200;0
"Unit";"Stalker";"Gateway";216;2
"Unit";"Stalker";"Gateway";216;2
"Unit";"Stalker";"Gateway";216;2
"Unit";"Stalker";"Gateway";216;2
"Unit";"Stalker";"Gateway";216;2
"Building";"RoboticsFacility";NA;200;0
"Upgrade";"ProtossGroundWeaponsLevel2";"Forge";180;0
"Upgrade";"ProtossGroundArmorsLevel2";"Forge";180;0
"Building";"HighTemplar";NA;232;0
"Building";"HighTemplar";NA;232;0
"Building";"HighTemplar";NA;232;0
"Unit";"Stalker";"Gateway";232;2
"Unit";"Stalker";"Gateway";232;2
"Unit";"Zealot";"Gateway";238;2
"Unit";"Zealot";"Gateway";238;2
"Unit";"Zealot";"Gateway";238;2
"Unit";"Zealot";"Gateway";238;2
"Unit";"Archon";"High Templar";247;0
"Unit";"Stalker";"Gateway";247;2
"Unit";"Stalker";"Gateway";249;2
"Unit";"Stalker";"Gateway";249;2
"Unit";"Stalker";"Gateway";249;2
"Unit";"Stalker";"Gateway";249;2
"Unit";"Stalker";"Gateway";249;2
"Building";"HighTemplar";NA;259;0
"Unit";"Zealot";"Gateway";259;2
"Unit";"Zealot";"Gateway";259;2
"Unit";"Zealot";"Gateway";259;2
"Unit";"Zealot";"Gateway";259;2
"Unit";"Zealot";"Gateway";259;2
"Unit";"Zealot";"Gateway";259;2
"Unit";"Zealot";"Gateway";259;2
"Unit";"Zealot";"Gateway";259;2
