"type";"unit_name";"on_building";"total_supply_lag";"supply"
"Building";"Pylon";NA;14;0
"Building";"Gateway";NA;16;0
"Building";"Assimilator";NA;17;0
"Building";"Nexus";NA;20;0
"Building";"CyberneticsCore";NA;20;0
"Building";"Assimilator";NA;21;0
"Building";"Pylon";NA;22;0
"Unit";"Stalker";"Gateway";22;2
"Building";"TwilightCouncil";NA;27;0
"Unit";"Stalker";"Gateway";29;2
"Building";"Gateway";NA;39;0
"Building";"Gateway";NA;39;0
"Building";"Pylon";NA;41;0
"Building";"RoboticsFacility";NA;41;0
"Building";"Assimilator";NA;43;0
"Building";"Nexus";NA;47;0
"Unit";"Stalker";"Gateway";47;2
"Unit";"Stalker";"Gateway";49;2
"Unit";"Stalker";"Gateway";51;2
"Building";"Pylon";NA;53;0
"Unit";"Observer";"Robotics Facility";53;1
"Unit";"Stalker";"Gateway";56;2
"Unit";"Stalker";"Gateway";58;2
"Unit";"Stalker";"Gateway";60;2
"Unit";"Observer";"Robotics Facility";63;1
"Building";"Pylon";NA;66;0
"Building";"Forge";NA;69;0
"Building";"Forge";NA;69;0
"Unit";"Sentry";"Gateway";74;2
"Unit";"Sentry";"Gateway";76;2
"Unit";"Sentry";"Gateway";78;2
"Upgrade";"Charge";"TwilightCouncil";82;0
"Building";"Gateway";NA;87;0
"Building";"Gateway";NA;87;0
"Building";"Gateway";NA;87;0
"Building";"Gateway";NA;87;0
"Building";"Pylon";NA;89;0
"Building";"Pylon";NA;90;0
"Upgrade";"ProtossGroundWeaponsLevel1";"Forge";90;0
"Unit";"Zealot";"Gateway";90;2
"Unit";"Zealot";"Gateway";92;2
"Unit";"Zealot";"Gateway";94;2
"Building";"Pylon";NA;96;0
"Building";"Pylon";NA;96;0
"Unit";"Immortal";"Robotics Facility";97;4
"Unit";"Stalker";"Gateway";103;2
"Unit";"Stalker";"Gateway";105;2
"Unit";"Stalker";"Gateway";107;2
"Unit";"Zealot";"Gateway";109;2
"Unit";"Zealot";"Gateway";111;2
"Unit";"Zealot";"Gateway";113;2
"Unit";"Zealot";"Gateway";115;2
"Building";"Pylon";NA;117;0
"Unit";"Zealot";"Gateway";117;2
"Building";"Pylon";NA;119;0
"Unit";"Zealot";"Gateway";119;2
"Unit";"Zealot";"Gateway";121;2
"Building";"Assimilator";NA;123;0
"Building";"Assimilator";NA;123;0
"Building";"Assimilator";NA;123;0
"Unit";"Zealot";"Gateway";126;2
"Unit";"Zealot";"Gateway";128;2
"Unit";"Zealot";"Gateway";130;2
"Unit";"Zealot";"Gateway";132;2
"Unit";"Stalker";"Gateway";134;2
"Unit";"Stalker";"Gateway";136;2
"Unit";"Stalker";"Gateway";138;2
"Unit";"Stalker";"Gateway";140;2
"Unit";"Stalker";"Gateway";142;2
"Unit";"Stalker";"Gateway";144;2
"Unit";"Stalker";"Gateway";146;2
"Building";"Pylon";NA;148;0
"Building";"Pylon";NA;148;0
"Building";"Pylon";NA;148;0
"Unit";"Stalker";"Gateway";148;2
"Unit";"Stalker";"Gateway";150;2
"Unit";"Stalker";"Gateway";152;2
"Unit";"Stalker";"Gateway";160;2
"Unit";"Stalker";"Gateway";162;2
"Unit";"Stalker";"Gateway";164;2
"Unit";"Stalker";"Gateway";166;2
"Unit";"Stalker";"Gateway";168;2
"Upgrade";"ProtossGroundWeaponsLevel2";"Forge";173;0
"Unit";"Observer";"Robotics Facility";173;1
"Building";"Gateway";NA;177;0
"Building";"Gateway";NA;177;0
"Building";"TemplarArchive";NA;179;0
"Unit";"Observer";"Robotics Facility";180;1
"Unit";"Zealot";"Gateway";181;2
"Unit";"Zealot";"Gateway";183;2
"Unit";"Zealot";"Gateway";185;2
"Unit";"Zealot";"Gateway";187;2
"Unit";"Zealot";"Gateway";189;2
"Unit";"Zealot";"Gateway";191;2
"Unit";"Zealot";"Gateway";193;2
"Building";"Pylon";NA;195;0
"Building";"PhotonCannon";NA;201;0
"Unit";"Stalker";"Gateway";201;2
"Unit";"Stalker";"Gateway";203;2
"Building";"HighTemplar";NA;205;0
"Building";"HighTemplar";NA;205;0
"Building";"HighTemplar";NA;205;0
"Building";"HighTemplar";NA;205;0
"Unit";"Zealot";"Gateway";205;2
"Unit";"Zealot";"Gateway";207;2
"Unit";"Zealot";"Gateway";209;2
"Unit";"Zealot";"Gateway";211;2
"Unit";"Zealot";"Gateway";213;2
"Building";"Pylon";NA;215;0
"Building";"HighTemplar";NA;215;0
"Building";"HighTemplar";NA;215;0
"Building";"HighTemplar";NA;215;0
"Building";"HighTemplar";NA;215;0
"Unit";"Stalker";"Gateway";215;2
"Unit";"Archon";"High Templar";217;0
"Unit";"Archon";"High Templar";217;0
"Unit";"Stalker";"Gateway";217;2
"Unit";"Zealot";"Gateway";219;2
"Unit";"Zealot";"Gateway";221;2
"Building";"Pylon";NA;226;0
"Building";"Pylon";NA;226;0
"Building";"Pylon";NA;226;0
"Building";"Pylon";NA;226;0
"Building";"Pylon";NA;226;0
"Building";"HighTemplar";NA;226;0
"Building";"HighTemplar";NA;226;0
"Building";"HighTemplar";NA;226;0
"Building";"HighTemplar";NA;226;0
"Unit";"Zealot";"Gateway";226;2
"Unit";"Zealot";"Gateway";228;2
"Unit";"Zealot";"Gateway";230;2
"Unit";"Zealot";"Gateway";232;2
"Unit";"Archon";"High Templar";234;0
"Unit";"Archon";"High Templar";234;0
"Unit";"Stalker";"Gateway";234;2
"Unit";"Stalker";"Gateway";236;2
"Unit";"Stalker";"Gateway";238;2
"Unit";"Stalker";"Gateway";240;2
"Unit";"Stalker";"Gateway";242;2
"Unit";"Stalker";"Gateway";244;2
"Unit";"Stalker";"Gateway";246;2
"Unit";"Stalker";"Gateway";248;2
"Unit";"Stalker";"Gateway";250;2
"Unit";"Stalker";"Gateway";252;2
"Unit";"Stalker";"Gateway";254;2
"Unit";"Stalker";"Gateway";256;2
"Unit";"Stalker";"Gateway";258;2
"Unit";"Archon";"High Templar";260;0
"Unit";"Zealot";"Gateway";260;2
"Unit";"Zealot";"Gateway";262;2
"Unit";"Zealot";"Gateway";264;2
"Unit";"Zealot";"Gateway";266;2
"Unit";"Zealot";"Gateway";268;2
"Unit";"Zealot";"Gateway";270;2
"Unit";"Zealot";"Gateway";272;2
"Unit";"Zealot";"Gateway";274;2
"Unit";"Zealot";"Gateway";276;2
"Building";"HighTemplar";NA;278;0
"Building";"HighTemplar";NA;278;0
"Building";"HighTemplar";NA;278;0
"Building";"HighTemplar";NA;278;0
"Building";"HighTemplar";NA;278;0
"Building";"HighTemplar";NA;278;0
"Unit";"Zealot";"Gateway";278;2
"Unit";"Zealot";"Gateway";280;2
"Unit";"Zealot";"Gateway";282;2
"Unit";"Archon";"High Templar";284;0
"Unit";"Archon";"High Templar";284;0
"Unit";"Archon";"High Templar";284;0
"Unit";"Stalker";"Gateway";284;2
"Unit";"Stalker";"Gateway";286;2
"Unit";"Stalker";"Gateway";288;2
"Building";"HighTemplar";NA;290;0
"Building";"HighTemplar";NA;290;0
"Unit";"Zealot";"Gateway";290;2
"Unit";"Zealot";"Gateway";292;2
"Unit";"Archon";"High Templar";294;0
"Unit";"Zealot";"Gateway";294;2
"Unit";"Zealot";"Gateway";296;2
"Unit";"Zealot";"Gateway";298;2
"Unit";"Zealot";"Gateway";300;2
"Unit";"Zealot";"Gateway";302;2
"Unit";"Zealot";"Gateway";304;2
"Building";"HighTemplar";NA;306;0
"Unit";"Zealot";"Gateway";306;2
"Unit";"Zealot";"Gateway";308;2
"Building";"HighTemplar";NA;310;0
"Building";"HighTemplar";NA;310;0
"Building";"HighTemplar";NA;310;0
"Building";"HighTemplar";NA;310;0
"Unit";"Zealot";"Gateway";310;2
"Unit";"Zealot";"Gateway";312;2
"Upgrade";"SprayProtoss";NA;314;0
"Upgrade";"SprayProtoss";NA;314;0
"Upgrade";"SprayProtoss";NA;314;0
"Upgrade";"WarpGateResearch";NA;314;0
"Upgrade";"BlinkTech";NA;314;0
"Upgrade";"SprayProtoss";NA;314;0
"Upgrade";"ProtossGroundArmorsLevel1";NA;314;0
"Upgrade";"SprayProtoss";NA;314;0
"Upgrade";"ProtossGroundArmorsLevel2";NA;314;0
"Upgrade";"PsiStormTech";NA;314;0
"Upgrade";"SprayProtoss";NA;314;0
