"type";"unit_name";"on_building";"total_supply_lag";"supply"
"Unit";"Overlord";"Larva";13;0
"Building";"SpawningPool";NA;17;0
"Building";"Hatchery";NA;18;0
"Building";"Extractor";NA;20;0
"Unit";"Queen";"Hatchery";21;2
"Unit";"Zergling";"Larva";23;1
"Unit";"Zergling";"Larva";24;1
"Unit";"Overlord";"Larva";25;0
"Unit";"Queen";"Hatchery";27;2
"Unit";"Queen";"Hatchery";30;2
"Unit";"Queen";"Hatchery";36;2
"Unit";"Overlord";"Larva";38;0
"Unit";"Queen";"Hatchery";38;2
"Building";"CreepTumorQueen";NA;40;0
"Building";"Hatchery";NA;40;0
"Unit";"Zergling";"Larva";40;1
"Unit";"Zergling";"Larva";41;1
"Unit";"Zergling";"Larva";42;1
"Unit";"Zergling";"Larva";43;1
"Building";"CreepTumorQueen";NA;44;0
"Unit";"Zergling";"Larva";44;1
"Unit";"Zergling";"Larva";45;1
"Unit";"Zergling";"Larva";46;1
"Unit";"Zergling";"Larva";47;1
"Unit";"Zergling";"Larva";48;1
"Unit";"Zergling";"Larva";49;1
"Unit";"Zergling";"Larva";50;1
"Unit";"Zergling";"Larva";51;1
"Unit";"Zergling";"Larva";52;1
"Unit";"Zergling";"Larva";53;1
"Building";"CreepTumor";NA;54;0
"Building";"CreepTumor";NA;54;0
"Unit";"Zergling";"Larva";54;1
"Unit";"Zergling";"Larva";55;1
"Unit";"Zergling";"Larva";56;1
"Unit";"Zergling";"Larva";57;1
"Unit";"Zergling";"Larva";58;1
"Unit";"Zergling";"Larva";59;1
"Unit";"Zergling";"Larva";60;1
"Unit";"Zergling";"Larva";61;1
"Unit";"Zergling";"Larva";62;1
"Unit";"Zergling";"Larva";63;1
"Unit";"Overlord";"Larva";64;0
"Building";"CreepTumorQueen";NA;64;0
"Unit";"Overlord";"Larva";64;0
"Building";"CreepTumorQueen";NA;66;0
"Building";"CreepTumor";NA;71;0
"Building";"CreepTumor";NA;71;0
"Building";"CreepTumorQueen";NA;81;0
"Building";"CreepTumorQueen";NA;83;0
"Building";"CreepTumor";NA;84;0
"Building";"CreepTumor";NA;84;0
"Building";"EvolutionChamber";NA;87;0
"Building";"EvolutionChamber";NA;87;0
"Building";"CreepTumor";NA;88;0
"Building";"CreepTumor";NA;88;0
"Unit";"Overlord";"Larva";90;0
"Unit";"Overlord";"Larva";90;0
"Unit";"Overlord";"Larva";90;0
"Building";"CreepTumor";NA;90;0
"Building";"CreepTumor";NA;90;0
"Unit";"Overlord";"Larva";90;0
"Building";"CreepTumorQueen";NA;90;0
"Building";"CreepTumorQueen";NA;90;0
"Unit";"Queen";"Hatchery";98;2
"Unit";"Queen";"Hatchery";100;2
"Building";"CreepTumor";NA;102;0
"Building";"CreepTumor";NA;102;0
"Building";"CreepTumor";NA;104;0
"Building";"CreepTumor";NA;104;0
"Building";"CreepTumor";NA;105;0
"Building";"CreepTumor";NA;105;0
"Building";"CreepTumor";NA;113;0
"Building";"CreepTumor";NA;114;0
"Building";"Extractor";NA;114;0
"Unit";"Zergling";"Larva";114;1
"Unit";"Zergling";"Larva";115;1
"Unit";"Zergling";"Larva";116;1
"Unit";"Zergling";"Larva";117;1
"Unit";"Zergling";"Larva";118;1
"Unit";"Zergling";"Larva";119;1
"Building";"BanelingNest";NA;120;0
"Building";"Hatchery";NA;120;0
"Building";"Extractor";NA;120;0
"Unit";"Zergling";"Larva";120;1
"Unit";"Zergling";"Larva";121;1
"Unit";"Zergling";"Larva";122;1
"Unit";"Zergling";"Larva";123;1
"Unit";"Zergling";"Larva";124;1
"Unit";"Zergling";"Larva";125;1
"Building";"Extractor";NA;126;0
"Building";"CreepTumor";NA;126;0
"Building";"CreepTumor";NA;126;0
"Unit";"Queen";"Hatchery";126;2
"Unit";"Queen";"Hatchery";128;2
"Unit";"Overlord";"Larva";130;0
"Building";"CreepTumor";NA;134;0
"Building";"CreepTumor";NA;134;0
"Unit";"Overlord";"Larva";134;0
"Building";"Extractor";NA;134;0
"Building";"CreepTumor";NA;134;0
"Building";"CreepTumor";NA;134;0
"Building";"CreepTumorQueen";NA;134;0
"Building";"Hatchery";NA;134;0
"Building";"CreepTumorQueen";NA;135;0
"Building";"CreepTumorQueen";NA;141;0
"Building";"Extractor";NA;141;0
"Unit";"Overlord";"Larva";141;0
"Unit";"Overlord";"Larva";141;0
"Building";"CreepTumor";NA;144;0
"Building";"CreepTumor";NA;144;0
"Building";"CreepTumorQueen";NA;144;0
"Building";"CreepTumorQueen";NA;144;0
"Unit";"Zergling";"Larva";144;1
"Unit";"Zergling";"Larva";145;1
"Unit";"Zergling";"Larva";146;1
"Unit";"Zergling";"Larva";147;1
"Unit";"Zergling";"Larva";148;1
"Unit";"Zergling";"Larva";149;1
"Unit";"Zergling";"Larva";150;1
"Unit";"Zergling";"Larva";151;1
"Unit";"Zergling";"Larva";152;1
"Unit";"Zergling";"Larva";153;1
"Unit";"Zergling";"Larva";154;1
"Unit";"Zergling";"Larva";155;1
"Unit";"Zergling";"Larva";156;1
"Unit";"Zergling";"Larva";157;1
"Unit";"Baneling";"Zergling";158;0
"Unit";"Baneling";"Zergling";158;0
"Unit";"Baneling";"Zergling";158;0
"Unit";"Baneling";"Zergling";158;0
"Unit";"Baneling";"Zergling";158;0
"Unit";"Baneling";"Zergling";158;0
"Unit";"Baneling";"Zergling";158;0
"Unit";"Baneling";"Zergling";158;0
"Unit";"Baneling";"Zergling";158;0
"Unit";"Baneling";"Zergling";158;0
"Building";"CreepTumor";NA;158;0
"Building";"CreepTumor";NA;158;0
"Building";"CreepTumor";NA;158;0
"Building";"CreepTumor";NA;158;0
"Unit";"Zergling";"Larva";158;1
"Unit";"Zergling";"Larva";159;1
"Unit";"Zergling";"Larva";160;1
"Unit";"Zergling";"Larva";161;1
"Unit";"Zergling";"Larva";162;1
"Unit";"Zergling";"Larva";163;1
"Unit";"Zergling";"Larva";164;1
"Unit";"Zergling";"Larva";165;1
"Unit";"Zergling";"Larva";166;1
"Unit";"Zergling";"Larva";167;1
"Unit";"Zergling";"Larva";168;1
"Unit";"Zergling";"Larva";169;1
"Unit";"Zergling";"Larva";170;1
"Unit";"Zergling";"Larva";171;1
"Unit";"Zergling";"Larva";172;1
"Unit";"Zergling";"Larva";173;1
"Unit";"Zergling";"Larva";174;1
"Unit";"Zergling";"Larva";175;1
"Unit";"Zergling";"Larva";176;1
"Unit";"Zergling";"Larva";177;1
"Unit";"Zergling";"Larva";178;1
"Unit";"Zergling";"Larva";179;1
"Unit";"Zergling";"Larva";180;1
"Unit";"Zergling";"Larva";181;1
"Unit";"Zergling";"Larva";182;1
"Unit";"Zergling";"Larva";183;1
"Unit";"Zergling";"Larva";184;1
"Unit";"Zergling";"Larva";185;1
"Unit";"Zergling";"Larva";186;1
"Unit";"Zergling";"Larva";187;1
"Unit";"Zergling";"Larva";188;1
"Unit";"Zergling";"Larva";189;1
"Unit";"Zergling";"Larva";190;1
"Unit";"Zergling";"Larva";191;1
"Building";"CreepTumor";NA;192;0
"Building";"CreepTumor";NA;192;0
"Unit";"Zergling";"Larva";192;1
"Unit";"Zergling";"Larva";193;1
"Unit";"Zergling";"Larva";194;1
"Unit";"Zergling";"Larva";195;1
"Unit";"Zergling";"Larva";196;1
"Unit";"Zergling";"Larva";197;1
"Unit";"Zergling";"Larva";198;1
"Unit";"Zergling";"Larva";199;1
"Unit";"Zergling";"Larva";200;1
"Unit";"Zergling";"Larva";201;1
"Unit";"Zergling";"Larva";202;1
"Unit";"Zergling";"Larva";203;1
"Unit";"Zergling";"Larva";204;1
"Unit";"Zergling";"Larva";205;1
"Unit";"Zergling";"Larva";206;1
"Unit";"Zergling";"Larva";207;1
"Unit";"Zergling";"Larva";208;1
"Unit";"Zergling";"Larva";209;1
"Unit";"Zergling";"Larva";210;1
"Unit";"Zergling";"Larva";211;1
"Building";"CreepTumorQueen";NA;212;0
"Building";"CreepTumorQueen";NA;212;0
"Building";"CreepTumorQueen";NA;212;0
"Building";"CreepTumorQueen";NA;212;0
"Building";"Spire";NA;212;0
"Unit";"Zergling";"Larva";212;1
"Unit";"Zergling";"Larva";213;1
"Unit";"Zergling";"Larva";214;1
"Unit";"Zergling";"Larva";215;1
"Unit";"Zergling";"Larva";216;1
"Unit";"Zergling";"Larva";217;1
"Unit";"Zergling";"Larva";218;1
"Unit";"Zergling";"Larva";219;1
"Unit";"Zergling";"Larva";220;1
"Unit";"Zergling";"Larva";221;1
"Unit";"Baneling";"Zergling";222;0
"Unit";"Baneling";"Zergling";222;0
"Unit";"Baneling";"Zergling";222;0
"Unit";"Baneling";"Zergling";222;0
"Unit";"Baneling";"Zergling";222;0
"Unit";"Baneling";"Zergling";222;0
"Unit";"Baneling";"Zergling";222;0
"Unit";"Zergling";"Larva";222;1
"Unit";"Zergling";"Larva";223;1
"Unit";"Zergling";"Larva";224;1
"Unit";"Zergling";"Larva";225;1
"Unit";"Overlord";"Larva";226;0
"Unit";"Overlord";"Larva";226;0
"Building";"CreepTumor";NA;226;0
"Building";"CreepTumor";NA;226;0
"Building";"CreepTumor";NA;226;0
"Building";"CreepTumor";NA;226;0
"Building";"CreepTumor";NA;226;0
"Building";"CreepTumor";NA;226;0
"Building";"CreepTumor";NA;226;0
"Unit";"Zergling";"Larva";226;1
"Unit";"Zergling";"Larva";227;1
"Unit";"Overlord";"Larva";228;0
"Unit";"Overlord";"Larva";228;0
"Unit";"Baneling";"Zergling";228;0
"Unit";"Baneling";"Zergling";228;0
"Unit";"Baneling";"Zergling";228;0
"Unit";"Baneling";"Zergling";228;0
"Unit";"Baneling";"Zergling";228;0
"Unit";"Baneling";"Zergling";228;0
"Unit";"Baneling";"Zergling";228;0
"Unit";"Baneling";"Zergling";228;0
"Unit";"Baneling";"Zergling";228;0
"Unit";"Baneling";"Zergling";228;0
"Unit";"Baneling";"Zergling";228;0
"Unit";"Baneling";"Zergling";228;0
"Unit";"Baneling";"Zergling";228;0
"Unit";"Baneling";"Zergling";228;0
"Building";"Hatchery";NA;228;0
"Unit";"Overlord";"Larva";228;0
"Unit";"Overlord";"Larva";228;0
"Unit";"Zergling";"Larva";228;1
"Unit";"Zergling";"Larva";229;1
"Unit";"Zergling";"Larva";230;1
"Unit";"Zergling";"Larva";231;1
"Unit";"Zergling";"Larva";232;1
"Unit";"Zergling";"Larva";233;1
"Unit";"Zergling";"Larva";234;1
"Unit";"Zergling";"Larva";235;1
"Unit";"Zergling";"Larva";236;1
"Unit";"Zergling";"Larva";237;1
"Unit";"Zergling";"Larva";238;1
"Unit";"Zergling";"Larva";239;1
"Unit";"Zergling";"Larva";240;1
"Unit";"Zergling";"Larva";241;1
"Unit";"Zergling";"Larva";242;1
"Unit";"Zergling";"Larva";243;1
"Unit";"Zergling";"Larva";244;1
"Unit";"Zergling";"Larva";245;1
"Unit";"Zergling";"Larva";246;1
"Unit";"Zergling";"Larva";247;1
"Unit";"Zergling";"Larva";248;1
"Unit";"Zergling";"Larva";249;1
"Unit";"Zergling";"Larva";250;1
"Unit";"Zergling";"Larva";251;1
"Unit";"Baneling";"Zergling";252;0
"Unit";"Baneling";"Zergling";252;0
"Unit";"Baneling";"Zergling";252;0
"Building";"CreepTumor";NA;252;0
"Building";"CreepTumor";NA;252;0
"Unit";"Zergling";"Larva";252;1
"Unit";"Zergling";"Larva";253;1
"Unit";"Zergling";"Larva";254;1
"Unit";"Zergling";"Larva";255;1
"Unit";"Zergling";"Larva";256;1
"Unit";"Zergling";"Larva";257;1
"Unit";"Zergling";"Larva";258;1
"Unit";"Zergling";"Larva";259;1
"Unit";"Zergling";"Larva";260;1
"Unit";"Zergling";"Larva";261;1
"Unit";"Zergling";"Larva";262;1
"Unit";"Zergling";"Larva";263;1
"Unit";"Zergling";"Larva";264;1
"Unit";"Zergling";"Larva";265;1
"Unit";"Zergling";"Larva";266;1
"Unit";"Zergling";"Larva";267;1
"Unit";"Zergling";"Larva";268;1
"Unit";"Zergling";"Larva";269;1
"Unit";"Zergling";"Larva";270;1
"Unit";"Zergling";"Larva";271;1
"Unit";"Zergling";"Larva";272;1
"Unit";"Zergling";"Larva";273;1
"Unit";"Zergling";"Larva";274;1
"Unit";"Zergling";"Larva";275;1
"Unit";"Zergling";"Larva";276;1
"Unit";"Zergling";"Larva";277;1
"Unit";"Zergling";"Larva";278;1
"Unit";"Zergling";"Larva";279;1
"Unit";"Zergling";"Larva";280;1
"Unit";"Zergling";"Larva";281;1
"Unit";"Zergling";"Larva";282;1
"Unit";"Zergling";"Larva";283;1
"Unit";"Zergling";"Larva";284;1
"Unit";"Zergling";"Larva";285;1
"Unit";"Zergling";"Larva";286;1
"Unit";"Zergling";"Larva";287;1
"Unit";"Zergling";"Larva";288;1
"Unit";"Zergling";"Larva";289;1
"Unit";"Zergling";"Larva";290;1
"Unit";"Zergling";"Larva";291;1
"Building";"CreepTumor";NA;292;0
"Building";"CreepTumor";NA;292;0
"Unit";"Zergling";"Larva";292;1
"Unit";"Zergling";"Larva";293;1
"Unit";"Zergling";"Larva";294;1
"Unit";"Zergling";"Larva";295;1
"Unit";"Zergling";"Larva";296;1
"Unit";"Zergling";"Larva";297;1
"Unit";"Zergling";"Larva";298;1
"Unit";"Zergling";"Larva";299;1
"Unit";"Zergling";"Larva";300;1
"Unit";"Zergling";"Larva";301;1
"Unit";"Zergling";"Larva";302;1
"Unit";"Zergling";"Larva";303;1
"Unit";"Zergling";"Larva";304;1
"Unit";"Zergling";"Larva";305;1
"Unit";"Mutalisk";"Larva";306;2
"Unit";"Mutalisk";"Larva";308;2
"Unit";"Mutalisk";"Larva";310;2
"Unit";"Mutalisk";"Larva";312;2
"Unit";"Mutalisk";"Larva";314;2
"Unit";"Mutalisk";"Larva";316;2
"Unit";"Mutalisk";"Larva";318;2
"Unit";"Mutalisk";"Larva";320;2
"Unit";"Mutalisk";"Larva";322;2
"Unit";"Zergling";"Larva";324;1
"Unit";"Zergling";"Larva";325;1
"Unit";"Zergling";"Larva";326;1
"Unit";"Zergling";"Larva";327;1
"Unit";"Zergling";"Larva";328;1
"Unit";"Zergling";"Larva";329;1
"Unit";"Zergling";"Larva";330;1
"Unit";"Zergling";"Larva";331;1
"Unit";"Zergling";"Larva";332;1
"Unit";"Zergling";"Larva";333;1
"Unit";"Zergling";"Larva";334;1
"Unit";"Zergling";"Larva";335;1
"Unit";"Zergling";"Larva";336;1
"Unit";"Zergling";"Larva";337;1
"Unit";"Zergling";"Larva";338;1
"Unit";"Zergling";"Larva";339;1
"Unit";"Mutalisk";"Larva";340;2
"Unit";"Mutalisk";"Larva";342;2
"Unit";"Mutalisk";"Larva";344;2
"Unit";"Zergling";"Larva";346;1
"Unit";"Zergling";"Larva";347;1
"Unit";"Zergling";"Larva";348;1
"Unit";"Zergling";"Larva";349;1
"Unit";"Zergling";"Larva";350;1
"Unit";"Zergling";"Larva";351;1
"Building";"CreepTumor";NA;352;0
"Building";"CreepTumor";NA;352;0
"Building";"CreepTumor";NA;352;0
"Unit";"Zergling";"Larva";352;1
"Unit";"Zergling";"Larva";353;1
"Unit";"Zergling";"Larva";354;1
"Unit";"Zergling";"Larva";355;1
"Unit";"Zergling";"Larva";356;1
"Unit";"Zergling";"Larva";357;1
"Unit";"Zergling";"Larva";358;1
"Unit";"Zergling";"Larva";359;1
"Unit";"Zergling";"Larva";360;1
"Unit";"Zergling";"Larva";361;1
"Unit";"Zergling";"Larva";362;1
"Unit";"Zergling";"Larva";363;1
"Building";"CreepTumorQueen";NA;364;0
"Unit";"Baneling";"Zergling";364;0
"Unit";"Baneling";"Zergling";364;0
"Unit";"Baneling";"Zergling";364;0
"Unit";"Baneling";"Zergling";364;0
"Unit";"Baneling";"Zergling";364;0
"Unit";"Baneling";"Zergling";364;0
"Unit";"Baneling";"Zergling";364;0
"Building";"CreepTumorQueen";NA;364;0
"Building";"CreepTumorQueen";NA;364;0
"Building";"CreepTumorQueen";NA;364;0
"Unit";"Zergling";"Larva";364;1
"Unit";"Zergling";"Larva";365;1
"Unit";"Zergling";"Larva";366;1
"Unit";"Zergling";"Larva";367;1
"Unit";"Zergling";"Larva";368;1
"Unit";"Zergling";"Larva";369;1
"Unit";"Zergling";"Larva";370;1
"Unit";"Zergling";"Larva";371;1
"Unit";"Zergling";"Larva";372;1
"Unit";"Zergling";"Larva";373;1
"Unit";"Zergling";"Larva";374;1
"Unit";"Zergling";"Larva";375;1
"Unit";"Zergling";"Larva";376;1
"Unit";"Zergling";"Larva";377;1
"Unit";"Zergling";"Larva";378;1
"Unit";"Zergling";"Larva";379;1
"Unit";"Zergling";"Larva";380;1
"Unit";"Zergling";"Larva";381;1
"Building";"CreepTumorQueen";NA;382;0
"Building";"CreepTumorQueen";NA;382;0
"Unit";"Mutalisk";"Larva";382;2
"Unit";"Mutalisk";"Larva";384;2
"Building";"CreepTumorQueen";NA;386;0
"Unit";"Zergling";"Larva";386;1
"Unit";"Zergling";"Larva";387;1
"Unit";"Zergling";"Larva";388;1
"Unit";"Zergling";"Larva";389;1
"Unit";"Zergling";"Larva";390;1
"Unit";"Zergling";"Larva";391;1
"Unit";"Zergling";"Larva";392;1
"Unit";"Zergling";"Larva";393;1
"Unit";"Zergling";"Larva";394;1
"Unit";"Zergling";"Larva";395;1
"Unit";"Zergling";"Larva";396;1
"Unit";"Zergling";"Larva";397;1
"Unit";"Zergling";"Larva";398;1
"Unit";"Zergling";"Larva";399;1
"Unit";"Zergling";"Larva";400;1
"Unit";"Zergling";"Larva";401;1
"Unit";"Zergling";"Larva";402;1
"Unit";"Zergling";"Larva";403;1
"Unit";"Zergling";"Larva";404;1
"Unit";"Zergling";"Larva";405;1
"Unit";"Zergling";"Larva";406;1
"Unit";"Zergling";"Larva";407;1
"Unit";"Zergling";"Larva";408;1
"Unit";"Zergling";"Larva";409;1
"Unit";"Zergling";"Larva";410;1
"Unit";"Zergling";"Larva";411;1
"Unit";"Zergling";"Larva";412;1
"Unit";"Zergling";"Larva";413;1
"Unit";"Zergling";"Larva";414;1
"Unit";"Zergling";"Larva";415;1
"Unit";"Zergling";"Larva";416;1
"Unit";"Zergling";"Larva";417;1
"Unit";"Zergling";"Larva";418;1
"Unit";"Zergling";"Larva";419;1
"Building";"InfestationPit";NA;420;0
"Building";"CreepTumor";NA;420;0
"Building";"CreepTumor";NA;420;0
"Unit";"Zergling";"Larva";420;1
"Unit";"Zergling";"Larva";421;1
"Unit";"Zergling";"Larva";422;1
"Unit";"Zergling";"Larva";423;1
"Unit";"Zergling";"Larva";424;1
"Unit";"Zergling";"Larva";425;1
"Unit";"Zergling";"Larva";426;1
"Unit";"Zergling";"Larva";427;1
"Unit";"Zergling";"Larva";428;1
"Unit";"Zergling";"Larva";429;1
"Unit";"Zergling";"Larva";430;1
"Unit";"Zergling";"Larva";431;1
"Unit";"Zergling";"Larva";432;1
"Unit";"Zergling";"Larva";433;1
"Unit";"Zergling";"Larva";434;1
"Unit";"Zergling";"Larva";435;1
"Building";"CreepTumor";NA;436;0
"Building";"CreepTumor";NA;436;0
"Building";"CreepTumor";NA;436;0
"Unit";"Zergling";"Larva";436;1
"Unit";"Zergling";"Larva";437;1
"Unit";"Zergling";"Larva";438;1
"Unit";"Zergling";"Larva";439;1
"Unit";"Zergling";"Larva";440;1
"Unit";"Zergling";"Larva";441;1
"Unit";"Zergling";"Larva";442;1
"Unit";"Zergling";"Larva";443;1
"Unit";"Zergling";"Larva";444;1
"Unit";"Zergling";"Larva";445;1
"Unit";"Zergling";"Larva";446;1
"Unit";"Zergling";"Larva";447;1
"Unit";"Zergling";"Larva";448;1
"Unit";"Zergling";"Larva";449;1
"Unit";"Baneling";"Zergling";450;0
"Unit";"Baneling";"Zergling";450;0
"Unit";"Baneling";"Zergling";450;0
"Unit";"Baneling";"Zergling";450;0
"Unit";"Baneling";"Zergling";450;0
"Unit";"Baneling";"Zergling";450;0
"Unit";"Baneling";"Zergling";450;0
"Unit";"Baneling";"Zergling";450;0
"Unit";"Zergling";"Larva";450;1
"Unit";"Zergling";"Larva";451;1
"Unit";"Zergling";"Larva";452;1
"Unit";"Zergling";"Larva";453;1
"Unit";"Zergling";"Larva";454;1
"Unit";"Zergling";"Larva";455;1
"Unit";"Zergling";"Larva";456;1
"Unit";"Zergling";"Larva";457;1
"Unit";"Zergling";"Larva";458;1
"Unit";"Zergling";"Larva";459;1
"Unit";"Zergling";"Larva";460;1
"Unit";"Zergling";"Larva";461;1
"Unit";"Zergling";"Larva";462;1
"Unit";"Zergling";"Larva";463;1
"Unit";"Zergling";"Larva";464;1
"Unit";"Zergling";"Larva";465;1
"Unit";"Zergling";"Larva";466;1
"Unit";"Zergling";"Larva";467;1
"Unit";"Zergling";"Larva";468;1
"Unit";"Zergling";"Larva";469;1
"Unit";"Zergling";"Larva";470;1
"Unit";"Zergling";"Larva";471;1
"Unit";"Zergling";"Larva";472;1
"Unit";"Zergling";"Larva";473;1
"Unit";"Zergling";"Larva";474;1
"Unit";"Zergling";"Larva";475;1
"Building";"CreepTumor";NA;476;0
"Building";"CreepTumor";NA;476;0
"Building";"CreepTumor";NA;476;0
"Building";"CreepTumor";NA;476;0
"Building";"CreepTumor";NA;476;0
"Building";"CreepTumorQueen";NA;476;0
"Building";"CreepTumorQueen";NA;476;0
"Unit";"Zergling";"Larva";476;1
"Unit";"Zergling";"Larva";477;1
"Unit";"Zergling";"Larva";478;1
"Unit";"Zergling";"Larva";479;1
"Unit";"Zergling";"Larva";480;1
"Unit";"Zergling";"Larva";481;1
"Unit";"Mutalisk";"Larva";482;2
"Unit";"Mutalisk";"Larva";484;2
"Unit";"Mutalisk";"Larva";486;2
"Unit";"Mutalisk";"Larva";488;2
"Unit";"Baneling";"Zergling";490;0
"Unit";"Baneling";"Zergling";490;0
"Unit";"Mutalisk";"Larva";490;2
"Unit";"Mutalisk";"Larva";492;2
"Unit";"Mutalisk";"Larva";494;2
"Building";"CreepTumor";NA;496;0
"Building";"CreepTumor";NA;496;0
"Building";"CreepTumor";NA;496;0
"Building";"CreepTumor";NA;496;0
"Building";"CreepTumor";NA;496;0
"Building";"CreepTumorQueen";NA;496;0
"Building";"CreepTumor";NA;496;0
"Building";"CreepTumor";NA;496;0
"Unit";"Mutalisk";"Larva";496;2
"Unit";"Mutalisk";"Larva";498;2
"Unit";"Mutalisk";"Larva";500;2
"Unit";"Mutalisk";"Larva";502;2
"Building";"CreepTumorQueen";NA;504;0
"Building";"Hatchery";NA;504;0
"Upgrade";"Burrow";"Hatchery";504;0
"Unit";"Zergling";"Larva";504;1
"Unit";"Zergling";"Larva";505;1
"Unit";"Zergling";"Larva";506;1
"Unit";"Zergling";"Larva";507;1
"Unit";"Zergling";"Larva";508;1
"Unit";"Zergling";"Larva";509;1
"Unit";"Zergling";"Larva";510;1
"Unit";"Zergling";"Larva";511;1
"Unit";"Zergling";"Larva";512;1
"Unit";"Zergling";"Larva";513;1
"Unit";"Zergling";"Larva";514;1
"Unit";"Zergling";"Larva";515;1
"Unit";"Zergling";"Larva";516;1
"Unit";"Zergling";"Larva";517;1
"Unit";"Zergling";"Larva";518;1
"Unit";"Zergling";"Larva";519;1
"Unit";"Zergling";"Larva";520;1
"Unit";"Zergling";"Larva";521;1
"Unit";"Zergling";"Larva";522;1
"Unit";"Zergling";"Larva";523;1
"Unit";"Zergling";"Larva";524;1
"Unit";"Zergling";"Larva";525;1
"Unit";"Zergling";"Larva";526;1
"Unit";"Zergling";"Larva";527;1
"Unit";"Zergling";"Larva";528;1
"Unit";"Zergling";"Larva";529;1
"Unit";"Zergling";"Larva";530;1
"Unit";"Zergling";"Larva";531;1
"Unit";"Zergling";"Larva";532;1
"Unit";"Zergling";"Larva";533;1
"Unit";"Zergling";"Larva";534;1
"Unit";"Zergling";"Larva";535;1
"Unit";"Zergling";"Larva";536;1
"Unit";"Zergling";"Larva";537;1
"Unit";"Zergling";"Larva";538;1
"Unit";"Zergling";"Larva";539;1
"Unit";"Zergling";"Larva";540;1
"Unit";"Zergling";"Larva";541;1
"Unit";"Zergling";"Larva";542;1
"Unit";"Zergling";"Larva";543;1
"Building";"UltraliskCavern";NA;544;0
"Unit";"Zergling";"Larva";544;1
"Unit";"Zergling";"Larva";545;1
"Unit";"Zergling";"Larva";546;1
"Unit";"Zergling";"Larva";547;1
"Unit";"Zergling";"Larva";548;1
"Unit";"Zergling";"Larva";549;1
"Unit";"Zergling";"Larva";550;1
"Unit";"Zergling";"Larva";551;1
"Unit";"Zergling";"Larva";552;1
"Unit";"Zergling";"Larva";553;1
"Unit";"Zergling";"Larva";554;1
"Unit";"Zergling";"Larva";555;1
"Unit";"Zergling";"Larva";556;1
"Unit";"Zergling";"Larva";557;1
"Unit";"Zergling";"Larva";558;1
"Unit";"Zergling";"Larva";559;1
"Unit";"Zergling";"Larva";560;1
"Unit";"Zergling";"Larva";561;1
"Building";"Extractor";NA;562;0
"Building";"CreepTumor";NA;562;0
"Building";"CreepTumor";NA;562;0
"Building";"CreepTumor";NA;562;0
"Building";"CreepTumor";NA;562;0
"Building";"CreepTumor";NA;562;0
"Building";"CreepTumor";NA;562;0
"Building";"CreepTumor";NA;562;0
"Building";"CreepTumor";NA;562;0
"Unit";"Overlord";"Larva";562;0
"Unit";"Overlord";"Larva";562;0
"Unit";"Overlord";"Larva";562;0
"Unit";"Ultralisk";"Larva";562;6
"Unit";"Zergling";"Larva";568;1
"Unit";"Zergling";"Larva";569;1
"Unit";"Zergling";"Larva";570;1
"Unit";"Zergling";"Larva";571;1
"Unit";"Zergling";"Larva";572;1
"Unit";"Zergling";"Larva";573;1
"Unit";"Zergling";"Larva";574;1
"Unit";"Zergling";"Larva";575;1
"Unit";"Zergling";"Larva";576;1
"Unit";"Zergling";"Larva";577;1
"Unit";"Zergling";"Larva";578;1
"Unit";"Zergling";"Larva";579;1
"Unit";"Zergling";"Larva";580;1
"Unit";"Zergling";"Larva";581;1
"Unit";"Zergling";"Larva";582;1
"Unit";"Zergling";"Larva";583;1
"Unit";"Zergling";"Larva";584;1
"Unit";"Zergling";"Larva";585;1
"Unit";"Zergling";"Larva";586;1
"Unit";"Zergling";"Larva";587;1
"Unit";"Zergling";"Larva";588;1
"Unit";"Zergling";"Larva";589;1
"Unit";"Zergling";"Larva";590;1
"Unit";"Zergling";"Larva";591;1
"Unit";"Ultralisk";"Larva";592;6
"Building";"CreepTumor";NA;598;0
"Unit";"Zergling";"Larva";598;1
"Unit";"Zergling";"Larva";599;1
"Unit";"Zergling";"Larva";600;1
"Unit";"Zergling";"Larva";601;1
"Unit";"Zergling";"Larva";602;1
"Unit";"Zergling";"Larva";603;1
"Unit";"Zergling";"Larva";604;1
"Unit";"Zergling";"Larva";605;1
"Unit";"Zergling";"Larva";606;1
"Unit";"Zergling";"Larva";607;1
"Unit";"Zergling";"Larva";608;1
"Unit";"Zergling";"Larva";609;1
"Unit";"Zergling";"Larva";610;1
"Unit";"Zergling";"Larva";611;1
"Unit";"Zergling";"Larva";612;1
"Unit";"Zergling";"Larva";613;1
"Unit";"Zergling";"Larva";614;1
"Unit";"Zergling";"Larva";615;1
"Unit";"Zergling";"Larva";616;1
"Unit";"Zergling";"Larva";617;1
"Unit";"Zergling";"Larva";618;1
"Unit";"Zergling";"Larva";619;1
"Unit";"Zergling";"Larva";620;1
"Unit";"Zergling";"Larva";621;1
"Unit";"Zergling";"Larva";622;1
"Unit";"Zergling";"Larva";623;1
"Unit";"Zergling";"Larva";624;1
"Unit";"Zergling";"Larva";625;1
"Unit";"Zergling";"Larva";626;1
"Unit";"Zergling";"Larva";627;1
"Unit";"Zergling";"Larva";628;1
"Unit";"Zergling";"Larva";629;1
"Unit";"Zergling";"Larva";630;1
"Unit";"Zergling";"Larva";631;1
"Upgrade";"ChitinousPlating";"UltraliskCavern";632;0
"Unit";"Ultralisk";"Larva";632;6
"Unit";"Zergling";"Larva";638;1
"Unit";"Zergling";"Larva";639;1
"Unit";"Zergling";"Larva";640;1
"Unit";"Zergling";"Larva";641;1
"Building";"CreepTumor";NA;642;0
"Building";"CreepTumor";NA;642;0
"Building";"CreepTumor";NA;642;0
"Building";"CreepTumor";NA;642;0
"Building";"CreepTumor";NA;642;0
"Building";"CreepTumor";NA;642;0
"Unit";"Baneling";"Zergling";642;0
"Unit";"Baneling";"Zergling";642;0
"Unit";"Baneling";"Zergling";642;0
"Unit";"Baneling";"Zergling";642;0
"Unit";"Baneling";"Zergling";642;0
"Unit";"Baneling";"Zergling";642;0
"Unit";"Baneling";"Zergling";642;0
"Unit";"Baneling";"Zergling";642;0
"Unit";"Baneling";"Zergling";642;0
"Unit";"Baneling";"Zergling";642;0
"Unit";"Baneling";"Zergling";642;0
"Unit";"Baneling";"Zergling";642;0
"Unit";"Baneling";"Zergling";642;0
"Unit";"Baneling";"Zergling";642;0
"Unit";"Baneling";"Zergling";642;0
"Unit";"Baneling";"Zergling";642;0
"Unit";"Baneling";"Zergling";642;0
"Unit";"Baneling";"Zergling";642;0
"Unit";"Baneling";"Zergling";642;0
"Unit";"Baneling";"Zergling";642;0
"Unit";"Baneling";"Zergling";642;0
"Unit";"Baneling";"Zergling";642;0
"Unit";"Baneling";"Zergling";642;0
"Unit";"Baneling";"Zergling";642;0
"Unit";"Baneling";"Zergling";642;0
"Unit";"Baneling";"Zergling";642;0
"Unit";"Baneling";"Zergling";642;0
"Unit";"Baneling";"Zergling";642;0
"Unit";"Baneling";"Zergling";642;0
"Unit";"Baneling";"Zergling";642;0
"Unit";"Baneling";"Zergling";642;0
"Unit";"Baneling";"Zergling";642;0
"Unit";"Baneling";"Zergling";642;0
"Unit";"Baneling";"Zergling";642;0
"Unit";"Baneling";"Zergling";642;0
"Unit";"Baneling";"Zergling";642;0
"Unit";"Baneling";"Zergling";642;0
"Unit";"Zergling";"Larva";642;1
"Unit";"Zergling";"Larva";643;1
"Unit";"Zergling";"Larva";644;1
"Unit";"Zergling";"Larva";645;1
"Upgrade";"SprayZerg";NA;646;0
"Upgrade";"SprayZerg";NA;646;0
"Upgrade";"SprayZerg";NA;646;0
"Upgrade";"zerglingmovementspeed";NA;646;0
"Upgrade";"SprayZerg";NA;646;0
"Upgrade";"SprayZerg";NA;646;0
"Upgrade";"SprayZerg";NA;646;0
"Upgrade";"SprayZerg";NA;646;0
"Upgrade";"ZergGroundArmorsLevel1";NA;646;0
"Upgrade";"ZergMeleeWeaponsLevel1";NA;646;0
"Upgrade";"overlordspeed";NA;646;0
"Upgrade";"SprayZerg";NA;646;0
"Upgrade";"SprayZerg";NA;646;0
"Upgrade";"CentrificalHooks";NA;646;0
"Upgrade";"SprayZerg";NA;646;0
"Upgrade";"ZergGroundArmorsLevel2";NA;646;0
"Upgrade";"ZergMeleeWeaponsLevel2";NA;646;0
"Upgrade";"ZergFlyerWeaponsLevel1";NA;646;0
"Upgrade";"SprayZerg";NA;646;0
"Upgrade";"SprayZerg";NA;646;0
"Upgrade";"zerglingattackspeed";NA;646;0
"Upgrade";"ZergGroundArmorsLevel3";NA;646;0
