"type";"unit_name";"on_building";"total_supply_lag";"supply"
"Unit";"Overlord";"Larva";13;0
"Building";"Hatchery";NA;17;0
"Building";"Extractor";NA;19;0
"Building";"SpawningPool";NA;19;0
"Unit";"Overlord";"Larva";23;0
"Unit";"Queen";"Hatchery";23;2
"Unit";"Queen";"Hatchery";25;2
"Unit";"Zergling";"Larva";27;1
"Unit";"Zergling";"Larva";28;1
"Unit";"Zergling";"Larva";29;1
"Unit";"Zergling";"Larva";30;1
"Unit";"Zergling";"Larva";31;1
"Unit";"Zergling";"Larva";32;1
"Building";"Hatchery";NA;34;0
"Unit";"Zergling";"Larva";37;1
"Unit";"Zergling";"Larva";38;1
"Unit";"Zergling";"Larva";39;1
"Unit";"Zergling";"Larva";40;1
"Building";"CreepTumorQueen";NA;41;0
"Unit";"Overlord";"Larva";42;0
"Unit";"Queen";"Hatchery";42;2
"Unit";"Zergling";"Larva";44;1
"Unit";"Zergling";"Larva";45;1
"Unit";"Zergling";"Larva";46;1
"Unit";"Zergling";"Larva";47;1
"Unit";"Zergling";"Larva";48;1
"Unit";"Zergling";"Larva";49;1
"Unit";"Zergling";"Larva";50;1
"Unit";"Zergling";"Larva";51;1
"Unit";"Zergling";"Larva";52;1
"Unit";"Zergling";"Larva";53;1
"Unit";"Zergling";"Larva";54;1
"Unit";"Zergling";"Larva";55;1
"Unit";"Zergling";"Larva";56;1
"Unit";"Zergling";"Larva";57;1
"Unit";"Zergling";"Larva";58;1
"Unit";"Zergling";"Larva";59;1
"Building";"CreepTumor";NA;60;0
"Unit";"Queen";"Hatchery";60;2
"Unit";"Overlord";"Larva";62;0
"Unit";"Queen";"Hatchery";62;2
"Unit";"Zergling";"Larva";64;1
"Unit";"Zergling";"Larva";65;1
"Unit";"Zergling";"Larva";66;1
"Unit";"Zergling";"Larva";67;1
"Unit";"Zergling";"Larva";68;1
"Unit";"Zergling";"Larva";69;1
"Unit";"Zergling";"Larva";70;1
"Unit";"Zergling";"Larva";71;1
"Unit";"Zergling";"Larva";72;1
"Unit";"Zergling";"Larva";73;1
"Unit";"Zergling";"Larva";74;1
"Unit";"Zergling";"Larva";75;1
"Unit";"Zergling";"Larva";76;1
"Unit";"Zergling";"Larva";77;1
"Unit";"Zergling";"Larva";78;1
"Unit";"Zergling";"Larva";79;1
"Unit";"Zergling";"Larva";80;1
"Unit";"Zergling";"Larva";81;1
"Unit";"Zergling";"Larva";82;1
"Unit";"Zergling";"Larva";83;1
"Unit";"Zergling";"Larva";84;1
"Unit";"Zergling";"Larva";85;1
"Unit";"Zergling";"Larva";86;1
"Unit";"Zergling";"Larva";87;1
"Unit";"Zergling";"Larva";88;1
"Unit";"Zergling";"Larva";89;1
"Unit";"Zergling";"Larva";90;1
"Unit";"Zergling";"Larva";91;1
"Building";"CreepTumorQueen";NA;99;0
"Building";"CreepTumor";NA;99;0
"Unit";"Overlord";"Larva";100;0
"Unit";"Overlord";"Larva";100;0
"Building";"EvolutionChamber";NA;100;0
"Building";"CreepTumor";NA;100;0
"Building";"CreepTumorQueen";NA;100;0
"Unit";"Overlord";"Larva";101;0
"Building";"EvolutionChamber";NA;101;0
"Building";"CreepTumorQueen";NA;114;0
"Building";"CreepTumorQueen";NA;117;0
"Building";"Extractor";NA;117;0
"Building";"CreepTumor";NA;121;0
"Building";"CreepTumor";NA;121;0
"Building";"CreepTumorQueen";NA;121;0
"Building";"CreepTumor";NA;121;0
"Unit";"Overlord";"Larva";127;0
"Unit";"Overlord";"Larva";127;0
"Unit";"Overlord";"Larva";127;0
"Building";"CreepTumorQueen";NA;127;0
"Building";"CreepTumorQueen";NA;127;0
"Building";"Extractor";NA;127;0
"Building";"BanelingNest";NA;128;0
"Unit";"Zergling";"Larva";134;1
"Unit";"Zergling";"Larva";135;1
"Unit";"Zergling";"Larva";136;1
"Unit";"Zergling";"Larva";137;1
"Unit";"Zergling";"Larva";138;1
"Unit";"Zergling";"Larva";139;1
"Unit";"Zergling";"Larva";140;1
"Unit";"Zergling";"Larva";141;1
"Building";"CreepTumor";NA;142;0
"Building";"CreepTumor";NA;142;0
"Unit";"Zergling";"Larva";142;1
"Unit";"Zergling";"Larva";143;1
"Unit";"Zergling";"Larva";144;1
"Unit";"Zergling";"Larva";145;1
"Unit";"Overlord";"Larva";146;0
"Unit";"Zergling";"Larva";146;1
"Unit";"Zergling";"Larva";147;1
"Unit";"Zergling";"Larva";148;1
"Unit";"Zergling";"Larva";149;1
"Unit";"Zergling";"Larva";150;1
"Unit";"Zergling";"Larva";151;1
"Unit";"Zergling";"Larva";152;1
"Unit";"Zergling";"Larva";153;1
"Unit";"Zergling";"Larva";154;1
"Unit";"Zergling";"Larva";155;1
"Unit";"Zergling";"Larva";156;1
"Unit";"Zergling";"Larva";157;1
"Unit";"Zergling";"Larva";158;1
"Unit";"Zergling";"Larva";159;1
"Unit";"Zergling";"Larva";160;1
"Unit";"Zergling";"Larva";161;1
"Unit";"Zergling";"Larva";162;1
"Unit";"Zergling";"Larva";163;1
"Unit";"Zergling";"Larva";164;1
"Unit";"Zergling";"Larva";165;1
"Unit";"Zergling";"Larva";166;1
"Unit";"Zergling";"Larva";167;1
"Unit";"Overlord";"Larva";168;0
"Unit";"Baneling";"Zergling";176;0
"Building";"Extractor";NA;176;0
"Unit";"Baneling";"Zergling";176;0
"Unit";"Baneling";"Zergling";176;0
"Unit";"Baneling";"Zergling";176;0
"Unit";"Baneling";"Zergling";176;0
"Building";"Hatchery";NA;176;0
"Unit";"Queen";"Hatchery";182;2
"Building";"Extractor";NA;184;0
"Building";"Extractor";NA;186;0
"Unit";"Zergling";"Larva";186;1
"Unit";"Zergling";"Larva";187;1
"Unit";"Zergling";"Larva";188;1
"Unit";"Zergling";"Larva";189;1
"Unit";"Zergling";"Larva";190;1
"Unit";"Zergling";"Larva";191;1
"Unit";"Zergling";"Larva";192;1
"Unit";"Zergling";"Larva";193;1
"Unit";"Overlord";"Larva";194;0
"Unit";"Zergling";"Larva";194;1
"Unit";"Zergling";"Larva";195;1
"Unit";"Zergling";"Larva";196;1
"Unit";"Zergling";"Larva";197;1
"Unit";"Zergling";"Larva";198;1
"Unit";"Zergling";"Larva";199;1
"Unit";"Zergling";"Larva";200;1
"Unit";"Zergling";"Larva";201;1
"Unit";"Zergling";"Larva";202;1
"Unit";"Zergling";"Larva";203;1
"Unit";"Zergling";"Larva";204;1
"Unit";"Zergling";"Larva";205;1
"Building";"CreepTumor";NA;206;0
"Unit";"Overlord";"Larva";206;0
"Building";"Spire";NA;206;0
"Unit";"Zergling";"Larva";206;1
"Unit";"Zergling";"Larva";207;1
"Unit";"Zergling";"Larva";208;1
"Unit";"Zergling";"Larva";209;1
"Unit";"Zergling";"Larva";210;1
"Unit";"Zergling";"Larva";211;1
"Unit";"Zergling";"Larva";212;1
"Unit";"Zergling";"Larva";213;1
"Unit";"Zergling";"Larva";214;1
"Unit";"Zergling";"Larva";215;1
"Building";"Hatchery";NA;216;0
"Unit";"Zergling";"Larva";216;1
"Unit";"Zergling";"Larva";217;1
"Unit";"Zergling";"Larva";218;1
"Unit";"Zergling";"Larva";219;1
"Unit";"Zergling";"Larva";220;1
"Unit";"Zergling";"Larva";221;1
"Unit";"Zergling";"Larva";222;1
"Unit";"Zergling";"Larva";223;1
"Building";"CreepTumorQueen";NA;224;0
"Unit";"Overlord";"Larva";224;0
"Unit";"Zergling";"Larva";224;1
"Unit";"Zergling";"Larva";225;1
"Unit";"Zergling";"Larva";226;1
"Unit";"Zergling";"Larva";227;1
"Unit";"Zergling";"Larva";228;1
"Unit";"Zergling";"Larva";229;1
"Unit";"Zergling";"Larva";230;1
"Unit";"Zergling";"Larva";231;1
"Unit";"Zergling";"Larva";232;1
"Unit";"Zergling";"Larva";233;1
"Unit";"Zergling";"Larva";234;1
"Unit";"Zergling";"Larva";235;1
"Unit";"Overlord";"Larva";236;0
"Unit";"Zergling";"Larva";236;1
"Unit";"Zergling";"Larva";237;1
"Unit";"Zergling";"Larva";238;1
"Unit";"Zergling";"Larva";239;1
"Unit";"Zergling";"Larva";240;1
"Unit";"Zergling";"Larva";241;1
"Unit";"Zergling";"Larva";242;1
"Unit";"Zergling";"Larva";243;1
"Unit";"Zergling";"Larva";244;1
"Unit";"Zergling";"Larva";245;1
"Unit";"Zergling";"Larva";246;1
"Unit";"Zergling";"Larva";247;1
"Unit";"Zergling";"Larva";248;1
"Unit";"Zergling";"Larva";249;1
"Unit";"Zergling";"Larva";250;1
"Unit";"Zergling";"Larva";251;1
"Unit";"Zergling";"Larva";252;1
"Unit";"Zergling";"Larva";253;1
"Unit";"Zergling";"Larva";254;1
"Unit";"Zergling";"Larva";255;1
"Unit";"Zergling";"Larva";256;1
"Unit";"Zergling";"Larva";257;1
"Unit";"Zergling";"Larva";258;1
"Unit";"Zergling";"Larva";259;1
"Unit";"Zergling";"Larva";260;1
"Unit";"Zergling";"Larva";261;1
"Unit";"Queen";"Hatchery";262;2
"Unit";"Overlord";"Larva";264;0
"Unit";"Baneling";"Zergling";264;0
"Unit";"Baneling";"Zergling";264;0
"Unit";"Baneling";"Zergling";264;0
"Unit";"Baneling";"Zergling";264;0
"Unit";"Baneling";"Zergling";264;0
"Unit";"Baneling";"Zergling";264;0
"Building";"CreepTumor";NA;264;0
"Unit";"Overlord";"Larva";275;0
"Unit";"Zergling";"Larva";275;1
"Unit";"Zergling";"Larva";276;1
"Unit";"Zergling";"Larva";277;1
"Unit";"Zergling";"Larva";278;1
"Unit";"Zergling";"Larva";279;1
"Unit";"Zergling";"Larva";280;1
"Unit";"Zergling";"Larva";281;1
"Unit";"Zergling";"Larva";282;1
"Building";"SporeCrawler";NA;283;0
"Unit";"Mutalisk";"Larva";283;2
"Unit";"Mutalisk";"Larva";285;2
"Unit";"Mutalisk";"Larva";287;2
"Unit";"Mutalisk";"Larva";289;2
"Unit";"Mutalisk";"Larva";291;2
"Unit";"Mutalisk";"Larva";293;2
"Unit";"Mutalisk";"Larva";295;2
"Unit";"Mutalisk";"Larva";297;2
"Unit";"Mutalisk";"Larva";299;2
"Unit";"Mutalisk";"Larva";301;2
"Unit";"Mutalisk";"Larva";303;2
"Building";"CreepTumor";NA;305;0
"Unit";"Zergling";"Larva";305;1
"Unit";"Zergling";"Larva";306;1
"Unit";"Zergling";"Larva";307;1
"Unit";"Zergling";"Larva";308;1
"Unit";"Zergling";"Larva";309;1
"Unit";"Zergling";"Larva";310;1
"Unit";"Zergling";"Larva";311;1
"Unit";"Zergling";"Larva";312;1
"Unit";"Zergling";"Larva";313;1
"Unit";"Zergling";"Larva";314;1
"Unit";"Zergling";"Larva";315;1
"Unit";"Zergling";"Larva";316;1
"Unit";"Zergling";"Larva";317;1
"Unit";"Zergling";"Larva";318;1
"Unit";"Zergling";"Larva";319;1
"Unit";"Zergling";"Larva";320;1
"Unit";"Zergling";"Larva";321;1
"Unit";"Zergling";"Larva";322;1
"Unit";"Zergling";"Larva";323;1
"Unit";"Zergling";"Larva";324;1
"Building";"CreepTumorQueen";NA;325;0
"Unit";"Baneling";"Zergling";325;0
"Unit";"Baneling";"Zergling";325;0
"Unit";"Baneling";"Zergling";325;0
"Unit";"Baneling";"Zergling";325;0
"Unit";"Baneling";"Zergling";325;0
"Unit";"Baneling";"Zergling";325;0
"Unit";"Zergling";"Larva";325;1
"Unit";"Zergling";"Larva";326;1
"Unit";"Zergling";"Larva";327;1
"Unit";"Zergling";"Larva";328;1
"Unit";"Zergling";"Larva";329;1
"Unit";"Zergling";"Larva";330;1
"Unit";"Zergling";"Larva";331;1
"Unit";"Zergling";"Larva";332;1
"Unit";"Zergling";"Larva";333;1
"Unit";"Zergling";"Larva";334;1
"Unit";"Zergling";"Larva";335;1
"Unit";"Zergling";"Larva";336;1
"Unit";"Zergling";"Larva";337;1
"Unit";"Zergling";"Larva";338;1
"Unit";"Overlord";"Larva";339;0
"Unit";"Zergling";"Larva";339;1
"Unit";"Zergling";"Larva";340;1
"Unit";"Zergling";"Larva";341;1
"Unit";"Zergling";"Larva";342;1
"Unit";"Zergling";"Larva";343;1
"Unit";"Zergling";"Larva";344;1
"Unit";"Zergling";"Larva";345;1
"Unit";"Zergling";"Larva";346;1
"Building";"Extractor";NA;352;0
"Unit";"Zergling";"Larva";352;1
"Unit";"Zergling";"Larva";353;1
"Unit";"Zergling";"Larva";354;1
"Unit";"Zergling";"Larva";355;1
"Unit";"Zergling";"Larva";356;1
"Unit";"Zergling";"Larva";357;1
"Unit";"Zergling";"Larva";358;1
"Unit";"Zergling";"Larva";359;1
"Unit";"Zergling";"Larva";360;1
"Unit";"Zergling";"Larva";361;1
"Unit";"Zergling";"Larva";362;1
"Unit";"Zergling";"Larva";363;1
"Unit";"Zergling";"Larva";364;1
"Unit";"Zergling";"Larva";365;1
"Unit";"Zergling";"Larva";366;1
"Unit";"Zergling";"Larva";367;1
"Unit";"Zergling";"Larva";368;1
"Unit";"Zergling";"Larva";369;1
"Unit";"Zergling";"Larva";370;1
"Unit";"Zergling";"Larva";371;1
"Building";"CreepTumor";NA;372;0
"Building";"CreepTumor";NA;372;0
"Building";"CreepTumor";NA;372;0
"Unit";"Baneling";"Zergling";372;0
"Unit";"Baneling";"Zergling";372;0
"Unit";"Baneling";"Zergling";372;0
"Unit";"Baneling";"Zergling";372;0
"Unit";"Baneling";"Zergling";372;0
"Unit";"Baneling";"Zergling";372;0
"Unit";"Baneling";"Zergling";372;0
"Unit";"Baneling";"Zergling";372;0
"Unit";"Baneling";"Zergling";372;0
"Unit";"Baneling";"Zergling";372;0
"Building";"CreepTumorQueen";NA;372;0
"Unit";"Baneling";"Zergling";372;0
"Unit";"Baneling";"Zergling";372;0
"Unit";"Baneling";"Zergling";372;0
"Unit";"Baneling";"Zergling";372;0
"Unit";"Overlord";"Larva";372;0
"Building";"InfestationPit";NA;372;0
"Unit";"Mutalisk";"Larva";372;2
"Unit";"Mutalisk";"Larva";374;2
"Unit";"Mutalisk";"Larva";376;2
"Building";"Extractor";NA;378;0
"Unit";"Overlord";"Larva";380;0
"Unit";"Zergling";"Larva";380;1
"Unit";"Zergling";"Larva";381;1
"Unit";"Zergling";"Larva";382;1
"Unit";"Zergling";"Larva";383;1
"Unit";"Zergling";"Larva";384;1
"Unit";"Zergling";"Larva";385;1
"Unit";"Zergling";"Larva";386;1
"Unit";"Zergling";"Larva";387;1
"Unit";"Zergling";"Larva";388;1
"Unit";"Zergling";"Larva";389;1
"Unit";"Zergling";"Larva";390;1
"Unit";"Zergling";"Larva";391;1
"Unit";"Zergling";"Larva";392;1
"Unit";"Zergling";"Larva";393;1
"Building";"CreepTumor";NA;394;0
"Building";"CreepTumor";NA;394;0
"Unit";"Overlord";"Larva";394;0
"Unit";"Overlord";"Larva";394;0
"Building";"CreepTumor";NA;394;0
"Unit";"Baneling";"Zergling";394;0
"Unit";"Baneling";"Zergling";394;0
"Unit";"Baneling";"Zergling";394;0
"Unit";"Baneling";"Zergling";394;0
"Unit";"Baneling";"Zergling";394;0
"Unit";"Baneling";"Zergling";394;0
"Building";"CreepTumor";NA;394;0
"Building";"CreepTumor";NA;394;0
"Unit";"Zergling";"Larva";394;1
"Unit";"Zergling";"Larva";395;1
"Unit";"Zergling";"Larva";396;1
"Unit";"Zergling";"Larva";397;1
"Unit";"Zergling";"Larva";398;1
"Unit";"Zergling";"Larva";399;1
"Unit";"Zergling";"Larva";400;1
"Unit";"Zergling";"Larva";401;1
"Unit";"Zergling";"Larva";402;1
"Unit";"Zergling";"Larva";403;1
"Unit";"Zergling";"Larva";404;1
"Unit";"Zergling";"Larva";405;1
"Unit";"Zergling";"Larva";406;1
"Unit";"Zergling";"Larva";407;1
"Unit";"Zergling";"Larva";408;1
"Unit";"Zergling";"Larva";409;1
"Unit";"Overlord";"Larva";410;0
"Unit";"Zergling";"Larva";410;1
"Unit";"Zergling";"Larva";411;1
"Unit";"Zergling";"Larva";412;1
"Unit";"Zergling";"Larva";413;1
"Unit";"Zergling";"Larva";414;1
"Unit";"Zergling";"Larva";415;1
"Unit";"Zergling";"Larva";416;1
"Unit";"Zergling";"Larva";417;1
"Building";"CreepTumor";NA;418;0
"Unit";"Zergling";"Larva";418;1
"Unit";"Zergling";"Larva";419;1
"Unit";"Zergling";"Larva";420;1
"Unit";"Zergling";"Larva";421;1
"Unit";"Zergling";"Larva";422;1
"Unit";"Zergling";"Larva";423;1
"Unit";"Zergling";"Larva";424;1
"Unit";"Zergling";"Larva";425;1
"Unit";"Zergling";"Larva";426;1
"Unit";"Zergling";"Larva";427;1
"Unit";"Zergling";"Larva";428;1
"Unit";"Zergling";"Larva";429;1
"Unit";"Zergling";"Larva";430;1
"Unit";"Zergling";"Larva";431;1
"Unit";"Zergling";"Larva";432;1
"Unit";"Zergling";"Larva";433;1
"Unit";"Zergling";"Larva";434;1
"Unit";"Zergling";"Larva";435;1
"Unit";"Zergling";"Larva";436;1
"Unit";"Zergling";"Larva";437;1
"Unit";"Zergling";"Larva";438;1
"Unit";"Zergling";"Larva";439;1
"Unit";"Zergling";"Larva";440;1
"Unit";"Zergling";"Larva";441;1
"Unit";"Zergling";"Larva";442;1
"Unit";"Zergling";"Larva";443;1
"Unit";"Zergling";"Larva";444;1
"Unit";"Zergling";"Larva";445;1
"Unit";"Zergling";"Larva";446;1
"Unit";"Zergling";"Larva";447;1
"Unit";"Zergling";"Larva";448;1
"Unit";"Zergling";"Larva";449;1
"Unit";"Zergling";"Larva";450;1
"Unit";"Zergling";"Larva";451;1
"Unit";"Zergling";"Larva";452;1
"Unit";"Zergling";"Larva";453;1
"Unit";"Baneling";"Zergling";454;0
"Unit";"Baneling";"Zergling";454;0
"Unit";"Baneling";"Zergling";454;0
"Unit";"Baneling";"Zergling";454;0
"Unit";"Baneling";"Zergling";454;0
"Unit";"Baneling";"Zergling";454;0
"Unit";"Baneling";"Zergling";454;0
"Unit";"Baneling";"Zergling";454;0
"Unit";"Baneling";"Zergling";454;0
"Unit";"Baneling";"Zergling";454;0
"Unit";"Baneling";"Zergling";454;0
"Unit";"Baneling";"Zergling";454;0
"Unit";"Baneling";"Zergling";454;0
"Unit";"Baneling";"Zergling";454;0
"Unit";"Baneling";"Zergling";454;0
"Unit";"Baneling";"Zergling";454;0
"Unit";"Baneling";"Zergling";454;0
"Unit";"Baneling";"Zergling";454;0
"Unit";"Baneling";"Zergling";454;0
"Unit";"Baneling";"Zergling";454;0
"Unit";"Baneling";"Zergling";454;0
"Unit";"Baneling";"Zergling";454;0
"Unit";"Baneling";"Zergling";454;0
"Unit";"Baneling";"Zergling";454;0
"Unit";"Baneling";"Zergling";454;0
"Unit";"Zergling";"Larva";454;1
"Unit";"Zergling";"Larva";455;1
"Unit";"Zergling";"Larva";456;1
"Unit";"Zergling";"Larva";457;1
"Unit";"Zergling";"Larva";458;1
"Unit";"Zergling";"Larva";459;1
"Unit";"Zergling";"Larva";460;1
"Unit";"Zergling";"Larva";461;1
"Unit";"Zergling";"Larva";462;1
"Unit";"Zergling";"Larva";463;1
"Unit";"Zergling";"Larva";464;1
"Unit";"Zergling";"Larva";465;1
"Unit";"Zergling";"Larva";466;1
"Unit";"Zergling";"Larva";467;1
"Unit";"Zergling";"Larva";468;1
"Unit";"Zergling";"Larva";469;1
"Unit";"Zergling";"Larva";470;1
"Unit";"Zergling";"Larva";471;1
"Unit";"Zergling";"Larva";472;1
"Unit";"Zergling";"Larva";473;1
"Unit";"Zergling";"Larva";474;1
"Unit";"Zergling";"Larva";475;1
"Unit";"Zergling";"Larva";476;1
"Unit";"Zergling";"Larva";477;1
"Unit";"Zergling";"Larva";478;1
"Unit";"Zergling";"Larva";479;1
"Unit";"Zergling";"Larva";480;1
"Unit";"Zergling";"Larva";481;1
"Unit";"Zergling";"Larva";482;1
"Unit";"Zergling";"Larva";483;1
"Unit";"Zergling";"Larva";484;1
"Unit";"Zergling";"Larva";485;1
"Unit";"Zergling";"Larva";486;1
"Unit";"Zergling";"Larva";487;1
"Unit";"Zergling";"Larva";488;1
"Unit";"Zergling";"Larva";489;1
"Unit";"Zergling";"Larva";490;1
"Unit";"Zergling";"Larva";491;1
"Unit";"Zergling";"Larva";492;1
"Unit";"Zergling";"Larva";493;1
"Unit";"Zergling";"Larva";494;1
"Unit";"Zergling";"Larva";495;1
"Unit";"Zergling";"Larva";496;1
"Unit";"Zergling";"Larva";497;1
"Unit";"Zergling";"Larva";498;1
"Unit";"Zergling";"Larva";499;1
"Unit";"Zergling";"Larva";500;1
"Unit";"Zergling";"Larva";501;1
"Unit";"Zergling";"Larva";502;1
"Unit";"Zergling";"Larva";503;1
"Unit";"Zergling";"Larva";504;1
"Unit";"Zergling";"Larva";505;1
"Unit";"Queen";"Hatchery";506;2
"Unit";"Queen";"Hatchery";508;2
"Unit";"Zergling";"Larva";510;1
"Unit";"Zergling";"Larva";511;1
"Unit";"Zergling";"Larva";512;1
"Unit";"Zergling";"Larva";513;1
"Unit";"Zergling";"Larva";514;1
"Unit";"Zergling";"Larva";515;1
"Unit";"Zergling";"Larva";516;1
"Unit";"Zergling";"Larva";517;1
"Unit";"Zergling";"Larva";518;1
"Unit";"Zergling";"Larva";519;1
"Unit";"Baneling";"Zergling";520;0
"Unit";"Baneling";"Zergling";520;0
"Unit";"Baneling";"Zergling";520;0
"Unit";"Baneling";"Zergling";520;0
"Unit";"Baneling";"Zergling";520;0
"Unit";"Baneling";"Zergling";520;0
"Unit";"Baneling";"Zergling";520;0
"Unit";"Baneling";"Zergling";520;0
"Unit";"Baneling";"Zergling";520;0
"Unit";"Baneling";"Zergling";520;0
"Unit";"Baneling";"Zergling";520;0
"Unit";"Baneling";"Zergling";520;0
"Unit";"Baneling";"Zergling";520;0
"Unit";"Baneling";"Zergling";520;0
"Unit";"Baneling";"Zergling";520;0
"Unit";"Baneling";"Zergling";520;0
"Unit";"Baneling";"Zergling";520;0
"Unit";"Baneling";"Zergling";520;0
"Unit";"Baneling";"Zergling";520;0
"Unit";"Baneling";"Zergling";520;0
"Unit";"Zergling";"Larva";520;1
"Unit";"Zergling";"Larva";521;1
"Unit";"Zergling";"Larva";522;1
"Unit";"Zergling";"Larva";523;1
"Unit";"Zergling";"Larva";524;1
"Unit";"Zergling";"Larva";525;1
"Unit";"Zergling";"Larva";526;1
"Unit";"Zergling";"Larva";527;1
"Unit";"Zergling";"Larva";528;1
"Unit";"Zergling";"Larva";529;1
"Unit";"Zergling";"Larva";530;1
"Unit";"Zergling";"Larva";531;1
"Unit";"Zergling";"Larva";532;1
"Unit";"Zergling";"Larva";533;1
"Unit";"Zergling";"Larva";534;1
"Unit";"Zergling";"Larva";535;1
"Unit";"Zergling";"Larva";536;1
"Unit";"Zergling";"Larva";537;1
"Unit";"Zergling";"Larva";538;1
"Unit";"Zergling";"Larva";539;1
"Unit";"Zergling";"Larva";540;1
"Unit";"Zergling";"Larva";541;1
"Unit";"Zergling";"Larva";542;1
"Unit";"Zergling";"Larva";543;1
"Unit";"Zergling";"Larva";544;1
"Unit";"Zergling";"Larva";545;1
"Unit";"Zergling";"Larva";546;1
"Unit";"Zergling";"Larva";547;1
"Unit";"Zergling";"Larva";548;1
"Unit";"Zergling";"Larva";549;1
"Unit";"Zergling";"Larva";550;1
"Unit";"Zergling";"Larva";551;1
"Unit";"Zergling";"Larva";552;1
"Unit";"Zergling";"Larva";553;1
"Unit";"Zergling";"Larva";554;1
"Unit";"Zergling";"Larva";555;1
"Unit";"Zergling";"Larva";556;1
"Unit";"Zergling";"Larva";557;1
"Unit";"Zergling";"Larva";558;1
"Unit";"Zergling";"Larva";559;1
"Unit";"Zergling";"Larva";560;1
"Unit";"Zergling";"Larva";561;1
"Unit";"Baneling";"Zergling";562;0
"Unit";"Baneling";"Zergling";562;0
"Unit";"Baneling";"Zergling";562;0
"Unit";"Baneling";"Zergling";562;0
"Unit";"Baneling";"Zergling";562;0
"Unit";"Baneling";"Zergling";562;0
"Unit";"Baneling";"Zergling";562;0
"Unit";"Baneling";"Zergling";562;0
"Unit";"Baneling";"Zergling";562;0
"Unit";"Zergling";"Larva";562;1
"Unit";"Zergling";"Larva";563;1
"Unit";"Zergling";"Larva";564;1
"Unit";"Zergling";"Larva";565;1
"Unit";"Zergling";"Larva";566;1
"Unit";"Zergling";"Larva";567;1
"Unit";"Zergling";"Larva";568;1
"Unit";"Zergling";"Larva";569;1
"Unit";"Zergling";"Larva";570;1
"Unit";"Zergling";"Larva";571;1
"Unit";"Zergling";"Larva";572;1
"Unit";"Zergling";"Larva";573;1
"Unit";"Zergling";"Larva";574;1
"Unit";"Zergling";"Larva";575;1
"Unit";"Zergling";"Larva";576;1
"Unit";"Zergling";"Larva";577;1
"Unit";"Zergling";"Larva";578;1
"Unit";"Zergling";"Larva";579;1
"Unit";"Zergling";"Larva";580;1
"Unit";"Zergling";"Larva";581;1
"Building";"UltraliskCavern";NA;582;0
"Building";"Hatchery";NA;582;0
"Unit";"Baneling";"Zergling";582;0
"Unit";"Baneling";"Zergling";582;0
"Unit";"Baneling";"Zergling";582;0
"Unit";"Baneling";"Zergling";582;0
"Unit";"Baneling";"Zergling";582;0
"Unit";"Baneling";"Zergling";582;0
"Unit";"Baneling";"Zergling";582;0
"Unit";"Baneling";"Zergling";582;0
"Unit";"Baneling";"Zergling";582;0
"Unit";"Zergling";"Larva";582;1
"Unit";"Zergling";"Larva";583;1
"Unit";"Zergling";"Larva";584;1
"Unit";"Zergling";"Larva";585;1
"Unit";"Zergling";"Larva";586;1
"Unit";"Zergling";"Larva";587;1
"Building";"Hatchery";NA;588;0
"Unit";"Zergling";"Larva";588;1
"Unit";"Zergling";"Larva";589;1
"Unit";"Zergling";"Larva";590;1
"Unit";"Zergling";"Larva";591;1
"Unit";"Zergling";"Larva";592;1
"Unit";"Zergling";"Larva";593;1
"Unit";"Zergling";"Larva";594;1
"Unit";"Zergling";"Larva";595;1
"Unit";"Zergling";"Larva";596;1
"Unit";"Zergling";"Larva";597;1
"Unit";"Zergling";"Larva";598;1
"Unit";"Zergling";"Larva";599;1
"Unit";"Zergling";"Larva";600;1
"Unit";"Zergling";"Larva";601;1
"Unit";"Zergling";"Larva";602;1
"Unit";"Zergling";"Larva";603;1
"Unit";"Zergling";"Larva";604;1
"Unit";"Zergling";"Larva";605;1
"Unit";"Zergling";"Larva";606;1
"Unit";"Zergling";"Larva";607;1
"Unit";"Zergling";"Larva";608;1
"Unit";"Zergling";"Larva";609;1
"Unit";"Zergling";"Larva";610;1
"Unit";"Zergling";"Larva";611;1
"Unit";"Zergling";"Larva";612;1
"Unit";"Zergling";"Larva";613;1
"Unit";"Zergling";"Larva";614;1
"Unit";"Zergling";"Larva";615;1
"Unit";"Zergling";"Larva";616;1
"Unit";"Zergling";"Larva";617;1
"Unit";"Zergling";"Larva";618;1
"Unit";"Zergling";"Larva";619;1
"Unit";"Zergling";"Larva";620;1
"Unit";"Zergling";"Larva";621;1
"Unit";"Ultralisk";"Larva";622;6
"Unit";"Ultralisk";"Larva";628;6
"Unit";"Ultralisk";"Larva";634;6
"Unit";"Ultralisk";"Larva";640;6
"Unit";"Ultralisk";"Larva";646;6
"Unit";"Baneling";"Zergling";652;0
"Unit";"Baneling";"Zergling";652;0
"Unit";"Baneling";"Zergling";652;0
"Unit";"Baneling";"Zergling";652;0
"Unit";"Baneling";"Zergling";652;0
"Unit";"Baneling";"Zergling";652;0
"Unit";"Baneling";"Zergling";652;0
"Unit";"Baneling";"Zergling";652;0
"Unit";"Baneling";"Zergling";652;0
"Unit";"Baneling";"Zergling";652;0
"Unit";"Baneling";"Zergling";652;0
"Unit";"Zergling";"Larva";652;1
"Unit";"Zergling";"Larva";653;1
"Unit";"Zergling";"Larva";654;1
"Unit";"Zergling";"Larva";655;1
"Unit";"Zergling";"Larva";656;1
"Unit";"Zergling";"Larva";657;1
"Unit";"Zergling";"Larva";658;1
"Unit";"Zergling";"Larva";659;1
"Unit";"Zergling";"Larva";660;1
"Unit";"Zergling";"Larva";661;1
"Unit";"Zergling";"Larva";662;1
"Unit";"Zergling";"Larva";663;1
"Unit";"Zergling";"Larva";664;1
"Unit";"Zergling";"Larva";665;1
"Unit";"Zergling";"Larva";666;1
"Unit";"Zergling";"Larva";667;1
"Unit";"Zergling";"Larva";668;1
"Unit";"Zergling";"Larva";669;1
"Unit";"Zergling";"Larva";670;1
"Unit";"Zergling";"Larva";671;1
"Unit";"Zergling";"Larva";672;1
"Unit";"Zergling";"Larva";673;1
"Unit";"Zergling";"Larva";674;1
"Unit";"Zergling";"Larva";675;1
"Building";"CreepTumor";NA;687;0
"Building";"CreepTumor";NA;687;0
"Unit";"Mutalisk";"Larva";687;2
"Unit";"Mutalisk";"Larva";689;2
"Unit";"Mutalisk";"Larva";691;2
"Unit";"Mutalisk";"Larva";693;2
"Building";"SpineCrawler";NA;695;0
"Unit";"Ultralisk";"Larva";697;6
"Unit";"Ultralisk";"Larva";703;6
"Unit";"Zergling";"Larva";709;1
"Unit";"Zergling";"Larva";710;1
"Unit";"Zergling";"Larva";711;1
"Unit";"Zergling";"Larva";712;1
"Unit";"Zergling";"Larva";713;1
"Unit";"Zergling";"Larva";714;1
"Unit";"Zergling";"Larva";715;1
"Unit";"Zergling";"Larva";716;1
"Unit";"Zergling";"Larva";717;1
"Unit";"Zergling";"Larva";718;1
"Unit";"Baneling";"Zergling";719;0
"Unit";"Baneling";"Zergling";719;0
"Unit";"Baneling";"Zergling";719;0
"Unit";"Baneling";"Zergling";719;0
"Unit";"Baneling";"Zergling";719;0
"Unit";"Baneling";"Zergling";719;0
"Unit";"Baneling";"Zergling";719;0
"Unit";"Baneling";"Zergling";719;0
"Unit";"Baneling";"Zergling";719;0
"Upgrade";"ChitinousPlating";"UltraliskCavern";719;0
"Building";"CreepTumorQueen";NA;719;0
"Building";"Hatchery";NA;719;0
"Building";"CreepTumorQueen";NA;719;0
"Unit";"Ultralisk";"Larva";719;6
"Unit";"Zergling";"Larva";725;1
"Unit";"Zergling";"Larva";726;1
"Unit";"Zergling";"Larva";727;1
"Unit";"Zergling";"Larva";728;1
"Unit";"Overlord";"Larva";729;0
"Unit";"Overlord";"Larva";729;0
"Unit";"Ultralisk";"Larva";729;6
"Unit";"Ultralisk";"Larva";735;6
"Unit";"Zergling";"Larva";741;1
"Unit";"Zergling";"Larva";742;1
"Unit";"Zergling";"Larva";743;1
"Unit";"Zergling";"Larva";744;1
"Unit";"Zergling";"Larva";745;1
"Unit";"Zergling";"Larva";746;1
"Unit";"Zergling";"Larva";747;1
"Unit";"Zergling";"Larva";748;1
"Unit";"Zergling";"Larva";749;1
"Unit";"Zergling";"Larva";750;1
"Unit";"Zergling";"Larva";751;1
"Unit";"Zergling";"Larva";752;1
"Unit";"Zergling";"Larva";753;1
"Unit";"Zergling";"Larva";754;1
"Unit";"Zergling";"Larva";755;1
"Unit";"Zergling";"Larva";756;1
"Unit";"Zergling";"Larva";757;1
"Unit";"Zergling";"Larva";758;1
"Unit";"Zergling";"Larva";759;1
"Unit";"Zergling";"Larva";760;1
"Unit";"Zergling";"Larva";761;1
"Unit";"Zergling";"Larva";762;1
"Upgrade";"Burrow";"Hatchery";763;0
"Unit";"Zergling";"Larva";763;1
"Unit";"Zergling";"Larva";764;1
"Unit";"Zergling";"Larva";765;1
"Unit";"Zergling";"Larva";766;1
"Unit";"Zergling";"Larva";767;1
"Unit";"Zergling";"Larva";768;1
"Unit";"Zergling";"Larva";769;1
"Unit";"Zergling";"Larva";770;1
"Unit";"Zergling";"Larva";771;1
"Unit";"Zergling";"Larva";772;1
"Unit";"Zergling";"Larva";773;1
"Unit";"Zergling";"Larva";774;1
"Unit";"Zergling";"Larva";775;1
"Unit";"Zergling";"Larva";776;1
"Unit";"Zergling";"Larva";777;1
"Unit";"Zergling";"Larva";778;1
"Unit";"Baneling";"Zergling";779;0
"Unit";"Baneling";"Zergling";779;0
"Unit";"Baneling";"Zergling";779;0
"Unit";"Baneling";"Zergling";779;0
"Unit";"Baneling";"Zergling";779;0
"Unit";"Baneling";"Zergling";779;0
"Unit";"Baneling";"Zergling";779;0
"Unit";"Baneling";"Zergling";779;0
"Unit";"Baneling";"Zergling";779;0
"Unit";"Baneling";"Zergling";779;0
"Unit";"Baneling";"Zergling";779;0
"Unit";"Baneling";"Zergling";779;0
"Unit";"Baneling";"Zergling";779;0
"Unit";"Zergling";"Larva";779;1
"Unit";"Zergling";"Larva";780;1
"Unit";"Zergling";"Larva";781;1
"Unit";"Zergling";"Larva";782;1
"Unit";"Baneling";"Zergling";783;0
"Unit";"Baneling";"Zergling";783;0
"Unit";"Baneling";"Zergling";783;0
"Unit";"Baneling";"Zergling";783;0
"Unit";"Baneling";"Zergling";783;0
"Unit";"Baneling";"Zergling";783;0
"Unit";"Baneling";"Zergling";783;0
"Unit";"Baneling";"Zergling";783;0
"Unit";"Baneling";"Zergling";783;0
"Unit";"Baneling";"Zergling";783;0
"Unit";"Corruptor";"Larva";783;2
"Unit";"Corruptor";"Larva";785;2
"Building";"Extractor";NA;790;0
"Building";"Extractor";NA;790;0
"Unit";"Zergling";"Larva";790;1
"Unit";"Zergling";"Larva";791;1
"Unit";"Zergling";"Larva";792;1
"Unit";"Zergling";"Larva";793;1
"Unit";"Zergling";"Larva";794;1
"Unit";"Zergling";"Larva";795;1
"Unit";"Zergling";"Larva";796;1
"Unit";"Zergling";"Larva";797;1
"Unit";"Zergling";"Larva";798;1
"Unit";"Zergling";"Larva";799;1
"Unit";"Zergling";"Larva";800;1
"Unit";"Zergling";"Larva";801;1
"Unit";"Zergling";"Larva";802;1
"Unit";"Zergling";"Larva";803;1
"Unit";"Zergling";"Larva";804;1
"Unit";"Zergling";"Larva";805;1
"Unit";"Zergling";"Larva";806;1
"Unit";"Zergling";"Larva";807;1
"Unit";"Zergling";"Larva";808;1
"Unit";"Zergling";"Larva";809;1
"Unit";"Corruptor";"Larva";810;2
"Unit";"Infestor";"Larva";812;2
"Unit";"Infestor";"Larva";814;2
"Building";"Extractor";NA;816;0
"Unit";"Zergling";"Larva";816;1
"Unit";"Zergling";"Larva";817;1
"Unit";"Zergling";"Larva";818;1
"Unit";"Zergling";"Larva";819;1
"Unit";"Zergling";"Larva";820;1
"Unit";"Zergling";"Larva";821;1
"Unit";"Zergling";"Larva";822;1
"Unit";"Zergling";"Larva";823;1
"Unit";"Zergling";"Larva";824;1
"Unit";"Zergling";"Larva";825;1
"Unit";"Zergling";"Larva";826;1
"Unit";"Zergling";"Larva";827;1
"Unit";"Zergling";"Larva";828;1
"Unit";"Zergling";"Larva";829;1
"Unit";"Zergling";"Larva";830;1
"Unit";"Zergling";"Larva";831;1
"Unit";"Zergling";"Larva";832;1
"Unit";"Zergling";"Larva";833;1
"Unit";"Zergling";"Larva";834;1
"Unit";"Zergling";"Larva";835;1
"Unit";"Zergling";"Larva";836;1
"Unit";"Zergling";"Larva";837;1
"Unit";"Zergling";"Larva";838;1
"Unit";"Zergling";"Larva";839;1
"Unit";"Zergling";"Larva";840;1
"Unit";"Zergling";"Larva";841;1
"Unit";"Corruptor";"Larva";842;2
"Unit";"Corruptor";"Larva";844;2
"Unit";"Corruptor";"Larva";846;2
"Unit";"Overlord";"Larva";848;0
"Unit";"Corruptor";"Larva";848;2
"Unit";"Corruptor";"Larva";850;2
"Unit";"Infestor";"Larva";852;2
"Unit";"Infestor";"Larva";854;2
"Building";"Hatchery";NA;856;0
"Unit";"Zergling";"Larva";856;1
"Unit";"Zergling";"Larva";857;1
"Unit";"Zergling";"Larva";858;1
"Unit";"Zergling";"Larva";859;1
"Unit";"Zergling";"Larva";860;1
"Unit";"Zergling";"Larva";861;1
"Unit";"Zergling";"Larva";862;1
"Unit";"Zergling";"Larva";863;1
"Unit";"Zergling";"Larva";864;1
"Unit";"Zergling";"Larva";865;1
"Unit";"Zergling";"Larva";866;1
"Unit";"Zergling";"Larva";867;1
"Unit";"Zergling";"Larva";868;1
"Unit";"Zergling";"Larva";869;1
"Unit";"Zergling";"Larva";870;1
"Unit";"Zergling";"Larva";871;1
"Unit";"Baneling";"Zergling";872;0
"Unit";"Baneling";"Zergling";872;0
"Unit";"Baneling";"Zergling";872;0
"Unit";"Baneling";"Zergling";872;0
"Building";"CreepTumor";NA;872;0
"Building";"CreepTumor";NA;872;0
"Building";"CreepTumor";NA;872;0
"Unit";"Ultralisk";"Larva";872;6
"Unit";"Ultralisk";"Larva";878;6
"Unit";"Zergling";"Larva";884;1
"Unit";"Zergling";"Larva";885;1
"Unit";"Zergling";"Larva";886;1
"Unit";"Zergling";"Larva";887;1
"Unit";"Zergling";"Larva";888;1
"Unit";"Zergling";"Larva";889;1
"Unit";"Zergling";"Larva";890;1
"Unit";"Zergling";"Larva";891;1
"Unit";"Zergling";"Larva";892;1
"Unit";"Zergling";"Larva";893;1
"Unit";"Zergling";"Larva";894;1
"Unit";"Zergling";"Larva";895;1
"Unit";"Zergling";"Larva";896;1
"Unit";"Zergling";"Larva";897;1
"Unit";"Baneling";"Zergling";898;0
"Unit";"Baneling";"Zergling";898;0
"Unit";"Baneling";"Zergling";898;0
"Unit";"Baneling";"Zergling";898;0
"Unit";"Zergling";"Larva";898;1
"Unit";"Zergling";"Larva";899;1
"Unit";"Zergling";"Larva";900;1
"Unit";"Zergling";"Larva";901;1
"Unit";"Zergling";"Larva";902;1
"Unit";"Zergling";"Larva";903;1
"Unit";"Zergling";"Larva";904;1
"Unit";"Zergling";"Larva";905;1
"Unit";"Zergling";"Larva";906;1
"Unit";"Zergling";"Larva";907;1
"Unit";"Zergling";"Larva";908;1
"Unit";"Zergling";"Larva";909;1
"Unit";"Zergling";"Larva";910;1
"Unit";"Zergling";"Larva";911;1
"Unit";"Zergling";"Larva";912;1
"Unit";"Zergling";"Larva";913;1
"Unit";"Zergling";"Larva";914;1
"Unit";"Zergling";"Larva";915;1
"Unit";"Zergling";"Larva";916;1
"Unit";"Zergling";"Larva";917;1
"Upgrade";"SprayZerg";NA;918;0
"Upgrade";"SprayZerg";NA;918;0
"Upgrade";"SprayZerg";NA;918;0
"Upgrade";"zerglingmovementspeed";NA;918;0
"Upgrade";"SprayZerg";NA;918;0
"Upgrade";"SprayZerg";NA;918;0
"Upgrade";"SprayZerg";NA;918;0
"Upgrade";"ZergMeleeWeaponsLevel1";NA;918;0
"Upgrade";"ZergGroundArmorsLevel1";NA;918;0
"Upgrade";"SprayZerg";NA;918;0
"Upgrade";"SprayZerg";NA;918;0
"Upgrade";"CentrificalHooks";NA;918;0
"Upgrade";"SprayZerg";NA;918;0
"Upgrade";"ZergMeleeWeaponsLevel2";NA;918;0
"Upgrade";"ZergGroundArmorsLevel2";NA;918;0
"Upgrade";"ZergFlyerWeaponsLevel1";NA;918;0
"Upgrade";"overlordspeed";NA;918;0
"Upgrade";"SprayZerg";NA;918;0
"Upgrade";"SprayZerg";NA;918;0
"Upgrade";"SprayZerg";NA;918;0
"Upgrade";"zerglingattackspeed";NA;918;0
"Upgrade";"SprayZerg";NA;918;0
"Upgrade";"ZergMeleeWeaponsLevel3";NA;918;0
"Upgrade";"ZergGroundArmorsLevel3";NA;918;0
"Upgrade";"SprayZerg";NA;918;0
"Upgrade";"ZergFlyerArmorsLevel1";NA;918;0
"Upgrade";"SprayZerg";NA;918;0
"Upgrade";"InfestorEnergyUpgrade";NA;918;0
"Upgrade";"SprayZerg";NA;918;0
"Upgrade";"SprayZerg";NA;918;0
"Upgrade";"SprayZerg";NA;918;0
