"type";"unit_name";"on_building";"total_supply_lag";"supply"
"Unit";"Overlord";"Larva";13;0
"Building";"Hatchery";NA;17;0
"Building";"Extractor";NA;19;0
"Building";"SpawningPool";NA;19;0
"Unit";"Overlord";"Larva";22;0
"Unit";"Queen";"Hatchery";22;2
"Unit";"Zergling";"Larva";24;1
"Unit";"Zergling";"Larva";25;1
"Unit";"Zergling";"Larva";26;1
"Unit";"Zergling";"Larva";27;1
"Unit";"Zergling";"Larva";28;1
"Unit";"Zergling";"Larva";29;1
"Building";"SpineCrawler";NA;30;0
"Unit";"Zergling";"Larva";30;1
"Unit";"Zergling";"Larva";31;1
"Unit";"Zergling";"Larva";32;1
"Unit";"Zergling";"Larva";33;1
"Unit";"Overlord";"Larva";34;0
"Unit";"Zergling";"Larva";34;1
"Unit";"Zergling";"Larva";35;1
"Unit";"Zergling";"Larva";36;1
"Unit";"Zergling";"Larva";37;1
"Unit";"Zergling";"Larva";38;1
"Unit";"Zergling";"Larva";39;1
"Unit";"Queen";"Hatchery";46;2
"Building";"CreepTumorQueen";NA;56;0
"Building";"Hatchery";NA;58;0
"Unit";"Overlord";"Larva";58;0
"Unit";"Overlord";"Larva";62;0
"Unit";"Overlord";"Larva";62;0
"Unit";"Queen";"Hatchery";62;2
"Building";"CreepTumor";NA;69;0
"Unit";"Zergling";"Larva";69;1
"Unit";"Zergling";"Larva";70;1
"Unit";"Zergling";"Larva";71;1
"Unit";"Zergling";"Larva";72;1
"Unit";"Queen";"Hatchery";73;2
"Building";"Extractor";NA;76;0
"Unit";"Overlord";"Larva";77;0
"Unit";"Zergling";"Larva";77;1
"Unit";"Zergling";"Larva";78;1
"Unit";"Zergling";"Larva";79;1
"Unit";"Zergling";"Larva";80;1
"Unit";"Overlord";"Larva";81;0
"Unit";"Overlord";"Larva";81;0
"Building";"CreepTumor";NA;81;0
"Unit";"Zergling";"Larva";84;1
"Unit";"Zergling";"Larva";85;1
"Unit";"Zergling";"Larva";86;1
"Unit";"Zergling";"Larva";87;1
"Unit";"Queen";"Hatchery";88;2
"Unit";"Queen";"Hatchery";90;2
"Building";"CreepTumor";NA;95;0
"Unit";"Zergling";"Larva";97;1
"Unit";"Zergling";"Larva";98;1
"Unit";"Zergling";"Larva";99;1
"Unit";"Zergling";"Larva";100;1
"Unit";"Zergling";"Larva";101;1
"Unit";"Zergling";"Larva";102;1
"Unit";"Zergling";"Larva";103;1
"Unit";"Zergling";"Larva";104;1
"Unit";"Zergling";"Larva";105;1
"Unit";"Zergling";"Larva";106;1
"Unit";"Zergling";"Larva";107;1
"Unit";"Zergling";"Larva";108;1
"Unit";"Zergling";"Larva";109;1
"Unit";"Zergling";"Larva";110;1
"Unit";"Zergling";"Larva";111;1
"Unit";"Zergling";"Larva";112;1
"Building";"CreepTumorQueen";NA;113;0
"Unit";"Queen";"Hatchery";113;2
"Unit";"Queen";"Hatchery";115;2
"Building";"BanelingNest";NA;121;0
"Building";"Extractor";NA;121;0
"Unit";"Queen";"Hatchery";121;2
"Unit";"Overlord";"Larva";125;0
"Building";"SporeCrawler";NA;126;0
"Building";"SporeCrawler";NA;126;0
"Building";"SporeCrawler";NA;138;0
"Building";"Extractor";NA;140;0
"Building";"CreepTumorQueen";NA;140;0
"Building";"CreepTumorQueen";NA;140;0
"Building";"Spire";NA;140;0
"Building";"Extractor";NA;142;0
"Building";"Extractor";NA;142;0
"Building";"CreepTumor";NA;144;0
"Unit";"Zergling";"Larva";144;1
"Unit";"Zergling";"Larva";145;1
"Unit";"Zergling";"Larva";146;1
"Unit";"Zergling";"Larva";147;1
"Building";"CreepTumorQueen";NA;148;0
"Building";"CreepTumorQueen";NA;148;0
"Building";"CreepTumorQueen";NA;148;0
"Unit";"Zergling";"Larva";148;1
"Unit";"Zergling";"Larva";149;1
"Unit";"Zergling";"Larva";150;1
"Unit";"Zergling";"Larva";151;1
"Unit";"Queen";"Hatchery";152;2
"Unit";"Zergling";"Larva";154;1
"Unit";"Zergling";"Larva";155;1
"Unit";"Zergling";"Larva";156;1
"Unit";"Zergling";"Larva";157;1
"Unit";"Zergling";"Larva";158;1
"Unit";"Zergling";"Larva";159;1
"Unit";"Zergling";"Larva";160;1
"Unit";"Zergling";"Larva";161;1
"Unit";"Zergling";"Larva";162;1
"Unit";"Zergling";"Larva";163;1
"Unit";"Zergling";"Larva";164;1
"Unit";"Zergling";"Larva";165;1
"Building";"EvolutionChamber";NA;166;0
"Building";"EvolutionChamber";NA;166;0
"Unit";"Baneling";"Zergling";166;0
"Unit";"Baneling";"Zergling";166;0
"Unit";"Baneling";"Zergling";166;0
"Unit";"Baneling";"Zergling";166;0
"Building";"CreepTumor";NA;175;0
"Building";"CreepTumor";NA;175;0
"Building";"CreepTumor";NA;175;0
"Building";"CreepTumorQueen";NA;175;0
"Building";"CreepTumorQueen";NA;175;0
"Building";"CreepTumorQueen";NA;175;0
"Building";"CreepTumorQueen";NA;178;0
"Building";"CreepTumorQueen";NA;178;0
"Building";"CreepTumorQueen";NA;178;0
"Unit";"Overlord";"Larva";178;0
"Building";"Hatchery";NA;178;0
"Unit";"Zergling";"Larva";178;1
"Unit";"Zergling";"Larva";179;1
"Unit";"Zergling";"Larva";180;1
"Unit";"Zergling";"Larva";181;1
"Unit";"Zergling";"Larva";182;1
"Unit";"Zergling";"Larva";183;1
"Unit";"Zergling";"Larva";184;1
"Unit";"Zergling";"Larva";185;1
"Building";"CreepTumor";NA;186;0
"Building";"CreepTumor";NA;186;0
"Building";"CreepTumor";NA;186;0
"Unit";"Overlord";"Larva";186;0
"Building";"CreepTumor";NA;186;0
"Building";"Hatchery";NA;186;0
"Building";"CreepTumor";NA;186;0
"Unit";"Overlord";"Larva";186;0
"Building";"CreepTumorQueen";NA;186;0
"Unit";"Mutalisk";"Larva";186;2
"Unit";"Mutalisk";"Larva";188;2
"Unit";"Mutalisk";"Larva";190;2
"Unit";"Mutalisk";"Larva";192;2
"Building";"CreepTumorQueen";NA;194;0
"Building";"CreepTumor";NA;197;0
"Building";"CreepTumor";NA;197;0
"Building";"CreepTumor";NA;197;0
"Unit";"Overlord";"Larva";197;0
"Unit";"Overlord";"Larva";197;0
"Unit";"Zergling";"Larva";197;1
"Unit";"Zergling";"Larva";198;1
"Unit";"Zergling";"Larva";199;1
"Unit";"Zergling";"Larva";200;1
"Unit";"Zergling";"Larva";201;1
"Unit";"Zergling";"Larva";202;1
"Unit";"Zergling";"Larva";203;1
"Unit";"Zergling";"Larva";204;1
"Unit";"Zergling";"Larva";205;1
"Unit";"Zergling";"Larva";206;1
"Unit";"Zergling";"Larva";207;1
"Unit";"Zergling";"Larva";208;1
"Unit";"Zergling";"Larva";209;1
"Unit";"Zergling";"Larva";210;1
"Unit";"Zergling";"Larva";211;1
"Unit";"Zergling";"Larva";212;1
"Unit";"Zergling";"Larva";213;1
"Unit";"Zergling";"Larva";214;1
"Unit";"Baneling";"Zergling";215;0
"Unit";"Baneling";"Zergling";215;0
"Unit";"Baneling";"Zergling";215;0
"Unit";"Baneling";"Zergling";215;0
"Unit";"Baneling";"Zergling";215;0
"Building";"CreepTumor";NA;215;0
"Building";"CreepTumor";NA;215;0
"Building";"CreepTumor";NA;215;0
"Unit";"Mutalisk";"Larva";215;2
"Unit";"Mutalisk";"Larva";217;2
"Building";"CreepTumor";NA;219;0
"Building";"CreepTumor";NA;219;0
"Unit";"Zergling";"Larva";219;1
"Unit";"Zergling";"Larva";220;1
"Unit";"Zergling";"Larva";221;1
"Unit";"Zergling";"Larva";222;1
"Unit";"Zergling";"Larva";223;1
"Unit";"Zergling";"Larva";224;1
"Unit";"Zergling";"Larva";225;1
"Unit";"Zergling";"Larva";226;1
"Unit";"Zergling";"Larva";227;1
"Unit";"Zergling";"Larva";228;1
"Unit";"Zergling";"Larva";229;1
"Unit";"Zergling";"Larva";230;1
"Building";"CreepTumor";NA;231;0
"Building";"CreepTumor";NA;231;0
"Building";"Hatchery";NA;231;0
"Building";"Extractor";NA;231;0
"Building";"CreepTumorQueen";NA;231;0
"Building";"CreepTumorQueen";NA;235;0
"Unit";"Mutalisk";"Larva";235;2
"Unit";"Mutalisk";"Larva";237;2
"Unit";"Mutalisk";"Larva";239;2
"Unit";"Mutalisk";"Larva";241;2
"Unit";"Mutalisk";"Larva";243;2
"Unit";"Mutalisk";"Larva";245;2
"Unit";"Zergling";"Larva";247;1
"Unit";"Zergling";"Larva";248;1
"Unit";"Zergling";"Larva";249;1
"Unit";"Zergling";"Larva";250;1
"Unit";"Zergling";"Larva";251;1
"Unit";"Zergling";"Larva";252;1
"Unit";"Zergling";"Larva";253;1
"Unit";"Zergling";"Larva";254;1
"Unit";"Overlord";"Larva";255;0
"Unit";"Zergling";"Larva";255;1
"Unit";"Zergling";"Larva";256;1
"Unit";"Zergling";"Larva";257;1
"Unit";"Zergling";"Larva";258;1
"Unit";"Overlord";"Larva";259;0
"Building";"CreepTumorQueen";NA;259;0
"Building";"CreepTumor";NA;259;0
"Building";"CreepTumor";NA;259;0
"Unit";"Overlord";"Larva";259;0
"Unit";"Overlord";"Larva";259;0
"Unit";"Mutalisk";"Larva";259;2
"Unit";"Mutalisk";"Larva";261;2
"Unit";"Mutalisk";"Larva";263;2
"Building";"CreepTumorQueen";NA;265;0
"Building";"CreepTumorQueen";NA;265;0
"Unit";"Zergling";"Larva";265;1
"Unit";"Zergling";"Larva";266;1
"Unit";"Zergling";"Larva";267;1
"Unit";"Zergling";"Larva";268;1
"Unit";"Zergling";"Larva";269;1
"Unit";"Zergling";"Larva";270;1
"Unit";"Zergling";"Larva";271;1
"Unit";"Zergling";"Larva";272;1
"Unit";"Zergling";"Larva";273;1
"Unit";"Zergling";"Larva";274;1
"Unit";"Zergling";"Larva";275;1
"Unit";"Zergling";"Larva";276;1
"Unit";"Zergling";"Larva";277;1
"Unit";"Zergling";"Larva";278;1
"Unit";"Zergling";"Larva";279;1
"Unit";"Zergling";"Larva";280;1
"Unit";"Zergling";"Larva";281;1
"Unit";"Zergling";"Larva";282;1
"Unit";"Zergling";"Larva";283;1
"Unit";"Zergling";"Larva";284;1
"Upgrade";"Burrow";"Hatchery";285;0
"Unit";"Zergling";"Larva";285;1
"Unit";"Zergling";"Larva";286;1
"Unit";"Baneling";"Zergling";287;0
"Unit";"Baneling";"Zergling";287;0
"Unit";"Baneling";"Zergling";287;0
"Unit";"Baneling";"Zergling";287;0
"Unit";"Baneling";"Zergling";287;0
"Unit";"Baneling";"Zergling";287;0
"Unit";"Baneling";"Zergling";287;0
"Unit";"Baneling";"Zergling";287;0
"Unit";"Baneling";"Zergling";287;0
"Unit";"Baneling";"Zergling";287;0
"Unit";"Baneling";"Zergling";287;0
"Unit";"Baneling";"Zergling";287;0
"Unit";"Zergling";"Larva";287;1
"Unit";"Zergling";"Larva";288;1
"Unit";"Zergling";"Larva";289;1
"Unit";"Zergling";"Larva";290;1
"Unit";"Zergling";"Larva";291;1
"Unit";"Zergling";"Larva";292;1
"Unit";"Zergling";"Larva";293;1
"Unit";"Zergling";"Larva";294;1
"Unit";"Zergling";"Larva";295;1
"Unit";"Zergling";"Larva";296;1
"Unit";"Zergling";"Larva";297;1
"Unit";"Zergling";"Larva";298;1
"Unit";"Overlord";"Larva";306;0
"Unit";"Zergling";"Larva";306;1
"Unit";"Zergling";"Larva";307;1
"Unit";"Zergling";"Larva";308;1
"Unit";"Zergling";"Larva";309;1
"Unit";"Zergling";"Larva";310;1
"Unit";"Zergling";"Larva";311;1
"Unit";"Zergling";"Larva";312;1
"Unit";"Zergling";"Larva";313;1
"Unit";"Zergling";"Larva";314;1
"Unit";"Zergling";"Larva";315;1
"Unit";"Zergling";"Larva";316;1
"Unit";"Zergling";"Larva";317;1
"Unit";"Zergling";"Larva";318;1
"Unit";"Zergling";"Larva";319;1
"Unit";"Zergling";"Larva";320;1
"Unit";"Zergling";"Larva";321;1
"Unit";"Zergling";"Larva";322;1
"Unit";"Zergling";"Larva";323;1
"Unit";"Zergling";"Larva";324;1
"Unit";"Zergling";"Larva";325;1
"Unit";"Zergling";"Larva";326;1
"Unit";"Zergling";"Larva";327;1
"Unit";"Overlord";"Larva";328;0
"Unit";"Overlord";"Larva";328;0
"Unit";"Mutalisk";"Larva";328;2
"Unit";"Mutalisk";"Larva";330;2
"Unit";"Mutalisk";"Larva";332;2
"Unit";"Mutalisk";"Larva";334;2
"Unit";"Mutalisk";"Larva";336;2
"Unit";"Zergling";"Larva";338;1
"Unit";"Zergling";"Larva";339;1
"Unit";"Zergling";"Larva";340;1
"Unit";"Zergling";"Larva";341;1
"Unit";"Zergling";"Larva";342;1
"Unit";"Zergling";"Larva";343;1
"Unit";"Zergling";"Larva";344;1
"Unit";"Zergling";"Larva";345;1
"Unit";"Zergling";"Larva";346;1
"Unit";"Zergling";"Larva";347;1
"Unit";"Zergling";"Larva";348;1
"Unit";"Zergling";"Larva";349;1
"Unit";"Zergling";"Larva";350;1
"Unit";"Zergling";"Larva";351;1
"Unit";"Zergling";"Larva";352;1
"Unit";"Zergling";"Larva";353;1
"Unit";"Zergling";"Larva";354;1
"Unit";"Zergling";"Larva";355;1
"Unit";"Zergling";"Larva";356;1
"Unit";"Zergling";"Larva";357;1
"Unit";"Zergling";"Larva";358;1
"Unit";"Zergling";"Larva";359;1
"Unit";"Zergling";"Larva";360;1
"Unit";"Zergling";"Larva";361;1
"Unit";"Zergling";"Larva";362;1
"Unit";"Zergling";"Larva";363;1
"Unit";"Zergling";"Larva";364;1
"Unit";"Zergling";"Larva";365;1
"Unit";"Zergling";"Larva";366;1
"Unit";"Zergling";"Larva";367;1
"Unit";"Zergling";"Larva";368;1
"Unit";"Zergling";"Larva";369;1
"Unit";"Baneling";"Zergling";370;0
"Unit";"Baneling";"Zergling";370;0
"Unit";"Baneling";"Zergling";370;0
"Unit";"Baneling";"Zergling";370;0
"Unit";"Baneling";"Zergling";370;0
"Unit";"Baneling";"Zergling";370;0
"Unit";"Baneling";"Zergling";370;0
"Unit";"Baneling";"Zergling";370;0
"Unit";"Baneling";"Zergling";370;0
"Unit";"Baneling";"Zergling";370;0
"Unit";"Baneling";"Zergling";370;0
"Unit";"Baneling";"Zergling";370;0
"Unit";"Baneling";"Zergling";370;0
"Unit";"Baneling";"Zergling";370;0
"Unit";"Baneling";"Zergling";370;0
"Unit";"Baneling";"Zergling";370;0
"Unit";"Baneling";"Zergling";370;0
"Building";"CreepTumor";NA;370;0
"Building";"CreepTumor";NA;370;0
"Building";"CreepTumor";NA;370;0
"Building";"CreepTumorQueen";NA;370;0
"Building";"CreepTumor";NA;370;0
"Building";"CreepTumor";NA;370;0
"Unit";"Zergling";"Larva";370;1
"Unit";"Zergling";"Larva";371;1
"Unit";"Zergling";"Larva";372;1
"Unit";"Zergling";"Larva";373;1
"Unit";"Zergling";"Larva";374;1
"Unit";"Zergling";"Larva";375;1
"Unit";"Zergling";"Larva";376;1
"Unit";"Zergling";"Larva";377;1
"Unit";"Zergling";"Larva";378;1
"Unit";"Zergling";"Larva";379;1
"Unit";"Zergling";"Larva";380;1
"Unit";"Zergling";"Larva";381;1
"Unit";"Zergling";"Larva";382;1
"Unit";"Zergling";"Larva";383;1
"Unit";"Zergling";"Larva";384;1
"Unit";"Zergling";"Larva";385;1
"Unit";"Zergling";"Larva";386;1
"Unit";"Zergling";"Larva";387;1
"Unit";"Zergling";"Larva";388;1
"Unit";"Zergling";"Larva";389;1
"Unit";"Baneling";"Zergling";390;0
"Unit";"Baneling";"Zergling";390;0
"Unit";"Baneling";"Zergling";390;0
"Unit";"Baneling";"Zergling";390;0
"Unit";"Baneling";"Zergling";390;0
"Unit";"Baneling";"Zergling";390;0
"Unit";"Baneling";"Zergling";390;0
"Unit";"Baneling";"Zergling";390;0
"Unit";"Baneling";"Zergling";390;0
"Unit";"Baneling";"Zergling";390;0
"Unit";"Baneling";"Zergling";390;0
"Unit";"Baneling";"Zergling";390;0
"Unit";"Baneling";"Zergling";390;0
"Unit";"Baneling";"Zergling";390;0
"Building";"InfestationPit";NA;390;0
"Unit";"Overlord";"Larva";390;0
"Building";"CreepTumor";NA;390;0
"Building";"CreepTumor";NA;390;0
"Building";"CreepTumor";NA;390;0
"Unit";"Overlord";"Larva";390;0
"Unit";"Baneling";"Zergling";390;0
"Unit";"Baneling";"Zergling";390;0
"Unit";"Baneling";"Zergling";390;0
"Unit";"Baneling";"Zergling";390;0
"Unit";"Baneling";"Zergling";390;0
"Unit";"Baneling";"Zergling";390;0
"Unit";"Baneling";"Zergling";390;0
"Unit";"Baneling";"Zergling";390;0
"Unit";"Baneling";"Zergling";390;0
"Unit";"Baneling";"Zergling";390;0
"Unit";"Baneling";"Zergling";390;0
"Unit";"Baneling";"Zergling";390;0
"Unit";"Baneling";"Zergling";390;0
"Unit";"Baneling";"Zergling";390;0
"Unit";"Baneling";"Zergling";390;0
"Unit";"Baneling";"Zergling";390;0
"Unit";"Baneling";"Zergling";390;0
"Unit";"Baneling";"Zergling";390;0
"Unit";"Baneling";"Zergling";390;0
"Unit";"Baneling";"Zergling";390;0
"Unit";"Baneling";"Zergling";390;0
"Unit";"Baneling";"Zergling";390;0
"Unit";"Baneling";"Zergling";390;0
"Unit";"Baneling";"Zergling";390;0
"Unit";"Baneling";"Zergling";390;0
"Unit";"Baneling";"Zergling";390;0
"Unit";"Zergling";"Larva";390;1
"Unit";"Zergling";"Larva";391;1
"Unit";"Zergling";"Larva";392;1
"Unit";"Zergling";"Larva";393;1
"Unit";"Zergling";"Larva";394;1
"Unit";"Zergling";"Larva";395;1
"Unit";"Zergling";"Larva";396;1
"Unit";"Zergling";"Larva";397;1
"Unit";"Zergling";"Larva";398;1
"Unit";"Zergling";"Larva";399;1
"Unit";"Zergling";"Larva";400;1
"Unit";"Zergling";"Larva";401;1
"Unit";"Zergling";"Larva";402;1
"Unit";"Zergling";"Larva";403;1
"Unit";"Zergling";"Larva";404;1
"Unit";"Zergling";"Larva";405;1
"Unit";"Zergling";"Larva";406;1
"Unit";"Zergling";"Larva";407;1
"Unit";"Zergling";"Larva";408;1
"Unit";"Zergling";"Larva";409;1
"Unit";"Zergling";"Larva";410;1
"Unit";"Zergling";"Larva";411;1
"Unit";"Zergling";"Larva";412;1
"Unit";"Zergling";"Larva";413;1
"Unit";"Zergling";"Larva";414;1
"Unit";"Zergling";"Larva";415;1
"Unit";"Zergling";"Larva";416;1
"Unit";"Zergling";"Larva";417;1
"Unit";"Zergling";"Larva";418;1
"Unit";"Zergling";"Larva";419;1
"Unit";"Zergling";"Larva";420;1
"Unit";"Zergling";"Larva";421;1
"Unit";"Zergling";"Larva";422;1
"Unit";"Zergling";"Larva";423;1
"Unit";"Zergling";"Larva";424;1
"Unit";"Zergling";"Larva";425;1
"Unit";"Zergling";"Larva";426;1
"Unit";"Zergling";"Larva";427;1
"Unit";"Zergling";"Larva";428;1
"Unit";"Zergling";"Larva";429;1
"Unit";"Zergling";"Larva";430;1
"Unit";"Zergling";"Larva";431;1
"Unit";"Zergling";"Larva";432;1
"Unit";"Zergling";"Larva";433;1
"Unit";"Zergling";"Larva";434;1
"Unit";"Zergling";"Larva";435;1
"Unit";"Zergling";"Larva";436;1
"Unit";"Zergling";"Larva";437;1
"Unit";"Zergling";"Larva";438;1
"Unit";"Zergling";"Larva";439;1
"Unit";"Zergling";"Larva";440;1
"Unit";"Zergling";"Larva";441;1
"Unit";"Zergling";"Larva";442;1
"Unit";"Zergling";"Larva";443;1
"Unit";"Zergling";"Larva";444;1
"Unit";"Zergling";"Larva";445;1
"Unit";"Zergling";"Larva";446;1
"Unit";"Zergling";"Larva";447;1
"Unit";"Zergling";"Larva";448;1
"Unit";"Zergling";"Larva";449;1
"Unit";"Zergling";"Larva";450;1
"Unit";"Zergling";"Larva";451;1
"Unit";"Zergling";"Larva";452;1
"Unit";"Zergling";"Larva";453;1
"Unit";"Zergling";"Larva";454;1
"Unit";"Zergling";"Larva";455;1
"Unit";"Zergling";"Larva";456;1
"Unit";"Zergling";"Larva";457;1
"Unit";"Zergling";"Larva";458;1
"Unit";"Zergling";"Larva";459;1
"Unit";"Zergling";"Larva";460;1
"Unit";"Zergling";"Larva";461;1
"Unit";"Zergling";"Larva";462;1
"Unit";"Zergling";"Larva";463;1
"Unit";"Zergling";"Larva";464;1
"Unit";"Zergling";"Larva";465;1
"Unit";"Zergling";"Larva";466;1
"Unit";"Zergling";"Larva";467;1
"Unit";"Zergling";"Larva";468;1
"Unit";"Zergling";"Larva";469;1
"Unit";"Zergling";"Larva";470;1
"Unit";"Zergling";"Larva";471;1
"Unit";"Zergling";"Larva";472;1
"Unit";"Zergling";"Larva";473;1
"Unit";"Zergling";"Larva";474;1
"Unit";"Zergling";"Larva";475;1
"Unit";"Zergling";"Larva";476;1
"Unit";"Zergling";"Larva";477;1
"Unit";"Zergling";"Larva";478;1
"Unit";"Zergling";"Larva";479;1
"Unit";"Zergling";"Larva";480;1
"Unit";"Zergling";"Larva";481;1
"Unit";"Baneling";"Zergling";482;0
"Unit";"Baneling";"Zergling";482;0
"Unit";"Baneling";"Zergling";482;0
"Unit";"Baneling";"Zergling";482;0
"Unit";"Baneling";"Zergling";482;0
"Unit";"Baneling";"Zergling";482;0
"Unit";"Baneling";"Zergling";482;0
"Unit";"Baneling";"Zergling";482;0
"Unit";"Baneling";"Zergling";482;0
"Unit";"Baneling";"Zergling";482;0
"Unit";"Baneling";"Zergling";482;0
"Unit";"Baneling";"Zergling";482;0
"Unit";"Baneling";"Zergling";482;0
"Unit";"Baneling";"Zergling";482;0
"Unit";"Baneling";"Zergling";482;0
"Unit";"Baneling";"Zergling";482;0
"Unit";"Baneling";"Zergling";482;0
"Unit";"Baneling";"Zergling";482;0
"Unit";"Baneling";"Zergling";482;0
"Unit";"Baneling";"Zergling";482;0
"Unit";"Baneling";"Zergling";482;0
"Unit";"Baneling";"Zergling";482;0
"Unit";"Baneling";"Zergling";482;0
"Unit";"Zergling";"Larva";482;1
"Unit";"Zergling";"Larva";483;1
"Unit";"Zergling";"Larva";484;1
"Unit";"Zergling";"Larva";485;1
"Unit";"Zergling";"Larva";486;1
"Unit";"Zergling";"Larva";487;1
"Unit";"Zergling";"Larva";488;1
"Unit";"Zergling";"Larva";489;1
"Unit";"Zergling";"Larva";490;1
"Unit";"Zergling";"Larva";491;1
"Unit";"Zergling";"Larva";492;1
"Unit";"Zergling";"Larva";493;1
"Unit";"Baneling";"Zergling";494;0
"Unit";"Baneling";"Zergling";494;0
"Unit";"Baneling";"Zergling";494;0
"Unit";"Baneling";"Zergling";494;0
"Unit";"Baneling";"Zergling";494;0
"Unit";"Baneling";"Zergling";494;0
"Unit";"Baneling";"Zergling";494;0
"Unit";"Baneling";"Zergling";494;0
"Unit";"Baneling";"Zergling";494;0
"Unit";"Zergling";"Larva";494;1
"Unit";"Zergling";"Larva";495;1
"Unit";"Zergling";"Larva";496;1
"Unit";"Zergling";"Larva";497;1
"Unit";"Zergling";"Larva";498;1
"Unit";"Zergling";"Larva";499;1
"Unit";"Mutalisk";"Larva";500;2
"Unit";"Mutalisk";"Larva";502;2
"Unit";"Mutalisk";"Larva";504;2
"Unit";"Mutalisk";"Larva";506;2
"Unit";"Mutalisk";"Larva";508;2
"Unit";"Zergling";"Larva";510;1
"Unit";"Zergling";"Larva";511;1
"Unit";"Zergling";"Larva";512;1
"Unit";"Zergling";"Larva";513;1
"Unit";"Zergling";"Larva";514;1
"Unit";"Zergling";"Larva";515;1
"Unit";"Zergling";"Larva";516;1
"Unit";"Zergling";"Larva";517;1
"Unit";"Zergling";"Larva";518;1
"Unit";"Zergling";"Larva";519;1
"Unit";"Zergling";"Larva";520;1
"Unit";"Zergling";"Larva";521;1
"Unit";"Zergling";"Larva";522;1
"Unit";"Zergling";"Larva";523;1
"Unit";"Zergling";"Larva";524;1
"Unit";"Zergling";"Larva";525;1
"Unit";"Zergling";"Larva";526;1
"Unit";"Zergling";"Larva";527;1
"Unit";"Zergling";"Larva";528;1
"Unit";"Zergling";"Larva";529;1
"Unit";"Zergling";"Larva";530;1
"Unit";"Zergling";"Larva";531;1
"Unit";"Zergling";"Larva";532;1
"Unit";"Zergling";"Larva";533;1
"Unit";"Zergling";"Larva";534;1
"Unit";"Zergling";"Larva";535;1
"Unit";"Zergling";"Larva";536;1
"Unit";"Zergling";"Larva";537;1
"Unit";"Zergling";"Larva";538;1
"Unit";"Zergling";"Larva";539;1
"Unit";"Zergling";"Larva";540;1
"Unit";"Zergling";"Larva";541;1
"Unit";"Zergling";"Larva";542;1
"Unit";"Zergling";"Larva";543;1
"Building";"Hatchery";NA;544;0
"Unit";"Mutalisk";"Larva";544;2
"Unit";"Mutalisk";"Larva";546;2
"Unit";"Mutalisk";"Larva";548;2
"Building";"Hatchery";NA;550;0
"Unit";"Zergling";"Larva";550;1
"Unit";"Zergling";"Larva";551;1
"Unit";"Zergling";"Larva";552;1
"Unit";"Zergling";"Larva";553;1
"Unit";"Zergling";"Larva";554;1
"Unit";"Zergling";"Larva";555;1
"Unit";"Zergling";"Larva";556;1
"Unit";"Zergling";"Larva";557;1
"Unit";"Zergling";"Larva";558;1
"Unit";"Zergling";"Larva";559;1
"Unit";"Zergling";"Larva";560;1
"Unit";"Zergling";"Larva";561;1
"Unit";"Zergling";"Larva";562;1
"Unit";"Zergling";"Larva";563;1
"Unit";"Zergling";"Larva";564;1
"Unit";"Zergling";"Larva";565;1
"Unit";"Zergling";"Larva";566;1
"Unit";"Zergling";"Larva";567;1
"Unit";"Zergling";"Larva";568;1
"Unit";"Zergling";"Larva";569;1
"Unit";"Zergling";"Larva";570;1
"Unit";"Zergling";"Larva";571;1
"Unit";"Zergling";"Larva";572;1
"Unit";"Zergling";"Larva";573;1
"Unit";"Zergling";"Larva";574;1
"Unit";"Zergling";"Larva";575;1
"Unit";"Zergling";"Larva";576;1
"Unit";"Zergling";"Larva";577;1
"Unit";"Zergling";"Larva";578;1
"Unit";"Zergling";"Larva";579;1
"Building";"CreepTumor";NA;580;0
"Building";"CreepTumor";NA;580;0
"Building";"CreepTumor";NA;580;0
"Unit";"Zergling";"Larva";580;1
"Unit";"Zergling";"Larva";581;1
"Unit";"Zergling";"Larva";582;1
"Unit";"Zergling";"Larva";583;1
"Unit";"Zergling";"Larva";584;1
"Unit";"Zergling";"Larva";585;1
"Unit";"Zergling";"Larva";586;1
"Unit";"Zergling";"Larva";587;1
"Unit";"Zergling";"Larva";588;1
"Unit";"Zergling";"Larva";589;1
"Unit";"Zergling";"Larva";590;1
"Unit";"Zergling";"Larva";591;1
"Unit";"Zergling";"Larva";592;1
"Unit";"Zergling";"Larva";593;1
"Unit";"Zergling";"Larva";594;1
"Unit";"Zergling";"Larva";595;1
"Unit";"Zergling";"Larva";596;1
"Unit";"Zergling";"Larva";597;1
"Building";"CreepTumor";NA;598;0
"Building";"CreepTumor";NA;598;0
"Unit";"Zergling";"Larva";598;1
"Unit";"Zergling";"Larva";599;1
"Unit";"Zergling";"Larva";600;1
"Unit";"Zergling";"Larva";601;1
"Unit";"Zergling";"Larva";602;1
"Unit";"Zergling";"Larva";603;1
"Unit";"Zergling";"Larva";604;1
"Unit";"Zergling";"Larva";605;1
"Unit";"Zergling";"Larva";606;1
"Unit";"Zergling";"Larva";607;1
"Unit";"Baneling";"Zergling";608;0
"Unit";"Baneling";"Zergling";608;0
"Unit";"Baneling";"Zergling";608;0
"Unit";"Baneling";"Zergling";608;0
"Unit";"Baneling";"Zergling";608;0
"Unit";"Baneling";"Zergling";608;0
"Unit";"Baneling";"Zergling";608;0
"Unit";"Baneling";"Zergling";608;0
"Unit";"Baneling";"Zergling";608;0
"Unit";"Baneling";"Zergling";608;0
"Unit";"Baneling";"Zergling";608;0
"Unit";"Baneling";"Zergling";608;0
"Unit";"Baneling";"Zergling";608;0
"Unit";"Baneling";"Zergling";608;0
"Unit";"Baneling";"Zergling";608;0
"Unit";"Baneling";"Zergling";608;0
"Unit";"Baneling";"Zergling";608;0
"Unit";"Zergling";"Larva";608;1
"Unit";"Zergling";"Larva";609;1
"Unit";"Zergling";"Larva";610;1
"Unit";"Zergling";"Larva";611;1
"Unit";"Zergling";"Larva";612;1
"Unit";"Zergling";"Larva";613;1
"Unit";"Zergling";"Larva";614;1
"Unit";"Zergling";"Larva";615;1
"Building";"CreepTumor";NA;616;0
"Unit";"Mutalisk";"Larva";616;2
"Unit";"Mutalisk";"Larva";618;2
"Building";"CreepTumor";NA;620;0
"Unit";"Baneling";"Zergling";620;0
"Unit";"Baneling";"Zergling";620;0
"Unit";"Baneling";"Zergling";620;0
"Unit";"Baneling";"Zergling";620;0
"Unit";"Zergling";"Larva";620;1
"Unit";"Zergling";"Larva";621;1
"Unit";"Zergling";"Larva";622;1
"Unit";"Zergling";"Larva";623;1
"Unit";"Zergling";"Larva";624;1
"Unit";"Zergling";"Larva";625;1
"Unit";"Zergling";"Larva";626;1
"Unit";"Zergling";"Larva";627;1
"Unit";"Zergling";"Larva";628;1
"Unit";"Zergling";"Larva";629;1
"Unit";"Zergling";"Larva";630;1
"Unit";"Zergling";"Larva";631;1
"Unit";"Zergling";"Larva";632;1
"Unit";"Zergling";"Larva";633;1
"Unit";"Zergling";"Larva";634;1
"Unit";"Zergling";"Larva";635;1
"Unit";"Zergling";"Larva";636;1
"Unit";"Zergling";"Larva";637;1
"Unit";"Zergling";"Larva";638;1
"Unit";"Zergling";"Larva";639;1
"Unit";"Overlord";"Larva";640;0
"Unit";"Overlord";"Larva";640;0
"Unit";"Baneling";"Zergling";640;0
"Unit";"Baneling";"Zergling";640;0
"Unit";"Baneling";"Zergling";640;0
"Unit";"Baneling";"Zergling";640;0
"Unit";"Baneling";"Zergling";640;0
"Unit";"Baneling";"Zergling";640;0
"Unit";"Baneling";"Zergling";640;0
"Unit";"Baneling";"Zergling";640;0
"Unit";"Baneling";"Zergling";640;0
"Unit";"Baneling";"Zergling";640;0
"Unit";"Baneling";"Zergling";640;0
"Unit";"Baneling";"Zergling";640;0
"Unit";"Baneling";"Zergling";640;0
"Unit";"Baneling";"Zergling";640;0
"Unit";"Baneling";"Zergling";640;0
"Unit";"Baneling";"Zergling";640;0
"Unit";"Baneling";"Zergling";640;0
"Unit";"Baneling";"Zergling";640;0
"Unit";"Baneling";"Zergling";640;0
"Unit";"Baneling";"Zergling";640;0
"Unit";"Baneling";"Zergling";640;0
"Unit";"Zergling";"Larva";640;1
"Unit";"Zergling";"Larva";641;1
"Unit";"Zergling";"Larva";642;1
"Unit";"Zergling";"Larva";643;1
"Unit";"Zergling";"Larva";644;1
"Unit";"Zergling";"Larva";645;1
"Unit";"Zergling";"Larva";646;1
"Unit";"Zergling";"Larva";647;1
"Unit";"Zergling";"Larva";648;1
"Unit";"Zergling";"Larva";649;1
"Unit";"Zergling";"Larva";650;1
"Unit";"Zergling";"Larva";651;1
"Unit";"Zergling";"Larva";652;1
"Unit";"Zergling";"Larva";653;1
"Unit";"Zergling";"Larva";654;1
"Unit";"Zergling";"Larva";655;1
"Unit";"Zergling";"Larva";656;1
"Unit";"Zergling";"Larva";657;1
"Unit";"Zergling";"Larva";658;1
"Unit";"Zergling";"Larva";659;1
"Unit";"Zergling";"Larva";660;1
"Unit";"Zergling";"Larva";661;1
"Unit";"Zergling";"Larva";662;1
"Unit";"Zergling";"Larva";663;1
"Unit";"Zergling";"Larva";664;1
"Unit";"Zergling";"Larva";665;1
"Unit";"Zergling";"Larva";666;1
"Unit";"Zergling";"Larva";667;1
"Unit";"Zergling";"Larva";668;1
"Unit";"Zergling";"Larva";669;1
"Unit";"Zergling";"Larva";670;1
"Unit";"Zergling";"Larva";671;1
"Unit";"Zergling";"Larva";672;1
"Unit";"Zergling";"Larva";673;1
"Unit";"Zergling";"Larva";674;1
"Unit";"Zergling";"Larva";675;1
"Unit";"Zergling";"Larva";676;1
"Unit";"Zergling";"Larva";677;1
"Unit";"Zergling";"Larva";678;1
"Unit";"Zergling";"Larva";679;1
"Unit";"Zergling";"Larva";680;1
"Unit";"Zergling";"Larva";681;1
"Unit";"Zergling";"Larva";682;1
"Unit";"Zergling";"Larva";683;1
"Unit";"Mutalisk";"Larva";684;2
"Unit";"Mutalisk";"Larva";686;2
"Unit";"Mutalisk";"Larva";688;2
"Unit";"Mutalisk";"Larva";690;2
"Unit";"Mutalisk";"Larva";692;2
"Unit";"Mutalisk";"Larva";694;2
"Unit";"Mutalisk";"Larva";696;2
"Unit";"Mutalisk";"Larva";698;2
"Unit";"Mutalisk";"Larva";700;2
"Unit";"Mutalisk";"Larva";702;2
"Unit";"Baneling";"Zergling";709;0
"Unit";"Baneling";"Zergling";709;0
"Unit";"Baneling";"Zergling";709;0
"Unit";"Baneling";"Zergling";709;0
"Unit";"Baneling";"Zergling";709;0
"Unit";"Baneling";"Zergling";709;0
"Unit";"Zergling";"Larva";709;1
"Unit";"Zergling";"Larva";710;1
"Unit";"Zergling";"Larva";711;1
"Unit";"Zergling";"Larva";712;1
"Unit";"Zergling";"Larva";713;1
"Unit";"Zergling";"Larva";714;1
"Unit";"Zergling";"Larva";715;1
"Unit";"Zergling";"Larva";716;1
"Unit";"Baneling";"Zergling";717;0
"Unit";"Baneling";"Zergling";717;0
"Unit";"Baneling";"Zergling";717;0
"Unit";"Baneling";"Zergling";717;0
"Unit";"Zergling";"Larva";717;1
"Unit";"Zergling";"Larva";718;1
"Unit";"Zergling";"Larva";719;1
"Unit";"Zergling";"Larva";720;1
"Unit";"Zergling";"Larva";721;1
"Unit";"Zergling";"Larva";722;1
"Unit";"Zergling";"Larva";723;1
"Unit";"Zergling";"Larva";724;1
"Unit";"Zergling";"Larva";725;1
"Unit";"Zergling";"Larva";726;1
"Unit";"Zergling";"Larva";727;1
"Unit";"Zergling";"Larva";728;1
"Unit";"Zergling";"Larva";729;1
"Unit";"Zergling";"Larva";730;1
"Unit";"Zergling";"Larva";731;1
"Unit";"Zergling";"Larva";732;1
"Unit";"Zergling";"Larva";733;1
"Unit";"Zergling";"Larva";734;1
"Unit";"Zergling";"Larva";735;1
"Unit";"Zergling";"Larva";736;1
"Unit";"Baneling";"Zergling";737;0
"Unit";"Baneling";"Zergling";737;0
"Unit";"Baneling";"Zergling";737;0
"Unit";"Baneling";"Zergling";737;0
"Unit";"Baneling";"Zergling";737;0
"Unit";"Baneling";"Zergling";737;0
"Unit";"Baneling";"Zergling";737;0
"Unit";"Baneling";"Zergling";737;0
"Unit";"Baneling";"Zergling";737;0
"Unit";"Baneling";"Zergling";737;0
"Unit";"Baneling";"Zergling";737;0
"Unit";"Baneling";"Zergling";737;0
"Unit";"Baneling";"Zergling";737;0
"Unit";"Baneling";"Zergling";737;0
"Unit";"Baneling";"Zergling";737;0
"Unit";"Baneling";"Zergling";737;0
"Unit";"Baneling";"Zergling";737;0
"Unit";"Baneling";"Zergling";737;0
"Unit";"Baneling";"Zergling";737;0
"Unit";"Baneling";"Zergling";737;0
"Unit";"Baneling";"Zergling";737;0
"Unit";"Baneling";"Zergling";737;0
"Unit";"Baneling";"Zergling";737;0
"Unit";"Baneling";"Zergling";737;0
"Unit";"Baneling";"Zergling";737;0
"Unit";"Baneling";"Zergling";737;0
"Upgrade";"SprayZerg";NA;737;0
"Upgrade";"SprayZerg";NA;737;0
"Upgrade";"SprayZerg";NA;737;0
"Upgrade";"zerglingmovementspeed";NA;737;0
"Upgrade";"SprayZerg";NA;737;0
"Upgrade";"SprayZerg";NA;737;0
"Upgrade";"SprayZerg";NA;737;0
"Upgrade";"CentrificalHooks";NA;737;0
"Upgrade";"overlordspeed";NA;737;0
"Upgrade";"SprayZerg";NA;737;0
"Upgrade";"SprayZerg";NA;737;0
"Upgrade";"SprayZerg";NA;737;0
"Upgrade";"ZergGroundArmorsLevel1";NA;737;0
"Upgrade";"ZergMeleeWeaponsLevel1";NA;737;0
"Upgrade";"ZergFlyerWeaponsLevel1";NA;737;0
"Upgrade";"SprayZerg";NA;737;0
"Upgrade";"ZergMeleeWeaponsLevel2";NA;737;0
"Upgrade";"ZergGroundArmorsLevel2";NA;737;0
"Upgrade";"SprayZerg";NA;737;0
"Upgrade";"ZergFlyerWeaponsLevel2";NA;737;0
"Upgrade";"SprayZerg";NA;737;0
"Upgrade";"SprayZerg";NA;737;0
"Upgrade";"SprayZerg";NA;737;0
