"Type";"UnitName";"OnBuilding";"TotalSupply";"Supply"
"Unit";"SCV";"Command Center";12;1
"Unit";"SCV";"Command Center";12;1
"Unit";"SCV";"Command Center";13;1
"Building";"SupplyDepot";NA;13;0
"Building";"Refinery";NA;14;0
"Unit";"SCV";"Command Center";15;1
"Unit";"SCV";"Command Center";15;1
"Unit";"SCV";"Command Center";16;1
"Unit";"SCV";"Command Center";18;1
"Building";"Barracks";NA;15;0
"Unit";"Reaper";"Barracks";19;1
"Unit";"SCV";"Command Center";19;1
"Unit";"SCV";"Command Center";21;1
"Building";"SupplyDepot";NA;21;0
"Unit";"SCV";"Command Center";21;1
"Building";"Refinery";NA;21;0
"Building";"Factory";NA;19;0
"Building";"BarracksReactor";NA;21;0
"Unit";"SCV";"Command Center";23;1
"Building";"CommandCenter";NA;19;0
"Unit";"SCV";"Command Center";24;1
"Unit";"Marine";"Barracks";23;1
"Unit";"Marine";"Barracks";23;1
"Unit";"Hellion";"Factory";23;2
"Unit";"SCV";"Command Center";24;1
"Unit";"Marine";"Barracks";27;1
"Unit";"Marine";"Barracks";27;1
"Unit";"SCV";"Command Center";29;1
"Unit";"SCV";"Command Center";32;1
"Unit";"SCV";"Command Center";32;1
"Unit";"Marine";"Barracks";33;1
"Unit";"Marine";"Barracks";33;1
"Unit";"SCV";"Command Center";33;1
"Unit";"SCV";"Command Center";34;1
"Unit";"Cyclone";"Factory";33;3
"Building";"Starport";NA;30;0
"Unit";"SCV";"Command Center";39;1
"Unit";"SCV";"Command Center";39;1
"Unit";"Marine";"Barracks";35;1
"Unit";"Marine";"Barracks";36;1
"Building";"SupplyDepot";NA;35;0
"Building";"FactoryTechLab";NA;42;0
"Unit";"SCV";"Command Center";42;1
"Unit";"SCV";"Command Center";46;1
"Unit";"Marine";"Barracks";46;1
"Unit";"Marine";"Barracks";46;1
"Unit";"SCV";"Command Center";46;1
"Unit";"SCV";"Command Center";48;1
"Building";"FactoryTechLab";NA;47;0
"Unit";"Marine";"Barracks";48;1
"Unit";"SCV";"Command Center";51;1
"Unit";"Marine";"Barracks";50;1
"Unit";"SCV";"Command Center";52;1
"Unit";"SCV";"Command Center";53;1
"Building";"SupplyDepot";NA;51;0
"Building";"SupplyDepot";NA;52;0
"Unit";"SCV";"Command Center";55;1
"Unit";"SCV";"Command Center";57;1
"Building";"Refinery";NA;55;0
"Unit";"SCV";"Command Center";57;1
"Unit";"Marine";"Barracks";57;1
"Unit";"Marine";"Barracks";57;1
"Unit";"SCV";"Command Center";58;1
"Unit";"Raven";"Starport";52;2
"Building";"SupplyDepot";NA;58;0
"Unit";"SCV";"Command Center";59;1
"Building";"CommandCenter";NA;47;0
"Unit";"SCV";"Command Center";62;1
"Unit";"SCV";"Command Center";65;1
"Unit";"SCV";"Command Center";66;1
"Building";"SupplyDepot";NA;66;0
"Unit";"SCV";"Command Center";67;1
"Unit";"SCV";"Command Center";70;1
"Unit";"SCV";"Command Center";70;1
"Unit";"Marine";"Barracks";69;1
"Unit";"SCV";"Command Center";71;1
"Unit";"SCV";"Command Center";73;1
"Building";"StarportReactor";NA;69;0
"Unit";"Marine";"Barracks";73;1
"Building";"Barracks";NA;69;0
"Building";"Refinery";NA;73;0
"Unit";"SCV";"Command Center";75;1
"Unit";"SCV";"Command Center";75;1
"Building";"Barracks";NA;70;0
"Building";"EngineeringBay";NA;75;0
"Unit";"SCV";"Command Center";76;1
"Building";"EngineeringBay";NA;75;0
"Unit";"SCV";"Command Center";77;1
"Unit";"Marine";"Barracks";76;1
"Unit";"SCV";"Command Center";78;1
"Unit";"SCV";"Command Center";79;1
"Building";"SupplyDepot";NA;78;0
"Unit";"SCV";"Command Center";79;1
"Unit";"Marine";"Barracks";78;1
"Unit";"Marine";"Barracks";78;1
"Unit";"Marine";"Barracks";78;1
"Unit";"Marine";"Barracks";78;1
"Building";"Barracks";NA;73;0
"Unit";"Marine";"Barracks";80;1
"Building";"Barracks";NA;75;0
"Unit";"SCV";"Command Center";81;1
"Unit";"SCV";"Command Center";82;1
"Unit";"SCV";"Command Center";83;1
"Building";"StarportReactor";NA;78;0
"Unit";"Marine";"Barracks";84;1
"Unit";"Marine";"Barracks";88;1
"Unit";"Marine";"Barracks";88;1
"Unit";"Marine";"Barracks";88;1
"Unit";"SCV";"Command Center";89;1
"Unit";"SCV";"Command Center";90;1
"Unit";"SCV";"Command Center";91;1
"Unit";"SCV";"Command Center";96;1
"Unit";"SCV";"Command Center";97;1
"Building";"SupplyDepot";NA;92;0
"Unit";"SCV";"Command Center";98;1
"Building";"SensorTower";NA;93;0
"Unit";"Marine";"Barracks";98;1
"Building";"BarracksReactor";NA;89;0
"Unit";"SCV";"Command Center";99;1
"Unit";"SCV";"Command Center";100;1
"Unit";"Marine";"Barracks";99;1
"Unit";"Marine";"Barracks";99;1
"Unit";"Marine";"Barracks";99;1
"Unit";"SCV";"Command Center";101;1
"Upgrade";"Stimpack";"TechLab";75;0
"Building";"SupplyDepot";NA;99;0
"Unit";"Medivac";"Starport";98;2
"Unit";"Marine";"Barracks";102;1
"Unit";"Medivac";"Starport";99;2
"Building";"SupplyDepot";NA;102;0
"Unit";"SCV";"Command Center";103;1
"Unit";"SCV";"Command Center";104;1
"Unit";"SCV";"Command Center";108;1
"Unit";"Marine";"Barracks";103;1
"Unit";"Marine";"Barracks";105;1
"Unit";"Marine";"Barracks";106;1
"Unit";"Marine";"Barracks";109;1
"Building";"BarracksReactor";NA;99;0
"Building";"SensorTower";NA;109;0
"Unit";"Marine";"Barracks";109;1
"Unit";"Marine";"Barracks";109;1
"Unit";"SCV";"Command Center";114;1
"Unit";"SCV";"Command Center";115;1
"Building";"SupplyDepot";NA;109;0
"Unit";"SCV";"Command Center";116;1
"Unit";"Marine";"Barracks";114;1
"Building";"Factory";NA;101;0
"Building";"Refinery";NA;114;0
"Building";"Refinery";NA;116;0
"Unit";"Marine";"Barracks";121;1
"Unit";"Marine";"Barracks";121;1
"Unit";"Marine";"Barracks";121;1
"Unit";"Marine";"Barracks";121;1
"Unit";"Marine";"Barracks";121;1
"Unit";"Marine";"Barracks";125;1
"Unit";"Marine";"Barracks";127;1
"Unit";"Marine";"Barracks";127;1
"Unit";"Marine";"Barracks";127;1
"Unit";"Marine";"Barracks";127;1
"Unit";"Marine";"Barracks";128;1
"Unit";"Marine";"Barracks";132;1
"Building";"SupplyDepot";NA;133;0
"Building";"Barracks";NA;120;0
"Building";"Barracks";NA;120;0
"Building";"SupplyDepot";NA;133;0
"Building";"Barracks";NA;125;0
"Unit";"Medivac";"Starport";132;2
"Unit";"Medivac";"Starport";132;2
"Building";"SupplyDepot";NA;135;0
"Building";"SupplyDepot";NA;135;0
"Unit";"Marine";"Barracks";139;1
"Unit";"Marine";"Barracks";139;1
"Unit";"Marine";"Barracks";139;1
"Unit";"Marine";"Barracks";139;1
"Unit";"Marine";"Barracks";139;1
"Unit";"Marine";"Barracks";139;1
"Unit";"Marine";"Barracks";139;1
"Unit";"Marine";"Barracks";139;1
"Building";"Armory";NA;133;0
"Unit";"Marine";"Barracks";143;1
"Upgrade";"TerranInfantryWeaponsLevel1";"EngineeringBay";114;0
"Upgrade";"TerranInfantryArmorsLevel1";"EngineeringBay";116;0
"Unit";"Marine";"Barracks";143;1
"Unit";"Marine";"Barracks";143;1
"Unit";"Marine";"Barracks";143;1
"Unit";"Marine";"Barracks";143;1
"Unit";"Marine";"Barracks";143;1
"Unit";"Marine";"Barracks";143;1
"Building";"BarracksReactor";NA;143;0
"Unit";"Marine";"Barracks";151;1
"Unit";"Marine";"Barracks";151;1
"Unit";"Marine";"Barracks";151;1
"Building";"BarracksReactor";NA;143;0
"Building";"SupplyDepot";NA;151;0
"Building";"SupplyDepot";NA;151;0
"Unit";"Medivac";"Starport";151;2
"Unit";"Marine";"Barracks";161;1
"Unit";"Marine";"Barracks";161;1
"Unit";"Marine";"Barracks";161;1
"Unit";"Marine";"Barracks";161;1
"Unit";"Marine";"Barracks";161;1
"Unit";"Marine";"Barracks";161;1
"Unit";"Marine";"Barracks";161;1
"Unit";"Marine";"Barracks";161;1
"Unit";"Marine";"Barracks";161;1
"Unit";"Marine";"Barracks";161;1
"Unit";"Marine";"Barracks";161;1
"Unit";"Marine";"Barracks";161;1
"Building";"BarracksReactor";NA;153;0
"Building";"BarracksReactor";NA;158;0
"Unit";"Marine";"Barracks";163;1
"Unit";"Marine";"Barracks";164;1
"Unit";"Marine";"Barracks";165;1
"Unit";"Medivac";"Starport";161;2
"Unit";"Marine";"Barracks";175;1
"Unit";"Marine";"Barracks";175;1
"Unit";"Marine";"Barracks";175;1
"Unit";"Marine";"Barracks";175;1
"Unit";"Marine";"Barracks";175;1
"Unit";"Marine";"Barracks";175;1
"Unit";"Marine";"Barracks";175;1
"Unit";"Marine";"Barracks";175;1
"Unit";"Marine";"Barracks";175;1
"Unit";"Marine";"Barracks";175;1
"Unit";"Marine";"Barracks";176;1
"Unit";"Marine";"Barracks";177;1
"Unit";"Marine";"Barracks";180;1
"Building";"CommandCenter";NA;152;0
"Unit";"Marine";"Barracks";193;1
"Unit";"Marine";"Barracks";193;1
"Unit";"Marine";"Barracks";193;1
"Unit";"Marine";"Barracks";193;1
"Unit";"Marine";"Barracks";193;1
"Unit";"Marine";"Barracks";193;1
"Unit";"Marine";"Barracks";193;1
"Unit";"Marine";"Barracks";193;1
"Unit";"Marine";"Barracks";193;1
"Unit";"Marine";"Barracks";193;1
"Unit";"Marine";"Barracks";193;1
"Unit";"Marine";"Barracks";193;1
"Unit";"Marine";"Barracks";193;1
"Unit";"Marine";"Barracks";193;1
"Unit";"Marine";"Barracks";193;1
"Unit";"Marine";"Barracks";193;1
"Upgrade";"TerranVehicleWeaponsLevel1";"Armory";166;0
"Unit";"Marine";"Barracks";193;1
"Unit";"Marine";"Barracks";194;1
"Unit";"Marine";"Barracks";194;1
"Unit";"Marine";"Barracks";196;1
"Unit";"Marine";"Barracks";197;1
"Building";"CommandCenter";NA;189;0
"Upgrade";"TerranInfantryWeaponsLevel2";"EngineeringBay";175;0
"Upgrade";"TerranInfantryArmorsLevel2";"EngineeringBay";175;0
"Unit";"Marine";"Barracks";209;1
"Unit";"Marine";"Barracks";209;1
"Unit";"Marine";"Barracks";209;1
"Unit";"Marine";"Barracks";209;1
"Unit";"Marine";"Barracks";209;1
"Unit";"Marine";"Barracks";209;1
"Unit";"Marine";"Barracks";209;1
"Unit";"Marine";"Barracks";209;1
"Unit";"Marine";"Barracks";209;1
"Unit";"Marine";"Barracks";209;1
"Unit";"Marine";"Barracks";209;1
"Unit";"Marine";"Barracks";209;1
"Unit";"Marine";"Barracks";210;1
"Unit";"Marine";"Barracks";210;1
"Unit";"Marine";"Barracks";212;1
"Unit";"Marine";"Barracks";214;1
"Unit";"Marine";"Barracks";214;1
"Unit";"Marine";"Barracks";215;1
"Unit";"Marine";"Barracks";216;1
"Unit";"Marine";"Barracks";216;1
"Unit";"Marine";"Barracks";218;1
"Unit";"Marine";"Barracks";218;1
"Unit";"Marine";"Barracks";220;1
"Unit";"Marine";"Barracks";220;1
"Unit";"Marine";"Barracks";222;1
"Unit";"Marine";"Barracks";223;1
"Unit";"Marine";"Barracks";223;1
"Unit";"Marine";"Barracks";225;1
"Unit";"Marine";"Barracks";230;1
"Unit";"Marine";"Barracks";230;1
"Unit";"Marine";"Barracks";230;1
"Unit";"Medivac";"Starport";215;2
"Unit";"Medivac";"Starport";215;2
"Unit";"Marine";"Barracks";230;1
"Unit";"Marine";"Barracks";230;1
"Unit";"Marine";"Barracks";231;1
"Unit";"Marine";"Barracks";242;1
"Unit";"Marine";"Barracks";242;1
"Unit";"Marine";"Barracks";242;1
"Unit";"Marine";"Barracks";242;1
"Unit";"Marine";"Barracks";242;1
"Unit";"Marine";"Barracks";242;1
"Unit";"Marine";"Barracks";242;1
"Unit";"Marine";"Barracks";249;1
"Unit";"Marine";"Barracks";249;1
"Unit";"Marine";"Barracks";252;1
"Unit";"Marine";"Barracks";252;1
"Unit";"Marine";"Barracks";252;1
"Unit";"Marine";"Barracks";253;1
"Unit";"Marine";"Barracks";265;1
"Unit";"Marine";"Barracks";265;1
"Unit";"Marine";"Barracks";265;1
"Unit";"Marine";"Barracks";265;1
"Unit";"Marine";"Barracks";265;1
"Unit";"Marine";"Barracks";265;1
"Unit";"Marine";"Barracks";265;1
"Unit";"Marine";"Barracks";265;1
"Unit";"Marine";"Barracks";265;1
"Unit";"Marine";"Barracks";265;1
"Unit";"Marine";"Barracks";265;1
"Unit";"Marine";"Barracks";265;1
"Unit";"Marine";"Barracks";265;1
"Unit";"Marine";"Barracks";265;1
"Unit";"Marine";"Barracks";265;1
"Unit";"Marine";"Barracks";265;1
"Unit";"Medivac";"Starport";265;2
"Unit";"Medivac";"Starport";265;2
"Unit";"Marine";"Barracks";265;1
"Unit";"Marine";"Barracks";266;1
"Unit";"Marine";"Barracks";267;1
"Unit";"Marine";"Barracks";267;1
"Unit";"Marine";"Barracks";269;1
"Unit";"Marine";"Barracks";269;1
"Unit";"Marine";"Barracks";271;1
"Unit";"Marine";"Barracks";281;1
"Unit";"Marine";"Barracks";281;1
"Unit";"Marine";"Barracks";281;1
"Unit";"Marine";"Barracks";281;1
"Unit";"Marine";"Barracks";281;1
"Unit";"Marine";"Barracks";281;1
"Unit";"Marine";"Barracks";281;1
"Unit";"Marine";"Barracks";281;1
"Unit";"Marine";"Barracks";281;1
"Unit";"Marine";"Barracks";285;1
"Unit";"Marine";"Barracks";286;1
"Unit";"Marine";"Barracks";287;1
"Unit";"Marine";"Barracks";292;1
"Unit";"Marine";"Barracks";292;1
"Unit";"Marine";"Barracks";292;1
"Unit";"Marine";"Barracks";292;1
"Unit";"Marine";"Barracks";292;1
"Unit";"Marine";"Barracks";293;1
"Unit";"Marine";"Barracks";293;1
"Unit";"Marine";"Barracks";295;1
"Unit";"Marine";"Barracks";301;1
"Unit";"Marine";"Barracks";301;1
"Unit";"Liberator";"Starport";281;3
"Unit";"Marine";"Barracks";314;1
"Unit";"Marine";"Barracks";314;1
"Unit";"Marine";"Barracks";314;1
"Unit";"Marine";"Barracks";314;1
"Unit";"Marine";"Barracks";314;1
"Unit";"Marine";"Barracks";314;1
"Unit";"Marine";"Barracks";314;1
"Unit";"Marine";"Barracks";314;1
"Unit";"Marine";"Barracks";314;1
"Unit";"Marine";"Barracks";314;1
"Unit";"Marine";"Barracks";314;1
"Unit";"Marine";"Barracks";314;1
"Unit";"Marine";"Barracks";314;1
"Unit";"Marine";"Barracks";314;1
"Unit";"Marine";"Barracks";314;1
"Unit";"Marine";"Barracks";314;1
"Unit";"Marine";"Barracks";317;1
"Unit";"Marine";"Barracks";318;1
"Unit";"Marine";"Barracks";319;1
"Unit";"Marine";"Barracks";320;1
"Unit";"Marine";"Barracks";321;1
"Unit";"Marine";"Barracks";321;1
"Unit";"Marine";"Barracks";323;1
"Unit";"Marine";"Barracks";323;1
"Unit";"Marine";"Barracks";333;1
"Unit";"Marine";"Barracks";333;1
"Unit";"Marine";"Barracks";333;1
"Unit";"Marine";"Barracks";333;1
"Unit";"Marine";"Barracks";333;1
"Unit";"Marine";"Barracks";333;1
"Unit";"Marine";"Barracks";333;1
"Unit";"Marine";"Barracks";333;1
"Unit";"Medivac";"Starport";314;2
"Unit";"Medivac";"Starport";314;2
"Building";"SensorTower";NA;333;0
"Upgrade";"TerranInfantryWeaponsLevel3";"EngineeringBay";265;0
"Unit";"Marine";"Barracks";333;1
"Unit";"Marine";"Barracks";334;1
"Unit";"Marine";"Barracks";335;1
"Unit";"Marine";"Barracks";342;1
"Unit";"Marine";"Barracks";343;1
"Upgrade";"TerranInfantryArmorsLevel3";"EngineeringBay";265;0
"Unit";"Marine";"Barracks";346;1
"Unit";"Marine";"Barracks";349;1
"Unit";"Marine";"Barracks";349;1
"Unit";"Marine";"Barracks";353;1
"Unit";"Marine";"Barracks";353;1
"Unit";"Marine";"Barracks";353;1
"Unit";"Marine";"Barracks";353;1
"Unit";"Marine";"Barracks";353;1
"Unit";"Marine";"Barracks";353;1
"Unit";"Marine";"Barracks";353;1
"Unit";"Marine";"Barracks";361;1
"Unit";"Marine";"Barracks";361;1
"Unit";"Marine";"Barracks";361;1
"Unit";"Marine";"Barracks";361;1
"Unit";"Marine";"Barracks";361;1
"Unit";"Marine";"Barracks";361;1
"Unit";"Marine";"Barracks";361;1
"Building";"Refinery";NA;375;0
"Building";"Refinery";NA;375;0
"Unit";"Marine";"Barracks";375;1
"Unit";"Marine";"Barracks";375;1
"Unit";"Marine";"Barracks";375;1
"Unit";"Marine";"Barracks";375;1
"Unit";"Marine";"Barracks";375;1
"Unit";"Marine";"Barracks";375;1
"Unit";"Marine";"Barracks";375;1
"Unit";"Marine";"Barracks";375;1
"Unit";"Marine";"Barracks";375;1
"Unit";"Marine";"Barracks";375;1
"Unit";"Marine";"Barracks";375;1
"Unit";"Marine";"Barracks";375;1
"Unit";"Marine";"Barracks";375;1
"Unit";"Marine";"Barracks";375;1
"Unit";"Marine";"Barracks";375;1
"Unit";"Marine";"Barracks";375;1
"Building";"CommandCenter";NA;368;0
"Unit";"Marine";"Barracks";375;1
"Unit";"Marine";"Barracks";376;1
"Unit";"Marine";"Barracks";377;1
"Unit";"Marine";"Barracks";378;1
"Unit";"Marine";"Barracks";379;1
"Unit";"Marine";"Barracks";379;1
"Unit";"Marine";"Barracks";386;1
"Unit";"Marine";"Barracks";386;1
"Unit";"Marine";"Barracks";386;1
"Unit";"Marine";"Barracks";386;1
"Unit";"Marine";"Barracks";386;1
"Unit";"Marine";"Barracks";386;1
"Unit";"Marine";"Barracks";387;1
"Unit";"Marine";"Barracks";391;1
"Unit";"Marine";"Barracks";393;1
"Unit";"Marine";"Barracks";393;1
"Unit";"Marine";"Barracks";393;1
"Unit";"Marine";"Barracks";393;1
"Unit";"Marine";"Barracks";393;1
"Unit";"Marine";"Barracks";394;1
"Unit";"Marine";"Barracks";395;1
"Building";"CommandCenter";NA;375;0
"Building";"CommandCenter";NA;375;0
"Unit";"Marine";"Barracks";405;1
"Unit";"Marine";"Barracks";405;1
"Unit";"Marine";"Barracks";405;1
"Unit";"Marine";"Barracks";405;1
"Unit";"Marine";"Barracks";405;1
"Unit";"Marine";"Barracks";405;1
"Unit";"Marine";"Barracks";405;1
"Building";"Starport";NA;393;0
"Unit";"Marine";"Barracks";412;1
"Unit";"Marine";"Barracks";412;1
"Unit";"Marine";"Barracks";412;1
"Unit";"Marine";"Barracks";412;1
"Unit";"Marine";"Barracks";412;1
"Unit";"Marine";"Barracks";412;1
"Unit";"Marine";"Barracks";412;1
"Unit";"Marine";"Barracks";412;1
"Unit";"Marine";"Barracks";412;1
"Building";"Factory";NA;393;0
"Unit";"Marine";"Barracks";412;1
"Unit";"Marine";"Barracks";413;1
"Unit";"Marine";"Barracks";414;1
"Unit";"Medivac";"Starport";412;2
"Unit";"Marine";"Barracks";419;1
"Unit";"Marine";"Barracks";419;1
"Unit";"Marine";"Barracks";419;1
"Unit";"Marine";"Barracks";419;1
"Unit";"Marine";"Barracks";419;1
"Unit";"Marine";"Barracks";420;1
"Unit";"Marine";"Barracks";421;1
"Unit";"Marine";"Barracks";421;1
"Unit";"Marine";"Barracks";423;1
"Unit";"Marine";"Barracks";423;1
"Upgrade";"TerranVehicleWeaponsLevel2";"Armory";375;0
"Unit";"Marine";"Barracks";428;1
"Unit";"Marine";"Barracks";428;1
"Unit";"Marine";"Barracks";428;1
"Unit";"Marine";"Barracks";428;1
"Unit";"Marine";"Barracks";429;1
"Unit";"Marine";"Barracks";430;1
"Unit";"Marine";"Barracks";433;1
"Unit";"Marine";"Barracks";434;1
"Unit";"Marine";"Barracks";435;1
"Unit";"Marine";"Barracks";446;1
"Unit";"Marine";"Barracks";446;1
"Unit";"Marine";"Barracks";446;1
"Unit";"Marine";"Barracks";446;1
"Unit";"Marine";"Barracks";446;1
"Unit";"Marine";"Barracks";446;1
"Unit";"Marine";"Barracks";446;1
"Unit";"Marine";"Barracks";446;1
"Unit";"Marine";"Barracks";446;1
"Unit";"Marine";"Barracks";446;1
"Unit";"Medivac";"Starport";431;2
"Unit";"Marine";"Barracks";446;1
"Unit";"Marine";"Barracks";447;1
"Unit";"Marine";"Barracks";449;1
"Unit";"Marine";"Barracks";449;1
"Unit";"Marine";"Barracks";450;1
"Unit";"Marine";"Barracks";452;1
"Unit";"Marine";"Barracks";452;1
"Unit";"Marine";"Barracks";453;1
"Unit";"Marine";"Barracks";453;1
"Unit";"Marine";"Barracks";455;1
"Unit";"Marine";"Barracks";456;1
"Unit";"Marine";"Barracks";457;1
"Unit";"Marine";"Barracks";466;1
"Unit";"Marine";"Barracks";467;1
"Unit";"Marine";"Barracks";467;1
"Unit";"Marine";"Barracks";467;1
"Unit";"Marine";"Barracks";467;1
"Unit";"Marine";"Barracks";467;1
"Unit";"Marine";"Barracks";467;1
"Unit";"SCV";"Command Center";470;1
"Unit";"Marine";"Barracks";467;1
"Building";"StarportTechLab";NA;476;0
"Unit";"Marine";"Barracks";483;1
"Unit";"Marine";"Barracks";483;1
"Unit";"Marine";"Barracks";483;1
"Unit";"Marine";"Barracks";483;1
"Unit";"Marine";"Barracks";483;1
"Unit";"Marine";"Barracks";483;1
"Unit";"Marine";"Barracks";483;1
"Unit";"Marine";"Barracks";483;1
"Unit";"Marine";"Barracks";483;1
"Unit";"Marine";"Barracks";494;1
"Unit";"Marine";"Barracks";494;1
"Unit";"Marine";"Barracks";494;1
"Unit";"Marine";"Barracks";494;1
"Unit";"Marine";"Barracks";494;1
"Unit";"Marine";"Barracks";494;1
"Unit";"Marine";"Barracks";494;1
"Unit";"Marine";"Barracks";494;1
"Unit";"Marine";"Barracks";494;1
"Unit";"Marine";"Barracks";494;1
"Unit";"Marine";"Barracks";494;1
"Unit";"Marine";"Barracks";494;1
"Unit";"Marine";"Barracks";494;1
"Unit";"Marine";"Barracks";494;1
"Unit";"Marine";"Barracks";494;1
"Unit";"Marine";"Barracks";494;1
