"type";"unit_name";"on_building";"total_supply";"supply"
"Building";"Refinery";NA;15;0
"Building";"Barracks";NA;15;0
"Unit";"Reaper";"Barracks";19;1
"Unit";"Marine";"Barracks";19;1
"Building";"Refinery";NA;22;0
"Building";"CommandCenter";NA;19;0
"Building";"Factory";NA;21;0
"Building";"BarracksReactor";NA;23;0
"Unit";"Marine";"Barracks";26;1
"Unit";"Marine";"Barracks";26;1
"Unit";"Cyclone";"Factory";26;3
"Unit";"Marine";"Barracks";30;1
"Unit";"Marine";"Barracks";30;1
"Building";"Starport";NA;27;0
"Unit";"Cyclone";"Factory";37;3
"Unit";"Marine";"Barracks";38;1
"Unit";"Marine";"Barracks";38;1
"Unit";"Marine";"Barracks";46;1
"Unit";"Marine";"Barracks";46;1
"Unit";"Medivac";"Starport";40;2
"Building";"EngineeringBay";NA;48;0
"Unit";"Marine";"Barracks";52;1
"Unit";"Marine";"Barracks";52;1
"Unit";"Cyclone";"Factory";51;3
"Building";"FactoryTechLab";NA;62;0
"Building";"Barracks";NA;54;0
"Building";"Barracks";NA;54;0
"Building";"BarracksTechLab";NA;63;0
"Building";"StarportReactor";NA;56;0
"Building";"Refinery";NA;64;0
"Building";"Refinery";NA;64;0
"Unit";"Marine";"Barracks";70;1
"Unit";"Marine";"Barracks";70;1
"Unit";"Marine";"Barracks";70;1
"Unit";"Marine";"Barracks";70;1
"Unit";"Marine";"Barracks";70;1
"Building";"StarportReactor";NA;68;0
"Building";"CommandCenter";NA;65;0
"Unit";"Marine";"Barracks";72;1
"Unit";"Marine";"Barracks";77;1
"Unit";"Marine";"Barracks";77;1
"Unit";"Marine";"Barracks";77;1
"Unit";"Marine";"Barracks";77;1
"Unit";"Marine";"Barracks";80;1
"Unit";"Marine";"Barracks";81;1
"Unit";"Marine";"Barracks";86;1
"Unit";"Marine";"Barracks";86;1
"Unit";"Marine";"Barracks";86;1
"Building";"EngineeringBay";NA;86;0
"Unit";"Marine";"Barracks";88;1
"Upgrade";"TerranInfantryWeaponsLevel1";"EngineeringBay";68;0
"Unit";"Medivac";"Starport";86;2
"Building";"Barracks";NA;79;0
"Building";"Barracks";NA;79;0
"Unit";"Marine";"Barracks";91;1
"Unit";"Marine";"Barracks";91;1
"Unit";"Marine";"Barracks";91;1
"Unit";"Marine";"Barracks";91;1
"Building";"MissileTurret";NA;91;0
"Unit";"Marine";"Barracks";91;1
"Building";"MissileTurret";NA;92;0
"Building";"MissileTurret";NA;92;0
"Building";"MissileTurret";NA;94;0
"Unit";"Marine";"Barracks";96;1
"Unit";"Marine";"Barracks";97;1
"Unit";"Marine";"Barracks";100;1
"Unit";"Marine";"Barracks";100;1
"Unit";"Marine";"Barracks";101;1
"Building";"Armory";NA;91;0
"Upgrade";"Stimpack";"TechLab";78;0
"Building";"BarracksReactor";NA;96;0
"Building";"BarracksReactor";NA;96;0
"Unit";"Marine";"Barracks";105;1
"Unit";"Marine";"Barracks";106;1
"Unit";"Marine";"Barracks";107;1
"Unit";"Medivac";"Starport";109;2
"Unit";"Medivac";"Starport";109;2
"Unit";"Marine";"Barracks";111;1
"Unit";"Marine";"Barracks";111;1
"Unit";"Marine";"Barracks";111;1
"Unit";"Marine";"Barracks";113;1
"Unit";"Marine";"Barracks";114;1
"Unit";"Marine";"Barracks";114;1
"Unit";"Marine";"Barracks";114;1
"Unit";"Marine";"Barracks";114;1
"Unit";"Marine";"Barracks";114;1
"Unit";"Marine";"Barracks";118;1
"Unit";"Marine";"Barracks";121;1
"Unit";"Marine";"Barracks";121;1
"Unit";"Marine";"Barracks";122;1
"Unit";"Marine";"Barracks";122;1
"Unit";"Marine";"Barracks";123;1
"Unit";"Marine";"Barracks";127;1
"Unit";"Medivac";"Starport";122;2
"Unit";"Medivac";"Starport";122;2
"Unit";"Marine";"Barracks";127;1
"Unit";"Marine";"Barracks";127;1
"Building";"Refinery";NA;127;0
"Unit";"Marine";"Barracks";133;1
"Upgrade";"TerranInfantryArmorsLevel1";"EngineeringBay";109;0
"Unit";"Marine";"Barracks";136;1
"Building";"Refinery";NA;135;0
"Unit";"Marine";"Barracks";142;1
"Unit";"Marine";"Barracks";144;1
"Unit";"Marine";"Barracks";144;1
"Unit";"Marine";"Barracks";144;1
"Unit";"Marine";"Barracks";144;1
"Unit";"Marine";"Barracks";144;1
"Building";"Factory";NA;133;0
"Building";"Barracks";NA;133;0
"Unit";"Marine";"Barracks";145;1
"Unit";"Marine";"Barracks";145;1
"Unit";"Marine";"Barracks";145;1
"Building";"Barracks";NA;133;0
"Unit";"Marine";"Barracks";150;1
"Unit";"Marine";"Barracks";151;1
"Unit";"Medivac";"Starport";151;2
"Unit";"Medivac";"Starport";151;2
"Unit";"Marine";"Barracks";155;1
"Unit";"Marine";"Barracks";155;1
"Unit";"Marine";"Barracks";155;1
"Unit";"Marine";"Barracks";155;1
"Unit";"Marine";"Barracks";155;1
"Unit";"Marine";"Barracks";155;1
"Unit";"Marine";"Barracks";155;1
"Unit";"Marine";"Barracks";156;1
"Unit";"Marine";"Barracks";156;1
"Building";"FactoryTechLab";NA;160;0
"Unit";"Marine";"Barracks";160;1
"Unit";"Marine";"Barracks";161;1
"Unit";"Marine";"Barracks";161;1
"Unit";"Marine";"Barracks";163;1
"Unit";"Marine";"Barracks";169;1
"Unit";"Marine";"Barracks";169;1
"Unit";"Marine";"Barracks";169;1
"Unit";"Marine";"Barracks";169;1
"Unit";"Marine";"Barracks";169;1
"Building";"BarracksReactor";NA;160;0
"Building";"BarracksReactor";NA;160;0
"Unit";"Marine";"Barracks";169;1
"Unit";"Marine";"Barracks";170;1
"Unit";"Marine";"Barracks";173;1
"Unit";"Marine";"Barracks";173;1
"Unit";"Marine";"Barracks";173;1
"Upgrade";"TerranInfantryWeaponsLevel2";"EngineeringBay";144;0
"Building";"SensorTower";NA;178;0
"Unit";"Marine";"Barracks";178;1
"Unit";"Medivac";"Starport";173;2
"Building";"SensorTower";NA;178;0
"Unit";"Medivac";"Starport";173;2
"Unit";"Marine";"Barracks";178;1
"Unit";"Marine";"Barracks";178;1
"Unit";"Marine";"Barracks";178;1
"Unit";"Marine";"Barracks";178;1
"Unit";"Marine";"Barracks";178;1
"Unit";"Marine";"Barracks";183;1
"Unit";"Marine";"Barracks";183;1
"Unit";"Marine";"Barracks";183;1
"Unit";"Marine";"Barracks";193;1
"Unit";"Marine";"Barracks";193;1
"Upgrade";"TerranVehicleWeaponsLevel1";"Armory";160;0
"Unit";"Marine";"Barracks";193;1
"Unit";"Marine";"Barracks";193;1
"Unit";"Marine";"Barracks";193;1
"Unit";"Marine";"Barracks";193;1
"Unit";"Marine";"Barracks";193;1
"Unit";"Marine";"Barracks";194;1
"Upgrade";"TerranInfantryArmorsLevel2";"EngineeringBay";160;0
"Unit";"Medivac";"Starport";193;2
"Unit";"Marine";"Barracks";203;1
