"Type";"UnitName";"OnBuilding";"TotalSupply";"Supply"
"Unit";"SCV";"Command Center";12;1
"Unit";"SCV";"Command Center";12;1
"Unit";"SCV";"Command Center";14;1
"Building";"SupplyDepot";NA;13;0
"Unit";"SCV";"Command Center";15;1
"Building";"Refinery";NA;14;0
"Unit";"SCV";"Command Center";15;1
"Unit";"SCV";"Command Center";17;1
"Building";"Barracks";NA;15;0
"Unit";"SCV";"Command Center";18;1
"Unit";"Reaper";"Barracks";19;1
"Unit";"SCV";"Command Center";19;1
"Unit";"SCV";"Command Center";20;1
"Building";"Refinery";NA;21;0
"Unit";"SCV";"Command Center";21;1
"Building";"BarracksReactor";NA;20;0
"Unit";"SCV";"Command Center";23;1
"Building";"Factory";NA;19;0
"Building";"SupplyDepot";NA;22;0
"Unit";"SCV";"Command Center";23;1
"Building";"CommandCenter";NA;19;0
"Unit";"SCV";"Command Center";24;1
"Unit";"SCV";"Command Center";25;1
"Unit";"Cyclone";"Factory";25;3
"Unit";"SCV";"Command Center";26;1
"Building";"BarracksTechLab";NA;26;0
"Unit";"Cyclone";"Factory";26;3
"Unit";"SCV";"Command Center";27;1
"Unit";"SCV";"Command Center";30;1
"Unit";"SCV";"Command Center";35;1
"Unit";"SCV";"Command Center";36;1
"Unit";"SCV";"Command Center";36;1
"Unit";"Cyclone";"Factory";35;3
"Unit";"Cyclone";"Factory";35;3
"Building";"SupplyDepot";NA;37;0
"Unit";"SCV";"Command Center";38;1
"Unit";"SCV";"Command Center";39;1
"Unit";"SCV";"Command Center";45;1
"Unit";"SCV";"Command Center";46;1
"Unit";"SCV";"Command Center";47;1
"Unit";"SCV";"Command Center";48;1
"Unit";"Cyclone";"Factory";47;3
"Unit";"SCV";"Command Center";50;1
"Unit";"SCV";"Command Center";51;1
"Building";"SupplyDepot";NA;50;0
"Unit";"Cyclone";"Factory";49;3
"Unit";"SCV";"Command Center";54;1
"Building";"CommandCenter";NA;38;0
"Unit";"SCV";"Command Center";56;1
"Building";"Refinery";NA;54;0
"Building";"Refinery";NA;55;0
"Unit";"SCV";"Command Center";59;1
"Unit";"SCV";"Command Center";62;1
"Unit";"SCV";"Command Center";62;1
"Unit";"SCV";"Command Center";63;1
"Unit";"SCV";"Command Center";63;1
"Unit";"Cyclone";"Factory";63;3
"Unit";"SCV";"Command Center";64;1
"Unit";"SCV";"Command Center";64;1
"Building";"Armory";NA;54;0
"Building";"EngineeringBay";NA;63;0
"Unit";"SCV";"Command Center";65;1
"Unit";"SCV";"Command Center";69;1
"Unit";"SCV";"Command Center";70;1
"Unit";"SCV";"Command Center";71;1
"Unit";"SCV";"Command Center";72;1
"Unit";"SCV";"Command Center";73;1
"Unit";"Cyclone";"Factory";71;3
"Unit";"SCV";"Command Center";74;1
"Unit";"SCV";"Command Center";75;1
"Building";"MissileTurret";NA;74;0
"Unit";"SCV";"Command Center";77;1
"Unit";"SCV";"Command Center";80;1
"Building";"BarracksTechLab";NA;77;0
"Unit";"SCV";"Command Center";81;1
"Unit";"SCV";"Command Center";82;1
"Building";"MissileTurret";NA;81;0
"Unit";"Cyclone";"Factory";80;3
"Unit";"SCV";"Command Center";83;1
"Unit";"SCV";"Command Center";84;1
"Unit";"SCV";"Command Center";85;1
"Unit";"SCV";"Command Center";90;1
"Unit";"SCV";"Command Center";90;1
"Unit";"SCV";"Command Center";91;1
"Unit";"SCV";"Command Center";92;1
"Unit";"SCV";"Command Center";93;1
"Building";"Refinery";NA;92;0
"Building";"Refinery";NA;92;0
"Unit";"SCV";"Command Center";95;1
"Unit";"SCV";"Command Center";95;1
"Building";"Factory";NA;90;0
"Unit";"SCV";"Command Center";98;1
"Unit";"SCV";"Command Center";98;1
"Building";"Factory";NA;91;0
"Building";"SupplyDepot";NA;97;0
"Building";"SupplyDepot";NA;97;0
"Building";"SupplyDepot";NA;97;0
"Unit";"SCV";"Command Center";99;1
"Unit";"SCV";"Command Center";99;1
"Unit";"Hellion";"Factory";98;2
"Unit";"SCV";"Command Center";101;1
"Unit";"Hellion";"Factory";99;2
"Building";"Armory";NA;93;0
"Upgrade";"TerranVehicleWeaponsLevel1";"Armory";82;0
"Unit";"SCV";"Command Center";101;1
"Unit";"SCV";"Command Center";102;1
"Unit";"SCV";"Command Center";105;1
"Unit";"SCV";"Command Center";108;1
"Unit";"SCV";"Command Center";110;1
"Unit";"SCV";"Command Center";111;1
"Unit";"SCV";"Command Center";112;1
"Unit";"Hellion";"Factory";111;2
"Unit";"Hellion";"Factory";111;2
"Unit";"Hellion";"Factory";114;2
"Building";"SupplyDepot";NA;114;0
"Building";"SupplyDepot";NA;119;0
"Building";"BarracksReactor";NA;115;0
"Unit";"Hellion";"Factory";119;2
"Building";"Starport";NA;119;0
"Unit";"Hellion";"Factory";121;2
"Building";"SupplyDepot";NA;121;0
"Building";"SupplyDepot";NA;121;0
"Unit";"Hellion";"Factory";125;2
"Unit";"Hellion";"Factory";125;2
"Unit";"SCV";"Command Center";125;1
"Unit";"SCV";"Command Center";125;1
"Unit";"SCV";"Command Center";125;1
"Building";"BarracksTechLab";NA;125;0
"Unit";"SCV";"Command Center";129;1
"Building";"SupplyDepot";NA;129;0
"Building";"SupplyDepot";NA;131;0
"Building";"Factory";NA;125;0
"Building";"Factory";NA;125;0
"Building";"CommandCenter";NA;121;0
"Unit";"Hellion";"Factory";132;2
"Unit";"Hellion";"Factory";133;2
"Upgrade";"TerranVehicleAndShipArmorsLevel1";"Armory";121;0
"Building";"BarracksTechLab";NA;133;0
"Building";"SensorTower";NA;133;0
"Unit";"SCV";"Command Center";137;1
"Unit";"Hellion";"Factory";133;2
"Building";"SensorTower";NA;133;0
"Unit";"SCV";"Command Center";137;1
"Unit";"Hellion";"Factory";135;2
"Upgrade";"TerranVehicleWeaponsLevel2";"Armory";121;0
"Unit";"Hellion";"Factory";143;2
"Unit";"Hellion";"Factory";143;2
"Building";"Refinery";NA;143;0
"Building";"Refinery";NA;143;0
"Building";"SensorTower";NA;143;0
"Building";"SupplyDepot";NA;143;0
"Building";"SupplyDepot";NA;143;0
"Building";"SupplyDepot";NA;143;0
"Building";"Starport";NA;143;0
"Building";"FusionCore";NA;143;0
"Building";"MissileTurret";NA;147;0
"Building";"MissileTurret";NA;147;0
"Building";"MissileTurret";NA;147;0
"Building";"SupplyDepot";NA;147;0
"Building";"StarportTechLab";NA;147;0
"Building";"MissileTurret";NA;147;0
"Building";"MissileTurret";NA;147;0
"Building";"MissileTurret";NA;147;0
"Building";"CommandCenter";NA;147;0
"Building";"CommandCenter";NA;147;0
"Building";"Starport";NA;147;0
"Building";"Starport";NA;147;0
"Upgrade";"TerranVehicleAndShipArmorsLevel2";"Armory";147;0
"Unit";"Hellion";"Factory";147;2
"Unit";"Hellion";"Factory";147;2
"Building";"MissileTurret";NA;147;0
"Building";"MissileTurret";NA;147;0
"Upgrade";"TerranVehicleWeaponsLevel3";"Armory";147;0
"Unit";"Liberator";"Starport";147;3
"Unit";"Liberator";"Starport";147;3
"Unit";"Liberator";"Starport";147;3
"Unit";"Hellion";"Factory";151;2
"Unit";"Hellion";"Factory";151;2
"Building";"StarportTechLab";NA;151;0
"Building";"StarportTechLab";NA;151;0
"Unit";"Hellion";"Factory";160;2
"Building";"SensorTower";NA;164;0
"Unit";"Liberator";"Starport";151;3
"Unit";"Liberator";"Starport";154;3
"Building";"CommandCenter";NA;147;0
"Unit";"Hellion";"Factory";166;2
"Unit";"Hellion";"Factory";166;2
"Building";"Refinery";NA;176;0
"Unit";"Hellion";"Factory";176;2
"Building";"Refinery";NA;176;0
"Unit";"Hellion";"Factory";176;2
"Building";"SensorTower";NA;176;0
"Upgrade";"TerranShipWeaponsLevel1";"Armory";164;0
"Unit";"Hellion";"Factory";180;2
"Unit";"Hellion";"Factory";180;2
"Building";"Refinery";NA;180;0
"Upgrade";"TerranVehicleAndShipArmorsLevel3";"Armory";166;0
"Building";"Refinery";NA;184;0
"Building";"Refinery";NA;184;0
"Unit";"Hellion";"Factory";184;2
"Unit";"Hellion";"Factory";184;2
"Unit";"Hellion";"Factory";184;2
"Unit";"Hellion";"Factory";184;2
"Unit";"Hellion";"Factory";184;2
"Unit";"Hellion";"Factory";184;2
"Unit";"Hellion";"Factory";186;2
"Unit";"Cyclone";"Factory";194;3
"Building";"MissileTurret";NA;198;0
"Building";"MissileTurret";NA;201;0
"Building";"MissileTurret";NA;201;0
"Building";"MissileTurret";NA;201;0
"Building";"BarracksReactor";NA;201;0
"Building";"Starport";NA;201;0
"Building";"Starport";NA;201;0
"Unit";"Cyclone";"Factory";201;3
"Unit";"Cyclone";"Factory";201;3
"Unit";"Cyclone";"Factory";201;3
"Unit";"Cyclone";"Factory";201;3
"Unit";"Cyclone";"Factory";201;3
"Unit";"Cyclone";"Factory";201;3
"Building";"MissileTurret";NA;219;0
"Building";"MissileTurret";NA;219;0
"Building";"MissileTurret";NA;219;0
"Building";"MissileTurret";NA;219;0
"Building";"MissileTurret";NA;219;0
"Building";"MissileTurret";NA;219;0
"Building";"StarportTechLab";NA;219;0
"Building";"StarportTechLab";NA;219;0
"Building";"Refinery";NA;219;0
"Building";"Refinery";NA;219;0
"Building";"Starport";NA;219;0
"Building";"Starport";NA;219;0
"Building";"Starport";NA;219;0
"Unit";"Raven";"Starport";219;2
"Building";"StarportTechLab";NA;219;0
"Unit";"Raven";"Starport";219;2
"Building";"StarportTechLab";NA;219;0
"Unit";"Raven";"Starport";219;2
"Building";"StarportTechLab";NA;219;0
