"Type";"UnitName";"OnBuilding";"TotalSupply";"Supply"
"Unit";"SCV";"Command Center";12;1
"Unit";"SCV";"Command Center";12;1
"Unit";"SCV";"Command Center";13;1
"Building";"SupplyDepot";NA;13;0
"Building";"Refinery";NA;14;0
"Unit";"SCV";"Command Center";15;1
"Unit";"SCV";"Command Center";15;1
"Unit";"SCV";"Command Center";17;1
"Unit";"SCV";"Command Center";17;1
"Building";"Barracks";NA;15;0
"Unit";"Reaper";"Barracks";19;1
"Unit";"SCV";"Command Center";19;1
"Unit";"SCV";"Command Center";21;1
"Building";"Refinery";NA;19;0
"Building";"Factory";NA;19;0
"Building";"SupplyDepot";NA;21;0
"Unit";"Reaper";"Barracks";20;1
"Unit";"SCV";"Command Center";22;1
"Building";"CommandCenter";NA;19;0
"Building";"BarracksTechLab";NA;23;0
"Unit";"SCV";"Command Center";23;1
"Unit";"Hellion";"Factory";23;2
"Unit";"SCV";"Command Center";24;1
"Building";"Starport";NA;23;0
"Unit";"SCV";"Command Center";27;1
"Unit";"SCV";"Command Center";28;1
"Unit";"Cyclone";"Factory";28;3
"Unit";"SCV";"Command Center";30;1
"Unit";"SCV";"Command Center";30;1
"Unit";"SCV";"Command Center";33;1
"Unit";"SCV";"Command Center";34;1
"Building";"SupplyDepot";NA;33;0
"Building";"FactoryTechLab";NA;35;0
"Unit";"SCV";"Command Center";35;1
"Unit";"SCV";"Command Center";36;1
"Unit";"Banshee";"Starport";30;3
"Unit";"SCV";"Command Center";37;1
"Unit";"SCV";"Command Center";38;1
"Building";"BarracksReactor";NA;35;0
"Unit";"SCV";"Command Center";42;1
"Unit";"SCV";"Command Center";43;1
"Building";"Bunker";NA;38;0
"Building";"SupplyDepot";NA;43;0
"Unit";"SCV";"Command Center";44;1
"Unit";"Marine";"Barracks";44;1
"Unit";"Marine";"Barracks";44;1
"Unit";"SCV";"Command Center";46;1
"Building";"SupplyDepot";NA;46;0
"Building";"Barracks";NA;39;0
"Unit";"Marine";"Barracks";47;1
"Building";"Barracks";NA;42;0
"Unit";"SCV";"Command Center";50;1
"Unit";"Marine";"Barracks";48;1
"Unit";"SCV";"Command Center";50;1
"Unit";"Banshee";"Starport";44;3
"Unit";"SCV";"Command Center";51;1
"Unit";"Marine";"Barracks";50;1
"Unit";"Marine";"Barracks";52;1
"Unit";"SCV";"Command Center";54;1
"Building";"BarracksTechLab";NA;53;0
"Unit";"SCV";"Command Center";58;1
"Unit";"Marine";"Barracks";58;1
"Unit";"Marine";"Barracks";59;1
"Unit";"SCV";"Command Center";61;1
"Unit";"SCV";"Command Center";62;1
"Unit";"Marauder";"Barracks";61;2
"Unit";"SCV";"Command Center";64;1
"Building";"Refinery";NA;62;0
"Unit";"SCV";"Command Center";65;1
"Building";"Refinery";NA;62;0
"Unit";"SCV";"Command Center";68;1
"Building";"StarportReactor";NA;61;0
"Unit";"SCV";"Command Center";69;1
"Unit";"Marine";"Barracks";68;1
"Unit";"SCV";"Command Center";70;1
"Unit";"Marine";"Barracks";70;1
"Unit";"SCV";"Command Center";73;1
"Unit";"SCV";"Command Center";75;1
"Unit";"Marauder";"Barracks";73;2
"Unit";"Marauder";"Barracks";73;2
"Building";"Barracks";NA;68;0
"Building";"Barracks";NA;68;0
"Building";"SupplyDepot";NA;73;0
"Unit";"Marine";"Barracks";75;1
"Building";"SupplyDepot";NA;73;0
"Unit";"Marine";"Barracks";75;1
"Unit";"Medivac";"Starport";73;2
"Unit";"SCV";"Command Center";76;1
"Unit";"Medivac";"Starport";73;2
"Building";"CommandCenter";NA;62;0
"Building";"SupplyDepot";NA;77;0
"Unit";"SCV";"Command Center";83;1
"Unit";"Marauder";"Barracks";77;2
"Unit";"Marine";"Barracks";81;1
"Unit";"Marine";"Barracks";82;1
"Unit";"Marauder";"Barracks";88;2
"Unit";"Marauder";"Barracks";88;2
"Unit";"Marine";"Barracks";89;1
"Unit";"Marine";"Barracks";91;1
"Unit";"Marine";"Barracks";93;1
"Building";"BarracksReactor";NA;83;0
"Building";"FactoryReactor";NA;83;0
"Unit";"SCV";"Command Center";93;1
"Unit";"SCV";"Command Center";97;1
"Upgrade";"Stimpack";"TechLab";70;0
"Building";"EngineeringBay";NA;93;0
"Unit";"Marauder";"Barracks";93;2
"Unit";"Marauder";"Barracks";95;2
"Unit";"Marine";"Barracks";97;1
"Unit";"SCV";"Command Center";100;1
"Building";"EngineeringBay";NA;93;0
"Unit";"Marine";"Barracks";98;1
"Unit";"Marine";"Barracks";99;1
"Unit";"SCV";"Command Center";102;1
"Unit";"Marauder";"Barracks";102;2
"Unit";"Marauder";"Barracks";104;2
"Unit";"SCV";"Command Center";111;1
"Unit";"SCV";"Command Center";111;1
"Unit";"Marine";"Barracks";111;1
"Unit";"SCV";"Command Center";115;1
"Unit";"SCV";"Command Center";116;1
"Unit";"Marine";"Barracks";116;1
"Unit";"Marauder";"Barracks";116;2
"Unit";"Marauder";"Barracks";116;2
"Unit";"Marauder";"Barracks";116;2
"Unit";"SCV";"Command Center";118;1
"Unit";"SCV";"Command Center";119;1
"Unit";"SCV";"Command Center";120;1
"Unit";"SCV";"Command Center";127;1
"Unit";"Marine";"Barracks";121;1
"Unit";"Medivac";"Starport";118;2
"Unit";"Medivac";"Starport";118;2
"Building";"SupplyDepot";NA;120;0
"Unit";"Marauder";"Barracks";121;2
"Building";"Armory";NA;111;0
"Unit";"Marauder";"Barracks";130;2
"Unit";"Marauder";"Barracks";130;2
"Unit";"SCV";"Command Center";136;1
"Unit";"SCV";"Command Center";136;1
"Building";"SupplyDepot";NA;131;0
"Unit";"Marine";"Barracks";136;1
"Unit";"Marine";"Barracks";136;1
"Building";"SupplyDepot";NA;131;0
"Building";"SupplyDepot";NA;131;0
"Unit";"Marine";"Barracks";136;1
"Unit";"Marine";"Barracks";136;1
"Unit";"Marauder";"Barracks";136;2
"Unit";"Marine";"Barracks";144;1
"Unit";"Marauder";"Barracks";144;2
"Unit";"Marauder";"Barracks";144;2
"Unit";"Marauder";"Barracks";148;2
"Building";"Refinery";NA;150;0
"Building";"Refinery";NA;150;0
"Unit";"Medivac";"Starport";148;2
"Unit";"Marine";"Barracks";150;1
"Unit";"Medivac";"Starport";148;2
"Unit";"Marine";"Barracks";151;1
"Building";"SupplyDepot";NA;150;0
"Upgrade";"TerranInfantryWeaponsLevel1";"EngineeringBay";121;0
"Upgrade";"TerranInfantryArmorsLevel1";"EngineeringBay";121;0
"Unit";"Marauder";"Barracks";155;2
"Building";"Starport";NA;150;0
"Unit";"Marauder";"Barracks";157;2
"Unit";"Marauder";"Barracks";157;2
"Unit";"Marine";"Barracks";157;1
"Unit";"Marine";"Barracks";157;1
"Unit";"SCV";"Command Center";163;1
"Unit";"SCV";"Command Center";163;1
"Unit";"SCV";"Command Center";163;1
"Unit";"Marine";"Barracks";159;1
"Unit";"Marine";"Barracks";163;1
"Building";"SupplyDepot";NA;163;0
"Building";"SupplyDepot";NA;163;0
"Building";"SupplyDepot";NA;163;0
"Building";"CommandCenter";NA;148;0
"Unit";"Marauder";"Barracks";176;2
"Unit";"Marauder";"Barracks";176;2
"Unit";"Marine";"Barracks";176;1
"Unit";"Marine";"Barracks";176;1
"Unit";"Marauder";"Barracks";176;2
"Unit";"Marine";"Barracks";176;1
"Unit";"Marine";"Barracks";176;1
"Building";"StarportTechLab";NA;176;0
"Unit";"Marine";"Barracks";180;1
"Unit";"Marine";"Barracks";181;1
"Unit";"Marauder";"Barracks";176;2
