"Type";"UnitName";"OnBuilding";"TotalSupply";"Supply"
"Unit";"SCV";"Command Center";12;1
"Unit";"SCV";"Command Center";12;1
"Unit";"SCV";"Command Center";13;1
"Building";"SupplyDepot";NA;13;0
"Unit";"SCV";"Command Center";15;1
"Building";"Refinery";NA;14;0
"Unit";"SCV";"Command Center";15;1
"Unit";"SCV";"Command Center";16;1
"Unit";"SCV";"Command Center";17;1
"Building";"Barracks";NA;15;0
"Unit";"Reaper";"Barracks";19;1
"Unit";"SCV";"Command Center";19;1
"Unit";"SCV";"Command Center";20;1
"Building";"SupplyDepot";NA;20;0
"Unit";"SCV";"Command Center";21;1
"Building";"Factory";NA;19;0
"Building";"BarracksReactor";NA;21;0
"Unit";"SCV";"Command Center";23;1
"Building";"CommandCenter";NA;19;0
"Unit";"Hellion";"Factory";23;2
"Building";"Refinery";NA;23;0
"Unit";"SCV";"Command Center";23;1
"Unit";"Marine";"Barracks";23;1
"Unit";"Marine";"Barracks";23;1
"Unit";"SCV";"Command Center";26;1
"Building";"FactoryTechLab";NA;26;0
"Building";"Starport";NA;23;0
"Unit";"Marine";"Barracks";27;1
"Unit";"Marine";"Barracks";28;1
"Unit";"SCV";"Command Center";29;1
"Unit";"SCV";"Command Center";30;1
"Unit";"SCV";"Command Center";33;1
"Unit";"SCV";"Command Center";33;1
"Unit";"SCV";"Command Center";35;1
"Unit";"Marine";"Barracks";34;1
"Unit";"Marine";"Barracks";34;1
"Unit";"SCV";"Command Center";36;1
"Unit";"SCV";"Command Center";37;1
"Unit";"Liberator";"Starport";33;3
"Unit";"Marine";"Barracks";37;1
"Unit";"Marine";"Barracks";38;1
"Unit";"SCV";"Command Center";39;1
"Building";"SupplyDepot";NA;44;0
"Building";"SupplyDepot";NA;46;0
"Unit";"SCV";"Command Center";47;1
"Unit";"SCV";"Command Center";47;1
"Unit";"Marine";"Barracks";47;1
"Building";"FactoryReactor";NA;47;0
"Building";"StarportReactor";NA;47;0
"Unit";"SCV";"Command Center";47;1
"Building";"EngineeringBay";NA;47;0
"Building";"Refinery";NA;47;0
"Building";"EngineeringBay";NA;47;0
"Building";"Refinery";NA;49;0
"Building";"Barracks";NA;47;0
"Building";"Barracks";NA;47;0
"Unit";"Marine";"Barracks";50;1
"Unit";"SCV";"Command Center";51;1
"Building";"CommandCenter";NA;40;0
"Unit";"SCV";"Command Center";51;1
"Building";"FactoryTechLab";NA;51;0
"Unit";"SCV";"Command Center";52;1
"Unit";"Marine";"Barracks";51;1
"Unit";"Marine";"Barracks";51;1
"Unit";"Medivac";"Starport";51;2
"Unit";"Medivac";"Starport";51;2
"Unit";"Marine";"Barracks";51;1
"Unit";"SCV";"Command Center";53;1
"Unit";"Marine";"Barracks";53;1
"Unit";"Marine";"Barracks";53;1
"Unit";"SCV";"Command Center";57;1
"Unit";"SCV";"Command Center";62;1
"Unit";"Marine";"Barracks";62;1
"Unit";"SCV";"Command Center";66;1
"Unit";"Marine";"Barracks";65;1
"Unit";"Marine";"Barracks";65;1
"Unit";"Marine";"Barracks";65;1
"Unit";"Marine";"Barracks";65;1
"Unit";"SCV";"Command Center";67;1
"Unit";"SCV";"Command Center";68;1
"Unit";"Marine";"Barracks";67;1
"Unit";"SCV";"Command Center";69;1
"Building";"SupplyDepot";NA;68;0
"Unit";"Marine";"Barracks";73;1
"Unit";"Marine";"Barracks";74;1
"Building";"SupplyDepot";NA;69;0
"Upgrade";"Stimpack";"TechLab";51;0
"Unit";"SCV";"Command Center";77;1
"Unit";"SCV";"Command Center";77;1
"Unit";"Marine";"Barracks";77;1
"Unit";"Marine";"Barracks";77;1
"Unit";"Marine";"Barracks";79;1
"Unit";"Marine";"Barracks";79;1
"Unit";"SCV";"Command Center";85;1
"Unit";"SCV";"Command Center";85;1
"Unit";"Marine";"Barracks";83;1
"Unit";"Marine";"Barracks";83;1
"Unit";"SCV";"Command Center";85;1
"Unit";"Marine";"Barracks";85;1
"Unit";"Marine";"Barracks";85;1
"Unit";"Marine";"Barracks";85;1
"Unit";"SCV";"Command Center";85;1
"Unit";"SCV";"Command Center";86;1
"Unit";"SCV";"Command Center";89;1
"Unit";"Marine";"Barracks";86;1
"Unit";"Marine";"Barracks";88;1
"Upgrade";"TerranInfantryWeaponsLevel1";"EngineeringBay";67;0
"Upgrade";"TerranInfantryArmorsLevel1";"EngineeringBay";68;0
"Unit";"Marine";"Barracks";90;1
"Unit";"Marine";"Barracks";91;1
"Unit";"Marine";"Barracks";94;1
"Unit";"SCV";"Command Center";98;1
"Unit";"SCV";"Command Center";98;1
"Unit";"SCV";"Command Center";98;1
"Unit";"SCV";"Command Center";101;1
"Unit";"SCV";"Command Center";102;1
"Unit";"SCV";"Command Center";103;1
"Unit";"Marine";"Barracks";104;1
"Unit";"Marine";"Barracks";104;1
"Unit";"Marine";"Barracks";104;1
"Unit";"Marine";"Barracks";104;1
"Unit";"Marine";"Barracks";104;1
"Unit";"SCV";"Command Center";104;1
"Unit";"SCV";"Command Center";105;1
"Unit";"SCV";"Command Center";106;1
"Unit";"SCV";"Command Center";112;1
"Unit";"SCV";"Command Center";113;1
"Unit";"Medivac";"Starport";104;2
"Unit";"SCV";"Command Center";115;1
"Building";"MissileTurret";NA;115;0
"Unit";"SCV";"Command Center";115;1
"Unit";"SCV";"Command Center";119;1
"Unit";"SCV";"Command Center";119;1
"Unit";"Marine";"Barracks";119;1
"Unit";"Marine";"Barracks";119;1
"Unit";"Marine";"Barracks";119;1
"Unit";"Marine";"Barracks";119;1
"Unit";"Marine";"Barracks";119;1
"Unit";"SCV";"Command Center";123;1
"Unit";"SCV";"Command Center";123;1
"Unit";"SCV";"Command Center";123;1
"Unit";"Medivac";"Starport";119;2
"Unit";"Medivac";"Starport";119;2
"Building";"Armory";NA;114;0
"Unit";"Marine";"Barracks";123;1
"Unit";"Marine";"Barracks";124;1
"Unit";"Marine";"Barracks";125;1
"Unit";"Marine";"Barracks";128;1
"Unit";"Marine";"Barracks";128;1
"Building";"Barracks";NA;120;0
"Building";"Barracks";NA;120;0
"Unit";"Marine";"Barracks";135;1
"Unit";"Marine";"Barracks";136;1
"Unit";"Marine";"Barracks";139;1
"Unit";"Marine";"Barracks";139;1
"Unit";"Marine";"Barracks";139;1
"Unit";"SCV";"Command Center";143;1
"Unit";"SCV";"Command Center";143;1
"Unit";"Marine";"Barracks";140;1
"Unit";"Marine";"Barracks";141;1
"Unit";"Marine";"Barracks";142;1
"Unit";"Marine";"Barracks";143;1
"Unit";"Marine";"Barracks";144;1
"Unit";"SCV";"Command Center";145;1
"Unit";"Marine";"Barracks";147;1
"Unit";"Marine";"Barracks";148;1
"Unit";"Medivac";"Starport";145;2
"Unit";"Medivac";"Starport";145;2
"Building";"BarracksReactor";NA;145;0
"Building";"BarracksReactor";NA;145;0
"Building";"SupplyDepot";NA;155;0
"Building";"SupplyDepot";NA;155;0
"Building";"SupplyDepot";NA;155;0
"Unit";"SCV";"Command Center";159;1
"Unit";"SCV";"Command Center";159;1
"Unit";"SCV";"Command Center";159;1
"Unit";"Marine";"Barracks";159;1
"Unit";"Marine";"Barracks";159;1
"Unit";"Marine";"Barracks";159;1
"Unit";"Marine";"Barracks";159;1
"Unit";"Marine";"Barracks";159;1
"Unit";"Marine";"Barracks";159;1
"Unit";"Marine";"Barracks";159;1
"Unit";"Marine";"Barracks";159;1
"Unit";"Marine";"Barracks";159;1
"Unit";"SCV";"Command Center";159;1
"Unit";"SCV";"Command Center";159;1
"Building";"SupplyDepot";NA;159;0
"Building";"MissileTurret";NA;159;0
"Unit";"Medivac";"Starport";159;2
"Unit";"Marine";"Barracks";162;1
"Unit";"Marine";"Barracks";162;1
"Unit";"Marine";"Barracks";164;1
"Unit";"Marine";"Barracks";168;1
"Unit";"Medivac";"Starport";159;2
"Unit";"Marine";"Barracks";173;1
"Unit";"Marine";"Barracks";173;1
"Building";"Factory";NA;159;0
"Unit";"Marine";"Barracks";179;1
"Unit";"Marine";"Barracks";179;1
"Unit";"Marine";"Barracks";179;1
"Unit";"SCV";"Command Center";181;1
"Unit";"Marine";"Barracks";187;1
"Unit";"Marine";"Barracks";187;1
"Unit";"Marine";"Barracks";187;1
"Unit";"SCV";"Command Center";187;1
"Unit";"SCV";"Command Center";187;1
"Unit";"SCV";"Command Center";187;1
"Unit";"SCV";"Command Center";191;1
"Building";"BarracksReactor";NA;187;0
"Unit";"Marine";"Barracks";191;1
"Building";"MissileTurret";NA;191;0
"Unit";"Marine";"Barracks";192;1
"Unit";"Marine";"Barracks";192;1
"Unit";"Marine";"Barracks";192;1
"Building";"FactoryTechLab";NA;193;0
"Unit";"Marine";"Barracks";193;1
"Upgrade";"TerranInfantryWeaponsLevel2";"EngineeringBay";162;0
"Upgrade";"TerranInfantryArmorsLevel2";"EngineeringBay";162;0
"Upgrade";"TerranVehicleWeaponsLevel1";"Armory";175;0
"Building";"CommandCenter";NA;183;0
"Unit";"Marine";"Barracks";198;1
"Unit";"Marine";"Barracks";198;1
"Unit";"Marine";"Barracks";198;1
"Unit";"Marine";"Barracks";198;1
"Unit";"Marine";"Barracks";198;1
"Unit";"Marine";"Barracks";198;1
"Building";"BarracksReactor";NA;193;0
"Unit";"Marine";"Barracks";199;1
"Unit";"Marine";"Barracks";199;1
"Unit";"Marine";"Barracks";199;1
"Unit";"Marine";"Barracks";200;1
"Unit";"Marine";"Barracks";201;1
"Unit";"Marine";"Barracks";202;1
"Unit";"Marine";"Barracks";205;1
"Unit";"Marine";"Barracks";205;1
"Unit";"Marine";"Barracks";205;1
"Unit";"Marine";"Barracks";205;1
"Unit";"Marine";"Barracks";212;1
"Unit";"Marine";"Barracks";212;1
"Unit";"Marine";"Barracks";212;1
"Unit";"Marine";"Barracks";212;1
"Unit";"Marine";"Barracks";212;1
"Unit";"Marine";"Barracks";212;1
"Unit";"Marine";"Barracks";215;1
"Unit";"Marine";"Barracks";215;1
"Unit";"Marine";"Barracks";215;1
"Unit";"Marine";"Barracks";215;1
"Unit";"Marine";"Barracks";221;1
"Unit";"Marine";"Barracks";221;1
"Unit";"Marine";"Barracks";221;1
"Unit";"Marine";"Barracks";221;1
"Unit";"Marine";"Barracks";221;1
"Unit";"Marine";"Barracks";221;1
"Unit";"Marine";"Barracks";221;1
"Unit";"Marine";"Barracks";222;1
"Unit";"Marine";"Barracks";223;1
"Unit";"Marine";"Barracks";224;1
