"type";"unit_name";"on_building";"total_supply";"supply"
"Building";"Refinery";NA;14;0
"Building";"Barracks";NA;15;0
"Unit";"Reaper";"Barracks";19;1
"Building";"Factory";NA;19;0
"Building";"Refinery";NA;21;0
"Unit";"Reaper";"Barracks";20;1
"Building";"CommandCenter";NA;19;0
"Unit";"Hellion";"Factory";22;2
"Building";"Starport";NA;24;0
"Building";"BarracksReactor";NA;24;0
"Unit";"Cyclone";"Factory";29;3
"Unit";"Marine";"Barracks";34;1
"Unit";"Marine";"Barracks";34;1
"Building";"FactoryTechLab";NA;34;0
"Unit";"Marine";"Barracks";38;1
"Unit";"Marine";"Barracks";38;1
"Unit";"Liberator";"Starport";34;3
"Unit";"Marine";"Barracks";42;1
"Unit";"Marine";"Barracks";42;1
"Unit";"Medivac";"Starport";47;2
"Building";"EngineeringBay";NA;51;0
"Building";"EngineeringBay";NA;51;0
"Building";"CommandCenter";NA;39;0
"Building";"BarracksTechLab";NA;55;0
"Building";"Refinery";NA;55;0
"Building";"Refinery";NA;55;0
"Building";"StarportReactor";NA;55;0
"Unit";"Marine";"Barracks";58;1
"Unit";"Marine";"Barracks";60;1
"Building";"StarportReactor";NA;60;0
"Unit";"Marine";"Barracks";64;1
"Unit";"Marine";"Barracks";68;1
"Building";"Barracks";NA;55;0
"Unit";"Marine";"Barracks";72;1
"Unit";"Marine";"Barracks";76;1
"Unit";"Marine";"Barracks";76;1
"Unit";"Marine";"Barracks";78;1
"Building";"Barracks";NA;71;0
"Building";"Barracks";NA;71;0
"Building";"Barracks";NA;72;0
"Unit";"Marine";"Barracks";82;1
"Unit";"Marine";"Barracks";83;1
"Unit";"Marine";"Barracks";84;1
"Unit";"Marine";"Barracks";85;1
"Unit";"Marine";"Barracks";86;1
"Building";"SensorTower";NA;90;0
"Unit";"Marine";"Barracks";92;1
"Unit";"Marine";"Barracks";92;1
"Unit";"Marine";"Barracks";92;1
"Unit";"Marine";"Barracks";93;1
"Unit";"Marine";"Barracks";93;1
"Building";"StarportReactor";NA;85;0
"Building";"Armory";NA;82;0
"Unit";"Marine";"Barracks";95;1
"Unit";"Marine";"Barracks";95;1
"Building";"MissileTurret";NA;99;0
"Building";"MissileTurret";NA;99;0
"Building";"BarracksReactor";NA;95;0
"Unit";"Marine";"Barracks";105;1
"Unit";"Marine";"Barracks";105;1
"Upgrade";"TerranInfantryWeaponsLevel1";"EngineeringBay";79;0
"Unit";"Marine";"Barracks";105;1
"Unit";"Marine";"Barracks";105;1
"Unit";"Marine";"Barracks";105;1
"Building";"Factory";NA;95;0
"Unit";"Marine";"Barracks";110;1
"Unit";"Marine";"Barracks";110;1
"Unit";"Marine";"Barracks";110;1
"Building";"MissileTurret";NA;113;0
"Upgrade";"Stimpack";"TechLab";85;0
"Building";"MissileTurret";NA;113;0
"Unit";"Marine";"Barracks";113;1
"Unit";"Marine";"Barracks";113;1
"Unit";"Marine";"Barracks";113;1
"Building";"Refinery";NA;113;0
"Building";"Refinery";NA;113;0
"Unit";"Medivac";"Starport";110;2
"Unit";"Medivac";"Starport";110;2
"Building";"FactoryTechLab";NA;115;0
"Unit";"Marine";"Barracks";118;1
"Unit";"Marine";"Barracks";118;1
"Unit";"Marine";"Barracks";118;1
"Upgrade";"TerranInfantryArmorsLevel1";"EngineeringBay";95;0
"Unit";"Marine";"Barracks";125;1
"Unit";"Marine";"Barracks";125;1
"Unit";"Marine";"Barracks";125;1
"Unit";"Marine";"Barracks";125;1
"Unit";"Medivac";"Starport";121;2
"Unit";"Medivac";"Starport";121;2
"Unit";"Marine";"Barracks";129;1
"Unit";"Marine";"Barracks";129;1
"Unit";"Marine";"Barracks";129;1
"Unit";"Marine";"Barracks";129;1
"Unit";"Marine";"Barracks";136;1
"Unit";"Marine";"Barracks";136;1
"Unit";"Marine";"Barracks";136;1
"Unit";"Marine";"Barracks";145;1
"Unit";"Marine";"Barracks";145;1
"Unit";"Medivac";"Starport";140;2
"Upgrade";"TerranVehicleWeaponsLevel1";"Armory";115;0
"Unit";"Marine";"Barracks";155;1
"Unit";"Marine";"Barracks";155;1
"Unit";"Marine";"Barracks";155;1
"Unit";"Marine";"Barracks";155;1
"Unit";"Marine";"Barracks";155;1
"Unit";"Marine";"Barracks";155;1
"Unit";"Marine";"Barracks";155;1
"Unit";"Marine";"Barracks";164;1
"Unit";"Marine";"Barracks";165;1
"Unit";"Marine";"Barracks";165;1
"Unit";"Marine";"Barracks";165;1
"Unit";"Marine";"Barracks";165;1
"Unit";"Marine";"Barracks";165;1
"Unit";"Marine";"Barracks";165;1
"Unit";"Marine";"Barracks";165;1
"Unit";"Marine";"Barracks";167;1
"Unit";"Marine";"Barracks";168;1
"Unit";"Medivac";"Starport";165;2
"Unit";"Medivac";"Starport";165;2
"Upgrade";"TerranInfantryWeaponsLevel2";"EngineeringBay";145;0
"Unit";"Marine";"Barracks";179;1
"Unit";"Marine";"Barracks";179;1
"Unit";"Marine";"Barracks";179;1
"Unit";"Marine";"Barracks";179;1
"Unit";"Marine";"Barracks";179;1
"Unit";"Marine";"Barracks";179;1
"Unit";"Medivac";"Starport";179;2
"Unit";"Marine";"Barracks";183;1
"Unit";"Marine";"Barracks";187;1
"Unit";"Marine";"Barracks";187;1
"Upgrade";"TerranInfantryArmorsLevel2";"EngineeringBay";164;0
"Unit";"Marine";"Barracks";187;1
"Unit";"Marine";"Barracks";187;1
"Unit";"Medivac";"Starport";187;2
"Unit";"Medivac";"Starport";187;2
"Unit";"Marine";"Barracks";190;1
"Unit";"Marine";"Barracks";190;1
"Unit";"Marine";"Barracks";192;1
"Unit";"Marine";"Barracks";196;1
"Unit";"Marine";"Barracks";196;1
"Unit";"Marine";"Barracks";196;1
"Unit";"Marine";"Barracks";196;1
"Unit";"Marine";"Barracks";196;1
"Unit";"Marine";"Barracks";196;1
"Unit";"Medivac";"Starport";192;2
"Unit";"Medivac";"Starport";192;2
"Building";"CommandCenter";NA;185;0
"Unit";"Marine";"Barracks";209;1
"Unit";"Marine";"Barracks";209;1
"Unit";"Marine";"Barracks";209;1
"Unit";"Marine";"Barracks";209;1
"Unit";"Marine";"Barracks";209;1
"Unit";"Marine";"Barracks";209;1
"Unit";"Marine";"Barracks";209;1
"Unit";"Marine";"Barracks";209;1
"Unit";"Marine";"Barracks";209;1
"Unit";"Marine";"Barracks";209;1
"Unit";"Marine";"Barracks";210;1
"Unit";"Marine";"Barracks";211;1
"Unit";"Medivac";"Starport";209;2
"Unit";"Medivac";"Starport";209;2
"Unit";"Marine";"Barracks";218;1
"Unit";"Marine";"Barracks";218;1
"Unit";"Marine";"Barracks";218;1
"Unit";"Marine";"Barracks";218;1
"Unit";"Marine";"Barracks";225;1
"Unit";"Marine";"Barracks";225;1
"Unit";"Marine";"Barracks";225;1
"Unit";"Marine";"Barracks";225;1
"Unit";"Marine";"Barracks";229;1
"Unit";"Marine";"Barracks";229;1
"Unit";"Liberator";"Starport";221;3
"Building";"Refinery";NA;231;0
"Unit";"Marine";"Barracks";233;1
"Unit";"Marine";"Barracks";233;1
"Unit";"Marine";"Barracks";233;1
"Building";"Refinery";NA;233;0
"Unit";"Marine";"Barracks";233;1
"Unit";"Marine";"Barracks";234;1
"Unit";"Marine";"Barracks";234;1
"Unit";"Marine";"Barracks";235;1
"Unit";"Medivac";"Starport";235;2
"Unit";"Marine";"Barracks";245;1
"Unit";"Marine";"Barracks";245;1
"Unit";"Marine";"Barracks";245;1
"Unit";"Marine";"Barracks";245;1
"Unit";"Marine";"Barracks";245;1
"Unit";"Marine";"Barracks";245;1
"Unit";"Marine";"Barracks";245;1
"Unit";"Marine";"Barracks";245;1
"Unit";"Marine";"Barracks";245;1
"Upgrade";"TerranInfantryWeaponsLevel3";"EngineeringBay";209;0
"Upgrade";"TerranInfantryArmorsLevel3";"EngineeringBay";209;0
"Unit";"Medivac";"Starport";245;2
"Unit";"Medivac";"Starport";245;2
"Unit";"Marine";"Barracks";247;1
"Unit";"Marine";"Barracks";248;1
"Unit";"Marine";"Barracks";249;1
"Unit";"Marine";"Barracks";250;1
"Unit";"Marine";"Barracks";251;1
"Unit";"Marine";"Barracks";252;1
"Unit";"Marine";"Barracks";253;1
"Unit";"Marine";"Barracks";254;1
"Unit";"Marine";"Barracks";256;1
"Unit";"Marine";"Barracks";260;1
"Unit";"Marine";"Barracks";261;1
"Unit";"Marine";"Barracks";268;1
"Unit";"Marine";"Barracks";268;1
"Unit";"Marine";"Barracks";268;1
"Unit";"Marine";"Barracks";269;1
"Unit";"Marine";"Barracks";269;1
"Unit";"Marine";"Barracks";269;1
"Unit";"Marine";"Barracks";269;1
"Unit";"Marine";"Barracks";269;1
"Unit";"Marine";"Barracks";270;1
"Unit";"Marine";"Barracks";280;1
"Unit";"Marine";"Barracks";280;1
"Unit";"Marine";"Barracks";280;1
"Unit";"Marine";"Barracks";280;1
"Unit";"Marine";"Barracks";280;1
"Building";"CommandCenter";NA;260;0
"Building";"Starport";NA;280;0
"Building";"Starport";NA;280;0
"Building";"Starport";NA;280;0
"Building";"Refinery";NA;285;0
"Building";"Refinery";NA;285;0
"Unit";"Marine";"Barracks";285;1
"Unit";"Marine";"Barracks";285;1
"Unit";"Marine";"Barracks";285;1
"Unit";"Marine";"Barracks";285;1
"Unit";"Marine";"Barracks";285;1
"Unit";"Marine";"Barracks";285;1
"Unit";"Marine";"Barracks";285;1
"Unit";"Marine";"Barracks";292;1
"Unit";"Marine";"Barracks";292;1
"Unit";"Marine";"Barracks";292;1
"Unit";"Marine";"Barracks";292;1
"Unit";"Marine";"Barracks";292;1
"Unit";"Marine";"Barracks";292;1
"Unit";"Marine";"Barracks";292;1
"Upgrade";"TerranVehicleWeaponsLevel2";"Armory";280;0
"Unit";"Marine";"Barracks";292;1
"Unit";"Marine";"Barracks";292;1
"Unit";"Marine";"Barracks";296;1
"Unit";"Marine";"Barracks";296;1
"Unit";"Marine";"Barracks";298;1
"Unit";"Marine";"Barracks";298;1
"Unit";"Marine";"Barracks";299;1
"Unit";"Marine";"Barracks";299;1
"Unit";"Marine";"Barracks";299;1
"Unit";"Marine";"Barracks";299;1
"Unit";"Marine";"Barracks";300;1
"Building";"CommandCenter";NA;285;0
"Unit";"Medivac";"Starport";299;2
"Unit";"Marine";"Barracks";307;1
"Unit";"Marine";"Barracks";307;1
"Unit";"Marine";"Barracks";307;1
"Unit";"Marine";"Barracks";307;1
"Unit";"Marine";"Barracks";307;1
"Unit";"Marine";"Barracks";315;1
"Unit";"Marine";"Barracks";315;1
"Unit";"Marine";"Barracks";315;1
"Unit";"Marine";"Barracks";315;1
"Unit";"Medivac";"Starport";310;2
"Unit";"Medivac";"Starport";310;2
"Unit";"Marine";"Barracks";317;1
"Unit";"Marine";"Barracks";317;1
"Building";"StarportTechLab";NA;317;0
"Unit";"Marine";"Barracks";323;1
"Unit";"Marine";"Barracks";323;1
"Unit";"Marine";"Barracks";323;1
"Unit";"Marine";"Barracks";323;1
"Unit";"Marine";"Barracks";323;1
"Unit";"Marine";"Barracks";323;1
"Unit";"Marine";"Barracks";323;1
"Building";"StarportReactor";NA;317;0
"Building";"StarportReactor";NA;317;0
"Unit";"Medivac";"Starport";321;2
"Unit";"Medivac";"Starport";323;2
"Building";"FusionCore";NA;317;0
"Unit";"Marine";"Barracks";340;1
"Unit";"Marine";"Barracks";345;1
"Unit";"Marine";"Barracks";345;1
"Unit";"Marine";"Barracks";345;1
"Unit";"Marine";"Barracks";348;1
"Unit";"Marine";"Barracks";348;1
"Unit";"Marine";"Barracks";348;1
"Unit";"Marine";"Barracks";348;1
"Unit";"Marine";"Barracks";348;1
"Unit";"Marine";"Barracks";348;1
"Unit";"Marine";"Barracks";348;1
"Unit";"Marine";"Barracks";348;1
"Unit";"Marine";"Barracks";348;1
"Unit";"Marine";"Barracks";348;1
"Unit";"Marine";"Barracks";349;1
"Unit";"Liberator";"Starport";348;3
"Building";"Refinery";NA;357;0
"Unit";"Liberator";"Starport";348;3
"Building";"Refinery";NA;357;0
"Unit";"Marine";"Barracks";359;1
"Unit";"Marine";"Barracks";359;1
"Unit";"Marine";"Barracks";359;1
"Unit";"Marine";"Barracks";359;1
"Unit";"Marine";"Barracks";359;1
"Unit";"Marine";"Barracks";359;1
"Unit";"Marine";"Barracks";359;1
"Unit";"Marine";"Barracks";359;1
"Unit";"Marine";"Barracks";359;1
"Building";"CommandCenter";NA;348;0
"Building";"CommandCenter";NA;348;0
"Unit";"Marine";"Barracks";365;1
"Unit";"Marine";"Barracks";366;1
"Unit";"Marine";"Barracks";376;1
"Unit";"Marine";"Barracks";376;1
