"Type";"UnitName";"OnBuilding";"TotalSupply";"Supply"
"Unit";"SCV";"Command Center";12;1
"Unit";"SCV";"Command Center";12;1
"Unit";"SCV";"Command Center";13;1
"Building";"SupplyDepot";NA;13;0
"Building";"Refinery";NA;14;0
"Unit";"SCV";"Command Center";15;1
"Unit";"SCV";"Command Center";15;1
"Building";"Refinery";NA;16;0
"Unit";"SCV";"Command Center";16;1
"Unit";"SCV";"Command Center";17;1
"Building";"Barracks";NA;15;0
"Unit";"Reaper";"Barracks";19;1
"Building";"SupplyDepot";NA;19;0
"Unit";"SCV";"Command Center";19;1
"Building";"Factory";NA;19;0
"Unit";"SCV";"Command Center";21;1
"Unit";"Reaper";"Barracks";19;1
"Unit";"SCV";"Command Center";21;1
"Unit";"Cyclone";"Factory";21;3
"Building";"SupplyDepot";NA;21;0
"Building";"Starport";NA;21;0
"Unit";"SCV";"Command Center";27;1
"Unit";"SCV";"Command Center";28;1
"Unit";"Cyclone";"Factory";27;3
"Unit";"Medivac";"Starport";27;2
"Unit";"SCV";"Command Center";32;1
"Building";"SupplyDepot";NA;32;0
"Building";"BarracksTechLab";NA;34;0
"Unit";"SCV";"Command Center";35;1
"Unit";"Cyclone";"Factory";35;3
"Unit";"Marine";"Barracks";35;1
"Building";"EngineeringBay";NA;36;0
"Building";"CommandCenter";NA;29;0
"Unit";"SCV";"Command Center";40;1
"Unit";"Marine";"Barracks";40;1
"Building";"StarportTechLab";NA;40;0
"Unit";"SCV";"Command Center";42;1
"Unit";"SCV";"Command Center";43;1
"Unit";"SCV";"Command Center";43;1
"Unit";"Marine";"Barracks";42;1
"Building";"FactoryReactor";NA;42;0
"Building";"Barracks";NA;40;0
"Unit";"SCV";"Command Center";43;1
"Building";"Barracks";NA;40;0
"Building";"SupplyDepot";NA;43;0
"Unit";"SCV";"Command Center";46;1
"Unit";"Raven";"Starport";42;2
"Unit";"Marine";"Barracks";46;1
"Unit";"SCV";"Command Center";46;1
"Unit";"SCV";"Command Center";48;1
"Unit";"SCV";"Command Center";51;1
"Unit";"Marine";"Barracks";50;1
"Unit";"Marine";"Barracks";50;1
"Unit";"Marine";"Barracks";52;1
"Building";"Refinery";NA;52;0
"Unit";"SCV";"Command Center";54;1
"Unit";"SCV";"Command Center";54;1
"Building";"BarracksReactor";NA;50;0
"Unit";"Marine";"Barracks";54;1
"Unit";"SCV";"Command Center";57;1
"Unit";"SCV";"Command Center";58;1
"Building";"StarportReactor";NA;52;0
"Unit";"Marine";"Barracks";59;1
"Unit";"Marine";"Barracks";59;1
"Unit";"SCV";"Command Center";60;1
"Unit";"SCV";"Command Center";61;1
"Building";"SupplyDepot";NA;54;0
"Building";"MissileTurret";NA;60;0
"Upgrade";"Stimpack";"TechLab";43;0
"Unit";"Marine";"Barracks";60;1
"Building";"SupplyDepot";NA;60;0
"Building";"MissileTurret";NA;62;0
"Unit";"Marine";"Barracks";62;1
"Unit";"SCV";"Command Center";64;1
"Unit";"SCV";"Command Center";65;1
"Unit";"Marine";"Barracks";64;1
"Unit";"Marine";"Barracks";64;1
"Unit";"Marine";"Barracks";65;1
"Unit";"SCV";"Command Center";69;1
"Unit";"SCV";"Command Center";73;1
"Unit";"Medivac";"Starport";67;2
"Unit";"Medivac";"Starport";67;2
"Building";"SupplyDepot";NA;73;0
"Unit";"Marine";"Barracks";73;1
"Unit";"Marine";"Barracks";74;1
"Unit";"Marine";"Barracks";74;1
"Building";"Refinery";NA;73;0
"Unit";"SCV";"Command Center";75;1
"Unit";"Marine";"Barracks";74;1
"Unit";"Marine";"Barracks";74;1
"Unit";"SCV";"Command Center";77;1
"Unit";"Marine";"Barracks";79;1
"Unit";"Marine";"Barracks";81;1
"Unit";"Marine";"Barracks";81;1
"Unit";"SCV";"Command Center";86;1
"Unit";"SCV";"Command Center";86;1
"Building";"SupplyDepot";NA;86;0
"Unit";"SCV";"Command Center";89;1
"Unit";"Marine";"Barracks";87;1
"Unit";"Marine";"Barracks";90;1
"Unit";"Marine";"Barracks";91;1
"Unit";"Marine";"Barracks";91;1
"Upgrade";"TerranInfantryWeaponsLevel1";"EngineeringBay";73;0
"Unit";"Marine";"Barracks";96;1
"Unit";"Marine";"Barracks";96;1
"Unit";"SCV";"Command Center";96;1
"Unit";"Marine";"Barracks";96;1
"Unit";"Marine";"Barracks";96;1
"Unit";"SCV";"Command Center";96;1
"Unit";"SCV";"Command Center";98;1
"Building";"CommandCenter";NA;86;0
"Unit";"Medivac";"Starport";96;2
"Unit";"Medivac";"Starport";96;2
"Unit";"SCV";"Command Center";101;1
"Unit";"Marine";"Barracks";98;1
"Unit";"Marine";"Barracks";98;1
"Unit";"Marine";"Barracks";98;1
"Unit";"SCV";"Command Center";102;1
"Unit";"SCV";"Command Center";107;1
"Unit";"Marine";"Barracks";107;1
"Unit";"Marine";"Barracks";107;1
"Building";"MissileTurret";NA;111;0
"Building";"Barracks";NA;96;0
"Building";"Barracks";NA;96;0
"Unit";"SCV";"Command Center";112;1
"Unit";"SCV";"Command Center";116;1
"Unit";"SCV";"Command Center";116;1
"Unit";"SCV";"Command Center";116;1
"Unit";"Marine";"Barracks";116;1
"Unit";"Marine";"Barracks";116;1
"Unit";"Marine";"Barracks";116;1
"Unit";"Marine";"Barracks";116;1
"Building";"Factory";NA;112;0
"Building";"SensorTower";NA;116;0
"Building";"Armory";NA;113;0
"Unit";"SCV";"Command Center";116;1
"Unit";"SCV";"Command Center";117;1
"Unit";"Marine";"Barracks";116;1
"Building";"Refinery";NA;116;0
"Unit";"SCV";"Command Center";119;1
"Building";"BarracksReactor";NA;116;0
"Building";"BarracksReactor";NA;116;0
"Unit";"SCV";"Command Center";123;1
"Building";"FactoryTechLab";NA;123;0
"Unit";"Marine";"Barracks";123;1
"Unit";"Marine";"Barracks";126;1
"Unit";"Marine";"Barracks";126;1
"Unit";"Marine";"Barracks";127;1
"Unit";"Liberator";"Starport";116;3
"Unit";"Marine";"Barracks";129;1
"Unit";"Liberator";"Starport";119;3
"Unit";"Marine";"Barracks";135;1
"Unit";"Marine";"Barracks";136;1
"Building";"SensorTower";NA;139;0
"Upgrade";"TerranInfantryArmorsLevel1";"EngineeringBay";116;0
"Unit";"Marine";"Barracks";140;1
"Unit";"Marine";"Barracks";140;1
"Unit";"Marine";"Barracks";140;1
"Unit";"Marine";"Barracks";141;1
"Building";"EngineeringBay";NA;140;0
"Unit";"Marine";"Barracks";141;1
"Building";"SupplyDepot";NA;145;0
"Building";"CommandCenter";NA;131;0
"Building";"SupplyDepot";NA;146;0
"Unit";"Marine";"Barracks";146;1
"Unit";"Marine";"Barracks";146;1
"Unit";"Marine";"Barracks";146;1
"Unit";"Marine";"Barracks";146;1
"Unit";"Marine";"Barracks";146;1
"Unit";"Marine";"Barracks";146;1
"Building";"Refinery";NA;146;0
"Unit";"Marine";"Barracks";146;1
"Unit";"Marine";"Barracks";146;1
"Unit";"Marine";"Barracks";146;1
"Unit";"Marine";"Barracks";146;1
"Unit";"Marine";"Barracks";146;1
"Unit";"Marine";"Barracks";146;1
"Unit";"Marine";"Barracks";146;1
"Unit";"Marine";"Barracks";150;1
"Unit";"Marine";"Barracks";153;1
"Unit";"Marine";"Barracks";155;1
"Unit";"Marine";"Barracks";155;1
"Unit";"Marine";"Barracks";155;1
"Unit";"SCV";"Command Center";161;1
"Unit";"Marine";"Barracks";155;1
"Unit";"Liberator";"Starport";150;3
"Unit";"Liberator";"Starport";152;3
"Building";"SupplyDepot";NA;161;0
"Building";"Refinery";NA;161;0
"Building";"Refinery";NA;161;0
"Upgrade";"TerranVehicleWeaponsLevel1";"Armory";146;0
"Building";"Barracks";NA;155;0
"Building";"Barracks";NA;155;0
"Unit";"Marine";"Barracks";166;1
"Building";"Barracks";NA;155;0
"Unit";"Marine";"Barracks";172;1
"Unit";"Marine";"Barracks";172;1
"Unit";"Marine";"Barracks";172;1
"Unit";"Marine";"Barracks";172;1
"Unit";"Marine";"Barracks";172;1
"Unit";"Marine";"Barracks";172;1
"Unit";"Marine";"Barracks";172;1
"Unit";"Marine";"Barracks";172;1
"Unit";"Marine";"Barracks";172;1
"Unit";"Marine";"Barracks";173;1
"Unit";"Marine";"Barracks";174;1
"Unit";"Marine";"Barracks";175;1
"Unit";"Marine";"Barracks";175;1
"Unit";"Marine";"Barracks";177;1
"Unit";"Marine";"Barracks";177;1
"Unit";"Marine";"Barracks";179;1
"Unit";"Marine";"Barracks";179;1
"Unit";"Marine";"Barracks";181;1
"Upgrade";"TerranInfantryWeaponsLevel2";"EngineeringBay";146;0
"Unit";"Marine";"Barracks";190;1
"Unit";"Marine";"Barracks";190;1
"Unit";"Marine";"Barracks";190;1
"Unit";"Marine";"Barracks";190;1
"Unit";"Marine";"Barracks";191;1
"Unit";"Marine";"Barracks";191;1
"Unit";"Marine";"Barracks";191;1
"Unit";"Marine";"Barracks";191;1
"Unit";"Marine";"Barracks";191;1
"Unit";"Medivac";"Starport";190;2
"Unit";"Medivac";"Starport";190;2
"Unit";"Marine";"Barracks";191;1
"Unit";"Marine";"Barracks";192;1
"Unit";"Marine";"Barracks";193;1
"Unit";"Marine";"Barracks";193;1
"Unit";"SCV";"Command Center";195;1
"Unit";"SCV";"Command Center";195;1
"Unit";"SCV";"Command Center";195;1
"Unit";"SCV";"Command Center";208;1
"Unit";"SCV";"Command Center";209;1
"Unit";"Marine";"Barracks";195;1
"Unit";"Marine";"Barracks";196;1
"Unit";"Marine";"Barracks";196;1
"Unit";"Marine";"Barracks";198;1
"Upgrade";"TerranInfantryArmorsLevel2";"EngineeringBay";172;0
"Unit";"Marine";"Barracks";211;1
"Unit";"Marine";"Barracks";211;1
"Unit";"Marine";"Barracks";217;1
"Unit";"Marine";"Barracks";217;1
"Unit";"Medivac";"Starport";211;2
"Unit";"Marine";"Barracks";219;1
"Unit";"Marine";"Barracks";219;1
"Unit";"Marine";"Barracks";219;1
"Unit";"Marine";"Barracks";219;1
"Unit";"Marine";"Barracks";221;1
"Unit";"Marine";"Barracks";221;1
"Unit";"Marine";"Barracks";221;1
"Unit";"Marine";"Barracks";221;1
"Unit";"Marine";"Barracks";221;1
"Unit";"Marine";"Barracks";221;1
"Unit";"Marine";"Barracks";221;1
"Unit";"Marine";"Barracks";227;1
"Unit";"Marine";"Barracks";227;1
"Unit";"Marine";"Barracks";227;1
"Building";"SupplyDepot";NA;227;0
