"type";"unit_name";"on_building";"total_supply";"supply"
"Building";"Refinery";NA;14;0
"Building";"Refinery";NA;16;0
"Building";"Barracks";NA;15;0
"Unit";"Reaper";"Barracks";19;1
"Building";"Factory";NA;19;0
"Unit";"Reaper";"Barracks";19;1
"Unit";"Hellion";"Factory";21;2
"Unit";"Cyclone";"Factory";26;3
"Building";"BarracksReactor";NA;26;0
"Building";"CommandCenter";NA;22;0
"Building";"Starport";NA;27;0
"Unit";"Marine";"Barracks";31;1
"Unit";"Marine";"Barracks";31;1
"Unit";"Cyclone";"Factory";32;3
"Unit";"Marine";"Barracks";36;1
"Unit";"Marine";"Barracks";36;1
"Building";"FactoryTechLab";NA;40;0
"Unit";"Marine";"Barracks";44;1
"Unit";"Marine";"Barracks";44;1
"Unit";"Liberator";"Starport";36;3
"Building";"BarracksTechLab";NA;53;0
"Building";"StarportReactor";NA;52;0
"Unit";"Marine";"Barracks";55;1
"Building";"Barracks";NA;52;0
"Building";"Barracks";NA;53;0
"Building";"Refinery";NA;57;0
"Building";"Refinery";NA;57;0
"Unit";"Marine";"Barracks";58;1
"Unit";"Marine";"Barracks";62;1
"Unit";"Marine";"Barracks";62;1
"Unit";"Marine";"Barracks";63;1
"Unit";"Marine";"Barracks";63;1
"Unit";"Marine";"Barracks";63;1
"Building";"StarportReactor";NA;60;0
"Unit";"Marine";"Barracks";65;1
"Unit";"Marine";"Barracks";66;1
"Unit";"Marine";"Barracks";69;1
"Building";"EngineeringBay";NA;69;0
"Unit";"Medivac";"Starport";72;2
"Unit";"Marine";"Barracks";77;1
"Unit";"Marine";"Barracks";77;1
"Unit";"Marine";"Barracks";77;1
"Unit";"Marine";"Barracks";77;1
"Unit";"Marine";"Barracks";77;1
"Unit";"Medivac";"Starport";77;2
"Unit";"Marine";"Barracks";80;1
"Upgrade";"Stimpack";"TechLab";63;0
"Unit";"Marine";"Barracks";86;1
"Unit";"Marine";"Barracks";86;1
"Unit";"Marine";"Barracks";89;1
"Unit";"Marine";"Barracks";89;1
"Unit";"Marine";"Barracks";89;1
"Building";"MissileTurret";NA;92;0
"Unit";"Marine";"Barracks";96;1
"Unit";"Marine";"Barracks";96;1
"Unit";"Marine";"Barracks";96;1
"Unit";"Marine";"Barracks";96;1
"Unit";"Marine";"Barracks";96;1
"Unit";"Marine";"Barracks";96;1
"Unit";"Marine";"Barracks";97;1
"Unit";"Marine";"Barracks";100;1
"Unit";"Marine";"Barracks";100;1
