"type";"unit_name";"on_building";"total_supply";"supply"
"Building";"Refinery";NA;15;0
"Building";"Barracks";NA;15;0
"Unit";"Reaper";"Barracks";19;1
"Building";"Refinery";NA;20;0
"Building";"BarracksReactor";NA;21;0
"Building";"CommandCenter";NA;20;0
"Unit";"Marine";"Barracks";23;1
"Unit";"Marine";"Barracks";23;1
"Building";"Factory";NA;22;0
"Unit";"Marine";"Barracks";27;1
"Unit";"Marine";"Barracks";27;1
"Building";"FactoryTechLab";NA;28;0
"Unit";"Marine";"Barracks";29;1
"Unit";"Marine";"Barracks";30;1
"Building";"Starport";NA;28;0
"Unit";"Marine";"Barracks";34;1
"Unit";"Marine";"Barracks";34;1
"Unit";"Marine";"Barracks";40;1
"Unit";"Marine";"Barracks";40;1
"Unit";"Liberator";"Starport";40;3
"Unit";"Marine";"Barracks";46;1
"Unit";"Marine";"Barracks";46;1
"Building";"Refinery";NA;55;0
"Building";"Refinery";NA;55;0
"Unit";"Liberator";"Starport";51;3
"Building";"FactoryReactor";NA;55;0
"Building";"EngineeringBay";NA;55;0
"Building";"EngineeringBay";NA;55;0
"Building";"Barracks";NA;55;0
"Building";"Barracks";NA;55;0
"Building";"Barracks";NA;55;0
"Building";"Barracks";NA;55;0
"Building";"CommandCenter";NA;51;0
"Building";"StarportReactor";NA;60;0
"Building";"FactoryTechLab";NA;64;0
"Building";"BarracksTechLab";NA;64;0
"Unit";"Marine";"Barracks";65;1
"Unit";"Marine";"Barracks";65;1
"Unit";"Marine";"Barracks";65;1
"Unit";"Marine";"Barracks";65;1
"Building";"BarracksReactor";NA;64;0
"Unit";"Medivac";"Starport";65;2
"Unit";"Medivac";"Starport";65;2
"Unit";"Marine";"Barracks";72;1
"Unit";"Marine";"Barracks";72;1
"Unit";"Marine";"Barracks";72;1
"Unit";"Marine";"Barracks";72;1
"Unit";"Marine";"Barracks";72;1
"Unit";"Marine";"Barracks";72;1
"Unit";"Marine";"Barracks";72;1
"Unit";"Marauder";"Barracks";72;2
"Building";"MissileTurret";NA;76;0
"Unit";"Marine";"Barracks";76;1
"Unit";"Marine";"Barracks";77;1
"Unit";"Marine";"Barracks";78;1
"Unit";"Medivac";"Starport";76;2
"Unit";"Medivac";"Starport";76;2
"Upgrade";"Stimpack";"TechLab";63;0
"Unit";"Marine";"Barracks";85;1
"Unit";"Marauder";"Barracks";82;2
"Unit";"Marine";"Barracks";85;1
"Unit";"Marine";"Barracks";85;1
"Unit";"Marauder";"Barracks";85;2
"Unit";"Marine";"Barracks";85;1
"Unit";"Marine";"Barracks";86;1
"Building";"Armory";NA;83;0
"Unit";"Medivac";"Starport";95;2
"Unit";"Marine";"Barracks";103;1
"Unit";"Medivac";"Starport";95;2
"Upgrade";"TerranInfantryWeaponsLevel1";"EngineeringBay";72;0
"Upgrade";"TerranInfantryArmorsLevel1";"EngineeringBay";72;0
"Unit";"Marine";"Barracks";112;1
"Unit";"Marine";"Barracks";112;1
"Unit";"Marine";"Barracks";112;1
"Unit";"Marine";"Barracks";112;1
"Unit";"Marine";"Barracks";112;1
"Unit";"Marine";"Barracks";112;1
"Unit";"Marauder";"Barracks";112;2
"Unit";"Marauder";"Barracks";112;2
"Unit";"Medivac";"Starport";112;2
"Unit";"Medivac";"Starport";112;2
"Unit";"Marine";"Barracks";121;1
"Unit";"Marine";"Barracks";121;1
"Unit";"Marine";"Barracks";121;1
"Unit";"Marauder";"Barracks";121;2
"Unit";"Marine";"Barracks";129;1
"Unit";"Marine";"Barracks";129;1
"Unit";"Marine";"Barracks";129;1
"Unit";"Marine";"Barracks";129;1
"Unit";"Marauder";"Barracks";129;2
"Unit";"Marine";"Barracks";134;1
"Unit";"Marine";"Barracks";134;1
"Unit";"Marauder";"Barracks";134;2
"Building";"Barracks";NA;125;0
"Building";"Barracks";NA;125;0
"Building";"Barracks";NA;129;0
"Unit";"Marauder";"Barracks";140;2
"Unit";"Marine";"Barracks";146;1
"Unit";"Marine";"Barracks";146;1
"Unit";"Marine";"Barracks";146;1
"Unit";"Marine";"Barracks";146;1
"Unit";"Marine";"Barracks";146;1
"Unit";"Marauder";"Barracks";146;2
"Building";"CommandCenter";NA;125;0
"Unit";"Marauder";"Barracks";146;2
"Unit";"Medivac";"Starport";146;2
"Unit";"Medivac";"Starport";146;2
"Building";"BarracksTechLab";NA;156;0
"Building";"BarracksTechLab";NA;156;0
"Building";"BarracksTechLab";NA;156;0
"Unit";"Marine";"Barracks";162;1
"Unit";"Marine";"Barracks";163;1
"Unit";"Marine";"Barracks";163;1
"Unit";"Marine";"Barracks";164;1
"Unit";"Marauder";"Barracks";162;2
"Unit";"Marauder";"Barracks";162;2
"Unit";"Marine";"Barracks";164;1
"Unit";"Marine";"Barracks";164;1
"Unit";"Marine";"Barracks";164;1
"Unit";"Marine";"Barracks";165;1
"Unit";"Marine";"Barracks";165;1
"Unit";"Marine";"Barracks";165;1
"Unit";"Marine";"Barracks";166;1
"Unit";"Marauder";"Barracks";165;2
"Unit";"Marauder";"Barracks";167;2
"Unit";"Marauder";"Barracks";174;2
"Upgrade";"TerranInfantryWeaponsLevel2";"EngineeringBay";140;0
"Upgrade";"TerranInfantryArmorsLevel2";"EngineeringBay";140;0
"Unit";"Marine";"Barracks";183;1
"Unit";"Marine";"Barracks";183;1
"Unit";"Marine";"Barracks";183;1
"Unit";"Marine";"Barracks";183;1
"Unit";"Marine";"Barracks";183;1
"Unit";"Marine";"Barracks";183;1
"Unit";"Marine";"Barracks";183;1
"Unit";"Marine";"Barracks";183;1
"Unit";"Marauder";"Barracks";183;2
"Unit";"Marauder";"Barracks";183;2
"Unit";"Marine";"Barracks";183;1
"Unit";"Medivac";"Starport";183;2
"Unit";"Medivac";"Starport";183;2
"Unit";"Marine";"Barracks";185;1
"Unit";"Marine";"Barracks";203;1
"Unit";"Marine";"Barracks";203;1
"Unit";"Marine";"Barracks";203;1
"Unit";"Marine";"Barracks";203;1
"Unit";"Marine";"Barracks";203;1
"Unit";"Marine";"Barracks";203;1
"Unit";"Marauder";"Barracks";203;2
"Unit";"Marauder";"Barracks";203;2
"Unit";"Marauder";"Barracks";203;2
"Unit";"Marauder";"Barracks";203;2
"Unit";"Marine";"Barracks";203;1
"Unit";"Marine";"Barracks";204;1
"Unit";"Marine";"Barracks";205;1
"Unit";"Marine";"Barracks";206;1
"Unit";"Marine";"Barracks";207;1
"Unit";"Marine";"Barracks";208;1
"Unit";"Marauder";"Barracks";203;2
"Unit";"Marine";"Barracks";209;1
"Unit";"Marine";"Barracks";219;1
"Unit";"Marine";"Barracks";219;1
"Unit";"Marauder";"Barracks";219;2
"Unit";"Marine";"Barracks";220;1
"Unit";"Marine";"Barracks";221;1
"Unit";"Marauder";"Barracks";226;2
"Unit";"Marauder";"Barracks";229;2
"Building";"MissileTurret";NA;232;0
"Unit";"Marine";"Barracks";232;1
"Unit";"Marine";"Barracks";232;1
"Unit";"Marine";"Barracks";232;1
"Unit";"Marine";"Barracks";232;1
"Unit";"Marine";"Barracks";232;1
"Unit";"Marauder";"Barracks";232;2
"Unit";"Marauder";"Barracks";232;2
"Unit";"Marine";"Barracks";234;1
"Unit";"Marine";"Barracks";235;1
"Building";"Refinery";NA;234;0
"Building";"Refinery";NA;234;0
"Unit";"Marine";"Barracks";236;1
"Building";"Refinery";NA;236;0
"Building";"Refinery";NA;236;0
"Unit";"Marine";"Barracks";248;1
"Unit";"Marine";"Barracks";248;1
"Unit";"Marine";"Barracks";248;1
"Unit";"Marine";"Barracks";248;1
"Unit";"Marine";"Barracks";248;1
"Unit";"Marine";"Barracks";248;1
"Unit";"Marine";"Barracks";248;1
"Unit";"Marine";"Barracks";250;1
"Unit";"Marine";"Barracks";252;1
"Unit";"Marauder";"Barracks";269;2
"Unit";"Marine";"Barracks";269;1
"Unit";"Marine";"Barracks";272;1
"Unit";"Marine";"Barracks";272;1
"Unit";"Marine";"Barracks";272;1
"Unit";"Marine";"Barracks";272;1
"Unit";"Marine";"Barracks";272;1
"Unit";"Marine";"Barracks";272;1
"Unit";"Marauder";"Barracks";272;2
"Upgrade";"TerranInfantryWeaponsLevel3";"EngineeringBay";238;0
