"type";"unit_name";"on_building";"total_supply_lag";"supply"
"Building";"Refinery";NA;15;0
"Building";"Barracks";NA;16;0
"Building";"Refinery";NA;17;0
"Building";"BarracksTechLab";NA;19;0
"Building";"GhostAcademy";NA;19;0
"Building";"Factory";NA;19;0
"Unit";"Ghost";"Barracks";20;2
"Unit";"Ghost";"Barracks";24;2
"Unit";"Cyclone";"Factory";27;3
