"Type";"UnitName";"OnBuilding";"TotalSupply";"Supply"
"Unit";"SCV";"Command Center";12;1
"Unit";"SCV";"Command Center";12;1
"Unit";"SCV";"Command Center";13;1
"Building";"SupplyDepot";NA;13;0
"Unit";"SCV";"Command Center";15;1
"Unit";"SCV";"Command Center";16;1
"Building";"Refinery";NA;15;0
"Unit";"SCV";"Command Center";16;1
"Unit";"SCV";"Command Center";17;1
"Building";"Barracks";NA;15;0
"Unit";"Reaper";"Barracks";19;1
"Unit";"SCV";"Command Center";20;1
"Building";"Refinery";NA;19;0
"Building";"SupplyDepot";NA;19;0
"Unit";"Reaper";"Barracks";19;1
"Building";"CommandCenter";NA;19;0
"Unit";"SCV";"Command Center";22;1
"Building";"Factory";NA;21;0
"Unit";"SCV";"Command Center";22;1
"Unit";"SCV";"Command Center";23;1
"Unit";"SCV";"Command Center";24;1
"Building";"Bunker";NA;23;0
"Building";"Barracks";NA;22;0
"Unit";"Cyclone";"Factory";24;3
"Building";"Barracks";NA;22;0
"Unit";"SCV";"Command Center";26;1
"Unit";"SCV";"Command Center";26;1
"Unit";"SCV";"Command Center";30;1
"Building";"BarracksTechLab";NA;29;0
"Unit";"Marine";"Barracks";29;1
"Unit";"SCV";"Command Center";30;1
"Unit";"SCV";"Command Center";31;1
"Unit";"Cyclone";"Factory";30;3
"Unit";"SCV";"Command Center";33;1
"Unit";"Marine";"Barracks";33;1
"Unit";"Marine";"Barracks";33;1
"Building";"SupplyDepot";NA;32;0
"Unit";"SCV";"Command Center";34;1
"Unit";"SCV";"Command Center";38;1
"Unit";"SCV";"Command Center";41;1
"Building";"EngineeringBay";NA;35;0
"Unit";"Marine";"Barracks";39;1
"Unit";"Marine";"Barracks";39;1
"Unit";"Marine";"Barracks";40;1
"Unit";"SCV";"Command Center";42;1
"Building";"SupplyDepot";NA;42;0
"Building";"SupplyDepot";NA;42;0
"Unit";"SCV";"Command Center";43;1
"Unit";"SCV";"Command Center";47;1
"Building";"BarracksTechLab";NA;47;0
"Unit";"SCV";"Command Center";48;1
"Unit";"Marine";"Barracks";48;1
"Unit";"SCV";"Command Center";49;1
"Building";"Starport";NA;44;0
"Unit";"SCV";"Command Center";50;1
"Building";"FactoryReactor";NA;44;0
"Building";"BarracksReactor";NA;47;0
"Unit";"SCV";"Command Center";52;1
"Unit";"Marine";"Barracks";53;1
"Unit";"Marine";"Barracks";53;1
"Unit";"SCV";"Command Center";53;1
"Unit";"SCV";"Command Center";54;1
"Unit";"SCV";"Command Center";57;1
"Unit";"Marine";"Barracks";55;1
"Unit";"Marine";"Barracks";55;1
"Unit";"SCV";"Command Center";58;1
"Unit";"Marine";"Barracks";56;1
"Unit";"Marauder";"Barracks";55;2
"Building";"SupplyDepot";NA;58;0
"Unit";"SCV";"Command Center";59;1
"Unit";"Medivac";"Starport";55;2
"Unit";"Medivac";"Starport";55;2
"Unit";"Marine";"Barracks";60;1
"Unit";"SCV";"Command Center";66;1
"Unit";"SCV";"Command Center";66;1
"Building";"Refinery";NA;64;0
"Upgrade";"Stimpack";"TechLab";45;0
"Building";"Refinery";NA;64;0
"Unit";"Marine";"Barracks";66;1
"Unit";"Marine";"Barracks";66;1
"Building";"Barracks";NA;55;0
"Building";"Barracks";NA;55;0
"Unit";"Marauder";"Barracks";66;2
"Building";"FactoryReactor";NA;59;0
"Building";"SupplyDepot";NA;71;0
"Unit";"Marine";"Barracks";71;1
"Building";"SupplyDepot";NA;71;0
"Unit";"SCV";"Command Center";78;1
"Unit";"SCV";"Command Center";78;1
"Unit";"Marine";"Barracks";74;1
"Building";"BarracksTechLab";NA;78;0
"Unit";"Marauder";"Barracks";78;2
"Unit";"SCV";"Command Center";79;1
"Upgrade";"TerranInfantryWeaponsLevel1";"EngineeringBay";55;0
"Unit";"Marine";"Barracks";79;1
"Unit";"Marine";"Barracks";79;1
"Unit";"Medivac";"Starport";78;2
"Unit";"Marine";"Barracks";81;1
"Building";"BarracksReactor";NA;78;0
"Unit";"Marine";"Barracks";84;1
"Unit";"SCV";"Command Center";85;1
"Unit";"SCV";"Command Center";85;1
"Unit";"Marauder";"Barracks";82;2
"Unit";"Marine";"Barracks";85;1
"Unit";"Marauder";"Barracks";86;2
"Unit";"Marine";"Barracks";90;1
"Building";"SupplyDepot";NA;90;0
"Unit";"Medivac";"Starport";85;2
"Building";"SupplyDepot";NA;90;0
"Building";"SupplyDepot";NA;95;0
"Unit";"SCV";"Command Center";101;1
"Unit";"SCV";"Command Center";101;1
"Unit";"Marine";"Barracks";99;1
"Unit";"Marauder";"Barracks";99;2
"Building";"BarracksTechLab";NA;101;0
"Building";"BarracksTechLab";NA;101;0
"Unit";"Marine";"Barracks";103;1
"Unit";"Marine";"Barracks";103;1
"Unit";"Marauder";"Barracks";104;2
"Unit";"Marine";"Barracks";106;1
"Unit";"Marine";"Barracks";106;1
"Unit";"Marine";"Barracks";106;1
"Unit";"Medivac";"Starport";104;2
"Unit";"Medivac";"Starport";104;2
"Unit";"Marauder";"Barracks";106;2
"Unit";"Marine";"Barracks";106;1
"Building";"SupplyDepot";NA;106;0
"Building";"SupplyDepot";NA;108;0
"Unit";"Marine";"Barracks";108;1
"Unit";"Marine";"Barracks";108;1
"Unit";"Marine";"Barracks";110;1
"Unit";"Marine";"Barracks";111;1
"Unit";"Marine";"Barracks";112;1
"Building";"SupplyDepot";NA;117;0
"Unit";"Marine";"Barracks";120;1
"Unit";"Marine";"Barracks";120;1
"Unit";"Medivac";"Starport";113;2
"Unit";"Marauder";"Barracks";121;2
"Unit";"Marine";"Barracks";125;1
"Unit";"Medivac";"Starport";120;2
"Unit";"Marine";"Barracks";125;1
"Unit";"Marine";"Barracks";125;1
"Unit";"Marauder";"Barracks";125;2
"Unit";"Marine";"Barracks";127;1
"Unit";"Marauder";"Barracks";125;2
"Upgrade";"TerranInfantryArmorsLevel1";"EngineeringBay";104;0
"Unit";"Marine";"Barracks";131;1
"Unit";"Marine";"Barracks";134;1
"Unit";"Marauder";"Barracks";129;2
"Building";"CommandCenter";NA;107;0
"Unit";"Marine";"Barracks";135;1
"Unit";"Marauder";"Barracks";136;2
"Unit";"Marine";"Barracks";138;1
