"Type";"UnitName";"OnBuilding";"TotalSupply";"Supply"
"Unit";"SCV";"Command Center";12;1
"Unit";"SCV";"Command Center";12;1
"Unit";"SCV";"Command Center";13;1
"Building";"SupplyDepot";NA;13;0
"Unit";"SCV";"Command Center";15;1
"Unit";"SCV";"Command Center";15;1
"Unit";"SCV";"Command Center";16;1
"Building";"Barracks";NA;15;0
"Unit";"SCV";"Command Center";18;1
"Unit";"Marine";"Barracks";18;1
"Building";"SupplyDepot";NA;19;0
"Unit";"Marine";"Barracks";19;1
"Unit";"SCV";"Command Center";20;1
"Unit";"Marine";"Barracks";20;1
"Unit";"SCV";"Command Center";22;1
"Building";"CommandCenter";NA;17;0
"Unit";"SCV";"Command Center";23;1
"Unit";"Marine";"Barracks";22;1
"Unit";"SCV";"Command Center";25;1
"Unit";"Marine";"Barracks";25;1
"Unit";"SCV";"Command Center";27;1
"Unit";"SCV";"Command Center";27;1
"Unit";"Marine";"Barracks";27;1
"Unit";"SCV";"Command Center";28;1
"Unit";"SCV";"Command Center";30;1
"Building";"Refinery";NA;28;0
"Building";"Refinery";NA;28;0
"Building";"CommandCenter";NA;22;0
"Unit";"SCV";"Command Center";31;1
"Unit";"SCV";"Command Center";32;1
"Unit";"Marine";"Barracks";30;1
"Building";"Barracks";NA;27;0
"Building";"Barracks";NA;27;0
"Unit";"SCV";"Command Center";33;1
"Unit";"SCV";"Command Center";34;1
"Unit";"Marine";"Barracks";35;1
"Unit";"Marine";"Barracks";36;1
"Unit";"SCV";"Command Center";36;1
"Building";"BarracksTechLab";NA;36;0
"Unit";"SCV";"Command Center";37;1
"Unit";"SCV";"Command Center";39;1
"Unit";"SCV";"Command Center";40;1
"Unit";"SCV";"Command Center";41;1
"Unit";"Marine";"Barracks";38;1
"Unit";"Marine";"Barracks";40;1
"Unit";"Marine";"Barracks";42;1
"Building";"Refinery";NA;39;0
"Unit";"SCV";"Command Center";42;1
"Unit";"SCV";"Command Center";43;1
"Unit";"SCV";"Command Center";47;1
"Unit";"SCV";"Command Center";48;1
"Building";"SupplyDepot";NA;46;0
"Unit";"SCV";"Command Center";49;1
"Building";"EngineeringBay";NA;45;0
"Unit";"SCV";"Command Center";50;1
"Unit";"SCV";"Command Center";51;1
"Unit";"SCV";"Command Center";52;1
"Unit";"SCV";"Command Center";53;1
"Unit";"Marauder";"Barracks";51;2
"Building";"Factory";NA;46;0
"Building";"SupplyDepot";NA;53;0
"Building";"MissileTurret";NA;54;0
"Unit";"SCV";"Command Center";56;1
"Building";"BarracksReactor";NA;50;0
"Unit";"SCV";"Command Center";56;1
"Building";"BarracksReactor";NA;51;0
"Unit";"SCV";"Command Center";59;1
"Unit";"Marauder";"Barracks";57;2
"Unit";"SCV";"Command Center";60;1
"Building";"SupplyDepot";NA;59;0
"Unit";"SCV";"Command Center";61;1
"Unit";"Marine";"Barracks";61;1
"Unit";"Marine";"Barracks";61;1
"Building";"Refinery";NA;60;0
"Unit";"SCV";"Command Center";61;1
"Unit";"SCV";"Command Center";64;1
"Unit";"Marine";"Barracks";64;1
"Unit";"SCV";"Command Center";65;1
"Unit";"Marine";"Barracks";64;1
"Building";"Starport";NA;59;0
"Building";"FactoryReactor";NA;59;0
"Unit";"Marauder";"Barracks";62;2
"Unit";"SCV";"Command Center";68;1
"Unit";"Marine";"Barracks";66;1
"Unit";"SCV";"Command Center";69;1
"Building";"SupplyDepot";NA;68;0
"Unit";"SCV";"Command Center";73;1
"Unit";"SCV";"Command Center";75;1
"Unit";"SCV";"Command Center";77;1
"Unit";"SCV";"Command Center";79;1
"Upgrade";"Stimpack";"TechLab";52;0
"Unit";"Marauder";"Barracks";76;2
"Unit";"SCV";"Command Center";79;1
"Unit";"SCV";"Command Center";80;1
"Building";"SupplyDepot";NA;78;0
"Unit";"Medivac";"Starport";78;2
"Unit";"Medivac";"Starport";78;2
"Unit";"Marine";"Barracks";81;1
"Unit";"Marine";"Barracks";81;1
"Unit";"Marine";"Barracks";81;1
"Unit";"Marine";"Barracks";81;1
"Unit";"SCV";"Command Center";86;1
"Unit";"SCV";"Command Center";86;1
"Unit";"SCV";"Command Center";86;1
"Building";"SupplyDepot";NA;81;0
"Building";"Barracks";NA;73;0
"Building";"SupplyDepot";NA;81;0
"Building";"Barracks";NA;73;0
"Building";"Barracks";NA;73;0
"Unit";"Marauder";"Barracks";86;2
"Unit";"SCV";"Command Center";94;1
"Unit";"SCV";"Command Center";95;1
"Building";"BarracksTechLab";NA;97;0
"Building";"BarracksTechLab";NA;97;0
"Building";"SupplyDepot";NA;97;0
"Unit";"Medivac";"Starport";97;2
"Unit";"Medivac";"Starport";97;2
"Unit";"Marine";"Barracks";101;1
"Unit";"Marine";"Barracks";101;1
"Unit";"Marine";"Barracks";101;1
"Unit";"Marine";"Barracks";101;1
"Unit";"Marauder";"Barracks";101;2
"Unit";"SCV";"Command Center";101;1
"Unit";"SCV";"Command Center";101;1
"Unit";"SCV";"Command Center";101;1
"Building";"BarracksReactor";NA;97;0
"Building";"Barracks";NA;90;0
"Upgrade";"TerranInfantryWeaponsLevel1";"EngineeringBay";78;0
"Building";"Barracks";NA;92;0
"Unit";"SCV";"Command Center";111;1
"Unit";"SCV";"Command Center";112;1
"Unit";"SCV";"Command Center";113;1
"Unit";"Marauder";"Barracks";105;2
"Unit";"Marauder";"Barracks";105;2
"Unit";"SCV";"Command Center";114;1
"Unit";"SCV";"Command Center";115;1
"Unit";"SCV";"Command Center";116;1
"Unit";"Marauder";"Barracks";114;2
"Building";"SupplyDepot";NA;114;0
"Unit";"Marauder";"Barracks";117;2
"Unit";"Marine";"Barracks";121;1
"Unit";"Marine";"Barracks";121;1
"Unit";"Marine";"Barracks";121;1
"Unit";"Marauder";"Barracks";121;2
"Building";"BarracksReactor";NA;114;0
"Building";"BarracksReactor";NA;114;0
"Building";"CommandCenter";NA;101;0
"Unit";"Marauder";"Barracks";124;2
"Unit";"Marine";"Barracks";128;1
"Unit";"Marine";"Barracks";129;1
"Unit";"Marine";"Barracks";130;1
"Unit";"Marine";"Barracks";131;1
"Unit";"Marauder";"Barracks";128;2
"Unit";"Marauder";"Barracks";131;2
"Unit";"SCV";"Command Center";135;1
"Unit";"SCV";"Command Center";136;1
"Unit";"Marine";"Barracks";135;1
"Unit";"Marine";"Barracks";135;1
"Unit";"SCV";"Command Center";137;1
"Unit";"Marine";"Barracks";135;1
"Unit";"Marine";"Barracks";135;1
"Unit";"Marine";"Barracks";135;1
"Unit";"Marauder";"Barracks";133;2
"Unit";"Medivac";"Starport";133;2
"Unit";"Medivac";"Starport";133;2
"Unit";"Marine";"Barracks";141;1
"Unit";"Marine";"Barracks";141;1
"Unit";"Marine";"Barracks";141;1
"Unit";"Marine";"Barracks";141;1
"Unit";"Marine";"Barracks";141;1
"Unit";"SCV";"Command Center";143;1
"Unit";"SCV";"Command Center";144;1
"Unit";"SCV";"Command Center";147;1
"Unit";"Marauder";"Barracks";139;2
"Unit";"Marauder";"Barracks";141;2
"Building";"MissileTurret";NA;148;0
"Building";"MissileTurret";NA;151;0
"Unit";"SCV";"Command Center";162;1
"Unit";"Marauder";"Barracks";151;2
"Unit";"Marine";"Barracks";157;1
"Unit";"Marine";"Barracks";157;1
"Unit";"Marine";"Barracks";157;1
"Unit";"Marine";"Barracks";157;1
"Unit";"Marauder";"Barracks";167;2
"Building";"SupplyDepot";NA;167;0
"Unit";"Marine";"Barracks";169;1
"Unit";"Marine";"Barracks";169;1
"Unit";"Marauder";"Barracks";167;2
"Unit";"Marauder";"Barracks";170;2
"Unit";"Marine";"Barracks";176;1
"Upgrade";"TerranInfantryArmorsLevel1";"EngineeringBay";128;0
"Unit";"Marine";"Barracks";178;1
"Unit";"Marine";"Barracks";178;1
"Unit";"Marine";"Barracks";178;1
"Unit";"Marine";"Barracks";178;1
"Unit";"Marine";"Barracks";178;1
"Unit";"Marine";"Barracks";178;1
"Unit";"Marine";"Barracks";178;1
"Building";"SupplyDepot";NA;179;0
"Building";"SupplyDepot";NA;182;0
"Building";"EngineeringBay";NA;178;0
"Building";"MissileTurret";NA;182;0
"Unit";"Marine";"Barracks";182;1
"Building";"MissileTurret";NA;185;0
"Building";"SupplyDepot";NA;185;0
"Unit";"Marine";"Barracks";192;1
"Unit";"Marine";"Barracks";192;1
"Unit";"Marine";"Barracks";192;1
"Unit";"Marine";"Barracks";192;1
"Unit";"Marine";"Barracks";192;1
"Unit";"Marine";"Barracks";192;1
"Unit";"Marine";"Barracks";192;1
"Unit";"Marine";"Barracks";192;1
"Unit";"Marine";"Barracks";192;1
"Unit";"Marine";"Barracks";192;1
"Unit";"Marauder";"Barracks";192;2
"Unit";"Marauder";"Barracks";192;2
"Building";"Armory";NA;176;0
"Unit";"Marine";"Barracks";193;1
"Unit";"Medivac";"Starport";192;2
"Unit";"Marine";"Barracks";193;1
"Unit";"Marine";"Barracks";193;1
"Unit";"Marine";"Barracks";193;1
"Unit";"Marauder";"Barracks";197;2
"Unit";"Medivac";"Starport";193;2
"Unit";"Marauder";"Barracks";203;2
"Unit";"Marauder";"Barracks";207;2
"Unit";"Marine";"Barracks";207;1
"Unit";"Marine";"Barracks";207;1
"Unit";"Marine";"Barracks";207;1
"Unit";"Marine";"Barracks";207;1
"Unit";"Marine";"Barracks";207;1
"Unit";"Marine";"Barracks";207;1
"Unit";"Marine";"Barracks";210;1
"Unit";"Marine";"Barracks";210;1
"Unit";"Marine";"Barracks";210;1
"Unit";"Marine";"Barracks";210;1
"Unit";"Marauder";"Barracks";213;2
"Unit";"Marine";"Barracks";227;1
"Unit";"Marine";"Barracks";227;1
"Unit";"Marine";"Barracks";227;1
"Unit";"Marine";"Barracks";227;1
"Unit";"Marine";"Barracks";227;1
"Unit";"Marine";"Barracks";227;1
"Unit";"Marauder";"Barracks";217;2
"Unit";"Marauder";"Barracks";219;2
"Unit";"Marine";"Barracks";231;1
"Unit";"Marine";"Barracks";231;1
"Unit";"Marine";"Barracks";231;1
"Unit";"Marine";"Barracks";231;1
"Unit";"Medivac";"Starport";227;2
"Unit";"Medivac";"Starport";227;2
"Unit";"Marauder";"Barracks";231;2
"Unit";"Marauder";"Barracks";239;2
"Unit";"Marauder";"Barracks";241;2
"Building";"SupplyDepot";NA;243;0
"Unit";"Marine";"Barracks";245;1
"Unit";"Marine";"Barracks";245;1
"Unit";"Marine";"Barracks";245;1
"Unit";"Marine";"Barracks";246;1
"Unit";"Marine";"Barracks";247;1
"Unit";"Marine";"Barracks";247;1
"Unit";"Marine";"Barracks";247;1
"Unit";"Marine";"Barracks";247;1
"Unit";"Marauder";"Barracks";251;2
"Unit";"Medivac";"Starport";247;2
"Unit";"Marauder";"Barracks";257;2
"Unit";"Marauder";"Barracks";257;2
"Unit";"Medivac";"Starport";253;2
"Building";"Barracks";NA;243;0
"Unit";"Marine";"Barracks";265;1
"Unit";"Marine";"Barracks";265;1
"Unit";"Marine";"Barracks";265;1
"Unit";"Marine";"Barracks";265;1
"Unit";"Marine";"Barracks";265;1
"Building";"CommandCenter";NA;227;0
"Building";"Starport";NA;257;0
"Building";"FactoryReactor";NA;257;0
"Unit";"Marauder";"Barracks";265;2
"Unit";"Marauder";"Barracks";280;2
"Unit";"Marine";"Barracks";282;1
"Unit";"Marine";"Barracks";282;1
"Unit";"Marine";"Barracks";282;1
"Unit";"Marine";"Barracks";282;1
"Unit";"Marauder";"Barracks";282;2
"Unit";"Marauder";"Barracks";282;2
"Unit";"Marine";"Barracks";282;1
"Unit";"Marine";"Barracks";282;1
"Unit";"Marine";"Barracks";282;1
"Unit";"Marine";"Barracks";282;1
"Unit";"Marine";"Barracks";282;1
"Building";"BarracksTechLab";NA;282;0
"Unit";"Marauder";"Barracks";282;2
"Unit";"Marine";"Barracks";288;1
"Unit";"Marine";"Barracks";288;1
"Unit";"Marine";"Barracks";288;1
"Unit";"Marine";"Barracks";288;1
"Unit";"Marine";"Barracks";288;1
"Unit";"Marauder";"Barracks";288;2
"Unit";"Marauder";"Barracks";290;2
"Unit";"SCV";"Command Center";297;1
"Unit";"Marine";"Barracks";292;1
"Unit";"SCV";"Command Center";297;1
"Unit";"SCV";"Command Center";297;1
"Unit";"Medivac";"Starport";292;2
"Unit";"Medivac";"Starport";292;2
"Unit";"Marauder";"Barracks";297;2
"Unit";"SCV";"Command Center";308;1
"Unit";"SCV";"Command Center";310;1
"Unit";"SCV";"Command Center";311;1
"Unit";"Marine";"Barracks";304;1
"Unit";"Marine";"Barracks";304;1
"Unit";"Marine";"Barracks";304;1
"Unit";"Marine";"Barracks";304;1
"Unit";"Marine";"Barracks";304;1
"Unit";"Marine";"Barracks";304;1
"Unit";"Marine";"Barracks";304;1
"Unit";"Marine";"Barracks";304;1
"Unit";"Marine";"Barracks";304;1
"Unit";"Marauder";"Barracks";304;2
"Unit";"Medivac";"Starport";297;2
"Unit";"Medivac";"Starport";297;2
"Unit";"Marauder";"Barracks";304;2
"Unit";"Marauder";"Barracks";306;2
"Unit";"SCV";"Command Center";318;1
"Unit";"SCV";"Command Center";319;1
"Upgrade";"TerranInfantryWeaponsLevel2";"EngineeringBay";265;0
"Upgrade";"TerranInfantryArmorsLevel2";"EngineeringBay";265;0
"Building";"MissileTurret";NA;316;0
"Unit";"Marine";"Barracks";322;1
"Unit";"Marine";"Barracks";323;1
"Unit";"Marine";"Barracks";325;1
"Unit";"Marine";"Barracks";327;1
"Unit";"Marine";"Barracks";327;1
"Unit";"Marauder";"Barracks";316;2
"Unit";"Marauder";"Barracks";330;2
"Unit";"Medivac";"Starport";312;2
"Unit";"Marauder";"Barracks";336;2
"Building";"CommandCenter";NA;284;0
"Unit";"Medivac";"Starport";332;2
"Unit";"Marine";"Barracks";342;1
"Unit";"Marine";"Barracks";342;1
"Unit";"Marine";"Barracks";342;1
"Unit";"Marauder";"Barracks";342;2
"Building";"Refinery";NA;349;0
"Building";"Refinery";NA;349;0
"Unit";"Marine";"Barracks";362;1
"Unit";"Marine";"Barracks";362;1
"Unit";"Marine";"Barracks";362;1
"Unit";"Marine";"Barracks";362;1
"Unit";"Marine";"Barracks";362;1
"Unit";"Marine";"Barracks";362;1
"Unit";"Marine";"Barracks";362;1
"Unit";"Marine";"Barracks";362;1
"Unit";"Marine";"Barracks";362;1
"Unit";"Marine";"Barracks";362;1
"Unit";"Marine";"Barracks";362;1
"Unit";"Marauder";"Barracks";362;2
"Unit";"Marauder";"Barracks";362;2
"Unit";"Marauder";"Barracks";362;2
"Unit";"Marine";"Barracks";362;1
"Unit";"Marine";"Barracks";363;1
"Unit";"Marine";"Barracks";364;1
"Unit";"Marine";"Barracks";364;1
"Unit";"Marine";"Barracks";366;1
"Unit";"Marine";"Barracks";367;1
"Unit";"Marauder";"Barracks";372;2
"Unit";"Marauder";"Barracks";373;2
"Unit";"Marauder";"Barracks";375;2
"Unit";"Medivac";"Starport";362;2
"Unit";"Medivac";"Starport";362;2
"Unit";"Marine";"Barracks";379;1
"Unit";"Marine";"Barracks";379;1
"Unit";"Marauder";"Barracks";379;2
"Unit";"Marauder";"Barracks";385;2
"Unit";"Marauder";"Barracks";391;2
"Unit";"Marauder";"Barracks";391;2
"Unit";"Marine";"Barracks";397;1
"Unit";"Marine";"Barracks";397;1
"Unit";"Marine";"Barracks";397;1
"Unit";"Marine";"Barracks";397;1
"Unit";"Marine";"Barracks";397;1
"Unit";"Marine";"Barracks";397;1
"Unit";"Marine";"Barracks";399;1
"Unit";"SCV";"Command Center";399;1
"Unit";"SCV";"Command Center";399;1
"Unit";"SCV";"Command Center";399;1
"Unit";"SCV";"Command Center";399;1
"Unit";"Marine";"Barracks";399;1
"Unit";"Marine";"Barracks";399;1
"Unit";"Marine";"Barracks";399;1
"Unit";"Marauder";"Barracks";397;2
"Unit";"Marauder";"Barracks";399;2
