"type";"unit_name";"on_building";"total_supply";"supply"
"Building";"Refinery";NA;15;0
"Building";"Barracks";NA;15;0
"Unit";"Reaper";"Barracks";19;1
"Building";"CommandCenter";NA;19;0
"Building";"BarracksReactor";NA;21;0
"Building";"Bunker";NA;22;0
"Building";"Refinery";NA;23;0
"Unit";"Marine";"Barracks";24;1
"Unit";"Marine";"Barracks";24;1
"Building";"Factory";NA;23;0
"Unit";"Marine";"Barracks";28;1
"Unit";"Marine";"Barracks";28;1
"Unit";"Marine";"Barracks";32;1
"Unit";"Marine";"Barracks";33;1
"Building";"Starport";NA;28;0
"Unit";"Marine";"Barracks";38;1
"Unit";"Marine";"Barracks";39;1
"Building";"FactoryTechLab";NA;39;0
"Unit";"Medivac";"Starport";38;2
"Unit";"Marine";"Barracks";41;1
"Unit";"Marine";"Barracks";42;1
"Unit";"Marine";"Barracks";50;1
"Unit";"Marine";"Barracks";50;1
"Unit";"Liberator";"Starport";46;3
"Building";"BarracksTechLab";NA;57;0
"Building";"CommandCenter";NA;42;0
"Building";"Refinery";NA;59;0
"Building";"EngineeringBay";NA;59;0
"Building";"StarportReactor";NA;59;0
"Building";"Barracks";NA;54;0
"Unit";"Marauder";"Barracks";63;2
"Building";"Barracks";NA;59;0
"Building";"Barracks";NA;59;0
"Building";"Barracks";NA;59;0
"Building";"MissileTurret";NA;64;0
"Building";"Refinery";NA;64;0
"Building";"MissileTurret";NA;69;0
"Building";"BarracksTechLab";NA;69;0
"Unit";"Marine";"Barracks";69;1
"Unit";"Marine";"Barracks";70;1
"Unit";"Marine";"Barracks";70;1
"Unit";"Marine";"Barracks";70;1
"Building";"MissileTurret";NA;70;0
"Unit";"Marine";"Barracks";70;1
"Building";"StarportReactor";NA;69;0
"Building";"BarracksReactor";NA;69;0
"Unit";"Marine";"Barracks";71;1
"Unit";"Marine";"Barracks";74;1
"Unit";"Marine";"Barracks";74;1
"Unit";"Marine";"Barracks";74;1
"Unit";"Marine";"Barracks";74;1
"Unit";"Marine";"Barracks";78;1
"Unit";"Marine";"Barracks";78;1
"Unit";"Marine";"Barracks";78;1
"Unit";"Marine";"Barracks";80;1
"Unit";"Marine";"Barracks";83;1
"Unit";"Marine";"Barracks";83;1
"Unit";"Marine";"Barracks";83;1
"Unit";"Marine";"Barracks";87;1
"Unit";"Marine";"Barracks";87;1
"Unit";"Marine";"Barracks";87;1
"Unit";"Marine";"Barracks";87;1
"Unit";"Marine";"Barracks";87;1
"Unit";"Medivac";"Starport";86;2
"Unit";"Medivac";"Starport";86;2
"Unit";"Marine";"Barracks";90;1
"Unit";"Marine";"Barracks";90;1
"Unit";"Marine";"Barracks";100;1
"Unit";"Marine";"Barracks";100;1
"Upgrade";"Stimpack";"TechLab";72;0
"Unit";"Marine";"Barracks";100;1
"Unit";"Marine";"Barracks";100;1
"Unit";"Marine";"Barracks";100;1
"Unit";"Medivac";"Starport";100;2
"Unit";"Medivac";"Starport";100;2
"Upgrade";"TerranInfantryWeaponsLevel1";"EngineeringBay";83;0
"Unit";"Marine";"Barracks";107;1
"Unit";"Marine";"Barracks";107;1
"Unit";"Marine";"Barracks";107;1
"Unit";"Marauder";"Barracks";107;2
