"Type";"UnitName";"OnBuilding";"TotalSupply";"Supply"
"Unit";"SCV";"Command Center";12;1
"Unit";"SCV";"Command Center";12;1
"Unit";"SCV";"Command Center";13;1
"Building";"SupplyDepot";NA;13;0
"Building";"Refinery";NA;14;0
"Unit";"SCV";"Command Center";15;1
"Unit";"SCV";"Command Center";15;1
"Unit";"SCV";"Command Center";16;1
"Unit";"SCV";"Command Center";17;1
"Building";"Barracks";NA;15;0
"Unit";"Reaper";"Barracks";19;1
"Unit";"SCV";"Command Center";19;1
"Unit";"SCV";"Command Center";21;1
"Building";"Factory";NA;19;0
"Building";"SupplyDepot";NA;21;0
"Unit";"SCV";"Command Center";21;1
"Building";"BarracksReactor";NA;21;0
"Unit";"SCV";"Command Center";22;1
"Building";"CommandCenter";NA;19;0
"Unit";"SCV";"Command Center";23;1
"Unit";"Marine";"Barracks";23;1
"Building";"Refinery";NA;23;0
"Unit";"Marine";"Barracks";23;1
"Building";"SupplyDepot";NA;23;0
"Unit";"SCV";"Command Center";24;1
"Building";"Bunker";NA;24;0
"Unit";"SCV";"Command Center";27;1
"Unit";"Marine";"Barracks";28;1
"Unit";"Marine";"Barracks";28;1
"Unit";"SCV";"Command Center";28;1
"Unit";"SCV";"Command Center";29;1
"Unit";"SCV";"Command Center";31;1
"Unit";"Marine";"Barracks";29;1
"Unit";"Marine";"Barracks";30;1
"Unit";"SCV";"Command Center";32;1
"Building";"EngineeringBay";NA;29;0
"Unit";"SCV";"Command Center";33;1
"Unit";"Marine";"Barracks";34;1
"Unit";"Marine";"Barracks";35;1
"Unit";"SCV";"Command Center";38;1
"Unit";"SCV";"Command Center";38;1
"Building";"FactoryTechLab";NA;38;0
"Unit";"Marine";"Barracks";38;1
"Unit";"Marine";"Barracks";39;1
"Building";"MissileTurret";NA;40;0
"Unit";"SCV";"Command Center";40;1
"Building";"Starport";NA;37;0
"Unit";"SCV";"Command Center";42;1
"Building";"SupplyDepot";NA;41;0
"Building";"Barracks";NA;37;0
"Unit";"SCV";"Command Center";44;1
"Building";"Barracks";NA;37;0
"Building";"SupplyDepot";NA;42;0
"Unit";"SCV";"Command Center";45;1
"Unit";"SCV";"Command Center";46;1
"Unit";"Marine";"Barracks";46;1
"Unit";"Marine";"Barracks";46;1
"Unit";"SCV";"Command Center";47;1
"Building";"BarracksTechLab";NA;47;0
"Building";"FactoryReactor";NA;45;0
"Unit";"SCV";"Command Center";49;1
"Building";"StarportReactor";NA;46;0
"Unit";"SCV";"Command Center";52;1
"Unit";"Marine";"Barracks";51;1
"Unit";"Marine";"Barracks";51;1
"Unit";"SCV";"Command Center";52;1
"Unit";"Marauder";"Barracks";52;2
"Unit";"Marauder";"Barracks";52;2
"Unit";"Marine";"Barracks";54;1
"Unit";"Marine";"Barracks";57;1
"Unit";"Marine";"Barracks";57;1
"Unit";"SCV";"Command Center";62;1
"Unit";"Marauder";"Barracks";61;2
"Unit";"Marine";"Barracks";62;1
"Building";"SupplyDepot";NA;62;0
"Unit";"Marine";"Barracks";62;1
"Building";"SupplyDepot";NA;62;0
"Unit";"Medivac";"Starport";61;2
"Unit";"Medivac";"Starport";61;2
"Unit";"Marine";"Barracks";63;1
"Unit";"SCV";"Command Center";68;1
"Unit";"SCV";"Command Center";68;1
"Building";"SupplyDepot";NA;67;0
"Building";"SupplyDepot";NA;67;0
"Unit";"Marine";"Barracks";68;1
"Unit";"Marine";"Barracks";68;1
"Unit";"Marine";"Barracks";68;1
"Building";"SupplyDepot";NA;68;0
"Unit";"Marine";"Barracks";74;1
"Unit";"Marine";"Barracks";76;1
"Unit";"SCV";"Command Center";80;1
"Unit";"Marauder";"Barracks";79;2
"Unit";"Marine";"Barracks";79;1
"Building";"Refinery";NA;80;0
"Building";"Refinery";NA;80;0
"Unit";"SCV";"Command Center";82;1
"Unit";"Marauder";"Barracks";80;2
"Unit";"SCV";"Command Center";85;1
"Building";"Barracks";NA;76;0
"Building";"SupplyDepot";NA;82;0
"Building";"Barracks";NA;76;0
"Upgrade";"Stimpack";"TechLab";62;0
"Unit";"SCV";"Command Center";88;1
"Unit";"Marine";"Barracks";86;1
"Building";"BarracksTechLab";NA;89;0
"Unit";"Marine";"Barracks";90;1
"Unit";"SCV";"Command Center";91;1
"Unit";"Marauder";"Barracks";90;2
"Unit";"Marine";"Barracks";91;1
"Unit";"Marine";"Barracks";91;1
"Building";"BarracksReactor";NA;89;0
"Unit";"Marauder";"Barracks";91;2
"Unit";"Marine";"Barracks";91;1
"Unit";"Marine";"Barracks";95;1
"Unit";"Marauder";"Barracks";93;2
"Unit";"Marauder";"Barracks";96;2
"Upgrade";"TerranInfantryWeaponsLevel1";"EngineeringBay";80;0
"Unit";"SCV";"Command Center";100;1
"Unit";"Marine";"Barracks";97;1
"Unit";"Marauder";"Barracks";97;2
"Building";"CommandCenter";NA;86;0
"Building";"SupplyDepot";NA;100;0
"Building";"SupplyDepot";NA;100;0
"Unit";"Marine";"Barracks";103;1
"Building";"Starport";NA;97;0
"Unit";"Liberator";"Starport";95;3
"Unit";"Liberator";"Starport";95;3
"Unit";"Marine";"Barracks";109;1
"Unit";"Marauder";"Barracks";109;2
"Unit";"Marauder";"Barracks";109;2
"Unit";"Marine";"Barracks";116;1
"Unit";"Marine";"Barracks";116;1
"Unit";"Marine";"Barracks";116;1
"Unit";"Marauder";"Barracks";116;2
"Unit";"Marine";"Barracks";121;1
"Unit";"Marauder";"Barracks";117;2
"Unit";"Marine";"Barracks";127;1
"Unit";"Marine";"Barracks";127;1
"Unit";"Marauder";"Barracks";127;2
"Unit";"Marauder";"Barracks";127;2
"Unit";"Marine";"Barracks";129;1
"Unit";"Marine";"Barracks";129;1
"Unit";"Liberator";"Starport";121;3
"Unit";"Marauder";"Barracks";129;2
"Unit";"Marine";"Barracks";131;1
"Unit";"Marine";"Barracks";135;1
"Unit";"Marauder";"Barracks";131;2
"Unit";"Liberator";"Starport";129;3
"Unit";"Liberator";"Starport";129;3
"Unit";"SCV";"Command Center";152;1
"Unit";"SCV";"Command Center";152;1
"Unit";"SCV";"Command Center";152;1
"Unit";"SCV";"Command Center";153;1
"Unit";"Liberator";"Starport";137;3
"Unit";"SCV";"Command Center";154;1
"Unit";"Liberator";"Starport";146;3
"Unit";"Liberator";"Starport";149;3
"Unit";"SCV";"Command Center";159;1
"Unit";"Marine";"Barracks";156;1
"Unit";"Marine";"Barracks";156;1
"Unit";"Marine";"Barracks";156;1
"Unit";"Marine";"Barracks";156;1
"Unit";"SCV";"Command Center";159;1
"Unit";"Marine";"Barracks";159;1
"Unit";"Marine";"Barracks";159;1
"Unit";"SCV";"Command Center";166;1
"Unit";"SCV";"Command Center";171;1
"Unit";"Marine";"Barracks";171;1
"Unit";"Marine";"Barracks";171;1
"Unit";"Marine";"Barracks";171;1
"Unit";"SCV";"Command Center";174;1
"Unit";"SCV";"Command Center";174;1
"Unit";"SCV";"Command Center";176;1
"Unit";"Medivac";"Starport";171;2
"Unit";"SCV";"Command Center";181;1
"Unit";"SCV";"Command Center";181;1
"Unit";"SCV";"Command Center";182;1
"Unit";"SCV";"Command Center";185;1
"Unit";"Marauder";"Barracks";182;2
"Unit";"Marauder";"Barracks";182;2
"Unit";"SCV";"Command Center";186;1
"Unit";"Marauder";"Barracks";182;2
"Unit";"SCV";"Command Center";187;1
"Unit";"Marine";"Barracks";187;1
"Unit";"Medivac";"Starport";184;2
"Unit";"SCV";"Command Center";195;1
"Unit";"SCV";"Command Center";195;1
"Unit";"Marine";"Barracks";195;1
"Unit";"SCV";"Command Center";201;1
"Unit";"SCV";"Command Center";201;1
"Unit";"Medivac";"Starport";187;2
"Unit";"Marine";"Barracks";201;1
"Unit";"Marauder";"Barracks";201;2
"Unit";"Marauder";"Barracks";201;2
"Unit";"SCV";"Command Center";204;1
"Unit";"SCV";"Command Center";206;1
"Unit";"SCV";"Command Center";206;1
"Unit";"Marine";"Barracks";202;1
"Unit";"Marine";"Barracks";202;1
"Unit";"Marauder";"Barracks";202;2
"Unit";"Marine";"Barracks";206;1
"Unit";"SCV";"Command Center";211;1
"Unit";"SCV";"Command Center";212;1
"Unit";"SCV";"Command Center";218;1
"Unit";"Marine";"Barracks";216;1
"Unit";"SCV";"Command Center";220;1
"Unit";"Marauder";"Barracks";216;2
"Unit";"Marauder";"Barracks";218;2
"Unit";"Marine";"Barracks";221;1
"Unit";"Liberator";"Starport";207;3
"Unit";"SCV";"Command Center";229;1
"Unit";"Marine";"Barracks";228;1
"Unit";"Marine";"Barracks";228;1
"Unit";"SCV";"Command Center";232;1
"Unit";"Marauder";"Barracks";228;2
"Unit";"Marauder";"Barracks";228;2
"Unit";"Marine";"Barracks";232;1
"Unit";"Marauder";"Barracks";232;2
"Unit";"Marine";"Barracks";240;1
"Unit";"Marine";"Barracks";240;1
"Unit";"Marine";"Barracks";240;1
"Unit";"Marauder";"Barracks";236;2
"Unit";"Marauder";"Barracks";240;2
"Unit";"Liberator";"Starport";229;3
"Unit";"Liberator";"Starport";229;3
"Unit";"Marine";"Barracks";241;1
"Unit";"SCV";"Command Center";243;1
"Unit";"Marauder";"Barracks";241;2
"Unit";"SCV";"Command Center";246;1
"Unit";"Marine";"Barracks";243;1
"Unit";"Marauder";"Barracks";246;2
"Building";"Refinery";NA;250;0
"Unit";"Marine";"Barracks";256;1
"Unit";"Marine";"Barracks";256;1
"Building";"Refinery";NA;256;0
"Unit";"SCV";"Command Center";261;1
"Unit";"SCV";"Command Center";261;1
"Unit";"SCV";"Command Center";261;1
"Unit";"Marine";"Barracks";258;1
"Unit";"Marauder";"Barracks";258;2
"Unit";"Liberator";"Starport";243;3
"Unit";"Marauder";"Barracks";275;2
"Unit";"Marine";"Barracks";277;1
"Unit";"Marine";"Barracks";277;1
"Unit";"Marauder";"Barracks";277;2
"Unit";"Marauder";"Barracks";277;2
"Unit";"Marine";"Barracks";277;1
"Unit";"Marine";"Barracks";277;1
"Unit";"SCV";"Command Center";277;1
"Unit";"Marauder";"Barracks";277;2
"Unit";"SCV";"Command Center";283;1
"Unit";"SCV";"Command Center";283;1
"Unit";"Marine";"Barracks";277;1
"Unit";"Marine";"Barracks";278;1
"Unit";"Medivac";"Starport";277;2
"Unit";"Medivac";"Starport";277;2
"Unit";"Medivac";"Starport";277;2
"Unit";"Medivac";"Starport";277;2
"Unit";"Marine";"Barracks";281;1
"Unit";"Marine";"Barracks";283;1
"Unit";"Marine";"Barracks";284;1
"Unit";"SCV";"Command Center";288;1
"Unit";"Marauder";"Barracks";279;2
"Unit";"Marine";"Barracks";286;1
"Unit";"SCV";"Command Center";288;1
"Unit";"SCV";"Command Center";292;1
"Unit";"Marine";"Barracks";290;1
"Unit";"Marine";"Barracks";291;1
"Building";"EngineeringBay";NA;288;0
"Unit";"Marine";"Barracks";300;1
"Unit";"Marine";"Barracks";301;1
"Unit";"Marine";"Barracks";302;1
"Unit";"Marine";"Barracks";304;1
"Unit";"Marine";"Barracks";306;1
