"Type";"UnitName";"OnBuilding";"TotalSupply";"Supply"
"Unit";"SCV";"Command Center";12;1
"Unit";"SCV";"Command Center";12;1
"Unit";"SCV";"Command Center";13;1
"Building";"SupplyDepot";NA;13;0
"Unit";"SCV";"Command Center";15;1
"Building";"Refinery";NA;14;0
"Unit";"SCV";"Command Center";16;1
"Unit";"SCV";"Command Center";16;1
"Unit";"SCV";"Command Center";17;1
"Building";"Barracks";NA;15;0
"Unit";"Reaper";"Barracks";19;1
"Unit";"SCV";"Command Center";19;1
"Unit";"SCV";"Command Center";21;1
"Building";"Refinery";NA;21;0
"Unit";"SCV";"Command Center";21;1
"Building";"SupplyDepot";NA;21;0
"Building";"Factory";NA;19;0
"Building";"BarracksReactor";NA;20;0
"Unit";"SCV";"Command Center";22;1
"Unit";"SCV";"Command Center";23;1
"Unit";"Marine";"Barracks";23;1
"Unit";"Marine";"Barracks";23;1
"Building";"CommandCenter";NA;19;0
"Unit";"SCV";"Command Center";24;1
"Unit";"Cyclone";"Factory";24;3
"Unit";"SCV";"Command Center";27;1
"Unit";"Marine";"Barracks";27;1
"Unit";"Marine";"Barracks";27;1
"Unit";"SCV";"Command Center";31;1
"Unit";"SCV";"Command Center";34;1
"Unit";"SCV";"Command Center";35;1
"Unit";"Marine";"Barracks";35;1
"Building";"Starport";NA;31;0
"Unit";"Marine";"Barracks";35;1
"Unit";"SCV";"Command Center";35;1
"Unit";"SCV";"Command Center";36;1
"Building";"SupplyDepot";NA;36;0
"Unit";"Cyclone";"Factory";37;3
"Unit";"SCV";"Command Center";39;1
"Unit";"SCV";"Command Center";40;1
"Unit";"SCV";"Command Center";44;1
"Unit";"SCV";"Command Center";45;1
"Unit";"Marine";"Barracks";41;1
"Unit";"Marine";"Barracks";41;1
"Building";"FactoryTechLab";NA;44;0
"Unit";"Medivac";"Starport";40;2
"Building";"EngineeringBay";NA;41;0
"Building";"SupplyDepot";NA;46;0
"Unit";"SCV";"Command Center";46;1
"Unit";"SCV";"Command Center";47;1
"Building";"SupplyDepot";NA;46;0
"Unit";"Marine";"Barracks";48;1
"Unit";"Marine";"Barracks";48;1
"Unit";"SCV";"Command Center";52;1
"Unit";"SCV";"Command Center";53;1
"Unit";"SCV";"Command Center";56;1
"Building";"MissileTurret";NA;54;0
"Unit";"SCV";"Command Center";57;1
"Building";"SupplyDepot";NA;54;0
"Building";"Bunker";NA;54;0
"Unit";"SCV";"Command Center";58;1
"Unit";"SCV";"Command Center";59;1
"Building";"SupplyDepot";NA;58;0
"Unit";"Marine";"Barracks";58;1
"Unit";"Marine";"Barracks";58;1
"Building";"MissileTurret";NA;60;0
"Building";"Refinery";NA;60;0
"Unit";"SCV";"Command Center";64;1
"Unit";"SCV";"Command Center";64;1
"Unit";"Medivac";"Starport";60;2
"Building";"Refinery";NA;62;0
"Building";"SupplyDepot";NA;62;0
"Unit";"SCV";"Command Center";64;1
"Unit";"Marine";"Barracks";68;1
"Building";"SupplyDepot";NA;68;0
"Unit";"SCV";"Command Center";69;1
"Unit";"SCV";"Command Center";70;1
"Unit";"SCV";"Command Center";70;1
"Unit";"Marine";"Barracks";70;1
"Unit";"Marine";"Barracks";70;1
"Unit";"SCV";"Command Center";71;1
"Unit";"SCV";"Command Center";72;1
"Unit";"Marine";"Barracks";73;1
"Unit";"Marine";"Barracks";74;1
"Upgrade";"TerranInfantryWeaponsLevel1";"EngineeringBay";62;0
"Unit";"SCV";"Command Center";76;1
"Unit";"SCV";"Command Center";76;1
"Unit";"Medivac";"Starport";73;2
"Unit";"SCV";"Command Center";79;1
"Unit";"SCV";"Command Center";80;1
"Building";"SupplyDepot";NA;80;0
"Unit";"SCV";"Command Center";83;1
"Building";"EngineeringBay";NA;80;0
"Unit";"SCV";"Command Center";84;1
"Unit";"Marine";"Barracks";81;1
"Unit";"Marine";"Barracks";81;1
"Building";"Barracks";NA;75;0
"Building";"Barracks";NA;75;0
"Building";"StarportTechLab";NA;85;0
"Unit";"SCV";"Command Center";85;1
"Unit";"SCV";"Command Center";86;1
"Building";"Armory";NA;78;0
"Building";"SupplyDepot";NA;87;0
"Unit";"SCV";"Command Center";89;1
"Building";"CommandCenter";NA;73;0
"Unit";"SCV";"Command Center";91;1
"Building";"SupplyDepot";NA;89;0
"Building";"FactoryReactor";NA;85;0
"Building";"MissileTurret";NA;91;0
"Unit";"SCV";"Command Center";91;1
"Unit";"Marine";"Barracks";91;1
"Unit";"Marauder";"Barracks";91;2
"Building";"Barracks";NA;85;0
"Building";"Barracks";NA;85;0
"Building";"StarportReactor";NA;91;0
"Unit";"Marine";"Barracks";95;1
"Unit";"Marine";"Barracks";95;1
"Unit";"Marauder";"Barracks";95;2
"Unit";"Marauder";"Barracks";95;2
"Building";"SupplyDepot";NA;97;0
"Building";"BarracksTechLab";NA;97;0
"Unit";"SCV";"Command Center";99;1
"Unit";"SCV";"Command Center";99;1
"Building";"SupplyDepot";NA;97;0
"Unit";"SCV";"Command Center";105;1
"Unit";"Marine";"Barracks";103;1
"Unit";"Marine";"Barracks";103;1
"Building";"BarracksReactor";NA;97;0
"Unit";"Marauder";"Barracks";103;2
"Unit";"Marauder";"Barracks";103;2
"Building";"CommandCenter";NA;91;0
"Unit";"SCV";"Command Center";105;1
"Upgrade";"TerranInfantryArmorsLevel1";"EngineeringBay";89;0
"Unit";"SCV";"Command Center";105;1
"Unit";"SCV";"Command Center";112;1
"Unit";"Marauder";"Barracks";105;2
"Unit";"Marine";"Barracks";106;1
"Building";"SupplyDepot";NA;105;0
"Building";"SupplyDepot";NA;108;0
"Unit";"SCV";"Command Center";113;1
"Building";"SupplyDepot";NA;113;0
"Building";"Refinery";NA;113;0
"Building";"Refinery";NA;113;0
"Building";"MissileTurret";NA;114;0
"Unit";"Marine";"Barracks";119;1
"Unit";"Marine";"Barracks";119;1
"Unit";"Marine";"Barracks";119;1
"Unit";"Marine";"Barracks";119;1
"Unit";"Marauder";"Barracks";119;2
"Unit";"Marauder";"Barracks";119;2
"Unit";"Marauder";"Barracks";119;2
"Unit";"SCV";"Command Center";119;1
"Unit";"SCV";"Command Center";119;1
"Unit";"SCV";"Command Center";119;1
"Upgrade";"Stimpack";"TechLab";99;0
"Unit";"Marine";"Barracks";119;1
"Unit";"Marauder";"Barracks";123;2
"Unit";"Marauder";"Barracks";125;2
"Unit";"Marauder";"Barracks";127;2
"Unit";"Marine";"Barracks";132;1
"Unit";"Marine";"Barracks";132;1
"Unit";"Marauder";"Barracks";133;2
"Unit";"Marauder";"Barracks";135;2
"Unit";"Marauder";"Barracks";137;2
"Upgrade";"TerranInfantryWeaponsLevel2";"EngineeringBay";105;0
"Unit";"Marine";"Barracks";139;1
"Unit";"Marine";"Barracks";139;1
"Unit";"SCV";"Command Center";147;1
"Unit";"SCV";"Command Center";147;1
"Unit";"SCV";"Command Center";147;1
"Unit";"Marauder";"Barracks";141;2
"Unit";"Marauder";"Barracks";143;2
"Unit";"Marauder";"Barracks";145;2
"Unit";"Medivac";"Starport";141;2
"Unit";"Medivac";"Starport";141;2
"Building";"SupplyDepot";NA;148;0
"Building";"MissileTurret";NA;149;0
"Building";"SupplyDepot";NA;149;0
"Building";"Refinery";NA;149;0
"Unit";"Marine";"Barracks";152;1
"Building";"SupplyDepot";NA;149;0
"Building";"Refinery";NA;149;0
"Unit";"Marauder";"Barracks";152;2
"Unit";"Marauder";"Barracks";154;2
"Building";"MissileTurret";NA;162;0
"Building";"MissileTurret";NA;162;0
"Unit";"Marine";"Barracks";163;1
"Unit";"Marauder";"Barracks";163;2
"Unit";"Marauder";"Barracks";163;2
"Building";"GhostAcademy";NA;167;0
"Unit";"Liberator";"Starport";163;3
"Unit";"Liberator";"Starport";163;3
"Building";"Starport";NA;163;0
"Unit";"SCV";"Command Center";172;1
"Unit";"SCV";"Command Center";172;1
"Unit";"SCV";"Command Center";172;1
"Building";"FusionCore";NA;163;0
"Unit";"Marine";"Barracks";172;1
"Unit";"Marine";"Barracks";172;1
"Unit";"Marauder";"Barracks";172;2
"Unit";"Marauder";"Barracks";172;2
"Building";"StarportTechLab";NA;187;0
"Unit";"Liberator";"Starport";172;3
"Unit";"Liberator";"Starport";175;3
"Upgrade";"TerranShipWeaponsLevel1";"Armory";163;0
"Upgrade";"TerranInfantryArmorsLevel2";"EngineeringBay";167;0
"Unit";"Marine";"Barracks";193;1
"Unit";"Marine";"Barracks";193;1
"Unit";"Marine";"Barracks";193;1
"Unit";"Marine";"Barracks";193;1
"Unit";"Marauder";"Barracks";193;2
"Unit";"Marauder";"Barracks";193;2
"Unit";"Marauder";"Barracks";193;2
"Upgrade";"TerranInfantryWeaponsLevel3";"EngineeringBay";167;0
"Unit";"SCV";"Command Center";195;1
"Unit";"SCV";"Command Center";195;1
"Unit";"Marine";"Barracks";193;1
"Unit";"Marine";"Barracks";194;1
"Unit";"Marine";"Barracks";195;1
"Unit";"Marine";"Barracks";196;1
"Unit";"Marauder";"Barracks";197;2
"Unit";"Marauder";"Barracks";199;2
"Unit";"Marauder";"Barracks";201;2
"Unit";"Liberator";"Starport";193;3
"Unit";"Liberator";"Starport";193;3
"Unit";"Liberator";"Starport";193;3
"Unit";"Marine";"Barracks";205;1
