"type";"unit_name";"on_building";"total_supply";"supply"
"Unit";"Overlord";"Larva";12;0
"Building";"SpawningPool";NA;19;0
"Building";"Hatchery";NA;17;0
"Building";"Extractor";NA;22;0
"Unit";"Zergling";"Larva";23;1
"Unit";"Zergling";"Larva";23;1
"Unit";"Zergling";"Larva";23;1
"Unit";"Zergling";"Larva";23;1
"Unit";"Overlord";"Larva";23;0
"Unit";"Queen";"Hatchery";23;2
"Unit";"Queen";"Hatchery";23;2
"Building";"Hatchery";NA;21;0
"Unit";"Queen";"Hatchery";34;2
"Unit";"Overlord";"Larva";36;0
"Building";"CreepTumorQueen";NA;36;0
"Unit";"Queen";"Hatchery";36;2
"Unit";"Overlord";"Larva";41;0
"Unit";"Overlord";"Larva";41;0
"Unit";"Zergling";"Larva";41;1
"Unit";"Zergling";"Larva";41;1
"Unit";"Zergling";"Larva";41;1
"Unit";"Zergling";"Larva";41;1
"Building";"CreepTumorQueen";NA;45;0
"Building";"CreepTumor";NA;45;0
"Unit";"Queen";"Hatchery";38;2
"Building";"CreepTumorQueen";NA;49;0
"Unit";"Overlord";"Larva";61;0
"Building";"CreepTumorQueen";NA;69;0
"Building";"CreepTumorQueen";NA;69;0
"Building";"CreepTumorQueen";NA;69;0
"Building";"SporeCrawler";NA;65;0
"Building";"CreepTumor";NA;69;0
"Unit";"Queen";"Hatchery";65;2
"Building";"CreepTumor";NA;69;0
"Unit";"Zergling";"Larva";69;1
"Unit";"Zergling";"Larva";69;1
"Unit";"Zergling";"Larva";69;1
"Unit";"Zergling";"Larva";69;1
"Unit";"Zergling";"Larva";69;1
"Unit";"Zergling";"Larva";69;1
"Unit";"Zergling";"Larva";69;1
"Unit";"Zergling";"Larva";69;1
"Building";"CreepTumor";NA;69;0
"Unit";"Overlord";"Larva";69;0
"Unit";"Overlord";"Larva";69;0
"Building";"CreepTumor";NA;69;0
"Building";"CreepTumor";NA;69;0
"Building";"CreepTumor";NA;69;0
"Unit";"Queen";"Hatchery";69;2
"Building";"SpineCrawler";NA;69;0
"Unit";"Overlord";"Larva";69;0
"Unit";"Zergling";"Larva";79;1
"Unit";"Zergling";"Larva";79;1
"Unit";"Zergling";"Larva";79;1
"Unit";"Zergling";"Larva";79;1
"Unit";"Zergling";"Larva";79;1
"Unit";"Zergling";"Larva";79;1
"Unit";"Zergling";"Larva";79;1
"Unit";"Zergling";"Larva";79;1
"Unit";"Zergling";"Larva";79;1
"Unit";"Zergling";"Larva";79;1
"Unit";"Zergling";"Larva";79;1
"Unit";"Zergling";"Larva";79;1
"Unit";"Zergling";"Larva";79;1
"Unit";"Zergling";"Larva";79;1
"Unit";"Zergling";"Larva";79;1
"Unit";"Zergling";"Larva";79;1
"Unit";"Zergling";"Larva";79;1
"Unit";"Zergling";"Larva";79;1
"Unit";"Zergling";"Larva";79;1
"Unit";"Zergling";"Larva";79;1
"Unit";"Zergling";"Larva";79;1
"Unit";"Zergling";"Larva";79;1
"Building";"BanelingNest";NA;69;0
"Unit";"Overlord";"Larva";81;0
"Unit";"Zergling";"Larva";81;1
"Unit";"Zergling";"Larva";81;1
"Building";"CreepTumor";NA;81;0
"Unit";"Zergling";"Larva";81;1
"Unit";"Zergling";"Larva";81;1
"Building";"CreepTumor";NA;103;0
"Building";"CreepTumor";NA;103;0
"Unit";"Baneling";"Zergling";103;0
"Unit";"Baneling";"Zergling";103;0
"Unit";"Baneling";"Zergling";103;0
"Unit";"Baneling";"Zergling";103;0
"Unit";"Baneling";"Zergling";103;0
"Unit";"Queen";"Hatchery";81;2
"Building";"CreepTumorQueen";NA;108;0
"Building";"CreepTumorQueen";NA;108;0
"Building";"CreepTumorQueen";NA;108;0
"Unit";"Overlord";"Larva";108;0
"Unit";"Overlord";"Larva";108;0
"Unit";"Queen";"Hatchery";103;2
"Unit";"Queen";"Hatchery";103;2
"Unit";"Baneling";"Zergling";114;0
"Unit";"Baneling";"Zergling";114;0
"Unit";"Baneling";"Zergling";114;0
"Building";"CreepTumor";NA;127;0
"Building";"Extractor";NA;118;0
"Building";"Extractor";NA;118;0
"Building";"EvolutionChamber";NA;118;0
"Building";"EvolutionChamber";NA;118;0
"Unit";"Baneling";"Zergling";127;0
"Unit";"Baneling";"Zergling";127;0
"Unit";"Baneling";"Zergling";127;0
"Building";"CreepTumorQueen";NA;127;0
"Building";"CreepTumorQueen";NA;127;0
"Building";"CreepTumorQueen";NA;127;0
"Building";"CreepTumorQueen";NA;127;0
"Unit";"Overlord";"Larva";130;0
"Unit";"Overlord";"Larva";130;0
"Unit";"Overlord";"Larva";130;0
"Building";"CreepTumorQueen";NA;138;0
"Building";"CreepTumorQueen";NA;138;0
"Building";"Extractor";NA;127;0
"Building";"CreepTumorQueen";NA;138;0
"Building";"CreepTumor";NA;138;0
"Building";"CreepTumor";NA;138;0
"Building";"CreepTumor";NA;138;0
"Building";"Extractor";NA;130;0
"Unit";"Overlord";"Larva";138;0
"Building";"Extractor";NA;130;0
"Building";"SporeCrawler";NA;138;0
"Building";"CreepTumorQueen";NA;143;0
"Building";"CreepTumorQueen";NA;143;0
"Building";"CreepTumorQueen";NA;143;0
"Building";"Hatchery";NA;127;0
"Unit";"Zergling";"Larva";143;1
"Unit";"Zergling";"Larva";143;1
"Unit";"Zergling";"Larva";143;1
"Unit";"Zergling";"Larva";143;1
"Unit";"Zergling";"Larva";143;1
"Unit";"Zergling";"Larva";143;1
"Unit";"Zergling";"Larva";143;1
"Unit";"Zergling";"Larva";143;1
"Unit";"Zergling";"Larva";143;1
"Unit";"Zergling";"Larva";143;1
"Unit";"Zergling";"Larva";143;1
"Unit";"Zergling";"Larva";143;1
"Unit";"Zergling";"Larva";143;1
"Unit";"Zergling";"Larva";143;1
"Unit";"Zergling";"Larva";143;1
"Unit";"Zergling";"Larva";143;1
"Building";"CreepTumorQueen";NA;143;0
"Building";"CreepTumorQueen";NA;143;0
"Building";"CreepTumor";NA;143;0
"Building";"CreepTumorQueen";NA;143;0
"Building";"CreepTumor";NA;143;0
"Building";"CreepTumor";NA;143;0
"Building";"CreepTumor";NA;143;0
"Building";"CreepTumor";NA;143;0
"Building";"CreepTumor";NA;145;0
"Building";"CreepTumor";NA;147;0
"Unit";"Zergling";"Larva";153;1
"Unit";"Zergling";"Larva";153;1
"Unit";"Zergling";"Larva";153;1
"Unit";"Zergling";"Larva";153;1
"Unit";"Zergling";"Larva";153;1
"Unit";"Zergling";"Larva";153;1
"Unit";"Zergling";"Larva";153;1
"Unit";"Zergling";"Larva";153;1
"Unit";"Zergling";"Larva";153;1
"Unit";"Zergling";"Larva";153;1
"Unit";"Overlord";"Larva";162;0
"Unit";"Zergling";"Larva";162;1
"Unit";"Zergling";"Larva";162;1
"Unit";"Overlord";"Larva";162;0
"Unit";"Zergling";"Larva";162;1
"Unit";"Zergling";"Larva";162;1
"Unit";"Zergling";"Larva";162;1
"Unit";"Zergling";"Larva";162;1
"Unit";"Zergling";"Larva";162;1
"Unit";"Zergling";"Larva";162;1
"Unit";"Zergling";"Larva";162;1
"Unit";"Zergling";"Larva";162;1
"Unit";"Queen";"Hatchery";162;2
"Building";"CreepTumor";NA;172;0
"Building";"CreepTumor";NA;172;0
"Building";"CreepTumor";NA;172;0
"Building";"CreepTumor";NA;172;0
"Building";"CreepTumor";NA;172;0
"Building";"CreepTumor";NA;172;0
"Building";"CreepTumor";NA;172;0
"Building";"CreepTumor";NA;172;0
"Building";"CreepTumor";NA;172;0
"Unit";"Zergling";"Larva";178;1
"Unit";"Zergling";"Larva";178;1
"Unit";"Zergling";"Larva";182;1
"Unit";"Zergling";"Larva";182;1
"Unit";"Zergling";"Larva";182;1
"Unit";"Zergling";"Larva";182;1
"Unit";"Zergling";"Larva";182;1
"Unit";"Zergling";"Larva";182;1
"Unit";"Zergling";"Larva";182;1
"Unit";"Zergling";"Larva";182;1
"Unit";"Zergling";"Larva";182;1
"Unit";"Zergling";"Larva";182;1
"Unit";"Zergling";"Larva";182;1
"Unit";"Zergling";"Larva";182;1
"Unit";"Zergling";"Larva";182;1
"Unit";"Zergling";"Larva";182;1
"Unit";"Zergling";"Larva";182;1
"Unit";"Zergling";"Larva";182;1
"Unit";"Baneling";"Zergling";182;0
"Unit";"Baneling";"Zergling";182;0
"Unit";"Baneling";"Zergling";182;0
"Unit";"Baneling";"Zergling";182;0
"Building";"SporeCrawler";NA;184;0
"Building";"SporeCrawler";NA;202;0
"Building";"Hatchery";NA;155;0
"Building";"CreepTumor";NA;210;0
"Building";"CreepTumor";NA;210;0
"Building";"CreepTumor";NA;210;0
"Upgrade";"ZergGroundArmorsLevel1";"EvolutionChamber";143;0
"Building";"HydraliskDen";NA;206;0
"Building";"CreepTumorQueen";NA;214;0
"Building";"CreepTumorQueen";NA;214;0
"Building";"CreepTumorQueen";NA;214;0
"Building";"CreepTumorQueen";NA;214;0
"Upgrade";"ZergMeleeWeaponsLevel1";"EvolutionChamber";162;0
"Building";"InfestationPit";NA;205;0
"Unit";"Hydralisk";"Larva";214;2
"Unit";"Hydralisk";"Larva";214;2
"Unit";"Hydralisk";"Larva";214;2
"Unit";"Hydralisk";"Larva";214;2
"Unit";"Hydralisk";"Larva";214;2
"Unit";"Hydralisk";"Larva";214;2
"Unit";"Hydralisk";"Larva";214;2
"Unit";"Hydralisk";"Larva";214;2
"Unit";"Hydralisk";"Larva";214;2
"Unit";"Hydralisk";"Larva";214;2
"Unit";"Hydralisk";"Larva";214;2
"Unit";"Hydralisk";"Larva";214;2
"Unit";"Hydralisk";"Larva";214;2
"Unit";"Zergling";"Larva";214;1
"Unit";"Zergling";"Larva";214;1
"Unit";"Zergling";"Larva";214;1
"Unit";"Zergling";"Larva";214;1
"Unit";"Zergling";"Larva";214;1
"Unit";"Zergling";"Larva";214;1
"Unit";"Zergling";"Larva";214;1
"Unit";"Zergling";"Larva";214;1
"Unit";"Zergling";"Larva";214;1
"Unit";"Zergling";"Larva";214;1
"Unit";"Zergling";"Larva";214;1
"Unit";"Zergling";"Larva";214;1
"Unit";"Zergling";"Larva";214;1
"Unit";"Zergling";"Larva";214;1
"Unit";"Zergling";"Larva";214;1
"Unit";"Zergling";"Larva";214;1
"Unit";"Zergling";"Larva";214;1
"Unit";"Zergling";"Larva";214;1
"Unit";"Zergling";"Larva";214;1
"Unit";"Zergling";"Larva";214;1
"Unit";"Zergling";"Larva";214;1
"Unit";"Zergling";"Larva";214;1
"Unit";"Zergling";"Larva";214;1
"Unit";"Zergling";"Larva";214;1
"Unit";"Zergling";"Larva";214;1
"Unit";"Zergling";"Larva";214;1
"Unit";"Zergling";"Larva";214;1
"Unit";"Zergling";"Larva";214;1
"Unit";"Baneling";"Zergling";214;0
"Unit";"Zergling";"Larva";214;1
"Unit";"Zergling";"Larva";214;1
"Unit";"Zergling";"Larva";214;1
"Unit";"Zergling";"Larva";214;1
"Unit";"Zergling";"Larva";214;1
"Unit";"Zergling";"Larva";214;1
"Unit";"Baneling";"Zergling";214;0
"Unit";"Baneling";"Zergling";214;0
"Building";"CreepTumorQueen";NA;264;0
"Unit";"Zergling";"Larva";264;1
"Unit";"Zergling";"Larva";264;1
"Unit";"Zergling";"Larva";264;1
"Unit";"Zergling";"Larva";264;1
"Unit";"Zergling";"Larva";264;1
"Unit";"Zergling";"Larva";264;1
"Unit";"Zergling";"Larva";264;1
"Unit";"Zergling";"Larva";264;1
"Unit";"Zergling";"Larva";264;1
"Unit";"Zergling";"Larva";264;1
"Unit";"Zergling";"Larva";264;1
"Unit";"Zergling";"Larva";264;1
"Unit";"Zergling";"Larva";264;1
"Unit";"Zergling";"Larva";264;1
"Unit";"Zergling";"Larva";264;1
"Unit";"Zergling";"Larva";264;1
"Unit";"Zergling";"Larva";264;1
"Unit";"Zergling";"Larva";264;1
"Building";"CreepTumorQueen";NA;292;0
"Building";"CreepTumorQueen";NA;292;0
"Building";"CreepTumor";NA;292;0
"Upgrade";"EvolveGroovedSpines";"HydraliskDen";214;0
"Building";"CreepTumor";NA;292;0
"Building";"CreepTumor";NA;292;0
"Building";"CreepTumor";NA;292;0
"Building";"CreepTumor";NA;292;0
"Building";"CreepTumor";NA;292;0
"Building";"CreepTumor";NA;292;0
"Unit";"Overlord";"Larva";292;0
"Unit";"Overlord";"Larva";292;0
"Unit";"Overlord";"Larva";292;0
"Unit";"Overlord";"Larva";292;0
"Unit";"Overlord";"Larva";292;0
"Unit";"Overlord";"Larva";292;0
"Unit";"Zergling";"Larva";292;1
"Unit";"Zergling";"Larva";292;1
"Unit";"Zergling";"Larva";292;1
"Unit";"Zergling";"Larva";292;1
"Unit";"Zergling";"Larva";292;1
"Unit";"Zergling";"Larva";292;1
"Unit";"Zergling";"Larva";292;1
"Unit";"Zergling";"Larva";292;1
"Unit";"Zergling";"Larva";292;1
"Unit";"Zergling";"Larva";292;1
"Unit";"Zergling";"Larva";292;1
"Unit";"Zergling";"Larva";292;1
"Unit";"Zergling";"Larva";292;1
"Unit";"Zergling";"Larva";292;1
"Unit";"Zergling";"Larva";292;1
"Unit";"Zergling";"Larva";292;1
"Unit";"Zergling";"Larva";292;1
"Unit";"Zergling";"Larva";292;1
"Unit";"Zergling";"Larva";292;1
"Unit";"Zergling";"Larva";292;1
"Unit";"Zergling";"Larva";292;1
"Unit";"Zergling";"Larva";292;1
"Unit";"Zergling";"Larva";292;1
"Unit";"Zergling";"Larva";292;1
"Unit";"Baneling";"Zergling";292;0
"Unit";"Baneling";"Zergling";292;0
"Unit";"Baneling";"Zergling";292;0
"Unit";"Baneling";"Zergling";292;0
"Unit";"Baneling";"Zergling";292;0
"Unit";"Baneling";"Zergling";292;0
"Unit";"Baneling";"Zergling";292;0
"Unit";"Overlord";"Larva";292;0
"Unit";"Overlord";"Larva";292;0
"Building";"CreepTumor";NA;316;0
"Building";"CreepTumorQueen";NA;316;0
"Building";"CreepTumorQueen";NA;316;0
"Building";"CreepTumor";NA;316;0
"Building";"CreepTumor";NA;316;0
"Building";"CreepTumorQueen";NA;316;0
"Building";"CreepTumor";NA;316;0
"Building";"CreepTumor";NA;316;0
"Building";"CreepTumor";NA;316;0
"Building";"CreepTumor";NA;316;0
"Upgrade";"ZergGroundArmorsLevel2";"EvolutionChamber";264;0
"Unit";"Zergling";"Larva";316;1
"Unit";"Zergling";"Larva";316;1
"Building";"Hatchery";NA;292;0
"Unit";"Zergling";"Larva";316;1
"Unit";"Zergling";"Larva";316;1
"Unit";"Zergling";"Larva";316;1
"Unit";"Zergling";"Larva";316;1
"Unit";"Zergling";"Larva";316;1
"Unit";"Zergling";"Larva";316;1
"Unit";"Zergling";"Larva";316;1
"Unit";"Zergling";"Larva";316;1
"Unit";"Zergling";"Larva";316;1
"Unit";"Zergling";"Larva";316;1
"Unit";"Zergling";"Larva";316;1
"Unit";"Zergling";"Larva";316;1
"Unit";"Zergling";"Larva";316;1
"Unit";"Zergling";"Larva";316;1
"Unit";"Zergling";"Larva";316;1
"Unit";"Zergling";"Larva";316;1
"Unit";"Baneling";"Zergling";316;0
"Unit";"Zergling";"Larva";316;1
"Unit";"Zergling";"Larva";316;1
"Unit";"Zergling";"Larva";316;1
"Unit";"Zergling";"Larva";316;1
"Unit";"Zergling";"Larva";316;1
"Unit";"Zergling";"Larva";316;1
"Unit";"Zergling";"Larva";316;1
"Unit";"Zergling";"Larva";316;1
"Unit";"Zergling";"Larva";316;1
"Unit";"Zergling";"Larva";316;1
"Unit";"Zergling";"Larva";316;1
"Unit";"Zergling";"Larva";316;1
"Unit";"Zergling";"Larva";316;1
"Unit";"Zergling";"Larva";316;1
"Unit";"Baneling";"Zergling";316;0
"Unit";"Baneling";"Zergling";316;0
"Unit";"Zergling";"Larva";316;1
"Unit";"Zergling";"Larva";316;1
"Unit";"Zergling";"Larva";316;1
"Unit";"Zergling";"Larva";316;1
"Unit";"Baneling";"Zergling";316;0
"Unit";"Baneling";"Zergling";316;0
"Unit";"Baneling";"Zergling";316;0
"Unit";"Baneling";"Zergling";316;0
"Unit";"Baneling";"Zergling";316;0
"Unit";"Baneling";"Zergling";316;0
"Unit";"Baneling";"Zergling";316;0
"Unit";"Baneling";"Zergling";316;0
"Unit";"Baneling";"Zergling";316;0
"Unit";"Baneling";"Zergling";316;0
"Unit";"Baneling";"Zergling";316;0
"Unit";"Baneling";"Zergling";316;0
"Unit";"Baneling";"Zergling";316;0
"Unit";"Baneling";"Zergling";316;0
"Unit";"Baneling";"Zergling";316;0
"Unit";"Baneling";"Zergling";316;0
"Unit";"Baneling";"Zergling";316;0
"Unit";"Baneling";"Zergling";316;0
"Unit";"Baneling";"Zergling";316;0
"Unit";"Baneling";"Zergling";316;0
"Unit";"Baneling";"Zergling";316;0
"Unit";"Baneling";"Zergling";316;0
"Unit";"Baneling";"Zergling";316;0
"Unit";"Baneling";"Zergling";316;0
"Unit";"Baneling";"Zergling";316;0
"Unit";"Baneling";"Zergling";316;0
"Unit";"Baneling";"Zergling";316;0
"Unit";"Baneling";"Zergling";316;0
"Unit";"Baneling";"Zergling";316;0
"Unit";"Baneling";"Zergling";316;0
"Unit";"Baneling";"Zergling";316;0
"Unit";"Baneling";"Zergling";316;0
"Building";"CreepTumor";NA;320;0
"Upgrade";"EvolveMuscularAugments";"HydraliskDen";292;0
"Unit";"Zergling";"Larva";320;1
"Unit";"Zergling";"Larva";320;1
"Unit";"Zergling";"Larva";320;1
"Unit";"Zergling";"Larva";320;1
"Unit";"Zergling";"Larva";320;1
"Unit";"Zergling";"Larva";320;1
"Unit";"Zergling";"Larva";320;1
"Unit";"Zergling";"Larva";320;1
"Unit";"Zergling";"Larva";320;1
"Unit";"Zergling";"Larva";320;1
"Unit";"Zergling";"Larva";320;1
"Unit";"Zergling";"Larva";320;1
"Unit";"Zergling";"Larva";320;1
"Unit";"Zergling";"Larva";320;1
"Unit";"Zergling";"Larva";320;1
"Unit";"Zergling";"Larva";320;1
"Unit";"Zergling";"Larva";320;1
"Unit";"Zergling";"Larva";320;1
"Building";"CreepTumor";NA;374;0
"Building";"CreepTumor";NA;374;0
"Unit";"Overlord";"Larva";374;0
"Unit";"Overlord";"Larva";374;0
"Unit";"Zergling";"Larva";374;1
"Unit";"Zergling";"Larva";374;1
"Unit";"Zergling";"Larva";374;1
"Unit";"Zergling";"Larva";374;1
"Unit";"Zergling";"Larva";374;1
"Unit";"Zergling";"Larva";374;1
"Unit";"Zergling";"Larva";374;1
"Unit";"Zergling";"Larva";374;1
"Unit";"Zergling";"Larva";374;1
"Unit";"Zergling";"Larva";374;1
"Unit";"Zergling";"Larva";374;1
"Unit";"Zergling";"Larva";374;1
"Unit";"Zergling";"Larva";374;1
"Unit";"Zergling";"Larva";374;1
"Unit";"Zergling";"Larva";374;1
"Unit";"Zergling";"Larva";374;1
"Unit";"Zergling";"Larva";374;1
"Unit";"Zergling";"Larva";374;1
"Unit";"Zergling";"Larva";374;1
"Unit";"Zergling";"Larva";374;1
"Unit";"Zergling";"Larva";374;1
"Unit";"Zergling";"Larva";374;1
"Unit";"Zergling";"Larva";374;1
"Unit";"Zergling";"Larva";374;1
"Unit";"Zergling";"Larva";374;1
"Unit";"Zergling";"Larva";374;1
"Unit";"Zergling";"Larva";374;1
"Unit";"Zergling";"Larva";374;1
"Building";"CreepTumor";NA;374;0
"Building";"CreepTumor";NA;374;0
"Unit";"Viper";"Larva";374;3
"Unit";"Viper";"Larva";374;3
"Unit";"Viper";"Larva";374;3
"Unit";"Viper";"Larva";374;3
"Building";"CreepTumorQueen";NA;374;0
"Building";"CreepTumorQueen";NA;411;0
"Building";"CreepTumorQueen";NA;414;0
"Building";"CreepTumorQueen";NA;414;0
"Building";"CreepTumorQueen";NA;414;0
"Building";"CreepTumor";NA;414;0
"Building";"CreepTumorQueen";NA;414;0
"Building";"CreepTumorQueen";NA;414;0
"Upgrade";"ZergMeleeWeaponsLevel2";"EvolutionChamber";320;0
"Building";"CreepTumor";NA;414;0
"Building";"CreepTumor";NA;414;0
"Building";"Extractor";NA;414;0
"Building";"Extractor";NA;414;0
"Unit";"Zergling";"Larva";414;1
"Unit";"Zergling";"Larva";414;1
"Unit";"Zergling";"Larva";414;1
"Unit";"Zergling";"Larva";414;1
"Unit";"Zergling";"Larva";414;1
"Unit";"Zergling";"Larva";414;1
"Unit";"Zergling";"Larva";414;1
"Unit";"Zergling";"Larva";414;1
"Unit";"Zergling";"Larva";414;1
"Unit";"Zergling";"Larva";414;1
"Unit";"Zergling";"Larva";414;1
"Unit";"Zergling";"Larva";414;1
"Unit";"Zergling";"Larva";414;1
"Unit";"Zergling";"Larva";414;1
"Unit";"Zergling";"Larva";414;1
"Unit";"Zergling";"Larva";414;1
"Unit";"Zergling";"Larva";414;1
"Unit";"Zergling";"Larva";414;1
"Unit";"Zergling";"Larva";414;1
"Unit";"Zergling";"Larva";414;1
"Unit";"Zergling";"Larva";414;1
"Unit";"Zergling";"Larva";414;1
"Unit";"Zergling";"Larva";414;1
"Unit";"Zergling";"Larva";414;1
"Unit";"Zergling";"Larva";414;1
"Unit";"Zergling";"Larva";414;1
"Unit";"Zergling";"Larva";414;1
"Unit";"Zergling";"Larva";414;1
"Unit";"Zergling";"Larva";414;1
"Unit";"Zergling";"Larva";414;1
"Unit";"Zergling";"Larva";414;1
"Unit";"Zergling";"Larva";414;1
"Unit";"Zergling";"Larva";414;1
"Unit";"Zergling";"Larva";414;1
"Unit";"Zergling";"Larva";414;1
"Unit";"Zergling";"Larva";414;1
"Unit";"Zergling";"Larva";414;1
"Unit";"Zergling";"Larva";414;1
"Upgrade";"ZergMissileWeaponsLevel1";"EvolutionChamber";374;0
"Building";"SporeCrawler";NA;414;0
"Building";"SporeCrawler";NA;414;0
"Building";"SporeCrawler";NA;414;0
"Building";"UltraliskCavern";NA;414;0
"Building";"Hatchery";NA;374;0
"Building";"Spire";NA;414;0
"Building";"CreepTumor";NA;452;0
"Unit";"Ultralisk";"Larva";452;6
"Unit";"Ultralisk";"Larva";452;6
"Building";"CreepTumor";NA;452;0
"Unit";"Zergling";"Larva";452;1
"Unit";"Zergling";"Larva";452;1
"Unit";"Zergling";"Larva";452;1
"Unit";"Zergling";"Larva";452;1
"Unit";"Zergling";"Larva";452;1
"Unit";"Zergling";"Larva";452;1
"Unit";"Zergling";"Larva";452;1
"Unit";"Zergling";"Larva";452;1
"Building";"CreepTumorQueen";NA;464;0
"Building";"CreepTumorQueen";NA;464;0
"Building";"CreepTumor";NA;464;0
"Building";"CreepTumorQueen";NA;464;0
"Building";"CreepTumorQueen";NA;472;0
"Building";"CreepTumorQueen";NA;472;0
"Building";"CreepTumorQueen";NA;472;0
"Building";"CreepTumorQueen";NA;472;0
"Building";"CreepTumorQueen";NA;472;0
"Building";"CreepTumorQueen";NA;472;0
"Building";"CreepTumorQueen";NA;472;0
"Upgrade";"ChitinousPlating";"UltraliskCavern";452;0
"Building";"CreepTumorQueen";NA;472;0
"Building";"CreepTumorQueen";NA;472;0
"Building";"CreepTumorQueen";NA;472;0
"Building";"CreepTumor";NA;472;0
"Building";"CreepTumor";NA;472;0
"Unit";"Zergling";"Larva";472;1
"Unit";"Zergling";"Larva";472;1
"Unit";"Zergling";"Larva";472;1
"Unit";"Zergling";"Larva";472;1
"Unit";"Corruptor";"Larva";472;2
"Unit";"Corruptor";"Larva";472;2
"Unit";"Corruptor";"Larva";472;2
"Unit";"Corruptor";"Larva";472;2
"Unit";"Corruptor";"Larva";472;2
"Unit";"Corruptor";"Larva";472;2
"Upgrade";"ZergMissileWeaponsLevel2";"EvolutionChamber";472;0
"Unit";"Zergling";"Larva";488;1
"Unit";"Zergling";"Larva";488;1
"Unit";"Zergling";"Larva";488;1
"Unit";"Zergling";"Larva";488;1
"Unit";"Zergling";"Larva";488;1
"Unit";"Zergling";"Larva";488;1
"Unit";"Zergling";"Larva";488;1
"Unit";"Zergling";"Larva";488;1
"Unit";"Zergling";"Larva";488;1
"Unit";"Zergling";"Larva";488;1
"Unit";"Zergling";"Larva";488;1
"Unit";"Zergling";"Larva";488;1
"Unit";"Zergling";"Larva";488;1
"Unit";"Zergling";"Larva";488;1
"Building";"CreepTumor";NA;488;0
"Building";"CreepTumorQueen";NA;488;0
"Building";"CreepTumorQueen";NA;488;0
"Building";"CreepTumorQueen";NA;488;0
"Building";"CreepTumor";NA;488;0
"Building";"CreepTumor";NA;488;0
"Unit";"Ultralisk";"Larva";488;6
"Building";"CreepTumor";NA;502;0
"Upgrade";"ZergGroundArmorsLevel3";"EvolutionChamber";472;0
"Unit";"Ultralisk";"Larva";488;6
"Unit";"Ultralisk";"Larva";488;6
"Unit";"Ultralisk";"Larva";488;6
"Building";"CreepTumorQueen";NA;502;0
"Building";"CreepTumorQueen";NA;502;0
"Building";"CreepTumorQueen";NA;502;0
"Building";"CreepTumor";NA;526;0
"Building";"CreepTumor";NA;526;0
"Building";"CreepTumor";NA;526;0
"Building";"CreepTumor";NA;526;0
"Building";"CreepTumor";NA;526;0
"Building";"CreepTumor";NA;526;0
"Building";"CreepTumor";NA;526;0
"Building";"CreepTumor";NA;526;0
"Building";"CreepTumor";NA;526;0
"Building";"CreepTumorQueen";NA;526;0
"Building";"CreepTumor";NA;526;0
"Building";"CreepTumorQueen";NA;526;0
"Building";"CreepTumorQueen";NA;526;0
"Building";"CreepTumorQueen";NA;526;0
"Building";"CreepTumor";NA;526;0
"Building";"CreepTumor";NA;526;0
"Building";"CreepTumor";NA;526;0
"Building";"CreepTumor";NA;526;0
"Building";"CreepTumor";NA;526;0
"Building";"CreepTumor";NA;526;0
"Building";"CreepTumor";NA;526;0
"Building";"CreepTumor";NA;526;0
"Building";"CreepTumor";NA;526;0
"Building";"CreepTumor";NA;526;0
"Building";"CreepTumor";NA;526;0
"Building";"Hatchery";NA;526;0
"Building";"CreepTumor";NA;526;0
"Building";"CreepTumor";NA;526;0
"Building";"CreepTumor";NA;526;0
"Building";"CreepTumor";NA;526;0
"Building";"CreepTumor";NA;526;0
"Building";"CreepTumor";NA;526;0
"Building";"CreepTumor";NA;526;0
"Building";"CreepTumor";NA;526;0
"Building";"Extractor";NA;526;0
"Building";"Extractor";NA;526;0
"Unit";"Zergling";"Larva";526;1
"Unit";"Zergling";"Larva";526;1
"Unit";"Zergling";"Larva";526;1
"Unit";"Zergling";"Larva";526;1
"Unit";"Zergling";"Larva";526;1
"Unit";"Zergling";"Larva";526;1
"Unit";"Zergling";"Larva";526;1
"Unit";"Zergling";"Larva";526;1
"Unit";"Zergling";"Larva";526;1
"Unit";"Zergling";"Larva";526;1
"Unit";"Zergling";"Larva";526;1
"Unit";"Zergling";"Larva";526;1
"Unit";"Zergling";"Larva";526;1
"Unit";"Zergling";"Larva";526;1
"Building";"CreepTumor";NA;526;0
"Building";"CreepTumorQueen";NA;526;0
"Building";"CreepTumorQueen";NA;526;0
"Building";"CreepTumor";NA;540;0
"Building";"CreepTumor";NA;540;0
"Building";"CreepTumor";NA;540;0
"Building";"Extractor";NA;540;0
"Building";"Extractor";NA;540;0
"Building";"SporeCrawler";NA;540;0
"Building";"SporeCrawler";NA;540;0
"Building";"SporeCrawler";NA;540;0
"Building";"CreepTumor";NA;540;0
"Building";"CreepTumor";NA;540;0
"Building";"CreepTumor";NA;540;0
"Building";"CreepTumor";NA;540;0
"Building";"CreepTumor";NA;540;0
"Building";"CreepTumor";NA;540;0
"Building";"CreepTumor";NA;540;0
"Building";"CreepTumor";NA;540;0
"Building";"CreepTumor";NA;540;0
"Building";"CreepTumor";NA;540;0
"Building";"CreepTumor";NA;540;0
"Building";"CreepTumorQueen";NA;540;0
"Building";"CreepTumorQueen";NA;540;0
"Unit";"Corruptor";"Larva";540;2
"Building";"CreepTumorQueen";NA;540;0
"Unit";"Corruptor";"Larva";540;2
"Unit";"Corruptor";"Larva";540;2
"Unit";"Corruptor";"Larva";540;2
"Unit";"Corruptor";"Larva";540;2
"Unit";"Corruptor";"Larva";540;2
"Building";"Hatchery";NA;540;0
"Building";"CreepTumorQueen";NA;540;0
"Building";"CreepTumorQueen";NA;552;0
"Unit";"Corruptor";"Larva";540;2
"Unit";"Corruptor";"Larva";540;2
"Building";"CreepTumor";NA;556;0
"Building";"CreepTumor";NA;556;0
"Building";"CreepTumorQueen";NA;556;0
"Building";"CreepTumorQueen";NA;556;0
"Building";"CreepTumor";NA;556;0
"Building";"CreepTumor";NA;556;0
"Building";"CreepTumor";NA;556;0
"Building";"CreepTumor";NA;556;0
"Building";"CreepTumorQueen";NA;556;0
"Building";"CreepTumorQueen";NA;556;0
"Building";"CreepTumorQueen";NA;556;0
"Building";"CreepTumorQueen";NA;556;0
"Unit";"Corruptor";"Larva";556;2
"Unit";"Corruptor";"Larva";556;2
"Unit";"Corruptor";"Larva";556;2
"Unit";"Corruptor";"Larva";556;2
"Unit";"Zergling";"Larva";556;1
"Unit";"Zergling";"Larva";556;1
"Unit";"Zergling";"Larva";556;1
"Unit";"Zergling";"Larva";556;1
"Unit";"Zergling";"Larva";556;1
"Unit";"Zergling";"Larva";556;1
"Unit";"Zergling";"Larva";556;1
"Unit";"Zergling";"Larva";556;1
"Unit";"Zergling";"Larva";556;1
"Unit";"Zergling";"Larva";556;1
"Unit";"Zergling";"Larva";556;1
"Unit";"Zergling";"Larva";556;1
"Unit";"Zergling";"Larva";556;1
"Unit";"Zergling";"Larva";556;1
"Unit";"Zergling";"Larva";556;1
"Unit";"Zergling";"Larva";556;1
"Unit";"Zergling";"Larva";556;1
"Unit";"Zergling";"Larva";556;1
"Unit";"Zergling";"Larva";556;1
"Unit";"Zergling";"Larva";556;1
"Unit";"Zergling";"Larva";556;1
"Unit";"Zergling";"Larva";556;1
"Unit";"Zergling";"Larva";556;1
"Unit";"Zergling";"Larva";556;1
"Unit";"Zergling";"Larva";556;1
"Unit";"Zergling";"Larva";556;1
"Unit";"Zergling";"Larva";556;1
"Unit";"Zergling";"Larva";556;1
"Unit";"Zergling";"Larva";556;1
"Unit";"Zergling";"Larva";556;1
"Unit";"Zergling";"Larva";556;1
"Unit";"Zergling";"Larva";556;1
"Unit";"Zergling";"Larva";556;1
"Unit";"Zergling";"Larva";556;1
"Unit";"Zergling";"Larva";556;1
"Unit";"Zergling";"Larva";556;1
"Building";"CreepTumorQueen";NA;584;0
"Building";"CreepTumor";NA;584;0
"Building";"CreepTumor";NA;584;0
"Building";"SporeCrawler";NA;584;0
"Building";"SporeCrawler";NA;584;0
"Building";"CreepTumorQueen";NA;600;0
"Building";"CreepTumorQueen";NA;600;0
"Building";"CreepTumorQueen";NA;600;0
"Unit";"Corruptor";"Larva";600;2
"Unit";"Corruptor";"Larva";600;2
"Unit";"Corruptor";"Larva";600;2
"Unit";"Corruptor";"Larva";600;2
"Building";"CreepTumorQueen";NA;600;0
"Unit";"Corruptor";"Larva";600;2
"Unit";"Corruptor";"Larva";600;2
"Unit";"Corruptor";"Larva";600;2
"Building";"CreepTumorQueen";NA;600;0
"Building";"CreepTumorQueen";NA;600;0
"Building";"CreepTumorQueen";NA;600;0
"Building";"CreepTumor";NA;600;0
"Building";"CreepTumor";NA;600;0
"Building";"CreepTumor";NA;600;0
"Building";"CreepTumor";NA;600;0
"Building";"CreepTumorQueen";NA;614;0
"Building";"CreepTumorQueen";NA;614;0
"Building";"CreepTumorQueen";NA;614;0
"Building";"CreepTumorQueen";NA;614;0
"Building";"CreepTumorQueen";NA;614;0
"Building";"CreepTumorQueen";NA;614;0
"Building";"CreepTumor";NA;614;0
"Building";"CreepTumorQueen";NA;614;0
"Building";"CreepTumorQueen";NA;614;0
"Building";"CreepTumorQueen";NA;614;0
"Building";"CreepTumorQueen";NA;614;0
"Building";"CreepTumorQueen";NA;614;0
"Building";"CreepTumor";NA;614;0
"Building";"CreepTumor";NA;614;0
"Building";"CreepTumor";NA;614;0
"Building";"CreepTumor";NA;614;0
