"type";"unit_name";"on_building";"total_supply";"supply"
"Unit";"Overlord";"Larva";13;0
"Building";"Extractor";NA;18;0
"Building";"SpawningPool";NA;19;0
"Building";"Hatchery";NA;18;0
"Unit";"Zergling";"Larva";24;1
"Unit";"Zergling";"Larva";24;1
"Unit";"Zergling";"Larva";25;1
"Unit";"Zergling";"Larva";25;1
"Unit";"Queen";"Hatchery";23;2
"Unit";"Overlord";"Larva";34;0
"Building";"Hatchery";NA;23;0
"Unit";"Overlord";"Larva";34;0
"Unit";"Queen";"Hatchery";34;2
"Unit";"Queen";"Hatchery";34;2
"Unit";"Zergling";"Larva";40;1
"Unit";"Zergling";"Larva";40;1
"Unit";"Zergling";"Larva";42;1
"Unit";"Zergling";"Larva";42;1
"Unit";"Zergling";"Larva";53;1
"Unit";"Zergling";"Larva";53;1
"Unit";"Zergling";"Larva";53;1
"Unit";"Zergling";"Larva";53;1
"Unit";"Zergling";"Larva";53;1
"Unit";"Zergling";"Larva";53;1
"Unit";"Overlord";"Larva";55;0
"Unit";"Overlord";"Larva";61;0
"Unit";"Overlord";"Larva";61;0
"Unit";"Queen";"Hatchery";61;2
"Unit";"Queen";"Hatchery";61;2
"Building";"CreepTumorQueen";NA;81;0
"Unit";"Overlord";"Larva";71;0
"Building";"CreepTumorQueen";NA;81;0
"Building";"EvolutionChamber";NA;69;0
"Building";"EvolutionChamber";NA;69;0
"Unit";"Overlord";"Larva";81;0
"Building";"SporeCrawler";NA;81;0
"Building";"Extractor";NA;83;0
"Building";"Extractor";NA;83;0
"Unit";"Queen";"Hatchery";81;2
"Unit";"Queen";"Hatchery";81;2
"Unit";"Zergling";"Larva";94;1
"Unit";"Zergling";"Larva";94;1
"Unit";"Zergling";"Larva";94;1
"Unit";"Zergling";"Larva";94;1
"Unit";"Zergling";"Larva";94;1
"Unit";"Zergling";"Larva";94;1
"Unit";"Zergling";"Larva";94;1
"Unit";"Zergling";"Larva";94;1
"Unit";"Zergling";"Larva";94;1
"Unit";"Zergling";"Larva";94;1
"Unit";"Zergling";"Larva";94;1
"Unit";"Zergling";"Larva";94;1
"Unit";"Zergling";"Larva";94;1
"Unit";"Zergling";"Larva";94;1
"Unit";"Zergling";"Larva";94;1
"Unit";"Zergling";"Larva";94;1
"Unit";"Zergling";"Larva";94;1
"Unit";"Zergling";"Larva";94;1
"Unit";"Zergling";"Larva";94;1
"Unit";"Zergling";"Larva";94;1
"Unit";"Zergling";"Larva";94;1
"Unit";"Zergling";"Larva";94;1
"Building";"CreepTumorQueen";NA;98;0
"Building";"CreepTumorQueen";NA;98;0
"Building";"CreepTumorQueen";NA;98;0
"Building";"CreepTumorQueen";NA;98;0
"Building";"Extractor";NA;114;0
"Building";"Extractor";NA;120;0
"Building";"CreepTumorQueen";NA;126;0
"Building";"CreepTumor";NA;127;0
"Building";"CreepTumor";NA;127;0
"Building";"CreepTumor";NA;127;0
"Building";"CreepTumor";NA;127;0
"Building";"CreepTumorQueen";NA;127;0
"Building";"CreepTumorQueen";NA;127;0
"Building";"CreepTumor";NA;127;0
"Building";"Extractor";NA;127;0
"Unit";"Overlord";"Larva";130;0
"Unit";"Overlord";"Larva";130;0
"Building";"CreepTumorQueen";NA;130;0
"Unit";"Zergling";"Larva";130;1
"Unit";"Zergling";"Larva";130;1
"Unit";"Zergling";"Larva";130;1
"Unit";"Zergling";"Larva";130;1
"Unit";"Zergling";"Larva";130;1
"Unit";"Zergling";"Larva";130;1
"Unit";"Zergling";"Larva";130;1
"Unit";"Zergling";"Larva";130;1
"Unit";"Zergling";"Larva";130;1
"Unit";"Zergling";"Larva";130;1
"Unit";"Zergling";"Larva";130;1
"Unit";"Zergling";"Larva";130;1
"Unit";"Zergling";"Larva";130;1
"Unit";"Zergling";"Larva";130;1
"Unit";"Zergling";"Larva";130;1
"Unit";"Zergling";"Larva";130;1
"Unit";"Zergling";"Larva";130;1
"Unit";"Zergling";"Larva";130;1
"Building";"CreepTumor";NA;134;0
"Unit";"Overlord";"Larva";134;0
"Building";"BanelingNest";NA;130;0
"Building";"CreepTumor";NA;152;0
"Building";"CreepTumor";NA;152;0
"Building";"CreepTumor";NA;152;0
"Building";"CreepTumor";NA;152;0
"Unit";"Zergling";"Larva";152;1
"Unit";"Zergling";"Larva";152;1
"Unit";"Zergling";"Larva";152;1
"Unit";"Zergling";"Larva";152;1
"Unit";"Zergling";"Larva";152;1
"Unit";"Zergling";"Larva";152;1
"Unit";"Zergling";"Larva";152;1
"Unit";"Zergling";"Larva";152;1
"Unit";"Zergling";"Larva";152;1
"Unit";"Zergling";"Larva";152;1
"Building";"CreepTumor";NA;152;0
"Building";"CreepTumor";NA;152;0
"Building";"CreepTumor";NA;152;0
"Building";"CreepTumor";NA;152;0
"Upgrade";"ZergGroundArmorsLevel1";"EvolutionChamber";127;0
"Upgrade";"ZergMeleeWeaponsLevel1";"EvolutionChamber";127;0
"Unit";"Overlord";"Larva";152;0
"Unit";"Baneling";"Zergling";167;0
"Unit";"Baneling";"Zergling";168;0
"Unit";"Baneling";"Zergling";169;0
"Building";"CreepTumor";NA;174;0
"Building";"CreepTumor";NA;174;0
"Building";"CreepTumorQueen";NA;174;0
"Building";"CreepTumor";NA;174;0
"Building";"CreepTumorQueen";NA;174;0
"Building";"CreepTumor";NA;174;0
"Building";"CreepTumorQueen";NA;174;0
"Building";"Hatchery";NA;134;0
"Building";"CreepTumor";NA;174;0
"Building";"CreepTumor";NA;174;0
"Unit";"Baneling";"Zergling";174;0
"Unit";"Baneling";"Zergling";174;0
"Building";"CreepTumor";NA;174;0
"Unit";"Baneling";"Zergling";174;0
"Unit";"Baneling";"Zergling";174;0
"Unit";"Overlord";"Larva";174;0
"Building";"CreepTumor";NA;174;0
"Unit";"Overlord";"Larva";174;0
"Unit";"Overlord";"Larva";174;0
"Unit";"Zergling";"Larva";174;1
"Unit";"Zergling";"Larva";174;1
"Unit";"Zergling";"Larva";174;1
"Unit";"Zergling";"Larva";174;1
"Unit";"Zergling";"Larva";174;1
"Unit";"Zergling";"Larva";174;1
"Unit";"Zergling";"Larva";174;1
"Unit";"Zergling";"Larva";174;1
"Unit";"Zergling";"Larva";174;1
"Unit";"Zergling";"Larva";174;1
"Building";"Spire";NA;152;0
"Building";"CreepTumor";NA;187;0
"Building";"CreepTumor";NA;187;0
"Building";"CreepTumor";NA;187;0
"Building";"CreepTumor";NA;187;0
"Unit";"Overlord";"Larva";187;0
"Building";"Hatchery";NA;156;0
"Building";"CreepTumorQueen";NA;199;0
"Building";"CreepTumorQueen";NA;199;0
"Unit";"Queen";"Hatchery";179;2
"Building";"CreepTumorQueen";NA;199;0
"Unit";"Queen";"Hatchery";183;2
"Unit";"Overlord";"Larva";199;0
"Building";"Extractor";NA;199;0
"Building";"Extractor";NA;199;0
"Unit";"Mutalisk";"Larva";201;2
"Unit";"Mutalisk";"Larva";201;2
"Unit";"Mutalisk";"Larva";201;2
"Unit";"Mutalisk";"Larva";201;2
"Unit";"Mutalisk";"Larva";201;2
"Unit";"Mutalisk";"Larva";201;2
"Unit";"Mutalisk";"Larva";201;2
"Unit";"Mutalisk";"Larva";201;2
"Unit";"Mutalisk";"Larva";201;2
"Unit";"Mutalisk";"Larva";201;2
"Unit";"Mutalisk";"Larva";201;2
"Unit";"Mutalisk";"Larva";201;2
"Unit";"Mutalisk";"Larva";201;2
"Unit";"Mutalisk";"Larva";201;2
"Building";"CreepTumor";NA;231;0
"Unit";"Queen";"Hatchery";203;2
"Unit";"Queen";"Hatchery";203;2
"Unit";"Queen";"Hatchery";203;2
"Unit";"Queen";"Hatchery";203;2
"Unit";"Overlord";"Larva";231;0
"Unit";"Overlord";"Larva";231;0
"Unit";"Overlord";"Larva";231;0
"Unit";"Mutalisk";"Larva";231;2
"Unit";"Mutalisk";"Larva";231;2
"Unit";"Mutalisk";"Larva";231;2
"Unit";"Mutalisk";"Larva";231;2
"Unit";"Mutalisk";"Larva";231;2
"Unit";"Overlord";"Larva";231;0
"Building";"InfestationPit";NA;231;0
"Building";"CreepTumorQueen";NA;239;0
"Upgrade";"ZergGroundArmorsLevel2";"EvolutionChamber";187;0
"Upgrade";"ZergMeleeWeaponsLevel2";"EvolutionChamber";187;0
"Building";"CreepTumorQueen";NA;249;0
"Building";"CreepTumorQueen";NA;249;0
"Unit";"Overlord";"Larva";249;0
"Building";"CreepTumorQueen";NA;249;0
"Unit";"Queen";"Hatchery";239;2
"Building";"CreepTumorQueen";NA;249;0
"Unit";"Zergling";"Larva";249;1
"Unit";"Zergling";"Larva";249;1
"Unit";"Zergling";"Larva";249;1
"Unit";"Zergling";"Larva";249;1
"Unit";"Zergling";"Larva";249;1
"Unit";"Zergling";"Larva";249;1
"Unit";"Zergling";"Larva";249;1
"Unit";"Zergling";"Larva";249;1
"Unit";"Zergling";"Larva";249;1
"Unit";"Zergling";"Larva";249;1
"Unit";"Zergling";"Larva";249;1
"Unit";"Zergling";"Larva";249;1
"Unit";"Zergling";"Larva";249;1
"Unit";"Zergling";"Larva";249;1
"Unit";"Zergling";"Larva";249;1
"Unit";"Zergling";"Larva";249;1
"Unit";"Zergling";"Larva";249;1
"Unit";"Zergling";"Larva";249;1
"Unit";"Zergling";"Larva";249;1
"Unit";"Zergling";"Larva";249;1
"Unit";"Zergling";"Larva";249;1
"Unit";"Zergling";"Larva";249;1
"Unit";"Zergling";"Larva";249;1
"Unit";"Zergling";"Larva";249;1
"Unit";"Zergling";"Larva";249;1
"Unit";"Zergling";"Larva";249;1
"Unit";"Zergling";"Larva";249;1
"Unit";"Zergling";"Larva";249;1
"Unit";"Zergling";"Larva";249;1
"Unit";"Zergling";"Larva";249;1
"Unit";"Zergling";"Larva";249;1
"Unit";"Zergling";"Larva";249;1
"Unit";"Overlord";"Larva";249;0
"Unit";"Mutalisk";"Larva";249;2
"Unit";"Mutalisk";"Larva";249;2
"Unit";"Mutalisk";"Larva";249;2
"Unit";"Mutalisk";"Larva";249;2
"Unit";"Mutalisk";"Larva";249;2
"Unit";"Mutalisk";"Larva";249;2
"Unit";"Mutalisk";"Larva";249;2
"Unit";"Mutalisk";"Larva";249;2
"Unit";"Mutalisk";"Larva";249;2
"Unit";"Overlord";"Larva";249;0
"Unit";"Zergling";"Larva";251;1
"Unit";"Zergling";"Larva";251;1
"Unit";"Zergling";"Larva";251;1
"Unit";"Zergling";"Larva";251;1
"Unit";"Zergling";"Larva";251;1
"Unit";"Zergling";"Larva";251;1
"Unit";"Zergling";"Larva";251;1
"Unit";"Zergling";"Larva";251;1
"Unit";"Zergling";"Larva";251;1
"Unit";"Zergling";"Larva";251;1
"Unit";"Zergling";"Larva";251;1
"Unit";"Zergling";"Larva";251;1
"Unit";"Zergling";"Larva";251;1
"Unit";"Zergling";"Larva";251;1
"Unit";"Zergling";"Larva";251;1
"Unit";"Zergling";"Larva";251;1
"Unit";"Zergling";"Larva";251;1
"Unit";"Zergling";"Larva";251;1
"Unit";"Zergling";"Larva";251;1
"Unit";"Zergling";"Larva";251;1
"Unit";"Baneling";"Zergling";283;0
"Unit";"Baneling";"Zergling";283;0
"Building";"CreepTumor";NA;295;0
"Unit";"Baneling";"Zergling";283;0
"Unit";"Baneling";"Zergling";283;0
"Unit";"Baneling";"Zergling";283;0
"Unit";"Baneling";"Zergling";283;0
"Unit";"Baneling";"Zergling";283;0
"Unit";"Baneling";"Zergling";283;0
"Unit";"Baneling";"Zergling";283;0
"Unit";"Baneling";"Zergling";283;0
"Unit";"Baneling";"Zergling";283;0
"Building";"CreepTumor";NA;301;0
"Building";"CreepTumor";NA;301;0
"Building";"CreepTumor";NA;301;0
"Unit";"Zergling";"Larva";301;1
"Unit";"Zergling";"Larva";301;1
"Unit";"Zergling";"Larva";301;1
"Unit";"Zergling";"Larva";301;1
"Unit";"Zergling";"Larva";301;1
"Unit";"Zergling";"Larva";301;1
"Unit";"Baneling";"Zergling";321;0
"Unit";"Baneling";"Zergling";321;0
"Unit";"Baneling";"Zergling";321;0
"Unit";"Baneling";"Zergling";321;0
"Unit";"Baneling";"Zergling";321;0
"Unit";"Baneling";"Zergling";321;0
"Unit";"Baneling";"Zergling";321;0
"Unit";"Baneling";"Zergling";321;0
"Unit";"Baneling";"Zergling";321;0
"Unit";"Baneling";"Zergling";321;0
"Unit";"Baneling";"Zergling";321;0
"Building";"CreepTumorQueen";NA;327;0
"Unit";"Baneling";"Zergling";328;0
"Unit";"Baneling";"Zergling";328;0
"Unit";"Baneling";"Zergling";328;0
"Unit";"Baneling";"Zergling";328;0
"Unit";"Baneling";"Zergling";328;0
"Unit";"Baneling";"Zergling";328;0
"Unit";"Zergling";"Larva";328;1
"Unit";"Zergling";"Larva";328;1
"Unit";"Zergling";"Larva";328;1
"Unit";"Zergling";"Larva";328;1
"Unit";"Zergling";"Larva";328;1
"Unit";"Zergling";"Larva";328;1
"Unit";"Zergling";"Larva";328;1
"Unit";"Zergling";"Larva";328;1
"Unit";"Zergling";"Larva";328;1
"Unit";"Zergling";"Larva";328;1
"Unit";"Zergling";"Larva";328;1
"Unit";"Zergling";"Larva";328;1
"Unit";"Zergling";"Larva";328;1
"Unit";"Zergling";"Larva";328;1
"Unit";"Zergling";"Larva";328;1
"Unit";"Zergling";"Larva";328;1
"Unit";"Zergling";"Larva";328;1
"Unit";"Zergling";"Larva";328;1
"Unit";"Zergling";"Larva";328;1
"Unit";"Zergling";"Larva";328;1
"Unit";"Zergling";"Larva";328;1
"Unit";"Zergling";"Larva";328;1
"Unit";"Zergling";"Larva";328;1
"Unit";"Zergling";"Larva";328;1
"Unit";"Zergling";"Larva";328;1
"Unit";"Zergling";"Larva";328;1
"Unit";"Zergling";"Larva";328;1
"Unit";"Zergling";"Larva";328;1
"Unit";"Zergling";"Larva";356;1
"Unit";"Zergling";"Larva";356;1
"Unit";"Zergling";"Larva";356;1
"Unit";"Zergling";"Larva";356;1
"Unit";"Zergling";"Larva";356;1
"Unit";"Zergling";"Larva";356;1
"Unit";"Zergling";"Larva";356;1
"Unit";"Zergling";"Larva";356;1
"Unit";"Zergling";"Larva";356;1
"Unit";"Zergling";"Larva";356;1
"Unit";"Zergling";"Larva";356;1
"Unit";"Zergling";"Larva";356;1
"Unit";"Zergling";"Larva";356;1
"Unit";"Zergling";"Larva";356;1
"Unit";"Zergling";"Larva";356;1
"Unit";"Zergling";"Larva";356;1
"Unit";"Zergling";"Larva";356;1
"Unit";"Zergling";"Larva";356;1
"Unit";"Zergling";"Larva";356;1
"Unit";"Zergling";"Larva";356;1
"Unit";"Zergling";"Larva";356;1
"Unit";"Zergling";"Larva";356;1
"Unit";"Zergling";"Larva";356;1
"Unit";"Zergling";"Larva";356;1
"Unit";"Zergling";"Larva";356;1
"Unit";"Zergling";"Larva";356;1
"Unit";"Zergling";"Larva";356;1
"Unit";"Zergling";"Larva";356;1
"Unit";"Zergling";"Larva";356;1
"Unit";"Zergling";"Larva";356;1
"Unit";"Baneling";"Zergling";386;0
"Unit";"Baneling";"Zergling";386;0
"Unit";"Baneling";"Zergling";386;0
"Unit";"Baneling";"Zergling";386;0
"Unit";"Baneling";"Zergling";386;0
"Unit";"Baneling";"Zergling";386;0
"Unit";"Baneling";"Zergling";386;0
"Unit";"Baneling";"Zergling";386;0
"Unit";"Zergling";"Larva";356;1
"Unit";"Zergling";"Larva";356;1
"Unit";"Zergling";"Larva";356;1
"Unit";"Zergling";"Larva";356;1
"Unit";"Zergling";"Larva";356;1
"Unit";"Zergling";"Larva";356;1
"Unit";"Zergling";"Larva";356;1
"Unit";"Zergling";"Larva";356;1
"Unit";"Zergling";"Larva";356;1
"Unit";"Zergling";"Larva";356;1
"Unit";"Zergling";"Larva";356;1
"Unit";"Zergling";"Larva";356;1
"Unit";"Zergling";"Larva";356;1
"Unit";"Zergling";"Larva";356;1
"Unit";"Zergling";"Larva";358;1
"Unit";"Zergling";"Larva";358;1
"Unit";"Zergling";"Larva";358;1
"Unit";"Zergling";"Larva";358;1
"Unit";"Zergling";"Larva";358;1
"Unit";"Zergling";"Larva";358;1
"Unit";"Zergling";"Larva";358;1
"Unit";"Zergling";"Larva";358;1
"Unit";"Zergling";"Larva";358;1
"Unit";"Zergling";"Larva";358;1
"Unit";"Zergling";"Larva";410;1
"Unit";"Zergling";"Larva";410;1
"Unit";"Zergling";"Larva";410;1
"Unit";"Zergling";"Larva";410;1
"Unit";"Zergling";"Larva";410;1
"Unit";"Zergling";"Larva";410;1
"Unit";"Zergling";"Larva";410;1
"Unit";"Zergling";"Larva";410;1
"Unit";"Zergling";"Larva";410;1
"Unit";"Zergling";"Larva";410;1
"Unit";"Zergling";"Larva";410;1
"Unit";"Zergling";"Larva";410;1
"Unit";"Zergling";"Larva";410;1
"Unit";"Zergling";"Larva";410;1
"Unit";"Zergling";"Larva";410;1
"Unit";"Zergling";"Larva";410;1
"Unit";"Zergling";"Larva";410;1
"Unit";"Zergling";"Larva";410;1
"Unit";"Zergling";"Larva";410;1
"Unit";"Zergling";"Larva";410;1
"Unit";"Zergling";"Larva";410;1
"Unit";"Zergling";"Larva";410;1
"Unit";"Zergling";"Larva";410;1
"Unit";"Zergling";"Larva";410;1
"Unit";"Zergling";"Larva";410;1
"Unit";"Zergling";"Larva";410;1
"Unit";"Zergling";"Larva";410;1
"Unit";"Zergling";"Larva";410;1
"Unit";"Zergling";"Larva";410;1
"Unit";"Zergling";"Larva";410;1
"Unit";"Zergling";"Larva";410;1
"Unit";"Zergling";"Larva";410;1
"Unit";"Mutalisk";"Larva";410;2
"Unit";"Mutalisk";"Larva";410;2
"Unit";"Mutalisk";"Larva";410;2
"Unit";"Mutalisk";"Larva";410;2
"Unit";"Mutalisk";"Larva";410;2
"Building";"CreepTumorQueen";NA;443;0
"Building";"CreepTumorQueen";NA;443;0
"Building";"CreepTumor";NA;443;0
"Building";"CreepTumor";NA;443;0
"Building";"CreepTumorQueen";NA;445;0
"Building";"CreepTumorQueen";NA;453;0
"Building";"CreepTumorQueen";NA;453;0
"Unit";"Zergling";"Larva";443;1
"Unit";"Zergling";"Larva";443;1
"Unit";"Zergling";"Larva";443;1
"Unit";"Zergling";"Larva";443;1
"Unit";"Zergling";"Larva";443;1
"Unit";"Zergling";"Larva";443;1
"Unit";"Zergling";"Larva";443;1
"Unit";"Zergling";"Larva";443;1
"Unit";"Zergling";"Larva";443;1
"Unit";"Zergling";"Larva";443;1
"Unit";"Zergling";"Larva";443;1
"Unit";"Zergling";"Larva";443;1
"Unit";"Zergling";"Larva";443;1
"Unit";"Zergling";"Larva";443;1
"Unit";"Zergling";"Larva";443;1
"Unit";"Zergling";"Larva";443;1
"Unit";"Zergling";"Larva";443;1
"Unit";"Zergling";"Larva";443;1
"Unit";"Zergling";"Larva";443;1
"Unit";"Zergling";"Larva";443;1
"Unit";"Zergling";"Larva";443;1
"Unit";"Zergling";"Larva";443;1
"Unit";"Zergling";"Larva";453;1
"Unit";"Zergling";"Larva";453;1
"Unit";"Zergling";"Larva";453;1
"Unit";"Zergling";"Larva";453;1
"Unit";"Zergling";"Larva";453;1
"Unit";"Zergling";"Larva";453;1
"Unit";"Zergling";"Larva";453;1
"Unit";"Zergling";"Larva";453;1
"Unit";"Zergling";"Larva";453;1
"Unit";"Zergling";"Larva";453;1
"Unit";"Zergling";"Larva";453;1
"Unit";"Zergling";"Larva";453;1
"Unit";"Zergling";"Larva";453;1
"Unit";"Zergling";"Larva";453;1
"Unit";"Zergling";"Larva";453;1
"Unit";"Zergling";"Larva";453;1
"Unit";"Zergling";"Larva";453;1
"Unit";"Zergling";"Larva";453;1
"Unit";"Zergling";"Larva";453;1
"Unit";"Zergling";"Larva";453;1
"Unit";"Zergling";"Larva";453;1
"Unit";"Zergling";"Larva";453;1
"Unit";"Zergling";"Larva";453;1
"Unit";"Zergling";"Larva";453;1
"Unit";"Zergling";"Larva";453;1
"Unit";"Zergling";"Larva";453;1
"Building";"UltraliskCavern";NA;442;0
"Unit";"Baneling";"Zergling";475;0
"Unit";"Baneling";"Zergling";475;0
"Unit";"Baneling";"Zergling";475;0
"Unit";"Baneling";"Zergling";475;0
"Unit";"Baneling";"Zergling";475;0
"Unit";"Baneling";"Zergling";475;0
"Unit";"Baneling";"Zergling";475;0
"Unit";"Baneling";"Zergling";475;0
"Unit";"Baneling";"Zergling";475;0
"Unit";"Baneling";"Zergling";475;0
"Unit";"Baneling";"Zergling";475;0
"Unit";"Baneling";"Zergling";475;0
"Unit";"Baneling";"Zergling";475;0
"Unit";"Baneling";"Zergling";475;0
"Unit";"Baneling";"Zergling";475;0
"Unit";"Baneling";"Zergling";475;0
"Unit";"Zergling";"Larva";475;1
"Unit";"Zergling";"Larva";475;1
"Unit";"Zergling";"Larva";475;1
"Unit";"Zergling";"Larva";475;1
"Unit";"Zergling";"Larva";475;1
"Unit";"Zergling";"Larva";475;1
"Unit";"Zergling";"Larva";475;1
"Unit";"Zergling";"Larva";475;1
"Unit";"Zergling";"Larva";475;1
"Unit";"Zergling";"Larva";475;1
"Unit";"Zergling";"Larva";475;1
"Unit";"Zergling";"Larva";475;1
"Unit";"Zergling";"Larva";475;1
"Unit";"Zergling";"Larva";475;1
"Unit";"Zergling";"Larva";475;1
"Unit";"Zergling";"Larva";475;1
"Unit";"Zergling";"Larva";475;1
"Unit";"Zergling";"Larva";475;1
"Unit";"Zergling";"Larva";475;1
"Unit";"Zergling";"Larva";475;1
"Unit";"Zergling";"Larva";475;1
"Unit";"Zergling";"Larva";475;1
"Unit";"Zergling";"Larva";475;1
"Unit";"Zergling";"Larva";475;1
"Unit";"Baneling";"Zergling";501;0
"Unit";"Baneling";"Zergling";501;0
"Unit";"Baneling";"Zergling";501;0
"Unit";"Baneling";"Zergling";501;0
"Unit";"Baneling";"Zergling";501;0
"Unit";"Baneling";"Zergling";501;0
"Unit";"Baneling";"Zergling";501;0
"Unit";"Baneling";"Zergling";501;0
"Unit";"Baneling";"Zergling";525;0
"Building";"Hatchery";NA;453;0
"Unit";"Ultralisk";"Larva";501;6
"Unit";"Ultralisk";"Larva";501;6
"Unit";"Mutalisk";"Larva";525;2
"Unit";"Mutalisk";"Larva";525;2
"Unit";"Mutalisk";"Larva";525;2
"Unit";"Mutalisk";"Larva";525;2
"Unit";"Mutalisk";"Larva";525;2
"Unit";"Mutalisk";"Larva";525;2
"Unit";"Mutalisk";"Larva";525;2
"Unit";"Mutalisk";"Larva";525;2
"Unit";"Mutalisk";"Larva";525;2
"Unit";"Mutalisk";"Larva";525;2
"Unit";"Baneling";"Zergling";558;0
"Unit";"Baneling";"Zergling";558;0
"Unit";"Baneling";"Zergling";558;0
"Unit";"Baneling";"Zergling";558;0
"Building";"CreepTumor";NA;560;0
"Building";"CreepTumor";NA;560;0
"Building";"CreepTumor";NA;560;0
"Building";"CreepTumor";NA;560;0
"Unit";"Ultralisk";"Larva";525;6
"Unit";"Infestor";"Larva";558;2
"Unit";"Infestor";"Larva";558;2
"Building";"CreepTumorQueen";NA;570;0
"Unit";"Ultralisk";"Larva";566;6
"Unit";"Ultralisk";"Larva";566;6
"Upgrade";"ChitinousPlating";"UltraliskCavern";560;0
"Unit";"Zergling";"Larva";570;1
"Unit";"Zergling";"Larva";570;1
"Unit";"Zergling";"Larva";570;1
"Unit";"Zergling";"Larva";570;1
"Unit";"Zergling";"Larva";570;1
"Unit";"Zergling";"Larva";570;1
"Unit";"Zergling";"Larva";570;1
"Unit";"Zergling";"Larva";570;1
"Unit";"Zergling";"Larva";570;1
"Unit";"Zergling";"Larva";570;1
"Unit";"Zergling";"Larva";570;1
"Unit";"Zergling";"Larva";570;1
"Unit";"Zergling";"Larva";570;1
"Unit";"Zergling";"Larva";570;1
"Unit";"Zergling";"Larva";570;1
"Unit";"Zergling";"Larva";570;1
"Unit";"Zergling";"Larva";570;1
"Unit";"Zergling";"Larva";570;1
"Unit";"Zergling";"Larva";570;1
"Unit";"Zergling";"Larva";570;1
"Unit";"Zergling";"Larva";570;1
"Unit";"Zergling";"Larva";570;1
"Unit";"Zergling";"Larva";570;1
"Unit";"Zergling";"Larva";570;1
"Unit";"Zergling";"Larva";570;1
"Unit";"Zergling";"Larva";570;1
"Unit";"Zergling";"Larva";570;1
"Unit";"Zergling";"Larva";570;1
"Unit";"Zergling";"Larva";570;1
"Unit";"Zergling";"Larva";570;1
"Unit";"Zergling";"Larva";570;1
"Unit";"Zergling";"Larva";570;1
"Unit";"Zergling";"Larva";570;1
"Unit";"Zergling";"Larva";570;1
"Unit";"Zergling";"Larva";570;1
"Unit";"Zergling";"Larva";570;1
"Upgrade";"ZergGroundArmorsLevel3";"EvolutionChamber";525;0
"Upgrade";"ZergMeleeWeaponsLevel3";"EvolutionChamber";525;0
"Building";"Extractor";NA;570;0
"Building";"Extractor";NA;570;0
"Unit";"Mutalisk";"Larva";570;2
"Unit";"Mutalisk";"Larva";570;2
"Unit";"Mutalisk";"Larva";570;2
"Unit";"Mutalisk";"Larva";570;2
"Unit";"Mutalisk";"Larva";570;2
"Unit";"Mutalisk";"Larva";570;2
"Unit";"Mutalisk";"Larva";570;2
"Unit";"Mutalisk";"Larva";570;2
"Building";"CreepTumor";NA;626;0
"Building";"SpineCrawler";NA;570;0
"Building";"CreepTumorQueen";NA;626;0
"Building";"SpineCrawler";NA;570;0
"Building";"CreepTumor";NA;626;0
"Unit";"Mutalisk";"Larva";626;2
"Unit";"Mutalisk";"Larva";626;2
"Unit";"Zergling";"Larva";649;1
"Unit";"Zergling";"Larva";649;1
"Unit";"Zergling";"Larva";649;1
"Unit";"Zergling";"Larva";649;1
"Unit";"Zergling";"Larva";649;1
"Unit";"Zergling";"Larva";649;1
"Unit";"Zergling";"Larva";649;1
"Unit";"Zergling";"Larva";649;1
"Unit";"Zergling";"Larva";649;1
"Unit";"Zergling";"Larva";649;1
"Unit";"Zergling";"Larva";649;1
"Unit";"Zergling";"Larva";649;1
"Unit";"Zergling";"Larva";649;1
"Unit";"Zergling";"Larva";649;1
"Unit";"Zergling";"Larva";649;1
"Unit";"Zergling";"Larva";649;1
"Unit";"Zergling";"Larva";649;1
"Unit";"Zergling";"Larva";649;1
"Unit";"Zergling";"Larva";649;1
"Unit";"Zergling";"Larva";649;1
"Unit";"Zergling";"Larva";649;1
"Unit";"Zergling";"Larva";649;1
"Unit";"Zergling";"Larva";649;1
"Unit";"Zergling";"Larva";649;1
"Building";"CreepTumorQueen";NA;649;0
"Unit";"Ultralisk";"Larva";649;6
"Unit";"Ultralisk";"Larva";649;6
"Unit";"Ultralisk";"Larva";649;6
"Unit";"Mutalisk";"Larva";673;2
"Unit";"Mutalisk";"Larva";673;2
"Unit";"Mutalisk";"Larva";673;2
"Unit";"Mutalisk";"Larva";673;2
"Unit";"Mutalisk";"Larva";673;2
"Unit";"Mutalisk";"Larva";673;2
"Unit";"Mutalisk";"Larva";673;2
"Unit";"Mutalisk";"Larva";673;2
"Unit";"Mutalisk";"Larva";673;2
"Unit";"Mutalisk";"Larva";673;2
"Unit";"Zergling";"Larva";693;1
"Unit";"Zergling";"Larva";693;1
"Unit";"Zergling";"Larva";695;1
"Unit";"Zergling";"Larva";695;1
"Unit";"Zergling";"Larva";695;1
"Unit";"Zergling";"Larva";695;1
"Unit";"Zergling";"Larva";695;1
"Unit";"Zergling";"Larva";695;1
"Unit";"Zergling";"Larva";695;1
"Unit";"Zergling";"Larva";695;1
"Unit";"Zergling";"Larva";695;1
"Unit";"Zergling";"Larva";695;1
"Unit";"Zergling";"Larva";695;1
"Unit";"Zergling";"Larva";695;1
"Unit";"Zergling";"Larva";695;1
"Unit";"Zergling";"Larva";695;1
"Unit";"Zergling";"Larva";695;1
"Unit";"Zergling";"Larva";695;1
"Unit";"Zergling";"Larva";699;1
"Unit";"Zergling";"Larva";699;1
"Unit";"Zergling";"Larva";699;1
"Unit";"Zergling";"Larva";699;1
"Unit";"Zergling";"Larva";703;1
"Unit";"Zergling";"Larva";703;1
"Unit";"Zergling";"Larva";703;1
"Unit";"Zergling";"Larva";703;1
"Unit";"Zergling";"Larva";707;1
"Unit";"Zergling";"Larva";707;1
"Unit";"Zergling";"Larva";707;1
"Unit";"Zergling";"Larva";707;1
"Unit";"Zergling";"Larva";711;1
"Unit";"Zergling";"Larva";711;1
"Unit";"Zergling";"Larva";713;1
"Unit";"Zergling";"Larva";713;1
"Unit";"Zergling";"Larva";713;1
"Unit";"Zergling";"Larva";713;1
"Unit";"Baneling";"Zergling";749;0
"Unit";"Baneling";"Zergling";749;0
"Unit";"Baneling";"Zergling";749;0
"Unit";"Baneling";"Zergling";749;0
"Unit";"Baneling";"Zergling";749;0
"Unit";"Overlord";"Larva";749;0
"Unit";"Overlord";"Larva";749;0
"Unit";"Baneling";"Zergling";749;0
"Unit";"Baneling";"Zergling";749;0
"Unit";"Baneling";"Zergling";749;0
"Unit";"Baneling";"Zergling";749;0
"Unit";"Baneling";"Zergling";749;0
"Unit";"Baneling";"Zergling";749;0
"Unit";"Baneling";"Zergling";749;0
"Unit";"Infestor";"Larva";749;2
"Unit";"Infestor";"Larva";749;2
"Unit";"Infestor";"Larva";749;2
"Unit";"Ultralisk";"Larva";749;6
"Unit";"Ultralisk";"Larva";749;6
"Unit";"Infestor";"Larva";749;2
"Building";"SpineCrawler";NA;749;0
"Building";"Hatchery";NA;749;0
"Building";"CreepTumor";NA;769;0
"Building";"Hatchery";NA;749;0
"Unit";"Baneling";"Zergling";769;0
"Unit";"Baneling";"Zergling";769;0
"Unit";"Baneling";"Zergling";769;0
"Unit";"Baneling";"Zergling";769;0
"Unit";"Baneling";"Zergling";769;0
"Unit";"Baneling";"Zergling";769;0
"Unit";"Baneling";"Zergling";769;0
"Unit";"Baneling";"Zergling";769;0
"Unit";"Baneling";"Zergling";769;0
"Unit";"Zergling";"Larva";769;1
"Unit";"Zergling";"Larva";769;1
"Unit";"Zergling";"Larva";769;1
"Unit";"Zergling";"Larva";769;1
"Unit";"Zergling";"Larva";769;1
"Unit";"Zergling";"Larva";769;1
"Unit";"Infestor";"Larva";769;2
"Unit";"Ultralisk";"Larva";769;6
"Unit";"Ultralisk";"Larva";769;6
"Unit";"Mutalisk";"Larva";780;2
"Unit";"Mutalisk";"Larva";780;2
"Unit";"Mutalisk";"Larva";780;2
"Unit";"Mutalisk";"Larva";780;2
"Unit";"Mutalisk";"Larva";780;2
"Unit";"Mutalisk";"Larva";780;2
"Building";"Extractor";NA;794;0
"Building";"Extractor";NA;794;0
"Unit";"Mutalisk";"Larva";806;2
"Unit";"Mutalisk";"Larva";806;2
"Building";"Hatchery";NA;769;0
