"type";"unit_name";"on_building";"total_supply";"supply"
"Unit";"Overlord";"Larva";13;0
"Building";"Extractor";NA;18;0
"Unit";"Overlord";"Larva";22;0
"Building";"SpawningPool";NA;19;0
"Building";"Hatchery";NA;17;0
"Unit";"Zergling";"Larva";22;1
"Unit";"Zergling";"Larva";22;1
"Unit";"Queen";"Hatchery";22;2
"Unit";"Queen";"Hatchery";23;2
"Building";"CreepTumorQueen";NA;35;0
"Unit";"Overlord";"Larva";35;0
"Unit";"Queen";"Hatchery";31;2
"Unit";"Overlord";"Larva";35;0
"Building";"CreepTumor";NA;38;0
"Building";"CreepTumorQueen";NA;40;0
"Building";"CreepTumorQueen";NA;47;0
"Unit";"Overlord";"Larva";46;0
"Unit";"Queen";"Hatchery";41;2
"Building";"CreepTumor";NA;47;0
"Building";"CreepTumorQueen";NA;48;0
"Building";"Hatchery";NA;35;0
"Unit";"Overlord";"Larva";50;0
"Unit";"Overlord";"Larva";50;0
"Building";"CreepTumor";NA;50;0
"Building";"EvolutionChamber";NA;50;0
"Building";"EvolutionChamber";NA;50;0
"Building";"CreepTumor";NA;50;0
"Building";"CreepTumorQueen";NA;55;0
"Unit";"Queen";"Hatchery";50;2
"Unit";"Queen";"Hatchery";50;2
"Unit";"Queen";"Hatchery";50;2
"Unit";"Overlord";"Larva";61;0
"Building";"CreepTumor";NA;67;0
"Unit";"Zergling";"Larva";67;1
"Unit";"Zergling";"Larva";67;1
"Unit";"Zergling";"Larva";67;1
"Unit";"Zergling";"Larva";67;1
"Unit";"Zergling";"Larva";67;1
"Unit";"Zergling";"Larva";67;1
"Building";"CreepTumor";NA;73;0
"Building";"CreepTumor";NA;73;0
"Building";"CreepTumor";NA;73;0
"Unit";"Zergling";"Larva";73;1
"Unit";"Zergling";"Larva";73;1
"Unit";"Zergling";"Larva";73;1
"Unit";"Zergling";"Larva";73;1
"Unit";"Zergling";"Larva";73;1
"Unit";"Zergling";"Larva";73;1
"Unit";"Zergling";"Larva";77;1
"Unit";"Zergling";"Larva";77;1
"Unit";"Zergling";"Larva";77;1
"Unit";"Zergling";"Larva";77;1
"Unit";"Zergling";"Larva";81;1
"Unit";"Zergling";"Larva";81;1
"Building";"CreepTumor";NA;85;0
"Building";"CreepTumor";NA;85;0
"Building";"CreepTumor";NA;89;0
"Building";"CreepTumor";NA;89;0
"Unit";"Zergling";"Larva";89;1
"Unit";"Zergling";"Larva";89;1
"Unit";"Zergling";"Larva";89;1
"Unit";"Zergling";"Larva";89;1
"Unit";"Zergling";"Larva";89;1
"Unit";"Zergling";"Larva";89;1
"Unit";"Zergling";"Larva";89;1
"Unit";"Zergling";"Larva";89;1
"Unit";"Zergling";"Larva";89;1
"Unit";"Zergling";"Larva";89;1
"Unit";"Zergling";"Larva";89;1
"Unit";"Zergling";"Larva";89;1
"Unit";"Zergling";"Larva";89;1
"Unit";"Zergling";"Larva";89;1
"Unit";"Overlord";"Larva";91;0
"Unit";"Overlord";"Larva";91;0
"Unit";"Overlord";"Larva";91;0
"Unit";"Overlord";"Larva";91;0
"Unit";"Overlord";"Larva";105;0
"Unit";"Overlord";"Larva";105;0
"Unit";"Overlord";"Larva";105;0
"Building";"CreepTumor";NA;105;0
"Unit";"Queen";"Hatchery";105;2
"Building";"CreepTumorQueen";NA;120;0
"Building";"Extractor";NA;105;0
"Building";"Extractor";NA;105;0
"Building";"Extractor";NA;105;0
"Building";"Extractor";NA;105;0
"Building";"Extractor";NA;105;0
"Unit";"Queen";"Hatchery";105;2
"Upgrade";"ZergGroundArmorsLevel1";"EvolutionChamber";79;0
"Upgrade";"ZergMeleeWeaponsLevel1";"EvolutionChamber";79;0
"Building";"BanelingNest";NA;105;0
"Building";"Hatchery";NA;91;0
"Building";"Hatchery";NA;105;0
"Unit";"Queen";"Hatchery";122;2
"Building";"CreepTumor";NA;132;0
"Building";"CreepTumor";NA;132;0
"Unit";"Zergling";"Larva";131;1
"Unit";"Zergling";"Larva";131;1
"Unit";"Overlord";"Larva";130;0
"Unit";"Overlord";"Larva";130;0
"Unit";"Zergling";"Larva";132;1
"Unit";"Zergling";"Larva";132;1
"Unit";"Zergling";"Larva";132;1
"Unit";"Zergling";"Larva";132;1
"Unit";"Zergling";"Larva";132;1
"Unit";"Zergling";"Larva";132;1
"Unit";"Queen";"Hatchery";124;2
"Unit";"Zergling";"Larva";132;1
"Unit";"Zergling";"Larva";132;1
"Unit";"Zergling";"Larva";132;1
"Unit";"Zergling";"Larva";132;1
"Unit";"Zergling";"Larva";132;1
"Unit";"Zergling";"Larva";132;1
"Unit";"Zergling";"Larva";132;1
"Unit";"Zergling";"Larva";132;1
"Unit";"Zergling";"Larva";132;1
"Unit";"Zergling";"Larva";132;1
"Building";"CreepTumorQueen";NA;134;0
"Building";"CreepTumorQueen";NA;144;0
"Unit";"Baneling";"Zergling";144;0
"Unit";"Baneling";"Zergling";144;0
"Unit";"Baneling";"Zergling";144;0
"Unit";"Overlord";"Larva";144;0
"Unit";"Overlord";"Larva";144;0
"Unit";"Baneling";"Zergling";154;0
"Building";"CreepTumor";NA;154;0
"Unit";"Baneling";"Zergling";154;0
"Unit";"Baneling";"Zergling";154;0
"Building";"CreepTumor";NA;154;0
"Building";"HydraliskDen";NA;154;0
"Building";"CreepTumor";NA;168;0
"Building";"CreepTumorQueen";NA;168;0
"Building";"CreepTumorQueen";NA;168;0
"Building";"InfestationPit";NA;154;0
"Building";"Extractor";NA;172;0
"Building";"Extractor";NA;172;0
"Building";"CreepTumor";NA;172;0
"Unit";"Hydralisk";"Larva";172;2
"Unit";"Hydralisk";"Larva";172;2
"Unit";"Hydralisk";"Larva";172;2
"Unit";"Hydralisk";"Larva";172;2
"Unit";"Hydralisk";"Larva";172;2
"Unit";"Hydralisk";"Larva";172;2
"Unit";"Hydralisk";"Larva";172;2
"Unit";"Hydralisk";"Larva";172;2
"Building";"CreepTumor";NA;172;0
"Building";"CreepTumor";NA;172;0
"Unit";"Zergling";"Larva";172;1
"Unit";"Zergling";"Larva";172;1
"Unit";"Overlord";"Larva";172;0
"Unit";"Overlord";"Larva";172;0
"Unit";"Zergling";"Larva";172;1
"Unit";"Zergling";"Larva";172;1
"Unit";"Zergling";"Larva";172;1
"Unit";"Zergling";"Larva";172;1
"Unit";"Zergling";"Larva";172;1
"Unit";"Zergling";"Larva";172;1
"Unit";"Zergling";"Larva";172;1
"Unit";"Zergling";"Larva";172;1
"Unit";"Zergling";"Larva";172;1
"Unit";"Zergling";"Larva";172;1
"Unit";"Zergling";"Larva";172;1
"Unit";"Zergling";"Larva";172;1
"Unit";"Zergling";"Larva";172;1
"Unit";"Zergling";"Larva";172;1
"Unit";"Zergling";"Larva";172;1
"Unit";"Zergling";"Larva";172;1
"Building";"CreepTumorQueen";NA;206;0
"Building";"CreepTumorQueen";NA;206;0
"Unit";"Baneling";"Zergling";206;0
"Unit";"Baneling";"Zergling";206;0
"Unit";"Baneling";"Zergling";206;0
"Unit";"Baneling";"Zergling";206;0
"Building";"CreepTumor";NA;207;0
"Unit";"Hydralisk";"Larva";206;2
"Unit";"Hydralisk";"Larva";206;2
"Unit";"Hydralisk";"Larva";206;2
"Unit";"Hydralisk";"Larva";206;2
"Unit";"Overlord";"Larva";207;0
"Unit";"Overlord";"Larva";207;0
"Unit";"Baneling";"Zergling";207;0
"Building";"CreepTumor";NA;207;0
"Unit";"Baneling";"Zergling";207;0
"Unit";"Baneling";"Zergling";207;0
"Unit";"Baneling";"Zergling";207;0
"Unit";"Baneling";"Zergling";207;0
"Unit";"Baneling";"Zergling";207;0
"Unit";"Baneling";"Zergling";207;0
"Unit";"Baneling";"Zergling";207;0
"Unit";"Baneling";"Zergling";207;0
"Unit";"Baneling";"Zergling";207;0
"Unit";"Baneling";"Zergling";207;0
"Unit";"Baneling";"Zergling";207;0
"Unit";"Baneling";"Zergling";207;0
"Unit";"Baneling";"Zergling";207;0
"Unit";"Baneling";"Zergling";207;0
"Upgrade";"EvolveMuscularAugments";"HydraliskDen";172;0
"Building";"CreepTumor";NA;208;0
"Unit";"Zergling";"Larva";208;1
"Unit";"Zergling";"Larva";208;1
"Unit";"Zergling";"Larva";208;1
"Unit";"Zergling";"Larva";208;1
"Unit";"Zergling";"Larva";208;1
"Unit";"Zergling";"Larva";208;1
"Unit";"Zergling";"Larva";208;1
"Unit";"Zergling";"Larva";208;1
"Unit";"Zergling";"Larva";208;1
"Unit";"Zergling";"Larva";208;1
"Unit";"Zergling";"Larva";208;1
"Unit";"Zergling";"Larva";208;1
"Unit";"Zergling";"Larva";208;1
"Unit";"Zergling";"Larva";208;1
"Unit";"Zergling";"Larva";208;1
"Unit";"Zergling";"Larva";208;1
"Unit";"Zergling";"Larva";208;1
"Unit";"Zergling";"Larva";208;1
"Unit";"Zergling";"Larva";208;1
"Unit";"Zergling";"Larva";208;1
"Unit";"Zergling";"Larva";208;1
"Unit";"Zergling";"Larva";208;1
"Unit";"Zergling";"Larva";208;1
"Unit";"Zergling";"Larva";208;1
"Unit";"Zergling";"Larva";208;1
"Unit";"Zergling";"Larva";208;1
"Building";"CreepTumor";NA;210;0
"Building";"CreepTumorQueen";NA;216;0
"Building";"CreepTumor";NA;216;0
"Building";"CreepTumor";NA;216;0
"Building";"CreepTumor";NA;216;0
"Building";"CreepTumor";NA;216;0
"Building";"Hatchery";NA;172;0
"Upgrade";"ZergGroundArmorsLevel2";"EvolutionChamber";168;0
"Upgrade";"ZergMeleeWeaponsLevel2";"EvolutionChamber";168;0
"Unit";"Zergling";"Larva";242;1
"Unit";"Zergling";"Larva";242;1
"Unit";"Zergling";"Larva";242;1
"Unit";"Zergling";"Larva";242;1
"Unit";"Zergling";"Larva";242;1
"Unit";"Zergling";"Larva";242;1
"Unit";"Zergling";"Larva";242;1
"Unit";"Zergling";"Larva";242;1
"Unit";"Zergling";"Larva";242;1
"Unit";"Zergling";"Larva";242;1
"Unit";"Zergling";"Larva";242;1
"Unit";"Zergling";"Larva";242;1
"Unit";"Zergling";"Larva";242;1
"Unit";"Zergling";"Larva";242;1
"Unit";"Zergling";"Larva";242;1
"Unit";"Zergling";"Larva";242;1
"Unit";"Zergling";"Larva";242;1
"Unit";"Zergling";"Larva";242;1
"Unit";"Zergling";"Larva";242;1
"Unit";"Zergling";"Larva";242;1
"Unit";"Zergling";"Larva";242;1
"Unit";"Zergling";"Larva";242;1
"Unit";"Zergling";"Larva";242;1
"Unit";"Zergling";"Larva";242;1
"Unit";"Zergling";"Larva";242;1
"Unit";"Zergling";"Larva";242;1
"Unit";"Zergling";"Larva";242;1
"Unit";"Zergling";"Larva";242;1
"Unit";"Zergling";"Larva";242;1
"Unit";"Zergling";"Larva";242;1
"Unit";"Zergling";"Larva";242;1
"Unit";"Zergling";"Larva";242;1
"Unit";"Zergling";"Larva";242;1
"Unit";"Zergling";"Larva";242;1
"Unit";"Zergling";"Larva";242;1
"Unit";"Zergling";"Larva";242;1
"Unit";"Zergling";"Larva";242;1
"Unit";"Zergling";"Larva";242;1
"Unit";"Zergling";"Larva";242;1
"Unit";"Zergling";"Larva";242;1
"Unit";"Zergling";"Larva";242;1
"Unit";"Zergling";"Larva";242;1
"Unit";"Zergling";"Larva";242;1
"Unit";"Zergling";"Larva";242;1
"Building";"Spire";NA;206;0
"Building";"CreepTumorQueen";NA;286;0
"Building";"UltraliskCavern";NA;242;0
"Unit";"Zergling";"Larva";286;1
"Unit";"Zergling";"Larva";286;1
"Unit";"Zergling";"Larva";286;1
"Unit";"Zergling";"Larva";286;1
"Unit";"Zergling";"Larva";286;1
"Unit";"Zergling";"Larva";286;1
"Unit";"Zergling";"Larva";286;1
"Unit";"Zergling";"Larva";286;1
"Unit";"Zergling";"Larva";286;1
"Unit";"Zergling";"Larva";286;1
"Unit";"Zergling";"Larva";286;1
"Unit";"Zergling";"Larva";286;1
"Unit";"Zergling";"Larva";286;1
"Unit";"Zergling";"Larva";286;1
"Unit";"Zergling";"Larva";286;1
"Unit";"Zergling";"Larva";286;1
"Unit";"Zergling";"Larva";286;1
"Unit";"Zergling";"Larva";286;1
"Unit";"Zergling";"Larva";286;1
"Unit";"Zergling";"Larva";286;1
"Unit";"Zergling";"Larva";286;1
"Unit";"Zergling";"Larva";286;1
"Unit";"Zergling";"Larva";286;1
"Unit";"Zergling";"Larva";286;1
"Unit";"Zergling";"Larva";286;1
"Unit";"Zergling";"Larva";286;1
"Unit";"Zergling";"Larva";286;1
"Unit";"Zergling";"Larva";286;1
"Unit";"Zergling";"Larva";286;1
"Unit";"Zergling";"Larva";286;1
"Unit";"Zergling";"Larva";286;1
"Unit";"Zergling";"Larva";286;1
"Unit";"Zergling";"Larva";286;1
"Unit";"Zergling";"Larva";286;1
"Unit";"Zergling";"Larva";286;1
"Unit";"Zergling";"Larva";286;1
"Unit";"Zergling";"Larva";286;1
"Unit";"Zergling";"Larva";286;1
"Unit";"Zergling";"Larva";286;1
"Unit";"Zergling";"Larva";286;1
"Unit";"Zergling";"Larva";286;1
"Unit";"Zergling";"Larva";286;1
"Unit";"Zergling";"Larva";286;1
"Unit";"Zergling";"Larva";286;1
"Unit";"Zergling";"Larva";286;1
"Unit";"Zergling";"Larva";286;1
"Unit";"Zergling";"Larva";286;1
"Unit";"Zergling";"Larva";286;1
"Unit";"Zergling";"Larva";286;1
"Unit";"Zergling";"Larva";286;1
"Unit";"Zergling";"Larva";286;1
"Unit";"Zergling";"Larva";286;1
"Unit";"Zergling";"Larva";286;1
"Unit";"Zergling";"Larva";286;1
"Unit";"Zergling";"Larva";286;1
"Unit";"Zergling";"Larva";286;1
"Building";"CreepTumorQueen";NA;342;0
"Building";"CreepTumor";NA;342;0
"Building";"CreepTumor";NA;342;0
"Building";"CreepTumorQueen";NA;342;0
"Building";"CreepTumorQueen";NA;342;0
"Unit";"Viper";"Larva";324;3
"Unit";"Viper";"Larva";324;3
"Building";"CreepTumor";NA;342;0
"Unit";"Viper";"Larva";324;3
"Building";"CreepTumorQueen";NA;342;0
"Unit";"Hydralisk";"Larva";334;2
"Unit";"Hydralisk";"Larva";334;2
"Unit";"Hydralisk";"Larva";334;2
"Unit";"Hydralisk";"Larva";334;2
"Building";"CreepTumorQueen";NA;342;0
"Building";"CreepTumorQueen";NA;351;0
"Building";"Extractor";NA;353;0
"Building";"Extractor";NA;359;0
"Unit";"Baneling";"Zergling";364;0
"Unit";"Baneling";"Zergling";365;0
"Unit";"Baneling";"Zergling";366;0
"Unit";"Baneling";"Zergling";367;0
"Unit";"Baneling";"Zergling";367;0
"Unit";"Baneling";"Zergling";367;0
"Unit";"Baneling";"Zergling";368;0
"Unit";"Baneling";"Zergling";368;0
"Unit";"Baneling";"Zergling";368;0
"Unit";"Baneling";"Zergling";368;0
"Unit";"Baneling";"Zergling";368;0
"Unit";"Baneling";"Zergling";368;0
"Unit";"Baneling";"Zergling";368;0
"Building";"Spire";NA;324;0
"Unit";"Hydralisk";"Larva";368;2
"Unit";"Hydralisk";"Larva";368;2
"Unit";"Hydralisk";"Larva";368;2
"Unit";"Hydralisk";"Larva";368;2
"Upgrade";"ChitinousPlating";"UltraliskCavern";342;0
"Building";"CreepTumor";NA;368;0
"Building";"CreepTumor";NA;368;0
"Building";"CreepTumor";NA;376;0
"Building";"CreepTumor";NA;376;0
"Building";"CreepTumor";NA;376;0
"Building";"CreepTumor";NA;376;0
"Building";"CreepTumor";NA;376;0
"Building";"CreepTumor";NA;376;0
"Building";"CreepTumor";NA;376;0
"Building";"CreepTumor";NA;376;0
"Unit";"Zergling";"Larva";376;1
"Unit";"Zergling";"Larva";376;1
"Unit";"Zergling";"Larva";376;1
"Unit";"Zergling";"Larva";376;1
"Unit";"Zergling";"Larva";376;1
"Unit";"Zergling";"Larva";376;1
"Unit";"Zergling";"Larva";376;1
"Unit";"Zergling";"Larva";376;1
"Unit";"Zergling";"Larva";376;1
"Unit";"Zergling";"Larva";376;1
"Unit";"Zergling";"Larva";376;1
"Unit";"Zergling";"Larva";376;1
"Unit";"Zergling";"Larva";376;1
"Unit";"Zergling";"Larva";376;1
"Unit";"Zergling";"Larva";376;1
"Unit";"Zergling";"Larva";376;1
"Unit";"Zergling";"Larva";376;1
"Unit";"Zergling";"Larva";376;1
"Unit";"Zergling";"Larva";376;1
"Unit";"Zergling";"Larva";376;1
"Unit";"Zergling";"Larva";376;1
"Unit";"Zergling";"Larva";376;1
"Upgrade";"ZergGroundArmorsLevel3";"EvolutionChamber";286;0
"Upgrade";"ZergMeleeWeaponsLevel3";"EvolutionChamber";286;0
"Unit";"Ultralisk";"Larva";376;6
"Unit";"Ultralisk";"Larva";376;6
"Unit";"Ultralisk";"Larva";376;6
"Unit";"Ultralisk";"Larva";376;6
"Unit";"Zergling";"Larva";398;1
"Unit";"Zergling";"Larva";398;1
"Unit";"Zergling";"Larva";398;1
"Unit";"Zergling";"Larva";398;1
"Unit";"Zergling";"Larva";398;1
"Unit";"Zergling";"Larva";398;1
"Unit";"Zergling";"Larva";398;1
"Unit";"Zergling";"Larva";398;1
"Unit";"Zergling";"Larva";398;1
"Unit";"Zergling";"Larva";398;1
"Unit";"Zergling";"Larva";398;1
"Unit";"Zergling";"Larva";398;1
"Unit";"Zergling";"Larva";398;1
"Unit";"Zergling";"Larva";398;1
"Unit";"Zergling";"Larva";398;1
"Unit";"Zergling";"Larva";398;1
"Unit";"Zergling";"Larva";398;1
"Unit";"Zergling";"Larva";398;1
"Unit";"Zergling";"Larva";398;1
"Unit";"Zergling";"Larva";398;1
"Unit";"Zergling";"Larva";398;1
"Unit";"Zergling";"Larva";398;1
"Unit";"Zergling";"Larva";398;1
"Unit";"Zergling";"Larva";398;1
"Unit";"Zergling";"Larva";398;1
"Unit";"Zergling";"Larva";398;1
"Unit";"Zergling";"Larva";398;1
"Unit";"Zergling";"Larva";398;1
"Unit";"Zergling";"Larva";398;1
"Unit";"Zergling";"Larva";398;1
"Unit";"Zergling";"Larva";398;1
"Unit";"Zergling";"Larva";398;1
"Unit";"Zergling";"Larva";398;1
"Unit";"Zergling";"Larva";398;1
"Unit";"Zergling";"Larva";398;1
"Unit";"Zergling";"Larva";398;1
"Unit";"Zergling";"Larva";398;1
"Unit";"Zergling";"Larva";398;1
"Unit";"Zergling";"Larva";398;1
"Unit";"Zergling";"Larva";398;1
"Unit";"Zergling";"Larva";398;1
"Unit";"Zergling";"Larva";398;1
"Building";"CreepTumor";NA;398;0
"Building";"Extractor";NA;398;0
"Building";"Extractor";NA;398;0
"Building";"CreepTumor";NA;422;0
"Building";"CreepTumor";NA;422;0
"Building";"CreepTumor";NA;422;0
"Building";"CreepTumor";NA;422;0
"Building";"CreepTumor";NA;422;0
"Building";"Hatchery";NA;368;0
"Unit";"Baneling";"Zergling";464;0
"Unit";"Baneling";"Zergling";464;0
"Unit";"Baneling";"Zergling";464;0
"Unit";"Baneling";"Zergling";464;0
"Unit";"Baneling";"Zergling";464;0
"Unit";"Baneling";"Zergling";464;0
"Unit";"Baneling";"Zergling";464;0
"Unit";"Baneling";"Zergling";464;0
"Unit";"Baneling";"Zergling";464;0
"Unit";"Baneling";"Zergling";464;0
"Unit";"Baneling";"Zergling";464;0
"Unit";"Baneling";"Zergling";464;0
"Unit";"Baneling";"Zergling";464;0
"Unit";"Baneling";"Zergling";464;0
"Unit";"Baneling";"Zergling";464;0
"Unit";"Baneling";"Zergling";464;0
"Unit";"Baneling";"Zergling";464;0
"Unit";"Baneling";"Zergling";464;0
"Unit";"Baneling";"Zergling";464;0
"Unit";"Baneling";"Zergling";464;0
"Unit";"Baneling";"Zergling";464;0
"Unit";"Baneling";"Zergling";464;0
"Unit";"Baneling";"Zergling";464;0
"Unit";"Baneling";"Zergling";464;0
"Unit";"Baneling";"Zergling";464;0
"Unit";"Baneling";"Zergling";464;0
"Unit";"Baneling";"Zergling";464;0
"Building";"CreepTumor";NA;464;0
"Building";"CreepTumor";NA;464;0
"Building";"CreepTumor";NA;464;0
"Building";"CreepTumor";NA;464;0
"Building";"CreepTumor";NA;464;0
"Building";"CreepTumor";NA;464;0
"Building";"CreepTumor";NA;464;0
"Building";"CreepTumor";NA;464;0
"Building";"CreepTumor";NA;464;0
"Unit";"Baneling";"Zergling";464;0
"Unit";"Baneling";"Zergling";464;0
"Unit";"Baneling";"Zergling";464;0
"Unit";"Baneling";"Zergling";464;0
"Unit";"Baneling";"Zergling";464;0
"Unit";"Baneling";"Zergling";464;0
"Unit";"Baneling";"Zergling";464;0
"Upgrade";"Burrow";"Hatchery";464;0
"Unit";"Overlord";"Larva";464;0
"Unit";"Overlord";"Larva";464;0
"Unit";"Overlord";"Larva";464;0
"Unit";"Overlord";"Larva";464;0
"Unit";"Overlord";"Larva";464;0
"Unit";"Overlord";"Larva";464;0
"Unit";"Overlord";"Larva";464;0
"Unit";"Overlord";"Larva";464;0
"Building";"CreepTumor";NA;464;0
"Building";"CreepTumor";NA;464;0
"Building";"CreepTumor";NA;464;0
"Unit";"Viper";"Larva";464;3
"Unit";"Viper";"Larva";464;3
"Unit";"Viper";"Larva";464;3
"Unit";"Viper";"Larva";464;3
"Unit";"Corruptor";"Larva";464;2
"Unit";"Corruptor";"Larva";464;2
"Unit";"Corruptor";"Larva";464;2
"Unit";"Corruptor";"Larva";464;2
"Unit";"Corruptor";"Larva";464;2
"Unit";"Corruptor";"Larva";464;2
"Unit";"Zergling";"Larva";464;1
"Unit";"Zergling";"Larva";464;1
"Unit";"Zergling";"Larva";464;1
"Unit";"Zergling";"Larva";464;1
"Unit";"Zergling";"Larva";464;1
"Unit";"Zergling";"Larva";464;1
"Unit";"Zergling";"Larva";464;1
"Unit";"Zergling";"Larva";464;1
"Unit";"Zergling";"Larva";464;1
"Unit";"Zergling";"Larva";464;1
"Unit";"Zergling";"Larva";464;1
"Unit";"Zergling";"Larva";464;1
"Unit";"Zergling";"Larva";467;1
"Unit";"Zergling";"Larva";467;1
"Unit";"Zergling";"Larva";467;1
"Unit";"Zergling";"Larva";467;1
"Unit";"Zergling";"Larva";467;1
"Unit";"Zergling";"Larva";467;1
"Building";"CreepTumor";NA;490;0
"Unit";"Corruptor";"Larva";506;2
"Unit";"Baneling";"Zergling";506;0
"Unit";"Baneling";"Zergling";506;0
"Unit";"Baneling";"Zergling";506;0
"Unit";"Baneling";"Zergling";506;0
"Unit";"Baneling";"Zergling";506;0
"Unit";"Baneling";"Zergling";506;0
"Unit";"Baneling";"Zergling";506;0
"Upgrade";"ZergMissileWeaponsLevel1";"EvolutionChamber";506;0
"Unit";"Zergling";"Larva";508;1
"Unit";"Zergling";"Larva";508;1
"Unit";"Corruptor";"Larva";508;2
"Unit";"Zergling";"Larva";510;1
"Unit";"Zergling";"Larva";510;1
"Unit";"Zergling";"Larva";510;1
"Unit";"Zergling";"Larva";510;1
"Unit";"Zergling";"Larva";510;1
"Unit";"Zergling";"Larva";510;1
"Unit";"Zergling";"Larva";510;1
"Unit";"Zergling";"Larva";510;1
"Unit";"Zergling";"Larva";510;1
"Unit";"Zergling";"Larva";510;1
"Unit";"Zergling";"Larva";510;1
"Unit";"Zergling";"Larva";510;1
"Unit";"Zergling";"Larva";510;1
"Unit";"Zergling";"Larva";510;1
"Unit";"Zergling";"Larva";510;1
"Unit";"Zergling";"Larva";510;1
"Unit";"Zergling";"Larva";510;1
"Unit";"Zergling";"Larva";510;1
"Unit";"Zergling";"Larva";510;1
"Unit";"Zergling";"Larva";510;1
"Unit";"Zergling";"Larva";510;1
"Unit";"Zergling";"Larva";510;1
"Unit";"Zergling";"Larva";510;1
"Unit";"Zergling";"Larva";510;1
"Unit";"Zergling";"Larva";510;1
"Unit";"Zergling";"Larva";510;1
"Unit";"Zergling";"Larva";510;1
"Unit";"Zergling";"Larva";510;1
"Unit";"Zergling";"Larva";510;1
"Unit";"Zergling";"Larva";510;1
"Unit";"Zergling";"Larva";510;1
"Unit";"Zergling";"Larva";510;1
"Unit";"Zergling";"Larva";510;1
"Unit";"Zergling";"Larva";510;1
"Unit";"Zergling";"Larva";510;1
"Unit";"Zergling";"Larva";510;1
"Unit";"Zergling";"Larva";510;1
"Unit";"Zergling";"Larva";510;1
"Unit";"Zergling";"Larva";510;1
"Unit";"Zergling";"Larva";510;1
"Unit";"Zergling";"Larva";510;1
"Unit";"Zergling";"Larva";510;1
"Unit";"Zergling";"Larva";510;1
"Unit";"Zergling";"Larva";510;1
"Unit";"Zergling";"Larva";510;1
"Unit";"Zergling";"Larva";510;1
"Unit";"Zergling";"Larva";510;1
"Unit";"Zergling";"Larva";510;1
"Unit";"Zergling";"Larva";510;1
"Unit";"Zergling";"Larva";510;1
"Unit";"Zergling";"Larva";510;1
"Unit";"Zergling";"Larva";510;1
"Unit";"Zergling";"Larva";510;1
"Unit";"Zergling";"Larva";510;1
"Unit";"Zergling";"Larva";510;1
"Unit";"Zergling";"Larva";510;1
"Unit";"Zergling";"Larva";510;1
"Unit";"Zergling";"Larva";510;1
"Unit";"Zergling";"Larva";510;1
"Unit";"Zergling";"Larva";510;1
"Unit";"Zergling";"Larva";510;1
"Unit";"Zergling";"Larva";510;1
"Unit";"Zergling";"Larva";510;1
"Unit";"Zergling";"Larva";510;1
"Unit";"Zergling";"Larva";510;1
"Unit";"Zergling";"Larva";510;1
"Unit";"Zergling";"Larva";510;1
"Unit";"Zergling";"Larva";510;1
"Unit";"Zergling";"Larva";510;1
"Unit";"Zergling";"Larva";510;1
"Unit";"Zergling";"Larva";510;1
"Unit";"Zergling";"Larva";510;1
"Unit";"Zergling";"Larva";510;1
"Unit";"Zergling";"Larva";510;1
"Unit";"Zergling";"Larva";510;1
"Unit";"Zergling";"Larva";510;1
"Unit";"Zergling";"Larva";510;1
"Unit";"Zergling";"Larva";510;1
"Unit";"Zergling";"Larva";510;1
"Unit";"Zergling";"Larva";510;1
"Unit";"Zergling";"Larva";512;1
"Unit";"Zergling";"Larva";512;1
"Unit";"Zergling";"Larva";512;1
"Unit";"Zergling";"Larva";512;1
"Unit";"Zergling";"Larva";512;1
"Unit";"Zergling";"Larva";512;1
"Unit";"Zergling";"Larva";512;1
"Unit";"Zergling";"Larva";512;1
"Unit";"Zergling";"Larva";512;1
"Unit";"Zergling";"Larva";512;1
