"type";"unit_name";"on_building";"total_supply";"supply"
"Unit";"Overlord";"Larva";13;0
"Building";"Extractor";NA;18;0
"Unit";"Overlord";"Larva";21;0
"Building";"SpawningPool";NA;19;0
"Building";"Hatchery";NA;17;0
"Unit";"Zergling";"Larva";22;1
"Unit";"Zergling";"Larva";22;1
"Unit";"Zergling";"Larva";23;1
"Unit";"Zergling";"Larva";23;1
"Unit";"Queen";"Hatchery";22;2
"Unit";"Queen";"Hatchery";23;2
"Building";"CreepTumorQueen";NA;34;0
"Unit";"Overlord";"Larva";34;0
"Unit";"Queen";"Hatchery";34;2
"Building";"CreepTumorQueen";NA;37;0
"Building";"CreepTumorQueen";NA;39;0
"Building";"CreepTumor";NA;39;0
"Building";"Hatchery";NA;30;0
"Unit";"Overlord";"Larva";43;0
"Unit";"Queen";"Hatchery";39;2
"Building";"CreepTumor";NA;49;0
"Building";"CreepTumor";NA;49;0
"Building";"CreepTumor";NA;49;0
"Unit";"Overlord";"Larva";49;0
"Unit";"Zergling";"Larva";49;1
"Unit";"Zergling";"Larva";49;1
"Unit";"Zergling";"Larva";49;1
"Unit";"Zergling";"Larva";49;1
"Unit";"Zergling";"Larva";49;1
"Unit";"Zergling";"Larva";49;1
"Building";"BanelingNest";NA;43;0
"Building";"CreepTumorQueen";NA;54;0
"Unit";"Queen";"Hatchery";48;2
"Unit";"Overlord";"Larva";54;0
"Unit";"Queen";"Hatchery";51;2
"Unit";"Zergling";"Larva";62;1
"Unit";"Zergling";"Larva";62;1
"Unit";"Zergling";"Larva";62;1
"Unit";"Zergling";"Larva";62;1
"Unit";"Overlord";"Larva";62;0
"Unit";"Zergling";"Larva";62;1
"Unit";"Zergling";"Larva";62;1
"Unit";"Zergling";"Larva";62;1
"Unit";"Zergling";"Larva";62;1
"Building";"CreepTumor";NA;66;0
"Building";"CreepTumorQueen";NA;66;0
"Building";"EvolutionChamber";NA;60;0
"Building";"CreepTumor";NA;66;0
"Unit";"Overlord";"Larva";68;0
"Building";"CreepTumor";NA;76;0
"Building";"CreepTumor";NA;76;0
"Unit";"Queen";"Hatchery";66;2
"Unit";"Zergling";"Larva";81;1
"Unit";"Zergling";"Larva";81;1
"Unit";"Zergling";"Larva";81;1
"Unit";"Zergling";"Larva";81;1
"Unit";"Zergling";"Larva";81;1
"Unit";"Zergling";"Larva";81;1
"Unit";"Zergling";"Larva";81;1
"Unit";"Zergling";"Larva";81;1
"Unit";"Zergling";"Larva";81;1
"Unit";"Zergling";"Larva";81;1
"Unit";"Zergling";"Larva";81;1
"Unit";"Zergling";"Larva";81;1
"Unit";"Overlord";"Larva";81;0
"Unit";"Queen";"Hatchery";76;2
"Building";"CreepTumor";NA;95;0
"Unit";"Overlord";"Larva";95;0
"Building";"CreepTumor";NA;97;0
"Building";"CreepTumor";NA;97;0
"Building";"CreepTumorQueen";NA;107;0
"Building";"Extractor";NA;107;0
"Building";"Extractor";NA;107;0
"Building";"CreepTumorQueen";NA;107;0
"Unit";"Overlord";"Larva";107;0
"Building";"CreepTumorQueen";NA;107;0
"Building";"CreepTumorQueen";NA;107;0
"Unit";"Zergling";"Larva";107;1
"Unit";"Zergling";"Larva";107;1
"Unit";"Overlord";"Larva";107;0
"Unit";"Zergling";"Larva";107;1
"Unit";"Zergling";"Larva";107;1
"Unit";"Zergling";"Larva";107;1
"Unit";"Zergling";"Larva";107;1
"Unit";"Zergling";"Larva";107;1
"Unit";"Zergling";"Larva";107;1
"Unit";"Queen";"Hatchery";107;2
"Unit";"Zergling";"Larva";113;1
"Unit";"Zergling";"Larva";113;1
"Unit";"Zergling";"Larva";113;1
"Unit";"Zergling";"Larva";113;1
"Unit";"Zergling";"Larva";113;1
"Unit";"Zergling";"Larva";113;1
"Unit";"Zergling";"Larva";113;1
"Unit";"Zergling";"Larva";113;1
"Unit";"Zergling";"Larva";113;1
"Unit";"Zergling";"Larva";113;1
"Unit";"Zergling";"Larva";113;1
"Unit";"Zergling";"Larva";113;1
"Unit";"Zergling";"Larva";113;1
"Unit";"Zergling";"Larva";113;1
"Unit";"Zergling";"Larva";113;1
"Unit";"Zergling";"Larva";113;1
"Building";"CreepTumor";NA;139;0
"Building";"CreepTumor";NA;139;0
"Building";"CreepTumor";NA;139;0
"Building";"CreepTumor";NA;139;0
"Building";"CreepTumor";NA;139;0
"Building";"CreepTumor";NA;139;0
"Building";"CreepTumor";NA;139;0
"Building";"CreepTumorQueen";NA;142;0
"Building";"CreepTumorQueen";NA;142;0
"Building";"CreepTumorQueen";NA;142;0
"Building";"CreepTumorQueen";NA;142;0
"Building";"EvolutionChamber";NA;143;0
"Building";"Extractor";NA;148;0
"Building";"CreepTumor";NA;148;0
"Building";"CreepTumor";NA;148;0
"Building";"CreepTumor";NA;148;0
"Building";"CreepTumor";NA;148;0
"Building";"CreepTumor";NA;148;0
"Building";"CreepTumor";NA;148;0
"Building";"CreepTumor";NA;148;0
"Building";"CreepTumorQueen";NA;148;0
"Building";"CreepTumor";NA;148;0
"Building";"CreepTumor";NA;148;0
"Building";"CreepTumorQueen";NA;148;0
"Unit";"Zergling";"Larva";148;1
"Unit";"Zergling";"Larva";148;1
"Building";"CreepTumorQueen";NA;148;0
"Building";"Extractor";NA;148;0
"Building";"HydraliskDen";NA;148;0
"Building";"CreepTumor";NA;148;0
"Building";"CreepTumor";NA;154;0
"Upgrade";"ZergGroundArmorsLevel1";"EvolutionChamber";113;0
"Unit";"Zergling";"Larva";154;1
"Unit";"Zergling";"Larva";154;1
"Unit";"Zergling";"Larva";154;1
"Unit";"Zergling";"Larva";154;1
"Unit";"Zergling";"Larva";154;1
"Unit";"Zergling";"Larva";154;1
"Unit";"Zergling";"Larva";154;1
"Unit";"Zergling";"Larva";154;1
"Unit";"Zergling";"Larva";154;1
"Unit";"Zergling";"Larva";154;1
"Unit";"Zergling";"Larva";154;1
"Unit";"Zergling";"Larva";154;1
"Unit";"Zergling";"Larva";154;1
"Unit";"Zergling";"Larva";154;1
"Building";"Hatchery";NA;123;0
"Unit";"Hydralisk";"Larva";156;2
"Unit";"Hydralisk";"Larva";156;2
"Unit";"Hydralisk";"Larva";156;2
"Building";"SporeCrawler";NA;170;0
"Unit";"Overlord";"Larva";170;0
"Unit";"Overlord";"Larva";170;0
"Unit";"Overlord";"Larva";170;0
"Unit";"Overlord";"Larva";170;0
"Unit";"Overlord";"Larva";170;0
"Unit";"Overlord";"Larva";170;0
"Unit";"Baneling";"Zergling";170;0
"Unit";"Baneling";"Zergling";170;0
"Unit";"Baneling";"Zergling";170;0
"Unit";"Baneling";"Zergling";170;0
"Unit";"Hydralisk";"Larva";170;2
"Unit";"Hydralisk";"Larva";170;2
"Unit";"Hydralisk";"Larva";170;2
"Unit";"Hydralisk";"Larva";170;2
"Unit";"Baneling";"Zergling";176;0
"Unit";"Baneling";"Zergling";176;0
"Unit";"Baneling";"Zergling";176;0
"Unit";"Baneling";"Zergling";176;0
"Building";"Hatchery";NA;153;0
"Unit";"Zergling";"Larva";184;1
"Unit";"Zergling";"Larva";184;1
"Unit";"Overlord";"Larva";184;0
"Unit";"Zergling";"Larva";184;1
"Unit";"Zergling";"Larva";184;1
"Unit";"Zergling";"Larva";184;1
"Unit";"Zergling";"Larva";184;1
"Unit";"Zergling";"Larva";184;1
"Unit";"Zergling";"Larva";184;1
"Unit";"Zergling";"Larva";184;1
"Unit";"Zergling";"Larva";184;1
"Unit";"Zergling";"Larva";184;1
"Unit";"Zergling";"Larva";184;1
"Unit";"Zergling";"Larva";184;1
"Unit";"Zergling";"Larva";184;1
"Unit";"Zergling";"Larva";184;1
"Unit";"Zergling";"Larva";184;1
"Unit";"Zergling";"Larva";184;1
"Unit";"Zergling";"Larva";184;1
"Unit";"Zergling";"Larva";184;1
"Unit";"Zergling";"Larva";184;1
"Unit";"Zergling";"Larva";184;1
"Unit";"Zergling";"Larva";184;1
"Unit";"Zergling";"Larva";184;1
"Unit";"Zergling";"Larva";184;1
"Unit";"Zergling";"Larva";184;1
"Unit";"Zergling";"Larva";184;1
"Unit";"Zergling";"Larva";184;1
"Unit";"Zergling";"Larva";184;1
"Unit";"Zergling";"Larva";184;1
"Unit";"Zergling";"Larva";184;1
"Upgrade";"EvolveGroovedSpines";"HydraliskDen";170;0
"Building";"CreepTumor";NA;214;0
"Building";"SporeCrawler";NA;184;0
"Unit";"Hydralisk";"Larva";214;2
"Unit";"Hydralisk";"Larva";214;2
"Unit";"Hydralisk";"Larva";214;2
"Unit";"Hydralisk";"Larva";214;2
"Unit";"Hydralisk";"Larva";214;2
"Building";"CreepTumor";NA;214;0
"Unit";"Hydralisk";"Larva";214;2
"Unit";"Hydralisk";"Larva";214;2
"Unit";"Hydralisk";"Larva";214;2
"Unit";"Hydralisk";"Larva";214;2
"Building";"CreepTumor";NA;219;0
"Building";"CreepTumor";NA;219;0
"Building";"CreepTumor";NA;219;0
"Building";"CreepTumor";NA;219;0
"Building";"Extractor";NA;214;0
"Building";"CreepTumor";NA;239;0
"Building";"CreepTumor";NA;239;0
"Building";"CreepTumor";NA;239;0
"Building";"CreepTumor";NA;239;0
"Building";"CreepTumor";NA;239;0
"Building";"CreepTumor";NA;239;0
"Building";"CreepTumor";NA;239;0
"Building";"CreepTumor";NA;239;0
"Building";"CreepTumor";NA;239;0
"Building";"InfestationPit";NA;214;0
"Building";"CreepTumorQueen";NA;239;0
"Building";"CreepTumorQueen";NA;239;0
"Building";"CreepTumorQueen";NA;239;0
"Upgrade";"ZergMeleeWeaponsLevel1";"EvolutionChamber";176;0
"Building";"CreepTumor";NA;239;0
"Unit";"Overlord";"Larva";239;0
"Unit";"Overlord";"Larva";239;0
"Unit";"Overlord";"Larva";239;0
"Building";"CreepTumorQueen";NA;239;0
"Building";"CreepTumorQueen";NA;254;0
"Building";"Extractor";NA;239;0
"Building";"SporeCrawler";NA;239;0
"Building";"Extractor";NA;239;0
"Unit";"Baneling";"Zergling";254;0
"Unit";"Baneling";"Zergling";254;0
"Unit";"Baneling";"Zergling";254;0
"Unit";"Baneling";"Zergling";254;0
"Unit";"Baneling";"Zergling";254;0
"Unit";"Baneling";"Zergling";254;0
"Unit";"Baneling";"Zergling";254;0
"Unit";"Baneling";"Zergling";254;0
"Unit";"Baneling";"Zergling";254;0
"Unit";"Baneling";"Zergling";254;0
"Unit";"Baneling";"Zergling";254;0
"Unit";"Baneling";"Zergling";254;0
"Unit";"Baneling";"Zergling";254;0
"Unit";"Zergling";"Larva";239;1
"Unit";"Zergling";"Larva";239;1
"Unit";"Baneling";"Zergling";254;0
"Unit";"Zergling";"Larva";239;1
"Unit";"Zergling";"Larva";239;1
"Unit";"Zergling";"Larva";239;1
"Unit";"Zergling";"Larva";239;1
"Unit";"Zergling";"Larva";239;1
"Unit";"Zergling";"Larva";239;1
"Unit";"Zergling";"Larva";239;1
"Unit";"Zergling";"Larva";239;1
"Unit";"Zergling";"Larva";239;1
"Unit";"Zergling";"Larva";239;1
"Unit";"Overlord";"Larva";254;0
"Unit";"Overlord";"Larva";254;0
"Upgrade";"EvolveMuscularAugments";"HydraliskDen";239;0
"Building";"CreepTumorQueen";NA;266;0
"Building";"CreepTumor";NA;266;0
"Building";"CreepTumor";NA;266;0
"Building";"CreepTumor";NA;266;0
"Building";"CreepTumorQueen";NA;266;0
"Building";"CreepTumorQueen";NA;266;0
"Building";"CreepTumorQueen";NA;266;0
"Unit";"Zergling";"Larva";266;1
"Unit";"Zergling";"Larva";266;1
"Unit";"Zergling";"Larva";266;1
"Unit";"Zergling";"Larva";266;1
"Unit";"Zergling";"Larva";266;1
"Unit";"Zergling";"Larva";266;1
"Unit";"Zergling";"Larva";266;1
"Unit";"Zergling";"Larva";266;1
"Unit";"Zergling";"Larva";266;1
"Unit";"Zergling";"Larva";266;1
"Unit";"Zergling";"Larva";266;1
"Unit";"Zergling";"Larva";266;1
"Unit";"Zergling";"Larva";266;1
"Unit";"Zergling";"Larva";266;1
"Unit";"Zergling";"Larva";266;1
"Unit";"Zergling";"Larva";266;1
"Unit";"Zergling";"Larva";266;1
"Unit";"Zergling";"Larva";266;1
"Unit";"Zergling";"Larva";266;1
"Unit";"Zergling";"Larva";266;1
"Unit";"Zergling";"Larva";266;1
"Unit";"Zergling";"Larva";266;1
"Building";"CreepTumorQueen";NA;266;0
"Unit";"Overlord";"Larva";266;0
"Unit";"Overlord";"Larva";266;0
"Unit";"Overlord";"Larva";266;0
"Building";"CreepTumorQueen";NA;288;0
"Building";"CreepTumor";NA;288;0
"Unit";"Overlord";"Larva";288;0
"Unit";"Overlord";"Larva";288;0
"Building";"SporeCrawler";NA;266;0
"Building";"SporeCrawler";NA;270;0
"Building";"CreepTumor";NA;288;0
"Building";"CreepTumor";NA;288;0
"Building";"CreepTumor";NA;288;0
"Building";"CreepTumor";NA;288;0
"Building";"CreepTumor";NA;288;0
"Building";"CreepTumor";NA;288;0
"Building";"CreepTumor";NA;288;0
"Unit";"Zergling";"Larva";288;1
"Unit";"Zergling";"Larva";288;1
"Unit";"Zergling";"Larva";288;1
"Unit";"Zergling";"Larva";288;1
"Unit";"Zergling";"Larva";288;1
"Unit";"Zergling";"Larva";288;1
"Unit";"Zergling";"Larva";288;1
"Unit";"Zergling";"Larva";288;1
"Unit";"Zergling";"Larva";288;1
"Unit";"Zergling";"Larva";288;1
"Unit";"Zergling";"Larva";288;1
"Unit";"Zergling";"Larva";288;1
"Unit";"Zergling";"Larva";288;1
"Unit";"Zergling";"Larva";288;1
"Unit";"Zergling";"Larva";288;1
"Unit";"Zergling";"Larva";288;1
"Unit";"Zergling";"Larva";288;1
"Unit";"Zergling";"Larva";288;1
"Unit";"Zergling";"Larva";288;1
"Unit";"Zergling";"Larva";288;1
"Unit";"Zergling";"Larva";288;1
"Unit";"Zergling";"Larva";288;1
"Building";"CreepTumorQueen";NA;288;0
"Building";"CreepTumorQueen";NA;288;0
"Building";"CreepTumor";NA;288;0
"Building";"CreepTumorQueen";NA;288;0
"Building";"CreepTumorQueen";NA;288;0
"Building";"CreepTumor";NA;288;0
"Building";"CreepTumor";NA;288;0
"Building";"CreepTumor";NA;288;0
"Building";"CreepTumor";NA;288;0
"Building";"CreepTumor";NA;288;0
"Building";"CreepTumor";NA;288;0
"Unit";"Zergling";"Larva";288;1
"Unit";"Zergling";"Larva";288;1
"Unit";"Zergling";"Larva";288;1
"Unit";"Zergling";"Larva";288;1
"Unit";"Zergling";"Larva";288;1
"Unit";"Zergling";"Larva";288;1
"Unit";"Zergling";"Larva";288;1
"Unit";"Zergling";"Larva";288;1
"Unit";"Zergling";"Larva";288;1
"Unit";"Zergling";"Larva";288;1
"Building";"CreepTumor";NA;310;0
"Building";"CreepTumor";NA;310;0
"Building";"CreepTumor";NA;310;0
"Building";"CreepTumor";NA;310;0
"Unit";"Baneling";"Zergling";320;0
"Unit";"Baneling";"Zergling";320;0
"Unit";"Baneling";"Zergling";320;0
"Unit";"Baneling";"Zergling";320;0
"Unit";"Baneling";"Zergling";320;0
"Unit";"Baneling";"Zergling";320;0
"Unit";"Baneling";"Zergling";320;0
"Unit";"Baneling";"Zergling";320;0
"Unit";"Baneling";"Zergling";320;0
"Unit";"Baneling";"Zergling";320;0
"Unit";"Zergling";"Larva";320;1
"Unit";"Zergling";"Larva";320;1
"Unit";"Zergling";"Larva";320;1
"Unit";"Zergling";"Larva";320;1
"Unit";"Zergling";"Larva";320;1
"Unit";"Zergling";"Larva";320;1
"Unit";"Zergling";"Larva";320;1
"Unit";"Zergling";"Larva";320;1
"Unit";"Zergling";"Larva";320;1
"Unit";"Zergling";"Larva";320;1
"Unit";"Zergling";"Larva";320;1
"Unit";"Zergling";"Larva";320;1
"Unit";"Zergling";"Larva";320;1
"Unit";"Zergling";"Larva";320;1
"Unit";"Zergling";"Larva";320;1
"Unit";"Zergling";"Larva";320;1
"Unit";"Zergling";"Larva";320;1
"Unit";"Zergling";"Larva";320;1
"Unit";"Zergling";"Larva";320;1
"Unit";"Zergling";"Larva";320;1
"Unit";"Zergling";"Larva";320;1
"Unit";"Zergling";"Larva";320;1
"Unit";"Zergling";"Larva";320;1
"Unit";"Zergling";"Larva";320;1
"Unit";"Zergling";"Larva";320;1
"Unit";"Zergling";"Larva";320;1
"Unit";"Zergling";"Larva";320;1
"Unit";"Zergling";"Larva";320;1
"Unit";"Zergling";"Larva";320;1
"Unit";"Zergling";"Larva";320;1
"Unit";"Zergling";"Larva";320;1
"Unit";"Zergling";"Larva";320;1
"Unit";"Zergling";"Larva";320;1
"Unit";"Zergling";"Larva";320;1
"Unit";"Zergling";"Larva";352;1
"Unit";"Zergling";"Larva";352;1
"Unit";"Zergling";"Larva";352;1
"Unit";"Zergling";"Larva";352;1
"Unit";"Zergling";"Larva";352;1
"Unit";"Zergling";"Larva";352;1
"Unit";"Zergling";"Larva";352;1
"Unit";"Zergling";"Larva";352;1
"Unit";"Zergling";"Larva";352;1
"Unit";"Zergling";"Larva";352;1
"Unit";"Zergling";"Larva";352;1
"Unit";"Zergling";"Larva";352;1
"Unit";"Zergling";"Larva";352;1
"Unit";"Zergling";"Larva";352;1
"Unit";"Zergling";"Larva";352;1
"Unit";"Zergling";"Larva";352;1
"Unit";"Baneling";"Zergling";354;0
"Unit";"Baneling";"Zergling";354;0
"Unit";"Baneling";"Zergling";354;0
"Unit";"Baneling";"Zergling";354;0
"Unit";"Baneling";"Zergling";354;0
"Unit";"Baneling";"Zergling";354;0
"Unit";"Baneling";"Zergling";354;0
"Unit";"Baneling";"Zergling";354;0
"Unit";"Baneling";"Zergling";354;0
"Unit";"Baneling";"Zergling";354;0
"Unit";"Baneling";"Zergling";354;0
"Unit";"Baneling";"Zergling";354;0
"Unit";"Baneling";"Zergling";354;0
"Unit";"Baneling";"Zergling";354;0
"Unit";"Baneling";"Zergling";354;0
"Unit";"Baneling";"Zergling";354;0
"Unit";"Baneling";"Zergling";354;0
"Unit";"Zergling";"Larva";354;1
"Unit";"Zergling";"Larva";354;1
"Unit";"Zergling";"Larva";354;1
"Unit";"Zergling";"Larva";354;1
"Unit";"Zergling";"Larva";354;1
"Unit";"Zergling";"Larva";354;1
"Unit";"Zergling";"Larva";354;1
"Unit";"Zergling";"Larva";354;1
"Upgrade";"ZergGroundArmorsLevel2";"EvolutionChamber";266;0
"Building";"Hatchery";NA;310;0
"Unit";"Zergling";"Larva";354;1
"Unit";"Zergling";"Larva";354;1
"Unit";"Zergling";"Larva";354;1
"Unit";"Zergling";"Larva";354;1
"Unit";"Zergling";"Larva";354;1
"Unit";"Zergling";"Larva";354;1
"Unit";"Zergling";"Larva";354;1
"Unit";"Zergling";"Larva";354;1
"Unit";"Zergling";"Larva";354;1
"Unit";"Zergling";"Larva";354;1
"Unit";"Zergling";"Larva";370;1
"Unit";"Zergling";"Larva";370;1
"Unit";"Zergling";"Larva";370;1
"Unit";"Zergling";"Larva";370;1
"Unit";"Zergling";"Larva";370;1
"Unit";"Zergling";"Larva";370;1
"Building";"UltraliskCavern";NA;352;0
"Unit";"Zergling";"Larva";388;1
"Unit";"Zergling";"Larva";388;1
"Unit";"Zergling";"Larva";388;1
"Unit";"Zergling";"Larva";388;1
"Unit";"Zergling";"Larva";388;1
"Unit";"Zergling";"Larva";388;1
"Unit";"Zergling";"Larva";388;1
"Unit";"Zergling";"Larva";388;1
"Unit";"Zergling";"Larva";388;1
"Unit";"Zergling";"Larva";388;1
"Unit";"Zergling";"Larva";388;1
"Unit";"Zergling";"Larva";388;1
"Unit";"Zergling";"Larva";388;1
"Unit";"Zergling";"Larva";388;1
"Unit";"Zergling";"Larva";388;1
"Unit";"Zergling";"Larva";388;1
"Unit";"Zergling";"Larva";388;1
"Unit";"Zergling";"Larva";388;1
"Unit";"Zergling";"Larva";388;1
"Unit";"Zergling";"Larva";388;1
"Unit";"Zergling";"Larva";388;1
"Unit";"Zergling";"Larva";388;1
"Unit";"Baneling";"Zergling";394;0
"Unit";"Baneling";"Zergling";394;0
"Unit";"Baneling";"Zergling";394;0
"Unit";"Baneling";"Zergling";394;0
"Unit";"Baneling";"Zergling";394;0
"Unit";"Hydralisk";"Larva";388;2
"Unit";"Baneling";"Zergling";394;0
"Unit";"Baneling";"Zergling";394;0
"Unit";"Baneling";"Zergling";394;0
"Unit";"Baneling";"Zergling";394;0
"Unit";"Baneling";"Zergling";394;0
"Unit";"Baneling";"Zergling";394;0
"Unit";"Hydralisk";"Larva";388;2
"Unit";"Baneling";"Zergling";394;0
"Unit";"Hydralisk";"Larva";388;2
"Unit";"Hydralisk";"Larva";394;2
"Unit";"Hydralisk";"Larva";394;2
"Unit";"Hydralisk";"Larva";394;2
"Unit";"Hydralisk";"Larva";394;2
"Unit";"Hydralisk";"Larva";416;2
"Unit";"Hydralisk";"Larva";416;2
"Unit";"Hydralisk";"Larva";416;2
"Unit";"Hydralisk";"Larva";416;2
"Unit";"Hydralisk";"Larva";416;2
"Unit";"Hydralisk";"Larva";416;2
"Upgrade";"ZergMeleeWeaponsLevel2";"EvolutionChamber";320;0
"Unit";"Hydralisk";"Larva";430;2
"Unit";"Hydralisk";"Larva";430;2
"Unit";"Hydralisk";"Larva";430;2
"Unit";"Hydralisk";"Larva";430;2
"Unit";"Hydralisk";"Larva";430;2
"Unit";"Hydralisk";"Larva";430;2
"Unit";"Hydralisk";"Larva";430;2
"Unit";"Hydralisk";"Larva";430;2
"Unit";"Hydralisk";"Larva";430;2
"Unit";"Hydralisk";"Larva";430;2
"Unit";"Hydralisk";"Larva";430;2
"Unit";"Zergling";"Larva";475;1
"Unit";"Zergling";"Larva";475;1
"Unit";"Zergling";"Larva";475;1
"Unit";"Zergling";"Larva";475;1
"Unit";"Zergling";"Larva";475;1
"Unit";"Zergling";"Larva";475;1
"Unit";"Zergling";"Larva";475;1
"Unit";"Zergling";"Larva";475;1
"Unit";"Zergling";"Larva";475;1
"Unit";"Zergling";"Larva";475;1
"Unit";"Zergling";"Larva";475;1
"Unit";"Zergling";"Larva";475;1
"Unit";"Baneling";"Zergling";475;0
"Unit";"Baneling";"Zergling";475;0
"Unit";"Baneling";"Zergling";475;0
"Unit";"Baneling";"Zergling";475;0
"Unit";"Baneling";"Zergling";475;0
"Unit";"Baneling";"Zergling";475;0
"Building";"CreepTumor";NA;475;0
"Building";"CreepTumor";NA;475;0
"Building";"CreepTumor";NA;475;0
"Building";"CreepTumor";NA;477;0
"Building";"CreepTumor";NA;477;0
"Building";"CreepTumor";NA;481;0
"Unit";"Zergling";"Larva";475;1
"Unit";"Zergling";"Larva";475;1
"Unit";"Zergling";"Larva";475;1
"Unit";"Zergling";"Larva";475;1
"Unit";"Zergling";"Larva";475;1
"Unit";"Zergling";"Larva";475;1
"Unit";"Zergling";"Larva";475;1
"Unit";"Zergling";"Larva";475;1
"Unit";"Zergling";"Larva";475;1
"Unit";"Zergling";"Larva";475;1
"Unit";"Zergling";"Larva";475;1
"Unit";"Zergling";"Larva";475;1
"Unit";"Zergling";"Larva";475;1
"Unit";"Zergling";"Larva";475;1
"Unit";"Zergling";"Larva";487;1
"Unit";"Zergling";"Larva";487;1
"Unit";"Zergling";"Larva";487;1
"Unit";"Zergling";"Larva";487;1
"Unit";"Zergling";"Larva";487;1
"Unit";"Zergling";"Larva";487;1
"Unit";"Zergling";"Larva";487;1
"Unit";"Zergling";"Larva";487;1
"Unit";"Zergling";"Larva";487;1
"Unit";"Zergling";"Larva";487;1
"Unit";"Zergling";"Larva";487;1
"Unit";"Zergling";"Larva";487;1
"Unit";"Zergling";"Larva";487;1
"Unit";"Zergling";"Larva";487;1
"Unit";"Zergling";"Larva";487;1
"Unit";"Zergling";"Larva";487;1
"Unit";"Zergling";"Larva";487;1
"Unit";"Zergling";"Larva";487;1
"Unit";"Zergling";"Larva";487;1
"Unit";"Zergling";"Larva";487;1
"Unit";"Zergling";"Larva";487;1
"Unit";"Zergling";"Larva";487;1
"Unit";"Zergling";"Larva";487;1
"Unit";"Zergling";"Larva";487;1
"Unit";"Zergling";"Larva";487;1
"Unit";"Zergling";"Larva";487;1
"Unit";"Zergling";"Larva";487;1
"Unit";"Zergling";"Larva";487;1
"Unit";"Zergling";"Larva";487;1
"Unit";"Zergling";"Larva";487;1
"Building";"CreepTumor";NA;501;0
"Building";"CreepTumor";NA;501;0
"Unit";"Baneling";"Zergling";501;0
"Unit";"Baneling";"Zergling";501;0
"Unit";"Baneling";"Zergling";501;0
"Unit";"Baneling";"Zergling";501;0
"Unit";"Baneling";"Zergling";501;0
"Unit";"Baneling";"Zergling";501;0
"Unit";"Baneling";"Zergling";501;0
"Unit";"Baneling";"Zergling";501;0
"Unit";"Baneling";"Zergling";501;0
"Unit";"Baneling";"Zergling";501;0
"Unit";"Baneling";"Zergling";501;0
"Unit";"Baneling";"Zergling";501;0
"Unit";"Baneling";"Zergling";501;0
"Unit";"Baneling";"Zergling";501;0
"Unit";"Baneling";"Zergling";501;0
"Unit";"Baneling";"Zergling";501;0
"Unit";"Baneling";"Zergling";501;0
"Unit";"Baneling";"Zergling";501;0
"Unit";"Baneling";"Zergling";501;0
"Unit";"Baneling";"Zergling";501;0
"Building";"EvolutionChamber";NA;487;0
"Building";"EvolutionChamber";NA;501;0
"Building";"EvolutionChamber";NA;501;0
"Unit";"Zergling";"Larva";503;1
"Unit";"Zergling";"Larva";503;1
"Unit";"Zergling";"Larva";509;1
"Unit";"Zergling";"Larva";509;1
"Unit";"Zergling";"Larva";509;1
"Unit";"Zergling";"Larva";509;1
"Unit";"Zergling";"Larva";513;1
"Unit";"Zergling";"Larva";513;1
"Unit";"Zergling";"Larva";513;1
"Unit";"Zergling";"Larva";513;1
"Unit";"Zergling";"Larva";517;1
"Unit";"Zergling";"Larva";517;1
"Unit";"Zergling";"Larva";517;1
"Unit";"Zergling";"Larva";517;1
"Building";"EvolutionChamber";NA;501;0
"Unit";"Viper";"Larva";531;3
"Unit";"Viper";"Larva";531;3
"Unit";"Viper";"Larva";531;3
"Unit";"Viper";"Larva";531;3
"Unit";"Zergling";"Larva";545;1
"Unit";"Zergling";"Larva";545;1
"Unit";"Zergling";"Larva";545;1
"Unit";"Zergling";"Larva";545;1
"Unit";"Zergling";"Larva";545;1
"Unit";"Zergling";"Larva";545;1
"Unit";"Zergling";"Larva";545;1
"Unit";"Zergling";"Larva";545;1
"Unit";"Zergling";"Larva";545;1
"Unit";"Zergling";"Larva";545;1
"Unit";"Zergling";"Larva";545;1
"Unit";"Zergling";"Larva";545;1
"Unit";"Zergling";"Larva";545;1
"Unit";"Zergling";"Larva";545;1
"Unit";"Zergling";"Larva";545;1
"Unit";"Zergling";"Larva";545;1
"Unit";"Zergling";"Larva";545;1
"Unit";"Zergling";"Larva";545;1
"Unit";"Zergling";"Larva";545;1
"Unit";"Zergling";"Larva";545;1
"Unit";"Zergling";"Larva";545;1
"Unit";"Zergling";"Larva";545;1
"Unit";"Zergling";"Larva";545;1
"Unit";"Zergling";"Larva";545;1
"Unit";"Zergling";"Larva";545;1
"Unit";"Zergling";"Larva";545;1
"Unit";"Zergling";"Larva";545;1
"Unit";"Zergling";"Larva";545;1
"Unit";"Zergling";"Larva";545;1
"Unit";"Zergling";"Larva";545;1
"Unit";"Zergling";"Larva";545;1
"Unit";"Zergling";"Larva";545;1
"Upgrade";"ZergMissileWeaponsLevel1";"EvolutionChamber";475;0
"Unit";"Zergling";"Larva";589;1
"Unit";"Zergling";"Larva";589;1
"Unit";"Zergling";"Larva";589;1
"Unit";"Zergling";"Larva";589;1
"Unit";"Zergling";"Larva";589;1
"Unit";"Zergling";"Larva";589;1
"Unit";"Zergling";"Larva";589;1
"Unit";"Zergling";"Larva";589;1
"Unit";"Zergling";"Larva";589;1
"Unit";"Zergling";"Larva";589;1
"Unit";"Zergling";"Larva";589;1
"Unit";"Zergling";"Larva";589;1
"Unit";"Zergling";"Larva";589;1
"Unit";"Zergling";"Larva";589;1
"Unit";"Zergling";"Larva";589;1
"Unit";"Zergling";"Larva";589;1
"Unit";"Zergling";"Larva";589;1
"Unit";"Zergling";"Larva";589;1
"Unit";"Zergling";"Larva";589;1
"Unit";"Zergling";"Larva";589;1
"Unit";"Zergling";"Larva";589;1
"Unit";"Zergling";"Larva";589;1
"Unit";"Zergling";"Larva";589;1
"Unit";"Zergling";"Larva";589;1
"Unit";"Zergling";"Larva";589;1
"Unit";"Zergling";"Larva";589;1
"Unit";"Zergling";"Larva";589;1
"Unit";"Zergling";"Larva";589;1
"Unit";"Zergling";"Larva";589;1
"Unit";"Zergling";"Larva";589;1
"Unit";"Zergling";"Larva";589;1
"Unit";"Zergling";"Larva";589;1
"Unit";"Zergling";"Larva";589;1
"Unit";"Zergling";"Larva";589;1
"Building";"Extractor";NA;589;0
"Building";"SporeCrawler";NA;589;0
"Building";"SporeCrawler";NA;589;0
"Unit";"Baneling";"Zergling";589;0
"Unit";"Baneling";"Zergling";589;0
"Unit";"Baneling";"Zergling";589;0
"Unit";"Baneling";"Zergling";589;0
"Unit";"Baneling";"Zergling";589;0
"Unit";"Baneling";"Zergling";589;0
"Unit";"Baneling";"Zergling";589;0
"Unit";"Baneling";"Zergling";589;0
"Unit";"Baneling";"Zergling";589;0
"Unit";"Baneling";"Zergling";589;0
"Unit";"Baneling";"Zergling";589;0
"Unit";"Baneling";"Zergling";589;0
"Unit";"Baneling";"Zergling";589;0
"Unit";"Baneling";"Zergling";589;0
"Unit";"Baneling";"Zergling";589;0
"Unit";"Baneling";"Zergling";589;0
"Unit";"Baneling";"Zergling";589;0
"Unit";"Baneling";"Zergling";589;0
"Unit";"Baneling";"Zergling";589;0
"Unit";"Baneling";"Zergling";589;0
"Building";"CreepTumor";NA;623;0
"Unit";"Hydralisk";"Larva";589;2
"Unit";"Hydralisk";"Larva";589;2
"Unit";"Hydralisk";"Larva";589;2
"Unit";"Hydralisk";"Larva";589;2
"Unit";"Hydralisk";"Larva";589;2
"Unit";"Zergling";"Larva";623;1
"Unit";"Zergling";"Larva";623;1
"Unit";"Zergling";"Larva";623;1
"Unit";"Zergling";"Larva";623;1
"Unit";"Zergling";"Larva";623;1
"Unit";"Zergling";"Larva";623;1
"Unit";"Zergling";"Larva";623;1
"Unit";"Zergling";"Larva";623;1
"Unit";"Zergling";"Larva";623;1
"Unit";"Zergling";"Larva";623;1
"Unit";"Zergling";"Larva";623;1
"Unit";"Zergling";"Larva";623;1
"Unit";"Zergling";"Larva";623;1
"Unit";"Zergling";"Larva";623;1
"Unit";"Zergling";"Larva";623;1
"Unit";"Zergling";"Larva";623;1
"Unit";"Zergling";"Larva";623;1
"Unit";"Zergling";"Larva";623;1
"Building";"CreepTumorQueen";NA;633;0
"Building";"CreepTumor";NA;633;0
"Building";"CreepTumorQueen";NA;649;0
"Building";"CreepTumorQueen";NA;651;0
"Building";"CreepTumorQueen";NA;659;0
"Unit";"Baneling";"Zergling";659;0
"Unit";"Baneling";"Zergling";659;0
"Unit";"Baneling";"Zergling";659;0
"Unit";"Baneling";"Zergling";659;0
"Unit";"Baneling";"Zergling";659;0
"Unit";"Baneling";"Zergling";659;0
"Unit";"Baneling";"Zergling";659;0
"Building";"Hatchery";NA;557;0
"Unit";"Zergling";"Larva";659;1
"Unit";"Zergling";"Larva";659;1
"Unit";"Zergling";"Larva";659;1
"Unit";"Zergling";"Larva";659;1
"Unit";"Zergling";"Larva";659;1
"Unit";"Zergling";"Larva";659;1
"Unit";"Zergling";"Larva";659;1
"Unit";"Zergling";"Larva";659;1
"Unit";"Zergling";"Larva";659;1
"Unit";"Zergling";"Larva";659;1
"Unit";"Zergling";"Larva";659;1
"Unit";"Zergling";"Larva";659;1
"Unit";"Zergling";"Larva";659;1
"Unit";"Zergling";"Larva";659;1
"Unit";"Zergling";"Larva";659;1
"Unit";"Zergling";"Larva";659;1
"Building";"CreepTumor";NA;675;0
"Building";"CreepTumor";NA;675;0
"Building";"CreepTumor";NA;675;0
"Building";"CreepTumor";NA;675;0
"Unit";"Zergling";"Larva";675;1
"Unit";"Zergling";"Larva";675;1
"Unit";"Zergling";"Larva";675;1
"Unit";"Zergling";"Larva";675;1
"Unit";"Zergling";"Larva";675;1
"Unit";"Zergling";"Larva";675;1
"Unit";"Zergling";"Larva";675;1
"Unit";"Zergling";"Larva";675;1
"Unit";"Zergling";"Larva";675;1
"Unit";"Zergling";"Larva";675;1
"Unit";"Zergling";"Larva";675;1
"Unit";"Zergling";"Larva";675;1
"Unit";"Zergling";"Larva";675;1
"Unit";"Zergling";"Larva";675;1
"Unit";"Zergling";"Larva";675;1
"Unit";"Zergling";"Larva";675;1
"Unit";"Zergling";"Larva";675;1
"Unit";"Zergling";"Larva";675;1
"Unit";"Zergling";"Larva";675;1
"Unit";"Zergling";"Larva";675;1
"Unit";"Zergling";"Larva";675;1
"Unit";"Zergling";"Larva";675;1
"Unit";"Zergling";"Larva";675;1
"Unit";"Zergling";"Larva";675;1
"Unit";"Zergling";"Larva";675;1
"Unit";"Zergling";"Larva";675;1
"Building";"Hatchery";NA;623;0
"Unit";"Hydralisk";"Larva";675;2
"Unit";"Hydralisk";"Larva";675;2
"Unit";"Hydralisk";"Larva";675;2
"Unit";"Hydralisk";"Larva";675;2
"Unit";"Hydralisk";"Larva";675;2
"Unit";"Hydralisk";"Larva";675;2
"Unit";"Hydralisk";"Larva";675;2
"Unit";"Zergling";"Larva";675;1
"Unit";"Zergling";"Larva";675;1
"Unit";"Zergling";"Larva";675;1
"Unit";"Zergling";"Larva";675;1
"Unit";"Zergling";"Larva";675;1
"Unit";"Zergling";"Larva";675;1
"Unit";"Zergling";"Larva";675;1
"Unit";"Zergling";"Larva";675;1
"Unit";"Zergling";"Larva";675;1
"Unit";"Zergling";"Larva";675;1
"Unit";"Zergling";"Larva";675;1
"Unit";"Zergling";"Larva";675;1
"Unit";"Zergling";"Larva";675;1
"Unit";"Zergling";"Larva";675;1
"Building";"SporeCrawler";NA;675;0
"Building";"SporeCrawler";NA;675;0
"Building";"EvolutionChamber";NA;701;0
"Unit";"Baneling";"Zergling";717;0
"Unit";"Baneling";"Zergling";723;0
"Upgrade";"ZergGroundArmorsLevel3";"EvolutionChamber";589;0
"Unit";"Baneling";"Zergling";727;0
"Unit";"Baneling";"Zergling";727;0
"Unit";"Baneling";"Zergling";729;0
"Unit";"Baneling";"Zergling";729;0
"Unit";"Baneling";"Zergling";729;0
"Unit";"Baneling";"Zergling";729;0
"Unit";"Baneling";"Zergling";729;0
"Unit";"Baneling";"Zergling";729;0
"Unit";"Baneling";"Zergling";729;0
"Unit";"Baneling";"Zergling";729;0
"Unit";"Baneling";"Zergling";729;0
"Unit";"Baneling";"Zergling";729;0
"Unit";"Viper";"Larva";675;3
"Unit";"Viper";"Larva";675;3
"Building";"CreepTumor";NA;736;0
"Building";"CreepTumor";NA;736;0
"Building";"CreepTumor";NA;736;0
"Building";"CreepTumor";NA;736;0
"Building";"CreepTumor";NA;736;0
"Unit";"Zergling";"Larva";736;1
"Unit";"Zergling";"Larva";736;1
"Unit";"Zergling";"Larva";736;1
"Unit";"Zergling";"Larva";736;1
"Unit";"Zergling";"Larva";736;1
"Unit";"Zergling";"Larva";736;1
"Unit";"Zergling";"Larva";736;1
"Unit";"Zergling";"Larva";736;1
"Unit";"Zergling";"Larva";736;1
"Unit";"Zergling";"Larva";736;1
"Unit";"Zergling";"Larva";736;1
"Unit";"Zergling";"Larva";736;1
"Unit";"Zergling";"Larva";736;1
"Unit";"Zergling";"Larva";736;1
"Unit";"Zergling";"Larva";736;1
"Unit";"Zergling";"Larva";736;1
"Unit";"Zergling";"Larva";736;1
"Unit";"Zergling";"Larva";736;1
"Unit";"Zergling";"Larva";736;1
"Unit";"Zergling";"Larva";736;1
"Unit";"Zergling";"Larva";736;1
"Unit";"Zergling";"Larva";736;1
"Unit";"Zergling";"Larva";736;1
"Unit";"Zergling";"Larva";736;1
"Unit";"Zergling";"Larva";736;1
"Unit";"Zergling";"Larva";736;1
"Unit";"Zergling";"Larva";736;1
"Unit";"Zergling";"Larva";736;1
"Unit";"Zergling";"Larva";736;1
"Unit";"Zergling";"Larva";736;1
"Unit";"Zergling";"Larva";736;1
"Unit";"Zergling";"Larva";736;1
"Unit";"Zergling";"Larva";736;1
"Unit";"Zergling";"Larva";736;1
"Unit";"Zergling";"Larva";736;1
"Unit";"Zergling";"Larva";736;1
"Unit";"Zergling";"Larva";736;1
"Unit";"Zergling";"Larva";736;1
"Unit";"Zergling";"Larva";736;1
"Unit";"Zergling";"Larva";736;1
"Unit";"Zergling";"Larva";736;1
"Unit";"Zergling";"Larva";736;1
"Unit";"Zergling";"Larva";736;1
"Unit";"Zergling";"Larva";736;1
"Building";"CreepTumor";NA;736;0
"Building";"CreepTumor";NA;736;0
"Building";"CreepTumor";NA;736;0
"Building";"CreepTumor";NA;736;0
"Building";"SporeCrawler";NA;736;0
"Building";"SporeCrawler";NA;736;0
"Building";"CreepTumorQueen";NA;780;0
"Unit";"Baneling";"Zergling";736;0
"Unit";"Baneling";"Zergling";736;0
"Unit";"Baneling";"Zergling";736;0
"Unit";"Baneling";"Zergling";736;0
"Unit";"Baneling";"Zergling";736;0
"Unit";"Baneling";"Zergling";736;0
"Unit";"Baneling";"Zergling";736;0
"Unit";"Baneling";"Zergling";736;0
"Unit";"Baneling";"Zergling";736;0
"Unit";"Baneling";"Zergling";736;0
"Unit";"Baneling";"Zergling";736;0
"Unit";"Baneling";"Zergling";736;0
"Unit";"Baneling";"Zergling";736;0
"Unit";"Baneling";"Zergling";736;0
"Unit";"Zergling";"Larva";780;1
"Unit";"Zergling";"Larva";780;1
"Unit";"Zergling";"Larva";780;1
"Unit";"Zergling";"Larva";780;1
"Unit";"Zergling";"Larva";780;1
"Unit";"Zergling";"Larva";780;1
"Unit";"Zergling";"Larva";780;1
"Unit";"Zergling";"Larva";780;1
"Unit";"Zergling";"Larva";780;1
"Unit";"Zergling";"Larva";780;1
"Unit";"Zergling";"Larva";780;1
"Unit";"Zergling";"Larva";780;1
"Unit";"Zergling";"Larva";780;1
"Unit";"Zergling";"Larva";780;1
"Unit";"Zergling";"Larva";780;1
"Unit";"Zergling";"Larva";780;1
"Unit";"Zergling";"Larva";780;1
"Unit";"Zergling";"Larva";780;1
"Unit";"Zergling";"Larva";780;1
"Unit";"Zergling";"Larva";780;1
"Unit";"Zergling";"Larva";780;1
"Unit";"Zergling";"Larva";780;1
"Unit";"Zergling";"Larva";780;1
"Unit";"Zergling";"Larva";780;1
"Unit";"Zergling";"Larva";780;1
"Unit";"Zergling";"Larva";780;1
"Unit";"Zergling";"Larva";780;1
"Unit";"Zergling";"Larva";780;1
"Unit";"Zergling";"Larva";780;1
"Unit";"Zergling";"Larva";780;1
"Unit";"Zergling";"Larva";780;1
"Unit";"Zergling";"Larva";780;1
"Building";"SporeCrawler";NA;780;0
"Building";"SporeCrawler";NA;780;0
"Building";"SporeCrawler";NA;780;0
"Building";"CreepTumor";NA;812;0
"Building";"CreepTumor";NA;814;0
"Unit";"Baneling";"Zergling";822;0
"Unit";"Baneling";"Zergling";822;0
"Unit";"Baneling";"Zergling";822;0
"Unit";"Baneling";"Zergling";822;0
"Unit";"Baneling";"Zergling";822;0
"Unit";"Baneling";"Zergling";822;0
"Unit";"Baneling";"Zergling";822;0
"Unit";"Baneling";"Zergling";822;0
"Unit";"Baneling";"Zergling";822;0
"Unit";"Baneling";"Zergling";822;0
"Unit";"Baneling";"Zergling";822;0
"Building";"SporeCrawler";NA;812;0
"Building";"SporeCrawler";NA;812;0
"Building";"SporeCrawler";NA;812;0
"Unit";"Zergling";"Larva";822;1
"Unit";"Zergling";"Larva";822;1
"Unit";"Zergling";"Larva";822;1
"Unit";"Zergling";"Larva";822;1
"Unit";"Zergling";"Larva";822;1
"Unit";"Zergling";"Larva";822;1
"Unit";"Zergling";"Larva";822;1
"Unit";"Zergling";"Larva";822;1
"Unit";"Zergling";"Larva";822;1
"Unit";"Zergling";"Larva";822;1
"Unit";"Zergling";"Larva";822;1
"Unit";"Zergling";"Larva";822;1
"Unit";"Zergling";"Larva";822;1
"Unit";"Zergling";"Larva";822;1
"Unit";"Baneling";"Zergling";836;0
"Unit";"Baneling";"Zergling";836;0
"Unit";"Baneling";"Zergling";836;0
"Unit";"Baneling";"Zergling";836;0
"Unit";"Baneling";"Zergling";836;0
"Unit";"Baneling";"Zergling";836;0
"Unit";"Baneling";"Zergling";836;0
"Unit";"Baneling";"Zergling";836;0
"Unit";"Baneling";"Zergling";836;0
"Unit";"Baneling";"Zergling";836;0
"Unit";"Baneling";"Zergling";836;0
"Unit";"Baneling";"Zergling";836;0
"Unit";"Baneling";"Zergling";836;0
"Unit";"Baneling";"Zergling";836;0
"Unit";"Baneling";"Zergling";836;0
"Unit";"Baneling";"Zergling";836;0
"Unit";"Baneling";"Zergling";836;0
"Unit";"Baneling";"Zergling";836;0
"Unit";"Baneling";"Zergling";836;0
"Unit";"Baneling";"Zergling";836;0
"Unit";"Baneling";"Zergling";836;0
"Unit";"Baneling";"Zergling";836;0
"Unit";"Baneling";"Zergling";836;0
"Upgrade";"Burrow";"Hatchery";822;0
"Unit";"Zergling";"Larva";836;1
"Unit";"Zergling";"Larva";836;1
"Unit";"Zergling";"Larva";836;1
"Unit";"Zergling";"Larva";836;1
"Unit";"Zergling";"Larva";836;1
"Unit";"Zergling";"Larva";836;1
"Unit";"Zergling";"Larva";836;1
"Unit";"Zergling";"Larva";836;1
"Unit";"Zergling";"Larva";836;1
"Unit";"Zergling";"Larva";836;1
"Unit";"Zergling";"Larva";836;1
"Unit";"Zergling";"Larva";836;1
"Unit";"Zergling";"Larva";836;1
"Unit";"Zergling";"Larva";836;1
"Unit";"Zergling";"Larva";836;1
"Unit";"Zergling";"Larva";836;1
"Unit";"Zergling";"Larva";836;1
"Unit";"Zergling";"Larva";836;1
"Unit";"Zergling";"Larva";836;1
"Unit";"Zergling";"Larva";836;1
"Unit";"Zergling";"Larva";856;1
"Unit";"Zergling";"Larva";856;1
"Unit";"Zergling";"Larva";856;1
"Unit";"Zergling";"Larva";856;1
"Unit";"Zergling";"Larva";856;1
"Unit";"Zergling";"Larva";856;1
"Unit";"Zergling";"Larva";856;1
"Unit";"Zergling";"Larva";856;1
"Unit";"Zergling";"Larva";856;1
"Unit";"Zergling";"Larva";856;1
"Unit";"Zergling";"Larva";856;1
"Unit";"Zergling";"Larva";856;1
"Unit";"Zergling";"Larva";856;1
"Unit";"Zergling";"Larva";856;1
"Unit";"Zergling";"Larva";856;1
"Unit";"Zergling";"Larva";856;1
"Unit";"Zergling";"Larva";856;1
"Unit";"Zergling";"Larva";856;1
"Unit";"Zergling";"Larva";856;1
"Unit";"Zergling";"Larva";856;1
"Unit";"Zergling";"Larva";856;1
"Unit";"Zergling";"Larva";856;1
"Unit";"Zergling";"Larva";856;1
"Unit";"Zergling";"Larva";856;1
"Unit";"Zergling";"Larva";856;1
"Unit";"Zergling";"Larva";856;1
"Unit";"Zergling";"Larva";856;1
"Unit";"Zergling";"Larva";856;1
"Unit";"Zergling";"Larva";856;1
"Unit";"Zergling";"Larva";856;1
"Unit";"Zergling";"Larva";856;1
"Unit";"Zergling";"Larva";856;1
"Unit";"Zergling";"Larva";856;1
"Unit";"Zergling";"Larva";856;1
"Unit";"Zergling";"Larva";856;1
"Unit";"Zergling";"Larva";856;1
"Unit";"Zergling";"Larva";856;1
"Unit";"Zergling";"Larva";856;1
"Unit";"Zergling";"Larva";856;1
"Unit";"Zergling";"Larva";856;1
"Unit";"Zergling";"Larva";856;1
"Unit";"Zergling";"Larva";856;1
"Unit";"Zergling";"Larva";856;1
"Unit";"Zergling";"Larva";856;1
"Unit";"Zergling";"Larva";856;1
"Unit";"Zergling";"Larva";856;1
"Unit";"Zergling";"Larva";856;1
"Unit";"Zergling";"Larva";856;1
"Unit";"Zergling";"Larva";856;1
"Unit";"Zergling";"Larva";856;1
"Unit";"Zergling";"Larva";856;1
"Unit";"Zergling";"Larva";856;1
"Unit";"Hydralisk";"Larva";856;2
"Unit";"Hydralisk";"Larva";856;2
"Unit";"Hydralisk";"Larva";856;2
"Unit";"Hydralisk";"Larva";856;2
"Unit";"Hydralisk";"Larva";856;2
"Unit";"Hydralisk";"Larva";856;2
"Unit";"Hydralisk";"Larva";856;2
"Unit";"Hydralisk";"Larva";856;2
"Unit";"Hydralisk";"Larva";856;2
"Unit";"Hydralisk";"Larva";856;2
"Unit";"Hydralisk";"Larva";856;2
"Unit";"Hydralisk";"Larva";856;2
"Unit";"Hydralisk";"Larva";856;2
"Unit";"Zergling";"Larva";908;1
"Unit";"Zergling";"Larva";908;1
"Unit";"Zergling";"Larva";910;1
"Unit";"Zergling";"Larva";910;1
"Unit";"Zergling";"Larva";912;1
"Unit";"Zergling";"Larva";912;1
"Unit";"Zergling";"Larva";912;1
"Unit";"Zergling";"Larva";912;1
"Unit";"Zergling";"Larva";916;1
"Unit";"Zergling";"Larva";916;1
"Unit";"Zergling";"Larva";916;1
"Unit";"Zergling";"Larva";916;1
"Unit";"Zergling";"Larva";920;1
"Unit";"Zergling";"Larva";920;1
"Unit";"Zergling";"Larva";920;1
"Unit";"Zergling";"Larva";920;1
"Unit";"Baneling";"Zergling";923;0
"Unit";"Baneling";"Zergling";923;0
"Unit";"Baneling";"Zergling";923;0
"Unit";"Baneling";"Zergling";923;0
"Unit";"Baneling";"Zergling";923;0
"Unit";"Baneling";"Zergling";923;0
"Unit";"Baneling";"Zergling";923;0
"Unit";"Baneling";"Zergling";923;0
"Unit";"Baneling";"Zergling";923;0
"Unit";"Baneling";"Zergling";923;0
"Unit";"Baneling";"Zergling";923;0
"Unit";"Baneling";"Zergling";923;0
"Unit";"Baneling";"Zergling";923;0
"Unit";"Baneling";"Zergling";923;0
"Unit";"Baneling";"Zergling";923;0
"Unit";"Baneling";"Zergling";923;0
"Unit";"Baneling";"Zergling";923;0
"Unit";"Baneling";"Zergling";923;0
"Unit";"Baneling";"Zergling";923;0
"Unit";"Baneling";"Zergling";923;0
"Unit";"Baneling";"Zergling";923;0
"Unit";"Hydralisk";"Larva";908;2
"Unit";"Baneling";"Zergling";923;0
"Unit";"Hydralisk";"Larva";908;2
"Unit";"Zergling";"Larva";923;1
"Unit";"Zergling";"Larva";923;1
"Unit";"Zergling";"Larva";923;1
"Unit";"Zergling";"Larva";923;1
"Unit";"Zergling";"Larva";923;1
"Unit";"Zergling";"Larva";923;1
"Unit";"Zergling";"Larva";923;1
"Unit";"Zergling";"Larva";923;1
"Unit";"Zergling";"Larva";923;1
"Unit";"Zergling";"Larva";923;1
"Unit";"Zergling";"Larva";923;1
"Unit";"Zergling";"Larva";923;1
"Unit";"Zergling";"Larva";923;1
"Unit";"Zergling";"Larva";923;1
"Building";"CreepTumor";NA;953;0
"Building";"CreepTumor";NA;953;0
"Building";"CreepTumor";NA;953;0
"Building";"CreepTumor";NA;955;0
"Building";"CreepTumor";NA;955;0
"Building";"CreepTumor";NA;955;0
"Building";"CreepTumor";NA;957;0
"Building";"CreepTumor";NA;957;0
"Unit";"Zergling";"Larva";957;1
"Unit";"Zergling";"Larva";957;1
"Unit";"Zergling";"Larva";957;1
"Unit";"Zergling";"Larva";957;1
"Unit";"Zergling";"Larva";957;1
"Unit";"Zergling";"Larva";957;1
"Unit";"Zergling";"Larva";957;1
"Unit";"Zergling";"Larva";957;1
"Unit";"Zergling";"Larva";957;1
"Unit";"Zergling";"Larva";957;1
"Unit";"Hydralisk";"Larva";957;2
"Unit";"Hydralisk";"Larva";957;2
"Unit";"Hydralisk";"Larva";957;2
"Unit";"Hydralisk";"Larva";957;2
"Unit";"Hydralisk";"Larva";957;2
"Building";"CreepTumor";NA;971;0
"Building";"CreepTumor";NA;971;0
"Unit";"Baneling";"Zergling";971;0
"Unit";"Baneling";"Zergling";971;0
"Unit";"Baneling";"Zergling";971;0
"Unit";"Baneling";"Zergling";971;0
"Unit";"Baneling";"Zergling";971;0
"Unit";"Baneling";"Zergling";971;0
"Unit";"Baneling";"Zergling";973;0
"Unit";"Baneling";"Zergling";973;0
"Unit";"Baneling";"Zergling";981;0
"Building";"Extractor";NA;991;0
"Building";"Extractor";NA;991;0
"Building";"SporeCrawler";NA;991;0
"Building";"SporeCrawler";NA;991;0
"Building";"CreepTumor";NA;994;0
"Building";"CreepTumor";NA;994;0
"Building";"CreepTumor";NA;994;0
"Unit";"Overlord";"Larva";991;0
"Building";"CreepTumor";NA;994;0
"Unit";"Overlord";"Larva";991;0
"Unit";"Overlord";"Larva";991;0
"Building";"CreepTumor";NA;994;0
"Building";"SpineCrawler";NA;991;0
"Building";"SpineCrawler";NA;991;0
"Building";"CreepTumor";NA;994;0
"Building";"CreepTumor";NA;994;0
"Building";"SpineCrawler";NA;991;0
"Unit";"Zergling";"Larva";994;1
"Unit";"Zergling";"Larva";994;1
"Unit";"Zergling";"Larva";994;1
"Unit";"Zergling";"Larva";994;1
"Unit";"Zergling";"Larva";994;1
"Unit";"Zergling";"Larva";994;1
"Unit";"Zergling";"Larva";994;1
"Unit";"Zergling";"Larva";994;1
"Unit";"Zergling";"Larva";994;1
"Unit";"Zergling";"Larva";994;1
"Unit";"Zergling";"Larva";994;1
"Unit";"Zergling";"Larva";994;1
"Unit";"Zergling";"Larva";994;1
"Unit";"Zergling";"Larva";994;1
"Unit";"Zergling";"Larva";994;1
"Unit";"Zergling";"Larva";994;1
"Unit";"Zergling";"Larva";994;1
"Unit";"Zergling";"Larva";994;1
"Unit";"Zergling";"Larva";994;1
"Unit";"Zergling";"Larva";994;1
"Unit";"Zergling";"Larva";994;1
"Unit";"Zergling";"Larva";994;1
"Unit";"Zergling";"Larva";994;1
"Unit";"Zergling";"Larva";994;1
"Unit";"Zergling";"Larva";994;1
"Unit";"Zergling";"Larva";994;1
"Unit";"Zergling";"Larva";994;1
"Unit";"Zergling";"Larva";994;1
"Unit";"Zergling";"Larva";994;1
"Unit";"Zergling";"Larva";994;1
"Unit";"Zergling";"Larva";994;1
"Unit";"Zergling";"Larva";994;1
"Unit";"Zergling";"Larva";994;1
"Unit";"Zergling";"Larva";994;1
"Unit";"Zergling";"Larva";994;1
"Unit";"Zergling";"Larva";994;1
"Unit";"Zergling";"Larva";994;1
"Unit";"Zergling";"Larva";994;1
"Unit";"Zergling";"Larva";994;1
"Unit";"Zergling";"Larva";994;1
"Unit";"Zergling";"Larva";994;1
"Unit";"Zergling";"Larva";994;1
"Unit";"Zergling";"Larva";994;1
"Unit";"Zergling";"Larva";994;1
"Unit";"Zergling";"Larva";994;1
"Unit";"Zergling";"Larva";994;1
"Unit";"Zergling";"Larva";994;1
"Unit";"Zergling";"Larva";994;1
"Unit";"Zergling";"Larva";994;1
"Unit";"Zergling";"Larva";994;1
"Unit";"Zergling";"Larva";994;1
"Unit";"Zergling";"Larva";994;1
"Unit";"Zergling";"Larva";994;1
"Unit";"Zergling";"Larva";994;1
"Unit";"Zergling";"Larva";994;1
"Unit";"Zergling";"Larva";994;1
"Unit";"Zergling";"Larva";994;1
"Unit";"Zergling";"Larva";994;1
"Unit";"Zergling";"Larva";994;1
"Unit";"Zergling";"Larva";994;1
"Building";"Spire";NA;991;0
"Building";"Spire";NA;991;0
"Unit";"Zergling";"Larva";1054;1
"Unit";"Zergling";"Larva";1054;1
"Unit";"Zergling";"Larva";1054;1
"Unit";"Zergling";"Larva";1054;1
"Unit";"Zergling";"Larva";1054;1
"Unit";"Zergling";"Larva";1054;1
"Unit";"Zergling";"Larva";1054;1
"Unit";"Zergling";"Larva";1054;1
"Unit";"Zergling";"Larva";1054;1
"Unit";"Zergling";"Larva";1054;1
"Building";"SpineCrawler";NA;1054;0
"Unit";"Zergling";"Larva";1064;1
"Unit";"Zergling";"Larva";1064;1
"Unit";"Zergling";"Larva";1064;1
"Unit";"Zergling";"Larva";1064;1
"Unit";"Zergling";"Larva";1064;1
"Unit";"Zergling";"Larva";1064;1
"Unit";"Zergling";"Larva";1064;1
"Unit";"Zergling";"Larva";1064;1
"Unit";"Zergling";"Larva";1064;1
"Unit";"Zergling";"Larva";1064;1
"Unit";"Zergling";"Larva";1064;1
"Unit";"Zergling";"Larva";1064;1
"Unit";"Zergling";"Larva";1064;1
"Unit";"Zergling";"Larva";1064;1
"Unit";"Zergling";"Larva";1064;1
"Unit";"Zergling";"Larva";1064;1
"Unit";"Zergling";"Larva";1064;1
"Unit";"Zergling";"Larva";1064;1
"Unit";"Zergling";"Larva";1064;1
"Unit";"Zergling";"Larva";1064;1
"Unit";"Zergling";"Larva";1064;1
"Unit";"Zergling";"Larva";1064;1
"Unit";"Zergling";"Larva";1064;1
"Unit";"Zergling";"Larva";1064;1
"Unit";"Zergling";"Larva";1064;1
"Unit";"Zergling";"Larva";1064;1
"Unit";"Zergling";"Larva";1064;1
"Unit";"Zergling";"Larva";1064;1
"Unit";"Zergling";"Larva";1064;1
"Unit";"Zergling";"Larva";1064;1
"Unit";"Zergling";"Larva";1064;1
"Unit";"Zergling";"Larva";1064;1
"Unit";"Zergling";"Larva";1064;1
"Unit";"Zergling";"Larva";1064;1
"Unit";"Zergling";"Larva";1064;1
"Unit";"Zergling";"Larva";1064;1
"Unit";"Zergling";"Larva";1064;1
"Unit";"Zergling";"Larva";1064;1
"Unit";"Zergling";"Larva";1064;1
"Unit";"Zergling";"Larva";1064;1
"Unit";"Zergling";"Larva";1064;1
"Unit";"Zergling";"Larva";1064;1
"Unit";"Zergling";"Larva";1064;1
"Unit";"Zergling";"Larva";1064;1
"Unit";"Zergling";"Larva";1064;1
"Unit";"Zergling";"Larva";1064;1
"Unit";"Zergling";"Larva";1064;1
"Unit";"Zergling";"Larva";1064;1
"Unit";"Hydralisk";"Larva";1064;2
"Unit";"Hydralisk";"Larva";1064;2
"Unit";"Hydralisk";"Larva";1064;2
"Unit";"Hydralisk";"Larva";1064;2
"Unit";"Hydralisk";"Larva";1064;2
"Unit";"Hydralisk";"Larva";1064;2
"Unit";"Hydralisk";"Larva";1064;2
"Unit";"Hydralisk";"Larva";1064;2
"Unit";"Hydralisk";"Larva";1064;2
"Unit";"Hydralisk";"Larva";1064;2
"Unit";"Zergling";"Larva";1064;1
"Unit";"Zergling";"Larva";1064;1
"Upgrade";"ZergMissileWeaponsLevel2";"EvolutionChamber";994;0
"Unit";"Hydralisk";"Larva";1064;2
"Unit";"Hydralisk";"Larva";1064;2
"Unit";"Baneling";"Zergling";1112;0
"Unit";"Baneling";"Zergling";1112;0
"Unit";"Baneling";"Zergling";1112;0
"Unit";"Baneling";"Zergling";1112;0
"Unit";"Baneling";"Zergling";1112;0
"Unit";"Baneling";"Zergling";1112;0
"Unit";"Baneling";"Zergling";1112;0
"Unit";"Baneling";"Zergling";1112;0
"Unit";"Baneling";"Zergling";1112;0
"Unit";"Baneling";"Zergling";1112;0
"Unit";"Baneling";"Zergling";1112;0
"Unit";"Baneling";"Zergling";1112;0
"Unit";"Baneling";"Zergling";1112;0
"Unit";"Baneling";"Zergling";1112;0
"Unit";"Baneling";"Zergling";1112;0
"Unit";"Baneling";"Zergling";1112;0
"Unit";"Baneling";"Zergling";1112;0
"Unit";"Baneling";"Zergling";1112;0
"Unit";"Baneling";"Zergling";1112;0
"Unit";"Baneling";"Zergling";1112;0
"Unit";"Baneling";"Zergling";1112;0
"Unit";"Baneling";"Zergling";1112;0
"Unit";"Baneling";"Zergling";1112;0
"Unit";"Baneling";"Zergling";1112;0
"Unit";"Baneling";"Zergling";1112;0
"Unit";"Zergling";"Larva";1132;1
"Unit";"Zergling";"Larva";1132;1
