"type";"unit_name";"on_building";"total_supply";"supply"
"Unit";"Overlord";"Larva";13;0
"Building";"SpawningPool";NA;19;0
"Building";"Hatchery";NA;17;0
"Unit";"Zergling";"Larva";24;1
"Unit";"Zergling";"Larva";24;1
"Unit";"Zergling";"Larva";24;1
"Unit";"Zergling";"Larva";24;1
"Unit";"Queen";"Hatchery";24;2
"Unit";"Overlord";"Larva";24;0
"Unit";"Queen";"Hatchery";24;2
"Building";"Hatchery";NA;21;0
"Unit";"Overlord";"Larva";31;0
"Building";"Extractor";NA;33;0
"Unit";"Queen";"Hatchery";33;2
"Unit";"Queen";"Hatchery";33;2
"Building";"CreepTumorQueen";NA;39;0
"Building";"CreepTumorQueen";NA;39;0
"Unit";"Overlord";"Larva";39;0
"Building";"Extractor";NA;39;0
"Unit";"Queen";"Hatchery";39;2
"Building";"CreepTumor";NA;47;0
"Building";"CreepTumorQueen";NA;52;0
"Building";"CreepTumorQueen";NA;52;0
"Building";"RoachWarren";NA;43;0
"Building";"CreepTumor";NA;52;0
"Unit";"Overlord";"Larva";58;0
"Unit";"Overlord";"Larva";58;0
"Unit";"Roach";"Larva";58;2
"Unit";"Roach";"Larva";58;2
"Building";"CreepTumor";NA;58;0
"Building";"CreepTumor";NA;58;0
"Building";"CreepTumor";NA;58;0
"Building";"CreepTumor";NA;58;0
"Building";"CreepTumorQueen";NA;58;0
"Unit";"Overlord";"Larva";58;0
"Unit";"Overlord";"Larva";58;0
"Unit";"Roach";"Larva";58;2
"Unit";"Roach";"Larva";58;2
"Unit";"Roach";"Larva";58;2
"Unit";"Roach";"Larva";58;2
"Building";"CreepTumor";NA;62;0
"Building";"CreepTumor";NA;62;0
"Building";"CreepTumor";NA;70;0
"Building";"CreepTumor";NA;70;0
"Building";"CreepTumor";NA;70;0
"Unit";"Roach";"Larva";70;2
"Unit";"Roach";"Larva";70;2
"Unit";"Roach";"Larva";70;2
"Unit";"Roach";"Larva";70;2
"Unit";"Roach";"Larva";70;2
"Unit";"Roach";"Larva";70;2
"Unit";"Roach";"Larva";70;2
"Unit";"Overlord";"Larva";70;0
"Unit";"Overlord";"Larva";70;0
"Unit";"Overlord";"Larva";70;0
"Building";"CreepTumor";NA;84;0
"Building";"CreepTumor";NA;84;0
"Building";"CreepTumor";NA;84;0
"Building";"CreepTumor";NA;84;0
"Building";"CreepTumor";NA;84;0
"Unit";"Roach";"Larva";84;2
"Unit";"Roach";"Larva";84;2
"Unit";"Roach";"Larva";84;2
"Unit";"Roach";"Larva";84;2
"Unit";"Roach";"Larva";84;2
"Unit";"Roach";"Larva";84;2
"Building";"CreepTumor";NA;96;0
"Building";"CreepTumor";NA;96;0
"Unit";"Queen";"Hatchery";84;2
"Unit";"Queen";"Hatchery";84;2
"Unit";"Queen";"Hatchery";84;2
"Unit";"Roach";"Larva";96;2
"Unit";"Roach";"Larva";96;2
"Unit";"Roach";"Larva";96;2
"Upgrade";"GlialReconstitution";"RoachWarren";84;0
"Building";"CreepTumor";NA;102;0
"Building";"CreepTumor";NA;108;0
"Building";"CreepTumor";NA;108;0
"Building";"CreepTumor";NA;108;0
"Building";"CreepTumor";NA;108;0
"Unit";"Overlord";"Larva";108;0
"Unit";"Overlord";"Larva";108;0
"Unit";"Overlord";"Larva";108;0
"Building";"Extractor";NA;114;0
"Building";"Extractor";NA;114;0
"Building";"CreepTumor";NA;114;0
"Building";"CreepTumor";NA;114;0
"Building";"EvolutionChamber";NA;114;0
"Building";"EvolutionChamber";NA;114;0
"Building";"CreepTumor";NA;114;0
"Building";"CreepTumor";NA;119;0
"Building";"CreepTumor";NA;119;0
"Building";"InfestationPit";NA;114;0
"Unit";"Overlord";"Larva";119;0
"Building";"BanelingNest";NA;114;0
"Building";"CreepTumor";NA;126;0
"Building";"CreepTumor";NA;126;0
"Building";"CreepTumor";NA;126;0
"Building";"CreepTumor";NA;126;0
"Building";"CreepTumor";NA;133;0
"Building";"Extractor";NA;133;0
"Building";"Extractor";NA;133;0
"Building";"CreepTumor";NA;138;0
"Building";"CreepTumor";NA;138;0
"Building";"CreepTumor";NA;138;0
"Building";"CreepTumor";NA;138;0
"Building";"Hatchery";NA;136;0
"Building";"UltraliskCavern";NA;150;0
"Unit";"Zergling";"Larva";150;1
"Unit";"Zergling";"Larva";150;1
"Unit";"Zergling";"Larva";150;1
"Unit";"Zergling";"Larva";150;1
"Unit";"Zergling";"Larva";150;1
"Unit";"Zergling";"Larva";150;1
"Unit";"Zergling";"Larva";150;1
"Unit";"Zergling";"Larva";150;1
"Unit";"Zergling";"Larva";150;1
"Unit";"Zergling";"Larva";150;1
"Unit";"Zergling";"Larva";150;1
"Unit";"Zergling";"Larva";150;1
"Unit";"Zergling";"Larva";150;1
"Unit";"Zergling";"Larva";150;1
"Unit";"Zergling";"Larva";150;1
"Unit";"Zergling";"Larva";150;1
"Unit";"Zergling";"Larva";150;1
"Unit";"Zergling";"Larva";150;1
"Unit";"Zergling";"Larva";150;1
"Unit";"Zergling";"Larva";150;1
"Unit";"Zergling";"Larva";150;1
"Unit";"Zergling";"Larva";150;1
"Unit";"Zergling";"Larva";150;1
"Unit";"Zergling";"Larva";150;1
"Unit";"Zergling";"Larva";150;1
"Unit";"Zergling";"Larva";150;1
"Unit";"Zergling";"Larva";150;1
"Unit";"Zergling";"Larva";150;1
"Unit";"Zergling";"Larva";150;1
"Unit";"Zergling";"Larva";150;1
"Unit";"Zergling";"Larva";150;1
"Unit";"Zergling";"Larva";150;1
"Unit";"Zergling";"Larva";150;1
"Unit";"Zergling";"Larva";150;1
"Unit";"Zergling";"Larva";150;1
"Unit";"Zergling";"Larva";150;1
"Unit";"Zergling";"Larva";150;1
"Unit";"Zergling";"Larva";150;1
"Unit";"Zergling";"Larva";150;1
"Unit";"Zergling";"Larva";150;1
"Unit";"Zergling";"Larva";150;1
"Unit";"Zergling";"Larva";150;1
"Upgrade";"ZergGroundArmorsLevel1";"EvolutionChamber";138;0
"Upgrade";"ZergMeleeWeaponsLevel1";"EvolutionChamber";138;0
"Unit";"Overlord";"Larva";150;0
"Unit";"Overlord";"Larva";150;0
"Unit";"Overlord";"Larva";150;0
"Unit";"Overlord";"Larva";150;0
"Unit";"Overlord";"Larva";150;0
"Unit";"Overlord";"Larva";150;0
"Unit";"Overlord";"Larva";150;0
"Unit";"Overlord";"Larva";150;0
"Unit";"Zergling";"Larva";202;1
"Unit";"Zergling";"Larva";202;1
"Unit";"Zergling";"Larva";202;1
"Unit";"Zergling";"Larva";202;1
"Unit";"Zergling";"Larva";202;1
"Unit";"Zergling";"Larva";202;1
"Unit";"Zergling";"Larva";202;1
"Unit";"Zergling";"Larva";202;1
"Unit";"Zergling";"Larva";202;1
"Unit";"Zergling";"Larva";202;1
"Unit";"Zergling";"Larva";202;1
"Unit";"Zergling";"Larva";202;1
"Unit";"Ultralisk";"Larva";192;6
"Unit";"Ultralisk";"Larva";192;6
"Unit";"Ultralisk";"Larva";192;6
"Unit";"Zergling";"Larva";202;1
"Unit";"Zergling";"Larva";202;1
"Unit";"Zergling";"Larva";202;1
"Unit";"Zergling";"Larva";202;1
"Unit";"Zergling";"Larva";202;1
"Unit";"Zergling";"Larva";202;1
"Unit";"Zergling";"Larva";202;1
"Unit";"Zergling";"Larva";202;1
"Unit";"Zergling";"Larva";202;1
"Unit";"Zergling";"Larva";202;1
"Unit";"Zergling";"Larva";202;1
"Unit";"Zergling";"Larva";202;1
"Unit";"Zergling";"Larva";202;1
"Unit";"Zergling";"Larva";202;1
"Unit";"Zergling";"Larva";202;1
"Unit";"Zergling";"Larva";202;1
"Unit";"Zergling";"Larva";202;1
"Unit";"Zergling";"Larva";202;1
"Unit";"Ultralisk";"Larva";202;6
"Upgrade";"ChitinousPlating";"UltraliskCavern";192;0
"Unit";"Ultralisk";"Larva";202;6
"Building";"BanelingNest";NA;202;0
"Unit";"Zergling";"Larva";262;1
"Unit";"Zergling";"Larva";262;1
"Unit";"Zergling";"Larva";262;1
"Unit";"Zergling";"Larva";262;1
"Unit";"Zergling";"Larva";262;1
"Unit";"Zergling";"Larva";262;1
"Unit";"Zergling";"Larva";262;1
"Unit";"Zergling";"Larva";262;1
"Unit";"Zergling";"Larva";262;1
"Unit";"Zergling";"Larva";262;1
"Unit";"Zergling";"Larva";262;1
"Unit";"Zergling";"Larva";262;1
"Unit";"Zergling";"Larva";262;1
"Unit";"Zergling";"Larva";262;1
"Unit";"Zergling";"Larva";262;1
"Unit";"Zergling";"Larva";262;1
"Unit";"Zergling";"Larva";262;1
"Unit";"Zergling";"Larva";262;1
"Unit";"Zergling";"Larva";262;1
"Unit";"Zergling";"Larva";262;1
"Unit";"Zergling";"Larva";262;1
"Unit";"Zergling";"Larva";262;1
"Unit";"Zergling";"Larva";262;1
"Unit";"Zergling";"Larva";262;1
"Unit";"Zergling";"Larva";262;1
"Unit";"Zergling";"Larva";262;1
"Unit";"Zergling";"Larva";262;1
"Unit";"Zergling";"Larva";262;1
"Unit";"Zergling";"Larva";262;1
"Unit";"Zergling";"Larva";262;1
"Unit";"Zergling";"Larva";262;1
"Unit";"Zergling";"Larva";262;1
"Unit";"Zergling";"Larva";262;1
"Unit";"Zergling";"Larva";262;1
"Unit";"Zergling";"Larva";262;1
"Unit";"Zergling";"Larva";262;1
"Unit";"Zergling";"Larva";262;1
"Unit";"Zergling";"Larva";262;1
"Building";"CreepTumor";NA;298;0
"Building";"CreepTumorQueen";NA;300;0
"Building";"CreepTumorQueen";NA;300;0
"Building";"CreepTumorQueen";NA;300;0
"Building";"CreepTumorQueen";NA;300;0
"Upgrade";"ZergGroundArmorsLevel2";"EvolutionChamber";202;0
"Upgrade";"ZergMeleeWeaponsLevel2";"EvolutionChamber";202;0
"Building";"CreepTumor";NA;300;0
"Building";"CreepTumor";NA;300;0
"Unit";"Overlord";"Larva";300;0
"Unit";"Overlord";"Larva";300;0
"Unit";"Overlord";"Larva";300;0
"Building";"CreepTumor";NA;300;0
"Building";"CreepTumor";NA;300;0
"Building";"CreepTumor";NA;300;0
"Building";"CreepTumor";NA;300;0
"Building";"CreepTumor";NA;300;0
"Building";"CreepTumorQueen";NA;300;0
"Building";"CreepTumorQueen";NA;300;0
"Building";"CreepTumorQueen";NA;300;0
"Building";"CreepTumorQueen";NA;300;0
"Unit";"Ultralisk";"Larva";300;6
"Unit";"Ultralisk";"Larva";300;6
"Unit";"Ultralisk";"Larva";300;6
"Building";"Spire";NA;296;0
"Building";"CreepTumor";NA;318;0
"Building";"CreepTumor";NA;318;0
"Building";"CreepTumor";NA;318;0
"Building";"CreepTumor";NA;318;0
"Building";"CreepTumor";NA;318;0
"Building";"CreepTumor";NA;318;0
"Building";"Hatchery";NA;300;0
"Building";"SporeCrawler";NA;318;0
"Building";"SporeCrawler";NA;318;0
"Unit";"Corruptor";"Larva";318;2
"Unit";"Corruptor";"Larva";318;2
"Unit";"Corruptor";"Larva";318;2
"Unit";"Corruptor";"Larva";318;2
"Unit";"Corruptor";"Larva";318;2
"Unit";"Corruptor";"Larva";318;2
"Unit";"Corruptor";"Larva";318;2
"Unit";"Corruptor";"Larva";318;2
"Unit";"Corruptor";"Larva";318;2
"Unit";"Corruptor";"Larva";318;2
"Unit";"Corruptor";"Larva";318;2
"Unit";"Queen";"Hatchery";318;2
"Building";"CreepTumor";NA;318;0
"Building";"CreepTumor";NA;318;0
"Building";"SporeCrawler";NA;318;0
"Building";"Extractor";NA;342;0
"Building";"Extractor";NA;342;0
"Building";"CreepTumor";NA;356;0
"Building";"CreepTumor";NA;356;0
"Building";"CreepTumor";NA;356;0
"Building";"CreepTumor";NA;356;0
"Building";"CreepTumor";NA;356;0
"Building";"CreepTumor";NA;356;0
"Building";"CreepTumor";NA;356;0
"Building";"CreepTumorQueen";NA;356;0
"Building";"CreepTumorQueen";NA;356;0
"Building";"CreepTumorQueen";NA;356;0
"Building";"CreepTumor";NA;356;0
"Upgrade";"ZergGroundArmorsLevel3";"EvolutionChamber";318;0
"Upgrade";"ZergMeleeWeaponsLevel3";"EvolutionChamber";318;0
"Building";"SporeCrawler";NA;356;0
"Unit";"Zergling";"Larva";356;1
"Unit";"Zergling";"Larva";356;1
"Unit";"Zergling";"Larva";356;1
"Unit";"Zergling";"Larva";356;1
"Unit";"Zergling";"Larva";356;1
"Unit";"Zergling";"Larva";356;1
"Unit";"Zergling";"Larva";356;1
"Unit";"Zergling";"Larva";356;1
"Unit";"Zergling";"Larva";356;1
"Unit";"Zergling";"Larva";356;1
"Unit";"Zergling";"Larva";356;1
"Unit";"Zergling";"Larva";356;1
"Unit";"Zergling";"Larva";356;1
"Unit";"Zergling";"Larva";356;1
"Unit";"Zergling";"Larva";356;1
"Unit";"Zergling";"Larva";356;1
"Unit";"Zergling";"Larva";356;1
"Unit";"Zergling";"Larva";356;1
"Unit";"Zergling";"Larva";356;1
"Unit";"Zergling";"Larva";356;1
"Unit";"Zergling";"Larva";356;1
"Unit";"Zergling";"Larva";356;1
"Unit";"Zergling";"Larva";356;1
"Unit";"Zergling";"Larva";356;1
"Building";"SporeCrawler";NA;356;0
"Building";"SpineCrawler";NA;356;0
"Building";"SpineCrawler";NA;356;0
"Building";"SpineCrawler";NA;356;0
"Building";"SpineCrawler";NA;386;0
"Building";"SpineCrawler";NA;386;0
"Unit";"Baneling";"Zergling";386;0
"Unit";"Baneling";"Zergling";386;0
"Unit";"Baneling";"Zergling";386;0
"Unit";"Baneling";"Zergling";386;0
"Building";"CreepTumorQueen";NA;386;0
"Building";"CreepTumorQueen";NA;386;0
"Building";"CreepTumorQueen";NA;386;0
"Building";"CreepTumorQueen";NA;386;0
"Unit";"Corruptor";"Larva";386;2
"Unit";"Corruptor";"Larva";386;2
"Unit";"Corruptor";"Larva";386;2
"Unit";"Corruptor";"Larva";386;2
"Unit";"Queen";"Hatchery";386;2
"Building";"Hatchery";NA;386;0
"Unit";"Zergling";"Larva";394;1
"Unit";"Zergling";"Larva";394;1
"Unit";"Zergling";"Larva";394;1
"Unit";"Zergling";"Larva";394;1
"Unit";"Zergling";"Larva";394;1
"Unit";"Zergling";"Larva";394;1
"Unit";"Zergling";"Larva";394;1
"Unit";"Zergling";"Larva";394;1
"Unit";"Zergling";"Larva";394;1
"Unit";"Zergling";"Larva";394;1
"Unit";"Zergling";"Larva";394;1
"Unit";"Zergling";"Larva";394;1
"Unit";"Zergling";"Larva";394;1
"Unit";"Zergling";"Larva";394;1
"Unit";"Zergling";"Larva";394;1
"Unit";"Zergling";"Larva";394;1
"Unit";"Zergling";"Larva";394;1
"Unit";"Zergling";"Larva";394;1
"Unit";"Zergling";"Larva";394;1
"Unit";"Zergling";"Larva";394;1
"Unit";"Zergling";"Larva";394;1
"Unit";"Zergling";"Larva";394;1
"Unit";"Zergling";"Larva";394;1
"Unit";"Zergling";"Larva";394;1
"Unit";"Zergling";"Larva";394;1
"Unit";"Zergling";"Larva";394;1
"Unit";"Zergling";"Larva";394;1
"Unit";"Zergling";"Larva";394;1
"Unit";"Zergling";"Larva";394;1
"Unit";"Zergling";"Larva";394;1
"Unit";"Zergling";"Larva";394;1
"Unit";"Zergling";"Larva";394;1
"Unit";"Zergling";"Larva";394;1
"Unit";"Zergling";"Larva";394;1
"Unit";"Zergling";"Larva";394;1
"Unit";"Zergling";"Larva";394;1
"Unit";"Zergling";"Larva";394;1
"Unit";"Zergling";"Larva";394;1
"Unit";"Zergling";"Larva";394;1
"Unit";"Zergling";"Larva";394;1
"Unit";"Zergling";"Larva";394;1
"Unit";"Zergling";"Larva";394;1
"Unit";"Zergling";"Larva";394;1
"Unit";"Zergling";"Larva";394;1
"Building";"CreepTumor";NA;451;0
"Building";"CreepTumor";NA;451;0
"Building";"CreepTumor";NA;451;0
"Building";"CreepTumor";NA;451;0
"Building";"CreepTumor";NA;451;0
"Building";"CreepTumor";NA;451;0
"Building";"Extractor";NA;451;0
"Building";"Extractor";NA;451;0
"Upgrade";"ZergMissileWeaponsLevel1";"EvolutionChamber";386;0
"Building";"CreepTumor";NA;451;0
"Building";"CreepTumor";NA;451;0
"Building";"CreepTumor";NA;451;0
"Building";"CreepTumor";NA;454;0
"Building";"CreepTumor";NA;454;0
"Building";"Hatchery";NA;451;0
"Building";"CreepTumor";NA;454;0
"Unit";"Infestor";"Larva";451;2
"Building";"CreepTumor";NA;454;0
"Unit";"Infestor";"Larva";451;2
"Unit";"Infestor";"Larva";451;2
"Unit";"Infestor";"Larva";451;2
"Unit";"Infestor";"Larva";451;2
"Unit";"Infestor";"Larva";451;2
"Unit";"Infestor";"Larva";451;2
"Unit";"Infestor";"Larva";451;2
"Building";"CreepTumor";NA;454;0
"Building";"CreepTumor";NA;454;0
"Upgrade";"Burrow";"Hatchery";451;0
"Building";"SporeCrawler";NA;470;0
"Building";"Extractor";NA;470;0
"Building";"Extractor";NA;470;0
"Building";"CreepTumor";NA;482;0
"Building";"CreepTumor";NA;482;0
"Building";"CreepTumor";NA;482;0
"Building";"SpineCrawler";NA;470;0
"Building";"SpineCrawler";NA;470;0
"Building";"CreepTumor";NA;482;0
"Building";"CreepTumor";NA;482;0
"Unit";"Queen";"Hatchery";470;2
"Building";"CreepTumor";NA;484;0
"Unit";"Zergling";"Larva";484;1
"Unit";"Zergling";"Larva";484;1
"Unit";"Zergling";"Larva";484;1
"Unit";"Zergling";"Larva";484;1
"Unit";"Zergling";"Larva";484;1
"Unit";"Zergling";"Larva";484;1
"Unit";"Zergling";"Larva";484;1
"Unit";"Zergling";"Larva";484;1
"Unit";"Zergling";"Larva";484;1
"Unit";"Zergling";"Larva";484;1
"Unit";"Zergling";"Larva";484;1
"Unit";"Zergling";"Larva";484;1
"Unit";"Zergling";"Larva";484;1
"Unit";"Zergling";"Larva";484;1
"Unit";"Zergling";"Larva";484;1
"Unit";"Zergling";"Larva";484;1
"Building";"CreepTumor";NA;484;0
"Building";"CreepTumor";NA;484;0
"Building";"CreepTumor";NA;484;0
"Building";"CreepTumor";NA;484;0
"Unit";"Infestor";"Larva";484;2
"Unit";"Infestor";"Larva";484;2
"Unit";"Infestor";"Larva";484;2
"Unit";"Infestor";"Larva";484;2
"Unit";"Infestor";"Larva";484;2
"Unit";"Infestor";"Larva";484;2
"Unit";"Infestor";"Larva";484;2
"Unit";"Infestor";"Larva";484;2
"Unit";"Infestor";"Larva";484;2
"Building";"Hatchery";NA;482;0
"Unit";"Infestor";"Larva";518;2
"Unit";"Baneling";"Zergling";520;0
"Unit";"Baneling";"Zergling";520;0
"Unit";"Baneling";"Zergling";520;0
"Unit";"Baneling";"Zergling";520;0
"Unit";"Baneling";"Zergling";520;0
"Unit";"Baneling";"Zergling";520;0
"Unit";"Baneling";"Zergling";520;0
"Unit";"Baneling";"Zergling";520;0
"Unit";"Baneling";"Zergling";520;0
"Unit";"Baneling";"Zergling";520;0
"Unit";"Baneling";"Zergling";520;0
"Unit";"Baneling";"Zergling";520;0
"Unit";"Baneling";"Zergling";520;0
"Unit";"Baneling";"Zergling";520;0
"Unit";"Baneling";"Zergling";520;0
"Unit";"Baneling";"Zergling";520;0
"Building";"CreepTumor";NA;520;0
"Building";"CreepTumor";NA;520;0
"Building";"CreepTumor";NA;520;0
"Building";"CreepTumorQueen";NA;520;0
"Building";"CreepTumorQueen";NA;520;0
"Unit";"Ultralisk";"Larva";520;6
"Unit";"Ultralisk";"Larva";520;6
"Unit";"Ultralisk";"Larva";520;6
"Unit";"Ultralisk";"Larva";520;6
"Building";"CreepTumorQueen";NA;520;0
"Building";"CreepTumorQueen";NA;520;0
"Building";"CreepTumorQueen";NA;544;0
"Building";"CreepTumorQueen";NA;544;0
"Building";"CreepTumorQueen";NA;544;0
"Building";"CreepTumor";NA;544;0
"Building";"CreepTumor";NA;544;0
"Building";"CreepTumor";NA;544;0
"Building";"CreepTumor";NA;544;0
"Building";"CreepTumor";NA;544;0
"Building";"CreepTumor";NA;544;0
"Building";"CreepTumor";NA;544;0
"Building";"CreepTumor";NA;544;0
"Building";"Extractor";NA;544;0
"Building";"Extractor";NA;544;0
"Building";"Hatchery";NA;544;0
"Building";"SporeCrawler";NA;544;0
"Building";"SpineCrawler";NA;544;0
"Building";"SpineCrawler";NA;544;0
"Building";"SpineCrawler";NA;544;0
"Unit";"Zergling";"Larva";544;1
"Unit";"Zergling";"Larva";544;1
"Unit";"Zergling";"Larva";544;1
"Unit";"Zergling";"Larva";544;1
"Unit";"Zergling";"Larva";544;1
"Unit";"Zergling";"Larva";544;1
"Unit";"Zergling";"Larva";544;1
"Unit";"Zergling";"Larva";544;1
"Unit";"Zergling";"Larva";544;1
"Unit";"Zergling";"Larva";544;1
"Unit";"Zergling";"Larva";544;1
"Unit";"Zergling";"Larva";544;1
"Unit";"Zergling";"Larva";544;1
"Unit";"Zergling";"Larva";544;1
"Unit";"Zergling";"Larva";544;1
"Unit";"Zergling";"Larva";544;1
"Unit";"Zergling";"Larva";544;1
"Unit";"Zergling";"Larva";544;1
"Unit";"Zergling";"Larva";544;1
"Unit";"Zergling";"Larva";544;1
"Unit";"Zergling";"Larva";544;1
"Unit";"Zergling";"Larva";544;1
"Unit";"Zergling";"Larva";544;1
"Unit";"Zergling";"Larva";544;1
"Unit";"Zergling";"Larva";544;1
"Unit";"Zergling";"Larva";544;1
"Unit";"Zergling";"Larva";544;1
"Unit";"Zergling";"Larva";544;1
"Unit";"Zergling";"Larva";544;1
"Unit";"Zergling";"Larva";544;1
"Unit";"Zergling";"Larva";544;1
"Unit";"Zergling";"Larva";544;1
"Unit";"Zergling";"Larva";544;1
"Unit";"Zergling";"Larva";544;1
"Unit";"Zergling";"Larva";544;1
"Unit";"Zergling";"Larva";544;1
"Unit";"Zergling";"Larva";544;1
"Unit";"Zergling";"Larva";544;1
"Unit";"Zergling";"Larva";544;1
"Unit";"Zergling";"Larva";544;1
"Unit";"Zergling";"Larva";544;1
"Unit";"Zergling";"Larva";544;1
"Unit";"Zergling";"Larva";544;1
"Unit";"Zergling";"Larva";544;1
"Unit";"Zergling";"Larva";544;1
"Unit";"Zergling";"Larva";544;1
"Unit";"Zergling";"Larva";544;1
"Unit";"Zergling";"Larva";544;1
"Unit";"Zergling";"Larva";544;1
"Unit";"Zergling";"Larva";544;1
"Unit";"Zergling";"Larva";544;1
"Unit";"Zergling";"Larva";544;1
"Unit";"Zergling";"Larva";544;1
"Unit";"Zergling";"Larva";544;1
"Unit";"Zergling";"Larva";544;1
"Unit";"Zergling";"Larva";544;1
"Unit";"Zergling";"Larva";544;1
"Unit";"Zergling";"Larva";544;1
"Unit";"Zergling";"Larva";544;1
"Unit";"Zergling";"Larva";544;1
"Unit";"Zergling";"Larva";544;1
"Unit";"Zergling";"Larva";544;1
"Unit";"Zergling";"Larva";544;1
"Unit";"Zergling";"Larva";544;1
"Unit";"Zergling";"Larva";544;1
"Unit";"Zergling";"Larva";544;1
"Unit";"Zergling";"Larva";544;1
"Unit";"Zergling";"Larva";544;1
"Unit";"Zergling";"Larva";544;1
"Unit";"Zergling";"Larva";544;1
"Unit";"Zergling";"Larva";544;1
"Unit";"Zergling";"Larva";544;1
"Unit";"Zergling";"Larva";544;1
"Unit";"Zergling";"Larva";544;1
"Unit";"Zergling";"Larva";544;1
"Unit";"Zergling";"Larva";544;1
"Unit";"Zergling";"Larva";544;1
"Unit";"Zergling";"Larva";544;1
"Unit";"Zergling";"Larva";544;1
"Unit";"Zergling";"Larva";544;1
"Unit";"Zergling";"Larva";544;1
"Unit";"Zergling";"Larva";544;1
"Unit";"Zergling";"Larva";544;1
"Unit";"Zergling";"Larva";544;1
"Unit";"Zergling";"Larva";544;1
"Unit";"Zergling";"Larva";544;1
"Unit";"Zergling";"Larva";544;1
"Unit";"Zergling";"Larva";544;1
"Unit";"Zergling";"Larva";544;1
"Unit";"Zergling";"Larva";544;1
"Unit";"Zergling";"Larva";544;1
"Unit";"Zergling";"Larva";544;1
"Unit";"Zergling";"Larva";544;1
"Unit";"Zergling";"Larva";544;1
"Unit";"Zergling";"Larva";544;1
"Unit";"Zergling";"Larva";544;1
"Unit";"Zergling";"Larva";544;1
"Unit";"Zergling";"Larva";544;1
"Building";"SporeCrawler";NA;544;0
"Unit";"Baneling";"Zergling";642;0
"Unit";"Baneling";"Zergling";642;0
"Unit";"Baneling";"Zergling";642;0
"Unit";"Baneling";"Zergling";642;0
"Unit";"Baneling";"Zergling";642;0
"Unit";"Baneling";"Zergling";642;0
"Unit";"Baneling";"Zergling";642;0
"Unit";"Baneling";"Zergling";642;0
"Unit";"Baneling";"Zergling";642;0
"Unit";"Baneling";"Zergling";642;0
"Unit";"Baneling";"Zergling";642;0
"Unit";"Baneling";"Zergling";642;0
"Unit";"Baneling";"Zergling";642;0
"Unit";"Baneling";"Zergling";642;0
"Unit";"Baneling";"Zergling";642;0
"Unit";"Baneling";"Zergling";642;0
"Unit";"Baneling";"Zergling";642;0
"Unit";"Baneling";"Zergling";642;0
"Unit";"Baneling";"Zergling";642;0
"Unit";"Baneling";"Zergling";642;0
"Unit";"Baneling";"Zergling";642;0
"Unit";"Baneling";"Zergling";642;0
"Unit";"Baneling";"Zergling";642;0
"Unit";"Baneling";"Zergling";642;0
"Unit";"Baneling";"Zergling";642;0
"Unit";"Baneling";"Zergling";642;0
"Unit";"Baneling";"Zergling";642;0
"Unit";"Baneling";"Zergling";642;0
"Unit";"Baneling";"Zergling";642;0
"Unit";"Baneling";"Zergling";642;0
"Unit";"Baneling";"Zergling";642;0
"Unit";"Baneling";"Zergling";642;0
"Unit";"Baneling";"Zergling";642;0
"Unit";"Baneling";"Zergling";642;0
"Unit";"Baneling";"Zergling";642;0
"Unit";"Baneling";"Zergling";642;0
"Unit";"Baneling";"Zergling";642;0
"Unit";"Baneling";"Zergling";642;0
"Unit";"Baneling";"Zergling";642;0
"Unit";"Baneling";"Zergling";642;0
"Unit";"Baneling";"Zergling";642;0
"Unit";"Baneling";"Zergling";642;0
"Unit";"Baneling";"Zergling";642;0
"Unit";"Baneling";"Zergling";642;0
"Unit";"Baneling";"Zergling";642;0
"Building";"CreepTumor";NA;642;0
"Building";"SporeCrawler";NA;642;0
"Building";"CreepTumor";NA;642;0
"Building";"CreepTumor";NA;642;0
"Building";"CreepTumor";NA;642;0
"Building";"CreepTumor";NA;642;0
"Building";"CreepTumor";NA;642;0
"Building";"CreepTumor";NA;642;0
"Building";"CreepTumorQueen";NA;642;0
"Building";"Extractor";NA;642;0
"Building";"Extractor";NA;642;0
