"type";"unit_name";"on_building";"total_supply";"supply"
"Unit";"Overlord";"Larva";13;0
"Building";"Extractor";NA;18;0
"Unit";"Overlord";"Larva";21;0
"Building";"SpawningPool";NA;19;0
"Building";"Hatchery";NA;17;0
"Unit";"Zergling";"Larva";22;1
"Unit";"Zergling";"Larva";22;1
"Unit";"Zergling";"Larva";23;1
"Unit";"Zergling";"Larva";23;1
"Unit";"Queen";"Hatchery";22;2
"Unit";"Queen";"Hatchery";23;2
"Unit";"Overlord";"Larva";34;0
"Unit";"Overlord";"Larva";39;0
"Building";"Hatchery";NA;29;0
"Building";"CreepTumorQueen";NA;48;0
"Unit";"Overlord";"Larva";46;0
"Unit";"Overlord";"Larva";46;0
"Unit";"Queen";"Hatchery";41;2
"Building";"Extractor";NA;48;0
"Building";"Extractor";NA;48;0
"Unit";"Queen";"Hatchery";46;2
"Building";"EvolutionChamber";NA;48;0
"Building";"EvolutionChamber";NA;48;0
"Building";"CreepTumor";NA;66;0
"Building";"CreepTumorQueen";NA;66;0
"Unit";"Zergling";"Larva";66;1
"Unit";"Zergling";"Larva";66;1
"Unit";"Zergling";"Larva";66;1
"Unit";"Zergling";"Larva";66;1
"Unit";"Zergling";"Larva";66;1
"Unit";"Zergling";"Larva";66;1
"Unit";"Zergling";"Larva";66;1
"Unit";"Zergling";"Larva";66;1
"Building";"CreepTumor";NA;66;0
"Unit";"Queen";"Hatchery";66;2
"Building";"CreepTumor";NA;74;0
"Unit";"Zergling";"Larva";66;1
"Unit";"Zergling";"Larva";66;1
"Unit";"Queen";"Hatchery";66;2
"Unit";"Zergling";"Larva";66;1
"Unit";"Zergling";"Larva";66;1
"Unit";"Overlord";"Larva";74;0
"Unit";"Overlord";"Larva";74;0
"Unit";"Overlord";"Larva";74;0
"Unit";"Overlord";"Larva";74;0
"Building";"CreepTumor";NA;82;0
"Building";"CreepTumorQueen";NA;82;0
"Building";"CreepTumorQueen";NA;82;0
"Unit";"Zergling";"Larva";82;1
"Unit";"Zergling";"Larva";82;1
"Unit";"Zergling";"Larva";82;1
"Unit";"Zergling";"Larva";82;1
"Unit";"Zergling";"Larva";82;1
"Unit";"Zergling";"Larva";82;1
"Unit";"Zergling";"Larva";82;1
"Unit";"Zergling";"Larva";82;1
"Unit";"Zergling";"Larva";82;1
"Unit";"Zergling";"Larva";82;1
"Unit";"Zergling";"Larva";82;1
"Unit";"Zergling";"Larva";82;1
"Building";"CreepTumor";NA;82;0
"Building";"CreepTumorQueen";NA;82;0
"Unit";"Queen";"Hatchery";82;2
"Unit";"Overlord";"Larva";101;0
"Unit";"Overlord";"Larva";101;0
"Building";"CreepTumor";NA;102;0
"Building";"CreepTumor";NA;102;0
"Building";"CreepTumor";NA;104;0
"Building";"CreepTumor";NA;104;0
"Upgrade";"ZergMeleeWeaponsLevel1";"EvolutionChamber";66;0
"Building";"BanelingNest";NA;89;0
"Unit";"Overlord";"Larva";104;0
"Unit";"Overlord";"Larva";104;0
"Unit";"Overlord";"Larva";104;0
"Building";"Extractor";NA;112;0
"Upgrade";"ZergGroundArmorsLevel1";"EvolutionChamber";82;0
"Unit";"Zergling";"Larva";112;1
"Unit";"Zergling";"Larva";112;1
"Building";"Extractor";NA;112;0
"Unit";"Zergling";"Larva";112;1
"Unit";"Zergling";"Larva";112;1
"Unit";"Zergling";"Larva";116;1
"Unit";"Zergling";"Larva";116;1
"Unit";"Baneling";"Zergling";117;0
"Unit";"Baneling";"Zergling";117;0
"Unit";"Baneling";"Zergling";117;0
"Unit";"Zergling";"Larva";117;1
"Unit";"Zergling";"Larva";117;1
"Unit";"Zergling";"Larva";117;1
"Unit";"Zergling";"Larva";117;1
"Unit";"Zergling";"Larva";117;1
"Unit";"Zergling";"Larva";117;1
"Unit";"Zergling";"Larva";117;1
"Unit";"Zergling";"Larva";117;1
"Unit";"Zergling";"Larva";117;1
"Unit";"Zergling";"Larva";117;1
"Unit";"Zergling";"Larva";117;1
"Unit";"Zergling";"Larva";117;1
"Building";"CreepTumor";NA;127;0
"Building";"CreepTumor";NA;127;0
"Building";"CreepTumorQueen";NA;135;0
"Building";"CreepTumorQueen";NA;135;0
"Unit";"Zergling";"Larva";135;1
"Unit";"Zergling";"Larva";135;1
"Unit";"Zergling";"Larva";135;1
"Unit";"Zergling";"Larva";135;1
"Unit";"Zergling";"Larva";135;1
"Unit";"Zergling";"Larva";135;1
"Unit";"Zergling";"Larva";135;1
"Unit";"Zergling";"Larva";135;1
"Unit";"Zergling";"Larva";135;1
"Unit";"Zergling";"Larva";135;1
"Unit";"Zergling";"Larva";135;1
"Unit";"Zergling";"Larva";135;1
"Unit";"Zergling";"Larva";135;1
"Unit";"Zergling";"Larva";135;1
"Building";"Hatchery";NA;104;0
"Building";"Spire";NA;112;0
"Unit";"Overlord";"Larva";135;0
"Unit";"Overlord";"Larva";135;0
"Unit";"Overlord";"Larva";135;0
"Unit";"Overlord";"Larva";135;0
"Building";"Extractor";NA;135;0
"Building";"CreepTumorQueen";NA;154;0
"Building";"CreepTumorQueen";NA;154;0
"Building";"CreepTumorQueen";NA;154;0
"Unit";"Baneling";"Zergling";154;0
"Unit";"Baneling";"Zergling";154;0
"Building";"SporeCrawler";NA;154;0
"Unit";"Zergling";"Larva";154;1
"Unit";"Zergling";"Larva";154;1
"Unit";"Zergling";"Larva";154;1
"Unit";"Zergling";"Larva";154;1
"Unit";"Zergling";"Larva";154;1
"Unit";"Zergling";"Larva";154;1
"Unit";"Zergling";"Larva";154;1
"Unit";"Zergling";"Larva";154;1
"Unit";"Zergling";"Larva";154;1
"Unit";"Zergling";"Larva";154;1
"Unit";"Zergling";"Larva";154;1
"Unit";"Zergling";"Larva";154;1
"Unit";"Zergling";"Larva";154;1
"Unit";"Zergling";"Larva";154;1
"Unit";"Zergling";"Larva";154;1
"Unit";"Zergling";"Larva";154;1
"Building";"CreepTumor";NA;160;0
"Building";"CreepTumor";NA;160;0
"Unit";"Mutalisk";"Larva";154;2
"Unit";"Mutalisk";"Larva";154;2
"Unit";"Mutalisk";"Larva";154;2
"Unit";"Mutalisk";"Larva";154;2
"Unit";"Mutalisk";"Larva";160;2
"Unit";"Mutalisk";"Larva";160;2
"Unit";"Mutalisk";"Larva";160;2
"Unit";"Overlord";"Larva";176;0
"Unit";"Overlord";"Larva";176;0
"Unit";"Queen";"Hatchery";154;2
"Unit";"Zergling";"Larva";184;1
"Unit";"Zergling";"Larva";184;1
"Unit";"Zergling";"Larva";184;1
"Unit";"Zergling";"Larva";184;1
"Unit";"Zergling";"Larva";184;1
"Unit";"Zergling";"Larva";184;1
"Unit";"Zergling";"Larva";184;1
"Unit";"Zergling";"Larva";184;1
"Unit";"Zergling";"Larva";184;1
"Unit";"Zergling";"Larva";184;1
"Upgrade";"ZergMeleeWeaponsLevel2";"EvolutionChamber";136;0
"Unit";"Mutalisk";"Larva";188;2
"Unit";"Mutalisk";"Larva";192;2
"Unit";"Mutalisk";"Larva";192;2
"Building";"InfestationPit";NA;184;0
"Building";"CreepTumor";NA;205;0
"Unit";"Zergling";"Larva";205;1
"Unit";"Zergling";"Larva";205;1
"Unit";"Zergling";"Larva";205;1
"Unit";"Zergling";"Larva";205;1
"Unit";"Zergling";"Larva";205;1
"Unit";"Zergling";"Larva";205;1
"Unit";"Zergling";"Larva";205;1
"Unit";"Zergling";"Larva";205;1
"Unit";"Zergling";"Larva";205;1
"Unit";"Zergling";"Larva";205;1
"Unit";"Mutalisk";"Larva";205;2
"Unit";"Mutalisk";"Larva";205;2
"Upgrade";"ZergGroundArmorsLevel2";"EvolutionChamber";154;0
"Building";"CreepTumorQueen";NA;221;0
"Building";"CreepTumor";NA;221;0
"Building";"CreepTumor";NA;229;0
"Building";"CreepTumor";NA;229;0
"Building";"CreepTumorQueen";NA;229;0
"Building";"CreepTumorQueen";NA;233;0
"Building";"Hatchery";NA;176;0
"Building";"Hatchery";NA;184;0
"Unit";"Zergling";"Larva";233;1
"Unit";"Zergling";"Larva";233;1
"Unit";"Zergling";"Larva";233;1
"Unit";"Zergling";"Larva";233;1
"Unit";"Zergling";"Larva";233;1
"Unit";"Zergling";"Larva";233;1
"Unit";"Zergling";"Larva";233;1
"Unit";"Zergling";"Larva";233;1
"Unit";"Zergling";"Larva";233;1
"Unit";"Zergling";"Larva";233;1
"Unit";"Zergling";"Larva";233;1
"Unit";"Zergling";"Larva";233;1
"Unit";"Zergling";"Larva";233;1
"Unit";"Zergling";"Larva";233;1
"Unit";"Overlord";"Larva";233;0
"Unit";"Overlord";"Larva";233;0
"Unit";"Overlord";"Larva";233;0
"Unit";"Overlord";"Larva";233;0
"Building";"CreepTumorQueen";NA;247;0
"Building";"CreepTumorQueen";NA;247;0
"Unit";"Zergling";"Larva";247;1
"Unit";"Zergling";"Larva";247;1
"Unit";"Zergling";"Larva";247;1
"Unit";"Zergling";"Larva";247;1
"Unit";"Zergling";"Larva";247;1
"Unit";"Zergling";"Larva";247;1
"Unit";"Zergling";"Larva";247;1
"Unit";"Zergling";"Larva";247;1
"Unit";"Zergling";"Larva";247;1
"Unit";"Zergling";"Larva";247;1
"Unit";"Zergling";"Larva";247;1
"Unit";"Zergling";"Larva";247;1
"Unit";"Zergling";"Larva";247;1
"Unit";"Zergling";"Larva";247;1
"Unit";"Zergling";"Larva";247;1
"Unit";"Zergling";"Larva";247;1
"Unit";"Baneling";"Zergling";247;0
"Unit";"Baneling";"Zergling";247;0
"Unit";"Baneling";"Zergling";247;0
"Unit";"Baneling";"Zergling";247;0
"Building";"Extractor";NA;263;0
"Building";"CreepTumor";NA;263;0
"Building";"Extractor";NA;263;0
"Building";"CreepTumorQueen";NA;263;0
"Unit";"Queen";"Hatchery";263;2
"Building";"Extractor";NA;263;0
"Building";"Extractor";NA;263;0
"Unit";"Zergling";"Larva";273;1
"Unit";"Zergling";"Larva";273;1
"Building";"CreepTumor";NA;275;0
"Unit";"Zergling";"Larva";273;1
"Unit";"Zergling";"Larva";273;1
"Unit";"Zergling";"Larva";273;1
"Unit";"Zergling";"Larva";273;1
"Unit";"Zergling";"Larva";273;1
"Unit";"Zergling";"Larva";273;1
"Unit";"Zergling";"Larva";273;1
"Unit";"Zergling";"Larva";273;1
"Unit";"Zergling";"Larva";273;1
"Unit";"Zergling";"Larva";273;1
"Unit";"Zergling";"Larva";273;1
"Unit";"Zergling";"Larva";273;1
"Unit";"Zergling";"Larva";273;1
"Unit";"Zergling";"Larva";273;1
"Unit";"Zergling";"Larva";273;1
"Unit";"Zergling";"Larva";273;1
"Unit";"Zergling";"Larva";273;1
"Unit";"Zergling";"Larva";273;1
"Unit";"Zergling";"Larva";273;1
"Unit";"Zergling";"Larva";273;1
"Unit";"Zergling";"Larva";273;1
"Unit";"Zergling";"Larva";273;1
"Unit";"Zergling";"Larva";273;1
"Unit";"Zergling";"Larva";273;1
"Unit";"Zergling";"Larva";273;1
"Unit";"Zergling";"Larva";273;1
"Unit";"Viper";"Larva";273;3
"Unit";"Viper";"Larva";273;3
"Unit";"Zergling";"Larva";275;1
"Unit";"Zergling";"Larva";275;1
"Unit";"Zergling";"Larva";275;1
"Unit";"Zergling";"Larva";275;1
"Unit";"Zergling";"Larva";275;1
"Unit";"Zergling";"Larva";275;1
"Unit";"Zergling";"Larva";275;1
"Unit";"Zergling";"Larva";275;1
"Unit";"Zergling";"Larva";275;1
"Unit";"Zergling";"Larva";275;1
"Unit";"Zergling";"Larva";275;1
"Unit";"Zergling";"Larva";275;1
"Unit";"Zergling";"Larva";275;1
"Unit";"Zergling";"Larva";275;1
"Unit";"Baneling";"Zergling";275;0
"Unit";"Zergling";"Larva";275;1
"Unit";"Zergling";"Larva";275;1
"Unit";"Baneling";"Zergling";275;0
"Unit";"Baneling";"Zergling";275;0
"Unit";"Baneling";"Zergling";275;0
"Unit";"Baneling";"Zergling";275;0
"Unit";"Baneling";"Zergling";275;0
"Unit";"Baneling";"Zergling";275;0
"Unit";"Baneling";"Zergling";275;0
"Unit";"Baneling";"Zergling";275;0
"Unit";"Baneling";"Zergling";275;0
"Unit";"Viper";"Larva";273;3
"Unit";"Viper";"Larva";273;3
"Unit";"Viper";"Larva";273;3
"Unit";"Viper";"Larva";273;3
"Unit";"Zergling";"Larva";303;1
"Unit";"Zergling";"Larva";303;1
"Unit";"Zergling";"Larva";303;1
"Unit";"Zergling";"Larva";303;1
"Unit";"Zergling";"Larva";303;1
"Unit";"Zergling";"Larva";303;1
"Unit";"Zergling";"Larva";303;1
"Unit";"Zergling";"Larva";303;1
"Unit";"Zergling";"Larva";303;1
"Unit";"Zergling";"Larva";303;1
"Unit";"Zergling";"Larva";303;1
"Unit";"Zergling";"Larva";303;1
"Unit";"Zergling";"Larva";303;1
"Unit";"Zergling";"Larva";303;1
"Unit";"Zergling";"Larva";303;1
"Unit";"Zergling";"Larva";303;1
"Building";"UltraliskCavern";NA;273;0
"Unit";"Zergling";"Larva";353;1
"Unit";"Zergling";"Larva";353;1
"Unit";"Zergling";"Larva";353;1
"Unit";"Zergling";"Larva";353;1
"Unit";"Zergling";"Larva";353;1
"Unit";"Zergling";"Larva";353;1
"Unit";"Zergling";"Larva";353;1
"Unit";"Zergling";"Larva";353;1
"Unit";"Overlord";"Larva";353;0
"Unit";"Overlord";"Larva";353;0
"Unit";"Overlord";"Larva";353;0
"Unit";"Zergling";"Larva";361;1
"Unit";"Zergling";"Larva";361;1
"Unit";"Zergling";"Larva";361;1
"Unit";"Zergling";"Larva";361;1
"Unit";"Zergling";"Larva";361;1
"Unit";"Zergling";"Larva";361;1
"Unit";"Zergling";"Larva";361;1
"Unit";"Zergling";"Larva";361;1
"Unit";"Zergling";"Larva";361;1
"Unit";"Zergling";"Larva";361;1
"Unit";"Zergling";"Larva";361;1
"Unit";"Zergling";"Larva";361;1
"Unit";"Zergling";"Larva";361;1
"Unit";"Zergling";"Larva";361;1
"Unit";"Zergling";"Larva";361;1
"Unit";"Zergling";"Larva";361;1
"Unit";"Zergling";"Larva";361;1
"Unit";"Zergling";"Larva";361;1
"Unit";"Zergling";"Larva";361;1
"Unit";"Zergling";"Larva";361;1
"Unit";"Zergling";"Larva";361;1
"Unit";"Zergling";"Larva";361;1
"Unit";"Zergling";"Larva";361;1
"Unit";"Zergling";"Larva";361;1
"Unit";"Zergling";"Larva";361;1
"Unit";"Zergling";"Larva";361;1
"Unit";"Zergling";"Larva";361;1
"Unit";"Zergling";"Larva";361;1
"Unit";"Zergling";"Larva";361;1
"Unit";"Zergling";"Larva";361;1
"Unit";"Zergling";"Larva";361;1
"Unit";"Zergling";"Larva";361;1
"Unit";"Zergling";"Larva";361;1
"Unit";"Zergling";"Larva";361;1
"Unit";"Zergling";"Larva";361;1
"Unit";"Zergling";"Larva";361;1
"Unit";"Zergling";"Larva";361;1
"Unit";"Zergling";"Larva";361;1
"Unit";"Zergling";"Larva";361;1
"Unit";"Zergling";"Larva";361;1
"Unit";"Zergling";"Larva";361;1
"Unit";"Zergling";"Larva";361;1
"Unit";"Zergling";"Larva";361;1
"Unit";"Zergling";"Larva";361;1
"Unit";"Zergling";"Larva";361;1
"Unit";"Zergling";"Larva";361;1
"Unit";"Zergling";"Larva";361;1
"Unit";"Zergling";"Larva";361;1
"Unit";"Baneling";"Zergling";393;0
"Unit";"Baneling";"Zergling";393;0
"Unit";"Baneling";"Zergling";393;0
"Unit";"Baneling";"Zergling";393;0
"Unit";"Baneling";"Zergling";393;0
"Unit";"Zergling";"Larva";399;1
"Unit";"Zergling";"Larva";399;1
"Unit";"Zergling";"Larva";405;1
"Unit";"Zergling";"Larva";405;1
"Unit";"Zergling";"Larva";405;1
"Unit";"Zergling";"Larva";405;1
"Unit";"Zergling";"Larva";405;1
"Unit";"Zergling";"Larva";405;1
"Unit";"Zergling";"Larva";405;1
"Unit";"Zergling";"Larva";405;1
"Unit";"Zergling";"Larva";405;1
"Unit";"Zergling";"Larva";405;1
"Unit";"Zergling";"Larva";405;1
"Unit";"Zergling";"Larva";405;1
"Unit";"Baneling";"Zergling";405;0
"Unit";"Baneling";"Zergling";405;0
"Unit";"Baneling";"Zergling";405;0
"Unit";"Baneling";"Zergling";405;0
"Unit";"Baneling";"Zergling";405;0
"Unit";"Baneling";"Zergling";405;0
"Unit";"Baneling";"Zergling";405;0
"Unit";"Baneling";"Zergling";405;0
"Unit";"Ultralisk";"Larva";361;6
"Upgrade";"ChitinousPlating";"UltraliskCavern";361;0
"Unit";"Zergling";"Larva";409;1
"Unit";"Zergling";"Larva";409;1
"Unit";"Zergling";"Larva";411;1
"Unit";"Zergling";"Larva";411;1
"Unit";"Zergling";"Larva";411;1
"Unit";"Zergling";"Larva";411;1
"Unit";"Zergling";"Larva";411;1
"Unit";"Zergling";"Larva";411;1
"Unit";"Zergling";"Larva";413;1
"Unit";"Zergling";"Larva";413;1
"Unit";"Zergling";"Larva";413;1
"Unit";"Zergling";"Larva";413;1
"Unit";"Zergling";"Larva";417;1
"Unit";"Zergling";"Larva";417;1
"Unit";"Ultralisk";"Larva";393;6
"Unit";"Ultralisk";"Larva";393;6
"Unit";"Zergling";"Larva";423;1
"Unit";"Zergling";"Larva";423;1
"Unit";"Zergling";"Larva";423;1
"Unit";"Zergling";"Larva";423;1
"Unit";"Zergling";"Larva";423;1
"Unit";"Zergling";"Larva";423;1
"Unit";"Zergling";"Larva";423;1
"Unit";"Zergling";"Larva";423;1
"Unit";"Zergling";"Larva";423;1
"Unit";"Zergling";"Larva";423;1
"Unit";"Zergling";"Larva";423;1
"Unit";"Zergling";"Larva";423;1
"Unit";"Zergling";"Larva";423;1
"Unit";"Zergling";"Larva";423;1
"Unit";"Zergling";"Larva";423;1
"Unit";"Zergling";"Larva";423;1
"Unit";"Zergling";"Larva";423;1
"Unit";"Zergling";"Larva";423;1
"Unit";"Zergling";"Larva";423;1
"Unit";"Zergling";"Larva";423;1
"Unit";"Baneling";"Zergling";429;0
"Unit";"Baneling";"Zergling";429;0
"Unit";"Baneling";"Zergling";429;0
"Unit";"Baneling";"Zergling";429;0
"Unit";"Baneling";"Zergling";429;0
"Unit";"Zergling";"Larva";423;1
"Unit";"Zergling";"Larva";423;1
"Unit";"Zergling";"Larva";423;1
"Unit";"Zergling";"Larva";423;1
"Unit";"Zergling";"Larva";423;1
"Unit";"Zergling";"Larva";423;1
"Unit";"Zergling";"Larva";423;1
"Unit";"Zergling";"Larva";423;1
"Unit";"Zergling";"Larva";429;1
"Unit";"Zergling";"Larva";429;1
"Unit";"Zergling";"Larva";429;1
"Unit";"Zergling";"Larva";429;1
"Unit";"Zergling";"Larva";443;1
"Unit";"Zergling";"Larva";443;1
"Unit";"Zergling";"Larva";443;1
"Unit";"Zergling";"Larva";443;1
"Unit";"Zergling";"Larva";443;1
"Unit";"Zergling";"Larva";443;1
"Unit";"Zergling";"Larva";443;1
"Unit";"Zergling";"Larva";443;1
"Unit";"Zergling";"Larva";443;1
"Unit";"Zergling";"Larva";443;1
"Unit";"Zergling";"Larva";443;1
"Unit";"Zergling";"Larva";443;1
"Unit";"Zergling";"Larva";475;1
"Unit";"Zergling";"Larva";475;1
"Unit";"Corruptor";"Larva";487;2
"Unit";"Corruptor";"Larva";487;2
"Unit";"Corruptor";"Larva";487;2
"Unit";"Corruptor";"Larva";487;2
"Unit";"Corruptor";"Larva";487;2
"Unit";"Corruptor";"Larva";487;2
"Unit";"Corruptor";"Larva";487;2
"Building";"CreepTumor";NA;501;0
"Unit";"Zergling";"Larva";501;1
"Unit";"Zergling";"Larva";501;1
"Unit";"Baneling";"Zergling";515;0
"Unit";"Zergling";"Larva";501;1
"Unit";"Zergling";"Larva";501;1
"Unit";"Zergling";"Larva";501;1
"Unit";"Zergling";"Larva";501;1
"Unit";"Baneling";"Zergling";515;0
"Unit";"Zergling";"Larva";501;1
"Unit";"Zergling";"Larva";501;1
"Unit";"Zergling";"Larva";501;1
"Unit";"Zergling";"Larva";501;1
"Unit";"Zergling";"Larva";501;1
"Unit";"Zergling";"Larva";501;1
"Unit";"Baneling";"Zergling";515;0
"Unit";"Baneling";"Zergling";515;0
"Unit";"Zergling";"Larva";501;1
"Unit";"Zergling";"Larva";501;1
"Unit";"Zergling";"Larva";501;1
"Unit";"Zergling";"Larva";501;1
"Unit";"Zergling";"Larva";501;1
"Unit";"Zergling";"Larva";501;1
"Unit";"Zergling";"Larva";501;1
"Unit";"Zergling";"Larva";501;1
"Unit";"Zergling";"Larva";501;1
"Unit";"Zergling";"Larva";501;1
"Upgrade";"ZergMeleeWeaponsLevel3";"EvolutionChamber";361;0
"Upgrade";"ZergGroundArmorsLevel3";"EvolutionChamber";361;0
"Unit";"Ultralisk";"Larva";501;6
"Unit";"Ultralisk";"Larva";501;6
"Unit";"Zergling";"Larva";537;1
"Unit";"Zergling";"Larva";537;1
"Unit";"Zergling";"Larva";537;1
"Unit";"Zergling";"Larva";537;1
"Unit";"Zergling";"Larva";537;1
"Unit";"Zergling";"Larva";537;1
"Unit";"Zergling";"Larva";537;1
"Unit";"Zergling";"Larva";537;1
"Unit";"Zergling";"Larva";537;1
"Unit";"Zergling";"Larva";537;1
"Unit";"Zergling";"Larva";537;1
"Unit";"Zergling";"Larva";537;1
"Unit";"Zergling";"Larva";537;1
"Unit";"Zergling";"Larva";537;1
"Unit";"Zergling";"Larva";537;1
"Unit";"Zergling";"Larva";537;1
"Unit";"Zergling";"Larva";537;1
"Unit";"Zergling";"Larva";537;1
"Unit";"Zergling";"Larva";537;1
"Unit";"Zergling";"Larva";537;1
"Unit";"Zergling";"Larva";537;1
"Unit";"Zergling";"Larva";537;1
"Unit";"Zergling";"Larva";537;1
"Unit";"Zergling";"Larva";537;1
"Unit";"Zergling";"Larva";537;1
"Unit";"Zergling";"Larva";537;1
"Unit";"Baneling";"Zergling";549;0
"Unit";"Baneling";"Zergling";549;0
"Unit";"Baneling";"Zergling";549;0
"Unit";"Baneling";"Zergling";549;0
"Unit";"Baneling";"Zergling";549;0
"Unit";"Baneling";"Zergling";549;0
"Unit";"Baneling";"Zergling";549;0
"Unit";"Baneling";"Zergling";549;0
"Unit";"Baneling";"Zergling";549;0
"Building";"HydraliskDen";NA;549;0
"Building";"Extractor";NA;575;0
"Unit";"Zergling";"Larva";575;1
"Unit";"Zergling";"Larva";575;1
"Unit";"Zergling";"Larva";582;1
"Unit";"Zergling";"Larva";582;1
"Unit";"Zergling";"Larva";582;1
"Unit";"Zergling";"Larva";582;1
"Unit";"Zergling";"Larva";582;1
"Unit";"Zergling";"Larva";582;1
"Unit";"Zergling";"Larva";582;1
"Unit";"Zergling";"Larva";582;1
"Unit";"Zergling";"Larva";582;1
"Unit";"Zergling";"Larva";582;1
"Unit";"Zergling";"Larva";582;1
"Unit";"Zergling";"Larva";582;1
"Unit";"Zergling";"Larva";582;1
"Unit";"Zergling";"Larva";582;1
"Unit";"Zergling";"Larva";582;1
"Unit";"Zergling";"Larva";582;1
"Building";"Extractor";NA;575;0
"Building";"CreepTumorQueen";NA;600;0
"Unit";"Baneling";"Zergling";600;0
"Unit";"Baneling";"Zergling";600;0
"Unit";"Baneling";"Zergling";600;0
"Unit";"Baneling";"Zergling";600;0
"Unit";"Baneling";"Zergling";600;0
"Unit";"Baneling";"Zergling";600;0
"Unit";"Baneling";"Zergling";600;0
"Unit";"Baneling";"Zergling";600;0
"Unit";"Baneling";"Zergling";600;0
"Unit";"Baneling";"Zergling";600;0
"Unit";"Baneling";"Zergling";600;0
"Unit";"Baneling";"Zergling";600;0
"Unit";"Zergling";"Larva";600;1
"Unit";"Zergling";"Larva";600;1
"Unit";"Zergling";"Larva";600;1
"Unit";"Zergling";"Larva";600;1
"Unit";"Zergling";"Larva";600;1
"Unit";"Zergling";"Larva";600;1
"Unit";"Zergling";"Larva";600;1
"Unit";"Zergling";"Larva";600;1
"Unit";"Zergling";"Larva";600;1
"Unit";"Zergling";"Larva";600;1
"Unit";"Zergling";"Larva";600;1
"Unit";"Zergling";"Larva";600;1
"Unit";"Zergling";"Larva";600;1
"Unit";"Zergling";"Larva";600;1
"Unit";"Zergling";"Larva";600;1
"Unit";"Zergling";"Larva";600;1
"Unit";"Zergling";"Larva";600;1
"Unit";"Zergling";"Larva";600;1
"Unit";"Zergling";"Larva";600;1
"Unit";"Zergling";"Larva";600;1
"Unit";"Zergling";"Larva";600;1
"Unit";"Zergling";"Larva";600;1
"Unit";"Zergling";"Larva";600;1
"Unit";"Zergling";"Larva";600;1
"Unit";"Zergling";"Larva";600;1
"Unit";"Zergling";"Larva";600;1
"Unit";"Zergling";"Larva";600;1
"Unit";"Zergling";"Larva";600;1
"Unit";"Zergling";"Larva";600;1
"Unit";"Zergling";"Larva";600;1
"Unit";"Zergling";"Larva";600;1
"Unit";"Zergling";"Larva";600;1
"Building";"Hatchery";NA;575;0
"Upgrade";"ZergMissileWeaponsLevel1";"EvolutionChamber";575;0
"Unit";"Corruptor";"Larva";632;2
"Unit";"Corruptor";"Larva";632;2
"Unit";"Corruptor";"Larva";632;2
"Unit";"Corruptor";"Larva";632;2
"Unit";"Corruptor";"Larva";632;2
"Unit";"Corruptor";"Larva";632;2
"Unit";"Corruptor";"Larva";632;2
"Unit";"Corruptor";"Larva";632;2
"Unit";"Corruptor";"Larva";632;2
"Unit";"Corruptor";"Larva";632;2
"Building";"CreepTumor";NA;644;0
"Unit";"Corruptor";"Larva";644;2
"Unit";"Corruptor";"Larva";644;2
"Unit";"Corruptor";"Larva";644;2
"Unit";"Corruptor";"Larva";644;2
"Unit";"Zergling";"Larva";668;1
"Unit";"Zergling";"Larva";668;1
"Unit";"Zergling";"Larva";668;1
"Unit";"Zergling";"Larva";668;1
"Unit";"Baneling";"Zergling";668;0
"Unit";"Zergling";"Larva";668;1
"Unit";"Zergling";"Larva";668;1
"Unit";"Zergling";"Larva";668;1
"Unit";"Zergling";"Larva";668;1
"Unit";"Zergling";"Larva";668;1
"Unit";"Zergling";"Larva";668;1
"Unit";"Zergling";"Larva";668;1
"Unit";"Zergling";"Larva";668;1
"Unit";"Zergling";"Larva";668;1
"Unit";"Zergling";"Larva";668;1
"Unit";"Zergling";"Larva";668;1
"Unit";"Zergling";"Larva";668;1
"Unit";"Zergling";"Larva";668;1
"Unit";"Zergling";"Larva";668;1
"Unit";"Zergling";"Larva";668;1
"Unit";"Zergling";"Larva";668;1
"Unit";"Zergling";"Larva";668;1
"Unit";"Zergling";"Larva";668;1
"Unit";"Zergling";"Larva";668;1
"Unit";"Zergling";"Larva";668;1
"Unit";"Baneling";"Zergling";668;0
"Unit";"Baneling";"Zergling";668;0
"Unit";"Baneling";"Zergling";668;0
"Unit";"Baneling";"Zergling";668;0
"Unit";"Ultralisk";"Larva";652;6
"Unit";"Zergling";"Larva";668;1
"Unit";"Zergling";"Larva";668;1
"Unit";"Zergling";"Larva";668;1
"Unit";"Zergling";"Larva";668;1
"Unit";"Zergling";"Larva";668;1
"Unit";"Zergling";"Larva";668;1
"Unit";"Zergling";"Larva";668;1
"Unit";"Zergling";"Larva";668;1
"Unit";"Zergling";"Larva";668;1
"Unit";"Zergling";"Larva";668;1
"Unit";"Zergling";"Larva";668;1
"Unit";"Zergling";"Larva";668;1
"Building";"CreepTumor";NA;710;0
"Unit";"Zergling";"Larva";710;1
"Unit";"Zergling";"Larva";710;1
"Unit";"Zergling";"Larva";710;1
"Unit";"Zergling";"Larva";710;1
"Unit";"Zergling";"Larva";710;1
"Unit";"Zergling";"Larva";710;1
"Unit";"Zergling";"Larva";710;1
"Unit";"Zergling";"Larva";710;1
"Unit";"Baneling";"Zergling";718;0
"Unit";"Baneling";"Zergling";718;0
"Unit";"Baneling";"Zergling";718;0
"Unit";"Baneling";"Zergling";718;0
"Unit";"Baneling";"Zergling";718;0
"Unit";"Baneling";"Zergling";718;0
"Unit";"Baneling";"Zergling";718;0
"Unit";"Zergling";"Larva";718;1
"Unit";"Zergling";"Larva";718;1
"Unit";"Zergling";"Larva";718;1
"Unit";"Zergling";"Larva";718;1
"Unit";"Zergling";"Larva";718;1
"Unit";"Zergling";"Larva";718;1
"Unit";"Zergling";"Larva";718;1
"Unit";"Zergling";"Larva";718;1
"Unit";"Zergling";"Larva";718;1
"Unit";"Zergling";"Larva";718;1
"Unit";"Corruptor";"Larva";718;2
"Unit";"Corruptor";"Larva";718;2
"Unit";"Corruptor";"Larva";718;2
"Unit";"Corruptor";"Larva";718;2
"Unit";"Corruptor";"Larva";718;2
"Unit";"Corruptor";"Larva";718;2
"Building";"Hatchery";NA;718;0
"Unit";"Zergling";"Larva";740;1
"Unit";"Zergling";"Larva";740;1
"Unit";"Zergling";"Larva";740;1
"Unit";"Zergling";"Larva";740;1
"Unit";"Zergling";"Larva";740;1
"Unit";"Zergling";"Larva";740;1
"Unit";"Zergling";"Larva";740;1
"Unit";"Zergling";"Larva";740;1
"Unit";"Zergling";"Larva";740;1
"Unit";"Zergling";"Larva";740;1
"Unit";"Zergling";"Larva";740;1
"Unit";"Zergling";"Larva";740;1
"Unit";"Zergling";"Larva";740;1
"Unit";"Zergling";"Larva";740;1
"Unit";"Zergling";"Larva";740;1
"Unit";"Zergling";"Larva";740;1
"Unit";"Zergling";"Larva";740;1
"Unit";"Zergling";"Larva";740;1
"Unit";"Zergling";"Larva";740;1
"Unit";"Zergling";"Larva";740;1
"Unit";"Zergling";"Larva";740;1
"Unit";"Zergling";"Larva";740;1
"Unit";"Zergling";"Larva";740;1
"Unit";"Zergling";"Larva";740;1
"Unit";"Zergling";"Larva";740;1
"Unit";"Zergling";"Larva";740;1
"Unit";"Zergling";"Larva";740;1
"Unit";"Zergling";"Larva";740;1
"Unit";"Zergling";"Larva";740;1
"Unit";"Zergling";"Larva";740;1
"Unit";"Zergling";"Larva";740;1
"Unit";"Zergling";"Larva";740;1
"Unit";"Zergling";"Larva";740;1
"Unit";"Zergling";"Larva";740;1
"Unit";"Zergling";"Larva";740;1
"Unit";"Zergling";"Larva";740;1
"Unit";"Zergling";"Larva";740;1
"Unit";"Zergling";"Larva";740;1
"Unit";"Zergling";"Larva";740;1
"Unit";"Zergling";"Larva";740;1
"Unit";"Zergling";"Larva";740;1
"Unit";"Zergling";"Larva";740;1
"Unit";"Zergling";"Larva";740;1
"Unit";"Zergling";"Larva";740;1
"Unit";"Hydralisk";"Larva";766;2
"Unit";"Hydralisk";"Larva";766;2
"Unit";"Hydralisk";"Larva";766;2
"Unit";"Hydralisk";"Larva";766;2
"Unit";"Hydralisk";"Larva";766;2
"Unit";"Hydralisk";"Larva";766;2
"Unit";"Hydralisk";"Larva";766;2
"Unit";"Hydralisk";"Larva";766;2
"Unit";"Viper";"Larva";784;3
"Unit";"Viper";"Larva";784;3
"Unit";"Corruptor";"Larva";784;2
"Building";"Extractor";NA;800;0
"Building";"Extractor";NA;800;0
"Upgrade";"ZergMissileWeaponsLevel2";"EvolutionChamber";740;0
"Unit";"Corruptor";"Larva";806;2
"Upgrade";"EvolveGroovedSpines";"HydraliskDen";800;0
"Unit";"Corruptor";"Larva";810;2
"Unit";"Corruptor";"Larva";810;2
"Unit";"Corruptor";"Larva";810;2
"Unit";"Corruptor";"Larva";810;2
"Unit";"Corruptor";"Larva";810;2
"Unit";"Zergling";"Larva";820;1
"Unit";"Zergling";"Larva";820;1
"Unit";"Zergling";"Larva";820;1
"Unit";"Zergling";"Larva";820;1
"Unit";"Zergling";"Larva";820;1
"Unit";"Zergling";"Larva";820;1
"Unit";"Zergling";"Larva";820;1
"Unit";"Zergling";"Larva";820;1
"Unit";"Zergling";"Larva";820;1
"Unit";"Zergling";"Larva";820;1
"Unit";"Zergling";"Larva";820;1
"Unit";"Zergling";"Larva";820;1
"Unit";"Zergling";"Larva";820;1
"Unit";"Zergling";"Larva";820;1
"Unit";"Zergling";"Larva";820;1
"Unit";"Zergling";"Larva";820;1
"Unit";"Zergling";"Larva";820;1
"Unit";"Zergling";"Larva";820;1
"Unit";"Zergling";"Larva";820;1
"Unit";"Zergling";"Larva";820;1
"Unit";"Zergling";"Larva";820;1
"Unit";"Zergling";"Larva";820;1
"Unit";"Zergling";"Larva";820;1
"Unit";"Zergling";"Larva";820;1
"Unit";"Zergling";"Larva";820;1
"Unit";"Zergling";"Larva";820;1
"Unit";"Zergling";"Larva";820;1
"Unit";"Zergling";"Larva";820;1
"Unit";"Zergling";"Larva";820;1
"Unit";"Zergling";"Larva";820;1
"Unit";"Hydralisk";"Larva";820;2
"Unit";"Ultralisk";"Larva";820;6
"Unit";"Ultralisk";"Larva";820;6
"Unit";"Ultralisk";"Larva";820;6
"Unit";"Ultralisk";"Larva";820;6
"Unit";"Ultralisk";"Larva";820;6
"Building";"Hatchery";NA;810;0
"Building";"CreepTumorQueen";NA;858;0
"Building";"Hatchery";NA;810;0
"Building";"CreepTumorQueen";NA;888;0
"Building";"CreepTumorQueen";NA;888;0
"Building";"CreepTumorQueen";NA;888;0
