"type";"unit_name";"on_building";"total_supply";"supply"
"Unit";"Overlord";"Larva";13;0
"Building";"Extractor";NA;21;0
"Building";"SpawningPool";NA;18;0
"Building";"Hatchery";NA;16;0
"Unit";"Queen";"Hatchery";23;2
"Unit";"Queen";"Hatchery";23;2
"Building";"RoachWarren";NA;23;0
"Unit";"Overlord";"Larva";26;0
"Unit";"Overlord";"Larva";26;0
"Unit";"Overlord";"Larva";26;0
"Unit";"Roach";"Larva";30;2
"Unit";"Roach";"Larva";30;2
"Unit";"Roach";"Larva";30;2
"Unit";"Roach";"Larva";30;2
"Unit";"Overlord";"Larva";30;0
"Unit";"Overlord";"Larva";30;0
"Unit";"Roach";"Larva";30;2
"Unit";"Roach";"Larva";38;2
"Unit";"Overlord";"Larva";38;0
"Unit";"Roach";"Larva";38;2
"Unit";"Roach";"Larva";38;2
"Unit";"Roach";"Larva";40;2
"Unit";"Roach";"Larva";42;2
"Unit";"Roach";"Larva";52;2
"Unit";"Roach";"Larva";52;2
"Unit";"Roach";"Larva";54;2
"Unit";"Overlord";"Larva";60;0
"Unit";"Overlord";"Larva";60;0
"Building";"Extractor";NA;62;0
"Building";"Extractor";NA;62;0
"Unit";"Overlord";"Larva";62;0
"Unit";"Overlord";"Larva";62;0
"Building";"Extractor";NA;66;0
"Unit";"Overlord";"Larva";81;0
"Unit";"Overlord";"Larva";81;0
"Unit";"Overlord";"Larva";81;0
"Building";"Hatchery";NA;81;0
"Unit";"Overlord";"Larva";81;0
"Unit";"Overlord";"Larva";81;0
"Unit";"Queen";"Hatchery";81;2
"Unit";"Queen";"Hatchery";81;2
"Building";"CreepTumorQueen";NA;85;0
"Building";"CreepTumorQueen";NA;85;0
"Unit";"Queen";"Hatchery";81;2
"Building";"Spire";NA;81;0
"Building";"CreepTumor";NA;103;0
"Building";"Hatchery";NA;81;0
"Building";"CreepTumor";NA;103;0
"Building";"CreepTumorQueen";NA;103;0
"Unit";"Mutalisk";"Larva";103;2
"Unit";"Mutalisk";"Larva";103;2
"Unit";"Mutalisk";"Larva";103;2
"Unit";"Mutalisk";"Larva";103;2
"Unit";"Mutalisk";"Larva";103;2
"Unit";"Mutalisk";"Larva";103;2
"Unit";"Mutalisk";"Larva";103;2
"Unit";"Mutalisk";"Larva";103;2
"Unit";"Mutalisk";"Larva";103;2
"Unit";"Queen";"Hatchery";97;2
"Unit";"Queen";"Hatchery";98;2
"Unit";"Queen";"Hatchery";101;2
"Building";"CreepTumorQueen";NA;121;0
"Unit";"Mutalisk";"Larva";103;2
"Building";"Extractor";NA;103;0
"Building";"Extractor";NA;103;0
"Building";"CreepTumorQueen";NA;129;0
"Unit";"Mutalisk";"Larva";121;2
"Building";"Extractor";NA;127;0
"Building";"Extractor";NA;127;0
"Unit";"Mutalisk";"Larva";129;2
"Unit";"Queen";"Hatchery";129;2
"Unit";"Queen";"Hatchery";129;2
"Unit";"Queen";"Hatchery";129;2
"Unit";"Queen";"Hatchery";129;2
"Building";"InfestationPit";NA;146;0
"Unit";"Overlord";"Larva";165;0
"Unit";"Overlord";"Larva";165;0
"Unit";"Overlord";"Larva";165;0
"Unit";"Overlord";"Larva";165;0
"Unit";"Mutalisk";"Larva";165;2
"Unit";"Mutalisk";"Larva";167;2
"Unit";"Mutalisk";"Larva";167;2
"Unit";"Mutalisk";"Larva";167;2
"Unit";"Mutalisk";"Larva";167;2
"Unit";"Mutalisk";"Larva";167;2
"Unit";"Mutalisk";"Larva";167;2
"Unit";"Mutalisk";"Larva";167;2
"Unit";"Mutalisk";"Larva";167;2
"Unit";"Mutalisk";"Larva";167;2
"Unit";"Overlord";"Larva";167;0
"Unit";"Overlord";"Larva";167;0
"Unit";"Mutalisk";"Larva";167;2
"Unit";"Mutalisk";"Larva";167;2
"Unit";"Mutalisk";"Larva";185;2
"Unit";"Mutalisk";"Larva";185;2
"Unit";"Mutalisk";"Larva";185;2
"Unit";"Mutalisk";"Larva";185;2
"Unit";"Overlord";"Larva";189;0
"Building";"EvolutionChamber";NA;189;0
"Building";"EvolutionChamber";NA;189;0
"Building";"EvolutionChamber";NA;197;0
"Unit";"Roach";"Larva";197;2
"Unit";"Roach";"Larva";197;2
"Unit";"Roach";"Larva";197;2
"Unit";"Roach";"Larva";197;2
"Unit";"Roach";"Larva";197;2
"Unit";"Roach";"Larva";197;2
"Unit";"Roach";"Larva";197;2
"Unit";"Roach";"Larva";197;2
"Unit";"Roach";"Larva";197;2
"Unit";"Roach";"Larva";197;2
"Unit";"Roach";"Larva";197;2
"Unit";"Roach";"Larva";197;2
"Unit";"Roach";"Larva";197;2
"Unit";"Roach";"Larva";197;2
"Unit";"Roach";"Larva";197;2
"Unit";"Roach";"Larva";197;2
"Unit";"Roach";"Larva";197;2
"Unit";"Roach";"Larva";197;2
"Unit";"Roach";"Larva";197;2
"Unit";"Roach";"Larva";197;2
"Unit";"Roach";"Larva";197;2
"Unit";"Roach";"Larva";197;2
"Unit";"Roach";"Larva";197;2
"Building";"UltraliskCavern";NA;197;0
"Unit";"Roach";"Larva";197;2
"Unit";"Roach";"Larva";197;2
"Unit";"Roach";"Larva";197;2
"Unit";"Roach";"Larva";197;2
"Unit";"Roach";"Larva";197;2
"Unit";"Roach";"Larva";197;2
"Unit";"Roach";"Larva";197;2
"Unit";"Roach";"Larva";197;2
"Unit";"Roach";"Larva";197;2
"Unit";"Roach";"Larva";197;2
"Building";"CreepTumorQueen";NA;243;0
"Building";"CreepTumorQueen";NA;243;0
"Building";"CreepTumorQueen";NA;243;0
"Building";"CreepTumorQueen";NA;253;0
"Upgrade";"GlialReconstitution";"RoachWarren";197;0
"Building";"CreepTumorQueen";NA;263;0
"Building";"Hatchery";NA;197;0
"Unit";"Roach";"Larva";263;2
"Unit";"Roach";"Larva";263;2
"Unit";"Roach";"Larva";263;2
"Unit";"Roach";"Larva";263;2
"Upgrade";"ZergGroundArmorsLevel1";"EvolutionChamber";197;0
"Upgrade";"ZergMissileWeaponsLevel1";"EvolutionChamber";197;0
"Unit";"Roach";"Larva";271;2
"Unit";"Roach";"Larva";271;2
"Unit";"Roach";"Larva";271;2
"Unit";"Roach";"Larva";271;2
"Unit";"Roach";"Larva";271;2
"Unit";"Roach";"Larva";271;2
"Unit";"Roach";"Larva";271;2
"Unit";"Roach";"Larva";271;2
"Unit";"Roach";"Larva";271;2
"Unit";"Roach";"Larva";271;2
"Unit";"Roach";"Larva";271;2
"Unit";"Roach";"Larva";271;2
"Unit";"Roach";"Larva";271;2
"Unit";"Roach";"Larva";271;2
"Unit";"Roach";"Larva";271;2
"Unit";"Roach";"Larva";271;2
"Unit";"Roach";"Larva";271;2
"Unit";"Roach";"Larva";271;2
"Unit";"Roach";"Larva";271;2
"Unit";"Roach";"Larva";271;2
"Unit";"Roach";"Larva";271;2
"Unit";"Roach";"Larva";271;2
"Unit";"Roach";"Larva";271;2
"Unit";"Roach";"Larva";271;2
"Unit";"Roach";"Larva";271;2
"Unit";"Roach";"Larva";271;2
"Unit";"Roach";"Larva";271;2
"Unit";"Roach";"Larva";271;2
"Unit";"Roach";"Larva";271;2
"Unit";"Roach";"Larva";271;2
"Unit";"Roach";"Larva";271;2
"Unit";"Roach";"Larva";271;2
"Unit";"Roach";"Larva";271;2
"Unit";"Roach";"Larva";271;2
"Unit";"Roach";"Larva";271;2
"Unit";"Roach";"Larva";271;2
"Unit";"Roach";"Larva";271;2
"Unit";"Roach";"Larva";271;2
"Unit";"Roach";"Larva";271;2
"Unit";"Roach";"Larva";271;2
"Unit";"Roach";"Larva";271;2
"Unit";"Roach";"Larva";271;2
"Building";"CreepTumorQueen";NA;360;0
"Building";"CreepTumorQueen";NA;362;0
"Unit";"Roach";"Larva";355;2
"Unit";"Roach";"Larva";355;2
"Unit";"Roach";"Larva";355;2
"Unit";"Roach";"Larva";355;2
"Unit";"Roach";"Larva";355;2
"Unit";"Roach";"Larva";355;2
"Building";"CreepTumorQueen";NA;362;0
"Building";"CreepTumorQueen";NA;362;0
"Building";"CreepTumorQueen";NA;362;0
"Building";"CreepTumorQueen";NA;362;0
"Building";"CreepTumorQueen";NA;374;0
"Upgrade";"ZergMeleeWeaponsLevel1";"EvolutionChamber";271;0
"Building";"CreepTumorQueen";NA;374;0
"Building";"CreepTumorQueen";NA;374;0
"Building";"CreepTumorQueen";NA;374;0
"Building";"CreepTumorQueen";NA;374;0
"Building";"HydraliskDen";NA;374;0
"Building";"CreepTumor";NA;374;0
"Building";"CreepTumor";NA;374;0
"Unit";"Overlord";"Larva";374;0
"Unit";"Overlord";"Larva";374;0
"Building";"CreepTumor";NA;374;0
"Unit";"Zergling";"Larva";374;1
"Unit";"Zergling";"Larva";374;1
"Unit";"Zergling";"Larva";374;1
"Unit";"Zergling";"Larva";374;1
"Unit";"Zergling";"Larva";374;1
"Unit";"Zergling";"Larva";374;1
"Unit";"Zergling";"Larva";374;1
"Unit";"Zergling";"Larva";374;1
"Unit";"Zergling";"Larva";374;1
"Unit";"Zergling";"Larva";374;1
"Unit";"Hydralisk";"Larva";378;2
"Unit";"Hydralisk";"Larva";378;2
"Unit";"Hydralisk";"Larva";378;2
"Unit";"Hydralisk";"Larva";378;2
"Unit";"Hydralisk";"Larva";378;2
"Unit";"Hydralisk";"Larva";378;2
"Unit";"Hydralisk";"Larva";378;2
"Unit";"Hydralisk";"Larva";378;2
"Unit";"Hydralisk";"Larva";378;2
"Unit";"Hydralisk";"Larva";378;2
"Unit";"Hydralisk";"Larva";380;2
"Unit";"Ultralisk";"Larva";374;6
"Unit";"Ultralisk";"Larva";374;6
"Unit";"Ultralisk";"Larva";374;6
"Unit";"Ultralisk";"Larva";374;6
"Unit";"Ultralisk";"Larva";374;6
"Unit";"Ultralisk";"Larva";374;6
"Unit";"Ultralisk";"Larva";374;6
"Unit";"Ultralisk";"Larva";374;6
"Upgrade";"ChitinousPlating";"UltraliskCavern";374;0
"Building";"HydraliskDen";NA;412;0
"Unit";"Hydralisk";"Larva";454;2
"Unit";"Hydralisk";"Larva";454;2
"Unit";"Hydralisk";"Larva";454;2
"Unit";"Hydralisk";"Larva";454;2
"Unit";"Hydralisk";"Larva";454;2
"Unit";"Hydralisk";"Larva";454;2
"Unit";"Hydralisk";"Larva";454;2
"Unit";"Hydralisk";"Larva";454;2
"Unit";"Hydralisk";"Larva";454;2
"Unit";"Hydralisk";"Larva";454;2
"Unit";"Hydralisk";"Larva";454;2
"Unit";"Hydralisk";"Larva";454;2
"Unit";"Hydralisk";"Larva";454;2
"Unit";"Hydralisk";"Larva";454;2
"Unit";"Hydralisk";"Larva";454;2
"Unit";"Hydralisk";"Larva";454;2
"Unit";"Hydralisk";"Larva";454;2
"Unit";"Hydralisk";"Larva";454;2
"Unit";"Hydralisk";"Larva";454;2
"Upgrade";"ZergMeleeWeaponsLevel2";"EvolutionChamber";382;0
"Upgrade";"ZergGroundArmorsLevel2";"EvolutionChamber";384;0
"Upgrade";"ZergMissileWeaponsLevel2";"EvolutionChamber";384;0
"Unit";"Hydralisk";"Larva";454;2
"Unit";"Hydralisk";"Larva";454;2
"Unit";"Hydralisk";"Larva";454;2
"Building";"UltraliskCavern";NA;454;0
"Unit";"Hydralisk";"Larva";498;2
"Unit";"Hydralisk";"Larva";498;2
"Unit";"Hydralisk";"Larva";498;2
"Unit";"Hydralisk";"Larva";498;2
"Unit";"Hydralisk";"Larva";498;2
"Unit";"Hydralisk";"Larva";498;2
"Unit";"Hydralisk";"Larva";498;2
"Unit";"Hydralisk";"Larva";498;2
"Unit";"Hydralisk";"Larva";498;2
"Unit";"Hydralisk";"Larva";498;2
"Unit";"Hydralisk";"Larva";498;2
"Unit";"Hydralisk";"Larva";498;2
"Unit";"Hydralisk";"Larva";498;2
"Unit";"Hydralisk";"Larva";498;2
"Unit";"Hydralisk";"Larva";498;2
"Unit";"Hydralisk";"Larva";498;2
"Unit";"Hydralisk";"Larva";498;2
"Unit";"Hydralisk";"Larva";498;2
"Unit";"Hydralisk";"Larva";498;2
"Unit";"Hydralisk";"Larva";498;2
"Building";"CreepTumor";NA;538;0
"Building";"CreepTumor";NA;538;0
"Building";"CreepTumor";NA;538;0
"Building";"CreepTumor";NA;538;0
"Building";"CreepTumor";NA;538;0
"Building";"CreepTumor";NA;538;0
"Building";"CreepTumor";NA;538;0
"Building";"CreepTumor";NA;538;0
"Building";"CreepTumor";NA;538;0
"Building";"CreepTumor";NA;538;0
"Building";"HydraliskDen";NA;538;0
"Building";"CreepTumor";NA;550;0
"Building";"CreepTumor";NA;553;0
"Building";"CreepTumor";NA;554;0
"Building";"CreepTumor";NA;554;0
"Building";"CreepTumor";NA;554;0
"Building";"CreepTumor";NA;554;0
"Building";"CreepTumor";NA;554;0
"Building";"CreepTumor";NA;554;0
"Building";"CreepTumor";NA;554;0
"Building";"CreepTumor";NA;554;0
"Building";"CreepTumor";NA;554;0
"Building";"Hatchery";NA;538;0
