"type";"unit_name";"on_building";"total_supply";"supply"
"Unit";"Overlord";"Larva";13;0
"Building";"Extractor";NA;18;0
"Unit";"Overlord";"Larva";21;0
"Building";"SpawningPool";NA;19;0
"Building";"Hatchery";NA;17;0
"Unit";"Zergling";"Larva";23;1
"Unit";"Zergling";"Larva";23;1
"Unit";"Zergling";"Larva";23;1
"Unit";"Zergling";"Larva";23;1
"Unit";"Queen";"Hatchery";22;2
"Unit";"Queen";"Hatchery";23;2
"Unit";"Overlord";"Larva";35;0
"Unit";"Queen";"Hatchery";35;2
"Building";"CreepTumorQueen";NA;38;0
"Unit";"Overlord";"Larva";38;0
"Unit";"Overlord";"Larva";43;0
"Building";"CreepTumor";NA;48;0
"Building";"Hatchery";NA;32;0
"Unit";"Zergling";"Larva";48;1
"Unit";"Zergling";"Larva";48;1
"Unit";"Zergling";"Larva";48;1
"Unit";"Zergling";"Larva";48;1
"Unit";"Zergling";"Larva";48;1
"Unit";"Zergling";"Larva";48;1
"Unit";"Zergling";"Larva";49;1
"Unit";"Zergling";"Larva";49;1
"Unit";"Zergling";"Larva";49;1
"Unit";"Zergling";"Larva";49;1
"Building";"CreepTumorQueen";NA;49;0
"Unit";"Queen";"Hatchery";48;2
"Unit";"Overlord";"Larva";49;0
"Unit";"Zergling";"Larva";60;1
"Unit";"Zergling";"Larva";60;1
"Unit";"Zergling";"Larva";60;1
"Unit";"Zergling";"Larva";60;1
"Unit";"Zergling";"Larva";61;1
"Unit";"Zergling";"Larva";61;1
"Unit";"Zergling";"Larva";61;1
"Unit";"Zergling";"Larva";61;1
"Building";"CreepTumor";NA;63;0
"Unit";"Overlord";"Larva";61;0
"Unit";"Queen";"Hatchery";49;2
"Building";"Extractor";NA;61;0
"Building";"Extractor";NA;61;0
"Unit";"Zergling";"Larva";63;1
"Unit";"Zergling";"Larva";63;1
"Unit";"Zergling";"Larva";63;1
"Unit";"Zergling";"Larva";63;1
"Unit";"Zergling";"Larva";63;1
"Unit";"Zergling";"Larva";63;1
"Unit";"Zergling";"Larva";63;1
"Unit";"Zergling";"Larva";63;1
"Building";"CreepTumor";NA;71;0
"Building";"CreepTumorQueen";NA;71;0
"Unit";"Overlord";"Larva";81;0
"Unit";"Overlord";"Larva";81;0
"Building";"BanelingNest";NA;61;0
"Building";"CreepTumor";NA;83;0
"Unit";"Overlord";"Larva";83;0
"Unit";"Queen";"Hatchery";73;2
"Unit";"Overlord";"Larva";86;0
"Unit";"Zergling";"Larva";86;1
"Unit";"Zergling";"Larva";86;1
"Unit";"Zergling";"Larva";86;1
"Unit";"Zergling";"Larva";86;1
"Unit";"Zergling";"Larva";86;1
"Unit";"Zergling";"Larva";86;1
"Building";"CreepTumor";NA;88;0
"Building";"CreepTumor";NA;101;0
"Building";"CreepTumorQueen";NA;101;0
"Building";"CreepTumorQueen";NA;102;0
"Building";"EvolutionChamber";NA;94;0
"Unit";"Queen";"Hatchery";88;2
"Building";"CreepTumor";NA;117;0
"Building";"CreepTumor";NA;117;0
"Building";"CreepTumor";NA;117;0
"Unit";"Zergling";"Larva";114;1
"Unit";"Zergling";"Larva";114;1
"Unit";"Zergling";"Larva";114;1
"Unit";"Zergling";"Larva";114;1
"Building";"CreepTumor";NA;117;0
"Unit";"Zergling";"Larva";114;1
"Unit";"Zergling";"Larva";114;1
"Unit";"Zergling";"Larva";114;1
"Unit";"Zergling";"Larva";114;1
"Unit";"Zergling";"Larva";114;1
"Unit";"Zergling";"Larva";114;1
"Unit";"Zergling";"Larva";114;1
"Unit";"Zergling";"Larva";114;1
"Building";"CreepTumor";NA;117;0
"Building";"RoachWarren";NA;112;0
"Building";"EvolutionChamber";NA;120;0
"Unit";"Baneling";"Zergling";132;0
"Unit";"Baneling";"Zergling";132;0
"Unit";"Baneling";"Zergling";132;0
"Unit";"Baneling";"Zergling";132;0
"Unit";"Overlord";"Larva";132;0
"Unit";"Overlord";"Larva";132;0
"Building";"Extractor";NA;132;0
"Building";"Extractor";NA;132;0
"Building";"SpineCrawler";NA;132;0
"Building";"SporeCrawler";NA;132;0
"Building";"SporeCrawler";NA;132;0
"Building";"SporeCrawler";NA;138;0
"Building";"Hatchery";NA;120;0
"Building";"CreepTumor";NA;143;0
"Building";"CreepTumor";NA;143;0
"Building";"CreepTumor";NA;143;0
"Upgrade";"GlialReconstitution";"RoachWarren";138;0
"Building";"SporeCrawler";NA;153;0
"Unit";"Roach";"Larva";153;2
"Unit";"Roach";"Larva";153;2
"Unit";"Roach";"Larva";153;2
"Unit";"Roach";"Larva";153;2
"Unit";"Roach";"Larva";153;2
"Unit";"Roach";"Larva";153;2
"Unit";"Roach";"Larva";153;2
"Unit";"Roach";"Larva";153;2
"Unit";"Roach";"Larva";153;2
"Upgrade";"ZergMissileWeaponsLevel1";"EvolutionChamber";138;0
"Building";"SporeCrawler";NA;157;0
"Building";"Extractor";NA;158;0
"Building";"CreepTumorQueen";NA;179;0
"Building";"CreepTumorQueen";NA;179;0
"Building";"CreepTumor";NA;179;0
"Building";"CreepTumor";NA;179;0
"Building";"CreepTumor";NA;179;0
"Building";"InfestationPit";NA;157;0
"Building";"CreepTumor";NA;179;0
"Building";"CreepTumor";NA;195;0
"Building";"CreepTumor";NA;195;0
"Building";"CreepTumor";NA;195;0
"Building";"HydraliskDen";NA;179;0
"Unit";"Overlord";"Larva";195;0
"Unit";"Overlord";"Larva";195;0
"Unit";"Roach";"Larva";199;2
"Unit";"Roach";"Larva";199;2
"Unit";"Overlord";"Larva";199;0
"Unit";"Overlord";"Larva";199;0
"Building";"SporeCrawler";NA;199;0
"Building";"SporeCrawler";NA;199;0
"Building";"SporeCrawler";NA;199;0
"Building";"SporeCrawler";NA;199;0
"Building";"SpineCrawler";NA;199;0
"Building";"SporeCrawler";NA;200;0
"Upgrade";"ZergGroundArmorsLevel1";"EvolutionChamber";159;0
"Building";"SporeCrawler";NA;200;0
"Unit";"Roach";"Larva";200;2
"Unit";"Roach";"Larva";200;2
"Unit";"Roach";"Larva";200;2
"Unit";"Roach";"Larva";202;2
"Unit";"Roach";"Larva";202;2
"Unit";"Queen";"Hatchery";204;2
"Unit";"Queen";"Hatchery";204;2
"Building";"Spire";NA;199;0
"Building";"CreepTumorQueen";NA;218;0
"Building";"CreepTumorQueen";NA;218;0
"Building";"CreepTumorQueen";NA;218;0
"Building";"CreepTumorQueen";NA;225;0
"Building";"CreepTumorQueen";NA;225;0
"Unit";"Viper";"Larva";225;3
"Unit";"Viper";"Larva";225;3
"Unit";"Viper";"Larva";225;3
"Unit";"Hydralisk";"Larva";225;2
"Unit";"Hydralisk";"Larva";225;2
"Unit";"Hydralisk";"Larva";225;2
"Unit";"Hydralisk";"Larva";225;2
"Unit";"Hydralisk";"Larva";225;2
"Unit";"Hydralisk";"Larva";225;2
"Unit";"Hydralisk";"Larva";225;2
"Unit";"Hydralisk";"Larva";225;2
"Unit";"Hydralisk";"Larva";225;2
"Building";"CreepTumor";NA;234;0
"Building";"CreepTumor";NA;234;0
"Upgrade";"ZergMissileWeaponsLevel2";"EvolutionChamber";204;0
"Building";"CreepTumor";NA;234;0
"Building";"CreepTumor";NA;234;0
"Building";"CreepTumor";NA;234;0
"Building";"Extractor";NA;225;0
"Building";"Extractor";NA;231;0
"Unit";"Hydralisk";"Larva";234;2
"Unit";"Hydralisk";"Larva";234;2
"Unit";"Hydralisk";"Larva";234;2
"Unit";"Hydralisk";"Larva";234;2
"Building";"CreepTumor";NA;252;0
"Upgrade";"EvolveGroovedSpines";"HydraliskDen";234;0
"Unit";"Hydralisk";"Larva";260;2
"Unit";"Hydralisk";"Larva";260;2
"Unit";"Hydralisk";"Larva";260;2
"Unit";"Hydralisk";"Larva";260;2
"Unit";"Hydralisk";"Larva";260;2
"Unit";"Hydralisk";"Larva";260;2
"Unit";"Hydralisk";"Larva";260;2
"Unit";"Hydralisk";"Larva";260;2
"Building";"Hatchery";NA;234;0
"Upgrade";"ZergGroundArmorsLevel2";"EvolutionChamber";225;0
"Building";"CreepTumor";NA;276;0
"Building";"CreepTumor";NA;276;0
"Building";"CreepTumor";NA;276;0
"Unit";"Overlord";"Larva";276;0
"Unit";"Overlord";"Larva";276;0
"Unit";"Overlord";"Larva";276;0
"Building";"NydusNetwork";NA;260;0
"Unit";"Hydralisk";"Larva";276;2
"Unit";"Hydralisk";"Larva";276;2
"Unit";"Hydralisk";"Larva";276;2
"Unit";"Hydralisk";"Larva";276;2
"Unit";"Hydralisk";"Larva";276;2
"Building";"CreepTumor";NA;289;0
"Building";"CreepTumor";NA;289;0
"Unit";"Hydralisk";"Larva";281;2
"Unit";"Hydralisk";"Larva";289;2
"Unit";"Hydralisk";"Larva";289;2
"Unit";"Hydralisk";"Larva";289;2
"Unit";"Hydralisk";"Larva";289;2
"Unit";"Hydralisk";"Larva";289;2
"Unit";"Hydralisk";"Larva";289;2
"Unit";"Hydralisk";"Larva";289;2
"Upgrade";"EvolveMuscularAugments";"HydraliskDen";276;0
"Unit";"Hydralisk";"Larva";289;2
"Building";"CreepTumor";NA;305;0
"Unit";"Hydralisk";"Larva";289;2
"Unit";"Hydralisk";"Larva";289;2
"Unit";"Hydralisk";"Larva";289;2
"Unit";"Hydralisk";"Larva";289;2
"Unit";"Hydralisk";"Larva";289;2
"Unit";"Hydralisk";"Larva";289;2
"Unit";"Hydralisk";"Larva";289;2
"Unit";"Hydralisk";"Larva";289;2
"Building";"CreepTumor";NA;305;0
"Unit";"Corruptor";"Larva";305;2
"Unit";"Corruptor";"Larva";305;2
"Unit";"Corruptor";"Larva";305;2
"Unit";"Corruptor";"Larva";305;2
"Unit";"Corruptor";"Larva";305;2
"Unit";"Corruptor";"Larva";305;2
"Building";"Hatchery";NA;279;0
"Unit";"Overlord";"Larva";336;0
"Unit";"Overlord";"Larva";336;0
"Unit";"Overlord";"Larva";336;0
"Unit";"Overlord";"Larva";336;0
"Building";"CreepTumor";NA;336;0
"Building";"CreepTumor";NA;336;0
"Building";"CreepTumor";NA;336;0
"Building";"Extractor";NA;336;0
"Building";"Extractor";NA;336;0
"Building";"CreepTumor";NA;336;0
"Upgrade";"ZergMissileWeaponsLevel3";"EvolutionChamber";260;0
"Unit";"Zergling";"Larva";351;1
"Unit";"Zergling";"Larva";351;1
"Unit";"Zergling";"Larva";351;1
"Unit";"Zergling";"Larva";351;1
"Unit";"Zergling";"Larva";351;1
"Unit";"Zergling";"Larva";351;1
"Unit";"Zergling";"Larva";351;1
"Unit";"Zergling";"Larva";351;1
"Unit";"Zergling";"Larva";351;1
"Unit";"Zergling";"Larva";351;1
"Unit";"Zergling";"Larva";351;1
"Unit";"Zergling";"Larva";351;1
"Unit";"Zergling";"Larva";351;1
"Unit";"Zergling";"Larva";351;1
"Unit";"Zergling";"Larva";351;1
"Unit";"Zergling";"Larva";351;1
"Unit";"Zergling";"Larva";351;1
"Unit";"Zergling";"Larva";351;1
"Unit";"Zergling";"Larva";351;1
"Unit";"Zergling";"Larva";351;1
"Unit";"Zergling";"Larva";351;1
"Unit";"Zergling";"Larva";351;1
"Unit";"Zergling";"Larva";351;1
"Unit";"Zergling";"Larva";351;1
"Unit";"Zergling";"Larva";351;1
"Unit";"Zergling";"Larva";351;1
"Unit";"Zergling";"Larva";351;1
"Unit";"Zergling";"Larva";351;1
"Unit";"Zergling";"Larva";351;1
"Unit";"Zergling";"Larva";351;1
"Unit";"Zergling";"Larva";351;1
"Unit";"Zergling";"Larva";351;1
"Unit";"Zergling";"Larva";351;1
"Unit";"Zergling";"Larva";351;1
"Unit";"Zergling";"Larva";351;1
"Unit";"Zergling";"Larva";351;1
"Unit";"Zergling";"Larva";351;1
"Unit";"Zergling";"Larva";351;1
"Unit";"Zergling";"Larva";351;1
"Unit";"Zergling";"Larva";351;1
"Unit";"Zergling";"Larva";351;1
"Unit";"Zergling";"Larva";351;1
"Unit";"Zergling";"Larva";351;1
"Unit";"Zergling";"Larva";351;1
"Building";"NydusCanal";NA;351;0
"Building";"Hatchery";NA;329;0
"Unit";"Corruptor";"Larva";351;2
"Unit";"Corruptor";"Larva";351;2
"Unit";"Corruptor";"Larva";351;2
"Unit";"Corruptor";"Larva";401;2
"Unit";"Corruptor";"Larva";401;2
"Building";"CreepTumor";NA;401;0
"Building";"NydusCanal";NA;401;0
"Unit";"Hydralisk";"Larva";401;2
"Unit";"Hydralisk";"Larva";401;2
"Unit";"Hydralisk";"Larva";401;2
"Unit";"Hydralisk";"Larva";401;2
"Unit";"Hydralisk";"Larva";401;2
"Unit";"Hydralisk";"Larva";401;2
"Unit";"Hydralisk";"Larva";401;2
"Unit";"Hydralisk";"Larva";401;2
"Unit";"Hydralisk";"Larva";401;2
"Unit";"Hydralisk";"Larva";401;2
"Unit";"Hydralisk";"Larva";401;2
"Unit";"Hydralisk";"Larva";401;2
"Unit";"Hydralisk";"Larva";401;2
"Unit";"Hydralisk";"Larva";401;2
"Building";"CreepTumor";NA;405;0
"Unit";"Viper";"Larva";401;3
"Unit";"Viper";"Larva";401;3
"Unit";"Viper";"Larva";401;3
"Building";"NydusCanal";NA;405;0
"Building";"NydusCanal";NA;442;0
"Unit";"Zergling";"Larva";442;1
"Unit";"Zergling";"Larva";442;1
"Unit";"Zergling";"Larva";442;1
"Unit";"Zergling";"Larva";442;1
"Unit";"Zergling";"Larva";442;1
"Unit";"Zergling";"Larva";442;1
"Unit";"Zergling";"Larva";442;1
"Unit";"Zergling";"Larva";442;1
"Unit";"Zergling";"Larva";442;1
"Unit";"Zergling";"Larva";442;1
"Unit";"Zergling";"Larva";442;1
"Unit";"Zergling";"Larva";442;1
"Unit";"Hydralisk";"Larva";454;2
"Unit";"Hydralisk";"Larva";454;2
"Unit";"Hydralisk";"Larva";454;2
"Unit";"Hydralisk";"Larva";454;2
"Unit";"Hydralisk";"Larva";454;2
"Unit";"Hydralisk";"Larva";454;2
"Unit";"Hydralisk";"Larva";454;2
"Unit";"Hydralisk";"Larva";454;2
"Unit";"Hydralisk";"Larva";454;2
"Unit";"Hydralisk";"Larva";454;2
"Unit";"Hydralisk";"Larva";454;2
"Unit";"Hydralisk";"Larva";454;2
"Unit";"Hydralisk";"Larva";454;2
"Unit";"Hydralisk";"Larva";454;2
"Unit";"Hydralisk";"Larva";454;2
"Building";"Hatchery";NA;442;0
"Unit";"Hydralisk";"Larva";454;2
"Unit";"Hydralisk";"Larva";454;2
"Unit";"Hydralisk";"Larva";454;2
"Unit";"Hydralisk";"Larva";454;2
"Unit";"Hydralisk";"Larva";454;2
"Unit";"Hydralisk";"Larva";454;2
"Unit";"Hydralisk";"Larva";454;2
"Unit";"Hydralisk";"Larva";454;2
"Unit";"Hydralisk";"Larva";454;2
"Unit";"Hydralisk";"Larva";454;2
"Unit";"Hydralisk";"Larva";454;2
"Unit";"Hydralisk";"Larva";454;2
"Unit";"Hydralisk";"Larva";454;2
"Unit";"Hydralisk";"Larva";454;2
"Building";"NydusCanal";NA;512;0
"Unit";"Zergling";"Larva";512;1
"Unit";"Zergling";"Larva";512;1
"Unit";"Zergling";"Larva";512;1
"Unit";"Zergling";"Larva";512;1
"Unit";"Zergling";"Larva";512;1
"Unit";"Zergling";"Larva";512;1
"Unit";"Zergling";"Larva";512;1
"Unit";"Zergling";"Larva";512;1
"Unit";"Zergling";"Larva";512;1
"Unit";"Zergling";"Larva";512;1
"Unit";"Zergling";"Larva";512;1
"Unit";"Zergling";"Larva";512;1
"Unit";"Zergling";"Larva";512;1
"Unit";"Zergling";"Larva";512;1
"Unit";"Zergling";"Larva";512;1
"Unit";"Zergling";"Larva";512;1
"Unit";"Zergling";"Larva";512;1
"Unit";"Zergling";"Larva";512;1
"Building";"CreepTumor";NA;512;0
"Upgrade";"ZergMeleeWeaponsLevel1";"EvolutionChamber";454;0
"Building";"NydusCanal";NA;526;0
"Unit";"Hydralisk";"Larva";512;2
"Unit";"Hydralisk";"Larva";512;2
"Building";"NydusCanal";NA;530;0
"Building";"CreepTumor";NA;534;0
"Building";"CreepTumorQueen";NA;534;0
"Building";"CreepTumorQueen";NA;534;0
"Building";"Extractor";NA;534;0
"Building";"Extractor";NA;534;0
"Building";"Hatchery";NA;484;0
"Building";"CreepTumorQueen";NA;534;0
"Unit";"Zergling";"Larva";534;1
"Unit";"Zergling";"Larva";534;1
"Unit";"Zergling";"Larva";534;1
"Unit";"Zergling";"Larva";534;1
"Unit";"Zergling";"Larva";534;1
"Unit";"Zergling";"Larva";534;1
"Unit";"Zergling";"Larva";534;1
"Unit";"Zergling";"Larva";534;1
"Unit";"Zergling";"Larva";534;1
"Unit";"Zergling";"Larva";534;1
"Unit";"Zergling";"Larva";534;1
"Unit";"Zergling";"Larva";534;1
"Unit";"Zergling";"Larva";534;1
"Unit";"Zergling";"Larva";534;1
"Unit";"Zergling";"Larva";534;1
"Unit";"Zergling";"Larva";534;1
"Unit";"Zergling";"Larva";534;1
"Unit";"Zergling";"Larva";534;1
"Upgrade";"ZergGroundArmorsLevel3";"EvolutionChamber";454;0
"Unit";"Corruptor";"Larva";534;2
"Unit";"Corruptor";"Larva";534;2
"Unit";"Corruptor";"Larva";534;2
"Unit";"Corruptor";"Larva";534;2
"Unit";"Corruptor";"Larva";534;2
"Unit";"Corruptor";"Larva";534;2
"Unit";"Corruptor";"Larva";534;2
"Unit";"Corruptor";"Larva";534;2
"Unit";"Corruptor";"Larva";534;2
"Unit";"Corruptor";"Larva";534;2
"Unit";"Corruptor";"Larva";534;2
"Unit";"Corruptor";"Larva";534;2
"Unit";"Corruptor";"Larva";534;2
"Unit";"Corruptor";"Larva";534;2
"Unit";"Corruptor";"Larva";534;2
"Unit";"Viper";"Larva";552;3
"Unit";"Viper";"Larva";552;3
"Unit";"Viper";"Larva";552;3
"Building";"CreepTumor";NA;582;0
"Building";"Extractor";NA;591;0
"Building";"Extractor";NA;591;0
"Unit";"Zergling";"Larva";591;1
"Unit";"Zergling";"Larva";591;1
"Unit";"Zergling";"Larva";591;1
"Unit";"Zergling";"Larva";591;1
"Unit";"Zergling";"Larva";591;1
"Unit";"Zergling";"Larva";591;1
"Unit";"Zergling";"Larva";591;1
"Unit";"Zergling";"Larva";591;1
"Unit";"Zergling";"Larva";591;1
"Unit";"Zergling";"Larva";591;1
"Unit";"Zergling";"Larva";591;1
"Unit";"Zergling";"Larva";591;1
"Unit";"Zergling";"Larva";591;1
"Unit";"Zergling";"Larva";591;1
"Unit";"Zergling";"Larva";591;1
"Unit";"Zergling";"Larva";591;1
"Unit";"Zergling";"Larva";591;1
"Unit";"Zergling";"Larva";591;1
"Unit";"Zergling";"Larva";591;1
"Unit";"Zergling";"Larva";591;1
"Unit";"Zergling";"Larva";591;1
"Unit";"Zergling";"Larva";591;1
"Unit";"Zergling";"Larva";591;1
"Unit";"Zergling";"Larva";591;1
"Unit";"Zergling";"Larva";591;1
"Unit";"Zergling";"Larva";591;1
"Unit";"Zergling";"Larva";591;1
"Unit";"Zergling";"Larva";591;1
"Unit";"Zergling";"Larva";591;1
"Unit";"Zergling";"Larva";591;1
"Unit";"Zergling";"Larva";591;1
"Unit";"Zergling";"Larva";591;1
"Unit";"Zergling";"Larva";591;1
"Unit";"Zergling";"Larva";591;1
"Building";"CreepTumor";NA;591;0
"Building";"CreepTumor";NA;591;0
"Building";"CreepTumor";NA;591;0
"Building";"Extractor";NA;591;0
"Building";"Extractor";NA;591;0
"Unit";"Hydralisk";"Larva";625;2
"Unit";"Hydralisk";"Larva";625;2
"Unit";"Hydralisk";"Larva";625;2
"Unit";"Hydralisk";"Larva";625;2
"Unit";"Hydralisk";"Larva";625;2
"Unit";"Hydralisk";"Larva";625;2
"Unit";"Hydralisk";"Larva";625;2
"Unit";"Hydralisk";"Larva";625;2
"Unit";"Hydralisk";"Larva";625;2
"Unit";"Hydralisk";"Larva";625;2
"Unit";"Hydralisk";"Larva";625;2
"Unit";"Hydralisk";"Larva";625;2
"Unit";"Hydralisk";"Larva";625;2
"Upgrade";"NeuralParasite";"InfestationPit";591;0
"Unit";"Hydralisk";"Larva";625;2
"Unit";"Hydralisk";"Larva";625;2
"Unit";"Hydralisk";"Larva";625;2
"Unit";"Hydralisk";"Larva";625;2
"Unit";"Hydralisk";"Larva";625;2
"Unit";"Zergling";"Larva";651;1
"Unit";"Zergling";"Larva";651;1
