"type";"unit_name";"on_building";"total_supply";"supply"
"Unit";"Overlord";"Larva";13;0
"Building";"Extractor";NA;17;0
"Unit";"Overlord";"Larva";21;0
"Building";"SpawningPool";NA;19;0
"Building";"Hatchery";NA;17;0
"Unit";"Zergling";"Larva";23;1
"Unit";"Zergling";"Larva";23;1
"Unit";"Zergling";"Larva";23;1
"Unit";"Zergling";"Larva";23;1
"Unit";"Queen";"Hatchery";23;2
"Unit";"Queen";"Hatchery";23;2
"Building";"CreepTumorQueen";NA;36;0
"Unit";"Overlord";"Larva";37;0
"Unit";"Queen";"Hatchery";35;2
"Building";"CreepTumorQueen";NA;40;0
"Building";"CreepTumor";NA;40;0
"Unit";"Overlord";"Larva";42;0
"Building";"Hatchery";NA;31;0
"Building";"CreepTumorQueen";NA;49;0
"Building";"CreepTumor";NA;49;0
"Building";"CreepTumor";NA;49;0
"Unit";"Queen";"Hatchery";42;2
"Unit";"Overlord";"Larva";49;0
"Building";"Extractor";NA;56;0
"Unit";"Queen";"Hatchery";49;2
"Unit";"Zergling";"Larva";59;1
"Unit";"Zergling";"Larva";59;1
"Building";"CreepTumor";NA;59;0
"Unit";"Zergling";"Larva";59;1
"Unit";"Zergling";"Larva";59;1
"Unit";"Zergling";"Larva";59;1
"Unit";"Zergling";"Larva";59;1
"Unit";"Zergling";"Larva";59;1
"Unit";"Zergling";"Larva";59;1
"Unit";"Zergling";"Larva";59;1
"Unit";"Zergling";"Larva";59;1
"Unit";"Zergling";"Larva";59;1
"Unit";"Zergling";"Larva";59;1
"Building";"CreepTumor";NA;59;0
"Unit";"Zergling";"Larva";59;1
"Unit";"Zergling";"Larva";59;1
"Building";"CreepTumorQueen";NA;59;0
"Building";"Extractor";NA;61;0
"Building";"Extractor";NA;61;0
"Unit";"Overlord";"Larva";61;0
"Unit";"Zergling";"Larva";63;1
"Unit";"Zergling";"Larva";63;1
"Unit";"Zergling";"Larva";69;1
"Unit";"Zergling";"Larva";69;1
"Unit";"Zergling";"Larva";75;1
"Unit";"Zergling";"Larva";75;1
"Unit";"Zergling";"Larva";75;1
"Unit";"Zergling";"Larva";75;1
"Unit";"Zergling";"Larva";75;1
"Unit";"Zergling";"Larva";75;1
"Building";"CreepTumor";NA;76;0
"Building";"CreepTumor";NA;87;0
"Building";"CreepTumor";NA;79;0
"Building";"CreepTumorQueen";NA;87;0
"Unit";"Overlord";"Larva";94;0
"Building";"CreepTumor";NA;99;0
"Building";"CreepTumor";NA;99;0
"Building";"CreepTumor";NA;99;0
"Unit";"Overlord";"Larva";99;0
"Unit";"Overlord";"Larva";99;0
"Building";"Extractor";NA;99;0
"Building";"Extractor";NA;99;0
"Building";"Spire";NA;75;0
"Unit";"Overlord";"Larva";109;0
"Building";"SporeCrawler";NA;109;0
"Unit";"Overlord";"Larva";115;0
"Building";"CreepTumor";NA;118;0
"Building";"CreepTumor";NA;118;0
"Building";"CreepTumor";NA;118;0
"Unit";"Mutalisk";"Larva";115;2
"Unit";"Overlord";"Larva";118;0
"Unit";"Mutalisk";"Larva";116;2
"Unit";"Mutalisk";"Larva";116;2
"Unit";"Mutalisk";"Larva";116;2
"Unit";"Mutalisk";"Larva";116;2
"Unit";"Mutalisk";"Larva";117;2
"Unit";"Mutalisk";"Larva";118;2
"Unit";"Mutalisk";"Larva";118;2
"Building";"CreepTumor";NA;121;0
"Building";"Hatchery";NA;109;0
"Building";"CreepTumor";NA;139;0
"Building";"CreepTumor";NA;139;0
"Building";"CreepTumor";NA;139;0
"Building";"CreepTumorQueen";NA;139;0
"Building";"CreepTumorQueen";NA;139;0
"Unit";"Queen";"Hatchery";118;2
"Building";"CreepTumor";NA;139;0
"Building";"EvolutionChamber";NA;139;0
"Building";"EvolutionChamber";NA;139;0
"Building";"CreepTumorQueen";NA;139;0
"Unit";"Overlord";"Larva";139;0
"Unit";"Overlord";"Larva";139;0
"Building";"BanelingNest";NA;139;0
"Unit";"Queen";"Hatchery";139;2
"Building";"InfestationPit";NA;150;0
"Unit";"Overlord";"Larva";153;0
"Unit";"Overlord";"Larva";153;0
"Unit";"Zergling";"Larva";153;1
"Unit";"Zergling";"Larva";153;1
"Unit";"Zergling";"Larva";153;1
"Unit";"Zergling";"Larva";153;1
"Unit";"Zergling";"Larva";153;1
"Unit";"Zergling";"Larva";153;1
"Unit";"Zergling";"Larva";153;1
"Unit";"Zergling";"Larva";153;1
"Unit";"Zergling";"Larva";153;1
"Unit";"Zergling";"Larva";153;1
"Unit";"Zergling";"Larva";153;1
"Unit";"Zergling";"Larva";153;1
"Unit";"Zergling";"Larva";153;1
"Unit";"Zergling";"Larva";153;1
"Unit";"Zergling";"Larva";153;1
"Unit";"Zergling";"Larva";153;1
"Unit";"Zergling";"Larva";153;1
"Unit";"Zergling";"Larva";153;1
"Unit";"Zergling";"Larva";153;1
"Unit";"Zergling";"Larva";153;1
"Unit";"Zergling";"Larva";153;1
"Unit";"Zergling";"Larva";153;1
"Unit";"Zergling";"Larva";153;1
"Unit";"Zergling";"Larva";153;1
"Unit";"Zergling";"Larva";153;1
"Unit";"Zergling";"Larva";153;1
"Unit";"Zergling";"Larva";153;1
"Unit";"Zergling";"Larva";153;1
"Unit";"Overlord";"Larva";153;0
"Unit";"Overlord";"Larva";153;0
"Unit";"Baneling";"Zergling";177;0
"Unit";"Baneling";"Zergling";177;0
"Unit";"Baneling";"Zergling";177;0
"Unit";"Baneling";"Zergling";177;0
"Unit";"Baneling";"Zergling";177;0
"Unit";"Baneling";"Zergling";177;0
"Unit";"Baneling";"Zergling";177;0
"Unit";"Baneling";"Zergling";177;0
"Unit";"Baneling";"Zergling";177;0
"Unit";"Baneling";"Zergling";177;0
"Unit";"Baneling";"Zergling";177;0
"Unit";"Baneling";"Zergling";177;0
"Unit";"Baneling";"Zergling";177;0
"Unit";"Baneling";"Zergling";177;0
"Unit";"Baneling";"Zergling";177;0
"Unit";"Zergling";"Larva";177;1
"Unit";"Zergling";"Larva";177;1
"Unit";"Zergling";"Larva";177;1
"Unit";"Zergling";"Larva";177;1
"Unit";"Zergling";"Larva";177;1
"Unit";"Zergling";"Larva";177;1
"Unit";"Zergling";"Larva";177;1
"Unit";"Zergling";"Larva";177;1
"Unit";"Zergling";"Larva";177;1
"Unit";"Zergling";"Larva";177;1
"Unit";"Zergling";"Larva";177;1
"Unit";"Zergling";"Larva";177;1
"Unit";"Zergling";"Larva";177;1
"Unit";"Zergling";"Larva";177;1
"Unit";"Zergling";"Larva";177;1
"Unit";"Zergling";"Larva";177;1
"Unit";"Zergling";"Larva";177;1
"Unit";"Zergling";"Larva";177;1
"Unit";"Zergling";"Larva";177;1
"Unit";"Zergling";"Larva";177;1
"Building";"Extractor";NA;177;0
"Building";"Extractor";NA;177;0
"Unit";"Overlord";"Larva";203;0
"Unit";"Zergling";"Larva";203;1
"Unit";"Zergling";"Larva";203;1
"Unit";"Zergling";"Larva";203;1
"Unit";"Zergling";"Larva";203;1
"Unit";"Zergling";"Larva";203;1
"Unit";"Zergling";"Larva";203;1
"Unit";"Zergling";"Larva";203;1
"Unit";"Zergling";"Larva";203;1
"Unit";"Zergling";"Larva";203;1
"Unit";"Zergling";"Larva";203;1
"Unit";"Zergling";"Larva";203;1
"Unit";"Zergling";"Larva";203;1
"Unit";"Zergling";"Larva";203;1
"Unit";"Zergling";"Larva";203;1
"Unit";"Zergling";"Larva";203;1
"Unit";"Zergling";"Larva";203;1
"Unit";"Zergling";"Larva";203;1
"Unit";"Zergling";"Larva";203;1
"Unit";"Overlord";"Larva";203;0
"Building";"CreepTumor";NA;221;0
"Building";"CreepTumor";NA;221;0
"Building";"CreepTumor";NA;221;0
"Building";"CreepTumorQueen";NA;221;0
"Building";"CreepTumor";NA;221;0
"Building";"CreepTumor";NA;221;0
"Building";"CreepTumorQueen";NA;228;0
"Building";"CreepTumor";NA;221;0
"Building";"CreepTumorQueen";NA;228;0
"Building";"CreepTumorQueen";NA;228;0
"Unit";"Overlord";"Larva";228;0
"Unit";"Zergling";"Larva";230;1
"Unit";"Zergling";"Larva";230;1
"Unit";"Zergling";"Larva";230;1
"Unit";"Zergling";"Larva";230;1
"Upgrade";"ZergMeleeWeaponsLevel1";"EvolutionChamber";181;0
"Upgrade";"ZergGroundArmorsLevel1";"EvolutionChamber";181;0
"Building";"CreepTumor";NA;236;0
"Building";"CreepTumor";NA;236;0
"Building";"CreepTumor";NA;236;0
"Building";"CreepTumor";NA;236;0
"Building";"CreepTumor";NA;236;0
"Building";"CreepTumor";NA;236;0
"Building";"CreepTumor";NA;236;0
"Building";"CreepTumor";NA;236;0
"Building";"CreepTumor";NA;236;0
"Unit";"Zergling";"Larva";236;1
"Unit";"Zergling";"Larva";236;1
"Unit";"Zergling";"Larva";236;1
"Unit";"Zergling";"Larva";236;1
"Unit";"Baneling";"Zergling";236;0
"Unit";"Zergling";"Larva";236;1
"Unit";"Zergling";"Larva";236;1
"Unit";"Zergling";"Larva";236;1
"Unit";"Zergling";"Larva";236;1
"Unit";"Zergling";"Larva";236;1
"Unit";"Zergling";"Larva";236;1
"Unit";"Zergling";"Larva";236;1
"Unit";"Zergling";"Larva";236;1
"Unit";"Baneling";"Zergling";236;0
"Unit";"Baneling";"Zergling";236;0
"Unit";"Baneling";"Zergling";236;0
"Unit";"Baneling";"Zergling";236;0
"Unit";"Baneling";"Zergling";236;0
"Unit";"Baneling";"Zergling";236;0
"Unit";"Baneling";"Zergling";236;0
"Unit";"Baneling";"Zergling";236;0
"Unit";"Baneling";"Zergling";236;0
"Unit";"Baneling";"Zergling";236;0
"Unit";"Baneling";"Zergling";236;0
"Unit";"Baneling";"Zergling";236;0
"Unit";"Baneling";"Zergling";236;0
"Unit";"Baneling";"Zergling";236;0
"Unit";"Baneling";"Zergling";236;0
"Unit";"Baneling";"Zergling";236;0
"Unit";"Baneling";"Zergling";236;0
"Unit";"Baneling";"Zergling";236;0
"Unit";"Baneling";"Zergling";236;0
"Unit";"Baneling";"Zergling";236;0
"Unit";"Baneling";"Zergling";236;0
"Unit";"Baneling";"Zergling";236;0
"Unit";"Zergling";"Larva";236;1
"Unit";"Zergling";"Larva";236;1
"Unit";"Zergling";"Larva";236;1
"Unit";"Zergling";"Larva";236;1
"Unit";"Zergling";"Larva";236;1
"Unit";"Zergling";"Larva";236;1
"Unit";"Overlord";"Larva";236;0
"Unit";"Overlord";"Larva";236;0
"Building";"UltraliskCavern";NA;236;0
"Building";"CreepTumor";NA;254;0
"Building";"CreepTumor";NA;254;0
"Building";"CreepTumor";NA;254;0
"Building";"CreepTumorQueen";NA;254;0
"Building";"CreepTumorQueen";NA;254;0
"Building";"CreepTumor";NA;254;0
"Building";"CreepTumor";NA;254;0
"Building";"CreepTumor";NA;254;0
"Building";"CreepTumor";NA;254;0
"Unit";"Overlord";"Larva";254;0
"Building";"CreepTumorQueen";NA;254;0
"Unit";"Overlord";"Larva";254;0
"Unit";"Overlord";"Larva";254;0
"Building";"CreepTumorQueen";NA;254;0
"Building";"CreepTumorQueen";NA;254;0
"Building";"CreepTumor";NA;254;0
"Building";"CreepTumor";NA;254;0
"Unit";"Zergling";"Larva";254;1
"Unit";"Zergling";"Larva";254;1
"Unit";"Zergling";"Larva";254;1
"Unit";"Zergling";"Larva";254;1
"Unit";"Zergling";"Larva";254;1
"Unit";"Zergling";"Larva";254;1
"Unit";"Zergling";"Larva";254;1
"Unit";"Zergling";"Larva";254;1
"Unit";"Zergling";"Larva";254;1
"Unit";"Zergling";"Larva";254;1
"Unit";"Zergling";"Larva";254;1
"Unit";"Zergling";"Larva";254;1
"Unit";"Zergling";"Larva";254;1
"Unit";"Zergling";"Larva";254;1
"Unit";"Zergling";"Larva";254;1
"Unit";"Zergling";"Larva";254;1
"Unit";"Ultralisk";"Larva";254;6
"Unit";"Ultralisk";"Larva";254;6
"Unit";"Ultralisk";"Larva";254;6
"Unit";"Ultralisk";"Larva";254;6
"Unit";"Ultralisk";"Larva";254;6
"Unit";"Ultralisk";"Larva";254;6
"Unit";"Ultralisk";"Larva";254;6
"Building";"CreepTumor";NA;258;0
"Building";"CreepTumor";NA;258;0
"Building";"CreepTumor";NA;258;0
"Building";"CreepTumor";NA;258;0
"Unit";"Zergling";"Larva";254;1
"Unit";"Zergling";"Larva";254;1
"Building";"CreepTumor";NA;258;0
"Unit";"Zergling";"Larva";254;1
"Unit";"Zergling";"Larva";254;1
"Unit";"Zergling";"Larva";254;1
"Unit";"Zergling";"Larva";254;1
"Unit";"Corruptor";"Larva";254;2
"Unit";"Corruptor";"Larva";254;2
"Building";"CreepTumor";NA;264;0
"Unit";"Zergling";"Larva";258;1
"Unit";"Zergling";"Larva";258;1
"Unit";"Zergling";"Larva";258;1
"Unit";"Zergling";"Larva";258;1
"Unit";"Zergling";"Larva";307;1
"Unit";"Zergling";"Larva";307;1
"Unit";"Zergling";"Larva";313;1
"Unit";"Zergling";"Larva";313;1
"Unit";"Zergling";"Larva";323;1
"Unit";"Zergling";"Larva";323;1
"Unit";"Zergling";"Larva";323;1
"Unit";"Zergling";"Larva";323;1
"Unit";"Zergling";"Larva";323;1
"Unit";"Zergling";"Larva";323;1
"Unit";"Zergling";"Larva";323;1
"Unit";"Zergling";"Larva";323;1
"Unit";"Zergling";"Larva";327;1
"Unit";"Zergling";"Larva";327;1
"Unit";"Zergling";"Larva";327;1
"Unit";"Zergling";"Larva";327;1
"Unit";"Zergling";"Larva";327;1
"Unit";"Zergling";"Larva";327;1
"Upgrade";"ChitinousPlating";"UltraliskCavern";254;0
"Building";"SpineCrawler";NA;271;0
"Building";"SpineCrawler";NA;271;0
"Unit";"Baneling";"Zergling";345;0
"Unit";"Corruptor";"Larva";327;2
"Upgrade";"ZergMeleeWeaponsLevel2";"EvolutionChamber";254;0
"Upgrade";"ZergGroundArmorsLevel2";"EvolutionChamber";254;0
"Unit";"Zergling";"Larva";345;1
"Unit";"Zergling";"Larva";345;1
"Unit";"Zergling";"Larva";345;1
"Unit";"Zergling";"Larva";345;1
"Unit";"Zergling";"Larva";345;1
"Unit";"Zergling";"Larva";345;1
"Unit";"Zergling";"Larva";345;1
"Unit";"Zergling";"Larva";345;1
"Unit";"Zergling";"Larva";345;1
"Unit";"Zergling";"Larva";345;1
"Building";"Hatchery";NA;254;0
"Unit";"Zergling";"Larva";345;1
"Unit";"Zergling";"Larva";345;1
