"type";"unit_name";"on_building";"total_supply_lag";"supply"
"Unit";"Overlord";"Larva";13;0
"Building";"SpawningPool";NA;17;0
"Building";"Hatchery";NA;18;0
"Building";"Extractor";NA;20;0
"Unit";"Queen";"Hatchery";21;2
"Unit";"Zergling";"Larva";23;1
"Unit";"Zergling";"Larva";24;1
"Unit";"Overlord";"Larva";25;0
"Unit";"Queen";"Hatchery";27;2
"Unit";"Queen";"Hatchery";31;2
"Unit";"Overlord";"Larva";35;0
"Unit";"Overlord";"Larva";38;0
"Unit";"Queen";"Hatchery";41;2
"Building";"CreepTumorQueen";NA;43;0
"Unit";"Queen";"Hatchery";43;2
"Unit";"Overlord";"Larva";52;0
"Unit";"Overlord";"Larva";53;0
"Unit";"Zergling";"Larva";53;1
"Unit";"Zergling";"Larva";54;1
"Building";"CreepTumor";NA;55;0
"Unit";"Overlord";"Larva";55;0
"Unit";"Zergling";"Larva";55;1
"Unit";"Zergling";"Larva";56;1
"Unit";"Zergling";"Larva";57;1
"Unit";"Zergling";"Larva";58;1
"Building";"CreepTumorQueen";NA;59;0
"Building";"Hatchery";NA;59;0
"Building";"Extractor";NA;61;0
"Building";"RoachWarren";NA;61;0
"Unit";"Zergling";"Larva";63;1
"Unit";"Zergling";"Larva";64;1
"Unit";"Zergling";"Larva";65;1
"Unit";"Zergling";"Larva";66;1
"Unit";"Overlord";"Larva";70;0
"Unit";"Overlord";"Larva";70;0
"Building";"Extractor";NA;70;0
"Building";"CreepTumorQueen";NA;70;0
"Building";"Extractor";NA;70;0
"Unit";"Overlord";"Larva";70;0
"Unit";"Overlord";"Larva";70;0
"Unit";"Roach";"Larva";70;2
"Unit";"Roach";"Larva";72;2
"Unit";"Roach";"Larva";74;2
"Building";"CreepTumor";NA;76;0
"Building";"CreepTumor";NA;76;0
"Unit";"Roach";"Larva";76;2
"Unit";"Roach";"Larva";78;2
"Unit";"Roach";"Larva";80;2
"Unit";"Roach";"Larva";82;2
"Unit";"Roach";"Larva";84;2
"Unit";"Roach";"Larva";86;2
"Unit";"Roach";"Larva";88;2
"Unit";"Roach";"Larva";90;2
"Unit";"Roach";"Larva";92;2
"Building";"CreepTumorQueen";NA;100;0
"Building";"CreepTumorQueen";NA;100;0
"Building";"EvolutionChamber";NA;101;0
"Building";"EvolutionChamber";NA;103;0
"Building";"CreepTumor";NA;107;0
"Unit";"Roach";"Larva";107;2
"Unit";"Roach";"Larva";109;2
"Unit";"Roach";"Larva";111;2
"Building";"CreepTumorQueen";NA;113;0
"Building";"CreepTumorQueen";NA;113;0
"Unit";"Roach";"Larva";113;2
"Unit";"Roach";"Larva";115;2
"Building";"CreepTumorQueen";NA;117;0
"Unit";"Roach";"Larva";118;2
"Unit";"Roach";"Larva";120;2
"Unit";"Roach";"Larva";122;2
"Unit";"Overlord";"Larva";124;0
"Unit";"Overlord";"Larva";124;0
"Unit";"Overlord";"Larva";124;0
"Building";"CreepTumor";NA;124;0
"Building";"CreepTumor";NA;124;0
"Building";"CreepTumor";NA;124;0
"Unit";"Queen";"Hatchery";124;2
"Unit";"Queen";"Hatchery";126;2
"Building";"Hatchery";NA;128;0
"Unit";"Roach";"Larva";128;2
"Unit";"Roach";"Larva";130;2
"Unit";"Roach";"Larva";132;2
"Unit";"Overlord";"Larva";149;0
"Building";"Extractor";NA;153;0
"Building";"Extractor";NA;153;0
"Building";"InfestationPit";NA;153;0
"Building";"HydraliskDen";NA;153;0
"Unit";"Roach";"Larva";153;2
"Unit";"Roach";"Larva";155;2
"Unit";"Roach";"Larva";157;2
"Unit";"Roach";"Larva";159;2
"Unit";"Roach";"Larva";161;2
"Unit";"Roach";"Larva";163;2
"Upgrade";"GlialReconstitution";"RoachWarren";165;0
"Unit";"Roach";"Larva";165;2
"Unit";"Roach";"Larva";167;2
"Unit";"Roach";"Larva";169;2
"Unit";"Roach";"Larva";171;2
"Unit";"Roach";"Larva";173;2
"Unit";"Roach";"Larva";175;2
"Unit";"Roach";"Larva";177;2
"Unit";"Roach";"Larva";179;2
"Unit";"Roach";"Larva";181;2
"Unit";"Roach";"Larva";183;2
"Unit";"Roach";"Larva";185;2
"Unit";"Roach";"Larva";187;2
"Unit";"Roach";"Larva";189;2
"Unit";"Roach";"Larva";191;2
"Unit";"Roach";"Larva";193;2
"Unit";"Roach";"Larva";195;2
"Unit";"Roach";"Larva";197;2
"Unit";"Roach";"Larva";199;2
"Unit";"Roach";"Larva";201;2
"Unit";"Roach";"Larva";203;2
"Unit";"Roach";"Larva";205;2
"Building";"Extractor";NA;207;0
"Building";"Extractor";NA;207;0
"Building";"CreepTumor";NA;207;0
"Building";"Hatchery";NA;211;0
"Unit";"Roach";"Larva";211;2
"Unit";"Roach";"Larva";213;2
"Building";"Hatchery";NA;215;0
"Unit";"Queen";"Hatchery";215;2
"Unit";"Queen";"Hatchery";217;2
"Unit";"Queen";"Hatchery";219;2
"Building";"CreepTumor";NA;230;0
"Unit";"Overlord";"Larva";230;0
"Unit";"Overlord";"Larva";230;0
"Building";"Extractor";NA;230;0
"Unit";"Overlord";"Larva";230;0
"Building";"Extractor";NA;230;0
"Unit";"Queen";"Hatchery";230;2
"Unit";"Roach";"Larva";232;2
"Unit";"Roach";"Larva";234;2
"Unit";"Roach";"Larva";236;2
"Unit";"Roach";"Larva";238;2
"Unit";"Roach";"Larva";240;2
"Unit";"Roach";"Larva";242;2
"Unit";"Roach";"Larva";244;2
"Unit";"Roach";"Larva";246;2
"Unit";"Overlord";"Larva";248;0
"Unit";"Roach";"Larva";248;2
"Unit";"Roach";"Larva";250;2
"Unit";"Roach";"Larva";252;2
"Unit";"Roach";"Larva";254;2
"Unit";"Roach";"Larva";256;2
"Unit";"Hydralisk";"Larva";258;2
"Unit";"Hydralisk";"Larva";260;2
"Unit";"Hydralisk";"Larva";262;2
"Unit";"Hydralisk";"Larva";264;2
"Unit";"Hydralisk";"Larva";266;2
"Unit";"Hydralisk";"Larva";268;2
"Unit";"Hydralisk";"Larva";270;2
"Unit";"Overlord";"Larva";272;0
"Unit";"Hydralisk";"Larva";272;2
"Unit";"Hydralisk";"Larva";274;2
"Unit";"Hydralisk";"Larva";276;2
"Unit";"Hydralisk";"Larva";278;2
"Unit";"Hydralisk";"Larva";280;2
"Unit";"Hydralisk";"Larva";282;2
"Building";"Hatchery";NA;284;0
"Unit";"Viper";"Larva";294;3
"Unit";"Viper";"Larva";297;3
"Unit";"Viper";"Larva";300;3
"Unit";"Viper";"Larva";303;3
"Unit";"Hydralisk";"Larva";306;2
"Unit";"Hydralisk";"Larva";308;2
"Unit";"Hydralisk";"Larva";310;2
"Unit";"Hydralisk";"Larva";312;2
"Building";"CreepTumor";NA;314;0
"Unit";"Hydralisk";"Larva";314;2
"Unit";"Hydralisk";"Larva";316;2
"Unit";"Roach";"Larva";318;2
"Unit";"Roach";"Larva";320;2
"Building";"CreepTumorQueen";NA;322;0
"Unit";"Roach";"Larva";322;2
"Building";"CreepTumorQueen";NA;324;0
"Unit";"Roach";"Larva";324;2
"Unit";"Roach";"Larva";326;2
"Unit";"Roach";"Larva";328;2
"Unit";"Roach";"Larva";330;2
"Unit";"Roach";"Larva";332;2
"Unit";"Roach";"Larva";334;2
"Unit";"Hydralisk";"Larva";342;2
"Unit";"Hydralisk";"Larva";344;2
"Building";"CreepTumor";NA;346;0
"Building";"CreepTumor";NA;346;0
"Building";"CreepTumorQueen";NA;348;0
"Unit";"Overlord";"Larva";348;0
"Building";"CreepTumor";NA;348;0
"Building";"CreepTumor";NA;348;0
"Building";"CreepTumor";NA;348;0
"Building";"Hatchery";NA;348;0
"Unit";"Viper";"Larva";348;3
"Unit";"Viper";"Larva";351;3
"Unit";"Viper";"Larva";354;3
"Unit";"Overlord";"Larva";357;0
"Unit";"Roach";"Larva";362;2
"Unit";"Roach";"Larva";364;2
"Unit";"Roach";"Larva";366;2
"Unit";"Roach";"Larva";368;2
"Unit";"Roach";"Larva";370;2
"Unit";"Roach";"Larva";372;2
"Unit";"Roach";"Larva";374;2
"Unit";"Roach";"Larva";376;2
"Unit";"Roach";"Larva";378;2
"Unit";"Roach";"Larva";380;2
"Unit";"Roach";"Larva";382;2
"Unit";"Roach";"Larva";384;2
"Unit";"Overlord";"Larva";386;0
"Unit";"Roach";"Larva";386;2
"Unit";"Roach";"Larva";388;2
"Unit";"Roach";"Larva";390;2
"Unit";"Roach";"Larva";392;2
"Building";"CreepTumorQueen";NA;394;0
"Unit";"Hydralisk";"Larva";394;2
"Unit";"Hydralisk";"Larva";396;2
"Unit";"Hydralisk";"Larva";398;2
"Unit";"Hydralisk";"Larva";400;2
"Unit";"Hydralisk";"Larva";402;2
"Unit";"Hydralisk";"Larva";404;2
"Unit";"Hydralisk";"Larva";406;2
"Upgrade";"SprayZerg";NA;408;0
"Upgrade";"SprayZerg";NA;408;0
"Upgrade";"zerglingmovementspeed";NA;408;0
"Upgrade";"SprayZerg";NA;408;0
"Upgrade";"SprayZerg";NA;408;0
"Upgrade";"SprayZerg";NA;408;0
"Upgrade";"SprayZerg";NA;408;0
"Upgrade";"ZergGroundArmorsLevel1";NA;408;0
"Upgrade";"ZergMissileWeaponsLevel1";NA;408;0
"Upgrade";"SprayZerg";NA;408;0
"Upgrade";"SprayZerg";NA;408;0
"Upgrade";"SprayZerg";NA;408;0
"Upgrade";"SprayZerg";NA;408;0
"Upgrade";"EvolveGroovedSpines";NA;408;0
"Upgrade";"SprayZerg";NA;408;0
"Upgrade";"ZergMissileWeaponsLevel2";NA;408;0
"Upgrade";"ZergGroundArmorsLevel2";NA;408;0
"Upgrade";"SprayZerg";NA;408;0
"Upgrade";"EvolveMuscularAugments";NA;408;0
"Upgrade";"SprayZerg";NA;408;0
"Upgrade";"overlordspeed";NA;408;0
"Upgrade";"SprayZerg";NA;408;0
