"type";"unit_name";"on_building";"total_supply";"supply"
"Unit";"Overlord";"Larva";13;0
"Building";"Extractor";NA;18;0
"Unit";"Overlord";"Larva";21;0
"Building";"SpawningPool";NA;19;0
"Building";"Hatchery";NA;17;0
"Unit";"Zergling";"Larva";23;1
"Unit";"Zergling";"Larva";23;1
"Unit";"Zergling";"Larva";23;1
"Unit";"Zergling";"Larva";23;1
"Unit";"Queen";"Hatchery";23;2
"Unit";"Queen";"Hatchery";23;2
"Unit";"Overlord";"Larva";34;0
"Building";"CreepTumorQueen";NA;38;0
"Unit";"Overlord";"Larva";39;0
"Building";"Hatchery";NA;30;0
"Unit";"Queen";"Hatchery";41;2
"Unit";"Overlord";"Larva";47;0
"Building";"CreepTumorQueen";NA;47;0
"Building";"CreepTumor";NA;47;0
"Building";"Extractor";NA;47;0
"Building";"Extractor";NA;47;0
"Unit";"Queen";"Hatchery";47;2
"Building";"RoachWarren";NA;47;0
"Building";"CreepTumorQueen";NA;56;0
"Building";"CreepTumor";NA;58;0
"Unit";"Queen";"Hatchery";49;2
"Unit";"Roach";"Larva";58;2
"Unit";"Roach";"Larva";58;2
"Unit";"Roach";"Larva";58;2
"Unit";"Roach";"Larva";58;2
"Unit";"Roach";"Larva";58;2
"Building";"CreepTumor";NA;58;0
"Unit";"Overlord";"Larva";58;0
"Unit";"Queen";"Hatchery";56;2
"Building";"CreepTumorQueen";NA;58;0
"Unit";"Overlord";"Larva";70;0
"Unit";"Overlord";"Larva";70;0
"Unit";"Roach";"Larva";72;2
"Unit";"Roach";"Larva";72;2
"Unit";"Roach";"Larva";72;2
"Building";"CreepTumor";NA;72;0
"Unit";"Queen";"Hatchery";70;2
"Unit";"Queen";"Hatchery";70;2
"Unit";"Overlord";"Larva";72;0
"Unit";"Overlord";"Larva";72;0
"Building";"CreepTumorQueen";NA;76;0
"Building";"CreepTumor";NA;76;0
"Building";"CreepTumor";NA;80;0
"Building";"CreepTumor";NA;80;0
"Unit";"Overlord";"Larva";90;0
"Building";"SporeCrawler";NA;90;0
"Building";"Extractor";NA;90;0
"Building";"SporeCrawler";NA;90;0
"Building";"BanelingNest";NA;90;0
"Unit";"Zergling";"Larva";97;1
"Unit";"Zergling";"Larva";97;1
"Unit";"Zergling";"Larva";97;1
"Unit";"Zergling";"Larva";97;1
"Building";"CreepTumor";NA;104;0
"Unit";"Roach";"Larva";104;2
"Unit";"Roach";"Larva";104;2
"Unit";"Roach";"Larva";104;2
"Unit";"Roach";"Larva";104;2
"Unit";"Roach";"Larva";104;2
"Unit";"Roach";"Larva";104;2
"Unit";"Roach";"Larva";104;2
"Unit";"Roach";"Larva";106;2
"Building";"CreepTumorQueen";NA;108;0
"Building";"CreepTumorQueen";NA;108;0
"Building";"CreepTumor";NA;126;0
"Building";"SporeCrawler";NA;124;0
"Unit";"Queen";"Hatchery";124;2
"Building";"HydraliskDen";NA;126;0
"Building";"Extractor";NA;128;0
"Building";"Extractor";NA;128;0
"Building";"SporeCrawler";NA;128;0
"Unit";"Zergling";"Larva";134;1
"Unit";"Zergling";"Larva";134;1
"Unit";"Zergling";"Larva";134;1
"Unit";"Zergling";"Larva";134;1
"Building";"EvolutionChamber";NA;128;0
"Unit";"Zergling";"Larva";134;1
"Unit";"Zergling";"Larva";134;1
"Unit";"Zergling";"Larva";134;1
"Unit";"Zergling";"Larva";134;1
"Unit";"Zergling";"Larva";134;1
"Unit";"Zergling";"Larva";134;1
"Unit";"Zergling";"Larva";134;1
"Unit";"Zergling";"Larva";134;1
"Building";"EvolutionChamber";NA;128;0
"Building";"Hatchery";NA;124;0
"Unit";"Zergling";"Larva";150;1
"Unit";"Zergling";"Larva";150;1
"Unit";"Overlord";"Larva";150;0
"Unit";"Overlord";"Larva";150;0
"Unit";"Overlord";"Larva";150;0
"Unit";"Overlord";"Larva";150;0
"Building";"CreepTumor";NA;150;0
"Building";"CreepTumor";NA;150;0
"Building";"CreepTumor";NA;150;0
"Upgrade";"GlialReconstitution";"RoachWarren";128;0
"Unit";"Overlord";"Larva";150;0
"Unit";"Overlord";"Larva";150;0
"Building";"Hatchery";NA;128;0
"Building";"CreepTumorQueen";NA;152;0
"Unit";"Zergling";"Larva";152;1
"Unit";"Zergling";"Larva";152;1
"Unit";"Zergling";"Larva";152;1
"Unit";"Zergling";"Larva";152;1
"Unit";"Zergling";"Larva";152;1
"Unit";"Zergling";"Larva";152;1
"Unit";"Zergling";"Larva";152;1
"Unit";"Zergling";"Larva";152;1
"Unit";"Zergling";"Larva";152;1
"Unit";"Zergling";"Larva";152;1
"Unit";"Zergling";"Larva";152;1
"Unit";"Zergling";"Larva";152;1
"Unit";"Zergling";"Larva";152;1
"Unit";"Zergling";"Larva";152;1
"Unit";"Zergling";"Larva";152;1
"Unit";"Zergling";"Larva";152;1
"Unit";"Zergling";"Larva";152;1
"Unit";"Zergling";"Larva";152;1
"Unit";"Zergling";"Larva";152;1
"Unit";"Zergling";"Larva";152;1
"Unit";"Zergling";"Larva";152;1
"Unit";"Zergling";"Larva";152;1
"Unit";"Zergling";"Larva";152;1
"Unit";"Zergling";"Larva";152;1
"Building";"CreepTumorQueen";NA;152;0
"Building";"CreepTumorQueen";NA;152;0
"Upgrade";"EvolveMuscularAugments";"HydraliskDen";150;0
"Unit";"Zergling";"Larva";152;1
"Unit";"Zergling";"Larva";152;1
"Unit";"Baneling";"Zergling";176;0
"Unit";"Baneling";"Zergling";176;0
"Unit";"Baneling";"Zergling";176;0
"Unit";"Baneling";"Zergling";176;0
"Unit";"Baneling";"Zergling";176;0
"Unit";"Baneling";"Zergling";176;0
"Unit";"Baneling";"Zergling";176;0
"Unit";"Baneling";"Zergling";176;0
"Unit";"Baneling";"Zergling";176;0
"Unit";"Baneling";"Zergling";176;0
"Unit";"Baneling";"Zergling";176;0
"Unit";"Baneling";"Zergling";176;0
"Unit";"Baneling";"Zergling";176;0
"Unit";"Hydralisk";"Larva";176;2
"Unit";"Baneling";"Zergling";176;0
"Unit";"Hydralisk";"Larva";176;2
"Unit";"Hydralisk";"Larva";176;2
"Unit";"Hydralisk";"Larva";176;2
"Unit";"Hydralisk";"Larva";176;2
"Unit";"Hydralisk";"Larva";176;2
"Unit";"Hydralisk";"Larva";176;2
"Unit";"Hydralisk";"Larva";176;2
"Unit";"Hydralisk";"Larva";176;2
"Unit";"Hydralisk";"Larva";176;2
"Unit";"Hydralisk";"Larva";176;2
"Building";"CreepTumor";NA;176;0
"Unit";"Hydralisk";"Larva";176;2
"Building";"CreepTumorQueen";NA;202;0
"Unit";"Hydralisk";"Larva";202;2
"Unit";"Hydralisk";"Larva";202;2
"Unit";"Hydralisk";"Larva";202;2
"Unit";"Hydralisk";"Larva";202;2
"Unit";"Hydralisk";"Larva";202;2
"Unit";"Hydralisk";"Larva";202;2
"Unit";"Hydralisk";"Larva";202;2
"Unit";"Zergling";"Larva";202;1
"Unit";"Zergling";"Larva";202;1
"Unit";"Zergling";"Larva";202;1
"Unit";"Zergling";"Larva";202;1
"Unit";"Zergling";"Larva";202;1
"Unit";"Zergling";"Larva";202;1
"Unit";"Zergling";"Larva";202;1
"Unit";"Zergling";"Larva";202;1
"Unit";"Zergling";"Larva";202;1
"Unit";"Zergling";"Larva";202;1
"Unit";"Zergling";"Larva";202;1
"Unit";"Zergling";"Larva";202;1
"Unit";"Zergling";"Larva";202;1
"Unit";"Zergling";"Larva";202;1
"Unit";"Zergling";"Larva";202;1
"Unit";"Zergling";"Larva";202;1
"Unit";"Zergling";"Larva";202;1
"Unit";"Zergling";"Larva";202;1
"Building";"CreepTumor";NA;202;0
"Building";"CreepTumor";NA;202;0
"Building";"CreepTumor";NA;212;0
"Building";"CreepTumor";NA;216;0
"Building";"CreepTumor";NA;216;0
"Unit";"Zergling";"Larva";202;1
"Unit";"Zergling";"Larva";202;1
"Unit";"Zergling";"Larva";202;1
"Unit";"Zergling";"Larva";202;1
"Unit";"Zergling";"Larva";202;1
"Unit";"Zergling";"Larva";202;1
"Unit";"Zergling";"Larva";202;1
"Unit";"Zergling";"Larva";202;1
"Building";"CreepTumorQueen";NA;234;0
"Building";"CreepTumorQueen";NA;234;0
"Building";"CreepTumor";NA;234;0
"Unit";"Zergling";"Larva";216;1
"Unit";"Zergling";"Larva";216;1
"Unit";"Zergling";"Larva";216;1
"Unit";"Zergling";"Larva";216;1
"Unit";"Zergling";"Larva";216;1
"Unit";"Zergling";"Larva";216;1
"Upgrade";"EvolveGroovedSpines";"HydraliskDen";202;0
"Unit";"Zergling";"Larva";234;1
"Unit";"Zergling";"Larva";234;1
"Unit";"Zergling";"Larva";234;1
"Unit";"Zergling";"Larva";234;1
"Unit";"Zergling";"Larva";234;1
"Unit";"Zergling";"Larva";234;1
"Unit";"Zergling";"Larva";234;1
"Unit";"Zergling";"Larva";234;1
"Unit";"Zergling";"Larva";234;1
"Unit";"Zergling";"Larva";234;1
"Unit";"Zergling";"Larva";234;1
"Unit";"Zergling";"Larva";234;1
"Unit";"Zergling";"Larva";234;1
"Unit";"Zergling";"Larva";234;1
"Unit";"Overlord";"Larva";242;0
"Unit";"Baneling";"Zergling";248;0
"Unit";"Baneling";"Zergling";248;0
"Unit";"Baneling";"Zergling";248;0
"Unit";"Baneling";"Zergling";248;0
"Unit";"Baneling";"Zergling";248;0
"Unit";"Baneling";"Zergling";248;0
"Unit";"Baneling";"Zergling";248;0
"Unit";"Baneling";"Zergling";248;0
"Unit";"Baneling";"Zergling";248;0
"Unit";"Baneling";"Zergling";248;0
"Unit";"Baneling";"Zergling";248;0
"Upgrade";"ZergMeleeWeaponsLevel1";"EvolutionChamber";176;0
"Building";"CreepTumor";NA;248;0
"Upgrade";"ZergGroundArmorsLevel1";"EvolutionChamber";176;0
"Building";"CreepTumor";NA;248;0
"Building";"CreepTumor";NA;248;0
"Building";"CreepTumor";NA;248;0
"Building";"CreepTumor";NA;252;0
"Unit";"Queen";"Hatchery";234;2
"Building";"CreepTumorQueen";NA;262;0
"Building";"CreepTumorQueen";NA;262;0
"Building";"CreepTumorQueen";NA;262;0
"Building";"CreepTumor";NA;262;0
"Building";"CreepTumor";NA;262;0
"Building";"InfestationPit";NA;234;0
"Unit";"Baneling";"Zergling";262;0
"Unit";"Baneling";"Zergling";264;0
"Unit";"Baneling";"Zergling";264;0
"Unit";"Baneling";"Zergling";264;0
"Unit";"Baneling";"Zergling";264;0
"Unit";"Baneling";"Zergling";264;0
"Building";"CreepTumor";NA;264;0
"Unit";"Overlord";"Larva";272;0
"Unit";"Overlord";"Larva";272;0
"Building";"CreepTumor";NA;272;0
"Building";"CreepTumor";NA;272;0
"Building";"CreepTumor";NA;272;0
"Building";"CreepTumor";NA;272;0
"Building";"CreepTumor";NA;272;0
"Unit";"Zergling";"Larva";272;1
"Unit";"Zergling";"Larva";272;1
"Unit";"Zergling";"Larva";272;1
"Unit";"Zergling";"Larva";272;1
"Unit";"Zergling";"Larva";272;1
"Unit";"Zergling";"Larva";272;1
"Building";"CreepTumor";NA;272;0
"Unit";"Hydralisk";"Larva";272;2
"Building";"CreepTumor";NA;272;0
"Unit";"Hydralisk";"Larva";272;2
"Unit";"Queen";"Hatchery";272;2
"Unit";"Hydralisk";"Larva";272;2
"Unit";"Hydralisk";"Larva";272;2
"Unit";"Hydralisk";"Larva";272;2
"Unit";"Hydralisk";"Larva";272;2
"Unit";"Hydralisk";"Larva";272;2
"Unit";"Hydralisk";"Larva";272;2
"Unit";"Hydralisk";"Larva";272;2
"Unit";"Hydralisk";"Larva";272;2
"Unit";"Hydralisk";"Larva";272;2
"Building";"CreepTumor";NA;272;0
"Building";"CreepTumor";NA;272;0
"Unit";"Zergling";"Larva";278;1
"Unit";"Zergling";"Larva";278;1
"Building";"CreepTumor";NA;302;0
"Unit";"Zergling";"Larva";278;1
"Unit";"Zergling";"Larva";278;1
"Unit";"Zergling";"Larva";280;1
"Unit";"Zergling";"Larva";280;1
"Unit";"Zergling";"Larva";280;1
"Unit";"Zergling";"Larva";280;1
"Unit";"Zergling";"Larva";280;1
"Unit";"Zergling";"Larva";280;1
"Unit";"Zergling";"Larva";280;1
"Unit";"Zergling";"Larva";280;1
"Unit";"Zergling";"Larva";280;1
"Unit";"Zergling";"Larva";280;1
"Unit";"Zergling";"Larva";280;1
"Unit";"Zergling";"Larva";280;1
"Unit";"Zergling";"Larva";280;1
"Unit";"Zergling";"Larva";280;1
"Unit";"Zergling";"Larva";280;1
"Unit";"Zergling";"Larva";280;1
"Unit";"Zergling";"Larva";280;1
"Unit";"Zergling";"Larva";280;1
"Unit";"Zergling";"Larva";280;1
"Unit";"Zergling";"Larva";280;1
"Unit";"Zergling";"Larva";280;1
"Unit";"Zergling";"Larva";280;1
"Unit";"Zergling";"Larva";280;1
"Unit";"Zergling";"Larva";280;1
"Unit";"Zergling";"Larva";280;1
"Unit";"Zergling";"Larva";280;1
"Unit";"Zergling";"Larva";280;1
"Unit";"Zergling";"Larva";280;1
"Unit";"Zergling";"Larva";282;1
"Unit";"Zergling";"Larva";282;1
"Unit";"Zergling";"Larva";282;1
"Unit";"Zergling";"Larva";282;1
"Unit";"Zergling";"Larva";290;1
"Unit";"Zergling";"Larva";290;1
"Building";"CreepTumor";NA;302;0
"Building";"CreepTumor";NA;302;0
"Building";"CreepTumor";NA;302;0
"Building";"CreepTumor";NA;302;0
"Building";"CreepTumor";NA;340;0
"Building";"CreepTumor";NA;340;0
"Building";"CreepTumor";NA;340;0
"Building";"CreepTumor";NA;340;0
"Building";"CreepTumor";NA;340;0
"Building";"Extractor";NA;340;0
"Building";"Extractor";NA;340;0
"Unit";"Baneling";"Zergling";340;0
"Unit";"Baneling";"Zergling";340;0
"Unit";"Baneling";"Zergling";340;0
"Unit";"Baneling";"Zergling";340;0
"Unit";"Baneling";"Zergling";340;0
"Unit";"Baneling";"Zergling";340;0
"Unit";"Baneling";"Zergling";340;0
"Unit";"Baneling";"Zergling";340;0
"Unit";"Baneling";"Zergling";340;0
"Unit";"Baneling";"Zergling";340;0
"Unit";"Baneling";"Zergling";340;0
"Unit";"Baneling";"Zergling";340;0
"Unit";"Baneling";"Zergling";340;0
"Unit";"Baneling";"Zergling";340;0
"Unit";"Baneling";"Zergling";340;0
"Unit";"Baneling";"Zergling";340;0
"Unit";"Baneling";"Zergling";340;0
"Unit";"Baneling";"Zergling";340;0
"Unit";"Baneling";"Zergling";340;0
"Unit";"Baneling";"Zergling";340;0
"Unit";"Baneling";"Zergling";340;0
"Unit";"Baneling";"Zergling";340;0
"Unit";"Baneling";"Zergling";340;0
"Unit";"Baneling";"Zergling";340;0
"Unit";"Baneling";"Zergling";340;0
"Unit";"Baneling";"Zergling";340;0
"Unit";"Baneling";"Zergling";340;0
"Unit";"Baneling";"Zergling";340;0
"Unit";"Baneling";"Zergling";340;0
"Unit";"Baneling";"Zergling";340;0
"Unit";"Baneling";"Zergling";340;0
"Unit";"Baneling";"Zergling";340;0
"Unit";"Baneling";"Zergling";340;0
"Unit";"Baneling";"Zergling";340;0
"Unit";"Baneling";"Zergling";340;0
"Unit";"Baneling";"Zergling";340;0
"Unit";"Baneling";"Zergling";340;0
"Unit";"Baneling";"Zergling";340;0
"Unit";"Baneling";"Zergling";340;0
"Unit";"Baneling";"Zergling";340;0
"Unit";"Baneling";"Zergling";340;0
"Unit";"Baneling";"Zergling";340;0
"Unit";"Baneling";"Zergling";340;0
"Unit";"Baneling";"Zergling";340;0
"Building";"CreepTumorQueen";NA;340;0
"Upgrade";"ZergMeleeWeaponsLevel2";"EvolutionChamber";272;0
"Building";"CreepTumor";NA;340;0
"Building";"CreepTumorQueen";NA;340;0
"Unit";"Zergling";"Larva";340;1
"Unit";"Zergling";"Larva";340;1
"Building";"CreepTumor";NA;340;0
"Unit";"Zergling";"Larva";340;1
"Unit";"Zergling";"Larva";340;1
"Unit";"Zergling";"Larva";340;1
"Unit";"Zergling";"Larva";340;1
"Building";"CreepTumor";NA;340;0
"Unit";"Zergling";"Larva";340;1
"Unit";"Zergling";"Larva";340;1
"Upgrade";"ZergGroundArmorsLevel2";"EvolutionChamber";272;0
"Building";"Extractor";NA;340;0
"Building";"Extractor";NA;340;0
"Building";"Spire";NA;340;0
"Upgrade";"Burrow";"Hatchery";340;0
"Building";"Hatchery";NA;340;0
"Building";"CreepTumor";NA;358;0
"Building";"CreepTumor";NA;358;0
"Building";"CreepTumor";NA;358;0
"Building";"CreepTumor";NA;358;0
"Unit";"Corruptor";"Larva";358;2
"Unit";"Corruptor";"Larva";358;2
"Unit";"Corruptor";"Larva";358;2
"Unit";"Corruptor";"Larva";358;2
"Unit";"Corruptor";"Larva";358;2
"Unit";"Corruptor";"Larva";358;2
"Unit";"Corruptor";"Larva";358;2
"Unit";"Queen";"Hatchery";358;2
"Unit";"Zergling";"Larva";384;1
"Unit";"Zergling";"Larva";384;1
"Unit";"Zergling";"Larva";384;1
"Unit";"Zergling";"Larva";384;1
"Unit";"Zergling";"Larva";384;1
"Unit";"Zergling";"Larva";384;1
"Unit";"Zergling";"Larva";384;1
"Unit";"Zergling";"Larva";384;1
"Unit";"Zergling";"Larva";384;1
"Unit";"Zergling";"Larva";384;1
"Unit";"Zergling";"Larva";384;1
"Unit";"Zergling";"Larva";384;1
"Unit";"Zergling";"Larva";384;1
"Unit";"Zergling";"Larva";384;1
"Unit";"Zergling";"Larva";384;1
"Unit";"Zergling";"Larva";384;1
"Unit";"Zergling";"Larva";384;1
"Unit";"Zergling";"Larva";384;1
"Unit";"Zergling";"Larva";384;1
"Unit";"Zergling";"Larva";384;1
"Unit";"Zergling";"Larva";384;1
"Unit";"Zergling";"Larva";384;1
"Unit";"Zergling";"Larva";384;1
"Unit";"Zergling";"Larva";384;1
"Unit";"Zergling";"Larva";384;1
"Unit";"Zergling";"Larva";384;1
"Unit";"Zergling";"Larva";384;1
"Unit";"Zergling";"Larva";384;1
"Unit";"Zergling";"Larva";384;1
"Unit";"Zergling";"Larva";384;1
"Unit";"Zergling";"Larva";384;1
"Unit";"Zergling";"Larva";384;1
"Unit";"Zergling";"Larva";384;1
"Unit";"Zergling";"Larva";384;1
"Unit";"Zergling";"Larva";384;1
"Unit";"Zergling";"Larva";384;1
"Unit";"Zergling";"Larva";384;1
"Unit";"Zergling";"Larva";384;1
"Unit";"Zergling";"Larva";384;1
"Unit";"Zergling";"Larva";384;1
"Building";"CreepTumor";NA;384;0
"Building";"CreepTumorQueen";NA;426;0
"Building";"CreepTumorQueen";NA;426;0
"Unit";"Corruptor";"Larva";384;2
"Unit";"Corruptor";"Larva";384;2
"Building";"CreepTumor";NA;426;0
"Building";"CreepTumor";NA;426;0
"Building";"CreepTumorQueen";NA;426;0
"Building";"CreepTumor";NA;426;0
"Building";"CreepTumorQueen";NA;430;0
"Unit";"Zergling";"Larva";430;1
"Unit";"Zergling";"Larva";430;1
"Unit";"Zergling";"Larva";430;1
"Unit";"Zergling";"Larva";430;1
"Unit";"Zergling";"Larva";430;1
"Unit";"Zergling";"Larva";430;1
"Unit";"Zergling";"Larva";430;1
"Unit";"Zergling";"Larva";430;1
"Unit";"Zergling";"Larva";430;1
"Unit";"Zergling";"Larva";430;1
"Unit";"Zergling";"Larva";430;1
"Unit";"Zergling";"Larva";430;1
"Unit";"Zergling";"Larva";430;1
"Unit";"Zergling";"Larva";430;1
"Unit";"Zergling";"Larva";430;1
"Unit";"Zergling";"Larva";430;1
"Unit";"Zergling";"Larva";430;1
"Unit";"Zergling";"Larva";430;1
"Unit";"Zergling";"Larva";430;1
"Unit";"Zergling";"Larva";430;1
"Unit";"Zergling";"Larva";430;1
"Unit";"Zergling";"Larva";430;1
"Unit";"Zergling";"Larva";430;1
"Unit";"Zergling";"Larva";430;1
"Unit";"Zergling";"Larva";430;1
"Unit";"Zergling";"Larva";430;1
"Unit";"Zergling";"Larva";430;1
"Unit";"Zergling";"Larva";430;1
"Unit";"Zergling";"Larva";430;1
"Unit";"Zergling";"Larva";430;1
"Unit";"Zergling";"Larva";430;1
"Unit";"Zergling";"Larva";430;1
"Unit";"Zergling";"Larva";430;1
"Unit";"Zergling";"Larva";430;1
"Unit";"Zergling";"Larva";430;1
"Unit";"Zergling";"Larva";430;1
"Unit";"Zergling";"Larva";430;1
"Unit";"Zergling";"Larva";430;1
"Unit";"Zergling";"Larva";430;1
"Unit";"Zergling";"Larva";430;1
"Unit";"Zergling";"Larva";430;1
"Unit";"Zergling";"Larva";430;1
"Unit";"Zergling";"Larva";430;1
"Unit";"Zergling";"Larva";430;1
"Unit";"Zergling";"Larva";430;1
"Unit";"Zergling";"Larva";430;1
"Unit";"Zergling";"Larva";430;1
"Unit";"Zergling";"Larva";430;1
"Unit";"Zergling";"Larva";430;1
"Unit";"Zergling";"Larva";430;1
"Unit";"Zergling";"Larva";430;1
"Unit";"Zergling";"Larva";430;1
"Unit";"Zergling";"Larva";430;1
"Unit";"Zergling";"Larva";430;1
"Building";"CreepTumor";NA;430;0
"Building";"CreepTumor";NA;430;0
"Unit";"Overlord";"Larva";430;0
"Unit";"Overlord";"Larva";430;0
"Unit";"Overlord";"Larva";430;0
"Building";"CreepTumor";NA;430;0
"Unit";"Baneling";"Zergling";430;0
"Unit";"Baneling";"Zergling";430;0
"Unit";"Baneling";"Zergling";430;0
"Unit";"Baneling";"Zergling";430;0
"Unit";"Baneling";"Zergling";430;0
"Unit";"Baneling";"Zergling";430;0
"Unit";"Baneling";"Zergling";430;0
"Unit";"Baneling";"Zergling";430;0
"Unit";"Baneling";"Zergling";430;0
"Unit";"Baneling";"Zergling";430;0
"Unit";"Baneling";"Zergling";430;0
"Unit";"Baneling";"Zergling";430;0
"Unit";"Baneling";"Zergling";430;0
"Unit";"Baneling";"Zergling";430;0
"Unit";"Baneling";"Zergling";430;0
"Unit";"Baneling";"Zergling";430;0
"Unit";"Baneling";"Zergling";430;0
"Unit";"Baneling";"Zergling";430;0
"Unit";"Baneling";"Zergling";430;0
"Unit";"Baneling";"Zergling";430;0
"Unit";"Baneling";"Zergling";430;0
"Unit";"Baneling";"Zergling";430;0
"Unit";"Baneling";"Zergling";430;0
"Unit";"Baneling";"Zergling";430;0
"Unit";"Baneling";"Zergling";430;0
"Unit";"Baneling";"Zergling";430;0
"Unit";"Baneling";"Zergling";430;0
"Unit";"Baneling";"Zergling";430;0
"Unit";"Baneling";"Zergling";430;0
"Building";"CreepTumor";NA;474;0
"Building";"CreepTumor";NA;484;0
"Building";"CreepTumor";NA;484;0
"Building";"SporeCrawler";NA;430;0
"Upgrade";"ZergMeleeWeaponsLevel3";"EvolutionChamber";358;0
"Building";"CreepTumor";NA;484;0
"Building";"CreepTumor";NA;484;0
"Building";"CreepTumor";NA;484;0
"Building";"CreepTumor";NA;484;0
"Upgrade";"ZergGroundArmorsLevel3";"EvolutionChamber";358;0
"Building";"SpineCrawler";NA;430;0
"Unit";"Baneling";"Zergling";484;0
"Unit";"Baneling";"Zergling";484;0
"Unit";"Baneling";"Zergling";484;0
"Unit";"Baneling";"Zergling";484;0
"Unit";"Baneling";"Zergling";484;0
"Unit";"Baneling";"Zergling";484;0
"Unit";"Baneling";"Zergling";484;0
"Unit";"Baneling";"Zergling";484;0
"Unit";"Baneling";"Zergling";484;0
"Unit";"Baneling";"Zergling";484;0
"Unit";"Baneling";"Zergling";484;0
"Unit";"Baneling";"Zergling";484;0
"Unit";"Baneling";"Zergling";484;0
"Unit";"Baneling";"Zergling";484;0
"Unit";"Baneling";"Zergling";484;0
"Unit";"Baneling";"Zergling";484;0
"Unit";"Baneling";"Zergling";484;0
"Unit";"Baneling";"Zergling";484;0
"Unit";"Zergling";"Larva";484;1
"Unit";"Zergling";"Larva";484;1
"Unit";"Zergling";"Larva";484;1
"Unit";"Zergling";"Larva";484;1
"Unit";"Zergling";"Larva";484;1
"Unit";"Zergling";"Larva";484;1
"Unit";"Zergling";"Larva";484;1
"Unit";"Zergling";"Larva";484;1
"Unit";"Zergling";"Larva";484;1
"Unit";"Zergling";"Larva";484;1
"Unit";"Zergling";"Larva";484;1
"Unit";"Zergling";"Larva";484;1
"Unit";"Zergling";"Larva";484;1
"Unit";"Zergling";"Larva";484;1
"Unit";"Zergling";"Larva";484;1
"Unit";"Zergling";"Larva";484;1
"Unit";"Zergling";"Larva";484;1
"Unit";"Zergling";"Larva";484;1
"Unit";"Zergling";"Larva";484;1
"Unit";"Zergling";"Larva";484;1
"Unit";"Zergling";"Larva";484;1
"Unit";"Zergling";"Larva";484;1
"Unit";"Zergling";"Larva";484;1
"Unit";"Zergling";"Larva";484;1
"Unit";"Zergling";"Larva";484;1
"Unit";"Zergling";"Larva";484;1
"Unit";"Zergling";"Larva";484;1
"Unit";"Zergling";"Larva";484;1
"Unit";"Zergling";"Larva";484;1
"Unit";"Zergling";"Larva";484;1
"Unit";"Zergling";"Larva";484;1
"Unit";"Zergling";"Larva";484;1
"Unit";"Zergling";"Larva";484;1
"Unit";"Zergling";"Larva";484;1
"Unit";"Zergling";"Larva";484;1
"Unit";"Zergling";"Larva";484;1
"Unit";"Zergling";"Larva";484;1
"Unit";"Zergling";"Larva";484;1
"Unit";"Zergling";"Larva";484;1
"Unit";"Zergling";"Larva";484;1
"Unit";"Zergling";"Larva";484;1
"Unit";"Zergling";"Larva";484;1
"Unit";"Zergling";"Larva";484;1
"Unit";"Zergling";"Larva";484;1
"Unit";"Zergling";"Larva";484;1
"Unit";"Zergling";"Larva";484;1
"Unit";"Zergling";"Larva";484;1
"Unit";"Zergling";"Larva";484;1
"Unit";"Zergling";"Larva";484;1
"Unit";"Zergling";"Larva";484;1
"Unit";"Zergling";"Larva";484;1
"Unit";"Zergling";"Larva";484;1
"Unit";"Zergling";"Larva";484;1
"Unit";"Zergling";"Larva";484;1
"Unit";"Zergling";"Larva";484;1
"Unit";"Zergling";"Larva";484;1
"Unit";"Zergling";"Larva";484;1
"Unit";"Zergling";"Larva";484;1
"Unit";"Zergling";"Larva";484;1
"Unit";"Zergling";"Larva";484;1
"Unit";"Zergling";"Larva";484;1
"Unit";"Zergling";"Larva";484;1
"Unit";"Zergling";"Larva";484;1
"Unit";"Zergling";"Larva";484;1
"Unit";"Zergling";"Larva";484;1
"Unit";"Zergling";"Larva";484;1
"Unit";"Zergling";"Larva";484;1
"Unit";"Zergling";"Larva";484;1
"Unit";"Zergling";"Larva";484;1
"Unit";"Zergling";"Larva";484;1
"Unit";"Zergling";"Larva";484;1
"Unit";"Zergling";"Larva";484;1
"Unit";"Zergling";"Larva";484;1
"Unit";"Zergling";"Larva";484;1
"Unit";"Zergling";"Larva";484;1
"Unit";"Zergling";"Larva";484;1
"Building";"CreepTumor";NA;560;0
"Building";"CreepTumor";NA;560;0
"Building";"SporeCrawler";NA;560;0
"Building";"CreepTumor";NA;560;0
"Building";"CreepTumorQueen";NA;560;0
"Building";"SpineCrawler";NA;560;0
"Building";"CreepTumorQueen";NA;560;0
"Unit";"Baneling";"Zergling";560;0
"Unit";"Baneling";"Zergling";560;0
"Unit";"Baneling";"Zergling";560;0
"Unit";"Baneling";"Zergling";560;0
"Unit";"Baneling";"Zergling";560;0
"Unit";"Baneling";"Zergling";560;0
"Unit";"Baneling";"Zergling";560;0
"Unit";"Baneling";"Zergling";560;0
"Unit";"Baneling";"Zergling";560;0
"Unit";"Baneling";"Zergling";560;0
"Unit";"Baneling";"Zergling";560;0
"Unit";"Baneling";"Zergling";560;0
"Unit";"Baneling";"Zergling";560;0
"Unit";"Baneling";"Zergling";560;0
"Unit";"Baneling";"Zergling";560;0
"Unit";"Baneling";"Zergling";560;0
"Unit";"Baneling";"Zergling";560;0
"Unit";"Baneling";"Zergling";560;0
"Unit";"Baneling";"Zergling";560;0
"Unit";"Baneling";"Zergling";560;0
"Unit";"Baneling";"Zergling";560;0
"Unit";"Baneling";"Zergling";560;0
"Unit";"Baneling";"Zergling";560;0
"Unit";"Baneling";"Zergling";560;0
"Unit";"Baneling";"Zergling";560;0
"Unit";"Baneling";"Zergling";560;0
"Unit";"Baneling";"Zergling";560;0
"Unit";"Baneling";"Zergling";560;0
"Unit";"Baneling";"Zergling";560;0
"Unit";"Baneling";"Zergling";560;0
"Unit";"Baneling";"Zergling";560;0
"Unit";"Baneling";"Zergling";560;0
"Unit";"Baneling";"Zergling";560;0
"Building";"CreepTumorQueen";NA;560;0
"Unit";"Baneling";"Zergling";560;0
"Unit";"Baneling";"Zergling";560;0
"Unit";"Baneling";"Zergling";560;0
"Unit";"Baneling";"Zergling";560;0
"Unit";"Baneling";"Zergling";560;0
"Unit";"Baneling";"Zergling";560;0
"Unit";"Baneling";"Zergling";560;0
"Unit";"Baneling";"Zergling";560;0
"Unit";"Baneling";"Zergling";560;0
"Unit";"Baneling";"Zergling";560;0
"Unit";"Baneling";"Zergling";560;0
"Unit";"Baneling";"Zergling";560;0
"Unit";"Baneling";"Zergling";560;0
"Unit";"Baneling";"Zergling";560;0
"Unit";"Baneling";"Zergling";560;0
"Unit";"Baneling";"Zergling";560;0
"Unit";"Baneling";"Zergling";560;0
"Unit";"Baneling";"Zergling";560;0
"Unit";"Baneling";"Zergling";560;0
"Unit";"Baneling";"Zergling";560;0
"Unit";"Baneling";"Zergling";560;0
"Unit";"Baneling";"Zergling";560;0
"Unit";"Baneling";"Zergling";560;0
"Unit";"Baneling";"Zergling";560;0
"Building";"CreepTumorQueen";NA;560;0
"Unit";"Baneling";"Zergling";560;0
"Unit";"Baneling";"Zergling";560;0
"Unit";"Baneling";"Zergling";560;0
"Unit";"Baneling";"Zergling";560;0
"Unit";"Baneling";"Zergling";560;0
"Unit";"Baneling";"Zergling";560;0
"Unit";"Baneling";"Zergling";560;0
"Unit";"Baneling";"Zergling";560;0
"Unit";"Baneling";"Zergling";560;0
"Unit";"Baneling";"Zergling";560;0
"Unit";"Baneling";"Zergling";560;0
"Unit";"Baneling";"Zergling";560;0
"Unit";"Baneling";"Zergling";560;0
"Unit";"Baneling";"Zergling";560;0
"Unit";"Baneling";"Zergling";560;0
"Unit";"Baneling";"Zergling";560;0
"Unit";"Baneling";"Zergling";560;0
"Unit";"Baneling";"Zergling";560;0
"Unit";"Baneling";"Zergling";560;0
"Unit";"Baneling";"Zergling";560;0
"Unit";"Baneling";"Zergling";560;0
"Unit";"Baneling";"Zergling";560;0
"Unit";"Baneling";"Zergling";560;0
"Unit";"Baneling";"Zergling";560;0
"Unit";"Baneling";"Zergling";560;0
"Unit";"Baneling";"Zergling";560;0
"Unit";"Baneling";"Zergling";560;0
"Unit";"Baneling";"Zergling";560;0
"Unit";"Baneling";"Zergling";560;0
"Unit";"Baneling";"Zergling";560;0
"Building";"CreepTumor";NA;560;0
"Building";"CreepTumor";NA;560;0
"Building";"CreepTumor";NA;560;0
"Building";"CreepTumor";NA;560;0
"Building";"CreepTumor";NA;560;0
"Building";"CreepTumor";NA;560;0
"Building";"SpineCrawler";NA;560;0
"Unit";"Overlord";"Larva";560;0
"Building";"SpineCrawler";NA;560;0
"Building";"Hatchery";NA;560;0
"Unit";"Overlord";"Larva";560;0
"Upgrade";"NeuralParasite";"InfestationPit";560;0
"Building";"Extractor";NA;560;0
"Building";"Extractor";NA;560;0
"Building";"Hatchery";NA;560;0
"Unit";"Corruptor";"Larva";560;2
"Unit";"Corruptor";"Larva";560;2
"Unit";"Corruptor";"Larva";560;2
"Unit";"Corruptor";"Larva";560;2
"Unit";"Corruptor";"Larva";560;2
"Unit";"Corruptor";"Larva";560;2
"Unit";"Corruptor";"Larva";560;2
"Unit";"Corruptor";"Larva";560;2
"Unit";"Corruptor";"Larva";560;2
"Upgrade";"ZergMissileWeaponsLevel1";"EvolutionChamber";560;0
"Unit";"Queen";"Hatchery";560;2
"Unit";"Corruptor";"Larva";560;2
"Unit";"Corruptor";"Larva";560;2
"Unit";"Corruptor";"Larva";560;2
"Unit";"Corruptor";"Larva";560;2
"Building";"CreepTumor";NA;578;0
"Building";"CreepTumor";NA;578;0
"Building";"CreepTumor";NA;578;0
