"type";"unit_name";"on_building";"total_supply";"supply"
"Unit";"Overlord";"Larva";12;0
"Building";"SpawningPool";NA;19;0
"Building";"Hatchery";NA;17;0
"Unit";"Overlord";"Larva";24;0
"Unit";"Zergling";"Larva";25;1
"Unit";"Zergling";"Larva";25;1
"Unit";"Zergling";"Larva";25;1
"Unit";"Zergling";"Larva";25;1
"Unit";"Queen";"Hatchery";24;2
"Unit";"Queen";"Hatchery";25;2
"Building";"Hatchery";NA;22;0
"Unit";"Overlord";"Larva";33;0
"Unit";"Overlord";"Larva";33;0
"Unit";"Overlord";"Larva";38;0
"Unit";"Queen";"Hatchery";35;2
"Building";"CreepTumorQueen";NA;42;0
"Building";"CreepTumor";NA;51;0
"Unit";"Queen";"Hatchery";44;2
"Unit";"Overlord";"Larva";51;0
"Building";"CreepTumorQueen";NA;51;0
"Unit";"Queen";"Hatchery";49;2
"Unit";"Zergling";"Larva";51;1
"Unit";"Zergling";"Larva";51;1
"Building";"Extractor";NA;51;0
"Building";"Extractor";NA;51;0
"Building";"CreepTumorQueen";NA;60;0
"Unit";"Overlord";"Larva";57;0
"Unit";"Queen";"Hatchery";51;2
"Building";"CreepTumor";NA;67;0
"Building";"CreepTumorQueen";NA;67;0
"Unit";"Overlord";"Larva";65;0
"Unit";"Queen";"Hatchery";60;2
"Building";"CreepTumorQueen";NA;67;0
"Building";"CreepTumor";NA;67;0
"Building";"CreepTumorQueen";NA;67;0
"Building";"CreepTumor";NA;67;0
"Building";"Extractor";NA;67;0
"Building";"Extractor";NA;67;0
"Unit";"Queen";"Hatchery";65;2
"Unit";"Overlord";"Larva";73;0
"Unit";"Overlord";"Larva";73;0
"Building";"CreepTumor";NA;80;0
"Building";"CreepTumor";NA;80;0
"Building";"CreepTumor";NA;80;0
"Unit";"Queen";"Hatchery";67;2
"Unit";"Zergling";"Larva";80;1
"Unit";"Zergling";"Larva";80;1
"Unit";"Zergling";"Larva";80;1
"Unit";"Zergling";"Larva";80;1
"Unit";"Zergling";"Larva";80;1
"Unit";"Zergling";"Larva";80;1
"Unit";"Zergling";"Larva";80;1
"Unit";"Zergling";"Larva";80;1
"Unit";"Overlord";"Larva";80;0
"Unit";"Queen";"Hatchery";80;2
"Building";"CreepTumor";NA;98;0
"Building";"CreepTumor";NA;98;0
"Unit";"Overlord";"Larva";98;0
"Unit";"Overlord";"Larva";98;0
"Unit";"Overlord";"Larva";98;0
"Building";"CreepTumorQueen";NA;104;0
"Building";"CreepTumorQueen";NA;104;0
"Building";"CreepTumorQueen";NA;109;0
"Building";"Extractor";NA;100;0
"Building";"Extractor";NA;100;0
"Building";"CreepTumorQueen";NA;109;0
"Building";"CreepTumorQueen";NA;112;0
"Building";"CreepTumor";NA;112;0
"Unit";"Zergling";"Larva";112;1
"Unit";"Zergling";"Larva";112;1
"Unit";"Zergling";"Larva";112;1
"Unit";"Zergling";"Larva";112;1
"Unit";"Zergling";"Larva";112;1
"Unit";"Zergling";"Larva";112;1
"Unit";"Queen";"Hatchery";100;2
"Building";"CreepTumor";NA;112;0
"Building";"CreepTumor";NA;112;0
"Building";"CreepTumorQueen";NA;118;0
"Building";"CreepTumorQueen";NA;118;0
"Building";"CreepTumor";NA;118;0
"Building";"CreepTumor";NA;118;0
"Unit";"Zergling";"Larva";118;1
"Unit";"Zergling";"Larva";118;1
"Unit";"Zergling";"Larva";118;1
"Unit";"Zergling";"Larva";118;1
"Unit";"Zergling";"Larva";118;1
"Unit";"Zergling";"Larva";118;1
"Unit";"Zergling";"Larva";118;1
"Unit";"Zergling";"Larva";118;1
"Unit";"Zergling";"Larva";118;1
"Unit";"Zergling";"Larva";118;1
"Unit";"Zergling";"Larva";118;1
"Unit";"Zergling";"Larva";118;1
"Unit";"Zergling";"Larva";118;1
"Unit";"Zergling";"Larva";118;1
"Unit";"Zergling";"Larva";118;1
"Unit";"Zergling";"Larva";118;1
"Unit";"Zergling";"Larva";118;1
"Unit";"Zergling";"Larva";118;1
"Unit";"Zergling";"Larva";118;1
"Unit";"Zergling";"Larva";118;1
"Building";"CreepTumor";NA;120;0
"Building";"HydraliskDen";NA;118;0
"Building";"SporeCrawler";NA;120;0
"Building";"CreepTumor";NA;140;0
"Building";"CreepTumor";NA;140;0
"Building";"CreepTumor";NA;140;0
"Building";"CreepTumor";NA;140;0
"Building";"CreepTumor";NA;140;0
"Building";"CreepTumor";NA;140;0
"Building";"CreepTumor";NA;140;0
"Building";"CreepTumor";NA;140;0
"Building";"EvolutionChamber";NA;120;0
"Building";"InfestationPit";NA;120;0
"Building";"EvolutionChamber";NA;140;0
"Unit";"Overlord";"Larva";144;0
"Unit";"Overlord";"Larva";144;0
"Unit";"Overlord";"Larva";144;0
"Unit";"Overlord";"Larva";144;0
"Unit";"Overlord";"Larva";144;0
"Unit";"Overlord";"Larva";144;0
"Building";"CreepTumor";NA;147;0
"Building";"CreepTumor";NA;147;0
"Building";"CreepTumor";NA;147;0
"Building";"CreepTumor";NA;147;0
"Unit";"Zergling";"Larva";147;1
"Unit";"Zergling";"Larva";147;1
"Unit";"Zergling";"Larva";147;1
"Unit";"Zergling";"Larva";147;1
"Unit";"Zergling";"Larva";147;1
"Unit";"Zergling";"Larva";147;1
"Unit";"Zergling";"Larva";147;1
"Unit";"Zergling";"Larva";147;1
"Unit";"Zergling";"Larva";147;1
"Unit";"Zergling";"Larva";147;1
"Unit";"Zergling";"Larva";147;1
"Unit";"Zergling";"Larva";147;1
"Unit";"Zergling";"Larva";147;1
"Unit";"Zergling";"Larva";147;1
"Unit";"Zergling";"Larva";147;1
"Unit";"Zergling";"Larva";147;1
"Unit";"Zergling";"Larva";147;1
"Unit";"Zergling";"Larva";147;1
"Unit";"Zergling";"Larva";147;1
"Unit";"Zergling";"Larva";147;1
"Unit";"Zergling";"Larva";147;1
"Unit";"Zergling";"Larva";147;1
"Unit";"Zergling";"Larva";147;1
"Unit";"Zergling";"Larva";147;1
"Unit";"Zergling";"Larva";147;1
"Unit";"Zergling";"Larva";147;1
"Unit";"Zergling";"Larva";147;1
"Unit";"Zergling";"Larva";147;1
"Unit";"Zergling";"Larva";147;1
"Unit";"Zergling";"Larva";147;1
"Building";"Hatchery";NA;120;0
"Building";"CreepTumor";NA;147;0
"Unit";"Hydralisk";"Larva";147;2
"Unit";"Hydralisk";"Larva";147;2
"Unit";"Hydralisk";"Larva";147;2
"Building";"CreepTumor";NA;177;0
"Building";"CreepTumor";NA;177;0
"Building";"CreepTumor";NA;177;0
"Upgrade";"EvolveGroovedSpines";"HydraliskDen";147;0
"Building";"SporeCrawler";NA;177;0
"Building";"CreepTumor";NA;177;0
"Building";"BanelingNest";NA;147;0
"Building";"CreepTumor";NA;183;0
"Unit";"Hydralisk";"Larva";177;2
"Unit";"Hydralisk";"Larva";177;2
"Unit";"Hydralisk";"Larva";177;2
"Unit";"Hydralisk";"Larva";177;2
"Unit";"Hydralisk";"Larva";177;2
"Unit";"Hydralisk";"Larva";177;2
"Unit";"Hydralisk";"Larva";177;2
"Unit";"Overlord";"Larva";183;0
"Unit";"Hydralisk";"Larva";183;2
"Unit";"Hydralisk";"Larva";183;2
"Unit";"Hydralisk";"Larva";183;2
"Unit";"Hydralisk";"Larva";183;2
"Unit";"Hydralisk";"Larva";183;2
"Unit";"Queen";"Hatchery";177;2
"Unit";"Baneling";"Zergling";197;0
"Unit";"Baneling";"Zergling";197;0
"Unit";"Baneling";"Zergling";197;0
"Unit";"Baneling";"Zergling";197;0
"Unit";"Baneling";"Zergling";197;0
"Unit";"Baneling";"Zergling";197;0
"Building";"CreepTumor";NA;207;0
"Unit";"Hydralisk";"Larva";197;2
"Unit";"Hydralisk";"Larva";197;2
"Unit";"Hydralisk";"Larva";197;2
"Unit";"Hydralisk";"Larva";197;2
"Unit";"Hydralisk";"Larva";197;2
"Building";"CreepTumor";NA;207;0
"Building";"CreepTumor";NA;207;0
"Building";"CreepTumor";NA;207;0
"Building";"CreepTumorQueen";NA;209;0
"Building";"CreepTumorQueen";NA;209;0
"Building";"CreepTumorQueen";NA;209;0
"Unit";"Zergling";"Larva";209;1
"Unit";"Zergling";"Larva";209;1
"Building";"Hatchery";NA;177;0
"Unit";"Zergling";"Larva";209;1
"Unit";"Zergling";"Larva";209;1
"Unit";"Zergling";"Larva";209;1
"Unit";"Zergling";"Larva";209;1
"Unit";"Zergling";"Larva";209;1
"Unit";"Zergling";"Larva";209;1
"Unit";"Zergling";"Larva";209;1
"Unit";"Zergling";"Larva";209;1
"Unit";"Zergling";"Larva";209;1
"Unit";"Zergling";"Larva";209;1
"Unit";"Zergling";"Larva";209;1
"Unit";"Zergling";"Larva";209;1
"Unit";"Zergling";"Larva";209;1
"Unit";"Zergling";"Larva";209;1
"Unit";"Zergling";"Larva";209;1
"Unit";"Zergling";"Larva";209;1
"Building";"CreepTumorQueen";NA;219;0
"Building";"CreepTumorQueen";NA;219;0
"Building";"CreepTumorQueen";NA;219;0
"Building";"CreepTumorQueen";NA;219;0
"Building";"SporeCrawler";NA;219;0
"Unit";"Overlord";"Larva";219;0
"Building";"CreepTumorQueen";NA;238;0
"Upgrade";"ZergGroundArmorsLevel1";"EvolutionChamber";177;0
"Building";"CreepTumorQueen";NA;238;0
"Upgrade";"ZergMeleeWeaponsLevel1";"EvolutionChamber";177;0
"Building";"CreepTumor";NA;238;0
"Building";"CreepTumor";NA;238;0
"Building";"CreepTumor";NA;238;0
"Building";"CreepTumor";NA;238;0
"Upgrade";"EvolveMuscularAugments";"HydraliskDen";197;0
"Building";"CreepTumorQueen";NA;238;0
"Building";"CreepTumorQueen";NA;238;0
"Building";"CreepTumor";NA;238;0
"Building";"CreepTumor";NA;238;0
"Building";"CreepTumor";NA;238;0
"Building";"CreepTumor";NA;238;0
"Building";"UltraliskCavern";NA;209;0
"Building";"SporeCrawler";NA;238;0
"Unit";"Zergling";"Larva";238;1
"Unit";"Zergling";"Larva";238;1
"Unit";"Zergling";"Larva";238;1
"Unit";"Zergling";"Larva";238;1
"Unit";"Zergling";"Larva";238;1
"Unit";"Zergling";"Larva";238;1
"Unit";"Zergling";"Larva";238;1
"Unit";"Zergling";"Larva";238;1
"Unit";"Zergling";"Larva";238;1
"Unit";"Zergling";"Larva";238;1
"Unit";"Zergling";"Larva";238;1
"Unit";"Zergling";"Larva";238;1
"Unit";"Zergling";"Larva";238;1
"Unit";"Zergling";"Larva";238;1
"Unit";"Zergling";"Larva";238;1
"Unit";"Zergling";"Larva";238;1
"Unit";"Zergling";"Larva";238;1
"Unit";"Zergling";"Larva";238;1
"Unit";"Zergling";"Larva";238;1
"Unit";"Zergling";"Larva";238;1
"Unit";"Zergling";"Larva";238;1
"Unit";"Zergling";"Larva";238;1
"Unit";"Zergling";"Larva";238;1
"Unit";"Zergling";"Larva";238;1
"Unit";"Zergling";"Larva";238;1
"Unit";"Zergling";"Larva";238;1
"Unit";"Zergling";"Larva";238;1
"Unit";"Zergling";"Larva";238;1
"Unit";"Zergling";"Larva";238;1
"Unit";"Zergling";"Larva";238;1
"Unit";"Zergling";"Larva";238;1
"Unit";"Zergling";"Larva";238;1
"Unit";"Zergling";"Larva";238;1
"Unit";"Zergling";"Larva";238;1
"Unit";"Queen";"Hatchery";238;2
"Unit";"Baneling";"Zergling";239;0
"Unit";"Baneling";"Zergling";239;0
"Unit";"Baneling";"Zergling";239;0
"Unit";"Baneling";"Zergling";239;0
"Building";"CreepTumor";NA;275;0
"Building";"CreepTumor";NA;275;0
"Building";"CreepTumorQueen";NA;275;0
"Building";"CreepTumorQueen";NA;275;0
"Building";"SporeCrawler";NA;275;0
"Building";"Spire";NA;238;0
"Building";"CreepTumorQueen";NA;275;0
"Building";"CreepTumorQueen";NA;275;0
"Building";"CreepTumorQueen";NA;275;0
"Unit";"Overlord";"Larva";275;0
"Unit";"Ultralisk";"Larva";275;6
"Unit";"Ultralisk";"Larva";275;6
"Unit";"Corruptor";"Larva";275;2
"Unit";"Corruptor";"Larva";275;2
"Unit";"Corruptor";"Larva";275;2
"Unit";"Overlord";"Larva";275;0
"Unit";"Overlord";"Larva";275;0
"Unit";"Overlord";"Larva";275;0
"Unit";"Baneling";"Zergling";275;0
"Building";"CreepTumorQueen";NA;275;0
"Unit";"Baneling";"Zergling";275;0
"Unit";"Baneling";"Zergling";275;0
"Unit";"Baneling";"Zergling";275;0
"Unit";"Baneling";"Zergling";275;0
"Unit";"Baneling";"Zergling";275;0
"Unit";"Baneling";"Zergling";275;0
"Unit";"Baneling";"Zergling";275;0
"Unit";"Baneling";"Zergling";275;0
"Unit";"Baneling";"Zergling";275;0
"Unit";"Baneling";"Zergling";275;0
"Unit";"Baneling";"Zergling";275;0
"Unit";"Baneling";"Zergling";275;0
"Unit";"Baneling";"Zergling";275;0
"Unit";"Baneling";"Zergling";275;0
"Unit";"Baneling";"Zergling";275;0
"Building";"CreepTumorQueen";NA;287;0
"Building";"CreepTumorQueen";NA;287;0
"Upgrade";"ChitinousPlating";"UltraliskCavern";275;0
"Unit";"Ultralisk";"Larva";293;6
"Building";"CreepTumor";NA;293;0
"Building";"CreepTumor";NA;293;0
"Building";"CreepTumor";NA;293;0
"Building";"CreepTumor";NA;293;0
"Building";"CreepTumorQueen";NA;299;0
"Unit";"Ultralisk";"Larva";293;6
"Unit";"Ultralisk";"Larva";293;6
"Building";"CreepTumorQueen";NA;299;0
"Building";"CreepTumorQueen";NA;299;0
"Building";"CreepTumorQueen";NA;299;0
"Building";"CreepTumorQueen";NA;299;0
"Building";"CreepTumor";NA;311;0
"Building";"CreepTumor";NA;311;0
"Building";"CreepTumor";NA;311;0
"Building";"CreepTumor";NA;311;0
"Building";"CreepTumor";NA;311;0
"Building";"CreepTumor";NA;311;0
"Unit";"Corruptor";"Larva";299;2
"Building";"CreepTumor";NA;311;0
"Unit";"Corruptor";"Larva";299;2
"Building";"CreepTumor";NA;311;0
"Building";"CreepTumor";NA;315;0
"Building";"CreepTumor";NA;315;0
"Building";"Hatchery";NA;293;0
"Building";"Hatchery";NA;293;0
"Unit";"Overlord";"Larva";315;0
"Building";"CreepTumorQueen";NA;315;0
"Building";"CreepTumorQueen";NA;315;0
"Building";"CreepTumor";NA;315;0
"Building";"CreepTumor";NA;315;0
"Building";"CreepTumor";NA;315;0
"Building";"CreepTumor";NA;315;0
"Building";"CreepTumor";NA;315;0
"Building";"EvolutionChamber";NA;315;0
"Building";"CreepTumor";NA;315;0
"Building";"CreepTumor";NA;315;0
"Building";"CreepTumor";NA;315;0
"Building";"EvolutionChamber";NA;315;0
"Building";"CreepTumorQueen";NA;315;0
"Unit";"Corruptor";"Larva";315;2
"Unit";"Corruptor";"Larva";315;2
"Building";"CreepTumorQueen";NA;319;0
"Building";"CreepTumorQueen";NA;319;0
"Building";"CreepTumorQueen";NA;319;0
"Building";"CreepTumor";NA;319;0
"Building";"CreepTumorQueen";NA;326;0
"Unit";"Overlord";"Larva";324;0
"Building";"CreepTumor";NA;328;0
"Building";"CreepTumor";NA;328;0
"Building";"CreepTumor";NA;328;0
"Building";"CreepTumor";NA;328;0
"Building";"CreepTumor";NA;342;0
"Building";"CreepTumor";NA;342;0
"Building";"CreepTumor";NA;342;0
"Building";"CreepTumor";NA;342;0
"Building";"CreepTumor";NA;342;0
"Building";"CreepTumor";NA;342;0
"Building";"CreepTumor";NA;342;0
"Building";"CreepTumor";NA;342;0
"Building";"CreepTumor";NA;342;0
"Building";"CreepTumor";NA;350;0
"Building";"CreepTumor";NA;350;0
"Building";"CreepTumor";NA;350;0
"Building";"CreepTumor";NA;350;0
"Building";"CreepTumor";NA;350;0
"Building";"CreepTumorQueen";NA;350;0
"Building";"CreepTumor";NA;350;0
"Building";"CreepTumor";NA;350;0
"Building";"CreepTumor";NA;350;0
"Building";"CreepTumor";NA;350;0
"Building";"Extractor";NA;350;0
"Building";"Extractor";NA;350;0
"Building";"CreepTumor";NA;350;0
"Building";"CreepTumor";NA;350;0
"Building";"CreepTumor";NA;350;0
"Building";"CreepTumor";NA;350;0
"Building";"CreepTumor";NA;350;0
"Building";"CreepTumor";NA;350;0
"Building";"CreepTumor";NA;350;0
"Building";"CreepTumor";NA;350;0
"Building";"CreepTumor";NA;350;0
"Building";"CreepTumor";NA;350;0
"Building";"CreepTumorQueen";NA;350;0
"Building";"CreepTumorQueen";NA;360;0
"Building";"SporeCrawler";NA;350;0
"Building";"CreepTumorQueen";NA;360;0
"Building";"SporeCrawler";NA;350;0
"Building";"CreepTumor";NA;360;0
"Building";"CreepTumor";NA;364;0
"Building";"CreepTumor";NA;364;0
"Building";"CreepTumor";NA;364;0
"Building";"CreepTumor";NA;364;0
"Building";"CreepTumor";NA;364;0
"Building";"CreepTumor";NA;364;0
"Upgrade";"ZergGroundArmorsLevel2";"EvolutionChamber";350;0
"Building";"CreepTumor";NA;364;0
"Building";"CreepTumor";NA;364;0
"Upgrade";"ZergMeleeWeaponsLevel2";"EvolutionChamber";350;0
"Building";"CreepTumor";NA;364;0
"Building";"CreepTumor";NA;364;0
"Building";"SporeCrawler";NA;364;0
"Building";"CreepTumor";NA;364;0
"Building";"Hatchery";NA;350;0
"Building";"CreepTumor";NA;364;0
"Building";"CreepTumor";NA;364;0
"Building";"CreepTumor";NA;364;0
"Building";"CreepTumor";NA;364;0
"Building";"CreepTumor";NA;364;0
"Building";"CreepTumor";NA;364;0
"Building";"Extractor";NA;364;0
"Building";"Extractor";NA;364;0
"Building";"CreepTumor";NA;379;0
"Building";"CreepTumor";NA;379;0
"Building";"SporeCrawler";NA;368;0
"Building";"CreepTumor";NA;379;0
"Building";"CreepTumor";NA;379;0
"Building";"CreepTumor";NA;379;0
"Building";"CreepTumorQueen";NA;379;0
"Building";"CreepTumorQueen";NA;379;0
"Building";"CreepTumor";NA;379;0
"Building";"CreepTumor";NA;379;0
"Building";"SporeCrawler";NA;379;0
"Building";"CreepTumor";NA;379;0
"Building";"CreepTumor";NA;379;0
"Building";"CreepTumor";NA;379;0
"Building";"CreepTumor";NA;379;0
"Building";"CreepTumor";NA;379;0
"Building";"CreepTumor";NA;379;0
"Building";"CreepTumor";NA;379;0
"Building";"CreepTumor";NA;379;0
"Building";"CreepTumor";NA;379;0
"Building";"CreepTumor";NA;379;0
"Building";"CreepTumor";NA;379;0
"Building";"CreepTumor";NA;379;0
"Building";"CreepTumor";NA;386;0
"Building";"CreepTumor";NA;386;0
"Building";"CreepTumor";NA;386;0
"Building";"SporeCrawler";NA;386;0
"Building";"CreepTumorQueen";NA;386;0
"Building";"CreepTumorQueen";NA;386;0
"Building";"SporeCrawler";NA;386;0
"Building";"SporeCrawler";NA;386;0
"Building";"SporeCrawler";NA;386;0
"Building";"SporeCrawler";NA;386;0
"Building";"SporeCrawler";NA;386;0
"Building";"CreepTumorQueen";NA;386;0
"Building";"CreepTumorQueen";NA;386;0
"Building";"CreepTumorQueen";NA;386;0
"Building";"CreepTumor";NA;386;0
"Building";"CreepTumor";NA;386;0
"Building";"SporeCrawler";NA;386;0
"Building";"SporeCrawler";NA;386;0
"Building";"SporeCrawler";NA;386;0
"Building";"CreepTumorQueen";NA;386;0
"Building";"CreepTumorQueen";NA;386;0
"Building";"CreepTumorQueen";NA;386;0
"Building";"CreepTumorQueen";NA;386;0
"Building";"CreepTumor";NA;395;0
"Building";"CreepTumor";NA;395;0
"Building";"CreepTumor";NA;395;0
"Building";"CreepTumor";NA;395;0
"Building";"CreepTumor";NA;395;0
"Building";"CreepTumorQueen";NA;395;0
"Building";"CreepTumorQueen";NA;395;0
"Building";"CreepTumorQueen";NA;395;0
"Building";"CreepTumorQueen";NA;395;0
"Building";"CreepTumorQueen";NA;395;0
"Building";"CreepTumorQueen";NA;395;0
"Building";"CreepTumorQueen";NA;395;0
"Upgrade";"ZergMeleeWeaponsLevel3";"EvolutionChamber";379;0
"Upgrade";"ZergGroundArmorsLevel3";"EvolutionChamber";379;0
"Building";"CreepTumorQueen";NA;395;0
"Building";"CreepTumorQueen";NA;395;0
"Building";"SporeCrawler";NA;395;0
"Building";"CreepTumorQueen";NA;395;0
"Building";"CreepTumorQueen";NA;395;0
"Building";"SporeCrawler";NA;395;0
"Building";"SporeCrawler";NA;395;0
"Building";"CreepTumorQueen";NA;395;0
"Building";"SporeCrawler";NA;395;0
"Building";"SporeCrawler";NA;395;0
"Building";"CreepTumor";NA;395;0
"Building";"CreepTumor";NA;395;0
"Building";"CreepTumor";NA;395;0
"Building";"CreepTumor";NA;395;0
"Building";"CreepTumor";NA;395;0
"Building";"CreepTumor";NA;395;0
"Building";"CreepTumor";NA;395;0
"Building";"CreepTumor";NA;395;0
"Building";"CreepTumor";NA;395;0
"Building";"CreepTumor";NA;395;0
"Building";"CreepTumor";NA;395;0
"Building";"CreepTumor";NA;395;0
"Building";"SporeCrawler";NA;395;0
"Building";"SporeCrawler";NA;395;0
"Building";"SporeCrawler";NA;395;0
"Building";"SporeCrawler";NA;395;0
"Building";"SporeCrawler";NA;395;0
"Building";"SporeCrawler";NA;395;0
"Building";"SporeCrawler";NA;395;0
"Building";"SporeCrawler";NA;395;0
"Building";"CreepTumor";NA;395;0
"Building";"CreepTumor";NA;395;0
"Building";"CreepTumor";NA;395;0
"Building";"SporeCrawler";NA;395;0
"Building";"SporeCrawler";NA;395;0
"Building";"SporeCrawler";NA;395;0
"Building";"SporeCrawler";NA;395;0
"Building";"Extractor";NA;395;0
"Building";"SpineCrawler";NA;395;0
"Building";"SpineCrawler";NA;395;0
"Building";"CreepTumor";NA;395;0
"Building";"CreepTumor";NA;395;0
"Building";"CreepTumor";NA;395;0
"Building";"CreepTumor";NA;395;0
"Building";"CreepTumor";NA;395;0
"Building";"CreepTumor";NA;395;0
"Building";"CreepTumor";NA;395;0
"Building";"CreepTumor";NA;395;0
"Building";"CreepTumor";NA;395;0
"Building";"CreepTumor";NA;395;0
"Building";"CreepTumor";NA;395;0
"Building";"CreepTumor";NA;395;0
"Building";"CreepTumor";NA;395;0
"Building";"CreepTumor";NA;395;0
"Building";"Hatchery";NA;395;0
"Unit";"Viper";"Larva";395;3
"Building";"CreepTumorQueen";NA;395;0
"Unit";"Viper";"Larva";395;3
"Unit";"Viper";"Larva";395;3
"Unit";"Viper";"Larva";395;3
"Unit";"Viper";"Larva";395;3
"Unit";"Viper";"Larva";395;3
"Unit";"Viper";"Larva";395;3
"Building";"CreepTumorQueen";NA;395;0
"Building";"CreepTumor";NA;395;0
"Building";"CreepTumor";NA;395;0
"Building";"CreepTumor";NA;395;0
"Building";"CreepTumor";NA;395;0
"Building";"CreepTumor";NA;416;0
"Upgrade";"ZergMissileWeaponsLevel1";"EvolutionChamber";395;0
"Building";"CreepTumor";NA;416;0
"Building";"SporeCrawler";NA;416;0
"Building";"SporeCrawler";NA;416;0
"Unit";"Corruptor";"Larva";416;2
"Unit";"Corruptor";"Larva";416;2
"Unit";"Corruptor";"Larva";416;2
"Unit";"Corruptor";"Larva";416;2
"Building";"CreepTumor";NA;416;0
"Building";"CreepTumor";NA;416;0
"Unit";"Corruptor";"Larva";416;2
"Unit";"Corruptor";"Larva";416;2
"Unit";"Corruptor";"Larva";416;2
"Unit";"Corruptor";"Larva";416;2
"Unit";"Corruptor";"Larva";416;2
"Building";"SpineCrawler";NA;416;0
"Unit";"Corruptor";"Larva";416;2
"Building";"SpineCrawler";NA;416;0
"Building";"Hatchery";NA;416;0
"Building";"Hatchery";NA;416;0
"Building";"CreepTumorQueen";NA;436;0
"Building";"CreepTumorQueen";NA;436;0
"Building";"CreepTumorQueen";NA;436;0
"Building";"CreepTumor";NA;436;0
"Building";"CreepTumor";NA;436;0
"Building";"SporeCrawler";NA;436;0
"Building";"CreepTumor";NA;436;0
"Building";"SporeCrawler";NA;436;0
"Building";"SporeCrawler";NA;436;0
"Building";"SporeCrawler";NA;436;0
"Building";"SporeCrawler";NA;436;0
"Building";"CreepTumorQueen";NA;436;0
"Building";"CreepTumorQueen";NA;436;0
"Building";"CreepTumorQueen";NA;436;0
"Unit";"Viper";"Larva";436;3
"Unit";"Viper";"Larva";436;3
"Unit";"Viper";"Larva";436;3
"Unit";"Viper";"Larva";436;3
"Unit";"Viper";"Larva";436;3
"Unit";"Corruptor";"Larva";436;2
"Unit";"Corruptor";"Larva";436;2
"Unit";"Corruptor";"Larva";436;2
"Unit";"Corruptor";"Larva";436;2
"Unit";"Corruptor";"Larva";436;2
"Unit";"Corruptor";"Larva";436;2
"Building";"CreepTumor";NA;463;0
"Building";"CreepTumor";NA;463;0
"Building";"CreepTumor";NA;463;0
"Building";"CreepTumor";NA;463;0
"Building";"CreepTumor";NA;463;0
"Building";"CreepTumorQueen";NA;463;0
"Building";"CreepTumorQueen";NA;463;0
"Building";"CreepTumorQueen";NA;463;0
"Building";"CreepTumor";NA;463;0
"Building";"CreepTumorQueen";NA;463;0
"Building";"CreepTumorQueen";NA;463;0
"Building";"CreepTumor";NA;463;0
"Building";"CreepTumor";NA;463;0
"Building";"CreepTumor";NA;463;0
"Building";"CreepTumor";NA;463;0
"Building";"CreepTumor";NA;463;0
"Building";"CreepTumor";NA;463;0
"Building";"CreepTumor";NA;463;0
"Building";"CreepTumor";NA;463;0
"Building";"CreepTumor";NA;463;0
"Building";"CreepTumor";NA;463;0
"Building";"CreepTumor";NA;463;0
"Building";"CreepTumor";NA;463;0
"Unit";"Corruptor";"Larva";463;2
"Unit";"Corruptor";"Larva";463;2
"Unit";"Corruptor";"Larva";463;2
"Unit";"Corruptor";"Larva";463;2
"Unit";"Corruptor";"Larva";463;2
"Unit";"Corruptor";"Larva";463;2
"Unit";"Corruptor";"Larva";463;2
"Unit";"Corruptor";"Larva";463;2
"Unit";"Corruptor";"Larva";463;2
"Unit";"Corruptor";"Larva";463;2
"Unit";"Corruptor";"Larva";463;2
"Unit";"Corruptor";"Larva";463;2
"Unit";"Corruptor";"Larva";463;2
"Unit";"Corruptor";"Larva";463;2
"Unit";"Corruptor";"Larva";463;2
"Unit";"Corruptor";"Larva";463;2
"Unit";"Corruptor";"Larva";463;2
"Building";"CreepTumor";NA;491;0
"Building";"CreepTumor";NA;497;0
"Building";"CreepTumor";NA;497;0
"Building";"CreepTumor";NA;497;0
"Building";"CreepTumor";NA;497;0
"Building";"CreepTumor";NA;497;0
"Building";"CreepTumor";NA;497;0
"Building";"CreepTumorQueen";NA;497;0
"Building";"CreepTumor";NA;497;0
"Building";"CreepTumor";NA;497;0
"Building";"CreepTumor";NA;497;0
"Building";"CreepTumor";NA;497;0
"Building";"CreepTumor";NA;497;0
"Building";"Extractor";NA;497;0
"Building";"CreepTumor";NA;497;0
"Building";"CreepTumor";NA;497;0
"Building";"CreepTumor";NA;497;0
"Building";"CreepTumor";NA;497;0
"Building";"Extractor";NA;497;0
"Building";"Extractor";NA;497;0
"Building";"CreepTumor";NA;497;0
"Building";"CreepTumor";NA;497;0
"Building";"CreepTumor";NA;497;0
"Building";"CreepTumor";NA;497;0
"Building";"CreepTumor";NA;497;0
"Unit";"Zergling";"Larva";497;1
"Unit";"Zergling";"Larva";497;1
"Unit";"Zergling";"Larva";497;1
"Unit";"Zergling";"Larva";497;1
"Unit";"Zergling";"Larva";497;1
"Unit";"Zergling";"Larva";497;1
"Unit";"Zergling";"Larva";497;1
"Unit";"Zergling";"Larva";497;1
"Unit";"Zergling";"Larva";497;1
"Unit";"Zergling";"Larva";497;1
"Unit";"Zergling";"Larva";497;1
"Unit";"Zergling";"Larva";497;1
"Unit";"Zergling";"Larva";497;1
"Unit";"Zergling";"Larva";497;1
"Unit";"Zergling";"Larva";497;1
"Unit";"Zergling";"Larva";497;1
"Unit";"Zergling";"Larva";497;1
"Unit";"Zergling";"Larva";497;1
"Unit";"Zergling";"Larva";497;1
"Unit";"Zergling";"Larva";497;1
"Unit";"Zergling";"Larva";497;1
"Unit";"Zergling";"Larva";497;1
"Unit";"Zergling";"Larva";497;1
"Unit";"Zergling";"Larva";497;1
"Unit";"Zergling";"Larva";497;1
"Unit";"Zergling";"Larva";497;1
"Unit";"Zergling";"Larva";497;1
"Unit";"Zergling";"Larva";497;1
"Unit";"Zergling";"Larva";497;1
"Unit";"Zergling";"Larva";497;1
"Unit";"Zergling";"Larva";497;1
"Unit";"Zergling";"Larva";497;1
"Unit";"Zergling";"Larva";497;1
"Unit";"Zergling";"Larva";497;1
"Unit";"Zergling";"Larva";497;1
"Unit";"Zergling";"Larva";497;1
"Building";"CreepTumor";NA;497;0
"Building";"CreepTumor";NA;497;0
"Building";"CreepTumor";NA;497;0
"Building";"CreepTumor";NA;497;0
"Building";"CreepTumor";NA;525;0
"Building";"CreepTumor";NA;533;0
"Building";"CreepTumor";NA;533;0
"Building";"CreepTumor";NA;533;0
"Building";"CreepTumor";NA;533;0
"Upgrade";"ZergMissileWeaponsLevel2";"EvolutionChamber";497;0
"Building";"CreepTumor";NA;533;0
"Building";"CreepTumor";NA;533;0
"Building";"CreepTumor";NA;533;0
"Unit";"Viper";"Larva";533;3
"Unit";"Viper";"Larva";533;3
"Unit";"Viper";"Larva";533;3
"Building";"CreepTumor";NA;552;0
"Unit";"Viper";"Larva";552;3
"Unit";"Viper";"Larva";552;3
"Building";"CreepTumor";NA;552;0
"Building";"CreepTumor";NA;552;0
"Building";"CreepTumor";NA;552;0
"Building";"CreepTumor";NA;552;0
"Unit";"Ultralisk";"Larva";552;6
"Unit";"Ultralisk";"Larva";552;6
"Building";"CreepTumor";NA;552;0
"Unit";"Queen";"Hatchery";552;2
"Unit";"Queen";"Hatchery";552;2
"Unit";"Queen";"Hatchery";552;2
"Unit";"Queen";"Hatchery";552;2
"Unit";"Queen";"Hatchery";552;2
"Building";"CreepTumor";NA;580;0
"Building";"CreepTumor";NA;580;0
"Building";"CreepTumor";NA;580;0
"Building";"CreepTumorQueen";NA;580;0
"Building";"Extractor";NA;580;0
"Building";"Extractor";NA;580;0
"Building";"CreepTumorQueen";NA;580;0
"Building";"CreepTumorQueen";NA;580;0
"Building";"CreepTumorQueen";NA;580;0
"Building";"CreepTumorQueen";NA;580;0
"Building";"CreepTumorQueen";NA;580;0
"Building";"CreepTumor";NA;580;0
"Building";"CreepTumorQueen";NA;580;0
"Unit";"Overlord";"Larva";580;0
"Unit";"Overlord";"Larva";580;0
"Unit";"Viper";"Larva";580;3
"Unit";"Viper";"Larva";580;3
"Unit";"Viper";"Larva";580;3
"Building";"Hatchery";NA;580;0
"Building";"CreepTumor";NA;580;0
"Building";"CreepTumor";NA;589;0
"Building";"CreepTumor";NA;589;0
"Building";"CreepTumor";NA;589;0
"Unit";"Zergling";"Larva";589;1
"Unit";"Zergling";"Larva";589;1
"Unit";"Zergling";"Larva";589;1
"Unit";"Zergling";"Larva";589;1
"Unit";"Zergling";"Larva";589;1
"Unit";"Zergling";"Larva";589;1
"Unit";"Zergling";"Larva";589;1
"Unit";"Zergling";"Larva";589;1
"Unit";"Zergling";"Larva";589;1
"Unit";"Zergling";"Larva";589;1
"Unit";"Zergling";"Larva";589;1
"Unit";"Zergling";"Larva";589;1
"Unit";"Zergling";"Larva";589;1
"Unit";"Zergling";"Larva";589;1
"Unit";"Zergling";"Larva";589;1
"Unit";"Zergling";"Larva";589;1
"Unit";"Zergling";"Larva";589;1
"Unit";"Zergling";"Larva";589;1
"Unit";"Zergling";"Larva";589;1
"Unit";"Zergling";"Larva";589;1
"Unit";"Zergling";"Larva";589;1
"Unit";"Zergling";"Larva";589;1
"Unit";"Zergling";"Larva";589;1
"Unit";"Zergling";"Larva";589;1
"Unit";"Zergling";"Larva";589;1
"Unit";"Zergling";"Larva";589;1
"Unit";"Zergling";"Larva";589;1
"Unit";"Zergling";"Larva";589;1
"Unit";"Zergling";"Larva";589;1
"Unit";"Zergling";"Larva";589;1
"Unit";"Zergling";"Larva";589;1
"Unit";"Zergling";"Larva";589;1
"Unit";"Zergling";"Larva";589;1
"Unit";"Zergling";"Larva";589;1
"Unit";"Zergling";"Larva";589;1
"Unit";"Zergling";"Larva";589;1
"Unit";"Zergling";"Larva";589;1
"Unit";"Zergling";"Larva";589;1
"Unit";"Zergling";"Larva";615;1
"Unit";"Zergling";"Larva";615;1
"Unit";"Zergling";"Larva";627;1
"Unit";"Zergling";"Larva";627;1
"Unit";"Zergling";"Larva";627;1
"Unit";"Zergling";"Larva";627;1
"Unit";"Zergling";"Larva";627;1
"Unit";"Zergling";"Larva";627;1
"Unit";"Zergling";"Larva";627;1
"Unit";"Zergling";"Larva";627;1
"Unit";"Zergling";"Larva";627;1
"Unit";"Zergling";"Larva";627;1
"Unit";"Zergling";"Larva";627;1
"Unit";"Zergling";"Larva";627;1
"Unit";"Zergling";"Larva";627;1
"Unit";"Zergling";"Larva";627;1
"Unit";"Zergling";"Larva";627;1
"Unit";"Zergling";"Larva";627;1
"Building";"Extractor";NA;645;0
"Building";"Extractor";NA;645;0
"Building";"SporeCrawler";NA;645;0
"Unit";"Corruptor";"Larva";645;2
"Unit";"Corruptor";"Larva";645;2
"Unit";"Corruptor";"Larva";645;2
"Unit";"Corruptor";"Larva";645;2
"Unit";"Corruptor";"Larva";645;2
"Unit";"Corruptor";"Larva";645;2
"Unit";"Corruptor";"Larva";645;2
"Unit";"Baneling";"Zergling";645;0
"Unit";"Baneling";"Zergling";645;0
"Unit";"Baneling";"Zergling";645;0
"Unit";"Baneling";"Zergling";645;0
"Unit";"Baneling";"Zergling";645;0
"Unit";"Baneling";"Zergling";645;0
"Unit";"Baneling";"Zergling";645;0
"Unit";"Baneling";"Zergling";645;0
"Unit";"Baneling";"Zergling";645;0
"Unit";"Baneling";"Zergling";659;0
"Unit";"Baneling";"Zergling";659;0
"Unit";"Baneling";"Zergling";659;0
"Unit";"Baneling";"Zergling";659;0
"Unit";"Baneling";"Zergling";659;0
"Unit";"Baneling";"Zergling";659;0
"Unit";"Baneling";"Zergling";659;0
"Unit";"Baneling";"Zergling";659;0
"Unit";"Baneling";"Zergling";659;0
"Unit";"Baneling";"Zergling";659;0
"Unit";"Baneling";"Zergling";659;0
"Unit";"Baneling";"Zergling";659;0
"Unit";"Baneling";"Zergling";659;0
"Unit";"Corruptor";"Larva";659;2
"Unit";"Corruptor";"Larva";659;2
"Unit";"Corruptor";"Larva";659;2
"Unit";"Corruptor";"Larva";659;2
"Unit";"Corruptor";"Larva";659;2
"Unit";"Corruptor";"Larva";659;2
"Unit";"Corruptor";"Larva";659;2
"Unit";"Corruptor";"Larva";659;2
"Unit";"Corruptor";"Larva";659;2
"Unit";"Corruptor";"Larva";659;2
"Unit";"Corruptor";"Larva";659;2
"Unit";"Corruptor";"Larva";659;2
"Building";"Hatchery";NA;645;0
"Building";"CreepTumorQueen";NA;683;0
"Building";"CreepTumorQueen";NA;683;0
"Unit";"Viper";"Larva";683;3
"Building";"CreepTumorQueen";NA;693;0
"Building";"CreepTumorQueen";NA;693;0
"Building";"CreepTumorQueen";NA;693;0
"Building";"CreepTumorQueen";NA;696;0
"Building";"CreepTumorQueen";NA;696;0
"Building";"CreepTumorQueen";NA;696;0
"Building";"CreepTumorQueen";NA;696;0
"Building";"CreepTumorQueen";NA;696;0
"Building";"CreepTumor";NA;696;0
"Building";"CreepTumor";NA;696;0
"Unit";"Viper";"Larva";696;3
"Unit";"Viper";"Larva";696;3
"Upgrade";"Burrow";"Hatchery";693;0
"Unit";"Zergling";"Larva";702;1
"Unit";"Zergling";"Larva";702;1
"Unit";"Zergling";"Larva";702;1
"Unit";"Zergling";"Larva";702;1
"Unit";"Zergling";"Larva";702;1
"Unit";"Zergling";"Larva";702;1
"Unit";"Zergling";"Larva";702;1
"Unit";"Zergling";"Larva";702;1
"Unit";"Zergling";"Larva";702;1
"Unit";"Zergling";"Larva";702;1
"Unit";"Zergling";"Larva";702;1
"Unit";"Zergling";"Larva";702;1
"Unit";"Zergling";"Larva";702;1
"Unit";"Zergling";"Larva";702;1
"Unit";"Zergling";"Larva";702;1
"Unit";"Zergling";"Larva";702;1
"Unit";"Zergling";"Larva";702;1
"Unit";"Zergling";"Larva";702;1
"Unit";"Zergling";"Larva";702;1
"Unit";"Zergling";"Larva";702;1
"Unit";"Zergling";"Larva";702;1
"Unit";"Zergling";"Larva";702;1
"Unit";"Zergling";"Larva";702;1
"Unit";"Zergling";"Larva";702;1
"Unit";"Zergling";"Larva";702;1
"Unit";"Zergling";"Larva";702;1
"Unit";"Zergling";"Larva";702;1
"Unit";"Zergling";"Larva";702;1
"Unit";"Zergling";"Larva";702;1
"Unit";"Zergling";"Larva";702;1
"Unit";"Zergling";"Larva";702;1
"Unit";"Zergling";"Larva";702;1
"Unit";"Zergling";"Larva";702;1
"Unit";"Zergling";"Larva";702;1
"Unit";"Corruptor";"Larva";736;2
"Unit";"Corruptor";"Larva";736;2
"Unit";"Corruptor";"Larva";736;2
"Unit";"Corruptor";"Larva";736;2
"Unit";"Corruptor";"Larva";736;2
"Unit";"Corruptor";"Larva";736;2
"Unit";"Zergling";"Larva";741;1
"Unit";"Zergling";"Larva";741;1
"Unit";"Zergling";"Larva";741;1
"Unit";"Zergling";"Larva";741;1
"Unit";"Zergling";"Larva";741;1
"Unit";"Zergling";"Larva";741;1
"Unit";"Zergling";"Larva";741;1
"Unit";"Zergling";"Larva";741;1
"Unit";"Zergling";"Larva";741;1
"Unit";"Zergling";"Larva";741;1
"Unit";"Zergling";"Larva";741;1
"Unit";"Zergling";"Larva";741;1
"Unit";"Zergling";"Larva";741;1
"Unit";"Zergling";"Larva";741;1
"Unit";"Zergling";"Larva";741;1
"Unit";"Zergling";"Larva";741;1
"Unit";"Zergling";"Larva";741;1
"Unit";"Zergling";"Larva";741;1
"Unit";"Zergling";"Larva";741;1
"Unit";"Zergling";"Larva";741;1
"Unit";"Zergling";"Larva";741;1
"Unit";"Zergling";"Larva";741;1
"Unit";"Zergling";"Larva";741;1
"Unit";"Zergling";"Larva";741;1
"Unit";"Zergling";"Larva";741;1
"Unit";"Zergling";"Larva";741;1
"Unit";"Zergling";"Larva";741;1
"Unit";"Zergling";"Larva";741;1
"Unit";"Zergling";"Larva";741;1
"Unit";"Zergling";"Larva";741;1
"Unit";"Zergling";"Larva";741;1
"Unit";"Zergling";"Larva";741;1
"Unit";"Zergling";"Larva";741;1
"Unit";"Zergling";"Larva";741;1
"Unit";"Zergling";"Larva";741;1
"Unit";"Zergling";"Larva";741;1
"Unit";"Zergling";"Larva";741;1
"Unit";"Zergling";"Larva";741;1
"Unit";"Zergling";"Larva";741;1
"Unit";"Zergling";"Larva";741;1
"Unit";"Zergling";"Larva";741;1
"Unit";"Zergling";"Larva";741;1
"Unit";"Zergling";"Larva";741;1
"Unit";"Zergling";"Larva";741;1
"Unit";"Zergling";"Larva";741;1
"Unit";"Zergling";"Larva";741;1
"Unit";"Zergling";"Larva";741;1
"Unit";"Zergling";"Larva";741;1
"Unit";"Zergling";"Larva";741;1
"Unit";"Zergling";"Larva";741;1
"Unit";"Zergling";"Larva";741;1
"Unit";"Zergling";"Larva";741;1
"Unit";"Zergling";"Larva";741;1
"Unit";"Zergling";"Larva";741;1
"Unit";"Zergling";"Larva";741;1
"Unit";"Zergling";"Larva";741;1
"Building";"CreepTumorQueen";NA;809;0
"Building";"CreepTumorQueen";NA;809;0
"Unit";"Zergling";"Larva";809;1
"Unit";"Zergling";"Larva";809;1
"Unit";"Zergling";"Larva";809;1
"Unit";"Zergling";"Larva";809;1
"Unit";"Zergling";"Larva";809;1
"Unit";"Zergling";"Larva";809;1
"Unit";"Zergling";"Larva";809;1
"Unit";"Zergling";"Larva";809;1
"Unit";"Zergling";"Larva";809;1
"Unit";"Zergling";"Larva";809;1
"Unit";"Zergling";"Larva";809;1
"Unit";"Zergling";"Larva";809;1
"Unit";"Zergling";"Larva";809;1
"Unit";"Zergling";"Larva";809;1
"Unit";"Zergling";"Larva";809;1
"Unit";"Zergling";"Larva";809;1
"Unit";"Zergling";"Larva";809;1
"Unit";"Zergling";"Larva";809;1
"Unit";"Zergling";"Larva";809;1
"Unit";"Zergling";"Larva";809;1
"Building";"CreepTumorQueen";NA;809;0
"Building";"CreepTumorQueen";NA;809;0
"Building";"CreepTumorQueen";NA;809;0
"Building";"Extractor";NA;829;0
"Building";"Extractor";NA;829;0
"Building";"CreepTumor";NA;829;0
"Building";"CreepTumor";NA;829;0
"Building";"CreepTumor";NA;829;0
"Building";"CreepTumor";NA;829;0
"Building";"CreepTumor";NA;829;0
"Building";"CreepTumor";NA;829;0
"Building";"CreepTumor";NA;829;0
"Building";"CreepTumor";NA;829;0
"Unit";"Zergling";"Larva";829;1
"Unit";"Zergling";"Larva";829;1
"Unit";"Zergling";"Larva";829;1
"Unit";"Zergling";"Larva";829;1
"Unit";"Zergling";"Larva";829;1
"Unit";"Zergling";"Larva";829;1
"Unit";"Zergling";"Larva";829;1
"Unit";"Zergling";"Larva";829;1
"Unit";"Zergling";"Larva";829;1
"Unit";"Zergling";"Larva";829;1
"Unit";"Zergling";"Larva";829;1
"Unit";"Zergling";"Larva";829;1
"Unit";"Zergling";"Larva";829;1
"Unit";"Zergling";"Larva";829;1
"Unit";"Zergling";"Larva";829;1
"Unit";"Zergling";"Larva";829;1
"Unit";"Zergling";"Larva";829;1
"Unit";"Zergling";"Larva";829;1
"Unit";"Zergling";"Larva";829;1
"Unit";"Zergling";"Larva";829;1
"Unit";"Zergling";"Larva";829;1
"Unit";"Zergling";"Larva";829;1
"Building";"CreepTumor";NA;829;0
"Unit";"Viper";"Larva";829;3
"Unit";"Viper";"Larva";829;3
"Unit";"Corruptor";"Larva";829;2
"Unit";"Corruptor";"Larva";829;2
"Unit";"Corruptor";"Larva";829;2
"Unit";"Corruptor";"Larva";829;2
"Unit";"Corruptor";"Larva";829;2
"Unit";"Corruptor";"Larva";829;2
"Unit";"Corruptor";"Larva";829;2
"Unit";"Corruptor";"Larva";829;2
"Building";"Hatchery";NA;829;0
"Building";"CreepTumor";NA;873;0
"Unit";"Viper";"Larva";873;3
"Unit";"Viper";"Larva";873;3
"Unit";"Viper";"Larva";873;3
"Unit";"Baneling";"Zergling";881;0
"Unit";"Baneling";"Zergling";881;0
"Unit";"Baneling";"Zergling";881;0
"Unit";"Baneling";"Zergling";881;0
"Unit";"Baneling";"Zergling";881;0
"Unit";"Baneling";"Zergling";881;0
"Unit";"Baneling";"Zergling";881;0
"Unit";"Baneling";"Zergling";881;0
"Unit";"Baneling";"Zergling";881;0
"Unit";"Baneling";"Zergling";881;0
"Unit";"Baneling";"Zergling";881;0
"Unit";"Baneling";"Zergling";881;0
"Unit";"Baneling";"Zergling";881;0
"Unit";"Zergling";"Larva";881;1
"Unit";"Zergling";"Larva";881;1
"Unit";"Zergling";"Larva";881;1
"Unit";"Zergling";"Larva";881;1
"Unit";"Zergling";"Larva";881;1
"Unit";"Zergling";"Larva";881;1
"Unit";"Zergling";"Larva";881;1
"Unit";"Zergling";"Larva";881;1
"Unit";"Zergling";"Larva";881;1
"Unit";"Zergling";"Larva";881;1
"Unit";"Zergling";"Larva";881;1
"Unit";"Zergling";"Larva";881;1
"Unit";"Zergling";"Larva";881;1
"Unit";"Zergling";"Larva";881;1
"Unit";"Zergling";"Larva";881;1
"Unit";"Zergling";"Larva";881;1
"Unit";"Zergling";"Larva";881;1
"Unit";"Zergling";"Larva";881;1
"Unit";"Zergling";"Larva";881;1
"Unit";"Zergling";"Larva";881;1
"Unit";"Zergling";"Larva";881;1
"Unit";"Zergling";"Larva";881;1
"Unit";"Zergling";"Larva";881;1
"Unit";"Zergling";"Larva";881;1
"Unit";"Zergling";"Larva";881;1
"Unit";"Zergling";"Larva";881;1
"Unit";"Zergling";"Larva";881;1
"Unit";"Zergling";"Larva";881;1
"Unit";"Zergling";"Larva";881;1
"Unit";"Zergling";"Larva";881;1
"Unit";"Zergling";"Larva";881;1
"Unit";"Zergling";"Larva";881;1
"Unit";"Zergling";"Larva";881;1
"Unit";"Zergling";"Larva";881;1
"Unit";"Zergling";"Larva";881;1
"Unit";"Zergling";"Larva";881;1
"Unit";"Zergling";"Larva";881;1
"Unit";"Zergling";"Larva";881;1
"Unit";"Zergling";"Larva";881;1
"Unit";"Zergling";"Larva";881;1
"Unit";"Zergling";"Larva";881;1
"Unit";"Zergling";"Larva";881;1
"Unit";"Zergling";"Larva";881;1
"Unit";"Zergling";"Larva";881;1
"Building";"CreepTumor";NA;890;0
"Building";"CreepTumor";NA;890;0
"Building";"CreepTumor";NA;890;0
"Building";"CreepTumor";NA;890;0
"Building";"CreepTumor";NA;890;0
"Building";"CreepTumorQueen";NA;890;0
"Building";"SporeCrawler";NA;934;0
"Building";"CreepTumor";NA;934;0
"Building";"CreepTumor";NA;934;0
"Building";"CreepTumor";NA;934;0
"Building";"CreepTumor";NA;934;0
"Building";"CreepTumor";NA;934;0
"Building";"CreepTumor";NA;934;0
"Building";"CreepTumor";NA;934;0
"Building";"CreepTumor";NA;934;0
"Building";"CreepTumor";NA;934;0
"Building";"CreepTumor";NA;934;0
"Building";"CreepTumor";NA;934;0
"Unit";"Zergling";"Larva";934;1
"Unit";"Zergling";"Larva";934;1
"Unit";"Zergling";"Larva";934;1
"Unit";"Zergling";"Larva";934;1
"Unit";"Zergling";"Larva";934;1
"Unit";"Zergling";"Larva";934;1
"Unit";"Zergling";"Larva";934;1
"Unit";"Zergling";"Larva";934;1
"Unit";"Zergling";"Larva";934;1
"Unit";"Zergling";"Larva";934;1
"Unit";"Zergling";"Larva";934;1
"Unit";"Zergling";"Larva";934;1
"Unit";"Zergling";"Larva";934;1
"Unit";"Zergling";"Larva";934;1
"Unit";"Zergling";"Larva";934;1
"Unit";"Zergling";"Larva";934;1
"Unit";"Zergling";"Larva";934;1
"Unit";"Zergling";"Larva";934;1
"Unit";"Zergling";"Larva";934;1
"Unit";"Zergling";"Larva";934;1
"Unit";"Zergling";"Larva";934;1
"Unit";"Zergling";"Larva";934;1
"Unit";"Zergling";"Larva";934;1
"Unit";"Zergling";"Larva";934;1
"Unit";"Zergling";"Larva";934;1
"Unit";"Zergling";"Larva";934;1
"Unit";"Zergling";"Larva";934;1
"Unit";"Zergling";"Larva";934;1
"Unit";"Zergling";"Larva";934;1
"Unit";"Zergling";"Larva";934;1
"Unit";"Zergling";"Larva";934;1
"Unit";"Zergling";"Larva";934;1
"Unit";"Zergling";"Larva";934;1
"Unit";"Zergling";"Larva";934;1
"Unit";"Zergling";"Larva";934;1
"Unit";"Zergling";"Larva";934;1
"Unit";"Zergling";"Larva";934;1
"Unit";"Zergling";"Larva";934;1
"Unit";"Zergling";"Larva";934;1
"Unit";"Zergling";"Larva";934;1
"Unit";"Zergling";"Larva";934;1
"Unit";"Zergling";"Larva";934;1
"Building";"CreepTumor";NA;934;0
"Building";"CreepTumor";NA;934;0
"Building";"CreepTumor";NA;934;0
"Building";"CreepTumor";NA;934;0
"Building";"CreepTumor";NA;976;0
"Building";"CreepTumor";NA;976;0
"Building";"CreepTumor";NA;976;0
"Unit";"Baneling";"Zergling";976;0
"Unit";"Baneling";"Zergling";976;0
"Unit";"Baneling";"Zergling";976;0
"Unit";"Baneling";"Zergling";976;0
"Unit";"Baneling";"Zergling";976;0
"Building";"Extractor";NA;982;0
"Building";"Extractor";NA;982;0
"Unit";"Corruptor";"Larva";982;2
"Unit";"Corruptor";"Larva";982;2
"Unit";"Corruptor";"Larva";982;2
"Building";"CreepTumorQueen";NA;982;0
"Building";"CreepTumorQueen";NA;982;0
"Building";"CreepTumorQueen";NA;982;0
"Building";"CreepTumorQueen";NA;988;0
"Building";"CreepTumorQueen";NA;988;0
"Building";"CreepTumorQueen";NA;988;0
"Building";"CreepTumor";NA;988;0
"Building";"HydraliskDen";NA;988;0
"Building";"Hatchery";NA;982;0
"Building";"CreepTumor";NA;988;0
"Building";"CreepTumor";NA;988;0
"Building";"CreepTumor";NA;988;0
"Unit";"Ultralisk";"Larva";988;6
"Unit";"Ultralisk";"Larva";988;6
"Building";"CreepTumor";NA;988;0
"Building";"CreepTumor";NA;988;0
"Building";"CreepTumor";NA;988;0
"Building";"CreepTumor";NA;988;0
"Building";"CreepTumor";NA;1000;0
"Building";"CreepTumor";NA;1000;0
"Building";"CreepTumorQueen";NA;1000;0
"Building";"CreepTumorQueen";NA;1000;0
"Building";"CreepTumorQueen";NA;1000;0
"Building";"CreepTumor";NA;1000;0
"Building";"CreepTumor";NA;1000;0
"Building";"CreepTumor";NA;1000;0
"Building";"CreepTumor";NA;1000;0
"Building";"CreepTumor";NA;1000;0
"Building";"CreepTumor";NA;1000;0
"Building";"CreepTumor";NA;1000;0
"Unit";"Ultralisk";"Larva";988;6
"Unit";"Ultralisk";"Larva";988;6
"Unit";"Ultralisk";"Larva";988;6
"Building";"CreepTumor";NA;1000;0
"Building";"CreepTumor";NA;1000;0
"Unit";"Baneling";"Zergling";1000;0
"Unit";"Baneling";"Zergling";1000;0
"Unit";"Baneling";"Zergling";1000;0
"Unit";"Baneling";"Zergling";1000;0
"Unit";"Baneling";"Zergling";1000;0
"Unit";"Baneling";"Zergling";1000;0
"Unit";"Baneling";"Zergling";1000;0
"Unit";"Baneling";"Zergling";1000;0
"Unit";"Hydralisk";"Larva";1034;2
"Unit";"Hydralisk";"Larva";1034;2
"Unit";"Hydralisk";"Larva";1034;2
"Unit";"Hydralisk";"Larva";1034;2
"Unit";"Hydralisk";"Larva";1034;2
"Unit";"Hydralisk";"Larva";1034;2
"Unit";"Hydralisk";"Larva";1034;2
"Unit";"Hydralisk";"Larva";1034;2
"Unit";"Hydralisk";"Larva";1034;2
"Unit";"Hydralisk";"Larva";1034;2
"Building";"CreepTumor";NA;1034;0
"Building";"CreepTumor";NA;1034;0
"Building";"CreepTumor";NA;1034;0
"Building";"CreepTumorQueen";NA;1034;0
"Building";"CreepTumor";NA;1034;0
"Building";"CreepTumor";NA;1034;0
"Building";"CreepTumor";NA;1034;0
"Unit";"Hydralisk";"Larva";1062;2
"Unit";"Hydralisk";"Larva";1062;2
"Unit";"Hydralisk";"Larva";1062;2
"Unit";"Hydralisk";"Larva";1062;2
"Unit";"Hydralisk";"Larva";1062;2
"Unit";"Hydralisk";"Larva";1062;2
"Unit";"Hydralisk";"Larva";1062;2
"Unit";"Hydralisk";"Larva";1062;2
"Unit";"Overlord";"Larva";1062;0
"Unit";"Overlord";"Larva";1062;0
"Unit";"Overlord";"Larva";1062;0
"Building";"CreepTumor";NA;1062;0
"Unit";"Overlord";"Larva";1063;0
"Unit";"Overlord";"Larva";1067;0
"Unit";"Overlord";"Larva";1067;0
"Unit";"Overlord";"Larva";1067;0
"Unit";"Overlord";"Larva";1083;0
"Unit";"Overlord";"Larva";1083;0
"Unit";"Overlord";"Larva";1083;0
"Building";"CreepTumor";NA;1083;0
"Building";"CreepTumor";NA;1083;0
"Building";"CreepTumor";NA;1083;0
"Building";"CreepTumor";NA;1083;0
"Building";"CreepTumor";NA;1083;0
"Building";"CreepTumor";NA;1083;0
"Building";"CreepTumor";NA;1083;0
"Unit";"Hydralisk";"Larva";1083;2
"Unit";"Hydralisk";"Larva";1083;2
"Unit";"Hydralisk";"Larva";1083;2
"Unit";"Hydralisk";"Larva";1083;2
"Unit";"Hydralisk";"Larva";1083;2
"Unit";"Hydralisk";"Larva";1083;2
"Unit";"Hydralisk";"Larva";1083;2
"Unit";"Hydralisk";"Larva";1083;2
"Unit";"Hydralisk";"Larva";1083;2
"Unit";"Hydralisk";"Larva";1083;2
"Unit";"Hydralisk";"Larva";1083;2
"Unit";"Hydralisk";"Larva";1083;2
"Building";"CreepTumor";NA;1083;0
"Unit";"Zergling";"Larva";1083;1
"Unit";"Zergling";"Larva";1083;1
"Unit";"Zergling";"Larva";1083;1
"Unit";"Zergling";"Larva";1083;1
"Unit";"Zergling";"Larva";1083;1
"Unit";"Zergling";"Larva";1083;1
"Unit";"Zergling";"Larva";1083;1
"Unit";"Zergling";"Larva";1083;1
"Unit";"Zergling";"Larva";1083;1
"Unit";"Zergling";"Larva";1083;1
"Unit";"Zergling";"Larva";1083;1
"Unit";"Zergling";"Larva";1083;1
"Unit";"Zergling";"Larva";1083;1
"Unit";"Zergling";"Larva";1083;1
"Unit";"Zergling";"Larva";1083;1
"Unit";"Zergling";"Larva";1083;1
"Unit";"Zergling";"Larva";1083;1
"Unit";"Zergling";"Larva";1083;1
"Unit";"Zergling";"Larva";1083;1
"Unit";"Zergling";"Larva";1083;1
"Unit";"Zergling";"Larva";1083;1
"Unit";"Zergling";"Larva";1083;1
"Unit";"Zergling";"Larva";1083;1
"Unit";"Zergling";"Larva";1083;1
"Unit";"Zergling";"Larva";1083;1
"Unit";"Zergling";"Larva";1083;1
"Unit";"Zergling";"Larva";1083;1
"Unit";"Zergling";"Larva";1083;1
"Unit";"Zergling";"Larva";1083;1
"Unit";"Zergling";"Larva";1083;1
"Unit";"Zergling";"Larva";1083;1
"Unit";"Zergling";"Larva";1083;1
"Unit";"Zergling";"Larva";1083;1
"Unit";"Zergling";"Larva";1083;1
"Unit";"Zergling";"Larva";1083;1
"Unit";"Zergling";"Larva";1083;1
"Unit";"Zergling";"Larva";1083;1
"Unit";"Zergling";"Larva";1083;1
"Unit";"Zergling";"Larva";1129;1
"Unit";"Zergling";"Larva";1129;1
"Unit";"Zergling";"Larva";1129;1
"Unit";"Zergling";"Larva";1129;1
"Unit";"Zergling";"Larva";1129;1
"Unit";"Zergling";"Larva";1129;1
"Unit";"Zergling";"Larva";1129;1
"Unit";"Zergling";"Larva";1129;1
"Unit";"Zergling";"Larva";1129;1
"Unit";"Zergling";"Larva";1129;1
"Unit";"Zergling";"Larva";1129;1
"Unit";"Zergling";"Larva";1129;1
"Unit";"Zergling";"Larva";1129;1
"Unit";"Zergling";"Larva";1129;1
"Unit";"Zergling";"Larva";1129;1
"Unit";"Zergling";"Larva";1129;1
"Unit";"Zergling";"Larva";1129;1
"Unit";"Zergling";"Larva";1129;1
"Unit";"Zergling";"Larva";1129;1
"Unit";"Zergling";"Larva";1129;1
"Unit";"Zergling";"Larva";1129;1
"Unit";"Zergling";"Larva";1129;1
"Unit";"Zergling";"Larva";1145;1
"Unit";"Zergling";"Larva";1145;1
"Unit";"Zergling";"Larva";1145;1
"Unit";"Zergling";"Larva";1145;1
"Unit";"Zergling";"Larva";1145;1
"Unit";"Zergling";"Larva";1145;1
"Unit";"Zergling";"Larva";1145;1
"Unit";"Zergling";"Larva";1145;1
"Unit";"Zergling";"Larva";1145;1
"Unit";"Zergling";"Larva";1145;1
"Unit";"Zergling";"Larva";1145;1
"Unit";"Zergling";"Larva";1145;1
"Unit";"Baneling";"Zergling";1167;0
"Unit";"Baneling";"Zergling";1167;0
"Unit";"Baneling";"Zergling";1167;0
"Unit";"Baneling";"Zergling";1167;0
"Unit";"Baneling";"Zergling";1167;0
"Unit";"Baneling";"Zergling";1167;0
"Unit";"Baneling";"Zergling";1167;0
"Unit";"Baneling";"Zergling";1167;0
"Unit";"Baneling";"Zergling";1167;0
"Building";"CreepTumor";NA;1179;0
"Building";"CreepTumor";NA;1179;0
"Unit";"Zergling";"Larva";1179;1
"Unit";"Zergling";"Larva";1179;1
"Unit";"Zergling";"Larva";1179;1
"Unit";"Zergling";"Larva";1179;1
"Unit";"Zergling";"Larva";1179;1
"Unit";"Zergling";"Larva";1179;1
"Unit";"Zergling";"Larva";1179;1
"Unit";"Zergling";"Larva";1179;1
"Unit";"Zergling";"Larva";1179;1
"Unit";"Zergling";"Larva";1179;1
"Unit";"Zergling";"Larva";1179;1
"Unit";"Zergling";"Larva";1179;1
"Unit";"Zergling";"Larva";1179;1
"Unit";"Zergling";"Larva";1179;1
"Unit";"Zergling";"Larva";1179;1
"Unit";"Zergling";"Larva";1179;1
"Unit";"Zergling";"Larva";1179;1
"Unit";"Zergling";"Larva";1179;1
"Unit";"Zergling";"Larva";1179;1
"Unit";"Zergling";"Larva";1179;1
"Unit";"Zergling";"Larva";1179;1
"Unit";"Zergling";"Larva";1179;1
"Unit";"Zergling";"Larva";1179;1
"Unit";"Zergling";"Larva";1179;1
"Unit";"Zergling";"Larva";1179;1
"Unit";"Zergling";"Larva";1179;1
"Unit";"Zergling";"Larva";1179;1
"Unit";"Zergling";"Larva";1179;1
"Unit";"Zergling";"Larva";1179;1
"Unit";"Zergling";"Larva";1179;1
"Unit";"Zergling";"Larva";1179;1
"Unit";"Zergling";"Larva";1179;1
"Unit";"Zergling";"Larva";1179;1
"Unit";"Zergling";"Larva";1179;1
"Unit";"Zergling";"Larva";1179;1
"Unit";"Zergling";"Larva";1179;1
"Unit";"Viper";"Larva";1179;3
"Unit";"Viper";"Larva";1179;3
"Unit";"Viper";"Larva";1179;3
"Unit";"Viper";"Larva";1179;3
"Building";"CreepTumor";NA;1215;0
"Unit";"Zergling";"Larva";1179;1
"Unit";"Zergling";"Larva";1179;1
"Unit";"Zergling";"Larva";1179;1
"Unit";"Zergling";"Larva";1179;1
"Unit";"Zergling";"Larva";1179;1
"Unit";"Zergling";"Larva";1179;1
"Unit";"Zergling";"Larva";1179;1
"Unit";"Zergling";"Larva";1179;1
"Unit";"Zergling";"Larva";1179;1
"Unit";"Zergling";"Larva";1179;1
"Unit";"Zergling";"Larva";1179;1
"Unit";"Zergling";"Larva";1179;1
"Unit";"Zergling";"Larva";1179;1
"Unit";"Zergling";"Larva";1179;1
"Unit";"Zergling";"Larva";1179;1
"Unit";"Zergling";"Larva";1179;1
"Unit";"Zergling";"Larva";1179;1
"Unit";"Zergling";"Larva";1179;1
"Unit";"Zergling";"Larva";1179;1
"Unit";"Zergling";"Larva";1179;1
"Unit";"Zergling";"Larva";1179;1
"Unit";"Zergling";"Larva";1179;1
"Unit";"Baneling";"Zergling";1215;0
"Unit";"Baneling";"Zergling";1215;0
"Unit";"Baneling";"Zergling";1215;0
"Unit";"Baneling";"Zergling";1215;0
"Unit";"Baneling";"Zergling";1215;0
"Unit";"Baneling";"Zergling";1215;0
"Unit";"Ultralisk";"Larva";1179;6
"Unit";"Ultralisk";"Larva";1179;6
"Unit";"Zergling";"Larva";1249;1
"Unit";"Zergling";"Larva";1249;1
"Unit";"Zergling";"Larva";1249;1
"Unit";"Zergling";"Larva";1249;1
"Unit";"Zergling";"Larva";1249;1
"Unit";"Zergling";"Larva";1249;1
"Unit";"Zergling";"Larva";1249;1
"Unit";"Zergling";"Larva";1249;1
"Unit";"Zergling";"Larva";1249;1
"Unit";"Zergling";"Larva";1249;1
"Unit";"Zergling";"Larva";1249;1
"Unit";"Zergling";"Larva";1249;1
"Unit";"Zergling";"Larva";1249;1
"Unit";"Zergling";"Larva";1249;1
"Unit";"Zergling";"Larva";1249;1
"Unit";"Zergling";"Larva";1249;1
"Unit";"Zergling";"Larva";1249;1
"Unit";"Zergling";"Larva";1249;1
"Unit";"Zergling";"Larva";1249;1
"Unit";"Zergling";"Larva";1249;1
"Unit";"Zergling";"Larva";1249;1
"Unit";"Zergling";"Larva";1249;1
"Unit";"Zergling";"Larva";1249;1
"Unit";"Zergling";"Larva";1249;1
"Unit";"Zergling";"Larva";1249;1
"Unit";"Zergling";"Larva";1249;1
"Building";"CreepTumor";NA;1261;0
"Unit";"Zergling";"Larva";1255;1
"Unit";"Zergling";"Larva";1255;1
"Unit";"Zergling";"Larva";1255;1
"Unit";"Zergling";"Larva";1255;1
"Unit";"Zergling";"Larva";1255;1
"Unit";"Zergling";"Larva";1255;1
"Unit";"Zergling";"Larva";1255;1
"Unit";"Zergling";"Larva";1255;1
"Unit";"Zergling";"Larva";1255;1
"Unit";"Zergling";"Larva";1255;1
"Unit";"Zergling";"Larva";1255;1
"Unit";"Zergling";"Larva";1255;1
"Unit";"Zergling";"Larva";1255;1
"Unit";"Zergling";"Larva";1255;1
"Building";"CreepTumor";NA;1261;0
"Unit";"Ultralisk";"Larva";1249;6
