"type";"unit_name";"on_building";"total_supply";"supply"
"Unit";"Overlord";"Larva";16;0
"Building";"Extractor";NA;17;0
"Building";"Hatchery";NA;15;0
"Building";"SpawningPool";NA;16;0
"Unit";"Overlord";"Larva";22;0
"Unit";"Queen";"Hatchery";21;2
"Unit";"Queen";"Hatchery";21;2
"Unit";"Overlord";"Larva";25;0
"Unit";"Overlord";"Larva";32;0
"Building";"EvolutionChamber";NA;37;0
"Unit";"Overlord";"Larva";41;0
"Unit";"Overlord";"Larva";42;0
"Unit";"Queen";"Hatchery";38;2
"Unit";"Overlord";"Larva";43;0
"Building";"CreepTumorQueen";NA;50;0
"Building";"Hatchery";NA;37;0
"Unit";"Zergling";"Larva";51;1
"Unit";"Zergling";"Larva";51;1
"Unit";"Zergling";"Larva";51;1
"Unit";"Zergling";"Larva";51;1
"Unit";"Zergling";"Larva";51;1
"Unit";"Zergling";"Larva";51;1
"Unit";"Zergling";"Larva";51;1
"Unit";"Zergling";"Larva";51;1
"Unit";"Zergling";"Larva";51;1
"Unit";"Zergling";"Larva";51;1
"Unit";"Zergling";"Larva";51;1
"Unit";"Zergling";"Larva";51;1
"Unit";"Zergling";"Larva";51;1
"Unit";"Zergling";"Larva";51;1
"Unit";"Zergling";"Larva";51;1
"Unit";"Zergling";"Larva";51;1
"Building";"CreepTumor";NA;51;0
"Unit";"Zergling";"Larva";51;1
"Unit";"Zergling";"Larva";51;1
"Unit";"Zergling";"Larva";51;1
"Unit";"Zergling";"Larva";51;1
"Unit";"Zergling";"Larva";51;1
"Unit";"Zergling";"Larva";51;1
"Building";"Extractor";NA;51;0
"Unit";"Queen";"Hatchery";51;2
"Unit";"Queen";"Hatchery";51;2
"Unit";"Queen";"Hatchery";51;2
"Building";"CreepTumor";NA;76;0
"Unit";"Zergling";"Larva";76;1
"Unit";"Zergling";"Larva";76;1
"Unit";"Zergling";"Larva";76;1
"Unit";"Zergling";"Larva";76;1
"Unit";"Zergling";"Larva";85;1
"Unit";"Zergling";"Larva";85;1
"Unit";"Zergling";"Larva";85;1
"Unit";"Zergling";"Larva";85;1
"Unit";"Overlord";"Larva";85;0
"Unit";"Overlord";"Larva";85;0
"Building";"CreepTumorQueen";NA;89;0
"Building";"CreepTumorQueen";NA;89;0
"Unit";"Overlord";"Larva";89;0
"Unit";"Overlord";"Larva";89;0
"Unit";"Overlord";"Larva";89;0
"Unit";"Queen";"Hatchery";79;2
"Upgrade";"ZergGroundArmorsLevel1";"EvolutionChamber";51;0
"Building";"CreepTumor";NA;95;0
"Unit";"Zergling";"Larva";95;1
"Unit";"Zergling";"Larva";95;1
"Unit";"Zergling";"Larva";95;1
"Unit";"Zergling";"Larva";95;1
"Unit";"Zergling";"Larva";95;1
"Unit";"Zergling";"Larva";95;1
"Unit";"Zergling";"Larva";95;1
"Unit";"Zergling";"Larva";95;1
"Building";"CreepTumor";NA;97;0
"Building";"CreepTumorQueen";NA;103;0
"Building";"CreepTumorQueen";NA;103;0
"Building";"CreepTumorQueen";NA;104;0
"Building";"Extractor";NA;95;0
"Building";"CreepTumor";NA;105;0
"Building";"EvolutionChamber";NA;95;0
"Building";"CreepTumorQueen";NA;107;0
"Unit";"Zergling";"Larva";107;1
"Unit";"Zergling";"Larva";107;1
"Unit";"Zergling";"Larva";107;1
"Unit";"Zergling";"Larva";107;1
"Unit";"Zergling";"Larva";107;1
"Unit";"Zergling";"Larva";107;1
"Building";"SporeCrawler";NA;107;0
"Unit";"Queen";"Hatchery";95;2
"Unit";"Queen";"Hatchery";95;2
"Building";"CreepTumor";NA;120;0
"Building";"BanelingNest";NA;95;0
"Building";"CreepTumor";NA;127;0
"Building";"CreepTumor";NA;127;0
"Building";"Extractor";NA;120;0
"Building";"Extractor";NA;120;0
"Unit";"Overlord";"Larva";127;0
"Unit";"Overlord";"Larva";127;0
"Unit";"Zergling";"Larva";136;1
"Unit";"Zergling";"Larva";136;1
"Unit";"Zergling";"Larva";136;1
"Unit";"Zergling";"Larva";136;1
"Unit";"Zergling";"Larva";136;1
"Unit";"Zergling";"Larva";136;1
"Unit";"Zergling";"Larva";136;1
"Unit";"Zergling";"Larva";136;1
"Unit";"Zergling";"Larva";136;1
"Unit";"Zergling";"Larva";136;1
"Unit";"Zergling";"Larva";136;1
"Unit";"Zergling";"Larva";136;1
"Unit";"Zergling";"Larva";136;1
"Unit";"Zergling";"Larva";136;1
"Building";"CreepTumor";NA;150;0
"Building";"CreepTumor";NA;150;0
"Unit";"Zergling";"Larva";136;1
"Unit";"Zergling";"Larva";136;1
"Unit";"Zergling";"Larva";136;1
"Unit";"Zergling";"Larva";136;1
"Unit";"Zergling";"Larva";136;1
"Unit";"Zergling";"Larva";136;1
"Unit";"Zergling";"Larva";136;1
"Unit";"Zergling";"Larva";136;1
"Unit";"Zergling";"Larva";136;1
"Unit";"Zergling";"Larva";136;1
"Unit";"Zergling";"Larva";136;1
"Unit";"Zergling";"Larva";136;1
"Unit";"Zergling";"Larva";136;1
"Unit";"Zergling";"Larva";136;1
"Unit";"Zergling";"Larva";136;1
"Unit";"Zergling";"Larva";136;1
"Building";"CreepTumorQueen";NA;154;0
"Building";"CreepTumorQueen";NA;154;0
"Building";"CreepTumorQueen";NA;154;0
"Building";"CreepTumorQueen";NA;154;0
"Building";"CreepTumor";NA;154;0
"Building";"Extractor";NA;154;0
"Unit";"Overlord";"Larva";154;0
"Unit";"Overlord";"Larva";154;0
"Building";"CreepTumor";NA;170;0
"Unit";"Baneling";"Zergling";170;0
"Building";"CreepTumorQueen";NA;170;0
"Unit";"Baneling";"Zergling";170;0
"Unit";"Baneling";"Zergling";170;0
"Unit";"Baneling";"Zergling";170;0
"Unit";"Baneling";"Zergling";170;0
"Unit";"Baneling";"Zergling";170;0
"Building";"CreepTumorQueen";NA;170;0
"Unit";"Baneling";"Zergling";170;0
"Unit";"Baneling";"Zergling";170;0
"Unit";"Baneling";"Zergling";170;0
"Unit";"Baneling";"Zergling";170;0
"Unit";"Baneling";"Zergling";170;0
"Building";"CreepTumorQueen";NA;170;0
"Unit";"Baneling";"Zergling";170;0
"Upgrade";"ZergMeleeWeaponsLevel1";"EvolutionChamber";120;0
"Building";"CreepTumor";NA;170;0
"Building";"CreepTumor";NA;170;0
"Building";"CreepTumor";NA;170;0
"Building";"CreepTumor";NA;170;0
"Building";"CreepTumor";NA;170;0
"Building";"CreepTumor";NA;170;0
"Building";"CreepTumorQueen";NA;175;0
"Building";"CreepTumorQueen";NA;175;0
"Building";"CreepTumor";NA;175;0
"Building";"CreepTumorQueen";NA;175;0
"Building";"CreepTumorQueen";NA;175;0
"Building";"CreepTumorQueen";NA;176;0
"Building";"CreepTumor";NA;178;0
"Unit";"Overlord";"Larva";178;0
"Unit";"Overlord";"Larva";178;0
"Building";"CreepTumor";NA;178;0
"Building";"CreepTumor";NA;178;0
"Building";"CreepTumor";NA;178;0
"Building";"InfestationPit";NA;170;0
"Building";"CreepTumor";NA;178;0
"Building";"CreepTumor";NA;178;0
"Building";"CreepTumor";NA;178;0
"Building";"CreepTumor";NA;178;0
"Building";"CreepTumor";NA;178;0
"Building";"CreepTumor";NA;178;0
"Building";"SporeCrawler";NA;178;0
"Building";"CreepTumor";NA;181;0
"Building";"CreepTumor";NA;181;0
"Building";"CreepTumor";NA;181;0
"Building";"CreepTumor";NA;181;0
"Building";"CreepTumor";NA;181;0
"Unit";"Zergling";"Larva";181;1
"Unit";"Zergling";"Larva";181;1
"Unit";"Zergling";"Larva";181;1
"Unit";"Zergling";"Larva";181;1
"Unit";"Zergling";"Larva";181;1
"Unit";"Zergling";"Larva";181;1
"Unit";"Zergling";"Larva";181;1
"Unit";"Zergling";"Larva";181;1
"Unit";"Zergling";"Larva";181;1
"Unit";"Zergling";"Larva";181;1
"Unit";"Zergling";"Larva";181;1
"Unit";"Zergling";"Larva";181;1
"Unit";"Zergling";"Larva";181;1
"Unit";"Zergling";"Larva";181;1
"Unit";"Zergling";"Larva";181;1
"Unit";"Zergling";"Larva";181;1
"Unit";"Zergling";"Larva";181;1
"Unit";"Zergling";"Larva";181;1
"Unit";"Zergling";"Larva";181;1
"Unit";"Zergling";"Larva";181;1
"Unit";"Zergling";"Larva";181;1
"Unit";"Zergling";"Larva";181;1
"Unit";"Zergling";"Larva";181;1
"Unit";"Zergling";"Larva";181;1
"Unit";"Zergling";"Larva";181;1
"Unit";"Zergling";"Larva";181;1
"Unit";"Zergling";"Larva";181;1
"Unit";"Zergling";"Larva";181;1
"Building";"Hatchery";NA;170;0
"Building";"CreepTumor";NA;181;0
"Building";"CreepTumor";NA;181;0
"Building";"CreepTumor";NA;181;0
"Building";"CreepTumor";NA;181;0
"Building";"CreepTumorQueen";NA;193;0
"Building";"CreepTumor";NA;193;0
"Unit";"Overlord";"Larva";209;0
"Building";"HydraliskDen";NA;181;0
"Building";"CreepTumorQueen";NA;211;0
"Building";"CreepTumorQueen";NA;211;0
"Building";"SporeCrawler";NA;209;0
"Building";"CreepTumor";NA;211;0
"Building";"CreepTumor";NA;211;0
"Building";"Hatchery";NA;178;0
"Unit";"Zergling";"Larva";211;1
"Unit";"Zergling";"Larva";211;1
"Unit";"Zergling";"Larva";211;1
"Unit";"Zergling";"Larva";211;1
"Unit";"Zergling";"Larva";211;1
"Unit";"Zergling";"Larva";211;1
"Unit";"Zergling";"Larva";211;1
"Unit";"Zergling";"Larva";211;1
"Unit";"Zergling";"Larva";211;1
"Unit";"Zergling";"Larva";211;1
"Unit";"Zergling";"Larva";211;1
"Unit";"Zergling";"Larva";211;1
"Unit";"Zergling";"Larva";211;1
"Unit";"Zergling";"Larva";211;1
"Unit";"Zergling";"Larva";211;1
"Unit";"Zergling";"Larva";211;1
"Unit";"Zergling";"Larva";211;1
"Unit";"Zergling";"Larva";211;1
"Upgrade";"ZergGroundArmorsLevel2";"EvolutionChamber";170;0
"Unit";"Zergling";"Larva";211;1
"Unit";"Zergling";"Larva";211;1
"Unit";"Zergling";"Larva";211;1
"Unit";"Zergling";"Larva";211;1
"Unit";"Zergling";"Larva";211;1
"Unit";"Zergling";"Larva";211;1
"Unit";"Zergling";"Larva";211;1
"Unit";"Zergling";"Larva";211;1
"Unit";"Zergling";"Larva";211;1
"Unit";"Zergling";"Larva";211;1
"Unit";"Zergling";"Larva";211;1
"Unit";"Zergling";"Larva";211;1
"Unit";"Zergling";"Larva";229;1
"Unit";"Zergling";"Larva";229;1
"Unit";"Zergling";"Larva";229;1
"Unit";"Zergling";"Larva";229;1
"Unit";"Zergling";"Larva";229;1
"Unit";"Zergling";"Larva";229;1
"Unit";"Zergling";"Larva";229;1
"Unit";"Zergling";"Larva";229;1
"Unit";"Zergling";"Larva";229;1
"Unit";"Zergling";"Larva";229;1
"Unit";"Zergling";"Larva";229;1
"Unit";"Zergling";"Larva";229;1
"Unit";"Zergling";"Larva";229;1
"Unit";"Zergling";"Larva";229;1
"Unit";"Zergling";"Larva";229;1
"Unit";"Zergling";"Larva";229;1
"Unit";"Zergling";"Larva";229;1
"Unit";"Zergling";"Larva";229;1
"Building";"CreepTumor";NA;241;0
"Building";"CreepTumor";NA;241;0
"Building";"CreepTumor";NA;259;0
"Building";"CreepTumorQueen";NA;259;0
"Unit";"Hydralisk";"Larva";259;2
"Building";"CreepTumor";NA;270;0
"Building";"CreepTumor";NA;270;0
"Unit";"Viper";"Larva";259;3
"Unit";"Viper";"Larva";260;3
"Unit";"Viper";"Larva";263;3
"Unit";"Viper";"Larva";268;3
"Unit";"Viper";"Larva";268;3
"Building";"CreepTumor";NA;270;0
"Building";"CreepTumor";NA;270;0
"Building";"CreepTumor";NA;270;0
"Building";"CreepTumor";NA;270;0
"Building";"CreepTumor";NA;270;0
"Building";"CreepTumor";NA;270;0
"Building";"CreepTumor";NA;270;0
"Building";"CreepTumor";NA;270;0
"Building";"CreepTumorQueen";NA;270;0
"Building";"CreepTumorQueen";NA;270;0
"Unit";"Overlord";"Larva";270;0
"Unit";"Overlord";"Larva";270;0
"Unit";"Overlord";"Larva";270;0
"Unit";"Baneling";"Zergling";285;0
"Unit";"Baneling";"Zergling";285;0
"Unit";"Baneling";"Zergling";285;0
"Unit";"Baneling";"Zergling";285;0
"Unit";"Baneling";"Zergling";285;0
"Unit";"Baneling";"Zergling";285;0
"Unit";"Baneling";"Zergling";285;0
"Unit";"Baneling";"Zergling";285;0
"Unit";"Baneling";"Zergling";285;0
"Unit";"Baneling";"Zergling";285;0
"Unit";"Baneling";"Zergling";285;0
"Unit";"Baneling";"Zergling";285;0
"Unit";"Baneling";"Zergling";285;0
"Unit";"Overlord";"Larva";285;0
"Unit";"Overlord";"Larva";285;0
"Unit";"Hydralisk";"Larva";276;2
"Unit";"Hydralisk";"Larva";279;2
"Unit";"Hydralisk";"Larva";282;2
"Building";"CreepTumorQueen";NA;285;0
"Building";"CreepTumorQueen";NA;285;0
"Building";"CreepTumor";NA;285;0
"Building";"CreepTumor";NA;285;0
"Upgrade";"ZergMeleeWeaponsLevel2";"EvolutionChamber";211;0
"Upgrade";"EvolveGroovedSpines";"HydraliskDen";270;0
"Building";"CreepTumor";NA;291;0
"Building";"CreepTumor";NA;291;0
"Unit";"Baneling";"Zergling";291;0
"Unit";"Zergling";"Larva";285;1
"Unit";"Zergling";"Larva";285;1
"Unit";"Baneling";"Zergling";291;0
"Unit";"Baneling";"Zergling";291;0
"Unit";"Baneling";"Zergling";291;0
"Unit";"Baneling";"Zergling";291;0
"Unit";"Zergling";"Larva";287;1
"Unit";"Zergling";"Larva";287;1
"Unit";"Zergling";"Larva";287;1
"Unit";"Zergling";"Larva";287;1
"Unit";"Zergling";"Larva";287;1
"Unit";"Zergling";"Larva";287;1
"Unit";"Zergling";"Larva";287;1
"Unit";"Zergling";"Larva";287;1
"Unit";"Zergling";"Larva";287;1
"Unit";"Zergling";"Larva";287;1
"Unit";"Zergling";"Larva";289;1
"Unit";"Zergling";"Larva";289;1
"Unit";"Zergling";"Larva";289;1
"Unit";"Zergling";"Larva";289;1
"Unit";"Zergling";"Larva";291;1
"Unit";"Zergling";"Larva";291;1
"Unit";"Zergling";"Larva";291;1
"Unit";"Zergling";"Larva";291;1
"Unit";"Zergling";"Larva";291;1
"Unit";"Zergling";"Larva";291;1
"Unit";"Zergling";"Larva";291;1
"Unit";"Zergling";"Larva";291;1
"Unit";"Zergling";"Larva";291;1
"Unit";"Zergling";"Larva";291;1
"Unit";"Zergling";"Larva";291;1
"Unit";"Zergling";"Larva";291;1
"Unit";"Zergling";"Larva";291;1
"Unit";"Zergling";"Larva";291;1
"Unit";"Zergling";"Larva";291;1
"Unit";"Zergling";"Larva";291;1
"Unit";"Zergling";"Larva";291;1
"Unit";"Zergling";"Larva";291;1
"Unit";"Zergling";"Larva";291;1
"Unit";"Zergling";"Larva";291;1
"Unit";"Zergling";"Larva";291;1
"Unit";"Zergling";"Larva";291;1
"Unit";"Zergling";"Larva";291;1
"Unit";"Zergling";"Larva";291;1
"Unit";"Zergling";"Larva";291;1
"Unit";"Zergling";"Larva";291;1
"Unit";"Zergling";"Larva";291;1
"Unit";"Zergling";"Larva";291;1
"Building";"CreepTumor";NA;291;0
"Unit";"Queen";"Hatchery";285;2
"Building";"Hatchery";NA;268;0
"Unit";"Zergling";"Larva";291;1
"Unit";"Zergling";"Larva";291;1
"Unit";"Zergling";"Larva";291;1
"Unit";"Zergling";"Larva";291;1
"Unit";"Zergling";"Larva";291;1
"Unit";"Zergling";"Larva";291;1
"Unit";"Zergling";"Larva";291;1
"Unit";"Zergling";"Larva";291;1
"Building";"Spire";NA;268;0
"Unit";"Queen";"Hatchery";285;2
"Unit";"Zergling";"Larva";345;1
"Unit";"Zergling";"Larva";345;1
"Unit";"Zergling";"Larva";345;1
"Unit";"Zergling";"Larva";345;1
"Unit";"Zergling";"Larva";347;1
"Unit";"Zergling";"Larva";347;1
"Unit";"Zergling";"Larva";347;1
"Unit";"Zergling";"Larva";347;1
"Unit";"Zergling";"Larva";347;1
"Unit";"Zergling";"Larva";347;1
"Unit";"Zergling";"Larva";347;1
"Unit";"Zergling";"Larva";347;1
"Unit";"Zergling";"Larva";347;1
"Unit";"Zergling";"Larva";347;1
"Unit";"Zergling";"Larva";347;1
"Unit";"Zergling";"Larva";347;1
"Unit";"Zergling";"Larva";347;1
"Unit";"Zergling";"Larva";347;1
"Unit";"Zergling";"Larva";347;1
"Unit";"Zergling";"Larva";347;1
"Unit";"Zergling";"Larva";347;1
"Unit";"Zergling";"Larva";347;1
"Unit";"Zergling";"Larva";347;1
"Unit";"Zergling";"Larva";347;1
"Unit";"Zergling";"Larva";347;1
"Unit";"Zergling";"Larva";347;1
"Building";"CreepTumor";NA;373;0
"Building";"CreepTumor";NA;373;0
"Unit";"Zergling";"Larva";373;1
"Unit";"Zergling";"Larva";373;1
"Unit";"Zergling";"Larva";373;1
"Unit";"Zergling";"Larva";373;1
"Unit";"Zergling";"Larva";373;1
"Unit";"Zergling";"Larva";373;1
"Unit";"Zergling";"Larva";373;1
"Unit";"Zergling";"Larva";373;1
"Unit";"Zergling";"Larva";373;1
"Unit";"Zergling";"Larva";373;1
"Unit";"Zergling";"Larva";373;1
"Unit";"Zergling";"Larva";373;1
"Unit";"Zergling";"Larva";373;1
"Unit";"Zergling";"Larva";373;1
"Unit";"Zergling";"Larva";373;1
"Unit";"Zergling";"Larva";373;1
"Unit";"Zergling";"Larva";373;1
"Unit";"Zergling";"Larva";373;1
"Unit";"Zergling";"Larva";373;1
"Unit";"Zergling";"Larva";373;1
"Unit";"Zergling";"Larva";373;1
"Unit";"Zergling";"Larva";373;1
"Unit";"Zergling";"Larva";373;1
"Unit";"Zergling";"Larva";373;1
"Unit";"Zergling";"Larva";373;1
"Unit";"Zergling";"Larva";373;1
"Unit";"Zergling";"Larva";373;1
"Unit";"Zergling";"Larva";373;1
"Unit";"Zergling";"Larva";373;1
"Unit";"Zergling";"Larva";373;1
"Unit";"Zergling";"Larva";373;1
"Unit";"Zergling";"Larva";373;1
"Unit";"Zergling";"Larva";373;1
"Unit";"Zergling";"Larva";373;1
"Unit";"Zergling";"Larva";373;1
"Unit";"Zergling";"Larva";373;1
"Upgrade";"EvolveMuscularAugments";"HydraliskDen";347;0
"Building";"CreepTumor";NA;409;0
"Building";"CreepTumor";NA;409;0
"Building";"CreepTumor";NA;409;0
"Unit";"Hydralisk";"Larva";373;2
"Unit";"Hydralisk";"Larva";373;2
"Unit";"Hydralisk";"Larva";373;2
"Unit";"Hydralisk";"Larva";373;2
"Unit";"Hydralisk";"Larva";373;2
"Unit";"Hydralisk";"Larva";373;2
"Unit";"Hydralisk";"Larva";373;2
"Unit";"Queen";"Hatchery";373;2
"Unit";"Zergling";"Larva";425;1
"Unit";"Zergling";"Larva";425;1
"Unit";"Zergling";"Larva";425;1
"Unit";"Zergling";"Larva";425;1
"Unit";"Zergling";"Larva";425;1
"Unit";"Zergling";"Larva";425;1
"Unit";"Zergling";"Larva";425;1
"Unit";"Zergling";"Larva";425;1
"Unit";"Zergling";"Larva";425;1
"Unit";"Zergling";"Larva";425;1
"Unit";"Zergling";"Larva";425;1
"Unit";"Zergling";"Larva";425;1
"Unit";"Zergling";"Larva";425;1
"Unit";"Zergling";"Larva";425;1
"Unit";"Zergling";"Larva";425;1
"Unit";"Zergling";"Larva";425;1
"Unit";"Zergling";"Larva";425;1
"Unit";"Zergling";"Larva";425;1
"Unit";"Zergling";"Larva";425;1
"Unit";"Zergling";"Larva";425;1
"Unit";"Zergling";"Larva";425;1
"Unit";"Zergling";"Larva";425;1
"Unit";"Zergling";"Larva";425;1
"Unit";"Zergling";"Larva";425;1
"Unit";"Zergling";"Larva";425;1
"Unit";"Zergling";"Larva";425;1
"Unit";"Zergling";"Larva";425;1
"Unit";"Zergling";"Larva";425;1
"Unit";"Zergling";"Larva";425;1
"Unit";"Zergling";"Larva";425;1
"Unit";"Zergling";"Larva";425;1
"Unit";"Zergling";"Larva";425;1
"Unit";"Zergling";"Larva";425;1
"Unit";"Zergling";"Larva";425;1
"Unit";"Zergling";"Larva";425;1
"Unit";"Zergling";"Larva";425;1
"Unit";"Zergling";"Larva";425;1
"Unit";"Zergling";"Larva";425;1
"Unit";"Zergling";"Larva";425;1
"Unit";"Zergling";"Larva";425;1
"Unit";"Zergling";"Larva";425;1
"Unit";"Zergling";"Larva";425;1
"Unit";"Zergling";"Larva";425;1
"Unit";"Zergling";"Larva";425;1
"Building";"CreepTumor";NA;425;0
"Building";"Extractor";NA;425;0
"Building";"Extractor";NA;425;0
"Unit";"Baneling";"Zergling";469;0
"Unit";"Baneling";"Zergling";469;0
"Unit";"Baneling";"Zergling";469;0
"Unit";"Baneling";"Zergling";469;0
"Unit";"Baneling";"Zergling";469;0
"Unit";"Baneling";"Zergling";469;0
"Unit";"Baneling";"Zergling";469;0
"Unit";"Baneling";"Zergling";469;0
"Building";"CreepTumor";NA;469;0
"Building";"CreepTumorQueen";NA;469;0
"Building";"CreepTumorQueen";NA;469;0
"Building";"CreepTumor";NA;469;0
"Building";"CreepTumor";NA;469;0
"Building";"CreepTumor";NA;469;0
"Building";"CreepTumor";NA;469;0
"Unit";"Baneling";"Zergling";469;0
"Unit";"Baneling";"Zergling";469;0
"Unit";"Baneling";"Zergling";469;0
"Unit";"Baneling";"Zergling";469;0
"Unit";"Baneling";"Zergling";469;0
"Unit";"Baneling";"Zergling";469;0
"Unit";"Baneling";"Zergling";469;0
"Unit";"Baneling";"Zergling";469;0
"Unit";"Baneling";"Zergling";469;0
"Unit";"Baneling";"Zergling";469;0
"Building";"CreepTumorQueen";NA;469;0
"Building";"CreepTumor";NA;469;0
"Building";"CreepTumorQueen";NA;469;0
"Building";"CreepTumor";NA;469;0
"Building";"CreepTumorQueen";NA;473;0
"Building";"CreepTumorQueen";NA;473;0
"Building";"CreepTumorQueen";NA;473;0
"Building";"CreepTumor";NA;473;0
"Building";"CreepTumorQueen";NA;473;0
"Building";"SporeCrawler";NA;473;0
"Building";"CreepTumor";NA;473;0
"Building";"UltraliskCavern";NA;469;0
"Building";"SporeCrawler";NA;473;0
"Building";"CreepTumorQueen";NA;473;0
"Building";"Hatchery";NA;469;0
"Building";"CreepTumor";NA;473;0
"Unit";"Viper";"Larva";473;3
"Unit";"Viper";"Larva";473;3
"Unit";"Viper";"Larva";473;3
"Unit";"Viper";"Larva";473;3
"Upgrade";"ZergGroundArmorsLevel3";"EvolutionChamber";469;0
"Upgrade";"ZergMeleeWeaponsLevel3";"EvolutionChamber";469;0
"Unit";"Corruptor";"Larva";473;2
"Unit";"Corruptor";"Larva";473;2
"Unit";"Corruptor";"Larva";473;2
"Unit";"Corruptor";"Larva";473;2
"Building";"SporeCrawler";NA;473;0
"Building";"SporeCrawler";NA;473;0
"Building";"CreepTumorQueen";NA;473;0
"Unit";"Baneling";"Zergling";473;0
"Unit";"Baneling";"Zergling";473;0
"Unit";"Baneling";"Zergling";473;0
"Unit";"Baneling";"Zergling";473;0
"Unit";"Baneling";"Zergling";473;0
"Unit";"Baneling";"Zergling";473;0
"Unit";"Baneling";"Zergling";473;0
"Unit";"Baneling";"Zergling";473;0
"Unit";"Baneling";"Zergling";473;0
"Unit";"Baneling";"Zergling";473;0
"Unit";"Baneling";"Zergling";473;0
"Unit";"Baneling";"Zergling";473;0
"Building";"CreepTumorQueen";NA;485;0
"Building";"CreepTumorQueen";NA;485;0
"Unit";"Zergling";"Larva";473;1
"Unit";"Zergling";"Larva";473;1
"Unit";"Zergling";"Larva";473;1
"Unit";"Zergling";"Larva";473;1
"Unit";"Zergling";"Larva";473;1
"Unit";"Zergling";"Larva";473;1
"Unit";"Zergling";"Larva";473;1
"Unit";"Zergling";"Larva";473;1
"Unit";"Zergling";"Larva";473;1
"Unit";"Zergling";"Larva";473;1
"Unit";"Zergling";"Larva";473;1
"Unit";"Zergling";"Larva";473;1
"Unit";"Zergling";"Larva";473;1
"Unit";"Zergling";"Larva";473;1
"Unit";"Zergling";"Larva";473;1
"Unit";"Zergling";"Larva";473;1
"Unit";"Zergling";"Larva";473;1
"Unit";"Zergling";"Larva";473;1
"Unit";"Zergling";"Larva";473;1
"Unit";"Zergling";"Larva";473;1
"Unit";"Zergling";"Larva";473;1
"Unit";"Zergling";"Larva";473;1
"Unit";"Zergling";"Larva";473;1
"Unit";"Zergling";"Larva";473;1
"Unit";"Zergling";"Larva";473;1
"Unit";"Zergling";"Larva";473;1
"Unit";"Zergling";"Larva";473;1
"Unit";"Zergling";"Larva";473;1
"Unit";"Zergling";"Larva";473;1
"Unit";"Zergling";"Larva";473;1
"Unit";"Zergling";"Larva";473;1
"Unit";"Zergling";"Larva";473;1
"Unit";"Zergling";"Larva";473;1
"Unit";"Zergling";"Larva";473;1
"Unit";"Zergling";"Larva";473;1
"Unit";"Zergling";"Larva";473;1
"Unit";"Zergling";"Larva";473;1
"Unit";"Zergling";"Larva";473;1
"Building";"CreepTumorQueen";NA;489;0
"Building";"CreepTumorQueen";NA;493;0
"Unit";"Queen";"Hatchery";473;2
"Unit";"Queen";"Hatchery";473;2
"Building";"CreepTumor";NA;543;0
"Building";"CreepTumorQueen";NA;543;0
"Building";"CreepTumor";NA;543;0
"Upgrade";"ChitinousPlating";"UltraliskCavern";473;0
"Building";"CreepTumor";NA;543;0
"Unit";"Ultralisk";"Larva";531;6
"Unit";"Ultralisk";"Larva";531;6
"Building";"CreepTumor";NA;543;0
"Building";"CreepTumor";NA;543;0
"Building";"CreepTumor";NA;543;0
"Building";"CreepTumor";NA;543;0
"Building";"CreepTumor";NA;543;0
"Building";"CreepTumor";NA;546;0
"Building";"CreepTumor";NA;546;0
"Building";"CreepTumor";NA;546;0
"Building";"SporeCrawler";NA;543;0
"Building";"SporeCrawler";NA;543;0
"Building";"CreepTumor";NA;558;0
"Building";"SpineCrawler";NA;543;0
"Building";"CreepTumor";NA;558;0
"Building";"Spire";NA;543;0
"Unit";"Zergling";"Larva";558;1
"Unit";"Zergling";"Larva";558;1
"Unit";"Zergling";"Larva";558;1
"Unit";"Zergling";"Larva";558;1
"Unit";"Zergling";"Larva";558;1
"Unit";"Zergling";"Larva";558;1
"Unit";"Zergling";"Larva";558;1
"Unit";"Zergling";"Larva";558;1
"Unit";"Zergling";"Larva";558;1
"Unit";"Zergling";"Larva";558;1
"Unit";"Zergling";"Larva";558;1
"Unit";"Zergling";"Larva";558;1
"Unit";"Zergling";"Larva";558;1
"Unit";"Zergling";"Larva";558;1
"Unit";"Zergling";"Larva";558;1
"Unit";"Zergling";"Larva";558;1
"Unit";"Zergling";"Larva";558;1
"Unit";"Zergling";"Larva";558;1
"Unit";"Zergling";"Larva";558;1
"Unit";"Zergling";"Larva";558;1
"Unit";"Zergling";"Larva";558;1
"Unit";"Zergling";"Larva";558;1
"Unit";"Zergling";"Larva";558;1
"Unit";"Zergling";"Larva";558;1
"Unit";"Zergling";"Larva";558;1
"Unit";"Zergling";"Larva";558;1
"Unit";"Zergling";"Larva";558;1
"Unit";"Zergling";"Larva";558;1
"Unit";"Zergling";"Larva";558;1
"Unit";"Zergling";"Larva";558;1
"Unit";"Zergling";"Larva";558;1
"Unit";"Zergling";"Larva";558;1
"Unit";"Zergling";"Larva";558;1
"Unit";"Zergling";"Larva";558;1
"Unit";"Zergling";"Larva";558;1
"Unit";"Zergling";"Larva";558;1
"Unit";"Zergling";"Larva";558;1
"Unit";"Zergling";"Larva";558;1
"Unit";"Ultralisk";"Larva";558;6
"Unit";"Ultralisk";"Larva";558;6
"Unit";"Ultralisk";"Larva";558;6
"Unit";"Ultralisk";"Larva";558;6
"Unit";"Ultralisk";"Larva";558;6
"Unit";"Zergling";"Larva";626;1
"Unit";"Zergling";"Larva";626;1
"Unit";"Zergling";"Larva";626;1
"Unit";"Zergling";"Larva";626;1
"Unit";"Zergling";"Larva";626;1
"Unit";"Zergling";"Larva";626;1
"Unit";"Zergling";"Larva";626;1
"Unit";"Zergling";"Larva";626;1
"Unit";"Zergling";"Larva";626;1
"Unit";"Zergling";"Larva";626;1
"Unit";"Zergling";"Larva";626;1
"Unit";"Zergling";"Larva";626;1
"Unit";"Zergling";"Larva";626;1
"Unit";"Zergling";"Larva";626;1
"Unit";"Zergling";"Larva";626;1
"Unit";"Zergling";"Larva";626;1
"Unit";"Zergling";"Larva";626;1
"Unit";"Zergling";"Larva";626;1
"Unit";"Zergling";"Larva";626;1
"Unit";"Zergling";"Larva";626;1
"Unit";"Zergling";"Larva";626;1
"Unit";"Zergling";"Larva";626;1
"Unit";"Zergling";"Larva";626;1
"Unit";"Zergling";"Larva";626;1
"Unit";"Zergling";"Larva";626;1
"Unit";"Zergling";"Larva";626;1
"Unit";"Zergling";"Larva";626;1
"Unit";"Zergling";"Larva";626;1
"Unit";"Zergling";"Larva";626;1
"Unit";"Zergling";"Larva";626;1
"Unit";"Hydralisk";"Larva";626;2
"Unit";"Hydralisk";"Larva";626;2
"Unit";"Hydralisk";"Larva";626;2
"Unit";"Hydralisk";"Larva";626;2
"Unit";"Hydralisk";"Larva";626;2
"Unit";"Hydralisk";"Larva";626;2
"Unit";"Hydralisk";"Larva";626;2
"Unit";"Hydralisk";"Larva";626;2
"Unit";"Hydralisk";"Larva";626;2
"Unit";"Hydralisk";"Larva";626;2
"Unit";"Hydralisk";"Larva";626;2
"Unit";"Hydralisk";"Larva";626;2
"Building";"CreepTumor";NA;656;0
"Building";"CreepTumor";NA;658;0
"Unit";"Viper";"Larva";628;3
"Unit";"Viper";"Larva";628;3
"Unit";"Viper";"Larva";634;3
"Unit";"Overlord";"Larva";680;0
"Building";"Extractor";NA;680;0
"Building";"Extractor";NA;680;0
"Building";"CreepTumor";NA;696;0
"Building";"CreepTumor";NA;696;0
"Building";"CreepTumor";NA;696;0
"Building";"CreepTumorQueen";NA;702;0
"Building";"CreepTumorQueen";NA;702;0
"Building";"CreepTumorQueen";NA;702;0
"Building";"Hatchery";NA;680;0
"Building";"CreepTumorQueen";NA;708;0
"Building";"Extractor";NA;702;0
"Unit";"Baneling";"Zergling";708;0
"Building";"Extractor";NA;702;0
"Unit";"Baneling";"Zergling";708;0
"Unit";"Baneling";"Zergling";708;0
"Unit";"Baneling";"Zergling";708;0
"Unit";"Baneling";"Zergling";708;0
"Unit";"Baneling";"Zergling";708;0
"Unit";"Baneling";"Zergling";708;0
"Unit";"Baneling";"Zergling";708;0
"Unit";"Baneling";"Zergling";708;0
"Unit";"Baneling";"Zergling";708;0
"Unit";"Baneling";"Zergling";708;0
"Unit";"Baneling";"Zergling";708;0
"Unit";"Baneling";"Zergling";708;0
"Unit";"Baneling";"Zergling";708;0
"Unit";"Baneling";"Zergling";708;0
"Unit";"Baneling";"Zergling";708;0
"Unit";"Baneling";"Zergling";708;0
"Unit";"Baneling";"Zergling";708;0
"Unit";"Baneling";"Zergling";708;0
"Unit";"Baneling";"Zergling";708;0
"Unit";"Baneling";"Zergling";708;0
"Unit";"Baneling";"Zergling";708;0
"Unit";"Baneling";"Zergling";708;0
"Unit";"Baneling";"Zergling";708;0
"Unit";"Baneling";"Zergling";708;0
"Unit";"Baneling";"Zergling";708;0
"Unit";"Baneling";"Zergling";708;0
"Unit";"Baneling";"Zergling";708;0
"Unit";"Baneling";"Zergling";708;0
"Unit";"Baneling";"Zergling";708;0
"Building";"CreepTumorQueen";NA;708;0
"Building";"CreepTumorQueen";NA;708;0
"Building";"CreepTumorQueen";NA;708;0
"Building";"CreepTumorQueen";NA;708;0
"Building";"CreepTumor";NA;708;0
"Unit";"Viper";"Larva";702;3
"Building";"CreepTumor";NA;708;0
"Building";"CreepTumor";NA;708;0
"Building";"CreepTumor";NA;708;0
"Building";"CreepTumor";NA;708;0
"Building";"CreepTumor";NA;708;0
"Building";"CreepTumor";NA;708;0
"Building";"CreepTumor";NA;708;0
"Building";"CreepTumor";NA;708;0
"Building";"CreepTumor";NA;708;0
"Building";"CreepTumorQueen";NA;708;0
"Building";"CreepTumorQueen";NA;708;0
"Building";"CreepTumorQueen";NA;708;0
"Building";"CreepTumorQueen";NA;708;0
"Building";"Extractor";NA;711;0
"Building";"Extractor";NA;711;0
"Unit";"Zergling";"Larva";711;1
"Unit";"Zergling";"Larva";711;1
"Unit";"Zergling";"Larva";711;1
"Unit";"Zergling";"Larva";711;1
"Unit";"Zergling";"Larva";711;1
"Unit";"Zergling";"Larva";711;1
"Unit";"Zergling";"Larva";711;1
"Unit";"Zergling";"Larva";711;1
"Unit";"Zergling";"Larva";711;1
"Unit";"Zergling";"Larva";711;1
"Unit";"Zergling";"Larva";711;1
"Unit";"Zergling";"Larva";711;1
"Building";"CreepTumor";NA;723;0
"Building";"CreepTumor";NA;723;0
"Building";"CreepTumor";NA;723;0
"Building";"CreepTumor";NA;723;0
"Building";"CreepTumor";NA;723;0
"Building";"CreepTumor";NA;723;0
"Building";"CreepTumor";NA;723;0
"Building";"CreepTumor";NA;723;0
"Building";"CreepTumor";NA;723;0
"Building";"CreepTumor";NA;723;0
"Building";"CreepTumor";NA;723;0
"Building";"CreepTumor";NA;723;0
"Building";"CreepTumor";NA;723;0
"Building";"CreepTumor";NA;723;0
"Building";"CreepTumor";NA;723;0
"Building";"CreepTumor";NA;723;0
"Building";"CreepTumor";NA;723;0
"Building";"CreepTumor";NA;723;0
"Building";"CreepTumorQueen";NA;723;0
"Unit";"Zergling";"Larva";723;1
"Unit";"Zergling";"Larva";723;1
"Unit";"Zergling";"Larva";723;1
"Unit";"Zergling";"Larva";723;1
"Unit";"Zergling";"Larva";723;1
"Unit";"Zergling";"Larva";723;1
"Unit";"Zergling";"Larva";723;1
"Unit";"Zergling";"Larva";723;1
"Unit";"Zergling";"Larva";723;1
"Unit";"Zergling";"Larva";723;1
"Unit";"Zergling";"Larva";723;1
"Unit";"Zergling";"Larva";723;1
"Unit";"Zergling";"Larva";723;1
"Unit";"Zergling";"Larva";723;1
"Unit";"Zergling";"Larva";723;1
"Unit";"Zergling";"Larva";723;1
"Unit";"Zergling";"Larva";723;1
"Unit";"Zergling";"Larva";723;1
"Building";"CreepTumor";NA;723;0
"Building";"CreepTumor";NA;741;0
"Building";"CreepTumor";NA;723;0
"Unit";"Zergling";"Larva";723;1
"Unit";"Zergling";"Larva";723;1
"Unit";"Zergling";"Larva";723;1
"Unit";"Zergling";"Larva";723;1
"Unit";"Zergling";"Larva";723;1
"Unit";"Zergling";"Larva";723;1
"Unit";"Zergling";"Larva";723;1
"Unit";"Zergling";"Larva";723;1
"Unit";"Zergling";"Larva";723;1
"Unit";"Zergling";"Larva";723;1
"Unit";"Zergling";"Larva";723;1
"Unit";"Zergling";"Larva";723;1
"Unit";"Zergling";"Larva";723;1
"Unit";"Zergling";"Larva";723;1
"Unit";"Zergling";"Larva";723;1
"Unit";"Zergling";"Larva";723;1
"Unit";"Zergling";"Larva";723;1
"Unit";"Zergling";"Larva";723;1
"Unit";"Zergling";"Larva";723;1
"Unit";"Zergling";"Larva";723;1
"Unit";"Zergling";"Larva";723;1
"Unit";"Zergling";"Larva";723;1
"Building";"CreepTumorQueen";NA;763;0
"Building";"CreepTumorQueen";NA;763;0
"Building";"Hatchery";NA;723;0
"Building";"CreepTumorQueen";NA;763;0
"Building";"CreepTumor";NA;763;0
"Building";"CreepTumor";NA;763;0
"Building";"CreepTumor";NA;763;0
"Building";"CreepTumor";NA;763;0
"Upgrade";"ZergMissileWeaponsLevel1";"EvolutionChamber";723;0
"Building";"SporeCrawler";NA;763;0
"Building";"Extractor";NA;763;0
"Building";"Extractor";NA;763;0
"Building";"CreepTumor";NA;783;0
"Building";"SpineCrawler";NA;763;0
"Building";"SpineCrawler";NA;763;0
"Building";"CreepTumorQueen";NA;783;0
"Building";"CreepTumorQueen";NA;783;0
"Building";"CreepTumorQueen";NA;783;0
"Upgrade";"Burrow";"Hatchery";763;0
"Building";"SporeCrawler";NA;783;0
"Building";"SporeCrawler";NA;783;0
"Building";"CreepTumor";NA;783;0
"Building";"CreepTumor";NA;783;0
"Building";"CreepTumorQueen";NA;783;0
"Building";"CreepTumor";NA;783;0
"Building";"CreepTumor";NA;783;0
"Building";"CreepTumor";NA;783;0
"Building";"CreepTumor";NA;783;0
"Building";"CreepTumor";NA;783;0
"Building";"CreepTumor";NA;783;0
"Building";"CreepTumor";NA;783;0
"Building";"CreepTumor";NA;783;0
"Building";"CreepTumor";NA;783;0
"Building";"CreepTumor";NA;783;0
"Building";"CreepTumor";NA;783;0
"Building";"CreepTumor";NA;783;0
"Building";"CreepTumorQueen";NA;783;0
"Building";"CreepTumorQueen";NA;783;0
"Building";"CreepTumorQueen";NA;783;0
"Building";"CreepTumor";NA;783;0
"Building";"CreepTumorQueen";NA;783;0
"Building";"CreepTumorQueen";NA;783;0
"Building";"CreepTumorQueen";NA;783;0
"Unit";"Zergling";"Larva";783;1
"Unit";"Zergling";"Larva";783;1
"Unit";"Zergling";"Larva";783;1
"Unit";"Zergling";"Larva";783;1
"Unit";"Zergling";"Larva";783;1
"Unit";"Zergling";"Larva";783;1
"Unit";"Zergling";"Larva";783;1
"Unit";"Zergling";"Larva";783;1
"Unit";"Zergling";"Larva";783;1
"Unit";"Zergling";"Larva";783;1
"Unit";"Zergling";"Larva";783;1
"Unit";"Zergling";"Larva";783;1
"Unit";"Zergling";"Larva";783;1
"Unit";"Zergling";"Larva";783;1
"Unit";"Zergling";"Larva";783;1
"Unit";"Zergling";"Larva";783;1
"Unit";"Zergling";"Larva";783;1
"Unit";"Zergling";"Larva";783;1
"Unit";"Zergling";"Larva";783;1
"Unit";"Zergling";"Larva";783;1
"Unit";"Zergling";"Larva";783;1
"Unit";"Zergling";"Larva";783;1
"Unit";"Zergling";"Larva";783;1
"Unit";"Zergling";"Larva";783;1
"Building";"CreepTumorQueen";NA;783;0
"Building";"CreepTumorQueen";NA;783;0
"Building";"CreepTumor";NA;783;0
"Building";"CreepTumorQueen";NA;783;0
"Building";"CreepTumor";NA;783;0
"Building";"CreepTumorQueen";NA;807;0
"Building";"CreepTumorQueen";NA;807;0
"Building";"CreepTumor";NA;807;0
"Building";"CreepTumor";NA;807;0
"Building";"CreepTumor";NA;807;0
"Building";"CreepTumor";NA;807;0
"Unit";"Baneling";"Zergling";807;0
"Building";"CreepTumor";NA;807;0
"Building";"CreepTumor";NA;807;0
"Building";"CreepTumor";NA;807;0
"Unit";"Baneling";"Zergling";807;0
"Unit";"Baneling";"Zergling";807;0
"Unit";"Baneling";"Zergling";807;0
"Unit";"Baneling";"Zergling";807;0
"Unit";"Baneling";"Zergling";807;0
"Unit";"Baneling";"Zergling";807;0
"Unit";"Baneling";"Zergling";807;0
"Unit";"Baneling";"Zergling";807;0
"Unit";"Baneling";"Zergling";807;0
"Building";"CreepTumor";NA;807;0
"Building";"CreepTumor";NA;807;0
"Building";"CreepTumor";NA;807;0
"Building";"CreepTumor";NA;807;0
"Building";"CreepTumor";NA;807;0
"Unit";"Baneling";"Zergling";807;0
"Unit";"Baneling";"Zergling";807;0
"Unit";"Baneling";"Zergling";807;0
"Unit";"Baneling";"Zergling";807;0
"Unit";"Baneling";"Zergling";807;0
"Unit";"Baneling";"Zergling";807;0
"Unit";"Baneling";"Zergling";807;0
"Unit";"Baneling";"Zergling";807;0
"Unit";"Baneling";"Zergling";807;0
"Unit";"Baneling";"Zergling";807;0
"Building";"CreepTumor";NA;807;0
"Building";"CreepTumor";NA;807;0
"Unit";"Zergling";"Larva";807;1
"Unit";"Zergling";"Larva";807;1
"Unit";"Zergling";"Larva";807;1
"Unit";"Zergling";"Larva";807;1
"Unit";"Zergling";"Larva";807;1
"Unit";"Zergling";"Larva";807;1
"Unit";"Zergling";"Larva";807;1
"Unit";"Zergling";"Larva";807;1
"Unit";"Zergling";"Larva";807;1
"Unit";"Zergling";"Larva";807;1
"Unit";"Zergling";"Larva";807;1
"Unit";"Zergling";"Larva";807;1
"Unit";"Zergling";"Larva";807;1
"Unit";"Zergling";"Larva";807;1
"Unit";"Zergling";"Larva";807;1
"Unit";"Zergling";"Larva";807;1
"Unit";"Zergling";"Larva";807;1
"Unit";"Zergling";"Larva";807;1
"Unit";"Zergling";"Larva";807;1
"Unit";"Zergling";"Larva";807;1
"Unit";"Zergling";"Larva";807;1
"Unit";"Zergling";"Larva";807;1
"Unit";"Zergling";"Larva";807;1
"Unit";"Zergling";"Larva";807;1
"Unit";"Zergling";"Larva";807;1
"Unit";"Zergling";"Larva";807;1
"Unit";"Zergling";"Larva";807;1
"Unit";"Zergling";"Larva";807;1
"Unit";"Zergling";"Larva";807;1
"Unit";"Zergling";"Larva";807;1
"Unit";"Zergling";"Larva";807;1
"Unit";"Zergling";"Larva";807;1
"Unit";"Zergling";"Larva";807;1
"Unit";"Zergling";"Larva";807;1
"Building";"CreepTumor";NA;807;0
"Building";"CreepTumor";NA;807;0
"Unit";"Hydralisk";"Larva";807;2
"Unit";"Hydralisk";"Larva";807;2
"Unit";"Hydralisk";"Larva";807;2
"Unit";"Hydralisk";"Larva";807;2
"Unit";"Hydralisk";"Larva";807;2
"Unit";"Hydralisk";"Larva";807;2
"Unit";"Hydralisk";"Larva";807;2
"Building";"CreepTumor";NA;817;0
"Building";"CreepTumor";NA;841;0
"Building";"CreepTumor";NA;841;0
"Building";"CreepTumor";NA;855;0
"Building";"CreepTumor";NA;855;0
"Unit";"Hydralisk";"Larva";841;2
"Unit";"Hydralisk";"Larva";841;2
"Unit";"Hydralisk";"Larva";841;2
"Unit";"Hydralisk";"Larva";841;2
"Unit";"Hydralisk";"Larva";841;2
"Unit";"Hydralisk";"Larva";841;2
"Unit";"Hydralisk";"Larva";841;2
"Unit";"Hydralisk";"Larva";841;2
"Unit";"Hydralisk";"Larva";841;2
"Unit";"Hydralisk";"Larva";841;2
"Unit";"Hydralisk";"Larva";841;2
"Unit";"Hydralisk";"Larva";841;2
"Unit";"Hydralisk";"Larva";841;2
"Unit";"Hydralisk";"Larva";841;2
"Unit";"Hydralisk";"Larva";841;2
"Unit";"Hydralisk";"Larva";841;2
"Building";"CreepTumor";NA;855;0
"Building";"CreepTumor";NA;855;0
"Building";"CreepTumor";NA;855;0
"Building";"CreepTumor";NA;887;0
"Building";"CreepTumor";NA;887;0
"Building";"Hatchery";NA;807;0
"Building";"Hatchery";NA;823;0
"Building";"Hatchery";NA;841;0
"Building";"CreepTumor";NA;895;0
"Unit";"Zergling";"Larva";895;1
"Unit";"Zergling";"Larva";895;1
"Unit";"Zergling";"Larva";895;1
"Unit";"Zergling";"Larva";895;1
"Unit";"Zergling";"Larva";895;1
"Unit";"Zergling";"Larva";895;1
"Unit";"Zergling";"Larva";895;1
"Unit";"Zergling";"Larva";895;1
"Unit";"Zergling";"Larva";895;1
"Unit";"Zergling";"Larva";895;1
"Unit";"Zergling";"Larva";895;1
"Unit";"Zergling";"Larva";895;1
"Unit";"Zergling";"Larva";895;1
"Unit";"Zergling";"Larva";895;1
"Unit";"Zergling";"Larva";895;1
"Unit";"Zergling";"Larva";895;1
"Unit";"Zergling";"Larva";895;1
"Unit";"Zergling";"Larva";895;1
"Unit";"Zergling";"Larva";895;1
"Unit";"Zergling";"Larva";895;1
"Unit";"Zergling";"Larva";895;1
"Unit";"Zergling";"Larva";895;1
"Building";"CreepTumor";NA;895;0
"Building";"CreepTumor";NA;895;0
"Building";"CreepTumor";NA;895;0
"Building";"CreepTumor";NA;895;0
"Building";"CreepTumor";NA;917;0
"Building";"CreepTumor";NA;917;0
"Unit";"Corruptor";"Larva";917;2
"Unit";"Corruptor";"Larva";917;2
"Unit";"Corruptor";"Larva";917;2
"Upgrade";"ZergMissileWeaponsLevel2";"EvolutionChamber";887;0
"Building";"CreepTumor";NA;923;0
"Building";"CreepTumor";NA;923;0
"Unit";"Corruptor";"Larva";917;2
"Unit";"Corruptor";"Larva";917;2
"Building";"CreepTumor";NA;927;0
"Building";"Extractor";NA;927;0
"Building";"Extractor";NA;927;0
"Unit";"Corruptor";"Larva";927;2
"Unit";"Corruptor";"Larva";927;2
"Unit";"Corruptor";"Larva";927;2
"Building";"CreepTumor";NA;927;0
"Building";"CreepTumor";NA;927;0
"Building";"SporeCrawler";NA;927;0
"Building";"SporeCrawler";NA;927;0
"Building";"SporeCrawler";NA;927;0
"Building";"CreepTumor";NA;933;0
"Building";"CreepTumor";NA;933;0
"Building";"CreepTumor";NA;933;0
"Building";"CreepTumor";NA;933;0
"Building";"CreepTumor";NA;933;0
"Building";"CreepTumor";NA;933;0
"Building";"CreepTumor";NA;933;0
"Building";"CreepTumor";NA;933;0
"Building";"CreepTumorQueen";NA;933;0
"Building";"CreepTumor";NA;933;0
"Building";"CreepTumor";NA;933;0
"Building";"CreepTumor";NA;933;0
"Building";"CreepTumor";NA;933;0
"Unit";"Corruptor";"Larva";933;2
"Unit";"Corruptor";"Larva";933;2
"Unit";"Corruptor";"Larva";933;2
"Unit";"Corruptor";"Larva";933;2
"Unit";"Zergling";"Larva";941;1
"Unit";"Zergling";"Larva";941;1
"Unit";"Zergling";"Larva";941;1
"Unit";"Zergling";"Larva";941;1
"Unit";"Zergling";"Larva";941;1
"Unit";"Zergling";"Larva";941;1
"Unit";"Zergling";"Larva";941;1
"Unit";"Zergling";"Larva";941;1
"Unit";"Zergling";"Larva";941;1
"Unit";"Zergling";"Larva";941;1
"Unit";"Zergling";"Larva";941;1
"Unit";"Zergling";"Larva";941;1
"Unit";"Zergling";"Larva";941;1
"Unit";"Zergling";"Larva";941;1
"Building";"CreepTumor";NA;941;0
"Unit";"Zergling";"Larva";941;1
"Unit";"Zergling";"Larva";941;1
"Unit";"Zergling";"Larva";941;1
"Unit";"Zergling";"Larva";941;1
"Unit";"Zergling";"Larva";941;1
"Unit";"Zergling";"Larva";941;1
"Unit";"Zergling";"Larva";941;1
"Unit";"Zergling";"Larva";941;1
"Unit";"Zergling";"Larva";941;1
"Unit";"Zergling";"Larva";941;1
"Unit";"Zergling";"Larva";941;1
"Unit";"Zergling";"Larva";941;1
"Unit";"Zergling";"Larva";941;1
"Unit";"Zergling";"Larva";941;1
"Unit";"Zergling";"Larva";941;1
"Unit";"Zergling";"Larva";941;1
"Building";"CreepTumor";NA;955;0
"Building";"CreepTumor";NA;955;0
"Building";"CreepTumor";NA;955;0
"Building";"CreepTumor";NA;955;0
"Building";"CreepTumor";NA;955;0
"Building";"CreepTumor";NA;957;0
"Building";"CreepTumor";NA;971;0
"Building";"SporeCrawler";NA;971;0
"Building";"SporeCrawler";NA;971;0
"Unit";"Zergling";"Larva";971;1
"Unit";"Zergling";"Larva";971;1
"Building";"SporeCrawler";NA;971;0
"Unit";"Zergling";"Larva";971;1
"Unit";"Zergling";"Larva";971;1
"Unit";"Zergling";"Larva";971;1
"Unit";"Zergling";"Larva";971;1
"Unit";"Zergling";"Larva";971;1
"Unit";"Zergling";"Larva";971;1
"Unit";"Zergling";"Larva";971;1
"Unit";"Zergling";"Larva";971;1
"Unit";"Zergling";"Larva";971;1
"Unit";"Zergling";"Larva";971;1
"Unit";"Zergling";"Larva";971;1
"Unit";"Zergling";"Larva";971;1
"Unit";"Zergling";"Larva";971;1
"Unit";"Zergling";"Larva";971;1
"Unit";"Zergling";"Larva";971;1
"Unit";"Zergling";"Larva";971;1
"Building";"SporeCrawler";NA;971;0
"Building";"CreepTumor";NA;971;0
"Unit";"Zergling";"Larva";989;1
"Unit";"Zergling";"Larva";989;1
"Unit";"Zergling";"Larva";989;1
"Unit";"Zergling";"Larva";989;1
"Unit";"Zergling";"Larva";989;1
"Unit";"Zergling";"Larva";989;1
"Unit";"Zergling";"Larva";989;1
"Unit";"Zergling";"Larva";989;1
"Unit";"Zergling";"Larva";989;1
"Unit";"Zergling";"Larva";989;1
"Unit";"Zergling";"Larva";989;1
"Unit";"Zergling";"Larva";989;1
"Unit";"Zergling";"Larva";989;1
"Unit";"Zergling";"Larva";989;1
"Unit";"Zergling";"Larva";989;1
"Unit";"Zergling";"Larva";989;1
"Unit";"Zergling";"Larva";989;1
"Unit";"Zergling";"Larva";989;1
"Unit";"Zergling";"Larva";989;1
"Unit";"Zergling";"Larva";989;1
"Unit";"Zergling";"Larva";989;1
"Unit";"Zergling";"Larva";989;1
"Unit";"Zergling";"Larva";989;1
"Unit";"Zergling";"Larva";989;1
"Unit";"Zergling";"Larva";989;1
"Unit";"Zergling";"Larva";989;1
"Unit";"Zergling";"Larva";989;1
"Unit";"Zergling";"Larva";989;1
"Unit";"Zergling";"Larva";989;1
"Unit";"Zergling";"Larva";989;1
"Unit";"Zergling";"Larva";989;1
"Unit";"Zergling";"Larva";989;1
"Unit";"Zergling";"Larva";989;1
"Unit";"Zergling";"Larva";989;1
"Unit";"Zergling";"Larva";989;1
"Unit";"Zergling";"Larva";989;1
"Unit";"Zergling";"Larva";989;1
"Unit";"Zergling";"Larva";989;1
"Unit";"Zergling";"Larva";989;1
"Unit";"Zergling";"Larva";989;1
"Unit";"Zergling";"Larva";989;1
"Unit";"Zergling";"Larva";989;1
"Unit";"Zergling";"Larva";989;1
"Unit";"Zergling";"Larva";989;1
"Unit";"Zergling";"Larva";989;1
"Unit";"Zergling";"Larva";989;1
"Unit";"Zergling";"Larva";989;1
"Unit";"Zergling";"Larva";989;1
"Unit";"Zergling";"Larva";989;1
"Unit";"Zergling";"Larva";989;1
"Unit";"Zergling";"Larva";989;1
"Unit";"Zergling";"Larva";989;1
"Unit";"Zergling";"Larva";989;1
"Unit";"Zergling";"Larva";989;1
"Unit";"Zergling";"Larva";989;1
"Unit";"Zergling";"Larva";989;1
"Unit";"Zergling";"Larva";989;1
"Unit";"Zergling";"Larva";989;1
"Unit";"Zergling";"Larva";989;1
"Unit";"Zergling";"Larva";989;1
"Unit";"Zergling";"Larva";989;1
"Unit";"Zergling";"Larva";989;1
"Unit";"Zergling";"Larva";989;1
"Unit";"Zergling";"Larva";989;1
"Building";"CreepTumor";NA;1029;0
"Building";"CreepTumor";NA;1029;0
"Upgrade";"ZergMissileWeaponsLevel3";"EvolutionChamber";971;0
"Building";"CreepTumor";NA;1053;0
"Building";"CreepTumor";NA;1053;0
"Building";"CreepTumor";NA;1053;0
"Building";"CreepTumor";NA;1053;0
"Building";"CreepTumor";NA;1053;0
"Building";"SporeCrawler";NA;1053;0
"Unit";"Baneling";"Zergling";1062;0
"Unit";"Baneling";"Zergling";1062;0
"Unit";"Baneling";"Zergling";1062;0
"Unit";"Baneling";"Zergling";1062;0
"Unit";"Baneling";"Zergling";1062;0
"Unit";"Baneling";"Zergling";1062;0
"Unit";"Baneling";"Zergling";1062;0
"Unit";"Baneling";"Zergling";1062;0
"Unit";"Baneling";"Zergling";1062;0
"Unit";"Baneling";"Zergling";1062;0
"Unit";"Baneling";"Zergling";1062;0
"Unit";"Baneling";"Zergling";1062;0
"Unit";"Baneling";"Zergling";1062;0
"Unit";"Baneling";"Zergling";1062;0
"Unit";"Baneling";"Zergling";1062;0
"Unit";"Baneling";"Zergling";1062;0
"Unit";"Baneling";"Zergling";1062;0
"Unit";"Baneling";"Zergling";1062;0
"Unit";"Baneling";"Zergling";1062;0
"Unit";"Baneling";"Zergling";1062;0
"Unit";"Baneling";"Zergling";1062;0
"Unit";"Baneling";"Zergling";1062;0
"Building";"SporeCrawler";NA;1062;0
"Building";"SpineCrawler";NA;1053;0
"Building";"CreepTumor";NA;1062;0
"Unit";"Hydralisk";"Larva";1062;2
"Unit";"Hydralisk";"Larva";1062;2
"Unit";"Hydralisk";"Larva";1062;2
"Unit";"Hydralisk";"Larva";1062;2
"Unit";"Hydralisk";"Larva";1062;2
"Unit";"Hydralisk";"Larva";1062;2
"Unit";"Hydralisk";"Larva";1062;2
"Unit";"Hydralisk";"Larva";1062;2
"Unit";"Hydralisk";"Larva";1062;2
"Unit";"Hydralisk";"Larva";1062;2
"Unit";"Hydralisk";"Larva";1062;2
"Unit";"Hydralisk";"Larva";1062;2
"Unit";"Hydralisk";"Larva";1062;2
"Unit";"Hydralisk";"Larva";1062;2
"Unit";"Hydralisk";"Larva";1062;2
"Unit";"Hydralisk";"Larva";1062;2
"Building";"SpineCrawler";NA;1053;0
"Building";"CreepTumor";NA;1062;0
"Building";"SpineCrawler";NA;1053;0
"Building";"CreepTumor";NA;1062;0
