"type";"unit_name";"on_building";"total_supply";"supply"
"Unit";"Overlord";"Larva";13;0
"Building";"Extractor";NA;19;0
"Unit";"Overlord";"Larva";22;0
"Building";"SpawningPool";NA;19;0
"Building";"Hatchery";NA;17;0
"Unit";"Zergling";"Larva";23;1
"Unit";"Zergling";"Larva";23;1
"Unit";"Zergling";"Larva";23;1
"Unit";"Zergling";"Larva";23;1
"Unit";"Queen";"Hatchery";23;2
"Unit";"Queen";"Hatchery";23;2
"Unit";"Overlord";"Larva";35;0
"Unit";"Queen";"Hatchery";35;2
"Building";"CreepTumorQueen";NA;46;0
"Building";"Hatchery";NA;32;0
"Unit";"Overlord";"Larva";46;0
"Unit";"Overlord";"Larva";46;0
"Unit";"Overlord";"Larva";46;0
"Unit";"Overlord";"Larva";46;0
"Unit";"Queen";"Hatchery";46;2
"Building";"CreepTumor";NA;57;0
"Unit";"Queen";"Hatchery";48;2
"Building";"CreepTumorQueen";NA;58;0
"Building";"Extractor";NA;58;0
"Building";"EvolutionChamber";NA;70;0
"Building";"SporeCrawler";NA;70;0
"Building";"CreepTumor";NA;74;0
"Building";"SporeCrawler";NA;70;0
"Unit";"Zergling";"Larva";74;1
"Unit";"Zergling";"Larva";74;1
"Unit";"Zergling";"Larva";74;1
"Unit";"Zergling";"Larva";74;1
"Unit";"Zergling";"Larva";74;1
"Unit";"Zergling";"Larva";74;1
"Unit";"Zergling";"Larva";74;1
"Unit";"Zergling";"Larva";74;1
"Building";"BanelingNest";NA;58;0
"Building";"CreepTumorQueen";NA;74;0
"Building";"CreepTumorQueen";NA;74;0
"Unit";"Zergling";"Larva";74;1
"Unit";"Zergling";"Larva";74;1
"Unit";"Zergling";"Larva";74;1
"Unit";"Zergling";"Larva";74;1
"Unit";"Zergling";"Larva";74;1
"Unit";"Zergling";"Larva";74;1
"Unit";"Zergling";"Larva";74;1
"Unit";"Zergling";"Larva";74;1
"Unit";"Zergling";"Larva";74;1
"Unit";"Zergling";"Larva";74;1
"Unit";"Zergling";"Larva";74;1
"Unit";"Zergling";"Larva";74;1
"Unit";"Zergling";"Larva";74;1
"Unit";"Zergling";"Larva";74;1
"Building";"Extractor";NA;82;0
"Unit";"Queen";"Hatchery";74;2
"Building";"EvolutionChamber";NA;82;0
"Unit";"Overlord";"Larva";82;0
"Building";"CreepTumorQueen";NA;99;0
"Building";"CreepTumorQueen";NA;101;0
"Unit";"Overlord";"Larva";99;0
"Building";"CreepTumor";NA;99;0
"Building";"CreepTumor";NA;99;0
"Building";"CreepTumor";NA;101;0
"Building";"CreepTumor";NA;101;0
"Building";"CreepTumor";NA;108;0
"Building";"Extractor";NA;108;0
"Building";"CreepTumor";NA;108;0
"Building";"CreepTumor";NA;108;0
"Unit";"Zergling";"Larva";108;1
"Unit";"Zergling";"Larva";108;1
"Unit";"Zergling";"Larva";108;1
"Unit";"Zergling";"Larva";108;1
"Unit";"Zergling";"Larva";108;1
"Unit";"Zergling";"Larva";108;1
"Unit";"Zergling";"Larva";108;1
"Unit";"Zergling";"Larva";108;1
"Unit";"Zergling";"Larva";108;1
"Unit";"Zergling";"Larva";108;1
"Unit";"Zergling";"Larva";108;1
"Unit";"Zergling";"Larva";108;1
"Unit";"Zergling";"Larva";108;1
"Unit";"Zergling";"Larva";108;1
"Unit";"Zergling";"Larva";108;1
"Unit";"Zergling";"Larva";108;1
"Unit";"Zergling";"Larva";108;1
"Unit";"Zergling";"Larva";108;1
"Unit";"Zergling";"Larva";108;1
"Unit";"Zergling";"Larva";108;1
"Unit";"Zergling";"Larva";108;1
"Unit";"Zergling";"Larva";108;1
"Building";"CreepTumorQueen";NA;108;0
"Building";"HydraliskDen";NA;108;0
"Building";"Hatchery";NA;101;0
"Unit";"Overlord";"Larva";130;0
"Unit";"Overlord";"Larva";130;0
"Unit";"Overlord";"Larva";130;0
"Unit";"Overlord";"Larva";130;0
"Unit";"Overlord";"Larva";130;0
"Upgrade";"ZergMeleeWeaponsLevel1";"EvolutionChamber";101;0
"Unit";"Overlord";"Larva";130;0
"Building";"Extractor";NA;130;0
"Unit";"Baneling";"Zergling";131;0
"Unit";"Baneling";"Zergling";131;0
"Unit";"Baneling";"Zergling";131;0
"Unit";"Baneling";"Zergling";131;0
"Unit";"Baneling";"Zergling";131;0
"Unit";"Baneling";"Zergling";131;0
"Unit";"Baneling";"Zergling";131;0
"Upgrade";"ZergGroundArmorsLevel1";"EvolutionChamber";108;0
"Building";"CreepTumorQueen";NA;138;0
"Unit";"Overlord";"Larva";143;0
"Unit";"Overlord";"Larva";143;0
"Building";"CreepTumorQueen";NA;143;0
"Building";"CreepTumorQueen";NA;143;0
"Building";"CreepTumorQueen";NA;143;0
"Building";"InfestationPit";NA;132;0
"Upgrade";"EvolveGroovedSpines";"HydraliskDen";132;0
"Unit";"Queen";"Hatchery";143;2
"Unit";"Hydralisk";"Larva";143;2
"Unit";"Hydralisk";"Larva";143;2
"Unit";"Hydralisk";"Larva";143;2
"Unit";"Hydralisk";"Larva";143;2
"Unit";"Hydralisk";"Larva";143;2
"Unit";"Hydralisk";"Larva";143;2
"Unit";"Hydralisk";"Larva";143;2
"Unit";"Hydralisk";"Larva";143;2
"Unit";"Hydralisk";"Larva";143;2
"Unit";"Hydralisk";"Larva";143;2
"Building";"Hatchery";NA;131;0
"Unit";"Zergling";"Larva";143;1
"Unit";"Zergling";"Larva";143;1
"Unit";"Zergling";"Larva";143;1
"Unit";"Zergling";"Larva";143;1
"Unit";"Zergling";"Larva";143;1
"Unit";"Zergling";"Larva";143;1
"Unit";"Zergling";"Larva";143;1
"Unit";"Zergling";"Larva";143;1
"Building";"Extractor";NA;143;0
"Unit";"Baneling";"Zergling";170;0
"Unit";"Baneling";"Zergling";170;0
"Unit";"Baneling";"Zergling";170;0
"Unit";"Baneling";"Zergling";170;0
"Unit";"Baneling";"Zergling";170;0
"Unit";"Baneling";"Zergling";170;0
"Unit";"Zergling";"Larva";170;1
"Unit";"Zergling";"Larva";170;1
"Unit";"Zergling";"Larva";170;1
"Unit";"Zergling";"Larva";170;1
"Unit";"Zergling";"Larva";170;1
"Unit";"Zergling";"Larva";170;1
"Unit";"Zergling";"Larva";170;1
"Unit";"Zergling";"Larva";170;1
"Unit";"Zergling";"Larva";170;1
"Unit";"Zergling";"Larva";170;1
"Unit";"Zergling";"Larva";170;1
"Unit";"Zergling";"Larva";170;1
"Unit";"Zergling";"Larva";170;1
"Unit";"Zergling";"Larva";170;1
"Unit";"Queen";"Hatchery";143;2
"Unit";"Zergling";"Larva";178;1
"Unit";"Zergling";"Larva";178;1
"Unit";"Zergling";"Larva";178;1
"Unit";"Zergling";"Larva";178;1
"Unit";"Hydralisk";"Larva";178;2
"Unit";"Hydralisk";"Larva";178;2
"Unit";"Hydralisk";"Larva";178;2
"Unit";"Hydralisk";"Larva";178;2
"Unit";"Hydralisk";"Larva";178;2
"Unit";"Hydralisk";"Larva";178;2
"Unit";"Zergling";"Larva";192;1
"Unit";"Zergling";"Larva";192;1
"Unit";"Zergling";"Larva";192;1
"Unit";"Zergling";"Larva";192;1
"Unit";"Zergling";"Larva";192;1
"Unit";"Zergling";"Larva";192;1
"Unit";"Zergling";"Larva";192;1
"Unit";"Zergling";"Larva";192;1
"Unit";"Zergling";"Larva";192;1
"Unit";"Zergling";"Larva";192;1
"Building";"CreepTumor";NA;210;0
"Building";"Extractor";NA;194;0
"Building";"Extractor";NA;194;0
"Unit";"Zergling";"Larva";220;1
"Unit";"Zergling";"Larva";220;1
"Unit";"Zergling";"Larva";220;1
"Unit";"Zergling";"Larva";220;1
"Unit";"Zergling";"Larva";220;1
"Unit";"Zergling";"Larva";220;1
"Unit";"Zergling";"Larva";220;1
"Unit";"Zergling";"Larva";220;1
"Unit";"Zergling";"Larva";220;1
"Unit";"Zergling";"Larva";220;1
"Unit";"Zergling";"Larva";220;1
"Unit";"Zergling";"Larva";220;1
"Unit";"Zergling";"Larva";220;1
"Unit";"Zergling";"Larva";220;1
"Unit";"Zergling";"Larva";220;1
"Unit";"Zergling";"Larva";220;1
"Unit";"Zergling";"Larva";220;1
"Unit";"Zergling";"Larva";220;1
"Unit";"Zergling";"Larva";220;1
"Unit";"Zergling";"Larva";220;1
"Unit";"Zergling";"Larva";220;1
"Unit";"Zergling";"Larva";220;1
"Unit";"Zergling";"Larva";220;1
"Unit";"Zergling";"Larva";220;1
"Unit";"Baneling";"Zergling";220;0
"Unit";"Baneling";"Zergling";220;0
"Unit";"Baneling";"Zergling";220;0
"Unit";"Baneling";"Zergling";220;0
"Unit";"Baneling";"Zergling";220;0
"Unit";"Baneling";"Zergling";220;0
"Unit";"Baneling";"Zergling";220;0
"Unit";"Zergling";"Larva";220;1
"Unit";"Zergling";"Larva";220;1
"Unit";"Zergling";"Larva";220;1
"Unit";"Zergling";"Larva";220;1
"Unit";"Zergling";"Larva";220;1
"Unit";"Zergling";"Larva";220;1
"Unit";"Zergling";"Larva";220;1
"Unit";"Zergling";"Larva";220;1
"Unit";"Zergling";"Larva";220;1
"Unit";"Zergling";"Larva";220;1
"Unit";"Zergling";"Larva";220;1
"Unit";"Zergling";"Larva";220;1
"Unit";"Zergling";"Larva";220;1
"Unit";"Zergling";"Larva";220;1
"Unit";"Zergling";"Larva";220;1
"Unit";"Zergling";"Larva";220;1
"Unit";"Zergling";"Larva";220;1
"Unit";"Zergling";"Larva";220;1
"Unit";"Zergling";"Larva";224;1
"Unit";"Zergling";"Larva";224;1
"Unit";"Zergling";"Larva";244;1
"Unit";"Zergling";"Larva";244;1
"Unit";"Zergling";"Larva";244;1
"Unit";"Zergling";"Larva";244;1
"Upgrade";"EvolveMuscularAugments";"HydraliskDen";194;0
"Unit";"Overlord";"Larva";244;0
"Unit";"Overlord";"Larva";244;0
"Unit";"Overlord";"Larva";244;0
"Upgrade";"ZergMissileWeaponsLevel1";"EvolutionChamber";178;0
"Unit";"Queen";"Hatchery";244;2
"Building";"CreepTumor";NA;268;0
"Unit";"Zergling";"Larva";268;1
"Unit";"Zergling";"Larva";268;1
"Unit";"Zergling";"Larva";268;1
"Unit";"Zergling";"Larva";268;1
"Unit";"Zergling";"Larva";268;1
"Unit";"Zergling";"Larva";268;1
"Unit";"Zergling";"Larva";268;1
"Unit";"Zergling";"Larva";268;1
"Unit";"Zergling";"Larva";268;1
"Unit";"Zergling";"Larva";268;1
"Unit";"Zergling";"Larva";268;1
"Unit";"Zergling";"Larva";268;1
"Unit";"Zergling";"Larva";268;1
"Unit";"Zergling";"Larva";268;1
"Unit";"Zergling";"Larva";268;1
"Unit";"Zergling";"Larva";268;1
"Unit";"Zergling";"Larva";268;1
"Unit";"Zergling";"Larva";268;1
"Unit";"Zergling";"Larva";268;1
"Unit";"Zergling";"Larva";268;1
"Unit";"Zergling";"Larva";268;1
"Unit";"Zergling";"Larva";268;1
"Unit";"Zergling";"Larva";268;1
"Unit";"Zergling";"Larva";268;1
"Unit";"Zergling";"Larva";268;1
"Unit";"Zergling";"Larva";268;1
"Building";"CreepTumorQueen";NA;268;0
"Unit";"Zergling";"Larva";268;1
"Unit";"Zergling";"Larva";268;1
"Unit";"Zergling";"Larva";268;1
"Unit";"Zergling";"Larva";268;1
"Unit";"Zergling";"Larva";268;1
"Unit";"Zergling";"Larva";268;1
"Unit";"Zergling";"Larva";268;1
"Unit";"Zergling";"Larva";268;1
"Unit";"Zergling";"Larva";268;1
"Unit";"Zergling";"Larva";268;1
"Unit";"Zergling";"Larva";268;1
"Unit";"Zergling";"Larva";268;1
"Unit";"Zergling";"Larva";268;1
"Unit";"Zergling";"Larva";268;1
"Unit";"Zergling";"Larva";268;1
"Unit";"Zergling";"Larva";268;1
"Unit";"Zergling";"Larva";296;1
"Unit";"Zergling";"Larva";296;1
"Unit";"Zergling";"Larva";296;1
"Unit";"Zergling";"Larva";296;1
"Unit";"Zergling";"Larva";296;1
"Unit";"Zergling";"Larva";296;1
"Unit";"Zergling";"Larva";296;1
"Unit";"Zergling";"Larva";296;1
"Building";"Spire";NA;244;0
"Unit";"Zergling";"Larva";315;1
"Unit";"Zergling";"Larva";315;1
"Unit";"Zergling";"Larva";315;1
"Unit";"Zergling";"Larva";315;1
"Unit";"Zergling";"Larva";315;1
"Unit";"Zergling";"Larva";315;1
"Unit";"Zergling";"Larva";315;1
"Unit";"Zergling";"Larva";315;1
"Unit";"Zergling";"Larva";315;1
"Unit";"Zergling";"Larva";315;1
"Upgrade";"ZergGroundArmorsLevel2";"EvolutionChamber";244;0
"Unit";"Zergling";"Larva";346;1
"Unit";"Zergling";"Larva";346;1
"Unit";"Zergling";"Larva";346;1
"Unit";"Zergling";"Larva";346;1
"Unit";"Zergling";"Larva";346;1
"Unit";"Zergling";"Larva";346;1
"Unit";"Zergling";"Larva";346;1
"Unit";"Zergling";"Larva";346;1
"Unit";"Zergling";"Larva";346;1
"Unit";"Zergling";"Larva";346;1
"Unit";"Zergling";"Larva";346;1
"Unit";"Zergling";"Larva";346;1
"Unit";"Zergling";"Larva";346;1
"Unit";"Zergling";"Larva";346;1
"Building";"Hatchery";NA;315;0
"Building";"CreepTumorQueen";NA;367;0
"Building";"CreepTumor";NA;367;0
"Building";"CreepTumorQueen";NA;367;0
"Building";"SpawningPool";NA;346;0
"Unit";"Zergling";"Larva";385;1
"Unit";"Zergling";"Larva";385;1
"Unit";"Zergling";"Larva";385;1
"Unit";"Zergling";"Larva";385;1
"Unit";"Zergling";"Larva";385;1
"Unit";"Zergling";"Larva";385;1
"Unit";"Zergling";"Larva";385;1
"Unit";"Zergling";"Larva";385;1
"Unit";"Zergling";"Larva";385;1
"Unit";"Zergling";"Larva";385;1
"Unit";"Zergling";"Larva";385;1
"Unit";"Zergling";"Larva";385;1
"Unit";"Zergling";"Larva";385;1
"Unit";"Zergling";"Larva";385;1
"Unit";"Zergling";"Larva";385;1
"Unit";"Zergling";"Larva";385;1
"Unit";"Zergling";"Larva";385;1
"Unit";"Zergling";"Larva";385;1
"Upgrade";"ZergMeleeWeaponsLevel2";"EvolutionChamber";333;0
"Unit";"Zergling";"Larva";385;1
"Unit";"Zergling";"Larva";385;1
"Unit";"Zergling";"Larva";385;1
"Unit";"Zergling";"Larva";385;1
"Unit";"Zergling";"Larva";385;1
"Unit";"Zergling";"Larva";385;1
"Unit";"Zergling";"Larva";385;1
"Unit";"Zergling";"Larva";385;1
"Unit";"Zergling";"Larva";385;1
"Unit";"Zergling";"Larva";385;1
"Unit";"Zergling";"Larva";385;1
"Unit";"Zergling";"Larva";385;1
"Unit";"Zergling";"Larva";397;1
"Unit";"Zergling";"Larva";397;1
"Building";"Extractor";NA;397;0
"Building";"Extractor";NA;397;0
"Unit";"Zergling";"Larva";397;1
"Unit";"Zergling";"Larva";397;1
"Unit";"Zergling";"Larva";397;1
"Unit";"Zergling";"Larva";397;1
"Unit";"Zergling";"Larva";397;1
"Unit";"Zergling";"Larva";397;1
"Unit";"Baneling";"Zergling";403;0
"Unit";"Baneling";"Zergling";403;0
"Unit";"Baneling";"Zergling";403;0
"Unit";"Baneling";"Zergling";403;0
"Unit";"Baneling";"Zergling";403;0
"Unit";"Baneling";"Zergling";403;0
"Unit";"Baneling";"Zergling";403;0
"Unit";"Baneling";"Zergling";403;0
"Unit";"Baneling";"Zergling";403;0
"Unit";"Baneling";"Zergling";403;0
"Unit";"Baneling";"Zergling";403;0
"Unit";"Baneling";"Zergling";403;0
"Building";"CreepTumor";NA;417;0
"Building";"CreepTumor";NA;417;0
"Building";"CreepTumor";NA;419;0
"Unit";"Corruptor";"Larva";415;2
"Unit";"Corruptor";"Larva";415;2
"Unit";"Corruptor";"Larva";415;2
"Unit";"Corruptor";"Larva";415;2
"Unit";"Corruptor";"Larva";415;2
"Unit";"Zergling";"Larva";423;1
"Unit";"Zergling";"Larva";423;1
"Unit";"Zergling";"Larva";423;1
"Unit";"Zergling";"Larva";423;1
"Unit";"Zergling";"Larva";423;1
"Unit";"Zergling";"Larva";423;1
"Unit";"Zergling";"Larva";423;1
"Unit";"Zergling";"Larva";423;1
"Unit";"Zergling";"Larva";423;1
"Unit";"Zergling";"Larva";423;1
"Unit";"Corruptor";"Larva";423;2
"Unit";"Corruptor";"Larva";423;2
"Unit";"Corruptor";"Larva";423;2
"Unit";"Corruptor";"Larva";423;2
"Unit";"Corruptor";"Larva";423;2
"Building";"Hatchery";NA;403;0
"Unit";"Zergling";"Larva";453;1
"Unit";"Zergling";"Larva";453;1
"Unit";"Zergling";"Larva";453;1
"Unit";"Zergling";"Larva";453;1
"Unit";"Zergling";"Larva";453;1
"Unit";"Zergling";"Larva";453;1
"Unit";"Zergling";"Larva";453;1
"Unit";"Zergling";"Larva";453;1
"Unit";"Zergling";"Larva";453;1
"Unit";"Zergling";"Larva";453;1
"Unit";"Zergling";"Larva";453;1
"Unit";"Zergling";"Larva";453;1
"Building";"Hatchery";NA;423;0
"Unit";"Zergling";"Larva";465;1
"Unit";"Zergling";"Larva";465;1
"Unit";"Zergling";"Larva";465;1
"Unit";"Zergling";"Larva";465;1
"Unit";"Zergling";"Larva";465;1
"Unit";"Zergling";"Larva";465;1
"Unit";"Zergling";"Larva";465;1
"Unit";"Zergling";"Larva";465;1
"Unit";"Zergling";"Larva";465;1
"Unit";"Zergling";"Larva";465;1
"Unit";"Zergling";"Larva";465;1
"Unit";"Zergling";"Larva";465;1
"Unit";"Zergling";"Larva";465;1
"Unit";"Zergling";"Larva";465;1
"Unit";"Zergling";"Larva";465;1
"Unit";"Zergling";"Larva";465;1
"Unit";"Zergling";"Larva";465;1
"Unit";"Zergling";"Larva";465;1
"Unit";"Zergling";"Larva";465;1
"Unit";"Zergling";"Larva";465;1
"Unit";"Zergling";"Larva";465;1
"Unit";"Zergling";"Larva";465;1
"Unit";"Zergling";"Larva";465;1
"Unit";"Zergling";"Larva";465;1
"Unit";"Zergling";"Larva";465;1
"Unit";"Zergling";"Larva";465;1
"Unit";"Zergling";"Larva";465;1
"Unit";"Zergling";"Larva";465;1
"Unit";"Zergling";"Larva";465;1
"Unit";"Zergling";"Larva";465;1
"Unit";"Zergling";"Larva";465;1
"Unit";"Zergling";"Larva";465;1
"Unit";"Zergling";"Larva";465;1
"Unit";"Zergling";"Larva";465;1
"Unit";"Zergling";"Larva";465;1
"Unit";"Zergling";"Larva";465;1
"Unit";"Zergling";"Larva";465;1
"Unit";"Zergling";"Larva";465;1
"Unit";"Zergling";"Larva";495;1
"Unit";"Zergling";"Larva";495;1
"Unit";"Zergling";"Larva";495;1
"Unit";"Zergling";"Larva";495;1
"Unit";"Zergling";"Larva";495;1
"Unit";"Zergling";"Larva";495;1
"Unit";"Zergling";"Larva";495;1
"Unit";"Zergling";"Larva";495;1
"Unit";"Zergling";"Larva";495;1
"Unit";"Zergling";"Larva";495;1
"Unit";"Zergling";"Larva";495;1
"Unit";"Zergling";"Larva";495;1
"Unit";"Zergling";"Larva";495;1
"Unit";"Zergling";"Larva";495;1
"Unit";"Zergling";"Larva";495;1
"Unit";"Zergling";"Larva";495;1
"Unit";"Zergling";"Larva";495;1
"Unit";"Zergling";"Larva";495;1
"Unit";"Queen";"Hatchery";495;2
"Unit";"Zergling";"Larva";521;1
"Unit";"Zergling";"Larva";521;1
"Unit";"Zergling";"Larva";521;1
"Unit";"Zergling";"Larva";521;1
"Unit";"Zergling";"Larva";521;1
"Unit";"Zergling";"Larva";521;1
"Unit";"Zergling";"Larva";521;1
"Unit";"Zergling";"Larva";521;1
"Unit";"Zergling";"Larva";521;1
"Unit";"Zergling";"Larva";521;1
"Unit";"Zergling";"Larva";521;1
"Unit";"Zergling";"Larva";521;1
"Unit";"Zergling";"Larva";521;1
"Unit";"Zergling";"Larva";521;1
"Unit";"Zergling";"Larva";521;1
"Unit";"Zergling";"Larva";521;1
"Unit";"Zergling";"Larva";521;1
"Unit";"Zergling";"Larva";521;1
"Unit";"Zergling";"Larva";521;1
"Unit";"Zergling";"Larva";521;1
"Unit";"Zergling";"Larva";521;1
"Unit";"Zergling";"Larva";521;1
"Unit";"Zergling";"Larva";521;1
"Unit";"Zergling";"Larva";521;1
"Unit";"Zergling";"Larva";521;1
"Unit";"Zergling";"Larva";521;1
"Upgrade";"ZergMeleeWeaponsLevel3";"EvolutionChamber";453;0
"Upgrade";"ZergGroundArmorsLevel3";"EvolutionChamber";453;0
"Unit";"Zergling";"Larva";521;1
"Unit";"Zergling";"Larva";521;1
"Unit";"Zergling";"Larva";521;1
"Unit";"Zergling";"Larva";521;1
"Unit";"Zergling";"Larva";521;1
"Unit";"Zergling";"Larva";521;1
"Unit";"Zergling";"Larva";521;1
"Unit";"Zergling";"Larva";521;1
"Unit";"Zergling";"Larva";521;1
"Unit";"Zergling";"Larva";521;1
"Unit";"Zergling";"Larva";521;1
"Unit";"Zergling";"Larva";521;1
"Unit";"Zergling";"Larva";521;1
"Unit";"Zergling";"Larva";521;1
"Building";"Hatchery";NA;465;0
"Unit";"Zergling";"Larva";563;1
"Unit";"Zergling";"Larva";563;1
"Unit";"Zergling";"Larva";563;1
"Unit";"Zergling";"Larva";563;1
"Unit";"Zergling";"Larva";563;1
"Unit";"Zergling";"Larva";563;1
"Unit";"Zergling";"Larva";563;1
"Unit";"Zergling";"Larva";563;1
"Unit";"Zergling";"Larva";563;1
"Unit";"Zergling";"Larva";563;1
"Unit";"Zergling";"Larva";563;1
"Unit";"Zergling";"Larva";563;1
"Unit";"Zergling";"Larva";563;1
"Unit";"Zergling";"Larva";563;1
"Unit";"Zergling";"Larva";563;1
"Unit";"Zergling";"Larva";563;1
"Unit";"Zergling";"Larva";563;1
"Unit";"Zergling";"Larva";563;1
"Unit";"Zergling";"Larva";563;1
"Unit";"Zergling";"Larva";563;1
"Unit";"Zergling";"Larva";563;1
"Unit";"Zergling";"Larva";563;1
"Unit";"Zergling";"Larva";585;1
"Unit";"Zergling";"Larva";585;1
"Unit";"Zergling";"Larva";585;1
"Unit";"Zergling";"Larva";585;1
"Unit";"Zergling";"Larva";585;1
"Unit";"Zergling";"Larva";585;1
"Unit";"Zergling";"Larva";585;1
"Unit";"Zergling";"Larva";585;1
"Unit";"Zergling";"Larva";585;1
"Unit";"Zergling";"Larva";585;1
"Unit";"Zergling";"Larva";585;1
"Unit";"Zergling";"Larva";585;1
"Unit";"Zergling";"Larva";585;1
"Unit";"Zergling";"Larva";585;1
"Unit";"Zergling";"Larva";585;1
"Unit";"Zergling";"Larva";585;1
"Unit";"Zergling";"Larva";585;1
"Unit";"Zergling";"Larva";585;1
"Unit";"Zergling";"Larva";585;1
"Unit";"Zergling";"Larva";585;1
"Unit";"Zergling";"Larva";585;1
"Unit";"Zergling";"Larva";585;1
"Unit";"Zergling";"Larva";585;1
"Unit";"Zergling";"Larva";585;1
