"type";"unit_name";"on_building";"total_supply";"supply"
"Unit";"Overlord";"Larva";12;0
"Building";"Extractor";NA;19;0
"Building";"SpawningPool";NA;19;0
"Unit";"Overlord";"Larva";21;0
"Building";"Hatchery";NA;17;0
"Unit";"Zergling";"Larva";22;1
"Unit";"Zergling";"Larva";22;1
"Unit";"Zergling";"Larva";22;1
"Unit";"Zergling";"Larva";22;1
"Unit";"Zergling";"Larva";22;1
"Unit";"Zergling";"Larva";22;1
"Unit";"Queen";"Hatchery";22;2
"Unit";"Queen";"Hatchery";22;2
"Building";"CreepTumorQueen";NA;36;0
"Unit";"Overlord";"Larva";37;0
"Unit";"Overlord";"Larva";37;0
"Unit";"Queen";"Hatchery";34;2
"Unit";"Queen";"Hatchery";37;2
"Building";"CreepTumorQueen";NA;40;0
"Building";"CreepTumor";NA;40;0
"Building";"CreepTumorQueen";NA;42;0
"Unit";"Overlord";"Larva";43;0
"Unit";"Overlord";"Larva";45;0
"Unit";"Queen";"Hatchery";42;2
"Building";"CreepTumorQueen";NA;48;0
"Building";"CreepTumor";NA;47;0
"Building";"CreepTumor";NA;48;0
"Unit";"Overlord";"Larva";48;0
"Building";"Hatchery";NA;38;0
"Building";"CreepTumorQueen";NA;56;0
"Building";"CreepTumor";NA;56;0
"Building";"CreepTumor";NA;56;0
"Unit";"Queen";"Hatchery";48;2
"Building";"Extractor";NA;56;0
"Building";"Extractor";NA;56;0
"Unit";"Overlord";"Larva";56;0
"Unit";"Zergling";"Larva";58;1
"Unit";"Zergling";"Larva";58;1
"Unit";"Zergling";"Larva";58;1
"Unit";"Zergling";"Larva";58;1
"Building";"CreepTumorQueen";NA;62;0
"Unit";"Zergling";"Larva";58;1
"Unit";"Zergling";"Larva";58;1
"Building";"CreepTumor";NA;60;0
"Building";"CreepTumorQueen";NA;65;0
"Building";"EvolutionChamber";NA;56;0
"Building";"CreepTumor";NA;65;0
"Building";"CreepTumor";NA;65;0
"Building";"EvolutionChamber";NA;56;0
"Unit";"Zergling";"Larva";65;1
"Unit";"Zergling";"Larva";65;1
"Unit";"Zergling";"Larva";65;1
"Unit";"Zergling";"Larva";65;1
"Unit";"Zergling";"Larva";65;1
"Unit";"Zergling";"Larva";65;1
"Unit";"Zergling";"Larva";65;1
"Unit";"Zergling";"Larva";65;1
"Unit";"Zergling";"Larva";65;1
"Unit";"Zergling";"Larva";65;1
"Building";"CreepTumor";NA;71;0
"Unit";"Zergling";"Larva";77;1
"Unit";"Zergling";"Larva";77;1
"Unit";"Zergling";"Larva";79;1
"Unit";"Zergling";"Larva";79;1
"Unit";"Zergling";"Larva";79;1
"Unit";"Zergling";"Larva";79;1
"Unit";"Zergling";"Larva";79;1
"Unit";"Zergling";"Larva";79;1
"Unit";"Zergling";"Larva";81;1
"Unit";"Zergling";"Larva";81;1
"Building";"CreepTumor";NA;83;0
"Building";"CreepTumor";NA;83;0
"Building";"CreepTumor";NA;83;0
"Unit";"Zergling";"Larva";83;1
"Unit";"Zergling";"Larva";83;1
"Unit";"Zergling";"Larva";93;1
"Unit";"Zergling";"Larva";93;1
"Unit";"Zergling";"Larva";93;1
"Unit";"Zergling";"Larva";93;1
"Unit";"Zergling";"Larva";93;1
"Unit";"Zergling";"Larva";93;1
"Unit";"Zergling";"Larva";93;1
"Unit";"Zergling";"Larva";93;1
"Building";"CreepTumorQueen";NA;93;0
"Building";"CreepTumorQueen";NA;93;0
"Building";"CreepTumorQueen";NA;93;0
"Unit";"Queen";"Hatchery";83;2
"Unit";"Overlord";"Larva";93;0
"Unit";"Zergling";"Larva";95;1
"Unit";"Zergling";"Larva";95;1
"Unit";"Zergling";"Larva";95;1
"Unit";"Zergling";"Larva";95;1
"Unit";"Zergling";"Larva";95;1
"Unit";"Zergling";"Larva";95;1
"Unit";"Overlord";"Larva";103;0
"Building";"CreepTumorQueen";NA;109;0
"Building";"CreepTumorQueen";NA;109;0
"Building";"CreepTumor";NA;109;0
"Building";"CreepTumorQueen";NA;109;0
"Building";"CreepTumor";NA;109;0
"Building";"CreepTumor";NA;109;0
"Building";"CreepTumor";NA;109;0
"Building";"CreepTumorQueen";NA;111;0
"Unit";"Overlord";"Larva";115;0
"Unit";"Overlord";"Larva";115;0
"Unit";"Overlord";"Larva";115;0
"Building";"CreepTumorQueen";NA;116;0
"Building";"CreepTumorQueen";NA;118;0
"Building";"CreepTumor";NA;119;0
"Building";"CreepTumor";NA;119;0
"Building";"CreepTumor";NA;119;0
"Building";"CreepTumor";NA;119;0
"Building";"CreepTumor";NA;119;0
"Building";"CreepTumor";NA;119;0
"Building";"CreepTumor";NA;119;0
"Unit";"Overlord";"Larva";119;0
"Building";"CreepTumor";NA;119;0
"Building";"CreepTumorQueen";NA;121;0
"Unit";"Overlord";"Larva";121;0
"Building";"CreepTumor";NA;121;0
"Building";"BanelingNest";NA;116;0
"Building";"CreepTumor";NA;121;0
"Building";"CreepTumor";NA;121;0
"Building";"CreepTumor";NA;121;0
"Building";"CreepTumor";NA;121;0
"Building";"CreepTumor";NA;121;0
"Upgrade";"ZergGroundArmorsLevel1";"EvolutionChamber";95;0
"Building";"CreepTumor";NA;125;0
"Building";"CreepTumor";NA;125;0
"Unit";"Overlord";"Larva";125;0
"Unit";"Overlord";"Larva";125;0
"Unit";"Overlord";"Larva";125;0
"Unit";"Overlord";"Larva";127;0
"Unit";"Zergling";"Larva";131;1
"Unit";"Zergling";"Larva";131;1
"Upgrade";"ZergMeleeWeaponsLevel1";"EvolutionChamber";107;0
"Unit";"Zergling";"Larva";131;1
"Unit";"Zergling";"Larva";131;1
"Unit";"Zergling";"Larva";131;1
"Unit";"Zergling";"Larva";131;1
"Unit";"Baneling";"Zergling";131;0
"Unit";"Baneling";"Zergling";131;0
"Unit";"Baneling";"Zergling";131;0
"Unit";"Baneling";"Zergling";131;0
"Unit";"Baneling";"Zergling";131;0
"Unit";"Baneling";"Zergling";131;0
"Unit";"Baneling";"Zergling";131;0
"Unit";"Baneling";"Zergling";131;0
"Unit";"Baneling";"Zergling";131;0
"Unit";"Baneling";"Zergling";131;0
"Unit";"Baneling";"Zergling";131;0
"Building";"Extractor";NA;131;0
"Building";"Extractor";NA;131;0
"Unit";"Overlord";"Larva";134;0
"Building";"Extractor";NA;134;0
"Building";"CreepTumor";NA;140;0
"Building";"CreepTumor";NA;140;0
"Building";"CreepTumor";NA;140;0
"Building";"CreepTumor";NA;140;0
"Building";"CreepTumor";NA;140;0
"Unit";"Overlord";"Larva";140;0
"Unit";"Overlord";"Larva";140;0
"Unit";"Zergling";"Larva";140;1
"Unit";"Zergling";"Larva";140;1
"Unit";"Zergling";"Larva";140;1
"Unit";"Zergling";"Larva";140;1
"Unit";"Zergling";"Larva";140;1
"Unit";"Zergling";"Larva";140;1
"Unit";"Zergling";"Larva";140;1
"Unit";"Zergling";"Larva";140;1
"Unit";"Zergling";"Larva";140;1
"Unit";"Zergling";"Larva";140;1
"Building";"CreepTumorQueen";NA;140;0
"Building";"CreepTumorQueen";NA;140;0
"Building";"CreepTumorQueen";NA;140;0
"Building";"CreepTumorQueen";NA;140;0
"Unit";"Overlord";"Larva";140;0
"Unit";"Overlord";"Larva";140;0
"Building";"CreepTumorQueen";NA;140;0
"Building";"CreepTumorQueen";NA;140;0
"Building";"CreepTumorQueen";NA;140;0
"Building";"CreepTumorQueen";NA;140;0
"Unit";"Overlord";"Larva";140;0
"Building";"CreepTumorQueen";NA;150;0
"Unit";"Zergling";"Larva";150;1
"Unit";"Zergling";"Larva";150;1
"Unit";"Zergling";"Larva";150;1
"Unit";"Zergling";"Larva";150;1
"Unit";"Zergling";"Larva";150;1
"Unit";"Zergling";"Larva";150;1
"Unit";"Zergling";"Larva";150;1
"Unit";"Zergling";"Larva";150;1
"Unit";"Zergling";"Larva";150;1
"Unit";"Zergling";"Larva";150;1
"Unit";"Zergling";"Larva";150;1
"Unit";"Zergling";"Larva";150;1
"Unit";"Zergling";"Larva";150;1
"Unit";"Zergling";"Larva";150;1
"Building";"CreepTumor";NA;164;0
"Building";"CreepTumor";NA;164;0
"Building";"CreepTumor";NA;164;0
"Building";"CreepTumor";NA;164;0
"Building";"CreepTumor";NA;164;0
"Building";"CreepTumor";NA;164;0
"Building";"CreepTumor";NA;164;0
"Building";"CreepTumorQueen";NA;164;0
"Unit";"Overlord";"Larva";150;0
"Building";"CreepTumorQueen";NA;164;0
"Building";"CreepTumor";NA;164;0
"Building";"CreepTumor";NA;164;0
"Building";"CreepTumor";NA;164;0
"Building";"CreepTumorQueen";NA;168;0
"Building";"Spire";NA;140;0
"Unit";"Overlord";"Larva";168;0
"Unit";"Zergling";"Larva";169;1
"Unit";"Zergling";"Larva";169;1
"Unit";"Zergling";"Larva";169;1
"Unit";"Zergling";"Larva";169;1
"Unit";"Zergling";"Larva";169;1
"Unit";"Zergling";"Larva";169;1
"Unit";"Zergling";"Larva";169;1
"Unit";"Zergling";"Larva";169;1
"Unit";"Zergling";"Larva";169;1
"Unit";"Zergling";"Larva";169;1
"Unit";"Baneling";"Zergling";173;0
"Unit";"Baneling";"Zergling";173;0
"Unit";"Baneling";"Zergling";173;0
"Unit";"Baneling";"Zergling";173;0
"Unit";"Baneling";"Zergling";173;0
"Unit";"Baneling";"Zergling";173;0
"Unit";"Baneling";"Zergling";173;0
"Unit";"Baneling";"Zergling";173;0
"Unit";"Baneling";"Zergling";173;0
"Unit";"Zergling";"Larva";173;1
"Unit";"Zergling";"Larva";173;1
"Unit";"Baneling";"Zergling";173;0
"Unit";"Baneling";"Zergling";173;0
"Building";"CreepTumorQueen";NA;173;0
"Building";"CreepTumor";NA;173;0
"Building";"CreepTumor";NA;173;0
"Building";"CreepTumorQueen";NA;173;0
"Building";"CreepTumor";NA;173;0
"Building";"CreepTumor";NA;173;0
"Building";"Hatchery";NA;140;0
"Unit";"Mutalisk";"Larva";183;2
"Unit";"Mutalisk";"Larva";183;2
"Unit";"Mutalisk";"Larva";183;2
"Unit";"Mutalisk";"Larva";183;2
"Building";"CreepTumor";NA;185;0
"Unit";"Mutalisk";"Larva";185;2
"Unit";"Mutalisk";"Larva";185;2
"Unit";"Mutalisk";"Larva";185;2
"Building";"CreepTumor";NA;193;0
"Building";"CreepTumor";NA;193;0
"Building";"CreepTumor";NA;193;0
"Building";"CreepTumor";NA;193;0
"Building";"CreepTumor";NA;193;0
"Building";"CreepTumor";NA;193;0
"Unit";"Mutalisk";"Larva";185;2
"Unit";"Mutalisk";"Larva";185;2
"Unit";"Overlord";"Larva";199;0
"Building";"CreepTumorQueen";NA;207;0
"Building";"CreepTumorQueen";NA;207;0
"Unit";"Mutalisk";"Larva";193;2
"Unit";"Mutalisk";"Larva";193;2
"Unit";"Zergling";"Larva";211;1
"Unit";"Zergling";"Larva";211;1
"Unit";"Zergling";"Larva";211;1
"Unit";"Zergling";"Larva";211;1
"Unit";"Zergling";"Larva";211;1
"Unit";"Zergling";"Larva";211;1
"Unit";"Zergling";"Larva";211;1
"Unit";"Zergling";"Larva";211;1
"Unit";"Zergling";"Larva";211;1
"Unit";"Zergling";"Larva";211;1
"Unit";"Zergling";"Larva";211;1
"Unit";"Zergling";"Larva";211;1
"Unit";"Zergling";"Larva";211;1
"Unit";"Zergling";"Larva";211;1
"Unit";"Zergling";"Larva";211;1
"Unit";"Zergling";"Larva";211;1
"Unit";"Zergling";"Larva";211;1
"Unit";"Zergling";"Larva";211;1
"Unit";"Zergling";"Larva";211;1
"Unit";"Zergling";"Larva";211;1
"Unit";"Baneling";"Zergling";215;0
"Unit";"Baneling";"Zergling";215;0
"Unit";"Baneling";"Zergling";215;0
"Unit";"Baneling";"Zergling";215;0
"Unit";"Baneling";"Zergling";215;0
"Unit";"Mutalisk";"Larva";215;2
"Unit";"Mutalisk";"Larva";215;2
"Unit";"Mutalisk";"Larva";215;2
"Unit";"Mutalisk";"Larva";215;2
"Unit";"Queen";"Hatchery";213;2
"Unit";"Queen";"Hatchery";215;2
"Unit";"Queen";"Hatchery";215;2
"Upgrade";"ZergMeleeWeaponsLevel2";"EvolutionChamber";183;0
"Upgrade";"ZergGroundArmorsLevel2";"EvolutionChamber";183;0
"Unit";"Mutalisk";"Larva";235;2
"Building";"CreepTumor";NA;246;0
"Building";"CreepTumor";NA;250;0
"Building";"CreepTumor";NA;253;0
"Building";"CreepTumor";NA;253;0
"Building";"CreepTumor";NA;253;0
"Building";"Extractor";NA;246;0
"Building";"Extractor";NA;246;0
"Unit";"Zergling";"Larva";258;1
"Unit";"Zergling";"Larva";258;1
"Unit";"Zergling";"Larva";258;1
"Unit";"Zergling";"Larva";258;1
"Unit";"Zergling";"Larva";258;1
"Unit";"Zergling";"Larva";258;1
"Unit";"Zergling";"Larva";258;1
"Unit";"Zergling";"Larva";258;1
"Unit";"Zergling";"Larva";258;1
"Unit";"Zergling";"Larva";258;1
"Unit";"Zergling";"Larva";258;1
"Unit";"Zergling";"Larva";258;1
"Unit";"Zergling";"Larva";258;1
"Unit";"Zergling";"Larva";258;1
"Unit";"Zergling";"Larva";258;1
"Unit";"Zergling";"Larva";258;1
"Unit";"Zergling";"Larva";258;1
"Unit";"Zergling";"Larva";258;1
"Unit";"Zergling";"Larva";258;1
"Unit";"Zergling";"Larva";258;1
"Unit";"Zergling";"Larva";258;1
"Unit";"Zergling";"Larva";258;1
"Unit";"Zergling";"Larva";258;1
"Unit";"Zergling";"Larva";258;1
"Unit";"Zergling";"Larva";258;1
"Unit";"Zergling";"Larva";258;1
"Unit";"Zergling";"Larva";258;1
"Unit";"Zergling";"Larva";258;1
"Unit";"Zergling";"Larva";258;1
"Unit";"Zergling";"Larva";258;1
"Unit";"Zergling";"Larva";258;1
"Unit";"Zergling";"Larva";258;1
"Unit";"Zergling";"Larva";258;1
"Unit";"Zergling";"Larva";258;1
"Building";"InfestationPit";NA;246;0
"Unit";"Baneling";"Zergling";264;0
"Unit";"Baneling";"Zergling";292;0
"Unit";"Baneling";"Zergling";292;0
"Unit";"Baneling";"Zergling";292;0
"Unit";"Baneling";"Zergling";292;0
"Unit";"Baneling";"Zergling";292;0
"Unit";"Baneling";"Zergling";292;0
"Unit";"Baneling";"Zergling";292;0
"Unit";"Baneling";"Zergling";292;0
"Unit";"Baneling";"Zergling";292;0
"Unit";"Baneling";"Zergling";292;0
"Unit";"Baneling";"Zergling";292;0
"Unit";"Baneling";"Zergling";292;0
"Unit";"Baneling";"Zergling";292;0
"Unit";"Mutalisk";"Larva";258;2
"Unit";"Mutalisk";"Larva";258;2
"Unit";"Mutalisk";"Larva";258;2
"Unit";"Overlord";"Larva";292;0
"Unit";"Overlord";"Larva";292;0
"Building";"CreepTumor";NA;292;0
"Unit";"Zergling";"Larva";292;1
"Unit";"Zergling";"Larva";292;1
"Unit";"Zergling";"Larva";292;1
"Unit";"Zergling";"Larva";292;1
"Unit";"Zergling";"Larva";292;1
"Unit";"Zergling";"Larva";292;1
"Unit";"Zergling";"Larva";292;1
"Unit";"Zergling";"Larva";292;1
"Unit";"Zergling";"Larva";292;1
"Unit";"Zergling";"Larva";292;1
"Unit";"Zergling";"Larva";292;1
"Unit";"Zergling";"Larva";292;1
"Unit";"Zergling";"Larva";292;1
"Unit";"Zergling";"Larva";292;1
"Unit";"Zergling";"Larva";292;1
"Unit";"Zergling";"Larva";292;1
"Unit";"Zergling";"Larva";292;1
"Unit";"Zergling";"Larva";292;1
"Unit";"Zergling";"Larva";292;1
"Unit";"Zergling";"Larva";292;1
"Building";"CreepTumorQueen";NA;298;0
"Building";"CreepTumorQueen";NA;304;0
"Unit";"Zergling";"Larva";300;1
"Unit";"Zergling";"Larva";300;1
"Unit";"Zergling";"Larva";308;1
"Unit";"Zergling";"Larva";308;1
"Unit";"Zergling";"Larva";308;1
"Unit";"Zergling";"Larva";308;1
"Unit";"Zergling";"Larva";308;1
"Unit";"Zergling";"Larva";308;1
"Unit";"Zergling";"Larva";308;1
"Unit";"Zergling";"Larva";308;1
"Unit";"Zergling";"Larva";308;1
"Unit";"Zergling";"Larva";308;1
"Unit";"Baneling";"Zergling";318;0
"Unit";"Baneling";"Zergling";318;0
"Unit";"Baneling";"Zergling";318;0
"Unit";"Baneling";"Zergling";318;0
"Unit";"Baneling";"Zergling";318;0
"Unit";"Baneling";"Zergling";318;0
"Unit";"Baneling";"Zergling";318;0
"Unit";"Baneling";"Zergling";318;0
"Unit";"Baneling";"Zergling";318;0
"Unit";"Baneling";"Zergling";318;0
"Unit";"Baneling";"Zergling";318;0
"Unit";"Baneling";"Zergling";318;0
"Unit";"Baneling";"Zergling";318;0
"Unit";"Baneling";"Zergling";318;0
"Unit";"Baneling";"Zergling";318;0
"Unit";"Baneling";"Zergling";318;0
"Unit";"Zergling";"Larva";318;1
"Unit";"Zergling";"Larva";318;1
"Unit";"Mutalisk";"Larva";318;2
"Unit";"Mutalisk";"Larva";318;2
"Unit";"Zergling";"Larva";318;1
"Unit";"Zergling";"Larva";318;1
"Unit";"Zergling";"Larva";318;1
"Unit";"Zergling";"Larva";318;1
"Unit";"Zergling";"Larva";318;1
"Unit";"Zergling";"Larva";318;1
"Unit";"Zergling";"Larva";318;1
"Unit";"Zergling";"Larva";318;1
"Building";"Hatchery";NA;258;0
"Unit";"Zergling";"Larva";318;1
"Unit";"Zergling";"Larva";318;1
"Unit";"Zergling";"Larva";318;1
"Unit";"Zergling";"Larva";318;1
"Unit";"Zergling";"Larva";318;1
"Unit";"Zergling";"Larva";318;1
"Unit";"Zergling";"Larva";318;1
"Unit";"Zergling";"Larva";318;1
"Unit";"Zergling";"Larva";318;1
"Unit";"Zergling";"Larva";318;1
"Unit";"Zergling";"Larva";330;1
"Unit";"Zergling";"Larva";330;1
"Unit";"Zergling";"Larva";330;1
"Unit";"Zergling";"Larva";330;1
"Unit";"Zergling";"Larva";330;1
"Unit";"Zergling";"Larva";330;1
"Unit";"Zergling";"Larva";330;1
"Unit";"Zergling";"Larva";330;1
"Building";"CreepTumorQueen";NA;330;0
"Unit";"Zergling";"Larva";330;1
"Unit";"Zergling";"Larva";330;1
"Building";"CreepTumorQueen";NA;330;0
"Unit";"Mutalisk";"Larva";364;2
"Unit";"Mutalisk";"Larva";364;2
"Unit";"Mutalisk";"Larva";364;2
"Unit";"Mutalisk";"Larva";364;2
"Unit";"Mutalisk";"Larva";364;2
"Unit";"Mutalisk";"Larva";364;2
"Unit";"Mutalisk";"Larva";364;2
"Building";"CreepTumor";NA;382;0
"Building";"CreepTumorQueen";NA;382;0
"Building";"CreepTumorQueen";NA;382;0
"Unit";"Mutalisk";"Larva";365;2
"Unit";"Mutalisk";"Larva";368;2
"Unit";"Mutalisk";"Larva";368;2
"Unit";"Mutalisk";"Larva";368;2
"Unit";"Mutalisk";"Larva";368;2
"Building";"CreepTumorQueen";NA;382;0
"Building";"CreepTumorQueen";NA;382;0
"Unit";"Queen";"Hatchery";364;2
"Building";"CreepTumorQueen";NA;382;0
"Building";"CreepTumorQueen";NA;382;0
"Unit";"Overlord";"Larva";382;0
"Unit";"Zergling";"Larva";382;1
"Unit";"Zergling";"Larva";382;1
"Unit";"Zergling";"Larva";382;1
"Unit";"Zergling";"Larva";382;1
"Unit";"Zergling";"Larva";382;1
"Unit";"Zergling";"Larva";382;1
"Unit";"Zergling";"Larva";382;1
"Unit";"Zergling";"Larva";382;1
"Unit";"Zergling";"Larva";382;1
"Unit";"Zergling";"Larva";382;1
"Unit";"Zergling";"Larva";382;1
"Unit";"Zergling";"Larva";382;1
"Unit";"Zergling";"Larva";382;1
"Unit";"Zergling";"Larva";382;1
"Unit";"Zergling";"Larva";382;1
"Unit";"Zergling";"Larva";382;1
"Unit";"Zergling";"Larva";382;1
"Unit";"Zergling";"Larva";382;1
"Unit";"Zergling";"Larva";382;1
"Unit";"Zergling";"Larva";382;1
"Unit";"Zergling";"Larva";382;1
"Unit";"Zergling";"Larva";382;1
"Unit";"Zergling";"Larva";382;1
"Unit";"Zergling";"Larva";382;1
"Unit";"Zergling";"Larva";382;1
"Unit";"Zergling";"Larva";382;1
"Unit";"Zergling";"Larva";382;1
"Unit";"Zergling";"Larva";382;1
"Unit";"Zergling";"Larva";382;1
"Unit";"Zergling";"Larva";382;1
"Unit";"Zergling";"Larva";382;1
"Unit";"Zergling";"Larva";382;1
"Unit";"Zergling";"Larva";382;1
"Unit";"Zergling";"Larva";382;1
"Unit";"Zergling";"Larva";382;1
"Unit";"Zergling";"Larva";382;1
"Building";"Extractor";NA;394;0
"Building";"Extractor";NA;394;0
"Unit";"Zergling";"Larva";430;1
"Unit";"Zergling";"Larva";430;1
"Unit";"Zergling";"Larva";430;1
"Unit";"Zergling";"Larva";430;1
"Unit";"Zergling";"Larva";430;1
"Unit";"Zergling";"Larva";430;1
"Unit";"Zergling";"Larva";430;1
"Unit";"Zergling";"Larva";430;1
"Unit";"Zergling";"Larva";430;1
"Unit";"Zergling";"Larva";430;1
"Unit";"Zergling";"Larva";430;1
"Unit";"Zergling";"Larva";430;1
"Unit";"Zergling";"Larva";430;1
"Unit";"Zergling";"Larva";430;1
"Unit";"Zergling";"Larva";430;1
"Unit";"Zergling";"Larva";430;1
"Unit";"Zergling";"Larva";430;1
"Unit";"Zergling";"Larva";430;1
"Building";"UltraliskCavern";NA;392;0
"Unit";"Baneling";"Zergling";448;0
"Unit";"Zergling";"Larva";448;1
"Unit";"Zergling";"Larva";448;1
"Unit";"Zergling";"Larva";448;1
"Unit";"Zergling";"Larva";448;1
"Unit";"Zergling";"Larva";448;1
"Unit";"Zergling";"Larva";448;1
"Unit";"Zergling";"Larva";448;1
"Unit";"Zergling";"Larva";448;1
"Unit";"Zergling";"Larva";448;1
"Unit";"Zergling";"Larva";448;1
"Unit";"Zergling";"Larva";448;1
"Unit";"Zergling";"Larva";448;1
"Unit";"Zergling";"Larva";448;1
"Unit";"Zergling";"Larva";448;1
"Unit";"Zergling";"Larva";448;1
"Unit";"Zergling";"Larva";448;1
"Unit";"Zergling";"Larva";448;1
"Unit";"Zergling";"Larva";448;1
"Unit";"Zergling";"Larva";448;1
"Unit";"Zergling";"Larva";448;1
"Unit";"Zergling";"Larva";448;1
"Unit";"Zergling";"Larva";448;1
"Unit";"Zergling";"Larva";448;1
"Unit";"Zergling";"Larva";448;1
"Unit";"Zergling";"Larva";448;1
"Unit";"Zergling";"Larva";448;1
"Building";"CreepTumorQueen";NA;448;0
"Building";"CreepTumorQueen";NA;448;0
"Building";"CreepTumor";NA;448;0
"Building";"CreepTumorQueen";NA;448;0
"Building";"CreepTumorQueen";NA;450;0
"Building";"CreepTumor";NA;450;0
"Building";"CreepTumor";NA;450;0
"Building";"CreepTumor";NA;450;0
"Building";"CreepTumor";NA;474;0
"Unit";"Overlord";"Larva";474;0
"Building";"CreepTumor";NA;474;0
"Building";"CreepTumor";NA;474;0
"Building";"CreepTumor";NA;474;0
"Building";"CreepTumor";NA;474;0
"Building";"CreepTumor";NA;474;0
"Unit";"Overlord";"Larva";474;0
"Unit";"Ultralisk";"Larva";474;6
"Unit";"Ultralisk";"Larva";474;6
"Unit";"Ultralisk";"Larva";474;6
"Upgrade";"ChitinousPlating";"UltraliskCavern";474;0
"Building";"CreepTumor";NA;492;0
"Building";"CreepTumor";NA;492;0
"Building";"CreepTumor";NA;492;0
"Building";"CreepTumor";NA;492;0
"Unit";"Overlord";"Larva";474;0
"Unit";"Overlord";"Larva";474;0
"Building";"CreepTumor";NA;492;0
"Building";"CreepTumorQueen";NA;492;0
"Building";"CreepTumorQueen";NA;492;0
"Building";"CreepTumorQueen";NA;492;0
"Building";"CreepTumorQueen";NA;492;0
"Building";"CreepTumor";NA;492;0
"Building";"CreepTumor";NA;492;0
"Building";"CreepTumor";NA;492;0
"Upgrade";"ZergMeleeWeaponsLevel3";"EvolutionChamber";448;0
"Unit";"Ultralisk";"Larva";474;6
"Unit";"Ultralisk";"Larva";474;6
"Unit";"Overlord";"Larva";492;0
"Upgrade";"Burrow";"Hatchery";474;0
"Building";"CreepTumorQueen";NA;504;0
"Building";"CreepTumorQueen";NA;504;0
"Building";"CreepTumor";NA;504;0
"Building";"CreepTumor";NA;504;0
"Building";"CreepTumor";NA;504;0
"Building";"CreepTumor";NA;504;0
"Upgrade";"ZergGroundArmorsLevel3";"EvolutionChamber";474;0
"Unit";"Overlord";"Larva";504;0
"Building";"SporeCrawler";NA;504;0
"Building";"SporeCrawler";NA;504;0
"Building";"SporeCrawler";NA;504;0
"Building";"SporeCrawler";NA;504;0
"Building";"SporeCrawler";NA;504;0
"Building";"SporeCrawler";NA;504;0
"Unit";"Zergling";"Larva";504;1
"Unit";"Zergling";"Larva";504;1
"Unit";"Zergling";"Larva";504;1
"Unit";"Zergling";"Larva";504;1
"Unit";"Zergling";"Larva";504;1
"Unit";"Zergling";"Larva";504;1
"Building";"CreepTumorQueen";NA;504;0
"Building";"CreepTumor";NA;504;0
"Building";"CreepTumor";NA;504;0
"Building";"Hatchery";NA;492;0
"Unit";"Ultralisk";"Larva";504;6
"Unit";"Ultralisk";"Larva";504;6
"Unit";"Ultralisk";"Larva";504;6
"Unit";"Ultralisk";"Larva";504;6
"Building";"CreepTumor";NA;510;0
"Building";"CreepTumor";NA;510;0
"Building";"CreepTumor";NA;534;0
"Building";"CreepTumor";NA;534;0
"Building";"CreepTumor";NA;534;0
"Building";"CreepTumor";NA;534;0
"Building";"CreepTumor";NA;534;0
"Unit";"Baneling";"Zergling";534;0
"Unit";"Baneling";"Zergling";534;0
"Unit";"Baneling";"Zergling";534;0
"Unit";"Baneling";"Zergling";534;0
"Unit";"Baneling";"Zergling";534;0
"Unit";"Baneling";"Zergling";534;0
"Unit";"Baneling";"Zergling";534;0
"Unit";"Baneling";"Zergling";534;0
"Unit";"Baneling";"Zergling";534;0
"Unit";"Baneling";"Zergling";534;0
"Unit";"Baneling";"Zergling";534;0
"Unit";"Baneling";"Zergling";534;0
"Unit";"Baneling";"Zergling";534;0
"Unit";"Baneling";"Zergling";534;0
"Unit";"Baneling";"Zergling";534;0
"Unit";"Baneling";"Zergling";534;0
"Unit";"Baneling";"Zergling";534;0
"Unit";"Baneling";"Zergling";534;0
"Unit";"Baneling";"Zergling";534;0
"Unit";"Baneling";"Zergling";534;0
"Unit";"Baneling";"Zergling";534;0
"Unit";"Baneling";"Zergling";534;0
"Unit";"Baneling";"Zergling";534;0
"Unit";"Baneling";"Zergling";534;0
"Unit";"Baneling";"Zergling";534;0
"Unit";"Baneling";"Zergling";534;0
"Unit";"Baneling";"Zergling";534;0
"Unit";"Baneling";"Zergling";534;0
"Unit";"Baneling";"Zergling";534;0
"Unit";"Baneling";"Zergling";534;0
"Unit";"Baneling";"Zergling";534;0
"Unit";"Baneling";"Zergling";534;0
"Unit";"Baneling";"Zergling";534;0
"Unit";"Baneling";"Zergling";534;0
"Unit";"Baneling";"Zergling";534;0
"Unit";"Baneling";"Zergling";534;0
"Unit";"Baneling";"Zergling";534;0
"Unit";"Baneling";"Zergling";534;0
"Unit";"Baneling";"Zergling";534;0
"Unit";"Baneling";"Zergling";534;0
"Unit";"Baneling";"Zergling";534;0
"Unit";"Baneling";"Zergling";534;0
"Unit";"Baneling";"Zergling";534;0
"Unit";"Baneling";"Zergling";534;0
"Unit";"Baneling";"Zergling";534;0
"Unit";"Baneling";"Zergling";534;0
"Unit";"Baneling";"Zergling";534;0
"Unit";"Baneling";"Zergling";534;0
"Unit";"Baneling";"Zergling";534;0
"Unit";"Baneling";"Zergling";534;0
"Unit";"Baneling";"Zergling";534;0
"Unit";"Baneling";"Zergling";534;0
"Unit";"Baneling";"Zergling";534;0
"Unit";"Baneling";"Zergling";534;0
"Unit";"Baneling";"Zergling";534;0
"Unit";"Baneling";"Zergling";534;0
"Unit";"Baneling";"Zergling";534;0
"Unit";"Baneling";"Zergling";534;0
"Unit";"Baneling";"Zergling";534;0
"Unit";"Baneling";"Zergling";534;0
"Unit";"Baneling";"Zergling";534;0
"Unit";"Baneling";"Zergling";534;0
"Unit";"Baneling";"Zergling";534;0
"Unit";"Baneling";"Zergling";534;0
"Unit";"Baneling";"Zergling";534;0
"Unit";"Baneling";"Zergling";534;0
"Unit";"Baneling";"Zergling";534;0
"Unit";"Baneling";"Zergling";534;0
"Unit";"Baneling";"Zergling";534;0
"Unit";"Baneling";"Zergling";534;0
"Unit";"Baneling";"Zergling";534;0
"Unit";"Baneling";"Zergling";534;0
"Unit";"Baneling";"Zergling";534;0
"Unit";"Baneling";"Zergling";534;0
"Unit";"Baneling";"Zergling";534;0
"Unit";"Baneling";"Zergling";534;0
"Unit";"Baneling";"Zergling";534;0
"Unit";"Baneling";"Zergling";534;0
"Unit";"Baneling";"Zergling";534;0
"Unit";"Baneling";"Zergling";534;0
"Unit";"Baneling";"Zergling";534;0
"Unit";"Baneling";"Zergling";534;0
"Unit";"Baneling";"Zergling";534;0
"Unit";"Baneling";"Zergling";534;0
"Unit";"Baneling";"Zergling";534;0
"Unit";"Baneling";"Zergling";534;0
"Unit";"Baneling";"Zergling";534;0
"Building";"CreepTumorQueen";NA;534;0
"Building";"CreepTumorQueen";NA;534;0
"Unit";"Overlord";"Larva";534;0
"Building";"Spire";NA;528;0
"Unit";"Zergling";"Larva";534;1
"Unit";"Zergling";"Larva";534;1
"Unit";"Zergling";"Larva";534;1
"Unit";"Zergling";"Larva";534;1
"Unit";"Zergling";"Larva";534;1
"Unit";"Zergling";"Larva";534;1
"Unit";"Zergling";"Larva";534;1
"Unit";"Zergling";"Larva";534;1
"Unit";"Zergling";"Larva";534;1
"Unit";"Zergling";"Larva";534;1
"Unit";"Zergling";"Larva";534;1
"Unit";"Zergling";"Larva";534;1
"Unit";"Zergling";"Larva";534;1
"Unit";"Zergling";"Larva";534;1
"Unit";"Zergling";"Larva";534;1
"Unit";"Zergling";"Larva";534;1
"Unit";"Zergling";"Larva";534;1
"Unit";"Zergling";"Larva";534;1
"Unit";"Zergling";"Larva";534;1
"Unit";"Zergling";"Larva";534;1
"Unit";"Zergling";"Larva";534;1
"Unit";"Zergling";"Larva";534;1
"Unit";"Zergling";"Larva";534;1
"Unit";"Zergling";"Larva";534;1
"Unit";"Zergling";"Larva";534;1
"Unit";"Zergling";"Larva";534;1
"Unit";"Zergling";"Larva";534;1
"Unit";"Zergling";"Larva";534;1
"Unit";"Zergling";"Larva";534;1
"Unit";"Zergling";"Larva";534;1
"Unit";"Zergling";"Larva";534;1
"Unit";"Zergling";"Larva";534;1
"Unit";"Zergling";"Larva";534;1
"Unit";"Zergling";"Larva";534;1
"Unit";"Zergling";"Larva";534;1
"Unit";"Zergling";"Larva";534;1
"Unit";"Zergling";"Larva";534;1
"Unit";"Zergling";"Larva";534;1
"Unit";"Zergling";"Larva";534;1
"Unit";"Zergling";"Larva";534;1
"Unit";"Zergling";"Larva";534;1
"Unit";"Zergling";"Larva";534;1
"Unit";"Zergling";"Larva";534;1
"Unit";"Zergling";"Larva";534;1
"Unit";"Zergling";"Larva";534;1
"Unit";"Zergling";"Larva";534;1
"Unit";"Zergling";"Larva";534;1
"Unit";"Zergling";"Larva";534;1
"Unit";"Zergling";"Larva";534;1
"Unit";"Zergling";"Larva";534;1
"Unit";"Zergling";"Larva";534;1
"Unit";"Zergling";"Larva";534;1
"Unit";"Zergling";"Larva";534;1
"Unit";"Zergling";"Larva";534;1
"Unit";"Zergling";"Larva";534;1
"Unit";"Zergling";"Larva";534;1
"Building";"CreepTumorQueen";NA;534;0
"Building";"CreepTumorQueen";NA;534;0
"Building";"CreepTumor";NA;534;0
"Building";"CreepTumor";NA;534;0
"Building";"CreepTumor";NA;534;0
"Building";"CreepTumor";NA;534;0
"Building";"CreepTumorQueen";NA;534;0
"Building";"CreepTumor";NA;534;0
"Building";"CreepTumor";NA;534;0
"Building";"CreepTumor";NA;534;0
"Building";"CreepTumorQueen";NA;534;0
"Building";"CreepTumorQueen";NA;534;0
"Building";"CreepTumorQueen";NA;534;0
"Building";"CreepTumorQueen";NA;590;0
"Unit";"Baneling";"Zergling";590;0
"Unit";"Baneling";"Zergling";590;0
"Unit";"Baneling";"Zergling";590;0
"Unit";"Baneling";"Zergling";590;0
"Unit";"Baneling";"Zergling";590;0
"Unit";"Baneling";"Zergling";590;0
"Unit";"Baneling";"Zergling";590;0
"Unit";"Baneling";"Zergling";590;0
"Unit";"Baneling";"Zergling";590;0
"Unit";"Baneling";"Zergling";590;0
"Unit";"Baneling";"Zergling";590;0
"Unit";"Baneling";"Zergling";590;0
"Unit";"Baneling";"Zergling";590;0
"Unit";"Baneling";"Zergling";590;0
"Unit";"Baneling";"Zergling";590;0
"Unit";"Baneling";"Zergling";590;0
"Unit";"Baneling";"Zergling";590;0
"Unit";"Baneling";"Zergling";590;0
"Unit";"Baneling";"Zergling";590;0
"Unit";"Baneling";"Zergling";590;0
"Unit";"Baneling";"Zergling";590;0
"Unit";"Baneling";"Zergling";590;0
"Unit";"Baneling";"Zergling";590;0
"Unit";"Baneling";"Zergling";590;0
"Unit";"Baneling";"Zergling";590;0
"Unit";"Baneling";"Zergling";590;0
"Unit";"Baneling";"Zergling";590;0
"Unit";"Baneling";"Zergling";590;0
"Unit";"Baneling";"Zergling";590;0
"Unit";"Baneling";"Zergling";590;0
"Unit";"Baneling";"Zergling";590;0
"Unit";"Baneling";"Zergling";590;0
"Unit";"Baneling";"Zergling";590;0
"Unit";"Baneling";"Zergling";590;0
"Unit";"Baneling";"Zergling";590;0
"Unit";"Baneling";"Zergling";590;0
"Unit";"Baneling";"Zergling";590;0
"Unit";"Baneling";"Zergling";590;0
"Unit";"Baneling";"Zergling";590;0
"Unit";"Baneling";"Zergling";590;0
"Unit";"Baneling";"Zergling";590;0
"Unit";"Baneling";"Zergling";590;0
"Unit";"Baneling";"Zergling";590;0
"Unit";"Baneling";"Zergling";590;0
"Unit";"Baneling";"Zergling";590;0
"Unit";"Baneling";"Zergling";590;0
"Unit";"Baneling";"Zergling";590;0
"Unit";"Baneling";"Zergling";590;0
"Unit";"Baneling";"Zergling";590;0
"Unit";"Baneling";"Zergling";590;0
"Unit";"Baneling";"Zergling";590;0
"Unit";"Baneling";"Zergling";590;0
"Unit";"Baneling";"Zergling";590;0
"Unit";"Baneling";"Zergling";590;0
"Building";"CreepTumor";NA;590;0
"Building";"CreepTumor";NA;590;0
"Building";"CreepTumor";NA;590;0
"Building";"CreepTumor";NA;590;0
"Building";"CreepTumor";NA;590;0
"Building";"CreepTumor";NA;590;0
"Building";"CreepTumor";NA;590;0
"Building";"CreepTumor";NA;590;0
"Building";"CreepTumor";NA;590;0
"Building";"CreepTumor";NA;590;0
"Building";"CreepTumor";NA;590;0
"Building";"CreepTumorQueen";NA;590;0
"Building";"CreepTumorQueen";NA;590;0
"Building";"CreepTumorQueen";NA;590;0
"Building";"CreepTumorQueen";NA;590;0
