"type";"unit_name";"on_building";"total_supply";"supply"
"Unit";"Overlord";"Larva";13;0
"Building";"Extractor";NA;18;0
"Unit";"Overlord";"Larva";20;0
"Building";"SpawningPool";NA;18;0
"Building";"Hatchery";NA;17;0
"Unit";"Zergling";"Larva";23;1
"Unit";"Zergling";"Larva";23;1
"Unit";"Zergling";"Larva";23;1
"Unit";"Zergling";"Larva";23;1
"Unit";"Queen";"Hatchery";22;2
"Unit";"Queen";"Hatchery";23;2
"Unit";"Overlord";"Larva";36;0
"Building";"CreepTumorQueen";NA;36;0
"Unit";"Queen";"Hatchery";34;2
"Unit";"Overlord";"Larva";40;0
"Building";"Hatchery";NA;31;0
"Unit";"Zergling";"Larva";46;1
"Unit";"Zergling";"Larva";46;1
"Unit";"Zergling";"Larva";46;1
"Unit";"Zergling";"Larva";46;1
"Unit";"Zergling";"Larva";46;1
"Unit";"Zergling";"Larva";46;1
"Building";"CreepTumor";NA;48;0
"Unit";"Overlord";"Larva";46;0
"Unit";"Queen";"Hatchery";42;2
"Building";"CreepTumorQueen";NA;60;0
"Unit";"Queen";"Hatchery";48;2
"Unit";"Overlord";"Larva";60;0
"Building";"Extractor";NA;63;0
"Building";"BanelingNest";NA;55;0
"Unit";"Zergling";"Larva";63;1
"Unit";"Zergling";"Larva";63;1
"Unit";"Zergling";"Larva";63;1
"Unit";"Zergling";"Larva";63;1
"Unit";"Zergling";"Larva";63;1
"Unit";"Zergling";"Larva";63;1
"Unit";"Queen";"Hatchery";58;2
"Building";"SporeCrawler";NA;65;0
"Building";"CreepTumor";NA;65;0
"Unit";"Overlord";"Larva";65;0
"Building";"CreepTumor";NA;76;0
"Building";"CreepTumorQueen";NA;77;0
"Building";"CreepTumorQueen";NA;77;0
"Building";"CreepTumorQueen";NA;77;0
"Unit";"Queen";"Hatchery";65;2
"Building";"SporeCrawler";NA;69;0
"Unit";"Overlord";"Larva";78;0
"Unit";"Zergling";"Larva";86;1
"Unit";"Zergling";"Larva";86;1
"Unit";"Zergling";"Larva";86;1
"Unit";"Zergling";"Larva";86;1
"Unit";"Zergling";"Larva";86;1
"Unit";"Zergling";"Larva";86;1
"Unit";"Zergling";"Larva";86;1
"Unit";"Zergling";"Larva";86;1
"Unit";"Zergling";"Larva";86;1
"Unit";"Zergling";"Larva";86;1
"Building";"Extractor";NA;97;0
"Building";"Extractor";NA;97;0
"Building";"CreepTumor";NA;108;0
"Unit";"Overlord";"Larva";108;0
"Unit";"Overlord";"Larva";108;0
"Unit";"Overlord";"Larva";108;0
"Building";"CreepTumor";NA;114;0
"Building";"Extractor";NA;114;0
"Building";"CreepTumor";NA;114;0
"Building";"CreepTumor";NA;114;0
"Building";"CreepTumor";NA;114;0
"Unit";"Overlord";"Larva";114;0
"Unit";"Overlord";"Larva";114;0
"Building";"CreepTumorQueen";NA;114;0
"Building";"CreepTumorQueen";NA;114;0
"Unit";"Overlord";"Larva";114;0
"Unit";"Overlord";"Larva";114;0
"Unit";"Overlord";"Larva";114;0
"Unit";"Overlord";"Larva";114;0
"Unit";"Overlord";"Larva";114;0
"Unit";"Overlord";"Larva";114;0
"Building";"CreepTumorQueen";NA;114;0
"Building";"HydraliskDen";NA;114;0
"Building";"CreepTumorQueen";NA;114;0
"Building";"CreepTumorQueen";NA;114;0
"Building";"CreepTumorQueen";NA;114;0
"Building";"CreepTumorQueen";NA;114;0
"Unit";"Baneling";"Zergling";114;0
"Unit";"Baneling";"Zergling";114;0
"Unit";"Baneling";"Zergling";114;0
"Unit";"Baneling";"Zergling";114;0
"Unit";"Baneling";"Zergling";114;0
"Unit";"Baneling";"Zergling";114;0
"Unit";"Baneling";"Zergling";114;0
"Unit";"Baneling";"Zergling";114;0
"Unit";"Baneling";"Zergling";114;0
"Unit";"Zergling";"Larva";123;1
"Unit";"Zergling";"Larva";123;1
"Unit";"Zergling";"Larva";123;1
"Unit";"Zergling";"Larva";123;1
"Building";"Hatchery";NA;114;0
"Building";"Hatchery";NA;114;0
"Unit";"Hydralisk";"Larva";127;2
"Unit";"Hydralisk";"Larva";127;2
"Unit";"Hydralisk";"Larva";127;2
"Unit";"Hydralisk";"Larva";127;2
"Unit";"Hydralisk";"Larva";127;2
"Unit";"Hydralisk";"Larva";127;2
"Unit";"Hydralisk";"Larva";127;2
"Unit";"Hydralisk";"Larva";127;2
"Building";"CreepTumor";NA;130;0
"Building";"CreepTumor";NA;130;0
"Building";"CreepTumor";NA;130;0
"Building";"CreepTumor";NA;130;0
"Building";"CreepTumor";NA;130;0
"Building";"CreepTumor";NA;130;0
"Building";"CreepTumor";NA;130;0
"Building";"Extractor";NA;130;0
"Unit";"Queen";"Hatchery";130;2
"Unit";"Zergling";"Larva";150;1
"Unit";"Zergling";"Larva";150;1
"Unit";"Zergling";"Larva";150;1
"Unit";"Zergling";"Larva";150;1
"Unit";"Zergling";"Larva";150;1
"Unit";"Zergling";"Larva";150;1
"Unit";"Zergling";"Larva";150;1
"Unit";"Zergling";"Larva";150;1
"Unit";"Zergling";"Larva";150;1
"Unit";"Zergling";"Larva";150;1
"Unit";"Zergling";"Larva";150;1
"Unit";"Zergling";"Larva";150;1
"Unit";"Zergling";"Larva";150;1
"Unit";"Zergling";"Larva";150;1
"Building";"CreepTumorQueen";NA;150;0
"Building";"CreepTumorQueen";NA;158;0
"Building";"CreepTumorQueen";NA;159;0
"Building";"CreepTumor";NA;159;0
"Building";"CreepTumor";NA;159;0
"Building";"CreepTumorQueen";NA;159;0
"Building";"CreepTumorQueen";NA;159;0
"Building";"CreepTumorQueen";NA;159;0
"Unit";"Zergling";"Larva";150;1
"Unit";"Zergling";"Larva";150;1
"Unit";"Zergling";"Larva";150;1
"Unit";"Zergling";"Larva";150;1
"Unit";"Zergling";"Larva";150;1
"Unit";"Zergling";"Larva";150;1
"Unit";"Zergling";"Larva";150;1
"Unit";"Zergling";"Larva";150;1
"Unit";"Zergling";"Larva";173;1
"Unit";"Zergling";"Larva";173;1
"Unit";"Zergling";"Larva";173;1
"Unit";"Zergling";"Larva";173;1
"Unit";"Zergling";"Larva";173;1
"Unit";"Zergling";"Larva";173;1
"Building";"Extractor";NA;173;0
"Unit";"Zergling";"Larva";173;1
"Unit";"Zergling";"Larva";173;1
"Unit";"Zergling";"Larva";175;1
"Unit";"Zergling";"Larva";175;1
"Unit";"Zergling";"Larva";175;1
"Unit";"Zergling";"Larva";175;1
"Unit";"Zergling";"Larva";175;1
"Unit";"Zergling";"Larva";175;1
"Building";"CreepTumor";NA;186;0
"Building";"CreepTumor";NA;186;0
"Building";"CreepTumor";NA;186;0
"Building";"CreepTumor";NA;186;0
"Building";"CreepTumor";NA;186;0
"Building";"CreepTumor";NA;186;0
"Upgrade";"EvolveGroovedSpines";"HydraliskDen";150;0
"Building";"CreepTumor";NA;192;0
"Building";"CreepTumor";NA;192;0
"Unit";"Queen";"Hatchery";159;2
"Unit";"Zergling";"Larva";184;1
"Unit";"Zergling";"Larva";184;1
"Unit";"Zergling";"Larva";185;1
"Unit";"Zergling";"Larva";185;1
"Unit";"Zergling";"Larva";185;1
"Unit";"Zergling";"Larva";185;1
"Unit";"Zergling";"Larva";185;1
"Unit";"Zergling";"Larva";185;1
"Unit";"Zergling";"Larva";185;1
"Unit";"Zergling";"Larva";185;1
"Unit";"Zergling";"Larva";185;1
"Unit";"Zergling";"Larva";185;1
"Unit";"Zergling";"Larva";185;1
"Unit";"Zergling";"Larva";185;1
"Building";"InfestationPit";NA;173;0
"Unit";"Zergling";"Larva";192;1
"Unit";"Zergling";"Larva";192;1
"Unit";"Zergling";"Larva";216;1
"Unit";"Zergling";"Larva";216;1
"Unit";"Zergling";"Larva";216;1
"Unit";"Zergling";"Larva";216;1
"Unit";"Zergling";"Larva";216;1
"Unit";"Zergling";"Larva";216;1
"Unit";"Zergling";"Larva";216;1
"Unit";"Zergling";"Larva";216;1
"Unit";"Zergling";"Larva";216;1
"Unit";"Zergling";"Larva";216;1
"Unit";"Zergling";"Larva";216;1
"Unit";"Zergling";"Larva";216;1
"Unit";"Zergling";"Larva";216;1
"Unit";"Zergling";"Larva";216;1
"Unit";"Zergling";"Larva";216;1
"Unit";"Zergling";"Larva";216;1
"Unit";"Zergling";"Larva";216;1
"Unit";"Zergling";"Larva";216;1
"Unit";"Zergling";"Larva";216;1
"Unit";"Zergling";"Larva";216;1
"Unit";"Zergling";"Larva";216;1
"Unit";"Zergling";"Larva";216;1
"Building";"Hatchery";NA;173;0
"Building";"CreepTumor";NA;252;0
"Building";"InfestationPit";NA;218;0
"Unit";"Baneling";"Zergling";244;0
"Building";"CreepTumor";NA;252;0
"Building";"CreepTumor";NA;252;0
"Unit";"Baneling";"Zergling";244;0
"Unit";"Baneling";"Zergling";244;0
"Building";"CreepTumor";NA;252;0
"Unit";"Baneling";"Zergling";244;0
"Unit";"Baneling";"Zergling";244;0
"Unit";"Baneling";"Zergling";244;0
"Unit";"Baneling";"Zergling";244;0
"Unit";"Baneling";"Zergling";244;0
"Unit";"Baneling";"Zergling";244;0
"Building";"CreepTumor";NA;252;0
"Unit";"Baneling";"Zergling";245;0
"Unit";"Baneling";"Zergling";245;0
"Unit";"Baneling";"Zergling";247;0
"Unit";"Baneling";"Zergling";247;0
"Unit";"Baneling";"Zergling";249;0
"Unit";"Baneling";"Zergling";249;0
"Unit";"Baneling";"Zergling";251;0
"Unit";"Baneling";"Zergling";252;0
"Building";"CreepTumor";NA;252;0
"Building";"CreepTumorQueen";NA;252;0
"Building";"CreepTumor";NA;252;0
"Building";"CreepTumor";NA;252;0
"Building";"CreepTumor";NA;252;0
"Building";"CreepTumor";NA;252;0
"Building";"CreepTumorQueen";NA;252;0
"Building";"CreepTumor";NA;252;0
"Building";"CreepTumorQueen";NA;252;0
"Building";"CreepTumorQueen";NA;252;0
"Building";"EvolutionChamber";NA;244;0
"Building";"EvolutionChamber";NA;244;0
"Unit";"Zergling";"Larva";252;1
"Unit";"Zergling";"Larva";252;1
"Unit";"Zergling";"Larva";252;1
"Unit";"Zergling";"Larva";252;1
"Unit";"Zergling";"Larva";252;1
"Unit";"Zergling";"Larva";252;1
"Unit";"Zergling";"Larva";252;1
"Unit";"Zergling";"Larva";252;1
"Unit";"Zergling";"Larva";252;1
"Unit";"Zergling";"Larva";252;1
"Unit";"Zergling";"Larva";252;1
"Unit";"Zergling";"Larva";252;1
"Unit";"Zergling";"Larva";252;1
"Unit";"Zergling";"Larva";252;1
"Unit";"Zergling";"Larva";252;1
"Unit";"Zergling";"Larva";252;1
"Unit";"Zergling";"Larva";252;1
"Unit";"Zergling";"Larva";252;1
"Unit";"Zergling";"Larva";252;1
"Unit";"Zergling";"Larva";252;1
"Unit";"Zergling";"Larva";252;1
"Unit";"Zergling";"Larva";252;1
"Unit";"Zergling";"Larva";252;1
"Unit";"Zergling";"Larva";252;1
"Unit";"Zergling";"Larva";252;1
"Unit";"Zergling";"Larva";252;1
"Unit";"Zergling";"Larva";252;1
"Unit";"Zergling";"Larva";252;1
"Unit";"Zergling";"Larva";252;1
"Unit";"Zergling";"Larva";252;1
"Unit";"Zergling";"Larva";252;1
"Unit";"Zergling";"Larva";252;1
"Building";"EvolutionChamber";NA;252;0
"Upgrade";"EvolveMuscularAugments";"HydraliskDen";218;0
"Building";"Extractor";NA;252;0
"Building";"CreepTumor";NA;252;0
"Unit";"Overlord";"Larva";252;0
"Unit";"Overlord";"Larva";252;0
"Building";"CreepTumor";NA;284;0
"Building";"CreepTumor";NA;284;0
"Building";"CreepTumor";NA;284;0
"Building";"CreepTumor";NA;284;0
"Building";"CreepTumorQueen";NA;284;0
"Building";"CreepTumorQueen";NA;284;0
"Building";"CreepTumorQueen";NA;284;0
"Building";"CreepTumorQueen";NA;284;0
"Unit";"Hydralisk";"Larva";284;2
"Unit";"Hydralisk";"Larva";284;2
"Unit";"Hydralisk";"Larva";284;2
"Unit";"Hydralisk";"Larva";284;2
"Unit";"Hydralisk";"Larva";284;2
"Unit";"Hydralisk";"Larva";284;2
"Unit";"Hydralisk";"Larva";284;2
"Unit";"Hydralisk";"Larva";284;2
"Unit";"Hydralisk";"Larva";284;2
"Building";"CreepTumorQueen";NA;284;0
"Building";"CreepTumorQueen";NA;284;0
"Building";"CreepTumorQueen";NA;284;0
"Building";"CreepTumorQueen";NA;284;0
"Upgrade";"Burrow";"Hatchery";252;0
"Unit";"Zergling";"Larva";302;1
"Unit";"Zergling";"Larva";302;1
"Unit";"Zergling";"Larva";302;1
"Unit";"Zergling";"Larva";302;1
"Unit";"Baneling";"Zergling";302;0
"Unit";"Baneling";"Zergling";302;0
"Unit";"Baneling";"Zergling";302;0
"Unit";"Baneling";"Zergling";302;0
"Unit";"Baneling";"Zergling";302;0
"Unit";"Baneling";"Zergling";302;0
"Unit";"Baneling";"Zergling";302;0
"Unit";"Baneling";"Zergling";302;0
"Unit";"Baneling";"Zergling";302;0
"Unit";"Baneling";"Zergling";302;0
"Unit";"Baneling";"Zergling";302;0
"Unit";"Baneling";"Zergling";302;0
"Unit";"Baneling";"Zergling";302;0
"Unit";"Baneling";"Zergling";302;0
"Unit";"Baneling";"Zergling";302;0
"Unit";"Baneling";"Zergling";302;0
"Unit";"Baneling";"Zergling";302;0
"Unit";"Baneling";"Zergling";302;0
"Unit";"Baneling";"Zergling";302;0
"Unit";"Baneling";"Zergling";302;0
"Building";"CreepTumor";NA;309;0
"Building";"CreepTumor";NA;309;0
"Building";"CreepTumor";NA;309;0
"Building";"CreepTumor";NA;309;0
"Building";"CreepTumor";NA;309;0
"Building";"CreepTumor";NA;309;0
"Building";"CreepTumor";NA;309;0
"Building";"CreepTumorQueen";NA;309;0
"Building";"CreepTumorQueen";NA;309;0
"Building";"CreepTumorQueen";NA;309;0
"Upgrade";"ZergMissileWeaponsLevel1";"EvolutionChamber";302;0
"Upgrade";"ZergMeleeWeaponsLevel1";"EvolutionChamber";302;0
"Upgrade";"ZergGroundArmorsLevel1";"EvolutionChamber";302;0
"Building";"UltraliskCavern";NA;309;0
"Unit";"Zergling";"Larva";309;1
"Unit";"Zergling";"Larva";309;1
"Unit";"Zergling";"Larva";309;1
"Unit";"Zergling";"Larva";309;1
"Unit";"Zergling";"Larva";309;1
"Unit";"Zergling";"Larva";309;1
"Unit";"Zergling";"Larva";309;1
"Unit";"Zergling";"Larva";309;1
"Unit";"Zergling";"Larva";309;1
"Unit";"Zergling";"Larva";309;1
"Unit";"Zergling";"Larva";309;1
"Unit";"Zergling";"Larva";309;1
"Unit";"Zergling";"Larva";309;1
"Unit";"Zergling";"Larva";309;1
"Unit";"Zergling";"Larva";309;1
"Unit";"Zergling";"Larva";309;1
"Unit";"Zergling";"Larva";309;1
"Unit";"Zergling";"Larva";309;1
"Unit";"Zergling";"Larva";309;1
"Unit";"Zergling";"Larva";309;1
"Unit";"Zergling";"Larva";309;1
"Unit";"Zergling";"Larva";309;1
"Unit";"Zergling";"Larva";309;1
"Unit";"Zergling";"Larva";309;1
"Unit";"Zergling";"Larva";309;1
"Unit";"Zergling";"Larva";309;1
"Unit";"Zergling";"Larva";309;1
"Unit";"Zergling";"Larva";309;1
"Unit";"Zergling";"Larva";309;1
"Unit";"Zergling";"Larva";309;1
"Unit";"Zergling";"Larva";309;1
"Unit";"Zergling";"Larva";309;1
"Unit";"Zergling";"Larva";309;1
"Unit";"Zergling";"Larva";309;1
"Unit";"Zergling";"Larva";309;1
"Unit";"Zergling";"Larva";309;1
"Unit";"Zergling";"Larva";309;1
"Unit";"Zergling";"Larva";309;1
"Unit";"Zergling";"Larva";309;1
"Unit";"Zergling";"Larva";309;1
"Unit";"Zergling";"Larva";309;1
"Unit";"Zergling";"Larva";309;1
"Unit";"Zergling";"Larva";309;1
"Unit";"Zergling";"Larva";309;1
"Unit";"Zergling";"Larva";309;1
"Unit";"Zergling";"Larva";309;1
"Unit";"Zergling";"Larva";309;1
"Unit";"Zergling";"Larva";309;1
"Unit";"Zergling";"Larva";309;1
"Unit";"Zergling";"Larva";309;1
"Unit";"Zergling";"Larva";309;1
"Unit";"Zergling";"Larva";309;1
"Unit";"Zergling";"Larva";309;1
"Unit";"Zergling";"Larva";309;1
"Unit";"Zergling";"Larva";309;1
"Unit";"Zergling";"Larva";309;1
"Building";"Hatchery";NA;309;0
"Building";"Hatchery";NA;309;0
"Building";"Hatchery";NA;309;0
"Unit";"Zergling";"Larva";365;1
"Unit";"Zergling";"Larva";365;1
"Unit";"Zergling";"Larva";365;1
"Unit";"Zergling";"Larva";365;1
"Unit";"Zergling";"Larva";365;1
"Unit";"Zergling";"Larva";365;1
"Unit";"Zergling";"Larva";365;1
"Unit";"Zergling";"Larva";365;1
"Unit";"Zergling";"Larva";365;1
"Unit";"Zergling";"Larva";365;1
"Unit";"Zergling";"Larva";365;1
"Unit";"Zergling";"Larva";365;1
"Unit";"Zergling";"Larva";365;1
"Unit";"Zergling";"Larva";365;1
"Unit";"Zergling";"Larva";365;1
"Unit";"Zergling";"Larva";365;1
"Unit";"Zergling";"Larva";365;1
"Unit";"Zergling";"Larva";365;1
"Unit";"Zergling";"Larva";365;1
"Unit";"Zergling";"Larva";365;1
"Building";"CreepTumor";NA;375;0
"Unit";"Ultralisk";"Larva";309;6
"Unit";"Ultralisk";"Larva";309;6
"Unit";"Ultralisk";"Larva";309;6
"Unit";"Baneling";"Zergling";375;0
"Unit";"Baneling";"Zergling";375;0
"Unit";"Baneling";"Zergling";375;0
"Unit";"Baneling";"Zergling";375;0
"Unit";"Baneling";"Zergling";375;0
"Unit";"Baneling";"Zergling";375;0
"Unit";"Baneling";"Zergling";375;0
"Unit";"Baneling";"Zergling";375;0
"Unit";"Baneling";"Zergling";375;0
"Unit";"Baneling";"Zergling";375;0
"Unit";"Baneling";"Zergling";375;0
"Unit";"Baneling";"Zergling";375;0
"Unit";"Baneling";"Zergling";375;0
"Unit";"Baneling";"Zergling";375;0
"Unit";"Baneling";"Zergling";375;0
"Unit";"Baneling";"Zergling";375;0
"Unit";"Baneling";"Zergling";375;0
"Unit";"Baneling";"Zergling";375;0
"Unit";"Baneling";"Zergling";375;0
"Unit";"Baneling";"Zergling";375;0
"Unit";"Baneling";"Zergling";375;0
"Unit";"Zergling";"Larva";375;1
"Unit";"Zergling";"Larva";375;1
"Unit";"Zergling";"Larva";375;1
"Unit";"Zergling";"Larva";375;1
"Unit";"Zergling";"Larva";375;1
"Unit";"Zergling";"Larva";375;1
"Unit";"Zergling";"Larva";375;1
"Unit";"Zergling";"Larva";375;1
"Unit";"Zergling";"Larva";375;1
"Unit";"Zergling";"Larva";375;1
"Unit";"Zergling";"Larva";375;1
"Unit";"Zergling";"Larva";375;1
"Unit";"Zergling";"Larva";375;1
"Unit";"Zergling";"Larva";375;1
"Unit";"Zergling";"Larva";385;1
"Unit";"Zergling";"Larva";385;1
"Unit";"Zergling";"Larva";391;1
"Unit";"Zergling";"Larva";391;1
"Unit";"Ultralisk";"Larva";365;6
"Unit";"Ultralisk";"Larva";365;6
"Unit";"Ultralisk";"Larva";365;6
"Unit";"Ultralisk";"Larva";365;6
"Upgrade";"ChitinousPlating";"UltraliskCavern";365;0
"Unit";"Zergling";"Larva";427;1
"Unit";"Zergling";"Larva";427;1
"Unit";"Zergling";"Larva";439;1
"Unit";"Zergling";"Larva";439;1
"Unit";"Zergling";"Larva";439;1
"Unit";"Zergling";"Larva";439;1
"Unit";"Zergling";"Larva";439;1
"Unit";"Zergling";"Larva";439;1
"Unit";"Zergling";"Larva";439;1
"Unit";"Zergling";"Larva";439;1
"Unit";"Zergling";"Larva";439;1
"Unit";"Zergling";"Larva";439;1
"Unit";"Zergling";"Larva";439;1
"Unit";"Zergling";"Larva";439;1
"Unit";"Zergling";"Larva";439;1
"Unit";"Zergling";"Larva";439;1
"Unit";"Zergling";"Larva";445;1
"Unit";"Zergling";"Larva";445;1
"Unit";"Zergling";"Larva";445;1
"Unit";"Zergling";"Larva";445;1
"Unit";"Baneling";"Zergling";461;0
"Unit";"Baneling";"Zergling";461;0
"Unit";"Baneling";"Zergling";461;0
"Unit";"Baneling";"Zergling";461;0
"Unit";"Baneling";"Zergling";461;0
"Unit";"Baneling";"Zergling";461;0
"Unit";"Baneling";"Zergling";461;0
"Unit";"Baneling";"Zergling";461;0
"Unit";"Baneling";"Zergling";461;0
"Unit";"Baneling";"Zergling";461;0
"Unit";"Baneling";"Zergling";461;0
"Unit";"Baneling";"Zergling";461;0
"Unit";"Baneling";"Zergling";461;0
"Unit";"Baneling";"Zergling";461;0
"Unit";"Baneling";"Zergling";461;0
"Unit";"Baneling";"Zergling";461;0
"Unit";"Baneling";"Zergling";461;0
"Unit";"Baneling";"Zergling";461;0
"Unit";"Baneling";"Zergling";461;0
"Unit";"Zergling";"Larva";453;1
"Unit";"Zergling";"Larva";453;1
"Unit";"Zergling";"Larva";461;1
"Unit";"Zergling";"Larva";461;1
"Unit";"Zergling";"Larva";461;1
"Unit";"Zergling";"Larva";461;1
"Unit";"Zergling";"Larva";461;1
"Unit";"Zergling";"Larva";461;1
"Unit";"Zergling";"Larva";461;1
"Unit";"Zergling";"Larva";461;1
"Unit";"Zergling";"Larva";461;1
"Unit";"Zergling";"Larva";461;1
"Unit";"Zergling";"Larva";461;1
"Unit";"Zergling";"Larva";461;1
"Unit";"Zergling";"Larva";461;1
"Unit";"Zergling";"Larva";461;1
"Unit";"Zergling";"Larva";461;1
"Unit";"Zergling";"Larva";461;1
"Unit";"Zergling";"Larva";461;1
"Unit";"Zergling";"Larva";461;1
"Unit";"Zergling";"Larva";461;1
"Unit";"Zergling";"Larva";461;1
"Unit";"Zergling";"Larva";461;1
"Unit";"Zergling";"Larva";461;1
"Unit";"Zergling";"Larva";461;1
"Unit";"Zergling";"Larva";461;1
"Unit";"Ultralisk";"Larva";421;6
"Unit";"Ultralisk";"Larva";421;6
"Unit";"Ultralisk";"Larva";421;6
"Unit";"Zergling";"Larva";465;1
"Unit";"Zergling";"Larva";465;1
"Unit";"Zergling";"Larva";465;1
"Unit";"Zergling";"Larva";465;1
"Unit";"Zergling";"Larva";465;1
"Unit";"Zergling";"Larva";465;1
"Unit";"Zergling";"Larva";465;1
"Unit";"Zergling";"Larva";465;1
"Unit";"Zergling";"Larva";465;1
"Unit";"Zergling";"Larva";465;1
"Unit";"Zergling";"Larva";465;1
"Unit";"Zergling";"Larva";465;1
"Unit";"Zergling";"Larva";465;1
"Unit";"Zergling";"Larva";465;1
"Unit";"Zergling";"Larva";465;1
"Unit";"Zergling";"Larva";465;1
"Unit";"Zergling";"Larva";465;1
"Unit";"Zergling";"Larva";465;1
"Building";"CreepTumorQueen";NA;509;0
"Building";"CreepTumorQueen";NA;509;0
"Building";"CreepTumorQueen";NA;509;0
"Building";"CreepTumorQueen";NA;509;0
"Building";"CreepTumorQueen";NA;511;0
"Unit";"Overlord";"Larva";509;0
"Unit";"Overlord";"Larva";509;0
"Unit";"Overlord";"Larva";509;0
"Building";"CreepTumorQueen";NA;527;0
"Unit";"Queen";"Hatchery";463;2
"Unit";"Infestor";"Larva";509;2
