"type";"unit_name";"on_building";"total_supply";"supply"
"Unit";"Overlord";"Larva";13;0
"Building";"Extractor";NA;18;0
"Unit";"Overlord";"Larva";22;0
"Building";"SpawningPool";NA;19;0
"Building";"Hatchery";NA;17;0
"Unit";"Zergling";"Larva";22;1
"Unit";"Zergling";"Larva";22;1
"Unit";"Zergling";"Larva";22;1
"Unit";"Zergling";"Larva";22;1
"Unit";"Queen";"Hatchery";22;2
"Unit";"Queen";"Hatchery";22;2
"Unit";"Overlord";"Larva";37;0
"Unit";"Overlord";"Larva";39;0
"Unit";"Overlord";"Larva";39;0
"Unit";"Queen";"Hatchery";39;2
"Building";"CreepTumorQueen";NA;42;0
"Unit";"Queen";"Hatchery";42;2
"Building";"BanelingNest";NA;40;0
"Building";"Hatchery";NA;39;0
"Building";"CreepTumorQueen";NA;56;0
"Unit";"Overlord";"Larva";50;0
"Building";"EvolutionChamber";NA;50;0
"Building";"Extractor";NA;50;0
"Building";"Extractor";NA;51;0
"Unit";"Overlord";"Larva";58;0
"Building";"CreepTumorQueen";NA;58;0
"Unit";"Zergling";"Larva";58;1
"Unit";"Zergling";"Larva";58;1
"Unit";"Zergling";"Larva";58;1
"Unit";"Zergling";"Larva";58;1
"Unit";"Zergling";"Larva";58;1
"Unit";"Zergling";"Larva";58;1
"Unit";"Zergling";"Larva";58;1
"Unit";"Zergling";"Larva";58;1
"Unit";"Zergling";"Larva";58;1
"Unit";"Zergling";"Larva";58;1
"Building";"HydraliskDen";NA;58;0
"Unit";"Zergling";"Larva";62;1
"Unit";"Zergling";"Larva";62;1
"Unit";"Baneling";"Zergling";70;0
"Unit";"Baneling";"Zergling";70;0
"Unit";"Baneling";"Zergling";70;0
"Unit";"Baneling";"Zergling";72;0
"Unit";"Queen";"Hatchery";62;2
"Building";"CreepTumorQueen";NA;78;0
"Unit";"Baneling";"Zergling";78;0
"Unit";"Baneling";"Zergling";78;0
"Building";"CreepTumor";NA;78;0
"Building";"CreepTumorQueen";NA;80;0
"Unit";"Zergling";"Larva";74;1
"Unit";"Zergling";"Larva";74;1
"Unit";"Zergling";"Larva";74;1
"Unit";"Zergling";"Larva";74;1
"Unit";"Zergling";"Larva";74;1
"Unit";"Zergling";"Larva";74;1
"Building";"CreepTumorQueen";NA;93;0
"Unit";"Hydralisk";"Larva";84;2
"Building";"CreepTumorQueen";NA;93;0
"Building";"CreepTumor";NA;93;0
"Unit";"Overlord";"Larva";90;0
"Unit";"Overlord";"Larva";93;0
"Unit";"Overlord";"Larva";93;0
"Unit";"Overlord";"Larva";93;0
"Unit";"Overlord";"Larva";93;0
"Unit";"Overlord";"Larva";93;0
"Unit";"Overlord";"Larva";93;0
"Building";"CreepTumor";NA;95;0
"Building";"CreepTumorQueen";NA;95;0
"Building";"CreepTumorQueen";NA;95;0
"Building";"CreepTumor";NA;95;0
"Unit";"Hydralisk";"Larva";95;2
"Unit";"Hydralisk";"Larva";95;2
"Unit";"Hydralisk";"Larva";95;2
"Unit";"Hydralisk";"Larva";95;2
"Unit";"Hydralisk";"Larva";95;2
"Unit";"Hydralisk";"Larva";95;2
"Unit";"Hydralisk";"Larva";95;2
"Unit";"Hydralisk";"Larva";95;2
"Upgrade";"EvolveGroovedSpines";"HydraliskDen";93;0
"Building";"Extractor";NA;105;0
"Building";"CreepTumorQueen";NA;118;0
"Building";"CreepTumorQueen";NA;118;0
"Building";"Extractor";NA;105;0
"Building";"Extractor";NA;105;0
"Unit";"Hydralisk";"Larva";111;2
"Unit";"Hydralisk";"Larva";111;2
"Unit";"Hydralisk";"Larva";118;2
"Unit";"Hydralisk";"Larva";118;2
"Unit";"Overlord";"Larva";136;0
"Unit";"Overlord";"Larva";136;0
"Building";"CreepTumorQueen";NA;141;0
"Building";"CreepTumorQueen";NA;141;0
"Building";"SporeCrawler";NA;136;0
"Building";"CreepTumorQueen";NA;141;0
"Unit";"Overlord";"Larva";141;0
"Unit";"Hydralisk";"Larva";141;2
"Unit";"Zergling";"Larva";141;1
"Unit";"Zergling";"Larva";141;1
"Unit";"Zergling";"Larva";141;1
"Unit";"Zergling";"Larva";141;1
"Building";"SpineCrawler";NA;141;0
"Unit";"Zergling";"Larva";141;1
"Unit";"Zergling";"Larva";141;1
"Unit";"Zergling";"Larva";141;1
"Unit";"Zergling";"Larva";141;1
"Unit";"Zergling";"Larva";141;1
"Unit";"Zergling";"Larva";141;1
"Unit";"Zergling";"Larva";141;1
"Unit";"Zergling";"Larva";141;1
"Building";"Hatchery";NA;136;0
"Unit";"Overlord";"Larva";155;0
"Unit";"Overlord";"Larva";155;0
"Unit";"Overlord";"Larva";155;0
"Unit";"Hydralisk";"Larva";155;2
"Unit";"Hydralisk";"Larva";155;2
"Unit";"Hydralisk";"Larva";155;2
"Unit";"Hydralisk";"Larva";155;2
"Unit";"Hydralisk";"Larva";155;2
"Unit";"Hydralisk";"Larva";155;2
"Unit";"Hydralisk";"Larva";155;2
"Unit";"Hydralisk";"Larva";155;2
"Unit";"Hydralisk";"Larva";155;2
"Unit";"Hydralisk";"Larva";155;2
"Unit";"Queen";"Hatchery";155;2
"Building";"Hatchery";NA;141;0
"Unit";"Hydralisk";"Larva";155;2
"Unit";"Hydralisk";"Larva";155;2
"Unit";"Hydralisk";"Larva";155;2
"Unit";"Zergling";"Larva";155;1
"Unit";"Zergling";"Larva";155;1
"Unit";"Zergling";"Larva";155;1
"Unit";"Zergling";"Larva";155;1
"Unit";"Zergling";"Larva";175;1
"Unit";"Zergling";"Larva";175;1
"Unit";"Zergling";"Larva";175;1
"Unit";"Zergling";"Larva";175;1
"Unit";"Zergling";"Larva";175;1
"Unit";"Zergling";"Larva";175;1
"Upgrade";"ZergGroundArmorsLevel1";"EvolutionChamber";141;0
"Unit";"Zergling";"Larva";175;1
"Unit";"Zergling";"Larva";175;1
"Unit";"Zergling";"Larva";175;1
"Unit";"Zergling";"Larva";175;1
"Building";"Extractor";NA;155;0
"Building";"Extractor";NA;175;0
"Unit";"Hydralisk";"Larva";187;2
"Unit";"Queen";"Hatchery";175;2
"Building";"EvolutionChamber";NA;197;0
"Unit";"Hydralisk";"Larva";197;2
"Unit";"Hydralisk";"Larva";197;2
"Unit";"Hydralisk";"Larva";197;2
"Unit";"Hydralisk";"Larva";197;2
"Unit";"Hydralisk";"Larva";197;2
"Unit";"Hydralisk";"Larva";197;2
"Unit";"Hydralisk";"Larva";197;2
"Unit";"Hydralisk";"Larva";197;2
"Unit";"Hydralisk";"Larva";197;2
"Building";"SpineCrawler";NA;197;0
"Building";"CreepTumor";NA;201;0
"Building";"CreepTumor";NA;201;0
"Unit";"Baneling";"Zergling";201;0
"Building";"CreepTumor";NA;201;0
"Unit";"Baneling";"Zergling";201;0
"Unit";"Baneling";"Zergling";201;0
"Unit";"Baneling";"Zergling";201;0
"Unit";"Baneling";"Zergling";201;0
"Unit";"Baneling";"Zergling";201;0
"Unit";"Baneling";"Zergling";201;0
"Unit";"Baneling";"Zergling";201;0
"Building";"CreepTumor";NA;201;0
"Upgrade";"EvolveMuscularAugments";"HydraliskDen";187;0
"Unit";"Zergling";"Larva";215;1
"Unit";"Zergling";"Larva";215;1
"Unit";"Zergling";"Larva";219;1
"Unit";"Zergling";"Larva";219;1
"Unit";"Zergling";"Larva";219;1
"Unit";"Zergling";"Larva";219;1
"Unit";"Zergling";"Larva";219;1
"Unit";"Zergling";"Larva";219;1
"Unit";"Zergling";"Larva";219;1
"Unit";"Zergling";"Larva";219;1
"Unit";"Zergling";"Larva";219;1
"Unit";"Zergling";"Larva";219;1
"Unit";"Zergling";"Larva";219;1
"Unit";"Zergling";"Larva";219;1
"Unit";"Zergling";"Larva";219;1
"Unit";"Zergling";"Larva";219;1
"Unit";"Zergling";"Larva";219;1
"Unit";"Zergling";"Larva";219;1
"Unit";"Zergling";"Larva";219;1
"Unit";"Zergling";"Larva";219;1
"Unit";"Zergling";"Larva";219;1
"Unit";"Zergling";"Larva";219;1
"Unit";"Hydralisk";"Larva";244;2
"Unit";"Hydralisk";"Larva";244;2
"Unit";"Hydralisk";"Larva";244;2
"Unit";"Hydralisk";"Larva";244;2
"Unit";"Hydralisk";"Larva";244;2
"Building";"CreepTumorQueen";NA;244;0
"Unit";"Zergling";"Larva";244;1
"Unit";"Zergling";"Larva";244;1
"Unit";"Zergling";"Larva";244;1
"Unit";"Zergling";"Larva";244;1
"Unit";"Zergling";"Larva";244;1
"Unit";"Zergling";"Larva";244;1
"Unit";"Zergling";"Larva";244;1
"Unit";"Zergling";"Larva";244;1
"Unit";"Zergling";"Larva";244;1
"Unit";"Zergling";"Larva";244;1
"Unit";"Zergling";"Larva";244;1
"Unit";"Zergling";"Larva";244;1
"Building";"Hatchery";NA;201;0
"Unit";"Baneling";"Zergling";266;0
"Unit";"Baneling";"Zergling";266;0
"Unit";"Baneling";"Zergling";266;0
"Unit";"Baneling";"Zergling";266;0
"Unit";"Baneling";"Zergling";266;0
"Building";"LurkerDenMP";NA;199;0
"Unit";"Zergling";"Larva";266;1
"Unit";"Zergling";"Larva";266;1
"Unit";"Zergling";"Larva";266;1
"Unit";"Zergling";"Larva";266;1
"Unit";"Zergling";"Larva";266;1
"Unit";"Zergling";"Larva";266;1
"Unit";"Zergling";"Larva";266;1
"Unit";"Zergling";"Larva";266;1
"Unit";"Zergling";"Larva";266;1
"Unit";"Zergling";"Larva";266;1
"Unit";"Zergling";"Larva";266;1
"Unit";"Zergling";"Larva";266;1
"Unit";"Zergling";"Larva";266;1
"Unit";"Zergling";"Larva";266;1
"Unit";"Zergling";"Larva";266;1
"Unit";"Zergling";"Larva";266;1
"Unit";"Zergling";"Larva";266;1
"Unit";"Zergling";"Larva";266;1
"Building";"CreepTumorQueen";NA;284;0
"Building";"CreepTumor";NA;270;0
"Building";"CreepTumorQueen";NA;284;0
"Building";"SporeCrawler";NA;266;0
"Building";"InfestationPit";NA;266;0
"Building";"SpineCrawler";NA;266;0
"Building";"SpineCrawler";NA;266;0
"Unit";"Hydralisk";"Larva";290;2
"Unit";"Hydralisk";"Larva";290;2
"Unit";"Hydralisk";"Larva";290;2
"Unit";"Hydralisk";"Larva";290;2
"Unit";"Hydralisk";"Larva";290;2
"Unit";"Hydralisk";"Larva";290;2
"Building";"Spire";NA;266;0
"Unit";"Overlord";"Larva";307;0
"Unit";"Overlord";"Larva";307;0
"Unit";"Overlord";"Larva";307;0
"Unit";"Overlord";"Larva";307;0
"Building";"CreepTumor";NA;307;0
"Building";"CreepTumor";NA;307;0
"Unit";"Overlord";"Larva";307;0
"Unit";"Overlord";"Larva";307;0
"Upgrade";"ZergMissileWeaponsLevel1";"EvolutionChamber";284;0
"Building";"SpineCrawler";NA;307;0
"Upgrade";"ZergGroundArmorsLevel2";"EvolutionChamber";290;0
"Unit";"Zergling";"Larva";318;1
"Unit";"Zergling";"Larva";318;1
"Unit";"Zergling";"Larva";318;1
"Unit";"Zergling";"Larva";318;1
"Unit";"Zergling";"Larva";318;1
"Unit";"Zergling";"Larva";318;1
"Unit";"Zergling";"Larva";318;1
"Unit";"Zergling";"Larva";318;1
"Unit";"Zergling";"Larva";318;1
"Unit";"Zergling";"Larva";318;1
"Unit";"Zergling";"Larva";318;1
"Unit";"Zergling";"Larva";318;1
"Unit";"Zergling";"Larva";318;1
"Unit";"Zergling";"Larva";318;1
"Unit";"Zergling";"Larva";318;1
"Unit";"Zergling";"Larva";318;1
"Unit";"Zergling";"Larva";318;1
"Unit";"Zergling";"Larva";318;1
"Unit";"Zergling";"Larva";318;1
"Unit";"Zergling";"Larva";318;1
"Unit";"Zergling";"Larva";318;1
"Unit";"Zergling";"Larva";318;1
"Unit";"Zergling";"Larva";318;1
"Unit";"Zergling";"Larva";318;1
"Unit";"Zergling";"Larva";318;1
"Unit";"Zergling";"Larva";318;1
"Unit";"Zergling";"Larva";318;1
"Unit";"Zergling";"Larva";318;1
"Unit";"Zergling";"Larva";318;1
"Unit";"Zergling";"Larva";318;1
"Unit";"Hydralisk";"Larva";348;2
"Unit";"Hydralisk";"Larva";348;2
"Unit";"Hydralisk";"Larva";348;2
"Unit";"Hydralisk";"Larva";348;2
"Unit";"Hydralisk";"Larva";348;2
"Unit";"Hydralisk";"Larva";348;2
"Unit";"Hydralisk";"Larva";348;2
"Unit";"Hydralisk";"Larva";348;2
"Unit";"Hydralisk";"Larva";348;2
"Unit";"Hydralisk";"Larva";348;2
"Unit";"Hydralisk";"Larva";348;2
"Unit";"Hydralisk";"Larva";348;2
"Unit";"Hydralisk";"Larva";348;2
"Unit";"Hydralisk";"Larva";348;2
"Unit";"Hydralisk";"Larva";348;2
"Unit";"Hydralisk";"Larva";348;2
"Unit";"Hydralisk";"Larva";348;2
"Unit";"Hydralisk";"Larva";348;2
"Unit";"Hydralisk";"Larva";348;2
"Unit";"Hydralisk";"Larva";348;2
"Unit";"Hydralisk";"Larva";368;2
"Unit";"Hydralisk";"Larva";368;2
"Unit";"Hydralisk";"Larva";368;2
"Unit";"Hydralisk";"Larva";368;2
"Unit";"Hydralisk";"Larva";368;2
"Unit";"Hydralisk";"Larva";368;2
"Unit";"Hydralisk";"Larva";368;2
"Unit";"Hydralisk";"Larva";368;2
"Unit";"Hydralisk";"Larva";368;2
"Unit";"Hydralisk";"Larva";368;2
"Building";"Extractor";NA;388;0
"Building";"Extractor";NA;388;0
"Building";"Extractor";NA;388;0
"Building";"Extractor";NA;388;0
"Building";"Extractor";NA;408;0
"Building";"Extractor";NA;408;0
"Building";"CreepTumorQueen";NA;417;0
"Building";"CreepTumorQueen";NA;417;0
"Unit";"Hydralisk";"Larva";417;2
"Unit";"Hydralisk";"Larva";417;2
"Unit";"Hydralisk";"Larva";417;2
"Unit";"Hydralisk";"Larva";417;2
"Unit";"Hydralisk";"Larva";417;2
"Unit";"Hydralisk";"Larva";417;2
"Unit";"Hydralisk";"Larva";417;2
"Unit";"Hydralisk";"Larva";417;2
"Unit";"Hydralisk";"Larva";417;2
"Unit";"Hydralisk";"Larva";417;2
"Unit";"Hydralisk";"Larva";417;2
"Building";"CreepTumor";NA;433;0
"Building";"Hatchery";NA;408;0
"Building";"CreepTumorQueen";NA;439;0
"Building";"CreepTumorQueen";NA;439;0
"Building";"CreepTumorQueen";NA;439;0
"Upgrade";"ZergMissileWeaponsLevel2";"EvolutionChamber";417;0
"Unit";"Corruptor";"Larva";439;2
"Unit";"Corruptor";"Larva";439;2
"Unit";"Corruptor";"Larva";439;2
"Building";"Hatchery";NA;433;0
"Unit";"Corruptor";"Larva";439;2
"Unit";"Corruptor";"Larva";439;2
"Building";"CreepTumor";NA;445;0
"Building";"CreepTumor";NA;445;0
"Upgrade";"ZergGroundArmorsLevel3";"EvolutionChamber";417;0
"Building";"Extractor";NA;445;0
"Building";"Extractor";NA;445;0
"Building";"SporeCrawler";NA;449;0
"Unit";"Corruptor";"Larva";449;2
"Building";"Hatchery";NA;439;0
"Building";"SpineCrawler";NA;449;0
"Building";"SpineCrawler";NA;449;0
"Unit";"Hydralisk";"Larva";451;2
"Unit";"Hydralisk";"Larva";451;2
"Unit";"Hydralisk";"Larva";451;2
"Unit";"Hydralisk";"Larva";451;2
"Unit";"Baneling";"Zergling";459;0
"Unit";"Baneling";"Zergling";459;0
"Unit";"Baneling";"Zergling";459;0
"Unit";"Corruptor";"Larva";459;2
"Unit";"Corruptor";"Larva";459;2
"Unit";"Corruptor";"Larva";459;2
"Building";"CreepTumorQueen";NA;468;0
"Unit";"Corruptor";"Larva";459;2
"Unit";"Corruptor";"Larva";459;2
"Unit";"Corruptor";"Larva";459;2
"Unit";"Zergling";"Larva";468;1
"Unit";"Zergling";"Larva";468;1
"Unit";"Zergling";"Larva";468;1
"Unit";"Zergling";"Larva";468;1
"Unit";"Zergling";"Larva";468;1
"Unit";"Zergling";"Larva";468;1
"Unit";"Zergling";"Larva";468;1
"Unit";"Zergling";"Larva";468;1
"Unit";"Zergling";"Larva";468;1
"Unit";"Zergling";"Larva";468;1
"Unit";"Zergling";"Larva";468;1
"Unit";"Zergling";"Larva";468;1
"Unit";"Zergling";"Larva";468;1
"Unit";"Zergling";"Larva";468;1
"Unit";"Zergling";"Larva";468;1
"Unit";"Zergling";"Larva";468;1
"Unit";"Zergling";"Larva";468;1
"Unit";"Zergling";"Larva";468;1
"Unit";"Zergling";"Larva";468;1
"Unit";"Zergling";"Larva";468;1
"Unit";"Zergling";"Larva";468;1
"Unit";"Zergling";"Larva";468;1
"Building";"UltraliskCavern";NA;459;0
"Building";"Extractor";NA;502;0
"Building";"Extractor";NA;502;0
"Unit";"Zergling";"Larva";502;1
"Unit";"Zergling";"Larva";502;1
"Unit";"Zergling";"Larva";502;1
"Unit";"Zergling";"Larva";502;1
"Unit";"Zergling";"Larva";502;1
"Unit";"Zergling";"Larva";502;1
"Unit";"Zergling";"Larva";502;1
"Unit";"Zergling";"Larva";502;1
"Unit";"Zergling";"Larva";502;1
"Unit";"Zergling";"Larva";502;1
"Unit";"Zergling";"Larva";502;1
"Unit";"Zergling";"Larva";502;1
"Unit";"Zergling";"Larva";502;1
"Unit";"Zergling";"Larva";502;1
"Unit";"Zergling";"Larva";502;1
"Unit";"Zergling";"Larva";502;1
"Unit";"Hydralisk";"Larva";502;2
"Unit";"Hydralisk";"Larva";502;2
"Unit";"Hydralisk";"Larva";502;2
"Unit";"Hydralisk";"Larva";518;2
"Unit";"Hydralisk";"Larva";518;2
"Unit";"Hydralisk";"Larva";518;2
"Unit";"Hydralisk";"Larva";518;2
"Unit";"Hydralisk";"Larva";518;2
"Unit";"Hydralisk";"Larva";518;2
"Unit";"Hydralisk";"Larva";518;2
"Unit";"Hydralisk";"Larva";518;2
"Unit";"Hydralisk";"Larva";518;2
"Unit";"Hydralisk";"Larva";518;2
"Unit";"Hydralisk";"Larva";518;2
"Building";"CreepTumor";NA;546;0
"Upgrade";"ChitinousPlating";"UltraliskCavern";546;0
"Unit";"Zergling";"Larva";551;1
"Unit";"Zergling";"Larva";551;1
"Unit";"Zergling";"Larva";551;1
"Unit";"Zergling";"Larva";551;1
"Unit";"Zergling";"Larva";551;1
"Unit";"Zergling";"Larva";551;1
"Unit";"Zergling";"Larva";551;1
"Unit";"Zergling";"Larva";551;1
"Unit";"Zergling";"Larva";551;1
"Unit";"Zergling";"Larva";551;1
"Unit";"Zergling";"Larva";551;1
"Unit";"Zergling";"Larva";551;1
"Unit";"Zergling";"Larva";551;1
"Unit";"Zergling";"Larva";551;1
"Unit";"Zergling";"Larva";551;1
"Unit";"Zergling";"Larva";551;1
"Unit";"Zergling";"Larva";551;1
"Unit";"Zergling";"Larva";551;1
"Building";"Hatchery";NA;548;0
"Building";"Hatchery";NA;551;0
"Unit";"Baneling";"Zergling";573;0
"Unit";"Baneling";"Zergling";573;0
"Unit";"Baneling";"Zergling";573;0
"Unit";"Baneling";"Zergling";573;0
"Unit";"Baneling";"Zergling";573;0
"Unit";"Baneling";"Zergling";573;0
"Unit";"Hydralisk";"Larva";576;2
"Unit";"Hydralisk";"Larva";576;2
"Building";"SporeCrawler";NA;576;0
"Building";"SporeCrawler";NA;576;0
"Building";"CreepTumorQueen";NA;580;0
"Building";"CreepTumor";NA;595;0
"Building";"SpineCrawler";NA;589;0
"Unit";"Baneling";"Zergling";595;0
"Unit";"Hydralisk";"Larva";595;2
"Unit";"Hydralisk";"Larva";595;2
"Unit";"Baneling";"Zergling";595;0
"Unit";"Baneling";"Zergling";595;0
"Unit";"Baneling";"Zergling";595;0
"Unit";"Ultralisk";"Larva";592;6
"Unit";"Ultralisk";"Larva";592;6
"Building";"Hatchery";NA;587;0
"Unit";"Hydralisk";"Larva";599;2
"Unit";"Hydralisk";"Larva";611;2
"Unit";"Hydralisk";"Larva";611;2
"Unit";"Hydralisk";"Larva";611;2
"Unit";"Hydralisk";"Larva";611;2
"Unit";"Hydralisk";"Larva";611;2
"Unit";"Hydralisk";"Larva";611;2
"Unit";"Hydralisk";"Larva";611;2
"Unit";"Hydralisk";"Larva";611;2
"Building";"Extractor";NA;611;0
"Unit";"Ultralisk";"Larva";629;6
"Unit";"Overlord";"Larva";657;0
"Unit";"Overlord";"Larva";657;0
"Unit";"Overlord";"Larva";657;0
"Unit";"Queen";"Hatchery";644;2
"Unit";"Hydralisk";"Larva";651;2
"Unit";"Hydralisk";"Larva";651;2
"Unit";"Hydralisk";"Larva";651;2
"Unit";"Hydralisk";"Larva";651;2
"Unit";"Hydralisk";"Larva";651;2
"Unit";"Hydralisk";"Larva";651;2
"Unit";"Hydralisk";"Larva";651;2
"Unit";"Hydralisk";"Larva";651;2
"Building";"Extractor";NA;657;0
"Building";"Extractor";NA;657;0
"Unit";"Overlord";"Larva";657;0
"Unit";"Overlord";"Larva";659;0
"Unit";"Corruptor";"Larva";657;2
"Unit";"Zergling";"Larva";675;1
"Unit";"Zergling";"Larva";675;1
"Unit";"Zergling";"Larva";675;1
"Unit";"Zergling";"Larva";675;1
"Unit";"Zergling";"Larva";675;1
"Unit";"Zergling";"Larva";675;1
"Unit";"Zergling";"Larva";675;1
"Unit";"Zergling";"Larva";675;1
"Unit";"Zergling";"Larva";675;1
"Unit";"Zergling";"Larva";675;1
"Unit";"Zergling";"Larva";675;1
"Unit";"Zergling";"Larva";675;1
"Unit";"Zergling";"Larva";675;1
"Unit";"Zergling";"Larva";675;1
"Unit";"Zergling";"Larva";675;1
"Unit";"Zergling";"Larva";675;1
"Unit";"Zergling";"Larva";675;1
"Unit";"Zergling";"Larva";675;1
"Unit";"Zergling";"Larva";675;1
"Unit";"Zergling";"Larva";675;1
"Unit";"Zergling";"Larva";675;1
"Unit";"Zergling";"Larva";675;1
"Unit";"Corruptor";"Larva";699;2
"Unit";"Corruptor";"Larva";699;2
"Unit";"Corruptor";"Larva";699;2
"Unit";"Baneling";"Zergling";700;0
"Unit";"Baneling";"Zergling";700;0
"Unit";"Baneling";"Zergling";700;0
"Unit";"Baneling";"Zergling";700;0
"Unit";"Baneling";"Zergling";700;0
"Unit";"Baneling";"Zergling";700;0
"Unit";"Baneling";"Zergling";700;0
"Upgrade";"ZergMissileWeaponsLevel3";"EvolutionChamber";644;0
"Unit";"Corruptor";"Larva";699;2
"Unit";"Corruptor";"Larva";699;2
"Unit";"Corruptor";"Larva";699;2
"Upgrade";"ZergMeleeWeaponsLevel1";"EvolutionChamber";675;0
"Unit";"Zergling";"Larva";712;1
"Unit";"Zergling";"Larva";712;1
"Unit";"Zergling";"Larva";712;1
"Unit";"Zergling";"Larva";712;1
"Unit";"Zergling";"Larva";712;1
"Unit";"Zergling";"Larva";712;1
"Unit";"Zergling";"Larva";712;1
"Unit";"Zergling";"Larva";712;1
"Unit";"Zergling";"Larva";712;1
"Unit";"Zergling";"Larva";712;1
"Unit";"Overlord";"Larva";712;0
"Unit";"Overlord";"Larva";712;0
"Unit";"Overlord";"Larva";712;0
"Unit";"Overlord";"Larva";712;0
"Unit";"Overlord";"Larva";712;0
"Unit";"Zergling";"Larva";722;1
"Unit";"Zergling";"Larva";722;1
"Unit";"Zergling";"Larva";722;1
"Unit";"Zergling";"Larva";722;1
"Unit";"Zergling";"Larva";722;1
"Unit";"Zergling";"Larva";722;1
"Unit";"Zergling";"Larva";722;1
"Unit";"Zergling";"Larva";722;1
"Unit";"Zergling";"Larva";722;1
"Unit";"Zergling";"Larva";722;1
"Unit";"Zergling";"Larva";722;1
"Unit";"Zergling";"Larva";722;1
"Unit";"Zergling";"Larva";722;1
"Unit";"Zergling";"Larva";722;1
"Unit";"Zergling";"Larva";722;1
"Unit";"Zergling";"Larva";722;1
"Unit";"Zergling";"Larva";722;1
"Unit";"Zergling";"Larva";722;1
"Building";"SpineCrawler";NA;722;0
"Unit";"Hydralisk";"Larva";740;2
"Unit";"Hydralisk";"Larva";740;2
"Unit";"Hydralisk";"Larva";740;2
"Unit";"Hydralisk";"Larva";740;2
"Unit";"Hydralisk";"Larva";740;2
"Unit";"Hydralisk";"Larva";740;2
"Unit";"Hydralisk";"Larva";740;2
"Unit";"Hydralisk";"Larva";740;2
"Unit";"Hydralisk";"Larva";740;2
"Unit";"Hydralisk";"Larva";740;2
"Unit";"Hydralisk";"Larva";740;2
"Unit";"Zergling";"Larva";740;1
"Unit";"Zergling";"Larva";740;1
"Unit";"Zergling";"Larva";740;1
"Unit";"Zergling";"Larva";740;1
"Unit";"Zergling";"Larva";740;1
"Unit";"Zergling";"Larva";740;1
"Unit";"Zergling";"Larva";740;1
"Unit";"Zergling";"Larva";740;1
"Unit";"Zergling";"Larva";764;1
"Unit";"Zergling";"Larva";764;1
"Unit";"Zergling";"Larva";764;1
"Unit";"Zergling";"Larva";764;1
"Unit";"Zergling";"Larva";764;1
"Unit";"Zergling";"Larva";764;1
"Unit";"Zergling";"Larva";764;1
"Unit";"Zergling";"Larva";764;1
"Unit";"Zergling";"Larva";764;1
"Unit";"Zergling";"Larva";764;1
"Unit";"Zergling";"Larva";770;1
"Unit";"Zergling";"Larva";770;1
"Unit";"Zergling";"Larva";770;1
"Unit";"Zergling";"Larva";770;1
"Unit";"Zergling";"Larva";770;1
"Unit";"Zergling";"Larva";770;1
"Unit";"Zergling";"Larva";770;1
"Unit";"Zergling";"Larva";770;1
"Unit";"Zergling";"Larva";770;1
"Unit";"Zergling";"Larva";770;1
"Unit";"Zergling";"Larva";770;1
"Unit";"Zergling";"Larva";770;1
"Unit";"Zergling";"Larva";770;1
"Unit";"Zergling";"Larva";770;1
"Unit";"Zergling";"Larva";770;1
"Unit";"Zergling";"Larva";770;1
"Unit";"Zergling";"Larva";770;1
"Unit";"Zergling";"Larva";770;1
"Unit";"Zergling";"Larva";770;1
"Unit";"Zergling";"Larva";770;1
"Unit";"Zergling";"Larva";770;1
"Unit";"Zergling";"Larva";770;1
"Unit";"Zergling";"Larva";770;1
"Unit";"Zergling";"Larva";770;1
"Unit";"Zergling";"Larva";770;1
"Unit";"Zergling";"Larva";770;1
"Unit";"Zergling";"Larva";770;1
"Unit";"Zergling";"Larva";770;1
"Unit";"Zergling";"Larva";770;1
"Unit";"Zergling";"Larva";770;1
"Unit";"Zergling";"Larva";770;1
"Unit";"Zergling";"Larva";770;1
"Unit";"Zergling";"Larva";770;1
"Unit";"Zergling";"Larva";770;1
"Unit";"Zergling";"Larva";770;1
"Unit";"Zergling";"Larva";770;1
"Unit";"Zergling";"Larva";770;1
"Unit";"Zergling";"Larva";770;1
"Unit";"Zergling";"Larva";770;1
"Unit";"Zergling";"Larva";770;1
"Unit";"Baneling";"Zergling";780;0
"Unit";"Baneling";"Zergling";780;0
"Unit";"Baneling";"Zergling";780;0
"Unit";"Baneling";"Zergling";780;0
"Unit";"Baneling";"Zergling";780;0
"Unit";"Baneling";"Zergling";780;0
"Unit";"Zergling";"Larva";780;1
"Unit";"Zergling";"Larva";780;1
"Unit";"Hydralisk";"Larva";820;2
"Unit";"Hydralisk";"Larva";820;2
"Unit";"Hydralisk";"Larva";820;2
"Unit";"Hydralisk";"Larva";820;2
"Unit";"Hydralisk";"Larva";820;2
"Unit";"Hydralisk";"Larva";820;2
"Unit";"Baneling";"Zergling";822;0
"Building";"Hatchery";NA;770;0
"Unit";"Hydralisk";"Larva";834;2
"Unit";"Hydralisk";"Larva";834;2
"Unit";"Hydralisk";"Larva";834;2
"Unit";"Hydralisk";"Larva";834;2
"Unit";"Hydralisk";"Larva";834;2
"Unit";"Hydralisk";"Larva";834;2
"Unit";"Zergling";"Larva";834;1
"Unit";"Zergling";"Larva";834;1
"Unit";"Zergling";"Larva";834;1
"Unit";"Zergling";"Larva";834;1
"Unit";"Zergling";"Larva";834;1
"Unit";"Zergling";"Larva";834;1
"Unit";"Zergling";"Larva";834;1
"Unit";"Zergling";"Larva";834;1
"Unit";"Zergling";"Larva";834;1
"Unit";"Zergling";"Larva";834;1
"Unit";"Zergling";"Larva";834;1
"Unit";"Zergling";"Larva";834;1
"Unit";"Zergling";"Larva";834;1
"Unit";"Zergling";"Larva";834;1
"Unit";"Zergling";"Larva";834;1
"Unit";"Zergling";"Larva";834;1
"Unit";"Zergling";"Larva";846;1
"Unit";"Zergling";"Larva";846;1
"Unit";"Zergling";"Larva";846;1
"Unit";"Zergling";"Larva";846;1
"Unit";"Zergling";"Larva";846;1
"Unit";"Zergling";"Larva";846;1
"Unit";"Zergling";"Larva";846;1
"Unit";"Zergling";"Larva";846;1
"Unit";"Zergling";"Larva";846;1
"Unit";"Zergling";"Larva";846;1
"Unit";"Zergling";"Larva";846;1
"Unit";"Zergling";"Larva";846;1
"Unit";"Baneling";"Zergling";874;0
"Unit";"Baneling";"Zergling";874;0
"Unit";"Baneling";"Zergling";874;0
"Unit";"Baneling";"Zergling";874;0
"Unit";"Baneling";"Zergling";874;0
"Unit";"Baneling";"Zergling";874;0
"Unit";"Baneling";"Zergling";874;0
"Unit";"Baneling";"Zergling";874;0
"Unit";"Baneling";"Zergling";874;0
"Unit";"Baneling";"Zergling";874;0
"Unit";"Baneling";"Zergling";874;0
"Unit";"Baneling";"Zergling";874;0
"Unit";"Baneling";"Zergling";874;0
"Building";"CreepTumor";NA;874;0
"Building";"Hatchery";NA;834;0
"Unit";"Zergling";"Larva";874;1
"Unit";"Zergling";"Larva";874;1
"Unit";"Zergling";"Larva";874;1
"Unit";"Zergling";"Larva";874;1
"Unit";"Zergling";"Larva";874;1
"Unit";"Zergling";"Larva";874;1
"Unit";"Zergling";"Larva";874;1
"Unit";"Zergling";"Larva";874;1
"Unit";"Zergling";"Larva";874;1
"Unit";"Zergling";"Larva";874;1
"Unit";"Zergling";"Larva";874;1
"Unit";"Zergling";"Larva";874;1
"Unit";"Zergling";"Larva";874;1
"Unit";"Zergling";"Larva";874;1
"Unit";"Zergling";"Larva";874;1
"Unit";"Zergling";"Larva";874;1
"Unit";"Zergling";"Larva";874;1
"Unit";"Zergling";"Larva";874;1
"Unit";"Zergling";"Larva";874;1
"Unit";"Zergling";"Larva";874;1
"Unit";"Zergling";"Larva";874;1
"Unit";"Zergling";"Larva";874;1
"Unit";"Zergling";"Larva";874;1
"Unit";"Zergling";"Larva";874;1
"Unit";"Zergling";"Larva";874;1
"Unit";"Zergling";"Larva";874;1
"Unit";"Zergling";"Larva";874;1
"Unit";"Zergling";"Larva";874;1
"Unit";"Zergling";"Larva";874;1
"Unit";"Zergling";"Larva";874;1
"Unit";"Zergling";"Larva";874;1
"Unit";"Zergling";"Larva";874;1
"Unit";"Zergling";"Larva";874;1
"Unit";"Zergling";"Larva";874;1
"Unit";"Zergling";"Larva";874;1
"Unit";"Zergling";"Larva";874;1
"Unit";"Zergling";"Larva";902;1
"Unit";"Zergling";"Larva";902;1
"Unit";"Zergling";"Larva";904;1
"Unit";"Zergling";"Larva";904;1
"Unit";"Zergling";"Larva";904;1
"Unit";"Zergling";"Larva";904;1
"Building";"Hatchery";NA;874;0
"Unit";"Ultralisk";"Larva";902;6
"Unit";"Baneling";"Zergling";916;0
"Unit";"Baneling";"Zergling";916;0
"Unit";"Baneling";"Zergling";916;0
"Unit";"Hydralisk";"Larva";931;2
"Unit";"Hydralisk";"Larva";931;2
"Unit";"Hydralisk";"Larva";931;2
"Unit";"Hydralisk";"Larva";931;2
"Unit";"Hydralisk";"Larva";931;2
"Unit";"Hydralisk";"Larva";931;2
"Unit";"Hydralisk";"Larva";931;2
"Unit";"Hydralisk";"Larva";931;2
"Unit";"Hydralisk";"Larva";931;2
"Unit";"Hydralisk";"Larva";931;2
"Unit";"Hydralisk";"Larva";951;2
"Unit";"Hydralisk";"Larva";951;2
"Unit";"Hydralisk";"Larva";951;2
"Unit";"Hydralisk";"Larva";951;2
"Unit";"Hydralisk";"Larva";951;2
"Unit";"Hydralisk";"Larva";951;2
"Unit";"Hydralisk";"Larva";951;2
"Unit";"Hydralisk";"Larva";951;2
"Unit";"Overlord";"Larva";951;0
"Unit";"Overlord";"Larva";951;0
"Unit";"Zergling";"Larva";951;1
"Unit";"Zergling";"Larva";951;1
"Unit";"Zergling";"Larva";951;1
"Unit";"Zergling";"Larva";951;1
"Unit";"Zergling";"Larva";951;1
"Unit";"Zergling";"Larva";951;1
"Unit";"Zergling";"Larva";951;1
"Unit";"Zergling";"Larva";951;1
"Unit";"Zergling";"Larva";951;1
"Unit";"Zergling";"Larva";951;1
"Unit";"Zergling";"Larva";951;1
"Unit";"Zergling";"Larva";951;1
"Building";"Extractor";NA;951;0
"Unit";"Ultralisk";"Larva";951;6
"Unit";"Zergling";"Larva";979;1
"Unit";"Zergling";"Larva";979;1
"Unit";"Zergling";"Larva";979;1
"Unit";"Zergling";"Larva";979;1
"Unit";"Zergling";"Larva";979;1
"Unit";"Zergling";"Larva";979;1
"Unit";"Zergling";"Larva";979;1
"Unit";"Zergling";"Larva";979;1
"Unit";"Zergling";"Larva";979;1
"Unit";"Zergling";"Larva";979;1
"Unit";"Zergling";"Larva";979;1
"Unit";"Zergling";"Larva";979;1
"Unit";"Zergling";"Larva";979;1
"Unit";"Zergling";"Larva";979;1
"Unit";"Zergling";"Larva";979;1
"Unit";"Zergling";"Larva";979;1
"Building";"CreepTumor";NA;979;0
"Unit";"Baneling";"Zergling";1001;0
"Unit";"Baneling";"Zergling";1001;0
"Unit";"Baneling";"Zergling";1001;0
"Unit";"Baneling";"Zergling";1001;0
"Unit";"Baneling";"Zergling";1001;0
"Unit";"Baneling";"Zergling";1001;0
"Unit";"Baneling";"Zergling";1001;0
"Unit";"Baneling";"Zergling";1001;0
"Unit";"Baneling";"Zergling";1001;0
"Unit";"Baneling";"Zergling";1001;0
"Unit";"Baneling";"Zergling";1001;0
"Unit";"Baneling";"Zergling";1001;0
"Unit";"Baneling";"Zergling";1001;0
"Unit";"Baneling";"Zergling";1001;0
"Unit";"Ultralisk";"Larva";1001;6
"Unit";"Ultralisk";"Larva";1001;6
"Unit";"Ultralisk";"Larva";1001;6
"Unit";"Ultralisk";"Larva";1001;6
"Upgrade";"ZergMeleeWeaponsLevel2";"EvolutionChamber";1001;0
"Building";"Extractor";NA;1025;0
"Building";"Extractor";NA;1025;0
"Building";"Hatchery";NA;1001;0
"Unit";"Hydralisk";"Larva";1025;2
"Unit";"Hydralisk";"Larva";1025;2
"Unit";"Hydralisk";"Larva";1025;2
"Unit";"Hydralisk";"Larva";1025;2
"Unit";"Hydralisk";"Larva";1025;2
"Unit";"Hydralisk";"Larva";1025;2
"Unit";"Hydralisk";"Larva";1025;2
"Unit";"Hydralisk";"Larva";1025;2
"Unit";"Hydralisk";"Larva";1025;2
"Unit";"Hydralisk";"Larva";1025;2
"Unit";"Hydralisk";"Larva";1025;2
"Unit";"Hydralisk";"Larva";1025;2
"Unit";"Hydralisk";"Larva";1025;2
"Unit";"Zergling";"Larva";1025;1
"Unit";"Zergling";"Larva";1025;1
"Unit";"Zergling";"Larva";1025;1
"Unit";"Zergling";"Larva";1025;1
"Unit";"Zergling";"Larva";1025;1
"Unit";"Zergling";"Larva";1025;1
"Unit";"Zergling";"Larva";1025;1
"Unit";"Zergling";"Larva";1025;1
"Unit";"Zergling";"Larva";1025;1
"Unit";"Zergling";"Larva";1025;1
"Unit";"Zergling";"Larva";1025;1
"Unit";"Zergling";"Larva";1025;1
"Unit";"Zergling";"Larva";1025;1
"Unit";"Zergling";"Larva";1025;1
"Unit";"Zergling";"Larva";1025;1
"Unit";"Zergling";"Larva";1025;1
"Unit";"Zergling";"Larva";1025;1
"Unit";"Zergling";"Larva";1025;1
"Unit";"Zergling";"Larva";1025;1
"Unit";"Zergling";"Larva";1025;1
"Unit";"Zergling";"Larva";1051;1
"Unit";"Zergling";"Larva";1051;1
"Unit";"Zergling";"Larva";1051;1
"Unit";"Zergling";"Larva";1051;1
"Unit";"Zergling";"Larva";1051;1
"Unit";"Zergling";"Larva";1051;1
"Unit";"Zergling";"Larva";1051;1
"Unit";"Zergling";"Larva";1051;1
"Unit";"Zergling";"Larva";1051;1
"Unit";"Zergling";"Larva";1051;1
"Unit";"Zergling";"Larva";1065;1
"Unit";"Zergling";"Larva";1065;1
"Unit";"Baneling";"Zergling";1081;0
"Unit";"Baneling";"Zergling";1081;0
"Unit";"Baneling";"Zergling";1081;0
"Unit";"Baneling";"Zergling";1081;0
"Unit";"Baneling";"Zergling";1091;0
"Unit";"Baneling";"Zergling";1091;0
"Unit";"Baneling";"Zergling";1091;0
"Unit";"Baneling";"Zergling";1091;0
"Unit";"Baneling";"Zergling";1091;0
"Building";"SporeCrawler";NA;1091;0
"Unit";"Zergling";"Larva";1091;1
"Unit";"Zergling";"Larva";1091;1
"Unit";"Zergling";"Larva";1091;1
"Unit";"Zergling";"Larva";1091;1
"Unit";"Zergling";"Larva";1091;1
"Unit";"Zergling";"Larva";1091;1
"Unit";"Zergling";"Larva";1091;1
"Unit";"Zergling";"Larva";1091;1
"Unit";"Zergling";"Larva";1091;1
"Unit";"Zergling";"Larva";1091;1
"Unit";"Zergling";"Larva";1091;1
"Unit";"Zergling";"Larva";1091;1
"Unit";"Zergling";"Larva";1091;1
"Unit";"Zergling";"Larva";1091;1
"Unit";"Zergling";"Larva";1091;1
"Unit";"Zergling";"Larva";1091;1
"Unit";"Zergling";"Larva";1091;1
"Unit";"Zergling";"Larva";1091;1
"Unit";"Zergling";"Larva";1091;1
"Unit";"Zergling";"Larva";1091;1
"Unit";"Zergling";"Larva";1091;1
"Unit";"Zergling";"Larva";1091;1
"Unit";"Zergling";"Larva";1091;1
"Unit";"Zergling";"Larva";1091;1
"Unit";"Zergling";"Larva";1091;1
"Unit";"Zergling";"Larva";1091;1
"Unit";"Zergling";"Larva";1091;1
"Unit";"Zergling";"Larva";1091;1
"Unit";"Zergling";"Larva";1091;1
"Unit";"Zergling";"Larva";1091;1
"Unit";"Zergling";"Larva";1091;1
"Unit";"Zergling";"Larva";1091;1
"Unit";"Zergling";"Larva";1091;1
"Unit";"Zergling";"Larva";1091;1
"Unit";"Zergling";"Larva";1091;1
"Unit";"Zergling";"Larva";1091;1
"Unit";"Zergling";"Larva";1091;1
"Unit";"Zergling";"Larva";1091;1
"Unit";"Zergling";"Larva";1091;1
"Unit";"Zergling";"Larva";1091;1
"Unit";"Zergling";"Larva";1091;1
"Unit";"Zergling";"Larva";1091;1
"Building";"SpineCrawler";NA;1091;0
"Unit";"Zergling";"Larva";1133;1
"Unit";"Zergling";"Larva";1133;1
"Unit";"Zergling";"Larva";1133;1
"Unit";"Zergling";"Larva";1133;1
"Unit";"Zergling";"Larva";1133;1
"Unit";"Zergling";"Larva";1133;1
"Unit";"Zergling";"Larva";1133;1
"Unit";"Zergling";"Larva";1133;1
"Unit";"Zergling";"Larva";1133;1
"Unit";"Zergling";"Larva";1133;1
"Unit";"Baneling";"Zergling";1133;0
"Unit";"Baneling";"Zergling";1133;0
"Unit";"Baneling";"Zergling";1133;0
"Unit";"Baneling";"Zergling";1133;0
"Unit";"Baneling";"Zergling";1133;0
"Unit";"Baneling";"Zergling";1133;0
"Unit";"Baneling";"Zergling";1133;0
"Building";"SpineCrawler";NA;1091;0
"Building";"SpineCrawler";NA;1091;0
"Unit";"Zergling";"Larva";1143;1
"Unit";"Zergling";"Larva";1143;1
"Unit";"Zergling";"Larva";1143;1
"Unit";"Zergling";"Larva";1143;1
"Unit";"Zergling";"Larva";1143;1
"Unit";"Zergling";"Larva";1143;1
"Unit";"Zergling";"Larva";1143;1
"Unit";"Zergling";"Larva";1143;1
"Unit";"Zergling";"Larva";1143;1
"Unit";"Zergling";"Larva";1143;1
"Unit";"Zergling";"Larva";1143;1
"Unit";"Zergling";"Larva";1143;1
"Unit";"Zergling";"Larva";1143;1
"Unit";"Zergling";"Larva";1143;1
"Unit";"Zergling";"Larva";1143;1
"Unit";"Zergling";"Larva";1143;1
"Unit";"Zergling";"Larva";1143;1
"Unit";"Zergling";"Larva";1143;1
"Unit";"Zergling";"Larva";1143;1
"Unit";"Zergling";"Larva";1143;1
"Unit";"Zergling";"Larva";1143;1
"Unit";"Zergling";"Larva";1143;1
"Unit";"Zergling";"Larva";1143;1
"Unit";"Zergling";"Larva";1143;1
"Unit";"Zergling";"Larva";1143;1
"Unit";"Zergling";"Larva";1143;1
"Unit";"Hydralisk";"Larva";1143;2
"Unit";"Hydralisk";"Larva";1143;2
"Unit";"Hydralisk";"Larva";1143;2
"Unit";"Hydralisk";"Larva";1143;2
"Unit";"Hydralisk";"Larva";1143;2
"Unit";"Hydralisk";"Larva";1143;2
"Unit";"Hydralisk";"Larva";1143;2
"Unit";"Corruptor";"Larva";1169;2
"Unit";"Baneling";"Zergling";1183;0
"Unit";"Baneling";"Zergling";1183;0
"Unit";"Baneling";"Zergling";1183;0
"Unit";"Baneling";"Zergling";1183;0
"Unit";"Baneling";"Zergling";1183;0
"Unit";"Baneling";"Zergling";1183;0
"Unit";"Baneling";"Zergling";1183;0
"Unit";"Corruptor";"Larva";1169;2
"Unit";"Corruptor";"Larva";1169;2
"Unit";"Hydralisk";"Larva";1183;2
"Unit";"Hydralisk";"Larva";1183;2
"Building";"SporeCrawler";NA;1185;0
"Building";"SporeCrawler";NA;1185;0
"Unit";"Hydralisk";"Larva";1185;2
"Unit";"Hydralisk";"Larva";1185;2
"Unit";"Corruptor";"Larva";1193;2
"Unit";"Corruptor";"Larva";1193;2
"Unit";"Queen";"Hatchery";1197;2
"Unit";"Zergling";"Larva";1206;1
"Unit";"Zergling";"Larva";1206;1
"Unit";"Zergling";"Larva";1206;1
"Unit";"Zergling";"Larva";1206;1
"Unit";"Zergling";"Larva";1206;1
"Unit";"Zergling";"Larva";1206;1
"Unit";"Zergling";"Larva";1206;1
"Unit";"Zergling";"Larva";1206;1
"Unit";"Zergling";"Larva";1206;1
"Unit";"Zergling";"Larva";1206;1
"Unit";"Zergling";"Larva";1206;1
"Unit";"Zergling";"Larva";1206;1
"Unit";"Zergling";"Larva";1206;1
"Unit";"Zergling";"Larva";1206;1
"Unit";"Zergling";"Larva";1206;1
"Unit";"Zergling";"Larva";1206;1
"Unit";"Zergling";"Larva";1206;1
"Unit";"Zergling";"Larva";1206;1
"Unit";"Zergling";"Larva";1206;1
"Unit";"Zergling";"Larva";1206;1
"Unit";"Zergling";"Larva";1206;1
"Unit";"Zergling";"Larva";1206;1
"Unit";"Zergling";"Larva";1206;1
"Unit";"Zergling";"Larva";1206;1
"Building";"Hatchery";NA;1206;0
"Unit";"Baneling";"Zergling";1208;0
"Unit";"Baneling";"Zergling";1216;0
"Unit";"Baneling";"Zergling";1224;0
"Unit";"Baneling";"Zergling";1226;0
"Unit";"Baneling";"Zergling";1230;0
"Unit";"Baneling";"Zergling";1230;0
"Unit";"Baneling";"Zergling";1230;0
"Unit";"Baneling";"Zergling";1230;0
"Unit";"Baneling";"Zergling";1230;0
"Unit";"Baneling";"Zergling";1230;0
"Unit";"Baneling";"Zergling";1230;0
"Unit";"Baneling";"Zergling";1230;0
"Building";"Hatchery";NA;1206;0
