"type";"unit_name";"on_building";"total_supply";"supply"
"Unit";"Overlord";"Larva";13;0
"Building";"Extractor";NA;19;0
"Unit";"Overlord";"Larva";22;0
"Building";"SpawningPool";NA;19;0
"Building";"Hatchery";NA;17;0
"Unit";"Zergling";"Larva";23;1
"Unit";"Zergling";"Larva";23;1
"Unit";"Zergling";"Larva";23;1
"Unit";"Zergling";"Larva";23;1
"Unit";"Queen";"Hatchery";22;2
"Unit";"Queen";"Hatchery";22;2
"Building";"CreepTumorQueen";NA;33;0
"Unit";"Overlord";"Larva";36;0
"Unit";"Zergling";"Larva";40;1
"Unit";"Zergling";"Larva";40;1
"Unit";"Queen";"Hatchery";39;2
"Unit";"Overlord";"Larva";41;0
"Building";"Hatchery";NA;29;0
"Unit";"Queen";"Hatchery";40;2
"Building";"CreepTumorQueen";NA;50;0
"Unit";"Overlord";"Larva";45;0
"Building";"CreepTumorQueen";NA;52;0
"Unit";"Zergling";"Larva";57;1
"Unit";"Zergling";"Larva";57;1
"Unit";"Queen";"Hatchery";50;2
"Unit";"Zergling";"Larva";57;1
"Unit";"Zergling";"Larva";57;1
"Building";"CreepTumor";NA;60;0
"Unit";"Queen";"Hatchery";52;2
"Building";"CreepTumorQueen";NA;69;0
"Building";"CreepTumor";NA;69;0
"Unit";"Overlord";"Larva";69;0
"Unit";"Overlord";"Larva";69;0
"Unit";"Overlord";"Larva";69;0
"Building";"CreepTumorQueen";NA;76;0
"Building";"Extractor";NA;74;0
"Building";"Extractor";NA;76;0
"Unit";"Overlord";"Larva";76;0
"Building";"CreepTumor";NA;78;0
"Unit";"Overlord";"Larva";78;0
"Building";"CreepTumor";NA;84;0
"Building";"EvolutionChamber";NA;76;0
"Building";"CreepTumor";NA;84;0
"Building";"EvolutionChamber";NA;76;0
"Unit";"Overlord";"Larva";84;0
"Unit";"Zergling";"Larva";88;1
"Unit";"Zergling";"Larva";88;1
"Unit";"Zergling";"Larva";88;1
"Unit";"Zergling";"Larva";88;1
"Unit";"Zergling";"Larva";88;1
"Unit";"Zergling";"Larva";88;1
"Unit";"Overlord";"Larva";88;0
"Building";"SporeCrawler";NA;90;0
"Building";"CreepTumor";NA;96;0
"Building";"SporeCrawler";NA;90;0
"Building";"SporeCrawler";NA;90;0
"Building";"Extractor";NA;90;0
"Building";"Extractor";NA;90;0
"Building";"CreepTumorQueen";NA;99;0
"Building";"CreepTumorQueen";NA;99;0
"Unit";"Zergling";"Larva";99;1
"Unit";"Zergling";"Larva";99;1
"Unit";"Zergling";"Larva";99;1
"Unit";"Zergling";"Larva";99;1
"Unit";"Zergling";"Larva";99;1
"Unit";"Zergling";"Larva";99;1
"Unit";"Zergling";"Larva";99;1
"Unit";"Zergling";"Larva";99;1
"Unit";"Zergling";"Larva";99;1
"Unit";"Zergling";"Larva";99;1
"Unit";"Zergling";"Larva";99;1
"Unit";"Zergling";"Larva";99;1
"Unit";"Zergling";"Larva";99;1
"Unit";"Zergling";"Larva";99;1
"Unit";"Zergling";"Larva";99;1
"Unit";"Zergling";"Larva";99;1
"Unit";"Zergling";"Larva";99;1
"Unit";"Zergling";"Larva";99;1
"Unit";"Zergling";"Larva";99;1
"Unit";"Zergling";"Larva";99;1
"Building";"BanelingNest";NA;90;0
"Building";"CreepTumorQueen";NA;121;0
"Building";"CreepTumorQueen";NA;121;0
"Building";"CreepTumorQueen";NA;122;0
"Building";"CreepTumorQueen";NA;122;0
"Unit";"Overlord";"Larva";125;0
"Building";"Extractor";NA;122;0
"Building";"CreepTumor";NA;137;0
"Building";"CreepTumor";NA;137;0
"Building";"CreepTumor";NA;137;0
"Building";"CreepTumor";NA;137;0
"Building";"CreepTumorQueen";NA;137;0
"Building";"CreepTumorQueen";NA;137;0
"Building";"CreepTumor";NA;137;0
"Building";"CreepTumor";NA;137;0
"Building";"CreepTumor";NA;137;0
"Building";"CreepTumor";NA;137;0
"Building";"Spire";NA;121;0
"Building";"Hatchery";NA;121;0
"Upgrade";"ZergGroundArmorsLevel1";"EvolutionChamber";99;0
"Upgrade";"ZergMeleeWeaponsLevel1";"EvolutionChamber";99;0
"Building";"CreepTumor";NA;144;0
"Building";"CreepTumor";NA;144;0
"Unit";"Overlord";"Larva";144;0
"Building";"CreepTumor";NA;146;0
"Unit";"Overlord";"Larva";144;0
"Building";"CreepTumor";NA;146;0
"Building";"CreepTumor";NA;146;0
"Building";"CreepTumor";NA;146;0
"Building";"CreepTumorQueen";NA;146;0
"Building";"CreepTumorQueen";NA;146;0
"Building";"CreepTumorQueen";NA;146;0
"Building";"CreepTumorQueen";NA;146;0
"Unit";"Zergling";"Larva";146;1
"Unit";"Zergling";"Larva";146;1
"Unit";"Zergling";"Larva";146;1
"Unit";"Zergling";"Larva";146;1
"Unit";"Zergling";"Larva";146;1
"Unit";"Zergling";"Larva";146;1
"Unit";"Zergling";"Larva";146;1
"Unit";"Zergling";"Larva";146;1
"Unit";"Mutalisk";"Larva";146;2
"Unit";"Mutalisk";"Larva";146;2
"Unit";"Mutalisk";"Larva";146;2
"Unit";"Mutalisk";"Larva";146;2
"Unit";"Mutalisk";"Larva";146;2
"Building";"CreepTumor";NA;150;0
"Unit";"Zergling";"Larva";150;1
"Unit";"Zergling";"Larva";150;1
"Unit";"Zergling";"Larva";150;1
"Unit";"Zergling";"Larva";150;1
"Building";"CreepTumor";NA;150;0
"Unit";"Zergling";"Larva";150;1
"Unit";"Zergling";"Larva";150;1
"Unit";"Zergling";"Larva";150;1
"Unit";"Zergling";"Larva";150;1
"Unit";"Zergling";"Larva";150;1
"Unit";"Zergling";"Larva";150;1
"Unit";"Zergling";"Larva";150;1
"Unit";"Zergling";"Larva";150;1
"Unit";"Zergling";"Larva";150;1
"Unit";"Zergling";"Larva";150;1
"Building";"CreepTumor";NA;150;0
"Building";"CreepTumor";NA;150;0
"Unit";"Overlord";"Larva";158;0
"Building";"CreepTumor";NA;182;0
"Building";"CreepTumor";NA;182;0
"Building";"CreepTumor";NA;182;0
"Building";"CreepTumor";NA;182;0
"Building";"CreepTumor";NA;182;0
"Building";"CreepTumor";NA;182;0
"Building";"CreepTumor";NA;182;0
"Building";"CreepTumor";NA;182;0
"Unit";"Baneling";"Zergling";185;0
"Unit";"Baneling";"Zergling";185;0
"Unit";"Baneling";"Zergling";185;0
"Unit";"Zergling";"Larva";185;1
"Unit";"Zergling";"Larva";185;1
"Unit";"Zergling";"Larva";185;1
"Unit";"Zergling";"Larva";185;1
"Unit";"Zergling";"Larva";185;1
"Unit";"Zergling";"Larva";185;1
"Unit";"Zergling";"Larva";185;1
"Unit";"Zergling";"Larva";185;1
"Unit";"Zergling";"Larva";185;1
"Unit";"Zergling";"Larva";185;1
"Unit";"Zergling";"Larva";185;1
"Unit";"Zergling";"Larva";185;1
"Unit";"Zergling";"Larva";185;1
"Unit";"Zergling";"Larva";185;1
"Unit";"Zergling";"Larva";185;1
"Unit";"Zergling";"Larva";185;1
"Unit";"Zergling";"Larva";185;1
"Unit";"Zergling";"Larva";185;1
"Unit";"Zergling";"Larva";185;1
"Unit";"Zergling";"Larva";185;1
"Building";"CreepTumor";NA;185;0
"Unit";"Mutalisk";"Larva";184;2
"Unit";"Mutalisk";"Larva";185;2
"Unit";"Mutalisk";"Larva";185;2
"Unit";"Mutalisk";"Larva";185;2
"Unit";"Mutalisk";"Larva";185;2
"Building";"CreepTumor";NA;185;0
"Building";"CreepTumor";NA;185;0
"Unit";"Overlord";"Larva";185;0
"Unit";"Baneling";"Zergling";186;0
"Unit";"Baneling";"Zergling";186;0
"Unit";"Baneling";"Zergling";186;0
"Building";"CreepTumor";NA;216;0
"Building";"CreepTumor";NA;216;0
"Building";"CreepTumor";NA;216;0
"Building";"CreepTumor";NA;216;0
"Building";"CreepTumor";NA;216;0
"Unit";"Zergling";"Larva";216;1
"Unit";"Zergling";"Larva";216;1
"Unit";"Zergling";"Larva";216;1
"Unit";"Zergling";"Larva";216;1
"Unit";"Zergling";"Larva";216;1
"Unit";"Zergling";"Larva";216;1
"Unit";"Zergling";"Larva";216;1
"Unit";"Zergling";"Larva";216;1
"Unit";"Zergling";"Larva";216;1
"Unit";"Zergling";"Larva";216;1
"Unit";"Zergling";"Larva";216;1
"Unit";"Zergling";"Larva";216;1
"Unit";"Zergling";"Larva";216;1
"Unit";"Zergling";"Larva";216;1
"Unit";"Zergling";"Larva";216;1
"Unit";"Zergling";"Larva";216;1
"Unit";"Zergling";"Larva";216;1
"Unit";"Zergling";"Larva";216;1
"Unit";"Zergling";"Larva";216;1
"Unit";"Zergling";"Larva";216;1
"Unit";"Zergling";"Larva";216;1
"Unit";"Zergling";"Larva";216;1
"Unit";"Zergling";"Larva";216;1
"Unit";"Zergling";"Larva";216;1
"Unit";"Zergling";"Larva";216;1
"Unit";"Zergling";"Larva";216;1
"Unit";"Zergling";"Larva";216;1
"Unit";"Zergling";"Larva";216;1
"Unit";"Zergling";"Larva";216;1
"Unit";"Zergling";"Larva";216;1
"Unit";"Zergling";"Larva";216;1
"Unit";"Zergling";"Larva";216;1
"Building";"Hatchery";NA;150;0
"Building";"CreepTumorQueen";NA;216;0
"Building";"Extractor";NA;216;0
"Building";"CreepTumor";NA;248;0
"Building";"CreepTumorQueen";NA;248;0
"Building";"CreepTumor";NA;248;0
"Building";"CreepTumor";NA;248;0
"Building";"CreepTumorQueen";NA;248;0
"Building";"Extractor";NA;216;0
"Building";"CreepTumorQueen";NA;250;0
"Building";"CreepTumor";NA;250;0
"Building";"CreepTumor";NA;250;0
"Unit";"Mutalisk";"Larva";216;2
"Unit";"Mutalisk";"Larva";216;2
"Unit";"Mutalisk";"Larva";216;2
"Building";"CreepTumor";NA;250;0
"Unit";"Overlord";"Larva";250;0
"Unit";"Overlord";"Larva";250;0
"Building";"CreepTumor";NA;250;0
"Unit";"Overlord";"Larva";250;0
"Building";"InfestationPit";NA;216;0
"Unit";"Zergling";"Larva";250;1
"Unit";"Zergling";"Larva";250;1
"Unit";"Zergling";"Larva";250;1
"Unit";"Zergling";"Larva";250;1
"Unit";"Zergling";"Larva";250;1
"Unit";"Zergling";"Larva";250;1
"Unit";"Zergling";"Larva";250;1
"Unit";"Zergling";"Larva";250;1
"Unit";"Zergling";"Larva";250;1
"Unit";"Zergling";"Larva";250;1
"Unit";"Zergling";"Larva";250;1
"Unit";"Zergling";"Larva";250;1
"Unit";"Zergling";"Larva";250;1
"Unit";"Zergling";"Larva";250;1
"Building";"CreepTumorQueen";NA;250;0
"Building";"CreepTumor";NA;270;0
"Building";"CreepTumor";NA;270;0
"Upgrade";"ZergGroundArmorsLevel2";"EvolutionChamber";185;0
"Upgrade";"ZergMeleeWeaponsLevel2";"EvolutionChamber";185;0
"Unit";"Mutalisk";"Larva";270;2
"Unit";"Mutalisk";"Larva";270;2
"Unit";"Mutalisk";"Larva";270;2
"Unit";"Mutalisk";"Larva";270;2
"Unit";"Mutalisk";"Larva";270;2
"Unit";"Overlord";"Larva";270;0
"Unit";"Queen";"Hatchery";250;2
"Unit";"Overlord";"Larva";273;0
"Unit";"Overlord";"Larva";273;0
"Building";"CreepTumorQueen";NA;273;0
"Building";"CreepTumor";NA;285;0
"Building";"CreepTumor";NA;285;0
"Building";"SporeCrawler";NA;285;0
"Building";"CreepTumor";NA;285;0
"Building";"CreepTumor";NA;285;0
"Building";"SporeCrawler";NA;285;0
"Building";"SporeCrawler";NA;285;0
"Unit";"Zergling";"Larva";285;1
"Unit";"Zergling";"Larva";285;1
"Unit";"Zergling";"Larva";285;1
"Unit";"Zergling";"Larva";285;1
"Unit";"Zergling";"Larva";285;1
"Unit";"Zergling";"Larva";285;1
"Unit";"Zergling";"Larva";285;1
"Unit";"Zergling";"Larva";285;1
"Unit";"Zergling";"Larva";285;1
"Unit";"Zergling";"Larva";285;1
"Unit";"Zergling";"Larva";285;1
"Unit";"Zergling";"Larva";285;1
"Unit";"Zergling";"Larva";285;1
"Unit";"Zergling";"Larva";285;1
"Unit";"Zergling";"Larva";285;1
"Unit";"Zergling";"Larva";285;1
"Unit";"Zergling";"Larva";285;1
"Unit";"Zergling";"Larva";285;1
"Unit";"Zergling";"Larva";285;1
"Unit";"Zergling";"Larva";285;1
"Building";"CreepTumor";NA;287;0
"Building";"CreepTumor";NA;289;0
"Unit";"Queen";"Hatchery";285;2
"Building";"SpineCrawler";NA;285;0
"Building";"SpineCrawler";NA;285;0
"Unit";"Zergling";"Larva";309;1
"Unit";"Zergling";"Larva";309;1
"Unit";"Zergling";"Larva";309;1
"Unit";"Zergling";"Larva";309;1
"Unit";"Zergling";"Larva";309;1
"Unit";"Zergling";"Larva";309;1
"Unit";"Zergling";"Larva";309;1
"Unit";"Zergling";"Larva";309;1
"Unit";"Zergling";"Larva";309;1
"Unit";"Zergling";"Larva";309;1
"Unit";"Zergling";"Larva";309;1
"Unit";"Zergling";"Larva";309;1
"Unit";"Zergling";"Larva";309;1
"Unit";"Zergling";"Larva";309;1
"Unit";"Zergling";"Larva";309;1
"Unit";"Zergling";"Larva";309;1
"Unit";"Zergling";"Larva";309;1
"Unit";"Zergling";"Larva";309;1
"Unit";"Baneling";"Zergling";312;0
"Unit";"Baneling";"Zergling";312;0
"Unit";"Baneling";"Zergling";312;0
"Unit";"Baneling";"Zergling";312;0
"Unit";"Baneling";"Zergling";312;0
"Unit";"Baneling";"Zergling";312;0
"Unit";"Baneling";"Zergling";312;0
"Unit";"Baneling";"Zergling";312;0
"Unit";"Baneling";"Zergling";312;0
"Unit";"Baneling";"Zergling";312;0
"Building";"SpineCrawler";NA;311;0
"Building";"CreepTumor";NA;334;0
"Building";"CreepTumor";NA;334;0
"Unit";"Zergling";"Larva";332;1
"Unit";"Zergling";"Larva";332;1
"Unit";"Zergling";"Larva";332;1
"Unit";"Zergling";"Larva";332;1
"Unit";"Zergling";"Larva";332;1
"Unit";"Zergling";"Larva";332;1
"Unit";"Zergling";"Larva";332;1
"Unit";"Zergling";"Larva";332;1
"Unit";"Zergling";"Larva";332;1
"Unit";"Zergling";"Larva";332;1
"Unit";"Zergling";"Larva";332;1
"Unit";"Zergling";"Larva";332;1
"Unit";"Zergling";"Larva";333;1
"Unit";"Zergling";"Larva";333;1
"Unit";"Zergling";"Larva";333;1
"Unit";"Zergling";"Larva";333;1
"Unit";"Zergling";"Larva";333;1
"Unit";"Zergling";"Larva";333;1
"Unit";"Zergling";"Larva";333;1
"Unit";"Zergling";"Larva";333;1
"Unit";"Zergling";"Larva";333;1
"Unit";"Zergling";"Larva";333;1
"Unit";"Zergling";"Larva";333;1
"Unit";"Zergling";"Larva";333;1
"Unit";"Queen";"Hatchery";332;2
"Building";"CreepTumor";NA;334;0
"Unit";"Overlord";"Larva";358;0
"Unit";"Zergling";"Larva";358;1
"Unit";"Zergling";"Larva";358;1
"Unit";"Zergling";"Larva";358;1
"Unit";"Zergling";"Larva";358;1
"Unit";"Zergling";"Larva";358;1
"Unit";"Zergling";"Larva";358;1
"Unit";"Zergling";"Larva";358;1
"Unit";"Zergling";"Larva";358;1
"Unit";"Zergling";"Larva";358;1
"Unit";"Zergling";"Larva";358;1
"Unit";"Zergling";"Larva";358;1
"Unit";"Zergling";"Larva";358;1
"Unit";"Zergling";"Larva";358;1
"Unit";"Zergling";"Larva";358;1
"Unit";"Zergling";"Larva";358;1
"Unit";"Zergling";"Larva";358;1
"Unit";"Zergling";"Larva";358;1
"Unit";"Zergling";"Larva";358;1
"Unit";"Zergling";"Larva";358;1
"Unit";"Zergling";"Larva";358;1
"Unit";"Zergling";"Larva";358;1
"Unit";"Zergling";"Larva";358;1
"Unit";"Zergling";"Larva";360;1
"Unit";"Zergling";"Larva";360;1
"Unit";"Baneling";"Zergling";360;0
"Unit";"Baneling";"Zergling";360;0
"Unit";"Baneling";"Zergling";360;0
"Unit";"Baneling";"Zergling";360;0
"Unit";"Baneling";"Zergling";360;0
"Unit";"Baneling";"Zergling";360;0
"Unit";"Baneling";"Zergling";360;0
"Unit";"Baneling";"Zergling";360;0
"Unit";"Baneling";"Zergling";360;0
"Unit";"Baneling";"Zergling";360;0
"Unit";"Baneling";"Zergling";360;0
"Unit";"Baneling";"Zergling";360;0
"Unit";"Baneling";"Zergling";360;0
"Building";"CreepTumor";NA;360;0
"Building";"CreepTumor";NA;360;0
"Building";"CreepTumor";NA;384;0
"Building";"CreepTumor";NA;384;0
"Building";"CreepTumor";NA;384;0
"Building";"UltraliskCavern";NA;334;0
"Building";"CreepTumorQueen";NA;384;0
"Unit";"Baneling";"Zergling";384;0
"Unit";"Baneling";"Zergling";384;0
