"type";"unit_name";"on_building";"total_supply";"supply"
"Unit";"Overlord";"Larva";13;0
"Building";"Extractor";NA;18;0
"Unit";"Overlord";"Larva";21;0
"Building";"SpawningPool";NA;19;0
"Building";"Hatchery";NA;17;0
"Unit";"Zergling";"Larva";23;1
"Unit";"Zergling";"Larva";23;1
"Unit";"Zergling";"Larva";23;1
"Unit";"Zergling";"Larva";23;1
"Unit";"Queen";"Hatchery";22;2
"Unit";"Queen";"Hatchery";23;2
"Unit";"Overlord";"Larva";36;0
"Unit";"Queen";"Hatchery";35;2
"Unit";"Overlord";"Larva";37;0
"Building";"CreepTumorQueen";NA;40;0
"Building";"Hatchery";NA;28;0
"Building";"CreepTumorQueen";NA;47;0
"Building";"CreepTumor";NA;47;0
"Unit";"Queen";"Hatchery";42;2
"Unit";"Queen";"Hatchery";47;2
"Unit";"Queen";"Hatchery";50;2
"Building";"EvolutionChamber";NA;50;0
"Building";"CreepTumorQueen";NA;59;0
"Unit";"Overlord";"Larva";56;0
"Unit";"Overlord";"Larva";59;0
"Building";"CreepTumorQueen";NA;65;0
"Building";"SporeCrawler";NA;63;0
"Building";"BanelingNest";NA;50;0
"Building";"SporeCrawler";NA;65;0
"Unit";"Zergling";"Larva";65;1
"Unit";"Zergling";"Larva";65;1
"Unit";"Zergling";"Larva";65;1
"Unit";"Zergling";"Larva";65;1
"Unit";"Zergling";"Larva";65;1
"Unit";"Zergling";"Larva";65;1
"Unit";"Zergling";"Larva";65;1
"Unit";"Zergling";"Larva";65;1
"Building";"SporeCrawler";NA;65;0
"Building";"CreepTumor";NA;65;0
"Building";"CreepTumorQueen";NA;65;0
"Unit";"Baneling";"Zergling";77;0
"Unit";"Baneling";"Zergling";77;0
"Unit";"Baneling";"Zergling";77;0
"Unit";"Baneling";"Zergling";77;0
"Building";"CreepTumorQueen";NA;77;0
"Building";"CreepTumor";NA;77;0
"Building";"CreepTumorQueen";NA;77;0
"Building";"Extractor";NA;77;0
"Building";"CreepTumorQueen";NA;90;0
"Building";"CreepTumorQueen";NA;90;0
"Building";"CreepTumor";NA;90;0
"Building";"CreepTumorQueen";NA;90;0
"Building";"CreepTumor";NA;90;0
"Unit";"Overlord";"Larva";90;0
"Unit";"Overlord";"Larva";90;0
"Building";"CreepTumor";NA;90;0
"Unit";"Overlord";"Larva";90;0
"Building";"CreepTumor";NA;90;0
"Unit";"Overlord";"Larva";90;0
"Building";"CreepTumorQueen";NA;90;0
"Building";"Extractor";NA;90;0
"Building";"CreepTumor";NA;90;0
"Building";"CreepTumor";NA;90;0
"Building";"CreepTumor";NA;90;0
"Building";"CreepTumor";NA;102;0
"Building";"CreepTumor";NA;102;0
"Building";"CreepTumor";NA;102;0
"Building";"EvolutionChamber";NA;90;0
"Building";"CreepTumor";NA;102;0
"Building";"SporeCrawler";NA;102;0
"Building";"Extractor";NA;102;0
"Building";"Extractor";NA;102;0
"Building";"Extractor";NA;102;0
"Unit";"Overlord";"Larva";102;0
"Unit";"Overlord";"Larva";102;0
"Unit";"Zergling";"Larva";112;1
"Unit";"Zergling";"Larva";112;1
"Unit";"Zergling";"Larva";112;1
"Unit";"Zergling";"Larva";112;1
"Building";"CreepTumor";NA;118;0
"Building";"CreepTumor";NA;118;0
"Building";"CreepTumor";NA;118;0
"Building";"Hatchery";NA;90;0
"Unit";"Zergling";"Larva";118;1
"Unit";"Zergling";"Larva";118;1
"Unit";"Zergling";"Larva";118;1
"Unit";"Zergling";"Larva";118;1
"Unit";"Zergling";"Larva";118;1
"Unit";"Zergling";"Larva";118;1
"Unit";"Zergling";"Larva";118;1
"Unit";"Zergling";"Larva";118;1
"Unit";"Zergling";"Larva";118;1
"Unit";"Zergling";"Larva";118;1
"Building";"CreepTumor";NA;122;0
"Upgrade";"ZergGroundArmorsLevel1";"EvolutionChamber";90;0
"Unit";"Zergling";"Larva";118;1
"Unit";"Zergling";"Larva";118;1
"Unit";"Zergling";"Larva";118;1
"Unit";"Zergling";"Larva";118;1
"Unit";"Zergling";"Larva";118;1
"Unit";"Zergling";"Larva";118;1
"Unit";"Zergling";"Larva";118;1
"Unit";"Zergling";"Larva";118;1
"Unit";"Zergling";"Larva";118;1
"Unit";"Zergling";"Larva";118;1
"Unit";"Zergling";"Larva";118;1
"Unit";"Zergling";"Larva";118;1
"Unit";"Zergling";"Larva";118;1
"Unit";"Zergling";"Larva";118;1
"Building";"CreepTumor";NA;132;0
"Building";"CreepTumor";NA;132;0
"Building";"Hatchery";NA;102;0
"Unit";"Zergling";"Larva";132;1
"Unit";"Zergling";"Larva";132;1
"Unit";"Zergling";"Larva";132;1
"Unit";"Zergling";"Larva";132;1
"Unit";"Zergling";"Larva";132;1
"Unit";"Zergling";"Larva";132;1
"Building";"HydraliskDen";NA;118;0
"Unit";"Baneling";"Zergling";132;0
"Unit";"Baneling";"Zergling";132;0
"Unit";"Baneling";"Zergling";132;0
"Unit";"Baneling";"Zergling";132;0
"Unit";"Baneling";"Zergling";132;0
"Building";"InfestationPit";NA;118;0
"Unit";"Zergling";"Larva";146;1
"Unit";"Zergling";"Larva";146;1
"Unit";"Zergling";"Larva";146;1
"Unit";"Zergling";"Larva";146;1
"Building";"CreepTumor";NA;146;0
"Unit";"Zergling";"Larva";146;1
"Unit";"Zergling";"Larva";146;1
"Unit";"Zergling";"Larva";146;1
"Unit";"Zergling";"Larva";146;1
"Unit";"Zergling";"Larva";146;1
"Unit";"Zergling";"Larva";146;1
"Unit";"Zergling";"Larva";146;1
"Unit";"Zergling";"Larva";146;1
"Building";"CreepTumor";NA;152;0
"Building";"CreepTumor";NA;152;0
"Building";"CreepTumor";NA;152;0
"Unit";"Zergling";"Larva";152;1
"Unit";"Zergling";"Larva";152;1
"Unit";"Hydralisk";"Larva";152;2
"Unit";"Hydralisk";"Larva";152;2
"Unit";"Hydralisk";"Larva";152;2
"Unit";"Hydralisk";"Larva";152;2
"Unit";"Hydralisk";"Larva";152;2
"Unit";"Hydralisk";"Larva";152;2
"Unit";"Hydralisk";"Larva";152;2
"Unit";"Baneling";"Zergling";166;0
"Unit";"Baneling";"Zergling";166;0
"Unit";"Baneling";"Zergling";166;0
"Unit";"Baneling";"Zergling";166;0
"Unit";"Baneling";"Zergling";166;0
"Unit";"Baneling";"Zergling";166;0
"Unit";"Overlord";"Larva";166;0
"Unit";"Overlord";"Larva";166;0
"Unit";"Overlord";"Larva";166;0
"Unit";"Hydralisk";"Larva";164;2
"Unit";"Hydralisk";"Larva";164;2
"Unit";"Hydralisk";"Larva";164;2
"Unit";"Hydralisk";"Larva";164;2
"Unit";"Baneling";"Zergling";166;0
"Unit";"Hydralisk";"Larva";164;2
"Building";"Extractor";NA;166;0
"Building";"Extractor";NA;166;0
"Upgrade";"ZergMeleeWeaponsLevel1";"EvolutionChamber";122;0
"Unit";"Hydralisk";"Larva";190;2
"Unit";"Hydralisk";"Larva";190;2
"Unit";"Hydralisk";"Larva";190;2
"Unit";"Hydralisk";"Larva";190;2
"Unit";"Overlord";"Larva";200;0
"Unit";"Overlord";"Larva";200;0
"Unit";"Overlord";"Larva";200;0
"Unit";"Hydralisk";"Larva";191;2
"Unit";"Hydralisk";"Larva";191;2
"Unit";"Hydralisk";"Larva";192;2
"Upgrade";"EvolveMuscularAugments";"HydraliskDen";180;0
"Unit";"Overlord";"Larva";200;0
"Unit";"Overlord";"Larva";200;0
"Unit";"Overlord";"Larva";200;0
"Building";"CreepTumorQueen";NA;208;0
"Unit";"Overlord";"Larva";208;0
"Unit";"Overlord";"Larva";208;0
"Unit";"Overlord";"Larva";208;0
"Building";"CreepTumor";NA;219;0
"Building";"Extractor";NA;219;0
"Building";"Extractor";NA;219;0
"Unit";"Zergling";"Larva";219;1
"Unit";"Zergling";"Larva";219;1
"Unit";"Zergling";"Larva";219;1
"Unit";"Zergling";"Larva";219;1
"Unit";"Zergling";"Larva";219;1
"Unit";"Zergling";"Larva";219;1
"Unit";"Zergling";"Larva";219;1
"Unit";"Zergling";"Larva";219;1
"Unit";"Zergling";"Larva";219;1
"Unit";"Zergling";"Larva";219;1
"Unit";"Baneling";"Zergling";219;0
"Unit";"Baneling";"Zergling";219;0
"Unit";"Baneling";"Zergling";219;0
"Unit";"Baneling";"Zergling";219;0
"Unit";"Baneling";"Zergling";219;0
"Unit";"Hydralisk";"Larva";219;2
"Unit";"Hydralisk";"Larva";219;2
"Unit";"Hydralisk";"Larva";219;2
"Unit";"Hydralisk";"Larva";219;2
"Unit";"Hydralisk";"Larva";219;2
"Unit";"Zergling";"Larva";225;1
"Unit";"Zergling";"Larva";225;1
"Unit";"Zergling";"Larva";225;1
"Unit";"Zergling";"Larva";225;1
"Unit";"Zergling";"Larva";225;1
"Unit";"Zergling";"Larva";225;1
"Building";"CreepTumor";NA;229;0
"Building";"CreepTumor";NA;235;0
"Unit";"Hydralisk";"Larva";225;2
"Unit";"Hydralisk";"Larva";225;2
"Building";"CreepTumor";NA;245;0
"Unit";"Zergling";"Larva";245;1
"Unit";"Zergling";"Larva";245;1
"Unit";"Zergling";"Larva";245;1
"Unit";"Zergling";"Larva";245;1
"Unit";"Zergling";"Larva";245;1
"Unit";"Zergling";"Larva";245;1
"Unit";"Zergling";"Larva";245;1
"Unit";"Zergling";"Larva";245;1
"Unit";"Zergling";"Larva";247;1
"Unit";"Zergling";"Larva";247;1
"Unit";"Zergling";"Larva";249;1
"Unit";"Zergling";"Larva";249;1
"Unit";"Baneling";"Zergling";251;0
"Unit";"Baneling";"Zergling";251;0
"Unit";"Baneling";"Zergling";251;0
"Unit";"Baneling";"Zergling";251;0
"Unit";"Baneling";"Zergling";251;0
"Unit";"Baneling";"Zergling";253;0
"Unit";"Baneling";"Zergling";255;0
"Unit";"Baneling";"Zergling";255;0
"Unit";"Baneling";"Zergling";255;0
"Unit";"Hydralisk";"Larva";245;2
"Unit";"Hydralisk";"Larva";245;2
"Unit";"Hydralisk";"Larva";245;2
"Unit";"Hydralisk";"Larva";245;2
"Unit";"Hydralisk";"Larva";247;2
"Unit";"Hydralisk";"Larva";249;2
"Building";"CreepTumor";NA;279;0
"Building";"CreepTumor";NA;279;0
"Building";"SporeCrawler";NA;267;0
"Unit";"Zergling";"Larva";279;1
"Unit";"Zergling";"Larva";279;1
"Unit";"Zergling";"Larva";279;1
"Unit";"Zergling";"Larva";279;1
"Unit";"Zergling";"Larva";279;1
"Unit";"Zergling";"Larva";279;1
"Unit";"Zergling";"Larva";279;1
"Unit";"Zergling";"Larva";279;1
"Unit";"Zergling";"Larva";279;1
"Unit";"Zergling";"Larva";279;1
"Unit";"Zergling";"Larva";279;1
"Unit";"Zergling";"Larva";279;1
"Upgrade";"EvolveGroovedSpines";"HydraliskDen";235;0
"Unit";"Zergling";"Larva";279;1
"Unit";"Zergling";"Larva";279;1
"Unit";"Zergling";"Larva";291;1
"Unit";"Zergling";"Larva";291;1
"Unit";"Zergling";"Larva";291;1
"Unit";"Zergling";"Larva";291;1
"Unit";"Zergling";"Larva";291;1
"Unit";"Zergling";"Larva";291;1
"Unit";"Zergling";"Larva";291;1
"Unit";"Zergling";"Larva";291;1
"Unit";"Zergling";"Larva";291;1
"Unit";"Zergling";"Larva";291;1
"Unit";"Zergling";"Larva";291;1
"Unit";"Zergling";"Larva";291;1
"Unit";"Zergling";"Larva";291;1
"Unit";"Zergling";"Larva";291;1
"Unit";"Zergling";"Larva";291;1
"Unit";"Zergling";"Larva";291;1
"Unit";"Zergling";"Larva";291;1
"Unit";"Zergling";"Larva";291;1
"Unit";"Zergling";"Larva";291;1
"Unit";"Zergling";"Larva";291;1
"Unit";"Zergling";"Larva";291;1
"Unit";"Zergling";"Larva";291;1
"Unit";"Zergling";"Larva";291;1
"Unit";"Zergling";"Larva";291;1
"Upgrade";"ZergGroundArmorsLevel2";"EvolutionChamber";222;0
"Unit";"Hydralisk";"Larva";291;2
"Unit";"Hydralisk";"Larva";291;2
"Unit";"Hydralisk";"Larva";291;2
"Unit";"Hydralisk";"Larva";291;2
"Unit";"Hydralisk";"Larva";291;2
"Unit";"Hydralisk";"Larva";291;2
"Unit";"Hydralisk";"Larva";291;2
"Unit";"Hydralisk";"Larva";291;2
"Unit";"Hydralisk";"Larva";291;2
"Unit";"Hydralisk";"Larva";291;2
"Unit";"Hydralisk";"Larva";291;2
"Building";"UltraliskCavern";NA;279;0
"Upgrade";"ZergMeleeWeaponsLevel2";"EvolutionChamber";225;0
"Unit";"Zergling";"Larva";293;1
"Unit";"Zergling";"Larva";293;1
"Unit";"Zergling";"Larva";293;1
"Unit";"Zergling";"Larva";293;1
"Unit";"Zergling";"Larva";293;1
"Unit";"Zergling";"Larva";293;1
"Unit";"Zergling";"Larva";293;1
"Unit";"Zergling";"Larva";293;1
"Unit";"Zergling";"Larva";293;1
"Unit";"Zergling";"Larva";293;1
"Unit";"Zergling";"Larva";293;1
"Unit";"Zergling";"Larva";293;1
"Unit";"Hydralisk";"Larva";293;2
"Unit";"Hydralisk";"Larva";293;2
"Unit";"Hydralisk";"Larva";293;2
"Unit";"Hydralisk";"Larva";293;2
"Unit";"Hydralisk";"Larva";293;2
"Unit";"Zergling";"Larva";339;1
"Unit";"Zergling";"Larva";339;1
"Unit";"Zergling";"Larva";339;1
"Unit";"Zergling";"Larva";339;1
"Unit";"Zergling";"Larva";339;1
"Unit";"Zergling";"Larva";339;1
"Unit";"Zergling";"Larva";339;1
"Unit";"Zergling";"Larva";339;1
"Unit";"Zergling";"Larva";339;1
"Unit";"Zergling";"Larva";339;1
"Unit";"Hydralisk";"Larva";339;2
"Unit";"Hydralisk";"Larva";339;2
"Unit";"Hydralisk";"Larva";339;2
"Unit";"Hydralisk";"Larva";339;2
"Building";"CreepTumor";NA;371;0
"Unit";"Baneling";"Zergling";371;0
"Unit";"Baneling";"Zergling";371;0
"Unit";"Baneling";"Zergling";371;0
"Unit";"Baneling";"Zergling";371;0
"Unit";"Baneling";"Zergling";371;0
"Unit";"Baneling";"Zergling";371;0
"Unit";"Baneling";"Zergling";371;0
"Unit";"Baneling";"Zergling";371;0
"Unit";"Baneling";"Zergling";371;0
"Unit";"Baneling";"Zergling";371;0
"Unit";"Baneling";"Zergling";371;0
"Unit";"Baneling";"Zergling";371;0
"Unit";"Baneling";"Zergling";379;0
"Unit";"Baneling";"Zergling";379;0
"Unit";"Baneling";"Zergling";379;0
"Unit";"Baneling";"Zergling";379;0
"Unit";"Baneling";"Zergling";379;0
"Unit";"Baneling";"Zergling";379;0
"Unit";"Baneling";"Zergling";379;0
"Unit";"Baneling";"Zergling";379;0
"Unit";"Baneling";"Zergling";379;0
"Unit";"Baneling";"Zergling";379;0
"Unit";"Overlord";"Larva";379;0
"Unit";"Overlord";"Larva";379;0
"Unit";"Overlord";"Larva";379;0
"Building";"CreepTumor";NA;379;0
"Building";"CreepTumor";NA;379;0
"Building";"CreepTumor";NA;379;0
"Unit";"Ultralisk";"Larva";379;6
"Building";"EvolutionChamber";NA;379;0
"Building";"EvolutionChamber";NA;379;0
"Upgrade";"ChitinousPlating";"UltraliskCavern";379;0
"Building";"Spire";NA;379;0
"Building";"CreepTumor";NA;385;0
"Unit";"Zergling";"Larva";385;1
"Unit";"Zergling";"Larva";385;1
"Unit";"Viper";"Larva";385;3
"Unit";"Ultralisk";"Larva";385;6
"Unit";"Ultralisk";"Larva";385;6
"Unit";"Ultralisk";"Larva";385;6
"Unit";"Ultralisk";"Larva";385;6
"Unit";"Ultralisk";"Larva";385;6
"Unit";"Zergling";"Larva";385;1
"Unit";"Zergling";"Larva";385;1
"Unit";"Zergling";"Larva";385;1
"Unit";"Zergling";"Larva";385;1
"Building";"CreepTumor";NA;390;0
"Building";"CreepTumor";NA;390;0
"Unit";"Viper";"Larva";385;3
"Unit";"Baneling";"Zergling";424;0
"Unit";"Baneling";"Zergling";424;0
"Unit";"Baneling";"Zergling";424;0
"Unit";"Baneling";"Zergling";424;0
"Unit";"Baneling";"Zergling";424;0
"Unit";"Baneling";"Zergling";424;0
"Building";"SporeCrawler";NA;427;0
"Building";"SporeCrawler";NA;427;0
"Building";"CreepTumorQueen";NA;427;0
"Unit";"Zergling";"Larva";427;1
"Unit";"Zergling";"Larva";427;1
"Unit";"Zergling";"Larva";427;1
"Unit";"Zergling";"Larva";427;1
"Building";"CreepTumor";NA;427;0
"Building";"CreepTumorQueen";NA;427;0
"Building";"CreepTumor";NA;427;0
"Building";"CreepTumorQueen";NA;427;0
"Building";"CreepTumor";NA;427;0
"Unit";"Queen";"Hatchery";427;2
"Building";"CreepTumorQueen";NA;427;0
"Building";"CreepTumorQueen";NA;427;0
"Building";"CreepTumorQueen";NA;431;0
"Building";"CreepTumorQueen";NA;431;0
"Building";"CreepTumorQueen";NA;431;0
"Building";"CreepTumorQueen";NA;431;0
"Building";"Hatchery";NA;390;0
"Building";"CreepTumorQueen";NA;433;0
"Building";"SporeCrawler";NA;433;0
"Upgrade";"ZergGroundArmorsLevel3";"EvolutionChamber";385;0
"Upgrade";"ZergMeleeWeaponsLevel3";"EvolutionChamber";385;0
"Unit";"Zergling";"Larva";433;1
"Unit";"Zergling";"Larva";433;1
"Unit";"Zergling";"Larva";433;1
"Unit";"Zergling";"Larva";433;1
"Unit";"Zergling";"Larva";433;1
"Unit";"Zergling";"Larva";433;1
"Unit";"Zergling";"Larva";433;1
"Unit";"Zergling";"Larva";433;1
"Unit";"Zergling";"Larva";433;1
"Unit";"Zergling";"Larva";433;1
"Unit";"Zergling";"Larva";435;1
"Unit";"Zergling";"Larva";435;1
"Unit";"Zergling";"Larva";435;1
"Unit";"Zergling";"Larva";435;1
"Unit";"Zergling";"Larva";439;1
"Unit";"Zergling";"Larva";439;1
"Unit";"Zergling";"Larva";441;1
"Unit";"Zergling";"Larva";441;1
"Unit";"Zergling";"Larva";441;1
"Unit";"Zergling";"Larva";441;1
"Unit";"Zergling";"Larva";441;1
"Unit";"Zergling";"Larva";441;1
"Unit";"Zergling";"Larva";441;1
"Unit";"Zergling";"Larva";441;1
"Building";"Hatchery";NA;427;0
"Unit";"Zergling";"Larva";441;1
"Unit";"Zergling";"Larva";441;1
"Unit";"Zergling";"Larva";441;1
"Unit";"Zergling";"Larva";441;1
"Unit";"Zergling";"Larva";441;1
"Unit";"Zergling";"Larva";441;1
"Unit";"Zergling";"Larva";441;1
"Unit";"Zergling";"Larva";441;1
"Unit";"Zergling";"Larva";441;1
"Unit";"Zergling";"Larva";441;1
"Unit";"Zergling";"Larva";441;1
"Unit";"Zergling";"Larva";441;1
"Unit";"Zergling";"Larva";441;1
"Unit";"Zergling";"Larva";441;1
"Upgrade";"ZergMissileWeaponsLevel1";"EvolutionChamber";427;0
"Unit";"Hydralisk";"Larva";433;2
"Unit";"Hydralisk";"Larva";435;2
"Unit";"Hydralisk";"Larva";435;2
"Unit";"Hydralisk";"Larva";439;2
"Unit";"Hydralisk";"Larva";441;2
"Unit";"Hydralisk";"Larva";441;2
"Unit";"Hydralisk";"Larva";441;2
"Unit";"Hydralisk";"Larva";441;2
"Unit";"Hydralisk";"Larva";441;2
"Unit";"Hydralisk";"Larva";441;2
"Unit";"Hydralisk";"Larva";441;2
"Unit";"Hydralisk";"Larva";441;2
"Unit";"Hydralisk";"Larva";441;2
"Unit";"Viper";"Larva";441;3
"Unit";"Viper";"Larva";441;3
"Unit";"Viper";"Larva";441;3
"Unit";"Viper";"Larva";441;3
"Unit";"Zergling";"Larva";471;1
"Unit";"Zergling";"Larva";471;1
"Unit";"Zergling";"Larva";471;1
"Unit";"Zergling";"Larva";471;1
"Unit";"Zergling";"Larva";471;1
"Unit";"Zergling";"Larva";471;1
"Unit";"Zergling";"Larva";471;1
"Unit";"Zergling";"Larva";471;1
"Unit";"Zergling";"Larva";471;1
"Unit";"Zergling";"Larva";471;1
"Unit";"Zergling";"Larva";471;1
"Unit";"Zergling";"Larva";471;1
"Unit";"Zergling";"Larva";471;1
"Unit";"Zergling";"Larva";471;1
"Unit";"Zergling";"Larva";471;1
"Unit";"Zergling";"Larva";471;1
"Unit";"Zergling";"Larva";471;1
"Unit";"Zergling";"Larva";471;1
"Unit";"Zergling";"Larva";471;1
"Unit";"Zergling";"Larva";471;1
"Unit";"Zergling";"Larva";471;1
"Unit";"Zergling";"Larva";471;1
"Unit";"Zergling";"Larva";471;1
"Unit";"Zergling";"Larva";471;1
"Unit";"Hydralisk";"Larva";471;2
"Unit";"Hydralisk";"Larva";471;2
"Unit";"Hydralisk";"Larva";471;2
"Unit";"Hydralisk";"Larva";471;2
"Building";"CreepTumor";NA;541;0
"Building";"CreepTumor";NA;541;0
"Building";"CreepTumor";NA;541;0
"Building";"CreepTumor";NA;541;0
"Building";"CreepTumor";NA;541;0
"Building";"CreepTumor";NA;541;0
"Building";"CreepTumor";NA;541;0
"Building";"CreepTumor";NA;541;0
"Unit";"Hydralisk";"Larva";541;2
"Unit";"Hydralisk";"Larva";541;2
"Unit";"Hydralisk";"Larva";541;2
"Unit";"Hydralisk";"Larva";541;2
"Unit";"Baneling";"Zergling";541;0
"Unit";"Baneling";"Zergling";541;0
"Unit";"Baneling";"Zergling";541;0
"Unit";"Baneling";"Zergling";541;0
"Unit";"Baneling";"Zergling";541;0
"Unit";"Baneling";"Zergling";541;0
"Building";"CreepTumor";NA;541;0
"Unit";"Baneling";"Zergling";541;0
"Unit";"Baneling";"Zergling";541;0
"Unit";"Baneling";"Zergling";541;0
"Unit";"Baneling";"Zergling";541;0
"Unit";"Baneling";"Zergling";541;0
"Unit";"Baneling";"Zergling";541;0
"Unit";"Baneling";"Zergling";541;0
"Unit";"Baneling";"Zergling";541;0
"Building";"CreepTumor";NA;541;0
"Building";"CreepTumor";NA;541;0
"Building";"CreepTumor";NA;541;0
"Building";"CreepTumor";NA;541;0
"Building";"CreepTumor";NA;541;0
"Building";"CreepTumor";NA;549;0
"Building";"CreepTumor";NA;549;0
"Building";"Extractor";NA;549;0
"Building";"CreepTumor";NA;550;0
"Building";"CreepTumor";NA;550;0
"Building";"CreepTumor";NA;550;0
"Building";"CreepTumor";NA;550;0
"Building";"CreepTumor";NA;550;0
"Building";"CreepTumor";NA;550;0
"Building";"CreepTumorQueen";NA;550;0
"Building";"CreepTumorQueen";NA;550;0
"Building";"CreepTumorQueen";NA;550;0
"Building";"CreepTumorQueen";NA;550;0
"Building";"CreepTumorQueen";NA;550;0
"Building";"CreepTumorQueen";NA;550;0
"Building";"CreepTumorQueen";NA;550;0
"Unit";"Ultralisk";"Larva";550;6
"Unit";"Ultralisk";"Larva";550;6
"Unit";"Ultralisk";"Larva";550;6
"Unit";"Ultralisk";"Larva";550;6
"Unit";"Ultralisk";"Larva";550;6
"Unit";"Ultralisk";"Larva";550;6
"Unit";"Ultralisk";"Larva";550;6
"Unit";"Ultralisk";"Larva";550;6
"Unit";"Ultralisk";"Larva";550;6
"Unit";"Ultralisk";"Larva";550;6
"Unit";"Viper";"Larva";550;3
"Unit";"Viper";"Larva";550;3
"Unit";"Viper";"Larva";550;3
"Building";"CreepTumorQueen";NA;550;0
"Building";"CreepTumorQueen";NA;550;0
"Building";"CreepTumor";NA;550;0
"Building";"CreepTumor";NA;550;0
"Building";"CreepTumor";NA;550;0
"Building";"CreepTumor";NA;550;0
"Building";"CreepTumor";NA;550;0
"Building";"CreepTumor";NA;550;0
"Building";"CreepTumor";NA;550;0
"Building";"CreepTumorQueen";NA;613;0
"Building";"CreepTumor";NA;550;0
"Building";"CreepTumor";NA;550;0
"Building";"CreepTumor";NA;550;0
"Building";"CreepTumor";NA;551;0
"Building";"CreepTumor";NA;579;0
"Building";"CreepTumor";NA;622;0
"Building";"CreepTumorQueen";NA;628;0
"Building";"CreepTumor";NA;622;0
"Unit";"Ultralisk";"Larva";550;6
"Unit";"Ultralisk";"Larva";550;6
"Unit";"Ultralisk";"Larva";550;6
"Building";"CreepTumor";NA;631;0
"Building";"CreepTumorQueen";NA;631;0
"Building";"CreepTumor";NA;631;0
"Unit";"Zergling";"Larva";631;1
"Unit";"Zergling";"Larva";631;1
"Unit";"Zergling";"Larva";631;1
"Unit";"Zergling";"Larva";631;1
"Unit";"Zergling";"Larva";631;1
"Unit";"Zergling";"Larva";631;1
"Unit";"Zergling";"Larva";631;1
"Unit";"Zergling";"Larva";631;1
"Unit";"Zergling";"Larva";631;1
"Unit";"Zergling";"Larva";631;1
"Unit";"Zergling";"Larva";631;1
"Unit";"Zergling";"Larva";631;1
"Unit";"Zergling";"Larva";631;1
"Unit";"Zergling";"Larva";631;1
"Unit";"Zergling";"Larva";631;1
"Unit";"Zergling";"Larva";631;1
"Unit";"Zergling";"Larva";631;1
"Unit";"Zergling";"Larva";631;1
"Unit";"Zergling";"Larva";631;1
"Unit";"Zergling";"Larva";631;1
"Unit";"Zergling";"Larva";631;1
"Unit";"Zergling";"Larva";631;1
"Unit";"Zergling";"Larva";631;1
"Unit";"Zergling";"Larva";631;1
"Unit";"Zergling";"Larva";631;1
"Unit";"Zergling";"Larva";631;1
"Unit";"Zergling";"Larva";631;1
"Unit";"Zergling";"Larva";631;1
"Unit";"Zergling";"Larva";631;1
"Unit";"Zergling";"Larva";631;1
"Unit";"Zergling";"Larva";631;1
"Unit";"Zergling";"Larva";631;1
"Unit";"Zergling";"Larva";631;1
"Unit";"Zergling";"Larva";631;1
"Unit";"Hydralisk";"Larva";631;2
"Unit";"Hydralisk";"Larva";631;2
"Unit";"Baneling";"Zergling";683;0
"Unit";"Baneling";"Zergling";683;0
"Unit";"Baneling";"Zergling";683;0
"Unit";"Baneling";"Zergling";683;0
"Unit";"Baneling";"Zergling";683;0
"Unit";"Baneling";"Zergling";683;0
"Unit";"Baneling";"Zergling";683;0
"Unit";"Baneling";"Zergling";683;0
"Unit";"Baneling";"Zergling";683;0
"Unit";"Baneling";"Zergling";683;0
"Unit";"Baneling";"Zergling";683;0
"Unit";"Baneling";"Zergling";683;0
"Unit";"Baneling";"Zergling";683;0
"Unit";"Baneling";"Zergling";683;0
"Unit";"Baneling";"Zergling";683;0
"Unit";"Baneling";"Zergling";683;0
"Unit";"Baneling";"Zergling";683;0
"Unit";"Baneling";"Zergling";683;0
"Building";"CreepTumor";NA;683;0
"Building";"CreepTumor";NA;683;0
"Building";"CreepTumor";NA;683;0
"Building";"CreepTumor";NA;683;0
"Building";"CreepTumor";NA;683;0
"Building";"CreepTumor";NA;683;0
"Building";"CreepTumor";NA;683;0
"Building";"CreepTumor";NA;683;0
"Building";"CreepTumor";NA;683;0
"Building";"CreepTumor";NA;683;0
"Building";"CreepTumor";NA;683;0
"Unit";"Hydralisk";"Larva";649;2
"Building";"CreepTumor";NA;687;0
"Building";"CreepTumor";NA;687;0
"Building";"CreepTumor";NA;689;0
"Building";"CreepTumor";NA;689;0
"Building";"CreepTumorQueen";NA;689;0
"Building";"CreepTumor";NA;689;0
"Building";"CreepTumorQueen";NA;689;0
"Building";"CreepTumor";NA;689;0
"Building";"CreepTumor";NA;689;0
"Building";"CreepTumor";NA;689;0
"Building";"CreepTumor";NA;689;0
"Building";"CreepTumor";NA;689;0
"Building";"CreepTumor";NA;689;0
"Building";"CreepTumor";NA;689;0
"Building";"CreepTumor";NA;689;0
"Building";"CreepTumor";NA;689;0
"Building";"CreepTumorQueen";NA;689;0
"Building";"CreepTumor";NA;689;0
"Building";"CreepTumor";NA;689;0
"Building";"CreepTumor";NA;689;0
"Building";"CreepTumor";NA;689;0
"Building";"CreepTumorQueen";NA;689;0
"Unit";"Zergling";"Larva";689;1
"Unit";"Zergling";"Larva";689;1
"Unit";"Zergling";"Larva";689;1
"Unit";"Zergling";"Larva";689;1
"Unit";"Zergling";"Larva";689;1
"Unit";"Zergling";"Larva";689;1
"Unit";"Zergling";"Larva";689;1
"Unit";"Zergling";"Larva";689;1
"Unit";"Zergling";"Larva";689;1
"Unit";"Zergling";"Larva";689;1
"Building";"CreepTumor";NA;689;0
"Building";"CreepTumor";NA;689;0
"Upgrade";"ZergMissileWeaponsLevel2";"EvolutionChamber";689;0
"Unit";"Hydralisk";"Larva";699;2
"Unit";"Hydralisk";"Larva";699;2
"Building";"SporeCrawler";NA;699;0
"Building";"SporeCrawler";NA;699;0
"Building";"CreepTumor";NA;703;0
"Unit";"Corruptor";"Larva";699;2
"Building";"CreepTumor";NA;703;0
"Unit";"Corruptor";"Larva";705;2
"Unit";"Corruptor";"Larva";705;2
"Unit";"Corruptor";"Larva";705;2
"Unit";"Corruptor";"Larva";705;2
"Unit";"Corruptor";"Larva";705;2
"Unit";"Corruptor";"Larva";705;2
"Unit";"Corruptor";"Larva";705;2
"Unit";"Corruptor";"Larva";705;2
"Unit";"Corruptor";"Larva";705;2
"Unit";"Corruptor";"Larva";705;2
"Unit";"Corruptor";"Larva";705;2
"Unit";"Corruptor";"Larva";705;2
"Unit";"Corruptor";"Larva";705;2
"Unit";"Corruptor";"Larva";705;2
"Unit";"Corruptor";"Larva";705;2
"Unit";"Corruptor";"Larva";705;2
"Unit";"Zergling";"Larva";705;1
"Unit";"Zergling";"Larva";705;1
"Unit";"Zergling";"Larva";705;1
"Unit";"Zergling";"Larva";705;1
"Unit";"Zergling";"Larva";705;1
"Unit";"Zergling";"Larva";705;1
"Unit";"Zergling";"Larva";705;1
"Unit";"Zergling";"Larva";705;1
"Unit";"Zergling";"Larva";705;1
"Unit";"Zergling";"Larva";705;1
"Unit";"Zergling";"Larva";705;1
"Unit";"Zergling";"Larva";705;1
"Unit";"Zergling";"Larva";705;1
"Unit";"Zergling";"Larva";705;1
"Unit";"Zergling";"Larva";705;1
"Unit";"Zergling";"Larva";705;1
"Unit";"Zergling";"Larva";705;1
"Unit";"Zergling";"Larva";705;1
"Unit";"Zergling";"Larva";705;1
"Unit";"Zergling";"Larva";705;1
"Unit";"Zergling";"Larva";705;1
"Unit";"Zergling";"Larva";705;1
"Unit";"Zergling";"Larva";705;1
"Unit";"Zergling";"Larva";705;1
"Unit";"Zergling";"Larva";705;1
"Unit";"Zergling";"Larva";705;1
"Unit";"Zergling";"Larva";705;1
"Unit";"Zergling";"Larva";705;1
"Unit";"Zergling";"Larva";705;1
"Unit";"Zergling";"Larva";705;1
"Unit";"Zergling";"Larva";705;1
"Unit";"Zergling";"Larva";705;1
"Unit";"Zergling";"Larva";705;1
"Unit";"Zergling";"Larva";705;1
"Unit";"Zergling";"Larva";705;1
"Unit";"Zergling";"Larva";705;1
"Unit";"Zergling";"Larva";705;1
"Unit";"Zergling";"Larva";705;1
"Unit";"Zergling";"Larva";705;1
"Unit";"Zergling";"Larva";705;1
"Unit";"Zergling";"Larva";705;1
"Unit";"Zergling";"Larva";705;1
"Unit";"Zergling";"Larva";705;1
"Unit";"Zergling";"Larva";705;1
"Unit";"Zergling";"Larva";705;1
"Unit";"Zergling";"Larva";705;1
"Unit";"Zergling";"Larva";705;1
"Unit";"Zergling";"Larva";705;1
"Unit";"Zergling";"Larva";705;1
"Unit";"Zergling";"Larva";705;1
"Unit";"Zergling";"Larva";705;1
"Unit";"Zergling";"Larva";705;1
"Unit";"Zergling";"Larva";705;1
"Unit";"Zergling";"Larva";705;1
"Unit";"Zergling";"Larva";705;1
"Unit";"Zergling";"Larva";705;1
"Unit";"Zergling";"Larva";705;1
"Unit";"Zergling";"Larva";705;1
"Unit";"Zergling";"Larva";705;1
"Unit";"Zergling";"Larva";705;1
"Unit";"Zergling";"Larva";705;1
"Unit";"Zergling";"Larva";705;1
"Unit";"Zergling";"Larva";705;1
"Unit";"Zergling";"Larva";705;1
"Unit";"Infestor";"Larva";705;2
"Unit";"Infestor";"Larva";705;2
"Unit";"Infestor";"Larva";705;2
"Unit";"Infestor";"Larva";705;2
"Unit";"Zergling";"Larva";801;1
"Unit";"Zergling";"Larva";801;1
"Unit";"Zergling";"Larva";801;1
"Unit";"Zergling";"Larva";801;1
"Unit";"Zergling";"Larva";801;1
"Unit";"Zergling";"Larva";801;1
"Unit";"Zergling";"Larva";801;1
"Unit";"Zergling";"Larva";801;1
"Unit";"Zergling";"Larva";801;1
"Unit";"Zergling";"Larva";801;1
"Unit";"Zergling";"Larva";801;1
"Unit";"Zergling";"Larva";801;1
"Unit";"Ultralisk";"Larva";719;6
"Unit";"Ultralisk";"Larva";721;6
"Unit";"Hydralisk";"Larva";801;2
"Unit";"Hydralisk";"Larva";801;2
"Unit";"Zergling";"Larva";837;1
"Unit";"Zergling";"Larva";837;1
"Unit";"Zergling";"Larva";837;1
"Unit";"Zergling";"Larva";837;1
"Unit";"Zergling";"Larva";837;1
"Unit";"Zergling";"Larva";837;1
"Unit";"Zergling";"Larva";837;1
"Unit";"Zergling";"Larva";837;1
"Unit";"Zergling";"Larva";837;1
"Unit";"Zergling";"Larva";837;1
"Unit";"Zergling";"Larva";837;1
"Unit";"Zergling";"Larva";837;1
"Unit";"Zergling";"Larva";837;1
"Unit";"Zergling";"Larva";837;1
"Unit";"Zergling";"Larva";837;1
"Unit";"Zergling";"Larva";837;1
"Unit";"Zergling";"Larva";837;1
"Unit";"Zergling";"Larva";837;1
"Unit";"Zergling";"Larva";837;1
"Unit";"Zergling";"Larva";837;1
"Unit";"Zergling";"Larva";837;1
"Unit";"Zergling";"Larva";837;1
"Unit";"Zergling";"Larva";837;1
"Unit";"Zergling";"Larva";837;1
"Unit";"Zergling";"Larva";837;1
"Unit";"Zergling";"Larva";837;1
"Unit";"Zergling";"Larva";837;1
"Unit";"Zergling";"Larva";837;1
"Unit";"Zergling";"Larva";837;1
"Unit";"Zergling";"Larva";837;1
"Unit";"Zergling";"Larva";837;1
"Unit";"Zergling";"Larva";837;1
"Unit";"Zergling";"Larva";837;1
"Unit";"Zergling";"Larva";837;1
"Unit";"Zergling";"Larva";837;1
"Unit";"Zergling";"Larva";837;1
