"type";"unit_name";"on_building";"total_supply";"supply"
"Unit";"Overlord";"Larva";13;0
"Building";"Extractor";NA;18;0
"Unit";"Overlord";"Larva";21;0
"Building";"Hatchery";NA;17;0
"Building";"SpawningPool";NA;18;0
"Unit";"Zergling";"Larva";23;1
"Unit";"Zergling";"Larva";23;1
"Unit";"Zergling";"Larva";23;1
"Unit";"Zergling";"Larva";23;1
"Unit";"Queen";"Hatchery";23;2
"Unit";"Queen";"Hatchery";23;2
"Building";"CreepTumorQueen";NA;31;0
"Unit";"Overlord";"Larva";37;0
"Unit";"Queen";"Hatchery";34;2
"Building";"Hatchery";NA;27;0
"Building";"CreepTumorQueen";NA;42;0
"Building";"CreepTumor";NA;42;0
"Building";"CreepTumorQueen";NA;51;0
"Unit";"Queen";"Hatchery";42;2
"Building";"BanelingNest";NA;42;0
"Unit";"Overlord";"Larva";55;0
"Unit";"Overlord";"Larva";55;0
"Unit";"Overlord";"Larva";55;0
"Unit";"Baneling";"Zergling";57;0
"Unit";"Baneling";"Zergling";57;0
"Unit";"Overlord";"Larva";57;0
"Unit";"Zergling";"Larva";57;1
"Unit";"Zergling";"Larva";57;1
"Unit";"Zergling";"Larva";57;1
"Unit";"Zergling";"Larva";57;1
"Unit";"Zergling";"Larva";57;1
"Unit";"Zergling";"Larva";57;1
"Unit";"Zergling";"Larva";57;1
"Unit";"Zergling";"Larva";57;1
"Unit";"Zergling";"Larva";57;1
"Unit";"Zergling";"Larva";57;1
"Unit";"Zergling";"Larva";57;1
"Unit";"Zergling";"Larva";57;1
"Building";"CreepTumorQueen";NA;57;0
"Building";"CreepTumor";NA;57;0
"Unit";"Overlord";"Larva";57;0
"Unit";"Zergling";"Larva";57;1
"Unit";"Zergling";"Larva";57;1
"Unit";"Zergling";"Larva";57;1
"Unit";"Zergling";"Larva";57;1
"Unit";"Zergling";"Larva";57;1
"Unit";"Zergling";"Larva";57;1
"Unit";"Zergling";"Larva";57;1
"Unit";"Zergling";"Larva";57;1
"Building";"CreepTumor";NA;69;0
"Unit";"Baneling";"Zergling";69;0
"Unit";"Baneling";"Zergling";69;0
"Unit";"Zergling";"Larva";69;1
"Unit";"Zergling";"Larva";69;1
"Unit";"Zergling";"Larva";69;1
"Unit";"Zergling";"Larva";69;1
"Unit";"Zergling";"Larva";69;1
"Unit";"Zergling";"Larva";69;1
"Unit";"Zergling";"Larva";69;1
"Unit";"Zergling";"Larva";69;1
"Unit";"Zergling";"Larva";69;1
"Unit";"Zergling";"Larva";69;1
"Unit";"Queen";"Hatchery";57;2
"Building";"CreepTumor";NA;77;0
"Unit";"Overlord";"Larva";77;0
"Building";"Extractor";NA;77;0
"Building";"Extractor";NA;77;0
"Building";"CreepTumor";NA;93;0
"Unit";"Overlord";"Larva";93;0
"Building";"CreepTumor";NA;101;0
"Unit";"Zergling";"Larva";98;1
"Unit";"Zergling";"Larva";98;1
"Unit";"Zergling";"Larva";99;1
"Unit";"Zergling";"Larva";99;1
"Unit";"Zergling";"Larva";100;1
"Unit";"Zergling";"Larva";100;1
"Unit";"Queen";"Hatchery";90;2
"Unit";"Zergling";"Larva";101;1
"Unit";"Zergling";"Larva";101;1
"Unit";"Zergling";"Larva";101;1
"Unit";"Zergling";"Larva";101;1
"Unit";"Zergling";"Larva";101;1
"Unit";"Zergling";"Larva";101;1
"Unit";"Queen";"Hatchery";93;2
"Building";"EvolutionChamber";NA;96;0
"Building";"EvolutionChamber";NA;101;0
"Unit";"Zergling";"Larva";104;1
"Unit";"Zergling";"Larva";104;1
"Unit";"Zergling";"Larva";104;1
"Unit";"Zergling";"Larva";104;1
"Unit";"Zergling";"Larva";104;1
"Unit";"Zergling";"Larva";104;1
"Unit";"Zergling";"Larva";104;1
"Unit";"Zergling";"Larva";104;1
"Unit";"Zergling";"Larva";104;1
"Unit";"Zergling";"Larva";104;1
"Unit";"Zergling";"Larva";104;1
"Unit";"Zergling";"Larva";104;1
"Building";"CreepTumor";NA;137;0
"Building";"CreepTumor";NA;137;0
"Unit";"Overlord";"Larva";132;0
"Building";"Extractor";NA;132;0
"Building";"Extractor";NA;137;0
"Building";"Extractor";NA;137;0
"Unit";"Overlord";"Larva";137;0
"Unit";"Baneling";"Zergling";141;0
"Unit";"Baneling";"Zergling";142;0
"Unit";"Baneling";"Zergling";143;0
"Unit";"Baneling";"Zergling";143;0
"Unit";"Overlord";"Larva";141;0
"Unit";"Zergling";"Larva";145;1
"Unit";"Zergling";"Larva";145;1
"Unit";"Zergling";"Larva";145;1
"Unit";"Zergling";"Larva";145;1
"Unit";"Zergling";"Larva";145;1
"Unit";"Zergling";"Larva";145;1
"Unit";"Zergling";"Larva";145;1
"Unit";"Zergling";"Larva";145;1
"Unit";"Zergling";"Larva";145;1
"Unit";"Zergling";"Larva";145;1
"Unit";"Zergling";"Larva";145;1
"Unit";"Zergling";"Larva";145;1
"Unit";"Zergling";"Larva";145;1
"Unit";"Zergling";"Larva";145;1
"Unit";"Overlord";"Larva";148;0
"Building";"CreepTumor";NA;148;0
"Unit";"Overlord";"Larva";148;0
"Unit";"Overlord";"Larva";148;0
"Unit";"Zergling";"Larva";148;1
"Unit";"Zergling";"Larva";148;1
"Building";"CreepTumor";NA;151;0
"Building";"CreepTumorQueen";NA;163;0
"Building";"CreepTumorQueen";NA;163;0
"Building";"Hatchery";NA;137;0
"Unit";"Zergling";"Larva";165;1
"Unit";"Zergling";"Larva";165;1
"Unit";"Overlord";"Larva";165;0
"Unit";"Overlord";"Larva";165;0
"Unit";"Zergling";"Larva";165;1
"Unit";"Zergling";"Larva";165;1
"Unit";"Zergling";"Larva";165;1
"Unit";"Zergling";"Larva";165;1
"Unit";"Zergling";"Larva";165;1
"Unit";"Zergling";"Larva";165;1
"Unit";"Zergling";"Larva";165;1
"Unit";"Zergling";"Larva";165;1
"Unit";"Zergling";"Larva";165;1
"Unit";"Zergling";"Larva";165;1
"Unit";"Zergling";"Larva";165;1
"Unit";"Zergling";"Larva";165;1
"Unit";"Zergling";"Larva";165;1
"Unit";"Zergling";"Larva";165;1
"Unit";"Zergling";"Larva";165;1
"Unit";"Zergling";"Larva";165;1
"Unit";"Zergling";"Larva";165;1
"Unit";"Zergling";"Larva";165;1
"Unit";"Zergling";"Larva";165;1
"Unit";"Zergling";"Larva";165;1
"Unit";"Zergling";"Larva";165;1
"Unit";"Zergling";"Larva";165;1
"Upgrade";"ZergMeleeWeaponsLevel1";"EvolutionChamber";141;0
"Building";"CreepTumor";NA;165;0
"Building";"CreepTumor";NA;165;0
"Building";"CreepTumor";NA;169;0
"Building";"CreepTumor";NA;191;0
"Unit";"Queen";"Hatchery";165;2
"Upgrade";"ZergGroundArmorsLevel1";"EvolutionChamber";148;0
"Building";"HydraliskDen";NA;165;0
"Unit";"Baneling";"Zergling";191;0
"Unit";"Baneling";"Zergling";191;0
"Building";"SporeCrawler";NA;191;0
"Building";"SporeCrawler";NA;191;0
"Unit";"Overlord";"Larva";191;0
"Unit";"Overlord";"Larva";191;0
"Unit";"Baneling";"Zergling";195;0
"Unit";"Baneling";"Zergling";195;0
"Unit";"Baneling";"Zergling";195;0
"Unit";"Baneling";"Zergling";195;0
"Unit";"Overlord";"Larva";201;0
"Unit";"Hydralisk";"Larva";195;2
"Unit";"Hydralisk";"Larva";195;2
"Unit";"Hydralisk";"Larva";195;2
"Unit";"Hydralisk";"Larva";195;2
"Unit";"Hydralisk";"Larva";195;2
"Unit";"Hydralisk";"Larva";195;2
"Building";"InfestationPit";NA;191;0
"Building";"CreepTumor";NA;205;0
"Building";"CreepTumor";NA;205;0
"Building";"CreepTumor";NA;205;0
"Unit";"Hydralisk";"Larva";205;2
"Unit";"Hydralisk";"Larva";205;2
"Unit";"Hydralisk";"Larva";205;2
"Building";"CreepTumor";NA;205;0
"Unit";"Overlord";"Larva";217;0
"Unit";"Hydralisk";"Larva";205;2
"Unit";"Hydralisk";"Larva";205;2
"Unit";"Hydralisk";"Larva";205;2
"Unit";"Hydralisk";"Larva";205;2
"Unit";"Hydralisk";"Larva";205;2
"Building";"Extractor";NA;217;0
"Building";"Extractor";NA;217;0
"Building";"SporeCrawler";NA;223;0
"Building";"SporeCrawler";NA;223;0
"Unit";"Hydralisk";"Larva";223;2
"Unit";"Hydralisk";"Larva";223;2
"Building";"CreepTumor";NA;240;0
"Upgrade";"EvolveGroovedSpines";"HydraliskDen";205;0
"Unit";"Overlord";"Larva";240;0
"Unit";"Overlord";"Larva";240;0
"Unit";"Overlord";"Larva";240;0
"Building";"CreepTumor";NA;247;0
"Building";"CreepTumor";NA;247;0
"Building";"CreepTumor";NA;247;0
"Unit";"Overlord";"Larva";247;0
"Building";"CreepTumorQueen";NA;247;0
"Upgrade";"ZergMeleeWeaponsLevel2";"EvolutionChamber";205;0
"Building";"CreepTumorQueen";NA;247;0
"Building";"CreepTumorQueen";NA;247;0
"Building";"CreepTumorQueen";NA;247;0
"Building";"CreepTumor";NA;247;0
"Building";"CreepTumor";NA;247;0
"Building";"CreepTumorQueen";NA;247;0
"Building";"CreepTumor";NA;247;0
"Building";"CreepTumor";NA;247;0
"Building";"CreepTumorQueen";NA;247;0
"Upgrade";"ZergGroundArmorsLevel2";"EvolutionChamber";223;0
"Building";"Hatchery";NA;244;0
"Upgrade";"EvolveMuscularAugments";"HydraliskDen";247;0
"Unit";"Viper";"Larva";247;3
"Unit";"Viper";"Larva";247;3
"Unit";"Viper";"Larva";247;3
"Unit";"Viper";"Larva";247;3
"Unit";"Viper";"Larva";247;3
"Building";"CreepTumor";NA;253;0
"Building";"CreepTumor";NA;262;0
"Building";"CreepTumorQueen";NA;262;0
"Building";"CreepTumorQueen";NA;262;0
"Building";"CreepTumor";NA;262;0
"Building";"CreepTumor";NA;262;0
"Building";"EvolutionChamber";NA;262;0
"Building";"CreepTumor";NA;262;0
"Building";"EvolutionChamber";NA;262;0
"Building";"CreepTumorQueen";NA;262;0
"Building";"CreepTumorQueen";NA;262;0
"Building";"EvolutionChamber";NA;262;0
"Building";"CreepTumorQueen";NA;262;0
"Building";"CreepTumorQueen";NA;262;0
"Building";"SporeCrawler";NA;262;0
"Building";"CreepTumorQueen";NA;262;0
"Building";"CreepTumorQueen";NA;262;0
"Building";"CreepTumorQueen";NA;262;0
"Building";"SporeCrawler";NA;262;0
"Building";"CreepTumorQueen";NA;262;0
"Building";"CreepTumorQueen";NA;262;0
"Building";"CreepTumorQueen";NA;262;0
"Building";"CreepTumorQueen";NA;262;0
"Building";"CreepTumorQueen";NA;262;0
"Building";"UltraliskCavern";NA;262;0
"Unit";"Baneling";"Zergling";262;0
"Unit";"Baneling";"Zergling";262;0
"Unit";"Baneling";"Zergling";262;0
"Unit";"Baneling";"Zergling";262;0
"Unit";"Baneling";"Zergling";262;0
"Unit";"Baneling";"Zergling";262;0
"Unit";"Baneling";"Zergling";262;0
"Unit";"Baneling";"Zergling";262;0
"Unit";"Baneling";"Zergling";262;0
"Unit";"Baneling";"Zergling";262;0
"Unit";"Baneling";"Zergling";262;0
"Unit";"Baneling";"Zergling";262;0
"Unit";"Baneling";"Zergling";262;0
"Unit";"Baneling";"Zergling";262;0
"Unit";"Baneling";"Zergling";262;0
"Unit";"Hydralisk";"Larva";262;2
"Unit";"Hydralisk";"Larva";262;2
"Unit";"Hydralisk";"Larva";262;2
"Unit";"Hydralisk";"Larva";262;2
"Unit";"Hydralisk";"Larva";262;2
"Unit";"Hydralisk";"Larva";262;2
"Unit";"Hydralisk";"Larva";262;2
"Unit";"Hydralisk";"Larva";262;2
"Unit";"Hydralisk";"Larva";262;2
"Unit";"Hydralisk";"Larva";262;2
"Unit";"Hydralisk";"Larva";262;2
"Unit";"Hydralisk";"Larva";262;2
"Unit";"Hydralisk";"Larva";262;2
"Unit";"Hydralisk";"Larva";262;2
"Unit";"Hydralisk";"Larva";262;2
"Unit";"Hydralisk";"Larva";262;2
"Unit";"Hydralisk";"Larva";262;2
"Unit";"Hydralisk";"Larva";262;2
"Unit";"Hydralisk";"Larva";262;2
"Unit";"Hydralisk";"Larva";262;2
"Unit";"Hydralisk";"Larva";262;2
"Unit";"Hydralisk";"Larva";262;2
"Unit";"Hydralisk";"Larva";262;2
"Unit";"Hydralisk";"Larva";262;2
"Unit";"Hydralisk";"Larva";262;2
"Unit";"Hydralisk";"Larva";262;2
"Building";"Extractor";NA;262;0
"Building";"Extractor";NA;262;0
"Unit";"Zergling";"Larva";314;1
"Unit";"Zergling";"Larva";314;1
"Unit";"Zergling";"Larva";314;1
"Unit";"Zergling";"Larva";314;1
"Unit";"Zergling";"Larva";314;1
"Unit";"Zergling";"Larva";314;1
"Unit";"Zergling";"Larva";314;1
"Unit";"Zergling";"Larva";314;1
"Unit";"Zergling";"Larva";314;1
"Unit";"Zergling";"Larva";314;1
"Unit";"Zergling";"Larva";314;1
"Unit";"Zergling";"Larva";314;1
"Unit";"Zergling";"Larva";314;1
"Unit";"Zergling";"Larva";314;1
"Unit";"Zergling";"Larva";314;1
"Unit";"Zergling";"Larva";314;1
"Unit";"Zergling";"Larva";314;1
"Unit";"Zergling";"Larva";314;1
"Unit";"Zergling";"Larva";314;1
"Unit";"Zergling";"Larva";314;1
"Unit";"Zergling";"Larva";314;1
"Unit";"Zergling";"Larva";314;1
"Unit";"Zergling";"Larva";314;1
"Unit";"Zergling";"Larva";314;1
"Upgrade";"ZergMeleeWeaponsLevel3";"EvolutionChamber";262;0
"Building";"CreepTumorQueen";NA;338;0
"Unit";"Zergling";"Larva";338;1
"Unit";"Zergling";"Larva";338;1
"Building";"CreepTumorQueen";NA;338;0
"Unit";"Zergling";"Larva";338;1
"Unit";"Zergling";"Larva";338;1
"Unit";"Zergling";"Larva";338;1
"Unit";"Zergling";"Larva";338;1
"Unit";"Zergling";"Larva";338;1
"Unit";"Zergling";"Larva";338;1
"Unit";"Zergling";"Larva";338;1
"Unit";"Zergling";"Larva";338;1
"Unit";"Zergling";"Larva";338;1
"Unit";"Zergling";"Larva";338;1
"Unit";"Zergling";"Larva";338;1
"Unit";"Zergling";"Larva";338;1
"Building";"CreepTumorQueen";NA;338;0
"Building";"CreepTumorQueen";NA;338;0
"Building";"CreepTumorQueen";NA;338;0
"Unit";"Zergling";"Larva";338;1
"Unit";"Zergling";"Larva";338;1
"Unit";"Zergling";"Larva";338;1
"Unit";"Zergling";"Larva";338;1
"Unit";"Zergling";"Larva";338;1
"Unit";"Zergling";"Larva";338;1
"Unit";"Zergling";"Larva";338;1
"Unit";"Zergling";"Larva";338;1
"Unit";"Zergling";"Larva";338;1
"Unit";"Zergling";"Larva";338;1
"Unit";"Zergling";"Larva";338;1
"Unit";"Zergling";"Larva";338;1
"Unit";"Zergling";"Larva";338;1
"Unit";"Zergling";"Larva";338;1
"Unit";"Zergling";"Larva";338;1
"Unit";"Zergling";"Larva";338;1
"Unit";"Zergling";"Larva";338;1
"Unit";"Zergling";"Larva";338;1
"Unit";"Zergling";"Larva";338;1
"Unit";"Zergling";"Larva";338;1
"Unit";"Zergling";"Larva";338;1
"Unit";"Zergling";"Larva";338;1
"Unit";"Zergling";"Larva";338;1
"Unit";"Zergling";"Larva";338;1
"Unit";"Zergling";"Larva";338;1
"Unit";"Zergling";"Larva";338;1
"Upgrade";"ChitinousPlating";"UltraliskCavern";314;0
