"type";"unit_name";"on_building";"total_supply";"supply"
"Unit";"Overlord";"Larva";13;0
"Building";"Extractor";NA;18;0
"Unit";"Overlord";"Larva";21;0
"Building";"SpawningPool";NA;19;0
"Building";"Hatchery";NA;17;0
"Unit";"Zergling";"Larva";22;1
"Unit";"Zergling";"Larva";22;1
"Unit";"Zergling";"Larva";22;1
"Unit";"Zergling";"Larva";22;1
"Unit";"Queen";"Hatchery";22;2
"Unit";"Queen";"Hatchery";22;2
"Building";"CreepTumorQueen";NA;34;0
"Unit";"Overlord";"Larva";36;0
"Unit";"Overlord";"Larva";37;0
"Unit";"Queen";"Hatchery";35;2
"Building";"CreepTumor";NA;38;0
"Building";"CreepTumorQueen";NA;41;0
"Building";"CreepTumor";NA;46;0
"Unit";"Zergling";"Larva";46;1
"Unit";"Zergling";"Larva";46;1
"Unit";"Zergling";"Larva";48;1
"Unit";"Zergling";"Larva";48;1
"Building";"CreepTumor";NA;48;0
"Unit";"Queen";"Hatchery";41;2
"Unit";"Overlord";"Larva";48;0
"Unit";"Overlord";"Larva";54;0
"Building";"CreepTumor";NA;55;0
"Building";"CreepTumor";NA;55;0
"Unit";"Zergling";"Larva";55;1
"Unit";"Zergling";"Larva";55;1
"Unit";"Zergling";"Larva";55;1
"Unit";"Zergling";"Larva";55;1
"Unit";"Queen";"Hatchery";55;2
"Building";"EvolutionChamber";NA;55;0
"Building";"CreepTumorQueen";NA;59;0
"Building";"EvolutionChamber";NA;55;0
"Building";"Hatchery";NA;46;0
"Building";"CreepTumorQueen";NA;69;0
"Building";"CreepTumorQueen";NA;73;0
"Building";"CreepTumor";NA;73;0
"Building";"CreepTumor";NA;73;0
"Building";"CreepTumorQueen";NA;73;0
"Building";"CreepTumor";NA;73;0
"Unit";"Queen";"Hatchery";69;2
"Building";"BanelingNest";NA;69;0
"Unit";"Overlord";"Larva";79;0
"Unit";"Overlord";"Larva";79;0
"Unit";"Overlord";"Larva";79;0
"Unit";"Overlord";"Larva";79;0
"Unit";"Queen";"Hatchery";73;2
"Building";"CreepTumorQueen";NA;81;0
"Building";"CreepTumor";NA;81;0
"Building";"CreepTumor";NA;83;0
"Unit";"Overlord";"Larva";81;0
"Unit";"Overlord";"Larva";81;0
"Unit";"Overlord";"Larva";81;0
"Building";"Extractor";NA;81;0
"Unit";"Zergling";"Larva";83;1
"Unit";"Zergling";"Larva";83;1
"Building";"CreepTumor";NA;86;0
"Unit";"Zergling";"Larva";83;1
"Unit";"Zergling";"Larva";83;1
"Unit";"Zergling";"Larva";83;1
"Unit";"Zergling";"Larva";83;1
"Unit";"Zergling";"Larva";83;1
"Unit";"Zergling";"Larva";83;1
"Building";"CreepTumor";NA;86;0
"Building";"CreepTumor";NA;88;0
"Building";"Extractor";NA;100;0
"Building";"Extractor";NA;104;0
"Building";"Extractor";NA;104;0
"Building";"CreepTumor";NA;113;0
"Building";"SporeCrawler";NA;104;0
"Building";"CreepTumor";NA;113;0
"Building";"CreepTumor";NA;113;0
"Unit";"Zergling";"Larva";113;1
"Unit";"Zergling";"Larva";113;1
"Unit";"Zergling";"Larva";113;1
"Unit";"Zergling";"Larva";113;1
"Unit";"Zergling";"Larva";113;1
"Unit";"Zergling";"Larva";113;1
"Unit";"Zergling";"Larva";113;1
"Unit";"Zergling";"Larva";113;1
"Unit";"Zergling";"Larva";113;1
"Unit";"Zergling";"Larva";113;1
"Unit";"Zergling";"Larva";113;1
"Unit";"Zergling";"Larva";113;1
"Unit";"Zergling";"Larva";113;1
"Unit";"Zergling";"Larva";113;1
"Unit";"Zergling";"Larva";113;1
"Unit";"Zergling";"Larva";113;1
"Unit";"Zergling";"Larva";113;1
"Unit";"Zergling";"Larva";113;1
"Unit";"Zergling";"Larva";113;1
"Unit";"Zergling";"Larva";113;1
"Building";"CreepTumor";NA;113;0
"Building";"CreepTumor";NA;113;0
"Building";"HydraliskDen";NA;113;0
"Upgrade";"ZergMeleeWeaponsLevel1";"EvolutionChamber";88;0
"Building";"Hatchery";NA;100;0
"Upgrade";"ZergGroundArmorsLevel1";"EvolutionChamber";100;0
"Building";"SpineCrawler";NA;129;0
"Building";"CreepTumor";NA;139;0
"Building";"CreepTumor";NA;139;0
"Unit";"Hydralisk";"Larva";139;2
"Unit";"Hydralisk";"Larva";139;2
"Unit";"Hydralisk";"Larva";139;2
"Unit";"Hydralisk";"Larva";139;2
"Unit";"Hydralisk";"Larva";139;2
"Unit";"Hydralisk";"Larva";139;2
"Building";"CreepTumor";NA;139;0
"Unit";"Baneling";"Zergling";144;0
"Unit";"Baneling";"Zergling";144;0
"Unit";"Baneling";"Zergling";144;0
"Unit";"Baneling";"Zergling";144;0
"Unit";"Baneling";"Zergling";144;0
"Unit";"Baneling";"Zergling";144;0
"Unit";"Baneling";"Zergling";144;0
"Unit";"Baneling";"Zergling";144;0
"Unit";"Baneling";"Zergling";144;0
"Unit";"Baneling";"Zergling";144;0
"Building";"CreepTumor";NA;144;0
"Building";"Extractor";NA;144;0
"Building";"Extractor";NA;144;0
"Unit";"Overlord";"Larva";163;0
"Unit";"Overlord";"Larva";163;0
"Unit";"Hydralisk";"Larva";144;2
"Unit";"Overlord";"Larva";163;0
"Unit";"Overlord";"Larva";163;0
"Unit";"Overlord";"Larva";163;0
"Unit";"Overlord";"Larva";163;0
"Building";"Extractor";NA;163;0
"Unit";"Overlord";"Larva";163;0
"Unit";"Overlord";"Larva";163;0
"Unit";"Overlord";"Larva";163;0
"Building";"CreepTumor";NA;165;0
"Building";"CreepTumor";NA;165;0
"Building";"CreepTumor";NA;167;0
"Building";"CreepTumor";NA;167;0
"Upgrade";"EvolveMuscularAugments";"HydraliskDen";144;0
"Building";"SporeCrawler";NA;167;0
"Building";"SporeCrawler";NA;167;0
"Building";"SporeCrawler";NA;167;0
"Building";"CreepTumor";NA;177;0
"Building";"CreepTumor";NA;177;0
"Building";"CreepTumor";NA;177;0
"Building";"SporeCrawler";NA;174;0
"Unit";"Overlord";"Larva";177;0
"Unit";"Overlord";"Larva";177;0
"Unit";"Zergling";"Larva";177;1
"Unit";"Zergling";"Larva";177;1
"Unit";"Zergling";"Larva";177;1
"Unit";"Zergling";"Larva";177;1
"Unit";"Zergling";"Larva";177;1
"Unit";"Zergling";"Larva";177;1
"Unit";"Zergling";"Larva";177;1
"Unit";"Zergling";"Larva";177;1
"Unit";"Zergling";"Larva";177;1
"Unit";"Zergling";"Larva";177;1
"Unit";"Zergling";"Larva";177;1
"Unit";"Zergling";"Larva";177;1
"Unit";"Zergling";"Larva";177;1
"Unit";"Zergling";"Larva";177;1
"Unit";"Hydralisk";"Larva";177;2
"Unit";"Hydralisk";"Larva";177;2
"Unit";"Hydralisk";"Larva";177;2
"Unit";"Hydralisk";"Larva";177;2
"Unit";"Hydralisk";"Larva";177;2
"Building";"SpineCrawler";NA;177;0
"Building";"SpineCrawler";NA;177;0
"Unit";"Zergling";"Larva";191;1
"Unit";"Zergling";"Larva";191;1
"Unit";"Zergling";"Larva";191;1
"Unit";"Zergling";"Larva";191;1
"Unit";"Zergling";"Larva";191;1
"Unit";"Zergling";"Larva";191;1
"Unit";"Zergling";"Larva";191;1
"Unit";"Zergling";"Larva";191;1
"Unit";"Zergling";"Larva";191;1
"Unit";"Zergling";"Larva";191;1
"Unit";"Zergling";"Larva";191;1
"Unit";"Zergling";"Larva";191;1
"Unit";"Zergling";"Larva";191;1
"Unit";"Zergling";"Larva";191;1
"Unit";"Zergling";"Larva";191;1
"Unit";"Zergling";"Larva";191;1
"Building";"CreepTumor";NA;201;0
"Building";"InfestationPit";NA;177;0
"Unit";"Baneling";"Zergling";217;0
"Unit";"Baneling";"Zergling";217;0
"Unit";"Baneling";"Zergling";217;0
"Unit";"Baneling";"Zergling";217;0
"Unit";"Baneling";"Zergling";217;0
"Unit";"Baneling";"Zergling";217;0
"Unit";"Baneling";"Zergling";217;0
"Unit";"Baneling";"Zergling";217;0
"Unit";"Baneling";"Zergling";217;0
"Unit";"Baneling";"Zergling";217;0
"Unit";"Baneling";"Zergling";217;0
"Unit";"Baneling";"Zergling";217;0
"Unit";"Baneling";"Zergling";217;0
"Unit";"Baneling";"Zergling";217;0
"Unit";"Baneling";"Zergling";217;0
"Unit";"Baneling";"Zergling";217;0
"Unit";"Baneling";"Zergling";217;0
"Unit";"Baneling";"Zergling";217;0
"Unit";"Baneling";"Zergling";217;0
"Unit";"Baneling";"Zergling";217;0
"Unit";"Baneling";"Zergling";217;0
"Unit";"Baneling";"Zergling";217;0
"Unit";"Baneling";"Zergling";217;0
"Upgrade";"EvolveGroovedSpines";"HydraliskDen";177;0
"Building";"CreepTumor";NA;217;0
"Unit";"Hydralisk";"Larva";217;2
"Unit";"Hydralisk";"Larva";217;2
"Unit";"Hydralisk";"Larva";217;2
"Unit";"Hydralisk";"Larva";217;2
"Unit";"Hydralisk";"Larva";217;2
"Unit";"Hydralisk";"Larva";217;2
"Unit";"Hydralisk";"Larva";217;2
"Unit";"Hydralisk";"Larva";217;2
"Unit";"Hydralisk";"Larva";217;2
"Unit";"Hydralisk";"Larva";217;2
"Unit";"Hydralisk";"Larva";217;2
"Building";"CreepTumor";NA;217;0
"Building";"CreepTumor";NA;217;0
"Building";"EvolutionChamber";NA;217;0
"Building";"EvolutionChamber";NA;217;0
"Building";"Hatchery";NA;191;0
"Building";"EvolutionChamber";NA;217;0
"Upgrade";"ZergMeleeWeaponsLevel2";"EvolutionChamber";177;0
"Upgrade";"ZergGroundArmorsLevel2";"EvolutionChamber";177;0
"Unit";"Zergling";"Larva";244;1
"Unit";"Zergling";"Larva";244;1
"Unit";"Zergling";"Larva";244;1
"Unit";"Zergling";"Larva";244;1
"Unit";"Zergling";"Larva";244;1
"Unit";"Zergling";"Larva";244;1
"Unit";"Zergling";"Larva";244;1
"Unit";"Zergling";"Larva";244;1
"Unit";"Zergling";"Larva";244;1
"Unit";"Zergling";"Larva";244;1
"Unit";"Zergling";"Larva";244;1
"Unit";"Zergling";"Larva";244;1
"Unit";"Zergling";"Larva";244;1
"Unit";"Zergling";"Larva";244;1
"Unit";"Zergling";"Larva";244;1
"Unit";"Zergling";"Larva";244;1
"Unit";"Zergling";"Larva";244;1
"Unit";"Zergling";"Larva";244;1
"Unit";"Zergling";"Larva";244;1
"Unit";"Zergling";"Larva";244;1
"Unit";"Zergling";"Larva";244;1
"Unit";"Zergling";"Larva";244;1
"Unit";"Zergling";"Larva";244;1
"Unit";"Zergling";"Larva";244;1
"Building";"Spire";NA;217;0
"Unit";"Hydralisk";"Larva";244;2
"Unit";"Hydralisk";"Larva";244;2
"Unit";"Hydralisk";"Larva";244;2
"Unit";"Hydralisk";"Larva";244;2
"Unit";"Hydralisk";"Larva";244;2
"Unit";"Hydralisk";"Larva";244;2
"Unit";"Hydralisk";"Larva";244;2
"Unit";"Hydralisk";"Larva";244;2
"Unit";"Hydralisk";"Larva";244;2
"Unit";"Hydralisk";"Larva";244;2
"Unit";"Hydralisk";"Larva";244;2
"Unit";"Hydralisk";"Larva";244;2
"Unit";"Hydralisk";"Larva";244;2
"Unit";"Zergling";"Larva";244;1
"Unit";"Zergling";"Larva";244;1
"Unit";"Zergling";"Larva";244;1
"Unit";"Zergling";"Larva";244;1
"Unit";"Zergling";"Larva";244;1
"Unit";"Zergling";"Larva";244;1
"Unit";"Zergling";"Larva";244;1
"Unit";"Zergling";"Larva";244;1
"Unit";"Zergling";"Larva";244;1
"Unit";"Zergling";"Larva";244;1
"Unit";"Zergling";"Larva";244;1
"Unit";"Zergling";"Larva";244;1
"Unit";"Zergling";"Larva";244;1
"Unit";"Zergling";"Larva";244;1
"Unit";"Zergling";"Larva";244;1
"Unit";"Zergling";"Larva";244;1
"Unit";"Hydralisk";"Larva";244;2
"Unit";"Hydralisk";"Larva";244;2
"Unit";"Hydralisk";"Larva";244;2
"Unit";"Hydralisk";"Larva";244;2
"Unit";"Hydralisk";"Larva";244;2
"Unit";"Hydralisk";"Larva";244;2
"Unit";"Hydralisk";"Larva";244;2
"Building";"CreepTumor";NA;294;0
"Unit";"Viper";"Larva";268;3
"Unit";"Viper";"Larva";268;3
"Building";"CreepTumorQueen";NA;324;0
"Building";"CreepTumorQueen";NA;324;0
"Building";"CreepTumorQueen";NA;324;0
"Building";"CreepTumorQueen";NA;324;0
"Building";"CreepTumorQueen";NA;330;0
"Unit";"Viper";"Larva";302;3
"Building";"CreepTumorQueen";NA;330;0
"Unit";"Viper";"Larva";330;3
"Unit";"Viper";"Larva";330;3
"Unit";"Viper";"Larva";330;3
"Building";"Extractor";NA;333;0
"Building";"Extractor";NA;333;0
"Unit";"Baneling";"Zergling";333;0
"Unit";"Baneling";"Zergling";333;0
"Unit";"Baneling";"Zergling";333;0
"Unit";"Baneling";"Zergling";333;0
"Unit";"Baneling";"Zergling";333;0
"Unit";"Baneling";"Zergling";333;0
"Unit";"Baneling";"Zergling";333;0
"Unit";"Baneling";"Zergling";333;0
"Unit";"Baneling";"Zergling";333;0
"Unit";"Baneling";"Zergling";333;0
"Unit";"Baneling";"Zergling";333;0
"Unit";"Baneling";"Zergling";333;0
"Unit";"Baneling";"Zergling";333;0
"Unit";"Baneling";"Zergling";333;0
"Unit";"Baneling";"Zergling";333;0
"Building";"CreepTumor";NA;336;0
"Building";"CreepTumor";NA;336;0
"Building";"CreepTumor";NA;336;0
"Building";"CreepTumor";NA;336;0
"Building";"CreepTumor";NA;336;0
"Upgrade";"ZergMissileWeaponsLevel1";"EvolutionChamber";268;0
"Building";"CreepTumorQueen";NA;345;0
"Building";"CreepTumorQueen";NA;345;0
"Building";"CreepTumorQueen";NA;345;0
"Building";"CreepTumorQueen";NA;345;0
"Building";"CreepTumor";NA;345;0
"Building";"CreepTumor";NA;345;0
"Building";"SporeCrawler";NA;345;0
"Building";"SpineCrawler";NA;345;0
"Building";"SpineCrawler";NA;345;0
"Building";"SpineCrawler";NA;345;0
"Building";"SpineCrawler";NA;345;0
"Building";"SpineCrawler";NA;345;0
"Building";"SpineCrawler";NA;345;0
"Building";"Hatchery";NA;345;0
"Unit";"Zergling";"Larva";350;1
"Unit";"Zergling";"Larva";350;1
"Unit";"Zergling";"Larva";350;1
"Unit";"Zergling";"Larva";350;1
"Unit";"Zergling";"Larva";350;1
"Unit";"Zergling";"Larva";350;1
"Unit";"Zergling";"Larva";350;1
"Unit";"Zergling";"Larva";350;1
"Unit";"Zergling";"Larva";350;1
"Unit";"Zergling";"Larva";350;1
"Unit";"Zergling";"Larva";350;1
"Unit";"Zergling";"Larva";350;1
"Unit";"Zergling";"Larva";350;1
"Unit";"Zergling";"Larva";350;1
"Unit";"Hydralisk";"Larva";350;2
"Unit";"Hydralisk";"Larva";350;2
"Unit";"Hydralisk";"Larva";350;2
"Unit";"Hydralisk";"Larva";350;2
"Unit";"Hydralisk";"Larva";350;2
"Unit";"Hydralisk";"Larva";350;2
"Unit";"Hydralisk";"Larva";350;2
"Unit";"Hydralisk";"Larva";350;2
"Unit";"Hydralisk";"Larva";350;2
"Unit";"Hydralisk";"Larva";350;2
"Unit";"Hydralisk";"Larva";350;2
"Unit";"Hydralisk";"Larva";350;2
"Unit";"Overlord";"Larva";350;0
"Unit";"Overlord";"Larva";350;0
"Unit";"Overlord";"Larva";350;0
"Building";"CreepTumor";NA;350;0
"Building";"CreepTumor";NA;350;0
"Building";"CreepTumor";NA;350;0
"Building";"CreepTumor";NA;350;0
"Unit";"Overlord";"Larva";350;0
"Unit";"Overlord";"Larva";350;0
"Building";"CreepTumor";NA;364;0
"Building";"CreepTumor";NA;364;0
"Building";"CreepTumor";NA;364;0
"Unit";"Viper";"Larva";350;3
"Unit";"Viper";"Larva";350;3
"Unit";"Viper";"Larva";350;3
"Building";"CreepTumor";NA;364;0
"Building";"CreepTumor";NA;372;0
"Building";"CreepTumor";NA;388;0
"Upgrade";"ZergMeleeWeaponsLevel3";"EvolutionChamber";345;0
"Building";"Spire";NA;350;0
"Building";"CreepTumor";NA;397;0
"Building";"Extractor";NA;397;0
"Building";"CreepTumor";NA;397;0
"Building";"CreepTumor";NA;397;0
"Building";"Extractor";NA;397;0
"Building";"CreepTumor";NA;397;0
"Building";"CreepTumor";NA;397;0
"Building";"CreepTumor";NA;397;0
"Unit";"Corruptor";"Larva";397;2
"Unit";"Corruptor";"Larva";397;2
"Unit";"Corruptor";"Larva";397;2
"Unit";"Corruptor";"Larva";397;2
"Unit";"Corruptor";"Larva";397;2
"Unit";"Corruptor";"Larva";397;2
"Unit";"Corruptor";"Larva";397;2
"Unit";"Corruptor";"Larva";397;2
"Unit";"Corruptor";"Larva";397;2
"Building";"CreepTumor";NA;415;0
"Building";"CreepTumor";NA;415;0
"Building";"Hatchery";NA;397;0
"Unit";"Zergling";"Larva";415;1
"Unit";"Zergling";"Larva";415;1
"Unit";"Zergling";"Larva";415;1
"Unit";"Zergling";"Larva";415;1
"Unit";"Zergling";"Larva";415;1
"Unit";"Zergling";"Larva";415;1
"Unit";"Zergling";"Larva";415;1
"Unit";"Zergling";"Larva";415;1
"Unit";"Zergling";"Larva";415;1
"Unit";"Zergling";"Larva";415;1
"Unit";"Zergling";"Larva";415;1
"Unit";"Zergling";"Larva";415;1
"Unit";"Zergling";"Larva";415;1
"Unit";"Zergling";"Larva";415;1
"Unit";"Zergling";"Larva";415;1
"Unit";"Zergling";"Larva";415;1
"Unit";"Zergling";"Larva";415;1
"Unit";"Zergling";"Larva";415;1
"Unit";"Zergling";"Larva";415;1
"Unit";"Zergling";"Larva";415;1
"Unit";"Zergling";"Larva";415;1
"Unit";"Zergling";"Larva";415;1
"Unit";"Zergling";"Larva";415;1
"Unit";"Zergling";"Larva";415;1
"Unit";"Zergling";"Larva";415;1
"Unit";"Zergling";"Larva";415;1
"Unit";"Zergling";"Larva";415;1
"Unit";"Zergling";"Larva";415;1
"Unit";"Zergling";"Larva";415;1
"Unit";"Zergling";"Larva";415;1
"Unit";"Hydralisk";"Larva";415;2
"Unit";"Hydralisk";"Larva";415;2
"Unit";"Hydralisk";"Larva";415;2
"Unit";"Hydralisk";"Larva";415;2
"Unit";"Zergling";"Larva";415;1
"Unit";"Zergling";"Larva";415;1
"Unit";"Hydralisk";"Larva";415;2
"Unit";"Zergling";"Larva";415;1
"Unit";"Zergling";"Larva";415;1
"Unit";"Zergling";"Larva";415;1
"Unit";"Zergling";"Larva";415;1
"Unit";"Zergling";"Larva";415;1
"Unit";"Zergling";"Larva";415;1
"Unit";"Zergling";"Larva";415;1
"Unit";"Zergling";"Larva";415;1
"Unit";"Zergling";"Larva";415;1
"Unit";"Zergling";"Larva";415;1
"Unit";"Zergling";"Larva";415;1
"Unit";"Zergling";"Larva";415;1
"Unit";"Zergling";"Larva";415;1
"Unit";"Zergling";"Larva";415;1
"Unit";"Zergling";"Larva";415;1
"Unit";"Zergling";"Larva";415;1
"Unit";"Zergling";"Larva";415;1
"Unit";"Zergling";"Larva";415;1
"Unit";"Hydralisk";"Larva";415;2
"Unit";"Zergling";"Larva";415;1
"Unit";"Zergling";"Larva";415;1
"Unit";"Hydralisk";"Larva";415;2
"Unit";"Zergling";"Larva";415;1
"Unit";"Zergling";"Larva";415;1
"Unit";"Hydralisk";"Larva";415;2
"Unit";"Zergling";"Larva";415;1
"Unit";"Zergling";"Larva";415;1
"Unit";"Zergling";"Larva";415;1
"Unit";"Zergling";"Larva";415;1
"Unit";"Zergling";"Larva";415;1
"Unit";"Zergling";"Larva";415;1
"Unit";"Baneling";"Zergling";445;0
"Unit";"Baneling";"Zergling";445;0
"Unit";"Baneling";"Zergling";445;0
"Unit";"Baneling";"Zergling";445;0
"Unit";"Baneling";"Zergling";445;0
"Unit";"Baneling";"Zergling";445;0
"Unit";"Baneling";"Zergling";445;0
"Unit";"Baneling";"Zergling";445;0
"Unit";"Baneling";"Zergling";445;0
"Unit";"Baneling";"Zergling";445;0
"Unit";"Baneling";"Zergling";445;0
"Unit";"Baneling";"Zergling";445;0
"Unit";"Baneling";"Zergling";445;0
"Unit";"Baneling";"Zergling";445;0
"Unit";"Baneling";"Zergling";445;0
"Unit";"Baneling";"Zergling";445;0
"Unit";"Baneling";"Zergling";445;0
"Unit";"Baneling";"Zergling";445;0
"Unit";"Baneling";"Zergling";445;0
"Unit";"Baneling";"Zergling";445;0
"Unit";"Baneling";"Zergling";445;0
"Unit";"Baneling";"Zergling";445;0
"Unit";"Baneling";"Zergling";445;0
"Unit";"Baneling";"Zergling";445;0
"Unit";"Baneling";"Zergling";445;0
"Unit";"Baneling";"Zergling";445;0
"Unit";"Baneling";"Zergling";445;0
"Unit";"Hydralisk";"Larva";415;2
"Unit";"Hydralisk";"Larva";415;2
"Unit";"Hydralisk";"Larva";415;2
"Unit";"Hydralisk";"Larva";415;2
"Unit";"Hydralisk";"Larva";415;2
"Unit";"Hydralisk";"Larva";415;2
"Unit";"Baneling";"Zergling";473;0
"Unit";"Baneling";"Zergling";473;0
"Unit";"Baneling";"Zergling";473;0
"Unit";"Baneling";"Zergling";473;0
"Unit";"Baneling";"Zergling";473;0
"Unit";"Baneling";"Zergling";473;0
"Unit";"Baneling";"Zergling";473;0
"Unit";"Baneling";"Zergling";473;0
"Unit";"Baneling";"Zergling";473;0
"Unit";"Baneling";"Zergling";473;0
"Unit";"Baneling";"Zergling";473;0
"Unit";"Baneling";"Zergling";473;0
"Unit";"Baneling";"Zergling";473;0
"Unit";"Infestor";"Larva";415;2
"Unit";"Infestor";"Larva";415;2
"Unit";"Infestor";"Larva";415;2
"Unit";"Infestor";"Larva";415;2
"Unit";"Infestor";"Larva";415;2
"Building";"CreepTumorQueen";NA;513;0
"Unit";"Zergling";"Larva";513;1
"Unit";"Zergling";"Larva";513;1
"Unit";"Zergling";"Larva";513;1
"Unit";"Zergling";"Larva";513;1
"Unit";"Zergling";"Larva";513;1
"Unit";"Zergling";"Larva";513;1
"Unit";"Zergling";"Larva";513;1
"Unit";"Zergling";"Larva";513;1
"Unit";"Zergling";"Larva";513;1
"Unit";"Zergling";"Larva";513;1
"Unit";"Zergling";"Larva";513;1
"Unit";"Zergling";"Larva";513;1
"Building";"CreepTumorQueen";NA;513;0
"Unit";"Zergling";"Larva";513;1
"Unit";"Zergling";"Larva";513;1
"Unit";"Zergling";"Larva";513;1
"Unit";"Zergling";"Larva";513;1
"Unit";"Zergling";"Larva";513;1
"Unit";"Zergling";"Larva";513;1
"Unit";"Zergling";"Larva";513;1
"Unit";"Zergling";"Larva";513;1
"Unit";"Hydralisk";"Larva";513;2
"Unit";"Hydralisk";"Larva";513;2
"Unit";"Hydralisk";"Larva";513;2
"Unit";"Hydralisk";"Larva";513;2
"Unit";"Hydralisk";"Larva";513;2
"Unit";"Hydralisk";"Larva";513;2
"Unit";"Hydralisk";"Larva";513;2
"Unit";"Hydralisk";"Larva";513;2
"Unit";"Hydralisk";"Larva";513;2
"Unit";"Hydralisk";"Larva";513;2
"Unit";"Corruptor";"Larva";513;2
"Building";"CreepTumorQueen";NA;553;0
"Building";"CreepTumorQueen";NA;553;0
"Unit";"Infestor";"Larva";513;2
"Unit";"Infestor";"Larva";513;2
"Unit";"Infestor";"Larva";513;2
"Unit";"Infestor";"Larva";513;2
"Upgrade";"ZergGroundArmorsLevel3";"EvolutionChamber";415;0
"Unit";"Baneling";"Zergling";553;0
"Unit";"Baneling";"Zergling";553;0
"Unit";"Baneling";"Zergling";553;0
"Unit";"Baneling";"Zergling";553;0
"Unit";"Baneling";"Zergling";553;0
"Unit";"Baneling";"Zergling";553;0
"Unit";"Baneling";"Zergling";553;0
"Unit";"Zergling";"Larva";553;1
"Unit";"Zergling";"Larva";553;1
"Unit";"Zergling";"Larva";553;1
"Unit";"Zergling";"Larva";553;1
"Unit";"Zergling";"Larva";553;1
"Unit";"Zergling";"Larva";553;1
"Unit";"Zergling";"Larva";553;1
"Unit";"Zergling";"Larva";553;1
"Unit";"Zergling";"Larva";553;1
"Unit";"Zergling";"Larva";553;1
"Unit";"Zergling";"Larva";553;1
"Unit";"Zergling";"Larva";553;1
"Unit";"Zergling";"Larva";553;1
"Unit";"Zergling";"Larva";553;1
"Unit";"Zergling";"Larva";553;1
"Unit";"Zergling";"Larva";553;1
"Unit";"Zergling";"Larva";553;1
"Unit";"Zergling";"Larva";553;1
"Building";"CreepTumor";NA;555;0
"Building";"CreepTumor";NA;555;0
"Building";"CreepTumor";NA;581;0
"Building";"CreepTumor";NA;581;0
"Building";"Hatchery";NA;553;0
"Unit";"Corruptor";"Larva";581;2
"Unit";"Corruptor";"Larva";581;2
"Unit";"Corruptor";"Larva";581;2
"Unit";"Zergling";"Larva";584;1
"Unit";"Zergling";"Larva";584;1
"Unit";"Zergling";"Larva";584;1
"Unit";"Zergling";"Larva";584;1
"Unit";"Zergling";"Larva";584;1
"Unit";"Zergling";"Larva";584;1
"Unit";"Zergling";"Larva";584;1
"Unit";"Zergling";"Larva";584;1
"Unit";"Zergling";"Larva";584;1
"Unit";"Zergling";"Larva";584;1
"Unit";"Zergling";"Larva";584;1
"Unit";"Zergling";"Larva";584;1
"Unit";"Zergling";"Larva";584;1
"Unit";"Zergling";"Larva";584;1
"Unit";"Zergling";"Larva";584;1
"Unit";"Zergling";"Larva";584;1
"Unit";"Zergling";"Larva";584;1
"Unit";"Zergling";"Larva";584;1
"Unit";"Zergling";"Larva";584;1
"Unit";"Zergling";"Larva";584;1
"Unit";"Zergling";"Larva";584;1
"Unit";"Zergling";"Larva";584;1
"Unit";"Baneling";"Zergling";584;0
"Unit";"Baneling";"Zergling";584;0
"Unit";"Baneling";"Zergling";584;0
"Unit";"Baneling";"Zergling";584;0
"Unit";"Baneling";"Zergling";584;0
"Unit";"Baneling";"Zergling";584;0
"Unit";"Baneling";"Zergling";584;0
"Unit";"Baneling";"Zergling";584;0
"Unit";"Baneling";"Zergling";584;0
"Unit";"Baneling";"Zergling";584;0
"Unit";"Baneling";"Zergling";584;0
"Unit";"Baneling";"Zergling";584;0
"Unit";"Baneling";"Zergling";584;0
"Unit";"Baneling";"Zergling";584;0
"Unit";"Baneling";"Zergling";584;0
"Unit";"Baneling";"Zergling";584;0
"Unit";"Hydralisk";"Larva";584;2
"Unit";"Hydralisk";"Larva";584;2
"Unit";"Hydralisk";"Larva";584;2
"Unit";"Hydralisk";"Larva";584;2
"Building";"SporeCrawler";NA;584;0
"Building";"CreepTumor";NA;620;0
"Building";"CreepTumor";NA;620;0
"Building";"SpineCrawler";NA;584;0
"Building";"SpineCrawler";NA;584;0
"Building";"SpineCrawler";NA;590;0
"Building";"SpineCrawler";NA;590;0
"Unit";"Corruptor";"Larva";612;2
"Unit";"Corruptor";"Larva";612;2
"Unit";"Corruptor";"Larva";612;2
"Unit";"Corruptor";"Larva";612;2
"Unit";"Zergling";"Larva";628;1
"Unit";"Zergling";"Larva";628;1
"Unit";"Zergling";"Larva";628;1
"Unit";"Zergling";"Larva";628;1
"Unit";"Zergling";"Larva";628;1
"Unit";"Zergling";"Larva";628;1
"Unit";"Zergling";"Larva";628;1
"Unit";"Zergling";"Larva";628;1
"Unit";"Zergling";"Larva";628;1
"Unit";"Zergling";"Larva";628;1
"Unit";"Zergling";"Larva";628;1
"Unit";"Zergling";"Larva";628;1
"Unit";"Zergling";"Larva";628;1
"Unit";"Zergling";"Larva";628;1
"Unit";"Zergling";"Larva";628;1
"Unit";"Zergling";"Larva";628;1
"Unit";"Zergling";"Larva";628;1
"Unit";"Zergling";"Larva";628;1
"Unit";"Hydralisk";"Larva";628;2
"Unit";"Hydralisk";"Larva";628;2
"Unit";"Hydralisk";"Larva";628;2
"Unit";"Hydralisk";"Larva";628;2
"Unit";"Hydralisk";"Larva";628;2
"Unit";"Hydralisk";"Larva";628;2
"Unit";"Hydralisk";"Larva";628;2
"Unit";"Hydralisk";"Larva";628;2
"Unit";"Hydralisk";"Larva";628;2
"Unit";"Zergling";"Larva";628;1
"Unit";"Zergling";"Larva";628;1
"Unit";"Zergling";"Larva";628;1
"Unit";"Zergling";"Larva";628;1
"Unit";"Zergling";"Larva";628;1
"Unit";"Zergling";"Larva";628;1
"Unit";"Zergling";"Larva";628;1
"Unit";"Zergling";"Larva";628;1
"Unit";"Zergling";"Larva";628;1
"Unit";"Zergling";"Larva";628;1
"Unit";"Zergling";"Larva";628;1
"Unit";"Zergling";"Larva";628;1
"Unit";"Zergling";"Larva";628;1
"Unit";"Zergling";"Larva";628;1
"Unit";"Zergling";"Larva";628;1
"Unit";"Zergling";"Larva";628;1
"Unit";"Zergling";"Larva";628;1
"Unit";"Zergling";"Larva";628;1
"Unit";"Zergling";"Larva";628;1
"Unit";"Zergling";"Larva";628;1
"Unit";"Corruptor";"Larva";628;2
"Unit";"Corruptor";"Larva";628;2
"Unit";"Zergling";"Larva";684;1
"Unit";"Zergling";"Larva";684;1
"Unit";"Zergling";"Larva";684;1
"Unit";"Zergling";"Larva";684;1
"Unit";"Zergling";"Larva";684;1
"Unit";"Zergling";"Larva";684;1
"Unit";"Zergling";"Larva";684;1
"Unit";"Zergling";"Larva";684;1
"Unit";"Zergling";"Larva";684;1
"Unit";"Zergling";"Larva";684;1
"Unit";"Zergling";"Larva";684;1
"Unit";"Zergling";"Larva";684;1
"Unit";"Zergling";"Larva";684;1
"Unit";"Zergling";"Larva";684;1
"Unit";"Hydralisk";"Larva";684;2
"Unit";"Hydralisk";"Larva";684;2
"Unit";"Overlord";"Larva";688;0
"Unit";"Overlord";"Larva";688;0
"Unit";"Overlord";"Larva";688;0
"Unit";"Overlord";"Larva";688;0
"Unit";"Overlord";"Larva";688;0
"Unit";"Corruptor";"Larva";688;2
"Unit";"Corruptor";"Larva";688;2
"Unit";"Corruptor";"Larva";688;2
"Unit";"Corruptor";"Larva";688;2
"Unit";"Corruptor";"Larva";688;2
"Unit";"Corruptor";"Larva";688;2
"Unit";"Corruptor";"Larva";688;2
"Unit";"Baneling";"Zergling";706;0
"Unit";"Baneling";"Zergling";706;0
"Unit";"Baneling";"Zergling";706;0
"Unit";"Baneling";"Zergling";706;0
"Unit";"Baneling";"Zergling";706;0
"Unit";"Baneling";"Zergling";706;0
"Unit";"Baneling";"Zergling";706;0
"Unit";"Baneling";"Zergling";706;0
"Unit";"Baneling";"Zergling";706;0
"Unit";"Baneling";"Zergling";706;0
"Unit";"Baneling";"Zergling";706;0
"Unit";"Baneling";"Zergling";706;0
"Unit";"Baneling";"Zergling";706;0
"Unit";"Baneling";"Zergling";706;0
"Unit";"Baneling";"Zergling";706;0
"Unit";"Baneling";"Zergling";706;0
"Unit";"Baneling";"Zergling";706;0
"Unit";"Baneling";"Zergling";706;0
"Unit";"Baneling";"Zergling";706;0
"Unit";"Baneling";"Zergling";706;0
"Unit";"Baneling";"Zergling";706;0
"Unit";"Baneling";"Zergling";706;0
"Unit";"Baneling";"Zergling";706;0
"Unit";"Baneling";"Zergling";706;0
"Building";"Extractor";NA;706;0
"Building";"Extractor";NA;720;0
"Unit";"Corruptor";"Larva";706;2
"Unit";"Corruptor";"Larva";708;2
"Unit";"Corruptor";"Larva";710;2
"Unit";"Corruptor";"Larva";714;2
"Unit";"Infestor";"Larva";706;2
"Unit";"Infestor";"Larva";706;2
"Unit";"Infestor";"Larva";706;2
"Unit";"Infestor";"Larva";706;2
"Unit";"Infestor";"Larva";706;2
"Unit";"Zergling";"Larva";738;1
"Unit";"Zergling";"Larva";738;1
"Unit";"Zergling";"Larva";738;1
"Unit";"Zergling";"Larva";738;1
"Unit";"Zergling";"Larva";738;1
"Unit";"Zergling";"Larva";738;1
"Unit";"Zergling";"Larva";738;1
"Unit";"Zergling";"Larva";738;1
"Unit";"Zergling";"Larva";738;1
"Unit";"Zergling";"Larva";738;1
"Unit";"Zergling";"Larva";738;1
"Unit";"Zergling";"Larva";738;1
"Building";"Extractor";NA;738;0
"Building";"SporeCrawler";NA;738;0
"Building";"Extractor";NA;738;0
"Unit";"Hydralisk";"Larva";738;2
"Unit";"Hydralisk";"Larva";738;2
"Unit";"Hydralisk";"Larva";738;2
"Unit";"Hydralisk";"Larva";738;2
"Unit";"Hydralisk";"Larva";738;2
"Unit";"Hydralisk";"Larva";738;2
"Unit";"Hydralisk";"Larva";738;2
"Building";"SpineCrawler";NA;738;0
"Unit";"Hydralisk";"Larva";738;2
"Unit";"Hydralisk";"Larva";738;2
"Unit";"Hydralisk";"Larva";738;2
"Unit";"Hydralisk";"Larva";738;2
"Unit";"Hydralisk";"Larva";738;2
"Building";"CreepTumorQueen";NA;786;0
"Building";"CreepTumorQueen";NA;786;0
"Unit";"Baneling";"Zergling";786;0
"Unit";"Baneling";"Zergling";786;0
"Unit";"Baneling";"Zergling";786;0
"Unit";"Baneling";"Zergling";786;0
"Unit";"Baneling";"Zergling";786;0
"Unit";"Baneling";"Zergling";786;0
"Unit";"Baneling";"Zergling";786;0
"Unit";"Baneling";"Zergling";786;0
"Unit";"Baneling";"Zergling";786;0
"Unit";"Baneling";"Zergling";786;0
"Unit";"Baneling";"Zergling";786;0
"Unit";"Baneling";"Zergling";786;0
"Building";"CreepTumorQueen";NA;786;0
"Building";"CreepTumorQueen";NA;786;0
"Building";"CreepTumorQueen";NA;786;0
"Building";"CreepTumor";NA;792;0
"Building";"CreepTumor";NA;792;0
"Building";"CreepTumor";NA;792;0
"Building";"CreepTumor";NA;792;0
"Unit";"Overlord";"Larva";792;0
"Unit";"Overlord";"Larva";792;0
"Unit";"Overlord";"Larva";792;0
"Building";"Hatchery";NA;786;0
"Unit";"Zergling";"Larva";792;1
"Unit";"Zergling";"Larva";792;1
"Unit";"Zergling";"Larva";792;1
"Unit";"Zergling";"Larva";792;1
"Unit";"Zergling";"Larva";792;1
"Unit";"Zergling";"Larva";792;1
"Unit";"Zergling";"Larva";792;1
"Unit";"Zergling";"Larva";792;1
"Unit";"Zergling";"Larva";792;1
"Unit";"Zergling";"Larva";792;1
"Unit";"Zergling";"Larva";792;1
"Unit";"Zergling";"Larva";792;1
"Unit";"Zergling";"Larva";792;1
"Unit";"Zergling";"Larva";792;1
"Unit";"Zergling";"Larva";792;1
"Unit";"Zergling";"Larva";792;1
"Unit";"Zergling";"Larva";792;1
"Unit";"Zergling";"Larva";792;1
"Unit";"Hydralisk";"Larva";792;2
"Unit";"Hydralisk";"Larva";792;2
"Unit";"Hydralisk";"Larva";792;2
"Unit";"Hydralisk";"Larva";792;2
"Unit";"Hydralisk";"Larva";792;2
"Unit";"Hydralisk";"Larva";792;2
"Unit";"Hydralisk";"Larva";792;2
"Unit";"Hydralisk";"Larva";792;2
"Unit";"Hydralisk";"Larva";792;2
"Unit";"Hydralisk";"Larva";792;2
"Unit";"Hydralisk";"Larva";792;2
"Building";"SporeCrawler";NA;792;0
"Building";"SporeCrawler";NA;792;0
"Building";"CreepTumor";NA;792;0
"Building";"CreepTumor";NA;832;0
"Building";"CreepTumor";NA;832;0
"Unit";"Zergling";"Larva";832;1
"Unit";"Zergling";"Larva";832;1
"Unit";"Zergling";"Larva";832;1
"Unit";"Zergling";"Larva";832;1
"Unit";"Zergling";"Larva";832;1
"Unit";"Zergling";"Larva";832;1
"Unit";"Baneling";"Zergling";832;0
"Unit";"Baneling";"Zergling";832;0
"Unit";"Baneling";"Zergling";832;0
"Unit";"Baneling";"Zergling";832;0
"Unit";"Baneling";"Zergling";832;0
"Unit";"Baneling";"Zergling";832;0
"Unit";"Zergling";"Larva";838;1
"Unit";"Zergling";"Larva";838;1
"Unit";"Zergling";"Larva";838;1
"Unit";"Zergling";"Larva";838;1
"Unit";"Zergling";"Larva";838;1
"Unit";"Zergling";"Larva";838;1
"Unit";"Zergling";"Larva";838;1
"Unit";"Zergling";"Larva";838;1
"Unit";"Zergling";"Larva";838;1
"Unit";"Zergling";"Larva";838;1
"Unit";"Zergling";"Larva";838;1
"Unit";"Zergling";"Larva";838;1
"Unit";"Hydralisk";"Larva";838;2
"Unit";"Hydralisk";"Larva";838;2
"Unit";"Hydralisk";"Larva";838;2
"Unit";"Hydralisk";"Larva";838;2
"Unit";"Hydralisk";"Larva";838;2
"Unit";"Hydralisk";"Larva";838;2
"Unit";"Hydralisk";"Larva";838;2
"Unit";"Hydralisk";"Larva";838;2
"Unit";"Zergling";"Larva";850;1
"Unit";"Zergling";"Larva";850;1
"Unit";"Zergling";"Larva";850;1
"Unit";"Zergling";"Larva";850;1
"Unit";"Zergling";"Larva";852;1
"Unit";"Zergling";"Larva";852;1
"Unit";"Zergling";"Larva";854;1
"Unit";"Zergling";"Larva";854;1
"Unit";"Zergling";"Larva";856;1
"Unit";"Zergling";"Larva";856;1
"Unit";"Zergling";"Larva";858;1
"Unit";"Zergling";"Larva";858;1
"Unit";"Overlord";"Larva";866;0
"Unit";"Overlord";"Larva";866;0
"Unit";"Overlord";"Larva";866;0
"Unit";"Hydralisk";"Larva";850;2
"Unit";"Hydralisk";"Larva";850;2
"Unit";"Hydralisk";"Larva";852;2
"Unit";"Hydralisk";"Larva";854;2
"Unit";"Hydralisk";"Larva";856;2
"Unit";"Baneling";"Zergling";866;0
"Unit";"Baneling";"Zergling";866;0
"Unit";"Baneling";"Zergling";866;0
"Unit";"Baneling";"Zergling";866;0
"Unit";"Baneling";"Zergling";866;0
"Unit";"Baneling";"Zergling";866;0
"Unit";"Baneling";"Zergling";866;0
"Unit";"Baneling";"Zergling";866;0
"Unit";"Baneling";"Zergling";866;0
"Unit";"Baneling";"Zergling";866;0
"Unit";"Baneling";"Zergling";866;0
"Unit";"Baneling";"Zergling";866;0
"Unit";"Overlord";"Larva";866;0
"Unit";"Overlord";"Larva";866;0
"Unit";"Zergling";"Larva";888;1
"Unit";"Zergling";"Larva";888;1
"Unit";"Zergling";"Larva";888;1
"Unit";"Zergling";"Larva";888;1
"Unit";"Zergling";"Larva";888;1
"Unit";"Zergling";"Larva";888;1
"Unit";"Zergling";"Larva";888;1
"Unit";"Zergling";"Larva";888;1
"Unit";"Zergling";"Larva";888;1
"Unit";"Zergling";"Larva";888;1
"Unit";"Zergling";"Larva";888;1
"Unit";"Zergling";"Larva";888;1
"Unit";"Zergling";"Larva";888;1
"Unit";"Zergling";"Larva";888;1
"Unit";"Zergling";"Larva";888;1
"Unit";"Zergling";"Larva";888;1
"Unit";"Zergling";"Larva";888;1
"Unit";"Zergling";"Larva";888;1
"Unit";"Zergling";"Larva";888;1
"Unit";"Zergling";"Larva";888;1
"Unit";"Hydralisk";"Larva";888;2
"Unit";"Hydralisk";"Larva";888;2
"Unit";"Hydralisk";"Larva";888;2
"Unit";"Hydralisk";"Larva";888;2
"Unit";"Hydralisk";"Larva";888;2
"Unit";"Hydralisk";"Larva";888;2
"Unit";"Hydralisk";"Larva";888;2
"Unit";"Hydralisk";"Larva";888;2
"Unit";"Hydralisk";"Larva";888;2
"Building";"Extractor";NA;888;0
"Building";"Extractor";NA;888;0
"Unit";"Infestor";"Larva";888;2
"Unit";"Infestor";"Larva";888;2
"Unit";"Infestor";"Larva";888;2
"Unit";"Infestor";"Larva";888;2
"Unit";"Infestor";"Larva";888;2
"Unit";"Infestor";"Larva";888;2
"Unit";"Zergling";"Larva";914;1
"Unit";"Zergling";"Larva";914;1
"Unit";"Zergling";"Larva";916;1
"Unit";"Zergling";"Larva";916;1
"Unit";"Zergling";"Larva";918;1
"Unit";"Zergling";"Larva";918;1
"Unit";"Zergling";"Larva";920;1
"Unit";"Zergling";"Larva";920;1
"Unit";"Zergling";"Larva";922;1
"Unit";"Zergling";"Larva";922;1
"Unit";"Zergling";"Larva";922;1
"Unit";"Zergling";"Larva";922;1
"Unit";"Zergling";"Larva";926;1
"Unit";"Zergling";"Larva";926;1
"Unit";"Zergling";"Larva";926;1
"Unit";"Zergling";"Larva";926;1
"Unit";"Zergling";"Larva";926;1
"Unit";"Zergling";"Larva";926;1
"Unit";"Zergling";"Larva";926;1
"Unit";"Zergling";"Larva";926;1
"Unit";"Zergling";"Larva";926;1
"Unit";"Zergling";"Larva";926;1
"Unit";"Hydralisk";"Larva";914;2
"Unit";"Hydralisk";"Larva";916;2
"Unit";"Hydralisk";"Larva";918;2
"Unit";"Baneling";"Zergling";926;0
"Unit";"Hydralisk";"Larva";920;2
"Unit";"Hydralisk";"Larva";922;2
"Unit";"Baneling";"Zergling";926;0
"Unit";"Baneling";"Zergling";926;0
"Unit";"Baneling";"Zergling";926;0
"Unit";"Baneling";"Zergling";926;0
"Unit";"Baneling";"Zergling";926;0
"Unit";"Baneling";"Zergling";926;0
"Unit";"Baneling";"Zergling";926;0
"Unit";"Baneling";"Zergling";926;0
"Building";"CreepTumor";NA;926;0
"Unit";"Baneling";"Zergling";926;0
"Unit";"Baneling";"Zergling";926;0
"Unit";"Baneling";"Zergling";926;0
"Unit";"Baneling";"Zergling";926;0
"Unit";"Baneling";"Zergling";926;0
"Unit";"Baneling";"Zergling";926;0
"Unit";"Baneling";"Zergling";926;0
"Unit";"Baneling";"Zergling";926;0
"Unit";"Corruptor";"Larva";970;2
"Unit";"Corruptor";"Larva";970;2
"Unit";"Corruptor";"Larva";970;2
"Unit";"Corruptor";"Larva";970;2
"Unit";"Corruptor";"Larva";970;2
"Unit";"Corruptor";"Larva";970;2
"Unit";"Corruptor";"Larva";970;2
"Unit";"Corruptor";"Larva";970;2
"Unit";"Corruptor";"Larva";970;2
"Unit";"Zergling";"Larva";988;1
"Unit";"Zergling";"Larva";988;1
"Unit";"Zergling";"Larva";988;1
"Unit";"Zergling";"Larva";988;1
"Unit";"Zergling";"Larva";988;1
"Unit";"Zergling";"Larva";988;1
"Unit";"Zergling";"Larva";988;1
"Unit";"Zergling";"Larva";988;1
"Unit";"Overlord";"Larva";988;0
"Unit";"Overlord";"Larva";988;0
"Unit";"Overlord";"Larva";988;0
"Unit";"Overlord";"Larva";988;0
"Unit";"Overlord";"Larva";988;0
"Unit";"Hydralisk";"Larva";988;2
"Unit";"Hydralisk";"Larva";988;2
"Unit";"Hydralisk";"Larva";988;2
"Unit";"Overlord";"Larva";996;0
"Unit";"Overlord";"Larva";996;0
"Unit";"Overlord";"Larva";996;0
"Unit";"Overlord";"Larva";996;0
"Upgrade";"NeuralParasite";"InfestationPit";970;0
"Unit";"Zergling";"Larva";1002;1
"Unit";"Zergling";"Larva";1002;1
"Unit";"Zergling";"Larva";1002;1
"Unit";"Zergling";"Larva";1002;1
"Unit";"Zergling";"Larva";1002;1
"Unit";"Zergling";"Larva";1002;1
"Unit";"Zergling";"Larva";1002;1
"Unit";"Zergling";"Larva";1002;1
"Unit";"Zergling";"Larva";1002;1
"Unit";"Zergling";"Larva";1002;1
"Unit";"Zergling";"Larva";1002;1
"Unit";"Zergling";"Larva";1002;1
"Unit";"Zergling";"Larva";1002;1
"Unit";"Zergling";"Larva";1002;1
"Unit";"Zergling";"Larva";1002;1
"Unit";"Zergling";"Larva";1002;1
"Unit";"Zergling";"Larva";1002;1
"Unit";"Zergling";"Larva";1002;1
"Unit";"Hydralisk";"Larva";1002;2
"Unit";"Hydralisk";"Larva";1002;2
"Unit";"Hydralisk";"Larva";1002;2
"Unit";"Hydralisk";"Larva";1002;2
"Unit";"Hydralisk";"Larva";1002;2
"Unit";"Hydralisk";"Larva";1002;2
"Unit";"Hydralisk";"Larva";1002;2
"Unit";"Hydralisk";"Larva";1002;2
