"type";"unit_name";"on_building";"total_supply";"supply"
"Unit";"Overlord";"Larva";13;0
"Building";"Extractor";NA;18;0
"Unit";"Overlord";"Larva";21;0
"Building";"SpawningPool";NA;19;0
"Building";"Hatchery";NA;17;0
"Unit";"Zergling";"Larva";22;1
"Unit";"Zergling";"Larva";22;1
"Unit";"Zergling";"Larva";23;1
"Unit";"Zergling";"Larva";23;1
"Unit";"Queen";"Hatchery";22;2
"Unit";"Queen";"Hatchery";23;2
"Building";"CreepTumorQueen";NA;32;0
"Unit";"Overlord";"Larva";38;0
"Building";"CreepTumor";NA;38;0
"Unit";"Queen";"Hatchery";35;2
"Building";"Hatchery";NA;27;0
"Unit";"Overlord";"Larva";40;0
"Unit";"Overlord";"Larva";40;0
"Unit";"Zergling";"Larva";46;1
"Unit";"Zergling";"Larva";46;1
"Unit";"Zergling";"Larva";46;1
"Unit";"Zergling";"Larva";46;1
"Building";"CreepTumor";NA;47;0
"Unit";"Zergling";"Larva";48;1
"Unit";"Zergling";"Larva";48;1
"Unit";"Zergling";"Larva";48;1
"Unit";"Zergling";"Larva";48;1
"Unit";"Zergling";"Larva";48;1
"Unit";"Zergling";"Larva";48;1
"Unit";"Zergling";"Larva";48;1
"Unit";"Zergling";"Larva";48;1
"Unit";"Zergling";"Larva";48;1
"Unit";"Zergling";"Larva";48;1
"Unit";"Overlord";"Larva";48;0
"Unit";"Zergling";"Larva";52;1
"Unit";"Zergling";"Larva";52;1
"Unit";"Zergling";"Larva";52;1
"Unit";"Zergling";"Larva";52;1
"Unit";"Zergling";"Larva";52;1
"Unit";"Zergling";"Larva";52;1
"Building";"CreepTumorQueen";NA;62;0
"Unit";"Zergling";"Larva";52;1
"Unit";"Zergling";"Larva";52;1
"Unit";"Zergling";"Larva";52;1
"Unit";"Zergling";"Larva";52;1
"Building";"CreepTumor";NA;62;0
"Building";"CreepTumorQueen";NA;62;0
"Unit";"Queen";"Hatchery";48;2
"Unit";"Overlord";"Larva";62;0
"Unit";"Zergling";"Larva";62;1
"Unit";"Zergling";"Larva";62;1
"Unit";"Zergling";"Larva";62;1
"Unit";"Zergling";"Larva";62;1
"Unit";"Overlord";"Larva";72;0
"Unit";"Zergling";"Larva";72;1
"Unit";"Zergling";"Larva";72;1
"Unit";"Zergling";"Larva";72;1
"Unit";"Zergling";"Larva";72;1
"Unit";"Zergling";"Larva";72;1
"Unit";"Zergling";"Larva";72;1
"Building";"BanelingNest";NA;52;0
"Building";"CreepTumor";NA;78;0
"Building";"CreepTumor";NA;78;0
"Building";"CreepTumor";NA;78;0
"Unit";"Queen";"Hatchery";62;2
"Building";"CreepTumorQueen";NA;84;0
"Unit";"Zergling";"Larva";84;1
"Unit";"Zergling";"Larva";84;1
"Unit";"Zergling";"Larva";84;1
"Unit";"Zergling";"Larva";84;1
"Unit";"Zergling";"Larva";84;1
"Unit";"Zergling";"Larva";84;1
"Unit";"Zergling";"Larva";84;1
"Unit";"Zergling";"Larva";84;1
"Unit";"Zergling";"Larva";84;1
"Unit";"Zergling";"Larva";84;1
"Unit";"Zergling";"Larva";84;1
"Unit";"Zergling";"Larva";84;1
"Unit";"Zergling";"Larva";84;1
"Unit";"Zergling";"Larva";84;1
"Unit";"Zergling";"Larva";84;1
"Unit";"Zergling";"Larva";84;1
"Unit";"Zergling";"Larva";102;1
"Unit";"Zergling";"Larva";102;1
"Unit";"Zergling";"Larva";102;1
"Unit";"Zergling";"Larva";102;1
"Unit";"Zergling";"Larva";102;1
"Unit";"Zergling";"Larva";102;1
"Unit";"Zergling";"Larva";102;1
"Unit";"Zergling";"Larva";102;1
"Unit";"Zergling";"Larva";102;1
"Unit";"Zergling";"Larva";102;1
"Unit";"Zergling";"Larva";102;1
"Unit";"Zergling";"Larva";102;1
"Unit";"Zergling";"Larva";102;1
"Unit";"Zergling";"Larva";102;1
"Unit";"Zergling";"Larva";102;1
"Unit";"Zergling";"Larva";102;1
"Unit";"Zergling";"Larva";102;1
"Unit";"Zergling";"Larva";102;1
"Unit";"Overlord";"Larva";102;0
"Unit";"Overlord";"Larva";102;0
"Unit";"Baneling";"Zergling";102;0
"Unit";"Baneling";"Zergling";102;0
"Unit";"Baneling";"Zergling";102;0
"Unit";"Baneling";"Zergling";102;0
"Unit";"Baneling";"Zergling";102;0
"Unit";"Baneling";"Zergling";102;0
"Unit";"Zergling";"Larva";120;1
"Unit";"Zergling";"Larva";120;1
"Unit";"Zergling";"Larva";120;1
"Unit";"Zergling";"Larva";120;1
"Unit";"Zergling";"Larva";120;1
"Unit";"Zergling";"Larva";120;1
"Unit";"Zergling";"Larva";120;1
"Unit";"Zergling";"Larva";120;1
"Unit";"Zergling";"Larva";120;1
"Unit";"Zergling";"Larva";120;1
"Unit";"Zergling";"Larva";120;1
"Unit";"Zergling";"Larva";120;1
"Unit";"Zergling";"Larva";132;1
"Unit";"Zergling";"Larva";132;1
"Unit";"Zergling";"Larva";132;1
"Unit";"Zergling";"Larva";132;1
"Unit";"Zergling";"Larva";132;1
"Unit";"Zergling";"Larva";132;1
"Unit";"Zergling";"Larva";132;1
"Unit";"Zergling";"Larva";132;1
"Unit";"Zergling";"Larva";132;1
"Unit";"Zergling";"Larva";132;1
"Unit";"Zergling";"Larva";132;1
"Unit";"Zergling";"Larva";132;1
"Unit";"Zergling";"Larva";132;1
"Unit";"Zergling";"Larva";132;1
"Unit";"Zergling";"Larva";132;1
"Unit";"Zergling";"Larva";132;1
"Unit";"Zergling";"Larva";132;1
"Unit";"Zergling";"Larva";132;1
"Unit";"Zergling";"Larva";132;1
"Unit";"Zergling";"Larva";132;1
"Unit";"Zergling";"Larva";132;1
"Unit";"Zergling";"Larva";132;1
"Unit";"Zergling";"Larva";132;1
"Unit";"Zergling";"Larva";132;1
"Unit";"Zergling";"Larva";132;1
"Unit";"Zergling";"Larva";132;1
"Unit";"Zergling";"Larva";132;1
"Unit";"Zergling";"Larva";132;1
"Unit";"Zergling";"Larva";132;1
"Unit";"Zergling";"Larva";132;1
"Unit";"Zergling";"Larva";132;1
"Unit";"Zergling";"Larva";132;1
"Unit";"Zergling";"Larva";132;1
"Unit";"Zergling";"Larva";132;1
