"type";"unit_name";"on_building";"total_supply";"supply"
"Unit";"Overlord";"Larva";13;0
"Building";"Extractor";NA;18;0
"Unit";"Overlord";"Larva";21;0
"Building";"SpawningPool";NA;19;0
"Building";"Hatchery";NA;17;0
"Unit";"Zergling";"Larva";22;1
"Unit";"Zergling";"Larva";22;1
"Unit";"Zergling";"Larva";22;1
"Unit";"Zergling";"Larva";22;1
"Unit";"Zergling";"Larva";22;1
"Unit";"Zergling";"Larva";22;1
"Unit";"Queen";"Hatchery";22;2
"Unit";"Queen";"Hatchery";22;2
"Unit";"Overlord";"Larva";38;0
"Unit";"Overlord";"Larva";39;0
"Unit";"Overlord";"Larva";43;0
"Building";"Hatchery";NA;36;0
"Unit";"Queen";"Hatchery";48;2
"Building";"Extractor";NA;51;0
"Unit";"Overlord";"Larva";58;0
"Building";"RoachWarren";NA;51;0
"Building";"SporeCrawler";NA;62;0
"Building";"Extractor";NA;62;0
"Building";"SporeCrawler";NA;62;0
"Building";"SporeCrawler";NA;62;0
"Unit";"Queen";"Hatchery";56;2
"Unit";"Roach";"Larva";64;2
"Unit";"Roach";"Larva";64;2
"Unit";"Overlord";"Larva";66;0
"Building";"CreepTumorQueen";NA;71;0
"Building";"EvolutionChamber";NA;71;0
"Unit";"Roach";"Larva";71;2
"Unit";"Roach";"Larva";71;2
"Unit";"Roach";"Larva";71;2
"Building";"EvolutionChamber";NA;71;0
"Unit";"Roach";"Larva";75;2
"Unit";"Roach";"Larva";75;2
"Unit";"Overlord";"Larva";75;0
"Unit";"Roach";"Larva";75;2
"Unit";"Overlord";"Larva";75;0
"Unit";"Overlord";"Larva";75;0
"Unit";"Overlord";"Larva";81;0
"Unit";"Overlord";"Larva";81;0
"Building";"Extractor";NA;81;0
"Building";"CreepTumorQueen";NA;87;0
"Unit";"Overlord";"Larva";104;0
"Unit";"Overlord";"Larva";105;0
"Upgrade";"GlialReconstitution";"RoachWarren";100;0
"Building";"Extractor";NA;111;0
"Building";"Extractor";NA;115;0
"Upgrade";"ZergMissileWeaponsLevel1";"EvolutionChamber";95;0
"Unit";"Roach";"Larva";122;2
"Unit";"Roach";"Larva";122;2
"Unit";"Roach";"Larva";122;2
"Unit";"Roach";"Larva";122;2
"Unit";"Roach";"Larva";122;2
"Upgrade";"ZergGroundArmorsLevel1";"EvolutionChamber";111;0
"Building";"InfestationPit";NA;123;0
"Building";"CreepTumorQueen";NA;140;0
"Building";"CreepTumor";NA;140;0
"Unit";"Roach";"Larva";138;2
"Unit";"Roach";"Larva";140;2
"Unit";"Roach";"Larva";140;2
"Unit";"Roach";"Larva";140;2
"Unit";"Roach";"Larva";140;2
"Unit";"Roach";"Larva";140;2
"Building";"HydraliskDen";NA;139;0
"Unit";"Queen";"Hatchery";136;2
"Unit";"Roach";"Larva";141;2
"Unit";"Roach";"Larva";141;2
"Unit";"Roach";"Larva";141;2
"Unit";"Roach";"Larva";141;2
"Unit";"Roach";"Larva";141;2
"Unit";"Overlord";"Larva";150;0
"Unit";"Overlord";"Larva";150;0
"Unit";"Overlord";"Larva";150;0
"Unit";"Overlord";"Larva";150;0
"Building";"Hatchery";NA;123;0
"Building";"Hatchery";NA;123;0
"Unit";"Overlord";"Larva";166;0
"Unit";"Overlord";"Larva";166;0
"Building";"Extractor";NA;166;0
"Unit";"Hydralisk";"Larva";173;2
"Unit";"Hydralisk";"Larva";178;2
"Unit";"Hydralisk";"Larva";178;2
"Unit";"Hydralisk";"Larva";178;2
"Unit";"Hydralisk";"Larva";180;2
"Building";"CreepTumorQueen";NA;182;0
"Unit";"Hydralisk";"Larva";180;2
"Unit";"Hydralisk";"Larva";180;2
"Unit";"Hydralisk";"Larva";180;2
"Unit";"Hydralisk";"Larva";180;2
"Upgrade";"EvolveGroovedSpines";"HydraliskDen";166;0
"Unit";"Hydralisk";"Larva";182;2
"Unit";"Hydralisk";"Larva";182;2
"Unit";"Hydralisk";"Larva";182;2
"Unit";"Hydralisk";"Larva";182;2
"Unit";"Hydralisk";"Larva";189;2
"Unit";"Hydralisk";"Larva";189;2
"Unit";"Hydralisk";"Larva";189;2
"Unit";"Overlord";"Larva";191;0
"Unit";"Overlord";"Larva";199;0
"Unit";"Hydralisk";"Larva";191;2
"Unit";"Hydralisk";"Larva";191;2
"Building";"CreepTumorQueen";NA;209;0
"Building";"CreepTumor";NA;207;0
"Unit";"Overlord";"Larva";207;0
"Unit";"Overlord";"Larva";207;0
"Unit";"Overlord";"Larva";207;0
"Unit";"Overlord";"Larva";207;0
"Upgrade";"ZergMissileWeaponsLevel2";"EvolutionChamber";166;0
"Unit";"Viper";"Larva";203;3
"Unit";"Viper";"Larva";217;3
"Unit";"Viper";"Larva";217;3
"Unit";"Hydralisk";"Larva";217;2
"Unit";"Hydralisk";"Larva";217;2
"Unit";"Viper";"Larva";217;3
"Unit";"Viper";"Larva";217;3
"Upgrade";"ZergGroundArmorsLevel2";"EvolutionChamber";177;0
"Building";"EvolutionChamber";NA;220;0
"Building";"EvolutionChamber";NA;220;0
"Building";"EvolutionChamber";NA;220;0
"Building";"EvolutionChamber";NA;220;0
"Unit";"Hydralisk";"Larva";220;2
"Unit";"Hydralisk";"Larva";220;2
"Unit";"Hydralisk";"Larva";220;2
"Unit";"Hydralisk";"Larva";220;2
"Unit";"Hydralisk";"Larva";220;2
"Unit";"Hydralisk";"Larva";230;2
"Building";"Extractor";NA;240;0
"Building";"Extractor";NA;240;0
"Upgrade";"EvolveMuscularAugments";"HydraliskDen";220;0
"Unit";"Hydralisk";"Larva";250;2
"Unit";"Hydralisk";"Larva";250;2
"Building";"Extractor";NA;252;0
"Unit";"Roach";"Larva";256;2
"Unit";"Roach";"Larva";256;2
"Unit";"Roach";"Larva";256;2
"Unit";"Roach";"Larva";256;2
"Unit";"Roach";"Larva";256;2
"Unit";"Hydralisk";"Larva";256;2
"Unit";"Hydralisk";"Larva";256;2
"Unit";"Hydralisk";"Larva";256;2
"Unit";"Hydralisk";"Larva";256;2
"Unit";"Hydralisk";"Larva";256;2
"Unit";"Hydralisk";"Larva";256;2
"Unit";"Hydralisk";"Larva";256;2
"Unit";"Hydralisk";"Larva";256;2
"Unit";"Hydralisk";"Larva";256;2
"Unit";"Hydralisk";"Larva";256;2
"Unit";"Hydralisk";"Larva";256;2
"Building";"Extractor";NA;288;0
"Unit";"Overlord";"Larva";288;0
"Unit";"Overlord";"Larva";288;0
"Building";"Hatchery";NA;278;0
"Building";"UltraliskCavern";NA;288;0
"Building";"Hatchery";NA;278;0
"Unit";"Roach";"Larva";288;2
"Unit";"Roach";"Larva";288;2
"Unit";"Roach";"Larva";288;2
"Unit";"Roach";"Larva";288;2
"Unit";"Roach";"Larva";288;2
"Unit";"Roach";"Larva";288;2
"Unit";"Hydralisk";"Larva";288;2
"Unit";"Hydralisk";"Larva";288;2
"Building";"Hatchery";NA;288;0
"Unit";"Hydralisk";"Larva";288;2
"Unit";"Hydralisk";"Larva";288;2
"Unit";"Hydralisk";"Larva";288;2
"Unit";"Hydralisk";"Larva";288;2
"Upgrade";"ZergMissileWeaponsLevel3";"EvolutionChamber";256;0
"Unit";"Zergling";"Larva";288;1
"Unit";"Zergling";"Larva";288;1
"Unit";"Zergling";"Larva";288;1
"Unit";"Zergling";"Larva";288;1
"Unit";"Zergling";"Larva";288;1
"Unit";"Zergling";"Larva";288;1
"Unit";"Zergling";"Larva";288;1
"Unit";"Zergling";"Larva";288;1
"Unit";"Zergling";"Larva";288;1
"Unit";"Zergling";"Larva";288;1
"Unit";"Zergling";"Larva";288;1
"Unit";"Zergling";"Larva";288;1
"Unit";"Zergling";"Larva";288;1
"Unit";"Zergling";"Larva";288;1
"Upgrade";"ZergGroundArmorsLevel3";"EvolutionChamber";256;0
"Unit";"Zergling";"Larva";300;1
"Unit";"Zergling";"Larva";300;1
"Unit";"Roach";"Larva";326;2
"Building";"Hatchery";NA;288;0
"Unit";"Roach";"Larva";326;2
"Unit";"Ultralisk";"Larva";300;6
"Unit";"Zergling";"Larva";328;1
"Unit";"Zergling";"Larva";328;1
"Unit";"Zergling";"Larva";340;1
"Unit";"Zergling";"Larva";340;1
"Unit";"Zergling";"Larva";340;1
"Unit";"Zergling";"Larva";340;1
"Unit";"Zergling";"Larva";340;1
"Unit";"Zergling";"Larva";340;1
"Unit";"Zergling";"Larva";340;1
"Unit";"Zergling";"Larva";340;1
"Unit";"Zergling";"Larva";340;1
"Unit";"Zergling";"Larva";340;1
"Upgrade";"ChitinousPlating";"UltraliskCavern";340;0
"Unit";"Viper";"Larva";356;3
"Unit";"Viper";"Larva";356;3
"Unit";"Hydralisk";"Larva";356;2
"Unit";"Hydralisk";"Larva";356;2
"Unit";"Hydralisk";"Larva";356;2
"Unit";"Hydralisk";"Larva";356;2
"Unit";"Hydralisk";"Larva";356;2
"Unit";"Hydralisk";"Larva";356;2
"Unit";"Hydralisk";"Larva";356;2
"Unit";"Hydralisk";"Larva";356;2
"Unit";"Hydralisk";"Larva";356;2
"Unit";"Hydralisk";"Larva";356;2
"Unit";"Hydralisk";"Larva";356;2
"Upgrade";"ZergMeleeWeaponsLevel1";"EvolutionChamber";340;0
"Unit";"Zergling";"Larva";362;1
"Unit";"Zergling";"Larva";362;1
"Unit";"Hydralisk";"Larva";386;2
"Unit";"Hydralisk";"Larva";386;2
"Unit";"Hydralisk";"Larva";386;2
"Unit";"Hydralisk";"Larva";386;2
"Unit";"Hydralisk";"Larva";386;2
"Unit";"Ultralisk";"Larva";386;6
"Unit";"Ultralisk";"Larva";386;6
"Unit";"Ultralisk";"Larva";386;6
"Unit";"Ultralisk";"Larva";386;6
"Unit";"Ultralisk";"Larva";386;6
"Unit";"Ultralisk";"Larva";386;6
"Unit";"Ultralisk";"Larva";386;6
"Unit";"Ultralisk";"Larva";386;6
"Unit";"Hydralisk";"Larva";386;2
"Unit";"Hydralisk";"Larva";386;2
"Unit";"Hydralisk";"Larva";386;2
"Unit";"Hydralisk";"Larva";386;2
"Unit";"Hydralisk";"Larva";386;2
"Unit";"Hydralisk";"Larva";386;2
"Unit";"Hydralisk";"Larva";386;2
"Unit";"Hydralisk";"Larva";386;2
"Unit";"Hydralisk";"Larva";386;2
"Unit";"Hydralisk";"Larva";386;2
"Unit";"Hydralisk";"Larva";392;2
"Unit";"Hydralisk";"Larva";392;2
"Unit";"Hydralisk";"Larva";392;2
"Unit";"Hydralisk";"Larva";394;2
"Unit";"Hydralisk";"Larva";396;2
"Unit";"Hydralisk";"Larva";396;2
"Unit";"Hydralisk";"Larva";444;2
"Unit";"Hydralisk";"Larva";444;2
"Unit";"Hydralisk";"Larva";464;2
"Unit";"Hydralisk";"Larva";472;2
"Unit";"Hydralisk";"Larva";472;2
"Unit";"Hydralisk";"Larva";478;2
"Unit";"Hydralisk";"Larva";478;2
"Unit";"Hydralisk";"Larva";478;2
"Unit";"Zergling";"Larva";482;1
"Unit";"Zergling";"Larva";482;1
"Unit";"Zergling";"Larva";482;1
"Unit";"Zergling";"Larva";482;1
"Unit";"Viper";"Larva";480;3
"Unit";"Viper";"Larva";482;3
"Unit";"Hydralisk";"Larva";484;2
"Unit";"Hydralisk";"Larva";486;2
"Unit";"Hydralisk";"Larva";494;2
"Unit";"Hydralisk";"Larva";494;2
"Unit";"Hydralisk";"Larva";494;2
"Unit";"Hydralisk";"Larva";494;2
"Unit";"Hydralisk";"Larva";496;2
"Unit";"Hydralisk";"Larva";496;2
"Unit";"Hydralisk";"Larva";506;2
"Unit";"Hydralisk";"Larva";514;2
"Unit";"Hydralisk";"Larva";514;2
"Unit";"Hydralisk";"Larva";514;2
"Unit";"Hydralisk";"Larva";514;2
"Unit";"Hydralisk";"Larva";514;2
"Unit";"Hydralisk";"Larva";520;2
"Unit";"Hydralisk";"Larva";520;2
"Unit";"Hydralisk";"Larva";520;2
"Unit";"Hydralisk";"Larva";520;2
"Unit";"Hydralisk";"Larva";520;2
"Unit";"Hydralisk";"Larva";520;2
"Unit";"Hydralisk";"Larva";520;2
"Unit";"Hydralisk";"Larva";530;2
"Unit";"Hydralisk";"Larva";530;2
"Unit";"Hydralisk";"Larva";530;2
"Unit";"Hydralisk";"Larva";544;2
"Unit";"Hydralisk";"Larva";544;2
"Unit";"Hydralisk";"Larva";544;2
"Unit";"Hydralisk";"Larva";544;2
"Unit";"Hydralisk";"Larva";544;2
"Unit";"Hydralisk";"Larva";550;2
"Unit";"Hydralisk";"Larva";550;2
"Unit";"Hydralisk";"Larva";550;2
"Unit";"Hydralisk";"Larva";550;2
"Unit";"Ultralisk";"Larva";563;6
"Unit";"Hydralisk";"Larva";571;2
"Unit";"Hydralisk";"Larva";571;2
"Unit";"Hydralisk";"Larva";571;2
"Unit";"Roach";"Larva";578;2
"Unit";"Roach";"Larva";578;2
"Unit";"Hydralisk";"Larva";578;2
"Unit";"Hydralisk";"Larva";578;2
"Unit";"Hydralisk";"Larva";578;2
"Unit";"Roach";"Larva";584;2
"Unit";"Roach";"Larva";584;2
"Unit";"Roach";"Larva";584;2
"Unit";"Roach";"Larva";584;2
"Unit";"Roach";"Larva";590;2
"Unit";"Roach";"Larva";590;2
"Unit";"Roach";"Larva";590;2
"Unit";"Hydralisk";"Larva";592;2
"Unit";"Hydralisk";"Larva";592;2
"Unit";"Hydralisk";"Larva";606;2
"Unit";"Hydralisk";"Larva";606;2
"Unit";"Hydralisk";"Larva";606;2
"Unit";"Roach";"Larva";624;2
"Unit";"Hydralisk";"Larva";618;2
"Unit";"Hydralisk";"Larva";618;2
"Unit";"Hydralisk";"Larva";618;2
"Unit";"Hydralisk";"Larva";618;2
"Unit";"Hydralisk";"Larva";618;2
"Unit";"Hydralisk";"Larva";618;2
"Unit";"Ultralisk";"Larva";614;6
"Unit";"Hydralisk";"Larva";624;2
"Unit";"Hydralisk";"Larva";624;2
"Unit";"Hydralisk";"Larva";626;2
"Unit";"Hydralisk";"Larva";626;2
"Unit";"Hydralisk";"Larva";626;2
"Unit";"Hydralisk";"Larva";626;2
"Unit";"Hydralisk";"Larva";626;2
"Unit";"Hydralisk";"Larva";648;2
"Unit";"Hydralisk";"Larva";648;2
"Unit";"Hydralisk";"Larva";648;2
"Unit";"Hydralisk";"Larva";658;2
"Unit";"Hydralisk";"Larva";658;2
"Unit";"Hydralisk";"Larva";664;2
"Unit";"Ultralisk";"Larva";658;6
"Unit";"Ultralisk";"Larva";658;6
"Unit";"Zergling";"Larva";670;1
"Unit";"Zergling";"Larva";670;1
"Unit";"Zergling";"Larva";670;1
"Unit";"Zergling";"Larva";670;1
"Unit";"Zergling";"Larva";670;1
"Unit";"Zergling";"Larva";670;1
"Unit";"Zergling";"Larva";670;1
"Unit";"Zergling";"Larva";670;1
"Unit";"Zergling";"Larva";670;1
"Unit";"Zergling";"Larva";670;1
"Unit";"Zergling";"Larva";670;1
"Unit";"Zergling";"Larva";670;1
"Unit";"Zergling";"Larva";670;1
"Unit";"Zergling";"Larva";670;1
"Unit";"Hydralisk";"Larva";670;2
"Unit";"Hydralisk";"Larva";670;2
"Unit";"Ultralisk";"Larva";664;6
"Unit";"Viper";"Larva";716;3
"Unit";"Viper";"Larva";721;3
"Unit";"Hydralisk";"Larva";724;2
"Unit";"Roach";"Larva";727;2
"Unit";"Ultralisk";"Larva";724;6
"Unit";"Hydralisk";"Larva";724;2
"Unit";"Roach";"Larva";727;2
"Unit";"Roach";"Larva";729;2
"Unit";"Roach";"Larva";729;2
"Unit";"Roach";"Larva";729;2
"Unit";"Roach";"Larva";729;2
"Unit";"Roach";"Larva";731;2
"Unit";"Roach";"Larva";741;2
"Building";"Hatchery";NA;724;0
"Unit";"Hydralisk";"Larva";741;2
"Unit";"Roach";"Larva";753;2
"Unit";"Ultralisk";"Larva";759;6
"Unit";"Viper";"Larva";762;3
"Unit";"Viper";"Larva";762;3
"Unit";"Viper";"Larva";762;3
"Unit";"Ultralisk";"Larva";768;6
"Building";"Hatchery";NA;762;0
"Unit";"Zergling";"Larva";783;1
"Unit";"Zergling";"Larva";783;1
