"type";"unit_name";"on_building";"total_supply";"supply"
"Unit";"Overlord";"Larva";13;0
"Building";"Extractor";NA;18;0
"Unit";"Overlord";"Larva";21;0
"Building";"SpawningPool";NA;19;0
"Building";"Hatchery";NA;17;0
"Unit";"Zergling";"Larva";22;1
"Unit";"Zergling";"Larva";22;1
"Unit";"Zergling";"Larva";23;1
"Unit";"Zergling";"Larva";23;1
"Unit";"Queen";"Hatchery";22;2
"Unit";"Queen";"Hatchery";23;2
"Unit";"Overlord";"Larva";36;0
"Unit";"Overlord";"Larva";39;0
"Unit";"Zergling";"Larva";42;1
"Unit";"Zergling";"Larva";42;1
"Unit";"Zergling";"Larva";42;1
"Unit";"Zergling";"Larva";42;1
"Unit";"Zergling";"Larva";42;1
"Unit";"Zergling";"Larva";42;1
"Unit";"Zergling";"Larva";42;1
"Unit";"Zergling";"Larva";42;1
"Unit";"Zergling";"Larva";42;1
"Unit";"Zergling";"Larva";42;1
"Building";"Hatchery";NA;32;0
"Unit";"Queen";"Hatchery";42;2
"Unit";"Overlord";"Larva";44;0
"Building";"Extractor";NA;54;0
"Building";"Extractor";NA;54;0
"Unit";"Queen";"Hatchery";56;2
"Building";"CreepTumorQueen";NA;67;0
"Unit";"Overlord";"Larva";67;0
"Unit";"Overlord";"Larva";67;0
"Building";"Extractor";NA;72;0
"Building";"CreepTumorQueen";NA;72;0
"Building";"SporeCrawler";NA;72;0
"Building";"SporeCrawler";NA;72;0
"Building";"CreepTumor";NA;72;0
"Unit";"Queen";"Hatchery";67;2
"Building";"CreepTumorQueen";NA;72;0
"Building";"SporeCrawler";NA;72;0
"Unit";"Queen";"Hatchery";72;2
"Unit";"Overlord";"Larva";81;0
"Unit";"Overlord";"Larva";83;0
"Building";"CreepTumor";NA;86;0
"Building";"CreepTumorQueen";NA;88;0
"Building";"CreepTumorQueen";NA;88;0
"Building";"CreepTumor";NA;88;0
"Building";"CreepTumor";NA;92;0
"Building";"Extractor";NA;92;0
"Unit";"Zergling";"Larva";92;1
"Unit";"Zergling";"Larva";92;1
"Building";"Extractor";NA;92;0
"Building";"CreepTumor";NA;96;0
"Unit";"Zergling";"Larva";96;1
"Unit";"Zergling";"Larva";96;1
"Unit";"Zergling";"Larva";96;1
"Unit";"Zergling";"Larva";96;1
"Unit";"Zergling";"Larva";96;1
"Unit";"Zergling";"Larva";96;1
"Unit";"Zergling";"Larva";96;1
"Unit";"Zergling";"Larva";96;1
"Unit";"Zergling";"Larva";96;1
"Unit";"Zergling";"Larva";96;1
"Unit";"Zergling";"Larva";96;1
"Unit";"Zergling";"Larva";96;1
"Building";"CreepTumor";NA;111;0
"Building";"CreepTumor";NA;111;0
"Building";"BanelingNest";NA;92;0
"Unit";"Overlord";"Larva";111;0
"Building";"CreepTumor";NA;111;0
"Unit";"Overlord";"Larva";111;0
"Unit";"Overlord";"Larva";111;0
"Unit";"Overlord";"Larva";111;0
"Unit";"Overlord";"Larva";111;0
"Unit";"Overlord";"Larva";111;0
"Unit";"Overlord";"Larva";111;0
"Building";"CreepTumorQueen";NA;111;0
"Building";"CreepTumorQueen";NA;111;0
"Building";"CreepTumorQueen";NA;111;0
"Building";"CreepTumor";NA;111;0
"Building";"Spire";NA;92;0
"Building";"CreepTumor";NA;111;0
"Building";"CreepTumor";NA;117;0
"Building";"CreepTumor";NA;117;0
"Building";"CreepTumor";NA;117;0
"Building";"CreepTumor";NA;117;0
"Building";"CreepTumor";NA;117;0
"Unit";"Mutalisk";"Larva";117;2
"Unit";"Mutalisk";"Larva";117;2
"Unit";"Mutalisk";"Larva";117;2
"Unit";"Mutalisk";"Larva";117;2
"Unit";"Mutalisk";"Larva";117;2
"Unit";"Mutalisk";"Larva";117;2
"Building";"CreepTumor";NA;117;0
"Unit";"Mutalisk";"Larva";117;2
"Unit";"Mutalisk";"Larva";117;2
"Unit";"Mutalisk";"Larva";117;2
"Building";"CreepTumor";NA;129;0
"Building";"CreepTumor";NA;129;0
"Unit";"Zergling";"Larva";132;1
"Unit";"Zergling";"Larva";132;1
"Unit";"Zergling";"Larva";132;1
"Unit";"Zergling";"Larva";132;1
"Unit";"Zergling";"Larva";132;1
"Unit";"Zergling";"Larva";132;1
"Unit";"Zergling";"Larva";132;1
"Unit";"Zergling";"Larva";132;1
"Unit";"Zergling";"Larva";132;1
"Unit";"Zergling";"Larva";132;1
"Unit";"Zergling";"Larva";132;1
"Unit";"Zergling";"Larva";132;1
"Unit";"Zergling";"Larva";132;1
"Unit";"Zergling";"Larva";132;1
"Building";"RoachWarren";NA;117;0
"Building";"CreepTumor";NA;150;0
"Building";"Hatchery";NA;117;0
"Building";"CreepTumor";NA;150;0
"Building";"CreepTumor";NA;150;0
"Unit";"Mutalisk";"Larva";136;2
"Building";"CreepTumor";NA;150;0
"Unit";"Mutalisk";"Larva";136;2
"Building";"CreepTumor";NA;150;0
"Unit";"Mutalisk";"Larva";136;2
"Unit";"Mutalisk";"Larva";136;2
"Building";"CreepTumor";NA;150;0
"Building";"CreepTumorQueen";NA;168;0
"Building";"CreepTumorQueen";NA;173;0
"Building";"CreepTumorQueen";NA;173;0
"Building";"CreepTumorQueen";NA;173;0
"Building";"CreepTumorQueen";NA;173;0
"Building";"CreepTumorQueen";NA;173;0
"Building";"CreepTumorQueen";NA;173;0
"Building";"CreepTumorQueen";NA;173;0
"Building";"CreepTumor";NA;173;0
"Unit";"Mutalisk";"Larva";173;2
"Unit";"Mutalisk";"Larva";173;2
"Unit";"Mutalisk";"Larva";173;2
"Unit";"Mutalisk";"Larva";173;2
"Unit";"Mutalisk";"Larva";173;2
"Unit";"Mutalisk";"Larva";173;2
"Building";"CreepTumor";NA;173;0
"Building";"CreepTumor";NA;173;0
"Building";"CreepTumor";NA;173;0
"Building";"CreepTumor";NA;173;0
"Building";"CreepTumor";NA;173;0
"Building";"CreepTumor";NA;173;0
"Building";"CreepTumor";NA;173;0
"Building";"CreepTumor";NA;173;0
"Building";"CreepTumor";NA;173;0
"Building";"CreepTumor";NA;173;0
"Building";"CreepTumor";NA;173;0
"Building";"CreepTumor";NA;173;0
"Building";"CreepTumorQueen";NA;190;0
"Building";"CreepTumorQueen";NA;190;0
"Building";"CreepTumorQueen";NA;190;0
"Building";"CreepTumorQueen";NA;190;0
"Building";"CreepTumorQueen";NA;190;0
"Unit";"Baneling";"Zergling";190;0
"Unit";"Baneling";"Zergling";190;0
"Unit";"Baneling";"Zergling";190;0
"Unit";"Baneling";"Zergling";190;0
"Unit";"Baneling";"Zergling";190;0
"Unit";"Baneling";"Zergling";190;0
"Unit";"Baneling";"Zergling";190;0
"Unit";"Baneling";"Zergling";190;0
"Unit";"Mutalisk";"Larva";190;2
"Unit";"Mutalisk";"Larva";190;2
"Unit";"Mutalisk";"Larva";190;2
"Unit";"Mutalisk";"Larva";190;2
"Building";"CreepTumor";NA;194;0
"Unit";"Overlord";"Larva";194;0
"Unit";"Overlord";"Larva";194;0
"Building";"CreepTumor";NA;202;0
"Building";"CreepTumor";NA;202;0
"Building";"CreepTumor";NA;202;0
"Building";"CreepTumor";NA;202;0
"Building";"CreepTumor";NA;202;0
"Building";"CreepTumor";NA;202;0
"Building";"CreepTumor";NA;202;0
"Building";"CreepTumor";NA;202;0
"Building";"CreepTumor";NA;202;0
"Unit";"Overlord";"Larva";194;0
"Unit";"Overlord";"Larva";194;0
"Unit";"Overlord";"Larva";194;0
"Unit";"Overlord";"Larva";194;0
"Building";"CreepTumor";NA;202;0
"Upgrade";"Burrow";"Hatchery";190;0
"Building";"CreepTumor";NA;202;0
"Building";"CreepTumor";NA;202;0
"Building";"CreepTumor";NA;202;0
"Unit";"Mutalisk";"Larva";202;2
"Unit";"Mutalisk";"Larva";202;2
"Unit";"Mutalisk";"Larva";202;2
"Unit";"Mutalisk";"Larva";202;2
"Unit";"Mutalisk";"Larva";202;2
"Unit";"Mutalisk";"Larva";202;2
"Unit";"Mutalisk";"Larva";202;2
"Unit";"Mutalisk";"Larva";202;2
"Unit";"Mutalisk";"Larva";202;2
"Unit";"Mutalisk";"Larva";202;2
"Unit";"Zergling";"Larva";227;1
"Unit";"Zergling";"Larva";227;1
"Unit";"Zergling";"Larva";227;1
"Unit";"Zergling";"Larva";227;1
"Unit";"Zergling";"Larva";227;1
"Unit";"Zergling";"Larva";227;1
"Unit";"Zergling";"Larva";227;1
"Unit";"Zergling";"Larva";227;1
"Building";"CreepTumor";NA;233;0
"Unit";"Zergling";"Larva";233;1
"Unit";"Zergling";"Larva";233;1
"Unit";"Zergling";"Larva";233;1
"Unit";"Zergling";"Larva";233;1
"Unit";"Zergling";"Larva";233;1
"Unit";"Zergling";"Larva";233;1
"Unit";"Zergling";"Larva";233;1
"Unit";"Zergling";"Larva";233;1
"Unit";"Zergling";"Larva";233;1
"Unit";"Zergling";"Larva";233;1
"Building";"CreepTumor";NA;233;0
"Building";"CreepTumor";NA;233;0
"Building";"CreepTumor";NA;233;0
"Building";"CreepTumor";NA;241;0
"Building";"CreepTumor";NA;241;0
"Building";"CreepTumor";NA;241;0
"Building";"CreepTumor";NA;241;0
"Building";"CreepTumor";NA;241;0
"Building";"CreepTumor";NA;241;0
"Unit";"Zergling";"Larva";233;1
"Unit";"Zergling";"Larva";233;1
"Building";"Extractor";NA;233;0
"Unit";"Zergling";"Larva";233;1
"Unit";"Zergling";"Larva";233;1
"Unit";"Zergling";"Larva";233;1
"Unit";"Zergling";"Larva";233;1
"Building";"Extractor";NA;233;0
"Unit";"Baneling";"Zergling";251;0
"Unit";"Baneling";"Zergling";251;0
"Unit";"Baneling";"Zergling";251;0
"Unit";"Baneling";"Zergling";251;0
"Unit";"Baneling";"Zergling";251;0
"Building";"CreepTumor";NA;251;0
"Unit";"Baneling";"Zergling";251;0
"Unit";"Baneling";"Zergling";251;0
"Unit";"Baneling";"Zergling";251;0
"Unit";"Baneling";"Zergling";251;0
"Unit";"Baneling";"Zergling";251;0
"Unit";"Baneling";"Zergling";251;0
"Unit";"Baneling";"Zergling";251;0
"Unit";"Baneling";"Zergling";251;0
"Unit";"Baneling";"Zergling";251;0
"Unit";"Baneling";"Zergling";251;0
"Unit";"Baneling";"Zergling";251;0
"Unit";"Baneling";"Zergling";251;0
"Unit";"Baneling";"Zergling";251;0
"Unit";"Baneling";"Zergling";251;0
"Unit";"Baneling";"Zergling";251;0
"Building";"InfestationPit";NA;233;0
"Building";"CreepTumorQueen";NA;257;0
"Building";"CreepTumorQueen";NA;257;0
"Building";"CreepTumorQueen";NA;257;0
"Building";"CreepTumorQueen";NA;257;0
