"type";"unit_name";"on_building";"total_supply";"supply"
"Unit";"Overlord";"Larva";15;0
"Building";"Hatchery";NA;15;0
"Building";"SpawningPool";NA;17;0
"Unit";"Overlord";"Larva";22;0
"Unit";"Queen";"Hatchery";22;2
"Unit";"Queen";"Hatchery";22;2
"Unit";"Overlord";"Larva";26;0
"Unit";"Queen";"Hatchery";26;2
"Unit";"Queen";"Hatchery";28;2
"Unit";"Overlord";"Larva";30;0
"Building";"CreepTumorQueen";NA;41;0
"Building";"CreepTumorQueen";NA;41;0
"Unit";"Overlord";"Larva";41;0
"Unit";"Queen";"Hatchery";34;2
"Unit";"Queen";"Hatchery";36;2
"Building";"Extractor";NA;41;0
"Building";"Extractor";NA;41;0
"Unit";"Overlord";"Larva";41;0
"Building";"CreepTumor";NA;46;0
"Building";"SporeCrawler";NA;50;0
"Building";"SporeCrawler";NA;50;0
"Unit";"Overlord";"Larva";54;0
"Building";"RoachWarren";NA;54;0
"Building";"Hatchery";NA;41;0
"Building";"CreepTumorQueen";NA;56;0
"Building";"CreepTumorQueen";NA;56;0
"Building";"CreepTumorQueen";NA;56;0
"Building";"CreepTumorQueen";NA;66;0
"Building";"CreepTumor";NA;56;0
"Building";"EvolutionChamber";NA;56;0
"Building";"Extractor";NA;66;0
"Building";"Extractor";NA;66;0
"Unit";"Roach";"Larva";66;2
"Unit";"Roach";"Larva";66;2
"Unit";"Roach";"Larva";66;2
"Unit";"Roach";"Larva";66;2
"Unit";"Roach";"Larva";66;2
"Unit";"Roach";"Larva";66;2
"Building";"CreepTumor";NA;66;0
"Building";"CreepTumor";NA;82;0
"Building";"CreepTumor";NA;82;0
"Unit";"Overlord";"Larva";82;0
"Unit";"Overlord";"Larva";82;0
"Unit";"Overlord";"Larva";82;0
"Building";"CreepTumorQueen";NA;82;0
"Building";"CreepTumorQueen";NA;82;0
"Building";"CreepTumorQueen";NA;82;0
"Building";"CreepTumorQueen";NA;82;0
"Unit";"Overlord";"Larva";82;0
"Unit";"Overlord";"Larva";82;0
"Unit";"Roach";"Larva";82;2
"Unit";"Roach";"Larva";82;2
"Unit";"Roach";"Larva";82;2
"Unit";"Roach";"Larva";82;2
"Unit";"Roach";"Larva";82;2
"Building";"HydraliskDen";NA;82;0
"Building";"CreepTumor";NA;99;0
"Unit";"Overlord";"Larva";95;0
"Building";"CreepTumor";NA;105;0
"Building";"CreepTumorQueen";NA;106;0
"Building";"CreepTumorQueen";NA;106;0
"Building";"CreepTumorQueen";NA;106;0
"Building";"CreepTumor";NA;106;0
"Building";"CreepTumor";NA;106;0
"Unit";"Hydralisk";"Larva";106;2
"Unit";"Hydralisk";"Larva";106;2
"Unit";"Hydralisk";"Larva";106;2
"Unit";"Hydralisk";"Larva";106;2
"Unit";"Hydralisk";"Larva";106;2
"Unit";"Hydralisk";"Larva";106;2
"Unit";"Hydralisk";"Larva";106;2
"Unit";"Hydralisk";"Larva";106;2
"Unit";"Hydralisk";"Larva";106;2
"Unit";"Hydralisk";"Larva";106;2
"Unit";"Hydralisk";"Larva";106;2
"Unit";"Hydralisk";"Larva";106;2
"Building";"Extractor";NA;106;0
"Building";"Extractor";NA;106;0
"Building";"CreepTumorQueen";NA;130;0
"Building";"CreepTumor";NA;130;0
"Building";"CreepTumor";NA;130;0
"Upgrade";"ZergMissileWeaponsLevel1";"EvolutionChamber";82;0
"Building";"CreepTumor";NA;130;0
"Building";"CreepTumorQueen";NA;130;0
"Building";"CreepTumor";NA;130;0
"Building";"CreepTumor";NA;130;0
"Building";"CreepTumorQueen";NA;130;0
"Unit";"Roach";"Larva";130;2
"Unit";"Roach";"Larva";130;2
"Unit";"Roach";"Larva";130;2
"Unit";"Roach";"Larva";130;2
"Unit";"Roach";"Larva";130;2
"Unit";"Roach";"Larva";130;2
"Unit";"Roach";"Larva";130;2
"Unit";"Roach";"Larva";130;2
"Building";"CreepTumorQueen";NA;138;0
"Building";"CreepTumorQueen";NA;146;0
"Building";"CreepTumorQueen";NA;146;0
"Unit";"Roach";"Larva";130;2
"Unit";"Roach";"Larva";130;2
"Unit";"Roach";"Larva";130;2
"Unit";"Roach";"Larva";130;2
"Unit";"Roach";"Larva";130;2
"Unit";"Roach";"Larva";130;2
"Unit";"Roach";"Larva";130;2
"Unit";"Roach";"Larva";130;2
"Unit";"Overlord";"Larva";130;0
"Unit";"Overlord";"Larva";130;0
"Unit";"Overlord";"Larva";130;0
"Upgrade";"EvolveGroovedSpines";"HydraliskDen";106;0
"Building";"CreepTumor";NA;146;0
"Building";"CreepTumor";NA;146;0
"Building";"CreepTumor";NA;162;0
"Building";"CreepTumorQueen";NA;162;0
"Building";"Hatchery";NA;106;0
"Building";"CreepTumor";NA;162;0
"Building";"CreepTumor";NA;162;0
"Building";"CreepTumor";NA;162;0
"Building";"CreepTumor";NA;162;0
"Building";"CreepTumor";NA;162;0
"Building";"CreepTumor";NA;162;0
"Building";"CreepTumor";NA;170;0
"Building";"CreepTumor";NA;170;0
"Building";"CreepTumor";NA;170;0
"Unit";"Overlord";"Larva";162;0
"Unit";"Overlord";"Larva";162;0
"Unit";"Overlord";"Larva";162;0
"Unit";"Overlord";"Larva";162;0
"Building";"CreepTumor";NA;170;0
"Building";"CreepTumor";NA;170;0
"Unit";"Roach";"Larva";170;2
"Unit";"Roach";"Larva";170;2
"Unit";"Roach";"Larva";170;2
"Unit";"Roach";"Larva";170;2
"Unit";"Roach";"Larva";170;2
"Unit";"Roach";"Larva";170;2
"Unit";"Roach";"Larva";170;2
"Unit";"Roach";"Larva";170;2
"Unit";"Roach";"Larva";170;2
"Building";"CreepTumorQueen";NA;170;0
"Building";"CreepTumorQueen";NA;170;0
"Unit";"Overlord";"Larva";170;0
"Upgrade";"EvolveMuscularAugments";"HydraliskDen";162;0
"Unit";"Roach";"Larva";188;2
"Unit";"Roach";"Larva";188;2
"Unit";"Roach";"Larva";188;2
"Unit";"Roach";"Larva";188;2
"Unit";"Roach";"Larva";188;2
"Unit";"Roach";"Larva";188;2
"Unit";"Roach";"Larva";188;2
"Unit";"Roach";"Larva";188;2
"Unit";"Roach";"Larva";188;2
"Unit";"Roach";"Larva";188;2
"Unit";"Roach";"Larva";188;2
"Unit";"Roach";"Larva";188;2
"Unit";"Roach";"Larva";188;2
"Building";"CreepTumor";NA;188;0
"Upgrade";"GlialReconstitution";"RoachWarren";170;0
"Building";"CreepTumor";NA;188;0
"Building";"CreepTumor";NA;188;0
"Building";"CreepTumor";NA;188;0
"Building";"InfestationPit";NA;188;0
"Building";"CreepTumorQueen";NA;214;0
"Building";"CreepTumorQueen";NA;214;0
"Building";"CreepTumorQueen";NA;214;0
"Building";"Hatchery";NA;170;0
"Upgrade";"ZergMissileWeaponsLevel2";"EvolutionChamber";168;0
"Unit";"Roach";"Larva";214;2
"Unit";"Roach";"Larva";214;2
"Unit";"Roach";"Larva";214;2
"Unit";"Roach";"Larva";214;2
"Unit";"Roach";"Larva";214;2
"Unit";"Roach";"Larva";214;2
"Unit";"Roach";"Larva";214;2
"Unit";"Roach";"Larva";214;2
"Unit";"Roach";"Larva";214;2
"Unit";"Roach";"Larva";214;2
"Unit";"Roach";"Larva";214;2
"Unit";"Hydralisk";"Larva";214;2
"Unit";"Hydralisk";"Larva";214;2
"Unit";"Hydralisk";"Larva";214;2
"Unit";"Hydralisk";"Larva";214;2
"Unit";"Hydralisk";"Larva";214;2
"Unit";"Hydralisk";"Larva";214;2
"Unit";"Hydralisk";"Larva";214;2
"Unit";"Roach";"Larva";250;2
"Unit";"Roach";"Larva";250;2
"Unit";"Roach";"Larva";250;2
"Unit";"Roach";"Larva";250;2
"Unit";"Roach";"Larva";250;2
"Unit";"Roach";"Larva";250;2
"Unit";"Roach";"Larva";250;2
"Unit";"Roach";"Larva";250;2
"Unit";"Roach";"Larva";250;2
"Unit";"Roach";"Larva";250;2
"Unit";"Roach";"Larva";250;2
"Unit";"Roach";"Larva";250;2
"Unit";"Roach";"Larva";250;2
"Unit";"Roach";"Larva";250;2
"Unit";"Roach";"Larva";250;2
"Unit";"Roach";"Larva";250;2
"Unit";"Roach";"Larva";250;2
"Unit";"Roach";"Larva";250;2
"Unit";"Roach";"Larva";250;2
"Unit";"Roach";"Larva";250;2
"Unit";"Roach";"Larva";250;2
"Unit";"Roach";"Larva";250;2
"Unit";"Roach";"Larva";250;2
"Unit";"Roach";"Larva";250;2
"Unit";"Roach";"Larva";250;2
"Unit";"Roach";"Larva";250;2
"Unit";"Roach";"Larva";250;2
"Unit";"Roach";"Larva";250;2
"Unit";"Roach";"Larva";250;2
"Unit";"Roach";"Larva";250;2
"Unit";"Roach";"Larva";250;2
"Unit";"Roach";"Larva";250;2
"Unit";"Roach";"Larva";250;2
"Unit";"Roach";"Larva";250;2
"Unit";"Roach";"Larva";250;2
"Unit";"Roach";"Larva";250;2
"Unit";"Roach";"Larva";250;2
"Unit";"Roach";"Larva";250;2
"Unit";"Roach";"Larva";250;2
"Unit";"Roach";"Larva";250;2
"Unit";"Roach";"Larva";250;2
"Unit";"Roach";"Larva";250;2
"Unit";"Roach";"Larva";250;2
"Unit";"Roach";"Larva";250;2
"Unit";"Roach";"Larva";250;2
"Unit";"Roach";"Larva";250;2
"Unit";"Roach";"Larva";250;2
"Unit";"Roach";"Larva";250;2
"Unit";"Roach";"Larva";250;2
"Unit";"Roach";"Larva";250;2
"Unit";"Roach";"Larva";250;2
"Unit";"Roach";"Larva";250;2
"Unit";"Roach";"Larva";340;2
"Unit";"Roach";"Larva";340;2
"Unit";"Roach";"Larva";340;2
"Unit";"Roach";"Larva";340;2
"Unit";"Roach";"Larva";362;2
"Unit";"Roach";"Larva";362;2
"Unit";"Roach";"Larva";362;2
"Unit";"Roach";"Larva";362;2
"Unit";"Roach";"Larva";362;2
"Unit";"Roach";"Larva";362;2
"Unit";"Roach";"Larva";362;2
"Unit";"Roach";"Larva";362;2
"Unit";"Roach";"Larva";362;2
"Unit";"Roach";"Larva";362;2
"Unit";"Roach";"Larva";362;2
"Unit";"Roach";"Larva";362;2
"Unit";"Roach";"Larva";362;2
"Unit";"Roach";"Larva";362;2
"Unit";"Roach";"Larva";362;2
"Unit";"Roach";"Larva";362;2
"Unit";"Roach";"Larva";362;2
"Unit";"Roach";"Larva";362;2
"Unit";"Roach";"Larva";362;2
"Unit";"Roach";"Larva";362;2
"Unit";"Roach";"Larva";362;2
"Unit";"Roach";"Larva";362;2
"Unit";"Roach";"Larva";362;2
"Unit";"Roach";"Larva";362;2
"Unit";"Roach";"Larva";362;2
"Unit";"Roach";"Larva";362;2
"Unit";"Roach";"Larva";362;2
"Unit";"Roach";"Larva";362;2
"Unit";"Roach";"Larva";362;2
"Unit";"Roach";"Larva";362;2
"Building";"Hatchery";NA;340;0
"Unit";"Overlord";"Larva";422;0
"Building";"CreepTumor";NA;432;0
"Building";"CreepTumor";NA;432;0
"Building";"CreepTumor";NA;432;0
"Building";"CreepTumor";NA;432;0
"Building";"CreepTumor";NA;432;0
"Building";"CreepTumor";NA;432;0
"Building";"CreepTumor";NA;450;0
"Building";"CreepTumor";NA;450;0
"Building";"CreepTumor";NA;450;0
"Unit";"Roach";"Larva";450;2
"Unit";"Roach";"Larva";450;2
"Unit";"Roach";"Larva";450;2
"Unit";"Roach";"Larva";450;2
"Unit";"Roach";"Larva";450;2
"Unit";"Roach";"Larva";450;2
"Unit";"Roach";"Larva";450;2
"Unit";"Roach";"Larva";450;2
"Unit";"Roach";"Larva";450;2
"Unit";"Roach";"Larva";450;2
"Unit";"Roach";"Larva";450;2
"Unit";"Roach";"Larva";450;2
"Unit";"Roach";"Larva";450;2
"Unit";"Roach";"Larva";450;2
"Unit";"Roach";"Larva";450;2
"Unit";"Roach";"Larva";450;2
"Unit";"Roach";"Larva";450;2
"Unit";"Roach";"Larva";450;2
"Unit";"Roach";"Larva";450;2
"Unit";"Roach";"Larva";450;2
"Unit";"Roach";"Larva";450;2
"Unit";"Roach";"Larva";450;2
"Unit";"Roach";"Larva";450;2
"Unit";"Roach";"Larva";450;2
"Unit";"Roach";"Larva";450;2
"Unit";"Roach";"Larva";450;2
"Unit";"Roach";"Larva";450;2
"Unit";"Roach";"Larva";450;2
"Unit";"Roach";"Larva";450;2
"Unit";"Roach";"Larva";450;2
"Unit";"Roach";"Larva";450;2
"Unit";"Roach";"Larva";450;2
"Unit";"Roach";"Larva";450;2
"Unit";"Roach";"Larva";450;2
"Unit";"Roach";"Larva";450;2
"Unit";"Roach";"Larva";450;2
"Unit";"Roach";"Larva";450;2
"Unit";"Roach";"Larva";450;2
"Unit";"Roach";"Larva";450;2
"Unit";"Roach";"Larva";450;2
"Unit";"Roach";"Larva";450;2
"Unit";"Roach";"Larva";450;2
"Unit";"Roach";"Larva";450;2
"Unit";"Roach";"Larva";450;2
"Unit";"Roach";"Larva";450;2
"Building";"Extractor";NA;450;0
"Building";"Extractor";NA;450;0
"Building";"Extractor";NA;450;0
"Building";"Extractor";NA;450;0
"Building";"Extractor";NA;450;0
"Building";"Extractor";NA;450;0
"Building";"CreepTumor";NA;540;0
"Building";"CreepTumor";NA;540;0
"Building";"CreepTumor";NA;540;0
"Building";"CreepTumor";NA;540;0
"Building";"CreepTumor";NA;540;0
"Building";"CreepTumor";NA;540;0
"Building";"Spire";NA;450;0
"Building";"EvolutionChamber";NA;540;0
"Unit";"Mutalisk";"Larva";540;2
"Unit";"Mutalisk";"Larva";540;2
"Unit";"Mutalisk";"Larva";540;2
"Unit";"Mutalisk";"Larva";540;2
"Unit";"Mutalisk";"Larva";540;2
"Unit";"Mutalisk";"Larva";540;2
"Unit";"Mutalisk";"Larva";540;2
"Unit";"Mutalisk";"Larva";540;2
"Unit";"Mutalisk";"Larva";540;2
"Unit";"Mutalisk";"Larva";540;2
"Unit";"Mutalisk";"Larva";540;2
"Unit";"Mutalisk";"Larva";540;2
"Unit";"Mutalisk";"Larva";540;2
"Unit";"Mutalisk";"Larva";540;2
"Unit";"Mutalisk";"Larva";540;2
"Unit";"Mutalisk";"Larva";540;2
"Unit";"Mutalisk";"Larva";540;2
"Unit";"Mutalisk";"Larva";540;2
"Unit";"Mutalisk";"Larva";540;2
"Unit";"Mutalisk";"Larva";540;2
"Unit";"Mutalisk";"Larva";540;2
"Unit";"Mutalisk";"Larva";540;2
"Unit";"Mutalisk";"Larva";540;2
"Unit";"Mutalisk";"Larva";540;2
"Unit";"Mutalisk";"Larva";540;2
"Unit";"Mutalisk";"Larva";540;2
"Unit";"Mutalisk";"Larva";540;2
"Unit";"Mutalisk";"Larva";540;2
"Unit";"Mutalisk";"Larva";540;2
"Unit";"Mutalisk";"Larva";540;2
"Unit";"Mutalisk";"Larva";540;2
"Unit";"Mutalisk";"Larva";540;2
"Unit";"Mutalisk";"Larva";540;2
"Unit";"Mutalisk";"Larva";540;2
"Unit";"Mutalisk";"Larva";540;2
"Unit";"Mutalisk";"Larva";540;2
"Unit";"Mutalisk";"Larva";540;2
"Unit";"Mutalisk";"Larva";540;2
"Unit";"Mutalisk";"Larva";540;2
"Unit";"Mutalisk";"Larva";540;2
"Unit";"Mutalisk";"Larva";540;2
"Unit";"Mutalisk";"Larva";540;2
"Unit";"Mutalisk";"Larva";540;2
"Unit";"Mutalisk";"Larva";540;2
"Unit";"Mutalisk";"Larva";540;2
"Unit";"Mutalisk";"Larva";540;2
"Unit";"Mutalisk";"Larva";540;2
"Unit";"Mutalisk";"Larva";540;2
"Unit";"Mutalisk";"Larva";540;2
"Unit";"Mutalisk";"Larva";540;2
"Unit";"Mutalisk";"Larva";540;2
"Building";"Extractor";NA;642;0
"Building";"Extractor";NA;642;0
"Building";"Extractor";NA;642;0
"Building";"Extractor";NA;642;0
"Unit";"Mutalisk";"Larva";642;2
"Unit";"Mutalisk";"Larva";642;2
"Unit";"Mutalisk";"Larva";642;2
"Unit";"Mutalisk";"Larva";642;2
"Unit";"Mutalisk";"Larva";642;2
"Unit";"Mutalisk";"Larva";642;2
"Unit";"Mutalisk";"Larva";642;2
"Unit";"Mutalisk";"Larva";642;2
"Unit";"Mutalisk";"Larva";642;2
"Unit";"Roach";"Larva";642;2
"Unit";"Roach";"Larva";642;2
"Unit";"Roach";"Larva";642;2
"Unit";"Roach";"Larva";642;2
"Unit";"Roach";"Larva";642;2
"Unit";"Roach";"Larva";642;2
"Unit";"Roach";"Larva";642;2
"Unit";"Roach";"Larva";642;2
"Unit";"Roach";"Larva";642;2
"Unit";"Roach";"Larva";642;2
"Unit";"Roach";"Larva";642;2
"Unit";"Roach";"Larva";642;2
"Unit";"Roach";"Larva";642;2
"Unit";"Roach";"Larva";642;2
"Unit";"Roach";"Larva";660;2
"Unit";"Roach";"Larva";660;2
"Unit";"Roach";"Larva";660;2
"Unit";"Roach";"Larva";660;2
"Unit";"Roach";"Larva";660;2
"Unit";"Roach";"Larva";660;2
"Unit";"Roach";"Larva";660;2
"Unit";"Roach";"Larva";660;2
"Building";"Hatchery";NA;642;0
"Unit";"Overlord";"Larva";688;0
"Unit";"Roach";"Larva";688;2
"Unit";"Roach";"Larva";688;2
"Unit";"Roach";"Larva";688;2
"Unit";"Roach";"Larva";688;2
"Unit";"Roach";"Larva";688;2
"Unit";"Roach";"Larva";688;2
"Building";"Hatchery";NA;642;0
"Unit";"Roach";"Larva";704;2
"Unit";"Roach";"Larva";718;2
"Unit";"Roach";"Larva";718;2
"Unit";"Roach";"Larva";718;2
"Unit";"Roach";"Larva";718;2
"Unit";"Roach";"Larva";718;2
"Unit";"Roach";"Larva";718;2
"Unit";"Roach";"Larva";718;2
"Unit";"Roach";"Larva";718;2
"Unit";"Roach";"Larva";718;2
"Unit";"Roach";"Larva";718;2
"Unit";"Roach";"Larva";738;2
"Unit";"Roach";"Larva";738;2
"Unit";"Roach";"Larva";738;2
"Unit";"Roach";"Larva";738;2
"Unit";"Roach";"Larva";738;2
"Unit";"Roach";"Larva";738;2
"Unit";"Roach";"Larva";738;2
"Unit";"Roach";"Larva";738;2
"Unit";"Roach";"Larva";750;2
"Unit";"Roach";"Larva";750;2
"Unit";"Roach";"Larva";750;2
"Unit";"Roach";"Larva";750;2
"Unit";"Roach";"Larva";750;2
"Unit";"Roach";"Larva";750;2
"Unit";"Roach";"Larva";750;2
"Unit";"Roach";"Larva";750;2
"Unit";"Roach";"Larva";750;2
"Unit";"Roach";"Larva";750;2
"Unit";"Roach";"Larva";750;2
"Unit";"Roach";"Larva";750;2
"Unit";"Roach";"Larva";750;2
"Unit";"Roach";"Larva";750;2
"Unit";"Roach";"Larva";750;2
"Unit";"Roach";"Larva";750;2
"Unit";"Roach";"Larva";750;2
"Unit";"Roach";"Larva";750;2
"Unit";"Roach";"Larva";750;2
"Unit";"Roach";"Larva";750;2
"Unit";"Roach";"Larva";750;2
"Unit";"Roach";"Larva";750;2
"Unit";"Roach";"Larva";750;2
"Unit";"Roach";"Larva";750;2
"Unit";"Roach";"Larva";750;2
"Unit";"Roach";"Larva";750;2
"Unit";"Roach";"Larva";750;2
"Unit";"Roach";"Larva";750;2
"Unit";"Roach";"Larva";750;2
"Unit";"Roach";"Larva";750;2
"Unit";"Roach";"Larva";750;2
"Unit";"Roach";"Larva";750;2
"Unit";"Roach";"Larva";750;2
"Unit";"Roach";"Larva";750;2
"Unit";"Roach";"Larva";750;2
"Unit";"Roach";"Larva";750;2
"Unit";"Roach";"Larva";750;2
"Unit";"Roach";"Larva";754;2
"Unit";"Roach";"Larva";754;2
"Unit";"Roach";"Larva";754;2
"Unit";"Roach";"Larva";754;2
"Unit";"Roach";"Larva";754;2
"Unit";"Roach";"Larva";754;2
"Unit";"Roach";"Larva";754;2
"Unit";"Roach";"Larva";754;2
"Unit";"Roach";"Larva";754;2
"Unit";"Roach";"Larva";754;2
"Unit";"Roach";"Larva";754;2
"Unit";"Roach";"Larva";754;2
"Unit";"Roach";"Larva";754;2
"Unit";"Roach";"Larva";754;2
"Unit";"Roach";"Larva";754;2
"Unit";"Roach";"Larva";754;2
"Unit";"Roach";"Larva";754;2
"Unit";"Roach";"Larva";754;2
"Unit";"Roach";"Larva";754;2
"Unit";"Roach";"Larva";754;2
"Unit";"Roach";"Larva";754;2
"Unit";"Roach";"Larva";870;2
"Unit";"Roach";"Larva";870;2
"Unit";"Roach";"Larva";870;2
"Unit";"Roach";"Larva";870;2
"Unit";"Roach";"Larva";870;2
"Unit";"Roach";"Larva";870;2
"Unit";"Roach";"Larva";870;2
"Unit";"Roach";"Larva";870;2
"Unit";"Roach";"Larva";870;2
"Unit";"Roach";"Larva";870;2
"Unit";"Roach";"Larva";870;2
"Unit";"Roach";"Larva";870;2
"Unit";"Roach";"Larva";870;2
"Unit";"Roach";"Larva";870;2
"Unit";"Roach";"Larva";898;2
"Unit";"Roach";"Larva";898;2
"Unit";"Roach";"Larva";898;2
"Unit";"Roach";"Larva";898;2
"Unit";"Roach";"Larva";898;2
"Unit";"Roach";"Larva";898;2
"Unit";"Roach";"Larva";898;2
"Building";"CreepTumorQueen";NA;912;0
"Building";"CreepTumorQueen";NA;912;0
"Building";"CreepTumor";NA;912;0
"Building";"CreepTumor";NA;912;0
"Building";"CreepTumorQueen";NA;912;0
