"type";"unit_name";"on_building";"total_supply";"supply"
"Unit";"Overlord";"Larva";13;0
"Building";"Extractor";NA;18;0
"Unit";"Overlord";"Larva";21;0
"Building";"SpawningPool";NA;19;0
"Building";"Hatchery";NA;17;0
"Unit";"Zergling";"Larva";22;1
"Unit";"Zergling";"Larva";22;1
"Unit";"Zergling";"Larva";22;1
"Unit";"Zergling";"Larva";22;1
"Unit";"Queen";"Hatchery";22;2
"Unit";"Queen";"Hatchery";22;2
"Building";"CreepTumorQueen";NA;35;0
"Unit";"Overlord";"Larva";37;0
"Building";"CreepTumor";NA;37;0
"Unit";"Queen";"Hatchery";35;2
"Building";"CreepTumorQueen";NA;40;0
"Unit";"Overlord";"Larva";40;0
"Building";"Hatchery";NA;35;0
"Building";"CreepTumor";NA;48;0
"Unit";"Queen";"Hatchery";40;2
"Unit";"Overlord";"Larva";48;0
"Building";"CreepTumor";NA;54;0
"Building";"CreepTumorQueen";NA;56;0
"Unit";"Zergling";"Larva";56;1
"Unit";"Zergling";"Larva";56;1
"Unit";"Zergling";"Larva";56;1
"Unit";"Zergling";"Larva";56;1
"Unit";"Zergling";"Larva";56;1
"Unit";"Zergling";"Larva";56;1
"Building";"Extractor";NA;56;0
"Unit";"Zergling";"Larva";56;1
"Unit";"Zergling";"Larva";56;1
"Unit";"Zergling";"Larva";56;1
"Unit";"Zergling";"Larva";56;1
"Building";"Extractor";NA;56;0
"Unit";"Queen";"Hatchery";48;2
"Building";"EvolutionChamber";NA;56;0
"Building";"EvolutionChamber";NA;56;0
"Unit";"Overlord";"Larva";65;0
"Building";"CreepTumor";NA;75;0
"Building";"SporeCrawler";NA;69;0
"Unit";"Queen";"Hatchery";56;2
"Building";"SporeCrawler";NA;71;0
"Building";"SporeCrawler";NA;71;0
"Building";"CreepTumorQueen";NA;78;0
"Building";"CreepTumor";NA;78;0
"Unit";"Zergling";"Larva";80;1
"Unit";"Zergling";"Larva";80;1
"Unit";"Zergling";"Larva";80;1
"Unit";"Zergling";"Larva";80;1
"Unit";"Overlord";"Larva";80;0
"Unit";"Overlord";"Larva";84;0
"Unit";"Zergling";"Larva";88;1
"Unit";"Zergling";"Larva";88;1
"Unit";"Zergling";"Larva";88;1
"Unit";"Zergling";"Larva";88;1
"Unit";"Zergling";"Larva";88;1
"Unit";"Zergling";"Larva";88;1
"Unit";"Zergling";"Larva";88;1
"Unit";"Zergling";"Larva";88;1
"Unit";"Zergling";"Larva";88;1
"Unit";"Zergling";"Larva";88;1
"Unit";"Zergling";"Larva";88;1
"Unit";"Zergling";"Larva";88;1
"Unit";"Zergling";"Larva";88;1
"Unit";"Zergling";"Larva";88;1
"Building";"CreepTumor";NA;88;0
"Building";"CreepTumor";NA;88;0
"Building";"CreepTumorQueen";NA;88;0
"Building";"CreepTumorQueen";NA;108;0
"Unit";"Queen";"Hatchery";88;2
"Building";"BanelingNest";NA;88;0
"Unit";"Overlord";"Larva";114;0
"Building";"HydraliskDen";NA;111;0
"Building";"Extractor";NA;114;0
"Building";"Extractor";NA;114;0
"Upgrade";"ZergMeleeWeaponsLevel1";"EvolutionChamber";86;0
"Unit";"Overlord";"Larva";120;0
"Upgrade";"ZergGroundArmorsLevel1";"EvolutionChamber";86;0
"Building";"CreepTumorQueen";NA;125;0
"Building";"CreepTumorQueen";NA;125;0
"Unit";"Queen";"Hatchery";125;2
"Building";"CreepTumor";NA;125;0
"Building";"CreepTumor";NA;125;0
"Building";"CreepTumorQueen";NA;125;0
"Building";"CreepTumorQueen";NA;125;0
"Building";"CreepTumor";NA;125;0
"Building";"Extractor";NA;125;0
"Building";"CreepTumor";NA;125;0
"Building";"CreepTumorQueen";NA;129;0
"Building";"Hatchery";NA;111;0
"Unit";"Overlord";"Larva";130;0
"Unit";"Overlord";"Larva";130;0
"Building";"CreepTumor";NA;143;0
"Building";"CreepTumor";NA;143;0
"Building";"CreepTumor";NA;143;0
"Building";"CreepTumor";NA;143;0
"Unit";"Hydralisk";"Larva";143;2
"Unit";"Hydralisk";"Larva";143;2
"Unit";"Hydralisk";"Larva";143;2
"Unit";"Overlord";"Larva";143;0
"Unit";"Hydralisk";"Larva";143;2
"Unit";"Overlord";"Larva";143;0
"Building";"CreepTumor";NA;151;0
"Building";"CreepTumor";NA;151;0
"Building";"CreepTumor";NA;151;0
"Building";"CreepTumor";NA;151;0
"Building";"CreepTumor";NA;151;0
"Upgrade";"EvolveGroovedSpines";"HydraliskDen";130;0
"Building";"CreepTumorQueen";NA;151;0
"Unit";"Queen";"Hatchery";143;2
"Building";"CreepTumor";NA;151;0
"Building";"CreepTumor";NA;151;0
"Building";"CreepTumor";NA;151;0
"Unit";"Hydralisk";"Larva";145;2
"Unit";"Hydralisk";"Larva";145;2
"Building";"CreepTumor";NA;151;0
"Unit";"Hydralisk";"Larva";145;2
"Unit";"Hydralisk";"Larva";151;2
"Building";"CreepTumorQueen";NA;156;0
"Building";"InfestationPit";NA;143;0
"Building";"CreepTumorQueen";NA;156;0
"Unit";"Overlord";"Larva";153;0
"Building";"CreepTumorQueen";NA;158;0
"Unit";"Hydralisk";"Larva";153;2
"Unit";"Hydralisk";"Larva";153;2
"Unit";"Hydralisk";"Larva";153;2
"Unit";"Hydralisk";"Larva";153;2
"Unit";"Zergling";"Larva";158;1
"Unit";"Zergling";"Larva";158;1
"Unit";"Zergling";"Larva";158;1
"Unit";"Zergling";"Larva";158;1
"Unit";"Zergling";"Larva";158;1
"Unit";"Zergling";"Larva";158;1
"Unit";"Zergling";"Larva";158;1
"Unit";"Zergling";"Larva";158;1
"Unit";"Zergling";"Larva";158;1
"Unit";"Zergling";"Larva";158;1
"Unit";"Zergling";"Larva";158;1
"Unit";"Zergling";"Larva";158;1
"Unit";"Zergling";"Larva";158;1
"Unit";"Zergling";"Larva";158;1
"Unit";"Zergling";"Larva";158;1
"Unit";"Zergling";"Larva";158;1
"Unit";"Hydralisk";"Larva";158;2
"Upgrade";"ZergMissileWeaponsLevel1";"EvolutionChamber";132;0
"Building";"Extractor";NA;166;0
"Building";"Extractor";NA;166;0
"Building";"Hatchery";NA;143;0
"Unit";"Hydralisk";"Larva";168;2
"Unit";"Hydralisk";"Larva";168;2
"Unit";"Hydralisk";"Larva";172;2
"Unit";"Hydralisk";"Larva";174;2
"Unit";"Hydralisk";"Larva";174;2
"Unit";"Overlord";"Larva";192;0
"Unit";"Overlord";"Larva";192;0
"Unit";"Overlord";"Larva";192;0
"Unit";"Overlord";"Larva";202;0
"Upgrade";"ZergGroundArmorsLevel2";"EvolutionChamber";143;0
"Unit";"Hydralisk";"Larva";192;2
"Unit";"Hydralisk";"Larva";192;2
"Unit";"Hydralisk";"Larva";192;2
"Building";"CreepTumorQueen";NA;202;0
"Upgrade";"EvolveMuscularAugments";"HydraliskDen";190;0
"Unit";"Zergling";"Larva";208;1
"Unit";"Zergling";"Larva";208;1
"Unit";"Zergling";"Larva";208;1
"Unit";"Zergling";"Larva";208;1
"Unit";"Zergling";"Larva";208;1
"Unit";"Zergling";"Larva";208;1
"Unit";"Zergling";"Larva";208;1
"Unit";"Zergling";"Larva";208;1
"Unit";"Zergling";"Larva";208;1
"Unit";"Zergling";"Larva";208;1
"Unit";"Zergling";"Larva";208;1
"Unit";"Zergling";"Larva";208;1
"Unit";"Zergling";"Larva";208;1
"Unit";"Zergling";"Larva";208;1
"Unit";"Zergling";"Larva";208;1
"Unit";"Zergling";"Larva";208;1
"Unit";"Zergling";"Larva";208;1
"Unit";"Zergling";"Larva";208;1
"Unit";"Zergling";"Larva";208;1
"Unit";"Zergling";"Larva";208;1
"Unit";"Zergling";"Larva";208;1
"Unit";"Zergling";"Larva";208;1
"Unit";"Zergling";"Larva";208;1
"Unit";"Zergling";"Larva";208;1
"Unit";"Overlord";"Larva";208;0
"Building";"SporeCrawler";NA;232;0
"Building";"CreepTumorQueen";NA;233;0
"Unit";"Baneling";"Zergling";237;0
"Unit";"Baneling";"Zergling";237;0
"Unit";"Baneling";"Zergling";237;0
"Unit";"Baneling";"Zergling";237;0
"Unit";"Baneling";"Zergling";237;0
"Unit";"Baneling";"Zergling";237;0
"Unit";"Baneling";"Zergling";237;0
"Unit";"Baneling";"Zergling";237;0
"Unit";"Baneling";"Zergling";237;0
"Unit";"Baneling";"Zergling";237;0
"Unit";"Baneling";"Zergling";237;0
"Unit";"Baneling";"Zergling";237;0
"Unit";"Baneling";"Zergling";237;0
"Unit";"Baneling";"Zergling";237;0
"Unit";"Baneling";"Zergling";237;0
"Unit";"Baneling";"Zergling";237;0
"Unit";"Baneling";"Zergling";237;0
"Unit";"Baneling";"Zergling";237;0
"Unit";"Baneling";"Zergling";237;0
"Unit";"Baneling";"Zergling";237;0
"Unit";"Baneling";"Zergling";237;0
"Unit";"Baneling";"Zergling";237;0
"Unit";"Baneling";"Zergling";237;0
"Unit";"Baneling";"Zergling";237;0
"Unit";"Baneling";"Zergling";237;0
"Unit";"Baneling";"Zergling";237;0
"Unit";"Baneling";"Zergling";237;0
"Unit";"Baneling";"Zergling";237;0
"Unit";"Baneling";"Zergling";237;0
"Unit";"Baneling";"Zergling";237;0
"Unit";"Baneling";"Zergling";237;0
"Unit";"Overlord";"Larva";237;0
"Unit";"Hydralisk";"Larva";237;2
"Unit";"Hydralisk";"Larva";237;2
"Unit";"Hydralisk";"Larva";237;2
"Unit";"Zergling";"Larva";237;1
"Unit";"Zergling";"Larva";237;1
"Unit";"Zergling";"Larva";237;1
"Unit";"Zergling";"Larva";237;1
"Unit";"Zergling";"Larva";237;1
"Unit";"Zergling";"Larva";237;1
"Unit";"Queen";"Hatchery";233;2
"Building";"CreepTumorQueen";NA;237;0
"Building";"CreepTumorQueen";NA;239;0
"Unit";"Overlord";"Larva";237;0
"Building";"CreepTumor";NA;251;0
"Building";"CreepTumor";NA;251;0
"Building";"CreepTumor";NA;251;0
"Building";"CreepTumor";NA;251;0
"Building";"CreepTumor";NA;251;0
"Building";"CreepTumor";NA;251;0
"Building";"CreepTumor";NA;251;0
"Building";"CreepTumorQueen";NA;251;0
"Unit";"Overlord";"Larva";251;0
"Unit";"Zergling";"Larva";251;1
"Unit";"Zergling";"Larva";251;1
"Building";"CreepTumorQueen";NA;251;0
"Unit";"Zergling";"Larva";251;1
"Unit";"Zergling";"Larva";251;1
"Unit";"Zergling";"Larva";251;1
"Unit";"Zergling";"Larva";251;1
"Unit";"Zergling";"Larva";251;1
"Unit";"Zergling";"Larva";251;1
"Unit";"Zergling";"Larva";251;1
"Unit";"Zergling";"Larva";251;1
"Unit";"Zergling";"Larva";251;1
"Unit";"Zergling";"Larva";251;1
"Unit";"Zergling";"Larva";251;1
"Unit";"Zergling";"Larva";251;1
"Unit";"Zergling";"Larva";251;1
"Unit";"Zergling";"Larva";251;1
"Unit";"Zergling";"Larva";251;1
"Unit";"Zergling";"Larva";251;1
"Unit";"Zergling";"Larva";251;1
"Unit";"Zergling";"Larva";251;1
"Unit";"Zergling";"Larva";251;1
"Unit";"Zergling";"Larva";251;1
"Unit";"Zergling";"Larva";251;1
"Unit";"Zergling";"Larva";251;1
"Unit";"Zergling";"Larva";251;1
"Unit";"Zergling";"Larva";251;1
"Unit";"Zergling";"Larva";251;1
"Unit";"Zergling";"Larva";251;1
"Unit";"Zergling";"Larva";251;1
"Unit";"Zergling";"Larva";251;1
"Unit";"Zergling";"Larva";251;1
"Unit";"Zergling";"Larva";251;1
"Building";"CreepTumor";NA;269;0
"Building";"CreepTumor";NA;269;0
"Building";"CreepTumor";NA;269;0
"Building";"CreepTumor";NA;269;0
"Unit";"Zergling";"Larva";267;1
"Unit";"Zergling";"Larva";267;1
"Unit";"Zergling";"Larva";269;1
"Unit";"Zergling";"Larva";269;1
"Unit";"Zergling";"Larva";269;1
"Unit";"Zergling";"Larva";269;1
"Unit";"Zergling";"Larva";271;1
"Unit";"Zergling";"Larva";271;1
"Unit";"Zergling";"Larva";271;1
"Unit";"Zergling";"Larva";271;1
"Unit";"Zergling";"Larva";271;1
"Unit";"Zergling";"Larva";271;1
"Unit";"Zergling";"Larva";271;1
"Unit";"Zergling";"Larva";271;1
"Unit";"Zergling";"Larva";271;1
"Unit";"Zergling";"Larva";271;1
"Unit";"Zergling";"Larva";271;1
"Unit";"Zergling";"Larva";271;1
"Unit";"Zergling";"Larva";271;1
"Unit";"Zergling";"Larva";271;1
"Unit";"Zergling";"Larva";271;1
"Unit";"Zergling";"Larva";271;1
"Unit";"Zergling";"Larva";271;1
"Unit";"Zergling";"Larva";271;1
"Unit";"Zergling";"Larva";283;1
"Unit";"Zergling";"Larva";283;1
"Unit";"Baneling";"Zergling";289;0
"Unit";"Baneling";"Zergling";289;0
"Unit";"Baneling";"Zergling";289;0
"Unit";"Baneling";"Zergling";289;0
"Unit";"Baneling";"Zergling";289;0
"Unit";"Baneling";"Zergling";289;0
"Unit";"Baneling";"Zergling";289;0
"Unit";"Baneling";"Zergling";289;0
"Unit";"Overlord";"Larva";289;0
"Unit";"Baneling";"Zergling";289;0
"Unit";"Baneling";"Zergling";289;0
"Unit";"Baneling";"Zergling";289;0
"Unit";"Baneling";"Zergling";289;0
"Unit";"Hydralisk";"Larva";283;2
"Building";"Hatchery";NA;237;0
"Unit";"Overlord";"Larva";307;0
"Building";"Hatchery";NA;251;0
"Building";"CreepTumor";NA;312;0
"Building";"CreepTumor";NA;312;0
"Building";"CreepTumor";NA;312;0
"Building";"CreepTumor";NA;312;0
"Building";"CreepTumor";NA;312;0
"Unit";"Viper";"Larva";312;3
"Unit";"Viper";"Larva";312;3
"Building";"CreepTumorQueen";NA;314;0
"Unit";"Overlord";"Larva";312;0
"Building";"CreepTumorQueen";NA;314;0
"Building";"CreepTumorQueen";NA;314;0
"Building";"CreepTumorQueen";NA;314;0
"Building";"CreepTumorQueen";NA;320;0
"Building";"CreepTumorQueen";NA;320;0
"Building";"CreepTumorQueen";NA;320;0
"Building";"CreepTumorQueen";NA;322;0
"Building";"CreepTumorQueen";NA;322;0
"Building";"CreepTumorQueen";NA;322;0
"Building";"CreepTumorQueen";NA;322;0
"Building";"CreepTumorQueen";NA;322;0
"Building";"CreepTumorQueen";NA;322;0
"Building";"CreepTumorQueen";NA;322;0
"Building";"Extractor";NA;320;0
"Building";"Extractor";NA;320;0
"Building";"CreepTumorQueen";NA;322;0
"Upgrade";"ZergMissileWeaponsLevel2";"EvolutionChamber";255;0
"Building";"CreepTumorQueen";NA;322;0
"Upgrade";"ZergMeleeWeaponsLevel2";"EvolutionChamber";269;0
"Building";"CreepTumorQueen";NA;324;0
"Building";"SpineCrawler";NA;322;0
"Building";"SpineCrawler";NA;322;0
"Building";"SpineCrawler";NA;322;0
"Building";"SpineCrawler";NA;322;0
"Building";"Spire";NA;312;0
"Unit";"Queen";"Hatchery";322;2
"Building";"SpineCrawler";NA;322;0
"Building";"Spire";NA;312;0
"Building";"SpineCrawler";NA;322;0
"Building";"SpineCrawler";NA;322;0
"Building";"SpineCrawler";NA;322;0
"Unit";"Viper";"Larva";326;3
"Building";"CreepTumorQueen";NA;328;0
"Building";"CreepTumorQueen";NA;328;0
"Building";"CreepTumorQueen";NA;328;0
"Building";"CreepTumorQueen";NA;328;0
"Building";"CreepTumorQueen";NA;328;0
"Building";"CreepTumorQueen";NA;328;0
"Unit";"Hydralisk";"Larva";328;2
"Unit";"Hydralisk";"Larva";328;2
"Unit";"Hydralisk";"Larva";328;2
"Unit";"Hydralisk";"Larva";328;2
"Unit";"Hydralisk";"Larva";328;2
"Unit";"Hydralisk";"Larva";328;2
"Unit";"Hydralisk";"Larva";328;2
"Building";"CreepTumorQueen";NA;328;0
"Building";"CreepTumor";NA;328;0
"Building";"CreepTumorQueen";NA;331;0
"Building";"CreepTumorQueen";NA;331;0
"Building";"CreepTumorQueen";NA;345;0
"Unit";"Queen";"Hatchery";345;2
"Building";"CreepTumor";NA;346;0
"Building";"CreepTumor";NA;346;0
"Building";"CreepTumor";NA;346;0
"Building";"CreepTumor";NA;346;0
"Building";"CreepTumor";NA;346;0
"Building";"CreepTumor";NA;346;0
"Building";"CreepTumor";NA;346;0
"Building";"CreepTumor";NA;346;0
"Building";"CreepTumor";NA;346;0
"Building";"CreepTumor";NA;346;0
"Unit";"Corruptor";"Larva";345;2
"Unit";"Corruptor";"Larva";345;2
"Unit";"Corruptor";"Larva";345;2
"Unit";"Corruptor";"Larva";345;2
"Unit";"Corruptor";"Larva";345;2
"Unit";"Corruptor";"Larva";345;2
"Building";"CreepTumor";NA;360;0
"Building";"CreepTumor";NA;360;0
"Building";"CreepTumor";NA;360;0
"Building";"CreepTumor";NA;360;0
"Building";"CreepTumor";NA;360;0
"Building";"CreepTumor";NA;360;0
"Building";"CreepTumor";NA;360;0
"Building";"CreepTumor";NA;360;0
"Unit";"Corruptor";"Larva";346;2
"Unit";"Corruptor";"Larva";346;2
"Building";"CreepTumor";NA;364;0
"Building";"CreepTumor";NA;364;0
"Building";"CreepTumor";NA;364;0
"Building";"CreepTumor";NA;364;0
"Building";"CreepTumor";NA;364;0
"Unit";"Corruptor";"Larva";364;2
"Unit";"Corruptor";"Larva";364;2
"Upgrade";"ZergGroundArmorsLevel3";"EvolutionChamber";345;0
"Upgrade";"ZergMissileWeaponsLevel3";"EvolutionChamber";345;0
"Building";"SporeCrawler";NA;364;0
"Building";"SporeCrawler";NA;364;0
"Building";"SporeCrawler";NA;364;0
"Building";"SporeCrawler";NA;364;0
"Building";"SporeCrawler";NA;364;0
"Building";"SporeCrawler";NA;364;0
"Building";"SporeCrawler";NA;368;0
"Unit";"Corruptor";"Larva";364;2
"Unit";"Corruptor";"Larva";364;2
"Unit";"Corruptor";"Larva";364;2
"Unit";"Zergling";"Larva";374;1
"Unit";"Zergling";"Larva";374;1
"Building";"CreepTumor";NA;374;0
"Building";"CreepTumorQueen";NA;374;0
"Unit";"Corruptor";"Larva";374;2
"Building";"CreepTumorQueen";NA;378;0
"Unit";"Corruptor";"Larva";374;2
"Unit";"Corruptor";"Larva";374;2
"Building";"CreepTumorQueen";NA;378;0
"Building";"CreepTumorQueen";NA;378;0
"Unit";"Corruptor";"Larva";378;2
"Unit";"Hydralisk";"Larva";382;2
"Unit";"Hydralisk";"Larva";382;2
"Unit";"Hydralisk";"Larva";382;2
"Unit";"Hydralisk";"Larva";382;2
