"type";"unit_name";"on_building";"total_supply";"supply"
"Unit";"Overlord";"Larva";13;0
"Building";"Extractor";NA;18;0
"Unit";"Overlord";"Larva";21;0
"Building";"Hatchery";NA;18;0
"Building";"SpawningPool";NA;20;0
"Unit";"Zergling";"Larva";23;1
"Unit";"Zergling";"Larva";23;1
"Unit";"Zergling";"Larva";23;1
"Unit";"Zergling";"Larva";23;1
"Unit";"Queen";"Hatchery";23;2
"Unit";"Queen";"Hatchery";23;2
"Building";"CreepTumorQueen";NA;34;0
"Unit";"Overlord";"Larva";36;0
"Building";"CreepTumor";NA;39;0
"Unit";"Overlord";"Larva";41;0
"Building";"CreepTumor";NA;43;0
"Building";"Hatchery";NA;30;0
"Unit";"Queen";"Hatchery";41;2
"Unit";"Overlord";"Larva";45;0
"Unit";"Overlord";"Larva";47;0
"Unit";"Zergling";"Larva";47;1
"Unit";"Zergling";"Larva";47;1
"Unit";"Zergling";"Larva";47;1
"Unit";"Zergling";"Larva";47;1
"Unit";"Zergling";"Larva";47;1
"Unit";"Zergling";"Larva";47;1
"Unit";"Zergling";"Larva";47;1
"Unit";"Zergling";"Larva";47;1
"Building";"Extractor";NA;49;0
"Building";"RoachWarren";NA;49;0
"Building";"CreepTumorQueen";NA;63;0
"Unit";"Queen";"Hatchery";49;2
"Unit";"Queen";"Hatchery";53;2
"Unit";"Overlord";"Larva";69;0
"Unit";"Overlord";"Larva";69;0
"Building";"CreepTumorQueen";NA;73;0
"Unit";"Roach";"Larva";69;2
"Unit";"Roach";"Larva";69;2
"Unit";"Overlord";"Larva";73;0
"Unit";"Overlord";"Larva";74;0
"Building";"CreepTumorQueen";NA;86;0
"Unit";"Roach";"Larva";86;2
"Unit";"Roach";"Larva";86;2
"Unit";"Roach";"Larva";86;2
"Unit";"Roach";"Larva";86;2
"Unit";"Roach";"Larva";86;2
"Building";"CreepTumor";NA;86;0
"Unit";"Overlord";"Larva";86;0
"Unit";"Roach";"Larva";97;2
"Unit";"Roach";"Larva";97;2
"Unit";"Roach";"Larva";97;2
"Unit";"Roach";"Larva";97;2
"Unit";"Overlord";"Larva";99;0
"Building";"EvolutionChamber";NA;105;0
"Building";"EvolutionChamber";NA;105;0
"Unit";"Roach";"Larva";117;2
"Unit";"Roach";"Larva";117;2
"Unit";"Roach";"Larva";117;2
"Unit";"Roach";"Larva";117;2
"Building";"Extractor";NA;117;0
"Building";"CreepTumorQueen";NA;117;0
"Building";"CreepTumorQueen";NA;125;0
"Building";"Extractor";NA;126;0
"Building";"Extractor";NA;130;0
"Building";"Extractor";NA;130;0
"Building";"CreepTumorQueen";NA;130;0
"Building";"CreepTumorQueen";NA;130;0
"Unit";"Overlord";"Larva";130;0
"Building";"CreepTumor";NA;133;0
"Building";"CreepTumor";NA;133;0
"Building";"CreepTumor";NA;133;0
"Unit";"Overlord";"Larva";133;0
"Building";"CreepTumorQueen";NA;133;0
"Unit";"Overlord";"Larva";133;0
"Unit";"Overlord";"Larva";133;0
"Unit";"Overlord";"Larva";133;0
"Building";"CreepTumorQueen";NA;133;0
"Upgrade";"GlialReconstitution";"RoachWarren";133;0
"Unit";"Roach";"Larva";135;2
"Unit";"Roach";"Larva";135;2
"Unit";"Roach";"Larva";135;2
"Unit";"Roach";"Larva";135;2
"Unit";"Roach";"Larva";135;2
"Unit";"Roach";"Larva";135;2
"Unit";"Roach";"Larva";135;2
"Unit";"Roach";"Larva";135;2
"Unit";"Roach";"Larva";135;2
"Unit";"Roach";"Larva";135;2
"Unit";"Roach";"Larva";135;2
"Unit";"Roach";"Larva";135;2
"Unit";"Roach";"Larva";135;2
"Building";"CreepTumor";NA;138;0
"Building";"CreepTumor";NA;138;0
"Building";"CreepTumor";NA;138;0
"Building";"InfestationPit";NA;135;0
"Building";"CreepTumor";NA;164;0
"Building";"CreepTumor";NA;164;0
"Building";"CreepTumor";NA;164;0
"Building";"CreepTumorQueen";NA;164;0
"Building";"CreepTumor";NA;164;0
"Unit";"Roach";"Larva";164;2
"Unit";"Roach";"Larva";164;2
"Unit";"Roach";"Larva";164;2
"Unit";"Roach";"Larva";164;2
"Unit";"Roach";"Larva";164;2
"Unit";"Roach";"Larva";164;2
"Unit";"Roach";"Larva";164;2
"Unit";"Roach";"Larva";164;2
"Unit";"Roach";"Larva";164;2
"Unit";"Roach";"Larva";164;2
"Unit";"Roach";"Larva";164;2
"Unit";"Roach";"Larva";164;2
"Building";"CreepTumor";NA;167;0
"Building";"CreepTumor";NA;167;0
"Building";"CreepTumorQueen";NA;167;0
"Unit";"Overlord";"Larva";167;0
"Unit";"Overlord";"Larva";167;0
"Upgrade";"ZergMissileWeaponsLevel1";"EvolutionChamber";133;0
"Building";"CreepTumorQueen";NA;167;0
"Upgrade";"ZergGroundArmorsLevel1";"EvolutionChamber";133;0
"Building";"CreepTumorQueen";NA;167;0
"Building";"CreepTumor";NA;191;0
"Building";"CreepTumor";NA;191;0
"Building";"Hatchery";NA;138;0
"Unit";"Overlord";"Larva";191;0
"Unit";"Overlord";"Larva";191;0
"Unit";"Overlord";"Larva";191;0
"Building";"Hatchery";NA;164;0
"Building";"CreepTumor";NA;191;0
"Building";"CreepTumor";NA;191;0
"Building";"Hatchery";NA;167;0
"Building";"CreepTumor";NA;191;0
"Building";"CreepTumor";NA;191;0
"Building";"CreepTumor";NA;191;0
"Building";"CreepTumor";NA;191;0
"Building";"CreepTumor";NA;192;0
"Unit";"Overlord";"Larva";191;0
"Unit";"Overlord";"Larva";191;0
"Unit";"Overlord";"Larva";191;0
"Unit";"Overlord";"Larva";191;0
"Unit";"Overlord";"Larva";200;0
"Building";"Extractor";NA;200;0
"Building";"Extractor";NA;200;0
"Building";"CreepTumor";NA;200;0
"Unit";"Roach";"Larva";200;2
"Unit";"Roach";"Larva";200;2
"Unit";"Roach";"Larva";200;2
"Unit";"Roach";"Larva";200;2
"Unit";"Roach";"Larva";200;2
"Unit";"Roach";"Larva";200;2
"Unit";"Roach";"Larva";200;2
"Unit";"Roach";"Larva";200;2
"Unit";"Roach";"Larva";200;2
"Unit";"Roach";"Larva";200;2
"Unit";"Roach";"Larva";200;2
"Unit";"Roach";"Larva";200;2
"Unit";"Roach";"Larva";200;2
"Unit";"Roach";"Larva";200;2
"Building";"CreepTumor";NA;200;0
"Unit";"Roach";"Larva";200;2
"Unit";"Roach";"Larva";200;2
"Building";"CreepTumor";NA;200;0
"Unit";"Roach";"Larva";200;2
"Unit";"Roach";"Larva";200;2
"Unit";"Roach";"Larva";236;2
"Unit";"Roach";"Larva";236;2
"Unit";"Roach";"Larva";236;2
"Unit";"Roach";"Larva";236;2
"Unit";"Roach";"Larva";236;2
"Unit";"Roach";"Larva";236;2
"Unit";"Roach";"Larva";236;2
"Unit";"Roach";"Larva";236;2
"Unit";"Roach";"Larva";236;2
"Unit";"Roach";"Larva";236;2
"Unit";"Roach";"Larva";236;2
"Unit";"Roach";"Larva";236;2
"Unit";"Roach";"Larva";236;2
"Unit";"Roach";"Larva";236;2
"Unit";"Roach";"Larva";236;2
"Unit";"Roach";"Larva";266;2
"Unit";"Roach";"Larva";266;2
"Unit";"Roach";"Larva";266;2
"Unit";"Roach";"Larva";266;2
"Unit";"Overlord";"Larva";266;0
"Unit";"Overlord";"Larva";266;0
"Unit";"Overlord";"Larva";274;0
"Building";"Hatchery";NA;266;0
"Upgrade";"ZergMissileWeaponsLevel2";"EvolutionChamber";236;0
"Upgrade";"ZergGroundArmorsLevel2";"EvolutionChamber";236;0
"Building";"CreepTumor";NA;274;0
"Unit";"Roach";"Larva";274;2
"Unit";"Roach";"Larva";274;2
"Unit";"Roach";"Larva";274;2
"Unit";"Roach";"Larva";274;2
"Unit";"Roach";"Larva";274;2
"Unit";"Roach";"Larva";274;2
"Unit";"Roach";"Larva";274;2
"Unit";"Roach";"Larva";274;2
"Unit";"Roach";"Larva";274;2
"Unit";"Roach";"Larva";274;2
"Unit";"Roach";"Larva";274;2
"Unit";"Roach";"Larva";274;2
"Unit";"Roach";"Larva";274;2
"Unit";"Roach";"Larva";274;2
"Unit";"Roach";"Larva";274;2
"Unit";"Roach";"Larva";274;2
"Unit";"Roach";"Larva";274;2
"Unit";"Roach";"Larva";274;2
"Unit";"Roach";"Larva";274;2
"Unit";"Roach";"Larva";274;2
"Unit";"Roach";"Larva";274;2
"Unit";"Roach";"Larva";274;2
"Unit";"Roach";"Larva";274;2
"Unit";"Roach";"Larva";274;2
"Unit";"Roach";"Larva";274;2
"Unit";"Roach";"Larva";274;2
"Unit";"Roach";"Larva";274;2
"Unit";"Roach";"Larva";274;2
"Unit";"Roach";"Larva";274;2
"Unit";"Roach";"Larva";274;2
"Building";"CreepTumorQueen";NA;274;0
"Building";"CreepTumorQueen";NA;274;0
"Building";"CreepTumorQueen";NA;274;0
"Building";"HydraliskDen";NA;274;0
"Building";"CreepTumorQueen";NA;334;0
"Building";"CreepTumor";NA;334;0
"Building";"CreepTumorQueen";NA;334;0
"Building";"CreepTumorQueen";NA;334;0
"Building";"CreepTumorQueen";NA;334;0
"Building";"CreepTumor";NA;334;0
"Building";"CreepTumor";NA;334;0
"Unit";"Hydralisk";"Larva";334;2
"Unit";"Hydralisk";"Larva";334;2
"Unit";"Hydralisk";"Larva";334;2
"Unit";"Hydralisk";"Larva";334;2
"Unit";"Hydralisk";"Larva";334;2
"Unit";"Hydralisk";"Larva";334;2
"Building";"CreepTumorQueen";NA;346;0
"Building";"CreepTumorQueen";NA;346;0
"Building";"CreepTumor";NA;346;0
"Building";"CreepTumorQueen";NA;346;0
"Building";"CreepTumor";NA;346;0
"Building";"CreepTumor";NA;346;0
"Building";"CreepTumor";NA;346;0
"Building";"CreepTumor";NA;346;0
"Unit";"Hydralisk";"Larva";346;2
"Unit";"Hydralisk";"Larva";346;2
"Unit";"Hydralisk";"Larva";346;2
"Unit";"Hydralisk";"Larva";346;2
"Unit";"Hydralisk";"Larva";346;2
"Unit";"Hydralisk";"Larva";346;2
"Unit";"Hydralisk";"Larva";346;2
"Unit";"Hydralisk";"Larva";346;2
"Unit";"Hydralisk";"Larva";346;2
"Unit";"Hydralisk";"Larva";346;2
"Unit";"Hydralisk";"Larva";346;2
"Unit";"Hydralisk";"Larva";346;2
"Unit";"Hydralisk";"Larva";346;2
"Unit";"Hydralisk";"Larva";346;2
"Unit";"Hydralisk";"Larva";346;2
"Unit";"Hydralisk";"Larva";346;2
"Unit";"Hydralisk";"Larva";346;2
"Unit";"Hydralisk";"Larva";346;2
"Unit";"Hydralisk";"Larva";346;2
"Unit";"Hydralisk";"Larva";346;2
"Unit";"Hydralisk";"Larva";346;2
"Upgrade";"EvolveMuscularAugments";"HydraliskDen";334;0
"Building";"CreepTumor";NA;346;0
"Building";"CreepTumor";NA;346;0
"Building";"CreepTumor";NA;346;0
"Building";"CreepTumor";NA;346;0
"Building";"CreepTumor";NA;388;0
"Building";"CreepTumor";NA;388;0
"Building";"CreepTumor";NA;388;0
"Building";"CreepTumor";NA;388;0
"Building";"CreepTumor";NA;388;0
"Building";"CreepTumor";NA;388;0
"Building";"Extractor";NA;388;0
"Building";"CreepTumor";NA;395;0
"Building";"Extractor";NA;395;0
"Upgrade";"ZergMissileWeaponsLevel3";"EvolutionChamber";334;0
"Upgrade";"ZergGroundArmorsLevel3";"EvolutionChamber";334;0
"Unit";"Hydralisk";"Larva";395;2
"Unit";"Hydralisk";"Larva";395;2
"Unit";"Hydralisk";"Larva";395;2
"Unit";"Hydralisk";"Larva";395;2
"Unit";"Hydralisk";"Larva";395;2
"Unit";"Hydralisk";"Larva";395;2
"Unit";"Hydralisk";"Larva";395;2
"Unit";"Hydralisk";"Larva";395;2
"Building";"CreepTumor";NA;395;0
"Building";"CreepTumor";NA;395;0
"Upgrade";"EvolveGroovedSpines";"HydraliskDen";395;0
"Building";"CreepTumor";NA;395;0
"Building";"CreepTumor";NA;395;0
"Building";"CreepTumor";NA;395;0
"Building";"CreepTumorQueen";NA;395;0
"Building";"CreepTumorQueen";NA;395;0
"Building";"CreepTumorQueen";NA;395;0
"Building";"CreepTumorQueen";NA;395;0
"Building";"CreepTumorQueen";NA;411;0
"Building";"Spire";NA;395;0
"Building";"Spire";NA;395;0
"Building";"SporeCrawler";NA;411;0
"Building";"Extractor";NA;411;0
"Building";"Extractor";NA;411;0
"Building";"SporeCrawler";NA;411;0
"Building";"SpineCrawler";NA;411;0
"Building";"SpineCrawler";NA;411;0
"Building";"SpineCrawler";NA;411;0
"Building";"SpineCrawler";NA;411;0
"Building";"SpineCrawler";NA;411;0
"Building";"SpineCrawler";NA;411;0
"Unit";"Hydralisk";"Larva";411;2
"Unit";"Hydralisk";"Larva";411;2
"Unit";"Hydralisk";"Larva";411;2
"Unit";"Hydralisk";"Larva";411;2
"Unit";"Hydralisk";"Larva";411;2
"Unit";"Hydralisk";"Larva";411;2
"Unit";"Hydralisk";"Larva";411;2
"Unit";"Hydralisk";"Larva";411;2
"Building";"CreepTumorQueen";NA;427;0
"Building";"CreepTumorQueen";NA;427;0
"Unit";"Hydralisk";"Larva";427;2
"Unit";"Hydralisk";"Larva";427;2
"Unit";"Hydralisk";"Larva";427;2
"Unit";"Hydralisk";"Larva";427;2
"Unit";"Hydralisk";"Larva";427;2
"Unit";"Hydralisk";"Larva";427;2
"Unit";"Hydralisk";"Larva";427;2
"Unit";"Hydralisk";"Larva";427;2
"Unit";"Hydralisk";"Larva";427;2
"Unit";"Hydralisk";"Larva";427;2
"Unit";"Hydralisk";"Larva";427;2
"Unit";"Hydralisk";"Larva";427;2
"Unit";"Hydralisk";"Larva";427;2
"Unit";"Hydralisk";"Larva";427;2
"Unit";"Hydralisk";"Larva";427;2
"Unit";"Hydralisk";"Larva";427;2
"Unit";"Hydralisk";"Larva";427;2
"Unit";"Hydralisk";"Larva";427;2
"Unit";"Hydralisk";"Larva";427;2
"Unit";"Hydralisk";"Larva";427;2
"Unit";"Hydralisk";"Larva";427;2
"Unit";"Hydralisk";"Larva";427;2
"Unit";"Hydralisk";"Larva";427;2
"Unit";"Hydralisk";"Larva";427;2
"Unit";"Hydralisk";"Larva";427;2
"Unit";"Hydralisk";"Larva";427;2
"Unit";"Hydralisk";"Larva";427;2
"Unit";"Hydralisk";"Larva";427;2
"Unit";"Hydralisk";"Larva";427;2
"Unit";"Hydralisk";"Larva";427;2
"Unit";"Hydralisk";"Larva";427;2
"Unit";"Hydralisk";"Larva";427;2
"Unit";"Hydralisk";"Larva";427;2
"Unit";"Hydralisk";"Larva";427;2
"Unit";"Hydralisk";"Larva";427;2
"Building";"CreepTumor";NA;455;0
"Building";"CreepTumor";NA;455;0
"Building";"CreepTumor";NA;455;0
"Building";"CreepTumor";NA;455;0
"Building";"CreepTumorQueen";NA;497;0
