"type";"unit_name";"on_building";"total_supply";"supply"
"Unit";"Overlord";"Larva";13;0
"Building";"Extractor";NA;18;0
"Building";"SpawningPool";NA;19;0
"Building";"Hatchery";NA;17;0
"Unit";"Overlord";"Larva";23;0
"Unit";"Zergling";"Larva";23;1
"Unit";"Zergling";"Larva";23;1
"Unit";"Zergling";"Larva";23;1
"Unit";"Zergling";"Larva";23;1
"Unit";"Queen";"Hatchery";23;2
"Unit";"Queen";"Hatchery";27;2
"Unit";"Overlord";"Larva";33;0
"Building";"Hatchery";NA;23;0
"Unit";"Zergling";"Larva";42;1
"Unit";"Zergling";"Larva";42;1
"Unit";"Zergling";"Larva";42;1
"Unit";"Zergling";"Larva";42;1
"Unit";"Zergling";"Larva";42;1
"Unit";"Zergling";"Larva";42;1
"Unit";"Zergling";"Larva";42;1
"Unit";"Zergling";"Larva";42;1
"Unit";"Zergling";"Larva";42;1
"Unit";"Zergling";"Larva";42;1
"Unit";"Zergling";"Larva";42;1
"Unit";"Zergling";"Larva";42;1
"Unit";"Zergling";"Larva";42;1
"Unit";"Zergling";"Larva";42;1
"Unit";"Queen";"Hatchery";38;2
"Building";"CreepTumorQueen";NA;46;0
"Unit";"Queen";"Hatchery";42;2
"Unit";"Overlord";"Larva";46;0
"Unit";"Overlord";"Larva";46;0
"Unit";"Zergling";"Larva";58;1
"Unit";"Zergling";"Larva";58;1
"Unit";"Zergling";"Larva";58;1
"Unit";"Zergling";"Larva";58;1
"Unit";"Zergling";"Larva";58;1
"Unit";"Zergling";"Larva";58;1
"Building";"CreepTumorQueen";NA;66;0
"Unit";"Overlord";"Larva";60;0
"Unit";"Overlord";"Larva";66;0
"Unit";"Queen";"Hatchery";60;2
"Building";"SporeCrawler";NA;72;0
"Building";"SporeCrawler";NA;72;0
"Building";"SporeCrawler";NA;73;0
"Building";"CreepTumor";NA;75;0
"Building";"BanelingNest";NA;66;0
"Unit";"Overlord";"Larva";79;0
"Unit";"Queen";"Hatchery";73;2
"Unit";"Queen";"Hatchery";79;2
"Building";"CreepTumor";NA;87;0
"Building";"Extractor";NA;82;0
"Building";"Extractor";NA;83;0
"Unit";"Baneling";"Zergling";87;0
"Unit";"Baneling";"Zergling";87;0
"Unit";"Baneling";"Zergling";87;0
"Unit";"Baneling";"Zergling";87;0
"Unit";"Baneling";"Zergling";87;0
"Building";"CreepTumorQueen";NA;97;0
"Unit";"Overlord";"Larva";97;0
"Building";"CreepTumorQueen";NA;102;0
"Building";"CreepTumorQueen";NA;103;0
"Building";"CreepTumorQueen";NA;103;0
"Unit";"Overlord";"Larva";99;0
"Building";"EvolutionChamber";NA;103;0
"Building";"EvolutionChamber";NA;103;0
"Building";"Extractor";NA;110;0
"Building";"CreepTumor";NA;111;0
"Building";"Extractor";NA;110;0
"Building";"CreepTumorQueen";NA;111;0
"Building";"CreepTumor";NA;111;0
"Building";"CreepTumorQueen";NA;111;0
"Building";"CreepTumor";NA;117;0
"Building";"CreepTumor";NA;117;0
"Building";"Extractor";NA;111;0
"Building";"CreepTumor";NA;120;0
"Building";"CreepTumor";NA;120;0
"Building";"CreepTumor";NA;120;0
"Unit";"Overlord";"Larva";123;0
"Unit";"Overlord";"Larva";123;0
"Unit";"Overlord";"Larva";123;0
"Unit";"Overlord";"Larva";123;0
"Unit";"Overlord";"Larva";123;0
"Unit";"Overlord";"Larva";123;0
"Unit";"Overlord";"Larva";123;0
"Building";"SporeCrawler";NA;123;0
"Unit";"Baneling";"Zergling";126;0
"Unit";"Baneling";"Zergling";126;0
"Unit";"Baneling";"Zergling";126;0
"Unit";"Baneling";"Zergling";126;0
"Building";"HydraliskDen";NA;123;0
"Building";"CreepTumor";NA;126;0
"Building";"CreepTumor";NA;126;0
"Building";"Hatchery";NA;117;0
"Unit";"Queen";"Hatchery";123;2
"Unit";"Overlord";"Larva";126;0
"Building";"CreepTumor";NA;126;0
"Building";"CreepTumor";NA;126;0
"Building";"CreepTumor";NA;126;0
"Building";"InfestationPit";NA;126;0
"Unit";"Queen";"Hatchery";126;2
"Unit";"Hydralisk";"Larva";126;2
"Unit";"Hydralisk";"Larva";126;2
"Unit";"Hydralisk";"Larva";126;2
"Unit";"Hydralisk";"Larva";126;2
"Unit";"Hydralisk";"Larva";126;2
"Unit";"Hydralisk";"Larva";126;2
"Unit";"Hydralisk";"Larva";126;2
"Unit";"Hydralisk";"Larva";126;2
"Unit";"Hydralisk";"Larva";126;2
"Unit";"Hydralisk";"Larva";126;2
"Building";"Extractor";NA;128;0
"Building";"Extractor";NA;128;0
"Building";"CreepTumor";NA;130;0
"Building";"CreepTumor";NA;130;0
"Building";"CreepTumor";NA;130;0
"Upgrade";"ZergMissileWeaponsLevel1";"EvolutionChamber";123;0
"Upgrade";"ZergGroundArmorsLevel1";"EvolutionChamber";123;0
"Building";"CreepTumorQueen";NA;164;0
"Building";"CreepTumorQueen";NA;164;0
"Building";"CreepTumorQueen";NA;164;0
"Unit";"Hydralisk";"Larva";164;2
"Unit";"Hydralisk";"Larva";164;2
"Unit";"Hydralisk";"Larva";164;2
"Unit";"Hydralisk";"Larva";164;2
"Unit";"Hydralisk";"Larva";164;2
"Unit";"Hydralisk";"Larva";164;2
"Unit";"Hydralisk";"Larva";164;2
"Unit";"Hydralisk";"Larva";164;2
"Unit";"Hydralisk";"Larva";164;2
"Unit";"Hydralisk";"Larva";164;2
"Unit";"Hydralisk";"Larva";164;2
"Unit";"Hydralisk";"Larva";164;2
"Upgrade";"EvolveGroovedSpines";"HydraliskDen";130;0
"Building";"CreepTumor";NA;164;0
"Building";"CreepTumor";NA;164;0
"Building";"CreepTumor";NA;164;0
"Building";"CreepTumor";NA;164;0
"Building";"CreepTumor";NA;164;0
"Building";"CreepTumor";NA;164;0
"Building";"Extractor";NA;164;0
"Building";"Extractor";NA;164;0
"Unit";"Queen";"Hatchery";188;2
"Unit";"Queen";"Hatchery";188;2
"Unit";"Queen";"Hatchery";188;2
"Building";"CreepTumorQueen";NA;200;0
"Building";"CreepTumorQueen";NA;200;0
"Unit";"Hydralisk";"Larva";194;2
"Unit";"Hydralisk";"Larva";194;2
"Unit";"Hydralisk";"Larva";194;2
"Unit";"Hydralisk";"Larva";194;2
"Unit";"Hydralisk";"Larva";194;2
"Unit";"Hydralisk";"Larva";194;2
"Unit";"Hydralisk";"Larva";194;2
"Unit";"Hydralisk";"Larva";194;2
"Unit";"Hydralisk";"Larva";194;2
"Unit";"Hydralisk";"Larva";194;2
"Unit";"Hydralisk";"Larva";194;2
"Building";"CreepTumor";NA;200;0
"Building";"CreepTumor";NA;200;0
"Building";"CreepTumor";NA;200;0
"Unit";"Hydralisk";"Larva";194;2
"Unit";"Hydralisk";"Larva";194;2
"Unit";"Hydralisk";"Larva";194;2
"Building";"Hatchery";NA;164;0
"Unit";"Overlord";"Larva";200;0
"Unit";"Overlord";"Larva";200;0
"Unit";"Overlord";"Larva";200;0
"Building";"CreepTumorQueen";NA;222;0
"Building";"CreepTumorQueen";NA;222;0
"Upgrade";"EvolveMuscularAugments";"HydraliskDen";194;0
"Building";"CreepTumor";NA;229;0
"Building";"CreepTumor";NA;229;0
"Building";"CreepTumor";NA;229;0
"Building";"CreepTumor";NA;229;0
"Building";"CreepTumor";NA;229;0
"Unit";"Viper";"Larva";229;3
"Unit";"Viper";"Larva";229;3
"Unit";"Viper";"Larva";229;3
"Unit";"Viper";"Larva";229;3
"Unit";"Overlord";"Larva";229;0
"Unit";"Overlord";"Larva";229;0
"Unit";"Overlord";"Larva";229;0
"Building";"CreepTumor";NA;229;0
"Building";"CreepTumor";NA;241;0
"Unit";"Viper";"Larva";229;3
"Unit";"Viper";"Larva";229;3
"Building";"Spire";NA;200;0
"Building";"Extractor";NA;241;0
"Building";"Extractor";NA;241;0
"Upgrade";"ZergMissileWeaponsLevel2";"EvolutionChamber";194;0
"Building";"CreepTumorQueen";NA;241;0
"Unit";"Queen";"Hatchery";229;2
"Building";"CreepTumorQueen";NA;241;0
"Unit";"Queen";"Hatchery";229;2
"Unit";"Queen";"Hatchery";229;2
"Upgrade";"ZergGroundArmorsLevel2";"EvolutionChamber";194;0
"Building";"CreepTumor";NA;247;0
"Building";"CreepTumorQueen";NA;247;0
"Building";"CreepTumorQueen";NA;247;0
"Building";"EvolutionChamber";NA;241;0
"Building";"EvolutionChamber";NA;241;0
"Building";"EvolutionChamber";NA;241;0
"Unit";"Overlord";"Larva";247;0
"Unit";"Overlord";"Larva";247;0
"Building";"EvolutionChamber";NA;241;0
"Building";"CreepTumorQueen";NA;253;0
"Building";"CreepTumorQueen";NA;253;0
"Building";"CreepTumorQueen";NA;253;0
"Building";"CreepTumorQueen";NA;253;0
"Unit";"Corruptor";"Larva";247;2
"Unit";"Corruptor";"Larva";247;2
"Unit";"Corruptor";"Larva";247;2
"Unit";"Corruptor";"Larva";247;2
"Unit";"Corruptor";"Larva";247;2
"Unit";"Corruptor";"Larva";247;2
"Unit";"Corruptor";"Larva";247;2
"Unit";"Corruptor";"Larva";247;2
"Building";"CreepTumorQueen";NA;253;0
"Building";"CreepTumorQueen";NA;269;0
"Building";"Hatchery";NA;229;0
"Building";"CreepTumorQueen";NA;269;0
"Building";"CreepTumorQueen";NA;269;0
"Building";"CreepTumor";NA;269;0
"Building";"CreepTumor";NA;269;0
"Building";"Hatchery";NA;253;0
"Building";"Spire";NA;269;0
"Unit";"Hydralisk";"Larva";275;2
"Unit";"Hydralisk";"Larva";275;2
"Unit";"Hydralisk";"Larva";275;2
"Unit";"Hydralisk";"Larva";275;2
"Unit";"Hydralisk";"Larva";275;2
"Unit";"Hydralisk";"Larva";275;2
"Unit";"Hydralisk";"Larva";275;2
"Unit";"Hydralisk";"Larva";275;2
"Unit";"Hydralisk";"Larva";275;2
"Unit";"Hydralisk";"Larva";275;2
"Unit";"Hydralisk";"Larva";275;2
"Unit";"Hydralisk";"Larva";275;2
"Unit";"Hydralisk";"Larva";275;2
"Unit";"Hydralisk";"Larva";275;2
"Unit";"Hydralisk";"Larva";275;2
"Unit";"Hydralisk";"Larva";275;2
"Unit";"Hydralisk";"Larva";275;2
"Unit";"Hydralisk";"Larva";275;2
"Unit";"Hydralisk";"Larva";275;2
"Unit";"Hydralisk";"Larva";275;2
"Unit";"Hydralisk";"Larva";275;2
"Unit";"Hydralisk";"Larva";275;2
"Unit";"Hydralisk";"Larva";275;2
"Unit";"Hydralisk";"Larva";275;2
"Unit";"Corruptor";"Larva";275;2
"Unit";"Corruptor";"Larva";275;2
"Unit";"Corruptor";"Larva";275;2
"Unit";"Corruptor";"Larva";275;2
"Unit";"Corruptor";"Larva";275;2
"Unit";"Corruptor";"Larva";275;2
"Unit";"Corruptor";"Larva";275;2
"Upgrade";"ZergGroundArmorsLevel3";"EvolutionChamber";275;0
"Upgrade";"ZergMissileWeaponsLevel3";"EvolutionChamber";275;0
"Building";"Extractor";NA;337;0
"Building";"Extractor";NA;337;0
"Unit";"Corruptor";"Larva";337;2
