"type";"unit_name";"on_building";"total_supply";"supply"
"Unit";"Overlord";"Larva";12;0
"Building";"SpawningPool";NA;19;0
"Building";"Hatchery";NA;17;0
"Unit";"Zergling";"Larva";23;1
"Unit";"Zergling";"Larva";23;1
"Unit";"Zergling";"Larva";23;1
"Unit";"Zergling";"Larva";23;1
"Unit";"Overlord";"Larva";24;0
"Unit";"Queen";"Hatchery";23;2
"Unit";"Queen";"Hatchery";24;2
"Unit";"Overlord";"Larva";31;0
"Building";"Hatchery";NA;23;0
"Unit";"Overlord";"Larva";36;0
"Building";"Extractor";NA;36;0
"Unit";"Queen";"Hatchery";36;2
"Unit";"Queen";"Hatchery";36;2
"Unit";"Overlord";"Larva";47;0
"Unit";"Overlord";"Larva";51;0
"Unit";"Overlord";"Larva";51;0
"Building";"CreepTumorQueen";NA;57;0
"Building";"Extractor";NA;61;0
"Unit";"Zergling";"Larva";62;1
"Unit";"Zergling";"Larva";62;1
"Unit";"Zergling";"Larva";63;1
"Unit";"Zergling";"Larva";63;1
"Unit";"Zergling";"Larva";63;1
"Unit";"Zergling";"Larva";63;1
"Unit";"Queen";"Hatchery";57;2
"Building";"CreepTumor";NA;63;0
"Unit";"Queen";"Hatchery";61;2
"Building";"EvolutionChamber";NA;71;0
"Unit";"Zergling";"Larva";73;1
"Unit";"Zergling";"Larva";73;1
"Unit";"Zergling";"Larva";73;1
"Unit";"Zergling";"Larva";73;1
"Unit";"Zergling";"Larva";73;1
"Unit";"Zergling";"Larva";73;1
"Unit";"Zergling";"Larva";73;1
"Unit";"Zergling";"Larva";73;1
"Building";"EvolutionChamber";NA;71;0
"Building";"BanelingNest";NA;69;0
"Unit";"Zergling";"Larva";85;1
"Unit";"Zergling";"Larva";85;1
"Unit";"Overlord";"Larva";85;0
"Unit";"Zergling";"Larva";85;1
"Unit";"Zergling";"Larva";85;1
"Unit";"Zergling";"Larva";85;1
"Unit";"Zergling";"Larva";85;1
"Unit";"Zergling";"Larva";85;1
"Unit";"Zergling";"Larva";85;1
"Unit";"Zergling";"Larva";85;1
"Unit";"Zergling";"Larva";85;1
"Unit";"Zergling";"Larva";85;1
"Unit";"Zergling";"Larva";85;1
"Unit";"Zergling";"Larva";93;1
"Unit";"Zergling";"Larva";93;1
"Building";"CreepTumor";NA;93;0
"Unit";"Zergling";"Larva";105;1
"Unit";"Zergling";"Larva";105;1
"Unit";"Zergling";"Larva";105;1
"Unit";"Zergling";"Larva";105;1
"Unit";"Zergling";"Larva";105;1
"Unit";"Zergling";"Larva";105;1
"Unit";"Zergling";"Larva";105;1
"Unit";"Zergling";"Larva";105;1
"Unit";"Zergling";"Larva";105;1
"Unit";"Zergling";"Larva";105;1
"Unit";"Zergling";"Larva";105;1
"Unit";"Zergling";"Larva";105;1
"Unit";"Zergling";"Larva";105;1
"Unit";"Zergling";"Larva";105;1
"Unit";"Zergling";"Larva";105;1
"Unit";"Zergling";"Larva";105;1
"Unit";"Zergling";"Larva";105;1
"Unit";"Zergling";"Larva";105;1
"Unit";"Zergling";"Larva";105;1
"Unit";"Zergling";"Larva";105;1
"Unit";"Zergling";"Larva";107;1
"Unit";"Zergling";"Larva";107;1
"Unit";"Zergling";"Larva";107;1
"Unit";"Zergling";"Larva";107;1
"Unit";"Zergling";"Larva";107;1
"Unit";"Zergling";"Larva";107;1
"Unit";"Zergling";"Larva";107;1
"Unit";"Zergling";"Larva";107;1
"Unit";"Zergling";"Larva";107;1
"Unit";"Zergling";"Larva";107;1
"Unit";"Zergling";"Larva";107;1
"Unit";"Zergling";"Larva";107;1
"Unit";"Zergling";"Larva";109;1
"Unit";"Zergling";"Larva";109;1
"Building";"CreepTumorQueen";NA;139;0
"Building";"CreepTumorQueen";NA;139;0
"Building";"CreepTumorQueen";NA;147;0
"Building";"CreepTumorQueen";NA;149;0
"Building";"CreepTumorQueen";NA;150;0
"Building";"CreepTumor";NA;150;0
"Unit";"Queen";"Hatchery";139;2
"Unit";"Overlord";"Larva";150;0
"Building";"CreepTumor";NA;151;0
"Building";"CreepTumor";NA;151;0
"Unit";"Zergling";"Larva";157;1
"Unit";"Zergling";"Larva";157;1
"Unit";"Zergling";"Larva";157;1
"Unit";"Zergling";"Larva";157;1
"Unit";"Zergling";"Larva";157;1
"Unit";"Zergling";"Larva";157;1
"Unit";"Zergling";"Larva";157;1
"Unit";"Zergling";"Larva";157;1
"Unit";"Zergling";"Larva";157;1
"Unit";"Zergling";"Larva";157;1
"Unit";"Zergling";"Larva";157;1
"Unit";"Zergling";"Larva";157;1
"Unit";"Zergling";"Larva";157;1
"Unit";"Zergling";"Larva";157;1
"Unit";"Zergling";"Larva";157;1
"Unit";"Zergling";"Larva";157;1
"Building";"CreepTumor";NA;157;0
"Unit";"Baneling";"Zergling";157;0
"Unit";"Baneling";"Zergling";157;0
"Unit";"Baneling";"Zergling";157;0
"Unit";"Baneling";"Zergling";157;0
"Unit";"Baneling";"Zergling";157;0
"Building";"CreepTumor";NA;157;0
"Building";"CreepTumor";NA;157;0
"Unit";"Queen";"Hatchery";151;2
"Upgrade";"ZergGroundArmorsLevel1";"EvolutionChamber";107;0
"Unit";"Zergling";"Larva";157;1
"Unit";"Zergling";"Larva";157;1
"Unit";"Zergling";"Larva";157;1
"Unit";"Zergling";"Larva";157;1
"Unit";"Zergling";"Larva";157;1
"Unit";"Zergling";"Larva";157;1
"Unit";"Overlord";"Larva";157;0
"Unit";"Zergling";"Larva";173;1
"Unit";"Zergling";"Larva";173;1
"Unit";"Zergling";"Larva";173;1
"Unit";"Zergling";"Larva";173;1
"Unit";"Zergling";"Larva";173;1
"Unit";"Zergling";"Larva";173;1
"Unit";"Zergling";"Larva";173;1
"Unit";"Zergling";"Larva";173;1
"Unit";"Zergling";"Larva";173;1
"Unit";"Zergling";"Larva";173;1
"Unit";"Overlord";"Larva";175;0
"Unit";"Overlord";"Larva";175;0
"Unit";"Overlord";"Larva";175;0
"Building";"Hatchery";NA;147;0
"Building";"CreepTumorQueen";NA;181;0
"Building";"CreepTumor";NA;181;0
"Building";"CreepTumor";NA;191;0
"Building";"SporeCrawler";NA;181;0
"Building";"Hatchery";NA;151;0
"Unit";"Zergling";"Larva";191;1
"Unit";"Zergling";"Larva";191;1
"Unit";"Zergling";"Larva";191;1
"Unit";"Zergling";"Larva";191;1
"Unit";"Zergling";"Larva";191;1
"Unit";"Zergling";"Larva";191;1
"Unit";"Zergling";"Larva";191;1
"Unit";"Zergling";"Larva";191;1
"Unit";"Zergling";"Larva";191;1
"Unit";"Zergling";"Larva";191;1
"Unit";"Zergling";"Larva";191;1
"Unit";"Zergling";"Larva";191;1
"Unit";"Zergling";"Larva";191;1
"Unit";"Zergling";"Larva";191;1
"Unit";"Baneling";"Zergling";191;0
"Unit";"Baneling";"Zergling";191;0
"Unit";"Baneling";"Zergling";191;0
"Unit";"Zergling";"Larva";191;1
"Unit";"Zergling";"Larva";191;1
"Unit";"Zergling";"Larva";191;1
"Unit";"Zergling";"Larva";191;1
"Unit";"Zergling";"Larva";191;1
"Unit";"Zergling";"Larva";191;1
"Unit";"Zergling";"Larva";191;1
"Unit";"Zergling";"Larva";191;1
"Unit";"Zergling";"Larva";191;1
"Unit";"Zergling";"Larva";191;1
"Unit";"Zergling";"Larva";191;1
"Unit";"Zergling";"Larva";191;1
"Unit";"Zergling";"Larva";191;1
"Unit";"Zergling";"Larva";191;1
"Unit";"Zergling";"Larva";191;1
"Unit";"Zergling";"Larva";191;1
"Unit";"Queen";"Hatchery";181;2
"Unit";"Queen";"Hatchery";181;2
"Unit";"Queen";"Hatchery";181;2
"Building";"CreepTumor";NA;191;0
"Unit";"Overlord";"Larva";191;0
"Unit";"Overlord";"Larva";191;0
"Upgrade";"ZergMeleeWeaponsLevel1";"EvolutionChamber";157;0
"Unit";"Zergling";"Larva";205;1
"Unit";"Zergling";"Larva";205;1
"Unit";"Zergling";"Larva";205;1
"Unit";"Zergling";"Larva";205;1
"Unit";"Zergling";"Larva";205;1
"Unit";"Zergling";"Larva";205;1
"Unit";"Zergling";"Larva";205;1
"Unit";"Zergling";"Larva";205;1
"Unit";"Zergling";"Larva";227;1
"Unit";"Zergling";"Larva";227;1
"Unit";"Zergling";"Larva";227;1
"Unit";"Zergling";"Larva";227;1
"Unit";"Zergling";"Larva";227;1
"Unit";"Zergling";"Larva";227;1
"Unit";"Zergling";"Larva";227;1
"Unit";"Zergling";"Larva";227;1
"Unit";"Queen";"Hatchery";191;2
"Unit";"Zergling";"Larva";227;1
"Unit";"Zergling";"Larva";227;1
"Unit";"Zergling";"Larva";227;1
"Unit";"Zergling";"Larva";227;1
"Unit";"Zergling";"Larva";227;1
"Unit";"Zergling";"Larva";227;1
"Unit";"Zergling";"Larva";227;1
"Unit";"Zergling";"Larva";227;1
"Unit";"Zergling";"Larva";227;1
"Unit";"Zergling";"Larva";227;1
"Unit";"Zergling";"Larva";227;1
"Unit";"Zergling";"Larva";227;1
"Unit";"Zergling";"Larva";227;1
"Unit";"Zergling";"Larva";227;1
"Unit";"Zergling";"Larva";243;1
"Unit";"Zergling";"Larva";243;1
"Unit";"Zergling";"Larva";243;1
"Unit";"Zergling";"Larva";243;1
"Unit";"Zergling";"Larva";243;1
"Unit";"Zergling";"Larva";243;1
"Unit";"Zergling";"Larva";243;1
"Unit";"Zergling";"Larva";243;1
"Unit";"Zergling";"Larva";245;1
"Unit";"Zergling";"Larva";245;1
"Unit";"Zergling";"Larva";245;1
"Unit";"Zergling";"Larva";245;1
"Unit";"Zergling";"Larva";245;1
"Unit";"Zergling";"Larva";245;1
"Unit";"Queen";"Hatchery";235;2
"Building";"CreepTumorQueen";NA;275;0
"Building";"CreepTumorQueen";NA;275;0
"Building";"CreepTumorQueen";NA;275;0
"Building";"CreepTumorQueen";NA;275;0
"Unit";"Zergling";"Larva";275;1
"Unit";"Zergling";"Larva";275;1
"Unit";"Zergling";"Larva";275;1
"Unit";"Zergling";"Larva";275;1
"Unit";"Zergling";"Larva";275;1
"Unit";"Zergling";"Larva";275;1
"Unit";"Zergling";"Larva";275;1
"Unit";"Zergling";"Larva";275;1
"Unit";"Zergling";"Larva";275;1
"Unit";"Zergling";"Larva";275;1
"Unit";"Zergling";"Larva";275;1
"Unit";"Zergling";"Larva";275;1
"Unit";"Zergling";"Larva";275;1
"Unit";"Zergling";"Larva";275;1
"Unit";"Zergling";"Larva";275;1
"Unit";"Zergling";"Larva";275;1
"Unit";"Zergling";"Larva";275;1
"Unit";"Zergling";"Larva";275;1
"Unit";"Zergling";"Larva";275;1
"Unit";"Zergling";"Larva";275;1
"Unit";"Zergling";"Larva";275;1
"Unit";"Zergling";"Larva";275;1
"Unit";"Zergling";"Larva";275;1
"Unit";"Zergling";"Larva";275;1
"Unit";"Zergling";"Larva";275;1
"Unit";"Zergling";"Larva";275;1
"Unit";"Zergling";"Larva";275;1
"Unit";"Zergling";"Larva";275;1
"Unit";"Zergling";"Larva";275;1
"Unit";"Zergling";"Larva";275;1
"Unit";"Zergling";"Larva";275;1
"Unit";"Zergling";"Larva";275;1
"Unit";"Zergling";"Larva";275;1
"Unit";"Zergling";"Larva";275;1
"Unit";"Zergling";"Larva";275;1
"Unit";"Zergling";"Larva";275;1
"Unit";"Zergling";"Larva";275;1
"Unit";"Zergling";"Larva";275;1
"Unit";"Zergling";"Larva";275;1
"Unit";"Zergling";"Larva";275;1
"Unit";"Zergling";"Larva";275;1
"Unit";"Zergling";"Larva";275;1
"Unit";"Zergling";"Larva";275;1
"Unit";"Zergling";"Larva";275;1
"Unit";"Zergling";"Larva";275;1
"Unit";"Zergling";"Larva";275;1
"Unit";"Zergling";"Larva";275;1
"Unit";"Zergling";"Larva";275;1
"Unit";"Zergling";"Larva";275;1
"Unit";"Zergling";"Larva";275;1
"Unit";"Zergling";"Larva";275;1
"Unit";"Zergling";"Larva";275;1
"Building";"CreepTumorQueen";NA;323;0
"Unit";"Zergling";"Larva";275;1
"Unit";"Zergling";"Larva";275;1
"Unit";"Zergling";"Larva";275;1
"Unit";"Zergling";"Larva";275;1
"Unit";"Zergling";"Larva";275;1
"Unit";"Zergling";"Larva";275;1
"Building";"CreepTumorQueen";NA;323;0
"Unit";"Zergling";"Larva";323;1
"Unit";"Zergling";"Larva";323;1
"Unit";"Zergling";"Larva";323;1
"Unit";"Zergling";"Larva";323;1
"Unit";"Zergling";"Larva";327;1
"Unit";"Zergling";"Larva";327;1
"Unit";"Zergling";"Larva";327;1
"Unit";"Zergling";"Larva";327;1
"Unit";"Zergling";"Larva";327;1
"Unit";"Zergling";"Larva";327;1
"Unit";"Zergling";"Larva";327;1
"Unit";"Zergling";"Larva";327;1
"Unit";"Zergling";"Larva";327;1
"Unit";"Zergling";"Larva";327;1
"Unit";"Zergling";"Larva";327;1
"Unit";"Zergling";"Larva";327;1
"Unit";"Zergling";"Larva";327;1
"Unit";"Zergling";"Larva";327;1
"Building";"CreepTumorQueen";NA;337;0
"Unit";"Zergling";"Larva";333;1
"Unit";"Zergling";"Larva";333;1
"Unit";"Zergling";"Larva";333;1
"Unit";"Zergling";"Larva";333;1
"Unit";"Zergling";"Larva";333;1
"Unit";"Zergling";"Larva";333;1
"Unit";"Zergling";"Larva";333;1
"Unit";"Zergling";"Larva";333;1
"Building";"CreepTumorQueen";NA;337;0
"Building";"CreepTumorQueen";NA;339;0
"Unit";"Baneling";"Zergling";337;0
"Unit";"Baneling";"Zergling";337;0
"Unit";"Baneling";"Zergling";337;0
"Unit";"Baneling";"Zergling";337;0
"Unit";"Baneling";"Zergling";337;0
"Unit";"Baneling";"Zergling";337;0
"Unit";"Baneling";"Zergling";337;0
"Unit";"Baneling";"Zergling";337;0
"Upgrade";"ZergGroundArmorsLevel2";"EvolutionChamber";243;0
"Unit";"Zergling";"Larva";351;1
"Unit";"Zergling";"Larva";351;1
"Unit";"Zergling";"Larva";351;1
"Unit";"Zergling";"Larva";351;1
"Unit";"Zergling";"Larva";351;1
"Unit";"Zergling";"Larva";351;1
"Unit";"Zergling";"Larva";351;1
"Unit";"Zergling";"Larva";351;1
"Unit";"Zergling";"Larva";351;1
"Unit";"Zergling";"Larva";351;1
"Unit";"Zergling";"Larva";351;1
"Unit";"Zergling";"Larva";351;1
"Unit";"Zergling";"Larva";351;1
"Unit";"Zergling";"Larva";351;1
"Unit";"Zergling";"Larva";351;1
"Unit";"Zergling";"Larva";351;1
"Unit";"Zergling";"Larva";351;1
"Unit";"Zergling";"Larva";351;1
"Unit";"Zergling";"Larva";351;1
"Unit";"Zergling";"Larva";351;1
"Unit";"Zergling";"Larva";351;1
"Unit";"Zergling";"Larva";351;1
"Unit";"Zergling";"Larva";351;1
"Unit";"Zergling";"Larva";351;1
"Unit";"Zergling";"Larva";351;1
"Unit";"Zergling";"Larva";351;1
"Unit";"Zergling";"Larva";351;1
"Unit";"Zergling";"Larva";351;1
"Unit";"Zergling";"Larva";351;1
"Unit";"Zergling";"Larva";351;1
"Building";"Extractor";NA;351;0
"Building";"InfestationPit";NA;333;0
"Building";"Extractor";NA;351;0
"Building";"Extractor";NA;359;0
"Building";"Extractor";NA;359;0
