"type";"unit_name";"on_building";"total_supply";"supply"
"Unit";"Overlord";"Larva";12;0
"Building";"SpawningPool";NA;19;0
"Building";"Hatchery";NA;17;0
"Building";"Extractor";NA;23;0
"Unit";"Zergling";"Larva";23;1
"Unit";"Zergling";"Larva";23;1
"Unit";"Zergling";"Larva";23;1
"Unit";"Zergling";"Larva";23;1
"Unit";"Overlord";"Larva";24;0
"Unit";"Queen";"Hatchery";23;2
"Unit";"Queen";"Hatchery";24;2
"Building";"Hatchery";NA;22;0
"Unit";"Overlord";"Larva";38;0
"Unit";"Queen";"Hatchery";32;2
"Building";"CreepTumorQueen";NA;43;0
"Unit";"Overlord";"Larva";43;0
"Unit";"Overlord";"Larva";43;0
"Unit";"Queen";"Hatchery";43;2
"Building";"CreepTumorQueen";NA;48;0
"Building";"CreepTumor";NA;48;0
"Building";"CreepTumorQueen";NA;58;0
"Unit";"Zergling";"Larva";58;1
"Unit";"Zergling";"Larva";58;1
"Unit";"Zergling";"Larva";58;1
"Unit";"Zergling";"Larva";58;1
"Unit";"Zergling";"Larva";58;1
"Unit";"Zergling";"Larva";58;1
"Unit";"Queen";"Hatchery";48;2
"Building";"CreepTumor";NA;62;0
"Building";"CreepTumor";NA;62;0
"Unit";"Overlord";"Larva";62;0
"Unit";"Overlord";"Larva";62;0
"Building";"CreepTumor";NA;68;0
"Unit";"Queen";"Hatchery";58;2
"Unit";"Overlord";"Larva";68;0
"Unit";"Zergling";"Larva";70;1
"Unit";"Zergling";"Larva";70;1
"Unit";"Zergling";"Larva";70;1
"Unit";"Zergling";"Larva";70;1
"Unit";"Zergling";"Larva";70;1
"Unit";"Zergling";"Larva";70;1
"Building";"CreepTumorQueen";NA;70;0
"Building";"CreepTumorQueen";NA;70;0
"Building";"CreepTumor";NA;72;0
"Building";"CreepTumor";NA;72;0
"Building";"CreepTumor";NA;85;0
"Building";"CreepTumor";NA;88;0
"Building";"CreepTumor";NA;88;0
"Building";"CreepTumor";NA;88;0
"Building";"CreepTumor";NA;88;0
"Building";"CreepTumor";NA;88;0
"Building";"Extractor";NA;88;0
"Building";"Extractor";NA;88;0
"Building";"CreepTumorQueen";NA;100;0
"Building";"CreepTumorQueen";NA;100;0
"Building";"CreepTumorQueen";NA;100;0
"Building";"SporeCrawler";NA;88;0
"Building";"CreepTumorQueen";NA;100;0
"Unit";"Zergling";"Larva";100;1
"Unit";"Zergling";"Larva";100;1
"Unit";"Zergling";"Larva";100;1
"Unit";"Zergling";"Larva";100;1
"Unit";"Zergling";"Larva";100;1
"Unit";"Zergling";"Larva";100;1
"Unit";"Zergling";"Larva";100;1
"Unit";"Zergling";"Larva";100;1
"Unit";"Zergling";"Larva";100;1
"Unit";"Zergling";"Larva";100;1
"Unit";"Zergling";"Larva";100;1
"Unit";"Zergling";"Larva";100;1
"Unit";"Zergling";"Larva";100;1
"Unit";"Zergling";"Larva";100;1
"Unit";"Zergling";"Larva";100;1
"Unit";"Zergling";"Larva";100;1
"Building";"CreepTumorQueen";NA;100;0
"Unit";"Queen";"Hatchery";88;2
"Building";"CreepTumor";NA;104;0
"Building";"Extractor";NA;100;0
"Building";"CreepTumor";NA;116;0
"Building";"Extractor";NA;100;0
"Building";"BanelingNest";NA;100;0
"Building";"EvolutionChamber";NA;118;0
"Building";"EvolutionChamber";NA;118;0
"Unit";"Baneling";"Zergling";126;0
"Unit";"Baneling";"Zergling";126;0
"Building";"CreepTumor";NA;126;0
"Building";"CreepTumor";NA;126;0
"Building";"CreepTumor";NA;126;0
"Building";"Extractor";NA;126;0
"Building";"CreepTumor";NA;131;0
"Building";"CreepTumor";NA;131;0
"Unit";"Overlord";"Larva";126;0
"Unit";"Overlord";"Larva";126;0
"Unit";"Overlord";"Larva";126;0
"Unit";"Overlord";"Larva";126;0
"Building";"CreepTumor";NA;131;0
"Building";"CreepTumor";NA;131;0
"Building";"Hatchery";NA;100;0
"Building";"CreepTumor";NA;132;0
"Building";"CreepTumor";NA;132;0
"Unit";"Zergling";"Larva";132;1
"Unit";"Zergling";"Larva";132;1
"Unit";"Zergling";"Larva";132;1
"Unit";"Zergling";"Larva";132;1
"Unit";"Zergling";"Larva";132;1
"Unit";"Zergling";"Larva";132;1
"Unit";"Zergling";"Larva";132;1
"Unit";"Zergling";"Larva";132;1
"Unit";"Zergling";"Larva";132;1
"Unit";"Zergling";"Larva";132;1
"Unit";"Zergling";"Larva";132;1
"Unit";"Zergling";"Larva";132;1
"Unit";"Zergling";"Larva";132;1
"Unit";"Zergling";"Larva";132;1
"Unit";"Zergling";"Larva";132;1
"Unit";"Zergling";"Larva";132;1
"Unit";"Zergling";"Larva";132;1
"Unit";"Zergling";"Larva";132;1
"Building";"CreepTumor";NA;132;0
"Building";"Hatchery";NA;118;0
"Unit";"Zergling";"Larva";132;1
"Unit";"Zergling";"Larva";132;1
"Unit";"Zergling";"Larva";132;1
"Unit";"Zergling";"Larva";132;1
"Unit";"Zergling";"Larva";132;1
"Unit";"Zergling";"Larva";132;1
"Unit";"Zergling";"Larva";132;1
"Unit";"Zergling";"Larva";132;1
"Unit";"Zergling";"Larva";132;1
"Unit";"Zergling";"Larva";132;1
"Unit";"Zergling";"Larva";132;1
"Unit";"Zergling";"Larva";132;1
"Unit";"Zergling";"Larva";132;1
"Unit";"Zergling";"Larva";132;1
"Unit";"Zergling";"Larva";132;1
"Unit";"Zergling";"Larva";132;1
"Unit";"Zergling";"Larva";132;1
"Unit";"Zergling";"Larva";132;1
"Unit";"Zergling";"Larva";132;1
"Unit";"Zergling";"Larva";132;1
"Unit";"Overlord";"Larva";150;0
"Unit";"Zergling";"Larva";150;1
"Unit";"Zergling";"Larva";150;1
"Unit";"Zergling";"Larva";150;1
"Unit";"Zergling";"Larva";150;1
"Unit";"Zergling";"Larva";150;1
"Unit";"Zergling";"Larva";150;1
"Unit";"Zergling";"Larva";150;1
"Unit";"Zergling";"Larva";150;1
"Building";"HydraliskDen";NA;150;0
"Unit";"Baneling";"Zergling";170;0
"Unit";"Baneling";"Zergling";170;0
"Unit";"Baneling";"Zergling";170;0
"Unit";"Baneling";"Zergling";170;0
"Unit";"Baneling";"Zergling";170;0
"Unit";"Baneling";"Zergling";170;0
"Unit";"Baneling";"Zergling";170;0
"Unit";"Baneling";"Zergling";178;0
"Unit";"Queen";"Hatchery";150;2
"Unit";"Zergling";"Larva";181;1
"Unit";"Zergling";"Larva";181;1
"Unit";"Zergling";"Larva";181;1
"Unit";"Zergling";"Larva";181;1
"Unit";"Zergling";"Larva";181;1
"Unit";"Zergling";"Larva";181;1
"Unit";"Zergling";"Larva";181;1
"Unit";"Zergling";"Larva";181;1
"Unit";"Zergling";"Larva";181;1
"Unit";"Zergling";"Larva";181;1
"Unit";"Zergling";"Larva";181;1
"Unit";"Zergling";"Larva";181;1
"Unit";"Queen";"Hatchery";150;2
"Unit";"Queen";"Hatchery";150;2
"Building";"InfestationPit";NA;170;0
"Unit";"Zergling";"Larva";199;1
"Unit";"Zergling";"Larva";199;1
"Unit";"Zergling";"Larva";199;1
"Unit";"Zergling";"Larva";199;1
"Unit";"Zergling";"Larva";199;1
"Unit";"Zergling";"Larva";199;1
"Unit";"Zergling";"Larva";199;1
"Unit";"Zergling";"Larva";199;1
"Unit";"Zergling";"Larva";199;1
"Unit";"Zergling";"Larva";199;1
"Unit";"Zergling";"Larva";199;1
"Unit";"Zergling";"Larva";199;1
"Unit";"Zergling";"Larva";199;1
"Unit";"Zergling";"Larva";199;1
"Unit";"Zergling";"Larva";199;1
"Unit";"Zergling";"Larva";199;1
"Unit";"Zergling";"Larva";199;1
"Unit";"Zergling";"Larva";199;1
"Unit";"Zergling";"Larva";199;1
"Unit";"Zergling";"Larva";199;1
"Unit";"Zergling";"Larva";199;1
"Unit";"Zergling";"Larva";199;1
"Upgrade";"ZergGroundArmorsLevel1";"EvolutionChamber";132;0
"Unit";"Zergling";"Larva";199;1
"Unit";"Zergling";"Larva";199;1
"Unit";"Zergling";"Larva";199;1
"Unit";"Zergling";"Larva";199;1
"Unit";"Zergling";"Larva";199;1
"Unit";"Zergling";"Larva";199;1
"Unit";"Zergling";"Larva";199;1
"Unit";"Zergling";"Larva";199;1
"Unit";"Zergling";"Larva";199;1
"Unit";"Zergling";"Larva";199;1
"Unit";"Zergling";"Larva";199;1
"Unit";"Zergling";"Larva";199;1
"Unit";"Zergling";"Larva";199;1
"Unit";"Zergling";"Larva";199;1
"Unit";"Zergling";"Larva";199;1
"Unit";"Zergling";"Larva";199;1
"Unit";"Zergling";"Larva";199;1
"Unit";"Zergling";"Larva";199;1
"Unit";"Zergling";"Larva";199;1
"Unit";"Zergling";"Larva";199;1
"Unit";"Zergling";"Larva";199;1
"Unit";"Zergling";"Larva";199;1
"Upgrade";"ZergMeleeWeaponsLevel1";"EvolutionChamber";150;0
"Building";"CreepTumorQueen";NA;231;0
"Building";"CreepTumorQueen";NA;231;0
"Building";"CreepTumorQueen";NA;231;0
"Building";"CreepTumorQueen";NA;231;0
"Unit";"Zergling";"Larva";199;1
"Unit";"Zergling";"Larva";199;1
"Unit";"Baneling";"Zergling";231;0
"Unit";"Zergling";"Larva";199;1
"Unit";"Zergling";"Larva";199;1
"Unit";"Zergling";"Larva";199;1
"Unit";"Zergling";"Larva";199;1
"Unit";"Zergling";"Larva";199;1
"Unit";"Zergling";"Larva";199;1
"Unit";"Baneling";"Zergling";231;0
"Unit";"Zergling";"Larva";199;1
"Unit";"Zergling";"Larva";199;1
"Unit";"Zergling";"Larva";199;1
"Unit";"Zergling";"Larva";199;1
"Unit";"Zergling";"Larva";199;1
"Unit";"Zergling";"Larva";199;1
"Unit";"Baneling";"Zergling";231;0
"Unit";"Baneling";"Zergling";231;0
"Unit";"Baneling";"Zergling";231;0
"Unit";"Baneling";"Zergling";231;0
"Unit";"Queen";"Hatchery";199;2
"Unit";"Queen";"Hatchery";199;2
"Unit";"Queen";"Hatchery";199;2
"Building";"CreepTumor";NA;257;0
"Building";"CreepTumor";NA;257;0
"Building";"CreepTumor";NA;257;0
"Unit";"Queen";"Hatchery";243;2
"Building";"CreepTumorQueen";NA;263;0
"Unit";"Zergling";"Larva";263;1
"Unit";"Zergling";"Larva";263;1
"Unit";"Zergling";"Larva";263;1
"Unit";"Zergling";"Larva";263;1
"Unit";"Zergling";"Larva";263;1
"Unit";"Zergling";"Larva";263;1
"Unit";"Zergling";"Larva";263;1
"Unit";"Zergling";"Larva";263;1
"Unit";"Zergling";"Larva";263;1
"Unit";"Zergling";"Larva";263;1
"Unit";"Zergling";"Larva";263;1
"Unit";"Zergling";"Larva";263;1
"Unit";"Zergling";"Larva";263;1
"Unit";"Zergling";"Larva";263;1
"Building";"CreepTumorQueen";NA;263;0
"Unit";"Baneling";"Zergling";263;0
"Unit";"Baneling";"Zergling";263;0
"Unit";"Baneling";"Zergling";263;0
"Building";"CreepTumorQueen";NA;279;0
"Unit";"Hydralisk";"Larva";263;2
"Unit";"Hydralisk";"Larva";263;2
"Unit";"Hydralisk";"Larva";263;2
"Unit";"Hydralisk";"Larva";263;2
"Unit";"Hydralisk";"Larva";263;2
"Unit";"Overlord";"Larva";265;0
"Unit";"Hydralisk";"Larva";263;2
"Building";"CreepTumorQueen";NA;279;0
"Building";"CreepTumor";NA;279;0
"Building";"CreepTumor";NA;279;0
"Building";"CreepTumor";NA;279;0
"Building";"CreepTumor";NA;279;0
"Unit";"Overlord";"Larva";279;0
"Unit";"Overlord";"Larva";279;0
"Upgrade";"EvolveGroovedSpines";"HydraliskDen";263;0
"Unit";"Zergling";"Larva";291;1
"Unit";"Zergling";"Larva";291;1
"Unit";"Zergling";"Larva";291;1
"Unit";"Zergling";"Larva";291;1
"Unit";"Zergling";"Larva";291;1
"Unit";"Zergling";"Larva";291;1
"Unit";"Zergling";"Larva";291;1
"Unit";"Zergling";"Larva";291;1
"Unit";"Zergling";"Larva";291;1
"Unit";"Zergling";"Larva";291;1
"Unit";"Zergling";"Larva";291;1
"Unit";"Zergling";"Larva";291;1
"Unit";"Zergling";"Larva";291;1
"Unit";"Zergling";"Larva";291;1
"Unit";"Zergling";"Larva";291;1
"Unit";"Zergling";"Larva";291;1
"Unit";"Zergling";"Larva";291;1
"Unit";"Zergling";"Larva";291;1
"Unit";"Zergling";"Larva";291;1
"Unit";"Zergling";"Larva";291;1
"Unit";"Zergling";"Larva";291;1
"Unit";"Zergling";"Larva";291;1
"Unit";"Zergling";"Larva";291;1
"Unit";"Zergling";"Larva";291;1
"Unit";"Zergling";"Larva";291;1
"Unit";"Zergling";"Larva";291;1
"Unit";"Zergling";"Larva";291;1
"Unit";"Zergling";"Larva";291;1
"Unit";"Zergling";"Larva";291;1
"Unit";"Zergling";"Larva";291;1
"Unit";"Zergling";"Larva";291;1
"Unit";"Zergling";"Larva";291;1
"Unit";"Zergling";"Larva";291;1
"Unit";"Zergling";"Larva";291;1
"Unit";"Zergling";"Larva";291;1
"Unit";"Zergling";"Larva";291;1
"Unit";"Baneling";"Zergling";313;0
"Unit";"Baneling";"Zergling";313;0
"Unit";"Baneling";"Zergling";313;0
"Unit";"Baneling";"Zergling";313;0
"Building";"CreepTumorQueen";NA;313;0
"Building";"CreepTumorQueen";NA;313;0
"Building";"CreepTumorQueen";NA;313;0
"Unit";"Baneling";"Zergling";313;0
"Unit";"Baneling";"Zergling";313;0
"Unit";"Baneling";"Zergling";313;0
"Unit";"Baneling";"Zergling";313;0
"Unit";"Baneling";"Zergling";313;0
"Unit";"Baneling";"Zergling";313;0
"Unit";"Baneling";"Zergling";313;0
"Unit";"Baneling";"Zergling";313;0
"Building";"CreepTumorQueen";NA;330;0
"Building";"CreepTumorQueen";NA;330;0
"Building";"CreepTumorQueen";NA;330;0
"Building";"CreepTumorQueen";NA;330;0
"Unit";"Zergling";"Larva";330;1
"Unit";"Zergling";"Larva";330;1
"Unit";"Zergling";"Larva";330;1
"Unit";"Zergling";"Larva";330;1
"Unit";"Zergling";"Larva";330;1
"Unit";"Zergling";"Larva";330;1
"Unit";"Zergling";"Larva";330;1
"Unit";"Zergling";"Larva";330;1
"Unit";"Zergling";"Larva";330;1
"Unit";"Zergling";"Larva";330;1
"Unit";"Zergling";"Larva";330;1
"Unit";"Zergling";"Larva";330;1
"Unit";"Zergling";"Larva";330;1
"Unit";"Zergling";"Larva";330;1
"Unit";"Zergling";"Larva";330;1
"Unit";"Zergling";"Larva";330;1
"Unit";"Zergling";"Larva";330;1
"Unit";"Zergling";"Larva";330;1
"Unit";"Zergling";"Larva";330;1
"Unit";"Zergling";"Larva";330;1
"Unit";"Zergling";"Larva";330;1
"Unit";"Zergling";"Larva";330;1
"Unit";"Zergling";"Larva";330;1
"Unit";"Zergling";"Larva";330;1
"Unit";"Zergling";"Larva";330;1
"Unit";"Zergling";"Larva";330;1
"Unit";"Zergling";"Larva";330;1
"Unit";"Zergling";"Larva";330;1
"Unit";"Zergling";"Larva";330;1
"Unit";"Zergling";"Larva";330;1
"Unit";"Zergling";"Larva";330;1
"Unit";"Zergling";"Larva";330;1
"Unit";"Zergling";"Larva";330;1
"Unit";"Zergling";"Larva";330;1
"Unit";"Zergling";"Larva";330;1
"Unit";"Zergling";"Larva";330;1
"Unit";"Zergling";"Larva";330;1
"Unit";"Zergling";"Larva";330;1
"Building";"CreepTumorQueen";NA;330;0
"Building";"CreepTumor";NA;330;0
"Building";"CreepTumor";NA;330;0
"Building";"CreepTumor";NA;330;0
"Upgrade";"ZergMeleeWeaponsLevel2";"EvolutionChamber";279;0
"Building";"CreepTumor";NA;336;0
"Building";"CreepTumor";NA;368;0
"Building";"CreepTumor";NA;368;0
"Unit";"Baneling";"Zergling";368;0
"Upgrade";"ZergGroundArmorsLevel2";"EvolutionChamber";279;0
"Building";"Hatchery";NA;291;0
"Upgrade";"EvolveMuscularAugments";"HydraliskDen";330;0
"Building";"CreepTumor";NA;368;0
"Building";"CreepTumor";NA;368;0
"Building";"CreepTumor";NA;368;0
"Building";"CreepTumor";NA;368;0
"Building";"CreepTumor";NA;375;0
"Building";"CreepTumor";NA;375;0
"Building";"CreepTumorQueen";NA;375;0
"Unit";"Zergling";"Larva";375;1
"Unit";"Zergling";"Larva";375;1
"Unit";"Zergling";"Larva";375;1
"Unit";"Zergling";"Larva";375;1
"Unit";"Zergling";"Larva";375;1
"Unit";"Zergling";"Larva";375;1
"Unit";"Zergling";"Larva";375;1
"Unit";"Zergling";"Larva";375;1
"Unit";"Zergling";"Larva";375;1
"Unit";"Zergling";"Larva";375;1
"Unit";"Zergling";"Larva";375;1
"Unit";"Zergling";"Larva";375;1
"Unit";"Zergling";"Larva";375;1
"Unit";"Zergling";"Larva";375;1
"Unit";"Zergling";"Larva";375;1
"Unit";"Zergling";"Larva";375;1
"Unit";"Zergling";"Larva";375;1
"Unit";"Zergling";"Larva";375;1
"Unit";"Zergling";"Larva";375;1
"Unit";"Zergling";"Larva";375;1
"Unit";"Zergling";"Larva";375;1
"Unit";"Zergling";"Larva";375;1
"Unit";"Zergling";"Larva";375;1
"Unit";"Zergling";"Larva";375;1
"Unit";"Zergling";"Larva";375;1
"Unit";"Zergling";"Larva";375;1
"Unit";"Zergling";"Larva";375;1
"Unit";"Zergling";"Larva";375;1
"Unit";"Zergling";"Larva";375;1
"Unit";"Zergling";"Larva";375;1
"Unit";"Zergling";"Larva";375;1
"Unit";"Zergling";"Larva";375;1
"Unit";"Zergling";"Larva";375;1
"Unit";"Zergling";"Larva";375;1
"Unit";"Zergling";"Larva";375;1
"Unit";"Zergling";"Larva";375;1
"Unit";"Zergling";"Larva";375;1
"Unit";"Zergling";"Larva";375;1
"Building";"CreepTumor";NA;375;0
"Unit";"Zergling";"Larva";395;1
"Unit";"Zergling";"Larva";395;1
"Unit";"Zergling";"Larva";395;1
"Unit";"Zergling";"Larva";395;1
"Unit";"Zergling";"Larva";395;1
"Unit";"Zergling";"Larva";395;1
"Unit";"Zergling";"Larva";395;1
"Unit";"Zergling";"Larva";395;1
"Unit";"Baneling";"Zergling";413;0
"Unit";"Baneling";"Zergling";413;0
"Unit";"Baneling";"Zergling";413;0
"Unit";"Baneling";"Zergling";413;0
"Unit";"Baneling";"Zergling";413;0
"Unit";"Baneling";"Zergling";413;0
"Unit";"Baneling";"Zergling";413;0
"Unit";"Baneling";"Zergling";413;0
"Building";"CreepTumor";NA;413;0
"Building";"CreepTumor";NA;413;0
"Unit";"Overlord";"Larva";413;0
"Unit";"Overlord";"Larva";413;0
"Unit";"Overlord";"Larva";413;0
"Unit";"Zergling";"Larva";421;1
"Unit";"Zergling";"Larva";421;1
"Unit";"Zergling";"Larva";421;1
"Unit";"Zergling";"Larva";421;1
"Unit";"Overlord";"Larva";421;0
"Unit";"Overlord";"Larva";421;0
"Unit";"Overlord";"Larva";421;0
"Unit";"Overlord";"Larva";421;0
"Unit";"Hydralisk";"Larva";421;2
"Unit";"Hydralisk";"Larva";421;2
"Unit";"Hydralisk";"Larva";421;2
"Unit";"Hydralisk";"Larva";421;2
"Unit";"Hydralisk";"Larva";421;2
"Unit";"Hydralisk";"Larva";421;2
"Unit";"Hydralisk";"Larva";421;2
"Unit";"Hydralisk";"Larva";421;2
"Unit";"Hydralisk";"Larva";421;2
"Unit";"Hydralisk";"Larva";421;2
"Unit";"Hydralisk";"Larva";421;2
"Unit";"Hydralisk";"Larva";421;2
"Unit";"Zergling";"Larva";449;1
"Unit";"Zergling";"Larva";449;1
"Unit";"Zergling";"Larva";449;1
"Unit";"Zergling";"Larva";449;1
"Unit";"Zergling";"Larva";449;1
"Unit";"Zergling";"Larva";449;1
"Unit";"Zergling";"Larva";449;1
"Unit";"Zergling";"Larva";449;1
"Unit";"Zergling";"Larva";449;1
"Unit";"Zergling";"Larva";449;1
"Unit";"Zergling";"Larva";449;1
"Unit";"Zergling";"Larva";449;1
"Unit";"Zergling";"Larva";449;1
"Unit";"Zergling";"Larva";449;1
"Unit";"Zergling";"Larva";449;1
"Unit";"Zergling";"Larva";449;1
"Unit";"Zergling";"Larva";449;1
"Unit";"Zergling";"Larva";449;1
"Unit";"Zergling";"Larva";449;1
"Unit";"Zergling";"Larva";449;1
"Unit";"Zergling";"Larva";449;1
"Unit";"Zergling";"Larva";449;1
"Unit";"Zergling";"Larva";449;1
"Unit";"Zergling";"Larva";449;1
"Unit";"Zergling";"Larva";449;1
"Unit";"Zergling";"Larva";449;1
"Unit";"Zergling";"Larva";449;1
"Unit";"Zergling";"Larva";449;1
"Unit";"Zergling";"Larva";449;1
"Unit";"Zergling";"Larva";449;1
"Unit";"Zergling";"Larva";449;1
"Unit";"Zergling";"Larva";449;1
"Unit";"Hydralisk";"Larva";429;2
"Unit";"Hydralisk";"Larva";439;2
"Unit";"Hydralisk";"Larva";441;2
"Unit";"Hydralisk";"Larva";441;2
"Unit";"Hydralisk";"Larva";445;2
"Unit";"Hydralisk";"Larva";447;2
"Unit";"Hydralisk";"Larva";447;2
"Unit";"Hydralisk";"Larva";447;2
"Upgrade";"ZergMissileWeaponsLevel1";"EvolutionChamber";413;0
"Building";"CreepTumor";NA;449;0
"Unit";"Zergling";"Larva";449;1
"Unit";"Zergling";"Larva";449;1
"Unit";"Zergling";"Larva";449;1
"Unit";"Zergling";"Larva";449;1
"Unit";"Zergling";"Larva";449;1
"Unit";"Zergling";"Larva";449;1
"Unit";"Zergling";"Larva";449;1
"Unit";"Zergling";"Larva";449;1
"Unit";"Zergling";"Larva";449;1
"Unit";"Zergling";"Larva";449;1
"Unit";"Zergling";"Larva";449;1
"Unit";"Zergling";"Larva";449;1
"Unit";"Zergling";"Larva";449;1
"Unit";"Zergling";"Larva";449;1
"Unit";"Zergling";"Larva";449;1
"Unit";"Zergling";"Larva";449;1
"Unit";"Zergling";"Larva";449;1
"Unit";"Zergling";"Larva";449;1
"Unit";"Zergling";"Larva";503;1
"Unit";"Zergling";"Larva";503;1
"Unit";"Zergling";"Larva";503;1
"Unit";"Zergling";"Larva";503;1
"Unit";"Zergling";"Larva";503;1
"Unit";"Zergling";"Larva";503;1
"Unit";"Zergling";"Larva";503;1
"Unit";"Zergling";"Larva";503;1
"Unit";"Zergling";"Larva";503;1
"Unit";"Zergling";"Larva";503;1
"Unit";"Zergling";"Larva";503;1
"Unit";"Zergling";"Larva";503;1
"Unit";"Zergling";"Larva";503;1
"Unit";"Zergling";"Larva";503;1
"Unit";"Zergling";"Larva";503;1
"Unit";"Zergling";"Larva";503;1
"Building";"CreepTumorQueen";NA;521;0
"Unit";"Zergling";"Larva";521;1
"Unit";"Zergling";"Larva";521;1
"Unit";"Zergling";"Larva";521;1
"Unit";"Zergling";"Larva";521;1
"Unit";"Zergling";"Larva";521;1
"Unit";"Zergling";"Larva";521;1
"Unit";"Zergling";"Larva";521;1
"Unit";"Zergling";"Larva";521;1
"Unit";"Zergling";"Larva";521;1
"Unit";"Zergling";"Larva";521;1
"Unit";"Zergling";"Larva";521;1
"Unit";"Zergling";"Larva";521;1
"Unit";"Zergling";"Larva";521;1
"Unit";"Zergling";"Larva";521;1
"Unit";"Zergling";"Larva";521;1
"Unit";"Zergling";"Larva";521;1
"Building";"CreepTumor";NA;537;0
"Building";"CreepTumorQueen";NA;537;0
"Unit";"Queen";"Hatchery";503;2
"Building";"CreepTumor";NA;553;0
"Building";"UltraliskCavern";NA;503;0
"Building";"CreepTumorQueen";NA;555;0
"Building";"CreepTumorQueen";NA;555;0
"Unit";"Viper";"Larva";553;3
"Unit";"Viper";"Larva";553;3
"Unit";"Viper";"Larva";553;3
"Unit";"Viper";"Larva";553;3
"Unit";"Baneling";"Zergling";555;0
"Unit";"Baneling";"Zergling";555;0
"Unit";"Baneling";"Zergling";555;0
"Unit";"Baneling";"Zergling";555;0
"Unit";"Baneling";"Zergling";555;0
"Unit";"Baneling";"Zergling";555;0
"Unit";"Baneling";"Zergling";555;0
"Unit";"Baneling";"Zergling";555;0
"Unit";"Baneling";"Zergling";555;0
"Unit";"Baneling";"Zergling";555;0
"Unit";"Baneling";"Zergling";555;0
"Unit";"Baneling";"Zergling";555;0
"Unit";"Baneling";"Zergling";555;0
"Unit";"Zergling";"Larva";555;1
"Unit";"Zergling";"Larva";555;1
"Unit";"Zergling";"Larva";555;1
"Unit";"Zergling";"Larva";555;1
"Unit";"Zergling";"Larva";555;1
"Unit";"Zergling";"Larva";555;1
"Unit";"Zergling";"Larva";555;1
"Unit";"Zergling";"Larva";555;1
"Unit";"Zergling";"Larva";555;1
"Unit";"Zergling";"Larva";555;1
"Unit";"Zergling";"Larva";555;1
"Unit";"Zergling";"Larva";555;1
"Unit";"Zergling";"Larva";555;1
"Unit";"Zergling";"Larva";555;1
"Unit";"Zergling";"Larva";555;1
"Unit";"Zergling";"Larva";555;1
"Unit";"Zergling";"Larva";555;1
"Unit";"Zergling";"Larva";555;1
"Unit";"Zergling";"Larva";555;1
"Unit";"Zergling";"Larva";555;1
"Unit";"Zergling";"Larva";555;1
"Unit";"Zergling";"Larva";555;1
"Unit";"Zergling";"Larva";555;1
"Unit";"Zergling";"Larva";555;1
"Unit";"Hydralisk";"Larva";555;2
"Unit";"Hydralisk";"Larva";555;2
"Unit";"Hydralisk";"Larva";555;2
"Building";"CreepTumor";NA;555;0
"Unit";"Hydralisk";"Larva";555;2
"Unit";"Hydralisk";"Larva";555;2
"Unit";"Hydralisk";"Larva";555;2
"Unit";"Hydralisk";"Larva";555;2
"Unit";"Baneling";"Zergling";599;0
"Unit";"Baneling";"Zergling";599;0
"Unit";"Baneling";"Zergling";599;0
"Unit";"Baneling";"Zergling";599;0
"Unit";"Baneling";"Zergling";599;0
"Unit";"Baneling";"Zergling";599;0
"Unit";"Baneling";"Zergling";599;0
"Unit";"Baneling";"Zergling";599;0
"Unit";"Baneling";"Zergling";599;0
"Unit";"Baneling";"Zergling";599;0
"Unit";"Baneling";"Zergling";599;0
"Unit";"Baneling";"Zergling";599;0
"Unit";"Baneling";"Zergling";599;0
"Unit";"Baneling";"Zergling";599;0
"Unit";"Baneling";"Zergling";599;0
"Unit";"Baneling";"Zergling";599;0
"Unit";"Baneling";"Zergling";599;0
"Unit";"Baneling";"Zergling";599;0
"Unit";"Baneling";"Zergling";599;0
"Unit";"Baneling";"Zergling";599;0
"Unit";"Baneling";"Zergling";599;0
"Unit";"Baneling";"Zergling";599;0
"Unit";"Baneling";"Zergling";599;0
"Unit";"Baneling";"Zergling";599;0
"Unit";"Baneling";"Zergling";599;0
"Unit";"Baneling";"Zergling";601;0
"Unit";"Baneling";"Zergling";605;0
"Unit";"Baneling";"Zergling";605;0
"Unit";"Baneling";"Zergling";605;0
"Unit";"Baneling";"Zergling";605;0
"Unit";"Baneling";"Zergling";605;0
"Unit";"Baneling";"Zergling";605;0
"Unit";"Baneling";"Zergling";605;0
"Unit";"Baneling";"Zergling";605;0
"Unit";"Baneling";"Zergling";605;0
"Unit";"Baneling";"Zergling";605;0
"Unit";"Baneling";"Zergling";605;0
"Unit";"Hydralisk";"Larva";599;2
"Unit";"Hydralisk";"Larva";599;2
"Unit";"Hydralisk";"Larva";599;2
"Unit";"Hydralisk";"Larva";599;2
"Unit";"Hydralisk";"Larva";599;2
"Unit";"Hydralisk";"Larva";599;2
"Building";"CreepTumor";NA;605;0
"Building";"CreepTumor";NA;605;0
"Building";"CreepTumor";NA;605;0
"Building";"CreepTumor";NA;605;0
"Unit";"Overlord";"Larva";617;0
"Unit";"Overlord";"Larva";617;0
"Unit";"Overlord";"Larva";617;0
"Unit";"Overlord";"Larva";617;0
"Building";"CreepTumor";NA;617;0
"Building";"CreepTumor";NA;617;0
"Upgrade";"ZergGroundArmorsLevel3";"EvolutionChamber";555;0
"Upgrade";"ZergMeleeWeaponsLevel3";"EvolutionChamber";555;0
"Unit";"Zergling";"Larva";617;1
"Unit";"Zergling";"Larva";617;1
"Unit";"Zergling";"Larva";617;1
"Unit";"Zergling";"Larva";617;1
"Unit";"Zergling";"Larva";617;1
"Unit";"Zergling";"Larva";617;1
"Unit";"Zergling";"Larva";617;1
"Unit";"Zergling";"Larva";617;1
"Unit";"Zergling";"Larva";617;1
"Unit";"Zergling";"Larva";617;1
"Unit";"Zergling";"Larva";617;1
"Unit";"Zergling";"Larva";617;1
"Unit";"Zergling";"Larva";617;1
"Unit";"Zergling";"Larva";617;1
"Unit";"Zergling";"Larva";617;1
"Unit";"Zergling";"Larva";617;1
"Unit";"Zergling";"Larva";617;1
"Unit";"Zergling";"Larva";617;1
"Unit";"Zergling";"Larva";617;1
"Unit";"Zergling";"Larva";617;1
"Unit";"Zergling";"Larva";617;1
"Unit";"Zergling";"Larva";617;1
"Unit";"Zergling";"Larva";617;1
"Unit";"Zergling";"Larva";617;1
"Unit";"Zergling";"Larva";617;1
"Unit";"Zergling";"Larva";617;1
"Unit";"Zergling";"Larva";617;1
"Unit";"Zergling";"Larva";617;1
"Unit";"Zergling";"Larva";617;1
"Unit";"Zergling";"Larva";617;1
"Building";"Hatchery";NA;605;0
"Unit";"Zergling";"Larva";617;1
"Unit";"Zergling";"Larva";617;1
"Unit";"Zergling";"Larva";619;1
"Unit";"Zergling";"Larva";619;1
"Unit";"Baneling";"Zergling";647;0
"Unit";"Baneling";"Zergling";647;0
"Unit";"Baneling";"Zergling";647;0
"Unit";"Baneling";"Zergling";647;0
"Unit";"Ultralisk";"Larva";617;6
"Unit";"Ultralisk";"Larva";617;6
"Unit";"Ultralisk";"Larva";617;6
"Unit";"Ultralisk";"Larva";617;6
"Unit";"Ultralisk";"Larva";617;6
"Unit";"Ultralisk";"Larva";617;6
"Unit";"Ultralisk";"Larva";617;6
"Unit";"Baneling";"Zergling";647;0
"Unit";"Baneling";"Zergling";647;0
"Unit";"Baneling";"Zergling";647;0
"Unit";"Baneling";"Zergling";647;0
"Unit";"Baneling";"Zergling";647;0
"Unit";"Baneling";"Zergling";647;0
"Unit";"Baneling";"Zergling";647;0
"Unit";"Baneling";"Zergling";647;0
"Unit";"Baneling";"Zergling";647;0
"Building";"CreepTumor";NA;647;0
"Unit";"Baneling";"Zergling";647;0
"Unit";"Baneling";"Zergling";647;0
"Unit";"Baneling";"Zergling";647;0
"Building";"CreepTumor";NA;647;0
"Unit";"Queen";"Hatchery";617;2
"Unit";"Queen";"Hatchery";617;2
"Unit";"Queen";"Hatchery";617;2
"Unit";"Queen";"Hatchery";617;2
"Unit";"Zergling";"Larva";701;1
"Unit";"Zergling";"Larva";701;1
"Unit";"Zergling";"Larva";701;1
"Unit";"Zergling";"Larva";701;1
"Unit";"Zergling";"Larva";701;1
"Unit";"Zergling";"Larva";701;1
"Unit";"Zergling";"Larva";701;1
"Unit";"Zergling";"Larva";701;1
"Unit";"Zergling";"Larva";701;1
"Unit";"Zergling";"Larva";701;1
"Unit";"Zergling";"Larva";701;1
"Unit";"Zergling";"Larva";701;1
"Unit";"Zergling";"Larva";701;1
"Unit";"Zergling";"Larva";701;1
"Unit";"Zergling";"Larva";701;1
"Unit";"Zergling";"Larva";701;1
"Unit";"Zergling";"Larva";701;1
"Unit";"Zergling";"Larva";701;1
"Unit";"Zergling";"Larva";701;1
"Unit";"Zergling";"Larva";701;1
"Unit";"Zergling";"Larva";701;1
"Unit";"Zergling";"Larva";701;1
"Unit";"Zergling";"Larva";701;1
"Unit";"Zergling";"Larva";701;1
"Unit";"Zergling";"Larva";701;1
"Unit";"Zergling";"Larva";701;1
"Unit";"Zergling";"Larva";701;1
"Unit";"Zergling";"Larva";701;1
"Unit";"Zergling";"Larva";701;1
"Unit";"Zergling";"Larva";701;1
"Building";"CreepTumorQueen";NA;715;0
"Building";"CreepTumorQueen";NA;715;0
"Building";"CreepTumorQueen";NA;731;0
"Building";"Hatchery";NA;693;0
"Building";"CreepTumor";NA;731;0
"Building";"CreepTumor";NA;731;0
"Building";"CreepTumorQueen";NA;731;0
"Upgrade";"ChitinousPlating";"UltraliskCavern";701;0
"Unit";"Zergling";"Larva";731;1
"Unit";"Zergling";"Larva";731;1
"Unit";"Zergling";"Larva";731;1
"Unit";"Zergling";"Larva";731;1
"Unit";"Zergling";"Larva";731;1
"Unit";"Zergling";"Larva";731;1
"Unit";"Zergling";"Larva";731;1
"Unit";"Zergling";"Larva";731;1
"Unit";"Viper";"Larva";731;3
"Unit";"Zergling";"Larva";742;1
"Unit";"Zergling";"Larva";742;1
"Unit";"Zergling";"Larva";742;1
"Unit";"Zergling";"Larva";742;1
"Unit";"Zergling";"Larva";742;1
"Unit";"Zergling";"Larva";742;1
"Unit";"Zergling";"Larva";742;1
"Unit";"Zergling";"Larva";742;1
"Unit";"Zergling";"Larva";742;1
"Unit";"Zergling";"Larva";742;1
"Unit";"Zergling";"Larva";742;1
"Unit";"Zergling";"Larva";742;1
"Unit";"Zergling";"Larva";742;1
"Unit";"Zergling";"Larva";742;1
"Unit";"Zergling";"Larva";742;1
"Unit";"Zergling";"Larva";742;1
"Unit";"Zergling";"Larva";742;1
"Unit";"Zergling";"Larva";742;1
"Unit";"Zergling";"Larva";742;1
"Unit";"Zergling";"Larva";742;1
"Unit";"Zergling";"Larva";742;1
"Unit";"Zergling";"Larva";742;1
"Unit";"Hydralisk";"Larva";742;2
"Unit";"Ultralisk";"Larva";742;6
"Unit";"Hydralisk";"Larva";742;2
"Unit";"Hydralisk";"Larva";742;2
"Unit";"Hydralisk";"Larva";742;2
"Unit";"Hydralisk";"Larva";742;2
"Unit";"Ultralisk";"Larva";742;6
"Unit";"Ultralisk";"Larva";742;6
"Unit";"Ultralisk";"Larva";742;6
"Unit";"Hydralisk";"Larva";742;2
"Unit";"Ultralisk";"Larva";742;6
"Unit";"Ultralisk";"Larva";742;6
"Unit";"Ultralisk";"Larva";742;6
"Unit";"Ultralisk";"Larva";742;6
"Unit";"Zergling";"Larva";764;1
"Unit";"Zergling";"Larva";764;1
"Unit";"Zergling";"Larva";764;1
"Unit";"Zergling";"Larva";764;1
"Unit";"Zergling";"Larva";764;1
"Unit";"Zergling";"Larva";764;1
"Unit";"Zergling";"Larva";764;1
"Unit";"Zergling";"Larva";764;1
"Unit";"Zergling";"Larva";764;1
"Unit";"Zergling";"Larva";764;1
"Unit";"Zergling";"Larva";764;1
"Unit";"Zergling";"Larva";764;1
"Unit";"Zergling";"Larva";764;1
"Unit";"Zergling";"Larva";764;1
"Unit";"Zergling";"Larva";764;1
"Unit";"Zergling";"Larva";764;1
"Unit";"Zergling";"Larva";764;1
"Unit";"Zergling";"Larva";764;1
"Unit";"Zergling";"Larva";764;1
"Unit";"Zergling";"Larva";764;1
"Unit";"Queen";"Hatchery";764;2
"Unit";"Hydralisk";"Larva";824;2
"Unit";"Hydralisk";"Larva";824;2
"Unit";"Hydralisk";"Larva";824;2
"Unit";"Hydralisk";"Larva";824;2
"Unit";"Hydralisk";"Larva";824;2
"Unit";"Hydralisk";"Larva";824;2
"Unit";"Hydralisk";"Larva";824;2
"Building";"CreepTumor";NA;844;0
"Building";"CreepTumor";NA;846;0
"Building";"CreepTumor";NA;846;0
"Unit";"Zergling";"Larva";846;1
"Unit";"Zergling";"Larva";846;1
"Unit";"Zergling";"Larva";846;1
"Unit";"Zergling";"Larva";846;1
"Unit";"Zergling";"Larva";846;1
"Unit";"Zergling";"Larva";846;1
"Unit";"Zergling";"Larva";846;1
"Unit";"Zergling";"Larva";846;1
"Unit";"Zergling";"Larva";846;1
"Unit";"Zergling";"Larva";846;1
"Unit";"Zergling";"Larva";846;1
"Unit";"Zergling";"Larva";846;1
"Unit";"Zergling";"Larva";846;1
"Unit";"Zergling";"Larva";846;1
"Unit";"Zergling";"Larva";846;1
"Unit";"Zergling";"Larva";846;1
"Unit";"Zergling";"Larva";846;1
"Unit";"Zergling";"Larva";846;1
"Unit";"Zergling";"Larva";846;1
"Unit";"Zergling";"Larva";846;1
"Building";"Extractor";NA;846;0
"Building";"Extractor";NA;846;0
"Unit";"Zergling";"Larva";880;1
"Unit";"Zergling";"Larva";880;1
"Unit";"Zergling";"Larva";880;1
"Unit";"Zergling";"Larva";880;1
"Unit";"Zergling";"Larva";880;1
"Unit";"Zergling";"Larva";880;1
"Unit";"Zergling";"Larva";880;1
"Unit";"Zergling";"Larva";880;1
"Unit";"Zergling";"Larva";880;1
"Unit";"Zergling";"Larva";880;1
"Unit";"Zergling";"Larva";880;1
"Unit";"Zergling";"Larva";880;1
"Unit";"Zergling";"Larva";880;1
"Unit";"Zergling";"Larva";880;1
"Unit";"Zergling";"Larva";880;1
"Unit";"Zergling";"Larva";880;1
"Unit";"Zergling";"Larva";880;1
"Unit";"Zergling";"Larva";880;1
"Unit";"Zergling";"Larva";880;1
"Unit";"Zergling";"Larva";880;1
"Unit";"Zergling";"Larva";880;1
"Unit";"Zergling";"Larva";880;1
"Unit";"Zergling";"Larva";880;1
"Unit";"Zergling";"Larva";880;1
"Unit";"Zergling";"Larva";904;1
"Unit";"Zergling";"Larva";904;1
"Unit";"Zergling";"Larva";904;1
"Unit";"Zergling";"Larva";904;1
"Unit";"Zergling";"Larva";904;1
"Unit";"Zergling";"Larva";904;1
"Unit";"Zergling";"Larva";904;1
"Unit";"Zergling";"Larva";904;1
"Unit";"Zergling";"Larva";904;1
"Unit";"Zergling";"Larva";904;1
"Unit";"Zergling";"Larva";904;1
"Unit";"Zergling";"Larva";904;1
"Unit";"Zergling";"Larva";904;1
"Unit";"Zergling";"Larva";904;1
"Unit";"Zergling";"Larva";904;1
"Unit";"Zergling";"Larva";904;1
"Unit";"Zergling";"Larva";904;1
"Unit";"Zergling";"Larva";904;1
"Unit";"Zergling";"Larva";904;1
"Unit";"Zergling";"Larva";904;1
"Unit";"Zergling";"Larva";904;1
"Unit";"Zergling";"Larva";904;1
"Building";"Hatchery";NA;844;0
"Building";"Hatchery";NA;844;0
"Building";"Extractor";NA;904;0
"Building";"Extractor";NA;904;0
"Building";"Extractor";NA;926;0
"Building";"Extractor";NA;926;0
"Unit";"Baneling";"Zergling";926;0
"Unit";"Baneling";"Zergling";926;0
"Unit";"Ultralisk";"Larva";926;6
"Unit";"Ultralisk";"Larva";926;6
"Unit";"Ultralisk";"Larva";926;6
"Unit";"Ultralisk";"Larva";926;6
"Unit";"Ultralisk";"Larva";926;6
"Unit";"Ultralisk";"Larva";926;6
"Unit";"Ultralisk";"Larva";926;6
"Unit";"Zergling";"Larva";926;1
"Unit";"Zergling";"Larva";926;1
"Unit";"Zergling";"Larva";926;1
"Unit";"Zergling";"Larva";926;1
"Unit";"Zergling";"Larva";926;1
"Unit";"Zergling";"Larva";926;1
"Unit";"Zergling";"Larva";926;1
"Unit";"Zergling";"Larva";926;1
"Unit";"Zergling";"Larva";926;1
"Unit";"Zergling";"Larva";926;1
"Unit";"Zergling";"Larva";926;1
"Unit";"Zergling";"Larva";926;1
"Unit";"Zergling";"Larva";926;1
"Unit";"Zergling";"Larva";926;1
"Unit";"Zergling";"Larva";926;1
"Unit";"Zergling";"Larva";926;1
"Unit";"Zergling";"Larva";926;1
"Unit";"Zergling";"Larva";926;1
"Unit";"Zergling";"Larva";926;1
"Unit";"Zergling";"Larva";926;1
"Unit";"Zergling";"Larva";926;1
"Unit";"Zergling";"Larva";926;1
"Unit";"Zergling";"Larva";926;1
"Unit";"Zergling";"Larva";926;1
"Unit";"Zergling";"Larva";926;1
"Unit";"Zergling";"Larva";926;1
"Unit";"Zergling";"Larva";926;1
"Unit";"Zergling";"Larva";926;1
"Unit";"Zergling";"Larva";926;1
"Unit";"Zergling";"Larva";926;1
"Unit";"Zergling";"Larva";926;1
"Unit";"Zergling";"Larva";926;1
"Unit";"Zergling";"Larva";926;1
"Unit";"Zergling";"Larva";926;1
"Unit";"Zergling";"Larva";926;1
"Unit";"Zergling";"Larva";926;1
"Unit";"Zergling";"Larva";926;1
"Unit";"Zergling";"Larva";926;1
"Unit";"Zergling";"Larva";926;1
"Unit";"Zergling";"Larva";926;1
"Unit";"Zergling";"Larva";926;1
"Unit";"Zergling";"Larva";926;1
"Unit";"Zergling";"Larva";1010;1
"Unit";"Zergling";"Larva";1010;1
"Unit";"Zergling";"Larva";1010;1
"Unit";"Zergling";"Larva";1010;1
"Unit";"Zergling";"Larva";1010;1
"Unit";"Zergling";"Larva";1010;1
"Unit";"Zergling";"Larva";1010;1
"Unit";"Zergling";"Larva";1010;1
"Unit";"Zergling";"Larva";1010;1
"Unit";"Zergling";"Larva";1010;1
"Unit";"Zergling";"Larva";1010;1
"Unit";"Zergling";"Larva";1010;1
"Unit";"Zergling";"Larva";1010;1
"Unit";"Zergling";"Larva";1010;1
"Unit";"Zergling";"Larva";1010;1
"Unit";"Zergling";"Larva";1010;1
"Unit";"Zergling";"Larva";1010;1
"Unit";"Zergling";"Larva";1010;1
"Unit";"Zergling";"Larva";1010;1
"Unit";"Zergling";"Larva";1010;1
"Unit";"Zergling";"Larva";1010;1
"Unit";"Zergling";"Larva";1010;1
"Unit";"Zergling";"Larva";1010;1
"Unit";"Zergling";"Larva";1010;1
"Building";"CreepTumor";NA;1010;0
"Unit";"Zergling";"Larva";1010;1
"Unit";"Zergling";"Larva";1010;1
"Unit";"Zergling";"Larva";1010;1
"Unit";"Zergling";"Larva";1010;1
"Unit";"Zergling";"Larva";1010;1
"Unit";"Zergling";"Larva";1010;1
"Unit";"Zergling";"Larva";1010;1
"Unit";"Zergling";"Larva";1010;1
"Unit";"Zergling";"Larva";1010;1
"Unit";"Zergling";"Larva";1010;1
"Unit";"Zergling";"Larva";1010;1
"Unit";"Zergling";"Larva";1010;1
"Unit";"Zergling";"Larva";1010;1
"Unit";"Zergling";"Larva";1010;1
"Unit";"Zergling";"Larva";1010;1
"Unit";"Zergling";"Larva";1010;1
"Unit";"Zergling";"Larva";1010;1
"Unit";"Zergling";"Larva";1010;1
"Unit";"Zergling";"Larva";1010;1
"Unit";"Zergling";"Larva";1010;1
"Unit";"Zergling";"Larva";1010;1
"Unit";"Zergling";"Larva";1010;1
"Unit";"Zergling";"Larva";1010;1
"Unit";"Zergling";"Larva";1010;1
"Building";"Extractor";NA;1010;0
"Building";"Extractor";NA;1010;0
"Unit";"Hydralisk";"Larva";1046;2
"Unit";"Hydralisk";"Larva";1046;2
"Unit";"Hydralisk";"Larva";1046;2
"Unit";"Hydralisk";"Larva";1046;2
"Unit";"Hydralisk";"Larva";1046;2
"Unit";"Hydralisk";"Larva";1046;2
"Unit";"Hydralisk";"Larva";1046;2
"Unit";"Hydralisk";"Larva";1046;2
"Unit";"Zergling";"Larva";1058;1
"Unit";"Zergling";"Larva";1058;1
"Unit";"Zergling";"Larva";1058;1
"Unit";"Zergling";"Larva";1058;1
"Unit";"Zergling";"Larva";1058;1
"Unit";"Zergling";"Larva";1058;1
"Unit";"Zergling";"Larva";1058;1
"Unit";"Zergling";"Larva";1058;1
"Unit";"Zergling";"Larva";1058;1
"Unit";"Zergling";"Larva";1058;1
"Unit";"Zergling";"Larva";1058;1
"Unit";"Zergling";"Larva";1058;1
"Unit";"Hydralisk";"Larva";1086;2
"Unit";"Hydralisk";"Larva";1086;2
"Unit";"Hydralisk";"Larva";1086;2
"Unit";"Hydralisk";"Larva";1086;2
"Unit";"Hydralisk";"Larva";1086;2
"Unit";"Hydralisk";"Larva";1086;2
"Unit";"Hydralisk";"Larva";1086;2
"Unit";"Hydralisk";"Larva";1086;2
"Unit";"Hydralisk";"Larva";1086;2
"Unit";"Hydralisk";"Larva";1086;2
"Unit";"Hydralisk";"Larva";1086;2
"Building";"CreepTumor";NA;1086;0
"Unit";"Viper";"Larva";1086;3
"Unit";"Zergling";"Larva";1108;1
"Unit";"Zergling";"Larva";1108;1
"Unit";"Zergling";"Larva";1108;1
"Unit";"Zergling";"Larva";1108;1
"Unit";"Zergling";"Larva";1108;1
"Unit";"Zergling";"Larva";1108;1
"Unit";"Zergling";"Larva";1108;1
"Unit";"Zergling";"Larva";1108;1
"Building";"Extractor";NA;1108;0
"Building";"Extractor";NA;1108;0
"Unit";"Zergling";"Larva";1111;1
"Unit";"Zergling";"Larva";1111;1
"Unit";"Zergling";"Larva";1111;1
"Unit";"Zergling";"Larva";1111;1
"Unit";"Zergling";"Larva";1111;1
"Unit";"Zergling";"Larva";1111;1
"Unit";"Zergling";"Larva";1111;1
"Unit";"Zergling";"Larva";1111;1
"Unit";"Zergling";"Larva";1111;1
"Unit";"Zergling";"Larva";1111;1
"Unit";"Zergling";"Larva";1111;1
"Unit";"Zergling";"Larva";1111;1
"Unit";"Zergling";"Larva";1111;1
"Unit";"Zergling";"Larva";1111;1
"Unit";"Zergling";"Larva";1111;1
"Unit";"Zergling";"Larva";1111;1
"Unit";"Zergling";"Larva";1111;1
"Unit";"Zergling";"Larva";1111;1
"Unit";"Zergling";"Larva";1111;1
"Unit";"Zergling";"Larva";1111;1
"Unit";"Zergling";"Larva";1111;1
"Unit";"Zergling";"Larva";1111;1
"Unit";"Zergling";"Larva";1111;1
"Unit";"Zergling";"Larva";1111;1
"Unit";"Zergling";"Larva";1111;1
"Unit";"Zergling";"Larva";1111;1
"Unit";"Zergling";"Larva";1113;1
"Unit";"Zergling";"Larva";1113;1
"Unit";"Zergling";"Larva";1113;1
"Unit";"Zergling";"Larva";1113;1
"Unit";"Zergling";"Larva";1113;1
"Unit";"Zergling";"Larva";1113;1
"Unit";"Zergling";"Larva";1113;1
"Unit";"Zergling";"Larva";1113;1
"Unit";"Zergling";"Larva";1113;1
"Unit";"Zergling";"Larva";1113;1
"Unit";"Zergling";"Larva";1113;1
"Unit";"Zergling";"Larva";1113;1
"Building";"CreepTumor";NA;1119;0
"Building";"CreepTumor";NA;1125;0
"Building";"CreepTumor";NA;1151;0
"Building";"SporeCrawler";NA;1119;0
"Building";"SporeCrawler";NA;1119;0
"Building";"SporeCrawler";NA;1151;0
"Unit";"Zergling";"Larva";1157;1
"Unit";"Zergling";"Larva";1157;1
"Unit";"Zergling";"Larva";1157;1
"Unit";"Zergling";"Larva";1157;1
"Unit";"Zergling";"Larva";1157;1
"Unit";"Zergling";"Larva";1157;1
"Unit";"Zergling";"Larva";1157;1
"Unit";"Zergling";"Larva";1157;1
"Unit";"Zergling";"Larva";1157;1
"Unit";"Zergling";"Larva";1157;1
"Unit";"Zergling";"Larva";1157;1
"Unit";"Zergling";"Larva";1157;1
"Unit";"Zergling";"Larva";1157;1
"Unit";"Zergling";"Larva";1157;1
"Unit";"Zergling";"Larva";1157;1
"Unit";"Zergling";"Larva";1157;1
"Unit";"Zergling";"Larva";1157;1
"Unit";"Zergling";"Larva";1157;1
