"type";"unit_name";"on_building";"total_supply";"supply"
"Unit";"Overlord";"Larva";13;0
"Building";"Extractor";NA;18;0
"Unit";"Overlord";"Larva";21;0
"Building";"SpawningPool";NA;19;0
"Building";"Hatchery";NA;17;0
"Unit";"Zergling";"Larva";23;1
"Unit";"Zergling";"Larva";23;1
"Unit";"Zergling";"Larva";23;1
"Unit";"Zergling";"Larva";23;1
"Unit";"Queen";"Hatchery";23;2
"Unit";"Queen";"Hatchery";23;2
"Unit";"Overlord";"Larva";36;0
"Unit";"Overlord";"Larva";37;0
"Unit";"Queen";"Hatchery";31;2
"Unit";"Queen";"Hatchery";49;2
"Unit";"Queen";"Hatchery";49;2
"Building";"CreepTumorQueen";NA;51;0
"Building";"EvolutionChamber";NA;51;0
"Building";"CreepTumorQueen";NA;58;0
"Building";"EvolutionChamber";NA;51;0
"Building";"CreepTumorQueen";NA;58;0
"Unit";"Overlord";"Larva";58;0
"Unit";"Overlord";"Larva";58;0
"Building";"CreepTumorQueen";NA;61;0
"Building";"Hatchery";NA;49;0
"Building";"Extractor";NA;58;0
"Building";"Extractor";NA;58;0
"Building";"BanelingNest";NA;51;0
"Building";"CreepTumorQueen";NA;71;0
"Building";"CreepTumorQueen";NA;71;0
"Unit";"Queen";"Hatchery";61;2
"Unit";"Zergling";"Larva";71;1
"Unit";"Zergling";"Larva";71;1
"Unit";"Overlord";"Larva";78;0
"Unit";"Overlord";"Larva";79;0
"Building";"CreepTumor";NA;86;0
"Building";"CreepTumor";NA;86;0
"Building";"CreepTumor";NA;86;0
"Building";"CreepTumor";NA;86;0
"Building";"CreepTumor";NA;86;0
"Building";"CreepTumorQueen";NA;86;0
"Building";"CreepTumorQueen";NA;86;0
"Building";"Extractor";NA;86;0
"Building";"CreepTumorQueen";NA;86;0
"Building";"Extractor";NA;86;0
"Building";"CreepTumorQueen";NA;86;0
"Unit";"Zergling";"Larva";86;1
"Unit";"Zergling";"Larva";86;1
"Unit";"Zergling";"Larva";86;1
"Unit";"Zergling";"Larva";86;1
"Unit";"Zergling";"Larva";86;1
"Unit";"Zergling";"Larva";86;1
"Building";"Extractor";NA;86;0
"Unit";"Zergling";"Larva";86;1
"Unit";"Zergling";"Larva";86;1
"Unit";"Zergling";"Larva";86;1
"Unit";"Zergling";"Larva";86;1
"Unit";"Zergling";"Larva";86;1
"Unit";"Zergling";"Larva";86;1
"Unit";"Zergling";"Larva";86;1
"Unit";"Zergling";"Larva";86;1
"Unit";"Zergling";"Larva";86;1
"Unit";"Zergling";"Larva";86;1
"Unit";"Zergling";"Larva";86;1
"Unit";"Zergling";"Larva";86;1
"Unit";"Zergling";"Larva";86;1
"Unit";"Zergling";"Larva";86;1
"Unit";"Zergling";"Larva";86;1
"Unit";"Zergling";"Larva";86;1
"Building";"CreepTumor";NA;90;0
"Building";"CreepTumor";NA;90;0
"Building";"CreepTumor";NA;90;0
"Building";"CreepTumor";NA;90;0
"Building";"CreepTumorQueen";NA;90;0
"Building";"CreepTumorQueen";NA;90;0
"Building";"CreepTumor";NA;90;0
"Building";"CreepTumorQueen";NA;92;0
"Upgrade";"ZergMeleeWeaponsLevel1";"EvolutionChamber";71;0
"Upgrade";"ZergGroundArmorsLevel1";"EvolutionChamber";71;0
"Building";"CreepTumor";NA;112;0
"Building";"SporeCrawler";NA;112;0
"Building";"CreepTumor";NA;112;0
"Building";"CreepTumor";NA;112;0
"Building";"HydraliskDen";NA;112;0
"Building";"CreepTumor";NA;117;0
"Building";"CreepTumor";NA;117;0
"Building";"CreepTumor";NA;117;0
"Building";"CreepTumor";NA;117;0
"Building";"CreepTumor";NA;117;0
"Building";"CreepTumor";NA;117;0
"Building";"Hatchery";NA;86;0
"Building";"CreepTumor";NA;117;0
"Building";"CreepTumor";NA;117;0
"Building";"CreepTumorQueen";NA;117;0
"Building";"CreepTumor";NA;117;0
"Building";"CreepTumorQueen";NA;117;0
"Building";"CreepTumorQueen";NA;117;0
"Unit";"Overlord";"Larva";117;0
"Unit";"Overlord";"Larva";117;0
"Unit";"Overlord";"Larva";117;0
"Unit";"Overlord";"Larva";117;0
"Unit";"Zergling";"Larva";119;1
"Unit";"Zergling";"Larva";119;1
"Unit";"Zergling";"Larva";119;1
"Unit";"Zergling";"Larva";119;1
"Unit";"Zergling";"Larva";119;1
"Unit";"Zergling";"Larva";119;1
"Unit";"Zergling";"Larva";119;1
"Unit";"Zergling";"Larva";119;1
"Unit";"Zergling";"Larva";119;1
"Unit";"Zergling";"Larva";119;1
"Unit";"Zergling";"Larva";119;1
"Unit";"Zergling";"Larva";119;1
"Building";"CreepTumor";NA;131;0
"Unit";"Hydralisk";"Larva";119;2
"Unit";"Hydralisk";"Larva";119;2
"Unit";"Hydralisk";"Larva";119;2
"Unit";"Hydralisk";"Larva";121;2
"Unit";"Hydralisk";"Larva";121;2
"Unit";"Hydralisk";"Larva";121;2
"Unit";"Hydralisk";"Larva";121;2
"Unit";"Hydralisk";"Larva";121;2
"Unit";"Hydralisk";"Larva";121;2
"Unit";"Hydralisk";"Larva";121;2
"Unit";"Hydralisk";"Larva";121;2
"Unit";"Hydralisk";"Larva";121;2
"Unit";"Hydralisk";"Larva";121;2
"Unit";"Hydralisk";"Larva";121;2
"Unit";"Hydralisk";"Larva";121;2
"Unit";"Hydralisk";"Larva";121;2
"Unit";"Zergling";"Larva";131;1
"Unit";"Zergling";"Larva";131;1
"Unit";"Zergling";"Larva";131;1
"Unit";"Zergling";"Larva";131;1
"Building";"CreepTumor";NA;131;0
"Unit";"Overlord";"Larva";131;0
"Unit";"Overlord";"Larva";131;0
"Building";"CreepTumor";NA;131;0
"Building";"CreepTumor";NA;131;0
"Building";"CreepTumorQueen";NA;131;0
"Building";"CreepTumor";NA;131;0
"Building";"CreepTumor";NA;131;0
"Building";"CreepTumor";NA;131;0
"Building";"CreepTumorQueen";NA;131;0
"Unit";"Queen";"Hatchery";119;2
"Building";"CreepTumorQueen";NA;143;0
"Building";"CreepTumorQueen";NA;167;0
"Building";"CreepTumor";NA;167;0
"Building";"InfestationPit";NA;131;0
"Unit";"Zergling";"Larva";169;1
"Unit";"Zergling";"Larva";169;1
"Unit";"Zergling";"Larva";169;1
"Unit";"Zergling";"Larva";169;1
"Unit";"Zergling";"Larva";169;1
"Unit";"Zergling";"Larva";169;1
"Unit";"Zergling";"Larva";169;1
"Unit";"Zergling";"Larva";169;1
"Unit";"Zergling";"Larva";169;1
"Unit";"Zergling";"Larva";169;1
"Unit";"Zergling";"Larva";169;1
"Unit";"Zergling";"Larva";169;1
"Unit";"Zergling";"Larva";169;1
"Unit";"Zergling";"Larva";169;1
"Unit";"Zergling";"Larva";169;1
"Unit";"Zergling";"Larva";169;1
"Unit";"Zergling";"Larva";169;1
"Unit";"Zergling";"Larva";169;1
"Unit";"Zergling";"Larva";169;1
"Unit";"Zergling";"Larva";169;1
"Unit";"Zergling";"Larva";169;1
"Unit";"Zergling";"Larva";169;1
"Unit";"Zergling";"Larva";169;1
"Unit";"Zergling";"Larva";169;1
"Unit";"Zergling";"Larva";169;1
"Unit";"Zergling";"Larva";169;1
"Unit";"Zergling";"Larva";169;1
"Unit";"Zergling";"Larva";169;1
"Unit";"Zergling";"Larva";169;1
"Unit";"Zergling";"Larva";169;1
"Unit";"Baneling";"Zergling";169;0
"Unit";"Baneling";"Zergling";169;0
"Unit";"Baneling";"Zergling";169;0
"Unit";"Baneling";"Zergling";169;0
"Unit";"Baneling";"Zergling";169;0
"Unit";"Baneling";"Zergling";169;0
"Upgrade";"ZergMissileWeaponsLevel1";"EvolutionChamber";119;0
"Unit";"Baneling";"Zergling";169;0
"Unit";"Baneling";"Zergling";169;0
"Unit";"Baneling";"Zergling";169;0
"Unit";"Baneling";"Zergling";169;0
"Unit";"Baneling";"Zergling";169;0
"Unit";"Baneling";"Zergling";169;0
"Unit";"Baneling";"Zergling";169;0
"Unit";"Baneling";"Zergling";169;0
"Upgrade";"ZergMeleeWeaponsLevel2";"EvolutionChamber";119;0
"Upgrade";"EvolveMuscularAugments";"HydraliskDen";167;0
"Building";"Hatchery";NA;131;0
"Unit";"Overlord";"Larva";199;0
"Unit";"Overlord";"Larva";199;0
"Unit";"Overlord";"Larva";199;0
"Unit";"Overlord";"Larva";199;0
"Building";"CreepTumor";NA;199;0
"Building";"CreepTumor";NA;199;0
"Building";"CreepTumor";NA;199;0
"Building";"CreepTumor";NA;199;0
"Unit";"Overlord";"Larva";199;0
"Unit";"Overlord";"Larva";199;0
"Unit";"Overlord";"Larva";199;0
"Unit";"Overlord";"Larva";199;0
"Unit";"Overlord";"Larva";199;0
"Building";"CreepTumor";NA;199;0
"Unit";"Overlord";"Larva";199;0
"Unit";"Overlord";"Larva";199;0
"Building";"CreepTumor";NA;199;0
"Unit";"Overlord";"Larva";199;0
"Building";"CreepTumor";NA;199;0
"Building";"CreepTumor";NA;199;0
"Building";"CreepTumor";NA;199;0
"Building";"CreepTumorQueen";NA;199;0
"Building";"CreepTumorQueen";NA;199;0
"Building";"CreepTumorQueen";NA;199;0
"Unit";"Zergling";"Larva";199;1
"Unit";"Zergling";"Larva";199;1
"Unit";"Zergling";"Larva";199;1
"Unit";"Zergling";"Larva";199;1
"Unit";"Zergling";"Larva";199;1
"Unit";"Zergling";"Larva";199;1
"Unit";"Zergling";"Larva";199;1
"Unit";"Zergling";"Larva";199;1
"Unit";"Zergling";"Larva";199;1
"Unit";"Zergling";"Larva";199;1
"Unit";"Zergling";"Larva";199;1
"Unit";"Zergling";"Larva";199;1
"Unit";"Zergling";"Larva";199;1
"Unit";"Zergling";"Larva";199;1
"Unit";"Zergling";"Larva";199;1
"Unit";"Zergling";"Larva";199;1
"Building";"CreepTumor";NA;210;0
"Unit";"Zergling";"Larva";199;1
"Unit";"Zergling";"Larva";199;1
"Building";"SporeCrawler";NA;210;0
"Unit";"Baneling";"Zergling";210;0
"Unit";"Baneling";"Zergling";210;0
"Unit";"Baneling";"Zergling";210;0
"Unit";"Baneling";"Zergling";210;0
"Unit";"Baneling";"Zergling";212;0
"Unit";"Baneling";"Zergling";212;0
"Unit";"Baneling";"Zergling";212;0
"Unit";"Baneling";"Zergling";220;0
"Unit";"Baneling";"Zergling";228;0
"Unit";"Baneling";"Zergling";228;0
"Upgrade";"EvolveGroovedSpines";"HydraliskDen";199;0
"Unit";"Zergling";"Larva";228;1
"Unit";"Zergling";"Larva";228;1
"Unit";"Zergling";"Larva";228;1
"Unit";"Zergling";"Larva";228;1
"Unit";"Zergling";"Larva";228;1
"Unit";"Zergling";"Larva";228;1
"Unit";"Zergling";"Larva";228;1
"Unit";"Zergling";"Larva";228;1
"Unit";"Zergling";"Larva";228;1
"Unit";"Zergling";"Larva";228;1
"Building";"Hatchery";NA;199;0
"Unit";"Zergling";"Larva";228;1
"Unit";"Zergling";"Larva";228;1
"Unit";"Zergling";"Larva";228;1
"Unit";"Zergling";"Larva";228;1
"Unit";"Zergling";"Larva";228;1
"Unit";"Zergling";"Larva";228;1
"Unit";"Zergling";"Larva";228;1
"Unit";"Zergling";"Larva";228;1
"Unit";"Zergling";"Larva";228;1
"Unit";"Zergling";"Larva";228;1
"Unit";"Zergling";"Larva";228;1
"Unit";"Zergling";"Larva";228;1
"Unit";"Zergling";"Larva";228;1
"Unit";"Zergling";"Larva";228;1
"Unit";"Zergling";"Larva";228;1
"Unit";"Zergling";"Larva";228;1
"Unit";"Zergling";"Larva";228;1
"Unit";"Zergling";"Larva";228;1
"Unit";"Zergling";"Larva";256;1
"Unit";"Zergling";"Larva";256;1
"Unit";"Zergling";"Larva";256;1
"Unit";"Zergling";"Larva";256;1
"Unit";"Zergling";"Larva";256;1
"Unit";"Zergling";"Larva";256;1
"Unit";"Zergling";"Larva";256;1
"Unit";"Zergling";"Larva";256;1
"Unit";"Zergling";"Larva";256;1
"Unit";"Zergling";"Larva";256;1
"Unit";"Zergling";"Larva";256;1
"Unit";"Zergling";"Larva";256;1
"Unit";"Zergling";"Larva";256;1
"Unit";"Zergling";"Larva";256;1
"Unit";"Zergling";"Larva";256;1
"Unit";"Zergling";"Larva";256;1
"Unit";"Zergling";"Larva";256;1
"Unit";"Zergling";"Larva";256;1
"Unit";"Zergling";"Larva";256;1
"Unit";"Zergling";"Larva";256;1
"Unit";"Zergling";"Larva";256;1
"Unit";"Zergling";"Larva";256;1
"Unit";"Zergling";"Larva";256;1
"Unit";"Zergling";"Larva";256;1
"Unit";"Zergling";"Larva";256;1
"Unit";"Zergling";"Larva";256;1
"Unit";"Zergling";"Larva";256;1
"Unit";"Zergling";"Larva";256;1
"Unit";"Zergling";"Larva";256;1
"Unit";"Zergling";"Larva";256;1
"Unit";"Baneling";"Zergling";256;0
"Unit";"Baneling";"Zergling";256;0
"Unit";"Baneling";"Zergling";256;0
"Unit";"Baneling";"Zergling";256;0
"Unit";"Baneling";"Zergling";256;0
"Unit";"Baneling";"Zergling";256;0
"Unit";"Baneling";"Zergling";256;0
"Unit";"Baneling";"Zergling";256;0
"Unit";"Baneling";"Zergling";256;0
"Unit";"Baneling";"Zergling";256;0
"Unit";"Baneling";"Zergling";256;0
"Unit";"Baneling";"Zergling";256;0
"Unit";"Baneling";"Zergling";256;0
"Unit";"Baneling";"Zergling";256;0
"Unit";"Hydralisk";"Larva";256;2
"Unit";"Hydralisk";"Larva";256;2
"Unit";"Hydralisk";"Larva";256;2
"Unit";"Hydralisk";"Larva";256;2
"Unit";"Hydralisk";"Larva";256;2
"Unit";"Hydralisk";"Larva";256;2
"Unit";"Hydralisk";"Larva";256;2
"Unit";"Hydralisk";"Larva";256;2
"Unit";"Hydralisk";"Larva";256;2
"Building";"CreepTumor";NA;304;0
"Building";"CreepTumor";NA;304;0
"Unit";"Hydralisk";"Larva";286;2
"Unit";"Hydralisk";"Larva";286;2
"Unit";"Hydralisk";"Larva";286;2
"Unit";"Hydralisk";"Larva";286;2
"Unit";"Hydralisk";"Larva";286;2
"Unit";"Hydralisk";"Larva";286;2
"Unit";"Hydralisk";"Larva";286;2
"Unit";"Hydralisk";"Larva";286;2
"Unit";"Hydralisk";"Larva";286;2
"Unit";"Hydralisk";"Larva";286;2
"Unit";"Baneling";"Zergling";304;0
"Unit";"Baneling";"Zergling";304;0
"Unit";"Baneling";"Zergling";304;0
"Unit";"Baneling";"Zergling";304;0
"Unit";"Baneling";"Zergling";304;0
"Unit";"Baneling";"Zergling";304;0
"Unit";"Baneling";"Zergling";304;0
"Unit";"Baneling";"Zergling";304;0
"Unit";"Baneling";"Zergling";304;0
"Unit";"Baneling";"Zergling";304;0
"Unit";"Zergling";"Larva";304;1
"Unit";"Zergling";"Larva";304;1
"Unit";"Zergling";"Larva";304;1
"Unit";"Zergling";"Larva";304;1
"Unit";"Zergling";"Larva";304;1
"Unit";"Zergling";"Larva";304;1
"Unit";"Zergling";"Larva";304;1
"Unit";"Zergling";"Larva";304;1
"Unit";"Zergling";"Larva";304;1
"Unit";"Zergling";"Larva";304;1
"Unit";"Zergling";"Larva";304;1
"Unit";"Zergling";"Larva";304;1
"Unit";"Zergling";"Larva";304;1
"Unit";"Zergling";"Larva";304;1
"Unit";"Zergling";"Larva";304;1
"Unit";"Zergling";"Larva";304;1
"Unit";"Zergling";"Larva";304;1
"Unit";"Zergling";"Larva";304;1
"Unit";"Zergling";"Larva";304;1
"Unit";"Zergling";"Larva";304;1
"Building";"Extractor";NA;324;0
"Building";"Extractor";NA;324;0
"Unit";"Zergling";"Larva";344;1
"Unit";"Zergling";"Larva";344;1
"Unit";"Zergling";"Larva";344;1
"Unit";"Zergling";"Larva";344;1
"Unit";"Zergling";"Larva";344;1
"Unit";"Zergling";"Larva";344;1
"Unit";"Zergling";"Larva";344;1
"Unit";"Zergling";"Larva";344;1
"Unit";"Zergling";"Larva";344;1
"Unit";"Zergling";"Larva";344;1
"Unit";"Zergling";"Larva";344;1
"Unit";"Zergling";"Larva";344;1
"Unit";"Zergling";"Larva";344;1
"Unit";"Zergling";"Larva";344;1
"Unit";"Zergling";"Larva";344;1
"Unit";"Zergling";"Larva";344;1
"Unit";"Zergling";"Larva";344;1
"Unit";"Zergling";"Larva";344;1
"Unit";"Zergling";"Larva";344;1
"Unit";"Zergling";"Larva";344;1
"Unit";"Zergling";"Larva";344;1
"Unit";"Zergling";"Larva";344;1
"Unit";"Zergling";"Larva";344;1
"Unit";"Zergling";"Larva";344;1
"Unit";"Zergling";"Larva";344;1
"Unit";"Zergling";"Larva";344;1
"Unit";"Zergling";"Larva";344;1
"Unit";"Zergling";"Larva";344;1
"Unit";"Zergling";"Larva";344;1
"Unit";"Zergling";"Larva";344;1
"Unit";"Zergling";"Larva";344;1
"Unit";"Zergling";"Larva";344;1
"Unit";"Zergling";"Larva";344;1
"Unit";"Zergling";"Larva";344;1
"Unit";"Zergling";"Larva";344;1
"Unit";"Zergling";"Larva";344;1
"Unit";"Zergling";"Larva";344;1
"Unit";"Zergling";"Larva";344;1
"Unit";"Zergling";"Larva";344;1
"Unit";"Zergling";"Larva";344;1
"Unit";"Zergling";"Larva";344;1
"Unit";"Zergling";"Larva";344;1
"Unit";"Zergling";"Larva";344;1
"Unit";"Zergling";"Larva";344;1
"Upgrade";"ZergMissileWeaponsLevel2";"EvolutionChamber";256;0
"Unit";"Zergling";"Larva";344;1
"Unit";"Zergling";"Larva";344;1
"Unit";"Zergling";"Larva";344;1
"Unit";"Zergling";"Larva";344;1
"Unit";"Zergling";"Larva";344;1
"Unit";"Zergling";"Larva";344;1
"Unit";"Zergling";"Larva";344;1
"Unit";"Zergling";"Larva";344;1
"Unit";"Zergling";"Larva";344;1
"Unit";"Zergling";"Larva";344;1
"Unit";"Zergling";"Larva";344;1
"Unit";"Zergling";"Larva";344;1
"Upgrade";"ZergGroundArmorsLevel2";"EvolutionChamber";256;0
"Unit";"Zergling";"Larva";344;1
"Unit";"Zergling";"Larva";344;1
"Unit";"Zergling";"Larva";344;1
"Unit";"Zergling";"Larva";344;1
"Unit";"Zergling";"Larva";344;1
"Unit";"Zergling";"Larva";344;1
"Unit";"Zergling";"Larva";344;1
"Unit";"Zergling";"Larva";344;1
"Unit";"Zergling";"Larva";344;1
"Unit";"Zergling";"Larva";344;1
"Unit";"Zergling";"Larva";344;1
"Unit";"Zergling";"Larva";344;1
"Unit";"Baneling";"Zergling";412;0
"Unit";"Baneling";"Zergling";412;0
"Unit";"Baneling";"Zergling";412;0
"Unit";"Baneling";"Zergling";412;0
"Unit";"Baneling";"Zergling";412;0
"Unit";"Baneling";"Zergling";412;0
"Unit";"Baneling";"Zergling";412;0
"Unit";"Baneling";"Zergling";412;0
"Unit";"Baneling";"Zergling";412;0
"Unit";"Hydralisk";"Larva";386;2
"Unit";"Hydralisk";"Larva";386;2
"Unit";"Hydralisk";"Larva";386;2
"Unit";"Hydralisk";"Larva";386;2
"Unit";"Hydralisk";"Larva";386;2
"Unit";"Hydralisk";"Larva";386;2
"Unit";"Hydralisk";"Larva";386;2
"Unit";"Hydralisk";"Larva";386;2
"Unit";"Zergling";"Larva";428;1
"Unit";"Zergling";"Larva";428;1
"Unit";"Zergling";"Larva";428;1
"Unit";"Zergling";"Larva";428;1
"Unit";"Zergling";"Larva";428;1
"Unit";"Zergling";"Larva";428;1
"Unit";"Zergling";"Larva";428;1
"Unit";"Zergling";"Larva";428;1
"Unit";"Zergling";"Larva";428;1
"Unit";"Zergling";"Larva";428;1
"Unit";"Zergling";"Larva";428;1
"Unit";"Zergling";"Larva";428;1
"Unit";"Zergling";"Larva";428;1
"Unit";"Zergling";"Larva";428;1
"Unit";"Zergling";"Larva";428;1
"Unit";"Zergling";"Larva";428;1
"Unit";"Zergling";"Larva";428;1
"Unit";"Zergling";"Larva";428;1
"Unit";"Zergling";"Larva";428;1
"Unit";"Zergling";"Larva";428;1
"Unit";"Zergling";"Larva";428;1
"Unit";"Zergling";"Larva";428;1
"Unit";"Zergling";"Larva";428;1
"Unit";"Zergling";"Larva";428;1
"Unit";"Zergling";"Larva";428;1
"Unit";"Zergling";"Larva";428;1
"Unit";"Zergling";"Larva";428;1
"Unit";"Zergling";"Larva";428;1
"Unit";"Zergling";"Larva";428;1
"Unit";"Zergling";"Larva";428;1
"Unit";"Zergling";"Larva";428;1
"Unit";"Zergling";"Larva";428;1
"Unit";"Zergling";"Larva";428;1
"Unit";"Zergling";"Larva";428;1
"Unit";"Zergling";"Larva";428;1
"Unit";"Zergling";"Larva";428;1
"Unit";"Zergling";"Larva";428;1
"Unit";"Zergling";"Larva";428;1
"Unit";"Zergling";"Larva";428;1
"Unit";"Zergling";"Larva";428;1
"Unit";"Zergling";"Larva";428;1
"Unit";"Zergling";"Larva";428;1
"Unit";"Zergling";"Larva";428;1
"Unit";"Zergling";"Larva";428;1
"Unit";"Zergling";"Larva";428;1
"Unit";"Zergling";"Larva";428;1
"Unit";"Zergling";"Larva";428;1
"Unit";"Zergling";"Larva";428;1
"Unit";"Zergling";"Larva";428;1
"Unit";"Zergling";"Larva";428;1
"Unit";"Zergling";"Larva";428;1
"Unit";"Zergling";"Larva";428;1
"Unit";"Zergling";"Larva";428;1
"Unit";"Zergling";"Larva";428;1
"Unit";"Zergling";"Larva";428;1
"Unit";"Zergling";"Larva";428;1
"Unit";"Zergling";"Larva";428;1
"Unit";"Zergling";"Larva";428;1
"Unit";"Zergling";"Larva";428;1
"Unit";"Zergling";"Larva";428;1
"Unit";"Zergling";"Larva";428;1
"Unit";"Zergling";"Larva";428;1
"Unit";"Zergling";"Larva";428;1
"Unit";"Zergling";"Larva";428;1
"Unit";"Zergling";"Larva";428;1
"Unit";"Zergling";"Larva";428;1
"Unit";"Zergling";"Larva";428;1
"Unit";"Zergling";"Larva";428;1
"Unit";"Zergling";"Larva";428;1
"Unit";"Zergling";"Larva";428;1
"Unit";"Zergling";"Larva";428;1
"Unit";"Zergling";"Larva";428;1
