"type";"unit_name";"on_building";"total_supply";"supply"
"Unit";"Overlord";"Larva";13;0
"Building";"Extractor";NA;19;0
"Unit";"Overlord";"Larva";21;0
"Building";"SpawningPool";NA;19;0
"Building";"Hatchery";NA;17;0
"Unit";"Zergling";"Larva";22;1
"Unit";"Zergling";"Larva";22;1
"Unit";"Zergling";"Larva";22;1
"Unit";"Zergling";"Larva";22;1
"Unit";"Queen";"Hatchery";22;2
"Unit";"Queen";"Hatchery";22;2
"Unit";"Overlord";"Larva";36;0
"Building";"CreepTumorQueen";NA;39;0
"Unit";"Queen";"Hatchery";34;2
"Unit";"Overlord";"Larva";40;0
"Building";"Hatchery";NA;32;0
"Building";"CreepTumorQueen";NA;50;0
"Building";"CreepTumor";NA;50;0
"Unit";"Queen";"Hatchery";46;2
"Unit";"Queen";"Hatchery";46;2
"Unit";"Overlord";"Larva";50;0
"Unit";"Zergling";"Larva";50;1
"Unit";"Zergling";"Larva";50;1
"Building";"CreepTumorQueen";NA;62;0
"Building";"CreepTumorQueen";NA;62;0
"Unit";"Queen";"Hatchery";50;2
"Unit";"Overlord";"Larva";62;0
"Unit";"Overlord";"Larva";62;0
"Unit";"Overlord";"Larva";62;0
"Building";"CreepTumorQueen";NA;64;0
"Building";"CreepTumorQueen";NA;64;0
"Building";"Extractor";NA;73;0
"Building";"Extractor";NA;73;0
"Building";"EvolutionChamber";NA;73;0
"Building";"EvolutionChamber";NA;73;0
"Building";"CreepTumor";NA;79;0
"Building";"CreepTumorQueen";NA;83;0
"Building";"CreepTumor";NA;82;0
"Building";"CreepTumorQueen";NA;85;0
"Building";"CreepTumor";NA;86;0
"Building";"CreepTumor";NA;86;0
"Building";"CreepTumor";NA;86;0
"Unit";"Zergling";"Larva";88;1
"Unit";"Zergling";"Larva";88;1
"Unit";"Zergling";"Larva";88;1
"Unit";"Zergling";"Larva";88;1
"Unit";"Zergling";"Larva";88;1
"Unit";"Zergling";"Larva";88;1
"Unit";"Zergling";"Larva";88;1
"Unit";"Zergling";"Larva";88;1
"Unit";"Zergling";"Larva";88;1
"Unit";"Zergling";"Larva";88;1
"Unit";"Zergling";"Larva";88;1
"Unit";"Zergling";"Larva";88;1
"Unit";"Overlord";"Larva";88;0
"Unit";"Overlord";"Larva";88;0
"Unit";"Overlord";"Larva";88;0
"Unit";"Overlord";"Larva";88;0
"Unit";"Overlord";"Larva";88;0
"Building";"CreepTumor";NA;100;0
"Building";"CreepTumor";NA;100;0
"Building";"CreepTumor";NA;100;0
"Building";"CreepTumor";NA;100;0
"Building";"CreepTumor";NA;100;0
"Building";"CreepTumor";NA;100;0
"Building";"Extractor";NA;88;0
"Building";"Extractor";NA;88;0
"Building";"CreepTumorQueen";NA;102;0
"Building";"CreepTumor";NA;102;0
"Building";"CreepTumorQueen";NA;102;0
"Building";"CreepTumorQueen";NA;102;0
"Unit";"Zergling";"Larva";102;1
"Unit";"Zergling";"Larva";102;1
"Unit";"Zergling";"Larva";102;1
"Unit";"Zergling";"Larva";102;1
"Unit";"Zergling";"Larva";102;1
"Unit";"Zergling";"Larva";102;1
"Unit";"Zergling";"Larva";102;1
"Unit";"Zergling";"Larva";102;1
"Unit";"Zergling";"Larva";102;1
"Unit";"Zergling";"Larva";102;1
"Unit";"Zergling";"Larva";102;1
"Unit";"Zergling";"Larva";102;1
"Unit";"Zergling";"Larva";102;1
"Unit";"Zergling";"Larva";102;1
"Unit";"Zergling";"Larva";102;1
"Unit";"Zergling";"Larva";102;1
"Unit";"Zergling";"Larva";102;1
"Unit";"Zergling";"Larva";102;1
"Building";"Hatchery";NA;73;0
"Building";"BanelingNest";NA;88;0
"Unit";"Zergling";"Larva";126;1
"Unit";"Zergling";"Larva";126;1
"Building";"CreepTumor";NA;129;0
"Unit";"Zergling";"Larva";126;1
"Unit";"Zergling";"Larva";126;1
"Unit";"Zergling";"Larva";126;1
"Unit";"Zergling";"Larva";126;1
"Building";"CreepTumor";NA;129;0
"Building";"CreepTumor";NA;129;0
"Unit";"Zergling";"Larva";129;1
"Unit";"Zergling";"Larva";129;1
"Unit";"Zergling";"Larva";129;1
"Unit";"Zergling";"Larva";129;1
"Unit";"Zergling";"Larva";129;1
"Unit";"Zergling";"Larva";129;1
"Unit";"Zergling";"Larva";129;1
"Unit";"Zergling";"Larva";129;1
"Building";"CreepTumorQueen";NA;135;0
"Unit";"Queen";"Hatchery";126;2
"Building";"CreepTumorQueen";NA;135;0
"Unit";"Baneling";"Zergling";135;0
"Unit";"Zergling";"Larva";135;1
"Unit";"Zergling";"Larva";135;1
"Unit";"Baneling";"Zergling";135;0
"Unit";"Baneling";"Zergling";135;0
"Unit";"Baneling";"Zergling";135;0
"Unit";"Baneling";"Zergling";135;0
"Unit";"Baneling";"Zergling";135;0
"Unit";"Baneling";"Zergling";135;0
"Unit";"Zergling";"Larva";135;1
"Unit";"Zergling";"Larva";135;1
"Unit";"Zergling";"Larva";135;1
"Unit";"Zergling";"Larva";135;1
"Unit";"Zergling";"Larva";135;1
"Unit";"Zergling";"Larva";135;1
"Unit";"Zergling";"Larva";135;1
"Unit";"Zergling";"Larva";135;1
"Unit";"Zergling";"Larva";135;1
"Unit";"Zergling";"Larva";135;1
"Unit";"Zergling";"Larva";135;1
"Unit";"Zergling";"Larva";135;1
"Building";"SporeCrawler";NA;135;0
"Building";"CreepTumorQueen";NA;143;0
"Building";"CreepTumorQueen";NA;143;0
"Building";"CreepTumor";NA;143;0
"Building";"HydraliskDen";NA;129;0
"Building";"CreepTumor";NA;144;0
"Building";"CreepTumor";NA;144;0
"Building";"CreepTumor";NA;144;0
"Building";"CreepTumor";NA;144;0
"Building";"CreepTumor";NA;144;0
"Building";"CreepTumor";NA;144;0
"Unit";"Zergling";"Larva";144;1
"Unit";"Zergling";"Larva";144;1
"Unit";"Zergling";"Larva";144;1
"Unit";"Zergling";"Larva";144;1
"Unit";"Zergling";"Larva";144;1
"Unit";"Zergling";"Larva";144;1
"Unit";"Zergling";"Larva";144;1
"Unit";"Zergling";"Larva";144;1
"Unit";"Zergling";"Larva";144;1
"Unit";"Zergling";"Larva";144;1
"Unit";"Zergling";"Larva";144;1
"Unit";"Zergling";"Larva";144;1
"Building";"SpineCrawler";NA;135;0
"Building";"SpineCrawler";NA;135;0
"Unit";"Overlord";"Larva";160;0
"Unit";"Overlord";"Larva";160;0
"Unit";"Overlord";"Larva";160;0
"Unit";"Overlord";"Larva";160;0
"Unit";"Overlord";"Larva";160;0
"Upgrade";"ZergMeleeWeaponsLevel1";"EvolutionChamber";102;0
"Unit";"Overlord";"Larva";160;0
"Building";"CreepTumorQueen";NA;160;0
"Building";"Hatchery";NA;102;0
"Building";"CreepTumorQueen";NA;172;0
"Building";"CreepTumor";NA;172;0
"Building";"CreepTumor";NA;172;0
"Building";"CreepTumor";NA;172;0
"Upgrade";"ZergGroundArmorsLevel1";"EvolutionChamber";102;0
"Building";"CreepTumor";NA;172;0
"Building";"SporeCrawler";NA;160;0
"Building";"CreepTumor";NA;172;0
"Building";"CreepTumor";NA;172;0
"Building";"CreepTumor";NA;172;0
"Unit";"Hydralisk";"Larva";172;2
"Building";"CreepTumor";NA;172;0
"Building";"CreepTumor";NA;172;0
"Unit";"Hydralisk";"Larva";172;2
"Building";"CreepTumor";NA;172;0
"Building";"CreepTumor";NA;172;0
"Building";"CreepTumor";NA;172;0
"Unit";"Zergling";"Larva";172;1
"Unit";"Zergling";"Larva";172;1
"Building";"CreepTumor";NA;172;0
"Unit";"Zergling";"Larva";172;1
"Unit";"Zergling";"Larva";172;1
"Unit";"Zergling";"Larva";172;1
"Unit";"Zergling";"Larva";172;1
"Unit";"Zergling";"Larva";172;1
"Unit";"Zergling";"Larva";172;1
"Unit";"Zergling";"Larva";172;1
"Unit";"Zergling";"Larva";172;1
"Unit";"Zergling";"Larva";172;1
"Unit";"Zergling";"Larva";172;1
"Unit";"Zergling";"Larva";172;1
"Unit";"Zergling";"Larva";172;1
"Unit";"Zergling";"Larva";172;1
"Unit";"Zergling";"Larva";172;1
"Unit";"Zergling";"Larva";172;1
"Unit";"Zergling";"Larva";172;1
"Building";"CreepTumor";NA;172;0
"Unit";"Overlord";"Larva";172;0
"Unit";"Overlord";"Larva";172;0
"Unit";"Overlord";"Larva";172;0
"Unit";"Overlord";"Larva";172;0
"Unit";"Hydralisk";"Larva";172;2
"Unit";"Hydralisk";"Larva";172;2
"Unit";"Hydralisk";"Larva";172;2
"Unit";"Hydralisk";"Larva";172;2
"Unit";"Hydralisk";"Larva";172;2
"Building";"CreepTumor";NA;194;0
"Building";"CreepTumor";NA;194;0
"Building";"CreepTumor";NA;194;0
"Building";"Extractor";NA;194;0
"Upgrade";"EvolveGroovedSpines";"HydraliskDen";172;0
"Unit";"Queen";"Hatchery";176;2
"Building";"InfestationPit";NA;194;0
"Building";"CreepTumor";NA;215;0
"Building";"CreepTumor";NA;215;0
"Building";"CreepTumor";NA;216;0
"Building";"CreepTumor";NA;219;0
"Building";"CreepTumor";NA;221;0
"Building";"CreepTumor";NA;221;0
"Building";"CreepTumor";NA;221;0
"Building";"CreepTumorQueen";NA;221;0
"Building";"CreepTumor";NA;221;0
"Building";"CreepTumor";NA;221;0
"Building";"CreepTumor";NA;221;0
"Unit";"Hydralisk";"Larva";211;2
"Unit";"Hydralisk";"Larva";211;2
"Building";"CreepTumorQueen";NA;221;0
"Building";"CreepTumor";NA;221;0
"Building";"CreepTumor";NA;221;0
"Building";"CreepTumorQueen";NA;221;0
"Building";"CreepTumor";NA;221;0
"Building";"CreepTumor";NA;221;0
"Building";"CreepTumor";NA;221;0
"Building";"CreepTumor";NA;221;0
"Unit";"Baneling";"Zergling";223;0
"Unit";"Baneling";"Zergling";225;0
"Unit";"Baneling";"Zergling";225;0
"Unit";"Baneling";"Zergling";225;0
"Unit";"Baneling";"Zergling";225;0
"Unit";"Baneling";"Zergling";225;0
"Unit";"Baneling";"Zergling";225;0
"Unit";"Hydralisk";"Larva";221;2
"Unit";"Hydralisk";"Larva";221;2
"Unit";"Hydralisk";"Larva";221;2
"Unit";"Hydralisk";"Larva";221;2
"Unit";"Hydralisk";"Larva";221;2
"Unit";"Hydralisk";"Larva";221;2
"Unit";"Hydralisk";"Larva";221;2
"Unit";"Hydralisk";"Larva";221;2
"Unit";"Hydralisk";"Larva";221;2
"Unit";"Hydralisk";"Larva";221;2
"Upgrade";"EvolveMuscularAugments";"HydraliskDen";221;0
"Building";"InfestationPit";NA;225;0
"Unit";"Hydralisk";"Larva";245;2
"Unit";"Hydralisk";"Larva";245;2
"Unit";"Hydralisk";"Larva";245;2
"Unit";"Hydralisk";"Larva";245;2
"Unit";"Hydralisk";"Larva";245;2
"Unit";"Hydralisk";"Larva";245;2
"Building";"EvolutionChamber";NA;245;0
"Unit";"Overlord";"Larva";257;0
"Upgrade";"ZergMeleeWeaponsLevel2";"EvolutionChamber";221;0
"Unit";"Overlord";"Larva";257;0
"Upgrade";"ZergGroundArmorsLevel2";"EvolutionChamber";221;0
"Building";"CreepTumor";NA;257;0
"Building";"CreepTumor";NA;257;0
"Building";"Hatchery";NA;245;0
"Building";"Extractor";NA;257;0
"Building";"Extractor";NA;257;0
"Building";"CreepTumor";NA;257;0
"Unit";"Baneling";"Zergling";257;0
"Building";"SporeCrawler";NA;257;0
"Unit";"Baneling";"Zergling";257;0
"Unit";"Baneling";"Zergling";257;0
"Unit";"Baneling";"Zergling";257;0
"Unit";"Baneling";"Zergling";257;0
"Unit";"Baneling";"Zergling";257;0
"Unit";"Baneling";"Zergling";257;0
"Unit";"Baneling";"Zergling";257;0
"Unit";"Baneling";"Zergling";257;0
"Unit";"Baneling";"Zergling";257;0
"Unit";"Baneling";"Zergling";257;0
"Unit";"Baneling";"Zergling";257;0
"Unit";"Baneling";"Zergling";257;0
"Unit";"Baneling";"Zergling";257;0
"Unit";"Baneling";"Zergling";257;0
"Unit";"Baneling";"Zergling";257;0
"Unit";"Baneling";"Zergling";257;0
"Unit";"Baneling";"Zergling";257;0
"Unit";"Baneling";"Zergling";257;0
"Unit";"Baneling";"Zergling";257;0
"Unit";"Zergling";"Larva";257;1
"Unit";"Zergling";"Larva";257;1
"Unit";"Zergling";"Larva";257;1
"Unit";"Zergling";"Larva";257;1
"Unit";"Zergling";"Larva";257;1
"Unit";"Zergling";"Larva";257;1
"Unit";"Zergling";"Larva";257;1
"Unit";"Zergling";"Larva";257;1
"Unit";"Zergling";"Larva";257;1
"Unit";"Zergling";"Larva";257;1
"Unit";"Zergling";"Larva";257;1
"Unit";"Zergling";"Larva";257;1
"Unit";"Zergling";"Larva";257;1
"Unit";"Zergling";"Larva";257;1
"Unit";"Zergling";"Larva";257;1
"Unit";"Zergling";"Larva";257;1
"Unit";"Zergling";"Larva";257;1
"Unit";"Zergling";"Larva";257;1
"Unit";"Zergling";"Larva";257;1
"Unit";"Zergling";"Larva";257;1
"Unit";"Zergling";"Larva";257;1
"Unit";"Zergling";"Larva";257;1
"Unit";"Zergling";"Larva";257;1
"Unit";"Zergling";"Larva";257;1
"Unit";"Zergling";"Larva";257;1
"Unit";"Zergling";"Larva";257;1
"Unit";"Zergling";"Larva";257;1
"Unit";"Zergling";"Larva";257;1
"Unit";"Zergling";"Larva";257;1
"Unit";"Zergling";"Larva";257;1
"Unit";"Zergling";"Larva";257;1
"Unit";"Zergling";"Larva";257;1
"Unit";"Zergling";"Larva";257;1
"Unit";"Zergling";"Larva";257;1
"Unit";"Zergling";"Larva";257;1
"Unit";"Zergling";"Larva";257;1
"Unit";"Zergling";"Larva";257;1
"Unit";"Zergling";"Larva";257;1
"Unit";"Zergling";"Larva";257;1
"Unit";"Zergling";"Larva";257;1
"Unit";"Zergling";"Larva";257;1
"Unit";"Zergling";"Larva";257;1
"Unit";"Zergling";"Larva";257;1
"Unit";"Zergling";"Larva";257;1
"Unit";"Zergling";"Larva";257;1
"Unit";"Zergling";"Larva";257;1
"Unit";"Zergling";"Larva";257;1
"Unit";"Zergling";"Larva";257;1
"Unit";"Zergling";"Larva";257;1
"Unit";"Zergling";"Larva";257;1
"Unit";"Zergling";"Larva";257;1
"Unit";"Zergling";"Larva";257;1
"Unit";"Zergling";"Larva";257;1
"Unit";"Zergling";"Larva";257;1
"Building";"SporeCrawler";NA;257;0
"Building";"SpineCrawler";NA;257;0
"Building";"SpineCrawler";NA;257;0
"Building";"SporeCrawler";NA;257;0
"Unit";"Zergling";"Larva";318;1
"Unit";"Zergling";"Larva";318;1
"Unit";"Zergling";"Larva";318;1
"Unit";"Zergling";"Larva";318;1
"Unit";"Zergling";"Larva";318;1
"Unit";"Zergling";"Larva";318;1
"Unit";"Zergling";"Larva";318;1
"Unit";"Zergling";"Larva";318;1
"Unit";"Zergling";"Larva";318;1
"Unit";"Zergling";"Larva";318;1
"Unit";"Zergling";"Larva";318;1
"Unit";"Zergling";"Larva";318;1
"Unit";"Zergling";"Larva";318;1
"Unit";"Zergling";"Larva";318;1
"Unit";"Zergling";"Larva";318;1
"Unit";"Zergling";"Larva";318;1
"Unit";"Zergling";"Larva";318;1
"Unit";"Zergling";"Larva";318;1
"Unit";"Zergling";"Larva";318;1
"Unit";"Zergling";"Larva";318;1
"Unit";"Zergling";"Larva";318;1
"Unit";"Zergling";"Larva";318;1
"Unit";"Zergling";"Larva";318;1
"Unit";"Zergling";"Larva";318;1
"Unit";"Zergling";"Larva";318;1
"Unit";"Zergling";"Larva";318;1
"Unit";"Zergling";"Larva";318;1
"Unit";"Zergling";"Larva";318;1
"Unit";"Zergling";"Larva";318;1
"Unit";"Zergling";"Larva";318;1
"Unit";"Zergling";"Larva";318;1
"Unit";"Zergling";"Larva";318;1
"Unit";"Zergling";"Larva";318;1
"Unit";"Zergling";"Larva";318;1
"Unit";"Zergling";"Larva";318;1
"Unit";"Zergling";"Larva";318;1
"Unit";"Zergling";"Larva";318;1
"Unit";"Zergling";"Larva";318;1
"Building";"Hatchery";NA;257;0
"Building";"CreepTumorQueen";NA;318;0
"Unit";"Baneling";"Zergling";318;0
"Unit";"Baneling";"Zergling";318;0
"Unit";"Baneling";"Zergling";318;0
"Unit";"Baneling";"Zergling";318;0
"Unit";"Baneling";"Zergling";318;0
"Unit";"Baneling";"Zergling";318;0
"Unit";"Baneling";"Zergling";318;0
"Unit";"Baneling";"Zergling";318;0
"Unit";"Baneling";"Zergling";318;0
"Unit";"Baneling";"Zergling";318;0
"Unit";"Baneling";"Zergling";318;0
"Building";"CreepTumorQueen";NA;318;0
"Building";"CreepTumorQueen";NA;318;0
"Building";"CreepTumorQueen";NA;356;0
"Building";"CreepTumorQueen";NA;356;0
