"type";"unit_name";"on_building";"total_supply";"supply"
"Unit";"Overlord";"Larva";12;0
"Building";"SpawningPool";NA;19;0
"Building";"Hatchery";NA;17;0
"Building";"Extractor";NA;22;0
"Unit";"Zergling";"Larva";24;1
"Unit";"Zergling";"Larva";24;1
"Unit";"Zergling";"Larva";24;1
"Unit";"Zergling";"Larva";24;1
"Unit";"Queen";"Hatchery";24;2
"Building";"Hatchery";NA;21;0
"Unit";"Overlord";"Larva";28;0
"Unit";"Queen";"Hatchery";28;2
"Unit";"Overlord";"Larva";32;0
"Unit";"Overlord";"Larva";39;0
"Unit";"Queen";"Hatchery";32;2
"Building";"EvolutionChamber";NA;35;0
"Unit";"Overlord";"Larva";47;0
"Building";"Extractor";NA;50;0
"Unit";"Zergling";"Larva";50;1
"Unit";"Zergling";"Larva";50;1
"Unit";"Zergling";"Larva";50;1
"Unit";"Zergling";"Larva";50;1
"Unit";"Zergling";"Larva";50;1
"Unit";"Zergling";"Larva";50;1
"Building";"EvolutionChamber";NA;50;0
"Unit";"Queen";"Hatchery";50;2
"Unit";"Queen";"Hatchery";50;2
"Unit";"Zergling";"Larva";53;1
"Unit";"Zergling";"Larva";53;1
"Unit";"Zergling";"Larva";53;1
"Unit";"Zergling";"Larva";53;1
"Unit";"Zergling";"Larva";53;1
"Unit";"Zergling";"Larva";53;1
"Unit";"Zergling";"Larva";53;1
"Unit";"Zergling";"Larva";53;1
"Unit";"Overlord";"Larva";63;0
"Building";"CreepTumorQueen";NA;72;0
"Building";"CreepTumorQueen";NA;72;0
"Unit";"Zergling";"Larva";72;1
"Unit";"Zergling";"Larva";72;1
"Unit";"Zergling";"Larva";72;1
"Unit";"Zergling";"Larva";72;1
"Unit";"Overlord";"Larva";72;0
"Unit";"Zergling";"Larva";76;1
"Unit";"Zergling";"Larva";76;1
"Unit";"Overlord";"Larva";76;0
"Building";"CreepTumor";NA;80;0
"Building";"CreepTumor";NA;82;0
"Unit";"Zergling";"Larva";82;1
"Unit";"Zergling";"Larva";82;1
"Unit";"Zergling";"Larva";82;1
"Unit";"Zergling";"Larva";82;1
"Unit";"Zergling";"Larva";82;1
"Unit";"Zergling";"Larva";82;1
"Unit";"Zergling";"Larva";82;1
"Unit";"Zergling";"Larva";82;1
"Unit";"Zergling";"Larva";82;1
"Unit";"Zergling";"Larva";82;1
"Unit";"Zergling";"Larva";82;1
"Unit";"Zergling";"Larva";82;1
"Unit";"Zergling";"Larva";82;1
"Unit";"Zergling";"Larva";82;1
"Building";"CreepTumorQueen";NA;82;0
"Unit";"Overlord";"Larva";82;0
"Building";"CreepTumorQueen";NA;82;0
"Upgrade";"ZergGroundArmorsLevel1";"EvolutionChamber";53;0
"Unit";"Overlord";"Larva";99;0
"Building";"CreepTumor";NA;105;0
"Building";"CreepTumor";NA;105;0
"Unit";"Zergling";"Larva";105;1
"Unit";"Zergling";"Larva";105;1
"Unit";"Zergling";"Larva";105;1
"Unit";"Zergling";"Larva";105;1
"Unit";"Zergling";"Larva";105;1
"Unit";"Zergling";"Larva";105;1
"Unit";"Zergling";"Larva";105;1
"Unit";"Zergling";"Larva";105;1
"Unit";"Zergling";"Larva";105;1
"Unit";"Zergling";"Larva";105;1
"Unit";"Zergling";"Larva";105;1
"Unit";"Zergling";"Larva";105;1
"Unit";"Zergling";"Larva";105;1
"Unit";"Zergling";"Larva";105;1
"Unit";"Zergling";"Larva";105;1
"Unit";"Zergling";"Larva";105;1
"Building";"CreepTumor";NA;105;0
"Building";"CreepTumorQueen";NA;105;0
"Building";"BanelingNest";NA;82;0
"Building";"CreepTumorQueen";NA;105;0
"Unit";"Queen";"Hatchery";99;2
"Unit";"Zergling";"Larva";121;1
"Unit";"Zergling";"Larva";121;1
"Unit";"Zergling";"Larva";121;1
"Unit";"Zergling";"Larva";121;1
"Unit";"Zergling";"Larva";121;1
"Unit";"Zergling";"Larva";121;1
"Unit";"Zergling";"Larva";121;1
"Unit";"Zergling";"Larva";121;1
"Unit";"Zergling";"Larva";121;1
"Unit";"Zergling";"Larva";121;1
"Unit";"Zergling";"Larva";121;1
"Unit";"Zergling";"Larva";121;1
"Unit";"Zergling";"Larva";121;1
"Unit";"Zergling";"Larva";121;1
"Unit";"Zergling";"Larva";121;1
"Unit";"Zergling";"Larva";121;1
"Unit";"Zergling";"Larva";121;1
"Unit";"Zergling";"Larva";121;1
"Unit";"Baneling";"Zergling";123;0
"Unit";"Baneling";"Zergling";123;0
"Unit";"Baneling";"Zergling";123;0
"Unit";"Baneling";"Zergling";123;0
"Unit";"Baneling";"Zergling";123;0
"Unit";"Baneling";"Zergling";123;0
"Upgrade";"ZergMeleeWeaponsLevel1";"EvolutionChamber";80;0
"Building";"CreepTumor";NA;141;0
"Unit";"Queen";"Hatchery";123;2
"Building";"CreepTumorQueen";NA;141;0
"Building";"Extractor";NA;141;0
"Building";"Extractor";NA;141;0
"Building";"CreepTumorQueen";NA;148;0
"Building";"SporeCrawler";NA;141;0
"Unit";"Baneling";"Zergling";152;0
"Building";"Extractor";NA;143;0
"Building";"Extractor";NA;148;0
"Building";"CreepTumorQueen";NA;157;0
"Building";"CreepTumor";NA;159;0
"Building";"CreepTumorQueen";NA;164;0
"Building";"CreepTumorQueen";NA;164;0
"Building";"CreepTumor";NA;159;0
"Building";"CreepTumor";NA;163;0
"Building";"CreepTumor";NA;164;0
"Building";"CreepTumor";NA;164;0
"Unit";"Zergling";"Larva";164;1
"Unit";"Zergling";"Larva";164;1
"Unit";"Zergling";"Larva";164;1
"Unit";"Zergling";"Larva";164;1
"Unit";"Zergling";"Larva";164;1
"Unit";"Zergling";"Larva";164;1
"Unit";"Zergling";"Larva";164;1
"Unit";"Zergling";"Larva";164;1
"Unit";"Zergling";"Larva";164;1
"Unit";"Zergling";"Larva";164;1
"Unit";"Zergling";"Larva";164;1
"Unit";"Zergling";"Larva";164;1
"Unit";"Zergling";"Larva";164;1
"Unit";"Zergling";"Larva";164;1
"Unit";"Zergling";"Larva";164;1
"Unit";"Zergling";"Larva";164;1
"Unit";"Overlord";"Larva";164;0
"Unit";"Overlord";"Larva";164;0
"Unit";"Overlord";"Larva";164;0
"Unit";"Overlord";"Larva";164;0
"Unit";"Overlord";"Larva";164;0
"Unit";"Baneling";"Zergling";181;0
"Unit";"Baneling";"Zergling";181;0
"Unit";"Baneling";"Zergling";181;0
"Unit";"Baneling";"Zergling";181;0
"Unit";"Baneling";"Zergling";181;0
"Unit";"Baneling";"Zergling";181;0
"Unit";"Baneling";"Zergling";181;0
"Unit";"Baneling";"Zergling";181;0
"Unit";"Baneling";"Zergling";181;0
"Unit";"Baneling";"Zergling";181;0
"Unit";"Baneling";"Zergling";181;0
"Unit";"Zergling";"Larva";181;1
"Unit";"Zergling";"Larva";181;1
"Unit";"Zergling";"Larva";181;1
"Unit";"Zergling";"Larva";181;1
"Unit";"Zergling";"Larva";181;1
"Unit";"Zergling";"Larva";181;1
"Unit";"Zergling";"Larva";181;1
"Unit";"Zergling";"Larva";181;1
"Unit";"Zergling";"Larva";181;1
"Unit";"Zergling";"Larva";181;1
"Unit";"Zergling";"Larva";181;1
"Unit";"Zergling";"Larva";181;1
"Unit";"Zergling";"Larva";181;1
"Unit";"Zergling";"Larva";181;1
"Unit";"Zergling";"Larva";181;1
"Unit";"Zergling";"Larva";181;1
"Unit";"Zergling";"Larva";181;1
"Unit";"Zergling";"Larva";181;1
"Unit";"Zergling";"Larva";181;1
"Unit";"Zergling";"Larva";181;1
"Building";"InfestationPit";NA;164;0
"Upgrade";"ZergGroundArmorsLevel2";"EvolutionChamber";141;0
"Building";"CreepTumor";NA;201;0
"Unit";"Zergling";"Larva";201;1
"Unit";"Zergling";"Larva";201;1
"Unit";"Zergling";"Larva";201;1
"Unit";"Zergling";"Larva";201;1
"Unit";"Zergling";"Larva";201;1
"Unit";"Zergling";"Larva";201;1
"Unit";"Zergling";"Larva";201;1
"Unit";"Zergling";"Larva";201;1
"Unit";"Zergling";"Larva";201;1
"Unit";"Zergling";"Larva";201;1
"Unit";"Zergling";"Larva";201;1
"Unit";"Zergling";"Larva";201;1
"Unit";"Zergling";"Larva";201;1
"Unit";"Zergling";"Larva";201;1
"Building";"CreepTumorQueen";NA;215;0
"Building";"CreepTumorQueen";NA;215;0
"Building";"CreepTumorQueen";NA;215;0
"Building";"CreepTumor";NA;215;0
"Unit";"Zergling";"Larva";215;1
"Unit";"Zergling";"Larva";215;1
"Unit";"Zergling";"Larva";215;1
"Unit";"Zergling";"Larva";215;1
"Unit";"Zergling";"Larva";215;1
"Unit";"Zergling";"Larva";215;1
"Unit";"Zergling";"Larva";215;1
"Unit";"Zergling";"Larva";215;1
"Unit";"Zergling";"Larva";215;1
"Unit";"Zergling";"Larva";215;1
"Unit";"Zergling";"Larva";215;1
"Unit";"Zergling";"Larva";215;1
"Unit";"Zergling";"Larva";215;1
"Unit";"Zergling";"Larva";215;1
"Unit";"Zergling";"Larva";215;1
"Unit";"Zergling";"Larva";215;1
"Unit";"Zergling";"Larva";215;1
"Unit";"Zergling";"Larva";215;1
"Building";"CreepTumor";NA;215;0
"Building";"CreepTumorQueen";NA;215;0
"Building";"CreepTumorQueen";NA;215;0
"Building";"CreepTumorQueen";NA;217;0
"Building";"CreepTumor";NA;217;0
"Building";"CreepTumor";NA;217;0
"Building";"CreepTumor";NA;217;0
"Building";"SporeCrawler";NA;215;0
"Building";"CreepTumorQueen";NA;217;0
"Upgrade";"ZergMeleeWeaponsLevel2";"EvolutionChamber";164;0
"Building";"Hatchery";NA;201;0
"Unit";"Zergling";"Larva";242;1
"Unit";"Zergling";"Larva";242;1
"Unit";"Zergling";"Larva";242;1
"Unit";"Zergling";"Larva";242;1
"Unit";"Zergling";"Larva";242;1
"Unit";"Zergling";"Larva";242;1
"Unit";"Zergling";"Larva";242;1
"Unit";"Zergling";"Larva";242;1
"Unit";"Zergling";"Larva";242;1
"Unit";"Zergling";"Larva";242;1
"Unit";"Zergling";"Larva";242;1
"Unit";"Zergling";"Larva";242;1
"Unit";"Zergling";"Larva";242;1
"Unit";"Zergling";"Larva";242;1
"Unit";"Zergling";"Larva";242;1
"Unit";"Zergling";"Larva";242;1
"Unit";"Zergling";"Larva";242;1
"Unit";"Zergling";"Larva";242;1
"Unit";"Zergling";"Larva";242;1
"Unit";"Zergling";"Larva";242;1
"Unit";"Zergling";"Larva";242;1
"Unit";"Zergling";"Larva";242;1
"Unit";"Zergling";"Larva";242;1
"Unit";"Zergling";"Larva";242;1
"Unit";"Baneling";"Zergling";242;0
"Unit";"Baneling";"Zergling";242;0
"Unit";"Zergling";"Larva";242;1
"Unit";"Zergling";"Larva";242;1
"Unit";"Zergling";"Larva";242;1
"Unit";"Zergling";"Larva";242;1
"Unit";"Zergling";"Larva";242;1
"Unit";"Zergling";"Larva";242;1
"Unit";"Zergling";"Larva";242;1
"Unit";"Zergling";"Larva";242;1
"Building";"CreepTumor";NA;266;0
"Building";"CreepTumor";NA;266;0
"Unit";"Zergling";"Larva";274;1
"Unit";"Zergling";"Larva";274;1
"Unit";"Zergling";"Larva";274;1
"Unit";"Zergling";"Larva";274;1
"Unit";"Zergling";"Larva";274;1
"Unit";"Zergling";"Larva";274;1
"Unit";"Zergling";"Larva";274;1
"Unit";"Zergling";"Larva";274;1
"Unit";"Zergling";"Larva";274;1
"Unit";"Zergling";"Larva";274;1
"Unit";"Overlord";"Larva";274;0
"Unit";"Overlord";"Larva";274;0
"Building";"CreepTumor";NA;284;0
"Building";"CreepTumor";NA;284;0
"Unit";"Zergling";"Larva";284;1
"Unit";"Zergling";"Larva";284;1
"Building";"CreepTumor";NA;284;0
"Unit";"Zergling";"Larva";284;1
"Unit";"Zergling";"Larva";284;1
"Unit";"Zergling";"Larva";284;1
"Unit";"Zergling";"Larva";284;1
"Unit";"Zergling";"Larva";284;1
"Unit";"Zergling";"Larva";284;1
"Unit";"Zergling";"Larva";284;1
"Unit";"Zergling";"Larva";284;1
"Unit";"Zergling";"Larva";284;1
"Unit";"Zergling";"Larva";284;1
"Unit";"Zergling";"Larva";284;1
"Unit";"Zergling";"Larva";284;1
"Unit";"Zergling";"Larva";284;1
"Unit";"Zergling";"Larva";284;1
"Building";"CreepTumorQueen";NA;284;0
"Building";"CreepTumorQueen";NA;284;0
"Unit";"Queen";"Hatchery";274;2
"Unit";"Baneling";"Zergling";301;0
"Unit";"Baneling";"Zergling";301;0
"Unit";"Baneling";"Zergling";301;0
"Unit";"Baneling";"Zergling";301;0
"Unit";"Baneling";"Zergling";301;0
"Unit";"Baneling";"Zergling";301;0
"Unit";"Baneling";"Zergling";301;0
"Unit";"Baneling";"Zergling";301;0
"Unit";"Baneling";"Zergling";301;0
"Unit";"Baneling";"Zergling";301;0
"Unit";"Zergling";"Larva";284;1
"Unit";"Zergling";"Larva";284;1
"Unit";"Zergling";"Larva";284;1
"Unit";"Zergling";"Larva";284;1
"Unit";"Zergling";"Larva";284;1
"Unit";"Zergling";"Larva";284;1
"Unit";"Zergling";"Larva";284;1
"Unit";"Zergling";"Larva";284;1
"Unit";"Zergling";"Larva";284;1
"Unit";"Zergling";"Larva";284;1
"Unit";"Zergling";"Larva";284;1
"Unit";"Zergling";"Larva";284;1
"Unit";"Zergling";"Larva";286;1
"Unit";"Zergling";"Larva";286;1
"Unit";"Zergling";"Larva";286;1
"Unit";"Zergling";"Larva";286;1
"Unit";"Zergling";"Larva";286;1
"Unit";"Zergling";"Larva";286;1
"Unit";"Baneling";"Zergling";301;0
"Unit";"Baneling";"Zergling";301;0
"Unit";"Baneling";"Zergling";301;0
"Unit";"Baneling";"Zergling";301;0
"Unit";"Baneling";"Zergling";301;0
"Unit";"Zergling";"Larva";301;1
"Unit";"Zergling";"Larva";301;1
"Unit";"Zergling";"Larva";301;1
"Unit";"Zergling";"Larva";301;1
"Unit";"Zergling";"Larva";301;1
"Unit";"Zergling";"Larva";301;1
"Building";"CreepTumor";NA;311;0
"Building";"CreepTumor";NA;307;0
"Building";"CreepTumor";NA;315;0
"Building";"Hatchery";NA;268;0
"Building";"Hatchery";NA;274;0
"Unit";"Zergling";"Larva";327;1
"Unit";"Zergling";"Larva";327;1
"Unit";"Zergling";"Larva";327;1
"Unit";"Zergling";"Larva";327;1
"Unit";"Zergling";"Larva";327;1
"Unit";"Zergling";"Larva";327;1
"Unit";"Zergling";"Larva";327;1
"Unit";"Zergling";"Larva";327;1
"Unit";"Zergling";"Larva";327;1
"Unit";"Zergling";"Larva";327;1
"Unit";"Zergling";"Larva";327;1
"Unit";"Zergling";"Larva";327;1
"Unit";"Zergling";"Larva";327;1
"Unit";"Zergling";"Larva";327;1
"Unit";"Zergling";"Larva";327;1
"Unit";"Zergling";"Larva";327;1
"Unit";"Zergling";"Larva";327;1
"Unit";"Zergling";"Larva";327;1
"Unit";"Zergling";"Larva";327;1
"Unit";"Zergling";"Larva";327;1
"Unit";"Zergling";"Larva";327;1
"Unit";"Zergling";"Larva";327;1
"Unit";"Zergling";"Larva";327;1
"Unit";"Zergling";"Larva";327;1
"Unit";"Zergling";"Larva";327;1
"Unit";"Zergling";"Larva";327;1
"Unit";"Zergling";"Larva";327;1
"Unit";"Zergling";"Larva";327;1
"Unit";"Zergling";"Larva";327;1
"Unit";"Zergling";"Larva";327;1
"Unit";"Zergling";"Larva";327;1
"Unit";"Zergling";"Larva";327;1
"Unit";"Zergling";"Larva";327;1
"Unit";"Zergling";"Larva";327;1
"Building";"CreepTumorQueen";NA;327;0
"Building";"CreepTumorQueen";NA;327;0
"Building";"CreepTumorQueen";NA;327;0
"Building";"Hatchery";NA;284;0
"Unit";"Zergling";"Larva";327;1
"Unit";"Zergling";"Larva";327;1
"Building";"CreepTumor";NA;327;0
"Building";"CreepTumor";NA;361;0
"Building";"CreepTumor";NA;361;0
"Building";"CreepTumor";NA;361;0
"Building";"CreepTumorQueen";NA;361;0
"Unit";"Zergling";"Larva";327;1
"Unit";"Zergling";"Larva";327;1
"Building";"CreepTumorQueen";NA;361;0
"Unit";"Zergling";"Larva";327;1
"Unit";"Zergling";"Larva";327;1
"Unit";"Zergling";"Larva";327;1
"Unit";"Zergling";"Larva";327;1
"Unit";"Zergling";"Larva";327;1
"Unit";"Zergling";"Larva";327;1
"Unit";"Zergling";"Larva";327;1
"Unit";"Zergling";"Larva";327;1
"Unit";"Zergling";"Larva";363;1
"Unit";"Zergling";"Larva";363;1
"Unit";"Zergling";"Larva";363;1
"Unit";"Zergling";"Larva";363;1
"Unit";"Zergling";"Larva";363;1
"Unit";"Zergling";"Larva";363;1
"Unit";"Zergling";"Larva";363;1
"Unit";"Zergling";"Larva";363;1
"Unit";"Zergling";"Larva";363;1
"Unit";"Zergling";"Larva";363;1
"Unit";"Zergling";"Larva";363;1
"Unit";"Zergling";"Larva";363;1
"Unit";"Zergling";"Larva";363;1
"Unit";"Zergling";"Larva";363;1
"Unit";"Zergling";"Larva";363;1
"Unit";"Zergling";"Larva";363;1
"Unit";"Zergling";"Larva";363;1
"Unit";"Zergling";"Larva";363;1
"Unit";"Zergling";"Larva";363;1
"Unit";"Zergling";"Larva";363;1
"Unit";"Zergling";"Larva";363;1
"Unit";"Zergling";"Larva";363;1
"Unit";"Zergling";"Larva";363;1
"Unit";"Zergling";"Larva";363;1
"Unit";"Zergling";"Larva";363;1
"Unit";"Zergling";"Larva";363;1
"Unit";"Zergling";"Larva";363;1
"Unit";"Zergling";"Larva";363;1
"Unit";"Queen";"Hatchery";327;2
"Building";"CreepTumor";NA;373;0
"Building";"CreepTumor";NA;373;0
"Unit";"Baneling";"Zergling";373;0
"Unit";"Baneling";"Zergling";373;0
"Unit";"Baneling";"Zergling";373;0
"Unit";"Baneling";"Zergling";373;0
"Building";"CreepTumor";NA;373;0
"Unit";"Baneling";"Zergling";373;0
"Unit";"Baneling";"Zergling";373;0
"Unit";"Baneling";"Zergling";373;0
"Unit";"Baneling";"Zergling";373;0
"Unit";"Baneling";"Zergling";373;0
"Unit";"Baneling";"Zergling";373;0
"Unit";"Baneling";"Zergling";373;0
"Unit";"Baneling";"Zergling";373;0
"Unit";"Baneling";"Zergling";373;0
"Unit";"Baneling";"Zergling";373;0
"Unit";"Baneling";"Zergling";373;0
"Unit";"Baneling";"Zergling";373;0
"Building";"CreepTumor";NA;403;0
"Building";"CreepTumorQueen";NA;403;0
"Building";"CreepTumor";NA;403;0
"Building";"CreepTumor";NA;403;0
"Unit";"Queen";"Hatchery";363;2
"Unit";"Baneling";"Zergling";409;0
"Unit";"Baneling";"Zergling";409;0
"Unit";"Baneling";"Zergling";409;0
"Unit";"Baneling";"Zergling";409;0
"Unit";"Baneling";"Zergling";409;0
"Unit";"Baneling";"Zergling";409;0
"Unit";"Baneling";"Zergling";409;0
"Unit";"Baneling";"Zergling";409;0
"Unit";"Zergling";"Larva";409;1
"Unit";"Zergling";"Larva";409;1
"Unit";"Zergling";"Larva";409;1
"Unit";"Zergling";"Larva";409;1
"Unit";"Zergling";"Larva";409;1
"Unit";"Zergling";"Larva";409;1
"Unit";"Zergling";"Larva";409;1
"Unit";"Zergling";"Larva";409;1
"Unit";"Zergling";"Larva";409;1
"Unit";"Zergling";"Larva";409;1
"Unit";"Baneling";"Zergling";409;0
"Unit";"Zergling";"Larva";409;1
"Unit";"Zergling";"Larva";409;1
"Unit";"Zergling";"Larva";409;1
"Unit";"Zergling";"Larva";409;1
"Unit";"Zergling";"Larva";409;1
"Unit";"Zergling";"Larva";409;1
"Unit";"Baneling";"Zergling";409;0
"Unit";"Baneling";"Zergling";409;0
"Unit";"Baneling";"Zergling";409;0
"Unit";"Baneling";"Zergling";409;0
"Unit";"Baneling";"Zergling";409;0
"Unit";"Baneling";"Zergling";409;0
"Unit";"Baneling";"Zergling";409;0
"Building";"CreepTumor";NA;411;0
"Unit";"Zergling";"Larva";411;1
"Unit";"Zergling";"Larva";411;1
"Unit";"Zergling";"Larva";411;1
"Unit";"Zergling";"Larva";411;1
"Unit";"Zergling";"Larva";411;1
"Unit";"Zergling";"Larva";411;1
"Unit";"Zergling";"Larva";411;1
"Unit";"Zergling";"Larva";411;1
"Unit";"Zergling";"Larva";411;1
"Unit";"Zergling";"Larva";411;1
"Unit";"Zergling";"Larva";411;1
"Unit";"Zergling";"Larva";411;1
"Unit";"Zergling";"Larva";411;1
"Unit";"Zergling";"Larva";411;1
"Unit";"Zergling";"Larva";411;1
"Unit";"Zergling";"Larva";411;1
"Unit";"Zergling";"Larva";411;1
"Unit";"Zergling";"Larva";411;1
"Unit";"Zergling";"Larva";411;1
"Unit";"Zergling";"Larva";411;1
"Unit";"Zergling";"Larva";411;1
"Unit";"Zergling";"Larva";411;1
"Unit";"Zergling";"Larva";427;1
"Unit";"Zergling";"Larva";427;1
"Unit";"Zergling";"Larva";427;1
"Unit";"Zergling";"Larva";427;1
"Unit";"Zergling";"Larva";427;1
"Unit";"Zergling";"Larva";427;1
"Unit";"Zergling";"Larva";427;1
"Unit";"Zergling";"Larva";427;1
"Unit";"Zergling";"Larva";427;1
"Unit";"Zergling";"Larva";427;1
"Upgrade";"ZergGroundArmorsLevel3";"EvolutionChamber";321;0
"Upgrade";"ZergMeleeWeaponsLevel3";"EvolutionChamber";321;0
"Unit";"Zergling";"Larva";427;1
"Unit";"Zergling";"Larva";427;1
"Unit";"Zergling";"Larva";427;1
"Unit";"Zergling";"Larva";427;1
"Unit";"Zergling";"Larva";427;1
"Unit";"Zergling";"Larva";427;1
"Building";"CreepTumor";NA;449;0
"Unit";"Zergling";"Larva";427;1
"Unit";"Zergling";"Larva";427;1
"Unit";"Zergling";"Larva";427;1
"Unit";"Zergling";"Larva";427;1
"Unit";"Zergling";"Larva";427;1
"Unit";"Zergling";"Larva";427;1
"Unit";"Zergling";"Larva";427;1
"Unit";"Zergling";"Larva";427;1
"Unit";"Zergling";"Larva";427;1
"Unit";"Zergling";"Larva";427;1
"Unit";"Zergling";"Larva";427;1
"Unit";"Zergling";"Larva";427;1
"Unit";"Zergling";"Larva";427;1
"Unit";"Zergling";"Larva";427;1
"Building";"CreepTumor";NA;449;0
"Building";"CreepTumor";NA;459;0
"Building";"CreepTumor";NA;459;0
"Building";"CreepTumor";NA;459;0
"Building";"CreepTumorQueen";NA;479;0
"Building";"CreepTumor";NA;479;0
"Building";"CreepTumor";NA;479;0
"Unit";"Overlord";"Larva";479;0
"Unit";"Overlord";"Larva";479;0
"Building";"CreepTumor";NA;479;0
"Building";"CreepTumorQueen";NA;479;0
"Building";"CreepTumorQueen";NA;479;0
"Unit";"Zergling";"Larva";479;1
"Unit";"Zergling";"Larva";479;1
"Unit";"Zergling";"Larva";479;1
"Unit";"Zergling";"Larva";479;1
"Unit";"Zergling";"Larva";479;1
"Unit";"Zergling";"Larva";479;1
"Unit";"Zergling";"Larva";479;1
"Unit";"Zergling";"Larva";479;1
"Unit";"Zergling";"Larva";479;1
"Unit";"Zergling";"Larva";479;1
"Unit";"Zergling";"Larva";479;1
"Unit";"Zergling";"Larva";479;1
"Unit";"Zergling";"Larva";479;1
"Unit";"Zergling";"Larva";479;1
"Unit";"Zergling";"Larva";479;1
"Unit";"Zergling";"Larva";479;1
"Unit";"Zergling";"Larva";479;1
"Unit";"Zergling";"Larva";479;1
"Unit";"Zergling";"Larva";479;1
"Unit";"Zergling";"Larva";479;1
"Unit";"Zergling";"Larva";479;1
"Unit";"Zergling";"Larva";479;1
"Unit";"Zergling";"Larva";479;1
"Unit";"Zergling";"Larva";479;1
"Unit";"Zergling";"Larva";479;1
"Unit";"Zergling";"Larva";479;1
"Unit";"Zergling";"Larva";479;1
"Unit";"Zergling";"Larva";479;1
"Unit";"Zergling";"Larva";479;1
"Unit";"Zergling";"Larva";479;1
"Building";"CreepTumorQueen";NA;479;0
"Unit";"Baneling";"Zergling";479;0
"Unit";"Baneling";"Zergling";479;0
"Unit";"Baneling";"Zergling";479;0
"Unit";"Baneling";"Zergling";479;0
"Unit";"Baneling";"Zergling";479;0
"Unit";"Baneling";"Zergling";479;0
"Unit";"Baneling";"Zergling";479;0
"Unit";"Baneling";"Zergling";479;0
"Unit";"Zergling";"Larva";479;1
"Unit";"Zergling";"Larva";479;1
"Unit";"Zergling";"Larva";479;1
"Unit";"Zergling";"Larva";479;1
"Unit";"Zergling";"Larva";479;1
"Unit";"Zergling";"Larva";479;1
"Unit";"Zergling";"Larva";479;1
"Unit";"Zergling";"Larva";479;1
"Unit";"Overlord";"Larva";479;0
"Unit";"Zergling";"Larva";479;1
"Unit";"Zergling";"Larva";479;1
"Building";"CreepTumor";NA;509;0
"Building";"CreepTumor";NA;509;0
"Building";"CreepTumor";NA;519;0
"Building";"CreepTumor";NA;519;0
"Unit";"Zergling";"Larva";509;1
"Unit";"Zergling";"Larva";509;1
"Unit";"Zergling";"Larva";509;1
"Unit";"Zergling";"Larva";509;1
"Unit";"Zergling";"Larva";509;1
"Unit";"Zergling";"Larva";509;1
"Unit";"Zergling";"Larva";509;1
"Unit";"Zergling";"Larva";509;1
"Unit";"Zergling";"Larva";509;1
"Unit";"Zergling";"Larva";509;1
"Unit";"Zergling";"Larva";509;1
"Unit";"Zergling";"Larva";509;1
"Unit";"Zergling";"Larva";509;1
"Unit";"Zergling";"Larva";509;1
"Unit";"Zergling";"Larva";509;1
"Unit";"Zergling";"Larva";509;1
"Unit";"Zergling";"Larva";509;1
"Unit";"Zergling";"Larva";509;1
"Unit";"Zergling";"Larva";509;1
"Unit";"Zergling";"Larva";509;1
"Unit";"Zergling";"Larva";509;1
"Unit";"Zergling";"Larva";509;1
"Unit";"Zergling";"Larva";509;1
"Unit";"Zergling";"Larva";509;1
"Unit";"Zergling";"Larva";509;1
"Unit";"Zergling";"Larva";509;1
"Unit";"Zergling";"Larva";509;1
"Unit";"Zergling";"Larva";509;1
"Unit";"Zergling";"Larva";509;1
"Unit";"Zergling";"Larva";509;1
"Unit";"Zergling";"Larva";509;1
"Unit";"Zergling";"Larva";509;1
"Unit";"Zergling";"Larva";509;1
"Unit";"Zergling";"Larva";509;1
"Unit";"Zergling";"Larva";509;1
"Unit";"Zergling";"Larva";509;1
"Unit";"Zergling";"Larva";509;1
"Unit";"Zergling";"Larva";509;1
"Unit";"Baneling";"Zergling";519;0
"Unit";"Baneling";"Zergling";519;0
"Unit";"Baneling";"Zergling";519;0
"Unit";"Baneling";"Zergling";519;0
"Unit";"Baneling";"Zergling";519;0
"Unit";"Baneling";"Zergling";519;0
"Unit";"Baneling";"Zergling";519;0
"Unit";"Baneling";"Zergling";519;0
"Unit";"Baneling";"Zergling";519;0
"Unit";"Baneling";"Zergling";519;0
"Unit";"Baneling";"Zergling";519;0
"Unit";"Baneling";"Zergling";519;0
"Unit";"Baneling";"Zergling";519;0
"Building";"CreepTumorQueen";NA;557;0
"Building";"CreepTumorQueen";NA;557;0
"Unit";"Zergling";"Larva";557;1
"Unit";"Zergling";"Larva";557;1
"Unit";"Zergling";"Larva";557;1
"Unit";"Zergling";"Larva";557;1
"Unit";"Zergling";"Larva";557;1
"Unit";"Zergling";"Larva";557;1
"Unit";"Zergling";"Larva";557;1
"Unit";"Zergling";"Larva";557;1
"Unit";"Zergling";"Larva";557;1
"Unit";"Zergling";"Larva";557;1
"Unit";"Zergling";"Larva";557;1
"Unit";"Zergling";"Larva";557;1
"Unit";"Zergling";"Larva";557;1
"Unit";"Zergling";"Larva";557;1
"Unit";"Zergling";"Larva";557;1
"Unit";"Zergling";"Larva";557;1
"Unit";"Zergling";"Larva";557;1
"Unit";"Zergling";"Larva";557;1
"Unit";"Zergling";"Larva";557;1
"Unit";"Zergling";"Larva";557;1
"Unit";"Zergling";"Larva";557;1
"Unit";"Zergling";"Larva";557;1
"Unit";"Zergling";"Larva";557;1
"Unit";"Zergling";"Larva";557;1
"Unit";"Zergling";"Larva";557;1
"Unit";"Zergling";"Larva";557;1
"Unit";"Zergling";"Larva";557;1
"Unit";"Zergling";"Larva";557;1
"Unit";"Zergling";"Larva";557;1
"Unit";"Zergling";"Larva";557;1
"Unit";"Zergling";"Larva";557;1
"Unit";"Zergling";"Larva";557;1
"Building";"CreepTumorQueen";NA;557;0
"Building";"Hatchery";NA;479;0
"Building";"CreepTumorQueen";NA;559;0
"Building";"CreepTumor";NA;557;0
"Building";"CreepTumorQueen";NA;589;0
"Unit";"Baneling";"Zergling";589;0
"Unit";"Baneling";"Zergling";589;0
"Unit";"Baneling";"Zergling";589;0
"Unit";"Baneling";"Zergling";589;0
"Unit";"Baneling";"Zergling";589;0
"Unit";"Baneling";"Zergling";589;0
"Unit";"Baneling";"Zergling";589;0
"Unit";"Baneling";"Zergling";589;0
"Unit";"Baneling";"Zergling";589;0
"Unit";"Baneling";"Zergling";589;0
"Unit";"Baneling";"Zergling";589;0
"Unit";"Baneling";"Zergling";589;0
"Unit";"Baneling";"Zergling";589;0
"Unit";"Baneling";"Zergling";589;0
"Unit";"Baneling";"Zergling";589;0
"Unit";"Baneling";"Zergling";589;0
"Unit";"Baneling";"Zergling";589;0
"Unit";"Baneling";"Zergling";589;0
"Unit";"Baneling";"Zergling";589;0
"Unit";"Baneling";"Zergling";589;0
"Unit";"Baneling";"Zergling";589;0
"Building";"CreepTumor";NA;599;0
"Building";"CreepTumor";NA;599;0
"Building";"CreepTumor";NA;599;0
"Building";"CreepTumor";NA;599;0
"Building";"CreepTumor";NA;599;0
"Building";"CreepTumor";NA;599;0
"Building";"CreepTumor";NA;599;0
"Unit";"Zergling";"Larva";599;1
"Unit";"Zergling";"Larva";599;1
"Unit";"Zergling";"Larva";599;1
"Unit";"Zergling";"Larva";599;1
"Unit";"Zergling";"Larva";599;1
"Unit";"Zergling";"Larva";599;1
"Unit";"Zergling";"Larva";599;1
"Unit";"Zergling";"Larva";599;1
"Unit";"Zergling";"Larva";599;1
"Unit";"Zergling";"Larva";599;1
"Unit";"Zergling";"Larva";599;1
"Unit";"Zergling";"Larva";599;1
"Unit";"Zergling";"Larva";599;1
"Unit";"Zergling";"Larva";599;1
"Unit";"Zergling";"Larva";599;1
"Unit";"Zergling";"Larva";599;1
"Unit";"Zergling";"Larva";599;1
"Unit";"Zergling";"Larva";599;1
"Unit";"Zergling";"Larva";599;1
"Unit";"Zergling";"Larva";599;1
"Unit";"Zergling";"Larva";599;1
"Unit";"Zergling";"Larva";599;1
"Unit";"Zergling";"Larva";599;1
"Unit";"Zergling";"Larva";599;1
"Unit";"Zergling";"Larva";599;1
"Unit";"Zergling";"Larva";599;1
"Unit";"Zergling";"Larva";599;1
"Unit";"Zergling";"Larva";599;1
"Unit";"Zergling";"Larva";599;1
"Unit";"Zergling";"Larva";599;1
"Unit";"Zergling";"Larva";599;1
"Unit";"Zergling";"Larva";599;1
"Unit";"Zergling";"Larva";599;1
"Unit";"Zergling";"Larva";599;1
"Unit";"Zergling";"Larva";599;1
"Unit";"Zergling";"Larva";599;1
"Unit";"Zergling";"Larva";599;1
"Unit";"Zergling";"Larva";599;1
"Unit";"Zergling";"Larva";599;1
"Unit";"Zergling";"Larva";599;1
"Building";"CreepTumor";NA;599;0
"Unit";"Zergling";"Larva";599;1
"Unit";"Zergling";"Larva";599;1
"Unit";"Zergling";"Larva";599;1
"Unit";"Zergling";"Larva";599;1
"Unit";"Zergling";"Larva";599;1
"Unit";"Zergling";"Larva";599;1
"Unit";"Zergling";"Larva";599;1
"Unit";"Zergling";"Larva";599;1
"Unit";"Zergling";"Larva";599;1
"Unit";"Zergling";"Larva";599;1
"Unit";"Zergling";"Larva";599;1
"Unit";"Zergling";"Larva";599;1
"Unit";"Zergling";"Larva";599;1
"Unit";"Zergling";"Larva";599;1
"Unit";"Zergling";"Larva";599;1
"Unit";"Zergling";"Larva";599;1
"Unit";"Zergling";"Larva";599;1
"Unit";"Zergling";"Larva";599;1
"Unit";"Zergling";"Larva";599;1
"Unit";"Zergling";"Larva";599;1
"Unit";"Zergling";"Larva";599;1
"Unit";"Zergling";"Larva";599;1
"Unit";"Zergling";"Larva";599;1
"Unit";"Zergling";"Larva";599;1
"Unit";"Zergling";"Larva";599;1
"Unit";"Zergling";"Larva";599;1
"Unit";"Zergling";"Larva";599;1
"Unit";"Zergling";"Larva";599;1
"Unit";"Zergling";"Larva";599;1
"Unit";"Zergling";"Larva";599;1
"Unit";"Zergling";"Larva";599;1
"Unit";"Zergling";"Larva";599;1
"Unit";"Zergling";"Larva";599;1
"Unit";"Zergling";"Larva";599;1
"Unit";"Zergling";"Larva";599;1
"Unit";"Zergling";"Larva";599;1
"Unit";"Zergling";"Larva";599;1
"Unit";"Zergling";"Larva";599;1
"Unit";"Zergling";"Larva";599;1
"Unit";"Zergling";"Larva";599;1
"Unit";"Zergling";"Larva";599;1
"Unit";"Zergling";"Larva";599;1
"Unit";"Zergling";"Larva";599;1
"Unit";"Zergling";"Larva";599;1
"Unit";"Zergling";"Larva";599;1
"Unit";"Zergling";"Larva";599;1
"Unit";"Zergling";"Larva";599;1
"Unit";"Zergling";"Larva";599;1
"Unit";"Zergling";"Larva";599;1
"Unit";"Zergling";"Larva";599;1
"Unit";"Zergling";"Larva";599;1
"Unit";"Zergling";"Larva";599;1
"Unit";"Zergling";"Larva";599;1
"Unit";"Zergling";"Larva";599;1
"Building";"CreepTumor";NA;639;0
"Unit";"Queen";"Hatchery";599;2
"Building";"CreepTumor";NA;639;0
"Unit";"Zergling";"Larva";695;1
"Unit";"Zergling";"Larva";695;1
"Unit";"Zergling";"Larva";695;1
"Unit";"Zergling";"Larva";695;1
"Unit";"Zergling";"Larva";695;1
"Unit";"Zergling";"Larva";695;1
"Unit";"Zergling";"Larva";695;1
"Unit";"Zergling";"Larva";695;1
"Unit";"Zergling";"Larva";695;1
"Unit";"Zergling";"Larva";695;1
"Unit";"Zergling";"Larva";695;1
"Unit";"Zergling";"Larva";695;1
"Unit";"Zergling";"Larva";695;1
"Unit";"Zergling";"Larva";695;1
"Unit";"Zergling";"Larva";695;1
"Unit";"Zergling";"Larva";695;1
"Unit";"Zergling";"Larva";695;1
"Unit";"Zergling";"Larva";695;1
"Unit";"Zergling";"Larva";695;1
"Unit";"Zergling";"Larva";695;1
"Unit";"Zergling";"Larva";695;1
"Unit";"Zergling";"Larva";695;1
"Unit";"Zergling";"Larva";695;1
"Unit";"Zergling";"Larva";695;1
"Unit";"Zergling";"Larva";695;1
"Unit";"Zergling";"Larva";695;1
"Unit";"Zergling";"Larva";695;1
"Unit";"Zergling";"Larva";695;1
"Unit";"Zergling";"Larva";695;1
"Unit";"Zergling";"Larva";695;1
"Unit";"Zergling";"Larva";695;1
"Unit";"Zergling";"Larva";695;1
"Unit";"Zergling";"Larva";695;1
"Unit";"Zergling";"Larva";695;1
"Unit";"Zergling";"Larva";695;1
"Unit";"Zergling";"Larva";695;1
"Unit";"Zergling";"Larva";695;1
"Unit";"Zergling";"Larva";695;1
"Unit";"Zergling";"Larva";695;1
"Unit";"Zergling";"Larva";695;1
"Unit";"Zergling";"Larva";695;1
"Unit";"Zergling";"Larva";695;1
"Unit";"Zergling";"Larva";695;1
"Unit";"Zergling";"Larva";695;1
"Unit";"Zergling";"Larva";695;1
"Unit";"Zergling";"Larva";695;1
"Unit";"Zergling";"Larva";695;1
"Unit";"Zergling";"Larva";695;1
"Unit";"Zergling";"Larva";695;1
"Unit";"Zergling";"Larva";695;1
"Unit";"Zergling";"Larva";695;1
"Unit";"Zergling";"Larva";695;1
"Unit";"Zergling";"Larva";695;1
"Unit";"Zergling";"Larva";695;1
"Unit";"Zergling";"Larva";695;1
"Unit";"Zergling";"Larva";695;1
"Unit";"Zergling";"Larva";695;1
"Unit";"Zergling";"Larva";695;1
"Unit";"Zergling";"Larva";695;1
"Unit";"Zergling";"Larva";695;1
"Unit";"Zergling";"Larva";695;1
"Unit";"Zergling";"Larva";695;1
"Unit";"Zergling";"Larva";695;1
"Unit";"Zergling";"Larva";695;1
"Unit";"Zergling";"Larva";695;1
"Unit";"Zergling";"Larva";695;1
"Unit";"Zergling";"Larva";695;1
"Unit";"Zergling";"Larva";695;1
"Unit";"Zergling";"Larva";695;1
"Unit";"Zergling";"Larva";695;1
"Unit";"Zergling";"Larva";695;1
"Unit";"Zergling";"Larva";695;1
"Unit";"Zergling";"Larva";695;1
"Unit";"Zergling";"Larva";695;1
"Building";"CreepTumor";NA;757;0
"Building";"CreepTumor";NA;759;0
"Building";"CreepTumor";NA;769;0
"Building";"CreepTumor";NA;769;0
"Building";"CreepTumor";NA;769;0
"Building";"CreepTumor";NA;769;0
"Upgrade";"ZergMissileWeaponsLevel1";"EvolutionChamber";683;0
"Unit";"Zergling";"Larva";769;1
"Unit";"Zergling";"Larva";769;1
"Unit";"Zergling";"Larva";769;1
"Unit";"Zergling";"Larva";769;1
"Unit";"Zergling";"Larva";769;1
"Unit";"Zergling";"Larva";769;1
"Unit";"Zergling";"Larva";769;1
"Unit";"Zergling";"Larva";769;1
"Unit";"Zergling";"Larva";769;1
"Unit";"Zergling";"Larva";769;1
"Unit";"Zergling";"Larva";769;1
"Unit";"Zergling";"Larva";769;1
"Unit";"Zergling";"Larva";769;1
"Unit";"Zergling";"Larva";769;1
"Unit";"Zergling";"Larva";769;1
"Unit";"Zergling";"Larva";769;1
"Unit";"Zergling";"Larva";769;1
"Unit";"Zergling";"Larva";769;1
"Unit";"Zergling";"Larva";769;1
"Unit";"Zergling";"Larva";769;1
"Unit";"Zergling";"Larva";769;1
"Unit";"Zergling";"Larva";769;1
"Unit";"Zergling";"Larva";769;1
"Unit";"Zergling";"Larva";769;1
"Unit";"Zergling";"Larva";769;1
"Unit";"Zergling";"Larva";769;1
"Unit";"Zergling";"Larva";769;1
"Unit";"Zergling";"Larva";769;1
"Unit";"Zergling";"Larva";769;1
"Unit";"Zergling";"Larva";769;1
"Unit";"Zergling";"Larva";769;1
"Unit";"Zergling";"Larva";769;1
"Unit";"Zergling";"Larva";769;1
"Unit";"Zergling";"Larva";769;1
"Unit";"Zergling";"Larva";769;1
"Unit";"Zergling";"Larva";769;1
"Unit";"Zergling";"Larva";769;1
"Unit";"Zergling";"Larva";769;1
"Unit";"Zergling";"Larva";769;1
"Unit";"Zergling";"Larva";769;1
"Building";"CreepTumor";NA;769;0
"Building";"CreepTumor";NA;769;0
"Building";"CreepTumor";NA;769;0
"Building";"CreepTumor";NA;769;0
"Unit";"Zergling";"Larva";769;1
"Unit";"Zergling";"Larva";769;1
"Unit";"Zergling";"Larva";769;1
"Unit";"Zergling";"Larva";769;1
"Unit";"Zergling";"Larva";769;1
"Unit";"Zergling";"Larva";769;1
"Unit";"Zergling";"Larva";769;1
"Unit";"Zergling";"Larva";769;1
