"type";"unit_name";"on_building";"total_supply";"supply"
"Unit";"Overlord";"Larva";13;0
"Building";"Extractor";NA;18;0
"Unit";"Overlord";"Larva";21;0
"Building";"SpawningPool";NA;19;0
"Building";"Hatchery";NA;17;0
"Unit";"Zergling";"Larva";22;1
"Unit";"Zergling";"Larva";22;1
"Unit";"Zergling";"Larva";22;1
"Unit";"Zergling";"Larva";22;1
"Unit";"Zergling";"Larva";22;1
"Unit";"Zergling";"Larva";22;1
"Unit";"Queen";"Hatchery";22;2
"Unit";"Queen";"Hatchery";22;2
"Unit";"Overlord";"Larva";38;0
"Unit";"Queen";"Hatchery";34;2
"Building";"CreepTumorQueen";NA;48;0
"Unit";"Overlord";"Larva";42;0
"Unit";"Overlord";"Larva";51;0
"Building";"CreepTumorQueen";NA;51;0
"Building";"CreepTumor";NA;51;0
"Unit";"Overlord";"Larva";51;0
"Building";"Extractor";NA;51;0
"Unit";"Overlord";"Larva";54;0
"Unit";"Queen";"Hatchery";51;2
"Unit";"Overlord";"Larva";54;0
"Unit";"Zergling";"Larva";55;1
"Unit";"Zergling";"Larva";55;1
"Unit";"Zergling";"Larva";55;1
"Unit";"Zergling";"Larva";55;1
"Building";"Hatchery";NA;40;0
"Unit";"Zergling";"Larva";57;1
"Unit";"Zergling";"Larva";57;1
"Building";"RoachWarren";NA;51;0
"Building";"CreepTumorQueen";NA;63;0
"Building";"CreepTumor";NA;63;0
"Building";"SporeCrawler";NA;70;0
"Building";"SporeCrawler";NA;70;0
"Building";"CreepTumorQueen";NA;75;0
"Building";"CreepTumor";NA;75;0
"Building";"CreepTumor";NA;75;0
"Building";"SporeCrawler";NA;75;0
"Unit";"Overlord";"Larva";78;0
"Building";"Extractor";NA;92;0
"Unit";"Roach";"Larva";93;2
"Unit";"Roach";"Larva";93;2
"Unit";"Roach";"Larva";93;2
"Unit";"Roach";"Larva";93;2
"Building";"CreepTumor";NA;96;0
"Unit";"Roach";"Larva";93;2
"Unit";"Roach";"Larva";93;2
"Unit";"Overlord";"Larva";96;0
"Unit";"Roach";"Larva";96;2
"Unit";"Roach";"Larva";96;2
"Unit";"Roach";"Larva";96;2
"Building";"CreepTumorQueen";NA;108;0
"Building";"CreepTumor";NA;119;0
"Building";"Extractor";NA;110;0
"Unit";"Overlord";"Larva";121;0
"Building";"EvolutionChamber";NA;127;0
"Unit";"Roach";"Larva";127;2
"Unit";"Roach";"Larva";127;2
"Unit";"Overlord";"Larva";133;0
"Building";"InfestationPit";NA;127;0
"Building";"Extractor";NA;133;0
"Unit";"Overlord";"Larva";133;0
"Building";"Extractor";NA;133;0
"Unit";"Overlord";"Larva";139;0
"Building";"CreepTumor";NA;143;0
"Building";"CreepTumor";NA;143;0
"Building";"CreepTumor";NA;148;0
"Building";"CreepTumor";NA;148;0
"Unit";"Queen";"Hatchery";143;2
"Unit";"Overlord";"Larva";152;0
"Building";"CreepTumor";NA;162;0
"Building";"CreepTumorQueen";NA;162;0
"Building";"CreepTumor";NA;162;0
"Building";"CreepTumor";NA;162;0
"Building";"CreepTumorQueen";NA;162;0
"Building";"EvolutionChamber";NA;152;0
"Building";"CreepTumor";NA;162;0
"Building";"HydraliskDen";NA;152;0
"Building";"Hatchery";NA;140;0
"Unit";"Overlord";"Larva";162;0
"Building";"CreepTumor";NA;162;0
"Building";"CreepTumor";NA;162;0
"Unit";"Overlord";"Larva";162;0
"Building";"CreepTumorQueen";NA;162;0
"Building";"CreepTumorQueen";NA;162;0
"Building";"CreepTumor";NA;162;0
"Building";"CreepTumor";NA;162;0
"Building";"Extractor";NA;162;0
"Building";"CreepTumor";NA;162;0
"Building";"Extractor";NA;162;0
"Building";"CreepTumor";NA;162;0
"Unit";"Overlord";"Larva";162;0
"Unit";"Overlord";"Larva";162;0
"Upgrade";"ZergMissileWeaponsLevel1";"EvolutionChamber";148;0
"Upgrade";"GlialReconstitution";"RoachWarren";162;0
"Unit";"Roach";"Larva";168;2
"Unit";"Roach";"Larva";168;2
"Unit";"Roach";"Larva";168;2
"Unit";"Roach";"Larva";168;2
"Unit";"Roach";"Larva";168;2
"Unit";"Roach";"Larva";168;2
"Unit";"Overlord";"Larva";168;0
"Building";"CreepTumor";NA;168;0
"Unit";"Overlord";"Larva";168;0
"Building";"CreepTumor";NA;168;0
"Building";"CreepTumor";NA;170;0
"Building";"CreepTumor";NA;180;0
"Building";"Spire";NA;162;0
"Upgrade";"Burrow";"Hatchery";162;0
"Building";"Hatchery";NA;162;0
"Unit";"Overlord";"Larva";180;0
"Upgrade";"EvolveGroovedSpines";"HydraliskDen";168;0
"Unit";"Overlord";"Larva";180;0
"Unit";"Hydralisk";"Larva";180;2
"Unit";"Hydralisk";"Larva";180;2
"Unit";"Hydralisk";"Larva";180;2
"Unit";"Hydralisk";"Larva";180;2
"Unit";"Hydralisk";"Larva";180;2
"Unit";"Hydralisk";"Larva";180;2
"Unit";"Hydralisk";"Larva";180;2
"Unit";"Hydralisk";"Larva";180;2
"Unit";"Hydralisk";"Larva";180;2
"Unit";"Overlord";"Larva";180;0
"Unit";"Overlord";"Larva";180;0
"Unit";"Overlord";"Larva";201;0
"Unit";"Overlord";"Larva";201;0
"Unit";"Queen";"Hatchery";180;2
"Unit";"Overlord";"Larva";219;0
"Unit";"Overlord";"Larva";219;0
"Unit";"Overlord";"Larva";219;0
"Unit";"Hydralisk";"Larva";219;2
"Unit";"Hydralisk";"Larva";219;2
"Unit";"Hydralisk";"Larva";219;2
"Unit";"Hydralisk";"Larva";219;2
"Unit";"Hydralisk";"Larva";219;2
"Unit";"Hydralisk";"Larva";219;2
"Unit";"Hydralisk";"Larva";219;2
"Unit";"Hydralisk";"Larva";219;2
"Unit";"Overlord";"Larva";219;0
"Building";"CreepTumor";NA;221;0
"Building";"CreepTumor";NA;221;0
"Unit";"Hydralisk";"Larva";221;2
"Unit";"Hydralisk";"Larva";221;2
"Unit";"Hydralisk";"Larva";221;2
"Unit";"Hydralisk";"Larva";221;2
"Unit";"Hydralisk";"Larva";221;2
"Unit";"Hydralisk";"Larva";221;2
"Unit";"Hydralisk";"Larva";221;2
"Unit";"Hydralisk";"Larva";221;2
"Building";"CreepTumor";NA;237;0
"Building";"Extractor";NA;221;0
"Building";"CreepTumor";NA;237;0
"Upgrade";"ZergGroundArmorsLevel1";"EvolutionChamber";180;0
"Unit";"Overlord";"Larva";253;0
"Unit";"Queen";"Hatchery";237;2
"Upgrade";"ZergMissileWeaponsLevel2";"EvolutionChamber";180;0
"Building";"CreepTumor";NA;253;0
"Building";"Extractor";NA;253;0
"Unit";"Viper";"Larva";253;3
"Unit";"Viper";"Larva";253;3
"Upgrade";"EvolveMuscularAugments";"HydraliskDen";221;0
"Unit";"Viper";"Larva";253;3
"Unit";"Viper";"Larva";253;3
"Unit";"Overlord";"Larva";253;0
"Building";"CreepTumor";NA;255;0
"Building";"CreepTumor";NA;255;0
"Building";"CreepTumor";NA;267;0
"Building";"CreepTumor";NA;267;0
"Unit";"Overlord";"Larva";267;0
"Unit";"Hydralisk";"Larva";267;2
"Unit";"Hydralisk";"Larva";267;2
"Unit";"Hydralisk";"Larva";267;2
"Unit";"Hydralisk";"Larva";267;2
"Unit";"Hydralisk";"Larva";267;2
"Unit";"Hydralisk";"Larva";267;2
"Unit";"Hydralisk";"Larva";267;2
"Unit";"Hydralisk";"Larva";267;2
"Building";"CreepTumor";NA;267;0
"Unit";"Hydralisk";"Larva";283;2
"Unit";"Hydralisk";"Larva";283;2
"Unit";"Hydralisk";"Larva";283;2
"Unit";"Hydralisk";"Larva";283;2
"Unit";"Hydralisk";"Larva";283;2
"Unit";"Hydralisk";"Larva";283;2
"Unit";"Hydralisk";"Larva";283;2
"Unit";"Hydralisk";"Larva";283;2
"Unit";"Hydralisk";"Larva";283;2
"Unit";"Hydralisk";"Larva";283;2
"Unit";"Hydralisk";"Larva";283;2
"Unit";"Hydralisk";"Larva";283;2
"Unit";"Hydralisk";"Larva";283;2
"Unit";"Hydralisk";"Larva";283;2
"Unit";"Hydralisk";"Larva";283;2
"Unit";"Hydralisk";"Larva";283;2
"Building";"Hatchery";NA;267;0
"Unit";"Overlord";"Larva";283;0
"Unit";"Overlord";"Larva";283;0
"Building";"Hatchery";NA;267;0
"Unit";"Hydralisk";"Larva";283;2
"Unit";"Hydralisk";"Larva";283;2
"Unit";"Overlord";"Larva";283;0
"Building";"CreepTumor";NA;319;0
"Building";"CreepTumor";NA;319;0
"Building";"CreepTumor";NA;319;0
"Building";"Extractor";NA;319;0
"Building";"Extractor";NA;319;0
"Unit";"Overlord";"Larva";319;0
"Building";"Extractor";NA;319;0
"Building";"Extractor";NA;319;0
"Unit";"Corruptor";"Larva";319;2
"Unit";"Corruptor";"Larva";319;2
"Unit";"Corruptor";"Larva";319;2
"Unit";"Corruptor";"Larva";319;2
"Unit";"Corruptor";"Larva";319;2
"Unit";"Corruptor";"Larva";319;2
"Unit";"Corruptor";"Larva";319;2
"Unit";"Corruptor";"Larva";319;2
"Building";"CreepTumor";NA;322;0
"Unit";"Overlord";"Larva";322;0
"Upgrade";"ZergGroundArmorsLevel2";"EvolutionChamber";283;0
"Unit";"Corruptor";"Larva";338;2
"Unit";"Corruptor";"Larva";338;2
"Unit";"Corruptor";"Larva";338;2
"Unit";"Corruptor";"Larva";338;2
"Upgrade";"ZergMissileWeaponsLevel3";"EvolutionChamber";291;0
"Unit";"Viper";"Larva";338;3
"Unit";"Viper";"Larva";338;3
"Unit";"Corruptor";"Larva";338;2
"Unit";"Corruptor";"Larva";338;2
"Unit";"Corruptor";"Larva";338;2
"Unit";"Corruptor";"Larva";338;2
"Unit";"Corruptor";"Larva";338;2
"Unit";"Corruptor";"Larva";338;2
"Unit";"Corruptor";"Larva";338;2
"Unit";"Hydralisk";"Larva";354;2
"Unit";"Hydralisk";"Larva";354;2
"Unit";"Hydralisk";"Larva";354;2
"Unit";"Hydralisk";"Larva";354;2
"Unit";"Hydralisk";"Larva";354;2
"Unit";"Hydralisk";"Larva";354;2
"Unit";"Hydralisk";"Larva";354;2
"Unit";"Hydralisk";"Larva";354;2
"Unit";"Hydralisk";"Larva";354;2
"Unit";"Hydralisk";"Larva";354;2
"Unit";"Hydralisk";"Larva";354;2
"Unit";"Hydralisk";"Larva";354;2
"Unit";"Hydralisk";"Larva";354;2
"Unit";"Overlord";"Larva";364;0
"Building";"Hatchery";NA;338;0
"Building";"SporeCrawler";NA;368;0
"Building";"Hatchery";NA;338;0
"Building";"SporeCrawler";NA;398;0
"Building";"SporeCrawler";NA;402;0
"Building";"SporeCrawler";NA;402;0
"Building";"SporeCrawler";NA;402;0
"Building";"SporeCrawler";NA;402;0
"Building";"SporeCrawler";NA;402;0
"Building";"SporeCrawler";NA;402;0
"Unit";"Corruptor";"Larva";402;2
"Unit";"Corruptor";"Larva";402;2
"Unit";"Corruptor";"Larva";402;2
