"Type";"UnitName";"OnBuilding";"TotalSupply";"Supply"
"Unit";"SCV";"Command Center";12;1
"Unit";"SCV";"Command Center";13;1
"Unit";"SCV";"Command Center";13;1
"Building";"SupplyDepot";NA;13;0
"Unit";"SCV";"Command Center";15;1
"Unit";"SCV";"Command Center";15;1
"Building";"Refinery";NA;15;0
"Unit";"SCV";"Command Center";16;1
"Unit";"SCV";"Command Center";17;1
"Building";"Barracks";NA;15;0
"Unit";"Reaper";"Barracks";19;1
"Unit";"SCV";"Command Center";19;1
"Building";"BarracksTechLab";NA;20;0
"Unit";"SCV";"Command Center";21;1
"Building";"SupplyDepot";NA;21;0
"Unit";"SCV";"Command Center";21;1
"Building";"Barracks";NA;20;0
"Unit";"SCV";"Command Center";22;1
"Unit";"Marauder";"Barracks";22;2
"Unit";"SCV";"Command Center";24;1
"Building";"CommandCenter";NA;19;0
"Unit";"Marine";"Barracks";24;1
"Building";"Refinery";NA;24;0
"Unit";"Marauder";"Barracks";26;2
"Building";"Barracks";NA;22;0
"Unit";"SCV";"Command Center";27;1
"Unit";"Marine";"Barracks";28;1
"Unit";"SCV";"Command Center";30;1
"Unit";"Marine";"Barracks";31;1
"Unit";"Marine";"Barracks";31;1
"Unit";"SCV";"Command Center";32;1
"Unit";"SCV";"Command Center";33;1
"Building";"EngineeringBay";NA;32;0
"Unit";"SCV";"Command Center";35;1
"Unit";"Marine";"Barracks";35;1
"Unit";"Marine";"Barracks";36;1
"Unit";"SCV";"Command Center";36;1
"Unit";"SCV";"Command Center";37;1
"Building";"BarracksReactor";NA;33;0
"Building";"MissileTurret";NA;38;0
"Unit";"SCV";"Command Center";40;1
"Building";"MissileTurret";NA;38;0
"Unit";"Marine";"Barracks";38;1
"Unit";"SCV";"Command Center";42;1
"Building";"SupplyDepot";NA;40;0
"Unit";"SCV";"Command Center";43;1
"Unit";"Marine";"Barracks";42;1
"Unit";"SCV";"Command Center";45;1
"Unit";"SCV";"Command Center";45;1
"Unit";"Marine";"Barracks";45;1
"Unit";"Marine";"Barracks";45;1
"Unit";"SCV";"Command Center";47;1
"Unit";"SCV";"Command Center";48;1
"Unit";"Marauder";"Barracks";47;2
"Building";"BarracksTechLab";NA;49;0
"Building";"SupplyDepot";NA;48;0
"Building";"Refinery";NA;51;0
"Unit";"SCV";"Command Center";55;1
"Building";"Factory";NA;45;0
"Upgrade";"Stimpack";"TechLab";36;0
"Unit";"SCV";"Command Center";55;1
"Building";"SupplyDepot";NA;53;0
"Unit";"Marine";"Barracks";55;1
"Unit";"Marine";"Barracks";55;1
"Unit";"Marine";"Barracks";55;1
"Unit";"Marine";"Barracks";55;1
"Unit";"SCV";"Command Center";55;1
"Building";"SupplyDepot";NA;55;0
"Unit";"SCV";"Command Center";56;1
"Unit";"SCV";"Command Center";61;1
"Unit";"SCV";"Command Center";63;1
"Unit";"Marine";"Barracks";62;1
"Unit";"Marine";"Barracks";62;1
"Unit";"Marauder";"Barracks";62;2
"Unit";"SCV";"Command Center";64;1
"Building";"Starport";NA;56;0
"Building";"SupplyDepot";NA;62;0
"Building";"FactoryReactor";NA;56;0
"Unit";"Marauder";"Barracks";63;2
"Unit";"SCV";"Command Center";67;1
"Unit";"SCV";"Command Center";70;1
"Unit";"Marine";"Barracks";67;1
"Unit";"Marine";"Barracks";67;1
"Unit";"SCV";"Command Center";73;1
"Building";"SupplyDepot";NA;70;0
"Unit";"SCV";"Command Center";76;1
"Unit";"Marauder";"Barracks";73;2
"Unit";"Marauder";"Barracks";73;2
"Unit";"Marine";"Barracks";76;1
"Unit";"Medivac";"Starport";73;2
"Unit";"Medivac";"Starport";73;2
"Unit";"SCV";"Command Center";78;1
"Unit";"Marine";"Barracks";77;1
"Building";"Refinery";NA;77;0
"Upgrade";"TerranInfantryWeaponsLevel1";"EngineeringBay";56;0
"Building";"SupplyDepot";NA;77;0
"Unit";"SCV";"Command Center";83;1
"Unit";"Marine";"Barracks";78;1
"Building";"FactoryReactor";NA;76;0
"Unit";"Marauder";"Barracks";82;2
"Unit";"SCV";"Command Center";89;1
"Unit";"Marine";"Barracks";89;1
"Unit";"Marine";"Barracks";89;1
"Building";"CommandCenter";NA;65;0
"Unit";"Marine";"Barracks";90;1
"Unit";"SCV";"Command Center";94;1
"Unit";"SCV";"Command Center";96;1
"Unit";"Marine";"Barracks";94;1
"Unit";"Marine";"Barracks";94;1
"Unit";"Medivac";"Starport";91;2
"Unit";"Medivac";"Starport";91;2
"Unit";"Marine";"Barracks";96;1
"Unit";"Marauder";"Barracks";96;2
"Building";"Barracks";NA;89;0
"Building";"Barracks";NA;89;0
"Unit";"SCV";"Command Center";101;1
"Unit";"SCV";"Command Center";108;1
"Unit";"Marine";"Barracks";108;1
"Unit";"Marine";"Barracks";108;1
"Unit";"Marauder";"Barracks";108;2
"Unit";"Medivac";"Starport";108;2
"Unit";"Medivac";"Starport";108;2
"Building";"BarracksTechLab";NA;110;0
"Building";"SupplyDepot";NA;110;0
"Building";"SupplyDepot";NA;112;0
"Unit";"Marine";"Barracks";114;1
"Unit";"Marine";"Barracks";114;1
"Building";"BarracksReactor";NA;110;0
"Unit";"Marauder";"Barracks";114;2
"Unit";"Marine";"Barracks";118;1
"Unit";"Marine";"Barracks";118;1
"Unit";"Marine";"Barracks";118;1
"Unit";"Marine";"Barracks";119;1
"Unit";"Medivac";"Starport";118;2
"Unit";"Medivac";"Starport";118;2
"Unit";"Marine";"Barracks";123;1
"Unit";"Marine";"Barracks";124;1
"Unit";"Marine";"Barracks";124;1
"Unit";"Marauder";"Barracks";120;2
"Unit";"Marauder";"Barracks";122;2
"Unit";"Marine";"Barracks";124;1
"Unit";"Marine";"Barracks";125;1
"Unit";"Marine";"Barracks";130;1
"Unit";"Marine";"Barracks";131;1
"Unit";"Marine";"Barracks";132;1
"Unit";"Marine";"Barracks";133;1
"Unit";"Marauder";"Barracks";135;2
"Unit";"Marine";"Barracks";137;1
"Unit";"Marine";"Barracks";138;1
"Unit";"Marine";"Barracks";145;1
"Unit";"Marine";"Barracks";147;1
"Unit";"Marine";"Barracks";147;1
"Unit";"Marauder";"Barracks";147;2
"Unit";"Marine";"Barracks";152;1
"Unit";"Marine";"Barracks";152;1
"Unit";"Marine";"Barracks";152;1
"Unit";"Marine";"Barracks";152;1
"Unit";"Marauder";"Barracks";152;2
"Unit";"Marauder";"Barracks";152;2
"Unit";"Marauder";"Barracks";152;2
"Unit";"SCV";"Command Center";152;1
"Unit";"SCV";"Command Center";152;1
"Building";"SupplyDepot";NA;152;0
"Building";"Refinery";NA;152;0
"Unit";"Marine";"Barracks";152;1
"Unit";"Marine";"Barracks";152;1
"Unit";"Marauder";"Barracks";164;2
"Unit";"Marauder";"Barracks";164;2
"Building";"SupplyDepot";NA;164;0
"Building";"SupplyDepot";NA;164;0
"Unit";"Marine";"Barracks";170;1
"Unit";"Marine";"Barracks";170;1
"Unit";"Marine";"Barracks";170;1
"Unit";"Marine";"Barracks";170;1
"Unit";"Marauder";"Barracks";170;2
"Unit";"Marauder";"Barracks";170;2
"Unit";"Marine";"Barracks";178;1
"Unit";"Marine";"Barracks";178;1
"Unit";"Marine";"Barracks";178;1
"Unit";"Marine";"Barracks";178;1
"Unit";"Marauder";"Barracks";178;2
