"Type";"UnitName";"OnBuilding";"TotalSupply";"Supply"
"Unit";"SCV";"Command Center";12;1
"Unit";"SCV";"Command Center";12;1
"Unit";"SCV";"Command Center";13;1
"Building";"SupplyDepot";NA;13;0
"Building";"Refinery";NA;14;0
"Unit";"SCV";"Command Center";15;1
"Unit";"SCV";"Command Center";15;1
"Unit";"SCV";"Command Center";16;1
"Building";"Barracks";NA;15;0
"Unit";"SCV";"Command Center";17;1
"Unit";"Marine";"Barracks";18;1
"Building";"SupplyDepot";NA;19;0
"Unit";"Marine";"Barracks";19;1
"Unit";"SCV";"Command Center";20;1
"Building";"Factory";NA;18;0
"Unit";"Marine";"Barracks";20;1
"Building";"Bunker";NA;20;0
"Unit";"SCV";"Command Center";21;1
"Unit";"Marine";"Barracks";22;1
"Building";"SupplyDepot";NA;23;0
"Unit";"Cyclone";"Factory";24;3
"Unit";"SCV";"Command Center";24;1
"Unit";"Marine";"Barracks";24;1
"Unit";"SCV";"Command Center";29;1
"Unit";"Marine";"Barracks";29;1
"Unit";"SCV";"Command Center";30;1
"Unit";"Cyclone";"Factory";29;3
"Building";"Bunker";NA;24;0
"Unit";"Marine";"Barracks";36;1
"Building";"Refinery";NA;36;0
"Unit";"Cyclone";"Factory";36;3
"Building";"SupplyDepot";NA;40;0
"Unit";"SCV";"Command Center";40;1
"Building";"EngineeringBay";NA;40;0
"Building";"BarracksReactor";NA;37;0
"Unit";"SCV";"Command Center";40;1
"Unit";"SCV";"Command Center";41;1
"Building";"CommandCenter";NA;36;0
"Building";"Starport";NA;40;0
"Unit";"Marine";"Barracks";42;1
"Building";"FactoryTechLab";NA;42;0
"Unit";"Marine";"Barracks";42;1
"Building";"MissileTurret";NA;42;0
"Unit";"Marine";"Barracks";43;1
"Unit";"Marine";"Barracks";44;1
"Unit";"SCV";"Command Center";45;1
"Unit";"Medivac";"Starport";43;2
"Unit";"SCV";"Command Center";47;1
"Unit";"Marine";"Barracks";45;1
"Unit";"Marine";"Barracks";46;1
"Unit";"SCV";"Command Center";53;1
"Unit";"Marine";"Barracks";51;1
"Unit";"Marine";"Barracks";52;1
"Unit";"SCV";"Command Center";54;1
"Unit";"Marine";"Barracks";54;1
"Unit";"Marine";"Barracks";55;1
"Unit";"SCV";"Command Center";56;1
"Unit";"SCV";"Command Center";57;1
"Unit";"SCV";"Command Center";59;1
"Unit";"Marine";"Barracks";57;1
"Unit";"Marine";"Barracks";58;1
"Unit";"SCV";"Command Center";60;1
"Building";"MissileTurret";NA;60;0
"Unit";"SCV";"Command Center";61;1
"Unit";"SCV";"Command Center";64;1
"Building";"SupplyDepot";NA;61;0
"Unit";"Marine";"Barracks";62;1
"Unit";"Marine";"Barracks";63;1
"Unit";"SCV";"Command Center";67;1
"Unit";"SCV";"Command Center";67;1
"Building";"MissileTurret";NA;66;0
"Building";"SupplyDepot";NA;69;0
"Unit";"SCV";"Command Center";69;1
"Unit";"SCV";"Command Center";69;1
"Unit";"Marine";"Barracks";69;1
"Unit";"Marine";"Barracks";69;1
"Building";"StarportTechLab";NA;69;0
"Building";"Refinery";NA;71;0
"Building";"Refinery";NA;71;0
"Unit";"SCV";"Command Center";71;1
"Unit";"SCV";"Command Center";71;1
"Unit";"Marine";"Barracks";77;1
"Unit";"Marine";"Barracks";77;1
"Unit";"Banshee";"Starport";77;3
"Unit";"SCV";"Command Center";82;1
"Unit";"SCV";"Command Center";82;1
"Building";"CommandCenter";NA;75;0
"Unit";"SCV";"Command Center";82;1
"Unit";"SCV";"Command Center";83;1
"Building";"Factory";NA;77;0
"Building";"Factory";NA;77;0
"Unit";"SCV";"Command Center";84;1
"Unit";"SCV";"Command Center";85;1
"Unit";"Banshee";"Starport";82;3
"Unit";"Hellion";"Factory";84;2
"Unit";"SCV";"Command Center";86;1
"Unit";"SCV";"Command Center";87;1
"Building";"BarracksReactor";NA;84;0
"Building";"SupplyDepot";NA;87;0
"Unit";"Hellion";"Factory";95;2
"Unit";"Hellion";"Factory";95;2
"Building";"Armory";NA;86;0
"Unit";"Hellion";"Factory";95;2
"Unit";"Hellion";"Factory";95;2
"Building";"SupplyDepot";NA;95;0
"Unit";"Hellion";"Factory";95;2
"Unit";"Hellion";"Factory";97;2
"Building";"Starport";NA;95;0
"Unit";"Hellion";"Factory";99;2
"Unit";"Hellion";"Factory";101;2
"Unit";"Hellion";"Factory";107;2
"Unit";"Hellion";"Factory";107;2
"Unit";"Banshee";"Starport";99;3
"Unit";"Hellion";"Factory";107;2
"Building";"Armory";NA;107;0
"Unit";"SCV";"Command Center";120;1
"Unit";"SCV";"Command Center";120;1
"Unit";"SCV";"Command Center";120;1
"Building";"StarportTechLab";NA;120;0
"Unit";"Hellion";"Factory";120;2
"Unit";"Hellion";"Factory";120;2
"Unit";"Hellion";"Factory";120;2
"Unit";"Hellion";"Factory";120;2
"Unit";"SCV";"Command Center";120;1
"Unit";"SCV";"Command Center";121;1
"Unit";"SCV";"Command Center";131;1
"Building";"SupplyDepot";NA;120;0
"Building";"SupplyDepot";NA;120;0
"Building";"SupplyDepot";NA;120;0
"Building";"MissileTurret";NA;123;0
"Unit";"Banshee";"Starport";120;3
"Building";"Refinery";NA;131;0
"Building";"Refinery";NA;131;0
"Building";"Factory";NA;123;0
"Unit";"Hellion";"Factory";137;2
"Unit";"Hellion";"Factory";137;2
"Unit";"Hellion";"Factory";137;2
"Unit";"Hellion";"Factory";137;2
"Unit";"SCV";"Command Center";137;1
"Unit";"SCV";"Command Center";137;1
"Upgrade";"TerranVehicleWeaponsLevel1";"Armory";120;0
"Unit";"SCV";"Command Center";137;1
"Unit";"Banshee";"Starport";134;3
"Unit";"Banshee";"Starport";137;3
