"type";"unit_name";"on_building";"total_supply_lag";"supply"
"Building";"Barracks";NA;16;0
"Building";"Refinery";NA;16;0
"Unit";"Reaper";"Barracks";19;1
"Building";"CommandCenter";NA;20;0
"Building";"BarracksReactor";NA;21;0
"Building";"CommandCenter";NA;23;0
"Building";"Barracks";NA;24;0
"Unit";"Marine";"Barracks";24;1
"Unit";"Marine";"Barracks";25;1
"Unit";"Marine";"Barracks";26;1
"Unit";"Marine";"Barracks";27;1
"Building";"EngineeringBay";NA;29;0
"Unit";"Marine";"Barracks";30;1
"Unit";"Marine";"Barracks";31;1
"Building";"BarracksTechLab";NA;32;0
"Unit";"Marine";"Barracks";34;1
"Unit";"Marine";"Barracks";35;1
"Building";"MissileTurret";NA;37;0
"Unit";"Marine";"Barracks";38;1
"Unit";"Marine";"Barracks";40;1
"Unit";"Marine";"Barracks";41;1
"Unit";"Marine";"Barracks";44;1
"Unit";"Marine";"Barracks";46;1
"Unit";"Marine";"Barracks";47;1
"Building";"Barracks";NA;49;0
"Upgrade";"Stimpack";"TechLab";50;0
"Building";"Factory";NA;50;0
"Building";"Refinery";NA;50;0
"Building";"Refinery";NA;50;0
"Unit";"Marine";"Barracks";50;1
"Upgrade";"TerranInfantryWeaponsLevel1";"EngineeringBay";53;0
"Building";"Bunker";NA;54;0
"Unit";"Marine";"Barracks";54;1
"Unit";"Marine";"Barracks";57;1
"Unit";"Marine";"Barracks";58;1
"Unit";"Marine";"Barracks";62;1
"Unit";"Marine";"Barracks";64;1
"Unit";"Marine";"Barracks";65;1
"Building";"FactoryReactor";NA;66;0
"Building";"Starport";NA;68;0
"Building";"Refinery";NA;68;0
"Unit";"Marine";"Barracks";68;1
"Building";"BarracksTechLab";NA;70;0
"Building";"Barracks";NA;70;0
"Building";"Barracks";NA;72;0
"Building";"MissileTurret";NA;72;0
"Unit";"Marauder";"Barracks";74;2
"Unit";"Marine";"Barracks";77;1
"Unit";"Marauder";"Barracks";78;2
"Building";"FactoryReactor";NA;80;0
"Unit";"Marauder";"Barracks";80;2
"Unit";"Marine";"Barracks";84;1
"Unit";"Marine";"Barracks";85;1
"Unit";"Medivac";"Starport";86;2
"Building";"BarracksReactor";NA;88;0
"Unit";"Medivac";"Starport";91;2
"Unit";"Marauder";"Barracks";93;2
"Building";"BarracksReactor";NA;95;0
"Unit";"Marine";"Barracks";98;1
"Unit";"Marauder";"Barracks";99;2
"Unit";"Medivac";"Starport";101;2
"Building";"Refinery";NA;105;0
"Unit";"Marine";"Barracks";106;1
"Unit";"Marine";"Barracks";107;1
"Unit";"Marine";"Barracks";108;1
"Unit";"Medivac";"Starport";109;2
"Unit";"Marine";"Barracks";111;1
"Unit";"Marine";"Barracks";112;1
"Unit";"Marine";"Barracks";113;1
"Unit";"Marauder";"Barracks";114;2
"Unit";"Marine";"Barracks";116;1
"Unit";"Marine";"Barracks";117;1
"Unit";"Marine";"Barracks";118;1
"Unit";"Marine";"Barracks";119;1
"Unit";"Marauder";"Barracks";120;2
"Unit";"Marauder";"Barracks";123;2
"Unit";"Marine";"Barracks";126;1
"Unit";"Marine";"Barracks";127;1
"Unit";"Marauder";"Barracks";129;2
"Unit";"Medivac";"Starport";132;2
"Unit";"Marauder";"Barracks";134;2
"Unit";"Marine";"Barracks";136;1
"Unit";"Marine";"Barracks";137;1
"Unit";"Medivac";"Starport";140;2
"Unit";"Marauder";"Barracks";143;2
"Unit";"Marine";"Barracks";145;1
"Unit";"Marauder";"Barracks";146;2
"Unit";"Marine";"Barracks";149;1
"Unit";"Marine";"Barracks";150;1
"Unit";"Marine";"Barracks";151;1
"Unit";"Medivac";"Starport";152;2
"Unit";"Marine";"Barracks";154;1
"Unit";"Marine";"Barracks";157;1
"Unit";"Medivac";"Starport";158;2
"Unit";"Marauder";"Barracks";160;2
"Unit";"Marauder";"Barracks";162;2
"Unit";"Marine";"Barracks";164;1
"Unit";"Marine";"Barracks";165;1
"Unit";"Marine";"Barracks";166;1
"Unit";"Marine";"Barracks";167;1
"Unit";"Marine";"Barracks";168;1
"Building";"Barracks";NA;169;0
"Unit";"Medivac";"Starport";169;2
"Building";"Barracks";NA;171;0
"Unit";"Marauder";"Barracks";171;2
"Building";"Barracks";NA;173;0
"Building";"GhostAcademy";NA;173;0
"Unit";"Marauder";"Barracks";173;2
"Unit";"Medivac";"Starport";176;2
"Unit";"Marine";"Barracks";183;1
"Unit";"Marine";"Barracks";184;1
"Unit";"Medivac";"Starport";185;2
"Unit";"Ghost";"Barracks";189;2
"Unit";"Ghost";"Barracks";191;2
"Unit";"Medivac";"Starport";194;2
"Building";"BarracksTechLab";NA;197;0
"Building";"BarracksTechLab";NA;197;0
"Unit";"Marine";"Barracks";197;1
"Unit";"Marine";"Barracks";198;1
"Building";"BarracksReactor";NA;199;0
"Unit";"Marine";"Barracks";199;1
"Unit";"Marine";"Barracks";200;1
"Unit";"Marauder";"Barracks";201;2
"Unit";"Marauder";"Barracks";203;2
"Unit";"Marine";"Barracks";205;1
"Unit";"Marauder";"Barracks";206;2
"Unit";"Marine";"Barracks";208;1
"Unit";"Marauder";"Barracks";209;2
"Unit";"Marine";"Barracks";211;1
"Unit";"Marauder";"Barracks";215;2
"Unit";"Marauder";"Barracks";217;2
"Unit";"Marine";"Barracks";222;1
"Unit";"Marauder";"Barracks";223;2
"Unit";"Marine";"Barracks";226;1
"Unit";"Marauder";"Barracks";227;2
"Unit";"Marine";"Barracks";230;1
"Unit";"Marauder";"Barracks";231;2
"Unit";"Marine";"Barracks";233;1
"Unit";"Marine";"Barracks";234;1
"Unit";"Marauder";"Barracks";235;2
"Unit";"Marine";"Barracks";237;1
"Unit";"Marauder";"Barracks";238;2
"Unit";"Marine";"Barracks";240;1
"Unit";"Marauder";"Barracks";241;2
"Unit";"Marine";"Barracks";243;1
"Unit";"Marauder";"Barracks";244;2
"Unit";"Marine";"Barracks";246;1
"Unit";"Marine";"Barracks";247;1
"Unit";"Marauder";"Barracks";248;2
"Unit";"Marauder";"Barracks";250;2
"Unit";"Marine";"Barracks";252;1
"Unit";"Marine";"Barracks";253;1
"Unit";"Marine";"Barracks";254;1
"Unit";"Marine";"Barracks";255;1
"Unit";"Marine";"Barracks";256;1
"Unit";"Marauder";"Barracks";257;2
"Unit";"Marine";"Barracks";259;1
"Unit";"Marauder";"Barracks";260;2
"Unit";"Marine";"Barracks";262;1
"Unit";"Ghost";"Barracks";263;2
"Unit";"Ghost";"Barracks";265;2
"Building";"Starport";NA;267;0
"Unit";"Marine";"Barracks";267;1
"Unit";"Marauder";"Barracks";268;2
"Unit";"Marine";"Barracks";270;1
"Unit";"Marauder";"Barracks";271;2
"Unit";"Marine";"Barracks";273;1
"Unit";"Marine";"Barracks";274;1
"Unit";"Marine";"Barracks";275;1
"Unit";"Marine";"Barracks";276;1
"Unit";"Marauder";"Barracks";277;2
"Unit";"Marauder";"Barracks";279;2
"Unit";"Marine";"Barracks";281;1
"Unit";"Marauder";"Barracks";282;2
"Unit";"Marine";"Barracks";284;1
"Unit";"Marauder";"Barracks";285;2
"Unit";"Marine";"Barracks";287;1
"Unit";"Marine";"Barracks";288;1
"Unit";"Marauder";"Barracks";289;2
"Unit";"Marine";"Barracks";291;1
"Unit";"Marauder";"Barracks";292;2
"Unit";"Marine";"Barracks";294;1
"Unit";"Marauder";"Barracks";295;2
"Unit";"Marine";"Barracks";297;1
"Unit";"Marauder";"Barracks";298;2
"Upgrade";"SprayTerran";NA;300;0
"Upgrade";"SprayTerran";NA;300;0
"Upgrade";"SprayTerran";NA;300;0
"Upgrade";"SprayTerran";NA;300;0
"Upgrade";"PunisherGrenades";NA;300;0
"Upgrade";"ShieldWall";NA;300;0
"Upgrade";"TerranInfantryArmorsLevel1";NA;300;0
