"type";"unit_name";"on_building";"total_supply";"supply"
"Building";"Refinery";NA;15;0
"Building";"Barracks";NA;15;0
"Building";"BarracksReactor";NA;19;0
"Unit";"Marine";"Barracks";19;1
"Unit";"Marine";"Barracks";19;1
"Unit";"Marine";"Barracks";23;1
"Unit";"Marine";"Barracks";23;1
"Building";"Refinery";NA;23;0
"Building";"CommandCenter";NA;19;0
"Unit";"Marine";"Barracks";26;1
"Unit";"Marine";"Barracks";26;1
"Building";"Factory";NA;21;0
"Unit";"Marine";"Barracks";29;1
"Unit";"Marine";"Barracks";30;1
"Building";"FactoryTechLab";NA;30;0
"Unit";"Marine";"Barracks";33;1
"Unit";"Marine";"Barracks";33;1
"Building";"Barracks";NA;30;0
"Unit";"Marine";"Barracks";38;1
"Unit";"Marine";"Barracks";38;1
"Building";"BarracksTechLab";NA;40;0
"Building";"EngineeringBay";NA;41;0
"Unit";"Marine";"Barracks";45;1
"Unit";"Marine";"Barracks";47;1
"Unit";"Marine";"Barracks";47;1
"Building";"Starport";NA;46;0
"Unit";"Marine";"Barracks";50;1
"Unit";"Marine";"Barracks";54;1
"Unit";"Marine";"Barracks";54;1
"Unit";"Marine";"Barracks";56;1
"Building";"FactoryReactor";NA;54;0
"Building";"Refinery";NA;57;0
"Building";"Refinery";NA;57;0
"Building";"Barracks";NA;53;0
"Unit";"Marine";"Barracks";61;1
"Building";"StarportReactor";NA;56;0
"Unit";"Marine";"Barracks";63;1
"Unit";"Marauder";"Barracks";63;2
"Unit";"Marauder";"Barracks";66;2
"Unit";"Marine";"Barracks";68;1
"Unit";"Marine";"Barracks";68;1
"Unit";"Marine";"Barracks";72;1
"Upgrade";"Stimpack";"TechLab";53;0
"Upgrade";"TerranInfantryWeaponsLevel1";"EngineeringBay";55;0
"Unit";"Medivac";"Starport";71;2
"Unit";"Medivac";"Starport";72;2
"Building";"MissileTurret";NA;76;0
"Building";"MissileTurret";NA;78;0
"Unit";"Marine";"Barracks";78;1
"Unit";"Marine";"Barracks";78;1
"Unit";"Marauder";"Barracks";78;2
"Unit";"Marine";"Barracks";85;1
"Unit";"Marauder";"Barracks";88;2
"Unit";"Medivac";"Starport";85;2
"Unit";"Medivac";"Starport";85;2
"Unit";"Marine";"Barracks";92;1
"Unit";"Marine";"Barracks";92;1
"Unit";"Marine";"Barracks";92;1
"Unit";"Marine";"Barracks";92;1
"Unit";"Marine";"Barracks";103;1
"Unit";"Marine";"Barracks";103;1
"Unit";"Marine";"Barracks";103;1
"Unit";"Marine";"Barracks";103;1
"Unit";"Liberator";"Starport";102;3
"Unit";"Liberator";"Starport";103;3
"Unit";"Marine";"Barracks";108;1
"Unit";"Marine";"Barracks";108;1
"Unit";"Marauder";"Barracks";108;2
"Unit";"Marauder";"Barracks";108;2
"Unit";"Marine";"Barracks";116;1
"Unit";"Marauder";"Barracks";122;2
"Unit";"Medivac";"Starport";118;2
"Unit";"Medivac";"Starport";118;2
"Unit";"Marine";"Barracks";123;1
"Unit";"Marine";"Barracks";123;1
"Upgrade";"TerranInfantryArmorsLevel1";"EngineeringBay";104;0
"Unit";"Marauder";"Barracks";123;2
"Unit";"Marine";"Barracks";123;1
"Unit";"Marine";"Barracks";129;1
"Unit";"Medivac";"Starport";125;2
"Unit";"Medivac";"Starport";127;2
"Unit";"Marine";"Barracks";134;1
"Unit";"Marine";"Barracks";134;1
"Unit";"Marauder";"Barracks";134;2
"Unit";"Marine";"Barracks";134;1
