"Type";"UnitName";"OnBuilding";"TotalSupply";"Supply"
"Unit";"SCV";"Command Center";12;1
"Unit";"SCV";"Command Center";12;1
"Unit";"SCV";"Command Center";13;1
"Building";"SupplyDepot";NA;13;0
"Unit";"SCV";"Command Center";15;1
"Unit";"SCV";"Command Center";15;1
"Unit";"SCV";"Command Center";16;1
"Building";"Refinery";NA;17;0
"Building";"Barracks";NA;15;0
"Unit";"SCV";"Command Center";17;1
"Unit";"Marine";"Barracks";19;1
"Building";"SupplyDepot";NA;19;0
"Unit";"SCV";"Command Center";20;1
"Building";"BarracksTechLab";NA;20;0
"Unit";"SCV";"Command Center";20;1
"Unit";"SCV";"Command Center";21;1
"Unit";"Marauder";"Barracks";21;2
"Unit";"SCV";"Command Center";22;1
"Building";"CommandCenter";NA;19;0
"Unit";"Marauder";"Barracks";23;2
"Unit";"SCV";"Command Center";25;1
"Building";"Barracks";NA;21;0
"Building";"Refinery";NA;25;0
"Unit";"SCV";"Command Center";28;1
"Unit";"Marine";"Barracks";26;1
"Building";"Barracks";NA;25;0
"Unit";"SCV";"Command Center";31;1
"Unit";"Marine";"Barracks";31;1
"Unit";"SCV";"Command Center";31;1
"Unit";"SCV";"Command Center";32;1
"Unit";"SCV";"Command Center";33;1
"Building";"EngineeringBay";NA;31;0
"Building";"BarracksReactor";NA;31;0
"Unit";"Marine";"Barracks";34;1
"Unit";"SCV";"Command Center";34;1
"Unit";"SCV";"Command Center";35;1
"Building";"SupplyDepot";NA;34;0
"Building";"BarracksReactor";NA;31;0
"Unit";"SCV";"Command Center";37;1
"Unit";"SCV";"Command Center";38;1
"Unit";"SCV";"Command Center";39;1
"Unit";"Marine";"Barracks";39;1
"Unit";"Marine";"Barracks";39;1
"Unit";"Marine";"Barracks";39;1
"Unit";"SCV";"Command Center";40;1
"Unit";"Marine";"Barracks";39;1
"Unit";"Marauder";"Barracks";39;2
"Unit";"SCV";"Command Center";41;1
"Unit";"SCV";"Command Center";45;1
"Unit";"Marine";"Barracks";43;1
"Unit";"Marine";"Barracks";44;1
"Unit";"Marine";"Barracks";44;1
"Unit";"Marine";"Barracks";46;1
"Building";"SupplyDepot";NA;44;0
"Unit";"SCV";"Command Center";49;1
"Unit";"SCV";"Command Center";50;1
"Building";"Refinery";NA;49;0
"Building";"MissileTurret";NA;50;0
"Building";"Factory";NA;40;0
"Unit";"SCV";"Command Center";55;1
"Unit";"Marine";"Barracks";54;1
"Unit";"Marine";"Barracks";54;1
"Unit";"SCV";"Command Center";56;1
"Unit";"Marine";"Barracks";55;1
"Unit";"Marine";"Barracks";55;1
"Upgrade";"Stimpack";"TechLab";34;0
"Unit";"Marauder";"Barracks";55;2
"Building";"SupplyDepot";NA;56;0
"Unit";"SCV";"Command Center";57;1
"Unit";"SCV";"Command Center";60;1
"Building";"SupplyDepot";NA;57;0
"Unit";"SCV";"Command Center";65;1
"Unit";"Marine";"Barracks";66;1
"Unit";"Marine";"Barracks";66;1
"Unit";"Marine";"Barracks";66;1
"Unit";"Marine";"Barracks";66;1
"Building";"SupplyDepot";NA;66;0
"Unit";"SCV";"Command Center";67;1
"Building";"Starport";NA;57;0
"Building";"FactoryReactor";NA;57;0
"Unit";"SCV";"Command Center";67;1
"Unit";"Marauder";"Barracks";67;2
"Unit";"SCV";"Command Center";72;1
"Unit";"SCV";"Command Center";73;1
"Unit";"Marine";"Barracks";68;1
"Unit";"Marine";"Barracks";69;1
"Unit";"Marine";"Barracks";70;1
"Unit";"Marine";"Barracks";71;1
"Building";"SupplyDepot";NA;68;0
"Unit";"Marauder";"Barracks";74;2
"Building";"SupplyDepot";NA;76;0
"Unit";"Marine";"Barracks";78;1
"Upgrade";"TerranInfantryWeaponsLevel1";"EngineeringBay";55;0
"Unit";"Marine";"Barracks";82;1
"Unit";"Marine";"Barracks";82;1
"Unit";"Marine";"Barracks";82;1
"Building";"FactoryReactor";NA;76;0
"Unit";"Medivac";"Starport";82;2
"Unit";"Medivac";"Starport";82;2
"Building";"SupplyDepot";NA;84;0
"Building";"SupplyDepot";NA;85;0
"Unit";"Marine";"Barracks";88;1
"Unit";"Marine";"Barracks";88;1
"Unit";"Marine";"Barracks";88;1
"Unit";"Marine";"Barracks";88;1
"Unit";"Marauder";"Barracks";88;2
"Building";"Barracks";NA;82;0
"Building";"Barracks";NA;82;0
"Unit";"SCV";"Command Center";98;1
"Unit";"SCV";"Command Center";98;1
"Unit";"Medivac";"Starport";92;2
"Unit";"Medivac";"Starport";92;2
"Unit";"SCV";"Command Center";98;1
"Unit";"SCV";"Command Center";99;1
"Building";"Refinery";NA;88;0
"Unit";"Marine";"Barracks";104;1
"Unit";"Marine";"Barracks";104;1
"Unit";"Marine";"Barracks";104;1
"Unit";"Marine";"Barracks";104;1
"Building";"BarracksTechLab";NA;104;0
"Building";"BarracksTechLab";NA;104;0
"Unit";"Medivac";"Starport";100;2
"Unit";"Medivac";"Starport";102;2
"Unit";"Marauder";"Barracks";106;2
"Unit";"Marine";"Barracks";110;1
"Unit";"Marine";"Barracks";110;1
"Unit";"Marine";"Barracks";110;1
"Unit";"Marine";"Barracks";110;1
"Building";"SupplyDepot";NA;106;0
"Building";"SupplyDepot";NA;106;0
"Unit";"Marine";"Barracks";120;1
"Unit";"Marine";"Barracks";120;1
"Unit";"Marine";"Barracks";120;1
"Unit";"Marine";"Barracks";120;1
"Unit";"Marine";"Barracks";120;1
"Unit";"Marauder";"Barracks";120;2
"Unit";"Marauder";"Barracks";120;2
"Upgrade";"TerranInfantryArmorsLevel1";"EngineeringBay";98;0
"Unit";"Marine";"Barracks";120;1
"Unit";"Marine";"Barracks";121;1
"Unit";"Marine";"Barracks";129;1
"Unit";"Marine";"Barracks";129;1
"Unit";"Marine";"Barracks";129;1
"Unit";"Marauder";"Barracks";129;2
"Unit";"Marauder";"Barracks";129;2
"Unit";"Marine";"Barracks";134;1
"Unit";"Marauder";"Barracks";133;2
"Unit";"Marauder";"Barracks";134;2
"Unit";"Marauder";"Barracks";136;2
"Unit";"Liberator";"Starport";129;3
"Unit";"Marine";"Barracks";138;1
"Unit";"Marine";"Barracks";138;1
"Building";"SupplyDepot";NA;138;0
"Unit";"Marauder";"Barracks";139;2
"Unit";"Marauder";"Barracks";141;2
"Unit";"Marine";"Barracks";148;1
"Unit";"Marine";"Barracks";148;1
"Unit";"Marauder";"Barracks";148;2
"Unit";"Liberator";"Starport";138;3
