"Type";"UnitName";"OnBuilding";"TotalSupply";"Supply"
"Unit";"SCV";"Command Center";12;1
"Unit";"SCV";"Command Center";12;1
"Unit";"SCV";"Command Center";13;1
"Building";"SupplyDepot";NA;13;0
"Unit";"SCV";"Command Center";15;1
"Building";"Refinery";NA;14;0
"Unit";"SCV";"Command Center";16;1
"Unit";"SCV";"Command Center";16;1
"Unit";"SCV";"Command Center";17;1
"Building";"Barracks";NA;15;0
"Unit";"Marine";"Barracks";19;1
"Unit";"SCV";"Command Center";20;1
"Unit";"SCV";"Command Center";20;1
"Building";"Refinery";NA;20;0
"Building";"BarracksReactor";NA;20;0
"Building";"Factory";NA;20;0
"Unit";"SCV";"Command Center";21;1
"Building";"SupplyDepot";NA;21;0
"Unit";"SCV";"Command Center";23;1
"Building";"CommandCenter";NA;19;0
"Unit";"SCV";"Command Center";24;1
"Unit";"Marine";"Barracks";24;1
"Unit";"Cyclone";"Factory";24;3
"Unit";"SCV";"Command Center";24;1
"Unit";"Cyclone";"Factory";24;3
"Building";"BarracksTechLab";NA;26;0
"Unit";"SCV";"Command Center";33;1
"Unit";"SCV";"Command Center";33;1
"Unit";"Hellion";"Factory";30;2
"Unit";"Marine";"Barracks";33;1
"Unit";"Hellion";"Factory";30;2
"Unit";"SCV";"Command Center";33;1
"Unit";"SCV";"Command Center";34;1
"Building";"SupplyDepot";NA;33;0
"Unit";"SCV";"Command Center";40;1
"Unit";"SCV";"Command Center";41;1
"Building";"FactoryTechLab";NA;42;0
"Unit";"Marine";"Barracks";42;1
"Unit";"SCV";"Command Center";43;1
"Unit";"SCV";"Command Center";43;1
"Building";"Bunker";NA;42;0
"Unit";"SCV";"Command Center";45;1
"Building";"Barracks";NA;41;0
"Building";"EngineeringBay";NA;47;0
"Unit";"Marine";"Barracks";48;1
"Unit";"SCV";"Command Center";48;1
"Unit";"SCV";"Command Center";48;1
"Unit";"Marine";"Barracks";48;1
"Unit";"Marine";"Barracks";48;1
"Building";"SupplyDepot";NA;48;0
"Unit";"SCV";"Command Center";49;1
"Unit";"SCV";"Command Center";50;1
"Unit";"Marine";"Barracks";50;1
"Building";"MissileTurret";NA;53;0
"Unit";"SCV";"Command Center";55;1
"Unit";"SCV";"Command Center";55;1
"Unit";"Marine";"Barracks";54;1
"Unit";"Marine";"Barracks";54;1
"Building";"SupplyDepot";NA;53;0
"Building";"Starport";NA;50;0
"Upgrade";"Stimpack";"TechLab";44;0
"Building";"FactoryReactor";NA;53;0
"Unit";"Marine";"Barracks";56;1
"Unit";"SCV";"Command Center";59;1
"Unit";"SCV";"Command Center";59;1
"Building";"Barracks";NA;49;0
"Unit";"SCV";"Command Center";61;1
"Building";"Refinery";NA;60;0
"Building";"Refinery";NA;60;0
"Unit";"SCV";"Command Center";63;1
"Unit";"Marine";"Barracks";61;1
"Unit";"Marine";"Barracks";61;1
"Building";"SupplyDepot";NA;61;0
"Unit";"SCV";"Command Center";64;1
"Unit";"Marine";"Barracks";63;1
"Unit";"Marine";"Barracks";63;1
"Building";"Barracks";NA;60;0
"Unit";"SCV";"Command Center";67;1
"Building";"Barracks";NA;60;0
"Unit";"Marine";"Barracks";67;1
"Unit";"Marine";"Barracks";67;1
"Unit";"SCV";"Command Center";70;1
"Building";"SupplyDepot";NA;67;0
"Unit";"Medivac";"Starport";65;2
"Unit";"Marauder";"Barracks";70;2
"Unit";"Marauder";"Barracks";70;2
"Unit";"Medivac";"Starport";67;2
"Building";"BarracksTechLab";NA;71;0
"Unit";"SCV";"Command Center";74;1
"Unit";"Marine";"Barracks";73;1
"Unit";"Marine";"Barracks";74;1
"Building";"SupplyDepot";NA;73;0
"Unit";"SCV";"Command Center";82;1
"Building";"SupplyDepot";NA;74;0
"Unit";"SCV";"Command Center";82;1
"Building";"BarracksReactor";NA;71;0
"Upgrade";"TerranInfantryWeaponsLevel1";"EngineeringBay";60;0
"Unit";"Marine";"Barracks";85;1
"Unit";"Marine";"Barracks";85;1
"Unit";"Marauder";"Barracks";85;2
"Unit";"Marauder";"Barracks";85;2
"Unit";"Marauder";"Barracks";85;2
"Unit";"Marine";"Barracks";87;1
"Unit";"Marine";"Barracks";87;1
"Unit";"Marine";"Barracks";87;1
"Unit";"Marine";"Barracks";88;1
"Unit";"Marine";"Barracks";93;1
"Unit";"Marauder";"Barracks";89;2
"Unit";"Marauder";"Barracks";91;2
"Unit";"Marine";"Barracks";95;1
"Unit";"Marine";"Barracks";96;1
"Unit";"Marine";"Barracks";97;1
"Unit";"Marine";"Barracks";98;1
"Unit";"SCV";"Command Center";104;1
"Unit";"SCV";"Command Center";104;1
"Unit";"Medivac";"Starport";95;2
"Unit";"Medivac";"Starport";95;2
"Unit";"Marine";"Barracks";104;1
"Unit";"Marauder";"Barracks";104;2
"Unit";"Marauder";"Barracks";104;2
"Building";"EngineeringBay";NA;104;0
"Unit";"Marine";"Barracks";106;1
"Unit";"Marine";"Barracks";106;1
"Unit";"Marine";"Barracks";114;1
"Unit";"Marine";"Barracks";119;1
"Unit";"Marine";"Barracks";119;1
"Unit";"Medivac";"Starport";114;2
"Unit";"Medivac";"Starport";114;2
"Building";"Armory";NA;104;0
"Unit";"Marine";"Barracks";121;1
"Unit";"Marine";"Barracks";121;1
"Unit";"Marauder";"Barracks";121;2
"Unit";"Marauder";"Barracks";121;2
"Unit";"SCV";"Command Center";122;1
"Unit";"Marine";"Barracks";122;1
"Unit";"Marine";"Barracks";122;1
"Unit";"Marine";"Barracks";124;1
"Unit";"Marine";"Barracks";128;1
"Unit";"Marine";"Barracks";129;1
"Unit";"SCV";"Command Center";140;1
"Unit";"Marine";"Barracks";140;1
"Unit";"SCV";"Command Center";140;1
"Unit";"Marine";"Barracks";140;1
"Unit";"Marine";"Barracks";140;1
"Unit";"Marine";"Barracks";140;1
"Unit";"Marauder";"Barracks";140;2
"Unit";"Marauder";"Barracks";140;2
"Building";"SupplyDepot";NA;143;0
"Building";"SupplyDepot";NA;143;0
"Upgrade";"TerranInfantryArmorsLevel1";"EngineeringBay";135;0
"Unit";"SCV";"Command Center";150;1
"Unit";"SCV";"Command Center";150;1
"Unit";"Marine";"Barracks";150;1
"Unit";"Marine";"Barracks";150;1
"Unit";"Marine";"Barracks";150;1
"Unit";"Marine";"Barracks";150;1
"Unit";"Marauder";"Barracks";150;2
"Unit";"Marauder";"Barracks";150;2
"Unit";"Marauder";"Barracks";150;2
"Building";"FactoryReactor";NA;150;0
"Building";"Starport";NA;150;0
"Unit";"Marine";"Barracks";152;1
"Building";"SupplyDepot";NA;152;0
"Building";"SupplyDepot";NA;156;0
"Building";"MissileTurret";NA;162;0
"Building";"MissileTurret";NA;162;0
"Building";"MissileTurret";NA;162;0
"Unit";"Marauder";"Barracks";162;2
"Unit";"Marauder";"Barracks";162;2
"Unit";"Marauder";"Barracks";162;2
"Building";"CommandCenter";NA;146;0
"Unit";"Marine";"Barracks";163;1
"Unit";"Marine";"Barracks";163;1
"Unit";"Marine";"Barracks";163;1
