"Type";"UnitName";"OnBuilding";"TotalSupply";"Supply"
"Unit";"SCV";"Command Center";12;1
"Unit";"SCV";"Command Center";12;1
"Unit";"SCV";"Command Center";13;1
"Building";"SupplyDepot";NA;13;0
"Unit";"SCV";"Command Center";15;1
"Unit";"SCV";"Command Center";15;1
"Building";"Refinery";NA;15;0
"Unit";"SCV";"Command Center";16;1
"Unit";"SCV";"Command Center";17;1
"Building";"Barracks";NA;15;0
"Unit";"Reaper";"Barracks";19;1
"Unit";"SCV";"Command Center";19;1
"Building";"Refinery";NA;19;0
"Unit";"SCV";"Command Center";20;1
"Building";"SupplyDepot";NA;21;0
"Unit";"SCV";"Command Center";22;1
"Building";"Factory";NA;20;0
"Building";"BarracksReactor";NA;22;0
"Unit";"SCV";"Command Center";23;1
"Building";"CommandCenter";NA;19;0
"Unit";"SCV";"Command Center";24;1
"Unit";"SCV";"Command Center";24;1
"Unit";"Hellion";"Factory";24;2
"Unit";"Hellion";"Factory";24;2
"Building";"BarracksTechLab";NA;24;0
"Building";"Starport";NA;23;0
"Unit";"SCV";"Command Center";25;1
"Unit";"SCV";"Command Center";31;1
"Unit";"SCV";"Command Center";31;1
"Building";"BarracksTechLab";NA;31;0
"Unit";"SCV";"Command Center";31;1
"Unit";"SCV";"Command Center";32;1
"Unit";"Medivac";"Starport";30;2
"Unit";"SCV";"Command Center";33;1
"Unit";"SCV";"Command Center";34;1
"Unit";"SCV";"Command Center";37;1
"Unit";"SCV";"Command Center";39;1
"Building";"StarportTechLab";NA;39;0
"Unit";"SCV";"Command Center";41;1
"Unit";"SCV";"Command Center";41;1
"Unit";"SCV";"Command Center";42;1
"Unit";"SCV";"Command Center";42;1
"Unit";"SCV";"Command Center";43;1
"Unit";"Marine";"Barracks";44;1
"Building";"SupplyDepot";NA;31;0
"Unit";"SCV";"Command Center";46;1
"Unit";"SCV";"Command Center";46;1
"Unit";"SCV";"Command Center";47;1
"Unit";"SCV";"Command Center";48;1
"Building";"SupplyDepot";NA;47;0
"Building";"SupplyDepot";NA;49;0
"Unit";"SCV";"Command Center";49;1
"Unit";"SCV";"Command Center";50;1
"Building";"StarportReactor";NA;46;0
"Building";"Barracks";NA;45;0
"Building";"Barracks";NA;45;0
"Building";"Refinery";NA;49;0
"Building";"Refinery";NA;49;0
"Building";"Barracks";NA;45;0
"Building";"Barracks";NA;46;0
"Unit";"SCV";"Command Center";51;1
"Unit";"SCV";"Command Center";52;1
"Upgrade";"Stimpack";"TechLab";41;0
"Unit";"SCV";"Command Center";53;1
"Unit";"SCV";"Command Center";54;1
"Building";"SupplyDepot";NA;51;0
"Building";"SupplyDepot";NA;51;0
"Unit";"SCV";"Command Center";55;1
"Unit";"SCV";"Command Center";56;1
"Building";"BarracksReactor";NA;53;0
"Building";"BarracksReactor";NA;53;0
"Unit";"Marine";"Barracks";57;1
"Unit";"Marine";"Barracks";57;1
"Unit";"Marine";"Barracks";57;1
"Unit";"Marine";"Barracks";57;1
"Unit";"Marine";"Barracks";59;1
"Unit";"Medivac";"Starport";57;2
"Unit";"Medivac";"Starport";57;2
"Unit";"Marine";"Barracks";59;1
"Unit";"Marine";"Barracks";59;1
"Unit";"Marine";"Barracks";59;1
"Unit";"Marine";"Barracks";59;1
"Unit";"Marine";"Barracks";60;1
"Unit";"Marauder";"Barracks";61;2
"Building";"EngineeringBay";NA;59;0
"Unit";"Marauder";"Barracks";62;2
"Unit";"Marine";"Barracks";63;1
"Unit";"Marine";"Barracks";68;1
"Unit";"Marine";"Barracks";69;1
"Unit";"Marine";"Barracks";70;1
"Unit";"Marine";"Barracks";71;1
"Unit";"Marine";"Barracks";72;1
"Unit";"Medivac";"Starport";68;2
"Unit";"Marauder";"Barracks";73;2
"Unit";"Marauder";"Barracks";75;2
"Unit";"Medivac";"Starport";71;2
"Unit";"Marine";"Barracks";77;1
"Unit";"Marine";"Barracks";78;1
"Unit";"Marine";"Barracks";79;1
"Unit";"Marine";"Barracks";83;1
"Unit";"Marine";"Barracks";83;1
"Unit";"Marine";"Barracks";83;1
"Building";"SupplyDepot";NA;83;0
"Unit";"Marine";"Barracks";85;1
"Building";"SupplyDepot";NA;83;0
"Unit";"Marine";"Barracks";94;1
"Unit";"Marine";"Barracks";94;1
"Unit";"Marine";"Barracks";94;1
"Unit";"Marauder";"Barracks";94;2
"Unit";"Marine";"Barracks";97;1
"Unit";"Marine";"Barracks";98;1
"Building";"SupplyDepot";NA;97;0
"Unit";"Marauder";"Barracks";98;2
"Building";"SupplyDepot";NA;98;0
"Unit";"Medivac";"Starport";97;2
"Unit";"Medivac";"Starport";97;2
"Unit";"Marine";"Barracks";104;1
"Unit";"Marine";"Barracks";104;1
"Unit";"Marine";"Barracks";104;1
"Unit";"Marauder";"Barracks";104;2
"Unit";"Marine";"Barracks";105;1
"Unit";"Marine";"Barracks";105;1
"Unit";"Marine";"Barracks";105;1
"Unit";"Marauder";"Barracks";105;2
"Unit";"Marine";"Barracks";111;1
"Unit";"Marine";"Barracks";112;1
"Unit";"Marine";"Barracks";113;1
"Unit";"Marine";"Barracks";114;1
"Unit";"Marine";"Barracks";121;1
"Unit";"Marine";"Barracks";121;1
"Unit";"Marine";"Barracks";121;1
"Unit";"Marine";"Barracks";121;1
"Unit";"Marine";"Barracks";122;1
"Unit";"Marine";"Barracks";123;1
"Unit";"Marauder";"Barracks";121;2
"Unit";"Marauder";"Barracks";124;2
"Unit";"Marine";"Barracks";125;1
"Upgrade";"TerranInfantryWeaponsLevel1";"EngineeringBay";98;0
"Unit";"Marine";"Barracks";133;1
"Unit";"Marine";"Barracks";133;1
"Unit";"Marine";"Barracks";133;1
"Unit";"Marine";"Barracks";133;1
"Unit";"Marine";"Barracks";133;1
"Unit";"Marauder";"Barracks";133;2
"Unit";"Marauder";"Barracks";133;2
"Unit";"Marine";"Barracks";143;1
"Unit";"Marine";"Barracks";143;1
"Unit";"Marine";"Barracks";143;1
"Unit";"Marine";"Barracks";143;1
"Unit";"Marauder";"Barracks";143;2
"Unit";"Marauder";"Barracks";143;2
"Unit";"Marine";"Barracks";145;1
"Unit";"Marine";"Barracks";145;1
"Unit";"Marine";"Barracks";145;1
"Unit";"Marine";"Barracks";146;1
"Unit";"Marine";"Barracks";147;1
"Unit";"Marauder";"Barracks";149;2
"Unit";"Marauder";"Barracks";151;2
"Unit";"Marine";"Barracks";155;1
"Unit";"Marine";"Barracks";155;1
"Unit";"Marine";"Barracks";155;1
"Unit";"Marauder";"Barracks";158;2
"Unit";"Marauder";"Barracks";160;2
"Unit";"Marine";"Barracks";165;1
"Unit";"Marine";"Barracks";165;1
"Unit";"Marine";"Barracks";165;1
"Unit";"Marine";"Barracks";165;1
"Unit";"Marine";"Barracks";165;1
"Unit";"Marine";"Barracks";165;1
