"Type";"UnitName";"OnBuilding";"TotalSupply";"Supply"
"Unit";"SCV";"Command Center";12;1
"Unit";"SCV";"Command Center";12;1
"Unit";"SCV";"Command Center";13;1
"Building";"SupplyDepot";NA;13;0
"Unit";"SCV";"Command Center";15;1
"Unit";"SCV";"Command Center";15;1
"Building";"Refinery";NA;15;0
"Unit";"SCV";"Command Center";16;1
"Building";"Barracks";NA;15;0
"Unit";"SCV";"Command Center";17;1
"Unit";"Marine";"Barracks";19;1
"Building";"BarracksTechLab";NA;20;0
"Unit";"SCV";"Command Center";20;1
"Building";"SupplyDepot";NA;20;0
"Unit";"Marauder";"Barracks";20;2
"Unit";"SCV";"Command Center";21;1
"Unit";"SCV";"Command Center";23;1
"Unit";"Marauder";"Barracks";21;2
"Unit";"SCV";"Command Center";24;1
"Building";"CommandCenter";NA;19;0
"Unit";"SCV";"Command Center";28;1
"Unit";"Marine";"Barracks";25;1
"Building";"Barracks";NA;21;0
"Building";"Barracks";NA;24;0
"Unit";"SCV";"Command Center";30;1
"Unit";"Marine";"Barracks";30;1
"Building";"Refinery";NA;30;0
"Unit";"SCV";"Command Center";30;1
"Unit";"SCV";"Command Center";31;1
"Building";"BarracksTechLab";NA;31;0
"Building";"EngineeringBay";NA;30;0
"Building";"BarracksReactor";NA;30;0
"Unit";"Marine";"Barracks";31;1
"Unit";"SCV";"Command Center";32;1
"Unit";"SCV";"Command Center";33;1
"Unit";"SCV";"Command Center";35;1
"Unit";"SCV";"Command Center";36;1
"Building";"Bunker";NA;33;0
"Unit";"Marine";"Barracks";36;1
"Unit";"Marine";"Barracks";36;1
"Unit";"Marine";"Barracks";36;1
"Unit";"Marine";"Barracks";37;1
"Unit";"SCV";"Command Center";38;1
"Unit";"SCV";"Command Center";38;1
"Building";"SupplyDepot";NA;37;0
"Unit";"SCV";"Command Center";43;1
"Unit";"Marine";"Barracks";43;1
"Unit";"Marine";"Barracks";43;1
"Unit";"Marine";"Barracks";43;1
"Unit";"Marine";"Barracks";43;1
"Unit";"SCV";"Command Center";45;1
"Unit";"SCV";"Command Center";45;1
"Building";"SupplyDepot";NA;45;0
"Unit";"SCV";"Command Center";51;1
"Building";"Refinery";NA;46;0
"Unit";"Marine";"Barracks";50;1
"Unit";"Marine";"Barracks";50;1
"Upgrade";"Stimpack";"TechLab";31;0
"Unit";"Marauder";"Barracks";50;2
"Unit";"Marauder";"Barracks";50;2
"Unit";"SCV";"Command Center";52;1
"Unit";"SCV";"Command Center";52;1
"Building";"Factory";NA;45;0
"Building";"SupplyDepot";NA;52;0
"Building";"SupplyDepot";NA;52;0
"Unit";"SCV";"Command Center";59;1
"Unit";"Marine";"Barracks";53;1
"Unit";"Marine";"Barracks";59;1
"Unit";"Marine";"Barracks";59;1
"Unit";"SCV";"Command Center";60;1
"Unit";"Marine";"Barracks";59;1
"Unit";"SCV";"Command Center";63;1
"Unit";"SCV";"Command Center";65;1
"Building";"SupplyDepot";NA;61;0
"Unit";"Marine";"Barracks";66;1
"Unit";"Marine";"Barracks";66;1
"Unit";"Marauder";"Barracks";67;2
"Unit";"Marauder";"Barracks";67;2
"Building";"FactoryReactor";NA;61;0
"Upgrade";"TerranInfantryWeaponsLevel1";"EngineeringBay";45;0
"Building";"Starport";NA;61;0
"Unit";"SCV";"Command Center";71;1
"Unit";"SCV";"Command Center";71;1
"Building";"SupplyDepot";NA;69;0
"Unit";"Marine";"Barracks";73;1
"Unit";"Marine";"Barracks";73;1
"Unit";"SCV";"Command Center";75;1
"Unit";"SCV";"Command Center";79;1
"Unit";"SCV";"Command Center";80;1
"Unit";"Marine";"Barracks";79;1
"Unit";"Marine";"Barracks";79;1
"Unit";"Marine";"Barracks";79;1
"Unit";"Marine";"Barracks";79;1
"Building";"Refinery";NA;80;0
"Building";"MissileTurret";NA;80;0
"Building";"MissileTurret";NA;80;0
"Unit";"SCV";"Command Center";86;1
"Unit";"SCV";"Command Center";86;1
"Unit";"Marine";"Barracks";82;1
"Unit";"Marine";"Barracks";83;1
"Building";"FactoryTechLab";NA;86;0
"Unit";"SCV";"Command Center";86;1
"Unit";"SCV";"Command Center";87;1
"Unit";"Medivac";"Starport";86;2
"Unit";"Medivac";"Starport";86;2
"Building";"CommandCenter";NA;71;0
"Unit";"Marine";"Barracks";86;1
"Unit";"Marine";"Barracks";86;1
"Building";"Barracks";NA;80;0
"Unit";"SCV";"Command Center";90;1
"Unit";"SCV";"Command Center";91;1
"Building";"SupplyDepot";NA;90;0
"Building";"Barracks";NA;80;0
"Unit";"Marine";"Barracks";96;1
"Unit";"Marine";"Barracks";96;1
"Unit";"Marine";"Barracks";96;1
"Building";"MissileTurret";NA;97;0
"Building";"Factory";NA;86;0
"Building";"BarracksTechLab";NA;100;0
"Unit";"Medivac";"Starport";100;2
"Unit";"Medivac";"Starport";100;2
"Unit";"Marine";"Barracks";103;1
"Unit";"Marine";"Barracks";103;1
"Unit";"SCV";"Command Center";103;1
"Unit";"Marauder";"Barracks";103;2
"Building";"BarracksReactor";NA;100;0
"Unit";"SCV";"Command Center";103;1
"Building";"FactoryTechLab";NA;103;0
"Unit";"Marine";"Barracks";103;1
"Unit";"Marine";"Barracks";103;1
"Building";"Refinery";NA;103;0
"Building";"Refinery";NA;103;0
"Unit";"Marine";"Barracks";107;1
"Building";"SupplyDepot";NA;103;0
"Upgrade";"TerranInfantryArmorsLevel1";"EngineeringBay";90;0
"Unit";"SCV";"Command Center";116;1
"Unit";"SCV";"Command Center";116;1
"Unit";"SCV";"Command Center";116;1
"Unit";"Marine";"Barracks";116;1
"Unit";"Marauder";"Barracks";116;2
"Unit";"Marine";"Barracks";116;1
"Unit";"Marine";"Barracks";116;1
"Unit";"Marine";"Barracks";116;1
"Unit";"Marauder";"Barracks";116;2
"Unit";"Marauder";"Barracks";116;2
"Unit";"Medivac";"Starport";116;2
"Unit";"SCV";"Command Center";116;1
"Unit";"Medivac";"Starport";116;2
"Unit";"SCV";"Command Center";119;1
"Unit";"SCV";"Command Center";119;1
"Unit";"SCV";"Command Center";131;1
"Unit";"SCV";"Command Center";134;1
"Unit";"SCV";"Command Center";135;1
"Building";"SupplyDepot";NA;122;0
"Building";"EngineeringBay";NA;119;0
"Unit";"Marine";"Barracks";129;1
"Unit";"Marine";"Barracks";129;1
"Unit";"Marine";"Barracks";129;1
"Building";"SupplyDepot";NA;127;0
"Unit";"Marauder";"Barracks";129;2
"Unit";"SCV";"Command Center";139;1
"Unit";"Medivac";"Starport";129;2
"Unit";"Marine";"Barracks";139;1
"Unit";"Marine";"Barracks";139;1
"Unit";"Marauder";"Barracks";139;2
"Building";"Armory";NA;119;0
"Unit";"Marine";"Barracks";142;1
"Unit";"Marauder";"Barracks";142;2
"Unit";"Marine";"Barracks";144;1
"Unit";"Marine";"Barracks";144;1
"Unit";"Medivac";"Starport";142;2
"Unit";"Marine";"Barracks";147;1
"Unit";"Marauder";"Barracks";147;2
"Unit";"Marine";"Barracks";151;1
"Unit";"Marauder";"Barracks";149;2
"Unit";"Marine";"Barracks";154;1
"Unit";"Marine";"Barracks";155;1
"Unit";"Marauder";"Barracks";152;2
"Building";"SupplyDepot";NA;156;0
"Building";"SupplyDepot";NA;158;0
"Building";"SupplyDepot";NA;159;0
