"Type";"UnitName";"OnBuilding";"TotalSupply";"Supply"
"Unit";"SCV";"Command Center";12;1
"Unit";"SCV";"Command Center";12;1
"Unit";"SCV";"Command Center";13;1
"Building";"SupplyDepot";NA;13;0
"Unit";"SCV";"Command Center";15;1
"Unit";"SCV";"Command Center";15;1
"Building";"Refinery";NA;15;0
"Unit";"SCV";"Command Center";16;1
"Unit";"SCV";"Command Center";17;1
"Building";"Barracks";NA;15;0
"Unit";"Reaper";"Barracks";19;1
"Unit";"SCV";"Command Center";19;1
"Building";"SupplyDepot";NA;19;0
"Unit";"SCV";"Command Center";21;1
"Unit";"SCV";"Command Center";21;1
"Building";"BarracksReactor";NA;20;0
"Unit";"SCV";"Command Center";22;1
"Building";"CommandCenter";NA;19;0
"Unit";"Marine";"Barracks";23;1
"Unit";"SCV";"Command Center";23;1
"Unit";"Marine";"Barracks";23;1
"Building";"Factory";NA;21;0
"Building";"SupplyDepot";NA;23;0
"Unit";"SCV";"Command Center";26;1
"Unit";"Marine";"Barracks";27;1
"Unit";"Marine";"Barracks";27;1
"Unit";"SCV";"Command Center";27;1
"Building";"FactoryTechLab";NA;27;0
"Building";"Refinery";NA;28;0
"Unit";"SCV";"Command Center";31;1
"Unit";"SCV";"Command Center";31;1
"Building";"Starport";NA;27;0
"Building";"Refinery";NA;28;0
"Unit";"Marine";"Barracks";31;1
"Building";"EngineeringBay";NA;31;0
"Unit";"Marine";"Barracks";31;1
"Unit";"SCV";"Command Center";32;1
"Unit";"SCV";"Command Center";33;1
"Unit";"SCV";"Command Center";35;1
"Unit";"SCV";"Command Center";36;1
"Building";"Barracks";NA;30;0
"Unit";"Marine";"Barracks";37;1
"Unit";"Marine";"Barracks";37;1
"Building";"SupplyDepot";NA;37;0
"Unit";"SCV";"Command Center";39;1
"Unit";"SCV";"Command Center";39;1
"Building";"BarracksTechLab";NA;39;0
"Building";"StarportReactor";NA;37;0
"Unit";"SCV";"Command Center";43;1
"Unit";"Marine";"Barracks";41;1
"Unit";"Marine";"Barracks";41;1
"Unit";"SCV";"Command Center";43;1
"Building";"Barracks";NA;39;0
"Unit";"Marine";"Barracks";43;1
"Unit";"SCV";"Command Center";47;1
"Unit";"SCV";"Command Center";47;1
"Unit";"Marine";"Barracks";47;1
"Unit";"Marine";"Barracks";47;1
"Unit";"SCV";"Command Center";48;1
"Unit";"SCV";"Command Center";49;1
"Building";"SupplyDepot";NA;47;0
"Building";"StarportReactor";NA;47;0
"Unit";"Marine";"Barracks";51;1
"Unit";"Marine";"Barracks";51;1
"Unit";"Marine";"Barracks";54;1
"Unit";"SCV";"Command Center";54;1
"Unit";"Marine";"Barracks";54;1
"Unit";"SCV";"Command Center";54;1
"Unit";"Marine";"Barracks";54;1
"Building";"SupplyDepot";NA;54;0
"Building";"Barracks";NA;50;0
"Unit";"SCV";"Command Center";61;1
"Unit";"SCV";"Command Center";61;1
"Building";"SupplyDepot";NA;61;0
"Unit";"Medivac";"Starport";56;2
"Unit";"Marine";"Barracks";61;1
"Unit";"Marine";"Barracks";61;1
"Unit";"Marine";"Barracks";61;1
"Unit";"Marine";"Barracks";61;1
"Unit";"Medivac";"Starport";61;2
"Building";"BarracksTechLab";NA;63;0
"Building";"Barracks";NA;56;0
"Upgrade";"TerranInfantryWeaponsLevel1";"EngineeringBay";47;0
"Unit";"Marine";"Barracks";65;1
"Building";"SupplyDepot";NA;65;0
"Unit";"Marine";"Barracks";68;1
"Unit";"Marine";"Barracks";68;1
"Unit";"Marine";"Barracks";68;1
"Unit";"Marine";"Barracks";71;1
"Unit";"Medivac";"Starport";65;2
"Building";"SupplyDepot";NA;69;0
"Building";"BarracksTechLab";NA;71;0
"Unit";"Marauder";"Barracks";72;2
"Upgrade";"Stimpack";"TechLab";54;0
"Unit";"Marine";"Barracks";74;1
"Unit";"Marine";"Barracks";74;1
"Unit";"Medivac";"Starport";72;2
"Unit";"Marine";"Barracks";78;1
"Unit";"Marine";"Barracks";78;1
"Unit";"Marine";"Barracks";78;1
"Unit";"Marine";"Barracks";78;1
"Unit";"Marauder";"Barracks";78;2
"Unit";"Marine";"Barracks";82;1
"Unit";"Marine";"Barracks";82;1
"Unit";"Marine";"Barracks";84;1
"Unit";"Marine";"Barracks";90;1
"Unit";"Marine";"Barracks";90;1
"Unit";"Marine";"Barracks";90;1
"Unit";"Marine";"Barracks";91;1
"Unit";"Marauder";"Barracks";90;2
"Unit";"Marauder";"Barracks";90;2
"Unit";"Marine";"Barracks";92;1
"Unit";"Marine";"Barracks";93;1
"Unit";"Marine";"Barracks";95;1
"Unit";"Marine";"Barracks";96;1
"Unit";"Marauder";"Barracks";94;2
"Unit";"Marauder";"Barracks";97;2
"Unit";"Marauder";"Barracks";99;2
"Unit";"Marine";"Barracks";103;1
"Unit";"Marine";"Barracks";103;1
"Unit";"Medivac";"Starport";101;2
"Unit";"Marauder";"Barracks";105;2
"Unit";"Marine";"Barracks";111;1
"Unit";"Marine";"Barracks";111;1
"Unit";"Marauder";"Barracks";107;2
"Unit";"Marauder";"Barracks";111;2
"Unit";"Marine";"Barracks";111;1
"Unit";"Marauder";"Barracks";115;2
"Unit";"SCV";"Command Center";123;1
"Unit";"Marauder";"Barracks";119;2
"Building";"Refinery";NA;123;0
"Unit";"Marauder";"Barracks";123;2
"Unit";"SCV";"Command Center";124;1
"Unit";"Marine";"Barracks";124;1
"Unit";"Marine";"Barracks";124;1
"Unit";"Marine";"Barracks";124;1
"Unit";"Marine";"Barracks";124;1
"Building";"SupplyDepot";NA;131;0
"Building";"SupplyDepot";NA;131;0
"Unit";"Marauder";"Barracks";136;2
"Unit";"Marauder";"Barracks";136;2
"Unit";"Marine";"Barracks";140;1
"Unit";"Marine";"Barracks";140;1
"Unit";"Marine";"Barracks";140;1
"Unit";"Marauder";"Barracks";140;2
"Unit";"Marauder";"Barracks";140;2
"Unit";"Marauder";"Barracks";140;2
"Unit";"Marine";"Barracks";140;1
"Unit";"Marine";"Barracks";140;1
"Unit";"Marine";"Barracks";141;1
"Building";"CommandCenter";NA;136;0
"Upgrade";"TerranInfantryArmorsLevel1";"EngineeringBay";129;0
"Unit";"Marine";"Barracks";149;1
"Unit";"Marine";"Barracks";149;1
