"type";"unit_name";"on_building";"total_supply";"supply"
"Building";"Refinery";NA;14;0
"Building";"Barracks";NA;15;0
"Unit";"Reaper";"Barracks";19;1
"Building";"Refinery";NA;20;0
"Building";"BarracksReactor";NA;20;0
"Building";"Factory";NA;19;0
"Building";"CommandCenter";NA;19;0
"Unit";"Marine";"Barracks";24;1
"Unit";"Cyclone";"Factory";25;3
"Unit";"Cyclone";"Factory";25;3
"Unit";"Marine";"Barracks";25;1
"Building";"BarracksTechLab";NA;35;0
"Unit";"Cyclone";"Factory";35;3
"Unit";"Cyclone";"Factory";35;3
"Unit";"Marine";"Barracks";39;1
"Unit";"Marine";"Barracks";49;1
"Building";"EngineeringBay";NA;47;0
"Building";"Barracks";NA;38;0
"Building";"Bunker";NA;47;0
"Building";"FactoryReactor";NA;47;0
"Building";"Starport";NA;50;0
"Unit";"Marine";"Barracks";55;1
"Unit";"Marine";"Barracks";56;1
"Building";"Refinery";NA;56;0
"Unit";"Marine";"Barracks";60;1
"Unit";"Marine";"Barracks";60;1
"Unit";"Marine";"Barracks";60;1
"Building";"FactoryReactor";NA;56;0
"Building";"Refinery";NA;62;0
"Unit";"Medivac";"Starport";62;2
"Building";"MissileTurret";NA;67;0
"Unit";"Marine";"Barracks";67;1
"Unit";"Marine";"Barracks";67;1
"Building";"Barracks";NA;59;0
"Unit";"Marine";"Barracks";67;1
"Unit";"Medivac";"Starport";63;2
"Upgrade";"Stimpack";"TechLab";52;0
"Building";"FactoryTechLab";NA;68;0
"Unit";"Marine";"Barracks";78;1
"Unit";"Marine";"Barracks";78;1
"Unit";"Marine";"Barracks";78;1
"Building";"CommandCenter";NA;60;0
"Unit";"Marine";"Barracks";78;1
"Unit";"Marine";"Barracks";78;1
"Unit";"Marine";"Barracks";80;1
"Unit";"Marine";"Barracks";83;1
"Unit";"Marine";"Barracks";83;1
"Unit";"Marine";"Barracks";87;1
"Unit";"Marine";"Barracks";87;1
"Upgrade";"TerranInfantryWeaponsLevel1";"EngineeringBay";64;0
"Unit";"Marine";"Barracks";91;1
"Unit";"Marine";"Barracks";91;1
"Unit";"Marine";"Barracks";92;1
"Unit";"Marine";"Barracks";97;1
"Unit";"Marine";"Barracks";97;1
"Unit";"Marine";"Barracks";97;1
"Unit";"Marine";"Barracks";98;1
"Unit";"Medivac";"Starport";94;2
"Unit";"Medivac";"Starport";94;2
"Building";"Barracks";NA;89;0
"Building";"Barracks";NA;91;0
"Unit";"Marine";"Barracks";101;1
"Unit";"Marine";"Barracks";101;1
"Unit";"Marine";"Barracks";105;1
"Unit";"Marine";"Barracks";105;1
"Building";"Factory";NA;100;0
"Building";"SensorTower";NA;115;0
"Unit";"Marine";"Barracks";115;1
"Unit";"Marine";"Barracks";115;1
"Unit";"Marine";"Barracks";115;1
"Unit";"Marine";"Barracks";115;1
"Unit";"Marine";"Barracks";115;1
"Building";"BarracksReactor";NA;115;0
"Building";"BarracksReactor";NA;115;0
"Unit";"Marine";"Barracks";118;1
"Unit";"Marine";"Barracks";118;1
"Unit";"Marine";"Barracks";120;1
"Unit";"Marine";"Barracks";121;1
"Unit";"Marine";"Barracks";121;1
"Building";"FactoryTechLab";NA;126;0
"Unit";"Marine";"Barracks";126;1
"Unit";"Marine";"Barracks";126;1
"Unit";"Marine";"Barracks";128;1
"Unit";"Marine";"Barracks";129;1
"Unit";"Marine";"Barracks";130;1
"Unit";"Marine";"Barracks";130;1
"Unit";"Marine";"Barracks";132;1
"Unit";"Marine";"Barracks";132;1
"Unit";"Marine";"Barracks";132;1
"Unit";"Marine";"Barracks";134;1
"Unit";"Marine";"Barracks";134;1
"Unit";"Marine";"Barracks";136;1
"Unit";"Marine";"Barracks";137;1
"Unit";"Marine";"Barracks";140;1
"Unit";"Marine";"Barracks";141;1
"Building";"Refinery";NA;140;0
"Building";"Refinery";NA;140;0
"Unit";"Marine";"Barracks";150;1
"Unit";"Marine";"Barracks";150;1
"Unit";"Medivac";"Starport";143;2
"Unit";"Marine";"Barracks";154;1
"Unit";"Marine";"Barracks";154;1
"Unit";"Marine";"Barracks";154;1
"Unit";"Marine";"Barracks";154;1
"Unit";"Marine";"Barracks";154;1
"Building";"MissileTurret";NA;154;0
"Building";"MissileTurret";NA;154;0
"Upgrade";"TerranInfantryArmorsLevel1";"EngineeringBay";126;0
"Unit";"Medivac";"Starport";150;2
"Unit";"Marine";"Barracks";159;1
"Unit";"Marine";"Barracks";159;1
"Unit";"Medivac";"Starport";157;2
"Unit";"Marine";"Barracks";166;1
"Unit";"Marine";"Barracks";168;1
"Unit";"Marine";"Barracks";168;1
"Unit";"Medivac";"Starport";164;2
"Unit";"Marine";"Barracks";168;1
"Unit";"Marine";"Barracks";168;1
"Unit";"Marine";"Barracks";168;1
"Unit";"Marine";"Barracks";168;1
"Building";"MissileTurret";NA;171;0
"Unit";"Marine";"Barracks";179;1
"Unit";"Medivac";"Starport";171;2
"Unit";"Medivac";"Starport";172;2
"Unit";"Marine";"Barracks";179;1
"Unit";"Marine";"Barracks";179;1
"Unit";"Marine";"Barracks";179;1
"Unit";"Marine";"Barracks";179;1
"Unit";"Marine";"Barracks";179;1
"Unit";"Marine";"Barracks";179;1
"Unit";"Marine";"Barracks";179;1
"Building";"EngineeringBay";NA;179;0
"Unit";"Marine";"Barracks";191;1
"Building";"CommandCenter";NA;168;0
"Building";"Factory";NA;179;0
"Building";"Armory";NA;179;0
"Unit";"Medivac";"Starport";191;2
"Unit";"Marine";"Barracks";192;1
"Unit";"Marine";"Barracks";192;1
"Unit";"Marine";"Barracks";192;1
"Unit";"Marine";"Barracks";192;1
"Unit";"Marine";"Barracks";192;1
"Unit";"Marine";"Barracks";192;1
"Unit";"Marine";"Barracks";192;1
"Unit";"Marine";"Barracks";192;1
"Unit";"Medivac";"Starport";191;2
"Building";"FactoryTechLab";NA;194;0
"Unit";"Marine";"Barracks";195;1
"Unit";"Marine";"Barracks";195;1
"Unit";"Marine";"Barracks";196;1
"Unit";"Marine";"Barracks";197;1
"Unit";"Medivac";"Starport";192;2
"Unit";"Marine";"Barracks";204;1
"Unit";"Marine";"Barracks";204;1
"Unit";"Marine";"Barracks";204;1
"Unit";"Marine";"Barracks";204;1
"Unit";"Medivac";"Starport";202;2
"Building";"Refinery";NA;204;0
"Building";"MissileTurret";NA;208;0
"Building";"Refinery";NA;208;0
"Building";"MissileTurret";NA;208;0
"Building";"MissileTurret";NA;210;0
"Unit";"Medivac";"Starport";208;2
"Unit";"Marine";"Barracks";216;1
"Unit";"Marine";"Barracks";216;1
"Unit";"Marine";"Barracks";216;1
"Unit";"Marine";"Barracks";216;1
"Unit";"Marine";"Barracks";218;1
"Unit";"Marine";"Barracks";218;1
"Unit";"Marine";"Barracks";218;1
"Unit";"Marine";"Barracks";218;1
"Unit";"Marine";"Barracks";219;1
"Unit";"Marine";"Barracks";220;1
"Unit";"Marine";"Barracks";221;1
"Unit";"Marine";"Barracks";222;1
"Unit";"Marine";"Barracks";222;1
"Unit";"Medivac";"Starport";216;2
"Unit";"Medivac";"Starport";216;2
"Building";"MissileTurret";NA;222;0
