"Type";"UnitName";"OnBuilding";"TotalSupply";"Supply"
"Unit";"SCV";"Command Center";12;1
"Unit";"SCV";"Command Center";12;1
"Unit";"SCV";"Command Center";13;1
"Building";"SupplyDepot";NA;13;0
"Unit";"SCV";"Command Center";15;1
"Unit";"SCV";"Command Center";15;1
"Building";"Refinery";NA;15;0
"Unit";"SCV";"Command Center";16;1
"Unit";"SCV";"Command Center";17;1
"Building";"Barracks";NA;15;0
"Unit";"Reaper";"Barracks";19;1
"Unit";"SCV";"Command Center";19;1
"Building";"Bunker";NA;19;0
"Building";"SupplyDepot";NA;19;0
"Unit";"SCV";"Command Center";21;1
"Building";"BarracksReactor";NA;20;0
"Unit";"SCV";"Command Center";21;1
"Unit";"SCV";"Command Center";22;1
"Unit";"Marine";"Barracks";22;1
"Unit";"Marine";"Barracks";23;1
"Unit";"SCV";"Command Center";23;1
"Building";"Barracks";NA;22;0
"Building";"Barracks";NA;22;0
"Unit";"SCV";"Command Center";27;1
"Building";"CommandCenter";NA;21;0
"Unit";"Marine";"Barracks";27;1
"Unit";"Marine";"Barracks";27;1
"Unit";"SCV";"Command Center";27;1
"Building";"SupplyDepot";NA;27;0
"Building";"BarracksTechLab";NA;27;0
"Building";"EngineeringBay";NA;27;0
"Unit";"SCV";"Command Center";30;1
"Unit";"Marine";"Barracks";30;1
"Unit";"Marine";"Barracks";30;1
"Building";"BarracksTechLab";NA;30;0
"Unit";"SCV";"Command Center";31;1
"Unit";"SCV";"Command Center";32;1
"Unit";"Marine";"Barracks";31;1
"Unit";"Marine";"Barracks";34;1
"Unit";"SCV";"Command Center";35;1
"Unit";"Marine";"Barracks";34;1
"Building";"SupplyDepot";NA;34;0
"Unit";"SCV";"Command Center";35;1
"Unit";"Marine";"Barracks";34;1
"Building";"MissileTurret";NA;37;0
"Unit";"Marine";"Barracks";37;1
"Unit";"SCV";"Command Center";40;1
"Unit";"Marine";"Barracks";37;1
"Unit";"Marine";"Barracks";39;1
"Unit";"Marine";"Barracks";41;1
"Unit";"SCV";"Command Center";42;1
"Unit";"SCV";"Command Center";44;1
"Unit";"Marine";"Barracks";42;1
"Unit";"SCV";"Command Center";47;1
"Unit";"Marine";"Barracks";44;1
"Unit";"Marine";"Barracks";45;1
"Unit";"Marine";"Barracks";46;1
"Building";"SupplyDepot";NA;44;0
"Unit";"SCV";"Command Center";48;1
"Unit";"SCV";"Command Center";50;1
"Unit";"Marine";"Barracks";49;1
"Unit";"SCV";"Command Center";54;1
"Building";"Refinery";NA;49;0
"Unit";"Marine";"Barracks";51;1
"Unit";"Marine";"Barracks";52;1
"Unit";"SCV";"Command Center";55;1
"Building";"Refinery";NA;53;0
"Unit";"Marine";"Barracks";55;1
"Unit";"SCV";"Command Center";57;1
"Building";"Factory";NA;48;0
"Unit";"Marine";"Barracks";56;1
"Unit";"SCV";"Command Center";60;1
"Building";"SupplyDepot";NA;58;0
"Building";"SupplyDepot";NA;58;0
"Unit";"SCV";"Command Center";62;1
"Unit";"Marine";"Barracks";62;1
"Unit";"Marine";"Barracks";62;1
"Unit";"Marine";"Barracks";62;1
"Unit";"SCV";"Command Center";64;1
"Upgrade";"TerranInfantryWeaponsLevel1";"EngineeringBay";42;0
"Unit";"SCV";"Command Center";65;1
"Upgrade";"Stimpack";"TechLab";42;0
"Unit";"SCV";"Command Center";69;1
"Building";"SupplyDepot";NA;66;0
"Building";"SupplyDepot";NA;66;0
"Unit";"SCV";"Command Center";70;1
"Unit";"SCV";"Command Center";72;1
"Unit";"Marine";"Barracks";71;1
"Unit";"Marine";"Barracks";71;1
"Unit";"Marine";"Barracks";71;1
"Unit";"Marine";"Barracks";71;1
"Building";"Starport";NA;65;0
"Building";"FactoryReactor";NA;65;0
"Unit";"SCV";"Command Center";73;1
"Unit";"SCV";"Command Center";74;1
"Unit";"Marine";"Barracks";74;1
"Unit";"Marine";"Barracks";75;1
"Unit";"Marauder";"Barracks";76;2
"Unit";"Marauder";"Barracks";77;2
"Building";"Refinery";NA;80;0
"Building";"SupplyDepot";NA;80;0
"Building";"SupplyDepot";NA;80;0
"Unit";"Medivac";"Starport";79;2
"Unit";"Marine";"Barracks";86;1
"Unit";"Marine";"Barracks";86;1
"Building";"FactoryTechLab";NA;86;0
"Unit";"Marauder";"Barracks";86;2
"Unit";"Marauder";"Barracks";86;2
"Building";"CommandCenter";NA;73;0
"Unit";"Medivac";"Starport";86;2
"Unit";"Marine";"Barracks";88;1
"Unit";"SCV";"Command Center";94;1
"Unit";"SCV";"Command Center";94;1
"Unit";"Marauder";"Barracks";90;2
"Unit";"Marauder";"Barracks";92;2
"Building";"SupplyDepot";NA;94;0
"Unit";"Medivac";"Starport";94;2
"Building";"Barracks";NA;88;0
"Building";"MissileTurret";NA;97;0
"Building";"Barracks";NA;88;0
"Building";"Barracks";NA;88;0
"Upgrade";"TerranInfantryArmorsLevel1";"EngineeringBay";79;0
"Unit";"Marine";"Barracks";99;1
"Unit";"Marine";"Barracks";99;1
"Unit";"Marauder";"Barracks";99;2
"Unit";"Marauder";"Barracks";101;2
"Unit";"SCV";"Command Center";105;1
"Unit";"SCV";"Command Center";105;1
"Unit";"Medivac";"Starport";99;2
"Unit";"Marauder";"Barracks";107;2
"Building";"BarracksTechLab";NA;115;0
"Building";"BarracksTechLab";NA;115;0
"Building";"BarracksTechLab";NA;115;0
"Unit";"Marauder";"Barracks";115;2
"Unit";"Marine";"Barracks";117;1
"Unit";"Marine";"Barracks";117;1
"Unit";"Marauder";"Barracks";115;2
"Unit";"Medivac";"Starport";117;2
"Unit";"Medivac";"Starport";117;2
