"Type";"UnitName";"OnBuilding";"TotalSupply";"Supply"
"Unit";"SCV";"Command Center";12;1
"Unit";"SCV";"Command Center";12;1
"Unit";"SCV";"Command Center";13;1
"Building";"SupplyDepot";NA;13;0
"Unit";"SCV";"Command Center";15;1
"Unit";"SCV";"Command Center";15;1
"Unit";"SCV";"Command Center";16;1
"Building";"Barracks";NA;15;0
"Unit";"SCV";"Command Center";17;1
"Building";"Refinery";NA;18;0
"Unit";"Marine";"Barracks";19;1
"Unit";"SCV";"Command Center";20;1
"Building";"SupplyDepot";NA;20;0
"Unit";"SCV";"Command Center";21;1
"Unit";"SCV";"Command Center";22;1
"Building";"BarracksReactor";NA;20;0
"Unit";"SCV";"Command Center";22;1
"Unit";"Marine";"Barracks";23;1
"Unit";"Marine";"Barracks";23;1
"Building";"Barracks";NA;21;0
"Building";"CommandCenter";NA;19;0
"Unit";"SCV";"Command Center";23;1
"Building";"Barracks";NA;21;0
"Building";"Bunker";NA;22;0
"Unit";"SCV";"Command Center";27;1
"Building";"BarracksTechLab";NA;27;0
"Unit";"SCV";"Command Center";28;1
"Unit";"SCV";"Command Center";28;1
"Unit";"Marine";"Barracks";28;1
"Unit";"Marine";"Barracks";28;1
"Building";"Refinery";NA;28;0
"Unit";"SCV";"Command Center";29;1
"Building";"EngineeringBay";NA;28;0
"Unit";"Marine";"Barracks";29;1
"Unit";"SCV";"Command Center";33;1
"Unit";"SCV";"Command Center";33;1
"Unit";"Marine";"Barracks";32;1
"Unit";"Marine";"Barracks";32;1
"Unit";"Marine";"Barracks";32;1
"Unit";"SCV";"Command Center";34;1
"Unit";"SCV";"Command Center";39;1
"Unit";"Marine";"Barracks";34;1
"Unit";"Marine";"Barracks";36;1
"Unit";"SCV";"Command Center";39;1
"Unit";"SCV";"Command Center";40;1
"Building";"SupplyDepot";NA;39;0
"Building";"BarracksTechLab";NA;42;0
"Unit";"SCV";"Command Center";43;1
"Unit";"SCV";"Command Center";44;1
"Unit";"Marine";"Barracks";43;1
"Unit";"Marine";"Barracks";43;1
"Unit";"Marine";"Barracks";43;1
"Unit";"SCV";"Command Center";45;1
"Unit";"SCV";"Command Center";50;1
"Unit";"Marine";"Barracks";48;1
"Unit";"Marine";"Barracks";49;1
"Building";"SupplyDepot";NA;46;0
"Unit";"Marauder";"Barracks";47;2
"Unit";"SCV";"Command Center";51;1
"Unit";"Marauder";"Barracks";49;2
"Building";"SupplyDepot";NA;50;0
"Unit";"SCV";"Command Center";56;1
"Unit";"SCV";"Command Center";57;1
"Unit";"Marine";"Barracks";54;1
"Unit";"Marine";"Barracks";54;1
"Unit";"Marauder";"Barracks";54;2
"Unit";"Marauder";"Barracks";57;2
"Unit";"SCV";"Command Center";61;1
"Unit";"SCV";"Command Center";61;1
"Building";"SupplyDepot";NA;59;0
"Upgrade";"Stimpack";"TechLab";39;0
"Building";"MissileTurret";NA;65;0
"Unit";"SCV";"Command Center";69;1
"Building";"MissileTurret";NA;67;0
"Unit";"SCV";"Command Center";69;1
"Unit";"Marine";"Barracks";67;1
"Unit";"Marine";"Barracks";67;1
"Unit";"Marine";"Barracks";67;1
"Unit";"Marine";"Barracks";67;1
"Upgrade";"TerranInfantryWeaponsLevel1";"EngineeringBay";44;0
"Building";"Factory";NA;59;0
"Unit";"SCV";"Command Center";75;1
"Unit";"SCV";"Command Center";75;1
"Unit";"SCV";"Command Center";75;1
"Unit";"SCV";"Command Center";76;1
"Building";"Refinery";NA;77;0
"Building";"Starport";NA;75;0
"Building";"FactoryReactor";NA;75;0
"Unit";"Marine";"Barracks";79;1
"Unit";"Marine";"Barracks";79;1
"Unit";"Marine";"Barracks";79;1
"Unit";"Marine";"Barracks";79;1
"Building";"Barracks";NA;79;0
"Building";"Barracks";NA;79;0
"Building";"CommandCenter";NA;75;0
"Unit";"Marine";"Barracks";79;1
"Unit";"Marine";"Barracks";80;1
"Unit";"Marine";"Barracks";81;1
"Unit";"Marine";"Barracks";82;1
"Unit";"SCV";"Command Center";83;1
"Unit";"SCV";"Command Center";83;1
"Building";"Refinery";NA;83;0
"Unit";"Medivac";"Starport";83;2
"Unit";"Medivac";"Starport";83;2
"Unit";"Marine";"Barracks";83;1
"Unit";"Marine";"Barracks";84;1
"Unit";"Marine";"Barracks";85;1
"Unit";"Marine";"Barracks";86;1
"Building";"SupplyDepot";NA;83;0
"Building";"BarracksReactor";NA;83;0
"Building";"BarracksReactor";NA;83;0
"Unit";"Marine";"Barracks";93;1
"Unit";"Marine";"Barracks";94;1
"Unit";"Marine";"Barracks";95;1
"Unit";"Marine";"Barracks";96;1
"Building";"EngineeringBay";NA;93;0
"Unit";"SCV";"Command Center";97;1
"Unit";"SCV";"Command Center";97;1
"Building";"FactoryReactor";NA;89;0
"Unit";"Medivac";"Starport";93;2
"Unit";"Medivac";"Starport";93;2
"Upgrade";"TerranInfantryArmorsLevel1";"EngineeringBay";79;0
"Unit";"Marine";"Barracks";97;1
"Unit";"Marine";"Barracks";98;1
"Unit";"Marine";"Barracks";99;1
"Unit";"Marine";"Barracks";100;1
"Building";"SupplyDepot";NA;97;0
"Unit";"Marine";"Barracks";101;1
"Unit";"Marine";"Barracks";101;1
"Unit";"Marine";"Barracks";101;1
"Unit";"Marine";"Barracks";101;1
"Unit";"SCV";"Command Center";107;1
"Unit";"SCV";"Command Center";107;1
"Building";"Armory";NA;93;0
"Unit";"SCV";"Command Center";111;1
"Unit";"Marine";"Barracks";107;1
"Unit";"SCV";"Command Center";115;1
"Unit";"SCV";"Command Center";116;1
"Unit";"Marauder";"Barracks";109;2
"Unit";"Marauder";"Barracks";110;2
"Unit";"SCV";"Command Center";117;1
"Building";"MissileTurret";NA;117;0
"Building";"SupplyDepot";NA;117;0
"Unit";"SCV";"Command Center";119;1
"Unit";"SCV";"Command Center";120;1
"Building";"Bunker";NA;117;0
"Unit";"SCV";"Command Center";125;1
"Unit";"Marauder";"Barracks";121;2
"Unit";"Marauder";"Barracks";123;2
"Unit";"SCV";"Command Center";128;1
"Unit";"SCV";"Command Center";128;1
"Unit";"Marine";"Barracks";128;1
"Unit";"Marine";"Barracks";128;1
"Unit";"SCV";"Command Center";133;1
"Building";"GhostAcademy";NA;126;0
"Unit";"SCV";"Command Center";133;1
"Unit";"SCV";"Command Center";134;1
"Building";"SupplyDepot";NA;129;0
"Unit";"Marauder";"Barracks";129;2
"Unit";"Marauder";"Barracks";131;2
"Unit";"SCV";"Command Center";138;1
"Building";"Refinery";NA;135;0
"Unit";"SCV";"Command Center";138;1
"Building";"Barracks";NA;126;0
"Unit";"SCV";"Command Center";139;1
"Building";"Barracks";NA;126;0
"Unit";"SCV";"Command Center";144;1
"Unit";"SCV";"Command Center";145;1
"Unit";"Marauder";"Barracks";140;2
"Building";"SupplyDepot";NA;142;0
"Unit";"Marauder";"Barracks";142;2
"Unit";"Marine";"Barracks";144;1
"Unit";"Marine";"Barracks";145;1
"Unit";"SCV";"Command Center";147;1
"Building";"BarracksTechLab";NA;149;0
"Building";"BarracksTechLab";NA;151;0
"Unit";"Ghost";"Barracks";151;2
"Unit";"Ghost";"Barracks";151;2
"Unit";"Marauder";"Barracks";156;2
"Unit";"Marauder";"Barracks";158;2
"Unit";"Marauder";"Barracks";160;2
"Unit";"Marauder";"Barracks";160;2
"Upgrade";"TerranInfantryWeaponsLevel2";"EngineeringBay";133;0
"Unit";"Liberator";"Starport";156;3
"Unit";"Liberator";"Starport";156;3
"Upgrade";"TerranInfantryArmorsLevel2";"EngineeringBay";135;0
"Unit";"Marauder";"Barracks";160;2
"Unit";"Marauder";"Barracks";162;2
"Unit";"Marine";"Barracks";168;1
"Unit";"Marine";"Barracks";168;1
"Unit";"Marine";"Barracks";168;1
"Unit";"Marauder";"Barracks";164;2
"Unit";"Marine";"Barracks";168;1
"Unit";"Marauder";"Barracks";166;2
"Unit";"SCV";"Command Center";174;1
"Unit";"SCV";"Command Center";174;1
"Unit";"SCV";"Command Center";174;1
"Building";"Refinery";NA;174;0
"Unit";"Marine";"Barracks";178;1
"Unit";"Marine";"Barracks";178;1
"Unit";"Medivac";"Starport";168;2
"Unit";"Medivac";"Starport";171;2
"Unit";"Marauder";"Barracks";174;2
"Unit";"Marauder";"Barracks";176;2
"Unit";"SCV";"Command Center";189;1
"Unit";"Marine";"Barracks";178;1
"Unit";"Marine";"Barracks";179;1
"Unit";"Marine";"Barracks";180;1
"Building";"MissileTurret";NA;189;0
"Unit";"Marauder";"Barracks";181;2
"Building";"MissileTurret";NA;189;0
"Building";"SupplyDepot";NA;186;0
"Unit";"Marine";"Barracks";189;1
"Building";"SupplyDepot";NA;189;0
"Unit";"Marauder";"Barracks";189;2
"Building";"SupplyDepot";NA;189;0
"Building";"MissileTurret";NA;189;0
"Building";"SupplyDepot";NA;189;0
"Building";"MissileTurret";NA;189;0
"Unit";"Marine";"Barracks";189;1
"Unit";"Marine";"Barracks";190;1
"Unit";"Marine";"Barracks";195;1
"Unit";"Marine";"Barracks";208;1
"Unit";"Marauder";"Barracks";206;2
"Unit";"Marine";"Barracks";208;1
"Unit";"Marine";"Barracks";208;1
"Building";"SupplyDepot";NA;206;0
"Unit";"Marauder";"Barracks";206;2
"Unit";"Ghost";"Barracks";205;2
"Unit";"Marauder";"Barracks";210;2
"Unit";"Marauder";"Barracks";216;2
"Unit";"Marauder";"Barracks";216;2
"Unit";"Marauder";"Barracks";218;2
"Building";"CommandCenter";NA;189;0
"Unit";"Marauder";"Barracks";220;2
"Unit";"Marauder";"Barracks";222;2
"Unit";"Marauder";"Barracks";224;2
"Unit";"Marauder";"Barracks";226;2
"Unit";"Marine";"Barracks";230;1
"Unit";"Marine";"Barracks";230;1
"Unit";"Marine";"Barracks";230;1
"Unit";"Marine";"Barracks";230;1
"Unit";"Marine";"Barracks";230;1
"Unit";"Marauder";"Barracks";228;2
"Building";"MissileTurret";NA;230;0
"Unit";"Marauder";"Barracks";230;2
"Unit";"Marauder";"Barracks";232;2
"Unit";"Marauder";"Barracks";234;2
"Unit";"Marine";"Barracks";243;1
"Unit";"Marauder";"Barracks";241;2
"Building";"SensorTower";NA;243;0
"Unit";"Liberator";"Starport";230;3
"Unit";"Liberator";"Starport";230;3
"Building";"SensorTower";NA;243;0
"Unit";"Marauder";"Barracks";243;2
"Upgrade";"TerranInfantryWeaponsLevel3";"EngineeringBay";208;0
"Upgrade";"TerranInfantryArmorsLevel3";"EngineeringBay";211;0
"Unit";"Marauder";"Barracks";258;2
"Unit";"Marauder";"Barracks";258;2
"Unit";"Marauder";"Barracks";258;2
"Unit";"Liberator";"Starport";252;3
"Unit";"Liberator";"Starport";255;3
"Unit";"Marine";"Barracks";266;1
"Unit";"Marine";"Barracks";266;1
"Unit";"Marine";"Barracks";266;1
"Unit";"Marauder";"Barracks";260;2
"Unit";"Marauder";"Barracks";260;2
"Unit";"Marauder";"Barracks";262;2
"Unit";"Marauder";"Barracks";264;2
"Unit";"SCV";"Command Center";266;1
"Unit";"SCV";"Command Center";266;1
"Unit";"SCV";"Command Center";266;1
"Unit";"Medivac";"Starport";266;2
"Unit";"Medivac";"Starport";269;2
"Unit";"Marauder";"Barracks";275;2
"Unit";"Marauder";"Barracks";277;2
"Unit";"Marine";"Barracks";286;1
"Unit";"Marine";"Barracks";286;1
"Unit";"Marine";"Barracks";286;1
"Unit";"Marine";"Barracks";286;1
"Unit";"Marine";"Barracks";286;1
"Unit";"Marine";"Barracks";286;1
"Unit";"Marine";"Barracks";286;1
"Unit";"Marine";"Barracks";286;1
"Unit";"Marauder";"Barracks";294;2
"Unit";"Marauder";"Barracks";294;2
"Unit";"Marine";"Barracks";294;1
"Unit";"Marine";"Barracks";295;1
"Unit";"Marine";"Barracks";295;1
"Unit";"Marine";"Barracks";297;1
"Unit";"Marine";"Barracks";297;1
"Unit";"Marine";"Barracks";299;1
"Unit";"Marauder";"Barracks";299;2
"Unit";"Marauder";"Barracks";301;2
"Unit";"Marine";"Barracks";304;1
"Unit";"Marauder";"Barracks";302;2
"Unit";"Marine";"Barracks";306;1
"Unit";"Marine";"Barracks";307;1
"Unit";"Marine";"Barracks";307;1
"Unit";"Marine";"Barracks";309;1
"Unit";"Marine";"Barracks";309;1
"Unit";"Marine";"Barracks";311;1
"Unit";"Marine";"Barracks";312;1
"Unit";"Marine";"Barracks";314;1
"Unit";"Marine";"Barracks";316;1
"Building";"CommandCenter";NA;286;0
"Unit";"Marine";"Barracks";317;1
"Unit";"Marine";"Barracks";319;1
"Unit";"Marine";"Barracks";320;1
"Unit";"Marine";"Barracks";320;1
"Unit";"Marine";"Barracks";322;1
"Building";"CommandCenter";NA;286;0
"Unit";"Marauder";"Barracks";325;2
"Unit";"Marauder";"Barracks";326;2
"Unit";"Marine";"Barracks";328;1
"Unit";"Marine";"Barracks";328;1
"Unit";"Marine";"Barracks";328;1
"Unit";"Marine";"Barracks";328;1
"Unit";"Marine";"Barracks";329;1
"Unit";"Marine";"Barracks";330;1
"Unit";"Marine";"Barracks";330;1
"Building";"MissileTurret";NA;333;0
"Building";"MissileTurret";NA;333;0
"Unit";"Liberator";"Starport";325;3
"Unit";"Liberator";"Starport";325;3
