"type";"unit_name";"on_building";"total_supply";"supply"
"Building";"Refinery";NA;14;0
"Building";"Barracks";NA;15;0
"Unit";"Reaper";"Barracks";19;1
"Building";"BarracksReactor";NA;20;0
"Building";"Refinery";NA;21;0
"Building";"Factory";NA;19;0
"Building";"CommandCenter";NA;19;0
"Unit";"Marine";"Barracks";23;1
"Unit";"Marine";"Barracks";23;1
"Unit";"Marine";"Barracks";27;1
"Unit";"Marine";"Barracks";27;1
"Building";"Starport";NA;24;0
"Unit";"Marine";"Barracks";30;1
"Unit";"Marine";"Barracks";30;1
"Unit";"Medivac";"Starport";30;2
"Unit";"Marine";"Barracks";32;1
"Unit";"Marine";"Barracks";32;1
"Unit";"Cyclone";"Factory";34;3
"Unit";"Marine";"Barracks";38;1
"Unit";"Marine";"Barracks";39;1
"Unit";"Marine";"Barracks";47;1
"Unit";"Marine";"Barracks";47;1
"Building";"EngineeringBay";NA;47;0
"Unit";"Cyclone";"Factory";47;3
"Unit";"Liberator";"Starport";40;3
"Unit";"Marine";"Barracks";51;1
"Unit";"Marine";"Barracks";51;1
"Building";"Bunker";NA;47;0
"Building";"FactoryTechLab";NA;54;0
"Unit";"Marine";"Barracks";61;1
"Unit";"Marine";"Barracks";61;1
"Unit";"Marine";"Barracks";65;1
"Unit";"Marine";"Barracks";65;1
"Unit";"Liberator";"Starport";61;3
"Unit";"Marine";"Barracks";74;1
"Unit";"Marine";"Barracks";74;1
"Building";"CommandCenter";NA;61;0
"Building";"Refinery";NA;74;0
"Building";"Refinery";NA;74;0
"Building";"StarportReactor";NA;74;0
"Unit";"Marine";"Barracks";78;1
"Unit";"Marine";"Barracks";78;1
"Building";"Barracks";NA;74;0
"Building";"Barracks";NA;74;0
"Unit";"Marine";"Barracks";84;1
"Unit";"Marine";"Barracks";84;1
"Building";"BarracksTechLab";NA;86;0
"Building";"BarracksTechLab";NA;86;0
"Unit";"Marine";"Barracks";88;1
"Unit";"Marine";"Barracks";88;1
"Building";"StarportReactor";NA;86;0
"Upgrade";"TerranInfantryWeaponsLevel1";"EngineeringBay";74;0
"Unit";"Marine";"Barracks";91;1
"Unit";"Marine";"Barracks";91;1
"Unit";"Marine";"Barracks";91;1
"Unit";"Marine";"Barracks";92;1
"Building";"Barracks";NA;86;0
"Building";"Barracks";NA;86;0
"Unit";"Marine";"Barracks";93;1
"Unit";"Marine";"Barracks";94;1
"Unit";"Marine";"Barracks";95;1
"Unit";"Marine";"Barracks";96;1
"Unit";"Medivac";"Starport";94;2
"Unit";"Medivac";"Starport";94;2
"Building";"Factory";NA;91;0
"Unit";"Marine";"Barracks";99;1
"Unit";"Marine";"Barracks";99;1
"Unit";"Marauder";"Barracks";99;2
"Unit";"Marauder";"Barracks";100;2
"Building";"BarracksReactor";NA;99;0
"Building";"Refinery";NA;109;0
"Building";"FactoryTechLab";NA;113;0
"Building";"Refinery";NA;113;0
"Unit";"Marine";"Barracks";121;1
"Unit";"Marine";"Barracks";121;1
"Unit";"Marine";"Barracks";121;1
"Unit";"Marine";"Barracks";121;1
"Unit";"Marine";"Barracks";121;1
"Building";"EngineeringBay";NA;120;0
"Unit";"Marauder";"Barracks";121;2
"Unit";"Marine";"Barracks";121;1
"Building";"SensorTower";NA;121;0
"Unit";"Marauder";"Barracks";121;2
"Upgrade";"Stimpack";"TechLab";99;0
"Upgrade";"TerranInfantryArmorsLevel1";"EngineeringBay";105;0
"Building";"Armory";NA;121;0
"Building";"MissileTurret";NA;135;0
"Building";"MissileTurret";NA;135;0
"Building";"MissileTurret";NA;137;0
"Building";"MissileTurret";NA;137;0
"Unit";"Marine";"Barracks";137;1
"Unit";"Marine";"Barracks";137;1
"Unit";"Marine";"Barracks";137;1
"Unit";"Marine";"Barracks";137;1
"Unit";"Marine";"Barracks";137;1
"Unit";"Marauder";"Barracks";137;2
"Unit";"Marine";"Barracks";137;1
"Unit";"Marauder";"Barracks";137;2
"Unit";"Marine";"Barracks";137;1
"Unit";"Marine";"Barracks";151;1
"Unit";"Marine";"Barracks";151;1
"Unit";"Marine";"Barracks";151;1
"Unit";"Marine";"Barracks";151;1
"Unit";"Marauder";"Barracks";151;2
"Unit";"Marauder";"Barracks";151;2
"Unit";"Marine";"Barracks";159;1
"Unit";"Marine";"Barracks";159;1
"Unit";"Marine";"Barracks";159;1
"Unit";"Marine";"Barracks";159;1
"Unit";"Marine";"Barracks";159;1
"Unit";"Marine";"Barracks";159;1
"Unit";"Marauder";"Barracks";159;2
"Unit";"Marauder";"Barracks";159;2
"Building";"GhostAcademy";NA;169;0
"Unit";"Marine";"Barracks";169;1
"Unit";"Marine";"Barracks";169;1
"Unit";"Marine";"Barracks";169;1
"Unit";"Marine";"Barracks";169;1
"Unit";"Marauder";"Barracks";169;2
"Unit";"Marauder";"Barracks";169;2
"Building";"Barracks";NA;169;0
"Building";"Barracks";NA;169;0
"Building";"Barracks";NA;169;0
"Upgrade";"TerranInfantryWeaponsLevel2";"EngineeringBay";159;0
"Upgrade";"TerranInfantryArmorsLevel2";"EngineeringBay";159;0
"Unit";"Ghost";"Barracks";177;2
"Unit";"Liberator";"Starport";169;3
"Unit";"Liberator";"Starport";169;3
"Building";"CommandCenter";NA;169;0
"Unit";"Marine";"Barracks";188;1
"Unit";"Marine";"Barracks";188;1
"Building";"BarracksTechLab";NA;188;0
"Building";"BarracksTechLab";NA;188;0
"Building";"BarracksTechLab";NA;188;0
"Unit";"Ghost";"Barracks";188;2
"Unit";"Ghost";"Barracks";188;2
"Unit";"Liberator";"Starport";188;3
"Unit";"Liberator";"Starport";188;3
"Unit";"Marine";"Barracks";194;1
"Unit";"Marine";"Barracks";194;1
"Unit";"Marine";"Barracks";194;1
"Unit";"Marine";"Barracks";194;1
"Unit";"Marine";"Barracks";194;1
"Unit";"Marine";"Barracks";194;1
"Unit";"Marauder";"Barracks";190;2
"Unit";"Marauder";"Barracks";192;2
"Unit";"Marauder";"Barracks";194;2
"Building";"Refinery";NA;194;0
"Unit";"Ghost";"Barracks";194;2
"Unit";"Ghost";"Barracks";194;2
"Building";"Refinery";NA;194;0
"Unit";"Marine";"Barracks";200;1
"Unit";"Marine";"Barracks";201;1
"Unit";"Marauder";"Barracks";208;2
"Upgrade";"TerranShipWeaponsLevel1";"Armory";180;0
"Unit";"Marauder";"Barracks";210;2
"Unit";"Marine";"Barracks";212;1
"Unit";"Marine";"Barracks";212;1
"Unit";"Marine";"Barracks";212;1
"Unit";"Marine";"Barracks";212;1
"Unit";"Ghost";"Barracks";206;2
"Unit";"Marauder";"Barracks";214;2
"Unit";"Marine";"Barracks";216;1
"Unit";"Ghost";"Barracks";212;2
"Unit";"Marine";"Barracks";225;1
"Unit";"Marine";"Barracks";226;1
"Unit";"Marine";"Barracks";226;1
"Unit";"Marine";"Barracks";226;1
"Unit";"Marine";"Barracks";226;1
"Unit";"Liberator";"Starport";216;3
