"Type";"UnitName";"OnBuilding";"TotalSupply";"Supply"
"Unit";"SCV";"Command Center";12;1
"Unit";"SCV";"Command Center";12;1
"Unit";"SCV";"Command Center";13;1
"Building";"SupplyDepot";NA;13;0
"Building";"Refinery";NA;14;0
"Unit";"SCV";"Command Center";15;1
"Unit";"SCV";"Command Center";15;1
"Unit";"SCV";"Command Center";16;1
"Unit";"SCV";"Command Center";17;1
"Building";"Barracks";NA;15;0
"Unit";"Marine";"Barracks";19;1
"Building";"SupplyDepot";NA;19;0
"Unit";"SCV";"Command Center";20;1
"Building";"Factory";NA;19;0
"Unit";"SCV";"Command Center";20;1
"Unit";"Marine";"Barracks";20;1
"Building";"Bunker";NA;20;0
"Unit";"SCV";"Command Center";21;1
"Unit";"Hellion";"Factory";21;2
"Unit";"SCV";"Command Center";23;1
"Building";"Starport";NA;21;0
"Building";"SupplyDepot";NA;23;0
"Building";"BarracksTechLab";NA;24;0
"Unit";"SCV";"Command Center";26;1
"Unit";"Hellion";"Factory";24;2
"Building";"Refinery";NA;27;0
"Unit";"SCV";"Command Center";27;1
"Unit";"Medivac";"Starport";27;2
"Unit";"SCV";"Command Center";30;1
"Unit";"Hellion";"Factory";28;2
"Unit";"SCV";"Command Center";36;1
"Building";"BarracksReactor";NA;31;0
"Unit";"SCV";"Command Center";37;1
"Building";"SupplyDepot";NA;37;0
"Building";"FactoryTechLab";NA;37;0
"Unit";"SCV";"Command Center";38;1
"Building";"EngineeringBay";NA;38;0
"Unit";"SCV";"Command Center";39;1
"Building";"CommandCenter";NA;36;0
"Unit";"Marine";"Barracks";39;1
"Unit";"Marine";"Barracks";39;1
"Unit";"Banshee";"Starport";38;3
"Unit";"SCV";"Command Center";39;1
"Unit";"Marine";"Barracks";40;1
"Unit";"Marine";"Barracks";41;1
"Unit";"SCV";"Command Center";46;1
"Unit";"SCV";"Command Center";49;1
"Unit";"SCV";"Command Center";49;1
"Building";"MissileTurret";NA;49;0
"Unit";"Banshee";"Starport";46;3
"Unit";"SCV";"Command Center";49;1
"Unit";"SCV";"Command Center";50;1
"Building";"Refinery";NA;49;0
"Unit";"Marine";"Barracks";51;1
"Unit";"Marine";"Barracks";51;1
"Building";"Refinery";NA;49;0
"Unit";"SCV";"Command Center";54;1
"Unit";"SCV";"Command Center";55;1
"Building";"Bunker";NA;51;0
"Unit";"SCV";"Command Center";58;1
"Unit";"SCV";"Command Center";59;1
"Unit";"Marine";"Barracks";60;1
"Unit";"Marine";"Barracks";60;1
"Unit";"SCV";"Command Center";60;1
"Building";"SupplyDepot";NA;60;0
"Unit";"SCV";"Command Center";61;1
"Building";"SupplyDepot";NA;60;0
"Unit";"Raven";"Starport";56;2
"Building";"SupplyDepot";NA;62;0
"Unit";"Marine";"Barracks";68;1
"Unit";"Marine";"Barracks";68;1
"Unit";"SCV";"Command Center";68;1
"Unit";"SCV";"Command Center";68;1
"Unit";"SCV";"Command Center";70;1
"Unit";"SCV";"Command Center";72;1
"Unit";"SCV";"Command Center";73;1
"Unit";"SCV";"Command Center";75;1
"Unit";"SCV";"Command Center";75;1
"Building";"StarportReactor";NA;72;0
"Unit";"SCV";"Command Center";75;1
"Unit";"SCV";"Command Center";76;1
"Building";"Barracks";NA;72;0
"Building";"Barracks";NA;72;0
"Building";"EngineeringBay";NA;75;0
"Unit";"SCV";"Command Center";77;1
"Unit";"SCV";"Command Center";78;1
"Building";"CommandCenter";NA;68;0
"Building";"Barracks";NA;74;0
"Building";"Barracks";NA;74;0
"Building";"SupplyDepot";NA;77;0
"Unit";"Marine";"Barracks";79;1
"Unit";"Marine";"Barracks";79;1
"Unit";"Medivac";"Starport";77;2
"Unit";"Medivac";"Starport";77;2
"Unit";"SCV";"Command Center";81;1
"Unit";"SCV";"Command Center";81;1
"Unit";"Marauder";"Barracks";79;2
"Building";"Armory";NA;75;0
"Building";"SupplyDepot";NA;81;0
"Unit";"SCV";"Command Center";87;1
"Unit";"SCV";"Command Center";88;1
"Building";"BarracksReactor";NA;79;0
"Unit";"Medivac";"Starport";89;2
"Building";"SupplyDepot";NA;91;0
"Unit";"Medivac";"Starport";89;2
"Unit";"Marine";"Barracks";93;1
"Unit";"Marine";"Barracks";93;1
"Unit";"SCV";"Command Center";93;1
"Unit";"Marine";"Barracks";93;1
"Unit";"SCV";"Command Center";93;1
"Unit";"Marine";"Barracks";93;1
"Building";"SupplyDepot";NA;93;0
"Upgrade";"TerranInfantryWeaponsLevel1";"EngineeringBay";75;0
"Building";"BarracksTechLab";NA;93;0
"Building";"BarracksTechLab";NA;93;0
"Unit";"Hellion";"Factory";93;2
"Upgrade";"Stimpack";"TechLab";77;0
"Unit";"Marine";"Barracks";103;1
"Unit";"Marauder";"Barracks";103;2
"Unit";"Marauder";"Barracks";103;2
"Unit";"Marauder";"Barracks";103;2
"Unit";"SCV";"Command Center";106;1
"Unit";"SCV";"Command Center";106;1
"Unit";"Marine";"Barracks";105;1
"Unit";"Marine";"Barracks";105;1
"Unit";"Marauder";"Barracks";106;2
"Unit";"SCV";"Command Center";114;1
"Unit";"SCV";"Command Center";114;1
"Unit";"SCV";"Command Center";114;1
"Unit";"Medivac";"Starport";105;2
"Unit";"Medivac";"Starport";105;2
"Building";"MissileTurret";NA;115;0
"Building";"MissileTurret";NA;116;0
"Building";"MissileTurret";NA;116;0
"Unit";"SCV";"Command Center";118;1
"Building";"GhostAcademy";NA;112;0
"Unit";"SCV";"Command Center";121;1
"Unit";"SCV";"Command Center";121;1
"Unit";"Hellion";"Factory";116;2
"Unit";"Hellion";"Factory";116;2
"Building";"SupplyDepot";NA;118;0
"Building";"SupplyDepot";NA;121;0
"Unit";"SCV";"Command Center";125;1
"Upgrade";"TerranInfantryArmorsLevel1";"EngineeringBay";103;0
"Unit";"Marine";"Barracks";128;1
"Unit";"Marauder";"Barracks";128;2
"Unit";"Marauder";"Barracks";128;2
"Unit";"Marauder";"Barracks";128;2
"Unit";"Marine";"Barracks";132;1
"Unit";"Marauder";"Barracks";132;2
"Unit";"Marine";"Barracks";133;1
"Upgrade";"TerranShipWeaponsLevel1";"Armory";106;0
"Unit";"SCV";"Command Center";143;1
"Unit";"SCV";"Command Center";143;1
"Unit";"SCV";"Command Center";143;1
"Building";"SupplyDepot";NA;141;0
"Unit";"Medivac";"Starport";133;2
"Unit";"Medivac";"Starport";133;2
"Building";"SupplyDepot";NA;143;0
"Building";"Bunker";NA;141;0
"Unit";"Marine";"Barracks";144;1
"Unit";"Marine";"Barracks";144;1
"Upgrade";"TerranInfantryWeaponsLevel2";"EngineeringBay";112;0
"Building";"Barracks";NA;134;0
"Building";"Barracks";NA;134;0
"Building";"Barracks";NA;134;0
"Building";"SupplyDepot";NA;151;0
"Unit";"Ghost";"Barracks";144;2
"Unit";"Ghost";"Barracks";144;2
"Unit";"Ghost";"Barracks";144;2
"Unit";"Ghost";"Barracks";144;2
"Unit";"Hellion";"Factory";151;2
"Unit";"Hellion";"Factory";151;2
"Unit";"Marine";"Barracks";151;1
"Unit";"Marine";"Barracks";153;1
"Unit";"Medivac";"Starport";153;2
"Unit";"Medivac";"Starport";153;2
