"Type";"UnitName";"OnBuilding";"TotalSupply";"Supply"
"Unit";"SCV";"Command Center";12;1
"Unit";"SCV";"Command Center";12;1
"Unit";"SCV";"Command Center";13;1
"Building";"SupplyDepot";NA;13;0
"Unit";"SCV";"Command Center";15;1
"Unit";"SCV";"Command Center";15;1
"Building";"Refinery";NA;15;0
"Unit";"SCV";"Command Center";16;1
"Building";"Barracks";NA;15;0
"Unit";"SCV";"Command Center";17;1
"Unit";"Reaper";"Barracks";18;1
"Unit";"SCV";"Command Center";19;1
"Building";"SupplyDepot";NA;20;0
"Unit";"SCV";"Command Center";20;1
"Unit";"SCV";"Command Center";21;1
"Building";"BarracksReactor";NA;20;0
"Unit";"SCV";"Command Center";22;1
"Building";"CommandCenter";NA;19;0
"Building";"Refinery";NA;23;0
"Unit";"Marine";"Barracks";23;1
"Unit";"Marine";"Barracks";23;1
"Unit";"SCV";"Command Center";23;1
"Building";"Factory";NA;22;0
"Unit";"SCV";"Command Center";26;1
"Unit";"Marine";"Barracks";26;1
"Unit";"Marine";"Barracks";26;1
"Unit";"SCV";"Command Center";27;1
"Unit";"SCV";"Command Center";30;1
"Unit";"SCV";"Command Center";30;1
"Unit";"Marine";"Barracks";30;1
"Unit";"Marine";"Barracks";30;1
"Unit";"SCV";"Command Center";31;1
"Building";"SupplyDepot";NA;31;0
"Unit";"SCV";"Command Center";32;1
"Building";"Starport";NA;28;0
"Unit";"Marine";"Barracks";35;1
"Unit";"Marine";"Barracks";35;1
"Unit";"SCV";"Command Center";35;1
"Unit";"SCV";"Command Center";36;1
"Unit";"SCV";"Command Center";39;1
"Building";"SupplyDepot";NA;37;0
"Unit";"SCV";"Command Center";40;1
"Building";"FactoryTechLab";NA;37;0
"Unit";"Marine";"Barracks";40;1
"Unit";"Marine";"Barracks";40;1
"Unit";"Medivac";"Starport";37;2
"Unit";"SCV";"Command Center";41;1
"Unit";"SCV";"Command Center";42;1
"Building";"Bunker";NA;41;0
"Unit";"SCV";"Command Center";47;1
"Building";"SupplyDepot";NA;43;0
"Unit";"SCV";"Command Center";48;1
"Unit";"SCV";"Command Center";49;1
"Unit";"SCV";"Command Center";51;1
"Unit";"Marine";"Barracks";51;1
"Unit";"Marine";"Barracks";51;1
"Unit";"SCV";"Command Center";52;1
"Building";"EngineeringBay";NA;50;0
"Building";"Refinery";NA;51;0
"Building";"SupplyDepot";NA;51;0
"Unit";"SCV";"Command Center";52;1
"Unit";"SCV";"Command Center";55;1
"Unit";"SCV";"Command Center";56;1
"Unit";"Liberator";"Starport";51;3
"Unit";"SCV";"Command Center";58;1
"Unit";"SCV";"Command Center";58;1
"Unit";"SCV";"Command Center";62;1
"Building";"CommandCenter";NA;49;0
"Building";"BarracksTechLab";NA;63;0
"Unit";"SCV";"Command Center";63;1
"Unit";"SCV";"Command Center";64;1
"Building";"Refinery";NA;64;0
"Unit";"SCV";"Command Center";65;1
"Building";"StarportReactor";NA;63;0
"Unit";"SCV";"Command Center";68;1
"Unit";"SCV";"Command Center";68;1
"Unit";"Marauder";"Barracks";67;2
"Building";"Barracks";NA;62;0
"Building";"Barracks";NA;62;0
"Building";"Barracks";NA;63;0
"Building";"Barracks";NA;63;0
"Unit";"SCV";"Command Center";68;1
"Unit";"SCV";"Command Center";69;1
"Unit";"Marine";"Barracks";70;1
"Unit";"Marine";"Barracks";72;1
"Unit";"Marine";"Barracks";72;1
"Building";"BarracksTechLab";NA;72;0
"Building";"SupplyDepot";NA;72;0
"Building";"SupplyDepot";NA;72;0
"Unit";"Marine";"Barracks";74;1
"Unit";"Marine";"Barracks";74;1
"Building";"SupplyDepot";NA;72;0
"Building";"StarportReactor";NA;70;0
"Unit";"SCV";"Command Center";77;1
"Unit";"SCV";"Command Center";77;1
"Unit";"Marauder";"Barracks";74;2
"Unit";"SCV";"Command Center";77;1
"Building";"BarracksReactor";NA;72;0
"Unit";"Marine";"Barracks";77;1
"Unit";"Marine";"Barracks";77;1
"Unit";"SCV";"Command Center";79;1
"Unit";"SCV";"Command Center";80;1
"Unit";"Marauder";"Barracks";77;2
"Unit";"Marine";"Barracks";79;1
"Unit";"Marine";"Barracks";79;1
"Unit";"Marine";"Barracks";84;1
"Unit";"Marine";"Barracks";84;1
"Building";"SupplyDepot";NA;84;0
"Unit";"Marauder";"Barracks";84;2
"Building";"SupplyDepot";NA;84;0
"Unit";"Marine";"Barracks";88;1
"Unit";"Marine";"Barracks";88;1
"Unit";"Medivac";"Starport";81;2
"Unit";"Medivac";"Starport";81;2
"Unit";"Marine";"Barracks";92;1
"Unit";"Marine";"Barracks";92;1
"Unit";"SCV";"Command Center";92;1
"Unit";"SCV";"Command Center";93;1
"Building";"SupplyDepot";NA;90;0
"Building";"SupplyDepot";NA;90;0
"Unit";"SCV";"Command Center";94;1
"Unit";"Marauder";"Barracks";92;2
"Upgrade";"TerranInfantryWeaponsLevel1";"EngineeringBay";68;0
"Unit";"Marine";"Barracks";96;1
"Unit";"Marine";"Barracks";96;1
"Unit";"Marine";"Barracks";96;1
"Unit";"SCV";"Command Center";104;1
"Unit";"SCV";"Command Center";105;1
"Unit";"SCV";"Command Center";106;1
"Unit";"Marine";"Barracks";102;1
"Unit";"Marine";"Barracks";102;1
"Building";"Refinery";NA;100;0
"Building";"Refinery";NA;102;0
"Unit";"Marine";"Barracks";106;1
"Unit";"Marine";"Barracks";107;1
"Building";"SupplyDepot";NA;103;0
"Upgrade";"Stimpack";"TechLab";74;0
"Unit";"Medivac";"Starport";104;2
"Unit";"Marauder";"Barracks";109;2
"Unit";"Medivac";"Starport";106;2
"Unit";"Marine";"Barracks";117;1
"Unit";"Marine";"Barracks";117;1
"Unit";"Marauder";"Barracks";116;2
"Unit";"Marine";"Barracks";119;1
"Unit";"Marine";"Barracks";119;1
"Unit";"Marine";"Barracks";119;1
"Unit";"Marine";"Barracks";119;1
"Unit";"Marine";"Barracks";121;1
"Building";"EngineeringBay";NA;119;0
"Building";"SupplyDepot";NA;125;0
"Building";"SupplyDepot";NA;125;0
"Unit";"Marine";"Barracks";127;1
"Unit";"Marine";"Barracks";127;1
"Unit";"Marauder";"Barracks";133;2
"Unit";"Marine";"Barracks";134;1
"Unit";"Marine";"Barracks";134;1
"Unit";"Marine";"Barracks";134;1
"Unit";"Marine";"Barracks";134;1
"Unit";"Marauder";"Barracks";133;2
"Building";"Armory";NA;119;0
"Unit";"Marine";"Barracks";134;1
"Unit";"Marine";"Barracks";135;1
"Unit";"Medivac";"Starport";134;2
"Unit";"Medivac";"Starport";134;2
"Unit";"Marine";"Barracks";136;1
"Unit";"Marine";"Barracks";138;1
"Unit";"Marine";"Barracks";139;1
"Unit";"Marine";"Barracks";146;1
"Unit";"Marine";"Barracks";146;1
"Unit";"Marauder";"Barracks";142;2
"Unit";"Marine";"Barracks";146;1
"Unit";"Marine";"Barracks";146;1
"Building";"GhostAcademy";NA;144;0
"Unit";"Marine";"Barracks";151;1
"Unit";"Marine";"Barracks";152;1
"Unit";"Marine";"Barracks";153;1
"Unit";"Marine";"Barracks";154;1
"Unit";"Marine";"Barracks";157;1
"Unit";"Medivac";"Starport";153;2
"Unit";"Medivac";"Starport";153;2
"Unit";"Marine";"Barracks";159;1
"Unit";"SCV";"Command Center";162;1
"Unit";"SCV";"Command Center";164;1
"Unit";"SCV";"Command Center";164;1
"Building";"Barracks";NA;146;0
"Unit";"Marine";"Barracks";161;1
"Unit";"Marine";"Barracks";161;1
"Building";"Barracks";NA;146;0
"Building";"Barracks";NA;146;0
"Unit";"Ghost";"Barracks";159;2
"Unit";"Ghost";"Barracks";159;2
"Unit";"SCV";"Command Center";169;1
"Unit";"SCV";"Command Center";170;1
"Unit";"SCV";"Command Center";171;1
"Upgrade";"TerranInfantryArmorsLevel1";"EngineeringBay";134;0
"Unit";"Marine";"Barracks";169;1
"Unit";"Marine";"Barracks";169;1
"Unit";"Marine";"Barracks";169;1
"Unit";"Marine";"Barracks";169;1
"Building";"BarracksTechLab";NA;174;0
"Building";"BarracksTechLab";NA;174;0
"Building";"BarracksTechLab";NA;174;0
"Unit";"Marine";"Barracks";174;1
"Building";"CommandCenter";NA;146;0
"Unit";"Marauder";"Barracks";174;2
"Unit";"Marauder";"Barracks";176;2
"Building";"Refinery";NA;178;0
"Unit";"Marine";"Barracks";185;1
"Unit";"Marine";"Barracks";185;1
"Unit";"Marine";"Barracks";185;1
"Unit";"Marine";"Barracks";185;1
"Unit";"Marine";"Barracks";186;1
"Unit";"Liberator";"Starport";172;3
"Unit";"Liberator";"Starport";172;3
"Unit";"Marauder";"Barracks";185;2
"Unit";"Marauder";"Barracks";185;2
"Unit";"Marauder";"Barracks";186;2
"Unit";"Marine";"Barracks";186;1
"Unit";"Marine";"Barracks";186;1
"Unit";"Marine";"Barracks";188;1
"Building";"MissileTurret";NA;190;0
"Unit";"Marine";"Barracks";190;1
"Unit";"Marine";"Barracks";191;1
"Unit";"Marine";"Barracks";192;1
"Unit";"Marine";"Barracks";193;1
"Unit";"Marine";"Barracks";194;1
"Unit";"Marauder";"Barracks";201;2
"Unit";"Marauder";"Barracks";203;2
"Unit";"Marine";"Barracks";210;1
"Unit";"Marine";"Barracks";210;1
"Unit";"Marine";"Barracks";210;1
"Unit";"Marauder";"Barracks";210;2
"Building";"SupplyDepot";NA;210;0
"Unit";"Marine";"Barracks";210;1
"Building";"SupplyDepot";NA;210;0
"Unit";"Marine";"Barracks";215;1
"Unit";"Marine";"Barracks";215;1
"Unit";"Marine";"Barracks";215;1
"Unit";"Marine";"Barracks";215;1
"Unit";"Marauder";"Barracks";215;2
"Unit";"Marine";"Barracks";222;1
"Unit";"Marine";"Barracks";222;1
"Unit";"Marine";"Barracks";222;1
"Unit";"Marauder";"Barracks";222;2
"Unit";"Marauder";"Barracks";224;2
"Unit";"Marine";"Barracks";229;1
"Unit";"Marine";"Barracks";229;1
"Upgrade";"TerranVehicleAndShipArmorsLevel1";"Armory";185;0
"Unit";"Liberator";"Starport";215;3
"Unit";"Liberator";"Starport";215;3
"Unit";"Marauder";"Barracks";229;2
"Unit";"Marauder";"Barracks";232;2
"Unit";"Marauder";"Barracks";233;2
"Upgrade";"TerranInfantryWeaponsLevel2";"EngineeringBay";181;0
"Unit";"Marauder";"Barracks";234;2
"Unit";"Marine";"Barracks";238;1
"Unit";"Marine";"Barracks";238;1
"Unit";"Marine";"Barracks";238;1
"Unit";"Marine";"Barracks";238;1
"Unit";"Marauder";"Barracks";236;2
"Unit";"Marine";"Barracks";238;1
"Unit";"Marine";"Barracks";239;1
"Unit";"Marine";"Barracks";246;1
