"Type";"UnitName";"OnBuilding";"TotalSupply";"Supply"
"Unit";"SCV";"Command Center";12;1
"Unit";"SCV";"Command Center";12;1
"Unit";"SCV";"Command Center";13;1
"Building";"SupplyDepot";NA;13;0
"Unit";"SCV";"Command Center";15;1
"Unit";"SCV";"Command Center";15;1
"Building";"Refinery";NA;15;0
"Unit";"SCV";"Command Center";16;1
"Unit";"SCV";"Command Center";17;1
"Building";"Barracks";NA;15;0
"Unit";"Reaper";"Barracks";19;1
"Unit";"SCV";"Command Center";19;1
"Unit";"SCV";"Command Center";21;1
"Unit";"SCV";"Command Center";21;1
"Building";"SupplyDepot";NA;21;0
"Building";"BarracksReactor";NA;20;0
"Building";"Refinery";NA;21;0
"Building";"Barracks";NA;19;0
"Unit";"SCV";"Command Center";23;1
"Building";"CommandCenter";NA;19;0
"Unit";"Marine";"Barracks";23;1
"Unit";"Marine";"Barracks";23;1
"Unit";"SCV";"Command Center";24;1
"Building";"BarracksTechLab";NA;24;0
"Building";"Factory";NA;22;0
"Unit";"Marine";"Barracks";24;1
"Unit";"Marine";"Barracks";27;1
"Unit";"Marine";"Barracks";28;1
"Unit";"Marine";"Barracks";28;1
"Unit";"SCV";"Command Center";29;1
"Building";"EngineeringBay";NA;28;0
"Unit";"SCV";"Command Center";29;1
"Unit";"Marine";"Barracks";29;1
"Unit";"SCV";"Command Center";32;1
"Unit";"Marine";"Barracks";29;1
"Unit";"Marine";"Barracks";32;1
"Unit";"SCV";"Command Center";34;1
"Unit";"Marine";"Barracks";33;1
"Unit";"SCV";"Command Center";38;1
"Unit";"SCV";"Command Center";38;1
"Unit";"Marine";"Barracks";36;1
"Building";"MissileTurret";NA;36;0
"Unit";"Marine";"Barracks";39;1
"Building";"Starport";NA;34;0
"Building";"FactoryReactor";NA;34;0
"Unit";"SCV";"Command Center";39;1
"Unit";"SCV";"Command Center";42;1
"Building";"MissileTurret";NA;42;0
"Unit";"Marine";"Barracks";42;1
"Unit";"Marine";"Barracks";43;1
"Unit";"Marine";"Barracks";44;1
"Building";"Refinery";NA;44;0
"Building";"SupplyDepot";NA;46;0
"Upgrade";"Stimpack";"TechLab";33;0
"Unit";"SCV";"Command Center";48;1
"Building";"SupplyDepot";NA;48;0
"Building";"FactoryTechLab";NA;48;0
"Unit";"Marine";"Barracks";48;1
"Unit";"Marine";"Barracks";48;1
"Unit";"Marine";"Barracks";48;1
"Building";"SupplyDepot";NA;48;0
"Building";"Bunker";NA;48;0
"Unit";"SCV";"Command Center";49;1
"Unit";"SCV";"Command Center";49;1
"Unit";"Medivac";"Starport";48;2
"Unit";"Medivac";"Starport";48;2
"Unit";"Marine";"Barracks";49;1
"Unit";"Marine";"Barracks";49;1
"Unit";"Marine";"Barracks";52;1
"Building";"SupplyDepot";NA;52;0
"Unit";"SCV";"Command Center";52;1
"Unit";"SCV";"Command Center";53;1
"Building";"SupplyDepot";NA;52;0
"Unit";"Marine";"Barracks";60;1
"Unit";"Marine";"Barracks";60;1
"Unit";"SCV";"Command Center";63;1
"Unit";"SCV";"Command Center";63;1
"Upgrade";"TerranInfantryWeaponsLevel1";"EngineeringBay";47;0
"Unit";"SCV";"Command Center";65;1
"Unit";"Marine";"Barracks";63;1
"Building";"SupplyDepot";NA;63;0
"Unit";"Medivac";"Starport";63;2
"Unit";"Medivac";"Starport";63;2
"Unit";"SCV";"Command Center";67;1
"Unit";"SCV";"Command Center";74;1
"Unit";"SCV";"Command Center";74;1
"Unit";"Marine";"Barracks";74;1
"Unit";"Marine";"Barracks";74;1
"Unit";"Marine";"Barracks";74;1
"Unit";"SCV";"Command Center";74;1
"Unit";"SCV";"Command Center";75;1
"Unit";"Marine";"Barracks";76;1
"Building";"SupplyDepot";NA;78;0
"Unit";"SCV";"Command Center";79;1
"Unit";"Marine";"Barracks";79;1
"Unit";"Marine";"Barracks";79;1
"Unit";"SCV";"Command Center";81;1
"Unit";"Marine";"Barracks";81;1
"Unit";"SCV";"Command Center";85;1
"Building";"Barracks";NA;74;0
"Building";"SupplyDepot";NA;82;0
"Unit";"Medivac";"Starport";81;2
"Building";"CommandCenter";NA;73;0
"Unit";"Marine";"Barracks";85;1
"Unit";"Marine";"Barracks";85;1
"Unit";"Medivac";"Starport";81;2
"Building";"Barracks";NA;77;0
"Unit";"SCV";"Command Center";87;1
"Building";"Refinery";NA;85;0
"Unit";"SCV";"Command Center";88;1
"Building";"Barracks";NA;78;0
"Unit";"Marine";"Barracks";86;1
"Unit";"Marine";"Barracks";90;1
"Unit";"Marine";"Barracks";91;1
"Unit";"SCV";"Command Center";97;1
"Unit";"SCV";"Command Center";97;1
"Unit";"Marine";"Barracks";96;1
"Building";"BarracksReactor";NA;88;0
"Unit";"SCV";"Command Center";99;1
"Unit";"SCV";"Command Center";100;1
"Unit";"Marine";"Barracks";99;1
"Unit";"Marine";"Barracks";99;1
"Unit";"Marine";"Barracks";101;1
"Unit";"SCV";"Command Center";102;1
"Unit";"SCV";"Command Center";103;1
"Building";"Factory";NA;97;0
"Building";"BarracksReactor";NA;99;0
"Building";"BarracksReactor";NA;99;0
"Unit";"Medivac";"Starport";101;2
"Unit";"Medivac";"Starport";101;2
"Unit";"Marine";"Barracks";104;1
"Unit";"Marine";"Barracks";104;1
"Unit";"Marine";"Barracks";104;1
"Unit";"Marine";"Barracks";105;1
"Unit";"SCV";"Command Center";107;1
"Unit";"SCV";"Command Center";108;1
"Unit";"Marine";"Barracks";106;1
"Building";"Refinery";NA;107;0
"Unit";"SCV";"Command Center";115;1
"Unit";"SCV";"Command Center";117;1
"Unit";"SCV";"Command Center";118;1
"Building";"SupplyDepot";NA;109;0
"Building";"SupplyDepot";NA;109;0
"Upgrade";"TerranInfantryArmorsLevel1";"EngineeringBay";88;0
"Unit";"Marine";"Barracks";120;1
"Unit";"Marine";"Barracks";120;1
"Unit";"Marine";"Barracks";120;1
"Unit";"SCV";"Command Center";121;1
"Unit";"SCV";"Command Center";123;1
"Unit";"Marine";"Barracks";123;1
"Unit";"Marine";"Barracks";123;1
"Unit";"Marine";"Barracks";123;1
"Unit";"Marine";"Barracks";123;1
"Unit";"SCV";"Command Center";127;1
"Unit";"SCV";"Command Center";127;1
"Unit";"SCV";"Command Center";128;1
"Unit";"Marine";"Barracks";127;1
"Unit";"Marine";"Barracks";127;1
"Unit";"Marine";"Barracks";127;1
"Unit";"Marine";"Barracks";132;1
"Unit";"SCV";"Command Center";133;1
"Building";"FactoryTechLab";NA;132;0
"Building";"SensorTower";NA;133;0
"Unit";"Marine";"Barracks";133;1
"Unit";"Marine";"Barracks";133;1
"Unit";"Marine";"Barracks";133;1
"Unit";"SCV";"Command Center";135;1
"Unit";"SCV";"Command Center";135;1
"Unit";"SCV";"Command Center";139;1
"Unit";"Marine";"Barracks";138;1
"Unit";"Marine";"Barracks";138;1
"Unit";"Marine";"Barracks";138;1
"Building";"Refinery";NA;138;0
"Unit";"SCV";"Command Center";145;1
"Unit";"SCV";"Command Center";145;1
"Building";"SupplyDepot";NA;143;0
"Building";"Factory";NA;133;0
"Building";"SupplyDepot";NA;145;0
"Unit";"Marine";"Barracks";145;1
"Unit";"Marine";"Barracks";145;1
"Building";"MissileTurret";NA;145;0
"Unit";"Marine";"Barracks";145;1
"Unit";"Marine";"Barracks";153;1
"Unit";"Marine";"Barracks";153;1
"Unit";"Marine";"Barracks";153;1
"Unit";"Marine";"Barracks";154;1
"Unit";"Marine";"Barracks";154;1
"Unit";"Marine";"Barracks";154;1
"Unit";"Marine";"Barracks";154;1
"Unit";"Marine";"Barracks";154;1
"Unit";"Marine";"Barracks";154;1
"Unit";"Marine";"Barracks";154;1
"Unit";"Marine";"Barracks";155;1
"Unit";"Marine";"Barracks";156;1
"Unit";"Medivac";"Starport";154;2
"Unit";"Marine";"Barracks";157;1
"Unit";"Marine";"Barracks";158;1
"Unit";"Marine";"Barracks";159;1
"Building";"FactoryTechLab";NA;160;0
"Unit";"Marine";"Barracks";160;1
"Unit";"Marine";"Barracks";161;1
"Unit";"Marine";"Barracks";162;1
"Unit";"SCV";"Command Center";166;1
"Unit";"SCV";"Command Center";166;1
"Unit";"SCV";"Command Center";166;1
"Unit";"Marine";"Barracks";168;1
"Unit";"Marine";"Barracks";168;1
"Unit";"Marine";"Barracks";168;1
"Building";"EngineeringBay";NA;166;0
"Building";"SensorTower";NA;174;0
"Unit";"Marine";"Barracks";177;1
"Unit";"Marine";"Barracks";180;1
"Building";"SupplyDepot";NA;177;0
"Unit";"Marauder";"Barracks";180;2
"Unit";"Marine";"Barracks";180;1
"Unit";"Marine";"Barracks";180;1
"Unit";"Marine";"Barracks";180;1
"Building";"Armory";NA;168;0
"Unit";"Marine";"Barracks";187;1
"Unit";"Marine";"Barracks";187;1
"Unit";"Marine";"Barracks";187;1
"Unit";"Marine";"Barracks";187;1
"Unit";"Marine";"Barracks";187;1
"Unit";"Marine";"Barracks";187;1
"Unit";"Marine";"Barracks";187;1
"Unit";"Marine";"Barracks";187;1
"Unit";"Marine";"Barracks";187;1
"Unit";"Medivac";"Starport";184;2
"Unit";"Medivac";"Starport";184;2
"Unit";"Marine";"Barracks";196;1
"Unit";"Marine";"Barracks";196;1
"Unit";"Marine";"Barracks";200;1
"Building";"SupplyDepot";NA;200;0
"Unit";"Marine";"Barracks";203;1
"Unit";"Marine";"Barracks";203;1
"Unit";"Marine";"Barracks";203;1
"Unit";"Marine";"Barracks";203;1
"Unit";"Marine";"Barracks";203;1
"Unit";"Marine";"Barracks";203;1
"Unit";"Marine";"Barracks";203;1
"Unit";"Marine";"Barracks";203;1
"Unit";"Marine";"Barracks";204;1
