"type";"unit_name";"on_building";"total_supply";"supply"
"Building";"Refinery";NA;15;0
"Building";"Barracks";NA;15;0
"Building";"Barracks";NA;15;0
"Building";"BarracksTechLab";NA;18;0
"Building";"BarracksTechLab";NA;18;0
"Unit";"Marauder";"Barracks";19;2
"Unit";"Marauder";"Barracks";19;2
"Unit";"Marauder";"Barracks";19;2
"Unit";"Marauder";"Barracks";21;2
"Unit";"Marauder";"Barracks";27;2
"Unit";"Marauder";"Barracks";27;2
"Unit";"Marauder";"Barracks";28;2
"Unit";"Marauder";"Barracks";32;2
"Unit";"Marauder";"Barracks";32;2
"Unit";"Marauder";"Barracks";34;2
"Unit";"Marauder";"Barracks";36;2
"Unit";"Marauder";"Barracks";38;2
"Unit";"Marauder";"Barracks";43;2
