"Type";"UnitName";"OnBuilding";"TotalSupply";"Supply"
"Unit";"SCV";"Command Center";12;1
"Unit";"SCV";"Command Center";12;1
"Building";"SupplyDepot";NA;13;0
"Unit";"SCV";"Command Center";14;1
"Unit";"SCV";"Command Center";14;1
"Building";"Refinery";NA;14;0
"Unit";"SCV";"Command Center";15;1
"Building";"Refinery";NA;16;0
"Unit";"SCV";"Command Center";16;1
"Unit";"SCV";"Command Center";17;1
"Building";"Barracks";NA;15;0
"Unit";"Reaper";"Barracks";19;1
"Building";"SupplyDepot";NA;19;0
"Unit";"SCV";"Command Center";19;1
"Building";"Factory";NA;19;0
"Unit";"SCV";"Command Center";20;1
"Unit";"SCV";"Command Center";22;1
"Unit";"Reaper";"Barracks";19;1
"Unit";"SCV";"Command Center";24;1
"Building";"SupplyDepot";NA;22;0
"Unit";"Cyclone";"Factory";22;3
"Building";"Starport";NA;21;0
"Unit";"SCV";"Command Center";24;1
"Unit";"SCV";"Command Center";29;1
"Building";"SupplyDepot";NA;28;0
"Unit";"Cyclone";"Factory";29;3
"Unit";"Medivac";"Starport";28;2
"Building";"BarracksTechLab";NA;29;0
"Unit";"SCV";"Command Center";35;1
"Building";"FactoryTechLab";NA;35;0
"Unit";"SCV";"Command Center";36;1
"Unit";"Banshee";"Starport";35;3
"Building";"BarracksReactor";NA;35;0
"Building";"CommandCenter";NA;35;0
"Unit";"Marine";"Barracks";40;1
"Unit";"Marine";"Barracks";40;1
"Unit";"SCV";"Command Center";40;1
"Building";"Refinery";NA;40;0
"Unit";"Marine";"Barracks";40;1
"Unit";"Marine";"Barracks";41;1
"Unit";"Banshee";"Starport";40;3
"Building";"Refinery";NA;42;0
"Unit";"SCV";"Command Center";45;1
"Unit";"SCV";"Command Center";45;1
"Unit";"Marine";"Barracks";45;1
"Unit";"Marine";"Barracks";45;1
"Unit";"SCV";"Command Center";48;1
"Unit";"SCV";"Command Center";49;1
"Building";"CommandCenter";NA;40;0
"Unit";"SCV";"Command Center";52;1
"Unit";"SCV";"Command Center";53;1
"Unit";"Marine";"Barracks";54;1
"Unit";"Marine";"Barracks";54;1
"Unit";"Banshee";"Starport";45;3
"Unit";"SCV";"Command Center";54;1
"Unit";"SCV";"Command Center";55;1
"Unit";"Marine";"Barracks";58;1
"Unit";"Marine";"Barracks";58;1
"Unit";"SCV";"Command Center";63;1
"Unit";"SCV";"Command Center";63;1
"Unit";"SCV";"Command Center";65;1
"Unit";"SCV";"Command Center";66;1
"Unit";"SCV";"Command Center";66;1
"Building";"Factory";NA;56;0
"Unit";"SCV";"Command Center";67;1
"Unit";"SCV";"Command Center";68;1
"Unit";"SCV";"Command Center";69;1
"Building";"SupplyDepot";NA;67;0
"Unit";"SCV";"Command Center";70;1
"Unit";"SCV";"Command Center";71;1
"Unit";"SCV";"Command Center";72;1
"Unit";"Raven";"Starport";65;2
"Building";"EngineeringBay";NA;70;0
"Building";"BarracksReactor";NA;67;0
"Unit";"SCV";"Command Center";73;1
"Unit";"SCV";"Command Center";74;1
"Unit";"SCV";"Command Center";75;1
"Unit";"Hellion";"Factory";73;2
"Unit";"Hellion";"Factory";73;2
"Unit";"SCV";"Command Center";78;1
"Unit";"SCV";"Command Center";79;1
"Building";"Armory";NA;70;0
"Building";"SupplyDepot";NA;83;0
"Unit";"SCV";"Command Center";87;1
"Unit";"SCV";"Command Center";87;1
"Unit";"SCV";"Command Center";87;1
"Building";"SupplyDepot";NA;85;0
"Building";"Refinery";NA;85;0
"Building";"Refinery";NA;85;0
"Building";"MissileTurret";NA;87;0
"Unit";"Hellion";"Factory";90;2
"Unit";"Hellion";"Factory";90;2
"Unit";"SCV";"Command Center";90;1
"Unit";"SCV";"Command Center";90;1
"Unit";"SCV";"Command Center";90;1
"Building";"Factory";NA;87;0
"Building";"MissileTurret";NA;90;0
"Building";"MissileTurret";NA;90;0
"Building";"MissileTurret";NA;90;0
"Unit";"SCV";"Command Center";94;1
"Unit";"Hellion";"Factory";90;2
"Unit";"Hellion";"Factory";90;2
"Unit";"SCV";"Command Center";97;1
"Unit";"SCV";"Command Center";102;1
"Unit";"SCV";"Command Center";102;1
"Building";"SupplyDepot";NA;102;0
"Building";"SupplyDepot";NA;102;0
"Building";"SensorTower";NA;103;0
"Unit";"SCV";"Command Center";105;1
"Unit";"SCV";"Command Center";105;1
"Building";"SupplyDepot";NA;102;0
"Building";"MissileTurret";NA;105;0
"Building";"MissileTurret";NA;105;0
"Building";"MissileTurret";NA;105;0
"Unit";"SCV";"Command Center";105;1
"Building";"SupplyDepot";NA;105;0
"Unit";"SCV";"Command Center";105;1
"Unit";"SCV";"Command Center";107;1
"Unit";"Hellion";"Factory";105;2
"Unit";"Hellion";"Factory";105;2
"Unit";"SCV";"Command Center";107;1
"Unit";"SCV";"Command Center";108;1
"Unit";"SCV";"Command Center";109;1
"Building";"SupplyDepot";NA;107;0
"Building";"SupplyDepot";NA;107;0
"Unit";"SCV";"Command Center";114;1
"Unit";"SCV";"Command Center";115;1
"Unit";"SCV";"Command Center";116;1
"Unit";"Hellion";"Factory";115;2
"Unit";"Hellion";"Factory";115;2
"Building";"SupplyDepot";NA;117;0
"Upgrade";"TerranVehicleWeaponsLevel1";"Armory";102;0
"Building";"Armory";NA;108;0
"Building";"Factory";NA;110;0
"Building";"Factory";NA;114;0
"Building";"BarracksReactor";NA;117;0
"Unit";"Hellion";"Factory";124;2
"Unit";"Hellion";"Factory";124;2
"Building";"FactoryTechLab";NA;124;0
"Unit";"SCV";"Command Center";128;1
"Unit";"SCV";"Command Center";128;1
"Unit";"SCV";"Command Center";128;1
"Unit";"SCV";"Command Center";128;1
"Building";"SensorTower";NA;129;0
"Building";"Refinery";NA;128;0
"Building";"Refinery";NA;129;0
"Unit";"SCV";"Command Center";132;1
"Unit";"SCV";"Command Center";132;1
"Building";"SupplyDepot";NA;131;0
"Building";"CommandCenter";NA;124;0
"Building";"SupplyDepot";NA;131;0
"Building";"SupplyDepot";NA;131;0
"Unit";"Thor";"Factory";128;6
"Building";"MissileTurret";NA;132;0
"Upgrade";"TerranVehicleAndShipArmorsLevel1";"Armory";131;0
"Unit";"Thor";"Factory";140;6
"Upgrade";"TerranVehicleWeaponsLevel2";"Armory";132;0
"Building";"MissileTurret";NA;140;0
"Building";"SensorTower";NA;140;0
"Building";"MissileTurret";NA;140;0
"Building";"CommandCenter";NA;140;0
