"Type";"UnitName";"OnBuilding";"TotalSupply";"Supply"
"Unit";"SCV";"Command Center";12;1
"Unit";"SCV";"Command Center";12;1
"Unit";"SCV";"Command Center";13;1
"Building";"SupplyDepot";NA;13;0
"Unit";"SCV";"Command Center";15;1
"Building";"Refinery";NA;14;0
"Unit";"SCV";"Command Center";15;1
"Unit";"SCV";"Command Center";16;1
"Building";"Refinery";NA;16;0
"Unit";"SCV";"Command Center";17;1
"Building";"Barracks";NA;15;0
"Unit";"Reaper";"Barracks";19;1
"Building";"SupplyDepot";NA;19;0
"Unit";"SCV";"Command Center";19;1
"Building";"Factory";NA;19;0
"Unit";"SCV";"Command Center";21;1
"Unit";"SCV";"Command Center";21;1
"Unit";"Reaper";"Barracks";19;1
"Unit";"SCV";"Command Center";22;1
"Building";"SupplyDepot";NA;22;0
"Unit";"Cyclone";"Factory";22;3
"Building";"BarracksTechLab";NA;24;0
"Unit";"SCV";"Command Center";24;1
"Building";"Starport";NA;22;0
"Unit";"SCV";"Command Center";28;1
"Unit";"Hellion";"Factory";25;2
"Unit";"SCV";"Command Center";32;1
"Unit";"SCV";"Command Center";32;1
"Building";"SupplyDepot";NA;32;0
"Building";"SupplyDepot";NA;32;0
"Unit";"Banshee";"Starport";30;3
"Unit";"SCV";"Command Center";34;1
"Unit";"SCV";"Command Center";37;1
"Unit";"SCV";"Command Center";39;1
"Unit";"Cyclone";"Factory";38;3
"Building";"SupplyDepot";NA;39;0
"Unit";"SCV";"Command Center";39;1
"Building";"BarracksReactor";NA;38;0
"Unit";"Banshee";"Starport";34;3
"Unit";"SCV";"Command Center";43;1
"Unit";"Marine";"Barracks";47;1
"Unit";"SCV";"Command Center";47;1
"Unit";"Marine";"Barracks";47;1
"Building";"FactoryTechLab";NA;47;0
"Unit";"SCV";"Command Center";49;1
"Building";"CommandCenter";NA;33;0
"Unit";"SCV";"Command Center";51;1
"Unit";"Raven";"Starport";47;2
"Unit";"SCV";"Command Center";52;1
"Unit";"SCV";"Command Center";55;1
"Unit";"Marine";"Barracks";56;1
"Unit";"SCV";"Command Center";56;1
"Unit";"SCV";"Command Center";56;1
"Building";"EngineeringBay";NA;56;0
"Building";"Refinery";NA;56;0
"Building";"SupplyDepot";NA;56;0
"Unit";"SCV";"Command Center";58;1
"Unit";"SCV";"Command Center";59;1
"Building";"StarportReactor";NA;56;0
"Building";"Barracks";NA;55;0
"Unit";"SCV";"Command Center";60;1
"Building";"Barracks";NA;55;0
"Unit";"SCV";"Command Center";61;1
"Unit";"Marine";"Barracks";62;1
"Unit";"SCV";"Command Center";62;1
"Unit";"SCV";"Command Center";63;1
"Unit";"SCV";"Command Center";65;1
"Unit";"SCV";"Command Center";67;1
"Building";"Refinery";NA;64;0
"Building";"SupplyDepot";NA;66;0
"Unit";"SCV";"Command Center";67;1
"Building";"BarracksReactor";NA;63;0
"Unit";"SCV";"Command Center";68;1
"Unit";"Marine";"Barracks";67;1
"Building";"BarracksReactor";NA;64;0
"Building";"SupplyDepot";NA;67;0
"Building";"Barracks";NA;63;0
"Building";"Barracks";NA;63;0
"Unit";"SCV";"Command Center";69;1
"Unit";"Medivac";"Starport";68;2
"Unit";"Marine";"Barracks";70;1
"Unit";"Marine";"Barracks";70;1
"Building";"SupplyDepot";NA;69;0
"Unit";"SCV";"Command Center";72;1
"Unit";"Marine";"Barracks";71;1
"Unit";"SCV";"Command Center";72;1
"Unit";"Medivac";"Starport";69;2
"Unit";"Marine";"Barracks";72;1
"Unit";"Marine";"Barracks";72;1
"Unit";"SCV";"Command Center";77;1
"Unit";"Marine";"Barracks";75;1
"Unit";"Marine";"Barracks";76;1
"Unit";"SCV";"Command Center";84;1
"Unit";"Marine";"Barracks";78;1
"Upgrade";"Stimpack";"TechLab";62;0
"Building";"SupplyDepot";NA;79;0
"Unit";"Marine";"Barracks";84;1
"Unit";"Marine";"Barracks";84;1
"Building";"BarracksReactor";NA;73;0
"Building";"BarracksReactor";NA;73;0
"Unit";"Marine";"Barracks";85;1
"Unit";"Marine";"Barracks";86;1
"Building";"SupplyDepot";NA;88;0
"Unit";"Medivac";"Starport";85;2
"Unit";"SCV";"Command Center";93;1
"Upgrade";"TerranInfantryWeaponsLevel1";"EngineeringBay";67;0
"Unit";"Marine";"Barracks";91;1
"Unit";"Marine";"Barracks";91;1
"Unit";"Marine";"Barracks";91;1
"Unit";"Marine";"Barracks";91;1
"Unit";"Marine";"Barracks";91;1
"Unit";"Marine";"Barracks";91;1
"Unit";"Marine";"Barracks";91;1
"Unit";"Marine";"Barracks";93;1
"Building";"FactoryTechLab";NA;93;0
"Building";"SupplyDepot";NA;93;0
"Unit";"SCV";"Command Center";103;1
"Unit";"Marine";"Barracks";96;1
"Unit";"SCV";"Command Center";103;1
"Unit";"Marine";"Barracks";96;1
"Unit";"Marine";"Barracks";97;1
"Unit";"Marine";"Barracks";98;1
"Unit";"Marine";"Barracks";104;1
"Unit";"Marine";"Barracks";104;1
"Unit";"Marine";"Barracks";104;1
"Unit";"Medivac";"Starport";96;2
"Unit";"Medivac";"Starport";96;2
"Building";"SupplyDepot";NA;104;0
"Unit";"SCV";"Command Center";110;1
"Unit";"SCV";"Command Center";110;1
"Unit";"Marine";"Barracks";104;1
"Unit";"Marine";"Barracks";106;1
"Unit";"Marine";"Barracks";110;1
"Unit";"Marine";"Barracks";110;1
"Unit";"Marine";"Barracks";110;1
"Unit";"Marine";"Barracks";110;1
"Unit";"SCV";"Command Center";117;1
"Unit";"Marine";"Barracks";121;1
"Unit";"Marine";"Barracks";121;1
"Unit";"Marine";"Barracks";121;1
"Unit";"Marine";"Barracks";121;1
"Unit";"Marine";"Barracks";121;1
"Unit";"Marine";"Barracks";121;1
"Unit";"Marine";"Barracks";122;1
"Unit";"SCV";"Command Center";126;1
"Unit";"Medivac";"Starport";113;2
"Unit";"Marine";"Barracks";125;1
"Unit";"Marine";"Barracks";126;1
"Unit";"SCV";"Command Center";131;1
"Unit";"SCV";"Command Center";133;1
"Unit";"Marine";"Barracks";126;1
"Unit";"Marine";"Barracks";127;1
"Building";"SupplyDepot";NA;136;0
"Unit";"Marine";"Barracks";138;1
"Unit";"Marine";"Barracks";138;1
"Unit";"Marine";"Barracks";138;1
"Unit";"Marine";"Barracks";138;1
"Unit";"Marine";"Barracks";138;1
"Unit";"Marine";"Barracks";139;1
"Unit";"Medivac";"Starport";136;2
"Unit";"Marine";"Barracks";144;1
"Unit";"Marine";"Barracks";144;1
"Unit";"Marine";"Barracks";144;1
"Unit";"Marine";"Barracks";144;1
"Unit";"Marine";"Barracks";144;1
"Unit";"Marine";"Barracks";144;1
"Upgrade";"TerranInfantryArmorsLevel1";"EngineeringBay";117;0
"Unit";"Marine";"Barracks";156;1
"Unit";"Marine";"Barracks";156;1
"Unit";"Marine";"Barracks";156;1
"Unit";"Marine";"Barracks";156;1
"Building";"Armory";NA;150;0
"Unit";"Marine";"Barracks";157;1
"Unit";"Marine";"Barracks";160;1
"Unit";"Marine";"Barracks";160;1
"Unit";"Marine";"Barracks";160;1
"Unit";"Marine";"Barracks";160;1
