"type";"unit_name";"on_building";"total_supply";"supply"
"Building";"Refinery";NA;14;0
"Building";"Barracks";NA;15;0
"Unit";"Reaper";"Barracks";18;1
"Building";"Refinery";NA;21;0
"Building";"BarracksReactor";NA;20;0
"Building";"Factory";NA;19;0
"Building";"CommandCenter";NA;19;0
"Unit";"Cyclone";"Factory";24;3
"Unit";"Marine";"Barracks";25;1
"Unit";"Cyclone";"Factory";25;3
"Unit";"Marine";"Barracks";33;1
"Building";"Bunker";NA;29;0
"Unit";"Cyclone";"Factory";33;3
"Unit";"Cyclone";"Factory";34;3
"Unit";"Marine";"Barracks";40;1
"Unit";"Cyclone";"Factory";41;3
"Building";"EngineeringBay";NA;41;0
"Unit";"Cyclone";"Factory";47;3
"Building";"MissileTurret";NA;52;0
"Unit";"Cyclone";"Factory";56;3
"Building";"Refinery";NA;56;0
"Building";"Refinery";NA;56;0
"Unit";"Cyclone";"Factory";56;3
"Building";"CommandCenter";NA;55;0
"Unit";"Cyclone";"Factory";67;3
"Unit";"Cyclone";"Factory";67;3
"Building";"MissileTurret";NA;76;0
"Unit";"Hellion";"Factory";77;2
"Unit";"Hellion";"Factory";77;2
"Building";"MissileTurret";NA;78;0
"Building";"Factory";NA;69;0
"Building";"Factory";NA;69;0
"Unit";"Hellion";"Factory";84;2
"Unit";"Hellion";"Factory";84;2
"Building";"Armory";NA;77;0
"Building";"FactoryTechLab";NA;85;0
"Building";"FactoryTechLab";NA;85;0
"Building";"Armory";NA;77;0
"Unit";"Hellion";"Factory";92;2
"Unit";"Hellion";"Factory";92;2
"Building";"MissileTurret";NA;92;0
"Building";"Refinery";NA;97;0
"Building";"Refinery";NA;97;0
"Unit";"Hellion";"Factory";97;2
"Unit";"Hellion";"Factory";97;2
"Building";"Refinery";NA;101;0
"Unit";"Hellion";"Factory";101;2
"Unit";"Hellion";"Factory";101;2
"Unit";"Hellion";"Factory";108;2
"Unit";"Hellion";"Factory";108;2
"Building";"Factory";NA;101;0
"Building";"Factory";NA;101;0
"Upgrade";"TerranVehicleWeaponsLevel1";"Armory";97;0
"Building";"Starport";NA;111;0
"Building";"Starport";NA;111;0
"Building";"FactoryReactor";NA;117;0
"Building";"MissileTurret";NA;118;0
"Building";"MissileTurret";NA;118;0
"Building";"FactoryTechLab";NA;118;0
"Unit";"Hellion";"Factory";118;2
"Unit";"Hellion";"Factory";118;2
"Building";"MissileTurret";NA;118;0
"Unit";"Hellion";"Factory";118;2
"Unit";"Hellion";"Factory";118;2
"Building";"StarportReactor";NA;118;0
"Building";"StarportReactor";NA;118;0
"Unit";"Hellion";"Factory";122;2
"Unit";"Hellion";"Factory";122;2
"Building";"SensorTower";NA;130;0
"Building";"MissileTurret";NA;135;0
"Building";"MissileTurret";NA;135;0
"Upgrade";"TerranVehicleWeaponsLevel2";"Armory";122;0
"Unit";"Hellion";"Factory";138;2
"Unit";"Hellion";"Factory";138;2
"Unit";"Hellion";"Factory";138;2
"Unit";"Hellion";"Factory";138;2
"Unit";"Liberator";"Starport";138;3
"Unit";"Hellion";"Factory";138;2
"Unit";"Hellion";"Factory";146;2
"Building";"CommandCenter";NA;138;0
"Unit";"Hellion";"Factory";146;2
"Unit";"Hellion";"Factory";146;2
"Unit";"Hellion";"Factory";146;2
"Building";"MissileTurret";NA;160;0
"Unit";"Liberator";"Starport";154;3
"Unit";"Liberator";"Starport";154;3
"Unit";"Hellion";"Factory";160;2
"Unit";"Hellion";"Factory";160;2
"Unit";"Hellion";"Factory";160;2
"Unit";"Hellion";"Factory";160;2
"Unit";"Hellion";"Factory";160;2
"Unit";"Hellion";"Factory";166;2
"Unit";"Hellion";"Factory";168;2
"Unit";"Hellion";"Factory";170;2
"Unit";"Hellion";"Factory";182;2
"Unit";"Hellion";"Factory";182;2
"Unit";"Hellion";"Factory";182;2
"Unit";"Hellion";"Factory";184;2
"Building";"CommandCenter";NA;176;0
"Unit";"Hellion";"Factory";196;2
"Unit";"Hellion";"Factory";196;2
"Unit";"Hellion";"Factory";196;2
"Unit";"Hellion";"Factory";196;2
"Unit";"Hellion";"Factory";196;2
"Building";"MissileTurret";NA;206;0
"Building";"MissileTurret";NA;206;0
"Unit";"Hellion";"Factory";206;2
"Unit";"Hellion";"Factory";206;2
"Unit";"Hellion";"Factory";206;2
"Unit";"Hellion";"Factory";206;2
"Unit";"Hellion";"Factory";206;2
"Unit";"Hellion";"Factory";206;2
"Building";"MissileTurret";NA;217;0
"Building";"Refinery";NA;217;0
"Building";"Refinery";NA;217;0
"Unit";"Hellion";"Factory";217;2
"Unit";"Hellion";"Factory";217;2
"Unit";"Hellion";"Factory";217;2
"Unit";"Liberator";"Starport";206;3
"Unit";"Liberator";"Starport";206;3
"Building";"Starport";NA;216;0
"Building";"MissileTurret";NA;219;0
"Building";"MissileTurret";NA;219;0
"Building";"Starport";NA;216;0
"Building";"Starport";NA;216;0
"Building";"MissileTurret";NA;233;0
"Upgrade";"TerranVehicleWeaponsLevel3";"Armory";196;0
"Building";"StarportTechLab";NA;233;0
"Building";"StarportTechLab";NA;233;0
"Building";"StarportTechLab";NA;233;0
"Unit";"Hellion";"Factory";233;2
"Unit";"Hellion";"Factory";233;2
"Unit";"Hellion";"Factory";237;2
"Unit";"Hellion";"Factory";237;2
"Building";"FusionCore";NA;233;0
"Unit";"Raven";"Starport";246;2
"Unit";"Raven";"Starport";246;2
"Unit";"Raven";"Starport";246;2
"Building";"Armory";NA;246;0
"Building";"MissileTurret";NA;252;0
"Building";"MissileTurret";NA;252;0
"Building";"MissileTurret";NA;252;0
"Building";"MissileTurret";NA;252;0
"Building";"MissileTurret";NA;252;0
"Building";"MissileTurret";NA;252;0
"Building";"MissileTurret";NA;252;0
"Building";"MissileTurret";NA;252;0
"Building";"MissileTurret";NA;252;0
"Building";"MissileTurret";NA;252;0
"Unit";"Raven";"Starport";252;2
"Unit";"Raven";"Starport";252;2
"Unit";"Hellion";"Factory";252;2
"Unit";"Hellion";"Factory";252;2
"Unit";"Hellion";"Factory";252;2
"Unit";"Hellion";"Factory";252;2
"Unit";"Hellion";"Factory";252;2
"Unit";"Hellion";"Factory";252;2
"Building";"MissileTurret";NA;252;0
"Unit";"Liberator";"Starport";252;3
"Unit";"Liberator";"Starport";252;3
"Unit";"Liberator";"Starport";252;3
"Unit";"Liberator";"Starport";252;3
"Unit";"Raven";"Starport";252;2
"Unit";"Raven";"Starport";254;2
"Building";"CommandCenter";NA;252;0
"Unit";"Raven";"Starport";280;2
"Unit";"Hellion";"Factory";288;2
"Unit";"Hellion";"Factory";288;2
"Unit";"Hellion";"Factory";288;2
"Unit";"Hellion";"Factory";288;2
"Unit";"Hellion";"Factory";288;2
"Building";"MissileTurret";NA;300;0
"Building";"MissileTurret";NA;300;0
"Building";"MissileTurret";NA;300;0
"Unit";"Hellion";"Factory";290;2
"Building";"Refinery";NA;300;0
"Building";"Refinery";NA;300;0
"Unit";"Hellion";"Factory";302;2
"Unit";"Hellion";"Factory";302;2
"Unit";"Hellion";"Factory";302;2
"Unit";"Hellion";"Factory";302;2
"Building";"StarportTechLab";NA;302;0
"Unit";"Hellion";"Factory";310;2
"Unit";"Hellion";"Factory";310;2
"Unit";"Raven";"Starport";302;2
"Unit";"Raven";"Starport";302;2
"Unit";"Hellion";"Factory";310;2
"Unit";"Hellion";"Factory";310;2
