"type";"unit_name";"on_building";"total_supply";"supply"
"Building";"Refinery";NA;13;0
"Building";"Barracks";NA;15;0
"Building";"Barracks";NA;15;0
"Building";"Refinery";NA;15;0
"Building";"Barracks";NA;15;0
"Unit";"Reaper";"Barracks";15;1
"Unit";"Reaper";"Barracks";15;1
"Unit";"Reaper";"Barracks";16;1
"Unit";"Reaper";"Barracks";16;1
"Unit";"Reaper";"Barracks";16;1
"Unit";"Reaper";"Barracks";17;1
"Unit";"Reaper";"Barracks";18;1
