"Type";"UnitName";"OnBuilding";"TotalSupply";"Supply"
"Unit";"SCV";"Command Center";12;1
"Unit";"SCV";"Command Center";12;1
"Unit";"SCV";"Command Center";13;1
"Building";"SupplyDepot";NA;13;0
"Unit";"SCV";"Command Center";15;1
"Unit";"SCV";"Command Center";15;1
"Building";"Refinery";NA;15;0
"Unit";"SCV";"Command Center";16;1
"Building";"Barracks";NA;15;0
"Unit";"SCV";"Command Center";17;1
"Unit";"Reaper";"Barracks";19;1
"Unit";"SCV";"Command Center";19;1
"Unit";"SCV";"Command Center";20;1
"Building";"SupplyDepot";NA;21;0
"Unit";"SCV";"Command Center";21;1
"Building";"Refinery";NA;21;0
"Building";"Barracks";NA;19;0
"Building";"BarracksReactor";NA;20;0
"Unit";"SCV";"Command Center";22;1
"Building";"CommandCenter";NA;19;0
"Unit";"SCV";"Command Center";23;1
"Building";"BarracksTechLab";NA;23;0
"Unit";"Marine";"Barracks";23;1
"Unit";"Marine";"Barracks";23;1
"Unit";"SCV";"Command Center";27;1
"Building";"Factory";NA;23;0
"Unit";"Marine";"Barracks";25;1
"Unit";"Marine";"Barracks";25;1
"Unit";"Marine";"Barracks";26;1
"Unit";"SCV";"Command Center";27;1
"Unit";"Marine";"Barracks";28;1
"Unit";"SCV";"Command Center";31;1
"Unit";"SCV";"Command Center";32;1
"Unit";"SCV";"Command Center";33;1
"Unit";"Marine";"Barracks";32;1
"Unit";"Marine";"Barracks";32;1
"Unit";"SCV";"Command Center";35;1
"Unit";"SCV";"Command Center";35;1
"Unit";"Marine";"Barracks";35;1
"Unit";"SCV";"Command Center";39;1
"Building";"SupplyDepot";NA;35;0
"Unit";"Marine";"Barracks";36;1
"Unit";"Marine";"Barracks";37;1
"Building";"FactoryReactor";NA;33;0
"Building";"Starport";NA;34;0
"Unit";"SCV";"Command Center";39;1
"Unit";"SCV";"Command Center";41;1
"Building";"SupplyDepot";NA;39;0
"Unit";"Marine";"Barracks";44;1
"Unit";"Marine";"Barracks";44;1
"Unit";"Marine";"Barracks";44;1
"Unit";"SCV";"Command Center";45;1
"Unit";"SCV";"Command Center";45;1
"Unit";"SCV";"Command Center";49;1
"Unit";"SCV";"Command Center";51;1
"Unit";"Marine";"Barracks";46;1
"Unit";"Marine";"Barracks";47;1
"Unit";"Marine";"Barracks";48;1
"Building";"SupplyDepot";NA;46;0
"Unit";"Medivac";"Starport";46;2
"Unit";"Medivac";"Starport";46;2
"Unit";"SCV";"Command Center";51;1
"Unit";"SCV";"Command Center";56;1
"Unit";"Marine";"Barracks";53;1
"Unit";"Marine";"Barracks";54;1
"Building";"EngineeringBay";NA;51;0
"Building";"EngineeringBay";NA;51;0
"Unit";"SCV";"Command Center";60;1
"Unit";"Marine";"Barracks";56;1
"Upgrade";"Stimpack";"TechLab";35;0
"Unit";"SCV";"Command Center";64;1
"Unit";"SCV";"Command Center";64;1
"Building";"FactoryTechLab";NA;62;0
"Building";"SupplyDepot";NA;66;0
"Unit";"Marine";"Barracks";68;1
"Unit";"Marine";"Barracks";68;1
"Unit";"Marine";"Barracks";68;1
"Unit";"SCV";"Command Center";68;1
"Unit";"SCV";"Command Center";68;1
"Building";"SupplyDepot";NA;68;0
"Unit";"SCV";"Command Center";73;1
"Unit";"Marine";"Barracks";73;1
"Unit";"Marine";"Barracks";74;1
"Unit";"Marine";"Barracks";74;1
"Building";"Barracks";NA;68;0
"Building";"Barracks";NA;68;0
"Building";"CommandCenter";NA;66;0
"Building";"Barracks";NA;71;0
"Unit";"SCV";"Command Center";75;1
"Unit";"SCV";"Command Center";75;1
"Building";"Refinery";NA;74;0
"Building";"Refinery";NA;74;0
"Unit";"Marine";"Barracks";74;1
"Unit";"Medivac";"Starport";74;2
"Unit";"Medivac";"Starport";74;2
"Unit";"Marine";"Barracks";79;1
"Unit";"Marine";"Barracks";79;1
"Unit";"Marine";"Barracks";79;1
"Unit";"SCV";"Command Center";84;1
"Unit";"SCV";"Command Center";84;1
"Unit";"SCV";"Command Center";89;1
"Unit";"SCV";"Command Center";89;1
"Unit";"Marine";"Barracks";87;1
"Unit";"Marine";"Barracks";87;1
"Unit";"Marine";"Barracks";87;1
"Building";"MissileTurret";NA;89;0
"Unit";"SCV";"Command Center";89;1
"Unit";"SCV";"Command Center";90;1
"Upgrade";"TerranInfantryWeaponsLevel1";"EngineeringBay";73;0
"Upgrade";"TerranInfantryArmorsLevel1";"EngineeringBay";73;0
"Building";"BarracksReactor";NA;84;0
"Building";"BarracksReactor";NA;84;0
"Building";"BarracksReactor";NA;84;0
"Unit";"SCV";"Command Center";94;1
"Unit";"Marine";"Barracks";91;1
"Unit";"Marine";"Barracks";92;1
"Unit";"Marine";"Barracks";93;1
"Unit";"SCV";"Command Center";94;1
"Unit";"SCV";"Command Center";96;1
"Building";"SupplyDepot";NA;94;0
"Building";"Armory";NA;87;0
"Building";"SupplyDepot";NA;96;0
"Building";"SupplyDepot";NA;96;0
"Unit";"Marine";"Barracks";96;1
"Unit";"Marine";"Barracks";96;1
"Unit";"Marine";"Barracks";96;1
"Unit";"Marine";"Barracks";96;1
"Unit";"Marine";"Barracks";96;1
"Unit";"Marine";"Barracks";96;1
"Unit";"Marine";"Barracks";97;1
"Unit";"Marine";"Barracks";98;1
"Unit";"Marine";"Barracks";99;1
"Unit";"SCV";"Command Center";102;1
"Unit";"SCV";"Command Center";102;1
"Unit";"SCV";"Command Center";102;1
"Unit";"Medivac";"Starport";96;2
"Unit";"Marine";"Barracks";102;1
"Unit";"Marine";"Barracks";103;1
"Unit";"Marine";"Barracks";104;1
"Unit";"Marine";"Barracks";104;1
"Unit";"Marine";"Barracks";106;1
"Building";"SupplyDepot";NA;102;0
"Unit";"SCV";"Command Center";112;1
"Unit";"SCV";"Command Center";112;1
"Building";"SupplyDepot";NA;106;0
"Unit";"Marine";"Barracks";111;1
"Unit";"Marine";"Barracks";111;1
"Building";"SupplyDepot";NA;116;0
"Unit";"Marine";"Barracks";116;1
"Unit";"Marine";"Barracks";116;1
"Building";"MissileTurret";NA;116;0
"Unit";"Marine";"Barracks";116;1
"Unit";"Marine";"Barracks";117;1
"Building";"MissileTurret";NA;123;0
"Building";"MissileTurret";NA;125;0
"Unit";"Marine";"Barracks";125;1
"Unit";"Marine";"Barracks";125;1
"Unit";"Marine";"Barracks";125;1
"Unit";"Marine";"Barracks";125;1
"Unit";"Marine";"Barracks";125;1
"Unit";"Marine";"Barracks";128;1
"Unit";"Marine";"Barracks";128;1
"Unit";"Marine";"Barracks";129;1
"Building";"MissileTurret";NA;129;0
"Building";"FactoryTechLab";NA;129;0
"Unit";"Marine";"Barracks";129;1
"Unit";"Marine";"Barracks";129;1
"Building";"Starport";NA;125;0
"Building";"Refinery";NA;134;0
"Building";"Refinery";NA;134;0
"Building";"MissileTurret";NA;134;0
"Unit";"Marine";"Barracks";137;1
"Unit";"Marine";"Barracks";137;1
"Unit";"Marine";"Barracks";137;1
"Unit";"Marine";"Barracks";137;1
"Building";"MissileTurret";NA;139;0
"Unit";"Marine";"Barracks";143;1
"Unit";"Marine";"Barracks";143;1
"Unit";"Marine";"Barracks";143;1
"Unit";"Marine";"Barracks";143;1
"Unit";"Marine";"Barracks";143;1
"Unit";"Marine";"Barracks";143;1
"Building";"SupplyDepot";NA;143;0
"Unit";"SCV";"Command Center";143;1
"Unit";"SCV";"Command Center";143;1
"Building";"SupplyDepot";NA;143;0
"Unit";"Marine";"Barracks";143;1
"Unit";"Marine";"Barracks";143;1
"Unit";"Marine";"Barracks";143;1
"Building";"SupplyDepot";NA;143;0
"Unit";"Marine";"Barracks";149;1
"Unit";"Marine";"Barracks";149;1
"Building";"SupplyDepot";NA;143;0
"Building";"SupplyDepot";NA;149;0
"Unit";"Raven";"Starport";139;2
"Unit";"Marine";"Barracks";149;1
"Unit";"SCV";"Command Center";154;1
"Unit";"Marine";"Barracks";149;1
"Unit";"Marine";"Barracks";151;1
"Unit";"Marine";"Barracks";151;1
"Unit";"Medivac";"Starport";149;2
"Unit";"Medivac";"Starport";149;2
"Unit";"Marine";"Barracks";156;1
"Unit";"Marine";"Barracks";156;1
"Unit";"Marine";"Barracks";156;1
"Unit";"Marine";"Barracks";156;1
"Unit";"Marine";"Barracks";156;1
"Unit";"Marine";"Barracks";158;1
"Building";"CommandCenter";NA;139;0
"Unit";"Marine";"Barracks";160;1
"Upgrade";"TerranInfantryWeaponsLevel2";"EngineeringBay";129;0
"Building";"SensorTower";NA;163;0
"Upgrade";"TerranInfantryArmorsLevel2";"EngineeringBay";131;0
"Building";"Refinery";NA;172;0
"Building";"Refinery";NA;173;0
"Building";"SensorTower";NA;173;0
"Unit";"Raven";"Starport";158;2
"Unit";"Marine";"Barracks";174;1
"Unit";"Marine";"Barracks";174;1
"Unit";"Marine";"Barracks";174;1
"Unit";"Marine";"Barracks";174;1
"Unit";"Marine";"Barracks";174;1
"Unit";"Marine";"Barracks";174;1
"Unit";"Marine";"Barracks";174;1
"Unit";"Marine";"Barracks";174;1
"Building";"Starport";NA;170;0
"Unit";"Marine";"Barracks";174;1
"Building";"Starport";NA;174;0
"Unit";"Marine";"Barracks";176;1
"Unit";"Marine";"Barracks";177;1
"Unit";"SCV";"Command Center";184;1
"Unit";"SCV";"Command Center";184;1
"Unit";"Marine";"Barracks";185;1
"Unit";"Marine";"Barracks";185;1
"Unit";"Marine";"Barracks";185;1
"Unit";"Marine";"Barracks";185;1
"Unit";"Marine";"Barracks";185;1
"Unit";"Marine";"Barracks";185;1
"Unit";"Marine";"Barracks";185;1
"Building";"StarportTechLab";NA;187;0
"Building";"StarportTechLab";NA;189;0
"Upgrade";"TerranVehicleWeaponsLevel1";"Armory";163;0
"Unit";"Marine";"Barracks";196;1
"Unit";"Marine";"Barracks";196;1
"Unit";"Marine";"Barracks";196;1
"Unit";"Marine";"Barracks";196;1
"Building";"MissileTurret";NA;196;0
"Building";"MissileTurret";NA;196;0
"Building";"MissileTurret";NA;196;0
"Unit";"Raven";"Starport";189;2
"Unit";"Raven";"Starport";196;2
"Unit";"Marine";"Barracks";200;1
"Unit";"Marine";"Barracks";200;1
"Unit";"Marine";"Barracks";200;1
"Unit";"Marine";"Barracks";200;1
"Unit";"Marine";"Barracks";200;1
"Unit";"Marine";"Barracks";200;1
"Unit";"Marine";"Barracks";200;1
"Unit";"Marine";"Barracks";200;1
"Unit";"Marine";"Barracks";200;1
"Unit";"Marine";"Barracks";204;1
"Unit";"Marine";"Barracks";205;1
"Unit";"Marine";"Barracks";213;1
"Unit";"Marine";"Barracks";213;1
"Unit";"Marine";"Barracks";213;1
"Unit";"Marine";"Barracks";213;1
"Unit";"Marine";"Barracks";213;1
"Unit";"Marine";"Barracks";213;1
"Unit";"Marine";"Barracks";213;1
"Unit";"Raven";"Starport";200;2
"Unit";"Raven";"Starport";202;2
"Unit";"Marine";"Barracks";213;1
"Unit";"Marine";"Barracks";214;1
"Unit";"Marine";"Barracks";215;1
"Unit";"Marine";"Barracks";216;1
"Unit";"Marine";"Barracks";217;1
"Unit";"Marine";"Barracks";218;1
"Unit";"Raven";"Starport";202;2
"Unit";"Marine";"Barracks";219;1
"Unit";"Marine";"Barracks";220;1
"Unit";"Marine";"Barracks";220;1
"Unit";"Marine";"Barracks";232;1
"Unit";"Marine";"Barracks";232;1
"Unit";"Marine";"Barracks";232;1
"Unit";"Marine";"Barracks";234;1
"Unit";"Marine";"Barracks";234;1
"Unit";"Marine";"Barracks";234;1
"Unit";"Marine";"Barracks";234;1
"Unit";"SCV";"Command Center";237;1
"Unit";"SCV";"Command Center";237;1
"Unit";"SCV";"Command Center";237;1
"Unit";"SCV";"Command Center";237;1
"Unit";"Raven";"Starport";222;2
"Upgrade";"TerranInfantryWeaponsLevel3";"EngineeringBay";196;0
"Upgrade";"TerranInfantryArmorsLevel3";"EngineeringBay";196;0
"Building";"Barracks";NA;222;0
"Building";"Barracks";NA;222;0
"Building";"Barracks";NA;222;0
"Unit";"Marine";"Barracks";243;1
"Unit";"Marine";"Barracks";243;1
"Unit";"Marine";"Barracks";243;1
"Unit";"Marine";"Barracks";243;1
"Unit";"Marine";"Barracks";243;1
"Unit";"Marine";"Barracks";243;1
"Unit";"Marine";"Barracks";243;1
"Unit";"Marine";"Barracks";243;1
"Unit";"Raven";"Starport";224;2
"Unit";"Marine";"Barracks";243;1
"Building";"CommandCenter";NA;213;0
