"type";"unit_name";"on_building";"total_supply";"supply"
"Building";"Refinery";NA;14;0
"Building";"Barracks";NA;15;0
"Unit";"Reaper";"Barracks";19;1
"Building";"Refinery";NA;20;0
"Unit";"Reaper";"Barracks";20;1
"Building";"Factory";NA;19;0
"Building";"CommandCenter";NA;19;0
"Unit";"Hellion";"Factory";23;2
"Building";"Starport";NA;23;0
"Building";"BarracksReactor";NA;23;0
"Unit";"Hellion";"Factory";28;2
"Unit";"Marine";"Barracks";28;1
"Unit";"Marine";"Barracks";28;1
"Unit";"Liberator";"Starport";28;3
"Unit";"Cyclone";"Factory";36;3
"Unit";"Marine";"Barracks";36;1
"Unit";"Marine";"Barracks";36;1
"Unit";"Marine";"Barracks";46;1
"Unit";"Marine";"Barracks";47;1
"Building";"FactoryTechLab";NA;48;0
"Unit";"Marine";"Barracks";49;1
"Unit";"Marine";"Barracks";50;1
"Unit";"Marine";"Barracks";55;1
"Unit";"Marine";"Barracks";55;1
"Building";"Barracks";NA;51;0
"Unit";"Marine";"Barracks";57;1
"Unit";"Marine";"Barracks";57;1
"Building";"Starport";NA;55;0
"Building";"BarracksTechLab";NA;57;0
"Building";"EngineeringBay";NA;57;0
"Unit";"Marine";"Barracks";61;1
"Unit";"Marine";"Barracks";61;1
"Building";"EngineeringBay";NA;59;0
"Unit";"Marine";"Barracks";63;1
"Building";"Barracks";NA;57;0
"Unit";"Marine";"Barracks";63;1
"Unit";"Marine";"Barracks";64;1
"Building";"Refinery";NA;65;0
"Building";"Refinery";NA;65;0
"Building";"StarportReactor";NA;63;0
"Unit";"Marine";"Barracks";72;1
"Unit";"Marine";"Barracks";72;1
"Unit";"Marine";"Barracks";72;1
"Unit";"Marine";"Barracks";74;1
"Unit";"Marine";"Barracks";74;1
"Building";"BarracksTechLab";NA;81;0
"Building";"CommandCenter";NA;67;0
"Unit";"Marine";"Barracks";82;1
"Unit";"Marine";"Barracks";82;1
"Unit";"Medivac";"Starport";82;2
"Unit";"Medivac";"Starport";82;2
"Unit";"Marine";"Barracks";84;1
"Unit";"Marine";"Barracks";84;1
"Unit";"Marine";"Barracks";86;1
"Unit";"Marine";"Barracks";86;1
"Building";"Barracks";NA;81;0
"Building";"Barracks";NA;82;0
"Upgrade";"Stimpack";"TechLab";72;0
"Unit";"Marine";"Barracks";92;1
"Unit";"Marine";"Barracks";93;1
"Unit";"Marine";"Barracks";94;1
"Upgrade";"TerranInfantryWeaponsLevel1";"EngineeringBay";77;0
"Unit";"Marine";"Barracks";95;1
"Unit";"Marine";"Barracks";96;1
"Building";"Refinery";NA;96;0
"Building";"BarracksTechLab";NA;98;0
"Building";"Refinery";NA;96;0
"Building";"Armory";NA;86;0
"Upgrade";"TerranInfantryArmorsLevel1";"EngineeringBay";80;0
"Unit";"Marine";"Barracks";102;1
"Unit";"Marine";"Barracks";102;1
"Unit";"Marine";"Barracks";102;1
"Unit";"Marine";"Barracks";103;1
"Building";"BarracksReactor";NA;100;0
"Building";"MissileTurret";NA;105;0
"Unit";"Marine";"Barracks";106;1
"Unit";"Marine";"Barracks";109;1
"Unit";"Marine";"Barracks";109;1
"Unit";"Marine";"Barracks";111;1
"Unit";"Marine";"Barracks";112;1
"Unit";"Marine";"Barracks";112;1
"Building";"BarracksReactor";NA;106;0
"Unit";"Marine";"Barracks";113;1
"Building";"Factory";NA;105;0
"Unit";"Marine";"Barracks";118;1
"Unit";"Marine";"Barracks";118;1
"Unit";"Marine";"Barracks";118;1
"Unit";"Marine";"Barracks";118;1
"Unit";"Marine";"Barracks";119;1
"Unit";"Marine";"Barracks";121;1
"Unit";"Marine";"Barracks";121;1
"Unit";"Marine";"Barracks";121;1
"Unit";"Marine";"Barracks";121;1
"Unit";"Marine";"Barracks";122;1
"Unit";"Marine";"Barracks";123;1
"Unit";"Marine";"Barracks";125;1
"Unit";"Marine";"Barracks";127;1
"Unit";"Marine";"Barracks";131;1
"Unit";"Marine";"Barracks";131;1
"Unit";"Marine";"Barracks";139;1
"Unit";"Marine";"Barracks";139;1
"Unit";"Marine";"Barracks";141;1
"Unit";"Marine";"Barracks";141;1
"Unit";"Marine";"Barracks";141;1
"Building";"MissileTurret";NA;141;0
"Building";"MissileTurret";NA;142;0
"Unit";"Medivac";"Starport";143;2
"Unit";"Marine";"Barracks";150;1
"Unit";"Marine";"Barracks";150;1
"Unit";"Marine";"Barracks";150;1
"Upgrade";"TerranVehicleWeaponsLevel1";"Armory";121;0
"Unit";"Marine";"Barracks";150;1
"Unit";"Marine";"Barracks";150;1
"Unit";"Marine";"Barracks";150;1
"Unit";"Marine";"Barracks";150;1
"Unit";"Marine";"Barracks";150;1
"Unit";"Medivac";"Starport";150;2
"Building";"MissileTurret";NA;150;0
"Upgrade";"TerranInfantryWeaponsLevel2";"EngineeringBay";118;0
"Upgrade";"TerranInfantryArmorsLevel2";"EngineeringBay";121;0
"Unit";"Marine";"Barracks";155;1
"Unit";"Marine";"Barracks";155;1
"Unit";"Marine";"Barracks";155;1
"Unit";"Marine";"Barracks";165;1
"Unit";"Marine";"Barracks";165;1
"Unit";"Marine";"Barracks";166;1
"Unit";"Marine";"Barracks";169;1
"Unit";"Marine";"Barracks";169;1
"Unit";"Marine";"Barracks";169;1
"Unit";"Marine";"Barracks";172;1
"Unit";"Marine";"Barracks";172;1
"Unit";"Marine";"Barracks";172;1
"Unit";"Marine";"Barracks";173;1
"Unit";"Marine";"Barracks";174;1
"Unit";"Marine";"Barracks";176;1
"Unit";"Marine";"Barracks";177;1
"Unit";"Marine";"Barracks";178;1
"Unit";"Marine";"Barracks";179;1
"Unit";"Marine";"Barracks";180;1
"Unit";"Marine";"Barracks";181;1
"Unit";"Marine";"Barracks";182;1
"Unit";"Marine";"Barracks";183;1
"Unit";"Medivac";"Starport";181;2
"Unit";"Marine";"Barracks";184;1
"Building";"BarracksReactor";NA;181;0
"Unit";"Marine";"Barracks";185;1
"Unit";"Marine";"Barracks";186;1
"Unit";"Marine";"Barracks";187;1
"Building";"Barracks";NA;181;0
"Unit";"Marine";"Barracks";193;1
"Unit";"Marine";"Barracks";194;1
"Unit";"Marine";"Barracks";195;1
"Unit";"Marine";"Barracks";196;1
"Unit";"Marine";"Barracks";199;1
"Unit";"Marine";"Barracks";199;1
"Upgrade";"TerranVehicleWeaponsLevel2";"Armory";172;0
"Unit";"Marine";"Barracks";199;1
"Unit";"Marine";"Barracks";200;1
"Building";"Barracks";NA;194;0
"Unit";"Marine";"Barracks";207;1
"Unit";"Marine";"Barracks";207;1
"Unit";"Marine";"Barracks";207;1
"Unit";"Marine";"Barracks";207;1
"Unit";"Marine";"Barracks";207;1
"Unit";"Marine";"Barracks";207;1
"Unit";"Marine";"Barracks";207;1
"Unit";"Marine";"Barracks";207;1
"Unit";"Medivac";"Starport";207;2
"Unit";"Marine";"Barracks";207;1
"Unit";"Marine";"Barracks";207;1
"Unit";"Medivac";"Starport";207;2
"Unit";"Marine";"Barracks";207;1
"Unit";"Marine";"Barracks";207;1
"Building";"Refinery";NA;207;0
"Unit";"Marine";"Barracks";215;1
"Unit";"Marine";"Barracks";215;1
"Unit";"Marine";"Barracks";215;1
"Unit";"Marine";"Barracks";215;1
"Unit";"Marine";"Barracks";215;1
"Unit";"Marine";"Barracks";215;1
"Unit";"Marine";"Barracks";217;1
"Unit";"Marine";"Barracks";218;1
"Unit";"Marine";"Barracks";221;1
"Unit";"Marine";"Barracks";223;1
"Unit";"Marine";"Barracks";223;1
"Unit";"Marine";"Barracks";224;1
"Unit";"Marine";"Barracks";224;1
"Unit";"Marine";"Barracks";224;1
"Unit";"Marine";"Barracks";224;1
"Unit";"Marine";"Barracks";229;1
"Upgrade";"TerranInfantryWeaponsLevel3";"EngineeringBay";185;0
"Upgrade";"TerranInfantryArmorsLevel3";"EngineeringBay";185;0
