"type";"unit_name";"on_building";"total_supply";"supply"
"Building";"Refinery";NA;14;0
"Building";"Barracks";NA;15;0
"Unit";"Reaper";"Barracks";19;1
"Building";"Factory";NA;19;0
"Unit";"Reaper";"Barracks";20;1
"Building";"Refinery";NA;21;0
"Building";"CommandCenter";NA;19;0
"Unit";"Hellion";"Factory";22;2
"Building";"Starport";NA;24;0
"Building";"BarracksReactor";NA;25;0
"Unit";"Cyclone";"Factory";29;3
"Unit";"Marine";"Barracks";30;1
"Unit";"Marine";"Barracks";30;1
"Unit";"Medivac";"Starport";30;2
"Unit";"Marine";"Barracks";37;1
"Unit";"Marine";"Barracks";37;1
"Building";"Bunker";NA;37;0
"Unit";"Cyclone";"Factory";40;3
"Unit";"Marine";"Barracks";46;1
"Unit";"Marine";"Barracks";46;1
"Building";"FactoryTechLab";NA;46;0
"Unit";"Marine";"Barracks";49;1
"Unit";"Marine";"Barracks";53;1
"Unit";"Marine";"Barracks";53;1
"Unit";"Liberator";"Starport";52;3
"Building";"EngineeringBay";NA;54;0
"Unit";"Marine";"Barracks";60;1
"Unit";"Marine";"Barracks";60;1
"Building";"MissileTurret";NA;65;0
"Unit";"Marine";"Barracks";69;1
"Unit";"Marine";"Barracks";69;1
"Building";"Refinery";NA;70;0
"Unit";"Marine";"Barracks";74;1
"Unit";"Marine";"Barracks";74;1
"Building";"StarportReactor";NA;70;0
"Building";"CommandCenter";NA;64;0
"Building";"FactoryTechLab";NA;79;0
"Unit";"Marine";"Barracks";79;1
"Building";"MissileTurret";NA;79;0
"Building";"Refinery";NA;79;0
"Building";"Barracks";NA;79;0
"Building";"Barracks";NA;79;0
"Unit";"Marine";"Barracks";83;1
"Building";"Armory";NA;82;0
"Unit";"Marine";"Barracks";88;1
"Building";"Barracks";NA;82;0
"Unit";"Marine";"Barracks";88;1
"Unit";"Marine";"Barracks";88;1
"Unit";"Marine";"Barracks";88;1
"Unit";"Marine";"Barracks";88;1
"Building";"Barracks";NA;82;0
"Unit";"Marine";"Barracks";88;1
"Unit";"Marine";"Barracks";89;1
"Unit";"Marine";"Barracks";90;1
"Building";"EngineeringBay";NA;89;0
"Building";"StarportReactor";NA;88;0
"Upgrade";"Stimpack";"TechLab";84;0
"Building";"SensorTower";NA;100;0
"Building";"SensorTower";NA;100;0
"Unit";"Marine";"Barracks";100;1
"Unit";"Marine";"Barracks";100;1
"Upgrade";"TerranInfantryWeaponsLevel1";"EngineeringBay";88;0
"Building";"BarracksReactor";NA;95;0
"Building";"BarracksReactor";NA;95;0
"Unit";"Marine";"Barracks";102;1
"Unit";"Marine";"Barracks";102;1
"Unit";"Marine";"Barracks";102;1
"Building";"Refinery";NA;102;0
"Building";"Refinery";NA;102;0
"Unit";"Marine";"Barracks";104;1
"Unit";"Marine";"Barracks";104;1
"Unit";"Medivac";"Starport";102;2
"Unit";"Medivac";"Starport";102;2
"Unit";"Marine";"Barracks";109;1
"Unit";"Marine";"Barracks";109;1
"Unit";"Marine";"Barracks";109;1
"Unit";"Marine";"Barracks";109;1
"Unit";"Marine";"Barracks";109;1
"Unit";"Marine";"Barracks";109;1
"Unit";"Marine";"Barracks";109;1
"Unit";"Marine";"Barracks";111;1
"Unit";"Marine";"Barracks";126;1
"Upgrade";"TerranVehicleWeaponsLevel1";"Armory";100;0
"Unit";"Marine";"Barracks";130;1
"Unit";"Marine";"Barracks";130;1
"Unit";"Marine";"Barracks";130;1
"Unit";"Marine";"Barracks";130;1
"Building";"Factory";NA;126;0
"Unit";"Marine";"Barracks";134;1
"Unit";"Marine";"Barracks";134;1
"Unit";"Marine";"Barracks";134;1
"Building";"FactoryTechLab";NA;134;0
"Unit";"Marine";"Barracks";134;1
"Unit";"Marine";"Barracks";134;1
"Unit";"Marine";"Barracks";134;1
"Upgrade";"TerranInfantryArmorsLevel1";"EngineeringBay";124;0
"Building";"Factory";NA;130;0
"Unit";"Marine";"Barracks";134;1
"Unit";"Marine";"Barracks";134;1
"Unit";"Marine";"Barracks";134;1
"Unit";"Marine";"Barracks";140;1
"Unit";"Marine";"Barracks";140;1
"Unit";"Marine";"Barracks";140;1
"Unit";"Marine";"Barracks";140;1
"Unit";"Marine";"Barracks";140;1
"Unit";"Marine";"Barracks";148;1
"Building";"Barracks";NA;140;0
"Unit";"Marine";"Barracks";148;1
"Building";"Barracks";NA;140;0
"Unit";"Marine";"Barracks";148;1
"Unit";"Marine";"Barracks";148;1
"Unit";"Marine";"Barracks";148;1
"Unit";"Marine";"Barracks";148;1
"Building";"Barracks";NA;140;0
"Unit";"Marine";"Barracks";148;1
"Upgrade";"TerranInfantryWeaponsLevel2";"EngineeringBay";130;0
"Unit";"Marine";"Barracks";148;1
"Unit";"Marine";"Barracks";148;1
"Building";"FactoryTechLab";NA;148;0
"Unit";"Marine";"Barracks";148;1
"Unit";"Marine";"Barracks";149;1
"Unit";"Marine";"Barracks";150;1
"Unit";"Marine";"Barracks";151;1
"Building";"MissileTurret";NA;155;0
"Unit";"Marine";"Barracks";155;1
"Unit";"Marine";"Barracks";155;1
"Unit";"Marine";"Barracks";155;1
"Building";"MissileTurret";NA;155;0
"Building";"MissileTurret";NA;155;0
"Building";"MissileTurret";NA;155;0
"Building";"MissileTurret";NA;157;0
"Building";"MissileTurret";NA;157;0
"Building";"MissileTurret";NA;157;0
"Building";"CommandCenter";NA;143;0
"Unit";"Marine";"Barracks";161;1
"Unit";"Marine";"Barracks";161;1
"Unit";"Marine";"Barracks";161;1
"Unit";"Marine";"Barracks";161;1
"Unit";"Marine";"Barracks";161;1
"Building";"BarracksReactor";NA;155;0
"Building";"BarracksReactor";NA;157;0
"Unit";"Marine";"Barracks";164;1
"Unit";"Marine";"Barracks";164;1
"Unit";"Marine";"Barracks";164;1
"Unit";"Marine";"Barracks";164;1
"Unit";"Marine";"Barracks";173;1
"Unit";"Marine";"Barracks";173;1
"Unit";"Marine";"Barracks";173;1
"Unit";"Marine";"Barracks";173;1
"Unit";"Marine";"Barracks";173;1
"Unit";"Marine";"Barracks";173;1
"Unit";"Marine";"Barracks";173;1
"Unit";"Marine";"Barracks";173;1
"Unit";"Marine";"Barracks";173;1
"Unit";"Marine";"Barracks";173;1
"Unit";"Marine";"Barracks";179;1
"Unit";"Marine";"Barracks";179;1
"Unit";"Marine";"Barracks";179;1
"Unit";"Marine";"Barracks";179;1
"Building";"StarportReactor";NA;173;0
"Unit";"Marine";"Barracks";183;1
"Unit";"Marine";"Barracks";183;1
"Unit";"Marine";"Barracks";183;1
"Unit";"Marine";"Barracks";183;1
"Unit";"Marine";"Barracks";185;1
"Unit";"Marine";"Barracks";185;1
"Unit";"Marine";"Barracks";185;1
"Unit";"Marine";"Barracks";185;1
"Unit";"Marine";"Barracks";196;1
