"type";"unit_name";"on_building";"total_supply";"supply"
"Building";"Refinery";NA;15;0
"Building";"Barracks";NA;15;0
"Unit";"Reaper";"Barracks";19;1
"Building";"Refinery";NA;20;0
"Unit";"Reaper";"Barracks";20;1
"Building";"CommandCenter";NA;19;0
"Building";"Factory";NA;24;0
"Unit";"Marine";"Barracks";27;1
"Building";"FactoryTechLab";NA;28;0
"Unit";"Marine";"Barracks";30;1
"Building";"Bunker";NA;29;0
"Building";"CommandCenter";NA;27;0
"Unit";"Marine";"Barracks";34;1
"Building";"Starport";NA;31;0
"Building";"Refinery";NA;36;0
"Building";"EngineeringBay";NA;35;0
"Building";"StarportTechLab";NA;39;0
"Building";"MissileTurret";NA;44;0
"Building";"MissileTurret";NA;44;0
"Building";"MissileTurret";NA;46;0
"Building";"Refinery";NA;46;0
"Unit";"Marine";"Barracks";46;1
"Unit";"Banshee";"Starport";44;3
"Unit";"Marine";"Barracks";51;1
"Building";"Refinery";NA;52;0
"Building";"Factory";NA;51;0
"Unit";"Banshee";"Starport";57;3
"Building";"Refinery";NA;73;0
"Building";"Armory";NA;65;0
"Building";"FactoryReactor";NA;73;0
"Building";"MissileTurret";NA;76;0
"Building";"MissileTurret";NA;78;0
"Building";"Starport";NA;75;0
"Building";"CommandCenter";NA;64;0
"Building";"Starport";NA;75;0
"Building";"MissileTurret";NA;78;0
"Building";"MissileTurret";NA;78;0
"Building";"Factory";NA;74;0
"Building";"Factory";NA;75;0
"Unit";"Hellion";"Factory";79;2
"Unit";"Hellion";"Factory";79;2
"Unit";"Raven";"Starport";78;2
"Building";"FactoryTechLab";NA;85;0
"Building";"FactoryTechLab";NA;85;0
"Unit";"Hellion";"Factory";85;2
"Unit";"Hellion";"Factory";85;2
"Building";"MissileTurret";NA;85;0
"Building";"MissileTurret";NA;85;0
"Unit";"Hellion";"Factory";87;2
"Unit";"Hellion";"Factory";89;2
"Building";"MissileTurret";NA;91;0
"Building";"MissileTurret";NA;91;0
"Building";"Refinery";NA;96;0
"Building";"Refinery";NA;96;0
"Building";"StarportTechLab";NA;96;0
"Unit";"Hellion";"Factory";96;2
"Building";"CommandCenter";NA;87;0
"Building";"StarportReactor";NA;96;0
"Building";"FusionCore";NA;96;0
"Building";"Armory";NA;96;0
"Building";"MissileTurret";NA;109;0
"Unit";"Thor";"Factory";109;6
"Unit";"Raven";"Starport";109;2
"Unit";"Raven";"Starport";109;2
"Building";"Starport";NA;111;0
"Building";"CommandCenter";NA;105;0
"Building";"Armory";NA;112;0
"Upgrade";"TerranShipWeaponsLevel1";"Armory";105;0
"Unit";"Hellion";"Factory";128;2
"Unit";"Hellion";"Factory";128;2
"Unit";"Hellion";"Factory";128;2
"Unit";"Hellion";"Factory";128;2
"Unit";"Hellion";"Factory";128;2
"Building";"StarportTechLab";NA;128;0
"Unit";"Hellion";"Factory";130;2
"Unit";"Hellion";"Factory";132;2
"Building";"Starport";NA;130;0
"Building";"Armory";NA;130;0
"Unit";"Battlecruiser";"Starport";124;6
"Building";"StarportTechLab";NA;144;0
"Unit";"Banshee";"Starport";144;3
"Unit";"Battlecruiser";"Starport";144;6
"Unit";"Battlecruiser";"Starport";144;6
"Building";"Refinery";NA;165;0
"Building";"Refinery";NA;165;0
"Unit";"Battlecruiser";"Starport";153;6
"Upgrade";"TerranShipWeaponsLevel2";"Armory";150;0
"Building";"MissileTurret";NA;170;0
"Unit";"Battlecruiser";"Starport";159;6
"Unit";"Battlecruiser";"Starport";159;6
"Unit";"Battlecruiser";"Starport";159;6
"Unit";"Hellion";"Factory";182;2
"Unit";"Hellion";"Factory";182;2
"Unit";"Hellion";"Factory";182;2
"Unit";"Hellion";"Factory";182;2
"Unit";"Hellion";"Factory";182;2
"Unit";"Battlecruiser";"Starport";180;6
"Unit";"Hellion";"Factory";202;2
"Unit";"Hellion";"Factory";204;2
"Upgrade";"TerranVehicleWeaponsLevel1";"Armory";180;0
"Unit";"Hellion";"Factory";218;2
"Unit";"Hellion";"Factory";220;2
"Building";"MissileTurret";NA;230;0
"Building";"MissileTurret";NA;230;0
"Unit";"Raven";"Starport";222;2
"Unit";"Raven";"Starport";222;2
"Building";"MissileTurret";NA;234;0
"Building";"Refinery";NA;234;0
"Building";"Refinery";NA;234;0
"Building";"CommandCenter";NA;230;0
"Unit";"Battlecruiser";"Starport";230;6
"Unit";"Battlecruiser";"Starport";230;6
"Upgrade";"TerranShipWeaponsLevel3";"Armory";222;0
"Unit";"Raven";"Starport";234;2
"Unit";"Raven";"Starport";234;2
"Building";"MissileTurret";NA;246;0
"Building";"CommandCenter";NA;234;0
"Building";"CommandCenter";NA;234;0
"Building";"Refinery";NA;250;0
"Building";"CommandCenter";NA;234;0
"Building";"Refinery";NA;250;0
"Unit";"Raven";"Starport";250;2
"Unit";"Raven";"Starport";250;2
"Unit";"Raven";"Starport";250;2
"Upgrade";"TerranVehicleWeaponsLevel2";"Armory";248;0
"Building";"CommandCenter";NA;250;0
"Unit";"Thor";"Factory";250;6
"Unit";"Thor";"Factory";250;6
"Unit";"Thor";"Factory";250;6
"Building";"MissileTurret";NA;250;0
"Building";"MissileTurret";NA;250;0
"Building";"MissileTurret";NA;250;0
"Building";"CommandCenter";NA;250;0
"Building";"CommandCenter";NA;250;0
"Building";"MissileTurret";NA;274;0
"Building";"SensorTower";NA;274;0
"Building";"SensorTower";NA;274;0
"Unit";"Thor";"Factory";274;6
"Unit";"Battlecruiser";"Starport";274;6
"Building";"MissileTurret";NA;274;0
"Building";"MissileTurret";NA;274;0
"Unit";"Hellion";"Factory";274;2
"Unit";"Hellion";"Factory";274;2
"Unit";"Hellion";"Factory";274;2
"Building";"MissileTurret";NA;286;0
"Building";"MissileTurret";NA;286;0
"Building";"MissileTurret";NA;286;0
"Building";"MissileTurret";NA;286;0
"Building";"MissileTurret";NA;286;0
"Unit";"Raven";"Starport";274;2
"Unit";"Raven";"Starport";274;2
"Unit";"Raven";"Starport";274;2
"Unit";"Thor";"Factory";274;6
"Unit";"Thor";"Factory";274;6
"Unit";"Hellion";"Factory";286;2
"Unit";"Hellion";"Factory";288;2
"Unit";"Raven";"Starport";280;2
"Building";"MissileTurret";NA;292;0
"Unit";"Thor";"Factory";290;6
"Building";"CommandCenter";NA;286;0
"Unit";"Hellion";"Factory";322;2
"Unit";"Hellion";"Factory";322;2
"Upgrade";"TerranVehicleWeaponsLevel3";"Armory";286;0
"Unit";"Thor";"Factory";322;6
"Unit";"Thor";"Factory";322;6
"Unit";"Thor";"Factory";322;6
"Unit";"Thor";"Factory";326;6
"Unit";"Thor";"Factory";332;6
"Building";"Factory";NA;344;0
"Building";"Starport";NA;344;0
"Unit";"Battlecruiser";"Starport";326;6
"Unit";"Battlecruiser";"Starport";326;6
"Unit";"Battlecruiser";"Starport";326;6
"Unit";"Battlecruiser";"Starport";326;6
"Building";"Factory";NA;344;0
"Building";"Starport";NA;344;0
"Unit";"Hellion";"Factory";344;2
"Unit";"Hellion";"Factory";344;2
"Building";"StarportTechLab";NA;380;0
"Building";"StarportTechLab";NA;380;0
"Unit";"Hellion";"Factory";380;2
"Unit";"Hellion";"Factory";382;2
"Building";"FactoryTechLab";NA;384;0
"Building";"FactoryTechLab";NA;384;0
"Unit";"Thor";"Factory";344;6
"Unit";"Raven";"Starport";356;2
"Unit";"Raven";"Starport";362;2
"Unit";"Hellion";"Factory";384;2
"Unit";"Hellion";"Factory";386;2
"Unit";"Raven";"Starport";384;2
"Unit";"Raven";"Starport";384;2
"Building";"MissileTurret";NA;398;0
"Unit";"Hellion";"Factory";402;2
"Unit";"Hellion";"Factory";402;2
"Unit";"Thor";"Factory";388;6
"Unit";"Raven";"Starport";398;2
"Unit";"Raven";"Starport";398;2
"Unit";"Raven";"Starport";398;2
"Building";"CommandCenter";NA;384;0
"Unit";"Thor";"Factory";398;6
"Unit";"Thor";"Factory";398;6
"Building";"Refinery";NA;410;0
"Building";"CommandCenter";NA;384;0
"Unit";"Raven";"Starport";416;2
"Unit";"Raven";"Starport";416;2
"Building";"MissileTurret";NA;438;0
"Unit";"Thor";"Factory";438;6
"Building";"MissileTurret";NA;438;0
"Building";"MissileTurret";NA;438;0
"Building";"MissileTurret";NA;438;0
