"type";"unit_name";"on_building";"total_supply";"supply"
"Building";"Refinery";NA;14;0
"Building";"Refinery";NA;16;0
"Building";"Barracks";NA;15;0
"Unit";"Reaper";"Barracks";19;1
"Building";"Factory";NA;19;0
"Unit";"Reaper";"Barracks";20;1
"Unit";"Cyclone";"Factory";22;3
"Building";"BarracksReactor";NA;25;0
"Unit";"Cyclone";"Factory";29;3
"Building";"CommandCenter";NA;25;0
"Unit";"Cyclone";"Factory";34;3
"Building";"EngineeringBay";NA;34;0
