"type";"unit_name";"on_building";"total_supply";"supply"
"Building";"Refinery";NA;14;0
"Building";"Refinery";NA;16;0
"Building";"Barracks";NA;15;0
"Unit";"Reaper";"Barracks";19;1
"Building";"Factory";NA;19;0
"Unit";"Reaper";"Barracks";19;1
"Unit";"Cyclone";"Factory";22;3
"Building";"Starport";NA;22;0
"Building";"BarracksTechLab";NA;29;0
"Unit";"Cyclone";"Factory";28;3
"Unit";"Medivac";"Starport";29;2
"Building";"FactoryTechLab";NA;36;0
"Building";"BarracksReactor";NA;36;0
"Unit";"Banshee";"Starport";36;3
"Building";"CommandCenter";NA;36;0
"Unit";"Marine";"Barracks";41;1
"Unit";"Marine";"Barracks";41;1
"Building";"Refinery";NA;43;0
"Building";"Refinery";NA;43;0
"Unit";"Banshee";"Starport";41;3
"Unit";"Marine";"Barracks";44;1
"Unit";"Marine";"Barracks";44;1
"Building";"CommandCenter";NA;41;0
"Unit";"Marine";"Barracks";51;1
"Unit";"Marine";"Barracks";57;1
"Unit";"Marine";"Barracks";57;1
"Unit";"Banshee";"Starport";52;3
"Building";"Factory";NA;58;0
"Building";"Factory";NA;59;0
"Unit";"Raven";"Starport";63;2
"Building";"BarracksReactor";NA;66;0
"Building";"Refinery";NA;75;0
"Building";"Refinery";NA;75;0
"Building";"EngineeringBay";NA;80;0
"Unit";"Hellion";"Factory";85;2
"Unit";"Hellion";"Factory";85;2
"Building";"MissileTurret";NA;93;0
"Building";"MissileTurret";NA;93;0
"Building";"MissileTurret";NA;95;0
"Unit";"Hellion";"Factory";98;2
"Unit";"Hellion";"Factory";98;2
"Building";"MissileTurret";NA;101;0
"Building";"MissileTurret";NA;101;0
"Building";"MissileTurret";NA;101;0
"Unit";"Hellion";"Factory";105;2
"Unit";"Hellion";"Factory";105;2
"Building";"Armory";NA;105;0
"Building";"Armory";NA;105;0
"Unit";"Hellion";"Factory";109;2
"Unit";"Hellion";"Factory";109;2
"Building";"CommandCenter";NA;101;0
"Building";"Refinery";NA;109;0
"Building";"Refinery";NA;113;0
"Building";"Factory";NA;109;0
"Building";"MissileTurret";NA;115;0
"Building";"Factory";NA;109;0
"Unit";"Hellion";"Factory";115;2
"Unit";"Hellion";"Factory";115;2
"Building";"MissileTurret";NA;115;0
"Building";"MissileTurret";NA;115;0
"Building";"SensorTower";NA;115;0
"Building";"MissileTurret";NA;115;0
"Building";"FactoryTechLab";NA;119;0
"Unit";"Hellion";"Factory";119;2
"Unit";"Hellion";"Factory";119;2
"Building";"FactoryReactor";NA;119;0
"Unit";"Liberator";"Starport";119;3
"Unit";"Hellion";"Factory";123;2
"Building";"SensorTower";NA;123;0
"Building";"SensorTower";NA;132;0
"Unit";"Hellion";"Factory";130;2
"Building";"Refinery";NA;132;0
"Unit";"Hellion";"Factory";135;2
"Unit";"Hellion";"Factory";135;2
"Unit";"Liberator";"Starport";130;3
"Upgrade";"TerranVehicleWeaponsLevel1";"Armory";121;0
"Unit";"Hellion";"Factory";137;2
"Unit";"Hellion";"Factory";137;2
"Building";"Starport";NA;144;0
"Building";"Starport";NA;144;0
"Building";"Starport";NA;144;0
"Building";"StarportTechLab";NA;148;0
"Building";"StarportTechLab";NA;148;0
"Building";"StarportTechLab";NA;148;0
"Building";"CommandCenter";NA;148;0
"Building";"SensorTower";NA;148;0
"Building";"MissileTurret";NA;148;0
"Unit";"Raven";"Starport";148;2
"Unit";"Raven";"Starport";148;2
"Unit";"Raven";"Starport";148;2
"Unit";"Thor";"Factory";148;6
"Unit";"Thor";"Factory";148;6
"Building";"Refinery";NA;148;0
"Building";"Refinery";NA;154;0
"Unit";"Raven";"Starport";148;2
"Unit";"Thor";"Factory";166;6
"Building";"MissileTurret";NA;174;0
"Unit";"Raven";"Starport";174;2
"Unit";"Raven";"Starport";174;2
"Unit";"Raven";"Starport";174;2
"Building";"MissileTurret";NA;174;0
"Unit";"Raven";"Starport";174;2
"Unit";"Raven";"Starport";176;2
"Unit";"Raven";"Starport";178;2
"Upgrade";"TerranVehicleWeaponsLevel2";"Armory";174;0
"Unit";"Raven";"Starport";180;2
"Unit";"Raven";"Starport";182;2
"Unit";"Raven";"Starport";184;2
"Building";"CommandCenter";NA;180;0
"Unit";"Thor";"Factory";186;6
"Unit";"Raven";"Starport";186;2
"Unit";"Raven";"Starport";188;2
"Unit";"Raven";"Starport";190;2
"Building";"MissileTurret";NA;204;0
"Unit";"Raven";"Starport";198;2
"Unit";"Raven";"Starport";200;2
"Unit";"Raven";"Starport";202;2
"Building";"MissileTurret";NA;204;0
"Unit";"Hellion";"Factory";204;2
"Unit";"Hellion";"Factory";204;2
"Unit";"Hellion";"Factory";204;2
"Unit";"Hellion";"Factory";204;2
"Unit";"Hellion";"Factory";204;2
"Unit";"Hellion";"Factory";204;2
"Building";"CommandCenter";NA;198;0
"Building";"CommandCenter";NA;198;0
"Unit";"Hellion";"Factory";210;2
"Unit";"Hellion";"Factory";212;2
"Unit";"Raven";"Starport";204;2
"Unit";"Raven";"Starport";206;2
"Unit";"Raven";"Starport";208;2
"Upgrade";"TerranShipWeaponsLevel1";"Armory";204;0
"Unit";"Hellion";"Factory";226;2
"Building";"CommandCenter";NA;204;0
"Building";"CommandCenter";NA;204;0
"Building";"CommandCenter";NA;204;0
"Upgrade";"TerranVehicleWeaponsLevel3";"Armory";204;0
"Building";"MissileTurret";NA;234;0
"Unit";"Hellion";"Factory";234;2
"Unit";"Hellion";"Factory";234;2
"Unit";"Raven";"Starport";234;2
"Unit";"Raven";"Starport";234;2
"Unit";"Raven";"Starport";234;2
"Building";"Refinery";NA;237;0
"Building";"Refinery";NA;247;0
"Unit";"Raven";"Starport";241;2
"Unit";"Raven";"Starport";243;2
"Unit";"Raven";"Starport";245;2
"Unit";"Thor";"Factory";247;6
"Unit";"Thor";"Factory";247;6
"Unit";"Hellion";"Factory";253;2
"Unit";"Hellion";"Factory";253;2
"Unit";"Hellion";"Factory";253;2
"Unit";"Hellion";"Factory";253;2
"Unit";"Hellion";"Factory";253;2
"Unit";"Raven";"Starport";247;2
"Building";"MissileTurret";NA;278;0
"Unit";"Hellion";"Factory";280;2
"Unit";"Hellion";"Factory";280;2
"Unit";"Hellion";"Factory";280;2
"Unit";"Hellion";"Factory";280;2
"Unit";"Hellion";"Factory";280;2
"Unit";"Hellion";"Factory";280;2
"Unit";"Raven";"Starport";280;2
"Unit";"Raven";"Starport";280;2
"Unit";"Raven";"Starport";280;2
"Unit";"Hellion";"Factory";280;2
"Building";"CommandCenter";NA;280;0
"Building";"MissileTurret";NA;292;0
"Building";"Refinery";NA;305;0
"Building";"Refinery";NA;305;0
"Building";"MissileTurret";NA;305;0
"Building";"MissileTurret";NA;305;0
"Building";"MissileTurret";NA;305;0
"Unit";"Raven";"Starport";305;2
"Building";"SensorTower";NA;307;0
"Building";"MissileTurret";NA;307;0
"Building";"MissileTurret";NA;307;0
"Building";"MissileTurret";NA;307;0
"Building";"CommandCenter";NA;305;0
"Building";"CommandCenter";NA;305;0
"Building";"SensorTower";NA;307;0
"Building";"SensorTower";NA;307;0
"Building";"CommandCenter";NA;305;0
"Building";"MissileTurret";NA;307;0
"Building";"MissileTurret";NA;307;0
"Building";"Refinery";NA;307;0
"Building";"Refinery";NA;307;0
"Building";"MissileTurret";NA;307;0
"Unit";"Liberator";"Starport";307;3
"Unit";"Liberator";"Starport";307;3
"Unit";"Raven";"Starport";307;2
"Unit";"Raven";"Starport";307;2
"Building";"CommandCenter";NA;307;0
"Building";"CommandCenter";NA;307;0
"Building";"MissileTurret";NA;317;0
"Building";"MissileTurret";NA;317;0
"Building";"MissileTurret";NA;317;0
"Building";"MissileTurret";NA;317;0
"Building";"MissileTurret";NA;317;0
"Building";"MissileTurret";NA;317;0
"Building";"MissileTurret";NA;317;0
"Unit";"Raven";"Starport";317;2
"Unit";"Raven";"Starport";317;2
"Unit";"Raven";"Starport";317;2
"Upgrade";"TerranShipWeaponsLevel2";"Armory";317;0
"Building";"MissileTurret";NA;317;0
"Building";"FusionCore";NA;317;0
"Building";"CommandCenter";NA;323;0
"Unit";"Battlecruiser";"Starport";323;6
"Building";"CommandCenter";NA;323;0
"Building";"SensorTower";NA;329;0
"Unit";"Battlecruiser";"Starport";323;6
"Building";"MissileTurret";NA;329;0
