"type";"unit_name";"on_building";"total_supply";"supply"
"Building";"Refinery";NA;15;0
"Building";"Barracks";NA;15;0
"Unit";"Reaper";"Barracks";18;1
"Unit";"Marine";"Barracks";20;1
"Building";"Refinery";NA;20;0
"Unit";"Marine";"Barracks";22;1
"Building";"Factory";NA;21;0
"Unit";"Marine";"Barracks";24;1
"Unit";"Cyclone";"Factory";25;3
"Unit";"Marine";"Barracks";26;1
"Building";"Starport";NA;25;0
"Unit";"Marine";"Barracks";32;1
"Building";"CommandCenter";NA;19;0
"Unit";"Cyclone";"Factory";32;3
"Unit";"Marine";"Barracks";33;1
"Building";"FactoryTechLab";NA;37;0
"Unit";"Marine";"Barracks";37;1
"Unit";"Marine";"Barracks";40;1
"Unit";"Marine";"Barracks";42;1
"Building";"BarracksTechLab";NA;48;0
"Unit";"Liberator";"Starport";47;3
"Unit";"Marine";"Barracks";60;1
"Unit";"Marine";"Barracks";62;1
"Building";"CommandCenter";NA;51;0
"Unit";"Liberator";"Starport";60;3
"Building";"Barracks";NA;62;0
"Building";"Barracks";NA;62;0
"Building";"EngineeringBay";NA;66;0
"Building";"EngineeringBay";NA;66;0
"Unit";"Marine";"Barracks";71;1
"Building";"Barracks";NA;65;0
"Building";"Refinery";NA;72;0
"Building";"Barracks";NA;66;0
"Building";"Refinery";NA;72;0
"Building";"EngineeringBay";NA;72;0
"Unit";"Marine";"Barracks";74;1
"Unit";"Marine";"Barracks";74;1
"Unit";"Marine";"Barracks";74;1
"Unit";"Marine";"Barracks";76;1
"Unit";"Marine";"Barracks";77;1
"Building";"Bunker";NA;75;0
"Unit";"Marine";"Barracks";78;1
"Unit";"Marine";"Barracks";78;1
"Unit";"Marine";"Barracks";78;1
"Unit";"Marine";"Barracks";79;1
"Unit";"Marine";"Barracks";80;1
"Building";"MissileTurret";NA;81;0
"Unit";"Marine";"Barracks";81;1
"Building";"MissileTurret";NA;83;0
"Building";"MissileTurret";NA;84;0
"Upgrade";"Stimpack";"TechLab";69;0
"Unit";"Marine";"Barracks";84;1
"Unit";"Marine";"Barracks";84;1
"Unit";"Marine";"Barracks";86;1
"Unit";"Marine";"Barracks";91;1
"Unit";"Marine";"Barracks";91;1
"Unit";"Marine";"Barracks";91;1
"Unit";"Marine";"Barracks";91;1
"Unit";"Medivac";"Starport";89;2
"Unit";"Marine";"Barracks";91;1
"Unit";"Marine";"Barracks";92;1
"Unit";"Marine";"Barracks";93;1
"Unit";"Marine";"Barracks";94;1
"Unit";"Marine";"Barracks";95;1
"Unit";"Marine";"Barracks";98;1
"Upgrade";"TerranInfantryWeaponsLevel1";"EngineeringBay";79;0
"Upgrade";"TerranInfantryArmorsLevel1";"EngineeringBay";79;0
"Unit";"Marine";"Barracks";99;1
"Unit";"Marine";"Barracks";100;1
"Unit";"Marine";"Barracks";101;1
"Unit";"Marine";"Barracks";103;1
"Unit";"Marine";"Barracks";103;1
"Unit";"Medivac";"Starport";103;2
"Unit";"Marine";"Barracks";107;1
"Unit";"Marine";"Barracks";108;1
"Unit";"Marine";"Barracks";119;1
"Unit";"Marine";"Barracks";119;1
"Unit";"Marine";"Barracks";119;1
"Unit";"Marine";"Barracks";119;1
"Unit";"Marine";"Barracks";119;1
"Building";"MissileTurret";NA;120;0
"Building";"Armory";NA;107;0
"Unit";"Marine";"Barracks";125;1
"Unit";"Marine";"Barracks";133;1
"Unit";"Marine";"Barracks";133;1
"Unit";"Marine";"Barracks";133;1
"Unit";"Marine";"Barracks";133;1
"Unit";"Marine";"Barracks";133;1
"Unit";"Marine";"Barracks";136;1
"Unit";"Marine";"Barracks";137;1
"Unit";"Marine";"Barracks";138;1
"Unit";"Marine";"Barracks";138;1
"Unit";"Marine";"Barracks";140;1
"Unit";"Medivac";"Starport";141;2
"Unit";"Marine";"Barracks";150;1
"Unit";"Marine";"Barracks";150;1
"Unit";"Marine";"Barracks";150;1
"Unit";"Marine";"Barracks";150;1
"Unit";"Marine";"Barracks";150;1
"Building";"MissileTurret";NA;150;0
"Unit";"Marine";"Barracks";155;1
"Unit";"Marine";"Barracks";156;1
"Unit";"Marine";"Barracks";156;1
"Unit";"Marine";"Barracks";156;1
"Unit";"Marine";"Barracks";160;1
"Unit";"Marine";"Barracks";163;1
"Unit";"Medivac";"Starport";163;2
"Unit";"Marine";"Barracks";171;1
"Unit";"Marine";"Barracks";171;1
"Unit";"Marine";"Barracks";171;1
"Unit";"Marine";"Barracks";171;1
"Upgrade";"TerranVehicleWeaponsLevel1";"Armory";141;0
"Building";"Refinery";NA;171;0
"Unit";"Marine";"Barracks";178;1
"Unit";"Marine";"Barracks";180;1
"Unit";"Marine";"Barracks";180;1
"Upgrade";"TerranInfantryWeaponsLevel2";"EngineeringBay";145;0
"Upgrade";"TerranInfantryArmorsLevel2";"EngineeringBay";145;0
"Unit";"Marine";"Barracks";180;1
"Building";"StarportReactor";NA;180;0
"Building";"Factory";NA;171;0
"Building";"BarracksReactor";NA;180;0
"Unit";"Marine";"Barracks";183;1
"Building";"BarracksReactor";NA;183;0
"Building";"BarracksReactor";NA;183;0
"Building";"BarracksReactor";NA;183;0
"Unit";"Marine";"Barracks";185;1
"Unit";"Marine";"Barracks";185;1
"Unit";"Marine";"Barracks";188;1
"Unit";"Marine";"Barracks";188;1
"Unit";"Marine";"Barracks";188;1
"Unit";"Marine";"Barracks";188;1
"Unit";"Marine";"Barracks";188;1
"Unit";"Marine";"Barracks";188;1
"Unit";"Marine";"Barracks";188;1
"Unit";"Marine";"Barracks";188;1
"Unit";"Marine";"Barracks";188;1
"Unit";"Medivac";"Starport";188;2
"Unit";"Medivac";"Starport";188;2
"Unit";"Marine";"Barracks";189;1
"Unit";"Marine";"Barracks";190;1
"Unit";"Marine";"Barracks";191;1
"Unit";"Marine";"Barracks";192;1
"Building";"MissileTurret";NA;196;0
"Building";"Refinery";NA;193;0
"Unit";"Marine";"Barracks";198;1
"Unit";"Marine";"Barracks";199;1
"Building";"FactoryTechLab";NA;200;0
"Unit";"Marine";"Barracks";201;1
"Unit";"Marine";"Barracks";214;1
"Unit";"Marine";"Barracks";214;1
"Unit";"Marine";"Barracks";214;1
"Unit";"Marine";"Barracks";214;1
"Unit";"Marine";"Barracks";214;1
