"Type";"UnitName";"OnBuilding";"TotalSupply";"Supply"
"Unit";"SCV";"Command Center";12;1
"Unit";"SCV";"Command Center";12;1
"Unit";"SCV";"Command Center";13;1
"Building";"SupplyDepot";NA;13;0
"Building";"Refinery";NA;14;0
"Unit";"SCV";"Command Center";15;1
"Unit";"SCV";"Command Center";15;1
"Unit";"SCV";"Command Center";16;1
"Unit";"SCV";"Command Center";18;1
"Building";"Barracks";NA;15;0
"Unit";"Reaper";"Barracks";19;1
"Unit";"SCV";"Command Center";19;1
"Unit";"SCV";"Command Center";20;1
"Building";"Refinery";NA;20;0
"Unit";"SCV";"Command Center";21;1
"Building";"SupplyDepot";NA;21;0
"Building";"Factory";NA;19;0
"Building";"BarracksReactor";NA;20;0
"Building";"CommandCenter";NA;19;0
"Unit";"SCV";"Command Center";23;1
"Unit";"SCV";"Command Center";23;1
"Unit";"Cyclone";"Factory";23;3
"Unit";"SCV";"Command Center";24;1
"Unit";"Cyclone";"Factory";24;3
"Building";"SupplyDepot";NA;24;0
"Unit";"SCV";"Command Center";28;1
"Unit";"SCV";"Command Center";28;1
"Unit";"Cyclone";"Factory";28;3
"Unit";"SCV";"Command Center";34;1
"Unit";"SCV";"Command Center";34;1
"Unit";"SCV";"Command Center";37;1
"Unit";"SCV";"Command Center";38;1
"Unit";"Cyclone";"Factory";37;3
"Unit";"Cyclone";"Factory";37;3
"Unit";"SCV";"Command Center";39;1
"Unit";"SCV";"Command Center";41;1
"Building";"SupplyDepot";NA;39;0
"Unit";"SCV";"Command Center";47;1
"Unit";"SCV";"Command Center";48;1
"Unit";"SCV";"Command Center";49;1
"Unit";"SCV";"Command Center";51;1
"Building";"BarracksTechLab";NA;50;0
"Building";"Barracks";NA;39;0
"Building";"Starport";NA;44;0
"Unit";"SCV";"Command Center";51;1
"Building";"Barracks";NA;41;0
"Building";"FactoryTechLab";NA;52;0
"Building";"Refinery";NA;51;0
"Unit";"SCV";"Command Center";52;1
"Building";"Refinery";NA;51;0
"Building";"CommandCenter";NA;37;0
"Unit";"SCV";"Command Center";53;1
"Unit";"SCV";"Command Center";54;1
"Building";"EngineeringBay";NA;52;0
"Building";"BarracksTechLab";NA;54;0
"Building";"EngineeringBay";NA;53;0
"Unit";"SCV";"Command Center";55;1
"Building";"Barracks";NA;51;0
"Unit";"SCV";"Command Center";56;1
"Building";"StarportReactor";NA;54;0
"Unit";"SCV";"Command Center";58;1
"Unit";"Marine";"Barracks";57;1
"Unit";"Marine";"Barracks";57;1
"Building";"BarracksReactor";NA;55;0
"Unit";"Marine";"Barracks";59;1
"Unit";"Marine";"Barracks";59;1
"Unit";"Marine";"Barracks";60;1
"Unit";"SCV";"Command Center";64;1
"Unit";"SCV";"Command Center";64;1
"Unit";"SCV";"Command Center";64;1
"Unit";"Marine";"Barracks";64;1
"Unit";"Marine";"Barracks";64;1
"Unit";"Marine";"Barracks";64;1
"Unit";"Marine";"Barracks";64;1
"Unit";"Marine";"Barracks";64;1
"Unit";"SCV";"Command Center";65;1
"Unit";"SCV";"Command Center";66;1
"Unit";"SCV";"Command Center";67;1
"Unit";"Marine";"Barracks";68;1
"Unit";"Marine";"Barracks";68;1
"Unit";"SCV";"Command Center";73;1
"Unit";"SCV";"Command Center";76;1
"Unit";"SCV";"Command Center";76;1
"Unit";"Marine";"Barracks";74;1
"Unit";"Marine";"Barracks";75;1
"Unit";"Marine";"Barracks";76;1
"Unit";"Marine";"Barracks";76;1
"Unit";"Medivac";"Starport";68;2
"Unit";"SCV";"Command Center";78;1
"Unit";"SCV";"Command Center";79;1
"Unit";"SCV";"Command Center";81;1
"Unit";"Marine";"Barracks";77;1
"Unit";"Marine";"Barracks";77;1
"Unit";"Marine";"Barracks";81;1
"Unit";"Marine";"Barracks";82;1
"Unit";"SCV";"Command Center";87;1
"Unit";"Marine";"Barracks";85;1
"Unit";"Marine";"Barracks";85;1
"Unit";"SCV";"Command Center";88;1
"Unit";"SCV";"Command Center";89;1
"Upgrade";"Stimpack";"TechLab";59;0
"Unit";"SCV";"Command Center";94;1
"Upgrade";"TerranInfantryWeaponsLevel1";"EngineeringBay";62;0
"Building";"SupplyDepot";NA;92;0
"Upgrade";"TerranInfantryArmorsLevel1";"EngineeringBay";65;0
"Building";"SupplyDepot";NA;99;0
"Unit";"SCV";"Command Center";100;1
"Building";"SupplyDepot";NA;99;0
"Building";"SupplyDepot";NA;100;0
"Unit";"Marine";"Barracks";100;1
"Unit";"Marine";"Barracks";100;1
"Unit";"Marine";"Barracks";100;1
"Unit";"SCV";"Command Center";100;1
"Unit";"SCV";"Command Center";101;1
"Unit";"SCV";"Command Center";101;1
"Unit";"Marine";"Barracks";100;1
"Unit";"Marine";"Barracks";100;1
"Unit";"Marine";"Barracks";100;1
"Unit";"Medivac";"Starport";100;2
"Unit";"Medivac";"Starport";100;2
"Unit";"Marine";"Barracks";101;1
"Unit";"Marine";"Barracks";101;1
"Unit";"Marine";"Barracks";101;1
"Unit";"SCV";"Command Center";104;1
"Unit";"SCV";"Command Center";105;1
"Unit";"SCV";"Command Center";106;1
"Building";"Armory";NA;100;0
"Unit";"Marine";"Barracks";107;1
"Unit";"Marine";"Barracks";107;1
"Unit";"Marine";"Barracks";107;1
"Unit";"SCV";"Command Center";117;1
"Unit";"Marine";"Barracks";114;1
"Unit";"Marine";"Barracks";114;1
"Unit";"SCV";"Command Center";120;1
"Building";"SupplyDepot";NA;114;0
"Unit";"SCV";"Command Center";120;1
"Unit";"SCV";"Command Center";123;1
"Unit";"Marine";"Barracks";120;1
"Unit";"Marine";"Barracks";127;1
"Unit";"Marine";"Barracks";127;1
"Unit";"Marine";"Barracks";127;1
"Building";"Factory";NA;110;0
"Unit";"Medivac";"Starport";128;2
"Unit";"Medivac";"Starport";128;2
"Unit";"Marine";"Barracks";130;1
"Unit";"Marine";"Barracks";130;1
"Unit";"Marine";"Barracks";130;1
"Building";"Barracks";NA;120;0
"Building";"Barracks";NA;120;0
"Unit";"Marine";"Barracks";130;1
"Unit";"Marine";"Barracks";131;1
"Unit";"Marine";"Barracks";142;1
"Unit";"Marine";"Barracks";142;1
"Unit";"Marine";"Barracks";142;1
"Unit";"Marine";"Barracks";142;1
"Unit";"Marine";"Barracks";142;1
"Unit";"Marine";"Barracks";142;1
"Unit";"Marine";"Barracks";142;1
"Unit";"Marine";"Barracks";142;1
"Building";"FactoryTechLab";NA;142;0
"Unit";"SCV";"Command Center";142;1
"Unit";"SCV";"Command Center";142;1
"Unit";"Marine";"Barracks";142;1
"Unit";"Marine";"Barracks";143;1
"Unit";"Marine";"Barracks";144;1
"Unit";"Marine";"Barracks";145;1
"Unit";"Marine";"Barracks";146;1
"Building";"Refinery";NA;145;0
"Building";"Refinery";NA;145;0
"Building";"SupplyDepot";NA;147;0
"Building";"SupplyDepot";NA;147;0
"Unit";"Marine";"Barracks";152;1
"Unit";"Marine";"Barracks";152;1
"Unit";"Marine";"Barracks";152;1
"Unit";"Marine";"Barracks";152;1
"Unit";"Marine";"Barracks";153;1
"Unit";"Marine";"Barracks";154;1
"Unit";"Marauder";"Barracks";155;2
"Unit";"Marauder";"Barracks";156;2
"Unit";"Marine";"Barracks";157;1
"Unit";"Marine";"Barracks";157;1
"Unit";"Marine";"Barracks";159;1
"Unit";"Marine";"Barracks";160;1
"Unit";"Marine";"Barracks";161;1
"Unit";"Marine";"Barracks";162;1
"Unit";"SCV";"Command Center";167;1
"Unit";"Marine";"Barracks";163;1
"Unit";"Marine";"Barracks";165;1
"Unit";"SCV";"Command Center";170;1
"Unit";"Marine";"Barracks";167;1
"Unit";"Marine";"Barracks";167;1
"Unit";"Marine";"Barracks";169;1
"Unit";"Marine";"Barracks";170;1
"Unit";"Marine";"Barracks";171;1
"Unit";"Marine";"Barracks";172;1
"Unit";"Marine";"Barracks";174;1
"Unit";"Marine";"Barracks";175;1
"Unit";"Marine";"Barracks";183;1
"Unit";"Marine";"Barracks";183;1
"Upgrade";"TerranVehicleWeaponsLevel1";"Armory";160;0
"Upgrade";"TerranInfantryWeaponsLevel2";"EngineeringBay";163;0
"Upgrade";"TerranInfantryArmorsLevel2";"EngineeringBay";163;0
"Unit";"SCV";"Command Center";187;1
"Unit";"SCV";"Command Center";187;1
"Unit";"Marine";"Barracks";187;1
"Unit";"SCV";"Command Center";187;1
"Unit";"SCV";"Command Center";188;1
"Unit";"SCV";"Command Center";192;1
"Unit";"SCV";"Command Center";192;1
"Unit";"Marine";"Barracks";192;1
"Unit";"SCV";"Command Center";192;1
"Unit";"Marine";"Barracks";194;1
"Unit";"Marine";"Barracks";196;1
"Unit";"SCV";"Command Center";197;1
"Unit";"SCV";"Command Center";197;1
"Building";"Barracks";NA;192;0
"Building";"Barracks";NA;192;0
"Building";"Barracks";NA;192;0
"Building";"Barracks";NA;194;0
"Unit";"SCV";"Command Center";198;1
"Unit";"SCV";"Command Center";200;1
"Building";"Barracks";NA;196;0
"Unit";"Marine";"Barracks";200;1
"Building";"SupplyDepot";NA;198;0
"Unit";"Marine";"Barracks";200;1
"Unit";"Marine";"Barracks";200;1
"Unit";"Marine";"Barracks";200;1
"Unit";"SCV";"Command Center";200;1
"Building";"SupplyDepot";NA;200;0
"Unit";"Marine";"Barracks";202;1
"Unit";"Marine";"Barracks";202;1
"Unit";"Marine";"Barracks";203;1
"Unit";"Marine";"Barracks";204;1
"Building";"Barracks";NA;197;0
"Unit";"Marine";"Barracks";205;1
"Building";"Barracks";NA;197;0
"Unit";"SCV";"Command Center";207;1
"Unit";"SCV";"Command Center";207;1
"Unit";"SCV";"Command Center";212;1
"Unit";"Marine";"Barracks";207;1
"Unit";"Marine";"Barracks";208;1
"Unit";"Marine";"Barracks";209;1
"Unit";"Marine";"Barracks";210;1
"Unit";"Marine";"Barracks";211;1
"Unit";"Marine";"Barracks";214;1
"Unit";"Marine";"Barracks";215;1
"Unit";"Marine";"Barracks";216;1
"Unit";"Marine";"Barracks";217;1
"Unit";"Marine";"Barracks";218;1
"Unit";"Marine";"Barracks";219;1
"Unit";"SCV";"Command Center";221;1
"Unit";"Marine";"Barracks";221;1
"Unit";"Marine";"Barracks";221;1
"Unit";"Marine";"Barracks";221;1
"Unit";"Marine";"Barracks";223;1
"Unit";"SCV";"Command Center";231;1
"Unit";"SCV";"Command Center";231;1
"Building";"BarracksReactor";NA;226;0
"Building";"BarracksReactor";NA;226;0
"Building";"BarracksReactor";NA;226;0
"Unit";"SCV";"Command Center";231;1
