"Type";"UnitName";"OnBuilding";"TotalSupply";"Supply"
"Unit";"SCV";"Command Center";12;1
"Unit";"SCV";"Command Center";12;1
"Unit";"SCV";"Command Center";13;1
"Building";"SupplyDepot";NA;13;0
"Unit";"SCV";"Command Center";15;1
"Building";"Refinery";NA;14;0
"Unit";"SCV";"Command Center";15;1
"Unit";"SCV";"Command Center";16;1
"Building";"Refinery";NA;16;0
"Unit";"SCV";"Command Center";18;1
"Building";"Barracks";NA;15;0
"Unit";"Reaper";"Barracks";19;1
"Building";"SupplyDepot";NA;19;0
"Building";"Factory";NA;19;0
"Unit";"SCV";"Command Center";20;1
"Unit";"Reaper";"Barracks";19;1
"Unit";"SCV";"Command Center";21;1
"Unit";"Cyclone";"Factory";20;3
"Unit";"SCV";"Command Center";22;1
"Unit";"SCV";"Command Center";26;1
"Unit";"SCV";"Command Center";28;1
"Unit";"Cyclone";"Factory";28;3
"Building";"Bunker";NA;27;0
"Unit";"SCV";"Command Center";32;1
"Building";"SupplyDepot";NA;28;0
"Building";"CommandCenter";NA;22;0
"Building";"BarracksReactor";NA;28;0
"Building";"Starport";NA;28;0
"Unit";"SCV";"Command Center";33;1
"Unit";"Marine";"Barracks";33;1
"Unit";"Marine";"Barracks";33;1
"Unit";"Cyclone";"Factory";33;3
"Unit";"Marine";"Barracks";34;1
"Unit";"Marine";"Barracks";35;1
"Unit";"SCV";"Command Center";36;1
"Unit";"SCV";"Command Center";39;1
"Building";"FactoryTechLab";NA;39;0
"Unit";"SCV";"Command Center";41;1
"Unit";"Marine";"Barracks";42;1
"Unit";"Marine";"Barracks";42;1
"Unit";"SCV";"Command Center";42;1
"Unit";"SCV";"Command Center";43;1
"Unit";"Liberator";"Starport";36;3
"Unit";"SCV";"Command Center";46;1
"Unit";"SCV";"Command Center";47;1
"Unit";"Marine";"Barracks";46;1
"Unit";"Marine";"Barracks";46;1
"Building";"SupplyDepot";NA;48;0
"Unit";"SCV";"Command Center";51;1
"Unit";"SCV";"Command Center";55;1
"Unit";"SCV";"Command Center";56;1
"Unit";"Marine";"Barracks";55;1
"Unit";"Marine";"Barracks";55;1
"Unit";"SCV";"Command Center";56;1
"Unit";"SCV";"Command Center";57;1
"Unit";"Marine";"Barracks";60;1
"Unit";"Marine";"Barracks";60;1
"Unit";"Liberator";"Starport";55;3
"Building";"SupplyDepot";NA;63;0
"Building";"BarracksTechLab";NA;67;0
"Unit";"SCV";"Command Center";67;1
"Unit";"SCV";"Command Center";67;1
"Building";"SupplyDepot";NA;67;0
"Building";"SupplyDepot";NA;67;0
"Building";"EngineeringBay";NA;67;0
"Building";"EngineeringBay";NA;67;0
"Unit";"SCV";"Command Center";69;1
"Unit";"SCV";"Command Center";69;1
"Unit";"Marine";"Barracks";69;1
"Building";"Barracks";NA;67;0
"Building";"StarportReactor";NA;67;0
"Building";"CommandCenter";NA;62;0
"Unit";"SCV";"Command Center";69;1
"Unit";"SCV";"Command Center";70;1
"Building";"Refinery";NA;69;0
"Building";"Refinery";NA;69;0
"Building";"SupplyDepot";NA;69;0
"Building";"SupplyDepot";NA;69;0
"Unit";"SCV";"Command Center";72;1
"Unit";"Marine";"Barracks";74;1
"Unit";"Marine";"Barracks";74;1
"Unit";"SCV";"Command Center";74;1
"Unit";"SCV";"Command Center";74;1
"Unit";"Marauder";"Barracks";74;2
"Unit";"SCV";"Command Center";75;1
"Unit";"SCV";"Command Center";77;1
"Unit";"Medivac";"Starport";74;2
"Unit";"Medivac";"Starport";74;2
"Unit";"SCV";"Command Center";82;1
"Unit";"Marine";"Barracks";79;1
"Unit";"Marine";"Barracks";79;1
"Unit";"SCV";"Command Center";82;1
"Unit";"Marauder";"Barracks";82;2
"Building";"Barracks";NA;74;0
"Building";"Barracks";NA;74;0
"Building";"Barracks";NA;75;0
"Unit";"Marine";"Barracks";88;1
"Building";"SupplyDepot";NA;88;0
"Building";"SupplyDepot";NA;88;0
"Unit";"Marine";"Barracks";93;1
"Building";"BarracksTechLab";NA;93;0
"Unit";"SCV";"Command Center";94;1
"Unit";"SCV";"Command Center";94;1
"Unit";"SCV";"Command Center";94;1
"Unit";"Marauder";"Barracks";93;2
"Building";"BarracksTechLab";NA;94;0
"Unit";"Marine";"Barracks";94;1
"Unit";"Marine";"Barracks";94;1
"Upgrade";"Stimpack";"TechLab";74;0
"Building";"SupplyDepot";NA;95;0
"Unit";"Marine";"Barracks";100;1
"Unit";"Marine";"Barracks";100;1
"Unit";"Marauder";"Barracks";98;2
"Unit";"Marauder";"Barracks";100;2
"Unit";"SCV";"Command Center";102;1
"Building";"StarportReactor";NA;94;0
"Unit";"SCV";"Command Center";102;1
"Unit";"Marauder";"Barracks";100;2
"Unit";"SCV";"Command Center";102;1
"Building";"SupplyDepot";NA;102;0
"Building";"SupplyDepot";NA;102;0
"Building";"SupplyDepot";NA;102;0
"Unit";"SCV";"Command Center";108;1
"Unit";"SCV";"Command Center";109;1
"Building";"Armory";NA;94;0
"Unit";"SCV";"Command Center";112;1
"Unit";"Marine";"Barracks";112;1
"Unit";"Marine";"Barracks";112;1
"Unit";"Marine";"Barracks";112;1
"Unit";"Marauder";"Barracks";112;2
"Unit";"Marauder";"Barracks";112;2
"Unit";"Marauder";"Barracks";113;2
"Upgrade";"TerranInfantryWeaponsLevel1";"EngineeringBay";93;0
"Upgrade";"TerranInfantryArmorsLevel1";"EngineeringBay";93;0
"Unit";"Medivac";"Starport";116;2
"Unit";"Medivac";"Starport";116;2
"Unit";"Marine";"Barracks";125;1
"Unit";"Marine";"Barracks";125;1
"Unit";"Marine";"Barracks";125;1
"Unit";"Marine";"Barracks";125;1
"Unit";"SCV";"Command Center";125;1
"Unit";"SCV";"Command Center";125;1
"Unit";"SCV";"Command Center";127;1
"Unit";"Marauder";"Barracks";125;2
"Unit";"Marauder";"Barracks";125;2
"Unit";"Marauder";"Barracks";125;2
"Building";"Refinery";NA;125;0
"Building";"Refinery";NA;125;0
"Building";"SupplyDepot";NA;129;0
"Unit";"SCV";"Command Center";142;1
"Unit";"SCV";"Command Center";142;1
"Unit";"SCV";"Command Center";142;1
"Unit";"Marine";"Barracks";133;1
"Unit";"Marine";"Barracks";133;1
"Unit";"Marine";"Barracks";133;1
"Unit";"Marine";"Barracks";133;1
"Unit";"Marauder";"Barracks";136;2
"Unit";"SCV";"Command Center";145;1
"Unit";"SCV";"Command Center";145;1
"Unit";"SCV";"Command Center";145;1
"Unit";"Marine";"Barracks";142;1
"Unit";"Marine";"Barracks";142;1
"Building";"SupplyDepot";NA;142;0
"Building";"SupplyDepot";NA;145;0
"Building";"SupplyDepot";NA;145;0
