"type";"unit_name";"on_building";"total_supply";"supply"
"Building";"Refinery";NA;14;0
"Building";"Refinery";NA;14;0
"Building";"Barracks";NA;13;0
"Building";"Factory";NA;16;0
"Building";"BarracksReactor";NA;16;0
"Unit";"Cyclone";"Factory";16;3
"Unit";"Cyclone";"Factory";16;3
"Unit";"Cyclone";"Factory";22;3
"Unit";"Cyclone";"Factory";22;3
"Unit";"Cyclone";"Factory";28;3
"Building";"BarracksTechLab";NA;29;0
