"type";"unit_name";"on_building";"total_supply";"supply"
"Building";"Refinery";NA;14;0
"Building";"Barracks";NA;15;0
"Unit";"Reaper";"Barracks";19;1
"Building";"Factory";NA;19;0
"Building";"Refinery";NA;21;0
"Building";"BarracksReactor";NA;20;0
"Building";"CommandCenter";NA;19;0
"Unit";"Hellion";"Factory";23;2
"Unit";"Hellion";"Factory";23;2
"Building";"BarracksTechLab";NA;24;0
"Building";"Starport";NA;23;0
"Unit";"Hellion";"Factory";25;2
"Unit";"Hellion";"Factory";29;2
"Unit";"Hellion";"Factory";36;2
"Unit";"Cyclone";"Factory";38;3
"Unit";"Raven";"Starport";35;2
"Unit";"Cyclone";"Factory";44;3
"Building";"Refinery";NA;50;0
"Building";"Refinery";NA;50;0
"Unit";"Cyclone";"Factory";55;3
"Unit";"Cyclone";"Factory";55;3
"Building";"CommandCenter";NA;50;0
"Building";"EngineeringBay";NA;58;0
"Unit";"Hellion";"Factory";59;2
"Unit";"Hellion";"Factory";62;2
"Unit";"Raven";"Starport";57;2
"Building";"MissileTurret";NA;75;0
"Unit";"Hellion";"Factory";73;2
"Unit";"Hellion";"Factory";73;2
"Building";"BarracksTechLab";NA;77;0
"Building";"Factory";NA;77;0
"Building";"StarportReactor";NA;77;0
"Building";"Refinery";NA;85;0
"Building";"Factory";NA;77;0
"Building";"Refinery";NA;86;0
"Unit";"Hellion";"Factory";86;2
"Unit";"Hellion";"Factory";86;2
"Building";"MissileTurret";NA;89;0
"Building";"Armory";NA;82;0
"Building";"Armory";NA;83;0
"Unit";"Hellion";"Factory";98;2
"Unit";"Hellion";"Factory";98;2
"Unit";"Hellion";"Factory";103;2
"Unit";"Hellion";"Factory";106;2
"Building";"SensorTower";NA;111;0
"Unit";"Hellion";"Factory";111;2
"Unit";"Hellion";"Factory";112;2
"Building";"Factory";NA;105;0
"Building";"Factory";NA;106;0
"Unit";"Hellion";"Factory";117;2
"Building";"CommandCenter";NA;99;0
"Building";"MissileTurret";NA;122;0
"Building";"MissileTurret";NA;122;0
"Building";"MissileTurret";NA;122;0
"Building";"MissileTurret";NA;122;0
"Building";"FactoryTechLab";NA;123;0
"Upgrade";"TerranVehicleWeaponsLevel1";"Armory";103;0
"Unit";"Hellion";"Factory";123;2
"Unit";"Hellion";"Factory";125;2
"Building";"FactoryReactor";NA;123;0
"Building";"SensorTower";NA;129;0
"Building";"Refinery";NA;129;0
"Building";"Refinery";NA;131;0
"Unit";"Hellion";"Factory";131;2
"Unit";"Hellion";"Factory";131;2
"Unit";"Hellion";"Factory";133;2
"Unit";"Hellion";"Factory";133;2
"Building";"MissileTurret";NA;137;0
"Building";"MissileTurret";NA;137;0
"Building";"MissileTurret";NA;137;0
"Building";"MissileTurret";NA;141;0
"Building";"MissileTurret";NA;141;0
"Building";"MissileTurret";NA;141;0
"Unit";"Thor";"Factory";141;6
"Unit";"Thor";"Factory";141;6
"Unit";"Thor";"Factory";141;6
"Unit";"Thor";"Factory";141;6
"Building";"Starport";NA;147;0
"Building";"Starport";NA;147;0
"Building";"MissileTurret";NA;153;0
"Building";"MissileTurret";NA;153;0
"Upgrade";"TerranVehicleWeaponsLevel2";"Armory";141;0
"Building";"MissileTurret";NA;153;0
"Building";"MissileTurret";NA;153;0
"Building";"MissileTurret";NA;153;0
"Building";"CommandCenter";NA;141;0
"Building";"StarportTechLab";NA;165;0
"Building";"StarportTechLab";NA;165;0
