"type";"unit_name";"on_building";"total_supply";"supply"
"Building";"Refinery";NA;14;0
"Building";"Refinery";NA;16;0
"Building";"Barracks";NA;15;0
"Unit";"Reaper";"Barracks";19;1
"Building";"Factory";NA;19;0
"Building";"Bunker";NA;19;0
"Unit";"Reaper";"Barracks";19;1
"Unit";"Marine";"Barracks";23;1
"Unit";"Hellion";"Factory";24;2
"Unit";"Marine";"Barracks";26;1
"Building";"FactoryTechLab";NA;30;0
"Unit";"Marine";"Barracks";32;1
