"type";"unit_name";"on_building";"total_supply_lag";"supply"
"Building";"Refinery";NA;15;0
"Building";"Barracks";NA;16;0
"Building";"Refinery";NA;17;0
"Building";"Factory";NA;19;0
"Unit";"Reaper";"Barracks";19;1
"Unit";"Reaper";"Barracks";21;1
"Building";"Starport";NA;23;0
"Unit";"Cyclone";"Factory";24;3
"Building";"BarracksTechLab";NA;28;0
"Unit";"Banshee";"Starport";30;3
"Unit";"Hellion";"Factory";33;2
"Unit";"Raven";"Starport";38;2
"Building";"CommandCenter";NA;40;0
"Building";"BarracksReactor";NA;40;0
"Unit";"Cyclone";"Factory";42;3
"Unit";"Banshee";"Starport";46;3
"Building";"FactoryTechLab";NA;51;0
"Unit";"Marine";"Barracks";51;1
"Unit";"Marine";"Barracks";52;1
"Building";"CommandCenter";NA;54;0
"Building";"Barracks";NA;55;0
"Building";"Barracks";NA;55;0
"Unit";"Marine";"Barracks";55;1
"Unit";"Marine";"Barracks";57;1
"Upgrade";"Stimpack";"TechLab";60;0
"Building";"BarracksReactor";NA;60;0
"Building";"StarportReactor";NA;60;0
"Unit";"Marine";"Barracks";62;1
"Unit";"Marine";"Barracks";63;1
"Unit";"Marine";"Barracks";64;1
"Building";"EngineeringBay";NA;66;0
"Unit";"Marine";"Barracks";68;1
"Unit";"Marine";"Barracks";69;1
"Unit";"Marine";"Barracks";70;1
"Unit";"Marine";"Barracks";73;1
"Unit";"Marine";"Barracks";74;1
"Unit";"Medivac";"Starport";75;2
"Unit";"Medivac";"Starport";79;2
"Unit";"Marine";"Barracks";81;1
"Unit";"Marine";"Barracks";82;1
"Unit";"Marine";"Barracks";83;1
"Unit";"Marine";"Barracks";84;1
"Unit";"Marine";"Barracks";85;1
"Building";"Refinery";NA;88;0
"Building";"Refinery";NA;88;0
"Unit";"Marine";"Barracks";88;1
"Unit";"Marine";"Barracks";89;1
"Unit";"Marine";"Barracks";90;1
"Unit";"Marauder";"Barracks";92;2
"Unit";"Marine";"Barracks";95;1
"Unit";"Marine";"Barracks";97;1
"Unit";"Marine";"Barracks";98;1
"Unit";"Marine";"Barracks";99;1
"Upgrade";"TerranInfantryWeaponsLevel1";"EngineeringBay";100;0
"Unit";"Marine";"Barracks";105;1
"Unit";"Marine";"Barracks";106;1
"Unit";"Marine";"Barracks";107;1
"Unit";"Marine";"Barracks";108;1
"Unit";"Marine";"Barracks";109;1
"Unit";"Marine";"Barracks";113;1
"Unit";"Marine";"Barracks";114;1
"Unit";"Marine";"Barracks";115;1
"Unit";"Medivac";"Starport";116;2
"Unit";"Medivac";"Starport";118;2
"Building";"Barracks";NA;121;0
"Building";"Barracks";NA;121;0
"Unit";"Marine";"Barracks";123;1
"Building";"Refinery";NA;127;0
"Building";"Refinery";NA;127;0
"Building";"Factory";NA;127;0
"Unit";"Marine";"Barracks";127;1
"Unit";"Marine";"Barracks";128;1
"Unit";"Marine";"Barracks";129;1
"Unit";"Medivac";"Starport";130;2
"Unit";"Marine";"Barracks";132;1
"Unit";"Medivac";"Starport";133;2
"Unit";"Marine";"Barracks";135;1
"Unit";"Marine";"Barracks";136;1
"Unit";"Marine";"Barracks";137;1
"Unit";"Marine";"Barracks";138;1
"Unit";"Marine";"Barracks";139;1
"Unit";"Marine";"Barracks";140;1
"Unit";"Marine";"Barracks";141;1
"Unit";"Marine";"Barracks";142;1
"Unit";"Marine";"Barracks";143;1
"Unit";"Marine";"Barracks";144;1
"Unit";"Marine";"Barracks";145;1
"Unit";"Marine";"Barracks";146;1
"Unit";"Medivac";"Starport";147;2
"Unit";"Medivac";"Starport";149;2
"Building";"BarracksReactor";NA;151;0
"Unit";"Marine";"Barracks";151;1
"Building";"BarracksReactor";NA;153;0
"Unit";"Marine";"Barracks";155;1
"Unit";"Marine";"Barracks";156;1
"Unit";"Marine";"Barracks";157;1
"Unit";"Marine";"Barracks";158;1
"Unit";"Marine";"Barracks";161;1
"Unit";"Marine";"Barracks";162;1
"Unit";"Marine";"Barracks";163;1
"Unit";"Marine";"Barracks";164;1
"Unit";"Marine";"Barracks";165;1
"Unit";"Medivac";"Starport";166;2
"Unit";"Medivac";"Starport";168;2
"Building";"FactoryTechLab";NA;170;0
"Unit";"Marine";"Barracks";170;1
"Building";"MissileTurret";NA;171;0
"Unit";"Marine";"Barracks";171;1
"Unit";"Marine";"Barracks";172;1
"Unit";"Marine";"Barracks";173;1
"Unit";"Marine";"Barracks";174;1
"Unit";"Marine";"Barracks";175;1
"Unit";"Marine";"Barracks";176;1
"Unit";"Marine";"Barracks";177;1
"Unit";"Marine";"Barracks";178;1
"Unit";"Marine";"Barracks";179;1
"Unit";"Marine";"Barracks";180;1
"Unit";"Marine";"Barracks";181;1
"Unit";"Marine";"Barracks";182;1
"Unit";"Marine";"Barracks";183;1
"Unit";"Marine";"Barracks";184;1
"Unit";"Marine";"Barracks";185;1
"Building";"MissileTurret";NA;186;0
"Unit";"Marine";"Barracks";186;1
"Unit";"Marine";"Barracks";187;1
"Unit";"Marine";"Barracks";188;1
"Building";"Armory";NA;192;0
"Building";"EngineeringBay";NA;192;0
"Unit";"Marine";"Barracks";192;1
"Unit";"Marine";"Barracks";193;1
"Unit";"Marine";"Barracks";197;1
"Unit";"Marine";"Barracks";201;1
"Unit";"Marine";"Barracks";202;1
"Unit";"Marine";"Barracks";203;1
"Unit";"Marine";"Barracks";205;1
"Unit";"Marine";"Barracks";206;1
"Unit";"Marine";"Barracks";207;1
"Unit";"Marine";"Barracks";208;1
"Unit";"Marine";"Barracks";209;1
"Unit";"Marine";"Barracks";210;1
"Unit";"Marine";"Barracks";211;1
"Unit";"Marine";"Barracks";212;1
"Unit";"Marine";"Barracks";213;1
"Unit";"Marine";"Barracks";214;1
"Unit";"Marine";"Barracks";215;1
"Unit";"Marine";"Barracks";216;1
"Unit";"Marine";"Barracks";217;1
"Unit";"Marine";"Barracks";218;1
"Unit";"Marine";"Barracks";219;1
"Upgrade";"TerranInfantryWeaponsLevel2";"EngineeringBay";220;0
"Unit";"Marine";"Barracks";220;1
"Unit";"Marine";"Barracks";221;1
"Unit";"Marine";"Barracks";222;1
"Unit";"Marine";"Barracks";223;1
"Unit";"Marine";"Barracks";224;1
"Unit";"Marine";"Barracks";225;1
"Unit";"Marine";"Barracks";226;1
"Unit";"Marine";"Barracks";227;1
"Unit";"Medivac";"Starport";228;2
"Unit";"Medivac";"Starport";230;2
"Unit";"Marine";"Barracks";232;1
"Unit";"Marine";"Barracks";233;1
"Unit";"Marine";"Barracks";234;1
"Unit";"Marine";"Barracks";235;1
"Unit";"Marine";"Barracks";236;1
"Unit";"Marine";"Barracks";237;1
"Unit";"Marine";"Barracks";238;1
"Unit";"Marine";"Barracks";239;1
"Unit";"Marine";"Barracks";240;1
"Unit";"Medivac";"Starport";241;2
"Unit";"Medivac";"Starport";243;2
"Building";"CommandCenter";NA;245;0
"Unit";"Medivac";"Starport";245;2
"Unit";"Medivac";"Starport";247;2
"Unit";"Marine";"Barracks";249;1
"Unit";"Marine";"Barracks";250;1
"Unit";"Marine";"Barracks";251;1
"Unit";"Marine";"Barracks";252;1
"Unit";"Marine";"Barracks";253;1
"Unit";"Marine";"Barracks";254;1
"Unit";"Marine";"Barracks";255;1
"Unit";"Marine";"Barracks";256;1
"Unit";"Marine";"Barracks";257;1
"Unit";"Marine";"Barracks";258;1
"Unit";"Marine";"Barracks";259;1
"Unit";"Marine";"Barracks";260;1
"Unit";"Marine";"Barracks";261;1
"Unit";"Marine";"Barracks";262;1
"Unit";"Marine";"Barracks";263;1
"Unit";"Marine";"Barracks";264;1
"Unit";"Marine";"Barracks";265;1
"Unit";"Marine";"Barracks";266;1
"Unit";"Marine";"Barracks";267;1
"Unit";"Marine";"Barracks";268;1
"Unit";"Marine";"Barracks";269;1
"Unit";"Marine";"Barracks";270;1
"Unit";"Marine";"Barracks";271;1
"Unit";"Marine";"Barracks";272;1
"Unit";"Marine";"Barracks";273;1
"Unit";"Marine";"Barracks";274;1
"Unit";"Marine";"Barracks";275;1
"Unit";"Marine";"Barracks";276;1
"Unit";"Medivac";"Starport";279;2
"Unit";"Medivac";"Starport";281;2
"Unit";"Marine";"Barracks";285;1
"Building";"Refinery";NA;286;0
"Unit";"Marine";"Barracks";286;1
"Unit";"Marine";"Barracks";287;1
"Unit";"Marine";"Barracks";288;1
"Unit";"Marine";"Barracks";289;1
"Unit";"Marine";"Barracks";290;1
"Unit";"Marine";"Barracks";291;1
"Unit";"Marine";"Barracks";292;1
"Upgrade";"SprayTerran";NA;293;0
"Upgrade";"BansheeCloak";NA;293;0
"Upgrade";"SprayTerran";NA;293;0
"Upgrade";"SprayTerran";NA;293;0
"Upgrade";"SprayTerran";NA;293;0
"Upgrade";"ShieldWall";NA;293;0
"Upgrade";"TerranInfantryArmorsLevel1";NA;293;0
"Upgrade";"SprayTerran";NA;293;0
"Upgrade";"TerranInfantryArmorsLevel2";NA;293;0
"Upgrade";"SprayTerran";NA;293;0
