"type";"unit_name";"on_building";"total_supply";"supply"
"Building";"Refinery";NA;14;0
"Building";"Barracks";NA;15;0
"Unit";"Reaper";"Barracks";19;1
"Building";"Refinery";NA;20;0
"Unit";"Reaper";"Barracks";20;1
"Building";"Factory";NA;19;0
"Building";"CommandCenter";NA;19;0
"Unit";"Hellion";"Factory";24;2
"Building";"BarracksReactor";NA;23;0
"Building";"Starport";NA;24;0
"Unit";"Marine";"Barracks";28;1
"Unit";"Marine";"Barracks";28;1
"Unit";"Marine";"Barracks";31;1
"Unit";"Marine";"Barracks";31;1
"Unit";"Cyclone";"Factory";29;3
"Unit";"Medivac";"Starport";29;2
"Unit";"Marine";"Barracks";34;1
"Unit";"Marine";"Barracks";35;1
"Building";"FactoryTechLab";NA;39;0
"Unit";"Marine";"Barracks";43;1
"Unit";"Marine";"Barracks";44;1
"Building";"EngineeringBay";NA;45;0
"Building";"Bunker";NA;45;0
"Unit";"Marine";"Barracks";47;1
"Unit";"Marine";"Barracks";48;1
"Building";"StarportReactor";NA;51;0
"Building";"BarracksTechLab";NA;53;0
"Building";"Refinery";NA;53;0
"Building";"Barracks";NA;51;0
"Building";"Barracks";NA;53;0
"Unit";"Marine";"Barracks";58;1
"Unit";"Marine";"Barracks";60;1
"Unit";"Marine";"Barracks";60;1
"Unit";"Marine";"Barracks";60;1
"Unit";"Marine";"Barracks";60;1
"Building";"StarportReactor";NA;60;0
"Building";"Barracks";NA;60;0
"Unit";"Marine";"Barracks";67;1
"Unit";"Marine";"Barracks";67;1
"Unit";"Marine";"Barracks";67;1
"Unit";"Marine";"Barracks";67;1
"Unit";"Marine";"Barracks";67;1
"Building";"Barracks";NA;60;0
"Building";"CommandCenter";NA;58;0
"Building";"Refinery";NA;67;0
"Unit";"Medivac";"Starport";67;2
"Unit";"Medivac";"Starport";67;2
"Upgrade";"TerranInfantryWeaponsLevel1";"EngineeringBay";58;0
"Building";"BarracksTechLab";NA;74;0
"Unit";"Marine";"Barracks";74;1
"Unit";"Marine";"Barracks";74;1
"Unit";"Marine";"Barracks";74;1
"Unit";"Marine";"Barracks";74;1
"Building";"BarracksTechLab";NA;74;0
"Unit";"Marauder";"Barracks";80;2
"Unit";"Marine";"Barracks";85;1
"Unit";"Marine";"Barracks";85;1
"Building";"Factory";NA;74;0
"Unit";"Marine";"Barracks";86;1
"Unit";"Marauder";"Barracks";86;2
"Unit";"Marine";"Barracks";87;1
"Upgrade";"Stimpack";"TechLab";63;0
"Unit";"Marine";"Barracks";87;1
"Unit";"Marauder";"Barracks";87;2
"Unit";"Marine";"Barracks";94;1
"Unit";"Marine";"Barracks";94;1
"Unit";"Marine";"Barracks";94;1
"Building";"FactoryTechLab";NA;94;0
"Unit";"Marine";"Barracks";100;1
"Unit";"Marine";"Barracks";100;1
"Unit";"Marine";"Barracks";108;1
"Unit";"Marine";"Barracks";108;1
"Unit";"Marine";"Barracks";108;1
"Unit";"Marine";"Barracks";108;1
"Unit";"Marauder";"Barracks";108;2
"Unit";"Marauder";"Barracks";108;2
"Unit";"Marauder";"Barracks";110;2
"Unit";"Medivac";"Starport";110;2
"Unit";"Medivac";"Starport";110;2
"Unit";"Marine";"Barracks";113;1
"Unit";"Marine";"Barracks";114;1
"Unit";"Marine";"Barracks";115;1
"Unit";"Marine";"Barracks";116;1
"Unit";"Marauder";"Barracks";125;2
"Building";"EngineeringBay";NA;125;0
"Unit";"Marine";"Barracks";135;1
"Unit";"Marine";"Barracks";135;1
"Unit";"Marauder";"Barracks";135;2
"Unit";"Marine";"Barracks";135;1
"Unit";"Marine";"Barracks";135;1
"Unit";"Marine";"Barracks";135;1
"Building";"Refinery";NA;135;0
"Building";"Refinery";NA;135;0
"Unit";"Marine";"Barracks";135;1
"Unit";"Marine";"Barracks";137;1
"Building";"Armory";NA;125;0
"Unit";"Marauder";"Barracks";139;2
"Unit";"Marine";"Barracks";143;1
"Unit";"Marine";"Barracks";143;1
"Unit";"Marauder";"Barracks";143;2
"Unit";"Marauder";"Barracks";144;2
"Unit";"Marine";"Barracks";146;1
"Unit";"Medivac";"Starport";145;2
"Unit";"Marine";"Barracks";150;1
"Unit";"Marine";"Barracks";150;1
"Unit";"Marine";"Barracks";150;1
"Unit";"Marine";"Barracks";153;1
"Unit";"Marine";"Barracks";155;1
"Unit";"Marauder";"Barracks";153;2
"Unit";"Marine";"Barracks";155;1
"Unit";"Marine";"Barracks";158;1
"Unit";"Marine";"Barracks";159;1
"Upgrade";"TerranInfantryArmorsLevel1";"EngineeringBay";135;0
"Unit";"Medivac";"Starport";155;2
"Unit";"Marauder";"Barracks";161;2
"Unit";"Marauder";"Barracks";162;2
"Unit";"Medivac";"Starport";156;2
"Unit";"Marine";"Barracks";174;1
"Unit";"Marine";"Barracks";174;1
"Unit";"Marine";"Barracks";179;1
"Unit";"Medivac";"Starport";178;2
"Unit";"Marine";"Barracks";179;1
"Unit";"Marauder";"Barracks";179;2
"Unit";"Marine";"Barracks";181;1
"Unit";"Marauder";"Barracks";181;2
"Unit";"Medivac";"Starport";179;2
"Unit";"Marine";"Barracks";185;1
"Unit";"Marine";"Barracks";187;1
"Unit";"Marine";"Barracks";187;1
"Unit";"Marauder";"Barracks";187;2
"Unit";"Marauder";"Barracks";187;2
"Building";"Starport";NA;182;0
"Building";"SensorTower";NA;190;0
"Unit";"Marine";"Barracks";190;1
"Building";"Starport";NA;182;0
"Unit";"Marine";"Barracks";192;1
"Building";"CommandCenter";NA;170;0
"Unit";"Marine";"Barracks";195;1
"Unit";"Marine";"Barracks";195;1
"Unit";"Marine";"Barracks";197;1
"Unit";"Marauder";"Barracks";195;2
"Unit";"Marauder";"Barracks";197;2
"Unit";"Marine";"Barracks";200;1
"Unit";"Marauder";"Barracks";201;2
"Building";"Refinery";NA;211;0
"Building";"Refinery";NA;211;0
"Building";"CommandCenter";NA;190;0
"Building";"StarportReactor";NA;209;0
"Building";"StarportReactor";NA;209;0
"Upgrade";"TerranInfantryWeaponsLevel2";"EngineeringBay";181;0
"Unit";"Marine";"Barracks";211;1
"Building";"Starport";NA;211;0
"Building";"Starport";NA;211;0
"Building";"Starport";NA;211;0
"Unit";"Marine";"Barracks";212;1
"Unit";"Marauder";"Barracks";212;2
"Unit";"Marine";"Barracks";212;1
"Unit";"Marine";"Barracks";212;1
"Unit";"Marine";"Barracks";212;1
"Unit";"Marauder";"Barracks";212;2
"Unit";"Marauder";"Barracks";212;2
"Unit";"Marine";"Barracks";222;1
"Unit";"Marine";"Barracks";222;1
"Unit";"Marine";"Barracks";222;1
"Unit";"Marine";"Barracks";222;1
"Unit";"Marine";"Barracks";222;1
"Upgrade";"TerranVehicleWeaponsLevel1";"Armory";211;0
"Unit";"Marauder";"Barracks";222;2
"Unit";"Marauder";"Barracks";222;2
"Unit";"Marine";"Barracks";222;1
"Unit";"Marauder";"Barracks";229;2
"Upgrade";"TerranInfantryArmorsLevel2";"EngineeringBay";211;0
"Unit";"Marine";"Barracks";235;1
"Unit";"Marine";"Barracks";235;1
"Unit";"Marine";"Barracks";235;1
"Unit";"Marine";"Barracks";235;1
"Unit";"Marine";"Barracks";235;1
"Building";"FusionCore";NA;223;0
"Building";"StarportTechLab";NA;237;0
"Unit";"Liberator";"Starport";234;3
"Unit";"Liberator";"Starport";234;3
"Unit";"Liberator";"Starport";234;3
"Unit";"Liberator";"Starport";234;3
"Unit";"Marine";"Barracks";245;1
"Unit";"Liberator";"Starport";245;3
"Unit";"Liberator";"Starport";245;3
"Unit";"Marine";"Barracks";264;1
"Unit";"Marine";"Barracks";264;1
"Unit";"Liberator";"Starport";257;3
"Unit";"Liberator";"Starport";257;3
