"Type";"UnitName";"OnBuilding";"TotalSupply";"Supply"
"Unit";"SCV";"Command Center";12;1
"Unit";"SCV";"Command Center";12;1
"Unit";"SCV";"Command Center";13;1
"Building";"SupplyDepot";NA;13;0
"Building";"Refinery";NA;14;0
"Unit";"SCV";"Command Center";15;1
"Unit";"SCV";"Command Center";15;1
"Unit";"SCV";"Command Center";16;1
"Unit";"SCV";"Command Center";17;1
"Building";"Barracks";NA;15;0
"Unit";"Reaper";"Barracks";19;1
"Unit";"SCV";"Command Center";19;1
"Unit";"SCV";"Command Center";21;1
"Building";"SupplyDepot";NA;20;0
"Building";"Refinery";NA;21;0
"Building";"Factory";NA;19;0
"Unit";"SCV";"Command Center";22;1
"Unit";"Reaper";"Barracks";20;1
"Unit";"SCV";"Command Center";22;1
"Building";"CommandCenter";NA;19;0
"Unit";"Hellion";"Factory";22;2
"Unit";"SCV";"Command Center";25;1
"Building";"Starport";NA;24;0
"Unit";"SCV";"Command Center";28;1
"Building";"BarracksReactor";NA;27;0
"Unit";"Cyclone";"Factory";28;3
"Unit";"SCV";"Command Center";29;1
"Unit";"Marine";"Barracks";29;1
"Unit";"Marine";"Barracks";29;1
"Unit";"SCV";"Command Center";32;1
"Unit";"SCV";"Command Center";36;1
"Unit";"SCV";"Command Center";36;1
"Unit";"Marine";"Barracks";36;1
"Unit";"Marine";"Barracks";36;1
"Unit";"SCV";"Command Center";36;1
"Unit";"SCV";"Command Center";37;1
"Unit";"Cyclone";"Factory";36;3
"Unit";"Marine";"Barracks";40;1
"Unit";"Marine";"Barracks";40;1
"Unit";"Liberator";"Starport";36;3
"Building";"CommandCenter";NA;33;0
"Building";"SupplyDepot";NA;50;0
"Building";"SupplyDepot";NA;50;0
"Building";"SupplyDepot";NA;50;0
"Building";"FactoryTechLab";NA;50;0
"Unit";"SCV";"Command Center";50;1
"Unit";"SCV";"Command Center";50;1
"Building";"BarracksTechLab";NA;50;0
"Building";"EngineeringBay";NA;50;0
"Unit";"SCV";"Command Center";50;1
"Unit";"SCV";"Command Center";52;1
"Building";"StarportReactor";NA;50;0
"Building";"Barracks";NA;50;0
"Building";"Barracks";NA;50;0
"Building";"SupplyDepot";NA;52;0
"Unit";"SCV";"Command Center";52;1
"Building";"SupplyDepot";NA;52;0
"Unit";"Marine";"Barracks";52;1
"Unit";"SCV";"Command Center";55;1
"Unit";"SCV";"Command Center";55;1
"Unit";"SCV";"Command Center";55;1
"Unit";"Marine";"Barracks";55;1
"Building";"SupplyDepot";NA;56;0
"Building";"MissileTurret";NA;56;0
"Building";"MissileTurret";NA;56;0
"Building";"SupplyDepot";NA;56;0
"Building";"MissileTurret";NA;59;0
"Unit";"SCV";"Command Center";59;1
"Unit";"SCV";"Command Center";59;1
"Unit";"Marine";"Barracks";59;1
"Unit";"Marine";"Barracks";59;1
"Unit";"Marine";"Barracks";59;1
"Unit";"Marine";"Barracks";59;1
"Unit";"SCV";"Command Center";60;1
"Building";"StarportReactor";NA;56;0
"Building";"Refinery";NA;60;0
"Building";"Refinery";NA;60;0
"Building";"SensorTower";NA;60;0
"Unit";"Marine";"Barracks";67;1
"Unit";"Marine";"Barracks";67;1
"Unit";"Marine";"Barracks";67;1
"Unit";"Marine";"Barracks";67;1
"Unit";"Marine";"Barracks";67;1
"Unit";"SCV";"Command Center";67;1
"Unit";"SCV";"Command Center";67;1
"Unit";"SCV";"Command Center";67;1
"Unit";"Marine";"Barracks";67;1
"Unit";"Marine";"Barracks";68;1
"Unit";"SCV";"Command Center";72;1
"Unit";"SCV";"Command Center";73;1
"Unit";"Marine";"Barracks";72;1
"Unit";"Marine";"Barracks";72;1
"Unit";"Marine";"Barracks";72;1
"Unit";"Marine";"Barracks";75;1
"Building";"SupplyDepot";NA;75;0
"Unit";"SCV";"Command Center";79;1
"Unit";"Medivac";"Starport";72;2
"Unit";"SCV";"Command Center";82;1
"Unit";"Marine";"Barracks";77;1
"Unit";"SCV";"Command Center";82;1
"Unit";"Marine";"Barracks";79;1
"Unit";"Marine";"Barracks";80;1
"Unit";"SCV";"Command Center";91;1
"Building";"EngineeringBay";NA;83;0
"Unit";"SCV";"Command Center";91;1
"Unit";"SCV";"Command Center";91;1
"Unit";"Marine";"Barracks";91;1
"Unit";"Marine";"Barracks";91;1
"Unit";"Marine";"Barracks";91;1
"Unit";"Marine";"Barracks";91;1
"Unit";"Marine";"Barracks";91;1
"Upgrade";"Stimpack";"TechLab";67;0
"Unit";"SCV";"Command Center";91;1
"Unit";"Marine";"Barracks";94;1
"Unit";"Marine";"Barracks";95;1
"Unit";"SCV";"Command Center";99;1
"Unit";"SCV";"Command Center";99;1
"Building";"Armory";NA;83;0
"Building";"Barracks";NA;84;0
"Unit";"SCV";"Command Center";99;1
"Unit";"Marine";"Barracks";99;1
"Unit";"Marine";"Barracks";99;1
"Unit";"Marine";"Barracks";99;1
"Building";"Barracks";NA;89;0
"Upgrade";"TerranInfantryWeaponsLevel1";"EngineeringBay";72;0
"Unit";"SCV";"Command Center";105;1
"Building";"SensorTower";NA;104;0
"Unit";"Marine";"Barracks";104;1
"Unit";"Marine";"Barracks";104;1
"Unit";"Marine";"Barracks";104;1
"Unit";"Marine";"Barracks";105;1
"Unit";"Marine";"Barracks";113;1
"Unit";"Marine";"Barracks";113;1
"Unit";"Marine";"Barracks";113;1
"Unit";"SCV";"Command Center";113;1
"Unit";"SCV";"Command Center";113;1
"Unit";"Marine";"Barracks";113;1
"Unit";"Marine";"Barracks";113;1
"Building";"Refinery";NA;113;0
"Building";"Refinery";NA;113;0
"Building";"SensorTower";NA;113;0
"Building";"BarracksReactor";NA;113;0
"Building";"BarracksReactor";NA;113;0
"Unit";"SCV";"Command Center";120;1
"Building";"SupplyDepot";NA;120;0
"Building";"SupplyDepot";NA;120;0
"Unit";"Marine";"Barracks";120;1
"Unit";"Marine";"Barracks";120;1
"Building";"SupplyDepot";NA;120;0
"Unit";"SCV";"Command Center";121;1
"Building";"Factory";NA;113;0
"Unit";"Marine";"Barracks";120;1
"Unit";"Marine";"Barracks";120;1
"Unit";"Marine";"Barracks";120;1
"Unit";"Marine";"Barracks";121;1
"Building";"MissileTurret";NA;121;0
"Building";"MissileTurret";NA;121;0
"Unit";"SCV";"Command Center";123;1
"Unit";"Marine";"Barracks";123;1
"Unit";"SCV";"Command Center";129;1
"Unit";"SCV";"Command Center";129;1
"Building";"FactoryTechLab";NA;128;0
"Unit";"Medivac";"Starport";123;2
"Unit";"Medivac";"Starport";123;2
"Unit";"Marine";"Barracks";128;1
"Unit";"Marine";"Barracks";128;1
"Unit";"Marine";"Barracks";128;1
"Unit";"Marine";"Barracks";129;1
"Unit";"Marine";"Barracks";129;1
"Unit";"Marine";"Barracks";129;1
"Unit";"Marine";"Barracks";129;1
"Upgrade";"TerranInfantryArmorsLevel1";"EngineeringBay";113;0
"Building";"CommandCenter";NA;116;0
"Unit";"Marine";"Barracks";130;1
"Unit";"Marine";"Barracks";130;1
"Unit";"Marine";"Barracks";136;1
"Unit";"SCV";"Command Center";143;1
"Unit";"Marine";"Barracks";143;1
"Unit";"Marine";"Barracks";143;1
"Unit";"Marine";"Barracks";143;1
"Unit";"Marine";"Barracks";143;1
"Unit";"Marine";"Barracks";143;1
"Unit";"SCV";"Command Center";143;1
"Unit";"Medivac";"Starport";132;2
"Unit";"Medivac";"Starport";134;2
"Unit";"Marine";"Barracks";145;1
"Unit";"Marine";"Barracks";145;1
"Unit";"Marine";"Barracks";145;1
"Building";"MissileTurret";NA;145;0
"Building";"MissileTurret";NA;145;0
"Unit";"Marine";"Barracks";145;1
"Unit";"SCV";"Command Center";157;1
"Unit";"Marine";"Barracks";147;1
"Unit";"Marine";"Barracks";148;1
"Unit";"Marine";"Barracks";149;1
"Unit";"Marine";"Barracks";150;1
"Building";"MissileTurret";NA;157;0
"Unit";"Marine";"Barracks";166;1
"Unit";"Marine";"Barracks";166;1
"Unit";"Marine";"Barracks";166;1
"Unit";"Marine";"Barracks";166;1
"Unit";"Marine";"Barracks";166;1
"Unit";"Marine";"Barracks";166;1
"Unit";"Marine";"Barracks";166;1
"Unit";"Marine";"Barracks";166;1
"Upgrade";"TerranInfantryWeaponsLevel2";"EngineeringBay";130;0
"Unit";"Marine";"Barracks";169;1
"Unit";"Marine";"Barracks";169;1
"Unit";"Marine";"Barracks";174;1
"Unit";"Marine";"Barracks";174;1
"Unit";"Marine";"Barracks";174;1
"Upgrade";"TerranVehicleWeaponsLevel1";"Armory";152;0
"Unit";"Marine";"Barracks";176;1
"Unit";"Marine";"Barracks";176;1
"Unit";"Marine";"Barracks";176;1
"Unit";"Marine";"Barracks";179;1
"Unit";"Marine";"Barracks";179;1
"Unit";"Marine";"Barracks";179;1
"Building";"Barracks";NA;169;0
"Building";"Barracks";NA;169;0
"Unit";"Marine";"Barracks";179;1
"Unit";"Marine";"Barracks";179;1
"Building";"Refinery";NA;182;0
"Building";"Refinery";NA;182;0
"Unit";"Marine";"Barracks";187;1
"Unit";"Marine";"Barracks";187;1
"Unit";"Marine";"Barracks";187;1
"Unit";"Marine";"Barracks";187;1
"Unit";"Marine";"Barracks";191;1
"Unit";"Marine";"Barracks";191;1
"Unit";"Marine";"Barracks";191;1
"Unit";"Marine";"Barracks";191;1
"Unit";"Marine";"Barracks";191;1
"Unit";"Marine";"Barracks";191;1
"Unit";"Marine";"Barracks";191;1
"Unit";"Marine";"Barracks";191;1
"Unit";"Marine";"Barracks";191;1
"Unit";"Marine";"Barracks";191;1
"Building";"BarracksReactor";NA;191;0
"Building";"BarracksReactor";NA;191;0
"Unit";"Marine";"Barracks";197;1
"Unit";"Marine";"Barracks";197;1
"Unit";"Medivac";"Starport";191;2
"Unit";"Medivac";"Starport";191;2
"Building";"CommandCenter";NA;182;0
"Unit";"Marine";"Barracks";200;1
"Unit";"Marine";"Barracks";200;1
"Unit";"Marine";"Barracks";200;1
"Building";"Factory";NA;191;0
"Unit";"Marine";"Barracks";203;1
"Unit";"Marine";"Barracks";203;1
"Unit";"Marine";"Barracks";203;1
"Unit";"Marine";"Barracks";207;1
"Unit";"Marine";"Barracks";207;1
"Unit";"Marine";"Barracks";207;1
"Unit";"Marine";"Barracks";214;1
"Unit";"Marine";"Barracks";215;1
"Unit";"Marine";"Barracks";216;1
"Unit";"Marine";"Barracks";216;1
"Unit";"Marine";"Barracks";216;1
"Unit";"Marine";"Barracks";216;1
"Unit";"Marine";"Barracks";216;1
"Unit";"Marine";"Barracks";216;1
"Unit";"Marine";"Barracks";216;1
"Unit";"Marine";"Barracks";216;1
"Unit";"Marine";"Barracks";216;1
"Unit";"Marine";"Barracks";216;1
"Unit";"Marine";"Barracks";216;1
"Unit";"SCV";"Command Center";216;1
"Unit";"SCV";"Command Center";216;1
"Unit";"SCV";"Command Center";216;1
"Building";"FactoryTechLab";NA;216;0
"Unit";"Marine";"Barracks";216;1
"Unit";"Marine";"Barracks";217;1
"Unit";"Marine";"Barracks";218;1
"Unit";"Marine";"Barracks";219;1
"Unit";"Marine";"Barracks";220;1
"Unit";"Marine";"Barracks";221;1
"Unit";"Marine";"Barracks";222;1
"Unit";"Marine";"Barracks";223;1
"Unit";"Marine";"Barracks";224;1
"Unit";"Marine";"Barracks";225;1
"Unit";"Marine";"Barracks";226;1
"Unit";"Marine";"Barracks";227;1
"Unit";"Marine";"Barracks";228;1
"Upgrade";"TerranInfantryArmorsLevel2";"EngineeringBay";191;0
"Upgrade";"TerranVehicleWeaponsLevel2";"Armory";191;0
"Unit";"Marine";"Barracks";232;1
"Unit";"Marine";"Barracks";233;1
"Building";"MissileTurret";NA;234;0
"Building";"MissileTurret";NA;234;0
"Building";"MissileTurret";NA;234;0
"Building";"MissileTurret";NA;234;0
"Unit";"Marine";"Barracks";234;1
"Unit";"Marine";"Barracks";235;1
"Unit";"Marine";"Barracks";236;1
"Unit";"Marine";"Barracks";238;1
"Unit";"Marine";"Barracks";239;1
"Unit";"Marine";"Barracks";239;1
"Building";"MissileTurret";NA;241;0
"Unit";"Marine";"Barracks";245;1
"Unit";"Marine";"Barracks";245;1
"Unit";"Marine";"Barracks";245;1
"Upgrade";"TerranInfantryWeaponsLevel3";"EngineeringBay";191;0
"Unit";"Marine";"Barracks";247;1
"Unit";"Marine";"Barracks";247;1
"Unit";"Marine";"Barracks";247;1
"Unit";"Marine";"Barracks";247;1
"Unit";"Marine";"Barracks";247;1
"Unit";"Marine";"Barracks";249;1
"Unit";"Marine";"Barracks";250;1
"Unit";"Marine";"Barracks";263;1
"Unit";"Marine";"Barracks";263;1
"Unit";"Marine";"Barracks";263;1
"Unit";"Marine";"Barracks";263;1
"Unit";"Marine";"Barracks";263;1
"Unit";"Marine";"Barracks";263;1
"Unit";"Marine";"Barracks";263;1
"Unit";"Marine";"Barracks";263;1
"Unit";"Marine";"Barracks";263;1
"Unit";"Marine";"Barracks";263;1
"Unit";"Marine";"Barracks";263;1
"Unit";"Marine";"Barracks";263;1
"Unit";"Marine";"Barracks";263;1
"Unit";"Marine";"Barracks";264;1
"Unit";"Marine";"Barracks";264;1
"Unit";"Marine";"Barracks";274;1
"Unit";"Marine";"Barracks";274;1
"Unit";"Marine";"Barracks";274;1
"Unit";"Marine";"Barracks";274;1
"Unit";"Marine";"Barracks";278;1
"Unit";"Marine";"Barracks";278;1
"Unit";"Marine";"Barracks";278;1
"Unit";"Marine";"Barracks";278;1
"Unit";"Marine";"Barracks";282;1
"Unit";"Marine";"Barracks";282;1
"Unit";"Marine";"Barracks";282;1
"Unit";"Marine";"Barracks";282;1
"Unit";"Marine";"Barracks";282;1
"Unit";"Marine";"Barracks";282;1
"Unit";"Marine";"Barracks";282;1
"Unit";"Marine";"Barracks";282;1
"Unit";"Marine";"Barracks";282;1
"Unit";"Marine";"Barracks";282;1
"Unit";"Marine";"Barracks";283;1
"Unit";"Marine";"Barracks";286;1
"Unit";"Marine";"Barracks";286;1
"Unit";"Marine";"Barracks";286;1
"Unit";"Medivac";"Starport";285;2
"Unit";"Medivac";"Starport";285;2
"Unit";"Marine";"Barracks";297;1
"Unit";"Marine";"Barracks";304;1
"Unit";"Marine";"Barracks";304;1
"Unit";"Medivac";"Starport";300;2
"Unit";"Medivac";"Starport";302;2
"Unit";"Marine";"Barracks";305;1
"Unit";"Marine";"Barracks";305;1
"Unit";"Marine";"Barracks";305;1
"Unit";"Marine";"Barracks";305;1
"Unit";"Marine";"Barracks";305;1
"Unit";"Marine";"Barracks";305;1
"Unit";"Marine";"Barracks";305;1
"Unit";"Marine";"Barracks";305;1
"Unit";"Marine";"Barracks";305;1
"Unit";"Marine";"Barracks";305;1
"Unit";"Marine";"Barracks";307;1
"Unit";"Marine";"Barracks";307;1
"Unit";"Marine";"Barracks";307;1
"Unit";"Marine";"Barracks";321;1
"Unit";"Marine";"Barracks";321;1
"Unit";"Marine";"Barracks";321;1
"Unit";"Marine";"Barracks";321;1
"Unit";"Medivac";"Starport";307;2
"Unit";"Marine";"Barracks";321;1
"Unit";"Medivac";"Starport";309;2
"Unit";"Marine";"Barracks";321;1
"Unit";"Marine";"Barracks";321;1
"Unit";"Marine";"Barracks";321;1
"Building";"CommandCenter";NA;297;0
"Upgrade";"TerranInfantryArmorsLevel3";"EngineeringBay";278;0
"Unit";"Marine";"Barracks";324;1
"Unit";"Marine";"Barracks";324;1
"Unit";"Marine";"Barracks";324;1
"Unit";"Marine";"Barracks";324;1
"Unit";"Marine";"Barracks";324;1
"Unit";"Marine";"Barracks";324;1
"Unit";"Marine";"Barracks";325;1
"Unit";"Marine";"Barracks";326;1
"Unit";"Medivac";"Starport";327;2
"Unit";"Medivac";"Starport";330;2
"Unit";"Marine";"Barracks";339;1
"Unit";"Marine";"Barracks";339;1
"Unit";"Marine";"Barracks";339;1
"Unit";"Marine";"Barracks";341;1
"Unit";"Marine";"Barracks";341;1
"Unit";"Marine";"Barracks";341;1
"Unit";"Marine";"Barracks";341;1
"Unit";"Marine";"Barracks";341;1
"Unit";"Marine";"Barracks";341;1
"Unit";"Marine";"Barracks";341;1
"Unit";"Marine";"Barracks";344;1
"Unit";"Marine";"Barracks";344;1
"Unit";"Marine";"Barracks";344;1
"Upgrade";"TerranVehicleWeaponsLevel3";"Armory";295;0
"Unit";"Marine";"Barracks";348;1
"Unit";"Marine";"Barracks";349;1
"Unit";"Marine";"Barracks";350;1
"Unit";"Medivac";"Starport";344;2
"Unit";"Marine";"Barracks";364;1
"Unit";"Marine";"Barracks";364;1
"Unit";"Marine";"Barracks";364;1
"Unit";"Marine";"Barracks";364;1
"Unit";"Marine";"Barracks";364;1
"Unit";"Marine";"Barracks";364;1
"Unit";"Marine";"Barracks";364;1
"Unit";"Marine";"Barracks";364;1
"Unit";"Marine";"Barracks";364;1
"Unit";"Marine";"Barracks";364;1
"Unit";"Marine";"Barracks";364;1
"Unit";"Marine";"Barracks";366;1
"Unit";"Marine";"Barracks";366;1
"Unit";"Marine";"Barracks";366;1
"Unit";"Marine";"Barracks";367;1
"Unit";"Marine";"Barracks";368;1
"Unit";"Marine";"Barracks";369;1
"Unit";"Marine";"Barracks";370;1
"Unit";"Marine";"Barracks";371;1
"Unit";"Marine";"Barracks";372;1
"Unit";"Marine";"Barracks";373;1
"Unit";"Medivac";"Starport";366;2
"Unit";"Medivac";"Starport";366;2
"Unit";"Marine";"Barracks";374;1
"Unit";"Marine";"Barracks";392;1
"Unit";"Marine";"Barracks";392;1
"Unit";"Marine";"Barracks";392;1
"Unit";"Marine";"Barracks";392;1
"Unit";"Marine";"Barracks";392;1
"Unit";"Marine";"Barracks";392;1
"Unit";"Marine";"Barracks";392;1
"Unit";"Marine";"Barracks";392;1
"Unit";"Marine";"Barracks";392;1
"Unit";"Marine";"Barracks";392;1
"Unit";"Marine";"Barracks";392;1
