"type";"unit_name";"on_building";"total_supply";"supply"
"Building";"Refinery";NA;14;0
"Building";"Refinery";NA;17;0
"Building";"Barracks";NA;15;0
"Building";"Barracks";NA;17;0
"Unit";"Reaper";"Barracks";18;1
"Unit";"Reaper";"Barracks";18;1
"Building";"Factory";NA;18;0
"Unit";"Reaper";"Barracks";19;1
"Unit";"Hellion";"Factory";20;2
"Unit";"Reaper";"Barracks";19;1
"Unit";"Hellion";"Factory";23;2
"Unit";"Reaper";"Barracks";21;1
