"Type";"UnitName";"OnBuilding";"TotalSupply";"Supply"
"Unit";"SCV";"Command Center";12;1
"Unit";"SCV";"Command Center";12;1
"Unit";"SCV";"Command Center";13;1
"Building";"SupplyDepot";NA;13;0
"Building";"Refinery";NA;14;0
"Unit";"SCV";"Command Center";15;1
"Unit";"SCV";"Command Center";15;1
"Building";"Refinery";NA;16;0
"Unit";"SCV";"Command Center";16;1
"Unit";"SCV";"Command Center";17;1
"Building";"Barracks";NA;15;0
"Unit";"Reaper";"Barracks";19;1
"Unit";"SCV";"Command Center";19;1
"Building";"SupplyDepot";NA;19;0
"Building";"Factory";NA;19;0
"Unit";"SCV";"Command Center";20;1
"Unit";"SCV";"Command Center";21;1
"Unit";"Reaper";"Barracks";19;1
"Building";"SupplyDepot";NA;21;0
"Unit";"SCV";"Command Center";22;1
"Unit";"Cyclone";"Factory";22;3
"Unit";"SCV";"Command Center";24;1
"Building";"Starport";NA;22;0
"Unit";"SCV";"Command Center";28;1
"Building";"FactoryTechLab";NA;29;0
"Unit";"SCV";"Command Center";29;1
"Building";"StarportTechLab";NA;30;0
"Unit";"SCV";"Command Center";30;1
"Building";"SupplyDepot";NA;30;0
"Building";"BarracksReactor";NA;29;0
"Unit";"SCV";"Command Center";31;1
"Unit";"Marine";"Barracks";32;1
"Unit";"Marine";"Barracks";32;1
"Building";"SupplyDepot";NA;32;0
"Unit";"SCV";"Command Center";32;1
"Building";"SupplyDepot";NA;32;0
"Unit";"SCV";"Command Center";35;1
"Unit";"Banshee";"Starport";31;3
"Unit";"Marine";"Barracks";33;1
"Unit";"Marine";"Barracks";34;1
"Building";"SupplyDepot";NA;36;0
"Unit";"Marine";"Barracks";40;1
"Unit";"Marine";"Barracks";41;1
"Unit";"SCV";"Command Center";42;1
"Building";"SupplyDepot";NA;42;0
"Unit";"Marine";"Barracks";42;1
"Unit";"Marine";"Barracks";43;1
"Unit";"SCV";"Command Center";45;1
"Unit";"Banshee";"Starport";42;3
"Building";"SupplyDepot";NA;45;0
"Unit";"Marine";"Barracks";47;1
"Unit";"Marine";"Barracks";47;1
"Unit";"SCV";"Command Center";48;1
"Unit";"Marine";"Barracks";51;1
"Unit";"Marine";"Barracks";52;1
"Unit";"SCV";"Command Center";54;1
"Unit";"SCV";"Command Center";57;1
"Unit";"Marine";"Barracks";56;1
"Unit";"Marine";"Barracks";56;1
"Unit";"Banshee";"Starport";56;3
"Unit";"SCV";"Command Center";60;1
"Unit";"Marine";"Barracks";60;1
"Unit";"Marine";"Barracks";60;1
"Unit";"SCV";"Command Center";63;1
"Building";"CommandCenter";NA;54;0
"Unit";"SCV";"Command Center";66;1
"Unit";"SCV";"Command Center";67;1
"Building";"Barracks";NA;60;0
"Building";"Barracks";NA;63;0
"Unit";"Marine";"Barracks";68;1
"Unit";"Marine";"Barracks";68;1
"Unit";"SCV";"Command Center";68;1
"Building";"FactoryReactor";NA;67;0
"Building";"EngineeringBay";NA;68;0
"Building";"SupplyDepot";NA;69;0
"Building";"EngineeringBay";NA;68;0
"Unit";"SCV";"Command Center";71;1
"Building";"StarportReactor";NA;68;0
"Building";"Refinery";NA;69;0
"Unit";"Marine";"Barracks";72;1
"Unit";"Marine";"Barracks";72;1
"Unit";"SCV";"Command Center";72;1
"Unit";"SCV";"Command Center";73;1
"Unit";"Marine";"Barracks";73;1
"Unit";"SCV";"Command Center";75;1
"Unit";"SCV";"Command Center";76;1
"Unit";"SCV";"Command Center";78;1
"Unit";"SCV";"Command Center";79;1
"Building";"SupplyDepot";NA;77;0
"Unit";"Marauder";"Barracks";77;2
"Unit";"Marauder";"Barracks";77;2
"Unit";"Marine";"Barracks";80;1
"Building";"Refinery";NA;80;0
"Unit";"SCV";"Command Center";80;1
"Unit";"SCV";"Command Center";86;1
"Unit";"Marine";"Barracks";82;1
"Unit";"SCV";"Command Center";87;1
"Unit";"Marauder";"Barracks";82;2
"Unit";"Medivac";"Starport";80;2
"Building";"MissileTurret";NA;86;0
"Unit";"Medivac";"Starport";80;2
"Unit";"Marine";"Barracks";88;1
"Unit";"SCV";"Command Center";90;1
"Unit";"Marauder";"Barracks";88;2
"Building";"MissileTurret";NA;88;0
"Unit";"SCV";"Command Center";95;1
"Unit";"Marine";"Barracks";90;1
"Building";"CommandCenter";NA;75;0
"Unit";"Marine";"Barracks";95;1
"Unit";"SCV";"Command Center";101;1
"Unit";"SCV";"Command Center";103;1
"Unit";"Marine";"Barracks";103;1
"Unit";"Marine";"Barracks";103;1
"Unit";"Marine";"Barracks";103;1
"Unit";"Medivac";"Starport";97;2
"Unit";"Medivac";"Starport";97;2
"Unit";"SCV";"Command Center";105;1
"Unit";"Marine";"Barracks";105;1
"Building";"FactoryTechLab";NA;105;0
"Unit";"Marine";"Barracks";106;1
"Unit";"SCV";"Command Center";115;1
"Unit";"Marine";"Barracks";115;1
"Unit";"Marine";"Barracks";115;1
"Building";"Barracks";NA;101;0
"Unit";"SCV";"Command Center";115;1
"Building";"Barracks";NA;103;0
"Unit";"Marine";"Barracks";115;1
"Unit";"SCV";"Command Center";116;1
"Unit";"Marine";"Barracks";115;1
"Upgrade";"Stimpack";"TechLab";86;0
"Unit";"SCV";"Command Center";119;1
"Upgrade";"TerranInfantryWeaponsLevel1";"EngineeringBay";88;0
"Upgrade";"TerranInfantryArmorsLevel1";"EngineeringBay";89;0
"Unit";"SCV";"Command Center";121;1
"Unit";"Marine";"Barracks";121;1
"Unit";"SCV";"Command Center";123;1
"Unit";"Medivac";"Starport";117;2
"Unit";"Medivac";"Starport";117;2
"Unit";"SCV";"Command Center";124;1
"Building";"MissileTurret";NA;124;0
"Building";"MissileTurret";NA;124;0
"Unit";"SCV";"Command Center";126;1
"Building";"BarracksReactor";NA;121;0
"Building";"BarracksReactor";NA;121;0
"Unit";"SCV";"Command Center";131;1
"Unit";"Marine";"Barracks";126;1
"Unit";"Marine";"Barracks";126;1
"Unit";"Marine";"Barracks";126;1
"Unit";"Marine";"Barracks";127;1
"Unit";"SCV";"Command Center";131;1
"Unit";"SCV";"Command Center";132;1
"Unit";"SCV";"Command Center";139;1
"Unit";"SCV";"Command Center";139;1
"Unit";"Marine";"Barracks";134;1
"Unit";"Marine";"Barracks";135;1
"Unit";"Marine";"Barracks";136;1
"Unit";"Marine";"Barracks";139;1
"Unit";"Marine";"Barracks";139;1
"Unit";"Marine";"Barracks";139;1
"Unit";"Marine";"Barracks";139;1
"Unit";"Medivac";"Starport";132;2
"Unit";"Medivac";"Starport";132;2
"Unit";"SCV";"Command Center";140;1
"Building";"SupplyDepot";NA;140;0
"Building";"Armory";NA;127;0
"Unit";"Marine";"Barracks";140;1
"Unit";"SCV";"Command Center";145;1
"Unit";"Marine";"Barracks";141;1
"Building";"SupplyDepot";NA;140;0
"Building";"SupplyDepot";NA;140;0
