"Type";"UnitName";"OnBuilding";"TotalSupply";"Supply"
"Unit";"SCV";"Command Center";12;1
"Unit";"SCV";"Command Center";12;1
"Unit";"SCV";"Command Center";13;1
"Building";"SupplyDepot";NA;13;0
"Unit";"SCV";"Command Center";15;1
"Building";"Refinery";NA;14;0
"Unit";"SCV";"Command Center";15;1
"Unit";"SCV";"Command Center";16;1
"Building";"Refinery";NA;16;0
"Unit";"SCV";"Command Center";17;1
"Building";"Barracks";NA;15;0
"Unit";"Reaper";"Barracks";19;1
"Building";"SupplyDepot";NA;19;0
"Unit";"SCV";"Command Center";19;1
"Building";"Factory";NA;19;0
"Unit";"SCV";"Command Center";21;1
"Unit";"Reaper";"Barracks";19;1
"Unit";"SCV";"Command Center";22;1
"Unit";"Cyclone";"Factory";22;3
"Building";"Starport";NA;22;0
"Building";"SupplyDepot";NA;24;0
"Unit";"SCV";"Command Center";24;1
"Unit";"Marine";"Barracks";24;1
"Building";"Bunker";NA;24;0
"Building";"Bunker";NA;27;0
"Unit";"SCV";"Command Center";29;1
"Unit";"Marine";"Barracks";29;1
"Unit";"Cyclone";"Factory";29;3
"Unit";"SCV";"Command Center";34;1
"Unit";"Liberator";"Starport";30;3
"Building";"FactoryTechLab";NA;35;0
"Building";"SupplyDepot";NA;38;0
"Unit";"Marine";"Barracks";38;1
"Building";"SupplyDepot";NA;38;0
"Unit";"SCV";"Command Center";38;1
"Unit";"Liberator";"Starport";38;3
"Unit";"SCV";"Command Center";40;1
"Unit";"Marine";"Barracks";40;1
"Building";"SupplyDepot";NA;40;0
"Unit";"SCV";"Command Center";43;1
"Unit";"SCV";"Command Center";46;1
"Building";"FactoryTechLab";NA;46;0
"Building";"BarracksTechLab";NA;46;0
"Building";"CommandCenter";NA;40;0
"Unit";"Banshee";"Starport";46;3
"Unit";"Marine";"Barracks";50;1
"Unit";"SCV";"Command Center";50;1
"Unit";"Banshee";"Starport";47;3
"Unit";"SCV";"Command Center";52;1
"Building";"EngineeringBay";NA;51;0
"Unit";"SCV";"Command Center";56;1
"Unit";"Marine";"Barracks";56;1
"Building";"CommandCenter";NA;50;0
"Unit";"Banshee";"Starport";52;3
"Unit";"SCV";"Command Center";58;1
"Unit";"SCV";"Command Center";58;1
"Unit";"Marine";"Barracks";58;1
"Building";"Barracks";NA;58;0
"Upgrade";"Stimpack";"TechLab";52;0
"Unit";"Marine";"Barracks";63;1
"Unit";"SCV";"Command Center";64;1
"Unit";"SCV";"Command Center";64;1
"Unit";"SCV";"Command Center";64;1
"Unit";"Marine";"Barracks";64;1
"Building";"StarportReactor";NA;64;0
"Building";"BarracksReactor";NA;65;0
"Unit";"Marine";"Barracks";69;1
"Unit";"SCV";"Command Center";69;1
"Unit";"SCV";"Command Center";69;1
"Unit";"Marine";"Barracks";70;1
"Unit";"Marine";"Barracks";70;1
"Building";"Barracks";NA;69;0
"Unit";"Medivac";"Starport";70;2
"Unit";"Medivac";"Starport";72;2
"Unit";"Marine";"Barracks";74;1
"Unit";"Marine";"Barracks";74;1
"Unit";"SCV";"Command Center";74;1
"Unit";"Marauder";"Barracks";74;2
"Unit";"Marine";"Barracks";74;1
"Unit";"SCV";"Command Center";80;1
"Unit";"Marine";"Barracks";78;1
"Unit";"Marine";"Barracks";79;1
"Unit";"Marauder";"Barracks";81;2
"Building";"BarracksTechLab";NA;87;0
"Unit";"Marauder";"Barracks";87;2
"Unit";"SCV";"Command Center";89;1
"Unit";"Marine";"Barracks";89;1
"Unit";"Marauder";"Barracks";89;2
"Unit";"Marauder";"Barracks";89;2
"Unit";"Marine";"Barracks";97;1
"Unit";"Marine";"Barracks";97;1
"Unit";"Marauder";"Barracks";97;2
"Unit";"Marauder";"Barracks";97;2
"Unit";"Marauder";"Barracks";99;2
"Unit";"Marauder";"Barracks";103;2
"Unit";"SCV";"Command Center";103;1
"Unit";"SCV";"Command Center";107;1
"Unit";"SCV";"Command Center";108;1
"Unit";"SCV";"Command Center";108;1
"Unit";"Medivac";"Starport";103;2
"Unit";"SCV";"Command Center";108;1
"Unit";"SCV";"Command Center";110;1
"Unit";"Marine";"Barracks";109;1
"Unit";"Marine";"Barracks";109;1
"Unit";"SCV";"Command Center";113;1
"Unit";"Marauder";"Barracks";109;2
"Unit";"SCV";"Command Center";113;1
"Building";"Refinery";NA;114;0
"Unit";"SCV";"Command Center";120;1
"Building";"Refinery";NA;114;0
"Building";"SupplyDepot";NA;114;0
"Unit";"SCV";"Command Center";120;1
"Unit";"Marine";"Barracks";117;1
"Unit";"SCV";"Command Center";121;1
"Unit";"Marine";"Barracks";117;1
"Unit";"Marauder";"Barracks";115;2
"Unit";"Marauder";"Barracks";118;2
"Unit";"SCV";"Command Center";122;1
"Unit";"SCV";"Command Center";124;1
"Unit";"SCV";"Command Center";130;1
"Unit";"SCV";"Command Center";130;1
"Unit";"SCV";"Command Center";131;1
"Unit";"Marine";"Barracks";130;1
"Unit";"Marine";"Barracks";130;1
"Unit";"Marauder";"Barracks";130;2
"Unit";"Marauder";"Barracks";130;2
"Unit";"SCV";"Command Center";132;1
"Unit";"Medivac";"Starport";132;2
"Building";"SupplyDepot";NA;141;0
"Unit";"SCV";"Command Center";144;1
"Unit";"SCV";"Command Center";144;1
"Unit";"Marine";"Barracks";144;1
"Unit";"Marine";"Barracks";144;1
"Unit";"Marauder";"Barracks";144;2
"Building";"Barracks";NA;141;0
"Building";"Barracks";NA;141;0
"Upgrade";"TerranInfantryWeaponsLevel1";"EngineeringBay";124;0
"Unit";"Medivac";"Starport";144;2
"Unit";"SCV";"Command Center";150;1
"Unit";"Marine";"Barracks";150;1
"Unit";"Marine";"Barracks";150;1
"Building";"SupplyDepot";NA;150;0
"Unit";"Marauder";"Barracks";150;2
"Building";"SupplyDepot";NA;150;0
"Building";"BarracksTechLab";NA;152;0
"Unit";"SCV";"Command Center";153;1
"Unit";"SCV";"Command Center";153;1
"Unit";"SCV";"Command Center";155;1
"Unit";"Marauder";"Barracks";153;2
"Unit";"Marine";"Barracks";155;1
"Unit";"SCV";"Command Center";157;1
"Unit";"SCV";"Command Center";158;1
"Building";"BarracksReactor";NA;152;0
"Unit";"SCV";"Command Center";159;1
"Unit";"Marine";"Barracks";160;1
"Unit";"SCV";"Command Center";163;1
"Unit";"Marauder";"Barracks";160;2
"Unit";"Marauder";"Barracks";160;2
"Unit";"Marine";"Barracks";160;1
"Unit";"Marine";"Barracks";162;1
"Unit";"SCV";"Command Center";173;1
"Unit";"Marine";"Barracks";168;1
"Unit";"Marine";"Barracks";168;1
"Unit";"Marauder";"Barracks";168;2
"Unit";"Marauder";"Barracks";170;2
"Unit";"Marauder";"Barracks";172;2
"Unit";"SCV";"Command Center";175;1
"Building";"SupplyDepot";NA;174;0
