"type";"unit_name";"on_building";"total_supply";"supply"
"Building";"Refinery";NA;14;0
"Building";"Barracks";NA;15;0
"Unit";"Reaper";"Barracks";19;1
"Building";"Refinery";NA;19;0
"Building";"Factory";NA;19;0
"Unit";"Hellion";"Factory";23;2
"Building";"BarracksReactor";NA;23;0
"Building";"CommandCenter";NA;19;0
"Unit";"Cyclone";"Factory";27;3
"Building";"EngineeringBay";NA;28;0
"Building";"MissileTurret";NA;33;0
"Unit";"Cyclone";"Factory";33;3
"Unit";"Cyclone";"Factory";33;3
"Unit";"Cyclone";"Factory";42;3
"Building";"Factory";NA;42;0
"Building";"MissileTurret";NA;47;0
"Building";"FactoryTechLab";NA;48;0
"Building";"BarracksTechLab";NA;48;0
"Unit";"Hellion";"Factory";50;2
"Unit";"Hellion";"Factory";50;2
"Building";"Refinery";NA;51;0
"Building";"Factory";NA;48;0
"Building";"Refinery";NA;52;0
"Building";"CommandCenter";NA;42;0
"Building";"Armory";NA;48;0
"Building";"Armory";NA;49;0
"Building";"Refinery";NA;60;0
"Unit";"Hellion";"Factory";62;2
"Unit";"Hellion";"Factory";69;2
"Unit";"Hellion";"Factory";69;2
"Building";"MissileTurret";NA;71;0
"Building";"SensorTower";NA;81;0
"Building";"Starport";NA;73;0
"Building";"BarracksReactor";NA;78;0
"Building";"Refinery";NA;84;0
"Unit";"Hellion";"Factory";84;2
"Unit";"Hellion";"Factory";84;2
"Upgrade";"TerranVehicleWeaponsLevel1";"Armory";67;0
"Building";"Factory";NA;95;0
"Building";"Factory";NA;97;0
"Unit";"Hellion";"Factory";100;2
"Unit";"Hellion";"Factory";100;2
"Building";"FactoryTechLab";NA;106;0
"Building";"FactoryTechLab";NA;106;0
"Building";"CommandCenter";NA;100;0
"Building";"MissileTurret";NA;106;0
"Building";"MissileTurret";NA;106;0
"Building";"MissileTurret";NA;106;0
"Building";"MissileTurret";NA;106;0
"Building";"MissileTurret";NA;106;0
"Unit";"Hellion";"Factory";106;2
"Unit";"Hellion";"Factory";106;2
"Upgrade";"TerranVehicleWeaponsLevel2";"Armory";100;0
"Building";"CommandCenter";NA;106;0
"Building";"Starport";NA;112;0
"Building";"Starport";NA;112;0
"Unit";"Hellion";"Factory";112;2
"Unit";"Hellion";"Factory";112;2
"Building";"StarportTechLab";NA;116;0
"Building";"StarportTechLab";NA;116;0
"Unit";"Hellion";"Factory";116;2
"Unit";"Hellion";"Factory";116;2
"Unit";"Hellion";"Factory";116;2
"Unit";"Hellion";"Factory";118;2
"Unit";"Hellion";"Factory";120;2
"Unit";"Hellion";"Factory";120;2
"Building";"Refinery";NA;120;0
"Building";"Refinery";NA;120;0
"Unit";"Hellion";"Factory";120;2
"Unit";"Hellion";"Factory";122;2
"Unit";"Hellion";"Factory";124;2
"Unit";"Hellion";"Factory";126;2
"Building";"Refinery";NA;143;0
"Building";"CommandCenter";NA;143;0
"Unit";"Hellion";"Factory";149;2
"Building";"CommandCenter";NA;147;0
"Building";"CommandCenter";NA;147;0
"Upgrade";"TerranShipWeaponsLevel1";"Armory";147;0
"Building";"Refinery";NA;154;0
"Upgrade";"TerranVehicleWeaponsLevel3";"Armory";147;0
"Building";"SensorTower";NA;154;0
"Unit";"Thor";"Factory";154;6
"Unit";"Hellion";"Factory";167;2
"Unit";"Hellion";"Factory";167;2
"Unit";"Raven";"Starport";167;2
"Unit";"Raven";"Starport";176;2
"Unit";"Raven";"Starport";181;2
"Unit";"Hellion";"Factory";192;2
"Unit";"Hellion";"Factory";192;2
"Unit";"Hellion";"Factory";192;2
"Unit";"Hellion";"Factory";192;2
"Unit";"Hellion";"Factory";192;2
"Unit";"Hellion";"Factory";192;2
"Building";"CommandCenter";NA;183;0
"Building";"CommandCenter";NA;183;0
"Unit";"Hellion";"Factory";192;2
"Building";"Refinery";NA;204;0
"Unit";"Raven";"Starport";192;2
"Building";"Refinery";NA;204;0
"Unit";"Thor";"Factory";204;6
"Unit";"Hellion";"Factory";208;2
"Unit";"Hellion";"Factory";208;2
"Unit";"Hellion";"Factory";208;2
"Unit";"Hellion";"Factory";214;2
"Unit";"Hellion";"Factory";216;2
"Unit";"Hellion";"Factory";224;2
"Unit";"Hellion";"Factory";224;2
"Unit";"Hellion";"Factory";224;2
"Unit";"Hellion";"Factory";226;2
"Building";"Refinery";NA;228;0
"Unit";"Hellion";"Factory";232;2
"Unit";"Hellion";"Factory";232;2
"Unit";"Hellion";"Factory";232;2
"Unit";"Hellion";"Factory";232;2
"Unit";"Hellion";"Factory";234;2
"Unit";"Raven";"Starport";232;2
"Unit";"Raven";"Starport";232;2
"Unit";"Hellion";"Factory";238;2
"Unit";"Hellion";"Factory";242;2
"Unit";"Hellion";"Factory";242;2
"Unit";"Hellion";"Factory";242;2
"Unit";"Hellion";"Factory";242;2
"Unit";"Hellion";"Factory";252;2
"Unit";"Hellion";"Factory";254;2
"Unit";"Hellion";"Factory";276;2
"Building";"Refinery";NA;278;0
"Building";"Refinery";NA;278;0
"Building";"StarportTechLab";NA;283;0
"Unit";"Hellion";"Factory";285;2
"Unit";"Hellion";"Factory";286;2
"Building";"StarportTechLab";NA;297;0
"Building";"EngineeringBay";NA;297;0
"Building";"FactoryTechLab";NA;306;0
"Building";"FactoryTechLab";NA;306;0
"Building";"Barracks";NA;313;0
"Building";"Refinery";NA;319;0
"Building";"Factory";NA;321;0
"Building";"Factory";NA;321;0
"Building";"Factory";NA;321;0
"Building";"Factory";NA;322;0
"Building";"Factory";NA;323;0
"Building";"Factory";NA;323;0
"Building";"Factory";NA;327;0
"Building";"FactoryTechLab";NA;333;0
"Building";"FactoryTechLab";NA;333;0
"Building";"FactoryTechLab";NA;333;0
"Building";"Factory";NA;327;0
"Unit";"Cyclone";"Factory";336;3
"Unit";"Cyclone";"Factory";336;3
"Unit";"Cyclone";"Factory";336;3
"Unit";"Cyclone";"Factory";336;3
"Unit";"Cyclone";"Factory";336;3
"Unit";"Cyclone";"Factory";336;3
"Building";"Refinery";NA;337;0
"Building";"Refinery";NA;338;0
"Building";"Refinery";NA;340;0
"Unit";"Hellion";"Factory";349;2
"Unit";"Hellion";"Factory";352;2
"Unit";"Hellion";"Factory";355;2
"Unit";"Cyclone";"Factory";361;3
"Unit";"Cyclone";"Factory";361;3
"Unit";"Cyclone";"Factory";361;3
"Unit";"Hellion";"Factory";367;2
"Building";"FactoryTechLab";NA;376;0
"Building";"FactoryTechLab";NA;376;0
"Unit";"Hellion";"Factory";367;2
"Unit";"Hellion";"Factory";370;2
"Unit";"Cyclone";"Factory";367;3
"Building";"Refinery";NA;376;0
"Unit";"Hellion";"Factory";391;2
"Unit";"Hellion";"Factory";391;2
"Unit";"Cyclone";"Factory";391;3
"Unit";"Cyclone";"Factory";391;3
"Building";"CommandCenter";NA;391;0
"Unit";"Cyclone";"Factory";409;3
"Unit";"Cyclone";"Factory";411;3
"Unit";"Cyclone";"Factory";411;3
"Unit";"Cyclone";"Factory";411;3
"Unit";"Cyclone";"Factory";411;3
"Unit";"Cyclone";"Factory";411;3
"Unit";"Hellion";"Factory";429;2
"Unit";"Hellion";"Factory";429;2
"Unit";"Hellion";"Factory";429;2
"Building";"Refinery";NA;429;0
"Unit";"Hellion";"Factory";429;2
"Unit";"Hellion";"Factory";429;2
"Unit";"Hellion";"Factory";429;2
"Building";"Refinery";NA;429;0
"Unit";"Hellion";"Factory";429;2
"Unit";"Hellion";"Factory";429;2
"Unit";"Hellion";"Factory";431;2
"Unit";"Hellion";"Factory";433;2
"Building";"Starport";NA;429;0
"Unit";"Hellion";"Factory";437;2
"Unit";"Hellion";"Factory";439;2
"Building";"Starport";NA;429;0
