"type";"unit_name";"on_building";"total_supply";"supply"
"Building";"Refinery";NA;14;0
"Building";"Barracks";NA;15;0
"Unit";"Reaper";"Barracks";19;1
"Building";"BarracksReactor";NA;21;0
"Building";"Factory";NA;19;0
"Building";"Bunker";NA;22;0
"Building";"CommandCenter";NA;19;0
"Unit";"Marine";"Barracks";23;1
"Unit";"Marine";"Barracks";23;1
"Building";"Refinery";NA;23;0
"Unit";"Hellion";"Factory";23;2
"Unit";"Marine";"Barracks";27;1
"Unit";"Marine";"Barracks";27;1
"Building";"Starport";NA;24;0
"Building";"FactoryTechLab";NA;30;0
"Unit";"Marine";"Barracks";30;1
"Unit";"Marine";"Barracks";32;1
"Building";"FactoryTechLab";NA;36;0
"Unit";"Marine";"Barracks";36;1
"Unit";"Marine";"Barracks";36;1
"Unit";"Raven";"Starport";36;2
"Unit";"Marine";"Barracks";41;1
"Unit";"Marine";"Barracks";41;1
"Unit";"Marine";"Barracks";49;1
"Building";"StarportReactor";NA;49;0
"Unit";"Marine";"Barracks";53;1
"Building";"Barracks";NA;48;0
"Building";"Barracks";NA;49;0
"Unit";"Marine";"Barracks";56;1
"Building";"BarracksTechLab";NA;56;0
"Unit";"Marine";"Barracks";56;1
"Unit";"Marine";"Barracks";56;1
"Building";"Refinery";NA;56;0
"Building";"Refinery";NA;56;0
"Building";"EngineeringBay";NA;56;0
"Building";"EngineeringBay";NA;56;0
"Unit";"Marine";"Barracks";62;1
"Unit";"Marine";"Barracks";62;1
"Unit";"Marine";"Barracks";62;1
"Building";"CommandCenter";NA;53;0
"Unit";"Marine";"Barracks";68;1
"Unit";"Marine";"Barracks";68;1
"Unit";"Marauder";"Barracks";68;2
"Upgrade";"Stimpack";"TechLab";55;0
"Building";"Refinery";NA;68;0
"Unit";"Medivac";"Starport";68;2
"Unit";"Medivac";"Starport";68;2
"Unit";"Marauder";"Barracks";68;2
"Unit";"Marine";"Barracks";74;1
"Unit";"Marine";"Barracks";74;1
"Unit";"Marauder";"Barracks";74;2
"Unit";"Marine";"Barracks";84;1
"Unit";"Marine";"Barracks";84;1
"Unit";"Marauder";"Barracks";84;2
"Unit";"Medivac";"Starport";81;2
"Unit";"Marauder";"Barracks";86;2
"Building";"Barracks";NA;81;0
"Building";"Barracks";NA;81;0
"Unit";"Marine";"Barracks";92;1
"Unit";"Marine";"Barracks";92;1
"Unit";"Marauder";"Barracks";92;2
"Upgrade";"TerranInfantryWeaponsLevel1";"EngineeringBay";71;0
"Upgrade";"TerranInfantryArmorsLevel1";"EngineeringBay";71;0
"Unit";"Marauder";"Barracks";94;2
"Building";"Refinery";NA;94;0
"Building";"CommandCenter";NA;80;0
"Unit";"Marine";"Barracks";97;1
"Unit";"Marine";"Barracks";97;1
"Building";"BarracksTechLab";NA;104;0
"Unit";"Marine";"Barracks";104;1
"Unit";"Medivac";"Starport";99;2
"Unit";"Marauder";"Barracks";104;2
"Building";"Armory";NA;94;0
"Unit";"Marine";"Barracks";109;1
"Unit";"Marine";"Barracks";109;1
"Building";"BarracksReactor";NA;104;0
"Unit";"Marine";"Barracks";113;1
"Unit";"Marine";"Barracks";113;1
"Unit";"Marauder";"Barracks";113;2
"Unit";"Marine";"Barracks";120;1
"Unit";"Marine";"Barracks";120;1
"Unit";"Marine";"Barracks";120;1
"Unit";"Medivac";"Starport";115;2
"Unit";"Marine";"Barracks";127;1
"Unit";"Marine";"Barracks";127;1
"Unit";"Marine";"Barracks";127;1
"Unit";"Marine";"Barracks";132;1
"Unit";"Marine";"Barracks";132;1
"Unit";"Marine";"Barracks";132;1
"Unit";"Marine";"Barracks";132;1
"Unit";"Marine";"Barracks";132;1
"Building";"Factory";NA;124;0
"Unit";"Marauder";"Barracks";133;2
"Unit";"Marauder";"Barracks";134;2
"Unit";"Marine";"Barracks";135;1
"Unit";"Marine";"Barracks";136;1
"Unit";"Marine";"Barracks";137;1
"Unit";"Thor";"Factory";130;6
"Building";"Refinery";NA;142;0
"Building";"Refinery";NA;143;0
"Building";"FactoryTechLab";NA;157;0
"Unit";"Marine";"Barracks";157;1
"Unit";"Marine";"Barracks";157;1
"Unit";"Marine";"Barracks";157;1
"Unit";"Marine";"Barracks";157;1
"Unit";"Marine";"Barracks";157;1
"Unit";"Marauder";"Barracks";157;2
"Unit";"Marauder";"Barracks";157;2
"Upgrade";"TerranShipWeaponsLevel1";"Armory";132;0
"Building";"Factory";NA;157;0
"Unit";"Marine";"Barracks";169;1
"Unit";"Marine";"Barracks";169;1
"Unit";"Marine";"Barracks";169;1
"Unit";"Thor";"Factory";157;6
"Unit";"Medivac";"Starport";160;2
"Unit";"Medivac";"Starport";160;2
"Building";"Armory";NA;157;0
"Unit";"Marauder";"Barracks";169;2
"Unit";"Marauder";"Barracks";169;2
"Upgrade";"TerranInfantryWeaponsLevel2";"EngineeringBay";132;0
"Upgrade";"TerranInfantryArmorsLevel2";"EngineeringBay";132;0
"Unit";"Marine";"Barracks";191;1
"Unit";"Marine";"Barracks";191;1
"Unit";"Marine";"Barracks";191;1
"Building";"FactoryTechLab";NA;191;0
"Unit";"Marauder";"Barracks";191;2
"Unit";"Marauder";"Barracks";191;2
"Unit";"Medivac";"Starport";183;2
"Unit";"Medivac";"Starport";185;2
"Unit";"Marine";"Barracks";201;1
"Unit";"Marine";"Barracks";201;1
"Unit";"Marine";"Barracks";201;1
"Unit";"Marine";"Barracks";201;1
"Unit";"Marine";"Barracks";201;1
"Unit";"Marine";"Barracks";201;1
"Building";"CommandCenter";NA;173;0
"Unit";"Marine";"Barracks";205;1
"Unit";"Marine";"Barracks";206;1
"Unit";"Marine";"Barracks";211;1
"Unit";"Marine";"Barracks";211;1
"Building";"BarracksTechLab";NA;211;0
"Unit";"Marauder";"Barracks";211;2
"Unit";"Marine";"Barracks";211;1
"Unit";"Marine";"Barracks";211;1
"Unit";"Marine";"Barracks";213;1
"Unit";"Marine";"Barracks";217;1
"Unit";"Marine";"Barracks";217;1
"Building";"Refinery";NA;217;0
"Unit";"Marauder";"Barracks";217;2
"Unit";"Marauder";"Barracks";217;2
"Upgrade";"TerranVehicleWeaponsLevel1";"Armory";197;0
"Unit";"Marine";"Barracks";222;1
"Unit";"Marauder";"Barracks";222;2
"Building";"Barracks";NA;215;0
"Unit";"Thor";"Factory";217;6
"Building";"Barracks";NA;215;0
"Building";"Barracks";NA;217;0
"Unit";"Medivac";"Starport";222;2
"Unit";"Medivac";"Starport";222;2
"Unit";"Marine";"Barracks";231;1
"Unit";"Marine";"Barracks";231;1
"Unit";"Marine";"Barracks";231;1
"Unit";"Marine";"Barracks";231;1
"Unit";"Marauder";"Barracks";231;2
"Unit";"Marauder";"Barracks";231;2
"Unit";"Marauder";"Barracks";231;2
"Building";"BarracksTechLab";NA;241;0
"Unit";"Marine";"Barracks";245;1
"Unit";"Marine";"Barracks";245;1
"Unit";"Marine";"Barracks";245;1
"Unit";"Marine";"Barracks";245;1
"Unit";"Medivac";"Starport";237;2
"Unit";"Medivac";"Starport";239;2
"Unit";"Marauder";"Barracks";245;2
"Unit";"Marauder";"Barracks";247;2
"Unit";"Thor";"Factory";237;6
"Building";"BarracksReactor";NA;241;0
"Building";"BarracksReactor";NA;245;0
"Unit";"Marine";"Barracks";271;1
"Unit";"Marine";"Barracks";271;1
"Unit";"Marine";"Barracks";271;1
"Unit";"Marine";"Barracks";271;1
"Unit";"Marine";"Barracks";271;1
"Unit";"Marine";"Barracks";271;1
"Unit";"Marine";"Barracks";271;1
"Upgrade";"TerranInfantryWeaponsLevel3";"EngineeringBay";215;0
"Upgrade";"TerranInfantryArmorsLevel3";"EngineeringBay";215;0
"Unit";"Marauder";"Barracks";271;2
"Unit";"Marauder";"Barracks";271;2
"Unit";"Marauder";"Barracks";271;2
"Unit";"Thor";"Factory";251;6
"Unit";"Marine";"Barracks";271;1
"Unit";"Marine";"Barracks";271;1
"Unit";"Marine";"Barracks";271;1
"Unit";"Marine";"Barracks";284;1
"Unit";"Marine";"Barracks";284;1
"Unit";"Marine";"Barracks";284;1
"Unit";"Marine";"Barracks";284;1
"Unit";"Marine";"Barracks";290;1
"Unit";"Marine";"Barracks";290;1
"Unit";"Marine";"Barracks";290;1
"Unit";"Marine";"Barracks";290;1
"Unit";"Marine";"Barracks";290;1
"Unit";"Thor";"Factory";271;6
"Unit";"Thor";"Factory";271;6
"Building";"Refinery";NA;293;0
"Unit";"Medivac";"Starport";290;2
"Unit";"Medivac";"Starport";290;2
"Unit";"Marauder";"Barracks";298;2
"Unit";"Marauder";"Barracks";299;2
"Unit";"Marine";"Barracks";304;1
"Unit";"Marine";"Barracks";304;1
"Unit";"Marine";"Barracks";304;1
"Unit";"Marine";"Barracks";304;1
"Unit";"Marine";"Barracks";304;1
"Unit";"Marine";"Barracks";304;1
"Unit";"Marine";"Barracks";330;1
"Unit";"Marine";"Barracks";330;1
"Unit";"Marine";"Barracks";330;1
"Unit";"Marine";"Barracks";330;1
"Unit";"Marine";"Barracks";330;1
"Unit";"Marine";"Barracks";330;1
"Unit";"Marine";"Barracks";330;1
"Unit";"Marine";"Barracks";330;1
"Unit";"Marine";"Barracks";330;1
"Unit";"Marauder";"Barracks";330;2
"Unit";"Marauder";"Barracks";330;2
"Unit";"Marauder";"Barracks";330;2
"Upgrade";"TerranVehicleWeaponsLevel2";"Armory";271;0
"Unit";"Marine";"Barracks";330;1
"Unit";"Marine";"Barracks";339;1
"Unit";"Marine";"Barracks";339;1
"Unit";"Marine";"Barracks";339;1
"Unit";"Marine";"Barracks";339;1
"Unit";"Marine";"Barracks";339;1
"Unit";"Marauder";"Barracks";338;2
"Unit";"Thor";"Factory";330;6
"Building";"CommandCenter";NA;304;0
"Unit";"Medivac";"Starport";345;2
"Unit";"Medivac";"Starport";345;2
"Unit";"Marine";"Barracks";361;1
"Unit";"Marine";"Barracks";361;1
"Unit";"Marine";"Barracks";361;1
"Unit";"Marine";"Barracks";361;1
"Unit";"Marine";"Barracks";361;1
"Unit";"Marine";"Barracks";361;1
"Unit";"Marine";"Barracks";361;1
"Building";"Refinery";NA;372;0
"Unit";"Marine";"Barracks";372;1
"Unit";"Marine";"Barracks";372;1
"Building";"Starport";NA;365;0
"Building";"Refinery";NA;372;0
"Building";"Starport";NA;365;0
"Building";"Starport";NA;365;0
"Unit";"Marine";"Barracks";372;1
"Unit";"Marine";"Barracks";372;1
"Unit";"Marine";"Barracks";372;1
"Unit";"Marine";"Barracks";372;1
"Unit";"Marine";"Barracks";372;1
"Unit";"Marine";"Barracks";372;1
