"Type";"UnitName";"OnBuilding";"TotalSupply";"Supply"
"Unit";"SCV";"Command Center";12;1
"Unit";"SCV";"Command Center";12;1
"Unit";"SCV";"Command Center";13;1
"Building";"SupplyDepot";NA;13;0
"Unit";"SCV";"Command Center";15;1
"Building";"Refinery";NA;14;0
"Unit";"SCV";"Command Center";15;1
"Unit";"SCV";"Command Center";16;1
"Unit";"SCV";"Command Center";17;1
"Building";"Barracks";NA;15;0
"Unit";"Reaper";"Barracks";19;1
"Unit";"SCV";"Command Center";19;1
"Unit";"SCV";"Command Center";21;1
"Building";"Refinery";NA;20;0
"Building";"SupplyDepot";NA;21;0
"Unit";"Reaper";"Barracks";20;1
"Building";"Factory";NA;19;0
"Unit";"SCV";"Command Center";22;1
"Building";"CommandCenter";NA;19;0
"Unit";"SCV";"Command Center";23;1
"Unit";"Hellion";"Factory";23;2
"Building";"BarracksTechLab";NA;23;0
"Unit";"SCV";"Command Center";24;1
"Building";"Starport";NA;23;0
"Unit";"Hellion";"Factory";25;2
"Unit";"SCV";"Command Center";28;1
"Unit";"SCV";"Command Center";28;1
"Unit";"SCV";"Command Center";30;1
"Unit";"Hellion";"Factory";31;2
"Unit";"SCV";"Command Center";33;1
"Unit";"SCV";"Command Center";33;1
"Unit";"SCV";"Command Center";35;1
"Building";"BarracksReactor";NA;31;0
"Unit";"SCV";"Command Center";36;1
"Building";"SupplyDepot";NA;33;0
"Building";"FactoryTechLab";NA;35;0
"Unit";"SCV";"Command Center";37;1
"Unit";"SCV";"Command Center";38;1
"Unit";"Banshee";"Starport";32;3
"Unit";"SCV";"Command Center";39;1
"Unit";"SCV";"Command Center";40;1
"Unit";"Marine";"Barracks";41;1
"Unit";"Marine";"Barracks";41;1
"Building";"SupplyDepot";NA;39;0
"Unit";"SCV";"Command Center";44;1
"Unit";"SCV";"Command Center";45;1
"Unit";"SCV";"Command Center";48;1
"Unit";"SCV";"Command Center";49;1
"Unit";"Marine";"Barracks";48;1
"Unit";"Marine";"Barracks";48;1
"Unit";"Banshee";"Starport";41;3
"Unit";"SCV";"Command Center";50;1
"Unit";"SCV";"Command Center";54;1
"Unit";"SCV";"Command Center";59;1
"Unit";"SCV";"Command Center";59;1
"Unit";"Marine";"Barracks";58;1
"Unit";"Marine";"Barracks";59;1
"Unit";"SCV";"Command Center";59;1
"Unit";"Banshee";"Starport";57;3
"Unit";"SCV";"Command Center";63;1
"Unit";"Marine";"Barracks";62;1
"Unit";"Marine";"Barracks";62;1
"Unit";"SCV";"Command Center";63;1
"Unit";"SCV";"Command Center";67;1
"Building";"Barracks";NA;59;0
"Building";"Barracks";NA;59;0
"Unit";"SCV";"Command Center";70;1
"Building";"EngineeringBay";NA;64;0
"Building";"CommandCenter";NA;54;0
"Building";"EngineeringBay";NA;64;0
"Unit";"SCV";"Command Center";71;1
"Unit";"SCV";"Command Center";72;1
"Unit";"SCV";"Command Center";73;1
"Unit";"Marine";"Barracks";73;1
"Building";"SupplyDepot";NA;72;0
"Building";"Refinery";NA;72;0
"Building";"Refinery";NA;72;0
"Unit";"SCV";"Command Center";74;1
"Building";"StarportReactor";NA;72;0
"Unit";"SCV";"Command Center";75;1
"Unit";"SCV";"Command Center";77;1
"Building";"BarracksReactor";NA;73;0
"Unit";"Marine";"Barracks";76;1
"Unit";"SCV";"Command Center";78;1
"Unit";"SCV";"Command Center";79;1
"Building";"Barracks";NA;73;0
"Unit";"Marine";"Barracks";79;1
"Unit";"Marine";"Barracks";79;1
"Building";"Barracks";NA;73;0
"Unit";"Marine";"Barracks";80;1
"Unit";"SCV";"Command Center";81;1
"Building";"SupplyDepot";NA;79;0
"Unit";"SCV";"Command Center";82;1
"Unit";"SCV";"Command Center";83;1
"Unit";"Marine";"Barracks";82;1
"Unit";"Marine";"Barracks";82;1
"Unit";"SCV";"Command Center";86;1
"Unit";"Marine";"Barracks";83;1
"Unit";"Marine";"Barracks";84;1
"Unit";"SCV";"Command Center";87;1
"Unit";"SCV";"Command Center";88;1
"Building";"MissileTurret";NA;87;0
"Building";"Refinery";NA;87;0
"Unit";"Marine";"Barracks";88;1
"Building";"SupplyDepot";NA;87;0
"Unit";"SCV";"Command Center";91;1
"Building";"Refinery";NA;87;0
"Unit";"Marine";"Barracks";89;1
"Unit";"Marine";"Barracks";90;1
"Unit";"SCV";"Command Center";94;1
"Unit";"SCV";"Command Center";95;1
"Building";"BarracksReactor";NA;85;0
"Building";"BarracksReactor";NA;85;0
"Unit";"Marine";"Barracks";94;1
"Unit";"Marine";"Barracks";94;1
"Unit";"SCV";"Command Center";97;1
"Unit";"Marine";"Barracks";96;1
"Unit";"SCV";"Command Center";100;1
"Unit";"SCV";"Command Center";101;1
"Unit";"Medivac";"Starport";94;2
"Unit";"Medivac";"Starport";94;2
"Building";"SupplyDepot";NA;96;0
"Unit";"Marine";"Barracks";98;1
"Unit";"Marine";"Barracks";100;1
"Unit";"Marine";"Barracks";102;1
"Building";"SupplyDepot";NA;104;0
"Building";"SupplyDepot";NA;105;0
"Unit";"Marine";"Barracks";112;1
"Unit";"Marine";"Barracks";112;1
"Unit";"Marine";"Barracks";112;1
"Unit";"Marine";"Barracks";112;1
"Unit";"Marine";"Barracks";112;1
"Unit";"Marine";"Barracks";112;1
"Unit";"Marine";"Barracks";112;1
"Upgrade";"Stimpack";"TechLab";80;0
"Building";"SensorTower";NA;115;0
"Building";"MissileTurret";NA;115;0
"Building";"MissileTurret";NA;115;0
"Unit";"Marine";"Barracks";121;1
"Unit";"Marine";"Barracks";122;1
"Unit";"Marine";"Barracks";122;1
"Unit";"Marine";"Barracks";122;1
"Unit";"Marine";"Barracks";122;1
"Unit";"Medivac";"Starport";115;2
"Unit";"Medivac";"Starport";115;2
"Building";"MissileTurret";NA;122;0
"Upgrade";"TerranInfantryWeaponsLevel1";"EngineeringBay";91;0
"Building";"Armory";NA;115;0
"Unit";"Marine";"Barracks";127;1
"Unit";"Marine";"Barracks";127;1
"Unit";"Marine";"Barracks";127;1
"Unit";"Marine";"Barracks";127;1
"Unit";"Marine";"Barracks";127;1
"Upgrade";"TerranInfantryArmorsLevel1";"EngineeringBay";98;0
"Unit";"Marine";"Barracks";131;1
"Unit";"Marine";"Barracks";131;1
"Unit";"Marine";"Barracks";131;1
"Unit";"Marine";"Barracks";131;1
"Unit";"Marine";"Barracks";131;1
"Unit";"Marine";"Barracks";136;1
"Unit";"Marine";"Barracks";136;1
"Building";"SupplyDepot";NA;136;0
"Building";"SupplyDepot";NA;136;0
"Unit";"Medivac";"Starport";131;2
"Building";"Factory";NA;131;0
"Building";"CommandCenter";NA;122;0
"Building";"MissileTurret";NA;136;0
"Unit";"Medivac";"Starport";136;2
"Unit";"Marine";"Barracks";143;1
"Unit";"Marine";"Barracks";143;1
"Unit";"Marine";"Barracks";143;1
"Unit";"Marine";"Barracks";143;1
"Unit";"Marine";"Barracks";143;1
"Unit";"Marine";"Barracks";143;1
"Unit";"Marine";"Barracks";143;1
"Unit";"Marine";"Barracks";143;1
"Unit";"Marine";"Barracks";143;1
"Unit";"Marine";"Barracks";147;1
"Unit";"Marine";"Barracks";148;1
"Unit";"Marine";"Barracks";149;1
"Unit";"Marine";"Barracks";149;1
"Unit";"Marine";"Barracks";151;1
"Unit";"Marine";"Barracks";152;1
"Unit";"Marine";"Barracks";152;1
"Unit";"Marine";"Barracks";156;1
"Unit";"Marine";"Barracks";156;1
"Building";"SensorTower";NA;156;0
"Building";"FactoryTechLab";NA;156;0
"Unit";"Marine";"Barracks";156;1
"Unit";"Marine";"Barracks";157;1
"Unit";"Marine";"Barracks";158;1
"Unit";"Marine";"Barracks";158;1
"Unit";"Marine";"Barracks";160;1
"Unit";"Marine";"Barracks";163;1
"Unit";"Marine";"Barracks";163;1
"Unit";"Marine";"Barracks";163;1
"Unit";"Marine";"Barracks";164;1
"Unit";"Marine";"Barracks";165;1
"Unit";"Marine";"Barracks";166;1
"Unit";"Marine";"Barracks";167;1
"Unit";"Marine";"Barracks";174;1
"Unit";"Marine";"Barracks";174;1
"Unit";"Marine";"Barracks";174;1
"Unit";"Marine";"Barracks";174;1
"Unit";"Marine";"Barracks";174;1
"Unit";"Marine";"Barracks";174;1
"Unit";"Medivac";"Starport";165;2
"Unit";"Medivac";"Starport";165;2
"Unit";"SCV";"Command Center";177;1
"Unit";"SCV";"Command Center";177;1
"Building";"Barracks";NA;163;0
"Building";"Barracks";NA;165;0
"Unit";"Marine";"Barracks";174;1
"Building";"Barracks";NA;165;0
"Unit";"Marine";"Barracks";175;1
"Unit";"Marine";"Barracks";176;1
"Building";"SupplyDepot";NA;174;0
"Building";"SupplyDepot";NA;177;0
"Building";"SupplyDepot";NA;183;0
"Building";"SupplyDepot";NA;187;0
"Unit";"SCV";"Command Center";192;1
"Unit";"SCV";"Command Center";192;1
"Unit";"SCV";"Command Center";192;1
"Unit";"SCV";"Command Center";192;1
"Upgrade";"TerranInfantryWeaponsLevel2";"EngineeringBay";156;0
"Upgrade";"TerranInfantryArmorsLevel2";"EngineeringBay";156;0
