"type";"unit_name";"on_building";"total_supply_lag";"supply"
"Building";"Refinery";NA;15;0
"Building";"Barracks";NA;16;0
"Unit";"Reaper";"Barracks";19;1
"Building";"CommandCenter";NA;20;0
"Building";"Factory";NA;20;0
"Building";"BarracksReactor";NA;21;0
"Building";"Refinery";NA;21;0
"Building";"Starport";NA;24;0
"Unit";"Marine";"Barracks";24;1
"Unit";"Marine";"Barracks";27;1
"Unit";"Medivac";"Starport";29;2
"Unit";"Marine";"Barracks";32;1
"Unit";"Marine";"Barracks";36;1
"Building";"CommandCenter";NA;40;0
"Unit";"Marine";"Barracks";41;1
"Unit";"Marine";"Barracks";42;1
"Building";"StarportReactor";NA;45;0
"Building";"FactoryTechLab";NA;45;0
"Building";"Barracks";NA;45;0
"Building";"Barracks";NA;45;0
"Unit";"Marine";"Barracks";45;1
"Unit";"Marine";"Barracks";46;1
"Building";"Refinery";NA;49;0
"Building";"Barracks";NA;52;0
"Building";"Barracks";NA;52;0
"Building";"FactoryReactor";NA;54;0
"Building";"EngineeringBay";NA;54;0
"Building";"EngineeringBay";NA;54;0
"Building";"StarportReactor";NA;55;0
"Unit";"Marine";"Barracks";55;1
"Unit";"Marine";"Barracks";57;1
"Unit";"Marine";"Barracks";58;1
"Unit";"Marine";"Barracks";59;1
"Unit";"Marine";"Barracks";60;1
"Building";"Refinery";NA;61;0
"Building";"BarracksTechLab";NA;63;0
"Building";"BarracksTechLab";NA;63;0
"Unit";"Marine";"Barracks";63;1
"Unit";"Marine";"Barracks";64;1
"Unit";"Marine";"Barracks";65;1
"Unit";"Marine";"Barracks";68;1
"Unit";"Marine";"Barracks";69;1
"Unit";"Medivac";"Starport";70;2
"Unit";"Medivac";"Starport";72;2
"Upgrade";"Stimpack";"TechLab";74;0
"Upgrade";"TerranInfantryWeaponsLevel1";"EngineeringBay";75;0
"Unit";"Marine";"Barracks";76;1
"Unit";"Marine";"Barracks";77;1
"Unit";"Marine";"Barracks";78;1
"Unit";"Marauder";"Barracks";81;2
"Unit";"Marauder";"Barracks";83;2
"Unit";"Marine";"Barracks";85;1
"Unit";"Marauder";"Barracks";86;2
"Unit";"Marauder";"Barracks";92;2
"Unit";"Medivac";"Starport";94;2
"Unit";"Medivac";"Starport";96;2
"Building";"Refinery";NA;98;0
"Unit";"Marine";"Barracks";99;1
"Unit";"Marine";"Barracks";100;1
"Unit";"Marine";"Barracks";101;1
"Unit";"Marine";"Barracks";102;1
"Building";"Barracks";NA;104;0
"Building";"Barracks";NA;104;0
"Building";"Barracks";NA;104;0
"Unit";"Marine";"Barracks";106;1
"Unit";"Marauder";"Barracks";108;2
"Unit";"Marauder";"Barracks";110;2
"Unit";"Marine";"Barracks";112;1
"Unit";"Marine";"Barracks";113;1
"Building";"Armory";NA;114;0
"Unit";"Medivac";"Starport";116;2
"Unit";"Medivac";"Starport";118;2
"Unit";"Marauder";"Barracks";120;2
"Unit";"Marauder";"Barracks";123;2
"Unit";"Marauder";"Barracks";125;2
"Unit";"Marine";"Barracks";128;1
"Unit";"Marine";"Barracks";129;1
"Building";"BarracksTechLab";NA;130;0
"Building";"BarracksTechLab";NA;130;0
"Building";"BarracksTechLab";NA;130;0
"Unit";"Marauder";"Barracks";130;2
"Unit";"Medivac";"Starport";132;2
"Unit";"Medivac";"Starport";134;2
"Unit";"Marauder";"Barracks";136;2
"Unit";"Marauder";"Barracks";138;2
"Unit";"Marine";"Barracks";140;1
"Unit";"Marine";"Barracks";141;1
"Unit";"Marauder";"Barracks";142;2
"Unit";"Marauder";"Barracks";144;2
"Unit";"Marauder";"Barracks";146;2
"Unit";"Marauder";"Barracks";148;2
"Unit";"Marine";"Barracks";150;1
"Unit";"Marine";"Barracks";151;1
"Unit";"Marauder";"Barracks";152;2
"Unit";"Marauder";"Barracks";154;2
"Unit";"Marine";"Barracks";156;1
"Unit";"Marine";"Barracks";157;1
"Unit";"Marauder";"Barracks";158;2
"Unit";"Marine";"Barracks";160;1
"Unit";"Medivac";"Starport";161;2
"Unit";"Medivac";"Starport";163;2
"Unit";"Marine";"Barracks";165;1
"Unit";"Marine";"Barracks";166;1
"Unit";"Marauder";"Barracks";167;2
"Unit";"Marauder";"Barracks";169;2
"Unit";"Marauder";"Barracks";171;2
"Unit";"Marauder";"Barracks";173;2
"Upgrade";"TerranInfantryWeaponsLevel2";"EngineeringBay";175;0
"Unit";"Marauder";"Barracks";175;2
"Unit";"Marauder";"Barracks";177;2
"Unit";"Medivac";"Starport";181;2
"Unit";"Marauder";"Barracks";183;2
"Unit";"Marauder";"Barracks";185;2
"Unit";"Medivac";"Starport";187;2
"Unit";"Marauder";"Barracks";189;2
"Unit";"Marauder";"Barracks";191;2
"Unit";"Marine";"Barracks";193;1
"Unit";"Marine";"Barracks";194;1
"Unit";"Marine";"Barracks";196;1
"Unit";"Marine";"Barracks";197;1
"Unit";"Marine";"Barracks";198;1
"Unit";"Marauder";"Barracks";199;2
"Unit";"Marauder";"Barracks";201;2
"Unit";"Marauder";"Barracks";203;2
"Unit";"Marauder";"Barracks";205;2
"Unit";"Marauder";"Barracks";207;2
"Unit";"Marine";"Barracks";209;1
"Unit";"Marine";"Barracks";210;1
"Unit";"Marine";"Barracks";211;1
"Unit";"Marine";"Barracks";212;1
"Unit";"Marauder";"Barracks";213;2
"Unit";"Marine";"Barracks";215;1
"Unit";"Marine";"Barracks";216;1
"Unit";"Liberator";"Starport";217;3
"Unit";"Liberator";"Starport";220;3
"Unit";"Marauder";"Barracks";223;2
"Unit";"Marauder";"Barracks";225;2
"Unit";"Marauder";"Barracks";227;2
"Unit";"Marine";"Barracks";229;1
"Unit";"Marine";"Barracks";230;1
"Unit";"Marauder";"Barracks";231;2
"Unit";"Marine";"Barracks";233;1
"Unit";"Marine";"Barracks";234;1
"Unit";"Marauder";"Barracks";235;2
"Unit";"Marauder";"Barracks";237;2
"Unit";"Marauder";"Barracks";239;2
"Unit";"Marauder";"Barracks";241;2
"Upgrade";"SprayTerran";NA;243;0
"Upgrade";"SprayTerran";NA;243;0
"Upgrade";"SprayTerran";NA;243;0
"Upgrade";"SprayTerran";NA;243;0
"Upgrade";"PunisherGrenades";NA;243;0
"Upgrade";"ShieldWall";NA;243;0
"Upgrade";"TerranInfantryArmorsLevel1";NA;243;0
"Upgrade";"SprayTerran";NA;243;0
"Upgrade";"TerranInfantryArmorsLevel2";NA;243;0
