"type";"unit_name";"on_building";"total_supply_lag";"supply"
"Building";"Barracks";NA;16;0
"Unit";"Marine";"Barracks";19;1
"Building";"CommandCenter";NA;20;0
"Unit";"Marine";"Barracks";20;1
"Unit";"Marine";"Barracks";22;1
"Building";"CommandCenter";NA;24;0
"Unit";"Marine";"Barracks";25;1
"Building";"Barracks";NA;27;0
"Unit";"Marine";"Barracks";27;1
"Building";"Barracks";NA;28;0
"Unit";"Marine";"Barracks";30;1
"Building";"Refinery";NA;31;0
"Building";"Refinery";NA;32;0
"Unit";"Marine";"Barracks";32;1
"Building";"EngineeringBay";NA;34;0
"Unit";"Marine";"Barracks";35;1
"Unit";"Marine";"Barracks";36;1
"Building";"BarracksTechLab";NA;39;0
"Building";"MissileTurret";NA;39;0
"Unit";"Marine";"Barracks";39;1
"Unit";"Marine";"Barracks";42;1
"Unit";"Marine";"Barracks";44;1
"Unit";"Marine";"Barracks";48;1
"Unit";"Marine";"Barracks";50;1
"Unit";"Marine";"Barracks";52;1
"Unit";"Marine";"Barracks";56;1
"Upgrade";"Stimpack";"TechLab";57;0
"Unit";"Marine";"Barracks";57;1
"Unit";"Marine";"Barracks";58;1
"Building";"Factory";NA;59;0
"Building";"Refinery";NA;62;0
"Building";"Refinery";NA;62;0
"Upgrade";"TerranInfantryWeaponsLevel1";"EngineeringBay";64;0
"Building";"BarracksTechLab";NA;64;0
"Building";"BarracksReactor";NA;64;0
"Unit";"Marine";"Barracks";67;1
"Unit";"Marine";"Barracks";68;1
"Building";"MissileTurret";NA;70;0
"Building";"Starport";NA;71;0
"Building";"FactoryReactor";NA;71;0
"Building";"Barracks";NA;72;0
"Building";"Barracks";NA;72;0
"Unit";"Marauder";"Barracks";75;2
"Unit";"Marauder";"Barracks";77;2
"Unit";"Marine";"Barracks";79;1
"Unit";"Marine";"Barracks";83;1
"Unit";"Marine";"Barracks";84;1
"Unit";"Marauder";"Barracks";87;2
"Unit";"Marauder";"Barracks";89;2
"Unit";"Medivac";"Starport";92;2
"Unit";"Medivac";"Starport";94;2
"Building";"FactoryReactor";NA;96;0
"Building";"BarracksTechLab";NA;102;0
"Building";"BarracksReactor";NA;102;0
"Unit";"Marauder";"Barracks";102;2
"Unit";"Marauder";"Barracks";105;2
"Unit";"Marine";"Barracks";107;1
"Unit";"Marine";"Barracks";108;1
"Unit";"Medivac";"Starport";110;2
"Unit";"Medivac";"Starport";112;2
"Building";"Refinery";NA;118;0
"Unit";"Marauder";"Barracks";120;2
"Unit";"Marine";"Barracks";122;1
"Unit";"Marine";"Barracks";123;1
"Building";"Barracks";NA;124;0
"Building";"Barracks";NA;124;0
"Building";"Barracks";NA;124;0
"Unit";"Marine";"Barracks";124;1
"Unit";"Marauder";"Barracks";125;2
"Building";"Refinery";NA;128;0
"Unit";"Marauder";"Barracks";129;2
"Unit";"Marauder";"Barracks";131;2
"Unit";"Marine";"Barracks";133;1
"Unit";"Marine";"Barracks";134;1
"Unit";"Marauder";"Barracks";136;2
"Unit";"Marine";"Barracks";138;1
"Building";"EngineeringBay";NA;139;0
"Building";"Armory";NA;139;0
"Unit";"Marauder";"Barracks";139;2
"Unit";"Marauder";"Barracks";141;2
"Unit";"Marine";"Barracks";143;1
"Unit";"Marine";"Barracks";144;1
"Unit";"Marine";"Barracks";145;1
"Unit";"Marauder";"Barracks";147;2
"Building";"BarracksTechLab";NA;149;0
"Building";"BarracksTechLab";NA;149;0
"Building";"BarracksReactor";NA;149;0
"Unit";"Marine";"Barracks";149;1
"Unit";"Marauder";"Barracks";150;2
"Unit";"Marauder";"Barracks";152;2
"Unit";"Marine";"Barracks";154;1
"Unit";"Marine";"Barracks";155;1
"Unit";"Marine";"Barracks";156;1
"Unit";"Medivac";"Starport";157;2
"Unit";"Medivac";"Starport";159;2
"Unit";"Marauder";"Barracks";161;2
"Unit";"Marine";"Barracks";163;1
"Unit";"Marine";"Barracks";164;1
"Unit";"Marine";"Barracks";165;1
"Unit";"Marine";"Barracks";166;1
"Building";"CommandCenter";NA;167;0
"Unit";"Marine";"Barracks";167;1
"Unit";"Marine";"Barracks";168;1
"Unit";"Marine";"Barracks";169;1
"Unit";"Marine";"Barracks";170;1
"Unit";"Marine";"Barracks";171;1
"Unit";"Marauder";"Barracks";172;2
"Unit";"Marine";"Barracks";174;1
"Unit";"Marauder";"Barracks";175;2
"Unit";"Marauder";"Barracks";177;2
"Unit";"Marauder";"Barracks";179;2
"Building";"MissileTurret";NA;181;0
"Building";"MissileTurret";NA;181;0
"Unit";"Liberator";"Starport";181;3
"Unit";"Liberator";"Starport";184;3
"Unit";"Marine";"Barracks";187;1
"Unit";"Marine";"Barracks";188;1
"Unit";"Marine";"Barracks";189;1
"Unit";"Marine";"Barracks";190;1
"Unit";"Marine";"Barracks";191;1
"Unit";"Marine";"Barracks";192;1
"Unit";"Marine";"Barracks";193;1
"Unit";"Marauder";"Barracks";194;2
"Unit";"Marauder";"Barracks";196;2
"Unit";"Marauder";"Barracks";198;2
"Unit";"Marine";"Barracks";200;1
"Building";"GhostAcademy";NA;204;0
"Unit";"Marauder";"Barracks";204;2
"Unit";"Marine";"Barracks";206;1
"Unit";"Marine";"Barracks";207;1
"Unit";"Marine";"Barracks";208;1
"Unit";"Marine";"Barracks";209;1
"Unit";"Marine";"Barracks";210;1
"Unit";"Marine";"Barracks";211;1
"Unit";"Marauder";"Barracks";212;2
"Unit";"Marine";"Barracks";214;1
"Unit";"Marine";"Barracks";215;1
"Unit";"Marine";"Barracks";216;1
"Unit";"Liberator";"Starport";217;3
"Unit";"Marine";"Barracks";220;1
"Unit";"Marine";"Barracks";221;1
"Unit";"Marine";"Barracks";222;1
"Unit";"Marine";"Barracks";223;1
"Unit";"Marine";"Barracks";224;1
"Unit";"Marine";"Barracks";225;1
"Unit";"Ghost";"Barracks";226;2
"Upgrade";"SprayTerran";NA;228;0
"Upgrade";"SprayTerran";NA;228;0
"Upgrade";"SprayTerran";NA;228;0
"Upgrade";"SprayTerran";NA;228;0
"Upgrade";"ShieldWall";NA;228;0
"Upgrade";"PunisherGrenades";NA;228;0
"Upgrade";"SprayTerran";NA;228;0
"Upgrade";"TerranInfantryArmorsLevel1";NA;228;0
"Upgrade";"SprayTerran";NA;228;0
