"type";"unit_name";"on_building";"total_supply_lag";"supply"
"Building";"Barracks";NA;16;0
"Building";"Refinery";NA;16;0
"Unit";"Marine";"Barracks";19;1
"Building";"CommandCenter";NA;20;0
"Building";"Factory";NA;20;0
"Building";"BarracksReactor";NA;21;0
"Building";"Refinery";NA;22;0
"Unit";"Marine";"Barracks";24;1
"Unit";"Marine";"Barracks";25;1
"Building";"Starport";NA;27;0
"Unit";"Marine";"Barracks";28;1
"Unit";"Marine";"Barracks";29;1
"Unit";"Medivac";"Starport";31;2
"Unit";"Marine";"Barracks";34;1
"Unit";"Marine";"Barracks";35;1
"Unit";"Marine";"Barracks";40;1
"Unit";"Marine";"Barracks";41;1
"Unit";"Medivac";"Starport";43;2
"Building";"EngineeringBay";NA;46;0
"Unit";"Marine";"Barracks";47;1
"Unit";"Marine";"Barracks";49;1
"Building";"FactoryTechLab";NA;51;0
"Unit";"Liberator";"Starport";51;3
"Unit";"Marine";"Barracks";56;1
"Unit";"Marine";"Barracks";57;1
"Unit";"Marine";"Barracks";60;1
"Unit";"Marine";"Barracks";61;1
"Unit";"Marine";"Barracks";65;1
"Unit";"Liberator";"Starport";67;3
"Unit";"Marine";"Barracks";70;1
"Building";"CommandCenter";NA;72;0
"Unit";"Marine";"Barracks";73;1
"Building";"Refinery";NA;74;0
"Building";"Refinery";NA;74;0
"Building";"Barracks";NA;76;0
"Building";"Barracks";NA;76;0
"Unit";"Marine";"Barracks";77;1
"Unit";"Marine";"Barracks";78;1
"Building";"MissileTurret";NA;82;0
"Unit";"Marine";"Barracks";82;1
"Unit";"Marine";"Barracks";84;1
"Building";"MissileTurret";NA;86;0
"Upgrade";"TerranInfantryWeaponsLevel1";"EngineeringBay";86;0
"Building";"Barracks";NA;88;0
"Building";"Barracks";NA;88;0
"Building";"BarracksTechLab";NA;88;0
"Building";"BarracksTechLab";NA;88;0
"Building";"StarportReactor";NA;89;0
"Unit";"Marine";"Barracks";89;1
"Unit";"Marine";"Barracks";90;1
"Unit";"Marine";"Barracks";93;1
"Unit";"Marine";"Barracks";94;1
"Unit";"Marine";"Barracks";95;1
"Unit";"Marine";"Barracks";96;1
"Building";"BarracksTechLab";NA;99;0
"Building";"BarracksReactor";NA;99;0
"Unit";"Marine";"Barracks";100;1
"Unit";"Marine";"Barracks";101;1
"Upgrade";"Stimpack";"TechLab";102;0
"Building";"MissileTurret";NA;103;0
"Unit";"Marine";"Barracks";103;1
"Unit";"Marine";"Barracks";104;1
"Unit";"Medivac";"Starport";105;2
"Unit";"Marine";"Barracks";107;1
"Unit";"Medivac";"Starport";108;2
"Unit";"Marine";"Barracks";111;1
"Unit";"Marauder";"Barracks";112;2
"Unit";"Marine";"Barracks";114;1
"Unit";"Marauder";"Barracks";115;2
"Building";"Refinery";NA;117;0
"Unit";"Marine";"Barracks";117;1
"Building";"Refinery";NA;118;0
"Building";"Bunker";NA;118;0
"Unit";"Marine";"Barracks";118;1
"Unit";"Marine";"Barracks";119;1
"Unit";"Medivac";"Starport";120;2
"Unit";"Marine";"Barracks";122;1
"Unit";"Marauder";"Barracks";123;2
"Unit";"Marauder";"Barracks";125;2
"Unit";"Marauder";"Barracks";127;2
"Unit";"Marine";"Barracks";129;1
"Unit";"Marine";"Barracks";130;1
"Building";"Factory";NA;131;0
"Unit";"Marine";"Barracks";131;1
"Unit";"Marauder";"Barracks";132;2
"Unit";"Marauder";"Barracks";134;2
"Unit";"Marauder";"Barracks";136;2
"Unit";"Marine";"Barracks";138;1
"Unit";"Marine";"Barracks";139;1
"Unit";"Medivac";"Starport";140;2
"Unit";"Medivac";"Starport";142;2
"Building";"Barracks";NA;144;0
"Unit";"Marine";"Barracks";144;1
"Building";"Barracks";NA;145;0
"Unit";"Marine";"Barracks";145;1
"Building";"Barracks";NA;146;0
"Unit";"Marauder";"Barracks";146;2
"Unit";"Marauder";"Barracks";148;2
"Unit";"Marine";"Barracks";150;1
"Unit";"Marine";"Barracks";151;1
"Unit";"Marine";"Barracks";152;1
"Unit";"Marine";"Barracks";153;1
"Building";"Armory";NA;154;0
"Building";"FactoryTechLab";NA;154;0
"Unit";"Marine";"Barracks";154;1
"Building";"EngineeringBay";NA;155;0
"Unit";"Marine";"Barracks";155;1
"Unit";"Medivac";"Starport";156;2
"Unit";"Medivac";"Starport";158;2
"Unit";"Marine";"Barracks";160;1
"Unit";"Marauder";"Barracks";161;2
"Unit";"Marine";"Barracks";163;1
"Unit";"Marine";"Barracks";164;1
"Unit";"Marauder";"Barracks";165;2
"Unit";"Marine";"Barracks";167;1
"Building";"BarracksTechLab";NA;168;0
"Building";"BarracksTechLab";NA;168;0
"Unit";"Marine";"Barracks";168;1
"Unit";"Marine";"Barracks";169;1
"Unit";"Marine";"Barracks";170;1
"Unit";"Marine";"Barracks";171;1
"Unit";"Marauder";"Barracks";172;2
"Unit";"Marine";"Barracks";174;1
"Unit";"Marine";"Barracks";175;1
"Unit";"Marine";"Barracks";176;1
"Unit";"Marauder";"Barracks";177;2
"Unit";"Marine";"Barracks";179;1
"Unit";"Marauder";"Barracks";180;2
"Unit";"Marine";"Barracks";182;1
"Unit";"Marine";"Barracks";183;1
"Unit";"Marine";"Barracks";184;1
"Unit";"Marauder";"Barracks";185;2
"Unit";"Marine";"Barracks";187;1
"Unit";"Marauder";"Barracks";188;2
"Unit";"Marine";"Barracks";190;1
"Unit";"Marauder";"Barracks";191;2
"Upgrade";"SprayTerran";NA;193;0
"Upgrade";"SprayTerran";NA;193;0
"Upgrade";"SprayTerran";NA;193;0
"Upgrade";"SprayTerran";NA;193;0
"Upgrade";"ShieldWall";NA;193;0
"Upgrade";"PunisherGrenades";NA;193;0
"Upgrade";"TerranInfantryArmorsLevel1";NA;193;0
"Upgrade";"SprayTerran";NA;193;0
