"type";"unit_name";"on_building";"total_supply_lag";"supply"
"Building";"Barracks";NA;16;0
"Building";"Refinery";NA;16;0
"Unit";"Marine";"Barracks";19;1
"Building";"CommandCenter";NA;20;0
"Building";"Factory";NA;20;0
"Building";"BarracksReactor";NA;21;0
"Building";"Refinery";NA;22;0
"Unit";"Marine";"Barracks";24;1
"Unit";"Marine";"Barracks";25;1
"Building";"Starport";NA;26;0
"Unit";"Marine";"Barracks";27;1
"Unit";"Marine";"Barracks";28;1
"Unit";"Medivac";"Starport";31;2
"Unit";"Marine";"Barracks";33;1
"Unit";"Marine";"Barracks";34;1
"Unit";"Marine";"Barracks";38;1
"Unit";"Marine";"Barracks";39;1
"Unit";"Medivac";"Starport";42;2
"Building";"EngineeringBay";NA;44;0
"Unit";"Marine";"Barracks";44;1
"Unit";"Marine";"Barracks";45;1
"Unit";"Marine";"Barracks";49;1
"Unit";"Marine";"Barracks";50;1
"Building";"FactoryTechLab";NA;52;0
"Unit";"Liberator";"Starport";52;3
"Building";"MissileTurret";NA;55;0
"Building";"MissileTurret";NA;55;0
"Unit";"Marine";"Barracks";56;1
"Unit";"Marine";"Barracks";57;1
"Unit";"Marine";"Barracks";61;1
"Unit";"Marine";"Barracks";62;1
"Unit";"Liberator";"Starport";64;3
"Unit";"Marine";"Barracks";70;1
"Unit";"Marine";"Barracks";71;1
"Unit";"Marine";"Barracks";74;1
"Unit";"Marine";"Barracks";75;1
"Building";"CommandCenter";NA;77;0
"Unit";"Marine";"Barracks";80;1
"Unit";"Marine";"Barracks";82;1
"Building";"Barracks";NA;83;0
"Building";"Barracks";NA;84;0
"Unit";"Marine";"Barracks";85;1
"Building";"Barracks";NA;86;0
"Building";"Barracks";NA;87;0
"Unit";"Marine";"Barracks";89;1
"Unit";"Marine";"Barracks";90;1
"Building";"Refinery";NA;91;0
"Building";"Refinery";NA;92;0
"Building";"BarracksTechLab";NA;94;0
"Building";"BarracksTechLab";NA;94;0
"Building";"MissileTurret";NA;96;0
"Building";"BarracksTechLab";NA;97;0
"Building";"BarracksReactor";NA;97;0
"Building";"MissileTurret";NA;98;0
"Unit";"Marine";"Barracks";98;1
"Unit";"Marine";"Barracks";99;1
"Building";"MissileTurret";NA;100;0
"Building";"StarportReactor";NA;100;0
"Building";"MissileTurret";NA;100;0
"Unit";"Marine";"Barracks";100;1
"Unit";"Marine";"Barracks";101;1
"Upgrade";"Stimpack";"TechLab";103;0
"Unit";"Marauder";"Barracks";103;2
"Unit";"Marine";"Barracks";105;1
"Unit";"Marine";"Barracks";106;1
"Unit";"Marine";"Barracks";107;1
"Unit";"Marine";"Barracks";108;1
"Unit";"Marine";"Barracks";109;1
"Unit";"Marauder";"Barracks";110;2
"Unit";"Marine";"Barracks";112;1
"Upgrade";"TerranInfantryWeaponsLevel1";"EngineeringBay";113;0
"Unit";"Marine";"Barracks";113;1
"Unit";"Marine";"Barracks";114;1
"Unit";"Marine";"Barracks";116;1
"Unit";"Marauder";"Barracks";117;2
"Unit";"Medivac";"Starport";119;2
"Unit";"Marauder";"Barracks";123;2
"Unit";"Marauder";"Barracks";125;2
"Unit";"Marine";"Barracks";127;1
"Unit";"Marine";"Barracks";129;1
"Unit";"Marine";"Barracks";130;1
"Unit";"Medivac";"Starport";131;2
"Unit";"Marine";"Barracks";133;1
"Unit";"Marine";"Barracks";134;1
"Unit";"Marine";"Barracks";135;1
"Building";"Factory";NA;136;0
"Unit";"Marine";"Barracks";136;1
"Unit";"Marauder";"Barracks";137;2
"Unit";"Medivac";"Starport";139;2
"Unit";"Marine";"Barracks";141;1
"Unit";"Marine";"Barracks";142;1
"Unit";"Marauder";"Barracks";143;2
"Unit";"Marine";"Barracks";145;1
"Building";"MissileTurret";NA;146;0
"Unit";"Medivac";"Starport";146;2
"Unit";"Marine";"Barracks";148;1
"Unit";"Marauder";"Barracks";149;2
"Unit";"Marine";"Barracks";151;1
"Unit";"Medivac";"Starport";152;2
"Unit";"Marine";"Barracks";154;1
"Unit";"Marauder";"Barracks";155;2
"Building";"Refinery";NA;157;0
"Building";"Refinery";NA;157;0
"Unit";"Marine";"Barracks";157;1
"Unit";"Marauder";"Barracks";158;2
"Unit";"Marine";"Barracks";160;1
"Unit";"Marine";"Barracks";161;1
"Unit";"Marauder";"Barracks";162;2
"Unit";"Marine";"Barracks";164;1
"Unit";"Marauder";"Barracks";165;2
"Unit";"Marauder";"Barracks";167;2
"Unit";"Marine";"Barracks";171;1
"Unit";"Marauder";"Barracks";172;2
"Unit";"Marine";"Barracks";174;1
"Building";"CommandCenter";NA;175;0
"Unit";"Marauder";"Barracks";175;2
"Unit";"Marine";"Barracks";178;1
"Unit";"Marauder";"Barracks";179;2
"Unit";"Marine";"Barracks";181;1
"Unit";"Marine";"Barracks";182;1
"Unit";"Marine";"Barracks";183;1
"Unit";"Marauder";"Barracks";184;2
"Unit";"Marauder";"Barracks";186;2
"Unit";"Marine";"Barracks";188;1
"Building";"Factory";NA;189;0
"Unit";"Marine";"Barracks";189;1
"Unit";"Marauder";"Barracks";190;2
"Unit";"Marine";"Barracks";192;1
"Unit";"Marauder";"Barracks";193;2
"Unit";"Marine";"Barracks";195;1
"Unit";"Marauder";"Barracks";196;2
"Unit";"Marine";"Barracks";198;1
"Unit";"Medivac";"Starport";199;2
"Unit";"Marine";"Barracks";201;1
"Unit";"Marauder";"Barracks";202;2
"Unit";"Marauder";"Barracks";204;2
"Unit";"Marine";"Barracks";206;1
"Unit";"Marauder";"Barracks";207;2
"Unit";"Marine";"Barracks";209;1
"Unit";"Marine";"Barracks";210;1
"Unit";"Marine";"Barracks";211;1
"Upgrade";"SprayTerran";NA;212;0
"Upgrade";"SprayTerran";NA;212;0
"Upgrade";"SprayTerran";NA;212;0
"Upgrade";"SprayTerran";NA;212;0
"Upgrade";"PunisherGrenades";NA;212;0
"Upgrade";"ShieldWall";NA;212;0
"Upgrade";"SprayTerran";NA;212;0
"Upgrade";"SprayTerran";NA;212;0
