"type";"unit_name";"on_building";"total_supply";"supply"
"Building";"Pylon";NA;13;0
"Building";"Assimilator";NA;16;0
"Building";"Gateway";NA;15;0
"Building";"Assimilator";NA;21;0
"Building";"Pylon";NA;21;0
"Building";"CyberneticsCore";NA;20;0
"Unit";"Adept";"Gateway";22;2
"Building";"Nexus";NA;19;0
"Unit";"Adept";"Gateway";24;2
"Building";"Stargate";NA;23;0
"Unit";"Adept";"Gateway";29;2
"Unit";"Oracle";"Stargate";32;3
"Building";"ShieldBattery";NA;36;0
"Building";"Pylon";NA;39;0
"Unit";"Sentry";"Gateway";38;2
"Building";"Assimilator";NA;42;0
"Building";"Assimilator";NA;43;0
"Building";"Gateway";NA;35;0
"Building";"Pylon";NA;46;0
"Unit";"Phoenix";"Stargate";46;2
"Building";"RoboticsFacility";NA;46;0
"Building";"TwilightCouncil";NA;50;0
"Building";"Gateway";NA;50;0
"Building";"Gateway";NA;53;0
"Building";"Pylon";NA;56;0
"Building";"Pylon";NA;56;0
"Building";"Gateway";NA;54;0
"Building";"TemplarArchive";NA;56;0
"Building";"Gateway";NA;56;0
"Building";"Pylon";NA;57;0
"Building";"HighTemplar";NA;58;0
"Building";"HighTemplar";NA;58;0
"Building";"HighTemplar";NA;58;0
"Building";"HighTemplar";NA;58;0
"Unit";"Archon";"High Templar";58;0
"Unit";"Archon";"High Templar";58;0
"Building";"Pylon";NA;58;0
"Building";"Pylon";NA;58;0
"Unit";"Zealot";"Gateway";59;2
"Unit";"Zealot";"Gateway";59;2
"Upgrade";"Charge";"TwilightCouncil";56;0
"Building";"Pylon";NA;58;0
"Unit";"Zealot";"Gateway";63;2
"Unit";"Zealot";"Gateway";63;2
"Unit";"Zealot";"Gateway";63;2
"Unit";"Zealot";"Gateway";63;2
"Unit";"Zealot";"Gateway";71;2
"Unit";"Zealot";"Gateway";71;2
"Unit";"Zealot";"Gateway";71;2
"Unit";"Zealot";"Gateway";71;2
"Unit";"Zealot";"Gateway";71;2
"Building";"Nexus";NA;58;0
"Unit";"Zealot";"Gateway";81;2
"Building";"HighTemplar";NA;83;0
"Building";"HighTemplar";NA;83;0
"Building";"HighTemplar";NA;83;0
"Building";"HighTemplar";NA;83;0
"Unit";"Immortal";"Robotics Facility";81;4
"Unit";"Zealot";"Gateway";83;2
"Unit";"Zealot";"Gateway";83;2
"Building";"Forge";NA;83;0
"Building";"Pylon";NA;93;0
"Unit";"Zealot";"Gateway";95;2
"Unit";"Zealot";"Gateway";95;2
"Building";"Pylon";NA;95;0
"Unit";"Immortal";"Robotics Facility";83;4
"Building";"RoboticsFacility";NA;83;0
"Unit";"Observer";"Robotics Facility";101;1
"Building";"HighTemplar";NA;107;0
"Building";"HighTemplar";NA;107;0
"Unit";"Zealot";"Gateway";107;2
"Unit";"Zealot";"Gateway";107;2
"Unit";"Zealot";"Gateway";107;2
"Unit";"Zealot";"Gateway";107;2
"Unit";"Immortal";"Robotics Facility";101;4
"Unit";"Archon";"High Templar";115;0
"Building";"Gateway";NA;101;0
"Building";"Gateway";NA;101;0
"Building";"Assimilator";NA;115;0
"Building";"Assimilator";NA;115;0
"Unit";"Zealot";"Gateway";119;2
"Unit";"Zealot";"Gateway";119;2
"Unit";"Zealot";"Gateway";119;2
"Unit";"Zealot";"Gateway";119;2
"Unit";"Zealot";"Gateway";119;2
"Unit";"Zealot";"Gateway";119;2
"Unit";"Zealot";"Gateway";119;2
"Unit";"Zealot";"Gateway";119;2
"Building";"Pylon";NA;119;0
"Unit";"Zealot";"Gateway";135;2
"Unit";"Zealot";"Gateway";135;2
"Unit";"Zealot";"Gateway";135;2
"Unit";"Zealot";"Gateway";135;2
"Unit";"Zealot";"Gateway";135;2
"Upgrade";"ProtossGroundWeaponsLevel1";"Forge";106;0
"Unit";"Immortal";"Robotics Facility";135;4
"Building";"Pylon";NA;145;0
"Building";"Nexus";NA;119;0
"Building";"Pylon";NA;149;0
"Building";"HighTemplar";NA;149;0
"Building";"HighTemplar";NA;149;0
"Building";"HighTemplar";NA;149;0
"Building";"HighTemplar";NA;149;0
"Building";"HighTemplar";NA;149;0
"Building";"HighTemplar";NA;149;0
"Building";"HighTemplar";NA;149;0
"Unit";"Immortal";"Robotics Facility";145;4
"Unit";"Sentry";"Gateway";155;2
"Building";"FleetBeacon";NA;149;0
"Unit";"Immortal";"Robotics Facility";149;4
"Unit";"Immortal";"Robotics Facility";149;4
"Unit";"Zealot";"Gateway";161;2
"Unit";"Zealot";"Gateway";161;2
"Unit";"Zealot";"Gateway";161;2
"Unit";"Zealot";"Gateway";161;2
"Unit";"Zealot";"Gateway";161;2
"Unit";"Oracle";"Stargate";155;3
"Building";"Gateway";NA;150;0
"Building";"Assimilator";NA;157;0
"Unit";"Archon";"High Templar";178;0
"Unit";"Zealot";"Gateway";178;2
"Unit";"Archon";"High Templar";178;0
"Unit";"Zealot";"Gateway";178;2
"Unit";"Zealot";"Gateway";178;2
"Unit";"Zealot";"Gateway";184;2
"Unit";"Zealot";"Gateway";184;2
"Unit";"Zealot";"Gateway";184;2
"Unit";"Zealot";"Gateway";184;2
"Upgrade";"ProtossGroundWeaponsLevel2";"Forge";149;0
"Building";"Pylon";NA;184;0
"Building";"HighTemplar";NA;192;0
"Building";"HighTemplar";NA;192;0
"Building";"Pylon";NA;192;0
"Unit";"Sentry";"Gateway";192;2
"Unit";"Immortal";"Robotics Facility";184;4
"Unit";"Archon";"High Templar";192;0
"Building";"HighTemplar";NA;206;0
"Building";"HighTemplar";NA;206;0
"Building";"HighTemplar";NA;207;0
"Building";"HighTemplar";NA;207;0
"Building";"HighTemplar";NA;207;0
"Building";"HighTemplar";NA;207;0
"Unit";"Archon";"High Templar";209;0
"Unit";"Archon";"High Templar";209;0
"Building";"Pylon";NA;209;0
"Building";"Assimilator";NA;209;0
"Unit";"Zealot";"Gateway";209;2
"Unit";"Zealot";"Gateway";209;2
"Unit";"Zealot";"Gateway";209;2
"Unit";"Zealot";"Gateway";209;2
"Unit";"Zealot";"Gateway";209;2
"Unit";"Oracle";"Stargate";207;3
"Unit";"Zealot";"Gateway";223;2
"Building";"ShieldBattery";NA;209;0
"Unit";"Zealot";"Gateway";223;2
"Unit";"Zealot";"Gateway";223;2
"Building";"ShieldBattery";NA;209;0
"Unit";"Zealot";"Gateway";223;2
"Building";"HighTemplar";NA;231;0
"Building";"HighTemplar";NA;231;0
"Building";"HighTemplar";NA;231;0
"Building";"HighTemplar";NA;231;0
"Upgrade";"ProtossGroundWeaponsLevel3";"Forge";192;0
"Building";"Pylon";NA;231;0
"Unit";"Immortal";"Robotics Facility";231;4
"Unit";"Immortal";"Robotics Facility";231;4
"Building";"OracleStasisTrap";NA;232;0
"Building";"PhotonCannon";NA;231;0
"Building";"Pylon";NA;231;0
"Unit";"Zealot";"Gateway";240;2
"Unit";"Zealot";"Gateway";240;2
"Unit";"Zealot";"Gateway";240;2
"Unit";"Zealot";"Gateway";240;2
"Unit";"Zealot";"Gateway";240;2
"Unit";"Zealot";"Gateway";240;2
"Unit";"Zealot";"Gateway";240;2
"Building";"Pylon";NA;240;0
"Unit";"Mothership";"Mothership Core";232;6
"Building";"Nexus";NA;240;0
"Unit";"Archon";"High Templar";263;0
"Unit";"Archon";"High Templar";263;0
"Building";"OracleStasisTrap";NA;263;0
"Unit";"Zealot";"Gateway";263;2
"Unit";"Zealot";"Gateway";263;2
"Unit";"Zealot";"Gateway";263;2
"Unit";"Zealot";"Gateway";263;2
"Unit";"Zealot";"Gateway";263;2
"Unit";"Zealot";"Gateway";263;2
"Unit";"Zealot";"Gateway";263;2
"Unit";"Zealot";"Gateway";263;2
"Unit";"Zealot";"Gateway";263;2
"Unit";"Immortal";"Robotics Facility";263;4
"Unit";"Immortal";"Robotics Facility";263;4
"Building";"HighTemplar";NA;281;0
"Building";"HighTemplar";NA;281;0
"Building";"HighTemplar";NA;281;0
"Building";"HighTemplar";NA;281;0
"Building";"HighTemplar";NA;281;0
"Building";"HighTemplar";NA;285;0
"Building";"HighTemplar";NA;285;0
"Building";"HighTemplar";NA;285;0
"Building";"HighTemplar";NA;289;0
"Upgrade";"ProtossShieldsLevel1";"Forge";257;0
"Unit";"Archon";"High Templar";289;0
"Unit";"Archon";"High Templar";289;0
"Unit";"Archon";"High Templar";289;0
"Unit";"Archon";"High Templar";289;0
"Unit";"Oracle";"Stargate";281;3
"Unit";"Immortal";"Robotics Facility";281;4
"Unit";"Immortal";"Robotics Facility";285;4
"Unit";"Zealot";"Gateway";292;2
"Unit";"Zealot";"Gateway";292;2
"Unit";"Zealot";"Gateway";292;2
"Unit";"Zealot";"Gateway";292;2
"Unit";"Zealot";"Gateway";292;2
"Unit";"Zealot";"Gateway";292;2
"Unit";"Zealot";"Gateway";292;2
"Unit";"Zealot";"Gateway";292;2
"Unit";"Zealot";"Gateway";292;2
"Building";"CyberneticsCore";NA;289;0
"Building";"Assimilator";NA;318;0
"Building";"Assimilator";NA;318;0
"Building";"PhotonCannon";NA;318;0
"Unit";"Zealot";"Gateway";318;2
"Unit";"Zealot";"Gateway";318;2
"Unit";"Zealot";"Gateway";318;2
"Unit";"Zealot";"Gateway";318;2
"Unit";"Zealot";"Gateway";318;2
"Unit";"Zealot";"Gateway";318;2
"Unit";"Immortal";"Robotics Facility";318;4
"Unit";"Immortal";"Robotics Facility";318;4
