"type";"unit_name";"on_building";"total_supply";"supply"
"Building";"Pylon";NA;13;0
"Building";"Assimilator";NA;15;0
"Building";"Gateway";NA;15;0
"Building";"Assimilator";NA;20;0
"Building";"Pylon";NA;21;0
"Building";"CyberneticsCore";NA;20;0
"Building";"Nexus";NA;19;0
"Unit";"Adept";"Gateway";22;2
"Building";"Stargate";NA;23;0
"Unit";"Adept";"Gateway";27;2
"Unit";"Oracle";"Stargate";29;3
"Building";"Pylon";NA;33;0
"Building";"Gateway";NA;33;0
"Building";"Pylon";NA;41;0
"Unit";"Oracle";"Stargate";39;3
"Unit";"Phoenix";"Stargate";48;2
"Building";"Pylon";NA;48;0
"Building";"Assimilator";NA;50;0
"Building";"Assimilator";NA;52;0
"Building";"TwilightCouncil";NA;48;0
"Building";"Nexus";NA;43;0
"Building";"RoboticsFacility";NA;48;0
"Building";"Pylon";NA;59;0
"Building";"Pylon";NA;61;0
"Unit";"Immortal";"Robotics Facility";59;4
"Building";"Gateway";NA;58;0
"Building";"Gateway";NA;58;0
"Building";"TemplarArchive";NA;59;0
"Building";"Assimilator";NA;61;0
"Building";"Assimilator";NA;61;0
"Unit";"Observer";"Robotics Facility";64;1
"Building";"Gateway";NA;59;0
"Building";"Gateway";NA;60;0
"Upgrade";"Charge";"TwilightCouncil";58;0
"Building";"HighTemplar";NA;76;0
"Building";"HighTemplar";NA;76;0
"Unit";"Zealot";"Gateway";78;2
"Unit";"Zealot";"Gateway";78;2
"Unit";"Zealot";"Gateway";78;2
"Unit";"Zealot";"Gateway";78;2
"Unit";"Immortal";"Robotics Facility";73;4
"Building";"Pylon";NA;87;0
"Building";"HighTemplar";NA;91;0
"Building";"HighTemplar";NA;91;0
"Building";"Forge";NA;78;0
"Unit";"Immortal";"Robotics Facility";78;4
"Building";"Pylon";NA;91;0
"Building";"Pylon";NA;91;0
"Building";"Gateway";NA;78;0
"Unit";"Zealot";"Gateway";95;2
"Unit";"Zealot";"Gateway";95;2
"Unit";"Zealot";"Gateway";95;2
"Unit";"Zealot";"Gateway";95;2
"Building";"Gateway";NA;79;0
"Unit";"Zealot";"Gateway";105;2
"Unit";"Zealot";"Gateway";105;2
"Unit";"Immortal";"Robotics Facility";91;4
"Building";"HighTemplar";NA;113;0
"Building";"HighTemplar";NA;113;0
"Building";"HighTemplar";NA;113;0
"Building";"HighTemplar";NA;113;0
"Unit";"Zealot";"Gateway";113;2
"Unit";"Zealot";"Gateway";115;2
"Unit";"Zealot";"Gateway";115;2
"Building";"Nexus";NA;91;0
"Building";"HighTemplar";NA;122;0
"Building";"HighTemplar";NA;122;0
"Unit";"Immortal";"Robotics Facility";109;4
"Unit";"Archon";"High Templar";122;0
"Building";"Pylon";NA;122;0
"Building";"Pylon";NA;122;0
"Building";"Pylon";NA;122;0
"Building";"HighTemplar";NA;130;0
"Building";"HighTemplar";NA;130;0
"Unit";"Zealot";"Gateway";132;2
"Unit";"Zealot";"Gateway";132;2
"Unit";"Zealot";"Gateway";132;2
"Unit";"Zealot";"Gateway";132;2
"Building";"Assimilator";NA;129;0
"Building";"Assimilator";NA;130;0
"Upgrade";"ProtossGroundWeaponsLevel1";"Forge";105;0
"Building";"ShieldBattery";NA;130;0
"Building";"ShieldBattery";NA;130;0
"Unit";"Immortal";"Robotics Facility";125;4
"Unit";"Zealot";"Gateway";141;2
"Unit";"Zealot";"Gateway";141;2
"Unit";"Zealot";"Gateway";141;2
"Unit";"Zealot";"Gateway";141;2
"Unit";"Zealot";"Gateway";154;2
"Building";"HighTemplar";NA;154;0
"Building";"HighTemplar";NA;154;0
"Building";"HighTemplar";NA;154;0
"Unit";"Oracle";"Stargate";140;3
"Unit";"Observer";"Robotics Facility";142;1
"Building";"PhotonCannon";NA;140;0
"Building";"PhotonCannon";NA;141;0
"Building";"Pylon";NA;161;0
"Building";"Pylon";NA;161;0
"Building";"PhotonCannon";NA;160;0
"Building";"HighTemplar";NA;164;0
"Building";"HighTemplar";NA;164;0
"Building";"HighTemplar";NA;164;0
"Building";"HighTemplar";NA;164;0
"Building";"HighTemplar";NA;164;0
"Building";"Pylon";NA;164;0
"Building";"Pylon";NA;164;0
"Building";"Pylon";NA;164;0
"Unit";"Zealot";"Gateway";164;2
"Unit";"Zealot";"Gateway";164;2
"Unit";"Zealot";"Gateway";164;2
"Building";"PhotonCannon";NA;164;0
"Building";"RoboticsFacility";NA;156;0
"Unit";"Archon";"High Templar";164;0
"Unit";"Archon";"High Templar";164;0
"Unit";"Observer";"Robotics Facility";170;1
"Unit";"Zealot";"Gateway";171;2
"Unit";"Zealot";"Gateway";171;2
"Unit";"Zealot";"Gateway";171;2
"Unit";"Zealot";"Gateway";171;2
"Unit";"Zealot";"Gateway";171;2
"Unit";"Zealot";"Gateway";171;2
"Unit";"Zealot";"Gateway";183;2
"Unit";"Zealot";"Gateway";183;2
"Unit";"Zealot";"Gateway";183;2
"Unit";"Zealot";"Gateway";189;2
"Unit";"Zealot";"Gateway";189;2
"Building";"FleetBeacon";NA;170;0
"Building";"HighTemplar";NA;189;0
"Building";"HighTemplar";NA;189;0
"Unit";"Zealot";"Gateway";189;2
"Building";"Stargate";NA;170;0
"Building";"Stargate";NA;170;0
"Unit";"Immortal";"Robotics Facility";183;4
"Unit";"Immortal";"Robotics Facility";183;4
"Unit";"Archon";"High Templar";195;0
"Building";"Pylon";NA;195;0
"Unit";"Zealot";"Gateway";203;2
"Unit";"Oracle";"Stargate";195;3
"Unit";"Zealot";"Gateway";208;2
"Unit";"Zealot";"Gateway";208;2
"Unit";"Zealot";"Gateway";208;2
"Unit";"Zealot";"Gateway";208;2
"Unit";"Zealot";"Gateway";208;2
"Unit";"Zealot";"Gateway";208;2
"Building";"Nexus";NA;195;0
"Upgrade";"ProtossGroundWeaponsLevel2";"Forge";189;0
"Unit";"Zealot";"Gateway";220;2
"Unit";"Zealot";"Gateway";220;2
"Unit";"Zealot";"Gateway";220;2
"Unit";"Zealot";"Gateway";220;2
"Unit";"Zealot";"Gateway";220;2
"Unit";"Zealot";"Gateway";220;2
"Unit";"Zealot";"Gateway";220;2
"Unit";"Zealot";"Gateway";220;2
"Unit";"Carrier";"Stargate";203;6
"Unit";"Carrier";"Stargate";203;6
"Unit";"Zealot";"Gateway";249;2
"Unit";"Zealot";"Gateway";249;2
"Unit";"Zealot";"Gateway";249;2
"Unit";"Zealot";"Gateway";249;2
"Unit";"Zealot";"Gateway";249;2
"Unit";"Zealot";"Gateway";249;2
"Unit";"Zealot";"Gateway";249;2
"Building";"HighTemplar";NA;263;0
"Building";"HighTemplar";NA;263;0
"Building";"HighTemplar";NA;263;0
"Building";"HighTemplar";NA;263;0
"Building";"HighTemplar";NA;263;0
"Building";"HighTemplar";NA;263;0
"Unit";"Carrier";"Stargate";220;6
"Unit";"Mothership";"Mothership Core";236;6
"Unit";"Carrier";"Stargate";236;6
"Building";"HighTemplar";NA;275;0
"Building";"HighTemplar";NA;275;0
"Building";"HighTemplar";NA;275;0
"Building";"HighTemplar";NA;275;0
"Building";"HighTemplar";NA;275;0
"Building";"HighTemplar";NA;275;0
"Building";"HighTemplar";NA;281;0
"Unit";"Archon";"High Templar";281;0
"Unit";"Archon";"High Templar";281;0
"Unit";"Archon";"High Templar";281;0
"Building";"Pylon";NA;281;0
"Building";"Pylon";NA;281;0
"Unit";"Observer";"Robotics Facility";281;1
"Upgrade";"ProtossAirWeaponsLevel1";"CyberneticsCore";263;0
"Building";"Assimilator";NA;281;0
"Upgrade";"ProtossShieldsLevel1";"Forge";263;0
"Building";"Assimilator";NA;281;0
"Unit";"Oracle";"Stargate";281;3
"Unit";"Carrier";"Stargate";269;6
"Unit";"Carrier";"Stargate";269;6
"Unit";"Zealot";"Gateway";297;2
"Unit";"Zealot";"Gateway";297;2
"Unit";"Zealot";"Gateway";297;2
"Building";"Gateway";NA;281;0
"Building";"Gateway";NA;281;0
"Building";"Gateway";NA;281;0
"Building";"Nexus";NA;275;0
"Unit";"Zealot";"Gateway";303;2
"Unit";"Zealot";"Gateway";303;2
"Unit";"Zealot";"Gateway";303;2
"Building";"ShieldBattery";NA;303;0
"Building";"ShieldBattery";NA;303;0
"Building";"Forge";NA;309;0
"Building";"CyberneticsCore";NA;309;0
"Building";"HighTemplar";NA;309;0
"Building";"PhotonCannon";NA;309;0
"Building";"PhotonCannon";NA;309;0
"Building";"PhotonCannon";NA;309;0
"Building";"PhotonCannon";NA;309;0
"Unit";"Zealot";"Gateway";309;2
"Building";"PhotonCannon";NA;309;0
"Building";"ShieldBattery";NA;309;0
"Building";"ShieldBattery";NA;309;0
"Building";"HighTemplar";NA;312;0
"Building";"HighTemplar";NA;312;0
"Building";"HighTemplar";NA;312;0
"Building";"HighTemplar";NA;312;0
"Building";"HighTemplar";NA;312;0
"Building";"HighTemplar";NA;312;0
"Building";"HighTemplar";NA;312;0
"Building";"HighTemplar";NA;312;0
"Building";"HighTemplar";NA;312;0
"Building";"HighTemplar";NA;312;0
