"type";"unit_name";"on_building";"total_supply_lag";"supply"
"Unit";"Overlord";"Larva";13;0
"Building";"SpawningPool";NA;17;0
"Building";"Hatchery";NA;18;0
"Building";"Extractor";NA;20;0
"Unit";"Queen";"Hatchery";21;2
"Unit";"Zergling";"Larva";23;1
"Unit";"Zergling";"Larva";24;1
"Unit";"Overlord";"Larva";25;0
"Unit";"Queen";"Hatchery";27;2
"Unit";"Queen";"Hatchery";30;2
"Unit";"Overlord";"Larva";36;0
"Building";"CreepTumorQueen";NA;41;0
"Unit";"Overlord";"Larva";41;0
"Unit";"Overlord";"Larva";43;0
"Unit";"Zergling";"Larva";45;1
"Unit";"Zergling";"Larva";46;1
"Unit";"Zergling";"Larva";47;1
"Unit";"Zergling";"Larva";48;1
"Unit";"Zergling";"Larva";49;1
"Unit";"Zergling";"Larva";50;1
"Unit";"Overlord";"Larva";51;0
"Building";"CreepTumor";NA;52;0
"Building";"Hatchery";NA;54;0
"Unit";"Queen";"Hatchery";59;2
"Unit";"Queen";"Hatchery";61;2
"Building";"CreepTumor";NA;67;0
"Unit";"Zergling";"Larva";68;1
"Unit";"Zergling";"Larva";69;1
"Building";"CreepTumorQueen";NA;71;0
"Unit";"Overlord";"Larva";72;0
"Unit";"Queen";"Hatchery";75;2
"Building";"SporeCrawler";NA;77;0
"Unit";"Queen";"Hatchery";77;2
"Building";"SporeCrawler";NA;79;0
"Unit";"Zergling";"Larva";80;1
"Unit";"Zergling";"Larva";81;1
"Building";"CreepTumorQueen";NA;82;0
"Building";"BanelingNest";NA;82;0
"Building";"CreepTumor";NA;82;0
"Building";"SporeCrawler";NA;82;0
"Unit";"Zergling";"Larva";82;1
"Unit";"Zergling";"Larva";83;1
"Unit";"Zergling";"Larva";84;1
"Unit";"Zergling";"Larva";85;1
"Building";"CreepTumorQueen";NA;86;0
"Unit";"Zergling";"Larva";86;1
"Unit";"Zergling";"Larva";87;1
"Unit";"Queen";"Hatchery";88;2
"Unit";"Zergling";"Larva";90;1
"Unit";"Zergling";"Larva";91;1
"Unit";"Zergling";"Larva";92;1
"Unit";"Zergling";"Larva";93;1
"Unit";"Overlord";"Larva";94;0
"Building";"CreepTumor";NA;97;0
"Unit";"Queen";"Hatchery";97;2
"Building";"CreepTumor";NA;99;0
"Unit";"Queen";"Hatchery";99;2
"Building";"CreepTumor";NA;101;0
"Unit";"Overlord";"Larva";107;0
"Building";"EvolutionChamber";NA;107;0
"Building";"EvolutionChamber";NA;107;0
"Building";"CreepTumorQueen";NA;112;0
"Building";"CreepTumor";NA;112;0
"Building";"CreepTumorQueen";NA;112;0
"Building";"Extractor";NA;112;0
"Building";"Extractor";NA;112;0
"Building";"CreepTumorQueen";NA;113;0
"Building";"Extractor";NA;115;0
"Building";"Extractor";NA;115;0
"Building";"CreepTumor";NA;115;0
"Building";"Extractor";NA;116;0
"Building";"CreepTumor";NA;117;0
"Building";"CreepTumorQueen";NA;118;0
"Unit";"Overlord";"Larva";125;0
"Unit";"Overlord";"Larva";125;0
"Unit";"Overlord";"Larva";125;0
"Building";"Hatchery";NA;125;0
"Building";"CreepTumor";NA;125;0
"Building";"CreepTumorQueen";NA;125;0
"Building";"CreepTumorQueen";NA;125;0
"Building";"Hatchery";NA;127;0
"Building";"Hatchery";NA;128;0
"Building";"CreepTumor";NA;132;0
"Unit";"Overlord";"Larva";132;0
"Unit";"Overlord";"Larva";132;0
"Building";"CreepTumor";NA;132;0
"Building";"CreepTumor";NA;132;0
"Building";"CreepTumor";NA;132;0
"Building";"CreepTumor";NA;132;0
"Building";"CreepTumor";NA;132;0
"Building";"CreepTumor";NA;132;0
"Building";"CreepTumorQueen";NA;132;0
"Unit";"Overlord";"Larva";132;0
"Unit";"Overlord";"Larva";132;0
"Unit";"Overlord";"Larva";132;0
"Building";"CreepTumorQueen";NA;132;0
"Unit";"Overlord";"Larva";132;0
"Unit";"Overlord";"Larva";132;0
"Unit";"Zergling";"Larva";132;1
"Unit";"Zergling";"Larva";133;1
"Unit";"Zergling";"Larva";134;1
"Unit";"Zergling";"Larva";135;1
"Unit";"Zergling";"Larva";136;1
"Unit";"Zergling";"Larva";137;1
"Unit";"Zergling";"Larva";138;1
"Unit";"Zergling";"Larva";139;1
"Unit";"Zergling";"Larva";140;1
"Unit";"Zergling";"Larva";141;1
"Unit";"Zergling";"Larva";142;1
"Unit";"Zergling";"Larva";143;1
"Unit";"Zergling";"Larva";144;1
"Unit";"Zergling";"Larva";145;1
"Unit";"Zergling";"Larva";146;1
"Unit";"Zergling";"Larva";147;1
"Unit";"Overlord";"Larva";148;0
"Building";"CreepTumor";NA;148;0
"Unit";"Overlord";"Larva";148;0
"Building";"CreepTumorQueen";NA;148;0
"Building";"CreepTumor";NA;148;0
"Building";"CreepTumor";NA;148;0
"Building";"CreepTumor";NA;148;0
"Building";"CreepTumorQueen";NA;148;0
"Building";"CreepTumorQueen";NA;148;0
"Building";"CreepTumorQueen";NA;148;0
"Building";"CreepTumorQueen";NA;148;0
"Building";"InfestationPit";NA;148;0
"Building";"Spire";NA;150;0
"Building";"SporeCrawler";NA;150;0
"Unit";"Zergling";"Larva";150;1
"Unit";"Zergling";"Larva";151;1
"Unit";"Zergling";"Larva";152;1
"Unit";"Zergling";"Larva";153;1
"Unit";"Zergling";"Larva";154;1
"Unit";"Zergling";"Larva";155;1
"Unit";"Zergling";"Larva";156;1
"Unit";"Zergling";"Larva";157;1
"Unit";"Zergling";"Larva";158;1
"Unit";"Zergling";"Larva";159;1
"Unit";"Zergling";"Larva";160;1
"Unit";"Zergling";"Larva";161;1
"Unit";"Zergling";"Larva";162;1
"Unit";"Zergling";"Larva";163;1
"Unit";"Zergling";"Larva";164;1
"Unit";"Zergling";"Larva";165;1
"Unit";"Zergling";"Larva";166;1
"Unit";"Zergling";"Larva";167;1
"Building";"CreepTumor";NA;168;0
"Unit";"Zergling";"Larva";168;1
"Unit";"Zergling";"Larva";169;1
"Unit";"Zergling";"Larva";170;1
"Unit";"Zergling";"Larva";171;1
"Unit";"Zergling";"Larva";172;1
"Unit";"Zergling";"Larva";173;1
"Unit";"Zergling";"Larva";174;1
"Unit";"Zergling";"Larva";175;1
"Unit";"Zergling";"Larva";176;1
"Unit";"Zergling";"Larva";177;1
"Unit";"Zergling";"Larva";178;1
"Unit";"Zergling";"Larva";179;1
"Unit";"Zergling";"Larva";180;1
"Unit";"Zergling";"Larva";181;1
"Unit";"Baneling";"Zergling";191;0
"Unit";"Baneling";"Zergling";191;0
"Unit";"Baneling";"Zergling";191;0
"Unit";"Baneling";"Zergling";191;0
"Unit";"Baneling";"Zergling";191;0
"Unit";"Zergling";"Larva";191;1
"Unit";"Zergling";"Larva";192;1
"Unit";"Zergling";"Larva";193;1
"Unit";"Zergling";"Larva";194;1
"Unit";"Zergling";"Larva";195;1
"Unit";"Zergling";"Larva";196;1
"Unit";"Zergling";"Larva";197;1
"Unit";"Zergling";"Larva";198;1
"Unit";"Zergling";"Larva";199;1
"Unit";"Zergling";"Larva";200;1
"Unit";"Zergling";"Larva";201;1
"Unit";"Zergling";"Larva";202;1
"Unit";"Zergling";"Larva";203;1
"Unit";"Zergling";"Larva";204;1
"Unit";"Zergling";"Larva";205;1
"Unit";"Zergling";"Larva";206;1
"Unit";"Zergling";"Larva";207;1
"Unit";"Zergling";"Larva";208;1
"Unit";"Zergling";"Larva";209;1
"Unit";"Zergling";"Larva";210;1
"Unit";"Zergling";"Larva";211;1
"Unit";"Zergling";"Larva";212;1
"Building";"CreepTumor";NA;213;0
"Building";"CreepTumor";NA;213;0
"Building";"CreepTumor";NA;213;0
"Building";"CreepTumor";NA;213;0
"Building";"CreepTumor";NA;213;0
"Unit";"Zergling";"Larva";213;1
"Unit";"Zergling";"Larva";214;1
"Unit";"Zergling";"Larva";215;1
"Unit";"Zergling";"Larva";216;1
"Unit";"Zergling";"Larva";217;1
"Unit";"Zergling";"Larva";218;1
"Unit";"Zergling";"Larva";219;1
"Unit";"Zergling";"Larva";220;1
"Unit";"Zergling";"Larva";221;1
"Unit";"Zergling";"Larva";222;1
"Unit";"Zergling";"Larva";223;1
"Unit";"Zergling";"Larva";224;1
"Unit";"Zergling";"Larva";225;1
"Unit";"Zergling";"Larva";226;1
"Unit";"Zergling";"Larva";227;1
"Unit";"Zergling";"Larva";228;1
"Unit";"Zergling";"Larva";229;1
"Unit";"Zergling";"Larva";230;1
"Unit";"Zergling";"Larva";231;1
"Unit";"Zergling";"Larva";232;1
"Unit";"Zergling";"Larva";233;1
"Unit";"Zergling";"Larva";234;1
"Unit";"Zergling";"Larva";235;1
"Unit";"Zergling";"Larva";236;1
"Unit";"Zergling";"Larva";237;1
"Unit";"Zergling";"Larva";238;1
"Unit";"Zergling";"Larva";239;1
"Unit";"Zergling";"Larva";240;1
"Unit";"Zergling";"Larva";241;1
"Unit";"Zergling";"Larva";242;1
"Unit";"Zergling";"Larva";243;1
"Unit";"Zergling";"Larva";244;1
"Unit";"Zergling";"Larva";245;1
"Unit";"Zergling";"Larva";246;1
"Unit";"Baneling";"Zergling";247;0
"Unit";"Baneling";"Zergling";247;0
"Unit";"Baneling";"Zergling";247;0
"Unit";"Baneling";"Zergling";247;0
"Building";"CreepTumor";NA;247;0
"Building";"CreepTumor";NA;247;0
"Building";"CreepTumor";NA;247;0
"Building";"CreepTumor";NA;247;0
"Unit";"Mutalisk";"Larva";247;2
"Unit";"Mutalisk";"Larva";249;2
"Unit";"Mutalisk";"Larva";251;2
"Unit";"Mutalisk";"Larva";253;2
"Unit";"Mutalisk";"Larva";255;2
"Building";"CreepTumorQueen";NA;257;0
"Building";"CreepTumorQueen";NA;257;0
"Building";"CreepTumorQueen";NA;257;0
"Building";"CreepTumor";NA;257;0
"Building";"CreepTumor";NA;257;0
"Building";"CreepTumorQueen";NA;257;0
"Building";"CreepTumor";NA;257;0
"Building";"CreepTumor";NA;257;0
"Building";"CreepTumorQueen";NA;257;0
"Unit";"Overlord";"Larva";257;0
"Unit";"Overlord";"Larva";257;0
"Unit";"Mutalisk";"Larva";257;2
"Unit";"Mutalisk";"Larva";259;2
"Unit";"Mutalisk";"Larva";261;2
"Building";"CreepTumorQueen";NA;263;0
"Building";"CreepTumorQueen";NA;263;0
"Unit";"Zergling";"Larva";263;1
"Unit";"Zergling";"Larva";264;1
"Unit";"Zergling";"Larva";265;1
"Unit";"Zergling";"Larva";266;1
"Unit";"Zergling";"Larva";267;1
"Unit";"Zergling";"Larva";268;1
"Unit";"Zergling";"Larva";269;1
"Unit";"Zergling";"Larva";270;1
"Unit";"Zergling";"Larva";271;1
"Unit";"Zergling";"Larva";272;1
"Unit";"Zergling";"Larva";273;1
"Unit";"Zergling";"Larva";274;1
"Unit";"Zergling";"Larva";275;1
"Unit";"Zergling";"Larva";276;1
"Unit";"Zergling";"Larva";277;1
"Unit";"Zergling";"Larva";278;1
"Unit";"Baneling";"Zergling";279;0
"Unit";"Baneling";"Zergling";279;0
"Unit";"Baneling";"Zergling";279;0
"Unit";"Baneling";"Zergling";279;0
"Unit";"Baneling";"Zergling";279;0
"Unit";"Baneling";"Zergling";279;0
"Unit";"Baneling";"Zergling";279;0
"Building";"CreepTumorQueen";NA;279;0
"Building";"CreepTumorQueen";NA;279;0
"Building";"CreepTumor";NA;279;0
"Building";"CreepTumor";NA;279;0
"Building";"CreepTumor";NA;279;0
"Unit";"Zergling";"Larva";279;1
"Unit";"Zergling";"Larva";280;1
"Unit";"Zergling";"Larva";281;1
"Unit";"Zergling";"Larva";282;1
"Unit";"Zergling";"Larva";283;1
"Unit";"Zergling";"Larva";284;1
"Unit";"Zergling";"Larva";285;1
"Unit";"Zergling";"Larva";286;1
"Unit";"Zergling";"Larva";287;1
"Unit";"Zergling";"Larva";288;1
"Unit";"Zergling";"Larva";289;1
"Unit";"Zergling";"Larva";290;1
"Unit";"Zergling";"Larva";291;1
"Unit";"Zergling";"Larva";292;1
"Unit";"Zergling";"Larva";293;1
"Unit";"Zergling";"Larva";294;1
"Unit";"Zergling";"Larva";295;1
"Unit";"Zergling";"Larva";296;1
"Building";"CreepTumorQueen";NA;297;0
"Unit";"Baneling";"Zergling";297;0
"Unit";"Baneling";"Zergling";297;0
"Unit";"Baneling";"Zergling";297;0
"Unit";"Baneling";"Zergling";297;0
"Unit";"Zergling";"Larva";297;1
"Unit";"Zergling";"Larva";298;1
"Unit";"Zergling";"Larva";299;1
"Unit";"Zergling";"Larva";300;1
"Unit";"Zergling";"Larva";301;1
"Unit";"Zergling";"Larva";302;1
"Unit";"Zergling";"Larva";303;1
"Unit";"Zergling";"Larva";304;1
"Unit";"Zergling";"Larva";305;1
"Unit";"Zergling";"Larva";306;1
"Building";"CreepTumorQueen";NA;307;0
"Building";"UltraliskCavern";NA;307;0
"Building";"CreepTumorQueen";NA;307;0
"Building";"CreepTumorQueen";NA;307;0
"Building";"CreepTumor";NA;307;0
"Building";"CreepTumor";NA;307;0
"Building";"CreepTumor";NA;307;0
"Building";"CreepTumor";NA;307;0
"Unit";"Queen";"Hatchery";307;2
"Unit";"Queen";"Hatchery";309;2
"Building";"CreepTumorQueen";NA;311;0
"Building";"CreepTumorQueen";NA;311;0
"Unit";"Baneling";"Zergling";311;0
"Unit";"Baneling";"Zergling";311;0
"Unit";"Baneling";"Zergling";311;0
"Unit";"Baneling";"Zergling";311;0
"Unit";"Baneling";"Zergling";311;0
"Unit";"Zergling";"Larva";311;1
"Unit";"Zergling";"Larva";312;1
"Unit";"Zergling";"Larva";313;1
"Unit";"Zergling";"Larva";314;1
"Unit";"Zergling";"Larva";315;1
"Unit";"Zergling";"Larva";316;1
"Unit";"Zergling";"Larva";317;1
"Unit";"Zergling";"Larva";318;1
"Unit";"Zergling";"Larva";319;1
"Unit";"Zergling";"Larva";320;1
"Unit";"Zergling";"Larva";321;1
"Unit";"Zergling";"Larva";322;1
"Unit";"Zergling";"Larva";323;1
"Unit";"Zergling";"Larva";324;1
"Unit";"Zergling";"Larva";325;1
"Unit";"Zergling";"Larva";326;1
"Unit";"Baneling";"Zergling";327;0
"Unit";"Baneling";"Zergling";327;0
"Unit";"Baneling";"Zergling";327;0
"Unit";"Baneling";"Zergling";327;0
"Unit";"Baneling";"Zergling";327;0
"Unit";"Baneling";"Zergling";327;0
"Unit";"Baneling";"Zergling";327;0
"Unit";"Baneling";"Zergling";327;0
"Unit";"Baneling";"Zergling";327;0
"Unit";"Overlord";"Larva";327;0
"Unit";"Overlord";"Larva";327;0
"Unit";"Overlord";"Larva";327;0
"Unit";"Overlord";"Larva";327;0
"Unit";"Baneling";"Zergling";327;0
"Unit";"Baneling";"Zergling";327;0
"Unit";"Baneling";"Zergling";327;0
"Unit";"Baneling";"Zergling";327;0
"Unit";"Baneling";"Zergling";327;0
"Unit";"Baneling";"Zergling";327;0
"Unit";"Baneling";"Zergling";327;0
"Unit";"Baneling";"Zergling";327;0
"Unit";"Baneling";"Zergling";327;0
"Unit";"Baneling";"Zergling";327;0
"Unit";"Ultralisk";"Larva";327;6
"Unit";"Zergling";"Larva";333;1
"Unit";"Zergling";"Larva";334;1
"Unit";"Zergling";"Larva";335;1
"Unit";"Zergling";"Larva";336;1
"Unit";"Zergling";"Larva";337;1
"Unit";"Zergling";"Larva";338;1
"Unit";"Zergling";"Larva";339;1
"Unit";"Zergling";"Larva";340;1
"Unit";"Zergling";"Larva";341;1
"Unit";"Zergling";"Larva";342;1
"Unit";"Zergling";"Larva";343;1
"Unit";"Zergling";"Larva";344;1
"Unit";"Zergling";"Larva";345;1
"Unit";"Zergling";"Larva";346;1
"Unit";"Zergling";"Larva";347;1
"Unit";"Zergling";"Larva";348;1
"Unit";"Zergling";"Larva";349;1
"Unit";"Zergling";"Larva";350;1
"Unit";"Zergling";"Larva";351;1
"Unit";"Zergling";"Larva";352;1
"Unit";"Ultralisk";"Larva";353;6
"Upgrade";"ChitinousPlating";"UltraliskCavern";359;0
"Unit";"Zergling";"Larva";359;1
"Unit";"Zergling";"Larva";360;1
"Unit";"Zergling";"Larva";361;1
"Unit";"Zergling";"Larva";362;1
"Unit";"Zergling";"Larva";363;1
"Unit";"Zergling";"Larva";364;1
"Unit";"Zergling";"Larva";365;1
"Unit";"Zergling";"Larva";366;1
"Unit";"Zergling";"Larva";367;1
"Unit";"Zergling";"Larva";368;1
"Unit";"Zergling";"Larva";369;1
"Unit";"Zergling";"Larva";370;1
"Unit";"Zergling";"Larva";371;1
"Unit";"Zergling";"Larva";372;1
"Unit";"Zergling";"Larva";373;1
"Unit";"Zergling";"Larva";374;1
"Unit";"Zergling";"Larva";375;1
"Unit";"Zergling";"Larva";376;1
"Unit";"Ultralisk";"Larva";377;6
"Unit";"Zergling";"Larva";383;1
"Unit";"Zergling";"Larva";384;1
"Unit";"Zergling";"Larva";385;1
"Unit";"Zergling";"Larva";386;1
"Unit";"Zergling";"Larva";387;1
"Unit";"Zergling";"Larva";388;1
"Unit";"Zergling";"Larva";389;1
"Unit";"Zergling";"Larva";390;1
"Unit";"Zergling";"Larva";391;1
"Unit";"Zergling";"Larva";392;1
"Unit";"Zergling";"Larva";393;1
"Unit";"Zergling";"Larva";394;1
"Unit";"Zergling";"Larva";395;1
"Unit";"Zergling";"Larva";396;1
"Unit";"Queen";"Hatchery";397;2
"Unit";"Queen";"Hatchery";399;2
"Unit";"Ultralisk";"Larva";401;6
"Unit";"Zergling";"Larva";407;1
"Unit";"Zergling";"Larva";408;1
"Unit";"Zergling";"Larva";409;1
"Unit";"Zergling";"Larva";410;1
"Unit";"Zergling";"Larva";411;1
"Unit";"Zergling";"Larva";412;1
"Unit";"Zergling";"Larva";413;1
"Unit";"Zergling";"Larva";414;1
"Unit";"Zergling";"Larva";415;1
"Unit";"Zergling";"Larva";416;1
"Unit";"Zergling";"Larva";417;1
"Unit";"Zergling";"Larva";418;1
"Unit";"Zergling";"Larva";419;1
"Unit";"Zergling";"Larva";420;1
"Unit";"Zergling";"Larva";421;1
"Unit";"Zergling";"Larva";422;1
"Unit";"Zergling";"Larva";423;1
"Unit";"Zergling";"Larva";424;1
"Unit";"Zergling";"Larva";425;1
"Unit";"Zergling";"Larva";426;1
"Unit";"Zergling";"Larva";427;1
"Unit";"Zergling";"Larva";428;1
"Unit";"Zergling";"Larva";429;1
"Unit";"Zergling";"Larva";430;1
"Unit";"Zergling";"Larva";431;1
"Unit";"Zergling";"Larva";432;1
"Unit";"Zergling";"Larva";433;1
"Unit";"Zergling";"Larva";434;1
"Unit";"Zergling";"Larva";435;1
"Unit";"Zergling";"Larva";436;1
"Unit";"Zergling";"Larva";437;1
"Unit";"Zergling";"Larva";438;1
"Unit";"Zergling";"Larva";439;1
"Unit";"Zergling";"Larva";440;1
"Unit";"Baneling";"Zergling";441;0
"Unit";"Baneling";"Zergling";441;0
"Unit";"Baneling";"Zergling";441;0
"Unit";"Baneling";"Zergling";441;0
"Unit";"Baneling";"Zergling";441;0
"Unit";"Baneling";"Zergling";441;0
"Unit";"Baneling";"Zergling";441;0
"Unit";"Baneling";"Zergling";441;0
"Unit";"Ultralisk";"Larva";441;6
"Unit";"Ultralisk";"Larva";447;6
"Unit";"Zergling";"Larva";453;1
"Unit";"Zergling";"Larva";454;1
"Unit";"Zergling";"Larva";455;1
"Unit";"Zergling";"Larva";456;1
"Unit";"Zergling";"Larva";457;1
"Unit";"Zergling";"Larva";458;1
"Unit";"Zergling";"Larva";459;1
"Unit";"Zergling";"Larva";460;1
"Unit";"Zergling";"Larva";461;1
"Unit";"Zergling";"Larva";462;1
"Unit";"Zergling";"Larva";463;1
"Unit";"Zergling";"Larva";464;1
"Unit";"Zergling";"Larva";465;1
"Unit";"Zergling";"Larva";466;1
"Unit";"Zergling";"Larva";467;1
"Unit";"Zergling";"Larva";468;1
"Unit";"Zergling";"Larva";469;1
"Unit";"Zergling";"Larva";470;1
"Unit";"Queen";"Hatchery";471;2
"Unit";"Queen";"Hatchery";473;2
"Unit";"Queen";"Hatchery";475;2
"Unit";"Zergling";"Larva";477;1
"Unit";"Zergling";"Larva";478;1
"Unit";"Zergling";"Larva";479;1
"Unit";"Zergling";"Larva";480;1
"Unit";"Zergling";"Larva";481;1
"Unit";"Zergling";"Larva";482;1
"Unit";"Zergling";"Larva";483;1
"Unit";"Zergling";"Larva";484;1
"Unit";"Queen";"Hatchery";485;2
"Unit";"Queen";"Hatchery";487;2
"Building";"CreepTumorQueen";NA;489;0
"Building";"CreepTumorQueen";NA;489;0
"Building";"CreepTumorQueen";NA;489;0
"Unit";"Ultralisk";"Larva";489;6
"Unit";"Ultralisk";"Larva";495;6
"Unit";"Zergling";"Larva";501;1
"Unit";"Zergling";"Larva";502;1
"Unit";"Zergling";"Larva";503;1
"Unit";"Zergling";"Larva";504;1
"Unit";"Zergling";"Larva";505;1
"Unit";"Zergling";"Larva";506;1
"Unit";"Zergling";"Larva";507;1
"Unit";"Zergling";"Larva";508;1
"Unit";"Zergling";"Larva";509;1
"Unit";"Zergling";"Larva";510;1
"Unit";"Zergling";"Larva";511;1
"Unit";"Zergling";"Larva";512;1
"Unit";"Zergling";"Larva";513;1
"Unit";"Zergling";"Larva";514;1
"Unit";"Queen";"Hatchery";515;2
"Unit";"Queen";"Hatchery";517;2
"Building";"CreepTumorQueen";NA;519;0
"Building";"CreepTumorQueen";NA;519;0
"Building";"CreepTumorQueen";NA;519;0
"Unit";"Corruptor";"Larva";519;2
"Unit";"Corruptor";"Larva";521;2
"Unit";"Corruptor";"Larva";523;2
"Unit";"Corruptor";"Larva";525;2
"Building";"CreepTumor";NA;527;0
"Building";"CreepTumor";NA;527;0
"Building";"CreepTumor";NA;527;0
"Building";"CreepTumor";NA;527;0
"Building";"CreepTumor";NA;527;0
"Building";"Hatchery";NA;527;0
"Building";"CreepTumor";NA;527;0
"Building";"CreepTumor";NA;527;0
"Building";"CreepTumor";NA;527;0
"Unit";"Corruptor";"Larva";527;2
"Unit";"Corruptor";"Larva";529;2
"Unit";"Baneling";"Zergling";531;0
"Unit";"Baneling";"Zergling";531;0
"Unit";"Baneling";"Zergling";531;0
"Unit";"Baneling";"Zergling";531;0
"Unit";"Baneling";"Zergling";531;0
"Unit";"Baneling";"Zergling";531;0
"Unit";"Baneling";"Zergling";531;0
"Unit";"Baneling";"Zergling";531;0
"Unit";"Baneling";"Zergling";531;0
"Unit";"Overlord";"Larva";531;0
"Building";"Hatchery";NA;531;0
"Unit";"Overlord";"Larva";531;0
"Unit";"Overlord";"Larva";531;0
"Unit";"Overlord";"Larva";531;0
"Building";"CreepTumorQueen";NA;531;0
"Unit";"Zergling";"Larva";531;1
"Unit";"Zergling";"Larva";532;1
"Unit";"Zergling";"Larva";533;1
"Unit";"Zergling";"Larva";534;1
"Unit";"Zergling";"Larva";535;1
"Unit";"Zergling";"Larva";536;1
"Unit";"Zergling";"Larva";537;1
"Unit";"Zergling";"Larva";538;1
"Unit";"Zergling";"Larva";539;1
"Unit";"Zergling";"Larva";540;1
"Unit";"Zergling";"Larva";541;1
"Unit";"Zergling";"Larva";542;1
"Unit";"Zergling";"Larva";543;1
"Unit";"Zergling";"Larva";544;1
"Unit";"Zergling";"Larva";545;1
"Unit";"Zergling";"Larva";546;1
"Unit";"Zergling";"Larva";547;1
"Unit";"Zergling";"Larva";548;1
"Unit";"Zergling";"Larva";549;1
"Unit";"Zergling";"Larva";550;1
"Unit";"Zergling";"Larva";551;1
"Unit";"Zergling";"Larva";552;1
"Unit";"Zergling";"Larva";553;1
"Unit";"Zergling";"Larva";554;1
"Unit";"Zergling";"Larva";555;1
"Unit";"Zergling";"Larva";556;1
"Unit";"Zergling";"Larva";557;1
"Unit";"Zergling";"Larva";558;1
"Unit";"Zergling";"Larva";559;1
"Unit";"Zergling";"Larva";560;1
"Unit";"Zergling";"Larva";561;1
"Unit";"Zergling";"Larva";562;1
"Unit";"Ultralisk";"Larva";563;6
"Unit";"Zergling";"Larva";569;1
"Unit";"Zergling";"Larva";570;1
"Unit";"Zergling";"Larva";571;1
"Unit";"Zergling";"Larva";572;1
"Unit";"Zergling";"Larva";573;1
"Unit";"Zergling";"Larva";574;1
"Unit";"Ultralisk";"Larva";575;6
"Building";"CreepTumor";NA;581;0
"Building";"CreepTumorQueen";NA;581;0
"Building";"CreepTumor";NA;581;0
"Building";"CreepTumor";NA;581;0
"Unit";"Ultralisk";"Larva";581;6
"Unit";"Ultralisk";"Larva";587;6
"Unit";"Ultralisk";"Larva";593;6
"Unit";"Ultralisk";"Larva";599;6
"Unit";"Ultralisk";"Larva";605;6
"Unit";"Ultralisk";"Larva";611;6
"Unit";"Zergling";"Larva";617;1
"Unit";"Zergling";"Larva";618;1
"Unit";"Zergling";"Larva";619;1
"Unit";"Zergling";"Larva";620;1
"Unit";"Zergling";"Larva";621;1
"Unit";"Zergling";"Larva";622;1
"Unit";"Zergling";"Larva";623;1
"Unit";"Zergling";"Larva";624;1
"Unit";"Zergling";"Larva";625;1
"Unit";"Zergling";"Larva";626;1
"Unit";"Zergling";"Larva";627;1
"Unit";"Zergling";"Larva";628;1
"Unit";"Zergling";"Larva";629;1
"Unit";"Zergling";"Larva";630;1
"Unit";"Zergling";"Larva";631;1
"Unit";"Zergling";"Larva";632;1
"Unit";"Zergling";"Larva";633;1
"Unit";"Zergling";"Larva";634;1
"Unit";"Zergling";"Larva";635;1
"Unit";"Zergling";"Larva";636;1
"Unit";"Zergling";"Larva";637;1
"Unit";"Zergling";"Larva";638;1
"Unit";"Zergling";"Larva";639;1
"Unit";"Zergling";"Larva";640;1
"Unit";"Zergling";"Larva";641;1
"Unit";"Zergling";"Larva";642;1
"Unit";"Zergling";"Larva";643;1
"Unit";"Zergling";"Larva";644;1
"Unit";"Zergling";"Larva";645;1
"Unit";"Zergling";"Larva";646;1
"Unit";"Zergling";"Larva";647;1
"Unit";"Zergling";"Larva";648;1
"Unit";"Zergling";"Larva";649;1
"Unit";"Zergling";"Larva";650;1
"Unit";"Corruptor";"Larva";651;2
"Unit";"Corruptor";"Larva";653;2
"Building";"CreepTumorQueen";NA;655;0
"Building";"CreepTumorQueen";NA;655;0
"Unit";"Zergling";"Larva";655;1
"Unit";"Zergling";"Larva";656;1
"Unit";"Zergling";"Larva";657;1
"Unit";"Zergling";"Larva";658;1
"Unit";"Zergling";"Larva";659;1
"Unit";"Zergling";"Larva";660;1
"Unit";"Zergling";"Larva";661;1
"Unit";"Zergling";"Larva";662;1
"Unit";"Zergling";"Larva";663;1
"Unit";"Zergling";"Larva";664;1
"Unit";"Zergling";"Larva";665;1
"Unit";"Zergling";"Larva";666;1
"Unit";"Zergling";"Larva";667;1
"Unit";"Zergling";"Larva";668;1
"Unit";"Zergling";"Larva";669;1
"Unit";"Zergling";"Larva";670;1
"Unit";"Zergling";"Larva";671;1
"Unit";"Zergling";"Larva";672;1
"Unit";"Zergling";"Larva";673;1
"Unit";"Zergling";"Larva";674;1
"Unit";"Zergling";"Larva";675;1
"Unit";"Zergling";"Larva";676;1
"Unit";"Zergling";"Larva";677;1
"Unit";"Zergling";"Larva";678;1
"Unit";"Zergling";"Larva";679;1
"Unit";"Zergling";"Larva";680;1
"Building";"CreepTumorQueen";NA;681;0
"Building";"CreepTumor";NA;681;0
"Building";"CreepTumor";NA;681;0
"Building";"Hatchery";NA;681;0
"Building";"CreepTumor";NA;681;0
"Building";"CreepTumor";NA;681;0
"Unit";"Corruptor";"Larva";681;2
"Unit";"Corruptor";"Larva";683;2
"Unit";"Zergling";"Larva";685;1
"Unit";"Zergling";"Larva";686;1
"Unit";"Zergling";"Larva";687;1
"Unit";"Zergling";"Larva";688;1
"Unit";"Zergling";"Larva";689;1
"Unit";"Zergling";"Larva";690;1
"Unit";"Zergling";"Larva";691;1
"Unit";"Zergling";"Larva";692;1
"Unit";"Zergling";"Larva";693;1
"Unit";"Zergling";"Larva";694;1
"Unit";"Zergling";"Larva";695;1
"Unit";"Zergling";"Larva";696;1
"Unit";"Zergling";"Larva";697;1
"Unit";"Zergling";"Larva";698;1
"Unit";"Zergling";"Larva";699;1
"Unit";"Zergling";"Larva";700;1
"Unit";"Zergling";"Larva";701;1
"Unit";"Zergling";"Larva";702;1
"Building";"CreepTumor";NA;703;0
"Building";"CreepTumor";NA;703;0
"Building";"CreepTumor";NA;703;0
"Building";"CreepTumor";NA;703;0
"Building";"CreepTumor";NA;703;0
"Unit";"Zergling";"Larva";703;1
"Unit";"Zergling";"Larva";704;1
"Unit";"Zergling";"Larva";705;1
"Unit";"Zergling";"Larva";706;1
"Unit";"Zergling";"Larva";707;1
"Unit";"Zergling";"Larva";708;1
"Unit";"Zergling";"Larva";709;1
"Unit";"Zergling";"Larva";710;1
"Unit";"Zergling";"Larva";711;1
"Unit";"Zergling";"Larva";712;1
"Building";"CreepTumor";NA;713;0
"Building";"Hatchery";NA;713;0
"Building";"CreepTumor";NA;713;0
"Unit";"Ultralisk";"Larva";713;6
"Building";"CreepTumorQueen";NA;719;0
"Building";"CreepTumorQueen";NA;719;0
"Unit";"Corruptor";"Larva";719;2
"Unit";"Corruptor";"Larva";721;2
"Unit";"Corruptor";"Larva";723;2
"Unit";"Zergling";"Larva";725;1
"Unit";"Zergling";"Larva";726;1
"Unit";"Zergling";"Larva";727;1
"Unit";"Zergling";"Larva";728;1
"Unit";"Zergling";"Larva";729;1
"Unit";"Zergling";"Larva";730;1
"Unit";"Zergling";"Larva";731;1
"Unit";"Zergling";"Larva";732;1
"Unit";"Zergling";"Larva";733;1
"Unit";"Zergling";"Larva";734;1
"Unit";"Zergling";"Larva";735;1
"Unit";"Zergling";"Larva";736;1
"Unit";"Zergling";"Larva";737;1
"Unit";"Zergling";"Larva";738;1
"Unit";"Zergling";"Larva";739;1
"Unit";"Zergling";"Larva";740;1
"Unit";"Zergling";"Larva";741;1
"Unit";"Zergling";"Larva";742;1
"Unit";"Zergling";"Larva";743;1
"Unit";"Zergling";"Larva";744;1
"Unit";"Zergling";"Larva";745;1
"Unit";"Zergling";"Larva";746;1
"Unit";"Zergling";"Larva";747;1
"Unit";"Zergling";"Larva";748;1
"Unit";"Zergling";"Larva";749;1
"Unit";"Zergling";"Larva";750;1
"Unit";"Zergling";"Larva";751;1
"Unit";"Zergling";"Larva";752;1
"Unit";"Zergling";"Larva";753;1
"Unit";"Zergling";"Larva";754;1
"Unit";"Zergling";"Larva";755;1
"Unit";"Zergling";"Larva";756;1
"Unit";"Zergling";"Larva";757;1
"Unit";"Zergling";"Larva";758;1
"Unit";"Zergling";"Larva";759;1
"Unit";"Zergling";"Larva";760;1
"Unit";"Zergling";"Larva";761;1
"Unit";"Zergling";"Larva";762;1
"Unit";"Zergling";"Larva";763;1
"Unit";"Zergling";"Larva";764;1
"Unit";"Zergling";"Larva";765;1
"Unit";"Zergling";"Larva";766;1
"Unit";"Zergling";"Larva";767;1
"Unit";"Zergling";"Larva";768;1
"Unit";"Zergling";"Larva";769;1
"Unit";"Zergling";"Larva";770;1
"Unit";"Zergling";"Larva";771;1
"Unit";"Zergling";"Larva";772;1
"Unit";"Ultralisk";"Larva";773;6
"Unit";"Zergling";"Larva";779;1
"Unit";"Zergling";"Larva";780;1
"Unit";"Zergling";"Larva";781;1
"Unit";"Zergling";"Larva";782;1
"Unit";"Zergling";"Larva";783;1
"Unit";"Zergling";"Larva";784;1
"Unit";"Zergling";"Larva";785;1
"Unit";"Zergling";"Larva";786;1
"Unit";"Zergling";"Larva";787;1
"Unit";"Zergling";"Larva";788;1
"Unit";"Zergling";"Larva";789;1
"Unit";"Zergling";"Larva";790;1
"Unit";"Baneling";"Zergling";791;0
"Unit";"Baneling";"Zergling";791;0
"Unit";"Baneling";"Zergling";791;0
"Unit";"Baneling";"Zergling";791;0
"Unit";"Baneling";"Zergling";791;0
"Unit";"Baneling";"Zergling";791;0
"Building";"CreepTumorQueen";NA;791;0
"Building";"CreepTumorQueen";NA;791;0
"Building";"CreepTumorQueen";NA;791;0
"Building";"CreepTumorQueen";NA;791;0
"Building";"CreepTumorQueen";NA;791;0
"Building";"CreepTumorQueen";NA;791;0
"Unit";"Zergling";"Larva";791;1
"Unit";"Zergling";"Larva";792;1
"Unit";"Zergling";"Larva";793;1
"Unit";"Zergling";"Larva";794;1
"Unit";"Zergling";"Larva";795;1
"Unit";"Zergling";"Larva";796;1
"Building";"Extractor";NA;797;0
"Unit";"Ultralisk";"Larva";797;6
"Unit";"Ultralisk";"Larva";803;6
"Unit";"Ultralisk";"Larva";809;6
"Unit";"Zergling";"Larva";815;1
"Unit";"Zergling";"Larva";816;1
"Unit";"Zergling";"Larva";817;1
"Unit";"Zergling";"Larva";818;1
"Unit";"Zergling";"Larva";819;1
"Unit";"Zergling";"Larva";820;1
"Unit";"Zergling";"Larva";821;1
"Unit";"Zergling";"Larva";822;1
"Unit";"Zergling";"Larva";823;1
"Unit";"Zergling";"Larva";824;1
"Unit";"Zergling";"Larva";825;1
"Unit";"Zergling";"Larva";826;1
"Unit";"Zergling";"Larva";827;1
"Unit";"Zergling";"Larva";828;1
"Unit";"Zergling";"Larva";829;1
"Unit";"Zergling";"Larva";830;1
"Unit";"Zergling";"Larva";831;1
"Unit";"Zergling";"Larva";832;1
"Unit";"Zergling";"Larva";833;1
"Unit";"Zergling";"Larva";834;1
"Unit";"Zergling";"Larva";835;1
"Unit";"Zergling";"Larva";836;1
"Unit";"Zergling";"Larva";837;1
"Unit";"Zergling";"Larva";838;1
"Unit";"Zergling";"Larva";839;1
"Unit";"Zergling";"Larva";840;1
"Unit";"Zergling";"Larva";841;1
"Unit";"Zergling";"Larva";842;1
"Unit";"Zergling";"Larva";843;1
"Unit";"Zergling";"Larva";844;1
"Unit";"Zergling";"Larva";845;1
"Unit";"Zergling";"Larva";846;1
"Building";"CreepTumorQueen";NA;847;0
"Building";"CreepTumorQueen";NA;847;0
"Building";"CreepTumorQueen";NA;847;0
"Building";"CreepTumorQueen";NA;847;0
"Unit";"Ultralisk";"Larva";847;6
"Unit";"Zergling";"Larva";853;1
"Unit";"Zergling";"Larva";854;1
"Unit";"Zergling";"Larva";855;1
"Unit";"Zergling";"Larva";856;1
"Unit";"Zergling";"Larva";857;1
"Unit";"Zergling";"Larva";858;1
"Unit";"Zergling";"Larva";859;1
"Unit";"Zergling";"Larva";860;1
"Unit";"Zergling";"Larva";861;1
"Unit";"Zergling";"Larva";862;1
"Unit";"Zergling";"Larva";863;1
"Unit";"Zergling";"Larva";864;1
"Unit";"Zergling";"Larva";865;1
"Unit";"Zergling";"Larva";866;1
"Unit";"Zergling";"Larva";867;1
"Unit";"Zergling";"Larva";868;1
"Unit";"Zergling";"Larva";869;1
"Unit";"Zergling";"Larva";870;1
"Unit";"Zergling";"Larva";871;1
"Unit";"Zergling";"Larva";872;1
"Unit";"Ultralisk";"Larva";873;6
"Unit";"Zergling";"Larva";879;1
"Unit";"Zergling";"Larva";880;1
"Unit";"Zergling";"Larva";881;1
"Unit";"Zergling";"Larva";882;1
"Unit";"Zergling";"Larva";883;1
"Unit";"Zergling";"Larva";884;1
"Unit";"Zergling";"Larva";885;1
"Unit";"Zergling";"Larva";886;1
"Unit";"Zergling";"Larva";887;1
"Unit";"Zergling";"Larva";888;1
"Unit";"Zergling";"Larva";889;1
"Unit";"Zergling";"Larva";890;1
"Unit";"Zergling";"Larva";891;1
"Unit";"Zergling";"Larva";892;1
"Unit";"Zergling";"Larva";893;1
"Unit";"Zergling";"Larva";894;1
"Unit";"Zergling";"Larva";895;1
"Unit";"Zergling";"Larva";896;1
"Unit";"Zergling";"Larva";897;1
"Unit";"Zergling";"Larva";898;1
"Building";"CreepTumor";NA;899;0
"Building";"CreepTumorQueen";NA;899;0
"Building";"CreepTumorQueen";NA;899;0
"Building";"CreepTumorQueen";NA;899;0
"Unit";"Zergling";"Larva";899;1
"Unit";"Zergling";"Larva";900;1
"Unit";"Zergling";"Larva";901;1
"Unit";"Zergling";"Larva";902;1
"Building";"Hatchery";NA;903;0
"Building";"CreepTumorQueen";NA;903;0
"Building";"CreepTumorQueen";NA;903;0
"Unit";"Zergling";"Larva";903;1
"Unit";"Zergling";"Larva";904;1
"Unit";"Zergling";"Larva";905;1
"Unit";"Zergling";"Larva";906;1
"Unit";"Zergling";"Larva";907;1
"Unit";"Zergling";"Larva";908;1
"Unit";"Zergling";"Larva";909;1
"Unit";"Zergling";"Larva";910;1
"Unit";"Zergling";"Larva";911;1
"Unit";"Zergling";"Larva";912;1
"Unit";"Zergling";"Larva";913;1
"Unit";"Zergling";"Larva";914;1
"Unit";"Zergling";"Larva";915;1
"Unit";"Zergling";"Larva";916;1
"Unit";"Zergling";"Larva";917;1
"Unit";"Zergling";"Larva";918;1
"Unit";"Zergling";"Larva";919;1
"Unit";"Zergling";"Larva";920;1
"Unit";"Zergling";"Larva";921;1
"Unit";"Zergling";"Larva";922;1
"Unit";"Zergling";"Larva";923;1
"Unit";"Zergling";"Larva";924;1
"Unit";"Zergling";"Larva";925;1
"Unit";"Zergling";"Larva";926;1
"Unit";"Zergling";"Larva";927;1
"Unit";"Zergling";"Larva";928;1
"Unit";"Zergling";"Larva";929;1
"Unit";"Zergling";"Larva";930;1
"Unit";"Zergling";"Larva";931;1
"Unit";"Zergling";"Larva";932;1
"Unit";"Ultralisk";"Larva";933;6
"Unit";"Ultralisk";"Larva";939;6
"Unit";"Zergling";"Larva";945;1
"Unit";"Zergling";"Larva";946;1
"Unit";"Zergling";"Larva";947;1
"Unit";"Zergling";"Larva";948;1
"Unit";"Zergling";"Larva";949;1
"Unit";"Zergling";"Larva";950;1
"Unit";"Zergling";"Larva";951;1
"Unit";"Zergling";"Larva";952;1
"Unit";"Zergling";"Larva";953;1
"Unit";"Zergling";"Larva";954;1
"Unit";"Zergling";"Larva";955;1
"Unit";"Zergling";"Larva";956;1
"Unit";"Zergling";"Larva";957;1
"Unit";"Zergling";"Larva";958;1
"Unit";"Zergling";"Larva";959;1
"Unit";"Zergling";"Larva";960;1
"Unit";"Zergling";"Larva";961;1
"Unit";"Zergling";"Larva";962;1
"Unit";"Zergling";"Larva";963;1
"Unit";"Zergling";"Larva";964;1
"Unit";"Zergling";"Larva";965;1
"Unit";"Zergling";"Larva";966;1
"Unit";"Zergling";"Larva";967;1
"Unit";"Zergling";"Larva";968;1
"Unit";"Zergling";"Larva";969;1
"Unit";"Zergling";"Larva";970;1
"Building";"CreepTumor";NA;971;0
"Building";"CreepTumor";NA;971;0
"Building";"CreepTumor";NA;971;0
"Building";"Extractor";NA;971;0
"Building";"Extractor";NA;971;0
"Unit";"Zergling";"Larva";971;1
"Unit";"Zergling";"Larva";972;1
"Unit";"Zergling";"Larva";973;1
"Unit";"Zergling";"Larva";974;1
"Unit";"Zergling";"Larva";975;1
"Unit";"Zergling";"Larva";976;1
"Unit";"Zergling";"Larva";977;1
"Unit";"Zergling";"Larva";978;1
"Unit";"Zergling";"Larva";979;1
"Unit";"Zergling";"Larva";980;1
"Unit";"Zergling";"Larva";981;1
"Unit";"Zergling";"Larva";982;1
"Unit";"Zergling";"Larva";983;1
"Unit";"Zergling";"Larva";984;1
"Unit";"Zergling";"Larva";985;1
"Unit";"Zergling";"Larva";986;1
"Building";"CreepTumor";NA;987;0
"Building";"CreepTumor";NA;987;0
"Building";"CreepTumorQueen";NA;987;0
"Upgrade";"Burrow";"Hatchery";987;0
"Unit";"Ultralisk";"Larva";987;6
"Unit";"Zergling";"Larva";993;1
"Unit";"Zergling";"Larva";994;1
"Unit";"Zergling";"Larva";995;1
"Unit";"Zergling";"Larva";996;1
"Unit";"Zergling";"Larva";997;1
"Unit";"Zergling";"Larva";998;1
"Unit";"Zergling";"Larva";999;1
"Unit";"Zergling";"Larva";1000;1
"Unit";"Zergling";"Larva";1001;1
"Unit";"Zergling";"Larva";1002;1
"Unit";"Zergling";"Larva";1003;1
"Unit";"Zergling";"Larva";1004;1
"Unit";"Zergling";"Larva";1005;1
"Unit";"Zergling";"Larva";1006;1
"Unit";"Zergling";"Larva";1007;1
"Unit";"Zergling";"Larva";1008;1
"Unit";"Zergling";"Larva";1009;1
"Unit";"Zergling";"Larva";1010;1
"Unit";"Zergling";"Larva";1011;1
"Unit";"Zergling";"Larva";1012;1
"Unit";"Zergling";"Larva";1013;1
"Unit";"Zergling";"Larva";1014;1
"Unit";"Zergling";"Larva";1015;1
"Unit";"Zergling";"Larva";1016;1
"Unit";"Zergling";"Larva";1017;1
"Unit";"Zergling";"Larva";1018;1
"Unit";"Zergling";"Larva";1019;1
"Unit";"Zergling";"Larva";1020;1
"Unit";"Zergling";"Larva";1021;1
"Unit";"Zergling";"Larva";1022;1
"Unit";"Zergling";"Larva";1023;1
"Unit";"Zergling";"Larva";1024;1
"Unit";"Zergling";"Larva";1025;1
"Unit";"Zergling";"Larva";1026;1
"Unit";"Zergling";"Larva";1027;1
"Unit";"Zergling";"Larva";1028;1
"Unit";"Zergling";"Larva";1029;1
"Unit";"Zergling";"Larva";1030;1
"Unit";"Zergling";"Larva";1031;1
"Unit";"Zergling";"Larva";1032;1
"Unit";"Zergling";"Larva";1033;1
"Unit";"Zergling";"Larva";1034;1
"Unit";"Zergling";"Larva";1035;1
"Unit";"Zergling";"Larva";1036;1
"Unit";"Zergling";"Larva";1037;1
"Unit";"Zergling";"Larva";1038;1
"Unit";"Zergling";"Larva";1039;1
"Unit";"Zergling";"Larva";1040;1
"Unit";"Overlord";"Larva";1041;0
"Unit";"Overlord";"Larva";1041;0
"Building";"Extractor";NA;1041;0
"Building";"Extractor";NA;1041;0
"Building";"Extractor";NA;1041;0
"Building";"Extractor";NA;1041;0
"Building";"CreepTumor";NA;1041;0
"Unit";"Baneling";"Zergling";1041;0
"Unit";"Baneling";"Zergling";1041;0
"Unit";"Baneling";"Zergling";1041;0
"Unit";"Baneling";"Zergling";1041;0
"Unit";"Baneling";"Zergling";1041;0
"Unit";"Baneling";"Zergling";1041;0
"Unit";"Baneling";"Zergling";1041;0
"Unit";"Baneling";"Zergling";1041;0
"Upgrade";"SprayZerg";NA;1041;0
"Upgrade";"SprayZerg";NA;1041;0
"Upgrade";"SprayZerg";NA;1041;0
"Upgrade";"zerglingmovementspeed";NA;1041;0
"Upgrade";"SprayZerg";NA;1041;0
"Upgrade";"SprayZerg";NA;1041;0
"Upgrade";"SprayZerg";NA;1041;0
"Upgrade";"SprayZerg";NA;1041;0
"Upgrade";"SprayZerg";NA;1041;0
"Upgrade";"SprayZerg";NA;1041;0
"Upgrade";"SprayZerg";NA;1041;0
"Upgrade";"ZergGroundArmorsLevel1";NA;1041;0
"Upgrade";"ZergMeleeWeaponsLevel1";NA;1041;0
"Upgrade";"CentrificalHooks";NA;1041;0
"Upgrade";"overlordspeed";NA;1041;0
"Upgrade";"ZergGroundArmorsLevel2";NA;1041;0
"Upgrade";"ZergMeleeWeaponsLevel2";NA;1041;0
"Upgrade";"ZergGroundArmorsLevel3";NA;1041;0
"Upgrade";"ZergMeleeWeaponsLevel3";NA;1041;0
"Upgrade";"SprayZerg";NA;1041;0
"Upgrade";"SprayZerg";NA;1041;0
"Upgrade";"SprayZerg";NA;1041;0
"Upgrade";"SprayZerg";NA;1041;0
"Upgrade";"SprayZerg";NA;1041;0
"Upgrade";"zerglingattackspeed";NA;1041;0
"Upgrade";"SprayZerg";NA;1041;0
"Upgrade";"SprayZerg";NA;1041;0
"Upgrade";"SprayZerg";NA;1041;0
"Upgrade";"SprayZerg";NA;1041;0
"Upgrade";"SprayZerg";NA;1041;0
"Upgrade";"SprayZerg";NA;1041;0
"Upgrade";"SprayZerg";NA;1041;0
"Upgrade";"SprayZerg";NA;1041;0
