"type";"unit_name";"on_building";"total_supply_lag";"supply"
"Unit";"Overlord";"Larva";13;0
"Building";"Hatchery";NA;17;0
"Building";"Extractor";NA;19;0
"Building";"SpawningPool";NA;19;0
"Unit";"Overlord";"Larva";22;0
"Unit";"Queen";"Hatchery";23;2
"Unit";"Zergling";"Larva";25;1
"Unit";"Zergling";"Larva";26;1
"Unit";"Queen";"Hatchery";27;2
"Unit";"Zergling";"Larva";29;1
"Unit";"Zergling";"Larva";30;1
"Unit";"Queen";"Hatchery";36;2
"Unit";"Queen";"Hatchery";38;2
"Unit";"Overlord";"Larva";40;0
"Building";"EvolutionChamber";NA;40;0
"Unit";"Zergling";"Larva";40;1
"Unit";"Zergling";"Larva";41;1
"Unit";"Zergling";"Larva";43;1
"Unit";"Zergling";"Larva";44;1
"Unit";"Zergling";"Larva";45;1
"Unit";"Zergling";"Larva";46;1
"Unit";"Zergling";"Larva";47;1
"Unit";"Zergling";"Larva";48;1
"Unit";"Zergling";"Larva";49;1
"Unit";"Zergling";"Larva";50;1
"Unit";"Zergling";"Larva";51;1
"Unit";"Zergling";"Larva";52;1
"Unit";"Zergling";"Larva";53;1
"Unit";"Zergling";"Larva";54;1
"Unit";"Queen";"Hatchery";55;2
"Unit";"Overlord";"Larva";57;0
"Unit";"Overlord";"Larva";57;0
"Unit";"Queen";"Hatchery";58;2
"Unit";"Queen";"Hatchery";60;2
"Unit";"Zergling";"Larva";70;1
"Unit";"Zergling";"Larva";71;1
"Unit";"Zergling";"Larva";72;1
"Unit";"Zergling";"Larva";73;1
"Unit";"Zergling";"Larva";74;1
"Unit";"Zergling";"Larva";75;1
"Unit";"Zergling";"Larva";76;1
"Unit";"Zergling";"Larva";77;1
"Building";"CreepTumorQueen";NA;78;0
"Building";"CreepTumorQueen";NA;78;0
"Unit";"Overlord";"Larva";78;0
"Unit";"Overlord";"Larva";78;0
"Unit";"Overlord";"Larva";78;0
"Building";"EvolutionChamber";NA;80;0
"Unit";"Queen";"Hatchery";80;2
"Unit";"Zergling";"Larva";82;1
"Unit";"Zergling";"Larva";83;1
"Unit";"Zergling";"Larva";84;1
"Unit";"Zergling";"Larva";85;1
"Unit";"Zergling";"Larva";86;1
"Unit";"Zergling";"Larva";87;1
"Unit";"Zergling";"Larva";88;1
"Unit";"Zergling";"Larva";89;1
"Unit";"Zergling";"Larva";90;1
"Unit";"Zergling";"Larva";91;1
"Building";"CreepTumorQueen";NA;92;0
"Unit";"Zergling";"Larva";92;1
"Unit";"Zergling";"Larva";93;1
"Unit";"Zergling";"Larva";94;1
"Unit";"Zergling";"Larva";95;1
"Unit";"Zergling";"Larva";96;1
"Unit";"Zergling";"Larva";97;1
"Unit";"Zergling";"Larva";98;1
"Unit";"Zergling";"Larva";99;1
"Unit";"Zergling";"Larva";100;1
"Unit";"Zergling";"Larva";101;1
"Unit";"Zergling";"Larva";102;1
"Unit";"Zergling";"Larva";103;1
"Unit";"Zergling";"Larva";104;1
"Unit";"Zergling";"Larva";105;1
"Unit";"Zergling";"Larva";106;1
"Unit";"Zergling";"Larva";107;1
"Unit";"Zergling";"Larva";108;1
"Unit";"Zergling";"Larva";109;1
"Unit";"Zergling";"Larva";110;1
"Unit";"Zergling";"Larva";111;1
"Unit";"Zergling";"Larva";112;1
"Unit";"Zergling";"Larva";113;1
"Unit";"Zergling";"Larva";114;1
"Unit";"Zergling";"Larva";115;1
"Building";"Hatchery";NA;116;0
"Unit";"Zergling";"Larva";116;1
"Unit";"Zergling";"Larva";117;1
"Unit";"Zergling";"Larva";118;1
"Unit";"Zergling";"Larva";119;1
"Unit";"Zergling";"Larva";120;1
"Unit";"Zergling";"Larva";121;1
"Unit";"Zergling";"Larva";122;1
"Unit";"Zergling";"Larva";123;1
"Unit";"Queen";"Hatchery";124;2
"Building";"Extractor";NA;126;0
"Building";"CreepTumor";NA;126;0
"Building";"Extractor";NA;126;0
"Unit";"Zergling";"Larva";126;1
"Unit";"Zergling";"Larva";127;1
"Unit";"Zergling";"Larva";128;1
"Unit";"Zergling";"Larva";129;1
"Unit";"Zergling";"Larva";130;1
"Unit";"Zergling";"Larva";131;1
"Unit";"Zergling";"Larva";132;1
"Unit";"Zergling";"Larva";133;1
"Unit";"Zergling";"Larva";134;1
"Unit";"Zergling";"Larva";135;1
"Building";"CreepTumorQueen";NA;136;0
"Unit";"Zergling";"Larva";136;1
"Unit";"Zergling";"Larva";137;1
"Unit";"Zergling";"Larva";138;1
"Unit";"Zergling";"Larva";139;1
"Unit";"Zergling";"Larva";140;1
"Unit";"Zergling";"Larva";141;1
"Unit";"Zergling";"Larva";142;1
"Unit";"Zergling";"Larva";143;1
"Unit";"Zergling";"Larva";144;1
"Unit";"Zergling";"Larva";145;1
"Unit";"Zergling";"Larva";146;1
"Unit";"Zergling";"Larva";147;1
"Unit";"Zergling";"Larva";148;1
"Unit";"Zergling";"Larva";149;1
"Unit";"Queen";"Hatchery";150;2
"Building";"CreepTumor";NA;154;0
"Building";"CreepTumor";NA;154;0
"Building";"CreepTumorQueen";NA;154;0
"Unit";"Queen";"Hatchery";154;2
"Unit";"Zergling";"Larva";156;1
"Unit";"Zergling";"Larva";157;1
"Unit";"Zergling";"Larva";158;1
"Unit";"Zergling";"Larva";159;1
"Unit";"Zergling";"Larva";160;1
"Unit";"Zergling";"Larva";161;1
"Unit";"Zergling";"Larva";162;1
"Unit";"Zergling";"Larva";163;1
"Unit";"Zergling";"Larva";164;1
"Unit";"Zergling";"Larva";165;1
"Unit";"Zergling";"Larva";166;1
"Unit";"Zergling";"Larva";167;1
"Unit";"Zergling";"Larva";168;1
"Unit";"Zergling";"Larva";169;1
"Building";"BanelingNest";NA;170;0
"Unit";"Overlord";"Larva";176;0
"Unit";"Overlord";"Larva";176;0
"Building";"CreepTumor";NA;176;0
"Building";"CreepTumorQueen";NA;176;0
"Building";"CreepTumor";NA;176;0
"Building";"CreepTumor";NA;176;0
"Unit";"Queen";"Hatchery";176;2
"Building";"HydraliskDen";NA;189;0
"Building";"CreepTumor";NA;189;0
"Building";"CreepTumor";NA;189;0
"Building";"CreepTumor";NA;189;0
"Building";"CreepTumor";NA;189;0
"Building";"CreepTumorQueen";NA;189;0
"Unit";"Overlord";"Larva";189;0
"Unit";"Overlord";"Larva";189;0
"Unit";"Overlord";"Larva";189;0
"Building";"CreepTumorQueen";NA;190;0
"Building";"CreepTumorQueen";NA;190;0
"Building";"Hatchery";NA;194;0
"Building";"CreepTumor";NA;194;0
"Building";"CreepTumor";NA;194;0
"Building";"CreepTumor";NA;194;0
"Building";"CreepTumor";NA;194;0
"Building";"CreepTumor";NA;194;0
"Building";"CreepTumor";NA;194;0
"Unit";"Queen";"Hatchery";194;2
"Building";"CreepTumorQueen";NA;196;0
"Building";"Extractor";NA;198;0
"Building";"Extractor";NA;200;0
"Unit";"Hydralisk";"Larva";200;2
"Unit";"Hydralisk";"Larva";202;2
"Unit";"Hydralisk";"Larva";204;2
"Unit";"Hydralisk";"Larva";206;2
"Unit";"Hydralisk";"Larva";208;2
"Unit";"Hydralisk";"Larva";210;2
"Unit";"Hydralisk";"Larva";212;2
"Building";"CreepTumor";NA;214;0
"Building";"CreepTumor";NA;214;0
"Building";"CreepTumor";NA;214;0
"Building";"CreepTumorQueen";NA;214;0
"Unit";"Overlord";"Larva";216;0
"Building";"CreepTumorQueen";NA;216;0
"Unit";"Overlord";"Larva";216;0
"Building";"Extractor";NA;216;0
"Building";"CreepTumor";NA;216;0
"Building";"CreepTumor";NA;216;0
"Unit";"Hydralisk";"Larva";216;2
"Unit";"Hydralisk";"Larva";218;2
"Unit";"Hydralisk";"Larva";220;2
"Building";"CreepTumorQueen";NA;222;0
"Building";"Hatchery";NA;223;0
"Unit";"Hydralisk";"Larva";223;2
"Unit";"Hydralisk";"Larva";225;2
"Unit";"Hydralisk";"Larva";227;2
"Unit";"Baneling";"Zergling";229;0
"Unit";"Baneling";"Zergling";229;0
"Unit";"Zergling";"Larva";229;1
"Unit";"Zergling";"Larva";230;1
"Unit";"Zergling";"Larva";231;1
"Unit";"Zergling";"Larva";232;1
"Unit";"Zergling";"Larva";233;1
"Unit";"Zergling";"Larva";234;1
"Unit";"Zergling";"Larva";235;1
"Unit";"Zergling";"Larva";236;1
"Unit";"Zergling";"Larva";237;1
"Unit";"Zergling";"Larva";238;1
"Unit";"Zergling";"Larva";239;1
"Unit";"Zergling";"Larva";240;1
"Unit";"Zergling";"Larva";241;1
"Unit";"Zergling";"Larva";242;1
"Building";"CreepTumor";NA;243;0
"Building";"CreepTumor";NA;243;0
"Building";"CreepTumor";NA;243;0
"Building";"CreepTumor";NA;243;0
"Building";"CreepTumor";NA;243;0
"Building";"CreepTumor";NA;243;0
"Building";"CreepTumor";NA;243;0
"Unit";"Baneling";"Zergling";243;0
"Unit";"Baneling";"Zergling";243;0
"Unit";"Baneling";"Zergling";243;0
"Unit";"Baneling";"Zergling";243;0
"Unit";"Baneling";"Zergling";243;0
"Unit";"Baneling";"Zergling";243;0
"Unit";"Baneling";"Zergling";243;0
"Unit";"Baneling";"Zergling";243;0
"Unit";"Zergling";"Larva";243;1
"Unit";"Zergling";"Larva";244;1
"Unit";"Zergling";"Larva";245;1
"Unit";"Zergling";"Larva";246;1
"Unit";"Zergling";"Larva";247;1
"Unit";"Zergling";"Larva";248;1
"Unit";"Zergling";"Larva";249;1
"Unit";"Zergling";"Larva";250;1
"Unit";"Zergling";"Larva";251;1
"Unit";"Zergling";"Larva";252;1
"Unit";"Zergling";"Larva";253;1
"Unit";"Zergling";"Larva";254;1
"Unit";"Zergling";"Larva";255;1
"Unit";"Zergling";"Larva";256;1
"Unit";"Zergling";"Larva";257;1
"Unit";"Zergling";"Larva";258;1
"Unit";"Zergling";"Larva";259;1
"Unit";"Zergling";"Larva";260;1
"Unit";"Overlord";"Larva";268;0
"Building";"CreepTumor";NA;268;0
"Building";"CreepTumor";NA;268;0
"Building";"CreepTumorQueen";NA;268;0
"Building";"CreepTumorQueen";NA;268;0
"Building";"CreepTumor";NA;268;0
"Building";"CreepTumor";NA;268;0
"Building";"CreepTumor";NA;268;0
"Building";"CreepTumor";NA;268;0
"Building";"CreepTumor";NA;268;0
"Unit";"Overlord";"Larva";268;0
"Unit";"Baneling";"Zergling";270;0
"Unit";"Baneling";"Zergling";270;0
"Unit";"Baneling";"Zergling";270;0
"Unit";"Baneling";"Zergling";270;0
"Unit";"Baneling";"Zergling";270;0
"Unit";"Baneling";"Zergling";270;0
"Unit";"Hydralisk";"Larva";270;2
"Unit";"Hydralisk";"Larva";272;2
"Unit";"Hydralisk";"Larva";274;2
"Building";"CreepTumor";NA;276;0
"Building";"CreepTumor";NA;276;0
"Building";"CreepTumor";NA;276;0
"Building";"CreepTumor";NA;276;0
"Unit";"Overlord";"Larva";276;0
"Unit";"Overlord";"Larva";276;0
"Unit";"Overlord";"Larva";276;0
"Unit";"Overlord";"Larva";276;0
"Unit";"Baneling";"Zergling";282;0
"Unit";"Baneling";"Zergling";282;0
"Unit";"Baneling";"Zergling";282;0
"Unit";"Baneling";"Zergling";282;0
"Unit";"Baneling";"Zergling";282;0
"Unit";"Baneling";"Zergling";282;0
"Unit";"Baneling";"Zergling";282;0
"Unit";"Baneling";"Zergling";282;0
"Unit";"Baneling";"Zergling";282;0
"Building";"CreepTumorQueen";NA;282;0
"Unit";"Hydralisk";"Larva";282;2
"Unit";"Zergling";"Larva";284;1
"Unit";"Zergling";"Larva";285;1
"Unit";"Zergling";"Larva";286;1
"Unit";"Zergling";"Larva";287;1
"Unit";"Zergling";"Larva";288;1
"Unit";"Zergling";"Larva";289;1
"Unit";"Zergling";"Larva";290;1
"Unit";"Zergling";"Larva";291;1
"Unit";"Zergling";"Larva";292;1
"Unit";"Zergling";"Larva";293;1
"Unit";"Zergling";"Larva";294;1
"Unit";"Zergling";"Larva";295;1
"Building";"InfestationPit";NA;297;0
"Building";"CreepTumorQueen";NA;297;0
"Building";"CreepTumorQueen";NA;297;0
"Building";"CreepTumorQueen";NA;297;0
"Building";"CreepTumor";NA;297;0
"Building";"CreepTumor";NA;297;0
"Building";"Hatchery";NA;297;0
"Unit";"Baneling";"Zergling";297;0
"Unit";"Baneling";"Zergling";297;0
"Unit";"Baneling";"Zergling";297;0
"Unit";"Baneling";"Zergling";297;0
"Unit";"Baneling";"Zergling";297;0
"Unit";"Baneling";"Zergling";297;0
"Unit";"Baneling";"Zergling";297;0
"Unit";"Zergling";"Larva";297;1
"Unit";"Zergling";"Larva";298;1
"Unit";"Zergling";"Larva";299;1
"Unit";"Zergling";"Larva";300;1
"Unit";"Zergling";"Larva";301;1
"Unit";"Zergling";"Larva";302;1
"Unit";"Zergling";"Larva";303;1
"Unit";"Zergling";"Larva";304;1
"Unit";"Zergling";"Larva";305;1
"Unit";"Zergling";"Larva";306;1
"Unit";"Zergling";"Larva";307;1
"Unit";"Zergling";"Larva";308;1
"Unit";"Zergling";"Larva";309;1
"Unit";"Zergling";"Larva";310;1
"Unit";"Zergling";"Larva";311;1
"Unit";"Zergling";"Larva";312;1
"Unit";"Zergling";"Larva";313;1
"Unit";"Zergling";"Larva";314;1
"Unit";"Zergling";"Larva";315;1
"Unit";"Zergling";"Larva";316;1
"Unit";"Zergling";"Larva";317;1
"Unit";"Zergling";"Larva";318;1
"Building";"CreepTumorQueen";NA;319;0
"Building";"CreepTumorQueen";NA;319;0
"Building";"CreepTumorQueen";NA;319;0
"Building";"CreepTumorQueen";NA;319;0
"Unit";"Hydralisk";"Larva";319;2
"Unit";"Hydralisk";"Larva";321;2
"Unit";"Zergling";"Larva";323;1
"Unit";"Zergling";"Larva";324;1
"Unit";"Zergling";"Larva";325;1
"Unit";"Zergling";"Larva";326;1
"Unit";"Zergling";"Larva";327;1
"Unit";"Zergling";"Larva";328;1
"Unit";"Zergling";"Larva";329;1
"Unit";"Zergling";"Larva";330;1
"Unit";"Zergling";"Larva";331;1
"Unit";"Zergling";"Larva";332;1
"Unit";"Zergling";"Larva";333;1
"Unit";"Zergling";"Larva";334;1
"Unit";"Zergling";"Larva";335;1
"Unit";"Zergling";"Larva";336;1
"Unit";"Zergling";"Larva";337;1
"Unit";"Zergling";"Larva";338;1
"Unit";"Zergling";"Larva";339;1
"Unit";"Zergling";"Larva";340;1
"Unit";"Zergling";"Larva";341;1
"Unit";"Zergling";"Larva";342;1
"Unit";"Zergling";"Larva";343;1
"Unit";"Zergling";"Larva";344;1
"Unit";"Zergling";"Larva";345;1
"Unit";"Zergling";"Larva";346;1
"Unit";"Zergling";"Larva";347;1
"Unit";"Zergling";"Larva";348;1
"Unit";"Zergling";"Larva";349;1
"Unit";"Zergling";"Larva";350;1
"Unit";"Zergling";"Larva";351;1
"Unit";"Zergling";"Larva";352;1
"Building";"Hatchery";NA;353;0
"Unit";"Baneling";"Zergling";353;0
"Unit";"Baneling";"Zergling";353;0
"Unit";"Baneling";"Zergling";353;0
"Unit";"Baneling";"Zergling";353;0
"Building";"CreepTumorQueen";NA;353;0
"Unit";"Baneling";"Zergling";353;0
"Unit";"Baneling";"Zergling";353;0
"Unit";"Baneling";"Zergling";353;0
"Unit";"Baneling";"Zergling";353;0
"Unit";"Baneling";"Zergling";353;0
"Unit";"Baneling";"Zergling";353;0
"Building";"CreepTumorQueen";NA;353;0
"Building";"CreepTumorQueen";NA;353;0
"Unit";"Baneling";"Zergling";356;0
"Unit";"Baneling";"Zergling";356;0
"Unit";"Baneling";"Zergling";356;0
"Unit";"Baneling";"Zergling";356;0
"Unit";"Baneling";"Zergling";356;0
"Unit";"Zergling";"Larva";361;1
"Unit";"Zergling";"Larva";362;1
"Unit";"Zergling";"Larva";363;1
"Unit";"Zergling";"Larva";364;1
"Unit";"Zergling";"Larva";365;1
"Unit";"Zergling";"Larva";366;1
"Unit";"Zergling";"Larva";367;1
"Unit";"Zergling";"Larva";368;1
"Unit";"Zergling";"Larva";369;1
"Unit";"Zergling";"Larva";370;1
"Unit";"Zergling";"Larva";371;1
"Unit";"Zergling";"Larva";372;1
"Unit";"Zergling";"Larva";373;1
"Unit";"Zergling";"Larva";374;1
"Unit";"Zergling";"Larva";375;1
"Unit";"Zergling";"Larva";376;1
"Unit";"Zergling";"Larva";377;1
"Unit";"Zergling";"Larva";378;1
"Unit";"Zergling";"Larva";379;1
"Unit";"Zergling";"Larva";380;1
"Building";"CreepTumor";NA;381;0
"Building";"CreepTumor";NA;381;0
"Building";"CreepTumor";NA;381;0
"Unit";"Hydralisk";"Larva";381;2
"Unit";"Zergling";"Larva";383;1
"Unit";"Zergling";"Larva";384;1
"Unit";"Zergling";"Larva";385;1
"Unit";"Zergling";"Larva";386;1
"Unit";"Zergling";"Larva";387;1
"Unit";"Zergling";"Larva";388;1
"Unit";"Zergling";"Larva";389;1
"Unit";"Zergling";"Larva";390;1
"Unit";"Zergling";"Larva";391;1
"Unit";"Zergling";"Larva";392;1
"Building";"CreepTumor";NA;393;0
"Building";"CreepTumor";NA;393;0
"Unit";"Hydralisk";"Larva";393;2
"Building";"CreepTumor";NA;395;0
"Building";"CreepTumorQueen";NA;397;0
"Unit";"Hydralisk";"Larva";397;2
"Unit";"Hydralisk";"Larva";399;2
"Unit";"Hydralisk";"Larva";401;2
"Unit";"Zergling";"Larva";403;1
"Unit";"Zergling";"Larva";404;1
"Unit";"Zergling";"Larva";405;1
"Unit";"Zergling";"Larva";406;1
"Unit";"Zergling";"Larva";407;1
"Unit";"Zergling";"Larva";408;1
"Unit";"Zergling";"Larva";409;1
"Unit";"Zergling";"Larva";410;1
"Building";"CreepTumor";NA;411;0
"Building";"CreepTumor";NA;411;0
"Building";"CreepTumor";NA;411;0
"Unit";"Hydralisk";"Larva";416;2
"Unit";"Hydralisk";"Larva";418;2
"Unit";"Zergling";"Larva";420;1
"Unit";"Zergling";"Larva";421;1
"Unit";"Zergling";"Larva";422;1
"Unit";"Zergling";"Larva";423;1
"Unit";"Zergling";"Larva";424;1
"Unit";"Zergling";"Larva";425;1
"Unit";"Zergling";"Larva";426;1
"Unit";"Zergling";"Larva";427;1
"Unit";"Zergling";"Larva";428;1
"Unit";"Zergling";"Larva";429;1
"Unit";"Zergling";"Larva";430;1
"Unit";"Zergling";"Larva";431;1
"Unit";"Zergling";"Larva";432;1
"Unit";"Zergling";"Larva";433;1
"Unit";"Zergling";"Larva";434;1
"Unit";"Zergling";"Larva";435;1
"Unit";"Zergling";"Larva";436;1
"Unit";"Zergling";"Larva";437;1
"Unit";"Zergling";"Larva";438;1
"Unit";"Zergling";"Larva";439;1
"Unit";"Zergling";"Larva";440;1
"Unit";"Zergling";"Larva";441;1
"Unit";"Baneling";"Zergling";442;0
"Unit";"Baneling";"Zergling";442;0
"Unit";"Baneling";"Zergling";442;0
"Unit";"Baneling";"Zergling";442;0
"Unit";"Baneling";"Zergling";442;0
"Building";"CreepTumorQueen";NA;442;0
"Building";"CreepTumorQueen";NA;442;0
"Unit";"Zergling";"Larva";442;1
"Unit";"Zergling";"Larva";443;1
"Unit";"Zergling";"Larva";444;1
"Unit";"Zergling";"Larva";445;1
"Unit";"Zergling";"Larva";446;1
"Unit";"Zergling";"Larva";447;1
"Unit";"Zergling";"Larva";448;1
"Unit";"Zergling";"Larva";449;1
"Unit";"Zergling";"Larva";450;1
"Unit";"Zergling";"Larva";451;1
"Unit";"Zergling";"Larva";452;1
"Unit";"Zergling";"Larva";453;1
"Unit";"Zergling";"Larva";454;1
"Unit";"Zergling";"Larva";455;1
"Unit";"Zergling";"Larva";456;1
"Unit";"Zergling";"Larva";457;1
"Unit";"Zergling";"Larva";458;1
"Unit";"Zergling";"Larva";459;1
"Unit";"Zergling";"Larva";460;1
"Unit";"Zergling";"Larva";461;1
"Unit";"Zergling";"Larva";462;1
"Unit";"Zergling";"Larva";463;1
"Unit";"Zergling";"Larva";464;1
"Unit";"Zergling";"Larva";465;1
"Unit";"Zergling";"Larva";466;1
"Unit";"Zergling";"Larva";467;1
"Unit";"Zergling";"Larva";468;1
"Unit";"Zergling";"Larva";469;1
"Building";"Extractor";NA;472;0
"Building";"Extractor";NA;474;0
"Building";"Extractor";NA;476;0
"Building";"Extractor";NA;479;0
"Building";"CreepTumor";NA;479;0
"Building";"CreepTumor";NA;479;0
"Building";"CreepTumor";NA;479;0
"Building";"CreepTumor";NA;479;0
"Building";"CreepTumorQueen";NA;479;0
"Building";"CreepTumor";NA;482;0
"Building";"CreepTumor";NA;482;0
"Building";"CreepTumor";NA;482;0
"Building";"CreepTumor";NA;482;0
"Building";"CreepTumor";NA;482;0
"Unit";"Baneling";"Zergling";482;0
"Unit";"Baneling";"Zergling";482;0
"Unit";"Baneling";"Zergling";482;0
"Unit";"Baneling";"Zergling";482;0
"Unit";"Baneling";"Zergling";482;0
"Unit";"Baneling";"Zergling";482;0
"Unit";"Baneling";"Zergling";482;0
"Unit";"Baneling";"Zergling";482;0
"Unit";"Baneling";"Zergling";482;0
"Unit";"Zergling";"Larva";482;1
"Unit";"Zergling";"Larva";483;1
"Unit";"Zergling";"Larva";484;1
"Unit";"Zergling";"Larva";485;1
"Unit";"Zergling";"Larva";486;1
"Unit";"Zergling";"Larva";487;1
"Unit";"Zergling";"Larva";488;1
"Unit";"Zergling";"Larva";489;1
"Unit";"Zergling";"Larva";490;1
"Unit";"Zergling";"Larva";491;1
"Unit";"Zergling";"Larva";492;1
"Unit";"Zergling";"Larva";493;1
"Unit";"Zergling";"Larva";494;1
"Unit";"Zergling";"Larva";495;1
"Unit";"Zergling";"Larva";496;1
"Unit";"Zergling";"Larva";497;1
"Unit";"Zergling";"Larva";498;1
"Unit";"Zergling";"Larva";499;1
"Unit";"Zergling";"Larva";500;1
"Unit";"Zergling";"Larva";501;1
"Unit";"Zergling";"Larva";502;1
"Unit";"Zergling";"Larva";503;1
"Unit";"Zergling";"Larva";504;1
"Unit";"Zergling";"Larva";505;1
"Unit";"Zergling";"Larva";506;1
"Unit";"Zergling";"Larva";507;1
"Unit";"Zergling";"Larva";508;1
"Unit";"Zergling";"Larva";509;1
"Unit";"Zergling";"Larva";510;1
"Unit";"Zergling";"Larva";511;1
"Building";"CreepTumor";NA;512;0
"Building";"CreepTumor";NA;512;0
"Building";"CreepTumor";NA;512;0
"Building";"CreepTumor";NA;512;0
"Building";"CreepTumor";NA;512;0
"Building";"CreepTumorQueen";NA;512;0
"Unit";"Viper";"Larva";512;3
"Unit";"Viper";"Larva";515;3
"Building";"CreepTumorQueen";NA;518;0
"Building";"CreepTumorQueen";NA;518;0
"Unit";"Queen";"Hatchery";518;2
"Unit";"Queen";"Hatchery";525;2
"Unit";"Viper";"Larva";532;3
"Building";"UltraliskCavern";NA;535;0
"Unit";"Viper";"Larva";535;3
"Unit";"Viper";"Larva";538;3
"Unit";"Baneling";"Zergling";541;0
"Unit";"Baneling";"Zergling";541;0
"Unit";"Baneling";"Zergling";541;0
"Unit";"Baneling";"Zergling";541;0
"Unit";"Baneling";"Zergling";541;0
"Unit";"Baneling";"Zergling";541;0
"Unit";"Baneling";"Zergling";541;0
"Unit";"Zergling";"Larva";541;1
"Unit";"Zergling";"Larva";542;1
"Unit";"Zergling";"Larva";543;1
"Unit";"Zergling";"Larva";544;1
"Unit";"Zergling";"Larva";545;1
"Unit";"Zergling";"Larva";546;1
"Unit";"Zergling";"Larva";547;1
"Unit";"Zergling";"Larva";548;1
"Unit";"Zergling";"Larva";549;1
"Unit";"Zergling";"Larva";550;1
"Unit";"Zergling";"Larva";551;1
"Unit";"Zergling";"Larva";552;1
"Unit";"Zergling";"Larva";553;1
"Unit";"Zergling";"Larva";554;1
"Unit";"Zergling";"Larva";555;1
"Unit";"Zergling";"Larva";556;1
"Unit";"Zergling";"Larva";557;1
"Unit";"Zergling";"Larva";558;1
"Unit";"Zergling";"Larva";559;1
"Unit";"Zergling";"Larva";560;1
"Unit";"Zergling";"Larva";561;1
"Unit";"Zergling";"Larva";562;1
"Unit";"Zergling";"Larva";563;1
"Unit";"Zergling";"Larva";564;1
"Unit";"Zergling";"Larva";565;1
"Unit";"Zergling";"Larva";566;1
"Unit";"Zergling";"Larva";567;1
"Unit";"Zergling";"Larva";568;1
"Unit";"Zergling";"Larva";569;1
"Unit";"Zergling";"Larva";570;1
"Building";"CreepTumor";NA;571;0
"Building";"CreepTumor";NA;571;0
"Building";"CreepTumor";NA;571;0
"Building";"CreepTumor";NA;571;0
"Unit";"Viper";"Larva";571;3
"Building";"CreepTumorQueen";NA;574;0
"Building";"CreepTumorQueen";NA;574;0
"Building";"CreepTumorQueen";NA;574;0
"Building";"CreepTumorQueen";NA;574;0
"Building";"SporeCrawler";NA;574;0
"Building";"CreepTumor";NA;574;0
"Building";"CreepTumor";NA;574;0
"Building";"CreepTumor";NA;574;0
"Building";"CreepTumor";NA;574;0
"Building";"CreepTumor";NA;574;0
"Building";"CreepTumor";NA;574;0
"Building";"EvolutionChamber";NA;574;0
"Building";"EvolutionChamber";NA;574;0
"Building";"EvolutionChamber";NA;574;0
"Building";"EvolutionChamber";NA;574;0
"Building";"EvolutionChamber";NA;574;0
"Building";"EvolutionChamber";NA;574;0
"Unit";"Hydralisk";"Larva";574;2
"Unit";"Zergling";"Larva";576;1
"Unit";"Zergling";"Larva";577;1
"Unit";"Zergling";"Larva";578;1
"Unit";"Zergling";"Larva";579;1
"Unit";"Zergling";"Larva";580;1
"Unit";"Zergling";"Larva";581;1
"Unit";"Zergling";"Larva";582;1
"Unit";"Zergling";"Larva";583;1
"Unit";"Baneling";"Zergling";584;0
"Unit";"Baneling";"Zergling";584;0
"Unit";"Baneling";"Zergling";584;0
"Unit";"Baneling";"Zergling";584;0
"Unit";"Baneling";"Zergling";584;0
"Unit";"Baneling";"Zergling";584;0
"Building";"CreepTumor";NA;584;0
"Building";"CreepTumor";NA;584;0
"Building";"CreepTumor";NA;584;0
"Building";"CreepTumor";NA;584;0
"Building";"CreepTumor";NA;584;0
"Building";"Hatchery";NA;584;0
"Upgrade";"ChitinousPlating";"UltraliskCavern";584;0
"Unit";"Hydralisk";"Larva";584;2
"Unit";"Hydralisk";"Larva";586;2
"Unit";"Hydralisk";"Larva";588;2
"Unit";"Hydralisk";"Larva";590;2
"Unit";"Hydralisk";"Larva";592;2
"Unit";"Hydralisk";"Larva";594;2
"Unit";"Hydralisk";"Larva";596;2
"Unit";"Zergling";"Larva";598;1
"Unit";"Zergling";"Larva";599;1
"Unit";"Zergling";"Larva";600;1
"Unit";"Zergling";"Larva";601;1
"Unit";"Zergling";"Larva";602;1
"Unit";"Zergling";"Larva";603;1
"Unit";"Zergling";"Larva";604;1
"Unit";"Zergling";"Larva";605;1
"Unit";"Zergling";"Larva";606;1
"Unit";"Zergling";"Larva";607;1
"Unit";"Zergling";"Larva";608;1
"Unit";"Zergling";"Larva";609;1
"Unit";"Zergling";"Larva";610;1
"Unit";"Zergling";"Larva";611;1
"Unit";"Zergling";"Larva";612;1
"Unit";"Zergling";"Larva";613;1
"Unit";"Zergling";"Larva";614;1
"Unit";"Zergling";"Larva";615;1
"Unit";"Zergling";"Larva";616;1
"Unit";"Zergling";"Larva";617;1
"Unit";"Zergling";"Larva";618;1
"Unit";"Zergling";"Larva";619;1
"Building";"CreepTumor";NA;620;0
"Building";"CreepTumor";NA;620;0
"Building";"CreepTumor";NA;620;0
"Building";"CreepTumor";NA;620;0
"Building";"CreepTumor";NA;620;0
"Building";"CreepTumor";NA;620;0
"Unit";"Baneling";"Zergling";620;0
"Unit";"Baneling";"Zergling";620;0
"Unit";"Baneling";"Zergling";620;0
"Unit";"Baneling";"Zergling";620;0
"Unit";"Baneling";"Zergling";620;0
"Unit";"Baneling";"Zergling";620;0
"Unit";"Baneling";"Zergling";620;0
"Unit";"Baneling";"Zergling";620;0
"Unit";"Baneling";"Zergling";620;0
"Unit";"Baneling";"Zergling";620;0
"Unit";"Baneling";"Zergling";620;0
"Unit";"Baneling";"Zergling";620;0
"Unit";"Baneling";"Zergling";620;0
"Unit";"Baneling";"Zergling";620;0
"Unit";"Baneling";"Zergling";620;0
"Unit";"Baneling";"Zergling";620;0
"Unit";"Baneling";"Zergling";620;0
"Unit";"Baneling";"Zergling";620;0
"Unit";"Baneling";"Zergling";620;0
"Unit";"Baneling";"Zergling";620;0
"Unit";"Hydralisk";"Larva";620;2
"Unit";"Hydralisk";"Larva";622;2
"Unit";"Hydralisk";"Larva";624;2
"Unit";"Zergling";"Larva";626;1
"Unit";"Zergling";"Larva";627;1
"Unit";"Zergling";"Larva";628;1
"Unit";"Zergling";"Larva";629;1
"Unit";"Zergling";"Larva";630;1
"Unit";"Zergling";"Larva";631;1
"Unit";"Zergling";"Larva";632;1
"Unit";"Zergling";"Larva";633;1
"Unit";"Zergling";"Larva";634;1
"Unit";"Zergling";"Larva";635;1
"Unit";"Zergling";"Larva";636;1
"Unit";"Zergling";"Larva";637;1
"Unit";"Zergling";"Larva";638;1
"Unit";"Zergling";"Larva";639;1
"Unit";"Zergling";"Larva";640;1
"Unit";"Zergling";"Larva";641;1
"Unit";"Zergling";"Larva";642;1
"Unit";"Zergling";"Larva";643;1
"Unit";"Zergling";"Larva";644;1
"Unit";"Zergling";"Larva";645;1
"Unit";"Zergling";"Larva";646;1
"Unit";"Zergling";"Larva";647;1
"Unit";"Zergling";"Larva";648;1
"Unit";"Zergling";"Larva";649;1
"Unit";"Zergling";"Larva";650;1
"Unit";"Zergling";"Larva";651;1
"Unit";"Zergling";"Larva";652;1
"Unit";"Zergling";"Larva";653;1
"Unit";"Zergling";"Larva";654;1
"Unit";"Zergling";"Larva";655;1
"Unit";"Zergling";"Larva";656;1
"Unit";"Zergling";"Larva";657;1
"Unit";"Zergling";"Larva";658;1
"Unit";"Zergling";"Larva";659;1
"Unit";"Zergling";"Larva";660;1
"Unit";"Zergling";"Larva";661;1
"Building";"CreepTumorQueen";NA;662;0
"Building";"CreepTumorQueen";NA;662;0
"Building";"Spire";NA;662;0
"Building";"CreepTumorQueen";NA;662;0
"Building";"Spire";NA;663;0
"Unit";"Baneling";"Zergling";664;0
"Unit";"Baneling";"Zergling";664;0
"Unit";"Baneling";"Zergling";664;0
"Unit";"Baneling";"Zergling";664;0
"Unit";"Baneling";"Zergling";664;0
"Unit";"Baneling";"Zergling";664;0
"Unit";"Baneling";"Zergling";664;0
"Unit";"Baneling";"Zergling";664;0
"Unit";"Baneling";"Zergling";664;0
"Unit";"Baneling";"Zergling";664;0
"Unit";"Hydralisk";"Larva";664;2
"Unit";"Hydralisk";"Larva";666;2
"Unit";"Zergling";"Larva";668;1
"Unit";"Zergling";"Larva";669;1
"Unit";"Zergling";"Larva";670;1
"Unit";"Zergling";"Larva";671;1
"Unit";"Zergling";"Larva";672;1
"Unit";"Zergling";"Larva";673;1
"Unit";"Zergling";"Larva";674;1
"Unit";"Zergling";"Larva";675;1
"Unit";"Zergling";"Larva";676;1
"Unit";"Zergling";"Larva";677;1
"Unit";"Zergling";"Larva";678;1
"Unit";"Zergling";"Larva";679;1
"Unit";"Hydralisk";"Larva";680;2
"Unit";"Hydralisk";"Larva";682;2
"Unit";"Hydralisk";"Larva";684;2
"Unit";"Hydralisk";"Larva";686;2
"Unit";"Zergling";"Larva";688;1
"Unit";"Zergling";"Larva";689;1
"Unit";"Zergling";"Larva";690;1
"Unit";"Zergling";"Larva";691;1
"Unit";"Zergling";"Larva";692;1
"Unit";"Zergling";"Larva";693;1
"Unit";"Zergling";"Larva";694;1
"Unit";"Zergling";"Larva";695;1
"Unit";"Zergling";"Larva";696;1
"Unit";"Zergling";"Larva";697;1
"Unit";"Zergling";"Larva";698;1
"Unit";"Zergling";"Larva";699;1
"Unit";"Zergling";"Larva";700;1
"Unit";"Zergling";"Larva";701;1
"Unit";"Zergling";"Larva";702;1
"Unit";"Zergling";"Larva";703;1
"Unit";"Zergling";"Larva";704;1
"Unit";"Zergling";"Larva";705;1
"Unit";"Zergling";"Larva";706;1
"Unit";"Zergling";"Larva";707;1
"Unit";"Zergling";"Larva";708;1
"Unit";"Zergling";"Larva";709;1
"Unit";"Zergling";"Larva";710;1
"Unit";"Zergling";"Larva";711;1
"Unit";"Zergling";"Larva";712;1
"Unit";"Zergling";"Larva";713;1
"Unit";"Zergling";"Larva";714;1
"Unit";"Zergling";"Larva";715;1
"Building";"CreepTumor";NA;716;0
"Building";"CreepTumor";NA;716;0
"Building";"CreepTumorQueen";NA;716;0
"Building";"CreepTumorQueen";NA;716;0
"Building";"CreepTumorQueen";NA;716;0
"Building";"CreepTumorQueen";NA;716;0
"Unit";"Zergling";"Larva";716;1
"Unit";"Zergling";"Larva";717;1
"Unit";"Zergling";"Larva";718;1
"Unit";"Zergling";"Larva";719;1
"Unit";"Zergling";"Larva";720;1
"Unit";"Zergling";"Larva";721;1
"Unit";"Zergling";"Larva";722;1
"Unit";"Zergling";"Larva";723;1
"Unit";"Zergling";"Larva";724;1
"Unit";"Zergling";"Larva";725;1
"Unit";"Zergling";"Larva";726;1
"Unit";"Zergling";"Larva";727;1
"Unit";"Zergling";"Larva";728;1
"Unit";"Zergling";"Larva";729;1
"Unit";"Zergling";"Larva";730;1
"Unit";"Zergling";"Larva";731;1
"Unit";"Zergling";"Larva";732;1
"Unit";"Zergling";"Larva";733;1
"Unit";"Zergling";"Larva";734;1
"Unit";"Zergling";"Larva";735;1
"Unit";"Zergling";"Larva";736;1
"Unit";"Zergling";"Larva";737;1
"Building";"CreepTumor";NA;738;0
"Building";"CreepTumor";NA;738;0
"Unit";"Baneling";"Zergling";738;0
"Unit";"Baneling";"Zergling";738;0
"Unit";"Baneling";"Zergling";738;0
"Unit";"Baneling";"Zergling";738;0
"Unit";"Baneling";"Zergling";738;0
"Unit";"Baneling";"Zergling";738;0
"Unit";"Baneling";"Zergling";738;0
"Unit";"Baneling";"Zergling";738;0
"Unit";"Baneling";"Zergling";738;0
"Unit";"Baneling";"Zergling";738;0
"Unit";"Baneling";"Zergling";738;0
"Unit";"Baneling";"Zergling";738;0
"Unit";"Baneling";"Zergling";738;0
"Unit";"Baneling";"Zergling";738;0
"Unit";"Baneling";"Zergling";738;0
"Unit";"Baneling";"Zergling";738;0
"Unit";"Baneling";"Zergling";738;0
"Unit";"Baneling";"Zergling";738;0
"Unit";"Baneling";"Zergling";738;0
"Unit";"Baneling";"Zergling";738;0
"Unit";"Baneling";"Zergling";738;0
"Unit";"Baneling";"Zergling";738;0
"Building";"CreepTumor";NA;738;0
"Building";"CreepTumor";NA;738;0
"Building";"CreepTumor";NA;738;0
"Building";"CreepTumor";NA;738;0
"Building";"CreepTumor";NA;738;0
"Building";"CreepTumor";NA;738;0
"Building";"CreepTumor";NA;738;0
"Building";"CreepTumor";NA;738;0
"Building";"CreepTumor";NA;738;0
"Unit";"Hydralisk";"Larva";738;2
"Unit";"Zergling";"Larva";740;1
"Unit";"Zergling";"Larva";741;1
"Unit";"Zergling";"Larva";742;1
"Unit";"Zergling";"Larva";743;1
"Unit";"Zergling";"Larva";744;1
"Unit";"Zergling";"Larva";745;1
"Unit";"Zergling";"Larva";746;1
"Unit";"Zergling";"Larva";747;1
"Unit";"Zergling";"Larva";748;1
"Unit";"Zergling";"Larva";749;1
"Unit";"Zergling";"Larva";750;1
"Unit";"Zergling";"Larva";751;1
"Unit";"Zergling";"Larva";752;1
"Unit";"Zergling";"Larva";753;1
"Unit";"Zergling";"Larva";754;1
"Unit";"Zergling";"Larva";755;1
"Unit";"Zergling";"Larva";756;1
"Unit";"Zergling";"Larva";757;1
"Unit";"Zergling";"Larva";758;1
"Unit";"Zergling";"Larva";759;1
"Unit";"Hydralisk";"Larva";760;2
"Unit";"Zergling";"Larva";762;1
"Unit";"Zergling";"Larva";763;1
"Unit";"Zergling";"Larva";764;1
"Unit";"Zergling";"Larva";765;1
"Unit";"Zergling";"Larva";766;1
"Unit";"Zergling";"Larva";767;1
"Unit";"Zergling";"Larva";768;1
"Unit";"Zergling";"Larva";769;1
"Unit";"Zergling";"Larva";770;1
"Unit";"Zergling";"Larva";771;1
"Unit";"Zergling";"Larva";772;1
"Unit";"Zergling";"Larva";773;1
"Unit";"Zergling";"Larva";774;1
"Unit";"Zergling";"Larva";775;1
"Unit";"Zergling";"Larva";776;1
"Unit";"Zergling";"Larva";777;1
"Unit";"Zergling";"Larva";778;1
"Unit";"Zergling";"Larva";779;1
"Unit";"Zergling";"Larva";780;1
"Unit";"Zergling";"Larva";781;1
"Unit";"Zergling";"Larva";782;1
"Unit";"Zergling";"Larva";783;1
"Unit";"Zergling";"Larva";784;1
"Unit";"Zergling";"Larva";785;1
"Unit";"Zergling";"Larva";786;1
"Unit";"Zergling";"Larva";787;1
"Unit";"Zergling";"Larva";788;1
"Unit";"Zergling";"Larva";789;1
"Unit";"Zergling";"Larva";790;1
"Unit";"Zergling";"Larva";791;1
"Unit";"Zergling";"Larva";792;1
"Unit";"Zergling";"Larva";793;1
"Unit";"Zergling";"Larva";794;1
"Unit";"Zergling";"Larva";795;1
"Unit";"Zergling";"Larva";796;1
"Unit";"Zergling";"Larva";797;1
"Unit";"Zergling";"Larva";798;1
"Unit";"Zergling";"Larva";799;1
"Unit";"Overlord";"Larva";800;0
"Unit";"Overlord";"Larva";800;0
"Unit";"Overlord";"Larva";800;0
"Unit";"Overlord";"Larva";800;0
"Unit";"Overlord";"Larva";800;0
"Unit";"Overlord";"Larva";800;0
"Unit";"Overlord";"Larva";800;0
"Unit";"Overlord";"Larva";800;0
"Building";"CreepTumor";NA;807;0
"Building";"CreepTumor";NA;807;0
"Building";"CreepTumor";NA;807;0
"Building";"CreepTumor";NA;807;0
"Building";"CreepTumor";NA;807;0
"Building";"CreepTumor";NA;807;0
"Building";"CreepTumor";NA;807;0
"Building";"CreepTumor";NA;807;0
"Building";"CreepTumor";NA;807;0
"Building";"CreepTumor";NA;807;0
"Building";"CreepTumor";NA;807;0
"Unit";"Baneling";"Zergling";807;0
"Unit";"Baneling";"Zergling";807;0
"Unit";"Baneling";"Zergling";807;0
"Unit";"Baneling";"Zergling";807;0
"Unit";"Baneling";"Zergling";807;0
"Unit";"Baneling";"Zergling";807;0
"Unit";"Baneling";"Zergling";807;0
"Unit";"Baneling";"Zergling";807;0
"Unit";"Baneling";"Zergling";807;0
"Unit";"Baneling";"Zergling";807;0
"Unit";"Baneling";"Zergling";807;0
"Unit";"Baneling";"Zergling";807;0
"Unit";"Baneling";"Zergling";807;0
"Unit";"Baneling";"Zergling";807;0
"Unit";"Baneling";"Zergling";807;0
"Unit";"Baneling";"Zergling";807;0
"Unit";"Baneling";"Zergling";807;0
"Unit";"Baneling";"Zergling";807;0
"Unit";"Baneling";"Zergling";807;0
"Unit";"Baneling";"Zergling";807;0
"Unit";"Baneling";"Zergling";807;0
"Unit";"Baneling";"Zergling";807;0
"Unit";"Baneling";"Zergling";807;0
"Unit";"Baneling";"Zergling";807;0
"Unit";"Baneling";"Zergling";807;0
"Unit";"Baneling";"Zergling";807;0
"Unit";"Baneling";"Zergling";807;0
"Unit";"Baneling";"Zergling";807;0
"Unit";"Baneling";"Zergling";807;0
"Unit";"Baneling";"Zergling";807;0
"Unit";"Baneling";"Zergling";807;0
"Unit";"Baneling";"Zergling";807;0
"Building";"Hatchery";NA;807;0
"Unit";"Baneling";"Zergling";807;0
"Unit";"Baneling";"Zergling";807;0
"Unit";"Baneling";"Zergling";807;0
"Unit";"Baneling";"Zergling";807;0
"Unit";"Baneling";"Zergling";807;0
"Unit";"Baneling";"Zergling";807;0
"Unit";"Baneling";"Zergling";807;0
"Unit";"Baneling";"Zergling";807;0
"Unit";"Baneling";"Zergling";807;0
"Unit";"Ultralisk";"Larva";807;6
"Unit";"Ultralisk";"Larva";813;6
"Unit";"Ultralisk";"Larva";819;6
"Building";"CreepTumorQueen";NA;825;0
"Building";"Hatchery";NA;825;0
"Upgrade";"Burrow";"Hatchery";825;0
"Building";"CreepTumor";NA;825;0
"Building";"CreepTumor";NA;825;0
"Building";"CreepTumorQueen";NA;825;0
"Building";"CreepTumorQueen";NA;825;0
"Building";"Extractor";NA;825;0
"Building";"CreepTumorQueen";NA;825;0
"Building";"CreepTumorQueen";NA;825;0
"Building";"CreepTumorQueen";NA;825;0
"Building";"CreepTumorQueen";NA;825;0
"Building";"CreepTumor";NA;825;0
"Building";"CreepTumor";NA;825;0
"Unit";"Ultralisk";"Larva";825;6
"Unit";"Ultralisk";"Larva";831;6
"Unit";"Ultralisk";"Larva";837;6
"Unit";"Ultralisk";"Larva";843;6
"Unit";"Infestor";"Larva";849;2
"Unit";"Infestor";"Larva";851;2
"Unit";"Infestor";"Larva";853;2
"Unit";"Infestor";"Larva";855;2
"Unit";"Infestor";"Larva";857;2
"Building";"CreepTumor";NA;859;0
"Building";"CreepTumor";NA;859;0
"Building";"CreepTumor";NA;859;0
"Building";"CreepTumor";NA;859;0
"Building";"CreepTumor";NA;859;0
"Building";"CreepTumor";NA;859;0
"Building";"CreepTumorQueen";NA;859;0
"Building";"CreepTumor";NA;859;0
"Building";"CreepTumorQueen";NA;859;0
"Building";"CreepTumorQueen";NA;859;0
"Building";"CreepTumorQueen";NA;859;0
"Unit";"Zergling";"Larva";859;1
"Unit";"Zergling";"Larva";860;1
"Building";"CreepTumor";NA;861;0
"Building";"CreepTumor";NA;861;0
"Upgrade";"SprayZerg";NA;861;0
"Upgrade";"SprayZerg";NA;861;0
"Upgrade";"zerglingmovementspeed";NA;861;0
"Upgrade";"ZergGroundArmorsLevel1";NA;861;0
"Upgrade";"SprayZerg";NA;861;0
"Upgrade";"SprayZerg";NA;861;0
"Upgrade";"ZergMeleeWeaponsLevel1";NA;861;0
"Upgrade";"SprayZerg";NA;861;0
"Upgrade";"SprayZerg";NA;861;0
"Upgrade";"ZergGroundArmorsLevel2";NA;861;0
"Upgrade";"SprayZerg";NA;861;0
"Upgrade";"ZergMissileWeaponsLevel1";NA;861;0
"Upgrade";"EvolveMuscularAugments";NA;861;0
"Upgrade";"CentrificalHooks";NA;861;0
"Upgrade";"SprayZerg";NA;861;0
"Upgrade";"SprayZerg";NA;861;0
"Upgrade";"SprayZerg";NA;861;0
"Upgrade";"SprayZerg";NA;861;0
"Upgrade";"overlordspeed";NA;861;0
"Upgrade";"ZergMeleeWeaponsLevel2";NA;861;0
"Upgrade";"ZergMissileWeaponsLevel2";NA;861;0
"Upgrade";"SprayZerg";NA;861;0
"Upgrade";"SprayZerg";NA;861;0
"Upgrade";"zerglingattackspeed";NA;861;0
"Upgrade";"ZergMeleeWeaponsLevel3";NA;861;0
"Upgrade";"SprayZerg";NA;861;0
"Upgrade";"ZergGroundArmorsLevel3";NA;861;0
"Upgrade";"SprayZerg";NA;861;0
"Upgrade";"ZergMissileWeaponsLevel3";NA;861;0
"Upgrade";"ZergFlyerArmorsLevel1";NA;861;0
"Upgrade";"SprayZerg";NA;861;0
"Upgrade";"SprayZerg";NA;861;0
"Upgrade";"InfestorEnergyUpgrade";NA;861;0
"Upgrade";"SprayZerg";NA;861;0
"Upgrade";"ZergFlyerWeaponsLevel1";NA;861;0
"Upgrade";"SprayZerg";NA;861;0
