"type";"unit_name";"on_building";"total_supply_lag";"supply"
"Unit";"Overlord";"Larva";13;0
"Building";"Hatchery";NA;17;0
"Building";"Extractor";NA;19;0
"Building";"SpawningPool";NA;19;0
"Unit";"Overlord";"Larva";21;0
"Unit";"Zergling";"Larva";22;1
"Unit";"Zergling";"Larva";23;1
"Unit";"Queen";"Hatchery";24;2
"Unit";"Queen";"Hatchery";26;2
"Building";"Hatchery";NA;35;0
"Unit";"Overlord";"Larva";36;0
"Unit";"Queen";"Hatchery";36;2
"Building";"EvolutionChamber";NA;44;0
"Unit";"Overlord";"Larva";44;0
"Unit";"Overlord";"Larva";44;0
"Building";"SporeCrawler";NA;44;0
"Building";"SporeCrawler";NA;44;0
"Unit";"Overlord";"Larva";44;0
"Building";"CreepTumorQueen";NA;44;0
"Building";"SporeCrawler";NA;50;0
"Building";"BanelingNest";NA;61;0
"Building";"Extractor";NA;67;0
"Building";"Extractor";NA;67;0
"Building";"Extractor";NA;68;0
"Building";"CreepTumor";NA;69;0
"Unit";"Overlord";"Larva";81;0
"Unit";"Overlord";"Larva";81;0
"Unit";"Zergling";"Larva";81;1
"Unit";"Zergling";"Larva";82;1
"Unit";"Zergling";"Larva";83;1
"Unit";"Zergling";"Larva";84;1
"Unit";"Zergling";"Larva";85;1
"Unit";"Zergling";"Larva";86;1
"Unit";"Zergling";"Larva";87;1
"Unit";"Zergling";"Larva";88;1
"Unit";"Zergling";"Larva";89;1
"Unit";"Zergling";"Larva";90;1
"Unit";"Baneling";"Zergling";91;0
"Unit";"Zergling";"Larva";91;1
"Unit";"Zergling";"Larva";92;1
"Unit";"Zergling";"Larva";93;1
"Unit";"Zergling";"Larva";94;1
"Unit";"Zergling";"Larva";95;1
"Unit";"Zergling";"Larva";96;1
"Unit";"Zergling";"Larva";97;1
"Unit";"Zergling";"Larva";98;1
"Unit";"Zergling";"Larva";99;1
"Unit";"Zergling";"Larva";100;1
"Unit";"Zergling";"Larva";101;1
"Unit";"Zergling";"Larva";102;1
"Building";"CreepTumor";NA;103;0
"Unit";"Zergling";"Larva";103;1
"Unit";"Zergling";"Larva";104;1
"Unit";"Zergling";"Larva";105;1
"Unit";"Zergling";"Larva";106;1
"Unit";"Zergling";"Larva";107;1
"Unit";"Zergling";"Larva";108;1
"Building";"HydraliskDen";NA;109;0
"Unit";"Baneling";"Zergling";109;0
"Unit";"Baneling";"Zergling";109;0
"Unit";"Baneling";"Zergling";109;0
"Unit";"Zergling";"Larva";109;1
"Unit";"Zergling";"Larva";110;1
"Unit";"Zergling";"Larva";111;1
"Unit";"Zergling";"Larva";112;1
"Unit";"Zergling";"Larva";113;1
"Unit";"Zergling";"Larva";114;1
"Unit";"Zergling";"Larva";115;1
"Unit";"Zergling";"Larva";116;1
"Unit";"Baneling";"Zergling";117;0
"Unit";"Zergling";"Larva";117;1
"Unit";"Zergling";"Larva";118;1
"Unit";"Zergling";"Larva";119;1
"Unit";"Zergling";"Larva";120;1
"Unit";"Zergling";"Larva";121;1
"Unit";"Zergling";"Larva";122;1
"Unit";"Zergling";"Larva";123;1
"Unit";"Zergling";"Larva";124;1
"Unit";"Zergling";"Larva";125;1
"Unit";"Zergling";"Larva";126;1
"Unit";"Zergling";"Larva";127;1
"Unit";"Zergling";"Larva";128;1
"Unit";"Zergling";"Larva";129;1
"Unit";"Zergling";"Larva";130;1
"Unit";"Zergling";"Larva";131;1
"Unit";"Zergling";"Larva";132;1
"Unit";"Zergling";"Larva";133;1
"Unit";"Zergling";"Larva";134;1
"Unit";"Zergling";"Larva";135;1
"Unit";"Zergling";"Larva";136;1
"Unit";"Zergling";"Larva";137;1
"Unit";"Zergling";"Larva";138;1
"Unit";"Zergling";"Larva";139;1
"Unit";"Zergling";"Larva";140;1
"Unit";"Zergling";"Larva";141;1
"Unit";"Zergling";"Larva";142;1
"Unit";"Zergling";"Larva";143;1
"Unit";"Zergling";"Larva";144;1
"Unit";"Zergling";"Larva";145;1
"Unit";"Zergling";"Larva";146;1
"Building";"Hatchery";NA;150;0
"Unit";"Baneling";"Zergling";152;0
"Unit";"Baneling";"Zergling";152;0
"Unit";"Baneling";"Zergling";152;0
"Building";"CreepTumor";NA;153;0
"Building";"CreepTumorQueen";NA;157;0
"Building";"Extractor";NA;159;0
"Building";"Extractor";NA;159;0
"Unit";"Hydralisk";"Larva";165;2
"Building";"Hatchery";NA;167;0
"Unit";"Hydralisk";"Larva";167;2
"Unit";"Overlord";"Larva";169;0
"Unit";"Overlord";"Larva";169;0
"Unit";"Overlord";"Larva";169;0
"Building";"CreepTumor";NA;169;0
"Building";"CreepTumor";NA;169;0
"Unit";"Overlord";"Larva";169;0
"Unit";"Overlord";"Larva";169;0
"Unit";"Overlord";"Larva";170;0
"Unit";"Hydralisk";"Larva";170;2
"Unit";"Hydralisk";"Larva";172;2
"Unit";"Hydralisk";"Larva";174;2
"Unit";"Hydralisk";"Larva";176;2
"Unit";"Hydralisk";"Larva";178;2
"Unit";"Hydralisk";"Larva";180;2
"Unit";"Hydralisk";"Larva";182;2
"Unit";"Queen";"Hatchery";192;2
"Unit";"Baneling";"Zergling";200;0
"Unit";"Baneling";"Zergling";200;0
"Building";"SporeCrawler";NA;200;0
"Building";"CreepTumor";NA;200;0
"Unit";"Overlord";"Larva";205;0
"Unit";"Overlord";"Larva";205;0
"Unit";"Hydralisk";"Larva";205;2
"Unit";"Hydralisk";"Larva";207;2
"Building";"Extractor";NA;209;0
"Unit";"Overlord";"Larva";209;0
"Building";"CreepTumor";NA;209;0
"Unit";"Hydralisk";"Larva";209;2
"Unit";"Hydralisk";"Larva";211;2
"Unit";"Hydralisk";"Larva";213;2
"Unit";"Hydralisk";"Larva";215;2
"Unit";"Hydralisk";"Larva";217;2
"Unit";"Zergling";"Larva";219;1
"Unit";"Zergling";"Larva";220;1
"Unit";"Zergling";"Larva";221;1
"Unit";"Zergling";"Larva";222;1
"Unit";"Baneling";"Zergling";223;0
"Unit";"Baneling";"Zergling";223;0
"Unit";"Baneling";"Zergling";223;0
"Unit";"Baneling";"Zergling";223;0
"Unit";"Baneling";"Zergling";223;0
"Unit";"Baneling";"Zergling";223;0
"Unit";"Zergling";"Larva";223;1
"Unit";"Zergling";"Larva";224;1
"Unit";"Zergling";"Larva";225;1
"Unit";"Zergling";"Larva";226;1
"Unit";"Zergling";"Larva";227;1
"Unit";"Zergling";"Larva";228;1
"Unit";"Zergling";"Larva";229;1
"Unit";"Zergling";"Larva";230;1
"Unit";"Overlord";"Larva";231;0
"Unit";"Overlord";"Larva";231;0
"Building";"CreepTumorQueen";NA;231;0
"Unit";"Hydralisk";"Larva";232;2
"Unit";"Hydralisk";"Larva";234;2
"Unit";"Hydralisk";"Larva";236;2
"Unit";"Hydralisk";"Larva";238;2
"Unit";"Hydralisk";"Larva";240;2
"Unit";"Hydralisk";"Larva";242;2
"Unit";"Hydralisk";"Larva";244;2
"Unit";"Hydralisk";"Larva";246;2
"Unit";"Hydralisk";"Larva";248;2
"Unit";"Hydralisk";"Larva";250;2
"Unit";"Hydralisk";"Larva";252;2
"Unit";"Zergling";"Larva";254;1
"Unit";"Zergling";"Larva";255;1
"Unit";"Zergling";"Larva";256;1
"Unit";"Zergling";"Larva";257;1
"Unit";"Zergling";"Larva";258;1
"Unit";"Zergling";"Larva";259;1
"Unit";"Zergling";"Larva";260;1
"Unit";"Zergling";"Larva";261;1
"Unit";"Zergling";"Larva";262;1
"Unit";"Zergling";"Larva";263;1
"Unit";"Zergling";"Larva";264;1
"Unit";"Zergling";"Larva";265;1
"Unit";"Zergling";"Larva";266;1
"Unit";"Zergling";"Larva";267;1
"Unit";"Zergling";"Larva";268;1
"Unit";"Zergling";"Larva";269;1
"Unit";"Zergling";"Larva";270;1
"Unit";"Zergling";"Larva";271;1
"Unit";"Zergling";"Larva";272;1
"Unit";"Zergling";"Larva";273;1
"Unit";"Zergling";"Larva";274;1
"Unit";"Zergling";"Larva";275;1
"Unit";"Zergling";"Larva";276;1
"Unit";"Zergling";"Larva";277;1
"Unit";"Zergling";"Larva";278;1
"Unit";"Zergling";"Larva";279;1
"Building";"CreepTumor";NA;280;0
"Building";"Hatchery";NA;280;0
"Unit";"Overlord";"Larva";280;0
"Unit";"Overlord";"Larva";280;0
"Unit";"Overlord";"Larva";280;0
"Unit";"Baneling";"Zergling";280;0
"Unit";"Baneling";"Zergling";280;0
"Unit";"Baneling";"Zergling";280;0
"Unit";"Baneling";"Zergling";280;0
"Unit";"Baneling";"Zergling";280;0
"Unit";"Baneling";"Zergling";280;0
"Unit";"Zergling";"Larva";280;1
"Unit";"Zergling";"Larva";281;1
"Unit";"Zergling";"Larva";282;1
"Unit";"Zergling";"Larva";283;1
"Unit";"Zergling";"Larva";284;1
"Unit";"Zergling";"Larva";285;1
"Unit";"Zergling";"Larva";286;1
"Unit";"Zergling";"Larva";287;1
"Unit";"Zergling";"Larva";288;1
"Unit";"Zergling";"Larva";289;1
"Unit";"Zergling";"Larva";290;1
"Unit";"Zergling";"Larva";291;1
"Unit";"Zergling";"Larva";292;1
"Unit";"Zergling";"Larva";293;1
"Unit";"Zergling";"Larva";294;1
"Unit";"Zergling";"Larva";295;1
"Unit";"Zergling";"Larva";296;1
"Unit";"Zergling";"Larva";297;1
"Unit";"Zergling";"Larva";298;1
"Unit";"Zergling";"Larva";299;1
"Unit";"Zergling";"Larva";300;1
"Unit";"Zergling";"Larva";301;1
"Unit";"Zergling";"Larva";302;1
"Unit";"Zergling";"Larva";303;1
"Unit";"Baneling";"Zergling";304;0
"Unit";"Baneling";"Zergling";304;0
"Unit";"Baneling";"Zergling";304;0
"Unit";"Baneling";"Zergling";304;0
"Unit";"Baneling";"Zergling";304;0
"Unit";"Baneling";"Zergling";304;0
"Unit";"Baneling";"Zergling";304;0
"Unit";"Baneling";"Zergling";304;0
"Unit";"Baneling";"Zergling";304;0
"Unit";"Baneling";"Zergling";304;0
"Unit";"Baneling";"Zergling";304;0
"Unit";"Baneling";"Zergling";304;0
"Unit";"Baneling";"Zergling";304;0
"Unit";"Baneling";"Zergling";304;0
"Unit";"Baneling";"Zergling";304;0
"Unit";"Baneling";"Zergling";304;0
"Unit";"Zergling";"Larva";304;1
"Unit";"Zergling";"Larva";305;1
"Unit";"Zergling";"Larva";306;1
"Unit";"Zergling";"Larva";307;1
"Unit";"Zergling";"Larva";308;1
"Unit";"Zergling";"Larva";309;1
"Unit";"Zergling";"Larva";310;1
"Unit";"Zergling";"Larva";311;1
"Unit";"Zergling";"Larva";312;1
"Unit";"Zergling";"Larva";313;1
"Unit";"Zergling";"Larva";314;1
"Unit";"Zergling";"Larva";315;1
"Unit";"Zergling";"Larva";316;1
"Unit";"Zergling";"Larva";317;1
"Unit";"Zergling";"Larva";318;1
"Unit";"Zergling";"Larva";319;1
"Unit";"Zergling";"Larva";320;1
"Unit";"Zergling";"Larva";321;1
"Unit";"Zergling";"Larva";322;1
"Unit";"Zergling";"Larva";323;1
"Unit";"Zergling";"Larva";324;1
"Unit";"Zergling";"Larva";325;1
"Unit";"Zergling";"Larva";326;1
"Unit";"Zergling";"Larva";327;1
"Unit";"Zergling";"Larva";328;1
"Unit";"Zergling";"Larva";329;1
"Unit";"Zergling";"Larva";330;1
"Unit";"Zergling";"Larva";331;1
"Unit";"Zergling";"Larva";332;1
"Unit";"Zergling";"Larva";333;1
"Unit";"Zergling";"Larva";334;1
"Unit";"Zergling";"Larva";335;1
"Unit";"Zergling";"Larva";336;1
"Unit";"Zergling";"Larva";337;1
"Unit";"Zergling";"Larva";338;1
"Unit";"Zergling";"Larva";339;1
"Unit";"Zergling";"Larva";340;1
"Unit";"Zergling";"Larva";341;1
"Unit";"Zergling";"Larva";342;1
"Unit";"Zergling";"Larva";343;1
"Unit";"Zergling";"Larva";344;1
"Unit";"Zergling";"Larva";345;1
"Unit";"Zergling";"Larva";346;1
"Unit";"Zergling";"Larva";347;1
"Unit";"Zergling";"Larva";348;1
"Unit";"Zergling";"Larva";349;1
"Unit";"Zergling";"Larva";350;1
"Unit";"Zergling";"Larva";351;1
"Unit";"Zergling";"Larva";352;1
"Unit";"Zergling";"Larva";353;1
"Unit";"Zergling";"Larva";354;1
"Unit";"Zergling";"Larva";355;1
"Unit";"Zergling";"Larva";356;1
"Unit";"Zergling";"Larva";357;1
"Unit";"Zergling";"Larva";358;1
"Unit";"Zergling";"Larva";359;1
"Unit";"Queen";"Hatchery";360;2
"Unit";"Zergling";"Larva";362;1
"Unit";"Zergling";"Larva";363;1
"Unit";"Zergling";"Larva";364;1
"Unit";"Zergling";"Larva";365;1
"Unit";"Zergling";"Larva";366;1
"Unit";"Zergling";"Larva";367;1
"Unit";"Zergling";"Larva";368;1
"Unit";"Zergling";"Larva";369;1
"Unit";"Zergling";"Larva";370;1
"Unit";"Zergling";"Larva";371;1
"Unit";"Zergling";"Larva";372;1
"Unit";"Zergling";"Larva";373;1
"Unit";"Zergling";"Larva";374;1
"Unit";"Zergling";"Larva";375;1
"Unit";"Zergling";"Larva";376;1
"Unit";"Zergling";"Larva";377;1
"Building";"Spire";NA;378;0
"Building";"InfestationPit";NA;378;0
"Unit";"Zergling";"Larva";378;1
"Unit";"Zergling";"Larva";379;1
"Unit";"Zergling";"Larva";380;1
"Unit";"Zergling";"Larva";381;1
"Unit";"Zergling";"Larva";382;1
"Unit";"Zergling";"Larva";383;1
"Unit";"Zergling";"Larva";384;1
"Unit";"Zergling";"Larva";385;1
"Unit";"Zergling";"Larva";386;1
"Unit";"Zergling";"Larva";387;1
"Unit";"Zergling";"Larva";388;1
"Unit";"Zergling";"Larva";389;1
"Unit";"Baneling";"Zergling";390;0
"Unit";"Baneling";"Zergling";390;0
"Unit";"Baneling";"Zergling";390;0
"Unit";"Baneling";"Zergling";390;0
"Unit";"Baneling";"Zergling";390;0
"Unit";"Baneling";"Zergling";390;0
"Unit";"Baneling";"Zergling";390;0
"Unit";"Baneling";"Zergling";390;0
"Unit";"Baneling";"Zergling";390;0
"Unit";"Baneling";"Zergling";390;0
"Unit";"Baneling";"Zergling";390;0
"Unit";"Baneling";"Zergling";390;0
"Unit";"Baneling";"Zergling";390;0
"Unit";"Baneling";"Zergling";390;0
"Unit";"Baneling";"Zergling";390;0
"Unit";"Baneling";"Zergling";390;0
"Unit";"Baneling";"Zergling";390;0
"Unit";"Baneling";"Zergling";390;0
"Unit";"Baneling";"Zergling";390;0
"Unit";"Baneling";"Zergling";390;0
"Unit";"Baneling";"Zergling";390;0
"Unit";"Baneling";"Zergling";390;0
"Unit";"Baneling";"Zergling";390;0
"Unit";"Zergling";"Larva";390;1
"Unit";"Zergling";"Larva";391;1
"Unit";"Zergling";"Larva";392;1
"Unit";"Zergling";"Larva";393;1
"Unit";"Zergling";"Larva";394;1
"Unit";"Zergling";"Larva";395;1
"Unit";"Zergling";"Larva";396;1
"Unit";"Zergling";"Larva";397;1
"Unit";"Zergling";"Larva";398;1
"Unit";"Zergling";"Larva";399;1
"Unit";"Zergling";"Larva";400;1
"Unit";"Zergling";"Larva";401;1
"Unit";"Zergling";"Larva";402;1
"Unit";"Zergling";"Larva";403;1
"Unit";"Zergling";"Larva";404;1
"Unit";"Zergling";"Larva";405;1
"Unit";"Zergling";"Larva";406;1
"Unit";"Zergling";"Larva";407;1
"Unit";"Zergling";"Larva";408;1
"Unit";"Zergling";"Larva";409;1
"Unit";"Zergling";"Larva";410;1
"Unit";"Zergling";"Larva";411;1
"Unit";"Zergling";"Larva";412;1
"Unit";"Zergling";"Larva";413;1
"Unit";"Zergling";"Larva";414;1
"Unit";"Zergling";"Larva";415;1
"Unit";"Zergling";"Larva";416;1
"Unit";"Zergling";"Larva";417;1
"Unit";"Baneling";"Zergling";418;0
"Unit";"Baneling";"Zergling";418;0
"Unit";"Baneling";"Zergling";418;0
"Unit";"Baneling";"Zergling";418;0
"Unit";"Baneling";"Zergling";418;0
"Unit";"Baneling";"Zergling";418;0
"Unit";"Baneling";"Zergling";418;0
"Unit";"Baneling";"Zergling";418;0
"Unit";"Baneling";"Zergling";418;0
"Unit";"Zergling";"Larva";418;1
"Unit";"Zergling";"Larva";419;1
"Unit";"Zergling";"Larva";420;1
"Unit";"Zergling";"Larva";421;1
"Unit";"Zergling";"Larva";422;1
"Unit";"Zergling";"Larva";423;1
"Unit";"Zergling";"Larva";424;1
"Unit";"Zergling";"Larva";425;1
"Unit";"Zergling";"Larva";426;1
"Unit";"Zergling";"Larva";427;1
"Unit";"Zergling";"Larva";428;1
"Unit";"Zergling";"Larva";429;1
"Unit";"Zergling";"Larva";430;1
"Unit";"Zergling";"Larva";431;1
"Unit";"Zergling";"Larva";432;1
"Unit";"Zergling";"Larva";433;1
"Unit";"Zergling";"Larva";434;1
"Unit";"Zergling";"Larva";435;1
"Unit";"Zergling";"Larva";436;1
"Unit";"Zergling";"Larva";437;1
"Unit";"Zergling";"Larva";438;1
"Unit";"Zergling";"Larva";439;1
"Unit";"Zergling";"Larva";440;1
"Unit";"Zergling";"Larva";441;1
"Unit";"Zergling";"Larva";442;1
"Unit";"Zergling";"Larva";443;1
"Unit";"Zergling";"Larva";444;1
"Unit";"Zergling";"Larva";445;1
"Unit";"Zergling";"Larva";446;1
"Unit";"Zergling";"Larva";447;1
"Unit";"Zergling";"Larva";448;1
"Unit";"Zergling";"Larva";449;1
"Unit";"Zergling";"Larva";450;1
"Unit";"Zergling";"Larva";451;1
"Unit";"Zergling";"Larva";452;1
"Unit";"Zergling";"Larva";453;1
"Unit";"Zergling";"Larva";454;1
"Unit";"Zergling";"Larva";455;1
"Unit";"Zergling";"Larva";456;1
"Unit";"Zergling";"Larva";457;1
"Unit";"Zergling";"Larva";460;1
"Unit";"Zergling";"Larva";461;1
"Unit";"Zergling";"Larva";462;1
"Unit";"Zergling";"Larva";463;1
"Unit";"Zergling";"Larva";464;1
"Unit";"Zergling";"Larva";465;1
"Unit";"Zergling";"Larva";466;1
"Unit";"Zergling";"Larva";467;1
"Unit";"Baneling";"Zergling";468;0
"Unit";"Baneling";"Zergling";468;0
"Unit";"Baneling";"Zergling";468;0
"Unit";"Baneling";"Zergling";468;0
"Unit";"Baneling";"Zergling";468;0
"Unit";"Baneling";"Zergling";468;0
"Unit";"Baneling";"Zergling";468;0
"Unit";"Baneling";"Zergling";468;0
"Unit";"Baneling";"Zergling";468;0
"Unit";"Baneling";"Zergling";468;0
"Unit";"Baneling";"Zergling";468;0
"Unit";"Baneling";"Zergling";468;0
"Unit";"Baneling";"Zergling";468;0
"Unit";"Baneling";"Zergling";468;0
"Unit";"Zergling";"Larva";468;1
"Unit";"Zergling";"Larva";469;1
"Unit";"Zergling";"Larva";470;1
"Unit";"Zergling";"Larva";471;1
"Unit";"Zergling";"Larva";472;1
"Unit";"Zergling";"Larva";473;1
"Unit";"Zergling";"Larva";474;1
"Unit";"Zergling";"Larva";475;1
"Unit";"Zergling";"Larva";476;1
"Unit";"Zergling";"Larva";477;1
"Unit";"Zergling";"Larva";478;1
"Unit";"Zergling";"Larva";479;1
"Unit";"Zergling";"Larva";480;1
"Unit";"Zergling";"Larva";481;1
"Unit";"Zergling";"Larva";482;1
"Unit";"Zergling";"Larva";483;1
"Unit";"Zergling";"Larva";484;1
"Unit";"Zergling";"Larva";485;1
"Unit";"Zergling";"Larva";486;1
"Unit";"Zergling";"Larva";487;1
"Unit";"Overlord";"Larva";488;0
"Unit";"Mutalisk";"Larva";488;2
"Unit";"Mutalisk";"Larva";490;2
"Unit";"Mutalisk";"Larva";492;2
"Unit";"Mutalisk";"Larva";494;2
"Unit";"Mutalisk";"Larva";496;2
"Unit";"Mutalisk";"Larva";498;2
"Unit";"Mutalisk";"Larva";500;2
"Unit";"Mutalisk";"Larva";502;2
"Unit";"Mutalisk";"Larva";504;2
"Unit";"Mutalisk";"Larva";506;2
"Unit";"Mutalisk";"Larva";508;2
"Unit";"Baneling";"Zergling";510;0
"Unit";"Baneling";"Zergling";510;0
"Unit";"Baneling";"Zergling";510;0
"Unit";"Baneling";"Zergling";510;0
"Unit";"Baneling";"Zergling";510;0
"Unit";"Baneling";"Zergling";510;0
"Building";"Extractor";NA;510;0
"Building";"Extractor";NA;510;0
"Building";"CreepTumorQueen";NA;510;0
"Unit";"Baneling";"Zergling";510;0
"Unit";"Baneling";"Zergling";510;0
"Unit";"Baneling";"Zergling";510;0
"Unit";"Baneling";"Zergling";510;0
"Unit";"Baneling";"Zergling";510;0
"Unit";"Baneling";"Zergling";510;0
"Unit";"Baneling";"Zergling";510;0
"Unit";"Baneling";"Zergling";510;0
"Unit";"Baneling";"Zergling";510;0
"Unit";"Baneling";"Zergling";510;0
"Unit";"Baneling";"Zergling";510;0
"Unit";"Baneling";"Zergling";510;0
"Unit";"Hydralisk";"Larva";510;2
"Unit";"Hydralisk";"Larva";512;2
"Unit";"Hydralisk";"Larva";514;2
"Unit";"Hydralisk";"Larva";516;2
"Unit";"Hydralisk";"Larva";518;2
"Unit";"Hydralisk";"Larva";520;2
"Unit";"Hydralisk";"Larva";522;2
"Unit";"Zergling";"Larva";524;1
"Unit";"Zergling";"Larva";525;1
"Unit";"Zergling";"Larva";526;1
"Unit";"Zergling";"Larva";527;1
"Unit";"Zergling";"Larva";528;1
"Unit";"Zergling";"Larva";529;1
"Unit";"Zergling";"Larva";530;1
"Unit";"Zergling";"Larva";531;1
"Unit";"Zergling";"Larva";532;1
"Unit";"Zergling";"Larva";533;1
"Unit";"Zergling";"Larva";534;1
"Unit";"Zergling";"Larva";535;1
"Unit";"Zergling";"Larva";536;1
"Unit";"Zergling";"Larva";537;1
"Unit";"Zergling";"Larva";538;1
"Unit";"Zergling";"Larva";539;1
"Unit";"Zergling";"Larva";540;1
"Unit";"Zergling";"Larva";541;1
"Unit";"Zergling";"Larva";542;1
"Unit";"Zergling";"Larva";543;1
"Unit";"Zergling";"Larva";544;1
"Unit";"Zergling";"Larva";545;1
"Unit";"Zergling";"Larva";546;1
"Unit";"Zergling";"Larva";547;1
"Unit";"Zergling";"Larva";548;1
"Unit";"Zergling";"Larva";549;1
"Unit";"Baneling";"Zergling";550;0
"Unit";"Baneling";"Zergling";550;0
"Unit";"Baneling";"Zergling";550;0
"Unit";"Baneling";"Zergling";550;0
"Unit";"Baneling";"Zergling";550;0
"Unit";"Baneling";"Zergling";550;0
"Unit";"Baneling";"Zergling";550;0
"Unit";"Baneling";"Zergling";550;0
"Unit";"Baneling";"Zergling";550;0
"Unit";"Baneling";"Zergling";550;0
"Unit";"Baneling";"Zergling";550;0
"Unit";"Hydralisk";"Larva";550;2
"Unit";"Hydralisk";"Larva";552;2
"Unit";"Hydralisk";"Larva";554;2
"Unit";"Hydralisk";"Larva";556;2
"Unit";"Zergling";"Larva";558;1
"Unit";"Zergling";"Larva";559;1
"Unit";"Zergling";"Larva";560;1
"Unit";"Zergling";"Larva";561;1
"Unit";"Zergling";"Larva";562;1
"Unit";"Zergling";"Larva";563;1
"Unit";"Zergling";"Larva";564;1
"Unit";"Zergling";"Larva";565;1
"Unit";"Baneling";"Zergling";566;0
"Unit";"Baneling";"Zergling";566;0
"Unit";"Baneling";"Zergling";566;0
"Unit";"Baneling";"Zergling";566;0
"Unit";"Baneling";"Zergling";566;0
"Unit";"Baneling";"Zergling";566;0
"Unit";"Baneling";"Zergling";566;0
"Building";"CreepTumor";NA;566;0
"Unit";"Zergling";"Larva";566;1
"Unit";"Zergling";"Larva";567;1
"Unit";"Zergling";"Larva";568;1
"Unit";"Zergling";"Larva";569;1
"Unit";"Zergling";"Larva";570;1
"Unit";"Zergling";"Larva";571;1
"Unit";"Zergling";"Larva";572;1
"Unit";"Zergling";"Larva";573;1
"Unit";"Zergling";"Larva";574;1
"Unit";"Zergling";"Larva";575;1
"Unit";"Zergling";"Larva";576;1
"Unit";"Zergling";"Larva";577;1
"Unit";"Queen";"Hatchery";578;2
"Building";"Extractor";NA;580;0
"Building";"Hatchery";NA;580;0
"Unit";"Zergling";"Larva";580;1
"Unit";"Zergling";"Larva";581;1
"Unit";"Zergling";"Larva";582;1
"Unit";"Zergling";"Larva";583;1
"Unit";"Zergling";"Larva";584;1
"Unit";"Zergling";"Larva";585;1
"Unit";"Zergling";"Larva";586;1
"Unit";"Zergling";"Larva";587;1
"Unit";"Zergling";"Larva";588;1
"Unit";"Zergling";"Larva";589;1
"Unit";"Zergling";"Larva";590;1
"Unit";"Zergling";"Larva";591;1
"Unit";"Zergling";"Larva";592;1
"Unit";"Zergling";"Larva";593;1
"Unit";"Zergling";"Larva";594;1
"Unit";"Zergling";"Larva";595;1
"Unit";"Zergling";"Larva";596;1
"Unit";"Zergling";"Larva";597;1
"Unit";"Zergling";"Larva";598;1
"Unit";"Zergling";"Larva";599;1
"Unit";"Zergling";"Larva";600;1
"Unit";"Zergling";"Larva";601;1
"Unit";"Zergling";"Larva";602;1
"Unit";"Zergling";"Larva";603;1
"Unit";"Zergling";"Larva";604;1
"Unit";"Zergling";"Larva";605;1
"Unit";"Zergling";"Larva";606;1
"Unit";"Zergling";"Larva";607;1
"Unit";"Zergling";"Larva";608;1
"Unit";"Zergling";"Larva";609;1
"Unit";"Zergling";"Larva";610;1
"Unit";"Zergling";"Larva";611;1
"Unit";"Zergling";"Larva";612;1
"Unit";"Zergling";"Larva";613;1
"Unit";"Zergling";"Larva";614;1
"Unit";"Zergling";"Larva";615;1
"Unit";"Zergling";"Larva";616;1
"Unit";"Zergling";"Larva";617;1
"Unit";"Zergling";"Larva";618;1
"Unit";"Zergling";"Larva";619;1
"Unit";"Zergling";"Larva";620;1
"Unit";"Zergling";"Larva";621;1
"Unit";"Zergling";"Larva";622;1
"Unit";"Zergling";"Larva";623;1
"Unit";"Zergling";"Larva";624;1
"Unit";"Zergling";"Larva";625;1
"Unit";"Baneling";"Zergling";626;0
"Unit";"Baneling";"Zergling";626;0
"Unit";"Baneling";"Zergling";626;0
"Unit";"Baneling";"Zergling";626;0
"Unit";"Baneling";"Zergling";626;0
"Unit";"Baneling";"Zergling";626;0
"Unit";"Baneling";"Zergling";626;0
"Unit";"Baneling";"Zergling";626;0
"Unit";"Baneling";"Zergling";626;0
"Unit";"Baneling";"Zergling";626;0
"Unit";"Baneling";"Zergling";626;0
"Unit";"Baneling";"Zergling";626;0
"Unit";"Baneling";"Zergling";626;0
"Unit";"Baneling";"Zergling";626;0
"Unit";"Baneling";"Zergling";626;0
"Unit";"Zergling";"Larva";626;1
"Unit";"Zergling";"Larva";627;1
"Unit";"Zergling";"Larva";628;1
"Unit";"Zergling";"Larva";629;1
"Unit";"Zergling";"Larva";630;1
"Unit";"Zergling";"Larva";631;1
"Unit";"Zergling";"Larva";632;1
"Unit";"Zergling";"Larva";633;1
"Unit";"Zergling";"Larva";634;1
"Unit";"Zergling";"Larva";635;1
"Unit";"Zergling";"Larva";636;1
"Unit";"Zergling";"Larva";637;1
"Unit";"Hydralisk";"Larva";638;2
"Unit";"Hydralisk";"Larva";640;2
"Unit";"Hydralisk";"Larva";642;2
"Unit";"Hydralisk";"Larva";644;2
"Unit";"Hydralisk";"Larva";646;2
"Unit";"Hydralisk";"Larva";648;2
"Unit";"Hydralisk";"Larva";650;2
"Unit";"Hydralisk";"Larva";652;2
"Unit";"Hydralisk";"Larva";654;2
"Unit";"Hydralisk";"Larva";656;2
"Unit";"Hydralisk";"Larva";658;2
"Unit";"Baneling";"Zergling";660;0
"Unit";"Baneling";"Zergling";660;0
"Unit";"Baneling";"Zergling";660;0
"Unit";"Baneling";"Zergling";660;0
"Unit";"Baneling";"Zergling";660;0
"Unit";"Baneling";"Zergling";660;0
"Unit";"Baneling";"Zergling";660;0
"Unit";"Baneling";"Zergling";660;0
"Unit";"Baneling";"Zergling";660;0
"Unit";"Baneling";"Zergling";660;0
"Unit";"Baneling";"Zergling";660;0
"Unit";"Baneling";"Zergling";660;0
"Unit";"Baneling";"Zergling";660;0
"Unit";"Baneling";"Zergling";660;0
"Unit";"Baneling";"Zergling";660;0
"Unit";"Baneling";"Zergling";660;0
"Unit";"Baneling";"Zergling";660;0
"Unit";"Baneling";"Zergling";660;0
"Unit";"Baneling";"Zergling";660;0
"Unit";"Baneling";"Zergling";660;0
"Unit";"Zergling";"Larva";660;1
"Unit";"Zergling";"Larva";661;1
"Unit";"Zergling";"Larva";662;1
"Unit";"Zergling";"Larva";663;1
"Unit";"Zergling";"Larva";664;1
"Unit";"Zergling";"Larva";665;1
"Unit";"Zergling";"Larva";666;1
"Unit";"Zergling";"Larva";667;1
"Unit";"Zergling";"Larva";668;1
"Unit";"Zergling";"Larva";669;1
"Unit";"Zergling";"Larva";670;1
"Unit";"Zergling";"Larva";671;1
"Unit";"Zergling";"Larva";672;1
"Unit";"Zergling";"Larva";673;1
"Unit";"Zergling";"Larva";674;1
"Unit";"Zergling";"Larva";675;1
"Unit";"Zergling";"Larva";676;1
"Unit";"Zergling";"Larva";677;1
"Unit";"Zergling";"Larva";678;1
"Unit";"Zergling";"Larva";679;1
"Unit";"Zergling";"Larva";680;1
"Unit";"Zergling";"Larva";681;1
"Unit";"Zergling";"Larva";682;1
"Unit";"Zergling";"Larva";683;1
"Unit";"Zergling";"Larva";684;1
"Unit";"Zergling";"Larva";685;1
"Unit";"Zergling";"Larva";686;1
"Unit";"Zergling";"Larva";687;1
"Unit";"Zergling";"Larva";688;1
"Unit";"Zergling";"Larva";689;1
"Unit";"Zergling";"Larva";690;1
"Unit";"Zergling";"Larva";691;1
"Unit";"Zergling";"Larva";692;1
"Unit";"Zergling";"Larva";693;1
"Unit";"Zergling";"Larva";694;1
"Unit";"Zergling";"Larva";695;1
"Unit";"Zergling";"Larva";696;1
"Unit";"Zergling";"Larva";697;1
"Unit";"Zergling";"Larva";698;1
"Unit";"Zergling";"Larva";699;1
"Unit";"Zergling";"Larva";700;1
"Unit";"Zergling";"Larva";701;1
"Unit";"Zergling";"Larva";702;1
"Unit";"Zergling";"Larva";703;1
"Unit";"Zergling";"Larva";704;1
"Unit";"Zergling";"Larva";705;1
"Unit";"Zergling";"Larva";706;1
"Unit";"Zergling";"Larva";707;1
"Unit";"Zergling";"Larva";708;1
"Unit";"Zergling";"Larva";709;1
"Unit";"Zergling";"Larva";710;1
"Unit";"Zergling";"Larva";711;1
"Unit";"Zergling";"Larva";712;1
"Unit";"Zergling";"Larva";713;1
"Unit";"Zergling";"Larva";714;1
"Unit";"Zergling";"Larva";715;1
"Unit";"Zergling";"Larva";716;1
"Unit";"Zergling";"Larva";717;1
"Unit";"Zergling";"Larva";718;1
"Unit";"Zergling";"Larva";719;1
"Unit";"Zergling";"Larva";720;1
"Unit";"Zergling";"Larva";721;1
"Unit";"Zergling";"Larva";722;1
"Unit";"Zergling";"Larva";723;1
"Unit";"Zergling";"Larva";724;1
"Unit";"Zergling";"Larva";725;1
"Unit";"Zergling";"Larva";726;1
"Unit";"Zergling";"Larva";727;1
"Unit";"Zergling";"Larva";728;1
"Unit";"Zergling";"Larva";729;1
"Unit";"Zergling";"Larva";730;1
"Unit";"Zergling";"Larva";731;1
"Unit";"Zergling";"Larva";732;1
"Unit";"Zergling";"Larva";733;1
"Unit";"Zergling";"Larva";734;1
"Unit";"Zergling";"Larva";735;1
"Unit";"Zergling";"Larva";736;1
"Unit";"Zergling";"Larva";737;1
"Unit";"Zergling";"Larva";738;1
"Unit";"Zergling";"Larva";739;1
"Unit";"Zergling";"Larva";740;1
"Unit";"Zergling";"Larva";741;1
"Unit";"Zergling";"Larva";742;1
"Unit";"Zergling";"Larva";743;1
"Unit";"Zergling";"Larva";744;1
"Unit";"Zergling";"Larva";745;1
"Unit";"Zergling";"Larva";746;1
"Unit";"Zergling";"Larva";747;1
"Unit";"Zergling";"Larva";748;1
"Unit";"Zergling";"Larva";749;1
"Unit";"Zergling";"Larva";750;1
"Unit";"Zergling";"Larva";751;1
"Unit";"Zergling";"Larva";752;1
"Unit";"Zergling";"Larva";753;1
"Unit";"Zergling";"Larva";754;1
"Unit";"Zergling";"Larva";755;1
"Unit";"Zergling";"Larva";756;1
"Unit";"Zergling";"Larva";757;1
"Unit";"Zergling";"Larva";758;1
"Unit";"Zergling";"Larva";759;1
"Unit";"Zergling";"Larva";760;1
"Unit";"Zergling";"Larva";761;1
"Unit";"Baneling";"Zergling";762;0
"Unit";"Baneling";"Zergling";762;0
"Unit";"Baneling";"Zergling";762;0
"Unit";"Baneling";"Zergling";762;0
"Unit";"Zergling";"Larva";762;1
"Unit";"Zergling";"Larva";763;1
"Unit";"Zergling";"Larva";764;1
"Unit";"Zergling";"Larva";765;1
"Unit";"Zergling";"Larva";766;1
"Unit";"Zergling";"Larva";767;1
"Unit";"Zergling";"Larva";768;1
"Unit";"Zergling";"Larva";769;1
"Unit";"Zergling";"Larva";770;1
"Unit";"Zergling";"Larva";771;1
"Unit";"Zergling";"Larva";772;1
"Unit";"Zergling";"Larva";773;1
"Unit";"Zergling";"Larva";774;1
"Unit";"Zergling";"Larva";775;1
"Unit";"Zergling";"Larva";776;1
"Unit";"Zergling";"Larva";777;1
"Unit";"Zergling";"Larva";778;1
"Unit";"Zergling";"Larva";779;1
"Unit";"Zergling";"Larva";780;1
"Unit";"Zergling";"Larva";781;1
"Unit";"Zergling";"Larva";782;1
"Unit";"Zergling";"Larva";783;1
"Unit";"Zergling";"Larva";784;1
"Unit";"Zergling";"Larva";785;1
"Unit";"Zergling";"Larva";786;1
"Unit";"Zergling";"Larva";787;1
"Unit";"Zergling";"Larva";788;1
"Unit";"Zergling";"Larva";789;1
"Unit";"Zergling";"Larva";790;1
"Unit";"Zergling";"Larva";791;1
"Unit";"Zergling";"Larva";792;1
"Unit";"Zergling";"Larva";793;1
"Unit";"Zergling";"Larva";794;1
"Unit";"Zergling";"Larva";795;1
"Unit";"Zergling";"Larva";796;1
"Unit";"Zergling";"Larva";797;1
"Unit";"Zergling";"Larva";798;1
"Unit";"Zergling";"Larva";799;1
"Unit";"Zergling";"Larva";800;1
"Unit";"Zergling";"Larva";801;1
"Unit";"Zergling";"Larva";802;1
"Unit";"Zergling";"Larva";803;1
"Unit";"Zergling";"Larva";804;1
"Unit";"Zergling";"Larva";805;1
"Unit";"Baneling";"Zergling";806;0
"Unit";"Baneling";"Zergling";806;0
"Unit";"Baneling";"Zergling";806;0
"Unit";"Baneling";"Zergling";806;0
"Unit";"Baneling";"Zergling";806;0
"Unit";"Baneling";"Zergling";806;0
"Unit";"Baneling";"Zergling";806;0
"Unit";"Baneling";"Zergling";806;0
"Building";"Hatchery";NA;806;0
"Unit";"Zergling";"Larva";806;1
"Unit";"Zergling";"Larva";807;1
"Unit";"Zergling";"Larva";808;1
"Unit";"Zergling";"Larva";809;1
"Unit";"Zergling";"Larva";810;1
"Unit";"Zergling";"Larva";811;1
"Unit";"Zergling";"Larva";812;1
"Unit";"Zergling";"Larva";813;1
"Unit";"Zergling";"Larva";814;1
"Unit";"Zergling";"Larva";815;1
"Unit";"Zergling";"Larva";816;1
"Unit";"Zergling";"Larva";817;1
"Unit";"Zergling";"Larva";818;1
"Unit";"Zergling";"Larva";819;1
"Unit";"Zergling";"Larva";820;1
"Unit";"Zergling";"Larva";821;1
"Unit";"Zergling";"Larva";822;1
"Unit";"Zergling";"Larva";823;1
"Unit";"Zergling";"Larva";824;1
"Unit";"Zergling";"Larva";825;1
"Unit";"Zergling";"Larva";826;1
"Unit";"Zergling";"Larva";827;1
"Unit";"Zergling";"Larva";828;1
"Unit";"Zergling";"Larva";829;1
"Unit";"Zergling";"Larva";830;1
"Unit";"Zergling";"Larva";831;1
"Unit";"Zergling";"Larva";832;1
"Unit";"Zergling";"Larva";833;1
"Unit";"Zergling";"Larva";834;1
"Unit";"Zergling";"Larva";835;1
"Unit";"Zergling";"Larva";836;1
"Unit";"Zergling";"Larva";837;1
"Unit";"Zergling";"Larva";838;1
"Unit";"Zergling";"Larva";839;1
"Unit";"Zergling";"Larva";840;1
"Unit";"Zergling";"Larva";841;1
"Unit";"Zergling";"Larva";842;1
"Unit";"Zergling";"Larva";843;1
"Unit";"Zergling";"Larva";844;1
"Unit";"Zergling";"Larva";845;1
"Unit";"Zergling";"Larva";846;1
"Unit";"Zergling";"Larva";847;1
"Unit";"Zergling";"Larva";852;1
"Unit";"Zergling";"Larva";853;1
"Unit";"Zergling";"Larva";854;1
"Unit";"Zergling";"Larva";855;1
"Unit";"Zergling";"Larva";856;1
"Unit";"Zergling";"Larva";857;1
"Unit";"Zergling";"Larva";858;1
"Unit";"Zergling";"Larva";859;1
"Unit";"Zergling";"Larva";860;1
"Unit";"Zergling";"Larva";861;1
"Unit";"Zergling";"Larva";862;1
"Unit";"Zergling";"Larva";863;1
"Unit";"Zergling";"Larva";864;1
"Unit";"Zergling";"Larva";865;1
"Unit";"Zergling";"Larva";866;1
"Unit";"Zergling";"Larva";867;1
"Unit";"Baneling";"Zergling";868;0
"Unit";"Baneling";"Zergling";868;0
"Unit";"Baneling";"Zergling";868;0
"Unit";"Baneling";"Zergling";868;0
"Unit";"Baneling";"Zergling";868;0
"Unit";"Baneling";"Zergling";868;0
"Unit";"Baneling";"Zergling";868;0
"Unit";"Baneling";"Zergling";868;0
"Unit";"Baneling";"Zergling";868;0
"Unit";"Baneling";"Zergling";868;0
"Unit";"Baneling";"Zergling";868;0
"Unit";"Baneling";"Zergling";868;0
"Unit";"Baneling";"Zergling";868;0
"Unit";"Baneling";"Zergling";868;0
"Unit";"Baneling";"Zergling";868;0
"Unit";"Baneling";"Zergling";868;0
"Unit";"Baneling";"Zergling";868;0
"Unit";"Baneling";"Zergling";868;0
"Unit";"Baneling";"Zergling";868;0
"Unit";"Baneling";"Zergling";868;0
"Unit";"Baneling";"Zergling";868;0
"Building";"Hatchery";NA;868;0
"Unit";"Zergling";"Larva";868;1
"Unit";"Zergling";"Larva";869;1
"Unit";"Zergling";"Larva";870;1
"Unit";"Zergling";"Larva";871;1
"Unit";"Zergling";"Larva";872;1
"Unit";"Zergling";"Larva";873;1
"Unit";"Zergling";"Larva";874;1
"Unit";"Zergling";"Larva";875;1
"Unit";"Zergling";"Larva";876;1
"Unit";"Zergling";"Larva";877;1
"Unit";"Zergling";"Larva";878;1
"Unit";"Zergling";"Larva";879;1
"Unit";"Zergling";"Larva";880;1
"Unit";"Zergling";"Larva";881;1
"Unit";"Zergling";"Larva";882;1
"Unit";"Zergling";"Larva";883;1
"Unit";"Zergling";"Larva";884;1
"Unit";"Zergling";"Larva";885;1
"Unit";"Zergling";"Larva";886;1
"Unit";"Zergling";"Larva";887;1
"Unit";"Zergling";"Larva";888;1
"Unit";"Zergling";"Larva";889;1
"Unit";"Zergling";"Larva";890;1
"Unit";"Zergling";"Larva";891;1
"Unit";"Zergling";"Larva";892;1
"Unit";"Zergling";"Larva";893;1
"Unit";"Zergling";"Larva";894;1
"Unit";"Zergling";"Larva";895;1
"Unit";"Zergling";"Larva";896;1
"Unit";"Zergling";"Larva";897;1
"Unit";"Zergling";"Larva";898;1
"Unit";"Zergling";"Larva";899;1
"Unit";"Zergling";"Larva";900;1
"Unit";"Zergling";"Larva";901;1
"Unit";"Zergling";"Larva";902;1
"Unit";"Zergling";"Larva";903;1
"Unit";"Zergling";"Larva";904;1
"Unit";"Zergling";"Larva";905;1
"Unit";"Zergling";"Larva";906;1
"Unit";"Zergling";"Larva";907;1
"Unit";"Zergling";"Larva";908;1
"Unit";"Zergling";"Larva";909;1
"Unit";"Zergling";"Larva";910;1
"Unit";"Zergling";"Larva";911;1
"Unit";"Zergling";"Larva";912;1
"Unit";"Zergling";"Larva";913;1
"Unit";"Zergling";"Larva";914;1
"Unit";"Zergling";"Larva";915;1
"Unit";"Baneling";"Zergling";916;0
"Unit";"Baneling";"Zergling";916;0
"Unit";"Baneling";"Zergling";916;0
"Unit";"Baneling";"Zergling";916;0
"Unit";"Baneling";"Zergling";916;0
"Unit";"Baneling";"Zergling";916;0
"Unit";"Baneling";"Zergling";916;0
"Unit";"Baneling";"Zergling";916;0
"Unit";"Zergling";"Larva";916;1
"Unit";"Zergling";"Larva";917;1
"Unit";"Zergling";"Larva";918;1
"Unit";"Zergling";"Larva";919;1
"Unit";"Zergling";"Larva";920;1
"Unit";"Zergling";"Larva";921;1
"Unit";"Zergling";"Larva";922;1
"Unit";"Zergling";"Larva";923;1
"Unit";"Zergling";"Larva";924;1
"Unit";"Zergling";"Larva";925;1
"Unit";"Zergling";"Larva";926;1
"Unit";"Zergling";"Larva";927;1
"Unit";"Zergling";"Larva";928;1
"Unit";"Zergling";"Larva";929;1
"Unit";"Zergling";"Larva";930;1
"Unit";"Zergling";"Larva";931;1
"Unit";"Zergling";"Larva";932;1
"Unit";"Zergling";"Larva";933;1
"Unit";"Zergling";"Larva";934;1
"Unit";"Zergling";"Larva";935;1
"Unit";"Zergling";"Larva";936;1
"Unit";"Zergling";"Larva";937;1
"Unit";"Zergling";"Larva";938;1
"Unit";"Zergling";"Larva";939;1
"Unit";"Zergling";"Larva";940;1
"Unit";"Zergling";"Larva";941;1
"Unit";"Zergling";"Larva";942;1
"Unit";"Zergling";"Larva";943;1
"Unit";"Zergling";"Larva";944;1
"Unit";"Zergling";"Larva";945;1
"Unit";"Baneling";"Zergling";946;0
"Unit";"Baneling";"Zergling";946;0
"Unit";"Baneling";"Zergling";946;0
"Unit";"Corruptor";"Larva";946;2
"Unit";"Corruptor";"Larva";948;2
"Unit";"Corruptor";"Larva";950;2
"Unit";"Corruptor";"Larva";952;2
"Unit";"Corruptor";"Larva";954;2
"Unit";"Corruptor";"Larva";956;2
"Unit";"Zergling";"Larva";963;1
"Unit";"Zergling";"Larva";964;1
"Unit";"Zergling";"Larva";965;1
"Unit";"Zergling";"Larva";966;1
"Unit";"Zergling";"Larva";967;1
"Unit";"Zergling";"Larva";968;1
"Unit";"Zergling";"Larva";969;1
"Unit";"Zergling";"Larva";970;1
"Unit";"Zergling";"Larva";971;1
"Unit";"Zergling";"Larva";972;1
"Unit";"Zergling";"Larva";973;1
"Unit";"Zergling";"Larva";974;1
"Unit";"Zergling";"Larva";975;1
"Unit";"Zergling";"Larva";976;1
"Unit";"Zergling";"Larva";977;1
"Unit";"Zergling";"Larva";978;1
"Unit";"Zergling";"Larva";979;1
"Unit";"Zergling";"Larva";980;1
"Unit";"Zergling";"Larva";981;1
"Unit";"Zergling";"Larva";982;1
"Unit";"Zergling";"Larva";983;1
"Unit";"Zergling";"Larva";984;1
"Unit";"Zergling";"Larva";985;1
"Unit";"Zergling";"Larva";986;1
"Unit";"Zergling";"Larva";987;1
"Unit";"Zergling";"Larva";988;1
"Unit";"Zergling";"Larva";989;1
"Unit";"Zergling";"Larva";990;1
"Unit";"Zergling";"Larva";991;1
"Unit";"Zergling";"Larva";992;1
"Unit";"Zergling";"Larva";993;1
"Unit";"Zergling";"Larva";994;1
"Unit";"Zergling";"Larva";995;1
"Unit";"Zergling";"Larva";996;1
"Unit";"Zergling";"Larva";997;1
"Unit";"Zergling";"Larva";998;1
"Unit";"Zergling";"Larva";999;1
"Unit";"Zergling";"Larva";1000;1
"Unit";"Zergling";"Larva";1001;1
"Unit";"Zergling";"Larva";1002;1
"Unit";"Zergling";"Larva";1003;1
"Unit";"Zergling";"Larva";1004;1
"Unit";"Zergling";"Larva";1005;1
"Unit";"Zergling";"Larva";1006;1
"Unit";"Zergling";"Larva";1007;1
"Unit";"Zergling";"Larva";1008;1
"Unit";"Zergling";"Larva";1009;1
"Unit";"Zergling";"Larva";1010;1
"Unit";"Zergling";"Larva";1011;1
"Unit";"Zergling";"Larva";1012;1
"Building";"Extractor";NA;1013;0
"Building";"Extractor";NA;1013;0
"Unit";"Baneling";"Zergling";1013;0
"Unit";"Hydralisk";"Larva";1013;2
"Unit";"Hydralisk";"Larva";1015;2
"Unit";"Zergling";"Larva";1017;1
"Unit";"Zergling";"Larva";1018;1
"Unit";"Zergling";"Larva";1019;1
"Unit";"Zergling";"Larva";1020;1
"Unit";"Zergling";"Larva";1021;1
"Unit";"Zergling";"Larva";1022;1
"Unit";"Zergling";"Larva";1023;1
"Unit";"Zergling";"Larva";1024;1
"Unit";"Zergling";"Larva";1025;1
"Unit";"Zergling";"Larva";1026;1
"Unit";"Zergling";"Larva";1027;1
"Unit";"Zergling";"Larva";1028;1
"Unit";"Zergling";"Larva";1029;1
"Unit";"Zergling";"Larva";1030;1
"Unit";"Zergling";"Larva";1031;1
"Unit";"Zergling";"Larva";1032;1
"Unit";"Zergling";"Larva";1033;1
"Unit";"Zergling";"Larva";1034;1
"Unit";"Zergling";"Larva";1035;1
"Unit";"Zergling";"Larva";1036;1
"Unit";"Zergling";"Larva";1037;1
"Unit";"Zergling";"Larva";1038;1
"Unit";"Baneling";"Zergling";1039;0
"Unit";"Baneling";"Zergling";1039;0
"Unit";"Baneling";"Zergling";1039;0
"Unit";"Baneling";"Zergling";1039;0
"Unit";"Baneling";"Zergling";1039;0
"Unit";"Baneling";"Zergling";1039;0
"Unit";"Baneling";"Zergling";1039;0
"Unit";"Baneling";"Zergling";1039;0
"Unit";"Baneling";"Zergling";1039;0
"Upgrade";"SprayZerg";NA;1039;0
"Upgrade";"SprayZerg";NA;1039;0
"Upgrade";"SprayZerg";NA;1039;0
"Upgrade";"zerglingmovementspeed";NA;1039;0
"Upgrade";"SprayZerg";NA;1039;0
"Upgrade";"ZergMeleeWeaponsLevel1";NA;1039;0
"Upgrade";"SprayZerg";NA;1039;0
"Upgrade";"SprayZerg";NA;1039;0
"Upgrade";"SprayZerg";NA;1039;0
"Upgrade";"EvolveMuscularAugments";NA;1039;0
"Upgrade";"CentrificalHooks";NA;1039;0
"Upgrade";"ZergMissileWeaponsLevel1";NA;1039;0
"Upgrade";"SprayZerg";NA;1039;0
"Upgrade";"SprayZerg";NA;1039;0
"Upgrade";"SprayZerg";NA;1039;0
"Upgrade";"ZergMeleeWeaponsLevel2";NA;1039;0
"Upgrade";"ZergGroundArmorsLevel1";NA;1039;0
"Upgrade";"SprayZerg";NA;1039;0
"Upgrade";"SprayZerg";NA;1039;0
"Upgrade";"zerglingattackspeed";NA;1039;0
"Upgrade";"ZergMissileWeaponsLevel2";NA;1039;0
"Upgrade";"SprayZerg";NA;1039;0
"Upgrade";"SprayZerg";NA;1039;0
"Upgrade";"SprayZerg";NA;1039;0
"Upgrade";"SprayZerg";NA;1039;0
"Upgrade";"ZergMeleeWeaponsLevel3";NA;1039;0
