"type";"unit_name";"on_building";"total_supply_lag"
"Unit";"Overlord";"Larva";13
"Building";"Extractor";NA;18
"Building";"SpawningPool";NA;18
"Building";"Hatchery";NA;20
"Unit";"Queen";"Hatchery";21
"Unit";"Zergling";"Larva";23
"Unit";"Zergling";"Larva";24
"Unit";"Overlord";"Larva";25
"Unit";"Queen";"Hatchery";28
"Unit";"Zergling";"Larva";33
"Unit";"Zergling";"Larva";34
"Unit";"Zergling";"Larva";35
"Unit";"Zergling";"Larva";36
"Unit";"Zergling";"Larva";39
"Unit";"Zergling";"Larva";40
"Building";"Hatchery";NA;41
"Unit";"Overlord";"Larva";41
"Building";"CreepTumorQueen";NA;44
"Unit";"Queen";"Hatchery";44
"Unit";"Overlord";"Larva";52
"Unit";"Overlord";"Larva";52
"Building";"EvolutionChamber";NA;52
"Building";"BanelingNest";NA;52
"Building";"CreepTumorQueen";NA;56
"Unit";"Queen";"Hatchery";59
"Building";"SporeCrawler";NA;61
"Unit";"Zergling";"Larva";61
"Unit";"Zergling";"Larva";62
"Building";"SporeCrawler";NA;63
"Unit";"Zergling";"Larva";63
"Unit";"Zergling";"Larva";64
"Unit";"Zergling";"Larva";65
"Unit";"Zergling";"Larva";66
"Unit";"Zergling";"Larva";67
"Unit";"Zergling";"Larva";68
"Unit";"Overlord";"Larva";69
"Building";"CreepTumor";NA;70
"Building";"CreepTumor";NA;70
"Unit";"Zergling";"Larva";70
"Unit";"Zergling";"Larva";71
"Unit";"Zergling";"Larva";72
"Unit";"Zergling";"Larva";73
"Unit";"Baneling";"Zergling";74
"Unit";"Baneling";"Zergling";74
"Unit";"Queen";"Hatchery";74
"Building";"Extractor";NA;81
"Building";"CreepTumorQueen";NA;83
"Unit";"Baneling";"Zergling";88
"Unit";"Baneling";"Zergling";88
"Unit";"Overlord";"Larva";88
"Building";"CreepTumor";NA;92
"Unit";"Overlord";"Larva";93
"Unit";"Overlord";"Larva";93
"Unit";"Overlord";"Larva";93
"Unit";"Overlord";"Larva";93
"Unit";"Overlord";"Larva";93
"Unit";"Queen";"Hatchery";94
"Unit";"Zergling";"Larva";96
"Unit";"Zergling";"Larva";97
"Unit";"Zergling";"Larva";98
"Unit";"Zergling";"Larva";99
"Unit";"Zergling";"Larva";100
"Unit";"Zergling";"Larva";101
"Unit";"Zergling";"Larva";102
"Unit";"Zergling";"Larva";103
"Building";"Extractor";NA;106
"Building";"Extractor";NA;106
"Building";"Extractor";NA;108
"Unit";"Overlord";"Larva";108
"Building";"CreepTumor";NA;110
"Building";"CreepTumorQueen";NA;111
"Building";"CreepTumorQueen";NA;111
"Unit";"Overlord";"Larva";111
"Unit";"Zergling";"Larva";111
"Unit";"Zergling";"Larva";112
"Unit";"Zergling";"Larva";113
"Unit";"Zergling";"Larva";114
"Unit";"Zergling";"Larva";115
"Unit";"Zergling";"Larva";116
"Unit";"Zergling";"Larva";117
"Unit";"Zergling";"Larva";118
"Unit";"Zergling";"Larva";119
"Unit";"Zergling";"Larva";120
"Building";"Hatchery";NA;121
"Unit";"Overlord";"Larva";123
"Unit";"Overlord";"Larva";123
"Unit";"Queen";"Hatchery";128
"Unit";"Baneling";"Zergling";130
"Unit";"Baneling";"Zergling";130
"Unit";"Baneling";"Zergling";130
"Unit";"Baneling";"Zergling";130
"Unit";"Baneling";"Zergling";130
"Unit";"Baneling";"Zergling";130
"Unit";"Baneling";"Zergling";130
"Unit";"Baneling";"Zergling";130
"Unit";"Baneling";"Zergling";130
"Building";"CreepTumor";NA;130
"Unit";"Overlord";"Larva";130
"Building";"CreepTumor";NA;130
"Unit";"Overlord";"Larva";130
"Building";"CreepTumor";NA;130
"Unit";"Zergling";"Larva";130
"Unit";"Zergling";"Larva";131
"Unit";"Zergling";"Larva";132
"Unit";"Zergling";"Larva";133
"Unit";"Zergling";"Larva";134
"Unit";"Zergling";"Larva";135
"Unit";"Zergling";"Larva";136
"Unit";"Zergling";"Larva";137
"Unit";"Zergling";"Larva";138
"Unit";"Zergling";"Larva";139
"Unit";"Zergling";"Larva";140
"Unit";"Zergling";"Larva";141
"Unit";"Zergling";"Larva";142
"Unit";"Zergling";"Larva";143
"Unit";"Zergling";"Larva";144
"Unit";"Zergling";"Larva";145
"Unit";"Baneling";"Zergling";146
"Unit";"Baneling";"Zergling";146
"Unit";"Baneling";"Zergling";146
"Unit";"Baneling";"Zergling";146
"Unit";"Baneling";"Zergling";146
"Unit";"Baneling";"Zergling";146
"Unit";"Baneling";"Zergling";146
"Unit";"Zergling";"Larva";146
"Unit";"Zergling";"Larva";147
"Unit";"Zergling";"Larva";148
"Unit";"Zergling";"Larva";149
"Unit";"Zergling";"Larva";150
"Unit";"Zergling";"Larva";151
"Unit";"Zergling";"Larva";152
"Unit";"Zergling";"Larva";153
"Unit";"Zergling";"Larva";154
"Unit";"Zergling";"Larva";155
"Unit";"Zergling";"Larva";156
"Unit";"Zergling";"Larva";157
"Unit";"Zergling";"Larva";158
"Unit";"Zergling";"Larva";159
"Unit";"Zergling";"Larva";160
"Unit";"Zergling";"Larva";161
"Unit";"Zergling";"Larva";162
"Unit";"Zergling";"Larva";163
"Unit";"Zergling";"Larva";164
"Unit";"Zergling";"Larva";165
"Unit";"Zergling";"Larva";166
"Unit";"Zergling";"Larva";167
"Unit";"Zergling";"Larva";168
"Unit";"Zergling";"Larva";169
"Unit";"Zergling";"Larva";170
"Unit";"Zergling";"Larva";171
"Unit";"Zergling";"Larva";172
"Unit";"Zergling";"Larva";173
"Unit";"Zergling";"Larva";174
"Unit";"Zergling";"Larva";175
"Unit";"Zergling";"Larva";176
"Unit";"Zergling";"Larva";177
"Unit";"Baneling";"Zergling";178
"Unit";"Baneling";"Zergling";178
"Unit";"Baneling";"Zergling";178
"Unit";"Baneling";"Zergling";178
"Unit";"Baneling";"Zergling";178
"Unit";"Baneling";"Zergling";178
"Unit";"Baneling";"Zergling";178
"Unit";"Baneling";"Zergling";178
"Unit";"Baneling";"Zergling";178
"Building";"Hatchery";NA;178
"Building";"HydraliskDen";NA;178
"Unit";"Zergling";"Larva";178
"Unit";"Zergling";"Larva";179
"Unit";"Zergling";"Larva";180
"Unit";"Zergling";"Larva";181
"Unit";"Zergling";"Larva";182
"Unit";"Zergling";"Larva";183
"Unit";"Zergling";"Larva";184
"Unit";"Zergling";"Larva";185
"Unit";"Zergling";"Larva";186
"Unit";"Zergling";"Larva";187
"Unit";"Zergling";"Larva";188
"Unit";"Zergling";"Larva";189
"Unit";"Zergling";"Larva";190
"Unit";"Zergling";"Larva";191
"Building";"CreepTumorQueen";NA;192
"Building";"CreepTumorQueen";NA;192
"Building";"CreepTumor";NA;199
"Building";"CreepTumorQueen";NA;199
"Building";"Extractor";NA;204
"Building";"CreepTumor";NA;204
"Unit";"Hydralisk";"Larva";204
"Unit";"Hydralisk";"Larva";206
"Unit";"Hydralisk";"Larva";208
"Unit";"Hydralisk";"Larva";210
"Unit";"Hydralisk";"Larva";212
"Building";"CreepTumorQueen";NA;214
"Building";"CreepTumorQueen";NA;214
"Unit";"Hydralisk";"Larva";214
"Unit";"Hydralisk";"Larva";216
"Unit";"Hydralisk";"Larva";218
"Unit";"Hydralisk";"Larva";220
"Unit";"Hydralisk";"Larva";222
"Unit";"Overlord";"Larva";224
"Unit";"Baneling";"Zergling";224
"Unit";"Baneling";"Zergling";224
"Unit";"Baneling";"Zergling";224
"Unit";"Baneling";"Zergling";224
"Unit";"Baneling";"Zergling";224
"Unit";"Baneling";"Zergling";224
"Unit";"Hydralisk";"Larva";224
"Unit";"Zergling";"Larva";226
"Unit";"Zergling";"Larva";227
"Unit";"Zergling";"Larva";228
"Unit";"Zergling";"Larva";229
"Unit";"Zergling";"Larva";230
"Unit";"Zergling";"Larva";231
"Unit";"Zergling";"Larva";232
"Unit";"Zergling";"Larva";233
"Unit";"Zergling";"Larva";234
"Unit";"Zergling";"Larva";235
"Unit";"Zergling";"Larva";236
"Unit";"Zergling";"Larva";237
"Unit";"Zergling";"Larva";238
"Unit";"Zergling";"Larva";239
"Unit";"Hydralisk";"Larva";240
"Unit";"Hydralisk";"Larva";242
"Unit";"Hydralisk";"Larva";244
"Unit";"Hydralisk";"Larva";246
"Unit";"Zergling";"Larva";248
"Unit";"Zergling";"Larva";249
"Unit";"Zergling";"Larva";250
"Unit";"Zergling";"Larva";251
"Unit";"Zergling";"Larva";252
"Unit";"Zergling";"Larva";253
"Unit";"Hydralisk";"Larva";254
"Unit";"Hydralisk";"Larva";256
"Unit";"Hydralisk";"Larva";258
"Unit";"Zergling";"Larva";260
"Unit";"Zergling";"Larva";261
"Unit";"Zergling";"Larva";262
"Unit";"Zergling";"Larva";263
"Unit";"Zergling";"Larva";264
"Unit";"Zergling";"Larva";265
"Unit";"Zergling";"Larva";266
"Unit";"Zergling";"Larva";267
"Unit";"Baneling";"Zergling";268
"Unit";"Baneling";"Zergling";268
"Unit";"Hydralisk";"Larva";268
"Unit";"Hydralisk";"Larva";270
"Unit";"Hydralisk";"Larva";272
"Unit";"Hydralisk";"Larva";274
"Unit";"Hydralisk";"Larva";276
"Unit";"Zergling";"Larva";278
"Unit";"Zergling";"Larva";279
"Unit";"Hydralisk";"Larva";280
"Unit";"Hydralisk";"Larva";282
"Unit";"Hydralisk";"Larva";284
"Unit";"Zergling";"Larva";286
"Unit";"Zergling";"Larva";287
"Unit";"Hydralisk";"Larva";288
"Unit";"Zergling";"Larva";290
"Unit";"Zergling";"Larva";291
"Unit";"Zergling";"Larva";292
"Unit";"Zergling";"Larva";293
"Unit";"Zergling";"Larva";294
"Unit";"Zergling";"Larva";295
"Unit";"Zergling";"Larva";296
"Unit";"Zergling";"Larva";297
"Unit";"Zergling";"Larva";298
"Unit";"Zergling";"Larva";299
"Unit";"Zergling";"Larva";300
"Unit";"Zergling";"Larva";301
"Unit";"Zergling";"Larva";302
"Unit";"Zergling";"Larva";303
"Unit";"Zergling";"Larva";304
"Unit";"Zergling";"Larva";305
"Unit";"Zergling";"Larva";306
"Unit";"Zergling";"Larva";307
"Unit";"Zergling";"Larva";308
"Unit";"Zergling";"Larva";309
"Unit";"Zergling";"Larva";310
"Unit";"Zergling";"Larva";311
"Unit";"Zergling";"Larva";312
"Unit";"Zergling";"Larva";313
"Building";"CreepTumorQueen";NA;314
"Building";"CreepTumorQueen";NA;314
"Building";"CreepTumorQueen";NA;314
"Unit";"Zergling";"Larva";314
"Unit";"Zergling";"Larva";315
"Unit";"Zergling";"Larva";316
"Unit";"Zergling";"Larva";317
"Unit";"Baneling";"Zergling";318
"Unit";"Baneling";"Zergling";318
"Unit";"Baneling";"Zergling";318
"Unit";"Baneling";"Zergling";318
"Unit";"Zergling";"Larva";318
"Unit";"Zergling";"Larva";319
"Unit";"Zergling";"Larva";320
"Unit";"Zergling";"Larva";321
"Unit";"Zergling";"Larva";322
"Unit";"Zergling";"Larva";323
"Unit";"Zergling";"Larva";324
"Unit";"Zergling";"Larva";325
"Unit";"Zergling";"Larva";326
"Unit";"Zergling";"Larva";327
"Unit";"Zergling";"Larva";328
"Unit";"Zergling";"Larva";329
"Unit";"Zergling";"Larva";330
"Unit";"Zergling";"Larva";331
"Unit";"Zergling";"Larva";332
"Unit";"Zergling";"Larva";333
"Unit";"Zergling";"Larva";334
"Unit";"Zergling";"Larva";335
"Unit";"Zergling";"Larva";336
"Unit";"Zergling";"Larva";337
"Unit";"Zergling";"Larva";338
"Unit";"Zergling";"Larva";339
"Unit";"Zergling";"Larva";340
"Unit";"Zergling";"Larva";341
"Unit";"Zergling";"Larva";342
"Unit";"Zergling";"Larva";343
"Unit";"Zergling";"Larva";344
"Unit";"Zergling";"Larva";345
"Unit";"Baneling";"Zergling";346
"Unit";"Baneling";"Zergling";346
"Unit";"Baneling";"Zergling";346
"Unit";"Baneling";"Zergling";346
"Unit";"Baneling";"Zergling";346
"Unit";"Baneling";"Zergling";346
"Unit";"Baneling";"Zergling";346
"Unit";"Baneling";"Zergling";346
"Unit";"Baneling";"Zergling";346
"Unit";"Baneling";"Zergling";346
"Unit";"Baneling";"Zergling";346
"Unit";"Baneling";"Zergling";346
"Unit";"Baneling";"Zergling";346
"Unit";"Baneling";"Zergling";346
"Unit";"Baneling";"Zergling";346
"Building";"CreepTumor";NA;346
"Building";"CreepTumor";NA;346
"Building";"CreepTumor";NA;346
"Building";"CreepTumor";NA;346
"Unit";"Hydralisk";"Larva";346
"Unit";"Hydralisk";"Larva";348
"Unit";"Hydralisk";"Larva";350
"Unit";"Hydralisk";"Larva";352
"Building";"CreepTumor";NA;354
"Unit";"Zergling";"Larva";354
"Unit";"Zergling";"Larva";355
"Unit";"Zergling";"Larva";356
"Unit";"Zergling";"Larva";357
"Unit";"Zergling";"Larva";358
"Unit";"Zergling";"Larva";359
"Unit";"Zergling";"Larva";360
"Unit";"Zergling";"Larva";361
"Unit";"Zergling";"Larva";362
"Unit";"Zergling";"Larva";363
"Unit";"Zergling";"Larva";364
"Unit";"Zergling";"Larva";365
"Unit";"Zergling";"Larva";366
"Unit";"Zergling";"Larva";367
"Unit";"Hydralisk";"Larva";368
"Unit";"Hydralisk";"Larva";370
"Unit";"Hydralisk";"Larva";372
"Unit";"Zergling";"Larva";374
"Unit";"Zergling";"Larva";375
"Unit";"Baneling";"Zergling";376
"Unit";"Baneling";"Zergling";376
"Unit";"Zergling";"Larva";376
"Unit";"Zergling";"Larva";377
"Unit";"Zergling";"Larva";378
"Unit";"Zergling";"Larva";379
"Unit";"Zergling";"Larva";380
"Unit";"Zergling";"Larva";381
"Unit";"Zergling";"Larva";382
"Unit";"Zergling";"Larva";383
"Unit";"Zergling";"Larva";384
"Unit";"Zergling";"Larva";385
"Unit";"Zergling";"Larva";386
"Unit";"Zergling";"Larva";387
"Upgrade";"SprayZerg";NA;388
"Upgrade";"SprayZerg";NA;388
"Upgrade";"SprayZerg";NA;388
"Upgrade";"zerglingmovementspeed";NA;388
"Upgrade";"overlordspeed";NA;388
"Upgrade";"SprayZerg";NA;388
"Upgrade";"SprayZerg";NA;388
"Upgrade";"ZergMeleeWeaponsLevel1";NA;388
"Upgrade";"SprayZerg";NA;388
"Upgrade";"SprayZerg";NA;388
"Upgrade";"CentrificalHooks";NA;388
"Upgrade";"SprayZerg";NA;388
"Upgrade";"ZergMeleeWeaponsLevel2";NA;388
"Upgrade";"EvolveMuscularAugments";NA;388
"Upgrade";"SprayZerg";NA;388
