"type";"unit_name";"on_building";"total_supply_lag";"supply"
"Unit";"Overlord";"Larva";13;0
"Building";"Hatchery";NA;17;0
"Building";"Extractor";NA;19;0
"Building";"SpawningPool";NA;19;0
"Unit";"Overlord";"Larva";22;0
"Unit";"Queen";"Hatchery";23;2
"Unit";"Zergling";"Larva";25;1
"Unit";"Zergling";"Larva";26;1
"Unit";"Queen";"Hatchery";27;2
"Building";"Hatchery";NA;34;0
"Unit";"Queen";"Hatchery";35;2
"Unit";"Overlord";"Larva";37;0
"Unit";"Overlord";"Larva";41;0
"Building";"CreepTumorQueen";NA;46;0
"Unit";"Queen";"Hatchery";48;2
"Building";"SporeCrawler";NA;51;0
"Building";"SporeCrawler";NA;51;0
"Unit";"Overlord";"Larva";54;0
"Unit";"Zergling";"Larva";58;1
"Unit";"Zergling";"Larva";59;1
"Unit";"Zergling";"Larva";60;1
"Unit";"Zergling";"Larva";61;1
"Building";"SporeCrawler";NA;63;0
"Unit";"Zergling";"Larva";63;1
"Unit";"Zergling";"Larva";64;1
"Unit";"Zergling";"Larva";65;1
"Unit";"Zergling";"Larva";66;1
"Unit";"Zergling";"Larva";67;1
"Unit";"Zergling";"Larva";68;1
"Building";"CreepTumorQueen";NA;69;0
"Building";"CreepTumorQueen";NA;69;0
"Unit";"Queen";"Hatchery";69;2
"Unit";"Overlord";"Larva";71;0
"Unit";"Overlord";"Larva";74;0
"Building";"CreepTumor";NA;78;0
"Building";"CreepTumor";NA;78;0
"Building";"BanelingNest";NA;78;0
"Building";"CreepTumor";NA;79;0
"Unit";"Overlord";"Larva";79;0
"Unit";"Overlord";"Larva";83;0
"Unit";"Overlord";"Larva";84;0
"Unit";"Zergling";"Larva";84;1
"Unit";"Zergling";"Larva";85;1
"Unit";"Zergling";"Larva";86;1
"Unit";"Zergling";"Larva";87;1
"Unit";"Zergling";"Larva";88;1
"Unit";"Zergling";"Larva";89;1
"Unit";"Zergling";"Larva";90;1
"Unit";"Zergling";"Larva";91;1
"Unit";"Zergling";"Larva";92;1
"Unit";"Zergling";"Larva";93;1
"Building";"Extractor";NA;96;0
"Building";"CreepTumor";NA;97;0
"Building";"CreepTumorQueen";NA;99;0
"Building";"CreepTumorQueen";NA;101;0
"Building";"CreepTumorQueen";NA;101;0
"Building";"CreepTumorQueen";NA;101;0
"Unit";"Zergling";"Larva";102;1
"Unit";"Zergling";"Larva";103;1
"Unit";"Zergling";"Larva";104;1
"Unit";"Zergling";"Larva";105;1
"Unit";"Zergling";"Larva";106;1
"Unit";"Zergling";"Larva";107;1
"Unit";"Zergling";"Larva";108;1
"Unit";"Zergling";"Larva";109;1
"Building";"CreepTumorQueen";NA;115;0
"Building";"CreepTumorQueen";NA;115;0
"Unit";"Zergling";"Larva";115;1
"Unit";"Zergling";"Larva";116;1
"Unit";"Zergling";"Larva";117;1
"Unit";"Zergling";"Larva";118;1
"Building";"CreepTumor";NA;119;0
"Building";"CreepTumor";NA;119;0
"Building";"CreepTumor";NA;119;0
"Building";"CreepTumor";NA;119;0
"Building";"CreepTumor";NA;119;0
"Building";"Hatchery";NA;123;0
"Building";"Extractor";NA;123;0
"Building";"Extractor";NA;123;0
"Unit";"Baneling";"Zergling";123;0
"Unit";"Baneling";"Zergling";123;0
"Unit";"Baneling";"Zergling";123;0
"Unit";"Baneling";"Zergling";123;0
"Unit";"Baneling";"Zergling";123;0
"Unit";"Baneling";"Zergling";123;0
"Unit";"Baneling";"Zergling";123;0
"Unit";"Zergling";"Larva";123;1
"Unit";"Zergling";"Larva";124;1
"Unit";"Zergling";"Larva";125;1
"Unit";"Zergling";"Larva";126;1
"Unit";"Zergling";"Larva";127;1
"Unit";"Zergling";"Larva";128;1
"Building";"CreepTumor";NA;129;0
"Unit";"Overlord";"Larva";129;0
"Building";"HydraliskDen";NA;129;0
"Unit";"Overlord";"Larva";129;0
"Building";"Extractor";NA;129;0
"Unit";"Zergling";"Larva";129;1
"Unit";"Zergling";"Larva";130;1
"Unit";"Zergling";"Larva";131;1
"Unit";"Zergling";"Larva";132;1
"Building";"CreepTumor";NA;140;0
"Building";"CreepTumor";NA;140;0
"Building";"CreepTumor";NA;140;0
"Building";"CreepTumorQueen";NA;141;0
"Building";"CreepTumorQueen";NA;143;0
"Building";"Extractor";NA;147;0
"Building";"CreepTumor";NA;147;0
"Unit";"Overlord";"Larva";148;0
"Building";"Hatchery";NA;151;0
"Unit";"Hydralisk";"Larva";151;2
"Unit";"Hydralisk";"Larva";153;2
"Unit";"Hydralisk";"Larva";155;2
"Unit";"Hydralisk";"Larva";157;2
"Building";"CreepTumor";NA;159;0
"Building";"CreepTumor";NA;159;0
"Building";"CreepTumor";NA;159;0
"Building";"CreepTumor";NA;159;0
"Building";"CreepTumor";NA;159;0
"Building";"EvolutionChamber";NA;159;0
"Building";"SporeCrawler";NA;167;0
"Unit";"Hydralisk";"Larva";167;2
"Unit";"Hydralisk";"Larva";169;2
"Unit";"Hydralisk";"Larva";171;2
"Unit";"Hydralisk";"Larva";173;2
"Unit";"Overlord";"Larva";175;0
"Unit";"Overlord";"Larva";175;0
"Unit";"Overlord";"Larva";175;0
"Building";"CreepTumor";NA;175;0
"Unit";"Zergling";"Larva";175;1
"Unit";"Zergling";"Larva";176;1
"Unit";"Zergling";"Larva";177;1
"Unit";"Zergling";"Larva";178;1
"Unit";"Zergling";"Larva";179;1
"Unit";"Zergling";"Larva";180;1
"Unit";"Zergling";"Larva";181;1
"Unit";"Zergling";"Larva";182;1
"Unit";"Zergling";"Larva";183;1
"Unit";"Zergling";"Larva";184;1
"Unit";"Hydralisk";"Larva";185;2
"Unit";"Hydralisk";"Larva";187;2
"Unit";"Zergling";"Larva";189;1
"Unit";"Zergling";"Larva";190;1
"Unit";"Zergling";"Larva";191;1
"Unit";"Zergling";"Larva";192;1
"Unit";"Zergling";"Larva";193;1
"Unit";"Zergling";"Larva";194;1
"Unit";"Zergling";"Larva";195;1
"Unit";"Zergling";"Larva";196;1
"Unit";"Zergling";"Larva";197;1
"Unit";"Zergling";"Larva";198;1
"Building";"CreepTumor";NA;199;0
"Building";"CreepTumor";NA;199;0
"Building";"CreepTumor";NA;199;0
"Building";"CreepTumor";NA;199;0
"Building";"CreepTumor";NA;199;0
"Building";"CreepTumorQueen";NA;199;0
"Building";"CreepTumorQueen";NA;199;0
"Unit";"Overlord";"Larva";199;0
"Unit";"Overlord";"Larva";199;0
"Unit";"Hydralisk";"Larva";199;2
"Unit";"Hydralisk";"Larva";201;2
"Unit";"Hydralisk";"Larva";203;2
"Unit";"Zergling";"Larva";205;1
"Unit";"Zergling";"Larva";206;1
"Unit";"Zergling";"Larva";207;1
"Unit";"Zergling";"Larva";208;1
"Unit";"Zergling";"Larva";209;1
"Unit";"Zergling";"Larva";210;1
"Unit";"Hydralisk";"Larva";211;2
"Unit";"Hydralisk";"Larva";213;2
"Unit";"Hydralisk";"Larva";215;2
"Unit";"Hydralisk";"Larva";217;2
"Unit";"Hydralisk";"Larva";219;2
"Unit";"Zergling";"Larva";221;1
"Unit";"Zergling";"Larva";222;1
"Unit";"Zergling";"Larva";223;1
"Unit";"Zergling";"Larva";224;1
"Building";"CreepTumor";NA;225;0
"Building";"CreepTumor";NA;225;0
"Building";"CreepTumor";NA;225;0
"Building";"CreepTumor";NA;225;0
"Unit";"Overlord";"Larva";225;0
"Unit";"Hydralisk";"Larva";225;2
"Unit";"Hydralisk";"Larva";227;2
"Building";"CreepTumorQueen";NA;229;0
"Unit";"Hydralisk";"Larva";229;2
"Unit";"Zergling";"Larva";231;1
"Unit";"Zergling";"Larva";232;1
"Unit";"Zergling";"Larva";233;1
"Unit";"Zergling";"Larva";234;1
"Unit";"Zergling";"Larva";235;1
"Unit";"Zergling";"Larva";236;1
"Unit";"Zergling";"Larva";237;1
"Unit";"Zergling";"Larva";238;1
"Unit";"Zergling";"Larva";239;1
"Unit";"Zergling";"Larva";240;1
"Unit";"Zergling";"Larva";241;1
"Unit";"Zergling";"Larva";242;1
"Unit";"Hydralisk";"Larva";244;2
"Unit";"Hydralisk";"Larva";246;2
"Unit";"Hydralisk";"Larva";248;2
"Unit";"Overlord";"Larva";250;0
"Unit";"Overlord";"Larva";250;0
"Unit";"Hydralisk";"Larva";250;2
"Unit";"Hydralisk";"Larva";252;2
"Unit";"Hydralisk";"Larva";254;2
"Unit";"Zergling";"Larva";256;1
"Unit";"Zergling";"Larva";257;1
"Unit";"Zergling";"Larva";258;1
"Unit";"Zergling";"Larva";259;1
"Building";"CreepTumor";NA;260;0
"Building";"CreepTumor";NA;260;0
"Building";"CreepTumor";NA;260;0
"Building";"CreepTumor";NA;260;0
"Building";"CreepTumor";NA;260;0
"Building";"CreepTumorQueen";NA;260;0
"Building";"CreepTumorQueen";NA;260;0
"Unit";"Overlord";"Larva";260;0
"Unit";"Overlord";"Larva";260;0
"Unit";"Overlord";"Larva";260;0
"Unit";"Hydralisk";"Larva";260;2
"Unit";"Hydralisk";"Larva";262;2
"Unit";"Hydralisk";"Larva";264;2
"Unit";"Hydralisk";"Larva";266;2
"Unit";"Hydralisk";"Larva";268;2
"Unit";"Hydralisk";"Larva";270;2
"Unit";"Hydralisk";"Larva";272;2
"Unit";"Hydralisk";"Larva";274;2
"Unit";"Zergling";"Larva";276;1
"Unit";"Zergling";"Larva";277;1
"Unit";"Zergling";"Larva";278;1
"Unit";"Zergling";"Larva";279;1
"Unit";"Zergling";"Larva";280;1
"Unit";"Zergling";"Larva";281;1
"Unit";"Baneling";"Zergling";285;0
"Unit";"Baneling";"Zergling";285;0
"Unit";"Baneling";"Zergling";285;0
"Unit";"Baneling";"Zergling";285;0
"Unit";"Baneling";"Zergling";285;0
"Unit";"Baneling";"Zergling";285;0
"Unit";"Baneling";"Zergling";285;0
"Unit";"Baneling";"Zergling";285;0
"Unit";"Baneling";"Zergling";285;0
"Unit";"Baneling";"Zergling";285;0
"Unit";"Baneling";"Zergling";285;0
"Unit";"Baneling";"Zergling";285;0
"Unit";"Baneling";"Zergling";285;0
"Unit";"Baneling";"Zergling";285;0
"Unit";"Baneling";"Zergling";285;0
"Unit";"Baneling";"Zergling";285;0
"Unit";"Baneling";"Zergling";285;0
"Unit";"Baneling";"Zergling";285;0
"Unit";"Baneling";"Zergling";285;0
"Unit";"Baneling";"Zergling";285;0
"Unit";"Baneling";"Zergling";285;0
"Unit";"Baneling";"Zergling";285;0
"Building";"Hatchery";NA;287;0
"Building";"CreepTumor";NA;288;0
"Building";"CreepTumorQueen";NA;288;0
"Unit";"Zergling";"Larva";288;1
"Unit";"Zergling";"Larva";289;1
"Building";"CreepTumorQueen";NA;290;0
"Unit";"Zergling";"Larva";290;1
"Unit";"Zergling";"Larva";291;1
"Unit";"Zergling";"Larva";292;1
"Unit";"Zergling";"Larva";293;1
"Unit";"Zergling";"Larva";294;1
"Unit";"Zergling";"Larva";295;1
"Unit";"Zergling";"Larva";296;1
"Unit";"Zergling";"Larva";297;1
"Unit";"Zergling";"Larva";298;1
"Unit";"Zergling";"Larva";299;1
"Unit";"Zergling";"Larva";300;1
"Unit";"Zergling";"Larva";301;1
"Unit";"Zergling";"Larva";302;1
"Unit";"Zergling";"Larva";303;1
"Unit";"Zergling";"Larva";304;1
"Unit";"Zergling";"Larva";305;1
"Unit";"Zergling";"Larva";306;1
"Unit";"Zergling";"Larva";307;1
"Unit";"Zergling";"Larva";308;1
"Unit";"Zergling";"Larva";309;1
"Unit";"Zergling";"Larva";310;1
"Unit";"Zergling";"Larva";311;1
"Unit";"Zergling";"Larva";312;1
"Unit";"Zergling";"Larva";313;1
"Unit";"Zergling";"Larva";314;1
"Unit";"Zergling";"Larva";315;1
"Unit";"Zergling";"Larva";316;1
"Unit";"Zergling";"Larva";317;1
"Unit";"Zergling";"Larva";318;1
"Unit";"Zergling";"Larva";319;1
"Unit";"Zergling";"Larva";320;1
"Unit";"Zergling";"Larva";321;1
"Unit";"Queen";"Hatchery";322;2
"Unit";"Baneling";"Zergling";324;0
"Unit";"Baneling";"Zergling";324;0
"Unit";"Baneling";"Zergling";324;0
"Unit";"Baneling";"Zergling";324;0
"Unit";"Baneling";"Zergling";324;0
"Unit";"Baneling";"Zergling";324;0
"Unit";"Baneling";"Zergling";324;0
"Unit";"Baneling";"Zergling";324;0
"Unit";"Zergling";"Larva";324;1
"Unit";"Zergling";"Larva";325;1
"Unit";"Zergling";"Larva";326;1
"Unit";"Zergling";"Larva";327;1
"Unit";"Zergling";"Larva";328;1
"Unit";"Zergling";"Larva";329;1
"Unit";"Zergling";"Larva";330;1
"Unit";"Zergling";"Larva";331;1
"Unit";"Zergling";"Larva";332;1
"Unit";"Zergling";"Larva";333;1
"Unit";"Zergling";"Larva";334;1
"Unit";"Zergling";"Larva";335;1
"Unit";"Zergling";"Larva";336;1
"Unit";"Zergling";"Larva";337;1
"Unit";"Zergling";"Larva";338;1
"Unit";"Zergling";"Larva";339;1
"Unit";"Zergling";"Larva";340;1
"Unit";"Zergling";"Larva";341;1
"Unit";"Zergling";"Larva";342;1
"Unit";"Zergling";"Larva";343;1
"Unit";"Zergling";"Larva";344;1
"Unit";"Zergling";"Larva";345;1
"Unit";"Zergling";"Larva";346;1
"Unit";"Zergling";"Larva";347;1
"Unit";"Zergling";"Larva";348;1
"Unit";"Zergling";"Larva";349;1
"Unit";"Zergling";"Larva";350;1
"Unit";"Zergling";"Larva";351;1
"Unit";"Zergling";"Larva";352;1
"Unit";"Zergling";"Larva";353;1
"Unit";"Zergling";"Larva";354;1
"Unit";"Zergling";"Larva";355;1
"Unit";"Zergling";"Larva";356;1
"Unit";"Zergling";"Larva";357;1
"Unit";"Zergling";"Larva";358;1
"Unit";"Zergling";"Larva";359;1
"Unit";"Zergling";"Larva";360;1
"Unit";"Zergling";"Larva";361;1
"Unit";"Zergling";"Larva";362;1
"Unit";"Zergling";"Larva";363;1
"Unit";"Zergling";"Larva";364;1
"Unit";"Zergling";"Larva";365;1
"Unit";"Zergling";"Larva";366;1
"Unit";"Zergling";"Larva";367;1
"Unit";"Zergling";"Larva";368;1
"Unit";"Zergling";"Larva";369;1
"Unit";"Zergling";"Larva";370;1
"Unit";"Zergling";"Larva";371;1
"Unit";"Zergling";"Larva";372;1
"Unit";"Zergling";"Larva";373;1
"Unit";"Zergling";"Larva";374;1
"Unit";"Zergling";"Larva";375;1
"Unit";"Zergling";"Larva";376;1
"Unit";"Zergling";"Larva";377;1
"Unit";"Zergling";"Larva";378;1
"Unit";"Zergling";"Larva";379;1
"Unit";"Zergling";"Larva";380;1
"Unit";"Zergling";"Larva";381;1
"Unit";"Zergling";"Larva";382;1
"Unit";"Zergling";"Larva";383;1
"Unit";"Zergling";"Larva";384;1
"Unit";"Zergling";"Larva";385;1
"Unit";"Zergling";"Larva";386;1
"Unit";"Zergling";"Larva";387;1
"Unit";"Zergling";"Larva";388;1
"Unit";"Zergling";"Larva";389;1
"Unit";"Zergling";"Larva";390;1
"Unit";"Zergling";"Larva";391;1
"Unit";"Hydralisk";"Larva";392;2
"Unit";"Hydralisk";"Larva";394;2
"Unit";"Hydralisk";"Larva";396;2
"Unit";"Hydralisk";"Larva";398;2
"Unit";"Hydralisk";"Larva";401;2
"Unit";"Hydralisk";"Larva";403;2
"Unit";"Hydralisk";"Larva";405;2
"Unit";"Hydralisk";"Larva";407;2
"Unit";"Hydralisk";"Larva";409;2
"Unit";"Hydralisk";"Larva";411;2
"Building";"CreepTumor";NA;413;0
"Unit";"Hydralisk";"Larva";413;2
"Unit";"Hydralisk";"Larva";415;2
"Unit";"Zergling";"Larva";417;1
"Unit";"Zergling";"Larva";418;1
"Unit";"Zergling";"Larva";419;1
"Unit";"Zergling";"Larva";420;1
"Unit";"Zergling";"Larva";421;1
"Unit";"Zergling";"Larva";422;1
"Unit";"Zergling";"Larva";423;1
"Unit";"Zergling";"Larva";424;1
"Unit";"Zergling";"Larva";425;1
"Unit";"Zergling";"Larva";426;1
"Unit";"Zergling";"Larva";427;1
"Unit";"Zergling";"Larva";428;1
"Unit";"Zergling";"Larva";429;1
"Unit";"Zergling";"Larva";430;1
"Unit";"Zergling";"Larva";431;1
"Unit";"Zergling";"Larva";432;1
"Unit";"Zergling";"Larva";433;1
"Unit";"Zergling";"Larva";434;1
"Unit";"Zergling";"Larva";435;1
"Unit";"Zergling";"Larva";436;1
"Building";"InfestationPit";NA;437;0
"Unit";"Zergling";"Larva";437;1
"Unit";"Zergling";"Larva";438;1
"Unit";"Zergling";"Larva";439;1
"Unit";"Zergling";"Larva";440;1
"Unit";"Zergling";"Larva";441;1
"Unit";"Zergling";"Larva";442;1
"Unit";"Zergling";"Larva";443;1
"Unit";"Zergling";"Larva";444;1
"Unit";"Zergling";"Larva";445;1
"Unit";"Zergling";"Larva";446;1
"Unit";"Zergling";"Larva";447;1
"Unit";"Zergling";"Larva";448;1
"Unit";"Zergling";"Larva";449;1
"Unit";"Zergling";"Larva";450;1
"Unit";"Zergling";"Larva";451;1
"Unit";"Zergling";"Larva";452;1
"Unit";"Zergling";"Larva";453;1
"Unit";"Zergling";"Larva";454;1
"Unit";"Zergling";"Larva";455;1
"Unit";"Zergling";"Larva";456;1
"Unit";"Zergling";"Larva";457;1
"Unit";"Zergling";"Larva";458;1
"Unit";"Zergling";"Larva";459;1
"Unit";"Zergling";"Larva";460;1
"Building";"CreepTumor";NA;461;0
"Building";"CreepTumor";NA;461;0
"Building";"CreepTumor";NA;461;0
"Building";"CreepTumor";NA;461;0
"Building";"CreepTumor";NA;461;0
"Building";"CreepTumor";NA;461;0
"Unit";"Baneling";"Zergling";461;0
"Unit";"Baneling";"Zergling";461;0
"Unit";"Baneling";"Zergling";461;0
"Unit";"Baneling";"Zergling";461;0
"Unit";"Baneling";"Zergling";461;0
"Unit";"Baneling";"Zergling";461;0
"Unit";"Baneling";"Zergling";461;0
"Unit";"Baneling";"Zergling";461;0
"Unit";"Baneling";"Zergling";461;0
"Unit";"Baneling";"Zergling";461;0
"Unit";"Baneling";"Zergling";461;0
"Unit";"Baneling";"Zergling";461;0
"Unit";"Baneling";"Zergling";461;0
"Unit";"Baneling";"Zergling";461;0
"Unit";"Baneling";"Zergling";461;0
"Unit";"Baneling";"Zergling";461;0
"Unit";"Baneling";"Zergling";461;0
"Unit";"Baneling";"Zergling";461;0
"Unit";"Baneling";"Zergling";461;0
"Unit";"Baneling";"Zergling";461;0
"Unit";"Baneling";"Zergling";461;0
"Unit";"Baneling";"Zergling";461;0
"Unit";"Baneling";"Zergling";461;0
"Unit";"Baneling";"Zergling";461;0
"Unit";"Baneling";"Zergling";461;0
"Unit";"Zergling";"Larva";461;1
"Unit";"Zergling";"Larva";462;1
"Unit";"Zergling";"Larva";463;1
"Unit";"Zergling";"Larva";464;1
"Unit";"Zergling";"Larva";465;1
"Unit";"Zergling";"Larva";466;1
"Unit";"Zergling";"Larva";467;1
"Unit";"Zergling";"Larva";468;1
"Unit";"Zergling";"Larva";469;1
"Unit";"Zergling";"Larva";470;1
"Unit";"Baneling";"Zergling";471;0
"Unit";"Baneling";"Zergling";471;0
"Unit";"Baneling";"Zergling";471;0
"Unit";"Baneling";"Zergling";471;0
"Unit";"Baneling";"Zergling";471;0
"Unit";"Baneling";"Zergling";471;0
"Unit";"Baneling";"Zergling";471;0
"Unit";"Baneling";"Zergling";471;0
"Unit";"Baneling";"Zergling";471;0
"Unit";"Baneling";"Zergling";471;0
"Unit";"Baneling";"Zergling";471;0
"Unit";"Baneling";"Zergling";471;0
"Unit";"Baneling";"Zergling";471;0
"Unit";"Baneling";"Zergling";471;0
"Unit";"Baneling";"Zergling";471;0
"Unit";"Baneling";"Zergling";471;0
"Unit";"Zergling";"Larva";471;1
"Unit";"Zergling";"Larva";472;1
"Unit";"Zergling";"Larva";473;1
"Unit";"Zergling";"Larva";474;1
"Unit";"Zergling";"Larva";475;1
"Unit";"Zergling";"Larva";476;1
"Unit";"Zergling";"Larva";477;1
"Unit";"Zergling";"Larva";478;1
"Unit";"Zergling";"Larva";479;1
"Unit";"Zergling";"Larva";480;1
"Unit";"Zergling";"Larva";481;1
"Unit";"Zergling";"Larva";482;1
"Unit";"Zergling";"Larva";483;1
"Unit";"Zergling";"Larva";484;1
"Unit";"Zergling";"Larva";485;1
"Unit";"Zergling";"Larva";486;1
"Unit";"Zergling";"Larva";487;1
"Unit";"Zergling";"Larva";488;1
"Unit";"Zergling";"Larva";489;1
"Unit";"Zergling";"Larva";490;1
"Unit";"Zergling";"Larva";491;1
"Unit";"Zergling";"Larva";492;1
"Unit";"Zergling";"Larva";493;1
"Unit";"Zergling";"Larva";494;1
"Unit";"Zergling";"Larva";495;1
"Unit";"Zergling";"Larva";496;1
"Unit";"Zergling";"Larva";497;1
"Unit";"Zergling";"Larva";498;1
"Unit";"Zergling";"Larva";499;1
"Unit";"Zergling";"Larva";500;1
"Unit";"Zergling";"Larva";501;1
"Unit";"Zergling";"Larva";502;1
"Unit";"Zergling";"Larva";503;1
"Unit";"Zergling";"Larva";504;1
"Unit";"Zergling";"Larva";505;1
"Unit";"Zergling";"Larva";506;1
"Unit";"Zergling";"Larva";507;1
"Unit";"Zergling";"Larva";508;1
"Unit";"Zergling";"Larva";509;1
"Unit";"Zergling";"Larva";510;1
"Unit";"Zergling";"Larva";519;1
"Unit";"Zergling";"Larva";520;1
"Unit";"Zergling";"Larva";521;1
"Unit";"Zergling";"Larva";522;1
"Unit";"Zergling";"Larva";523;1
"Unit";"Zergling";"Larva";524;1
"Unit";"Zergling";"Larva";525;1
"Unit";"Zergling";"Larva";526;1
"Unit";"Zergling";"Larva";527;1
"Unit";"Zergling";"Larva";528;1
"Unit";"Zergling";"Larva";529;1
"Unit";"Zergling";"Larva";530;1
"Unit";"Zergling";"Larva";531;1
"Unit";"Zergling";"Larva";532;1
"Unit";"Zergling";"Larva";533;1
"Unit";"Zergling";"Larva";534;1
"Unit";"Baneling";"Zergling";535;0
"Unit";"Baneling";"Zergling";535;0
"Unit";"Baneling";"Zergling";535;0
"Unit";"Baneling";"Zergling";535;0
"Unit";"Baneling";"Zergling";535;0
"Unit";"Baneling";"Zergling";535;0
"Unit";"Baneling";"Zergling";535;0
"Unit";"Baneling";"Zergling";535;0
"Unit";"Baneling";"Zergling";535;0
"Unit";"Baneling";"Zergling";535;0
"Unit";"Baneling";"Zergling";535;0
"Unit";"Baneling";"Zergling";535;0
"Unit";"Baneling";"Zergling";535;0
"Unit";"Zergling";"Larva";535;1
"Unit";"Zergling";"Larva";536;1
"Unit";"Zergling";"Larva";537;1
"Unit";"Zergling";"Larva";538;1
"Unit";"Zergling";"Larva";539;1
"Unit";"Zergling";"Larva";540;1
"Unit";"Zergling";"Larva";541;1
"Unit";"Zergling";"Larva";542;1
"Unit";"Zergling";"Larva";543;1
"Unit";"Zergling";"Larva";544;1
"Unit";"Zergling";"Larva";545;1
"Unit";"Zergling";"Larva";546;1
"Unit";"Zergling";"Larva";547;1
"Unit";"Zergling";"Larva";548;1
"Unit";"Zergling";"Larva";549;1
"Unit";"Zergling";"Larva";550;1
"Unit";"Zergling";"Larva";551;1
"Unit";"Zergling";"Larva";552;1
"Unit";"Zergling";"Larva";553;1
"Unit";"Zergling";"Larva";554;1
"Unit";"Zergling";"Larva";555;1
"Unit";"Zergling";"Larva";556;1
"Unit";"Zergling";"Larva";557;1
"Unit";"Zergling";"Larva";558;1
"Unit";"Zergling";"Larva";559;1
"Unit";"Zergling";"Larva";560;1
"Unit";"Zergling";"Larva";561;1
"Unit";"Zergling";"Larva";562;1
"Unit";"Zergling";"Larva";563;1
"Unit";"Zergling";"Larva";564;1
"Unit";"Zergling";"Larva";565;1
"Unit";"Zergling";"Larva";566;1
"Unit";"Zergling";"Larva";567;1
"Unit";"Zergling";"Larva";568;1
"Unit";"Zergling";"Larva";569;1
"Unit";"Zergling";"Larva";570;1
"Unit";"Zergling";"Larva";571;1
"Unit";"Zergling";"Larva";572;1
"Unit";"Zergling";"Larva";573;1
"Unit";"Zergling";"Larva";574;1
"Unit";"Zergling";"Larva";575;1
"Unit";"Zergling";"Larva";576;1
"Unit";"Zergling";"Larva";577;1
"Unit";"Zergling";"Larva";578;1
"Unit";"Zergling";"Larva";579;1
"Unit";"Zergling";"Larva";580;1
"Unit";"Zergling";"Larva";581;1
"Unit";"Zergling";"Larva";582;1
"Unit";"Zergling";"Larva";583;1
"Unit";"Zergling";"Larva";584;1
"Upgrade";"SprayZerg";NA;585;0
"Upgrade";"SprayZerg";NA;585;0
"Upgrade";"SprayZerg";NA;585;0
"Upgrade";"zerglingmovementspeed";NA;585;0
"Upgrade";"SprayZerg";NA;585;0
"Upgrade";"SprayZerg";NA;585;0
"Upgrade";"SprayZerg";NA;585;0
"Upgrade";"SprayZerg";NA;585;0
"Upgrade";"EvolveMuscularAugments";NA;585;0
"Upgrade";"CentrificalHooks";NA;585;0
"Upgrade";"SprayZerg";NA;585;0
"Upgrade";"overlordspeed";NA;585;0
"Upgrade";"SprayZerg";NA;585;0
"Upgrade";"ZergMeleeWeaponsLevel1";NA;585;0
"Upgrade";"SprayZerg";NA;585;0
"Upgrade";"ZergMeleeWeaponsLevel2";NA;585;0
