"type";"unit_name";"on_building";"total_supply_lag"
"Unit";"Overlord";"Larva";13
"Building";"Hatchery";NA;17
"Building";"SpawningPool";NA;18
"Building";"Extractor";NA;18
"Unit";"Overlord";"Larva";22
"Unit";"Queen";"Hatchery";22
"Unit";"Zergling";"Larva";24
"Unit";"Zergling";"Larva";25
"Unit";"Queen";"Hatchery";27
"Building";"Hatchery";NA;34
"Unit";"Overlord";"Larva";37
"Unit";"Queen";"Hatchery";37
"Unit";"Overlord";"Larva";49
"Unit";"Overlord";"Larva";49
"Building";"CreepTumorQueen";NA;49
"Unit";"Queen";"Hatchery";49
"Building";"RoachWarren";NA;51
"Building";"Extractor";NA;62
"Unit";"Overlord";"Larva";67
"Unit";"Overlord";"Larva";67
"Unit";"Overlord";"Larva";67
"Building";"CreepTumor";NA;67
"Building";"CreepTumorQueen";NA;67
"Unit";"Overlord";"Larva";67
"Unit";"Overlord";"Larva";67
"Unit";"Roach";"Larva";67
"Unit";"Roach";"Larva";69
"Unit";"Roach";"Larva";71
"Unit";"Roach";"Larva";73
"Unit";"Roach";"Larva";75
"Unit";"Roach";"Larva";77
"Unit";"Zergling";"Larva";79
"Unit";"Zergling";"Larva";80
"Unit";"Zergling";"Larva";81
"Unit";"Zergling";"Larva";82
"Unit";"Zergling";"Larva";83
"Unit";"Zergling";"Larva";84
"Unit";"Zergling";"Larva";85
"Unit";"Zergling";"Larva";86
"Unit";"Zergling";"Larva";87
"Unit";"Zergling";"Larva";88
"Unit";"Zergling";"Larva";89
"Unit";"Zergling";"Larva";90
"Unit";"Zergling";"Larva";91
"Unit";"Zergling";"Larva";92
"Unit";"Zergling";"Larva";93
"Unit";"Zergling";"Larva";94
"Unit";"Zergling";"Larva";95
"Unit";"Zergling";"Larva";96
"Unit";"Zergling";"Larva";97
"Unit";"Zergling";"Larva";98
"Building";"CreepTumorQueen";NA;99
"Unit";"Zergling";"Larva";99
"Unit";"Zergling";"Larva";100
"Unit";"Zergling";"Larva";101
"Unit";"Zergling";"Larva";102
"Unit";"Overlord";"Larva";103
"Unit";"Overlord";"Larva";103
"Unit";"Overlord";"Larva";103
"Unit";"Overlord";"Larva";103
"Building";"EvolutionChamber";NA;103
"Building";"Extractor";NA;103
"Unit";"Overlord";"Larva";103
"Upgrade";"GlialReconstitution";"RoachWarren";127
"Building";"Extractor";NA;129
"Building";"Extractor";NA;129
"Unit";"Overlord";"Larva";129
"Unit";"Overlord";"Larva";129
"Unit";"Roach";"Larva";129
"Unit";"Roach";"Larva";131
"Unit";"Roach";"Larva";133
"Unit";"Roach";"Larva";135
"Unit";"Roach";"Larva";137
"Unit";"Roach";"Larva";139
"Unit";"Roach";"Larva";141
"Unit";"Roach";"Larva";143
"Building";"CreepTumor";NA;145
"Building";"Hatchery";NA;145
"Upgrade";"Burrow";"Hatchery";145
"Unit";"Roach";"Larva";150
"Unit";"Roach";"Larva";152
"Unit";"Overlord";"Larva";154
"Unit";"Roach";"Larva";156
"Unit";"Roach";"Larva";158
"Unit";"Roach";"Larva";160
"Unit";"Roach";"Larva";162
"Unit";"Roach";"Larva";164
"Unit";"Overlord";"Larva";166
"Unit";"Overlord";"Larva";166
"Building";"CreepTumor";NA;166
"Unit";"Overlord";"Larva";166
"Upgrade";"TunnelingClaws";"RoachWarren";166
"Unit";"Roach";"Larva";172
"Unit";"Roach";"Larva";174
"Unit";"Roach";"Larva";176
"Unit";"Roach";"Larva";178
"Unit";"Roach";"Larva";180
"Unit";"Roach";"Larva";182
"Unit";"Roach";"Larva";184
"Unit";"Roach";"Larva";186
"Unit";"Overlord";"Larva";188
"Building";"CreepTumor";NA;188
"Unit";"Roach";"Larva";188
"Building";"HydraliskDen";NA;190
"Unit";"Zergling";"Larva";190
"Unit";"Zergling";"Larva";191
"Unit";"Zergling";"Larva";192
"Unit";"Zergling";"Larva";193
"Unit";"Zergling";"Larva";194
"Unit";"Zergling";"Larva";195
"Unit";"Zergling";"Larva";196
"Unit";"Zergling";"Larva";197
"Unit";"Zergling";"Larva";198
"Unit";"Zergling";"Larva";199
"Unit";"Zergling";"Larva";200
"Unit";"Zergling";"Larva";201
"Unit";"Zergling";"Larva";202
"Unit";"Zergling";"Larva";203
"Unit";"Zergling";"Larva";204
"Unit";"Zergling";"Larva";205
"Unit";"Zergling";"Larva";206
"Unit";"Zergling";"Larva";207
"Unit";"Zergling";"Larva";208
"Unit";"Zergling";"Larva";209
"Unit";"Zergling";"Larva";210
"Unit";"Zergling";"Larva";211
"Unit";"Zergling";"Larva";212
"Unit";"Zergling";"Larva";213
"Building";"Hatchery";NA;214
"Unit";"Zergling";"Larva";214
"Unit";"Zergling";"Larva";215
"Unit";"Zergling";"Larva";216
"Unit";"Zergling";"Larva";217
"Unit";"Zergling";"Larva";218
"Unit";"Zergling";"Larva";219
"Unit";"Zergling";"Larva";223
"Unit";"Zergling";"Larva";224
"Unit";"Zergling";"Larva";225
"Unit";"Zergling";"Larva";226
"Unit";"Zergling";"Larva";227
"Unit";"Zergling";"Larva";228
"Unit";"Zergling";"Larva";229
"Unit";"Zergling";"Larva";230
"Unit";"Zergling";"Larva";231
"Unit";"Zergling";"Larva";232
"Unit";"Zergling";"Larva";233
"Unit";"Zergling";"Larva";234
"Unit";"Zergling";"Larva";235
"Unit";"Zergling";"Larva";236
"Unit";"Zergling";"Larva";237
"Unit";"Zergling";"Larva";238
"Unit";"Zergling";"Larva";239
"Unit";"Zergling";"Larva";240
"Unit";"Zergling";"Larva";241
"Unit";"Zergling";"Larva";242
"Unit";"Zergling";"Larva";243
"Unit";"Zergling";"Larva";244
"Unit";"Zergling";"Larva";245
"Unit";"Zergling";"Larva";246
"Unit";"Roach";"Larva";247
"Unit";"Overlord";"Larva";249
"Unit";"Zergling";"Larva";249
"Unit";"Zergling";"Larva";250
"Unit";"Zergling";"Larva";251
"Unit";"Zergling";"Larva";252
"Unit";"Zergling";"Larva";253
"Unit";"Zergling";"Larva";254
"Unit";"Zergling";"Larva";255
"Unit";"Zergling";"Larva";256
"Unit";"Zergling";"Larva";257
"Unit";"Zergling";"Larva";258
"Unit";"Zergling";"Larva";259
"Unit";"Zergling";"Larva";260
"Unit";"Zergling";"Larva";261
"Unit";"Zergling";"Larva";262
"Unit";"Zergling";"Larva";263
"Unit";"Zergling";"Larva";264
"Unit";"Zergling";"Larva";265
"Unit";"Zergling";"Larva";266
"Unit";"Zergling";"Larva";267
"Unit";"Zergling";"Larva";268
"Unit";"Zergling";"Larva";269
"Unit";"Zergling";"Larva";270
"Unit";"Zergling";"Larva";271
"Unit";"Zergling";"Larva";272
"Unit";"Zergling";"Larva";273
"Unit";"Zergling";"Larva";274
"Unit";"Zergling";"Larva";275
"Unit";"Zergling";"Larva";276
"Unit";"Zergling";"Larva";277
"Unit";"Zergling";"Larva";278
"Building";"CreepTumor";NA;279
"Unit";"Hydralisk";"Larva";279
"Unit";"Hydralisk";"Larva";281
"Unit";"Hydralisk";"Larva";283
"Unit";"Hydralisk";"Larva";285
"Unit";"Hydralisk";"Larva";287
"Unit";"Hydralisk";"Larva";289
"Unit";"Hydralisk";"Larva";291
"Unit";"Hydralisk";"Larva";293
"Unit";"Hydralisk";"Larva";295
"Unit";"Hydralisk";"Larva";297
"Unit";"Hydralisk";"Larva";299
"Unit";"Hydralisk";"Larva";301
"Unit";"Hydralisk";"Larva";303
"Unit";"Hydralisk";"Larva";305
"Unit";"Hydralisk";"Larva";307
"Unit";"Hydralisk";"Larva";309
"Unit";"Zergling";"Larva";311
"Unit";"Zergling";"Larva";312
"Unit";"Zergling";"Larva";313
"Unit";"Zergling";"Larva";314
"Unit";"Zergling";"Larva";315
"Unit";"Zergling";"Larva";316
"Unit";"Zergling";"Larva";317
"Unit";"Zergling";"Larva";318
"Unit";"Zergling";"Larva";319
"Unit";"Zergling";"Larva";320
"Unit";"Zergling";"Larva";321
"Unit";"Zergling";"Larva";322
"Building";"CreepTumor";NA;323
"Unit";"Zergling";"Larva";323
"Unit";"Zergling";"Larva";324
"Unit";"Zergling";"Larva";325
"Unit";"Zergling";"Larva";326
"Unit";"Hydralisk";"Larva";327
"Unit";"Hydralisk";"Larva";329
"Unit";"Zergling";"Larva";331
"Unit";"Zergling";"Larva";332
"Unit";"Zergling";"Larva";333
"Unit";"Zergling";"Larva";334
"Unit";"Zergling";"Larva";335
"Unit";"Zergling";"Larva";336
"Unit";"Zergling";"Larva";337
"Unit";"Zergling";"Larva";338
"Unit";"Zergling";"Larva";339
"Unit";"Zergling";"Larva";340
"Unit";"Zergling";"Larva";341
"Unit";"Zergling";"Larva";342
"Unit";"Zergling";"Larva";343
"Unit";"Zergling";"Larva";344
"Unit";"Zergling";"Larva";345
"Unit";"Zergling";"Larva";346
"Unit";"Roach";"Larva";347
"Unit";"Roach";"Larva";349
"Unit";"Roach";"Larva";351
"Unit";"Roach";"Larva";353
"Unit";"Roach";"Larva";355
"Unit";"Roach";"Larva";357
"Unit";"Roach";"Larva";359
"Unit";"Roach";"Larva";361
"Unit";"Roach";"Larva";363
"Unit";"Roach";"Larva";365
"Unit";"Roach";"Larva";367
"Unit";"Roach";"Larva";369
"Unit";"Roach";"Larva";371
"Unit";"Roach";"Larva";373
"Unit";"Zergling";"Larva";375
"Unit";"Zergling";"Larva";376
"Unit";"Hydralisk";"Larva";377
"Unit";"Hydralisk";"Larva";379
"Unit";"Hydralisk";"Larva";381
"Unit";"Roach";"Larva";383
"Unit";"Roach";"Larva";385
"Unit";"Roach";"Larva";387
"Unit";"Roach";"Larva";389
"Unit";"Roach";"Larva";391
"Unit";"Zergling";"Larva";393
"Unit";"Zergling";"Larva";394
"Unit";"Zergling";"Larva";395
"Unit";"Zergling";"Larva";396
"Unit";"Roach";"Larva";397
"Unit";"Roach";"Larva";399
"Unit";"Roach";"Larva";401
"Unit";"Zergling";"Larva";403
"Unit";"Zergling";"Larva";404
"Unit";"Zergling";"Larva";405
"Unit";"Zergling";"Larva";406
"Unit";"Zergling";"Larva";407
"Unit";"Zergling";"Larva";408
"Building";"Hatchery";NA;409
"Unit";"Roach";"Larva";409
"Unit";"Hydralisk";"Larva";411
"Unit";"Hydralisk";"Larva";413
"Unit";"Hydralisk";"Larva";415
"Unit";"Zergling";"Larva";417
"Unit";"Zergling";"Larva";418
"Unit";"Zergling";"Larva";419
"Unit";"Zergling";"Larva";420
"Unit";"Zergling";"Larva";421
"Unit";"Zergling";"Larva";422
"Unit";"Zergling";"Larva";423
"Unit";"Zergling";"Larva";424
"Unit";"Zergling";"Larva";425
"Unit";"Zergling";"Larva";426
"Unit";"Zergling";"Larva";427
"Unit";"Zergling";"Larva";428
"Unit";"Zergling";"Larva";429
"Unit";"Zergling";"Larva";430
"Unit";"Hydralisk";"Larva";431
"Unit";"Hydralisk";"Larva";433
"Unit";"Hydralisk";"Larva";435
"Unit";"Zergling";"Larva";437
"Unit";"Zergling";"Larva";438
"Unit";"Zergling";"Larva";439
"Unit";"Zergling";"Larva";440
"Unit";"Zergling";"Larva";441
"Unit";"Zergling";"Larva";442
"Unit";"Zergling";"Larva";443
"Unit";"Zergling";"Larva";444
"Unit";"Zergling";"Larva";445
"Unit";"Zergling";"Larva";446
"Unit";"Zergling";"Larva";447
"Unit";"Zergling";"Larva";448
"Unit";"Zergling";"Larva";449
"Unit";"Zergling";"Larva";450
"Unit";"Zergling";"Larva";451
"Unit";"Zergling";"Larva";452
"Unit";"Zergling";"Larva";453
"Unit";"Zergling";"Larva";454
"Building";"CreepTumorQueen";NA;455
"Unit";"Roach";"Larva";455
"Unit";"Roach";"Larva";457
"Unit";"Roach";"Larva";459
"Unit";"Roach";"Larva";461
"Unit";"Roach";"Larva";463
"Unit";"Roach";"Larva";465
"Unit";"Zergling";"Larva";467
"Unit";"Zergling";"Larva";468
"Unit";"Zergling";"Larva";469
"Unit";"Zergling";"Larva";470
"Unit";"Zergling";"Larva";471
"Unit";"Zergling";"Larva";472
"Building";"CreepTumorQueen";NA;473
"Unit";"Zergling";"Larva";473
"Unit";"Zergling";"Larva";474
"Unit";"Zergling";"Larva";475
"Unit";"Zergling";"Larva";476
"Unit";"Zergling";"Larva";477
"Unit";"Zergling";"Larva";478
"Unit";"Zergling";"Larva";479
"Unit";"Zergling";"Larva";480
"Unit";"Zergling";"Larva";481
"Unit";"Zergling";"Larva";482
"Unit";"Roach";"Larva";483
"Unit";"Zergling";"Larva";485
"Unit";"Zergling";"Larva";486
"Unit";"Zergling";"Larva";487
"Unit";"Zergling";"Larva";488
"Unit";"Zergling";"Larva";489
"Unit";"Zergling";"Larva";490
"Unit";"Zergling";"Larva";491
"Unit";"Zergling";"Larva";492
"Unit";"Zergling";"Larva";493
"Unit";"Zergling";"Larva";494
"Unit";"Zergling";"Larva";495
"Unit";"Zergling";"Larva";496
"Unit";"Zergling";"Larva";497
"Unit";"Zergling";"Larva";498
"Unit";"Zergling";"Larva";499
"Unit";"Zergling";"Larva";500
"Unit";"Zergling";"Larva";501
"Unit";"Zergling";"Larva";502
"Unit";"Zergling";"Larva";503
"Unit";"Zergling";"Larva";504
"Unit";"Zergling";"Larva";505
"Unit";"Zergling";"Larva";506
"Unit";"Zergling";"Larva";507
"Unit";"Zergling";"Larva";508
"Unit";"Zergling";"Larva";509
"Unit";"Zergling";"Larva";510
"Unit";"Zergling";"Larva";511
"Unit";"Zergling";"Larva";512
"Unit";"Zergling";"Larva";513
"Unit";"Zergling";"Larva";514
"Unit";"Zergling";"Larva";515
"Unit";"Zergling";"Larva";516
"Unit";"Zergling";"Larva";517
"Unit";"Zergling";"Larva";518
"Unit";"Zergling";"Larva";519
"Unit";"Zergling";"Larva";520
"Unit";"Zergling";"Larva";521
"Unit";"Zergling";"Larva";522
"Unit";"Zergling";"Larva";523
"Unit";"Zergling";"Larva";524
"Unit";"Zergling";"Larva";525
"Unit";"Zergling";"Larva";526
"Unit";"Zergling";"Larva";527
"Unit";"Zergling";"Larva";528
"Unit";"Zergling";"Larva";529
"Unit";"Zergling";"Larva";530
"Unit";"Roach";"Larva";531
"Unit";"Roach";"Larva";533
"Unit";"Roach";"Larva";535
"Unit";"Roach";"Larva";537
"Unit";"Roach";"Larva";539
"Unit";"Roach";"Larva";541
"Building";"CreepTumorQueen";NA;543
"Unit";"Roach";"Larva";543
"Unit";"Roach";"Larva";545
"Unit";"Roach";"Larva";547
"Unit";"Roach";"Larva";549
"Unit";"Roach";"Larva";551
"Unit";"Roach";"Larva";553
"Unit";"Roach";"Larva";555
"Unit";"Roach";"Larva";557
"Unit";"Roach";"Larva";559
"Building";"CreepTumorQueen";NA;561
"Unit";"Roach";"Larva";561
"Unit";"Roach";"Larva";563
"Unit";"Roach";"Larva";565
"Unit";"Roach";"Larva";567
"Unit";"Roach";"Larva";569
"Unit";"Roach";"Larva";571
"Unit";"Roach";"Larva";573
"Unit";"Roach";"Larva";575
"Unit";"Roach";"Larva";577
"Unit";"Roach";"Larva";579
"Unit";"Roach";"Larva";581
"Unit";"Roach";"Larva";583
"Building";"CreepTumor";NA;585
"Building";"CreepTumor";NA;585
"Unit";"Roach";"Larva";585
"Unit";"Roach";"Larva";587
"Unit";"Roach";"Larva";589
"Unit";"Roach";"Larva";591
"Unit";"Roach";"Larva";593
"Unit";"Roach";"Larva";595
"Unit";"Roach";"Larva";597
"Unit";"Zergling";"Larva";599
"Unit";"Zergling";"Larva";600
"Unit";"Zergling";"Larva";601
"Unit";"Zergling";"Larva";602
"Unit";"Zergling";"Larva";603
"Unit";"Zergling";"Larva";604
"Unit";"Zergling";"Larva";605
"Unit";"Zergling";"Larva";606
"Unit";"Zergling";"Larva";607
"Unit";"Zergling";"Larva";608
"Unit";"Zergling";"Larva";609
"Unit";"Zergling";"Larva";610
"Unit";"Zergling";"Larva";611
"Unit";"Zergling";"Larva";612
"Unit";"Zergling";"Larva";613
"Unit";"Zergling";"Larva";614
"Unit";"Zergling";"Larva";615
"Unit";"Zergling";"Larva";616
"Unit";"Zergling";"Larva";617
"Unit";"Zergling";"Larva";618
"Unit";"Zergling";"Larva";619
"Unit";"Zergling";"Larva";620
"Unit";"Zergling";"Larva";621
"Unit";"Zergling";"Larva";622
"Unit";"Zergling";"Larva";623
"Unit";"Zergling";"Larva";624
"Unit";"Zergling";"Larva";625
"Unit";"Zergling";"Larva";626
"Unit";"Roach";"Larva";627
"Unit";"Roach";"Larva";629
"Unit";"Roach";"Larva";631
"Unit";"Roach";"Larva";633
"Unit";"Roach";"Larva";635
"Unit";"Roach";"Larva";637
"Unit";"Roach";"Larva";639
"Unit";"Overlord";"Larva";641
"Unit";"Zergling";"Larva";641
"Unit";"Zergling";"Larva";642
"Unit";"Zergling";"Larva";643
"Unit";"Zergling";"Larva";644
"Unit";"Roach";"Larva";645
"Unit";"Roach";"Larva";647
"Unit";"Roach";"Larva";649
"Unit";"Roach";"Larva";651
"Unit";"Roach";"Larva";653
"Unit";"Roach";"Larva";655
"Unit";"Roach";"Larva";657
"Unit";"Roach";"Larva";659
"Unit";"Zergling";"Larva";661
"Unit";"Zergling";"Larva";662
"Unit";"Zergling";"Larva";663
"Unit";"Zergling";"Larva";664
"Unit";"Zergling";"Larva";665
"Unit";"Zergling";"Larva";666
"Unit";"Zergling";"Larva";667
"Unit";"Zergling";"Larva";668
"Unit";"Zergling";"Larva";669
"Unit";"Zergling";"Larva";670
"Unit";"Zergling";"Larva";671
"Unit";"Zergling";"Larva";672
"Unit";"Zergling";"Larva";673
"Unit";"Zergling";"Larva";674
"Unit";"Zergling";"Larva";675
"Unit";"Zergling";"Larva";676
"Unit";"Zergling";"Larva";677
"Unit";"Zergling";"Larva";678
"Unit";"Zergling";"Larva";679
"Unit";"Zergling";"Larva";680
"Unit";"Roach";"Larva";681
"Unit";"Roach";"Larva";683
"Unit";"Roach";"Larva";685
"Unit";"Roach";"Larva";687
"Unit";"Zergling";"Larva";689
"Unit";"Zergling";"Larva";690
"Unit";"Zergling";"Larva";691
"Unit";"Zergling";"Larva";692
"Unit";"Zergling";"Larva";693
"Unit";"Zergling";"Larva";694
"Unit";"Zergling";"Larva";695
"Unit";"Zergling";"Larva";696
"Unit";"Zergling";"Larva";697
"Unit";"Zergling";"Larva";698
"Building";"Hatchery";NA;699
"Unit";"Roach";"Larva";699
"Unit";"Roach";"Larva";701
"Unit";"Roach";"Larva";703
"Unit";"Roach";"Larva";705
"Unit";"Queen";"Hatchery";707
"Unit";"Roach";"Larva";709
"Unit";"Roach";"Larva";711
"Unit";"Roach";"Larva";713
"Unit";"Roach";"Larva";715
"Unit";"Roach";"Larva";717
"Unit";"Roach";"Larva";719
"Unit";"Roach";"Larva";721
"Unit";"Roach";"Larva";723
"Building";"RoachWarren";NA;725
"Unit";"Zergling";"Larva";725
"Unit";"Zergling";"Larva";726
"Unit";"Zergling";"Larva";727
"Unit";"Zergling";"Larva";728
"Unit";"Zergling";"Larva";729
"Unit";"Zergling";"Larva";730
"Unit";"Zergling";"Larva";731
"Unit";"Zergling";"Larva";732
"Unit";"Zergling";"Larva";733
"Unit";"Zergling";"Larva";734
"Unit";"Zergling";"Larva";735
"Unit";"Zergling";"Larva";736
"Unit";"Zergling";"Larva";737
"Unit";"Zergling";"Larva";738
"Unit";"Zergling";"Larva";739
"Unit";"Zergling";"Larva";740
"Unit";"Zergling";"Larva";741
"Unit";"Zergling";"Larva";742
"Unit";"Zergling";"Larva";743
"Unit";"Zergling";"Larva";744
"Unit";"Zergling";"Larva";745
"Unit";"Zergling";"Larva";746
"Unit";"Zergling";"Larva";747
"Unit";"Zergling";"Larva";748
"Unit";"Hydralisk";"Larva";749
"Unit";"Hydralisk";"Larva";751
"Unit";"Queen";"Hatchery";753
"Unit";"Zergling";"Larva";755
"Unit";"Zergling";"Larva";756
"Unit";"Zergling";"Larva";757
"Unit";"Zergling";"Larva";758
"Unit";"Zergling";"Larva";759
"Unit";"Zergling";"Larva";760
"Unit";"Zergling";"Larva";761
"Unit";"Zergling";"Larva";762
"Unit";"Zergling";"Larva";763
"Unit";"Zergling";"Larva";764
"Unit";"Zergling";"Larva";765
"Unit";"Zergling";"Larva";766
"Unit";"Zergling";"Larva";767
"Unit";"Zergling";"Larva";768
"Unit";"Zergling";"Larva";769
"Unit";"Zergling";"Larva";770
"Unit";"Zergling";"Larva";771
"Unit";"Zergling";"Larva";772
"Unit";"Zergling";"Larva";773
"Unit";"Zergling";"Larva";774
"Unit";"Zergling";"Larva";775
"Unit";"Zergling";"Larva";776
"Unit";"Zergling";"Larva";777
"Unit";"Zergling";"Larva";778
"Unit";"Zergling";"Larva";779
"Unit";"Zergling";"Larva";780
"Unit";"Zergling";"Larva";781
"Unit";"Zergling";"Larva";782
"Unit";"Zergling";"Larva";783
"Unit";"Zergling";"Larva";784
"Unit";"Zergling";"Larva";785
"Unit";"Zergling";"Larva";786
"Unit";"Zergling";"Larva";787
"Unit";"Zergling";"Larva";788
"Unit";"Zergling";"Larva";789
"Unit";"Zergling";"Larva";790
"Unit";"Zergling";"Larva";791
"Unit";"Zergling";"Larva";792
"Unit";"Zergling";"Larva";793
"Unit";"Zergling";"Larva";794
"Unit";"Roach";"Larva";795
"Unit";"Roach";"Larva";797
"Unit";"Roach";"Larva";799
"Unit";"Roach";"Larva";801
"Unit";"Roach";"Larva";803
"Unit";"Roach";"Larva";805
"Unit";"Roach";"Larva";807
"Unit";"Roach";"Larva";809
"Unit";"Zergling";"Larva";811
"Unit";"Zergling";"Larva";812
"Upgrade";"SprayZerg";NA;813
"Upgrade";"SprayZerg";NA;813
"Upgrade";"SprayZerg";NA;813
"Upgrade";"overlordspeed";NA;813
"Upgrade";"SprayZerg";NA;813
"Upgrade";"zerglingmovementspeed";NA;813
"Upgrade";"SprayZerg";NA;813
"Upgrade";"SprayZerg";NA;813
"Upgrade";"ZergMissileWeaponsLevel1";NA;813
"Upgrade";"SprayZerg";NA;813
"Upgrade";"SprayZerg";NA;813
"Upgrade";"EvolveMuscularAugments";NA;813
"Upgrade";"ZergMissileWeaponsLevel2";NA;813
"Upgrade";"SprayZerg";NA;813
"Upgrade";"SprayZerg";NA;813
"Upgrade";"ZergMeleeWeaponsLevel1";NA;813
"Upgrade";"SprayZerg";NA;813
"Upgrade";"SprayZerg";NA;813
