"type";"unit_name";"on_building";"total_supply_lag";"supply"
"Unit";"Overlord";"Larva";13;0
"Building";"Extractor";NA;18;0
"Building";"SpawningPool";NA;18;0
"Building";"Hatchery";NA;20;0
"Unit";"Queen";"Hatchery";21;2
"Unit";"Zergling";"Larva";23;1
"Unit";"Zergling";"Larva";24;1
"Unit";"Overlord";"Larva";25;0
"Unit";"Queen";"Hatchery";28;2
"Unit";"Zergling";"Larva";33;1
"Unit";"Zergling";"Larva";34;1
"Unit";"Zergling";"Larva";35;1
"Unit";"Zergling";"Larva";36;1
"Unit";"Zergling";"Larva";39;1
"Unit";"Zergling";"Larva";40;1
"Building";"Hatchery";NA;41;0
"Unit";"Overlord";"Larva";41;0
"Building";"CreepTumorQueen";NA;44;0
"Unit";"Queen";"Hatchery";44;2
"Unit";"Overlord";"Larva";52;0
"Unit";"Overlord";"Larva";52;0
"Building";"EvolutionChamber";NA;52;0
"Building";"BanelingNest";NA;52;0
"Building";"CreepTumorQueen";NA;56;0
"Unit";"Queen";"Hatchery";59;2
"Building";"SporeCrawler";NA;61;0
"Unit";"Zergling";"Larva";61;1
"Unit";"Zergling";"Larva";62;1
"Building";"SporeCrawler";NA;63;0
"Unit";"Zergling";"Larva";63;1
"Unit";"Zergling";"Larva";64;1
"Unit";"Zergling";"Larva";65;1
"Unit";"Zergling";"Larva";66;1
"Unit";"Zergling";"Larva";67;1
"Unit";"Zergling";"Larva";68;1
"Unit";"Overlord";"Larva";69;0
"Building";"CreepTumor";NA;70;0
"Building";"CreepTumor";NA;70;0
"Unit";"Zergling";"Larva";70;1
"Unit";"Zergling";"Larva";71;1
"Unit";"Zergling";"Larva";72;1
"Unit";"Zergling";"Larva";73;1
"Unit";"Baneling";"Zergling";74;0
"Unit";"Baneling";"Zergling";74;0
"Unit";"Queen";"Hatchery";74;2
"Building";"Extractor";NA;81;0
"Building";"CreepTumorQueen";NA;83;0
"Unit";"Baneling";"Zergling";88;0
"Unit";"Baneling";"Zergling";88;0
"Unit";"Overlord";"Larva";88;0
"Building";"CreepTumor";NA;92;0
"Unit";"Overlord";"Larva";93;0
"Unit";"Overlord";"Larva";93;0
"Unit";"Overlord";"Larva";93;0
"Unit";"Overlord";"Larva";93;0
"Unit";"Overlord";"Larva";93;0
"Unit";"Queen";"Hatchery";94;2
"Unit";"Zergling";"Larva";96;1
"Unit";"Zergling";"Larva";97;1
"Unit";"Zergling";"Larva";98;1
"Unit";"Zergling";"Larva";99;1
"Unit";"Zergling";"Larva";100;1
"Unit";"Zergling";"Larva";101;1
"Unit";"Zergling";"Larva";102;1
"Unit";"Zergling";"Larva";103;1
"Building";"Extractor";NA;106;0
"Building";"Extractor";NA;106;0
"Building";"Extractor";NA;108;0
"Unit";"Overlord";"Larva";108;0
"Building";"CreepTumor";NA;110;0
"Building";"CreepTumorQueen";NA;111;0
"Building";"CreepTumorQueen";NA;111;0
"Unit";"Overlord";"Larva";111;0
"Unit";"Zergling";"Larva";111;1
"Unit";"Zergling";"Larva";112;1
"Unit";"Zergling";"Larva";113;1
"Unit";"Zergling";"Larva";114;1
"Unit";"Zergling";"Larva";115;1
"Unit";"Zergling";"Larva";116;1
"Unit";"Zergling";"Larva";117;1
"Unit";"Zergling";"Larva";118;1
"Unit";"Zergling";"Larva";119;1
"Unit";"Zergling";"Larva";120;1
"Building";"Hatchery";NA;121;0
"Unit";"Overlord";"Larva";123;0
"Unit";"Overlord";"Larva";123;0
"Unit";"Queen";"Hatchery";128;2
"Unit";"Baneling";"Zergling";130;0
"Unit";"Baneling";"Zergling";130;0
"Unit";"Baneling";"Zergling";130;0
"Unit";"Baneling";"Zergling";130;0
"Unit";"Baneling";"Zergling";130;0
"Unit";"Baneling";"Zergling";130;0
"Unit";"Baneling";"Zergling";130;0
"Unit";"Baneling";"Zergling";130;0
"Unit";"Baneling";"Zergling";130;0
"Building";"CreepTumor";NA;130;0
"Unit";"Overlord";"Larva";130;0
"Building";"CreepTumor";NA;130;0
"Unit";"Overlord";"Larva";130;0
"Building";"CreepTumor";NA;130;0
"Unit";"Zergling";"Larva";130;1
"Unit";"Zergling";"Larva";131;1
"Unit";"Zergling";"Larva";132;1
"Unit";"Zergling";"Larva";133;1
"Unit";"Zergling";"Larva";134;1
"Unit";"Zergling";"Larva";135;1
"Unit";"Zergling";"Larva";136;1
"Unit";"Zergling";"Larva";137;1
"Unit";"Zergling";"Larva";138;1
"Unit";"Zergling";"Larva";139;1
"Unit";"Zergling";"Larva";140;1
"Unit";"Zergling";"Larva";141;1
"Unit";"Zergling";"Larva";142;1
"Unit";"Zergling";"Larva";143;1
"Unit";"Zergling";"Larva";144;1
"Unit";"Zergling";"Larva";145;1
"Unit";"Baneling";"Zergling";146;0
"Unit";"Baneling";"Zergling";146;0
"Unit";"Baneling";"Zergling";146;0
"Unit";"Baneling";"Zergling";146;0
"Unit";"Baneling";"Zergling";146;0
"Unit";"Baneling";"Zergling";146;0
"Unit";"Baneling";"Zergling";146;0
"Unit";"Zergling";"Larva";146;1
"Unit";"Zergling";"Larva";147;1
"Unit";"Zergling";"Larva";148;1
"Unit";"Zergling";"Larva";149;1
"Unit";"Zergling";"Larva";150;1
"Unit";"Zergling";"Larva";151;1
"Unit";"Zergling";"Larva";152;1
"Unit";"Zergling";"Larva";153;1
"Unit";"Zergling";"Larva";154;1
"Unit";"Zergling";"Larva";155;1
"Unit";"Zergling";"Larva";156;1
"Unit";"Zergling";"Larva";157;1
"Unit";"Zergling";"Larva";158;1
"Unit";"Zergling";"Larva";159;1
"Unit";"Zergling";"Larva";160;1
"Unit";"Zergling";"Larva";161;1
"Unit";"Zergling";"Larva";162;1
"Unit";"Zergling";"Larva";163;1
"Unit";"Zergling";"Larva";164;1
"Unit";"Zergling";"Larva";165;1
"Unit";"Zergling";"Larva";166;1
"Unit";"Zergling";"Larva";167;1
"Unit";"Zergling";"Larva";168;1
"Unit";"Zergling";"Larva";169;1
"Unit";"Zergling";"Larva";170;1
"Unit";"Zergling";"Larva";171;1
"Unit";"Zergling";"Larva";172;1
"Unit";"Zergling";"Larva";173;1
"Unit";"Zergling";"Larva";174;1
"Unit";"Zergling";"Larva";175;1
"Unit";"Zergling";"Larva";176;1
"Unit";"Zergling";"Larva";177;1
"Unit";"Baneling";"Zergling";178;0
"Unit";"Baneling";"Zergling";178;0
"Unit";"Baneling";"Zergling";178;0
"Unit";"Baneling";"Zergling";178;0
"Unit";"Baneling";"Zergling";178;0
"Unit";"Baneling";"Zergling";178;0
"Unit";"Baneling";"Zergling";178;0
"Unit";"Baneling";"Zergling";178;0
"Unit";"Baneling";"Zergling";178;0
"Building";"Hatchery";NA;178;0
"Building";"HydraliskDen";NA;178;0
"Unit";"Zergling";"Larva";178;1
"Unit";"Zergling";"Larva";179;1
"Unit";"Zergling";"Larva";180;1
"Unit";"Zergling";"Larva";181;1
"Unit";"Zergling";"Larva";182;1
"Unit";"Zergling";"Larva";183;1
"Unit";"Zergling";"Larva";184;1
"Unit";"Zergling";"Larva";185;1
"Unit";"Zergling";"Larva";186;1
"Unit";"Zergling";"Larva";187;1
"Unit";"Zergling";"Larva";188;1
"Unit";"Zergling";"Larva";189;1
"Unit";"Zergling";"Larva";190;1
"Unit";"Zergling";"Larva";191;1
"Building";"CreepTumorQueen";NA;192;0
"Building";"CreepTumorQueen";NA;192;0
"Building";"CreepTumor";NA;199;0
"Building";"CreepTumorQueen";NA;199;0
"Building";"Extractor";NA;204;0
"Building";"CreepTumor";NA;204;0
"Unit";"Hydralisk";"Larva";204;2
"Unit";"Hydralisk";"Larva";206;2
"Unit";"Hydralisk";"Larva";208;2
"Unit";"Hydralisk";"Larva";210;2
"Unit";"Hydralisk";"Larva";212;2
"Building";"CreepTumorQueen";NA;214;0
"Building";"CreepTumorQueen";NA;214;0
"Unit";"Hydralisk";"Larva";214;2
"Unit";"Hydralisk";"Larva";216;2
"Unit";"Hydralisk";"Larva";218;2
"Unit";"Hydralisk";"Larva";220;2
"Unit";"Hydralisk";"Larva";222;2
"Unit";"Overlord";"Larva";224;0
"Unit";"Baneling";"Zergling";224;0
"Unit";"Baneling";"Zergling";224;0
"Unit";"Baneling";"Zergling";224;0
"Unit";"Baneling";"Zergling";224;0
"Unit";"Baneling";"Zergling";224;0
"Unit";"Baneling";"Zergling";224;0
"Unit";"Hydralisk";"Larva";224;2
"Unit";"Zergling";"Larva";226;1
"Unit";"Zergling";"Larva";227;1
"Unit";"Zergling";"Larva";228;1
"Unit";"Zergling";"Larva";229;1
"Unit";"Zergling";"Larva";230;1
"Unit";"Zergling";"Larva";231;1
"Unit";"Zergling";"Larva";232;1
"Unit";"Zergling";"Larva";233;1
"Unit";"Zergling";"Larva";234;1
"Unit";"Zergling";"Larva";235;1
"Unit";"Zergling";"Larva";236;1
"Unit";"Zergling";"Larva";237;1
"Unit";"Zergling";"Larva";238;1
"Unit";"Zergling";"Larva";239;1
"Unit";"Hydralisk";"Larva";240;2
"Unit";"Hydralisk";"Larva";242;2
"Unit";"Hydralisk";"Larva";244;2
"Unit";"Hydralisk";"Larva";246;2
"Unit";"Zergling";"Larva";248;1
"Unit";"Zergling";"Larva";249;1
"Unit";"Zergling";"Larva";250;1
"Unit";"Zergling";"Larva";251;1
"Unit";"Zergling";"Larva";252;1
"Unit";"Zergling";"Larva";253;1
"Unit";"Hydralisk";"Larva";254;2
"Unit";"Hydralisk";"Larva";256;2
"Unit";"Hydralisk";"Larva";258;2
"Unit";"Zergling";"Larva";260;1
"Unit";"Zergling";"Larva";261;1
"Unit";"Zergling";"Larva";262;1
"Unit";"Zergling";"Larva";263;1
"Unit";"Zergling";"Larva";264;1
"Unit";"Zergling";"Larva";265;1
"Unit";"Zergling";"Larva";266;1
"Unit";"Zergling";"Larva";267;1
"Unit";"Baneling";"Zergling";268;0
"Unit";"Baneling";"Zergling";268;0
"Unit";"Hydralisk";"Larva";268;2
"Unit";"Hydralisk";"Larva";270;2
"Unit";"Hydralisk";"Larva";272;2
"Unit";"Hydralisk";"Larva";274;2
"Unit";"Hydralisk";"Larva";276;2
"Unit";"Zergling";"Larva";278;1
"Unit";"Zergling";"Larva";279;1
"Unit";"Hydralisk";"Larva";280;2
"Unit";"Hydralisk";"Larva";282;2
"Unit";"Hydralisk";"Larva";284;2
"Unit";"Zergling";"Larva";286;1
"Unit";"Zergling";"Larva";287;1
"Unit";"Hydralisk";"Larva";288;2
"Unit";"Zergling";"Larva";290;1
"Unit";"Zergling";"Larva";291;1
"Unit";"Zergling";"Larva";292;1
"Unit";"Zergling";"Larva";293;1
"Unit";"Zergling";"Larva";294;1
"Unit";"Zergling";"Larva";295;1
"Unit";"Zergling";"Larva";296;1
"Unit";"Zergling";"Larva";297;1
"Unit";"Zergling";"Larva";298;1
"Unit";"Zergling";"Larva";299;1
"Unit";"Zergling";"Larva";300;1
"Unit";"Zergling";"Larva";301;1
"Unit";"Zergling";"Larva";302;1
"Unit";"Zergling";"Larva";303;1
"Unit";"Zergling";"Larva";304;1
"Unit";"Zergling";"Larva";305;1
"Unit";"Zergling";"Larva";306;1
"Unit";"Zergling";"Larva";307;1
"Unit";"Zergling";"Larva";308;1
"Unit";"Zergling";"Larva";309;1
"Unit";"Zergling";"Larva";310;1
"Unit";"Zergling";"Larva";311;1
"Unit";"Zergling";"Larva";312;1
"Unit";"Zergling";"Larva";313;1
"Building";"CreepTumorQueen";NA;314;0
"Building";"CreepTumorQueen";NA;314;0
"Building";"CreepTumorQueen";NA;314;0
"Unit";"Zergling";"Larva";314;1
"Unit";"Zergling";"Larva";315;1
"Unit";"Zergling";"Larva";316;1
"Unit";"Zergling";"Larva";317;1
"Unit";"Baneling";"Zergling";318;0
"Unit";"Baneling";"Zergling";318;0
"Unit";"Baneling";"Zergling";318;0
"Unit";"Baneling";"Zergling";318;0
"Unit";"Zergling";"Larva";318;1
"Unit";"Zergling";"Larva";319;1
"Unit";"Zergling";"Larva";320;1
"Unit";"Zergling";"Larva";321;1
"Unit";"Zergling";"Larva";322;1
"Unit";"Zergling";"Larva";323;1
"Unit";"Zergling";"Larva";324;1
"Unit";"Zergling";"Larva";325;1
"Unit";"Zergling";"Larva";326;1
"Unit";"Zergling";"Larva";327;1
"Unit";"Zergling";"Larva";328;1
"Unit";"Zergling";"Larva";329;1
"Unit";"Zergling";"Larva";330;1
"Unit";"Zergling";"Larva";331;1
"Unit";"Zergling";"Larva";332;1
"Unit";"Zergling";"Larva";333;1
"Unit";"Zergling";"Larva";334;1
"Unit";"Zergling";"Larva";335;1
"Unit";"Zergling";"Larva";336;1
"Unit";"Zergling";"Larva";337;1
"Unit";"Zergling";"Larva";338;1
"Unit";"Zergling";"Larva";339;1
"Unit";"Zergling";"Larva";340;1
"Unit";"Zergling";"Larva";341;1
"Unit";"Zergling";"Larva";342;1
"Unit";"Zergling";"Larva";343;1
"Unit";"Zergling";"Larva";344;1
"Unit";"Zergling";"Larva";345;1
"Unit";"Baneling";"Zergling";346;0
"Unit";"Baneling";"Zergling";346;0
"Unit";"Baneling";"Zergling";346;0
"Unit";"Baneling";"Zergling";346;0
"Unit";"Baneling";"Zergling";346;0
"Unit";"Baneling";"Zergling";346;0
"Unit";"Baneling";"Zergling";346;0
"Unit";"Baneling";"Zergling";346;0
"Unit";"Baneling";"Zergling";346;0
"Unit";"Baneling";"Zergling";346;0
"Unit";"Baneling";"Zergling";346;0
"Unit";"Baneling";"Zergling";346;0
"Unit";"Baneling";"Zergling";346;0
"Unit";"Baneling";"Zergling";346;0
"Unit";"Baneling";"Zergling";346;0
"Building";"CreepTumor";NA;346;0
"Building";"CreepTumor";NA;346;0
"Building";"CreepTumor";NA;346;0
"Building";"CreepTumor";NA;346;0
"Unit";"Hydralisk";"Larva";346;2
"Unit";"Hydralisk";"Larva";348;2
"Unit";"Hydralisk";"Larva";350;2
"Unit";"Hydralisk";"Larva";352;2
"Building";"CreepTumor";NA;354;0
"Unit";"Zergling";"Larva";354;1
"Unit";"Zergling";"Larva";355;1
"Unit";"Zergling";"Larva";356;1
"Unit";"Zergling";"Larva";357;1
"Unit";"Zergling";"Larva";358;1
"Unit";"Zergling";"Larva";359;1
"Unit";"Zergling";"Larva";360;1
"Unit";"Zergling";"Larva";361;1
"Unit";"Zergling";"Larva";362;1
"Unit";"Zergling";"Larva";363;1
"Unit";"Zergling";"Larva";364;1
"Unit";"Zergling";"Larva";365;1
"Unit";"Zergling";"Larva";366;1
"Unit";"Zergling";"Larva";367;1
"Unit";"Hydralisk";"Larva";368;2
"Unit";"Hydralisk";"Larva";370;2
"Unit";"Hydralisk";"Larva";372;2
"Unit";"Zergling";"Larva";374;1
"Unit";"Zergling";"Larva";375;1
"Unit";"Baneling";"Zergling";376;0
"Unit";"Baneling";"Zergling";376;0
"Unit";"Zergling";"Larva";376;1
"Unit";"Zergling";"Larva";377;1
"Unit";"Zergling";"Larva";378;1
"Unit";"Zergling";"Larva";379;1
"Unit";"Zergling";"Larva";380;1
"Unit";"Zergling";"Larva";381;1
"Unit";"Zergling";"Larva";382;1
"Unit";"Zergling";"Larva";383;1
"Unit";"Zergling";"Larva";384;1
"Unit";"Zergling";"Larva";385;1
"Unit";"Zergling";"Larva";386;1
"Unit";"Zergling";"Larva";387;1
"Upgrade";"SprayZerg";NA;388;0
"Upgrade";"SprayZerg";NA;388;0
"Upgrade";"SprayZerg";NA;388;0
"Upgrade";"zerglingmovementspeed";NA;388;0
"Upgrade";"overlordspeed";NA;388;0
"Upgrade";"SprayZerg";NA;388;0
"Upgrade";"SprayZerg";NA;388;0
"Upgrade";"ZergMeleeWeaponsLevel1";NA;388;0
"Upgrade";"SprayZerg";NA;388;0
"Upgrade";"SprayZerg";NA;388;0
"Upgrade";"CentrificalHooks";NA;388;0
"Upgrade";"SprayZerg";NA;388;0
"Upgrade";"ZergMeleeWeaponsLevel2";NA;388;0
"Upgrade";"EvolveMuscularAugments";NA;388;0
"Upgrade";"SprayZerg";NA;388;0
