"type";"unit_name";"on_building";"total_supply_lag";"supply"
"Building";"Hatchery";NA;14;0
"Unit";"Overlord";"Larva";16;0
"Building";"SpawningPool";NA;16;0
"Building";"Extractor";NA;19;0
"Unit";"Queen";"Hatchery";22;2
"Unit";"Queen";"Hatchery";24;2
"Unit";"Overlord";"Larva";28;0
"Unit";"Zergling";"Larva";30;1
"Unit";"Zergling";"Larva";31;1
"Unit";"Queen";"Hatchery";34;2
"Unit";"Queen";"Hatchery";36;2
"Unit";"Overlord";"Larva";38;0
"Unit";"Zergling";"Larva";38;1
"Unit";"Zergling";"Larva";39;1
"Unit";"Zergling";"Larva";40;1
"Unit";"Zergling";"Larva";41;1
"Building";"Hatchery";NA;42;0
"Building";"CreepTumorQueen";NA;46;0
"Building";"CreepTumorQueen";NA;46;0
"Unit";"Overlord";"Larva";49;0
"Building";"Extractor";NA;51;0
"Building";"Extractor";NA;51;0
"Unit";"Overlord";"Larva";53;0
"Building";"SporeCrawler";NA;58;0
"Building";"CreepTumor";NA;60;0
"Building";"CreepTumor";NA;60;0
"Building";"CreepTumorQueen";NA;63;0
"Building";"CreepTumorQueen";NA;63;0
"Building";"Extractor";NA;63;0
"Unit";"Queen";"Hatchery";63;2
"Building";"SporeCrawler";NA;65;0
"Building";"SporeCrawler";NA;69;0
"Building";"CreepTumor";NA;75;0
"Building";"CreepTumor";NA;75;0
"Building";"CreepTumor";NA;75;0
"Building";"CreepTumor";NA;75;0
"Building";"CreepTumorQueen";NA;75;0
"Building";"CreepTumorQueen";NA;75;0
"Unit";"Overlord";"Larva";80;0
"Unit";"Overlord";"Larva";80;0
"Unit";"Overlord";"Larva";80;0
"Unit";"Overlord";"Larva";80;0
"Building";"HydraliskDen";NA;80;0
"Unit";"Zergling";"Larva";84;1
"Unit";"Zergling";"Larva";85;1
"Unit";"Zergling";"Larva";86;1
"Unit";"Zergling";"Larva";87;1
"Unit";"Zergling";"Larva";88;1
"Unit";"Zergling";"Larva";89;1
"Unit";"Zergling";"Larva";90;1
"Unit";"Zergling";"Larva";91;1
"Unit";"Zergling";"Larva";92;1
"Unit";"Zergling";"Larva";93;1
"Unit";"Zergling";"Larva";94;1
"Unit";"Zergling";"Larva";95;1
"Unit";"Zergling";"Larva";96;1
"Unit";"Zergling";"Larva";97;1
"Unit";"Zergling";"Larva";98;1
"Unit";"Zergling";"Larva";99;1
"Unit";"Zergling";"Larva";100;1
"Unit";"Zergling";"Larva";101;1
"Building";"CreepTumor";NA;102;0
"Building";"CreepTumor";NA;102;0
"Building";"CreepTumor";NA;102;0
"Building";"CreepTumor";NA;102;0
"Building";"CreepTumor";NA;102;0
"Unit";"Overlord";"Larva";102;0
"Unit";"Hydralisk";"Larva";102;2
"Unit";"Hydralisk";"Larva";104;2
"Unit";"Hydralisk";"Larva";106;2
"Unit";"Hydralisk";"Larva";108;2
"Unit";"Hydralisk";"Larva";110;2
"Unit";"Hydralisk";"Larva";112;2
"Unit";"Hydralisk";"Larva";114;2
"Unit";"Hydralisk";"Larva";116;2
"Unit";"Hydralisk";"Larva";118;2
"Building";"Spire";NA;120;0
"Building";"Extractor";NA;122;0
"Building";"CreepTumor";NA;122;0
"Building";"Extractor";NA;122;0
"Building";"CreepTumor";NA;122;0
"Building";"CreepTumor";NA;122;0
"Building";"CreepTumor";NA;122;0
"Building";"CreepTumor";NA;122;0
"Building";"CreepTumor";NA;132;0
"Unit";"Overlord";"Larva";132;0
"Unit";"Overlord";"Larva";132;0
"Unit";"Overlord";"Larva";132;0
"Unit";"Overlord";"Larva";132;0
"Building";"CreepTumor";NA;133;0
"Building";"Hatchery";NA;133;0
"Building";"EvolutionChamber";NA;133;0
"Unit";"Corruptor";"Larva";133;2
"Unit";"Corruptor";"Larva";135;2
"Unit";"Corruptor";"Larva";137;2
"Unit";"Corruptor";"Larva";139;2
"Unit";"Corruptor";"Larva";141;2
"Unit";"Corruptor";"Larva";143;2
"Unit";"Corruptor";"Larva";145;2
"Unit";"Corruptor";"Larva";147;2
"Unit";"Corruptor";"Larva";149;2
"Unit";"Corruptor";"Larva";151;2
"Building";"CreepTumor";NA;153;0
"Building";"CreepTumor";NA;153;0
"Building";"Hatchery";NA;166;0
"Building";"EvolutionChamber";NA;166;0
"Building";"BanelingNest";NA;166;0
"Building";"CreepTumor";NA;166;0
"Unit";"Hydralisk";"Larva";166;2
"Unit";"Hydralisk";"Larva";168;2
"Unit";"Hydralisk";"Larva";170;2
"Unit";"Hydralisk";"Larva";172;2
"Unit";"Hydralisk";"Larva";174;2
"Unit";"Hydralisk";"Larva";176;2
"Unit";"Hydralisk";"Larva";178;2
"Unit";"Overlord";"Larva";180;0
"Unit";"Overlord";"Larva";180;0
"Unit";"Overlord";"Larva";180;0
"Unit";"Hydralisk";"Larva";180;2
"Unit";"Hydralisk";"Larva";182;2
"Unit";"Hydralisk";"Larva";184;2
"Building";"Extractor";NA;186;0
"Building";"Extractor";NA;186;0
"Building";"CreepTumor";NA;186;0
"Building";"SporeCrawler";NA;192;0
"Unit";"Hydralisk";"Larva";192;2
"Unit";"Hydralisk";"Larva";194;2
"Unit";"Hydralisk";"Larva";196;2
"Unit";"Hydralisk";"Larva";198;2
"Unit";"Hydralisk";"Larva";200;2
"Unit";"Hydralisk";"Larva";202;2
"Unit";"Hydralisk";"Larva";204;2
"Unit";"Hydralisk";"Larva";206;2
"Unit";"Hydralisk";"Larva";208;2
"Unit";"Hydralisk";"Larva";210;2
"Building";"CreepTumor";NA;212;0
"Unit";"Zergling";"Larva";212;1
"Unit";"Zergling";"Larva";213;1
"Unit";"Zergling";"Larva";214;1
"Unit";"Zergling";"Larva";215;1
"Unit";"Zergling";"Larva";216;1
"Unit";"Zergling";"Larva";217;1
"Unit";"Zergling";"Larva";218;1
"Unit";"Zergling";"Larva";219;1
"Unit";"Zergling";"Larva";220;1
"Unit";"Zergling";"Larva";221;1
"Unit";"Zergling";"Larva";222;1
"Unit";"Zergling";"Larva";223;1
"Unit";"Zergling";"Larva";224;1
"Unit";"Zergling";"Larva";225;1
"Unit";"Overlord";"Larva";226;0
"Unit";"Overlord";"Larva";226;0
"Unit";"Overlord";"Larva";226;0
"Unit";"Overlord";"Larva";226;0
"Unit";"Overlord";"Larva";226;0
"Building";"SporeCrawler";NA;226;0
"Building";"Extractor";NA;227;0
"Building";"Extractor";NA;228;0
"Building";"CreepTumor";NA;229;0
"Building";"Spire";NA;232;0
"Building";"CreepTumor";NA;232;0
"Unit";"Corruptor";"Larva";232;2
"Unit";"Corruptor";"Larva";234;2
"Unit";"Corruptor";"Larva";236;2
"Unit";"Corruptor";"Larva";238;2
"Unit";"Corruptor";"Larva";240;2
"Unit";"Corruptor";"Larva";242;2
"Unit";"Corruptor";"Larva";244;2
"Building";"InfestationPit";NA;246;0
"Unit";"Baneling";"Zergling";246;0
"Unit";"Baneling";"Zergling";246;0
"Unit";"Baneling";"Zergling";246;0
"Unit";"Baneling";"Zergling";246;0
"Unit";"Baneling";"Zergling";246;0
"Unit";"Baneling";"Zergling";246;0
"Unit";"Baneling";"Zergling";246;0
"Unit";"Baneling";"Zergling";246;0
"Unit";"Baneling";"Zergling";246;0
"Unit";"Baneling";"Zergling";246;0
"Unit";"Baneling";"Zergling";246;0
"Unit";"Baneling";"Zergling";246;0
"Unit";"Baneling";"Zergling";246;0
"Unit";"Baneling";"Zergling";246;0
"Unit";"Baneling";"Zergling";246;0
"Unit";"Hydralisk";"Larva";246;2
"Unit";"Hydralisk";"Larva";248;2
"Unit";"Hydralisk";"Larva";250;2
"Unit";"Hydralisk";"Larva";252;2
"Unit";"Hydralisk";"Larva";254;2
"Unit";"Overlord";"Larva";256;0
"Unit";"Overlord";"Larva";256;0
"Unit";"Overlord";"Larva";256;0
"Unit";"Overlord";"Larva";256;0
"Unit";"Infestor";"Larva";257;2
"Unit";"Infestor";"Larva";259;2
"Unit";"Infestor";"Larva";261;2
"Unit";"Infestor";"Larva";263;2
"Unit";"Infestor";"Larva";265;2
"Unit";"Infestor";"Larva";267;2
"Unit";"Infestor";"Larva";269;2
"Unit";"Infestor";"Larva";271;2
"Unit";"Hydralisk";"Larva";273;2
"Unit";"Hydralisk";"Larva";275;2
"Unit";"Hydralisk";"Larva";277;2
"Unit";"Hydralisk";"Larva";279;2
"Unit";"Hydralisk";"Larva";281;2
"Unit";"Hydralisk";"Larva";283;2
"Unit";"Hydralisk";"Larva";285;2
"Unit";"Hydralisk";"Larva";287;2
"Unit";"Hydralisk";"Larva";289;2
"Unit";"Hydralisk";"Larva";291;2
"Unit";"Hydralisk";"Larva";293;2
"Unit";"Hydralisk";"Larva";295;2
"Upgrade";"Burrow";"Hatchery";297;0
"Building";"CreepTumor";NA;297;0
"Building";"Hatchery";NA;297;0
"Building";"CreepTumor";NA;297;0
"Upgrade";"NeuralParasite";"InfestationPit";297;0
"Building";"Hatchery";NA;297;0
"Building";"CreepTumor";NA;297;0
"Building";"UltraliskCavern";NA;297;0
"Unit";"Corruptor";"Larva";297;2
"Unit";"Corruptor";"Larva";299;2
"Unit";"Corruptor";"Larva";301;2
"Unit";"Corruptor";"Larva";303;2
"Unit";"Corruptor";"Larva";305;2
"Unit";"Zergling";"Larva";307;1
"Unit";"Zergling";"Larva";308;1
"Unit";"Zergling";"Larva";309;1
"Unit";"Zergling";"Larva";310;1
"Unit";"Zergling";"Larva";311;1
"Unit";"Zergling";"Larva";312;1
"Unit";"Zergling";"Larva";313;1
"Unit";"Zergling";"Larva";314;1
"Unit";"Zergling";"Larva";315;1
"Unit";"Zergling";"Larva";316;1
"Unit";"Zergling";"Larva";317;1
"Unit";"Zergling";"Larva";318;1
"Unit";"Zergling";"Larva";319;1
"Unit";"Zergling";"Larva";320;1
"Unit";"Zergling";"Larva";321;1
"Unit";"Zergling";"Larva";322;1
"Unit";"Zergling";"Larva";323;1
"Unit";"Zergling";"Larva";324;1
"Unit";"Zergling";"Larva";325;1
"Unit";"Zergling";"Larva";326;1
"Unit";"Zergling";"Larva";327;1
"Unit";"Zergling";"Larva";328;1
"Unit";"Queen";"Hatchery";329;2
"Building";"Extractor";NA;331;0
"Unit";"Zergling";"Larva";331;1
"Unit";"Zergling";"Larva";332;1
"Building";"Extractor";NA;333;0
"Unit";"Zergling";"Larva";333;1
"Unit";"Zergling";"Larva";334;1
"Unit";"Zergling";"Larva";335;1
"Unit";"Zergling";"Larva";336;1
"Unit";"Zergling";"Larva";337;1
"Unit";"Zergling";"Larva";338;1
"Unit";"Zergling";"Larva";339;1
"Unit";"Zergling";"Larva";340;1
"Unit";"Zergling";"Larva";341;1
"Unit";"Zergling";"Larva";342;1
"Unit";"Zergling";"Larva";343;1
"Unit";"Zergling";"Larva";344;1
"Unit";"Zergling";"Larva";345;1
"Unit";"Zergling";"Larva";346;1
"Unit";"Zergling";"Larva";347;1
"Unit";"Zergling";"Larva";348;1
"Unit";"Zergling";"Larva";349;1
"Unit";"Zergling";"Larva";350;1
"Unit";"Zergling";"Larva";351;1
"Unit";"Zergling";"Larva";352;1
"Unit";"Zergling";"Larva";353;1
"Unit";"Zergling";"Larva";354;1
"Unit";"Corruptor";"Larva";355;2
"Unit";"Ultralisk";"Larva";358;6
"Unit";"Ultralisk";"Larva";364;6
"Building";"Extractor";NA;370;0
"Building";"Extractor";NA;370;0
"Unit";"Overlord";"Larva";370;0
"Unit";"Overlord";"Larva";370;0
"Unit";"Overlord";"Larva";370;0
"Unit";"Overlord";"Larva";370;0
"Unit";"Overlord";"Larva";370;0
"Unit";"Ultralisk";"Larva";370;6
"Building";"CreepTumor";NA;376;0
"Building";"Hatchery";NA;376;0
"Upgrade";"ChitinousPlating";"UltraliskCavern";377;0
"Unit";"Ultralisk";"Larva";377;6
"Unit";"Ultralisk";"Larva";383;6
"Unit";"Ultralisk";"Larva";389;6
"Unit";"Ultralisk";"Larva";395;6
"Building";"Hatchery";NA;403;0
"Building";"SporeCrawler";NA;403;0
"Building";"SporeCrawler";NA;403;0
"Unit";"Queen";"Hatchery";403;2
"Unit";"Hydralisk";"Larva";405;2
"Unit";"Hydralisk";"Larva";407;2
"Unit";"Hydralisk";"Larva";409;2
"Unit";"Hydralisk";"Larva";411;2
"Unit";"Hydralisk";"Larva";413;2
"Unit";"Hydralisk";"Larva";415;2
"Unit";"Hydralisk";"Larva";417;2
"Unit";"Hydralisk";"Larva";419;2
"Unit";"Hydralisk";"Larva";421;2
"Unit";"Hydralisk";"Larva";423;2
"Unit";"Hydralisk";"Larva";425;2
"Unit";"Zergling";"Larva";427;1
"Unit";"Zergling";"Larva";428;1
"Unit";"Corruptor";"Larva";429;2
"Unit";"Corruptor";"Larva";431;2
"Unit";"Corruptor";"Larva";433;2
"Unit";"Corruptor";"Larva";435;2
"Unit";"Corruptor";"Larva";437;2
"Unit";"Corruptor";"Larva";439;2
"Unit";"Corruptor";"Larva";441;2
"Unit";"Corruptor";"Larva";443;2
"Unit";"Corruptor";"Larva";445;2
"Unit";"Corruptor";"Larva";447;2
"Unit";"Corruptor";"Larva";449;2
"Unit";"Corruptor";"Larva";451;2
"Unit";"Corruptor";"Larva";453;2
"Unit";"Corruptor";"Larva";455;2
"Unit";"Corruptor";"Larva";457;2
"Unit";"Corruptor";"Larva";459;2
"Unit";"Corruptor";"Larva";461;2
"Unit";"Corruptor";"Larva";463;2
"Unit";"Corruptor";"Larva";465;2
"Unit";"Corruptor";"Larva";467;2
"Unit";"Zergling";"Larva";469;1
"Unit";"Zergling";"Larva";470;1
"Unit";"Zergling";"Larva";471;1
"Unit";"Zergling";"Larva";472;1
"Unit";"Zergling";"Larva";473;1
"Unit";"Zergling";"Larva";474;1
"Unit";"Zergling";"Larva";475;1
"Unit";"Zergling";"Larva";476;1
"Unit";"Zergling";"Larva";477;1
"Unit";"Zergling";"Larva";478;1
"Unit";"Zergling";"Larva";479;1
"Unit";"Zergling";"Larva";480;1
"Unit";"Zergling";"Larva";481;1
"Unit";"Zergling";"Larva";482;1
"Unit";"Zergling";"Larva";483;1
"Unit";"Zergling";"Larva";484;1
"Unit";"Zergling";"Larva";485;1
"Unit";"Zergling";"Larva";486;1
"Unit";"Zergling";"Larva";487;1
"Unit";"Zergling";"Larva";488;1
"Unit";"Zergling";"Larva";489;1
"Unit";"Zergling";"Larva";490;1
"Unit";"Zergling";"Larva";491;1
"Unit";"Zergling";"Larva";492;1
"Unit";"Zergling";"Larva";493;1
"Unit";"Zergling";"Larva";494;1
"Unit";"Zergling";"Larva";495;1
"Unit";"Zergling";"Larva";496;1
"Unit";"Zergling";"Larva";497;1
"Unit";"Zergling";"Larva";498;1
"Unit";"Zergling";"Larva";499;1
"Unit";"Zergling";"Larva";500;1
"Unit";"Zergling";"Larva";501;1
"Unit";"Zergling";"Larva";502;1
"Unit";"Zergling";"Larva";503;1
"Unit";"Zergling";"Larva";504;1
"Unit";"Zergling";"Larva";505;1
"Unit";"Zergling";"Larva";506;1
"Unit";"Zergling";"Larva";507;1
"Unit";"Zergling";"Larva";508;1
"Unit";"Zergling";"Larva";509;1
"Unit";"Zergling";"Larva";510;1
"Unit";"Zergling";"Larva";511;1
"Unit";"Zergling";"Larva";512;1
"Unit";"Zergling";"Larva";513;1
"Unit";"Zergling";"Larva";514;1
"Unit";"Zergling";"Larva";515;1
"Unit";"Zergling";"Larva";516;1
"Unit";"Zergling";"Larva";517;1
"Unit";"Zergling";"Larva";518;1
"Unit";"Zergling";"Larva";519;1
"Unit";"Zergling";"Larva";520;1
"Unit";"Zergling";"Larva";521;1
"Unit";"Zergling";"Larva";522;1
"Upgrade";"SprayZerg";NA;523;0
"Upgrade";"SprayZerg";NA;523;0
"Upgrade";"SprayZerg";NA;523;0
"Upgrade";"zerglingmovementspeed";NA;523;0
"Upgrade";"SprayZerg";NA;523;0
"Upgrade";"EvolveMuscularAugments";NA;523;0
"Upgrade";"SprayZerg";NA;523;0
"Upgrade";"SprayZerg";NA;523;0
"Upgrade";"SprayZerg";NA;523;0
"Upgrade";"SprayZerg";NA;523;0
"Upgrade";"ZergFlyerWeaponsLevel1";NA;523;0
"Upgrade";"ZergMissileWeaponsLevel1";NA;523;0
"Upgrade";"CentrificalHooks";NA;523;0
"Upgrade";"overlordspeed";NA;523;0
"Upgrade";"ZergMeleeWeaponsLevel1";NA;523;0
"Upgrade";"ZergFlyerArmorsLevel1";NA;523;0
"Upgrade";"ZergMissileWeaponsLevel2";NA;523;0
"Upgrade";"InfestorEnergyUpgrade";NA;523;0
"Upgrade";"SprayZerg";NA;523;0
"Upgrade";"ZergMeleeWeaponsLevel2";NA;523;0
"Upgrade";"ZergFlyerWeaponsLevel2";NA;523;0
"Upgrade";"SprayZerg";NA;523;0
"Upgrade";"SprayZerg";NA;523;0
"Upgrade";"ZergGroundArmorsLevel1";NA;523;0
"Upgrade";"ZergFlyerArmorsLevel2";NA;523;0
"Upgrade";"SprayZerg";NA;523;0
"Upgrade";"zerglingattackspeed";NA;523;0
"Upgrade";"SprayZerg";NA;523;0
"Upgrade";"SprayZerg";NA;523;0
"Upgrade";"ZergMeleeWeaponsLevel3";NA;523;0
"Upgrade";"ZergGroundArmorsLevel2";NA;523;0
"Upgrade";"ZergFlyerArmorsLevel3";NA;523;0
"Upgrade";"ZergFlyerWeaponsLevel3";NA;523;0
"Upgrade";"SprayZerg";NA;523;0
"Upgrade";"SprayZerg";NA;523;0
