"type";"unit_name";"on_building";"total_supply_lag"
"Unit";"Overlord";"Larva";13
"Building";"SpawningPool";NA;17
"Building";"Hatchery";NA;18
"Unit";"Queen";"Hatchery";21
"Unit";"Zergling";"Larva";23
"Unit";"Zergling";"Larva";24
"Unit";"Overlord";"Larva";25
"Building";"Hatchery";NA;25
"Building";"Extractor";NA;25
"Unit";"Queen";"Hatchery";27
"Unit";"Queen";"Hatchery";29
"Building";"CreepTumorQueen";NA;36
"Unit";"Overlord";"Larva";40
"Building";"CreepTumor";NA;40
"Building";"CreepTumor";NA;49
"Unit";"Overlord";"Larva";49
"Unit";"Overlord";"Larva";54
"Building";"CreepTumor";NA;59
"Unit";"Overlord";"Larva";59
"Unit";"Queen";"Hatchery";59
"Unit";"Queen";"Hatchery";61
"Unit";"Queen";"Hatchery";63
"Building";"EvolutionChamber";NA;65
"Building";"EvolutionChamber";NA;65
"Building";"Extractor";NA;68
"Unit";"Overlord";"Larva";68
"Building";"CreepTumor";NA;68
"Building";"CreepTumorQueen";NA;68
"Unit";"Zergling";"Larva";68
"Unit";"Zergling";"Larva";69
"Unit";"Zergling";"Larva";70
"Unit";"Zergling";"Larva";71
"Unit";"Zergling";"Larva";72
"Unit";"Zergling";"Larva";73
"Unit";"Zergling";"Larva";74
"Unit";"Zergling";"Larva";75
"Unit";"Zergling";"Larva";76
"Unit";"Zergling";"Larva";77
"Unit";"Zergling";"Larva";78
"Unit";"Zergling";"Larva";79
"Unit";"Zergling";"Larva";80
"Unit";"Zergling";"Larva";81
"Unit";"Zergling";"Larva";82
"Unit";"Zergling";"Larva";83
"Unit";"Zergling";"Larva";84
"Unit";"Zergling";"Larva";85
"Unit";"Zergling";"Larva";86
"Unit";"Zergling";"Larva";87
"Unit";"Zergling";"Larva";88
"Unit";"Zergling";"Larva";89
"Unit";"Zergling";"Larva";90
"Unit";"Zergling";"Larva";91
"Unit";"Zergling";"Larva";92
"Unit";"Zergling";"Larva";93
"Unit";"Zergling";"Larva";94
"Unit";"Zergling";"Larva";95
"Building";"BanelingNest";NA;96
"Unit";"Zergling";"Larva";99
"Unit";"Zergling";"Larva";100
"Unit";"Zergling";"Larva";101
"Unit";"Zergling";"Larva";102
"Unit";"Zergling";"Larva";103
"Unit";"Zergling";"Larva";104
"Unit";"Overlord";"Larva";105
"Unit";"Queen";"Hatchery";105
"Unit";"Queen";"Hatchery";107
"Building";"CreepTumorQueen";NA;110
"Building";"CreepTumorQueen";NA;110
"Building";"CreepTumorQueen";NA;110
"Building";"CreepTumorQueen";NA;118
"Building";"CreepTumor";NA;118
"Building";"SporeCrawler";NA;118
"Unit";"Overlord";"Larva";118
"Unit";"Overlord";"Larva";118
"Building";"SporeCrawler";NA;118
"Building";"SporeCrawler";NA;118
"Unit";"Zergling";"Larva";118
"Unit";"Zergling";"Larva";119
"Unit";"Zergling";"Larva";120
"Unit";"Zergling";"Larva";121
"Unit";"Baneling";"Zergling";122
"Unit";"Baneling";"Zergling";122
"Unit";"Baneling";"Zergling";122
"Unit";"Baneling";"Zergling";122
"Unit";"Baneling";"Zergling";122
"Unit";"Baneling";"Zergling";122
"Unit";"Baneling";"Zergling";122
"Unit";"Baneling";"Zergling";122
"Unit";"Zergling";"Larva";122
"Unit";"Zergling";"Larva";123
"Unit";"Zergling";"Larva";124
"Unit";"Zergling";"Larva";125
"Building";"Extractor";NA;126
"Building";"Extractor";NA;126
"Unit";"Zergling";"Larva";126
"Unit";"Zergling";"Larva";127
"Unit";"Zergling";"Larva";128
"Unit";"Zergling";"Larva";129
"Unit";"Zergling";"Larva";130
"Unit";"Zergling";"Larva";131
"Unit";"Zergling";"Larva";132
"Unit";"Zergling";"Larva";133
"Unit";"Zergling";"Larva";134
"Unit";"Zergling";"Larva";135
"Unit";"Overlord";"Larva";139
"Building";"CreepTumorQueen";NA;140
"Building";"CreepTumorQueen";NA;141
"Building";"CreepTumorQueen";NA;141
"Building";"Extractor";NA;141
"Building";"Extractor";NA;141
"Unit";"Overlord";"Larva";149
"Unit";"Overlord";"Larva";149
"Building";"CreepTumorQueen";NA;152
"Building";"CreepTumorQueen";NA;152
"Building";"CreepTumorQueen";NA;152
"Unit";"Overlord";"Larva";152
"Unit";"Zergling";"Larva";154
"Unit";"Zergling";"Larva";155
"Unit";"Zergling";"Larva";156
"Unit";"Zergling";"Larva";157
"Unit";"Zergling";"Larva";158
"Unit";"Zergling";"Larva";159
"Unit";"Zergling";"Larva";160
"Unit";"Zergling";"Larva";161
"Building";"CreepTumor";NA;162
"Building";"CreepTumor";NA;162
"Building";"CreepTumor";NA;162
"Building";"Spire";NA;162
"Unit";"Zergling";"Larva";162
"Unit";"Zergling";"Larva";163
"Unit";"Zergling";"Larva";164
"Unit";"Zergling";"Larva";165
"Unit";"Zergling";"Larva";166
"Unit";"Zergling";"Larva";167
"Unit";"Zergling";"Larva";168
"Unit";"Zergling";"Larva";169
"Unit";"Zergling";"Larva";170
"Unit";"Zergling";"Larva";171
"Unit";"Zergling";"Larva";172
"Unit";"Zergling";"Larva";173
"Unit";"Zergling";"Larva";174
"Unit";"Zergling";"Larva";175
"Unit";"Zergling";"Larva";176
"Unit";"Zergling";"Larva";177
"Building";"CreepTumor";NA;178
"Building";"CreepTumor";NA;178
"Building";"CreepTumor";NA;178
"Unit";"Zergling";"Larva";178
"Unit";"Zergling";"Larva";179
"Unit";"Zergling";"Larva";180
"Unit";"Zergling";"Larva";181
"Unit";"Zergling";"Larva";182
"Unit";"Zergling";"Larva";183
"Unit";"Zergling";"Larva";184
"Unit";"Zergling";"Larva";185
"Unit";"Zergling";"Larva";186
"Unit";"Zergling";"Larva";187
"Unit";"Zergling";"Larva";188
"Unit";"Zergling";"Larva";189
"Unit";"Zergling";"Larva";190
"Unit";"Zergling";"Larva";191
"Building";"Hatchery";NA;192
"Building";"Hatchery";NA;195
"Unit";"Baneling";"Zergling";195
"Unit";"Baneling";"Zergling";195
"Unit";"Baneling";"Zergling";195
"Unit";"Baneling";"Zergling";195
"Unit";"Baneling";"Zergling";195
"Unit";"Baneling";"Zergling";195
"Unit";"Baneling";"Zergling";195
"Unit";"Baneling";"Zergling";195
"Unit";"Zergling";"Larva";195
"Unit";"Zergling";"Larva";196
"Unit";"Zergling";"Larva";197
"Unit";"Zergling";"Larva";198
"Unit";"Zergling";"Larva";199
"Unit";"Zergling";"Larva";200
"Unit";"Zergling";"Larva";201
"Unit";"Zergling";"Larva";202
"Unit";"Zergling";"Larva";203
"Unit";"Zergling";"Larva";204
"Unit";"Overlord";"Larva";205
"Unit";"Overlord";"Larva";205
"Unit";"Zergling";"Larva";205
"Unit";"Zergling";"Larva";206
"Unit";"Zergling";"Larva";207
"Unit";"Zergling";"Larva";208
"Unit";"Zergling";"Larva";209
"Unit";"Zergling";"Larva";210
"Unit";"Mutalisk";"Larva";211
"Unit";"Mutalisk";"Larva";213
"Unit";"Mutalisk";"Larva";215
"Unit";"Mutalisk";"Larva";217
"Unit";"Mutalisk";"Larva";219
"Unit";"Mutalisk";"Larva";221
"Unit";"Mutalisk";"Larva";223
"Unit";"Mutalisk";"Larva";225
"Unit";"Mutalisk";"Larva";227
"Unit";"Zergling";"Larva";229
"Unit";"Zergling";"Larva";230
"Unit";"Zergling";"Larva";231
"Unit";"Zergling";"Larva";232
"Unit";"Zergling";"Larva";233
"Unit";"Zergling";"Larva";234
"Unit";"Zergling";"Larva";235
"Unit";"Zergling";"Larva";236
"Unit";"Zergling";"Larva";237
"Unit";"Zergling";"Larva";238
"Unit";"Zergling";"Larva";239
"Unit";"Zergling";"Larva";240
"Unit";"Zergling";"Larva";241
"Unit";"Zergling";"Larva";242
"Unit";"Zergling";"Larva";243
"Unit";"Zergling";"Larva";244
"Unit";"Zergling";"Larva";245
"Unit";"Zergling";"Larva";246
"Unit";"Zergling";"Larva";247
"Unit";"Zergling";"Larva";248
"Unit";"Zergling";"Larva";249
"Unit";"Zergling";"Larva";250
"Unit";"Zergling";"Larva";251
"Unit";"Zergling";"Larva";252
"Unit";"Zergling";"Larva";253
"Unit";"Zergling";"Larva";254
"Unit";"Zergling";"Larva";255
"Unit";"Zergling";"Larva";256
"Unit";"Baneling";"Zergling";257
"Unit";"Baneling";"Zergling";257
"Unit";"Baneling";"Zergling";257
"Unit";"Baneling";"Zergling";257
"Unit";"Baneling";"Zergling";257
"Unit";"Baneling";"Zergling";257
"Unit";"Baneling";"Zergling";257
"Unit";"Baneling";"Zergling";257
"Unit";"Baneling";"Zergling";257
"Unit";"Baneling";"Zergling";257
"Unit";"Zergling";"Larva";257
"Unit";"Zergling";"Larva";258
"Unit";"Zergling";"Larva";259
"Unit";"Zergling";"Larva";260
"Unit";"Zergling";"Larva";261
"Unit";"Zergling";"Larva";262
"Unit";"Zergling";"Larva";263
"Unit";"Zergling";"Larva";264
"Unit";"Zergling";"Larva";265
"Unit";"Zergling";"Larva";266
"Unit";"Zergling";"Larva";267
"Unit";"Zergling";"Larva";268
"Unit";"Zergling";"Larva";269
"Unit";"Zergling";"Larva";270
"Unit";"Zergling";"Larva";271
"Unit";"Zergling";"Larva";272
"Unit";"Zergling";"Larva";273
"Unit";"Zergling";"Larva";274
"Unit";"Zergling";"Larva";275
"Unit";"Zergling";"Larva";276
"Unit";"Zergling";"Larva";277
"Unit";"Zergling";"Larva";278
"Unit";"Mutalisk";"Larva";279
"Unit";"Mutalisk";"Larva";281
"Unit";"Mutalisk";"Larva";283
"Unit";"Mutalisk";"Larva";285
"Unit";"Zergling";"Larva";287
"Unit";"Zergling";"Larva";288
"Unit";"Zergling";"Larva";289
"Unit";"Zergling";"Larva";290
"Unit";"Zergling";"Larva";291
"Unit";"Zergling";"Larva";292
"Unit";"Zergling";"Larva";293
"Unit";"Zergling";"Larva";294
"Unit";"Zergling";"Larva";295
"Unit";"Zergling";"Larva";296
"Unit";"Zergling";"Larva";297
"Unit";"Zergling";"Larva";298
"Unit";"Zergling";"Larva";299
"Unit";"Zergling";"Larva";300
"Unit";"Mutalisk";"Larva";301
"Unit";"Mutalisk";"Larva";303
"Unit";"Zergling";"Larva";305
"Unit";"Zergling";"Larva";306
"Unit";"Zergling";"Larva";307
"Unit";"Zergling";"Larva";308
"Unit";"Zergling";"Larva";309
"Unit";"Zergling";"Larva";310
"Unit";"Zergling";"Larva";311
"Unit";"Zergling";"Larva";312
"Unit";"Mutalisk";"Larva";313
"Unit";"Zergling";"Larva";315
"Unit";"Zergling";"Larva";316
"Unit";"Zergling";"Larva";317
"Unit";"Zergling";"Larva";318
"Unit";"Zergling";"Larva";319
"Unit";"Zergling";"Larva";320
"Unit";"Zergling";"Larva";321
"Unit";"Zergling";"Larva";322
"Unit";"Zergling";"Larva";323
"Unit";"Zergling";"Larva";324
"Unit";"Zergling";"Larva";325
"Unit";"Zergling";"Larva";326
"Unit";"Baneling";"Zergling";327
"Unit";"Baneling";"Zergling";327
"Unit";"Baneling";"Zergling";327
"Unit";"Baneling";"Zergling";327
"Unit";"Zergling";"Larva";327
"Unit";"Zergling";"Larva";328
"Unit";"Zergling";"Larva";329
"Unit";"Zergling";"Larva";330
"Unit";"Zergling";"Larva";331
"Unit";"Zergling";"Larva";332
"Unit";"Zergling";"Larva";333
"Unit";"Zergling";"Larva";334
"Unit";"Zergling";"Larva";335
"Unit";"Zergling";"Larva";336
"Unit";"Zergling";"Larva";337
"Unit";"Zergling";"Larva";338
"Unit";"Zergling";"Larva";339
"Unit";"Zergling";"Larva";340
"Unit";"Zergling";"Larva";341
"Unit";"Zergling";"Larva";342
"Unit";"Zergling";"Larva";343
"Unit";"Zergling";"Larva";344
"Unit";"Zergling";"Larva";345
"Unit";"Zergling";"Larva";346
"Unit";"Zergling";"Larva";347
"Unit";"Zergling";"Larva";348
"Unit";"Zergling";"Larva";349
"Unit";"Zergling";"Larva";350
"Unit";"Zergling";"Larva";351
"Unit";"Zergling";"Larva";352
"Unit";"Zergling";"Larva";353
"Unit";"Zergling";"Larva";354
"Unit";"Zergling";"Larva";355
"Unit";"Zergling";"Larva";356
"Unit";"Zergling";"Larva";357
"Unit";"Zergling";"Larva";358
"Unit";"Mutalisk";"Larva";359
"Unit";"Mutalisk";"Larva";361
"Unit";"Mutalisk";"Larva";363
"Unit";"Mutalisk";"Larva";365
"Unit";"Zergling";"Larva";367
"Unit";"Zergling";"Larva";368
"Unit";"Zergling";"Larva";369
"Unit";"Zergling";"Larva";370
"Building";"CreepTumorQueen";NA;371
"Unit";"Zergling";"Larva";371
"Unit";"Zergling";"Larva";372
"Unit";"Zergling";"Larva";373
"Unit";"Zergling";"Larva";374
"Unit";"Zergling";"Larva";375
"Unit";"Zergling";"Larva";376
"Unit";"Zergling";"Larva";377
"Unit";"Zergling";"Larva";378
"Unit";"Zergling";"Larva";379
"Unit";"Zergling";"Larva";380
"Unit";"Zergling";"Larva";381
"Unit";"Zergling";"Larva";382
"Unit";"Zergling";"Larva";383
"Unit";"Zergling";"Larva";384
"Building";"CreepTumorQueen";NA;385
"Unit";"Zergling";"Larva";385
"Unit";"Zergling";"Larva";386
"Unit";"Zergling";"Larva";387
"Unit";"Zergling";"Larva";388
"Unit";"Zergling";"Larva";389
"Unit";"Zergling";"Larva";390
"Unit";"Zergling";"Larva";391
"Unit";"Zergling";"Larva";392
"Unit";"Zergling";"Larva";393
"Unit";"Zergling";"Larva";394
"Unit";"Mutalisk";"Larva";395
"Unit";"Mutalisk";"Larva";397
"Building";"Extractor";NA;399
"Unit";"Baneling";"Zergling";399
"Unit";"Baneling";"Zergling";399
"Unit";"Baneling";"Zergling";399
"Unit";"Baneling";"Zergling";399
"Unit";"Zergling";"Larva";399
"Unit";"Zergling";"Larva";400
"Unit";"Zergling";"Larva";401
"Unit";"Zergling";"Larva";402
"Unit";"Zergling";"Larva";403
"Unit";"Zergling";"Larva";404
"Building";"CreepTumor";NA;405
"Building";"CreepTumor";NA;405
"Unit";"Zergling";"Larva";405
"Unit";"Zergling";"Larva";406
"Unit";"Zergling";"Larva";407
"Unit";"Zergling";"Larva";408
"Unit";"Mutalisk";"Larva";411
"Unit";"Mutalisk";"Larva";413
"Building";"CreepTumor";NA;421
"Building";"CreepTumor";NA;421
"Unit";"Mutalisk";"Larva";421
"Unit";"Overlord";"Larva";423
"Unit";"Overlord";"Larva";423
"Unit";"Zergling";"Larva";423
"Unit";"Zergling";"Larva";424
"Unit";"Zergling";"Larva";425
"Unit";"Zergling";"Larva";426
"Unit";"Zergling";"Larva";427
"Unit";"Zergling";"Larva";428
"Unit";"Zergling";"Larva";429
"Unit";"Zergling";"Larva";430
"Building";"CreepTumor";NA;431
"Building";"CreepTumor";NA;431
"Unit";"Zergling";"Larva";431
"Unit";"Zergling";"Larva";432
"Unit";"Zergling";"Larva";433
"Unit";"Zergling";"Larva";434
"Unit";"Mutalisk";"Larva";435
"Unit";"Mutalisk";"Larva";437
"Unit";"Zergling";"Larva";439
"Unit";"Zergling";"Larva";440
"Unit";"Zergling";"Larva";441
"Unit";"Zergling";"Larva";442
"Unit";"Zergling";"Larva";443
"Unit";"Zergling";"Larva";444
"Unit";"Baneling";"Zergling";445
"Unit";"Baneling";"Zergling";445
"Unit";"Baneling";"Zergling";445
"Unit";"Baneling";"Zergling";445
"Unit";"Baneling";"Zergling";445
"Unit";"Baneling";"Zergling";445
"Unit";"Baneling";"Zergling";445
"Unit";"Zergling";"Larva";445
"Unit";"Zergling";"Larva";446
"Unit";"Zergling";"Larva";447
"Unit";"Zergling";"Larva";448
"Unit";"Zergling";"Larva";449
"Unit";"Zergling";"Larva";450
"Unit";"Zergling";"Larva";451
"Unit";"Zergling";"Larva";452
"Unit";"Zergling";"Larva";453
"Unit";"Zergling";"Larva";454
"Building";"CreepTumor";NA;455
"Building";"CreepTumor";NA;455
"Upgrade";"SprayZerg";NA;455
"Upgrade";"SprayZerg";NA;455
"Upgrade";"SprayZerg";NA;455
"Upgrade";"SprayZerg";NA;455
"Upgrade";"zerglingmovementspeed";NA;455
"Upgrade";"ZergGroundArmorsLevel1";NA;455
"Upgrade";"ZergMeleeWeaponsLevel1";NA;455
"Upgrade";"SprayZerg";NA;455
"Upgrade";"SprayZerg";NA;455
"Upgrade";"CentrificalHooks";NA;455
"Upgrade";"overlordspeed";NA;455
"Upgrade";"SprayZerg";NA;455
"Upgrade";"SprayZerg";NA;455
"Upgrade";"ZergGroundArmorsLevel2";NA;455
"Upgrade";"ZergMeleeWeaponsLevel2";NA;455
