"type";"unit_name";"on_building";"total_supply_lag";"supply"
"Unit";"Overlord";"Larva";13;0
"Building";"Hatchery";NA;17;0
"Building";"Extractor";NA;19;0
"Building";"SpawningPool";NA;19;0
"Unit";"Overlord";"Larva";22;0
"Unit";"Queen";"Hatchery";23;2
"Unit";"Zergling";"Larva";25;1
"Unit";"Zergling";"Larva";26;1
"Unit";"Queen";"Hatchery";27;2
"Unit";"Zergling";"Larva";29;1
"Unit";"Zergling";"Larva";30;1
"Unit";"Zergling";"Larva";31;1
"Unit";"Zergling";"Larva";32;1
"Building";"Hatchery";NA;37;0
"Unit";"Queen";"Hatchery";39;2
"Unit";"Overlord";"Larva";41;0
"Unit";"Overlord";"Larva";43;0
"Building";"CreepTumorQueen";NA;43;0
"Unit";"Overlord";"Larva";43;0
"Unit";"Zergling";"Larva";47;1
"Unit";"Zergling";"Larva";48;1
"Unit";"Queen";"Hatchery";51;2
"Unit";"Zergling";"Larva";53;1
"Unit";"Zergling";"Larva";54;1
"Building";"CreepTumor";NA;57;0
"Unit";"Zergling";"Larva";62;1
"Unit";"Zergling";"Larva";63;1
"Unit";"Queen";"Hatchery";64;2
"Building";"Extractor";NA;67;0
"Unit";"Overlord";"Larva";70;0
"Unit";"Queen";"Hatchery";70;2
"Unit";"Zergling";"Larva";84;1
"Unit";"Zergling";"Larva";85;1
"Unit";"Zergling";"Larva";86;1
"Unit";"Zergling";"Larva";87;1
"Unit";"Zergling";"Larva";88;1
"Unit";"Zergling";"Larva";89;1
"Unit";"Zergling";"Larva";90;1
"Unit";"Zergling";"Larva";91;1
"Unit";"Zergling";"Larva";92;1
"Unit";"Zergling";"Larva";93;1
"Unit";"Zergling";"Larva";94;1
"Unit";"Zergling";"Larva";95;1
"Unit";"Queen";"Hatchery";101;2
"Building";"Extractor";NA;103;0
"Building";"Spire";NA;105;0
"Unit";"Overlord";"Larva";106;0
"Building";"CreepTumorQueen";NA;106;0
"Building";"Extractor";NA;106;0
"Building";"BanelingNest";NA;106;0
"Unit";"Overlord";"Larva";106;0
"Unit";"Overlord";"Larva";108;0
"Unit";"Queen";"Hatchery";108;2
"Unit";"Overlord";"Larva";111;0
"Building";"Extractor";NA;120;0
"Building";"Extractor";NA;120;0
"Unit";"Zergling";"Larva";128;1
"Unit";"Zergling";"Larva";129;1
"Unit";"Zergling";"Larva";130;1
"Unit";"Zergling";"Larva";131;1
"Building";"CreepTumorQueen";NA;132;0
"Building";"CreepTumorQueen";NA;132;0
"Building";"CreepTumorQueen";NA;132;0
"Building";"CreepTumor";NA;132;0
"Unit";"Mutalisk";"Larva";132;2
"Unit";"Mutalisk";"Larva";134;2
"Unit";"Mutalisk";"Larva";136;2
"Unit";"Mutalisk";"Larva";138;2
"Unit";"Mutalisk";"Larva";140;2
"Unit";"Zergling";"Larva";143;1
"Unit";"Zergling";"Larva";144;1
"Building";"EvolutionChamber";NA;145;0
"Building";"EvolutionChamber";NA;145;0
"Unit";"Zergling";"Larva";145;1
"Unit";"Zergling";"Larva";146;1
"Unit";"Zergling";"Larva";147;1
"Unit";"Zergling";"Larva";148;1
"Unit";"Zergling";"Larva";149;1
"Unit";"Zergling";"Larva";150;1
"Building";"CreepTumor";NA;151;0
"Unit";"Overlord";"Larva";151;0
"Unit";"Overlord";"Larva";151;0
"Unit";"Overlord";"Larva";151;0
"Building";"CreepTumorQueen";NA;151;0
"Unit";"Baneling";"Zergling";151;0
"Unit";"Baneling";"Zergling";151;0
"Unit";"Baneling";"Zergling";151;0
"Unit";"Baneling";"Zergling";151;0
"Unit";"Baneling";"Zergling";151;0
"Unit";"Baneling";"Zergling";151;0
"Unit";"Zergling";"Larva";151;1
"Unit";"Zergling";"Larva";152;1
"Building";"CreepTumor";NA;153;0
"Building";"CreepTumor";NA;153;0
"Building";"Hatchery";NA;153;0
"Building";"CreepTumorQueen";NA;153;0
"Unit";"Overlord";"Larva";153;0
"Building";"CreepTumorQueen";NA;153;0
"Unit";"Overlord";"Larva";153;0
"Unit";"Zergling";"Larva";153;1
"Unit";"Zergling";"Larva";154;1
"Building";"CreepTumorQueen";NA;155;0
"Unit";"Zergling";"Larva";155;1
"Unit";"Zergling";"Larva";156;1
"Unit";"Zergling";"Larva";157;1
"Unit";"Zergling";"Larva";158;1
"Unit";"Zergling";"Larva";159;1
"Unit";"Zergling";"Larva";160;1
"Unit";"Zergling";"Larva";161;1
"Unit";"Zergling";"Larva";162;1
"Unit";"Zergling";"Larva";163;1
"Unit";"Zergling";"Larva";164;1
"Unit";"Zergling";"Larva";165;1
"Unit";"Zergling";"Larva";166;1
"Unit";"Zergling";"Larva";167;1
"Unit";"Zergling";"Larva";168;1
"Unit";"Zergling";"Larva";169;1
"Unit";"Zergling";"Larva";170;1
"Unit";"Mutalisk";"Larva";171;2
"Unit";"Mutalisk";"Larva";173;2
"Building";"CreepTumor";NA;178;0
"Building";"CreepTumor";NA;178;0
"Building";"CreepTumor";NA;178;0
"Unit";"Zergling";"Larva";184;1
"Unit";"Zergling";"Larva";185;1
"Unit";"Zergling";"Larva";186;1
"Unit";"Zergling";"Larva";187;1
"Unit";"Zergling";"Larva";188;1
"Unit";"Zergling";"Larva";189;1
"Unit";"Zergling";"Larva";190;1
"Unit";"Zergling";"Larva";191;1
"Unit";"Zergling";"Larva";192;1
"Unit";"Zergling";"Larva";193;1
"Unit";"Baneling";"Zergling";194;0
"Unit";"Baneling";"Zergling";194;0
"Unit";"Baneling";"Zergling";194;0
"Unit";"Baneling";"Zergling";194;0
"Building";"CreepTumor";NA;194;0
"Building";"CreepTumor";NA;194;0
"Building";"CreepTumor";NA;194;0
"Unit";"Zergling";"Larva";194;1
"Unit";"Zergling";"Larva";195;1
"Unit";"Zergling";"Larva";196;1
"Unit";"Zergling";"Larva";197;1
"Unit";"Zergling";"Larva";198;1
"Unit";"Zergling";"Larva";199;1
"Unit";"Zergling";"Larva";200;1
"Unit";"Zergling";"Larva";201;1
"Unit";"Zergling";"Larva";202;1
"Unit";"Zergling";"Larva";203;1
"Unit";"Zergling";"Larva";204;1
"Unit";"Zergling";"Larva";205;1
"Unit";"Zergling";"Larva";206;1
"Unit";"Zergling";"Larva";207;1
"Unit";"Zergling";"Larva";208;1
"Unit";"Zergling";"Larva";209;1
"Unit";"Zergling";"Larva";210;1
"Unit";"Zergling";"Larva";211;1
"Unit";"Zergling";"Larva";212;1
"Unit";"Zergling";"Larva";213;1
"Unit";"Zergling";"Larva";214;1
"Unit";"Zergling";"Larva";215;1
"Unit";"Zergling";"Larva";216;1
"Unit";"Zergling";"Larva";217;1
"Unit";"Baneling";"Zergling";218;0
"Unit";"Baneling";"Zergling";218;0
"Unit";"Baneling";"Zergling";218;0
"Unit";"Baneling";"Zergling";218;0
"Unit";"Baneling";"Zergling";218;0
"Building";"CreepTumor";NA;218;0
"Building";"CreepTumor";NA;218;0
"Building";"CreepTumor";NA;218;0
"Unit";"Overlord";"Larva";218;0
"Unit";"Zergling";"Larva";218;1
"Unit";"Zergling";"Larva";219;1
"Unit";"Zergling";"Larva";220;1
"Unit";"Zergling";"Larva";221;1
"Unit";"Zergling";"Larva";222;1
"Unit";"Zergling";"Larva";223;1
"Unit";"Zergling";"Larva";224;1
"Unit";"Zergling";"Larva";225;1
"Unit";"Zergling";"Larva";226;1
"Unit";"Zergling";"Larva";227;1
"Unit";"Zergling";"Larva";228;1
"Unit";"Zergling";"Larva";229;1
"Unit";"Zergling";"Larva";230;1
"Unit";"Zergling";"Larva";231;1
"Unit";"Zergling";"Larva";232;1
"Unit";"Zergling";"Larva";233;1
"Unit";"Zergling";"Larva";234;1
"Unit";"Zergling";"Larva";235;1
"Unit";"Zergling";"Larva";236;1
"Unit";"Zergling";"Larva";237;1
"Unit";"Zergling";"Larva";238;1
"Unit";"Zergling";"Larva";239;1
"Unit";"Zergling";"Larva";240;1
"Unit";"Zergling";"Larva";241;1
"Unit";"Zergling";"Larva";242;1
"Unit";"Zergling";"Larva";243;1
"Unit";"Zergling";"Larva";244;1
"Unit";"Zergling";"Larva";245;1
"Building";"Spire";NA;246;0
"Building";"SporeCrawler";NA;246;0
"Unit";"Queen";"Hatchery";246;2
"Unit";"Queen";"Hatchery";253;2
"Unit";"Overlord";"Larva";255;0
"Unit";"Baneling";"Zergling";263;0
"Unit";"Baneling";"Zergling";263;0
"Unit";"Baneling";"Zergling";263;0
"Unit";"Queen";"Hatchery";263;2
"Building";"Extractor";NA;270;0
"Unit";"Zergling";"Larva";270;1
"Unit";"Zergling";"Larva";271;1
"Unit";"Zergling";"Larva";272;1
"Unit";"Zergling";"Larva";273;1
"Unit";"Zergling";"Larva";274;1
"Unit";"Zergling";"Larva";275;1
"Unit";"Zergling";"Larva";276;1
"Unit";"Zergling";"Larva";277;1
"Unit";"Zergling";"Larva";278;1
"Unit";"Zergling";"Larva";279;1
"Unit";"Zergling";"Larva";280;1
"Unit";"Zergling";"Larva";281;1
"Unit";"Zergling";"Larva";282;1
"Unit";"Zergling";"Larva";283;1
"Unit";"Zergling";"Larva";284;1
"Unit";"Zergling";"Larva";285;1
"Unit";"Zergling";"Larva";286;1
"Unit";"Zergling";"Larva";287;1
"Unit";"Zergling";"Larva";288;1
"Unit";"Zergling";"Larva";289;1
"Unit";"Zergling";"Larva";290;1
"Unit";"Zergling";"Larva";291;1
"Unit";"Zergling";"Larva";292;1
"Unit";"Zergling";"Larva";293;1
"Unit";"Zergling";"Larva";294;1
"Unit";"Zergling";"Larva";295;1
"Unit";"Zergling";"Larva";296;1
"Unit";"Zergling";"Larva";297;1
"Unit";"Baneling";"Zergling";298;0
"Unit";"Baneling";"Zergling";298;0
"Unit";"Baneling";"Zergling";298;0
"Unit";"Baneling";"Zergling";298;0
"Unit";"Baneling";"Zergling";298;0
"Unit";"Baneling";"Zergling";298;0
"Unit";"Baneling";"Zergling";298;0
"Unit";"Baneling";"Zergling";298;0
"Unit";"Baneling";"Zergling";298;0
"Unit";"Baneling";"Zergling";298;0
"Unit";"Baneling";"Zergling";298;0
"Unit";"Baneling";"Zergling";298;0
"Unit";"Baneling";"Zergling";298;0
"Unit";"Baneling";"Zergling";298;0
"Unit";"Baneling";"Zergling";298;0
"Unit";"Baneling";"Zergling";298;0
"Unit";"Baneling";"Zergling";298;0
"Unit";"Baneling";"Zergling";298;0
"Building";"CreepTumor";NA;298;0
"Building";"CreepTumor";NA;298;0
"Building";"CreepTumor";NA;298;0
"Unit";"Mutalisk";"Larva";298;2
"Unit";"Overlord";"Larva";300;0
"Unit";"Overlord";"Larva";300;0
"Unit";"Overlord";"Larva";300;0
"Unit";"Overlord";"Larva";300;0
"Unit";"Overlord";"Larva";300;0
"Unit";"Baneling";"Zergling";300;0
"Unit";"Baneling";"Zergling";300;0
"Unit";"Baneling";"Zergling";300;0
"Unit";"Baneling";"Zergling";300;0
"Unit";"Baneling";"Zergling";300;0
"Unit";"Baneling";"Zergling";300;0
"Unit";"Baneling";"Zergling";300;0
"Building";"CreepTumorQueen";NA;300;0
"Building";"CreepTumorQueen";NA;300;0
"Building";"CreepTumorQueen";NA;300;0
"Building";"CreepTumorQueen";NA;300;0
"Building";"CreepTumorQueen";NA;300;0
"Unit";"Overlord";"Larva";300;0
"Unit";"Overlord";"Larva";300;0
"Unit";"Overlord";"Larva";300;0
"Unit";"Mutalisk";"Larva";300;2
"Unit";"Mutalisk";"Larva";302;2
"Unit";"Mutalisk";"Larva";304;2
"Unit";"Mutalisk";"Larva";306;2
"Unit";"Mutalisk";"Larva";308;2
"Unit";"Mutalisk";"Larva";310;2
"Unit";"Mutalisk";"Larva";312;2
"Unit";"Mutalisk";"Larva";314;2
"Building";"InfestationPit";NA;316;0
"Unit";"Zergling";"Larva";316;1
"Unit";"Zergling";"Larva";317;1
"Unit";"Zergling";"Larva";318;1
"Unit";"Zergling";"Larva";319;1
"Unit";"Zergling";"Larva";320;1
"Unit";"Zergling";"Larva";321;1
"Unit";"Zergling";"Larva";322;1
"Unit";"Zergling";"Larva";323;1
"Unit";"Zergling";"Larva";324;1
"Unit";"Zergling";"Larva";325;1
"Unit";"Zergling";"Larva";326;1
"Unit";"Zergling";"Larva";327;1
"Unit";"Zergling";"Larva";328;1
"Unit";"Zergling";"Larva";329;1
"Unit";"Zergling";"Larva";330;1
"Unit";"Zergling";"Larva";331;1
"Building";"CreepTumorQueen";NA;332;0
"Building";"CreepTumorQueen";NA;332;0
"Building";"CreepTumorQueen";NA;332;0
"Building";"CreepTumorQueen";NA;332;0
"Unit";"Mutalisk";"Larva";332;2
"Building";"CreepTumorQueen";NA;334;0
"Unit";"Mutalisk";"Larva";334;2
"Unit";"Mutalisk";"Larva";336;2
"Unit";"Mutalisk";"Larva";338;2
"Unit";"Mutalisk";"Larva";340;2
"Unit";"Mutalisk";"Larva";342;2
"Building";"CreepTumorQueen";NA;344;0
"Unit";"Queen";"Hatchery";344;2
"Unit";"Zergling";"Larva";346;1
"Unit";"Zergling";"Larva";347;1
"Unit";"Zergling";"Larva";348;1
"Unit";"Zergling";"Larva";349;1
"Unit";"Zergling";"Larva";350;1
"Unit";"Zergling";"Larva";351;1
"Unit";"Zergling";"Larva";352;1
"Unit";"Zergling";"Larva";353;1
"Unit";"Zergling";"Larva";354;1
"Unit";"Zergling";"Larva";355;1
"Building";"CreepTumor";NA;356;0
"Building";"CreepTumor";NA;356;0
"Building";"CreepTumorQueen";NA;356;0
"Building";"CreepTumorQueen";NA;356;0
"Building";"CreepTumorQueen";NA;356;0
"Unit";"Overlord";"Larva";356;0
"Unit";"Zergling";"Larva";356;1
"Unit";"Zergling";"Larva";357;1
"Unit";"Zergling";"Larva";358;1
"Unit";"Zergling";"Larva";359;1
"Unit";"Zergling";"Larva";360;1
"Unit";"Zergling";"Larva";361;1
"Unit";"Zergling";"Larva";362;1
"Unit";"Zergling";"Larva";363;1
"Unit";"Zergling";"Larva";364;1
"Unit";"Zergling";"Larva";365;1
"Unit";"Zergling";"Larva";366;1
"Unit";"Zergling";"Larva";367;1
"Unit";"Zergling";"Larva";368;1
"Unit";"Zergling";"Larva";369;1
"Unit";"Zergling";"Larva";370;1
"Unit";"Zergling";"Larva";371;1
"Unit";"Zergling";"Larva";372;1
"Unit";"Zergling";"Larva";373;1
"Unit";"Zergling";"Larva";374;1
"Unit";"Zergling";"Larva";375;1
"Unit";"Zergling";"Larva";376;1
"Unit";"Zergling";"Larva";377;1
"Unit";"Zergling";"Larva";378;1
"Unit";"Zergling";"Larva";379;1
"Unit";"Zergling";"Larva";380;1
"Unit";"Zergling";"Larva";381;1
"Unit";"Zergling";"Larva";382;1
"Unit";"Zergling";"Larva";383;1
"Unit";"Zergling";"Larva";384;1
"Unit";"Zergling";"Larva";385;1
"Unit";"Zergling";"Larva";386;1
"Unit";"Zergling";"Larva";387;1
"Unit";"Baneling";"Zergling";388;0
"Unit";"Baneling";"Zergling";388;0
"Unit";"Baneling";"Zergling";388;0
"Unit";"Baneling";"Zergling";388;0
"Unit";"Baneling";"Zergling";388;0
"Unit";"Baneling";"Zergling";388;0
"Unit";"Baneling";"Zergling";388;0
"Unit";"Baneling";"Zergling";388;0
"Unit";"Baneling";"Zergling";388;0
"Unit";"Baneling";"Zergling";388;0
"Unit";"Baneling";"Zergling";388;0
"Unit";"Baneling";"Zergling";388;0
"Unit";"Zergling";"Larva";388;1
"Unit";"Zergling";"Larva";389;1
"Unit";"Zergling";"Larva";390;1
"Unit";"Zergling";"Larva";391;1
"Unit";"Zergling";"Larva";392;1
"Unit";"Zergling";"Larva";393;1
"Unit";"Zergling";"Larva";394;1
"Unit";"Zergling";"Larva";395;1
"Unit";"Zergling";"Larva";396;1
"Unit";"Zergling";"Larva";397;1
"Unit";"Zergling";"Larva";398;1
"Unit";"Zergling";"Larva";399;1
"Unit";"Baneling";"Zergling";400;0
"Unit";"Baneling";"Zergling";400;0
"Unit";"Baneling";"Zergling";400;0
"Unit";"Baneling";"Zergling";400;0
"Unit";"Baneling";"Zergling";400;0
"Unit";"Baneling";"Zergling";400;0
"Unit";"Zergling";"Larva";400;1
"Unit";"Zergling";"Larva";401;1
"Unit";"Zergling";"Larva";402;1
"Unit";"Zergling";"Larva";403;1
"Unit";"Zergling";"Larva";404;1
"Unit";"Zergling";"Larva";405;1
"Unit";"Zergling";"Larva";406;1
"Unit";"Zergling";"Larva";407;1
"Unit";"Zergling";"Larva";408;1
"Unit";"Zergling";"Larva";409;1
"Unit";"Zergling";"Larva";410;1
"Unit";"Zergling";"Larva";411;1
"Unit";"Zergling";"Larva";412;1
"Unit";"Zergling";"Larva";413;1
"Unit";"Zergling";"Larva";414;1
"Unit";"Zergling";"Larva";415;1
"Unit";"Zergling";"Larva";416;1
"Unit";"Zergling";"Larva";417;1
"Unit";"Zergling";"Larva";418;1
"Unit";"Zergling";"Larva";419;1
"Unit";"Zergling";"Larva";420;1
"Unit";"Zergling";"Larva";421;1
"Unit";"Zergling";"Larva";428;1
"Unit";"Zergling";"Larva";429;1
"Unit";"Zergling";"Larva";430;1
"Unit";"Zergling";"Larva";431;1
"Unit";"Zergling";"Larva";432;1
"Unit";"Zergling";"Larva";433;1
"Unit";"Zergling";"Larva";434;1
"Unit";"Zergling";"Larva";435;1
"Building";"CreepTumor";NA;436;0
"Building";"UltraliskCavern";NA;436;0
"Unit";"Baneling";"Zergling";436;0
"Unit";"Baneling";"Zergling";436;0
"Unit";"Baneling";"Zergling";436;0
"Unit";"Baneling";"Zergling";436;0
"Unit";"Baneling";"Zergling";436;0
"Unit";"Baneling";"Zergling";436;0
"Unit";"Baneling";"Zergling";436;0
"Unit";"Baneling";"Zergling";436;0
"Unit";"Baneling";"Zergling";436;0
"Unit";"Baneling";"Zergling";436;0
"Unit";"Baneling";"Zergling";436;0
"Unit";"Baneling";"Zergling";436;0
"Unit";"Baneling";"Zergling";436;0
"Unit";"Baneling";"Zergling";436;0
"Unit";"Baneling";"Zergling";436;0
"Unit";"Baneling";"Zergling";436;0
"Unit";"Baneling";"Zergling";436;0
"Unit";"Baneling";"Zergling";436;0
"Unit";"Baneling";"Zergling";436;0
"Unit";"Baneling";"Zergling";436;0
"Unit";"Baneling";"Zergling";436;0
"Unit";"Baneling";"Zergling";436;0
"Unit";"Baneling";"Zergling";436;0
"Unit";"Baneling";"Zergling";436;0
"Unit";"Zergling";"Larva";436;1
"Unit";"Zergling";"Larva";437;1
"Unit";"Zergling";"Larva";438;1
"Unit";"Zergling";"Larva";439;1
"Unit";"Zergling";"Larva";440;1
"Unit";"Zergling";"Larva";441;1
"Unit";"Zergling";"Larva";442;1
"Unit";"Zergling";"Larva";443;1
"Unit";"Zergling";"Larva";444;1
"Unit";"Zergling";"Larva";445;1
"Unit";"Zergling";"Larva";446;1
"Unit";"Zergling";"Larva";447;1
"Unit";"Zergling";"Larva";448;1
"Unit";"Zergling";"Larva";449;1
"Unit";"Zergling";"Larva";450;1
"Unit";"Zergling";"Larva";451;1
"Unit";"Zergling";"Larva";452;1
"Unit";"Zergling";"Larva";453;1
"Unit";"Zergling";"Larva";454;1
"Unit";"Zergling";"Larva";455;1
"Unit";"Zergling";"Larva";456;1
"Unit";"Zergling";"Larva";457;1
"Unit";"Zergling";"Larva";458;1
"Unit";"Zergling";"Larva";459;1
"Unit";"Zergling";"Larva";460;1
"Unit";"Zergling";"Larva";461;1
"Unit";"Zergling";"Larva";462;1
"Unit";"Zergling";"Larva";463;1
"Unit";"Zergling";"Larva";464;1
"Unit";"Zergling";"Larva";465;1
"Unit";"Zergling";"Larva";466;1
"Unit";"Zergling";"Larva";467;1
"Unit";"Zergling";"Larva";468;1
"Unit";"Zergling";"Larva";469;1
"Unit";"Ultralisk";"Larva";470;6
"Unit";"Ultralisk";"Larva";476;6
"Unit";"Ultralisk";"Larva";482;6
"Unit";"Zergling";"Larva";488;1
"Unit";"Zergling";"Larva";489;1
"Unit";"Zergling";"Larva";490;1
"Unit";"Zergling";"Larva";491;1
"Unit";"Zergling";"Larva";492;1
"Unit";"Zergling";"Larva";493;1
"Unit";"Zergling";"Larva";494;1
"Unit";"Zergling";"Larva";495;1
"Unit";"Zergling";"Larva";496;1
"Unit";"Zergling";"Larva";497;1
"Unit";"Queen";"Hatchery";498;2
"Building";"Hatchery";NA;500;0
"Upgrade";"ChitinousPlating";"UltraliskCavern";500;0
"Unit";"Baneling";"Zergling";500;0
"Unit";"Baneling";"Zergling";500;0
"Unit";"Baneling";"Zergling";500;0
"Unit";"Baneling";"Zergling";500;0
"Unit";"Baneling";"Zergling";500;0
"Unit";"Ultralisk";"Larva";500;6
"Unit";"Ultralisk";"Larva";506;6
"Unit";"Zergling";"Larva";512;1
"Unit";"Zergling";"Larva";513;1
"Unit";"Zergling";"Larva";514;1
"Unit";"Zergling";"Larva";515;1
"Unit";"Zergling";"Larva";516;1
"Unit";"Zergling";"Larva";517;1
"Unit";"Zergling";"Larva";518;1
"Unit";"Zergling";"Larva";519;1
"Unit";"Zergling";"Larva";520;1
"Unit";"Zergling";"Larva";521;1
"Unit";"Zergling";"Larva";522;1
"Unit";"Zergling";"Larva";523;1
"Unit";"Zergling";"Larva";524;1
"Unit";"Zergling";"Larva";525;1
"Unit";"Zergling";"Larva";526;1
"Unit";"Zergling";"Larva";527;1
"Unit";"Zergling";"Larva";528;1
"Unit";"Zergling";"Larva";529;1
"Unit";"Zergling";"Larva";530;1
"Unit";"Zergling";"Larva";531;1
"Unit";"Zergling";"Larva";532;1
"Unit";"Zergling";"Larva";533;1
"Unit";"Zergling";"Larva";534;1
"Unit";"Zergling";"Larva";535;1
"Building";"Extractor";NA;536;0
"Unit";"Ultralisk";"Larva";536;6
"Unit";"Ultralisk";"Larva";542;6
"Unit";"Zergling";"Larva";548;1
"Unit";"Zergling";"Larva";549;1
"Unit";"Zergling";"Larva";550;1
"Unit";"Zergling";"Larva";551;1
"Unit";"Zergling";"Larva";552;1
"Unit";"Zergling";"Larva";553;1
"Unit";"Zergling";"Larva";554;1
"Unit";"Zergling";"Larva";555;1
"Unit";"Zergling";"Larva";556;1
"Unit";"Zergling";"Larva";557;1
"Unit";"Zergling";"Larva";558;1
"Unit";"Zergling";"Larva";559;1
"Unit";"Zergling";"Larva";560;1
"Unit";"Zergling";"Larva";561;1
"Unit";"Zergling";"Larva";562;1
"Unit";"Zergling";"Larva";563;1
"Unit";"Zergling";"Larva";564;1
"Unit";"Zergling";"Larva";565;1
"Unit";"Zergling";"Larva";566;1
"Unit";"Zergling";"Larva";567;1
"Building";"CreepTumorQueen";NA;568;0
"Building";"CreepTumorQueen";NA;568;0
"Upgrade";"Burrow";"Hatchery";568;0
"Unit";"Ultralisk";"Larva";568;6
"Unit";"Ultralisk";"Larva";574;6
"Unit";"Ultralisk";"Larva";580;6
"Unit";"Ultralisk";"Larva";586;6
"Building";"Spire";NA;592;0
"Building";"Extractor";NA;592;0
"Building";"Extractor";NA;592;0
"Unit";"Ultralisk";"Larva";592;6
"Unit";"Zergling";"Larva";598;1
"Unit";"Zergling";"Larva";599;1
"Unit";"Zergling";"Larva";600;1
"Unit";"Zergling";"Larva";601;1
"Unit";"Zergling";"Larva";602;1
"Unit";"Zergling";"Larva";603;1
"Unit";"Zergling";"Larva";604;1
"Unit";"Zergling";"Larva";605;1
"Unit";"Zergling";"Larva";606;1
"Unit";"Zergling";"Larva";607;1
"Unit";"Zergling";"Larva";608;1
"Unit";"Zergling";"Larva";609;1
"Unit";"Zergling";"Larva";610;1
"Unit";"Zergling";"Larva";611;1
"Unit";"Zergling";"Larva";612;1
"Unit";"Zergling";"Larva";613;1
"Unit";"Zergling";"Larva";614;1
"Unit";"Zergling";"Larva";615;1
"Unit";"Zergling";"Larva";616;1
"Unit";"Zergling";"Larva";617;1
"Unit";"Queen";"Hatchery";618;2
"Unit";"Queen";"Hatchery";620;2
"Unit";"Queen";"Hatchery";622;2
"Unit";"Queen";"Hatchery";624;2
"Unit";"Zergling";"Larva";626;1
"Unit";"Zergling";"Larva";627;1
"Unit";"Zergling";"Larva";628;1
"Unit";"Zergling";"Larva";629;1
"Unit";"Zergling";"Larva";630;1
"Unit";"Zergling";"Larva";631;1
"Unit";"Zergling";"Larva";632;1
"Unit";"Zergling";"Larva";633;1
"Unit";"Zergling";"Larva";634;1
"Unit";"Zergling";"Larva";635;1
"Unit";"Zergling";"Larva";636;1
"Unit";"Zergling";"Larva";637;1
"Unit";"Zergling";"Larva";638;1
"Unit";"Zergling";"Larva";639;1
"Unit";"Zergling";"Larva";640;1
"Unit";"Zergling";"Larva";641;1
"Unit";"Zergling";"Larva";642;1
"Unit";"Zergling";"Larva";643;1
"Unit";"Corruptor";"Larva";644;2
"Unit";"Corruptor";"Larva";646;2
"Unit";"Corruptor";"Larva";648;2
"Unit";"Corruptor";"Larva";650;2
"Unit";"Corruptor";"Larva";652;2
"Unit";"Corruptor";"Larva";654;2
"Unit";"Corruptor";"Larva";656;2
"Unit";"Corruptor";"Larva";658;2
"Unit";"Corruptor";"Larva";660;2
"Building";"Hatchery";NA;662;0
"Unit";"Baneling";"Zergling";662;0
"Unit";"Baneling";"Zergling";662;0
"Unit";"Baneling";"Zergling";662;0
"Unit";"Baneling";"Zergling";662;0
"Unit";"Corruptor";"Larva";662;2
"Building";"CreepTumor";NA;664;0
"Unit";"Baneling";"Zergling";664;0
"Unit";"Baneling";"Zergling";664;0
"Unit";"Baneling";"Zergling";664;0
"Building";"SpawningPool";NA;664;0
"Building";"CreepTumorQueen";NA;664;0
"Building";"CreepTumorQueen";NA;664;0
"Building";"CreepTumorQueen";NA;664;0
"Building";"CreepTumorQueen";NA;664;0
"Building";"CreepTumorQueen";NA;664;0
"Building";"Hatchery";NA;664;0
"Building";"CreepTumor";NA;664;0
"Building";"CreepTumor";NA;664;0
"Building";"CreepTumor";NA;664;0
"Building";"CreepTumor";NA;664;0
"Building";"CreepTumor";NA;664;0
"Unit";"Zergling";"Larva";664;1
"Unit";"Zergling";"Larva";665;1
"Unit";"Zergling";"Larva";666;1
"Unit";"Zergling";"Larva";667;1
"Unit";"Zergling";"Larva";668;1
"Unit";"Zergling";"Larva";669;1
"Unit";"Zergling";"Larva";670;1
"Unit";"Zergling";"Larva";671;1
"Unit";"Zergling";"Larva";672;1
"Unit";"Zergling";"Larva";673;1
"Unit";"Zergling";"Larva";674;1
"Unit";"Zergling";"Larva";675;1
"Unit";"Zergling";"Larva";676;1
"Unit";"Zergling";"Larva";677;1
"Unit";"Zergling";"Larva";678;1
"Unit";"Zergling";"Larva";679;1
"Unit";"Zergling";"Larva";680;1
"Unit";"Zergling";"Larva";681;1
"Unit";"Zergling";"Larva";682;1
"Unit";"Zergling";"Larva";683;1
"Unit";"Zergling";"Larva";684;1
"Unit";"Zergling";"Larva";685;1
"Unit";"Zergling";"Larva";686;1
"Unit";"Zergling";"Larva";687;1
"Unit";"Zergling";"Larva";688;1
"Unit";"Zergling";"Larva";689;1
"Unit";"Zergling";"Larva";690;1
"Unit";"Zergling";"Larva";691;1
"Unit";"Corruptor";"Larva";692;2
"Unit";"Corruptor";"Larva";694;2
"Building";"CreepTumorQueen";NA;696;0
"Building";"CreepTumorQueen";NA;696;0
"Unit";"Corruptor";"Larva";696;2
"Unit";"Corruptor";"Larva";698;2
"Unit";"Corruptor";"Larva";700;2
"Unit";"Corruptor";"Larva";702;2
"Unit";"Corruptor";"Larva";704;2
"Building";"Extractor";NA;706;0
"Unit";"Zergling";"Larva";709;1
"Unit";"Zergling";"Larva";710;1
"Unit";"Zergling";"Larva";711;1
"Unit";"Zergling";"Larva";712;1
"Unit";"Zergling";"Larva";713;1
"Unit";"Zergling";"Larva";714;1
"Unit";"Zergling";"Larva";715;1
"Unit";"Zergling";"Larva";716;1
"Building";"CreepTumor";NA;717;0
"Building";"CreepTumor";NA;717;0
"Building";"CreepTumor";NA;717;0
"Unit";"Zergling";"Larva";717;1
"Unit";"Zergling";"Larva";718;1
"Unit";"Zergling";"Larva";719;1
"Unit";"Zergling";"Larva";720;1
"Unit";"Zergling";"Larva";721;1
"Unit";"Zergling";"Larva";722;1
"Unit";"Zergling";"Larva";723;1
"Unit";"Zergling";"Larva";724;1
"Unit";"Zergling";"Larva";725;1
"Unit";"Zergling";"Larva";726;1
"Unit";"Zergling";"Larva";727;1
"Unit";"Zergling";"Larva";728;1
"Unit";"Zergling";"Larva";729;1
"Unit";"Zergling";"Larva";730;1
"Unit";"Zergling";"Larva";731;1
"Unit";"Zergling";"Larva";732;1
"Unit";"Zergling";"Larva";733;1
"Unit";"Zergling";"Larva";734;1
"Unit";"Zergling";"Larva";735;1
"Unit";"Zergling";"Larva";736;1
"Unit";"Zergling";"Larva";737;1
"Unit";"Zergling";"Larva";738;1
"Building";"UltraliskCavern";NA;739;0
"Unit";"Zergling";"Larva";739;1
"Unit";"Zergling";"Larva";740;1
"Unit";"Zergling";"Larva";741;1
"Unit";"Zergling";"Larva";742;1
"Unit";"Zergling";"Larva";743;1
"Unit";"Zergling";"Larva";744;1
"Unit";"Zergling";"Larva";745;1
"Unit";"Zergling";"Larva";746;1
"Unit";"Zergling";"Larva";747;1
"Unit";"Zergling";"Larva";748;1
"Unit";"Zergling";"Larva";749;1
"Unit";"Zergling";"Larva";750;1
"Unit";"Zergling";"Larva";751;1
"Unit";"Zergling";"Larva";752;1
"Unit";"Zergling";"Larva";753;1
"Unit";"Zergling";"Larva";754;1
"Unit";"Zergling";"Larva";755;1
"Unit";"Zergling";"Larva";756;1
"Unit";"Baneling";"Zergling";757;0
"Unit";"Baneling";"Zergling";757;0
"Unit";"Baneling";"Zergling";757;0
"Unit";"Baneling";"Zergling";757;0
"Unit";"Baneling";"Zergling";757;0
"Unit";"Baneling";"Zergling";757;0
"Building";"CreepTumorQueen";NA;757;0
"Unit";"Zergling";"Larva";757;1
"Unit";"Zergling";"Larva";758;1
"Unit";"Zergling";"Larva";759;1
"Unit";"Zergling";"Larva";760;1
"Unit";"Zergling";"Larva";761;1
"Unit";"Zergling";"Larva";762;1
"Unit";"Zergling";"Larva";763;1
"Unit";"Zergling";"Larva";764;1
"Building";"CreepTumorQueen";NA;765;0
"Unit";"Zergling";"Larva";765;1
"Unit";"Zergling";"Larva";766;1
"Unit";"Zergling";"Larva";767;1
"Unit";"Zergling";"Larva";768;1
"Unit";"Zergling";"Larva";769;1
"Unit";"Zergling";"Larva";770;1
"Unit";"Zergling";"Larva";771;1
"Unit";"Zergling";"Larva";772;1
"Unit";"Zergling";"Larva";773;1
"Unit";"Zergling";"Larva";774;1
"Unit";"Zergling";"Larva";775;1
"Unit";"Zergling";"Larva";776;1
"Unit";"Zergling";"Larva";777;1
"Unit";"Zergling";"Larva";778;1
"Unit";"Zergling";"Larva";779;1
"Unit";"Zergling";"Larva";780;1
"Unit";"Zergling";"Larva";781;1
"Unit";"Zergling";"Larva";782;1
"Unit";"Zergling";"Larva";783;1
"Unit";"Zergling";"Larva";784;1
"Unit";"Zergling";"Larva";785;1
"Unit";"Zergling";"Larva";786;1
"Unit";"Zergling";"Larva";787;1
"Unit";"Zergling";"Larva";788;1
"Unit";"Zergling";"Larva";789;1
"Unit";"Zergling";"Larva";790;1
"Unit";"Zergling";"Larva";791;1
"Unit";"Zergling";"Larva";792;1
"Unit";"Zergling";"Larva";793;1
"Unit";"Zergling";"Larva";794;1
"Unit";"Zergling";"Larva";795;1
"Unit";"Zergling";"Larva";796;1
"Unit";"Zergling";"Larva";797;1
"Unit";"Zergling";"Larva";798;1
"Unit";"Zergling";"Larva";799;1
"Unit";"Zergling";"Larva";800;1
"Unit";"Zergling";"Larva";801;1
"Unit";"Zergling";"Larva";802;1
"Unit";"Zergling";"Larva";803;1
"Unit";"Zergling";"Larva";804;1
"Building";"Spire";NA;805;0
"Unit";"Zergling";"Larva";805;1
"Unit";"Zergling";"Larva";806;1
"Unit";"Zergling";"Larva";807;1
"Unit";"Zergling";"Larva";808;1
"Unit";"Zergling";"Larva";809;1
"Unit";"Zergling";"Larva";810;1
"Unit";"Zergling";"Larva";811;1
"Unit";"Zergling";"Larva";812;1
"Unit";"Zergling";"Larva";813;1
"Unit";"Zergling";"Larva";814;1
"Unit";"Zergling";"Larva";815;1
"Unit";"Zergling";"Larva";816;1
"Unit";"Zergling";"Larva";817;1
"Unit";"Zergling";"Larva";818;1
"Unit";"Zergling";"Larva";819;1
"Unit";"Zergling";"Larva";820;1
"Unit";"Ultralisk";"Larva";821;6
"Unit";"Ultralisk";"Larva";827;6
"Unit";"Zergling";"Larva";833;1
"Unit";"Zergling";"Larva";834;1
"Unit";"Zergling";"Larva";835;1
"Unit";"Zergling";"Larva";836;1
"Unit";"Zergling";"Larva";837;1
"Unit";"Zergling";"Larva";838;1
"Unit";"Baneling";"Zergling";839;0
"Unit";"Baneling";"Zergling";839;0
"Unit";"Baneling";"Zergling";839;0
"Unit";"Baneling";"Zergling";839;0
"Unit";"Baneling";"Zergling";839;0
"Unit";"Baneling";"Zergling";839;0
"Unit";"Zergling";"Larva";839;1
"Unit";"Zergling";"Larva";840;1
"Unit";"Zergling";"Larva";841;1
"Unit";"Zergling";"Larva";842;1
"Unit";"Zergling";"Larva";843;1
"Unit";"Zergling";"Larva";844;1
"Building";"CreepTumor";NA;845;0
"Building";"CreepTumor";NA;845;0
"Building";"CreepTumor";NA;845;0
"Unit";"Infestor";"Larva";845;2
"Building";"CreepTumor";NA;847;0
"Building";"CreepTumorQueen";NA;847;0
"Unit";"Zergling";"Larva";847;1
"Unit";"Zergling";"Larva";848;1
"Unit";"Zergling";"Larva";849;1
"Unit";"Zergling";"Larva";850;1
"Unit";"Zergling";"Larva";851;1
"Unit";"Zergling";"Larva";852;1
"Unit";"Zergling";"Larva";853;1
"Unit";"Zergling";"Larva";854;1
"Unit";"Zergling";"Larva";855;1
"Unit";"Zergling";"Larva";856;1
"Building";"Hatchery";NA;857;0
"Unit";"Zergling";"Larva";857;1
"Unit";"Zergling";"Larva";858;1
"Unit";"Zergling";"Larva";859;1
"Unit";"Zergling";"Larva";860;1
"Unit";"Zergling";"Larva";861;1
"Unit";"Zergling";"Larva";862;1
"Unit";"Zergling";"Larva";863;1
"Unit";"Zergling";"Larva";864;1
"Unit";"Zergling";"Larva";865;1
"Unit";"Zergling";"Larva";866;1
"Unit";"Zergling";"Larva";867;1
"Unit";"Zergling";"Larva";868;1
"Unit";"Zergling";"Larva";869;1
"Unit";"Zergling";"Larva";870;1
"Unit";"Baneling";"Zergling";871;0
"Unit";"Baneling";"Zergling";871;0
"Unit";"Baneling";"Zergling";871;0
"Building";"Extractor";NA;872;0
"Building";"CreepTumor";NA;872;0
"Unit";"Zergling";"Larva";879;1
"Unit";"Zergling";"Larva";880;1
"Unit";"Zergling";"Larva";881;1
"Unit";"Zergling";"Larva";882;1
"Unit";"Zergling";"Larva";883;1
"Unit";"Zergling";"Larva";884;1
"Unit";"Zergling";"Larva";885;1
"Unit";"Zergling";"Larva";886;1
"Unit";"Zergling";"Larva";887;1
"Unit";"Zergling";"Larva";888;1
"Unit";"Zergling";"Larva";889;1
"Unit";"Zergling";"Larva";890;1
"Unit";"Zergling";"Larva";891;1
"Unit";"Zergling";"Larva";892;1
"Unit";"Zergling";"Larva";893;1
"Unit";"Zergling";"Larva";894;1
"Unit";"Zergling";"Larva";895;1
"Unit";"Zergling";"Larva";896;1
"Unit";"Zergling";"Larva";897;1
"Unit";"Zergling";"Larva";898;1
"Unit";"Zergling";"Larva";899;1
"Unit";"Zergling";"Larva";900;1
"Unit";"Zergling";"Larva";901;1
"Unit";"Zergling";"Larva";902;1
"Unit";"Zergling";"Larva";903;1
"Unit";"Zergling";"Larva";904;1
"Unit";"Zergling";"Larva";905;1
"Unit";"Zergling";"Larva";906;1
"Unit";"Zergling";"Larva";907;1
"Unit";"Zergling";"Larva";908;1
"Unit";"Zergling";"Larva";909;1
"Unit";"Zergling";"Larva";910;1
"Unit";"Zergling";"Larva";911;1
"Unit";"Zergling";"Larva";912;1
"Unit";"Zergling";"Larva";913;1
"Unit";"Zergling";"Larva";914;1
"Upgrade";"SprayZerg";NA;915;0
"Upgrade";"SprayZerg";NA;915;0
"Upgrade";"SprayZerg";NA;915;0
"Upgrade";"zerglingmovementspeed";NA;915;0
"Upgrade";"SprayZerg";NA;915;0
"Upgrade";"SprayZerg";NA;915;0
"Upgrade";"CentrificalHooks";NA;915;0
"Upgrade";"SprayZerg";NA;915;0
"Upgrade";"ZergMeleeWeaponsLevel1";NA;915;0
"Upgrade";"ZergGroundArmorsLevel1";NA;915;0
"Upgrade";"SprayZerg";NA;915;0
"Upgrade";"overlordspeed";NA;915;0
"Upgrade";"ZergFlyerWeaponsLevel1";NA;915;0
"Upgrade";"ZergMeleeWeaponsLevel2";NA;915;0
"Upgrade";"ZergGroundArmorsLevel2";NA;915;0
"Upgrade";"SprayZerg";NA;915;0
"Upgrade";"SprayZerg";NA;915;0
"Upgrade";"ZergMeleeWeaponsLevel3";NA;915;0
"Upgrade";"ZergGroundArmorsLevel3";NA;915;0
"Upgrade";"SprayZerg";NA;915;0
"Upgrade";"SprayZerg";NA;915;0
"Upgrade";"SprayZerg";NA;915;0
"Upgrade";"SprayZerg";NA;915;0
"Upgrade";"SprayZerg";NA;915;0
"Upgrade";"SprayZerg";NA;915;0
"Upgrade";"SprayZerg";NA;915;0
"Upgrade";"zerglingattackspeed";NA;915;0
"Upgrade";"SprayZerg";NA;915;0
"Upgrade";"SprayZerg";NA;915;0
"Upgrade";"SprayZerg";NA;915;0
"Upgrade";"SprayZerg";NA;915;0
