"type";"unit_name";"on_building";"total_supply_lag";"supply"
"Unit";"Overlord";"Larva";13;0
"Building";"Hatchery";NA;17;0
"Building";"Extractor";NA;19;0
"Building";"SpawningPool";NA;19;0
"Unit";"Overlord";"Larva";22;0
"Unit";"Queen";"Hatchery";23;2
"Unit";"Zergling";"Larva";25;1
"Unit";"Zergling";"Larva";26;1
"Unit";"Queen";"Hatchery";27;2
"Unit";"Zergling";"Larva";29;1
"Unit";"Zergling";"Larva";30;1
"Building";"Hatchery";NA;34;0
"Unit";"Queen";"Hatchery";34;2
"Unit";"Overlord";"Larva";37;0
"Building";"CreepTumorQueen";NA;43;0
"Unit";"Overlord";"Larva";49;0
"Building";"CreepTumor";NA;50;0
"Unit";"Queen";"Hatchery";50;2
"Building";"CreepTumorQueen";NA;55;0
"Unit";"Queen";"Hatchery";55;2
"Unit";"Overlord";"Larva";58;0
"Unit";"Queen";"Hatchery";58;2
"Building";"CreepTumorQueen";NA;60;0
"Unit";"Overlord";"Larva";62;0
"Unit";"Overlord";"Larva";64;0
"Building";"CreepTumor";NA;65;0
"Building";"CreepTumor";NA;65;0
"Building";"EvolutionChamber";NA;65;0
"Building";"EvolutionChamber";NA;65;0
"Building";"CreepTumorQueen";NA;66;0
"Building";"CreepTumorQueen";NA;67;0
"Building";"CreepTumor";NA;69;0
"Building";"SporeCrawler";NA;72;0
"Building";"SporeCrawler";NA;72;0
"Building";"SporeCrawler";NA;72;0
"Unit";"Overlord";"Larva";72;0
"Building";"CreepTumor";NA;73;0
"Unit";"Zergling";"Larva";73;1
"Unit";"Zergling";"Larva";74;1
"Unit";"Zergling";"Larva";75;1
"Unit";"Zergling";"Larva";76;1
"Unit";"Zergling";"Larva";77;1
"Unit";"Zergling";"Larva";78;1
"Building";"CreepTumor";NA;79;0
"Building";"CreepTumor";NA;79;0
"Building";"CreepTumor";NA;79;0
"Unit";"Zergling";"Larva";79;1
"Unit";"Zergling";"Larva";80;1
"Unit";"Zergling";"Larva";81;1
"Unit";"Zergling";"Larva";82;1
"Building";"CreepTumor";NA;84;0
"Unit";"Overlord";"Larva";84;0
"Building";"Extractor";NA;90;0
"Unit";"Queen";"Hatchery";90;2
"Building";"Extractor";NA;92;0
"Unit";"Queen";"Hatchery";92;2
"Unit";"Overlord";"Larva";94;0
"Building";"Extractor";NA;95;0
"Building";"Extractor";NA;96;0
"Building";"CreepTumor";NA;96;0
"Building";"CreepTumor";NA;96;0
"Building";"CreepTumor";NA;96;0
"Building";"Extractor";NA;100;0
"Building";"CreepTumorQueen";NA;100;0
"Unit";"Overlord";"Larva";100;0
"Building";"BanelingNest";NA;104;0
"Unit";"Overlord";"Larva";104;0
"Unit";"Overlord";"Larva";112;0
"Building";"CreepTumor";NA;114;0
"Unit";"Overlord";"Larva";114;0
"Unit";"Overlord";"Larva";114;0
"Unit";"Zergling";"Larva";114;1
"Unit";"Zergling";"Larva";115;1
"Unit";"Zergling";"Larva";116;1
"Unit";"Zergling";"Larva";117;1
"Building";"CreepTumor";NA;118;0
"Building";"CreepTumor";NA;118;0
"Unit";"Zergling";"Larva";118;1
"Unit";"Zergling";"Larva";119;1
"Unit";"Zergling";"Larva";120;1
"Unit";"Zergling";"Larva";121;1
"Unit";"Zergling";"Larva";122;1
"Unit";"Zergling";"Larva";123;1
"Unit";"Zergling";"Larva";124;1
"Unit";"Zergling";"Larva";125;1
"Building";"CreepTumor";NA;126;0
"Building";"Hatchery";NA;127;0
"Building";"SporeCrawler";NA;128;0
"Unit";"Zergling";"Larva";128;1
"Unit";"Zergling";"Larva";129;1
"Unit";"Zergling";"Larva";130;1
"Unit";"Zergling";"Larva";131;1
"Unit";"Zergling";"Larva";132;1
"Unit";"Zergling";"Larva";133;1
"Unit";"Zergling";"Larva";134;1
"Unit";"Zergling";"Larva";135;1
"Unit";"Zergling";"Larva";136;1
"Unit";"Zergling";"Larva";137;1
"Unit";"Zergling";"Larva";138;1
"Unit";"Zergling";"Larva";139;1
"Unit";"Overlord";"Larva";140;0
"Unit";"Zergling";"Larva";140;1
"Unit";"Zergling";"Larva";141;1
"Unit";"Zergling";"Larva";142;1
"Unit";"Zergling";"Larva";143;1
"Building";"CreepTumor";NA;144;0
"Building";"CreepTumor";NA;144;0
"Unit";"Baneling";"Zergling";144;0
"Unit";"Baneling";"Zergling";144;0
"Unit";"Baneling";"Zergling";144;0
"Unit";"Baneling";"Zergling";144;0
"Unit";"Baneling";"Zergling";144;0
"Unit";"Baneling";"Zergling";144;0
"Unit";"Baneling";"Zergling";144;0
"Unit";"Zergling";"Larva";144;1
"Unit";"Zergling";"Larva";145;1
"Unit";"Zergling";"Larva";146;1
"Unit";"Zergling";"Larva";147;1
"Unit";"Zergling";"Larva";148;1
"Unit";"Zergling";"Larva";149;1
"Unit";"Zergling";"Larva";150;1
"Unit";"Zergling";"Larva";151;1
"Unit";"Zergling";"Larva";152;1
"Unit";"Zergling";"Larva";153;1
"Unit";"Zergling";"Larva";154;1
"Unit";"Zergling";"Larva";155;1
"Unit";"Zergling";"Larva";156;1
"Unit";"Zergling";"Larva";157;1
"Unit";"Zergling";"Larva";158;1
"Unit";"Zergling";"Larva";159;1
"Unit";"Zergling";"Larva";160;1
"Unit";"Zergling";"Larva";161;1
"Building";"CreepTumor";NA;162;0
"Building";"HydraliskDen";NA;162;0
"Unit";"Zergling";"Larva";162;1
"Unit";"Zergling";"Larva";163;1
"Unit";"Zergling";"Larva";164;1
"Unit";"Zergling";"Larva";165;1
"Building";"CreepTumor";NA;166;0
"Unit";"Overlord";"Larva";166;0
"Building";"CreepTumorQueen";NA;166;0
"Unit";"Overlord";"Larva";166;0
"Building";"CreepTumorQueen";NA;166;0
"Unit";"Overlord";"Larva";166;0
"Unit";"Overlord";"Larva";166;0
"Unit";"Overlord";"Larva";166;0
"Unit";"Overlord";"Larva";166;0
"Unit";"Hydralisk";"Larva";166;2
"Unit";"Hydralisk";"Larva";168;2
"Unit";"Hydralisk";"Larva";170;2
"Unit";"Hydralisk";"Larva";172;2
"Unit";"Hydralisk";"Larva";174;2
"Building";"CreepTumorQueen";NA;176;0
"Building";"CreepTumorQueen";NA;176;0
"Building";"CreepTumorQueen";NA;176;0
"Building";"CreepTumor";NA;176;0
"Unit";"Hydralisk";"Larva";176;2
"Unit";"Hydralisk";"Larva";178;2
"Unit";"Hydralisk";"Larva";180;2
"Building";"CreepTumorQueen";NA;182;0
"Building";"CreepTumorQueen";NA;182;0
"Building";"CreepTumorQueen";NA;182;0
"Unit";"Hydralisk";"Larva";182;2
"Unit";"Hydralisk";"Larva";184;2
"Unit";"Baneling";"Zergling";186;0
"Unit";"Baneling";"Zergling";186;0
"Unit";"Zergling";"Larva";186;1
"Unit";"Zergling";"Larva";187;1
"Unit";"Zergling";"Larva";188;1
"Unit";"Zergling";"Larva";189;1
"Unit";"Zergling";"Larva";190;1
"Unit";"Zergling";"Larva";191;1
"Unit";"Zergling";"Larva";192;1
"Unit";"Zergling";"Larva";193;1
"Unit";"Zergling";"Larva";194;1
"Unit";"Zergling";"Larva";195;1
"Unit";"Zergling";"Larva";196;1
"Unit";"Zergling";"Larva";197;1
"Building";"CreepTumor";NA;198;0
"Unit";"Zergling";"Larva";198;1
"Unit";"Zergling";"Larva";199;1
"Unit";"Zergling";"Larva";200;1
"Unit";"Zergling";"Larva";201;1
"Unit";"Zergling";"Larva";202;1
"Unit";"Zergling";"Larva";203;1
"Building";"CreepTumor";NA;204;0
"Building";"CreepTumor";NA;204;0
"Unit";"Baneling";"Zergling";204;0
"Unit";"Zergling";"Larva";206;1
"Unit";"Zergling";"Larva";207;1
"Building";"InfestationPit";NA;208;0
"Unit";"Zergling";"Larva";208;1
"Unit";"Zergling";"Larva";209;1
"Unit";"Zergling";"Larva";210;1
"Unit";"Zergling";"Larva";211;1
"Building";"CreepTumorQueen";NA;212;0
"Unit";"Hydralisk";"Larva";212;2
"Unit";"Hydralisk";"Larva";214;2
"Unit";"Hydralisk";"Larva";216;2
"Building";"CreepTumorQueen";NA;218;0
"Building";"CreepTumorQueen";NA;218;0
"Building";"CreepTumorQueen";NA;218;0
"Building";"CreepTumorQueen";NA;222;0
"Building";"CreepTumor";NA;222;0
"Unit";"Zergling";"Larva";222;1
"Unit";"Zergling";"Larva";223;1
"Unit";"Zergling";"Larva";224;1
"Unit";"Zergling";"Larva";225;1
"Unit";"Zergling";"Larva";226;1
"Unit";"Zergling";"Larva";227;1
"Unit";"Zergling";"Larva";228;1
"Unit";"Zergling";"Larva";229;1
"Unit";"Zergling";"Larva";230;1
"Unit";"Zergling";"Larva";231;1
"Unit";"Zergling";"Larva";232;1
"Unit";"Zergling";"Larva";233;1
"Unit";"Zergling";"Larva";234;1
"Unit";"Zergling";"Larva";235;1
"Unit";"Zergling";"Larva";236;1
"Unit";"Zergling";"Larva";237;1
"Unit";"Zergling";"Larva";238;1
"Unit";"Zergling";"Larva";239;1
"Unit";"Zergling";"Larva";240;1
"Unit";"Zergling";"Larva";241;1
"Unit";"Zergling";"Larva";242;1
"Unit";"Zergling";"Larva";243;1
"Unit";"Overlord";"Larva";244;0
"Unit";"Zergling";"Larva";244;1
"Unit";"Zergling";"Larva";245;1
"Unit";"Zergling";"Larva";246;1
"Unit";"Zergling";"Larva";247;1
"Unit";"Zergling";"Larva";248;1
"Unit";"Zergling";"Larva";249;1
"Unit";"Zergling";"Larva";250;1
"Unit";"Zergling";"Larva";251;1
"Unit";"Overlord";"Larva";252;0
"Unit";"Baneling";"Zergling";252;0
"Unit";"Zergling";"Larva";252;1
"Unit";"Zergling";"Larva";253;1
"Unit";"Zergling";"Larva";254;1
"Unit";"Zergling";"Larva";255;1
"Unit";"Zergling";"Larva";256;1
"Unit";"Zergling";"Larva";257;1
"Unit";"Zergling";"Larva";258;1
"Unit";"Zergling";"Larva";259;1
"Building";"CreepTumor";NA;260;0
"Building";"CreepTumor";NA;260;0
"Building";"CreepTumor";NA;260;0
"Building";"CreepTumor";NA;260;0
"Building";"Extractor";NA;265;0
"Building";"Extractor";NA;265;0
"Unit";"Overlord";"Larva";265;0
"Unit";"Overlord";"Larva";265;0
"Unit";"Overlord";"Larva";265;0
"Unit";"Zergling";"Larva";265;1
"Unit";"Zergling";"Larva";266;1
"Unit";"Zergling";"Larva";267;1
"Unit";"Zergling";"Larva";268;1
"Unit";"Zergling";"Larva";269;1
"Unit";"Zergling";"Larva";270;1
"Unit";"Zergling";"Larva";271;1
"Unit";"Zergling";"Larva";272;1
"Unit";"Zergling";"Larva";273;1
"Unit";"Zergling";"Larva";274;1
"Unit";"Zergling";"Larva";275;1
"Unit";"Zergling";"Larva";276;1
"Unit";"Zergling";"Larva";277;1
"Unit";"Zergling";"Larva";278;1
"Unit";"Zergling";"Larva";279;1
"Unit";"Zergling";"Larva";280;1
"Unit";"Zergling";"Larva";281;1
"Unit";"Zergling";"Larva";282;1
"Unit";"Zergling";"Larva";283;1
"Unit";"Zergling";"Larva";284;1
"Unit";"Baneling";"Zergling";285;0
"Unit";"Baneling";"Zergling";285;0
"Unit";"Baneling";"Zergling";285;0
"Unit";"Baneling";"Zergling";285;0
"Unit";"Baneling";"Zergling";285;0
"Unit";"Baneling";"Zergling";285;0
"Unit";"Baneling";"Zergling";285;0
"Unit";"Baneling";"Zergling";285;0
"Unit";"Baneling";"Zergling";285;0
"Unit";"Baneling";"Zergling";285;0
"Unit";"Baneling";"Zergling";285;0
"Unit";"Baneling";"Zergling";285;0
"Unit";"Baneling";"Zergling";285;0
"Unit";"Baneling";"Zergling";285;0
"Unit";"Zergling";"Larva";285;1
"Unit";"Zergling";"Larva";286;1
"Unit";"Zergling";"Larva";287;1
"Unit";"Zergling";"Larva";288;1
"Unit";"Zergling";"Larva";289;1
"Unit";"Zergling";"Larva";290;1
"Unit";"Zergling";"Larva";291;1
"Unit";"Zergling";"Larva";292;1
"Unit";"Zergling";"Larva";293;1
"Unit";"Zergling";"Larva";294;1
"Unit";"Zergling";"Larva";295;1
"Unit";"Zergling";"Larva";296;1
"Unit";"Zergling";"Larva";297;1
"Unit";"Zergling";"Larva";298;1
"Unit";"Zergling";"Larva";299;1
"Unit";"Zergling";"Larva";300;1
"Unit";"Zergling";"Larva";301;1
"Unit";"Zergling";"Larva";302;1
"Unit";"Hydralisk";"Larva";303;2
"Unit";"Hydralisk";"Larva";305;2
"Unit";"Hydralisk";"Larva";307;2
"Unit";"Hydralisk";"Larva";309;2
"Unit";"Hydralisk";"Larva";311;2
"Unit";"Hydralisk";"Larva";313;2
"Unit";"Hydralisk";"Larva";315;2
"Unit";"Hydralisk";"Larva";317;2
"Unit";"Hydralisk";"Larva";319;2
"Unit";"Hydralisk";"Larva";321;2
"Unit";"Baneling";"Zergling";323;0
"Building";"UltraliskCavern";NA;323;0
"Unit";"Baneling";"Zergling";323;0
"Unit";"Baneling";"Zergling";323;0
"Unit";"Baneling";"Zergling";323;0
"Unit";"Baneling";"Zergling";323;0
"Unit";"Baneling";"Zergling";323;0
"Unit";"Baneling";"Zergling";323;0
"Unit";"Baneling";"Zergling";323;0
"Unit";"Hydralisk";"Larva";323;2
"Unit";"Hydralisk";"Larva";325;2
"Unit";"Hydralisk";"Larva";327;2
"Unit";"Hydralisk";"Larva";329;2
"Unit";"Hydralisk";"Larva";331;2
"Unit";"Hydralisk";"Larva";333;2
"Unit";"Hydralisk";"Larva";335;2
"Unit";"Hydralisk";"Larva";337;2
"Unit";"Hydralisk";"Larva";339;2
"Building";"CreepTumorQueen";NA;341;0
"Unit";"Queen";"Hatchery";341;2
"Building";"CreepTumorQueen";NA;343;0
"Unit";"Zergling";"Larva";343;1
"Unit";"Zergling";"Larva";344;1
"Unit";"Zergling";"Larva";345;1
"Unit";"Zergling";"Larva";346;1
"Unit";"Zergling";"Larva";347;1
"Unit";"Zergling";"Larva";348;1
"Unit";"Zergling";"Larva";349;1
"Unit";"Zergling";"Larva";350;1
"Unit";"Zergling";"Larva";351;1
"Unit";"Zergling";"Larva";352;1
"Unit";"Zergling";"Larva";353;1
"Unit";"Zergling";"Larva";354;1
"Unit";"Zergling";"Larva";355;1
"Unit";"Zergling";"Larva";356;1
"Building";"CreepTumorQueen";NA;357;0
"Unit";"Zergling";"Larva";357;1
"Unit";"Zergling";"Larva";358;1
"Unit";"Zergling";"Larva";359;1
"Unit";"Zergling";"Larva";360;1
"Unit";"Zergling";"Larva";361;1
"Unit";"Zergling";"Larva";362;1
"Unit";"Zergling";"Larva";363;1
"Unit";"Zergling";"Larva";364;1
"Unit";"Zergling";"Larva";365;1
"Unit";"Zergling";"Larva";366;1
"Unit";"Zergling";"Larva";367;1
"Unit";"Zergling";"Larva";368;1
"Unit";"Zergling";"Larva";369;1
"Unit";"Zergling";"Larva";370;1
"Building";"CreepTumor";NA;371;0
"Building";"CreepTumor";NA;371;0
"Building";"CreepTumor";NA;376;0
"Building";"CreepTumorQueen";NA;376;0
"Unit";"Viper";"Larva";376;3
"Unit";"Viper";"Larva";379;3
"Building";"CreepTumorQueen";NA;382;0
"Unit";"Viper";"Larva";382;3
"Unit";"Zergling";"Larva";385;1
"Unit";"Zergling";"Larva";386;1
"Unit";"Zergling";"Larva";387;1
"Unit";"Zergling";"Larva";388;1
"Unit";"Zergling";"Larva";389;1
"Unit";"Zergling";"Larva";390;1
"Unit";"Zergling";"Larva";391;1
"Unit";"Zergling";"Larva";392;1
"Unit";"Ultralisk";"Larva";393;6
"Upgrade";"ChitinousPlating";"UltraliskCavern";399;0
"Unit";"Ultralisk";"Larva";399;6
"Unit";"Ultralisk";"Larva";405;6
"Building";"Hatchery";NA;411;0
"Unit";"Zergling";"Larva";411;1
"Unit";"Zergling";"Larva";412;1
"Unit";"Zergling";"Larva";413;1
"Unit";"Zergling";"Larva";414;1
"Unit";"Ultralisk";"Larva";415;6
"Building";"CreepTumor";NA;421;0
"Unit";"Ultralisk";"Larva";421;6
"Building";"CreepTumorQueen";NA;427;0
"Unit";"Overlord";"Larva";427;0
"Unit";"Overlord";"Larva";427;0
"Building";"CreepTumorQueen";NA;427;0
"Building";"CreepTumorQueen";NA;427;0
"Building";"CreepTumorQueen";NA;427;0
"Building";"Extractor";NA;427;0
"Building";"CreepTumorQueen";NA;427;0
"Unit";"Overlord";"Larva";427;0
"Unit";"Overlord";"Larva";427;0
"Building";"CreepTumorQueen";NA;427;0
"Building";"CreepTumorQueen";NA;427;0
"Building";"CreepTumor";NA;427;0
"Unit";"Ultralisk";"Larva";427;6
"Unit";"Ultralisk";"Larva";433;6
"Building";"CreepTumor";NA;439;0
"Building";"CreepTumor";NA;439;0
"Building";"CreepTumor";NA;439;0
"Building";"CreepTumor";NA;439;0
"Unit";"Zergling";"Larva";439;1
"Unit";"Zergling";"Larva";440;1
"Unit";"Zergling";"Larva";441;1
"Unit";"Zergling";"Larva";442;1
"Unit";"Zergling";"Larva";443;1
"Unit";"Zergling";"Larva";444;1
"Unit";"Zergling";"Larva";445;1
"Unit";"Zergling";"Larva";446;1
"Unit";"Zergling";"Larva";447;1
"Unit";"Zergling";"Larva";448;1
"Unit";"Zergling";"Larva";449;1
"Unit";"Zergling";"Larva";450;1
"Unit";"Zergling";"Larva";451;1
"Unit";"Zergling";"Larva";452;1
"Unit";"Zergling";"Larva";453;1
"Unit";"Zergling";"Larva";454;1
"Unit";"Zergling";"Larva";455;1
"Unit";"Zergling";"Larva";456;1
"Unit";"Ultralisk";"Larva";457;6
"Unit";"Ultralisk";"Larva";463;6
"Unit";"Ultralisk";"Larva";469;6
"Unit";"Zergling";"Larva";475;1
"Unit";"Zergling";"Larva";476;1
"Unit";"Zergling";"Larva";477;1
"Unit";"Zergling";"Larva";478;1
"Unit";"Zergling";"Larva";479;1
"Unit";"Zergling";"Larva";480;1
"Unit";"Zergling";"Larva";481;1
"Unit";"Zergling";"Larva";482;1
"Unit";"Zergling";"Larva";483;1
"Unit";"Zergling";"Larva";484;1
"Unit";"Zergling";"Larva";485;1
"Unit";"Zergling";"Larva";486;1
"Building";"CreepTumorQueen";NA;487;0
"Unit";"Viper";"Larva";487;3
"Building";"CreepTumor";NA;497;0
"Building";"CreepTumorQueen";NA;497;0
"Building";"CreepTumor";NA;497;0
"Building";"CreepTumor";NA;497;0
"Building";"CreepTumor";NA;497;0
"Building";"CreepTumor";NA;497;0
"Building";"CreepTumorQueen";NA;497;0
"Building";"CreepTumorQueen";NA;497;0
"Unit";"Ultralisk";"Larva";497;6
"Unit";"Ultralisk";"Larva";503;6
"Unit";"Zergling";"Larva";509;1
"Unit";"Zergling";"Larva";510;1
"Unit";"Zergling";"Larva";511;1
"Unit";"Zergling";"Larva";512;1
"Unit";"Zergling";"Larva";513;1
"Unit";"Zergling";"Larva";514;1
"Unit";"Zergling";"Larva";515;1
"Unit";"Zergling";"Larva";516;1
"Unit";"Zergling";"Larva";517;1
"Unit";"Zergling";"Larva";518;1
"Unit";"Zergling";"Larva";519;1
"Unit";"Zergling";"Larva";520;1
"Unit";"Zergling";"Larva";521;1
"Unit";"Zergling";"Larva";522;1
"Building";"CreepTumor";NA;523;0
"Building";"CreepTumorQueen";NA;523;0
"Building";"CreepTumor";NA;523;0
"Building";"CreepTumor";NA;523;0
"Building";"CreepTumor";NA;523;0
"Building";"CreepTumorQueen";NA;523;0
"Unit";"Overlord";"Larva";523;0
"Building";"CreepTumor";NA;523;0
"Building";"CreepTumor";NA;523;0
"Building";"Spire";NA;523;0
"Building";"CreepTumor";NA;523;0
"Building";"CreepTumor";NA;523;0
"Building";"CreepTumor";NA;523;0
"Unit";"Viper";"Larva";523;3
"Building";"CreepTumor";NA;526;0
"Building";"CreepTumor";NA;526;0
"Building";"Extractor";NA;526;0
"Building";"Extractor";NA;526;0
"Unit";"Viper";"Larva";526;3
"Unit";"Viper";"Larva";529;3
"Building";"CreepTumorQueen";NA;532;0
"Building";"CreepTumorQueen";NA;532;0
"Building";"CreepTumorQueen";NA;532;0
"Building";"CreepTumor";NA;532;0
"Unit";"Baneling";"Zergling";532;0
"Unit";"Baneling";"Zergling";532;0
"Unit";"Baneling";"Zergling";532;0
"Unit";"Baneling";"Zergling";532;0
"Unit";"Baneling";"Zergling";532;0
"Unit";"Baneling";"Zergling";532;0
"Unit";"Baneling";"Zergling";532;0
"Unit";"Baneling";"Zergling";532;0
"Unit";"Baneling";"Zergling";532;0
"Unit";"Baneling";"Zergling";532;0
"Unit";"Baneling";"Zergling";532;0
"Unit";"Baneling";"Zergling";532;0
"Unit";"Baneling";"Zergling";532;0
"Unit";"Baneling";"Zergling";532;0
"Unit";"Ultralisk";"Larva";532;6
"Unit";"Ultralisk";"Larva";538;6
"Unit";"Zergling";"Larva";544;1
"Unit";"Zergling";"Larva";545;1
"Unit";"Zergling";"Larva";546;1
"Unit";"Zergling";"Larva";547;1
"Unit";"Zergling";"Larva";548;1
"Unit";"Zergling";"Larva";549;1
"Unit";"Zergling";"Larva";550;1
"Unit";"Zergling";"Larva";551;1
"Unit";"Zergling";"Larva";552;1
"Unit";"Zergling";"Larva";553;1
"Unit";"Zergling";"Larva";554;1
"Unit";"Zergling";"Larva";555;1
"Unit";"Zergling";"Larva";556;1
"Unit";"Zergling";"Larva";557;1
"Unit";"Zergling";"Larva";558;1
"Unit";"Zergling";"Larva";559;1
"Unit";"Zergling";"Larva";560;1
"Unit";"Zergling";"Larva";561;1
"Unit";"Zergling";"Larva";562;1
"Unit";"Zergling";"Larva";563;1
"Unit";"Zergling";"Larva";564;1
"Unit";"Zergling";"Larva";565;1
"Unit";"Zergling";"Larva";566;1
"Unit";"Zergling";"Larva";567;1
"Unit";"Zergling";"Larva";568;1
"Unit";"Zergling";"Larva";569;1
"Unit";"Zergling";"Larva";570;1
"Unit";"Zergling";"Larva";571;1
"Unit";"Zergling";"Larva";572;1
"Unit";"Zergling";"Larva";573;1
"Unit";"Zergling";"Larva";574;1
"Unit";"Zergling";"Larva";575;1
"Unit";"Zergling";"Larva";576;1
"Unit";"Zergling";"Larva";577;1
"Unit";"Zergling";"Larva";578;1
"Unit";"Zergling";"Larva";579;1
"Unit";"Zergling";"Larva";580;1
"Unit";"Zergling";"Larva";581;1
"Unit";"Zergling";"Larva";582;1
"Unit";"Zergling";"Larva";583;1
"Building";"CreepTumor";NA;584;0
"Building";"CreepTumorQueen";NA;584;0
"Building";"CreepTumorQueen";NA;584;0
"Building";"CreepTumorQueen";NA;584;0
"Unit";"Ultralisk";"Larva";584;6
"Unit";"Ultralisk";"Larva";590;6
"Unit";"Ultralisk";"Larva";596;6
"Unit";"Ultralisk";"Larva";602;6
"Unit";"Zergling";"Larva";608;1
"Unit";"Zergling";"Larva";609;1
"Unit";"Zergling";"Larva";610;1
"Unit";"Zergling";"Larva";611;1
"Unit";"Zergling";"Larva";612;1
"Unit";"Zergling";"Larva";613;1
"Unit";"Zergling";"Larva";614;1
"Unit";"Zergling";"Larva";615;1
"Unit";"Zergling";"Larva";616;1
"Unit";"Zergling";"Larva";617;1
"Unit";"Zergling";"Larva";618;1
"Unit";"Zergling";"Larva";619;1
"Unit";"Zergling";"Larva";620;1
"Unit";"Zergling";"Larva";621;1
"Unit";"Zergling";"Larva";622;1
"Unit";"Zergling";"Larva";623;1
"Unit";"Zergling";"Larva";624;1
"Unit";"Zergling";"Larva";625;1
"Unit";"Zergling";"Larva";626;1
"Unit";"Zergling";"Larva";627;1
"Unit";"Zergling";"Larva";628;1
"Unit";"Zergling";"Larva";629;1
"Building";"CreepTumorQueen";NA;630;0
"Unit";"Queen";"Hatchery";630;2
"Unit";"Queen";"Hatchery";632;2
"Unit";"Queen";"Hatchery";634;2
"Building";"CreepTumorQueen";NA;636;0
"Building";"Extractor";NA;636;0
"Building";"CreepTumor";NA;636;0
"Building";"CreepTumor";NA;636;0
"Building";"CreepTumor";NA;636;0
"Unit";"Zergling";"Larva";636;1
"Unit";"Zergling";"Larva";637;1
"Unit";"Zergling";"Larva";638;1
"Unit";"Zergling";"Larva";639;1
"Unit";"Zergling";"Larva";640;1
"Unit";"Zergling";"Larva";641;1
"Unit";"Baneling";"Zergling";642;0
"Unit";"Baneling";"Zergling";642;0
"Unit";"Baneling";"Zergling";642;0
"Unit";"Baneling";"Zergling";642;0
"Unit";"Baneling";"Zergling";642;0
"Building";"Hatchery";NA;642;0
"Unit";"Baneling";"Zergling";642;0
"Unit";"Baneling";"Zergling";642;0
"Unit";"Baneling";"Zergling";642;0
"Building";"CreepTumor";NA;642;0
"Building";"CreepTumorQueen";NA;642;0
"Building";"Hatchery";NA;642;0
"Building";"CreepTumor";NA;642;0
"Building";"CreepTumor";NA;642;0
"Unit";"Hydralisk";"Larva";642;2
"Unit";"Hydralisk";"Larva";644;2
"Unit";"Hydralisk";"Larva";646;2
"Unit";"Hydralisk";"Larva";648;2
"Unit";"Hydralisk";"Larva";650;2
"Unit";"Hydralisk";"Larva";652;2
"Unit";"Hydralisk";"Larva";654;2
"Unit";"Hydralisk";"Larva";656;2
"Unit";"Hydralisk";"Larva";658;2
"Unit";"Hydralisk";"Larva";660;2
"Unit";"Hydralisk";"Larva";662;2
"Unit";"Hydralisk";"Larva";664;2
"Unit";"Zergling";"Larva";666;1
"Unit";"Zergling";"Larva";667;1
"Unit";"Zergling";"Larva";668;1
"Unit";"Zergling";"Larva";669;1
"Unit";"Zergling";"Larva";670;1
"Unit";"Zergling";"Larva";671;1
"Unit";"Zergling";"Larva";672;1
"Unit";"Zergling";"Larva";673;1
"Unit";"Zergling";"Larva";674;1
"Unit";"Zergling";"Larva";675;1
"Unit";"Zergling";"Larva";676;1
"Unit";"Zergling";"Larva";677;1
"Unit";"Zergling";"Larva";678;1
"Unit";"Zergling";"Larva";679;1
"Unit";"Zergling";"Larva";680;1
"Unit";"Zergling";"Larva";681;1
"Unit";"Zergling";"Larva";682;1
"Unit";"Zergling";"Larva";683;1
"Unit";"Zergling";"Larva";684;1
"Unit";"Zergling";"Larva";685;1
"Unit";"Zergling";"Larva";686;1
"Unit";"Zergling";"Larva";687;1
"Unit";"Hydralisk";"Larva";688;2
"Unit";"Hydralisk";"Larva";690;2
"Unit";"Hydralisk";"Larva";692;2
"Unit";"Hydralisk";"Larva";694;2
"Unit";"Viper";"Larva";696;3
"Unit";"Viper";"Larva";699;3
"Unit";"Viper";"Larva";702;3
"Unit";"Viper";"Larva";705;3
"Building";"CreepTumor";NA;708;0
"Building";"CreepTumor";NA;708;0
"Unit";"Baneling";"Zergling";708;0
"Unit";"Baneling";"Zergling";708;0
"Unit";"Baneling";"Zergling";708;0
"Unit";"Baneling";"Zergling";708;0
"Unit";"Baneling";"Zergling";708;0
"Unit";"Baneling";"Zergling";708;0
"Unit";"Baneling";"Zergling";708;0
"Unit";"Baneling";"Zergling";708;0
"Unit";"Baneling";"Zergling";708;0
"Unit";"Hydralisk";"Larva";708;2
"Unit";"Hydralisk";"Larva";710;2
"Unit";"Hydralisk";"Larva";712;2
"Unit";"Hydralisk";"Larva";714;2
"Unit";"Hydralisk";"Larva";716;2
"Unit";"Hydralisk";"Larva";718;2
"Unit";"Zergling";"Larva";720;1
"Unit";"Zergling";"Larva";721;1
"Unit";"Zergling";"Larva";722;1
"Unit";"Zergling";"Larva";723;1
"Unit";"Zergling";"Larva";724;1
"Unit";"Zergling";"Larva";725;1
"Unit";"Zergling";"Larva";726;1
"Unit";"Zergling";"Larva";727;1
"Unit";"Zergling";"Larva";728;1
"Unit";"Zergling";"Larva";729;1
"Unit";"Zergling";"Larva";730;1
"Unit";"Zergling";"Larva";731;1
"Unit";"Zergling";"Larva";732;1
"Unit";"Zergling";"Larva";733;1
"Unit";"Zergling";"Larva";734;1
"Unit";"Zergling";"Larva";735;1
"Unit";"Zergling";"Larva";736;1
"Unit";"Zergling";"Larva";737;1
"Unit";"Zergling";"Larva";738;1
"Unit";"Zergling";"Larva";739;1
"Unit";"Zergling";"Larva";740;1
"Unit";"Zergling";"Larva";741;1
"Unit";"Zergling";"Larva";742;1
"Unit";"Zergling";"Larva";743;1
"Unit";"Zergling";"Larva";744;1
"Unit";"Zergling";"Larva";745;1
"Unit";"Zergling";"Larva";746;1
"Unit";"Zergling";"Larva";747;1
"Unit";"Zergling";"Larva";748;1
"Unit";"Zergling";"Larva";749;1
"Unit";"Zergling";"Larva";750;1
"Unit";"Zergling";"Larva";751;1
"Unit";"Zergling";"Larva";752;1
"Unit";"Zergling";"Larva";753;1
"Unit";"Zergling";"Larva";754;1
"Unit";"Zergling";"Larva";755;1
"Unit";"Ultralisk";"Larva";756;6
"Unit";"Ultralisk";"Larva";762;6
"Building";"CreepTumorQueen";NA;768;0
"Building";"CreepTumorQueen";NA;768;0
"Building";"CreepTumorQueen";NA;768;0
"Building";"CreepTumorQueen";NA;768;0
"Unit";"Hydralisk";"Larva";768;2
"Unit";"Hydralisk";"Larva";770;2
"Unit";"Hydralisk";"Larva";772;2
"Unit";"Hydralisk";"Larva";774;2
"Unit";"Hydralisk";"Larva";776;2
"Unit";"Hydralisk";"Larva";778;2
"Building";"CreepTumorQueen";NA;780;0
"Building";"CreepTumorQueen";NA;780;0
"Building";"Extractor";NA;780;0
"Building";"Extractor";NA;780;0
"Unit";"Queen";"Hatchery";780;2
"Unit";"Queen";"Hatchery";782;2
"Unit";"Baneling";"Zergling";784;0
"Unit";"Baneling";"Zergling";784;0
"Unit";"Baneling";"Zergling";784;0
"Unit";"Baneling";"Zergling";784;0
"Unit";"Baneling";"Zergling";784;0
"Unit";"Baneling";"Zergling";784;0
"Unit";"Hydralisk";"Larva";784;2
"Unit";"Hydralisk";"Larva";786;2
"Unit";"Hydralisk";"Larva";788;2
"Unit";"Hydralisk";"Larva";790;2
"Building";"Hatchery";NA;792;0
"Unit";"Hydralisk";"Larva";792;2
"Unit";"Hydralisk";"Larva";794;2
"Unit";"Hydralisk";"Larva";796;2
"Unit";"Hydralisk";"Larva";798;2
"Unit";"Hydralisk";"Larva";800;2
"Building";"CreepTumor";NA;802;0
"Building";"CreepTumorQueen";NA;802;0
"Building";"CreepTumor";NA;802;0
"Building";"CreepTumor";NA;802;0
"Unit";"Zergling";"Larva";802;1
"Unit";"Zergling";"Larva";803;1
"Unit";"Zergling";"Larva";804;1
"Unit";"Zergling";"Larva";805;1
"Unit";"Zergling";"Larva";806;1
"Unit";"Zergling";"Larva";807;1
"Unit";"Zergling";"Larva";808;1
"Unit";"Zergling";"Larva";809;1
"Unit";"Zergling";"Larva";810;1
"Unit";"Zergling";"Larva";811;1
"Building";"Hatchery";NA;812;0
"Building";"CreepTumor";NA;812;0
"Building";"CreepTumor";NA;812;0
"Upgrade";"Burrow";"Hatchery";812;0
"Unit";"Hydralisk";"Larva";812;2
"Unit";"Hydralisk";"Larva";814;2
"Unit";"Hydralisk";"Larva";816;2
"Unit";"Hydralisk";"Larva";818;2
"Unit";"Hydralisk";"Larva";820;2
"Unit";"Hydralisk";"Larva";822;2
"Unit";"Hydralisk";"Larva";824;2
"Unit";"Hydralisk";"Larva";826;2
"Unit";"Hydralisk";"Larva";828;2
"Unit";"Hydralisk";"Larva";830;2
"Unit";"Hydralisk";"Larva";832;2
"Unit";"Hydralisk";"Larva";834;2
"Unit";"Hydralisk";"Larva";836;2
"Unit";"Hydralisk";"Larva";838;2
"Unit";"Hydralisk";"Larva";840;2
"Unit";"Hydralisk";"Larva";842;2
"Building";"CreepTumor";NA;844;0
"Building";"CreepTumor";NA;844;0
"Unit";"Zergling";"Larva";844;1
"Unit";"Zergling";"Larva";845;1
"Upgrade";"SprayZerg";NA;846;0
"Upgrade";"SprayZerg";NA;846;0
"Upgrade";"SprayZerg";NA;846;0
"Upgrade";"zerglingmovementspeed";NA;846;0
"Upgrade";"SprayZerg";NA;846;0
"Upgrade";"SprayZerg";NA;846;0
"Upgrade";"overlordspeed";NA;846;0
"Upgrade";"ZergGroundArmorsLevel1";NA;846;0
"Upgrade";"ZergMissileWeaponsLevel1";NA;846;0
"Upgrade";"SprayZerg";NA;846;0
"Upgrade";"CentrificalHooks";NA;846;0
"Upgrade";"EvolveMuscularAugments";NA;846;0
"Upgrade";"ZergGroundArmorsLevel2";NA;846;0
"Upgrade";"ZergMissileWeaponsLevel2";NA;846;0
"Upgrade";"ZergMeleeWeaponsLevel1";NA;846;0
"Upgrade";"SprayZerg";NA;846;0
"Upgrade";"SprayZerg";NA;846;0
"Upgrade";"ZergMeleeWeaponsLevel2";NA;846;0
"Upgrade";"ZergGroundArmorsLevel3";NA;846;0
"Upgrade";"zerglingattackspeed";NA;846;0
"Upgrade";"ZergMissileWeaponsLevel3";NA;846;0
"Upgrade";"SprayZerg";NA;846;0
"Upgrade";"ZergMeleeWeaponsLevel3";NA;846;0
"Upgrade";"SprayZerg";NA;846;0
"Upgrade";"ZergFlyerArmorsLevel1";NA;846;0
"Upgrade";"SprayZerg";NA;846;0
"Upgrade";"SprayZerg";NA;846;0
"Upgrade";"SprayZerg";NA;846;0
"Upgrade";"SprayZerg";NA;846;0
"Upgrade";"SprayZerg";NA;846;0
"Upgrade";"SprayZerg";NA;846;0
"Upgrade";"SprayZerg";NA;846;0
