"type";"unit_name";"on_building";"total_supply_lag";"supply"
"Unit";"Overlord";"Larva";13;0
"Building";"Hatchery";NA;17;0
"Building";"Extractor";NA;19;0
"Building";"SpawningPool";NA;19;0
"Unit";"Overlord";"Larva";22;0
"Unit";"Queen";"Hatchery";23;2
"Unit";"Queen";"Hatchery";25;2
"Unit";"Zergling";"Larva";27;1
"Unit";"Zergling";"Larva";28;1
"Unit";"Zergling";"Larva";29;1
"Unit";"Zergling";"Larva";30;1
"Unit";"Queen";"Hatchery";36;2
"Unit";"Overlord";"Larva";38;0
"Unit";"Overlord";"Larva";46;0
"Building";"CreepTumorQueen";NA;46;0
"Unit";"Overlord";"Larva";46;0
"Building";"Hatchery";NA;46;0
"Unit";"Queen";"Hatchery";49;2
"Unit";"Queen";"Hatchery";51;2
"Unit";"Zergling";"Larva";53;1
"Unit";"Zergling";"Larva";54;1
"Unit";"Zergling";"Larva";55;1
"Unit";"Zergling";"Larva";56;1
"Unit";"Zergling";"Larva";57;1
"Unit";"Zergling";"Larva";58;1
"Unit";"Zergling";"Larva";59;1
"Unit";"Zergling";"Larva";60;1
"Unit";"Overlord";"Larva";61;0
"Unit";"Zergling";"Larva";61;1
"Unit";"Zergling";"Larva";62;1
"Unit";"Zergling";"Larva";63;1
"Unit";"Zergling";"Larva";64;1
"Unit";"Overlord";"Larva";65;0
"Unit";"Zergling";"Larva";68;1
"Unit";"Zergling";"Larva";69;1
"Unit";"Zergling";"Larva";70;1
"Unit";"Zergling";"Larva";71;1
"Unit";"Queen";"Hatchery";72;2
"Unit";"Overlord";"Larva";74;0
"Unit";"Queen";"Hatchery";74;2
"Building";"CreepTumorQueen";NA;77;0
"Unit";"Overlord";"Larva";77;0
"Building";"EvolutionChamber";NA;81;0
"Building";"EvolutionChamber";NA;81;0
"Building";"CreepTumor";NA;85;0
"Building";"CreepTumorQueen";NA;87;0
"Building";"CreepTumorQueen";NA;87;0
"Unit";"Queen";"Hatchery";90;2
"Building";"CreepTumor";NA;92;0
"Building";"CreepTumorQueen";NA;92;0
"Building";"CreepTumorQueen";NA;92;0
"Unit";"Overlord";"Larva";92;0
"Building";"CreepTumor";NA;94;0
"Building";"CreepTumor";NA;94;0
"Unit";"Overlord";"Larva";94;0
"Unit";"Overlord";"Larva";94;0
"Building";"RoachWarren";NA;95;0
"Unit";"Overlord";"Larva";100;0
"Building";"Extractor";NA;100;0
"Building";"Extractor";NA;100;0
"Building";"Extractor";NA;100;0
"Building";"Extractor";NA;100;0
"Unit";"Overlord";"Larva";100;0
"Unit";"Queen";"Hatchery";100;2
"Unit";"Zergling";"Larva";102;1
"Unit";"Zergling";"Larva";103;1
"Unit";"Zergling";"Larva";104;1
"Unit";"Zergling";"Larva";105;1
"Building";"CreepTumor";NA;106;0
"Building";"CreepTumor";NA;106;0
"Building";"Extractor";NA;106;0
"Unit";"Queen";"Hatchery";106;2
"Building";"CreepTumorQueen";NA;108;0
"Unit";"Zergling";"Larva";108;1
"Unit";"Zergling";"Larva";109;1
"Unit";"Zergling";"Larva";110;1
"Unit";"Zergling";"Larva";111;1
"Unit";"Zergling";"Larva";112;1
"Unit";"Zergling";"Larva";113;1
"Unit";"Zergling";"Larva";114;1
"Unit";"Zergling";"Larva";115;1
"Unit";"Zergling";"Larva";116;1
"Unit";"Zergling";"Larva";117;1
"Unit";"Zergling";"Larva";118;1
"Unit";"Zergling";"Larva";119;1
"Unit";"Roach";"Larva";132;2
"Unit";"Roach";"Larva";134;2
"Building";"CreepTumorQueen";NA;136;0
"Building";"CreepTumorQueen";NA;136;0
"Unit";"Roach";"Larva";148;2
"Building";"CreepTumor";NA;158;0
"Building";"CreepTumor";NA;158;0
"Building";"CreepTumor";NA;158;0
"Building";"CreepTumor";NA;158;0
"Building";"CreepTumor";NA;158;0
"Building";"CreepTumor";NA;158;0
"Unit";"Roach";"Larva";160;2
"Unit";"Roach";"Larva";162;2
"Unit";"Roach";"Larva";164;2
"Unit";"Roach";"Larva";166;2
"Unit";"Roach";"Larva";168;2
"Unit";"Roach";"Larva";170;2
"Unit";"Roach";"Larva";172;2
"Upgrade";"GlialReconstitution";"RoachWarren";174;0
"Unit";"Roach";"Larva";174;2
"Unit";"Roach";"Larva";176;2
"Unit";"Roach";"Larva";178;2
"Building";"CreepTumorQueen";NA;180;0
"Building";"CreepTumorQueen";NA;180;0
"Building";"CreepTumorQueen";NA;180;0
"Building";"Hatchery";NA;180;0
"Unit";"Overlord";"Larva";187;0
"Unit";"Overlord";"Larva";187;0
"Unit";"Overlord";"Larva";187;0
"Building";"InfestationPit";NA;187;0
"Building";"SporeCrawler";NA;187;0
"Building";"CreepTumor";NA;187;0
"Unit";"Overlord";"Larva";187;0
"Unit";"Overlord";"Larva";187;0
"Building";"SporeCrawler";NA;187;0
"Unit";"Roach";"Larva";187;2
"Unit";"Roach";"Larva";189;2
"Unit";"Roach";"Larva";191;2
"Building";"SporeCrawler";NA;193;0
"Building";"CreepTumor";NA;193;0
"Unit";"Roach";"Larva";193;2
"Unit";"Roach";"Larva";195;2
"Unit";"Roach";"Larva";197;2
"Unit";"Roach";"Larva";199;2
"Unit";"Roach";"Larva";201;2
"Unit";"Roach";"Larva";203;2
"Building";"Hatchery";NA;205;0
"Unit";"Roach";"Larva";205;2
"Building";"Extractor";NA;207;0
"Building";"Extractor";NA;207;0
"Building";"HydraliskDen";NA;209;0
"Building";"CreepTumor";NA;217;0
"Unit";"Queen";"Hatchery";219;2
"Unit";"Queen";"Hatchery";221;2
"Unit";"Queen";"Hatchery";223;2
"Building";"SporeCrawler";NA;233;0
"Building";"Spire";NA;233;0
"Unit";"Overlord";"Larva";236;0
"Unit";"Overlord";"Larva";236;0
"Unit";"Overlord";"Larva";236;0
"Unit";"Roach";"Larva";236;2
"Unit";"Roach";"Larva";238;2
"Unit";"Roach";"Larva";240;2
"Unit";"Roach";"Larva";242;2
"Unit";"Roach";"Larva";244;2
"Unit";"Roach";"Larva";246;2
"Unit";"Roach";"Larva";248;2
"Unit";"Roach";"Larva";250;2
"Unit";"Roach";"Larva";252;2
"Unit";"Roach";"Larva";254;2
"Unit";"Roach";"Larva";256;2
"Unit";"Roach";"Larva";258;2
"Unit";"Overlord";"Larva";260;0
"Unit";"Overlord";"Larva";260;0
"Unit";"Overlord";"Larva";260;0
"Unit";"Overlord";"Larva";260;0
"Unit";"Viper";"Larva";260;3
"Unit";"Roach";"Larva";263;2
"Unit";"Roach";"Larva";265;2
"Unit";"Roach";"Larva";267;2
"Unit";"Roach";"Larva";269;2
"Unit";"Roach";"Larva";271;2
"Unit";"Roach";"Larva";273;2
"Unit";"Roach";"Larva";275;2
"Unit";"Roach";"Larva";277;2
"Unit";"Roach";"Larva";279;2
"Unit";"Roach";"Larva";281;2
"Unit";"Roach";"Larva";283;2
"Unit";"Roach";"Larva";285;2
"Unit";"Roach";"Larva";287;2
"Unit";"Viper";"Larva";289;3
"Unit";"Viper";"Larva";292;3
"Unit";"Roach";"Larva";295;2
"Unit";"Roach";"Larva";297;2
"Unit";"Roach";"Larva";299;2
"Unit";"Roach";"Larva";301;2
"Unit";"Roach";"Larva";303;2
"Unit";"Roach";"Larva";305;2
"Unit";"Viper";"Larva";307;3
"Building";"CreepTumor";NA;310;0
"Building";"CreepTumorQueen";NA;310;0
"Building";"CreepTumorQueen";NA;310;0
"Building";"CreepTumorQueen";NA;310;0
"Building";"CreepTumorQueen";NA;310;0
"Building";"CreepTumorQueen";NA;310;0
"Unit";"Viper";"Larva";310;3
"Building";"CreepTumorQueen";NA;313;0
"Building";"CreepTumorQueen";NA;313;0
"Building";"Hatchery";NA;313;0
"Building";"CreepTumorQueen";NA;313;0
"Upgrade";"Burrow";"Hatchery";313;0
"Building";"CreepTumorQueen";NA;313;0
"Unit";"Roach";"Larva";313;2
"Unit";"Roach";"Larva";315;2
"Unit";"Roach";"Larva";317;2
"Unit";"Roach";"Larva";319;2
"Unit";"Roach";"Larva";321;2
"Unit";"Roach";"Larva";323;2
"Unit";"Roach";"Larva";325;2
"Unit";"Roach";"Larva";327;2
"Unit";"Roach";"Larva";329;2
"Unit";"Roach";"Larva";331;2
"Unit";"Roach";"Larva";333;2
"Unit";"Roach";"Larva";335;2
"Unit";"Roach";"Larva";337;2
"Unit";"Roach";"Larva";339;2
"Unit";"Roach";"Larva";341;2
"Unit";"Roach";"Larva";343;2
"Unit";"Roach";"Larva";345;2
"Unit";"Roach";"Larva";347;2
"Unit";"Roach";"Larva";349;2
"Unit";"Roach";"Larva";351;2
"Unit";"Roach";"Larva";353;2
"Unit";"Roach";"Larva";355;2
"Unit";"Roach";"Larva";357;2
"Unit";"Roach";"Larva";359;2
"Unit";"Roach";"Larva";361;2
"Unit";"Roach";"Larva";363;2
"Unit";"Roach";"Larva";365;2
"Unit";"Roach";"Larva";367;2
"Unit";"Roach";"Larva";369;2
"Unit";"Roach";"Larva";371;2
"Unit";"Roach";"Larva";373;2
"Unit";"Roach";"Larva";375;2
"Unit";"Roach";"Larva";377;2
"Unit";"Roach";"Larva";379;2
"Unit";"Roach";"Larva";381;2
"Unit";"Roach";"Larva";383;2
"Building";"Extractor";NA;385;0
"Unit";"Roach";"Larva";385;2
"Unit";"Roach";"Larva";387;2
"Unit";"Roach";"Larva";389;2
"Unit";"Roach";"Larva";391;2
"Unit";"Roach";"Larva";393;2
"Unit";"Hydralisk";"Larva";395;2
"Unit";"Hydralisk";"Larva";397;2
"Unit";"Hydralisk";"Larva";399;2
"Unit";"Hydralisk";"Larva";401;2
"Unit";"Hydralisk";"Larva";403;2
"Unit";"Hydralisk";"Larva";405;2
"Unit";"Hydralisk";"Larva";407;2
"Building";"Extractor";NA;414;0
"Building";"CreepTumor";NA;415;0
"Building";"Extractor";NA;415;0
"Building";"Extractor";NA;415;0
"Unit";"Zergling";"Larva";415;1
"Unit";"Zergling";"Larva";416;1
"Unit";"Zergling";"Larva";417;1
"Unit";"Zergling";"Larva";418;1
"Unit";"Zergling";"Larva";419;1
"Unit";"Zergling";"Larva";420;1
"Unit";"Zergling";"Larva";421;1
"Unit";"Zergling";"Larva";422;1
"Unit";"Zergling";"Larva";423;1
"Unit";"Zergling";"Larva";424;1
"Unit";"Zergling";"Larva";425;1
"Unit";"Zergling";"Larva";426;1
"Unit";"Zergling";"Larva";427;1
"Unit";"Zergling";"Larva";428;1
"Unit";"Zergling";"Larva";429;1
"Unit";"Zergling";"Larva";430;1
"Unit";"Zergling";"Larva";431;1
"Unit";"Zergling";"Larva";432;1
"Building";"Hatchery";NA;433;0
"Upgrade";"TunnelingClaws";"RoachWarren";433;0
"Unit";"Roach";"Larva";433;2
"Unit";"Roach";"Larva";435;2
"Unit";"Roach";"Larva";437;2
"Unit";"Roach";"Larva";439;2
"Unit";"Roach";"Larva";441;2
"Unit";"Roach";"Larva";443;2
"Unit";"Roach";"Larva";445;2
"Unit";"Roach";"Larva";447;2
"Unit";"Roach";"Larva";449;2
"Unit";"Roach";"Larva";451;2
"Unit";"Roach";"Larva";453;2
"Unit";"Roach";"Larva";455;2
"Unit";"Hydralisk";"Larva";457;2
"Unit";"Hydralisk";"Larva";459;2
"Unit";"Hydralisk";"Larva";461;2
"Unit";"Hydralisk";"Larva";463;2
"Unit";"Hydralisk";"Larva";465;2
"Unit";"Hydralisk";"Larva";467;2
"Unit";"Hydralisk";"Larva";469;2
"Unit";"Roach";"Larva";471;2
"Unit";"Roach";"Larva";473;2
"Unit";"Roach";"Larva";475;2
"Unit";"Roach";"Larva";477;2
"Unit";"Roach";"Larva";479;2
"Unit";"Roach";"Larva";481;2
"Unit";"Roach";"Larva";483;2
"Unit";"Roach";"Larva";485;2
"Unit";"Roach";"Larva";487;2
"Unit";"Roach";"Larva";489;2
"Unit";"Roach";"Larva";491;2
"Unit";"Roach";"Larva";493;2
"Unit";"Roach";"Larva";495;2
"Unit";"Roach";"Larva";497;2
"Unit";"Roach";"Larva";499;2
"Unit";"Roach";"Larva";501;2
"Unit";"Viper";"Larva";503;3
"Unit";"Viper";"Larva";506;3
"Unit";"Viper";"Larva";509;3
"Unit";"Zergling";"Larva";512;1
"Unit";"Zergling";"Larva";513;1
"Unit";"Zergling";"Larva";514;1
"Unit";"Zergling";"Larva";515;1
"Unit";"Zergling";"Larva";516;1
"Unit";"Zergling";"Larva";517;1
"Building";"CreepTumorQueen";NA;518;0
"Building";"CreepTumorQueen";NA;518;0
"Building";"CreepTumorQueen";NA;518;0
"Building";"CreepTumorQueen";NA;518;0
"Unit";"Viper";"Larva";518;3
"Unit";"Viper";"Larva";521;3
"Building";"CreepTumor";NA;537;0
"Building";"CreepTumor";NA;537;0
"Building";"CreepTumor";NA;537;0
"Unit";"Roach";"Larva";537;2
"Unit";"Roach";"Larva";539;2
"Unit";"Roach";"Larva";541;2
"Unit";"Roach";"Larva";543;2
"Unit";"Roach";"Larva";545;2
"Unit";"Roach";"Larva";547;2
"Unit";"Roach";"Larva";549;2
"Building";"CreepTumor";NA;551;0
"Building";"CreepTumor";NA;551;0
"Building";"CreepTumor";NA;551;0
"Building";"CreepTumor";NA;551;0
"Building";"Extractor";NA;551;0
"Building";"CreepTumorQueen";NA;551;0
"Building";"Extractor";NA;551;0
"Building";"CreepTumorQueen";NA;551;0
"Building";"CreepTumorQueen";NA;551;0
"Building";"CreepTumorQueen";NA;551;0
"Building";"SporeCrawler";NA;551;0
"Building";"SpineCrawler";NA;551;0
"Building";"SporeCrawler";NA;551;0
"Upgrade";"SprayZerg";NA;551;0
"Upgrade";"SprayZerg";NA;551;0
"Upgrade";"zerglingmovementspeed";NA;551;0
"Upgrade";"SprayZerg";NA;551;0
"Upgrade";"SprayZerg";NA;551;0
"Upgrade";"ZergGroundArmorsLevel1";NA;551;0
"Upgrade";"ZergMissileWeaponsLevel1";NA;551;0
"Upgrade";"SprayZerg";NA;551;0
"Upgrade";"SprayZerg";NA;551;0
"Upgrade";"SprayZerg";NA;551;0
"Upgrade";"ZergGroundArmorsLevel2";NA;551;0
"Upgrade";"SprayZerg";NA;551;0
"Upgrade";"ZergMissileWeaponsLevel2";NA;551;0
"Upgrade";"EvolveMuscularAugments";NA;551;0
"Upgrade";"SprayZerg";NA;551;0
"Upgrade";"SprayZerg";NA;551;0
"Upgrade";"SprayZerg";NA;551;0
"Upgrade";"ZergMissileWeaponsLevel3";NA;551;0
"Upgrade";"ZergFlyerArmorsLevel1";NA;551;0
"Upgrade";"SprayZerg";NA;551;0
"Upgrade";"SprayZerg";NA;551;0
"Upgrade";"ZergFlyerArmorsLevel2";NA;551;0
"Upgrade";"ZergGroundArmorsLevel3";NA;551;0
"Upgrade";"overlordspeed";NA;551;0
