"type";"unit_name";"on_building";"total_supply";"supply"
"Unit";"Overlord";"Larva";13;0
"Building";"Extractor";NA;17;0
"Building";"Hatchery";NA;16;0
"Building";"SpawningPool";NA;19;0
"Unit";"Zergling";"Larva";23;1
"Unit";"Zergling";"Larva";23;1
"Unit";"Zergling";"Larva";23;1
"Unit";"Zergling";"Larva";23;1
"Unit";"Overlord";"Larva";23;0
"Unit";"Queen";"Hatchery";23;2
"Unit";"Queen";"Hatchery";23;2
"Unit";"Overlord";"Larva";37;0
"Unit";"Overlord";"Larva";37;0
"Unit";"Queen";"Hatchery";37;2
"Unit";"Overlord";"Larva";40;0
"Building";"CreepTumorQueen";NA;46;0
"Building";"Hatchery";NA;35;0
"Unit";"Overlord";"Larva";50;0
"Unit";"Overlord";"Larva";50;0
"Building";"CreepTumor";NA;52;0
"Unit";"Queen";"Hatchery";47;2
"Unit";"Overlord";"Larva";52;0
"Unit";"Overlord";"Larva";52;0
"Unit";"Zergling";"Larva";53;1
"Unit";"Zergling";"Larva";53;1
"Building";"CreepTumorQueen";NA;58;0
"Unit";"Zergling";"Larva";58;1
"Unit";"Zergling";"Larva";58;1
"Building";"CreepTumor";NA;62;0
"Unit";"Zergling";"Larva";64;1
"Unit";"Zergling";"Larva";64;1
"Building";"SporeCrawler";NA;62;0
"Building";"SporeCrawler";NA;62;0
"Unit";"Queen";"Hatchery";62;2
"Building";"Extractor";NA;71;0
"Building";"CreepTumor";NA;76;0
"Building";"Extractor";NA;71;0
"Building";"CreepTumor";NA;76;0
"Building";"CreepTumorQueen";NA;84;0
"Building";"HydraliskDen";NA;79;0
"Building";"Extractor";NA;84;0
"Building";"CreepTumorQueen";NA;91;0
"Building";"Extractor";NA;87;0
"Building";"CreepTumor";NA;91;0
"Building";"Extractor";NA;91;0
"Unit";"Overlord";"Larva";101;0
"Unit";"Overlord";"Larva";101;0
"Unit";"Overlord";"Larva";101;0
"Unit";"Overlord";"Larva";101;0
"Unit";"Overlord";"Larva";101;0
"Building";"CreepTumor";NA;101;0
"Unit";"Overlord";"Larva";101;0
"Building";"EvolutionChamber";NA;101;0
"Building";"CreepTumor";NA;104;0
"Building";"CreepTumorQueen";NA;104;0
"Building";"CreepTumor";NA;104;0
"Unit";"Hydralisk";"Larva";102;2
"Building";"CreepTumorQueen";NA;105;0
"Unit";"Hydralisk";"Larva";102;2
"Unit";"Hydralisk";"Larva";102;2
"Unit";"Hydralisk";"Larva";102;2
"Unit";"Hydralisk";"Larva";102;2
"Unit";"Hydralisk";"Larva";102;2
"Unit";"Hydralisk";"Larva";102;2
"Building";"CreepTumorQueen";NA;105;0
"Unit";"Hydralisk";"Larva";102;2
"Unit";"Zergling";"Larva";105;1
"Unit";"Zergling";"Larva";105;1
"Upgrade";"EvolveGroovedSpines";"HydraliskDen";101;0
"Unit";"Hydralisk";"Larva";105;2
"Unit";"Hydralisk";"Larva";105;2
"Unit";"Hydralisk";"Larva";105;2
"Unit";"Hydralisk";"Larva";105;2
"Unit";"Hydralisk";"Larva";105;2
"Unit";"Hydralisk";"Larva";105;2
"Building";"CreepTumor";NA;123;0
"Building";"CreepTumor";NA;123;0
"Building";"CreepTumor";NA;123;0
"Building";"CreepTumor";NA;123;0
"Building";"CreepTumor";NA;123;0
"Building";"Hatchery";NA;101;0
"Unit";"Hydralisk";"Larva";123;2
"Unit";"Hydralisk";"Larva";123;2
"Unit";"Hydralisk";"Larva";123;2
"Unit";"Hydralisk";"Larva";123;2
"Unit";"Hydralisk";"Larva";123;2
"Building";"SporeCrawler";NA;123;0
"Unit";"Hydralisk";"Larva";154;2
"Unit";"Hydralisk";"Larva";154;2
"Building";"CreepTumor";NA;157;0
"Building";"CreepTumor";NA;157;0
"Unit";"Overlord";"Larva";157;0
"Unit";"Overlord";"Larva";157;0
"Unit";"Overlord";"Larva";157;0
"Unit";"Overlord";"Larva";157;0
"Unit";"Overlord";"Larva";157;0
"Unit";"Overlord";"Larva";157;0
"Unit";"Overlord";"Larva";157;0
"Building";"CreepTumor";NA;157;0
"Building";"CreepTumor";NA;157;0
"Building";"CreepTumor";NA;161;0
"Unit";"Overlord";"Larva";161;0
"Unit";"Overlord";"Larva";161;0
"Unit";"Overlord";"Larva";161;0
"Unit";"Overlord";"Larva";161;0
"Building";"BanelingNest";NA;157;0
"Building";"SporeCrawler";NA;161;0
"Building";"SporeCrawler";NA;161;0
"Upgrade";"EvolveMuscularAugments";"HydraliskDen";155;0
"Building";"CreepTumor";NA;161;0
"Building";"CreepTumor";NA;161;0
"Unit";"Zergling";"Larva";161;1
"Unit";"Zergling";"Larva";161;1
"Unit";"Zergling";"Larva";161;1
"Unit";"Zergling";"Larva";161;1
"Unit";"Zergling";"Larva";161;1
"Unit";"Zergling";"Larva";161;1
"Unit";"Zergling";"Larva";161;1
"Unit";"Zergling";"Larva";161;1
"Unit";"Zergling";"Larva";161;1
"Unit";"Zergling";"Larva";161;1
"Unit";"Zergling";"Larva";161;1
"Unit";"Zergling";"Larva";161;1
"Unit";"Zergling";"Larva";161;1
"Unit";"Zergling";"Larva";161;1
"Unit";"Zergling";"Larva";161;1
"Unit";"Zergling";"Larva";161;1
"Unit";"Zergling";"Larva";161;1
"Unit";"Zergling";"Larva";161;1
"Unit";"Zergling";"Larva";161;1
"Unit";"Zergling";"Larva";161;1
"Unit";"Zergling";"Larva";161;1
"Unit";"Zergling";"Larva";161;1
"Unit";"Zergling";"Larva";161;1
"Unit";"Zergling";"Larva";161;1
"Unit";"Zergling";"Larva";161;1
"Unit";"Zergling";"Larva";161;1
"Unit";"Zergling";"Larva";161;1
"Unit";"Zergling";"Larva";161;1
"Unit";"Zergling";"Larva";161;1
"Unit";"Zergling";"Larva";161;1
"Unit";"Zergling";"Larva";161;1
"Unit";"Zergling";"Larva";161;1
"Unit";"Zergling";"Larva";161;1
"Unit";"Zergling";"Larva";161;1
"Unit";"Zergling";"Larva";161;1
"Unit";"Zergling";"Larva";161;1
"Building";"CreepTumor";NA;161;0
"Unit";"Zergling";"Larva";161;1
"Unit";"Zergling";"Larva";161;1
"Unit";"Zergling";"Larva";161;1
"Unit";"Zergling";"Larva";161;1
"Unit";"Zergling";"Larva";161;1
"Unit";"Zergling";"Larva";161;1
"Unit";"Zergling";"Larva";161;1
"Unit";"Zergling";"Larva";161;1
"Unit";"Zergling";"Larva";161;1
"Unit";"Zergling";"Larva";161;1
"Building";"SporeCrawler";NA;161;0
"Unit";"Zergling";"Larva";197;1
"Unit";"Zergling";"Larva";197;1
"Upgrade";"ZergMissileWeaponsLevel1";"EvolutionChamber";154;0
"Unit";"Zergling";"Larva";197;1
"Unit";"Zergling";"Larva";197;1
"Unit";"Zergling";"Larva";197;1
"Unit";"Zergling";"Larva";197;1
"Building";"EvolutionChamber";NA;197;0
"Building";"EvolutionChamber";NA;197;0
"Unit";"Zergling";"Larva";205;1
"Unit";"Zergling";"Larva";205;1
"Unit";"Zergling";"Larva";205;1
"Unit";"Zergling";"Larva";205;1
"Unit";"Zergling";"Larva";205;1
"Unit";"Zergling";"Larva";205;1
"Unit";"Zergling";"Larva";205;1
"Unit";"Zergling";"Larva";205;1
"Unit";"Zergling";"Larva";205;1
"Unit";"Zergling";"Larva";205;1
"Unit";"Zergling";"Larva";205;1
"Unit";"Zergling";"Larva";205;1
"Unit";"Zergling";"Larva";205;1
"Unit";"Zergling";"Larva";205;1
"Unit";"Zergling";"Larva";205;1
"Unit";"Zergling";"Larva";205;1
"Unit";"Zergling";"Larva";205;1
"Unit";"Zergling";"Larva";205;1
"Unit";"Zergling";"Larva";205;1
"Unit";"Zergling";"Larva";205;1
"Building";"CreepTumor";NA;207;0
"Building";"CreepTumor";NA;207;0
"Unit";"Zergling";"Larva";207;1
"Unit";"Zergling";"Larva";207;1
"Unit";"Zergling";"Larva";207;1
"Unit";"Zergling";"Larva";207;1
"Unit";"Zergling";"Larva";207;1
"Unit";"Zergling";"Larva";207;1
"Unit";"Zergling";"Larva";209;1
"Unit";"Zergling";"Larva";209;1
"Building";"LurkerDenMP";NA;157;0
"Unit";"Baneling";"Zergling";225;0
"Unit";"Baneling";"Zergling";233;0
"Unit";"Baneling";"Zergling";233;0
"Unit";"Baneling";"Zergling";233;0
"Unit";"Baneling";"Zergling";233;0
"Unit";"Baneling";"Zergling";233;0
"Unit";"Baneling";"Zergling";233;0
"Unit";"Baneling";"Zergling";233;0
"Unit";"Baneling";"Zergling";233;0
"Unit";"Baneling";"Zergling";233;0
"Unit";"Baneling";"Zergling";233;0
"Unit";"Baneling";"Zergling";233;0
"Unit";"Baneling";"Zergling";233;0
"Unit";"Baneling";"Zergling";233;0
"Unit";"Baneling";"Zergling";233;0
"Unit";"Baneling";"Zergling";233;0
"Unit";"Baneling";"Zergling";233;0
"Unit";"Baneling";"Zergling";233;0
"Unit";"Baneling";"Zergling";233;0
"Unit";"Baneling";"Zergling";233;0
"Unit";"Baneling";"Zergling";233;0
"Unit";"Baneling";"Zergling";233;0
"Unit";"Baneling";"Zergling";233;0
"Unit";"Baneling";"Zergling";233;0
"Unit";"Baneling";"Zergling";233;0
"Unit";"Baneling";"Zergling";233;0
"Building";"CreepTumor";NA;233;0
"Building";"CreepTumor";NA;233;0
"Building";"Extractor";NA;241;0
"Building";"Hatchery";NA;161;0
"Building";"Extractor";NA;241;0
"Building";"CreepTumor";NA;251;0
"Building";"CreepTumor";NA;251;0
"Building";"CreepTumor";NA;251;0
"Unit";"Hydralisk";"Larva";251;2
"Unit";"Hydralisk";"Larva";251;2
"Unit";"Hydralisk";"Larva";251;2
"Unit";"Hydralisk";"Larva";251;2
"Unit";"Hydralisk";"Larva";251;2
"Unit";"Hydralisk";"Larva";251;2
"Unit";"Zergling";"Larva";251;1
"Unit";"Zergling";"Larva";251;1
"Unit";"Zergling";"Larva";251;1
"Unit";"Zergling";"Larva";251;1
"Unit";"Zergling";"Larva";251;1
"Unit";"Zergling";"Larva";251;1
"Unit";"Zergling";"Larva";251;1
"Unit";"Zergling";"Larva";251;1
"Unit";"Zergling";"Larva";251;1
"Unit";"Zergling";"Larva";251;1
"Unit";"Zergling";"Larva";251;1
"Unit";"Zergling";"Larva";251;1
"Unit";"Zergling";"Larva";251;1
"Unit";"Zergling";"Larva";251;1
"Unit";"Zergling";"Larva";251;1
"Unit";"Zergling";"Larva";251;1
"Unit";"Zergling";"Larva";251;1
"Unit";"Zergling";"Larva";251;1
"Unit";"Zergling";"Larva";251;1
"Unit";"Zergling";"Larva";251;1
"Unit";"Zergling";"Larva";251;1
"Unit";"Zergling";"Larva";251;1
"Unit";"Zergling";"Larva";251;1
"Unit";"Zergling";"Larva";251;1
"Unit";"Zergling";"Larva";251;1
"Unit";"Zergling";"Larva";251;1
"Unit";"Zergling";"Larva";251;1
"Unit";"Zergling";"Larva";251;1
"Unit";"Zergling";"Larva";291;1
"Unit";"Zergling";"Larva";291;1
"Unit";"Zergling";"Larva";291;1
"Unit";"Zergling";"Larva";291;1
"Unit";"Zergling";"Larva";291;1
"Unit";"Zergling";"Larva";291;1
"Unit";"Zergling";"Larva";291;1
"Unit";"Zergling";"Larva";291;1
"Unit";"Zergling";"Larva";291;1
"Unit";"Zergling";"Larva";291;1
"Unit";"Zergling";"Larva";291;1
"Unit";"Zergling";"Larva";291;1
"Unit";"Zergling";"Larva";291;1
"Unit";"Zergling";"Larva";291;1
"Unit";"Zergling";"Larva";291;1
"Unit";"Zergling";"Larva";291;1
"Unit";"Zergling";"Larva";291;1
"Unit";"Zergling";"Larva";291;1
"Unit";"Zergling";"Larva";291;1
"Unit";"Zergling";"Larva";291;1
"Unit";"Zergling";"Larva";291;1
"Unit";"Zergling";"Larva";291;1
"Unit";"Zergling";"Larva";291;1
"Unit";"Zergling";"Larva";291;1
"Unit";"Zergling";"Larva";291;1
"Unit";"Zergling";"Larva";291;1
"Unit";"Zergling";"Larva";291;1
"Unit";"Zergling";"Larva";291;1
"Unit";"Zergling";"Larva";291;1
"Unit";"Zergling";"Larva";291;1
"Unit";"Zergling";"Larva";291;1
"Unit";"Zergling";"Larva";291;1
"Unit";"Zergling";"Larva";291;1
"Unit";"Zergling";"Larva";291;1
"Unit";"Zergling";"Larva";291;1
"Unit";"Zergling";"Larva";291;1
"Unit";"Zergling";"Larva";291;1
"Unit";"Zergling";"Larva";291;1
"Unit";"Zergling";"Larva";291;1
"Unit";"Zergling";"Larva";291;1
"Unit";"Zergling";"Larva";291;1
"Unit";"Zergling";"Larva";291;1
"Unit";"Zergling";"Larva";291;1
"Unit";"Zergling";"Larva";291;1
"Building";"CreepTumor";NA;291;0
"Building";"CreepTumor";NA;291;0
"Building";"CreepTumor";NA;311;0
"Building";"CreepTumor";NA;335;0
"Upgrade";"ZergMeleeWeaponsLevel1";"EvolutionChamber";251;0
"Upgrade";"ZergGroundArmorsLevel1";"EvolutionChamber";251;0
"Upgrade";"ZergMissileWeaponsLevel2";"EvolutionChamber";251;0
"Unit";"Hydralisk";"Larva";291;2
"Unit";"Hydralisk";"Larva";291;2
"Unit";"Hydralisk";"Larva";291;2
"Unit";"Hydralisk";"Larva";291;2
"Unit";"Hydralisk";"Larva";293;2
"Unit";"Hydralisk";"Larva";293;2
"Unit";"Hydralisk";"Larva";293;2
"Unit";"Hydralisk";"Larva";293;2
"Unit";"Hydralisk";"Larva";293;2
"Unit";"Baneling";"Zergling";335;0
"Unit";"Baneling";"Zergling";335;0
"Unit";"Baneling";"Zergling";335;0
"Unit";"Baneling";"Zergling";335;0
"Unit";"Baneling";"Zergling";335;0
"Unit";"Baneling";"Zergling";335;0
"Unit";"Baneling";"Zergling";335;0
"Unit";"Baneling";"Zergling";335;0
"Unit";"Baneling";"Zergling";335;0
"Unit";"Baneling";"Zergling";335;0
"Unit";"Baneling";"Zergling";335;0
"Unit";"Baneling";"Zergling";335;0
"Unit";"Baneling";"Zergling";335;0
"Unit";"Baneling";"Zergling";335;0
"Unit";"Baneling";"Zergling";335;0
"Unit";"Baneling";"Zergling";335;0
"Unit";"Baneling";"Zergling";335;0
"Unit";"Baneling";"Zergling";335;0
"Unit";"Baneling";"Zergling";335;0
"Unit";"Baneling";"Zergling";335;0
"Unit";"Hydralisk";"Larva";335;2
"Unit";"Hydralisk";"Larva";335;2
"Unit";"Hydralisk";"Larva";335;2
"Unit";"Hydralisk";"Larva";335;2
"Building";"CreepTumor";NA;335;0
"Unit";"Hydralisk";"Larva";335;2
"Unit";"Hydralisk";"Larva";335;2
"Unit";"Hydralisk";"Larva";335;2
"Unit";"Hydralisk";"Larva";335;2
"Unit";"Hydralisk";"Larva";335;2
"Unit";"Hydralisk";"Larva";335;2
"Unit";"Hydralisk";"Larva";335;2
"Unit";"Hydralisk";"Larva";335;2
"Unit";"Hydralisk";"Larva";335;2
"Building";"CreepTumor";NA;361;0
"Building";"CreepTumor";NA;363;0
"Unit";"Zergling";"Larva";363;1
"Unit";"Zergling";"Larva";363;1
"Unit";"Zergling";"Larva";363;1
"Unit";"Zergling";"Larva";363;1
"Unit";"Zergling";"Larva";363;1
"Unit";"Zergling";"Larva";363;1
"Unit";"Zergling";"Larva";363;1
"Unit";"Zergling";"Larva";363;1
"Unit";"Zergling";"Larva";363;1
"Unit";"Zergling";"Larva";363;1
"Unit";"Zergling";"Larva";363;1
"Unit";"Zergling";"Larva";363;1
"Unit";"Zergling";"Larva";363;1
"Unit";"Zergling";"Larva";363;1
"Unit";"Zergling";"Larva";363;1
"Unit";"Zergling";"Larva";363;1
"Unit";"Zergling";"Larva";363;1
"Unit";"Zergling";"Larva";363;1
"Unit";"Zergling";"Larva";363;1
"Unit";"Zergling";"Larva";363;1
"Building";"InfestationPit";NA;361;0
"Building";"Hatchery";NA;361;0
