"type";"unit_name";"on_building";"total_supply";"supply"
"Unit";"Overlord";"Larva";12;0
"Building";"SpawningPool";NA;17;0
"Unit";"Zergling";"Larva";20;1
"Unit";"Zergling";"Larva";20;1
"Unit";"Zergling";"Larva";20;1
"Unit";"Zergling";"Larva";20;1
"Unit";"Zergling";"Larva";20;1
"Unit";"Zergling";"Larva";20;1
"Building";"Extractor";NA;20;0
"Building";"Hatchery";NA;19;0
"Unit";"Overlord";"Larva";26;0
"Unit";"Queen";"Hatchery";22;2
"Building";"Hatchery";NA;20;0
"Unit";"Queen";"Hatchery";26;2
"Building";"CreepTumorQueen";NA;39;0
"Unit";"Zergling";"Larva";39;1
"Unit";"Zergling";"Larva";39;1
"Unit";"Zergling";"Larva";39;1
"Unit";"Zergling";"Larva";39;1
"Unit";"Zergling";"Larva";39;1
"Unit";"Zergling";"Larva";39;1
"Unit";"Zergling";"Larva";39;1
"Unit";"Zergling";"Larva";39;1
"Unit";"Overlord";"Larva";46;0
"Building";"CreepTumor";NA;52;0
"Unit";"Overlord";"Larva";56;0
"Building";"EvolutionChamber";NA;52;0
"Unit";"Overlord";"Larva";56;0
"Unit";"Queen";"Hatchery";57;2
"Building";"SporeCrawler";NA;67;0
"Building";"SporeCrawler";NA;72;0
"Building";"SporeCrawler";NA;74;0
"Building";"Extractor";NA;81;0
"Unit";"Overlord";"Larva";82;0
"Unit";"Overlord";"Larva";83;0
"Unit";"Overlord";"Larva";84;0
"Unit";"Overlord";"Larva";84;0
"Building";"BanelingNest";NA;81;0
"Building";"CreepTumor";NA;86;0
"Unit";"Zergling";"Larva";86;1
"Unit";"Zergling";"Larva";86;1
"Unit";"Zergling";"Larva";86;1
"Unit";"Zergling";"Larva";86;1
"Unit";"Zergling";"Larva";86;1
"Unit";"Zergling";"Larva";86;1
"Unit";"Zergling";"Larva";86;1
"Unit";"Zergling";"Larva";86;1
"Unit";"Zergling";"Larva";86;1
"Unit";"Zergling";"Larva";86;1
"Unit";"Zergling";"Larva";86;1
"Unit";"Zergling";"Larva";86;1
"Unit";"Zergling";"Larva";86;1
"Unit";"Zergling";"Larva";86;1
"Unit";"Zergling";"Larva";86;1
"Unit";"Zergling";"Larva";86;1
"Unit";"Zergling";"Larva";86;1
"Unit";"Zergling";"Larva";86;1
"Unit";"Zergling";"Larva";86;1
"Unit";"Zergling";"Larva";86;1
"Unit";"Zergling";"Larva";86;1
"Unit";"Zergling";"Larva";86;1
"Unit";"Zergling";"Larva";86;1
"Unit";"Zergling";"Larva";86;1
"Unit";"Zergling";"Larva";86;1
"Unit";"Zergling";"Larva";86;1
"Unit";"Baneling";"Zergling";86;0
"Unit";"Baneling";"Zergling";86;0
"Unit";"Baneling";"Zergling";86;0
"Unit";"Baneling";"Zergling";86;0
"Unit";"Baneling";"Zergling";86;0
"Unit";"Baneling";"Zergling";86;0
"Unit";"Baneling";"Zergling";86;0
"Unit";"Zergling";"Larva";86;1
"Unit";"Zergling";"Larva";86;1
"Unit";"Zergling";"Larva";86;1
"Unit";"Zergling";"Larva";86;1
"Unit";"Zergling";"Larva";86;1
"Unit";"Zergling";"Larva";86;1
"Unit";"Zergling";"Larva";86;1
"Unit";"Zergling";"Larva";86;1
"Unit";"Zergling";"Larva";86;1
"Unit";"Zergling";"Larva";86;1
"Unit";"Zergling";"Larva";86;1
"Unit";"Zergling";"Larva";86;1
"Upgrade";"ZergMeleeWeaponsLevel1";"EvolutionChamber";80;0
"Building";"CreepTumor";NA;127;0
"Unit";"Overlord";"Larva";127;0
"Unit";"Overlord";"Larva";135;0
"Building";"Extractor";NA;135;0
"Unit";"Overlord";"Larva";137;0
"Unit";"Overlord";"Larva";137;0
"Unit";"Overlord";"Larva";137;0
"Unit";"Overlord";"Larva";137;0
"Unit";"Overlord";"Larva";137;0
"Building";"Hatchery";NA;114;0
"Building";"Extractor";NA;137;0
"Building";"CreepTumor";NA;147;0
"Building";"Extractor";NA;141;0
"Unit";"Overlord";"Larva";147;0
"Building";"Extractor";NA;142;0
"Building";"HydraliskDen";NA;148;0
"Building";"SporeCrawler";NA;148;0
"Unit";"Zergling";"Larva";148;1
"Unit";"Zergling";"Larva";148;1
"Building";"Extractor";NA;148;0
"Building";"Extractor";NA;148;0
"Unit";"Zergling";"Larva";148;1
"Unit";"Zergling";"Larva";148;1
"Unit";"Zergling";"Larva";148;1
"Unit";"Zergling";"Larva";148;1
"Unit";"Zergling";"Larva";148;1
"Unit";"Zergling";"Larva";148;1
"Unit";"Zergling";"Larva";148;1
"Unit";"Zergling";"Larva";148;1
"Unit";"Zergling";"Larva";148;1
"Unit";"Zergling";"Larva";148;1
"Unit";"Zergling";"Larva";148;1
"Unit";"Zergling";"Larva";148;1
"Unit";"Zergling";"Larva";148;1
"Unit";"Zergling";"Larva";148;1
"Unit";"Zergling";"Larva";148;1
"Unit";"Zergling";"Larva";148;1
"Unit";"Zergling";"Larva";148;1
"Unit";"Zergling";"Larva";148;1
"Unit";"Zergling";"Larva";148;1
"Unit";"Zergling";"Larva";148;1
"Unit";"Zergling";"Larva";148;1
"Unit";"Zergling";"Larva";148;1
"Unit";"Zergling";"Larva";148;1
"Unit";"Zergling";"Larva";148;1
"Unit";"Overlord";"Larva";155;0
"Building";"CreepTumor";NA;182;0
"Unit";"Overlord";"Larva";182;0
"Upgrade";"ZergGroundArmorsLevel1";"EvolutionChamber";137;0
"Unit";"Overlord";"Larva";182;0
"Unit";"Overlord";"Larva";182;0
"Unit";"Overlord";"Larva";182;0
"Unit";"Queen";"Hatchery";182;2
"Unit";"Overlord";"Larva";182;0
"Unit";"Overlord";"Larva";182;0
"Unit";"Hydralisk";"Larva";182;2
"Unit";"Hydralisk";"Larva";182;2
"Unit";"Hydralisk";"Larva";182;2
"Unit";"Hydralisk";"Larva";182;2
"Unit";"Hydralisk";"Larva";182;2
"Unit";"Hydralisk";"Larva";182;2
"Unit";"Hydralisk";"Larva";182;2
"Unit";"Hydralisk";"Larva";182;2
"Unit";"Hydralisk";"Larva";182;2
"Unit";"Hydralisk";"Larva";182;2
"Unit";"Hydralisk";"Larva";182;2
"Unit";"Hydralisk";"Larva";182;2
"Unit";"Hydralisk";"Larva";182;2
"Building";"CreepTumor";NA;184;0
"Unit";"Hydralisk";"Larva";182;2
"Unit";"Hydralisk";"Larva";182;2
"Unit";"Hydralisk";"Larva";182;2
"Unit";"Hydralisk";"Larva";182;2
"Unit";"Hydralisk";"Larva";182;2
"Unit";"Overlord";"Larva";184;0
"Unit";"Hydralisk";"Larva";220;2
"Unit";"Hydralisk";"Larva";220;2
"Unit";"Hydralisk";"Larva";220;2
"Unit";"Hydralisk";"Larva";220;2
"Unit";"Hydralisk";"Larva";220;2
"Unit";"Hydralisk";"Larva";220;2
"Unit";"Hydralisk";"Larva";220;2
"Unit";"Hydralisk";"Larva";220;2
"Unit";"Hydralisk";"Larva";220;2
"Upgrade";"EvolveGroovedSpines";"HydraliskDen";184;0
"Unit";"Hydralisk";"Larva";220;2
"Building";"CreepTumor";NA;220;0
"Unit";"Hydralisk";"Larva";220;2
"Unit";"Hydralisk";"Larva";220;2
"Unit";"Hydralisk";"Larva";220;2
"Unit";"Hydralisk";"Larva";220;2
"Unit";"Hydralisk";"Larva";220;2
"Unit";"Hydralisk";"Larva";220;2
"Unit";"Hydralisk";"Larva";220;2
"Unit";"Hydralisk";"Larva";220;2
"Unit";"Hydralisk";"Larva";220;2
"Unit";"Hydralisk";"Larva";220;2
"Unit";"Hydralisk";"Larva";220;2
"Unit";"Hydralisk";"Larva";238;2
"Unit";"Hydralisk";"Larva";238;2
"Unit";"Hydralisk";"Larva";238;2
"Unit";"Hydralisk";"Larva";238;2
"Unit";"Zergling";"Larva";258;1
"Unit";"Zergling";"Larva";258;1
"Unit";"Zergling";"Larva";258;1
"Unit";"Zergling";"Larva";258;1
"Unit";"Zergling";"Larva";258;1
"Unit";"Zergling";"Larva";258;1
"Unit";"Zergling";"Larva";258;1
"Unit";"Zergling";"Larva";258;1
"Unit";"Zergling";"Larva";258;1
"Unit";"Zergling";"Larva";258;1
"Unit";"Zergling";"Larva";262;1
"Unit";"Zergling";"Larva";262;1
"Unit";"Zergling";"Larva";262;1
"Unit";"Zergling";"Larva";262;1
"Unit";"Zergling";"Larva";262;1
"Unit";"Zergling";"Larva";262;1
"Unit";"Zergling";"Larva";262;1
"Unit";"Zergling";"Larva";262;1
"Unit";"Baneling";"Zergling";262;0
"Unit";"Zergling";"Larva";262;1
"Unit";"Zergling";"Larva";262;1
"Unit";"Zergling";"Larva";262;1
"Unit";"Zergling";"Larva";262;1
"Unit";"Zergling";"Larva";262;1
"Unit";"Zergling";"Larva";262;1
"Unit";"Zergling";"Larva";262;1
"Unit";"Zergling";"Larva";262;1
"Unit";"Overlord";"Larva";268;0
"Unit";"Zergling";"Larva";268;1
"Unit";"Zergling";"Larva";268;1
"Unit";"Zergling";"Larva";268;1
"Unit";"Zergling";"Larva";268;1
"Unit";"Zergling";"Larva";272;1
"Unit";"Zergling";"Larva";272;1
"Unit";"Zergling";"Larva";272;1
"Unit";"Zergling";"Larva";272;1
"Unit";"Zergling";"Larva";276;1
"Unit";"Zergling";"Larva";276;1
"Unit";"Zergling";"Larva";278;1
"Unit";"Zergling";"Larva";278;1
"Unit";"Zergling";"Larva";282;1
"Unit";"Zergling";"Larva";282;1
"Unit";"Zergling";"Larva";284;1
"Unit";"Zergling";"Larva";284;1
"Unit";"Zergling";"Larva";286;1
"Unit";"Zergling";"Larva";286;1
"Unit";"Baneling";"Zergling";296;0
"Unit";"Baneling";"Zergling";296;0
"Unit";"Baneling";"Zergling";296;0
"Unit";"Zergling";"Larva";296;1
"Unit";"Zergling";"Larva";296;1
"Unit";"Zergling";"Larva";296;1
"Unit";"Zergling";"Larva";296;1
"Unit";"Zergling";"Larva";296;1
"Unit";"Zergling";"Larva";296;1
"Unit";"Baneling";"Zergling";300;0
"Unit";"Baneling";"Zergling";300;0
"Unit";"Baneling";"Zergling";300;0
"Unit";"Zergling";"Larva";300;1
"Unit";"Zergling";"Larva";300;1
"Unit";"Zergling";"Larva";300;1
"Unit";"Zergling";"Larva";300;1
"Unit";"Zergling";"Larva";300;1
"Unit";"Zergling";"Larva";300;1
"Unit";"Zergling";"Larva";300;1
"Unit";"Zergling";"Larva";300;1
"Unit";"Zergling";"Larva";306;1
"Unit";"Zergling";"Larva";306;1
"Unit";"Zergling";"Larva";308;1
"Unit";"Zergling";"Larva";308;1
"Unit";"Zergling";"Larva";308;1
"Unit";"Zergling";"Larva";308;1
"Upgrade";"ZergMeleeWeaponsLevel2";"EvolutionChamber";220;0
"Unit";"Zergling";"Larva";314;1
"Unit";"Zergling";"Larva";314;1
"Upgrade";"EvolveMuscularAugments";"HydraliskDen";270;0
"Unit";"Zergling";"Larva";320;1
"Unit";"Zergling";"Larva";320;1
"Unit";"Zergling";"Larva";320;1
"Unit";"Zergling";"Larva";320;1
"Unit";"Zergling";"Larva";334;1
"Unit";"Zergling";"Larva";334;1
"Unit";"Zergling";"Larva";334;1
"Unit";"Zergling";"Larva";334;1
"Unit";"Zergling";"Larva";334;1
"Unit";"Zergling";"Larva";334;1
"Unit";"Zergling";"Larva";336;1
"Unit";"Zergling";"Larva";336;1
"Unit";"Zergling";"Larva";336;1
"Unit";"Zergling";"Larva";336;1
