"type";"unit_name";"on_building";"total_supply";"supply"
"Unit";"Overlord";"Larva";12;0
"Building";"Extractor";NA;17;0
"Unit";"Overlord";"Larva";22;0
"Building";"SpawningPool";NA;19;0
"Building";"Hatchery";NA;17;0
"Unit";"Zergling";"Larva";22;1
"Unit";"Zergling";"Larva";22;1
"Unit";"Zergling";"Larva";22;1
"Unit";"Zergling";"Larva";22;1
"Unit";"Queen";"Hatchery";22;2
"Unit";"Queen";"Hatchery";22;2
"Unit";"Overlord";"Larva";35;0
"Unit";"Zergling";"Larva";37;1
"Unit";"Zergling";"Larva";37;1
"Unit";"Zergling";"Larva";37;1
"Unit";"Zergling";"Larva";37;1
"Unit";"Queen";"Hatchery";35;2
"Building";"CreepTumorQueen";NA;46;0
"Unit";"Overlord";"Larva";43;0
"Building";"SporeCrawler";NA;49;0
"Building";"SporeCrawler";NA;49;0
"Building";"Hatchery";NA;37;0
"Building";"Extractor";NA;53;0
"Unit";"Overlord";"Larva";55;0
"Unit";"Overlord";"Larva";55;0
"Building";"CreepTumor";NA;56;0
"Building";"CreepTumorQueen";NA;62;0
"Building";"Extractor";NA;61;0
"Unit";"Queen";"Hatchery";60;2
"Building";"SporeCrawler";NA;62;0
"Unit";"Queen";"Hatchery";61;2
"Unit";"Zergling";"Larva";67;1
"Unit";"Zergling";"Larva";67;1
"Unit";"Zergling";"Larva";67;1
"Unit";"Zergling";"Larva";67;1
"Unit";"Zergling";"Larva";67;1
"Unit";"Zergling";"Larva";67;1
"Unit";"Zergling";"Larva";67;1
"Unit";"Zergling";"Larva";67;1
"Unit";"Overlord";"Larva";67;0
"Unit";"Overlord";"Larva";67;0
"Building";"CreepTumor";NA;83;0
"Unit";"Overlord";"Larva";83;0
"Unit";"Overlord";"Larva";83;0
"Building";"HydraliskDen";NA;73;0
"Unit";"Zergling";"Larva";87;1
"Unit";"Zergling";"Larva";87;1
"Unit";"Zergling";"Larva";88;1
"Unit";"Zergling";"Larva";88;1
"Unit";"Zergling";"Larva";88;1
"Unit";"Zergling";"Larva";88;1
"Unit";"Zergling";"Larva";92;1
"Unit";"Zergling";"Larva";92;1
"Unit";"Zergling";"Larva";92;1
"Unit";"Zergling";"Larva";92;1
"Unit";"Zergling";"Larva";92;1
"Unit";"Zergling";"Larva";92;1
"Unit";"Zergling";"Larva";92;1
"Unit";"Zergling";"Larva";92;1
"Unit";"Zergling";"Larva";98;1
"Unit";"Zergling";"Larva";98;1
"Unit";"Zergling";"Larva";98;1
"Unit";"Zergling";"Larva";98;1
"Unit";"Zergling";"Larva";98;1
"Unit";"Zergling";"Larva";98;1
"Unit";"Zergling";"Larva";98;1
"Unit";"Zergling";"Larva";98;1
"Unit";"Zergling";"Larva";98;1
"Unit";"Zergling";"Larva";98;1
"Unit";"Zergling";"Larva";98;1
"Unit";"Zergling";"Larva";98;1
"Unit";"Overlord";"Larva";118;0
"Building";"Extractor";NA;118;0
"Building";"Extractor";NA;118;0
"Building";"EvolutionChamber";NA;118;0
"Building";"EvolutionChamber";NA;118;0
"Building";"CreepTumor";NA;124;0
"Upgrade";"EvolveMuscularAugments";"HydraliskDen";104;0
"Building";"Extractor";NA;135;0
"Building";"BanelingNest";NA;124;0
"Unit";"Overlord";"Larva";138;0
"Unit";"Overlord";"Larva";138;0
"Unit";"Overlord";"Larva";138;0
"Unit";"Overlord";"Larva";138;0
"Unit";"Overlord";"Larva";138;0
"Unit";"Overlord";"Larva";138;0
"Unit";"Queen";"Hatchery";138;2
"Building";"CreepTumorQueen";NA;138;0
"Building";"Hatchery";NA;124;0
"Unit";"Hydralisk";"Larva";138;2
"Unit";"Hydralisk";"Larva";138;2
"Unit";"Hydralisk";"Larva";138;2
"Unit";"Hydralisk";"Larva";138;2
"Unit";"Hydralisk";"Larva";138;2
"Unit";"Hydralisk";"Larva";138;2
"Unit";"Hydralisk";"Larva";138;2
"Unit";"Hydralisk";"Larva";138;2
"Unit";"Hydralisk";"Larva";138;2
"Unit";"Hydralisk";"Larva";138;2
"Unit";"Baneling";"Zergling";140;0
"Unit";"Hydralisk";"Larva";138;2
"Unit";"Baneling";"Zergling";140;0
"Unit";"Hydralisk";"Larva";138;2
"Unit";"Baneling";"Zergling";140;0
"Unit";"Hydralisk";"Larva";138;2
"Unit";"Baneling";"Zergling";140;0
"Unit";"Baneling";"Zergling";140;0
"Unit";"Baneling";"Zergling";140;0
"Unit";"Baneling";"Zergling";140;0
"Unit";"Baneling";"Zergling";140;0
"Unit";"Hydralisk";"Larva";138;2
"Unit";"Zergling";"Larva";140;1
"Unit";"Zergling";"Larva";140;1
"Unit";"Zergling";"Larva";140;1
"Unit";"Zergling";"Larva";140;1
"Unit";"Zergling";"Larva";140;1
"Unit";"Zergling";"Larva";140;1
"Unit";"Zergling";"Larva";140;1
"Unit";"Zergling";"Larva";140;1
"Unit";"Zergling";"Larva";140;1
"Unit";"Zergling";"Larva";140;1
"Unit";"Zergling";"Larva";140;1
"Unit";"Zergling";"Larva";140;1
"Building";"Extractor";NA;140;0
"Unit";"Zergling";"Larva";140;1
"Unit";"Zergling";"Larva";140;1
"Unit";"Hydralisk";"Larva";182;2
"Unit";"Hydralisk";"Larva";182;2
"Unit";"Hydralisk";"Larva";182;2
"Unit";"Hydralisk";"Larva";182;2
"Unit";"Hydralisk";"Larva";182;2
"Unit";"Hydralisk";"Larva";182;2
"Unit";"Hydralisk";"Larva";182;2
"Unit";"Hydralisk";"Larva";182;2
"Upgrade";"EvolveGroovedSpines";"HydraliskDen";140;0
"Upgrade";"ZergMeleeWeaponsLevel1";"EvolutionChamber";138;0
"Upgrade";"ZergMissileWeaponsLevel1";"EvolutionChamber";138;0
"Unit";"Zergling";"Larva";201;1
"Unit";"Zergling";"Larva";201;1
"Unit";"Zergling";"Larva";201;1
"Unit";"Zergling";"Larva";201;1
"Unit";"Hydralisk";"Larva";201;2
"Unit";"Hydralisk";"Larva";201;2
"Unit";"Hydralisk";"Larva";201;2
"Unit";"Hydralisk";"Larva";201;2
"Unit";"Hydralisk";"Larva";201;2
"Unit";"Hydralisk";"Larva";201;2
"Unit";"Hydralisk";"Larva";201;2
"Unit";"Hydralisk";"Larva";201;2
"Unit";"Hydralisk";"Larva";201;2
"Unit";"Hydralisk";"Larva";201;2
"Unit";"Hydralisk";"Larva";201;2
"Unit";"Zergling";"Larva";201;1
"Unit";"Zergling";"Larva";201;1
"Unit";"Zergling";"Larva";201;1
"Unit";"Zergling";"Larva";201;1
"Unit";"Zergling";"Larva";201;1
"Unit";"Zergling";"Larva";201;1
"Unit";"Zergling";"Larva";201;1
"Unit";"Zergling";"Larva";201;1
"Unit";"Zergling";"Larva";201;1
"Unit";"Zergling";"Larva";201;1
"Unit";"Zergling";"Larva";201;1
"Unit";"Zergling";"Larva";201;1
"Unit";"Hydralisk";"Larva";201;2
"Building";"CreepTumor";NA;227;0
"Building";"Extractor";NA;205;0
"Building";"CreepTumorQueen";NA;241;0
"Unit";"Overlord";"Larva";239;0
"Building";"LurkerDenMP";NA;182;0
"Building";"Hatchery";NA;185;0
"Unit";"Queen";"Hatchery";227;2
"Unit";"Overlord";"Larva";245;0
"Unit";"Overlord";"Larva";245;0
"Unit";"Baneling";"Zergling";245;0
"Unit";"Overlord";"Larva";245;0
"Unit";"Baneling";"Zergling";245;0
"Unit";"Baneling";"Zergling";245;0
"Unit";"Baneling";"Zergling";245;0
"Unit";"Baneling";"Zergling";245;0
"Unit";"Baneling";"Zergling";245;0
"Unit";"Baneling";"Zergling";245;0
"Unit";"Baneling";"Zergling";245;0
"Unit";"Overlord";"Larva";245;0
"Unit";"Zergling";"Larva";245;1
"Unit";"Zergling";"Larva";245;1
"Unit";"Zergling";"Larva";245;1
"Unit";"Zergling";"Larva";245;1
"Unit";"Zergling";"Larva";245;1
"Unit";"Zergling";"Larva";245;1
"Unit";"Zergling";"Larva";253;1
"Unit";"Zergling";"Larva";253;1
"Unit";"Zergling";"Larva";253;1
"Unit";"Zergling";"Larva";253;1
"Unit";"Zergling";"Larva";253;1
"Unit";"Zergling";"Larva";253;1
"Unit";"Zergling";"Larva";253;1
"Unit";"Zergling";"Larva";253;1
"Unit";"Zergling";"Larva";253;1
"Unit";"Zergling";"Larva";253;1
"Unit";"Zergling";"Larva";253;1
"Unit";"Zergling";"Larva";253;1
"Unit";"Zergling";"Larva";253;1
"Unit";"Zergling";"Larva";253;1
"Unit";"Zergling";"Larva";253;1
"Unit";"Zergling";"Larva";253;1
"Unit";"Zergling";"Larva";253;1
"Unit";"Zergling";"Larva";253;1
"Unit";"Hydralisk";"Larva";253;2
"Unit";"Hydralisk";"Larva";253;2
"Unit";"Hydralisk";"Larva";253;2
"Unit";"Hydralisk";"Larva";253;2
"Unit";"Hydralisk";"Larva";253;2
"Unit";"Hydralisk";"Larva";253;2
"Unit";"Hydralisk";"Larva";253;2
"Unit";"Hydralisk";"Larva";253;2
"Unit";"Hydralisk";"Larva";253;2
"Unit";"Hydralisk";"Larva";255;2
"Unit";"Zergling";"Larva";287;1
"Unit";"Zergling";"Larva";287;1
"Unit";"Zergling";"Larva";287;1
"Unit";"Zergling";"Larva";287;1
"Unit";"Zergling";"Larva";287;1
"Unit";"Zergling";"Larva";287;1
"Unit";"Zergling";"Larva";287;1
"Unit";"Zergling";"Larva";287;1
"Unit";"Zergling";"Larva";287;1
"Unit";"Zergling";"Larva";287;1
"Unit";"Zergling";"Larva";287;1
"Unit";"Zergling";"Larva";287;1
"Unit";"Zergling";"Larva";287;1
"Unit";"Zergling";"Larva";287;1
"Unit";"Zergling";"Larva";287;1
"Unit";"Zergling";"Larva";287;1
"Unit";"Zergling";"Larva";287;1
"Unit";"Zergling";"Larva";287;1
"Unit";"Zergling";"Larva";287;1
"Unit";"Zergling";"Larva";287;1
"Unit";"Zergling";"Larva";287;1
"Unit";"Zergling";"Larva";287;1
"Unit";"Zergling";"Larva";287;1
"Unit";"Zergling";"Larva";287;1
"Unit";"Zergling";"Larva";293;1
"Unit";"Zergling";"Larva";293;1
"Unit";"Zergling";"Larva";297;1
"Unit";"Zergling";"Larva";297;1
"Unit";"Zergling";"Larva";297;1
"Unit";"Zergling";"Larva";297;1
"Unit";"Zergling";"Larva";301;1
"Unit";"Zergling";"Larva";301;1
"Unit";"Zergling";"Larva";301;1
"Unit";"Zergling";"Larva";301;1
"Unit";"Zergling";"Larva";305;1
"Unit";"Zergling";"Larva";305;1
"Unit";"Zergling";"Larva";305;1
"Unit";"Zergling";"Larva";305;1
"Unit";"Zergling";"Larva";309;1
"Unit";"Zergling";"Larva";309;1
"Unit";"Overlord";"Larva";315;0
"Upgrade";"ZergMissileWeaponsLevel2";"EvolutionChamber";245;0
"Upgrade";"ZergMeleeWeaponsLevel2";"EvolutionChamber";245;0
"Unit";"Baneling";"Zergling";331;0
"Unit";"Baneling";"Zergling";331;0
"Unit";"Baneling";"Zergling";331;0
"Unit";"Baneling";"Zergling";331;0
"Unit";"Baneling";"Zergling";331;0
"Unit";"Baneling";"Zergling";331;0
"Unit";"Baneling";"Zergling";331;0
"Unit";"Baneling";"Zergling";331;0
"Unit";"Baneling";"Zergling";331;0
"Unit";"Baneling";"Zergling";331;0
"Unit";"Baneling";"Zergling";331;0
"Unit";"Hydralisk";"Larva";343;2
"Unit";"Hydralisk";"Larva";343;2
"Unit";"Hydralisk";"Larva";343;2
"Unit";"Hydralisk";"Larva";343;2
"Unit";"Hydralisk";"Larva";343;2
"Unit";"Hydralisk";"Larva";343;2
"Unit";"Hydralisk";"Larva";343;2
"Unit";"Hydralisk";"Larva";343;2
"Unit";"Hydralisk";"Larva";343;2
"Unit";"Hydralisk";"Larva";343;2
"Unit";"Hydralisk";"Larva";343;2
"Unit";"Hydralisk";"Larva";343;2
"Unit";"Hydralisk";"Larva";343;2
"Unit";"Hydralisk";"Larva";343;2
"Building";"Spire";NA;343;0
"Unit";"Zergling";"Larva";371;1
"Unit";"Zergling";"Larva";371;1
"Unit";"Zergling";"Larva";371;1
"Unit";"Zergling";"Larva";371;1
"Unit";"Zergling";"Larva";371;1
"Unit";"Zergling";"Larva";371;1
"Unit";"Zergling";"Larva";371;1
"Unit";"Zergling";"Larva";371;1
"Unit";"Zergling";"Larva";371;1
"Unit";"Zergling";"Larva";371;1
"Unit";"Zergling";"Larva";371;1
"Unit";"Zergling";"Larva";371;1
"Unit";"Zergling";"Larva";371;1
"Unit";"Zergling";"Larva";371;1
"Unit";"Zergling";"Larva";371;1
"Unit";"Zergling";"Larva";371;1
"Unit";"Zergling";"Larva";371;1
"Unit";"Zergling";"Larva";371;1
"Unit";"Zergling";"Larva";371;1
"Unit";"Zergling";"Larva";371;1
"Unit";"Zergling";"Larva";371;1
"Unit";"Zergling";"Larva";371;1
"Unit";"Zergling";"Larva";371;1
"Unit";"Zergling";"Larva";371;1
"Unit";"Zergling";"Larva";371;1
"Unit";"Zergling";"Larva";371;1
"Unit";"Zergling";"Larva";371;1
"Unit";"Zergling";"Larva";371;1
"Unit";"Zergling";"Larva";371;1
"Unit";"Zergling";"Larva";371;1
"Unit";"Zergling";"Larva";371;1
"Unit";"Zergling";"Larva";371;1
"Unit";"Zergling";"Larva";371;1
"Unit";"Zergling";"Larva";371;1
"Unit";"Zergling";"Larva";371;1
"Unit";"Zergling";"Larva";371;1
"Unit";"Zergling";"Larva";377;1
"Unit";"Zergling";"Larva";377;1
"Unit";"Zergling";"Larva";377;1
"Unit";"Zergling";"Larva";377;1
"Unit";"Zergling";"Larva";377;1
"Unit";"Zergling";"Larva";377;1
"Unit";"Zergling";"Larva";377;1
"Unit";"Zergling";"Larva";377;1
"Unit";"Zergling";"Larva";377;1
"Unit";"Zergling";"Larva";377;1
