"type";"unit_name";"on_building";"total_supply";"supply"
"Unit";"Overlord";"Larva";13;0
"Building";"Extractor";NA;18;0
"Unit";"Overlord";"Larva";21;0
"Building";"SpawningPool";NA;19;0
"Building";"Hatchery";NA;17;0
"Unit";"Zergling";"Larva";22;1
"Unit";"Zergling";"Larva";22;1
"Unit";"Zergling";"Larva";23;1
"Unit";"Zergling";"Larva";23;1
"Unit";"Zergling";"Larva";23;1
"Unit";"Zergling";"Larva";23;1
"Unit";"Queen";"Hatchery";22;2
"Unit";"Queen";"Hatchery";23;2
"Unit";"Overlord";"Larva";33;0
"Unit";"Overlord";"Larva";37;0
"Building";"SporeCrawler";NA;40;0
"Unit";"Queen";"Hatchery";37;2
"Building";"SporeCrawler";NA;40;0
"Building";"Hatchery";NA;29;0
"Unit";"Overlord";"Larva";45;0
"Building";"CreepTumorQueen";NA;47;0
"Building";"SporeCrawler";NA;50;0
"Building";"Extractor";NA;50;0
"Unit";"Queen";"Hatchery";47;2
"Building";"Extractor";NA;50;0
"Building";"CreepTumorQueen";NA;55;0
"Building";"CreepTumor";NA;55;0
"Unit";"Overlord";"Larva";55;0
"Building";"HydraliskDen";NA;65;0
"Unit";"Overlord";"Larva";68;0
"Building";"CreepTumor";NA;73;0
"Building";"CreepTumor";NA;73;0
"Building";"Extractor";NA;73;0
"Unit";"Overlord";"Larva";73;0
"Unit";"Overlord";"Larva";73;0
"Building";"CreepTumorQueen";NA;75;0
"Unit";"Hydralisk";"Larva";73;2
"Unit";"Hydralisk";"Larva";73;2
"Unit";"Hydralisk";"Larva";73;2
"Unit";"Hydralisk";"Larva";73;2
"Unit";"Hydralisk";"Larva";73;2
"Unit";"Hydralisk";"Larva";73;2
"Unit";"Overlord";"Larva";76;0
"Unit";"Overlord";"Larva";76;0
"Unit";"Overlord";"Larva";76;0
"Unit";"Overlord";"Larva";76;0
"Unit";"Overlord";"Larva";76;0
"Unit";"Zergling";"Larva";88;1
"Unit";"Zergling";"Larva";88;1
"Unit";"Zergling";"Larva";88;1
"Unit";"Zergling";"Larva";88;1
"Unit";"Hydralisk";"Larva";88;2
"Unit";"Hydralisk";"Larva";88;2
"Unit";"Hydralisk";"Larva";88;2
"Unit";"Hydralisk";"Larva";88;2
"Upgrade";"EvolveMuscularAugments";"HydraliskDen";75;0
"Unit";"Zergling";"Larva";88;1
"Unit";"Zergling";"Larva";88;1
"Unit";"Zergling";"Larva";88;1
"Unit";"Zergling";"Larva";88;1
"Unit";"Zergling";"Larva";88;1
"Unit";"Zergling";"Larva";88;1
"Building";"CreepTumorQueen";NA;98;0
"Unit";"Hydralisk";"Larva";88;2
"Unit";"Hydralisk";"Larva";88;2
"Unit";"Hydralisk";"Larva";88;2
"Unit";"Zergling";"Larva";98;1
"Unit";"Zergling";"Larva";98;1
"Unit";"Zergling";"Larva";98;1
"Unit";"Zergling";"Larva";98;1
"Unit";"Hydralisk";"Larva";98;2
"Unit";"Hydralisk";"Larva";98;2
"Unit";"Zergling";"Larva";106;1
"Unit";"Zergling";"Larva";106;1
"Unit";"Zergling";"Larva";106;1
"Unit";"Zergling";"Larva";106;1
"Unit";"Zergling";"Larva";106;1
"Unit";"Zergling";"Larva";106;1
"Unit";"Zergling";"Larva";106;1
"Unit";"Zergling";"Larva";106;1
"Unit";"Hydralisk";"Larva";106;2
"Unit";"Hydralisk";"Larva";106;2
"Unit";"Hydralisk";"Larva";106;2
"Unit";"Overlord";"Larva";128;0
"Unit";"Zergling";"Larva";128;1
"Unit";"Zergling";"Larva";128;1
"Unit";"Zergling";"Larva";128;1
"Unit";"Zergling";"Larva";128;1
"Unit";"Zergling";"Larva";128;1
"Unit";"Zergling";"Larva";128;1
"Unit";"Zergling";"Larva";128;1
"Unit";"Zergling";"Larva";128;1
"Unit";"Zergling";"Larva";128;1
"Unit";"Zergling";"Larva";128;1
"Unit";"Zergling";"Larva";128;1
"Unit";"Zergling";"Larva";128;1
"Unit";"Zergling";"Larva";128;1
"Unit";"Zergling";"Larva";128;1
"Unit";"Hydralisk";"Larva";128;2
"Unit";"Hydralisk";"Larva";128;2
"Building";"Extractor";NA;134;0
"Unit";"Overlord";"Larva";134;0
"Unit";"Hydralisk";"Larva";134;2
"Unit";"Zergling";"Larva";157;1
"Unit";"Zergling";"Larva";157;1
"Unit";"Zergling";"Larva";157;1
"Unit";"Zergling";"Larva";157;1
"Unit";"Hydralisk";"Larva";153;2
"Unit";"Hydralisk";"Larva";153;2
"Upgrade";"EvolveGroovedSpines";"HydraliskDen";120;0
"Unit";"Hydralisk";"Larva";157;2
"Unit";"Hydralisk";"Larva";157;2
"Unit";"Hydralisk";"Larva";157;2
"Unit";"Zergling";"Larva";167;1
"Unit";"Zergling";"Larva";167;1
"Unit";"Zergling";"Larva";167;1
"Unit";"Zergling";"Larva";167;1
"Unit";"Zergling";"Larva";167;1
"Unit";"Zergling";"Larva";167;1
"Unit";"Zergling";"Larva";167;1
"Unit";"Zergling";"Larva";167;1
"Unit";"Zergling";"Larva";167;1
"Unit";"Zergling";"Larva";167;1
"Unit";"Hydralisk";"Larva";167;2
"Unit";"Hydralisk";"Larva";167;2
"Unit";"Hydralisk";"Larva";167;2
"Unit";"Hydralisk";"Larva";167;2
"Unit";"Zergling";"Larva";169;1
"Unit";"Zergling";"Larva";169;1
"Unit";"Zergling";"Larva";169;1
"Unit";"Zergling";"Larva";169;1
"Unit";"Hydralisk";"Larva";169;2
"Unit";"Hydralisk";"Larva";169;2
"Unit";"Zergling";"Larva";173;1
"Unit";"Zergling";"Larva";173;1
"Unit";"Hydralisk";"Larva";173;2
"Unit";"Hydralisk";"Larva";173;2
"Unit";"Zergling";"Larva";191;1
"Unit";"Zergling";"Larva";191;1
"Unit";"Hydralisk";"Larva";191;2
"Unit";"Hydralisk";"Larva";191;2
"Unit";"Hydralisk";"Larva";195;2
"Unit";"Zergling";"Larva";205;1
"Unit";"Zergling";"Larva";205;1
"Unit";"Zergling";"Larva";205;1
"Unit";"Zergling";"Larva";205;1
"Unit";"Zergling";"Larva";205;1
"Unit";"Zergling";"Larva";205;1
"Unit";"Hydralisk";"Larva";205;2
"Unit";"Hydralisk";"Larva";205;2
"Unit";"Hydralisk";"Larva";211;2
"Unit";"Hydralisk";"Larva";211;2
"Unit";"Hydralisk";"Larva";211;2
"Unit";"Hydralisk";"Larva";219;2
"Unit";"Hydralisk";"Larva";219;2
"Unit";"Hydralisk";"Larva";223;2
