"type";"unit_name";"on_building";"total_supply";"supply"
"Unit";"Overlord";"Larva";13;0
"Building";"Extractor";NA;17;0
"Building";"SpawningPool";NA;19;0
"Building";"Hatchery";NA;17;0
"Unit";"Overlord";"Larva";22;0
"Unit";"Zergling";"Larva";22;1
"Unit";"Zergling";"Larva";22;1
"Unit";"Zergling";"Larva";22;1
"Unit";"Zergling";"Larva";22;1
"Unit";"Zergling";"Larva";22;1
"Unit";"Zergling";"Larva";22;1
"Unit";"Queen";"Hatchery";22;2
"Unit";"Queen";"Hatchery";22;2
"Unit";"Overlord";"Larva";41;0
"Unit";"Overlord";"Larva";41;0
"Building";"CreepTumorQueen";NA;41;0
"Unit";"Queen";"Hatchery";38;2
"Unit";"Overlord";"Larva";41;0
"Building";"SporeCrawler";NA;41;0
"Building";"CreepTumor";NA;46;0
"Building";"CreepTumorQueen";NA;49;0
"Building";"SporeCrawler";NA;41;0
"Building";"Hatchery";NA;38;0
"Unit";"Overlord";"Larva";50;0
"Building";"CreepTumor";NA;54;0
"Building";"CreepTumor";NA;54;0
"Building";"RoachWarren";NA;49;0
"Building";"Extractor";NA;54;0
"Building";"Extractor";NA;54;0
"Building";"CreepTumor";NA;63;0
"Building";"CreepTumor";NA;69;0
"Unit";"Roach";"Larva";63;2
"Unit";"Roach";"Larva";63;2
"Unit";"Overlord";"Larva";69;0
"Building";"EvolutionChamber";NA;66;0
"Unit";"Overlord";"Larva";69;0
"Unit";"Roach";"Larva";69;2
"Unit";"Roach";"Larva";69;2
"Unit";"Roach";"Larva";69;2
"Unit";"Roach";"Larva";73;2
"Unit";"Roach";"Larva";75;2
"Unit";"Roach";"Larva";75;2
"Unit";"Zergling";"Larva";76;1
"Unit";"Zergling";"Larva";76;1
"Unit";"Zergling";"Larva";76;1
"Unit";"Zergling";"Larva";76;1
"Unit";"Zergling";"Larva";76;1
"Unit";"Zergling";"Larva";76;1
"Unit";"Zergling";"Larva";76;1
"Unit";"Zergling";"Larva";76;1
"Unit";"Roach";"Larva";82;2
"Unit";"Roach";"Larva";82;2
"Unit";"Roach";"Larva";84;2
"Unit";"Overlord";"Larva";96;0
"Unit";"Overlord";"Larva";96;0
"Unit";"Overlord";"Larva";96;0
"Unit";"Overlord";"Larva";96;0
"Building";"CreepTumor";NA;102;0
"Unit";"Zergling";"Larva";102;1
"Unit";"Zergling";"Larva";102;1
"Unit";"Zergling";"Larva";102;1
"Unit";"Zergling";"Larva";102;1
"Unit";"Zergling";"Larva";102;1
"Unit";"Zergling";"Larva";102;1
"Unit";"Zergling";"Larva";102;1
"Unit";"Zergling";"Larva";102;1
"Unit";"Zergling";"Larva";102;1
"Unit";"Zergling";"Larva";102;1
"Unit";"Zergling";"Larva";102;1
"Unit";"Zergling";"Larva";102;1
"Building";"CreepTumor";NA;105;0
"Unit";"Zergling";"Larva";105;1
"Unit";"Zergling";"Larva";105;1
"Unit";"Zergling";"Larva";105;1
"Unit";"Zergling";"Larva";105;1
"Unit";"Zergling";"Larva";105;1
"Unit";"Zergling";"Larva";105;1
"Building";"CreepTumor";NA;131;0
"Unit";"Roach";"Larva";128;2
"Unit";"Roach";"Larva";128;2
"Unit";"Roach";"Larva";128;2
"Unit";"Roach";"Larva";131;2
"Unit";"Roach";"Larva";131;2
"Building";"Extractor";NA;134;0
"Unit";"Overlord";"Larva";134;0
"Unit";"Overlord";"Larva";134;0
"Upgrade";"ZergMissileWeaponsLevel1";"EvolutionChamber";102;0
"Unit";"Overlord";"Larva";148;0
"Unit";"Overlord";"Larva";148;0
"Building";"CreepTumor";NA;148;0
"Upgrade";"GlialReconstitution";"RoachWarren";120;0
"Building";"Hatchery";NA;105;0
"Unit";"Zergling";"Larva";148;1
"Unit";"Zergling";"Larva";148;1
"Unit";"Zergling";"Larva";148;1
"Unit";"Zergling";"Larva";148;1
"Unit";"Overlord";"Larva";148;0
"Unit";"Overlord";"Larva";148;0
"Unit";"Overlord";"Larva";148;0
"Unit";"Overlord";"Larva";148;0
"Building";"EvolutionChamber";NA;148;0
"Unit";"Zergling";"Larva";152;1
"Unit";"Zergling";"Larva";152;1
"Unit";"Zergling";"Larva";152;1
"Unit";"Zergling";"Larva";152;1
"Unit";"Zergling";"Larva";152;1
"Unit";"Zergling";"Larva";152;1
"Unit";"Zergling";"Larva";157;1
"Unit";"Zergling";"Larva";157;1
"Unit";"Zergling";"Larva";157;1
"Unit";"Zergling";"Larva";157;1
"Unit";"Zergling";"Larva";157;1
"Unit";"Zergling";"Larva";157;1
"Unit";"Zergling";"Larva";157;1
"Unit";"Zergling";"Larva";157;1
"Unit";"Roach";"Larva";166;2
"Unit";"Roach";"Larva";166;2
"Unit";"Roach";"Larva";166;2
"Unit";"Roach";"Larva";174;2
"Unit";"Roach";"Larva";174;2
"Unit";"Roach";"Larva";174;2
"Unit";"Roach";"Larva";174;2
"Unit";"Roach";"Larva";174;2
"Building";"CreepTumor";NA;200;0
"Unit";"Roach";"Larva";186;2
"Unit";"Roach";"Larva";186;2
"Unit";"Roach";"Larva";186;2
"Building";"CreepTumor";NA;200;0
"Unit";"Roach";"Larva";200;2
"Unit";"Roach";"Larva";200;2
"Building";"Extractor";NA;200;0
"Unit";"Queen";"Hatchery";180;2
"Unit";"Roach";"Larva";200;2
"Unit";"Roach";"Larva";200;2
"Building";"BanelingNest";NA;186;0
"Building";"Extractor";NA;214;0
"Building";"CreepTumor";NA;226;0
"Unit";"Overlord";"Larva";227;0
"Unit";"Queen";"Hatchery";220;2
"Upgrade";"ZergGroundArmorsLevel1";"EvolutionChamber";200;0
"Building";"SporeCrawler";NA;235;0
"Building";"SporeCrawler";NA;235;0
"Unit";"Zergling";"Larva";237;1
"Unit";"Zergling";"Larva";237;1
"Unit";"Roach";"Larva";237;2
"Unit";"Zergling";"Larva";237;1
"Unit";"Zergling";"Larva";237;1
"Unit";"Zergling";"Larva";237;1
"Unit";"Zergling";"Larva";237;1
"Unit";"Roach";"Larva";237;2
"Unit";"Roach";"Larva";237;2
"Unit";"Roach";"Larva";237;2
"Unit";"Roach";"Larva";237;2
"Unit";"Roach";"Larva";237;2
"Unit";"Roach";"Larva";237;2
"Unit";"Roach";"Larva";237;2
"Unit";"Roach";"Larva";237;2
"Building";"Spire";NA;214;0
"Unit";"Roach";"Larva";239;2
"Unit";"Roach";"Larva";239;2
"Unit";"Roach";"Larva";239;2
"Upgrade";"ZergMissileWeaponsLevel2";"EvolutionChamber";200;0
"Unit";"Roach";"Larva";263;2
"Unit";"Roach";"Larva";263;2
"Unit";"Roach";"Larva";263;2
"Unit";"Mutalisk";"Larva";269;2
"Unit";"Mutalisk";"Larva";269;2
"Unit";"Mutalisk";"Larva";269;2
"Unit";"Mutalisk";"Larva";269;2
"Unit";"Mutalisk";"Larva";269;2
"Unit";"Zergling";"Larva";269;1
"Unit";"Zergling";"Larva";269;1
"Unit";"Zergling";"Larva";269;1
"Unit";"Zergling";"Larva";269;1
"Unit";"Zergling";"Larva";269;1
"Unit";"Zergling";"Larva";269;1
"Unit";"Zergling";"Larva";269;1
"Unit";"Zergling";"Larva";269;1
"Unit";"Zergling";"Larva";269;1
"Unit";"Zergling";"Larva";269;1
"Unit";"Mutalisk";"Larva";269;2
"Unit";"Mutalisk";"Larva";275;2
"Unit";"Mutalisk";"Larva";275;2
"Unit";"Zergling";"Larva";291;1
"Unit";"Zergling";"Larva";291;1
"Unit";"Zergling";"Larva";293;1
"Unit";"Zergling";"Larva";293;1
"Unit";"Zergling";"Larva";295;1
"Unit";"Zergling";"Larva";295;1
"Unit";"Zergling";"Larva";295;1
"Unit";"Zergling";"Larva";295;1
"Unit";"Mutalisk";"Larva";299;2
"Unit";"Mutalisk";"Larva";299;2
"Unit";"Mutalisk";"Larva";309;2
"Unit";"Zergling";"Larva";309;1
"Unit";"Zergling";"Larva";309;1
"Unit";"Zergling";"Larva";309;1
"Unit";"Zergling";"Larva";309;1
"Unit";"Zergling";"Larva";309;1
"Unit";"Zergling";"Larva";309;1
"Unit";"Zergling";"Larva";309;1
"Unit";"Zergling";"Larva";309;1
"Unit";"Zergling";"Larva";309;1
"Unit";"Zergling";"Larva";309;1
"Unit";"Mutalisk";"Larva";309;2
"Unit";"Roach";"Larva";313;2
"Unit";"Roach";"Larva";313;2
"Building";"CreepTumor";NA;315;0
"Unit";"Zergling";"Larva";313;1
"Unit";"Zergling";"Larva";313;1
"Building";"Extractor";NA;313;0
"Building";"Extractor";NA;313;0
"Unit";"Queen";"Hatchery";313;2
"Unit";"Queen";"Hatchery";313;2
"Unit";"Zergling";"Larva";327;1
"Unit";"Zergling";"Larva";327;1
"Unit";"Zergling";"Larva";327;1
"Unit";"Zergling";"Larva";327;1
"Unit";"Zergling";"Larva";327;1
"Unit";"Zergling";"Larva";327;1
"Unit";"Zergling";"Larva";333;1
"Unit";"Zergling";"Larva";333;1
"Unit";"Zergling";"Larva";333;1
"Unit";"Zergling";"Larva";333;1
"Unit";"Zergling";"Larva";333;1
"Unit";"Zergling";"Larva";333;1
"Unit";"Zergling";"Larva";333;1
"Unit";"Zergling";"Larva";333;1
"Building";"BanelingNest";NA;313;0
"Unit";"Mutalisk";"Larva";336;2
"Unit";"Mutalisk";"Larva";346;2
"Unit";"Roach";"Larva";358;2
"Unit";"Roach";"Larva";358;2
"Unit";"Roach";"Larva";358;2
"Unit";"Mutalisk";"Larva";358;2
"Unit";"Mutalisk";"Larva";358;2
"Unit";"Mutalisk";"Larva";358;2
"Building";"Hatchery";NA;327;0
"Unit";"Zergling";"Larva";358;1
"Unit";"Zergling";"Larva";358;1
"Unit";"Zergling";"Larva";358;1
"Unit";"Zergling";"Larva";358;1
"Unit";"Zergling";"Larva";358;1
"Unit";"Zergling";"Larva";358;1
"Unit";"Roach";"Larva";358;2
"Unit";"Roach";"Larva";358;2
"Unit";"Roach";"Larva";360;2
"Unit";"Roach";"Larva";373;2
"Unit";"Roach";"Larva";373;2
"Unit";"Roach";"Larva";379;2
"Unit";"Roach";"Larva";379;2
"Unit";"Roach";"Larva";381;2
"Unit";"Roach";"Larva";383;2
"Unit";"Roach";"Larva";383;2
"Unit";"Roach";"Larva";383;2
"Unit";"Roach";"Larva";383;2
"Unit";"Roach";"Larva";383;2
"Unit";"Baneling";"Zergling";387;0
"Unit";"Baneling";"Zergling";387;0
"Unit";"Baneling";"Zergling";387;0
"Unit";"Zergling";"Larva";387;1
"Unit";"Zergling";"Larva";387;1
"Unit";"Zergling";"Larva";387;1
"Unit";"Zergling";"Larva";387;1
"Unit";"Zergling";"Larva";387;1
"Unit";"Zergling";"Larva";387;1
"Unit";"Zergling";"Larva";387;1
"Unit";"Zergling";"Larva";387;1
"Unit";"Zergling";"Larva";387;1
"Unit";"Zergling";"Larva";387;1
"Unit";"Zergling";"Larva";387;1
"Unit";"Zergling";"Larva";387;1
"Unit";"Baneling";"Zergling";389;0
"Unit";"Baneling";"Zergling";389;0
"Unit";"Baneling";"Zergling";389;0
"Unit";"Baneling";"Zergling";389;0
"Unit";"Baneling";"Zergling";389;0
"Unit";"Queen";"Hatchery";379;2
"Unit";"Roach";"Larva";389;2
"Unit";"Roach";"Larva";389;2
"Unit";"Roach";"Larva";423;2
"Unit";"Roach";"Larva";423;2
"Unit";"Roach";"Larva";423;2
"Unit";"Roach";"Larva";423;2
"Unit";"Roach";"Larva";423;2
"Unit";"Roach";"Larva";423;2
"Unit";"Roach";"Larva";423;2
"Unit";"Roach";"Larva";423;2
"Unit";"Roach";"Larva";423;2
"Unit";"Roach";"Larva";423;2
"Unit";"Roach";"Larva";423;2
"Unit";"Roach";"Larva";423;2
"Unit";"Roach";"Larva";423;2
"Unit";"Roach";"Larva";423;2
"Unit";"Roach";"Larva";423;2
"Unit";"Roach";"Larva";423;2
"Unit";"Overlord";"Larva";423;0
"Unit";"Overlord";"Larva";423;0
"Unit";"Roach";"Larva";423;2
"Unit";"Roach";"Larva";423;2
"Unit";"Roach";"Larva";423;2
"Unit";"Queen";"Hatchery";423;2
"Unit";"Overlord";"Larva";451;0
"Unit";"Overlord";"Larva";451;0
"Unit";"Overlord";"Larva";451;0
"Unit";"Overlord";"Larva";453;0
"Building";"CreepTumor";NA;463;0
"Unit";"Zergling";"Larva";461;1
"Unit";"Zergling";"Larva";461;1
"Unit";"Zergling";"Larva";461;1
"Unit";"Zergling";"Larva";461;1
"Unit";"Zergling";"Larva";461;1
"Unit";"Zergling";"Larva";461;1
"Unit";"Zergling";"Larva";461;1
"Unit";"Zergling";"Larva";461;1
"Unit";"Zergling";"Larva";461;1
"Unit";"Zergling";"Larva";461;1
"Unit";"Zergling";"Larva";461;1
"Unit";"Zergling";"Larva";461;1
"Unit";"Roach";"Larva";465;2
"Unit";"Zergling";"Larva";465;1
"Unit";"Zergling";"Larva";465;1
"Unit";"Zergling";"Larva";465;1
"Unit";"Zergling";"Larva";465;1
"Unit";"Roach";"Larva";477;2
"Unit";"Roach";"Larva";477;2
"Building";"Extractor";NA;481;0
"Unit";"Roach";"Larva";487;2
"Unit";"Roach";"Larva";487;2
"Unit";"Roach";"Larva";487;2
"Unit";"Roach";"Larva";487;2
