"type";"unit_name";"on_building";"total_supply";"supply"
"Unit";"Overlord";"Larva";12;0
"Building";"Extractor";NA;19;0
"Building";"SpawningPool";NA;17;0
"Unit";"Zergling";"Larva";19;1
"Unit";"Zergling";"Larva";19;1
"Unit";"Zergling";"Larva";19;1
"Unit";"Zergling";"Larva";19;1
"Unit";"Zergling";"Larva";19;1
"Unit";"Zergling";"Larva";19;1
"Unit";"Overlord";"Larva";19;0
"Unit";"Queen";"Hatchery";19;2
"Building";"Hatchery";NA;19;0
"Unit";"Queen";"Hatchery";28;2
"Building";"CreepTumorQueen";NA;36;0
"Building";"EvolutionChamber";NA;36;0
"Unit";"Zergling";"Larva";43;1
"Unit";"Zergling";"Larva";43;1
"Unit";"Zergling";"Larva";43;1
"Unit";"Zergling";"Larva";43;1
"Unit";"Overlord";"Larva";43;0
"Building";"CreepTumorQueen";NA;43;0
"Unit";"Queen";"Hatchery";40;2
"Building";"Hatchery";NA;31;0
"Building";"CreepTumorQueen";NA;55;0
"Building";"CreepTumor";NA;57;0
"Building";"CreepTumor";NA;57;0
"Building";"SporeCrawler";NA;63;0
"Unit";"Queen";"Hatchery";57;2
"Building";"SporeCrawler";NA;63;0
"Unit";"Overlord";"Larva";63;0
"Unit";"Overlord";"Larva";68;0
"Building";"SporeCrawler";NA;72;0
"Building";"CreepTumorQueen";NA;79;0
"Building";"CreepTumor";NA;79;0
"Building";"CreepTumor";NA;82;0
"Building";"CreepTumor";NA;82;0
"Building";"Extractor";NA;80;0
"Building";"Extractor";NA;80;0
"Unit";"Overlord";"Larva";88;0
"Building";"CreepTumor";NA;88;0
"Upgrade";"ZergMeleeWeaponsLevel1";"EvolutionChamber";63;0
"Unit";"Overlord";"Larva";88;0
"Unit";"Overlord";"Larva";90;0
"Building";"CreepTumorQueen";NA;91;0
"Building";"CreepTumor";NA;91;0
"Building";"CreepTumor";NA;91;0
"Building";"Hatchery";NA;72;0
"Building";"Extractor";NA;91;0
"Building";"CreepTumor";NA;91;0
"Building";"BanelingNest";NA;88;0
"Building";"CreepTumorQueen";NA;104;0
"Building";"Extractor";NA;99;0
"Building";"Extractor";NA;106;0
"Building";"CreepTumor";NA;111;0
"Building";"CreepTumor";NA;111;0
"Building";"CreepTumor";NA;111;0
"Unit";"Overlord";"Larva";111;0
"Unit";"Overlord";"Larva";111;0
"Building";"SporeCrawler";NA;111;0
"Unit";"Zergling";"Larva";111;1
"Unit";"Zergling";"Larva";111;1
"Unit";"Zergling";"Larva";111;1
"Unit";"Zergling";"Larva";111;1
"Unit";"Zergling";"Larva";111;1
"Unit";"Zergling";"Larva";111;1
"Unit";"Zergling";"Larva";111;1
"Unit";"Zergling";"Larva";111;1
"Unit";"Zergling";"Larva";111;1
"Unit";"Zergling";"Larva";111;1
"Unit";"Zergling";"Larva";111;1
"Unit";"Zergling";"Larva";111;1
"Unit";"Queen";"Hatchery";111;2
"Unit";"Overlord";"Larva";111;0
"Unit";"Overlord";"Larva";111;0
"Unit";"Overlord";"Larva";111;0
"Building";"HydraliskDen";NA;111;0
"Building";"CreepTumor";NA;128;0
"Unit";"Zergling";"Larva";128;1
"Unit";"Zergling";"Larva";128;1
"Unit";"Zergling";"Larva";128;1
"Unit";"Zergling";"Larva";128;1
"Unit";"Zergling";"Larva";128;1
"Unit";"Zergling";"Larva";128;1
"Unit";"Hydralisk";"Larva";128;2
"Unit";"Hydralisk";"Larva";128;2
"Unit";"Hydralisk";"Larva";128;2
"Unit";"Hydralisk";"Larva";128;2
"Unit";"Hydralisk";"Larva";128;2
"Unit";"Hydralisk";"Larva";128;2
"Unit";"Hydralisk";"Larva";128;2
"Unit";"Hydralisk";"Larva";128;2
"Building";"CreepTumor";NA;128;0
"Unit";"Hydralisk";"Larva";128;2
"Unit";"Hydralisk";"Larva";128;2
"Unit";"Hydralisk";"Larva";128;2
"Unit";"Hydralisk";"Larva";128;2
"Unit";"Hydralisk";"Larva";128;2
"Unit";"Hydralisk";"Larva";128;2
"Unit";"Hydralisk";"Larva";128;2
"Unit";"Overlord";"Larva";128;0
"Unit";"Overlord";"Larva";128;0
"Unit";"Overlord";"Larva";128;0
"Upgrade";"ZergGroundArmorsLevel1";"EvolutionChamber";111;0
"Unit";"Overlord";"Larva";130;0
"Unit";"Overlord";"Larva";164;0
"Building";"CreepTumor";NA;164;0
"Unit";"Overlord";"Larva";164;0
"Unit";"Overlord";"Larva";164;0
"Building";"Hatchery";NA;111;0
"Unit";"Hydralisk";"Larva";164;2
"Unit";"Hydralisk";"Larva";164;2
"Unit";"Hydralisk";"Larva";164;2
"Unit";"Overlord";"Larva";164;0
"Unit";"Hydralisk";"Larva";164;2
"Unit";"Hydralisk";"Larva";164;2
"Unit";"Hydralisk";"Larva";164;2
"Unit";"Hydralisk";"Larva";164;2
"Unit";"Hydralisk";"Larva";164;2
"Unit";"Hydralisk";"Larva";164;2
"Unit";"Hydralisk";"Larva";164;2
"Unit";"Hydralisk";"Larva";164;2
"Unit";"Overlord";"Larva";164;0
"Upgrade";"EvolveGroovedSpines";"HydraliskDen";128;0
"Unit";"Queen";"Hatchery";164;2
"Unit";"Zergling";"Larva";164;1
"Unit";"Zergling";"Larva";164;1
"Unit";"Zergling";"Larva";164;1
"Unit";"Zergling";"Larva";164;1
"Unit";"Zergling";"Larva";164;1
"Unit";"Zergling";"Larva";164;1
"Unit";"Zergling";"Larva";164;1
"Unit";"Zergling";"Larva";164;1
"Unit";"Zergling";"Larva";164;1
"Unit";"Zergling";"Larva";164;1
"Unit";"Zergling";"Larva";164;1
"Unit";"Zergling";"Larva";164;1
"Unit";"Zergling";"Larva";164;1
"Unit";"Zergling";"Larva";164;1
"Unit";"Zergling";"Larva";164;1
"Unit";"Zergling";"Larva";164;1
"Unit";"Zergling";"Larva";164;1
"Unit";"Zergling";"Larva";164;1
"Unit";"Zergling";"Larva";164;1
"Unit";"Zergling";"Larva";164;1
"Unit";"Zergling";"Larva";164;1
"Unit";"Zergling";"Larva";164;1
"Unit";"Zergling";"Larva";164;1
"Unit";"Zergling";"Larva";164;1
"Unit";"Zergling";"Larva";164;1
"Unit";"Zergling";"Larva";164;1
"Unit";"Zergling";"Larva";186;1
"Unit";"Zergling";"Larva";186;1
"Unit";"Zergling";"Larva";186;1
"Unit";"Zergling";"Larva";186;1
"Unit";"Zergling";"Larva";186;1
"Unit";"Zergling";"Larva";186;1
"Unit";"Zergling";"Larva";186;1
"Unit";"Zergling";"Larva";186;1
"Unit";"Zergling";"Larva";186;1
"Unit";"Zergling";"Larva";186;1
"Building";"CreepTumorQueen";NA;212;0
"Unit";"Zergling";"Larva";224;1
"Unit";"Zergling";"Larva";224;1
"Unit";"Zergling";"Larva";224;1
"Unit";"Zergling";"Larva";224;1
"Unit";"Zergling";"Larva";224;1
"Unit";"Zergling";"Larva";224;1
"Unit";"Zergling";"Larva";224;1
"Unit";"Zergling";"Larva";224;1
"Unit";"Zergling";"Larva";224;1
"Unit";"Zergling";"Larva";224;1
"Unit";"Zergling";"Larva";224;1
"Unit";"Zergling";"Larva";224;1
"Unit";"Zergling";"Larva";224;1
"Unit";"Zergling";"Larva";224;1
"Unit";"Zergling";"Larva";224;1
"Unit";"Zergling";"Larva";224;1
"Unit";"Zergling";"Larva";224;1
"Unit";"Zergling";"Larva";224;1
"Unit";"Zergling";"Larva";224;1
"Unit";"Zergling";"Larva";224;1
"Unit";"Zergling";"Larva";224;1
"Unit";"Zergling";"Larva";224;1
"Unit";"Zergling";"Larva";224;1
"Unit";"Zergling";"Larva";224;1
"Unit";"Zergling";"Larva";224;1
"Unit";"Zergling";"Larva";224;1
"Unit";"Zergling";"Larva";224;1
"Unit";"Zergling";"Larva";224;1
"Building";"Extractor";NA;224;0
"Building";"Extractor";NA;224;0
"Unit";"Zergling";"Larva";252;1
"Unit";"Zergling";"Larva";252;1
"Unit";"Zergling";"Larva";252;1
"Unit";"Zergling";"Larva";252;1
"Unit";"Zergling";"Larva";252;1
"Unit";"Zergling";"Larva";252;1
"Unit";"Zergling";"Larva";252;1
"Unit";"Zergling";"Larva";252;1
"Unit";"Zergling";"Larva";252;1
"Unit";"Zergling";"Larva";252;1
"Unit";"Zergling";"Larva";252;1
"Unit";"Zergling";"Larva";252;1
"Unit";"Zergling";"Larva";252;1
"Unit";"Zergling";"Larva";252;1
"Unit";"Zergling";"Larva";252;1
"Unit";"Zergling";"Larva";252;1
"Unit";"Zergling";"Larva";252;1
"Unit";"Zergling";"Larva";252;1
"Unit";"Zergling";"Larva";252;1
"Unit";"Zergling";"Larva";252;1
"Unit";"Zergling";"Larva";252;1
"Unit";"Zergling";"Larva";252;1
"Unit";"Zergling";"Larva";252;1
"Unit";"Zergling";"Larva";252;1
"Unit";"Zergling";"Larva";252;1
"Unit";"Zergling";"Larva";252;1
"Unit";"Zergling";"Larva";252;1
"Unit";"Zergling";"Larva";252;1
"Unit";"Zergling";"Larva";252;1
"Unit";"Zergling";"Larva";252;1
"Unit";"Zergling";"Larva";252;1
"Unit";"Zergling";"Larva";252;1
"Unit";"Hydralisk";"Larva";276;2
"Unit";"Hydralisk";"Larva";276;2
"Unit";"Hydralisk";"Larva";276;2
"Unit";"Hydralisk";"Larva";276;2
"Unit";"Hydralisk";"Larva";276;2
"Unit";"Hydralisk";"Larva";276;2
"Unit";"Hydralisk";"Larva";276;2
"Unit";"Hydralisk";"Larva";280;2
"Unit";"Hydralisk";"Larva";280;2
"Unit";"Hydralisk";"Larva";280;2
"Unit";"Hydralisk";"Larva";280;2
"Building";"CreepTumor";NA;284;0
"Building";"CreepTumor";NA;284;0
"Building";"CreepTumorQueen";NA;290;0
"Unit";"Hydralisk";"Larva";284;2
"Unit";"Hydralisk";"Larva";284;2
"Unit";"Hydralisk";"Larva";284;2
"Building";"CreepTumorQueen";NA;298;0
"Unit";"Hydralisk";"Larva";284;2
"Building";"CreepTumorQueen";NA;298;0
"Unit";"Hydralisk";"Larva";284;2
"Unit";"Hydralisk";"Larva";284;2
"Unit";"Hydralisk";"Larva";284;2
"Unit";"Hydralisk";"Larva";284;2
"Unit";"Hydralisk";"Larva";298;2
"Unit";"Hydralisk";"Larva";298;2
"Unit";"Hydralisk";"Larva";298;2
"Unit";"Hydralisk";"Larva";298;2
"Unit";"Hydralisk";"Larva";298;2
"Unit";"Hydralisk";"Larva";298;2
"Unit";"Zergling";"Larva";312;1
"Unit";"Zergling";"Larva";312;1
"Unit";"Overlord";"Larva";314;0
"Unit";"Hydralisk";"Larva";306;2
"Unit";"Hydralisk";"Larva";306;2
"Upgrade";"ZergMeleeWeaponsLevel2";"EvolutionChamber";224;0
"Upgrade";"EvolveMuscularAugments";"HydraliskDen";284;0
"Unit";"Overlord";"Larva";339;0
"Unit";"Zergling";"Larva";341;1
"Unit";"Zergling";"Larva";341;1
"Unit";"Zergling";"Larva";343;1
"Unit";"Zergling";"Larva";343;1
"Unit";"Zergling";"Larva";343;1
"Unit";"Zergling";"Larva";343;1
"Unit";"Zergling";"Larva";343;1
"Unit";"Zergling";"Larva";343;1
"Unit";"Zergling";"Larva";343;1
"Unit";"Zergling";"Larva";343;1
"Unit";"Zergling";"Larva";343;1
"Unit";"Zergling";"Larva";343;1
"Unit";"Zergling";"Larva";343;1
"Unit";"Zergling";"Larva";343;1
"Unit";"Zergling";"Larva";343;1
"Unit";"Zergling";"Larva";343;1
"Unit";"Overlord";"Larva";343;0
"Unit";"Overlord";"Larva";343;0
"Unit";"Overlord";"Larva";343;0
"Unit";"Zergling";"Larva";343;1
"Unit";"Zergling";"Larva";343;1
"Unit";"Zergling";"Larva";343;1
"Unit";"Zergling";"Larva";343;1
"Unit";"Zergling";"Larva";343;1
"Unit";"Zergling";"Larva";343;1
"Unit";"Zergling";"Larva";343;1
"Unit";"Zergling";"Larva";343;1
"Unit";"Hydralisk";"Larva";359;2
"Unit";"Hydralisk";"Larva";359;2
"Unit";"Hydralisk";"Larva";359;2
"Unit";"Hydralisk";"Larva";359;2
"Unit";"Hydralisk";"Larva";359;2
"Unit";"Hydralisk";"Larva";359;2
"Unit";"Hydralisk";"Larva";359;2
"Unit";"Hydralisk";"Larva";359;2
"Unit";"Hydralisk";"Larva";359;2
"Unit";"Hydralisk";"Larva";359;2
"Unit";"Hydralisk";"Larva";359;2
"Unit";"Hydralisk";"Larva";359;2
"Unit";"Hydralisk";"Larva";367;2
"Unit";"Hydralisk";"Larva";367;2
"Unit";"Hydralisk";"Larva";367;2
"Unit";"Hydralisk";"Larva";367;2
"Unit";"Zergling";"Larva";379;1
"Unit";"Zergling";"Larva";379;1
"Unit";"Zergling";"Larva";379;1
"Unit";"Zergling";"Larva";379;1
"Unit";"Zergling";"Larva";379;1
"Unit";"Zergling";"Larva";379;1
"Unit";"Hydralisk";"Larva";371;2
"Unit";"Hydralisk";"Larva";373;2
"Unit";"Hydralisk";"Larva";373;2
"Unit";"Hydralisk";"Larva";373;2
"Unit";"Hydralisk";"Larva";373;2
"Unit";"Hydralisk";"Larva";391;2
"Unit";"Hydralisk";"Larva";391;2
"Unit";"Hydralisk";"Larva";403;2
"Unit";"Hydralisk";"Larva";403;2
"Unit";"Hydralisk";"Larva";405;2
"Unit";"Hydralisk";"Larva";405;2
"Unit";"Hydralisk";"Larva";415;2
"Unit";"Hydralisk";"Larva";415;2
"Unit";"Hydralisk";"Larva";415;2
"Unit";"Hydralisk";"Larva";415;2
"Unit";"Hydralisk";"Larva";415;2
"Unit";"Hydralisk";"Larva";419;2
"Unit";"Hydralisk";"Larva";419;2
"Unit";"Zergling";"Larva";419;1
"Unit";"Zergling";"Larva";419;1
"Unit";"Zergling";"Larva";419;1
"Unit";"Zergling";"Larva";419;1
"Unit";"Zergling";"Larva";419;1
"Unit";"Zergling";"Larva";419;1
"Unit";"Zergling";"Larva";419;1
"Unit";"Zergling";"Larva";419;1
"Unit";"Hydralisk";"Larva";419;2
"Unit";"Overlord";"Larva";437;0
"Unit";"Zergling";"Larva";451;1
"Unit";"Zergling";"Larva";451;1
"Unit";"Hydralisk";"Larva";451;2
"Unit";"Hydralisk";"Larva";451;2
"Unit";"Hydralisk";"Larva";451;2
"Unit";"Hydralisk";"Larva";451;2
"Unit";"Hydralisk";"Larva";451;2
"Unit";"Hydralisk";"Larva";451;2
"Unit";"Hydralisk";"Larva";451;2
"Unit";"Hydralisk";"Larva";453;2
"Unit";"Hydralisk";"Larva";453;2
"Unit";"Hydralisk";"Larva";453;2
"Unit";"Hydralisk";"Larva";455;2
"Unit";"Hydralisk";"Larva";457;2
"Unit";"Hydralisk";"Larva";459;2
"Unit";"Hydralisk";"Larva";463;2
"Unit";"Hydralisk";"Larva";463;2
"Unit";"Hydralisk";"Larva";463;2
"Unit";"Hydralisk";"Larva";467;2
"Unit";"Hydralisk";"Larva";467;2
"Unit";"Hydralisk";"Larva";467;2
"Building";"CreepTumorQueen";NA;473;0
"Building";"CreepTumorQueen";NA;485;0
"Unit";"Zergling";"Larva";473;1
"Unit";"Zergling";"Larva";473;1
"Unit";"Zergling";"Larva";473;1
"Unit";"Zergling";"Larva";473;1
"Unit";"Zergling";"Larva";473;1
"Unit";"Zergling";"Larva";473;1
"Unit";"Zergling";"Larva";473;1
"Unit";"Zergling";"Larva";473;1
"Unit";"Zergling";"Larva";473;1
"Unit";"Zergling";"Larva";473;1
"Unit";"Zergling";"Larva";473;1
"Unit";"Zergling";"Larva";473;1
"Unit";"Zergling";"Larva";473;1
"Unit";"Zergling";"Larva";473;1
"Unit";"Zergling";"Larva";473;1
"Unit";"Zergling";"Larva";473;1
"Building";"CreepTumorQueen";NA;485;0
"Unit";"Zergling";"Larva";473;1
"Unit";"Zergling";"Larva";473;1
"Unit";"Zergling";"Larva";473;1
"Unit";"Zergling";"Larva";473;1
"Unit";"Zergling";"Larva";473;1
"Unit";"Zergling";"Larva";473;1
"Unit";"Zergling";"Larva";473;1
"Unit";"Zergling";"Larva";473;1
"Unit";"Zergling";"Larva";473;1
"Unit";"Zergling";"Larva";473;1
"Unit";"Zergling";"Larva";473;1
"Unit";"Zergling";"Larva";473;1
"Unit";"Zergling";"Larva";473;1
"Unit";"Zergling";"Larva";473;1
"Unit";"Zergling";"Larva";473;1
"Unit";"Zergling";"Larva";473;1
"Unit";"Zergling";"Larva";473;1
"Unit";"Zergling";"Larva";473;1
"Building";"Hatchery";NA;449;0
"Building";"CreepTumorQueen";NA;491;0
"Building";"CreepTumor";NA;491;0
"Building";"CreepTumor";NA;491;0
"Building";"CreepTumorQueen";NA;491;0
"Building";"CreepTumor";NA;491;0
"Building";"CreepTumor";NA;491;0
"Building";"CreepTumor";NA;491;0
"Building";"CreepTumorQueen";NA;491;0
"Building";"CreepTumorQueen";NA;491;0
"Building";"CreepTumorQueen";NA;501;0
"Building";"CreepTumorQueen";NA;525;0
"Unit";"Zergling";"Larva";493;1
"Unit";"Zergling";"Larva";493;1
"Unit";"Zergling";"Larva";501;1
"Unit";"Zergling";"Larva";501;1
"Unit";"Zergling";"Larva";505;1
"Unit";"Zergling";"Larva";505;1
"Unit";"Zergling";"Larva";507;1
"Unit";"Zergling";"Larva";507;1
"Unit";"Zergling";"Larva";507;1
"Unit";"Zergling";"Larva";507;1
"Unit";"Zergling";"Larva";511;1
"Unit";"Zergling";"Larva";511;1
"Unit";"Zergling";"Larva";511;1
"Unit";"Zergling";"Larva";511;1
"Unit";"Baneling";"Zergling";525;0
"Unit";"Baneling";"Zergling";525;0
"Unit";"Baneling";"Zergling";525;0
"Unit";"Baneling";"Zergling";525;0
"Unit";"Baneling";"Zergling";525;0
"Unit";"Baneling";"Zergling";525;0
"Unit";"Baneling";"Zergling";525;0
"Unit";"Baneling";"Zergling";525;0
"Unit";"Baneling";"Zergling";525;0
"Unit";"Baneling";"Zergling";525;0
"Unit";"Baneling";"Zergling";525;0
"Unit";"Baneling";"Zergling";525;0
"Unit";"Baneling";"Zergling";525;0
"Unit";"Baneling";"Zergling";525;0
"Unit";"Baneling";"Zergling";525;0
"Unit";"Baneling";"Zergling";525;0
"Unit";"Baneling";"Zergling";525;0
"Unit";"Baneling";"Zergling";525;0
"Unit";"Baneling";"Zergling";525;0
"Unit";"Baneling";"Zergling";525;0
"Unit";"Baneling";"Zergling";525;0
"Unit";"Zergling";"Larva";525;1
"Unit";"Zergling";"Larva";525;1
"Unit";"Zergling";"Larva";525;1
"Unit";"Zergling";"Larva";525;1
"Unit";"Overlord";"Larva";539;0
"Unit";"Zergling";"Larva";539;1
"Unit";"Zergling";"Larva";539;1
"Unit";"Zergling";"Larva";539;1
"Unit";"Zergling";"Larva";539;1
"Unit";"Zergling";"Larva";539;1
"Unit";"Zergling";"Larva";539;1
"Unit";"Zergling";"Larva";539;1
"Unit";"Zergling";"Larva";539;1
"Unit";"Zergling";"Larva";539;1
"Unit";"Zergling";"Larva";539;1
"Upgrade";"ZergMissileWeaponsLevel1";"EvolutionChamber";453;0
"Unit";"Zergling";"Larva";553;1
"Unit";"Zergling";"Larva";553;1
"Unit";"Zergling";"Larva";553;1
"Unit";"Zergling";"Larva";553;1
"Unit";"Hydralisk";"Larva";543;2
"Unit";"Zergling";"Larva";553;1
"Unit";"Zergling";"Larva";553;1
"Unit";"Hydralisk";"Larva";543;2
"Unit";"Zergling";"Larva";553;1
"Unit";"Zergling";"Larva";553;1
"Unit";"Hydralisk";"Larva";553;2
"Unit";"Hydralisk";"Larva";553;2
"Building";"CreepTumor";NA;565;0
"Building";"CreepTumor";NA;565;0
"Unit";"Zergling";"Larva";565;1
"Unit";"Zergling";"Larva";565;1
"Unit";"Zergling";"Larva";565;1
"Unit";"Zergling";"Larva";565;1
"Unit";"Zergling";"Larva";565;1
"Unit";"Zergling";"Larva";565;1
"Unit";"Zergling";"Larva";565;1
"Unit";"Zergling";"Larva";565;1
"Unit";"Zergling";"Larva";565;1
"Unit";"Zergling";"Larva";565;1
"Unit";"Zergling";"Larva";565;1
"Unit";"Zergling";"Larva";565;1
"Unit";"Zergling";"Larva";565;1
"Unit";"Zergling";"Larva";565;1
"Unit";"Zergling";"Larva";565;1
"Unit";"Zergling";"Larva";565;1
"Unit";"Zergling";"Larva";565;1
"Unit";"Zergling";"Larva";565;1
"Unit";"Zergling";"Larva";565;1
"Unit";"Zergling";"Larva";565;1
"Unit";"Zergling";"Larva";565;1
"Unit";"Zergling";"Larva";565;1
"Unit";"Zergling";"Larva";565;1
"Unit";"Zergling";"Larva";565;1
"Unit";"Zergling";"Larva";565;1
"Unit";"Zergling";"Larva";565;1
"Unit";"Zergling";"Larva";565;1
"Unit";"Zergling";"Larva";565;1
"Unit";"Zergling";"Larva";565;1
"Unit";"Zergling";"Larva";565;1
"Unit";"Zergling";"Larva";565;1
"Unit";"Zergling";"Larva";565;1
"Unit";"Zergling";"Larva";569;1
"Unit";"Zergling";"Larva";569;1
"Unit";"Zergling";"Larva";569;1
"Unit";"Zergling";"Larva";569;1
"Unit";"Zergling";"Larva";569;1
"Unit";"Zergling";"Larva";569;1
"Unit";"Zergling";"Larva";569;1
"Unit";"Zergling";"Larva";569;1
"Unit";"Zergling";"Larva";569;1
"Unit";"Zergling";"Larva";569;1
"Unit";"Zergling";"Larva";569;1
"Unit";"Zergling";"Larva";569;1
"Unit";"Zergling";"Larva";591;1
"Unit";"Zergling";"Larva";591;1
"Unit";"Zergling";"Larva";599;1
"Unit";"Zergling";"Larva";599;1
"Building";"InfestationPit";NA;569;0
"Unit";"Queen";"Hatchery";599;2
"Building";"CreepTumor";NA;630;0
"Unit";"Baneling";"Zergling";630;0
"Unit";"Zergling";"Larva";630;1
"Unit";"Zergling";"Larva";630;1
"Unit";"Baneling";"Zergling";630;0
"Unit";"Baneling";"Zergling";630;0
"Unit";"Baneling";"Zergling";630;0
"Unit";"Baneling";"Zergling";630;0
"Unit";"Zergling";"Larva";630;1
"Unit";"Zergling";"Larva";630;1
"Unit";"Baneling";"Zergling";632;0
"Unit";"Baneling";"Zergling";632;0
"Unit";"Zergling";"Larva";630;1
"Unit";"Zergling";"Larva";630;1
"Unit";"Zergling";"Larva";630;1
"Unit";"Zergling";"Larva";630;1
"Unit";"Zergling";"Larva";630;1
"Unit";"Zergling";"Larva";630;1
"Unit";"Zergling";"Larva";630;1
"Unit";"Zergling";"Larva";630;1
"Unit";"Zergling";"Larva";630;1
"Unit";"Zergling";"Larva";630;1
"Unit";"Zergling";"Larva";630;1
"Unit";"Zergling";"Larva";630;1
"Unit";"Zergling";"Larva";630;1
"Unit";"Zergling";"Larva";630;1
"Unit";"Zergling";"Larva";630;1
"Unit";"Zergling";"Larva";630;1
"Unit";"Zergling";"Larva";630;1
"Unit";"Zergling";"Larva";630;1
"Unit";"Zergling";"Larva";630;1
"Unit";"Zergling";"Larva";630;1
"Unit";"Zergling";"Larva";630;1
"Unit";"Zergling";"Larva";630;1
"Unit";"Zergling";"Larva";630;1
"Unit";"Zergling";"Larva";630;1
"Unit";"Zergling";"Larva";630;1
"Unit";"Zergling";"Larva";630;1
"Unit";"Zergling";"Larva";630;1
"Unit";"Zergling";"Larva";630;1
"Unit";"Zergling";"Larva";630;1
"Unit";"Zergling";"Larva";630;1
"Unit";"Zergling";"Larva";630;1
"Unit";"Zergling";"Larva";630;1
"Unit";"Hydralisk";"Larva";632;2
"Unit";"Hydralisk";"Larva";632;2
"Unit";"Hydralisk";"Larva";632;2
"Unit";"Zergling";"Larva";668;1
"Unit";"Zergling";"Larva";668;1
"Unit";"Zergling";"Larva";668;1
"Unit";"Zergling";"Larva";668;1
"Building";"CreepTumor";NA;678;0
"Unit";"Hydralisk";"Larva";674;2
"Unit";"Hydralisk";"Larva";674;2
"Unit";"Hydralisk";"Larva";674;2
"Unit";"Hydralisk";"Larva";674;2
"Unit";"Zergling";"Larva";678;1
"Unit";"Zergling";"Larva";678;1
"Unit";"Zergling";"Larva";678;1
"Unit";"Zergling";"Larva";678;1
"Unit";"Zergling";"Larva";678;1
"Unit";"Zergling";"Larva";678;1
"Unit";"Zergling";"Larva";678;1
"Unit";"Zergling";"Larva";678;1
"Unit";"Zergling";"Larva";678;1
"Unit";"Zergling";"Larva";678;1
"Unit";"Zergling";"Larva";678;1
"Unit";"Zergling";"Larva";678;1
"Unit";"Zergling";"Larva";678;1
"Unit";"Zergling";"Larva";678;1
"Unit";"Zergling";"Larva";678;1
"Unit";"Zergling";"Larva";678;1
"Unit";"Zergling";"Larva";678;1
"Unit";"Zergling";"Larva";678;1
"Unit";"Zergling";"Larva";678;1
"Unit";"Zergling";"Larva";678;1
"Building";"CreepTumor";NA;678;0
"Building";"CreepTumor";NA;678;0
"Building";"CreepTumor";NA;678;0
"Upgrade";"ZergMissileWeaponsLevel2";"EvolutionChamber";613;0
"Unit";"Hydralisk";"Larva";678;2
"Unit";"Hydralisk";"Larva";678;2
"Unit";"Hydralisk";"Larva";678;2
"Unit";"Zergling";"Larva";706;1
"Unit";"Zergling";"Larva";706;1
"Unit";"Zergling";"Larva";706;1
"Unit";"Zergling";"Larva";706;1
"Unit";"Zergling";"Larva";706;1
"Unit";"Zergling";"Larva";706;1
"Unit";"Zergling";"Larva";706;1
"Unit";"Zergling";"Larva";706;1
"Unit";"Zergling";"Larva";706;1
"Unit";"Zergling";"Larva";706;1
"Unit";"Overlord";"Larva";706;0
"Building";"CreepTumor";NA;712;0
"Building";"CreepTumor";NA;712;0
"Unit";"Zergling";"Larva";706;1
"Unit";"Zergling";"Larva";706;1
"Unit";"Zergling";"Larva";706;1
"Unit";"Zergling";"Larva";706;1
"Unit";"Zergling";"Larva";706;1
"Unit";"Zergling";"Larva";706;1
"Unit";"Zergling";"Larva";706;1
"Unit";"Zergling";"Larva";706;1
"Unit";"Zergling";"Larva";708;1
"Unit";"Zergling";"Larva";708;1
"Unit";"Zergling";"Larva";712;1
"Unit";"Zergling";"Larva";712;1
"Unit";"Baneling";"Zergling";722;0
"Unit";"Baneling";"Zergling";722;0
"Unit";"Baneling";"Zergling";722;0
"Unit";"Baneling";"Zergling";722;0
"Unit";"Baneling";"Zergling";722;0
"Unit";"Baneling";"Zergling";722;0
"Unit";"Baneling";"Zergling";722;0
"Unit";"Baneling";"Zergling";722;0
"Unit";"Baneling";"Zergling";722;0
"Unit";"Baneling";"Zergling";722;0
"Unit";"Hydralisk";"Larva";722;2
"Unit";"Hydralisk";"Larva";722;2
"Unit";"Hydralisk";"Larva";722;2
"Unit";"Hydralisk";"Larva";722;2
"Unit";"Hydralisk";"Larva";722;2
"Unit";"Hydralisk";"Larva";722;2
"Unit";"Hydralisk";"Larva";722;2
"Unit";"Hydralisk";"Larva";722;2
"Unit";"Hydralisk";"Larva";722;2
"Building";"Extractor";NA;734;0
"Building";"SporeCrawler";NA;734;0
"Building";"Extractor";NA;734;0
"Unit";"Zergling";"Larva";752;1
"Unit";"Zergling";"Larva";752;1
"Unit";"Zergling";"Larva";752;1
"Unit";"Zergling";"Larva";752;1
"Unit";"Zergling";"Larva";752;1
"Unit";"Zergling";"Larva";752;1
"Unit";"Zergling";"Larva";752;1
"Unit";"Zergling";"Larva";752;1
"Unit";"Zergling";"Larva";752;1
"Unit";"Zergling";"Larva";752;1
"Unit";"Zergling";"Larva";752;1
"Unit";"Zergling";"Larva";752;1
"Unit";"Zergling";"Larva";752;1
"Unit";"Zergling";"Larva";752;1
"Unit";"Zergling";"Larva";752;1
"Unit";"Zergling";"Larva";752;1
"Building";"SpineCrawler";NA;734;0
"Building";"Hatchery";NA;706;0
"Unit";"Hydralisk";"Larva";752;2
"Unit";"Hydralisk";"Larva";752;2
"Unit";"Hydralisk";"Larva";752;2
"Unit";"Zergling";"Larva";752;1
"Unit";"Zergling";"Larva";752;1
"Unit";"Zergling";"Larva";752;1
"Unit";"Zergling";"Larva";752;1
"Unit";"Zergling";"Larva";752;1
"Unit";"Zergling";"Larva";752;1
"Unit";"Zergling";"Larva";752;1
"Unit";"Zergling";"Larva";752;1
"Unit";"Zergling";"Larva";754;1
"Unit";"Zergling";"Larva";754;1
"Unit";"Hydralisk";"Larva";752;2
"Unit";"Hydralisk";"Larva";752;2
"Building";"CreepTumor";NA;768;0
"Unit";"Hydralisk";"Larva";752;2
"Unit";"Hydralisk";"Larva";752;2
"Unit";"Hydralisk";"Larva";768;2
"Unit";"Hydralisk";"Larva";768;2
"Unit";"Hydralisk";"Larva";768;2
"Unit";"Hydralisk";"Larva";768;2
"Unit";"Hydralisk";"Larva";768;2
"Unit";"Hydralisk";"Larva";768;2
"Unit";"Baneling";"Zergling";784;0
"Unit";"Baneling";"Zergling";784;0
"Unit";"Baneling";"Zergling";784;0
"Unit";"Zergling";"Larva";780;1
"Unit";"Zergling";"Larva";780;1
"Unit";"Baneling";"Zergling";784;0
"Unit";"Baneling";"Zergling";784;0
"Unit";"Zergling";"Larva";784;1
"Unit";"Zergling";"Larva";784;1
"Unit";"Zergling";"Larva";809;1
"Unit";"Zergling";"Larva";809;1
"Unit";"Zergling";"Larva";809;1
"Unit";"Zergling";"Larva";809;1
"Unit";"Zergling";"Larva";809;1
"Unit";"Zergling";"Larva";809;1
"Unit";"Hydralisk";"Larva";809;2
"Unit";"Hydralisk";"Larva";809;2
"Unit";"Zergling";"Larva";809;1
"Unit";"Zergling";"Larva";809;1
