"type";"unit_name";"on_building";"total_supply";"supply"
"Unit";"Overlord";"Larva";12;0
"Building";"Hatchery";NA;17;0
"Building";"SpawningPool";NA;18;0
"Building";"Extractor";NA;23;0
"Unit";"Overlord";"Larva";26;0
"Unit";"Queen";"Hatchery";23;2
"Unit";"Queen";"Hatchery";23;2
"Unit";"Overlord";"Larva";26;0
"Building";"Hatchery";NA;22;0
"Building";"RoachWarren";NA;26;0
"Unit";"Overlord";"Larva";37;0
"Unit";"Overlord";"Larva";39;0
"Unit";"Queen";"Hatchery";37;2
"Unit";"Roach";"Larva";42;2
"Unit";"Roach";"Larva";42;2
"Unit";"Roach";"Larva";42;2
"Unit";"Overlord";"Larva";42;0
"Unit";"Zergling";"Larva";42;1
"Unit";"Zergling";"Larva";42;1
"Unit";"Zergling";"Larva";42;1
"Unit";"Zergling";"Larva";42;1
"Unit";"Zergling";"Larva";42;1
"Unit";"Zergling";"Larva";42;1
"Unit";"Zergling";"Larva";44;1
"Unit";"Zergling";"Larva";44;1
"Unit";"Zergling";"Larva";44;1
"Unit";"Zergling";"Larva";44;1
"Unit";"Zergling";"Larva";44;1
"Unit";"Zergling";"Larva";44;1
"Unit";"Zergling";"Larva";44;1
"Unit";"Zergling";"Larva";44;1
"Unit";"Zergling";"Larva";44;1
"Unit";"Zergling";"Larva";44;1
"Unit";"Zergling";"Larva";44;1
"Unit";"Zergling";"Larva";44;1
"Unit";"Zergling";"Larva";44;1
"Unit";"Zergling";"Larva";44;1
"Unit";"Zergling";"Larva";54;1
"Unit";"Zergling";"Larva";54;1
"Unit";"Zergling";"Larva";54;1
"Unit";"Zergling";"Larva";54;1
"Unit";"Zergling";"Larva";56;1
"Unit";"Zergling";"Larva";56;1
"Unit";"Zergling";"Larva";64;1
"Unit";"Zergling";"Larva";64;1
"Unit";"Zergling";"Larva";64;1
"Unit";"Zergling";"Larva";64;1
"Unit";"Zergling";"Larva";64;1
"Unit";"Zergling";"Larva";64;1
"Unit";"Zergling";"Larva";64;1
"Unit";"Zergling";"Larva";64;1
"Unit";"Zergling";"Larva";70;1
"Unit";"Zergling";"Larva";70;1
"Unit";"Zergling";"Larva";70;1
"Unit";"Zergling";"Larva";70;1
"Unit";"Zergling";"Larva";76;1
"Unit";"Zergling";"Larva";76;1
"Unit";"Zergling";"Larva";76;1
"Unit";"Zergling";"Larva";76;1
"Unit";"Zergling";"Larva";76;1
"Unit";"Zergling";"Larva";76;1
"Unit";"Zergling";"Larva";84;1
"Unit";"Zergling";"Larva";84;1
"Unit";"Zergling";"Larva";88;1
"Unit";"Zergling";"Larva";88;1
"Unit";"Zergling";"Larva";88;1
"Unit";"Zergling";"Larva";88;1
"Unit";"Zergling";"Larva";92;1
"Unit";"Zergling";"Larva";92;1
"Unit";"Zergling";"Larva";92;1
"Unit";"Zergling";"Larva";92;1
"Unit";"Overlord";"Larva";94;0
"Unit";"Zergling";"Larva";94;1
"Unit";"Zergling";"Larva";94;1
"Unit";"Zergling";"Larva";94;1
"Unit";"Zergling";"Larva";94;1
"Unit";"Overlord";"Larva";96;0
"Unit";"Overlord";"Larva";111;0
"Unit";"Overlord";"Larva";111;0
"Building";"Extractor";NA;118;0
"Building";"Extractor";NA;118;0
"Building";"SporeCrawler";NA;118;0
"Building";"SporeCrawler";NA;118;0
"Building";"CreepTumorQueen";NA;132;0
"Building";"CreepTumorQueen";NA;147;0
"Building";"HydraliskDen";NA;146;0
"Building";"CreepTumor";NA;148;0
"Building";"EvolutionChamber";NA;146;0
"Unit";"Overlord";"Larva";146;0
"Unit";"Overlord";"Larva";146;0
"Unit";"Overlord";"Larva";146;0
"Unit";"Overlord";"Larva";146;0
"Building";"Extractor";NA;148;0
"Building";"Extractor";NA;148;0
"Building";"BanelingNest";NA;146;0
"Unit";"Overlord";"Larva";153;0
"Unit";"Overlord";"Larva";153;0
"Building";"CreepTumor";NA;159;0
"Building";"SporeCrawler";NA;153;0
"Building";"SpineCrawler";NA;148;0
"Unit";"Hydralisk";"Larva";159;2
"Unit";"Hydralisk";"Larva";159;2
"Unit";"Hydralisk";"Larva";159;2
"Unit";"Hydralisk";"Larva";159;2
"Building";"Hatchery";NA;146;0
"Unit";"Hydralisk";"Larva";159;2
"Unit";"Zergling";"Larva";159;1
"Unit";"Zergling";"Larva";159;1
"Unit";"Zergling";"Larva";159;1
"Unit";"Zergling";"Larva";159;1
"Unit";"Hydralisk";"Larva";159;2
"Unit";"Hydralisk";"Larva";159;2
"Unit";"Hydralisk";"Larva";159;2
"Unit";"Hydralisk";"Larva";159;2
"Unit";"Hydralisk";"Larva";165;2
"Building";"Extractor";NA;167;0
"Building";"Extractor";NA;167;0
"Unit";"Queen";"Hatchery";167;2
"Upgrade";"EvolveMuscularAugments";"HydraliskDen";159;0
"Building";"Extractor";NA;181;0
"Building";"SporeCrawler";NA;183;0
"Unit";"Hydralisk";"Larva";183;2
"Unit";"Hydralisk";"Larva";183;2
"Unit";"Hydralisk";"Larva";183;2
"Unit";"Hydralisk";"Larva";183;2
"Unit";"Hydralisk";"Larva";183;2
"Unit";"Hydralisk";"Larva";192;2
"Unit";"Baneling";"Zergling";192;0
"Unit";"Baneling";"Zergling";192;0
"Unit";"Baneling";"Zergling";192;0
"Unit";"Baneling";"Zergling";192;0
"Unit";"Baneling";"Zergling";192;0
"Unit";"Baneling";"Zergling";192;0
"Unit";"Baneling";"Zergling";192;0
"Unit";"Baneling";"Zergling";192;0
"Building";"CreepTumor";NA;194;0
"Unit";"Zergling";"Larva";192;1
"Unit";"Zergling";"Larva";192;1
"Unit";"Zergling";"Larva";192;1
"Unit";"Zergling";"Larva";192;1
"Unit";"Zergling";"Larva";194;1
"Unit";"Zergling";"Larva";194;1
"Building";"CreepTumor";NA;209;0
"Unit";"Hydralisk";"Larva";194;2
"Unit";"Hydralisk";"Larva";205;2
"Unit";"Hydralisk";"Larva";205;2
"Unit";"Hydralisk";"Larva";209;2
"Unit";"Hydralisk";"Larva";211;2
"Unit";"Baneling";"Zergling";217;0
"Unit";"Baneling";"Zergling";217;0
"Unit";"Baneling";"Zergling";217;0
"Unit";"Baneling";"Zergling";217;0
"Unit";"Hydralisk";"Larva";217;2
"Unit";"Hydralisk";"Larva";217;2
"Upgrade";"ZergMissileWeaponsLevel1";"EvolutionChamber";167;0
"Unit";"Hydralisk";"Larva";217;2
"Unit";"Zergling";"Larva";217;1
"Unit";"Zergling";"Larva";217;1
"Unit";"Zergling";"Larva";219;1
"Unit";"Zergling";"Larva";219;1
"Unit";"Zergling";"Larva";219;1
"Unit";"Zergling";"Larva";219;1
"Unit";"Zergling";"Larva";219;1
"Unit";"Zergling";"Larva";219;1
"Unit";"Zergling";"Larva";219;1
"Unit";"Zergling";"Larva";219;1
"Unit";"Zergling";"Larva";219;1
"Unit";"Zergling";"Larva";219;1
"Unit";"Zergling";"Larva";219;1
"Unit";"Zergling";"Larva";219;1
"Unit";"Overlord";"Larva";219;0
"Unit";"Overlord";"Larva";227;0
"Unit";"Overlord";"Larva";227;0
"Unit";"Overlord";"Larva";247;0
"Unit";"Overlord";"Larva";247;0
"Upgrade";"EvolveGroovedSpines";"HydraliskDen";217;0
"Unit";"Hydralisk";"Larva";247;2
"Unit";"Hydralisk";"Larva";247;2
"Unit";"Hydralisk";"Larva";247;2
"Unit";"Hydralisk";"Larva";247;2
"Unit";"Hydralisk";"Larva";247;2
"Unit";"Hydralisk";"Larva";247;2
"Building";"InfestationPit";NA;247;0
"Unit";"Hydralisk";"Larva";247;2
"Unit";"Hydralisk";"Larva";247;2
"Unit";"Hydralisk";"Larva";247;2
"Unit";"Hydralisk";"Larva";247;2
"Unit";"Hydralisk";"Larva";247;2
"Unit";"Zergling";"Larva";247;1
"Unit";"Zergling";"Larva";247;1
"Unit";"Baneling";"Zergling";247;0
"Unit";"Baneling";"Zergling";247;0
"Unit";"Baneling";"Zergling";247;0
"Unit";"Baneling";"Zergling";247;0
"Building";"CreepTumor";NA;259;0
"Unit";"Hydralisk";"Larva";247;2
"Unit";"Hydralisk";"Larva";247;2
"Unit";"Hydralisk";"Larva";247;2
"Building";"Extractor";NA;259;0
"Unit";"Zergling";"Larva";282;1
"Unit";"Zergling";"Larva";282;1
"Unit";"Zergling";"Larva";282;1
"Unit";"Zergling";"Larva";282;1
"Unit";"Zergling";"Larva";282;1
"Unit";"Zergling";"Larva";282;1
"Unit";"Zergling";"Larva";282;1
"Unit";"Zergling";"Larva";282;1
"Unit";"Zergling";"Larva";282;1
"Unit";"Zergling";"Larva";282;1
"Unit";"Zergling";"Larva";282;1
"Unit";"Zergling";"Larva";282;1
"Unit";"Zergling";"Larva";282;1
"Unit";"Zergling";"Larva";282;1
"Unit";"Zergling";"Larva";282;1
"Unit";"Zergling";"Larva";282;1
"Unit";"Zergling";"Larva";282;1
"Unit";"Zergling";"Larva";282;1
"Unit";"Zergling";"Larva";282;1
"Unit";"Zergling";"Larva";282;1
"Unit";"Zergling";"Larva";282;1
"Unit";"Zergling";"Larva";282;1
"Unit";"Zergling";"Larva";282;1
"Unit";"Zergling";"Larva";282;1
"Unit";"Zergling";"Larva";282;1
"Unit";"Zergling";"Larva";282;1
"Unit";"Zergling";"Larva";282;1
"Unit";"Zergling";"Larva";282;1
"Unit";"Zergling";"Larva";282;1
"Unit";"Zergling";"Larva";282;1
"Unit";"Zergling";"Larva";282;1
"Unit";"Zergling";"Larva";282;1
"Unit";"Zergling";"Larva";282;1
"Unit";"Zergling";"Larva";282;1
"Unit";"Zergling";"Larva";282;1
"Unit";"Zergling";"Larva";282;1
"Unit";"Zergling";"Larva";282;1
"Unit";"Zergling";"Larva";282;1
"Unit";"Zergling";"Larva";282;1
"Unit";"Zergling";"Larva";282;1
