"type";"unit_name";"on_building";"total_supply";"supply"
"Unit";"Overlord";"Larva";12;0
"Building";"Extractor";NA;21;0
"Building";"SpawningPool";NA;19;0
"Building";"Hatchery";NA;17;0
"Unit";"Zergling";"Larva";23;1
"Unit";"Zergling";"Larva";23;1
"Unit";"Overlord";"Larva";23;0
"Unit";"Queen";"Hatchery";23;2
"Unit";"Queen";"Hatchery";23;2
"Building";"Hatchery";NA;21;0
"Unit";"Overlord";"Larva";33;0
"Unit";"Overlord";"Larva";34;0
"Unit";"Overlord";"Larva";47;0
"Building";"Extractor";NA;51;0
"Building";"SporeCrawler";NA;52;0
"Building";"SporeCrawler";NA;52;0
"Building";"RoachWarren";NA;50;0
"Unit";"Overlord";"Larva";60;0
"Unit";"Overlord";"Larva";60;0
"Unit";"Overlord";"Larva";60;0
"Unit";"Overlord";"Larva";60;0
"Building";"Extractor";NA;60;0
"Unit";"Queen";"Hatchery";56;2
"Unit";"Roach";"Larva";60;2
"Unit";"Roach";"Larva";60;2
"Unit";"Roach";"Larva";60;2
"Unit";"Roach";"Larva";60;2
"Unit";"Roach";"Larva";60;2
"Unit";"Roach";"Larva";60;2
"Unit";"Overlord";"Larva";60;0
"Unit";"Overlord";"Larva";60;0
"Building";"Extractor";NA;68;0
"Building";"Extractor";NA;70;0
"Building";"Extractor";NA;74;0
"Building";"EvolutionChamber";NA;78;0
"Building";"HydraliskDen";NA;74;0
"Unit";"Queen";"Hatchery";85;2
"Building";"CreepTumorQueen";NA;101;0
"Unit";"Overlord";"Larva";102;0
"Unit";"Overlord";"Larva";102;0
"Unit";"Overlord";"Larva";102;0
"Building";"CreepTumor";NA;102;0
"Unit";"Roach";"Larva";102;2
"Unit";"Roach";"Larva";102;2
"Unit";"Roach";"Larva";102;2
"Unit";"Roach";"Larva";102;2
"Upgrade";"GlialReconstitution";"RoachWarren";92;0
"Building";"CreepTumorQueen";NA;110;0
"Unit";"Overlord";"Larva";110;0
"Upgrade";"EvolveGroovedSpines";"HydraliskDen";102;0
"Building";"CreepTumor";NA;116;0
"Unit";"Hydralisk";"Larva";110;2
"Unit";"Hydralisk";"Larva";110;2
"Unit";"Hydralisk";"Larva";110;2
"Unit";"Roach";"Larva";113;2
"Unit";"Roach";"Larva";113;2
"Unit";"Roach";"Larva";113;2
"Building";"CreepTumorQueen";NA;116;0
"Unit";"Roach";"Larva";116;2
"Unit";"Roach";"Larva";116;2
"Unit";"Roach";"Larva";116;2
"Unit";"Overlord";"Larva";116;0
"Unit";"Overlord";"Larva";116;0
"Building";"CreepTumor";NA;128;0
"Building";"Hatchery";NA;102;0
"Unit";"Overlord";"Larva";122;0
"Building";"CreepTumor";NA;134;0
"Building";"SporeCrawler";NA;116;0
"Unit";"Hydralisk";"Larva";128;2
"Unit";"Hydralisk";"Larva";128;2
"Unit";"Overlord";"Larva";134;0
"Building";"LurkerDenMP";NA;102;0
"Upgrade";"ZergMissileWeaponsLevel1";"EvolutionChamber";102;0
"Unit";"Roach";"Larva";137;2
"Unit";"Roach";"Larva";141;2
"Unit";"Roach";"Larva";141;2
"Unit";"Roach";"Larva";141;2
"Unit";"Roach";"Larva";141;2
"Unit";"Roach";"Larva";141;2
"Unit";"Roach";"Larva";141;2
"Unit";"Roach";"Larva";141;2
"Unit";"Roach";"Larva";141;2
"Unit";"Roach";"Larva";141;2
"Unit";"Queen";"Hatchery";137;2
"Unit";"Roach";"Larva";143;2
"Unit";"Roach";"Larva";143;2
"Upgrade";"EvolveMuscularAugments";"HydraliskDen";134;0
"Unit";"Overlord";"Larva";163;0
"Unit";"Overlord";"Larva";163;0
"Unit";"Overlord";"Larva";163;0
"Unit";"Overlord";"Larva";163;0
"Unit";"Overlord";"Larva";163;0
"Unit";"Overlord";"Larva";163;0
"Unit";"Overlord";"Larva";163;0
"Unit";"Overlord";"Larva";167;0
"Unit";"Overlord";"Larva";167;0
"Unit";"Overlord";"Larva";167;0
"Unit";"Overlord";"Larva";167;0
"Unit";"Roach";"Larva";167;2
"Unit";"Roach";"Larva";167;2
"Unit";"Roach";"Larva";167;2
"Unit";"Roach";"Larva";167;2
"Unit";"Roach";"Larva";167;2
"Unit";"Roach";"Larva";167;2
"Unit";"Roach";"Larva";167;2
"Unit";"Roach";"Larva";167;2
"Unit";"Roach";"Larva";167;2
"Unit";"Roach";"Larva";167;2
"Unit";"Roach";"Larva";167;2
"Building";"CreepTumorQueen";NA;177;0
"Building";"CreepTumorQueen";NA;177;0
"Unit";"Roach";"Larva";177;2
"Unit";"Roach";"Larva";177;2
"Unit";"Roach";"Larva";177;2
"Building";"CreepTumorQueen";NA;189;0
"Unit";"Hydralisk";"Larva";189;2
"Unit";"Hydralisk";"Larva";189;2
"Unit";"Hydralisk";"Larva";189;2
"Building";"Hatchery";NA;167;0
"Unit";"Hydralisk";"Larva";195;2
"Unit";"Hydralisk";"Larva";195;2
"Unit";"Hydralisk";"Larva";195;2
"Unit";"Hydralisk";"Larva";195;2
"Unit";"Hydralisk";"Larva";195;2
"Unit";"Hydralisk";"Larva";195;2
"Unit";"Hydralisk";"Larva";195;2
"Unit";"Hydralisk";"Larva";195;2
"Unit";"Hydralisk";"Larva";195;2
"Unit";"Hydralisk";"Larva";195;2
"Unit";"Hydralisk";"Larva";195;2
"Unit";"Hydralisk";"Larva";195;2
"Unit";"Roach";"Larva";201;2
"Unit";"Roach";"Larva";201;2
"Unit";"Roach";"Larva";201;2
"Unit";"Roach";"Larva";201;2
"Unit";"Roach";"Larva";201;2
"Unit";"Roach";"Larva";201;2
"Unit";"Roach";"Larva";201;2
"Unit";"Roach";"Larva";225;2
"Unit";"Roach";"Larva";225;2
"Unit";"Roach";"Larva";225;2
"Unit";"Roach";"Larva";225;2
"Unit";"Roach";"Larva";225;2
"Unit";"Roach";"Larva";225;2
"Unit";"Roach";"Larva";225;2
"Unit";"Roach";"Larva";225;2
"Unit";"Roach";"Larva";225;2
"Unit";"Roach";"Larva";225;2
"Unit";"Roach";"Larva";225;2
"Unit";"Roach";"Larva";225;2
"Building";"CreepTumorQueen";NA;239;0
"Unit";"Roach";"Larva";233;2
"Unit";"Roach";"Larva";237;2
"Building";"CreepTumorQueen";NA;263;0
"Unit";"Roach";"Larva";239;2
"Unit";"Roach";"Larva";239;2
"Building";"SporeCrawler";NA;271;0
"Building";"CreepTumor";NA;283;0
"Building";"CreepTumor";NA;283;0
"Building";"CreepTumor";NA;283;0
"Building";"CreepTumor";NA;283;0
"Upgrade";"ZergMissileWeaponsLevel2";"EvolutionChamber";201;0
"Building";"CreepTumorQueen";NA;283;0
"Unit";"Queen";"Hatchery";271;2
"Building";"Hatchery";NA;267;0
"Building";"CreepTumor";NA;288;0
"Unit";"Hydralisk";"Larva";288;2
"Unit";"Hydralisk";"Larva";288;2
"Unit";"Hydralisk";"Larva";288;2
"Unit";"Roach";"Larva";290;2
"Unit";"Roach";"Larva";290;2
"Unit";"Roach";"Larva";290;2
"Unit";"Roach";"Larva";290;2
"Unit";"Roach";"Larva";290;2
"Unit";"Roach";"Larva";290;2
"Unit";"Roach";"Larva";290;2
"Unit";"Roach";"Larva";290;2
"Unit";"Roach";"Larva";290;2
"Unit";"Roach";"Larva";290;2
"Building";"Extractor";NA;296;0
"Building";"Extractor";NA;296;0
"Unit";"Hydralisk";"Larva";326;2
"Unit";"Hydralisk";"Larva";326;2
"Unit";"Hydralisk";"Larva";326;2
"Unit";"Hydralisk";"Larva";326;2
"Unit";"Hydralisk";"Larva";326;2
"Unit";"Hydralisk";"Larva";326;2
"Unit";"Hydralisk";"Larva";326;2
"Unit";"Hydralisk";"Larva";328;2
"Unit";"Hydralisk";"Larva";330;2
"Unit";"Hydralisk";"Larva";330;2
"Unit";"Hydralisk";"Larva";340;2
"Unit";"Hydralisk";"Larva";340;2
"Unit";"Hydralisk";"Larva";340;2
"Unit";"Hydralisk";"Larva";353;2
"Unit";"Hydralisk";"Larva";353;2
"Unit";"Hydralisk";"Larva";353;2
"Unit";"Hydralisk";"Larva";353;2
"Unit";"Hydralisk";"Larva";353;2
"Unit";"Zergling";"Larva";359;1
"Unit";"Zergling";"Larva";359;1
"Unit";"Zergling";"Larva";359;1
"Unit";"Zergling";"Larva";359;1
"Unit";"Zergling";"Larva";359;1
"Unit";"Zergling";"Larva";359;1
"Unit";"Zergling";"Larva";359;1
"Unit";"Zergling";"Larva";359;1
"Unit";"Zergling";"Larva";359;1
"Unit";"Zergling";"Larva";359;1
"Unit";"Zergling";"Larva";359;1
"Unit";"Zergling";"Larva";359;1
"Unit";"Zergling";"Larva";359;1
"Unit";"Zergling";"Larva";359;1
"Building";"CreepTumor";NA;383;0
"Unit";"Hydralisk";"Larva";369;2
"Unit";"Hydralisk";"Larva";369;2
"Unit";"Hydralisk";"Larva";369;2
"Unit";"Hydralisk";"Larva";369;2
"Building";"Hatchery";NA;340;0
"Unit";"Hydralisk";"Larva";383;2
"Unit";"Hydralisk";"Larva";383;2
"Unit";"Hydralisk";"Larva";383;2
"Unit";"Hydralisk";"Larva";383;2
"Unit";"Hydralisk";"Larva";383;2
"Unit";"Zergling";"Larva";383;1
"Unit";"Zergling";"Larva";383;1
"Unit";"Zergling";"Larva";383;1
"Unit";"Zergling";"Larva";383;1
"Unit";"Zergling";"Larva";383;1
"Unit";"Zergling";"Larva";383;1
"Unit";"Zergling";"Larva";383;1
"Unit";"Zergling";"Larva";383;1
"Unit";"Zergling";"Larva";383;1
"Unit";"Zergling";"Larva";383;1
"Unit";"Queen";"Hatchery";383;2
"Unit";"Hydralisk";"Larva";401;2
"Unit";"Hydralisk";"Larva";401;2
"Unit";"Hydralisk";"Larva";401;2
"Unit";"Hydralisk";"Larva";401;2
"Unit";"Hydralisk";"Larva";401;2
"Building";"SporeCrawler";NA;423;0
"Building";"Extractor";NA;423;0
"Building";"Extractor";NA;423;0
"Building";"SpineCrawler";NA;423;0
"Building";"CreepTumor";NA;423;0
"Building";"CreepTumor";NA;423;0
"Building";"CreepTumorQueen";NA;423;0
"Building";"CreepTumor";NA;423;0
"Building";"CreepTumorQueen";NA;423;0
"Building";"CreepTumorQueen";NA;423;0
"Building";"SpineCrawler";NA;423;0
"Building";"SpineCrawler";NA;423;0
"Building";"SpineCrawler";NA;423;0
"Building";"SpineCrawler";NA;423;0
"Building";"SpineCrawler";NA;423;0
"Building";"SpineCrawler";NA;423;0
"Building";"SpineCrawler";NA;423;0
"Building";"SpineCrawler";NA;423;0
"Building";"SpineCrawler";NA;423;0
"Building";"SpineCrawler";NA;423;0
"Building";"SpineCrawler";NA;423;0
"Upgrade";"ZergGroundArmorsLevel1";"EvolutionChamber";423;0
"Building";"SpineCrawler";NA;423;0
