"type";"unit_name";"on_building";"total_supply_lag";"supply"
"Building";"Extractor";NA;13;0
"Building";"SpawningPool";NA;13;0
"Unit";"Overlord";"Larva";16;0
"Unit";"Zergling";"Larva";16;1
"Unit";"Zergling";"Larva";17;1
"Unit";"Zergling";"Larva";18;1
"Unit";"Zergling";"Larva";19;1
"Unit";"Zergling";"Larva";20;1
"Unit";"Zergling";"Larva";21;1
"Unit";"Zergling";"Larva";22;1
"Unit";"Zergling";"Larva";23;1
"Unit";"Queen";"Hatchery";24;2
"Unit";"Zergling";"Larva";26;1
"Unit";"Zergling";"Larva";27;1
"Unit";"Zergling";"Larva";28;1
"Unit";"Zergling";"Larva";29;1
"Building";"Hatchery";NA;30;0
"Building";"EvolutionChamber";NA;30;0
"Unit";"Overlord";"Larva";30;0
"Unit";"Zergling";"Larva";30;1
"Unit";"Zergling";"Larva";31;1
"Unit";"Zergling";"Larva";32;1
"Unit";"Zergling";"Larva";33;1
"Unit";"Zergling";"Larva";34;1
"Unit";"Zergling";"Larva";35;1
"Unit";"Zergling";"Larva";36;1
"Unit";"Zergling";"Larva";37;1
"Unit";"Zergling";"Larva";38;1
"Unit";"Zergling";"Larva";39;1
"Unit";"Zergling";"Larva";40;1
"Unit";"Zergling";"Larva";41;1
"Unit";"Zergling";"Larva";42;1
"Unit";"Zergling";"Larva";43;1
"Unit";"Zergling";"Larva";44;1
"Unit";"Zergling";"Larva";45;1
"Unit";"Zergling";"Larva";46;1
"Unit";"Zergling";"Larva";47;1
"Unit";"Zergling";"Larva";48;1
"Unit";"Zergling";"Larva";49;1
"Unit";"Zergling";"Larva";50;1
"Unit";"Zergling";"Larva";51;1
"Unit";"Zergling";"Larva";52;1
"Unit";"Zergling";"Larva";53;1
"Unit";"Zergling";"Larva";54;1
"Unit";"Zergling";"Larva";55;1
"Unit";"Zergling";"Larva";56;1
"Unit";"Zergling";"Larva";57;1
"Unit";"Zergling";"Larva";58;1
"Unit";"Zergling";"Larva";59;1
"Unit";"Zergling";"Larva";60;1
"Unit";"Zergling";"Larva";61;1
"Unit";"Queen";"Hatchery";73;2
"Unit";"Overlord";"Larva";77;0
"Building";"Hatchery";NA;81;0
"Unit";"Overlord";"Larva";83;0
"Unit";"Overlord";"Larva";88;0
"Building";"CreepTumorQueen";NA;90;0
"Unit";"Zergling";"Larva";90;1
"Unit";"Zergling";"Larva";91;1
"Unit";"Zergling";"Larva";92;1
"Unit";"Zergling";"Larva";93;1
"Unit";"Zergling";"Larva";94;1
"Unit";"Zergling";"Larva";95;1
"Unit";"Zergling";"Larva";96;1
"Unit";"Zergling";"Larva";97;1
"Unit";"Zergling";"Larva";98;1
"Unit";"Zergling";"Larva";99;1
"Unit";"Zergling";"Larva";100;1
"Unit";"Zergling";"Larva";101;1
"Building";"Extractor";NA;102;0
"Unit";"Zergling";"Larva";102;1
"Unit";"Zergling";"Larva";103;1
"Unit";"Queen";"Hatchery";106;2
"Building";"CreepTumor";NA;108;0
"Unit";"Zergling";"Larva";108;1
"Unit";"Zergling";"Larva";109;1
"Unit";"Zergling";"Larva";110;1
"Unit";"Zergling";"Larva";111;1
"Unit";"Overlord";"Larva";116;0
"Building";"CreepTumor";NA;120;0
"Unit";"Overlord";"Larva";120;0
"Unit";"Queen";"Hatchery";120;2
"Unit";"Overlord";"Larva";130;0
"Building";"Extractor";NA;130;0
"Building";"Extractor";NA;132;0
"Building";"CreepTumor";NA;132;0
"Building";"SporeCrawler";NA;132;0
"Building";"SporeCrawler";NA;139;0
"Building";"HydraliskDen";NA;139;0
"Building";"BanelingNest";NA;145;0
"Unit";"Overlord";"Larva";148;0
"Building";"Extractor";NA;150;0
"Building";"Extractor";NA;150;0
"Building";"Hatchery";NA;150;0
"Building";"CreepTumorQueen";NA;151;0
"Unit";"Overlord";"Larva";157;0
"Unit";"Overlord";"Larva";157;0
"Unit";"Baneling";"Zergling";157;0
"Unit";"Baneling";"Zergling";157;0
"Unit";"Baneling";"Zergling";157;0
"Unit";"Baneling";"Zergling";157;0
"Unit";"Baneling";"Zergling";157;0
"Unit";"Baneling";"Zergling";157;0
"Unit";"Baneling";"Zergling";157;0
"Building";"CreepTumorQueen";NA;157;0
"Building";"CreepTumor";NA;157;0
"Unit";"Hydralisk";"Larva";158;2
"Unit";"Hydralisk";"Larva";160;2
"Unit";"Hydralisk";"Larva";162;2
"Unit";"Hydralisk";"Larva";164;2
"Unit";"Hydralisk";"Larva";166;2
"Unit";"Overlord";"Larva";168;0
"Unit";"Overlord";"Larva";168;0
"Unit";"Overlord";"Larva";168;0
"Unit";"Overlord";"Larva";168;0
"Unit";"Overlord";"Larva";168;0
"Building";"CreepTumor";NA;168;0
"Building";"CreepTumor";NA;168;0
"Building";"CreepTumorQueen";NA;168;0
"Unit";"Overlord";"Larva";168;0
"Unit";"Overlord";"Larva";168;0
"Unit";"Overlord";"Larva";168;0
"Unit";"Hydralisk";"Larva";168;2
"Unit";"Hydralisk";"Larva";170;2
"Unit";"Hydralisk";"Larva";172;2
"Unit";"Hydralisk";"Larva";174;2
"Unit";"Hydralisk";"Larva";176;2
"Unit";"Hydralisk";"Larva";178;2
"Unit";"Baneling";"Zergling";180;0
"Unit";"Baneling";"Zergling";180;0
"Unit";"Baneling";"Zergling";180;0
"Unit";"Baneling";"Zergling";180;0
"Unit";"Hydralisk";"Larva";180;2
"Unit";"Hydralisk";"Larva";182;2
"Unit";"Hydralisk";"Larva";184;2
"Unit";"Zergling";"Larva";186;1
"Unit";"Zergling";"Larva";187;1
"Unit";"Zergling";"Larva";188;1
"Unit";"Zergling";"Larva";189;1
"Unit";"Zergling";"Larva";190;1
"Unit";"Zergling";"Larva";191;1
"Building";"CreepTumor";NA;192;0
"Building";"CreepTumorQueen";NA;192;0
"Upgrade";"SprayZerg";NA;192;0
"Upgrade";"zerglingmovementspeed";NA;192;0
"Upgrade";"SprayZerg";NA;192;0
"Upgrade";"SprayZerg";NA;192;0
"Upgrade";"SprayZerg";NA;192;0
"Upgrade";"ZergMeleeWeaponsLevel1";NA;192;0
"Upgrade";"SprayZerg";NA;192;0
"Upgrade";"SprayZerg";NA;192;0
"Upgrade";"overlordspeed";NA;192;0
"Upgrade";"EvolveMuscularAugments";NA;192;0
"Upgrade";"CentrificalHooks";NA;192;0
