"type";"unit_name";"on_building";"total_supply";"supply"
"Unit";"Overlord";"Larva";12;0
"Building";"Extractor";NA;18;0
"Unit";"Overlord";"Larva";22;0
"Building";"Hatchery";NA;17;0
"Building";"SpawningPool";NA;19;0
"Unit";"Zergling";"Larva";23;1
"Unit";"Zergling";"Larva";23;1
"Unit";"Queen";"Hatchery";23;2
"Unit";"Queen";"Hatchery";23;2
"Unit";"Zergling";"Larva";29;1
"Unit";"Zergling";"Larva";29;1
"Unit";"Zergling";"Larva";29;1
"Unit";"Zergling";"Larva";29;1
"Building";"CreepTumorQueen";NA;34;0
"Unit";"Overlord";"Larva";38;0
"Building";"CreepTumor";NA;41;0
"Unit";"Queen";"Hatchery";38;2
"Building";"Hatchery";NA;30;0
"Unit";"Overlord";"Larva";51;0
"Building";"CreepTumorQueen";NA;52;0
"Building";"CreepTumor";NA;53;0
"Building";"Extractor";NA;52;0
"Building";"Extractor";NA;52;0
"Building";"EvolutionChamber";NA;52;0
"Building";"RoachWarren";NA;52;0
"Unit";"Overlord";"Larva";57;0
"Building";"CreepTumor";NA;57;0
"Building";"CreepTumor";NA;59;0
"Building";"CreepTumorQueen";NA;63;0
"Unit";"Roach";"Larva";63;2
"Building";"SporeCrawler";NA;67;0
"Building";"SporeCrawler";NA;69;0
"Building";"CreepTumor";NA;73;0
"Building";"SporeCrawler";NA;73;0
"Unit";"Queen";"Hatchery";68;2
"Building";"CreepTumor";NA;76;0
"Unit";"Overlord";"Larva";76;0
"Unit";"Overlord";"Larva";77;0
"Unit";"Overlord";"Larva";82;0
"Unit";"Overlord";"Larva";82;0
"Building";"CreepTumor";NA;82;0
"Unit";"Overlord";"Larva";82;0
"Unit";"Overlord";"Larva";82;0
"Building";"CreepTumor";NA;82;0
"Unit";"Roach";"Larva";82;2
"Unit";"Overlord";"Larva";82;0
"Unit";"Roach";"Larva";82;2
"Unit";"Roach";"Larva";82;2
"Unit";"Roach";"Larva";82;2
"Unit";"Roach";"Larva";82;2
"Unit";"Roach";"Larva";82;2
"Unit";"Roach";"Larva";82;2
"Unit";"Roach";"Larva";82;2
"Unit";"Roach";"Larva";82;2
"Unit";"Roach";"Larva";82;2
"Unit";"Roach";"Larva";82;2
"Upgrade";"ZergMissileWeaponsLevel1";"EvolutionChamber";73;0
"Upgrade";"GlialReconstitution";"RoachWarren";76;0
"Unit";"Overlord";"Larva";82;0
"Unit";"Overlord";"Larva";84;0
"Unit";"Overlord";"Larva";102;0
"Unit";"Overlord";"Larva";104;0
"Unit";"Overlord";"Larva";104;0
"Building";"CreepTumor";NA;104;0
"Unit";"Overlord";"Larva";104;0
"Unit";"Roach";"Larva";104;2
"Unit";"Roach";"Larva";104;2
"Building";"CreepTumor";NA;104;0
"Unit";"Overlord";"Larva";104;0
"Unit";"Roach";"Larva";104;2
"Unit";"Roach";"Larva";104;2
"Unit";"Roach";"Larva";104;2
"Unit";"Roach";"Larva";104;2
"Unit";"Roach";"Larva";104;2
"Unit";"Roach";"Larva";104;2
"Unit";"Roach";"Larva";104;2
"Building";"CreepTumor";NA;108;0
"Upgrade";"Burrow";"Hatchery";104;0
"Unit";"Roach";"Larva";110;2
"Unit";"Roach";"Larva";110;2
"Unit";"Roach";"Larva";110;2
"Unit";"Roach";"Larva";110;2
"Unit";"Roach";"Larva";110;2
"Unit";"Roach";"Larva";110;2
"Unit";"Roach";"Larva";110;2
"Building";"CreepTumor";NA;124;0
"Building";"Extractor";NA;124;0
"Building";"Extractor";NA;124;0
"Upgrade";"TunnelingClaws";"RoachWarren";108;0
"Unit";"Roach";"Larva";141;2
"Unit";"Roach";"Larva";141;2
"Unit";"Roach";"Larva";141;2
"Unit";"Roach";"Larva";141;2
"Unit";"Roach";"Larva";141;2
"Unit";"Roach";"Larva";141;2
"Unit";"Roach";"Larva";141;2
"Unit";"Roach";"Larva";141;2
"Unit";"Roach";"Larva";141;2
"Unit";"Overlord";"Larva";141;0
"Unit";"Roach";"Larva";149;2
"Unit";"Roach";"Larva";159;2
"Unit";"Roach";"Larva";159;2
"Unit";"Roach";"Larva";159;2
"Building";"CreepTumor";NA;159;0
"Unit";"Overlord";"Larva";159;0
"Building";"CreepTumor";NA;159;0
"Unit";"Overlord";"Larva";159;0
"Unit";"Queen";"Hatchery";141;2
"Building";"Extractor";NA;161;0
"Unit";"Overlord";"Larva";167;0
"Unit";"Overlord";"Larva";167;0
"Unit";"Overlord";"Larva";169;0
"Unit";"Overlord";"Larva";169;0
"Unit";"Overlord";"Larva";169;0
"Unit";"Roach";"Larva";171;2
"Unit";"Roach";"Larva";172;2
"Unit";"Roach";"Larva";172;2
"Upgrade";"ZergMissileWeaponsLevel2";"EvolutionChamber";124;0
"Unit";"Overlord";"Larva";178;0
"Unit";"Overlord";"Larva";178;0
"Unit";"Roach";"Larva";178;2
"Unit";"Roach";"Larva";178;2
"Unit";"Roach";"Larva";178;2
"Unit";"Roach";"Larva";178;2
"Unit";"Roach";"Larva";178;2
"Unit";"Roach";"Larva";182;2
"Building";"Hatchery";NA;159;0
"Unit";"Roach";"Larva";182;2
"Unit";"Roach";"Larva";182;2
"Unit";"Roach";"Larva";182;2
"Unit";"Roach";"Larva";188;2
"Building";"Spire";NA;167;0
"Unit";"Roach";"Larva";192;2
"Unit";"Roach";"Larva";192;2
"Unit";"Roach";"Larva";194;2
"Unit";"Roach";"Larva";194;2
"Unit";"Roach";"Larva";194;2
"Unit";"Mutalisk";"Larva";213;2
"Unit";"Mutalisk";"Larva";213;2
"Unit";"Mutalisk";"Larva";213;2
"Unit";"Mutalisk";"Larva";213;2
"Unit";"Mutalisk";"Larva";213;2
"Unit";"Mutalisk";"Larva";213;2
"Building";"SporeCrawler";NA;215;0
"Unit";"Overlord";"Larva";215;0
"Unit";"Mutalisk";"Larva";215;2
"Unit";"Mutalisk";"Larva";215;2
"Unit";"Mutalisk";"Larva";215;2
"Building";"CreepTumor";NA;231;0
"Building";"Extractor";NA;221;0
"Building";"Extractor";NA;231;0
"Unit";"Mutalisk";"Larva";231;2
"Unit";"Mutalisk";"Larva";231;2
"Unit";"Mutalisk";"Larva";231;2
"Building";"SpineCrawler";NA;231;0
"Unit";"Queen";"Hatchery";237;2
"Unit";"Overlord";"Larva";248;0
"Unit";"Overlord";"Larva";251;0
"Unit";"Roach";"Larva";251;2
"Unit";"Roach";"Larva";251;2
"Unit";"Roach";"Larva";251;2
"Unit";"Roach";"Larva";251;2
"Unit";"Roach";"Larva";251;2
"Unit";"Roach";"Larva";251;2
"Unit";"Roach";"Larva";251;2
"Unit";"Roach";"Larva";251;2
"Unit";"Roach";"Larva";251;2
"Unit";"Roach";"Larva";251;2
"Unit";"Roach";"Larva";251;2
"Unit";"Roach";"Larva";251;2
"Unit";"Roach";"Larva";251;2
"Unit";"Roach";"Larva";251;2
"Unit";"Roach";"Larva";251;2
"Unit";"Roach";"Larva";251;2
"Unit";"Roach";"Larva";251;2
"Unit";"Roach";"Larva";251;2
"Unit";"Roach";"Larva";251;2
"Unit";"Roach";"Larva";251;2
"Unit";"Roach";"Larva";251;2
"Unit";"Roach";"Larva";251;2
"Unit";"Roach";"Larva";251;2
"Unit";"Roach";"Larva";251;2
"Unit";"Roach";"Larva";251;2
"Unit";"Roach";"Larva";251;2
"Unit";"Roach";"Larva";251;2
"Building";"Hatchery";NA;248;0
"Unit";"Roach";"Larva";251;2
"Unit";"Overlord";"Larva";251;0
"Unit";"Roach";"Larva";251;2
"Unit";"Roach";"Larva";251;2
"Building";"CreepTumor";NA;281;0
"Unit";"Roach";"Larva";251;2
"Unit";"Roach";"Larva";253;2
"Unit";"Roach";"Larva";253;2
"Unit";"Roach";"Larva";253;2
"Unit";"Roach";"Larva";253;2
"Unit";"Roach";"Larva";255;2
"Unit";"Roach";"Larva";281;2
"Unit";"Roach";"Larva";281;2
"Unit";"Roach";"Larva";281;2
"Building";"CreepTumor";NA;305;0
"Unit";"Overlord";"Larva";305;0
"Unit";"Overlord";"Larva";305;0
"Upgrade";"ZergMeleeWeaponsLevel1";"EvolutionChamber";249;0
"Unit";"Roach";"Larva";321;2
"Unit";"Roach";"Larva";323;2
"Unit";"Roach";"Larva";323;2
"Unit";"Roach";"Larva";323;2
"Building";"HydraliskDen";NA;337;0
"Unit";"Overlord";"Larva";339;0
"Building";"InfestationPit";NA;337;0
"Building";"SporeCrawler";NA;339;0
"Building";"Extractor";NA;339;0
"Building";"Extractor";NA;339;0
"Unit";"Hydralisk";"Larva";339;2
"Unit";"Hydralisk";"Larva";339;2
"Unit";"Hydralisk";"Larva";339;2
"Unit";"Hydralisk";"Larva";339;2
"Unit";"Hydralisk";"Larva";339;2
"Unit";"Hydralisk";"Larva";339;2
"Unit";"Hydralisk";"Larva";339;2
"Unit";"Hydralisk";"Larva";339;2
"Unit";"Hydralisk";"Larva";339;2
"Unit";"Hydralisk";"Larva";339;2
"Unit";"Hydralisk";"Larva";339;2
"Unit";"Hydralisk";"Larva";339;2
"Unit";"Hydralisk";"Larva";339;2
"Unit";"Hydralisk";"Larva";339;2
"Unit";"Hydralisk";"Larva";339;2
"Unit";"Hydralisk";"Larva";339;2
"Unit";"Hydralisk";"Larva";339;2
"Unit";"Hydralisk";"Larva";339;2
"Unit";"Hydralisk";"Larva";339;2
"Unit";"Hydralisk";"Larva";341;2
"Unit";"Hydralisk";"Larva";341;2
"Unit";"Hydralisk";"Larva";341;2
"Unit";"Hydralisk";"Larva";341;2
"Unit";"Hydralisk";"Larva";341;2
"Unit";"Hydralisk";"Larva";341;2
"Unit";"Overlord";"Larva";341;0
"Unit";"Hydralisk";"Larva";341;2
"Unit";"Hydralisk";"Larva";379;2
"Unit";"Hydralisk";"Larva";379;2
"Unit";"Hydralisk";"Larva";379;2
"Unit";"Hydralisk";"Larva";379;2
"Unit";"Hydralisk";"Larva";379;2
"Unit";"Hydralisk";"Larva";391;2
"Unit";"Hydralisk";"Larva";391;2
"Upgrade";"ZergGroundArmorsLevel1";"EvolutionChamber";339;0
"Building";"CreepTumor";NA;395;0
"Upgrade";"EvolveGroovedSpines";"HydraliskDen";341;0
"Unit";"Roach";"Larva";393;2
"Unit";"Roach";"Larva";393;2
"Unit";"Roach";"Larva";393;2
"Unit";"Roach";"Larva";393;2
"Unit";"Roach";"Larva";393;2
"Unit";"Roach";"Larva";393;2
"Unit";"Roach";"Larva";393;2
"Unit";"Roach";"Larva";393;2
"Unit";"Roach";"Larva";393;2
"Unit";"Roach";"Larva";393;2
"Unit";"Roach";"Larva";393;2
"Unit";"Roach";"Larva";393;2
"Unit";"Roach";"Larva";393;2
"Unit";"Roach";"Larva";393;2
"Unit";"Roach";"Larva";397;2
"Unit";"Overlord";"Larva";407;0
