"type";"unit_name";"on_building";"total_supply";"supply"
"Unit";"Overlord";"Larva";13;0
"Building";"SpawningPool";NA;15;0
"Unit";"Zergling";"Larva";19;1
"Unit";"Zergling";"Larva";19;1
"Unit";"Zergling";"Larva";19;1
"Unit";"Zergling";"Larva";19;1
"Unit";"Zergling";"Larva";19;1
"Unit";"Zergling";"Larva";19;1
"Building";"Hatchery";NA;18;0
"Building";"Extractor";NA;25;0
"Unit";"Overlord";"Larva";25;0
"Unit";"Queen";"Hatchery";25;2
"Building";"Hatchery";NA;19;0
"Unit";"Overlord";"Larva";33;0
"Unit";"Queen";"Hatchery";29;2
"Unit";"Queen";"Hatchery";31;2
"Building";"CreepTumorQueen";NA;38;0
"Unit";"Overlord";"Larva";33;0
"Building";"CreepTumor";NA;46;0
"Building";"SporeCrawler";NA;46;0
"Building";"SporeCrawler";NA;46;0
"Building";"SporeCrawler";NA;49;0
"Unit";"Overlord";"Larva";55;0
"Unit";"Overlord";"Larva";55;0
"Building";"CreepTumor";NA;60;0
"Unit";"Overlord";"Larva";60;0
"Unit";"Overlord";"Larva";60;0
"Unit";"Zergling";"Larva";60;1
"Unit";"Zergling";"Larva";60;1
"Unit";"Zergling";"Larva";60;1
"Unit";"Zergling";"Larva";60;1
"Unit";"Zergling";"Larva";60;1
"Unit";"Zergling";"Larva";60;1
"Unit";"Zergling";"Larva";60;1
"Unit";"Zergling";"Larva";60;1
"Building";"BanelingNest";NA;60;0
"Building";"CreepTumor";NA;71;0
"Building";"Extractor";NA;71;0
"Building";"Extractor";NA;71;0
"Building";"Extractor";NA;77;0
"Building";"Extractor";NA;77;0
"Building";"CreepTumor";NA;92;0
"Building";"Extractor";NA;77;0
"Building";"CreepTumorQueen";NA;92;0
"Unit";"Overlord";"Larva";92;0
"Unit";"Overlord";"Larva";92;0
"Unit";"Overlord";"Larva";92;0
"Unit";"Queen";"Hatchery";77;2
"Unit";"Zergling";"Larva";92;1
"Unit";"Zergling";"Larva";92;1
"Unit";"Zergling";"Larva";93;1
"Unit";"Zergling";"Larva";93;1
"Unit";"Zergling";"Larva";93;1
"Unit";"Zergling";"Larva";93;1
"Unit";"Zergling";"Larva";93;1
"Unit";"Zergling";"Larva";93;1
"Unit";"Zergling";"Larva";93;1
"Unit";"Zergling";"Larva";93;1
"Unit";"Zergling";"Larva";93;1
"Unit";"Zergling";"Larva";93;1
"Unit";"Zergling";"Larva";93;1
"Unit";"Zergling";"Larva";93;1
"Unit";"Zergling";"Larva";93;1
"Unit";"Zergling";"Larva";93;1
"Unit";"Zergling";"Larva";93;1
"Unit";"Zergling";"Larva";93;1
"Unit";"Zergling";"Larva";93;1
"Unit";"Zergling";"Larva";93;1
"Unit";"Zergling";"Larva";95;1
"Unit";"Zergling";"Larva";95;1
"Unit";"Zergling";"Larva";95;1
"Unit";"Zergling";"Larva";95;1
"Unit";"Zergling";"Larva";95;1
"Unit";"Zergling";"Larva";95;1
"Building";"CreepTumor";NA;97;0
"Unit";"Overlord";"Larva";115;0
"Unit";"Overlord";"Larva";115;0
"Unit";"Zergling";"Larva";115;1
"Unit";"Zergling";"Larva";115;1
"Unit";"Overlord";"Larva";115;0
"Unit";"Zergling";"Larva";115;1
"Unit";"Zergling";"Larva";115;1
"Unit";"Zergling";"Larva";115;1
"Unit";"Zergling";"Larva";115;1
"Building";"Spire";NA;92;0
"Building";"CreepTumor";NA;135;0
"Unit";"Overlord";"Larva";135;0
"Unit";"Mutalisk";"Larva";135;2
"Unit";"Mutalisk";"Larva";137;2
"Unit";"Mutalisk";"Larva";137;2
"Unit";"Mutalisk";"Larva";137;2
"Unit";"Mutalisk";"Larva";137;2
"Unit";"Mutalisk";"Larva";137;2
"Unit";"Mutalisk";"Larva";138;2
"Unit";"Overlord";"Larva";139;0
"Building";"Hatchery";NA;115;0
"Unit";"Overlord";"Larva";139;0
"Unit";"Mutalisk";"Larva";139;2
"Unit";"Mutalisk";"Larva";139;2
"Unit";"Mutalisk";"Larva";139;2
"Unit";"Mutalisk";"Larva";139;2
"Building";"EvolutionChamber";NA;139;0
"Building";"EvolutionChamber";NA;139;0
"Unit";"Zergling";"Larva";155;1
"Unit";"Zergling";"Larva";155;1
"Unit";"Zergling";"Larva";157;1
"Unit";"Zergling";"Larva";157;1
"Unit";"Zergling";"Larva";159;1
"Unit";"Zergling";"Larva";159;1
"Unit";"Zergling";"Larva";161;1
"Unit";"Zergling";"Larva";161;1
"Unit";"Zergling";"Larva";161;1
"Unit";"Zergling";"Larva";161;1
"Unit";"Zergling";"Larva";161;1
"Unit";"Zergling";"Larva";161;1
"Unit";"Mutalisk";"Larva";153;2
"Unit";"Mutalisk";"Larva";153;2
"Unit";"Mutalisk";"Larva";153;2
"Unit";"Zergling";"Larva";161;1
"Unit";"Zergling";"Larva";161;1
"Unit";"Mutalisk";"Larva";161;2
"Unit";"Mutalisk";"Larva";161;2
"Unit";"Queen";"Hatchery";161;2
"Unit";"Zergling";"Larva";181;1
"Unit";"Zergling";"Larva";181;1
"Unit";"Zergling";"Larva";181;1
"Unit";"Zergling";"Larva";181;1
"Unit";"Zergling";"Larva";181;1
"Unit";"Zergling";"Larva";181;1
"Unit";"Zergling";"Larva";181;1
"Unit";"Zergling";"Larva";181;1
"Unit";"Zergling";"Larva";181;1
"Unit";"Zergling";"Larva";181;1
"Unit";"Overlord";"Larva";181;0
"Unit";"Mutalisk";"Larva";181;2
"Unit";"Mutalisk";"Larva";181;2
"Unit";"Mutalisk";"Larva";181;2
"Building";"InfestationPit";NA;206;0
"Unit";"Overlord";"Larva";214;0
"Unit";"Mutalisk";"Larva";214;2
"Unit";"Overlord";"Larva";214;0
"Unit";"Overlord";"Larva";214;0
"Unit";"Mutalisk";"Larva";214;2
"Unit";"Mutalisk";"Larva";214;2
"Unit";"Mutalisk";"Larva";214;2
"Unit";"Mutalisk";"Larva";214;2
"Upgrade";"ZergMeleeWeaponsLevel1";"EvolutionChamber";214;0
"Upgrade";"ZergGroundArmorsLevel1";"EvolutionChamber";214;0
"Unit";"Mutalisk";"Larva";224;2
"Unit";"Mutalisk";"Larva";224;2
"Unit";"Mutalisk";"Larva";224;2
"Unit";"Mutalisk";"Larva";224;2
"Unit";"Mutalisk";"Larva";224;2
"Unit";"Mutalisk";"Larva";224;2
"Unit";"Mutalisk";"Larva";224;2
"Unit";"Mutalisk";"Larva";224;2
"Unit";"Mutalisk";"Larva";224;2
"Unit";"Zergling";"Larva";224;1
"Unit";"Zergling";"Larva";224;1
"Unit";"Zergling";"Larva";224;1
"Unit";"Zergling";"Larva";224;1
"Unit";"Zergling";"Larva";224;1
"Unit";"Zergling";"Larva";224;1
"Unit";"Zergling";"Larva";224;1
"Unit";"Zergling";"Larva";224;1
"Unit";"Zergling";"Larva";224;1
"Unit";"Zergling";"Larva";224;1
"Unit";"Zergling";"Larva";224;1
"Unit";"Zergling";"Larva";224;1
"Unit";"Zergling";"Larva";224;1
"Unit";"Zergling";"Larva";224;1
"Unit";"Zergling";"Larva";224;1
"Unit";"Zergling";"Larva";224;1
"Unit";"Zergling";"Larva";224;1
"Unit";"Zergling";"Larva";224;1
"Unit";"Zergling";"Larva";224;1
"Unit";"Zergling";"Larva";224;1
"Unit";"Zergling";"Larva";224;1
"Unit";"Zergling";"Larva";224;1
"Building";"Extractor";NA;242;0
"Unit";"Zergling";"Larva";264;1
"Unit";"Zergling";"Larva";264;1
"Unit";"Zergling";"Larva";264;1
"Unit";"Zergling";"Larva";264;1
"Unit";"Zergling";"Larva";264;1
"Unit";"Zergling";"Larva";264;1
"Unit";"Zergling";"Larva";264;1
"Unit";"Zergling";"Larva";264;1
"Unit";"Zergling";"Larva";264;1
"Unit";"Zergling";"Larva";264;1
"Unit";"Zergling";"Larva";264;1
"Unit";"Zergling";"Larva";264;1
"Unit";"Zergling";"Larva";264;1
"Unit";"Zergling";"Larva";264;1
"Unit";"Zergling";"Larva";264;1
"Unit";"Zergling";"Larva";264;1
"Unit";"Zergling";"Larva";264;1
"Unit";"Zergling";"Larva";264;1
"Unit";"Zergling";"Larva";264;1
"Unit";"Zergling";"Larva";264;1
"Unit";"Zergling";"Larva";264;1
"Unit";"Zergling";"Larva";264;1
"Unit";"Zergling";"Larva";264;1
"Unit";"Zergling";"Larva";264;1
"Unit";"Zergling";"Larva";264;1
"Unit";"Zergling";"Larva";264;1
"Unit";"Zergling";"Larva";264;1
"Unit";"Zergling";"Larva";264;1
"Unit";"Zergling";"Larva";264;1
"Unit";"Zergling";"Larva";264;1
"Building";"Extractor";NA;242;0
"Unit";"Zergling";"Larva";294;1
"Unit";"Zergling";"Larva";294;1
"Unit";"Zergling";"Larva";294;1
"Unit";"Zergling";"Larva";294;1
"Unit";"Zergling";"Larva";294;1
"Unit";"Zergling";"Larva";294;1
"Unit";"Zergling";"Larva";294;1
"Unit";"Zergling";"Larva";294;1
"Unit";"Zergling";"Larva";294;1
"Unit";"Zergling";"Larva";294;1
"Unit";"Zergling";"Larva";294;1
"Unit";"Zergling";"Larva";294;1
"Unit";"Zergling";"Larva";294;1
"Unit";"Zergling";"Larva";294;1
"Unit";"Zergling";"Larva";294;1
"Unit";"Zergling";"Larva";294;1
"Unit";"Zergling";"Larva";294;1
"Unit";"Zergling";"Larva";294;1
"Unit";"Baneling";"Zergling";294;0
"Unit";"Baneling";"Zergling";294;0
"Unit";"Baneling";"Zergling";294;0
"Unit";"Baneling";"Zergling";294;0
"Unit";"Baneling";"Zergling";294;0
"Unit";"Baneling";"Zergling";294;0
"Unit";"Baneling";"Zergling";294;0
"Unit";"Baneling";"Zergling";294;0
"Unit";"Baneling";"Zergling";294;0
"Unit";"Baneling";"Zergling";294;0
"Unit";"Baneling";"Zergling";294;0
"Unit";"Baneling";"Zergling";294;0
"Unit";"Baneling";"Zergling";294;0
"Unit";"Baneling";"Zergling";294;0
"Unit";"Baneling";"Zergling";294;0
"Unit";"Baneling";"Zergling";294;0
"Unit";"Baneling";"Zergling";294;0
"Unit";"Baneling";"Zergling";294;0
"Unit";"Zergling";"Larva";294;1
"Unit";"Zergling";"Larva";294;1
"Unit";"Zergling";"Larva";294;1
"Unit";"Zergling";"Larva";294;1
"Unit";"Zergling";"Larva";294;1
"Unit";"Zergling";"Larva";294;1
"Unit";"Zergling";"Larva";294;1
"Unit";"Zergling";"Larva";294;1
"Unit";"Zergling";"Larva";294;1
"Unit";"Zergling";"Larva";294;1
"Unit";"Zergling";"Larva";294;1
"Unit";"Zergling";"Larva";294;1
"Unit";"Zergling";"Larva";294;1
"Unit";"Zergling";"Larva";294;1
"Unit";"Zergling";"Larva";294;1
"Unit";"Zergling";"Larva";294;1
"Unit";"Zergling";"Larva";328;1
"Unit";"Zergling";"Larva";328;1
"Unit";"Zergling";"Larva";328;1
"Unit";"Zergling";"Larva";328;1
"Unit";"Zergling";"Larva";328;1
"Unit";"Zergling";"Larva";328;1
"Unit";"Zergling";"Larva";328;1
"Unit";"Zergling";"Larva";328;1
"Unit";"Zergling";"Larva";328;1
"Unit";"Zergling";"Larva";328;1
"Unit";"Mutalisk";"Larva";328;2
"Unit";"Mutalisk";"Larva";328;2
"Unit";"Mutalisk";"Larva";328;2
"Unit";"Mutalisk";"Larva";328;2
"Unit";"Mutalisk";"Larva";328;2
"Unit";"Baneling";"Zergling";338;0
"Unit";"Baneling";"Zergling";341;0
"Unit";"Baneling";"Zergling";341;0
"Unit";"Baneling";"Zergling";341;0
"Unit";"Baneling";"Zergling";341;0
"Unit";"Baneling";"Zergling";341;0
"Unit";"Baneling";"Zergling";341;0
"Unit";"Baneling";"Zergling";341;0
"Unit";"Baneling";"Zergling";341;0
"Unit";"Baneling";"Zergling";341;0
"Unit";"Baneling";"Zergling";341;0
"Unit";"Baneling";"Zergling";341;0
"Unit";"Baneling";"Zergling";341;0
"Unit";"Mutalisk";"Larva";328;2
"Unit";"Mutalisk";"Larva";351;2
"Unit";"Mutalisk";"Larva";351;2
"Upgrade";"ZergGroundArmorsLevel2";"EvolutionChamber";294;0
"Upgrade";"ZergMeleeWeaponsLevel2";"EvolutionChamber";294;0
"Unit";"Corruptor";"Larva";357;2
"Unit";"Corruptor";"Larva";357;2
"Unit";"Corruptor";"Larva";357;2
"Unit";"Corruptor";"Larva";357;2
"Unit";"Corruptor";"Larva";357;2
"Unit";"Corruptor";"Larva";357;2
"Unit";"Baneling";"Zergling";357;0
"Unit";"Baneling";"Zergling";357;0
"Unit";"Baneling";"Zergling";357;0
"Unit";"Baneling";"Zergling";357;0
"Unit";"Baneling";"Zergling";357;0
"Unit";"Baneling";"Zergling";357;0
"Unit";"Baneling";"Zergling";357;0
"Unit";"Baneling";"Zergling";357;0
"Unit";"Baneling";"Zergling";357;0
"Unit";"Baneling";"Zergling";357;0
"Unit";"Zergling";"Larva";357;1
"Unit";"Zergling";"Larva";357;1
"Unit";"Zergling";"Larva";357;1
"Unit";"Zergling";"Larva";357;1
"Unit";"Zergling";"Larva";357;1
"Unit";"Zergling";"Larva";357;1
"Unit";"Zergling";"Larva";357;1
"Unit";"Zergling";"Larva";357;1
"Unit";"Zergling";"Larva";357;1
"Unit";"Zergling";"Larva";357;1
"Unit";"Zergling";"Larva";357;1
"Unit";"Zergling";"Larva";357;1
"Unit";"Zergling";"Larva";357;1
"Unit";"Zergling";"Larva";357;1
"Unit";"Overlord";"Larva";357;0
"Unit";"Overlord";"Larva";357;0
"Unit";"Overlord";"Larva";357;0
"Unit";"Overlord";"Larva";357;0
"Unit";"Overlord";"Larva";357;0
"Unit";"Overlord";"Larva";357;0
"Building";"Hatchery";NA;357;0
"Building";"UltraliskCavern";NA;369;0
"Unit";"Zergling";"Larva";383;1
"Unit";"Zergling";"Larva";383;1
"Unit";"Zergling";"Larva";383;1
"Unit";"Zergling";"Larva";383;1
"Unit";"Zergling";"Larva";383;1
"Unit";"Zergling";"Larva";383;1
"Unit";"Zergling";"Larva";383;1
"Unit";"Zergling";"Larva";383;1
"Unit";"Zergling";"Larva";383;1
"Unit";"Zergling";"Larva";383;1
"Unit";"Zergling";"Larva";383;1
"Unit";"Zergling";"Larva";383;1
"Unit";"Zergling";"Larva";383;1
"Unit";"Zergling";"Larva";383;1
"Unit";"Zergling";"Larva";383;1
"Unit";"Zergling";"Larva";383;1
"Unit";"Zergling";"Larva";383;1
"Unit";"Zergling";"Larva";383;1
"Unit";"Zergling";"Larva";383;1
"Unit";"Zergling";"Larva";383;1
"Unit";"Zergling";"Larva";383;1
"Unit";"Zergling";"Larva";383;1
"Unit";"Zergling";"Larva";383;1
"Unit";"Zergling";"Larva";383;1
"Unit";"Zergling";"Larva";383;1
"Unit";"Zergling";"Larva";383;1
"Unit";"Zergling";"Larva";383;1
"Unit";"Zergling";"Larva";383;1
"Unit";"Zergling";"Larva";383;1
"Unit";"Zergling";"Larva";383;1
"Unit";"Zergling";"Larva";383;1
"Unit";"Zergling";"Larva";383;1
"Unit";"Zergling";"Larva";383;1
"Unit";"Zergling";"Larva";383;1
"Unit";"Zergling";"Larva";383;1
"Unit";"Zergling";"Larva";383;1
"Unit";"Zergling";"Larva";383;1
"Unit";"Zergling";"Larva";383;1
"Unit";"Zergling";"Larva";383;1
"Unit";"Zergling";"Larva";383;1
"Unit";"Zergling";"Larva";383;1
"Unit";"Zergling";"Larva";383;1
"Unit";"Zergling";"Larva";383;1
"Unit";"Zergling";"Larva";383;1
"Unit";"Zergling";"Larva";383;1
"Unit";"Zergling";"Larva";383;1
"Unit";"Zergling";"Larva";383;1
"Unit";"Zergling";"Larva";383;1
"Unit";"Zergling";"Larva";383;1
"Unit";"Zergling";"Larva";383;1
"Unit";"Zergling";"Larva";383;1
"Unit";"Zergling";"Larva";383;1
"Unit";"Zergling";"Larva";383;1
"Unit";"Zergling";"Larva";383;1
"Unit";"Zergling";"Larva";383;1
"Unit";"Zergling";"Larva";383;1
"Unit";"Zergling";"Larva";383;1
"Unit";"Zergling";"Larva";383;1
"Unit";"Zergling";"Larva";383;1
"Unit";"Zergling";"Larva";383;1
"Unit";"Zergling";"Larva";383;1
"Unit";"Zergling";"Larva";383;1
"Unit";"Zergling";"Larva";383;1
"Unit";"Zergling";"Larva";383;1
"Unit";"Zergling";"Larva";383;1
"Unit";"Zergling";"Larva";383;1
"Building";"SporeCrawler";NA;383;0
"Building";"SporeCrawler";NA;383;0
"Building";"Extractor";NA;383;0
"Unit";"Ultralisk";"Larva";383;6
"Unit";"Ultralisk";"Larva";383;6
"Unit";"Ultralisk";"Larva";383;6
"Building";"Extractor";NA;385;0
"Building";"SporeCrawler";NA;449;0
"Unit";"Corruptor";"Larva";419;2
"Unit";"Corruptor";"Larva";431;2
"Unit";"Corruptor";"Larva";439;2
"Unit";"Corruptor";"Larva";449;2
"Building";"CreepTumorQueen";NA;473;0
"Building";"CreepTumorQueen";NA;476;0
"Upgrade";"ChitinousPlating";"UltraliskCavern";383;0
"Unit";"Zergling";"Larva";484;1
"Unit";"Zergling";"Larva";484;1
"Unit";"Zergling";"Larva";484;1
"Unit";"Zergling";"Larva";484;1
"Unit";"Zergling";"Larva";484;1
"Unit";"Zergling";"Larva";484;1
"Unit";"Zergling";"Larva";484;1
"Unit";"Zergling";"Larva";484;1
"Unit";"Zergling";"Larva";484;1
"Unit";"Zergling";"Larva";484;1
"Unit";"Zergling";"Larva";484;1
"Unit";"Zergling";"Larva";484;1
"Unit";"Zergling";"Larva";484;1
"Unit";"Zergling";"Larva";484;1
"Unit";"Zergling";"Larva";484;1
"Unit";"Zergling";"Larva";484;1
"Unit";"Zergling";"Larva";484;1
"Unit";"Zergling";"Larva";484;1
"Unit";"Zergling";"Larva";484;1
"Unit";"Zergling";"Larva";484;1
"Unit";"Zergling";"Larva";484;1
"Unit";"Zergling";"Larva";484;1
"Unit";"Zergling";"Larva";484;1
"Unit";"Zergling";"Larva";484;1
"Unit";"Zergling";"Larva";484;1
"Unit";"Zergling";"Larva";484;1
"Unit";"Zergling";"Larva";484;1
"Unit";"Zergling";"Larva";484;1
"Unit";"Zergling";"Larva";484;1
"Unit";"Zergling";"Larva";484;1
"Unit";"Zergling";"Larva";484;1
"Unit";"Zergling";"Larva";484;1
"Unit";"Zergling";"Larva";484;1
"Unit";"Zergling";"Larva";484;1
"Unit";"Zergling";"Larva";484;1
"Unit";"Zergling";"Larva";484;1
"Unit";"Zergling";"Larva";484;1
"Unit";"Zergling";"Larva";484;1
"Unit";"Zergling";"Larva";484;1
"Unit";"Zergling";"Larva";484;1
"Unit";"Zergling";"Larva";484;1
"Unit";"Zergling";"Larva";484;1
"Building";"CreepTumor";NA;526;0
"Upgrade";"ZergGroundArmorsLevel3";"EvolutionChamber";449;0
"Upgrade";"ZergMeleeWeaponsLevel3";"EvolutionChamber";449;0
"Building";"CreepTumorQueen";NA;526;0
"Building";"CreepTumorQueen";NA;526;0
"Unit";"Zergling";"Larva";526;1
"Unit";"Zergling";"Larva";526;1
"Unit";"Zergling";"Larva";526;1
"Unit";"Zergling";"Larva";526;1
"Unit";"Zergling";"Larva";526;1
"Unit";"Zergling";"Larva";526;1
"Unit";"Zergling";"Larva";526;1
"Unit";"Zergling";"Larva";526;1
"Unit";"Zergling";"Larva";526;1
"Unit";"Zergling";"Larva";526;1
"Unit";"Zergling";"Larva";526;1
"Unit";"Zergling";"Larva";526;1
"Unit";"Zergling";"Larva";526;1
"Unit";"Zergling";"Larva";526;1
"Unit";"Zergling";"Larva";526;1
"Unit";"Zergling";"Larva";526;1
"Unit";"Zergling";"Larva";526;1
"Unit";"Zergling";"Larva";526;1
"Unit";"Zergling";"Larva";526;1
"Unit";"Zergling";"Larva";526;1
"Unit";"Zergling";"Larva";526;1
"Unit";"Zergling";"Larva";526;1
"Unit";"Zergling";"Larva";526;1
"Unit";"Zergling";"Larva";526;1
"Unit";"Zergling";"Larva";526;1
"Unit";"Zergling";"Larva";526;1
"Unit";"Zergling";"Larva";526;1
"Unit";"Zergling";"Larva";526;1
"Unit";"Zergling";"Larva";526;1
"Unit";"Zergling";"Larva";526;1
"Unit";"Zergling";"Larva";526;1
"Unit";"Zergling";"Larva";526;1
"Unit";"Zergling";"Larva";526;1
"Unit";"Zergling";"Larva";526;1
"Unit";"Zergling";"Larva";526;1
"Unit";"Zergling";"Larva";526;1
"Unit";"Zergling";"Larva";526;1
"Unit";"Zergling";"Larva";526;1
"Unit";"Zergling";"Larva";526;1
"Unit";"Zergling";"Larva";526;1
"Building";"CreepTumor";NA;526;0
"Unit";"Ultralisk";"Larva";526;6
"Unit";"Ultralisk";"Larva";526;6
"Unit";"Ultralisk";"Larva";526;6
"Unit";"Zergling";"Larva";584;1
"Unit";"Zergling";"Larva";584;1
"Unit";"Zergling";"Larva";584;1
"Unit";"Zergling";"Larva";584;1
"Unit";"Zergling";"Larva";584;1
"Unit";"Zergling";"Larva";584;1
"Unit";"Zergling";"Larva";584;1
"Unit";"Zergling";"Larva";584;1
"Unit";"Zergling";"Larva";584;1
"Unit";"Zergling";"Larva";584;1
"Unit";"Zergling";"Larva";584;1
"Unit";"Zergling";"Larva";584;1
"Unit";"Zergling";"Larva";584;1
"Unit";"Zergling";"Larva";584;1
"Unit";"Zergling";"Larva";584;1
"Unit";"Zergling";"Larva";584;1
"Unit";"Zergling";"Larva";584;1
"Unit";"Zergling";"Larva";584;1
"Unit";"Zergling";"Larva";584;1
"Unit";"Zergling";"Larva";584;1
"Unit";"Zergling";"Larva";584;1
"Unit";"Zergling";"Larva";584;1
"Unit";"Zergling";"Larva";584;1
"Unit";"Zergling";"Larva";584;1
"Unit";"Zergling";"Larva";584;1
"Unit";"Zergling";"Larva";584;1
"Unit";"Zergling";"Larva";584;1
"Unit";"Zergling";"Larva";584;1
"Unit";"Zergling";"Larva";584;1
"Unit";"Zergling";"Larva";584;1
"Unit";"Zergling";"Larva";584;1
"Unit";"Zergling";"Larva";584;1
"Unit";"Zergling";"Larva";584;1
"Unit";"Zergling";"Larva";584;1
"Unit";"Zergling";"Larva";584;1
"Unit";"Zergling";"Larva";584;1
"Unit";"Zergling";"Larva";584;1
"Unit";"Zergling";"Larva";584;1
"Unit";"Zergling";"Larva";584;1
"Unit";"Zergling";"Larva";584;1
"Unit";"Zergling";"Larva";584;1
"Unit";"Zergling";"Larva";584;1
"Unit";"Zergling";"Larva";584;1
"Unit";"Zergling";"Larva";584;1
"Unit";"Zergling";"Larva";584;1
"Unit";"Zergling";"Larva";584;1
"Unit";"Zergling";"Larva";584;1
"Unit";"Zergling";"Larva";584;1
"Unit";"Zergling";"Larva";584;1
"Unit";"Zergling";"Larva";584;1
"Unit";"Zergling";"Larva";584;1
"Unit";"Zergling";"Larva";584;1
"Unit";"Zergling";"Larva";584;1
"Unit";"Zergling";"Larva";584;1
"Unit";"Zergling";"Larva";584;1
"Unit";"Zergling";"Larva";584;1
"Unit";"Zergling";"Larva";584;1
"Unit";"Zergling";"Larva";584;1
"Unit";"Zergling";"Larva";584;1
"Unit";"Zergling";"Larva";584;1
"Unit";"Zergling";"Larva";584;1
"Unit";"Zergling";"Larva";584;1
"Unit";"Zergling";"Larva";584;1
"Unit";"Zergling";"Larva";584;1
"Unit";"Zergling";"Larva";584;1
"Unit";"Zergling";"Larva";584;1
"Unit";"Zergling";"Larva";584;1
"Unit";"Zergling";"Larva";584;1
"Unit";"Zergling";"Larva";584;1
"Unit";"Zergling";"Larva";584;1
"Unit";"Zergling";"Larva";584;1
"Unit";"Zergling";"Larva";584;1
"Unit";"Zergling";"Larva";584;1
"Unit";"Zergling";"Larva";584;1
"Unit";"Zergling";"Larva";584;1
"Unit";"Zergling";"Larva";584;1
"Unit";"Zergling";"Larva";584;1
"Unit";"Zergling";"Larva";584;1
"Unit";"Zergling";"Larva";584;1
"Unit";"Zergling";"Larva";584;1
"Unit";"Zergling";"Larva";584;1
"Unit";"Zergling";"Larva";584;1
"Unit";"Zergling";"Larva";584;1
"Unit";"Zergling";"Larva";584;1
"Unit";"Zergling";"Larva";584;1
"Unit";"Zergling";"Larva";584;1
"Unit";"Zergling";"Larva";584;1
"Unit";"Zergling";"Larva";584;1
"Unit";"Zergling";"Larva";584;1
"Unit";"Zergling";"Larva";584;1
"Unit";"Zergling";"Larva";674;1
"Unit";"Zergling";"Larva";674;1
"Unit";"Zergling";"Larva";674;1
"Unit";"Zergling";"Larva";674;1
"Unit";"Zergling";"Larva";674;1
"Unit";"Zergling";"Larva";674;1
"Unit";"Zergling";"Larva";674;1
"Unit";"Zergling";"Larva";674;1
"Unit";"Zergling";"Larva";674;1
"Unit";"Zergling";"Larva";674;1
"Unit";"Zergling";"Larva";674;1
"Unit";"Zergling";"Larva";674;1
"Unit";"Zergling";"Larva";674;1
"Unit";"Zergling";"Larva";674;1
"Unit";"Zergling";"Larva";674;1
"Unit";"Zergling";"Larva";674;1
"Unit";"Zergling";"Larva";674;1
"Unit";"Zergling";"Larva";674;1
"Unit";"Zergling";"Larva";674;1
"Unit";"Zergling";"Larva";674;1
"Unit";"Zergling";"Larva";674;1
"Unit";"Zergling";"Larva";674;1
"Unit";"Zergling";"Larva";674;1
"Unit";"Zergling";"Larva";674;1
"Unit";"Zergling";"Larva";674;1
"Unit";"Zergling";"Larva";674;1
"Unit";"Zergling";"Larva";674;1
"Unit";"Zergling";"Larva";674;1
"Unit";"Zergling";"Larva";674;1
"Unit";"Zergling";"Larva";674;1
"Unit";"Zergling";"Larva";674;1
"Unit";"Zergling";"Larva";674;1
"Unit";"Zergling";"Larva";674;1
"Unit";"Zergling";"Larva";674;1
"Unit";"Zergling";"Larva";674;1
"Unit";"Zergling";"Larva";674;1
"Unit";"Zergling";"Larva";674;1
"Unit";"Zergling";"Larva";674;1
"Unit";"Zergling";"Larva";674;1
"Unit";"Zergling";"Larva";674;1
"Unit";"Zergling";"Larva";674;1
"Unit";"Zergling";"Larva";674;1
"Unit";"Zergling";"Larva";674;1
"Unit";"Zergling";"Larva";674;1
"Unit";"Zergling";"Larva";674;1
"Unit";"Zergling";"Larva";674;1
"Unit";"Zergling";"Larva";674;1
"Unit";"Zergling";"Larva";674;1
"Unit";"Zergling";"Larva";674;1
"Unit";"Zergling";"Larva";674;1
"Unit";"Zergling";"Larva";674;1
"Unit";"Zergling";"Larva";674;1
"Unit";"Zergling";"Larva";674;1
"Unit";"Zergling";"Larva";674;1
"Unit";"Zergling";"Larva";674;1
"Unit";"Zergling";"Larva";674;1
"Unit";"Zergling";"Larva";674;1
"Unit";"Zergling";"Larva";674;1
"Unit";"Zergling";"Larva";674;1
"Unit";"Zergling";"Larva";674;1
"Unit";"Zergling";"Larva";674;1
"Unit";"Zergling";"Larva";674;1
"Unit";"Mutalisk";"Larva";736;2
"Unit";"Mutalisk";"Larva";736;2
"Unit";"Mutalisk";"Larva";736;2
"Unit";"Mutalisk";"Larva";736;2
"Unit";"Mutalisk";"Larva";736;2
"Unit";"Mutalisk";"Larva";736;2
"Unit";"Mutalisk";"Larva";736;2
"Unit";"Mutalisk";"Larva";736;2
"Unit";"Mutalisk";"Larva";736;2
"Unit";"Mutalisk";"Larva";736;2
"Unit";"Mutalisk";"Larva";736;2
"Unit";"Mutalisk";"Larva";736;2
"Unit";"Mutalisk";"Larva";736;2
"Unit";"Mutalisk";"Larva";736;2
"Building";"Extractor";NA;736;0
"Building";"Extractor";NA;736;0
