"type";"unit_name";"on_building";"total_supply";"supply"
"Unit";"Overlord";"Larva";12;0
"Building";"Extractor";NA;17;0
"Building";"Hatchery";NA;17;0
"Building";"SpawningPool";NA;19;0
"Unit";"Overlord";"Larva";22;0
"Unit";"Zergling";"Larva";23;1
"Unit";"Zergling";"Larva";23;1
"Unit";"Zergling";"Larva";23;1
"Unit";"Zergling";"Larva";23;1
"Unit";"Queen";"Hatchery";23;2
"Unit";"Queen";"Hatchery";23;2
"Unit";"Overlord";"Larva";36;0
"Building";"CreepTumorQueen";NA;40;0
"Building";"CreepTumorQueen";NA;41;0
"Unit";"Queen";"Hatchery";38;2
"Unit";"Overlord";"Larva";41;0
"Unit";"Zergling";"Larva";41;1
"Unit";"Zergling";"Larva";41;1
"Unit";"Zergling";"Larva";41;1
"Unit";"Zergling";"Larva";41;1
"Unit";"Zergling";"Larva";41;1
"Unit";"Zergling";"Larva";41;1
"Unit";"Overlord";"Larva";42;0
"Building";"Hatchery";NA;30;0
"Unit";"Queen";"Hatchery";41;2
"Building";"CreepTumor";NA;51;0
"Building";"SporeCrawler";NA;43;0
"Building";"CreepTumorQueen";NA;56;0
"Building";"CreepTumor";NA;58;0
"Unit";"Overlord";"Larva";59;0
"Building";"SporeCrawler";NA;60;0
"Building";"SporeCrawler";NA;62;0
"Building";"CreepTumor";NA;62;0
"Building";"Extractor";NA;67;0
"Building";"Extractor";NA;67;0
"Building";"Extractor";NA;67;0
"Unit";"Overlord";"Larva";67;0
"Building";"EvolutionChamber";NA;67;0
"Building";"CreepTumor";NA;72;0
"Building";"HydraliskDen";NA;70;0
"Unit";"Overlord";"Larva";76;0
"Unit";"Overlord";"Larva";76;0
"Unit";"Overlord";"Larva";80;0
"Building";"Extractor";NA;87;0
"Unit";"Hydralisk";"Larva";87;2
"Unit";"Hydralisk";"Larva";87;2
"Unit";"Hydralisk";"Larva";87;2
"Unit";"Hydralisk";"Larva";92;2
"Unit";"Overlord";"Larva";92;0
"Unit";"Zergling";"Larva";92;1
"Unit";"Zergling";"Larva";92;1
"Unit";"Zergling";"Larva";92;1
"Unit";"Zergling";"Larva";92;1
"Unit";"Overlord";"Larva";92;0
"Unit";"Zergling";"Larva";92;1
"Unit";"Zergling";"Larva";92;1
"Unit";"Zergling";"Larva";92;1
"Unit";"Zergling";"Larva";92;1
"Unit";"Zergling";"Larva";92;1
"Unit";"Zergling";"Larva";92;1
"Unit";"Zergling";"Larva";92;1
"Unit";"Zergling";"Larva";92;1
"Building";"CreepTumorQueen";NA;98;0
"Unit";"Hydralisk";"Larva";92;2
"Building";"CreepTumor";NA;98;0
"Building";"CreepTumorQueen";NA;100;0
"Unit";"Hydralisk";"Larva";98;2
"Unit";"Hydralisk";"Larva";98;2
"Unit";"Hydralisk";"Larva";98;2
"Unit";"Hydralisk";"Larva";100;2
"Unit";"Hydralisk";"Larva";100;2
"Upgrade";"EvolveGroovedSpines";"HydraliskDen";92;0
"Unit";"Hydralisk";"Larva";112;2
"Unit";"Hydralisk";"Larva";114;2
"Unit";"Hydralisk";"Larva";114;2
"Unit";"Hydralisk";"Larva";120;2
"Unit";"Hydralisk";"Larva";120;2
"Building";"LurkerDenMP";NA;87;0
"Unit";"Hydralisk";"Larva";126;2
"Building";"Extractor";NA;126;0
"Building";"CreepTumor";NA;134;0
"Building";"CreepTumor";NA;140;0
"Building";"CreepTumor";NA;140;0
"Unit";"Zergling";"Larva";140;1
"Unit";"Zergling";"Larva";140;1
"Unit";"Zergling";"Larva";140;1
"Unit";"Zergling";"Larva";140;1
"Unit";"Zergling";"Larva";140;1
"Unit";"Zergling";"Larva";140;1
"Unit";"Zergling";"Larva";140;1
"Unit";"Zergling";"Larva";140;1
"Upgrade";"ZergMissileWeaponsLevel1";"EvolutionChamber";92;0
"Building";"Extractor";NA;145;0
"Unit";"Zergling";"Larva";153;1
"Unit";"Zergling";"Larva";153;1
"Unit";"Overlord";"Larva";153;0
"Unit";"Overlord";"Larva";153;0
"Unit";"Overlord";"Larva";153;0
"Unit";"Overlord";"Larva";153;0
"Unit";"Overlord";"Larva";153;0
"Building";"CreepTumor";NA;158;0
"Building";"CreepTumor";NA;158;0
"Unit";"Overlord";"Larva";156;0
"Building";"CreepTumor";NA;158;0
"Upgrade";"EvolveMuscularAugments";"HydraliskDen";145;0
"Building";"Extractor";NA;158;0
"Unit";"Zergling";"Larva";158;1
"Unit";"Zergling";"Larva";158;1
"Unit";"Zergling";"Larva";158;1
"Unit";"Zergling";"Larva";158;1
"Unit";"Zergling";"Larva";158;1
"Unit";"Zergling";"Larva";158;1
"Unit";"Hydralisk";"Larva";158;2
"Unit";"Hydralisk";"Larva";158;2
"Unit";"Hydralisk";"Larva";158;2
"Unit";"Hydralisk";"Larva";158;2
"Unit";"Hydralisk";"Larva";158;2
"Building";"Hatchery";NA;145;0
"Unit";"Overlord";"Larva";177;0
"Unit";"Overlord";"Larva";177;0
"Unit";"Overlord";"Larva";177;0
"Unit";"Overlord";"Larva";177;0
"Unit";"Overlord";"Larva";177;0
"Building";"CreepTumor";NA;177;0
"Unit";"Hydralisk";"Larva";177;2
"Unit";"Hydralisk";"Larva";177;2
"Building";"InfestationPit";NA;177;0
"Unit";"Hydralisk";"Larva";186;2
"Unit";"Hydralisk";"Larva";186;2
"Unit";"Hydralisk";"Larva";186;2
"Unit";"Hydralisk";"Larva";186;2
"Unit";"Hydralisk";"Larva";186;2
"Unit";"Hydralisk";"Larva";186;2
"Unit";"Hydralisk";"Larva";186;2
"Unit";"Hydralisk";"Larva";186;2
"Unit";"Hydralisk";"Larva";186;2
"Unit";"Hydralisk";"Larva";186;2
"Unit";"Hydralisk";"Larva";186;2
"Building";"SporeCrawler";NA;186;0
"Unit";"Queen";"Hatchery";186;2
"Building";"SpineCrawler";NA;186;0
"Building";"SpineCrawler";NA;186;0
"Building";"SpineCrawler";NA;186;0
"Building";"SpineCrawler";NA;186;0
"Building";"SpineCrawler";NA;186;0
"Unit";"Hydralisk";"Larva";212;2
"Unit";"Hydralisk";"Larva";212;2
"Unit";"Hydralisk";"Larva";212;2
"Unit";"Hydralisk";"Larva";212;2
"Unit";"Hydralisk";"Larva";212;2
"Unit";"Hydralisk";"Larva";212;2
"Unit";"Hydralisk";"Larva";212;2
"Unit";"Hydralisk";"Larva";212;2
"Unit";"Hydralisk";"Larva";212;2
"Unit";"Zergling";"Larva";212;1
"Unit";"Zergling";"Larva";212;1
"Unit";"Zergling";"Larva";212;1
"Unit";"Zergling";"Larva";212;1
"Unit";"Zergling";"Larva";212;1
"Unit";"Zergling";"Larva";212;1
"Building";"CreepTumor";NA;214;0
"Unit";"Hydralisk";"Larva";212;2
"Unit";"Hydralisk";"Larva";212;2
"Unit";"Hydralisk";"Larva";212;2
"Unit";"Hydralisk";"Larva";212;2
"Unit";"Hydralisk";"Larva";212;2
"Building";"EvolutionChamber";NA;232;0
"Unit";"Hydralisk";"Larva";251;2
"Unit";"Hydralisk";"Larva";251;2
"Unit";"Hydralisk";"Larva";251;2
"Unit";"Hydralisk";"Larva";251;2
"Unit";"Hydralisk";"Larva";251;2
"Unit";"Hydralisk";"Larva";251;2
"Unit";"Hydralisk";"Larva";251;2
"Unit";"Hydralisk";"Larva";251;2
"Unit";"Hydralisk";"Larva";251;2
"Unit";"Hydralisk";"Larva";251;2
"Unit";"Hydralisk";"Larva";251;2
"Unit";"Hydralisk";"Larva";251;2
"Unit";"Hydralisk";"Larva";251;2
"Unit";"Hydralisk";"Larva";251;2
"Unit";"Hydralisk";"Larva";251;2
"Unit";"Hydralisk";"Larva";251;2
"Unit";"Hydralisk";"Larva";251;2
"Upgrade";"ZergMissileWeaponsLevel2";"EvolutionChamber";186;0
"Unit";"Hydralisk";"Larva";285;2
"Unit";"Hydralisk";"Larva";285;2
"Unit";"Hydralisk";"Larva";285;2
"Unit";"Hydralisk";"Larva";285;2
"Unit";"Hydralisk";"Larva";285;2
"Unit";"Hydralisk";"Larva";285;2
"Unit";"Hydralisk";"Larva";285;2
"Unit";"Hydralisk";"Larva";285;2
"Unit";"Hydralisk";"Larva";285;2
"Unit";"Hydralisk";"Larva";285;2
"Unit";"Hydralisk";"Larva";285;2
"Unit";"Hydralisk";"Larva";285;2
"Unit";"Hydralisk";"Larva";285;2
"Unit";"Hydralisk";"Larva";285;2
"Unit";"Hydralisk";"Larva";285;2
"Unit";"Hydralisk";"Larva";303;2
"Unit";"Hydralisk";"Larva";303;2
"Unit";"Hydralisk";"Larva";303;2
"Unit";"Hydralisk";"Larva";303;2
"Unit";"Hydralisk";"Larva";303;2
"Unit";"Zergling";"Larva";315;1
"Unit";"Zergling";"Larva";315;1
"Unit";"Zergling";"Larva";315;1
"Unit";"Zergling";"Larva";315;1
"Unit";"Zergling";"Larva";315;1
"Unit";"Zergling";"Larva";315;1
"Unit";"Zergling";"Larva";315;1
"Unit";"Zergling";"Larva";315;1
"Unit";"Zergling";"Larva";315;1
"Unit";"Zergling";"Larva";315;1
"Building";"CreepTumor";NA;327;0
"Building";"CreepTumor";NA;335;0
"Unit";"Queen";"Hatchery";315;2
"Building";"Extractor";NA;337;0
"Building";"Extractor";NA;337;0
"Unit";"Zergling";"Larva";337;1
"Unit";"Zergling";"Larva";337;1
"Unit";"Overlord";"Larva";347;0
"Unit";"Overlord";"Larva";347;0
"Unit";"Overlord";"Larva";347;0
"Unit";"Overlord";"Larva";347;0
"Unit";"Overlord";"Larva";347;0
"Building";"CreepTumor";NA;347;0
"Building";"CreepTumor";NA;347;0
"Building";"Hatchery";NA;337;0
"Building";"Spire";NA;337;0
"Building";"CreepTumorQueen";NA;352;0
"Building";"CreepTumorQueen";NA;352;0
"Building";"SpineCrawler";NA;347;0
"Building";"SpineCrawler";NA;347;0
"Building";"SpineCrawler";NA;347;0
"Unit";"Hydralisk";"Larva";352;2
"Unit";"Hydralisk";"Larva";352;2
"Unit";"Hydralisk";"Larva";352;2
"Unit";"Hydralisk";"Larva";352;2
"Unit";"Hydralisk";"Larva";352;2
"Unit";"Hydralisk";"Larva";352;2
"Unit";"Hydralisk";"Larva";352;2
"Unit";"Hydralisk";"Larva";352;2
"Building";"SporeCrawler";NA;352;0
"Unit";"Hydralisk";"Larva";352;2
"Unit";"Hydralisk";"Larva";352;2
"Unit";"Hydralisk";"Larva";352;2
"Unit";"Hydralisk";"Larva";352;2
"Unit";"Hydralisk";"Larva";352;2
"Unit";"Hydralisk";"Larva";352;2
"Upgrade";"ZergGroundArmorsLevel1";"EvolutionChamber";347;0
"Building";"SpineCrawler";NA;352;0
"Unit";"Hydralisk";"Larva";368;2
"Unit";"Hydralisk";"Larva";368;2
"Unit";"Hydralisk";"Larva";368;2
"Unit";"Hydralisk";"Larva";368;2
"Unit";"Hydralisk";"Larva";368;2
"Unit";"Hydralisk";"Larva";368;2
"Building";"SpineCrawler";NA;368;0
"Building";"SpineCrawler";NA;368;0
"Building";"SpineCrawler";NA;368;0
"Unit";"Corruptor";"Larva";380;2
"Unit";"Corruptor";"Larva";380;2
"Unit";"Corruptor";"Larva";380;2
"Unit";"Corruptor";"Larva";380;2
"Unit";"Corruptor";"Larva";380;2
"Unit";"Corruptor";"Larva";380;2
"Upgrade";"ZergMissileWeaponsLevel3";"EvolutionChamber";347;0
"Unit";"Hydralisk";"Larva";392;2
"Unit";"Hydralisk";"Larva";392;2
"Unit";"Hydralisk";"Larva";392;2
"Unit";"Hydralisk";"Larva";392;2
"Unit";"Hydralisk";"Larva";392;2
"Unit";"Hydralisk";"Larva";392;2
"Unit";"Hydralisk";"Larva";392;2
"Unit";"Hydralisk";"Larva";392;2
"Unit";"Hydralisk";"Larva";392;2
"Unit";"Hydralisk";"Larva";392;2
"Unit";"Hydralisk";"Larva";392;2
"Unit";"Hydralisk";"Larva";392;2
"Unit";"Corruptor";"Larva";392;2
"Unit";"Corruptor";"Larva";394;2
"Unit";"Corruptor";"Larva";398;2
"Unit";"Corruptor";"Larva";398;2
"Building";"CreepTumor";NA;404;0
"Unit";"Corruptor";"Larva";436;2
"Unit";"Corruptor";"Larva";436;2
"Unit";"Corruptor";"Larva";436;2
"Unit";"Corruptor";"Larva";436;2
"Building";"CreepTumor";NA;444;0
"Building";"CreepTumor";NA;444;0
"Building";"SpineCrawler";NA;444;0
"Building";"SpineCrawler";NA;444;0
"Unit";"Overlord";"Larva";444;0
"Unit";"Overlord";"Larva";444;0
"Unit";"Hydralisk";"Larva";444;2
"Unit";"Hydralisk";"Larva";444;2
"Unit";"Hydralisk";"Larva";444;2
"Unit";"Hydralisk";"Larva";444;2
"Unit";"Hydralisk";"Larva";444;2
"Unit";"Hydralisk";"Larva";444;2
"Unit";"Hydralisk";"Larva";444;2
"Unit";"Hydralisk";"Larva";444;2
"Unit";"Hydralisk";"Larva";444;2
"Unit";"Hydralisk";"Larva";444;2
"Unit";"Hydralisk";"Larva";444;2
"Unit";"Hydralisk";"Larva";444;2
"Unit";"Hydralisk";"Larva";444;2
"Unit";"Hydralisk";"Larva";444;2
"Unit";"Hydralisk";"Larva";444;2
"Unit";"Hydralisk";"Larva";444;2
