"type";"unit_name";"on_building";"total_supply";"supply"
"Unit";"Overlord";"Larva";12;0
"Building";"Extractor";NA;17;0
"Building";"SpawningPool";NA;16;0
"Unit";"Zergling";"Larva";18;1
"Unit";"Zergling";"Larva";18;1
"Unit";"Zergling";"Larva";18;1
"Unit";"Zergling";"Larva";18;1
"Unit";"Zergling";"Larva";18;1
"Unit";"Zergling";"Larva";18;1
