"type";"unit_name";"on_building";"total_supply_lag";"supply"
"Unit";"Overlord";"Larva";13;0
"Building";"Hatchery";NA;16;0
"Building";"Extractor";NA;19;0
"Building";"SpawningPool";NA;19;0
"Unit";"Overlord";"Larva";23;0
"Unit";"Queen";"Hatchery";25;2
"Unit";"Queen";"Hatchery";29;2
"Unit";"Zergling";"Larva";31;1
"Unit";"Zergling";"Larva";32;1
"Unit";"Queen";"Hatchery";36;2
"Unit";"Overlord";"Larva";38;0
"Unit";"Overlord";"Larva";40;0
"Unit";"Queen";"Hatchery";40;2
"Building";"CreepTumorQueen";NA;47;0
"Building";"CreepTumorQueen";NA;51;0
"Building";"Extractor";NA;54;0
"Building";"Extractor";NA;54;0
"Building";"CreepTumor";NA;54;0
"Unit";"Overlord";"Larva";54;0
"Building";"Extractor";NA;55;0
"Building";"CreepTumor";NA;58;0
"Unit";"Overlord";"Larva";59;0
"Building";"CreepTumor";NA;61;0
"Building";"HydraliskDen";NA;64;0
"Building";"SporeCrawler";NA;64;0
"Building";"SporeCrawler";NA;65;0
"Building";"CreepTumor";NA;65;0
"Unit";"Overlord";"Larva";65;0
"Building";"CreepTumor";NA;65;0
"Building";"Hatchery";NA;66;0
"Unit";"Overlord";"Larva";66;0
"Unit";"Overlord";"Larva";66;0
"Building";"CreepTumorQueen";NA;66;0
"Unit";"Hydralisk";"Larva";67;2
"Unit";"Hydralisk";"Larva";69;2
"Unit";"Hydralisk";"Larva";71;2
"Building";"LurkerDenMP";NA;73;0
"Unit";"Hydralisk";"Larva";73;2
"Building";"CreepTumor";NA;75;0
"Building";"CreepTumor";NA;75;0
"Unit";"Hydralisk";"Larva";75;2
"Unit";"Hydralisk";"Larva";77;2
"Unit";"Hydralisk";"Larva";79;2
"Unit";"Hydralisk";"Larva";81;2
"Unit";"Overlord";"Larva";83;0
"Unit";"Hydralisk";"Larva";83;2
"Building";"CreepTumor";NA;85;0
"Unit";"Hydralisk";"Larva";85;2
"Building";"CreepTumor";NA;87;0
"Building";"CreepTumor";NA;87;0
"Unit";"Hydralisk";"Larva";87;2
"Unit";"Hydralisk";"Larva";89;2
"Unit";"Hydralisk";"Larva";91;2
"Unit";"Hydralisk";"Larva";93;2
"Unit";"Hydralisk";"Larva";95;2
"Unit";"Zergling";"Larva";97;1
"Unit";"Zergling";"Larva";98;1
"Unit";"Zergling";"Larva";99;1
"Unit";"Zergling";"Larva";100;1
"Unit";"Zergling";"Larva";101;1
"Unit";"Zergling";"Larva";102;1
"Unit";"Zergling";"Larva";103;1
"Unit";"Zergling";"Larva";104;1
"Building";"CreepTumor";NA;105;0
"Building";"CreepTumor";NA;105;0
"Unit";"Zergling";"Larva";105;1
"Unit";"Zergling";"Larva";106;1
"Unit";"Zergling";"Larva";107;1
"Unit";"Zergling";"Larva";108;1
"Unit";"Zergling";"Larva";109;1
"Unit";"Zergling";"Larva";110;1
"Unit";"Zergling";"Larva";111;1
"Unit";"Zergling";"Larva";112;1
"Unit";"Overlord";"Larva";113;0
"Unit";"Zergling";"Larva";113;1
"Unit";"Zergling";"Larva";114;1
"Unit";"Zergling";"Larva";115;1
"Unit";"Zergling";"Larva";116;1
"Unit";"Zergling";"Larva";117;1
"Unit";"Zergling";"Larva";118;1
"Unit";"Zergling";"Larva";119;1
"Unit";"Zergling";"Larva";120;1
"Unit";"Zergling";"Larva";121;1
"Unit";"Zergling";"Larva";122;1
"Unit";"Zergling";"Larva";123;1
"Unit";"Zergling";"Larva";124;1
"Unit";"Zergling";"Larva";125;1
"Unit";"Zergling";"Larva";126;1
"Unit";"Zergling";"Larva";127;1
"Unit";"Zergling";"Larva";128;1
"Unit";"Zergling";"Larva";129;1
"Unit";"Zergling";"Larva";130;1
"Unit";"Zergling";"Larva";131;1
"Unit";"Zergling";"Larva";132;1
"Unit";"Zergling";"Larva";133;1
"Unit";"Zergling";"Larva";134;1
"Unit";"Overlord";"Larva";135;0
"Unit";"Overlord";"Larva";135;0
"Unit";"Overlord";"Larva";135;0
"Unit";"Zergling";"Larva";135;1
"Unit";"Zergling";"Larva";136;1
"Unit";"Zergling";"Larva";137;1
"Unit";"Zergling";"Larva";138;1
"Unit";"Zergling";"Larva";139;1
"Unit";"Zergling";"Larva";140;1
"Unit";"Hydralisk";"Larva";141;2
"Unit";"Hydralisk";"Larva";143;2
"Unit";"Zergling";"Larva";145;1
"Unit";"Zergling";"Larva";146;1
"Unit";"Zergling";"Larva";147;1
"Unit";"Zergling";"Larva";148;1
"Unit";"Zergling";"Larva";149;1
"Unit";"Zergling";"Larva";150;1
"Unit";"Zergling";"Larva";151;1
"Unit";"Zergling";"Larva";152;1
"Unit";"Zergling";"Larva";153;1
"Unit";"Zergling";"Larva";154;1
"Unit";"Zergling";"Larva";155;1
"Unit";"Zergling";"Larva";156;1
"Unit";"Zergling";"Larva";157;1
"Unit";"Zergling";"Larva";158;1
"Unit";"Zergling";"Larva";159;1
"Unit";"Zergling";"Larva";160;1
"Unit";"Zergling";"Larva";161;1
"Unit";"Zergling";"Larva";162;1
"Unit";"Zergling";"Larva";163;1
"Unit";"Zergling";"Larva";164;1
"Unit";"Hydralisk";"Larva";165;2
"Unit";"Hydralisk";"Larva";167;2
"Unit";"Hydralisk";"Larva";169;2
"Unit";"Zergling";"Larva";171;1
"Unit";"Zergling";"Larva";172;1
"Unit";"Zergling";"Larva";173;1
"Unit";"Zergling";"Larva";174;1
"Unit";"Zergling";"Larva";175;1
"Unit";"Zergling";"Larva";176;1
"Unit";"Zergling";"Larva";177;1
"Unit";"Zergling";"Larva";178;1
"Unit";"Hydralisk";"Larva";179;2
"Unit";"Zergling";"Larva";181;1
"Unit";"Zergling";"Larva";182;1
"Unit";"Zergling";"Larva";183;1
"Unit";"Zergling";"Larva";184;1
"Unit";"Zergling";"Larva";185;1
"Unit";"Zergling";"Larva";186;1
"Unit";"Zergling";"Larva";187;1
"Unit";"Zergling";"Larva";188;1
"Unit";"Zergling";"Larva";189;1
"Unit";"Zergling";"Larva";190;1
"Unit";"Zergling";"Larva";191;1
"Unit";"Zergling";"Larva";192;1
"Unit";"Zergling";"Larva";193;1
"Unit";"Zergling";"Larva";194;1
"Unit";"Hydralisk";"Larva";195;2
"Unit";"Hydralisk";"Larva";197;2
"Unit";"Zergling";"Larva";199;1
"Unit";"Zergling";"Larva";200;1
"Unit";"Zergling";"Larva";201;1
"Unit";"Zergling";"Larva";202;1
"Unit";"Hydralisk";"Larva";203;2
"Unit";"Hydralisk";"Larva";205;2
"Unit";"Zergling";"Larva";207;1
"Unit";"Zergling";"Larva";208;1
"Unit";"Zergling";"Larva";209;1
"Unit";"Zergling";"Larva";210;1
"Unit";"Zergling";"Larva";211;1
"Unit";"Zergling";"Larva";212;1
"Unit";"Zergling";"Larva";213;1
"Unit";"Zergling";"Larva";214;1
"Unit";"Zergling";"Larva";215;1
"Unit";"Zergling";"Larva";216;1
"Unit";"Hydralisk";"Larva";217;2
"Unit";"Zergling";"Larva";219;1
"Unit";"Zergling";"Larva";220;1
"Unit";"Zergling";"Larva";221;1
"Unit";"Zergling";"Larva";222;1
"Unit";"Zergling";"Larva";223;1
"Unit";"Zergling";"Larva";224;1
"Unit";"Zergling";"Larva";225;1
"Unit";"Zergling";"Larva";226;1
"Unit";"Zergling";"Larva";227;1
"Unit";"Zergling";"Larva";228;1
"Unit";"Hydralisk";"Larva";229;2
"Unit";"Queen";"Hatchery";231;2
"Unit";"Hydralisk";"Larva";233;2
"Building";"EvolutionChamber";NA;235;0
"Unit";"Hydralisk";"Larva";235;2
"Building";"InfestationPit";NA;241;0
"Building";"CreepTumor";NA;245;0
"Building";"CreepTumor";NA;245;0
"Building";"Extractor";NA;250;0
"Building";"Hatchery";NA;250;0
"Building";"Extractor";NA;250;0
"Building";"CreepTumor";NA;254;0
"Building";"CreepTumor";NA;254;0
"Unit";"Overlord";"Larva";255;0
"Unit";"Overlord";"Larva";255;0
"Building";"Spire";NA;255;0
"Unit";"Overlord";"Larva";255;0
"Unit";"Overlord";"Larva";255;0
"Unit";"Overlord";"Larva";255;0
"Unit";"Overlord";"Larva";256;0
"Unit";"Overlord";"Larva";256;0
"Unit";"Overlord";"Larva";256;0
"Unit";"Overlord";"Larva";256;0
"Unit";"Hydralisk";"Larva";259;2
"Unit";"Hydralisk";"Larva";264;2
"Unit";"Hydralisk";"Larva";266;2
"Unit";"Hydralisk";"Larva";268;2
"Unit";"Hydralisk";"Larva";270;2
"Building";"Extractor";NA;272;0
"Building";"Extractor";NA;272;0
"Unit";"Queen";"Hatchery";279;2
"Unit";"Overlord";"Larva";281;0
"Unit";"Corruptor";"Larva";285;2
"Unit";"Hydralisk";"Larva";287;2
"Unit";"Hydralisk";"Larva";289;2
"Building";"CreepTumor";NA;291;0
"Unit";"Corruptor";"Larva";291;2
"Unit";"Corruptor";"Larva";293;2
"Unit";"Corruptor";"Larva";295;2
"Unit";"Corruptor";"Larva";297;2
"Unit";"Corruptor";"Larva";299;2
"Unit";"Corruptor";"Larva";301;2
"Unit";"Corruptor";"Larva";303;2
"Upgrade";"SprayZerg";NA;305;0
"Upgrade";"SprayZerg";NA;305;0
"Upgrade";"SprayZerg";NA;305;0
"Upgrade";"zerglingmovementspeed";NA;305;0
"Upgrade";"SprayZerg";NA;305;0
"Upgrade";"EvolveMuscularAugments";NA;305;0
"Upgrade";"SprayZerg";NA;305;0
"Upgrade";"SprayZerg";NA;305;0
"Upgrade";"ZergMissileWeaponsLevel1";NA;305;0
"Upgrade";"SprayZerg";NA;305;0
"Upgrade";"DiggingClaws";NA;305;0
"Upgrade";"overlordspeed";NA;305;0
