"type";"unit_name";"on_building";"total_supply";"supply"
"Unit";"Overlord";"Larva";13;0
"Building";"Extractor";NA;18;0
"Unit";"Overlord";"Larva";21;0
"Building";"SpawningPool";NA;20;0
"Building";"Hatchery";NA;17;0
"Unit";"Zergling";"Larva";22;1
"Unit";"Zergling";"Larva";22;1
"Unit";"Zergling";"Larva";22;1
"Unit";"Zergling";"Larva";22;1
"Unit";"Queen";"Hatchery";22;2
"Unit";"Queen";"Hatchery";22;2
"Unit";"Queen";"Hatchery";36;2
"Unit";"Overlord";"Larva";38;0
"Unit";"Overlord";"Larva";40;0
"Building";"CreepTumorQueen";NA;43;0
"Building";"Hatchery";NA;30;0
"Unit";"Zergling";"Larva";43;1
"Unit";"Zergling";"Larva";43;1
"Unit";"Zergling";"Larva";43;1
"Unit";"Zergling";"Larva";43;1
"Unit";"Zergling";"Larva";43;1
"Unit";"Zergling";"Larva";43;1
"Unit";"Zergling";"Larva";43;1
"Unit";"Zergling";"Larva";43;1
"Unit";"Zergling";"Larva";43;1
"Unit";"Zergling";"Larva";43;1
"Unit";"Zergling";"Larva";51;1
"Unit";"Zergling";"Larva";51;1
"Unit";"Zergling";"Larva";51;1
"Unit";"Zergling";"Larva";51;1
"Unit";"Queen";"Hatchery";51;2
"Building";"CreepTumor";NA;67;0
"Building";"SporeCrawler";NA;67;0
"Building";"SporeCrawler";NA;67;0
"Building";"RoachWarren";NA;62;0
"Unit";"Overlord";"Larva";72;0
"Unit";"Queen";"Hatchery";69;2
"Unit";"Overlord";"Larva";72;0
"Building";"CreepTumor";NA;72;0
"Building";"Extractor";NA;72;0
"Building";"Extractor";NA;72;0
"Building";"HydraliskDen";NA;72;0
"Unit";"Overlord";"Larva";73;0
"Unit";"Overlord";"Larva";73;0
"Building";"CreepTumorQueen";NA;78;0
"Building";"CreepTumor";NA;78;0
"Unit";"Queen";"Hatchery";73;2
"Building";"Extractor";NA;89;0
"Building";"Extractor";NA;91;0
"Building";"CreepTumor";NA;96;0
"Building";"CreepTumor";NA;96;0
"Unit";"Hydralisk";"Larva";96;2
"Unit";"Hydralisk";"Larva";96;2
"Unit";"Hydralisk";"Larva";96;2
"Building";"EvolutionChamber";NA;96;0
"Upgrade";"EvolveGroovedSpines";"HydraliskDen";96;0
"Unit";"Hydralisk";"Larva";110;2
"Unit";"Hydralisk";"Larva";110;2
"Unit";"Hydralisk";"Larva";110;2
"Unit";"Hydralisk";"Larva";110;2
"Unit";"Hydralisk";"Larva";110;2
"Unit";"Zergling";"Larva";110;1
"Unit";"Zergling";"Larva";110;1
"Unit";"Roach";"Larva";110;2
"Unit";"Roach";"Larva";110;2
"Unit";"Roach";"Larva";110;2
"Unit";"Roach";"Larva";110;2
"Unit";"Overlord";"Larva";120;0
"Unit";"Overlord";"Larva";120;0
"Unit";"Overlord";"Larva";130;0
"Unit";"Overlord";"Larva";130;0
"Building";"Extractor";NA;122;0
"Building";"Hatchery";NA;101;0
"Building";"CreepTumor";NA;130;0
"Unit";"Hydralisk";"Larva";130;2
"Unit";"Hydralisk";"Larva";130;2
"Building";"CreepTumorQueen";NA;134;0
"Building";"CreepTumorQueen";NA;134;0
"Building";"InfestationPit";NA;130;0
"Building";"CreepTumor";NA;156;0
"Building";"CreepTumor";NA;158;0
"Building";"BanelingNest";NA;133;0
"Building";"CreepTumorQueen";NA;160;0
"Upgrade";"ZergMissileWeaponsLevel1";"EvolutionChamber";120;0
"Unit";"Zergling";"Larva";160;1
"Unit";"Zergling";"Larva";160;1
"Unit";"Zergling";"Larva";160;1
"Unit";"Zergling";"Larva";160;1
"Unit";"Zergling";"Larva";160;1
"Unit";"Zergling";"Larva";160;1
"Unit";"Zergling";"Larva";160;1
"Unit";"Zergling";"Larva";160;1
"Unit";"Zergling";"Larva";160;1
"Unit";"Zergling";"Larva";160;1
"Unit";"Zergling";"Larva";160;1
"Unit";"Zergling";"Larva";160;1
"Unit";"Zergling";"Larva";160;1
"Unit";"Zergling";"Larva";160;1
"Unit";"Zergling";"Larva";160;1
"Unit";"Zergling";"Larva";160;1
"Unit";"Zergling";"Larva";160;1
"Unit";"Zergling";"Larva";160;1
"Unit";"Zergling";"Larva";160;1
"Unit";"Zergling";"Larva";160;1
"Unit";"Zergling";"Larva";160;1
"Unit";"Zergling";"Larva";160;1
"Building";"SporeCrawler";NA;164;0
"Unit";"Overlord";"Larva";186;0
"Unit";"Overlord";"Larva";186;0
"Unit";"Overlord";"Larva";186;0
"Building";"Extractor";NA;186;0
"Building";"Extractor";NA;186;0
"Building";"Hatchery";NA;147;0
"Unit";"Hydralisk";"Larva";186;2
"Unit";"Overlord";"Larva";187;0
"Unit";"Overlord";"Larva";187;0
"Unit";"Overlord";"Larva";187;0
"Unit";"Zergling";"Larva";190;1
"Unit";"Zergling";"Larva";190;1
"Unit";"Zergling";"Larva";190;1
"Unit";"Zergling";"Larva";190;1
"Unit";"Zergling";"Larva";190;1
"Unit";"Zergling";"Larva";190;1
"Unit";"Zergling";"Larva";190;1
"Unit";"Zergling";"Larva";190;1
"Unit";"Zergling";"Larva";190;1
"Unit";"Zergling";"Larva";190;1
"Unit";"Zergling";"Larva";190;1
"Unit";"Zergling";"Larva";190;1
"Unit";"Zergling";"Larva";190;1
"Unit";"Zergling";"Larva";190;1
"Unit";"Zergling";"Larva";190;1
"Unit";"Zergling";"Larva";190;1
"Unit";"Zergling";"Larva";190;1
"Unit";"Zergling";"Larva";190;1
"Building";"EvolutionChamber";NA;187;0
"Unit";"Hydralisk";"Larva";188;2
"Unit";"Hydralisk";"Larva";188;2
"Unit";"Hydralisk";"Larva";188;2
"Unit";"Hydralisk";"Larva";188;2
"Upgrade";"EvolveMuscularAugments";"HydraliskDen";186;0
"Unit";"Hydralisk";"Larva";190;2
"Unit";"Hydralisk";"Larva";190;2
"Unit";"Hydralisk";"Larva";191;2
"Unit";"Hydralisk";"Larva";191;2
"Unit";"Hydralisk";"Larva";191;2
"Unit";"Hydralisk";"Larva";191;2
"Unit";"Hydralisk";"Larva";191;2
"Building";"Spire";NA;186;0
"Unit";"Baneling";"Zergling";231;0
"Building";"CreepTumor";NA;231;0
"Unit";"Baneling";"Zergling";231;0
"Unit";"Baneling";"Zergling";231;0
"Unit";"Baneling";"Zergling";231;0
"Unit";"Baneling";"Zergling";231;0
"Unit";"Baneling";"Zergling";231;0
"Unit";"Baneling";"Zergling";231;0
"Unit";"Baneling";"Zergling";231;0
"Unit";"Baneling";"Zergling";231;0
"Unit";"Baneling";"Zergling";231;0
"Unit";"Baneling";"Zergling";231;0
"Unit";"Baneling";"Zergling";231;0
"Building";"CreepTumor";NA;252;0
"Building";"CreepTumorQueen";NA;252;0
"Building";"CreepTumorQueen";NA;252;0
"Building";"CreepTumorQueen";NA;252;0
"Unit";"Hydralisk";"Larva";252;2
"Unit";"Hydralisk";"Larva";252;2
"Unit";"Hydralisk";"Larva";252;2
"Unit";"Hydralisk";"Larva";252;2
"Unit";"Hydralisk";"Larva";252;2
"Building";"CreepTumor";NA;252;0
"Building";"CreepTumorQueen";NA;262;0
"Building";"CreepTumorQueen";NA;262;0
"Building";"CreepTumorQueen";NA;262;0
"Unit";"Corruptor";"Larva";252;2
"Unit";"Corruptor";"Larva";252;2
"Unit";"Corruptor";"Larva";252;2
"Unit";"Corruptor";"Larva";252;2
"Unit";"Corruptor";"Larva";252;2
"Upgrade";"ZergMissileWeaponsLevel2";"EvolutionChamber";221;0
"Building";"CreepTumor";NA;262;0
"Building";"CreepTumor";NA;262;0
"Building";"CreepTumor";NA;262;0
"Building";"CreepTumor";NA;262;0
"Building";"CreepTumor";NA;262;0
"Building";"CreepTumor";NA;262;0
"Building";"CreepTumor";NA;262;0
"Unit";"Corruptor";"Larva";262;2
"Unit";"Corruptor";"Larva";262;2
"Building";"Extractor";NA;272;0
"Building";"Extractor";NA;274;0
"Building";"Hatchery";NA;262;0
"Unit";"Overlord";"Larva";276;0
"Unit";"Overlord";"Larva";276;0
"Unit";"Overlord";"Larva";276;0
"Unit";"Overlord";"Larva";276;0
"Unit";"Overlord";"Larva";276;0
"Unit";"Overlord";"Larva";276;0
"Unit";"Overlord";"Larva";276;0
"Unit";"Overlord";"Larva";276;0
"Unit";"Overlord";"Larva";276;0
"Unit";"Overlord";"Larva";276;0
"Unit";"Corruptor";"Larva";276;2
"Unit";"Overlord";"Larva";278;0
"Unit";"Corruptor";"Larva";278;2
"Unit";"Corruptor";"Larva";278;2
"Unit";"Overlord";"Larva";278;0
"Unit";"Corruptor";"Larva";278;2
"Unit";"Corruptor";"Larva";278;2
"Unit";"Corruptor";"Larva";278;2
"Unit";"Corruptor";"Larva";278;2
"Building";"CreepTumor";NA;278;0
"Building";"CreepTumor";NA;278;0
"Building";"CreepTumor";NA;278;0
"Building";"CreepTumor";NA;278;0
"Building";"CreepTumor";NA;278;0
"Building";"CreepTumor";NA;278;0
"Building";"SporeCrawler";NA;282;0
"Building";"SporeCrawler";NA;282;0
"Building";"Hatchery";NA;278;0
"Building";"SpineCrawler";NA;290;0
"Building";"SpineCrawler";NA;290;0
"Building";"SpineCrawler";NA;290;0
"Building";"SpineCrawler";NA;290;0
"Building";"SpineCrawler";NA;290;0
"Building";"SpineCrawler";NA;290;0
"Building";"CreepTumor";NA;308;0
"Building";"CreepTumor";NA;308;0
"Building";"CreepTumor";NA;308;0
"Building";"SporeCrawler";NA;308;0
"Building";"CreepTumor";NA;310;0
"Building";"CreepTumor";NA;310;0
"Unit";"Corruptor";"Larva";308;2
"Unit";"Corruptor";"Larva";308;2
"Building";"Extractor";NA;310;0
"Building";"SpineCrawler";NA;310;0
"Building";"SpineCrawler";NA;310;0
"Building";"SpineCrawler";NA;310;0
"Building";"SpineCrawler";NA;310;0
"Building";"SpineCrawler";NA;310;0
"Building";"SpineCrawler";NA;310;0
"Building";"CreepTumor";NA;314;0
"Unit";"Corruptor";"Larva";314;2
"Unit";"Corruptor";"Larva";314;2
"Unit";"Corruptor";"Larva";314;2
"Unit";"Corruptor";"Larva";314;2
"Unit";"Corruptor";"Larva";314;2
"Building";"Hatchery";NA;310;0
"Unit";"Corruptor";"Larva";324;2
"Unit";"Corruptor";"Larva";324;2
"Building";"CreepTumor";NA;328;0
"Unit";"Viper";"Larva";328;3
"Unit";"Viper";"Larva";328;3
"Unit";"Viper";"Larva";328;3
"Unit";"Viper";"Larva";328;3
"Building";"CreepTumor";NA;340;0
"Unit";"Corruptor";"Larva";328;2
"Unit";"Corruptor";"Larva";328;2
"Unit";"Corruptor";"Larva";328;2
"Unit";"Corruptor";"Larva";328;2
"Unit";"Corruptor";"Larva";328;2
"Unit";"Corruptor";"Larva";328;2
"Unit";"Corruptor";"Larva";328;2
"Unit";"Corruptor";"Larva";328;2
"Unit";"Corruptor";"Larva";340;2
"Unit";"Corruptor";"Larva";340;2
"Unit";"Corruptor";"Larva";340;2
"Building";"SporeCrawler";NA;340;0
"Building";"SpineCrawler";NA;340;0
"Building";"SpineCrawler";NA;340;0
"Building";"SporeCrawler";NA;340;0
"Building";"SpineCrawler";NA;340;0
"Building";"SporeCrawler";NA;340;0
"Building";"SpineCrawler";NA;340;0
"Building";"SpineCrawler";NA;340;0
"Unit";"Corruptor";"Larva";340;2
"Building";"CreepTumorQueen";NA;362;0
"Building";"CreepTumorQueen";NA;362;0
"Building";"CreepTumorQueen";NA;364;0
"Building";"CreepTumorQueen";NA;364;0
"Building";"CreepTumor";NA;364;0
"Building";"CreepTumor";NA;364;0
"Building";"Extractor";NA;364;0
"Unit";"Corruptor";"Larva";364;2
"Unit";"Corruptor";"Larva";364;2
"Unit";"Corruptor";"Larva";364;2
"Unit";"Corruptor";"Larva";364;2
"Unit";"Corruptor";"Larva";364;2
"Unit";"Corruptor";"Larva";364;2
"Unit";"Corruptor";"Larva";364;2
"Building";"CreepTumor";NA;364;0
"Unit";"Corruptor";"Larva";364;2
"Unit";"Corruptor";"Larva";364;2
"Unit";"Corruptor";"Larva";364;2
"Unit";"Corruptor";"Larva";364;2
"Unit";"Corruptor";"Larva";364;2
"Unit";"Corruptor";"Larva";364;2
"Unit";"Corruptor";"Larva";364;2
"Building";"CreepTumor";NA;378;0
"Building";"CreepTumor";NA;378;0
"Building";"SporeCrawler";NA;378;0
"Building";"SporeCrawler";NA;378;0
"Building";"SporeCrawler";NA;378;0
"Building";"SporeCrawler";NA;378;0
"Building";"SporeCrawler";NA;378;0
"Building";"Hatchery";NA;364;0
"Building";"CreepTumor";NA;392;0
"Unit";"Viper";"Larva";392;3
"Unit";"Viper";"Larva";392;3
"Unit";"Viper";"Larva";392;3
"Unit";"Viper";"Larva";392;3
"Building";"CreepTumor";NA;392;0
"Building";"CreepTumor";NA;398;0
"Building";"CreepTumor";NA;401;0
"Upgrade";"ZergMissileWeaponsLevel3";"EvolutionChamber";364;0
"Unit";"Corruptor";"Larva";392;2
"Unit";"Corruptor";"Larva";392;2
"Unit";"Corruptor";"Larva";392;2
"Unit";"Corruptor";"Larva";392;2
"Unit";"Corruptor";"Larva";392;2
"Unit";"Corruptor";"Larva";392;2
"Unit";"Corruptor";"Larva";392;2
"Unit";"Corruptor";"Larva";392;2
"Building";"CreepTumor";NA;404;0
"Building";"CreepTumor";NA;404;0
"Building";"CreepTumor";NA;404;0
"Building";"CreepTumor";NA;404;0
"Building";"CreepTumorQueen";NA;420;0
"Building";"SporeCrawler";NA;420;0
"Building";"SporeCrawler";NA;420;0
"Building";"SporeCrawler";NA;420;0
"Building";"SporeCrawler";NA;420;0
"Building";"SporeCrawler";NA;420;0
"Building";"SporeCrawler";NA;420;0
"Building";"EvolutionChamber";NA;420;0
"Building";"CreepTumorQueen";NA;423;0
"Building";"CreepTumorQueen";NA;423;0
"Building";"CreepTumorQueen";NA;423;0
"Unit";"Viper";"Larva";420;3
"Unit";"Viper";"Larva";420;3
"Unit";"Viper";"Larva";420;3
"Unit";"Viper";"Larva";420;3
"Unit";"Viper";"Larva";420;3
"Building";"CreepTumor";NA;423;0
"Building";"CreepTumorQueen";NA;423;0
"Building";"CreepTumor";NA;423;0
"Building";"CreepTumor";NA;423;0
"Building";"CreepTumor";NA;423;0
"Building";"CreepTumor";NA;438;0
"Building";"CreepTumor";NA;438;0
"Building";"CreepTumor";NA;438;0
"Building";"CreepTumor";NA;438;0
"Building";"CreepTumor";NA;438;0
"Building";"CreepTumor";NA;438;0
"Building";"CreepTumor";NA;438;0
"Building";"Extractor";NA;438;0
"Building";"Extractor";NA;438;0
"Building";"CreepTumor";NA;448;0
"Building";"CreepTumor";NA;448;0
"Building";"CreepTumor";NA;448;0
"Building";"SporeCrawler";NA;448;0
"Building";"SpineCrawler";NA;438;0
"Building";"SpineCrawler";NA;438;0
"Building";"SpineCrawler";NA;438;0
"Building";"SpineCrawler";NA;438;0
"Building";"SpineCrawler";NA;446;0
"Building";"SpineCrawler";NA;448;0
"Building";"Hatchery";NA;438;0
"Building";"CreepTumor";NA;448;0
"Building";"CreepTumor";NA;448;0
"Building";"SporeCrawler";NA;448;0
"Building";"SporeCrawler";NA;448;0
"Building";"SporeCrawler";NA;448;0
"Building";"SporeCrawler";NA;448;0
"Building";"SporeCrawler";NA;448;0
"Building";"SporeCrawler";NA;448;0
"Building";"SporeCrawler";NA;461;0
"Building";"SporeCrawler";NA;461;0
"Building";"SporeCrawler";NA;461;0
"Building";"CreepTumor";NA;461;0
"Unit";"Corruptor";"Larva";461;2
"Unit";"Corruptor";"Larva";461;2
"Unit";"Corruptor";"Larva";461;2
"Unit";"Corruptor";"Larva";461;2
"Unit";"Corruptor";"Larva";461;2
"Unit";"Corruptor";"Larva";461;2
"Unit";"Corruptor";"Larva";461;2
"Unit";"Corruptor";"Larva";461;2
"Unit";"Corruptor";"Larva";461;2
"Unit";"Corruptor";"Larva";461;2
"Unit";"Corruptor";"Larva";461;2
"Unit";"Corruptor";"Larva";461;2
"Unit";"Corruptor";"Larva";461;2
"Unit";"Corruptor";"Larva";461;2
"Unit";"Corruptor";"Larva";461;2
"Building";"CreepTumor";NA;461;0
"Building";"CreepTumor";NA;463;0
"Upgrade";"ZergGroundArmorsLevel1";"EvolutionChamber";448;0
"Unit";"Hydralisk";"Larva";461;2
"Unit";"Hydralisk";"Larva";461;2
"Upgrade";"ZergMeleeWeaponsLevel1";"EvolutionChamber";448;0
"Unit";"Hydralisk";"Larva";461;2
"Unit";"Hydralisk";"Larva";461;2
"Unit";"Hydralisk";"Larva";461;2
"Unit";"Corruptor";"Larva";461;2
"Building";"CreepTumorQueen";NA;491;0
"Building";"CreepTumorQueen";NA;491;0
"Building";"CreepTumor";NA;491;0
"Building";"CreepTumorQueen";NA;491;0
"Building";"CreepTumorQueen";NA;503;0
"Building";"SpineCrawler";NA;501;0
