"type";"unit_name";"on_building";"total_supply_lag";"supply"
"Unit";"Overlord";"Larva";13;0
"Building";"Hatchery";NA;16;0
"Building";"Extractor";NA;19;0
"Building";"SpawningPool";NA;19;0
"Unit";"Overlord";"Larva";22;0
"Unit";"Queen";"Hatchery";23;2
"Unit";"Queen";"Hatchery";25;2
"Unit";"Zergling";"Larva";27;1
"Unit";"Zergling";"Larva";28;1
"Building";"Hatchery";NA;36;0
"Building";"CreepTumorQueen";NA;36;0
"Unit";"Zergling";"Larva";36;1
"Unit";"Zergling";"Larva";37;1
"Unit";"Queen";"Hatchery";38;2
"Unit";"Overlord";"Larva";40;0
"Building";"CreepTumor";NA;42;0
"Building";"CreepTumorQueen";NA;42;0
"Unit";"Zergling";"Larva";44;1
"Unit";"Zergling";"Larva";45;1
"Unit";"Overlord";"Larva";49;0
"Unit";"Overlord";"Larva";49;0
"Unit";"Queen";"Hatchery";49;2
"Building";"CreepTumor";NA;51;0
"Building";"CreepTumor";NA;51;0
"Unit";"Overlord";"Larva";51;0
"Building";"CreepTumorQueen";NA;56;0
"Building";"SporeCrawler";NA;57;0
"Building";"SporeCrawler";NA;57;0
"Unit";"Zergling";"Larva";59;1
"Unit";"Zergling";"Larva";60;1
"Unit";"Zergling";"Larva";61;1
"Unit";"Zergling";"Larva";62;1
"Building";"CreepTumor";NA;64;0
"Building";"SporeCrawler";NA;66;0
"Unit";"Overlord";"Larva";66;0
"Unit";"Zergling";"Larva";66;1
"Unit";"Zergling";"Larva";67;1
"Building";"BanelingNest";NA;68;0
"Unit";"Queen";"Hatchery";73;2
"Building";"Extractor";NA;77;0
"Building";"Extractor";NA;77;0
"Unit";"Zergling";"Larva";77;1
"Unit";"Zergling";"Larva";78;1
"Unit";"Zergling";"Larva";79;1
"Unit";"Zergling";"Larva";80;1
"Unit";"Zergling";"Larva";81;1
"Unit";"Zergling";"Larva";82;1
"Building";"CreepTumor";NA;85;0
"Building";"CreepTumor";NA;85;0
"Building";"CreepTumor";NA;85;0
"Building";"HydraliskDen";NA;85;0
"Unit";"Overlord";"Larva";85;0
"Unit";"Overlord";"Larva";90;0
"Building";"Extractor";NA;93;0
"Unit";"Overlord";"Larva";93;0
"Unit";"Zergling";"Larva";96;1
"Unit";"Zergling";"Larva";97;1
"Unit";"Zergling";"Larva";98;1
"Unit";"Zergling";"Larva";99;1
"Unit";"Zergling";"Larva";100;1
"Unit";"Zergling";"Larva";101;1
"Unit";"Zergling";"Larva";102;1
"Unit";"Zergling";"Larva";103;1
"Building";"CreepTumor";NA;104;0
"Building";"CreepTumorQueen";NA;104;0
"Building";"CreepTumorQueen";NA;104;0
"Unit";"Hydralisk";"Larva";104;2
"Unit";"Hydralisk";"Larva";106;2
"Unit";"Hydralisk";"Larva";108;2
"Unit";"Hydralisk";"Larva";110;2
"Building";"Extractor";NA;112;0
"Building";"CreepTumor";NA;112;0
"Building";"CreepTumor";NA;112;0
"Unit";"Hydralisk";"Larva";112;2
"Unit";"Zergling";"Larva";114;1
"Unit";"Zergling";"Larva";115;1
"Unit";"Zergling";"Larva";116;1
"Unit";"Zergling";"Larva";117;1
"Unit";"Zergling";"Larva";118;1
"Unit";"Zergling";"Larva";119;1
"Unit";"Overlord";"Larva";124;0
"Unit";"Overlord";"Larva";124;0
"Building";"EvolutionChamber";NA;124;0
"Building";"CreepTumor";NA;124;0
"Building";"CreepTumor";NA;124;0
"Building";"CreepTumor";NA;124;0
"Unit";"Hydralisk";"Larva";127;2
"Building";"CreepTumor";NA;132;0
"Building";"CreepTumor";NA;132;0
"Building";"Extractor";NA;132;0
"Building";"Hatchery";NA;138;0
"Building";"InfestationPit";NA;139;0
"Building";"CreepTumorQueen";NA;139;0
"Building";"CreepTumor";NA;139;0
"Unit";"Hydralisk";"Larva";139;2
"Unit";"Hydralisk";"Larva";141;2
"Unit";"Hydralisk";"Larva";143;2
"Building";"CreepTumor";NA;145;0
"Building";"CreepTumorQueen";NA;145;0
"Building";"CreepTumor";NA;145;0
"Building";"CreepTumorQueen";NA;145;0
"Building";"CreepTumor";NA;145;0
"Building";"CreepTumor";NA;145;0
"Building";"CreepTumorQueen";NA;145;0
"Building";"CreepTumorQueen";NA;145;0
"Building";"CreepTumorQueen";NA;145;0
"Unit";"Overlord";"Larva";145;0
"Unit";"Overlord";"Larva";145;0
"Unit";"Overlord";"Larva";154;0
"Building";"CreepTumorQueen";NA;154;0
"Building";"CreepTumor";NA;154;0
"Unit";"Overlord";"Larva";154;0
"Unit";"Overlord";"Larva";154;0
"Unit";"Overlord";"Larva";154;0
"Building";"Spire";NA;157;0
"Unit";"Overlord";"Larva";157;0
"Unit";"Overlord";"Larva";157;0
"Unit";"Hydralisk";"Larva";157;2
"Unit";"Hydralisk";"Larva";159;2
"Building";"CreepTumor";NA;165;0
"Building";"CreepTumor";NA;165;0
"Building";"CreepTumor";NA;165;0
"Building";"CreepTumor";NA;165;0
"Building";"CreepTumor";NA;165;0
"Building";"CreepTumor";NA;165;0
"Building";"CreepTumor";NA;165;0
"Building";"CreepTumor";NA;165;0
"Building";"CreepTumor";NA;165;0
"Unit";"Hydralisk";"Larva";165;2
"Unit";"Hydralisk";"Larva";167;2
"Building";"CreepTumor";NA;169;0
"Building";"CreepTumorQueen";NA;169;0
"Building";"CreepTumorQueen";NA;169;0
"Unit";"Hydralisk";"Larva";169;2
"Unit";"Hydralisk";"Larva";171;2
"Unit";"Hydralisk";"Larva";173;2
"Unit";"Zergling";"Larva";175;1
"Unit";"Zergling";"Larva";176;1
"Unit";"Zergling";"Larva";177;1
"Unit";"Zergling";"Larva";178;1
"Unit";"Zergling";"Larva";179;1
"Unit";"Zergling";"Larva";180;1
"Unit";"Zergling";"Larva";181;1
"Unit";"Zergling";"Larva";182;1
"Unit";"Zergling";"Larva";183;1
"Unit";"Zergling";"Larva";184;1
"Unit";"Zergling";"Larva";185;1
"Unit";"Zergling";"Larva";186;1
"Unit";"Zergling";"Larva";187;1
"Unit";"Zergling";"Larva";188;1
"Building";"Hatchery";NA;193;0
"Building";"CreepTumor";NA;193;0
"Building";"CreepTumor";NA;193;0
"Building";"CreepTumor";NA;193;0
"Building";"CreepTumor";NA;193;0
"Building";"CreepTumor";NA;193;0
"Building";"CreepTumor";NA;193;0
"Building";"CreepTumor";NA;193;0
"Building";"CreepTumor";NA;193;0
"Building";"CreepTumor";NA;193;0
"Unit";"Zergling";"Larva";193;1
"Unit";"Zergling";"Larva";194;1
"Unit";"Zergling";"Larva";195;1
"Unit";"Zergling";"Larva";196;1
"Unit";"Zergling";"Larva";197;1
"Unit";"Zergling";"Larva";198;1
"Unit";"Zergling";"Larva";199;1
"Unit";"Zergling";"Larva";200;1
"Unit";"Zergling";"Larva";201;1
"Unit";"Zergling";"Larva";202;1
"Building";"CreepTumor";NA;203;0
"Building";"CreepTumor";NA;203;0
"Unit";"Overlord";"Larva";203;0
"Unit";"Hydralisk";"Larva";213;2
"Unit";"Hydralisk";"Larva";215;2
"Unit";"Zergling";"Larva";217;1
"Unit";"Zergling";"Larva";218;1
"Unit";"Zergling";"Larva";219;1
"Unit";"Zergling";"Larva";220;1
"Unit";"Zergling";"Larva";221;1
"Unit";"Zergling";"Larva";222;1
"Unit";"Zergling";"Larva";223;1
"Unit";"Zergling";"Larva";224;1
"Unit";"Zergling";"Larva";225;1
"Unit";"Zergling";"Larva";226;1
"Unit";"Zergling";"Larva";227;1
"Unit";"Zergling";"Larva";228;1
"Building";"CreepTumor";NA;229;0
"Building";"CreepTumor";NA;229;0
"Building";"CreepTumor";NA;229;0
"Building";"CreepTumor";NA;229;0
"Building";"CreepTumor";NA;229;0
"Unit";"Overlord";"Larva";229;0
"Unit";"Baneling";"Zergling";229;0
"Unit";"Baneling";"Zergling";229;0
"Unit";"Baneling";"Zergling";229;0
"Unit";"Baneling";"Zergling";229;0
"Unit";"Baneling";"Zergling";229;0
"Unit";"Baneling";"Zergling";229;0
"Unit";"Baneling";"Zergling";229;0
"Unit";"Baneling";"Zergling";229;0
"Unit";"Baneling";"Zergling";229;0
"Unit";"Baneling";"Zergling";229;0
"Unit";"Baneling";"Zergling";229;0
"Unit";"Baneling";"Zergling";229;0
"Unit";"Baneling";"Zergling";229;0
"Unit";"Baneling";"Zergling";229;0
"Unit";"Baneling";"Zergling";229;0
"Unit";"Baneling";"Zergling";229;0
"Unit";"Baneling";"Zergling";229;0
"Building";"Extractor";NA;232;0
"Building";"CreepTumor";NA;232;0
"Building";"CreepTumor";NA;232;0
"Building";"CreepTumor";NA;232;0
"Building";"CreepTumor";NA;232;0
"Building";"CreepTumor";NA;232;0
"Building";"CreepTumor";NA;232;0
"Building";"CreepTumor";NA;232;0
"Unit";"Corruptor";"Larva";232;2
"Unit";"Corruptor";"Larva";234;2
"Unit";"Corruptor";"Larva";236;2
"Unit";"Corruptor";"Larva";238;2
"Unit";"Corruptor";"Larva";240;2
"Unit";"Corruptor";"Larva";242;2
"Unit";"Corruptor";"Larva";244;2
"Building";"SpineCrawler";NA;246;0
"Building";"Extractor";NA;249;0
"Building";"SporeCrawler";NA;249;0
"Building";"SpineCrawler";NA;249;0
"Building";"SpineCrawler";NA;249;0
"Building";"SporeCrawler";NA;254;0
"Unit";"Zergling";"Larva";254;1
"Unit";"Zergling";"Larva";255;1
"Unit";"Zergling";"Larva";256;1
"Unit";"Zergling";"Larva";257;1
"Unit";"Zergling";"Larva";258;1
"Unit";"Zergling";"Larva";259;1
"Unit";"Zergling";"Larva";260;1
"Unit";"Zergling";"Larva";261;1
"Unit";"Zergling";"Larva";262;1
"Unit";"Zergling";"Larva";263;1
"Unit";"Zergling";"Larva";264;1
"Unit";"Zergling";"Larva";265;1
"Unit";"Zergling";"Larva";266;1
"Unit";"Zergling";"Larva";267;1
"Unit";"Zergling";"Larva";268;1
"Unit";"Zergling";"Larva";269;1
"Unit";"Zergling";"Larva";270;1
"Unit";"Zergling";"Larva";271;1
"Unit";"Zergling";"Larva";272;1
"Unit";"Zergling";"Larva";273;1
"Unit";"Zergling";"Larva";274;1
"Unit";"Zergling";"Larva";275;1
"Unit";"Zergling";"Larva";276;1
"Unit";"Zergling";"Larva";277;1
"Unit";"Zergling";"Larva";278;1
"Unit";"Zergling";"Larva";279;1
"Unit";"Zergling";"Larva";280;1
"Unit";"Zergling";"Larva";281;1
"Unit";"Zergling";"Larva";282;1
"Unit";"Zergling";"Larva";283;1
"Unit";"Zergling";"Larva";284;1
"Unit";"Zergling";"Larva";285;1
"Unit";"Zergling";"Larva";286;1
"Unit";"Zergling";"Larva";287;1
"Unit";"Overlord";"Larva";288;0
"Unit";"Corruptor";"Larva";292;2
"Unit";"Corruptor";"Larva";294;2
"Unit";"Corruptor";"Larva";296;2
"Unit";"Corruptor";"Larva";298;2
"Building";"CreepTumor";NA;300;0
"Unit";"Corruptor";"Larva";300;2
"Unit";"Corruptor";"Larva";302;2
"Unit";"Corruptor";"Larva";304;2
"Building";"Hatchery";NA;306;0
"Unit";"Zergling";"Larva";306;1
"Unit";"Zergling";"Larva";307;1
"Unit";"Zergling";"Larva";308;1
"Unit";"Zergling";"Larva";309;1
"Unit";"Zergling";"Larva";310;1
"Unit";"Zergling";"Larva";311;1
"Unit";"Zergling";"Larva";312;1
"Unit";"Zergling";"Larva";313;1
"Unit";"Zergling";"Larva";314;1
"Unit";"Zergling";"Larva";315;1
"Unit";"Zergling";"Larva";316;1
"Unit";"Zergling";"Larva";317;1
"Unit";"Zergling";"Larva";318;1
"Unit";"Zergling";"Larva";319;1
"Unit";"Zergling";"Larva";320;1
"Unit";"Zergling";"Larva";321;1
"Unit";"Zergling";"Larva";322;1
"Unit";"Zergling";"Larva";323;1
"Unit";"Zergling";"Larva";324;1
"Unit";"Zergling";"Larva";325;1
"Unit";"Zergling";"Larva";326;1
"Unit";"Zergling";"Larva";327;1
"Unit";"Zergling";"Larva";328;1
"Unit";"Zergling";"Larva";329;1
"Unit";"Zergling";"Larva";330;1
"Unit";"Zergling";"Larva";331;1
"Unit";"Zergling";"Larva";332;1
"Unit";"Zergling";"Larva";333;1
"Unit";"Zergling";"Larva";334;1
"Unit";"Zergling";"Larva";335;1
"Building";"Spire";NA;336;0
"Building";"Extractor";NA;339;0
"Unit";"Corruptor";"Larva";339;2
"Unit";"Corruptor";"Larva";341;2
"Building";"SporeCrawler";NA;343;0
"Building";"SporeCrawler";NA;343;0
"Unit";"Corruptor";"Larva";343;2
"Building";"SporeCrawler";NA;345;0
"Unit";"Corruptor";"Larva";345;2
"Building";"SporeCrawler";NA;347;0
"Building";"SporeCrawler";NA;347;0
"Building";"SporeCrawler";NA;347;0
"Building";"CreepTumor";NA;353;0
"Building";"Extractor";NA;353;0
"Unit";"Overlord";"Larva";354;0
"Unit";"Overlord";"Larva";354;0
"Unit";"Overlord";"Larva";354;0
"Building";"EvolutionChamber";NA;354;0
"Building";"CreepTumor";NA;354;0
"Building";"CreepTumor";NA;354;0
"Building";"CreepTumor";NA;354;0
"Building";"CreepTumor";NA;354;0
"Building";"CreepTumor";NA;354;0
"Building";"CreepTumor";NA;357;0
"Building";"CreepTumor";NA;357;0
"Unit";"Infestor";"Larva";359;2
"Upgrade";"NeuralParasite";"InfestationPit";361;0
"Building";"SporeCrawler";NA;361;0
"Building";"SporeCrawler";NA;361;0
"Building";"SporeCrawler";NA;361;0
"Building";"SporeCrawler";NA;361;0
"Building";"SporeCrawler";NA;361;0
"Unit";"Infestor";"Larva";361;2
"Unit";"Infestor";"Larva";363;2
"Unit";"Infestor";"Larva";365;2
"Unit";"Infestor";"Larva";367;2
"Unit";"Baneling";"Zergling";369;0
"Unit";"Baneling";"Zergling";369;0
"Unit";"Baneling";"Zergling";369;0
"Unit";"Baneling";"Zergling";369;0
"Building";"CreepTumor";NA;369;0
"Building";"CreepTumor";NA;369;0
"Building";"CreepTumor";NA;369;0
"Building";"CreepTumor";NA;369;0
"Building";"CreepTumor";NA;369;0
"Unit";"Hydralisk";"Larva";369;2
"Unit";"Hydralisk";"Larva";371;2
"Unit";"Hydralisk";"Larva";373;2
"Unit";"Hydralisk";"Larva";375;2
"Unit";"Hydralisk";"Larva";377;2
"Building";"SporeCrawler";NA;379;0
"Building";"SporeCrawler";NA;379;0
"Unit";"Hydralisk";"Larva";379;2
"Unit";"Zergling";"Larva";381;1
"Unit";"Zergling";"Larva";382;1
"Building";"SporeCrawler";NA;383;0
"Building";"SporeCrawler";NA;383;0
"Building";"SporeCrawler";NA;383;0
"Building";"SporeCrawler";NA;383;0
"Building";"SporeCrawler";NA;383;0
"Unit";"Infestor";"Larva";383;2
"Unit";"Infestor";"Larva";385;2
"Unit";"Infestor";"Larva";387;2
"Unit";"Hydralisk";"Larva";389;2
"Unit";"Hydralisk";"Larva";391;2
"Unit";"Hydralisk";"Larva";393;2
"Unit";"Hydralisk";"Larva";395;2
"Unit";"Hydralisk";"Larva";403;2
"Unit";"Hydralisk";"Larva";405;2
"Unit";"Hydralisk";"Larva";407;2
"Unit";"Zergling";"Larva";409;1
"Unit";"Zergling";"Larva";410;1
"Unit";"Zergling";"Larva";411;1
"Unit";"Zergling";"Larva";412;1
"Unit";"Zergling";"Larva";413;1
"Unit";"Zergling";"Larva";414;1
"Unit";"Zergling";"Larva";415;1
"Unit";"Zergling";"Larva";416;1
"Unit";"Zergling";"Larva";417;1
"Unit";"Zergling";"Larva";418;1
"Unit";"Infestor";"Larva";419;2
"Unit";"Infestor";"Larva";421;2
"Building";"CreepTumorQueen";NA;423;0
"Unit";"Infestor";"Larva";423;2
"Unit";"Infestor";"Larva";425;2
"Building";"CreepTumor";NA;430;0
"Building";"SporeCrawler";NA;430;0
"Building";"SporeCrawler";NA;430;0
"Building";"SporeCrawler";NA;430;0
"Building";"CreepTumor";NA;435;0
"Building";"SporeCrawler";NA;435;0
"Building";"SporeCrawler";NA;435;0
"Unit";"Infestor";"Larva";435;2
"Building";"SporeCrawler";NA;437;0
"Unit";"Infestor";"Larva";437;2
"Unit";"Infestor";"Larva";439;2
"Unit";"Infestor";"Larva";441;2
"Building";"SporeCrawler";NA;443;0
"Building";"CreepTumor";NA;443;0
"Building";"CreepTumor";NA;443;0
"Building";"CreepTumor";NA;443;0
"Unit";"Zergling";"Larva";443;1
"Unit";"Zergling";"Larva";444;1
"Unit";"Zergling";"Larva";445;1
"Unit";"Zergling";"Larva";446;1
"Unit";"Zergling";"Larva";447;1
"Unit";"Zergling";"Larva";448;1
"Unit";"Zergling";"Larva";449;1
"Unit";"Zergling";"Larva";450;1
"Unit";"Zergling";"Larva";451;1
"Unit";"Zergling";"Larva";452;1
"Unit";"Zergling";"Larva";453;1
"Unit";"Zergling";"Larva";454;1
"Unit";"Zergling";"Larva";455;1
"Unit";"Zergling";"Larva";456;1
"Unit";"Zergling";"Larva";457;1
"Unit";"Zergling";"Larva";458;1
"Unit";"Zergling";"Larva";459;1
"Unit";"Zergling";"Larva";460;1
"Unit";"Zergling";"Larva";461;1
"Unit";"Zergling";"Larva";462;1
"Unit";"Zergling";"Larva";463;1
"Unit";"Zergling";"Larva";464;1
"Unit";"Zergling";"Larva";465;1
"Unit";"Zergling";"Larva";466;1
"Building";"SporeCrawler";NA;467;0
"Building";"UltraliskCavern";NA;467;0
"Unit";"Queen";"Hatchery";467;2
"Building";"CreepTumor";NA;469;0
"Building";"CreepTumor";NA;469;0
"Building";"CreepTumor";NA;469;0
"Building";"CreepTumor";NA;469;0
"Building";"CreepTumor";NA;469;0
"Building";"CreepTumorQueen";NA;469;0
"Building";"SporeCrawler";NA;469;0
"Building";"CreepTumorQueen";NA;469;0
"Building";"SporeCrawler";NA;469;0
"Building";"SporeCrawler";NA;471;0
"Building";"SporeCrawler";NA;471;0
"Building";"SporeCrawler";NA;473;0
"Building";"SporeCrawler";NA;473;0
"Building";"SporeCrawler";NA;475;0
"Unit";"Zergling";"Larva";477;1
"Unit";"Zergling";"Larva";478;1
"Unit";"Zergling";"Larva";479;1
"Unit";"Zergling";"Larva";480;1
"Unit";"Zergling";"Larva";481;1
"Unit";"Zergling";"Larva";482;1
"Unit";"Zergling";"Larva";483;1
"Unit";"Zergling";"Larva";484;1
"Unit";"Zergling";"Larva";485;1
"Unit";"Zergling";"Larva";486;1
"Unit";"Infestor";"Larva";487;2
"Unit";"Infestor";"Larva";489;2
"Building";"CreepTumor";NA;491;0
"Unit";"Corruptor";"Larva";491;2
"Unit";"Corruptor";"Larva";493;2
"Building";"CreepTumor";NA;495;0
"Building";"CreepTumor";NA;495;0
"Building";"CreepTumor";NA;495;0
"Unit";"Corruptor";"Larva";495;2
"Building";"CreepTumor";NA;497;0
"Building";"CreepTumor";NA;497;0
"Upgrade";"Burrow";"Hatchery";497;0
"Upgrade";"ChitinousPlating";"UltraliskCavern";497;0
"Building";"SpineCrawler";NA;498;0
"Building";"CreepTumor";NA;498;0
"Unit";"Corruptor";"Larva";498;2
"Building";"SpineCrawler";NA;502;0
"Unit";"Zergling";"Larva";502;1
"Unit";"Zergling";"Larva";503;1
"Unit";"Zergling";"Larva";504;1
"Unit";"Zergling";"Larva";505;1
"Unit";"Zergling";"Larva";506;1
"Unit";"Zergling";"Larva";507;1
"Unit";"Zergling";"Larva";508;1
"Unit";"Zergling";"Larva";509;1
"Building";"CreepTumorQueen";NA;510;0
"Building";"CreepTumorQueen";NA;510;0
"Unit";"Corruptor";"Larva";510;2
"Unit";"Zergling";"Larva";512;1
"Unit";"Zergling";"Larva";513;1
"Unit";"Zergling";"Larva";514;1
"Unit";"Zergling";"Larva";515;1
"Unit";"Zergling";"Larva";516;1
"Unit";"Zergling";"Larva";517;1
"Building";"Extractor";NA;518;0
"Building";"CreepTumor";NA;518;0
"Building";"CreepTumor";NA;518;0
"Unit";"Zergling";"Larva";518;1
"Unit";"Zergling";"Larva";519;1
"Unit";"Zergling";"Larva";520;1
"Unit";"Zergling";"Larva";521;1
"Building";"CreepTumor";NA;522;0
"Building";"CreepTumor";NA;522;0
"Building";"Hatchery";NA;522;0
"Building";"Extractor";NA;522;0
"Building";"CreepTumorQueen";NA;522;0
"Building";"CreepTumorQueen";NA;522;0
"Building";"CreepTumorQueen";NA;522;0
"Building";"SporeCrawler";NA;522;0
"Building";"SporeCrawler";NA;522;0
"Building";"SporeCrawler";NA;522;0
"Building";"SporeCrawler";NA;522;0
"Building";"SporeCrawler";NA;522;0
"Building";"SporeCrawler";NA;524;0
"Building";"SporeCrawler";NA;525;0
"Building";"SporeCrawler";NA;525;0
"Building";"SporeCrawler";NA;529;0
"Building";"CreepTumorQueen";NA;529;0
"Building";"CreepTumorQueen";NA;529;0
"Unit";"Infestor";"Larva";533;2
"Unit";"Infestor";"Larva";535;2
"Unit";"Infestor";"Larva";537;2
"Unit";"Zergling";"Larva";539;1
"Unit";"Zergling";"Larva";540;1
"Unit";"Zergling";"Larva";541;1
"Unit";"Zergling";"Larva";542;1
"Unit";"Zergling";"Larva";543;1
"Unit";"Zergling";"Larva";544;1
"Unit";"Zergling";"Larva";545;1
"Unit";"Zergling";"Larva";546;1
"Unit";"Zergling";"Larva";547;1
"Unit";"Zergling";"Larva";548;1
"Unit";"Zergling";"Larva";549;1
"Unit";"Zergling";"Larva";550;1
"Unit";"Zergling";"Larva";551;1
"Unit";"Zergling";"Larva";552;1
"Unit";"Zergling";"Larva";553;1
"Unit";"Zergling";"Larva";554;1
"Unit";"Zergling";"Larva";555;1
"Unit";"Zergling";"Larva";556;1
"Unit";"Zergling";"Larva";557;1
"Unit";"Zergling";"Larva";558;1
"Building";"CreepTumor";NA;559;0
"Building";"CreepTumor";NA;559;0
"Building";"CreepTumor";NA;559;0
"Building";"CreepTumor";NA;559;0
"Building";"CreepTumor";NA;559;0
"Building";"SporeCrawler";NA;565;0
"Building";"SporeCrawler";NA;565;0
"Building";"SporeCrawler";NA;565;0
"Building";"SporeCrawler";NA;565;0
"Building";"SporeCrawler";NA;565;0
"Building";"SporeCrawler";NA;565;0
"Building";"SporeCrawler";NA;566;0
"Building";"SporeCrawler";NA;566;0
"Unit";"Corruptor";"Larva";568;2
"Unit";"Corruptor";"Larva";570;2
"Unit";"Corruptor";"Larva";572;2
"Unit";"Zergling";"Larva";574;1
"Unit";"Zergling";"Larva";575;1
"Unit";"Baneling";"Zergling";576;0
"Unit";"Baneling";"Zergling";576;0
"Unit";"Baneling";"Zergling";576;0
"Unit";"Baneling";"Zergling";576;0
"Unit";"Baneling";"Zergling";576;0
"Unit";"Baneling";"Zergling";576;0
"Unit";"Baneling";"Zergling";576;0
"Unit";"Baneling";"Zergling";576;0
"Unit";"Baneling";"Zergling";576;0
"Unit";"Baneling";"Zergling";576;0
"Unit";"Baneling";"Zergling";576;0
"Unit";"Baneling";"Zergling";576;0
"Unit";"Baneling";"Zergling";576;0
"Building";"CreepTumor";NA;576;0
"Building";"SporeCrawler";NA;576;0
"Building";"SporeCrawler";NA;576;0
"Building";"SporeCrawler";NA;576;0
"Building";"SporeCrawler";NA;576;0
"Building";"SporeCrawler";NA;576;0
"Building";"SporeCrawler";NA;576;0
"Unit";"Zergling";"Larva";576;1
"Unit";"Zergling";"Larva";577;1
"Unit";"Zergling";"Larva";578;1
"Unit";"Zergling";"Larva";579;1
"Unit";"Zergling";"Larva";580;1
"Unit";"Zergling";"Larva";581;1
"Unit";"Zergling";"Larva";582;1
"Unit";"Zergling";"Larva";583;1
"Unit";"Zergling";"Larva";584;1
"Unit";"Zergling";"Larva";585;1
"Unit";"Zergling";"Larva";586;1
"Unit";"Zergling";"Larva";587;1
"Unit";"Zergling";"Larva";588;1
"Unit";"Zergling";"Larva";589;1
"Unit";"Zergling";"Larva";590;1
"Unit";"Zergling";"Larva";591;1
"Unit";"Zergling";"Larva";592;1
"Unit";"Zergling";"Larva";593;1
"Unit";"Zergling";"Larva";594;1
"Unit";"Zergling";"Larva";595;1
"Unit";"Zergling";"Larva";596;1
"Unit";"Zergling";"Larva";597;1
"Unit";"Zergling";"Larva";598;1
"Unit";"Zergling";"Larva";599;1
"Unit";"Zergling";"Larva";600;1
"Unit";"Zergling";"Larva";601;1
"Unit";"Corruptor";"Larva";602;2
"Unit";"Corruptor";"Larva";604;2
"Unit";"Corruptor";"Larva";606;2
"Unit";"Hydralisk";"Larva";608;2
"Unit";"Hydralisk";"Larva";610;2
"Unit";"Hydralisk";"Larva";612;2
"Unit";"Hydralisk";"Larva";614;2
"Building";"CreepTumor";NA;616;0
"Building";"CreepTumor";NA;616;0
"Unit";"Corruptor";"Larva";616;2
"Unit";"Corruptor";"Larva";618;2
"Unit";"Corruptor";"Larva";620;2
"Unit";"Corruptor";"Larva";622;2
"Unit";"Corruptor";"Larva";624;2
"Unit";"Corruptor";"Larva";626;2
"Unit";"Corruptor";"Larva";628;2
"Unit";"Corruptor";"Larva";630;2
"Unit";"Infestor";"Larva";632;2
"Unit";"Infestor";"Larva";634;2
"Unit";"Infestor";"Larva";636;2
"Unit";"Infestor";"Larva";638;2
"Unit";"Infestor";"Larva";640;2
"Building";"Extractor";NA;645;0
"Building";"Extractor";NA;645;0
"Unit";"Ultralisk";"Larva";648;6
"Unit";"Ultralisk";"Larva";654;6
"Unit";"Ultralisk";"Larva";660;6
"Unit";"Infestor";"Larva";666;2
"Unit";"Infestor";"Larva";668;2
"Unit";"Infestor";"Larva";670;2
"Unit";"Infestor";"Larva";672;2
"Unit";"Ultralisk";"Larva";674;6
"Unit";"Ultralisk";"Larva";680;6
"Building";"SpineCrawler";NA;686;0
"Building";"SpineCrawler";NA;686;0
"Building";"SpineCrawler";NA;689;0
"Unit";"Infestor";"Larva";689;2
"Unit";"Infestor";"Larva";691;2
"Unit";"Infestor";"Larva";693;2
"Unit";"Zergling";"Larva";695;1
"Unit";"Zergling";"Larva";696;1
"Unit";"Zergling";"Larva";697;1
"Unit";"Zergling";"Larva";698;1
"Unit";"Zergling";"Larva";699;1
"Unit";"Zergling";"Larva";700;1
"Building";"SporeCrawler";NA;701;0
"Unit";"Zergling";"Larva";701;1
"Unit";"Zergling";"Larva";702;1
"Unit";"Zergling";"Larva";703;1
"Unit";"Zergling";"Larva";704;1
"Unit";"Zergling";"Larva";705;1
"Unit";"Zergling";"Larva";706;1
"Unit";"Zergling";"Larva";707;1
"Unit";"Zergling";"Larva";708;1
"Unit";"Zergling";"Larva";709;1
"Unit";"Zergling";"Larva";710;1
"Unit";"Ultralisk";"Larva";711;6
"Unit";"Ultralisk";"Larva";717;6
"Unit";"Ultralisk";"Larva";723;6
"Unit";"Zergling";"Larva";729;1
"Unit";"Zergling";"Larva";730;1
"Unit";"Zergling";"Larva";731;1
"Unit";"Zergling";"Larva";732;1
"Unit";"Zergling";"Larva";733;1
"Unit";"Zergling";"Larva";734;1
"Unit";"Zergling";"Larva";735;1
"Unit";"Zergling";"Larva";736;1
"Unit";"Zergling";"Larva";737;1
"Unit";"Zergling";"Larva";738;1
"Unit";"Zergling";"Larva";739;1
"Unit";"Zergling";"Larva";740;1
"Unit";"Zergling";"Larva";741;1
"Unit";"Zergling";"Larva";742;1
"Unit";"Zergling";"Larva";743;1
"Unit";"Zergling";"Larva";744;1
"Unit";"Infestor";"Larva";745;2
"Unit";"Infestor";"Larva";747;2
"Unit";"Infestor";"Larva";749;2
"Unit";"Overlord";"Larva";751;0
"Unit";"Overlord";"Larva";751;0
"Unit";"Overlord";"Larva";751;0
"Unit";"Overlord";"Larva";751;0
"Unit";"Zergling";"Larva";751;1
"Unit";"Zergling";"Larva";752;1
"Unit";"Zergling";"Larva";753;1
"Unit";"Zergling";"Larva";754;1
"Unit";"Zergling";"Larva";755;1
"Unit";"Zergling";"Larva";756;1
"Unit";"Zergling";"Larva";757;1
"Unit";"Zergling";"Larva";758;1
"Unit";"Zergling";"Larva";759;1
"Unit";"Zergling";"Larva";760;1
"Unit";"Zergling";"Larva";761;1
"Unit";"Zergling";"Larva";762;1
"Unit";"Zergling";"Larva";763;1
"Unit";"Zergling";"Larva";764;1
"Unit";"Zergling";"Larva";765;1
"Unit";"Zergling";"Larva";766;1
"Unit";"Zergling";"Larva";767;1
"Unit";"Zergling";"Larva";768;1
"Unit";"Zergling";"Larva";769;1
"Unit";"Zergling";"Larva";770;1
"Unit";"Zergling";"Larva";771;1
"Unit";"Zergling";"Larva";772;1
"Unit";"Zergling";"Larva";773;1
"Unit";"Zergling";"Larva";774;1
"Unit";"Zergling";"Larva";775;1
"Unit";"Zergling";"Larva";776;1
"Unit";"Zergling";"Larva";777;1
"Unit";"Zergling";"Larva";778;1
"Unit";"Zergling";"Larva";779;1
"Unit";"Zergling";"Larva";780;1
"Unit";"Zergling";"Larva";781;1
"Unit";"Zergling";"Larva";782;1
"Unit";"Zergling";"Larva";783;1
"Unit";"Zergling";"Larva";784;1
"Unit";"Zergling";"Larva";785;1
"Unit";"Zergling";"Larva";786;1
"Unit";"Zergling";"Larva";787;1
"Unit";"Zergling";"Larva";788;1
"Unit";"Zergling";"Larva";789;1
"Unit";"Zergling";"Larva";790;1
"Upgrade";"SprayZerg";NA;791;0
"Upgrade";"SprayZerg";NA;791;0
"Upgrade";"SprayZerg";NA;791;0
"Upgrade";"zerglingmovementspeed";NA;791;0
"Upgrade";"SprayZerg";NA;791;0
"Upgrade";"SprayZerg";NA;791;0
"Upgrade";"EvolveGroovedSpines";NA;791;0
"Upgrade";"CentrificalHooks";NA;791;0
"Upgrade";"SprayZerg";NA;791;0
"Upgrade";"EvolveMuscularAugments";NA;791;0
"Upgrade";"SprayZerg";NA;791;0
"Upgrade";"ZergMeleeWeaponsLevel1";NA;791;0
"Upgrade";"overlordspeed";NA;791;0
"Upgrade";"SprayZerg";NA;791;0
"Upgrade";"zerglingattackspeed";NA;791;0
"Upgrade";"SprayZerg";NA;791;0
"Upgrade";"ZergMeleeWeaponsLevel2";NA;791;0
"Upgrade";"SprayZerg";NA;791;0
"Upgrade";"InfestorEnergyUpgrade";NA;791;0
"Upgrade";"ZergFlyerWeaponsLevel1";NA;791;0
"Upgrade";"ZergMeleeWeaponsLevel3";NA;791;0
"Upgrade";"ZergGroundArmorsLevel1";NA;791;0
"Upgrade";"ZergFlyerArmorsLevel1";NA;791;0
"Upgrade";"ZergMissileWeaponsLevel1";NA;791;0
"Upgrade";"SprayZerg";NA;791;0
"Upgrade";"ZergFlyerWeaponsLevel2";NA;791;0
"Upgrade";"ZergGroundArmorsLevel2";NA;791;0
"Upgrade";"ZergFlyerArmorsLevel2";NA;791;0
"Upgrade";"SprayZerg";NA;791;0
"Upgrade";"ZergMissileWeaponsLevel2";NA;791;0
"Upgrade";"SprayZerg";NA;791;0
"Upgrade";"ZergFlyerWeaponsLevel3";NA;791;0
"Upgrade";"ZergFlyerArmorsLevel3";NA;791;0
"Upgrade";"SprayZerg";NA;791;0
"Upgrade";"ZergGroundArmorsLevel3";NA;791;0
"Upgrade";"ZergMissileWeaponsLevel3";NA;791;0
