"type";"unit_name";"on_building";"total_supply";"supply"
"Unit";"Overlord";"Larva";12;0
"Building";"SpawningPool";NA;19;0
"Building";"Extractor";NA;19;0
"Building";"Hatchery";NA;17;0
"Unit";"Queen";"Hatchery";23;2
"Unit";"Overlord";"Larva";25;0
"Building";"Hatchery";NA;19;0
"Unit";"Queen";"Hatchery";24;2
"Building";"CreepTumorQueen";NA;32;0
"Unit";"Zergling";"Larva";32;1
"Unit";"Zergling";"Larva";32;1
"Unit";"Zergling";"Larva";32;1
"Unit";"Zergling";"Larva";32;1
"Unit";"Zergling";"Larva";32;1
"Unit";"Zergling";"Larva";32;1
"Unit";"Zergling";"Larva";35;1
"Unit";"Zergling";"Larva";35;1
"Building";"CreepTumor";NA;37;0
"Unit";"Queen";"Hatchery";32;2
"Unit";"Zergling";"Larva";37;1
"Unit";"Zergling";"Larva";37;1
"Unit";"Overlord";"Larva";51;0
"Unit";"Overlord";"Larva";51;0
"Building";"CreepTumor";NA;60;0
"Building";"SporeCrawler";NA;63;0
"Building";"SporeCrawler";NA;63;0
"Building";"SporeCrawler";NA;64;0
"Building";"Extractor";NA;68;0
"Building";"Extractor";NA;68;0
"Building";"CreepTumor";NA;68;0
"Building";"EvolutionChamber";NA;68;0
"Unit";"Overlord";"Larva";72;0
"Unit";"Overlord";"Larva";72;0
"Building";"Extractor";NA;77;0
"Building";"HydraliskDen";NA;77;0
"Building";"Extractor";NA;84;0
"Building";"Extractor";NA;84;0
"Unit";"Overlord";"Larva";84;0
"Unit";"Overlord";"Larva";84;0
"Unit";"Overlord";"Larva";88;0
"Unit";"Overlord";"Larva";90;0
"Unit";"Overlord";"Larva";90;0
"Unit";"Overlord";"Larva";91;0
"Building";"BanelingNest";NA;84;0
"Building";"Hatchery";NA;84;0
"Building";"SporeCrawler";NA;105;0
"Upgrade";"ZergMissileWeaponsLevel1";"EvolutionChamber";89;0
"Building";"Extractor";NA;105;0
"Building";"SporeCrawler";NA;105;0
"Unit";"Queen";"Hatchery";104;2
"Unit";"Queen";"Hatchery";105;2
"Unit";"Queen";"Hatchery";105;2
"Building";"Spire";NA;91;0
"Building";"Spire";NA;91;0
"Building";"SporeCrawler";NA;105;0
"Unit";"Overlord";"Larva";112;0
"Unit";"Overlord";"Larva";112;0
"Unit";"Queen";"Hatchery";105;2
"Upgrade";"EvolveGroovedSpines";"HydraliskDen";105;0
"Unit";"Overlord";"Larva";127;0
"Unit";"Overlord";"Larva";127;0
"Unit";"Overlord";"Larva";127;0
"Building";"Extractor";NA;127;0
"Building";"CreepTumorQueen";NA;127;0
"Building";"CreepTumorQueen";NA;127;0
"Unit";"Queen";"Hatchery";127;2
"Unit";"Queen";"Hatchery";127;2
"Building";"SporeCrawler";NA;127;0
"Unit";"Overlord";"Larva";127;0
"Unit";"Overlord";"Larva";127;0
"Unit";"Overlord";"Larva";127;0
"Unit";"Overlord";"Larva";127;0
"Building";"Extractor";NA;127;0
"Unit";"Corruptor";"Larva";127;2
"Unit";"Corruptor";"Larva";127;2
"Unit";"Corruptor";"Larva";127;2
"Unit";"Corruptor";"Larva";127;2
"Unit";"Corruptor";"Larva";127;2
"Unit";"Corruptor";"Larva";127;2
"Unit";"Corruptor";"Larva";127;2
"Unit";"Corruptor";"Larva";127;2
"Unit";"Overlord";"Larva";140;0
"Unit";"Overlord";"Larva";140;0
"Building";"SporeCrawler";NA;140;0
"Building";"SporeCrawler";NA;140;0
"Building";"Extractor";NA;140;0
"Unit";"Corruptor";"Larva";156;2
"Unit";"Corruptor";"Larva";156;2
"Unit";"Corruptor";"Larva";156;2
"Unit";"Corruptor";"Larva";156;2
"Unit";"Corruptor";"Larva";156;2
"Unit";"Corruptor";"Larva";156;2
"Unit";"Corruptor";"Larva";156;2
"Unit";"Corruptor";"Larva";156;2
"Unit";"Corruptor";"Larva";156;2
"Unit";"Corruptor";"Larva";179;2
"Unit";"Corruptor";"Larva";179;2
"Unit";"Corruptor";"Larva";179;2
"Unit";"Corruptor";"Larva";179;2
"Unit";"Corruptor";"Larva";179;2
"Upgrade";"ZergMissileWeaponsLevel2";"EvolutionChamber";140;0
"Unit";"Corruptor";"Larva";179;2
"Unit";"Corruptor";"Larva";179;2
"Unit";"Corruptor";"Larva";179;2
"Unit";"Corruptor";"Larva";179;2
"Unit";"Corruptor";"Larva";179;2
"Unit";"Hydralisk";"Larva";189;2
"Building";"Hatchery";NA;179;0
"Building";"InfestationPit";NA;189;0
"Building";"Hatchery";NA;179;0
"Unit";"Zergling";"Larva";212;1
"Unit";"Zergling";"Larva";212;1
"Unit";"Zergling";"Larva";212;1
"Unit";"Zergling";"Larva";212;1
"Unit";"Zergling";"Larva";212;1
"Unit";"Zergling";"Larva";212;1
"Unit";"Zergling";"Larva";212;1
"Unit";"Zergling";"Larva";212;1
"Unit";"Zergling";"Larva";212;1
"Unit";"Zergling";"Larva";212;1
"Unit";"Zergling";"Larva";212;1
"Unit";"Zergling";"Larva";212;1
"Unit";"Zergling";"Larva";212;1
"Unit";"Zergling";"Larva";212;1
"Unit";"Zergling";"Larva";212;1
"Unit";"Zergling";"Larva";212;1
"Unit";"Zergling";"Larva";212;1
"Unit";"Zergling";"Larva";212;1
"Unit";"Zergling";"Larva";212;1
"Unit";"Zergling";"Larva";212;1
"Unit";"Zergling";"Larva";212;1
"Unit";"Zergling";"Larva";212;1
"Unit";"Zergling";"Larva";212;1
"Unit";"Zergling";"Larva";212;1
"Unit";"Hydralisk";"Larva";212;2
"Unit";"Hydralisk";"Larva";212;2
"Unit";"Hydralisk";"Larva";212;2
"Unit";"Hydralisk";"Larva";212;2
"Unit";"Hydralisk";"Larva";212;2
"Unit";"Hydralisk";"Larva";212;2
"Upgrade";"EvolveMuscularAugments";"HydraliskDen";212;0
"Unit";"Zergling";"Larva";236;1
"Unit";"Zergling";"Larva";236;1
"Unit";"Overlord";"Larva";236;0
"Unit";"Overlord";"Larva";236;0
"Unit";"Overlord";"Larva";236;0
"Unit";"Overlord";"Larva";236;0
"Unit";"Hydralisk";"Larva";214;2
"Unit";"Hydralisk";"Larva";236;2
"Unit";"Hydralisk";"Larva";236;2
"Unit";"Hydralisk";"Larva";236;2
"Unit";"Hydralisk";"Larva";236;2
"Unit";"Hydralisk";"Larva";236;2
"Unit";"Hydralisk";"Larva";236;2
"Building";"SporeCrawler";NA;248;0
"Building";"Extractor";NA;248;0
"Building";"SporeCrawler";NA;248;0
"Building";"SporeCrawler";NA;248;0
"Unit";"Zergling";"Larva";248;1
"Unit";"Zergling";"Larva";248;1
"Unit";"Hydralisk";"Larva";248;2
"Unit";"Hydralisk";"Larva";248;2
"Unit";"Hydralisk";"Larva";248;2
"Unit";"Hydralisk";"Larva";248;2
"Unit";"Baneling";"Zergling";267;0
"Unit";"Baneling";"Zergling";267;0
"Unit";"Baneling";"Zergling";267;0
"Unit";"Baneling";"Zergling";267;0
"Unit";"Hydralisk";"Larva";253;2
"Unit";"Hydralisk";"Larva";253;2
"Unit";"Hydralisk";"Larva";253;2
"Unit";"Hydralisk";"Larva";253;2
"Unit";"Hydralisk";"Larva";253;2
"Building";"SpineCrawler";NA;248;0
"Building";"Extractor";NA;269;0
"Building";"SpineCrawler";NA;277;0
"Unit";"Corruptor";"Larva";287;2
"Unit";"Corruptor";"Larva";287;2
"Unit";"Corruptor";"Larva";287;2
"Unit";"Corruptor";"Larva";287;2
"Unit";"Corruptor";"Larva";287;2
"Unit";"Corruptor";"Larva";287;2
"Unit";"Corruptor";"Larva";287;2
"Unit";"Corruptor";"Larva";311;2
"Unit";"Corruptor";"Larva";311;2
"Unit";"Corruptor";"Larva";311;2
"Unit";"Corruptor";"Larva";311;2
"Unit";"Corruptor";"Larva";311;2
"Unit";"Corruptor";"Larva";311;2
"Unit";"Corruptor";"Larva";311;2
"Unit";"Corruptor";"Larva";311;2
"Unit";"Corruptor";"Larva";311;2
"Unit";"Corruptor";"Larva";311;2
"Unit";"Corruptor";"Larva";311;2
"Unit";"Corruptor";"Larva";311;2
"Unit";"Corruptor";"Larva";311;2
"Unit";"Corruptor";"Larva";311;2
"Building";"Extractor";NA;311;0
"Building";"Extractor";NA;311;0
"Building";"SporeCrawler";NA;311;0
"Building";"SporeCrawler";NA;311;0
"Building";"SporeCrawler";NA;311;0
"Building";"SporeCrawler";NA;311;0
"Building";"SporeCrawler";NA;311;0
"Unit";"Corruptor";"Larva";311;2
"Unit";"Corruptor";"Larva";311;2
"Unit";"Corruptor";"Larva";311;2
"Unit";"Corruptor";"Larva";311;2
"Unit";"Zergling";"Larva";347;1
"Unit";"Zergling";"Larva";347;1
"Unit";"Zergling";"Larva";347;1
"Unit";"Zergling";"Larva";347;1
"Unit";"Zergling";"Larva";347;1
"Unit";"Zergling";"Larva";347;1
"Unit";"Zergling";"Larva";347;1
"Unit";"Zergling";"Larva";347;1
"Unit";"Zergling";"Larva";347;1
"Unit";"Zergling";"Larva";347;1
"Unit";"Zergling";"Larva";347;1
"Unit";"Zergling";"Larva";347;1
"Unit";"Zergling";"Larva";347;1
"Unit";"Zergling";"Larva";347;1
"Unit";"Zergling";"Larva";347;1
"Unit";"Zergling";"Larva";347;1
"Unit";"Zergling";"Larva";347;1
"Unit";"Zergling";"Larva";347;1
"Unit";"Corruptor";"Larva";339;2
"Unit";"Corruptor";"Larva";339;2
"Unit";"Corruptor";"Larva";339;2
"Unit";"Corruptor";"Larva";341;2
"Unit";"Overlord";"Larva";365;0
"Unit";"Overlord";"Larva";365;0
"Unit";"Overlord";"Larva";365;0
"Unit";"Overlord";"Larva";365;0
"Unit";"Overlord";"Larva";365;0
"Unit";"Overlord";"Larva";365;0
"Unit";"Overlord";"Larva";365;0
"Unit";"Overlord";"Larva";365;0
"Unit";"Overlord";"Larva";377;0
"Unit";"Overlord";"Larva";377;0
"Unit";"Overlord";"Larva";377;0
"Unit";"Overlord";"Larva";377;0
"Unit";"Corruptor";"Larva";377;2
"Unit";"Corruptor";"Larva";377;2
"Unit";"Corruptor";"Larva";377;2
"Unit";"Corruptor";"Larva";377;2
"Unit";"Corruptor";"Larva";377;2
"Unit";"Corruptor";"Larva";377;2
"Unit";"Corruptor";"Larva";377;2
"Unit";"Corruptor";"Larva";377;2
"Unit";"Corruptor";"Larva";377;2
"Unit";"Corruptor";"Larva";377;2
"Unit";"Corruptor";"Larva";377;2
"Unit";"Corruptor";"Larva";377;2
"Unit";"Corruptor";"Larva";377;2
"Unit";"Corruptor";"Larva";377;2
"Unit";"Corruptor";"Larva";377;2
"Unit";"Corruptor";"Larva";377;2
"Unit";"Corruptor";"Larva";377;2
"Unit";"Corruptor";"Larva";377;2
"Unit";"Corruptor";"Larva";377;2
"Unit";"Corruptor";"Larva";377;2
"Unit";"Corruptor";"Larva";420;2
"Unit";"Corruptor";"Larva";420;2
"Unit";"Corruptor";"Larva";420;2
"Unit";"Corruptor";"Larva";420;2
"Unit";"Corruptor";"Larva";420;2
"Unit";"Corruptor";"Larva";420;2
"Unit";"Corruptor";"Larva";420;2
"Unit";"Corruptor";"Larva";420;2
"Unit";"Corruptor";"Larva";420;2
"Unit";"Corruptor";"Larva";420;2
"Unit";"Corruptor";"Larva";420;2
"Unit";"Corruptor";"Larva";420;2
"Unit";"Corruptor";"Larva";420;2
"Unit";"Corruptor";"Larva";420;2
"Unit";"Corruptor";"Larva";420;2
"Unit";"Corruptor";"Larva";420;2
"Unit";"Corruptor";"Larva";455;2
"Unit";"Corruptor";"Larva";455;2
"Unit";"Corruptor";"Larva";455;2
"Unit";"Corruptor";"Larva";455;2
"Unit";"Corruptor";"Larva";455;2
"Unit";"Corruptor";"Larva";455;2
"Unit";"Corruptor";"Larva";455;2
"Unit";"Corruptor";"Larva";455;2
"Unit";"Corruptor";"Larva";455;2
"Unit";"Hydralisk";"Larva";455;2
"Unit";"Hydralisk";"Larva";455;2
"Unit";"Hydralisk";"Larva";455;2
"Unit";"Hydralisk";"Larva";455;2
"Unit";"Hydralisk";"Larva";455;2
"Unit";"Hydralisk";"Larva";455;2
"Building";"Hatchery";NA;440;0
"Unit";"Hydralisk";"Larva";473;2
"Unit";"Hydralisk";"Larva";473;2
"Unit";"Hydralisk";"Larva";473;2
"Unit";"Hydralisk";"Larva";473;2
"Unit";"Hydralisk";"Larva";473;2
"Unit";"Hydralisk";"Larva";473;2
"Unit";"Hydralisk";"Larva";473;2
"Building";"CreepTumorQueen";NA;485;0
"Building";"CreepTumorQueen";NA;487;0
"Building";"CreepTumorQueen";NA;499;0
"Building";"CreepTumorQueen";NA;499;0
"Unit";"Corruptor";"Larva";499;2
"Unit";"Corruptor";"Larva";499;2
"Unit";"Corruptor";"Larva";499;2
"Unit";"Corruptor";"Larva";499;2
"Unit";"Corruptor";"Larva";499;2
"Unit";"Corruptor";"Larva";499;2
"Unit";"Corruptor";"Larva";499;2
"Unit";"Corruptor";"Larva";499;2
"Unit";"Corruptor";"Larva";499;2
"Unit";"Corruptor";"Larva";499;2
"Building";"Hatchery";NA;473;0
"Unit";"Hydralisk";"Larva";499;2
"Unit";"Hydralisk";"Larva";499;2
"Unit";"Hydralisk";"Larva";499;2
"Unit";"Hydralisk";"Larva";499;2
"Unit";"Hydralisk";"Larva";499;2
"Unit";"Hydralisk";"Larva";499;2
"Unit";"Hydralisk";"Larva";499;2
"Unit";"Hydralisk";"Larva";499;2
