"type";"unit_name";"on_building";"total_supply";"supply"
"Unit";"Overlord";"Larva";12;0
"Building";"Extractor";NA;18;0
"Building";"SpawningPool";NA;19;0
"Building";"Hatchery";NA;17;0
"Unit";"Overlord";"Larva";23;0
"Unit";"Zergling";"Larva";24;1
"Unit";"Zergling";"Larva";24;1
"Unit";"Queen";"Hatchery";24;2
"Unit";"Queen";"Hatchery";24;2
"Unit";"Zergling";"Larva";29;1
"Unit";"Zergling";"Larva";29;1
"Unit";"Zergling";"Larva";31;1
"Unit";"Zergling";"Larva";31;1
"Unit";"Overlord";"Larva";39;0
"Unit";"Queen";"Hatchery";32;2
"Unit";"Overlord";"Larva";41;0
"Building";"CreepTumorQueen";NA;43;0
"Unit";"Zergling";"Larva";43;1
"Unit";"Zergling";"Larva";43;1
"Unit";"Zergling";"Larva";43;1
"Unit";"Zergling";"Larva";43;1
"Unit";"Zergling";"Larva";50;1
"Unit";"Zergling";"Larva";50;1
"Unit";"Zergling";"Larva";50;1
"Unit";"Zergling";"Larva";50;1
"Building";"EvolutionChamber";NA;50;0
"Unit";"Overlord";"Larva";54;0
"Building";"CreepTumor";NA;54;0
"Building";"CreepTumorQueen";NA;61;0
"Building";"RoachWarren";NA;48;0
"Building";"SporeCrawler";NA;54;0
"Building";"SporeCrawler";NA;54;0
"Unit";"Overlord";"Larva";61;0
"Unit";"Overlord";"Larva";61;0
"Building";"Extractor";NA;62;0
"Building";"Extractor";NA;62;0
"Building";"CreepTumor";NA;62;0
"Building";"Extractor";NA;62;0
"Unit";"Overlord";"Larva";71;0
"Unit";"Overlord";"Larva";71;0
"Building";"CreepTumor";NA;74;0
"Building";"CreepTumorQueen";NA;74;0
"Unit";"Roach";"Larva";74;2
"Unit";"Roach";"Larva";74;2
"Unit";"Roach";"Larva";74;2
"Unit";"Roach";"Larva";74;2
"Unit";"Roach";"Larva";74;2
"Unit";"Roach";"Larva";74;2
"Building";"CreepTumorQueen";NA;86;0
"Unit";"Roach";"Larva";76;2
"Unit";"Roach";"Larva";76;2
"Building";"CreepTumor";NA;86;0
"Unit";"Overlord";"Larva";84;0
"Upgrade";"GlialReconstitution";"RoachWarren";69;0
"Unit";"Roach";"Larva";88;2
"Unit";"Roach";"Larva";88;2
"Unit";"Roach";"Larva";88;2
"Building";"CreepTumor";NA;88;0
"Unit";"Roach";"Larva";88;2
"Unit";"Roach";"Larva";88;2
"Unit";"Roach";"Larva";90;2
"Building";"CreepTumorQueen";NA;98;0
"Unit";"Overlord";"Larva";92;0
"Upgrade";"ZergMissileWeaponsLevel1";"EvolutionChamber";69;0
"Unit";"Roach";"Larva";104;2
"Unit";"Roach";"Larva";104;2
"Unit";"Roach";"Larva";104;2
"Unit";"Roach";"Larva";104;2
"Unit";"Roach";"Larva";104;2
"Building";"Hatchery";NA;74;0
"Building";"HydraliskDen";NA;104;0
"Unit";"Roach";"Larva";115;2
"Unit";"Roach";"Larva";115;2
"Unit";"Roach";"Larva";115;2
"Unit";"Roach";"Larva";115;2
"Unit";"Roach";"Larva";115;2
"Unit";"Queen";"Hatchery";115;2
"Building";"CreepTumor";NA;146;0
"Building";"CreepTumor";NA;146;0
"Building";"CreepTumor";NA;146;0
"Building";"CreepTumor";NA;150;0
"Building";"Extractor";NA;146;0
"Building";"Extractor";NA;146;0
"Unit";"Overlord";"Larva";147;0
"Building";"CreepTumorQueen";NA;154;0
"Building";"SporeCrawler";NA;150;0
"Unit";"Hydralisk";"Larva";154;2
"Unit";"Hydralisk";"Larva";154;2
"Unit";"Hydralisk";"Larva";155;2
"Unit";"Hydralisk";"Larva";155;2
"Unit";"Hydralisk";"Larva";155;2
"Unit";"Hydralisk";"Larva";155;2
"Unit";"Overlord";"Larva";155;0
"Unit";"Hydralisk";"Larva";155;2
"Upgrade";"EvolveGroovedSpines";"HydraliskDen";143;0
"Unit";"Hydralisk";"Larva";155;2
"Unit";"Hydralisk";"Larva";155;2
"Unit";"Hydralisk";"Larva";155;2
"Unit";"Hydralisk";"Larva";155;2
"Unit";"Hydralisk";"Larva";155;2
"Unit";"Hydralisk";"Larva";167;2
"Unit";"Roach";"Larva";171;2
"Unit";"Roach";"Larva";171;2
"Building";"CreepTumor";NA;179;0
"Building";"CreepTumor";NA;179;0
"Unit";"Roach";"Larva";171;2
"Unit";"Overlord";"Larva";177;0
"Unit";"Roach";"Larva";171;2
"Unit";"Overlord";"Larva";179;0
"Unit";"Overlord";"Larva";179;0
"Unit";"Overlord";"Larva";181;0
"Unit";"Overlord";"Larva";188;0
"Unit";"Roach";"Larva";190;2
"Unit";"Roach";"Larva";190;2
"Unit";"Roach";"Larva";190;2
"Unit";"Roach";"Larva";190;2
"Unit";"Roach";"Larva";190;2
"Unit";"Roach";"Larva";190;2
"Upgrade";"EvolveMuscularAugments";"HydraliskDen";185;0
"Unit";"Roach";"Larva";190;2
"Unit";"Roach";"Larva";190;2
"Unit";"Roach";"Larva";190;2
"Unit";"Roach";"Larva";190;2
"Unit";"Roach";"Larva";190;2
"Unit";"Roach";"Larva";190;2
"Unit";"Roach";"Larva";190;2
"Unit";"Roach";"Larva";190;2
"Unit";"Roach";"Larva";190;2
"Unit";"Roach";"Larva";190;2
"Unit";"Roach";"Larva";190;2
"Upgrade";"ZergMissileWeaponsLevel2";"EvolutionChamber";155;0
"Unit";"Roach";"Larva";202;2
"Unit";"Roach";"Larva";202;2
"Unit";"Roach";"Larva";202;2
"Unit";"Roach";"Larva";202;2
"Unit";"Roach";"Larva";202;2
"Unit";"Roach";"Larva";202;2
"Unit";"Roach";"Larva";224;2
"Unit";"Roach";"Larva";224;2
"Unit";"Roach";"Larva";224;2
"Unit";"Roach";"Larva";224;2
"Unit";"Roach";"Larva";234;2
"Unit";"Roach";"Larva";234;2
"Unit";"Roach";"Larva";234;2
"Unit";"Roach";"Larva";234;2
"Unit";"Roach";"Larva";238;2
"Unit";"Roach";"Larva";238;2
"Unit";"Roach";"Larva";242;2
"Unit";"Roach";"Larva";244;2
"Unit";"Roach";"Larva";263;2
"Unit";"Roach";"Larva";263;2
"Unit";"Roach";"Larva";263;2
"Unit";"Overlord";"Larva";265;0
"Unit";"Hydralisk";"Larva";268;2
"Unit";"Hydralisk";"Larva";268;2
"Unit";"Hydralisk";"Larva";268;2
"Unit";"Roach";"Larva";272;2
"Unit";"Roach";"Larva";276;2
"Unit";"Roach";"Larva";278;2
"Unit";"Roach";"Larva";278;2
"Unit";"Roach";"Larva";278;2
"Unit";"Roach";"Larva";278;2
"Unit";"Roach";"Larva";278;2
"Unit";"Roach";"Larva";278;2
"Unit";"Roach";"Larva";278;2
"Unit";"Roach";"Larva";278;2
"Unit";"Roach";"Larva";278;2
"Unit";"Roach";"Larva";278;2
"Unit";"Roach";"Larva";278;2
"Unit";"Roach";"Larva";284;2
"Unit";"Roach";"Larva";284;2
"Unit";"Overlord";"Larva";294;0
"Building";"Hatchery";NA;257;0
"Unit";"Roach";"Larva";296;2
"Unit";"Roach";"Larva";296;2
"Unit";"Roach";"Larva";308;2
"Unit";"Roach";"Larva";310;2
"Unit";"Overlord";"Larva";314;0
"Unit";"Overlord";"Larva";314;0
"Unit";"Overlord";"Larva";314;0
"Unit";"Roach";"Larva";314;2
"Unit";"Roach";"Larva";314;2
"Unit";"Overlord";"Larva";314;0
"Unit";"Overlord";"Larva";314;0
"Unit";"Overlord";"Larva";318;0
"Unit";"Hydralisk";"Larva";320;2
"Unit";"Hydralisk";"Larva";320;2
"Unit";"Roach";"Larva";326;2
"Unit";"Roach";"Larva";326;2
"Unit";"Roach";"Larva";326;2
"Unit";"Roach";"Larva";326;2
"Unit";"Roach";"Larva";326;2
"Unit";"Roach";"Larva";327;2
"Building";"Extractor";NA;333;0
"Unit";"Roach";"Larva";335;2
"Unit";"Roach";"Larva";335;2
"Unit";"Roach";"Larva";335;2
"Unit";"Roach";"Larva";335;2
"Unit";"Roach";"Larva";335;2
"Building";"Extractor";NA;333;0
"Unit";"Roach";"Larva";341;2
"Unit";"Roach";"Larva";343;2
"Unit";"Roach";"Larva";345;2
"Unit";"Roach";"Larva";345;2
"Unit";"Roach";"Larva";345;2
"Unit";"Roach";"Larva";345;2
"Unit";"Roach";"Larva";345;2
"Unit";"Roach";"Larva";345;2
"Unit";"Roach";"Larva";345;2
"Unit";"Roach";"Larva";355;2
"Unit";"Roach";"Larva";355;2
"Unit";"Roach";"Larva";357;2
"Unit";"Roach";"Larva";357;2
"Unit";"Roach";"Larva";361;2
"Unit";"Roach";"Larva";361;2
"Unit";"Hydralisk";"Larva";377;2
