"type";"unit_name";"on_building";"total_supply_lag";"supply"
"Building";"Refinery";NA;15;0
"Building";"Barracks";NA;16;0
"Unit";"Reaper";"Barracks";19;1
"Building";"CommandCenter";NA;20;0
"Building";"Factory";NA;20;0
"Building";"BarracksReactor";NA;21;0
"Building";"Refinery";NA;22;0
"Building";"Starport";NA;24;0
"Unit";"Hellion";"Factory";25;2
"Unit";"Hellion";"Factory";27;2
"Building";"BarracksTechLab";NA;29;0
"Unit";"Medivac";"Starport";31;2
"Unit";"Marine";"Barracks";35;1
"Unit";"Hellion";"Factory";40;2
"Unit";"Hellion";"Factory";42;2
"Unit";"Raven";"Starport";45;2
"Building";"CommandCenter";NA;50;0
"Unit";"Marine";"Barracks";52;1
"Unit";"Marine";"Barracks";53;1
"Unit";"Marine";"Barracks";56;1
"Unit";"Marine";"Barracks";57;1
"Building";"EngineeringBay";NA;58;0
"Building";"EngineeringBay";NA;59;0
"Building";"FactoryReactor";NA;62;0
"Building";"Barracks";NA;63;0
"Building";"Barracks";NA;63;0
"Unit";"Marine";"Barracks";64;1
"Building";"Refinery";NA;65;0
"Building";"Refinery";NA;65;0
"Unit";"Marine";"Barracks";67;1
"Building";"StarportReactor";NA;68;0
"Building";"Barracks";NA;68;0
"Building";"Barracks";NA;68;0
"Upgrade";"TerranInfantryWeaponsLevel1";"EngineeringBay";69;0
"Unit";"Marine";"Barracks";71;1
"Upgrade";"Stimpack";"TechLab";72;0
"Unit";"Marine";"Barracks";72;1
"Unit";"Marine";"Barracks";73;1
"Building";"FactoryReactor";NA;76;0
"Building";"Barracks";NA;76;0
"Building";"Barracks";NA;76;0
"Unit";"Marine";"Barracks";76;1
"Unit";"Marine";"Barracks";77;1
"Unit";"Marine";"Barracks";78;1
"Unit";"Medivac";"Starport";80;2
"Unit";"Medivac";"Starport";82;2
"Unit";"Marine";"Barracks";85;1
"Unit";"Marine";"Barracks";86;1
"Unit";"Marine";"Barracks";87;1
"Unit";"Marine";"Barracks";88;1
"Building";"BarracksReactor";NA;89;0
"Building";"BarracksReactor";NA;89;0
"Unit";"Marine";"Barracks";90;1
"Unit";"Marine";"Barracks";92;1
"Unit";"Marine";"Barracks";93;1
"Unit";"Marine";"Barracks";97;1
"Building";"MissileTurret";NA;98;0
"Building";"BarracksTechLab";NA;98;0
"Building";"BarracksReactor";NA;98;0
"Building";"Armory";NA;98;0
"Building";"MissileTurret";NA;98;0
"Building";"MissileTurret";NA;98;0
"Unit";"Marine";"Barracks";98;1
"Unit";"Marine";"Barracks";99;1
"Unit";"Marine";"Barracks";100;1
"Unit";"Marine";"Barracks";101;1
"Unit";"Marine";"Barracks";102;1
"Unit";"Medivac";"Starport";103;2
"Unit";"Marine";"Barracks";106;1
"Unit";"Marine";"Barracks";107;1
"Unit";"Marine";"Barracks";108;1
"Unit";"Marine";"Barracks";109;1
"Unit";"Medivac";"Starport";110;2
"Unit";"Marine";"Barracks";114;1
"Unit";"Marine";"Barracks";116;1
"Unit";"Marine";"Barracks";117;1
"Unit";"Marine";"Barracks";118;1
"Unit";"Marine";"Barracks";119;1
"Unit";"Marine";"Barracks";121;1
"Unit";"Marine";"Barracks";122;1
"Unit";"Marine";"Barracks";123;1
"Unit";"Marine";"Barracks";124;1
"Unit";"Medivac";"Starport";125;2
"Unit";"Medivac";"Starport";127;2
"Unit";"Marine";"Barracks";129;1
"Unit";"Marine";"Barracks";130;1
"Unit";"Marine";"Barracks";131;1
"Unit";"Marine";"Barracks";132;1
"Unit";"Marine";"Barracks";133;1
"Unit";"Marine";"Barracks";134;1
"Unit";"Marine";"Barracks";135;1
"Unit";"Marine";"Barracks";136;1
"Unit";"Marine";"Barracks";137;1
"Unit";"Marine";"Barracks";138;1
"Unit";"Marine";"Barracks";139;1
"Unit";"Marine";"Barracks";140;1
"Unit";"Marine";"Barracks";141;1
"Unit";"Medivac";"Starport";142;2
"Unit";"Medivac";"Starport";144;2
"Unit";"Marine";"Barracks";146;1
"Unit";"Marine";"Barracks";147;1
"Unit";"Marine";"Barracks";148;1
"Unit";"Marine";"Barracks";149;1
"Unit";"Marine";"Barracks";150;1
"Unit";"Marine";"Barracks";151;1
"Upgrade";"TerranInfantryWeaponsLevel2";"EngineeringBay";152;0
"Unit";"Marauder";"Barracks";152;2
"Unit";"Marine";"Barracks";154;1
"Unit";"Marine";"Barracks";155;1
"Unit";"Marine";"Barracks";156;1
"Unit";"Marine";"Barracks";157;1
"Unit";"Marine";"Barracks";158;1
"Unit";"Marine";"Barracks";159;1
"Building";"Barracks";NA;160;0
"Building";"Refinery";NA;160;0
"Unit";"Marine";"Barracks";160;1
"Unit";"Marine";"Barracks";161;1
"Unit";"Marine";"Barracks";162;1
"Building";"CommandCenter";NA;163;0
"Unit";"Marine";"Barracks";163;1
"Unit";"Marine";"Barracks";164;1
"Unit";"Marine";"Barracks";165;1
"Unit";"Marine";"Barracks";166;1
"Unit";"Marauder";"Barracks";167;2
"Unit";"Marine";"Barracks";169;1
"Unit";"Marine";"Barracks";170;1
"Unit";"Marine";"Barracks";171;1
"Unit";"Marine";"Barracks";172;1
"Unit";"Marine";"Barracks";173;1
"Unit";"Marine";"Barracks";174;1
"Unit";"Marine";"Barracks";175;1
"Unit";"Medivac";"Starport";176;2
"Unit";"Medivac";"Starport";178;2
"Building";"Factory";NA;180;0
"Unit";"Marine";"Barracks";180;1
"Unit";"Marine";"Barracks";181;1
"Unit";"Marine";"Barracks";182;1
"Unit";"Marine";"Barracks";183;1
"Unit";"Marine";"Barracks";184;1
"Unit";"Marine";"Barracks";185;1
"Unit";"Marine";"Barracks";186;1
"Unit";"Marine";"Barracks";187;1
"Unit";"Marine";"Barracks";188;1
"Unit";"Marine";"Barracks";189;1
"Building";"SensorTower";NA;193;0
"Unit";"Marine";"Barracks";193;1
"Unit";"Marine";"Barracks";194;1
"Unit";"Marine";"Barracks";195;1
"Unit";"Marine";"Barracks";196;1
"Building";"BarracksReactor";NA;197;0
"Unit";"Marine";"Barracks";197;1
"Unit";"Marine";"Barracks";198;1
"Unit";"Marine";"Barracks";199;1
"Unit";"Marauder";"Barracks";200;2
"Unit";"Marauder";"Barracks";202;2
"Unit";"Marine";"Barracks";204;1
"Unit";"Marine";"Barracks";205;1
"Building";"FactoryTechLab";NA;206;0
"Unit";"Marine";"Barracks";206;1
"Unit";"Marine";"Barracks";207;1
"Building";"MissileTurret";NA;208;0
"Unit";"Marine";"Barracks";208;1
"Unit";"Marine";"Barracks";209;1
"Unit";"Marine";"Barracks";210;1
"Unit";"Marine";"Barracks";211;1
"Unit";"Marine";"Barracks";212;1
"Unit";"Marine";"Barracks";213;1
"Unit";"Marine";"Barracks";214;1
"Unit";"Marauder";"Barracks";215;2
"Unit";"Marine";"Barracks";217;1
"Building";"MissileTurret";NA;218;0
"Unit";"Marine";"Barracks";218;1
"Unit";"Marine";"Barracks";219;1
"Unit";"Marine";"Barracks";220;1
"Unit";"Marauder";"Barracks";221;2
"Unit";"Marauder";"Barracks";223;2
"Unit";"Marine";"Barracks";225;1
"Unit";"Marine";"Barracks";226;1
"Unit";"Marine";"Barracks";227;1
"Unit";"Medivac";"Starport";228;2
"Unit";"Medivac";"Starport";230;2
"Unit";"Marine";"Barracks";232;1
"Unit";"Marine";"Barracks";233;1
"Unit";"Marine";"Barracks";234;1
"Unit";"Marine";"Barracks";235;1
"Unit";"Marauder";"Barracks";236;2
"Unit";"Marine";"Barracks";238;1
"Unit";"Marine";"Barracks";239;1
"Unit";"Marine";"Barracks";240;1
"Unit";"Marine";"Barracks";241;1
"Unit";"Marine";"Barracks";242;1
"Unit";"Marine";"Barracks";243;1
"Unit";"Marine";"Barracks";244;1
"Unit";"Marauder";"Barracks";245;2
"Unit";"Thor";"Factory";247;6
"Unit";"Marauder";"Barracks";253;2
"Unit";"Marine";"Barracks";255;1
"Unit";"Marine";"Barracks";256;1
"Unit";"Marine";"Barracks";257;1
"Unit";"Marine";"Barracks";258;1
"Unit";"Marine";"Barracks";259;1
"Unit";"Marine";"Barracks";260;1
"Unit";"Marine";"Barracks";261;1
"Upgrade";"TerranInfantryWeaponsLevel3";"EngineeringBay";262;0
"Unit";"Marine";"Barracks";262;1
"Unit";"Marauder";"Barracks";263;2
"Unit";"Marine";"Barracks";265;1
"Unit";"Marine";"Barracks";266;1
"Unit";"Marauder";"Barracks";267;2
"Unit";"Marine";"Barracks";269;1
"Unit";"Marine";"Barracks";270;1
"Unit";"Marine";"Barracks";271;1
"Unit";"Marine";"Barracks";272;1
"Unit";"Marine";"Barracks";273;1
"Unit";"Marine";"Barracks";274;1
"Unit";"Marine";"Barracks";275;1
"Unit";"Marine";"Barracks";276;1
"Unit";"Marine";"Barracks";277;1
"Unit";"Marine";"Barracks";278;1
"Unit";"Marauder";"Barracks";279;2
"Unit";"Marauder";"Barracks";281;2
"Upgrade";"TerranVehicleWeaponsLevel1";"Armory";283;0
"Unit";"Medivac";"Starport";283;2
"Unit";"Medivac";"Starport";285;2
"Unit";"Marine";"Barracks";287;1
"Unit";"Marine";"Barracks";288;1
"Unit";"Marine";"Barracks";289;1
"Unit";"Marine";"Barracks";290;1
"Unit";"Marine";"Barracks";291;1
"Unit";"Marauder";"Barracks";292;2
"Unit";"Marauder";"Barracks";294;2
"Unit";"Thor";"Factory";296;6
"Unit";"Marine";"Barracks";302;1
"Unit";"Marine";"Barracks";303;1
"Unit";"Marine";"Barracks";304;1
"Unit";"Marine";"Barracks";305;1
"Unit";"Marine";"Barracks";306;1
"Unit";"Marine";"Barracks";307;1
"Building";"MissileTurret";NA;308;0
"Building";"MissileTurret";NA;308;0
"Building";"MissileTurret";NA;308;0
"Unit";"Marine";"Barracks";308;1
"Unit";"Marine";"Barracks";309;1
"Unit";"Marine";"Barracks";310;1
"Building";"CommandCenter";NA;311;0
"Unit";"Marine";"Barracks";311;1
"Unit";"Marine";"Barracks";312;1
"Unit";"Marine";"Barracks";313;1
"Unit";"Medivac";"Starport";314;2
"Unit";"Marine";"Barracks";316;1
"Unit";"Medivac";"Starport";317;2
"Unit";"Marauder";"Barracks";322;2
"Unit";"Marine";"Barracks";324;1
"Unit";"Marine";"Barracks";325;1
"Unit";"Marine";"Barracks";326;1
"Unit";"Marine";"Barracks";328;1
"Unit";"Marauder";"Barracks";329;2
"Unit";"Marine";"Barracks";331;1
"Unit";"Marine";"Barracks";332;1
"Unit";"Marine";"Barracks";333;1
"Unit";"Marauder";"Barracks";334;2
"Building";"FactoryReactor";NA;336;0
"Unit";"Marine";"Barracks";336;1
"Unit";"Marine";"Barracks";337;1
"Unit";"Marauder";"Barracks";338;2
"Unit";"Marine";"Barracks";340;1
"Unit";"Marauder";"Barracks";341;2
"Unit";"Marauder";"Barracks";343;2
"Unit";"Marauder";"Barracks";345;2
"Unit";"Marine";"Barracks";347;1
"Unit";"Marine";"Barracks";348;1
"Unit";"Marine";"Barracks";349;1
"Unit";"Marine";"Barracks";350;1
"Unit";"Marine";"Barracks";351;1
"Unit";"Marine";"Barracks";352;1
"Unit";"Marine";"Barracks";353;1
"Unit";"Marine";"Barracks";354;1
"Unit";"Medivac";"Starport";355;2
"Unit";"Medivac";"Starport";357;2
"Unit";"Thor";"Factory";359;6
"Unit";"Marine";"Barracks";365;1
"Unit";"Marauder";"Barracks";366;2
"Unit";"Marine";"Barracks";368;1
"Unit";"Marauder";"Barracks";369;2
"Building";"EngineeringBay";NA;371;0
"Unit";"Marine";"Barracks";374;1
"Unit";"Marine";"Barracks";375;1
"Unit";"Marine";"Barracks";376;1
"Unit";"Marine";"Barracks";377;1
"Unit";"Marine";"Barracks";378;1
"Unit";"Marine";"Barracks";379;1
"Unit";"Marine";"Barracks";380;1
"Unit";"Marine";"Barracks";381;1
"Unit";"Marine";"Barracks";382;1
"Unit";"Marine";"Barracks";383;1
"Unit";"Marauder";"Barracks";384;2
"Unit";"Marauder";"Barracks";387;2
"Unit";"Marine";"Barracks";389;1
"Unit";"Marine";"Barracks";390;1
"Unit";"Marine";"Barracks";391;1
"Unit";"Marine";"Barracks";392;1
"Unit";"Thor";"Factory";395;6
"Unit";"Marauder";"Barracks";401;2
"Unit";"Marine";"Barracks";403;1
"Unit";"Marine";"Barracks";404;1
"Unit";"Marine";"Barracks";405;1
"Unit";"Marine";"Barracks";406;1
"Unit";"Marine";"Barracks";407;1
"Unit";"Marauder";"Barracks";408;2
"Unit";"Medivac";"Starport";410;2
"Unit";"Medivac";"Starport";412;2
"Unit";"Marine";"Barracks";414;1
"Building";"MissileTurret";NA;415;0
"Building";"MissileTurret";NA;415;0
"Unit";"Marauder";"Barracks";415;2
"Unit";"Marine";"Barracks";417;1
"Building";"MissileTurret";NA;418;0
"Unit";"Marine";"Barracks";418;1
"Unit";"Marine";"Barracks";419;1
"Unit";"Marauder";"Barracks";420;2
"Unit";"Marine";"Barracks";422;1
"Unit";"Marine";"Barracks";423;1
"Unit";"Marine";"Barracks";424;1
"Unit";"Marauder";"Barracks";425;2
"Unit";"Marine";"Barracks";427;1
"Unit";"Marine";"Barracks";428;1
"Upgrade";"SprayTerran";NA;429;0
"Upgrade";"SprayTerran";NA;429;0
"Upgrade";"SprayTerran";NA;429;0
"Upgrade";"SprayTerran";NA;429;0
"Upgrade";"TerranInfantryArmorsLevel1";NA;429;0
"Upgrade";"ShieldWall";NA;429;0
"Upgrade";"SprayTerran";NA;429;0
"Upgrade";"SprayTerran";NA;429;0
"Upgrade";"TerranInfantryArmorsLevel2";NA;429;0
"Upgrade";"PunisherGrenades";NA;429;0
"Upgrade";"SprayTerran";NA;429;0
"Upgrade";"DrillClaws";NA;429;0
"Upgrade";"SprayTerran";NA;429;0
"Upgrade";"TerranInfantryArmorsLevel3";NA;429;0
"Upgrade";"SprayTerran";NA;429;0
