"Type";"UnitName";"OnBuilding";"TotalSupply";"Supply"
"Unit";"SCV";"Command Center";12;1
"Unit";"SCV";"Command Center";12;1
"Unit";"SCV";"Command Center";13;1
"Building";"SupplyDepot";NA;13;0
"Unit";"SCV";"Command Center";15;1
"Unit";"SCV";"Command Center";15;1
"Building";"Barracks";NA;15;0
"Building";"Refinery";NA;16;0
"Unit";"SCV";"Command Center";16;1
"Building";"Barracks";NA;15;0
"Unit";"SCV";"Command Center";17;1
"Unit";"Marine";"Barracks";17;1
"Unit";"Marine";"Barracks";18;1
"Building";"SupplyDepot";NA;18;0
"Unit";"Marine";"Barracks";19;1
"Building";"Bunker";NA;18;0
"Unit";"Marine";"Barracks";20;1
"Building";"Bunker";NA;20;0
"Unit";"Marine";"Barracks";21;1
"Unit";"Marine";"Barracks";23;1
"Unit";"Marine";"Barracks";24;1
"Unit";"Marine";"Barracks";25;1
"Building";"Factory";NA;22;0
"Building";"Refinery";NA;25;0
"Unit";"SCV";"Command Center";27;1
"Building";"SupplyDepot";NA;27;0
"Unit";"Cyclone";"Factory";27;3
"Unit";"SCV";"Command Center";28;1
"Building";"Starport";NA;28;0
"Unit";"SCV";"Command Center";32;1
"Building";"SupplyDepot";NA;31;0
"Unit";"SCV";"Command Center";33;1
"Unit";"Cyclone";"Factory";32;3
"Building";"StarportTechLab";NA;32;0
"Unit";"Marine";"Barracks";34;1
"Unit";"Cyclone";"Factory";37;3
"Unit";"Marine";"Barracks";38;1
"Unit";"SCV";"Command Center";38;1
"Unit";"Marine";"Barracks";38;1
"Unit";"Banshee";"Starport";37;3
"Unit";"SCV";"Command Center";42;1
"Unit";"Marine";"Barracks";48;1
"Unit";"Marine";"Barracks";48;1
"Unit";"SCV";"Command Center";48;1
"Unit";"Cyclone";"Factory";48;3
"Unit";"SCV";"Command Center";51;1
"Unit";"Cyclone";"Factory";55;3
"Unit";"Marine";"Barracks";58;1
"Building";"SupplyDepot";NA;55;0
"Building";"SupplyDepot";NA;55;0
"Unit";"Banshee";"Starport";58;3
"Unit";"SCV";"Command Center";59;1
"Unit";"Marine";"Barracks";59;1
"Unit";"SCV";"Command Center";64;1
"Building";"FactoryTechLab";NA;65;0
"Unit";"SCV";"Command Center";65;1
"Unit";"Marine";"Barracks";65;1
"Unit";"Marine";"Barracks";65;1
"Unit";"SCV";"Command Center";66;1
"Unit";"SCV";"Command Center";69;1
"Unit";"Raven";"Starport";65;2
"Unit";"SCV";"Command Center";69;1
"Building";"SupplyDepot";NA;69;0
"Unit";"SCV";"Command Center";72;1
"Unit";"Marine";"Barracks";74;1
"Unit";"Marine";"Barracks";74;1
"Unit";"Marine";"Barracks";74;1
"Unit";"Raven";"Starport";74;2
"Unit";"SCV";"Command Center";79;1
"Unit";"SCV";"Command Center";79;1
"Unit";"SCV";"Command Center";80;1
"Unit";"SCV";"Command Center";81;1
"Unit";"Marine";"Barracks";82;1
"Unit";"Marine";"Barracks";82;1
"Unit";"SCV";"Command Center";83;1
"Unit";"Raven";"Starport";80;2
"Unit";"SCV";"Command Center";88;1
"Building";"CommandCenter";NA;79;0
"Building";"BarracksTechLab";NA;88;0
"Unit";"SCV";"Command Center";88;1
"Building";"Barracks";NA;83;0
"Building";"Barracks";NA;83;0
"Building";"Barracks";NA;83;0
"Unit";"Marine";"Barracks";89;1
"Unit";"Marine";"Barracks";90;1
"Unit";"SCV";"Command Center";90;1
"Unit";"Marine";"Barracks";93;1
"Unit";"Marine";"Barracks";93;1
"Unit";"Marine";"Barracks";93;1
"Unit";"Marine";"Barracks";93;1
"Unit";"Marine";"Barracks";93;1
"Unit";"SCV";"Command Center";93;1
"Unit";"Medivac";"Starport";93;2
"Unit";"Marine";"Barracks";93;1
"Unit";"Marine";"Barracks";94;1
"Building";"Refinery";NA;93;0
"Unit";"Marine";"Barracks";98;1
"Unit";"SCV";"Command Center";99;1
"Unit";"SCV";"Command Center";104;1
"Unit";"Marine";"Barracks";105;1
"Unit";"Marine";"Barracks";105;1
"Unit";"Marine";"Barracks";105;1
"Unit";"Marine";"Barracks";105;1
"Unit";"Marine";"Barracks";105;1
"Unit";"Medivac";"Starport";105;2
"Unit";"Marine";"Barracks";106;1
"Unit";"SCV";"Command Center";111;1
"Unit";"Marine";"Barracks";107;1
"Unit";"Marine";"Barracks";108;1
"Unit";"Marine";"Barracks";109;1
"Unit";"Marine";"Barracks";110;1
"Building";"SupplyDepot";NA;111;0
"Building";"SupplyDepot";NA;111;0
"Building";"Refinery";NA;111;0
"Upgrade";"Stimpack";"TechLab";93;0
"Building";"SupplyDepot";NA;114;0
"Unit";"SCV";"Command Center";119;1
"Unit";"Marine";"Barracks";119;1
"Unit";"Marine";"Barracks";119;1
"Unit";"Marine";"Barracks";119;1
"Unit";"Marine";"Barracks";119;1
"Unit";"Marine";"Barracks";119;1
"Unit";"Marine";"Barracks";120;1
"Unit";"Marine";"Barracks";121;1
"Unit";"Marine";"Barracks";122;1
"Unit";"Marine";"Barracks";123;1
"Unit";"Marine";"Barracks";129;1
"Unit";"Marine";"Barracks";129;1
"Unit";"Marine";"Barracks";129;1
"Unit";"Marine";"Barracks";129;1
"Unit";"Marauder";"Barracks";129;2
"Unit";"Medivac";"Starport";129;2
"Unit";"Marine";"Barracks";129;1
"Unit";"Marine";"Barracks";135;1
"Unit";"Marine";"Barracks";135;1
"Unit";"Marine";"Barracks";135;1
"Unit";"Marine";"Barracks";135;1
"Unit";"Marine";"Barracks";137;1
"Unit";"Marine";"Barracks";138;1
"Unit";"Marine";"Barracks";139;1
"Unit";"Medivac";"Starport";138;2
"Unit";"Marine";"Barracks";145;1
"Unit";"Marine";"Barracks";145;1
