"Type";"UnitName";"OnBuilding";"TotalSupply";"Supply"
"Unit";"SCV";"Command Center";12;1
"Unit";"SCV";"Command Center";12;1
"Unit";"SCV";"Command Center";13;1
"Building";"SupplyDepot";NA;13;0
"Unit";"SCV";"Command Center";15;1
"Building";"Refinery";NA;15;0
"Unit";"SCV";"Command Center";15;1
"Unit";"SCV";"Command Center";16;1
"Unit";"SCV";"Command Center";17;1
"Building";"Barracks";NA;15;0
"Unit";"Marine";"Barracks";19;1
"Unit";"Marine";"Barracks";19;1
"Unit";"SCV";"Command Center";20;1
"Unit";"SCV";"Command Center";22;1
"Building";"SupplyDepot";NA;22;0
"Building";"BarracksReactor";NA;21;0
"Building";"Factory";NA;20;0
"Building";"Refinery";NA;23;0
"Unit";"SCV";"Command Center";23;1
"Building";"CommandCenter";NA;19;0
"Unit";"SCV";"Command Center";23;1
"Unit";"Marine";"Barracks";24;1
"Unit";"Hellion";"Factory";24;2
"Unit";"Hellion";"Factory";24;2
"Unit";"SCV";"Command Center";24;1
"Unit";"Hellion";"Factory";31;2
"Building";"Starport";NA;25;0
"Unit";"Hellion";"Factory";31;2
"Unit";"Marine";"Barracks";31;1
"Unit";"SCV";"Command Center";35;1
"Unit";"SCV";"Command Center";35;1
"Building";"Armory";NA;26;0
"Unit";"Hellion";"Factory";31;2
"Unit";"Hellion";"Factory";33;2
"Unit";"Medivac";"Starport";33;2
"Building";"SupplyDepot";NA;36;0
"Unit";"SCV";"Command Center";40;1
"Unit";"SCV";"Command Center";40;1
"Unit";"Hellion";"Factory";38;2
"Building";"SupplyDepot";NA;40;0
"Unit";"SCV";"Command Center";44;1
"Unit";"SCV";"Command Center";44;1
"Unit";"SCV";"Command Center";48;1
"Unit";"SCV";"Command Center";48;1
"Unit";"Hellion";"Factory";48;2
"Unit";"Hellion";"Factory";48;2
"Unit";"SCV";"Command Center";50;1
"Unit";"SCV";"Command Center";56;1
"Unit";"SCV";"Command Center";56;1
"Unit";"Liberator";"Starport";50;3
"Unit";"SCV";"Command Center";57;1
"Unit";"Hellion";"Factory";57;2
"Unit";"Hellion";"Factory";57;2
"Building";"SupplyDepot";NA;57;0
"Unit";"SCV";"Command Center";67;1
"Unit";"SCV";"Command Center";67;1
"Building";"Factory";NA;57;0
"Unit";"SCV";"Command Center";67;1
"Building";"Refinery";NA;67;0
"Building";"Factory";NA;59;0
"Unit";"SCV";"Command Center";70;1
"Unit";"SCV";"Command Center";70;1
"Building";"FactoryTechLab";NA;69;0
"Building";"SupplyDepot";NA;70;0
"Building";"SupplyDepot";NA;70;0
"Unit";"Marine";"Barracks";70;1
"Building";"Bunker";NA;69;0
"Building";"FactoryTechLab";NA;70;0
"Building";"Bunker";NA;70;0
"Unit";"Liberator";"Starport";69;3
"Upgrade";"TerranVehicleWeaponsLevel1";"Armory";59;0
"Building";"SupplyDepot";NA;72;0
"Unit";"SCV";"Command Center";76;1
"Unit";"SCV";"Command Center";76;1
"Unit";"Hellion";"Factory";73;2
"Unit";"Hellion";"Factory";73;2
"Building";"Refinery";NA;76;0
"Unit";"Hellion";"Factory";78;2
"Unit";"Hellion";"Factory";80;2
"Unit";"Medivac";"Starport";82;2
"Building";"SupplyDepot";NA;82;0
"Building";"SupplyDepot";NA;82;0
"Unit";"Hellion";"Factory";82;2
"Unit";"Hellion";"Factory";84;2
"Building";"SupplyDepot";NA;86;0
"Building";"SupplyDepot";NA;86;0
"Building";"CommandCenter";NA;76;0
"Building";"SupplyDepot";NA;92;0
"Building";"SupplyDepot";NA;92;0
"Unit";"SCV";"Command Center";92;1
"Unit";"SCV";"Command Center";92;1
"Unit";"Thor";"Factory";92;6
"Unit";"Thor";"Factory";92;6
"Unit";"Hellion";"Factory";92;2
"Unit";"Hellion";"Factory";92;2
"Building";"SupplyDepot";NA;94;0
"Unit";"Hellion";"Factory";106;2
"Unit";"Hellion";"Factory";108;2
"Building";"SupplyDepot";NA;110;0
"Building";"SupplyDepot";NA;110;0
"Unit";"SCV";"Command Center";110;1
"Unit";"SCV";"Command Center";110;1
"Upgrade";"TerranVehicleWeaponsLevel2";"Armory";88;0
"Building";"Armory";NA;94;0
"Unit";"SCV";"Command Center";114;1
"Unit";"SCV";"Command Center";115;1
"Unit";"Hellion";"Factory";110;2
"Unit";"Hellion";"Factory";112;2
"Building";"Factory";NA;110;0
"Building";"Factory";NA;110;0
"Building";"Refinery";NA;116;0
"Unit";"Hellion";"Factory";118;2
"Unit";"Hellion";"Factory";120;2
"Building";"Refinery";NA;122;0
"Unit";"Hellion";"Factory";122;2
"Unit";"Hellion";"Factory";124;2
"Building";"FactoryTechLab";NA;130;0
"Building";"FactoryTechLab";NA;130;0
"Unit";"Hellion";"Factory";126;2
"Unit";"SCV";"Command Center";130;1
"Unit";"SCV";"Command Center";130;1
"Unit";"SCV";"Command Center";134;1
"Unit";"SCV";"Command Center";134;1
"Unit";"SCV";"Command Center";134;1
"Unit";"Hellion";"Factory";134;2
"Unit";"Hellion";"Factory";134;2
"Unit";"Hellion";"Factory";137;2
"Unit";"Hellion";"Factory";139;2
"Unit";"SCV";"Command Center";141;1
"Unit";"SCV";"Command Center";141;1
"Unit";"SCV";"Command Center";141;1
"Unit";"SCV";"Command Center";145;1
"Unit";"SCV";"Command Center";147;1
"Unit";"SCV";"Command Center";147;1
"Unit";"Hellion";"Factory";141;2
"Unit";"Hellion";"Factory";143;2
"Unit";"Hellion";"Factory";147;2
"Unit";"SCV";"Command Center";148;1
"Unit";"Hellion";"Factory";148;2
"Building";"StarportReactor";NA;141;0
"Unit";"Hellion";"Factory";151;2
"Unit";"Hellion";"Factory";151;2
"Unit";"Hellion";"Factory";153;2
"Unit";"Hellion";"Factory";155;2
"Unit";"Hellion";"Factory";158;2
"Unit";"Hellion";"Factory";160;2
"Building";"SupplyDepot";NA;160;0
"Building";"CommandCenter";NA;148;0
