"Type";"UnitName";"OnBuilding";"TotalSupply";"Supply"
"Unit";"SCV";"Command Center";12;1
"Unit";"SCV";"Command Center";12;1
"Unit";"SCV";"Command Center";13;1
"Building";"SupplyDepot";NA;13;0
"Unit";"SCV";"Command Center";15;1
"Unit";"SCV";"Command Center";15;1
"Building";"Barracks";NA;15;0
"Unit";"SCV";"Command Center";16;1
"Building";"Barracks";NA;15;0
"Unit";"Marine";"Barracks";17;1
"Unit";"Marine";"Barracks";18;1
"Unit";"Marine";"Barracks";19;1
"Building";"Bunker";NA;18;0
"Unit";"SCV";"Command Center";19;1
"Building";"Bunker";NA;19;0
"Unit";"Marine";"Barracks";19;1
"Building";"SupplyDepot";NA;20;0
"Building";"Bunker";NA;19;0
"Unit";"SCV";"Command Center";23;1
"Building";"Bunker";NA;21;0
"Unit";"Marine";"Barracks";23;1
"Unit";"Marine";"Barracks";23;1
"Building";"Refinery";NA;23;0
"Unit";"SCV";"Command Center";24;1
"Building";"SupplyDepot";NA;23;0
"Unit";"Marine";"Barracks";24;1
"Unit";"Marine";"Barracks";25;1
"Unit";"SCV";"Command Center";27;1
"Unit";"Marine";"Barracks";29;1
"Unit";"Marine";"Barracks";29;1
"Building";"Refinery";NA;28;0
"Unit";"Marine";"Barracks";32;1
"Unit";"Marine";"Barracks";32;1
"Unit";"SCV";"Command Center";34;1
"Unit";"Marine";"Barracks";32;1
"Unit";"Marine";"Barracks";33;1
"Unit";"SCV";"Command Center";34;1
"Unit";"SCV";"Command Center";37;1
"Unit";"SCV";"Command Center";38;1
"Building";"Factory";NA;34;0
"Building";"Factory";NA;37;0
"Unit";"SCV";"Command Center";40;1
"Building";"CommandCenter";NA;34;0
"Unit";"SCV";"Command Center";41;1
"Building";"FactoryReactor";NA;40;0
"Building";"Starport";NA;40;0
"Unit";"SCV";"Command Center";41;1
"Building";"SupplyDepot";NA;41;0
"Unit";"SCV";"Command Center";42;1
"Building";"FactoryReactor";NA;41;0
"Unit";"SCV";"Command Center";43;1
"Unit";"Cyclone";"Factory";43;3
"Unit";"Cyclone";"Factory";43;3
"Unit";"SCV";"Command Center";44;1
"Unit";"Marine";"Barracks";44;1
"Unit";"Hellion";"Factory";44;2
"Unit";"SCV";"Command Center";51;1
"Unit";"SCV";"Command Center";51;1
"Unit";"SCV";"Command Center";55;1
"Building";"SupplyDepot";NA;55;0
"Unit";"SCV";"Command Center";56;1
"Unit";"Marine";"Barracks";55;1
"Unit";"Marine";"Barracks";55;1
"Unit";"Cyclone";"Factory";55;3
"Building";"CommandCenter";NA;42;0
"Unit";"SCV";"Command Center";57;1
"Unit";"SCV";"Command Center";58;1
"Unit";"Marine";"Barracks";58;1
"Unit";"Marine";"Barracks";60;1
"Unit";"SCV";"Command Center";64;1
"Unit";"Hellion";"Factory";60;2
"Unit";"Hellion";"Factory";64;2
"Unit";"SCV";"Command Center";65;1
"Building";"SupplyDepot";NA;64;0
"Unit";"SCV";"Command Center";68;1
"Building";"Refinery";NA;66;0
"Unit";"Marine";"Barracks";71;1
"Unit";"Marine";"Barracks";71;1
"Building";"Refinery";NA;69;0
"Unit";"SCV";"Command Center";75;1
"Unit";"SCV";"Command Center";75;1
"Building";"SupplyDepot";NA;74;0
"Building";"SupplyDepot";NA;75;0
"Unit";"SCV";"Command Center";77;1
"Unit";"Hellion";"Factory";77;2
"Unit";"Hellion";"Factory";77;2
"Building";"Armory";NA;74;0
"Unit";"SCV";"Command Center";80;1
"Unit";"SCV";"Command Center";80;1
"Unit";"SCV";"Command Center";80;1
"Unit";"Medivac";"Starport";79;2
"Unit";"Marine";"Barracks";80;1
"Unit";"Marine";"Barracks";80;1
"Building";"SupplyDepot";NA;79;0
"Unit";"SCV";"Command Center";84;1
"Building";"EngineeringBay";NA;84;0
"Unit";"Cyclone";"Factory";84;3
"Building";"FactoryTechLab";NA;90;0
"Unit";"Marine";"Barracks";91;1
"Unit";"Marine";"Barracks";91;1
"Unit";"Hellion";"Factory";91;2
"Unit";"SCV";"Command Center";92;1
"Unit";"SCV";"Command Center";92;1
"Unit";"SCV";"Command Center";92;1
"Unit";"Medivac";"Starport";91;2
"Unit";"Marine";"Barracks";104;1
"Unit";"Marine";"Barracks";104;1
"Unit";"Hellion";"Factory";104;2
"Unit";"Hellion";"Factory";104;2
"Unit";"SCV";"Command Center";104;1
"Unit";"SCV";"Command Center";104;1
"Unit";"SCV";"Command Center";104;1
"Building";"Factory";NA;97;0
"Building";"Factory";NA;97;0
"Building";"Armory";NA;95;0
"Building";"MissileTurret";NA;104;0
"Building";"MissileTurret";NA;106;0
"Building";"MissileTurret";NA;106;0
"Unit";"Marine";"Barracks";110;1
"Unit";"Marine";"Barracks";110;1
"Building";"SupplyDepot";NA;106;0
"Unit";"Liberator";"Starport";104;3
"Unit";"SCV";"Command Center";115;1
"Unit";"SCV";"Command Center";115;1
"Unit";"Hellion";"Factory";115;2
"Unit";"Hellion";"Factory";115;2
"Building";"FactoryTechLab";NA;118;0
"Building";"FactoryTechLab";NA;118;0
"Building";"SupplyDepot";NA;118;0
"Unit";"Marine";"Barracks";120;1
"Unit";"Marine";"Barracks";120;1
"Upgrade";"TerranVehicleWeaponsLevel1";"Armory";104;0
"Unit";"Hellion";"Factory";124;2
"Building";"Refinery";NA;126;0
"Building";"Refinery";NA;126;0
"Building";"SupplyDepot";NA;126;0
"Building";"SupplyDepot";NA;126;0
"Unit";"SCV";"Command Center";128;1
"Unit";"SCV";"Command Center";128;1
"Unit";"SCV";"Command Center";128;1
"Building";"SupplyDepot";NA;128;0
"Building";"MissileTurret";NA;128;0
"Unit";"Hellion";"Factory";128;2
"Unit";"SCV";"Command Center";131;1
"Unit";"SCV";"Command Center";131;1
"Unit";"SCV";"Command Center";131;1
"Building";"SupplyDepot";NA;128;0
"Unit";"Medivac";"Starport";128;2
"Unit";"Hellion";"Factory";131;2
"Unit";"SCV";"Command Center";133;1
"Unit";"SCV";"Command Center";134;1
"Unit";"SCV";"Command Center";134;1
"Unit";"Hellion";"Factory";136;2
"Building";"SupplyDepot";NA;136;0
"Unit";"Hellion";"Factory";145;2
"Unit";"Hellion";"Factory";145;2
"Unit";"Liberator";"Starport";145;3
"Upgrade";"TerranVehicleAndShipArmorsLevel1";"Armory";131;0
"Building";"CommandCenter";NA;136;0
"Building";"Starport";NA;145;0
"Building";"Starport";NA;145;0
"Unit";"Hellion";"Factory";152;2
"Unit";"Hellion";"Factory";152;2
"Building";"SupplyDepot";NA;152;0
"Building";"SupplyDepot";NA;152;0
"Building";"SupplyDepot";NA;152;0
"Upgrade";"TerranVehicleWeaponsLevel2";"Armory";138;0
"Building";"Starport";NA;152;0
"Building";"CommandCenter";NA;145;0
"Unit";"Hellion";"Factory";156;2
"Unit";"Hellion";"Factory";156;2
