"Type";"UnitName";"OnBuilding";"TotalSupply";"Supply"
"Unit";"SCV";"Command Center";12;1
"Unit";"SCV";"Command Center";13;1
"Unit";"SCV";"Command Center";13;1
"Building";"SupplyDepot";NA;14;0
"Building";"Refinery";NA;15;0
"Unit";"SCV";"Command Center";15;1
"Unit";"SCV";"Command Center";15;1
"Unit";"SCV";"Command Center";16;1
"Building";"Barracks";NA;15;0
"Unit";"SCV";"Command Center";17;1
"Unit";"Marine";"Barracks";19;1
"Unit";"Marine";"Barracks";19;1
"Unit";"SCV";"Command Center";20;1
"Unit";"SCV";"Command Center";21;1
"Building";"Factory";NA;20;0
"Building";"Refinery";NA;22;0
"Building";"BarracksReactor";NA;21;0
"Building";"CommandCenter";NA;19;0
"Unit";"SCV";"Command Center";23;1
"Unit";"Marine";"Barracks";23;1
"Unit";"Hellion";"Factory";23;2
"Unit";"Hellion";"Factory";23;2
"Unit";"SCV";"Command Center";23;1
"Building";"Starport";NA;23;0
"Unit";"SCV";"Command Center";29;1
"Unit";"Hellion";"Factory";25;2
"Unit";"Hellion";"Factory";27;2
"Unit";"Marine";"Barracks";30;1
"Unit";"SCV";"Command Center";30;1
"Unit";"SCV";"Command Center";30;1
"Unit";"Medivac";"Starport";31;2
"Building";"SupplyDepot";NA;38;0
"Building";"Armory";NA;30;0
"Unit";"SCV";"Command Center";40;1
"Unit";"SCV";"Command Center";40;1
"Building";"SupplyDepot";NA;38;0
"Unit";"Marine";"Barracks";40;1
"Unit";"Hellion";"Factory";40;2
"Unit";"Hellion";"Factory";40;2
"Unit";"SCV";"Command Center";40;1
"Unit";"SCV";"Command Center";42;1
"Building";"SupplyDepot";NA;40;0
"Unit";"Marine";"Barracks";42;1
"Unit";"SCV";"Command Center";47;1
"Unit";"SCV";"Command Center";48;1
"Unit";"Hellion";"Factory";43;2
"Unit";"Hellion";"Factory";43;2
"Unit";"SCV";"Command Center";50;1
"Unit";"SCV";"Command Center";51;1
"Unit";"Marine";"Barracks";49;1
"Unit";"SCV";"Command Center";56;1
"Unit";"SCV";"Command Center";57;1
"Unit";"SCV";"Command Center";59;1
"Unit";"SCV";"Command Center";60;1
"Building";"Refinery";NA;61;0
"Building";"Refinery";NA;61;0
"Unit";"SCV";"Command Center";61;1
"Building";"SupplyDepot";NA;61;0
"Building";"SupplyDepot";NA;63;0
"Unit";"SCV";"Command Center";64;1
"Unit";"SCV";"Command Center";64;1
"Building";"Factory";NA;61;0
"Building";"Factory";NA;61;0
"Unit";"Liberator";"Starport";61;3
"Unit";"Liberator";"Starport";61;3
"Building";"SupplyDepot";NA;64;0
"Building";"FactoryReactor";NA;63;0
"Unit";"SCV";"Command Center";64;1
"Unit";"SCV";"Command Center";64;1
"Building";"SupplyDepot";NA;64;0
"Building";"SupplyDepot";NA;64;0
"Building";"FactoryTechLab";NA;66;0
"Building";"SupplyDepot";NA;66;0
"Unit";"SCV";"Command Center";72;1
"Unit";"SCV";"Command Center";72;1
"Building";"FactoryTechLab";NA;66;0
"Upgrade";"TerranVehicleWeaponsLevel1";"Armory";56;0
"Unit";"Hellion";"Factory";74;2
"Unit";"Hellion";"Factory";74;2
"Unit";"SCV";"Command Center";74;1
"Unit";"SCV";"Command Center";74;1
"Unit";"SCV";"Command Center";80;1
"Unit";"SCV";"Command Center";80;1
"Unit";"SCV";"Command Center";82;1
"Unit";"SCV";"Command Center";82;1
"Building";"SupplyDepot";NA;82;0
"Unit";"Hellion";"Factory";82;2
"Unit";"Hellion";"Factory";82;2
"Unit";"SCV";"Command Center";90;1
"Unit";"SCV";"Command Center";90;1
"Unit";"Hellion";"Factory";90;2
"Unit";"Hellion";"Factory";90;2
"Unit";"SCV";"Command Center";90;1
"Unit";"SCV";"Command Center";91;1
"Building";"CommandCenter";NA;82;0
"Unit";"SCV";"Command Center";96;1
"Unit";"SCV";"Command Center";97;1
"Unit";"Hellion";"Factory";92;2
"Unit";"Hellion";"Factory";94;2
"Building";"Refinery";NA;98;0
"Building";"Refinery";NA;98;0
"Unit";"SCV";"Command Center";98;1
"Unit";"SCV";"Command Center";99;1
"Building";"Factory";NA;90;0
"Building";"Factory";NA;90;0
"Unit";"Medivac";"Starport";92;2
"Unit";"Medivac";"Starport";96;2
"Unit";"SCV";"Command Center";104;1
"Unit";"SCV";"Command Center";105;1
"Unit";"Hellion";"Factory";100;2
"Building";"FactoryTechLab";NA;106;0
"Building";"FactoryTechLab";NA;106;0
"Building";"SupplyDepot";NA;106;0
"Unit";"Hellion";"Factory";106;2
"Unit";"SCV";"Command Center";110;1
"Unit";"SCV";"Command Center";111;1
"Unit";"Thor";"Factory";98;6
"Unit";"Thor";"Factory";100;6
"Unit";"SCV";"Command Center";116;1
"Unit";"Hellion";"Factory";112;2
"Unit";"SCV";"Command Center";130;1
"Upgrade";"TerranVehicleWeaponsLevel2";"Armory";90;0
"Unit";"SCV";"Command Center";130;1
"Unit";"SCV";"Command Center";133;1
"Unit";"Hellion";"Factory";131;2
"Unit";"Hellion";"Factory";133;2
"Unit";"Hellion";"Factory";133;2
"Building";"SupplyDepot";NA;133;0
"Building";"SupplyDepot";NA;133;0
"Building";"SupplyDepot";NA;133;0
"Unit";"Hellion";"Factory";136;2
"Unit";"Hellion";"Factory";138;2
"Unit";"Hellion";"Factory";142;2
"Unit";"SCV";"Command Center";146;1
"Unit";"Hellion";"Factory";142;2
"Unit";"Hellion";"Factory";144;2
"Unit";"Hellion";"Factory";148;2
"Unit";"Hellion";"Factory";149;2
"Unit";"Hellion";"Factory";149;2
"Unit";"Hellion";"Factory";151;2
"Building";"SupplyDepot";NA;153;0
"Building";"SupplyDepot";NA;153;0
"Unit";"Hellion";"Factory";155;2
"Building";"Armory";NA;146;0
"Unit";"Hellion";"Factory";157;2
"Unit";"Hellion";"Factory";159;2
