"Type";"UnitName";"OnBuilding";"TotalSupply";"Supply"
"Unit";"SCV";"Command Center";12;1
"Unit";"SCV";"Command Center";12;1
"Unit";"SCV";"Command Center";13;1
"Building";"SupplyDepot";NA;13;0
"Unit";"SCV";"Command Center";15;1
"Unit";"SCV";"Command Center";15;1
"Building";"Refinery";NA;15;0
"Unit";"SCV";"Command Center";16;1
"Building";"Barracks";NA;15;0
"Unit";"SCV";"Command Center";17;1
"Unit";"Reaper";"Barracks";19;1
"Unit";"SCV";"Command Center";19;1
"Building";"SupplyDepot";NA;19;0
"Unit";"Marine";"Barracks";19;1
"Unit";"SCV";"Command Center";21;1
"Unit";"SCV";"Command Center";22;1
"Building";"Refinery";NA;23;0
"Unit";"SCV";"Command Center";24;1
"Building";"CommandCenter";NA;19;0
"Building";"BarracksReactor";NA;23;0
"Building";"Factory";NA;21;0
"Unit";"SCV";"Command Center";24;1
"Unit";"SCV";"Command Center";26;1
"Unit";"SCV";"Command Center";26;1
"Building";"BarracksTechLab";NA;26;0
"Unit";"Hellion";"Factory";26;2
"Unit";"Hellion";"Factory";26;2
"Unit";"SCV";"Command Center";27;1
"Unit";"SCV";"Command Center";28;1
"Building";"Starport";NA;26;0
"Building";"SupplyDepot";NA;28;0
"Unit";"SCV";"Command Center";32;1
"Unit";"SCV";"Command Center";33;1
"Unit";"Hellion";"Factory";32;2
"Unit";"Hellion";"Factory";32;2
"Building";"BarracksTechLab";NA;33;0
"Unit";"SCV";"Command Center";35;1
"Unit";"SCV";"Command Center";35;1
"Unit";"SCV";"Command Center";41;1
"Building";"SupplyDepot";NA;36;0
"Unit";"SCV";"Command Center";41;1
"Unit";"Marine";"Barracks";42;1
"Unit";"Marine";"Barracks";42;1
"Unit";"SCV";"Command Center";43;1
"Unit";"SCV";"Command Center";44;1
"Unit";"SCV";"Command Center";46;1
"Unit";"Marine";"Barracks";46;1
"Unit";"Marine";"Barracks";46;1
"Unit";"SCV";"Command Center";47;1
"Unit";"SCV";"Command Center";48;1
"Unit";"SCV";"Command Center";53;1
"Unit";"Raven";"Starport";46;2
"Unit";"SCV";"Command Center";53;1
"Building";"Refinery";NA;53;0
"Unit";"Marine";"Barracks";53;1
"Building";"EngineeringBay";NA;53;0
"Building";"EngineeringBay";NA;53;0
"Building";"Refinery";NA;53;0
"Building";"CommandCenter";NA;44;0
"Building";"FactoryReactor";NA;53;0
"Building";"Barracks";NA;53;0
"Unit";"SCV";"Command Center";58;1
"Unit";"SCV";"Command Center";58;1
"Building";"SupplyDepot";NA;58;0
"Building";"SupplyDepot";NA;58;0
"Building";"Barracks";NA;53;0
"Unit";"SCV";"Command Center";60;1
"Unit";"SCV";"Command Center";60;1
"Unit";"Marine";"Barracks";60;1
"Unit";"Marine";"Barracks";60;1
"Unit";"Marine";"Barracks";60;1
"Unit";"Marine";"Barracks";60;1
"Unit";"SCV";"Command Center";60;1
"Unit";"Marine";"Barracks";60;1
"Building";"StarportReactor";NA;58;0
"Unit";"SCV";"Command Center";62;1
"Building";"Barracks";NA;58;0
"Building";"Barracks";NA;58;0
"Unit";"Marine";"Barracks";68;1
"Unit";"Marine";"Barracks";68;1
"Unit";"Marine";"Barracks";68;1
"Unit";"SCV";"Command Center";69;1
"Unit";"SCV";"Command Center";72;1
"Unit";"SCV";"Command Center";72;1
"Unit";"Marine";"Barracks";72;1
"Unit";"Marine";"Barracks";72;1
"Unit";"Marine";"Barracks";72;1
"Unit";"Marine";"Barracks";72;1
"Unit";"Marine";"Barracks";72;1
"Unit";"SCV";"Command Center";73;1
"Upgrade";"Stimpack";"TechLab";58;0
"Building";"BarracksReactor";NA;69;0
"Building";"BarracksReactor";NA;69;0
"Unit";"SCV";"Command Center";73;1
"Building";"SupplyDepot";NA;73;0
"Unit";"SCV";"Command Center";75;1
"Building";"SupplyDepot";NA;73;0
"Unit";"Medivac";"Starport";72;2
"Unit";"Medivac";"Starport";72;2
"Building";"SupplyDepot";NA;75;0
"Unit";"Marine";"Barracks";81;1
"Unit";"Marine";"Barracks";81;1
"Unit";"Marine";"Barracks";81;1
"Unit";"Marine";"Barracks";81;1
"Unit";"SCV";"Command Center";87;1
"Unit";"SCV";"Command Center";87;1
"Building";"SupplyDepot";NA;81;0
"Unit";"SCV";"Command Center";87;1
"Unit";"Marine";"Barracks";82;1
"Unit";"Marine";"Barracks";82;1
"Unit";"Marine";"Barracks";82;1
"Unit";"Marine";"Barracks";82;1
"Unit";"Marine";"Barracks";82;1
"Upgrade";"TerranInfantryWeaponsLevel1";"EngineeringBay";62;0
"Upgrade";"TerranInfantryArmorsLevel1";"EngineeringBay";62;0
"Building";"SupplyDepot";NA;87;0
"Building";"SupplyDepot";NA;87;0
"Unit";"SCV";"Command Center";91;1
"Building";"Armory";NA;73;0
"Unit";"SCV";"Command Center";99;1
"Unit";"SCV";"Command Center";99;1
"Unit";"SCV";"Command Center";100;1
"Unit";"SCV";"Command Center";100;1
"Unit";"SCV";"Command Center";101;1
"Unit";"Marine";"Barracks";100;1
"Unit";"Marine";"Barracks";100;1
"Building";"SupplyDepot";NA;100;0
"Unit";"SCV";"Command Center";105;1
"Unit";"Marine";"Barracks";102;1
"Unit";"Marine";"Barracks";102;1
"Unit";"Marine";"Barracks";102;1
"Unit";"Marine";"Barracks";102;1
"Unit";"Marine";"Barracks";102;1
"Unit";"Marine";"Barracks";102;1
"Unit";"SCV";"Command Center";114;1
"Unit";"SCV";"Command Center";114;1
"Unit";"SCV";"Command Center";114;1
"Unit";"Marine";"Barracks";107;1
"Unit";"Marine";"Barracks";114;1
"Unit";"Marine";"Barracks";114;1
"Unit";"Marine";"Barracks";114;1
"Unit";"Marine";"Barracks";114;1
"Unit";"Marine";"Barracks";114;1
"Unit";"Marine";"Barracks";114;1
"Unit";"SCV";"Command Center";114;1
"Unit";"SCV";"Command Center";115;1
"Unit";"Medivac";"Starport";107;2
"Unit";"SCV";"Command Center";118;1
"Unit";"Medivac";"Starport";107;2
"Building";"CommandCenter";NA;99;0
"Building";"Refinery";NA;117;0
"Unit";"SCV";"Command Center";126;1
"Unit";"SCV";"Command Center";126;1
"Building";"Refinery";NA;126;0
"Unit";"Marine";"Barracks";131;1
"Unit";"Marine";"Barracks";131;1
"Unit";"Marine";"Barracks";131;1
"Unit";"Marine";"Barracks";131;1
"Unit";"Marine";"Barracks";131;1
"Unit";"Marauder";"Barracks";131;2
"Building";"SupplyDepot";NA;99;0
"Unit";"Marine";"Barracks";133;1
"Unit";"Marine";"Barracks";133;1
"Unit";"Marine";"Barracks";133;1
"Unit";"Marine";"Barracks";136;1
"Building";"Barracks";NA;124;0
"Building";"Factory";NA;131;0
"Building";"Barracks";NA;126;0
"Unit";"Marine";"Barracks";140;1
"Unit";"Marine";"Barracks";140;1
"Unit";"Marine";"Barracks";140;1
"Unit";"Marauder";"Barracks";138;2
"Unit";"SCV";"Command Center";144;1
"Unit";"Marine";"Barracks";140;1
"Unit";"Medivac";"Starport";138;2
"Unit";"Medivac";"Starport";138;2
"Unit";"Marine";"Barracks";140;1
"Unit";"SCV";"Command Center";149;1
"Building";"BarracksTechLab";NA;147;0
"Building";"BarracksTechLab";NA;149;0
"Building";"FactoryTechLab";NA;149;0
"Unit";"SCV";"Command Center";155;1
"Unit";"Marine";"Barracks";149;1
"Unit";"Marine";"Barracks";149;1
"Unit";"Marine";"Barracks";149;1
"Unit";"Marine";"Barracks";149;1
"Unit";"Marine";"Barracks";149;1
"Unit";"Marauder";"Barracks";147;2
"Unit";"SCV";"Command Center";155;1
"Unit";"SCV";"Command Center";157;1
"Unit";"SCV";"Command Center";166;1
"Unit";"Marine";"Barracks";165;1
"Unit";"Marine";"Barracks";166;1
"Unit";"Marine";"Barracks";166;1
"Unit";"Marine";"Barracks";166;1
"Unit";"Marine";"Barracks";166;1
"Unit";"Marine";"Barracks";166;1
"Unit";"Marine";"Barracks";166;1
"Unit";"Marine";"Barracks";166;1
"Unit";"Marauder";"Barracks";166;2
"Unit";"Marauder";"Barracks";166;2
"Unit";"Marauder";"Barracks";166;2
"Unit";"Marine";"Barracks";168;1
"Unit";"Marine";"Barracks";176;1
"Unit";"Medivac";"Starport";166;2
"Unit";"Marauder";"Barracks";176;2
"Unit";"Marauder";"Barracks";178;2
"Upgrade";"TerranInfantryWeaponsLevel2";"EngineeringBay";133;0
"Upgrade";"TerranInfantryArmorsLevel2";"EngineeringBay";133;0
"Unit";"Marine";"Barracks";182;1
"Unit";"Marine";"Barracks";182;1
"Unit";"SCV";"Command Center";186;1
"Unit";"Marine";"Barracks";183;1
"Unit";"Marauder";"Barracks";183;2
"Unit";"Marauder";"Barracks";186;2
"Unit";"Marauder";"Barracks";188;2
"Unit";"Marine";"Barracks";190;1
"Unit";"Marine";"Barracks";190;1
"Unit";"Marine";"Barracks";190;1
"Unit";"Marine";"Barracks";190;1
"Unit";"Marine";"Barracks";190;1
"Unit";"Marine";"Barracks";190;1
"Unit";"Marine";"Barracks";191;1
"Unit";"Marine";"Barracks";193;1
"Upgrade";"TerranVehicleAndShipArmorsLevel1";"Armory";156;0
"Unit";"Medivac";"Starport";190;2
"Unit";"Medivac";"Starport";190;2
"Unit";"Marauder";"Barracks";196;2
"Unit";"Marine";"Barracks";201;1
"Building";"Refinery";NA;208;0
"Building";"Refinery";NA;208;0
"Unit";"Marine";"Barracks";215;1
"Unit";"Marine";"Barracks";215;1
"Unit";"Marine";"Barracks";215;1
"Unit";"Marine";"Barracks";215;1
"Unit";"Marine";"Barracks";215;1
"Unit";"Marine";"Barracks";215;1
"Unit";"Marauder";"Barracks";215;2
"Unit";"Marauder";"Barracks";215;2
"Unit";"Marauder";"Barracks";215;2
"Unit";"Marine";"Barracks";218;1
"Unit";"Marine";"Barracks";219;1
"Unit";"Marine";"Barracks";219;1
"Unit";"Marine";"Barracks";219;1
"Unit";"Marine";"Barracks";219;1
"Unit";"Marine";"Barracks";219;1
"Unit";"Marine";"Barracks";219;1
"Unit";"Marine";"Barracks";220;1
"Unit";"Marauder";"Barracks";221;2
"Building";"Starport";NA;215;0
"Building";"Starport";NA;215;0
"Unit";"Marauder";"Barracks";223;2
"Unit";"Marauder";"Barracks";225;2
"Unit";"Marine";"Barracks";227;1
"Unit";"Marine";"Barracks";228;1
"Unit";"Marine";"Barracks";229;1
"Unit";"Marine";"Barracks";229;1
"Unit";"Marine";"Barracks";231;1
"Unit";"Marine";"Barracks";231;1
"Unit";"Marine";"Barracks";233;1
"Building";"FusionCore";NA;215;0
"Unit";"Marine";"Barracks";234;1
"Unit";"Marauder";"Barracks";235;2
"Unit";"Marauder";"Barracks";237;2
"Unit";"Marauder";"Barracks";239;2
"Unit";"Marine";"Barracks";241;1
"Unit";"Marine";"Barracks";242;1
"Unit";"Marine";"Barracks";243;1
"Unit";"Marine";"Barracks";243;1
"Unit";"Marine";"Barracks";245;1
"Unit";"Marine";"Barracks";245;1
"Unit";"Marine";"Barracks";248;1
"Unit";"Marine";"Barracks";248;1
"Unit";"Marauder";"Barracks";249;2
"Unit";"Marine";"Barracks";255;1
"Unit";"Marine";"Barracks";256;1
"Unit";"Marine";"Barracks";257;1
"Unit";"Marauder";"Barracks";251;2
"Unit";"Marauder";"Barracks";253;2
"Unit";"Liberator";"Starport";248;3
"Unit";"Liberator";"Starport";249;3
"Building";"StarportTechLab";NA;263;0
"Upgrade";"TerranShipWeaponsLevel1";"Armory";234;0
"Unit";"Marine";"Barracks";278;1
"Unit";"Marine";"Barracks";278;1
"Unit";"Marine";"Barracks";278;1
"Unit";"Marine";"Barracks";278;1
"Unit";"Marine";"Barracks";278;1
"Unit";"Marine";"Barracks";278;1
"Unit";"Liberator";"Starport";263;3
"Unit";"Marauder";"Barracks";278;2
"Unit";"Marauder";"Barracks";278;2
"Unit";"Marauder";"Barracks";278;2
"Unit";"Marine";"Barracks";278;1
"Unit";"Marine";"Barracks";278;1
"Unit";"Marine";"Barracks";278;1
"Unit";"Marine";"Barracks";279;1
"Unit";"Marine";"Barracks";280;1
"Unit";"Marine";"Barracks";281;1
"Unit";"Marine";"Barracks";282;1
"Unit";"Marine";"Barracks";283;1
"Unit";"Marauder";"Barracks";287;2
"Unit";"Marauder";"Barracks";289;2
"Unit";"Marauder";"Barracks";291;2
"Unit";"Liberator";"Starport";278;3
"Unit";"Liberator";"Starport";278;3
"Unit";"Liberator";"Starport";278;3
"Unit";"Marine";"Barracks";293;1
"Unit";"Marine";"Barracks";294;1
"Building";"CommandCenter";NA;263;0
"Upgrade";"TerranInfantryWeaponsLevel3";"EngineeringBay";241;0
"Upgrade";"TerranInfantryArmorsLevel3";"EngineeringBay";241;0
"Unit";"Liberator";"Starport";284;3
"Unit";"Marauder";"Barracks";301;2
"Unit";"Marine";"Barracks";318;1
"Unit";"Marine";"Barracks";318;1
"Unit";"Marine";"Barracks";318;1
"Unit";"Marine";"Barracks";318;1
"Unit";"Marine";"Barracks";318;1
"Unit";"Marauder";"Barracks";318;2
"Unit";"Marine";"Barracks";318;1
"Unit";"Marauder";"Barracks";318;2
"Unit";"Marine";"Barracks";318;1
"Unit";"Marine";"Barracks";318;1
"Unit";"Marine";"Barracks";323;1
"Unit";"Marauder";"Barracks";321;2
"Unit";"Marine";"Barracks";324;1
"Unit";"Marine";"Barracks";325;1
"Unit";"Marine";"Barracks";326;1
"Unit";"Marine";"Barracks";328;1
"Unit";"Marine";"Barracks";330;1
"Unit";"Marine";"Barracks";333;1
"Unit";"Marine";"Barracks";335;1
"Unit";"Marauder";"Barracks";328;2
"Unit";"Marauder";"Barracks";330;2
"Unit";"Liberator";"Starport";318;3
"Unit";"Liberator";"Starport";318;3
"Unit";"Liberator";"Starport";318;3
"Unit";"Marine";"Barracks";335;1
"Unit";"Marine";"Barracks";338;1
"Unit";"Marine";"Barracks";339;1
"Unit";"Marine";"Barracks";340;1
"Unit";"Marine";"Barracks";341;1
"Unit";"Marauder";"Barracks";336;2
"Unit";"Marine";"Barracks";342;1
"Unit";"Marine";"Barracks";344;1
"Unit";"Medivac";"Starport";344;2
"Unit";"Marine";"Barracks";367;1
"Unit";"Marine";"Barracks";369;1
