"Type";"UnitName";"OnBuilding";"TotalSupply";"Supply"
"Unit";"SCV";"Command Center";12;1
"Unit";"SCV";"Command Center";12;1
"Unit";"SCV";"Command Center";13;1
"Building";"SupplyDepot";NA;13;0
"Unit";"SCV";"Command Center";15;1
"Building";"Refinery";NA;14;0
"Unit";"SCV";"Command Center";15;1
"Unit";"SCV";"Command Center";16;1
"Unit";"SCV";"Command Center";17;1
"Building";"Barracks";NA;15;0
"Unit";"Reaper";"Barracks";19;1
"Unit";"SCV";"Command Center";19;1
"Unit";"SCV";"Command Center";20;1
"Building";"SupplyDepot";NA;20;0
"Unit";"SCV";"Command Center";21;1
"Building";"Refinery";NA;21;0
"Building";"Factory";NA;19;0
"Building";"BarracksReactor";NA;20;0
"Building";"CommandCenter";NA;19;0
"Unit";"SCV";"Command Center";23;1
"Building";"BarracksTechLab";NA;23;0
"Unit";"Hellion";"Factory";23;2
"Unit";"Hellion";"Factory";23;2
"Unit";"SCV";"Command Center";24;1
"Building";"Starport";NA;23;0
"Unit";"SCV";"Command Center";28;1
"Unit";"Hellion";"Factory";24;2
"Unit";"Hellion";"Factory";26;2
"Unit";"SCV";"Command Center";29;1
"Unit";"SCV";"Command Center";30;1
"Unit";"SCV";"Command Center";36;1
"Unit";"Hellion";"Factory";35;2
"Unit";"Hellion";"Factory";35;2
"Unit";"SCV";"Command Center";36;1
"Building";"BarracksReactor";NA;30;0
"Unit";"Banshee";"Starport";30;3
"Unit";"SCV";"Command Center";37;1
"Building";"SupplyDepot";NA;36;0
"Unit";"SCV";"Command Center";42;1
"Building";"SupplyDepot";NA;42;0
"Unit";"Marine";"Barracks";46;1
"Unit";"Marine";"Barracks";46;1
"Unit";"SCV";"Command Center";47;1
"Unit";"SCV";"Command Center";47;1
"Building";"FactoryTechLab";NA;47;0
"Building";"SupplyDepot";NA;47;0
"Unit";"SCV";"Command Center";49;1
"Building";"Bunker";NA;47;0
"Unit";"SCV";"Command Center";52;1
"Unit";"SCV";"Command Center";52;1
"Unit";"SCV";"Command Center";52;1
"Unit";"SCV";"Command Center";54;1
"Building";"Refinery";NA;52;0
"Building";"Refinery";NA;52;0
"Unit";"SCV";"Command Center";54;1
"Unit";"SCV";"Command Center";55;1
"Unit";"SCV";"Command Center";57;1
"Unit";"Marine";"Barracks";56;1
"Unit";"SCV";"Command Center";57;1
"Building";"StarportReactor";NA;55;0
"Unit";"SCV";"Command Center";58;1
"Building";"Barracks";NA;54;0
"Building";"Barracks";NA;54;0
"Building";"CommandCenter";NA;51;0
"Building";"EngineeringBay";NA;58;0
"Building";"EngineeringBay";NA;58;0
"Unit";"Marine";"Barracks";60;1
"Unit";"SCV";"Command Center";62;1
"Unit";"SCV";"Command Center";62;1
"Unit";"Marine";"Barracks";62;1
"Unit";"Marine";"Barracks";62;1
"Building";"SupplyDepot";NA;62;0
"Building";"SupplyDepot";NA;62;0
"Unit";"SCV";"Command Center";65;1
"Unit";"SCV";"Command Center";65;1
"Unit";"SCV";"Command Center";67;1
"Unit";"SCV";"Command Center";68;1
"Building";"StarportReactor";NA;63;0
"Unit";"Marine";"Barracks";67;1
"Unit";"Marine";"Barracks";67;1
"Unit";"Marine";"Barracks";67;1
"Unit";"SCV";"Command Center";69;1
"Unit";"SCV";"Command Center";70;1
"Building";"Barracks";NA;65;0
"Unit";"Marine";"Barracks";74;1
"Unit";"Marine";"Barracks";74;1
"Unit";"Marine";"Barracks";74;1
"Unit";"Marine";"Barracks";74;1
"Unit";"Marine";"Barracks";74;1
"Unit";"SCV";"Command Center";76;1
"Unit";"SCV";"Command Center";76;1
"Unit";"Medivac";"Starport";74;2
"Unit";"Medivac";"Starport";74;2
"Building";"SupplyDepot";NA;76;0
"Unit";"Marine";"Barracks";76;1
"Unit";"Marine";"Barracks";81;1
"Unit";"Marine";"Barracks";81;1
"Unit";"Marine";"Barracks";81;1
"Unit";"SCV";"Command Center";83;1
"Unit";"Marine";"Barracks";81;1
"Unit";"Marine";"Barracks";81;1
"Upgrade";"Stimpack";"TechLab";62;0
"Unit";"SCV";"Command Center";87;1
"Unit";"SCV";"Command Center";87;1
"Unit";"Marine";"Barracks";83;1
"Unit";"Marine";"Barracks";87;1
"Unit";"Marine";"Barracks";94;1
"Unit";"Marine";"Barracks";94;1
"Unit";"Marine";"Barracks";94;1
"Building";"Armory";NA;76;0
"Unit";"SCV";"Command Center";97;1
"Building";"Bunker";NA;88;0
"Unit";"SCV";"Command Center";98;1
"Unit";"SCV";"Command Center";98;1
"Building";"Barracks";NA;83;0
"Unit";"SCV";"Command Center";101;1
"Unit";"SCV";"Command Center";104;1
"Unit";"SCV";"Command Center";104;1
"Building";"SupplyDepot";NA;101;0
"Upgrade";"TerranInfantryWeaponsLevel1";"EngineeringBay";74;0
"Upgrade";"TerranInfantryArmorsLevel1";"EngineeringBay";74;0
"Building";"SupplyDepot";NA;101;0
"Unit";"Marine";"Barracks";104;1
"Unit";"SCV";"Command Center";107;1
"Unit";"SCV";"Command Center";107;1
"Unit";"Marine";"Barracks";105;1
"Unit";"Marine";"Barracks";105;1
"Unit";"Marine";"Barracks";105;1
"Unit";"Marine";"Barracks";105;1
"Unit";"Marine";"Barracks";105;1
"Building";"Factory";NA;97;0
"Unit";"SCV";"Command Center";110;1
"Unit";"SCV";"Command Center";110;1
"Unit";"SCV";"Command Center";115;1
"Building";"FactoryTechLab";NA;115;0
"Unit";"SCV";"Command Center";115;1
"Unit";"Marine";"Barracks";115;1
"Unit";"Marine";"Barracks";115;1
"Unit";"SCV";"Command Center";117;1
"Unit";"Marine";"Barracks";115;1
"Unit";"SCV";"Command Center";117;1
"Building";"Refinery";NA;115;0
"Building";"Refinery";NA;115;0
"Building";"BarracksReactor";NA;108;0
"Building";"MissileTurret";NA;117;0
"Unit";"Marine";"Barracks";118;1
"Unit";"Marine";"Barracks";118;1
"Unit";"Marine";"Barracks";118;1
"Unit";"SCV";"Command Center";118;1
"Unit";"SCV";"Command Center";121;1
"Unit";"Marine";"Barracks";119;1
"Unit";"SCV";"Command Center";124;1
"Unit";"Marine";"Barracks";124;1
"Unit";"Marine";"Barracks";124;1
"Unit";"Marine";"Barracks";124;1
"Building";"SensorTower";NA;129;0
"Unit";"SCV";"Command Center";131;1
"Unit";"SCV";"Command Center";131;1
"Unit";"Marine";"Barracks";130;1
"Unit";"Marine";"Barracks";130;1
"Unit";"Marine";"Barracks";130;1
"Unit";"Marine";"Barracks";130;1
"Building";"SupplyDepot";NA;134;0
"Building";"SupplyDepot";NA;134;0
"Upgrade";"TerranVehicleWeaponsLevel1";"Armory";115;0
"Unit";"SCV";"Command Center";140;1
"Unit";"SCV";"Command Center";140;1
"Unit";"Marine";"Barracks";140;1
"Unit";"Marine";"Barracks";140;1
"Unit";"Marine";"Barracks";140;1
"Unit";"Marine";"Barracks";140;1
"Unit";"Marine";"Barracks";140;1
"Unit";"Marine";"Barracks";140;1
"Unit";"Marine";"Barracks";140;1
"Unit";"Marine";"Barracks";140;1
"Unit";"Marine";"Barracks";140;1
"Building";"SupplyDepot";NA;140;0
"Building";"SupplyDepot";NA;140;0
"Unit";"Medivac";"Starport";140;2
"Unit";"Medivac";"Starport";140;2
"Building";"CommandCenter";NA;128;0
"Unit";"Marine";"Barracks";142;1
"Unit";"Marine";"Barracks";151;1
"Unit";"Marine";"Barracks";151;1
"Unit";"Marine";"Barracks";151;1
"Unit";"Marine";"Barracks";151;1
"Unit";"Marine";"Barracks";151;1
"Building";"Factory";NA;140;0
"Upgrade";"TerranInfantryWeaponsLevel2";"EngineeringBay";124;0
"Building";"Barracks";NA;140;0
"Building";"Barracks";NA;140;0
"Building";"Barracks";NA;140;0
"Unit";"Marine";"Barracks";161;1
"Unit";"Marine";"Barracks";161;1
"Unit";"Marine";"Barracks";161;1
"Unit";"Marine";"Barracks";161;1
"Upgrade";"TerranInfantryArmorsLevel2";"EngineeringBay";129;0
"Unit";"Medivac";"Starport";161;2
"Unit";"Medivac";"Starport";161;2
"Unit";"Marine";"Barracks";169;1
"Unit";"Marine";"Barracks";169;1
"Unit";"Marine";"Barracks";169;1
"Unit";"Marine";"Barracks";169;1
"Unit";"Marine";"Barracks";169;1
"Unit";"Marine";"Barracks";169;1
"Unit";"Marine";"Barracks";169;1
"Unit";"Marine";"Barracks";171;1
"Unit";"Marine";"Barracks";171;1
"Unit";"Marine";"Barracks";171;1
"Unit";"Marine";"Barracks";171;1
"Building";"BarracksTechLab";NA;171;0
"Building";"BarracksTechLab";NA;171;0
"Building";"FactoryTechLab";NA;171;0
"Unit";"SCV";"Command Center";173;1
"Unit";"SCV";"Command Center";173;1
"Unit";"SCV";"Command Center";173;1
"Unit";"Medivac";"Starport";170;2
"Unit";"SCV";"Command Center";183;1
"Building";"SensorTower";NA;180;0
"Building";"Refinery";NA;180;0
"Building";"SupplyDepot";NA;183;0
"Building";"SupplyDepot";NA;183;0
"Building";"Bunker";NA;179;0
"Building";"SupplyDepot";NA;185;0
"Upgrade";"TerranVehicleWeaponsLevel2";"Armory";161;0
"Building";"SupplyDepot";NA;185;0
"Unit";"Marine";"Barracks";186;1
"Unit";"Marine";"Barracks";186;1
"Unit";"Marine";"Barracks";186;1
"Unit";"Marine";"Barracks";186;1
"Unit";"Marine";"Barracks";186;1
"Building";"BarracksTechLab";NA;186;0
"Unit";"Marauder";"Barracks";186;2
"Unit";"Marauder";"Barracks";186;2
"Unit";"Marine";"Barracks";186;1
"Unit";"Marauder";"Barracks";186;2
"Unit";"Medivac";"Starport";186;2
"Unit";"Medivac";"Starport";186;2
"Building";"SupplyDepot";NA;186;0
"Unit";"Marine";"Barracks";191;1
"Unit";"Marine";"Barracks";191;1
"Unit";"Marauder";"Barracks";191;2
"Unit";"Marauder";"Barracks";191;2
"Unit";"Marauder";"Barracks";193;2
"Building";"SupplyDepot";NA;203;0
"Unit";"Marine";"Barracks";210;1
"Unit";"Marine";"Barracks";210;1
"Unit";"Marauder";"Barracks";210;2
"Unit";"Marine";"Barracks";210;1
"Unit";"Marine";"Barracks";210;1
"Unit";"Marine";"Barracks";210;1
"Unit";"Marauder";"Barracks";210;2
"Unit";"Marine";"Barracks";212;1
"Unit";"Marauder";"Barracks";212;2
"Building";"Refinery";NA;222;0
"Building";"Refinery";NA;222;0
"Upgrade";"TerranInfantryWeaponsLevel3";"EngineeringBay";191;0
"Upgrade";"TerranInfantryArmorsLevel3";"EngineeringBay";191;0
"Building";"Starport";NA;222;0
"Building";"Starport";NA;222;0
"Building";"Starport";NA;222;0
"Unit";"Marine";"Barracks";222;1
"Unit";"Marine";"Barracks";222;1
"Building";"FusionCore";NA;222;0
"Unit";"Marauder";"Barracks";222;2
"Unit";"Marauder";"Barracks";222;2
"Unit";"Marine";"Barracks";222;1
"Unit";"Marine";"Barracks";222;1
"Unit";"Marauder";"Barracks";222;2
"Unit";"Marauder";"Barracks";222;2
"Unit";"Marine";"Barracks";230;1
"Unit";"Marine";"Barracks";230;1
"Unit";"Marauder";"Barracks";230;2
"Unit";"Marauder";"Barracks";230;2
"Unit";"Marine";"Barracks";234;1
"Unit";"Marine";"Barracks";234;1
"Unit";"Marine";"Barracks";234;1
"Unit";"Marine";"Barracks";234;1
"Unit";"Marauder";"Barracks";234;2
"Unit";"Marine";"Barracks";234;1
"Unit";"Marauder";"Barracks";234;2
"Unit";"Marine";"Barracks";241;1
"Unit";"Marine";"Barracks";241;1
"Unit";"Marine";"Barracks";247;1
"Unit";"Marine";"Barracks";247;1
"Unit";"Marine";"Barracks";247;1
"Unit";"Marauder";"Barracks";247;2
"Unit";"Marauder";"Barracks";247;2
"Unit";"Marine";"Barracks";249;1
"Unit";"Marine";"Barracks";249;1
"Unit";"Marauder";"Barracks";249;2
"Unit";"Liberator";"Starport";234;3
"Unit";"Marauder";"Barracks";249;2
"Unit";"Liberator";"Starport";234;3
"Unit";"Marine";"Barracks";249;1
"Unit";"Marine";"Barracks";249;1
"Unit";"Marine";"Barracks";260;1
"Unit";"Marine";"Barracks";260;1
"Unit";"Marine";"Barracks";260;1
"Unit";"Marauder";"Barracks";260;2
"Unit";"Marauder";"Barracks";260;2
"Unit";"Marauder";"Barracks";260;2
"Unit";"Liberator";"Starport";260;3
"Upgrade";"TerranShipWeaponsLevel1";"Armory";241;0
"Building";"CommandCenter";NA;249;0
"Unit";"Marine";"Barracks";281;1
"Unit";"Marine";"Barracks";281;1
"Unit";"Marine";"Barracks";281;1
"Unit";"Marine";"Barracks";281;1
"Unit";"Marine";"Barracks";281;1
"Unit";"Marine";"Barracks";281;1
"Unit";"Marauder";"Barracks";281;2
"Unit";"Marauder";"Barracks";281;2
"Unit";"Marauder";"Barracks";281;2
"Unit";"Liberator";"Starport";279;3
"Unit";"Liberator";"Starport";279;3
"Unit";"Marine";"Barracks";284;1
"Unit";"Marine";"Barracks";284;1
"Building";"Starport";NA;281;0
"Unit";"Marauder";"Barracks";284;2
"Unit";"Marine";"Barracks";292;1
"Unit";"Marine";"Barracks";296;1
"Unit";"Marine";"Barracks";296;1
"Unit";"Marauder";"Barracks";290;2
"Unit";"Marauder";"Barracks";296;2
"Unit";"Marauder";"Barracks";296;2
"Unit";"Marine";"Barracks";302;1
"Unit";"Marine";"Barracks";302;1
"Unit";"Liberator";"Starport";281;3
"Building";"Refinery";NA;304;0
"Unit";"Marauder";"Barracks";304;2
"Unit";"Marine";"Barracks";308;1
"Unit";"Marine";"Barracks";309;1
"Unit";"Marine";"Barracks";309;1
"Unit";"Marauder";"Barracks";309;2
"Unit";"Liberator";"Starport";296;3
"Unit";"Liberator";"Starport";302;3
"Unit";"Marine";"Barracks";325;1
"Unit";"Marine";"Barracks";325;1
"Unit";"Marine";"Barracks";325;1
"Unit";"Marine";"Barracks";325;1
"Unit";"Marauder";"Barracks";325;2
"Unit";"Marauder";"Barracks";325;2
"Unit";"Marauder";"Barracks";325;2
"Unit";"Liberator";"Starport";317;3
"Unit";"Marine";"Barracks";333;1
"Unit";"Marine";"Barracks";333;1
"Building";"CommandCenter";NA;294;0
"Unit";"Marauder";"Barracks";333;2
"Unit";"Marine";"Barracks";343;1
"Unit";"Marauder";"Barracks";343;2
