"type";"unit_name";"on_building";"total_supply_lag";"supply"
"Building";"Barracks";NA;16;0
"Building";"Refinery";NA;16;0
"Unit";"Reaper";"Barracks";19;1
"Building";"CommandCenter";NA;20;0
"Unit";"Marine";"Barracks";21;1
"Building";"Factory";NA;23;0
"Building";"BarracksReactor";NA;24;0
"Building";"Refinery";NA;25;0
"Building";"Starport";NA;27;0
"Unit";"Hellion";"Factory";27;2
"Unit";"Hellion";"Factory";30;2
"Building";"BarracksTechLab";NA;32;0
"Unit";"Hellion";"Factory";34;2
"Unit";"Hellion";"Factory";36;2
"Unit";"Raven";"Starport";40;2
"Unit";"Hellion";"Factory";44;2
"Building";"BarracksTechLab";NA;46;0
"Unit";"Hellion";"Factory";48;2
"Building";"CommandCenter";NA;52;0
"Unit";"Marine";"Barracks";54;1
"Building";"Barracks";NA;56;0
"Building";"Barracks";NA;57;0
"Building";"StarportReactor";NA;57;0
"Unit";"Marine";"Barracks";58;1
"Upgrade";"Stimpack";"TechLab";60;0
"Unit";"Marine";"Barracks";62;1
"Building";"EngineeringBay";NA;64;0
"Building";"EngineeringBay";NA;64;0
"Building";"Refinery";NA;65;0
"Building";"Refinery";NA;65;0
"Unit";"Marine";"Barracks";66;1
"Building";"StarportReactor";NA;67;0
"Unit";"Marine";"Barracks";68;1
"Unit";"Marine";"Barracks";69;1
"Unit";"Marine";"Barracks";71;1
"Unit";"Marine";"Barracks";72;1
"Unit";"Marine";"Barracks";74;1
"Unit";"Marine";"Barracks";76;1
"Unit";"Marine";"Barracks";77;1
"Unit";"Marine";"Barracks";79;1
"Unit";"Marine";"Barracks";81;1
"Unit";"Marine";"Barracks";82;1
"Unit";"Medivac";"Starport";83;2
"Unit";"Marine";"Barracks";85;1
"Unit";"Medivac";"Starport";86;2
"Unit";"Marine";"Barracks";88;1
"Building";"Barracks";NA;89;0
"Unit";"Marine";"Barracks";89;1
"Building";"Barracks";NA;90;0
"Unit";"Marine";"Barracks";90;1
"Upgrade";"TerranInfantryWeaponsLevel1";"EngineeringBay";91;0
"Unit";"Marine";"Barracks";91;1
"Unit";"Marine";"Barracks";94;1
"Unit";"Marine";"Barracks";95;1
"Unit";"Marine";"Barracks";96;1
"Unit";"Marine";"Barracks";97;1
"Unit";"Marine";"Barracks";100;1
"Unit";"Medivac";"Starport";101;2
"Unit";"Marine";"Barracks";104;1
"Unit";"Marine";"Barracks";107;1
"Unit";"Medivac";"Starport";108;2
"Building";"Armory";NA;111;0
"Building";"Refinery";NA;113;0
"Building";"Refinery";NA;113;0
"Unit";"Marine";"Barracks";113;1
"Unit";"Marine";"Barracks";114;1
"Unit";"Marine";"Barracks";117;1
"Unit";"Medivac";"Starport";118;2
"Unit";"Marine";"Barracks";120;1
"Unit";"Marine";"Barracks";121;1
"Unit";"Marine";"Barracks";124;1
"Unit";"Marine";"Barracks";125;1
"Unit";"Marine";"Barracks";126;1
"Unit";"Marine";"Barracks";128;1
"Unit";"Marine";"Barracks";130;1
"Building";"Factory";NA;131;0
"Unit";"Marine";"Barracks";131;1
"Unit";"Marine";"Barracks";132;1
"Unit";"Marine";"Barracks";133;1
"Building";"BarracksReactor";NA;134;0
"Building";"BarracksReactor";NA;134;0
"Unit";"Marine";"Barracks";134;1
"Unit";"Marine";"Barracks";138;1
"Unit";"Marine";"Barracks";139;1
"Unit";"Marine";"Barracks";140;1
"Unit";"Marine";"Barracks";141;1
"Unit";"Marine";"Barracks";142;1
"Unit";"Marine";"Barracks";143;1
"Unit";"Marine";"Barracks";144;1
"Unit";"Marine";"Barracks";145;1
"Unit";"Marine";"Barracks";146;1
"Building";"CommandCenter";NA;147;0
"Unit";"Marine";"Barracks";147;1
"Building";"FactoryTechLab";NA;148;0
"Unit";"Marine";"Barracks";148;1
"Unit";"Marine";"Barracks";149;1
"Unit";"Marine";"Barracks";150;1
"Upgrade";"TerranInfantryWeaponsLevel2";"EngineeringBay";151;0
"Building";"Barracks";NA;151;0
"Unit";"Marine";"Barracks";151;1
"Building";"Barracks";NA;152;0
"Unit";"Marine";"Barracks";152;1
"Unit";"Marine";"Barracks";153;1
"Unit";"Marine";"Barracks";154;1
"Unit";"Marine";"Barracks";155;1
"Building";"Barracks";NA;156;0
"Unit";"Marauder";"Barracks";156;2
"Unit";"Marine";"Barracks";158;1
"Unit";"Marine";"Barracks";159;1
"Unit";"Marine";"Barracks";160;1
"Upgrade";"TerranVehicleWeaponsLevel1";"Armory";161;0
"Unit";"Marine";"Barracks";161;1
"Unit";"Marine";"Barracks";162;1
"Unit";"Liberator";"Starport";163;3
"Unit";"Liberator";"Starport";166;3
"Unit";"Marauder";"Barracks";169;2
"Unit";"Marine";"Barracks";171;1
"Unit";"Marine";"Barracks";172;1
"Unit";"Marine";"Barracks";173;1
"Unit";"Marine";"Barracks";174;1
"Unit";"Marine";"Barracks";175;1
"Unit";"Marine";"Barracks";176;1
"Unit";"Marine";"Barracks";177;1
"Unit";"Marine";"Barracks";178;1
"Unit";"Marine";"Barracks";179;1
"Unit";"Marine";"Barracks";180;1
"Unit";"Marauder";"Barracks";181;2
"Building";"BarracksTechLab";NA;183;0
"Building";"BarracksTechLab";NA;183;0
"Unit";"Marine";"Barracks";183;1
"Unit";"Marine";"Barracks";184;1
"Unit";"Marine";"Barracks";185;1
"Unit";"Medivac";"Starport";186;2
"Unit";"Medivac";"Starport";188;2
"Building";"BarracksTechLab";NA;190;0
"Unit";"Marauder";"Barracks";190;2
"Unit";"Marauder";"Barracks";192;2
"Unit";"Marine";"Barracks";194;1
"Unit";"Marauder";"Barracks";195;2
"Unit";"Marine";"Barracks";197;1
"Unit";"Marine";"Barracks";198;1
"Unit";"Marine";"Barracks";199;1
"Unit";"Marine";"Barracks";200;1
"Unit";"Marine";"Barracks";201;1
"Unit";"Marine";"Barracks";202;1
"Unit";"Marine";"Barracks";203;1
"Unit";"Marine";"Barracks";204;1
"Unit";"Marine";"Barracks";205;1
"Unit";"Marauder";"Barracks";206;2
"Unit";"Marine";"Barracks";208;1
"Unit";"Marine";"Barracks";209;1
"Unit";"Marine";"Barracks";210;1
"Unit";"Marauder";"Barracks";211;2
"Unit";"Marine";"Barracks";213;1
"Unit";"Medivac";"Starport";214;2
"Unit";"Marine";"Barracks";216;1
"Unit";"Marauder";"Barracks";217;2
"Unit";"Medivac";"Starport";219;2
"Unit";"Marauder";"Barracks";221;2
"Unit";"Marine";"Barracks";223;1
"Unit";"Marauder";"Barracks";224;2
"Unit";"Marine";"Barracks";226;1
"Unit";"Marine";"Barracks";227;1
"Unit";"Marine";"Barracks";228;1
"Building";"GhostAcademy";NA;229;0
"Unit";"Marauder";"Barracks";229;2
"Unit";"Marine";"Barracks";231;1
"Unit";"Marine";"Barracks";232;1
"Unit";"Marine";"Barracks";233;1
"Unit";"Marine";"Barracks";234;1
"Unit";"Marine";"Barracks";235;1
"Unit";"Marauder";"Barracks";236;2
"Unit";"Marine";"Barracks";238;1
"Unit";"Marine";"Barracks";239;1
"Unit";"Marauder";"Barracks";240;2
"Unit";"Marine";"Barracks";242;1
"Upgrade";"TerranInfantryWeaponsLevel3";"EngineeringBay";243;0
"Unit";"Marauder";"Barracks";243;2
"Unit";"Marine";"Barracks";245;1
"Unit";"Marine";"Barracks";246;1
"Unit";"Marauder";"Barracks";247;2
"Unit";"Marine";"Barracks";249;1
"Unit";"Marauder";"Barracks";250;2
"Unit";"Medivac";"Starport";252;2
"Unit";"Medivac";"Starport";254;2
"Unit";"Marauder";"Barracks";256;2
"Unit";"Marine";"Barracks";258;1
"Unit";"Marine";"Barracks";259;1
"Unit";"Marauder";"Barracks";260;2
"Building";"Refinery";NA;262;0
"Building";"Refinery";NA;262;0
"Unit";"Marauder";"Barracks";262;2
"Unit";"Marine";"Barracks";264;1
"Unit";"Marine";"Barracks";265;1
"Unit";"Marauder";"Barracks";266;2
"Unit";"Marauder";"Barracks";268;2
"Unit";"Marine";"Barracks";270;1
"Unit";"Marine";"Barracks";271;1
"Unit";"Medivac";"Starport";272;2
"Unit";"Medivac";"Starport";274;2
"Unit";"Marine";"Barracks";276;1
"Unit";"Marine";"Barracks";277;1
"Unit";"Marine";"Barracks";278;1
"Unit";"Marine";"Barracks";279;1
"Unit";"Marine";"Barracks";280;1
"Unit";"Marine";"Barracks";281;1
"Unit";"Marine";"Barracks";282;1
"Unit";"Marine";"Barracks";283;1
"Building";"Starport";NA;284;0
"Unit";"Marine";"Barracks";284;1
"Unit";"Marauder";"Barracks";285;2
"Unit";"Marauder";"Barracks";287;2
"Unit";"Marine";"Barracks";289;1
"Unit";"Marine";"Barracks";290;1
"Unit";"Marine";"Barracks";291;1
"Unit";"Marine";"Barracks";292;1
"Unit";"Marine";"Barracks";293;1
"Unit";"Marine";"Barracks";294;1
"Unit";"Marine";"Barracks";295;1
"Unit";"Marine";"Barracks";296;1
"Unit";"Marine";"Barracks";297;1
"Building";"Starport";NA;298;0
"Building";"StarportReactor";NA;298;0
"Unit";"Marauder";"Barracks";298;2
"Unit";"Marine";"Barracks";300;1
"Unit";"Marine";"Barracks";301;1
"Unit";"Marine";"Barracks";302;1
"Unit";"Marauder";"Barracks";303;2
"Unit";"Marine";"Barracks";305;1
"Unit";"Marine";"Barracks";306;1
"Unit";"Marine";"Barracks";307;1
"Unit";"Marine";"Barracks";308;1
"Unit";"Marine";"Barracks";309;1
"Building";"CommandCenter";NA;310;0
"Unit";"Marine";"Barracks";310;1
"Unit";"Marine";"Barracks";311;1
"Unit";"Marine";"Barracks";312;1
"Unit";"Marauder";"Barracks";313;2
"Unit";"Marine";"Barracks";315;1
"Unit";"Marauder";"Barracks";316;2
"Unit";"Marine";"Barracks";318;1
"Unit";"Marine";"Barracks";319;1
"Unit";"Marine";"Barracks";320;1
"Unit";"Marine";"Barracks";321;1
"Unit";"Marine";"Barracks";322;1
"Building";"SensorTower";NA;323;0
"Unit";"Marauder";"Barracks";323;2
"Unit";"Marine";"Barracks";325;1
"Unit";"Marauder";"Barracks";326;2
"Unit";"Marauder";"Barracks";328;2
"Unit";"Marine";"Barracks";330;1
"Unit";"Medivac";"Starport";331;2
"Unit";"Medivac";"Starport";333;2
"Unit";"Medivac";"Starport";335;2
"Unit";"Medivac";"Starport";337;2
"Unit";"Marauder";"Barracks";339;2
"Unit";"Marine";"Barracks";341;1
"Unit";"Marauder";"Barracks";342;2
"Unit";"Marine";"Barracks";344;1
"Building";"Armory";NA;345;0
"Building";"SensorTower";NA;345;0
"Unit";"Marauder";"Barracks";345;2
"Unit";"Marine";"Barracks";347;1
"Unit";"Marine";"Barracks";348;1
"Unit";"Marine";"Barracks";349;1
"Unit";"Marine";"Barracks";350;1
"Unit";"Medivac";"Starport";351;2
"Unit";"Medivac";"Starport";353;2
"Unit";"Medivac";"Starport";355;2
"Upgrade";"TerranShipWeaponsLevel1";"Armory";357;0
"Upgrade";"PersonalCloaking";"GhostAcademy";357;0
"Unit";"Ghost";"Barracks";357;2
"Unit";"Ghost";"Barracks";359;2
"Building";"StarportReactor";NA;361;0
"Unit";"Marauder";"Barracks";361;2
"Unit";"Marine";"Barracks";363;1
"Unit";"Marine";"Barracks";364;1
"Unit";"Marine";"Barracks";365;1
"Unit";"Marine";"Barracks";366;1
"Unit";"Marine";"Barracks";367;1
"Unit";"Marauder";"Barracks";368;2
"Unit";"Marine";"Barracks";370;1
"Unit";"Marine";"Barracks";371;1
"Unit";"Marine";"Barracks";372;1
"Unit";"Marine";"Barracks";373;1
"Unit";"Marine";"Barracks";374;1
"Unit";"Liberator";"Starport";375;3
"Unit";"Liberator";"Starport";378;3
"Unit";"Liberator";"Starport";381;3
"Unit";"Marine";"Barracks";384;1
"Unit";"Marauder";"Barracks";385;2
"Unit";"Ghost";"Barracks";387;2
"Unit";"Marine";"Barracks";389;1
"Building";"GhostAcademy";NA;390;0
"Unit";"Marauder";"Barracks";390;2
"Unit";"Marine";"Barracks";392;1
"Unit";"Marine";"Barracks";393;1
"Building";"CommandCenter";NA;394;0
"Unit";"Marauder";"Barracks";394;2
"Unit";"Marine";"Barracks";396;1
"Unit";"Marine";"Barracks";397;1
"Unit";"Marine";"Barracks";398;1
"Unit";"Marauder";"Barracks";399;2
"Unit";"Marine";"Barracks";401;1
"Unit";"Marine";"Barracks";402;1
"Unit";"Marauder";"Barracks";403;2
"Unit";"Marine";"Barracks";405;1
"Unit";"Marine";"Barracks";406;1
"Unit";"Marauder";"Barracks";407;2
"Unit";"Marine";"Barracks";409;1
"Unit";"Marine";"Barracks";410;1
"Unit";"Marauder";"Barracks";411;2
"Unit";"Marine";"Barracks";413;1
"Unit";"Marine";"Barracks";414;1
"Unit";"Marine";"Barracks";415;1
"Unit";"Marauder";"Barracks";416;2
"Unit";"Marine";"Barracks";418;1
"Upgrade";"TerranShipWeaponsLevel2";"Armory";419;0
"Unit";"Marine";"Barracks";419;1
"Building";"Starport";NA;420;0
"Building";"Starport";NA;420;0
"Building";"FusionCore";NA;420;0
"Unit";"Marauder";"Barracks";420;2
"Building";"StarportTechLab";NA;422;0
"Building";"StarportTechLab";NA;422;0
"Unit";"Raven";"Starport";422;2
"Unit";"Raven";"Starport";424;2
"Unit";"Medivac";"Starport";426;2
"Unit";"Medivac";"Starport";428;2
"Unit";"Marine";"Barracks";430;1
"Unit";"Marine";"Barracks";431;1
"Unit";"Marine";"Barracks";432;1
"Unit";"Marine";"Barracks";433;1
"Unit";"Marine";"Barracks";434;1
"Unit";"Marine";"Barracks";435;1
"Building";"Refinery";NA;436;0
"Building";"Refinery";NA;436;0
"Building";"Refinery";NA;436;0
"Building";"Refinery";NA;436;0
"Building";"CommandCenter";NA;436;0
"Unit";"Marauder";"Barracks";436;2
"Unit";"Marine";"Barracks";438;1
"Unit";"Raven";"Starport";439;2
"Unit";"Raven";"Starport";441;2
"Unit";"Medivac";"Starport";443;2
"Unit";"Medivac";"Starport";445;2
"Unit";"Marauder";"Barracks";447;2
"Unit";"Marine";"Barracks";449;1
"Unit";"Marine";"Barracks";450;1
"Unit";"Marine";"Barracks";451;1
"Unit";"Marine";"Barracks";452;1
"Unit";"Marauder";"Barracks";453;2
"Building";"CommandCenter";NA;455;0
"Unit";"Medivac";"Starport";455;2
"Unit";"Marine";"Barracks";457;1
"Unit";"Marine";"Barracks";458;1
"Unit";"Marine";"Barracks";459;1
"Unit";"Marine";"Barracks";460;1
"Unit";"Marine";"Barracks";461;1
"Unit";"Marine";"Barracks";462;1
"Unit";"Marine";"Barracks";463;1
"Unit";"Marine";"Barracks";464;1
"Unit";"Marine";"Barracks";465;1
"Unit";"Marine";"Barracks";466;1
"Unit";"Marauder";"Barracks";467;2
"Unit";"Marine";"Barracks";469;1
"Unit";"Marine";"Barracks";470;1
"Unit";"Marine";"Barracks";471;1
"Unit";"Marine";"Barracks";472;1
"Unit";"Marine";"Barracks";473;1
"Unit";"Marauder";"Barracks";474;2
"Unit";"Raven";"Starport";476;2
"Unit";"Raven";"Starport";478;2
"Unit";"Marauder";"Barracks";480;2
"Unit";"Marine";"Barracks";482;1
"Unit";"Marine";"Barracks";483;1
"Unit";"Marine";"Barracks";484;1
"Unit";"Marine";"Barracks";485;1
"Unit";"Marine";"Barracks";486;1
"Building";"StarportTechLab";NA;487;0
"Unit";"Marine";"Barracks";487;1
"Unit";"Marine";"Barracks";488;1
"Building";"CommandCenter";NA;489;0
"Unit";"Marauder";"Barracks";489;2
"Unit";"Marine";"Barracks";491;1
"Unit";"Marine";"Barracks";492;1
"Unit";"Marauder";"Barracks";493;2
"Unit";"Marine";"Barracks";495;1
"Unit";"Raven";"Starport";496;2
"Unit";"Ghost";"Barracks";498;2
"Unit";"Raven";"Starport";500;2
"Unit";"Marine";"Barracks";502;1
"Building";"Barracks";NA;503;0
"Building";"Barracks";NA;503;0
"Unit";"Marauder";"Barracks";503;2
"Unit";"Marine";"Barracks";505;1
"Unit";"Raven";"Starport";506;2
"Unit";"Marine";"Barracks";508;1
"Unit";"Marine";"Barracks";509;1
"Unit";"Ghost";"Barracks";510;2
"Unit";"Ghost";"Barracks";512;2
"Unit";"Raven";"Starport";514;2
"Unit";"Medivac";"Starport";516;2
"Unit";"Marauder";"Barracks";518;2
"Unit";"Marine";"Barracks";520;1
"Unit";"Marauder";"Barracks";521;2
"Unit";"Marine";"Barracks";523;1
"Building";"MissileTurret";NA;524;0
"Building";"Barracks";NA;524;0
"Building";"Barracks";NA;524;0
"Unit";"Ghost";"Barracks";524;2
"Unit";"Ghost";"Barracks";526;2
"Unit";"Ghost";"Barracks";528;2
"Unit";"Medivac";"Starport";530;2
"Building";"Refinery";NA;532;0
"Building";"Refinery";NA;532;0
"Unit";"Ghost";"Barracks";532;2
"Unit";"Ghost";"Barracks";534;2
"Building";"BarracksTechLab";NA;536;0
"Building";"BarracksTechLab";NA;536;0
"Building";"MissileTurret";NA;536;0
"Building";"MissileTurret";NA;536;0
"Building";"MissileTurret";NA;536;0
"Building";"MissileTurret";NA;536;0
"Building";"MissileTurret";NA;536;0
"Unit";"Ghost";"Barracks";536;2
"Unit";"Ghost";"Barracks";538;2
"Unit";"Ghost";"Barracks";540;2
"Unit";"Ghost";"Barracks";542;2
"Unit";"Ghost";"Barracks";544;2
"Unit";"Ghost";"Barracks";546;2
"Unit";"Ghost";"Barracks";548;2
"Unit";"Marauder";"Barracks";550;2
"Unit";"Marine";"Barracks";552;1
"Unit";"Marine";"Barracks";553;1
"Building";"MissileTurret";NA;554;0
"Unit";"Marine";"Barracks";554;1
"Unit";"Marine";"Barracks";555;1
"Unit";"Marine";"Barracks";556;1
"Building";"BarracksTechLab";NA;557;0
"Building";"BarracksReactor";NA;557;0
"Building";"MissileTurret";NA;557;0
"Building";"MissileTurret";NA;557;0
"Building";"MissileTurret";NA;557;0
"Building";"MissileTurret";NA;557;0
"Building";"MissileTurret";NA;557;0
"Unit";"Marine";"Barracks";557;1
"Unit";"Marine";"Barracks";558;1
"Unit";"Marauder";"Barracks";559;2
"Unit";"Marauder";"Barracks";561;2
"Unit";"Marauder";"Barracks";563;2
"Unit";"Liberator";"Starport";565;3
"Unit";"Liberator";"Starport";568;3
"Unit";"Marauder";"Barracks";571;2
"Unit";"Marine";"Barracks";573;1
"Unit";"Marauder";"Barracks";574;2
"Unit";"Marine";"Barracks";576;1
"Unit";"Raven";"Starport";577;2
"Unit";"Raven";"Starport";579;2
"Unit";"Raven";"Starport";581;2
"Building";"MissileTurret";NA;583;0
"Building";"MissileTurret";NA;583;0
"Unit";"Medivac";"Starport";583;2
"Building";"MissileTurret";NA;585;0
"Building";"MissileTurret";NA;585;0
"Building";"CommandCenter";NA;585;0
"Building";"CommandCenter";NA;585;0
"Building";"CommandCenter";NA;585;0
"Unit";"Raven";"Starport";585;2
"Building";"CommandCenter";NA;587;0
"Upgrade";"TerranShipWeaponsLevel3";"Armory";587;0
"Unit";"Liberator";"Starport";587;3
"Unit";"Liberator";"Starport";590;3
"Unit";"Ghost";"Barracks";593;2
"Unit";"Ghost";"Barracks";595;2
"Unit";"Marauder";"Barracks";597;2
"Unit";"Marine";"Barracks";599;1
"Unit";"Liberator";"Starport";600;3
"Unit";"Liberator";"Starport";603;3
"Unit";"Raven";"Starport";606;2
"Unit";"Raven";"Starport";608;2
"Unit";"Raven";"Starport";610;2
"Unit";"Liberator";"Starport";612;3
"Unit";"Liberator";"Starport";615;3
"Unit";"Marauder";"Barracks";618;2
"Unit";"Marauder";"Barracks";620;2
"Unit";"Marine";"Barracks";622;1
"Unit";"Marine";"Barracks";623;1
"Building";"Refinery";NA;624;0
"Building";"Refinery";NA;624;0
"Unit";"Marauder";"Barracks";624;2
"Unit";"Marine";"Barracks";626;1
"Unit";"Marine";"Barracks";627;1
"Unit";"Marauder";"Barracks";628;2
"Unit";"Marauder";"Barracks";630;2
"Unit";"Marine";"Barracks";632;1
"Unit";"Marauder";"Barracks";633;2
"Unit";"Marine";"Barracks";635;1
"Unit";"Marauder";"Barracks";636;2
"Unit";"Marine";"Barracks";638;1
"Unit";"Marauder";"Barracks";639;2
"Unit";"Marine";"Barracks";641;1
"Unit";"Marine";"Barracks";642;1
"Unit";"Liberator";"Starport";643;3
"Unit";"Liberator";"Starport";646;3
"Unit";"Cyclone";"Factory";649;3
"Unit";"Cyclone";"Factory";652;3
"Unit";"Marauder";"Barracks";655;2
"Unit";"Marine";"Barracks";657;1
"Unit";"Marine";"Barracks";658;1
"Unit";"Marauder";"Barracks";659;2
"Unit";"Marauder";"Barracks";661;2
"Unit";"Marine";"Barracks";663;1
"Unit";"Ghost";"Barracks";664;2
"Unit";"Marine";"Barracks";666;1
"Unit";"Marine";"Barracks";667;1
"Unit";"Marine";"Barracks";668;1
"Unit";"Ghost";"Barracks";669;2
"Unit";"Marauder";"Barracks";671;2
"Unit";"Marauder";"Barracks";673;2
"Unit";"Marauder";"Barracks";675;2
"Unit";"Marine";"Barracks";677;1
"Unit";"Cyclone";"Factory";678;3
"Unit";"Ghost";"Barracks";681;2
"Unit";"Ghost";"Barracks";683;2
"Unit";"Marine";"Barracks";685;1
"Unit";"Marine";"Barracks";686;1
"Unit";"Marine";"Barracks";687;1
"Unit";"Marine";"Barracks";688;1
"Unit";"Raven";"Starport";689;2
"Unit";"Raven";"Starport";691;2
"Unit";"Raven";"Starport";693;2
"Unit";"Marine";"Barracks";695;1
"Unit";"Marauder";"Barracks";696;2
"Unit";"Marauder";"Barracks";698;2
"Unit";"Marine";"Barracks";700;1
"Unit";"Marauder";"Barracks";701;2
"Unit";"Marine";"Barracks";703;1
"Unit";"Marine";"Barracks";704;1
"Unit";"Marine";"Barracks";705;1
"Unit";"Raven";"Starport";706;2
"Unit";"Raven";"Starport";708;2
"Unit";"Raven";"Starport";710;2
"Unit";"Marine";"Barracks";712;1
"Unit";"Marauder";"Barracks";713;2
"Unit";"Marine";"Barracks";715;1
"Unit";"Marine";"Barracks";716;1
"Unit";"Marauder";"Barracks";717;2
"Unit";"Marine";"Barracks";719;1
"Unit";"Marauder";"Barracks";720;2
"Unit";"Marine";"Barracks";722;1
"Unit";"Marine";"Barracks";723;1
"Unit";"Marine";"Barracks";724;1
"Unit";"Marine";"Barracks";725;1
"Unit";"Marine";"Barracks";726;1
"Unit";"Marine";"Barracks";727;1
"Unit";"Marine";"Barracks";728;1
"Unit";"Marine";"Barracks";729;1
"Upgrade";"SprayTerran";NA;730;0
"Upgrade";"SprayTerran";NA;730;0
"Upgrade";"SprayTerran";NA;730;0
"Upgrade";"SprayTerran";NA;730;0
"Upgrade";"TerranInfantryArmorsLevel1";NA;730;0
"Upgrade";"ShieldWall";NA;730;0
"Upgrade";"SprayTerran";NA;730;0
"Upgrade";"SprayTerran";NA;730;0
"Upgrade";"TerranInfantryArmorsLevel2";NA;730;0
"Upgrade";"SprayTerran";NA;730;0
"Upgrade";"PunisherGrenades";NA;730;0
"Upgrade";"SprayTerran";NA;730;0
"Upgrade";"TerranInfantryArmorsLevel3";NA;730;0
"Upgrade";"HiSecAutoTracking";NA;730;0
"Upgrade";"SprayTerran";NA;730;0
"Upgrade";"TerranBuildingArmor";NA;730;0
"Upgrade";"SprayTerran";NA;730;0
"Upgrade";"TerranVehicleAndShipArmorsLevel1";NA;730;0
"Upgrade";"SprayTerran";NA;730;0
"Upgrade";"SprayTerran";NA;730;0
"Upgrade";"RavenCorvidReactor";NA;730;0
"Upgrade";"SprayTerran";NA;730;0
"Upgrade";"SprayTerran";NA;730;0
"Upgrade";"TerranVehicleAndShipArmorsLevel2";NA;730;0
"Upgrade";"SprayTerran";NA;730;0
"Upgrade";"SprayTerran";NA;730;0
"Upgrade";"LiberatorAGRangeUpgrade";NA;730;0
"Upgrade";"SprayTerran";NA;730;0
"Upgrade";"SprayTerran";NA;730;0
"Upgrade";"SprayTerran";NA;730;0
"Upgrade";"SprayTerran";NA;730;0
"Upgrade";"SprayTerran";NA;730;0
"Upgrade";"SprayTerran";NA;730;0
"Upgrade";"SprayTerran";NA;730;0
"Upgrade";"SprayTerran";NA;730;0
