"Type";"UnitName";"OnBuilding";"TotalSupply";"Supply"
"Unit";"SCV";"Command Center";12;1
"Unit";"SCV";"Command Center";12;1
"Unit";"SCV";"Command Center";13;1
"Building";"SupplyDepot";NA;13;0
"Unit";"SCV";"Command Center";15;1
"Building";"Refinery";NA;14;0
"Unit";"SCV";"Command Center";15;1
"Unit";"SCV";"Command Center";16;1
"Unit";"SCV";"Command Center";17;1
"Building";"Barracks";NA;15;0
"Unit";"Reaper";"Barracks";19;1
"Unit";"SCV";"Command Center";19;1
"Unit";"SCV";"Command Center";21;1
"Unit";"SCV";"Command Center";21;1
"Building";"BarracksReactor";NA;20;0
"Building";"Factory";NA;19;0
"Building";"SupplyDepot";NA;21;0
"Building";"CommandCenter";NA;19;0
"Building";"BarracksTechLab";NA;23;0
"Unit";"SCV";"Command Center";23;1
"Unit";"Hellion";"Factory";23;2
"Unit";"Hellion";"Factory";23;2
"Building";"Refinery";NA;23;0
"Unit";"SCV";"Command Center";23;1
"Building";"Starport";NA;23;0
"Building";"SupplyDepot";NA;23;0
"Unit";"SCV";"Command Center";28;1
"Unit";"SCV";"Command Center";29;1
"Unit";"Hellion";"Factory";29;2
"Unit";"Hellion";"Factory";29;2
"Unit";"SCV";"Command Center";30;1
"Unit";"SCV";"Command Center";31;1
"Building";"SupplyDepot";NA;31;0
"Unit";"SCV";"Command Center";36;1
"Unit";"SCV";"Command Center";37;1
"Unit";"Hellion";"Factory";37;2
"Unit";"Hellion";"Factory";37;2
"Unit";"SCV";"Command Center";38;1
"Unit";"SCV";"Command Center";39;1
"Unit";"SCV";"Command Center";43;1
"Building";"BarracksTechLab";NA;43;0
"Unit";"SCV";"Command Center";45;1
"Unit";"SCV";"Command Center";45;1
"Unit";"SCV";"Command Center";46;1
"Building";"FactoryTechLab";NA;45;0
"Unit";"Banshee";"Starport";38;3
"Unit";"Marine";"Barracks";47;1
"Unit";"SCV";"Command Center";49;1
"Building";"CommandCenter";NA;36;0
"Unit";"SCV";"Command Center";52;1
"Unit";"SCV";"Command Center";54;1
"Building";"Refinery";NA;53;0
"Building";"Refinery";NA;53;0
"Building";"EngineeringBay";NA;53;0
"Building";"Barracks";NA;47;0
"Building";"Barracks";NA;47;0
"Building";"EngineeringBay";NA;54;0
"Unit";"SCV";"Command Center";56;1
"Unit";"Marine";"Barracks";55;1
"Unit";"Banshee";"Starport";55;3
"Building";"SupplyDepot";NA;58;0
"Unit";"Marine";"Barracks";58;1
"Unit";"Marine";"Barracks";58;1
"Unit";"Marine";"Barracks";58;1
"Unit";"SCV";"Command Center";61;1
"Unit";"Marine";"Barracks";61;1
"Unit";"SCV";"Command Center";64;1
"Unit";"Marine";"Barracks";61;1
"Unit";"Marine";"Barracks";62;1
"Unit";"SCV";"Command Center";67;1
"Unit";"SCV";"Command Center";67;1
"Unit";"SCV";"Command Center";67;1
"Upgrade";"Stimpack";"TechLab";55;0
"Unit";"Marine";"Barracks";67;1
"Unit";"Marine";"Barracks";67;1
"Unit";"Marine";"Barracks";67;1
"Unit";"SCV";"Command Center";69;1
"Unit";"SCV";"Command Center";70;1
"Unit";"SCV";"Command Center";75;1
"Unit";"Marine";"Barracks";74;1
"Unit";"Marine";"Barracks";74;1
"Unit";"Marine";"Barracks";74;1
"Unit";"Marine";"Barracks";74;1
"Unit";"SCV";"Command Center";78;1
"Unit";"Marine";"Barracks";78;1
"Upgrade";"TerranInfantryWeaponsLevel1";"EngineeringBay";61;0
"Unit";"SCV";"Command Center";82;1
"Unit";"SCV";"Command Center";82;1
"Unit";"Marine";"Barracks";82;1
"Unit";"SCV";"Command Center";83;1
"Unit";"Marine";"Barracks";83;1
"Building";"StarportReactor";NA;78;0
"Unit";"Marine";"Barracks";83;1
"Unit";"SCV";"Command Center";87;1
"Unit";"SCV";"Command Center";87;1
"Unit";"SCV";"Command Center";88;1
"Unit";"Marine";"Barracks";86;1
"Building";"BarracksReactor";NA;82;0
"Unit";"Marine";"Barracks";88;1
"Unit";"SCV";"Command Center";90;1
"Unit";"SCV";"Command Center";91;1
"Unit";"SCV";"Command Center";92;1
"Unit";"Marine";"Barracks";89;1
"Unit";"Marine";"Barracks";93;1
"Unit";"Marine";"Barracks";94;1
"Unit";"SCV";"Command Center";99;1
"Unit";"SCV";"Command Center";99;1
"Unit";"Marine";"Barracks";97;1
"Unit";"Marine";"Barracks";97;1
"Unit";"SCV";"Command Center";100;1
"Unit";"Marine";"Barracks";98;1
"Building";"Armory";NA;92;0
"Building";"SupplyDepot";NA;107;0
"Building";"SupplyDepot";NA;107;0
"Building";"SupplyDepot";NA;107;0
"Building";"Barracks";NA;99;0
"Building";"Barracks";NA;99;0
"Unit";"SCV";"Command Center";107;1
"Unit";"SCV";"Command Center";107;1
"Building";"SupplyDepot";NA;107;0
"Building";"SupplyDepot";NA;107;0
"Unit";"SCV";"Command Center";107;1
"Unit";"SCV";"Command Center";109;1
"Unit";"SCV";"Command Center";109;1
"Unit";"Medivac";"Starport";107;2
"Building";"MissileTurret";NA;109;0
"Building";"BarracksReactor";NA;107;0
"Building";"BarracksReactor";NA;107;0
"Unit";"Marine";"Barracks";114;1
"Unit";"Marine";"Barracks";114;1
"Unit";"Marine";"Barracks";114;1
"Unit";"SCV";"Command Center";114;1
"Unit";"SCV";"Command Center";114;1
"Unit";"Marine";"Barracks";114;1
"Unit";"Marine";"Barracks";114;1
"Upgrade";"TerranInfantryArmorsLevel1";"EngineeringBay";103;0
"Unit";"SCV";"Command Center";114;1
"Unit";"SCV";"Command Center";117;1
"Unit";"SCV";"Command Center";118;1
"Unit";"Marine";"Barracks";114;1
"Unit";"Marine";"Barracks";115;1
"Unit";"Marine";"Barracks";116;1
"Unit";"Marine";"Barracks";117;1
"Building";"SupplyDepot";NA;114;0
"Building";"SupplyDepot";NA;114;0
"Unit";"SCV";"Command Center";122;1
"Unit";"Marine";"Barracks";122;1
"Unit";"Marine";"Barracks";122;1
"Building";"MissileTurret";NA;129;0
"Building";"SensorTower";NA;131;0
"Unit";"Marine";"Barracks";131;1
"Unit";"Marine";"Barracks";131;1
"Building";"SupplyDepot";NA;131;0
"Unit";"SCV";"Command Center";131;1
"Unit";"SCV";"Command Center";131;1
"Unit";"SCV";"Command Center";131;1
"Building";"Bunker";NA;129;0
"Unit";"Marine";"Barracks";131;1
"Unit";"Marine";"Barracks";131;1
"Unit";"Marine";"Barracks";131;1
"Upgrade";"TerranVehicleWeaponsLevel1";"Armory";110;0
"Unit";"Marine";"Barracks";131;1
"Unit";"Marine";"Barracks";131;1
"Unit";"Marine";"Barracks";131;1
"Unit";"Marine";"Barracks";131;1
"Unit";"SCV";"Command Center";139;1
"Unit";"SCV";"Command Center";139;1
"Unit";"Marine";"Barracks";139;1
"Unit";"Marine";"Barracks";139;1
"Building";"Refinery";NA;139;0
"Building";"Refinery";NA;139;0
"Unit";"Marine";"Barracks";143;1
"Unit";"Marine";"Barracks";143;1
"Unit";"Marine";"Barracks";143;1
"Upgrade";"TerranInfantryWeaponsLevel2";"EngineeringBay";114;0
"Unit";"SCV";"Command Center";147;1
"Unit";"Marine";"Barracks";145;1
"Unit";"Marine";"Barracks";145;1
"Unit";"Marine";"Barracks";145;1
"Unit";"Marine";"Barracks";147;1
"Unit";"Marine";"Barracks";147;1
"Unit";"SCV";"Command Center";154;1
"Unit";"Medivac";"Starport";146;2
"Unit";"Medivac";"Starport";147;2
"Building";"Factory";NA;143;0
"Unit";"Marine";"Barracks";151;1
"Unit";"Marine";"Barracks";151;1
"Unit";"Marine";"Barracks";156;1
"Unit";"Marine";"Barracks";156;1
"Unit";"Marine";"Barracks";156;1
"Unit";"Marine";"Barracks";156;1
"Unit";"Marine";"Barracks";167;1
"Unit";"Marine";"Barracks";167;1
"Unit";"Marine";"Barracks";167;1
"Unit";"Marine";"Barracks";168;1
"Unit";"Marine";"Barracks";168;1
"Unit";"Marine";"Barracks";168;1
"Unit";"Marine";"Barracks";168;1
"Unit";"Marine";"Barracks";168;1
"Unit";"Marine";"Barracks";168;1
"Unit";"Marine";"Barracks";168;1
"Building";"CommandCenter";NA;151;0
"Building";"SupplyDepot";NA;167;0
"Building";"SupplyDepot";NA;167;0
"Unit";"Marine";"Barracks";168;1
"Building";"SupplyDepot";NA;168;0
"Building";"SupplyDepot";NA;168;0
"Building";"SupplyDepot";NA;168;0
"Building";"SupplyDepot";NA;169;0
"Unit";"Marine";"Barracks";170;1
"Unit";"Marine";"Barracks";176;1
"Unit";"Marine";"Barracks";177;1
"Unit";"Marine";"Barracks";177;1
"Unit";"Marine";"Barracks";177;1
"Unit";"Marine";"Barracks";177;1
"Unit";"Marine";"Barracks";179;1
"Unit";"Marine";"Barracks";184;1
"Unit";"Marine";"Barracks";184;1
"Unit";"Medivac";"Starport";179;2
"Unit";"Medivac";"Starport";179;2
"Unit";"Marine";"Barracks";184;1
"Unit";"Marine";"Barracks";184;1
"Unit";"Marine";"Barracks";185;1
"Unit";"Marine";"Barracks";185;1
"Unit";"Marine";"Barracks";185;1
"Upgrade";"TerranInfantryArmorsLevel2";"EngineeringBay";167;0
"Unit";"Marine";"Barracks";193;1
"Unit";"Marine";"Barracks";193;1
"Unit";"Medivac";"Starport";187;2
"Unit";"Marine";"Barracks";193;1
"Unit";"Marine";"Barracks";193;1
"Upgrade";"TerranVehicleWeaponsLevel2";"Armory";168;0
"Unit";"Marauder";"Barracks";193;2
"Unit";"Marine";"Barracks";196;1
"Unit";"Marine";"Barracks";196;1
"Unit";"Marine";"Barracks";196;1
"Unit";"Marine";"Barracks";196;1
"Unit";"Marine";"Barracks";196;1
"Unit";"Marine";"Barracks";197;1
"Unit";"Marine";"Barracks";202;1
"Unit";"Marine";"Barracks";202;1
"Unit";"Marauder";"Barracks";202;2
"Unit";"Marine";"Barracks";204;1
"Unit";"Marine";"Barracks";205;1
"Unit";"Marine";"Barracks";206;1
"Unit";"Marine";"Barracks";207;1
"Unit";"Marine";"Barracks";208;1
"Unit";"Marine";"Barracks";209;1
"Unit";"Marine";"Barracks";212;1
"Unit";"Marine";"Barracks";212;1
"Unit";"Marine";"Barracks";214;1
"Unit";"Marine";"Barracks";214;1
"Unit";"Marine";"Barracks";218;1
"Building";"Barracks";NA;204;0
"Building";"Barracks";NA;204;0
"Building";"Barracks";NA;204;0
"Unit";"Marine";"Barracks";222;1
"Unit";"Marine";"Barracks";222;1
"Unit";"Marauder";"Barracks";222;2
"Unit";"Marine";"Barracks";225;1
"Unit";"Marine";"Barracks";225;1
"Unit";"Marine";"Barracks";225;1
"Unit";"SCV";"Command Center";232;1
"Unit";"SCV";"Command Center";232;1
"Unit";"SCV";"Command Center";232;1
"Unit";"SCV";"Command Center";232;1
"Unit";"Marauder";"Barracks";227;2
"Building";"BarracksTechLab";NA;229;0
"Building";"BarracksTechLab";NA;229;0
"Building";"BarracksTechLab";NA;232;0
"Unit";"SCV";"Command Center";232;1
"Unit";"SCV";"Command Center";233;1
