"Type";"UnitName";"OnBuilding";"TotalSupply";"Supply"
"Unit";"SCV";"Command Center";12;1
"Unit";"SCV";"Command Center";12;1
"Unit";"SCV";"Command Center";13;1
"Building";"SupplyDepot";NA;13;0
"Building";"Refinery";NA;14;0
"Unit";"SCV";"Command Center";15;1
"Unit";"SCV";"Command Center";15;1
"Unit";"SCV";"Command Center";16;1
"Unit";"SCV";"Command Center";17;1
"Building";"Barracks";NA;15;0
"Unit";"Marine";"Barracks";19;1
"Unit";"SCV";"Command Center";20;1
"Building";"Factory";NA;19;0
"Building";"BarracksReactor";NA;20;0
"Unit";"SCV";"Command Center";20;1
"Building";"SupplyDepot";NA;20;0
"Unit";"SCV";"Command Center";22;1
"Unit";"Hellion";"Factory";22;2
"Unit";"Hellion";"Factory";22;2
"Building";"SupplyDepot";NA;22;0
"Building";"Starport";NA;21;0
"Building";"CommandCenter";NA;20;0
"Unit";"Hellion";"Factory";23;2
"Unit";"Hellion";"Factory";25;2
"Unit";"SCV";"Command Center";27;1
"Building";"Refinery";NA;27;0
"Unit";"Medivac";"Starport";27;2
"Unit";"SCV";"Command Center";31;1
"Unit";"SCV";"Command Center";34;1
"Unit";"SCV";"Command Center";36;1
"Unit";"SCV";"Command Center";36;1
"Unit";"SCV";"Command Center";37;1
"Unit";"SCV";"Command Center";38;1
"Unit";"SCV";"Command Center";39;1
"Building";"StarportTechLab";NA;39;0
"Unit";"SCV";"Command Center";39;1
"Unit";"Hellion";"Factory";39;2
"Unit";"Hellion";"Factory";39;2
"Building";"SupplyDepot";NA;39;0
"Building";"Armory";NA;37;0
"Unit";"SCV";"Command Center";41;1
"Building";"CommandCenter";NA;35;0
"Unit";"SCV";"Command Center";46;1
"Unit";"SCV";"Command Center";46;1
"Unit";"Hellion";"Factory";46;2
"Unit";"Hellion";"Factory";46;2
"Unit";"SCV";"Command Center";48;1
"Unit";"SCV";"Command Center";49;1
"Unit";"Banshee";"Starport";41;3
"Unit";"SCV";"Command Center";53;1
"Unit";"SCV";"Command Center";54;1
"Unit";"Hellion";"Factory";53;2
"Unit";"Hellion";"Factory";53;2
"Unit";"SCV";"Command Center";59;1
"Unit";"SCV";"Command Center";64;1
"Building";"Refinery";NA;58;0
"Building";"Refinery";NA;58;0
"Building";"SupplyDepot";NA;58;0
"Unit";"SCV";"Command Center";64;1
"Unit";"Hellion";"Factory";64;2
"Unit";"Hellion";"Factory";64;2
"Unit";"SCV";"Command Center";66;1
"Unit";"SCV";"Command Center";66;1
"Unit";"Banshee";"Starport";55;3
"Building";"SupplyDepot";NA;66;0
"Unit";"SCV";"Command Center";73;1
"Unit";"Hellion";"Factory";72;2
"Unit";"Hellion";"Factory";72;2
"Unit";"SCV";"Command Center";76;1
"Unit";"SCV";"Command Center";76;1
"Building";"Refinery";NA;73;0
"Building";"Refinery";NA;73;0
"Unit";"SCV";"Command Center";77;1
"Unit";"SCV";"Command Center";81;1
"Unit";"SCV";"Command Center";82;1
"Building";"SupplyDepot";NA;76;0
"Building";"SupplyDepot";NA;77;0
"Unit";"SCV";"Command Center";83;1
"Building";"Factory";NA;72;0
"Building";"Factory";NA;73;0
"Unit";"SCV";"Command Center";84;1
"Unit";"SCV";"Command Center";85;1
"Upgrade";"TerranVehicleWeaponsLevel1";"Armory";58;0
"Unit";"Raven";"Starport";76;2
"Unit";"SCV";"Command Center";86;1
"Unit";"Hellion";"Factory";84;2
"Unit";"Hellion";"Factory";84;2
"Building";"SupplyDepot";NA;86;0
"Unit";"SCV";"Command Center";87;1
"Unit";"SCV";"Command Center";88;1
"Building";"FactoryTechLab";NA;87;0
"Building";"FactoryTechLab";NA;87;0
"Unit";"SCV";"Command Center";91;1
"Unit";"SCV";"Command Center";99;1
"Unit";"Hellion";"Factory";98;2
"Unit";"Hellion";"Factory";98;2
"Unit";"SCV";"Command Center";99;1
"Unit";"SCV";"Command Center";105;1
"Unit";"SCV";"Command Center";105;1
"Building";"StarportReactor";NA;99;0
"Unit";"Hellion";"Factory";100;2
"Unit";"Hellion";"Factory";102;2
"Unit";"Thor";"Factory";98;6
"Unit";"Thor";"Factory";98;6
"Building";"BarracksReactor";NA;105;0
"Unit";"SCV";"Command Center";123;1
"Unit";"Hellion";"Factory";107;2
"Unit";"SCV";"Command Center";123;1
"Unit";"Hellion";"Factory";109;2
"Building";"Factory";NA;105;0
"Building";"Factory";NA;105;0
"Unit";"SCV";"Command Center";123;1
"Unit";"SCV";"Command Center";126;1
"Building";"SupplyDepot";NA;123;0
"Building";"SupplyDepot";NA;123;0
"Unit";"Medivac";"Starport";123;2
"Building";"EngineeringBay";NA;123;0
"Unit";"Hellion";"Factory";129;2
"Unit";"Hellion";"Factory";129;2
"Unit";"SCV";"Command Center";133;1
"Unit";"SCV";"Command Center";133;1
"Building";"SupplyDepot";NA;133;0
"Unit";"SCV";"Command Center";139;1
"Unit";"SCV";"Command Center";139;1
"Unit";"SCV";"Command Center";139;1
"Unit";"Hellion";"Factory";137;2
"Unit";"Hellion";"Factory";137;2
"Unit";"Hellion";"Factory";139;2
"Building";"SupplyDepot";NA;139;0
"Building";"SupplyDepot";NA;139;0
"Unit";"Hellion";"Factory";140;2
"Unit";"Hellion";"Factory";140;2
"Unit";"Hellion";"Factory";146;2
"Unit";"Hellion";"Factory";146;2
"Unit";"Hellion";"Factory";148;2
"Unit";"Hellion";"Factory";150;2
"Building";"SupplyDepot";NA;152;0
"Upgrade";"TerranVehicleWeaponsLevel2";"Armory";123;0
"Building";"SensorTower";NA;152;0
"Building";"CommandCenter";NA;139;0
