"type";"unit_name";"on_building";"total_supply";"supply"
"Building";"Refinery";NA;14;0
"Building";"Barracks";NA;15;0
"Unit";"Reaper";"Barracks";19;1
"Building";"Refinery";NA;20;0
"Building";"Factory";NA;19;0
"Building";"BarracksReactor";NA;21;0
"Building";"CommandCenter";NA;19;0
"Building";"Starport";NA;23;0
"Unit";"Hellion";"Factory";24;2
"Building";"BarracksTechLab";NA;25;0
"Unit";"Hellion";"Factory";25;2
"Unit";"Hellion";"Factory";30;2
"Unit";"Hellion";"Factory";31;2
"Unit";"Hellion";"Factory";36;2
"Unit";"Hellion";"Factory";36;2
"Unit";"Cyclone";"Factory";46;3
"Unit";"Banshee";"Starport";39;3
"Unit";"Cyclone";"Factory";47;3
"Building";"Armory";NA;46;0
"Unit";"Banshee";"Starport";56;3
"Unit";"Hellion";"Factory";63;2
"Unit";"Hellion";"Factory";63;2
"Building";"Refinery";NA;64;0
"Unit";"Hellion";"Factory";69;2
"Building";"Refinery";NA;78;0
"Building";"CommandCenter";NA;64;0
"Building";"BarracksTechLab";NA;82;0
"Unit";"Hellion";"Factory";82;2
"Unit";"Hellion";"Factory";82;2
"Building";"Factory";NA;78;0
"Building";"Factory";NA;79;0
"Building";"StarportReactor";NA;82;0
"Building";"EngineeringBay";NA;88;0
"Upgrade";"TerranVehicleWeaponsLevel1";"Armory";75;0
"Building";"Armory";NA;88;0
"Unit";"Hellion";"Factory";93;2
"Unit";"Hellion";"Factory";93;2
"Building";"CommandCenter";NA;88;0
"Building";"Refinery";NA;95;0
"Building";"Refinery";NA;95;0
"Unit";"Thor";"Factory";93;6
"Unit";"Hellion";"Factory";99;2
"Unit";"Thor";"Factory";95;6
"Unit";"Hellion";"Factory";99;2
"Building";"Refinery";NA;117;0
"Building";"Refinery";NA;117;0
"Unit";"Hellion";"Factory";117;2
"Unit";"Hellion";"Factory";117;2
"Unit";"Hellion";"Factory";120;2
"Unit";"Hellion";"Factory";122;2
"Upgrade";"TerranVehicleWeaponsLevel2";"Armory";99;0
"Unit";"Hellion";"Factory";127;2
"Unit";"Hellion";"Factory";132;2
"Unit";"Hellion";"Factory";135;2
"Building";"BarracksTechLab";NA;139;0
"Building";"MissileTurret";NA;142;0
"Unit";"Hellion";"Factory";139;2
"Building";"MissileTurret";NA;142;0
"Building";"MissileTurret";NA;142;0
"Building";"Factory";NA;135;0
"Building";"Factory";NA;135;0
"Building";"Factory";NA;135;0
"Building";"SensorTower";NA;148;0
"Building";"MissileTurret";NA;148;0
"Building";"Refinery";NA;148;0
"Building";"Refinery";NA;148;0
"Building";"FactoryTechLab";NA;158;0
"Building";"FactoryTechLab";NA;158;0
"Building";"FactoryReactor";NA;158;0
"Unit";"Hellion";"Factory";159;2
"Unit";"Hellion";"Factory";159;2
"Building";"SensorTower";NA;159;0
"Unit";"Hellion";"Factory";163;2
"Unit";"Hellion";"Factory";163;2
"Unit";"Hellion";"Factory";163;2
"Unit";"Hellion";"Factory";163;2
"Building";"CommandCenter";NA;159;0
"Unit";"Hellion";"Factory";163;2
"Unit";"Hellion";"Factory";171;2
"Unit";"Hellion";"Factory";171;2
"Unit";"Hellion";"Factory";171;2
"Unit";"Hellion";"Factory";173;2
"Unit";"Hellion";"Factory";173;2
"Building";"CommandCenter";NA;163;0
"Building";"MissileTurret";NA;179;0
"Building";"MissileTurret";NA;179;0
"Building";"Refinery";NA;181;0
"Building";"Refinery";NA;181;0
"Upgrade";"TerranVehicleWeaponsLevel3";"Armory";159;0
"Unit";"Hellion";"Factory";183;2
"Unit";"Hellion";"Factory";183;2
"Unit";"Hellion";"Factory";183;2
"Building";"CommandCenter";NA;173;0
"Building";"Refinery";NA;196;0
"Building";"Refinery";NA;196;0
"Building";"MissileTurret";NA;196;0
"Building";"MissileTurret";NA;196;0
"Building";"MissileTurret";NA;196;0
"Building";"MissileTurret";NA;196;0
"Building";"Starport";NA;194;0
"Building";"Starport";NA;195;0
"Building";"Starport";NA;195;0
"Building";"Starport";NA;195;0
"Unit";"Cyclone";"Factory";204;3
"Unit";"Cyclone";"Factory";204;3
"Unit";"Cyclone";"Factory";204;3
"Unit";"Cyclone";"Factory";204;3
"Unit";"Cyclone";"Factory";204;3
"Unit";"Cyclone";"Factory";204;3
"Unit";"Cyclone";"Factory";204;3
"Unit";"Cyclone";"Factory";204;3
"Building";"StarportTechLab";NA;206;0
"Building";"StarportTechLab";NA;206;0
"Building";"StarportTechLab";NA;206;0
"Building";"StarportTechLab";NA;206;0
"Unit";"Cyclone";"Factory";230;3
"Unit";"Cyclone";"Factory";230;3
"Unit";"Cyclone";"Factory";230;3
"Unit";"Cyclone";"Factory";230;3
"Unit";"Cyclone";"Factory";230;3
"Unit";"Cyclone";"Factory";230;3
"Unit";"Cyclone";"Factory";230;3
"Unit";"Cyclone";"Factory";230;3
"Building";"FusionCore";NA;206;0
"Building";"Refinery";NA;242;0
"Building";"Refinery";NA;242;0
"Building";"Starport";NA;262;0
"Building";"Starport";NA;262;0
"Upgrade";"TerranShipWeaponsLevel1";"Armory";230;0
"Building";"Starport";NA;262;0
"Building";"StarportTechLab";NA;262;0
"Building";"StarportTechLab";NA;262;0
"Building";"StarportTechLab";NA;262;0
"Building";"CommandCenter";NA;262;0
"Building";"CommandCenter";NA;262;0
"Building";"CommandCenter";NA;262;0
"Unit";"Battlecruiser";"Starport";262;6
"Unit";"Battlecruiser";"Starport";262;6
"Unit";"Battlecruiser";"Starport";262;6
"Building";"Starport";NA;262;0
"Building";"Starport";NA;262;0
"Building";"Starport";NA;262;0
"Unit";"Battlecruiser";"Starport";262;6
"Building";"StarportTechLab";NA;284;0
"Building";"StarportTechLab";NA;284;0
"Unit";"Cyclone";"Factory";284;3
"Unit";"Cyclone";"Factory";284;3
"Unit";"Cyclone";"Factory";284;3
"Unit";"Cyclone";"Factory";291;3
"Unit";"Cyclone";"Factory";291;3
"Unit";"Cyclone";"Factory";291;3
"Unit";"Cyclone";"Factory";291;3
"Unit";"Cyclone";"Factory";291;3
"Unit";"Battlecruiser";"Starport";262;6
"Unit";"Cyclone";"Factory";300;3
"Unit";"Cyclone";"Factory";300;3
"Unit";"Cyclone";"Factory";300;3
"Building";"StarportTechLab";NA;321;0
"Unit";"Cyclone";"Factory";321;3
"Unit";"Battlecruiser";"Starport";300;6
"Unit";"Battlecruiser";"Starport";321;6
"Unit";"Cyclone";"Factory";339;3
"Unit";"Cyclone";"Factory";345;3
"Unit";"Cyclone";"Factory";345;3
"Unit";"Cyclone";"Factory";345;3
"Upgrade";"TerranShipWeaponsLevel2";"Armory";321;0
"Unit";"Cyclone";"Factory";357;3
"Unit";"Cyclone";"Factory";357;3
"Unit";"Cyclone";"Factory";357;3
"Building";"MissileTurret";NA;357;0
"Building";"MissileTurret";NA;357;0
"Building";"MissileTurret";NA;357;0
"Building";"EngineeringBay";NA;357;0
"Building";"MissileTurret";NA;357;0
"Building";"MissileTurret";NA;357;0
"Building";"EngineeringBay";NA;357;0
"Building";"GhostAcademy";NA;357;0
"Building";"Barracks";NA;357;0
"Building";"Barracks";NA;357;0
"Building";"Barracks";NA;357;0
"Building";"Barracks";NA;357;0
"Building";"Barracks";NA;357;0
"Building";"Barracks";NA;357;0
"Building";"Barracks";NA;357;0
"Building";"Barracks";NA;357;0
"Building";"Barracks";NA;357;0
"Building";"Barracks";NA;357;0
"Building";"Barracks";NA;357;0
"Building";"Barracks";NA;357;0
"Building";"Barracks";NA;357;0
"Building";"Barracks";NA;357;0
"Building";"Barracks";NA;357;0
"Building";"Barracks";NA;357;0
"Building";"Barracks";NA;357;0
"Building";"Barracks";NA;357;0
"Building";"BarracksTechLab";NA;366;0
"Building";"BarracksTechLab";NA;366;0
"Building";"BarracksTechLab";NA;366;0
"Building";"BarracksTechLab";NA;366;0
"Building";"BarracksTechLab";NA;366;0
"Building";"BarracksTechLab";NA;366;0
"Building";"BarracksTechLab";NA;366;0
"Building";"BarracksTechLab";NA;366;0
"Building";"BarracksTechLab";NA;366;0
"Building";"BarracksTechLab";NA;366;0
"Building";"BarracksTechLab";NA;366;0
"Building";"BarracksTechLab";NA;366;0
"Building";"BarracksTechLab";NA;366;0
"Building";"BarracksTechLab";NA;366;0
"Building";"BarracksTechLab";NA;366;0
"Building";"BarracksTechLab";NA;366;0
"Building";"BarracksTechLab";NA;366;0
"Building";"BarracksTechLab";NA;366;0
"Unit";"Cyclone";"Factory";366;3
"Unit";"Cyclone";"Factory";366;3
"Unit";"Cyclone";"Factory";366;3
"Unit";"Cyclone";"Factory";366;3
"Unit";"Cyclone";"Factory";366;3
"Unit";"Cyclone";"Factory";366;3
"Unit";"Cyclone";"Factory";366;3
"Unit";"Cyclone";"Factory";366;3
"Unit";"Banshee";"Starport";366;3
"Unit";"Banshee";"Starport";366;3
"Unit";"Cyclone";"Factory";390;3
"Unit";"Cyclone";"Factory";390;3
"Unit";"Cyclone";"Factory";390;3
"Unit";"Cyclone";"Factory";390;3
"Unit";"Cyclone";"Factory";390;3
"Unit";"Cyclone";"Factory";390;3
"Unit";"Cyclone";"Factory";390;3
"Unit";"Cyclone";"Factory";390;3
"Unit";"Ghost";"Barracks";390;2
"Unit";"Ghost";"Barracks";390;2
"Unit";"Ghost";"Barracks";390;2
"Unit";"Ghost";"Barracks";390;2
"Unit";"Ghost";"Barracks";390;2
"Unit";"Ghost";"Barracks";390;2
"Unit";"Ghost";"Barracks";390;2
"Unit";"Ghost";"Barracks";390;2
"Unit";"Ghost";"Barracks";390;2
"Unit";"Ghost";"Barracks";390;2
"Upgrade";"TerranInfantryWeaponsLevel1";"EngineeringBay";366;0
