"type";"unit_name";"on_building";"total_supply";"supply"
"Building";"Refinery";NA;14;0
"Building";"Barracks";NA;15;0
"Unit";"Marine";"Barracks";19;1
"Building";"Factory";NA;19;0
"Building";"BarracksReactor";NA;21;0
"Unit";"Hellion";"Factory";23;2
"Unit";"Hellion";"Factory";23;2
"Building";"BarracksTechLab";NA;23;0
"Unit";"Hellion";"Factory";27;2
"Building";"Factory";NA;23;0
"Unit";"Hellion";"Factory";28;2
"Building";"Refinery";NA;28;0
"Building";"CommandCenter";NA;22;0
"Unit";"Hellion";"Factory";30;2
"Unit";"Marine";"Barracks";33;1
"Unit";"Hellion";"Factory";31;2
"Unit";"Hellion";"Factory";40;2
"Unit";"Hellion";"Factory";44;2
"Unit";"Hellion";"Factory";44;2
"Unit";"Hellion";"Factory";47;2
"Unit";"Hellion";"Factory";51;2
"Unit";"Hellion";"Factory";52;2
"Unit";"Hellion";"Factory";58;2
"Unit";"Hellion";"Factory";58;2
"Building";"Refinery";NA;62;0
"Building";"Refinery";NA;62;0
"Unit";"Cyclone";"Factory";67;3
"Unit";"Cyclone";"Factory";67;3
"Building";"Factory";NA;67;0
"Unit";"Hellion";"Factory";70;2
"Building";"Factory";NA;67;0
"Unit";"Hellion";"Factory";73;2
"Unit";"Hellion";"Factory";77;2
"Unit";"Cyclone";"Factory";86;3
"Unit";"Cyclone";"Factory";86;3
"Unit";"Hellion";"Factory";86;2
"Unit";"Hellion";"Factory";86;2
"Unit";"Hellion";"Factory";86;2
"Unit";"Hellion";"Factory";86;2
"Unit";"Hellion";"Factory";89;2
"Building";"CommandCenter";NA;82;0
"Building";"FactoryTechLab";NA;106;0
"Unit";"Hellion";"Factory";94;2
"Building";"Armory";NA;92;0
"Unit";"Hellion";"Factory";110;2
"Building";"Factory";NA;106;0
"Unit";"Hellion";"Factory";111;2
"Unit";"Hellion";"Factory";111;2
"Building";"FactoryTechLab";NA;118;0
"Building";"FactoryTechLab";NA;118;0
"Unit";"Hellion";"Factory";118;2
"Building";"Refinery";NA;121;0
"Building";"Refinery";NA;123;0
"Building";"EngineeringBay";NA;123;0
"Building";"EngineeringBay";NA;123;0
"Building";"CommandCenter";NA;114;0
"Unit";"Hellion";"Factory";129;2
"Unit";"Hellion";"Factory";129;2
"Building";"SensorTower";NA;129;0
"Building";"MissileTurret";NA;130;0
"Building";"MissileTurret";NA;130;0
"Unit";"Hellion";"Factory";130;2
"Unit";"Hellion";"Factory";139;2
"Upgrade";"TerranVehicleWeaponsLevel1";"Armory";127;0
"Unit";"Thor";"Factory";136;6
"Building";"Starport";NA;139;0
"Building";"Starport";NA;139;0
"Unit";"Hellion";"Factory";140;2
"Unit";"Hellion";"Factory";140;2
"Building";"Bunker";NA;140;0
"Unit";"Hellion";"Factory";141;2
"Unit";"Hellion";"Factory";153;2
"Unit";"Hellion";"Factory";153;2
"Unit";"Hellion";"Factory";153;2
"Unit";"Hellion";"Factory";156;2
"Unit";"Hellion";"Factory";160;2
"Unit";"Hellion";"Factory";162;2
"Unit";"Hellion";"Factory";165;2
"Unit";"Hellion";"Factory";167;2
"Building";"StarportReactor";NA;163;0
"Building";"StarportReactor";NA;163;0
"Unit";"Thor";"Factory";162;6
"Unit";"Hellion";"Factory";172;2
"Unit";"Hellion";"Factory";174;2
"Building";"CommandCenter";NA;163;0
"Unit";"Hellion";"Factory";187;2
"Unit";"Hellion";"Factory";187;2
"Building";"Refinery";NA;189;0
"Building";"Refinery";NA;190;0
"Unit";"Liberator";"Starport";187;3
"Unit";"Liberator";"Starport";187;3
"Unit";"Liberator";"Starport";187;3
"Building";"CommandCenter";NA;177;0
"Building";"Armory";NA;188;0
"Unit";"Hellion";"Factory";194;2
"Unit";"Hellion";"Factory";194;2
