"Type";"UnitName";"OnBuilding";"TotalSupply";"Supply"
"Unit";"SCV";"Command Center";12;1
"Unit";"SCV";"Command Center";12;1
"Unit";"SCV";"Command Center";13;1
"Building";"SupplyDepot";NA;13;0
"Unit";"SCV";"Command Center";15;1
"Unit";"SCV";"Command Center";15;1
"Building";"Refinery";NA;15;0
"Unit";"SCV";"Command Center";16;1
"Building";"Barracks";NA;15;0
"Unit";"SCV";"Command Center";17;1
"Unit";"Reaper";"Barracks";19;1
"Unit";"SCV";"Command Center";19;1
"Building";"SupplyDepot";NA;19;0
"Unit";"Marine";"Barracks";19;1
"Unit";"SCV";"Command Center";21;1
"Unit";"SCV";"Command Center";22;1
"Unit";"SCV";"Command Center";23;1
"Building";"CommandCenter";NA;19;0
"Building";"BarracksReactor";NA;22;0
"Building";"Factory";NA;21;0
"Unit";"SCV";"Command Center";24;1
"Unit";"SCV";"Command Center";25;1
"Unit";"SCV";"Command Center";26;1
"Unit";"Hellion";"Factory";26;2
"Unit";"Hellion";"Factory";26;2
"Unit";"SCV";"Command Center";27;1
"Unit";"SCV";"Command Center";32;1
"Building";"Refinery";NA;32;0
"Building";"Starport";NA;27;0
"Unit";"Hellion";"Factory";33;2
"Unit";"Hellion";"Factory";33;2
"Unit";"SCV";"Command Center";34;1
"Building";"BarracksTechLab";NA;34;0
"Unit";"SCV";"Command Center";34;1
"Building";"StarportTechLab";NA;34;0
"Unit";"SCV";"Command Center";38;1
"Unit";"SCV";"Command Center";41;1
"Building";"CommandCenter";NA;27;0
"Unit";"SCV";"Command Center";41;1
"Unit";"SCV";"Command Center";41;1
"Unit";"SCV";"Command Center";43;1
"Unit";"Marine";"Barracks";43;1
"Unit";"SCV";"Command Center";44;1
"Unit";"SCV";"Command Center";44;1
"Building";"Barracks";NA;40;0
"Building";"Barracks";NA;40;0
"Unit";"SCV";"Command Center";46;1
"Building";"EngineeringBay";NA;44;0
"Building";"FactoryReactor";NA;43;0
"Unit";"SCV";"Command Center";47;1
"Building";"EngineeringBay";NA;45;0
"Building";"Refinery";NA;48;0
"Building";"Refinery";NA;48;0
"Unit";"SCV";"Command Center";50;1
"Unit";"SCV";"Command Center";50;1
"Unit";"Marine";"Barracks";49;1
"Unit";"Marine";"Barracks";49;1
"Building";"SupplyDepot";NA;48;0
"Building";"SupplyDepot";NA;49;0
"Unit";"Marine";"Barracks";50;1
"Building";"StarportReactor";NA;48;0
"Unit";"SCV";"Command Center";50;1
"Unit";"SCV";"Command Center";55;1
"Unit";"Marine";"Barracks";55;1
"Unit";"Marine";"Barracks";55;1
"Unit";"Marine";"Barracks";56;1
"Unit";"Marine";"Barracks";56;1
"Unit";"Marine";"Barracks";56;1
"Unit";"SCV";"Command Center";57;1
"Unit";"SCV";"Command Center";57;1
"Unit";"SCV";"Command Center";61;1
"Building";"SupplyDepot";NA;56;0
"Building";"SupplyDepot";NA;56;0
"Unit";"Marine";"Barracks";59;1
"Unit";"Marine";"Barracks";59;1
"Unit";"Medivac";"Starport";56;2
"Unit";"SCV";"Command Center";62;1
"Unit";"SCV";"Command Center";63;1
"Unit";"Medivac";"Starport";56;2
"Upgrade";"Stimpack";"TechLab";45;0
"Unit";"SCV";"Command Center";64;1
"Unit";"Marine";"Barracks";64;1
"Unit";"Marine";"Barracks";64;1
"Unit";"Marine";"Barracks";64;1
"Unit";"SCV";"Command Center";73;1
"Building";"SupplyDepot";NA;65;0
"Building";"SupplyDepot";NA;65;0
"Unit";"Marine";"Barracks";77;1
"Unit";"Marine";"Barracks";77;1
"Unit";"Marine";"Barracks";77;1
"Unit";"Marine";"Barracks";78;1
"Unit";"Marine";"Barracks";78;1
"Unit";"Marine";"Barracks";78;1
"Unit";"Marine";"Barracks";79;1
"Unit";"Marine";"Barracks";80;1
"Unit";"Marine";"Barracks";81;1
"Building";"SupplyDepot";NA;80;0
"Unit";"Marine";"Barracks";82;1
"Building";"SupplyDepot";NA;82;0
"Building";"SupplyDepot";NA;82;0
"Unit";"Marine";"Barracks";83;1
"Unit";"Marine";"Barracks";84;1
"Unit";"Marine";"Barracks";85;1
"Unit";"Marine";"Barracks";86;1
"Upgrade";"TerranInfantryWeaponsLevel1";"EngineeringBay";62;0
"Unit";"Marine";"Barracks";87;1
"Building";"Barracks";NA;82;0
"Building";"Barracks";NA;82;0
"Unit";"Marine";"Barracks";88;1
"Unit";"Marine";"Barracks";89;1
"Unit";"Marine";"Barracks";90;1
"Unit";"Marine";"Barracks";91;1
"Unit";"Marine";"Barracks";92;1
"Unit";"SCV";"Command Center";93;1
"Unit";"SCV";"Command Center";93;1
"Unit";"SCV";"Command Center";97;1
"Unit";"Marine";"Barracks";93;1
"Unit";"Marine";"Barracks";93;1
"Unit";"Marine";"Barracks";93;1
"Unit";"Medivac";"Starport";93;2
"Unit";"Marine";"Barracks";94;1
"Unit";"Medivac";"Starport";93;2
"Unit";"Marine";"Barracks";95;1
"Unit";"SCV";"Command Center";98;1
"Unit";"SCV";"Command Center";99;1
"Unit";"Marine";"Barracks";97;1
"Unit";"Marine";"Barracks";97;1
"Unit";"SCV";"Command Center";110;1
"Unit";"SCV";"Command Center";110;1
"Unit";"SCV";"Command Center";113;1
"Building";"EngineeringBay";NA;92;0
"Unit";"SCV";"Command Center";114;1
"Unit";"SCV";"Command Center";115;1
"Unit";"Marine";"Barracks";114;1
"Unit";"Marine";"Barracks";114;1
"Unit";"SCV";"Command Center";117;1
"Unit";"Medivac";"Starport";103;2
"Unit";"Medivac";"Starport";106;2
"Unit";"SCV";"Command Center";117;1
"Unit";"SCV";"Command Center";118;1
"Unit";"SCV";"Command Center";121;1
"Building";"BarracksReactor";NA;114;0
"Building";"BarracksReactor";NA;114;0
"Unit";"Marine";"Barracks";126;1
"Unit";"Marine";"Barracks";126;1
"Unit";"Marine";"Barracks";126;1
"Unit";"Marine";"Barracks";126;1
"Unit";"Marine";"Barracks";126;1
"Unit";"SCV";"Command Center";127;1
"Unit";"SCV";"Command Center";128;1
"Building";"SupplyDepot";NA;126;0
"Unit";"SCV";"Command Center";129;1
"Building";"SupplyDepot";NA;126;0
"Unit";"SCV";"Command Center";134;1
"Building";"Armory";NA;117;0
"Unit";"Marine";"Barracks";137;1
"Unit";"Marine";"Barracks";138;1
"Unit";"Marine";"Barracks";138;1
"Unit";"Marine";"Barracks";138;1
"Unit";"Marine";"Barracks";138;1
"Unit";"Marine";"Barracks";138;1
"Unit";"Marine";"Barracks";138;1
"Unit";"Marine";"Barracks";138;1
"Unit";"Marauder";"Barracks";137;2
"Unit";"SCV";"Command Center";146;1
"Unit";"SCV";"Command Center";148;1
"Unit";"SCV";"Command Center";148;1
"Unit";"Marine";"Barracks";138;1
"Building";"MissileTurret";NA;148;0
"Building";"SupplyDepot";NA;151;0
"Unit";"Liberator";"Starport";138;3
"Unit";"Liberator";"Starport";138;3
"Unit";"Marine";"Barracks";152;1
"Unit";"Marine";"Barracks";152;1
"Building";"Refinery";NA;152;0
"Building";"Refinery";NA;152;0
"Unit";"Marauder";"Barracks";152;2
"Unit";"Marine";"Barracks";152;1
"Unit";"Marine";"Barracks";152;1
"Unit";"Marine";"Barracks";152;1
"Unit";"Marine";"Barracks";152;1
"Unit";"Marine";"Barracks";152;1
"Unit";"Marine";"Barracks";152;1
"Building";"SupplyDepot";NA;152;0
"Building";"SupplyDepot";NA;152;0
"Unit";"Marine";"Barracks";168;1
"Unit";"Marine";"Barracks";168;1
"Unit";"Marine";"Barracks";168;1
"Unit";"Marine";"Barracks";168;1
"Unit";"Marine";"Barracks";168;1
"Building";"Factory";NA;152;0
"Building";"SupplyDepot";NA;168;0
"Building";"SupplyDepot";NA;168;0
"Building";"SupplyDepot";NA;168;0
"Building";"SupplyDepot";NA;168;0
"Unit";"Marine";"Barracks";168;1
"Unit";"Marine";"Barracks";168;1
"Unit";"Marine";"Barracks";168;1
"Unit";"Marine";"Barracks";168;1
"Unit";"Marine";"Barracks";168;1
"Unit";"Liberator";"Starport";162;3
"Unit";"Marine";"Barracks";173;1
"Unit";"Marine";"Barracks";173;1
"Unit";"Marine";"Barracks";177;1
"Unit";"Marine";"Barracks";177;1
"Unit";"Marine";"Barracks";177;1
"Building";"FactoryTechLab";NA;177;0
"Unit";"Marine";"Barracks";178;1
"Unit";"Marine";"Barracks";178;1
"Upgrade";"TerranInfantryArmorsLevel1";"EngineeringBay";152;0
"Unit";"Marauder";"Barracks";178;2
"Unit";"Medivac";"Starport";177;2
"Unit";"Marine";"Barracks";188;1
"Unit";"Marine";"Barracks";188;1
"Unit";"Marine";"Barracks";188;1
"Unit";"Marine";"Barracks";188;1
"Unit";"Marine";"Barracks";188;1
"Unit";"Marine";"Barracks";188;1
"Unit";"Marine";"Barracks";188;1
"Unit";"Marine";"Barracks";188;1
"Unit";"Marine";"Barracks";188;1
"Upgrade";"TerranInfantryWeaponsLevel2";"EngineeringBay";152;0
"Unit";"Marine";"Barracks";200;1
"Unit";"Marine";"Barracks";201;1
"Unit";"Marine";"Barracks";201;1
"Unit";"Marine";"Barracks";201;1
"Unit";"Marine";"Barracks";201;1
"Unit";"Marine";"Barracks";201;1
"Unit";"Marine";"Barracks";201;1
"Unit";"Marine";"Barracks";201;1
"Unit";"Marine";"Barracks";201;1
"Unit";"Liberator";"Starport";190;3
"Unit";"Medivac";"Starport";200;2
"Building";"CommandCenter";NA;178;0
"Unit";"Marine";"Barracks";210;1
"Unit";"Marine";"Barracks";210;1
"Unit";"Marine";"Barracks";210;1
"Unit";"Marine";"Barracks";210;1
"Unit";"Marine";"Barracks";210;1
"Unit";"Marine";"Barracks";210;1
"Unit";"Marine";"Barracks";210;1
"Unit";"Marine";"Barracks";210;1
"Unit";"Marine";"Barracks";210;1
"Upgrade";"TerranVehicleWeaponsLevel1";"Armory";183;0
"Unit";"Marine";"Barracks";215;1
"Unit";"Marine";"Barracks";216;1
"Unit";"Marine";"Barracks";217;1
"Unit";"Marauder";"Barracks";221;2
"Unit";"Marine";"Barracks";224;1
"Unit";"Liberator";"Starport";210;3
"Unit";"Marine";"Barracks";224;1
"Unit";"Liberator";"Starport";215;3
"Unit";"Marine";"Barracks";229;1
"Unit";"Marine";"Barracks";229;1
"Unit";"Marauder";"Barracks";227;2
"Unit";"Marine";"Barracks";234;1
"Unit";"Marine";"Barracks";234;1
"Unit";"Marine";"Barracks";234;1
"Unit";"Marine";"Barracks";234;1
"Unit";"Marine";"Barracks";234;1
"Unit";"Marine";"Barracks";234;1
"Unit";"Marine";"Barracks";237;1
"Unit";"Marine";"Barracks";241;1
"Unit";"Marine";"Barracks";241;1
"Unit";"Marine";"Barracks";241;1
"Unit";"Marine";"Barracks";242;1
"Unit";"Marine";"Barracks";243;1
"Unit";"Marine";"Barracks";248;1
"Unit";"Marine";"Barracks";248;1
"Unit";"Marine";"Barracks";248;1
"Unit";"Marine";"Barracks";248;1
"Unit";"Marine";"Barracks";248;1
"Unit";"Marine";"Barracks";251;1
"Unit";"Marauder";"Barracks";249;2
"Unit";"Marine";"Barracks";251;1
"Unit";"Marine";"Barracks";252;1
"Unit";"Marine";"Barracks";253;1
"Upgrade";"TerranInfantryArmorsLevel2";"EngineeringBay";224;0
"Unit";"Marine";"Barracks";254;1
"Unit";"Marine";"Barracks";255;1
"Unit";"Marine";"Barracks";256;1
"Unit";"Marine";"Barracks";257;1
"Unit";"Marine";"Barracks";258;1
"Unit";"Marauder";"Barracks";259;2
"Unit";"Marine";"Barracks";261;1
"Unit";"Marine";"Barracks";263;1
"Unit";"Marine";"Barracks";263;1
"Unit";"Marine";"Barracks";264;1
"Unit";"Marine";"Barracks";265;1
"Unit";"Marine";"Barracks";272;1
"Unit";"Marine";"Barracks";276;1
"Unit";"Marine";"Barracks";276;1
"Unit";"Marine";"Barracks";277;1
"Unit";"Marine";"Barracks";277;1
"Unit";"Marine";"Barracks";277;1
"Unit";"Marine";"Barracks";277;1
"Unit";"Marine";"Barracks";277;1
"Unit";"Marine";"Barracks";277;1
"Unit";"Marauder";"Barracks";277;2
"Unit";"Marine";"Barracks";277;1
"Unit";"Marine";"Barracks";278;1
"Unit";"Marine";"Barracks";279;1
"Unit";"Marine";"Barracks";280;1
"Unit";"Marine";"Barracks";281;1
"Unit";"Liberator";"Starport";278;3
"Unit";"Marine";"Barracks";295;1
"Unit";"Marine";"Barracks";295;1
"Unit";"Marine";"Barracks";295;1
"Unit";"Marine";"Barracks";295;1
"Unit";"Marine";"Barracks";295;1
"Unit";"Marine";"Barracks";295;1
"Upgrade";"TerranVehicleWeaponsLevel2";"Armory";277;0
"Unit";"Marine";"Barracks";295;1
"Upgrade";"TerranInfantryWeaponsLevel3";"EngineeringBay";276;0
"Unit";"Marine";"Barracks";298;1
"Unit";"Marine";"Barracks";298;1
"Unit";"Marine";"Barracks";298;1
"Unit";"Marine";"Barracks";298;1
"Unit";"Marauder";"Barracks";298;2
"Unit";"Marine";"Barracks";302;1
"Unit";"Marine";"Barracks";302;1
"Unit";"Marine";"Barracks";302;1
"Unit";"Liberator";"Starport";298;3
