"Type";"UnitName";"OnBuilding";"TotalSupply";"Supply"
"Unit";"SCV";"Command Center";12;1
"Unit";"SCV";"Command Center";12;1
"Unit";"SCV";"Command Center";13;1
"Building";"SupplyDepot";NA;13;0
"Unit";"SCV";"Command Center";15;1
"Unit";"SCV";"Command Center";16;1
"Building";"Refinery";NA;15;0
"Unit";"SCV";"Command Center";16;1
"Building";"Barracks";NA;15;0
"Unit";"SCV";"Command Center";17;1
"Unit";"Reaper";"Barracks";19;1
"Unit";"SCV";"Command Center";19;1
"Building";"SupplyDepot";NA;19;0
"Unit";"Marine";"Barracks";19;1
"Unit";"SCV";"Command Center";20;1
"Unit";"SCV";"Command Center";22;1
"Building";"Refinery";NA;23;0
"Unit";"SCV";"Command Center";23;1
"Building";"CommandCenter";NA;19;0
"Unit";"SCV";"Command Center";24;1
"Building";"BarracksReactor";NA;23;0
"Building";"Factory";NA;23;0
"Unit";"SCV";"Command Center";26;1
"Building";"SupplyDepot";NA;26;0
"Unit";"SCV";"Command Center";26;1
"Building";"BarracksTechLab";NA;26;0
"Unit";"SCV";"Command Center";27;1
"Unit";"Hellion";"Factory";27;2
"Unit";"Hellion";"Factory";27;2
"Unit";"SCV";"Command Center";27;1
"Building";"Starport";NA;26;0
"Unit";"SCV";"Command Center";28;1
"Unit";"SCV";"Command Center";33;1
"Unit";"Marine";"Barracks";28;1
"Building";"SupplyDepot";NA;28;0
"Unit";"SCV";"Command Center";34;1
"Unit";"Hellion";"Factory";34;2
"Unit";"Hellion";"Factory";34;2
"Unit";"SCV";"Command Center";35;1
"Unit";"SCV";"Command Center";38;1
"Unit";"SCV";"Command Center";43;1
"Building";"SupplyDepot";NA;40;0
"Unit";"Hellion";"Factory";42;2
"Unit";"Hellion";"Factory";43;2
"Unit";"SCV";"Command Center";43;1
"Unit";"Marine";"Barracks";43;1
"Unit";"SCV";"Command Center";45;1
"Unit";"SCV";"Command Center";52;1
"Unit";"SCV";"Command Center";52;1
"Unit";"SCV";"Command Center";52;1
"Unit";"SCV";"Command Center";53;1
"Unit";"Liberator";"Starport";50;3
"Unit";"SCV";"Command Center";54;1
"Unit";"Marine";"Barracks";54;1
"Building";"FactoryReactor";NA;52;0
"Building";"Refinery";NA;54;0
"Building";"Refinery";NA;54;0
"Unit";"SCV";"Command Center";56;1
"Unit";"SCV";"Command Center";59;1
"Unit";"SCV";"Command Center";61;1
"Building";"Barracks";NA;52;0
"Building";"Barracks";NA;54;0
"Unit";"SCV";"Command Center";62;1
"Upgrade";"Stimpack";"TechLab";43;0
"Building";"CommandCenter";NA;50;0
"Unit";"Marine";"Barracks";62;1
"Unit";"SCV";"Command Center";63;1
"Building";"FactoryTechLab";NA;65;0
"Building";"EngineeringBay";NA;63;0
"Unit";"SCV";"Command Center";66;1
"Building";"EngineeringBay";NA;63;0
"Unit";"Marine";"Barracks";65;1
"Unit";"Marine";"Barracks";65;1
"Unit";"SCV";"Command Center";66;1
"Unit";"Marine";"Barracks";66;1
"Building";"StarportReactor";NA;63;0
"Unit";"Marine";"Barracks";67;1
"Unit";"Marine";"Barracks";67;1
"Building";"Bunker";NA;66;0
"Unit";"Marine";"Barracks";71;1
"Unit";"Marine";"Barracks";71;1
"Unit";"SCV";"Command Center";74;1
"Unit";"SCV";"Command Center";74;1
"Unit";"Marine";"Barracks";74;1
"Unit";"SCV";"Command Center";74;1
"Unit";"Marine";"Barracks";74;1
"Unit";"SCV";"Command Center";76;1
"Unit";"Marine";"Barracks";74;1
"Unit";"Medivac";"Starport";74;2
"Unit";"Medivac";"Starport";74;2
"Building";"Barracks";NA;68;0
"Building";"Barracks";NA;70;0
"Building";"SupplyDepot";NA;80;0
"Unit";"Marine";"Barracks";87;1
"Unit";"Marine";"Barracks";87;1
"Unit";"Marine";"Barracks";87;1
"Unit";"Marine";"Barracks";87;1
"Unit";"Marine";"Barracks";87;1
"Unit";"Marine";"Barracks";87;1
"Unit";"Marine";"Barracks";87;1
"Unit";"Marine";"Barracks";87;1
"Unit";"Marine";"Barracks";87;1
"Unit";"Marine";"Barracks";91;1
"Unit";"Marine";"Barracks";91;1
"Unit";"Marine";"Barracks";92;1
"Unit";"Marine";"Barracks";92;1
"Unit";"SCV";"Command Center";100;1
"Unit";"SCV";"Command Center";100;1
"Unit";"SCV";"Command Center";100;1
"Unit";"Marine";"Barracks";100;1
"Upgrade";"TerranInfantryArmorsLevel1";"EngineeringBay";80;0
"Unit";"Marine";"Barracks";100;1
"Unit";"Marine";"Barracks";100;1
"Unit";"Marine";"Barracks";100;1
"Unit";"Marine";"Barracks";100;1
"Unit";"SCV";"Command Center";100;1
"Unit";"SCV";"Command Center";101;1
"Unit";"SCV";"Command Center";102;1
"Building";"BarracksReactor";NA;100;0
"Unit";"Medivac";"Starport";100;2
"Unit";"Medivac";"Starport";100;2
"Upgrade";"TerranInfantryWeaponsLevel1";"EngineeringBay";87;0
"Unit";"Marine";"Barracks";111;1
"Unit";"Marine";"Barracks";111;1
"Unit";"Marine";"Barracks";111;1
"Unit";"Marine";"Barracks";111;1
"Unit";"Marine";"Barracks";111;1
"Unit";"Marine";"Barracks";111;1
"Unit";"Marine";"Barracks";111;1
"Unit";"Marine";"Barracks";111;1
"Building";"Armory";NA;100;0
"Unit";"Marine";"Barracks";115;1
"Unit";"Marine";"Barracks";116;1
"Unit";"SCV";"Command Center";123;1
"Unit";"Marine";"Barracks";123;1
"Unit";"Marine";"Barracks";123;1
"Unit";"Marine";"Barracks";123;1
"Unit";"SCV";"Command Center";125;1
"Unit";"SCV";"Command Center";125;1
"Unit";"SCV";"Command Center";125;1
"Unit";"Marine";"Barracks";129;1
"Unit";"SCV";"Command Center";132;1
"Unit";"SCV";"Command Center";132;1
"Unit";"SCV";"Command Center";132;1
"Unit";"Marine";"Barracks";132;1
"Unit";"Marine";"Barracks";132;1
"Unit";"Marine";"Barracks";132;1
"Unit";"SCV";"Command Center";136;1
"Unit";"SCV";"Command Center";136;1
"Unit";"SCV";"Command Center";136;1
"Unit";"Marine";"Barracks";133;1
"Unit";"Marine";"Barracks";133;1
"Unit";"Marine";"Barracks";133;1
