"Type";"UnitName";"OnBuilding";"TotalSupply";"Supply"
"Unit";"SCV";"Command Center";12;1
"Unit";"SCV";"Command Center";12;1
"Unit";"SCV";"Command Center";13;1
"Building";"SupplyDepot";NA;13;0
"Building";"Refinery";NA;14;0
"Unit";"SCV";"Command Center";15;1
"Unit";"SCV";"Command Center";16;1
"Unit";"SCV";"Command Center";16;1
"Unit";"SCV";"Command Center";17;1
"Building";"Barracks";NA;15;0
"Unit";"Reaper";"Barracks";19;1
"Unit";"SCV";"Command Center";19;1
"Unit";"SCV";"Command Center";21;1
"Building";"SupplyDepot";NA;21;0
"Unit";"SCV";"Command Center";21;1
"Building";"Factory";NA;19;0
"Building";"BarracksReactor";NA;20;0
"Building";"Refinery";NA;21;0
"Unit";"Marine";"Barracks";23;1
"Unit";"Marine";"Barracks";23;1
"Building";"CommandCenter";NA;19;0
"Unit";"SCV";"Command Center";23;1
"Unit";"SCV";"Command Center";26;1
"Unit";"SCV";"Command Center";26;1
"Building";"BarracksTechLab";NA;26;0
"Unit";"Hellion";"Factory";26;2
"Unit";"Hellion";"Factory";26;2
"Building";"Starport";NA;25;0
"Unit";"SCV";"Command Center";27;1
"Building";"SupplyDepot";NA;27;0
"Unit";"SCV";"Command Center";32;1
"Unit";"Hellion";"Factory";32;2
"Unit";"Hellion";"Factory";32;2
"Unit";"SCV";"Command Center";33;1
"Unit";"SCV";"Command Center";34;1
"Unit";"SCV";"Command Center";39;1
"Building";"SupplyDepot";NA;34;0
"Unit";"SCV";"Command Center";40;1
"Unit";"Hellion";"Factory";39;2
"Unit";"SCV";"Command Center";41;1
"Unit";"Hellion";"Factory";39;2
"Unit";"Banshee";"Starport";33;3
"Building";"BarracksTechLab";NA;40;0
"Building";"SupplyDepot";NA;41;0
"Unit";"SCV";"Command Center";50;1
"Unit";"SCV";"Command Center";50;1
"Unit";"Marine";"Barracks";50;1
"Unit";"SCV";"Command Center";50;1
"Unit";"SCV";"Command Center";51;1
"Unit";"SCV";"Command Center";53;1
"Unit";"SCV";"Command Center";55;1
"Unit";"Marine";"Barracks";53;1
"Unit";"Banshee";"Starport";50;3
"Unit";"SCV";"Command Center";55;1
"Unit";"SCV";"Command Center";56;1
"Building";"FactoryReactor";NA;53;0
"Unit";"SCV";"Command Center";61;1
"Unit";"Marine";"Barracks";61;1
"Unit";"SCV";"Command Center";62;1
"Building";"EngineeringBay";NA;57;0
"Building";"EngineeringBay";NA;58;0
"Unit";"SCV";"Command Center";63;1
"Unit";"SCV";"Command Center";65;1
"Unit";"Marine";"Barracks";65;1
"Unit";"SCV";"Command Center";66;1
"Building";"Barracks";NA;58;0
"Unit";"SCV";"Command Center";67;1
"Building";"Barracks";NA;58;0
"Building";"CommandCenter";NA;52;0
"Building";"Refinery";NA;66;0
"Building";"Refinery";NA;66;0
"Unit";"SCV";"Command Center";69;1
"Building";"StarportReactor";NA;64;0
"Building";"SupplyDepot";NA;68;0
"Unit";"SCV";"Command Center";70;1
"Unit";"Marine";"Barracks";69;1
"Unit";"SCV";"Command Center";71;1
"Building";"SupplyDepot";NA;71;0
"Unit";"SCV";"Command Center";72;1
"Unit";"Marine";"Barracks";71;1
"Unit";"Marine";"Barracks";71;1
"Unit";"SCV";"Command Center";74;1
"Unit";"SCV";"Command Center";76;1
"Upgrade";"Stimpack";"TechLab";61;0
"Unit";"SCV";"Command Center";78;1
"Unit";"Marine";"Barracks";78;1
"Unit";"Marine";"Barracks";78;1
"Unit";"SCV";"Command Center";79;1
"Unit";"Marine";"Barracks";78;1
"Unit";"SCV";"Command Center";80;1
"Unit";"SCV";"Command Center";83;1
"Unit";"Marine";"Barracks";80;1
"Unit";"Medivac";"Starport";78;2
"Unit";"Marine";"Barracks";80;1
"Unit";"Medivac";"Starport";78;2
"Unit";"Marine";"Barracks";81;1
"Unit";"Marine";"Barracks";82;1
"Unit";"SCV";"Command Center";85;1
"Building";"Barracks";NA;78;0
"Unit";"Marine";"Barracks";86;1
"Unit";"Marine";"Barracks";87;1
"Unit";"Marine";"Barracks";90;1
"Building";"Barracks";NA;79;0
"Unit";"SCV";"Command Center";96;1
"Unit";"SCV";"Command Center";96;1
"Unit";"Marine";"Barracks";95;1
"Unit";"Marine";"Barracks";95;1
"Building";"SupplyDepot";NA;95;0
"Building";"SupplyDepot";NA;95;0
"Upgrade";"TerranInfantryWeaponsLevel1";"EngineeringBay";73;0
"Upgrade";"TerranInfantryArmorsLevel1";"EngineeringBay";73;0
"Unit";"Marine";"Barracks";96;1
"Unit";"SCV";"Command Center";99;1
"Unit";"SCV";"Command Center";100;1
"Unit";"Marine";"Barracks";97;1
"Unit";"Marine";"Barracks";103;1
"Unit";"Marine";"Barracks";103;1
"Unit";"SCV";"Command Center";104;1
"Unit";"SCV";"Command Center";104;1
"Building";"SupplyDepot";NA;107;0
"Unit";"SCV";"Command Center";110;1
"Unit";"SCV";"Command Center";110;1
"Unit";"SCV";"Command Center";111;1
"Building";"SupplyDepot";NA;107;0
"Unit";"Marine";"Barracks";107;1
"Unit";"Marine";"Barracks";108;1
"Unit";"Marine";"Barracks";109;1
"Building";"SupplyDepot";NA;107;0
"Unit";"Marine";"Barracks";109;1
"Building";"Armory";NA;99;0
"Building";"SupplyDepot";NA;107;0
"Building";"BarracksReactor";NA;103;0
"Building";"BarracksReactor";NA;103;0
"Unit";"SCV";"Command Center";111;1
"Unit";"SCV";"Command Center";112;1
"Unit";"SCV";"Command Center";114;1
"Unit";"Marine";"Barracks";111;1
"Building";"Refinery";NA;111;0
"Building";"Refinery";NA;111;0
"Unit";"Marine";"Barracks";114;1
"Unit";"Marine";"Barracks";115;1
"Unit";"SCV";"Command Center";118;1
"Unit";"Marine";"Barracks";118;1
"Building";"SupplyDepot";NA;118;0
"Building";"SupplyDepot";NA;118;0
"Unit";"Medivac";"Starport";114;2
"Unit";"Medivac";"Starport";114;2
"Unit";"SCV";"Command Center";122;1
"Unit";"SCV";"Command Center";122;1
"Unit";"Marine";"Barracks";120;1
"Unit";"Marine";"Barracks";120;1
"Unit";"Marine";"Barracks";120;1
"Unit";"Marine";"Barracks";120;1
"Unit";"Marine";"Barracks";120;1
"Unit";"Marine";"Barracks";121;1
"Unit";"SCV";"Command Center";124;1
"Unit";"Marine";"Barracks";122;1
"Unit";"Marine";"Barracks";123;1
"Unit";"Marine";"Barracks";130;1
"Unit";"Marine";"Barracks";132;1
"Unit";"Marine";"Barracks";133;1
"Unit";"Marine";"Barracks";134;1
"Building";"Factory";NA;118;0
"Building";"SupplyDepot";NA;130;0
"Building";"SupplyDepot";NA;130;0
"Unit";"Marine";"Barracks";138;1
"Unit";"Marine";"Barracks";138;1
"Unit";"Marine";"Barracks";138;1
"Unit";"Marine";"Barracks";139;1
"Unit";"Marine";"Barracks";140;1
"Unit";"Marine";"Barracks";141;1
"Unit";"Marine";"Barracks";142;1
"Unit";"Marine";"Barracks";143;1
"Unit";"Marine";"Barracks";150;1
"Unit";"Marine";"Barracks";150;1
"Unit";"Marine";"Barracks";150;1
"Unit";"Marine";"Barracks";150;1
"Unit";"Marine";"Barracks";150;1
"Unit";"Marine";"Barracks";150;1
"Unit";"Marine";"Barracks";150;1
"Unit";"Marine";"Barracks";151;1
"Unit";"Marine";"Barracks";152;1
"Unit";"Marine";"Barracks";153;1
"Unit";"Marine";"Barracks";154;1
"Unit";"Marine";"Barracks";155;1
"Unit";"Marine";"Barracks";156;1
"Unit";"Marine";"Barracks";156;1
"Unit";"Marine";"Barracks";158;1
"Unit";"Medivac";"Starport";153;2
"Unit";"Marine";"Barracks";159;1
"Unit";"Marine";"Barracks";160;1
"Unit";"Marine";"Barracks";161;1
"Building";"FactoryTechLab";NA;162;0
"Unit";"Medivac";"Starport";162;2
"Unit";"Marine";"Barracks";162;1
"Unit";"Marine";"Barracks";163;1
"Unit";"Marine";"Barracks";164;1
"Unit";"Marine";"Barracks";165;1
"Unit";"Marauder";"Barracks";167;2
"Unit";"Marauder";"Barracks";179;2
"Upgrade";"TerranInfantryWeaponsLevel2";"EngineeringBay";141;0
"Upgrade";"TerranInfantryArmorsLevel2";"EngineeringBay";141;0
"Building";"Barracks";NA;162;0
"Building";"Barracks";NA;171;0
"Building";"CommandCenter";NA;162;0
"Unit";"Marine";"Barracks";183;1
"Unit";"Marine";"Barracks";183;1
"Unit";"Marine";"Barracks";183;1
"Unit";"Marine";"Barracks";183;1
"Unit";"Marine";"Barracks";183;1
"Unit";"Marine";"Barracks";183;1
"Unit";"Marine";"Barracks";183;1
"Unit";"Marine";"Barracks";183;1
"Unit";"Marine";"Barracks";183;1
"Unit";"Marine";"Barracks";183;1
"Unit";"Marine";"Barracks";183;1
"Unit";"Marine";"Barracks";183;1
"Unit";"Marine";"Barracks";184;1
"Unit";"Marine";"Barracks";184;1
"Unit";"Marine";"Barracks";186;1
"Unit";"Marine";"Barracks";186;1
"Unit";"Marine";"Barracks";186;1
"Unit";"Marine";"Barracks";186;1
"Unit";"Marine";"Barracks";186;1
"Unit";"Marine";"Barracks";186;1
"Unit";"Marine";"Barracks";186;1
"Unit";"Marauder";"Barracks";186;2
"Unit";"Marine";"Barracks";194;1
"Unit";"Marine";"Barracks";195;1
"Unit";"Marine";"Barracks";195;1
"Unit";"Marine";"Barracks";197;1
"Unit";"Marine";"Barracks";197;1
"Unit";"Marine";"Barracks";197;1
"Unit";"Marine";"Barracks";197;1
"Unit";"Marine";"Barracks";197;1
"Unit";"Marine";"Barracks";197;1
"Unit";"Marine";"Barracks";204;1
"Unit";"Medivac";"Starport";194;2
"Unit";"Marauder";"Barracks";204;2
"Unit";"Cyclone";"Factory";206;3
"Unit";"Marine";"Barracks";206;1
"Unit";"Marine";"Barracks";207;1
"Unit";"Marine";"Barracks";207;1
"Unit";"Marine";"Barracks";209;1
"Unit";"Marine";"Barracks";209;1
"Unit";"Marine";"Barracks";209;1
"Unit";"Marine";"Barracks";209;1
"Unit";"Marine";"Barracks";209;1
"Building";"BarracksTechLab";NA;215;0
"Unit";"Marine";"Barracks";215;1
"Unit";"Marine";"Barracks";218;1
"Unit";"Marine";"Barracks";223;1
"Building";"GhostAcademy";NA;216;0
"Unit";"Medivac";"Starport";218;2
"Unit";"Medivac";"Starport";218;2
"Unit";"Marine";"Barracks";224;1
"Unit";"Marine";"Barracks";224;1
"Unit";"Marine";"Barracks";226;1
"Unit";"Marine";"Barracks";226;1
"Unit";"Marine";"Barracks";226;1
"Unit";"Marine";"Barracks";231;1
"Unit";"Marine";"Barracks";231;1
"Unit";"Marine";"Barracks";233;1
"Unit";"Marine";"Barracks";233;1
"Unit";"Marauder";"Barracks";233;2
"Unit";"Marine";"Barracks";247;1
"Unit";"Marine";"Barracks";250;1
"Unit";"Marine";"Barracks";250;1
"Unit";"Marine";"Barracks";250;1
"Unit";"Marine";"Barracks";250;1
"Unit";"Marine";"Barracks";250;1
"Unit";"Marine";"Barracks";250;1
"Unit";"Marine";"Barracks";250;1
"Unit";"Marine";"Barracks";250;1
"Unit";"Marine";"Barracks";250;1
"Unit";"Marauder";"Barracks";250;2
"Unit";"Marauder";"Barracks";250;2
"Unit";"Marine";"Barracks";250;1
"Unit";"Marine";"Barracks";251;1
"Unit";"Marine";"Barracks";252;1
"Unit";"Marine";"Barracks";266;1
"Unit";"Marine";"Barracks";266;1
"Unit";"Marine";"Barracks";266;1
"Unit";"Marine";"Barracks";266;1
"Unit";"Marine";"Barracks";266;1
"Unit";"Marine";"Barracks";266;1
"Unit";"Marine";"Barracks";266;1
"Unit";"Marine";"Barracks";266;1
"Unit";"Marine";"Barracks";266;1
"Unit";"Marine";"Barracks";266;1
"Unit";"Marauder";"Barracks";266;2
"Unit";"Marine";"Barracks";266;1
"Unit";"Marine";"Barracks";267;1
"Unit";"Marine";"Barracks";268;1
"Unit";"Marine";"Barracks";269;1
"Unit";"Marine";"Barracks";271;1
"Unit";"Marine";"Barracks";271;1
"Unit";"Marine";"Barracks";271;1
"Unit";"Marine";"Barracks";271;1
"Unit";"Marine";"Barracks";275;1
"Unit";"Marine";"Barracks";276;1
"Unit";"Marine";"Barracks";278;1
"Unit";"Marine";"Barracks";279;1
"Unit";"Marine";"Barracks";280;1
"Unit";"Marine";"Barracks";281;1
"Unit";"Marine";"Barracks";282;1
"Unit";"Marine";"Barracks";288;1
"Upgrade";"TerranInfantryWeaponsLevel3";"EngineeringBay";250;0
"Upgrade";"TerranInfantryArmorsLevel3";"EngineeringBay";250;0
"Unit";"Marine";"Barracks";288;1
"Unit";"Marine";"Barracks";288;1
"Unit";"Marine";"Barracks";288;1
"Unit";"Marine";"Barracks";288;1
"Unit";"Marine";"Barracks";288;1
"Unit";"Marine";"Barracks";289;1
"Unit";"Marine";"Barracks";294;1
"Unit";"Marine";"Barracks";294;1
"Unit";"Marine";"Barracks";294;1
"Unit";"Marine";"Barracks";294;1
"Unit";"Marine";"Barracks";294;1
"Unit";"Marine";"Barracks";300;1
"Unit";"Marine";"Barracks";300;1
"Unit";"Marine";"Barracks";300;1
"Unit";"Marine";"Barracks";300;1
"Building";"SupplyDepot";NA;300;0
"Building";"SupplyDepot";NA;300;0
"Building";"SupplyDepot";NA;300;0
"Unit";"Marine";"Barracks";309;1
"Unit";"Marine";"Barracks";309;1
"Unit";"Marine";"Barracks";309;1
"Unit";"Marine";"Barracks";309;1
"Unit";"Marine";"Barracks";309;1
"Unit";"Marine";"Barracks";309;1
"Unit";"Marine";"Barracks";309;1
"Unit";"Marine";"Barracks";309;1
"Unit";"Marine";"Barracks";309;1
"Unit";"Marine";"Barracks";309;1
"Unit";"Medivac";"Starport";309;2
"Unit";"Medivac";"Starport";309;2
"Unit";"Marine";"Barracks";309;1
"Unit";"Marine";"Barracks";314;1
"Unit";"Marine";"Barracks";314;1
"Unit";"Marine";"Barracks";319;1
"Unit";"Marine";"Barracks";319;1
"Unit";"Marine";"Barracks";319;1
"Unit";"Marine";"Barracks";319;1
"Unit";"Marine";"Barracks";319;1
"Unit";"Marine";"Barracks";319;1
"Unit";"Marine";"Barracks";319;1
"Building";"SupplyDepot";NA;323;0
"Unit";"Marine";"Barracks";323;1
"Unit";"Marine";"Barracks";324;1
"Unit";"Marine";"Barracks";324;1
