"Type";"UnitName";"OnBuilding";"TotalSupply";"Supply"
"Unit";"SCV";"Command Center";12;1
"Unit";"SCV";"Command Center";12;1
"Unit";"SCV";"Command Center";13;1
"Building";"SupplyDepot";NA;13;0
"Unit";"SCV";"Command Center";15;1
"Unit";"SCV";"Command Center";15;1
"Building";"Refinery";NA;15;0
"Unit";"SCV";"Command Center";16;1
"Building";"Barracks";NA;15;0
"Unit";"SCV";"Command Center";17;1
"Unit";"Reaper";"Barracks";19;1
"Unit";"SCV";"Command Center";19;1
"Unit";"SCV";"Command Center";20;1
"Unit";"SCV";"Command Center";21;1
"Building";"SupplyDepot";NA;21;0
"Building";"Barracks";NA;19;0
"Building";"BarracksReactor";NA;20;0
"Building";"Refinery";NA;22;0
"Unit";"SCV";"Command Center";23;1
"Building";"CommandCenter";NA;19;0
"Building";"BarracksTechLab";NA;23;0
"Unit";"Marine";"Barracks";23;1
"Unit";"Marine";"Barracks";23;1
"Unit";"SCV";"Command Center";23;1
"Unit";"SCV";"Command Center";26;1
"Unit";"Marine";"Barracks";27;1
"Unit";"Marine";"Barracks";27;1
"Unit";"Marine";"Barracks";27;1
"Unit";"SCV";"Command Center";27;1
"Unit";"SCV";"Command Center";31;1
"Unit";"Marine";"Barracks";28;1
"Unit";"Marine";"Barracks";29;1
"Unit";"Marine";"Barracks";30;1
"Building";"Factory";NA;24;0
"Unit";"SCV";"Command Center";32;1
"Unit";"SCV";"Command Center";36;1
"Unit";"Marine";"Barracks";36;1
"Unit";"Marine";"Barracks";36;1
"Unit";"Marine";"Barracks";36;1
"Unit";"SCV";"Command Center";36;1
"Unit";"SCV";"Command Center";38;1
"Unit";"SCV";"Command Center";41;1
"Building";"SupplyDepot";NA;37;0
"Unit";"SCV";"Command Center";42;1
"Building";"FactoryReactor";NA;36;0
"Building";"Starport";NA;36;0
"Unit";"Marine";"Barracks";43;1
"Unit";"SCV";"Command Center";43;1
"Unit";"Marine";"Barracks";43;1
"Unit";"Marine";"Barracks";43;1
"Building";"Bunker";NA;42;0
"Building";"SupplyDepot";NA;44;0
"Unit";"SCV";"Command Center";49;1
"Unit";"SCV";"Command Center";49;1
"Unit";"Marine";"Barracks";45;1
"Unit";"Marine";"Barracks";46;1
"Unit";"Marine";"Barracks";48;1
"Unit";"SCV";"Command Center";49;1
"Unit";"SCV";"Command Center";51;1
"Unit";"Marine";"Barracks";51;1
"Unit";"Marine";"Barracks";52;1
"Unit";"Marine";"Barracks";53;1
"Unit";"SCV";"Command Center";54;1
"Upgrade";"Stimpack";"TechLab";36;0
"Unit";"SCV";"Command Center";55;1
"Unit";"SCV";"Command Center";59;1
"Unit";"Marine";"Barracks";56;1
"Unit";"Marine";"Barracks";57;1
"Unit";"SCV";"Command Center";60;1
"Unit";"Marine";"Barracks";59;1
"Unit";"Medivac";"Starport";54;2
"Unit";"Medivac";"Starport";54;2
"Unit";"SCV";"Command Center";61;1
"Unit";"SCV";"Command Center";64;1
"Unit";"Marine";"Barracks";70;1
"Unit";"Marine";"Barracks";70;1
"Unit";"Marine";"Barracks";70;1
"Unit";"SCV";"Command Center";70;1
"Unit";"SCV";"Command Center";71;1
"Building";"EngineeringBay";NA;68;0
"Building";"EngineeringBay";NA;61;0
"Unit";"SCV";"Command Center";75;1
"Unit";"SCV";"Command Center";76;1
"Unit";"Marine";"Barracks";77;1
"Unit";"Marine";"Barracks";77;1
"Unit";"Marine";"Barracks";77;1
"Unit";"SCV";"Command Center";77;1
"Unit";"SCV";"Command Center";78;1
"Unit";"SCV";"Command Center";83;1
"Unit";"SCV";"Command Center";84;1
"Unit";"Marine";"Barracks";79;1
"Unit";"Marine";"Barracks";82;1
"Unit";"Marine";"Barracks";82;1
"Building";"Barracks";NA;75;0
"Unit";"Medivac";"Starport";83;2
"Unit";"Marine";"Barracks";87;1
"Building";"SupplyDepot";NA;87;0
"Unit";"Marine";"Barracks";89;1
"Unit";"Marine";"Barracks";89;1
"Building";"SupplyDepot";NA;87;0
"Unit";"SCV";"Command Center";89;1
"Unit";"SCV";"Command Center";89;1
"Unit";"Medivac";"Starport";87;2
"Unit";"Marine";"Barracks";91;1
"Building";"Barracks";NA;84;0
"Unit";"Marine";"Barracks";92;1
"Unit";"Marine";"Barracks";96;1
"Building";"BarracksReactor";NA;89;0
"Unit";"Marine";"Barracks";98;1
"Unit";"Marine";"Barracks";99;1
"Unit";"Marine";"Barracks";100;1
"Unit";"SCV";"Command Center";101;1
"Unit";"SCV";"Command Center";102;1
"Unit";"Marine";"Barracks";101;1
"Unit";"Marine";"Barracks";101;1
"Unit";"Marine";"Barracks";101;1
"Building";"Refinery";NA;101;0
"Building";"Refinery";NA;102;0
"Building";"SupplyDepot";NA;102;0
"Unit";"Marine";"Barracks";103;1
"Building";"Armory";NA;98;0
"Unit";"Marine";"Barracks";104;1
"Building";"Barracks";NA;98;0
"Upgrade";"TerranInfantryWeaponsLevel1";"EngineeringBay";89;0
"Upgrade";"TerranInfantryArmorsLevel1";"EngineeringBay";89;0
"Building";"BarracksReactor";NA;101;0
"Building";"SupplyDepot";NA;106;0
"Unit";"Medivac";"Starport";103;2
"Unit";"Medivac";"Starport";103;2
"Building";"CommandCenter";NA;91;0
"Building";"FactoryReactor";NA;102;0
"Unit";"Marine";"Barracks";111;1
"Unit";"Marine";"Barracks";111;1
"Unit";"Marine";"Barracks";111;1
"Unit";"Marine";"Barracks";111;1
"Unit";"Marine";"Barracks";111;1
"Unit";"Marine";"Barracks";111;1
"Unit";"Marine";"Barracks";111;1
"Unit";"Marine";"Barracks";115;1
"Unit";"Marine";"Barracks";116;1
"Unit";"Marine";"Barracks";117;1
"Building";"BarracksReactor";NA;111;0
"Unit";"Marine";"Barracks";125;1
"Unit";"Marine";"Barracks";125;1
"Unit";"Marine";"Barracks";125;1
"Unit";"Marine";"Barracks";125;1
"Unit";"Marine";"Barracks";125;1
"Unit";"Marine";"Barracks";125;1
"Unit";"Marine";"Barracks";125;1
"Unit";"SCV";"Command Center";125;1
"Unit";"SCV";"Command Center";125;1
"Unit";"Marine";"Barracks";125;1
"Unit";"Marine";"Barracks";125;1
"Building";"SensorTower";NA;125;0
"Unit";"Marine";"Barracks";125;1
"Unit";"Marine";"Barracks";126;1
"Unit";"Marine";"Barracks";127;1
"Unit";"Marine";"Barracks";127;1
"Unit";"Marine";"Barracks";129;1
"Unit";"Marine";"Barracks";130;1
"Unit";"Marine";"Barracks";131;1
"Unit";"Marine";"Barracks";134;1
"Unit";"Marine";"Barracks";135;1
"Unit";"Marine";"Barracks";136;1
"Unit";"Marine";"Barracks";137;1
"Unit";"Marine";"Barracks";138;1
"Unit";"Marine";"Barracks";138;1
"Unit";"Marine";"Barracks";140;1
"Unit";"Marine";"Barracks";141;1
"Unit";"Marine";"Barracks";142;1
"Unit";"Marine";"Barracks";143;1
"Unit";"Marine";"Barracks";144;1
"Unit";"SCV";"Command Center";149;1
"Unit";"Marine";"Barracks";145;1
"Unit";"Marine";"Barracks";146;1
"Unit";"Marine";"Barracks";147;1
"Unit";"Marine";"Barracks";147;1
"Unit";"Marine";"Barracks";149;1
"Unit";"Marine";"Barracks";150;1
"Unit";"Marine";"Barracks";151;1
"Unit";"SCV";"Command Center";152;1
"Unit";"SCV";"Command Center";154;1
"Unit";"Marine";"Barracks";152;1
"Unit";"Marine";"Barracks";153;1
"Unit";"SCV";"Command Center";162;1
"Unit";"Marine";"Barracks";155;1
