"type";"unit_name";"on_building";"total_supply";"supply"
"Building";"Refinery";NA;14;0
"Building";"Barracks";NA;15;0
"Unit";"Reaper";"Barracks";19;1
"Building";"Refinery";NA;19;0
"Building";"Factory";NA;19;0
"Building";"BarracksReactor";NA;20;0
"Unit";"Hellion";"Factory";23;2
"Building";"CommandCenter";NA;19;0
"Unit";"Hellion";"Factory";23;2
"Building";"BarracksTechLab";NA;24;0
"Building";"Starport";NA;23;0
"Unit";"Hellion";"Factory";25;2
"Unit";"Hellion";"Factory";27;2
"Unit";"Hellion";"Factory";35;2
"Unit";"Hellion";"Factory";35;2
"Unit";"Cyclone";"Factory";44;3
"Unit";"Cyclone";"Factory";44;3
"Unit";"Banshee";"Starport";44;3
"Unit";"Hellion";"Factory";52;2
"Unit";"Hellion";"Factory";52;2
"Building";"Armory";NA;44;0
"Unit";"Banshee";"Starport";55;3
"Unit";"Hellion";"Factory";65;2
"Unit";"Hellion";"Factory";65;2
"Building";"CommandCenter";NA;55;0
"Building";"BarracksTechLab";NA;70;0
"Building";"Refinery";NA;76;0
"Building";"Refinery";NA;76;0
"Building";"EngineeringBay";NA;76;0
"Building";"Factory";NA;70;0
"Building";"Factory";NA;70;0
"Building";"MissileTurret";NA;81;0
"Building";"MissileTurret";NA;81;0
"Building";"MissileTurret";NA;81;0
"Building";"MissileTurret";NA;81;0
"Unit";"Thor";"Factory";78;6
"Unit";"Hellion";"Factory";84;2
"Unit";"Hellion";"Factory";84;2
"Building";"MissileTurret";NA;85;0
"Unit";"Hellion";"Factory";91;2
"Upgrade";"TerranVehicleWeaponsLevel1";"Armory";78;0
"Unit";"Thor";"Factory";85;6
"Building";"MissileTurret";NA;103;0
"Building";"StarportReactor";NA;101;0
"Unit";"Thor";"Factory";99;6
"Unit";"Hellion";"Factory";121;2
"Building";"Refinery";NA;122;0
"Building";"Refinery";NA;122;0
"Unit";"Thor";"Factory";119;6
"Building";"MissileTurret";NA;124;0
"Building";"MissileTurret";NA;126;0
"Unit";"Hellion";"Factory";126;2
"Unit";"Hellion";"Factory";140;2
"Unit";"Hellion";"Factory";140;2
"Unit";"Hellion";"Factory";140;2
"Unit";"Hellion";"Factory";140;2
"Upgrade";"TerranVehicleWeaponsLevel2";"Armory";120;0
"Unit";"Hellion";"Factory";149;2
"Unit";"Hellion";"Factory";149;2
"Unit";"Hellion";"Factory";149;2
"Unit";"Hellion";"Factory";151;2
"Unit";"Thor";"Factory";149;6
"Unit";"Hellion";"Factory";155;2
"Building";"Factory";NA;151;0
"Unit";"Hellion";"Factory";157;2
"Unit";"Hellion";"Factory";157;2
"Building";"Factory";NA;151;0
"Building";"CommandCenter";NA;149;0
"Building";"BarracksTechLab";NA;163;0
"Building";"FactoryTechLab";NA;165;0
"Building";"Armory";NA;157;0
"Building";"MissileTurret";NA;169;0
"Building";"MissileTurret";NA;169;0
"Building";"MissileTurret";NA;169;0
"Unit";"Hellion";"Factory";169;2
"Unit";"Hellion";"Factory";169;2
"Building";"FactoryReactor";NA;169;0
"Building";"FactoryReactor";NA;169;0
"Building";"Factory";NA;169;0
"Unit";"Hellion";"Factory";173;2
"Unit";"Hellion";"Factory";173;2
"Unit";"Hellion";"Factory";173;2
"Unit";"Hellion";"Factory";173;2
"Unit";"Hellion";"Factory";173;2
"Unit";"Hellion";"Factory";173;2
"Unit";"Thor";"Factory";169;6
"Unit";"Thor";"Factory";169;6
"Unit";"Hellion";"Factory";173;2
"Building";"Refinery";NA;173;0
"Building";"Refinery";NA;173;0
"Unit";"Hellion";"Factory";173;2
"Unit";"Cyclone";"Factory";199;3
"Unit";"Cyclone";"Factory";199;3
"Unit";"Cyclone";"Factory";199;3
"Unit";"Cyclone";"Factory";199;3
"Unit";"Cyclone";"Factory";199;3
"Building";"CommandCenter";NA;173;0
"Unit";"Cyclone";"Factory";201;3
"Unit";"Cyclone";"Factory";201;3
"Unit";"Cyclone";"Factory";201;3
"Unit";"Cyclone";"Factory";201;3
"Unit";"Hellion";"Factory";201;2
"Upgrade";"TerranVehicleWeaponsLevel3";"Armory";169;0
"Unit";"Hellion";"Factory";216;2
"Unit";"Hellion";"Factory";216;2
"Unit";"Hellion";"Factory";216;2
"Unit";"Hellion";"Factory";216;2
"Building";"SensorTower";NA;228;0
"Building";"MissileTurret";NA;228;0
"Building";"MissileTurret";NA;230;0
"Building";"FactoryTechLab";NA;230;0
"Unit";"Cyclone";"Factory";230;3
"Unit";"Cyclone";"Factory";230;3
"Unit";"Cyclone";"Factory";230;3
"Unit";"Cyclone";"Factory";230;3
"Building";"SensorTower";NA;238;0
"Unit";"Cyclone";"Factory";256;3
"Unit";"Cyclone";"Factory";256;3
"Unit";"Cyclone";"Factory";256;3
"Unit";"Cyclone";"Factory";256;3
"Unit";"Cyclone";"Factory";256;3
"Unit";"Cyclone";"Factory";256;3
"Unit";"Cyclone";"Factory";256;3
"Unit";"Cyclone";"Factory";256;3
"Unit";"Cyclone";"Factory";256;3
"Building";"MissileTurret";NA;268;0
"Building";"MissileTurret";NA;271;0
"Building";"SensorTower";NA;274;0
"Unit";"Hellion";"Factory";268;2
"Unit";"Hellion";"Factory";271;2
"Unit";"Cyclone";"Factory";286;3
"Unit";"Cyclone";"Factory";286;3
"Unit";"Cyclone";"Factory";286;3
"Unit";"Cyclone";"Factory";286;3
"Unit";"Cyclone";"Factory";286;3
"Unit";"Cyclone";"Factory";286;3
"Unit";"Cyclone";"Factory";286;3
"Unit";"Hellion";"Factory";290;2
"Upgrade";"TerranShipWeaponsLevel1";"Armory";256;0
"Building";"Refinery";NA;290;0
"Building";"Refinery";NA;290;0
"Unit";"Hellion";"Factory";290;2
"Unit";"Hellion";"Factory";293;2
"Unit";"Cyclone";"Factory";290;3
"Building";"Starport";NA;299;0
"Building";"Starport";NA;299;0
"Building";"Starport";NA;305;0
"Building";"Starport";NA;305;0
"Building";"Starport";NA;305;0
"Unit";"Hellion";"Factory";320;2
"Unit";"Hellion";"Factory";320;2
"Unit";"Hellion";"Factory";320;2
"Unit";"Hellion";"Factory";320;2
"Unit";"Hellion";"Factory";320;2
"Unit";"Hellion";"Factory";320;2
"Unit";"Hellion";"Factory";320;2
"Unit";"Hellion";"Factory";320;2
"Unit";"Hellion";"Factory";320;2
"Unit";"Hellion";"Factory";320;2
"Building";"StarportTechLab";NA;320;0
"Building";"StarportTechLab";NA;320;0
"Building";"StarportTechLab";NA;320;0
"Building";"StarportTechLab";NA;320;0
"Building";"StarportTechLab";NA;320;0
"Unit";"Hellion";"Factory";325;2
"Unit";"Hellion";"Factory";327;2
"Unit";"Hellion";"Factory";329;2
"Unit";"Hellion";"Factory";345;2
"Unit";"Hellion";"Factory";345;2
"Unit";"Hellion";"Factory";345;2
"Building";"FusionCore";NA;320;0
