"type";"unit_name";"on_building";"total_supply";"supply"
"Building";"Refinery";NA;15;0
"Building";"Barracks";NA;15;0
"Unit";"Reaper";"Barracks";18;1
"Unit";"Marine";"Barracks";19;1
"Building";"CommandCenter";NA;19;0
"Building";"BarracksReactor";NA;22;0
"Building";"Factory";NA;21;0
"Building";"Refinery";NA;26;0
"Unit";"Hellion";"Factory";27;2
"Unit";"Hellion";"Factory";27;2
"Building";"BarracksTechLab";NA;27;0
"Building";"Starport";NA;26;0
"Building";"CommandCenter";NA;24;0
"Unit";"Hellion";"Factory";31;2
"Unit";"Hellion";"Factory";31;2
"Building";"BarracksTechLab";NA;35;0
"Building";"Barracks";NA;41;0
"Building";"Barracks";NA;41;0
"Building";"StarportReactor";NA;43;0
"Building";"EngineeringBay";NA;46;0
"Building";"EngineeringBay";NA;46;0
"Building";"Refinery";NA;47;0
"Building";"Refinery";NA;48;0
"Unit";"Marine";"Barracks";51;1
"Unit";"Marine";"Barracks";52;1
"Unit";"Marine";"Barracks";52;1
"Unit";"Marine";"Barracks";53;1
"Building";"BarracksReactor";NA;51;0
"Unit";"Medivac";"Starport";52;2
"Unit";"Marine";"Barracks";55;1
"Unit";"Marine";"Barracks";56;1
"Unit";"Marine";"Barracks";58;1
"Unit";"Marine";"Barracks";59;1
"Unit";"Marine";"Barracks";61;1
"Unit";"Marine";"Barracks";61;1
"Unit";"Marine";"Barracks";62;1
"Unit";"Medivac";"Starport";61;2
"Unit";"Marine";"Barracks";79;1
"Unit";"Marine";"Barracks";79;1
"Unit";"Marine";"Barracks";79;1
"Unit";"Marine";"Barracks";79;1
"Unit";"Marine";"Barracks";79;1
"Unit";"Marine";"Barracks";89;1
"Unit";"Marine";"Barracks";89;1
"Unit";"Marine";"Barracks";89;1
"Unit";"Marine";"Barracks";89;1
"Upgrade";"TerranInfantryWeaponsLevel1";"EngineeringBay";59;0
"Upgrade";"TerranInfantryArmorsLevel1";"EngineeringBay";59;0
"Upgrade";"Stimpack";"TechLab";58;0
"Building";"Barracks";NA;79;0
"Building";"Barracks";NA;79;0
"Unit";"Marine";"Barracks";90;1
"Building";"Refinery";NA;89;0
"Building";"Refinery";NA;89;0
"Unit";"Marine";"Barracks";92;1
"Building";"Armory";NA;86;0
"Unit";"Medivac";"Starport";92;2
"Unit";"Medivac";"Starport";93;2
"Unit";"Marine";"Barracks";107;1
"Unit";"Marine";"Barracks";107;1
"Unit";"Marine";"Barracks";107;1
"Unit";"Marine";"Barracks";107;1
"Unit";"Marine";"Barracks";107;1
"Building";"BarracksReactor";NA;103;0
"Building";"BarracksReactor";NA;103;0
"Unit";"Marine";"Barracks";114;1
"Unit";"Marine";"Barracks";114;1
"Unit";"Marine";"Barracks";114;1
"Unit";"Marine";"Barracks";114;1
"Unit";"Marine";"Barracks";115;1
"Unit";"Medivac";"Starport";110;2
"Unit";"Medivac";"Starport";110;2
"Unit";"Marine";"Barracks";118;1
"Unit";"Marine";"Barracks";118;1
"Unit";"Marine";"Barracks";118;1
"Unit";"Marine";"Barracks";118;1
"Unit";"Marine";"Barracks";118;1
"Unit";"Marine";"Barracks";119;1
"Unit";"Marine";"Barracks";120;1
"Unit";"Marine";"Barracks";127;1
"Unit";"Marauder";"Barracks";127;2
"Unit";"Marine";"Barracks";127;1
"Unit";"Marine";"Barracks";134;1
"Unit";"Marine";"Barracks";134;1
"Unit";"Marine";"Barracks";134;1
"Unit";"Marine";"Barracks";134;1
"Unit";"Marine";"Barracks";134;1
"Unit";"Marine";"Barracks";134;1
"Unit";"Marine";"Barracks";134;1
"Unit";"Marine";"Barracks";135;1
"Unit";"Marine";"Barracks";138;1
"Unit";"Medivac";"Starport";134;2
"Unit";"Medivac";"Starport";134;2
"Unit";"Marine";"Barracks";138;1
"Unit";"Marine";"Barracks";146;1
"Unit";"Marine";"Barracks";146;1
"Unit";"Marine";"Barracks";147;1
"Unit";"Marine";"Barracks";147;1
"Unit";"Marine";"Barracks";147;1
"Unit";"Marine";"Barracks";147;1
"Unit";"Marauder";"Barracks";147;2
"Building";"Barracks";NA;138;0
"Building";"Barracks";NA;138;0
"Building";"Barracks";NA;144;0
"Upgrade";"TerranInfantryWeaponsLevel2";"EngineeringBay";118;0
"Upgrade";"TerranInfantryArmorsLevel2";"EngineeringBay";118;0
"Building";"CommandCenter";NA;134;0
"Unit";"Marine";"Barracks";162;1
"Unit";"Marine";"Barracks";162;1
"Unit";"Marine";"Barracks";162;1
"Unit";"Marine";"Barracks";162;1
"Unit";"Marine";"Barracks";162;1
"Unit";"Marine";"Barracks";162;1
"Unit";"Marine";"Barracks";162;1
"Unit";"Marine";"Barracks";162;1
"Unit";"Marauder";"Barracks";162;2
"Building";"BarracksTechLab";NA;162;0
"Building";"Factory";NA;154;0
"Building";"BarracksTechLab";NA;162;0
"Unit";"Marine";"Barracks";162;1
"Unit";"Marine";"Barracks";162;1
"Unit";"Marine";"Barracks";163;1
"Unit";"Marauder";"Barracks";170;2
"Unit";"Marine";"Barracks";172;1
"Unit";"Marine";"Barracks";172;1
"Unit";"Marine";"Barracks";172;1
"Unit";"Marine";"Barracks";172;1
"Unit";"Marine";"Barracks";172;1
"Unit";"Marine";"Barracks";172;1
"Unit";"Marauder";"Barracks";172;2
"Unit";"Marauder";"Barracks";172;2
"Unit";"Marine";"Barracks";175;1
"Unit";"Marine";"Barracks";175;1
"Unit";"Marine";"Barracks";175;1
"Unit";"Marauder";"Barracks";175;2
"Unit";"Marauder";"Barracks";183;2
"Unit";"Marauder";"Barracks";185;2
"Unit";"Marine";"Barracks";187;1
"Unit";"Marine";"Barracks";187;1
"Unit";"Marine";"Barracks";187;1
"Unit";"Marine";"Barracks";190;1
"Unit";"Marine";"Barracks";190;1
"Unit";"Marine";"Barracks";190;1
"Unit";"Marine";"Barracks";190;1
"Unit";"Marine";"Barracks";192;1
"Unit";"Marine";"Barracks";192;1
"Unit";"Marauder";"Barracks";190;2
"Unit";"Marauder";"Barracks";192;2
"Unit";"Marine";"Barracks";196;1
"Unit";"Marine";"Barracks";197;1
"Unit";"Marauder";"Barracks";194;2
"Unit";"Marine";"Barracks";198;1
"Unit";"Marine";"Barracks";202;1
"Unit";"Marine";"Barracks";203;1
"Unit";"Marine";"Barracks";203;1
"Unit";"Marine";"Barracks";203;1
"Unit";"Marine";"Barracks";205;1
"Unit";"Marine";"Barracks";205;1
"Unit";"Marauder";"Barracks";205;2
"Unit";"Marine";"Barracks";209;1
"Unit";"Marine";"Barracks";214;1
"Unit";"Marauder";"Barracks";207;2
"Unit";"Marine";"Barracks";218;1
"Unit";"Marine";"Barracks";220;1
"Unit";"Marine";"Barracks";220;1
"Unit";"Marine";"Barracks";222;1
"Unit";"Marauder";"Barracks";224;2
"Unit";"Marine";"Barracks";226;1
"Unit";"Marine";"Barracks";226;1
"Unit";"Marauder";"Barracks";226;2
"Unit";"Marauder";"Barracks";226;2
"Unit";"Marine";"Barracks";230;1
"Unit";"Marine";"Barracks";230;1
"Unit";"Marine";"Barracks";230;1
"Unit";"Marine";"Barracks";230;1
"Unit";"Marine";"Barracks";230;1
"Unit";"Marine";"Barracks";234;1
"Unit";"Marauder";"Barracks";230;2
"Unit";"Marauder";"Barracks";234;2
"Unit";"Marauder";"Barracks";236;2
