"type";"unit_name";"on_building";"total_supply";"supply"
"Building";"Refinery";NA;14;0
"Building";"Barracks";NA;15;0
"Unit";"Reaper";"Barracks";19;1
"Building";"Refinery";NA;20;0
"Building";"Factory";NA;19;0
"Building";"BarracksReactor";NA;20;0
"Building";"CommandCenter";NA;19;0
"Unit";"Hellion";"Factory";24;2
"Unit";"Hellion";"Factory";24;2
"Unit";"Hellion";"Factory";30;2
"Unit";"Hellion";"Factory";30;2
"Building";"Armory";NA;24;0
"Building";"BarracksReactor";NA;30;0
"Building";"Factory";NA;30;0
"Unit";"Hellion";"Factory";38;2
"Unit";"Hellion";"Factory";38;2
"Building";"Refinery";NA;47;0
"Unit";"Cyclone";"Factory";48;3
"Unit";"Cyclone";"Factory";49;3
"Unit";"Cyclone";"Factory";51;3
"Unit";"Cyclone";"Factory";51;3
"Unit";"Hellion";"Factory";57;2
"Unit";"Hellion";"Factory";57;2
"Building";"Refinery";NA;65;0
"Upgrade";"TerranVehicleWeaponsLevel1";"Armory";47;0
"Building";"CommandCenter";NA;47;0
"Unit";"Hellion";"Factory";69;2
"Unit";"Hellion";"Factory";69;2
"Unit";"Hellion";"Factory";71;2
"Unit";"Hellion";"Factory";73;2
"Building";"Factory";NA;69;0
"Building";"Factory";NA;69;0
"Building";"Factory";NA;71;0
"Unit";"Hellion";"Factory";81;2
"Unit";"Hellion";"Factory";81;2
"Unit";"Cyclone";"Factory";85;3
"Building";"FactoryTechLab";NA;87;0
"Building";"FactoryTechLab";NA;87;0
"Building";"FactoryTechLab";NA;89;0
"Unit";"Cyclone";"Factory";91;3
"Unit";"Hellion";"Factory";94;2
"Unit";"Hellion";"Factory";94;2
"Unit";"Hellion";"Factory";94;2
"Unit";"Hellion";"Factory";94;2
"Unit";"Cyclone";"Factory";94;3
"Unit";"Hellion";"Factory";97;2
"Unit";"Hellion";"Factory";110;2
"Unit";"Hellion";"Factory";110;2
"Unit";"Hellion";"Factory";110;2
"Unit";"Hellion";"Factory";110;2
"Unit";"Hellion";"Factory";119;2
"Unit";"Hellion";"Factory";119;2
"Unit";"Hellion";"Factory";119;2
"Unit";"Hellion";"Factory";119;2
"Unit";"Hellion";"Factory";121;2
"Upgrade";"TerranVehicleWeaponsLevel2";"Armory";105;0
"Unit";"Hellion";"Factory";129;2
"Unit";"Hellion";"Factory";129;2
"Unit";"Hellion";"Factory";129;2
"Unit";"Hellion";"Factory";139;2
"Unit";"Hellion";"Factory";139;2
"Unit";"Hellion";"Factory";139;2
"Unit";"Hellion";"Factory";139;2
"Building";"Refinery";NA;148;0
"Building";"Refinery";NA;148;0
"Unit";"Hellion";"Factory";148;2
"Unit";"Hellion";"Factory";148;2
"Building";"EngineeringBay";NA;148;0
"Unit";"Hellion";"Factory";148;2
"Unit";"Hellion";"Factory";148;2
"Unit";"Hellion";"Factory";159;2
"Unit";"Hellion";"Factory";159;2
"Unit";"Hellion";"Factory";159;2
"Unit";"Hellion";"Factory";159;2
"Unit";"Hellion";"Factory";159;2
"Building";"CommandCenter";NA;148;0
"Unit";"Hellion";"Factory";165;2
"Unit";"Hellion";"Factory";165;2
"Unit";"Hellion";"Factory";165;2
"Unit";"Hellion";"Factory";171;2
"Unit";"Hellion";"Factory";171;2
"Unit";"Hellion";"Factory";177;2
"Unit";"Hellion";"Factory";177;2
"Unit";"Hellion";"Factory";177;2
"Unit";"Hellion";"Factory";190;2
"Unit";"Hellion";"Factory";190;2
"Unit";"Hellion";"Factory";190;2
"Unit";"Hellion";"Factory";190;2
"Building";"CommandCenter";NA;170;0
"Building";"BarracksTechLab";NA;190;0
"Unit";"Thor";"Factory";181;6
"Unit";"Thor";"Factory";181;6
"Unit";"Thor";"Factory";181;6
"Building";"GhostAcademy";NA;190;0
"Building";"Barracks";NA;190;0
"Building";"Barracks";NA;190;0
"Unit";"Hellion";"Factory";219;2
"Unit";"Hellion";"Factory";219;2
"Unit";"Hellion";"Factory";219;2
"Unit";"Ghost";"Barracks";219;2
"Unit";"Thor";"Factory";219;6
"Unit";"Thor";"Factory";219;6
"Building";"BarracksTechLab";NA;225;0
"Building";"BarracksTechLab";NA;225;0
"Unit";"Hellion";"Factory";225;2
"Unit";"Hellion";"Factory";225;2
"Unit";"Cyclone";"Factory";225;3
"Unit";"Cyclone";"Factory";225;3
"Building";"Refinery";NA;239;0
"Unit";"Ghost";"Barracks";227;2
"Building";"MissileTurret";NA;243;0
"Building";"Refinery";NA;243;0
"Unit";"Ghost";"Barracks";243;2
"Unit";"Ghost";"Barracks";243;2
"Upgrade";"PersonalCloaking";"GhostAcademy";225;0
"Unit";"Hellion";"Factory";251;2
"Unit";"Hellion";"Factory";251;2
"Unit";"Hellion";"Factory";251;2
"Unit";"Hellion";"Factory";251;2
"Upgrade";"TerranVehicleWeaponsLevel3";"Armory";219;0
"Unit";"Hellion";"Factory";263;2
"Unit";"Hellion";"Factory";263;2
"Unit";"Hellion";"Factory";263;2
"Unit";"Hellion";"Factory";263;2
"Unit";"Ghost";"Barracks";255;2
"Unit";"Ghost";"Barracks";263;2
"Unit";"Ghost";"Barracks";263;2
"Unit";"Hellion";"Factory";275;2
"Unit";"Hellion";"Factory";275;2
"Unit";"Hellion";"Factory";275;2
"Unit";"Hellion";"Factory";275;2
"Unit";"Ghost";"Barracks";275;2
"Unit";"Ghost";"Barracks";275;2
"Unit";"Hellion";"Factory";285;2
"Unit";"Hellion";"Factory";285;2
"Unit";"Hellion";"Factory";285;2
"Unit";"Hellion";"Factory";285;2
"Unit";"Ghost";"Barracks";285;2
"Unit";"Hellion";"Factory";285;2
"Unit";"Hellion";"Factory";285;2
"Unit";"Hellion";"Factory";285;2
"Unit";"Hellion";"Factory";289;2
"Unit";"Hellion";"Factory";291;2
"Unit";"Ghost";"Barracks";289;2
"Unit";"Ghost";"Barracks";289;2
"Building";"CommandCenter";NA;275;0
"Building";"CommandCenter";NA;275;0
"Building";"CommandCenter";NA;275;0
"Unit";"Hellion";"Factory";313;2
"Unit";"Hellion";"Factory";313;2
"Unit";"Hellion";"Factory";313;2
"Unit";"Ghost";"Barracks";313;2
"Unit";"Ghost";"Barracks";313;2
"Unit";"Ghost";"Barracks";313;2
"Unit";"Hellion";"Factory";321;2
"Unit";"Hellion";"Factory";321;2
"Unit";"Hellion";"Factory";321;2
"Unit";"Hellion";"Factory";321;2
"Unit";"Marine";"Barracks";321;1
"Unit";"Marine";"Barracks";323;1
"Unit";"Ghost";"Barracks";321;2
"Building";"Refinery";NA;334;0
