"type";"unit_name";"on_building";"total_supply";"supply"
"Building";"Refinery";NA;15;0
"Building";"Barracks";NA;15;0
"Unit";"Reaper";"Barracks";19;1
"Unit";"Marine";"Barracks";20;1
"Building";"CommandCenter";NA;19;0
"Building";"Factory";NA;21;0
"Building";"BarracksReactor";NA;23;0
"Unit";"Hellion";"Factory";26;2
"Unit";"Hellion";"Factory";26;2
"Building";"BarracksTechLab";NA;27;0
"Building";"Starport";NA;26;0
"Unit";"Hellion";"Factory";34;2
"Unit";"Hellion";"Factory";34;2
"Building";"Refinery";NA;35;0
"Building";"BarracksTechLab";NA;36;0
"Unit";"Banshee";"Starport";36;3
"Building";"CommandCenter";NA;32;0
"Unit";"Marine";"Barracks";45;1
"Building";"Refinery";NA;45;0
"Building";"Refinery";NA;45;0
"Building";"FactoryReactor";NA;45;0
"Building";"Barracks";NA;45;0
"Unit";"Marine";"Barracks";53;1
"Building";"Barracks";NA;45;0
"Building";"StarportReactor";NA;51;0
"Building";"EngineeringBay";NA;54;0
"Building";"EngineeringBay";NA;55;0
"Unit";"Marine";"Barracks";58;1
"Unit";"Marine";"Barracks";59;1
"Unit";"Marine";"Barracks";59;1
"Unit";"Marine";"Barracks";60;1
"Unit";"Medivac";"Starport";59;2
"Unit";"Medivac";"Starport";59;2
"Unit";"Marine";"Barracks";61;1
"Unit";"Marine";"Barracks";64;1
"Unit";"Marine";"Barracks";64;1
"Unit";"Marine";"Barracks";64;1
"Building";"Refinery";NA;72;0
"Unit";"Marine";"Barracks";78;1
"Unit";"Marine";"Barracks";78;1
"Unit";"Marine";"Barracks";78;1
"Unit";"Marine";"Barracks";78;1
"Unit";"Marine";"Barracks";78;1
"Upgrade";"Stimpack";"TechLab";55;0
"Building";"Refinery";NA;78;0
"Unit";"Marine";"Barracks";79;1
"Unit";"Marine";"Barracks";80;1
"Unit";"Marine";"Barracks";86;1
"Unit";"Marine";"Barracks";86;1
"Unit";"Marine";"Barracks";86;1
"Unit";"Marine";"Barracks";97;1
"Unit";"Marine";"Barracks";98;1
"Unit";"Marine";"Barracks";98;1
"Unit";"Marine";"Barracks";98;1
"Unit";"Marine";"Barracks";98;1
"Building";"Armory";NA;86;0
"Building";"Barracks";NA;87;0
"Building";"Barracks";NA;88;0
"Unit";"Medivac";"Starport";98;2
"Unit";"Medivac";"Starport";98;2
"Unit";"Marine";"Barracks";101;1
"Unit";"Marine";"Barracks";102;1
"Unit";"Marine";"Barracks";103;1
"Unit";"Marine";"Barracks";108;1
"Unit";"Marine";"Barracks";108;1
"Upgrade";"TerranInfantryWeaponsLevel1";"EngineeringBay";78;0
"Unit";"Marine";"Barracks";109;1
"Upgrade";"TerranInfantryArmorsLevel1";"EngineeringBay";79;0
"Unit";"Marine";"Barracks";109;1
"Unit";"Marine";"Barracks";115;1
"Unit";"Marine";"Barracks";116;1
"Unit";"Marine";"Barracks";123;1
"Unit";"Marine";"Barracks";123;1
"Unit";"Marine";"Barracks";123;1
"Unit";"Marine";"Barracks";125;1
"Unit";"Marine";"Barracks";126;1
"Unit";"Marine";"Barracks";127;1
"Unit";"Marine";"Barracks";128;1
"Unit";"Marine";"Barracks";128;1
"Unit";"Medivac";"Starport";127;2
"Unit";"Medivac";"Starport";127;2
"Unit";"Marine";"Barracks";130;1
"Unit";"Marine";"Barracks";131;1
"Building";"BarracksReactor";NA;127;0
"Building";"BarracksReactor";NA;127;0
"Unit";"Marine";"Barracks";134;1
"Unit";"Marine";"Barracks";135;1
"Unit";"Marine";"Barracks";135;1
"Unit";"Marine";"Barracks";141;1
"Unit";"Marine";"Barracks";142;1
"Unit";"Marine";"Barracks";143;1
"Unit";"Marine";"Barracks";144;1
"Unit";"Marine";"Barracks";144;1
"Unit";"Marine";"Barracks";146;1
"Unit";"Marine";"Barracks";146;1
"Unit";"Marine";"Barracks";146;1
"Unit";"Marine";"Barracks";147;1
"Unit";"Marine";"Barracks";148;1
"Unit";"Marine";"Barracks";148;1
"Building";"GhostAcademy";NA;146;0
"Unit";"Marine";"Barracks";149;1
"Unit";"Marine";"Barracks";150;1
"Unit";"Medivac";"Starport";148;2
"Unit";"Medivac";"Starport";148;2
"Unit";"Marine";"Barracks";158;1
"Building";"CommandCenter";NA;132;0
"Building";"Barracks";NA;146;0
"Building";"Barracks";NA;146;0
"Building";"Barracks";NA;146;0
"Unit";"Marine";"Barracks";164;1
"Unit";"Marine";"Barracks";164;1
"Unit";"Marine";"Barracks";164;1
"Unit";"Marine";"Barracks";164;1
"Unit";"Marine";"Barracks";164;1
"Unit";"Marine";"Barracks";164;1
"Unit";"Marine";"Barracks";164;1
"Unit";"Marine";"Barracks";164;1
"Unit";"Marine";"Barracks";164;1
"Unit";"Marine";"Barracks";165;1
"Unit";"Marine";"Barracks";166;1
"Unit";"Marine";"Barracks";166;1
"Unit";"Marine";"Barracks";168;1
"Unit";"Marine";"Barracks";168;1
"Unit";"Marine";"Barracks";170;1
"Unit";"Marine";"Barracks";170;1
"Unit";"Marine";"Barracks";172;1
"Upgrade";"TerranInfantryWeaponsLevel2";"EngineeringBay";137;0
"Unit";"Marine";"Barracks";174;1
"Building";"BarracksTechLab";NA;174;0
"Building";"BarracksTechLab";NA;174;0
"Building";"BarracksTechLab";NA;174;0
"Upgrade";"TerranInfantryArmorsLevel2";"EngineeringBay";146;0
"Building";"Refinery";NA;182;0
"Building";"Refinery";NA;183;0
"Unit";"Marine";"Barracks";183;1
"Unit";"Marine";"Barracks";183;1
"Unit";"Marine";"Barracks";183;1
"Unit";"Marauder";"Barracks";183;2
"Unit";"Marauder";"Barracks";183;2
"Unit";"Marauder";"Barracks";183;2
"Unit";"Marauder";"Barracks";183;2
"Unit";"Medivac";"Starport";183;2
"Unit";"Medivac";"Starport";183;2
"Upgrade";"PersonalCloaking";"GhostAcademy";183;0
"Unit";"Marauder";"Barracks";197;2
"Unit";"Marauder";"Barracks";197;2
"Unit";"Marauder";"Barracks";197;2
"Unit";"Marauder";"Barracks";201;2
"Unit";"Marauder";"Barracks";201;2
"Unit";"Marauder";"Barracks";203;2
"Building";"CommandCenter";NA;197;0
"Upgrade";"TerranShipWeaponsLevel1";"Armory";183;0
"Unit";"Marine";"Barracks";209;1
