"type";"unit_name";"on_building";"total_supply";"supply"
"Building";"Refinery";NA;15;0
"Building";"Barracks";NA;15;0
"Unit";"Marine";"Barracks";19;1
"Unit";"Reaper";"Barracks";20;1
"Building";"Refinery";NA;22;0
"Building";"CommandCenter";NA;19;0
"Building";"Factory";NA;22;0
"Building";"BarracksReactor";NA;24;0
"Building";"BarracksTechLab";NA;27;0
"Unit";"Hellion";"Factory";27;2
"Unit";"Hellion";"Factory";27;2
"Building";"Starport";NA;26;0
"Unit";"Hellion";"Factory";30;2
"Unit";"Hellion";"Factory";32;2
"Building";"BarracksTechLab";NA;36;0
"Unit";"Hellion";"Factory";42;2
"Unit";"Hellion";"Factory";42;2
"Unit";"Banshee";"Starport";36;3
"Unit";"Marine";"Barracks";53;1
"Unit";"Marine";"Barracks";53;1
"Unit";"Banshee";"Starport";53;3
"Unit";"Marine";"Barracks";59;1
"Unit";"Marine";"Barracks";59;1
"Building";"CommandCenter";NA;44;0
"Building";"Refinery";NA;66;0
"Building";"Refinery";NA;67;0
"Unit";"Marine";"Barracks";67;1
"Building";"EngineeringBay";NA;66;0
"Building";"EngineeringBay";NA;66;0
"Building";"FactoryReactor";NA;66;0
"Building";"StarportReactor";NA;67;0
"Building";"Barracks";NA;67;0
"Unit";"Marine";"Barracks";70;1
"Building";"Barracks";NA;67;0
"Building";"Barracks";NA;69;0
"Building";"Barracks";NA;69;0
"Unit";"Marine";"Barracks";74;1
"Unit";"Medivac";"Starport";72;2
"Unit";"Medivac";"Starport";72;2
"Unit";"Marine";"Barracks";76;1
"Unit";"Marine";"Barracks";76;1
"Unit";"Marine";"Barracks";76;1
"Unit";"Marine";"Barracks";76;1
"Building";"Bunker";NA;75;0
"Unit";"Marine";"Barracks";77;1
"Unit";"Marine";"Barracks";82;1
"Unit";"Marine";"Barracks";86;1
"Unit";"Marine";"Barracks";86;1
"Unit";"Marine";"Barracks";86;1
"Building";"BarracksReactor";NA;77;0
"Building";"BarracksReactor";NA;77;0
"Unit";"Marine";"Barracks";89;1
"Unit";"Medivac";"Starport";86;2
"Unit";"Marine";"Barracks";90;1
"Unit";"Marine";"Barracks";91;1
"Unit";"Medivac";"Starport";89;2
"Unit";"Marine";"Barracks";92;1
"Unit";"Marine";"Barracks";97;1
"Unit";"Marine";"Barracks";97;1
"Unit";"Marine";"Barracks";98;1
"Unit";"Marine";"Barracks";98;1
"Upgrade";"Stimpack";"TechLab";72;0
"Building";"Refinery";NA;101;0
"Unit";"Marine";"Barracks";107;1
"Unit";"Marine";"Barracks";107;1
"Unit";"Marine";"Barracks";107;1
"Unit";"Marine";"Barracks";107;1
"Unit";"Marine";"Barracks";107;1
"Building";"Refinery";NA;106;0
"Unit";"Marine";"Barracks";112;1
"Unit";"Marine";"Barracks";112;1
"Unit";"Marine";"Barracks";112;1
"Unit";"Marine";"Barracks";112;1
"Unit";"Marine";"Barracks";112;1
"Unit";"Marine";"Barracks";113;1
"Unit";"Marine";"Barracks";114;1
"Unit";"Marine";"Barracks";115;1
"Upgrade";"TerranInfantryArmorsLevel1";"EngineeringBay";78;0
"Upgrade";"TerranInfantryWeaponsLevel1";"EngineeringBay";78;0
"Unit";"Marine";"Barracks";117;1
"Building";"Armory";NA;102;0
"Unit";"Marine";"Barracks";117;1
"Unit";"Marine";"Barracks";121;1
"Unit";"Marine";"Barracks";121;1
"Unit";"Marine";"Barracks";121;1
"Unit";"Liberator";"Starport";112;3
"Unit";"Marine";"Barracks";131;1
"Unit";"Marine";"Barracks";131;1
"Unit";"Marine";"Barracks";131;1
"Unit";"Marine";"Barracks";131;1
"Unit";"Marine";"Barracks";131;1
"Unit";"Liberator";"Starport";118;3
"Unit";"Marine";"Barracks";134;1
"Unit";"Marine";"Barracks";134;1
"Unit";"Marine";"Barracks";134;1
"Unit";"Marine";"Barracks";134;1
"Unit";"Marine";"Barracks";137;1
"Unit";"Marine";"Barracks";137;1
"Unit";"Marine";"Barracks";137;1
"Unit";"Marine";"Barracks";137;1
"Unit";"Marine";"Barracks";137;1
"Unit";"Marine";"Barracks";145;1
"Unit";"Marine";"Barracks";146;1
"Unit";"Marine";"Barracks";146;1
"Unit";"Marine";"Barracks";148;1
"Unit";"Marine";"Barracks";149;1
"Unit";"Marine";"Barracks";149;1
