"Type";"UnitName";"OnBuilding";"TotalSupply";"Supply"
"Unit";"SCV";"Command Center";12;1
"Unit";"SCV";"Command Center";13;1
"Unit";"SCV";"Command Center";13;1
"Building";"SupplyDepot";NA;13;0
"Unit";"SCV";"Command Center";15;1
"Unit";"SCV";"Command Center";15;1
"Building";"Refinery";NA;15;0
"Unit";"SCV";"Command Center";16;1
"Building";"Barracks";NA;15;0
"Unit";"SCV";"Command Center";17;1
"Unit";"Reaper";"Barracks";19;1
"Unit";"SCV";"Command Center";19;1
"Building";"SupplyDepot";NA;19;0
"Unit";"SCV";"Command Center";21;1
"Unit";"Marine";"Barracks";21;1
"Unit";"SCV";"Command Center";21;1
"Building";"Factory";NA;21;0
"Unit";"SCV";"Command Center";24;1
"Building";"BarracksReactor";NA;23;0
"Building";"CommandCenter";NA;19;0
"Unit";"SCV";"Command Center";24;1
"Unit";"SCV";"Command Center";25;1
"Building";"BarracksTechLab";NA;25;0
"Building";"Refinery";NA;25;0
"Unit";"Hellion";"Factory";26;2
"Unit";"Hellion";"Factory";26;2
"Unit";"SCV";"Command Center";26;1
"Building";"Starport";NA;25;0
"Unit";"SCV";"Command Center";32;1
"Unit";"SCV";"Command Center";32;1
"Unit";"Hellion";"Factory";31;2
"Unit";"Hellion";"Factory";31;2
"Building";"BarracksTechLab";NA;32;0
"Unit";"SCV";"Command Center";32;1
"Unit";"SCV";"Command Center";33;1
"Unit";"Hellion";"Factory";38;2
"Unit";"Hellion";"Factory";38;2
"Unit";"SCV";"Command Center";40;1
"Unit";"SCV";"Command Center";40;1
"Unit";"SCV";"Command Center";46;1
"Unit";"Banshee";"Starport";38;3
"Building";"SupplyDepot";NA;40;0
"Building";"SupplyDepot";NA;44;0
"Unit";"Marine";"Barracks";46;1
"Unit";"Marine";"Barracks";46;1
"Unit";"SCV";"Command Center";50;1
"Unit";"SCV";"Command Center";50;1
"Unit";"Marine";"Barracks";54;1
"Unit";"Marine";"Barracks";54;1
"Unit";"SCV";"Command Center";56;1
"Unit";"SCV";"Command Center";56;1
"Unit";"Marine";"Barracks";54;1
"Unit";"Marine";"Barracks";55;1
"Unit";"Banshee";"Starport";54;3
"Unit";"SCV";"Command Center";58;1
"Unit";"SCV";"Command Center";60;1
"Unit";"SCV";"Command Center";63;1
"Unit";"SCV";"Command Center";64;1
"Unit";"Marine";"Barracks";65;1
"Unit";"Reaper";"Barracks";58;1
"Unit";"SCV";"Command Center";65;1
"Unit";"SCV";"Command Center";66;1
"Unit";"SCV";"Command Center";69;1
"Unit";"SCV";"Command Center";70;1
"Unit";"Marine";"Barracks";71;1
"Unit";"Marine";"Barracks";71;1
"Unit";"SCV";"Command Center";71;1
"Unit";"SCV";"Command Center";73;1
"Unit";"SCV";"Command Center";75;1
"Building";"CommandCenter";NA;58;0
"Unit";"Marine";"Barracks";73;1
"Unit";"SCV";"Command Center";77;1
"Building";"StarportReactor";NA;71;0
"Unit";"SCV";"Command Center";77;1
"Unit";"Marine";"Barracks";77;1
"Building";"Barracks";NA;71;0
"Unit";"Marine";"Barracks";78;1
"Building";"EngineeringBay";NA;78;0
"Unit";"Marine";"Barracks";82;1
"Unit";"SCV";"Command Center";82;1
"Unit";"SCV";"Command Center";82;1
"Unit";"SCV";"Command Center";85;1
"Unit";"SCV";"Command Center";85;1
"Building";"Barracks";NA;78;0
"Unit";"Marine";"Barracks";86;1
"Unit";"Marine";"Barracks";86;1
"Unit";"SCV";"Command Center";86;1
"Building";"StarportReactor";NA;83;0
"Unit";"SCV";"Command Center";88;1
"Unit";"Marine";"Barracks";88;1
"Building";"Barracks";NA;82;0
"Unit";"SCV";"Command Center";90;1
"Unit";"SCV";"Command Center";91;1
"Unit";"Marine";"Barracks";88;1
"Unit";"SCV";"Command Center";91;1
"Building";"Refinery";NA;91;0
"Unit";"Marine";"Barracks";93;1
"Building";"Refinery";NA;92;0
"Unit";"Marine";"Barracks";93;1
"Unit";"SCV";"Command Center";96;1
"Building";"SupplyDepot";NA;93;0
"Building";"SupplyDepot";NA;93;0
"Unit";"SCV";"Command Center";97;1
"Building";"Barracks";NA;86;0
"Unit";"SCV";"Command Center";99;1
"Unit";"Medivac";"Starport";94;2
"Unit";"SCV";"Command Center";100;1
"Building";"BarracksReactor";NA;96;0
"Unit";"SCV";"Command Center";101;1
"Unit";"Medivac";"Starport";100;2
"Unit";"SCV";"Command Center";105;1
"Unit";"Marine";"Barracks";105;1
"Unit";"Marine";"Barracks";105;1
"Unit";"Marine";"Barracks";105;1
"Unit";"Marine";"Barracks";105;1
"Unit";"Marine";"Barracks";105;1
"Unit";"SCV";"Command Center";106;1
"Unit";"Marine";"Barracks";105;1
"Unit";"Marine";"Barracks";105;1
"Unit";"SCV";"Command Center";109;1
"Upgrade";"Stimpack";"TechLab";88;0
"Building";"BarracksReactor";NA;105;0
"Unit";"Medivac";"Starport";105;2
"Building";"SupplyDepot";NA;114;0
"Building";"SupplyDepot";NA;114;0
"Building";"SupplyDepot";NA;114;0
"Unit";"SCV";"Command Center";118;1
"Upgrade";"TerranInfantryWeaponsLevel1";"EngineeringBay";93;0
"Unit";"Marine";"Barracks";118;1
"Unit";"Marine";"Barracks";118;1
"Unit";"Marine";"Barracks";120;1
"Unit";"Marine";"Barracks";120;1
"Unit";"Marine";"Barracks";120;1
"Unit";"Marine";"Barracks";120;1
"Unit";"Marine";"Barracks";120;1
"Unit";"Marine";"Barracks";120;1
"Unit";"Marine";"Barracks";120;1
"Unit";"Marine";"Barracks";121;1
"Unit";"Marine";"Barracks";121;1
"Unit";"Medivac";"Starport";120;2
"Building";"SupplyDepot";NA;123;0
"Building";"SupplyDepot";NA;123;0
"Unit";"SCV";"Command Center";130;1
"Unit";"SCV";"Command Center";130;1
"Unit";"SCV";"Command Center";130;1
"Unit";"Marine";"Barracks";123;1
"Unit";"Marine";"Barracks";123;1
"Building";"EngineeringBay";NA;123;0
"Unit";"SCV";"Command Center";137;1
"Unit";"SCV";"Command Center";137;1
"Building";"Armory";NA;123;0
"Unit";"SCV";"Command Center";141;1
"Unit";"Marine";"Barracks";141;1
"Unit";"SCV";"Command Center";141;1
"Unit";"Marine";"Barracks";141;1
"Unit";"Marine";"Barracks";141;1
"Unit";"Marine";"Barracks";146;1
"Unit";"Marine";"Barracks";146;1
"Unit";"Marine";"Barracks";146;1
"Unit";"Marine";"Barracks";146;1
"Unit";"Marine";"Barracks";146;1
"Unit";"Marine";"Barracks";146;1
"Unit";"Marine";"Barracks";146;1
"Unit";"Marine";"Barracks";146;1
"Unit";"SCV";"Command Center";146;1
"Unit";"Marine";"Barracks";146;1
"Unit";"Marine";"Barracks";146;1
"Unit";"Marine";"Barracks";147;1
"Unit";"Marine";"Barracks";148;1
"Unit";"Marine";"Barracks";149;1
"Unit";"Marine";"Barracks";149;1
"Unit";"Medivac";"Starport";146;2
"Unit";"Medivac";"Starport";146;2
"Unit";"Marine";"Barracks";156;1
"Unit";"Marine";"Barracks";156;1
"Unit";"Marine";"Barracks";156;1
"Unit";"Marauder";"Barracks";155;2
"Unit";"SCV";"Command Center";156;1
"Unit";"SCV";"Command Center";156;1
"Unit";"Marine";"Barracks";156;1
"Unit";"Marine";"Barracks";157;1
"Unit";"Marine";"Barracks";158;1
"Unit";"Marine";"Barracks";159;1
"Unit";"Marine";"Barracks";159;1
"Building";"MissileTurret";NA;161;0
"Unit";"Marine";"Barracks";165;1
"Unit";"Marine";"Barracks";166;1
"Unit";"Marine";"Barracks";167;1
"Unit";"Marauder";"Barracks";168;2
"Unit";"Medivac";"Starport";161;2
"Unit";"Marine";"Barracks";172;1
"Unit";"Marine";"Barracks";173;1
"Unit";"Marine";"Barracks";174;1
"Unit";"Marine";"Barracks";175;1
"Unit";"Medivac";"Starport";168;2
"Unit";"Marine";"Barracks";177;1
"Unit";"Marine";"Barracks";177;1
"Unit";"Marine";"Barracks";178;1
"Unit";"SCV";"Command Center";184;1
"Unit";"Marauder";"Barracks";180;2
"Unit";"Marine";"Barracks";184;1
"Unit";"Marine";"Barracks";184;1
"Unit";"Marine";"Barracks";185;1
"Unit";"SCV";"Command Center";191;1
"Unit";"SCV";"Command Center";191;1
"Unit";"Marine";"Barracks";186;1
"Unit";"Marine";"Barracks";187;1
"Unit";"Marine";"Barracks";190;1
"Unit";"SCV";"Command Center";193;1
"Unit";"Marine";"Barracks";194;1
"Unit";"Marine";"Barracks";194;1
"Unit";"Marine";"Barracks";196;1
"Unit";"Marine";"Barracks";197;1
"Unit";"Marine";"Barracks";198;1
"Unit";"Marine";"Barracks";201;1
"Unit";"Marine";"Barracks";202;1
"Unit";"Marauder";"Barracks";194;2
"Unit";"Marine";"Barracks";204;1
"Building";"CommandCenter";NA;168;0
"Unit";"Marine";"Barracks";205;1
"Unit";"Marine";"Barracks";206;1
"Unit";"Medivac";"Starport";205;2
"Unit";"Medivac";"Starport";205;2
"Unit";"Marine";"Barracks";215;1
"Unit";"Marine";"Barracks";215;1
"Unit";"Marine";"Barracks";215;1
"Unit";"Marine";"Barracks";215;1
"Unit";"Marine";"Barracks";215;1
"Unit";"Marine";"Barracks";215;1
"Unit";"Marine";"Barracks";215;1
"Unit";"SCV";"Command Center";217;1
"Unit";"SCV";"Command Center";217;1
"Unit";"Marine";"Barracks";215;1
"Unit";"Marine";"Barracks";216;1
"Unit";"Marine";"Barracks";221;1
"Unit";"Marine";"Barracks";222;1
"Unit";"Marine";"Barracks";222;1
"Unit";"Marine";"Barracks";224;1
"Unit";"Marine";"Barracks";228;1
"Unit";"Marine";"Barracks";228;1
"Unit";"Marine";"Barracks";229;1
"Upgrade";"TerranInfantryArmorsLevel1";"EngineeringBay";193;0
"Unit";"Marine";"Barracks";232;1
"Unit";"Marine";"Barracks";232;1
"Unit";"SCV";"Command Center";232;1
"Unit";"Medivac";"Starport";231;2
"Unit";"Marine";"Barracks";232;1
"Unit";"Marine";"Barracks";233;1
