"Type";"UnitName";"OnBuilding";"TotalSupply";"Supply"
"Unit";"SCV";"Command Center";12;1
"Unit";"SCV";"Command Center";12;1
"Unit";"SCV";"Command Center";13;1
"Building";"SupplyDepot";NA;13;0
"Unit";"SCV";"Command Center";15;1
"Unit";"SCV";"Command Center";15;1
"Building";"Refinery";NA;15;0
"Building";"Barracks";NA;15;0
"Unit";"SCV";"Command Center";16;1
"Building";"Barracks";NA;15;0
"Unit";"Marine";"Barracks";17;1
"Unit";"Marine";"Barracks";18;1
"Unit";"Marine";"Barracks";19;1
"Building";"Bunker";NA;18;0
"Building";"SupplyDepot";NA;19;0
"Unit";"SCV";"Command Center";20;1
"Unit";"Marine";"Barracks";20;1
"Building";"Bunker";NA;20;0
"Unit";"Marine";"Barracks";21;1
"Unit";"SCV";"Command Center";23;1
"Unit";"Marine";"Barracks";23;1
"Unit";"SCV";"Command Center";25;1
"Building";"Bunker";NA;23;0
"Unit";"Marine";"Barracks";25;1
"Unit";"SCV";"Command Center";27;1
"Building";"SupplyDepot";NA;27;0
"Building";"Refinery";NA;28;0
"Unit";"SCV";"Command Center";29;1
"Building";"Factory";NA;25;0
"Unit";"SCV";"Command Center";29;1
"Unit";"SCV";"Command Center";31;1
"Building";"FactoryReactor";NA;30;0
"Building";"SupplyDepot";NA;31;0
"Building";"Starport";NA;30;0
"Building";"StarportTechLab";NA;32;0
"Unit";"SCV";"Command Center";32;1
"Unit";"Cyclone";"Factory";32;3
"Unit";"SCV";"Command Center";32;1
"Unit";"Cyclone";"Factory";32;3
"Building";"SupplyDepot";NA;33;0
"Unit";"SCV";"Command Center";40;1
"Unit";"Banshee";"Starport";33;3
"Building";"CommandCenter";NA;32;0
"Unit";"SCV";"Command Center";40;1
"Building";"FactoryTechLab";NA;41;0
"Unit";"Marine";"Barracks";44;1
"Unit";"Marine";"Barracks";44;1
"Unit";"SCV";"Command Center";45;1
"Building";"Barracks";NA;40;0
"Unit";"SCV";"Command Center";47;1
"Unit";"SCV";"Command Center";49;1
"Unit";"SCV";"Command Center";49;1
"Unit";"Marine";"Barracks";49;1
"Unit";"Marine";"Barracks";49;1
"Unit";"Banshee";"Starport";47;3
"Unit";"SCV";"Command Center";49;1
"Unit";"SCV";"Command Center";50;1
"Building";"CommandCenter";NA;40;0
"Unit";"SCV";"Command Center";56;1
"Unit";"Marine";"Barracks";51;1
"Unit";"Marine";"Barracks";52;1
"Unit";"SCV";"Command Center";59;1
"Unit";"Marine";"Barracks";61;1
"Unit";"Marine";"Barracks";61;1
"Unit";"SCV";"Command Center";61;1
"Building";"EngineeringBay";NA;59;0
"Building";"EngineeringBay";NA;61;0
"Unit";"Marine";"Barracks";62;1
"Building";"Refinery";NA;62;0
"Building";"Refinery";NA;62;0
"Unit";"SCV";"Command Center";64;1
"Unit";"SCV";"Command Center";64;1
"Unit";"SCV";"Command Center";64;1
"Unit";"Marine";"Barracks";62;1
"Unit";"Marine";"Barracks";63;1
"Building";"Barracks";NA;59;0
"Unit";"SCV";"Command Center";66;1
"Unit";"SCV";"Command Center";67;1
"Unit";"SCV";"Command Center";68;1
"Unit";"Marine";"Barracks";66;1
"Unit";"Marine";"Barracks";69;1
"Unit";"SCV";"Command Center";71;1
"Unit";"SCV";"Command Center";72;1
"Unit";"SCV";"Command Center";73;1
"Building";"StarportReactor";NA;66;0
"Unit";"Marine";"Barracks";75;1
"Unit";"Marine";"Barracks";75;1
"Unit";"Marine";"Barracks";76;1
"Building";"BarracksReactor";NA;74;0
"Building";"SupplyDepot";NA;79;0
"Unit";"Marine";"Barracks";79;1
"Building";"SupplyDepot";NA;79;0
"Building";"SupplyDepot";NA;81;0
"Building";"SupplyDepot";NA;82;0
"Unit";"Marine";"Barracks";82;1
"Building";"SupplyDepot";NA;82;0
"Unit";"Marine";"Barracks";83;1
"Unit";"Marine";"Barracks";83;1
"Unit";"Marine";"Barracks";83;1
"Unit";"Marine";"Barracks";83;1
"Unit";"Medivac";"Starport";82;2
"Unit";"Medivac";"Starport";82;2
"Unit";"SCV";"Command Center";84;1
"Unit";"SCV";"Command Center";84;1
"Unit";"Marine";"Barracks";83;1
"Unit";"Marine";"Barracks";84;1
"Unit";"Marine";"Barracks";88;1
"Unit";"Marine";"Barracks";88;1
"Unit";"Marine";"Barracks";88;1
"Building";"Armory";NA;82;0
"Unit";"SCV";"Command Center";92;1
"Upgrade";"Stimpack";"TechLab";74;0
"Upgrade";"TerranInfantryWeaponsLevel1";"EngineeringBay";79;0
"Building";"Barracks";NA;83;0
"Building";"Barracks";NA;84;0
"Upgrade";"TerranInfantryArmorsLevel1";"EngineeringBay";81;0
"Unit";"Marine";"Barracks";100;1
"Unit";"Marine";"Barracks";100;1
"Unit";"Marine";"Barracks";100;1
"Unit";"Marine";"Barracks";100;1
"Unit";"Marine";"Barracks";100;1
"Building";"SupplyDepot";NA;100;0
"Building";"SupplyDepot";NA;100;0
"Building";"SupplyDepot";NA;100;0
"Building";"SupplyDepot";NA;100;0
"Unit";"Marine";"Barracks";100;1
"Unit";"Marine";"Barracks";101;1
"Unit";"Marine";"Barracks";105;1
"Unit";"Marine";"Barracks";105;1
"Unit";"SCV";"Command Center";105;1
"Unit";"SCV";"Command Center";105;1
"Unit";"SCV";"Command Center";105;1
"Building";"Factory";NA;100;0
"Unit";"SCV";"Command Center";109;1
"Unit";"SCV";"Command Center";110;1
"Unit";"Marine";"Barracks";108;1
"Unit";"SCV";"Command Center";112;1
"Building";"BarracksReactor";NA;105;0
"Building";"BarracksReactor";NA;105;0
"Unit";"SCV";"Command Center";112;1
"Unit";"Marine";"Barracks";112;1
"Unit";"Marine";"Barracks";112;1
"Unit";"Marine";"Barracks";112;1
"Unit";"Marine";"Barracks";112;1
"Unit";"SCV";"Command Center";115;1
"Building";"Refinery";NA;112;0
"Unit";"Marine";"Barracks";114;1
"Building";"Refinery";NA;115;0
"Unit";"SCV";"Command Center";122;1
"Unit";"SCV";"Command Center";122;1
"Unit";"SCV";"Command Center";122;1
"Building";"SupplyDepot";NA;116;0
