"type";"unit_name";"on_building";"total_supply";"supply"
"Building";"Refinery";NA;15;0
"Building";"Barracks";NA;15;0
"Unit";"Reaper";"Barracks";19;1
"Building";"Factory";NA;20;0
"Building";"CommandCenter";NA;20;0
"Building";"BarracksReactor";NA;22;0
"Building";"Starport";NA;24;0
"Building";"BarracksTechLab";NA;26;0
"Unit";"Hellion";"Factory";26;2
"Unit";"Hellion";"Factory";26;2
"Building";"Refinery";NA;33;0
"Unit";"Hellion";"Factory";33;2
"Unit";"Hellion";"Factory";33;2
"Building";"Refinery";NA;34;0
"Unit";"Hellion";"Factory";36;2
"Unit";"Hellion";"Factory";38;2
"Building";"StarportReactor";NA;41;0
"Unit";"Marine";"Barracks";48;1
"Building";"FactoryTechLab";NA;50;0
"Building";"CommandCenter";NA;34;0
"Building";"EngineeringBay";NA;50;0
"Unit";"Marine";"Barracks";53;1
"Building";"Barracks";NA;50;0
"Unit";"Medivac";"Starport";53;2
"Unit";"Medivac";"Starport";53;2
"Building";"Barracks";NA;50;0
"Building";"Barracks";NA;50;0
"Building";"EngineeringBay";NA;55;0
"Building";"BarracksTechLab";NA;61;0
"Unit";"Marine";"Barracks";61;1
"Unit";"Marine";"Barracks";61;1
"Unit";"Marine";"Barracks";61;1
"Building";"BarracksReactor";NA;61;0
"Unit";"Marine";"Barracks";61;1
"Unit";"Marine";"Barracks";62;1
"Unit";"Medivac";"Starport";61;2
"Unit";"Medivac";"Starport";61;2
"Building";"Refinery";NA;63;0
"Unit";"Marine";"Barracks";65;1
"Unit";"Marine";"Barracks";66;1
"Unit";"Marine";"Barracks";66;1
"Unit";"Marine";"Barracks";68;1
"Upgrade";"Stimpack";"TechLab";55;0
"Unit";"Marine";"Barracks";70;1
"Unit";"Marine";"Barracks";70;1
"Unit";"Marine";"Barracks";76;1
"Unit";"Marine";"Barracks";76;1
"Building";"Barracks";NA;63;0
"Building";"Barracks";NA;63;0
"Unit";"Marine";"Barracks";80;1
"Unit";"Marine";"Barracks";80;1
"Unit";"Marine";"Barracks";80;1
"Unit";"Marine";"Barracks";83;1
"Unit";"Marine";"Barracks";88;1
"Unit";"Marine";"Barracks";88;1
"Unit";"Marine";"Barracks";88;1
"Unit";"Marine";"Barracks";91;1
"Unit";"Marine";"Barracks";91;1
"Unit";"Marine";"Barracks";91;1
"Unit";"Marine";"Barracks";93;1
"Unit";"Marine";"Barracks";94;1
"Unit";"Marine";"Barracks";96;1
"Building";"BarracksReactor";NA;91;0
"Building";"BarracksReactor";NA;91;0
"Unit";"Marine";"Barracks";97;1
"Unit";"Marine";"Barracks";98;1
"Unit";"Marine";"Barracks";100;1
"Unit";"Marine";"Barracks";102;1
"Unit";"Medivac";"Starport";97;2
"Unit";"Medivac";"Starport";97;2
"Building";"Refinery";NA;102;0
"Building";"Refinery";NA;102;0
"Upgrade";"TerranInfantryWeaponsLevel1";"EngineeringBay";88;0
"Upgrade";"TerranInfantryArmorsLevel1";"EngineeringBay";92;0
"Unit";"Marine";"Barracks";116;1
"Unit";"Marine";"Barracks";116;1
"Unit";"Marine";"Barracks";116;1
"Unit";"Marine";"Barracks";116;1
"Unit";"Marine";"Barracks";116;1
"Unit";"Marine";"Barracks";116;1
"Unit";"Marine";"Barracks";116;1
"Unit";"Marine";"Barracks";116;1
"Unit";"Marine";"Barracks";116;1
"Unit";"Marine";"Barracks";116;1
"Unit";"Marine";"Barracks";119;1
"Unit";"Marine";"Barracks";120;1
"Unit";"Marine";"Barracks";120;1
"Unit";"Marine";"Barracks";122;1
"Unit";"Marine";"Barracks";122;1
"Unit";"Marine";"Barracks";122;1
"Unit";"Marine";"Barracks";122;1
"Unit";"Marine";"Barracks";126;1
"Unit";"Marine";"Barracks";126;1
"Unit";"Marine";"Barracks";126;1
"Unit";"Medivac";"Starport";126;2
"Unit";"Medivac";"Starport";126;2
"Unit";"Marine";"Barracks";131;1
"Building";"Armory";NA;116;0
"Unit";"Marine";"Barracks";132;1
"Unit";"Marine";"Barracks";132;1
"Unit";"Marine";"Barracks";134;1
"Unit";"Marine";"Barracks";134;1
"Unit";"Marine";"Barracks";134;1
"Unit";"Marine";"Barracks";134;1
"Unit";"Marine";"Barracks";139;1
"Unit";"Marine";"Barracks";139;1
"Unit";"Marine";"Barracks";139;1
"Building";"CommandCenter";NA;116;0
"Unit";"Marine";"Barracks";149;1
"Unit";"Marine";"Barracks";150;1
"Unit";"Marine";"Barracks";150;1
"Unit";"Marine";"Barracks";152;1
"Unit";"Marine";"Barracks";152;1
"Unit";"Marine";"Barracks";164;1
"Unit";"Marine";"Barracks";164;1
"Unit";"Marine";"Barracks";164;1
"Unit";"Marine";"Barracks";164;1
"Unit";"Marine";"Barracks";164;1
"Unit";"Marine";"Barracks";164;1
"Unit";"Marine";"Barracks";164;1
"Unit";"Marine";"Barracks";164;1
"Unit";"Marine";"Barracks";164;1
"Unit";"Marine";"Barracks";164;1
"Unit";"Marine";"Barracks";164;1
"Unit";"Marine";"Barracks";165;1
"Unit";"Marine";"Barracks";166;1
"Unit";"Marine";"Barracks";167;1
"Unit";"Marine";"Barracks";168;1
"Unit";"Marine";"Barracks";169;1
"Unit";"Marine";"Barracks";170;1
"Unit";"Marine";"Barracks";183;1
"Unit";"Marine";"Barracks";183;1
"Unit";"Marine";"Barracks";183;1
"Unit";"Marine";"Barracks";183;1
"Unit";"Marine";"Barracks";183;1
"Unit";"Marine";"Barracks";183;1
"Unit";"Marine";"Barracks";183;1
"Unit";"Marine";"Barracks";183;1
"Unit";"Marine";"Barracks";183;1
"Unit";"Marine";"Barracks";183;1
"Unit";"Marine";"Barracks";183;1
"Unit";"Marine";"Barracks";184;1
"Unit";"Marine";"Barracks";185;1
"Unit";"Marine";"Barracks";186;1
"Unit";"Marine";"Barracks";187;1
"Unit";"Marine";"Barracks";188;1
"Unit";"Marine";"Barracks";189;1
"Building";"CommandCenter";NA;164;0
"Building";"CommandCenter";NA;164;0
"Unit";"Liberator";"Starport";183;3
"Unit";"Liberator";"Starport";183;3
"Unit";"Marine";"Barracks";204;1
"Unit";"Marine";"Barracks";204;1
"Unit";"Marine";"Barracks";204;1
"Unit";"Marine";"Barracks";204;1
"Unit";"Marine";"Barracks";204;1
"Unit";"Marine";"Barracks";204;1
"Unit";"Marine";"Barracks";204;1
"Unit";"Marine";"Barracks";204;1
"Unit";"Marine";"Barracks";204;1
"Unit";"Marine";"Barracks";205;1
"Unit";"Marine";"Barracks";212;1
"Unit";"Marine";"Barracks";213;1
"Unit";"Marine";"Barracks";218;1
"Unit";"Marine";"Barracks";218;1
"Unit";"Marine";"Barracks";218;1
"Upgrade";"TerranVehicleWeaponsLevel1";"Armory";183;0
"Unit";"Medivac";"Starport";205;2
"Unit";"Medivac";"Starport";208;2
"Unit";"Marine";"Barracks";218;1
"Unit";"Marine";"Barracks";219;1
"Upgrade";"TerranInfantryWeaponsLevel2";"EngineeringBay";183;0
"Upgrade";"TerranInfantryArmorsLevel2";"EngineeringBay";183;0
"Unit";"Marine";"Barracks";241;1
"Unit";"Marine";"Barracks";241;1
"Unit";"Marine";"Barracks";241;1
"Unit";"Marine";"Barracks";241;1
"Unit";"Marine";"Barracks";241;1
"Unit";"Marine";"Barracks";241;1
"Unit";"Marine";"Barracks";241;1
"Unit";"Marine";"Barracks";241;1
"Unit";"Marine";"Barracks";241;1
"Unit";"Marine";"Barracks";241;1
"Unit";"Marine";"Barracks";242;1
"Unit";"Marine";"Barracks";243;1
"Unit";"Marine";"Barracks";244;1
"Building";"Refinery";NA;252;0
"Building";"Refinery";NA;252;0
"Unit";"Liberator";"Starport";242;3
"Unit";"Liberator";"Starport";242;3
