"type";"unit_name";"on_building";"total_supply";"supply"
"Building";"Refinery";NA;15;0
"Building";"Barracks";NA;15;0
"Unit";"Reaper";"Barracks";19;1
"Unit";"Marine";"Barracks";19;1
"Building";"Refinery";NA;23;0
"Building";"CommandCenter";NA;19;0
"Building";"Factory";NA;21;0
"Building";"BarracksReactor";NA;23;0
"Building";"BarracksTechLab";NA;26;0
"Unit";"Hellion";"Factory";26;2
"Unit";"Hellion";"Factory";26;2
"Building";"Starport";NA;26;0
"Unit";"Hellion";"Factory";27;2
"Unit";"Hellion";"Factory";29;2
"Unit";"Hellion";"Factory";40;2
"Building";"BarracksTechLab";NA;42;0
"Unit";"Hellion";"Factory";42;2
"Unit";"Hellion";"Factory";45;2
"Unit";"Medivac";"Starport";44;2
"Building";"CommandCenter";NA;34;0
"Unit";"Hellion";"Factory";50;2
"Building";"Refinery";NA;53;0
"Building";"Refinery";NA;55;0
"Unit";"Hellion";"Factory";55;2
"Building";"Armory";NA;56;0
"Building";"Armory";NA;57;0
"Unit";"Hellion";"Factory";65;2
"Unit";"Liberator";"Starport";63;3
"Unit";"Hellion";"Factory";68;2
"Building";"Factory";NA;65;0
"Unit";"Hellion";"Factory";81;2
"Unit";"Cyclone";"Factory";81;3
"Unit";"Raven";"Starport";80;2
"Building";"BarracksReactor";NA;83;0
"Building";"Factory";NA;83;0
"Building";"Factory";NA;85;0
"Unit";"Hellion";"Factory";90;2
"Unit";"Hellion";"Factory";90;2
"Upgrade";"TerranVehicleWeaponsLevel1";"Armory";80;0
"Building";"EngineeringBay";NA;92;0
"Building";"Refinery";NA;92;0
"Building";"FactoryTechLab";NA;96;0
"Building";"Refinery";NA;92;0
"Unit";"Hellion";"Factory";92;2
"Building";"Factory";NA;96;0
"Unit";"Medivac";"Starport";103;2
"Unit";"Thor";"Factory";103;6
"Unit";"Hellion";"Factory";114;2
"Unit";"Hellion";"Factory";114;2
"Unit";"Medivac";"Starport";113;2
"Unit";"Medivac";"Starport";113;2
"Building";"FactoryReactor";NA;113;0
"Unit";"Hellion";"Factory";134;2
"Unit";"Hellion";"Factory";134;2
"Unit";"Hellion";"Factory";134;2
"Unit";"Hellion";"Factory";134;2
"Building";"CommandCenter";NA;109;0
"Unit";"Hellion";"Factory";136;2
"Unit";"Hellion";"Factory";136;2
"Unit";"Hellion";"Factory";144;2
"Building";"Refinery";NA;148;0
"Building";"CommandCenter";NA;129;0
"Building";"Refinery";NA;148;0
"Unit";"Hellion";"Factory";148;2
"Unit";"Hellion";"Factory";148;2
"Unit";"Hellion";"Factory";148;2
"Unit";"Hellion";"Factory";156;2
"Unit";"Hellion";"Factory";156;2
"Unit";"Hellion";"Factory";156;2
"Upgrade";"TerranVehicleWeaponsLevel2";"Armory";136;0
"Building";"Refinery";NA;162;0
"Building";"Refinery";NA;162;0
"Unit";"Hellion";"Factory";162;2
"Unit";"Hellion";"Factory";164;2
"Unit";"Hellion";"Factory";164;2
"Unit";"Hellion";"Factory";164;2
"Unit";"Hellion";"Factory";164;2
"Unit";"Hellion";"Factory";164;2
"Building";"CommandCenter";NA;162;0
"Building";"CommandCenter";NA;162;0
"Building";"CommandCenter";NA;162;0
"Building";"Starport";NA;164;0
"Building";"Starport";NA;164;0
"Unit";"Hellion";"Factory";172;2
"Building";"Starport";NA;164;0
"Unit";"Hellion";"Factory";172;2
"Unit";"Hellion";"Factory";172;2
"Building";"StarportTechLab";NA;180;0
"Building";"StarportTechLab";NA;180;0
"Building";"StarportTechLab";NA;180;0
"Building";"Starport";NA;174;0
"Building";"Starport";NA;174;0
"Building";"MissileTurret";NA;180;0
"Building";"MissileTurret";NA;180;0
"Building";"MissileTurret";NA;180;0
"Building";"MissileTurret";NA;180;0
"Building";"SensorTower";NA;180;0
"Building";"StarportTechLab";NA;180;0
"Unit";"Thor";"Factory";180;6
"Building";"StarportTechLab";NA;180;0
"Building";"MissileTurret";NA;186;0
"Building";"MissileTurret";NA;186;0
"Building";"MissileTurret";NA;186;0
"Building";"MissileTurret";NA;186;0
"Building";"MissileTurret";NA;186;0
"Unit";"Raven";"Starport";180;2
"Unit";"Raven";"Starport";180;2
"Unit";"Raven";"Starport";180;2
"Unit";"Raven";"Starport";180;2
"Building";"MissileTurret";NA;186;0
"Building";"MissileTurret";NA;194;0
"Unit";"Raven";"Starport";186;2
"Upgrade";"TerranVehicleWeaponsLevel3";"Armory";180;0
"Building";"SensorTower";NA;196;0
"Building";"Refinery";NA;196;0
"Building";"MissileTurret";NA;196;0
"Building";"FusionCore";NA;196;0
"Building";"GhostAcademy";NA;196;0
"Building";"Barracks";NA;196;0
"Building";"Barracks";NA;196;0
"Building";"Barracks";NA;196;0
"Unit";"Raven";"Starport";196;2
"Unit";"Raven";"Starport";196;2
"Unit";"Raven";"Starport";196;2
"Unit";"Raven";"Starport";196;2
"Unit";"Raven";"Starport";196;2
"Unit";"Hellion";"Factory";200;2
"Unit";"Hellion";"Factory";200;2
"Unit";"Hellion";"Factory";200;2
"Unit";"Hellion";"Factory";200;2
"Building";"MissileTurret";NA;218;0
"Building";"MissileTurret";NA;218;0
"Building";"MissileTurret";NA;218;0
"Upgrade";"TerranShipWeaponsLevel1";"Armory";196;0
"Building";"MissileTurret";NA;218;0
"Building";"MissileTurret";NA;218;0
"Building";"MissileTurret";NA;218;0
"Building";"MissileTurret";NA;218;0
"Building";"MissileTurret";NA;218;0
"Unit";"Liberator";"Starport";218;3
"Unit";"Liberator";"Starport";218;3
"Unit";"Liberator";"Starport";218;3
"Unit";"Liberator";"Starport";218;3
"Building";"CommandCenter";NA;218;0
"Building";"Refinery";NA;230;0
"Building";"Refinery";NA;230;0
"Building";"MissileTurret";NA;230;0
"Building";"MissileTurret";NA;230;0
"Building";"MissileTurret";NA;230;0
"Building";"MissileTurret";NA;230;0
"Building";"BarracksTechLab";NA;230;0
"Building";"BarracksTechLab";NA;230;0
"Building";"BarracksTechLab";NA;230;0
"Building";"SensorTower";NA;230;0
"Building";"SensorTower";NA;230;0
"Building";"MissileTurret";NA;230;0
"Building";"MissileTurret";NA;230;0
"Building";"MissileTurret";NA;230;0
"Building";"MissileTurret";NA;230;0
"Building";"Barracks";NA;230;0
"Building";"MissileTurret";NA;230;0
"Building";"Barracks";NA;230;0
"Building";"Barracks";NA;230;0
"Building";"Barracks";NA;230;0
"Building";"BarracksTechLab";NA;230;0
"Unit";"Battlecruiser";"Starport";230;6
"Upgrade";"PersonalCloaking";"GhostAcademy";230;0
"Unit";"Battlecruiser";"Starport";230;6
"Unit";"Battlecruiser";"Starport";230;6
"Building";"BarracksReactor";NA;230;0
"Building";"CommandCenter";NA;230;0
"Unit";"Raven";"Starport";248;2
"Unit";"Raven";"Starport";248;2
"Unit";"Raven";"Starport";248;2
"Building";"BarracksReactor";NA;248;0
"Building";"BarracksReactor";NA;248;0
"Upgrade";"TerranShipWeaponsLevel2";"Armory";230;0
"Upgrade";"Stimpack";"TechLab";248;0
"Building";"CommandCenter";NA;248;0
"Building";"CommandCenter";NA;248;0
"Building";"CommandCenter";NA;248;0
"Unit";"Raven";"Starport";254;2
"Unit";"Raven";"Starport";254;2
"Unit";"Raven";"Starport";254;2
"Unit";"Raven";"Starport";254;2
"Unit";"Raven";"Starport";254;2
"Building";"CommandCenter";NA;248;0
"Building";"Refinery";NA;254;0
"Unit";"Ghost";"Barracks";254;2
"Building";"MissileTurret";NA;264;0
"Building";"MissileTurret";NA;264;0
"Building";"Refinery";NA;264;0
"Building";"MissileTurret";NA;264;0
"Building";"MissileTurret";NA;266;0
"Building";"MissileTurret";NA;266;0
"Building";"MissileTurret";NA;266;0
"Building";"MissileTurret";NA;266;0
"Building";"EngineeringBay";NA;266;0
"Unit";"Ghost";"Barracks";266;2
"Unit";"Ghost";"Barracks";266;2
"Unit";"Ghost";"Barracks";266;2
"Building";"GhostAcademy";NA;272;0
"Building";"GhostAcademy";NA;272;0
"Building";"GhostAcademy";NA;272;0
"Building";"GhostAcademy";NA;272;0
"Building";"GhostAcademy";NA;272;0
"Upgrade";"TerranInfantryWeaponsLevel1";"EngineeringBay";266;0
"Building";"MissileTurret";NA;272;0
"Building";"MissileTurret";NA;272;0
"Unit";"Raven";"Starport";272;2
"Upgrade";"TerranInfantryArmorsLevel1";"EngineeringBay";272;0
"Unit";"Medivac";"Starport";272;2
"Unit";"Ghost";"Barracks";276;2
"Unit";"Ghost";"Barracks";276;2
"Unit";"Ghost";"Barracks";276;2
"Building";"MissileTurret";NA;276;0
"Building";"MissileTurret";NA;276;0
"Building";"MissileTurret";NA;278;0
"Building";"MissileTurret";NA;278;0
"Building";"MissileTurret";NA;282;0
"Unit";"Ghost";"Barracks";282;2
"Unit";"Ghost";"Barracks";282;2
"Upgrade";"TerranShipWeaponsLevel3";"Armory";276;0
