"Type";"UnitName";"OnBuilding";"TotalSupply";"Supply"
"Unit";"SCV";"Command Center";12;1
"Unit";"SCV";"Command Center";12;1
"Unit";"SCV";"Command Center";13;1
"Building";"SupplyDepot";NA;13;0
"Unit";"SCV";"Command Center";15;1
"Unit";"SCV";"Command Center";15;1
"Building";"Refinery";NA;15;0
"Unit";"SCV";"Command Center";16;1
"Building";"Barracks";NA;15;0
"Unit";"SCV";"Command Center";17;1
"Unit";"Reaper";"Barracks";19;1
"Unit";"SCV";"Command Center";19;1
"Building";"SupplyDepot";NA;19;0
"Unit";"Marine";"Barracks";19;1
"Unit";"SCV";"Command Center";20;1
"Unit";"SCV";"Command Center";22;1
"Unit";"SCV";"Command Center";23;1
"Building";"Factory";NA;21;0
"Building";"CommandCenter";NA;19;0
"Building";"BarracksReactor";NA;23;0
"Unit";"SCV";"Command Center";25;1
"Unit";"SCV";"Command Center";26;1
"Unit";"Hellion";"Factory";26;2
"Unit";"SCV";"Command Center";27;1
"Unit";"Hellion";"Factory";26;2
"Unit";"SCV";"Command Center";27;1
"Building";"BarracksTechLab";NA;27;0
"Unit";"SCV";"Command Center";29;1
"Building";"Refinery";NA;32;0
"Building";"Starport";NA;27;0
"Unit";"SCV";"Command Center";34;1
"Unit";"SCV";"Command Center";34;1
"Unit";"Hellion";"Factory";32;2
"Unit";"Hellion";"Factory";32;2
"Unit";"SCV";"Command Center";34;1
"Building";"BarracksTechLab";NA;34;0
"Unit";"SCV";"Command Center";35;1
"Building";"CommandCenter";NA;25;0
"Unit";"SCV";"Command Center";40;1
"Unit";"SCV";"Command Center";42;1
"Unit";"SCV";"Command Center";42;1
"Unit";"SCV";"Command Center";44;1
"Building";"FactoryReactor";NA;42;0
"Unit";"SCV";"Command Center";46;1
"Unit";"SCV";"Command Center";46;1
"Building";"Barracks";NA;40;0
"Building";"Refinery";NA;46;0
"Building";"EngineeringBay";NA;46;0
"Building";"Barracks";NA;43;0
"Building";"Refinery";NA;46;0
"Building";"EngineeringBay";NA;46;0
"Unit";"SCV";"Command Center";48;1
"Unit";"SCV";"Command Center";48;1
"Unit";"SCV";"Command Center";48;1
"Unit";"SCV";"Command Center";49;1
"Building";"StarportReactor";NA;48;0
"Unit";"SCV";"Command Center";50;1
"Unit";"SCV";"Command Center";50;1
"Unit";"Marine";"Barracks";50;1
"Unit";"Marine";"Barracks";50;1
"Unit";"Marine";"Barracks";50;1
"Unit";"SCV";"Command Center";52;1
"Unit";"SCV";"Command Center";53;1
"Unit";"SCV";"Command Center";53;1
"Unit";"SCV";"Command Center";58;1
"Unit";"SCV";"Command Center";58;1
"Unit";"Marine";"Barracks";54;1
"Unit";"Marine";"Barracks";55;1
"Unit";"SCV";"Command Center";59;1
"Unit";"SCV";"Command Center";60;1
"Unit";"Marine";"Barracks";60;1
"Unit";"Marine";"Barracks";60;1
"Unit";"Marine";"Barracks";60;1
"Unit";"Marine";"Barracks";62;1
"Upgrade";"Stimpack";"TechLab";48;0
"Building";"SupplyDepot";NA;67;0
"Building";"SupplyDepot";NA;67;0
"Unit";"SCV";"Command Center";70;1
"Unit";"SCV";"Command Center";70;1
"Unit";"Marine";"Barracks";70;1
"Unit";"Marine";"Barracks";70;1
"Unit";"Marine";"Barracks";70;1
"Unit";"Marine";"Barracks";70;1
"Unit";"Marine";"Barracks";70;1
"Unit";"SCV";"Command Center";77;1
"Unit";"SCV";"Command Center";77;1
"Unit";"SCV";"Command Center";77;1
"Unit";"Medivac";"Starport";70;2
"Unit";"Medivac";"Starport";70;2
"Unit";"Marine";"Barracks";77;1
"Unit";"Marine";"Barracks";77;1
"Unit";"Marine";"Barracks";77;1
"Unit";"Marine";"Barracks";77;1
"Unit";"Marine";"Barracks";77;1
"Unit";"SCV";"Command Center";77;1
"Building";"SupplyDepot";NA;77;0
"Building";"SupplyDepot";NA;77;0
"Building";"SupplyDepot";NA;77;0
"Unit";"Marine";"Barracks";84;1
"Unit";"Marine";"Barracks";88;1
"Unit";"Marine";"Barracks";89;1
"Unit";"Marine";"Barracks";90;1
"Unit";"Marine";"Barracks";90;1
"Unit";"Medivac";"Starport";80;2
"Unit";"Marine";"Barracks";90;1
"Unit";"Marine";"Barracks";91;1
"Unit";"Marine";"Barracks";92;1
"Building";"Barracks";NA;77;0
"Building";"Barracks";NA;77;0
"Unit";"Marine";"Barracks";93;1
"Unit";"Marine";"Barracks";94;1
"Unit";"SCV";"Command Center";97;1
"Upgrade";"TerranInfantryArmorsLevel1";"EngineeringBay";70;0
"Unit";"SCV";"Command Center";100;1
"Unit";"SCV";"Command Center";100;1
"Unit";"Marine";"Barracks";97;1
"Unit";"Marine";"Barracks";98;1
"Unit";"Marine";"Barracks";99;1
"Unit";"Medivac";"Starport";97;2
"Unit";"Medivac";"Starport";97;2
"Unit";"SCV";"Command Center";106;1
"Unit";"SCV";"Command Center";107;1
"Upgrade";"TerranInfantryWeaponsLevel1";"EngineeringBay";77;0
"Building";"SupplyDepot";NA;105;0
"Building";"SupplyDepot";NA;108;0
"Unit";"Marine";"Barracks";114;1
"Unit";"Marine";"Barracks";114;1
"Unit";"Marine";"Barracks";114;1
"Unit";"Marine";"Barracks";114;1
"Building";"Armory";NA;103;0
"Unit";"Marine";"Barracks";114;1
"Unit";"Marine";"Barracks";118;1
"Unit";"Marine";"Barracks";118;1
"Unit";"Medivac";"Starport";114;2
"Unit";"Medivac";"Starport";114;2
"Unit";"Marine";"Barracks";118;1
"Building";"BarracksReactor";NA;114;0
"Unit";"Marine";"Barracks";118;1
"Building";"BarracksReactor";NA;114;0
"Unit";"Marine";"Barracks";118;1
"Building";"SupplyDepot";NA;119;0
"Building";"SupplyDepot";NA;119;0
"Unit";"SCV";"Command Center";127;1
"Unit";"SCV";"Command Center";127;1
"Unit";"SCV";"Command Center";127;1
"Building";"SupplyDepot";NA;119;0
"Building";"Refinery";NA;127;0
"Unit";"Marine";"Barracks";128;1
"Unit";"Marine";"Barracks";128;1
"Unit";"Marine";"Barracks";128;1
"Unit";"Marine";"Barracks";128;1
"Building";"Refinery";NA;127;0
"Unit";"SCV";"Command Center";128;1
"Unit";"SCV";"Command Center";129;1
"Unit";"SCV";"Command Center";130;1
"Unit";"Marine";"Barracks";128;1
"Unit";"Marine";"Barracks";128;1
"Unit";"Marine";"Barracks";128;1
"Unit";"Marine";"Barracks";128;1
"Unit";"Marauder";"Barracks";128;2
"Unit";"SCV";"Command Center";135;1
"Unit";"SCV";"Command Center";136;1
"Unit";"SCV";"Command Center";137;1
"Unit";"Marine";"Barracks";131;1
"Unit";"Marine";"Barracks";142;1
"Unit";"Marine";"Barracks";142;1
"Unit";"Marine";"Barracks";142;1
"Unit";"Marine";"Barracks";142;1
"Unit";"Marine";"Barracks";142;1
"Unit";"Marine";"Barracks";142;1
"Unit";"Marine";"Barracks";142;1
"Unit";"Medivac";"Starport";131;2
"Unit";"Medivac";"Starport";131;2
"Unit";"Marauder";"Barracks";144;2
"Building";"Bunker";NA;138;0
"Unit";"Marine";"Barracks";148;1
"Building";"SupplyDepot";NA;153;0
"Building";"SupplyDepot";NA;162;0
"Building";"SupplyDepot";NA;162;0
"Unit";"SCV";"Command Center";162;1
"Unit";"SCV";"Command Center";162;1
"Unit";"Marine";"Barracks";162;1
"Unit";"Marine";"Barracks";162;1
"Upgrade";"TerranVehicleAndShipArmorsLevel1";"Armory";131;0
"Building";"SupplyDepot";NA;162;0
"Building";"SupplyDepot";NA;162;0
"Unit";"Marine";"Barracks";162;1
"Unit";"Marine";"Barracks";162;1
"Building";"SupplyDepot";NA;162;0
"Unit";"Marine";"Barracks";162;1
"Unit";"Marine";"Barracks";162;1
"Unit";"Marine";"Barracks";162;1
"Unit";"Marine";"Barracks";162;1
"Unit";"Marauder";"Barracks";162;2
"Unit";"Marine";"Barracks";164;1
"Unit";"Marine";"Barracks";165;1
"Unit";"Medivac";"Starport";162;2
"Unit";"Medivac";"Starport";162;2
"Upgrade";"TerranInfantryArmorsLevel2";"EngineeringBay";131;0
"Upgrade";"TerranInfantryWeaponsLevel2";"EngineeringBay";131;0
"Unit";"Marine";"Barracks";166;1
"Unit";"Marine";"Barracks";167;1
"Unit";"Marine";"Barracks";168;1
"Unit";"Marine";"Barracks";168;1
"Unit";"Marine";"Barracks";170;1
"Unit";"Marine";"Barracks";170;1
"Unit";"Marine";"Barracks";175;1
"Unit";"Marine";"Barracks";175;1
"Unit";"Marine";"Barracks";182;1
"Unit";"Marine";"Barracks";182;1
"Unit";"Marine";"Barracks";182;1
"Unit";"Marine";"Barracks";186;1
"Unit";"Marine";"Barracks";186;1
"Unit";"Marine";"Barracks";186;1
"Unit";"Marine";"Barracks";186;1
"Unit";"Marine";"Barracks";186;1
"Unit";"Medivac";"Starport";182;2
"Unit";"Medivac";"Starport";182;2
"Unit";"Marauder";"Barracks";187;2
"Unit";"Marine";"Barracks";188;1
"Unit";"Marine";"Barracks";189;1
"Unit";"Marine";"Barracks";202;1
"Unit";"Marine";"Barracks";202;1
"Unit";"Marauder";"Barracks";202;2
"Unit";"Marine";"Barracks";204;1
"Unit";"Marine";"Barracks";204;1
"Unit";"Marine";"Barracks";204;1
"Unit";"Marine";"Barracks";204;1
"Unit";"Marine";"Barracks";204;1
"Unit";"Marine";"Barracks";204;1
"Unit";"Marine";"Barracks";204;1
"Unit";"Marine";"Barracks";208;1
"Unit";"Marine";"Barracks";214;1
"Building";"SupplyDepot";NA;214;0
"Building";"SupplyDepot";NA;214;0
"Building";"SupplyDepot";NA;214;0
"Unit";"Marine";"Barracks";216;1
"Unit";"Marine";"Barracks";216;1
"Unit";"Marine";"Barracks";216;1
"Unit";"Marine";"Barracks";216;1
"Unit";"Marine";"Barracks";216;1
"Unit";"Marine";"Barracks";216;1
"Unit";"Marine";"Barracks";216;1
"Unit";"Medivac";"Starport";216;2
"Unit";"Medivac";"Starport";216;2
"Building";"Barracks";NA;214;0
"Building";"Barracks";NA;214;0
"Building";"Barracks";NA;214;0
"Upgrade";"TerranVehicleAndShipArmorsLevel2";"Armory";191;0
