"Type";"UnitName";"OnBuilding";"TotalSupply";"Supply"
"Unit";"SCV";"Command Center";12;1
"Unit";"SCV";"Command Center";12;1
"Unit";"SCV";"Command Center";13;1
"Building";"SupplyDepot";NA;13;0
"Unit";"SCV";"Command Center";15;1
"Unit";"SCV";"Command Center";15;1
"Building";"Refinery";NA;15;0
"Unit";"SCV";"Command Center";16;1
"Building";"Barracks";NA;15;0
"Unit";"SCV";"Command Center";18;1
"Unit";"Reaper";"Barracks";19;1
"Unit";"SCV";"Command Center";19;1
"Unit";"Marine";"Barracks";20;1
"Unit";"SCV";"Command Center";21;1
"Building";"SupplyDepot";NA;20;0
"Unit";"SCV";"Command Center";23;1
"Building";"Refinery";NA;21;0
"Building";"CommandCenter";NA;19;0
"Building";"Factory";NA;21;0
"Unit";"SCV";"Command Center";24;1
"Unit";"SCV";"Command Center";25;1
"Unit";"Hellion";"Factory";24;2
"Building";"BarracksReactor";NA;24;0
"Unit";"SCV";"Command Center";26;1
"Unit";"SCV";"Command Center";26;1
"Unit";"SCV";"Command Center";30;1
"Unit";"SCV";"Command Center";30;1
"Building";"BarracksTechLab";NA;28;0
"Unit";"Hellion";"Factory";29;2
"Unit";"Hellion";"Factory";29;2
"Unit";"SCV";"Command Center";30;1
"Unit";"SCV";"Command Center";32;1
"Building";"Starport";NA;29;0
"Unit";"SCV";"Command Center";36;1
"Unit";"SCV";"Command Center";37;1
"Unit";"Hellion";"Factory";36;2
"Unit";"Hellion";"Factory";36;2
"Building";"BarracksTechLab";NA;38;0
"Building";"SupplyDepot";NA;38;0
"Unit";"SCV";"Command Center";38;1
"Unit";"SCV";"Command Center";40;1
"Unit";"Marine";"Barracks";44;1
"Unit";"SCV";"Command Center";46;1
"Building";"SupplyDepot";NA;46;0
"Unit";"SCV";"Command Center";46;1
"Building";"SupplyDepot";NA;46;0
"Unit";"SCV";"Command Center";48;1
"Unit";"Marine";"Barracks";48;1
"Unit";"SCV";"Command Center";50;1
"Unit";"SCV";"Command Center";50;1
"Building";"Barracks";NA;46;0
"Building";"Barracks";NA;46;0
"Building";"FactoryReactor";NA;46;0
"Unit";"Marine";"Barracks";51;1
"Unit";"SCV";"Command Center";53;1
"Unit";"Banshee";"Starport";48;3
"Unit";"SCV";"Command Center";53;1
"Unit";"Marine";"Barracks";53;1
"Unit";"Marine";"Barracks";53;1
"Unit";"Marine";"Barracks";53;1
"Unit";"SCV";"Command Center";55;1
"Building";"Bunker";NA;53;0
"Unit";"SCV";"Command Center";61;1
"Unit";"Cyclone";"Factory";55;3
"Unit";"Cyclone";"Factory";55;3
"Unit";"Marine";"Barracks";61;1
"Unit";"Marine";"Barracks";61;1
"Unit";"SCV";"Command Center";62;1
"Building";"BarracksReactor";NA;54;0
"Unit";"SCV";"Command Center";63;1
"Building";"SupplyDepot";NA;61;0
"Building";"SupplyDepot";NA;62;0
"Building";"SupplyDepot";NA;63;0
"Unit";"SCV";"Command Center";72;1
"Unit";"Marine";"Barracks";63;1
"Unit";"Marine";"Barracks";70;1
"Unit";"Marine";"Barracks";71;1
"Unit";"Banshee";"Starport";55;3
"Unit";"SCV";"Command Center";74;1
"Unit";"SCV";"Command Center";74;1
"Upgrade";"Stimpack";"TechLab";50;0
"Unit";"SCV";"Command Center";81;1
"Unit";"SCV";"Command Center";82;1
"Unit";"SCV";"Command Center";83;1
"Unit";"Marine";"Barracks";83;1
"Unit";"SCV";"Command Center";84;1
"Unit";"Marine";"Barracks";84;1
"Unit";"Marine";"Barracks";84;1
"Unit";"Marine";"Barracks";84;1
"Unit";"Marine";"Barracks";84;1
"Unit";"SCV";"Command Center";85;1
"Unit";"SCV";"Command Center";87;1
"Building";"CommandCenter";NA;53;0
"Building";"EngineeringBay";NA;85;0
"Unit";"Marine";"Barracks";88;1
"Building";"EngineeringBay";NA;85;0
"Building";"Refinery";NA;87;0
"Unit";"SCV";"Command Center";92;1
"Unit";"Marine";"Barracks";88;1
"Unit";"Marine";"Barracks";89;1
"Building";"Refinery";NA;88;0
"Unit";"SCV";"Command Center";93;1
"Building";"SupplyDepot";NA;92;0
"Building";"SupplyDepot";NA;93;0
"Unit";"SCV";"Command Center";98;1
"Unit";"Marine";"Barracks";94;1
"Unit";"Marine";"Barracks";94;1
"Unit";"Marine";"Barracks";94;1
"Unit";"SCV";"Command Center";99;1
"Building";"Barracks";NA;86;0
"Unit";"Marine";"Barracks";99;1
"Building";"Barracks";NA;86;0
"Unit";"Marine";"Barracks";99;1
"Unit";"Marine";"Barracks";100;1
"Unit";"Marine";"Barracks";101;1
"Unit";"Marine";"Barracks";103;1
"Unit";"SCV";"Command Center";106;1
"Unit";"Medivac";"Starport";99;2
"Unit";"Medivac";"Starport";99;2
"Unit";"Marine";"Barracks";104;1
"Unit";"Marine";"Barracks";105;1
"Building";"SupplyDepot";NA;106;0
"Building";"BarracksTechLab";NA;106;0
"Unit";"Marine";"Barracks";106;1
"Unit";"Marine";"Barracks";107;1
"Unit";"SCV";"Command Center";114;1
"Unit";"Marine";"Barracks";108;1
"Unit";"Marine";"Barracks";114;1
"Building";"BarracksReactor";NA;106;0
"Unit";"Marine";"Barracks";116;1
"Unit";"Marine";"Barracks";116;1
"Unit";"Marine";"Barracks";116;1
"Unit";"SCV";"Command Center";121;1
"Unit";"SCV";"Command Center";121;1
"Unit";"SCV";"Command Center";121;1
"Unit";"Marauder";"Barracks";117;2
"Unit";"Marine";"Barracks";120;1
"Unit";"Marine";"Barracks";121;1
"Unit";"Marine";"Barracks";121;1
"Unit";"Marine";"Barracks";121;1
"Unit";"SCV";"Command Center";126;1
"Building";"SupplyDepot";NA;121;0
"Unit";"Marine";"Barracks";121;1
"Building";"SupplyDepot";NA;121;0
"Unit";"SCV";"Command Center";131;1
"Unit";"Marauder";"Barracks";122;2
"Unit";"Marauder";"Barracks";127;2
"Unit";"SCV";"Command Center";135;1
"Unit";"Marine";"Barracks";134;1
"Unit";"Marine";"Barracks";134;1
"Unit";"Marine";"Barracks";134;1
"Unit";"Marine";"Barracks";134;1
"Unit";"Marine";"Barracks";135;1
"Unit";"Marine";"Barracks";135;1
"Building";"SupplyDepot";NA;134;0
"Building";"Refinery";NA;135;0
"Building";"Refinery";NA;135;0
"Building";"SupplyDepot";NA;135;0
"Building";"SupplyDepot";NA;135;0
"Unit";"Marine";"Barracks";140;1
"Unit";"Marine";"Barracks";140;1
"Unit";"SCV";"Command Center";141;1
"Unit";"SCV";"Command Center";147;1
