"type";"unit_name";"on_building";"total_supply";"supply"
"Building";"Refinery";NA;15;0
"Building";"Barracks";NA;15;0
"Unit";"Reaper";"Barracks";19;1
"Unit";"Marine";"Barracks";19;1
"Building";"CommandCenter";NA;19;0
"Building";"Factory";NA;21;0
"Building";"BarracksReactor";NA;22;0
"Building";"BarracksTechLab";NA;26;0
"Unit";"Hellion";"Factory";26;2
"Building";"Starport";NA;26;0
"Unit";"Hellion";"Factory";29;2
"Unit";"Hellion";"Factory";29;2
"Building";"CommandCenter";NA;24;0
"Building";"BarracksTechLab";NA;32;0
"Building";"Refinery";NA;32;0
"Unit";"Hellion";"Factory";38;2
"Unit";"Hellion";"Factory";38;2
"Unit";"Hellion";"Factory";40;2
"Unit";"Hellion";"Factory";42;2
"Building";"Refinery";NA;46;0
"Building";"Refinery";NA;46;0
"Unit";"Liberator";"Starport";39;3
"Unit";"Hellion";"Factory";52;2
"Unit";"Hellion";"Factory";52;2
"Unit";"Cyclone";"Factory";64;3
"Building";"Armory";NA;57;0
"Building";"Armory";NA;57;0
"Unit";"Cyclone";"Factory";64;3
"Building";"Refinery";NA;72;0
"Unit";"Hellion";"Factory";76;2
"Unit";"Hellion";"Factory";76;2
"Building";"Factory";NA;72;0
"Building";"Factory";NA;72;0
"Building";"StarportReactor";NA;78;0
"Building";"Refinery";NA;82;0
"Unit";"Hellion";"Factory";82;2
"Unit";"Hellion";"Factory";93;2
"Unit";"Hellion";"Factory";93;2
"Building";"EngineeringBay";NA;95;0
"Unit";"Hellion";"Factory";102;2
"Unit";"Hellion";"Factory";102;2
"Building";"MissileTurret";NA;105;0
"Building";"MissileTurret";NA;106;0
"Building";"MissileTurret";NA;106;0
"Unit";"Hellion";"Factory";108;2
"Unit";"Hellion";"Factory";110;2
"Upgrade";"TerranVehicleWeaponsLevel1";"Armory";93;0
"Unit";"Hellion";"Factory";123;2
"Unit";"Hellion";"Factory";123;2
"Building";"Factory";NA;115;0
"Building";"Factory";NA;115;0
"Unit";"Hellion";"Factory";132;2
"Unit";"Hellion";"Factory";132;2
"Building";"FactoryTechLab";NA;133;0
"Building";"MissileTurret";NA;133;0
"Building";"CommandCenter";NA;115;0
"Building";"FactoryReactor";NA;133;0
"Unit";"Hellion";"Factory";140;2
"Unit";"Hellion";"Factory";140;2
"Building";"Refinery";NA;143;0
"Unit";"Hellion";"Factory";143;2
"Building";"Refinery";NA;143;0
"Unit";"Hellion";"Factory";143;2
"Unit";"Hellion";"Factory";153;2
"Unit";"Hellion";"Factory";153;2
"Building";"MissileTurret";NA;159;0
"Building";"MissileTurret";NA;159;0
"Building";"MissileTurret";NA;159;0
"Building";"SensorTower";NA;159;0
"Upgrade";"TerranVehicleWeaponsLevel2";"Armory";140;0
"Unit";"Hellion";"Factory";159;2
"Unit";"Hellion";"Factory";159;2
"Building";"Factory";NA;159;0
"Building";"Factory";NA;159;0
"Unit";"Hellion";"Factory";163;2
"Building";"Factory";NA;159;0
"Building";"CommandCenter";NA;159;0
"Unit";"Hellion";"Factory";163;2
"Building";"FactoryTechLab";NA;165;0
"Building";"FactoryTechLab";NA;165;0
"Unit";"Hellion";"Factory";165;2
"Building";"FactoryReactor";NA;165;0
"Unit";"Hellion";"Factory";167;2
"Unit";"Hellion";"Factory";167;2
"Unit";"Hellion";"Factory";167;2
"Unit";"Hellion";"Factory";167;2
"Unit";"Hellion";"Factory";169;2
"Unit";"Hellion";"Factory";169;2
"Unit";"Hellion";"Factory";171;2
"Unit";"Hellion";"Factory";173;2
"Unit";"Hellion";"Factory";173;2
"Unit";"Hellion";"Factory";175;2
"Unit";"Hellion";"Factory";175;2
"Unit";"Thor";"Factory";169;6
"Building";"Refinery";NA;191;0
"Building";"MissileTurret";NA;193;0
"Building";"MissileTurret";NA;193;0
"Building";"MissileTurret";NA;193;0
"Building";"MissileTurret";NA;193;0
"Unit";"Hellion";"Factory";193;2
"Building";"MissileTurret";NA;193;0
"Unit";"Hellion";"Factory";193;2
"Building";"MissileTurret";NA;193;0
"Unit";"Thor";"Factory";179;6
"Building";"Refinery";NA;193;0
"Unit";"Thor";"Factory";193;6
"Unit";"Thor";"Factory";193;6
"Unit";"Thor";"Factory";193;6
"Unit";"Hellion";"Factory";203;2
"Unit";"Hellion";"Factory";203;2
"Unit";"Hellion";"Factory";227;2
"Unit";"Hellion";"Factory";227;2
"Unit";"Thor";"Factory";215;6
"Unit";"Thor";"Factory";221;6
"Building";"Starport";NA;231;0
"Building";"Starport";NA;231;0
"Building";"MissileTurret";NA;235;0
"Building";"MissileTurret";NA;235;0
"Building";"Starport";NA;231;0
"Building";"MissileTurret";NA;235;0
"Building";"MissileTurret";NA;235;0
"Building";"MissileTurret";NA;235;0
"Building";"StarportTechLab";NA;247;0
"Building";"StarportTechLab";NA;247;0
"Building";"StarportTechLab";NA;247;0
"Unit";"Hellion";"Factory";247;2
"Unit";"Hellion";"Factory";247;2
"Unit";"Thor";"Factory";247;6
"Unit";"Thor";"Factory";247;6
"Building";"CommandCenter";NA;247;0
"Building";"Starport";NA;247;0
"Upgrade";"TerranVehicleWeaponsLevel3";"Armory";231;0
"Building";"Starport";NA;247;0
"Unit";"Hellion";"Factory";263;2
"Unit";"Hellion";"Factory";263;2
"Unit";"Hellion";"Factory";263;2
"Unit";"Hellion";"Factory";263;2
"Unit";"Hellion";"Factory";263;2
"Building";"StarportTechLab";NA;263;0
"Building";"StarportTechLab";NA;263;0
"Unit";"Hellion";"Factory";263;2
"Unit";"Hellion";"Factory";263;2
"Unit";"Thor";"Factory";263;6
"Unit";"Thor";"Factory";263;6
"Unit";"Hellion";"Factory";273;2
"Unit";"Hellion";"Factory";273;2
"Unit";"Hellion";"Factory";273;2
"Unit";"Hellion";"Factory";273;2
"Unit";"Raven";"Starport";263;2
"Unit";"Raven";"Starport";263;2
"Unit";"Raven";"Starport";263;2
"Unit";"Hellion";"Factory";273;2
"Unit";"Thor";"Factory";263;6
"Unit";"Thor";"Factory";263;6
"Unit";"Hellion";"Factory";273;2
"Building";"Refinery";NA;297;0
"Building";"Refinery";NA;297;0
"Unit";"Raven";"Starport";273;2
"Unit";"Raven";"Starport";273;2
"Unit";"Thor";"Factory";289;6
"Unit";"Raven";"Starport";297;2
"Upgrade";"TerranShipWeaponsLevel1";"Armory";297;0
"Unit";"Raven";"Starport";331;2
"Unit";"Raven";"Starport";331;2
"Unit";"Raven";"Starport";331;2
"Unit";"Raven";"Starport";331;2
"Building";"MissileTurret";NA;331;0
"Building";"MissileTurret";NA;331;0
"Building";"MissileTurret";NA;331;0
"Building";"MissileTurret";NA;331;0
"Building";"MissileTurret";NA;331;0
"Unit";"Hellion";"Factory";339;2
"Unit";"Hellion";"Factory";339;2
"Unit";"Hellion";"Factory";339;2
"Unit";"Hellion";"Factory";339;2
"Unit";"Hellion";"Factory";339;2
"Unit";"Hellion";"Factory";339;2
"Unit";"Hellion";"Factory";339;2
"Upgrade";"TerranShipWeaponsLevel2";"Armory";339;0
"Unit";"Hellion";"Factory";353;2
"Unit";"Hellion";"Factory";353;2
"Unit";"Hellion";"Factory";353;2
"Unit";"Hellion";"Factory";353;2
"Unit";"Raven";"Starport";353;2
"Unit";"Raven";"Starport";353;2
"Unit";"Raven";"Starport";353;2
"Unit";"Raven";"Starport";353;2
