"type";"unit_name";"on_building";"total_supply";"supply"
"Building";"Barracks";NA;15;0
"Building";"Barracks";NA;16;0
"Unit";"Marine";"Barracks";19;1
"Unit";"Marine";"Barracks";19;1
"Unit";"Marine";"Barracks";19;1
"Unit";"Marine";"Barracks";22;1
"Unit";"Marine";"Barracks";22;1
"Building";"Refinery";NA;20;0
"Building";"Refinery";NA;20;0
"Unit";"Marine";"Barracks";25;1
"Unit";"Marine";"Barracks";25;1
"Building";"Bunker";NA;23;0
"Building";"Bunker";NA;23;0
"Unit";"Marine";"Barracks";25;1
"Unit";"Marine";"Barracks";27;1
"Unit";"Marine";"Barracks";29;1
"Unit";"Marine";"Barracks";30;1
"Building";"Factory";NA;29;0
"Unit";"Marine";"Barracks";34;1
"Unit";"Marine";"Barracks";34;1
"Building";"FactoryTechLab";NA;34;0
"Building";"Starport";NA;34;0
"Building";"Bunker";NA;36;0
"Building";"Bunker";NA;37;0
"Building";"EngineeringBay";NA;37;0
"Building";"CommandCenter";NA;36;0
"Unit";"Banshee";"Starport";38;3
"Building";"FactoryReactor";NA;39;0
"Building";"Barracks";NA;39;0
"Unit";"Cyclone";"Factory";45;3
"Unit";"Cyclone";"Factory";45;3
"Unit";"Banshee";"Starport";43;3
"Building";"BarracksTechLab";NA;47;0
"Building";"BarracksTechLab";NA;47;0
"Upgrade";"TerranInfantryWeaponsLevel1";"EngineeringBay";40;0
"Unit";"Cyclone";"Factory";58;3
"Unit";"Raven";"Starport";53;2
"Building";"Refinery";NA;65;0
"Building";"Refinery";NA;65;0
"Unit";"Hellion";"Factory";65;2
"Unit";"Hellion";"Factory";65;2
"Building";"CommandCenter";NA;58;0
"Unit";"Marine";"Barracks";70;1
"Unit";"Marine";"Barracks";70;1
"Building";"StarportReactor";NA;66;0
"Unit";"Medivac";"Starport";75;2
"Building";"Armory";NA;71;0
"Unit";"Marine";"Barracks";77;1
"Unit";"Marine";"Barracks";77;1
"Unit";"Marine";"Barracks";77;1
"Unit";"Marine";"Barracks";77;1
"Unit";"Medivac";"Starport";77;2
"Unit";"Marine";"Barracks";81;1
"Unit";"Marine";"Barracks";83;1
"Upgrade";"TerranInfantryArmorsLevel1";"EngineeringBay";70;0
"Upgrade";"Stimpack";"TechLab";71;0
"Unit";"Marine";"Barracks";90;1
"Unit";"Marine";"Barracks";90;1
"Unit";"Marine";"Barracks";90;1
"Unit";"Marine";"Barracks";94;1
"Unit";"Medivac";"Starport";94;2
"Unit";"Medivac";"Starport";94;2
"Unit";"Marine";"Barracks";96;1
"Unit";"Marine";"Barracks";99;1
"Unit";"Marine";"Barracks";99;1
"Unit";"Marine";"Barracks";100;1
"Unit";"Marine";"Barracks";106;1
"Unit";"Marine";"Barracks";107;1
"Unit";"Marine";"Barracks";108;1
"Unit";"Marine";"Barracks";109;1
"Unit";"Marine";"Barracks";110;1
"Unit";"Marine";"Barracks";111;1
"Unit";"Marine";"Barracks";112;1
"Building";"Barracks";NA;100;0
"Building";"Barracks";NA;100;0
"Building";"Refinery";NA;114;0
"Building";"Refinery";NA;114;0
"Unit";"Medivac";"Starport";113;2
"Unit";"Medivac";"Starport";114;2
"Unit";"Marine";"Barracks";115;1
"Unit";"Marine";"Barracks";117;1
"Unit";"Marine";"Barracks";118;1
"Unit";"Marauder";"Barracks";115;2
