"Type";"UnitName";"OnBuilding";"TotalSupply";"Supply"
"Unit";"SCV";"Command Center";12;1
"Unit";"SCV";"Command Center";12;1
"Unit";"SCV";"Command Center";14;1
"Building";"SupplyDepot";NA;13;0
"Unit";"SCV";"Command Center";15;1
"Unit";"SCV";"Command Center";15;1
"Building";"Refinery";NA;15;0
"Building";"Barracks";NA;15;0
"Unit";"SCV";"Command Center";16;1
"Building";"Barracks";NA;15;0
"Unit";"SCV";"Command Center";17;1
"Unit";"Marine";"Barracks";17;1
"Unit";"Marine";"Barracks";18;1
"Unit";"Marine";"Barracks";19;1
"Unit";"SCV";"Command Center";20;1
"Building";"Bunker";NA;18;0
"Building";"SupplyDepot";NA;21;0
"Unit";"Marine";"Barracks";23;1
"Building";"Bunker";NA;20;0
"Unit";"SCV";"Command Center";23;1
"Unit";"Marine";"Barracks";23;1
"Unit";"Marine";"Barracks";24;1
"Unit";"Marine";"Barracks";26;1
"Unit";"Marine";"Barracks";27;1
"Building";"Factory";NA;24;0
"Unit";"SCV";"Command Center";29;1
"Building";"Refinery";NA;27;0
"Building";"SupplyDepot";NA;30;0
"Unit";"SCV";"Command Center";30;1
"Building";"Starport";NA;29;0
"Unit";"SCV";"Command Center";31;1
"Building";"StarportTechLab";NA;31;0
"Unit";"Cyclone";"Factory";31;3
"Unit";"SCV";"Command Center";32;1
"Building";"SupplyDepot";NA;32;0
"Unit";"SCV";"Command Center";36;1
"Unit";"SCV";"Command Center";37;1
"Unit";"Banshee";"Starport";32;3
"Unit";"Cyclone";"Factory";36;3
"Unit";"SCV";"Command Center";44;1
"Unit";"Banshee";"Starport";38;3
"Unit";"Cyclone";"Factory";45;3
"Unit";"SCV";"Command Center";45;1
"Building";"BarracksTechLab";NA;48;0
"Building";"SupplyDepot";NA;52;0
"Unit";"SCV";"Command Center";52;1
"Building";"BarracksReactor";NA;48;0
"Unit";"SCV";"Command Center";52;1
"Unit";"Cyclone";"Factory";52;3
"Building";"Barracks";NA;48;0
"Unit";"SCV";"Command Center";53;1
"Building";"CommandCenter";NA;44;0
"Unit";"Marine";"Barracks";54;1
"Unit";"Marine";"Barracks";54;1
"Unit";"Marine";"Barracks";54;1
"Building";"FactoryTechLab";NA;57;0
"Building";"StarportReactor";NA;57;0
"Unit";"Marine";"Barracks";61;1
"Unit";"Marine";"Barracks";61;1
"Unit";"Marine";"Barracks";61;1
"Unit";"SCV";"Command Center";61;1
"Unit";"Marine";"Barracks";64;1
"Unit";"Marine";"Barracks";65;1
"Unit";"Marine";"Barracks";65;1
"Unit";"Marine";"Barracks";65;1
"Unit";"Medivac";"Starport";65;2
"Unit";"Medivac";"Starport";65;2
"Building";"SupplyDepot";NA;66;0
"Unit";"SCV";"Command Center";66;1
"Unit";"Marine";"Barracks";66;1
"Unit";"Marine";"Barracks";69;1
"Unit";"Marine";"Barracks";69;1
"Unit";"SCV";"Command Center";73;1
"Unit";"Marine";"Barracks";73;1
"Upgrade";"Stimpack";"TechLab";61;0
"Building";"SupplyDepot";NA;74;0
"Unit";"Marine";"Barracks";75;1
"Building";"SupplyDepot";NA;75;0
"Unit";"SCV";"Command Center";79;1
"Unit";"SCV";"Command Center";79;1
"Unit";"Medivac";"Starport";78;2
"Unit";"Marine";"Barracks";79;1
"Unit";"Marine";"Barracks";80;1
"Building";"SupplyDepot";NA;80;0
"Unit";"SCV";"Command Center";80;1
"Unit";"Marine";"Barracks";82;1
"Unit";"Marine";"Barracks";82;1
"Unit";"Marine";"Barracks";86;1
"Unit";"Marine";"Barracks";86;1
"Unit";"SCV";"Command Center";91;1
"Unit";"Marauder";"Barracks";87;2
"Unit";"Marauder";"Barracks";89;2
"Unit";"Marine";"Barracks";91;1
"Unit";"Marine";"Barracks";91;1
"Unit";"Marine";"Barracks";96;1
"Unit";"Marine";"Barracks";97;1
"Unit";"Marauder";"Barracks";96;2
"Building";"Barracks";NA;91;0
"Unit";"Marauder";"Barracks";96;2
"Building";"Barracks";NA;91;0
"Unit";"SCV";"Command Center";104;1
"Unit";"Marine";"Barracks";104;1
"Unit";"Marauder";"Barracks";100;2
"Unit";"Marine";"Barracks";104;1
"Unit";"Marauder";"Barracks";102;2
"Building";"BarracksTechLab";NA;104;0
"Unit";"Marauder";"Barracks";106;2
"Unit";"Marine";"Barracks";111;1
"Unit";"Marine";"Barracks";111;1
"Unit";"Marine";"Barracks";111;1
"Unit";"Marauder";"Barracks";111;2
"Building";"BarracksReactor";NA;104;0
"Unit";"Medivac";"Starport";111;2
"Unit";"Medivac";"Starport";111;2
"Unit";"Marine";"Barracks";111;1
"Unit";"Marine";"Barracks";113;1
"Unit";"Marine";"Barracks";114;1
"Unit";"SCV";"Command Center";118;1
"Unit";"Marauder";"Barracks";115;2
"Unit";"Marine";"Barracks";118;1
"Unit";"Marine";"Barracks";118;1
"Unit";"Marauder";"Barracks";116;2
"Unit";"Marine";"Barracks";122;1
"Building";"SupplyDepot";NA;122;0
"Building";"SupplyDepot";NA;125;0
"Unit";"Marauder";"Barracks";126;2
"Unit";"Marine";"Barracks";133;1
"Unit";"Marine";"Barracks";133;1
"Unit";"Marine";"Barracks";133;1
"Unit";"Marauder";"Barracks";133;2
"Unit";"Marine";"Barracks";135;1
"Unit";"Marine";"Barracks";135;1
"Unit";"Marine";"Barracks";135;1
"Building";"SupplyDepot";NA;135;0
"Unit";"Marine";"Barracks";135;1
"Building";"SupplyDepot";NA;135;0
"Unit";"Medivac";"Starport";135;2
"Unit";"Medivac";"Starport";135;2
"Unit";"Marine";"Barracks";143;1
"Unit";"Marine";"Barracks";143;1
"Unit";"Marine";"Barracks";143;1
"Unit";"Marine";"Barracks";143;1
"Unit";"Marine";"Barracks";143;1
"Unit";"Marauder";"Barracks";143;2
"Unit";"Marine";"Barracks";148;1
"Unit";"Marine";"Barracks";148;1
"Unit";"Marine";"Barracks";148;1
"Unit";"Marauder";"Barracks";148;2
