"Type";"UnitName";"OnBuilding";"TotalSupply";"Supply"
"Unit";"SCV";"Command Center";12;1
"Unit";"SCV";"Command Center";13;1
"Building";"SupplyDepot";NA;13;0
"Unit";"SCV";"Command Center";13;1
"Building";"Refinery";NA;14;0
"Unit";"SCV";"Command Center";14;1
"Unit";"SCV";"Command Center";16;1
"Unit";"SCV";"Command Center";16;1
"Unit";"SCV";"Command Center";18;1
"Building";"Barracks";NA;15;0
"Unit";"Reaper";"Barracks";19;1
"Unit";"SCV";"Command Center";19;1
"Unit";"SCV";"Command Center";20;1
"Building";"Refinery";NA;20;0
"Unit";"SCV";"Command Center";21;1
"Building";"Factory";NA;19;0
"Building";"SupplyDepot";NA;21;0
"Building";"BarracksReactor";NA;20;0
"Unit";"SCV";"Command Center";23;1
"Building";"CommandCenter";NA;19;0
"Unit";"SCV";"Command Center";24;1
"Building";"BarracksTechLab";NA;24;0
"Unit";"Hellion";"Factory";24;2
"Unit";"Hellion";"Factory";24;2
"Building";"Starport";NA;23;0
"Unit";"SCV";"Command Center";25;1
"Unit";"SCV";"Command Center";30;1
"Building";"SupplyDepot";NA;25;0
"Unit";"SCV";"Command Center";30;1
"Unit";"Hellion";"Factory";29;2
"Unit";"Hellion";"Factory";29;2
"Unit";"SCV";"Command Center";30;1
"Unit";"SCV";"Command Center";36;1
"Unit";"SCV";"Command Center";37;1
"Building";"SupplyDepot";NA;36;0
"Unit";"Hellion";"Factory";36;2
"Unit";"SCV";"Command Center";37;1
"Unit";"Hellion";"Factory";37;2
"Unit";"SCV";"Command Center";38;1
"Unit";"SCV";"Command Center";41;1
"Unit";"SCV";"Command Center";44;1
"Unit";"Hellion";"Factory";39;2
"Unit";"Hellion";"Factory";42;2
"Unit";"SCV";"Command Center";46;1
"Unit";"SCV";"Command Center";51;1
"Building";"SupplyDepot";NA;46;0
"Unit";"SCV";"Command Center";51;1
"Unit";"Liberator";"Starport";41;3
"Unit";"SCV";"Command Center";57;1
"Unit";"SCV";"Command Center";57;1
"Building";"Refinery";NA;53;0
"Building";"Refinery";NA;54;0
"Unit";"SCV";"Command Center";57;1
"Unit";"SCV";"Command Center";58;1
"Unit";"Cyclone";"Factory";57;3
"Unit";"Cyclone";"Factory";57;3
"Unit";"SCV";"Command Center";59;1
"Unit";"SCV";"Command Center";60;1
"Unit";"SCV";"Command Center";67;1
"Unit";"SCV";"Command Center";68;1
"Building";"CommandCenter";NA;49;0
"Building";"BarracksTechLab";NA;69;0
"Unit";"SCV";"Command Center";69;1
"Unit";"SCV";"Command Center";70;1
"Unit";"Cyclone";"Factory";69;3
"Building";"SupplyDepot";NA;69;0
"Unit";"Cyclone";"Factory";71;3
"Building";"SupplyDepot";NA;71;0
"Unit";"SCV";"Command Center";73;1
"Unit";"Banshee";"Starport";67;3
"Unit";"SCV";"Command Center";76;1
"Building";"Armory";NA;67;0
"Building";"Armory";NA;67;0
"Unit";"SCV";"Command Center";84;1
"Building";"SupplyDepot";NA;76;0
"Unit";"SCV";"Command Center";84;1
"Unit";"SCV";"Command Center";84;1
"Unit";"SCV";"Command Center";85;1
"Building";"Refinery";NA;84;0
"Building";"Factory";NA;76;0
"Building";"Factory";NA;76;0
"Building";"Refinery";NA;84;0
"Unit";"SCV";"Command Center";86;1
"Unit";"Hellion";"Factory";85;2
"Unit";"Hellion";"Factory";85;2
"Unit";"SCV";"Command Center";87;1
"Unit";"SCV";"Command Center";87;1
"Building";"SupplyDepot";NA;86;0
"Building";"SupplyDepot";NA;86;0
"Unit";"SCV";"Command Center";95;1
"Unit";"SCV";"Command Center";95;1
"Building";"StarportReactor";NA;86;0
"Unit";"SCV";"Command Center";95;1
"Unit";"Hellion";"Factory";95;2
"Unit";"Hellion";"Factory";95;2
"Unit";"SCV";"Command Center";95;1
"Unit";"SCV";"Command Center";96;1
"Building";"SupplyDepot";NA;95;0
"Unit";"SCV";"Command Center";98;1
"Building";"SupplyDepot";NA;95;0
"Unit";"SCV";"Command Center";102;1
"Unit";"SCV";"Command Center";104;1
"Unit";"Hellion";"Factory";98;2
"Unit";"Hellion";"Factory";100;2
"Building";"SupplyDepot";NA;104;0
"Building";"SupplyDepot";NA;104;0
"Unit";"SCV";"Command Center";106;1
"Unit";"Thor";"Factory";95;6
"Unit";"Thor";"Factory";95;6
"Unit";"SCV";"Command Center";107;1
"Unit";"SCV";"Command Center";111;1
"Unit";"Medivac";"Starport";104;2
"Unit";"Medivac";"Starport";104;2
"Unit";"SCV";"Command Center";111;1
"Unit";"Hellion";"Factory";107;2
"Unit";"Hellion";"Factory";109;2
"Unit";"SCV";"Command Center";124;1
"Unit";"SCV";"Command Center";125;1
"Building";"SupplyDepot";NA;111;0
"Building";"SupplyDepot";NA;112;0
"Upgrade";"TerranVehicleWeaponsLevel1";"Armory";88;0
"Upgrade";"TerranVehicleAndShipArmorsLevel1";"Armory";88;0
"Unit";"SCV";"Command Center";130;1
"Building";"SupplyDepot";NA;124;0
"Unit";"SCV";"Command Center";135;1
"Building";"EngineeringBay";NA;124;0
"Unit";"SCV";"Command Center";137;1
"Unit";"Hellion";"Factory";135;2
"Building";"SupplyDepot";NA;137;0
"Building";"SupplyDepot";NA;137;0
"Building";"SensorTower";NA;139;0
"Building";"SupplyDepot";NA;138;0
"Unit";"Medivac";"Starport";137;2
"Unit";"Medivac";"Starport";137;2
"Unit";"SCV";"Command Center";142;1
"Unit";"SCV";"Command Center";142;1
"Unit";"Hellion";"Factory";139;2
"Building";"Factory";NA;131;0
"Building";"SensorTower";NA;142;0
"Building";"Factory";NA;135;0
"Unit";"Hellion";"Factory";142;2
"Unit";"Hellion";"Factory";150;2
"Building";"SupplyDepot";NA;150;0
"Building";"SupplyDepot";NA;150;0
"Unit";"Hellion";"Factory";152;2
"Building";"FactoryTechLab";NA;152;0
"Building";"FactoryTechLab";NA;152;0
"Unit";"Hellion";"Factory";154;2
"Unit";"Medivac";"Starport";152;2
"Building";"SupplyDepot";NA;154;0
"Building";"SupplyDepot";NA;154;0
"Unit";"Hellion";"Factory";156;2
"Unit";"Thor";"Factory";152;6
"Unit";"Hellion";"Factory";156;2
"Unit";"Hellion";"Factory";156;2
"Building";"CommandCenter";NA;150;0
"Unit";"Hellion";"Factory";160;2
"Unit";"Hellion";"Factory";160;2
"Unit";"Hellion";"Factory";162;2
"Unit";"Medivac";"Starport";160;2
"Unit";"Medivac";"Starport";160;2
"Unit";"Hellion";"Factory";172;2
"Unit";"Hellion";"Factory";172;2
"Unit";"Hellion";"Factory";178;2
"Unit";"Hellion";"Factory";178;2
"Unit";"Hellion";"Factory";182;2
"Building";"CommandCenter";NA;156;0
"Unit";"Hellion";"Factory";184;2
"Unit";"Thor";"Factory";176;6
"Unit";"Hellion";"Factory";190;2
"Unit";"Hellion";"Factory";190;2
"Unit";"Hellion";"Factory";190;2
"Upgrade";"TerranVehicleWeaponsLevel2";"Armory";154;0
"Unit";"Medivac";"Starport";190;2
"Unit";"Medivac";"Starport";190;2
"Building";"Refinery";NA;192;0
"Unit";"SCV";"Command Center";202;1
"Unit";"SCV";"Command Center";204;1
"Unit";"SCV";"Command Center";206;1
"Building";"Refinery";NA;194;0
"Unit";"Hellion";"Factory";194;2
"Unit";"Hellion";"Factory";200;2
"Unit";"Hellion";"Factory";200;2
"Unit";"SCV";"Command Center";210;1
"Unit";"Thor";"Factory";190;6
"Unit";"Hellion";"Factory";213;2
"Unit";"Hellion";"Factory";213;2
"Building";"CommandCenter";NA;184;0
"Upgrade";"TerranVehicleAndShipArmorsLevel2";"Armory";176;0
"Building";"SupplyDepot";NA;226;0
"Building";"SupplyDepot";NA;226;0
"Building";"SupplyDepot";NA;226;0
"Unit";"Thor";"Factory";215;6
"Unit";"Thor";"Factory";220;6
