"type";"unit_name";"on_building";"total_supply";"supply"
"Building";"Refinery";NA;15;0
"Building";"Barracks";NA;15;0
"Unit";"Reaper";"Barracks";19;1
"Unit";"Marine";"Barracks";19;1
"Building";"Refinery";NA;23;0
"Building";"CommandCenter";NA;19;0
"Building";"Factory";NA;21;0
"Building";"BarracksReactor";NA;23;0
"Unit";"Hellion";"Factory";27;2
"Building";"BarracksTechLab";NA;27;0
"Unit";"Hellion";"Factory";27;2
"Building";"Starport";NA;26;0
"Unit";"Hellion";"Factory";28;2
"Unit";"Hellion";"Factory";30;2
"Unit";"Hellion";"Factory";40;2
"Unit";"Hellion";"Factory";40;2
"Unit";"Hellion";"Factory";48;2
"Unit";"Banshee";"Starport";40;3
"Building";"Armory";NA;42;0
"Unit";"Hellion";"Factory";50;2
"Unit";"Hellion";"Factory";59;2
"Unit";"Hellion";"Factory";59;2
"Unit";"Banshee";"Starport";52;3
"Unit";"Hellion";"Factory";62;2
"Unit";"Hellion";"Factory";62;2
"Unit";"Hellion";"Factory";75;2
"Unit";"Hellion";"Factory";75;2
"Unit";"Banshee";"Starport";68;3
"Building";"BarracksTechLab";NA;75;0
"Building";"Refinery";NA;75;0
"Building";"Refinery";NA;75;0
"Building";"EngineeringBay";NA;75;0
"Building";"EngineeringBay";NA;75;0
"Building";"CommandCenter";NA;62;0
"Unit";"Hellion";"Factory";77;2
"Unit";"Hellion";"Factory";81;2
"Building";"Barracks";NA;76;0
"Building";"Barracks";NA;76;0
"Building";"Barracks";NA;76;0
"Building";"Barracks";NA;81;0
"Unit";"Banshee";"Starport";85;3
"Building";"BarracksTechLab";NA;92;0
"Building";"BarracksReactor";NA;92;0
"Building";"BarracksReactor";NA;92;0
"Building";"BarracksReactor";NA;92;0
"Building";"MissileTurret";NA;95;0
"Building";"MissileTurret";NA;95;0
"Building";"Barracks";NA;92;0
"Building";"Barracks";NA;92;0
"Building";"Barracks";NA;92;0
"Unit";"Marine";"Barracks";96;1
"Unit";"Marine";"Barracks";96;1
"Unit";"Marine";"Barracks";96;1
"Unit";"Marine";"Barracks";96;1
"Unit";"Marine";"Barracks";96;1
"Unit";"Marine";"Barracks";96;1
"Unit";"Marine";"Barracks";96;1
"Unit";"Marine";"Barracks";96;1
"Unit";"Medivac";"Starport";95;2
"Unit";"Medivac";"Starport";95;2
"Unit";"Marine";"Barracks";96;1
"Unit";"Marine";"Barracks";97;1
"Unit";"Marine";"Barracks";99;1
"Building";"Refinery";NA;99;0
"Building";"Refinery";NA;102;0
"Unit";"Marine";"Barracks";111;1
"Unit";"Marine";"Barracks";111;1
"Unit";"Marine";"Barracks";111;1
"Unit";"Marine";"Barracks";111;1
"Unit";"Marine";"Barracks";111;1
"Building";"Bunker";NA;109;0
"Building";"BarracksReactor";NA;99;0
"Building";"BarracksReactor";NA;99;0
"Unit";"Marine";"Barracks";115;1
"Upgrade";"TerranInfantryWeaponsLevel1";"EngineeringBay";95;0
"Upgrade";"TerranInfantryArmorsLevel1";"EngineeringBay";95;0
"Unit";"Marine";"Barracks";122;1
"Unit";"Marine";"Barracks";122;1
"Unit";"Marine";"Barracks";122;1
"Unit";"Marine";"Barracks";122;1
"Unit";"Marine";"Barracks";122;1
"Unit";"Marine";"Barracks";122;1
"Unit";"Marine";"Barracks";122;1
"Unit";"Marine";"Barracks";123;1
"Unit";"Marine";"Barracks";123;1
"Unit";"Marine";"Barracks";123;1
"Unit";"Marine";"Barracks";123;1
"Unit";"Marine";"Barracks";123;1
"Upgrade";"Stimpack";"TechLab";95;0
"Building";"Factory";NA;114;0
"Building";"MissileTurret";NA;123;0
"Unit";"Marine";"Barracks";135;1
"Unit";"Marine";"Barracks";135;1
"Unit";"Marine";"Barracks";135;1
"Unit";"Marine";"Barracks";135;1
"Upgrade";"TerranVehicleWeaponsLevel1";"Armory";102;0
"Unit";"Marine";"Barracks";135;1
"Unit";"Marine";"Barracks";135;1
"Unit";"Marine";"Barracks";135;1
"Unit";"Marine";"Barracks";135;1
"Unit";"Marine";"Barracks";135;1
"Unit";"Marine";"Barracks";137;1
"Unit";"Marine";"Barracks";137;1
"Building";"FactoryTechLab";NA;147;0
"Unit";"Marine";"Barracks";147;1
"Unit";"Marine";"Barracks";147;1
"Unit";"Marine";"Barracks";147;1
"Unit";"Marine";"Barracks";147;1
"Unit";"Marine";"Barracks";147;1
"Unit";"Marine";"Barracks";147;1
"Unit";"Marine";"Barracks";149;1
"Unit";"Marine";"Barracks";149;1
"Unit";"Marine";"Barracks";149;1
"Unit";"Marine";"Barracks";149;1
"Unit";"Medivac";"Starport";149;2
"Unit";"Medivac";"Starport";149;2
"Unit";"Marine";"Barracks";164;1
"Unit";"Marine";"Barracks";164;1
"Unit";"Marine";"Barracks";164;1
"Unit";"Marine";"Barracks";164;1
"Unit";"Marine";"Barracks";164;1
"Unit";"Marauder";"Barracks";164;2
"Unit";"Marauder";"Barracks";164;2
"Unit";"Marine";"Barracks";164;1
"Unit";"Marine";"Barracks";164;1
"Unit";"Marine";"Barracks";164;1
"Unit";"Marine";"Barracks";164;1
"Upgrade";"TerranInfantryWeaponsLevel2";"EngineeringBay";147;0
"Unit";"Marine";"Barracks";164;1
"Upgrade";"TerranInfantryArmorsLevel2";"EngineeringBay";147;0
"Unit";"Marauder";"Barracks";169;2
"Unit";"Marine";"Barracks";180;1
"Unit";"Marine";"Barracks";180;1
"Unit";"Marine";"Barracks";180;1
"Unit";"Marine";"Barracks";180;1
"Unit";"Marine";"Barracks";180;1
"Unit";"Marine";"Barracks";180;1
"Unit";"Marine";"Barracks";180;1
"Unit";"Marine";"Barracks";180;1
"Unit";"Marine";"Barracks";180;1
"Unit";"Marine";"Barracks";180;1
"Unit";"Marine";"Barracks";180;1
"Unit";"Marauder";"Barracks";180;2
"Unit";"Marine";"Barracks";180;1
"Unit";"Marine";"Barracks";181;1
"Unit";"Marine";"Barracks";182;1
"Unit";"Marine";"Barracks";183;1
"Unit";"Marine";"Barracks";184;1
"Unit";"Marine";"Barracks";185;1
"Unit";"Marine";"Barracks";186;1
"Unit";"Marine";"Barracks";187;1
"Unit";"Marine";"Barracks";188;1
"Unit";"Marine";"Barracks";189;1
"Unit";"Marauder";"Barracks";190;2
"Unit";"Marauder";"Barracks";191;2
"Unit";"Marine";"Barracks";194;1
"Unit";"Marine";"Barracks";195;1
"Unit";"Marine";"Barracks";196;1
"Unit";"Marine";"Barracks";197;1
"Unit";"Marine";"Barracks";198;1
"Unit";"Marine";"Barracks";199;1
"Unit";"Marine";"Barracks";200;1
"Unit";"Marine";"Barracks";201;1
"Unit";"Marine";"Barracks";202;1
"Unit";"Marauder";"Barracks";204;2
"Unit";"Marauder";"Barracks";206;2
"Unit";"Marine";"Barracks";217;1
"Unit";"Marine";"Barracks";217;1
"Unit";"Marine";"Barracks";219;1
"Unit";"Marine";"Barracks";219;1
"Unit";"Marauder";"Barracks";217;2
"Unit";"Marauder";"Barracks";219;2
"Unit";"Marine";"Barracks";221;1
"Unit";"Marine";"Barracks";221;1
"Unit";"Marine";"Barracks";221;1
"Unit";"Marine";"Barracks";221;1
"Unit";"Marine";"Barracks";221;1
"Unit";"Medivac";"Starport";221;2
"Unit";"Medivac";"Starport";221;2
"Unit";"Marauder";"Barracks";225;2
"Unit";"Marauder";"Barracks";227;2
"Building";"CommandCenter";NA;199;0
"Unit";"Marine";"Barracks";234;1
"Unit";"Marine";"Barracks";234;1
"Unit";"Marine";"Barracks";238;1
"Unit";"Marine";"Barracks";238;1
"Unit";"Marine";"Barracks";238;1
"Unit";"Marine";"Barracks";238;1
"Unit";"Marauder";"Barracks";238;2
"Unit";"Marauder";"Barracks";240;2
"Unit";"Medivac";"Starport";244;2
"Unit";"Medivac";"Starport";244;2
"Unit";"Marauder";"Barracks";248;2
"Unit";"Marauder";"Barracks";250;2
"Unit";"Marine";"Barracks";252;1
"Unit";"Marine";"Barracks";252;1
"Unit";"Marine";"Barracks";256;1
"Unit";"Marine";"Barracks";256;1
"Unit";"Marine";"Barracks";256;1
"Unit";"Marine";"Barracks";256;1
"Unit";"Marine";"Barracks";258;1
"Unit";"Marine";"Barracks";258;1
"Unit";"Marine";"Barracks";260;1
"Unit";"Marine";"Barracks";260;1
"Unit";"Marauder";"Barracks";256;2
"Unit";"Marine";"Barracks";260;1
"Unit";"Marauder";"Barracks";258;2
"Unit";"Medivac";"Starport";252;2
"Unit";"Medivac";"Starport";254;2
