"Type";"UnitName";"OnBuilding";"TotalSupply";"Supply"
"Unit";"SCV";"Command Center";12;1
"Unit";"SCV";"Command Center";12;1
"Unit";"SCV";"Command Center";13;1
"Building";"SupplyDepot";NA;13;0
"Unit";"SCV";"Command Center";15;1
"Building";"Refinery";NA;14;0
"Unit";"SCV";"Command Center";16;1
"Unit";"SCV";"Command Center";16;1
"Unit";"SCV";"Command Center";17;1
"Building";"Barracks";NA;15;0
"Unit";"Reaper";"Barracks";19;1
"Unit";"SCV";"Command Center";19;1
"Unit";"SCV";"Command Center";21;1
"Building";"SupplyDepot";NA;20;0
"Building";"Refinery";NA;21;0
"Unit";"SCV";"Command Center";22;1
"Building";"Factory";NA;19;0
"Building";"BarracksReactor";NA;20;0
"Unit";"SCV";"Command Center";22;1
"Building";"CommandCenter";NA;19;0
"Unit";"SCV";"Command Center";24;1
"Building";"BarracksTechLab";NA;24;0
"Unit";"Hellion";"Factory";24;2
"Unit";"Hellion";"Factory";24;2
"Building";"Starport";NA;23;0
"Unit";"SCV";"Command Center";25;1
"Unit";"Hellion";"Factory";25;2
"Unit";"SCV";"Command Center";29;1
"Unit";"Hellion";"Factory";27;2
"Unit";"SCV";"Command Center";30;1
"Unit";"SCV";"Command Center";36;1
"Unit";"SCV";"Command Center";36;1
"Unit";"Hellion";"Factory";36;2
"Unit";"SCV";"Command Center";37;1
"Unit";"Banshee";"Starport";30;3
"Unit";"SCV";"Command Center";38;1
"Building";"SupplyDepot";NA;36;0
"Building";"BarracksReactor";NA;35;0
"Building";"SupplyDepot";NA;40;0
"Building";"FactoryTechLab";NA;45;0
"Unit";"SCV";"Command Center";45;1
"Unit";"SCV";"Command Center";45;1
"Unit";"Marine";"Barracks";45;1
"Unit";"Marine";"Barracks";45;1
"Unit";"SCV";"Command Center";45;1
"Unit";"SCV";"Command Center";47;1
"Unit";"SCV";"Command Center";49;1
"Building";"Refinery";NA;47;0
"Building";"Refinery";NA;47;0
"Unit";"Marine";"Barracks";50;1
"Building";"SupplyDepot";NA;47;0
"Unit";"Marine";"Barracks";50;1
"Unit";"SCV";"Command Center";51;1
"Unit";"SCV";"Command Center";53;1
"Unit";"SCV";"Command Center";55;1
"Unit";"SCV";"Command Center";55;1
"Building";"BarracksTechLab";NA;55;0
"Unit";"Banshee";"Starport";51;3
"Building";"CommandCenter";NA;45;0
"Unit";"SCV";"Command Center";58;1
"Unit";"SCV";"Command Center";58;1
"Unit";"SCV";"Command Center";62;1
"Building";"EngineeringBay";NA;58;0
"Building";"Barracks";NA;55;0
"Building";"Barracks";NA;55;0
"Building";"EngineeringBay";NA;58;0
"Unit";"Marine";"Barracks";62;1
"Unit";"SCV";"Command Center";63;1
"Unit";"SCV";"Command Center";63;1
"Building";"SupplyDepot";NA;63;0
"Building";"SupplyDepot";NA;63;0
"Building";"StarportReactor";NA;63;0
"Unit";"Marine";"Barracks";67;1
"Unit";"SCV";"Command Center";67;1
"Unit";"Marine";"Barracks";67;1
"Unit";"Marine";"Barracks";67;1
"Unit";"Marine";"Barracks";67;1
"Unit";"Marine";"Barracks";67;1
"Unit";"SCV";"Command Center";67;1
"Unit";"SCV";"Command Center";67;1
"Unit";"SCV";"Command Center";68;1
"Unit";"SCV";"Command Center";73;1
"Unit";"SCV";"Command Center";77;1
"Unit";"SCV";"Command Center";77;1
"Unit";"Marine";"Barracks";75;1
"Unit";"Marine";"Barracks";75;1
"Unit";"Marine";"Barracks";75;1
"Unit";"Marine";"Barracks";75;1
"Unit";"Marine";"Barracks";75;1
"Unit";"SCV";"Command Center";77;1
"Unit";"Medivac";"Starport";76;2
"Unit";"Marine";"Barracks";84;1
"Unit";"SCV";"Command Center";85;1
"Building";"SupplyDepot";NA;84;0
"Unit";"SCV";"Command Center";87;1
"Unit";"Marine";"Barracks";85;1
"Upgrade";"Stimpack";"TechLab";67;0
"Unit";"Marine";"Barracks";87;1
"Unit";"Marine";"Barracks";87;1
"Unit";"SCV";"Command Center";89;1
"Unit";"Marine";"Barracks";89;1
"Building";"Barracks";NA;79;0
"Building";"Barracks";NA;84;0
"Building";"SupplyDepot";NA;89;0
"Unit";"Marine";"Barracks";91;1
"Unit";"Marine";"Barracks";91;1
"Building";"SupplyDepot";NA;89;0
"Unit";"Marine";"Barracks";91;1
"Unit";"Marine";"Barracks";92;1
"Unit";"Medivac";"Starport";89;2
"Unit";"Medivac";"Starport";89;2
"Unit";"SCV";"Command Center";95;1
"Unit";"SCV";"Command Center";103;1
"Unit";"SCV";"Command Center";103;1
"Building";"Factory";NA;89;0
"Building";"SupplyDepot";NA;97;0
"Building";"SupplyDepot";NA;97;0
"Unit";"Marine";"Barracks";104;1
"Unit";"Marine";"Barracks";104;1
"Unit";"Marine";"Barracks";104;1
"Unit";"SCV";"Command Center";106;1
"Upgrade";"TerranInfantryWeaponsLevel1";"EngineeringBay";84;0
"Unit";"Marine";"Barracks";104;1
"Unit";"Marine";"Barracks";104;1
"Upgrade";"TerranInfantryArmorsLevel1";"EngineeringBay";84;0
"Unit";"SCV";"Command Center";106;1
"Unit";"SCV";"Command Center";106;1
"Building";"BarracksReactor";NA;97;0
"Building";"BarracksReactor";NA;97;0
"Unit";"Medivac";"Starport";104;2
"Unit";"SCV";"Command Center";109;1
"Building";"Barracks";NA;97;0
"Unit";"Marine";"Barracks";106;1
"Unit";"Marine";"Barracks";107;1
"Unit";"Marine";"Barracks";108;1
"Building";"Refinery";NA;106;0
"Building";"Refinery";NA;106;0
"Unit";"Marine";"Barracks";120;1
"Unit";"Marine";"Barracks";120;1
"Unit";"Marine";"Barracks";120;1
"Unit";"Marine";"Barracks";120;1
"Unit";"Marine";"Barracks";120;1
"Unit";"Marine";"Barracks";120;1
"Unit";"Marine";"Barracks";120;1
"Unit";"Marine";"Barracks";120;1
"Unit";"Marine";"Barracks";120;1
"Unit";"Medivac";"Starport";120;2
"Unit";"Marine";"Barracks";126;1
"Unit";"Marine";"Barracks";126;1
"Unit";"Marine";"Barracks";126;1
"Unit";"Marine";"Barracks";126;1
"Unit";"SCV";"Command Center";131;1
"Unit";"Marine";"Barracks";129;1
"Unit";"Marine";"Barracks";129;1
"Unit";"Marine";"Barracks";131;1
"Unit";"Marine";"Barracks";131;1
"Unit";"Marine";"Barracks";131;1
"Building";"SupplyDepot";NA;131;0
"Building";"SupplyDepot";NA;131;0
"Building";"SupplyDepot";NA;131;0
"Building";"SupplyDepot";NA;135;0
"Building";"SupplyDepot";NA;135;0
"Unit";"Marine";"Barracks";135;1
"Unit";"Marine";"Barracks";136;1
"Unit";"Marine";"Barracks";137;1
"Unit";"Marine";"Barracks";138;1
"Unit";"Medivac";"Starport";135;2
"Unit";"Medivac";"Starport";135;2
"Unit";"Marine";"Barracks";141;1
"Unit";"Marine";"Barracks";141;1
"Unit";"Marine";"Barracks";141;1
"Building";"BarracksReactor";NA;135;0
"Unit";"Marine";"Barracks";141;1
"Unit";"Marine";"Barracks";141;1
"Building";"SupplyDepot";NA;141;0
"Building";"SupplyDepot";NA;141;0
"Building";"SupplyDepot";NA;141;0
"Unit";"Marine";"Barracks";141;1
"Unit";"Marine";"Barracks";145;1
"Unit";"Marine";"Barracks";145;1
"Unit";"Marine";"Barracks";145;1
"Building";"CommandCenter";NA;120;0
"Building";"Armory";NA;135;0
"Unit";"Marine";"Barracks";154;1
"Unit";"Marine";"Barracks";154;1
"Unit";"Marine";"Barracks";154;1
"Unit";"Marine";"Barracks";154;1
"Unit";"Marine";"Barracks";158;1
"Unit";"Marine";"Barracks";158;1
"Unit";"Marine";"Barracks";158;1
"Unit";"Marine";"Barracks";158;1
"Unit";"Marine";"Barracks";158;1
"Unit";"Marine";"Barracks";158;1
"Unit";"Marine";"Barracks";162;1
"Unit";"Marine";"Barracks";162;1
"Unit";"Marine";"Barracks";162;1
"Unit";"Medivac";"Starport";158;2
"Unit";"Medivac";"Starport";158;2
"Unit";"Marine";"Barracks";164;1
"Unit";"Marine";"Barracks";165;1
"Unit";"SCV";"Command Center";168;1
"Unit";"SCV";"Command Center";168;1
"Unit";"Marine";"Barracks";168;1
"Unit";"Marine";"Barracks";168;1
"Unit";"Marine";"Barracks";168;1
"Unit";"Marine";"Barracks";168;1
"Unit";"Marine";"Barracks";183;1
"Unit";"Marine";"Barracks";183;1
"Unit";"Marine";"Barracks";183;1
"Unit";"Medivac";"Starport";171;2
"Unit";"Marine";"Barracks";183;1
"Unit";"Marine";"Barracks";183;1
"Unit";"Marine";"Barracks";183;1
"Unit";"Marine";"Barracks";183;1
"Unit";"Marine";"Barracks";183;1
"Unit";"Marine";"Barracks";183;1
"Unit";"Marine";"Barracks";183;1
"Unit";"Marine";"Barracks";183;1
"Unit";"Marine";"Barracks";183;1
"Unit";"Marine";"Barracks";188;1
"Unit";"Marine";"Barracks";188;1
"Unit";"SCV";"Command Center";194;1
"Unit";"SCV";"Command Center";194;1
"Unit";"Medivac";"Starport";188;2
"Unit";"Medivac";"Starport";188;2
"Unit";"Marine";"Barracks";199;1
"Unit";"Marine";"Barracks";199;1
"Unit";"Marine";"Barracks";199;1
"Unit";"Marine";"Barracks";199;1
"Unit";"Marine";"Barracks";199;1
"Unit";"Marine";"Barracks";199;1
"Unit";"Marine";"Barracks";201;1
"Unit";"Marine";"Barracks";201;1
"Unit";"Marine";"Barracks";201;1
"Unit";"Marine";"Barracks";201;1
"Unit";"Marine";"Barracks";211;1
"Unit";"Marine";"Barracks";211;1
"Unit";"Marine";"Barracks";211;1
"Unit";"Marine";"Barracks";211;1
"Unit";"Medivac";"Starport";211;2
"Unit";"Medivac";"Starport";211;2
"Unit";"Marine";"Barracks";215;1
"Unit";"Marine";"Barracks";215;1
"Unit";"Marine";"Barracks";215;1
"Unit";"Marine";"Barracks";216;1
"Unit";"Marine";"Barracks";219;1
"Unit";"Marine";"Barracks";219;1
"Unit";"SCV";"Command Center";223;1
"Unit";"SCV";"Command Center";223;1
"Unit";"Marine";"Barracks";223;1
"Unit";"Marine";"Barracks";224;1
"Unit";"Marine";"Barracks";225;1
"Unit";"Marine";"Barracks";226;1
"Unit";"Marine";"Barracks";227;1
"Unit";"Marine";"Barracks";227;1
"Unit";"Marine";"Barracks";227;1
"Unit";"Marine";"Barracks";227;1
"Unit";"Marine";"Barracks";231;1
"Unit";"Marine";"Barracks";231;1
"Unit";"Marine";"Barracks";231;1
"Unit";"Medivac";"Starport";228;2
"Unit";"Medivac";"Starport";229;2
"Building";"Starport";NA;227;0
"Unit";"Marine";"Barracks";239;1
"Building";"FusionCore";NA;227;0
"Building";"Refinery";NA;242;0
"Building";"Refinery";NA;242;0
"Building";"StarportTechLab";NA;246;0
"Building";"GhostAcademy";NA;247;0
"Unit";"Marine";"Barracks";247;1
"Unit";"Marine";"Barracks";247;1
"Unit";"Marine";"Barracks";247;1
"Building";"Barracks";NA;247;0
"Building";"Barracks";NA;247;0
"Unit";"Marine";"Barracks";247;1
"Unit";"Marine";"Barracks";247;1
"Unit";"Marine";"Barracks";247;1
"Unit";"Marine";"Barracks";247;1
"Unit";"Marine";"Barracks";247;1
"Unit";"Marine";"Barracks";247;1
"Unit";"Marine";"Barracks";247;1
"Unit";"Marine";"Barracks";247;1
"Building";"Barracks";NA;247;0
"Unit";"Marine";"Barracks";247;1
"Unit";"Marine";"Barracks";250;1
"Unit";"SCV";"Command Center";257;1
"Unit";"SCV";"Command Center";257;1
"Unit";"Marine";"Barracks";250;1
"Building";"CommandCenter";NA;246;0
"Unit";"Marine";"Barracks";250;1
"Unit";"Marine";"Barracks";258;1
"Unit";"Marine";"Barracks";258;1
"Unit";"Marine";"Barracks";258;1
"Unit";"Marine";"Barracks";258;1
"Unit";"Marine";"Barracks";258;1
"Building";"BarracksTechLab";NA;259;0
"Building";"BarracksTechLab";NA;259;0
"Building";"BarracksTechLab";NA;259;0
"Unit";"Marine";"Barracks";264;1
"Unit";"Marine";"Barracks";265;1
"Unit";"Marine";"Barracks";269;1
"Unit";"Marine";"Barracks";269;1
"Unit";"Marine";"Barracks";269;1
"Unit";"Marauder";"Barracks";269;2
"Unit";"Marine";"Barracks";269;1
"Unit";"Marine";"Barracks";269;1
"Unit";"Marine";"Barracks";269;1
"Unit";"Marauder";"Barracks";269;2
"Unit";"Marauder";"Barracks";269;2
"Unit";"Marine";"Barracks";271;1
"Unit";"Marine";"Barracks";271;1
"Unit";"Marine";"Barracks";271;1
"Unit";"Ghost";"Barracks";271;2
"Unit";"Marine";"Barracks";286;1
"Unit";"Marine";"Barracks";286;1
"Unit";"Marine";"Barracks";286;1
"Unit";"Ghost";"Barracks";288;2
"Unit";"Ghost";"Barracks";288;2
"Unit";"Ghost";"Barracks";288;2
"Unit";"Ghost";"Barracks";288;2
