"Type";"UnitName";"OnBuilding";"TotalSupply";"Supply"
"Unit";"SCV";"Command Center";12;1
"Unit";"SCV";"Command Center";12;1
"Unit";"SCV";"Command Center";13;1
"Building";"SupplyDepot";NA;13;0
"Unit";"SCV";"Command Center";15;1
"Unit";"SCV";"Command Center";15;1
"Building";"Refinery";NA;15;0
"Unit";"SCV";"Command Center";16;1
"Building";"Barracks";NA;15;0
"Unit";"SCV";"Command Center";17;1
"Unit";"Reaper";"Barracks";19;1
"Unit";"SCV";"Command Center";19;1
"Building";"SupplyDepot";NA;19;0
"Unit";"SCV";"Command Center";20;1
"Unit";"Marine";"Barracks";19;1
"Unit";"SCV";"Command Center";22;1
"Unit";"SCV";"Command Center";23;1
"Building";"Bunker";NA;21;0
"Building";"CommandCenter";NA;19;0
"Unit";"SCV";"Command Center";24;1
"Building";"BarracksReactor";NA;23;0
"Building";"Factory";NA;21;0
"Unit";"SCV";"Command Center";25;1
"Unit";"SCV";"Command Center";26;1
"Unit";"Hellion";"Factory";27;2
"Unit";"Hellion";"Factory";27;2
"Unit";"SCV";"Command Center";28;1
"Unit";"SCV";"Command Center";28;1
"Building";"BarracksTechLab";NA;28;0
"Unit";"SCV";"Command Center";32;1
"Unit";"SCV";"Command Center";33;1
"Building";"Starport";NA;28;0
"Unit";"SCV";"Command Center";34;1
"Building";"SupplyDepot";NA;34;0
"Unit";"SCV";"Command Center";36;1
"Building";"CommandCenter";NA;26;0
"Unit";"SCV";"Command Center";36;1
"Building";"BarracksTechLab";NA;36;0
"Unit";"Hellion";"Factory";36;2
"Unit";"Hellion";"Factory";36;2
"Unit";"SCV";"Command Center";37;1
"Unit";"SCV";"Command Center";38;1
"Building";"SupplyDepot";NA;38;0
"Unit";"SCV";"Command Center";44;1
"Building";"Refinery";NA;39;0
"Unit";"SCV";"Command Center";45;1
"Unit";"Marine";"Barracks";45;1
"Unit";"SCV";"Command Center";45;1
"Unit";"Hellion";"Factory";45;2
"Unit";"Hellion";"Factory";45;2
"Unit";"Banshee";"Starport";38;3
"Unit";"SCV";"Command Center";46;1
"Unit";"SCV";"Command Center";46;1
"Unit";"SCV";"Command Center";58;1
"Unit";"SCV";"Command Center";58;1
"Unit";"SCV";"Command Center";58;1
"Unit";"Banshee";"Starport";53;3
"Unit";"SCV";"Command Center";61;1
"Unit";"SCV";"Command Center";61;1
"Unit";"SCV";"Command Center";61;1
"Unit";"Marine";"Barracks";61;1
"Unit";"Hellion";"Factory";61;2
"Unit";"Hellion";"Factory";61;2
"Building";"EngineeringBay";NA;61;0
"Unit";"SCV";"Command Center";64;1
"Unit";"SCV";"Command Center";65;1
"Unit";"SCV";"Command Center";72;1
"Unit";"Marine";"Barracks";67;1
"Unit";"SCV";"Command Center";72;1
"Unit";"SCV";"Command Center";73;1
"Unit";"SCV";"Command Center";74;1
"Building";"EngineeringBay";NA;58;0
"Unit";"SCV";"Command Center";76;1
"Unit";"SCV";"Command Center";77;1
"Unit";"Marine";"Barracks";75;1
"Unit";"Banshee";"Starport";61;3
"Unit";"SCV";"Command Center";78;1
"Unit";"SCV";"Command Center";79;1
"Unit";"SCV";"Command Center";80;1
"Building";"SupplyDepot";NA;78;0
"Building";"SupplyDepot";NA;79;0
"Unit";"SCV";"Command Center";85;1
"Building";"Barracks";NA;72;0
"Unit";"Marine";"Barracks";81;1
"Building";"Barracks";NA;72;0
"Unit";"SCV";"Command Center";86;1
"Unit";"SCV";"Command Center";87;1
"Unit";"SCV";"Command Center";90;1
"Unit";"SCV";"Command Center";90;1
"Unit";"Marine";"Barracks";89;1
"Building";"Refinery";NA;88;0
"Unit";"Medivac";"Starport";86;2
"Building";"Refinery";NA;89;0
"Unit";"SCV";"Command Center";92;1
"Unit";"SCV";"Command Center";92;1
"Unit";"SCV";"Command Center";93;1
"Unit";"SCV";"Command Center";97;1
"Building";"BarracksReactor";NA;92;0
"Unit";"SCV";"Command Center";100;1
"Building";"BarracksReactor";NA;92;0
"Building";"SupplyDepot";NA;97;0
"Unit";"Marauder";"Barracks";97;2
"Building";"SupplyDepot";NA;97;0
"Unit";"SCV";"Command Center";101;1
"Building";"Barracks";NA;92;0
"Building";"Barracks";NA;92;0
"Building";"SupplyDepot";NA;101;0
"Unit";"SCV";"Command Center";104;1
"Unit";"SCV";"Command Center";104;1
"Unit";"Marine";"Barracks";102;1
"Unit";"Marine";"Barracks";104;1
"Unit";"Marine";"Barracks";104;1
"Unit";"Marine";"Barracks";104;1
"Upgrade";"Stimpack";"TechLab";82;0
"Unit";"SCV";"Command Center";106;1
"Unit";"SCV";"Command Center";106;1
"Building";"BarracksTechLab";NA;105;0
"Building";"StarportReactor";NA;104;0
"Unit";"Marine";"Barracks";111;1
"Building";"Armory";NA;100;0
"Unit";"Marine";"Barracks";111;1
"Unit";"Marine";"Barracks";111;1
"Unit";"Marine";"Barracks";111;1
"Upgrade";"TerranInfantryWeaponsLevel1";"EngineeringBay";90;0
"Unit";"Marauder";"Barracks";107;2
"Unit";"SCV";"Command Center";111;1
"Unit";"SCV";"Command Center";111;1
"Unit";"SCV";"Command Center";112;1
"Upgrade";"TerranInfantryArmorsLevel1";"EngineeringBay";92;0
"Building";"BarracksReactor";NA;105;0
"Building";"Barracks";NA;104;0
"Unit";"SCV";"Command Center";119;1
"Unit";"SCV";"Command Center";122;1
"Unit";"SCV";"Command Center";122;1
"Unit";"Marauder";"Barracks";113;2
"Building";"Barracks";NA;105;0
"Unit";"Marine";"Barracks";122;1
"Unit";"Marine";"Barracks";122;1
"Unit";"Marine";"Barracks";122;1
"Unit";"Marine";"Barracks";122;1
"Building";"SupplyDepot";NA;122;0
"Building";"SupplyDepot";NA;122;0
"Unit";"SCV";"Command Center";123;1
"Unit";"SCV";"Command Center";123;1
"Building";"BarracksTechLab";NA;127;0
"Building";"Refinery";NA;127;0
"Unit";"SCV";"Command Center";133;1
"Unit";"SCV";"Command Center";133;1
"Building";"Refinery";NA;127;0
"Unit";"Marine";"Barracks";133;1
"Unit";"Marine";"Barracks";133;1
"Unit";"Marine";"Barracks";133;1
"Unit";"Marine";"Barracks";133;1
"Unit";"Marauder";"Barracks";133;2
"Unit";"Marauder";"Barracks";133;2
"Unit";"SCV";"Command Center";135;1
"Unit";"SCV";"Command Center";135;1
"Unit";"SCV";"Command Center";135;1
"Unit";"Medivac";"Starport";132;2
"Building";"SupplyDepot";NA;138;0
"Building";"SupplyDepot";NA;143;0
"Unit";"Marine";"Barracks";148;1
"Unit";"SCV";"Command Center";148;1
"Unit";"SCV";"Command Center";148;1
"Unit";"SCV";"Command Center";148;1
"Unit";"Marine";"Barracks";148;1
"Unit";"Marine";"Barracks";148;1
"Unit";"Marine";"Barracks";148;1
"Unit";"Marine";"Barracks";148;1
"Unit";"Marine";"Barracks";148;1
"Unit";"Marauder";"Barracks";148;2
"Unit";"Marauder";"Barracks";148;2
"Unit";"Marauder";"Barracks";148;2
"Building";"SupplyDepot";NA;148;0
"Building";"SupplyDepot";NA;148;0
"Building";"SupplyDepot";NA;148;0
"Building";"Factory";NA;148;0
"Unit";"Marine";"Barracks";163;1
"Unit";"Marine";"Barracks";163;1
"Unit";"Marine";"Barracks";163;1
"Unit";"Marine";"Barracks";163;1
"Unit";"Marine";"Barracks";163;1
"Unit";"Marine";"Barracks";163;1
"Unit";"Marine";"Barracks";163;1
"Upgrade";"TerranVehicleAndShipArmorsLevel1";"Armory";133;0
"Unit";"Marauder";"Barracks";163;2
"Unit";"Marauder";"Barracks";163;2
"Unit";"Marauder";"Barracks";163;2
"Unit";"Medivac";"Starport";163;2
"Unit";"Medivac";"Starport";163;2
"Building";"FactoryTechLab";NA;170;0
"Unit";"Marine";"Barracks";180;1
"Unit";"Marine";"Barracks";180;1
"Upgrade";"TerranInfantryWeaponsLevel2";"EngineeringBay";139;0
"Unit";"Marine";"Barracks";180;1
"Unit";"Marine";"Barracks";180;1
"Unit";"Marine";"Barracks";180;1
"Unit";"Marine";"Barracks";180;1
"Unit";"Marauder";"Barracks";180;2
"Unit";"Marauder";"Barracks";180;2
"Unit";"Marauder";"Barracks";180;2
"Unit";"Marauder";"Barracks";180;2
"Unit";"Medivac";"Starport";180;2
"Unit";"Medivac";"Starport";180;2
"Unit";"Marine";"Barracks";184;1
"Unit";"Marine";"Barracks";185;1
"Unit";"Marine";"Barracks";185;1
"Unit";"Marauder";"Barracks";186;2
"Unit";"Marauder";"Barracks";188;2
"Unit";"Marauder";"Barracks";190;2
"Unit";"Marauder";"Barracks";192;2
"Unit";"Medivac";"Starport";194;2
"Unit";"Medivac";"Starport";196;2
"Unit";"Marine";"Barracks";201;1
"Unit";"Marine";"Barracks";201;1
"Unit";"Marine";"Barracks";201;1
"Unit";"Marine";"Barracks";201;1
"Unit";"Marine";"Barracks";201;1
"Unit";"Marine";"Barracks";201;1
"Unit";"Marine";"Barracks";205;1
"Unit";"Marine";"Barracks";207;1
"Unit";"SCV";"Command Center";209;1
"Unit";"Marauder";"Barracks";201;2
"Unit";"SCV";"Command Center";209;1
"Unit";"Marauder";"Barracks";203;2
"Unit";"SCV";"Command Center";209;1
"Unit";"Marine";"Barracks";213;1
"Unit";"Marauder";"Barracks";219;2
"Unit";"Marine";"Barracks";228;1
"Unit";"Marine";"Barracks";228;1
"Unit";"Marine";"Barracks";228;1
"Unit";"Marine";"Barracks";228;1
"Upgrade";"TerranInfantryArmorsLevel2";"EngineeringBay";176;0
"Unit";"Medivac";"Starport";209;2
"Unit";"Medivac";"Starport";211;2
"Unit";"Marauder";"Barracks";228;2
"Unit";"Marauder";"Barracks";228;2
"Unit";"Marauder";"Barracks";228;2
"Building";"SupplyDepot";NA;228;0
"Building";"SupplyDepot";NA;228;0
"Building";"SupplyDepot";NA;228;0
"Unit";"Marauder";"Barracks";229;2
"Unit";"Marine";"Barracks";245;1
"Unit";"Marine";"Barracks";245;1
"Unit";"Marine";"Barracks";245;1
"Unit";"Marine";"Barracks";245;1
"Unit";"Marine";"Barracks";245;1
"Unit";"Marine";"Barracks";245;1
"Unit";"Marine";"Barracks";245;1
"Unit";"Marine";"Barracks";245;1
"Unit";"Marine";"Barracks";245;1
"Unit";"Marine";"Barracks";245;1
"Unit";"Marine";"Barracks";247;1
"Building";"CommandCenter";NA;228;0
"Unit";"Medivac";"Starport";247;2
"Unit";"Medivac";"Starport";247;2
"Unit";"Marine";"Barracks";257;1
"Unit";"Marine";"Barracks";257;1
"Unit";"Marine";"Barracks";257;1
"Unit";"Marine";"Barracks";257;1
"Unit";"Marine";"Barracks";257;1
"Unit";"Marine";"Barracks";257;1
"Unit";"Marauder";"Barracks";257;2
"Unit";"Marauder";"Barracks";257;2
"Unit";"Marauder";"Barracks";257;2
"Unit";"Marauder";"Barracks";257;2
