"Type";"UnitName";"OnBuilding";"TotalSupply";"Supply"
"Unit";"SCV";"Command Center";12;1
"Unit";"SCV";"Command Center";13;1
"Unit";"SCV";"Command Center";13;1
"Building";"SupplyDepot";NA;13;0
"Unit";"SCV";"Command Center";15;1
"Building";"Refinery";NA;14;0
"Unit";"SCV";"Command Center";16;1
"Unit";"SCV";"Command Center";16;1
"Building";"Barracks";NA;15;0
"Unit";"SCV";"Command Center";17;1
"Unit";"Reaper";"Barracks";18;1
"Unit";"SCV";"Command Center";19;1
"Building";"Refinery";NA;21;0
"Unit";"SCV";"Command Center";21;1
"Building";"SupplyDepot";NA;21;0
"Building";"Factory";NA;19;0
"Building";"BarracksReactor";NA;20;0
"Unit";"SCV";"Command Center";22;1
"Building";"CommandCenter";NA;19;0
"Unit";"SCV";"Command Center";22;1
"Unit";"SCV";"Command Center";23;1
"Unit";"Hellion";"Factory";23;2
"Unit";"Hellion";"Factory";23;2
"Unit";"SCV";"Command Center";24;1
"Building";"BarracksReactor";NA;23;0
"Building";"Factory";NA;23;0
"Unit";"SCV";"Command Center";29;1
"Unit";"SCV";"Command Center";29;1
"Unit";"Hellion";"Factory";25;2
"Unit";"Hellion";"Factory";27;2
"Unit";"SCV";"Command Center";30;1
"Unit";"SCV";"Command Center";31;1
"Building";"SupplyDepot";NA;30;0
"Unit";"SCV";"Command Center";36;1
"Unit";"SCV";"Command Center";38;1
"Unit";"SCV";"Command Center";38;1
"Unit";"SCV";"Command Center";39;1
"Unit";"Hellion";"Factory";38;2
"Unit";"Hellion";"Factory";38;2
"Unit";"Cyclone";"Factory";38;3
"Unit";"Cyclone";"Factory";38;3
"Building";"SupplyDepot";NA;40;0
"Unit";"Hellion";"Factory";42;2
"Unit";"SCV";"Command Center";52;1
"Unit";"SCV";"Command Center";52;1
"Unit";"Hellion";"Factory";52;2
"Unit";"Hellion";"Factory";52;2
"Unit";"Hellion";"Factory";52;2
"Building";"Armory";NA;40;0
"Unit";"Hellion";"Factory";52;2
"Unit";"SCV";"Command Center";54;1
"Unit";"SCV";"Command Center";55;1
"Building";"SupplyDepot";NA;54;0
"Unit";"SCV";"Command Center";64;1
"Unit";"SCV";"Command Center";65;1
"Unit";"Cyclone";"Factory";66;3
"Unit";"SCV";"Command Center";66;1
"Unit";"SCV";"Command Center";67;1
"Building";"SupplyDepot";NA;66;0
"Unit";"SCV";"Command Center";71;1
"Unit";"Cyclone";"Factory";68;3
"Unit";"Cyclone";"Factory";68;3
"Unit";"Hellion";"Factory";73;2
"Unit";"SCV";"Command Center";73;1
"Unit";"SCV";"Command Center";73;1
"Unit";"Cyclone";"Factory";73;3
"Unit";"Hellion";"Factory";74;2
"Unit";"SCV";"Command Center";82;1
"Unit";"SCV";"Command Center";84;1
"Unit";"Hellion";"Factory";83;2
"Unit";"Hellion";"Factory";83;2
"Unit";"SCV";"Command Center";91;1
"Unit";"SCV";"Command Center";91;1
"Unit";"Hellion";"Factory";91;2
"Building";"Refinery";NA;91;0
"Building";"Factory";NA;80;0
"Building";"Factory";NA;80;0
"Unit";"SCV";"Command Center";95;1
"Unit";"SCV";"Command Center";96;1
"Building";"FactoryTechLab";NA;95;0
"Building";"Refinery";NA;97;0
"Unit";"SCV";"Command Center";99;1
"Building";"FactoryTechLab";NA;99;0
"Building";"FactoryTechLab";NA;100;0
"Unit";"SCV";"Command Center";101;1
"Unit";"SCV";"Command Center";101;1
"Building";"Starport";NA;99;0
"Unit";"Hellion";"Factory";102;2
"Building";"CommandCenter";NA;91;0
"Unit";"SCV";"Command Center";106;1
"Unit";"SCV";"Command Center";106;1
"Building";"SupplyDepot";NA;106;0
"Unit";"SCV";"Command Center";106;1
"Unit";"SCV";"Command Center";106;1
"Building";"SupplyDepot";NA;106;0
"Building";"SupplyDepot";NA;106;0
"Unit";"SCV";"Command Center";108;1
"Unit";"SCV";"Command Center";108;1
"Upgrade";"TerranVehicleWeaponsLevel1";"Armory";102;0
"Unit";"Hellion";"Factory";110;2
"Unit";"Hellion";"Factory";110;2
"Unit";"Hellion";"Factory";116;2
"Unit";"Hellion";"Factory";116;2
"Unit";"SCV";"Command Center";120;1
"Unit";"SCV";"Command Center";120;1
"Unit";"SCV";"Command Center";120;1
"Unit";"Cyclone";"Factory";120;3
"Unit";"SCV";"Command Center";121;1
"Unit";"Thor";"Factory";116;6
"Building";"Refinery";NA;120;0
"Building";"Refinery";NA;121;0
"Unit";"SCV";"Command Center";133;1
"Unit";"Hellion";"Factory";133;2
"Building";"SupplyDepot";NA;134;0
"Building";"SupplyDepot";NA;134;0
"Unit";"SCV";"Command Center";136;1
"Upgrade";"TerranVehicleWeaponsLevel2";"Armory";120;0
"Building";"SupplyDepot";NA;136;0
"Building";"SupplyDepot";NA;136;0
"Building";"SupplyDepot";NA;136;0
"Building";"SupplyDepot";NA;136;0
"Building";"SupplyDepot";NA;136;0
"Building";"SupplyDepot";NA;136;0
"Unit";"SCV";"Command Center";137;1
"Unit";"SCV";"Command Center";137;1
"Unit";"SCV";"Command Center";137;1
"Unit";"Thor";"Factory";136;6
"Unit";"Thor";"Factory";136;6
"Unit";"Hellion";"Factory";137;2
"Unit";"Hellion";"Factory";137;2
"Building";"SupplyDepot";NA;137;0
"Unit";"Medivac";"Starport";137;2
"Unit";"Medivac";"Starport";137;2
"Unit";"SCV";"Command Center";146;1
"Unit";"Hellion";"Factory";152;2
"Unit";"SCV";"Command Center";160;1
"Building";"CommandCenter";NA;136;0
"Unit";"Hellion";"Factory";161;2
"Building";"Factory";NA;140;0
"Building";"EngineeringBay";NA;161;0
"Building";"Starport";NA;156;0
"Unit";"Hellion";"Factory";161;2
"Building";"Armory";NA;140;0
"Unit";"Hellion";"Factory";164;2
"Building";"FactoryTechLab";NA;166;0
"Building";"CommandCenter";NA;156;0
"Unit";"Thor";"Factory";164;6
"Unit";"Hellion";"Factory";170;2
"Unit";"Hellion";"Factory";170;2
"Building";"StarportTechLab";NA;170;0
"Building";"CommandCenter";NA;160;0
"Unit";"SCV";"Command Center";170;1
"Building";"Refinery";NA;181;0
"Building";"Refinery";NA;181;0
"Building";"CommandCenter";NA;168;0
"Unit";"Hellion";"Factory";181;2
"Unit";"Hellion";"Factory";181;2
"Unit";"Hellion";"Factory";181;2
"Unit";"Hellion";"Factory";181;2
"Unit";"Raven";"Starport";181;2
"Building";"SensorTower";NA;187;0
"Upgrade";"TerranVehicleWeaponsLevel3";"Armory";166;0
"Unit";"Hellion";"Factory";187;2
"Building";"MissileTurret";NA;191;0
"Building";"MissileTurret";NA;193;0
"Upgrade";"TerranVehicleAndShipArmorsLevel1";"Armory";181;0
"Unit";"Hellion";"Factory";193;2
"Unit";"Hellion";"Factory";193;2
"Unit";"SCV";"Command Center";193;1
"Unit";"SCV";"Command Center";193;1
"Unit";"Cyclone";"Factory";193;3
"Unit";"Cyclone";"Factory";193;3
"Unit";"Cyclone";"Factory";193;3
"Unit";"Hellion";"Factory";193;2
"Unit";"Hellion";"Factory";195;2
"Unit";"SCV";"Command Center";208;1
"Building";"CommandCenter";NA;193;0
"Building";"Factory";NA;199;0
"Unit";"Hellion";"Factory";212;2
"Unit";"Hellion";"Factory";213;2
"Unit";"Hellion";"Factory";213;2
"Unit";"Hellion";"Factory";213;2
"Building";"Factory";NA;199;0
"Building";"CommandCenter";NA;193;0
"Building";"FactoryTechLab";NA;221;0
"Unit";"Thor";"Factory";212;6
"Unit";"Thor";"Factory";212;6
"Unit";"Hellion";"Factory";213;2
"Unit";"Hellion";"Factory";215;2
"Unit";"Hellion";"Factory";217;2
"Building";"FactoryTechLab";NA;221;0
"Upgrade";"TerranShipWeaponsLevel1";"Armory";193;0
"Upgrade";"TerranVehicleAndShipArmorsLevel2";"Armory";213;0
"Building";"Starport";NA;239;0
"Building";"Starport";NA;239;0
"Unit";"Hellion";"Factory";239;2
"Unit";"Hellion";"Factory";239;2
"Unit";"Hellion";"Factory";239;2
"Unit";"Hellion";"Factory";239;2
