"Type";"UnitName";"OnBuilding";"TotalSupply";"Supply"
"Unit";"SCV";"Command Center";12;1
"Unit";"SCV";"Command Center";12;1
"Unit";"SCV";"Command Center";13;1
"Building";"SupplyDepot";NA;13;0
"Building";"Refinery";NA;14;0
"Unit";"SCV";"Command Center";15;1
"Unit";"SCV";"Command Center";16;1
"Unit";"SCV";"Command Center";16;1
"Unit";"SCV";"Command Center";17;1
"Building";"Barracks";NA;15;0
"Unit";"SCV";"Command Center";18;1
"Unit";"Reaper";"Barracks";19;1
"Unit";"SCV";"Command Center";21;1
"Building";"SupplyDepot";NA;21;0
"Unit";"SCV";"Command Center";21;1
"Building";"BarracksReactor";NA;21;0
"Building";"CommandCenter";NA;19;0
"Unit";"SCV";"Command Center";22;1
"Unit";"SCV";"Command Center";23;1
"Building";"Refinery";NA;23;0
"Unit";"Marine";"Barracks";24;1
"Unit";"Marine";"Barracks";24;1
"Building";"Factory";NA;22;0
"Unit";"SCV";"Command Center";24;1
"Unit";"SCV";"Command Center";28;1
"Unit";"SCV";"Command Center";28;1
"Unit";"Hellion";"Factory";28;2
"Unit";"Hellion";"Factory";28;2
"Building";"BarracksTechLab";NA;28;0
"Unit";"SCV";"Command Center";28;1
"Unit";"SCV";"Command Center";30;1
"Building";"SupplyDepot";NA;30;0
"Unit";"SCV";"Command Center";35;1
"Unit";"SCV";"Command Center";36;1
"Unit";"Hellion";"Factory";35;2
"Unit";"Hellion";"Factory";35;2
"Building";"SupplyDepot";NA;36;0
"Unit";"SCV";"Command Center";42;1
"Unit";"SCV";"Command Center";42;1
"Unit";"SCV";"Command Center";42;1
"Unit";"SCV";"Command Center";43;1
"Unit";"SCV";"Command Center";44;1
"Unit";"SCV";"Command Center";45;1
"Unit";"SCV";"Command Center";46;1
"Building";"CommandCenter";NA;35;0
"Building";"FactoryReactor";NA;44;0
"Unit";"SCV";"Command Center";47;1
"Unit";"Marine";"Barracks";47;1
"Unit";"SCV";"Command Center";48;1
"Unit";"SCV";"Command Center";49;1
"Building";"Barracks";NA;44;0
"Building";"Barracks";NA;44;0
"Unit";"SCV";"Command Center";51;1
"Unit";"Marine";"Barracks";51;1
"Unit";"SCV";"Command Center";52;1
"Unit";"SCV";"Command Center";53;1
"Building";"FactoryTechLab";NA;53;0
"Building";"SupplyDepot";NA;52;0
"Unit";"Marine";"Barracks";53;1
"Unit";"Marine";"Barracks";53;1
"Unit";"SCV";"Command Center";55;1
"Unit";"SCV";"Command Center";56;1
"Unit";"SCV";"Command Center";56;1
"Unit";"Marauder";"Barracks";54;2
"Unit";"Marine";"Barracks";56;1
"Unit";"Marine";"Barracks";56;1
"Building";"Refinery";NA;56;0
"Building";"Refinery";NA;56;0
"Unit";"SCV";"Command Center";59;1
"Unit";"Marine";"Barracks";57;1
"Unit";"Marine";"Barracks";59;1
"Upgrade";"Stimpack";"TechLab";44;0
"Building";"Starport";NA;53;0
"Building";"Bunker";NA;56;0
"Unit";"SCV";"Command Center";65;1
"Unit";"SCV";"Command Center";66;1
"Building";"EngineeringBay";NA;59;0
"Building";"EngineeringBay";NA;59;0
"Unit";"SCV";"Command Center";68;1
"Unit";"SCV";"Command Center";69;1
"Unit";"Marine";"Barracks";67;1
"Unit";"Marine";"Barracks";67;1
"Unit";"Marauder";"Barracks";66;2
"Unit";"SCV";"Command Center";71;1
"Unit";"Marine";"Barracks";78;1
"Unit";"Marine";"Barracks";78;1
"Unit";"Marine";"Barracks";78;1
"Unit";"Marine";"Barracks";78;1
"Unit";"Marine";"Barracks";78;1
"Building";"StarportReactor";NA;71;0
"Building";"SupplyDepot";NA;78;0
"Building";"SupplyDepot";NA;78;0
"Building";"SupplyDepot";NA;78;0
"Building";"SupplyDepot";NA;78;0
"Unit";"SCV";"Command Center";83;1
"Unit";"SCV";"Command Center";83;1
"Unit";"Marine";"Barracks";83;1
"Unit";"Marine";"Barracks";83;1
"Unit";"Marine";"Barracks";83;1
"Unit";"Marine";"Barracks";83;1
"Unit";"Marauder";"Barracks";83;2
"Unit";"SCV";"Command Center";83;1
"Unit";"SCV";"Command Center";84;1
"Unit";"Marine";"Barracks";85;1
"Unit";"Marine";"Barracks";85;1
"Unit";"SCV";"Command Center";91;1
"Unit";"Marine";"Barracks";89;1
"Unit";"Medivac";"Starport";83;2
"Unit";"Medivac";"Starport";83;2
"Building";"SupplyDepot";NA;89;0
"Building";"SupplyDepot";NA;89;0
"Building";"Barracks";NA;83;0
"Building";"SupplyDepot";NA;93;0
"Building";"Barracks";NA;83;0
"Unit";"Marine";"Barracks";93;1
"Building";"SupplyDepot";NA;93;0
"Unit";"Marauder";"Barracks";93;2
"Unit";"SCV";"Command Center";101;1
"Unit";"SCV";"Command Center";101;1
"Unit";"Marine";"Barracks";101;1
"Unit";"Marine";"Barracks";101;1
"Unit";"Marine";"Barracks";101;1
"Unit";"SCV";"Command Center";104;1
"Unit";"Marine";"Barracks";104;1
"Unit";"Marine";"Barracks";104;1
"Unit";"SCV";"Command Center";109;1
"Unit";"SCV";"Command Center";109;1
"Building";"SupplyDepot";NA;107;0
"Unit";"Marine";"Barracks";110;1
"Building";"SupplyDepot";NA;109;0
"Unit";"Marine";"Barracks";110;1
"Unit";"Marine";"Barracks";110;1
"Unit";"Medivac";"Starport";106;2
"Unit";"Medivac";"Starport";106;2
"Unit";"SCV";"Command Center";114;1
"Unit";"Marine";"Barracks";112;1
"Unit";"Marine";"Barracks";112;1
"Building";"BarracksReactor";NA;106;0
"Building";"BarracksReactor";NA;106;0
"Unit";"Marine";"Barracks";114;1
"Unit";"Marine";"Barracks";121;1
"Unit";"Marine";"Barracks";122;1
"Unit";"Marine";"Barracks";122;1
"Unit";"Marauder";"Barracks";123;2
"Unit";"Marine";"Barracks";124;1
"Unit";"Marine";"Barracks";124;1
"Unit";"Marine";"Barracks";124;1
"Unit";"Marine";"Barracks";124;1
"Unit";"Marine";"Barracks";124;1
"Upgrade";"TerranInfantryWeaponsLevel1";"EngineeringBay";101;0
"Upgrade";"TerranInfantryArmorsLevel1";"EngineeringBay";101;0
"Unit";"Marine";"Barracks";125;1
"Unit";"Marine";"Barracks";126;1
"Unit";"Marine";"Barracks";127;1
"Unit";"Marine";"Barracks";128;1
"Unit";"Medivac";"Starport";128;2
"Unit";"Medivac";"Starport";128;2
"Unit";"Marine";"Barracks";135;1
"Unit";"Marine";"Barracks";135;1
"Unit";"Marine";"Barracks";135;1
"Unit";"Marine";"Barracks";135;1
"Unit";"Marine";"Barracks";135;1
"Building";"SupplyDepot";NA;139;0
"Building";"SupplyDepot";NA;139;0
"Building";"SupplyDepot";NA;148;0
"Unit";"SCV";"Command Center";148;1
"Building";"SupplyDepot";NA;148;0
"Building";"Refinery";NA;148;0
"Building";"Refinery";NA;148;0
"Unit";"Marine";"Barracks";148;1
"Unit";"Marine";"Barracks";148;1
"Unit";"Marine";"Barracks";148;1
"Unit";"Marine";"Barracks";148;1
"Unit";"Marine";"Barracks";148;1
"Unit";"Marine";"Barracks";148;1
"Unit";"Marine";"Barracks";148;1
"Unit";"Medivac";"Starport";148;2
"Unit";"Medivac";"Starport";148;2
"Unit";"Marine";"Barracks";149;1
"Unit";"Marine";"Barracks";149;1
"Unit";"Marine";"Barracks";149;1
"Unit";"Marine";"Barracks";149;1
"Unit";"Marine";"Barracks";151;1
"Unit";"Marine";"Barracks";151;1
"Building";"Armory";NA;148;0
"Unit";"Marine";"Barracks";156;1
"Unit";"Marine";"Barracks";156;1
"Unit";"Marine";"Barracks";156;1
"Unit";"Marine";"Barracks";160;1
"Unit";"Marine";"Barracks";162;1
"Unit";"Marine";"Barracks";162;1
"Unit";"Marine";"Barracks";164;1
"Unit";"Marine";"Barracks";166;1
"Unit";"Marauder";"Barracks";161;2
"Unit";"Marine";"Barracks";166;1
"Unit";"Marine";"Barracks";167;1
"Unit";"Medivac";"Starport";156;2
"Unit";"Medivac";"Starport";158;2
"Building";"SupplyDepot";NA;169;0
"Building";"SupplyDepot";NA;169;0
"Building";"SupplyDepot";NA;169;0
"Unit";"Marine";"Barracks";182;1
"Unit";"Marine";"Barracks";182;1
"Unit";"Marine";"Barracks";182;1
"Unit";"Marine";"Barracks";182;1
"Unit";"Marine";"Barracks";182;1
"Unit";"Marine";"Barracks";182;1
"Unit";"Marine";"Barracks";182;1
"Unit";"Marine";"Barracks";182;1
"Unit";"Marine";"Barracks";182;1
"Unit";"Medivac";"Starport";182;2
"Unit";"Medivac";"Starport";182;2
"Unit";"Marine";"Barracks";182;1
"Unit";"Marine";"Barracks";183;1
"Unit";"Marine";"Barracks";183;1
"Unit";"Marauder";"Barracks";189;2
"Unit";"Marine";"Barracks";191;1
"Unit";"Marine";"Barracks";191;1
"Unit";"Marine";"Barracks";191;1
"Unit";"Marine";"Barracks";191;1
"Building";"CommandCenter";NA;170;0
"Unit";"Marine";"Barracks";195;1
"Unit";"Marine";"Barracks";195;1
"Unit";"Marine";"Barracks";196;1
"Unit";"Marine";"Barracks";196;1
"Unit";"Marauder";"Barracks";198;2
"Unit";"Marine";"Barracks";200;1
"Unit";"Marine";"Barracks";201;1
"Unit";"Marine";"Barracks";202;1
"Unit";"Marine";"Barracks";203;1
"Unit";"Marine";"Barracks";204;1
"Unit";"Marine";"Barracks";205;1
"Unit";"Marine";"Barracks";206;1
"Unit";"Marine";"Barracks";208;1
"Unit";"Marine";"Barracks";208;1
"Building";"Barracks";NA;200;0
"Unit";"Marine";"Barracks";218;1
"Unit";"Marine";"Barracks";218;1
"Unit";"Marine";"Barracks";218;1
"Unit";"Marine";"Barracks";218;1
"Unit";"Marine";"Barracks";218;1
"Unit";"Marine";"Barracks";218;1
"Unit";"Marine";"Barracks";218;1
"Unit";"Marine";"Barracks";218;1
"Unit";"Marine";"Barracks";218;1
"Upgrade";"TerranInfantryWeaponsLevel2";"EngineeringBay";182;0
"Upgrade";"TerranInfantryArmorsLevel2";"EngineeringBay";182;0
"Unit";"Marine";"Barracks";219;1
"Unit";"Marine";"Barracks";220;1
"Unit";"Marine";"Barracks";220;1
"Unit";"Marine";"Barracks";222;1
"Unit";"Marine";"Barracks";222;1
"Unit";"Marine";"Barracks";224;1
"Unit";"Marauder";"Barracks";227;2
"Unit";"Marine";"Barracks";228;1
"Unit";"Marine";"Barracks";228;1
"Unit";"Marine";"Barracks";228;1
"Unit";"Marine";"Barracks";229;1
"Unit";"Marine";"Barracks";229;1
"Unit";"Marine";"Barracks";231;1
"Unit";"Marine";"Barracks";231;1
"Unit";"Marine";"Barracks";233;1
"Unit";"Marine";"Barracks";236;1
"Unit";"Marine";"Barracks";237;1
"Unit";"Marauder";"Barracks";234;2
"Unit";"Marine";"Barracks";244;1
"Unit";"Marine";"Barracks";244;1
"Unit";"Marine";"Barracks";244;1
"Unit";"Marine";"Barracks";244;1
"Unit";"Marine";"Barracks";244;1
"Unit";"Marine";"Barracks";244;1
"Unit";"Marine";"Barracks";244;1
"Unit";"Marine";"Barracks";245;1
"Unit";"Marine";"Barracks";246;1
"Building";"BarracksReactor";NA;238;0
"Building";"Barracks";NA;238;0
"Unit";"Marine";"Barracks";248;1
"Unit";"Marine";"Barracks";249;1
"Unit";"Marine";"Barracks";254;1
"Unit";"Marine";"Barracks";254;1
"Unit";"Marine";"Barracks";254;1
"Unit";"Marine";"Barracks";254;1
"Building";"Barracks";NA;238;0
"Unit";"Marine";"Barracks";254;1
"Unit";"Marine";"Barracks";255;1
"Unit";"Marauder";"Barracks";256;2
"Unit";"Marine";"Barracks";257;1
"Unit";"Marine";"Barracks";257;1
"Unit";"Marine";"Barracks";257;1
"Unit";"Marine";"Barracks";258;1
"Unit";"Marine";"Barracks";259;1
"Unit";"Marine";"Barracks";260;1
"Unit";"SCV";"Command Center";265;1
"Unit";"SCV";"Command Center";265;1
"Unit";"SCV";"Command Center";265;1
"Building";"BarracksTechLab";NA;265;0
"Building";"BarracksTechLab";NA;265;0
"Unit";"Marine";"Barracks";265;1
"Unit";"Marine";"Barracks";265;1
"Unit";"SCV";"Command Center";273;1
"Unit";"SCV";"Command Center";274;1
"Unit";"SCV";"Command Center";274;1
"Unit";"Marine";"Barracks";271;1
"Unit";"Marine";"Barracks";271;1
"Unit";"Marine";"Barracks";271;1
"Unit";"Marine";"Barracks";271;1
"Unit";"Marine";"Barracks";272;1
"Unit";"Marine";"Barracks";272;1
"Unit";"Marauder";"Barracks";270;2
"Unit";"SCV";"Command Center";278;1
"Unit";"SCV";"Command Center";279;1
"Unit";"SCV";"Command Center";279;1
"Unit";"Medivac";"Starport";276;2
"Unit";"Medivac";"Starport";276;2
"Building";"Barracks";NA;265;0
"Unit";"SCV";"Command Center";289;1
"Unit";"SCV";"Command Center";290;1
"Unit";"Marine";"Barracks";287;1
"Unit";"Marine";"Barracks";289;1
"Unit";"Marine";"Barracks";289;1
"Unit";"Marine";"Barracks";289;1
"Unit";"Marine";"Barracks";289;1
"Unit";"Marine";"Barracks";289;1
"Unit";"Marine";"Barracks";289;1
"Unit";"Marine";"Barracks";289;1
"Unit";"Marauder";"Barracks";289;2
"Unit";"Marauder";"Barracks";289;2
"Unit";"Marauder";"Barracks";289;2
"Unit";"Marine";"Barracks";292;1
"Unit";"Marine";"Barracks";292;1
"Unit";"Marine";"Barracks";298;1
"Unit";"Marine";"Barracks";302;1
"Unit";"Marine";"Barracks";306;1
"Unit";"Marine";"Barracks";306;1
"Unit";"Marine";"Barracks";306;1
"Unit";"Marine";"Barracks";306;1
"Unit";"Marauder";"Barracks";306;2
"Unit";"Marauder";"Barracks";308;2
"Unit";"Marauder";"Barracks";310;2
"Unit";"Marine";"Barracks";320;1
"Unit";"Marine";"Barracks";320;1
"Unit";"Marine";"Barracks";320;1
"Unit";"Marine";"Barracks";320;1
"Unit";"Marine";"Barracks";320;1
"Unit";"Marine";"Barracks";320;1
"Unit";"Marine";"Barracks";320;1
"Unit";"Marine";"Barracks";320;1
"Unit";"Marine";"Barracks";320;1
"Unit";"Marine";"Barracks";320;1
"Unit";"Marine";"Barracks";324;1
"Unit";"Marauder";"Barracks";320;2
"Unit";"Marauder";"Barracks";322;2
"Unit";"Medivac";"Starport";324;2
"Unit";"Medivac";"Starport";324;2
"Unit";"Marine";"Barracks";326;1
"Unit";"Marine";"Barracks";327;1
"Unit";"Marine";"Barracks";328;1
"Unit";"Marine";"Barracks";328;1
"Unit";"Marine";"Barracks";330;1
"Unit";"Marine";"Barracks";330;1
"Unit";"Marine";"Barracks";345;1
"Unit";"Marine";"Barracks";345;1
"Unit";"Marine";"Barracks";345;1
"Unit";"Marine";"Barracks";345;1
"Unit";"Marine";"Barracks";345;1
"Unit";"Marine";"Barracks";345;1
"Unit";"Marine";"Barracks";345;1
"Unit";"Marine";"Barracks";345;1
"Building";"SupplyDepot";NA;345;0
"Building";"SupplyDepot";NA;345;0
"Building";"SupplyDepot";NA;345;0
"Building";"SupplyDepot";NA;351;0
"Building";"SupplyDepot";NA;351;0
"Upgrade";"TerranInfantryWeaponsLevel3";"EngineeringBay";278;0
"Upgrade";"TerranInfantryArmorsLevel3";"EngineeringBay";278;0
"Building";"SupplyDepot";NA;351;0
"Unit";"Medivac";"Starport";341;2
"Unit";"Medivac";"Starport";343;2
