"type";"unit_name";"on_building";"total_supply_lag";"supply"
"Building";"Refinery";NA;15;0
"Building";"Barracks";NA;16;0
"Unit";"Marine";"Barracks";19;1
"Building";"CommandCenter";NA;20;0
"Building";"BarracksReactor";NA;20;0
"Building";"Factory";NA;21;0
"Unit";"Marine";"Barracks";23;1
"Unit";"Reaper";"Barracks";24;1
"Building";"CommandCenter";NA;26;0
"Unit";"Marine";"Barracks";27;1
"Unit";"Marine";"Barracks";28;1
"Unit";"Marine";"Barracks";30;1
"Unit";"Marine";"Barracks";33;1
"Unit";"Marine";"Barracks";35;1
"Unit";"Marine";"Barracks";37;1
"Unit";"Marine";"Barracks";39;1
"Unit";"Marine";"Barracks";42;1
"Unit";"Marine";"Barracks";45;1
"Unit";"Marine";"Barracks";47;1
"Building";"Starport";NA;49;0
"Unit";"Marine";"Barracks";49;1
"Unit";"Marine";"Barracks";53;1
"Unit";"Marine";"Barracks";56;1
"Unit";"Marine";"Barracks";58;1
"Building";"Barracks";NA;61;0
"Building";"Barracks";NA;62;0
"Unit";"Medivac";"Starport";65;2
"Building";"Refinery";NA;67;0
"Unit";"Marine";"Barracks";67;1
"Unit";"Marine";"Barracks";68;1
"Building";"EngineeringBay";NA;69;0
"Unit";"Liberator";"Starport";73;3
"Building";"BarracksTechLab";NA;76;0
"Building";"BarracksTechLab";NA;76;0
"Unit";"Marine";"Barracks";79;1
"Unit";"Marine";"Barracks";80;1
"Building";"FactoryReactor";NA;81;0
"Building";"Refinery";NA;81;0
"Building";"Refinery";NA;81;0
"Building";"Barracks";NA;82;0
"Building";"Barracks";NA;82;0
"Unit";"Marauder";"Barracks";85;2
"Building";"MissileTurret";NA;87;0
"Unit";"Marine";"Barracks";89;1
"Unit";"Marine";"Barracks";90;1
"Unit";"Marauder";"Barracks";91;2
"Unit";"Marauder";"Barracks";94;2
"Unit";"Marine";"Barracks";96;1
"Unit";"Marine";"Barracks";97;1
"Upgrade";"TerranInfantryWeaponsLevel1";"EngineeringBay";100;0
"Building";"BarracksTechLab";NA;100;0
"Building";"BarracksReactor";NA;100;0
"Unit";"Medivac";"Starport";100;2
"Unit";"Marauder";"Barracks";103;2
"Unit";"Medivac";"Starport";105;2
"Unit";"Marine";"Barracks";107;1
"Unit";"Marine";"Barracks";108;1
"Upgrade";"Stimpack";"TechLab";110;0
"Unit";"Medivac";"Starport";112;2
"Building";"MissileTurret";NA;114;0
"Unit";"Marauder";"Barracks";114;2
"Unit";"Marine";"Barracks";116;1
"Unit";"Marine";"Barracks";117;1
"Unit";"Marine";"Barracks";118;1
"Unit";"Marine";"Barracks";119;1
"Unit";"Marauder";"Barracks";120;2
"Unit";"Marauder";"Barracks";122;2
"Unit";"Medivac";"Starport";124;2
"Unit";"Marine";"Barracks";129;1
"Unit";"Marauder";"Barracks";130;2
"Unit";"Marauder";"Barracks";132;2
"Building";"Refinery";NA;137;0
"Unit";"Marauder";"Barracks";137;2
"Unit";"Marine";"Barracks";139;1
"Unit";"Marine";"Barracks";140;1
"Building";"Armory";NA;141;0
"Building";"EngineeringBay";NA;141;0
"Unit";"Marine";"Barracks";141;1
"Unit";"Marine";"Barracks";142;1
"Unit";"Marauder";"Barracks";143;2
"Unit";"Marauder";"Barracks";145;2
"Unit";"Marine";"Barracks";147;1
"Unit";"Marine";"Barracks";148;1
"Unit";"Marine";"Barracks";149;1
"Building";"FactoryReactor";NA;150;0
"Building";"Starport";NA;150;0
"Unit";"Marauder";"Barracks";150;2
"Unit";"Marine";"Barracks";152;1
"Unit";"Marauder";"Barracks";153;2
"Unit";"Marauder";"Barracks";155;2
"Unit";"Marine";"Barracks";157;1
"Unit";"Marine";"Barracks";158;1
"Unit";"Medivac";"Starport";159;2
"Unit";"Medivac";"Starport";161;2
"Unit";"Marine";"Barracks";163;1
"Unit";"Marine";"Barracks";167;1
"Unit";"Marauder";"Barracks";168;2
"Unit";"Marauder";"Barracks";170;2
"Unit";"Marine";"Barracks";172;1
"Unit";"Marine";"Barracks";173;1
"Unit";"Marine";"Barracks";174;1
"Unit";"Marine";"Barracks";175;1
"Unit";"Marauder";"Barracks";179;2
"Unit";"Marine";"Barracks";181;1
"Unit";"Marauder";"Barracks";182;2
"Unit";"Marine";"Barracks";184;1
"Unit";"Marauder";"Barracks";185;2
"Unit";"Marine";"Barracks";187;1
"Unit";"Marauder";"Barracks";190;2
"Unit";"Marine";"Barracks";195;1
"Unit";"Marauder";"Barracks";196;2
"Unit";"Marauder";"Barracks";198;2
"Unit";"Marine";"Barracks";200;1
"Unit";"Marine";"Barracks";201;1
"Unit";"Marine";"Barracks";202;1
"Unit";"Marine";"Barracks";206;1
"Unit";"Marine";"Barracks";207;1
"Unit";"Marauder";"Barracks";209;2
"Unit";"Marine";"Barracks";211;1
"Unit";"Marine";"Barracks";212;1
"Unit";"Marine";"Barracks";213;1
"Unit";"Marauder";"Barracks";214;2
"Building";"CommandCenter";NA;216;0
"Unit";"Marine";"Barracks";216;1
"Unit";"Marine";"Barracks";217;1
"Building";"MissileTurret";NA;218;0
"Building";"MissileTurret";NA;218;0
"Unit";"Medivac";"Starport";218;2
"Unit";"Marauder";"Barracks";220;2
"Unit";"Marine";"Barracks";222;1
"Building";"Refinery";NA;223;0
"Unit";"Marauder";"Barracks";226;2
"Unit";"Marine";"Barracks";228;1
"Unit";"Marine";"Barracks";229;1
"Unit";"Marauder";"Barracks";230;2
"Unit";"Marine";"Barracks";232;1
"Unit";"Marine";"Barracks";233;1
"Unit";"Marauder";"Barracks";234;2
"Unit";"Marine";"Barracks";236;1
"Unit";"Medivac";"Starport";237;2
"Unit";"Marine";"Barracks";239;1
"Unit";"Medivac";"Starport";240;2
"Unit";"Marauder";"Barracks";242;2
"Unit";"Marauder";"Barracks";244;2
"Unit";"Marine";"Barracks";246;1
"Unit";"Marine";"Barracks";247;1
"Unit";"Marauder";"Barracks";248;2
"Unit";"Marauder";"Barracks";253;2
"Unit";"Marauder";"Barracks";255;2
"Unit";"Marine";"Barracks";257;1
"Unit";"Marine";"Barracks";258;1
"Unit";"Marine";"Barracks";260;1
"Unit";"Marauder";"Barracks";261;2
"Unit";"Marauder";"Barracks";263;2
"Unit";"Marauder";"Barracks";265;2
"Unit";"Marine";"Barracks";267;1
"Unit";"Marine";"Barracks";268;1
"Unit";"Marine";"Barracks";269;1
"Upgrade";"SprayTerran";NA;270;0
"Upgrade";"SprayTerran";NA;270;0
"Upgrade";"SprayTerran";NA;270;0
"Upgrade";"SprayTerran";NA;270;0
"Upgrade";"ShieldWall";NA;270;0
"Upgrade";"PunisherGrenades";NA;270;0
"Upgrade";"SprayTerran";NA;270;0
"Upgrade";"SprayTerran";NA;270;0
