"type";"unit_name";"on_building";"total_supply_lag";"supply"
"Unit";"Overlord";"Larva";13;0
"Building";"Extractor";NA;17;0
"Building";"SpawningPool";NA;18;0
"Building";"Hatchery";NA;19;0
"Unit";"Zergling";"Larva";20;1
"Unit";"Zergling";"Larva";21;1
"Unit";"Queen";"Hatchery";22;2
"Unit";"Overlord";"Larva";26;0
"Unit";"Queen";"Hatchery";26;2
"Unit";"Zergling";"Larva";31;1
"Unit";"Zergling";"Larva";32;1
"Unit";"Queen";"Hatchery";33;2
"Unit";"Zergling";"Larva";35;1
"Unit";"Zergling";"Larva";36;1
"Unit";"Zergling";"Larva";37;1
"Unit";"Zergling";"Larva";38;1
"Unit";"Overlord";"Larva";39;0
"Building";"CreepTumorQueen";NA;41;0
"Building";"Hatchery";NA;43;0
"Building";"CreepTumor";NA;43;0
"Building";"CreepTumorQueen";NA;47;0
"Unit";"Overlord";"Larva";47;0
"Building";"SporeCrawler";NA;52;0
"Building";"CreepTumor";NA;55;0
"Building";"CreepTumor";NA;57;0
"Unit";"Zergling";"Larva";57;1
"Unit";"Zergling";"Larva";58;1
"Unit";"Queen";"Hatchery";59;2
"Building";"SporeCrawler";NA;61;0
"Building";"EvolutionChamber";NA;61;0
"Unit";"Overlord";"Larva";61;0
"Building";"CreepTumor";NA;64;0
"Unit";"Overlord";"Larva";64;0
"Building";"CreepTumor";NA;64;0
"Unit";"Overlord";"Larva";64;0
"Unit";"Overlord";"Larva";64;0
"Building";"Extractor";NA;64;0
"Building";"EvolutionChamber";NA;64;0
"Unit";"Queen";"Hatchery";64;2
"Building";"CreepTumor";NA;70;0
"Unit";"Overlord";"Larva";75;0
"Building";"CreepTumor";NA;80;0
"Unit";"Overlord";"Larva";80;0
"Unit";"Zergling";"Larva";80;1
"Unit";"Zergling";"Larva";81;1
"Unit";"Zergling";"Larva";82;1
"Unit";"Zergling";"Larva";83;1
"Unit";"Zergling";"Larva";84;1
"Unit";"Zergling";"Larva";85;1
"Building";"CreepTumor";NA;86;0
"Unit";"Zergling";"Larva";86;1
"Unit";"Zergling";"Larva";87;1
"Unit";"Zergling";"Larva";88;1
"Unit";"Zergling";"Larva";89;1
"Building";"Extractor";NA;93;0
"Building";"Extractor";NA;93;0
"Building";"Extractor";NA;94;0
"Building";"CreepTumor";NA;102;0
"Building";"Extractor";NA;108;0
"Building";"CreepTumorQueen";NA;108;0
"Building";"Hatchery";NA;108;0
"Unit";"Overlord";"Larva";109;0
"Unit";"Zergling";"Larva";113;1
"Unit";"Zergling";"Larva";114;1
"Unit";"Zergling";"Larva";115;1
"Unit";"Zergling";"Larva";116;1
"Unit";"Zergling";"Larva";117;1
"Unit";"Zergling";"Larva";118;1
"Unit";"Zergling";"Larva";119;1
"Unit";"Zergling";"Larva";120;1
"Unit";"Zergling";"Larva";121;1
"Unit";"Zergling";"Larva";122;1
"Building";"BanelingNest";NA;123;0
"Unit";"Zergling";"Larva";123;1
"Unit";"Zergling";"Larva";124;1
"Unit";"Zergling";"Larva";125;1
"Unit";"Zergling";"Larva";126;1
"Unit";"Zergling";"Larva";127;1
"Unit";"Zergling";"Larva";128;1
"Unit";"Zergling";"Larva";129;1
"Unit";"Zergling";"Larva";130;1
"Unit";"Zergling";"Larva";131;1
"Unit";"Zergling";"Larva";132;1
"Unit";"Zergling";"Larva";133;1
"Unit";"Zergling";"Larva";134;1
"Building";"CreepTumor";NA;135;0
"Building";"CreepTumor";NA;135;0
"Building";"CreepTumorQueen";NA;135;0
"Unit";"Zergling";"Larva";135;1
"Unit";"Zergling";"Larva";136;1
"Unit";"Zergling";"Larva";137;1
"Unit";"Zergling";"Larva";138;1
"Building";"HydraliskDen";NA;139;0
"Unit";"Zergling";"Larva";139;1
"Unit";"Zergling";"Larva";140;1
"Unit";"Zergling";"Larva";141;1
"Unit";"Zergling";"Larva";142;1
"Unit";"Zergling";"Larva";143;1
"Unit";"Zergling";"Larva";144;1
"Unit";"Overlord";"Larva";147;0
"Unit";"Overlord";"Larva";147;0
"Unit";"Zergling";"Larva";147;1
"Unit";"Zergling";"Larva";148;1
"Unit";"Overlord";"Larva";149;0
"Unit";"Zergling";"Larva";149;1
"Unit";"Zergling";"Larva";150;1
"Unit";"Zergling";"Larva";151;1
"Unit";"Zergling";"Larva";152;1
"Unit";"Zergling";"Larva";153;1
"Unit";"Zergling";"Larva";154;1
"Unit";"Zergling";"Larva";155;1
"Unit";"Zergling";"Larva";156;1
"Unit";"Zergling";"Larva";157;1
"Unit";"Zergling";"Larva";158;1
"Unit";"Zergling";"Larva";159;1
"Unit";"Zergling";"Larva";160;1
"Unit";"Zergling";"Larva";161;1
"Unit";"Zergling";"Larva";162;1
"Unit";"Zergling";"Larva";163;1
"Unit";"Zergling";"Larva";164;1
"Unit";"Zergling";"Larva";165;1
"Unit";"Zergling";"Larva";166;1
"Unit";"Zergling";"Larva";167;1
"Unit";"Zergling";"Larva";168;1
"Unit";"Zergling";"Larva";169;1
"Unit";"Zergling";"Larva";170;1
"Unit";"Zergling";"Larva";171;1
"Unit";"Zergling";"Larva";172;1
"Unit";"Zergling";"Larva";173;1
"Unit";"Zergling";"Larva";174;1
"Unit";"Zergling";"Larva";175;1
"Unit";"Zergling";"Larva";176;1
"Unit";"Zergling";"Larva";177;1
"Unit";"Zergling";"Larva";178;1
"Unit";"Zergling";"Larva";179;1
"Unit";"Zergling";"Larva";180;1
"Unit";"Zergling";"Larva";181;1
"Unit";"Zergling";"Larva";182;1
"Unit";"Zergling";"Larva";183;1
"Unit";"Zergling";"Larva";184;1
"Building";"CreepTumor";NA;185;0
"Upgrade";"SprayZerg";NA;185;0
"Upgrade";"SprayZerg";NA;185;0
"Upgrade";"zerglingmovementspeed";NA;185;0
"Upgrade";"SprayZerg";NA;185;0
"Upgrade";"SprayZerg";NA;185;0
"Upgrade";"SprayZerg";NA;185;0
"Upgrade";"ZergGroundArmorsLevel1";NA;185;0
"Upgrade";"SprayZerg";NA;185;0
