"type";"unit_name";"on_building";"total_supply_lag"
"Building";"Barracks";NA;15
"Building";"Refinery";NA;15
"Building";"Barracks";NA;15
"Building";"Refinery";NA;16
"Unit";"Reaper";"Barracks";17
"Unit";"Reaper";"Barracks";18
"Unit";"Reaper";"Barracks";20
"Building";"Factory";NA;21
"Unit";"Reaper";"Barracks";22
