"type";"unit_name";"on_building";"total_supply_lag";"supply"
"Building";"Pylon";NA;14;0
"Building";"Gateway";NA;16;0
"Building";"Assimilator";NA;16;0
"Building";"Assimilator";NA;17;0
"Building";"Gateway";NA;19;0
"Building";"CyberneticsCore";NA;20;0
"Building";"Pylon";NA;22;0
"Unit";"Stalker";"Gateway";24;2
"Unit";"Stalker";"Gateway";26;2
"Building";"Pylon";NA;28;0
"Unit";"Stalker";"Gateway";28;2
"Unit";"Stalker";"Gateway";30;2
"Building";"Nexus";NA;35;0
"Building";"Pylon";NA;35;0
"Building";"TwilightCouncil";NA;36;0
"Building";"RoboticsFacility";NA;37;0
"Unit";"Sentry";"Gateway";37;2
"Unit";"Sentry";"Gateway";39;2
"Building";"DarkShrine";NA;43;0
"Unit";"Phoenix";"Stargate";48;2
"Building";"Pylon";NA;52;0
"Unit";"Observer";"Robotics Facility";52;1
"Building";"Assimilator";NA;54;0
"Building";"Assimilator";NA;55;0
"Building";"Pylon";NA;55;0
"Building";"Nexus";NA;59;0
"Building";"DarkTemplar";NA;59;0
"Building";"DarkTemplar";NA;60;0
"Building";"Pylon";NA;61;0
"Unit";"Phoenix";"Stargate";63;2
"Building";"Gateway";NA;66;0
"Building";"Gateway";NA;66;0
"Building";"Gateway";NA;66;0
"Unit";"Immortal";"Robotics Facility";67;4
"Building";"Gateway";NA;72;0
"Building";"Gateway";NA;72;0
"Unit";"Sentry";"Gateway";72;2
"Unit";"Stalker";"Gateway";74;2
"Building";"Pylon";NA;76;0
"Building";"Pylon";NA;77;0
"Unit";"Immortal";"Robotics Facility";77;4
"Unit";"Stalker";"Gateway";83;2
"Unit";"Stalker";"Gateway";85;2
"Unit";"Stalker";"Gateway";87;2
"Unit";"Stalker";"Gateway";89;2
"Unit";"Phoenix";"Stargate";91;2
"Building";"DarkTemplar";NA;98;0
"Building";"DarkTemplar";NA;98;0
"Unit";"Stalker";"Gateway";98;2
"Unit";"Stalker";"Gateway";100;2
"Unit";"Stalker";"Gateway";102;2
"Unit";"Archon";"High Templar";104;0
"Unit";"Stalker";"Gateway";104;2
"Unit";"Stalker";"Gateway";106;2
"Unit";"Phoenix";"Stargate";110;2
"Building";"Pylon";NA;112;0
"Unit";"Stalker";"Gateway";114;2
"Unit";"Stalker";"Gateway";116;2
"Building";"Pylon";NA;118;0
"Building";"Pylon";NA;118;0
"Unit";"Stalker";"Gateway";118;2
"Unit";"Stalker";"Gateway";120;2
"Unit";"Sentry";"Gateway";122;2
"Unit";"Stalker";"Gateway";124;2
"Unit";"Stalker";"Gateway";126;2
"Unit";"Stalker";"Gateway";128;2
"Unit";"Stalker";"Gateway";130;2
"Unit";"Stalker";"Gateway";132;2
"Unit";"Stalker";"Gateway";134;2
"Unit";"Stalker";"Gateway";136;2
"Unit";"Stalker";"Gateway";139;2
"Unit";"Stalker";"Gateway";141;2
"Unit";"Stalker";"Gateway";143;2
"Building";"RoboticsBay";NA;146;0
"Building";"Assimilator";NA;146;0
"Building";"Assimilator";NA;146;0
"Unit";"Stalker";"Gateway";149;2
"Unit";"Stalker";"Gateway";151;2
"Unit";"Stalker";"Gateway";153;2
"Unit";"Stalker";"Gateway";155;2
"Building";"Nexus";NA;157;0
"Building";"RoboticsFacility";NA;161;0
"Building";"Pylon";NA;161;0
"Building";"Pylon";NA;161;0
"Building";"Pylon";NA;161;0
"Building";"Pylon";NA;161;0
"Unit";"Disruptor";"Robotics Facility";161;3
"Building";"Pylon";NA;164;0
"Building";"Forge";NA;165;0
"Unit";"Stalker";"Gateway";165;2
"Unit";"Stalker";"Gateway";167;2
"Unit";"Stalker";"Gateway";169;2
"Unit";"Stalker";"Gateway";171;2
"Unit";"Stalker";"Gateway";173;2
"Unit";"Stalker";"Gateway";175;2
"Unit";"Stalker";"Gateway";177;2
"Unit";"Disruptor";"Robotics Facility";179;3
"Building";"Pylon";NA;182;0
"Building";"Pylon";NA;182;0
"Building";"Assimilator";NA;182;0
"Unit";"Phoenix";"Stargate";182;2
"Building";"Pylon";NA;184;0
"Unit";"Disruptor";"Robotics Facility";184;3
"Unit";"Stalker";"Gateway";187;2
"Unit";"Stalker";"Gateway";189;2
"Unit";"Stalker";"Gateway";191;2
"Unit";"Disruptor";"Robotics Facility";193;3
"Unit";"Disruptor";"Robotics Facility";196;3
"Building";"PhotonCannon";NA;199;0
"Building";"PhotonCannon";NA;199;0
"Building";"PhotonCannon";NA;199;0
"Upgrade";"Charge";"TwilightCouncil";199;0
"Upgrade";"ProtossGroundWeaponsLevel1";"Forge";199;0
"Building";"Assimilator";NA;199;0
"Building";"PhotonCannon";NA;199;0
"Unit";"Disruptor";"Robotics Facility";199;3
"Unit";"Disruptor";"Robotics Facility";202;3
"Building";"Stargate";NA;205;0
"Unit";"Disruptor";"Robotics Facility";205;3
"Unit";"Stalker";"Gateway";208;2
"Unit";"Stalker";"Gateway";210;2
"Unit";"Stalker";"Gateway";212;2
"Unit";"Stalker";"Gateway";214;2
"Unit";"Stalker";"Gateway";216;2
"Unit";"Stalker";"Gateway";218;2
"Unit";"Stalker";"Gateway";220;2
"Unit";"Disruptor";"Robotics Facility";222;3
"Building";"Nexus";NA;225;0
"Building";"Pylon";NA;225;0
"Building";"Pylon";NA;225;0
"Building";"Assimilator";NA;225;0
"Building";"Assimilator";NA;225;0
"Unit";"Oracle";"Stargate";225;3
"Unit";"Disruptor";"Robotics Facility";228;3
"Building";"PhotonCannon";NA;231;0
"Unit";"Stalker";"Gateway";231;2
"Unit";"Stalker";"Gateway";233;2
"Unit";"Stalker";"Gateway";235;2
"Unit";"Stalker";"Gateway";237;2
"Unit";"Stalker";"Gateway";239;2
"Unit";"Stalker";"Gateway";241;2
"Unit";"Stalker";"Gateway";243;2
"Building";"PhotonCannon";NA;245;0
"Building";"PhotonCannon";NA;245;0
"Unit";"Phoenix";"Stargate";245;2
"Unit";"Disruptor";"Robotics Facility";247;3
"Unit";"Disruptor";"Robotics Facility";250;3
"Building";"Gateway";NA;253;0
"Building";"Gateway";NA;253;0
"Unit";"Stalker";"Gateway";253;2
"Unit";"Stalker";"Gateway";255;2
"Unit";"Stalker";"Gateway";257;2
"Unit";"Stalker";"Gateway";259;2
"Building";"Gateway";NA;261;0
"Building";"Gateway";NA;261;0
"Building";"Gateway";NA;261;0
"Building";"Gateway";NA;261;0
"Unit";"Disruptor";"Robotics Facility";261;3
"Unit";"Disruptor";"Robotics Facility";264;3
"Unit";"Phoenix";"Stargate";267;2
"Unit";"Stalker";"Gateway";269;2
"Unit";"Stalker";"Gateway";271;2
"Unit";"Stalker";"Gateway";273;2
"Unit";"Stalker";"Gateway";275;2
"Unit";"Stalker";"Gateway";277;2
"Unit";"Stalker";"Gateway";279;2
"Unit";"Stalker";"Gateway";281;2
"Unit";"Oracle";"Stargate";283;3
"Unit";"Zealot";"Gateway";286;2
"Unit";"Zealot";"Gateway";288;2
"Unit";"Zealot";"Gateway";290;2
"Unit";"Zealot";"Gateway";292;2
"Unit";"Zealot";"Gateway";294;2
"Unit";"Zealot";"Gateway";296;2
"Unit";"Zealot";"Gateway";298;2
"Building";"Stargate";NA;300;0
"Building";"FleetBeacon";NA;300;0
"Building";"Stargate";NA;300;0
"Unit";"Zealot";"Gateway";300;2
"Unit";"Zealot";"Gateway";302;2
"Unit";"Zealot";"Gateway";304;2
"Unit";"Zealot";"Gateway";306;2
"Unit";"Zealot";"Gateway";308;2
"Unit";"Zealot";"Gateway";310;2
"Unit";"Zealot";"Gateway";312;2
"Unit";"Zealot";"Gateway";314;2
"Unit";"Zealot";"Gateway";316;2
"Unit";"Zealot";"Gateway";318;2
"Unit";"Zealot";"Gateway";320;2
"Unit";"Carrier";"Stargate";322;6
"Unit";"Carrier";"Stargate";328;6
"Unit";"Carrier";"Stargate";334;6
"Unit";"Stalker";"Gateway";340;2
"Unit";"Stalker";"Gateway";342;2
"Building";"TemplarArchive";NA;344;0
"Unit";"Phoenix";"Stargate";344;2
"Upgrade";"ProtossGroundWeaponsLevel2";"Forge";346;0
"Upgrade";"ProtossAirWeaponsLevel1";"CyberneticsCore";346;0
"Building";"DarkTemplar";NA;346;0
"Building";"DarkTemplar";NA;346;0
"Unit";"Carrier";"Stargate";346;6
"Unit";"Carrier";"Stargate";352;6
"Unit";"Carrier";"Stargate";358;6
"Building";"HighTemplar";NA;364;0
"Building";"HighTemplar";NA;364;0
"Building";"HighTemplar";NA;364;0
"Building";"HighTemplar";NA;364;0
"Unit";"Zealot";"Gateway";364;2
"Unit";"Zealot";"Gateway";366;2
"Unit";"Zealot";"Gateway";368;2
"Unit";"Zealot";"Gateway";370;2
"Unit";"Zealot";"Gateway";372;2
"Unit";"Zealot";"Gateway";374;2
"Unit";"Zealot";"Gateway";376;2
"Unit";"Archon";"High Templar";378;0
"Unit";"Archon";"High Templar";378;0
"Building";"DarkTemplar";NA;378;0
"Unit";"Observer";"Robotics Facility";378;1
"Building";"DarkTemplar";NA;379;0
"Unit";"Zealot";"Gateway";379;2
"Unit";"Zealot";"Gateway";381;2
"Unit";"Zealot";"Gateway";383;2
"Unit";"Zealot";"Gateway";385;2
"Unit";"Zealot";"Gateway";387;2
"Unit";"Zealot";"Gateway";389;2
"Unit";"Zealot";"Gateway";391;2
"Unit";"Zealot";"Gateway";393;2
"Building";"Nexus";NA;395;0
"Building";"Assimilator";NA;395;0
"Upgrade";"ProtossAirWeaponsLevel2";"CyberneticsCore";395;0
"Upgrade";"ProtossGroundWeaponsLevel3";"Forge";395;0
"Unit";"Zealot";"Gateway";395;2
"Unit";"Zealot";"Gateway";397;2
"Unit";"Zealot";"Gateway";399;2
"Unit";"Zealot";"Gateway";401;2
"Unit";"Zealot";"Gateway";403;2
"Unit";"Zealot";"Gateway";405;2
"Unit";"Zealot";"Gateway";407;2
"Unit";"Zealot";"Gateway";409;2
"Unit";"Zealot";"Gateway";411;2
"Unit";"Zealot";"Gateway";413;2
"Unit";"Zealot";"Gateway";415;2
"Building";"Stargate";NA;417;0
"Building";"Stargate";NA;417;0
"Building";"Stargate";NA;417;0
"Unit";"Oracle";"Stargate";417;3
"Building";"Nexus";NA;420;0
"Building";"DarkTemplar";NA;420;0
"Building";"DarkTemplar";NA;420;0
"Building";"DarkTemplar";NA;420;0
"Building";"DarkTemplar";NA;420;0
"Unit";"Tempest";"Stargate";420;4
"Building";"Assimilator";NA;424;0
"Unit";"Tempest";"Stargate";424;4
"Unit";"Tempest";"Stargate";428;4
"Unit";"Tempest";"Stargate";432;4
"Unit";"Tempest";"Stargate";436;4
"Unit";"Tempest";"Stargate";440;4
"Unit";"Tempest";"Stargate";444;4
"Building";"Pylon";NA;448;0
"Building";"Pylon";NA;448;0
"Unit";"Tempest";"Stargate";448;4
"Building";"CyberneticsCore";NA;452;0
"Building";"Nexus";NA;452;0
"Building";"Pylon";NA;452;0
"Unit";"Tempest";"Stargate";452;4
"Building";"Assimilator";NA;456;0
"Upgrade";"ProtossAirWeaponsLevel3";"CyberneticsCore";456;0
"Building";"Assimilator";NA;456;0
"Unit";"Oracle";"Stargate";456;3
"Unit";"Tempest";"Stargate";459;4
"Building";"Pylon";NA;463;0
"Unit";"Oracle";"Stargate";463;3
"Upgrade";"ProtossShieldsLevel1";"Forge";466;0
"Building";"DarkTemplar";NA;466;0
"Unit";"Tempest";"Stargate";466;4
"Unit";"Tempest";"Stargate";470;4
"Unit";"Tempest";"Stargate";474;4
"Unit";"Stalker";"Gateway";478;2
"Building";"PhotonCannon";NA;480;0
"Building";"PhotonCannon";NA;480;0
"Building";"PhotonCannon";NA;480;0
"Building";"PhotonCannon";NA;480;0
"Building";"PhotonCannon";NA;480;0
"Unit";"Tempest";"Stargate";480;4
"Unit";"Tempest";"Stargate";484;4
"Unit";"Tempest";"Stargate";488;4
"Unit";"Tempest";"Stargate";492;4
"Building";"HighTemplar";NA;496;0
"Building";"HighTemplar";NA;496;0
"Building";"HighTemplar";NA;496;0
"Building";"HighTemplar";NA;496;0
"Building";"HighTemplar";NA;496;0
"Building";"HighTemplar";NA;496;0
"Unit";"Archon";"High Templar";496;0
"Unit";"Archon";"High Templar";496;0
"Unit";"Archon";"High Templar";496;0
"Upgrade";"ProtossShieldsLevel2";"Forge";496;0
"Building";"FleetBeacon";NA;496;0
"Building";"PhotonCannon";NA;496;0
"Building";"PhotonCannon";NA;496;0
"Unit";"Zealot";"Gateway";496;2
"Unit";"Zealot";"Gateway";498;2
"Unit";"Zealot";"Gateway";500;2
"Unit";"Zealot";"Gateway";502;2
"Unit";"Zealot";"Gateway";504;2
"Unit";"Zealot";"Gateway";506;2
"Building";"Pylon";NA;508;0
"Building";"Pylon";NA;508;0
"Building";"Pylon";NA;508;0
"Building";"PhotonCannon";NA;508;0
"Unit";"Oracle";"Stargate";508;3
"Unit";"Oracle";"Stargate";511;3
"Building";"HighTemplar";NA;514;0
"Building";"HighTemplar";NA;514;0
"Building";"HighTemplar";NA;514;0
"Building";"HighTemplar";NA;514;0
"Unit";"Archon";"High Templar";514;0
"Unit";"Archon";"High Templar";514;0
"Unit";"Oracle";"Stargate";514;3
"Unit";"Tempest";"Stargate";517;4
"Unit";"Zealot";"Gateway";521;2
"Unit";"Zealot";"Gateway";523;2
"Unit";"Oracle";"Stargate";525;3
"Upgrade";"ProtossShieldsLevel3";"Forge";528;0
"Unit";"Oracle";"Stargate";528;3
"Unit";"Tempest";"Stargate";531;4
"Unit";"Tempest";"Stargate";535;4
"Unit";"Tempest";"Stargate";539;4
"Unit";"Zealot";"Gateway";543;2
"Unit";"Zealot";"Gateway";545;2
"Unit";"Zealot";"Gateway";547;2
"Unit";"Zealot";"Gateway";549;2
"Unit";"Zealot";"Gateway";551;2
"Unit";"Zealot";"Gateway";553;2
"Unit";"Zealot";"Gateway";555;2
"Unit";"Zealot";"Gateway";557;2
"Unit";"Zealot";"Gateway";559;2
"Unit";"Zealot";"Gateway";561;2
"Unit";"Zealot";"Gateway";563;2
"Unit";"Zealot";"Gateway";565;2
"Unit";"Zealot";"Gateway";567;2
"Unit";"Tempest";"Stargate";569;4
"Unit";"Tempest";"Stargate";573;4
"Unit";"Zealot";"Gateway";577;2
"Unit";"Zealot";"Gateway";579;2
"Unit";"Zealot";"Gateway";581;2
"Unit";"Zealot";"Gateway";583;2
"Unit";"Zealot";"Gateway";585;2
"Unit";"Zealot";"Gateway";587;2
"Unit";"Zealot";"Gateway";589;2
"Unit";"Zealot";"Gateway";591;2
"Unit";"Zealot";"Gateway";593;2
"Unit";"Zealot";"Gateway";595;2
"Unit";"Stalker";"Gateway";597;2
"Unit";"Stalker";"Gateway";600;2
"Unit";"Stalker";"Gateway";602;2
"Unit";"Stalker";"Gateway";610;2
"Unit";"Stalker";"Gateway";612;2
"Unit";"Stalker";"Gateway";614;2
"Unit";"Stalker";"Gateway";616;2
"Unit";"Stalker";"Gateway";618;2
"Unit";"Stalker";"Gateway";620;2
"Unit";"Zealot";"Gateway";622;2
"Unit";"Zealot";"Gateway";624;2
"Unit";"Zealot";"Gateway";626;2
"Unit";"Zealot";"Gateway";628;2
"Unit";"Stalker";"Gateway";632;2
"Unit";"Stalker";"Gateway";634;2
"Unit";"Zealot";"Gateway";636;2
"Unit";"Zealot";"Gateway";638;2
"Unit";"Zealot";"Gateway";640;2
"Unit";"Zealot";"Gateway";642;2
"Unit";"Zealot";"Gateway";644;2
"Upgrade";"SprayProtoss";NA;647;0
"Upgrade";"WarpGateResearch";NA;647;0
"Upgrade";"SprayProtoss";NA;647;0
"Upgrade";"SprayProtoss";NA;647;0
"Upgrade";"SprayProtoss";NA;647;0
"Upgrade";"BlinkTech";NA;647;0
"Upgrade";"SprayProtoss";NA;647;0
"Upgrade";"SprayProtoss";NA;647;0
"Upgrade";"SprayProtoss";NA;647;0
"Upgrade";"SprayProtoss";NA;647;0
"Upgrade";"CarrierLaunchSpeedUpgrade";NA;647;0
"Upgrade";"SprayProtoss";NA;647;0
"Upgrade";"SprayProtoss";NA;647;0
"Upgrade";"SprayProtoss";NA;647;0
"Upgrade";"SprayProtoss";NA;647;0
"Upgrade";"SprayProtoss";NA;647;0
"Upgrade";"SprayProtoss";NA;647;0
"Upgrade";"ProtossAirArmorsLevel1";NA;647;0
"Upgrade";"ProtossAirArmorsLevel2";NA;647;0
"Upgrade";"ProtossAirArmorsLevel3";NA;647;0
