"type";"unit_name";"on_building";"total_supply_lag";"supply"
"Building";"Pylon";NA;15;0
"Building";"Gateway";NA;16;0
"Building";"Assimilator";NA;17;0
"Building";"Nexus";NA;20;0
"Building";"CyberneticsCore";NA;20;0
"Building";"Assimilator";NA;21;0
"Building";"Pylon";NA;22;0
"Unit";"Adept";"Gateway";24;2
"Building";"Stargate";NA;27;0
"Unit";"Adept";"Gateway";28;2
"Building";"Pylon";NA;32;0
"Unit";"Oracle";"Stargate";34;3
"Unit";"Adept";"Gateway";39;2
"Building";"Gateway";NA;43;0
"Building";"Gateway";NA;47;0
"Building";"Assimilator";NA;48;0
"Building";"Stargate";NA;50;0
"Building";"Assimilator";NA;50;0
"Building";"Pylon";NA;53;0
"Building";"Nexus";NA;53;0
"Building";"Gateway";NA;53;0
"Building";"Pylon";NA;53;0
"Unit";"Oracle";"Stargate";53;3
"Unit";"Oracle";"Stargate";56;3
"Building";"Pylon";NA;61;0
"Building";"Forge";NA;61;0
"Building";"TwilightCouncil";NA;61;0
"Building";"Forge";NA;61;0
"Unit";"Oracle";"Stargate";61;3
"Unit";"Oracle";"Stargate";64;3
"Building";"Pylon";NA;69;0
"Building";"Pylon";NA;69;0
"Building";"Gateway";NA;72;0
"Building";"Gateway";NA;72;0
"Building";"Gateway";NA;74;0
"Unit";"Oracle";"Stargate";77;3
"Upgrade";"ProtossGroundWeaponsLevel1";"Forge";81;0
"Upgrade";"Charge";"TwilightCouncil";81;0
"Building";"Assimilator";NA;84;0
"Building";"Gateway";NA;84;0
"Building";"Gateway";NA;84;0
"Building";"Assimilator";NA;84;0
"Building";"Pylon";NA;84;0
"Building";"Gateway";NA;84;0
"Unit";"Oracle";"Stargate";87;3
"Unit";"Oracle";"Stargate";90;3
"Building";"TemplarArchive";NA;93;0
"Unit";"Sentry";"Gateway";96;2
"Unit";"Zealot";"Gateway";98;2
"Unit";"Zealot";"Gateway";100;2
"Unit";"Zealot";"Gateway";102;2
"Unit";"Zealot";"Gateway";104;2
"Building";"Pylon";NA;106;0
"Building";"Pylon";NA;107;0
"Building";"Pylon";NA;107;0
"Unit";"Oracle";"Stargate";107;3
"Unit";"Oracle";"Stargate";110;3
"Building";"Nexus";NA;113;0
"Building";"Pylon";NA;113;0
"Building";"Pylon";NA;113;0
"Unit";"Zealot";"Gateway";113;2
"Building";"Pylon";NA;115;0
"Building";"PhotonCannon";NA;115;0
"Upgrade";"ProtossGroundWeaponsLevel2";"Forge";115;0
"Building";"PhotonCannon";NA;115;0
"Building";"PhotonCannon";NA;115;0
"Building";"HighTemplar";NA;115;0
"Building";"HighTemplar";NA;115;0
"Building";"HighTemplar";NA;115;0
"Building";"HighTemplar";NA;115;0
"Unit";"Oracle";"Stargate";115;3
"Building";"Assimilator";NA;118;0
"Unit";"Archon";"High Templar";118;0
"Unit";"Archon";"High Templar";118;0
"Unit";"Zealot";"Gateway";118;2
"Unit";"Zealot";"Gateway";120;2
"Unit";"Zealot";"Gateway";122;2
"Unit";"Zealot";"Gateway";124;2
"Unit";"Zealot";"Gateway";126;2
"Building";"Assimilator";NA;128;0
"Unit";"Zealot";"Gateway";128;2
"Building";"Gateway";NA;133;0
"Building";"PhotonCannon";NA;133;0
"Building";"HighTemplar";NA;133;0
"Building";"HighTemplar";NA;133;0
"Unit";"Archon";"High Templar";133;0
"Unit";"Zealot";"Gateway";133;2
"Unit";"Zealot";"Gateway";135;2
"Unit";"Zealot";"Gateway";137;2
"Unit";"Zealot";"Gateway";139;2
"Unit";"Zealot";"Gateway";141;2
"Building";"HighTemplar";NA;143;0
"Building";"HighTemplar";NA;143;0
"Building";"HighTemplar";NA;143;0
"Building";"HighTemplar";NA;143;0
"Building";"HighTemplar";NA;143;0
"Building";"HighTemplar";NA;143;0
"Unit";"Zealot";"Gateway";143;2
"Unit";"Zealot";"Gateway";145;2
"Unit";"Zealot";"Gateway";147;2
"Unit";"Zealot";"Gateway";149;2
"Unit";"Archon";"High Templar";151;0
"Unit";"Archon";"High Templar";151;0
"Unit";"Archon";"High Templar";151;0
"Building";"Pylon";NA;151;0
"Building";"Pylon";NA;151;0
"Building";"Pylon";NA;151;0
"Building";"RoboticsFacility";NA;151;0
"Building";"RoboticsFacility";NA;151;0
"Building";"Pylon";NA;151;0
"Unit";"Zealot";"Gateway";151;2
"Unit";"Zealot";"Gateway";153;2
"Unit";"Zealot";"Gateway";155;2
"Unit";"Zealot";"Gateway";157;2
"Unit";"Zealot";"Gateway";159;2
"Unit";"Zealot";"Gateway";161;2
"Unit";"Zealot";"Gateway";163;2
"Unit";"Zealot";"Gateway";165;2
"Unit";"Zealot";"Gateway";167;2
"Unit";"Zealot";"Gateway";169;2
"Unit";"Zealot";"Gateway";171;2
"Unit";"Zealot";"Gateway";173;2
"Unit";"Zealot";"Gateway";175;2
"Unit";"Zealot";"Gateway";177;2
"Unit";"Zealot";"Gateway";179;2
"Unit";"Zealot";"Gateway";181;2
"Unit";"Zealot";"Gateway";183;2
"Unit";"Zealot";"Gateway";185;2
"Unit";"Zealot";"Gateway";187;2
"Unit";"Zealot";"Gateway";189;2
"Upgrade";"SprayProtoss";NA;191;0
"Upgrade";"SprayProtoss";NA;191;0
"Upgrade";"WarpGateResearch";NA;191;0
"Upgrade";"SprayProtoss";NA;191;0
"Upgrade";"SprayProtoss";NA;191;0
"Upgrade";"SprayProtoss";NA;191;0
"Upgrade";"ProtossGroundArmorsLevel1";NA;191;0
"Upgrade";"SprayProtoss";NA;191;0
"Upgrade";"ProtossGroundArmorsLevel2";NA;191;0
