"type";"unit_name";"on_building";"total_supply";"supply"
"Building";"Pylon";NA;13;0
"Building";"Assimilator";NA;15;0
"Building";"Gateway";NA;14;0
"Building";"Pylon";NA;20;0
"Building";"CyberneticsCore";NA;20;0
"Building";"Assimilator";NA;20;0
"Unit";"Adept";"Gateway";21;2
"Building";"Nexus";NA;19;0
"Unit";"Stalker";"Gateway";23;2
"Building";"TwilightCouncil";NA;30;0
"Building";"Gateway";NA;32;0
"Building";"ShieldBattery";NA;33;0
"Building";"Gateway";NA;32;0
"Unit";"Stalker";"Gateway";33;2
"Building";"Pylon";NA;35;0
"Unit";"Stalker";"Gateway";42;2
"Unit";"Stalker";"Gateway";42;2
"Unit";"Stalker";"Gateway";42;2
"Building";"Pylon";NA;41;0
"Unit";"Stalker";"Gateway";54;2
"Building";"RoboticsFacility";NA;41;0
"Building";"Assimilator";NA;51;0
"Unit";"Stalker";"Gateway";57;2
"Unit";"Stalker";"Gateway";57;2
"Building";"Assimilator";NA;52;0
"Building";"Pylon";NA;62;0
"Building";"DarkShrine";NA;41;0
"Unit";"Stalker";"Gateway";62;2
"Building";"Pylon";NA;62;0
"Unit";"Stalker";"Gateway";64;2
"Unit";"Stalker";"Gateway";64;2
"Building";"Forge";NA;62;0
"Building";"DarkTemplar";NA;74;0
"Building";"DarkTemplar";NA;74;0
"Building";"Pylon";NA;73;0
"Building";"DarkTemplar";NA;76;0
"Building";"Nexus";NA;62;0
"Unit";"Observer";"Robotics Facility";74;1
"Unit";"Observer";"Robotics Facility";77;1
"Building";"Pylon";NA;82;0
"Unit";"Observer";"Robotics Facility";82;1
"Building";"TemplarArchive";NA;80;0
"Unit";"Zealot";"Gateway";92;2
"Unit";"Zealot";"Gateway";92;2
"Upgrade";"ProtossGroundWeaponsLevel1";"Forge";76;0
"Upgrade";"Charge";"TwilightCouncil";78;0
"Unit";"Sentry";"Gateway";99;2
"Building";"HighTemplar";NA;99;0
"Building";"HighTemplar";NA;99;0
"Building";"Pylon";NA;99;0
"Building";"Gateway";NA;97;0
"Building";"Assimilator";NA;101;0
"Building";"Pylon";NA;103;0
"Building";"Gateway";NA;97;0
"Building";"PhotonCannon";NA;98;0
"Building";"Gateway";NA;97;0
"Building";"Forge";NA;98;0
"Building";"PhotonCannon";NA;99;0
"Building";"HighTemplar";NA;106;0
"Building";"HighTemplar";NA;106;0
"Building";"HighTemplar";NA;106;0
"Building";"HighTemplar";NA;106;0
"Unit";"Zealot";"Gateway";106;2
"Unit";"Zealot";"Gateway";106;2
"Building";"ShieldBattery";NA;104;0
"Building";"PhotonCannon";NA;104;0
"Building";"Assimilator";NA;106;0
"Unit";"Archon";"High Templar";111;0
"Unit";"Zealot";"Gateway";111;2
"Unit";"Zealot";"Gateway";111;2
"Building";"Gateway";NA;106;0
"Building";"Gateway";NA;106;0
"Unit";"Zealot";"Gateway";115;2
"Unit";"Zealot";"Gateway";115;2
"Unit";"Zealot";"Gateway";115;2
"Unit";"Zealot";"Gateway";115;2
"Building";"Gateway";NA;106;0
"Upgrade";"ProtossGroundArmorsLevel1";"Forge";98;0
"Building";"HighTemplar";NA;123;0
"Unit";"Zealot";"Gateway";123;2
"Unit";"Zealot";"Gateway";123;2
"Unit";"Zealot";"Gateway";123;2
"Unit";"Zealot";"Gateway";123;2
"Unit";"Zealot";"Gateway";123;2
"Unit";"Zealot";"Gateway";123;2
"Unit";"Zealot";"Gateway";123;2
"Unit";"Zealot";"Gateway";123;2
"Building";"Pylon";NA;123;0
"Building";"Pylon";NA;139;0
"Building";"HighTemplar";NA;140;0
"Building";"HighTemplar";NA;140;0
"Building";"HighTemplar";NA;140;0
"Building";"HighTemplar";NA;140;0
"Building";"HighTemplar";NA;140;0
"Building";"PhotonCannon";NA;139;0
"Building";"ShieldBattery";NA;139;0
"Building";"PhotonCannon";NA;139;0
"Building";"ShieldBattery";NA;139;0
"Unit";"Archon";"High Templar";142;0
"Unit";"Archon";"High Templar";142;0
"Upgrade";"ProtossGroundWeaponsLevel2";"Forge";111;0
"Unit";"Immortal";"Robotics Facility";140;4
"Building";"Pylon";NA;142;0
"Building";"Pylon";NA;142;0
"Building";"Pylon";NA;142;0
"Building";"Pylon";NA;142;0
"Building";"Pylon";NA;142;0
"Unit";"Stalker";"Gateway";146;2
"Unit";"Stalker";"Gateway";146;2
"Unit";"Stalker";"Gateway";146;2
"Building";"Nexus";NA;139;0
"Unit";"Stalker";"Gateway";146;2
"Unit";"Stalker";"Gateway";146;2
"Unit";"Stalker";"Gateway";146;2
"Building";"PhotonCannon";NA;142;0
"Building";"PhotonCannon";NA;142;0
"Building";"ShieldBattery";NA;142;0
"Building";"ShieldBattery";NA;142;0
"Unit";"Zealot";"Gateway";158;2
"Building";"PhotonCannon";NA;142;0
"Unit";"Zealot";"Gateway";158;2
"Building";"PhotonCannon";NA;142;0
"Unit";"Zealot";"Gateway";162;2
"Unit";"Zealot";"Gateway";164;2
"Unit";"Zealot";"Gateway";164;2
"Unit";"Zealot";"Gateway";164;2
"Unit";"Zealot";"Gateway";164;2
"Unit";"Zealot";"Gateway";164;2
"Unit";"Zealot";"Gateway";164;2
"Unit";"Zealot";"Gateway";164;2
"Building";"HighTemplar";NA;164;0
"Upgrade";"ProtossGroundArmorsLevel2";"Forge";140;0
"Building";"Pylon";NA;178;0
"Building";"Assimilator";NA;178;0
"Building";"Assimilator";NA;178;0
"Building";"Stargate";NA;178;0
"Building";"Pylon";NA;178;0
"Building";"Pylon";NA;178;0
"Upgrade";"ProtossShieldsLevel1";"Forge";178;0
"Building";"Stargate";NA;178;0
"Building";"Pylon";NA;178;0
"Building";"PhotonCannon";NA;178;0
"Building";"Nexus";NA;178;0
"Building";"PhotonCannon";NA;178;0
"Building";"HighTemplar";NA;178;0
"Building";"HighTemplar";NA;178;0
"Building";"HighTemplar";NA;178;0
"Building";"HighTemplar";NA;178;0
"Building";"HighTemplar";NA;178;0
"Building";"HighTemplar";NA;178;0
"Building";"HighTemplar";NA;178;0
"Building";"HighTemplar";NA;178;0
"Building";"HighTemplar";NA;178;0
"Building";"FleetBeacon";NA;178;0
"Building";"Stargate";NA;178;0
"Building";"PhotonCannon";NA;178;0
"Building";"PhotonCannon";NA;178;0
"Building";"PhotonCannon";NA;178;0
"Building";"PhotonCannon";NA;178;0
"Building";"ShieldBattery";NA;178;0
"Building";"Assimilator";NA;178;0
"Building";"PhotonCannon";NA;178;0
"Unit";"Archon";"High Templar";178;0
"Unit";"Archon";"High Templar";178;0
"Unit";"Archon";"High Templar";178;0
"Unit";"Archon";"High Templar";178;0
"Unit";"Archon";"High Templar";178;0
"Building";"PhotonCannon";NA;178;0
"Building";"Assimilator";NA;178;0
"Upgrade";"ProtossGroundWeaponsLevel3";"Forge";178;0
"Unit";"Tempest";"Stargate";178;4
"Unit";"Tempest";"Stargate";178;4
"Unit";"Tempest";"Stargate";178;4
"Unit";"Zealot";"Gateway";190;2
"Unit";"Zealot";"Gateway";190;2
"Unit";"Zealot";"Gateway";190;2
"Unit";"Zealot";"Gateway";190;2
"Unit";"Zealot";"Gateway";190;2
"Unit";"Zealot";"Gateway";190;2
"Upgrade";"ProtossAirWeaponsLevel1";"CyberneticsCore";178;0
"Upgrade";"ProtossShieldsLevel2";"Forge";178;0
"Unit";"Oracle";"Stargate";190;3
"Unit";"Oracle";"Stargate";190;3
"Unit";"Tempest";"Stargate";202;4
"Unit";"Zealot";"Gateway";212;2
"Unit";"Zealot";"Gateway";212;2
"Unit";"Zealot";"Gateway";216;2
"Unit";"Zealot";"Gateway";216;2
"Building";"HighTemplar";NA;220;0
"Building";"HighTemplar";NA;220;0
"Building";"HighTemplar";NA;220;0
"Building";"HighTemplar";NA;220;0
"Building";"HighTemplar";NA;220;0
"Building";"HighTemplar";NA;220;0
"Building";"HighTemplar";NA;220;0
"Upgrade";"ProtossGroundArmorsLevel3";"Forge";202;0
"Building";"PhotonCannon";NA;220;0
"Building";"HighTemplar";NA;220;0
"Unit";"Zealot";"Gateway";220;2
"Unit";"Immortal";"Robotics Facility";220;4
"Unit";"Archon";"High Templar";220;0
"Unit";"Archon";"High Templar";220;0
"Unit";"Archon";"High Templar";220;0
"Unit";"Carrier";"Stargate";212;6
"Unit";"Carrier";"Stargate";212;6
"Unit";"Zealot";"Gateway";226;2
"Unit";"Zealot";"Gateway";226;2
"Unit";"Zealot";"Gateway";226;2
"Unit";"Zealot";"Gateway";226;2
"Unit";"Zealot";"Gateway";226;2
"Unit";"Zealot";"Gateway";226;2
"Unit";"Zealot";"Gateway";226;2
"Unit";"Carrier";"Stargate";212;6
"Building";"HighTemplar";NA;258;0
"Building";"HighTemplar";NA;258;0
"Upgrade";"ProtossAirWeaponsLevel2";"CyberneticsCore";226;0
"Unit";"Carrier";"Stargate";258;6
"Unit";"Carrier";"Stargate";258;6
"Upgrade";"ProtossShieldsLevel3";"Forge";226;0
"Unit";"Oracle";"Stargate";270;3
"Unit";"Oracle";"Stargate";270;3
"Unit";"Zealot";"Gateway";273;2
"Unit";"Zealot";"Gateway";273;2
"Unit";"Zealot";"Gateway";273;2
"Building";"HighTemplar";NA;276;0
"Building";"HighTemplar";NA;276;0
"Building";"Pylon";NA;282;0
"Building";"Pylon";NA;282;0
"Building";"Pylon";NA;282;0
"Unit";"Carrier";"Stargate";282;6
"Unit";"Carrier";"Stargate";282;6
"Unit";"Tempest";"Stargate";282;4
"Unit";"Zealot";"Gateway";298;2
"Unit";"Zealot";"Gateway";298;2
"Unit";"Zealot";"Gateway";298;2
"Unit";"Zealot";"Gateway";298;2
"Unit";"Zealot";"Gateway";298;2
"Unit";"Zealot";"Gateway";298;2
"Unit";"Zealot";"Gateway";298;2
"Building";"Nexus";NA;282;0
"Unit";"Zealot";"Gateway";312;2
"Unit";"Zealot";"Gateway";312;2
"Unit";"Zealot";"Gateway";312;2
"Unit";"Zealot";"Gateway";312;2
"Unit";"Zealot";"Gateway";312;2
"Unit";"Zealot";"Gateway";312;2
"Unit";"Zealot";"Gateway";312;2
"Unit";"Zealot";"Gateway";312;2
"Unit";"Zealot";"Gateway";328;2
