"type";"unit_name";"on_building";"total_supply_lag";"supply"
"Building";"Pylon";NA;14;0
"Building";"Gateway";NA;16;0
"Building";"Assimilator";NA;17;0
"Building";"Nexus";NA;20;0
"Building";"CyberneticsCore";NA;21;0
"Building";"Pylon";NA;22;0
"Building";"Assimilator";NA;22;0
"Unit";"Stalker";"Gateway";23;2
"Building";"TwilightCouncil";NA;27;0
"Unit";"Stalker";"Gateway";30;2
"Building";"Pylon";NA;35;0
"Unit";"Stalker";"Gateway";35;2
"Building";"ShieldBattery";NA;38;0
"Unit";"Stalker";"Gateway";39;2
"Building";"Gateway";NA;44;0
"Building";"Gateway";NA;44;0
"Building";"RoboticsFacility";NA;46;0
"Building";"Assimilator";NA;46;0
"Building";"Pylon";NA;48;0
"Building";"Assimilator";NA;48;0
"Unit";"Stalker";"Gateway";48;2
"Unit";"Observer";"Robotics Facility";56;1
"Unit";"Stalker";"Gateway";57;2
"Unit";"Stalker";"Gateway";59;2
"Unit";"Stalker";"Gateway";61;2
"Building";"RoboticsBay";NA;63;0
"Building";"Pylon";NA;64;0
"Building";"Pylon";NA;64;0
"Unit";"Observer";"Robotics Facility";64;1
"Building";"Nexus";NA;67;0
"Unit";"Observer";"Robotics Facility";69;1
"Building";"Gateway";NA;70;0
"Building";"Gateway";NA;70;0
"Unit";"Disruptor";"Robotics Facility";71;3
"Building";"Gateway";NA;74;0
"Unit";"Stalker";"Gateway";75;2
"Unit";"Stalker";"Gateway";77;2
"Unit";"Stalker";"Gateway";79;2
"Building";"Pylon";NA;81;0
"Building";"Pylon";NA;81;0
"Unit";"Disruptor";"Robotics Facility";81;3
"Building";"Pylon";NA;86;0
"Unit";"Disruptor";"Robotics Facility";88;3
"Building";"Gateway";NA;92;0
"Building";"Gateway";NA;92;0
"Building";"Pylon";NA;92;0
"Unit";"Stalker";"Gateway";95;2
"Unit";"Stalker";"Gateway";97;2
"Unit";"Disruptor";"Robotics Facility";99;3
"Unit";"Stalker";"Gateway";105;2
"Unit";"Stalker";"Gateway";107;2
"Unit";"Stalker";"Gateway";109;2
"Unit";"Stalker";"Gateway";111;2
"Unit";"Stalker";"Gateway";114;2
"Unit";"Stalker";"Gateway";116;2
"Unit";"Disruptor";"Robotics Facility";118;3
"Building";"Pylon";NA;122;0
"Unit";"Stalker";"Gateway";122;2
"Unit";"Stalker";"Gateway";124;2
"Building";"Forge";NA;126;0
"Building";"Pylon";NA;126;0
"Building";"Nexus";NA;126;0
"Building";"Pylon";NA;126;0
"Building";"Pylon";NA;126;0
"Unit";"Disruptor";"Robotics Facility";126;3
"Building";"Pylon";NA;129;0
"Building";"Pylon";NA;129;0
"Upgrade";"Charge";"TwilightCouncil";129;0
"Unit";"Disruptor";"Robotics Facility";129;3
"Unit";"Stalker";"Gateway";132;2
"Unit";"Stalker";"Gateway";134;2
"Unit";"Stalker";"Gateway";136;2
"Unit";"Stalker";"Gateway";138;2
"Unit";"Stalker";"Gateway";140;2
"Unit";"Stalker";"Gateway";142;2
"Building";"ShieldBattery";NA;144;0
"Building";"Assimilator";NA;144;0
"Building";"ShieldBattery";NA;144;0
"Building";"Assimilator";NA;144;0
"Unit";"Zealot";"Gateway";144;2
"Unit";"Zealot";"Gateway";146;2
"Unit";"Zealot";"Gateway";148;2
"Unit";"Zealot";"Gateway";150;2
"Unit";"Zealot";"Gateway";152;2
"Unit";"Zealot";"Gateway";154;2
"Unit";"Zealot";"Gateway";156;2
"Unit";"Zealot";"Gateway";158;2
"Unit";"Observer";"Robotics Facility";160;1
"Building";"PhotonCannon";NA;165;0
"Unit";"Zealot";"Gateway";166;2
"Building";"Forge";NA;168;0
"Unit";"Adept";"Gateway";168;2
"Unit";"Adept";"Gateway";170;2
"Unit";"Adept";"Gateway";172;2
"Unit";"Adept";"Gateway";174;2
"Unit";"Adept";"Gateway";176;2
"Unit";"Adept";"Gateway";178;2
"Unit";"Adept";"Gateway";180;2
"Unit";"Stalker";"Gateway";183;2
"Unit";"Stalker";"Gateway";185;2
"Unit";"Stalker";"Gateway";187;2
"Unit";"Stalker";"Gateway";189;2
"Unit";"Stalker";"Gateway";191;2
"Unit";"Stalker";"Gateway";193;2
"Unit";"Disruptor";"Robotics Facility";197;3
"Unit";"Zealot";"Gateway";200;2
"Unit";"Zealot";"Gateway";202;2
"Unit";"Zealot";"Gateway";204;2
"Unit";"Zealot";"Gateway";206;2
"Unit";"Zealot";"Gateway";208;2
"Unit";"Zealot";"Gateway";210;2
"Unit";"Zealot";"Gateway";212;2
"Unit";"Stalker";"Gateway";214;2
"Building";"Gateway";NA;216;0
"Building";"Gateway";NA;216;0
"Building";"Gateway";NA;216;0
"Building";"Pylon";NA;216;0
"Building";"Pylon";NA;216;0
"Unit";"Zealot";"Gateway";216;2
"Upgrade";"ProtossGroundWeaponsLevel1";"Forge";218;0
"Building";"Nexus";NA;218;0
"Building";"Pylon";NA;218;0
"Unit";"Zealot";"Gateway";218;2
"Unit";"Zealot";"Gateway";220;2
"Unit";"Zealot";"Gateway";222;2
"Unit";"Adept";"Gateway";224;2
"Unit";"Adept";"Gateway";226;2
"Unit";"Adept";"Gateway";228;2
"Unit";"Stalker";"Gateway";230;2
"Unit";"Stalker";"Gateway";232;2
"Unit";"Adept";"Gateway";234;2
"Unit";"Adept";"Gateway";236;2
"Unit";"Adept";"Gateway";238;2
"Unit";"Stalker";"Gateway";240;2
"Unit";"Stalker";"Gateway";242;2
"Unit";"Stalker";"Gateway";244;2
"Unit";"Adept";"Gateway";246;2
"Unit";"Adept";"Gateway";248;2
"Building";"RoboticsFacility";NA;252;0
"Building";"Gateway";NA;252;0
"Building";"Gateway";NA;252;0
"Unit";"Stalker";"Gateway";252;2
"Unit";"Stalker";"Gateway";254;2
"Unit";"Stalker";"Gateway";256;2
"Unit";"Zealot";"Gateway";258;2
"Unit";"Zealot";"Gateway";260;2
"Unit";"Zealot";"Gateway";262;2
"Building";"Gateway";NA;264;0
"Unit";"Adept";"Gateway";264;2
"Unit";"Adept";"Gateway";266;2
"Unit";"Adept";"Gateway";268;2
"Unit";"Stalker";"Gateway";270;2
"Unit";"Stalker";"Gateway";272;2
"Unit";"Stalker";"Gateway";274;2
"Unit";"Stalker";"Gateway";276;2
"Unit";"Stalker";"Gateway";278;2
"Unit";"Stalker";"Gateway";280;2
"Building";"TemplarArchive";NA;282;0
"Unit";"Adept";"Gateway";282;2
"Unit";"Adept";"Gateway";284;2
"Upgrade";"ProtossGroundWeaponsLevel2";"Forge";287;0
"Unit";"Adept";"Gateway";287;2
"Unit";"Adept";"Gateway";289;2
"Unit";"Adept";"Gateway";291;2
"Unit";"Adept";"Gateway";293;2
"Unit";"Adept";"Gateway";295;2
"Unit";"Adept";"Gateway";297;2
"Unit";"Zealot";"Gateway";299;2
"Unit";"Zealot";"Gateway";301;2
"Unit";"Zealot";"Gateway";303;2
"Unit";"Zealot";"Gateway";305;2
"Unit";"Zealot";"Gateway";307;2
"Building";"HighTemplar";NA;309;0
"Building";"HighTemplar";NA;309;0
"Unit";"Adept";"Gateway";309;2
"Unit";"Archon";"High Templar";311;0
"Unit";"Adept";"Gateway";311;2
"Unit";"Adept";"Gateway";313;2
"Unit";"Adept";"Gateway";315;2
"Unit";"Immortal";"Robotics Facility";317;4
"Unit";"Immortal";"Robotics Facility";321;4
"Unit";"Adept";"Gateway";325;2
"Unit";"Adept";"Gateway";327;2
"Unit";"Zealot";"Gateway";329;2
"Unit";"Zealot";"Gateway";331;2
"Unit";"Zealot";"Gateway";333;2
"Unit";"Zealot";"Gateway";335;2
"Unit";"Zealot";"Gateway";337;2
"Unit";"Zealot";"Gateway";339;2
"Building";"PhotonCannon";NA;341;0
"Building";"PhotonCannon";NA;341;0
"Building";"ShieldBattery";NA;341;0
"Unit";"Adept";"Gateway";341;2
"Unit";"Adept";"Gateway";343;2
"Unit";"Immortal";"Robotics Facility";345;4
"Unit";"Immortal";"Robotics Facility";349;4
"Unit";"Adept";"Gateway";353;2
"Unit";"Adept";"Gateway";355;2
"Building";"HighTemplar";NA;357;0
"Building";"HighTemplar";NA;357;0
"Building";"HighTemplar";NA;357;0
"Building";"HighTemplar";NA;357;0
"Upgrade";"ProtossShieldsLevel1";"Forge";357;0
"Unit";"Archon";"High Templar";357;0
"Unit";"Archon";"High Templar";357;0
"Unit";"Zealot";"Gateway";357;2
"Unit";"Zealot";"Gateway";359;2
"Unit";"Zealot";"Gateway";361;2
"Unit";"Zealot";"Gateway";363;2
"Unit";"Zealot";"Gateway";365;2
"Unit";"Zealot";"Gateway";367;2
"Unit";"Zealot";"Gateway";369;2
"Unit";"Zealot";"Gateway";371;2
"Upgrade";"ProtossGroundWeaponsLevel3";"Forge";373;0
"Unit";"Adept";"Gateway";373;2
"Unit";"Adept";"Gateway";375;2
"Building";"Assimilator";NA;377;0
"Building";"Assimilator";NA;377;0
"Unit";"Adept";"Gateway";377;2
"Unit";"Adept";"Gateway";379;2
"Unit";"Zealot";"Gateway";381;2
"Unit";"Zealot";"Gateway";383;2
"Unit";"Zealot";"Gateway";385;2
"Unit";"Zealot";"Gateway";387;2
"Unit";"Zealot";"Gateway";389;2
"Unit";"Zealot";"Gateway";391;2
"Unit";"Zealot";"Gateway";393;2
"Unit";"Zealot";"Gateway";395;2
"Unit";"Zealot";"Gateway";397;2
"Unit";"Zealot";"Gateway";399;2
"Unit";"Zealot";"Gateway";401;2
"Unit";"Zealot";"Gateway";403;2
"Unit";"Zealot";"Gateway";405;2
"Unit";"Zealot";"Gateway";407;2
"Unit";"Immortal";"Robotics Facility";409;4
"Unit";"Immortal";"Robotics Facility";413;4
"Unit";"Adept";"Gateway";417;2
"Unit";"Adept";"Gateway";419;2
"Unit";"Adept";"Gateway";421;2
"Unit";"Adept";"Gateway";423;2
"Unit";"Zealot";"Gateway";425;2
"Unit";"Zealot";"Gateway";427;2
"Unit";"Zealot";"Gateway";429;2
"Unit";"Zealot";"Gateway";431;2
"Unit";"Zealot";"Gateway";433;2
"Unit";"Zealot";"Gateway";435;2
"Unit";"Stalker";"Gateway";437;2
"Unit";"Stalker";"Gateway";439;2
"Unit";"Stalker";"Gateway";441;2
"Unit";"Stalker";"Gateway";443;2
"Unit";"Zealot";"Gateway";445;2
"Unit";"Stalker";"Gateway";447;2
"Unit";"Stalker";"Gateway";449;2
"Unit";"Stalker";"Gateway";451;2
"Unit";"Stalker";"Gateway";453;2
"Unit";"Stalker";"Gateway";455;2
"Unit";"Stalker";"Gateway";457;2
"Unit";"Stalker";"Gateway";459;2
"Unit";"Stalker";"Gateway";461;2
"Unit";"Stalker";"Gateway";463;2
"Unit";"Stalker";"Gateway";465;2
"Unit";"Stalker";"Gateway";467;2
"Unit";"Stalker";"Gateway";469;2
"Unit";"Stalker";"Gateway";471;2
"Unit";"Stalker";"Gateway";473;2
"Unit";"Zealot";"Gateway";475;2
"Unit";"Zealot";"Gateway";477;2
"Unit";"Zealot";"Gateway";479;2
"Unit";"Zealot";"Gateway";481;2
"Unit";"Zealot";"Gateway";483;2
"Unit";"Zealot";"Gateway";485;2
"Unit";"Zealot";"Gateway";487;2
"Upgrade";"SprayProtoss";NA;489;0
"Upgrade";"SprayProtoss";NA;489;0
"Upgrade";"WarpGateResearch";NA;489;0
"Upgrade";"BlinkTech";NA;489;0
"Upgrade";"SprayProtoss";NA;489;0
"Upgrade";"SprayProtoss";NA;489;0
"Upgrade";"SprayProtoss";NA;489;0
"Upgrade";"SprayProtoss";NA;489;0
"Upgrade";"ProtossGroundArmorsLevel1";NA;489;0
"Upgrade";"SprayProtoss";NA;489;0
"Upgrade";"ProtossGroundArmorsLevel2";NA;489;0
"Upgrade";"SprayProtoss";NA;489;0
"Upgrade";"ProtossGroundArmorsLevel3";NA;489;0
