"type";"unit_name";"on_building";"total_supply";"supply"
"Building";"Pylon";NA;13;0
"Building";"Assimilator";NA;16;0
"Building";"Gateway";NA;15;0
"Building";"Assimilator";NA;20;0
"Building";"CyberneticsCore";NA;20;0
"Unit";"Zealot";"Gateway";20;2
"Building";"Pylon";NA;21;0
"Unit";"Stalker";"Gateway";21;2
"Building";"ShieldBattery";NA;23;0
"Building";"ShieldBattery";NA;23;0
"Building";"Gateway";NA;21;0
"Building";"Gateway";NA;21;0
"Building";"Pylon";NA;25;0
"Unit";"Stalker";"Gateway";25;2
"Building";"Pylon";NA;25;0
"Unit";"Stalker";"Gateway";25;2
"Unit";"Stalker";"Gateway";25;2
"Building";"ShieldBattery";NA;27;0
"Unit";"Stalker";"Gateway";31;2
"Unit";"Stalker";"Gateway";31;2
"Unit";"Stalker";"Gateway";31;2
"Building";"ShieldBattery";NA;31;0
"Unit";"Zealot";"Gateway";37;2
"Unit";"Zealot";"Gateway";37;2
"Building";"CyberneticsCore";NA;37;0
"Unit";"Stalker";"Gateway";41;2
"Unit";"Stalker";"Gateway";41;2
"Unit";"Stalker";"Gateway";41;2
"Unit";"Stalker";"Gateway";41;2
"Unit";"Stalker";"Gateway";45;2
"Building";"Pylon";NA;49;0
"Unit";"Stalker";"Gateway";47;2
"Unit";"Stalker";"Gateway";49;2
"Unit";"Stalker";"Gateway";51;2
"Unit";"Stalker";"Gateway";53;2
"Unit";"Stalker";"Gateway";55;2
"Unit";"Stalker";"Gateway";57;2
"Unit";"Stalker";"Gateway";59;2
"Building";"Stargate";NA;59;0
"Unit";"Stalker";"Gateway";61;2
"Building";"Pylon";NA;63;0
"Unit";"Stalker";"Gateway";63;2
"Unit";"Oracle";"Stargate";63;3
"Unit";"Sentry";"Gateway";67;2
"Unit";"Stalker";"Gateway";74;2
"Unit";"Stalker";"Gateway";74;2
"Unit";"Stalker";"Gateway";81;2
"Unit";"Stalker";"Gateway";81;2
"Unit";"Stalker";"Gateway";85;2
"Unit";"Stalker";"Gateway";85;2
"Building";"Gateway";NA;85;0
"Building";"Gateway";NA;85;0
"Building";"TwilightCouncil";NA;89;0
"Building";"Nexus";NA;89;0
"Building";"RoboticsFacility";NA;89;0
"Building";"TemplarArchive";NA;91;0
"Building";"HighTemplar";NA;94;0
"Building";"HighTemplar";NA;94;0
"Building";"HighTemplar";NA;94;0
"Building";"HighTemplar";NA;94;0
"Building";"Pylon";NA;94;0
"Unit";"Archon";"High Templar";96;0
"Unit";"Archon";"High Templar";96;0
"Building";"HighTemplar";NA;98;0
"Building";"HighTemplar";NA;98;0
"Building";"HighTemplar";NA;98;0
"Building";"HighTemplar";NA;98;0
"Unit";"Archon";"High Templar";98;0
"Unit";"Archon";"High Templar";98;0
"Unit";"Zealot";"Gateway";104;2
"Unit";"Zealot";"Gateway";104;2
"Unit";"Zealot";"Gateway";104;2
"Unit";"Zealot";"Gateway";104;2
"Building";"HighTemplar";NA;112;0
"Building";"HighTemplar";NA;112;0
"Unit";"Zealot";"Gateway";112;2
"Unit";"Zealot";"Gateway";112;2
"Building";"Pylon";NA;116;0
"Building";"Pylon";NA;116;0
"Unit";"Archon";"High Templar";116;0
"Upgrade";"Charge";"TwilightCouncil";102;0
"Building";"Assimilator";NA;116;0
"Building";"Assimilator";NA;116;0
"Building";"Forge";NA;117;0
"Building";"Nexus";NA;119;0
"Building";"Pylon";NA;125;0
"Building";"HighTemplar";NA;131;0
"Building";"HighTemplar";NA;131;0
"Building";"HighTemplar";NA;131;0
"Building";"HighTemplar";NA;131;0
"Building";"Assimilator";NA;131;0
"Unit";"Immortal";"Robotics Facility";126;4
"Building";"Assimilator";NA;131;0
"Unit";"Archon";"High Templar";133;0
"Unit";"Archon";"High Templar";133;0
"Upgrade";"ProtossGroundWeaponsLevel1";"Forge";123;0
"Building";"Gateway";NA;129;0
"Building";"Gateway";NA;130;0
"Unit";"Zealot";"Gateway";137;2
"Unit";"Zealot";"Gateway";139;2
"Unit";"Zealot";"Gateway";139;2
"Unit";"Zealot";"Gateway";139;2
"Building";"Pylon";NA;137;0
"Building";"Pylon";NA;139;0
"Unit";"Immortal";"Robotics Facility";137;4
"Unit";"Zealot";"Gateway";149;2
"Building";"Gateway";NA;137;0
"Building";"Gateway";NA;137;0
"Building";"RoboticsFacility";NA;145;0
"Building";"HighTemplar";NA;151;0
"Building";"HighTemplar";NA;151;0
"Building";"HighTemplar";NA;151;0
"Building";"HighTemplar";NA;151;0
"Building";"Pylon";NA;151;0
"Building";"Pylon";NA;151;0
"Building";"Forge";NA;151;0
"Unit";"Immortal";"Robotics Facility";151;4
"Building";"Nexus";NA;151;0
"Building";"Assimilator";NA;158;0
"Upgrade";"ProtossGroundWeaponsLevel2";"Forge";145;0
"Unit";"Immortal";"Robotics Facility";155;4
"Building";"Assimilator";NA;158;0
"Unit";"Immortal";"Robotics Facility";158;4
"Unit";"Archon";"High Templar";171;0
"Unit";"Archon";"High Templar";171;0
"Building";"Pylon";NA;171;0
"Building";"Pylon";NA;171;0
"Building";"Pylon";NA;171;0
"Building";"HighTemplar";NA;171;0
"Building";"HighTemplar";NA;171;0
"Building";"HighTemplar";NA;171;0
"Building";"HighTemplar";NA;171;0
"Building";"HighTemplar";NA;171;0
"Building";"HighTemplar";NA;171;0
"Building";"RoboticsBay";NA;171;0
"Unit";"Archon";"High Templar";171;0
"Unit";"Archon";"High Templar";171;0
"Unit";"Archon";"High Templar";171;0
"Upgrade";"ProtossGroundArmorsLevel1";"Forge";160;0
"Unit";"Immortal";"Robotics Facility";171;4
"Unit";"Immortal";"Robotics Facility";171;4
"Building";"Pylon";NA;171;0
"Building";"Gateway";NA;171;0
"Building";"Gateway";NA;171;0
"Building";"Gateway";NA;171;0
"Building";"Nexus";NA;171;0
"Upgrade";"GraviticDrive";"RoboticsBay";171;0
"Building";"Pylon";NA;179;0
"Unit";"Zealot";"Gateway";179;2
"Unit";"Zealot";"Gateway";181;2
"Unit";"Zealot";"Gateway";181;2
"Unit";"Zealot";"Gateway";181;2
"Unit";"Zealot";"Gateway";181;2
"Unit";"Zealot";"Gateway";181;2
"Unit";"Zealot";"Gateway";181;2
"Unit";"Zealot";"Gateway";196;2
"Unit";"Zealot";"Gateway";196;2
"Unit";"Zealot";"Gateway";196;2
"Building";"Assimilator";NA;181;0
"Building";"Assimilator";NA;184;0
"Unit";"Zealot";"Gateway";204;2
"Unit";"Zealot";"Gateway";204;2
"Unit";"Zealot";"Gateway";204;2
"Upgrade";"ProtossGroundWeaponsLevel3";"Forge";179;0
"Building";"Stargate";NA;210;0
"Building";"Stargate";NA;210;0
"Building";"Stargate";NA;210;0
"Unit";"Zealot";"Gateway";221;2
"Upgrade";"ProtossGroundArmorsLevel2";"Forge";181;0
"Building";"FleetBeacon";NA;215;0
"Building";"Pylon";NA;223;0
"Building";"Pylon";NA;223;0
"Unit";"Zealot";"Gateway";223;2
"Unit";"Zealot";"Gateway";223;2
"Unit";"Zealot";"Gateway";223;2
"Unit";"Zealot";"Gateway";223;2
"Unit";"Zealot";"Gateway";223;2
