"type";"unit_name";"on_building";"total_supply";"supply"
"Building";"Pylon";NA;13;0
"Building";"Assimilator";NA;16;0
"Building";"Gateway";NA;15;0
"Building";"Assimilator";NA;19;0
"Building";"CyberneticsCore";NA;18;0
"Building";"Pylon";NA;20;0
"Unit";"Adept";"Gateway";21;2
"Building";"Nexus";NA;18;0
"Unit";"Adept";"Gateway";24;2
"Building";"Stargate";NA;24;0
"Unit";"Phoenix";"Stargate";32;2
"Unit";"Adept";"Gateway";33;2
"Unit";"Phoenix";"Stargate";37;2
"Building";"Pylon";NA;42;0
"Building";"Assimilator";NA;43;0
"Building";"Assimilator";NA;44;0
"Unit";"Phoenix";"Stargate";47;2
"Building";"Pylon";NA;50;0
"Building";"Forge";NA;48;0
"Unit";"Phoenix";"Stargate";50;2
"Building";"RoboticsFacility";NA;54;0
"Building";"Pylon";NA;58;0
"Unit";"Phoenix";"Stargate";58;2
"Building";"Pylon";NA;59;0
"Building";"Pylon";NA;59;0
"Building";"Pylon";NA;60;0
"Building";"RoboticsFacility";NA;56;0
"Unit";"Observer";"Robotics Facility";61;1
"Unit";"Observer";"Robotics Facility";64;1
"Unit";"Observer";"Robotics Facility";65;1
"Building";"ShieldBattery";NA;64;0
"Building";"ShieldBattery";NA;64;0
"Unit";"Phoenix";"Stargate";66;2
"Building";"RoboticsBay";NA;61;0
"Unit";"Observer";"Robotics Facility";69;1
"Unit";"Observer";"Robotics Facility";70;1
"Unit";"Disruptor";"Robotics Facility";75;3
"Unit";"Disruptor";"Robotics Facility";75;3
"Building";"Pylon";NA;79;0
"Building";"Pylon";NA;86;0
"Building";"PhotonCannon";NA;86;0
"Unit";"Disruptor";"Robotics Facility";79;3
"Unit";"Disruptor";"Robotics Facility";79;3
"Building";"PhotonCannon";NA;86;0
"Building";"PhotonCannon";NA;86;0
"Building";"ShieldBattery";NA;86;0
"Building";"PhotonCannon";NA;86;0
"Building";"PhotonCannon";NA;86;0
"Building";"FleetBeacon";NA;86;0
"Building";"Nexus";NA;79;0
"Unit";"Disruptor";"Robotics Facility";86;3
"Unit";"Disruptor";"Robotics Facility";89;3
"Building";"Pylon";NA;98;0
"Building";"Pylon";NA;98;0
"Unit";"Tempest";"Stargate";94;4
"Building";"ShieldBattery";NA;96;0
"Building";"ShieldBattery";NA;96;0
"Building";"ShieldBattery";NA;98;0
"Building";"ShieldBattery";NA;98;0
"Building";"Assimilator";NA;106;0
"Building";"Assimilator";NA;110;0
"Unit";"Disruptor";"Robotics Facility";105;3
"Building";"Stargate";NA;110;0
"Unit";"Disruptor";"Robotics Facility";110;3
"Upgrade";"ProtossAirWeaponsLevel1";"CyberneticsCore";96;0
"Building";"Assimilator";NA;115;0
"Building";"Assimilator";NA;115;0
"Unit";"Tempest";"Stargate";113;4
"Building";"Pylon";NA;118;0
"Building";"Pylon";NA;118;0
"Building";"Pylon";NA;121;0
"Building";"Pylon";NA;121;0
"Building";"PhotonCannon";NA;121;0
"Building";"Nexus";NA;110;0
"Building";"PhotonCannon";NA;127;0
"Building";"PhotonCannon";NA;127;0
"Unit";"Disruptor";"Robotics Facility";127;3
"Unit";"Disruptor";"Robotics Facility";127;3
"Unit";"Tempest";"Stargate";126;4
"Unit";"Tempest";"Stargate";126;4
"Building";"ShieldBattery";NA;127;0
"Building";"ShieldBattery";NA;127;0
"Building";"Pylon";NA;143;0
"Unit";"Tempest";"Stargate";127;4
"Building";"ShieldBattery";NA;143;0
"Building";"TwilightCouncil";NA;143;0
"Building";"Stargate";NA;143;0
"Building";"Stargate";NA;147;0
"Upgrade";"ProtossShieldsLevel1";"Forge";143;0
"Unit";"Carrier";"Stargate";143;6
"Building";"Nexus";NA;143;0
"Upgrade";"ProtossAirWeaponsLevel2";"CyberneticsCore";129;0
"Unit";"Carrier";"Stargate";147;6
"Unit";"Carrier";"Stargate";147;6
"Building";"Assimilator";NA;160;0
"Building";"PhotonCannon";NA;153;0
"Building";"PhotonCannon";NA;160;0
"Building";"Assimilator";NA;160;0
"Building";"PhotonCannon";NA;160;0
"Building";"PhotonCannon";NA;160;0
"Building";"ShieldBattery";NA;160;0
"Building";"ShieldBattery";NA;160;0
"Unit";"Carrier";"Stargate";153;6
"Unit";"Carrier";"Stargate";153;6
"Unit";"Disruptor";"Robotics Facility";160;3
"Unit";"Disruptor";"Robotics Facility";160;3
"Building";"PhotonCannon";NA;168;0
"Building";"PhotonCannon";NA;168;0
"Building";"PhotonCannon";NA;168;0
"Unit";"Carrier";"Stargate";153;6
"Unit";"Mothership";"Mothership Core";167;6
"Unit";"Carrier";"Stargate";160;6
"Building";"PhotonCannon";NA;195;0
"Building";"PhotonCannon";NA;195;0
"Building";"PhotonCannon";NA;195;0
"Building";"PhotonCannon";NA;195;0
"Building";"PhotonCannon";NA;195;0
"Upgrade";"ProtossShieldsLevel2";"Forge";167;0
"Unit";"Carrier";"Stargate";168;6
"Building";"Pylon";NA;207;0
"Building";"Pylon";NA;207;0
"Building";"Pylon";NA;207;0
"Building";"Pylon";NA;207;0
"Building";"Pylon";NA;207;0
"Building";"PhotonCannon";NA;207;0
"Building";"Pylon";NA;207;0
"Building";"Pylon";NA;207;0
"Building";"PhotonCannon";NA;207;0
"Upgrade";"ProtossAirWeaponsLevel3";"CyberneticsCore";168;0
"Building";"PhotonCannon";NA;207;0
"Building";"PhotonCannon";NA;207;0
"Building";"PhotonCannon";NA;207;0
"Building";"PhotonCannon";NA;207;0
"Building";"PhotonCannon";NA;207;0
"Building";"ShieldBattery";NA;207;0
"Building";"ShieldBattery";NA;213;0
"Building";"ShieldBattery";NA;213;0
"Unit";"Observer";"Robotics Facility";213;1
"Unit";"Observer";"Robotics Facility";213;1
"Building";"PhotonCannon";NA;213;0
"Building";"PhotonCannon";NA;213;0
"Building";"PhotonCannon";NA;213;0
"Building";"PhotonCannon";NA;213;0
"Building";"PhotonCannon";NA;213;0
"Building";"ShieldBattery";NA;213;0
"Building";"ShieldBattery";NA;213;0
"Building";"ShieldBattery";NA;213;0
"Unit";"Observer";"Robotics Facility";213;1
"Unit";"Observer";"Robotics Facility";214;1
"Building";"Pylon";NA;217;0
"Building";"Pylon";NA;217;0
"Building";"Pylon";NA;217;0
"Building";"PhotonCannon";NA;217;0
"Building";"PhotonCannon";NA;217;0
"Building";"PhotonCannon";NA;217;0
"Building";"PhotonCannon";NA;217;0
"Building";"PhotonCannon";NA;217;0
"Building";"PhotonCannon";NA;217;0
"Building";"PhotonCannon";NA;217;0
"Building";"PhotonCannon";NA;217;0
"Building";"PhotonCannon";NA;217;0
"Building";"PhotonCannon";NA;217;0
"Building";"PhotonCannon";NA;217;0
"Building";"PhotonCannon";NA;217;0
