"type";"unit_name";"on_building";"total_supply";"supply"
"Building";"Pylon";NA;13;0
"Building";"Assimilator";NA;16;0
"Building";"Gateway";NA;15;0
"Building";"CyberneticsCore";NA;20;0
"Building";"Assimilator";NA;20;0
"Building";"Pylon";NA;21;0
"Unit";"Stalker";"Gateway";22;2
"Building";"Nexus";NA;19;0
"Unit";"Stalker";"Gateway";24;2
"Building";"ShieldBattery";NA;27;0
"Building";"TwilightCouncil";NA;27;0
"Unit";"Stalker";"Gateway";32;2
"Building";"RoboticsFacility";NA;33;0
"Building";"Gateway";NA;35;0
"Building";"Gateway";NA;36;0
"Unit";"Observer";"Robotics Facility";41;1
"Building";"Pylon";NA;43;0
"Building";"Assimilator";NA;43;0
"Building";"Assimilator";NA;43;0
"Unit";"Stalker";"Gateway";46;2
"Unit";"Stalker";"Gateway";46;2
"Unit";"Stalker";"Gateway";46;2
"Building";"Pylon";NA;45;0
"Unit";"Observer";"Robotics Facility";45;1
"Unit";"Observer";"Robotics Facility";46;1
"Building";"Pylon";NA;55;0
"Unit";"Stalker";"Gateway";60;2
"Unit";"Stalker";"Gateway";60;2
"Building";"Pylon";NA;58;0
"Unit";"Observer";"Robotics Facility";58;1
"Building";"RoboticsBay";NA;60;0
"Unit";"Disruptor";"Robotics Facility";71;3
"Building";"Pylon";NA;75;0
"Building";"Pylon";NA;80;0
"Unit";"Stalker";"Gateway";82;2
"Unit";"Disruptor";"Robotics Facility";77;3
"Unit";"Stalker";"Gateway";86;2
"Unit";"Stalker";"Gateway";88;2
"Building";"Nexus";NA;71;0
"Building";"Stargate";NA;82;0
"Unit";"Disruptor";"Robotics Facility";86;3
"Building";"Pylon";NA;97;0
"Building";"Assimilator";NA;97;0
"Unit";"Phoenix";"Stargate";97;2
"Building";"Assimilator";NA;98;0
"Unit";"Stalker";"Gateway";108;2
"Unit";"Stalker";"Gateway";108;2
"Building";"Forge";NA;98;0
"Unit";"Disruptor";"Robotics Facility";101;3
"Unit";"Stalker";"Gateway";124;2
"Unit";"Stalker";"Gateway";124;2
"Building";"Pylon";NA;118;0
"Unit";"Disruptor";"Robotics Facility";118;3
"Building";"Pylon";NA;128;0
"Building";"FleetBeacon";NA;118;0
"Building";"Forge";NA;129;0
"Building";"Pylon";NA;132;0
"Building";"PhotonCannon";NA;132;0
"Building";"PhotonCannon";NA;132;0
"Building";"Pylon";NA;135;0
"Building";"Pylon";NA;135;0
"Building";"Pylon";NA;135;0
"Unit";"Tempest";"Stargate";134;4
"Upgrade";"ProtossGroundWeaponsLevel1";"Forge";124;0
"Building";"Stargate";NA;135;0
"Building";"Stargate";NA;135;0
"Building";"Assimilator";NA;135;0
"Building";"Pylon";NA;135;0
"Building";"Assimilator";NA;135;0
"Unit";"Disruptor";"Robotics Facility";135;3
"Building";"PhotonCannon";NA;135;0
"Building";"PhotonCannon";NA;135;0
"Building";"ShieldBattery";NA;135;0
"Building";"PhotonCannon";NA;139;0
"Building";"Nexus";NA;135;0
"Unit";"Adept";"Gateway";144;2
"Unit";"Adept";"Gateway";144;2
"Unit";"Adept";"Gateway";144;2
"Unit";"Tempest";"Stargate";139;4
"Unit";"Tempest";"Stargate";139;4
"Unit";"Tempest";"Stargate";140;4
"Building";"Pylon";NA;144;0
"Building";"Pylon";NA;144;0
"Building";"Pylon";NA;159;0
"Unit";"Disruptor";"Robotics Facility";144;3
"Unit";"Adept";"Gateway";163;2
"Unit";"Adept";"Gateway";163;2
"Unit";"Adept";"Gateway";163;2
"Building";"TemplarArchive";NA;144;0
"Upgrade";"Charge";"TwilightCouncil";140;0
"Upgrade";"ProtossGroundArmorsLevel1";"Forge";140;0
"Building";"PhotonCannon";NA;173;0
"Building";"PhotonCannon";NA;173;0
"Upgrade";"ProtossAirWeaponsLevel1";"CyberneticsCore";144;0
"Building";"Pylon";NA;176;0
"Unit";"Carrier";"Stargate";144;6
"Unit";"Carrier";"Stargate";144;6
"Building";"PhotonCannon";NA;176;0
"Building";"Gateway";NA;176;0
"Building";"Gateway";NA;176;0
"Building";"PhotonCannon";NA;182;0
"Unit";"Oracle";"Stargate";176;3
"Building";"ShieldBattery";NA;182;0
"Building";"Gateway";NA;176;0
"Building";"Gateway";NA;176;0
"Unit";"Adept";"Gateway";191;2
"Unit";"Adept";"Gateway";191;2
"Unit";"Adept";"Gateway";191;2
"Unit";"Tempest";"Stargate";188;4
"Unit";"Tempest";"Stargate";188;4
"Upgrade";"ProtossGroundWeaponsLevel2";"Forge";176;0
"Unit";"Tempest";"Stargate";191;4
"Upgrade";"ProtossShieldsLevel1";"Forge";188;0
"Unit";"Adept";"Gateway";209;2
"Unit";"Adept";"Gateway";209;2
"Unit";"Adept";"Gateway";209;2
"Unit";"Adept";"Gateway";209;2
"Unit";"Adept";"Gateway";217;2
"Unit";"Adept";"Gateway";217;2
"Unit";"Adept";"Gateway";217;2
"Unit";"Oracle";"Stargate";217;3
"Unit";"Tempest";"Stargate";217;4
"Unit";"Tempest";"Stargate";217;4
"Unit";"Tempest";"Stargate";226;4
"Building";"Assimilator";NA;238;0
"Building";"Pylon";NA;238;0
"Building";"Assimilator";NA;238;0
"Building";"Pylon";NA;238;0
"Unit";"Adept";"Gateway";238;2
"Unit";"Adept";"Gateway";238;2
"Unit";"Adept";"Gateway";238;2
"Unit";"Adept";"Gateway";238;2
"Unit";"Adept";"Gateway";238;2
"Unit";"Adept";"Gateway";238;2
"Unit";"Adept";"Gateway";238;2
"Building";"Nexus";NA;234;0
"Unit";"Carrier";"Stargate";238;6
"Unit";"Carrier";"Stargate";238;6
"Unit";"Carrier";"Stargate";238;6
"Unit";"Oracle";"Stargate";279;3
"Unit";"Tempest";"Stargate";279;4
"Unit";"Carrier";"Stargate";279;6
"Unit";"Carrier";"Stargate";279;6
"Upgrade";"ProtossShieldsLevel2";"Forge";279;0
"Building";"HighTemplar";NA;299;0
"Building";"HighTemplar";NA;299;0
"Building";"HighTemplar";NA;299;0
"Building";"HighTemplar";NA;299;0
"Building";"HighTemplar";NA;299;0
"Building";"HighTemplar";NA;299;0
"Building";"HighTemplar";NA;299;0
"Upgrade";"ProtossGroundWeaponsLevel3";"Forge";279;0
"Unit";"Observer";"Robotics Facility";299;1
"Upgrade";"ProtossAirWeaponsLevel2";"CyberneticsCore";282;0
"Unit";"Tempest";"Stargate";299;4
"Unit";"Tempest";"Stargate";299;4
"Unit";"Tempest";"Stargate";299;4
"Unit";"Adept";"Gateway";313;2
"Unit";"Adept";"Gateway";313;2
"Unit";"Adept";"Gateway";313;2
"Unit";"Adept";"Gateway";313;2
"Unit";"Adept";"Gateway";313;2
"Unit";"Adept";"Gateway";313;2
"Unit";"Adept";"Gateway";313;2
"Unit";"Disruptor";"Robotics Facility";301;3
"Unit";"Adept";"Gateway";330;2
"Unit";"Adept";"Gateway";330;2
"Unit";"Adept";"Gateway";330;2
"Unit";"Adept";"Gateway";330;2
"Unit";"Adept";"Gateway";330;2
"Unit";"Adept";"Gateway";330;2
"Unit";"Adept";"Gateway";330;2
"Unit";"Observer";"Robotics Facility";327;1
"Unit";"Tempest";"Stargate";327;4
"Building";"Pylon";NA;345;0
"Building";"Pylon";NA;345;0
"Building";"Pylon";NA;345;0
"Unit";"Adept";"Gateway";350;2
"Unit";"Adept";"Gateway";350;2
"Unit";"Adept";"Gateway";350;2
"Unit";"Adept";"Gateway";350;2
"Unit";"Adept";"Gateway";350;2
"Unit";"Adept";"Gateway";350;2
"Unit";"Adept";"Gateway";350;2
"Upgrade";"ProtossShieldsLevel3";"Forge";301;0
"Upgrade";"ProtossGroundArmorsLevel2";"Forge";327;0
"Building";"Nexus";NA;330;0
"Building";"Assimilator";NA;364;0
"Building";"Nexus";NA;330;0
"Building";"Assimilator";NA;364;0
"Unit";"Stalker";"Gateway";364;2
"Unit";"Stalker";"Gateway";364;2
"Building";"PhotonCannon";NA;364;0
"Building";"PhotonCannon";NA;364;0
"Unit";"Adept";"Gateway";368;2
"Unit";"Adept";"Gateway";368;2
"Building";"PhotonCannon";NA;364;0
"Building";"Pylon";NA;364;0
"Unit";"Adept";"Gateway";374;2
"Unit";"Adept";"Gateway";374;2
"Unit";"Adept";"Gateway";374;2
"Building";"PhotonCannon";NA;364;0
"Building";"Pylon";NA;364;0
"Building";"Pylon";NA;364;0
"Building";"PhotonCannon";NA;364;0
"Building";"CyberneticsCore";NA;364;0
"Unit";"Tempest";"Stargate";381;4
"Unit";"Tempest";"Stargate";381;4
"Unit";"Tempest";"Stargate";381;4
"Upgrade";"ProtossAirWeaponsLevel3";"CyberneticsCore";374;0
"Unit";"Tempest";"Stargate";393;4
"Upgrade";"ProtossAirArmorsLevel1";"CyberneticsCore";393;0
"Building";"Nexus";NA;393;0
"Unit";"Oracle";"Stargate";393;3
"Building";"Assimilator";NA;397;0
"Building";"Pylon";NA;397;0
"Building";"Assimilator";NA;397;0
"Unit";"Adept";"Gateway";400;2
"Unit";"Adept";"Gateway";400;2
"Unit";"Adept";"Gateway";400;2
"Unit";"Adept";"Gateway";400;2
"Unit";"Adept";"Gateway";400;2
"Unit";"Adept";"Gateway";400;2
"Unit";"Adept";"Gateway";400;2
"Upgrade";"ProtossGroundArmorsLevel3";"Forge";393;0
"Building";"Pylon";NA;400;0
"Building";"Pylon";NA;400;0
"Unit";"Carrier";"Stargate";393;6
"Unit";"Adept";"Gateway";420;2
"Unit";"Adept";"Gateway";420;2
"Unit";"Adept";"Gateway";420;2
"Unit";"Adept";"Gateway";420;2
"Unit";"Adept";"Gateway";420;2
"Unit";"Adept";"Gateway";420;2
"Unit";"Adept";"Gateway";420;2
"Unit";"Archon";"High Templar";420;0
"Unit";"Archon";"High Templar";420;0
"Unit";"Disruptor";"Robotics Facility";414;3
