"type";"unit_name";"on_building";"total_supply";"supply"
"Building";"Pylon";NA;14;0
"Building";"Pylon";NA;17;0
"Building";"Forge";NA;15;0
"Building";"PhotonCannon";NA;19;0
"Building";"PhotonCannon";NA;19;0
"Building";"Pylon";NA;22;0
"Building";"PhotonCannon";NA;21;0
"Building";"Assimilator";NA;23;0
"Building";"Gateway";NA;21;0
"Building";"Assimilator";NA;23;0
"Building";"PhotonCannon";NA;23;0
"Building";"Pylon";NA;25;0
"Building";"CyberneticsCore";NA;27;0
"Building";"Gateway";NA;27;0
"Unit";"Stalker";"Gateway";28;2
"Unit";"Stalker";"Gateway";29;2
"Building";"Nexus";NA;27;0
"Building";"RoboticsFacility";NA;30;0
"Building";"ShieldBattery";NA;36;0
"Building";"ShieldBattery";NA;37;0
"Building";"Stargate";NA;36;0
"Unit";"Immortal";"Robotics Facility";37;4
"Building";"ShieldBattery";NA;41;0
"Building";"Pylon";NA;41;0
"Unit";"Phoenix";"Stargate";43;2
"Building";"Pylon";NA;47;0
"Unit";"Observer";"Robotics Facility";47;1
"Unit";"Stalker";"Gateway";53;2
"Unit";"Stalker";"Gateway";53;2
"Unit";"Phoenix";"Stargate";48;2
"Building";"Assimilator";NA;57;0
"Building";"Assimilator";NA;57;0
"Unit";"Stalker";"Gateway";61;2
"Unit";"Immortal";"Robotics Facility";53;4
"Unit";"Phoenix";"Stargate";61;2
"Unit";"Phoenix";"Stargate";67;2
"Building";"Pylon";NA;70;0
"Unit";"Immortal";"Robotics Facility";67;4
"Building";"Pylon";NA;72;0
"Building";"ShieldBattery";NA;70;0
"Building";"Gateway";NA;70;0
"Building";"Gateway";NA;70;0
"Building";"Gateway";NA;70;0
"Building";"Pylon";NA;76;0
"Building";"Pylon";NA;77;0
"Building";"Pylon";NA;77;0
"Building";"RoboticsBay";NA;76;0
"Unit";"Observer";"Robotics Facility";79;1
"Building";"Assimilator";NA;79;0
"Building";"Assimilator";NA;79;0
"Building";"RoboticsFacility";NA;79;0
"Building";"PhotonCannon";NA;79;0
"Building";"PhotonCannon";NA;79;0
"Building";"PhotonCannon";NA;79;0
"Building";"ShieldBattery";NA;79;0
"Building";"Nexus";NA;77;0
"Unit";"Phoenix";"Stargate";82;2
"Building";"Pylon";NA;88;0
"Unit";"Disruptor";"Robotics Facility";87;3
"Unit";"Disruptor";"Robotics Facility";87;3
"Building";"Pylon";NA;88;0
"Unit";"Disruptor";"Robotics Facility";88;3
"Building";"Stargate";NA;88;0
"Building";"Stargate";NA;88;0
"Building";"FleetBeacon";NA;88;0
"Unit";"Disruptor";"Robotics Facility";94;3
"Building";"Stargate";NA;88;0
"Building";"Pylon";NA;97;0
"Building";"Pylon";NA;97;0
"Building";"Pylon";NA;97;0
"Building";"Pylon";NA;100;0
"Building";"Assimilator";NA;100;0
"Building";"Assimilator";NA;100;0
"Building";"Pylon";NA;103;0
"Unit";"Disruptor";"Robotics Facility";100;3
"Unit";"Disruptor";"Robotics Facility";100;3
"Building";"CyberneticsCore";NA;103;0
"Unit";"Stalker";"Gateway";112;2
"Unit";"Stalker";"Gateway";112;2
"Unit";"Stalker";"Gateway";112;2
"Unit";"Stalker";"Gateway";112;2
"Building";"PhotonCannon";NA;103;0
"Building";"PhotonCannon";NA;106;0
"Building";"PhotonCannon";NA;106;0
"Building";"ShieldBattery";NA;106;0
"Building";"ShieldBattery";NA;106;0
"Building";"Nexus";NA;94;0
"Upgrade";"ProtossAirWeaponsLevel1";"CyberneticsCore";94;0
"Unit";"Tempest";"Stargate";120;4
"Unit";"Tempest";"Stargate";120;4
"Unit";"Tempest";"Stargate";123;4
"Upgrade";"ProtossAirArmorsLevel1";"CyberneticsCore";123;0
"Unit";"Tempest";"Stargate";138;4
"Unit";"Tempest";"Stargate";138;4
"Unit";"Tempest";"Stargate";138;4
"Building";"Pylon";NA;142;0
"Building";"Pylon";NA;142;0
"Building";"Assimilator";NA;142;0
"Building";"Stargate";NA;142;0
"Building";"Stargate";NA;142;0
"Building";"Assimilator";NA;142;0
"Building";"TwilightCouncil";NA;142;0
"Upgrade";"ProtossShieldsLevel1";"Forge";138;0
"Upgrade";"ProtossAirWeaponsLevel2";"CyberneticsCore";138;0
"Building";"PhotonCannon";NA;154;0
"Building";"PhotonCannon";NA;154;0
"Building";"Nexus";NA;142;0
"Unit";"Carrier";"Stargate";154;6
"Unit";"Carrier";"Stargate";154;6
"Unit";"Carrier";"Stargate";154;6
"Upgrade";"ProtossAirArmorsLevel2";"CyberneticsCore";154;0
"Unit";"Carrier";"Stargate";154;6
"Building";"PhotonCannon";NA;154;0
"Building";"PhotonCannon";NA;154;0
"Building";"ShieldBattery";NA;154;0
"Building";"ShieldBattery";NA;154;0
"Unit";"Carrier";"Stargate";154;6
"Unit";"Carrier";"Stargate";154;6
"Building";"TemplarArchive";NA;178;0
"Building";"HighTemplar";NA;190;0
"Building";"HighTemplar";NA;190;0
"Building";"HighTemplar";NA;190;0
"Building";"HighTemplar";NA;190;0
"Unit";"Mothership";"Mothership Core";154;6
"Unit";"Observer";"Robotics Facility";190;1
"Unit";"Observer";"Robotics Facility";190;1
"Building";"HighTemplar";NA;198;0
"Building";"HighTemplar";NA;198;0
"Building";"HighTemplar";NA;198;0
"Building";"HighTemplar";NA;198;0
"Upgrade";"ProtossShieldsLevel2";"Forge";172;0
"Unit";"Observer";"Robotics Facility";198;1
"Upgrade";"ProtossAirWeaponsLevel3";"CyberneticsCore";154;0
"Building";"PhotonCannon";NA;198;0
"Building";"PhotonCannon";NA;198;0
"Building";"ShieldBattery";NA;198;0
"Unit";"Carrier";"Stargate";184;6
"Building";"Pylon";NA;199;0
"Building";"Pylon";NA;199;0
"Building";"Assimilator";NA;205;0
"Building";"Assimilator";NA;205;0
"Upgrade";"ProtossAirArmorsLevel3";"CyberneticsCore";190;0
"Building";"Nexus";NA;199;0
"Building";"Pylon";NA;205;0
"Unit";"Carrier";"Stargate";199;6
"Unit";"Carrier";"Stargate";199;6
"Building";"PhotonCannon";NA;205;0
"Building";"PhotonCannon";NA;205;0
"Building";"PhotonCannon";NA;217;0
"Unit";"Carrier";"Stargate";205;6
"Unit";"Carrier";"Stargate";205;6
"Building";"ShieldBattery";NA;217;0
"Building";"ShieldBattery";NA;217;0
"Building";"PhotonCannon";NA;217;0
"Unit";"Observer";"Robotics Facility";229;1
"Unit";"Observer";"Robotics Facility";229;1
"Unit";"Oracle";"Stargate";229;3
"Upgrade";"ProtossShieldsLevel3";"Forge";217;0
