"type";"unit_name";"on_building";"total_supply_lag";"supply"
"Building";"Pylon";NA;14;0
"Building";"Gateway";NA;16;0
"Building";"Assimilator";NA;17;0
"Building";"Pylon";NA;20;0
"Building";"CyberneticsCore";NA;20;0
"Unit";"Zealot";"Gateway";20;2
"Unit";"Stalker";"Gateway";23;2
"Building";"Nexus";NA;25;0
"Building";"Assimilator";NA;26;0
"Unit";"Stalker";"Gateway";27;2
"Building";"Pylon";NA;29;0
"Building";"TwilightCouncil";NA;31;0
"Building";"RoboticsFacility";NA;36;0
"Building";"Gateway";NA;40;0
"Building";"Gateway";NA;40;0
"Unit";"Observer";"Robotics Facility";43;1
"Unit";"Stalker";"Gateway";45;2
"Building";"Pylon";NA;47;0
"Building";"Assimilator";NA;47;0
"Unit";"Observer";"Robotics Facility";49;1
"Unit";"Stalker";"Gateway";52;2
"Unit";"Stalker";"Gateway";54;2
"Unit";"Stalker";"Gateway";56;2
"Building";"Nexus";NA;60;0
"Building";"Gateway";NA;61;0
"Building";"Gateway";NA;61;0
"Building";"Gateway";NA;61;0
"Building";"Gateway";NA;61;0
"Upgrade";"Charge";"TwilightCouncil";63;0
"Building";"Gateway";NA;63;0
"Building";"Pylon";NA;63;0
"Unit";"Immortal";"Robotics Facility";63;4
"Building";"Pylon";NA;69;0
"Unit";"Sentry";"Gateway";69;2
"Unit";"Sentry";"Gateway";74;2
"Unit";"Zealot";"Gateway";76;2
"Building";"Pylon";NA;78;0
"Unit";"Immortal";"Robotics Facility";78;4
"Unit";"Zealot";"Gateway";82;2
"Unit";"Zealot";"Gateway";84;2
"Unit";"Zealot";"Gateway";86;2
"Building";"Pylon";NA;88;0
"Unit";"Stalker";"Gateway";88;2
"Unit";"Stalker";"Gateway";90;2
"Unit";"Stalker";"Gateway";92;2
"Unit";"Zealot";"Gateway";94;2
"Unit";"Zealot";"Gateway";96;2
"Unit";"Zealot";"Gateway";98;2
"Unit";"Zealot";"Gateway";100;2
"Building";"Pylon";NA;105;0
"Building";"Pylon";NA;106;0
"Unit";"Immortal";"Robotics Facility";106;4
"Building";"Pylon";NA;112;0
"Unit";"Phoenix";"Stargate";112;2
"Building";"Forge";NA;114;0
"Building";"Forge";NA;114;0
"Unit";"Zealot";"Gateway";117;2
"Unit";"Zealot";"Gateway";119;2
"Unit";"Zealot";"Gateway";121;2
"Unit";"Zealot";"Gateway";123;2
"Unit";"Zealot";"Gateway";125;2
"Unit";"Zealot";"Gateway";127;2
"Unit";"Zealot";"Gateway";129;2
"Building";"Pylon";NA;131;0
"Building";"TemplarArchive";NA;131;0
"Building";"Assimilator";NA;134;0
"Upgrade";"ProtossGroundWeaponsLevel1";"Forge";134;0
"Building";"Assimilator";NA;134;0
"Building";"Assimilator";NA;135;0
"Unit";"Zealot";"Gateway";135;2
"Unit";"Zealot";"Gateway";137;2
"Unit";"Zealot";"Gateway";139;2
"Unit";"Zealot";"Gateway";141;2
"Unit";"Zealot";"Gateway";143;2
"Unit";"Zealot";"Gateway";145;2
"Unit";"Zealot";"Gateway";147;2
"Unit";"Zealot";"Gateway";149;2
"Unit";"Immortal";"Robotics Facility";151;4
"Building";"Pylon";NA;155;0
"Unit";"Stalker";"Gateway";155;2
"Unit";"Stalker";"Gateway";157;2
"Unit";"Stalker";"Gateway";159;2
"Unit";"Stalker";"Gateway";161;2
"Unit";"Stalker";"Gateway";163;2
"Unit";"Stalker";"Gateway";165;2
"Unit";"Stalker";"Gateway";167;2
"Unit";"Stalker";"Gateway";169;2
"Unit";"Immortal";"Robotics Facility";171;4
"Unit";"Zealot";"Gateway";175;2
"Unit";"Zealot";"Gateway";177;2
"Unit";"Zealot";"Gateway";179;2
"Unit";"Zealot";"Gateway";181;2
"Unit";"Zealot";"Gateway";183;2
"Unit";"Zealot";"Gateway";185;2
"Unit";"Zealot";"Gateway";187;2
"Upgrade";"ProtossGroundWeaponsLevel2";"Forge";189;0
"Unit";"Zealot";"Gateway";189;2
"Unit";"Zealot";"Gateway";191;2
"Building";"HighTemplar";NA;193;0
"Building";"HighTemplar";NA;193;0
"Building";"HighTemplar";NA;193;0
"Unit";"Zealot";"Gateway";193;2
"Unit";"Zealot";"Gateway";195;2
"Unit";"Zealot";"Gateway";197;2
"Unit";"Immortal";"Robotics Facility";199;4
"Building";"Nexus";NA;204;0
"Unit";"Zealot";"Gateway";204;2
"Unit";"Zealot";"Gateway";206;2
"Unit";"Stalker";"Gateway";208;2
"Unit";"Stalker";"Gateway";210;2
"Unit";"Stalker";"Gateway";212;2
"Unit";"Zealot";"Gateway";214;2
"Unit";"Zealot";"Gateway";216;2
"Unit";"Zealot";"Gateway";218;2
"Unit";"Archon";"High Templar";220;0
"Unit";"Stalker";"Gateway";220;2
"Unit";"Stalker";"Gateway";222;2
"Unit";"Stalker";"Gateway";224;2
"Building";"HighTemplar";NA;226;0
"Building";"HighTemplar";NA;226;0
"Building";"Assimilator";NA;226;0
"Unit";"Stalker";"Gateway";226;2
"Unit";"Stalker";"Gateway";228;2
"Unit";"Stalker";"Gateway";230;2
"Building";"Pylon";NA;233;0
"Unit";"Stalker";"Gateway";233;2
"Unit";"Stalker";"Gateway";235;2
"Unit";"Stalker";"Gateway";237;2
"Unit";"Immortal";"Robotics Facility";239;4
"Building";"Pylon";NA;244;0
"Unit";"Stalker";"Gateway";244;2
"Unit";"Stalker";"Gateway";246;2
"Unit";"Stalker";"Gateway";248;2
"Upgrade";"ProtossShieldsLevel1";"Forge";250;0
"Unit";"Stalker";"Gateway";250;2
"Unit";"Stalker";"Gateway";252;2
"Unit";"Stalker";"Gateway";254;2
"Building";"HighTemplar";NA;256;0
"Building";"HighTemplar";NA;256;0
"Unit";"Zealot";"Gateway";257;2
"Unit";"Zealot";"Gateway";259;2
"Unit";"Zealot";"Gateway";261;2
"Unit";"Zealot";"Gateway";263;2
"Unit";"Zealot";"Gateway";265;2
"Unit";"Zealot";"Gateway";267;2
"Unit";"Zealot";"Gateway";269;2
"Unit";"Zealot";"Gateway";271;2
"Unit";"Archon";"High Templar";273;0
"Unit";"Immortal";"Robotics Facility";273;4
"Unit";"Zealot";"Gateway";277;2
"Unit";"Zealot";"Gateway";279;2
"Unit";"Zealot";"Gateway";281;2
"Unit";"Zealot";"Gateway";283;2
"Unit";"Zealot";"Gateway";285;2
"Unit";"Zealot";"Gateway";287;2
"Unit";"Zealot";"Gateway";289;2
"Unit";"Zealot";"Gateway";291;2
"Unit";"Immortal";"Robotics Facility";293;4
"Unit";"Zealot";"Gateway";297;2
"Unit";"Zealot";"Gateway";299;2
"Unit";"Zealot";"Gateway";301;2
"Unit";"Zealot";"Gateway";303;2
"Unit";"Zealot";"Gateway";305;2
"Unit";"Zealot";"Gateway";307;2
"Unit";"Zealot";"Gateway";309;2
"Unit";"Zealot";"Gateway";311;2
"Unit";"Zealot";"Gateway";313;2
"Unit";"Zealot";"Gateway";315;2
"Unit";"Zealot";"Gateway";317;2
"Unit";"Zealot";"Gateway";319;2
"Unit";"Zealot";"Gateway";321;2
"Unit";"Zealot";"Gateway";323;2
"Unit";"Zealot";"Gateway";325;2
"Unit";"Zealot";"Gateway";327;2
"Building";"Nexus";NA;329;0
"Unit";"Immortal";"Robotics Facility";329;4
"Building";"Pylon";NA;333;0
"Unit";"Zealot";"Gateway";333;2
"Unit";"Zealot";"Gateway";335;2
"Unit";"Zealot";"Gateway";337;2
"Unit";"Zealot";"Gateway";339;2
"Unit";"Zealot";"Gateway";341;2
"Unit";"Zealot";"Gateway";343;2
"Unit";"Zealot";"Gateway";345;2
"Unit";"Zealot";"Gateway";347;2
"Unit";"Stalker";"Gateway";349;2
"Unit";"Stalker";"Gateway";351;2
"Unit";"Stalker";"Gateway";353;2
"Unit";"Stalker";"Gateway";355;2
"Unit";"Stalker";"Gateway";357;2
"Building";"Gateway";NA;359;0
"Building";"Gateway";NA;359;0
"Building";"Gateway";NA;359;0
"Building";"HighTemplar";NA;359;0
"Building";"HighTemplar";NA;359;0
"Building";"HighTemplar";NA;359;0
"Building";"HighTemplar";NA;359;0
"Building";"HighTemplar";NA;359;0
"Unit";"Immortal";"Robotics Facility";359;4
"Building";"PhotonCannon";NA;363;0
"Building";"Pylon";NA;363;0
"Unit";"Zealot";"Gateway";363;2
"Unit";"Zealot";"Gateway";365;2
"Unit";"Zealot";"Gateway";367;2
"Unit";"Zealot";"Gateway";369;2
"Unit";"Immortal";"Robotics Facility";371;4
"Building";"HighTemplar";NA;375;0
"Building";"HighTemplar";NA;375;0
"Building";"HighTemplar";NA;375;0
"Building";"HighTemplar";NA;375;0
"Unit";"Archon";"High Templar";375;0
"Unit";"Archon";"High Templar";375;0
"Building";"HighTemplar";NA;375;0
"Building";"HighTemplar";NA;375;0
"Building";"HighTemplar";NA;375;0
"Building";"HighTemplar";NA;375;0
"Building";"Pylon";NA;375;0
"Building";"ShieldBattery";NA;375;0
"Unit";"Archon";"High Templar";375;0
"Unit";"Archon";"High Templar";375;0
"Building";"Pylon";NA;379;0
"Unit";"Stalker";"Gateway";380;2
"Unit";"Stalker";"Gateway";382;2
"Unit";"Stalker";"Gateway";384;2
"Unit";"Stalker";"Gateway";386;2
"Unit";"Zealot";"Gateway";388;2
"Building";"Pylon";NA;391;0
"Building";"HighTemplar";NA;391;0
"Building";"HighTemplar";NA;391;0
"Building";"HighTemplar";NA;391;0
"Building";"HighTemplar";NA;391;0
"Building";"HighTemplar";NA;391;0
"Building";"HighTemplar";NA;391;0
"Unit";"Zealot";"Gateway";391;2
"Unit";"Archon";"High Templar";393;0
"Unit";"Archon";"High Templar";393;0
"Unit";"Archon";"High Templar";393;0
"Upgrade";"SprayProtoss";NA;393;0
"Upgrade";"SprayProtoss";NA;393;0
"Upgrade";"WarpGateResearch";NA;393;0
"Upgrade";"SprayProtoss";NA;393;0
"Upgrade";"BlinkTech";NA;393;0
"Upgrade";"SprayProtoss";NA;393;0
"Upgrade";"ProtossGroundArmorsLevel1";NA;393;0
"Upgrade";"PsiStormTech";NA;393;0
"Upgrade";"SprayProtoss";NA;393;0
"Upgrade";"SprayProtoss";NA;393;0
"Upgrade";"ProtossGroundArmorsLevel2";NA;393;0
"Upgrade";"SprayProtoss";NA;393;0
"Upgrade";"ProtossGroundArmorsLevel3";NA;393;0
"Upgrade";"SprayProtoss";NA;393;0
