"Type";"UnitName";"OnBuilding";"TotalSupply";"Supply"
"Unit";"SCV";"Command Center";12;1
"Unit";"SCV";"Command Center";12;1
"Unit";"SCV";"Command Center";13;1
"Building";"SupplyDepot";NA;13;0
"Unit";"SCV";"Command Center";15;1
"Unit";"SCV";"Command Center";15;1
"Building";"Refinery";NA;15;0
"Unit";"SCV";"Command Center";16;1
"Building";"Barracks";NA;15;0
"Unit";"SCV";"Command Center";18;1
"Unit";"Marine";"Barracks";18;1
"Building";"BarracksTechLab";NA;20;0
"Unit";"SCV";"Command Center";20;1
"Unit";"Marauder";"Barracks";20;2
"Building";"SupplyDepot";NA;20;0
"Unit";"SCV";"Command Center";23;1
"Unit";"Marauder";"Barracks";23;2
"Unit";"SCV";"Command Center";23;1
"Building";"CommandCenter";NA;19;0
"Unit";"Marine";"Barracks";24;1
"Unit";"SCV";"Command Center";27;1
"Unit";"SCV";"Command Center";29;1
"Unit";"Marine";"Barracks";27;1
"Unit";"SCV";"Command Center";29;1
"Unit";"SCV";"Command Center";29;1
"Building";"Barracks";NA;27;0
"Unit";"Marine";"Barracks";30;1
"Building";"CommandCenter";NA;23;0
"Unit";"SCV";"Command Center";33;1
"Unit";"SCV";"Command Center";33;1
"Building";"Barracks";NA;29;0
"Unit";"Marine";"Barracks";34;1
"Unit";"SCV";"Command Center";34;1
"Unit";"SCV";"Command Center";36;1
"Building";"Refinery";NA;34;0
"Unit";"SCV";"Command Center";37;1
"Unit";"SCV";"Command Center";38;1
"Building";"BarracksReactor";NA;34;0
"Building";"BarracksTechLab";NA;36;0
"Unit";"Marine";"Barracks";36;1
"Unit";"SCV";"Command Center";39;1
"Unit";"SCV";"Command Center";40;1
"Unit";"SCV";"Command Center";42;1
"Unit";"Marine";"Barracks";41;1
"Unit";"Marine";"Barracks";41;1
"Unit";"Marine";"Barracks";41;1
"Unit";"Marine";"Barracks";42;1
"Unit";"SCV";"Command Center";42;1
"Unit";"SCV";"Command Center";43;1
"Unit";"SCV";"Command Center";45;1
"Building";"EngineeringBay";NA;42;0
"Building";"EngineeringBay";NA;42;0
"Building";"Refinery";NA;43;0
"Building";"Refinery";NA;43;0
"Unit";"SCV";"Command Center";49;1
"Unit";"SCV";"Command Center";50;1
"Unit";"Marine";"Barracks";45;1
"Unit";"SCV";"Command Center";51;1
"Building";"Factory";NA;40;0
"Unit";"SCV";"Command Center";53;1
"Unit";"SCV";"Command Center";54;1
"Unit";"Marine";"Barracks";52;1
"Unit";"Marine";"Barracks";52;1
"Unit";"Marine";"Barracks";52;1
"Building";"SupplyDepot";NA;52;0
"Building";"SupplyDepot";NA;52;0
"Unit";"SCV";"Command Center";61;1
"Unit";"SCV";"Command Center";61;1
"Unit";"SCV";"Command Center";61;1
"Unit";"Marine";"Barracks";61;1
"Unit";"Marine";"Barracks";61;1
"Unit";"SCV";"Command Center";61;1
"Unit";"SCV";"Command Center";62;1
"Unit";"SCV";"Command Center";62;1
"Building";"SupplyDepot";NA;61;0
"Unit";"Marine";"Barracks";64;1
"Unit";"Marine";"Barracks";66;1
"Unit";"SCV";"Command Center";66;1
"Unit";"SCV";"Command Center";67;1
"Unit";"Marine";"Barracks";66;1
"Unit";"Marine";"Barracks";66;1
"Unit";"SCV";"Command Center";69;1
"Upgrade";"Stimpack";"TechLab";42;0
"Building";"Starport";NA;61;0
"Building";"FactoryReactor";NA;61;0
"Building";"SupplyDepot";NA;69;0
"Building";"SupplyDepot";NA;69;0
"Unit";"SCV";"Command Center";71;1
"Unit";"SCV";"Command Center";72;1
"Unit";"SCV";"Command Center";76;1
"Unit";"Marine";"Barracks";76;1
"Unit";"Marine";"Barracks";76;1
"Unit";"SCV";"Command Center";78;1
"Unit";"Marauder";"Barracks";76;2
"Unit";"Marauder";"Barracks";76;2
"Unit";"SCV";"Command Center";78;1
"Unit";"SCV";"Command Center";78;1
"Unit";"SCV";"Command Center";82;1
"Unit";"SCV";"Command Center";86;1
"Unit";"Marine";"Barracks";79;1
"Unit";"SCV";"Command Center";88;1
"Unit";"Marauder";"Barracks";82;2
"Unit";"SCV";"Command Center";91;1
"Unit";"SCV";"Command Center";91;1
"Unit";"Marine";"Barracks";89;1
"Unit";"Marauder";"Barracks";88;2
"Unit";"SCV";"Command Center";92;1
"Unit";"Medivac";"Starport";87;2
"Unit";"Medivac";"Starport";87;2
"Unit";"SCV";"Command Center";94;1
"Building";"SupplyDepot";NA;92;0
"Building";"FactoryReactor";NA;88;0
"Unit";"Marine";"Barracks";94;1
"Building";"SupplyDepot";NA;94;0
"Unit";"Marauder";"Barracks";94;2
"Upgrade";"TerranInfantryWeaponsLevel1";"EngineeringBay";69;0
"Upgrade";"TerranInfantryArmorsLevel1";"EngineeringBay";69;0
"Building";"Armory";NA;88;0
"Unit";"SCV";"Command Center";105;1
"Unit";"SCV";"Command Center";105;1
"Unit";"SCV";"Command Center";105;1
"Building";"SupplyDepot";NA;100;0
"Building";"Barracks";NA;88;0
"Building";"Barracks";NA;88;0
"Building";"SupplyDepot";NA;104;0
"Unit";"Marine";"Barracks";105;1
"Unit";"Marauder";"Barracks";105;2
"Unit";"Medivac";"Starport";105;2
"Unit";"SCV";"Command Center";112;1
"Unit";"Medivac";"Starport";106;2
"Unit";"Marine";"Barracks";111;1
"Building";"BarracksTechLab";NA;111;0
"Unit";"Marauder";"Barracks";111;2
"Building";"Refinery";NA;112;0
"Building";"Refinery";NA;112;0
"Unit";"Marauder";"Barracks";112;2
"Unit";"SCV";"Command Center";120;1
"Unit";"Marine";"Barracks";114;1
"Building";"BarracksReactor";NA;111;0
"Unit";"Marine";"Barracks";122;1
"Unit";"Marine";"Barracks";122;1
"Unit";"Marine";"Barracks";122;1
"Unit";"Marine";"Barracks";122;1
"Building";"Starport";NA;114;0
"Unit";"Marine";"Barracks";126;1
"Unit";"Marine";"Barracks";126;1
"Unit";"Marine";"Barracks";126;1
"Unit";"Marine";"Barracks";126;1
"Unit";"Marine";"Barracks";127;1
"Unit";"SCV";"Command Center";130;1
"Building";"SupplyDepot";NA;126;0
"Unit";"SCV";"Command Center";130;1
"Building";"SupplyDepot";NA;129;0
"Building";"SupplyDepot";NA;129;0
"Unit";"Marine";"Barracks";130;1
"Unit";"Marauder";"Barracks";130;2
"Unit";"Marine";"Barracks";137;1
"Unit";"Marine";"Barracks";137;1
"Unit";"Marine";"Barracks";137;1
"Unit";"Marine";"Barracks";137;1
"Unit";"Marauder";"Barracks";137;2
"Building";"CommandCenter";NA;116;0
"Unit";"Marauder";"Barracks";137;2
"Unit";"Marine";"Barracks";138;1
"Building";"SupplyDepot";NA;140;0
"Unit";"Marine";"Barracks";140;1
"Unit";"Marine";"Barracks";141;1
"Unit";"Marine";"Barracks";142;1
"Building";"SupplyDepot";NA;140;0
"Unit";"Marine";"Barracks";143;1
"Building";"SupplyDepot";NA;140;0
"Unit";"Marauder";"Barracks";144;2
"Unit";"Marauder";"Barracks";146;2
"Unit";"Marauder";"Barracks";148;2
"Unit";"Marine";"Barracks";149;1
"Building";"MissileTurret";NA;153;0
"Unit";"Marine";"Barracks";153;1
"Unit";"Marine";"Barracks";153;1
"Unit";"Marauder";"Barracks";153;2
"Unit";"Marine";"Barracks";159;1
"Unit";"Marauder";"Barracks";155;2
"Unit";"Marauder";"Barracks";157;2
"Building";"Refinery";NA;160;0
"Building";"Refinery";NA;160;0
"Building";"GhostAcademy";NA;160;0
"Unit";"Marine";"Barracks";165;1
"Unit";"Marine";"Barracks";169;1
"Unit";"Marauder";"Barracks";162;2
"Unit";"Marauder";"Barracks";165;2
"Unit";"Marauder";"Barracks";167;2
"Upgrade";"TerranShipWeaponsLevel1";"Armory";140;0
"Unit";"Marine";"Barracks";169;1
"Upgrade";"TerranInfantryWeaponsLevel2";"EngineeringBay";136;0
"Upgrade";"TerranInfantryArmorsLevel2";"EngineeringBay";137;0
"Unit";"Marine";"Barracks";173;1
"Unit";"Marauder";"Barracks";171;2
"Unit";"Marauder";"Barracks";173;2
"Unit";"Marauder";"Barracks";178;2
"Unit";"Marine";"Barracks";178;1
"Unit";"Marine";"Barracks";178;1
"Unit";"Marauder";"Barracks";179;2
"Unit";"Marauder";"Barracks";181;2
"Unit";"Marauder";"Barracks";187;2
"Unit";"Marine";"Barracks";191;1
"Unit";"Marine";"Barracks";191;1
"Unit";"Marauder";"Barracks";191;2
"Unit";"Marauder";"Barracks";191;2
"Unit";"Medivac";"Starport";189;2
"Unit";"Medivac";"Starport";189;2
"Unit";"Marine";"Barracks";191;1
"Unit";"Marine";"Barracks";191;1
"Unit";"Marauder";"Barracks";191;2
"Unit";"Medivac";"Starport";191;2
"Unit";"Marine";"Barracks";195;1
"Unit";"Marine";"Barracks";195;1
"Unit";"Marauder";"Barracks";195;2
"Unit";"Marauder";"Barracks";197;2
"Unit";"Marine";"Barracks";205;1
"Unit";"Marine";"Barracks";207;1
"Unit";"Liberator";"Starport";191;3
"Unit";"Marauder";"Barracks";205;2
"Unit";"Marine";"Barracks";209;1
"Unit";"Marauder";"Barracks";211;2
"Unit";"Marauder";"Barracks";213;2
"Unit";"Marine";"Barracks";215;1
"Unit";"Liberator";"Starport";199;3
"Unit";"Marine";"Barracks";215;1
"Unit";"Liberator";"Starport";201;3
