"Type";"UnitName";"OnBuilding";"TotalSupply";"Supply"
"Unit";"SCV";"Command Center";12;1
"Unit";"SCV";"Command Center";12;1
"Unit";"SCV";"Command Center";13;1
"Building";"SupplyDepot";NA;13;0
"Building";"Refinery";NA;14;0
"Unit";"SCV";"Command Center";15;1
"Unit";"SCV";"Command Center";15;1
"Unit";"SCV";"Command Center";16;1
"Unit";"SCV";"Command Center";17;1
"Building";"Barracks";NA;15;0
"Unit";"Reaper";"Barracks";19;1
"Unit";"SCV";"Command Center";19;1
"Unit";"SCV";"Command Center";20;1
"Building";"Factory";NA;19;0
"Unit";"SCV";"Command Center";22;1
"Building";"BarracksReactor";NA;20;0
"Building";"SupplyDepot";NA;22;0
"Building";"Refinery";NA;22;0
"Building";"CommandCenter";NA;19;0
"Unit";"SCV";"Command Center";23;1
"Building";"Barracks";NA;21;0
"Building";"BarracksTechLab";NA;23;0
"Unit";"SCV";"Command Center";23;1
"Unit";"Hellion";"Factory";23;2
"Unit";"Hellion";"Factory";23;2
"Unit";"SCV";"Command Center";24;1
"Unit";"SCV";"Command Center";29;1
"Unit";"SCV";"Command Center";30;1
"Unit";"Hellion";"Factory";29;2
"Building";"BarracksReactor";NA;24;0
"Building";"Bunker";NA;25;0
"Unit";"SCV";"Command Center";30;1
"Unit";"Hellion";"Factory";30;2
"Unit";"SCV";"Command Center";31;1
"Unit";"Marine";"Barracks";31;1
"Unit";"SCV";"Command Center";34;1
"Unit";"SCV";"Command Center";37;1
"Unit";"Marine";"Barracks";38;1
"Unit";"SCV";"Command Center";39;1
"Building";"SupplyDepot";NA;37;0
"Unit";"Marine";"Barracks";40;1
"Unit";"SCV";"Command Center";41;1
"Building";"FactoryTechLab";NA;40;0
"Building";"SupplyDepot";NA;40;0
"Unit";"SCV";"Command Center";43;1
"Unit";"SCV";"Command Center";44;1
"Unit";"SCV";"Command Center";45;1
"Building";"Barracks";NA;37;0
"Building";"Starport";NA;41;0
"Unit";"Marine";"Barracks";46;1
"Unit";"Marine";"Barracks";46;1
"Unit";"Marine";"Barracks";46;1
"Unit";"SCV";"Command Center";46;1
"Unit";"SCV";"Command Center";47;1
"Unit";"SCV";"Command Center";51;1
"Unit";"Marine";"Barracks";48;1
"Unit";"Marine";"Barracks";48;1
"Unit";"Marine";"Barracks";48;1
"Unit";"SCV";"Command Center";52;1
"Unit";"SCV";"Command Center";53;1
"Building";"EngineeringBay";NA;52;0
"Unit";"Marine";"Barracks";53;1
"Unit";"Marine";"Barracks";54;1
"Unit";"Marine";"Barracks";55;1
"Unit";"Marauder";"Barracks";53;2
"Unit";"SCV";"Command Center";58;1
"Upgrade";"Stimpack";"TechLab";37;0
"Building";"StarportReactor";NA;51;0
"Unit";"Marine";"Barracks";58;1
"Unit";"SCV";"Command Center";59;1
"Unit";"SCV";"Command Center";65;1
"Building";"Refinery";NA;60;0
"Building";"SupplyDepot";NA;61;0
"Unit";"SCV";"Command Center";67;1
"Unit";"Marine";"Barracks";67;1
"Unit";"Marine";"Barracks";67;1
"Unit";"SCV";"Command Center";68;1
"Building";"Refinery";NA;67;0
"Unit";"Marine";"Barracks";68;1
"Unit";"Marine";"Barracks";68;1
"Unit";"Medivac";"Starport";67;2
"Unit";"SCV";"Command Center";69;1
"Unit";"Marine";"Barracks";69;1
"Unit";"SCV";"Command Center";76;1
"Building";"CommandCenter";NA;58;0
"Unit";"Medivac";"Starport";69;2
"Building";"SupplyDepot";NA;77;0
"Building";"SupplyDepot";NA;77;0
"Building";"SupplyDepot";NA;77;0
"Unit";"SCV";"Command Center";79;1
"Unit";"SCV";"Command Center";79;1
"Unit";"Marine";"Barracks";79;1
"Unit";"Marine";"Barracks";79;1
"Unit";"Marine";"Barracks";79;1
"Unit";"Marine";"Barracks";79;1
"Unit";"Marauder";"Barracks";79;2
"Unit";"SCV";"Command Center";81;1
"Unit";"SCV";"Command Center";83;1
"Unit";"Medivac";"Starport";79;2
"Unit";"Marine";"Barracks";83;1
"Unit";"Marine";"Barracks";85;1
"Unit";"SCV";"Command Center";89;1
"Unit";"SCV";"Command Center";90;1
"Unit";"SCV";"Command Center";95;1
"Unit";"SCV";"Command Center";96;1
"Unit";"SCV";"Command Center";96;1
"Unit";"Medivac";"Starport";89;2
"Building";"Starport";NA;87;0
"Unit";"Marine";"Barracks";97;1
"Unit";"Marine";"Barracks";97;1
"Unit";"Medivac";"Starport";91;2
"Unit";"SCV";"Command Center";97;1
"Unit";"SCV";"Command Center";98;1
"Unit";"Marauder";"Barracks";97;2
"Upgrade";"TerranInfantryWeaponsLevel1";"EngineeringBay";76;0
"Unit";"SCV";"Command Center";100;1
"Building";"EngineeringBay";NA;97;0
"Unit";"SCV";"Command Center";106;1
"Unit";"SCV";"Command Center";107;1
"Unit";"SCV";"Command Center";110;1
"Building";"Refinery";NA;111;0
"Building";"Refinery";NA;111;0
"Building";"Armory";NA;97;0
"Building";"SupplyDepot";NA;111;0
"Building";"SupplyDepot";NA;111;0
"Building";"SupplyDepot";NA;111;0
"Building";"StarportReactor";NA;104;0
"Unit";"Liberator";"Starport";102;3
"Unit";"SCV";"Command Center";114;1
"Unit";"Marine";"Barracks";114;1
"Unit";"Marine";"Barracks";114;1
"Building";"Barracks";NA;107;0
"Building";"Barracks";NA;107;0
"Unit";"Marine";"Barracks";114;1
"Unit";"Marine";"Barracks";114;1
"Unit";"Marauder";"Barracks";114;2
"Unit";"Marine";"Barracks";118;1
"Unit";"Marine";"Barracks";118;1
"Unit";"Marine";"Barracks";122;1
"Unit";"Marine";"Barracks";122;1
"Unit";"Marauder";"Barracks";122;2
"Unit";"SCV";"Command Center";124;1
"Building";"BarracksTechLab";NA;124;0
"Building";"BarracksTechLab";NA;124;0
"Unit";"SCV";"Command Center";128;1
"Unit";"SCV";"Command Center";128;1
"Building";"MissileTurret";NA;128;0
"Building";"MissileTurret";NA;128;0
"Unit";"Marine";"Barracks";130;1
"Unit";"Marine";"Barracks";130;1
"Unit";"Marine";"Barracks";130;1
"Unit";"Marine";"Barracks";130;1
"Unit";"Marauder";"Barracks";128;2
"Unit";"Liberator";"Starport";122;3
"Unit";"Liberator";"Starport";124;3
"Unit";"SCV";"Command Center";133;1
"Unit";"Marine";"Barracks";133;1
"Unit";"Marauder";"Barracks";133;2
"Unit";"Marine";"Barracks";133;1
"Unit";"Marine";"Barracks";134;1
"Unit";"Marine";"Barracks";135;1
"Unit";"Marine";"Barracks";137;1
"Unit";"Marine";"Barracks";137;1
"Building";"SupplyDepot";NA;137;0
"Building";"SupplyDepot";NA;137;0
"Building";"SupplyDepot";NA;137;0
"Unit";"Liberator";"Starport";131;3
"Unit";"Liberator";"Starport";131;3
"Unit";"Marauder";"Barracks";146;2
"Upgrade";"TerranInfantryArmorsLevel1";"EngineeringBay";118;0
"Unit";"Marine";"Barracks";149;1
"Unit";"Marine";"Barracks";150;1
"Unit";"Marine";"Barracks";151;1
"Unit";"Marauder";"Barracks";147;2
"Building";"MissileTurret";NA;154;0
"Building";"MissileTurret";NA;160;0
"Building";"GhostAcademy";NA;154;0
"Unit";"SCV";"Command Center";167;1
"Unit";"Liberator";"Starport";145;3
"Unit";"Medivac";"Starport";160;2
"Unit";"Medivac";"Starport";160;2
"Unit";"Marine";"Barracks";167;1
"Unit";"Marine";"Barracks";167;1
"Unit";"Marine";"Barracks";167;1
"Unit";"Marine";"Barracks";167;1
"Building";"SupplyDepot";NA;167;0
"Building";"SupplyDepot";NA;167;0
"Building";"SupplyDepot";NA;167;0
"Unit";"Medivac";"Starport";165;2
"Unit";"Marine";"Barracks";179;1
"Unit";"Marine";"Barracks";179;1
"Unit";"Marine";"Barracks";179;1
"Unit";"Marine";"Barracks";179;1
"Unit";"Ghost";"Barracks";171;2
"Unit";"Ghost";"Barracks";171;2
"Building";"CommandCenter";NA;147;0
"Unit";"Ghost";"Barracks";179;2
"Unit";"Marine";"Barracks";181;1
"Unit";"Marine";"Barracks";182;1
"Unit";"Marine";"Barracks";183;1
"Unit";"Marine";"Barracks";184;1
"Unit";"Marine";"Barracks";191;1
"Unit";"Marine";"Barracks";191;1
"Unit";"Marauder";"Barracks";191;2
"Unit";"Marauder";"Barracks";191;2
"Unit";"Marine";"Barracks";195;1
"Unit";"Marine";"Barracks";195;1
"Unit";"Marine";"Barracks";195;1
"Building";"Barracks";NA;189;0
"Unit";"Marine";"Barracks";196;1
"Building";"Barracks";NA;189;0
"Unit";"Marauder";"Barracks";195;2
"Unit";"Marauder";"Barracks";197;2
"Unit";"Marauder";"Barracks";199;2
"Unit";"Marine";"Barracks";201;1
"Unit";"Marine";"Barracks";202;1
"Unit";"Marine";"Barracks";203;1
"Building";"Barracks";NA;191;0
"Unit";"Marine";"Barracks";204;1
"Unit";"Marine";"Barracks";209;1
"Unit";"Marauder";"Barracks";205;2
"Unit";"Marine";"Barracks";212;1
"Unit";"Marine";"Barracks";213;1
"Unit";"Marine";"Barracks";214;1
"Unit";"Marauder";"Barracks";207;2
"Upgrade";"TerranShipWeaponsLevel1";"Armory";181;0
"Building";"BarracksTechLab";NA;215;0
"Unit";"Marauder";"Barracks";215;2
"Unit";"Marauder";"Barracks";216;2
"Unit";"Marine";"Barracks";223;1
"Unit";"Marine";"Barracks";223;1
"Unit";"Marine";"Barracks";223;1
"Unit";"Marine";"Barracks";223;1
"Unit";"Liberator";"Starport";214;3
"Unit";"Liberator";"Starport";214;3
"Unit";"Liberator";"Starport";214;3
"Unit";"Liberator";"Starport";214;3
"Building";"MissileTurret";NA;223;0
"Building";"BarracksReactor";NA;215;0
"Building";"BarracksReactor";NA;215;0
"Building";"Refinery";NA;223;0
"Building";"MissileTurret";NA;223;0
"Unit";"Marine";"Barracks";223;1
"Building";"Refinery";NA;223;0
"Unit";"Ghost";"Barracks";223;2
"Unit";"Marine";"Barracks";223;1
"Unit";"Marine";"Barracks";225;1
"Unit";"Marine";"Barracks";227;1
"Unit";"Marine";"Barracks";228;1
"Unit";"Marine";"Barracks";243;1
"Unit";"Marine";"Barracks";243;1
"Unit";"Marine";"Barracks";246;1
"Unit";"Marine";"Barracks";246;1
"Unit";"Marine";"Barracks";246;1
"Unit";"Marauder";"Barracks";243;2
"Unit";"Marauder";"Barracks";244;2
"Unit";"Marine";"Barracks";248;1
"Unit";"Marauder";"Barracks";246;2
"Unit";"Marine";"Barracks";248;1
"Unit";"Marauder";"Barracks";247;2
"Unit";"Marine";"Barracks";249;1
"Unit";"Marine";"Barracks";250;1
"Unit";"Marine";"Barracks";251;1
"Unit";"Liberator";"Starport";231;3
"Unit";"Marine";"Barracks";252;1
"Unit";"Marine";"Barracks";253;1
"Unit";"Marine";"Barracks";254;1
"Unit";"Marauder";"Barracks";255;2
"Unit";"Marine";"Barracks";260;1
"Unit";"Marauder";"Barracks";257;2
"Unit";"SCV";"Command Center";268;1
"Unit";"SCV";"Command Center";268;1
"Unit";"SCV";"Command Center";268;1
"Unit";"SCV";"Command Center";268;1
"Unit";"Marauder";"Barracks";260;2
"Unit";"Marauder";"Barracks";262;2
"Unit";"SCV";"Command Center";279;1
"Unit";"SCV";"Command Center";280;1
"Unit";"SCV";"Command Center";281;1
"Unit";"Liberator";"Starport";252;3
"Unit";"Liberator";"Starport";252;3
"Unit";"Marine";"Barracks";283;1
"Unit";"Marine";"Barracks";287;1
"Unit";"Marine";"Barracks";287;1
"Unit";"Marine";"Barracks";287;1
"Unit";"Ghost";"Barracks";287;2
"Unit";"Ghost";"Barracks";287;2
"Unit";"Ghost";"Barracks";287;2
"Unit";"Ghost";"Barracks";287;2
"Unit";"Marine";"Barracks";300;1
"Unit";"Marine";"Barracks";300;1
"Unit";"Medivac";"Starport";290;2
"Unit";"Medivac";"Starport";290;2
"Unit";"Marine";"Barracks";300;1
"Unit";"Marine";"Barracks";300;1
"Unit";"Marine";"Barracks";300;1
"Unit";"Marine";"Barracks";300;1
"Unit";"Marauder";"Barracks";300;2
"Unit";"Marauder";"Barracks";302;2
"Unit";"Marine";"Barracks";308;1
"Unit";"Marine";"Barracks";308;1
"Unit";"Marine";"Barracks";308;1
"Unit";"Marauder";"Barracks";308;2
"Unit";"Marauder";"Barracks";308;2
"Unit";"Marine";"Barracks";309;1
"Unit";"Medivac";"Starport";300;2
"Upgrade";"TerranInfantryArmorsLevel2";"EngineeringBay";252;0
"Unit";"Marine";"Barracks";324;1
"Unit";"Marine";"Barracks";324;1
"Unit";"Marine";"Barracks";324;1
"Unit";"Marine";"Barracks";324;1
"Unit";"Marine";"Barracks";324;1
"Unit";"Marauder";"Barracks";324;2
"Unit";"Marauder";"Barracks";324;2
"Unit";"SCV";"Command Center";332;1
"Unit";"Marine";"Barracks";332;1
"Unit";"Marine";"Barracks";332;1
"Unit";"Marine";"Barracks";332;1
"Unit";"Marauder";"Barracks";332;2
"Unit";"Marauder";"Barracks";332;2
"Unit";"Marine";"Barracks";332;1
"Unit";"Marine";"Barracks";333;1
"Unit";"Marine";"Barracks";334;1
"Unit";"Marine";"Barracks";335;1
"Unit";"Medivac";"Starport";332;2
"Unit";"Medivac";"Starport";332;2
"Unit";"Marauder";"Barracks";349;2
"Unit";"Marauder";"Barracks";349;2
"Unit";"Liberator";"Starport";332;3
"Unit";"Liberator";"Starport";333;3
"Unit";"Marine";"Barracks";357;1
"Unit";"Marine";"Barracks";357;1
"Unit";"Marauder";"Barracks";357;2
"Unit";"Marine";"Barracks";357;1
"Unit";"Marauder";"Barracks";357;2
"Unit";"Marine";"Barracks";357;1
"Unit";"Marine";"Barracks";357;1
"Unit";"Marine";"Barracks";357;1
"Unit";"Marine";"Barracks";361;1
"Unit";"Marine";"Barracks";361;1
"Unit";"Marauder";"Barracks";361;2
"Unit";"Marauder";"Barracks";361;2
"Unit";"Marine";"Barracks";367;1
"Unit";"Marauder";"Barracks";369;2
