"type";"unit_name";"on_building";"total_supply";"supply"
"Building";"Refinery";NA;15;0
"Building";"Barracks";NA;15;0
"Unit";"Marine";"Barracks";18;1
"Building";"BarracksReactor";NA;20;0
"Unit";"Marine";"Barracks";22;1
"Unit";"Marine";"Barracks";22;1
"Building";"Refinery";NA;22;0
"Building";"Factory";NA;21;0
"Building";"CommandCenter";NA;19;0
"Unit";"Marine";"Barracks";23;1
"Unit";"Marine";"Barracks";24;1
"Building";"FactoryTechLab";NA;27;0
"Unit";"Marine";"Barracks";27;1
"Unit";"Marine";"Barracks";28;1
"Unit";"Marine";"Barracks";32;1
"Unit";"Marine";"Barracks";32;1
"Building";"Barracks";NA;27;0
"Unit";"Marine";"Barracks";37;1
"Unit";"Marine";"Barracks";37;1
"Building";"BarracksTechLab";NA;37;0
"Unit";"Marine";"Barracks";42;1
"Unit";"Marine";"Barracks";42;1
"Unit";"Marine";"Barracks";44;1
"Building";"EngineeringBay";NA;44;0
"Building";"Starport";NA;42;0
"Unit";"Marine";"Barracks";48;1
"Unit";"Marine";"Barracks";48;1
"Unit";"Marine";"Barracks";50;1
"Unit";"Marine";"Barracks";53;1
"Unit";"Marine";"Barracks";53;1
"Building";"Refinery";NA;53;0
"Building";"FactoryReactor";NA;49;0
"Building";"StarportReactor";NA;50;0
"Building";"Barracks";NA;49;0
"Unit";"Marine";"Barracks";59;1
"Unit";"Marine";"Barracks";59;1
"Building";"Refinery";NA;60;0
"Unit";"Marine";"Barracks";60;1
"Unit";"Marine";"Barracks";60;1
"Unit";"Medivac";"Starport";60;2
"Unit";"Marine";"Barracks";64;1
"Unit";"Marine";"Barracks";64;1
"Unit";"Medivac";"Starport";61;2
"Upgrade";"Stimpack";"TechLab";50;0
"Unit";"Marauder";"Barracks";68;2
"Unit";"Marauder";"Barracks";68;2
"Unit";"Marine";"Barracks";74;1
"Unit";"Marine";"Barracks";74;1
"Unit";"Medivac";"Starport";72;2
"Unit";"Marine";"Barracks";79;1
"Unit";"Marine";"Barracks";79;1
"Unit";"Medivac";"Starport";74;2
"Unit";"Marine";"Barracks";81;1
"Unit";"Marine";"Barracks";81;1
"Upgrade";"TerranInfantryWeaponsLevel1";"EngineeringBay";60;0
"Unit";"Marauder";"Barracks";83;2
"Unit";"Marauder";"Barracks";84;2
"Unit";"Marine";"Barracks";89;1
"Unit";"Liberator";"Starport";83;3
"Unit";"Marauder";"Barracks";91;2
"Unit";"Marauder";"Barracks";93;2
"Unit";"Marine";"Barracks";104;1
"Unit";"Marine";"Barracks";104;1
"Unit";"Marauder";"Barracks";104;2
"Unit";"Marauder";"Barracks";104;2
"Unit";"Marine";"Barracks";104;1
"Unit";"Marine";"Barracks";105;1
"Unit";"Marauder";"Barracks";106;2
"Unit";"Marauder";"Barracks";110;2
"Unit";"Marine";"Barracks";110;1
"Unit";"Marine";"Barracks";111;1
"Unit";"Marine";"Barracks";112;1
"Unit";"Marauder";"Barracks";114;2
"Unit";"Marine";"Barracks";116;1
"Unit";"Marine";"Barracks";117;1
"Unit";"Medivac";"Starport";116;2
"Unit";"Medivac";"Starport";116;2
"Unit";"Marine";"Barracks";118;1
"Building";"Barracks";NA;110;0
"Building";"Barracks";NA;112;0
"Unit";"Marauder";"Barracks";119;2
"Unit";"Marine";"Barracks";121;1
"Unit";"Marine";"Barracks";122;1
"Building";"Factory";NA;118;0
"Unit";"Marauder";"Barracks";127;2
"Building";"BarracksTechLab";NA;132;0
"Building";"BarracksTechLab";NA;132;0
"Unit";"Marine";"Barracks";132;1
"Building";"CommandCenter";NA;112;0
"Building";"FactoryTechLab";NA;136;0
"Unit";"Marauder";"Barracks";134;2
"Unit";"Marine";"Barracks";137;1
"Unit";"Marine";"Barracks";137;1
"Unit";"Marine";"Barracks";137;1
"Unit";"Marauder";"Barracks";137;2
"Unit";"Marauder";"Barracks";137;2
"Unit";"Marine";"Barracks";137;1
"Unit";"Marine";"Barracks";137;1
"Building";"Refinery";NA;137;0
"Building";"EngineeringBay";NA;137;0
"Unit";"Marine";"Barracks";139;1
"Building";"Refinery";NA;139;0
"Unit";"Marine";"Barracks";148;1
"Unit";"Marine";"Barracks";148;1
"Unit";"Marauder";"Barracks";148;2
"Unit";"Marauder";"Barracks";148;2
"Building";"Armory";NA;137;0
"Unit";"Marine";"Barracks";149;1
"Unit";"Marine";"Barracks";149;1
"Unit";"Marine";"Barracks";149;1
"Unit";"Marine";"Barracks";149;1
"Unit";"Marauder";"Barracks";155;2
"Unit";"Marauder";"Barracks";155;2
"Unit";"Marauder";"Barracks";157;2
"Unit";"Marine";"Barracks";159;1
"Unit";"Marine";"Barracks";159;1
"Unit";"Marine";"Barracks";159;1
"Unit";"Marine";"Barracks";159;1
"Upgrade";"TerranInfantryArmorsLevel1";"EngineeringBay";139;0
"Unit";"Marauder";"Barracks";159;2
"Unit";"Marauder";"Barracks";161;2
"Unit";"Marauder";"Barracks";165;2
"Unit";"Marine";"Barracks";165;1
"Unit";"Marine";"Barracks";169;1
"Unit";"Marine";"Barracks";169;1
"Unit";"Marine";"Barracks";169;1
"Unit";"Marine";"Barracks";171;1
"Unit";"Medivac";"Starport";165;2
"Unit";"Marauder";"Barracks";173;2
"Unit";"Medivac";"Starport";165;2
"Unit";"Marine";"Barracks";173;1
"Unit";"Marine";"Barracks";175;1
"Unit";"Marauder";"Barracks";179;2
"Unit";"Marine";"Barracks";186;1
"Unit";"Marine";"Barracks";186;1
"Unit";"Marine";"Barracks";186;1
"Unit";"Marine";"Barracks";187;1
"Unit";"Marauder";"Barracks";186;2
"Unit";"Marauder";"Barracks";186;2
"Unit";"Marauder";"Barracks";188;2
"Unit";"Marine";"Barracks";190;1
"Unit";"Marine";"Barracks";191;1
"Unit";"Marine";"Barracks";192;1
"Unit";"Medivac";"Starport";188;2
"Unit";"Medivac";"Starport";188;2
"Unit";"Marine";"Barracks";193;1
"Unit";"Marine";"Barracks";198;1
"Unit";"Marine";"Barracks";198;1
"Unit";"Marine";"Barracks";198;1
"Unit";"Marine";"Barracks";200;1
"Unit";"Marine";"Barracks";201;1
"Unit";"Marine";"Barracks";213;1
"Unit";"Marine";"Barracks";213;1
"Unit";"Marauder";"Barracks";213;2
"Unit";"Marauder";"Barracks";213;2
"Unit";"Marine";"Barracks";213;1
"Unit";"Marine";"Barracks";213;1
"Unit";"Marauder";"Barracks";213;2
"Building";"CommandCenter";NA;198;0
"Unit";"Marine";"Barracks";213;1
"Unit";"Marine";"Barracks";214;1
"Unit";"Marine";"Barracks";217;1
"Unit";"Marauder";"Barracks";215;2
"Unit";"Marine";"Barracks";219;1
"Unit";"Marine";"Barracks";220;1
"Unit";"Marine";"Barracks";223;1
"Unit";"Marine";"Barracks";223;1
"Unit";"Marine";"Barracks";224;1
"Unit";"Marine";"Barracks";226;1
"Unit";"Marine";"Barracks";228;1
"Unit";"Marauder";"Barracks";225;2
"Unit";"Medivac";"Starport";223;2
"Unit";"Marine";"Barracks";230;1
"Unit";"Marauder";"Barracks";230;2
"Unit";"Marine";"Barracks";231;1
"Unit";"Marine";"Barracks";232;1
"Upgrade";"TerranInfantryWeaponsLevel2";"EngineeringBay";213;0
