"type";"unit_name";"on_building";"total_supply";"supply"
"Building";"Refinery";NA;14;0
"Building";"Barracks";NA;15;0
"Unit";"Marine";"Barracks";19;1
"Building";"BarracksReactor";NA;20;0
"Building";"Refinery";NA;20;0
"Building";"Factory";NA;20;0
"Building";"CommandCenter";NA;19;0
"Unit";"Cyclone";"Factory";24;3
"Unit";"Cyclone";"Factory";24;3
"Building";"BarracksTechLab";NA;24;0
"Unit";"Marine";"Barracks";34;1
"Building";"Barracks";NA;33;0
"Unit";"Marine";"Barracks";37;1
"Building";"Barracks";NA;34;0
"Building";"FactoryReactor";NA;35;0
"Unit";"Marine";"Barracks";40;1
"Building";"EngineeringBay";NA;40;0
"Unit";"Marine";"Barracks";44;1
"Unit";"Marine";"Barracks";44;1
"Unit";"Marine";"Barracks";44;1
"Unit";"Marine";"Barracks";44;1
"Unit";"Marine";"Barracks";45;1
"Building";"Starport";NA;42;0
"Building";"MissileTurret";NA;46;0
"Building";"FactoryReactor";NA;43;0
"Building";"Bunker";NA;46;0
"Unit";"Marine";"Barracks";53;1
"Unit";"Marine";"Barracks";54;1
"Unit";"Marine";"Barracks";54;1
"Unit";"Marine";"Barracks";54;1
"Unit";"Marine";"Barracks";54;1
"Upgrade";"Stimpack";"TechLab";35;0
"Building";"Refinery";NA;61;0
"Unit";"Marine";"Barracks";61;1
"Unit";"Marine";"Barracks";61;1
"Unit";"Marine";"Barracks";61;1
"Unit";"Marine";"Barracks";61;1
"Unit";"Marine";"Barracks";63;1
"Unit";"Medivac";"Starport";61;2
"Unit";"Medivac";"Starport";61;2
"Building";"FactoryReactor";NA;61;0
"Unit";"Marine";"Barracks";67;1
"Unit";"Marine";"Barracks";67;1
"Unit";"Marine";"Barracks";67;1
"Unit";"Marine";"Barracks";67;1
"Unit";"Marine";"Barracks";67;1
"Building";"MissileTurret";NA;72;0
"Unit";"Marine";"Barracks";79;1
"Unit";"Marine";"Barracks";79;1
"Unit";"Marine";"Barracks";79;1
"Unit";"Marine";"Barracks";79;1
"Upgrade";"TerranInfantryWeaponsLevel1";"EngineeringBay";56;0
"Unit";"Medivac";"Starport";79;2
"Unit";"Medivac";"Starport";79;2
"Unit";"Marine";"Barracks";89;1
"Unit";"Marine";"Barracks";89;1
"Unit";"Marine";"Barracks";89;1
"Unit";"Marine";"Barracks";89;1
"Building";"Refinery";NA;89;0
"Building";"CommandCenter";NA;72;0
"Unit";"Medivac";"Starport";89;2
"Unit";"Medivac";"Starport";89;2
"Unit";"Marine";"Barracks";89;1
"Unit";"Marine";"Barracks";91;1
"Unit";"Marine";"Barracks";92;1
"Unit";"Marine";"Barracks";95;1
"Unit";"Marine";"Barracks";95;1
"Building";"Barracks";NA;89;0
"Building";"Barracks";NA;89;0
"Unit";"Marine";"Barracks";100;1
"Unit";"Marine";"Barracks";101;1
"Unit";"Marauder";"Barracks";100;2
"Unit";"Marine";"Barracks";102;1
"Unit";"Marine";"Barracks";103;1
"Building";"BarracksTechLab";NA;108;0
"Building";"BarracksTechLab";NA;108;0
"Unit";"Marine";"Barracks";110;1
"Building";"EngineeringBay";NA;104;0
"Unit";"Marine";"Barracks";110;1
"Unit";"Marauder";"Barracks";110;2
"Unit";"Marine";"Barracks";110;1
"Building";"Refinery";NA;114;0
"Building";"Armory";NA;103;0
"Unit";"Marauder";"Barracks";116;2
"Unit";"Marauder";"Barracks";116;2
"Unit";"Marauder";"Barracks";118;2
"Upgrade";"TerranInfantryArmorsLevel1";"EngineeringBay";102;0
"Unit";"Marine";"Barracks";131;1
"Unit";"Marauder";"Barracks";131;2
"Unit";"Marauder";"Barracks";131;2
"Unit";"Marauder";"Barracks";131;2
"Unit";"Marine";"Barracks";131;1
"Unit";"Marine";"Barracks";131;1
"Unit";"Marine";"Barracks";131;1
"Unit";"Marauder";"Barracks";132;2
"Unit";"Marauder";"Barracks";134;2
"Unit";"Liberator";"Starport";131;3
"Unit";"Liberator";"Starport";131;3
"Unit";"Marine";"Barracks";138;1
"Unit";"Marine";"Barracks";138;1
"Unit";"Marine";"Barracks";139;1
"Unit";"Marine";"Barracks";140;1
"Unit";"Marauder";"Barracks";138;2
"Unit";"Marine";"Barracks";151;1
"Unit";"Marauder";"Barracks";141;2
"Unit";"Marauder";"Barracks";143;2
"Unit";"Marine";"Barracks";152;1
"Unit";"Marine";"Barracks";153;1
"Unit";"Marauder";"Barracks";155;2
"Unit";"Marine";"Barracks";162;1
"Unit";"Marine";"Barracks";163;1
"Unit";"Marine";"Barracks";164;1
"Unit";"Marauder";"Barracks";158;2
"Unit";"Marauder";"Barracks";160;2
"Unit";"Marauder";"Barracks";164;2
"Unit";"Liberator";"Starport";157;3
"Unit";"Medivac";"Starport";166;2
"Unit";"Marauder";"Barracks";169;2
"Unit";"Marine";"Barracks";173;1
"Unit";"Marine";"Barracks";173;1
"Unit";"Marine";"Barracks";173;1
"Unit";"Marine";"Barracks";173;1
"Unit";"Marauder";"Barracks";173;2
"Unit";"Marauder";"Barracks";173;2
"Building";"Barracks";NA;166;0
"Building";"Barracks";NA;166;0
"Building";"Barracks";NA;166;0
"Unit";"Medivac";"Starport";175;2
"Unit";"Marine";"Barracks";182;1
"Unit";"Marine";"Barracks";183;1
"Upgrade";"TerranInfantryWeaponsLevel2";"EngineeringBay";138;0
"Unit";"Marine";"Barracks";184;1
"Unit";"Marauder";"Barracks";180;2
"Unit";"Marauder";"Barracks";186;2
"Unit";"Marine";"Barracks";190;1
"Unit";"Medivac";"Starport";186;2
"Building";"BarracksTechLab";NA;190;0
"Building";"BarracksTechLab";NA;190;0
"Unit";"Marauder";"Barracks";190;2
"Unit";"Marine";"Barracks";192;1
"Unit";"Marine";"Barracks";193;1
"Unit";"Marine";"Barracks";194;1
"Unit";"Marauder";"Barracks";195;2
"Building";"GhostAcademy";NA;192;0
"Unit";"Medivac";"Starport";190;2
"Building";"BarracksReactor";NA;190;0
"Unit";"Marine";"Barracks";209;1
"Unit";"Marine";"Barracks";209;1
"Unit";"Marauder";"Barracks";209;2
"Unit";"Marauder";"Barracks";209;2
"Unit";"Medivac";"Starport";207;2
"Unit";"Marine";"Barracks";211;1
"Unit";"Medivac";"Starport";209;2
"Building";"CommandCenter";NA;190;0
"Unit";"Marine";"Barracks";219;1
"Unit";"Marine";"Barracks";219;1
"Unit";"Marine";"Barracks";222;1
"Unit";"Marine";"Barracks";222;1
"Unit";"Marine";"Barracks";222;1
"Unit";"Marine";"Barracks";222;1
"Unit";"Marine";"Barracks";222;1
"Unit";"Marine";"Barracks";222;1
"Unit";"Medivac";"Starport";217;2
"Unit";"Ghost";"Barracks";220;2
"Unit";"Ghost";"Barracks";220;2
"Unit";"Medivac";"Starport";220;2
"Building";"MissileTurret";NA;233;0
"Unit";"Ghost";"Barracks";235;2
"Unit";"Ghost";"Barracks";235;2
"Building";"Refinery";NA;241;0
"Unit";"Marine";"Barracks";241;1
"Unit";"Marine";"Barracks";241;1
"Unit";"Marine";"Barracks";241;1
"Unit";"Marine";"Barracks";241;1
"Unit";"Marine";"Barracks";241;1
"Unit";"Marauder";"Barracks";241;2
"Unit";"Marine";"Barracks";244;1
"Unit";"Marauder";"Barracks";244;2
"Unit";"Marauder";"Barracks";244;2
"Unit";"Marine";"Barracks";244;1
"Unit";"Marine";"Barracks";246;1
"Upgrade";"TerranInfantryArmorsLevel2";"EngineeringBay";211;0
"Unit";"Marine";"Barracks";255;1
"Unit";"Marine";"Barracks";255;1
"Unit";"Marine";"Barracks";255;1
"Unit";"Marine";"Barracks";255;1
"Unit";"Marine";"Barracks";255;1
"Unit";"Marauder";"Barracks";255;2
"Unit";"Marauder";"Barracks";256;2
"Unit";"Marauder";"Barracks";258;2
"Unit";"Marauder";"Barracks";260;2
"Unit";"Marauder";"Barracks";261;2
"Unit";"Medivac";"Starport";255;2
"Unit";"Medivac";"Starport";255;2
"Upgrade";"TerranInfantryWeaponsLevel3";"EngineeringBay";213;0
"Unit";"Marine";"Barracks";281;1
"Unit";"Marine";"Barracks";281;1
"Unit";"Marine";"Barracks";281;1
"Unit";"Marauder";"Barracks";281;2
"Unit";"Marauder";"Barracks";281;2
"Unit";"Marauder";"Barracks";281;2
"Unit";"Marine";"Barracks";290;1
"Unit";"Marine";"Barracks";290;1
"Unit";"Marauder";"Barracks";288;2
"Unit";"Marauder";"Barracks";290;2
"Unit";"Marauder";"Barracks";290;2
"Unit";"Liberator";"Starport";281;3
"Unit";"Marine";"Barracks";290;1
"Unit";"Marine";"Barracks";290;1
"Unit";"Marauder";"Barracks";290;2
"Unit";"Marauder";"Barracks";290;2
"Unit";"Marine";"Barracks";290;1
"Unit";"Marine";"Barracks";290;1
"Unit";"Marine";"Barracks";292;1
"Unit";"Marine";"Barracks";292;1
"Unit";"Marauder";"Barracks";292;2
"Unit";"Marauder";"Barracks";294;2
"Unit";"Marauder";"Barracks";296;2
