"type";"unit_name";"on_building";"total_supply";"supply"
"Building";"Refinery";NA;14;0
"Building";"Barracks";NA;15;0
"Unit";"Marine";"Barracks";19;1
"Unit";"Marine";"Barracks";20;1
"Building";"Factory";NA;19;0
"Unit";"Marine";"Barracks";22;1
"Unit";"Cyclone";"Factory";24;3
"Building";"BarracksReactor";NA;24;0
"Building";"Refinery";NA;25;0
"Building";"EngineeringBay";NA;28;0
"Building";"CommandCenter";NA;22;0
"Unit";"Hellion";"Factory";29;2
"Unit";"Hellion";"Factory";29;2
"Building";"BarracksTechLab";NA;29;0
"Building";"MissileTurret";NA;30;0
"Building";"Bunker";NA;30;0
"Unit";"Marine";"Barracks";35;1
"Building";"FactoryReactor";NA;36;0
"Unit";"Marauder";"Barracks";37;2
"Building";"MissileTurret";NA;37;0
"Building";"Barracks";NA;36;0
"Building";"Barracks";NA;37;0
"Building";"FactoryTechLab";NA;43;0
"Unit";"Marauder";"Barracks";43;2
"Unit";"Marine";"Barracks";44;1
"Unit";"Marine";"Barracks";44;1
"Upgrade";"TerranInfantryWeaponsLevel1";"EngineeringBay";35;0
"Building";"Refinery";NA;44;0
"Building";"Starport";NA;40;0
"Unit";"Marine";"Barracks";52;1
"Unit";"Marine";"Barracks";52;1
"Unit";"Marine";"Barracks";52;1
"Unit";"Marine";"Barracks";52;1
"Unit";"Marauder";"Barracks";52;2
"Upgrade";"Stimpack";"TechLab";38;0
"Building";"StarportReactor";NA;52;0
"Unit";"Marine";"Barracks";56;1
"Unit";"Marine";"Barracks";56;1
"Unit";"Marine";"Barracks";58;1
"Unit";"Marine";"Barracks";65;1
"Unit";"Marine";"Barracks";65;1
"Unit";"Marine";"Barracks";65;1
"Unit";"Marine";"Barracks";65;1
"Unit";"Marauder";"Barracks";65;2
"Unit";"Medivac";"Starport";65;2
"Unit";"Medivac";"Starport";65;2
"Unit";"Marine";"Barracks";73;1
"Unit";"Marine";"Barracks";73;1
"Unit";"Marine";"Barracks";73;1
"Unit";"Marine";"Barracks";73;1
"Unit";"Marauder";"Barracks";73;2
"Building";"FactoryReactor";NA;71;0
"Unit";"Marine";"Barracks";83;1
"Building";"Barracks";NA;67;0
"Building";"Barracks";NA;71;0
"Building";"EngineeringBay";NA;83;0
"Upgrade";"TerranInfantryArmorsLevel1";"EngineeringBay";65;0
"Unit";"Medivac";"Starport";85;2
"Unit";"Medivac";"Starport";85;2
"Building";"Armory";NA;77;0
"Unit";"Marine";"Barracks";88;1
"Building";"Refinery";NA;88;0
"Unit";"Marauder";"Barracks";88;2
"Unit";"Marine";"Barracks";88;1
"Unit";"Marine";"Barracks";88;1
"Building";"FactoryReactor";NA;88;0
"Unit";"Marauder";"Barracks";88;2
"Building";"MissileTurret";NA;98;0
"Unit";"Marine";"Barracks";103;1
"Unit";"Marine";"Barracks";103;1
"Unit";"Marine";"Barracks";103;1
"Unit";"Marine";"Barracks";103;1
"Unit";"Marauder";"Barracks";103;2
"Unit";"Marine";"Barracks";103;1
"Unit";"Marauder";"Barracks";103;2
"Unit";"Marine";"Barracks";103;1
"Unit";"Marine";"Barracks";103;1
"Unit";"Marine";"Barracks";104;1
"Unit";"Marine";"Barracks";105;1
"Unit";"Marine";"Barracks";106;1
"Unit";"Marine";"Barracks";109;1
"Unit";"Marine";"Barracks";112;1
"Unit";"Marauder";"Barracks";107;2
"Unit";"Marauder";"Barracks";110;2
"Unit";"Marine";"Barracks";119;1
"Unit";"Marine";"Barracks";119;1
"Unit";"Marine";"Barracks";119;1
"Unit";"Marine";"Barracks";119;1
"Unit";"Marine";"Barracks";123;1
"Unit";"Marauder";"Barracks";119;2
"Unit";"Marauder";"Barracks";121;2
"Unit";"Medivac";"Starport";119;2
"Unit";"Medivac";"Starport";119;2
"Unit";"Marine";"Barracks";123;1
"Building";"MissileTurret";NA;132;0
"Unit";"Marauder";"Barracks";128;2
"Unit";"Marauder";"Barracks";130;2
"Unit";"Marine";"Barracks";136;1
"Building";"Bunker";NA;136;0
"Unit";"Marine";"Barracks";143;1
"Unit";"Marine";"Barracks";143;1
"Unit";"Marine";"Barracks";143;1
"Unit";"Marine";"Barracks";143;1
"Unit";"Marine";"Barracks";143;1
"Unit";"Marauder";"Barracks";143;2
"Unit";"Marauder";"Barracks";143;2
"Unit";"Marine";"Barracks";144;1
"Building";"MissileTurret";NA;144;0
"Building";"Bunker";NA;143;0
"Unit";"Liberator";"Starport";136;3
"Upgrade";"TerranInfantryWeaponsLevel2";"EngineeringBay";107;0
"Upgrade";"TerranInfantryArmorsLevel2";"EngineeringBay";107;0
"Unit";"Marine";"Barracks";159;1
"Unit";"Marine";"Barracks";159;1
"Unit";"Marine";"Barracks";159;1
"Unit";"Marine";"Barracks";159;1
"Unit";"Marauder";"Barracks";159;2
"Unit";"Marauder";"Barracks";159;2
"Unit";"Marine";"Barracks";159;1
"Unit";"Marine";"Barracks";159;1
"Unit";"Marauder";"Barracks";163;2
"Unit";"Marauder";"Barracks";163;2
"Unit";"Marine";"Barracks";169;1
"Unit";"Marine";"Barracks";169;1
"Unit";"Marine";"Barracks";169;1
"Unit";"Marine";"Barracks";169;1
"Unit";"Marine";"Barracks";169;1
"Unit";"Marine";"Barracks";169;1
"Unit";"Marauder";"Barracks";169;2
"Unit";"Marauder";"Barracks";169;2
"Unit";"Marine";"Barracks";185;1
"Unit";"Marine";"Barracks";185;1
"Unit";"Marine";"Barracks";185;1
"Unit";"Marauder";"Barracks";185;2
"Unit";"Marauder";"Barracks";185;2
"Unit";"Liberator";"Starport";179;3
"Unit";"Liberator";"Starport";179;3
"Unit";"Marine";"Barracks";185;1
"Unit";"Marine";"Barracks";185;1
"Unit";"Marauder";"Barracks";188;2
"Unit";"Marauder";"Barracks";190;2
"Unit";"Marine";"Barracks";198;1
"Unit";"Marine";"Barracks";198;1
"Unit";"Marine";"Barracks";198;1
"Unit";"Marauder";"Barracks";200;2
"Unit";"Marauder";"Barracks";202;2
"Unit";"Marine";"Barracks";207;1
"Unit";"Marine";"Barracks";207;1
"Unit";"Marine";"Barracks";211;1
"Unit";"Marine";"Barracks";211;1
"Unit";"Marauder";"Barracks";207;2
"Unit";"Marauder";"Barracks";209;2
"Upgrade";"TerranInfantryWeaponsLevel3";"EngineeringBay";179;0
"Unit";"Medivac";"Starport";211;2
"Unit";"Medivac";"Starport";211;2
"Unit";"Marauder";"Barracks";215;2
"Unit";"Marauder";"Barracks";217;2
