"Type";"UnitName";"OnBuilding";"TotalSupply";"Supply"
"Unit";"SCV";"Command Center";12;1
"Unit";"SCV";"Command Center";12;1
"Unit";"SCV";"Command Center";13;1
"Building";"SupplyDepot";NA;13;0
"Unit";"SCV";"Command Center";15;1
"Unit";"SCV";"Command Center";15;1
"Building";"Refinery";NA;15;0
"Unit";"SCV";"Command Center";16;1
"Unit";"SCV";"Command Center";17;1
"Building";"Barracks";NA;15;0
"Unit";"Reaper";"Barracks";19;1
"Unit";"SCV";"Command Center";19;1
"Building";"Refinery";NA;20;0
"Unit";"SCV";"Command Center";21;1
"Building";"SupplyDepot";NA;21;0
"Unit";"Reaper";"Barracks";20;1
"Unit";"SCV";"Command Center";22;1
"Unit";"SCV";"Command Center";24;1
"Building";"Factory";NA;21;0
"Building";"BarracksReactor";NA;23;0
"Unit";"SCV";"Command Center";25;1
"Unit";"Marine";"Barracks";25;1
"Unit";"Marine";"Barracks";25;1
"Unit";"SCV";"Command Center";26;1
"Unit";"Cyclone";"Factory";25;3
"Unit";"Marine";"Barracks";29;1
"Unit";"SCV";"Command Center";32;1
"Unit";"Marine";"Barracks";29;1
"Building";"CommandCenter";NA;19;0
"Unit";"SCV";"Command Center";33;1
"Unit";"SCV";"Command Center";36;1
"Building";"CommandCenter";NA;25;0
"Unit";"Marine";"Barracks";36;1
"Unit";"Marine";"Barracks";36;1
"Unit";"Cyclone";"Factory";36;3
"Unit";"SCV";"Command Center";37;1
"Unit";"Marine";"Barracks";37;1
"Unit";"Marine";"Barracks";38;1
"Unit";"SCV";"Command Center";43;1
"Unit";"SCV";"Command Center";43;1
"Unit";"SCV";"Command Center";47;1
"Unit";"SCV";"Command Center";47;1
"Unit";"Cyclone";"Factory";45;3
"Building";"BarracksTechLab";NA;47;0
"Unit";"SCV";"Command Center";49;1
"Unit";"SCV";"Command Center";49;1
"Unit";"SCV";"Command Center";49;1
"Unit";"SCV";"Command Center";52;1
"Unit";"SCV";"Command Center";55;1
"Unit";"SCV";"Command Center";55;1
"Unit";"Marauder";"Barracks";55;2
"Unit";"SCV";"Command Center";55;1
"Unit";"SCV";"Command Center";56;1
"Unit";"SCV";"Command Center";57;1
"Unit";"Cyclone";"Factory";55;3
"Unit";"SCV";"Command Center";60;1
"Building";"Bunker";NA;55;0
"Unit";"SCV";"Command Center";61;1
"Unit";"SCV";"Command Center";63;1
"Unit";"Marauder";"Barracks";61;2
"Unit";"SCV";"Command Center";66;1
"Unit";"SCV";"Command Center";67;1
"Unit";"SCV";"Command Center";68;1
"Unit";"SCV";"Command Center";71;1
"Building";"Barracks";NA;56;0
"Unit";"SCV";"Command Center";73;1
"Unit";"SCV";"Command Center";73;1
"Unit";"Marauder";"Barracks";73;2
"Building";"SupplyDepot";NA;75;0
"Unit";"Cyclone";"Factory";75;3
"Unit";"Cyclone";"Factory";75;3
"Building";"SupplyDepot";NA;75;0
"Unit";"SCV";"Command Center";79;1
"Unit";"SCV";"Command Center";79;1
"Unit";"SCV";"Command Center";79;1
"Building";"SupplyDepot";NA;79;0
"Building";"BarracksReactor";NA;77;0
"Unit";"Marauder";"Barracks";79;2
"Building";"SupplyDepot";NA;85;0
"Unit";"SCV";"Command Center";88;1
"Unit";"SCV";"Command Center";88;1
"Unit";"SCV";"Command Center";88;1
"Building";"SupplyDepot";NA;85;0
"Unit";"Cyclone";"Factory";88;3
"Unit";"Cyclone";"Factory";88;3
"Unit";"Marine";"Barracks";90;1
"Unit";"Marine";"Barracks";90;1
"Building";"Barracks";NA;79;0
"Building";"Barracks";NA;77;0
"Unit";"SCV";"Command Center";101;1
"Unit";"SCV";"Command Center";101;1
"Unit";"SCV";"Command Center";101;1
"Building";"Barracks";NA;77;0
"Unit";"Marine";"Barracks";101;1
"Unit";"Marine";"Barracks";101;1
"Unit";"SCV";"Command Center";104;1
"Unit";"SCV";"Command Center";104;1
"Unit";"SCV";"Command Center";104;1
"Unit";"Marauder";"Barracks";101;2
"Building";"Barracks";NA;93;0
"Building";"SupplyDepot";NA;104;0
"Unit";"SCV";"Command Center";106;1
"Building";"SupplyDepot";NA;104;0
"Building";"EngineeringBay";NA;104;0
"Unit";"Marine";"Barracks";109;1
"Building";"SupplyDepot";NA;105;0
"Unit";"Marine";"Barracks";109;1
"Building";"Barracks";NA;90;0
"Upgrade";"Stimpack";"TechLab";85;0
"Unit";"SCV";"Command Center";112;1
"Unit";"SCV";"Command Center";112;1
"Building";"FactoryTechLab";NA;111;0
"Building";"BarracksReactor";NA;104;0
"Building";"BarracksReactor";NA;104;0
"Building";"BarracksReactor";NA;104;0
"Unit";"Marauder";"Barracks";112;2
"Unit";"SCV";"Command Center";116;1
"Unit";"SCV";"Command Center";116;1
"Unit";"SCV";"Command Center";116;1
"Building";"Starport";NA;111;0
"Unit";"Marine";"Barracks";116;1
"Unit";"Marine";"Barracks";116;1
"Unit";"Marine";"Barracks";116;1
"Unit";"Marine";"Barracks";116;1
"Unit";"Marine";"Barracks";116;1
"Unit";"Marine";"Barracks";116;1
"Unit";"Marine";"Barracks";116;1
"Unit";"Marine";"Barracks";116;1
"Unit";"SCV";"Command Center";121;1
"Unit";"SCV";"Command Center";121;1
"Unit";"SCV";"Command Center";121;1
"Building";"Refinery";NA;118;0
"Building";"Refinery";NA;118;0
"Unit";"SCV";"Command Center";129;1
"Building";"GhostAcademy";NA;118;0
"Building";"SupplyDepot";NA;121;0
"Building";"SupplyDepot";NA;121;0
"Building";"SupplyDepot";NA;121;0
"Building";"BarracksTechLab";NA;129;0
"Building";"BarracksTechLab";NA;130;0
"Unit";"Marauder";"Barracks";123;2
"Unit";"SCV";"Command Center";133;1
"Unit";"SCV";"Command Center";133;1
"Unit";"SCV";"Command Center";135;1
"Building";"SupplyDepot";NA;133;0
"Building";"SupplyDepot";NA;133;0
"Unit";"Medivac";"Starport";132;2
"Building";"SupplyDepot";NA;133;0
"Building";"SupplyDepot";NA;135;0
"Building";"SupplyDepot";NA;135;0
"Unit";"Marine";"Barracks";135;1
"Unit";"Marine";"Barracks";135;1
"Unit";"Marine";"Barracks";135;1
"Unit";"Marine";"Barracks";135;1
"Unit";"SCV";"Command Center";138;1
"Unit";"SCV";"Command Center";138;1
"Unit";"SCV";"Command Center";138;1
"Unit";"Marine";"Barracks";135;1
"Unit";"Marine";"Barracks";135;1
"Unit";"Marine";"Barracks";135;1
"Unit";"Marine";"Barracks";135;1
"Unit";"Ghost";"Barracks";135;2
"Unit";"Ghost";"Barracks";135;2
"Unit";"SCV";"Command Center";144;1
"Unit";"SCV";"Command Center";145;1
"Unit";"SCV";"Command Center";146;1
"Unit";"Ghost";"Barracks";135;2
"Building";"EngineeringBay";NA;140;0
"Building";"SupplyDepot";NA;145;0
"Unit";"Marine";"Barracks";155;1
"Unit";"Marine";"Barracks";155;1
"Unit";"Marine";"Barracks";155;1
"Unit";"Marine";"Barracks";155;1
"Unit";"Marine";"Barracks";155;1
"Unit";"Marine";"Barracks";155;1
"Unit";"Marine";"Barracks";155;1
"Unit";"Marine";"Barracks";155;1
"Unit";"Medivac";"Starport";160;2
"Unit";"Medivac";"Starport";160;2
"Unit";"Marine";"Barracks";167;1
"Unit";"Marine";"Barracks";168;1
"Unit";"Marine";"Barracks";168;1
"Unit";"Marine";"Barracks";168;1
"Unit";"Marine";"Barracks";168;1
"Unit";"Marine";"Barracks";168;1
"Unit";"Marine";"Barracks";168;1
"Unit";"Marine";"Barracks";168;1
"Building";"CommandCenter";NA;156;0
"Unit";"Marine";"Barracks";180;1
"Unit";"Marine";"Barracks";180;1
"Unit";"Marine";"Barracks";180;1
"Unit";"Marine";"Barracks";180;1
"Unit";"Marine";"Barracks";180;1
"Unit";"Marine";"Barracks";180;1
"Unit";"Marine";"Barracks";180;1
"Unit";"Marine";"Barracks";180;1
"Unit";"SCV";"Command Center";180;1
"Unit";"Marauder";"Barracks";180;2
"Unit";"SCV";"Command Center";180;1
"Unit";"Marauder";"Barracks";180;2
"Unit";"SCV";"Command Center";180;1
"Unit";"Marauder";"Barracks";180;2
"Building";"SupplyDepot";NA;180;0
"Building";"Refinery";NA;180;0
"Building";"Refinery";NA;180;0
"Unit";"Medivac";"Starport";180;2
"Unit";"Medivac";"Starport";180;2
"Unit";"Marine";"Barracks";188;1
"Unit";"Marine";"Barracks";188;1
"Unit";"Marine";"Barracks";191;1
"Unit";"Marine";"Barracks";191;1
"Unit";"Marine";"Barracks";195;1
"Unit";"Marine";"Barracks";197;1
"Unit";"Marine";"Barracks";197;1
"Unit";"SCV";"Command Center";199;1
"Unit";"SCV";"Command Center";199;1
"Unit";"SCV";"Command Center";199;1
"Building";"SupplyDepot";NA;201;0
"Unit";"Marine";"Barracks";211;1
"Unit";"Marine";"Barracks";211;1
"Unit";"Marine";"Barracks";211;1
"Unit";"Marine";"Barracks";211;1
"Unit";"Marine";"Barracks";211;1
"Unit";"Marine";"Barracks";211;1
"Unit";"Marine";"Barracks";211;1
"Unit";"Marine";"Barracks";211;1
"Building";"CommandCenter";NA;188;0
"Unit";"Marine";"Barracks";219;1
"Unit";"Marine";"Barracks";219;1
"Unit";"Marine";"Barracks";219;1
"Unit";"Marine";"Barracks";219;1
"Unit";"Marine";"Barracks";219;1
"Unit";"Marine";"Barracks";219;1
"Unit";"Marine";"Barracks";219;1
"Unit";"Marine";"Barracks";219;1
"Unit";"SCV";"Command Center";219;1
"Unit";"SCV";"Command Center";219;1
"Unit";"SCV";"Command Center";219;1
"Unit";"SCV";"Command Center";219;1
"Unit";"Marauder";"Barracks";219;2
"Unit";"Marauder";"Barracks";219;2
"Unit";"Marauder";"Barracks";219;2
"Unit";"Liberator";"Starport";219;3
"Unit";"Liberator";"Starport";219;3
"Unit";"Marine";"Barracks";237;1
"Unit";"Marine";"Barracks";237;1
"Unit";"Marine";"Barracks";237;1
"Unit";"Marine";"Barracks";237;1
"Unit";"Marine";"Barracks";237;1
"Unit";"Marine";"Barracks";237;1
"Unit";"Marine";"Barracks";237;1
"Unit";"Marine";"Barracks";237;1
"Unit";"SCV";"Command Center";237;1
"Unit";"SCV";"Command Center";237;1
"Unit";"SCV";"Command Center";237;1
"Unit";"SCV";"Command Center";237;1
"Upgrade";"TerranInfantryWeaponsLevel1";"EngineeringBay";211;0
"Unit";"SCV";"Command Center";237;1
"Upgrade";"TerranInfantryArmorsLevel1";"EngineeringBay";211;0
"Unit";"Marauder";"Barracks";237;2
"Unit";"Marauder";"Barracks";237;2
"Unit";"Marauder";"Barracks";237;2
"Unit";"Marine";"Barracks";260;1
"Unit";"Marine";"Barracks";262;1
"Unit";"Marine";"Barracks";262;1
"Unit";"Marine";"Barracks";262;1
"Unit";"Marine";"Barracks";262;1
"Unit";"Marine";"Barracks";262;1
"Unit";"Marine";"Barracks";262;1
"Unit";"Marine";"Barracks";262;1
"Unit";"Marauder";"Barracks";262;2
"Unit";"Marauder";"Barracks";262;2
"Unit";"Marauder";"Barracks";262;2
"Unit";"Liberator";"Starport";262;3
"Unit";"Liberator";"Starport";262;3
"Unit";"Marine";"Barracks";276;1
"Unit";"Marine";"Barracks";276;1
"Unit";"Marine";"Barracks";276;1
"Unit";"Marine";"Barracks";276;1
"Unit";"Marine";"Barracks";276;1
"Unit";"Marine";"Barracks";276;1
"Unit";"Marine";"Barracks";276;1
"Unit";"Marine";"Barracks";276;1
"Unit";"Marine";"Barracks";276;1
"Unit";"Marine";"Barracks";276;1
"Unit";"Marine";"Barracks";276;1
"Building";"CommandCenter";NA;243;0
"Building";"CommandCenter";NA;246;0
"Unit";"Marine";"Barracks";282;1
"Building";"Barracks";NA;276;0
"Unit";"Marine";"Barracks";293;1
"Unit";"Marine";"Barracks";293;1
"Unit";"Marine";"Barracks";293;1
"Unit";"Marine";"Barracks";293;1
"Unit";"Marine";"Barracks";293;1
"Unit";"Marine";"Barracks";293;1
"Unit";"Marine";"Barracks";293;1
"Unit";"Marine";"Barracks";293;1
"Unit";"Marine";"Barracks";293;1
"Unit";"Marine";"Barracks";293;1
"Building";"Barracks";NA;276;0
"Building";"Barracks";NA;276;0
"Building";"Barracks";NA;276;0
"Building";"Barracks";NA;276;0
"Building";"Barracks";NA;276;0
"Building";"Barracks";NA;276;0
"Building";"Refinery";NA;293;0
"Building";"Refinery";NA;293;0
"Unit";"Liberator";"Starport";293;3
"Unit";"Liberator";"Starport";293;3
"Unit";"Ghost";"Barracks";304;2
"Unit";"Ghost";"Barracks";304;2
"Building";"Armory";NA;293;0
"Unit";"Ghost";"Barracks";304;2
"Unit";"Marine";"Barracks";310;1
"Unit";"Marine";"Barracks";310;1
"Unit";"Marine";"Barracks";310;1
"Unit";"Marine";"Barracks";310;1
"Unit";"Marine";"Barracks";310;1
"Unit";"Marine";"Barracks";310;1
"Unit";"Marine";"Barracks";310;1
"Unit";"Marine";"Barracks";310;1
"Unit";"Marine";"Barracks";310;1
"Building";"BarracksTechLab";NA;316;0
"Building";"BarracksTechLab";NA;316;0
"Building";"BarracksTechLab";NA;316;0
"Building";"BarracksTechLab";NA;316;0
"Unit";"SCV";"Command Center";317;1
"Unit";"SCV";"Command Center";317;1
"Unit";"SCV";"Command Center";322;1
"Unit";"SCV";"Command Center";324;1
"Unit";"SCV";"Command Center";324;1
"Unit";"SCV";"Command Center";324;1
"Unit";"SCV";"Command Center";324;1
"Unit";"Liberator";"Starport";310;3
"Unit";"Liberator";"Starport";310;3
"Building";"BarracksReactor";NA;316;0
"Building";"BarracksReactor";NA;324;0
"Unit";"Marine";"Barracks";338;1
"Unit";"Marine";"Barracks";338;1
"Unit";"Marine";"Barracks";338;1
"Unit";"Marine";"Barracks";338;1
"Unit";"Marine";"Barracks";338;1
"Unit";"Marine";"Barracks";338;1
"Unit";"Marine";"Barracks";338;1
"Unit";"Marine";"Barracks";338;1
"Unit";"Marine";"Barracks";338;1
"Unit";"Marine";"Barracks";338;1
"Unit";"Marine";"Barracks";338;1
"Unit";"Marine";"Barracks";338;1
"Building";"Barracks";NA;325;0
"Unit";"Marauder";"Barracks";338;2
"Unit";"Marauder";"Barracks";338;2
"Unit";"Marauder";"Barracks";338;2
"Unit";"Marauder";"Barracks";338;2
"Unit";"Marauder";"Barracks";338;2
"Building";"Barracks";NA;325;0
"Building";"Factory";NA;332;0
"Building";"Factory";NA;332;0
"Unit";"Medivac";"Starport";338;2
"Unit";"Medivac";"Starport";338;2
"Unit";"Marine";"Barracks";356;1
"Unit";"Marine";"Barracks";358;1
"Unit";"Marine";"Barracks";358;1
"Unit";"Marine";"Barracks";360;1
"Unit";"Marine";"Barracks";360;1
"Unit";"Marine";"Barracks";360;1
"Unit";"Marine";"Barracks";360;1
"Unit";"Marine";"Barracks";360;1
"Unit";"Marine";"Barracks";360;1
"Unit";"Marine";"Barracks";360;1
"Unit";"Marine";"Barracks";360;1
"Unit";"Marine";"Barracks";360;1
"Unit";"Marauder";"Barracks";360;2
"Unit";"Marauder";"Barracks";360;2
"Unit";"Marauder";"Barracks";360;2
"Unit";"Marauder";"Barracks";360;2
"Unit";"Marauder";"Barracks";360;2
"Unit";"Marauder";"Barracks";360;2
"Unit";"Marauder";"Barracks";360;2
"Unit";"Thor";"Factory";338;6
"Building";"FactoryTechLab";NA;360;0
"Building";"FactoryTechLab";NA;360;0
"Unit";"Medivac";"Starport";360;2
"Unit";"Medivac";"Starport";362;2
"Building";"BarracksReactor";NA;360;0
"Building";"BarracksReactor";NA;360;0
"Unit";"Marine";"Barracks";396;1
"Unit";"Marine";"Barracks";396;1
"Unit";"Marine";"Barracks";396;1
"Unit";"Marine";"Barracks";396;1
"Unit";"Marine";"Barracks";396;1
"Unit";"Marine";"Barracks";396;1
"Unit";"Marine";"Barracks";396;1
"Unit";"Marine";"Barracks";396;1
"Unit";"Marine";"Barracks";396;1
"Unit";"Marine";"Barracks";396;1
"Unit";"Marine";"Barracks";396;1
"Unit";"Marine";"Barracks";396;1
"Unit";"Marauder";"Barracks";396;2
"Unit";"Marauder";"Barracks";396;2
"Unit";"Marauder";"Barracks";396;2
"Unit";"Marauder";"Barracks";396;2
"Unit";"Marauder";"Barracks";396;2
"Unit";"Marauder";"Barracks";396;2
"Unit";"Marauder";"Barracks";396;2
"Unit";"Thor";"Factory";390;6
"Unit";"Marine";"Barracks";426;1
"Unit";"Marine";"Barracks";426;1
"Unit";"Marine";"Barracks";426;1
"Unit";"Marine";"Barracks";426;1
"Unit";"Marine";"Barracks";426;1
"Unit";"Marine";"Barracks";426;1
"Unit";"Marine";"Barracks";426;1
"Unit";"Marine";"Barracks";426;1
"Unit";"Marine";"Barracks";426;1
"Unit";"Marine";"Barracks";426;1
"Unit";"Marine";"Barracks";426;1
"Unit";"Marine";"Barracks";426;1
"Unit";"Marine";"Barracks";426;1
"Unit";"Marine";"Barracks";426;1
"Unit";"Thor";"Factory";400;6
"Unit";"Marine";"Barracks";446;1
"Unit";"Marine";"Barracks";446;1
"Unit";"Marine";"Barracks";446;1
"Unit";"Marine";"Barracks";446;1
"Unit";"Marine";"Barracks";446;1
"Unit";"Marine";"Barracks";446;1
"Unit";"Marine";"Barracks";446;1
"Unit";"Marine";"Barracks";446;1
"Unit";"Marine";"Barracks";446;1
"Unit";"Marine";"Barracks";446;1
"Unit";"Marine";"Barracks";446;1
"Unit";"Marine";"Barracks";446;1
"Unit";"Marine";"Barracks";446;1
"Unit";"SCV";"Command Center";452;1
"Unit";"SCV";"Command Center";452;1
"Unit";"SCV";"Command Center";452;1
"Unit";"SCV";"Command Center";452;1
"Unit";"Marauder";"Barracks";446;2
"Unit";"Marauder";"Barracks";446;2
"Unit";"Marauder";"Barracks";446;2
"Unit";"Marauder";"Barracks";446;2
"Unit";"SCV";"Command Center";465;1
"Unit";"Marine";"Barracks";452;1
"Unit";"Marine";"Barracks";452;1
"Unit";"Marine";"Barracks";453;1
"Unit";"Marine";"Barracks";454;1
"Unit";"Marine";"Barracks";455;1
"Unit";"Marine";"Barracks";455;1
"Unit";"Marine";"Barracks";457;1
"Unit";"Marine";"Barracks";457;1
"Unit";"Marine";"Barracks";459;1
"Unit";"Marine";"Barracks";460;1
"Unit";"Marauder";"Barracks";463;2
"Unit";"Marauder";"Barracks";463;2
"Unit";"Marauder";"Barracks";469;2
"Unit";"Marauder";"Barracks";471;2
"Unit";"Marauder";"Barracks";473;2
"Building";"Barracks";NA;469;0
"Unit";"SCV";"Command Center";498;1
"Unit";"SCV";"Command Center";498;1
"Unit";"SCV";"Command Center";498;1
"Unit";"SCV";"Command Center";498;1
"Unit";"SCV";"Command Center";498;1
"Building";"Barracks";NA;473;0
"Building";"Barracks";NA;477;0
"Building";"Barracks";NA;477;0
"Unit";"SCV";"Command Center";498;1
"Unit";"Marine";"Barracks";498;1
"Unit";"Marine";"Barracks";498;1
"Unit";"Marine";"Barracks";498;1
"Unit";"Marine";"Barracks";498;1
"Unit";"Marine";"Barracks";498;1
"Unit";"Marine";"Barracks";498;1
"Unit";"Marine";"Barracks";498;1
"Unit";"Marine";"Barracks";498;1
"Unit";"Marine";"Barracks";498;1
"Unit";"Marine";"Barracks";498;1
"Building";"Barracks";NA;477;0
"Unit";"Marine";"Barracks";498;1
"Unit";"Marine";"Barracks";498;1
"Unit";"Marine";"Barracks";498;1
"Building";"Barracks";NA;477;0
"Unit";"Marine";"Barracks";517;1
"Unit";"Marine";"Barracks";517;1
"Unit";"Marine";"Barracks";517;1
"Unit";"Marine";"Barracks";517;1
"Unit";"Marine";"Barracks";517;1
"Unit";"Marine";"Barracks";517;1
"Unit";"Marine";"Barracks";517;1
"Unit";"Marine";"Barracks";517;1
"Unit";"Marine";"Barracks";517;1
"Unit";"Marine";"Barracks";517;1
"Unit";"Marine";"Barracks";517;1
"Unit";"Marine";"Barracks";517;1
"Unit";"Marine";"Barracks";517;1
"Unit";"Marine";"Barracks";517;1
"Unit";"Marine";"Barracks";517;1
"Unit";"Marine";"Barracks";517;1
"Unit";"Marine";"Barracks";517;1
"Unit";"Marine";"Barracks";517;1
"Unit";"Marine";"Barracks";517;1
"Upgrade";"TerranInfantryWeaponsLevel2";"EngineeringBay";452;0
"Upgrade";"TerranInfantryArmorsLevel2";"EngineeringBay";452;0
"Unit";"Hellion";"Factory";517;2
"Unit";"Hellion";"Factory";517;2
"Unit";"Hellion";"Factory";517;2
"Unit";"Ghost";"Barracks";517;2
"Unit";"Ghost";"Barracks";517;2
"Unit";"Ghost";"Barracks";517;2
"Building";"SupplyDepot";NA;517;0
"Building";"BarracksReactor";NA;517;0
"Building";"BarracksReactor";NA;517;0
"Unit";"Marine";"Barracks";517;1
"Unit";"Marine";"Barracks";518;1
"Unit";"Marine";"Barracks";519;1
"Unit";"Marine";"Barracks";520;1
"Unit";"Marine";"Barracks";520;1
"Unit";"Marine";"Barracks";520;1
"Unit";"Marine";"Barracks";523;1
"Unit";"Marine";"Barracks";523;1
"Unit";"Marine";"Barracks";525;1
"Unit";"Marine";"Barracks";526;1
"Unit";"Marine";"Barracks";526;1
"Unit";"Marine";"Barracks";528;1
"Unit";"Marine";"Barracks";528;1
