"type";"unit_name";"on_building";"total_supply";"supply"
"Building";"Refinery";NA;15;0
"Building";"Barracks";NA;15;0
"Unit";"Marine";"Barracks";18;1
"Building";"Barracks";NA;17;0
"Building";"Bunker";NA;18;0
"Unit";"Marine";"Barracks";18;1
"Unit";"Marine";"Barracks";20;1
"Unit";"Marine";"Barracks";21;1
"Unit";"Marine";"Barracks";23;1
