"type";"unit_name";"on_building";"total_supply";"supply"
"Building";"Refinery";NA;15;0
"Building";"Refinery";NA;16;0
"Building";"Barracks";NA;15;0
"Unit";"Reaper";"Barracks";19;1
"Building";"Factory";NA;19;0
"Unit";"Reaper";"Barracks";19;1
"Unit";"Cyclone";"Factory";25;3
"Building";"Starport";NA;24;0
"Unit";"Cyclone";"Factory";30;3
"Unit";"Medivac";"Starport";30;2
"Building";"FactoryTechLab";NA;34;0
"Building";"CommandCenter";NA;26;0
"Building";"Barracks";NA;30;0
"Unit";"Liberator";"Starport";34;3
"Building";"BarracksTechLab";NA;36;0
"Building";"Barracks";NA;36;0
"Building";"BarracksReactor";NA;36;0
"Unit";"Marine";"Barracks";41;1
"Building";"StarportReactor";NA;40;0
"Building";"BarracksReactor";NA;41;0
"Unit";"Marine";"Barracks";45;1
"Unit";"Marine";"Barracks";45;1
"Unit";"Marine";"Barracks";46;1
"Unit";"Marine";"Barracks";47;1
"Unit";"Marine";"Barracks";47;1
"Unit";"Marine";"Barracks";48;1
"Building";"Refinery";NA;48;0
"Building";"Refinery";NA;48;0
"Unit";"Marine";"Barracks";50;1
"Unit";"Marauder";"Barracks";53;2
"Unit";"Medivac";"Starport";50;2
"Unit";"Marine";"Barracks";57;1
"Unit";"Marine";"Barracks";57;1
"Unit";"Marine";"Barracks";57;1
"Unit";"Marine";"Barracks";59;1
"Unit";"Marine";"Barracks";60;1
"Unit";"Medivac";"Starport";59;2
"Unit";"Marine";"Barracks";71;1
"Unit";"Marine";"Barracks";71;1
"Unit";"Marine";"Barracks";71;1
"Unit";"Marine";"Barracks";71;1
"Unit";"Medivac";"Starport";71;2
"Building";"Barracks";NA;65;0
"Building";"EngineeringBay";NA;75;0
"Building";"EngineeringBay";NA;76;0
"Unit";"Marine";"Barracks";80;1
"Unit";"Marine";"Barracks";80;1
"Unit";"Marine";"Barracks";80;1
"Unit";"Marine";"Barracks";80;1
"Building";"BarracksTechLab";NA;82;0
"Unit";"Marauder";"Barracks";82;2
"Unit";"Liberator";"Starport";75;3
"Upgrade";"Stimpack";"TechLab";57;0
"Unit";"Marine";"Barracks";84;1
"Unit";"Marine";"Barracks";84;1
"Unit";"Marine";"Barracks";84;1
"Unit";"Marauder";"Barracks";93;2
"Unit";"Marauder";"Barracks";93;2
"Unit";"Marine";"Barracks";97;1
"Unit";"Marine";"Barracks";97;1
"Unit";"Marine";"Barracks";97;1
"Unit";"Liberator";"Starport";93;3
"Unit";"Marine";"Barracks";107;1
"Unit";"Marine";"Barracks";107;1
"Unit";"Marine";"Barracks";107;1
"Unit";"Marine";"Barracks";107;1
"Unit";"Marauder";"Barracks";107;2
"Unit";"Marine";"Barracks";112;1
"Unit";"Marine";"Barracks";112;1
"Unit";"Marine";"Barracks";112;1
"Unit";"Marine";"Barracks";114;1
"Unit";"Medivac";"Starport";107;2
"Building";"CommandCenter";NA;97;0
