"Type";"UnitName";"OnBuilding";"TotalSupply";"Supply"
"Unit";"SCV";"Command Center";12;1
"Unit";"SCV";"Command Center";12;1
"Unit";"SCV";"Command Center";13;1
"Building";"SupplyDepot";NA;13;0
"Unit";"SCV";"Command Center";15;1
"Unit";"SCV";"Command Center";15;1
"Building";"Refinery";NA;15;0
"Unit";"SCV";"Command Center";16;1
"Building";"Barracks";NA;15;0
"Unit";"SCV";"Command Center";18;1
"Unit";"Reaper";"Barracks";19;1
"Unit";"SCV";"Command Center";19;1
"Building";"SupplyDepot";NA;19;0
"Building";"BarracksTechLab";NA;20;0
"Unit";"SCV";"Command Center";21;1
"Unit";"SCV";"Command Center";22;1
"Unit";"SCV";"Command Center";22;1
"Building";"CommandCenter";NA;19;0
"Unit";"Marauder";"Barracks";22;2
"Building";"Barracks";NA;21;0
"Building";"Barracks";NA;21;0
"Building";"Refinery";NA;23;0
"Unit";"SCV";"Command Center";26;1
"Unit";"Marine";"Barracks";26;1
"Unit";"Marauder";"Barracks";26;2
"Unit";"SCV";"Command Center";26;1
"Unit";"Marine";"Barracks";26;1
"Unit";"SCV";"Command Center";30;1
"Unit";"SCV";"Command Center";31;1
"Building";"EngineeringBay";NA;28;0
"Unit";"Marine";"Barracks";31;1
"Unit";"Marine";"Barracks";31;1
"Unit";"Marine";"Barracks";32;1
"Unit";"SCV";"Command Center";33;1
"Unit";"SCV";"Command Center";34;1
"Unit";"SCV";"Command Center";38;1
"Unit";"Marine";"Barracks";34;1
"Unit";"Marine";"Barracks";38;1
"Unit";"SCV";"Command Center";41;1
"Building";"MissileTurret";NA;39;0
"Unit";"SCV";"Command Center";41;1
"Building";"Factory";NA;34;0
"Unit";"Marine";"Barracks";41;1
"Unit";"Marine";"Barracks";41;1
"Unit";"SCV";"Command Center";42;1
"Building";"BarracksTechLab";NA;42;0
"Building";"MissileTurret";NA;44;0
"Building";"SupplyDepot";NA;44;0
"Unit";"SCV";"Command Center";47;1
"Unit";"SCV";"Command Center";47;1
"Building";"SupplyDepot";NA;47;0
"Unit";"Marine";"Barracks";47;1
"Unit";"Marine";"Barracks";47;1
"Building";"Starport";NA;46;0
"Building";"FactoryReactor";NA;46;0
"Unit";"SCV";"Command Center";47;1
"Unit";"SCV";"Command Center";47;1
"Building";"SupplyDepot";NA;47;0
"Upgrade";"Stimpack";"TechLab";36;0
"Unit";"Marauder";"Barracks";47;2
"Unit";"SCV";"Command Center";51;1
"Building";"Refinery";NA;49;0
"Unit";"SCV";"Command Center";53;1
"Building";"SupplyDepot";NA;51;0
"Unit";"Marine";"Barracks";53;1
"Unit";"SCV";"Command Center";55;1
"Unit";"Marine";"Barracks";55;1
"Unit";"SCV";"Command Center";56;1
"Building";"BarracksReactor";NA;51;0
"Unit";"SCV";"Command Center";58;1
"Unit";"Marine";"Barracks";57;1
"Unit";"Medivac";"Starport";53;2
"Upgrade";"TerranInfantryWeaponsLevel1";"EngineeringBay";44;0
"Building";"SupplyDepot";NA;57;0
"Unit";"SCV";"Command Center";60;1
"Unit";"Medivac";"Starport";56;2
"Unit";"SCV";"Command Center";61;1
"Unit";"Marauder";"Barracks";59;2
"Unit";"Marine";"Barracks";61;1
"Unit";"Marine";"Barracks";61;1
"Building";"SupplyDepot";NA;61;0
"Unit";"SCV";"Command Center";66;1
"Unit";"Marauder";"Barracks";65;2
"Building";"SupplyDepot";NA;65;0
"Building";"FactoryReactor";NA;59;0
"Unit";"SCV";"Command Center";74;1
"Unit";"SCV";"Command Center";74;1
"Unit";"Marauder";"Barracks";69;2
"Unit";"Marine";"Barracks";73;1
"Unit";"Marine";"Barracks";73;1
"Building";"SupplyDepot";NA;74;0
"Unit";"SCV";"Command Center";78;1
"Unit";"Medivac";"Starport";73;2
"Unit";"Medivac";"Starport";74;2
"Unit";"Marine";"Barracks";77;1
"Unit";"SCV";"Command Center";82;1
"Unit";"Marine";"Barracks";78;1
"Unit";"Marine";"Barracks";80;1
"Unit";"Marine";"Barracks";82;1
"Unit";"SCV";"Command Center";88;1
"Building";"SupplyDepot";NA;82;0
"Unit";"Marauder";"Barracks";87;2
"Unit";"SCV";"Command Center";93;1
"Building";"Refinery";NA;91;0
"Unit";"SCV";"Command Center";93;1
"Unit";"SCV";"Command Center";97;1
"Unit";"SCV";"Command Center";97;1
"Unit";"Marine";"Barracks";97;1
"Building";"CommandCenter";NA;77;0
"Building";"Barracks";NA;92;0
"Unit";"Marauder";"Barracks";97;2
"Unit";"Marauder";"Barracks";97;2
"Building";"Barracks";NA;92;0
"Unit";"SCV";"Command Center";99;1
"Unit";"Marine";"Barracks";99;1
"Unit";"Liberator";"Starport";95;3
"Building";"EngineeringBay";NA;97;0
"Unit";"Marine";"Barracks";104;1
"Unit";"SCV";"Command Center";109;1
"Unit";"Marine";"Barracks";109;1
"Building";"BarracksTechLab";NA;109;0
"Unit";"Marauder";"Barracks";109;2
"Unit";"Marauder";"Barracks";109;2
"Building";"Armory";NA;97;0
"Unit";"SCV";"Command Center";110;1
"Unit";"SCV";"Command Center";110;1
"Unit";"Marine";"Barracks";110;1
"Unit";"SCV";"Command Center";116;1
"Unit";"Marine";"Barracks";111;1
"Building";"Refinery";NA;110;0
"Building";"Refinery";NA;110;0
"Building";"BarracksReactor";NA;109;0
"Unit";"Liberator";"Starport";109;3
"Unit";"Liberator";"Starport";109;3
"Upgrade";"TerranInfantryArmorsLevel1";"EngineeringBay";97;0
"Building";"SupplyDepot";NA;118;0
"Building";"SupplyDepot";NA;119;0
"Building";"SupplyDepot";NA;119;0
"Unit";"SCV";"Command Center";127;1
"Unit";"SCV";"Command Center";127;1
"Unit";"SCV";"Command Center";127;1
"Unit";"Marine";"Barracks";127;1
"Unit";"Marine";"Barracks";127;1
"Unit";"Marine";"Barracks";127;1
"Unit";"Marine";"Barracks";127;1
"Unit";"Marauder";"Barracks";127;2
"Unit";"Marauder";"Barracks";127;2
"Unit";"Marauder";"Barracks";127;2
"Unit";"SCV";"Command Center";127;1
"Unit";"SCV";"Command Center";128;1
"Building";"SupplyDepot";NA;127;0
"Building";"SupplyDepot";NA;127;0
"Unit";"Marine";"Barracks";130;1
"Unit";"Marine";"Barracks";130;1
"Unit";"Marine";"Barracks";134;1
"Unit";"Marine";"Barracks";134;1
"Building";"SupplyDepot";NA;142;0
"Unit";"Marauder";"Barracks";142;2
"Unit";"Marauder";"Barracks";142;2
"Unit";"Marauder";"Barracks";142;2
"Building";"SupplyDepot";NA;142;0
"Building";"SupplyDepot";NA;142;0
"Unit";"Marine";"Barracks";142;1
"Unit";"Liberator";"Starport";134;3
"Unit";"Marine";"Barracks";146;1
"Building";"GhostAcademy";NA;146;0
"Unit";"Marauder";"Barracks";146;2
"Unit";"Marauder";"Barracks";146;2
"Unit";"Marauder";"Barracks";146;2
"Unit";"Liberator";"Starport";142;3
"Unit";"Marine";"Barracks";166;1
"Unit";"Marauder";"Barracks";157;2
"Unit";"Marauder";"Barracks";157;2
"Unit";"Marauder";"Barracks";166;2
"Unit";"Marine";"Barracks";166;1
"Unit";"Marine";"Barracks";166;1
"Building";"FusionCore";NA;153;0
"Unit";"Marine";"Barracks";166;1
"Unit";"Marauder";"Barracks";167;2
"Unit";"Marauder";"Barracks";167;2
"Unit";"Marine";"Barracks";173;1
"Unit";"Marauder";"Barracks";171;2
"Unit";"Marine";"Barracks";173;1
"Unit";"Marauder";"Barracks";176;2
"Unit";"Marine";"Barracks";183;1
"Unit";"Marine";"Barracks";183;1
"Unit";"Marine";"Barracks";183;1
"Upgrade";"TerranInfantryArmorsLevel2";"EngineeringBay";146;0
"Upgrade";"TerranInfantryWeaponsLevel2";"EngineeringBay";146;0
"Unit";"SCV";"Command Center";184;1
"Unit";"SCV";"Command Center";184;1
"Unit";"SCV";"Command Center";184;1
"Unit";"Marauder";"Barracks";183;2
"Unit";"Marauder";"Barracks";183;2
"Building";"CommandCenter";NA;166;0
"Unit";"SCV";"Command Center";189;1
"Unit";"SCV";"Command Center";190;1
"Unit";"Marine";"Barracks";184;1
"Upgrade";"TerranShipWeaponsLevel1";"Armory";166;0
"Unit";"Marauder";"Barracks";186;2
"Unit";"Marine";"Barracks";196;1
"Unit";"Marine";"Barracks";196;1
"Building";"Starport";NA;184;0
"Unit";"Liberator";"Starport";183;3
"Unit";"Liberator";"Starport";183;3
"Unit";"Marauder";"Barracks";196;2
"Unit";"Marauder";"Barracks";196;2
"Unit";"Marine";"Barracks";196;1
"Unit";"Marine";"Barracks";198;1
"Building";"Refinery";NA;196;0
"Building";"Refinery";NA;196;0
"Unit";"Marauder";"Barracks";199;2
"Unit";"Marine";"Barracks";201;1
"Unit";"Marine";"Barracks";202;1
"Unit";"Marine";"Barracks";209;1
"Building";"StarportTechLab";NA;213;0
"Unit";"Marine";"Barracks";214;1
"Unit";"Medivac";"Starport";203;2
"Unit";"Medivac";"Starport";206;2
"Unit";"Marine";"Barracks";215;1
"Unit";"Marine";"Barracks";219;1
"Unit";"Marine";"Barracks";219;1
"Unit";"Marine";"Barracks";221;1
"Unit";"Ghost";"Barracks";219;2
"Unit";"Ghost";"Barracks";219;2
"Unit";"Ghost";"Barracks";219;2
"Unit";"Marine";"Barracks";225;1
"Unit";"Marine";"Barracks";226;1
"Unit";"Marine";"Barracks";227;1
"Unit";"Medivac";"Starport";221;2
"Unit";"Medivac";"Starport";223;2
"Unit";"Marine";"Barracks";235;1
"Unit";"Marine";"Barracks";235;1
"Unit";"Marauder";"Barracks";233;2
"Unit";"Ghost";"Barracks";229;2
"Unit";"Ghost";"Barracks";231;2
"Unit";"Liberator";"Starport";228;3
"Unit";"Marauder";"Barracks";244;2
"Unit";"Marine";"Barracks";246;1
"Unit";"Marine";"Barracks";246;1
"Unit";"Marine";"Barracks";246;1
"Unit";"Marine";"Barracks";246;1
"Unit";"Medivac";"Starport";242;2
"Unit";"Liberator";"Starport";238;3
"Building";"CommandCenter";NA;225;0
"Unit";"Marine";"Barracks";253;1
"Unit";"Marine";"Barracks";253;1
"Unit";"Marine";"Barracks";255;1
"Unit";"Marine";"Barracks";256;1
"Unit";"Medivac";"Starport";250;2
"Unit";"Marauder";"Barracks";253;2
"Unit";"Marine";"Barracks";261;1
"Unit";"Marine";"Barracks";261;1
