"Type";"UnitName";"OnBuilding";"TotalSupply";"Supply"
"Unit";"SCV";"Command Center";12;1
"Unit";"SCV";"Command Center";12;1
"Unit";"SCV";"Command Center";13;1
"Building";"SupplyDepot";NA;13;0
"Building";"Refinery";NA;14;0
"Unit";"SCV";"Command Center";15;1
"Unit";"SCV";"Command Center";15;1
"Unit";"SCV";"Command Center";16;1
"Unit";"SCV";"Command Center";17;1
"Building";"Barracks";NA;15;0
"Unit";"Reaper";"Barracks";19;1
"Unit";"SCV";"Command Center";19;1
"Unit";"SCV";"Command Center";21;1
"Unit";"SCV";"Command Center";21;1
"Building";"SupplyDepot";NA;21;0
"Building";"BarracksReactor";NA;20;0
"Unit";"SCV";"Command Center";22;1
"Unit";"SCV";"Command Center";23;1
"Building";"CommandCenter";NA;19;0
"Unit";"SCV";"Command Center";24;1
"Unit";"Marine";"Barracks";25;1
"Unit";"Marine";"Barracks";25;1
"Unit";"SCV";"Command Center";25;1
"Building";"Barracks";NA;23;0
"Building";"Barracks";NA;23;0
"Unit";"SCV";"Command Center";28;1
"Building";"Bunker";NA;25;0
"Unit";"Marine";"Barracks";26;1
"Unit";"Marine";"Barracks";27;1
"Unit";"SCV";"Command Center";29;1
"Building";"BarracksTechLab";NA;29;0
"Building";"BarracksTechLab";NA;29;0
"Unit";"SCV";"Command Center";29;1
"Unit";"SCV";"Command Center";33;1
"Unit";"Marine";"Barracks";32;1
"Unit";"Marine";"Barracks";32;1
"Building";"EngineeringBay";NA;29;0
"Unit";"SCV";"Command Center";33;1
"Unit";"Marine";"Barracks";33;1
"Unit";"Marine";"Barracks";33;1
"Unit";"SCV";"Command Center";35;1
"Unit";"SCV";"Command Center";37;1
"Building";"SupplyDepot";NA;35;0
"Unit";"Marine";"Barracks";37;1
"Unit";"Marine";"Barracks";37;1
"Unit";"SCV";"Command Center";40;1
"Unit";"SCV";"Command Center";41;1
"Unit";"SCV";"Command Center";45;1
"Unit";"Marine";"Barracks";44;1
"Unit";"Marine";"Barracks";45;1
"Building";"SupplyDepot";NA;42;0
"Unit";"Marauder";"Barracks";44;2
"Unit";"Marauder";"Barracks";44;2
"Unit";"SCV";"Command Center";46;1
"Unit";"SCV";"Command Center";46;1
"Unit";"Marine";"Barracks";47;1
"Unit";"Marine";"Barracks";49;1
"Unit";"Marine";"Barracks";51;1
"Unit";"Marauder";"Barracks";49;2
"Building";"SupplyDepot";NA;54;0
"Unit";"SCV";"Command Center";57;1
"Unit";"SCV";"Command Center";57;1
"Building";"Refinery";NA;55;0
"Building";"Refinery";NA;55;0
"Building";"SupplyDepot";NA;55;0
"Unit";"SCV";"Command Center";60;1
"Unit";"SCV";"Command Center";61;1
"Unit";"Marine";"Barracks";62;1
"Unit";"SCV";"Command Center";64;1
"Unit";"SCV";"Command Center";64;1
"Unit";"Marauder";"Barracks";62;2
"Building";"Factory";NA;58;0
"Building";"SupplyDepot";NA;64;0
"Unit";"SCV";"Command Center";65;1
"Unit";"SCV";"Command Center";66;1
"Upgrade";"Stimpack";"TechLab";45;0
"Unit";"Marauder";"Barracks";64;2
"Unit";"SCV";"Command Center";69;1
"Upgrade";"TerranInfantryWeaponsLevel1";"EngineeringBay";54;0
"Building";"Starport";NA;69;0
"Building";"FactoryReactor";NA;69;0
"Unit";"Marine";"Barracks";74;1
"Unit";"Marine";"Barracks";74;1
"Unit";"Marine";"Barracks";74;1
"Unit";"Marauder";"Barracks";74;2
"Building";"CommandCenter";NA;64;0
"Unit";"Marine";"Barracks";74;1
"Unit";"Marine";"Barracks";75;1
"Unit";"Marine";"Barracks";77;1
"Unit";"Marauder";"Barracks";76;2
"Building";"Refinery";NA;79;0
"Unit";"SCV";"Command Center";84;1
"Unit";"SCV";"Command Center";84;1
"Unit";"Marine";"Barracks";79;1
"Unit";"Medivac";"Starport";79;2
"Unit";"Medivac";"Starport";79;2
"Unit";"Marauder";"Barracks";81;2
"Building";"Barracks";NA;74;0
"Building";"Barracks";NA;74;0
"Unit";"Marine";"Barracks";84;1
"Unit";"Marauder";"Barracks";84;2
"Building";"FactoryReactor";NA;79;0
"Unit";"Marine";"Barracks";86;1
"Building";"MissileTurret";NA;87;0
"Building";"MissileTurret";NA;87;0
"Building";"MissileTurret";NA;87;0
"Unit";"SCV";"Command Center";93;1
"Unit";"SCV";"Command Center";93;1
"Building";"MissileTurret";NA;91;0
"Unit";"SCV";"Command Center";94;1
"Unit";"Marine";"Barracks";91;1
"Building";"Refinery";NA;87;0
"Building";"BarracksTechLab";NA;93;0
"Unit";"Marine";"Barracks";93;1
"Unit";"Marine";"Barracks";96;1
"Unit";"Marauder";"Barracks";94;2
"Unit";"Medivac";"Starport";91;2
"Unit";"Medivac";"Starport";91;2
"Building";"SupplyDepot";NA;96;0
"Building";"SupplyDepot";NA;97;0
"Unit";"Marine";"Barracks";101;1
"Unit";"SCV";"Command Center";102;1
"Unit";"SCV";"Command Center";102;1
"Unit";"SCV";"Command Center";102;1
"Building";"BarracksReactor";NA;93;0
"Building";"MissileTurret";NA;101;0
"Unit";"Marine";"Barracks";101;1
"Unit";"SCV";"Command Center";113;1
"Unit";"SCV";"Command Center";113;1
"Unit";"SCV";"Command Center";113;1
"Unit";"Marauder";"Barracks";103;2
"Unit";"Marine";"Barracks";109;1
"Unit";"Marauder";"Barracks";109;2
"Building";"MissileTurret";NA;113;0
"Building";"EngineeringBay";NA;109;0
"Building";"Refinery";NA;114;0
"Unit";"SCV";"Command Center";120;1
"Unit";"SCV";"Command Center";120;1
"Building";"SupplyDepot";NA;122;0
"Unit";"Marine";"Barracks";122;1
"Building";"Armory";NA;109;0
"Unit";"Marine";"Barracks";122;1
"Unit";"Marine";"Barracks";122;1
"Unit";"Marine";"Barracks";122;1
"Building";"SupplyDepot";NA;122;0
"Building";"SupplyDepot";NA;122;0
"Unit";"Marauder";"Barracks";122;2
"Building";"Starport";NA;114;0
"Building";"FactoryReactor";NA;122;0
"Upgrade";"TerranInfantryArmorsLevel1";"EngineeringBay";100;0
"Unit";"Marine";"Barracks";130;1
"Unit";"Marine";"Barracks";130;1
"Unit";"Marine";"Barracks";130;1
"Unit";"Marine";"Barracks";130;1
"Unit";"Marauder";"Barracks";130;2
"Unit";"Marauder";"Barracks";130;2
"Unit";"Marine";"Barracks";130;1
"Unit";"Marine";"Barracks";130;1
"Unit";"Marine";"Barracks";131;1
"Unit";"Marauder";"Barracks";134;2
"Unit";"Marauder";"Barracks";136;2
"Unit";"Liberator";"Starport";130;3
"Unit";"Liberator";"Starport";130;3
"Unit";"Marine";"Barracks";138;1
"Unit";"Liberator";"Starport";130;3
"Unit";"Liberator";"Starport";130;3
"Unit";"Marine";"Barracks";138;1
"Unit";"Marauder";"Barracks";138;2
"Unit";"Marine";"Barracks";139;1
"Unit";"Marine";"Barracks";140;1
"Unit";"Marine";"Barracks";151;1
"Unit";"Marauder";"Barracks";141;2
"Unit";"Marauder";"Barracks";143;2
"Unit";"Marauder";"Barracks";161;2
"Unit";"Marine";"Barracks";168;1
"Unit";"Marine";"Barracks";168;1
"Unit";"Marine";"Barracks";168;1
"Unit";"Marine";"Barracks";168;1
"Unit";"Marauder";"Barracks";168;2
"Unit";"Marauder";"Barracks";168;2
"Building";"SupplyDepot";NA;168;0
"Unit";"Marauder";"Barracks";168;2
"Building";"GhostAcademy";NA;168;0
