"type";"unit_name";"on_building";"total_supply";"supply"
"Building";"Refinery";NA;15;0
"Building";"Refinery";NA;15;0
"Building";"Barracks";NA;15;0
"Unit";"Reaper";"Barracks";18;1
"Building";"BarracksTechLab";NA;19;0
"Building";"Factory";NA;18;0
"Unit";"Marauder";"Barracks";21;2
"Unit";"Cyclone";"Factory";25;3
"Unit";"Marauder";"Barracks";25;2
"Building";"Starport";NA;26;0
"Unit";"Marauder";"Barracks";32;2
"Unit";"Cyclone";"Factory";33;3
"Unit";"Medivac";"Starport";36;2
