"type";"unit_name";"on_building";"total_supply";"supply"
"Building";"Refinery";NA;15;0
"Building";"Barracks";NA;15;0
"Unit";"Reaper";"Barracks";19;1
"Unit";"Marine";"Barracks";19;1
"Unit";"Marine";"Barracks";21;1
"Building";"Factory";NA;22;0
"Building";"CommandCenter";NA;20;0
"Unit";"Cyclone";"Factory";27;3
"Building";"Barracks";NA;27;0
"Building";"CommandCenter";NA;26;0
"Unit";"Cyclone";"Factory";33;3
"Building";"Barracks";NA;32;0
"Building";"BarracksReactor";NA;33;0
