"type";"unit_name";"on_building";"total_supply";"supply"
"Building";"Refinery";NA;14;0
"Building";"Barracks";NA;15;0
"Unit";"Marine";"Barracks";19;1
"Building";"Refinery";NA;20;0
"Building";"Factory";NA;20;0
"Building";"BarracksReactor";NA;20;0
"Building";"CommandCenter";NA;19;0
"Unit";"Marine";"Barracks";23;1
"Unit";"Hellion";"Factory";23;2
"Unit";"Hellion";"Factory";23;2
"Building";"BarracksTechLab";NA;30;0
"Unit";"Hellion";"Factory";28;2
"Unit";"Hellion";"Factory";30;2
"Unit";"Hellion";"Factory";32;2
"Unit";"Hellion";"Factory";34;2
"Building";"Starport";NA;31;0
"Unit";"Marine";"Barracks";37;1
"Building";"Bunker";NA;46;0
"Unit";"Marine";"Barracks";48;1
"Unit";"Marine";"Barracks";48;1
"Unit";"Liberator";"Starport";46;3
"Unit";"Marine";"Barracks";50;1
"Unit";"Marine";"Barracks";57;1
"Building";"StarportTechLab";NA;57;0
