"Type";"UnitName";"OnBuilding";"TotalSupply";"Supply"
"Unit";"SCV";"Command Center";12;1
"Unit";"SCV";"Command Center";12;1
"Unit";"SCV";"Command Center";13;1
"Building";"SupplyDepot";NA;13;0
"Unit";"SCV";"Command Center";15;1
"Unit";"SCV";"Command Center";15;1
"Building";"Refinery";NA;15;0
"Unit";"SCV";"Command Center";16;1
"Unit";"SCV";"Command Center";17;1
"Building";"Barracks";NA;15;0
"Unit";"Reaper";"Barracks";19;1
"Unit";"SCV";"Command Center";19;1
"Building";"SupplyDepot";NA;19;0
"Unit";"SCV";"Command Center";21;1
"Unit";"SCV";"Command Center";21;1
"Building";"BarracksReactor";NA;20;0
"Unit";"SCV";"Command Center";22;1
"Building";"Bunker";NA;21;0
"Building";"Refinery";NA;22;0
"Building";"CommandCenter";NA;19;0
"Unit";"SCV";"Command Center";23;1
"Unit";"Marine";"Barracks";24;1
"Unit";"Marine";"Barracks";24;1
"Building";"Factory";NA;22;0
"Unit";"SCV";"Command Center";24;1
"Unit";"SCV";"Command Center";28;1
"Unit";"Marine";"Barracks";28;1
"Unit";"Marine";"Barracks";28;1
"Building";"EngineeringBay";NA;28;0
"Unit";"SCV";"Command Center";28;1
"Building";"Starport";NA;28;0
"Unit";"Marine";"Barracks";31;1
"Unit";"Marine";"Barracks";31;1
"Building";"Bunker";NA;28;0
"Unit";"SCV";"Command Center";32;1
"Building";"MissileTurret";NA;31;0
"Unit";"SCV";"Command Center";35;1
"Unit";"SCV";"Command Center";35;1
"Building";"SupplyDepot";NA;32;0
"Building";"FactoryTechLab";NA;35;0
"Unit";"Marine";"Barracks";35;1
"Unit";"Medivac";"Starport";35;2
"Unit";"SCV";"Command Center";38;1
"Unit";"Marine";"Barracks";38;1
"Unit";"Marine";"Barracks";38;1
"Building";"SupplyDepot";NA;38;0
"Unit";"SCV";"Command Center";43;1
"Unit";"SCV";"Command Center";43;1
"Building";"Bunker";NA;40;0
"Unit";"SCV";"Command Center";45;1
"Building";"FactoryReactor";NA;40;0
"Unit";"Marine";"Barracks";45;1
"Unit";"Marine";"Barracks";45;1
"Unit";"Raven";"Starport";41;2
"Unit";"Marine";"Barracks";48;1
"Unit";"Marine";"Barracks";48;1
"Unit";"SCV";"Command Center";48;1
"Unit";"SCV";"Command Center";50;1
"Building";"SupplyDepot";NA;50;0
"Unit";"Marine";"Barracks";54;1
"Unit";"Marine";"Barracks";54;1
"Unit";"SCV";"Command Center";54;1
"Building";"Barracks";NA;48;0
"Building";"Barracks";NA;48;0
"Unit";"SCV";"Command Center";56;1
"Unit";"Banshee";"Starport";50;3
"Unit";"SCV";"Command Center";56;1
"Unit";"Marine";"Barracks";57;1
"Unit";"Marine";"Barracks";57;1
"Building";"BarracksTechLab";NA;62;0
"Building";"BarracksTechLab";NA;62;0
"Unit";"SCV";"Command Center";64;1
"Unit";"SCV";"Command Center";64;1
"Building";"Bunker";NA;62;0
"Unit";"Marine";"Barracks";64;1
"Unit";"Marine";"Barracks";64;1
"Unit";"SCV";"Command Center";64;1
"Unit";"Banshee";"Starport";62;3
"Building";"Refinery";NA;67;0
"Building";"Refinery";NA;68;0
"Building";"SupplyDepot";NA;69;0
"Upgrade";"TerranInfantryWeaponsLevel1";"EngineeringBay";57;0
"Unit";"SCV";"Command Center";72;1
"Unit";"SCV";"Command Center";72;1
"Unit";"Marine";"Barracks";72;1
"Unit";"Marine";"Barracks";72;1
"Unit";"Marine";"Barracks";72;1
"Unit";"Marine";"Barracks";72;1
"Unit";"SCV";"Command Center";72;1
"Unit";"SCV";"Command Center";72;1
"Building";"SupplyDepot";NA;72;0
"Building";"SupplyDepot";NA;72;0
"Building";"MissileTurret";NA;72;0
"Building";"MissileTurret";NA;72;0
"Building";"SupplyDepot";NA;72;0
"Unit";"Marine";"Barracks";75;1
"Unit";"SCV";"Command Center";80;1
"Unit";"Marine";"Barracks";80;1
"Unit";"SCV";"Command Center";82;1
"Unit";"Marauder";"Barracks";80;2
"Unit";"Marauder";"Barracks";80;2
"Unit";"Marine";"Barracks";80;1
"Unit";"SCV";"Command Center";83;1
"Unit";"SCV";"Command Center";84;1
"Building";"Barracks";NA;80;0
"Unit";"Marauder";"Barracks";84;2
"Building";"Barracks";NA;80;0
"Unit";"Medivac";"Starport";83;2
"Unit";"Medivac";"Starport";83;2
"Unit";"SCV";"Command Center";91;1
"Upgrade";"Stimpack";"TechLab";72;0
"Unit";"SCV";"Command Center";93;1
"Building";"BarracksTechLab";NA;93;0
"Building";"BarracksReactor";NA;93;0
"Unit";"Marauder";"Barracks";99;2
"Unit";"Marauder";"Barracks";99;2
"Unit";"Marauder";"Barracks";99;2
"Unit";"SCV";"Command Center";99;1
"Unit";"Marine";"Barracks";99;1
"Unit";"Marine";"Barracks";99;1
"Building";"MissileTurret";NA;106;0
"Unit";"SCV";"Command Center";108;1
"Building";"CommandCenter";NA;91;0
"Building";"MissileTurret";NA;108;0
"Unit";"Marine";"Barracks";108;1
"Unit";"Marauder";"Barracks";108;2
"Unit";"Marauder";"Barracks";108;2
"Upgrade";"TerranInfantryArmorsLevel1";"EngineeringBay";91;0
"Unit";"Marine";"Barracks";109;1
"Unit";"Marine";"Barracks";109;1
"Unit";"Marine";"Barracks";109;1
"Unit";"Marauder";"Barracks";109;2
"Unit";"Marine";"Barracks";109;1
"Unit";"Marauder";"Barracks";110;2
"Unit";"Medivac";"Starport";109;2
"Unit";"Medivac";"Starport";109;2
"Unit";"SCV";"Command Center";126;1
"Unit";"SCV";"Command Center";126;1
"Unit";"Marine";"Barracks";120;1
"Unit";"Marine";"Barracks";120;1
"Unit";"Marine";"Barracks";126;1
"Unit";"Marine";"Barracks";126;1
"Unit";"Marine";"Barracks";126;1
"Unit";"Marauder";"Barracks";126;2
"Unit";"Marauder";"Barracks";126;2
"Unit";"Marine";"Barracks";128;1
"Unit";"Marine";"Barracks";131;1
"Unit";"Marine";"Barracks";131;1
"Unit";"Marine";"Barracks";131;1
"Unit";"Marine";"Barracks";132;1
"Unit";"Marine";"Barracks";137;1
"Unit";"Medivac";"Starport";131;2
"Unit";"Medivac";"Starport";131;2
"Unit";"Marauder";"Barracks";133;2
"Unit";"Marauder";"Barracks";135;2
"Unit";"Marine";"Barracks";138;1
"Unit";"Marauder";"Barracks";139;2
"Unit";"Marine";"Barracks";140;1
"Unit";"Marine";"Barracks";141;1
"Unit";"Marine";"Barracks";142;1
"Unit";"Marine";"Barracks";147;1
"Unit";"Marine";"Barracks";149;1
"Unit";"Marine";"Barracks";151;1
"Unit";"Marine";"Barracks";152;1
"Unit";"Marine";"Barracks";154;1
"Unit";"Medivac";"Starport";143;2
"Unit";"Medivac";"Starport";145;2
"Unit";"Marine";"Barracks";156;1
"Unit";"Marine";"Barracks";156;1
"Unit";"Marine";"Barracks";159;1
"Unit";"Marauder";"Barracks";157;2
"Unit";"Marauder";"Barracks";158;2
"Unit";"Marine";"Barracks";160;1
"Unit";"SCV";"Command Center";168;1
"Unit";"SCV";"Command Center";168;1
"Unit";"Marine";"Barracks";161;1
"Building";"EngineeringBay";NA;160;0
"Unit";"Marine";"Barracks";166;1
"Unit";"Marine";"Barracks";167;1
"Unit";"Marine";"Barracks";168;1
"Unit";"Medivac";"Starport";162;2
"Unit";"Marine";"Barracks";174;1
"Unit";"Marine";"Barracks";174;1
"Unit";"Marine";"Barracks";177;1
"Unit";"Marauder";"Barracks";174;2
"Unit";"Marine";"Barracks";178;1
"Building";"Armory";NA;160;0
"Building";"Starport";NA;168;0
"Unit";"Marine";"Barracks";182;1
"Unit";"Marine";"Barracks";182;1
"Building";"StarportTechLab";NA;188;0
"Unit";"Marine";"Barracks";190;1
"Unit";"Marine";"Barracks";190;1
"Unit";"Marine";"Barracks";190;1
"Unit";"Marine";"Barracks";191;1
"Unit";"Marine";"Barracks";191;1
"Unit";"SCV";"Command Center";193;1
"Unit";"Marine";"Barracks";193;1
"Unit";"Marine";"Barracks";193;1
"Unit";"Marine";"Barracks";193;1
"Unit";"Marauder";"Barracks";193;2
"Unit";"Marine";"Barracks";194;1
"Unit";"Marauder";"Barracks";193;2
"Unit";"SCV";"Command Center";199;1
"Unit";"Marine";"Barracks";197;1
"Unit";"Liberator";"Starport";191;3
"Unit";"Marine";"Barracks";198;1
"Unit";"Marine";"Barracks";199;1
"Unit";"Liberator";"Starport";193;3
"Unit";"Liberator";"Starport";193;3
"Unit";"Marine";"Barracks";201;1
"Unit";"Marine";"Barracks";205;1
"Unit";"Marauder";"Barracks";202;2
"Unit";"Marauder";"Barracks";209;2
"Unit";"Marauder";"Barracks";210;2
"Unit";"Marine";"Barracks";217;1
