"type";"unit_name";"on_building";"total_supply";"supply"
"Building";"Refinery";NA;15;0
"Building";"Barracks";NA;15;0
"Unit";"Marine";"Barracks";19;1
"Building";"BarracksTechLab";NA;20;0
"Unit";"Marauder";"Barracks";21;2
"Building";"Barracks";NA;21;0
"Building";"CommandCenter";NA;20;0
"Unit";"Marauder";"Barracks";24;2
"Building";"BarracksReactor";NA;24;0
"Unit";"Marauder";"Barracks";28;2
"Building";"Barracks";NA;24;0
"Unit";"Marine";"Barracks";32;1
"Unit";"Marine";"Barracks";32;1
"Unit";"Marauder";"Barracks";29;2
"Building";"BarracksTechLab";NA;32;0
"Building";"Refinery";NA;32;0
"Unit";"Marine";"Barracks";38;1
"Unit";"Marauder";"Barracks";38;2
"Building";"EngineeringBay";NA;34;0
"Unit";"Marine";"Barracks";45;1
"Unit";"Marauder";"Barracks";45;2
"Unit";"Marine";"Barracks";45;1
"Unit";"Marauder";"Barracks";45;2
"Unit";"Marine";"Barracks";45;1
"Unit";"Marine";"Barracks";51;1
"Upgrade";"Stimpack";"TechLab";32;0
"Unit";"Marine";"Barracks";51;1
"Unit";"Marauder";"Barracks";51;2
"Unit";"Marine";"Barracks";62;1
"Unit";"Marine";"Barracks";62;1
"Unit";"Marauder";"Barracks";62;2
"Unit";"Marauder";"Barracks";64;2
"Building";"Factory";NA;56;0
"Unit";"Marine";"Barracks";69;1
"Unit";"Marine";"Barracks";73;1
"Unit";"Marine";"Barracks";73;1
"Unit";"Marauder";"Barracks";73;2
"Unit";"Marine";"Barracks";73;1
"Building";"Refinery";NA;74;0
"Building";"Refinery";NA;74;0
"Building";"CommandCenter";NA;59;0
"Building";"FactoryReactor";NA;73;0
"Building";"Starport";NA;73;0
"Unit";"Marine";"Barracks";83;1
"Unit";"Marine";"Barracks";83;1
"Unit";"Marine";"Barracks";83;1
"Unit";"Marauder";"Barracks";83;2
"Upgrade";"TerranInfantryWeaponsLevel1";"EngineeringBay";64;0
"Building";"Barracks";NA;78;0
"Building";"Barracks";NA;78;0
"Building";"MissileTurret";NA;88;0
"Building";"MissileTurret";NA;92;0
"Unit";"Medivac";"Starport";85;2
"Unit";"Medivac";"Starport";85;2
"Building";"FactoryReactor";NA;85;0
"Building";"MissileTurret";NA;94;0
"Unit";"Marine";"Barracks";94;1
"Unit";"Marine";"Barracks";100;1
"Unit";"Marine";"Barracks";100;1
"Unit";"Marine";"Barracks";101;1
"Building";"Bunker";NA;94;0
"Unit";"Marine";"Barracks";101;1
"Building";"Bunker";NA;100;0
"Unit";"Marine";"Barracks";102;1
"Unit";"Medivac";"Starport";101;2
"Unit";"Marine";"Barracks";102;1
"Unit";"Marine";"Barracks";105;1
"Unit";"Marine";"Barracks";112;1
"Unit";"Marine";"Barracks";112;1
"Unit";"Marine";"Barracks";113;1
"Unit";"Marine";"Barracks";113;1
"Unit";"Marine";"Barracks";113;1
"Unit";"Marine";"Barracks";113;1
"Unit";"Marine";"Barracks";113;1
"Unit";"Marine";"Barracks";114;1
"Unit";"Marine";"Barracks";115;1
"Unit";"Marine";"Barracks";116;1
"Upgrade";"TerranInfantryArmorsLevel1";"EngineeringBay";102;0
"Unit";"Marine";"Barracks";124;1
"Unit";"Marine";"Barracks";124;1
"Unit";"Marine";"Barracks";124;1
"Unit";"Medivac";"Starport";119;2
"Unit";"Marauder";"Barracks";124;2
"Unit";"Marine";"Barracks";128;1
"Unit";"Marine";"Barracks";128;1
"Unit";"Marine";"Barracks";129;1
"Unit";"Marine";"Barracks";130;1
"Unit";"Marine";"Barracks";131;1
"Building";"Armory";NA;119;0
"Building";"EngineeringBay";NA;128;0
"Unit";"Marine";"Barracks";136;1
"Unit";"Marine";"Barracks";138;1
"Unit";"Marine";"Barracks";139;1
"Unit";"Marine";"Barracks";141;1
"Unit";"Medivac";"Starport";138;2
"Unit";"Marauder";"Barracks";143;2
"Building";"BarracksTechLab";NA;149;0
"Building";"GhostAcademy";NA;144;0
"Building";"BarracksReactor";NA;149;0
"Unit";"Marine";"Barracks";157;1
"Unit";"Marine";"Barracks";157;1
"Unit";"Marine";"Barracks";157;1
"Unit";"Marine";"Barracks";157;1
"Unit";"Marine";"Barracks";158;1
"Unit";"Marine";"Barracks";161;1
"Unit";"Marauder";"Barracks";166;2
"Unit";"Liberator";"Starport";159;3
"Unit";"Marine";"Barracks";166;1
"Unit";"Liberator";"Starport";159;3
"Unit";"Marine";"Barracks";166;1
"Unit";"Marine";"Barracks";166;1
"Unit";"Marine";"Barracks";166;1
"Unit";"Marine";"Barracks";166;1
"Unit";"Marine";"Barracks";166;1
"Unit";"Marine";"Barracks";172;1
"Unit";"Marine";"Barracks";176;1
"Unit";"Marine";"Barracks";182;1
"Building";"Refinery";NA;182;0
"Unit";"Marine";"Barracks";183;1
"Building";"Refinery";NA;183;0
"Building";"MissileTurret";NA;184;0
"Unit";"Marine";"Barracks";187;1
"Unit";"Marine";"Barracks";187;1
"Unit";"Marine";"Barracks";188;1
"Unit";"Marine";"Barracks";190;1
"Unit";"Marine";"Barracks";191;1
"Unit";"Marine";"Barracks";192;1
"Unit";"Marine";"Barracks";193;1
"Unit";"Marine";"Barracks";194;1
"Upgrade";"TerranInfantryWeaponsLevel2";"EngineeringBay";160;0
"Unit";"Marine";"Barracks";194;1
"Unit";"Marauder";"Barracks";194;2
"Upgrade";"TerranInfantryArmorsLevel2";"EngineeringBay";160;0
"Unit";"Marine";"Barracks";194;1
"Unit";"Medivac";"Starport";193;2
"Unit";"Medivac";"Starport";193;2
"Unit";"Marine";"Barracks";195;1
"Unit";"Marine";"Barracks";196;1
"Unit";"Marine";"Barracks";197;1
"Building";"MissileTurret";NA;198;0
"Unit";"Marine";"Barracks";198;1
"Unit";"Marine";"Barracks";199;1
"Unit";"Marine";"Barracks";209;1
"Unit";"Marine";"Barracks";210;1
"Unit";"Marine";"Barracks";210;1
"Unit";"Marauder";"Barracks";209;2
"Unit";"Marauder";"Barracks";210;2
