"type";"unit_name";"on_building";"total_supply";"supply"
"Building";"Refinery";NA;14;0
"Building";"Barracks";NA;15;0
"Building";"Barracks";NA;15;0
"Building";"BarracksTechLab";NA;17;0
"Building";"BarracksTechLab";NA;18;0
"Unit";"Marauder";"Barracks";18;2
"Unit";"Marauder";"Barracks";18;2
"Unit";"Marauder";"Barracks";20;2
"Unit";"Marauder";"Barracks";20;2
"Unit";"Marauder";"Barracks";22;2
"Unit";"Marauder";"Barracks";26;2
"Unit";"Marauder";"Barracks";28;2
