"type";"unit_name";"on_building";"total_supply";"supply"
"Building";"Refinery";NA;13;0
"Building";"Refinery";NA;13;0
"Building";"Barracks";NA;13;0
"Building";"BarracksReactor";NA;15;0
"Building";"Factory";NA;15;0
"Unit";"Cyclone";"Factory";16;3
"Unit";"Cyclone";"Factory";16;3
"Unit";"Cyclone";"Factory";22;3
"Unit";"Cyclone";"Factory";22;3
