"type";"unit_name";"on_building";"total_supply_lag";"supply"
"Building";"Barracks";NA;16;0
"Building";"Refinery";NA;16;0
"Unit";"Reaper";"Barracks";19;1
"Building";"CommandCenter";NA;20;0
"Unit";"Reaper";"Barracks";21;1
"Building";"CommandCenter";NA;24;0
"Building";"BarracksReactor";NA;24;0
"Building";"Barracks";NA;25;0
"Building";"Barracks";NA;27;0
"Unit";"Marine";"Barracks";27;1
"Unit";"Marine";"Barracks";29;1
"Building";"EngineeringBay";NA;30;0
"Building";"BarracksTechLab";NA;31;0
"Unit";"Marine";"Barracks";31;1
"Unit";"Marine";"Barracks";32;1
"Unit";"Marine";"Barracks";37;1
"Unit";"Marine";"Barracks";38;1
"Building";"BarracksTechLab";NA;39;0
"Unit";"Marine";"Barracks";39;1
"Unit";"Marine";"Barracks";42;1
"Unit";"Marine";"Barracks";43;1
"Building";"Factory";NA;46;0
"Unit";"Marine";"Barracks";46;1
"Unit";"Marine";"Barracks";48;1
"Building";"Refinery";NA;49;0
"Upgrade";"Stimpack";"TechLab";49;0
"Unit";"Marine";"Barracks";49;1
"Unit";"Marine";"Barracks";50;1
"Upgrade";"TerranInfantryWeaponsLevel1";"EngineeringBay";53;0
"Unit";"Marine";"Barracks";54;1
"Unit";"Marine";"Barracks";55;1
"Unit";"Marine";"Barracks";62;1
"Unit";"Marine";"Barracks";63;1
"Building";"Starport";NA;64;0
"Unit";"Marine";"Barracks";64;1
"Unit";"Marine";"Barracks";65;1
"Building";"FactoryReactor";NA;66;0
"Building";"Refinery";NA;66;0
"Unit";"Marine";"Barracks";69;1
"Unit";"Marine";"Barracks";70;1
"Unit";"Marine";"Barracks";71;1
"Unit";"Marine";"Barracks";72;1
"Building";"Refinery";NA;76;0
"Unit";"Marine";"Barracks";76;1
"Unit";"Marine";"Barracks";77;1
"Unit";"Marine";"Barracks";78;1
"Unit";"Marine";"Barracks";79;1
"Unit";"Medivac";"Starport";82;2
"Building";"Barracks";NA;84;0
"Unit";"Medivac";"Starport";84;2
"Building";"Barracks";NA;89;0
"Building";"BarracksReactor";NA;89;0
"Building";"MissileTurret";NA;89;0
"Unit";"Marine";"Barracks";89;1
"Building";"MissileTurret";NA;90;0
"Unit";"Marine";"Barracks";90;1
"Unit";"Marine";"Barracks";91;1
"Unit";"Marine";"Barracks";96;1
"Unit";"Marine";"Barracks";97;1
"Unit";"Marine";"Barracks";98;1
"Unit";"Medivac";"Starport";101;2
"Unit";"Medivac";"Starport";103;2
"Unit";"Marine";"Barracks";108;1
"Unit";"Marine";"Barracks";109;1
"Unit";"Marine";"Barracks";110;1
"Building";"BarracksReactor";NA;111;0
"Building";"BarracksReactor";NA;111;0
"Building";"Refinery";NA;111;0
"Building";"Refinery";NA;111;0
"Unit";"Marine";"Barracks";111;1
"Unit";"Marine";"Barracks";112;1
"Unit";"Marine";"Barracks";116;1
"Unit";"Marine";"Barracks";117;1
"Unit";"Marine";"Barracks";118;1
"Unit";"Marine";"Barracks";122;1
"Unit";"Marine";"Barracks";123;1
"Unit";"Marine";"Barracks";124;1
"Unit";"Marine";"Barracks";125;1
"Unit";"Marine";"Barracks";126;1
"Building";"Armory";NA;127;0
"Unit";"Medivac";"Starport";127;2
"Building";"EngineeringBay";NA;129;0
"Unit";"Medivac";"Starport";129;2
"Unit";"Marine";"Barracks";134;1
"Unit";"Marine";"Barracks";135;1
"Unit";"Marine";"Barracks";136;1
"Unit";"Marine";"Barracks";137;1
"Building";"SensorTower";NA;138;0
"Unit";"Marine";"Barracks";138;1
"Unit";"Marine";"Barracks";139;1
"Unit";"Marine";"Barracks";140;1
"Unit";"Marine";"Barracks";141;1
"Unit";"Marine";"Barracks";142;1
"Unit";"Marine";"Barracks";143;1
"Building";"BarracksReactor";NA;144;0
"Unit";"Medivac";"Starport";144;2
"Unit";"Medivac";"Starport";146;2
"Unit";"Marine";"Barracks";148;1
"Unit";"Marine";"Barracks";149;1
"Unit";"Marine";"Barracks";150;1
"Unit";"Marine";"Barracks";151;1
"Unit";"Marine";"Barracks";152;1
"Unit";"Marine";"Barracks";153;1
"Unit";"Marine";"Barracks";154;1
"Unit";"Marine";"Barracks";155;1
"Unit";"Marine";"Barracks";156;1
"Unit";"Marine";"Barracks";157;1
"Unit";"Marine";"Barracks";158;1
"Unit";"Marine";"Barracks";159;1
"Unit";"Marine";"Barracks";160;1
"Unit";"Marine";"Barracks";161;1
"Unit";"Marine";"Barracks";162;1
"Unit";"Marine";"Barracks";163;1
"Unit";"Marine";"Barracks";164;1
"Unit";"Marine";"Barracks";165;1
"Unit";"Marine";"Barracks";166;1
"Unit";"Marine";"Barracks";167;1
"Unit";"Marine";"Barracks";168;1
"Unit";"Marine";"Barracks";169;1
"Unit";"Marine";"Barracks";170;1
"Unit";"Marine";"Barracks";171;1
"Unit";"Marine";"Barracks";172;1
"Unit";"Marine";"Barracks";173;1
"Unit";"Marine";"Barracks";174;1
"Unit";"Marine";"Barracks";175;1
"Unit";"Marine";"Barracks";176;1
"Unit";"Marine";"Barracks";177;1
"Unit";"Marine";"Barracks";178;1
"Unit";"Marine";"Barracks";179;1
"Unit";"Marine";"Barracks";180;1
"Unit";"Marine";"Barracks";181;1
"Unit";"Marine";"Barracks";182;1
"Unit";"Marine";"Barracks";183;1
"Unit";"Marine";"Barracks";184;1
"Unit";"Marine";"Barracks";185;1
"Unit";"Marine";"Barracks";186;1
"Unit";"Marine";"Barracks";187;1
"Upgrade";"SprayTerran";NA;188;0
"Upgrade";"SprayTerran";NA;188;0
"Upgrade";"SprayTerran";NA;188;0
"Upgrade";"SprayTerran";NA;188;0
"Upgrade";"ShieldWall";NA;188;0
"Upgrade";"TerranInfantryArmorsLevel1";NA;188;0
"Upgrade";"SprayTerran";NA;188;0
