"type";"unit_name";"on_building";"total_supply_lag";"supply"
"Building";"Pylon";NA;14;0
"Building";"Gateway";NA;16;0
"Building";"Assimilator";NA;17;0
"Building";"Nexus";NA;20;0
"Building";"CyberneticsCore";NA;20;0
"Building";"Assimilator";NA;22;0
"Building";"Pylon";NA;22;0
"Unit";"Adept";"Gateway";23;2
"Building";"Stargate";NA;27;0
"Unit";"Adept";"Gateway";27;2
"Building";"Gateway";NA;35;0
"Building";"Gateway";NA;36;0
"Unit";"Oracle";"Stargate";37;3
"Building";"Pylon";NA;41;0
"Building";"TwilightCouncil";NA;43;0
"Unit";"Adept";"Gateway";44;2
"Building";"Pylon";NA;47;0
"Unit";"Phoenix";"Stargate";48;2
"Building";"Pylon";NA;51;0
"Building";"Assimilator";NA;52;0
"Unit";"Adept";"Gateway";53;2
"Unit";"Adept";"Gateway";55;2
"Unit";"Adept";"Gateway";57;2
"Building";"Nexus";NA;59;0
"Building";"Assimilator";NA;61;0
"Building";"Pylon";NA;62;0
"Building";"Pylon";NA;62;0
"Unit";"Adept";"Gateway";62;2
"Unit";"Adept";"Gateway";64;2
"Unit";"Adept";"Gateway";66;2
"Building";"Pylon";NA;71;0
"Unit";"Adept";"Gateway";72;2
"Unit";"Adept";"Gateway";74;2
"Unit";"Adept";"Gateway";76;2
"Building";"RoboticsFacility";NA;79;0
"Building";"Forge";NA;80;0
"Unit";"Sentry";"Gateway";80;2
"Unit";"Sentry";"Gateway";82;2
"Upgrade";"Charge";"TwilightCouncil";87;0
"Unit";"Sentry";"Gateway";90;2
"Building";"Assimilator";NA;92;0
"Building";"Assimilator";NA;93;0
"Building";"Pylon";NA;95;0
"Building";"Pylon";NA;95;0
"Upgrade";"ProtossGroundWeaponsLevel1";"Forge";99;0
"Building";"Pylon";NA;101;0
"Building";"Gateway";NA;101;0
"Unit";"Phoenix";"Stargate";101;2
"Building";"Gateway";NA;103;0
"Building";"Gateway";NA;103;0
"Building";"Gateway";NA;105;0
"Unit";"Adept";"Gateway";106;2
"Unit";"Adept";"Gateway";108;2
"Unit";"Observer";"Robotics Facility";110;1
"Building";"TemplarArchive";NA;111;0
"Building";"Gateway";NA;111;0
"Unit";"Adept";"Gateway";111;2
"Building";"Pylon";NA;113;0
"Unit";"Immortal";"Robotics Facility";113;4
"Building";"Pylon";NA;117;0
"Unit";"Zealot";"Gateway";117;2
"Unit";"Zealot";"Gateway";119;2
"Building";"Nexus";NA;121;0
"Building";"Pylon";NA;121;0
"Unit";"Immortal";"Robotics Facility";121;4
"Building";"HighTemplar";NA;125;0
"Building";"HighTemplar";NA;125;0
"Building";"HighTemplar";NA;125;0
"Building";"HighTemplar";NA;125;0
"Building";"RoboticsFacility";NA;125;0
"Unit";"Zealot";"Gateway";125;2
"Unit";"Zealot";"Gateway";127;2
"Unit";"Zealot";"Gateway";129;2
"Building";"PhotonCannon";NA;131;0
"Building";"PhotonCannon";NA;131;0
"Building";"PhotonCannon";NA;131;0
"Building";"HighTemplar";NA;134;0
"Building";"HighTemplar";NA;134;0
"Unit";"Immortal";"Robotics Facility";134;4
"Upgrade";"ProtossGroundWeaponsLevel2";"Forge";138;0
"Unit";"Archon";"High Templar";138;0
"Unit";"Zealot";"Gateway";138;2
"Unit";"Zealot";"Gateway";140;2
"Unit";"Zealot";"Gateway";142;2
"Unit";"Zealot";"Gateway";144;2
"Unit";"Zealot";"Gateway";146;2
"Unit";"Zealot";"Gateway";148;2
"Building";"Pylon";NA;151;0
"Unit";"Immortal";"Robotics Facility";151;4
"Building";"Assimilator";NA;155;0
"Building";"Assimilator";NA;155;0
"Unit";"Phoenix";"Stargate";155;2
"Unit";"Immortal";"Robotics Facility";161;4
"Building";"HighTemplar";NA;166;0
"Building";"HighTemplar";NA;166;0
"Building";"HighTemplar";NA;166;0
"Building";"OracleStasisTrap";NA;166;0
"Building";"HighTemplar";NA;166;0
"Unit";"Archon";"High Templar";166;0
"Unit";"Archon";"High Templar";166;0
"Unit";"Immortal";"Robotics Facility";166;4
"Unit";"Phoenix";"Stargate";170;2
"Building";"Gateway";NA;172;0
"Building";"Gateway";NA;172;0
"Building";"Gateway";NA;172;0
"Building";"Gateway";NA;172;0
"Unit";"Zealot";"Gateway";172;2
"Unit";"Zealot";"Gateway";174;2
"Unit";"Zealot";"Gateway";176;2
"Unit";"Zealot";"Gateway";178;2
"Unit";"Immortal";"Robotics Facility";180;4
"Building";"HighTemplar";NA;184;0
"Building";"HighTemplar";NA;184;0
"Building";"HighTemplar";NA;184;0
"Unit";"Archon";"High Templar";184;0
"Unit";"Immortal";"Robotics Facility";184;4
"Building";"FleetBeacon";NA;188;0
"Building";"Pylon";NA;188;0
"Building";"HighTemplar";NA;188;0
"Building";"HighTemplar";NA;188;0
"Unit";"Archon";"High Templar";188;0
"Building";"Pylon";NA;188;0
"Building";"Pylon";NA;188;0
"Building";"Pylon";NA;188;0
"Building";"Pylon";NA;188;0
"Building";"HighTemplar";NA;188;0
"Building";"HighTemplar";NA;188;0
"Building";"HighTemplar";NA;188;0
"Building";"HighTemplar";NA;188;0
"Unit";"Zealot";"Gateway";188;2
"Unit";"Zealot";"Gateway";190;2
"Unit";"Zealot";"Gateway";192;2
"Unit";"Zealot";"Gateway";194;2
"Unit";"Zealot";"Gateway";196;2
"Building";"Stargate";NA;198;0
"Unit";"Archon";"High Templar";198;0
"Unit";"Archon";"High Templar";198;0
"Building";"Stargate";NA;198;0
"Building";"Stargate";NA;198;0
"Unit";"Zealot";"Gateway";198;2
"Unit";"Zealot";"Gateway";200;2
"Unit";"Zealot";"Gateway";202;2
"Unit";"Zealot";"Gateway";204;2
"Unit";"Zealot";"Gateway";206;2
"Unit";"Zealot";"Gateway";208;2
"Unit";"Zealot";"Gateway";210;2
"Unit";"Zealot";"Gateway";212;2
"Unit";"Zealot";"Gateway";214;2
"Unit";"Zealot";"Gateway";216;2
"Unit";"Zealot";"Gateway";218;2
"Unit";"Zealot";"Gateway";220;2
"Unit";"Zealot";"Gateway";222;2
"Unit";"Zealot";"Gateway";224;2
"Unit";"Zealot";"Gateway";226;2
"Unit";"Carrier";"Stargate";228;6
"Unit";"Carrier";"Stargate";234;6
"Unit";"Carrier";"Stargate";240;6
"Building";"Nexus";NA;246;0
"Building";"PhotonCannon";NA;246;0
"Building";"PhotonCannon";NA;246;0
"Building";"Pylon";NA;246;0
"Building";"Pylon";NA;246;0
"Building";"Pylon";NA;246;0
"Upgrade";"ProtossAirWeaponsLevel1";"CyberneticsCore";246;0
"Building";"Pylon";NA;246;0
"Building";"Pylon";NA;246;0
"Building";"Pylon";NA;246;0
"Unit";"Carrier";"Stargate";246;6
"Building";"Assimilator";NA;252;0
"Building";"Assimilator";NA;252;0
"Building";"Stargate";NA;252;0
"Building";"HighTemplar";NA;252;0
"Building";"HighTemplar";NA;252;0
"Building";"HighTemplar";NA;252;0
"Building";"HighTemplar";NA;252;0
"Building";"HighTemplar";NA;252;0
"Building";"HighTemplar";NA;252;0
"Building";"PhotonCannon";NA;252;0
"Unit";"Archon";"High Templar";252;0
"Unit";"Archon";"High Templar";252;0
"Unit";"Archon";"High Templar";252;0
"Building";"PhotonCannon";NA;252;0
"Building";"PhotonCannon";NA;252;0
"Building";"PhotonCannon";NA;252;0
"Building";"PhotonCannon";NA;252;0
"Building";"PhotonCannon";NA;252;0
"Building";"PhotonCannon";NA;252;0
"Building";"PhotonCannon";NA;252;0
"Building";"PhotonCannon";NA;252;0
"Unit";"Carrier";"Stargate";252;6
"Unit";"Carrier";"Stargate";258;6
"Unit";"Carrier";"Stargate";269;6
"Unit";"Phoenix";"Stargate";275;2
"Unit";"Stalker";"Gateway";277;2
"Unit";"Stalker";"Gateway";279;2
"Unit";"Stalker";"Gateway";281;2
"Unit";"Stalker";"Gateway";283;2
"Unit";"Stalker";"Gateway";285;2
"Unit";"Stalker";"Gateway";287;2
"Unit";"Stalker";"Gateway";289;2
"Building";"HighTemplar";NA;291;0
"Building";"HighTemplar";NA;291;0
"Building";"HighTemplar";NA;291;0
"Building";"HighTemplar";NA;291;0
"Building";"HighTemplar";NA;291;0
"Upgrade";"ProtossAirWeaponsLevel2";"CyberneticsCore";291;0
"Building";"Stargate";NA;291;0
"Building";"CyberneticsCore";NA;291;0
"Unit";"Carrier";"Stargate";291;6
"Unit";"Zealot";"Gateway";297;2
"Unit";"Zealot";"Gateway";299;2
"Unit";"Zealot";"Gateway";301;2
"Unit";"Zealot";"Gateway";303;2
"Unit";"Zealot";"Gateway";305;2
"Unit";"Zealot";"Gateway";307;2
"Unit";"Zealot";"Gateway";309;2
"Building";"DarkShrine";NA;311;0
"Upgrade";"ProtossGroundWeaponsLevel3";"Forge";311;0
"Unit";"Zealot";"Gateway";311;2
"Unit";"Zealot";"Gateway";313;2
"Unit";"Zealot";"Gateway";315;2
"Unit";"Zealot";"Gateway";317;2
"Unit";"Zealot";"Gateway";319;2
"Unit";"Zealot";"Gateway";321;2
"Unit";"Zealot";"Gateway";323;2
"Unit";"Zealot";"Gateway";325;2
"Unit";"Zealot";"Gateway";327;2
"Unit";"Carrier";"Stargate";329;6
"Unit";"Carrier";"Stargate";335;6
"Unit";"Carrier";"Stargate";341;6
"Unit";"Oracle";"Stargate";347;3
"Unit";"Oracle";"Stargate";350;3
"Upgrade";"ProtossAirWeaponsLevel3";"CyberneticsCore";353;0
"Unit";"Carrier";"Stargate";356;6
"Building";"HighTemplar";NA;362;0
"Building";"HighTemplar";NA;362;0
"Building";"HighTemplar";NA;362;0
"Building";"HighTemplar";NA;362;0
"Building";"HighTemplar";NA;362;0
"Building";"HighTemplar";NA;362;0
"Unit";"Archon";"High Templar";362;0
"Unit";"Archon";"High Templar";362;0
"Unit";"Carrier";"Stargate";362;6
"Unit";"Observer";"Robotics Facility";368;1
"Unit";"Observer";"Robotics Facility";369;1
"Building";"HighTemplar";NA;370;0
"Unit";"Observer";"Robotics Facility";370;1
"Upgrade";"ProtossShieldsLevel1";"Forge";371;0
"Unit";"Zealot";"Gateway";371;2
"Unit";"Zealot";"Gateway";373;2
"Unit";"Zealot";"Gateway";375;2
"Unit";"Zealot";"Gateway";377;2
"Unit";"Zealot";"Gateway";379;2
"Building";"Pylon";NA;381;0
"Building";"Nexus";NA;381;0
"Building";"Pylon";NA;381;0
"Building";"Pylon";NA;381;0
"Building";"Assimilator";NA;381;0
"Unit";"Oracle";"Stargate";381;3
"Unit";"Oracle";"Stargate";384;3
"Building";"PhotonCannon";NA;387;0
"Building";"PhotonCannon";NA;387;0
"Building";"PhotonCannon";NA;387;0
"Building";"PhotonCannon";NA;387;0
"Building";"PhotonCannon";NA;387;0
"Unit";"Zealot";"Gateway";387;2
"Unit";"Zealot";"Gateway";389;2
"Unit";"Zealot";"Gateway";391;2
"Unit";"Zealot";"Gateway";393;2
"Unit";"Zealot";"Gateway";395;2
"Unit";"Zealot";"Gateway";397;2
"Unit";"Zealot";"Gateway";399;2
"Unit";"Zealot";"Gateway";401;2
"Unit";"Zealot";"Gateway";403;2
"Unit";"Zealot";"Gateway";405;2
"Unit";"Zealot";"Gateway";407;2
"Unit";"Zealot";"Gateway";409;2
"Building";"Assimilator";NA;411;0
"Unit";"Carrier";"Stargate";411;6
"Unit";"Carrier";"Stargate";417;6
"Unit";"Carrier";"Stargate";423;6
"Unit";"Zealot";"Gateway";429;2
"Unit";"Zealot";"Gateway";431;2
"Unit";"Zealot";"Gateway";433;2
"Unit";"Zealot";"Gateway";435;2
"Unit";"Zealot";"Gateway";437;2
"Unit";"Zealot";"Gateway";439;2
"Unit";"Zealot";"Gateway";441;2
"Unit";"Carrier";"Stargate";443;6
"Unit";"Carrier";"Stargate";449;6
"Building";"DarkTemplar";NA;455;0
"Building";"DarkTemplar";NA;455;0
"Building";"PhotonCannon";NA;455;0
"Building";"PhotonCannon";NA;455;0
"Building";"PhotonCannon";NA;455;0
"Building";"PhotonCannon";NA;455;0
"Building";"PhotonCannon";NA;455;0
"Upgrade";"ProtossShieldsLevel2";"Forge";455;0
"Building";"PhotonCannon";NA;455;0
"Building";"PhotonCannon";NA;455;0
"Building";"DarkTemplar";NA;455;0
"Building";"DarkTemplar";NA;455;0
"Building";"Pylon";NA;455;0
"Building";"Pylon";NA;455;0
"Upgrade";"SprayProtoss";NA;455;0
"Upgrade";"SprayProtoss";NA;455;0
"Upgrade";"WarpGateResearch";NA;455;0
"Upgrade";"SprayProtoss";NA;455;0
"Upgrade";"AdeptPiercingAttack";NA;455;0
"Upgrade";"SprayProtoss";NA;455;0
"Upgrade";"SprayProtoss";NA;455;0
"Upgrade";"SprayProtoss";NA;455;0
"Upgrade";"PsiStormTech";NA;455;0
"Upgrade";"SprayProtoss";NA;455;0
"Upgrade";"CarrierLaunchSpeedUpgrade";NA;455;0
"Upgrade";"SprayProtoss";NA;455;0
"Upgrade";"BlinkTech";NA;455;0
"Upgrade";"SprayProtoss";NA;455;0
"Upgrade";"ProtossAirArmorsLevel1";NA;455;0
"Upgrade";"SprayProtoss";NA;455;0
"Upgrade";"ProtossAirArmorsLevel2";NA;455;0
"Upgrade";"SprayProtoss";NA;455;0
