"type";"unit_name";"on_building";"total_supply";"supply"
"Unit";"Overlord";"Larva";14;0
"Building";"SpawningPool";NA;12;0
"Unit";"Zergling";"Larva";15;1
"Unit";"Zergling";"Larva";15;1
"Unit";"Zergling";"Larva";15;1
"Unit";"Zergling";"Larva";15;1
"Unit";"Zergling";"Larva";15;1
"Unit";"Zergling";"Larva";15;1
"Unit";"Zergling";"Larva";15;1
"Unit";"Zergling";"Larva";15;1
"Unit";"Zergling";"Larva";21;1
"Unit";"Zergling";"Larva";21;1
"Unit";"Zergling";"Larva";23;1
"Unit";"Zergling";"Larva";23;1
"Unit";"Overlord";"Larva";25;0
"Unit";"Queen";"Hatchery";23;2
"Building";"Hatchery";NA;15;0
"Unit";"Zergling";"Larva";30;1
"Unit";"Zergling";"Larva";30;1
"Unit";"Queen";"Hatchery";27;2
"Unit";"Zergling";"Larva";31;1
"Unit";"Zergling";"Larva";31;1
"Unit";"Zergling";"Larva";31;1
"Unit";"Zergling";"Larva";31;1
"Unit";"Zergling";"Larva";31;1
"Unit";"Zergling";"Larva";31;1
"Unit";"Zergling";"Larva";31;1
"Unit";"Zergling";"Larva";31;1
"Unit";"Zergling";"Larva";35;1
"Unit";"Zergling";"Larva";35;1
"Unit";"Zergling";"Larva";35;1
"Unit";"Zergling";"Larva";35;1
"Unit";"Zergling";"Larva";35;1
"Unit";"Zergling";"Larva";35;1
"Unit";"Overlord";"Larva";39;0
"Unit";"Zergling";"Larva";49;1
"Unit";"Zergling";"Larva";49;1
"Unit";"Zergling";"Larva";50;1
"Unit";"Zergling";"Larva";50;1
"Building";"CreepTumorQueen";NA;51;0
"Unit";"Zergling";"Larva";50;1
"Unit";"Zergling";"Larva";50;1
"Unit";"Zergling";"Larva";51;1
"Unit";"Zergling";"Larva";51;1
"Unit";"Zergling";"Larva";51;1
"Unit";"Zergling";"Larva";51;1
"Unit";"Zergling";"Larva";51;1
"Unit";"Zergling";"Larva";51;1
"Unit";"Zergling";"Larva";51;1
"Unit";"Zergling";"Larva";51;1
"Unit";"Zergling";"Larva";51;1
"Unit";"Zergling";"Larva";51;1
"Unit";"Overlord";"Larva";51;0
"Unit";"Queen";"Hatchery";77;2
"Building";"EvolutionChamber";NA;80;0
"Building";"EvolutionChamber";NA;85;0
"Building";"Extractor";NA;85;0
"Building";"Extractor";NA;85;0
"Building";"RoachWarren";NA;85;0
"Unit";"Overlord";"Larva";96;0
"Unit";"Overlord";"Larva";96;0
"Unit";"Queen";"Hatchery";92;2
"Building";"Extractor";NA;98;0
"Unit";"Overlord";"Larva";101;0
"Unit";"Overlord";"Larva";101;0
"Unit";"Overlord";"Larva";103;0
"Unit";"Roach";"Larva";103;2
"Unit";"Roach";"Larva";103;2
"Unit";"Zergling";"Larva";103;1
"Unit";"Zergling";"Larva";103;1
"Unit";"Zergling";"Larva";103;1
"Unit";"Zergling";"Larva";103;1
"Unit";"Zergling";"Larva";103;1
"Unit";"Zergling";"Larva";103;1
"Unit";"Roach";"Larva";103;2
"Unit";"Roach";"Larva";103;2
"Unit";"Roach";"Larva";103;2
"Unit";"Roach";"Larva";103;2
"Unit";"Overlord";"Larva";117;0
"Unit";"Overlord";"Larva";117;0
"Building";"Extractor";NA;121;0
"Unit";"Roach";"Larva";130;2
"Unit";"Roach";"Larva";130;2
"Unit";"Roach";"Larva";130;2
"Unit";"Roach";"Larva";130;2
"Unit";"Roach";"Larva";131;2
"Unit";"Roach";"Larva";131;2
"Unit";"Roach";"Larva";131;2
"Upgrade";"ZergMissileWeaponsLevel1";"EvolutionChamber";103;0
"Unit";"Roach";"Larva";131;2
"Unit";"Roach";"Larva";131;2
"Unit";"Roach";"Larva";131;2
"Unit";"Roach";"Larva";131;2
"Unit";"Roach";"Larva";143;2
"Unit";"Overlord";"Larva";143;0
"Unit";"Roach";"Larva";153;2
"Unit";"Roach";"Larva";153;2
"Unit";"Roach";"Larva";153;2
"Upgrade";"GlialReconstitution";"RoachWarren";131;0
"Unit";"Roach";"Larva";155;2
"Unit";"Roach";"Larva";155;2
"Unit";"Roach";"Larva";155;2
"Unit";"Roach";"Larva";155;2
"Building";"CreepTumorQueen";NA;159;0
"Unit";"Overlord";"Larva";159;0
"Unit";"Overlord";"Larva";159;0
"Unit";"Overlord";"Larva";159;0
"Unit";"Overlord";"Larva";161;0
"Unit";"Overlord";"Larva";161;0
"Unit";"Roach";"Larva";169;2
"Unit";"Roach";"Larva";169;2
"Unit";"Roach";"Larva";169;2
"Unit";"Roach";"Larva";169;2
"Unit";"Roach";"Larva";169;2
"Unit";"Roach";"Larva";169;2
"Unit";"Roach";"Larva";169;2
"Unit";"Roach";"Larva";169;2
"Unit";"Roach";"Larva";169;2
"Unit";"Queen";"Hatchery";169;2
"Building";"EvolutionChamber";NA;181;0
"Unit";"Roach";"Larva";187;2
"Unit";"Roach";"Larva";187;2
"Unit";"Roach";"Larva";187;2
"Unit";"Roach";"Larva";187;2
"Unit";"Roach";"Larva";187;2
"Unit";"Roach";"Larva";187;2
"Unit";"Roach";"Larva";187;2
"Building";"CreepTumor";NA;187;0
"Upgrade";"ZergGroundArmorsLevel1";"EvolutionChamber";155;0
"Unit";"Roach";"Larva";187;2
"Building";"Hatchery";NA;161;0
"Unit";"Overlord";"Larva";203;0
"Unit";"Overlord";"Larva";203;0
"Unit";"Overlord";"Larva";209;0
"Unit";"Overlord";"Larva";209;0
"Building";"SporeCrawler";NA;209;0
"Upgrade";"ZergMissileWeaponsLevel2";"EvolutionChamber";169;0
"Unit";"Roach";"Larva";209;2
"Unit";"Roach";"Larva";209;2
"Unit";"Roach";"Larva";209;2
"Unit";"Roach";"Larva";209;2
"Unit";"Roach";"Larva";209;2
"Unit";"Roach";"Larva";209;2
"Unit";"Roach";"Larva";209;2
"Upgrade";"Burrow";"Hatchery";206;0
"Unit";"Roach";"Larva";209;2
"Unit";"Roach";"Larva";209;2
"Unit";"Roach";"Larva";217;2
"Upgrade";"TunnelingClaws";"RoachWarren";209;0
"Unit";"Roach";"Larva";217;2
"Unit";"Roach";"Larva";217;2
"Unit";"Roach";"Larva";223;2
"Unit";"Roach";"Larva";229;2
"Unit";"Roach";"Larva";229;2
"Unit";"Roach";"Larva";229;2
"Unit";"Roach";"Larva";235;2
"Unit";"Roach";"Larva";235;2
"Unit";"Roach";"Larva";235;2
"Unit";"Roach";"Larva";241;2
"Unit";"Roach";"Larva";241;2
"Unit";"Roach";"Larva";241;2
"Unit";"Roach";"Larva";241;2
"Unit";"Roach";"Larva";241;2
"Unit";"Roach";"Larva";247;2
"Unit";"Roach";"Larva";247;2
"Unit";"Roach";"Larva";247;2
"Unit";"Roach";"Larva";247;2
