"type";"unit_name";"on_building";"total_supply";"supply"
"Unit";"Overlord";"Larva";12;0
"Building";"Extractor";NA;18;0
"Unit";"Overlord";"Larva";21;0
"Building";"SpawningPool";NA;19;0
"Building";"Hatchery";NA;17;0
"Unit";"Zergling";"Larva";22;1
"Unit";"Zergling";"Larva";22;1
"Unit";"Zergling";"Larva";22;1
"Unit";"Zergling";"Larva";22;1
"Unit";"Queen";"Hatchery";22;2
"Unit";"Queen";"Hatchery";22;2
"Unit";"Overlord";"Larva";36;0
"Building";"EvolutionChamber";NA;36;0
"Unit";"Queen";"Hatchery";33;2
"Building";"RoachWarren";NA;38;0
"Building";"Extractor";NA;45;0
"Unit";"Overlord";"Larva";48;0
"Building";"CreepTumorQueen";NA;52;0
"Unit";"Overlord";"Larva";52;0
"Unit";"Overlord";"Larva";52;0
"Unit";"Roach";"Larva";52;2
"Unit";"Roach";"Larva";52;2
"Unit";"Roach";"Larva";52;2
"Unit";"Roach";"Larva";52;2
"Unit";"Overlord";"Larva";52;0
"Unit";"Roach";"Larva";52;2
"Unit";"Overlord";"Larva";52;0
"Building";"CreepTumor";NA;60;0
"Building";"CreepTumorQueen";NA;60;0
"Unit";"Roach";"Larva";60;2
"Unit";"Roach";"Larva";60;2
"Unit";"Roach";"Larva";60;2
"Unit";"Roach";"Larva";60;2
"Building";"Extractor";NA;62;0
"Unit";"Roach";"Larva";71;2
"Unit";"Roach";"Larva";71;2
"Upgrade";"GlialReconstitution";"RoachWarren";52;0
"Unit";"Roach";"Larva";71;2
"Upgrade";"ZergMissileWeaponsLevel1";"EvolutionChamber";52;0
"Unit";"Roach";"Larva";73;2
"Unit";"Roach";"Larva";73;2
"Unit";"Roach";"Larva";73;2
"Unit";"Overlord";"Larva";79;0
"Unit";"Roach";"Larva";81;2
"Unit";"Roach";"Larva";85;2
"Unit";"Roach";"Larva";85;2
"Unit";"Roach";"Larva";90;2
"Unit";"Roach";"Larva";90;2
"Unit";"Roach";"Larva";90;2
"Unit";"Roach";"Larva";90;2
"Building";"Hatchery";NA;63;0
"Unit";"Roach";"Larva";96;2
"Unit";"Roach";"Larva";96;2
"Unit";"Roach";"Larva";96;2
"Unit";"Roach";"Larva";96;2
"Unit";"Roach";"Larva";102;2
"Unit";"Roach";"Larva";102;2
"Unit";"Roach";"Larva";104;2
"Unit";"Roach";"Larva";104;2
"Unit";"Roach";"Larva";104;2
"Unit";"Roach";"Larva";125;2
"Unit";"Roach";"Larva";125;2
"Unit";"Overlord";"Larva";127;0
"Unit";"Overlord";"Larva";127;0
"Building";"CreepTumor";NA;128;0
"Unit";"Overlord";"Larva";128;0
"Unit";"Overlord";"Larva";128;0
"Building";"Extractor";NA;128;0
"Unit";"Overlord";"Larva";132;0
"Unit";"Roach";"Larva";140;2
"Unit";"Roach";"Larva";140;2
"Unit";"Roach";"Larva";142;2
"Unit";"Roach";"Larva";148;2
"Unit";"Roach";"Larva";148;2
"Unit";"Roach";"Larva";148;2
"Unit";"Roach";"Larva";148;2
"Unit";"Roach";"Larva";148;2
"Unit";"Roach";"Larva";148;2
"Building";"Extractor";NA;148;0
"Unit";"Roach";"Larva";148;2
"Unit";"Roach";"Larva";148;2
"Unit";"Overlord";"Larva";154;0
"Unit";"Overlord";"Larva";154;0
"Unit";"Overlord";"Larva";154;0
"Building";"CreepTumor";NA;164;0
"Unit";"Roach";"Larva";170;2
"Building";"CreepTumor";NA;170;0
"Unit";"Overlord";"Larva";170;0
"Unit";"Overlord";"Larva";170;0
"Unit";"Roach";"Larva";170;2
"Unit";"Roach";"Larva";170;2
"Unit";"Roach";"Larva";170;2
"Unit";"Roach";"Larva";170;2
"Unit";"Roach";"Larva";170;2
"Unit";"Roach";"Larva";170;2
"Unit";"Roach";"Larva";170;2
"Unit";"Roach";"Larva";170;2
"Unit";"Roach";"Larva";170;2
"Unit";"Roach";"Larva";170;2
"Unit";"Roach";"Larva";172;2
"Unit";"Roach";"Larva";172;2
"Unit";"Roach";"Larva";180;2
"Unit";"Roach";"Larva";180;2
"Unit";"Roach";"Larva";180;2
"Unit";"Roach";"Larva";180;2
"Unit";"Roach";"Larva";180;2
"Unit";"Roach";"Larva";192;2
"Unit";"Roach";"Larva";192;2
"Unit";"Roach";"Larva";192;2
"Upgrade";"ZergMissileWeaponsLevel2";"EvolutionChamber";139;0
"Unit";"Overlord";"Larva";196;0
"Unit";"Overlord";"Larva";196;0
"Unit";"Overlord";"Larva";208;0
"Unit";"Overlord";"Larva";212;0
"Building";"CreepTumor";NA;212;0
"Unit";"Roach";"Larva";212;2
"Unit";"Roach";"Larva";212;2
"Unit";"Roach";"Larva";212;2
"Unit";"Roach";"Larva";212;2
"Unit";"Roach";"Larva";212;2
"Unit";"Roach";"Larva";212;2
"Unit";"Roach";"Larva";212;2
"Unit";"Roach";"Larva";212;2
"Unit";"Roach";"Larva";212;2
"Unit";"Roach";"Larva";212;2
"Unit";"Roach";"Larva";212;2
"Unit";"Roach";"Larva";212;2
"Unit";"Roach";"Larva";212;2
"Building";"Hatchery";NA;180;0
"Unit";"Roach";"Larva";212;2
"Unit";"Roach";"Larva";240;2
"Unit";"Roach";"Larva";240;2
"Unit";"Roach";"Larva";240;2
"Unit";"Roach";"Larva";240;2
"Unit";"Roach";"Larva";240;2
"Unit";"Roach";"Larva";240;2
"Unit";"Roach";"Larva";240;2
"Unit";"Roach";"Larva";240;2
"Unit";"Roach";"Larva";240;2
"Unit";"Roach";"Larva";240;2
"Unit";"Roach";"Larva";240;2
"Unit";"Roach";"Larva";240;2
"Unit";"Roach";"Larva";240;2
"Unit";"Roach";"Larva";240;2
"Unit";"Roach";"Larva";240;2
"Unit";"Roach";"Larva";240;2
"Unit";"Roach";"Larva";240;2
"Unit";"Roach";"Larva";240;2
"Unit";"Roach";"Larva";240;2
"Unit";"Roach";"Larva";258;2
"Unit";"Roach";"Larva";258;2
"Building";"Extractor";NA;258;0
"Unit";"Roach";"Larva";262;2
"Unit";"Roach";"Larva";262;2
"Unit";"Roach";"Larva";264;2
"Unit";"Roach";"Larva";270;2
"Unit";"Roach";"Larva";270;2
"Unit";"Roach";"Larva";282;2
"Unit";"Roach";"Larva";282;2
"Unit";"Roach";"Larva";282;2
"Unit";"Roach";"Larva";282;2
"Unit";"Roach";"Larva";282;2
"Unit";"Roach";"Larva";284;2
"Unit";"Roach";"Larva";288;2
"Unit";"Roach";"Larva";288;2
"Unit";"Roach";"Larva";288;2
"Upgrade";"ZergGroundArmorsLevel1";"EvolutionChamber";228;0
"Unit";"Roach";"Larva";290;2
"Unit";"Roach";"Larva";294;2
"Unit";"Roach";"Larva";294;2
