"type";"unit_name";"on_building";"total_supply";"supply"
"Unit";"Overlord";"Larva";12;0
"Building";"Extractor";NA;18;0
"Unit";"Overlord";"Larva";21;0
"Building";"SpawningPool";NA;19;0
"Building";"Hatchery";NA;17;0
"Unit";"Zergling";"Larva";23;1
"Unit";"Zergling";"Larva";23;1
"Unit";"Queen";"Hatchery";22;2
"Unit";"Queen";"Hatchery";22;2
"Unit";"Overlord";"Larva";38;0
"Unit";"Zergling";"Larva";40;1
"Unit";"Zergling";"Larva";40;1
"Unit";"Zergling";"Larva";40;1
"Unit";"Zergling";"Larva";40;1
"Building";"BanelingNest";NA;35;0
"Unit";"Overlord";"Larva";40;0
"Unit";"Baneling";"Zergling";44;0
"Unit";"Zergling";"Larva";44;1
"Unit";"Zergling";"Larva";44;1
"Unit";"Baneling";"Zergling";44;0
"Unit";"Zergling";"Larva";44;1
"Unit";"Zergling";"Larva";44;1
"Unit";"Zergling";"Larva";44;1
"Unit";"Zergling";"Larva";44;1
"Unit";"Zergling";"Larva";44;1
"Unit";"Zergling";"Larva";44;1
"Unit";"Zergling";"Larva";44;1
"Unit";"Zergling";"Larva";44;1
"Unit";"Zergling";"Larva";44;1
"Unit";"Zergling";"Larva";44;1
"Building";"Hatchery";NA;34;0
"Unit";"Queen";"Hatchery";40;2
"Unit";"Baneling";"Zergling";44;0
"Unit";"Baneling";"Zergling";44;0
"Unit";"Zergling";"Larva";56;1
"Unit";"Zergling";"Larva";56;1
"Unit";"Zergling";"Larva";56;1
"Unit";"Zergling";"Larva";56;1
"Unit";"Zergling";"Larva";56;1
"Unit";"Zergling";"Larva";56;1
"Unit";"Zergling";"Larva";56;1
"Unit";"Zergling";"Larva";56;1
"Unit";"Zergling";"Larva";56;1
"Unit";"Zergling";"Larva";56;1
"Unit";"Zergling";"Larva";56;1
"Unit";"Zergling";"Larva";56;1
"Unit";"Zergling";"Larva";56;1
"Unit";"Zergling";"Larva";56;1
"Unit";"Zergling";"Larva";58;1
"Unit";"Zergling";"Larva";58;1
"Unit";"Zergling";"Larva";58;1
"Unit";"Zergling";"Larva";58;1
"Unit";"Zergling";"Larva";58;1
"Unit";"Zergling";"Larva";58;1
"Unit";"Zergling";"Larva";58;1
"Unit";"Zergling";"Larva";58;1
"Unit";"Zergling";"Larva";58;1
"Unit";"Zergling";"Larva";58;1
"Unit";"Baneling";"Zergling";82;0
"Unit";"Baneling";"Zergling";82;0
"Unit";"Baneling";"Zergling";82;0
"Unit";"Baneling";"Zergling";82;0
"Unit";"Overlord";"Larva";88;0
"Building";"RoachWarren";NA;82;0
"Unit";"Zergling";"Larva";89;1
"Unit";"Zergling";"Larva";89;1
"Unit";"Zergling";"Larva";89;1
"Unit";"Zergling";"Larva";89;1
"Unit";"Zergling";"Larva";89;1
"Unit";"Zergling";"Larva";89;1
"Unit";"Zergling";"Larva";89;1
"Unit";"Zergling";"Larva";89;1
"Unit";"Zergling";"Larva";89;1
"Unit";"Zergling";"Larva";89;1
"Unit";"Zergling";"Larva";89;1
"Unit";"Zergling";"Larva";89;1
"Unit";"Zergling";"Larva";89;1
"Unit";"Zergling";"Larva";89;1
"Unit";"Zergling";"Larva";89;1
"Unit";"Zergling";"Larva";89;1
"Unit";"Zergling";"Larva";89;1
"Unit";"Zergling";"Larva";89;1
"Unit";"Baneling";"Zergling";89;0
"Unit";"Baneling";"Zergling";89;0
"Unit";"Baneling";"Zergling";89;0
"Unit";"Baneling";"Zergling";89;0
"Unit";"Baneling";"Zergling";89;0
"Unit";"Baneling";"Zergling";89;0
"Unit";"Zergling";"Larva";89;1
"Unit";"Zergling";"Larva";89;1
"Unit";"Zergling";"Larva";89;1
"Unit";"Zergling";"Larva";89;1
"Building";"EvolutionChamber";NA;89;0
"Unit";"Zergling";"Larva";89;1
"Unit";"Zergling";"Larva";89;1
"Unit";"Zergling";"Larva";89;1
"Unit";"Zergling";"Larva";89;1
"Unit";"Zergling";"Larva";89;1
"Unit";"Zergling";"Larva";89;1
"Unit";"Zergling";"Larva";89;1
"Unit";"Zergling";"Larva";89;1
"Unit";"Zergling";"Larva";89;1
"Unit";"Zergling";"Larva";89;1
"Building";"Extractor";NA;132;0
"Building";"Extractor";NA;132;0
"Building";"Extractor";NA;132;0
"Unit";"Queen";"Hatchery";121;2
"Unit";"Overlord";"Larva";132;0
"Unit";"Zergling";"Larva";135;1
"Unit";"Zergling";"Larva";135;1
"Unit";"Zergling";"Larva";137;1
"Unit";"Zergling";"Larva";137;1
"Unit";"Zergling";"Larva";137;1
"Unit";"Zergling";"Larva";137;1
"Unit";"Zergling";"Larva";137;1
"Unit";"Zergling";"Larva";137;1
"Unit";"Zergling";"Larva";137;1
"Unit";"Zergling";"Larva";137;1
"Unit";"Zergling";"Larva";137;1
"Unit";"Zergling";"Larva";137;1
"Unit";"Zergling";"Larva";137;1
"Unit";"Zergling";"Larva";137;1
"Unit";"Baneling";"Zergling";141;0
"Unit";"Baneling";"Zergling";141;0
"Unit";"Baneling";"Zergling";141;0
"Unit";"Zergling";"Larva";141;1
"Unit";"Zergling";"Larva";141;1
"Unit";"Zergling";"Larva";141;1
"Unit";"Zergling";"Larva";141;1
"Unit";"Zergling";"Larva";141;1
"Unit";"Zergling";"Larva";141;1
"Unit";"Zergling";"Larva";141;1
"Unit";"Zergling";"Larva";141;1
"Unit";"Zergling";"Larva";141;1
"Unit";"Zergling";"Larva";141;1
"Unit";"Zergling";"Larva";141;1
"Unit";"Zergling";"Larva";141;1
"Unit";"Zergling";"Larva";155;1
"Unit";"Zergling";"Larva";155;1
"Unit";"Zergling";"Larva";155;1
"Unit";"Zergling";"Larva";155;1
"Unit";"Zergling";"Larva";155;1
"Unit";"Zergling";"Larva";155;1
"Unit";"Baneling";"Zergling";155;0
"Unit";"Baneling";"Zergling";155;0
"Building";"SpineCrawler";NA;153;0
"Unit";"Overlord";"Larva";167;0
"Unit";"Overlord";"Larva";167;0
"Unit";"Overlord";"Larva";167;0
"Unit";"Overlord";"Larva";167;0
"Unit";"Overlord";"Larva";167;0
"Unit";"Overlord";"Larva";173;0
"Unit";"Baneling";"Zergling";178;0
"Unit";"Baneling";"Zergling";178;0
"Upgrade";"ZergMissileWeaponsLevel1";"EvolutionChamber";153;0
"Building";"CreepTumorQueen";NA;189;0
"Building";"Extractor";NA;182;0
"Building";"SporeCrawler";NA;189;0
"Building";"SporeCrawler";NA;189;0
"Building";"SporeCrawler";NA;189;0
"Building";"SporeCrawler";NA;189;0
"Building";"SporeCrawler";NA;189;0
"Building";"SporeCrawler";NA;189;0
"Building";"SporeCrawler";NA;189;0
"Building";"SporeCrawler";NA;189;0
"Building";"Extractor";NA;189;0
"Unit";"Queen";"Hatchery";189;2
"Building";"SporeCrawler";NA;196;0
"Building";"HydraliskDen";NA;189;0
"Unit";"Roach";"Larva";198;2
"Unit";"Roach";"Larva";198;2
"Unit";"Roach";"Larva";198;2
"Unit";"Roach";"Larva";199;2
"Unit";"Roach";"Larva";201;2
"Building";"Hatchery";NA;189;0
"Unit";"Hydralisk";"Larva";204;2
"Unit";"Hydralisk";"Larva";204;2
"Unit";"Hydralisk";"Larva";204;2
"Unit";"Hydralisk";"Larva";204;2
"Unit";"Hydralisk";"Larva";214;2
"Unit";"Hydralisk";"Larva";214;2
"Unit";"Overlord";"Larva";214;0
"Unit";"Overlord";"Larva";214;0
"Unit";"Overlord";"Larva";214;0
"Unit";"Hydralisk";"Larva";222;2
"Unit";"Hydralisk";"Larva";222;2
"Upgrade";"GlialReconstitution";"RoachWarren";204;0
"Unit";"Hydralisk";"Larva";226;2
"Unit";"Hydralisk";"Larva";226;2
"Unit";"Hydralisk";"Larva";226;2
"Building";"SporeCrawler";NA;227;0
"Building";"SporeCrawler";NA;227;0
"Building";"SporeCrawler";NA;227;0
"Upgrade";"EvolveMuscularAugments";"HydraliskDen";214;0
"Unit";"Hydralisk";"Larva";227;2
"Unit";"Hydralisk";"Larva";227;2
"Unit";"Hydralisk";"Larva";227;2
"Unit";"Roach";"Larva";231;2
"Unit";"Roach";"Larva";231;2
"Unit";"Roach";"Larva";231;2
"Unit";"Roach";"Larva";231;2
"Unit";"Roach";"Larva";231;2
"Unit";"Overlord";"Larva";237;0
"Unit";"Overlord";"Larva";237;0
"Unit";"Overlord";"Larva";237;0
"Building";"LurkerDenMP";NA;214;0
"Building";"CreepTumorQueen";NA;253;0
"Upgrade";"ZergMissileWeaponsLevel2";"EvolutionChamber";214;0
"Unit";"Hydralisk";"Larva";253;2
"Unit";"Hydralisk";"Larva";253;2
"Unit";"Hydralisk";"Larva";253;2
"Unit";"Hydralisk";"Larva";253;2
"Unit";"Hydralisk";"Larva";253;2
"Building";"CreepTumor";NA;253;0
"Unit";"Hydralisk";"Larva";253;2
"Unit";"Hydralisk";"Larva";253;2
"Unit";"Overlord";"Larva";263;0
"Unit";"Overlord";"Larva";263;0
"Unit";"Overlord";"Larva";263;0
"Unit";"Overlord";"Larva";263;0
"Unit";"Overlord";"Larva";263;0
"Unit";"Overlord";"Larva";267;0
"Unit";"Overlord";"Larva";267;0
"Unit";"Hydralisk";"Larva";267;2
"Unit";"Hydralisk";"Larva";267;2
"Unit";"Hydralisk";"Larva";267;2
"Unit";"Hydralisk";"Larva";267;2
"Unit";"Hydralisk";"Larva";267;2
"Unit";"Hydralisk";"Larva";267;2
"Unit";"Hydralisk";"Larva";267;2
"Unit";"Hydralisk";"Larva";267;2
"Unit";"Hydralisk";"Larva";267;2
"Unit";"Hydralisk";"Larva";267;2
"Unit";"Hydralisk";"Larva";267;2
"Unit";"Hydralisk";"Larva";267;2
"Unit";"Hydralisk";"Larva";267;2
"Upgrade";"EvolveGroovedSpines";"HydraliskDen";267;0
"Unit";"Roach";"Larva";293;2
"Unit";"Roach";"Larva";293;2
"Unit";"Roach";"Larva";293;2
"Unit";"Roach";"Larva";293;2
"Unit";"Roach";"Larva";293;2
"Unit";"Roach";"Larva";293;2
"Unit";"Roach";"Larva";293;2
"Unit";"Roach";"Larva";293;2
"Unit";"Roach";"Larva";293;2
"Unit";"Roach";"Larva";293;2
"Unit";"Roach";"Larva";293;2
"Unit";"Roach";"Larva";315;2
"Unit";"Roach";"Larva";315;2
"Unit";"Roach";"Larva";315;2
"Unit";"Roach";"Larva";315;2
"Unit";"Roach";"Larva";315;2
"Upgrade";"ZergGroundArmorsLevel1";"EvolutionChamber";267;0
"Building";"CreepTumor";NA;325;0
"Unit";"Hydralisk";"Larva";325;2
"Unit";"Hydralisk";"Larva";325;2
"Unit";"Hydralisk";"Larva";325;2
"Unit";"Hydralisk";"Larva";325;2
"Unit";"Hydralisk";"Larva";325;2
"Unit";"Hydralisk";"Larva";325;2
