"type";"unit_name";"on_building";"total_supply";"supply"
"Unit";"Overlord";"Larva";13;0
"Building";"Extractor";NA;18;0
"Unit";"Overlord";"Larva";21;0
"Building";"SpawningPool";NA;19;0
"Building";"Hatchery";NA;17;0
"Unit";"Zergling";"Larva";22;1
"Unit";"Zergling";"Larva";22;1
"Unit";"Zergling";"Larva";22;1
"Unit";"Zergling";"Larva";22;1
"Unit";"Zergling";"Larva";22;1
"Unit";"Zergling";"Larva";22;1
"Unit";"Queen";"Hatchery";22;2
"Unit";"Queen";"Hatchery";22;2
"Unit";"Overlord";"Larva";38;0
"Unit";"Zergling";"Larva";38;1
"Unit";"Zergling";"Larva";38;1
"Unit";"Zergling";"Larva";40;1
"Unit";"Zergling";"Larva";40;1
"Unit";"Zergling";"Larva";40;1
"Unit";"Zergling";"Larva";40;1
"Unit";"Zergling";"Larva";40;1
"Unit";"Zergling";"Larva";40;1
"Building";"BanelingNest";NA;36;0
"Unit";"Overlord";"Larva";40;0
"Unit";"Zergling";"Larva";40;1
"Unit";"Zergling";"Larva";40;1
"Unit";"Zergling";"Larva";40;1
"Unit";"Zergling";"Larva";40;1
"Unit";"Baneling";"Zergling";48;0
"Unit";"Baneling";"Zergling";49;0
"Building";"Hatchery";NA;34;0
"Unit";"Baneling";"Zergling";55;0
"Unit";"Baneling";"Zergling";55;0
"Unit";"Baneling";"Zergling";55;0
"Unit";"Baneling";"Zergling";55;0
"Unit";"Zergling";"Larva";61;1
"Unit";"Zergling";"Larva";61;1
"Building";"Extractor";NA;67;0
"Building";"Extractor";NA;67;0
"Building";"EvolutionChamber";NA;67;0
"Unit";"Queen";"Hatchery";61;2
"Unit";"Overlord";"Larva";74;0
"Unit";"Overlord";"Larva";74;0
"Building";"RoachWarren";NA;70;0
"Building";"CreepTumorQueen";NA;86;0
"Unit";"Overlord";"Larva";93;0
"Unit";"Overlord";"Larva";93;0
"Building";"Extractor";NA;93;0
"Unit";"Overlord";"Larva";93;0
"Unit";"Overlord";"Larva";93;0
"Building";"Extractor";NA;93;0
"Unit";"Zergling";"Larva";95;1
"Unit";"Zergling";"Larva";95;1
"Unit";"Zergling";"Larva";95;1
"Unit";"Zergling";"Larva";95;1
"Unit";"Zergling";"Larva";95;1
"Unit";"Zergling";"Larva";95;1
"Unit";"Zergling";"Larva";95;1
"Unit";"Zergling";"Larva";95;1
"Unit";"Zergling";"Larva";95;1
"Unit";"Zergling";"Larva";95;1
"Unit";"Overlord";"Larva";95;0
"Unit";"Overlord";"Larva";95;0
"Building";"CreepTumor";NA;105;0
"Unit";"Roach";"Larva";105;2
"Unit";"Roach";"Larva";105;2
"Unit";"Roach";"Larva";105;2
"Unit";"Roach";"Larva";105;2
"Unit";"Roach";"Larva";105;2
"Unit";"Roach";"Larva";105;2
"Unit";"Roach";"Larva";105;2
"Unit";"Roach";"Larva";105;2
"Unit";"Roach";"Larva";105;2
"Unit";"Roach";"Larva";105;2
"Unit";"Roach";"Larva";105;2
"Unit";"Baneling";"Zergling";110;0
"Unit";"Baneling";"Zergling";110;0
"Unit";"Roach";"Larva";110;2
"Unit";"Roach";"Larva";110;2
"Unit";"Roach";"Larva";110;2
"Upgrade";"ZergMissileWeaponsLevel1";"EvolutionChamber";86;0
"Unit";"Roach";"Larva";132;2
"Unit";"Roach";"Larva";132;2
"Unit";"Roach";"Larva";132;2
"Unit";"Roach";"Larva";132;2
"Unit";"Roach";"Larva";132;2
"Unit";"Roach";"Larva";132;2
"Unit";"Roach";"Larva";132;2
"Unit";"Roach";"Larva";132;2
"Upgrade";"GlialReconstitution";"RoachWarren";105;0
"Building";"CreepTumor";NA;138;0
"Unit";"Roach";"Larva";138;2
"Unit";"Overlord";"Larva";138;0
"Unit";"Overlord";"Larva";138;0
"Unit";"Overlord";"Larva";138;0
"Unit";"Overlord";"Larva";138;0
"Building";"Extractor";NA;156;0
"Unit";"Roach";"Larva";156;2
"Building";"CreepTumor";NA;157;0
"Unit";"Roach";"Larva";156;2
"Building";"HydraliskDen";NA;156;0
"Unit";"Roach";"Larva";162;2
"Unit";"Roach";"Larva";162;2
"Unit";"Roach";"Larva";162;2
"Unit";"Roach";"Larva";162;2
"Unit";"Roach";"Larva";162;2
"Unit";"Roach";"Larva";162;2
"Unit";"Roach";"Larva";162;2
"Unit";"Roach";"Larva";162;2
"Unit";"Roach";"Larva";162;2
"Unit";"Roach";"Larva";162;2
"Unit";"Roach";"Larva";166;2
"Unit";"Roach";"Larva";166;2
"Unit";"Roach";"Larva";166;2
"Unit";"Overlord";"Larva";186;0
"Unit";"Overlord";"Larva";186;0
"Unit";"Overlord";"Larva";186;0
"Unit";"Overlord";"Larva";186;0
"Building";"Hatchery";NA;156;0
"Unit";"Roach";"Larva";192;2
"Unit";"Roach";"Larva";192;2
"Unit";"Roach";"Larva";192;2
"Unit";"Roach";"Larva";192;2
"Unit";"Roach";"Larva";192;2
"Unit";"Roach";"Larva";192;2
"Unit";"Roach";"Larva";192;2
"Unit";"Roach";"Larva";192;2
"Unit";"Roach";"Larva";192;2
"Unit";"Roach";"Larva";192;2
"Unit";"Roach";"Larva";192;2
"Unit";"Roach";"Larva";192;2
"Unit";"Roach";"Larva";192;2
"Unit";"Roach";"Larva";192;2
"Unit";"Roach";"Larva";192;2
"Unit";"Roach";"Larva";192;2
"Unit";"Roach";"Larva";192;2
"Unit";"Roach";"Larva";192;2
"Unit";"Roach";"Larva";192;2
"Unit";"Roach";"Larva";206;2
"Unit";"Roach";"Larva";210;2
"Unit";"Roach";"Larva";210;2
"Unit";"Roach";"Larva";210;2
"Unit";"Roach";"Larva";210;2
"Unit";"Roach";"Larva";210;2
"Upgrade";"ZergMissileWeaponsLevel2";"EvolutionChamber";162;0
"Upgrade";"EvolveGroovedSpines";"HydraliskDen";192;0
"Unit";"Roach";"Larva";212;2
"Unit";"Roach";"Larva";242;2
"Unit";"Roach";"Larva";242;2
"Unit";"Roach";"Larva";242;2
"Unit";"Roach";"Larva";242;2
"Unit";"Roach";"Larva";242;2
"Unit";"Roach";"Larva";242;2
"Unit";"Roach";"Larva";242;2
"Unit";"Roach";"Larva";242;2
"Unit";"Roach";"Larva";242;2
"Unit";"Roach";"Larva";242;2
"Building";"LurkerDenMP";NA;192;0
"Unit";"Roach";"Larva";242;2
"Unit";"Roach";"Larva";244;2
"Unit";"Roach";"Larva";244;2
"Unit";"Roach";"Larva";244;2
"Unit";"Roach";"Larva";244;2
"Unit";"Roach";"Larva";244;2
"Building";"CreepTumor";NA;244;0
"Unit";"Hydralisk";"Larva";244;2
"Unit";"Hydralisk";"Larva";264;2
"Unit";"Hydralisk";"Larva";264;2
"Unit";"Hydralisk";"Larva";292;2
"Unit";"Hydralisk";"Larva";292;2
"Unit";"Hydralisk";"Larva";292;2
"Building";"Hatchery";NA;244;0
"Unit";"Roach";"Larva";293;2
"Unit";"Roach";"Larva";293;2
"Unit";"Roach";"Larva";293;2
"Unit";"Roach";"Larva";293;2
"Unit";"Roach";"Larva";293;2
"Upgrade";"EvolveMuscularAugments";"HydraliskDen";282;0
"Unit";"Hydralisk";"Larva";293;2
"Unit";"Hydralisk";"Larva";293;2
"Unit";"Hydralisk";"Larva";293;2
"Unit";"Roach";"Larva";299;2
"Unit";"Overlord";"Larva";299;0
"Unit";"Overlord";"Larva";301;0
"Unit";"Overlord";"Larva";301;0
"Building";"CreepTumor";NA;309;0
"Building";"Extractor";NA;299;0
"Building";"Extractor";NA;299;0
"Building";"SpineCrawler";NA;309;0
"Upgrade";"ZergGroundArmorsLevel1";"EvolutionChamber";292;0
"Building";"SpineCrawler";NA;315;0
"Building";"SpineCrawler";NA;315;0
"Unit";"Roach";"Larva";317;2
"Unit";"Roach";"Larva";317;2
"Unit";"Roach";"Larva";317;2
"Unit";"Roach";"Larva";317;2
"Unit";"Roach";"Larva";317;2
"Building";"CreepTumor";NA;335;0
"Building";"SpineCrawler";NA;317;0
"Building";"SpineCrawler";NA;317;0
"Building";"SpineCrawler";NA;317;0
"Unit";"Roach";"Larva";335;2
"Unit";"Roach";"Larva";335;2
"Unit";"Roach";"Larva";335;2
"Unit";"Roach";"Larva";335;2
"Unit";"Roach";"Larva";335;2
"Unit";"Roach";"Larva";335;2
"Unit";"Roach";"Larva";335;2
"Unit";"Roach";"Larva";335;2
"Unit";"Roach";"Larva";335;2
"Unit";"Roach";"Larva";335;2
"Unit";"Roach";"Larva";335;2
"Unit";"Roach";"Larva";335;2
"Unit";"Roach";"Larva";335;2
"Unit";"Roach";"Larva";335;2
"Unit";"Roach";"Larva";335;2
"Unit";"Roach";"Larva";335;2
"Unit";"Roach";"Larva";335;2
"Unit";"Roach";"Larva";335;2
"Building";"Hatchery";NA;317;0
"Upgrade";"Burrow";"Hatchery";317;0
"Building";"InfestationPit";NA;371;0
"Unit";"Hydralisk";"Larva";371;2
"Unit";"Hydralisk";"Larva";371;2
"Unit";"Hydralisk";"Larva";371;2
"Unit";"Hydralisk";"Larva";371;2
"Unit";"Roach";"Larva";379;2
"Unit";"Roach";"Larva";379;2
"Unit";"Roach";"Larva";379;2
"Unit";"Roach";"Larva";379;2
"Unit";"Roach";"Larva";379;2
"Unit";"Roach";"Larva";379;2
"Unit";"Roach";"Larva";379;2
"Unit";"Roach";"Larva";379;2
"Unit";"Roach";"Larva";379;2
"Unit";"Hydralisk";"Larva";379;2
"Unit";"Hydralisk";"Larva";379;2
"Unit";"Hydralisk";"Larva";379;2
"Unit";"Hydralisk";"Larva";379;2
"Unit";"Hydralisk";"Larva";379;2
"Unit";"Hydralisk";"Larva";379;2
"Unit";"Hydralisk";"Larva";379;2
"Unit";"Hydralisk";"Larva";379;2
"Unit";"Hydralisk";"Larva";379;2
"Unit";"Hydralisk";"Larva";379;2
"Unit";"Hydralisk";"Larva";379;2
"Unit";"Hydralisk";"Larva";379;2
"Unit";"Hydralisk";"Larva";379;2
"Unit";"Hydralisk";"Larva";379;2
"Unit";"Hydralisk";"Larva";379;2
"Unit";"Hydralisk";"Larva";379;2
"Unit";"Hydralisk";"Larva";379;2
"Unit";"Hydralisk";"Larva";379;2
"Unit";"Hydralisk";"Larva";379;2
"Unit";"Hydralisk";"Larva";379;2
"Unit";"Hydralisk";"Larva";379;2
"Unit";"Hydralisk";"Larva";439;2
"Unit";"Hydralisk";"Larva";439;2
"Unit";"Hydralisk";"Larva";439;2
"Unit";"Hydralisk";"Larva";439;2
"Unit";"Hydralisk";"Larva";439;2
"Unit";"Hydralisk";"Larva";439;2
"Unit";"Hydralisk";"Larva";439;2
"Unit";"Hydralisk";"Larva";439;2
"Unit";"Hydralisk";"Larva";439;2
"Unit";"Roach";"Larva";439;2
"Unit";"Roach";"Larva";439;2
"Unit";"Roach";"Larva";439;2
"Unit";"Roach";"Larva";439;2
"Unit";"Roach";"Larva";439;2
"Unit";"Roach";"Larva";439;2
"Unit";"Roach";"Larva";439;2
"Unit";"Roach";"Larva";439;2
"Unit";"Roach";"Larva";439;2
"Unit";"Roach";"Larva";439;2
"Unit";"Roach";"Larva";439;2
"Unit";"Roach";"Larva";439;2
"Unit";"Roach";"Larva";439;2
"Unit";"Roach";"Larva";439;2
"Unit";"Roach";"Larva";439;2
"Unit";"Roach";"Larva";439;2
"Unit";"Roach";"Larva";439;2
"Unit";"Hydralisk";"Larva";439;2
"Unit";"Hydralisk";"Larva";439;2
"Unit";"Roach";"Larva";457;2
"Unit";"Roach";"Larva";457;2
"Building";"Extractor";NA;491;0
"Building";"Extractor";NA;491;0
"Unit";"Roach";"Larva";495;2
"Unit";"Roach";"Larva";495;2
"Unit";"Roach";"Larva";495;2
"Unit";"Overlord";"Larva";495;0
"Unit";"Overlord";"Larva";495;0
"Unit";"Hydralisk";"Larva";505;2
"Unit";"Hydralisk";"Larva";505;2
"Unit";"Hydralisk";"Larva";505;2
"Unit";"Hydralisk";"Larva";505;2
"Unit";"Hydralisk";"Larva";505;2
"Unit";"Hydralisk";"Larva";505;2
"Unit";"Hydralisk";"Larva";505;2
"Unit";"Hydralisk";"Larva";505;2
"Unit";"Hydralisk";"Larva";505;2
"Building";"Hatchery";NA;495;0
"Unit";"Overlord";"Larva";505;0
"Unit";"Overlord";"Larva";505;0
"Unit";"Roach";"Larva";505;2
"Building";"Hatchery";NA;505;0
"Unit";"Roach";"Larva";526;2
"Unit";"Roach";"Larva";526;2
"Unit";"Roach";"Larva";526;2
"Unit";"Roach";"Larva";526;2
"Unit";"Roach";"Larva";526;2
"Unit";"Roach";"Larva";526;2
"Unit";"Roach";"Larva";526;2
"Unit";"Roach";"Larva";526;2
"Unit";"Roach";"Larva";526;2
"Unit";"Roach";"Larva";526;2
"Unit";"Roach";"Larva";526;2
"Unit";"Roach";"Larva";526;2
"Unit";"Roach";"Larva";526;2
"Unit";"Roach";"Larva";526;2
"Unit";"Hydralisk";"Larva";526;2
"Unit";"Hydralisk";"Larva";526;2
"Unit";"Hydralisk";"Larva";526;2
"Unit";"Hydralisk";"Larva";526;2
"Unit";"Hydralisk";"Larva";526;2
"Unit";"Roach";"Larva";564;2
"Unit";"Roach";"Larva";564;2
"Unit";"Roach";"Larva";564;2
"Unit";"Roach";"Larva";564;2
"Unit";"Roach";"Larva";564;2
"Unit";"Roach";"Larva";564;2
"Unit";"Roach";"Larva";564;2
"Unit";"Roach";"Larva";564;2
"Unit";"Roach";"Larva";564;2
"Unit";"Roach";"Larva";564;2
"Unit";"Roach";"Larva";564;2
"Unit";"Roach";"Larva";564;2
"Unit";"Hydralisk";"Larva";564;2
"Unit";"Hydralisk";"Larva";564;2
"Unit";"Hydralisk";"Larva";564;2
"Unit";"Hydralisk";"Larva";564;2
"Unit";"Roach";"Larva";596;2
"Unit";"Roach";"Larva";596;2
"Unit";"Roach";"Larva";596;2
"Unit";"Roach";"Larva";596;2
"Unit";"Roach";"Larva";596;2
"Unit";"Hydralisk";"Larva";596;2
"Unit";"Hydralisk";"Larva";596;2
"Unit";"Hydralisk";"Larva";596;2
"Unit";"Hydralisk";"Larva";596;2
"Unit";"Hydralisk";"Larva";596;2
"Unit";"Hydralisk";"Larva";596;2
"Unit";"Roach";"Larva";596;2
"Unit";"Roach";"Larva";596;2
"Unit";"Roach";"Larva";596;2
"Unit";"Roach";"Larva";596;2
"Unit";"Roach";"Larva";596;2
