"type";"unit_name";"on_building";"total_supply";"supply"
"Unit";"Overlord";"Larva";13;0
"Building";"Extractor";NA;17;0
"Unit";"Overlord";"Larva";21;0
"Building";"Hatchery";NA;16;0
"Building";"SpawningPool";NA;19;0
"Unit";"Zergling";"Larva";22;1
"Unit";"Zergling";"Larva";22;1
"Unit";"Queen";"Hatchery";22;2
"Unit";"Queen";"Hatchery";22;2
"Unit";"Queen";"Hatchery";34;2
"Unit";"Overlord";"Larva";36;0
"Unit";"Zergling";"Larva";36;1
"Unit";"Zergling";"Larva";36;1
"Unit";"Zergling";"Larva";36;1
"Unit";"Zergling";"Larva";36;1
"Building";"CreepTumorQueen";NA;36;0
"Unit";"Zergling";"Larva";36;1
"Unit";"Zergling";"Larva";36;1
"Building";"BanelingNest";NA;34;0
"Building";"CreepTumor";NA;45;0
"Unit";"Zergling";"Larva";45;1
"Unit";"Zergling";"Larva";45;1
"Unit";"Zergling";"Larva";45;1
"Unit";"Zergling";"Larva";45;1
"Unit";"Zergling";"Larva";45;1
"Unit";"Zergling";"Larva";45;1
"Unit";"Zergling";"Larva";45;1
"Unit";"Zergling";"Larva";45;1
"Unit";"Zergling";"Larva";45;1
"Unit";"Zergling";"Larva";45;1
"Unit";"Zergling";"Larva";45;1
"Unit";"Zergling";"Larva";45;1
"Unit";"Zergling";"Larva";45;1
"Unit";"Zergling";"Larva";45;1
"Building";"Hatchery";NA;34;0
"Unit";"Baneling";"Zergling";59;0
"Unit";"Baneling";"Zergling";59;0
"Unit";"Baneling";"Zergling";59;0
"Unit";"Baneling";"Zergling";59;0
"Unit";"Baneling";"Zergling";59;0
"Unit";"Baneling";"Zergling";59;0
"Building";"EvolutionChamber";NA;45;0
"Unit";"Baneling";"Zergling";59;0
"Unit";"Baneling";"Zergling";59;0
"Unit";"Baneling";"Zergling";59;0
"Unit";"Zergling";"Larva";59;1
"Unit";"Zergling";"Larva";59;1
"Unit";"Zergling";"Larva";59;1
"Unit";"Zergling";"Larva";59;1
"Unit";"Zergling";"Larva";59;1
"Unit";"Zergling";"Larva";59;1
"Unit";"Overlord";"Larva";59;0
"Unit";"Overlord";"Larva";59;0
"Building";"Extractor";NA;59;0
"Unit";"Queen";"Hatchery";59;2
"Unit";"Zergling";"Larva";72;1
"Unit";"Zergling";"Larva";72;1
"Unit";"Zergling";"Larva";72;1
"Unit";"Zergling";"Larva";72;1
"Unit";"Zergling";"Larva";72;1
"Unit";"Zergling";"Larva";72;1
"Unit";"Zergling";"Larva";72;1
"Unit";"Zergling";"Larva";72;1
"Unit";"Zergling";"Larva";72;1
"Unit";"Zergling";"Larva";72;1
"Unit";"Zergling";"Larva";72;1
"Unit";"Zergling";"Larva";72;1
"Unit";"Zergling";"Larva";72;1
"Unit";"Zergling";"Larva";72;1
"Building";"RoachWarren";NA;72;0
"Unit";"Overlord";"Larva";100;0
"Unit";"Overlord";"Larva";100;0
"Unit";"Roach";"Larva";100;2
"Unit";"Roach";"Larva";100;2
"Building";"Extractor";NA;100;0
"Unit";"Baneling";"Zergling";105;0
"Unit";"Baneling";"Zergling";105;0
"Unit";"Baneling";"Zergling";105;0
"Unit";"Baneling";"Zergling";105;0
"Unit";"Overlord";"Larva";105;0
"Unit";"Roach";"Larva";109;2
"Unit";"Roach";"Larva";109;2
"Unit";"Roach";"Larva";109;2
"Unit";"Roach";"Larva";109;2
"Unit";"Roach";"Larva";109;2
"Unit";"Roach";"Larva";109;2
"Unit";"Roach";"Larva";109;2
"Unit";"Roach";"Larva";109;2
"Unit";"Roach";"Larva";109;2
"Unit";"Overlord";"Larva";109;0
"Unit";"Overlord";"Larva";109;0
"Unit";"Roach";"Larva";109;2
"Unit";"Roach";"Larva";109;2
"Unit";"Roach";"Larva";109;2
"Unit";"Overlord";"Larva";127;0
"Unit";"Overlord";"Larva";135;0
"Unit";"Overlord";"Larva";135;0
"Building";"Extractor";NA;135;0
"Upgrade";"ZergMissileWeaponsLevel1";"EvolutionChamber";109;0
"Building";"Extractor";NA;135;0
"Unit";"Roach";"Larva";142;2
"Unit";"Roach";"Larva";142;2
"Building";"CreepTumorQueen";NA;148;0
"Building";"CreepTumorQueen";NA;148;0
"Building";"CreepTumorQueen";NA;149;0
"Unit";"Roach";"Larva";148;2
"Unit";"Roach";"Larva";148;2
"Unit";"Roach";"Larva";148;2
"Unit";"Roach";"Larva";148;2
"Unit";"Roach";"Larva";148;2
"Unit";"Roach";"Larva";148;2
"Unit";"Roach";"Larva";148;2
"Upgrade";"GlialReconstitution";"RoachWarren";135;0
"Building";"Extractor";NA;157;0
"Unit";"Roach";"Larva";171;2
"Unit";"Roach";"Larva";171;2
"Unit";"Roach";"Larva";171;2
"Unit";"Overlord";"Larva";171;0
"Unit";"Overlord";"Larva";171;0
"Unit";"Overlord";"Larva";171;0
"Unit";"Overlord";"Larva";171;0
"Building";"Hatchery";NA;135;0
"Building";"CreepTumor";NA;177;0
"Building";"CreepTumor";NA;177;0
"Building";"CreepTumor";NA;177;0
"Unit";"Overlord";"Larva";171;0
"Unit";"Overlord";"Larva";171;0
"Unit";"Overlord";"Larva";171;0
"Unit";"Roach";"Larva";177;2
"Unit";"Roach";"Larva";177;2
"Unit";"Roach";"Larva";177;2
"Unit";"Roach";"Larva";177;2
"Unit";"Roach";"Larva";177;2
"Unit";"Roach";"Larva";177;2
"Unit";"Roach";"Larva";177;2
"Unit";"Roach";"Larva";177;2
"Unit";"Overlord";"Larva";177;0
"Unit";"Roach";"Larva";177;2
"Unit";"Roach";"Larva";177;2
"Unit";"Roach";"Larva";177;2
"Unit";"Roach";"Larva";177;2
"Unit";"Roach";"Larva";177;2
"Unit";"Roach";"Larva";177;2
"Unit";"Roach";"Larva";177;2
"Unit";"Queen";"Hatchery";177;2
"Unit";"Roach";"Larva";193;2
"Unit";"Roach";"Larva";193;2
"Unit";"Roach";"Larva";193;2
"Unit";"Roach";"Larva";193;2
"Unit";"Roach";"Larva";193;2
"Unit";"Roach";"Larva";193;2
"Unit";"Roach";"Larva";193;2
"Unit";"Roach";"Larva";205;2
"Unit";"Roach";"Larva";207;2
"Unit";"Roach";"Larva";207;2
"Unit";"Roach";"Larva";207;2
"Unit";"Roach";"Larva";207;2
"Unit";"Roach";"Larva";223;2
"Unit";"Roach";"Larva";223;2
"Unit";"Roach";"Larva";223;2
"Unit";"Overlord";"Larva";233;0
"Unit";"Overlord";"Larva";233;0
