"type";"unit_name";"on_building";"total_supply";"supply"
"Unit";"Overlord";"Larva";14;0
"Building";"SpawningPool";NA;12;0
"Unit";"Zergling";"Larva";15;1
"Unit";"Zergling";"Larva";15;1
"Unit";"Zergling";"Larva";15;1
"Unit";"Zergling";"Larva";15;1
"Unit";"Zergling";"Larva";15;1
"Unit";"Zergling";"Larva";15;1
"Unit";"Zergling";"Larva";15;1
"Unit";"Zergling";"Larva";15;1
"Unit";"Zergling";"Larva";21;1
"Unit";"Zergling";"Larva";21;1
"Unit";"Zergling";"Larva";23;1
"Unit";"Zergling";"Larva";23;1
"Unit";"Overlord";"Larva";25;0
"Unit";"Queen";"Hatchery";23;2
"Building";"Hatchery";NA;15;0
"Unit";"Queen";"Hatchery";28;2
"Unit";"Queen";"Hatchery";31;2
"Building";"CreepTumorQueen";NA;37;0
"Building";"EvolutionChamber";NA;46;0
"Building";"EvolutionChamber";NA;46;0
"Unit";"Overlord";"Larva";48;0
"Building";"CreepTumorQueen";NA;53;0
"Unit";"Overlord";"Larva";53;0
"Building";"RoachWarren";NA;48;0
"Unit";"Overlord";"Larva";53;0
"Building";"Extractor";NA;53;0
"Unit";"Queen";"Hatchery";53;2
"Building";"CreepTumorQueen";NA;62;0
"Building";"Extractor";NA;62;0
"Building";"Extractor";NA;62;0
"Building";"CreepTumor";NA;70;0
"Unit";"Overlord";"Larva";68;0
"Building";"CreepTumor";NA;71;0
"Building";"CreepTumorQueen";NA;71;0
"Unit";"Overlord";"Larva";71;0
"Unit";"Overlord";"Larva";71;0
"Unit";"Overlord";"Larva";71;0
"Unit";"Overlord";"Larva";74;0
"Building";"CreepTumor";NA;74;0
"Building";"CreepTumor";NA;77;0
"Unit";"Roach";"Larva";74;2
"Unit";"Overlord";"Larva";77;0
"Unit";"Roach";"Larva";78;2
"Building";"CreepTumor";NA;83;0
"Building";"Hatchery";NA;70;0
"Unit";"Overlord";"Larva";85;0
"Unit";"Roach";"Larva";92;2
"Unit";"Roach";"Larva";92;2
"Unit";"Roach";"Larva";92;2
"Building";"CreepTumor";NA;92;0
"Building";"Extractor";NA;92;0
"Unit";"Roach";"Larva";92;2
"Unit";"Roach";"Larva";92;2
"Unit";"Roach";"Larva";92;2
"Unit";"Roach";"Larva";92;2
"Unit";"Roach";"Larva";92;2
"Unit";"Roach";"Larva";94;2
"Unit";"Roach";"Larva";94;2
"Unit";"Roach";"Larva";94;2
"Unit";"Roach";"Larva";94;2
"Building";"Extractor";NA;100;0
"Building";"Extractor";NA;100;0
"Building";"SporeCrawler";NA;112;0
"Building";"SporeCrawler";NA;118;0
"Building";"SporeCrawler";NA;118;0
"Building";"SporeCrawler";NA;118;0
"Building";"SporeCrawler";NA;118;0
"Building";"SporeCrawler";NA;118;0
"Building";"SporeCrawler";NA;118;0
"Building";"SporeCrawler";NA;118;0
"Upgrade";"ZergMissileWeaponsLevel1";"EvolutionChamber";83;0
"Building";"SporeCrawler";NA;118;0
"Building";"HydraliskDen";NA;118;0
"Unit";"Overlord";"Larva";125;0
"Upgrade";"GlialReconstitution";"RoachWarren";100;0
"Unit";"Overlord";"Larva";125;0
"Unit";"Overlord";"Larva";125;0
"Unit";"Overlord";"Larva";125;0
"Unit";"Overlord";"Larva";129;0
"Unit";"Overlord";"Larva";129;0
"Unit";"Overlord";"Larva";129;0
"Building";"SporeCrawler";NA;129;0
"Building";"Extractor";NA;129;0
"Building";"SporeCrawler";NA;129;0
"Unit";"Hydralisk";"Larva";129;2
"Unit";"Hydralisk";"Larva";129;2
"Unit";"Hydralisk";"Larva";129;2
"Unit";"Hydralisk";"Larva";129;2
"Unit";"Hydralisk";"Larva";129;2
"Unit";"Hydralisk";"Larva";129;2
"Unit";"Hydralisk";"Larva";129;2
"Unit";"Hydralisk";"Larva";134;2
"Unit";"Hydralisk";"Larva";134;2
"Unit";"Overlord";"Larva";134;0
"Unit";"Hydralisk";"Larva";134;2
"Upgrade";"EvolveGroovedSpines";"HydraliskDen";129;0
"Unit";"Overlord";"Larva";150;0
"Unit";"Hydralisk";"Larva";148;2
"Unit";"Hydralisk";"Larva";154;2
"Unit";"Hydralisk";"Larva";154;2
"Unit";"Hydralisk";"Larva";154;2
"Building";"SporeCrawler";NA;158;0
"Upgrade";"ZergGroundArmorsLevel1";"EvolutionChamber";129;0
"Unit";"Overlord";"Larva";158;0
"Unit";"Overlord";"Larva";158;0
"Unit";"Hydralisk";"Larva";158;2
"Unit";"Hydralisk";"Larva";158;2
"Unit";"Hydralisk";"Larva";166;2
"Unit";"Hydralisk";"Larva";166;2
"Building";"SporeCrawler";NA;168;0
"Building";"SporeCrawler";NA;168;0
"Building";"InfestationPit";NA;160;0
"Unit";"Hydralisk";"Larva";168;2
"Unit";"Hydralisk";"Larva";168;2
"Upgrade";"ZergMissileWeaponsLevel2";"EvolutionChamber";129;0
"Unit";"Hydralisk";"Larva";170;2
"Unit";"Hydralisk";"Larva";176;2
"Upgrade";"EvolveMuscularAugments";"HydraliskDen";166;0
"Unit";"Hydralisk";"Larva";193;2
"Unit";"Hydralisk";"Larva";193;2
"Unit";"Hydralisk";"Larva";193;2
"Unit";"Hydralisk";"Larva";193;2
"Unit";"Roach";"Larva";195;2
"Unit";"Roach";"Larva";195;2
"Unit";"Roach";"Larva";195;2
"Unit";"Roach";"Larva";195;2
"Unit";"Roach";"Larva";195;2
"Unit";"Roach";"Larva";195;2
"Unit";"Roach";"Larva";209;2
"Unit";"Roach";"Larva";209;2
"Unit";"Roach";"Larva";209;2
"Unit";"Hydralisk";"Larva";220;2
"Unit";"Hydralisk";"Larva";220;2
"Unit";"Hydralisk";"Larva";220;2
"Unit";"Queen";"Hatchery";220;2
"Unit";"Roach";"Larva";226;2
"Unit";"Infestor";"Larva";220;2
"Unit";"Roach";"Larva";232;2
"Unit";"Infestor";"Larva";226;2
"Unit";"Infestor";"Larva";226;2
"Unit";"Roach";"Larva";232;2
"Unit";"Infestor";"Larva";226;2
"Unit";"Infestor";"Larva";226;2
"Unit";"Overlord";"Larva";236;0
"Unit";"Overlord";"Larva";236;0
"Unit";"Overlord";"Larva";236;0
"Upgrade";"ZergGroundArmorsLevel2";"EvolutionChamber";195;0
"Unit";"Overlord";"Larva";238;0
"Unit";"Overlord";"Larva";238;0
"Unit";"Overlord";"Larva";238;0
"Unit";"Overlord";"Larva";248;0
"Unit";"Overlord";"Larva";250;0
"Unit";"Roach";"Larva";250;2
"Unit";"Roach";"Larva";250;2
"Unit";"Roach";"Larva";250;2
"Unit";"Roach";"Larva";250;2
"Unit";"Roach";"Larva";250;2
"Unit";"Roach";"Larva";250;2
"Unit";"Roach";"Larva";250;2
"Unit";"Roach";"Larva";250;2
"Unit";"Roach";"Larva";250;2
"Unit";"Roach";"Larva";250;2
"Unit";"Roach";"Larva";250;2
"Unit";"Roach";"Larva";250;2
"Upgrade";"Burrow";"Hatchery";234;0
"Unit";"Roach";"Larva";250;2
"Unit";"Roach";"Larva";250;2
"Unit";"Roach";"Larva";274;2
"Unit";"Roach";"Larva";274;2
"Unit";"Roach";"Larva";278;2
"Unit";"Roach";"Larva";278;2
"Unit";"Roach";"Larva";278;2
"Unit";"Roach";"Larva";278;2
"Unit";"Hydralisk";"Larva";278;2
"Unit";"Hydralisk";"Larva";278;2
"Unit";"Roach";"Larva";278;2
"Unit";"Roach";"Larva";278;2
"Unit";"Roach";"Larva";278;2
