"type";"unit_name";"on_building";"total_supply";"supply"
"Unit";"Overlord";"Larva";13;0
"Building";"Extractor";NA;17;0
"Unit";"Overlord";"Larva";22;0
"Building";"SpawningPool";NA;19;0
"Building";"Hatchery";NA;17;0
"Unit";"Zergling";"Larva";22;1
"Unit";"Zergling";"Larva";22;1
"Unit";"Zergling";"Larva";22;1
"Unit";"Zergling";"Larva";22;1
"Unit";"Zergling";"Larva";22;1
"Unit";"Zergling";"Larva";22;1
"Unit";"Queen";"Hatchery";22;2
"Unit";"Queen";"Hatchery";22;2
"Unit";"Zergling";"Larva";30;1
"Unit";"Zergling";"Larva";30;1
"Unit";"Overlord";"Larva";39;0
"Building";"BanelingNest";NA;30;0
"Unit";"Zergling";"Larva";39;1
"Unit";"Zergling";"Larva";39;1
"Unit";"Zergling";"Larva";39;1
"Unit";"Zergling";"Larva";39;1
"Unit";"Zergling";"Larva";39;1
"Unit";"Zergling";"Larva";39;1
"Unit";"Zergling";"Larva";39;1
"Unit";"Zergling";"Larva";39;1
"Unit";"Baneling";"Zergling";43;0
"Unit";"Zergling";"Larva";43;1
"Unit";"Zergling";"Larva";43;1
"Unit";"Zergling";"Larva";43;1
"Unit";"Zergling";"Larva";43;1
"Unit";"Zergling";"Larva";43;1
"Unit";"Zergling";"Larva";43;1
"Unit";"Zergling";"Larva";43;1
"Unit";"Zergling";"Larva";43;1
"Unit";"Baneling";"Zergling";49;0
"Unit";"Baneling";"Zergling";49;0
"Unit";"Overlord";"Larva";49;0
"Building";"Extractor";NA;49;0
"Building";"Hatchery";NA;36;0
"Unit";"Zergling";"Larva";63;1
"Unit";"Zergling";"Larva";63;1
"Unit";"Zergling";"Larva";63;1
"Unit";"Zergling";"Larva";63;1
"Unit";"Zergling";"Larva";65;1
"Unit";"Zergling";"Larva";65;1
"Unit";"Zergling";"Larva";66;1
"Unit";"Zergling";"Larva";66;1
"Unit";"Zergling";"Larva";69;1
"Unit";"Zergling";"Larva";69;1
"Unit";"Baneling";"Zergling";73;0
"Unit";"Baneling";"Zergling";73;0
"Unit";"Zergling";"Larva";73;1
"Unit";"Zergling";"Larva";73;1
"Unit";"Zergling";"Larva";73;1
"Unit";"Zergling";"Larva";73;1
"Unit";"Baneling";"Zergling";77;0
"Unit";"Baneling";"Zergling";77;0
"Unit";"Baneling";"Zergling";79;0
"Unit";"Baneling";"Zergling";79;0
"Building";"SpineCrawler";NA;69;0
"Unit";"Zergling";"Larva";79;1
"Unit";"Zergling";"Larva";79;1
"Unit";"Zergling";"Larva";79;1
"Unit";"Zergling";"Larva";79;1
"Unit";"Zergling";"Larva";79;1
"Unit";"Zergling";"Larva";79;1
"Unit";"Zergling";"Larva";79;1
"Unit";"Zergling";"Larva";79;1
"Unit";"Zergling";"Larva";79;1
"Unit";"Zergling";"Larva";79;1
"Unit";"Zergling";"Larva";79;1
"Unit";"Zergling";"Larva";79;1
"Building";"Extractor";NA;83;0
"Unit";"Overlord";"Larva";101;0
"Building";"Extractor";NA;101;0
"Building";"RoachWarren";NA;83;0
"Unit";"Roach";"Larva";109;2
"Unit";"Roach";"Larva";109;2
"Unit";"Queen";"Hatchery";109;2
"Unit";"Overlord";"Larva";112;0
"Unit";"Overlord";"Larva";112;0
"Building";"Spire";NA;101;0
"Unit";"Mutalisk";"Larva";121;2
"Unit";"Mutalisk";"Larva";121;2
"Unit";"Mutalisk";"Larva";121;2
"Unit";"Mutalisk";"Larva";121;2
"Unit";"Mutalisk";"Larva";121;2
"Unit";"Mutalisk";"Larva";121;2
"Unit";"Overlord";"Larva";121;0
"Unit";"Overlord";"Larva";121;0
"Building";"EvolutionChamber";NA;121;0
"Building";"EvolutionChamber";NA;121;0
"Building";"Extractor";NA;136;0
"Unit";"Roach";"Larva";136;2
"Unit";"Roach";"Larva";136;2
"Unit";"Roach";"Larva";136;2
"Unit";"Roach";"Larva";136;2
"Unit";"Queen";"Hatchery";124;2
"Unit";"Overlord";"Larva";151;0
"Unit";"Overlord";"Larva";151;0
"Building";"CreepTumorQueen";NA;156;0
"Building";"Extractor";NA;156;0
"Unit";"Overlord";"Larva";156;0
"Unit";"Zergling";"Larva";156;1
"Unit";"Zergling";"Larva";156;1
"Unit";"Zergling";"Larva";156;1
"Unit";"Zergling";"Larva";156;1
"Unit";"Zergling";"Larva";156;1
"Unit";"Zergling";"Larva";156;1
"Unit";"Zergling";"Larva";156;1
"Unit";"Zergling";"Larva";156;1
"Unit";"Zergling";"Larva";156;1
"Unit";"Zergling";"Larva";156;1
"Building";"CreepTumorQueen";NA;156;0
"Upgrade";"GlialReconstitution";"RoachWarren";137;0
"Unit";"Zergling";"Larva";164;1
"Unit";"Zergling";"Larva";164;1
"Unit";"Zergling";"Larva";164;1
"Unit";"Zergling";"Larva";164;1
"Unit";"Zergling";"Larva";164;1
"Unit";"Zergling";"Larva";164;1
"Unit";"Zergling";"Larva";164;1
"Unit";"Zergling";"Larva";164;1
"Unit";"Zergling";"Larva";164;1
"Unit";"Zergling";"Larva";164;1
"Unit";"Zergling";"Larva";164;1
"Unit";"Zergling";"Larva";164;1
"Unit";"Zergling";"Larva";164;1
"Unit";"Zergling";"Larva";164;1
"Unit";"Overlord";"Larva";174;0
"Unit";"Roach";"Larva";174;2
"Unit";"Roach";"Larva";174;2
"Unit";"Roach";"Larva";174;2
"Unit";"Overlord";"Larva";174;0
"Unit";"Roach";"Larva";188;2
"Unit";"Baneling";"Zergling";194;0
"Unit";"Baneling";"Zergling";196;0
"Unit";"Baneling";"Zergling";196;0
"Unit";"Baneling";"Zergling";196;0
"Unit";"Baneling";"Zergling";196;0
"Unit";"Baneling";"Zergling";196;0
"Unit";"Baneling";"Zergling";196;0
"Unit";"Baneling";"Zergling";196;0
"Unit";"Baneling";"Zergling";196;0
"Unit";"Baneling";"Zergling";196;0
"Unit";"Baneling";"Zergling";196;0
"Unit";"Baneling";"Zergling";196;0
"Unit";"Baneling";"Zergling";196;0
"Unit";"Baneling";"Zergling";196;0
"Unit";"Roach";"Larva";194;2
"Unit";"Roach";"Larva";194;2
"Unit";"Roach";"Larva";194;2
"Unit";"Roach";"Larva";194;2
"Unit";"Roach";"Larva";194;2
"Unit";"Roach";"Larva";194;2
"Unit";"Roach";"Larva";194;2
"Unit";"Roach";"Larva";194;2
"Unit";"Baneling";"Zergling";196;0
"Unit";"Baneling";"Zergling";196;0
"Unit";"Baneling";"Zergling";196;0
"Unit";"Baneling";"Zergling";196;0
"Unit";"Baneling";"Zergling";196;0
"Unit";"Baneling";"Zergling";196;0
"Unit";"Baneling";"Zergling";196;0
"Unit";"Baneling";"Zergling";196;0
"Unit";"Baneling";"Zergling";196;0
"Unit";"Baneling";"Zergling";196;0
"Unit";"Baneling";"Zergling";197;0
"Building";"CreepTumorQueen";NA;197;0
"Building";"CreepTumor";NA;197;0
"Building";"CreepTumor";NA;197;0
"Building";"HydraliskDen";NA;194;0
"Unit";"Overlord";"Larva";197;0
"Unit";"Overlord";"Larva";213;0
"Upgrade";"ZergMissileWeaponsLevel1";"EvolutionChamber";164;0
"Upgrade";"ZergGroundArmorsLevel1";"EvolutionChamber";174;0
"Unit";"Overlord";"Larva";213;0
"Unit";"Overlord";"Larva";213;0
"Unit";"Overlord";"Larva";213;0
"Building";"Hatchery";NA;174;0
"Unit";"Roach";"Larva";213;2
"Unit";"Roach";"Larva";213;2
"Unit";"Roach";"Larva";213;2
"Unit";"Roach";"Larva";213;2
"Unit";"Roach";"Larva";213;2
"Unit";"Roach";"Larva";213;2
