"type";"unit_name";"on_building";"total_supply";"supply"
"Unit";"Overlord";"Larva";14;0
"Building";"SpawningPool";NA;12;0
"Unit";"Zergling";"Larva";15;1
"Unit";"Zergling";"Larva";15;1
"Unit";"Zergling";"Larva";15;1
"Unit";"Zergling";"Larva";15;1
"Unit";"Zergling";"Larva";15;1
"Unit";"Zergling";"Larva";15;1
"Unit";"Zergling";"Larva";15;1
"Unit";"Zergling";"Larva";15;1
"Unit";"Zergling";"Larva";21;1
"Unit";"Zergling";"Larva";21;1
"Unit";"Zergling";"Larva";23;1
"Unit";"Zergling";"Larva";23;1
"Unit";"Overlord";"Larva";25;0
"Unit";"Queen";"Hatchery";23;2
"Building";"Hatchery";NA;15;0
"Building";"CreepTumorQueen";NA;34;0
"Unit";"Queen";"Hatchery";31;2
"Unit";"Queen";"Hatchery";34;2
"Unit";"Zergling";"Larva";39;1
"Unit";"Zergling";"Larva";39;1
"Unit";"Overlord";"Larva";43;0
"Building";"Extractor";NA;43;0
"Building";"Extractor";NA;46;0
"Unit";"Zergling";"Larva";48;1
"Unit";"Zergling";"Larva";48;1
"Building";"SpineCrawler";NA;39;0
"Unit";"Zergling";"Larva";49;1
"Unit";"Zergling";"Larva";49;1
"Unit";"Zergling";"Larva";49;1
"Unit";"Zergling";"Larva";49;1
"Unit";"Zergling";"Larva";49;1
"Unit";"Zergling";"Larva";49;1
"Unit";"Zergling";"Larva";49;1
"Unit";"Zergling";"Larva";49;1
"Unit";"Zergling";"Larva";49;1
"Unit";"Zergling";"Larva";49;1
"Unit";"Zergling";"Larva";53;1
"Unit";"Zergling";"Larva";53;1
"Unit";"Zergling";"Larva";53;1
"Unit";"Zergling";"Larva";53;1
"Unit";"Zergling";"Larva";69;1
"Unit";"Zergling";"Larva";69;1
"Unit";"Zergling";"Larva";69;1
"Unit";"Zergling";"Larva";69;1
"Unit";"Queen";"Hatchery";64;2
"Building";"CreepTumor";NA;80;0
"Unit";"Queen";"Hatchery";71;2
"Building";"Extractor";NA;85;0
"Building";"Extractor";NA;85;0
"Unit";"Overlord";"Larva";87;0
"Unit";"Overlord";"Larva";89;0
"Unit";"Overlord";"Larva";89;0
"Building";"CreepTumor";NA;89;0
"Building";"EvolutionChamber";NA;89;0
"Unit";"Queen";"Hatchery";85;2
"Building";"CreepTumorQueen";NA;96;0
"Building";"CreepTumor";NA;96;0
"Unit";"Zergling";"Larva";97;1
"Unit";"Zergling";"Larva";97;1
"Unit";"Zergling";"Larva";98;1
"Unit";"Zergling";"Larva";98;1
"Unit";"Zergling";"Larva";98;1
"Unit";"Zergling";"Larva";98;1
"Building";"RoachWarren";NA;90;0
"Unit";"Roach";"Larva";111;2
"Unit";"Roach";"Larva";111;2
"Unit";"Overlord";"Larva";111;0
"Unit";"Overlord";"Larva";111;0
"Building";"CreepTumor";NA;111;0
"Unit";"Overlord";"Larva";115;0
"Unit";"Overlord";"Larva";115;0
"Building";"Spire";NA;102;0
"Building";"CreepTumor";NA;116;0
"Building";"Extractor";NA;115;0
"Building";"Extractor";NA;116;0
"Building";"CreepTumor";NA;117;0
"Unit";"Mutalisk";"Larva";116;2
"Unit";"Mutalisk";"Larva";116;2
"Unit";"Mutalisk";"Larva";116;2
"Unit";"Mutalisk";"Larva";116;2
"Unit";"Mutalisk";"Larva";116;2
"Unit";"Mutalisk";"Larva";116;2
"Unit";"Mutalisk";"Larva";116;2
"Building";"CreepTumor";NA;122;0
"Unit";"Mutalisk";"Larva";122;2
"Unit";"Mutalisk";"Larva";122;2
"Unit";"Mutalisk";"Larva";122;2
"Unit";"Mutalisk";"Larva";122;2
"Unit";"Overlord";"Larva";122;0
"Unit";"Mutalisk";"Larva";122;2
"Building";"Hatchery";NA;115;0
"Unit";"Overlord";"Larva";136;0
"Unit";"Overlord";"Larva";136;0
"Unit";"Mutalisk";"Larva";136;2
"Unit";"Overlord";"Larva";144;0
"Unit";"Overlord";"Larva";144;0
"Unit";"Overlord";"Larva";146;0
"Unit";"Zergling";"Larva";148;1
"Unit";"Zergling";"Larva";148;1
"Unit";"Zergling";"Larva";148;1
"Unit";"Zergling";"Larva";148;1
"Unit";"Zergling";"Larva";148;1
"Unit";"Zergling";"Larva";148;1
"Unit";"Mutalisk";"Larva";148;2
"Unit";"Mutalisk";"Larva";148;2
"Unit";"Mutalisk";"Larva";148;2
"Unit";"Overlord";"Larva";148;0
"Building";"CreepTumor";NA;148;0
"Unit";"Mutalisk";"Larva";148;2
"Unit";"Overlord";"Larva";160;0
"Unit";"Overlord";"Larva";160;0
"Unit";"Mutalisk";"Larva";150;2
"Unit";"Mutalisk";"Larva";152;2
"Unit";"Overlord";"Larva";160;0
"Unit";"Mutalisk";"Larva";160;2
"Unit";"Mutalisk";"Larva";162;2
"Unit";"Mutalisk";"Larva";162;2
"Unit";"Mutalisk";"Larva";162;2
"Unit";"Zergling";"Larva";168;1
"Unit";"Zergling";"Larva";168;1
"Unit";"Zergling";"Larva";168;1
"Unit";"Zergling";"Larva";168;1
"Unit";"Zergling";"Larva";168;1
"Unit";"Zergling";"Larva";168;1
"Unit";"Zergling";"Larva";168;1
"Unit";"Zergling";"Larva";168;1
"Unit";"Zergling";"Larva";168;1
"Unit";"Zergling";"Larva";168;1
"Unit";"Zergling";"Larva";168;1
"Unit";"Zergling";"Larva";168;1
"Unit";"Zergling";"Larva";168;1
"Unit";"Zergling";"Larva";168;1
"Unit";"Zergling";"Larva";168;1
"Unit";"Zergling";"Larva";168;1
"Building";"CreepTumor";NA;172;0
"Unit";"Mutalisk";"Larva";168;2
"Unit";"Mutalisk";"Larva";168;2
"Unit";"Mutalisk";"Larva";172;2
"Unit";"Overlord";"Larva";194;0
"Unit";"Mutalisk";"Larva";190;2
"Unit";"Mutalisk";"Larva";194;2
