"type";"unit_name";"on_building";"total_supply";"supply"
"Unit";"Overlord";"Larva";12;0
"Building";"Extractor";NA;17;0
"Building";"SpawningPool";NA;19;0
"Unit";"Overlord";"Larva";22;0
"Building";"Hatchery";NA;17;0
"Unit";"Zergling";"Larva";22;1
"Unit";"Zergling";"Larva";22;1
"Unit";"Zergling";"Larva";22;1
"Unit";"Zergling";"Larva";22;1
"Unit";"Zergling";"Larva";22;1
"Unit";"Zergling";"Larva";22;1
"Unit";"Queen";"Hatchery";22;2
"Unit";"Queen";"Hatchery";22;2
"Unit";"Overlord";"Larva";38;0
"Unit";"Zergling";"Larva";40;1
"Unit";"Zergling";"Larva";40;1
"Unit";"Zergling";"Larva";40;1
"Unit";"Zergling";"Larva";40;1
"Unit";"Zergling";"Larva";40;1
"Unit";"Zergling";"Larva";40;1
"Unit";"Zergling";"Larva";40;1
"Unit";"Zergling";"Larva";40;1
"Building";"BanelingNest";NA;38;0
"Unit";"Zergling";"Larva";40;1
"Unit";"Zergling";"Larva";40;1
"Unit";"Zergling";"Larva";40;1
"Unit";"Zergling";"Larva";40;1
"Unit";"Zergling";"Larva";40;1
"Unit";"Zergling";"Larva";40;1
"Unit";"Zergling";"Larva";42;1
"Unit";"Zergling";"Larva";42;1
"Unit";"Zergling";"Larva";42;1
"Unit";"Zergling";"Larva";42;1
"Unit";"Baneling";"Zergling";52;0
"Unit";"Baneling";"Zergling";52;0
"Building";"Hatchery";NA;36;0
"Unit";"Zergling";"Larva";60;1
"Unit";"Zergling";"Larva";60;1
"Unit";"Zergling";"Larva";60;1
"Unit";"Zergling";"Larva";60;1
"Unit";"Zergling";"Larva";60;1
"Unit";"Zergling";"Larva";60;1
"Unit";"Overlord";"Larva";60;0
"Unit";"Overlord";"Larva";60;0
"Building";"EvolutionChamber";NA;60;0
"Unit";"Zergling";"Larva";67;1
"Unit";"Zergling";"Larva";67;1
"Unit";"Zergling";"Larva";67;1
"Unit";"Zergling";"Larva";67;1
"Unit";"Zergling";"Larva";67;1
"Unit";"Zergling";"Larva";67;1
"Unit";"Zergling";"Larva";67;1
"Unit";"Zergling";"Larva";67;1
"Unit";"Zergling";"Larva";67;1
"Unit";"Zergling";"Larva";67;1
"Unit";"Baneling";"Zergling";67;0
"Unit";"Baneling";"Zergling";67;0
"Unit";"Baneling";"Zergling";77;0
"Unit";"Baneling";"Zergling";77;0
"Unit";"Baneling";"Zergling";77;0
"Unit";"Zergling";"Larva";77;1
"Unit";"Zergling";"Larva";77;1
"Unit";"Zergling";"Larva";77;1
"Unit";"Zergling";"Larva";77;1
"Unit";"Zergling";"Larva";77;1
"Unit";"Zergling";"Larva";77;1
"Unit";"Zergling";"Larva";77;1
"Unit";"Zergling";"Larva";77;1
"Unit";"Zergling";"Larva";77;1
"Unit";"Zergling";"Larva";77;1
"Unit";"Zergling";"Larva";77;1
"Unit";"Zergling";"Larva";77;1
"Unit";"Zergling";"Larva";77;1
"Unit";"Zergling";"Larva";77;1
"Unit";"Zergling";"Larva";77;1
"Unit";"Zergling";"Larva";77;1
"Unit";"Zergling";"Larva";77;1
"Unit";"Zergling";"Larva";77;1
"Unit";"Zergling";"Larva";77;1
"Unit";"Zergling";"Larva";77;1
"Unit";"Zergling";"Larva";77;1
"Unit";"Zergling";"Larva";77;1
"Unit";"Zergling";"Larva";77;1
"Unit";"Zergling";"Larva";77;1
"Unit";"Zergling";"Larva";77;1
"Unit";"Zergling";"Larva";77;1
"Unit";"Zergling";"Larva";77;1
"Unit";"Zergling";"Larva";77;1
"Unit";"Baneling";"Zergling";91;0
"Unit";"Queen";"Hatchery";77;2
"Unit";"Overlord";"Larva";105;0
"Unit";"Overlord";"Larva";105;0
"Unit";"Overlord";"Larva";105;0
"Unit";"Zergling";"Larva";114;1
"Unit";"Zergling";"Larva";114;1
"Unit";"Zergling";"Larva";114;1
"Unit";"Zergling";"Larva";114;1
"Unit";"Zergling";"Larva";117;1
"Unit";"Zergling";"Larva";117;1
"Unit";"Zergling";"Larva";117;1
"Unit";"Zergling";"Larva";117;1
"Unit";"Zergling";"Larva";117;1
"Unit";"Zergling";"Larva";117;1
"Building";"RoachWarren";NA;107;0
"Unit";"Baneling";"Zergling";121;0
"Unit";"Baneling";"Zergling";121;0
"Unit";"Baneling";"Zergling";121;0
"Unit";"Zergling";"Larva";121;1
"Unit";"Zergling";"Larva";121;1
"Unit";"Zergling";"Larva";121;1
"Unit";"Zergling";"Larva";121;1
"Unit";"Zergling";"Larva";121;1
"Unit";"Zergling";"Larva";121;1
"Unit";"Zergling";"Larva";121;1
"Unit";"Zergling";"Larva";121;1
"Unit";"Zergling";"Larva";121;1
"Unit";"Zergling";"Larva";121;1
"Unit";"Zergling";"Larva";121;1
"Unit";"Zergling";"Larva";121;1
"Unit";"Zergling";"Larva";121;1
"Unit";"Zergling";"Larva";121;1
"Unit";"Zergling";"Larva";127;1
"Unit";"Zergling";"Larva";127;1
"Unit";"Zergling";"Larva";127;1
"Unit";"Zergling";"Larva";127;1
"Unit";"Zergling";"Larva";127;1
"Unit";"Zergling";"Larva";127;1
"Upgrade";"ZergMissileWeaponsLevel1";"EvolutionChamber";105;0
"Building";"Extractor";NA;147;0
"Building";"Extractor";NA;147;0
"Unit";"Overlord";"Larva";153;0
"Unit";"Overlord";"Larva";160;0
"Unit";"Roach";"Larva";160;2
"Unit";"Zergling";"Larva";160;1
"Unit";"Zergling";"Larva";160;1
"Unit";"Roach";"Larva";160;2
"Unit";"Roach";"Larva";160;2
"Unit";"Zergling";"Larva";160;1
"Unit";"Zergling";"Larva";160;1
"Unit";"Zergling";"Larva";160;1
"Unit";"Zergling";"Larva";160;1
"Unit";"Zergling";"Larva";160;1
"Unit";"Zergling";"Larva";160;1
"Unit";"Zergling";"Larva";160;1
"Unit";"Zergling";"Larva";160;1
"Unit";"Zergling";"Larva";160;1
"Unit";"Zergling";"Larva";160;1
"Unit";"Zergling";"Larva";160;1
"Unit";"Zergling";"Larva";160;1
"Unit";"Zergling";"Larva";160;1
"Unit";"Zergling";"Larva";160;1
"Unit";"Baneling";"Zergling";160;0
"Unit";"Baneling";"Zergling";160;0
"Building";"CreepTumorQueen";NA;182;0
"Unit";"Roach";"Larva";160;2
"Unit";"Roach";"Larva";160;2
"Unit";"Roach";"Larva";160;2
"Building";"SpineCrawler";NA;160;0
"Building";"SpineCrawler";NA;160;0
"Building";"SpineCrawler";NA;160;0
"Unit";"Zergling";"Larva";182;1
"Unit";"Zergling";"Larva";182;1
"Unit";"Zergling";"Larva";182;1
"Unit";"Zergling";"Larva";182;1
"Unit";"Zergling";"Larva";182;1
"Unit";"Zergling";"Larva";182;1
"Unit";"Zergling";"Larva";182;1
"Unit";"Zergling";"Larva";182;1
"Unit";"Zergling";"Larva";182;1
"Unit";"Zergling";"Larva";182;1
"Unit";"Zergling";"Larva";182;1
"Unit";"Zergling";"Larva";182;1
"Unit";"Zergling";"Larva";182;1
"Unit";"Zergling";"Larva";182;1
"Unit";"Roach";"Larva";182;2
"Unit";"Roach";"Larva";182;2
"Unit";"Roach";"Larva";182;2
"Unit";"Roach";"Larva";182;2
"Unit";"Zergling";"Larva";188;1
"Unit";"Zergling";"Larva";188;1
"Unit";"Zergling";"Larva";188;1
"Unit";"Zergling";"Larva";188;1
"Unit";"Zergling";"Larva";188;1
"Unit";"Zergling";"Larva";188;1
"Unit";"Zergling";"Larva";188;1
"Unit";"Zergling";"Larva";188;1
"Unit";"Roach";"Larva";188;2
"Unit";"Roach";"Larva";188;2
