"type";"unit_name";"on_building";"total_supply";"supply"
"Unit";"Overlord";"Larva";13;0
"Building";"Extractor";NA;18;0
"Unit";"Overlord";"Larva";21;0
"Building";"SpawningPool";NA;19;0
"Building";"Hatchery";NA;17;0
"Unit";"Zergling";"Larva";23;1
"Unit";"Zergling";"Larva";23;1
"Unit";"Queen";"Hatchery";23;2
"Unit";"Queen";"Hatchery";23;2
"Unit";"Zergling";"Larva";33;1
"Unit";"Zergling";"Larva";33;1
"Unit";"Overlord";"Larva";36;0
"Unit";"Zergling";"Larva";36;1
"Unit";"Zergling";"Larva";36;1
"Building";"BanelingNest";NA;33;0
"Unit";"Queen";"Hatchery";35;2
"Unit";"Zergling";"Larva";38;1
"Unit";"Zergling";"Larva";38;1
"Unit";"Zergling";"Larva";40;1
"Unit";"Zergling";"Larva";40;1
"Unit";"Zergling";"Larva";40;1
"Unit";"Zergling";"Larva";40;1
"Unit";"Zergling";"Larva";40;1
"Unit";"Zergling";"Larva";40;1
"Unit";"Zergling";"Larva";40;1
"Unit";"Zergling";"Larva";40;1
"Unit";"Zergling";"Larva";40;1
"Unit";"Zergling";"Larva";40;1
"Unit";"Zergling";"Larva";40;1
"Unit";"Zergling";"Larva";40;1
"Unit";"Zergling";"Larva";40;1
"Unit";"Zergling";"Larva";40;1
"Unit";"Zergling";"Larva";40;1
"Unit";"Zergling";"Larva";40;1
"Unit";"Zergling";"Larva";40;1
"Unit";"Zergling";"Larva";40;1
"Unit";"Overlord";"Larva";54;0
"Unit";"Baneling";"Zergling";62;0
"Unit";"Baneling";"Zergling";62;0
"Unit";"Baneling";"Zergling";62;0
"Unit";"Baneling";"Zergling";62;0
"Unit";"Baneling";"Zergling";62;0
"Unit";"Baneling";"Zergling";62;0
"Unit";"Baneling";"Zergling";62;0
"Unit";"Zergling";"Larva";62;1
"Unit";"Zergling";"Larva";62;1
"Building";"Hatchery";NA;38;0
"Building";"EvolutionChamber";NA;70;0
"Building";"CreepTumorQueen";NA;70;0
"Unit";"Baneling";"Zergling";70;0
"Unit";"Baneling";"Zergling";70;0
"Unit";"Zergling";"Larva";70;1
"Unit";"Zergling";"Larva";70;1
"Unit";"Zergling";"Larva";70;1
"Unit";"Zergling";"Larva";70;1
"Unit";"Zergling";"Larva";70;1
"Unit";"Zergling";"Larva";70;1
"Unit";"Zergling";"Larva";70;1
"Unit";"Zergling";"Larva";70;1
"Unit";"Zergling";"Larva";70;1
"Unit";"Zergling";"Larva";70;1
"Unit";"Zergling";"Larva";70;1
"Unit";"Zergling";"Larva";70;1
"Building";"RoachWarren";NA;70;0
"Unit";"Overlord";"Larva";73;0
"Building";"Extractor";NA;73;0
"Unit";"Roach";"Larva";85;2
"Unit";"Roach";"Larva";85;2
"Unit";"Roach";"Larva";85;2
"Unit";"Roach";"Larva";85;2
"Unit";"Overlord";"Larva";85;0
"Unit";"Zergling";"Larva";85;1
"Unit";"Zergling";"Larva";85;1
"Unit";"Zergling";"Larva";85;1
"Unit";"Zergling";"Larva";85;1
"Unit";"Zergling";"Larva";85;1
"Unit";"Zergling";"Larva";85;1
"Unit";"Zergling";"Larva";85;1
"Unit";"Zergling";"Larva";85;1
"Unit";"Zergling";"Larva";85;1
"Unit";"Zergling";"Larva";85;1
"Unit";"Zergling";"Larva";85;1
"Unit";"Zergling";"Larva";85;1
"Unit";"Roach";"Larva";99;2
"Unit";"Roach";"Larva";99;2
"Unit";"Roach";"Larva";99;2
"Unit";"Roach";"Larva";99;2
"Building";"CreepTumor";NA;105;0
"Unit";"Roach";"Larva";105;2
"Unit";"Roach";"Larva";105;2
"Unit";"Roach";"Larva";105;2
"Building";"Extractor";NA;116;0
"Unit";"Overlord";"Larva";126;0
"Unit";"Overlord";"Larva";134;0
"Unit";"Overlord";"Larva";134;0
"Unit";"Roach";"Larva";134;2
"Unit";"Roach";"Larva";134;2
"Unit";"Roach";"Larva";134;2
"Unit";"Overlord";"Larva";135;0
"Unit";"Queen";"Hatchery";135;2
"Building";"Extractor";NA;143;0
"Unit";"Overlord";"Larva";143;0
"Unit";"Roach";"Larva";143;2
"Unit";"Roach";"Larva";143;2
"Unit";"Roach";"Larva";143;2
"Unit";"Roach";"Larva";143;2
"Unit";"Roach";"Larva";143;2
"Unit";"Roach";"Larva";143;2
"Building";"CreepTumor";NA;148;0
"Building";"Extractor";NA;148;0
"Unit";"Overlord";"Larva";162;0
"Upgrade";"ZergMissileWeaponsLevel1";"EvolutionChamber";135;0
"Unit";"Roach";"Larva";162;2
"Unit";"Roach";"Larva";162;2
"Unit";"Roach";"Larva";162;2
"Unit";"Roach";"Larva";162;2
"Unit";"Roach";"Larva";162;2
"Unit";"Roach";"Larva";165;2
"Unit";"Roach";"Larva";165;2
"Unit";"Overlord";"Larva";165;0
"Unit";"Overlord";"Larva";165;0
"Unit";"Overlord";"Larva";165;0
"Unit";"Overlord";"Larva";177;0
"Unit";"Roach";"Larva";179;2
"Unit";"Roach";"Larva";179;2
"Unit";"Roach";"Larva";179;2
"Unit";"Roach";"Larva";179;2
"Unit";"Roach";"Larva";179;2
"Unit";"Roach";"Larva";179;2
"Unit";"Roach";"Larva";179;2
"Upgrade";"GlialReconstitution";"RoachWarren";162;0
"Building";"CreepTumor";NA;179;0
"Building";"Extractor";NA;179;0
"Unit";"Overlord";"Larva";179;0
"Unit";"Overlord";"Larva";179;0
"Unit";"Roach";"Larva";197;2
"Unit";"Roach";"Larva";197;2
"Unit";"Roach";"Larva";197;2
"Unit";"Roach";"Larva";197;2
"Unit";"Roach";"Larva";197;2
"Unit";"Roach";"Larva";197;2
"Unit";"Roach";"Larva";197;2
"Unit";"Roach";"Larva";197;2
"Unit";"Roach";"Larva";197;2
"Unit";"Roach";"Larva";197;2
"Unit";"Roach";"Larva";197;2
"Unit";"Roach";"Larva";197;2
"Unit";"Roach";"Larva";197;2
"Unit";"Roach";"Larva";197;2
"Unit";"Roach";"Larva";197;2
"Unit";"Roach";"Larva";213;2
"Unit";"Roach";"Larva";213;2
"Unit";"Roach";"Larva";213;2
"Unit";"Roach";"Larva";213;2
"Unit";"Roach";"Larva";213;2
"Unit";"Roach";"Larva";227;2
"Unit";"Roach";"Larva";227;2
"Unit";"Roach";"Larva";227;2
"Building";"HydraliskDen";NA;227;0
"Unit";"Roach";"Larva";237;2
"Unit";"Roach";"Larva";237;2
"Unit";"Roach";"Larva";237;2
"Unit";"Roach";"Larva";237;2
"Unit";"Roach";"Larva";237;2
"Unit";"Roach";"Larva";237;2
"Unit";"Roach";"Larva";237;2
"Unit";"Roach";"Larva";237;2
"Unit";"Roach";"Larva";237;2
"Unit";"Overlord";"Larva";237;0
"Upgrade";"ZergMissileWeaponsLevel2";"EvolutionChamber";197;0
"Unit";"Overlord";"Larva";261;0
"Unit";"Overlord";"Larva";261;0
"Building";"Hatchery";NA;227;0
"Unit";"Roach";"Larva";267;2
"Unit";"Roach";"Larva";267;2
"Unit";"Roach";"Larva";267;2
"Unit";"Roach";"Larva";267;2
"Unit";"Roach";"Larva";267;2
"Unit";"Roach";"Larva";267;2
"Unit";"Roach";"Larva";267;2
"Unit";"Roach";"Larva";267;2
"Unit";"Roach";"Larva";267;2
"Unit";"Roach";"Larva";267;2
"Unit";"Roach";"Larva";267;2
"Unit";"Roach";"Larva";267;2
"Building";"CreepTumor";NA;289;0
"Unit";"Roach";"Larva";289;2
"Unit";"Roach";"Larva";289;2
"Unit";"Roach";"Larva";289;2
"Unit";"Roach";"Larva";289;2
"Unit";"Roach";"Larva";289;2
"Unit";"Roach";"Larva";289;2
"Unit";"Roach";"Larva";289;2
"Unit";"Roach";"Larva";289;2
"Unit";"Roach";"Larva";289;2
"Unit";"Roach";"Larva";289;2
"Building";"Extractor";NA;291;0
"Building";"Extractor";NA;291;0
"Building";"LurkerDenMP";NA;261;0
"Unit";"Hydralisk";"Larva";315;2
"Unit";"Hydralisk";"Larva";315;2
"Unit";"Hydralisk";"Larva";315;2
"Unit";"Hydralisk";"Larva";315;2
"Unit";"Hydralisk";"Larva";315;2
"Unit";"Hydralisk";"Larva";315;2
"Unit";"Roach";"Larva";315;2
"Unit";"Roach";"Larva";315;2
"Unit";"Roach";"Larva";315;2
"Unit";"Roach";"Larva";315;2
"Unit";"Roach";"Larva";315;2
"Unit";"Roach";"Larva";315;2
"Unit";"Roach";"Larva";315;2
"Unit";"Roach";"Larva";341;2
"Unit";"Roach";"Larva";341;2
"Unit";"Roach";"Larva";341;2
"Unit";"Roach";"Larva";341;2
"Unit";"Roach";"Larva";341;2
"Unit";"Roach";"Larva";341;2
"Unit";"Roach";"Larva";341;2
"Unit";"Overlord";"Larva";341;0
"Unit";"Overlord";"Larva";341;0
"Unit";"Roach";"Larva";355;2
"Unit";"Roach";"Larva";355;2
"Unit";"Roach";"Larva";355;2
"Unit";"Roach";"Larva";355;2
"Unit";"Roach";"Larva";355;2
"Unit";"Roach";"Larva";355;2
"Unit";"Roach";"Larva";355;2
"Unit";"Roach";"Larva";355;2
"Unit";"Roach";"Larva";355;2
"Unit";"Roach";"Larva";355;2
"Unit";"Roach";"Larva";355;2
"Unit";"Roach";"Larva";355;2
"Unit";"Roach";"Larva";355;2
"Unit";"Roach";"Larva";355;2
"Unit";"Roach";"Larva";355;2
"Unit";"Roach";"Larva";355;2
"Unit";"Roach";"Larva";355;2
"Unit";"Roach";"Larva";355;2
"Unit";"Roach";"Larva";355;2
"Unit";"Roach";"Larva";355;2
"Unit";"Roach";"Larva";355;2
"Unit";"Roach";"Larva";355;2
"Unit";"Roach";"Larva";355;2
"Unit";"Roach";"Larva";355;2
"Unit";"Roach";"Larva";355;2
"Unit";"Overlord";"Larva";355;0
"Unit";"Queen";"Hatchery";355;2
"Upgrade";"ZergGroundArmorsLevel1";"EvolutionChamber";341;0
"Unit";"Roach";"Larva";381;2
"Unit";"Roach";"Larva";405;2
"Unit";"Roach";"Larva";405;2
"Unit";"Queen";"Hatchery";405;2
"Unit";"Overlord";"Larva";413;0
"Unit";"Overlord";"Larva";415;0
"Unit";"Overlord";"Larva";415;0
"Unit";"Overlord";"Larva";415;0
"Unit";"Overlord";"Larva";415;0
"Unit";"Hydralisk";"Larva";415;2
"Unit";"Hydralisk";"Larva";415;2
"Unit";"Hydralisk";"Larva";415;2
"Unit";"Hydralisk";"Larva";415;2
"Unit";"Hydralisk";"Larva";415;2
"Unit";"Hydralisk";"Larva";415;2
"Unit";"Hydralisk";"Larva";415;2
"Unit";"Hydralisk";"Larva";415;2
"Unit";"Hydralisk";"Larva";415;2
"Unit";"Overlord";"Larva";415;0
"Unit";"Overlord";"Larva";433;0
"Unit";"Overlord";"Larva";433;0
"Unit";"Overlord";"Larva";433;0
"Building";"InfestationPit";NA;415;0
"Unit";"Overlord";"Larva";433;0
"Upgrade";"EvolveGroovedSpines";"HydraliskDen";433;0
"Unit";"Roach";"Larva";433;2
"Unit";"Roach";"Larva";433;2
"Unit";"Roach";"Larva";433;2
"Unit";"Roach";"Larva";433;2
"Unit";"Roach";"Larva";433;2
"Unit";"Roach";"Larva";433;2
"Unit";"Roach";"Larva";433;2
"Unit";"Roach";"Larva";433;2
"Unit";"Overlord";"Larva";433;0
"Building";"Hatchery";NA;433;0
