"type";"unit_name";"on_building";"total_supply";"supply"
"Unit";"Overlord";"Larva";12;0
"Building";"SpawningPool";NA;16;0
"Building";"Extractor";NA;18;0
"Unit";"Zergling";"Larva";21;1
"Unit";"Zergling";"Larva";21;1
"Unit";"Queen";"Hatchery";21;2
"Unit";"Overlord";"Larva";22;0
"Building";"Hatchery";NA;18;0
"Unit";"Queen";"Hatchery";26;2
"Building";"CreepTumorQueen";NA;30;0
"Unit";"Queen";"Hatchery";26;2
"Unit";"Overlord";"Larva";34;0
"Building";"CreepTumor";NA;40;0
"Building";"CreepTumorQueen";NA;40;0
"Building";"EvolutionChamber";NA;40;0
"Building";"EvolutionChamber";NA;40;0
"Building";"RoachWarren";NA;40;0
"Building";"SpineCrawler";NA;40;0
"Building";"CreepTumor";NA;47;0
"Unit";"Overlord";"Larva";52;0
"Unit";"Overlord";"Larva";53;0
"Building";"Extractor";NA;53;0
"Building";"Extractor";NA;53;0
"Building";"Extractor";NA;53;0
"Building";"CreepTumorQueen";NA;54;0
"Building";"CreepTumor";NA;61;0
"Unit";"Overlord";"Larva";61;0
"Building";"CreepTumor";NA;64;0
"Unit";"Overlord";"Larva";61;0
"Unit";"Overlord";"Larva";66;0
"Unit";"Roach";"Larva";66;2
"Unit";"Roach";"Larva";66;2
"Unit";"Roach";"Larva";66;2
"Unit";"Roach";"Larva";66;2
"Upgrade";"ZergMissileWeaponsLevel1";"EvolutionChamber";52;0
"Building";"HydraliskDen";NA;66;0
"Upgrade";"ZergGroundArmorsLevel1";"EvolutionChamber";53;0
"Unit";"Overlord";"Larva";66;0
"Building";"CreepTumor";NA;66;0
"Building";"CreepTumor";NA;72;0
"Unit";"Roach";"Larva";66;2
"Unit";"Roach";"Larva";66;2
"Unit";"Overlord";"Larva";74;0
"Unit";"Roach";"Larva";78;2
"Unit";"Roach";"Larva";78;2
"Unit";"Roach";"Larva";78;2
"Unit";"Roach";"Larva";78;2
"Building";"Hatchery";NA;66;0
"Upgrade";"GlialReconstitution";"RoachWarren";66;0
"Building";"CreepTumor";NA;86;0
"Unit";"Roach";"Larva";86;2
"Building";"CreepTumor";NA;86;0
"Unit";"Roach";"Larva";86;2
"Unit";"Roach";"Larva";86;2
"Unit";"Roach";"Larva";86;2
"Unit";"Roach";"Larva";86;2
"Unit";"Roach";"Larva";86;2
"Unit";"Roach";"Larva";86;2
"Unit";"Roach";"Larva";86;2
"Building";"CreepTumorQueen";NA;86;0
"Building";"CreepTumorQueen";NA;86;0
"Building";"CreepTumorQueen";NA;86;0
"Unit";"Overlord";"Larva";86;0
"Unit";"Overlord";"Larva";86;0
"Unit";"Overlord";"Larva";102;0
"Unit";"Roach";"Larva";102;2
"Unit";"Roach";"Larva";102;2
"Unit";"Roach";"Larva";102;2
"Unit";"Roach";"Larva";102;2
"Unit";"Roach";"Larva";102;2
"Building";"CreepTumorQueen";NA;102;0
"Building";"CreepTumor";NA;102;0
"Building";"CreepTumor";NA;102;0
"Building";"CreepTumor";NA;102;0
"Unit";"Overlord";"Larva";102;0
"Unit";"Roach";"Larva";112;2
"Unit";"Roach";"Larva";112;2
"Unit";"Roach";"Larva";112;2
"Unit";"Roach";"Larva";112;2
"Unit";"Roach";"Larva";112;2
"Unit";"Roach";"Larva";112;2
"Unit";"Roach";"Larva";112;2
"Building";"CreepTumor";NA;112;0
"Building";"CreepTumor";NA;112;0
"Building";"CreepTumor";NA;112;0
"Building";"CreepTumor";NA;112;0
"Building";"CreepTumor";NA;112;0
"Building";"Hatchery";NA;86;0
"Building";"CreepTumor";NA;112;0
"Unit";"Overlord";"Larva";112;0
"Unit";"Roach";"Larva";112;2
"Unit";"Roach";"Larva";112;2
"Unit";"Roach";"Larva";112;2
"Unit";"Roach";"Larva";112;2
"Unit";"Roach";"Larva";112;2
"Unit";"Roach";"Larva";112;2
"Unit";"Roach";"Larva";126;2
"Unit";"Roach";"Larva";126;2
"Unit";"Roach";"Larva";126;2
"Unit";"Overlord";"Larva";126;0
"Upgrade";"ZergMissileWeaponsLevel2";"EvolutionChamber";86;0
"Unit";"Overlord";"Larva";126;0
"Upgrade";"ZergGroundArmorsLevel2";"EvolutionChamber";86;0
"Unit";"Roach";"Larva";144;2
"Unit";"Roach";"Larva";144;2
"Unit";"Roach";"Larva";144;2
"Unit";"Roach";"Larva";144;2
"Unit";"Roach";"Larva";144;2
"Unit";"Roach";"Larva";144;2
"Unit";"Roach";"Larva";144;2
"Unit";"Roach";"Larva";144;2
"Unit";"Roach";"Larva";144;2
"Unit";"Roach";"Larva";144;2
"Unit";"Roach";"Larva";144;2
"Unit";"Queen";"Hatchery";144;2
"Unit";"Roach";"Larva";152;2
"Unit";"Roach";"Larva";152;2
"Unit";"Roach";"Larva";152;2
"Unit";"Roach";"Larva";152;2
"Unit";"Roach";"Larva";152;2
"Unit";"Roach";"Larva";152;2
"Unit";"Overlord";"Larva";152;0
"Unit";"Roach";"Larva";180;2
"Unit";"Roach";"Larva";180;2
"Building";"Extractor";NA;192;0
"Unit";"Overlord";"Larva";192;0
"Building";"Extractor";NA;192;0
"Building";"InfestationPit";NA;180;0
"Unit";"Roach";"Larva";192;2
"Building";"CreepTumor";NA;198;0
"Building";"CreepTumor";NA;198;0
"Building";"CreepTumor";NA;198;0
"Building";"CreepTumor";NA;198;0
"Building";"CreepTumor";NA;198;0
"Building";"CreepTumor";NA;200;0
"Building";"CreepTumor";NA;200;0
"Building";"CreepTumor";NA;200;0
"Building";"CreepTumor";NA;200;0
"Building";"CreepTumor";NA;200;0
"Unit";"Overlord";"Larva";200;0
"Unit";"Roach";"Larva";200;2
"Unit";"Roach";"Larva";200;2
"Unit";"Roach";"Larva";200;2
"Unit";"Hydralisk";"Larva";200;2
"Unit";"Hydralisk";"Larva";200;2
"Unit";"Hydralisk";"Larva";200;2
"Unit";"Hydralisk";"Larva";200;2
"Upgrade";"EvolveGroovedSpines";"HydraliskDen";200;0
"Unit";"Roach";"Larva";200;2
"Unit";"Roach";"Larva";200;2
"Unit";"Roach";"Larva";200;2
"Unit";"Roach";"Larva";200;2
"Unit";"Roach";"Larva";200;2
"Unit";"Roach";"Larva";200;2
"Unit";"Roach";"Larva";200;2
"Building";"CreepTumor";NA;200;0
"Building";"CreepTumor";NA;214;0
"Unit";"Overlord";"Larva";200;0
"Building";"CreepTumor";NA;214;0
"Building";"CreepTumor";NA;214;0
"Building";"CreepTumor";NA;214;0
"Building";"CreepTumor";NA;214;0
"Unit";"Roach";"Larva";228;2
"Unit";"Roach";"Larva";228;2
"Unit";"Roach";"Larva";228;2
"Unit";"Roach";"Larva";228;2
"Unit";"Roach";"Larva";228;2
"Unit";"Roach";"Larva";228;2
"Unit";"Roach";"Larva";228;2
"Unit";"Roach";"Larva";228;2
"Unit";"Roach";"Larva";228;2
"Unit";"Roach";"Larva";228;2
"Building";"Spire";NA;200;0
"Unit";"Overlord";"Larva";228;0
"Building";"Hatchery";NA;200;0
