"type";"unit_name";"on_building";"total_supply";"supply"
"Unit";"Overlord";"Larva";13;0
"Building";"Extractor";NA;17;0
"Unit";"Overlord";"Larva";21;0
"Building";"SpawningPool";NA;19;0
"Building";"Hatchery";NA;17;0
"Unit";"Queen";"Hatchery";22;2
"Unit";"Queen";"Hatchery";22;2
"Unit";"Overlord";"Larva";33;0
"Unit";"Overlord";"Larva";34;0
"Unit";"Queen";"Hatchery";28;2
"Unit";"Queen";"Hatchery";30;2
"Building";"CreepTumorQueen";NA;42;0
"Building";"Extractor";NA;45;0
"Building";"Extractor";NA;45;0
"Building";"EvolutionChamber";NA;49;0
"Building";"EvolutionChamber";NA;52;0
"Building";"RoachWarren";NA;49;0
"Building";"CreepTumor";NA;55;0
"Building";"Extractor";NA;52;0
"Unit";"Overlord";"Larva";60;0
"Unit";"Overlord";"Larva";60;0
"Unit";"Overlord";"Larva";60;0
"Building";"CreepTumor";NA;61;0
"Unit";"Roach";"Larva";61;2
"Unit";"Roach";"Larva";61;2
"Unit";"Roach";"Larva";61;2
"Unit";"Roach";"Larva";61;2
"Unit";"Roach";"Larva";61;2
"Unit";"Roach";"Larva";61;2
"Unit";"Roach";"Larva";61;2
"Unit";"Roach";"Larva";61;2
"Unit";"Roach";"Larva";61;2
"Unit";"Roach";"Larva";61;2
"Unit";"Roach";"Larva";61;2
"Unit";"Roach";"Larva";77;2
"Unit";"Roach";"Larva";77;2
"Unit";"Overlord";"Larva";79;0
"Unit";"Overlord";"Larva";79;0
"Unit";"Overlord";"Larva";79;0
"Building";"CreepTumor";NA;83;0
"Building";"NydusNetwork";NA;61;0
"Building";"NydusCanal";NA;87;0
"Unit";"Roach";"Larva";87;2
"Unit";"Roach";"Larva";87;2
"Unit";"Roach";"Larva";87;2
"Unit";"Roach";"Larva";87;2
"Unit";"Roach";"Larva";87;2
"Unit";"Roach";"Larva";87;2
"Unit";"Roach";"Larva";87;2
"Unit";"Roach";"Larva";87;2
"Unit";"Overlord";"Larva";87;0
"Unit";"Overlord";"Larva";87;0
"Upgrade";"GlialReconstitution";"RoachWarren";87;0
"Unit";"Overlord";"Larva";103;0
"Building";"EvolutionChamber";NA;103;0
"Building";"EvolutionChamber";NA;103;0
"Unit";"Roach";"Larva";103;2
"Unit";"Roach";"Larva";103;2
"Unit";"Roach";"Larva";103;2
"Unit";"Roach";"Larva";103;2
"Unit";"Roach";"Larva";103;2
"Unit";"Roach";"Larva";103;2
"Unit";"Roach";"Larva";103;2
"Unit";"Roach";"Larva";103;2
"Building";"Hatchery";NA;103;0
"Unit";"Roach";"Larva";115;2
"Unit";"Roach";"Larva";115;2
"Building";"CreepTumor";NA;119;0
"Unit";"Roach";"Larva";119;2
"Unit";"Roach";"Larva";119;2
"Unit";"Roach";"Larva";119;2
"Unit";"Roach";"Larva";119;2
"Unit";"Roach";"Larva";119;2
"Unit";"Roach";"Larva";119;2
"Unit";"Roach";"Larva";119;2
"Unit";"Queen";"Hatchery";119;2
"Building";"SpineCrawler";NA;119;0
"Unit";"Roach";"Larva";127;2
"Building";"SpineCrawler";NA;119;0
"Building";"SpineCrawler";NA;119;0
"Unit";"Queen";"Hatchery";123;2
"Unit";"Queen";"Hatchery";123;2
"Unit";"Roach";"Larva";142;2
"Unit";"Roach";"Larva";142;2
"Unit";"Roach";"Larva";142;2
"Unit";"Roach";"Larva";142;2
"Unit";"Roach";"Larva";142;2
"Unit";"Roach";"Larva";142;2
"Unit";"Roach";"Larva";142;2
"Unit";"Roach";"Larva";142;2
"Building";"CreepTumor";NA;156;0
"Unit";"Roach";"Larva";146;2
"Unit";"Roach";"Larva";146;2
"Unit";"Roach";"Larva";146;2
"Unit";"Roach";"Larva";156;2
"Unit";"Roach";"Larva";156;2
"Unit";"Roach";"Larva";156;2
"Building";"CreepTumorQueen";NA;168;0
"Upgrade";"ZergMissileWeaponsLevel1";"EvolutionChamber";123;0
"Upgrade";"ZergGroundArmorsLevel1";"EvolutionChamber";123;0
"Unit";"Roach";"Larva";176;2
"Unit";"Roach";"Larva";176;2
"Unit";"Roach";"Larva";176;2
"Unit";"Roach";"Larva";183;2
"Unit";"Roach";"Larva";183;2
"Unit";"Roach";"Larva";183;2
"Unit";"Roach";"Larva";183;2
"Unit";"Roach";"Larva";183;2
"Unit";"Overlord";"Larva";189;0
"Unit";"Overlord";"Larva";195;0
"Unit";"Roach";"Larva";199;2
"Unit";"Roach";"Larva";199;2
"Unit";"Roach";"Larva";199;2
"Unit";"Roach";"Larva";199;2
"Unit";"Roach";"Larva";199;2
"Unit";"Roach";"Larva";199;2
"Unit";"Roach";"Larva";199;2
"Unit";"Roach";"Larva";199;2
"Unit";"Overlord";"Larva";199;0
"Unit";"Overlord";"Larva";199;0
"Unit";"Roach";"Larva";203;2
"Unit";"Roach";"Larva";207;2
"Unit";"Roach";"Larva";207;2
"Unit";"Roach";"Larva";207;2
"Unit";"Roach";"Larva";215;2
"Unit";"Roach";"Larva";238;2
"Unit";"Roach";"Larva";238;2
"Unit";"Roach";"Larva";238;2
"Upgrade";"ZergMissileWeaponsLevel2";"EvolutionChamber";199;0
"Unit";"Roach";"Larva";241;2
"Unit";"Roach";"Larva";241;2
"Unit";"Roach";"Larva";241;2
"Unit";"Roach";"Larva";241;2
"Unit";"Roach";"Larva";241;2
"Unit";"Roach";"Larva";241;2
"Unit";"Roach";"Larva";241;2
"Unit";"Roach";"Larva";241;2
"Unit";"Roach";"Larva";241;2
"Unit";"Roach";"Larva";247;2
"Unit";"Roach";"Larva";247;2
"Unit";"Roach";"Larva";247;2
"Unit";"Roach";"Larva";265;2
"Unit";"Roach";"Larva";265;2
"Unit";"Roach";"Larva";265;2
"Unit";"Roach";"Larva";265;2
"Unit";"Roach";"Larva";265;2
"Unit";"Roach";"Larva";269;2
"Unit";"Roach";"Larva";269;2
"Building";"CreepTumor";NA;271;0
"Building";"Extractor";NA;271;0
"Building";"Hatchery";NA;238;0
"Unit";"Roach";"Larva";271;2
"Unit";"Roach";"Larva";271;2
"Unit";"Roach";"Larva";287;2
"Unit";"Roach";"Larva";287;2
"Unit";"Roach";"Larva";287;2
"Unit";"Roach";"Larva";287;2
"Unit";"Roach";"Larva";287;2
"Unit";"Roach";"Larva";288;2
"Unit";"Roach";"Larva";288;2
"Unit";"Roach";"Larva";288;2
"Unit";"Roach";"Larva";288;2
"Unit";"Roach";"Larva";288;2
"Unit";"Roach";"Larva";292;2
"Unit";"Roach";"Larva";292;2
"Unit";"Roach";"Larva";304;2
"Unit";"Roach";"Larva";304;2
"Unit";"Roach";"Larva";304;2
"Unit";"Roach";"Larva";316;2
"Unit";"Roach";"Larva";316;2
"Unit";"Roach";"Larva";316;2
"Unit";"Roach";"Larva";316;2
"Unit";"Roach";"Larva";316;2
"Unit";"Roach";"Larva";316;2
"Unit";"Roach";"Larva";316;2
"Unit";"Roach";"Larva";316;2
"Unit";"Roach";"Larva";316;2
"Unit";"Roach";"Larva";322;2
"Unit";"Roach";"Larva";322;2
"Unit";"Roach";"Larva";322;2
"Unit";"Roach";"Larva";322;2
"Unit";"Roach";"Larva";322;2
