"type";"unit_name";"on_building";"total_supply";"supply"
"Unit";"Overlord";"Larva";13;0
"Building";"Extractor";NA;18;0
"Unit";"Overlord";"Larva";21;0
"Building";"SpawningPool";NA;19;0
"Building";"Hatchery";NA;17;0
"Unit";"Queen";"Hatchery";22;2
"Unit";"Queen";"Hatchery";23;2
"Unit";"Zergling";"Larva";27;1
"Unit";"Zergling";"Larva";27;1
"Unit";"Overlord";"Larva";31;0
"Unit";"Zergling";"Larva";37;1
"Unit";"Zergling";"Larva";37;1
"Unit";"Zergling";"Larva";37;1
"Unit";"Zergling";"Larva";37;1
"Unit";"Zergling";"Larva";38;1
"Unit";"Zergling";"Larva";38;1
"Unit";"Zergling";"Larva";38;1
"Unit";"Zergling";"Larva";38;1
"Unit";"Zergling";"Larva";38;1
"Unit";"Zergling";"Larva";38;1
"Unit";"Overlord";"Larva";38;0
"Building";"Hatchery";NA;27;0
"Building";"BanelingNest";NA;38;0
"Unit";"Overlord";"Larva";54;0
"Unit";"Queen";"Hatchery";52;2
"Building";"Extractor";NA;56;0
"Unit";"Queen";"Hatchery";54;2
"Unit";"Overlord";"Larva";58;0
"Unit";"Zergling";"Larva";66;1
"Unit";"Zergling";"Larva";66;1
"Unit";"Zergling";"Larva";66;1
"Unit";"Zergling";"Larva";66;1
"Unit";"Zergling";"Larva";66;1
"Unit";"Zergling";"Larva";66;1
"Unit";"Zergling";"Larva";66;1
"Unit";"Zergling";"Larva";66;1
"Unit";"Zergling";"Larva";66;1
"Unit";"Zergling";"Larva";66;1
"Unit";"Zergling";"Larva";70;1
"Unit";"Zergling";"Larva";70;1
"Unit";"Zergling";"Larva";70;1
"Unit";"Zergling";"Larva";70;1
"Unit";"Zergling";"Larva";70;1
"Unit";"Zergling";"Larva";70;1
"Unit";"Zergling";"Larva";70;1
"Unit";"Zergling";"Larva";70;1
"Unit";"Zergling";"Larva";71;1
"Unit";"Zergling";"Larva";71;1
"Unit";"Zergling";"Larva";71;1
"Unit";"Zergling";"Larva";71;1
"Unit";"Baneling";"Zergling";73;0
"Unit";"Baneling";"Zergling";73;0
"Unit";"Baneling";"Zergling";77;0
"Unit";"Baneling";"Zergling";77;0
"Unit";"Zergling";"Larva";77;1
"Unit";"Zergling";"Larva";77;1
"Unit";"Zergling";"Larva";77;1
"Unit";"Zergling";"Larva";77;1
"Unit";"Baneling";"Zergling";81;0
"Unit";"Baneling";"Zergling";81;0
"Building";"Extractor";NA;73;0
"Unit";"Zergling";"Larva";81;1
"Unit";"Zergling";"Larva";81;1
"Unit";"Zergling";"Larva";93;1
"Unit";"Zergling";"Larva";93;1
"Building";"CreepTumorQueen";NA;107;0
"Unit";"Baneling";"Zergling";111;0
"Building";"EvolutionChamber";NA;111;0
"Unit";"Overlord";"Larva";112;0
"Building";"CreepTumorQueen";NA;116;0
"Building";"RoachWarren";NA;111;0
"Unit";"Zergling";"Larva";116;1
"Unit";"Zergling";"Larva";116;1
"Unit";"Zergling";"Larva";116;1
"Unit";"Zergling";"Larva";116;1
"Unit";"Zergling";"Larva";116;1
"Unit";"Zergling";"Larva";116;1
"Building";"CreepTumor";NA;116;0
"Building";"CreepTumorQueen";NA;116;0
"Unit";"Zergling";"Larva";121;1
"Unit";"Zergling";"Larva";121;1
"Unit";"Zergling";"Larva";124;1
"Unit";"Zergling";"Larva";124;1
"Unit";"Baneling";"Zergling";126;0
"Unit";"Baneling";"Zergling";126;0
"Unit";"Baneling";"Zergling";126;0
"Unit";"Baneling";"Zergling";132;0
"Unit";"Overlord";"Larva";132;0
"Unit";"Overlord";"Larva";132;0
"Unit";"Roach";"Larva";132;2
"Unit";"Roach";"Larva";132;2
"Unit";"Roach";"Larva";132;2
"Unit";"Overlord";"Larva";136;0
"Building";"CreepTumorQueen";NA;137;0
"Building";"CreepTumor";NA;136;0
"Building";"Extractor";NA;136;0
"Unit";"Overlord";"Larva";136;0
"Building";"Extractor";NA;136;0
"Unit";"Overlord";"Larva";139;0
"Unit";"Roach";"Larva";143;2
"Unit";"Roach";"Larva";143;2
"Unit";"Roach";"Larva";143;2
"Unit";"Roach";"Larva";143;2
"Unit";"Roach";"Larva";143;2
"Unit";"Roach";"Larva";143;2
"Unit";"Roach";"Larva";143;2
"Unit";"Roach";"Larva";143;2
"Unit";"Overlord";"Larva";143;0
"Unit";"Roach";"Larva";143;2
"Unit";"Roach";"Larva";143;2
"Unit";"Roach";"Larva";143;2
"Building";"CreepTumor";NA;147;0
"Building";"CreepTumorQueen";NA;163;0
"Building";"CreepTumor";NA;163;0
"Building";"CreepTumor";NA;167;0
"Unit";"Roach";"Larva";163;2
"Unit";"Roach";"Larva";163;2
"Unit";"Roach";"Larva";163;2
"Unit";"Roach";"Larva";163;2
"Unit";"Overlord";"Larva";169;0
"Unit";"Roach";"Larva";169;2
"Unit";"Roach";"Larva";169;2
"Unit";"Roach";"Larva";169;2
"Unit";"Roach";"Larva";169;2
"Unit";"Roach";"Larva";169;2
"Unit";"Roach";"Larva";169;2
"Unit";"Roach";"Larva";169;2
"Unit";"Roach";"Larva";169;2
"Unit";"Roach";"Larva";169;2
"Unit";"Overlord";"Larva";185;0
"Unit";"Roach";"Larva";189;2
"Unit";"Roach";"Larva";189;2
"Unit";"Roach";"Larva";189;2
"Unit";"Roach";"Larva";189;2
"Upgrade";"ZergMissileWeaponsLevel1";"EvolutionChamber";136;0
"Unit";"Roach";"Larva";191;2
"Unit";"Roach";"Larva";191;2
"Unit";"Overlord";"Larva";195;0
"Unit";"Overlord";"Larva";195;0
"Building";"Hatchery";NA;147;0
"Unit";"Baneling";"Zergling";197;0
"Building";"CreepTumor";NA;207;0
"Upgrade";"GlialReconstitution";"RoachWarren";169;0
"Unit";"Roach";"Larva";203;2
"Unit";"Roach";"Larva";203;2
"Unit";"Roach";"Larva";203;2
"Unit";"Roach";"Larva";203;2
"Unit";"Roach";"Larva";203;2
"Building";"CreepTumor";NA;207;0
"Unit";"Roach";"Larva";207;2
"Unit";"Roach";"Larva";207;2
"Unit";"Roach";"Larva";207;2
"Unit";"Roach";"Larva";207;2
"Unit";"Roach";"Larva";207;2
"Unit";"Roach";"Larva";207;2
"Unit";"Roach";"Larva";207;2
"Unit";"Roach";"Larva";207;2
"Unit";"Roach";"Larva";207;2
"Unit";"Roach";"Larva";207;2
"Unit";"Roach";"Larva";207;2
"Unit";"Roach";"Larva";209;2
"Unit";"Roach";"Larva";217;2
"Unit";"Roach";"Larva";217;2
"Unit";"Roach";"Larva";217;2
"Unit";"Roach";"Larva";217;2
"Building";"CreepTumor";NA;233;0
"Building";"CreepTumor";NA;243;0
"Unit";"Roach";"Larva";241;2
"Unit";"Roach";"Larva";241;2
"Unit";"Roach";"Larva";241;2
"Unit";"Roach";"Larva";241;2
"Unit";"Roach";"Larva";241;2
"Unit";"Roach";"Larva";241;2
"Unit";"Roach";"Larva";241;2
"Unit";"Roach";"Larva";241;2
"Unit";"Roach";"Larva";241;2
"Unit";"Overlord";"Larva";249;0
"Unit";"Overlord";"Larva";249;0
"Unit";"Overlord";"Larva";249;0
"Unit";"Overlord";"Larva";267;0
"Unit";"Overlord";"Larva";267;0
"Unit";"Overlord";"Larva";267;0
"Unit";"Overlord";"Larva";267;0
"Building";"CreepTumor";NA;267;0
"Unit";"Roach";"Larva";267;2
"Unit";"Roach";"Larva";267;2
"Unit";"Roach";"Larva";267;2
"Unit";"Roach";"Larva";267;2
"Building";"CreepTumor";NA;275;0
"Building";"HydraliskDen";NA;267;0
"Unit";"Roach";"Larva";284;2
"Unit";"Roach";"Larva";284;2
"Unit";"Roach";"Larva";286;2
"Unit";"Roach";"Larva";286;2
"Unit";"Roach";"Larva";286;2
"Unit";"Roach";"Larva";286;2
"Unit";"Roach";"Larva";286;2
"Unit";"Roach";"Larva";286;2
"Unit";"Roach";"Larva";286;2
"Unit";"Roach";"Larva";286;2
"Upgrade";"ZergMissileWeaponsLevel2";"EvolutionChamber";241;0
"Building";"Extractor";NA;290;0
"Building";"Extractor";NA;294;0
"Building";"Extractor";NA;294;0
"Unit";"Roach";"Larva";306;2
"Unit";"Roach";"Larva";306;2
"Unit";"Roach";"Larva";306;2
"Unit";"Roach";"Larva";306;2
"Unit";"Roach";"Larva";306;2
"Unit";"Queen";"Hatchery";290;2
"Unit";"Roach";"Larva";309;2
"Unit";"Roach";"Larva";309;2
"Unit";"Roach";"Larva";309;2
"Unit";"Roach";"Larva";309;2
"Unit";"Roach";"Larva";309;2
"Unit";"Roach";"Larva";309;2
"Unit";"Roach";"Larva";309;2
"Unit";"Roach";"Larva";319;2
"Unit";"Roach";"Larva";321;2
"Unit";"Roach";"Larva";321;2
"Unit";"Roach";"Larva";321;2
"Unit";"Roach";"Larva";321;2
"Unit";"Roach";"Larva";321;2
"Unit";"Roach";"Larva";321;2
"Unit";"Roach";"Larva";321;2
"Unit";"Roach";"Larva";321;2
"Unit";"Roach";"Larva";321;2
"Unit";"Roach";"Larva";321;2
"Unit";"Roach";"Larva";321;2
"Unit";"Roach";"Larva";321;2
"Unit";"Hydralisk";"Larva";335;2
"Unit";"Roach";"Larva";359;2
"Unit";"Roach";"Larva";361;2
"Unit";"Roach";"Larva";361;2
"Unit";"Roach";"Larva";361;2
"Unit";"Roach";"Larva";361;2
"Unit";"Roach";"Larva";361;2
"Unit";"Roach";"Larva";361;2
"Unit";"Roach";"Larva";361;2
"Unit";"Roach";"Larva";361;2
"Unit";"Roach";"Larva";361;2
"Unit";"Overlord";"Larva";361;0
"Unit";"Roach";"Larva";361;2
"Unit";"Roach";"Larva";363;2
"Unit";"Roach";"Larva";363;2
"Building";"LurkerDenMP";NA;294;0
"Unit";"Overlord";"Larva";363;0
"Unit";"Hydralisk";"Larva";389;2
"Unit";"Hydralisk";"Larva";389;2
"Unit";"Hydralisk";"Larva";389;2
"Unit";"Hydralisk";"Larva";389;2
"Unit";"Hydralisk";"Larva";389;2
"Unit";"Hydralisk";"Larva";389;2
"Unit";"Hydralisk";"Larva";389;2
"Unit";"Hydralisk";"Larva";389;2
"Unit";"Hydralisk";"Larva";389;2
"Unit";"Hydralisk";"Larva";389;2
"Unit";"Hydralisk";"Larva";389;2
"Unit";"Roach";"Larva";389;2
"Unit";"Roach";"Larva";389;2
"Unit";"Roach";"Larva";389;2
"Building";"Hatchery";NA;361;0
"Unit";"Queen";"Hatchery";389;2
"Unit";"Roach";"Larva";389;2
"Unit";"Roach";"Larva";389;2
"Unit";"Roach";"Larva";389;2
"Unit";"Roach";"Larva";389;2
"Building";"CreepTumor";NA;417;0
"Unit";"Roach";"Larva";427;2
"Unit";"Roach";"Larva";427;2
"Unit";"Roach";"Larva";427;2
"Unit";"Roach";"Larva";427;2
"Unit";"Roach";"Larva";436;2
"Unit";"Roach";"Larva";436;2
"Unit";"Roach";"Larva";436;2
"Unit";"Roach";"Larva";436;2
"Unit";"Roach";"Larva";436;2
"Unit";"Roach";"Larva";436;2
"Unit";"Roach";"Larva";436;2
"Building";"InfestationPit";NA;436;0
"Unit";"Hydralisk";"Larva";436;2
"Unit";"Hydralisk";"Larva";436;2
"Unit";"Roach";"Larva";450;2
"Unit";"Roach";"Larva";450;2
"Unit";"Roach";"Larva";450;2
"Unit";"Roach";"Larva";450;2
"Unit";"Roach";"Larva";450;2
"Unit";"Roach";"Larva";450;2
"Upgrade";"EvolveMuscularAugments";"HydraliskDen";436;0
"Unit";"Hydralisk";"Larva";454;2
"Unit";"Hydralisk";"Larva";454;2
"Unit";"Hydralisk";"Larva";454;2
"Unit";"Hydralisk";"Larva";454;2
"Unit";"Hydralisk";"Larva";454;2
"Unit";"Hydralisk";"Larva";454;2
"Unit";"Hydralisk";"Larva";454;2
"Unit";"Hydralisk";"Larva";454;2
"Unit";"Hydralisk";"Larva";454;2
"Unit";"Hydralisk";"Larva";454;2
"Unit";"Hydralisk";"Larva";454;2
"Unit";"Roach";"Larva";466;2
"Unit";"Roach";"Larva";466;2
"Unit";"Roach";"Larva";466;2
"Unit";"Roach";"Larva";466;2
"Unit";"Roach";"Larva";466;2
"Unit";"Roach";"Larva";466;2
"Unit";"Roach";"Larva";492;2
"Unit";"Roach";"Larva";492;2
"Unit";"Roach";"Larva";492;2
"Unit";"Roach";"Larva";492;2
"Unit";"Queen";"Hatchery";492;2
"Unit";"Queen";"Hatchery";492;2
"Building";"CreepTumor";NA;508;0
"Upgrade";"EvolveGroovedSpines";"HydraliskDen";492;0
"Unit";"Queen";"Hatchery";508;2
"Unit";"Roach";"Larva";523;2
"Unit";"Roach";"Larva";523;2
"Unit";"Roach";"Larva";523;2
"Unit";"Roach";"Larva";523;2
"Unit";"Hydralisk";"Larva";523;2
"Unit";"Hydralisk";"Larva";523;2
"Unit";"Hydralisk";"Larva";523;2
"Unit";"Roach";"Larva";525;2
