"type";"unit_name";"on_building";"total_supply";"supply"
"Unit";"Overlord";"Larva";12;0
"Building";"Extractor";NA;17;0
"Unit";"Overlord";"Larva";21;0
"Building";"SpawningPool";NA;19;0
"Building";"Hatchery";NA;17;0
"Unit";"Zergling";"Larva";22;1
"Unit";"Zergling";"Larva";22;1
"Unit";"Zergling";"Larva";22;1
"Unit";"Zergling";"Larva";22;1
"Unit";"Queen";"Hatchery";22;2
"Unit";"Queen";"Hatchery";22;2
"Building";"BanelingNest";NA;24;0
"Unit";"Overlord";"Larva";36;0
"Unit";"Zergling";"Larva";36;1
"Unit";"Zergling";"Larva";36;1
"Unit";"Baneling";"Zergling";41;0
"Unit";"Baneling";"Zergling";41;0
"Unit";"Overlord";"Larva";41;0
"Building";"Hatchery";NA;30;0
"Unit";"Zergling";"Larva";45;1
"Unit";"Zergling";"Larva";45;1
"Building";"CreepTumorQueen";NA;45;0
"Unit";"Zergling";"Larva";45;1
"Unit";"Zergling";"Larva";45;1
"Unit";"Zergling";"Larva";45;1
"Unit";"Zergling";"Larva";45;1
"Unit";"Zergling";"Larva";45;1
"Unit";"Zergling";"Larva";45;1
"Unit";"Zergling";"Larva";45;1
"Unit";"Zergling";"Larva";45;1
"Unit";"Queen";"Hatchery";41;2
"Unit";"Overlord";"Larva";45;0
"Building";"CreepTumor";NA;61;0
"Unit";"Queen";"Hatchery";55;2
"Building";"EvolutionChamber";NA;61;0
"Unit";"Overlord";"Larva";67;0
"Building";"RoachWarren";NA;61;0
"Building";"Extractor";NA;75;0
"Building";"Extractor";NA;75;0
"Unit";"Baneling";"Zergling";75;0
"Unit";"Baneling";"Zergling";75;0
"Unit";"Overlord";"Larva";76;0
"Building";"EvolutionChamber";NA;84;0
"Building";"Extractor";NA;84;0
"Building";"Extractor";NA;84;0
"Unit";"Overlord";"Larva";84;0
"Unit";"Overlord";"Larva";84;0
"Unit";"Overlord";"Larva";99;0
"Unit";"Overlord";"Larva";99;0
"Unit";"Overlord";"Larva";99;0
"Unit";"Overlord";"Larva";99;0
"Building";"CreepTumor";NA;99;0
"Building";"CreepTumorQueen";NA;99;0
"Unit";"Overlord";"Larva";99;0
"Unit";"Overlord";"Larva";99;0
"Unit";"Roach";"Larva";99;2
"Unit";"Roach";"Larva";99;2
"Unit";"Roach";"Larva";99;2
"Unit";"Roach";"Larva";99;2
"Unit";"Roach";"Larva";99;2
"Unit";"Roach";"Larva";99;2
"Unit";"Roach";"Larva";99;2
"Unit";"Roach";"Larva";99;2
"Unit";"Roach";"Larva";99;2
"Unit";"Roach";"Larva";99;2
"Building";"CreepTumorQueen";NA;99;0
"Building";"CreepTumorQueen";NA;99;0
"Upgrade";"ZergMissileWeaponsLevel1";"EvolutionChamber";84;0
"Unit";"Roach";"Larva";99;2
"Unit";"Roach";"Larva";99;2
"Unit";"Roach";"Larva";99;2
"Unit";"Roach";"Larva";99;2
"Unit";"Roach";"Larva";99;2
"Unit";"Roach";"Larva";99;2
"Unit";"Roach";"Larva";99;2
"Building";"CreepTumor";NA;119;0
"Building";"Hatchery";NA;84;0
"Building";"CreepTumor";NA;119;0
"Building";"Extractor";NA;119;0
"Building";"CreepTumor";NA;133;0
"Unit";"Roach";"Larva";119;2
"Unit";"Roach";"Larva";119;2
"Upgrade";"GlialReconstitution";"RoachWarren";99;0
"Building";"CreepTumorQueen";NA;134;0
"Unit";"Overlord";"Larva";136;0
"Unit";"Overlord";"Larva";136;0
"Unit";"Overlord";"Larva";136;0
"Building";"CreepTumorQueen";NA;141;0
"Unit";"Queen";"Hatchery";136;2
"Building";"HydraliskDen";NA;140;0
"Upgrade";"ZergGroundArmorsLevel1";"EvolutionChamber";99;0
"Unit";"Roach";"Larva";146;2
"Unit";"Roach";"Larva";146;2
"Unit";"Roach";"Larva";146;2
"Unit";"Roach";"Larva";146;2
"Unit";"Roach";"Larva";146;2
"Unit";"Roach";"Larva";146;2
"Unit";"Roach";"Larva";146;2
"Unit";"Roach";"Larva";146;2
"Unit";"Roach";"Larva";146;2
"Unit";"Roach";"Larva";146;2
"Unit";"Roach";"Larva";146;2
"Unit";"Roach";"Larva";146;2
"Building";"CreepTumorQueen";NA;172;0
"Unit";"Roach";"Larva";148;2
"Unit";"Roach";"Larva";148;2
"Unit";"Roach";"Larva";148;2
"Unit";"Roach";"Larva";148;2
"Unit";"Roach";"Larva";148;2
"Unit";"Roach";"Larva";148;2
"Unit";"Roach";"Larva";148;2
"Building";"CreepTumor";NA;172;0
"Building";"CreepTumor";NA;172;0
"Building";"Extractor";NA;148;0
"Unit";"Overlord";"Larva";172;0
"Unit";"Overlord";"Larva";172;0
"Unit";"Overlord";"Larva";172;0
"Unit";"Roach";"Larva";172;2
"Unit";"Roach";"Larva";172;2
"Unit";"Roach";"Larva";172;2
"Unit";"Roach";"Larva";172;2
"Unit";"Roach";"Larva";172;2
"Unit";"Roach";"Larva";172;2
"Unit";"Roach";"Larva";172;2
"Unit";"Roach";"Larva";200;2
"Unit";"Roach";"Larva";200;2
"Unit";"Roach";"Larva";200;2
"Unit";"Hydralisk";"Larva";200;2
"Unit";"Hydralisk";"Larva";200;2
"Unit";"Hydralisk";"Larva";200;2
"Unit";"Hydralisk";"Larva";200;2
"Unit";"Hydralisk";"Larva";200;2
"Unit";"Hydralisk";"Larva";200;2
"Unit";"Hydralisk";"Larva";200;2
"Upgrade";"EvolveGroovedSpines";"HydraliskDen";186;0
"Upgrade";"ZergMissileWeaponsLevel2";"EvolutionChamber";146;0
"Unit";"Roach";"Larva";203;2
"Unit";"Roach";"Larva";209;2
"Unit";"Roach";"Larva";209;2
"Unit";"Roach";"Larva";211;2
"Unit";"Roach";"Larva";211;2
"Unit";"Roach";"Larva";211;2
"Unit";"Roach";"Larva";211;2
"Unit";"Roach";"Larva";211;2
"Unit";"Roach";"Larva";211;2
"Unit";"Roach";"Larva";213;2
"Unit";"Roach";"Larva";213;2
"Unit";"Roach";"Larva";213;2
"Building";"CreepTumorQueen";NA;223;0
"Unit";"Overlord";"Larva";247;0
"Unit";"Overlord";"Larva";247;0
"Building";"InfestationPit";NA;247;0
"Unit";"Roach";"Larva";247;2
"Unit";"Roach";"Larva";247;2
"Unit";"Roach";"Larva";247;2
"Unit";"Roach";"Larva";247;2
"Unit";"Roach";"Larva";247;2
"Unit";"Roach";"Larva";247;2
"Unit";"Roach";"Larva";247;2
"Unit";"Roach";"Larva";247;2
"Unit";"Roach";"Larva";247;2
"Unit";"Roach";"Larva";247;2
"Unit";"Roach";"Larva";247;2
"Unit";"Roach";"Larva";247;2
"Unit";"Roach";"Larva";247;2
"Unit";"Roach";"Larva";247;2
"Unit";"Roach";"Larva";247;2
"Unit";"Roach";"Larva";247;2
"Unit";"Roach";"Larva";247;2
"Unit";"Roach";"Larva";247;2
