"type";"unit_name";"on_building";"total_supply";"supply"
"Unit";"Overlord";"Larva";12;0
"Building";"Extractor";NA;18;0
"Unit";"Overlord";"Larva";21;0
"Building";"SpawningPool";NA;19;0
"Building";"Hatchery";NA;17;0
"Unit";"Zergling";"Larva";22;1
"Unit";"Zergling";"Larva";22;1
"Unit";"Zergling";"Larva";22;1
"Unit";"Zergling";"Larva";22;1
"Unit";"Zergling";"Larva";22;1
"Unit";"Zergling";"Larva";22;1
"Unit";"Zergling";"Larva";22;1
"Unit";"Zergling";"Larva";22;1
"Unit";"Queen";"Hatchery";22;2
"Unit";"Zergling";"Larva";26;1
"Unit";"Zergling";"Larva";26;1
"Building";"BanelingNest";NA;22;0
"Unit";"Zergling";"Larva";30;1
"Unit";"Zergling";"Larva";30;1
"Unit";"Zergling";"Larva";30;1
"Unit";"Zergling";"Larva";30;1
"Unit";"Baneling";"Zergling";34;0
"Unit";"Baneling";"Zergling";34;0
"Unit";"Overlord";"Larva";38;0
"Unit";"Overlord";"Larva";38;0
"Unit";"Overlord";"Larva";38;0
"Unit";"Queen";"Hatchery";38;2
"Building";"Hatchery";NA;38;0
"Building";"EvolutionChamber";NA;48;0
"Unit";"Zergling";"Larva";49;1
"Unit";"Zergling";"Larva";49;1
"Unit";"Zergling";"Larva";49;1
"Unit";"Zergling";"Larva";49;1
"Unit";"Zergling";"Larva";49;1
"Unit";"Zergling";"Larva";49;1
"Building";"CreepTumorQueen";NA;51;0
"Building";"EvolutionChamber";NA;50;0
"Unit";"Overlord";"Larva";61;0
"Building";"CreepTumor";NA;66;0
"Building";"Extractor";NA;66;0
"Unit";"Overlord";"Larva";66;0
"Building";"Hatchery";NA;49;0
"Unit";"Queen";"Hatchery";66;2
"Unit";"Zergling";"Larva";69;1
"Unit";"Zergling";"Larva";69;1
"Unit";"Zergling";"Larva";69;1
"Unit";"Zergling";"Larva";69;1
"Unit";"Zergling";"Larva";69;1
"Unit";"Zergling";"Larva";69;1
"Unit";"Zergling";"Larva";69;1
"Unit";"Zergling";"Larva";69;1
"Unit";"Zergling";"Larva";69;1
"Unit";"Zergling";"Larva";69;1
"Unit";"Zergling";"Larva";69;1
"Unit";"Zergling";"Larva";69;1
"Unit";"Zergling";"Larva";69;1
"Unit";"Zergling";"Larva";69;1
"Unit";"Zergling";"Larva";69;1
"Unit";"Zergling";"Larva";69;1
"Unit";"Zergling";"Larva";69;1
"Unit";"Zergling";"Larva";69;1
"Unit";"Zergling";"Larva";69;1
"Unit";"Zergling";"Larva";69;1
"Unit";"Queen";"Hatchery";69;2
"Unit";"Zergling";"Larva";91;1
"Unit";"Zergling";"Larva";91;1
"Unit";"Zergling";"Larva";91;1
"Unit";"Zergling";"Larva";91;1
"Unit";"Zergling";"Larva";91;1
"Unit";"Zergling";"Larva";91;1
"Unit";"Zergling";"Larva";91;1
"Unit";"Zergling";"Larva";91;1
"Unit";"Zergling";"Larva";91;1
"Unit";"Zergling";"Larva";91;1
"Unit";"Zergling";"Larva";91;1
"Unit";"Zergling";"Larva";91;1
"Upgrade";"ZergMeleeWeaponsLevel1";"EvolutionChamber";61;0
"Unit";"Zergling";"Larva";91;1
"Unit";"Zergling";"Larva";91;1
"Unit";"Zergling";"Larva";91;1
"Unit";"Zergling";"Larva";91;1
"Unit";"Zergling";"Larva";91;1
"Unit";"Zergling";"Larva";91;1
"Unit";"Zergling";"Larva";91;1
"Unit";"Zergling";"Larva";91;1
"Unit";"Zergling";"Larva";91;1
"Unit";"Zergling";"Larva";91;1
"Unit";"Zergling";"Larva";91;1
"Unit";"Zergling";"Larva";91;1
"Building";"CreepTumorQueen";NA;105;0
"Unit";"Overlord";"Larva";105;0
"Unit";"Zergling";"Larva";117;1
"Unit";"Zergling";"Larva";117;1
"Unit";"Zergling";"Larva";117;1
"Unit";"Zergling";"Larva";117;1
"Unit";"Zergling";"Larva";117;1
"Unit";"Zergling";"Larva";117;1
"Unit";"Zergling";"Larva";117;1
"Unit";"Zergling";"Larva";117;1
"Unit";"Zergling";"Larva";117;1
"Unit";"Zergling";"Larva";117;1
"Unit";"Zergling";"Larva";117;1
"Unit";"Zergling";"Larva";117;1
"Unit";"Zergling";"Larva";117;1
"Unit";"Zergling";"Larva";117;1
"Unit";"Zergling";"Larva";117;1
"Unit";"Zergling";"Larva";117;1
"Unit";"Baneling";"Zergling";117;0
"Unit";"Baneling";"Zergling";117;0
"Unit";"Baneling";"Zergling";117;0
"Unit";"Baneling";"Zergling";117;0
"Unit";"Baneling";"Zergling";117;0
"Unit";"Baneling";"Zergling";117;0
"Unit";"Baneling";"Zergling";117;0
"Unit";"Baneling";"Zergling";117;0
"Unit";"Baneling";"Zergling";117;0
"Unit";"Baneling";"Zergling";117;0
"Unit";"Baneling";"Zergling";117;0
"Unit";"Baneling";"Zergling";117;0
"Unit";"Baneling";"Zergling";117;0
"Unit";"Baneling";"Zergling";117;0
"Upgrade";"ZergGroundArmorsLevel1";"EvolutionChamber";69;0
"Building";"CreepTumor";NA;129;0
"Unit";"Zergling";"Larva";117;1
"Unit";"Zergling";"Larva";117;1
"Unit";"Zergling";"Larva";117;1
"Unit";"Zergling";"Larva";117;1
"Unit";"Zergling";"Larva";117;1
"Unit";"Zergling";"Larva";117;1
"Unit";"Zergling";"Larva";117;1
"Unit";"Zergling";"Larva";117;1
"Unit";"Zergling";"Larva";117;1
"Unit";"Zergling";"Larva";117;1
"Unit";"Baneling";"Zergling";133;0
"Unit";"Baneling";"Zergling";133;0
"Unit";"Baneling";"Zergling";133;0
"Unit";"Baneling";"Zergling";133;0
"Unit";"Baneling";"Zergling";133;0
"Unit";"Zergling";"Larva";133;1
"Unit";"Zergling";"Larva";133;1
"Unit";"Overlord";"Larva";143;0
"Unit";"Overlord";"Larva";143;0
"Unit";"Queen";"Hatchery";145;2
"Unit";"Zergling";"Larva";157;1
"Unit";"Zergling";"Larva";157;1
"Unit";"Zergling";"Larva";157;1
"Unit";"Zergling";"Larva";157;1
"Unit";"Zergling";"Larva";157;1
"Unit";"Zergling";"Larva";157;1
"Unit";"Zergling";"Larva";157;1
"Unit";"Zergling";"Larva";157;1
"Unit";"Zergling";"Larva";157;1
"Unit";"Zergling";"Larva";157;1
"Unit";"Zergling";"Larva";157;1
"Unit";"Zergling";"Larva";157;1
"Unit";"Zergling";"Larva";157;1
"Unit";"Zergling";"Larva";157;1
"Unit";"Zergling";"Larva";157;1
"Unit";"Zergling";"Larva";157;1
"Unit";"Zergling";"Larva";157;1
"Unit";"Zergling";"Larva";157;1
"Unit";"Zergling";"Larva";157;1
"Unit";"Zergling";"Larva";157;1
"Unit";"Zergling";"Larva";157;1
"Unit";"Zergling";"Larva";157;1
"Unit";"Zergling";"Larva";157;1
"Unit";"Zergling";"Larva";157;1
"Unit";"Zergling";"Larva";157;1
"Unit";"Zergling";"Larva";157;1
"Unit";"Zergling";"Larva";157;1
"Unit";"Zergling";"Larva";157;1
"Unit";"Zergling";"Larva";157;1
"Unit";"Zergling";"Larva";157;1
"Unit";"Baneling";"Zergling";177;0
"Unit";"Baneling";"Zergling";177;0
"Unit";"Baneling";"Zergling";177;0
"Unit";"Baneling";"Zergling";177;0
"Unit";"Baneling";"Zergling";177;0
"Unit";"Baneling";"Zergling";177;0
"Unit";"Baneling";"Zergling";177;0
"Unit";"Baneling";"Zergling";177;0
"Unit";"Baneling";"Zergling";177;0
"Unit";"Baneling";"Zergling";177;0
"Unit";"Baneling";"Zergling";177;0
"Unit";"Baneling";"Zergling";177;0
"Unit";"Zergling";"Larva";177;1
"Unit";"Zergling";"Larva";177;1
"Unit";"Baneling";"Zergling";177;0
"Building";"SpineCrawler";NA;157;0
"Building";"SpineCrawler";NA;157;0
"Building";"SpineCrawler";NA;157;0
"Unit";"Zergling";"Larva";189;1
"Unit";"Zergling";"Larva";189;1
"Unit";"Zergling";"Larva";189;1
"Unit";"Zergling";"Larva";189;1
"Unit";"Zergling";"Larva";189;1
"Unit";"Zergling";"Larva";189;1
"Unit";"Zergling";"Larva";189;1
"Unit";"Zergling";"Larva";189;1
"Unit";"Zergling";"Larva";189;1
"Unit";"Zergling";"Larva";189;1
"Unit";"Zergling";"Larva";189;1
"Unit";"Zergling";"Larva";189;1
"Building";"CreepTumor";NA;191;0
"Unit";"Zergling";"Larva";191;1
"Unit";"Zergling";"Larva";191;1
"Unit";"Zergling";"Larva";191;1
"Unit";"Zergling";"Larva";191;1
"Unit";"Zergling";"Larva";191;1
"Unit";"Zergling";"Larva";191;1
"Unit";"Zergling";"Larva";191;1
"Unit";"Zergling";"Larva";191;1
"Unit";"Zergling";"Larva";191;1
"Unit";"Zergling";"Larva";191;1
"Unit";"Zergling";"Larva";191;1
"Unit";"Zergling";"Larva";191;1
"Unit";"Zergling";"Larva";191;1
"Unit";"Zergling";"Larva";191;1
"Unit";"Zergling";"Larva";191;1
"Unit";"Zergling";"Larva";191;1
"Unit";"Zergling";"Larva";191;1
"Unit";"Zergling";"Larva";191;1
"Unit";"Zergling";"Larva";215;1
"Unit";"Zergling";"Larva";215;1
"Unit";"Zergling";"Larva";215;1
"Unit";"Zergling";"Larva";215;1
"Unit";"Zergling";"Larva";215;1
"Unit";"Zergling";"Larva";215;1
"Unit";"Zergling";"Larva";215;1
"Unit";"Zergling";"Larva";215;1
"Unit";"Zergling";"Larva";215;1
"Unit";"Zergling";"Larva";215;1
"Unit";"Baneling";"Zergling";215;0
"Unit";"Baneling";"Zergling";215;0
"Unit";"Baneling";"Zergling";215;0
"Unit";"Baneling";"Zergling";215;0
"Unit";"Baneling";"Zergling";215;0
"Unit";"Baneling";"Zergling";215;0
"Unit";"Baneling";"Zergling";215;0
"Unit";"Baneling";"Zergling";215;0
"Unit";"Zergling";"Larva";221;1
"Unit";"Zergling";"Larva";221;1
"Unit";"Zergling";"Larva";221;1
"Unit";"Zergling";"Larva";221;1
"Unit";"Zergling";"Larva";221;1
"Unit";"Zergling";"Larva";221;1
"Unit";"Zergling";"Larva";221;1
"Unit";"Zergling";"Larva";221;1
"Unit";"Zergling";"Larva";221;1
"Unit";"Zergling";"Larva";221;1
"Unit";"Zergling";"Larva";221;1
"Unit";"Zergling";"Larva";221;1
"Unit";"Zergling";"Larva";221;1
"Unit";"Zergling";"Larva";221;1
"Unit";"Zergling";"Larva";221;1
"Unit";"Zergling";"Larva";221;1
"Unit";"Zergling";"Larva";247;1
"Unit";"Zergling";"Larva";247;1
"Unit";"Zergling";"Larva";247;1
"Unit";"Zergling";"Larva";247;1
"Unit";"Zergling";"Larva";247;1
"Unit";"Zergling";"Larva";247;1
"Unit";"Zergling";"Larva";247;1
"Unit";"Zergling";"Larva";247;1
"Unit";"Zergling";"Larva";247;1
"Unit";"Zergling";"Larva";247;1
"Unit";"Zergling";"Larva";247;1
"Unit";"Zergling";"Larva";247;1
"Unit";"Zergling";"Larva";247;1
"Unit";"Zergling";"Larva";247;1
"Unit";"Zergling";"Larva";247;1
"Unit";"Zergling";"Larva";247;1
"Unit";"Zergling";"Larva";247;1
"Unit";"Zergling";"Larva";247;1
"Unit";"Zergling";"Larva";247;1
"Unit";"Zergling";"Larva";247;1
"Unit";"Zergling";"Larva";247;1
"Unit";"Zergling";"Larva";247;1
"Unit";"Zergling";"Larva";247;1
"Unit";"Zergling";"Larva";247;1
"Unit";"Zergling";"Larva";247;1
"Unit";"Zergling";"Larva";247;1
"Unit";"Zergling";"Larva";247;1
"Unit";"Zergling";"Larva";247;1
"Unit";"Zergling";"Larva";247;1
"Unit";"Zergling";"Larva";247;1
"Unit";"Zergling";"Larva";269;1
"Unit";"Zergling";"Larva";269;1
"Unit";"Zergling";"Larva";269;1
"Unit";"Zergling";"Larva";269;1
"Unit";"Zergling";"Larva";269;1
"Unit";"Zergling";"Larva";269;1
"Unit";"Queen";"Hatchery";247;2
"Unit";"Queen";"Hatchery";277;2
"Unit";"Zergling";"Larva";288;1
"Unit";"Zergling";"Larva";288;1
"Unit";"Zergling";"Larva";288;1
"Unit";"Zergling";"Larva";288;1
"Unit";"Zergling";"Larva";288;1
"Unit";"Zergling";"Larva";288;1
"Unit";"Zergling";"Larva";288;1
"Unit";"Zergling";"Larva";288;1
"Unit";"Zergling";"Larva";288;1
"Unit";"Zergling";"Larva";288;1
"Unit";"Zergling";"Larva";288;1
"Unit";"Zergling";"Larva";288;1
"Unit";"Zergling";"Larva";288;1
"Unit";"Zergling";"Larva";288;1
"Unit";"Zergling";"Larva";288;1
"Unit";"Zergling";"Larva";288;1
"Unit";"Zergling";"Larva";288;1
"Unit";"Zergling";"Larva";288;1
"Unit";"Zergling";"Larva";288;1
"Unit";"Zergling";"Larva";288;1
"Unit";"Zergling";"Larva";317;1
"Unit";"Zergling";"Larva";317;1
"Unit";"Zergling";"Larva";317;1
"Unit";"Zergling";"Larva";317;1
"Unit";"Zergling";"Larva";317;1
"Unit";"Zergling";"Larva";317;1
"Unit";"Zergling";"Larva";317;1
"Unit";"Zergling";"Larva";317;1
"Unit";"Zergling";"Larva";317;1
"Unit";"Zergling";"Larva";317;1
"Unit";"Baneling";"Zergling";317;0
"Unit";"Zergling";"Larva";317;1
"Unit";"Zergling";"Larva";317;1
"Unit";"Baneling";"Zergling";317;0
"Unit";"Baneling";"Zergling";317;0
"Unit";"Baneling";"Zergling";317;0
"Unit";"Baneling";"Zergling";317;0
"Unit";"Baneling";"Zergling";317;0
"Unit";"Baneling";"Zergling";317;0
"Unit";"Baneling";"Zergling";317;0
"Unit";"Baneling";"Zergling";317;0
"Unit";"Baneling";"Zergling";317;0
"Unit";"Baneling";"Zergling";317;0
"Unit";"Baneling";"Zergling";317;0
"Unit";"Zergling";"Larva";317;1
"Unit";"Zergling";"Larva";317;1
"Unit";"Zergling";"Larva";317;1
"Unit";"Zergling";"Larva";317;1
"Unit";"Zergling";"Larva";317;1
"Unit";"Zergling";"Larva";317;1
"Unit";"Zergling";"Larva";317;1
"Unit";"Zergling";"Larva";317;1
"Unit";"Zergling";"Larva";325;1
"Unit";"Zergling";"Larva";325;1
"Unit";"Zergling";"Larva";325;1
"Unit";"Zergling";"Larva";325;1
"Unit";"Zergling";"Larva";325;1
"Unit";"Zergling";"Larva";325;1
"Unit";"Zergling";"Larva";325;1
"Unit";"Zergling";"Larva";325;1
"Unit";"Zergling";"Larva";325;1
"Unit";"Zergling";"Larva";325;1
"Unit";"Zergling";"Larva";347;1
"Unit";"Zergling";"Larva";347;1
"Unit";"Zergling";"Larva";347;1
"Unit";"Zergling";"Larva";347;1
"Unit";"Zergling";"Larva";347;1
"Unit";"Zergling";"Larva";347;1
"Unit";"Zergling";"Larva";347;1
"Unit";"Zergling";"Larva";347;1
"Unit";"Zergling";"Larva";347;1
"Unit";"Zergling";"Larva";347;1
"Unit";"Zergling";"Larva";347;1
"Unit";"Zergling";"Larva";347;1
"Unit";"Zergling";"Larva";347;1
"Unit";"Zergling";"Larva";347;1
"Building";"SpineCrawler";NA;329;0
"Building";"Hatchery";NA;310;0
"Unit";"Zergling";"Larva";349;1
"Unit";"Zergling";"Larva";349;1
"Unit";"Zergling";"Larva";361;1
"Unit";"Zergling";"Larva";361;1
"Unit";"Zergling";"Larva";361;1
"Unit";"Zergling";"Larva";361;1
"Unit";"Zergling";"Larva";361;1
"Unit";"Zergling";"Larva";361;1
"Unit";"Zergling";"Larva";361;1
"Unit";"Zergling";"Larva";361;1
"Unit";"Zergling";"Larva";361;1
"Unit";"Zergling";"Larva";361;1
"Unit";"Zergling";"Larva";361;1
"Unit";"Zergling";"Larva";361;1
"Unit";"Zergling";"Larva";361;1
"Unit";"Zergling";"Larva";361;1
"Unit";"Zergling";"Larva";361;1
"Unit";"Zergling";"Larva";361;1
"Unit";"Zergling";"Larva";361;1
"Unit";"Zergling";"Larva";361;1
"Unit";"Zergling";"Larva";361;1
"Unit";"Zergling";"Larva";361;1
"Unit";"Zergling";"Larva";361;1
"Unit";"Zergling";"Larva";361;1
"Unit";"Zergling";"Larva";361;1
"Unit";"Zergling";"Larva";361;1
"Upgrade";"ZergMeleeWeaponsLevel2";"EvolutionChamber";310;0
"Unit";"Zergling";"Larva";387;1
"Unit";"Zergling";"Larva";387;1
"Unit";"Zergling";"Larva";387;1
"Unit";"Zergling";"Larva";387;1
"Unit";"Zergling";"Larva";387;1
"Unit";"Zergling";"Larva";387;1
"Unit";"Zergling";"Larva";387;1
"Unit";"Zergling";"Larva";387;1
"Unit";"Zergling";"Larva";387;1
"Unit";"Zergling";"Larva";387;1
"Unit";"Zergling";"Larva";387;1
"Unit";"Zergling";"Larva";387;1
"Unit";"Zergling";"Larva";387;1
"Unit";"Zergling";"Larva";387;1
"Unit";"Zergling";"Larva";387;1
"Unit";"Zergling";"Larva";387;1
"Unit";"Zergling";"Larva";387;1
"Unit";"Zergling";"Larva";387;1
"Unit";"Zergling";"Larva";387;1
"Unit";"Zergling";"Larva";387;1
"Unit";"Zergling";"Larva";387;1
"Unit";"Zergling";"Larva";387;1
"Unit";"Zergling";"Larva";387;1
"Unit";"Zergling";"Larva";387;1
"Unit";"Zergling";"Larva";387;1
"Unit";"Zergling";"Larva";387;1
"Unit";"Zergling";"Larva";387;1
"Unit";"Zergling";"Larva";387;1
"Unit";"Zergling";"Larva";389;1
"Unit";"Zergling";"Larva";389;1
"Unit";"Zergling";"Larva";389;1
"Unit";"Zergling";"Larva";389;1
"Unit";"Zergling";"Larva";389;1
"Unit";"Zergling";"Larva";389;1
"Unit";"Zergling";"Larva";391;1
"Unit";"Zergling";"Larva";391;1
"Unit";"Zergling";"Larva";391;1
"Unit";"Zergling";"Larva";391;1
"Unit";"Zergling";"Larva";391;1
"Unit";"Zergling";"Larva";391;1
"Unit";"Baneling";"Zergling";427;0
"Unit";"Baneling";"Zergling";427;0
"Unit";"Baneling";"Zergling";427;0
"Unit";"Baneling";"Zergling";427;0
"Unit";"Baneling";"Zergling";427;0
"Unit";"Baneling";"Zergling";427;0
"Unit";"Baneling";"Zergling";427;0
"Unit";"Baneling";"Zergling";427;0
"Unit";"Baneling";"Zergling";427;0
"Unit";"Baneling";"Zergling";427;0
"Unit";"Baneling";"Zergling";427;0
"Unit";"Baneling";"Zergling";427;0
"Unit";"Baneling";"Zergling";427;0
"Unit";"Baneling";"Zergling";427;0
"Unit";"Baneling";"Zergling";427;0
"Unit";"Baneling";"Zergling";427;0
"Unit";"Baneling";"Zergling";427;0
"Unit";"Baneling";"Zergling";427;0
"Unit";"Baneling";"Zergling";427;0
"Unit";"Baneling";"Zergling";427;0
"Unit";"Baneling";"Zergling";427;0
"Unit";"Zergling";"Larva";427;1
"Unit";"Zergling";"Larva";427;1
"Unit";"Zergling";"Larva";427;1
"Unit";"Zergling";"Larva";427;1
"Unit";"Zergling";"Larva";427;1
"Unit";"Zergling";"Larva";427;1
"Unit";"Zergling";"Larva";427;1
"Unit";"Zergling";"Larva";427;1
"Unit";"Zergling";"Larva";427;1
"Unit";"Zergling";"Larva";427;1
"Unit";"Zergling";"Larva";427;1
"Unit";"Zergling";"Larva";427;1
"Unit";"Zergling";"Larva";427;1
"Unit";"Zergling";"Larva";427;1
"Unit";"Zergling";"Larva";427;1
"Unit";"Zergling";"Larva";427;1
"Unit";"Zergling";"Larva";427;1
"Unit";"Zergling";"Larva";427;1
"Unit";"Baneling";"Zergling";427;0
"Building";"SpineCrawler";NA;427;0
"Unit";"Overlord";"Larva";448;0
"Unit";"Overlord";"Larva";448;0
"Unit";"Overlord";"Larva";448;0
"Unit";"Overlord";"Larva";448;0
"Unit";"Overlord";"Larva";448;0
"Unit";"Overlord";"Larva";448;0
"Unit";"Baneling";"Zergling";448;0
"Unit";"Baneling";"Zergling";448;0
"Unit";"Baneling";"Zergling";448;0
"Unit";"Baneling";"Zergling";448;0
"Unit";"Baneling";"Zergling";448;0
"Unit";"Baneling";"Zergling";448;0
"Unit";"Baneling";"Zergling";448;0
"Unit";"Baneling";"Zergling";448;0
"Building";"Hatchery";NA;427;0
"Unit";"Zergling";"Larva";448;1
"Unit";"Zergling";"Larva";448;1
"Unit";"Zergling";"Larva";448;1
"Unit";"Zergling";"Larva";448;1
"Unit";"Zergling";"Larva";448;1
"Unit";"Zergling";"Larva";448;1
"Unit";"Zergling";"Larva";448;1
"Unit";"Zergling";"Larva";448;1
"Unit";"Zergling";"Larva";448;1
"Unit";"Zergling";"Larva";448;1
"Unit";"Zergling";"Larva";448;1
"Unit";"Zergling";"Larva";448;1
"Unit";"Zergling";"Larva";448;1
"Unit";"Zergling";"Larva";448;1
"Unit";"Zergling";"Larva";448;1
"Unit";"Zergling";"Larva";448;1
"Unit";"Zergling";"Larva";448;1
"Unit";"Zergling";"Larva";448;1
"Unit";"Zergling";"Larva";448;1
"Unit";"Zergling";"Larva";448;1
"Unit";"Zergling";"Larva";448;1
"Unit";"Zergling";"Larva";448;1
"Unit";"Zergling";"Larva";448;1
"Unit";"Zergling";"Larva";448;1
"Unit";"Zergling";"Larva";448;1
"Unit";"Zergling";"Larva";448;1
"Unit";"Zergling";"Larva";448;1
"Unit";"Zergling";"Larva";448;1
"Unit";"Zergling";"Larva";448;1
"Unit";"Zergling";"Larva";448;1
"Unit";"Zergling";"Larva";448;1
"Unit";"Zergling";"Larva";448;1
"Unit";"Zergling";"Larva";448;1
"Unit";"Zergling";"Larva";448;1
"Unit";"Zergling";"Larva";448;1
"Unit";"Zergling";"Larva";448;1
"Unit";"Zergling";"Larva";448;1
"Unit";"Zergling";"Larva";448;1
"Unit";"Zergling";"Larva";486;1
"Unit";"Zergling";"Larva";486;1
"Unit";"Zergling";"Larva";486;1
"Unit";"Zergling";"Larva";486;1
"Unit";"Zergling";"Larva";486;1
"Unit";"Zergling";"Larva";486;1
"Unit";"Zergling";"Larva";486;1
"Unit";"Zergling";"Larva";486;1
"Unit";"Zergling";"Larva";486;1
"Unit";"Zergling";"Larva";486;1
"Unit";"Zergling";"Larva";486;1
"Unit";"Zergling";"Larva";486;1
"Unit";"Zergling";"Larva";486;1
"Unit";"Zergling";"Larva";486;1
"Unit";"Zergling";"Larva";486;1
"Unit";"Zergling";"Larva";486;1
"Unit";"Zergling";"Larva";486;1
"Unit";"Zergling";"Larva";486;1
