"type";"unit_name";"on_building";"total_supply";"supply"
"Unit";"Overlord";"Larva";12;0
"Building";"Extractor";NA;18;0
"Unit";"Overlord";"Larva";21;0
"Building";"SpawningPool";NA;19;0
"Building";"Hatchery";NA;17;0
"Unit";"Zergling";"Larva";22;1
"Unit";"Zergling";"Larva";22;1
"Unit";"Zergling";"Larva";23;1
"Unit";"Zergling";"Larva";23;1
"Unit";"Queen";"Hatchery";22;2
"Unit";"Queen";"Hatchery";22;2
"Unit";"Zergling";"Larva";35;1
"Unit";"Zergling";"Larva";35;1
"Unit";"Overlord";"Larva";35;0
"Unit";"Zergling";"Larva";35;1
"Unit";"Zergling";"Larva";35;1
"Unit";"Zergling";"Larva";36;1
"Unit";"Zergling";"Larva";36;1
"Unit";"Queen";"Hatchery";35;2
"Building";"CreepTumorQueen";NA;45;0
"Building";"Hatchery";NA;30;0
"Unit";"Overlord";"Larva";52;0
"Building";"CreepTumor";NA;57;0
"Unit";"Zergling";"Larva";57;1
"Unit";"Zergling";"Larva";57;1
"Unit";"Zergling";"Larva";57;1
"Unit";"Zergling";"Larva";57;1
"Building";"Extractor";NA;57;0
"Unit";"Overlord";"Larva";62;0
"Unit";"Zergling";"Larva";66;1
"Unit";"Zergling";"Larva";66;1
"Building";"RoachWarren";NA;57;0
"Building";"Extractor";NA;66;0
"Building";"EvolutionChamber";NA;69;0
"Unit";"Overlord";"Larva";73;0
"Unit";"Overlord";"Larva";78;0
"Unit";"Roach";"Larva";88;2
"Building";"CreepTumor";NA;91;0
"Unit";"Overlord";"Larva";89;0
"Unit";"Roach";"Larva";89;2
"Building";"Extractor";NA;89;0
"Unit";"Roach";"Larva";89;2
"Unit";"Roach";"Larva";89;2
"Unit";"Overlord";"Larva";91;0
"Unit";"Roach";"Larva";91;2
"Unit";"Roach";"Larva";91;2
"Unit";"Roach";"Larva";95;2
"Unit";"Roach";"Larva";95;2
"Unit";"Roach";"Larva";95;2
"Unit";"Overlord";"Larva";99;0
"Unit";"Roach";"Larva";101;2
"Unit";"Roach";"Larva";101;2
"Building";"Extractor";NA;101;0
"Unit";"Roach";"Larva";103;2
"Unit";"Roach";"Larva";103;2
"Unit";"Roach";"Larva";103;2
"Unit";"Roach";"Larva";103;2
"Unit";"Roach";"Larva";103;2
"Unit";"Roach";"Larva";112;2
"Unit";"Roach";"Larva";112;2
"Unit";"Roach";"Larva";112;2
"Unit";"Overlord";"Larva";116;0
"Unit";"Overlord";"Larva";116;0
"Unit";"Roach";"Larva";126;2
"Building";"CreepTumor";NA;132;0
"Unit";"Roach";"Larva";132;2
"Unit";"Overlord";"Larva";132;0
"Unit";"Roach";"Larva";132;2
"Unit";"Roach";"Larva";132;2
"Unit";"Overlord";"Larva";132;0
"Unit";"Roach";"Larva";132;2
"Unit";"Roach";"Larva";132;2
"Unit";"Roach";"Larva";132;2
"Unit";"Roach";"Larva";132;2
"Unit";"Roach";"Larva";132;2
"Upgrade";"GlialReconstitution";"RoachWarren";103;0
"Upgrade";"ZergMissileWeaponsLevel1";"EvolutionChamber";93;0
"Unit";"Roach";"Larva";150;2
"Unit";"Roach";"Larva";150;2
"Unit";"Roach";"Larva";150;2
"Unit";"Roach";"Larva";150;2
"Unit";"Roach";"Larva";150;2
"Unit";"Roach";"Larva";150;2
"Unit";"Roach";"Larva";150;2
"Unit";"Roach";"Larva";150;2
"Building";"CreepTumor";NA;150;0
"Unit";"Overlord";"Larva";150;0
"Unit";"Overlord";"Larva";150;0
"Unit";"Overlord";"Larva";150;0
"Building";"Extractor";NA;150;0
"Unit";"Roach";"Larva";166;2
"Unit";"Roach";"Larva";166;2
"Unit";"Roach";"Larva";166;2
"Building";"Hatchery";NA;134;0
"Unit";"Roach";"Larva";166;2
"Unit";"Roach";"Larva";166;2
"Unit";"Roach";"Larva";166;2
"Unit";"Roach";"Larva";166;2
"Unit";"Roach";"Larva";166;2
"Unit";"Roach";"Larva";166;2
"Unit";"Roach";"Larva";166;2
"Building";"HydraliskDen";NA;166;0
"Unit";"Queen";"Hatchery";166;2
"Unit";"Queen";"Hatchery";166;2
"Unit";"Queen";"Hatchery";166;2
"Unit";"Roach";"Larva";178;2
"Unit";"Roach";"Larva";178;2
"Unit";"Roach";"Larva";178;2
"Building";"SporeCrawler";NA;182;0
"Unit";"Roach";"Larva";192;2
"Unit";"Roach";"Larva";192;2
"Building";"CreepTumorQueen";NA;204;0
"Unit";"Roach";"Larva";192;2
"Unit";"Roach";"Larva";192;2
"Building";"SporeCrawler";NA;204;0
"Unit";"Hydralisk";"Larva";194;2
"Unit";"Hydralisk";"Larva";196;2
"Building";"SporeCrawler";NA;204;0
"Building";"SporeCrawler";NA;204;0
"Unit";"Hydralisk";"Larva";204;2
"Unit";"Hydralisk";"Larva";204;2
"Building";"SporeCrawler";NA;212;0
"Unit";"Hydralisk";"Larva";212;2
"Unit";"Hydralisk";"Larva";212;2
"Unit";"Hydralisk";"Larva";212;2
"Unit";"Hydralisk";"Larva";212;2
"Unit";"Overlord";"Larva";216;0
"Unit";"Hydralisk";"Larva";216;2
"Building";"CreepTumorQueen";NA;220;0
"Unit";"Hydralisk";"Larva";216;2
"Unit";"Overlord";"Larva";220;0
"Unit";"Overlord";"Larva";220;0
"Building";"CreepTumor";NA;230;0
"Building";"CreepTumor";NA;232;0
"Upgrade";"ZergMissileWeaponsLevel2";"EvolutionChamber";166;0
"Building";"CreepTumor";NA;232;0
"Unit";"Hydralisk";"Larva";232;2
"Unit";"Hydralisk";"Larva";232;2
"Unit";"Hydralisk";"Larva";232;2
"Unit";"Overlord";"Larva";241;0
"Unit";"Overlord";"Larva";241;0
"Unit";"Overlord";"Larva";241;0
"Unit";"Overlord";"Larva";241;0
"Unit";"Hydralisk";"Larva";241;2
"Unit";"Hydralisk";"Larva";241;2
"Unit";"Hydralisk";"Larva";241;2
"Unit";"Overlord";"Larva";247;0
"Unit";"Overlord";"Larva";247;0
"Upgrade";"EvolveGroovedSpines";"HydraliskDen";232;0
"Unit";"Hydralisk";"Larva";253;2
"Unit";"Hydralisk";"Larva";253;2
"Unit";"Hydralisk";"Larva";253;2
"Unit";"Hydralisk";"Larva";253;2
"Unit";"Hydralisk";"Larva";253;2
"Unit";"Hydralisk";"Larva";253;2
"Unit";"Hydralisk";"Larva";253;2
"Unit";"Hydralisk";"Larva";253;2
"Unit";"Hydralisk";"Larva";253;2
"Unit";"Hydralisk";"Larva";253;2
"Unit";"Hydralisk";"Larva";253;2
"Unit";"Hydralisk";"Larva";268;2
