"type";"unit_name";"on_building";"total_supply";"supply"
"Unit";"Overlord";"Larva";13;0
"Building";"Extractor";NA;18;0
"Building";"SpawningPool";NA;19;0
"Unit";"Overlord";"Larva";22;0
"Building";"Hatchery";NA;17;0
"Unit";"Zergling";"Larva";22;1
"Unit";"Zergling";"Larva";22;1
"Unit";"Zergling";"Larva";22;1
"Unit";"Zergling";"Larva";22;1
"Unit";"Queen";"Hatchery";22;2
"Unit";"Queen";"Hatchery";22;2
"Building";"CreepTumorQueen";NA;35;0
"Unit";"Overlord";"Larva";35;0
"Unit";"Queen";"Hatchery";31;2
"Building";"BanelingNest";NA;35;0
"Building";"CreepTumorQueen";NA;41;0
"Building";"SpineCrawler";NA;37;0
"Building";"CreepTumor";NA;41;0
"Unit";"Zergling";"Larva";38;1
"Unit";"Zergling";"Larva";38;1
"Unit";"Zergling";"Larva";38;1
"Unit";"Zergling";"Larva";38;1
"Unit";"Overlord";"Larva";42;0
"Building";"CreepTumor";NA;51;0
"Building";"CreepTumor";NA;51;0
"Unit";"Zergling";"Larva";52;1
"Unit";"Zergling";"Larva";52;1
"Unit";"Overlord";"Larva";53;0
"Building";"Extractor";NA;55;0
"Building";"Extractor";NA;55;0
"Building";"Extractor";NA;55;0
"Building";"CreepTumorQueen";NA;61;0
"Building";"CreepTumor";NA;61;0
"Building";"CreepTumor";NA;61;0
"Building";"Hatchery";NA;49;0
"Building";"EvolutionChamber";NA;63;0
"Building";"EvolutionChamber";NA;64;0
"Building";"CreepTumor";NA;73;0
"Building";"CreepTumor";NA;73;0
"Unit";"Baneling";"Zergling";73;0
"Unit";"Baneling";"Zergling";73;0
"Unit";"Baneling";"Zergling";73;0
"Unit";"Overlord";"Larva";73;0
"Building";"HydraliskDen";NA;67;0
"Unit";"Zergling";"Larva";73;1
"Unit";"Zergling";"Larva";73;1
"Unit";"Zergling";"Larva";73;1
"Unit";"Zergling";"Larva";73;1
"Unit";"Zergling";"Larva";73;1
"Unit";"Zergling";"Larva";73;1
"Building";"CreepTumor";NA;75;0
"Unit";"Overlord";"Larva";73;0
"Unit";"Hydralisk";"Larva";75;2
"Unit";"Hydralisk";"Larva";75;2
"Unit";"Hydralisk";"Larva";75;2
"Building";"CreepTumorQueen";NA;81;0
"Unit";"Overlord";"Larva";82;0
"Building";"SporeCrawler";NA;82;0
"Unit";"Queen";"Hatchery";81;2
"Building";"SporeCrawler";NA;88;0
"Building";"SporeCrawler";NA;90;0
"Unit";"Hydralisk";"Larva";90;2
"Unit";"Overlord";"Larva";92;0
"Building";"CreepTumorQueen";NA;103;0
"Building";"CreepTumor";NA;106;0
"Building";"CreepTumor";NA;106;0
"Upgrade";"EvolveGroovedSpines";"HydraliskDen";88;0
"Building";"CreepTumor";NA;106;0
"Unit";"Overlord";"Larva";104;0
"Unit";"Overlord";"Larva";106;0
"Unit";"Hydralisk";"Larva";106;2
"Unit";"Hydralisk";"Larva";106;2
"Building";"Extractor";NA;110;0
"Building";"Extractor";NA;110;0
"Upgrade";"ZergMissileWeaponsLevel1";"EvolutionChamber";81;0
"Upgrade";"ZergGroundArmorsLevel1";"EvolutionChamber";81;0
"Unit";"Hydralisk";"Larva";111;2
"Unit";"Hydralisk";"Larva";111;2
"Unit";"Hydralisk";"Larva";118;2
"Unit";"Hydralisk";"Larva";118;2
"Unit";"Hydralisk";"Larva";118;2
"Unit";"Overlord";"Larva";119;0
"Building";"CreepTumor";NA;124;0
"Building";"CreepTumor";NA;125;0
"Building";"CreepTumor";NA;125;0
"Building";"CreepTumor";NA;125;0
"Unit";"Overlord";"Larva";125;0
"Unit";"Overlord";"Larva";125;0
"Unit";"Overlord";"Larva";131;0
"Unit";"Overlord";"Larva";131;0
"Unit";"Overlord";"Larva";131;0
"Unit";"Overlord";"Larva";131;0
"Unit";"Overlord";"Larva";131;0
"Unit";"Zergling";"Larva";131;1
"Unit";"Zergling";"Larva";131;1
"Upgrade";"EvolveMuscularAugments";"HydraliskDen";118;0
"Unit";"Zergling";"Larva";131;1
"Unit";"Zergling";"Larva";131;1
"Unit";"Zergling";"Larva";131;1
"Unit";"Zergling";"Larva";131;1
"Unit";"Zergling";"Larva";131;1
"Unit";"Zergling";"Larva";131;1
"Unit";"Zergling";"Larva";131;1
"Unit";"Zergling";"Larva";131;1
"Unit";"Zergling";"Larva";131;1
"Unit";"Zergling";"Larva";131;1
"Unit";"Zergling";"Larva";131;1
"Unit";"Zergling";"Larva";131;1
"Building";"CreepTumor";NA;131;0
"Building";"CreepTumorQueen";NA;131;0
"Building";"CreepTumor";NA;131;0
"Unit";"Zergling";"Larva";131;1
"Unit";"Zergling";"Larva";131;1
"Unit";"Zergling";"Larva";131;1
"Unit";"Zergling";"Larva";131;1
"Unit";"Zergling";"Larva";131;1
"Unit";"Zergling";"Larva";131;1
"Building";"CreepTumorQueen";NA;131;0
"Unit";"Hydralisk";"Larva";131;2
"Unit";"Hydralisk";"Larva";131;2
"Building";"CreepTumorQueen";NA;145;0
"Unit";"Baneling";"Zergling";145;0
"Unit";"Baneling";"Zergling";145;0
"Unit";"Baneling";"Zergling";145;0
"Unit";"Baneling";"Zergling";145;0
"Unit";"Baneling";"Zergling";145;0
"Unit";"Zergling";"Larva";151;1
"Unit";"Zergling";"Larva";151;1
"Unit";"Zergling";"Larva";151;1
"Unit";"Zergling";"Larva";151;1
"Unit";"Zergling";"Larva";151;1
"Unit";"Zergling";"Larva";151;1
"Unit";"Zergling";"Larva";151;1
"Unit";"Zergling";"Larva";151;1
"Unit";"Baneling";"Zergling";155;0
"Unit";"Baneling";"Zergling";155;0
"Unit";"Baneling";"Zergling";155;0
"Unit";"Hydralisk";"Larva";145;2
"Building";"Hatchery";NA;119;0
"Unit";"Baneling";"Zergling";155;0
"Unit";"Baneling";"Zergling";155;0
"Unit";"Baneling";"Zergling";155;0
"Building";"CreepTumorQueen";NA;155;0
"Building";"CreepTumor";NA;155;0
"Building";"CreepTumor";NA;155;0
"Unit";"Hydralisk";"Larva";155;2
"Unit";"Hydralisk";"Larva";155;2
"Unit";"Hydralisk";"Larva";155;2
"Unit";"Zergling";"Larva";163;1
"Unit";"Zergling";"Larva";163;1
"Unit";"Baneling";"Zergling";173;0
"Unit";"Baneling";"Zergling";173;0
"Unit";"Baneling";"Zergling";173;0
"Unit";"Hydralisk";"Larva";167;2
"Unit";"Baneling";"Zergling";174;0
"Building";"LurkerDenMP";NA;131;0
"Unit";"Zergling";"Larva";179;1
"Unit";"Zergling";"Larva";179;1
"Unit";"Zergling";"Larva";179;1
"Unit";"Zergling";"Larva";179;1
"Unit";"Zergling";"Larva";179;1
"Unit";"Zergling";"Larva";179;1
"Unit";"Zergling";"Larva";179;1
"Unit";"Zergling";"Larva";179;1
"Unit";"Zergling";"Larva";179;1
"Unit";"Zergling";"Larva";179;1
"Unit";"Zergling";"Larva";179;1
"Unit";"Zergling";"Larva";179;1
"Unit";"Baneling";"Zergling";179;0
"Unit";"Baneling";"Zergling";179;0
"Unit";"Baneling";"Zergling";179;0
"Unit";"Hydralisk";"Larva";179;2
"Building";"SporeCrawler";NA;179;0
"Unit";"Hydralisk";"Larva";179;2
"Unit";"Hydralisk";"Larva";179;2
"Unit";"Hydralisk";"Larva";179;2
"Unit";"Zergling";"Larva";194;1
"Unit";"Zergling";"Larva";194;1
"Unit";"Zergling";"Larva";194;1
"Unit";"Zergling";"Larva";194;1
"Unit";"Zergling";"Larva";194;1
"Unit";"Zergling";"Larva";194;1
"Unit";"Hydralisk";"Larva";182;2
"Unit";"Hydralisk";"Larva";182;2
"Unit";"Hydralisk";"Larva";182;2
"Unit";"Hydralisk";"Larva";182;2
"Unit";"Hydralisk";"Larva";194;2
"Unit";"Baneling";"Zergling";198;0
"Unit";"Baneling";"Zergling";198;0
"Unit";"Baneling";"Zergling";200;0
"Unit";"Baneling";"Zergling";200;0
"Unit";"Baneling";"Zergling";200;0
"Building";"SporeCrawler";NA;196;0
"Building";"SporeCrawler";NA;196;0
"Unit";"Hydralisk";"Larva";202;2
"Unit";"Hydralisk";"Larva";202;2
"Unit";"Hydralisk";"Larva";218;2
"Unit";"Hydralisk";"Larva";218;2
"Unit";"Hydralisk";"Larva";218;2
"Unit";"Zergling";"Larva";218;1
"Unit";"Zergling";"Larva";218;1
"Unit";"Hydralisk";"Larva";218;2
"Unit";"Hydralisk";"Larva";218;2
"Unit";"Hydralisk";"Larva";218;2
"Unit";"Hydralisk";"Larva";218;2
"Upgrade";"ZergMissileWeaponsLevel2";"EvolutionChamber";167;0
"Unit";"Hydralisk";"Larva";222;2
"Upgrade";"ZergGroundArmorsLevel2";"EvolutionChamber";167;0
"Unit";"Hydralisk";"Larva";222;2
"Unit";"Hydralisk";"Larva";228;2
"Unit";"Hydralisk";"Larva";236;2
