"type";"unit_name";"on_building";"total_supply";"supply"
"Unit";"Overlord";"Larva";13;0
"Building";"Extractor";NA;18;0
"Unit";"Overlord";"Larva";22;0
"Building";"Hatchery";NA;18;0
"Building";"SpawningPool";NA;20;0
"Unit";"Zergling";"Larva";23;1
"Unit";"Zergling";"Larva";23;1
"Unit";"Zergling";"Larva";23;1
"Unit";"Zergling";"Larva";23;1
"Unit";"Zergling";"Larva";23;1
"Unit";"Zergling";"Larva";23;1
"Unit";"Queen";"Hatchery";23;2
"Unit";"Queen";"Hatchery";23;2
"Building";"EvolutionChamber";NA;37;0
"Unit";"Overlord";"Larva";40;0
"Unit";"Queen";"Hatchery";37;2
"Building";"BanelingNest";NA;39;0
"Unit";"Zergling";"Larva";42;1
"Unit";"Zergling";"Larva";42;1
"Unit";"Zergling";"Larva";42;1
"Unit";"Zergling";"Larva";42;1
"Unit";"Zergling";"Larva";42;1
"Unit";"Zergling";"Larva";42;1
"Unit";"Zergling";"Larva";42;1
"Unit";"Zergling";"Larva";42;1
"Unit";"Zergling";"Larva";42;1
"Unit";"Zergling";"Larva";42;1
"Unit";"Zergling";"Larva";42;1
"Unit";"Zergling";"Larva";42;1
"Unit";"Zergling";"Larva";42;1
"Unit";"Zergling";"Larva";42;1
"Unit";"Zergling";"Larva";42;1
"Unit";"Zergling";"Larva";42;1
"Building";"CreepTumorQueen";NA;44;0
"Unit";"Overlord";"Larva";61;0
"Building";"CreepTumor";NA;63;0
"Building";"CreepTumorQueen";NA;63;0
"Unit";"Zergling";"Larva";63;1
"Unit";"Zergling";"Larva";63;1
"Unit";"Zergling";"Larva";63;1
"Unit";"Zergling";"Larva";63;1
"Unit";"Zergling";"Larva";63;1
"Unit";"Zergling";"Larva";63;1
"Unit";"Zergling";"Larva";63;1
"Unit";"Zergling";"Larva";63;1
"Unit";"Zergling";"Larva";63;1
"Unit";"Zergling";"Larva";63;1
"Unit";"Baneling";"Zergling";73;0
"Unit";"Baneling";"Zergling";73;0
"Unit";"Baneling";"Zergling";73;0
"Unit";"Baneling";"Zergling";73;0
"Unit";"Baneling";"Zergling";73;0
"Building";"CreepTumor";NA;73;0
"Building";"CreepTumor";NA;73;0
"Unit";"Overlord";"Larva";73;0
"Unit";"Overlord";"Larva";73;0
"Building";"CreepTumorQueen";NA;73;0
"Unit";"Zergling";"Larva";79;1
"Unit";"Zergling";"Larva";79;1
"Building";"Extractor";NA;79;0
"Building";"Hatchery";NA;63;0
"Building";"EvolutionChamber";NA;79;0
"Upgrade";"ZergMeleeWeaponsLevel1";"EvolutionChamber";63;0
"Unit";"Zergling";"Larva";81;1
"Unit";"Zergling";"Larva";81;1
"Unit";"Zergling";"Larva";81;1
"Unit";"Zergling";"Larva";81;1
"Unit";"Zergling";"Larva";81;1
"Unit";"Zergling";"Larva";81;1
"Unit";"Zergling";"Larva";81;1
"Unit";"Zergling";"Larva";81;1
"Unit";"Zergling";"Larva";81;1
"Unit";"Zergling";"Larva";81;1
"Unit";"Zergling";"Larva";81;1
"Unit";"Zergling";"Larva";81;1
"Unit";"Zergling";"Larva";81;1
"Unit";"Zergling";"Larva";81;1
"Unit";"Zergling";"Larva";81;1
"Unit";"Zergling";"Larva";81;1
"Unit";"Zergling";"Larva";81;1
"Unit";"Zergling";"Larva";81;1
"Building";"CreepTumorQueen";NA;81;0
"Unit";"Zergling";"Larva";81;1
"Unit";"Zergling";"Larva";81;1
"Unit";"Zergling";"Larva";81;1
"Unit";"Zergling";"Larva";81;1
"Unit";"Zergling";"Larva";81;1
"Unit";"Zergling";"Larva";81;1
"Unit";"Zergling";"Larva";81;1
"Unit";"Zergling";"Larva";81;1
"Building";"CreepTumor";NA;81;0
"Building";"CreepTumor";NA;81;0
"Building";"CreepTumor";NA;81;0
"Building";"CreepTumorQueen";NA;113;0
"Building";"CreepTumor";NA;113;0
"Unit";"Zergling";"Larva";113;1
"Unit";"Zergling";"Larva";113;1
"Unit";"Zergling";"Larva";113;1
"Unit";"Zergling";"Larva";113;1
"Unit";"Zergling";"Larva";113;1
"Unit";"Zergling";"Larva";113;1
"Unit";"Zergling";"Larva";113;1
"Unit";"Zergling";"Larva";113;1
"Unit";"Zergling";"Larva";113;1
"Unit";"Zergling";"Larva";113;1
"Unit";"Zergling";"Larva";113;1
"Unit";"Zergling";"Larva";113;1
"Unit";"Zergling";"Larva";113;1
"Unit";"Zergling";"Larva";113;1
"Unit";"Zergling";"Larva";113;1
"Unit";"Zergling";"Larva";113;1
"Unit";"Zergling";"Larva";113;1
"Unit";"Zergling";"Larva";113;1
"Unit";"Zergling";"Larva";113;1
"Unit";"Zergling";"Larva";113;1
"Unit";"Zergling";"Larva";113;1
"Unit";"Zergling";"Larva";113;1
"Unit";"Zergling";"Larva";113;1
"Unit";"Zergling";"Larva";113;1
"Unit";"Zergling";"Larva";113;1
"Unit";"Zergling";"Larva";113;1
"Unit";"Zergling";"Larva";113;1
"Unit";"Zergling";"Larva";113;1
"Unit";"Zergling";"Larva";113;1
"Unit";"Zergling";"Larva";113;1
"Unit";"Zergling";"Larva";113;1
"Unit";"Zergling";"Larva";113;1
"Unit";"Zergling";"Larva";133;1
"Unit";"Zergling";"Larva";133;1
"Unit";"Zergling";"Larva";133;1
"Unit";"Zergling";"Larva";133;1
"Unit";"Zergling";"Larva";133;1
"Unit";"Zergling";"Larva";133;1
"Unit";"Zergling";"Larva";133;1
"Unit";"Zergling";"Larva";133;1
"Building";"CreepTumorQueen";NA;145;0
"Building";"Hatchery";NA;110;0
"Building";"CreepTumor";NA;145;0
"Building";"CreepTumor";NA;145;0
"Building";"CreepTumor";NA;145;0
"Building";"CreepTumor";NA;145;0
"Building";"CreepTumor";NA;145;0
"Building";"Extractor";NA;145;0
"Building";"Extractor";NA;145;0
"Building";"HydraliskDen";NA;145;0
"Upgrade";"ZergGroundArmorsLevel1";"EvolutionChamber";113;0
"Unit";"Queen";"Hatchery";145;2
"Unit";"Zergling";"Larva";168;1
"Unit";"Zergling";"Larva";168;1
"Unit";"Zergling";"Larva";168;1
"Unit";"Zergling";"Larva";168;1
"Unit";"Zergling";"Larva";168;1
"Unit";"Zergling";"Larva";168;1
"Unit";"Zergling";"Larva";168;1
"Unit";"Zergling";"Larva";168;1
"Unit";"Zergling";"Larva";168;1
"Unit";"Zergling";"Larva";168;1
"Unit";"Zergling";"Larva";168;1
"Unit";"Zergling";"Larva";168;1
"Unit";"Zergling";"Larva";168;1
"Unit";"Zergling";"Larva";168;1
"Unit";"Zergling";"Larva";168;1
"Unit";"Zergling";"Larva";168;1
"Unit";"Zergling";"Larva";168;1
"Unit";"Zergling";"Larva";168;1
"Unit";"Zergling";"Larva";168;1
"Unit";"Zergling";"Larva";168;1
"Unit";"Zergling";"Larva";168;1
"Unit";"Zergling";"Larva";168;1
"Building";"Spire";NA;145;0
"Unit";"Overlord";"Larva";168;0
"Building";"Extractor";NA;191;0
"Building";"Extractor";NA;191;0
"Unit";"Overlord";"Larva";201;0
"Unit";"Overlord";"Larva";201;0
"Unit";"Overlord";"Larva";201;0
"Unit";"Overlord";"Larva";201;0
"Building";"CreepTumor";NA;204;0
"Building";"CreepTumor";NA;204;0
"Unit";"Mutalisk";"Larva";204;2
"Unit";"Overlord";"Larva";204;0
"Unit";"Overlord";"Larva";204;0
"Unit";"Overlord";"Larva";204;0
"Unit";"Overlord";"Larva";204;0
"Building";"CreepTumor";NA;204;0
"Building";"LurkerDenMP";NA;168;0
"Unit";"Mutalisk";"Larva";204;2
"Unit";"Mutalisk";"Larva";204;2
"Unit";"Mutalisk";"Larva";204;2
"Unit";"Mutalisk";"Larva";204;2
"Unit";"Mutalisk";"Larva";204;2
"Unit";"Hydralisk";"Larva";206;2
"Unit";"Hydralisk";"Larva";206;2
"Unit";"Hydralisk";"Larva";206;2
"Unit";"Hydralisk";"Larva";206;2
"Unit";"Hydralisk";"Larva";206;2
"Unit";"Hydralisk";"Larva";206;2
"Unit";"Zergling";"Larva";216;1
"Unit";"Zergling";"Larva";216;1
"Unit";"Zergling";"Larva";216;1
"Unit";"Zergling";"Larva";216;1
"Unit";"Zergling";"Larva";216;1
"Unit";"Zergling";"Larva";216;1
"Unit";"Zergling";"Larva";216;1
"Unit";"Zergling";"Larva";216;1
"Unit";"Zergling";"Larva";216;1
"Unit";"Zergling";"Larva";216;1
"Unit";"Zergling";"Larva";216;1
"Unit";"Zergling";"Larva";216;1
"Unit";"Zergling";"Larva";216;1
"Unit";"Zergling";"Larva";216;1
"Unit";"Zergling";"Larva";216;1
"Unit";"Zergling";"Larva";216;1
"Building";"SpineCrawler";NA;216;0
"Building";"SpineCrawler";NA;216;0
"Upgrade";"ZergMeleeWeaponsLevel2";"EvolutionChamber";191;0
"Upgrade";"ZergGroundArmorsLevel2";"EvolutionChamber";191;0
"Building";"CreepTumor";NA;244;0
"Building";"CreepTumor";NA;244;0
"Building";"Hatchery";NA;228;0
"Building";"SpineCrawler";NA;258;0
"Building";"Extractor";NA;260;0
"Building";"Extractor";NA;260;0
"Building";"CreepTumor";NA;260;0
"Building";"CreepTumor";NA;260;0
"Building";"SpineCrawler";NA;258;0
"Building";"CreepTumor";NA;260;0
"Building";"SpineCrawler";NA;258;0
"Unit";"Hydralisk";"Larva";260;2
"Unit";"Hydralisk";"Larva";260;2
"Unit";"Hydralisk";"Larva";260;2
"Unit";"Hydralisk";"Larva";260;2
"Building";"CreepTumor";NA;260;0
"Building";"CreepTumor";NA;260;0
"Building";"InfestationPit";NA;260;0
"Unit";"Overlord";"Larva";260;0
"Unit";"Overlord";"Larva";260;0
"Unit";"Overlord";"Larva";260;0
"Unit";"Zergling";"Larva";268;1
"Unit";"Zergling";"Larva";268;1
"Unit";"Zergling";"Larva";268;1
"Unit";"Zergling";"Larva";268;1
"Unit";"Zergling";"Larva";268;1
"Unit";"Zergling";"Larva";268;1
"Unit";"Zergling";"Larva";268;1
"Unit";"Zergling";"Larva";268;1
"Unit";"Zergling";"Larva";268;1
"Unit";"Zergling";"Larva";268;1
"Unit";"Zergling";"Larva";268;1
"Unit";"Zergling";"Larva";268;1
"Building";"SporeCrawler";NA;293;0
"Building";"Hatchery";NA;268;0
"Building";"SpineCrawler";NA;293;0
"Upgrade";"Burrow";"Hatchery";281;0
"Building";"SpineCrawler";NA;293;0
"Unit";"Overlord";"Larva";293;0
"Unit";"Overlord";"Larva";293;0
"Unit";"Overlord";"Larva";293;0
"Unit";"Hydralisk";"Larva";293;2
"Unit";"Hydralisk";"Larva";293;2
"Unit";"Hydralisk";"Larva";293;2
"Unit";"Hydralisk";"Larva";293;2
"Unit";"Hydralisk";"Larva";293;2
"Unit";"Hydralisk";"Larva";293;2
"Unit";"Hydralisk";"Larva";293;2
"Unit";"Hydralisk";"Larva";293;2
"Unit";"Hydralisk";"Larva";293;2
"Unit";"Hydralisk";"Larva";293;2
"Unit";"Hydralisk";"Larva";293;2
"Building";"NydusNetwork";NA;293;0
"Building";"Extractor";NA;317;0
"Building";"Extractor";NA;317;0
"Unit";"Zergling";"Larva";317;1
"Unit";"Zergling";"Larva";317;1
"Unit";"Zergling";"Larva";317;1
"Unit";"Zergling";"Larva";317;1
"Unit";"Zergling";"Larva";317;1
"Unit";"Zergling";"Larva";317;1
"Unit";"Zergling";"Larva";317;1
"Unit";"Zergling";"Larva";317;1
"Unit";"Zergling";"Larva";317;1
"Unit";"Zergling";"Larva";317;1
"Unit";"Zergling";"Larva";317;1
"Unit";"Zergling";"Larva";317;1
"Unit";"Zergling";"Larva";317;1
"Unit";"Zergling";"Larva";317;1
"Unit";"Zergling";"Larva";317;1
"Unit";"Zergling";"Larva";317;1
"Unit";"Zergling";"Larva";317;1
"Unit";"Zergling";"Larva";317;1
"Unit";"Zergling";"Larva";317;1
"Unit";"Zergling";"Larva";317;1
"Unit";"Zergling";"Larva";317;1
"Unit";"Zergling";"Larva";317;1
"Unit";"Zergling";"Larva";317;1
"Unit";"Zergling";"Larva";317;1
"Upgrade";"ZergMissileWeaponsLevel1";"EvolutionChamber";293;0
"Building";"Spire";NA;293;0
"Unit";"Zergling";"Larva";317;1
"Unit";"Zergling";"Larva";317;1
"Unit";"Zergling";"Larva";317;1
"Unit";"Zergling";"Larva";317;1
"Unit";"Zergling";"Larva";317;1
"Unit";"Zergling";"Larva";317;1
"Unit";"Zergling";"Larva";317;1
"Unit";"Zergling";"Larva";317;1
"Unit";"Zergling";"Larva";317;1
"Unit";"Zergling";"Larva";317;1
"Unit";"Zergling";"Larva";317;1
"Unit";"Zergling";"Larva";317;1
"Unit";"Zergling";"Larva";317;1
"Unit";"Zergling";"Larva";317;1
"Unit";"Zergling";"Larva";317;1
"Unit";"Zergling";"Larva";317;1
"Unit";"Zergling";"Larva";317;1
"Unit";"Zergling";"Larva";317;1
"Unit";"Zergling";"Larva";317;1
"Unit";"Zergling";"Larva";317;1
"Unit";"Zergling";"Larva";317;1
"Unit";"Zergling";"Larva";317;1
"Unit";"Zergling";"Larva";317;1
"Unit";"Zergling";"Larva";317;1
"Unit";"Zergling";"Larva";317;1
"Unit";"Zergling";"Larva";317;1
"Unit";"Zergling";"Larva";317;1
"Unit";"Zergling";"Larva";317;1
"Unit";"Zergling";"Larva";317;1
"Unit";"Zergling";"Larva";317;1
"Unit";"Zergling";"Larva";317;1
"Unit";"Zergling";"Larva";317;1
"Building";"SporeCrawler";NA;317;0
"Building";"NydusCanal";NA;341;0
"Building";"SpineCrawler";NA;317;0
"Unit";"Baneling";"Zergling";373;0
"Unit";"Baneling";"Zergling";373;0
"Unit";"Corruptor";"Larva";373;2
"Unit";"Corruptor";"Larva";373;2
"Unit";"Corruptor";"Larva";373;2
"Unit";"Corruptor";"Larva";373;2
"Unit";"Corruptor";"Larva";373;2
"Unit";"Corruptor";"Larva";373;2
"Unit";"Corruptor";"Larva";385;2
"Unit";"Corruptor";"Larva";385;2
"Unit";"Corruptor";"Larva";385;2
"Unit";"Corruptor";"Larva";385;2
"Unit";"Corruptor";"Larva";385;2
"Unit";"Corruptor";"Larva";385;2
"Unit";"Corruptor";"Larva";385;2
"Unit";"Corruptor";"Larva";385;2
"Unit";"Corruptor";"Larva";385;2
"Unit";"Corruptor";"Larva";385;2
"Unit";"Hydralisk";"Larva";385;2
"Unit";"Hydralisk";"Larva";385;2
"Unit";"Hydralisk";"Larva";385;2
"Unit";"Hydralisk";"Larva";385;2
"Unit";"Hydralisk";"Larva";385;2
"Unit";"Hydralisk";"Larva";385;2
"Unit";"Hydralisk";"Larva";385;2
"Unit";"Hydralisk";"Larva";385;2
"Building";"NydusCanal";NA;424;0
"Unit";"Zergling";"Larva";424;1
"Unit";"Zergling";"Larva";424;1
"Unit";"Zergling";"Larva";424;1
"Unit";"Zergling";"Larva";424;1
"Unit";"Zergling";"Larva";424;1
"Unit";"Zergling";"Larva";424;1
"Unit";"Zergling";"Larva";424;1
"Unit";"Zergling";"Larva";424;1
"Unit";"Zergling";"Larva";424;1
"Unit";"Zergling";"Larva";424;1
"Unit";"Zergling";"Larva";424;1
"Unit";"Zergling";"Larva";424;1
"Unit";"Zergling";"Larva";424;1
"Unit";"Zergling";"Larva";424;1
"Unit";"Zergling";"Larva";424;1
"Unit";"Zergling";"Larva";424;1
"Unit";"Zergling";"Larva";424;1
"Unit";"Zergling";"Larva";424;1
"Unit";"Zergling";"Larva";424;1
"Unit";"Zergling";"Larva";424;1
"Unit";"Zergling";"Larva";424;1
"Unit";"Zergling";"Larva";424;1
"Unit";"Zergling";"Larva";424;1
"Unit";"Zergling";"Larva";424;1
"Unit";"Zergling";"Larva";424;1
"Unit";"Zergling";"Larva";424;1
"Unit";"Zergling";"Larva";424;1
"Unit";"Zergling";"Larva";424;1
"Unit";"Zergling";"Larva";424;1
"Unit";"Zergling";"Larva";424;1
"Unit";"Zergling";"Larva";424;1
"Unit";"Zergling";"Larva";424;1
"Unit";"Zergling";"Larva";424;1
"Unit";"Zergling";"Larva";424;1
"Unit";"Zergling";"Larva";424;1
"Unit";"Zergling";"Larva";424;1
"Unit";"Zergling";"Larva";424;1
"Unit";"Zergling";"Larva";424;1
"Unit";"Zergling";"Larva";424;1
"Unit";"Zergling";"Larva";424;1
"Unit";"Zergling";"Larva";424;1
"Unit";"Zergling";"Larva";424;1
"Unit";"Zergling";"Larva";424;1
"Unit";"Zergling";"Larva";424;1
"Building";"Hatchery";NA;385;0
"Building";"Hatchery";NA;388;0
"Building";"Extractor";NA;468;0
"Building";"Extractor";NA;468;0
"Unit";"Baneling";"Zergling";486;0
"Unit";"Baneling";"Zergling";486;0
"Unit";"Baneling";"Zergling";486;0
"Unit";"Baneling";"Zergling";486;0
"Unit";"Baneling";"Zergling";486;0
"Unit";"Queen";"Hatchery";468;2
