"type";"unit_name";"on_building";"total_supply_lag";"supply"
"Unit";"Overlord";"Larva";13;0
"Building";"Hatchery";NA;16;0
"Building";"SpawningPool";NA;18;0
"Building";"Extractor";NA;19;0
"Unit";"Overlord";"Larva";21;0
"Unit";"Queen";"Hatchery";22;2
"Unit";"Zergling";"Larva";24;1
"Unit";"Zergling";"Larva";25;1
"Unit";"Queen";"Hatchery";26;2
"Unit";"Queen";"Hatchery";36;2
"Unit";"Overlord";"Larva";38;0
"Building";"BanelingNest";NA;39;0
"Building";"CreepTumorQueen";NA;43;0
"Unit";"Zergling";"Larva";43;1
"Unit";"Zergling";"Larva";44;1
"Unit";"Zergling";"Larva";45;1
"Unit";"Zergling";"Larva";46;1
"Unit";"Overlord";"Larva";51;0
"Building";"Hatchery";NA;52;0
"Building";"CreepTumor";NA;52;0
"Unit";"Baneling";"Zergling";53;0
"Building";"EvolutionChamber";NA;59;0
"Building";"CreepTumorQueen";NA;60;0
"Unit";"Overlord";"Larva";62;0
"Building";"Extractor";NA;62;0
"Building";"Extractor";NA;62;0
"Unit";"Baneling";"Zergling";62;0
"Unit";"Zergling";"Larva";62;1
"Unit";"Zergling";"Larva";63;1
"Unit";"Overlord";"Larva";64;0
"Unit";"Zergling";"Larva";64;1
"Unit";"Zergling";"Larva";65;1
"Building";"RoachWarren";NA;68;0
"Unit";"Zergling";"Larva";68;1
"Unit";"Zergling";"Larva";69;1
"Building";"CreepTumor";NA;70;0
"Building";"CreepTumor";NA;70;0
"Unit";"Baneling";"Zergling";71;0
"Unit";"Zergling";"Larva";71;1
"Unit";"Zergling";"Larva";72;1
"Unit";"Baneling";"Zergling";75;0
"Unit";"Baneling";"Zergling";75;0
"Unit";"Zergling";"Larva";76;1
"Unit";"Zergling";"Larva";77;1
"Unit";"Roach";"Larva";87;2
"Unit";"Roach";"Larva";89;2
"Unit";"Roach";"Larva";93;2
"Unit";"Roach";"Larva";95;2
"Unit";"Roach";"Larva";97;2
"Unit";"Overlord";"Larva";99;0
"Building";"Extractor";NA;99;0
"Unit";"Overlord";"Larva";99;0
"Unit";"Overlord";"Larva";99;0
"Unit";"Overlord";"Larva";99;0
"Upgrade";"GlialReconstitution";"RoachWarren";99;0
"Unit";"Overlord";"Larva";99;0
"Unit";"Roach";"Larva";100;2
"Unit";"Roach";"Larva";102;2
"Unit";"Roach";"Larva";104;2
"Unit";"Roach";"Larva";106;2
"Unit";"Roach";"Larva";108;2
"Unit";"Roach";"Larva";110;2
"Unit";"Roach";"Larva";112;2
"Unit";"Roach";"Larva";114;2
"Unit";"Roach";"Larva";116;2
"Unit";"Roach";"Larva";118;2
"Unit";"Roach";"Larva";120;2
"Unit";"Roach";"Larva";122;2
"Unit";"Roach";"Larva";124;2
"Unit";"Roach";"Larva";126;2
"Unit";"Roach";"Larva";128;2
"Unit";"Roach";"Larva";130;2
"Unit";"Roach";"Larva";132;2
"Unit";"Roach";"Larva";134;2
"Unit";"Roach";"Larva";136;2
"Unit";"Roach";"Larva";138;2
"Unit";"Roach";"Larva";140;2
"Unit";"Roach";"Larva";143;2
"Unit";"Roach";"Larva";146;2
"Unit";"Roach";"Larva";162;2
"Unit";"Roach";"Larva";165;2
"Unit";"Roach";"Larva";167;2
"Unit";"Roach";"Larva";169;2
"Unit";"Roach";"Larva";171;2
"Unit";"Overlord";"Larva";174;0
"Unit";"Overlord";"Larva";174;0
"Unit";"Roach";"Larva";174;2
"Unit";"Roach";"Larva";176;2
"Unit";"Overlord";"Larva";178;0
"Unit";"Overlord";"Larva";178;0
"Unit";"Overlord";"Larva";178;0
"Building";"EvolutionChamber";NA;178;0
"Unit";"Overlord";"Larva";178;0
"Unit";"Roach";"Larva";178;2
"Unit";"Roach";"Larva";183;2
"Unit";"Roach";"Larva";185;2
"Unit";"Roach";"Larva";187;2
"Building";"HydraliskDen";NA;190;0
"Unit";"Roach";"Larva";190;2
"Unit";"Roach";"Larva";192;2
"Unit";"Roach";"Larva";194;2
"Unit";"Roach";"Larva";196;2
"Building";"Extractor";NA;198;0
"Unit";"Roach";"Larva";198;2
"Unit";"Roach";"Larva";202;2
"Unit";"Roach";"Larva";204;2
"Unit";"Roach";"Larva";206;2
"Unit";"Roach";"Larva";208;2
"Unit";"Roach";"Larva";210;2
"Unit";"Overlord";"Larva";212;0
"Building";"Extractor";NA;213;0
"Building";"LurkerDenMP";NA;214;0
"Unit";"Queen";"Hatchery";214;2
"Unit";"Hydralisk";"Larva";220;2
"Unit";"Hydralisk";"Larva";222;2
"Unit";"Hydralisk";"Larva";224;2
"Unit";"Hydralisk";"Larva";226;2
"Unit";"Overlord";"Larva";228;0
"Unit";"Hydralisk";"Larva";228;2
"Unit";"Queen";"Hatchery";230;2
"Unit";"Hydralisk";"Larva";232;2
"Unit";"Hydralisk";"Larva";234;2
"Building";"Hatchery";NA;236;0
"Unit";"Queen";"Hatchery";236;2
"Unit";"Overlord";"Larva";238;0
"Unit";"Hydralisk";"Larva";238;2
"Unit";"Roach";"Larva";241;2
"Unit";"Roach";"Larva";243;2
"Unit";"Overlord";"Larva";245;0
"Unit";"Roach";"Larva";245;2
"Building";"SporeCrawler";NA;247;0
"Unit";"Roach";"Larva";247;2
"Unit";"Roach";"Larva";249;2
"Unit";"Overlord";"Larva";251;0
"Unit";"Overlord";"Larva";251;0
"Unit";"Roach";"Larva";251;2
"Unit";"Roach";"Larva";253;2
"Unit";"Roach";"Larva";255;2
"Unit";"Roach";"Larva";257;2
"Unit";"Roach";"Larva";259;2
"Unit";"Roach";"Larva";261;2
"Unit";"Roach";"Larva";263;2
"Unit";"Roach";"Larva";265;2
"Unit";"Roach";"Larva";267;2
"Unit";"Roach";"Larva";269;2
"Unit";"Roach";"Larva";271;2
"Unit";"Roach";"Larva";273;2
"Unit";"Roach";"Larva";275;2
"Unit";"Roach";"Larva";277;2
"Unit";"Roach";"Larva";279;2
"Unit";"Roach";"Larva";281;2
"Unit";"Roach";"Larva";283;2
"Unit";"Roach";"Larva";290;2
"Unit";"Roach";"Larva";292;2
"Unit";"Roach";"Larva";296;2
"Unit";"Hydralisk";"Larva";298;2
"Unit";"Hydralisk";"Larva";300;2
"Unit";"Roach";"Larva";302;2
"Building";"SporeCrawler";NA;304;0
"Unit";"Overlord";"Larva";304;0
"Unit";"Overlord";"Larva";304;0
"Unit";"Hydralisk";"Larva";304;2
"Unit";"Hydralisk";"Larva";306;2
"Unit";"Hydralisk";"Larva";308;2
"Unit";"Roach";"Larva";310;2
"Unit";"Roach";"Larva";312;2
"Building";"EvolutionChamber";NA;314;0
"Building";"EvolutionChamber";NA;314;0
"Unit";"Roach";"Larva";317;2
"Unit";"Roach";"Larva";319;2
"Unit";"Roach";"Larva";321;2
"Unit";"Roach";"Larva";324;2
"Unit";"Roach";"Larva";326;2
"Unit";"Roach";"Larva";328;2
"Unit";"Roach";"Larva";330;2
"Unit";"Roach";"Larva";332;2
"Unit";"Roach";"Larva";334;2
"Unit";"Roach";"Larva";336;2
"Building";"Hatchery";NA;338;0
"Building";"InfestationPit";NA;338;0
"Unit";"Overlord";"Larva";338;0
"Unit";"Roach";"Larva";338;2
"Unit";"Roach";"Larva";340;2
"Unit";"Roach";"Larva";342;2
"Unit";"Roach";"Larva";344;2
"Unit";"Roach";"Larva";346;2
"Unit";"Hydralisk";"Larva";348;2
"Unit";"Hydralisk";"Larva";366;2
"Unit";"Overlord";"Larva";368;0
"Unit";"Overlord";"Larva";368;0
"Unit";"Overlord";"Larva";368;0
"Building";"Spire";NA;368;0
"Unit";"Overlord";"Larva";368;0
"Unit";"Overlord";"Larva";368;0
"Building";"SporeCrawler";NA;368;0
"Building";"SporeCrawler";NA;368;0
"Unit";"Overlord";"Larva";368;0
"Building";"SporeCrawler";NA;369;0
"Unit";"Overlord";"Larva";371;0
"Unit";"Overlord";"Larva";371;0
"Unit";"Overlord";"Larva";371;0
"Unit";"Roach";"Larva";371;2
"Unit";"Roach";"Larva";373;2
"Building";"Extractor";NA;375;0
"Building";"Extractor";NA;375;0
"Building";"SpineCrawler";NA;375;0
"Unit";"Viper";"Larva";375;3
"Unit";"Viper";"Larva";378;3
"Unit";"Viper";"Larva";381;3
"Building";"SpineCrawler";NA;384;0
"Unit";"Corruptor";"Larva";384;2
"Unit";"Corruptor";"Larva";386;2
"Unit";"Overlord";"Larva";388;0
"Unit";"Overlord";"Larva";388;0
"Unit";"Hydralisk";"Larva";392;2
"Unit";"Hydralisk";"Larva";394;2
"Unit";"Hydralisk";"Larva";396;2
"Unit";"Hydralisk";"Larva";398;2
"Unit";"Hydralisk";"Larva";400;2
"Unit";"Hydralisk";"Larva";402;2
"Unit";"Hydralisk";"Larva";404;2
"Unit";"Hydralisk";"Larva";406;2
"Unit";"Hydralisk";"Larva";408;2
"Unit";"Hydralisk";"Larva";410;2
"Unit";"Roach";"Larva";412;2
"Unit";"Roach";"Larva";414;2
"Unit";"Roach";"Larva";416;2
"Unit";"Hydralisk";"Larva";418;2
"Unit";"Hydralisk";"Larva";420;2
"Unit";"Hydralisk";"Larva";422;2
"Unit";"Corruptor";"Larva";424;2
"Unit";"Corruptor";"Larva";426;2
"Unit";"Corruptor";"Larva";428;2
"Unit";"Roach";"Larva";430;2
"Unit";"Roach";"Larva";432;2
"Unit";"Roach";"Larva";434;2
"Unit";"Hydralisk";"Larva";436;2
"Unit";"Hydralisk";"Larva";438;2
"Unit";"Roach";"Larva";440;2
"Unit";"Roach";"Larva";442;2
"Unit";"Roach";"Larva";444;2
"Unit";"Roach";"Larva";446;2
"Unit";"Overlord";"Larva";449;0
"Building";"SporeCrawler";NA;449;0
"Unit";"Corruptor";"Larva";449;2
"Unit";"Corruptor";"Larva";451;2
"Unit";"Corruptor";"Larva";453;2
"Unit";"Corruptor";"Larva";455;2
"Unit";"Corruptor";"Larva";457;2
"Unit";"Corruptor";"Larva";459;2
"Unit";"Corruptor";"Larva";461;2
"Unit";"Corruptor";"Larva";463;2
"Unit";"Corruptor";"Larva";465;2
"Unit";"Corruptor";"Larva";467;2
"Unit";"Hydralisk";"Larva";469;2
"Unit";"Hydralisk";"Larva";471;2
"Unit";"Hydralisk";"Larva";473;2
"Unit";"Hydralisk";"Larva";475;2
"Unit";"Hydralisk";"Larva";477;2
"Unit";"Hydralisk";"Larva";479;2
"Unit";"Hydralisk";"Larva";481;2
"Unit";"Hydralisk";"Larva";483;2
"Unit";"Hydralisk";"Larva";485;2
"Unit";"Hydralisk";"Larva";487;2
"Unit";"Hydralisk";"Larva";489;2
"Unit";"Zergling";"Larva";491;1
"Unit";"Zergling";"Larva";492;1
"Unit";"Zergling";"Larva";493;1
"Unit";"Zergling";"Larva";494;1
"Unit";"Zergling";"Larva";495;1
"Unit";"Zergling";"Larva";496;1
"Unit";"Queen";"Hatchery";497;2
"Unit";"Hydralisk";"Larva";499;2
"Unit";"Hydralisk";"Larva";501;2
"Unit";"Hydralisk";"Larva";503;2
"Unit";"Hydralisk";"Larva";505;2
"Unit";"Roach";"Larva";507;2
"Unit";"Roach";"Larva";509;2
"Building";"Hatchery";NA;512;0
"Building";"Hatchery";NA;512;0
"Unit";"Hydralisk";"Larva";512;2
"Unit";"Hydralisk";"Larva";514;2
"Unit";"Hydralisk";"Larva";516;2
"Unit";"Hydralisk";"Larva";518;2
"Unit";"Hydralisk";"Larva";520;2
"Unit";"Hydralisk";"Larva";522;2
"Unit";"Hydralisk";"Larva";524;2
"Unit";"Roach";"Larva";526;2
"Unit";"Hydralisk";"Larva";528;2
"Unit";"Roach";"Larva";530;2
"Unit";"Roach";"Larva";532;2
"Unit";"Overlord";"Larva";534;0
"Unit";"Hydralisk";"Larva";534;2
"Unit";"Hydralisk";"Larva";536;2
"Unit";"Overlord";"Larva";538;0
"Unit";"Hydralisk";"Larva";538;2
"Unit";"Roach";"Larva";540;2
"Unit";"Roach";"Larva";542;2
"Unit";"Roach";"Larva";544;2
"Unit";"Roach";"Larva";546;2
"Unit";"Roach";"Larva";548;2
"Unit";"Roach";"Larva";550;2
"Unit";"Roach";"Larva";552;2
"Unit";"Roach";"Larva";554;2
"Unit";"Roach";"Larva";556;2
"Unit";"Roach";"Larva";558;2
"Unit";"Roach";"Larva";560;2
"Unit";"Roach";"Larva";562;2
"Upgrade";"SprayZerg";NA;564;0
"Upgrade";"SprayZerg";NA;564;0
"Upgrade";"SprayZerg";NA;564;0
"Upgrade";"zerglingmovementspeed";NA;564;0
"Upgrade";"SprayZerg";NA;564;0
"Upgrade";"ZergMissileWeaponsLevel1";NA;564;0
"Upgrade";"overlordspeed";NA;564;0
"Upgrade";"ZergMissileWeaponsLevel2";NA;564;0
"Upgrade";"SprayZerg";NA;564;0
"Upgrade";"SprayZerg";NA;564;0
"Upgrade";"SprayZerg";NA;564;0
"Upgrade";"SprayZerg";NA;564;0
"Upgrade";"ZergGroundArmorsLevel1";NA;564;0
"Upgrade";"SprayZerg";NA;564;0
"Upgrade";"DiggingClaws";NA;564;0
"Upgrade";"ZergGroundArmorsLevel2";NA;564;0
"Upgrade";"ZergMissileWeaponsLevel3";NA;564;0
"Upgrade";"EvolveMuscularAugments";NA;564;0
"Upgrade";"SprayZerg";NA;564;0
"Upgrade";"SprayZerg";NA;564;0
"Upgrade";"ZergGroundArmorsLevel3";NA;564;0
"Upgrade";"SprayZerg";NA;564;0
"Upgrade";"SprayZerg";NA;564;0
