"type";"unit_name";"on_building";"total_supply";"supply"
"Unit";"Overlord";"Larva";12;0
"Building";"Extractor";NA;18;0
"Unit";"Overlord";"Larva";21;0
"Building";"SpawningPool";NA;19;0
"Building";"Hatchery";NA;17;0
"Unit";"Zergling";"Larva";22;1
"Unit";"Zergling";"Larva";22;1
"Unit";"Zergling";"Larva";22;1
"Unit";"Zergling";"Larva";22;1
"Unit";"Zergling";"Larva";22;1
"Unit";"Zergling";"Larva";22;1
"Unit";"Queen";"Hatchery";22;2
"Unit";"Queen";"Hatchery";22;2
"Unit";"Overlord";"Larva";31;0
"Unit";"Zergling";"Larva";35;1
"Unit";"Zergling";"Larva";35;1
"Unit";"Zergling";"Larva";35;1
"Unit";"Zergling";"Larva";35;1
"Unit";"Queen";"Hatchery";33;2
"Building";"BanelingNest";NA;33;0
"Unit";"Overlord";"Larva";41;0
"Building";"CreepTumorQueen";NA;43;0
"Unit";"Overlord";"Larva";45;0
"Unit";"Zergling";"Larva";45;1
"Unit";"Zergling";"Larva";45;1
"Unit";"Zergling";"Larva";45;1
"Unit";"Zergling";"Larva";45;1
"Unit";"Zergling";"Larva";45;1
"Unit";"Zergling";"Larva";45;1
"Unit";"Zergling";"Larva";45;1
"Unit";"Zergling";"Larva";45;1
"Unit";"Baneling";"Zergling";54;0
"Unit";"Zergling";"Larva";54;1
"Unit";"Zergling";"Larva";54;1
"Unit";"Zergling";"Larva";54;1
"Unit";"Zergling";"Larva";54;1
"Unit";"Zergling";"Larva";54;1
"Unit";"Zergling";"Larva";54;1
"Unit";"Zergling";"Larva";54;1
"Unit";"Zergling";"Larva";54;1
"Unit";"Zergling";"Larva";54;1
"Unit";"Zergling";"Larva";54;1
"Unit";"Zergling";"Larva";54;1
"Unit";"Zergling";"Larva";54;1
"Unit";"Zergling";"Larva";54;1
"Unit";"Zergling";"Larva";54;1
"Unit";"Zergling";"Larva";54;1
"Unit";"Zergling";"Larva";54;1
"Building";"CreepTumorQueen";NA;54;0
"Unit";"Zergling";"Larva";54;1
"Unit";"Zergling";"Larva";54;1
"Unit";"Zergling";"Larva";54;1
"Unit";"Zergling";"Larva";54;1
"Unit";"Baneling";"Zergling";70;0
"Unit";"Baneling";"Zergling";70;0
"Unit";"Zergling";"Larva";77;1
"Unit";"Zergling";"Larva";77;1
"Unit";"Zergling";"Larva";77;1
"Unit";"Zergling";"Larva";77;1
"Unit";"Zergling";"Larva";77;1
"Unit";"Zergling";"Larva";77;1
"Unit";"Zergling";"Larva";77;1
"Unit";"Zergling";"Larva";77;1
"Unit";"Zergling";"Larva";77;1
"Unit";"Zergling";"Larva";77;1
"Unit";"Zergling";"Larva";77;1
"Unit";"Zergling";"Larva";77;1
"Unit";"Zergling";"Larva";77;1
"Unit";"Zergling";"Larva";77;1
"Unit";"Zergling";"Larva";77;1
"Unit";"Zergling";"Larva";77;1
"Building";"CreepTumor";NA;79;0
"Building";"CreepTumor";NA;79;0
"Unit";"Overlord";"Larva";95;0
"Unit";"Zergling";"Larva";95;1
"Unit";"Zergling";"Larva";95;1
"Unit";"Zergling";"Larva";95;1
"Unit";"Zergling";"Larva";95;1
"Unit";"Zergling";"Larva";95;1
"Unit";"Zergling";"Larva";95;1
"Unit";"Baneling";"Zergling";95;0
"Unit";"Baneling";"Zergling";95;0
"Unit";"Zergling";"Larva";95;1
"Unit";"Zergling";"Larva";95;1
"Unit";"Zergling";"Larva";95;1
"Unit";"Zergling";"Larva";95;1
"Unit";"Zergling";"Larva";95;1
"Unit";"Zergling";"Larva";95;1
"Unit";"Zergling";"Larva";95;1
"Unit";"Zergling";"Larva";95;1
"Unit";"Baneling";"Zergling";109;0
"Unit";"Baneling";"Zergling";109;0
"Unit";"Zergling";"Larva";109;1
"Unit";"Zergling";"Larva";109;1
"Unit";"Zergling";"Larva";109;1
"Unit";"Zergling";"Larva";109;1
"Unit";"Zergling";"Larva";109;1
"Unit";"Zergling";"Larva";109;1
"Unit";"Zergling";"Larva";109;1
"Unit";"Zergling";"Larva";109;1
"Unit";"Zergling";"Larva";109;1
"Unit";"Zergling";"Larva";109;1
"Unit";"Zergling";"Larva";109;1
"Unit";"Zergling";"Larva";109;1
"Unit";"Zergling";"Larva";109;1
"Unit";"Zergling";"Larva";109;1
"Unit";"Zergling";"Larva";109;1
"Unit";"Zergling";"Larva";109;1
"Unit";"Zergling";"Larva";109;1
"Unit";"Zergling";"Larva";109;1
"Unit";"Queen";"Hatchery";109;2
"Building";"Hatchery";NA;95;0
"Building";"CreepTumor";NA;122;0
"Unit";"Zergling";"Larva";121;1
"Unit";"Zergling";"Larva";121;1
"Unit";"Zergling";"Larva";121;1
"Unit";"Zergling";"Larva";121;1
"Unit";"Zergling";"Larva";121;1
"Unit";"Zergling";"Larva";121;1
"Unit";"Zergling";"Larva";121;1
"Unit";"Zergling";"Larva";121;1
"Unit";"Baneling";"Zergling";122;0
"Unit";"Queen";"Hatchery";109;2
"Unit";"Baneling";"Zergling";122;0
"Unit";"Baneling";"Zergling";122;0
"Unit";"Baneling";"Zergling";143;0
"Unit";"Baneling";"Zergling";143;0
"Unit";"Baneling";"Zergling";143;0
"Unit";"Queen";"Hatchery";140;2
"Unit";"Zergling";"Larva";143;1
"Unit";"Zergling";"Larva";143;1
"Unit";"Zergling";"Larva";143;1
"Unit";"Zergling";"Larva";143;1
"Unit";"Zergling";"Larva";143;1
"Unit";"Zergling";"Larva";143;1
"Unit";"Zergling";"Larva";143;1
"Unit";"Zergling";"Larva";143;1
"Unit";"Zergling";"Larva";143;1
"Unit";"Zergling";"Larva";143;1
"Unit";"Zergling";"Larva";143;1
"Unit";"Zergling";"Larva";143;1
"Unit";"Zergling";"Larva";143;1
"Unit";"Zergling";"Larva";143;1
"Unit";"Zergling";"Larva";143;1
"Unit";"Zergling";"Larva";143;1
"Unit";"Queen";"Hatchery";143;2
"Unit";"Zergling";"Larva";161;1
"Unit";"Zergling";"Larva";161;1
"Unit";"Zergling";"Larva";161;1
"Unit";"Zergling";"Larva";161;1
"Unit";"Zergling";"Larva";161;1
"Unit";"Zergling";"Larva";161;1
"Unit";"Zergling";"Larva";161;1
"Unit";"Zergling";"Larva";161;1
"Unit";"Zergling";"Larva";161;1
"Unit";"Zergling";"Larva";161;1
"Unit";"Zergling";"Larva";161;1
"Unit";"Zergling";"Larva";161;1
"Unit";"Zergling";"Larva";161;1
"Unit";"Zergling";"Larva";161;1
"Unit";"Baneling";"Zergling";161;0
"Unit";"Baneling";"Zergling";161;0
"Unit";"Baneling";"Zergling";161;0
"Unit";"Baneling";"Zergling";161;0
"Unit";"Baneling";"Zergling";177;0
"Unit";"Baneling";"Zergling";177;0
"Unit";"Baneling";"Zergling";177;0
"Unit";"Zergling";"Larva";177;1
"Unit";"Zergling";"Larva";177;1
"Unit";"Zergling";"Larva";177;1
"Unit";"Zergling";"Larva";177;1
"Unit";"Zergling";"Larva";177;1
"Unit";"Zergling";"Larva";177;1
"Unit";"Zergling";"Larva";177;1
"Unit";"Zergling";"Larva";177;1
"Unit";"Zergling";"Larva";177;1
"Unit";"Zergling";"Larva";177;1
"Unit";"Zergling";"Larva";177;1
"Unit";"Zergling";"Larva";177;1
"Unit";"Baneling";"Zergling";190;0
"Unit";"Baneling";"Zergling";190;0
"Unit";"Baneling";"Zergling";190;0
"Unit";"Baneling";"Zergling";190;0
"Unit";"Baneling";"Zergling";190;0
"Unit";"Baneling";"Zergling";190;0
"Unit";"Baneling";"Zergling";190;0
"Unit";"Baneling";"Zergling";190;0
"Unit";"Zergling";"Larva";190;1
"Unit";"Zergling";"Larva";190;1
"Unit";"Zergling";"Larva";190;1
"Unit";"Zergling";"Larva";190;1
"Unit";"Zergling";"Larva";190;1
"Unit";"Zergling";"Larva";190;1
"Unit";"Zergling";"Larva";190;1
"Unit";"Zergling";"Larva";190;1
"Unit";"Baneling";"Zergling";194;0
"Unit";"Baneling";"Zergling";194;0
"Unit";"Baneling";"Zergling";194;0
"Building";"CreepTumorQueen";NA;229;0
"Unit";"Zergling";"Larva";225;1
"Unit";"Zergling";"Larva";225;1
"Unit";"Zergling";"Larva";225;1
"Unit";"Zergling";"Larva";225;1
"Building";"Extractor";NA;225;0
"Building";"Extractor";NA;225;0
"Building";"EvolutionChamber";NA;225;0
"Unit";"Zergling";"Larva";231;1
"Unit";"Zergling";"Larva";231;1
"Unit";"Zergling";"Larva";231;1
"Unit";"Zergling";"Larva";231;1
"Unit";"Zergling";"Larva";231;1
"Unit";"Zergling";"Larva";231;1
"Unit";"Zergling";"Larva";231;1
"Unit";"Zergling";"Larva";231;1
"Unit";"Zergling";"Larva";231;1
"Unit";"Zergling";"Larva";231;1
"Building";"RoachWarren";NA;225;0
"Unit";"Zergling";"Larva";243;1
"Unit";"Zergling";"Larva";243;1
"Unit";"Baneling";"Zergling";243;0
"Unit";"Overlord";"Larva";243;0
"Unit";"Overlord";"Larva";243;0
"Unit";"Baneling";"Zergling";245;0
"Unit";"Baneling";"Zergling";245;0
"Unit";"Baneling";"Zergling";245;0
"Unit";"Zergling";"Larva";247;1
"Unit";"Zergling";"Larva";247;1
"Unit";"Zergling";"Larva";247;1
"Unit";"Zergling";"Larva";247;1
"Unit";"Zergling";"Larva";247;1
"Unit";"Zergling";"Larva";247;1
"Unit";"Zergling";"Larva";247;1
"Unit";"Zergling";"Larva";247;1
"Unit";"Zergling";"Larva";247;1
"Unit";"Zergling";"Larva";247;1
"Unit";"Zergling";"Larva";247;1
"Unit";"Zergling";"Larva";247;1
"Unit";"Zergling";"Larva";247;1
"Unit";"Zergling";"Larva";247;1
"Unit";"Zergling";"Larva";247;1
"Unit";"Zergling";"Larva";247;1
"Unit";"Zergling";"Larva";247;1
"Unit";"Zergling";"Larva";247;1
"Unit";"Zergling";"Larva";247;1
"Unit";"Zergling";"Larva";247;1
"Unit";"Zergling";"Larva";247;1
"Unit";"Zergling";"Larva";247;1
"Building";"Extractor";NA;247;0
"Building";"CreepTumorQueen";NA;271;0
"Unit";"Baneling";"Zergling";271;0
"Unit";"Baneling";"Zergling";271;0
"Unit";"Queen";"Hatchery";247;2
"Unit";"Roach";"Larva";275;2
"Unit";"Roach";"Larva";275;2
"Unit";"Roach";"Larva";275;2
"Unit";"Roach";"Larva";275;2
"Unit";"Baneling";"Zergling";280;0
"Unit";"Baneling";"Zergling";280;0
"Unit";"Zergling";"Larva";280;1
"Unit";"Zergling";"Larva";280;1
"Unit";"Zergling";"Larva";280;1
"Unit";"Zergling";"Larva";280;1
"Unit";"Zergling";"Larva";280;1
"Unit";"Zergling";"Larva";280;1
"Unit";"Zergling";"Larva";280;1
"Unit";"Zergling";"Larva";280;1
"Unit";"Zergling";"Larva";280;1
"Unit";"Zergling";"Larva";280;1
"Unit";"Zergling";"Larva";280;1
"Unit";"Zergling";"Larva";280;1
"Unit";"Zergling";"Larva";280;1
"Unit";"Zergling";"Larva";280;1
"Unit";"Zergling";"Larva";280;1
"Unit";"Zergling";"Larva";280;1
"Unit";"Zergling";"Larva";280;1
"Unit";"Zergling";"Larva";280;1
"Unit";"Zergling";"Larva";280;1
"Unit";"Zergling";"Larva";280;1
"Unit";"Overlord";"Larva";312;0
"Upgrade";"ZergMissileWeaponsLevel1";"EvolutionChamber";273;0
"Unit";"Roach";"Larva";315;2
"Unit";"Roach";"Larva";315;2
"Unit";"Roach";"Larva";315;2
"Unit";"Overlord";"Larva";315;0
"Unit";"Overlord";"Larva";315;0
"Unit";"Overlord";"Larva";315;0
"Unit";"Overlord";"Larva";315;0
"Building";"Extractor";NA;315;0
"Building";"Extractor";NA;315;0
"Unit";"Roach";"Larva";321;2
"Unit";"Roach";"Larva";321;2
"Unit";"Roach";"Larva";321;2
"Unit";"Roach";"Larva";321;2
"Unit";"Roach";"Larva";321;2
"Unit";"Roach";"Larva";321;2
"Unit";"Roach";"Larva";321;2
"Unit";"Roach";"Larva";321;2
"Building";"CreepTumorQueen";NA;321;0
"Unit";"Overlord";"Larva";321;0
"Building";"CreepTumor";NA;337;0
"Unit";"Overlord";"Larva";321;0
"Unit";"Overlord";"Larva";321;0
"Unit";"Roach";"Larva";337;2
"Unit";"Roach";"Larva";337;2
"Unit";"Roach";"Larva";337;2
"Unit";"Roach";"Larva";338;2
"Unit";"Roach";"Larva";339;2
"Building";"Hatchery";NA;315;0
"Unit";"Roach";"Larva";343;2
"Unit";"Roach";"Larva";343;2
"Unit";"Roach";"Larva";343;2
"Unit";"Roach";"Larva";343;2
"Building";"CreepTumor";NA;353;0
"Unit";"Roach";"Larva";353;2
"Unit";"Roach";"Larva";353;2
"Unit";"Roach";"Larva";353;2
"Unit";"Roach";"Larva";353;2
"Unit";"Roach";"Larva";353;2
"Unit";"Zergling";"Larva";361;1
"Unit";"Zergling";"Larva";361;1
"Unit";"Overlord";"Larva";372;0
"Unit";"Overlord";"Larva";372;0
"Unit";"Roach";"Larva";372;2
"Unit";"Roach";"Larva";372;2
"Unit";"Roach";"Larva";372;2
"Building";"CreepTumor";NA;379;0
"Unit";"Overlord";"Larva";379;0
"Unit";"Overlord";"Larva";379;0
"Unit";"Roach";"Larva";379;2
"Unit";"Roach";"Larva";391;2
"Unit";"Roach";"Larva";391;2
"Unit";"Roach";"Larva";391;2
"Unit";"Roach";"Larva";391;2
"Unit";"Roach";"Larva";391;2
"Unit";"Roach";"Larva";391;2
"Unit";"Baneling";"Zergling";393;0
"Upgrade";"GlialReconstitution";"RoachWarren";372;0
"Unit";"Roach";"Larva";393;2
"Unit";"Roach";"Larva";393;2
"Unit";"Roach";"Larva";393;2
"Unit";"Roach";"Larva";393;2
"Unit";"Roach";"Larva";393;2
"Unit";"Roach";"Larva";393;2
"Unit";"Roach";"Larva";393;2
"Unit";"Roach";"Larva";393;2
"Unit";"Roach";"Larva";393;2
