"type";"unit_name";"on_building";"total_supply";"supply"
"Unit";"Overlord";"Larva";13;0
"Building";"Extractor";NA;18;0
"Unit";"Overlord";"Larva";21;0
"Building";"SpawningPool";NA;19;0
"Building";"Hatchery";NA;17;0
"Unit";"Queen";"Hatchery";22;2
"Unit";"Queen";"Hatchery";22;2
"Unit";"Zergling";"Larva";26;1
"Unit";"Zergling";"Larva";26;1
"Unit";"Zergling";"Larva";26;1
"Unit";"Zergling";"Larva";26;1
"Building";"CreepTumorQueen";NA;37;0
"Building";"EvolutionChamber";NA;37;0
"Building";"Extractor";NA;37;0
"Building";"Extractor";NA;37;0
"Building";"RoachWarren";NA;37;0
"Building";"EvolutionChamber";NA;41;0
"Unit";"Queen";"Hatchery";37;2
"Unit";"Overlord";"Larva";43;0
"Unit";"Overlord";"Larva";43;0
"Unit";"Overlord";"Larva";44;0
"Unit";"Overlord";"Larva";46;0
"Unit";"Overlord";"Larva";46;0
"Building";"CreepTumor";NA;48;0
"Building";"CreepTumorQueen";NA;49;0
"Unit";"Queen";"Hatchery";46;2
"Unit";"Roach";"Larva";55;2
"Unit";"Roach";"Larva";55;2
"Unit";"Roach";"Larva";55;2
"Unit";"Roach";"Larva";56;2
"Unit";"Roach";"Larva";56;2
"Upgrade";"GlialReconstitution";"RoachWarren";46;0
"Unit";"Overlord";"Larva";56;0
"Unit";"Roach";"Larva";56;2
"Unit";"Roach";"Larva";56;2
"Unit";"Roach";"Larva";62;2
"Unit";"Roach";"Larva";62;2
"Building";"CreepTumor";NA;66;0
"Building";"CreepTumor";NA;66;0
"Unit";"Roach";"Larva";64;2
"Unit";"Roach";"Larva";66;2
"Unit";"Roach";"Larva";68;2
"Unit";"Roach";"Larva";68;2
"Unit";"Overlord";"Larva";68;0
"Unit";"Overlord";"Larva";74;0
"Upgrade";"ZergMissileWeaponsLevel1";"EvolutionChamber";48;0
"Unit";"Roach";"Larva";76;2
"Building";"CreepTumor";NA;82;0
"Building";"CreepTumorQueen";NA;82;0
"Building";"CreepTumor";NA;82;0
"Unit";"Roach";"Larva";82;2
"Unit";"Roach";"Larva";84;2
"Unit";"Roach";"Larva";84;2
"Unit";"Roach";"Larva";84;2
"Unit";"Roach";"Larva";84;2
"Unit";"Roach";"Larva";84;2
"Unit";"Roach";"Larva";84;2
"Upgrade";"ZergGroundArmorsLevel1";"EvolutionChamber";56;0
"Unit";"Overlord";"Larva";84;0
"Unit";"Roach";"Larva";98;2
"Unit";"Roach";"Larva";98;2
"Unit";"Roach";"Larva";98;2
"Unit";"Roach";"Larva";98;2
"Unit";"Roach";"Larva";98;2
"Unit";"Roach";"Larva";98;2
"Unit";"Roach";"Larva";98;2
"Unit";"Roach";"Larva";98;2
"Unit";"Roach";"Larva";98;2
"Unit";"Roach";"Larva";102;2
"Unit";"Roach";"Larva";102;2
"Unit";"Roach";"Larva";108;2
"Unit";"Roach";"Larva";108;2
"Unit";"Roach";"Larva";108;2
"Unit";"Roach";"Larva";108;2
"Unit";"Roach";"Larva";120;2
"Unit";"Roach";"Larva";122;2
"Unit";"Roach";"Larva";122;2
"Unit";"Overlord";"Larva";124;0
"Unit";"Overlord";"Larva";124;0
"Unit";"Roach";"Larva";134;2
"Unit";"Roach";"Larva";134;2
"Unit";"Roach";"Larva";134;2
"Unit";"Roach";"Larva";134;2
"Unit";"Roach";"Larva";134;2
"Unit";"Roach";"Larva";134;2
"Unit";"Roach";"Larva";134;2
"Unit";"Roach";"Larva";134;2
"Unit";"Roach";"Larva";134;2
"Unit";"Roach";"Larva";134;2
"Unit";"Roach";"Larva";142;2
"Unit";"Roach";"Larva";142;2
"Unit";"Roach";"Larva";146;2
"Unit";"Roach";"Larva";146;2
"Unit";"Roach";"Larva";146;2
"Unit";"Roach";"Larva";152;2
"Building";"Hatchery";NA;128;0
"Unit";"Roach";"Larva";158;2
"Unit";"Roach";"Larva";158;2
"Unit";"Roach";"Larva";158;2
"Building";"CreepTumor";NA;166;0
"Unit";"Roach";"Larva";166;2
"Unit";"Roach";"Larva";166;2
"Unit";"Roach";"Larva";166;2
"Building";"CreepTumor";NA;179;0
"Unit";"Roach";"Larva";176;2
"Unit";"Roach";"Larva";177;2
"Unit";"Roach";"Larva";183;2
"Building";"CreepTumor";NA;183;0
"Unit";"Roach";"Larva";189;2
"Unit";"Roach";"Larva";189;2
"Unit";"Overlord";"Larva";189;0
"Unit";"Overlord";"Larva";189;0
"Unit";"Overlord";"Larva";189;0
"Unit";"Overlord";"Larva";189;0
"Building";"SporeCrawler";NA;189;0
"Unit";"Roach";"Larva";189;2
"Unit";"Roach";"Larva";189;2
"Unit";"Roach";"Larva";189;2
"Unit";"Roach";"Larva";189;2
"Unit";"Roach";"Larva";189;2
"Unit";"Roach";"Larva";189;2
"Unit";"Queen";"Hatchery";189;2
"Unit";"Roach";"Larva";193;2
"Unit";"Roach";"Larva";193;2
"Unit";"Roach";"Larva";193;2
"Unit";"Roach";"Larva";193;2
"Building";"CreepTumor";NA;219;0
"Building";"CreepTumor";NA;219;0
"Unit";"Roach";"Larva";219;2
"Unit";"Roach";"Larva";219;2
"Unit";"Roach";"Larva";219;2
"Unit";"Roach";"Larva";219;2
"Unit";"Roach";"Larva";219;2
"Unit";"Roach";"Larva";219;2
"Building";"CreepTumorQueen";NA;219;0
"Building";"CreepTumorQueen";NA;219;0
"Building";"CreepTumor";NA;219;0
"Building";"Extractor";NA;219;0
"Building";"Extractor";NA;219;0
"Unit";"Roach";"Larva";236;2
"Upgrade";"ZergMissileWeaponsLevel2";"EvolutionChamber";189;0
"Building";"Extractor";NA;242;0
"Unit";"Roach";"Larva";244;2
"Unit";"Roach";"Larva";244;2
"Unit";"Roach";"Larva";244;2
"Unit";"Roach";"Larva";244;2
"Building";"CreepTumor";NA;251;0
"Building";"CreepTumor";NA;251;0
"Building";"CreepTumor";NA;251;0
"Building";"CreepTumor";NA;259;0
"Unit";"Overlord";"Larva";259;0
"Unit";"Overlord";"Larva";259;0
"Unit";"Overlord";"Larva";259;0
"Unit";"Roach";"Larva";259;2
"Unit";"Overlord";"Larva";259;0
"Unit";"Roach";"Larva";259;2
"Unit";"Roach";"Larva";259;2
"Unit";"Roach";"Larva";259;2
"Unit";"Roach";"Larva";259;2
"Unit";"Roach";"Larva";259;2
"Unit";"Roach";"Larva";259;2
"Unit";"Roach";"Larva";259;2
"Unit";"Roach";"Larva";273;2
"Unit";"Roach";"Larva";273;2
"Unit";"Roach";"Larva";275;2
"Unit";"Roach";"Larva";275;2
"Unit";"Roach";"Larva";275;2
"Unit";"Roach";"Larva";275;2
"Unit";"Overlord";"Larva";275;0
"Unit";"Overlord";"Larva";275;0
"Unit";"Roach";"Larva";275;2
"Unit";"Roach";"Larva";275;2
"Unit";"Roach";"Larva";275;2
"Building";"Spire";NA;259;0
"Unit";"Mutalisk";"Larva";293;2
"Unit";"Mutalisk";"Larva";293;2
"Unit";"Mutalisk";"Larva";293;2
"Unit";"Mutalisk";"Larva";293;2
"Unit";"Mutalisk";"Larva";293;2
"Building";"Hatchery";NA;279;0
"Unit";"Mutalisk";"Larva";296;2
"Unit";"Mutalisk";"Larva";296;2
"Unit";"Zergling";"Larva";307;1
"Unit";"Zergling";"Larva";307;1
"Unit";"Zergling";"Larva";307;1
"Unit";"Zergling";"Larva";307;1
"Unit";"Zergling";"Larva";307;1
"Unit";"Zergling";"Larva";307;1
"Unit";"Zergling";"Larva";307;1
"Unit";"Zergling";"Larva";307;1
"Unit";"Zergling";"Larva";307;1
"Unit";"Zergling";"Larva";307;1
"Unit";"Zergling";"Larva";307;1
"Unit";"Zergling";"Larva";307;1
"Unit";"Zergling";"Larva";307;1
"Unit";"Zergling";"Larva";307;1
"Unit";"Zergling";"Larva";307;1
"Unit";"Zergling";"Larva";307;1
"Unit";"Zergling";"Larva";307;1
"Unit";"Zergling";"Larva";307;1
"Unit";"Zergling";"Larva";307;1
"Unit";"Zergling";"Larva";307;1
"Unit";"Roach";"Larva";307;2
"Unit";"Roach";"Larva";307;2
"Unit";"Mutalisk";"Larva";307;2
"Unit";"Mutalisk";"Larva";307;2
"Unit";"Mutalisk";"Larva";311;2
"Unit";"Mutalisk";"Larva";311;2
