"type";"unit_name";"on_building";"total_supply";"supply"
"Unit";"Overlord";"Larva";12;0
"Building";"Extractor";NA;18;0
"Building";"Hatchery";NA;17;0
"Building";"SpawningPool";NA;20;0
"Unit";"Overlord";"Larva";23;0
"Unit";"Zergling";"Larva";23;1
"Unit";"Zergling";"Larva";23;1
"Unit";"Zergling";"Larva";23;1
"Unit";"Zergling";"Larva";23;1
"Unit";"Zergling";"Larva";23;1
"Unit";"Zergling";"Larva";23;1
"Unit";"Queen";"Hatchery";23;2
"Unit";"Queen";"Hatchery";23;2
"Unit";"Overlord";"Larva";39;0
"Unit";"Zergling";"Larva";39;1
"Unit";"Zergling";"Larva";39;1
"Unit";"Zergling";"Larva";39;1
"Unit";"Zergling";"Larva";39;1
"Building";"BanelingNest";NA;39;0
"Unit";"Baneling";"Zergling";50;0
"Unit";"Baneling";"Zergling";50;0
"Unit";"Baneling";"Zergling";50;0
"Building";"Hatchery";NA;37;0
"Building";"Extractor";NA;50;0
"Building";"EvolutionChamber";NA;50;0
"Unit";"Overlord";"Larva";54;0
"Unit";"Overlord";"Larva";54;0
"Unit";"Overlord";"Larva";54;0
"Unit";"Zergling";"Larva";57;1
"Unit";"Zergling";"Larva";57;1
"Unit";"Zergling";"Larva";63;1
"Unit";"Zergling";"Larva";63;1
"Unit";"Zergling";"Larva";63;1
"Unit";"Zergling";"Larva";63;1
"Unit";"Zergling";"Larva";63;1
"Unit";"Zergling";"Larva";63;1
"Unit";"Zergling";"Larva";63;1
"Unit";"Zergling";"Larva";63;1
"Unit";"Zergling";"Larva";63;1
"Unit";"Zergling";"Larva";63;1
"Unit";"Zergling";"Larva";63;1
"Unit";"Zergling";"Larva";63;1
"Unit";"Zergling";"Larva";63;1
"Unit";"Zergling";"Larva";63;1
"Unit";"Zergling";"Larva";63;1
"Unit";"Zergling";"Larva";63;1
"Unit";"Queen";"Hatchery";57;2
"Unit";"Queen";"Hatchery";57;2
"Building";"RoachWarren";NA;73;0
"Building";"Extractor";NA;85;0
"Unit";"Zergling";"Larva";96;1
"Unit";"Zergling";"Larva";96;1
"Unit";"Zergling";"Larva";96;1
"Unit";"Zergling";"Larva";96;1
"Unit";"Zergling";"Larva";96;1
"Unit";"Zergling";"Larva";96;1
"Unit";"Zergling";"Larva";96;1
"Unit";"Zergling";"Larva";96;1
"Unit";"Zergling";"Larva";96;1
"Unit";"Zergling";"Larva";96;1
"Building";"CreepTumorQueen";NA;96;0
"Unit";"Roach";"Larva";106;2
"Unit";"Roach";"Larva";106;2
"Unit";"Overlord";"Larva";106;0
"Unit";"Overlord";"Larva";106;0
"Unit";"Overlord";"Larva";106;0
"Unit";"Queen";"Hatchery";96;2
"Upgrade";"ZergMissileWeaponsLevel1";"EvolutionChamber";73;0
"Unit";"Overlord";"Larva";110;0
"Building";"CreepTumorQueen";NA;114;0
"Building";"CreepTumor";NA;114;0
"Unit";"Roach";"Larva";115;2
"Unit";"Roach";"Larva";115;2
"Building";"Extractor";NA;121;0
"Unit";"Roach";"Larva";125;2
"Unit";"Roach";"Larva";125;2
"Unit";"Roach";"Larva";125;2
"Unit";"Roach";"Larva";125;2
"Building";"Extractor";NA;125;0
"Building";"CreepTumor";NA;129;0
"Unit";"Roach";"Larva";129;2
"Unit";"Roach";"Larva";129;2
"Building";"CreepTumor";NA;135;0
"Building";"CreepTumorQueen";NA;137;0
"Building";"CreepTumorQueen";NA;137;0
"Unit";"Roach";"Larva";141;2
"Unit";"Roach";"Larva";141;2
"Unit";"Roach";"Larva";141;2
"Unit";"Roach";"Larva";141;2
"Unit";"Roach";"Larva";141;2
"Unit";"Roach";"Larva";141;2
"Unit";"Overlord";"Larva";141;0
"Unit";"Overlord";"Larva";141;0
"Unit";"Overlord";"Larva";141;0
"Unit";"Overlord";"Larva";141;0
"Building";"EvolutionChamber";NA;141;0
"Building";"CreepTumor";NA;153;0
"Building";"CreepTumor";NA;153;0
"Unit";"Overlord";"Larva";141;0
"Unit";"Overlord";"Larva";141;0
"Unit";"Overlord";"Larva";141;0
"Unit";"Overlord";"Larva";141;0
"Unit";"Overlord";"Larva";141;0
"Building";"CreepTumor";NA;153;0
"Upgrade";"GlialReconstitution";"RoachWarren";129;0
"Unit";"Roach";"Larva";153;2
"Unit";"Roach";"Larva";153;2
"Unit";"Roach";"Larva";153;2
"Unit";"Roach";"Larva";153;2
"Unit";"Roach";"Larva";153;2
"Unit";"Roach";"Larva";153;2
"Building";"Hatchery";NA;125;0
"Building";"Extractor";NA;153;0
"Building";"CreepTumor";NA;168;0
"Building";"CreepTumor";NA;168;0
"Unit";"Roach";"Larva";166;2
"Unit";"Roach";"Larva";166;2
"Unit";"Roach";"Larva";166;2
"Unit";"Roach";"Larva";166;2
"Unit";"Roach";"Larva";166;2
"Unit";"Roach";"Larva";166;2
"Unit";"Roach";"Larva";166;2
"Upgrade";"Burrow";"Hatchery";153;0
"Unit";"Roach";"Larva";168;2
"Unit";"Roach";"Larva";168;2
"Unit";"Roach";"Larva";168;2
"Unit";"Roach";"Larva";168;2
"Unit";"Roach";"Larva";192;2
"Unit";"Roach";"Larva";192;2
"Unit";"Roach";"Larva";192;2
"Unit";"Roach";"Larva";192;2
"Unit";"Roach";"Larva";192;2
"Unit";"Roach";"Larva";192;2
"Unit";"Roach";"Larva";192;2
"Unit";"Overlord";"Larva";192;0
"Unit";"Overlord";"Larva";192;0
"Unit";"Overlord";"Larva";192;0
"Upgrade";"TunnelingClaws";"RoachWarren";168;0
"Building";"HydraliskDen";NA;192;0
"Unit";"Roach";"Larva";192;2
"Unit";"Roach";"Larva";192;2
"Unit";"Roach";"Larva";192;2
"Unit";"Roach";"Larva";192;2
"Unit";"Roach";"Larva";192;2
"Unit";"Roach";"Larva";196;2
"Unit";"Roach";"Larva";196;2
"Unit";"Roach";"Larva";196;2
"Unit";"Roach";"Larva";196;2
"Unit";"Roach";"Larva";196;2
"Unit";"Roach";"Larva";196;2
"Building";"SpineCrawler";NA;192;0
"Building";"SpineCrawler";NA;192;0
"Upgrade";"ZergMissileWeaponsLevel2";"EvolutionChamber";153;0
"Unit";"Roach";"Larva";220;2
"Unit";"Roach";"Larva";220;2
"Unit";"Roach";"Larva";220;2
"Unit";"Roach";"Larva";220;2
"Unit";"Roach";"Larva";220;2
"Unit";"Roach";"Larva";220;2
"Unit";"Roach";"Larva";220;2
"Unit";"Roach";"Larva";220;2
"Unit";"Roach";"Larva";220;2
"Unit";"Roach";"Larva";220;2
"Upgrade";"ZergGroundArmorsLevel1";"EvolutionChamber";184;0
"Unit";"Roach";"Larva";232;2
"Unit";"Roach";"Larva";232;2
"Unit";"Roach";"Larva";232;2
"Unit";"Roach";"Larva";232;2
"Unit";"Roach";"Larva";232;2
"Unit";"Roach";"Larva";232;2
"Unit";"Roach";"Larva";264;2
"Unit";"Roach";"Larva";264;2
"Unit";"Roach";"Larva";264;2
"Unit";"Roach";"Larva";264;2
"Unit";"Roach";"Larva";264;2
"Unit";"Roach";"Larva";264;2
"Unit";"Roach";"Larva";264;2
"Unit";"Roach";"Larva";264;2
"Unit";"Roach";"Larva";264;2
"Unit";"Roach";"Larva";264;2
"Unit";"Roach";"Larva";264;2
"Unit";"Roach";"Larva";264;2
"Unit";"Roach";"Larva";264;2
"Unit";"Roach";"Larva";264;2
"Upgrade";"EvolveMuscularAugments";"HydraliskDen";252;0
"Unit";"Roach";"Larva";264;2
"Unit";"Roach";"Larva";264;2
"Unit";"Roach";"Larva";264;2
"Unit";"Roach";"Larva";264;2
"Unit";"Roach";"Larva";264;2
"Unit";"Roach";"Larva";264;2
"Unit";"Roach";"Larva";264;2
"Unit";"Roach";"Larva";264;2
"Unit";"Roach";"Larva";264;2
