"type";"unit_name";"on_building";"total_supply";"supply"
"Unit";"Overlord";"Larva";12;0
"Building";"Extractor";NA;17;0
"Unit";"Overlord";"Larva";22;0
"Building";"SpawningPool";NA;19;0
"Building";"Hatchery";NA;17;0
"Unit";"Zergling";"Larva";22;1
"Unit";"Zergling";"Larva";22;1
"Unit";"Zergling";"Larva";22;1
"Unit";"Zergling";"Larva";22;1
"Unit";"Zergling";"Larva";22;1
"Unit";"Zergling";"Larva";22;1
"Unit";"Queen";"Hatchery";22;2
"Unit";"Queen";"Hatchery";22;2
"Unit";"Overlord";"Larva";38;0
"Unit";"Overlord";"Larva";38;0
"Building";"BanelingNest";NA;36;0
"Unit";"Overlord";"Larva";40;0
"Unit";"Zergling";"Larva";41;1
"Unit";"Zergling";"Larva";41;1
"Unit";"Zergling";"Larva";41;1
"Unit";"Zergling";"Larva";41;1
"Unit";"Zergling";"Larva";41;1
"Unit";"Zergling";"Larva";41;1
"Unit";"Zergling";"Larva";41;1
"Unit";"Zergling";"Larva";41;1
"Unit";"Zergling";"Larva";41;1
"Unit";"Zergling";"Larva";41;1
"Unit";"Zergling";"Larva";41;1
"Unit";"Zergling";"Larva";41;1
"Unit";"Baneling";"Zergling";41;0
"Unit";"Baneling";"Zergling";41;0
"Building";"Hatchery";NA;36;0
"Unit";"Zergling";"Larva";41;1
"Unit";"Zergling";"Larva";41;1
"Unit";"Zergling";"Larva";41;1
"Unit";"Zergling";"Larva";41;1
"Unit";"Zergling";"Larva";41;1
"Unit";"Zergling";"Larva";41;1
"Unit";"Zergling";"Larva";41;1
"Unit";"Zergling";"Larva";41;1
"Building";"EvolutionChamber";NA;53;0
"Unit";"Zergling";"Larva";63;1
"Unit";"Zergling";"Larva";63;1
"Unit";"Zergling";"Larva";63;1
"Unit";"Zergling";"Larva";63;1
"Unit";"Zergling";"Larva";63;1
"Unit";"Zergling";"Larva";63;1
"Unit";"Zergling";"Larva";63;1
"Unit";"Zergling";"Larva";63;1
"Unit";"Zergling";"Larva";67;1
"Unit";"Zergling";"Larva";67;1
"Unit";"Overlord";"Larva";67;0
"Unit";"Overlord";"Larva";67;0
"Unit";"Zergling";"Larva";77;1
"Unit";"Zergling";"Larva";77;1
"Unit";"Zergling";"Larva";77;1
"Unit";"Zergling";"Larva";77;1
"Unit";"Zergling";"Larva";77;1
"Unit";"Zergling";"Larva";77;1
"Unit";"Zergling";"Larva";77;1
"Unit";"Zergling";"Larva";77;1
"Unit";"Zergling";"Larva";77;1
"Unit";"Zergling";"Larva";77;1
"Unit";"Queen";"Hatchery";77;2
"Unit";"Baneling";"Zergling";96;0
"Unit";"Baneling";"Zergling";96;0
"Unit";"Overlord";"Larva";99;0
"Unit";"Overlord";"Larva";104;0
"Unit";"Overlord";"Larva";104;0
"Building";"Extractor";NA;104;0
"Building";"Extractor";NA;104;0
"Unit";"Zergling";"Larva";112;1
"Unit";"Zergling";"Larva";112;1
"Unit";"Zergling";"Larva";112;1
"Unit";"Zergling";"Larva";112;1
"Unit";"Zergling";"Larva";112;1
"Unit";"Zergling";"Larva";112;1
"Unit";"Zergling";"Larva";112;1
"Unit";"Zergling";"Larva";112;1
"Unit";"Zergling";"Larva";112;1
"Unit";"Zergling";"Larva";112;1
"Unit";"Baneling";"Zergling";112;0
"Unit";"Baneling";"Zergling";112;0
"Upgrade";"ZergMissileWeaponsLevel1";"EvolutionChamber";90;0
"Building";"RoachWarren";NA;104;0
"Unit";"Baneling";"Zergling";122;0
"Unit";"Baneling";"Zergling";122;0
"Unit";"Baneling";"Zergling";122;0
"Unit";"Baneling";"Zergling";122;0
"Unit";"Baneling";"Zergling";122;0
"Unit";"Overlord";"Larva";134;0
"Unit";"Overlord";"Larva";134;0
"Unit";"Overlord";"Larva";134;0
"Building";"Extractor";NA;136;0
"Building";"Extractor";NA;136;0
"Unit";"Baneling";"Zergling";136;0
"Unit";"Baneling";"Zergling";136;0
"Unit";"Baneling";"Zergling";136;0
"Unit";"Overlord";"Larva";140;0
"Unit";"Overlord";"Larva";140;0
"Unit";"Overlord";"Larva";140;0
"Unit";"Overlord";"Larva";140;0
"Unit";"Roach";"Larva";140;2
"Unit";"Roach";"Larva";140;2
"Unit";"Roach";"Larva";140;2
"Unit";"Roach";"Larva";142;2
"Unit";"Roach";"Larva";142;2
"Unit";"Roach";"Larva";142;2
"Unit";"Roach";"Larva";144;2
"Unit";"Roach";"Larva";144;2
"Unit";"Roach";"Larva";144;2
"Unit";"Roach";"Larva";144;2
"Unit";"Roach";"Larva";144;2
"Unit";"Zergling";"Larva";156;1
"Unit";"Zergling";"Larva";156;1
"Unit";"Roach";"Larva";156;2
"Unit";"Roach";"Larva";156;2
"Unit";"Roach";"Larva";156;2
"Unit";"Roach";"Larva";156;2
"Unit";"Roach";"Larva";156;2
"Unit";"Roach";"Larva";156;2
"Unit";"Roach";"Larva";156;2
"Unit";"Roach";"Larva";156;2
"Unit";"Roach";"Larva";164;2
"Building";"SpineCrawler";NA;144;0
"Upgrade";"GlialReconstitution";"RoachWarren";140;0
"Building";"SpineCrawler";NA;150;0
"Unit";"Roach";"Larva";164;2
"Unit";"Roach";"Larva";164;2
"Unit";"Roach";"Larva";166;2
"Unit";"Roach";"Larva";166;2
"Unit";"Roach";"Larva";176;2
"Unit";"Overlord";"Larva";182;0
"Unit";"Overlord";"Larva";182;0
"Building";"Extractor";NA;186;0
"Building";"Hatchery";NA;156;0
"Unit";"Overlord";"Larva";207;0
"Unit";"Overlord";"Larva";207;0
"Unit";"Overlord";"Larva";207;0
"Unit";"Roach";"Larva";207;2
"Unit";"Baneling";"Zergling";207;0
"Unit";"Baneling";"Zergling";207;0
"Unit";"Roach";"Larva";207;2
"Unit";"Roach";"Larva";207;2
"Unit";"Roach";"Larva";207;2
"Unit";"Roach";"Larva";207;2
"Unit";"Roach";"Larva";207;2
"Unit";"Roach";"Larva";207;2
"Unit";"Roach";"Larva";207;2
"Building";"HydraliskDen";NA;207;0
"Unit";"Roach";"Larva";207;2
"Unit";"Roach";"Larva";207;2
"Unit";"Roach";"Larva";207;2
"Unit";"Roach";"Larva";207;2
"Unit";"Roach";"Larva";207;2
"Unit";"Roach";"Larva";207;2
"Upgrade";"ZergMissileWeaponsLevel2";"EvolutionChamber";156;0
"Unit";"Roach";"Larva";223;2
"Unit";"Roach";"Larva";223;2
"Unit";"Roach";"Larva";223;2
"Unit";"Roach";"Larva";235;2
"Unit";"Roach";"Larva";235;2
"Unit";"Roach";"Larva";235;2
"Unit";"Roach";"Larva";235;2
"Unit";"Roach";"Larva";235;2
"Unit";"Roach";"Larva";235;2
"Unit";"Roach";"Larva";235;2
"Unit";"Roach";"Larva";235;2
"Unit";"Roach";"Larva";235;2
"Unit";"Roach";"Larva";241;2
"Unit";"Roach";"Larva";241;2
"Building";"EvolutionChamber";NA;241;0
"Building";"Extractor";NA;259;0
"Building";"Hatchery";NA;223;0
"Building";"Extractor";NA;270;0
"Unit";"Hydralisk";"Larva";270;2
"Unit";"Hydralisk";"Larva";270;2
"Unit";"Hydralisk";"Larva";270;2
"Unit";"Hydralisk";"Larva";270;2
"Unit";"Hydralisk";"Larva";270;2
"Building";"SpineCrawler";NA;270;0
"Unit";"Hydralisk";"Larva";279;2
"Unit";"Hydralisk";"Larva";279;2
"Unit";"Hydralisk";"Larva";279;2
"Unit";"Hydralisk";"Larva";279;2
"Upgrade";"EvolveGroovedSpines";"HydraliskDen";270;0
"Unit";"Hydralisk";"Larva";289;2
"Unit";"Hydralisk";"Larva";289;2
"Unit";"Hydralisk";"Larva";289;2
"Unit";"Hydralisk";"Larva";289;2
"Unit";"Hydralisk";"Larva";289;2
"Building";"SporeCrawler";NA;297;0
"Building";"SporeCrawler";NA;297;0
"Building";"SporeCrawler";NA;297;0
"Building";"SpineCrawler";NA;289;0
"Building";"Hatchery";NA;270;0
"Building";"SpineCrawler";NA;297;0
"Building";"SporeCrawler";NA;307;0
"Unit";"Hydralisk";"Larva";303;2
"Unit";"Hydralisk";"Larva";307;2
"Unit";"Hydralisk";"Larva";307;2
"Unit";"Hydralisk";"Larva";307;2
"Unit";"Hydralisk";"Larva";307;2
"Unit";"Hydralisk";"Larva";307;2
"Unit";"Hydralisk";"Larva";307;2
"Unit";"Roach";"Larva";307;2
"Unit";"Roach";"Larva";307;2
"Unit";"Roach";"Larva";307;2
"Unit";"Roach";"Larva";307;2
"Unit";"Roach";"Larva";307;2
"Upgrade";"ZergGroundArmorsLevel1";"EvolutionChamber";270;0
"Building";"LurkerDenMP";NA;278;0
"Unit";"Roach";"Larva";331;2
"Unit";"Roach";"Larva";331;2
"Unit";"Roach";"Larva";331;2
"Unit";"Roach";"Larva";331;2
"Unit";"Roach";"Larva";331;2
"Unit";"Roach";"Larva";331;2
"Unit";"Roach";"Larva";331;2
"Unit";"Roach";"Larva";331;2
"Building";"InfestationPit";NA;331;0
"Unit";"Roach";"Larva";347;2
"Unit";"Roach";"Larva";347;2
"Unit";"Roach";"Larva";347;2
"Upgrade";"EvolveMuscularAugments";"HydraliskDen";347;0
"Unit";"Roach";"Larva";353;2
"Unit";"Roach";"Larva";353;2
"Unit";"Roach";"Larva";353;2
"Unit";"Roach";"Larva";353;2
"Unit";"Roach";"Larva";353;2
"Unit";"Roach";"Larva";353;2
"Unit";"Roach";"Larva";353;2
"Unit";"Roach";"Larva";353;2
"Unit";"Roach";"Larva";353;2
"Unit";"Roach";"Larva";353;2
"Unit";"Roach";"Larva";353;2
"Unit";"Queen";"Hatchery";353;2
"Unit";"Hydralisk";"Larva";361;2
"Unit";"Hydralisk";"Larva";375;2
"Unit";"Hydralisk";"Larva";375;2
"Unit";"Hydralisk";"Larva";375;2
"Unit";"Hydralisk";"Larva";375;2
"Unit";"Hydralisk";"Larva";375;2
"Unit";"Hydralisk";"Larva";375;2
"Unit";"Hydralisk";"Larva";375;2
"Upgrade";"ZergGroundArmorsLevel2";"EvolutionChamber";347;0
"Unit";"Overlord";"Larva";394;0
"Unit";"Overlord";"Larva";394;0
"Unit";"Overlord";"Larva";394;0
"Unit";"Hydralisk";"Larva";394;2
"Unit";"Hydralisk";"Larva";396;2
"Unit";"Hydralisk";"Larva";396;2
"Unit";"Hydralisk";"Larva";396;2
"Unit";"Hydralisk";"Larva";396;2
"Unit";"Hydralisk";"Larva";396;2
"Unit";"Hydralisk";"Larva";396;2
"Unit";"Hydralisk";"Larva";396;2
"Unit";"Hydralisk";"Larva";396;2
"Unit";"Hydralisk";"Larva";396;2
"Unit";"Hydralisk";"Larva";396;2
"Unit";"Hydralisk";"Larva";396;2
"Unit";"Hydralisk";"Larva";396;2
"Unit";"Roach";"Larva";396;2
"Unit";"Roach";"Larva";396;2
"Unit";"Roach";"Larva";396;2
"Unit";"Roach";"Larva";396;2
"Unit";"Roach";"Larva";396;2
"Unit";"Roach";"Larva";396;2
"Unit";"Roach";"Larva";396;2
"Unit";"Hydralisk";"Larva";396;2
"Unit";"Hydralisk";"Larva";396;2
"Unit";"Hydralisk";"Larva";396;2
"Unit";"Hydralisk";"Larva";396;2
"Unit";"Hydralisk";"Larva";396;2
"Unit";"Hydralisk";"Larva";396;2
"Unit";"Hydralisk";"Larva";396;2
"Unit";"Hydralisk";"Larva";396;2
"Unit";"Hydralisk";"Larva";396;2
"Unit";"Roach";"Larva";452;2
"Unit";"Roach";"Larva";452;2
"Unit";"Roach";"Larva";452;2
"Unit";"Roach";"Larva";452;2
"Unit";"Roach";"Larva";452;2
"Unit";"Hydralisk";"Larva";452;2
"Unit";"Hydralisk";"Larva";452;2
"Unit";"Hydralisk";"Larva";452;2
"Unit";"Hydralisk";"Larva";452;2
"Unit";"Hydralisk";"Larva";452;2
"Unit";"Hydralisk";"Larva";452;2
"Building";"Hatchery";NA;474;0
"Unit";"Roach";"Larva";494;2
"Unit";"Roach";"Larva";494;2
"Unit";"Roach";"Larva";494;2
"Unit";"Roach";"Larva";494;2
"Unit";"Roach";"Larva";494;2
"Unit";"Roach";"Larva";494;2
"Unit";"Roach";"Larva";494;2
"Unit";"Roach";"Larva";494;2
"Unit";"Roach";"Larva";494;2
"Unit";"Roach";"Larva";494;2
"Unit";"Roach";"Larva";494;2
"Unit";"Roach";"Larva";494;2
"Unit";"Roach";"Larva";494;2
"Unit";"Roach";"Larva";494;2
"Building";"Extractor";NA;494;0
"Building";"Extractor";NA;494;0
"Unit";"Viper";"Larva";494;3
"Building";"Extractor";NA;522;0
"Building";"Spire";NA;479;0
"Unit";"Zergling";"Larva";522;1
"Unit";"Zergling";"Larva";522;1
"Unit";"Zergling";"Larva";522;1
"Unit";"Zergling";"Larva";522;1
"Unit";"Zergling";"Larva";522;1
"Unit";"Zergling";"Larva";522;1
"Unit";"Zergling";"Larva";522;1
"Unit";"Zergling";"Larva";522;1
"Unit";"Zergling";"Larva";522;1
"Unit";"Zergling";"Larva";522;1
"Unit";"Zergling";"Larva";522;1
"Unit";"Zergling";"Larva";522;1
"Unit";"Zergling";"Larva";522;1
"Unit";"Zergling";"Larva";522;1
"Unit";"Zergling";"Larva";522;1
"Unit";"Zergling";"Larva";522;1
"Unit";"Zergling";"Larva";522;1
"Unit";"Zergling";"Larva";522;1
"Unit";"Zergling";"Larva";522;1
"Unit";"Zergling";"Larva";522;1
"Unit";"Zergling";"Larva";522;1
"Unit";"Zergling";"Larva";522;1
"Unit";"Zergling";"Larva";522;1
"Unit";"Zergling";"Larva";522;1
"Unit";"Zergling";"Larva";522;1
"Unit";"Zergling";"Larva";522;1
"Unit";"Zergling";"Larva";522;1
"Unit";"Zergling";"Larva";522;1
"Unit";"Zergling";"Larva";522;1
"Unit";"Zergling";"Larva";522;1
"Unit";"Zergling";"Larva";522;1
"Unit";"Zergling";"Larva";522;1
"Unit";"Zergling";"Larva";522;1
"Unit";"Zergling";"Larva";522;1
"Unit";"Zergling";"Larva";559;1
"Unit";"Zergling";"Larva";559;1
"Unit";"Zergling";"Larva";559;1
"Unit";"Zergling";"Larva";559;1
"Unit";"Zergling";"Larva";559;1
"Unit";"Zergling";"Larva";559;1
"Unit";"Zergling";"Larva";559;1
"Unit";"Zergling";"Larva";559;1
"Unit";"Zergling";"Larva";559;1
"Unit";"Zergling";"Larva";559;1
"Unit";"Zergling";"Larva";559;1
"Unit";"Zergling";"Larva";559;1
"Unit";"Zergling";"Larva";559;1
"Unit";"Zergling";"Larva";559;1
"Building";"SpineCrawler";NA;525;0
"Building";"SpineCrawler";NA;525;0
"Building";"SpineCrawler";NA;525;0
"Building";"SpineCrawler";NA;525;0
"Unit";"Hydralisk";"Larva";573;2
"Unit";"Hydralisk";"Larva";573;2
"Unit";"Hydralisk";"Larva";573;2
"Unit";"Hydralisk";"Larva";573;2
"Unit";"Hydralisk";"Larva";573;2
"Unit";"Hydralisk";"Larva";573;2
"Unit";"Hydralisk";"Larva";573;2
"Unit";"Hydralisk";"Larva";573;2
"Unit";"Hydralisk";"Larva";573;2
"Unit";"Hydralisk";"Larva";573;2
"Unit";"Zergling";"Larva";573;1
"Unit";"Zergling";"Larva";573;1
"Unit";"Zergling";"Larva";573;1
"Unit";"Zergling";"Larva";573;1
"Unit";"Zergling";"Larva";573;1
"Unit";"Zergling";"Larva";573;1
"Unit";"Zergling";"Larva";573;1
"Unit";"Zergling";"Larva";573;1
"Unit";"Zergling";"Larva";573;1
"Unit";"Zergling";"Larva";573;1
"Unit";"Zergling";"Larva";573;1
"Unit";"Zergling";"Larva";573;1
"Unit";"Zergling";"Larva";573;1
"Unit";"Zergling";"Larva";573;1
"Unit";"Zergling";"Larva";573;1
"Unit";"Zergling";"Larva";573;1
"Unit";"Zergling";"Larva";573;1
"Unit";"Zergling";"Larva";573;1
"Unit";"Zergling";"Larva";573;1
"Unit";"Zergling";"Larva";573;1
"Unit";"Zergling";"Larva";573;1
"Unit";"Zergling";"Larva";573;1
"Unit";"Zergling";"Larva";615;1
"Unit";"Zergling";"Larva";615;1
"Unit";"Zergling";"Larva";615;1
"Unit";"Zergling";"Larva";615;1
"Unit";"Zergling";"Larva";623;1
"Unit";"Zergling";"Larva";623;1
"Unit";"Zergling";"Larva";623;1
"Unit";"Zergling";"Larva";623;1
"Unit";"Zergling";"Larva";623;1
"Unit";"Zergling";"Larva";623;1
"Unit";"Zergling";"Larva";623;1
"Unit";"Zergling";"Larva";623;1
"Unit";"Zergling";"Larva";623;1
"Unit";"Zergling";"Larva";623;1
"Unit";"Hydralisk";"Larva";627;2
"Unit";"Hydralisk";"Larva";627;2
"Unit";"Hydralisk";"Larva";627;2
"Unit";"Hydralisk";"Larva";627;2
"Unit";"Hydralisk";"Larva";627;2
"Unit";"Hydralisk";"Larva";627;2
"Unit";"Viper";"Larva";627;3
"Unit";"Viper";"Larva";627;3
"Building";"Hatchery";NA;573;0
"Unit";"Hydralisk";"Larva";643;2
"Unit";"Hydralisk";"Larva";643;2
"Unit";"Hydralisk";"Larva";643;2
"Unit";"Hydralisk";"Larva";643;2
"Unit";"Hydralisk";"Larva";643;2
"Unit";"Hydralisk";"Larva";643;2
"Unit";"Hydralisk";"Larva";643;2
"Unit";"Hydralisk";"Larva";643;2
"Unit";"Zergling";"Larva";655;1
"Unit";"Zergling";"Larva";655;1
"Unit";"Overlord";"Larva";655;0
"Unit";"Overlord";"Larva";655;0
"Upgrade";"ZergMissileWeaponsLevel3";"EvolutionChamber";573;0
