"type";"unit_name";"on_building";"total_supply_lag";"supply"
"Unit";"Overlord";"Larva";13;0
"Building";"Hatchery";NA;17;0
"Building";"Extractor";NA;19;0
"Building";"SpawningPool";NA;19;0
"Unit";"Overlord";"Larva";23;0
"Unit";"Queen";"Hatchery";23;2
"Unit";"Queen";"Hatchery";25;2
"Unit";"Zergling";"Larva";27;1
"Unit";"Zergling";"Larva";28;1
"Unit";"Zergling";"Larva";29;1
"Unit";"Zergling";"Larva";30;1
"Unit";"Zergling";"Larva";31;1
"Unit";"Zergling";"Larva";32;1
"Unit";"Zergling";"Larva";34;1
"Unit";"Zergling";"Larva";35;1
"Unit";"Zergling";"Larva";36;1
"Unit";"Zergling";"Larva";37;1
"Building";"Hatchery";NA;38;0
"Unit";"Overlord";"Larva";38;0
"Unit";"Zergling";"Larva";38;1
"Unit";"Zergling";"Larva";39;1
"Unit";"Zergling";"Larva";40;1
"Unit";"Zergling";"Larva";41;1
"Unit";"Zergling";"Larva";42;1
"Unit";"Zergling";"Larva";43;1
"Unit";"Zergling";"Larva";44;1
"Unit";"Zergling";"Larva";45;1
"Unit";"Zergling";"Larva";46;1
"Unit";"Zergling";"Larva";47;1
"Unit";"Zergling";"Larva";48;1
"Unit";"Zergling";"Larva";49;1
"Unit";"Zergling";"Larva";50;1
"Unit";"Zergling";"Larva";51;1
"Unit";"Zergling";"Larva";52;1
"Unit";"Zergling";"Larva";53;1
"Unit";"Zergling";"Larva";54;1
"Unit";"Zergling";"Larva";55;1
"Unit";"Zergling";"Larva";56;1
"Unit";"Zergling";"Larva";57;1
"Unit";"Zergling";"Larva";58;1
"Unit";"Zergling";"Larva";59;1
"Unit";"Zergling";"Larva";60;1
"Unit";"Zergling";"Larva";61;1
"Unit";"Zergling";"Larva";62;1
"Unit";"Zergling";"Larva";63;1
"Building";"BanelingNest";NA;64;0
"Unit";"Overlord";"Larva";64;0
"Unit";"Overlord";"Larva";67;0
"Unit";"Zergling";"Larva";67;1
"Unit";"Zergling";"Larva";68;1
"Unit";"Baneling";"Zergling";78;0
"Unit";"Baneling";"Zergling";78;0
"Unit";"Zergling";"Larva";78;1
"Unit";"Zergling";"Larva";79;1
"Unit";"Zergling";"Larva";80;1
"Unit";"Zergling";"Larva";81;1
"Unit";"Zergling";"Larva";82;1
"Unit";"Zergling";"Larva";83;1
"Unit";"Zergling";"Larva";84;1
"Unit";"Zergling";"Larva";85;1
"Unit";"Baneling";"Zergling";86;0
"Unit";"Zergling";"Larva";86;1
"Unit";"Zergling";"Larva";87;1
"Unit";"Zergling";"Larva";88;1
"Unit";"Zergling";"Larva";89;1
"Unit";"Zergling";"Larva";90;1
"Unit";"Zergling";"Larva";91;1
"Unit";"Zergling";"Larva";92;1
"Unit";"Zergling";"Larva";93;1
"Unit";"Zergling";"Larva";94;1
"Unit";"Zergling";"Larva";95;1
"Unit";"Zergling";"Larva";96;1
"Unit";"Zergling";"Larva";97;1
"Unit";"Zergling";"Larva";98;1
"Unit";"Zergling";"Larva";99;1
"Unit";"Zergling";"Larva";100;1
"Unit";"Zergling";"Larva";101;1
"Unit";"Baneling";"Zergling";102;0
"Unit";"Zergling";"Larva";102;1
"Unit";"Zergling";"Larva";103;1
"Unit";"Zergling";"Larva";104;1
"Unit";"Zergling";"Larva";105;1
"Unit";"Zergling";"Larva";106;1
"Unit";"Zergling";"Larva";107;1
"Unit";"Zergling";"Larva";108;1
"Unit";"Zergling";"Larva";109;1
"Building";"CreepTumorQueen";NA;116;0
"Unit";"Queen";"Hatchery";118;2
"Unit";"Baneling";"Zergling";120;0
"Unit";"Baneling";"Zergling";120;0
"Building";"Extractor";NA;124;0
"Building";"EvolutionChamber";NA;124;0
"Building";"Extractor";NA;124;0
"Unit";"Queen";"Hatchery";124;2
"Building";"CreepTumor";NA;130;0
"Unit";"Baneling";"Zergling";130;0
"Unit";"Baneling";"Zergling";130;0
"Unit";"Baneling";"Zergling";130;0
"Unit";"Zergling";"Larva";130;1
"Unit";"Zergling";"Larva";131;1
"Unit";"Zergling";"Larva";132;1
"Unit";"Zergling";"Larva";133;1
"Unit";"Zergling";"Larva";134;1
"Unit";"Zergling";"Larva";135;1
"Unit";"Zergling";"Larva";136;1
"Unit";"Zergling";"Larva";137;1
"Unit";"Zergling";"Larva";138;1
"Unit";"Zergling";"Larva";139;1
"Unit";"Zergling";"Larva";140;1
"Unit";"Zergling";"Larva";141;1
"Building";"Hatchery";NA;142;0
"Unit";"Zergling";"Larva";142;1
"Unit";"Zergling";"Larva";143;1
"Unit";"Zergling";"Larva";144;1
"Unit";"Zergling";"Larva";145;1
"Unit";"Baneling";"Zergling";146;0
"Unit";"Baneling";"Zergling";146;0
"Building";"RoachWarren";NA;146;0
"Building";"CreepTumorQueen";NA;146;0
"Unit";"Queen";"Hatchery";146;2
"Unit";"Overlord";"Larva";148;0
"Unit";"Overlord";"Larva";148;0
"Building";"CreepTumor";NA;148;0
"Unit";"Overlord";"Larva";149;0
"Unit";"Overlord";"Larva";151;0
"Unit";"Roach";"Larva";155;2
"Unit";"Roach";"Larva";157;2
"Unit";"Roach";"Larva";159;2
"Unit";"Roach";"Larva";161;2
"Building";"CreepTumor";NA;163;0
"Building";"CreepTumor";NA;163;0
"Unit";"Roach";"Larva";163;2
"Unit";"Roach";"Larva";165;2
"Unit";"Baneling";"Zergling";167;0
"Unit";"Roach";"Larva";174;2
"Unit";"Overlord";"Larva";176;0
"Unit";"Roach";"Larva";176;2
"Unit";"Roach";"Larva";178;2
"Unit";"Roach";"Larva";180;2
"Unit";"Roach";"Larva";182;2
"Building";"Extractor";NA;184;0
"Unit";"Overlord";"Larva";184;0
"Unit";"Overlord";"Larva";184;0
"Unit";"Queen";"Hatchery";184;2
"Unit";"Roach";"Larva";189;2
"Unit";"Roach";"Larva";191;2
"Unit";"Roach";"Larva";193;2
"Upgrade";"GlialReconstitution";"RoachWarren";195;0
"Unit";"Roach";"Larva";195;2
"Unit";"Roach";"Larva";197;2
"Unit";"Roach";"Larva";199;2
"Unit";"Roach";"Larva";201;2
"Unit";"Roach";"Larva";208;2
"Building";"Extractor";NA;210;0
"Unit";"Roach";"Larva";210;2
"Unit";"Roach";"Larva";212;2
"Building";"CreepTumor";NA;214;0
"Unit";"Overlord";"Larva";214;0
"Unit";"Roach";"Larva";214;2
"Unit";"Roach";"Larva";216;2
"Building";"Hatchery";NA;218;0
"Unit";"Roach";"Larva";218;2
"Building";"CreepTumorQueen";NA;220;0
"Unit";"Roach";"Larva";220;2
"Unit";"Roach";"Larva";222;2
"Unit";"Roach";"Larva";224;2
"Unit";"Roach";"Larva";226;2
"Unit";"Roach";"Larva";228;2
"Unit";"Roach";"Larva";230;2
"Building";"Extractor";NA;233;0
"Unit";"Overlord";"Larva";233;0
"Unit";"Overlord";"Larva";233;0
"Unit";"Overlord";"Larva";233;0
"Unit";"Overlord";"Larva";233;0
"Unit";"Overlord";"Larva";233;0
"Unit";"Overlord";"Larva";233;0
"Building";"HydraliskDen";NA;233;0
"Building";"CreepTumor";NA;233;0
"Building";"CreepTumor";NA;235;0
"Unit";"Roach";"Larva";235;2
"Unit";"Roach";"Larva";237;2
"Unit";"Roach";"Larva";239;2
"Unit";"Roach";"Larva";241;2
"Unit";"Roach";"Larva";243;2
"Unit";"Roach";"Larva";245;2
"Unit";"Roach";"Larva";247;2
"Unit";"Roach";"Larva";249;2
"Building";"CreepTumorQueen";NA;251;0
"Unit";"Roach";"Larva";257;2
"Unit";"Roach";"Larva";259;2
"Unit";"Roach";"Larva";261;2
"Unit";"Roach";"Larva";263;2
"Unit";"Overlord";"Larva";265;0
"Unit";"Overlord";"Larva";265;0
"Building";"LurkerDenMP";NA;266;0
"Building";"CreepTumor";NA;266;0
"Unit";"Roach";"Larva";266;2
"Unit";"Roach";"Larva";268;2
"Unit";"Roach";"Larva";270;2
"Unit";"Roach";"Larva";272;2
"Unit";"Roach";"Larva";274;2
"Unit";"Roach";"Larva";276;2
"Unit";"Roach";"Larva";278;2
"Unit";"Roach";"Larva";280;2
"Unit";"Roach";"Larva";282;2
"Unit";"Roach";"Larva";284;2
"Unit";"Roach";"Larva";286;2
"Unit";"Roach";"Larva";288;2
"Unit";"Roach";"Larva";290;2
"Unit";"Queen";"Hatchery";292;2
"Unit";"Hydralisk";"Larva";294;2
"Unit";"Hydralisk";"Larva";296;2
"Unit";"Hydralisk";"Larva";298;2
"Unit";"Hydralisk";"Larva";300;2
"Unit";"Hydralisk";"Larva";302;2
"Unit";"Hydralisk";"Larva";304;2
"Building";"SpineCrawler";NA;306;0
"Building";"SpineCrawler";NA;306;0
"Building";"Extractor";NA;306;0
"Building";"Extractor";NA;306;0
"Building";"SpineCrawler";NA;306;0
"Building";"InfestationPit";NA;309;0
"Unit";"Roach";"Larva";309;2
"Unit";"Roach";"Larva";311;2
"Building";"SpineCrawler";NA;313;0
"Building";"SpineCrawler";NA;313;0
"Building";"SporeCrawler";NA;313;0
"Building";"EvolutionChamber";NA;313;0
"Unit";"Roach";"Larva";320;2
"Unit";"Roach";"Larva";322;2
"Unit";"Roach";"Larva";324;2
"Unit";"Roach";"Larva";326;2
"Unit";"Roach";"Larva";328;2
"Unit";"Roach";"Larva";330;2
"Building";"CreepTumorQueen";NA;332;0
"Building";"SpineCrawler";NA;337;0
"Building";"SpineCrawler";NA;337;0
"Building";"SpineCrawler";NA;337;0
"Unit";"Hydralisk";"Larva";337;2
"Unit";"Hydralisk";"Larva";339;2
"Unit";"Hydralisk";"Larva";341;2
"Unit";"Hydralisk";"Larva";343;2
"Unit";"Hydralisk";"Larva";345;2
"Unit";"Hydralisk";"Larva";347;2
"Unit";"Hydralisk";"Larva";349;2
"Unit";"Hydralisk";"Larva";351;2
"Unit";"Hydralisk";"Larva";353;2
"Unit";"Hydralisk";"Larva";355;2
"Unit";"Hydralisk";"Larva";357;2
"Building";"CreepTumorQueen";NA;359;0
"Unit";"Hydralisk";"Larva";359;2
"Unit";"Hydralisk";"Larva";361;2
"Building";"SpineCrawler";NA;363;0
"Building";"SpineCrawler";NA;363;0
"Unit";"Queen";"Hatchery";363;2
"Building";"SpineCrawler";NA;365;0
"Unit";"Hydralisk";"Larva";372;2
"Unit";"Hydralisk";"Larva";374;2
"Unit";"Hydralisk";"Larva";376;2
"Unit";"Hydralisk";"Larva";378;2
"Unit";"Hydralisk";"Larva";380;2
"Unit";"Hydralisk";"Larva";382;2
"Unit";"Hydralisk";"Larva";384;2
"Unit";"Hydralisk";"Larva";386;2
"Unit";"Hydralisk";"Larva";388;2
"Unit";"Hydralisk";"Larva";390;2
"Unit";"Hydralisk";"Larva";392;2
"Unit";"Hydralisk";"Larva";394;2
"Unit";"Hydralisk";"Larva";396;2
"Unit";"Hydralisk";"Larva";398;2
"Unit";"Hydralisk";"Larva";400;2
"Unit";"Hydralisk";"Larva";402;2
"Unit";"Hydralisk";"Larva";404;2
"Unit";"Hydralisk";"Larva";406;2
"Unit";"Hydralisk";"Larva";408;2
"Unit";"Hydralisk";"Larva";410;2
"Unit";"Hydralisk";"Larva";425;2
"Unit";"Hydralisk";"Larva";427;2
"Unit";"Hydralisk";"Larva";429;2
"Unit";"Hydralisk";"Larva";431;2
"Building";"CreepTumor";NA;433;0
"Unit";"Roach";"Larva";433;2
"Unit";"Roach";"Larva";435;2
"Unit";"Roach";"Larva";437;2
"Unit";"Roach";"Larva";439;2
"Unit";"Roach";"Larva";441;2
"Unit";"Roach";"Larva";443;2
"Unit";"Roach";"Larva";445;2
"Unit";"Roach";"Larva";447;2
"Unit";"Roach";"Larva";449;2
"Unit";"Roach";"Larva";451;2
"Unit";"Roach";"Larva";453;2
"Unit";"Roach";"Larva";455;2
"Unit";"Roach";"Larva";457;2
"Unit";"Roach";"Larva";459;2
"Unit";"Roach";"Larva";461;2
"Unit";"Roach";"Larva";463;2
"Unit";"Roach";"Larva";465;2
"Unit";"Roach";"Larva";467;2
"Unit";"Roach";"Larva";469;2
"Upgrade";"SprayZerg";NA;471;0
"Upgrade";"SprayZerg";NA;471;0
"Upgrade";"SprayZerg";NA;471;0
"Upgrade";"zerglingmovementspeed";NA;471;0
"Upgrade";"SprayZerg";NA;471;0
"Upgrade";"SprayZerg";NA;471;0
"Upgrade";"SprayZerg";NA;471;0
"Upgrade";"SprayZerg";NA;471;0
"Upgrade";"ZergMissileWeaponsLevel1";NA;471;0
"Upgrade";"SprayZerg";NA;471;0
"Upgrade";"SprayZerg";NA;471;0
"Upgrade";"ZergMissileWeaponsLevel2";NA;471;0
"Upgrade";"EvolveGroovedSpines";NA;471;0
"Upgrade";"overlordspeed";NA;471;0
"Upgrade";"ZergGroundArmorsLevel1";NA;471;0
"Upgrade";"EvolveMuscularAugments";NA;471;0
"Upgrade";"DiggingClaws";NA;471;0
"Upgrade";"SprayZerg";NA;471;0
"Upgrade";"ZergGroundArmorsLevel2";NA;471;0
"Upgrade";"ZergMissileWeaponsLevel3";NA;471;0
