"Type";"UnitName";"OnBuilding";"TotalSupply";"Supply"
"Unit";"SCV";"Command Center";12;1
"Unit";"SCV";"Command Center";13;1
"Unit";"SCV";"Command Center";13;1
"Building";"SupplyDepot";NA;13;0
"Unit";"SCV";"Command Center";15;1
"Unit";"SCV";"Command Center";16;1
"Building";"Refinery";NA;15;0
"Unit";"SCV";"Command Center";16;1
"Unit";"SCV";"Command Center";17;1
"Building";"Barracks";NA;15;0
"Unit";"Reaper";"Barracks";19;1
"Unit";"SCV";"Command Center";19;1
"Building";"SupplyDepot";NA;19;0
"Unit";"Marine";"Barracks";20;1
"Unit";"SCV";"Command Center";21;1
"Unit";"SCV";"Command Center";22;1
"Unit";"SCV";"Command Center";24;1
"Building";"CommandCenter";NA;19;0
"Building";"Factory";NA;21;0
"Building";"Refinery";NA;24;0
"Unit";"SCV";"Command Center";24;1
"Building";"BarracksReactor";NA;23;0
"Unit";"SCV";"Command Center";26;1
"Unit";"SCV";"Command Center";26;1
"Unit";"SCV";"Command Center";27;1
"Building";"Starport";NA;25;0
"Building";"BarracksTechLab";NA;27;0
"Unit";"SCV";"Command Center";27;1
"Unit";"Hellion";"Factory";27;2
"Unit";"Hellion";"Factory";27;2
"Building";"SupplyDepot";NA;27;0
"Building";"SupplyDepot";NA;27;0
"Unit";"SCV";"Command Center";29;1
"Unit";"SCV";"Command Center";34;1
"Unit";"Hellion";"Factory";34;2
"Unit";"Hellion";"Factory";34;2
"Unit";"SCV";"Command Center";35;1
"Building";"BarracksTechLab";NA;35;0
"Building";"SupplyDepot";NA;35;0
"Unit";"SCV";"Command Center";41;1
"Unit";"SCV";"Command Center";41;1
"Unit";"Hellion";"Factory";41;2
"Unit";"Hellion";"Factory";41;2
"Unit";"SCV";"Command Center";43;1
"Unit";"SCV";"Command Center";43;1
"Unit";"Banshee";"Starport";34;3
"Unit";"SCV";"Command Center";52;1
"Unit";"SCV";"Command Center";52;1
"Unit";"Marine";"Barracks";52;1
"Unit";"Marine";"Barracks";52;1
"Unit";"SCV";"Command Center";52;1
"Unit";"SCV";"Command Center";53;1
"Unit";"SCV";"Command Center";58;1
"Unit";"Marine";"Barracks";54;1
"Unit";"Banshee";"Starport";49;3
"Unit";"Marine";"Barracks";56;1
"Unit";"SCV";"Command Center";58;1
"Unit";"SCV";"Command Center";58;1
"Building";"Refinery";NA;58;0
"Building";"Refinery";NA;58;0
"Building";"CommandCenter";NA;41;0
"Building";"EngineeringBay";NA;58;0
"Unit";"SCV";"Command Center";64;1
"Building";"EngineeringBay";NA;58;0
"Unit";"SCV";"Command Center";66;1
"Unit";"Marine";"Barracks";66;1
"Unit";"SCV";"Command Center";68;1
"Building";"FactoryReactor";NA;66;0
"Unit";"Marine";"Barracks";69;1
"Unit";"SCV";"Command Center";70;1
"Building";"Barracks";NA;66;0
"Unit";"SCV";"Command Center";70;1
"Building";"Barracks";NA;66;0
"Building";"StarportReactor";NA;68;0
"Unit";"SCV";"Command Center";71;1
"Unit";"Marine";"Barracks";70;1
"Unit";"Marine";"Barracks";73;1
"Unit";"Marine";"Barracks";73;1
"Unit";"SCV";"Command Center";74;1
"Unit";"SCV";"Command Center";74;1
"Unit";"Marine";"Barracks";73;1
"Unit";"Marine";"Barracks";73;1
"Building";"Barracks";NA;70;0
"Building";"Barracks";NA;70;0
"Unit";"Medivac";"Starport";73;2
"Unit";"Medivac";"Starport";74;2
"Unit";"SCV";"Command Center";81;1
"Unit";"Marine";"Barracks";81;1
"Unit";"Marine";"Barracks";81;1
"Unit";"Marine";"Barracks";81;1
"Unit";"Marine";"Barracks";81;1
"Building";"Armory";NA;73;0
"Building";"SupplyDepot";NA;85;0
"Building";"SupplyDepot";NA;85;0
"Building";"SupplyDepot";NA;85;0
"Unit";"SCV";"Command Center";90;1
"Unit";"SCV";"Command Center";90;1
"Unit";"Medivac";"Starport";85;2
"Unit";"SCV";"Command Center";90;1
"Unit";"Medivac";"Starport";85;2
"Building";"BarracksReactor";NA;83;0
"Building";"BarracksReactor";NA;85;0
"Unit";"SCV";"Command Center";90;1
"Upgrade";"TerranInfantryWeaponsLevel1";"EngineeringBay";72;0
"Upgrade";"TerranInfantryArmorsLevel1";"EngineeringBay";72;0
"Unit";"SCV";"Command Center";91;1
"Unit";"Marine";"Barracks";90;1
"Unit";"Marine";"Barracks";90;1
"Unit";"Marine";"Barracks";90;1
"Unit";"Marine";"Barracks";90;1
"Unit";"Marine";"Barracks";90;1
"Upgrade";"Stimpack";"TechLab";73;0
"Building";"SupplyDepot";NA;91;0
"Unit";"Marine";"Barracks";97;1
"Unit";"Marine";"Barracks";97;1
"Building";"Bunker";NA;90;0
"Unit";"SCV";"Command Center";100;1
"Unit";"SCV";"Command Center";101;1
"Unit";"SCV";"Command Center";102;1
"Unit";"SCV";"Command Center";106;1
"Unit";"Marine";"Barracks";109;1
"Unit";"Marine";"Barracks";109;1
"Unit";"Marine";"Barracks";109;1
"Unit";"Marine";"Barracks";109;1
"Unit";"Marine";"Barracks";109;1
"Unit";"Liberator";"Starport";97;3
"Unit";"Marine";"Barracks";109;1
"Unit";"Marine";"Barracks";109;1
"Unit";"Marine";"Barracks";109;1
"Unit";"Marine";"Barracks";109;1
"Building";"Refinery";NA;110;0
"Unit";"Marine";"Barracks";110;1
"Unit";"Marine";"Barracks";119;1
"Unit";"Marine";"Barracks";119;1
"Unit";"Marine";"Barracks";119;1
"Unit";"Marine";"Barracks";122;1
"Unit";"Marine";"Barracks";122;1
"Unit";"Marine";"Barracks";122;1
"Unit";"Marine";"Barracks";122;1
"Unit";"Marine";"Barracks";122;1
"Unit";"Marine";"Barracks";122;1
"Unit";"Marine";"Barracks";123;1
"Unit";"Marine";"Barracks";124;1
"Unit";"Marine";"Barracks";125;1
"Unit";"Marine";"Barracks";126;1
"Unit";"Marine";"Barracks";127;1
"Upgrade";"TerranVehicleAndShipArmorsLevel1";"Armory";104;0
"Unit";"Marine";"Barracks";128;1
"Unit";"Marine";"Barracks";129;1
"Unit";"Marine";"Barracks";130;1
"Unit";"Marine";"Barracks";131;1
"Unit";"Marine";"Barracks";132;1
"Unit";"Marine";"Barracks";133;1
"Unit";"Marine";"Barracks";134;1
"Unit";"Medivac";"Starport";126;2
"Unit";"Medivac";"Starport";126;2
"Building";"Refinery";NA;135;0
"Unit";"Marine";"Barracks";135;1
"Unit";"Marine";"Barracks";136;1
"Unit";"Marine";"Barracks";137;1
"Unit";"Marine";"Barracks";138;1
"Unit";"Marine";"Barracks";139;1
"Unit";"Marine";"Barracks";140;1
"Unit";"Marine";"Barracks";141;1
"Unit";"Marine";"Barracks";142;1
"Unit";"Marine";"Barracks";143;1
"Unit";"Marine";"Barracks";148;1
"Unit";"Marine";"Barracks";149;1
"Unit";"Marine";"Barracks";150;1
"Unit";"Marine";"Barracks";151;1
"Unit";"Marine";"Barracks";152;1
"Building";"Factory";NA;135;0
"Building";"Barracks";NA;135;0
"Unit";"Marine";"Barracks";153;1
"Unit";"SCV";"Command Center";157;1
"Building";"Barracks";NA;135;0
"Unit";"SCV";"Command Center";157;1
"Unit";"SCV";"Command Center";157;1
"Unit";"Marine";"Barracks";154;1
"Unit";"Marine";"Barracks";155;1
"Unit";"Marine";"Barracks";156;1
"Unit";"Medivac";"Starport";153;2
"Unit";"Marine";"Barracks";157;1
"Unit";"Marine";"Barracks";158;1
"Unit";"SCV";"Command Center";163;1
"Unit";"SCV";"Command Center";164;1
"Unit";"SCV";"Command Center";165;1
"Upgrade";"TerranInfantryWeaponsLevel2";"EngineeringBay";122;0
"Building";"BarracksTechLab";NA;163;0
"Building";"BarracksTechLab";NA;164;0
"Building";"SupplyDepot";NA;163;0
"Building";"FactoryTechLab";NA;169;0
"Building";"SupplyDepot";NA;163;0
"Unit";"SCV";"Command Center";174;1
"Upgrade";"TerranInfantryArmorsLevel2";"EngineeringBay";123;0
"Unit";"Marine";"Barracks";169;1
"Building";"SupplyDepot";NA;169;0
"Building";"CommandCenter";NA;141;0
"Unit";"Marine";"Barracks";176;1
"Unit";"Marine";"Barracks";176;1
"Unit";"Marine";"Barracks";176;1
"Unit";"Marine";"Barracks";176;1
"Unit";"Marine";"Barracks";176;1
"Unit";"Marine";"Barracks";176;1
"Unit";"Marine";"Barracks";176;1
"Unit";"Marine";"Barracks";176;1
"Unit";"Marine";"Barracks";176;1
"Unit";"Marine";"Barracks";176;1
"Unit";"SCV";"Command Center";179;1
"Unit";"SCV";"Command Center";179;1
"Unit";"Marine";"Barracks";190;1
"Unit";"Marine";"Barracks";190;1
"Unit";"Marine";"Barracks";190;1
"Unit";"Marine";"Barracks";190;1
"Unit";"Marine";"Barracks";190;1
"Unit";"Marauder";"Barracks";190;2
"Unit";"Marauder";"Barracks";190;2
"Unit";"Marauder";"Barracks";190;2
"Unit";"Marine";"Barracks";190;1
"Unit";"Marine";"Barracks";190;1
"Unit";"Marine";"Barracks";190;1
"Unit";"Marine";"Barracks";190;1
"Unit";"SCV";"Command Center";201;1
"Unit";"SCV";"Command Center";201;1
"Unit";"SCV";"Command Center";201;1
"Unit";"Marauder";"Barracks";195;2
"Unit";"Marauder";"Barracks";197;2
"Unit";"Marine";"Barracks";201;1
"Unit";"Marine";"Barracks";201;1
"Unit";"Marine";"Barracks";201;1
"Unit";"SCV";"Command Center";205;1
"Unit";"Marine";"Barracks";205;1
"Unit";"Marine";"Barracks";205;1
"Unit";"Marine";"Barracks";206;1
"Upgrade";"TerranVehicleAndShipArmorsLevel2";"Armory";169;0
"Building";"SupplyDepot";NA;203;0
"Building";"Starport";NA;195;0
"Building";"SupplyDepot";NA;204;0
"Unit";"Marauder";"Barracks";206;2
"Unit";"Marine";"Barracks";208;1
"Unit";"Marine";"Barracks";208;1
"Building";"Starport";NA;201;0
"Unit";"Marauder";"Barracks";219;2
"Unit";"Marauder";"Barracks";219;2
"Unit";"Marine";"Barracks";223;1
"Unit";"Marine";"Barracks";223;1
"Unit";"Marine";"Barracks";223;1
"Unit";"Marine";"Barracks";223;1
"Unit";"Marine";"Barracks";223;1
"Unit";"Marine";"Barracks";223;1
"Unit";"Marine";"Barracks";223;1
"Unit";"Marine";"Barracks";223;1
"Unit";"Marauder";"Barracks";223;2
"Building";"StarportTechLab";NA;223;0
"Unit";"Marine";"Barracks";227;1
"Unit";"Marine";"Barracks";228;1
"Unit";"Marine";"Barracks";229;1
"Unit";"Marine";"Barracks";230;1
"Unit";"Marine";"Barracks";231;1
"Unit";"Marauder";"Barracks";223;2
"Unit";"Marauder";"Barracks";223;2
"Building";"SupplyDepot";NA;237;0
"Building";"SupplyDepot";NA;237;0
"Building";"SupplyDepot";NA;237;0
"Unit";"Marine";"Barracks";237;1
"Unit";"Marine";"Barracks";237;1
"Unit";"Marauder";"Barracks";237;2
