"type";"unit_name";"on_building";"total_supply";"supply"
"Building";"Refinery";NA;14;0
"Building";"Barracks";NA;15;0
"Unit";"Reaper";"Barracks";19;1
"Building";"Bunker";NA;20;0
"Building";"Factory";NA;19;0
"Building";"CommandCenter";NA;19;0
"Building";"BarracksReactor";NA;20;0
"Unit";"Marine";"Barracks";22;1
"Unit";"Marine";"Barracks";22;1
"Unit";"Cyclone";"Factory";22;3
"Building";"Refinery";NA;23;0
"Unit";"Marine";"Barracks";23;1
"Unit";"Marine";"Barracks";24;1
"Unit";"Hellion";"Factory";32;2
"Building";"BarracksTechLab";NA;33;0
"Unit";"Hellion";"Factory";33;2
"Unit";"Hellion";"Factory";39;2
"Unit";"Hellion";"Factory";39;2
"Building";"Starport";NA;37;0
"Building";"CommandCenter";NA;32;0
"Building";"EngineeringBay";NA;47;0
"Unit";"Marine";"Barracks";48;1
"Building";"EngineeringBay";NA;47;0
"Building";"FactoryReactor";NA;50;0
"Building";"Refinery";NA;53;0
"Building";"Refinery";NA;53;0
"Building";"Barracks";NA;48;0
"Building";"Barracks";NA;50;0
"Building";"StarportReactor";NA;56;0
"Unit";"Marine";"Barracks";59;1
"Unit";"Marine";"Barracks";59;1
"Unit";"Marine";"Barracks";59;1
"Upgrade";"Stimpack";"TechLab";48;0
"Building";"FactoryTechLab";NA;62;0
"Unit";"Marine";"Barracks";65;1
"Unit";"Marine";"Barracks";66;1
"Unit";"Marine";"Barracks";67;1
"Unit";"Medivac";"Starport";65;2
"Unit";"Medivac";"Starport";65;2
"Building";"Barracks";NA;62;0
"Building";"Barracks";NA;62;0
"Upgrade";"TerranInfantryWeaponsLevel1";"EngineeringBay";59;0
"Upgrade";"TerranInfantryArmorsLevel1";"EngineeringBay";59;0
"Unit";"Marine";"Barracks";76;1
"Unit";"Marine";"Barracks";76;1
"Unit";"Marine";"Barracks";76;1
"Unit";"Marine";"Barracks";76;1
"Unit";"Marine";"Barracks";76;1
"Building";"Refinery";NA;76;0
"Building";"Refinery";NA;76;0
"Unit";"Marine";"Barracks";79;1
"Unit";"Marine";"Barracks";79;1
"Unit";"Marine";"Barracks";79;1
"Unit";"Marine";"Barracks";79;1
"Building";"Armory";NA;76;0
"Unit";"Marine";"Barracks";86;1
"Building";"BarracksReactor";NA;78;0
"Building";"BarracksReactor";NA;78;0
"Unit";"Marine";"Barracks";87;1
"Unit";"Medivac";"Starport";86;2
"Unit";"Medivac";"Starport";86;2
"Unit";"Marine";"Barracks";96;1
"Unit";"Marine";"Barracks";96;1
"Unit";"Marine";"Barracks";96;1
"Unit";"Marine";"Barracks";96;1
"Unit";"Marine";"Barracks";96;1
"Unit";"Marine";"Barracks";96;1
"Unit";"Marine";"Barracks";96;1
"Unit";"Marine";"Barracks";96;1
"Unit";"Marauder";"Barracks";96;2
"Unit";"Marine";"Barracks";100;1
"Unit";"Marine";"Barracks";101;1
"Unit";"Marine";"Barracks";102;1
"Unit";"Marine";"Barracks";108;1
"Unit";"Marine";"Barracks";108;1
"Unit";"Marine";"Barracks";108;1
"Unit";"Marine";"Barracks";108;1
"Unit";"Marine";"Barracks";108;1
"Unit";"Marine";"Barracks";108;1
"Unit";"Medivac";"Starport";108;2
"Unit";"Marine";"Barracks";110;1
"Unit";"Marine";"Barracks";111;1
"Unit";"Marine";"Barracks";112;1
"Unit";"Marine";"Barracks";113;1
"Unit";"Marine";"Barracks";114;1
"Unit";"Medivac";"Starport";110;2
"Unit";"Marine";"Barracks";119;1
"Unit";"Marine";"Barracks";119;1
"Unit";"Marine";"Barracks";119;1
"Unit";"Marauder";"Barracks";119;2
"Unit";"Marine";"Barracks";126;1
"Unit";"Marine";"Barracks";126;1
"Unit";"Marine";"Barracks";126;1
"Unit";"Marine";"Barracks";128;1
"Unit";"Marine";"Barracks";128;1
"Unit";"Marine";"Barracks";128;1
"Unit";"Medivac";"Starport";128;2
"Unit";"Medivac";"Starport";128;2
"Unit";"Marine";"Barracks";136;1
"Unit";"Marine";"Barracks";136;1
"Unit";"Marine";"Barracks";136;1
"Unit";"Marine";"Barracks";136;1
"Unit";"Marine";"Barracks";136;1
"Unit";"Marauder";"Barracks";131;2
"Unit";"Marine";"Barracks";136;1
"Unit";"Marine";"Barracks";138;1
"Building";"CommandCenter";NA;110;0
"Unit";"Marine";"Barracks";138;1
"Unit";"Marine";"Barracks";150;1
"Unit";"Marine";"Barracks";150;1
"Unit";"Marine";"Barracks";150;1
"Unit";"Marine";"Barracks";150;1
"Unit";"Marine";"Barracks";150;1
"Unit";"Marine";"Barracks";150;1
"Unit";"Marine";"Barracks";150;1
"Unit";"Medivac";"Starport";150;2
"Unit";"Marine";"Barracks";153;1
"Unit";"Marine";"Barracks";153;1
"Unit";"Marine";"Barracks";153;1
"Unit";"Marine";"Barracks";154;1
"Unit";"Marine";"Barracks";155;1
"Upgrade";"TerranInfantryArmorsLevel2";"EngineeringBay";113;0
"Upgrade";"TerranInfantryWeaponsLevel2";"EngineeringBay";113;0
"Unit";"Marine";"Barracks";160;1
"Unit";"Marine";"Barracks";160;1
"Unit";"Marine";"Barracks";172;1
"Unit";"Marine";"Barracks";172;1
"Unit";"Marine";"Barracks";172;1
"Unit";"Marine";"Barracks";172;1
"Unit";"Marine";"Barracks";172;1
"Unit";"Marine";"Barracks";172;1
"Unit";"Marine";"Barracks";172;1
"Unit";"Marine";"Barracks";172;1
"Unit";"Marine";"Barracks";172;1
"Unit";"Marine";"Barracks";173;1
"Unit";"Marine";"Barracks";181;1
"Unit";"Marine";"Barracks";181;1
"Unit";"Medivac";"Starport";179;2
"Unit";"Medivac";"Starport";179;2
"Unit";"Marauder";"Barracks";181;2
"Unit";"Marine";"Barracks";182;1
"Unit";"Marine";"Barracks";182;1
"Unit";"Marine";"Barracks";182;1
"Unit";"Marine";"Barracks";182;1
"Unit";"Marine";"Barracks";182;1
