"Type";"UnitName";"OnBuilding";"TotalSupply";"Supply"
"Unit";"SCV";"Command Center";12;1
"Unit";"SCV";"Command Center";12;1
"Unit";"SCV";"Command Center";13;1
"Building";"SupplyDepot";NA;13;0
"Unit";"SCV";"Command Center";15;1
"Unit";"SCV";"Command Center";15;1
"Building";"Refinery";NA;15;0
"Unit";"SCV";"Command Center";16;1
"Building";"Barracks";NA;15;0
"Unit";"SCV";"Command Center";17;1
"Unit";"Reaper";"Barracks";19;1
"Unit";"SCV";"Command Center";19;1
"Building";"SupplyDepot";NA;19;0
"Unit";"Marine";"Barracks";19;1
"Unit";"SCV";"Command Center";21;1
"Unit";"SCV";"Command Center";22;1
"Building";"Refinery";NA;21;0
"Unit";"SCV";"Command Center";23;1
"Building";"CommandCenter";NA;19;0
"Building";"Factory";NA;21;0
"Building";"BarracksReactor";NA;23;0
"Unit";"SCV";"Command Center";24;1
"Unit";"SCV";"Command Center";25;1
"Unit";"SCV";"Command Center";26;1
"Building";"BarracksTechLab";NA;26;0
"Unit";"Hellion";"Factory";26;2
"Unit";"Hellion";"Factory";26;2
"Unit";"SCV";"Command Center";27;1
"Building";"SupplyDepot";NA;27;0
"Building";"Starport";NA;26;0
"Unit";"SCV";"Command Center";28;1
"Unit";"SCV";"Command Center";33;1
"Unit";"SCV";"Command Center";33;1
"Unit";"Hellion";"Factory";33;2
"Unit";"Hellion";"Factory";33;2
"Building";"BarracksTechLab";NA;33;0
"Unit";"SCV";"Command Center";35;1
"Building";"SupplyDepot";NA;34;0
"Unit";"SCV";"Command Center";36;1
"Unit";"SCV";"Command Center";41;1
"Unit";"Hellion";"Factory";40;2
"Unit";"Hellion";"Factory";41;2
"Unit";"SCV";"Command Center";42;1
"Unit";"SCV";"Command Center";42;1
"Unit";"Banshee";"Starport";35;3
"Building";"SupplyDepot";NA;42;0
"Unit";"SCV";"Command Center";49;1
"Unit";"SCV";"Command Center";49;1
"Unit";"Hellion";"Factory";48;2
"Unit";"Hellion";"Factory";48;2
"Unit";"SCV";"Command Center";54;1
"Unit";"SCV";"Command Center";54;1
"Unit";"SCV";"Command Center";59;1
"Unit";"SCV";"Command Center";60;1
"Unit";"Hellion";"Factory";58;2
"Unit";"Hellion";"Factory";58;2
"Unit";"Banshee";"Starport";52;3
"Unit";"SCV";"Command Center";61;1
"Unit";"SCV";"Command Center";61;1
"Building";"SupplyDepot";NA;60;0
"Building";"Refinery";NA;69;0
"Building";"Refinery";NA;69;0
"Building";"EngineeringBay";NA;69;0
"Unit";"Marine";"Barracks";71;1
"Unit";"Marine";"Barracks";71;1
"Building";"EngineeringBay";NA;70;0
"Building";"CommandCenter";NA;54;0
"Building";"StarportReactor";NA;71;0
"Unit";"Marine";"Barracks";73;1
"Unit";"Marine";"Barracks";73;1
"Building";"Barracks";NA;71;0
"Unit";"Marine";"Barracks";75;1
"Unit";"Marine";"Barracks";75;1
"Unit";"Marine";"Barracks";75;1
"Unit";"SCV";"Command Center";75;1
"Unit";"SCV";"Command Center";75;1
"Unit";"Marine";"Barracks";75;1
"Unit";"SCV";"Command Center";78;1
"Unit";"SCV";"Command Center";79;1
"Unit";"Medivac";"Starport";78;2
"Unit";"Medivac";"Starport";78;2
"Unit";"SCV";"Command Center";81;1
"Unit";"SCV";"Command Center";82;1
"Unit";"Marine";"Barracks";81;1
"Unit";"Marine";"Barracks";81;1
"Unit";"Marine";"Barracks";81;1
"Unit";"SCV";"Command Center";87;1
"Building";"Barracks";NA;78;0
"Building";"Barracks";NA;78;0
"Building";"SupplyDepot";NA;83;0
"Building";"Barracks";NA;78;0
"Unit";"Medivac";"Starport";88;2
"Unit";"Medivac";"Starport";89;2
"Upgrade";"TerranInfantryArmorsLevel1";"EngineeringBay";75;0
"Upgrade";"TerranInfantryWeaponsLevel1";"EngineeringBay";75;0
"Unit";"SCV";"Command Center";93;1
"Unit";"Marine";"Barracks";93;1
"Unit";"SCV";"Command Center";93;1
"Unit";"Marine";"Barracks";93;1
"Building";"Armory";NA;83;0
"Unit";"Marine";"Barracks";93;1
"Unit";"SCV";"Command Center";97;1
"Unit";"SCV";"Command Center";99;1
"Unit";"Marine";"Barracks";98;1
"Unit";"Marine";"Barracks";100;1
"Unit";"Medivac";"Starport";93;2
"Unit";"SCV";"Command Center";102;1
"Unit";"SCV";"Command Center";103;1
"Building";"BarracksReactor";NA;97;0
"Building";"BarracksReactor";NA;97;0
"Building";"BarracksReactor";NA;97;0
"Unit";"Marine";"Barracks";104;1
"Unit";"Marine";"Barracks";104;1
"Unit";"SCV";"Command Center";108;1
"Unit";"SCV";"Command Center";109;1
"Building";"SupplyDepot";NA;106;0
"Building";"SupplyDepot";NA;106;0
"Unit";"Marine";"Barracks";108;1
"Building";"SupplyDepot";NA;106;0
"Unit";"Medivac";"Starport";104;2
"Unit";"SCV";"Command Center";112;1
"Upgrade";"Stimpack";"TechLab";89;0
"Unit";"Marine";"Barracks";110;1
"Unit";"SCV";"Command Center";115;1
"Unit";"SCV";"Command Center";115;1
"Unit";"Marine";"Barracks";114;1
"Unit";"Marine";"Barracks";114;1
"Unit";"Marine";"Barracks";114;1
"Unit";"Marine";"Barracks";114;1
"Unit";"Marine";"Barracks";114;1
"Unit";"Marine";"Barracks";114;1
"Unit";"Marine";"Barracks";114;1
"Unit";"Marine";"Barracks";114;1
"Unit";"SCV";"Command Center";117;1
"Unit";"SCV";"Command Center";119;1
"Unit";"Marine";"Barracks";118;1
"Unit";"Marine";"Barracks";121;1
"Unit";"Marine";"Barracks";122;1
"Unit";"Marine";"Barracks";123;1
"Unit";"Marine";"Barracks";124;1
"Unit";"Marine";"Barracks";125;1
"Unit";"Marine";"Barracks";126;1
"Unit";"Marine";"Barracks";127;1
"Building";"SupplyDepot";NA;128;0
"Building";"SupplyDepot";NA;128;0
"Unit";"Marine";"Barracks";130;1
"Unit";"Marine";"Barracks";131;1
"Unit";"SCV";"Command Center";139;1
"Unit";"Marine";"Barracks";132;1
"Unit";"Marine";"Barracks";133;1
"Building";"MissileTurret";NA;139;0
"Unit";"SCV";"Command Center";144;1
"Unit";"SCV";"Command Center";144;1
"Unit";"SCV";"Command Center";144;1
"Unit";"Marine";"Barracks";142;1
"Unit";"Marine";"Barracks";142;1
"Unit";"Marine";"Barracks";142;1
"Unit";"Marine";"Barracks";142;1
"Unit";"Marine";"Barracks";142;1
"Unit";"Marine";"Barracks";142;1
"Unit";"Marine";"Barracks";142;1
"Unit";"Marine";"Barracks";142;1
"Unit";"Marine";"Barracks";143;1
"Building";"MissileTurret";NA;144;0
"Unit";"Marine";"Barracks";147;1
"Unit";"Marine";"Barracks";148;1
"Unit";"Marine";"Barracks";148;1
"Unit";"SCV";"Command Center";156;1
"Unit";"SCV";"Command Center";156;1
"Unit";"SCV";"Command Center";156;1
"Unit";"Marine";"Barracks";156;1
"Unit";"Marine";"Barracks";156;1
"Unit";"Marine";"Barracks";156;1
"Unit";"Marine";"Barracks";156;1
"Unit";"Marine";"Barracks";156;1
"Unit";"Marine";"Barracks";156;1
"Unit";"Marine";"Barracks";157;1
"Unit";"Marine";"Barracks";159;1
"Building";"MissileTurret";NA;159;0
"Unit";"SCV";"Command Center";159;1
"Unit";"SCV";"Command Center";160;1
"Unit";"SCV";"Command Center";161;1
"Unit";"Marine";"Barracks";162;1
"Unit";"Medivac";"Starport";159;2
"Unit";"Medivac";"Starport";159;2
"Unit";"SCV";"Command Center";170;1
"Unit";"SCV";"Command Center";171;1
"Unit";"Marine";"Barracks";170;1
"Unit";"Marine";"Barracks";170;1
"Unit";"Marine";"Barracks";170;1
"Building";"Refinery";NA;173;0
"Building";"Refinery";NA;173;0
"Unit";"Marine";"Barracks";180;1
"Unit";"Marine";"Barracks";180;1
"Unit";"Marine";"Barracks";180;1
"Unit";"Marine";"Barracks";180;1
"Unit";"Marine";"Barracks";180;1
"Upgrade";"TerranInfantryWeaponsLevel2";"EngineeringBay";142;0
"Upgrade";"TerranInfantryArmorsLevel2";"EngineeringBay";142;0
"Unit";"Marine";"Barracks";183;1
"Unit";"Marine";"Barracks";183;1
"Unit";"Marine";"Barracks";183;1
"Unit";"Marine";"Barracks";183;1
"Unit";"SCV";"Command Center";188;1
"Unit";"SCV";"Command Center";188;1
"Unit";"SCV";"Command Center";188;1
"Unit";"Marine";"Barracks";183;1
"Unit";"Marine";"Barracks";184;1
"Unit";"Marine";"Barracks";185;1
"Unit";"Marine";"Barracks";186;1
"Unit";"Marine";"Barracks";188;1
"Building";"MissileTurret";NA;188;0
"Unit";"SCV";"Command Center";192;1
"Unit";"Marine";"Barracks";193;1
"Unit";"Marine";"Barracks";193;1
"Unit";"Marine";"Barracks";199;1
"Unit";"Marine";"Barracks";199;1
"Unit";"Marine";"Barracks";201;1
"Unit";"Marine";"Barracks";203;1
"Upgrade";"TerranVehicleAndShipArmorsLevel1";"Armory";179;0
