"type";"unit_name";"on_building";"total_supply";"supply"
"Building";"Refinery";NA;15;0
"Building";"Barracks";NA;15;0
"Unit";"Reaper";"Barracks";19;1
"Unit";"Marine";"Barracks";19;1
"Building";"Refinery";NA;21;0
"Building";"CommandCenter";NA;19;0
"Building";"Factory";NA;21;0
"Building";"BarracksReactor";NA;23;0
"Building";"BarracksTechLab";NA;26;0
"Unit";"Hellion";"Factory";26;2
"Unit";"Hellion";"Factory";26;2
"Building";"Starport";NA;26;0
"Unit";"Hellion";"Factory";28;2
"Unit";"Hellion";"Factory";30;2
"Unit";"Hellion";"Factory";39;2
"Unit";"Hellion";"Factory";39;2
"Unit";"Hellion";"Factory";43;2
"Unit";"Hellion";"Factory";45;2
"Unit";"Liberator";"Starport";42;3
"Building";"Refinery";NA;54;0
"Building";"BarracksTechLab";NA;56;0
"Building";"Refinery";NA;54;0
"Unit";"Cyclone";"Factory";54;3
"Unit";"Cyclone";"Factory";55;3
"Unit";"Hellion";"Factory";68;2
"Unit";"Hellion";"Factory";69;2
"Building";"CommandCenter";NA;48;0
"Building";"StarportReactor";NA;70;0
"Building";"Armory";NA;70;0
"Unit";"Hellion";"Factory";77;2
"Unit";"Hellion";"Factory";77;2
"Building";"Armory";NA;70;0
"Building";"Factory";NA;73;0
"Unit";"Hellion";"Factory";84;2
"Unit";"Hellion";"Factory";84;2
"Unit";"Medivac";"Starport";85;2
"Unit";"Medivac";"Starport";85;2
"Building";"Refinery";NA;86;0
"Building";"Factory";NA;80;0
"Building";"Refinery";NA;86;0
"Unit";"Hellion";"Factory";92;2
"Unit";"Hellion";"Factory";99;2
"Unit";"Thor";"Factory";87;6
"Unit";"Hellion";"Factory";103;2
"Unit";"Hellion";"Factory";103;2
"Unit";"Hellion";"Factory";109;2
"Building";"Refinery";NA;111;0
"Building";"Refinery";NA;111;0
"Unit";"Hellion";"Factory";111;2
"Unit";"Hellion";"Factory";113;2
"Upgrade";"TerranVehicleWeaponsLevel1";"Armory";98;0
"Unit";"Hellion";"Factory";120;2
"Unit";"Hellion";"Factory";128;2
"Building";"BarracksReactor";NA;126;0
"Unit";"Hellion";"Factory";133;2
"Unit";"Hellion";"Factory";133;2
"Unit";"Hellion";"Factory";138;2
"Unit";"Hellion";"Factory";140;2
"Unit";"Hellion";"Factory";155;2
"Unit";"Hellion";"Factory";155;2
"Unit";"Medivac";"Starport";158;2
"Unit";"Medivac";"Starport";158;2
"Building";"EngineeringBay";NA;165;0
"Unit";"Hellion";"Factory";168;2
"Unit";"Hellion";"Factory";168;2
"Unit";"Thor";"Factory";165;6
"Unit";"Thor";"Factory";168;6
"Unit";"Hellion";"Factory";181;2
"Unit";"Hellion";"Factory";181;2
"Unit";"Hellion";"Factory";194;2
"Unit";"Medivac";"Starport";188;2
"Building";"SensorTower";NA;201;0
"Unit";"Hellion";"Factory";198;2
"Upgrade";"TerranVehicleWeaponsLevel2";"Armory";165;0
"Unit";"Hellion";"Factory";210;2
"Building";"Factory";NA;201;0
"Building";"Factory";NA;201;0
"Unit";"Hellion";"Factory";213;2
"Unit";"Hellion";"Factory";214;2
"Unit";"Hellion";"Factory";216;2
"Unit";"Hellion";"Factory";216;2
"Unit";"Hellion";"Factory";216;2
"Unit";"Hellion";"Factory";220;2
"Unit";"Hellion";"Factory";223;2
"Unit";"Hellion";"Factory";227;2
"Unit";"Hellion";"Factory";234;2
"Unit";"Hellion";"Factory";236;2
"Unit";"Hellion";"Factory";236;2
"Unit";"Hellion";"Factory";238;2
"Unit";"Hellion";"Factory";238;2
"Unit";"Hellion";"Factory";240;2
"Unit";"Medivac";"Starport";242;2
"Unit";"Medivac";"Starport";242;2
"Unit";"Hellion";"Factory";249;2
"Unit";"Hellion";"Factory";249;2
"Unit";"Hellion";"Factory";255;2
"Building";"FactoryTechLab";NA;263;0
"Building";"FactoryTechLab";NA;263;0
"Unit";"Thor";"Factory";255;6
"Building";"SensorTower";NA;267;0
"Building";"SensorTower";NA;267;0
"Unit";"Thor";"Factory";267;6
"Unit";"Hellion";"Factory";276;2
"Unit";"Hellion";"Factory";276;2
"Unit";"Hellion";"Factory";276;2
"Unit";"Hellion";"Factory";282;2
"Unit";"Hellion";"Factory";282;2
"Unit";"Hellion";"Factory";282;2
"Unit";"Hellion";"Factory";286;2
"Unit";"Hellion";"Factory";294;2
"Unit";"Hellion";"Factory";294;2
"Building";"SensorTower";NA;294;0
"Building";"CommandCenter";NA;276;0
"Unit";"Hellion";"Factory";294;2
"Unit";"Hellion";"Factory";300;2
"Unit";"Hellion";"Factory";300;2
"Unit";"Hellion";"Factory";302;2
"Unit";"Medivac";"Starport";300;2
"Unit";"Medivac";"Starport";300;2
"Unit";"Hellion";"Factory";302;2
"Unit";"Hellion";"Factory";302;2
"Building";"Refinery";NA;306;0
"Building";"Refinery";NA;312;0
"Unit";"Hellion";"Factory";316;2
"Unit";"Thor";"Factory";312;6
"Building";"Starport";NA;316;0
"Building";"Starport";NA;316;0
"Unit";"Hellion";"Factory";316;2
"Unit";"Hellion";"Factory";316;2
