"type";"unit_name";"on_building";"total_supply_lag";"supply"
"Building";"Refinery";NA;15;0
"Building";"Barracks";NA;16;0
"Unit";"Reaper";"Barracks";19;1
"Building";"CommandCenter";NA;20;0
"Building";"Factory";NA;20;0
"Building";"BarracksReactor";NA;21;0
"Building";"Refinery";NA;22;0
"Building";"Starport";NA;24;0
"Unit";"Hellion";"Factory";25;2
"Unit";"Hellion";"Factory";27;2
"Building";"BarracksTechLab";NA;29;0
"Unit";"Hellion";"Factory";30;2
"Unit";"Hellion";"Factory";32;2
"Unit";"Medivac";"Starport";37;2
"Building";"Armory";NA;39;0
"Unit";"Hellion";"Factory";41;2
"Unit";"Hellion";"Factory";43;2
"Unit";"Hellion";"Factory";49;2
"Unit";"Hellion";"Factory";51;2
"Building";"BarracksTechLab";NA;53;0
"Unit";"Banshee";"Starport";54;3
"Unit";"Marine";"Barracks";59;1
"Building";"CommandCenter";NA;64;0
"Unit";"Marine";"Barracks";65;1
"Unit";"Banshee";"Starport";67;3
"Upgrade";"Stimpack";"TechLab";70;0
"Building";"FactoryReactor";NA;71;0
"Unit";"Marine";"Barracks";72;1
"Building";"Barracks";NA;73;0
"Building";"Barracks";NA;74;0
"Building";"Refinery";NA;75;0
"Building";"Refinery";NA;75;0
"Building";"EngineeringBay";NA;75;0
"Building";"EngineeringBay";NA;75;0
"Unit";"Marine";"Barracks";77;1
"Building";"StarportReactor";NA;80;0
"Unit";"Marine";"Barracks";84;1
"Unit";"Marine";"Barracks";85;1
"Unit";"Marine";"Barracks";89;1
"Unit";"Marine";"Barracks";90;1
"Unit";"Marine";"Barracks";91;1
"Unit";"Marine";"Barracks";93;1
"Unit";"Marine";"Barracks";94;1
"Unit";"Medivac";"Starport";96;2
"Unit";"Medivac";"Starport";98;2
"Upgrade";"TerranInfantryWeaponsLevel1";"EngineeringBay";100;0
"Unit";"Marine";"Barracks";102;1
"Unit";"Marine";"Barracks";103;1
"Unit";"Marine";"Barracks";104;1
"Unit";"Marine";"Barracks";105;1
"Unit";"Marine";"Barracks";106;1
"Unit";"Marine";"Barracks";109;1
"Unit";"Marine";"Barracks";110;1
"Unit";"Marine";"Barracks";111;1
"Unit";"Marine";"Barracks";112;1
"Unit";"Marine";"Barracks";114;1
"Unit";"Marine";"Barracks";117;1
"Unit";"Marine";"Barracks";119;1
"Unit";"Marine";"Barracks";121;1
"Unit";"Marine";"Barracks";122;1
"Building";"Refinery";NA;123;0
"Unit";"Marine";"Barracks";123;1
"Unit";"Medivac";"Starport";124;2
"Unit";"Medivac";"Starport";126;2
"Unit";"Marine";"Barracks";131;1
"Unit";"Marine";"Barracks";132;1
"Unit";"Marine";"Barracks";133;1
"Unit";"Marine";"Barracks";135;1
"Building";"Barracks";NA;136;0
"Building";"Barracks";NA;136;0
"Building";"Refinery";NA;138;0
"Unit";"Marine";"Barracks";139;1
"Unit";"Marine";"Barracks";140;1
"Unit";"Marine";"Barracks";143;1
"Unit";"Marine";"Barracks";144;1
"Unit";"Marine";"Barracks";145;1
"Unit";"Marine";"Barracks";146;1
"Unit";"Marine";"Barracks";149;1
"Building";"Factory";NA;151;0
"Unit";"Marine";"Barracks";151;1
"Building";"BarracksReactor";NA;152;0
"Building";"BarracksReactor";NA;152;0
"Unit";"Marine";"Barracks";153;1
"Unit";"Marine";"Barracks";154;1
"Unit";"Marine";"Barracks";155;1
"Upgrade";"TerranInfantryWeaponsLevel2";"EngineeringBay";156;0
"Upgrade";"TerranVehicleWeaponsLevel1";"Armory";156;0
"Unit";"Liberator";"Starport";156;3
"Unit";"Liberator";"Starport";159;3
"Unit";"Marine";"Barracks";162;1
"Unit";"Marine";"Barracks";164;1
"Unit";"Marine";"Barracks";165;1
"Unit";"Marine";"Barracks";166;1
"Unit";"Marine";"Barracks";167;1
"Unit";"Marine";"Barracks";168;1
"Unit";"Marine";"Barracks";169;1
"Unit";"Marine";"Barracks";170;1
"Unit";"Marine";"Barracks";171;1
"Unit";"Marine";"Barracks";172;1
"Building";"FactoryTechLab";NA;173;0
"Building";"CommandCenter";NA;173;0
"Unit";"Marine";"Barracks";173;1
"Unit";"Marine";"Barracks";174;1
"Unit";"Marine";"Barracks";175;1
"Unit";"Marine";"Barracks";176;1
"Unit";"Marine";"Barracks";177;1
"Unit";"Marine";"Barracks";178;1
"Unit";"Marine";"Barracks";179;1
"Unit";"Marine";"Barracks";180;1
"Unit";"Marine";"Barracks";181;1
"Unit";"Marine";"Barracks";182;1
"Unit";"Marine";"Barracks";183;1
"Unit";"Medivac";"Starport";184;2
"Unit";"Medivac";"Starport";186;2
"Unit";"Marine";"Barracks";188;1
"Unit";"Marine";"Barracks";189;1
"Unit";"Marine";"Barracks";190;1
"Unit";"Marine";"Barracks";191;1
"Unit";"Marine";"Barracks";192;1
"Unit";"Marine";"Barracks";193;1
"Unit";"Marine";"Barracks";194;1
"Unit";"Marine";"Barracks";195;1
"Unit";"Marine";"Barracks";196;1
"Unit";"Marine";"Barracks";197;1
"Building";"Barracks";NA;198;0
"Unit";"Marine";"Barracks";198;1
"Unit";"Marine";"Barracks";199;1
"Building";"Barracks";NA;200;0
"Unit";"Marine";"Barracks";200;1
"Building";"Barracks";NA;201;0
"Unit";"Marine";"Barracks";201;1
"Unit";"Marine";"Barracks";202;1
"Unit";"Marine";"Barracks";203;1
"Unit";"Marine";"Barracks";204;1
"Unit";"Medivac";"Starport";205;2
"Unit";"Medivac";"Starport";207;2
"Unit";"Marine";"Barracks";209;1
"Unit";"Marine";"Barracks";210;1
"Unit";"Marine";"Barracks";211;1
"Unit";"Marine";"Barracks";212;1
"Unit";"Marine";"Barracks";213;1
"Unit";"Marine";"Barracks";214;1
"Unit";"Marine";"Barracks";215;1
"Unit";"Marine";"Barracks";216;1
"Unit";"Marine";"Barracks";217;1
"Unit";"Marauder";"Barracks";218;2
"Unit";"Marine";"Barracks";220;1
"Unit";"Medivac";"Starport";221;2
"Unit";"Medivac";"Starport";223;2
"Unit";"Marine";"Barracks";225;1
"Unit";"Marine";"Barracks";226;1
"Unit";"Marine";"Barracks";227;1
"Unit";"Marine";"Barracks";228;1
"Upgrade";"TerranInfantryWeaponsLevel3";"EngineeringBay";229;0
"Unit";"Marine";"Barracks";229;1
"Unit";"Marine";"Barracks";230;1
"Unit";"Marine";"Barracks";231;1
"Unit";"Marine";"Barracks";232;1
"Building";"Starport";NA;234;0
"Building";"Starport";NA;234;0
"Unit";"Marine";"Barracks";234;1
"Unit";"Medivac";"Starport";235;2
"Unit";"Medivac";"Starport";237;2
"Unit";"Marine";"Barracks";239;1
"Unit";"Marine";"Barracks";240;1
"Unit";"Marine";"Barracks";241;1
"Building";"Refinery";NA;242;0
"Building";"Refinery";NA;242;0
"Unit";"Marine";"Barracks";242;1
"Unit";"Marine";"Barracks";243;1
"Unit";"Marine";"Barracks";244;1
"Unit";"Marine";"Barracks";245;1
"Unit";"Marine";"Barracks";246;1
"Unit";"Marine";"Barracks";247;1
"Unit";"Marine";"Barracks";248;1
"Unit";"Marine";"Barracks";249;1
"Unit";"Marine";"Barracks";250;1
"Building";"BarracksTechLab";NA;251;0
"Building";"BarracksTechLab";NA;251;0
"Unit";"Marine";"Barracks";251;1
"Unit";"Marine";"Barracks";252;1
"Building";"StarportReactor";NA;253;0
"Building";"StarportReactor";NA;253;0
"Unit";"Marauder";"Barracks";253;2
"Unit";"Marine";"Barracks";255;1
"Unit";"Marine";"Barracks";256;1
"Unit";"Marine";"Barracks";257;1
"Unit";"Marine";"Barracks";258;1
"Unit";"Marauder";"Barracks";259;2
"Unit";"Marine";"Barracks";261;1
"Unit";"Marauder";"Barracks";262;2
"Building";"CommandCenter";NA;264;0
"Unit";"Marine";"Barracks";264;1
"Unit";"Medivac";"Starport";265;2
"Unit";"Medivac";"Starport";267;2
"Unit";"Marauder";"Barracks";269;2
"Unit";"Marine";"Barracks";271;1
"Unit";"Marine";"Barracks";272;1
"Unit";"Marine";"Barracks";273;1
"Unit";"Marauder";"Barracks";274;2
"Unit";"Marine";"Barracks";276;1
"Unit";"Marine";"Barracks";277;1
"Unit";"Marine";"Barracks";278;1
"Unit";"Marine";"Barracks";279;1
"Unit";"Marine";"Barracks";280;1
"Unit";"Marine";"Barracks";281;1
"Unit";"Marauder";"Barracks";282;2
"Unit";"Marine";"Barracks";284;1
"Unit";"Marine";"Barracks";285;1
"Unit";"Marine";"Barracks";286;1
"Unit";"Marauder";"Barracks";287;2
"Unit";"Marauder";"Barracks";289;2
"Unit";"Marauder";"Barracks";291;2
"Upgrade";"TerranShipWeaponsLevel1";"Armory";293;0
"Unit";"Marine";"Barracks";293;1
"Unit";"Marine";"Barracks";294;1
"Unit";"Marine";"Barracks";295;1
"Unit";"Marine";"Barracks";296;1
"Unit";"Marine";"Barracks";297;1
"Unit";"Marine";"Barracks";298;1
"Unit";"Marine";"Barracks";299;1
"Unit";"Marine";"Barracks";300;1
"Unit";"Marauder";"Barracks";301;2
"Unit";"Marine";"Barracks";303;1
"Unit";"Marauder";"Barracks";304;2
"Unit";"Marine";"Barracks";306;1
"Unit";"Marine";"Barracks";307;1
"Unit";"Marine";"Barracks";308;1
"Unit";"Marine";"Barracks";309;1
"Unit";"Marauder";"Barracks";310;2
"Unit";"Medivac";"Starport";312;2
"Building";"BarracksTechLab";NA;314;0
"Building";"GhostAcademy";NA;314;0
"Unit";"Marine";"Barracks";314;1
"Building";"Armory";NA;315;0
"Unit";"Marine";"Barracks";315;1
"Unit";"Marine";"Barracks";316;1
"Unit";"Marauder";"Barracks";317;2
"Unit";"Marine";"Barracks";319;1
"Unit";"Marine";"Barracks";320;1
"Unit";"Marine";"Barracks";321;1
"Unit";"Marine";"Barracks";322;1
"Unit";"Marine";"Barracks";323;1
"Unit";"Marauder";"Barracks";324;2
"Unit";"Marine";"Barracks";326;1
"Unit";"Marauder";"Barracks";327;2
"Unit";"Marine";"Barracks";329;1
"Building";"CommandCenter";NA;330;0
"Unit";"Marine";"Barracks";330;1
"Unit";"Marine";"Barracks";331;1
"Unit";"Marine";"Barracks";332;1
"Unit";"Marauder";"Barracks";333;2
"Unit";"Marauder";"Barracks";335;2
"Unit";"Marauder";"Barracks";337;2
"Unit";"Marine";"Barracks";339;1
"Unit";"Marine";"Barracks";340;1
"Unit";"Marine";"Barracks";341;1
"Unit";"Marauder";"Barracks";342;2
"Building";"CommandCenter";NA;344;0
"Unit";"Marauder";"Barracks";344;2
"Unit";"Marine";"Barracks";346;1
"Unit";"Marine";"Barracks";347;1
"Unit";"Marine";"Barracks";348;1
"Unit";"Marauder";"Barracks";349;2
"Unit";"Marine";"Barracks";351;1
"Unit";"Marauder";"Barracks";352;2
"Unit";"Marine";"Barracks";354;1
"Unit";"Marine";"Barracks";355;1
"Unit";"Marauder";"Barracks";356;2
"Unit";"Marine";"Barracks";358;1
"Unit";"Marine";"Barracks";359;1
"Unit";"Marine";"Barracks";360;1
"Unit";"Marauder";"Barracks";361;2
"Unit";"Marine";"Barracks";363;1
"Unit";"Marine";"Barracks";364;1
"Unit";"Marauder";"Barracks";365;2
"Unit";"Marauder";"Barracks";367;2
"Upgrade";"TerranVehicleWeaponsLevel2";"Armory";369;0
"Unit";"Marauder";"Barracks";369;2
"Unit";"Marine";"Barracks";371;1
"Unit";"Marine";"Barracks";372;1
"Unit";"Marauder";"Barracks";373;2
"Unit";"Marauder";"Barracks";375;2
"Unit";"Marine";"Barracks";377;1
"Unit";"Marine";"Barracks";378;1
"Unit";"Marauder";"Barracks";379;2
"Unit";"Marine";"Barracks";381;1
"Unit";"Marine";"Barracks";382;1
"Unit";"Marine";"Barracks";383;1
"Unit";"Marauder";"Barracks";384;2
"Unit";"Liberator";"Starport";386;3
"Unit";"Marauder";"Barracks";389;2
"Unit";"Marine";"Barracks";391;1
"Unit";"Marine";"Barracks";392;1
"Unit";"Liberator";"Starport";393;3
"Unit";"Marauder";"Barracks";396;2
"Unit";"Marine";"Barracks";398;1
"Unit";"Marauder";"Barracks";399;2
"Unit";"Thor";"Factory";401;6
"Unit";"Marine";"Barracks";407;1
"Unit";"Marauder";"Barracks";408;2
"Unit";"Marine";"Barracks";410;1
"Unit";"Marauder";"Barracks";411;2
"Unit";"Marine";"Barracks";413;1
"Unit";"Marine";"Barracks";414;1
"Unit";"Marine";"Barracks";415;1
"Unit";"Marine";"Barracks";416;1
"Unit";"Marine";"Barracks";417;1
"Unit";"Marine";"Barracks";418;1
"Unit";"Marine";"Barracks";419;1
"Unit";"Marauder";"Barracks";420;2
"Unit";"Marine";"Barracks";422;1
"Unit";"Medivac";"Starport";423;2
"Unit";"Medivac";"Starport";425;2
"Unit";"Medivac";"Starport";427;2
"Unit";"Marauder";"Barracks";429;2
"Unit";"Marine";"Barracks";431;1
"Unit";"Marine";"Barracks";434;1
"Unit";"Marauder";"Barracks";435;2
"Unit";"Marine";"Barracks";437;1
"Unit";"Marine";"Barracks";438;1
"Unit";"Marine";"Barracks";439;1
"Unit";"Marauder";"Barracks";440;2
"Unit";"Marine";"Barracks";442;1
"Unit";"Marine";"Barracks";443;1
"Unit";"Marauder";"Barracks";444;2
"Unit";"Marine";"Barracks";446;1
"Unit";"Marauder";"Barracks";449;2
"Unit";"Medivac";"Starport";451;2
"Unit";"Medivac";"Starport";453;2
"Unit";"Medivac";"Starport";455;2
"Unit";"Marine";"Barracks";457;1
"Unit";"Marine";"Barracks";458;1
"Unit";"Marauder";"Barracks";459;2
"Building";"Factory";NA;461;0
"Unit";"Medivac";"Starport";461;2
"Unit";"Medivac";"Starport";463;2
"Unit";"Marauder";"Barracks";465;2
"Unit";"Marine";"Barracks";467;1
"Unit";"Marine";"Barracks";468;1
"Unit";"Marine";"Barracks";469;1
"Unit";"Marauder";"Barracks";470;2
"Unit";"Marauder";"Barracks";472;2
"Unit";"Marine";"Barracks";474;1
"Unit";"Marine";"Barracks";475;1
"Unit";"Marauder";"Barracks";476;2
"Unit";"Marine";"Barracks";478;1
"Unit";"Marine";"Barracks";479;1
"Unit";"Marine";"Barracks";480;1
"Unit";"Marine";"Barracks";481;1
"Unit";"Marine";"Barracks";482;1
"Unit";"Marauder";"Barracks";483;2
"Unit";"Marine";"Barracks";485;1
"Building";"GhostAcademy";NA;486;0
"Building";"CommandCenter";NA;486;0
"Building";"FactoryTechLab";NA;486;0
"Unit";"Marauder";"Barracks";486;2
"Unit";"Marine";"Barracks";488;1
"Building";"Barracks";NA;489;0
"Building";"Barracks";NA;489;0
"Building";"Barracks";NA;489;0
"Building";"Barracks";NA;489;0
"Unit";"Marauder";"Barracks";489;2
"Unit";"Marine";"Barracks";491;1
"Unit";"Marine";"Barracks";492;1
"Unit";"Marauder";"Barracks";493;2
"Unit";"Marine";"Barracks";495;1
"Upgrade";"TerranVehicleWeaponsLevel3";"Armory";496;0
"Unit";"Marauder";"Barracks";496;2
"Unit";"Marine";"Barracks";498;1
"Unit";"Marine";"Barracks";499;1
"Unit";"Marauder";"Barracks";500;2
"Unit";"Marine";"Barracks";502;1
"Unit";"Marine";"Barracks";503;1
"Unit";"Marine";"Barracks";504;1
"Unit";"Marine";"Barracks";505;1
"Unit";"Marauder";"Barracks";506;2
"Unit";"Marauder";"Barracks";508;2
"Unit";"Marine";"Barracks";510;1
"Unit";"Marine";"Barracks";511;1
"Unit";"Marine";"Barracks";512;1
"Unit";"Marauder";"Barracks";513;2
"Unit";"Medivac";"Starport";515;2
"Unit";"Medivac";"Starport";517;2
"Unit";"Marine";"Barracks";519;1
"Unit";"Marine";"Barracks";520;1
"Building";"Refinery";NA;521;0
"Building";"Refinery";NA;521;0
"Building";"MissileTurret";NA;521;0
"Unit";"Marine";"Barracks";521;1
"Unit";"Marauder";"Barracks";522;2
"Unit";"Marine";"Barracks";524;1
"Unit";"Marauder";"Barracks";525;2
"Unit";"Marine";"Barracks";527;1
"Building";"FactoryTechLab";NA;528;0
"Unit";"Marauder";"Barracks";528;2
"Unit";"Marine";"Barracks";530;1
"Unit";"Marauder";"Barracks";531;2
"Unit";"Marine";"Barracks";533;1
"Unit";"Marine";"Barracks";534;1
"Unit";"Marine";"Barracks";535;1
"Unit";"Marine";"Barracks";536;1
"Unit";"Marine";"Barracks";537;1
"Unit";"Marine";"Barracks";538;1
"Unit";"Marauder";"Barracks";539;2
"Unit";"Marine";"Barracks";541;1
"Unit";"Marauder";"Barracks";542;2
"Unit";"Marine";"Barracks";544;1
"Unit";"Marauder";"Barracks";545;2
"Unit";"Marine";"Barracks";547;1
"Unit";"Marine";"Barracks";548;1
"Unit";"Marine";"Barracks";549;1
"Unit";"Marine";"Barracks";550;1
"Unit";"Marauder";"Barracks";551;2
"Unit";"Marine";"Barracks";553;1
"Unit";"Marine";"Barracks";554;1
"Unit";"Marine";"Barracks";555;1
"Unit";"Marine";"Barracks";556;1
"Unit";"Marine";"Barracks";557;1
"Unit";"Marine";"Barracks";558;1
"Unit";"Marine";"Barracks";559;1
"Unit";"Marine";"Barracks";560;1
"Unit";"Marauder";"Barracks";561;2
"Unit";"Marine";"Barracks";563;1
"Unit";"Marauder";"Barracks";564;2
"Unit";"Marine";"Barracks";566;1
"Unit";"Marine";"Barracks";567;1
"Unit";"Marine";"Barracks";568;1
"Unit";"Marine";"Barracks";569;1
"Unit";"Marine";"Barracks";570;1
"Unit";"Marauder";"Barracks";571;2
"Unit";"Marine";"Barracks";573;1
"Unit";"Marine";"Barracks";574;1
"Unit";"Marauder";"Barracks";575;2
"Unit";"Marauder";"Barracks";577;2
"Unit";"Marine";"Barracks";579;1
"Unit";"Marine";"Barracks";580;1
"Unit";"Marauder";"Barracks";581;2
"Unit";"Marauder";"Barracks";583;2
"Unit";"Marine";"Barracks";585;1
"Unit";"Marauder";"Barracks";586;2
"Unit";"Marauder";"Barracks";588;2
"Unit";"Marine";"Barracks";590;1
"Unit";"Marine";"Barracks";591;1
"Unit";"Marine";"Barracks";592;1
"Unit";"Marine";"Barracks";593;1
"Unit";"Marine";"Barracks";594;1
"Unit";"Marine";"Barracks";595;1
"Unit";"Marauder";"Barracks";596;2
"Unit";"Marine";"Barracks";598;1
"Unit";"Marine";"Barracks";599;1
"Unit";"Marine";"Barracks";600;1
"Unit";"Marauder";"Barracks";601;2
"Unit";"Marine";"Barracks";603;1
"Unit";"Marauder";"Barracks";604;2
"Unit";"Marine";"Barracks";606;1
"Unit";"Marine";"Barracks";607;1
"Unit";"Marauder";"Barracks";608;2
"Unit";"Marine";"Barracks";610;1
"Unit";"Marine";"Barracks";611;1
"Unit";"Marine";"Barracks";612;1
"Unit";"Marauder";"Barracks";613;2
"Unit";"Marine";"Barracks";615;1
"Unit";"Marine";"Barracks";616;1
"Unit";"Marine";"Barracks";617;1
"Unit";"Marine";"Barracks";618;1
"Unit";"Marine";"Barracks";619;1
"Unit";"Marine";"Barracks";620;1
"Unit";"Marine";"Barracks";621;1
"Unit";"Marine";"Barracks";622;1
"Unit";"Marine";"Barracks";627;1
"Unit";"Marine";"Barracks";628;1
"Unit";"Marine";"Barracks";629;1
"Unit";"Marauder";"Barracks";630;2
"Unit";"Marine";"Barracks";632;1
"Unit";"Marine";"Barracks";633;1
"Unit";"Marauder";"Barracks";636;2
"Unit";"Marine";"Barracks";638;1
"Unit";"Marauder";"Barracks";639;2
"Unit";"Marine";"Barracks";641;1
"Unit";"Marauder";"Barracks";642;2
"Upgrade";"SprayTerran";NA;644;0
"Upgrade";"SprayTerran";NA;644;0
"Upgrade";"SprayTerran";NA;644;0
"Upgrade";"BansheeCloak";NA;644;0
"Upgrade";"SprayTerran";NA;644;0
"Upgrade";"TerranInfantryArmorsLevel1";NA;644;0
"Upgrade";"ShieldWall";NA;644;0
"Upgrade";"SprayTerran";NA;644;0
"Upgrade";"TerranInfantryArmorsLevel2";NA;644;0
"Upgrade";"SprayTerran";NA;644;0
"Upgrade";"SprayTerran";NA;644;0
"Upgrade";"TerranInfantryArmorsLevel3";NA;644;0
"Upgrade";"SprayTerran";NA;644;0
"Upgrade";"SprayTerran";NA;644;0
"Upgrade";"SprayTerran";NA;644;0
"Upgrade";"GhostMoebiusReactor";NA;644;0
"Upgrade";"SprayTerran";NA;644;0
"Upgrade";"SprayTerran";NA;644;0
"Upgrade";"PunisherGrenades";NA;644;0
"Upgrade";"SprayTerran";NA;644;0
"Upgrade";"SprayTerran";NA;644;0
