"Type";"UnitName";"OnBuilding";"TotalSupply";"Supply"
"Unit";"SCV";"Command Center";12;1
"Unit";"SCV";"Command Center";12;1
"Unit";"SCV";"Command Center";13;1
"Building";"SupplyDepot";NA;13;0
"Unit";"SCV";"Command Center";15;1
"Unit";"SCV";"Command Center";15;1
"Building";"Refinery";NA;15;0
"Unit";"SCV";"Command Center";16;1
"Building";"Barracks";NA;15;0
"Unit";"SCV";"Command Center";17;1
"Unit";"Reaper";"Barracks";19;1
"Unit";"SCV";"Command Center";19;1
"Unit";"SCV";"Command Center";20;1
"Building";"SupplyDepot";NA;19;0
"Unit";"Marine";"Barracks";21;1
"Unit";"SCV";"Command Center";22;1
"Building";"Refinery";NA;22;0
"Unit";"SCV";"Command Center";23;1
"Building";"Factory";NA;21;0
"Building";"CommandCenter";NA;19;0
"Unit";"SCV";"Command Center";24;1
"Building";"BarracksReactor";NA;23;0
"Unit";"SCV";"Command Center";25;1
"Unit";"SCV";"Command Center";26;1
"Building";"BarracksTechLab";NA;27;0
"Building";"Starport";NA;25;0
"Unit";"Hellion";"Factory";27;2
"Unit";"Hellion";"Factory";27;2
"Unit";"SCV";"Command Center";28;1
"Unit";"SCV";"Command Center";28;1
"Unit";"SCV";"Command Center";34;1
"Unit";"SCV";"Command Center";34;1
"Unit";"Hellion";"Factory";32;2
"Unit";"Hellion";"Factory";32;2
"Building";"BarracksTechLab";NA;34;0
"Unit";"SCV";"Command Center";36;1
"Unit";"SCV";"Command Center";36;1
"Building";"SupplyDepot";NA;34;0
"Unit";"Hellion";"Factory";36;2
"Unit";"SCV";"Command Center";42;1
"Building";"SupplyDepot";NA;40;0
"Unit";"SCV";"Command Center";42;1
"Unit";"Hellion";"Factory";42;2
"Unit";"Marine";"Barracks";42;1
"Building";"Barracks";NA;36;0
"Unit";"SCV";"Command Center";48;1
"Building";"SupplyDepot";NA;49;0
"Unit";"SCV";"Command Center";50;1
"Unit";"SCV";"Command Center";50;1
"Unit";"Banshee";"Starport";42;3
"Unit";"SCV";"Command Center";50;1
"Unit";"SCV";"Command Center";52;1
"Unit";"Marine";"Barracks";51;1
"Unit";"SCV";"Command Center";55;1
"Unit";"SCV";"Command Center";56;1
"Building";"Refinery";NA;56;0
"Building";"Refinery";NA;56;0
"Unit";"SCV";"Command Center";58;1
"Building";"FactoryReactor";NA;55;0
"Unit";"Marine";"Barracks";59;1
"Building";"EngineeringBay";NA;57;0
"Unit";"Marine";"Barracks";59;1
"Unit";"Marine";"Barracks";59;1
"Building";"EngineeringBay";NA;58;0
"Building";"CommandCenter";NA;49;0
"Unit";"Marine";"Barracks";64;1
"Unit";"Marauder";"Barracks";61;2
"Unit";"SCV";"Command Center";64;1
"Unit";"SCV";"Command Center";64;1
"Building";"Bunker";NA;61;0
"Building";"Bunker";NA;61;0
"Unit";"Banshee";"Starport";60;3
"Unit";"Marine";"Barracks";64;1
"Unit";"SCV";"Command Center";73;1
"Unit";"SCV";"Command Center";73;1
"Unit";"Marine";"Barracks";75;1
"Unit";"Marine";"Barracks";75;1
"Unit";"Marine";"Barracks";75;1
"Upgrade";"Stimpack";"TechLab";60;0
"Unit";"SCV";"Command Center";75;1
"Unit";"SCV";"Command Center";78;1
"Unit";"Marine";"Barracks";75;1
"Unit";"Marine";"Barracks";76;1
"Unit";"Marine";"Barracks";77;1
"Building";"SupplyDepot";NA;75;0
"Building";"SupplyDepot";NA;75;0
"Unit";"Medivac";"Starport";75;2
"Unit";"Medivac";"Starport";75;2
"Building";"Barracks";NA;75;0
"Unit";"Marine";"Barracks";80;1
"Unit";"Marine";"Barracks";81;1
"Unit";"Marine";"Barracks";83;1
"Building";"Barracks";NA;75;0
"Unit";"SCV";"Command Center";87;1
"Unit";"SCV";"Command Center";87;1
"Unit";"SCV";"Command Center";87;1
"Unit";"Marine";"Barracks";87;1
"Unit";"Marine";"Barracks";88;1
"Unit";"Marine";"Barracks";89;1
"Unit";"Medivac";"Starport";87;2
"Unit";"SCV";"Command Center";90;1
"Unit";"Medivac";"Starport";87;2
"Building";"SupplyDepot";NA;90;0
"Unit";"SCV";"Command Center";93;1
"Unit";"SCV";"Command Center";93;1
"Unit";"Marine";"Barracks";93;1
"Unit";"Marine";"Barracks";94;1
"Unit";"Marine";"Barracks";95;1
"Building";"BarracksReactor";NA;90;0
"Building";"BarracksReactor";NA;90;0
"Building";"Armory";NA;87;0
"Upgrade";"TerranInfantryWeaponsLevel1";"EngineeringBay";78;0
"Upgrade";"TerranInfantryArmorsLevel1";"EngineeringBay";78;0
"Building";"SupplyDepot";NA;103;0
"Unit";"Marine";"Barracks";103;1
"Unit";"Marine";"Barracks";104;1
"Unit";"Marine";"Barracks";105;1
"Unit";"SCV";"Command Center";106;1
"Unit";"SCV";"Command Center";106;1
"Building";"Barracks";NA;93;0
"Building";"SupplyDepot";NA;105;0
"Building";"Barracks";NA;93;0
"Building";"Barracks";NA;93;0
"Building";"SupplyDepot";NA;106;0
"Unit";"SCV";"Command Center";109;1
"Building";"Refinery";NA;106;0
"Building";"Refinery";NA;106;0
"Unit";"SCV";"Command Center";109;1
"Unit";"Marine";"Barracks";106;1
"Unit";"Marine";"Barracks";106;1
"Unit";"Marine";"Barracks";106;1
"Unit";"Marine";"Barracks";106;1
"Unit";"Marine";"Barracks";106;1
"Unit";"Marine";"Barracks";107;1
"Unit";"Marine";"Barracks";108;1
"Building";"BarracksTechLab";NA;111;0
"Building";"BarracksTechLab";NA;111;0
"Unit";"Marine";"Barracks";117;1
"Unit";"Marine";"Barracks";118;1
"Unit";"Marine";"Barracks";119;1
"Building";"BarracksReactor";NA;115;0
"Unit";"Marine";"Barracks";120;1
"Unit";"Marine";"Barracks";121;1
"Unit";"Marine";"Barracks";122;1
"Unit";"SCV";"Command Center";123;1
"Unit";"Marine";"Barracks";123;1
"Unit";"Marine";"Barracks";123;1
"Unit";"Marine";"Barracks";123;1
"Unit";"Marine";"Barracks";123;1
"Unit";"Marine";"Barracks";123;1
"Unit";"Marauder";"Barracks";123;2
"Unit";"Marine";"Barracks";123;1
"Unit";"Marine";"Barracks";123;1
"Unit";"Marine";"Barracks";123;1
"Unit";"Marine";"Barracks";124;1
"Unit";"Marauder";"Barracks";125;2
"Unit";"Marine";"Barracks";127;1
"Unit";"Marine";"Barracks";132;1
"Unit";"Marauder";"Barracks";134;2
"Building";"Factory";NA;123;0
"Building";"SupplyDepot";NA;138;0
"Building";"SupplyDepot";NA;138;0
"Building";"SupplyDepot";NA;140;0
"Building";"SupplyDepot";NA;140;0
"Building";"SupplyDepot";NA;141;0
"Unit";"SCV";"Command Center";144;1
"Unit";"SCV";"Command Center";144;1
"Unit";"SCV";"Command Center";144;1
"Unit";"Marine";"Barracks";144;1
"Unit";"Marine";"Barracks";144;1
"Building";"FactoryTechLab";NA;144;0
"Unit";"Marauder";"Barracks";144;2
"Unit";"Marauder";"Barracks";144;2
"Unit";"SCV";"Command Center";144;1
"Unit";"SCV";"Command Center";145;1
"Unit";"Marauder";"Barracks";144;2
"Unit";"SCV";"Command Center";146;1
"Building";"SensorTower";NA;144;0
"Unit";"Medivac";"Starport";144;2
"Unit";"Medivac";"Starport";144;2
"Unit";"Marine";"Barracks";147;1
"Unit";"Marine";"Barracks";147;1
"Unit";"Marine";"Barracks";147;1
"Unit";"SCV";"Command Center";153;1
"Unit";"SCV";"Command Center";154;1
"Upgrade";"TerranInfantryWeaponsLevel2";"EngineeringBay";122;0
"Upgrade";"TerranInfantryArmorsLevel2";"EngineeringBay";123;0
"Unit";"Marauder";"Barracks";149;2
"Unit";"Marauder";"Barracks";151;2
"Unit";"Marauder";"Barracks";155;2
"Unit";"Medivac";"Starport";158;2
"Unit";"Medivac";"Starport";158;2
"Unit";"Marauder";"Barracks";167;2
"Unit";"Marine";"Barracks";173;1
"Unit";"Marine";"Barracks";173;1
"Unit";"Marine";"Barracks";179;1
"Unit";"Marine";"Barracks";179;1
"Unit";"Marine";"Barracks";179;1
"Unit";"Marine";"Barracks";179;1
"Unit";"Marauder";"Barracks";179;2
"Unit";"Marauder";"Barracks";179;2
"Unit";"Marine";"Barracks";181;1
"Unit";"Marine";"Barracks";181;1
"Unit";"Marauder";"Barracks";179;2
"Unit";"Marine";"Barracks";181;1
"Unit";"Marine";"Barracks";181;1
"Unit";"Marine";"Barracks";181;1
"Unit";"Marine";"Barracks";182;1
"Unit";"Marine";"Barracks";183;1
"Unit";"Marine";"Barracks";184;1
"Unit";"Marine";"Barracks";189;1
"Unit";"Marine";"Barracks";190;1
"Unit";"Marine";"Barracks";193;1
"Unit";"Marine";"Barracks";194;1
"Unit";"Marauder";"Barracks";185;2
"Unit";"Marauder";"Barracks";185;2
"Unit";"Marauder";"Barracks";191;2
"Unit";"Marine";"Barracks";195;1
"Unit";"Marine";"Barracks";196;1
"Unit";"Marine";"Barracks";197;1
"Unit";"Marine";"Barracks";198;1
"Unit";"Marine";"Barracks";199;1
"Unit";"Marine";"Barracks";200;1
"Unit";"Marine";"Barracks";201;1
"Unit";"Marine";"Barracks";202;1
"Unit";"Marauder";"Barracks";203;2
"Unit";"Marauder";"Barracks";203;2
"Unit";"Marauder";"Barracks";207;2
"Unit";"Marine";"Barracks";209;1
"Building";"CommandCenter";NA;179;0
"Unit";"Marine";"Barracks";210;1
"Unit";"Marine";"Barracks";212;1
"Unit";"Marine";"Barracks";212;1
"Unit";"Marine";"Barracks";213;1
"Unit";"Marine";"Barracks";216;1
"Unit";"Marine";"Barracks";216;1
"Unit";"Marine";"Barracks";216;1
"Unit";"Marauder";"Barracks";217;2
"Unit";"Marine";"Barracks";223;1
"Unit";"Marine";"Barracks";224;1
"Unit";"Marauder";"Barracks";223;2
"Unit";"Medivac";"Starport";216;2
"Unit";"Medivac";"Starport";216;2
"Unit";"Marauder";"Barracks";223;2
"Unit";"Marauder";"Barracks";231;2
"Unit";"Marauder";"Barracks";235;2
"Unit";"Marauder";"Barracks";241;2
"Unit";"Medivac";"Starport";237;2
"Unit";"Marine";"Barracks";243;1
"Unit";"Marine";"Barracks";243;1
"Unit";"Marine";"Barracks";243;1
"Unit";"Marauder";"Barracks";243;2
"Unit";"Marine";"Barracks";249;1
"Unit";"Marine";"Barracks";249;1
"Unit";"Marine";"Barracks";249;1
"Unit";"Marine";"Barracks";249;1
"Unit";"Marine";"Barracks";249;1
"Unit";"Marauder";"Barracks";245;2
"Unit";"Marauder";"Barracks";247;2
"Unit";"SCV";"Command Center";254;1
"Unit";"SCV";"Command Center";254;1
"Unit";"Marine";"Barracks";251;1
