"Type";"UnitName";"OnBuilding";"TotalSupply";"Supply"
"Unit";"SCV";"Command Center";12;1
"Unit";"SCV";"Command Center";12;1
"Unit";"SCV";"Command Center";13;1
"Building";"SupplyDepot";NA;13;0
"Unit";"SCV";"Command Center";15;1
"Unit";"SCV";"Command Center";16;1
"Building";"Refinery";NA;15;0
"Unit";"SCV";"Command Center";16;1
"Building";"Barracks";NA;15;0
"Unit";"SCV";"Command Center";17;1
"Unit";"Reaper";"Barracks";19;1
"Unit";"SCV";"Command Center";19;1
"Building";"SupplyDepot";NA;19;0
"Unit";"Marine";"Barracks";19;1
"Unit";"SCV";"Command Center";20;1
"Unit";"SCV";"Command Center";23;1
"Building";"Refinery";NA;23;0
"Unit";"SCV";"Command Center";24;1
"Building";"BarracksReactor";NA;23;0
"Building";"CommandCenter";NA;19;0
"Building";"Factory";NA;22;0
"Unit";"SCV";"Command Center";24;1
"Unit";"SCV";"Command Center";26;1
"Building";"BarracksTechLab";NA;26;0
"Unit";"Hellion";"Factory";26;2
"Unit";"Hellion";"Factory";26;2
"Unit";"SCV";"Command Center";26;1
"Unit";"SCV";"Command Center";27;1
"Building";"Starport";NA;26;0
"Unit";"SCV";"Command Center";31;1
"Unit";"SCV";"Command Center";33;1
"Unit";"Hellion";"Factory";31;2
"Unit";"Hellion";"Factory";31;2
"Unit";"SCV";"Command Center";33;1
"Building";"BarracksTechLab";NA;33;0
"Unit";"SCV";"Command Center";34;1
"Building";"SupplyDepot";NA;33;0
"Unit";"SCV";"Command Center";41;1
"Unit";"SCV";"Command Center";41;1
"Unit";"Hellion";"Factory";40;2
"Unit";"Hellion";"Factory";41;2
"Building";"SupplyDepot";NA;41;0
"Unit";"SCV";"Command Center";42;1
"Unit";"Banshee";"Starport";34;3
"Unit";"SCV";"Command Center";51;1
"Unit";"SCV";"Command Center";51;1
"Unit";"SCV";"Command Center";53;1
"Building";"SupplyDepot";NA;51;0
"Unit";"SCV";"Command Center";53;1
"Unit";"Marine";"Barracks";53;1
"Unit";"Marine";"Barracks";53;1
"Unit";"SCV";"Command Center";53;1
"Unit";"Banshee";"Starport";51;3
"Unit";"SCV";"Command Center";55;1
"Building";"Refinery";NA;53;0
"Building";"Refinery";NA;54;0
"Building";"EngineeringBay";NA;53;0
"Building";"EngineeringBay";NA;53;0
"Unit";"SCV";"Command Center";61;1
"Unit";"SCV";"Command Center";61;1
"Unit";"Marine";"Barracks";58;1
"Unit";"Marine";"Barracks";61;1
"Unit";"SCV";"Command Center";66;1
"Building";"CommandCenter";NA;51;0
"Unit";"SCV";"Command Center";66;1
"Unit";"Marine";"Barracks";66;1
"Unit";"Marine";"Barracks";66;1
"Unit";"SCV";"Command Center";67;1
"Building";"StarportReactor";NA;63;0
"Building";"SupplyDepot";NA;66;0
"Building";"SupplyDepot";NA;66;0
"Unit";"SCV";"Command Center";70;1
"Building";"Barracks";NA;62;0
"Building";"Barracks";NA;62;0
"Unit";"Marine";"Barracks";70;1
"Unit";"Marine";"Barracks";70;1
"Unit";"SCV";"Command Center";71;1
"Unit";"SCV";"Command Center";75;1
"Unit";"Marine";"Barracks";74;1
"Unit";"Marine";"Barracks";74;1
"Unit";"Marine";"Barracks";74;1
"Unit";"SCV";"Command Center";75;1
"Unit";"Marine";"Barracks";75;1
"Unit";"Marine";"Barracks";75;1
"Building";"StarportReactor";NA;74;0
"Unit";"Marine";"Barracks";76;1
"Unit";"Marine";"Barracks";78;1
"Unit";"Marine";"Barracks";78;1
"Unit";"SCV";"Command Center";79;1
"Unit";"SCV";"Command Center";79;1
"Building";"Barracks";NA;72;0
"Building";"Barracks";NA;72;0
"Building";"SupplyDepot";NA;79;0
"Unit";"SCV";"Command Center";82;1
"Building";"SupplyDepot";NA;79;0
"Building";"SupplyDepot";NA;79;0
"Building";"SupplyDepot";NA;80;0
"Unit";"SCV";"Command Center";85;1
"Unit";"Marine";"Barracks";82;1
"Unit";"Marine";"Barracks";82;1
"Upgrade";"TerranInfantryWeaponsLevel1";"EngineeringBay";70;0
"Upgrade";"TerranInfantryArmorsLevel1";"EngineeringBay";70;0
"Unit";"Marine";"Barracks";87;1
"Unit";"SCV";"Command Center";89;1
"Unit";"SCV";"Command Center";89;1
"Unit";"Marine";"Barracks";88;1
"Unit";"Marine";"Barracks";89;1
"Unit";"Medivac";"Starport";87;2
"Unit";"Medivac";"Starport";87;2
"Unit";"Marine";"Barracks";92;1
"Unit";"Marine";"Barracks";92;1
"Building";"BarracksReactor";NA;88;0
"Unit";"SCV";"Command Center";95;1
"Unit";"SCV";"Command Center";95;1
"Building";"BarracksReactor";NA;88;0
"Building";"SupplyDepot";NA;92;0
"Unit";"Marine";"Barracks";95;1
"Unit";"Marine";"Barracks";95;1
"Unit";"Marine";"Barracks";100;1
"Unit";"Marine";"Barracks";100;1
"Unit";"SCV";"Command Center";104;1
"Unit";"SCV";"Command Center";104;1
"Unit";"Marine";"Barracks";104;1
"Unit";"Marine";"Barracks";104;1
"Unit";"Marine";"Barracks";104;1
"Unit";"Marine";"Barracks";104;1
"Unit";"Marine";"Barracks";104;1
"Unit";"Marine";"Barracks";104;1
"Unit";"Medivac";"Starport";100;2
"Unit";"Medivac";"Starport";100;2
"Building";"Armory";NA;91;0
"Unit";"SCV";"Command Center";110;1
"Unit";"SCV";"Command Center";110;1
"Building";"SupplyDepot";NA;107;0
"Unit";"Marine";"Barracks";110;1
"Unit";"Marine";"Barracks";110;1
"Unit";"Marine";"Barracks";110;1
"Building";"SupplyDepot";NA;110;0
"Unit";"Marine";"Barracks";115;1
"Unit";"Marine";"Barracks";115;1
"Unit";"SCV";"Command Center";120;1
"Unit";"Marine";"Barracks";115;1
"Building";"Refinery";NA;115;0
"Building";"Refinery";NA;115;0
"Upgrade";"Stimpack";"TechLab";86;0
"Unit";"Marine";"Barracks";129;1
"Unit";"Marine";"Barracks";129;1
"Unit";"Marine";"Barracks";129;1
"Unit";"Marine";"Barracks";129;1
"Unit";"Marine";"Barracks";129;1
"Unit";"Marine";"Barracks";129;1
"Unit";"Marine";"Barracks";129;1
"Unit";"Marine";"Barracks";129;1
"Unit";"Marauder";"Barracks";129;2
"Unit";"SCV";"Command Center";137;1
"Unit";"Marine";"Barracks";129;1
"Unit";"SCV";"Command Center";139;1
"Unit";"Marine";"Barracks";139;1
"Unit";"Marine";"Barracks";139;1
"Unit";"Marine";"Barracks";139;1
"Unit";"Marine";"Barracks";139;1
"Unit";"Marine";"Barracks";139;1
"Unit";"Marine";"Barracks";139;1
"Unit";"Marine";"Barracks";139;1
"Unit";"SCV";"Command Center";140;1
"Unit";"SCV";"Command Center";140;1
"Unit";"SCV";"Command Center";141;1
"Unit";"SCV";"Command Center";149;1
"Unit";"SCV";"Command Center";150;1
"Unit";"Marine";"Barracks";149;1
"Unit";"Marine";"Barracks";149;1
"Unit";"Marine";"Barracks";149;1
"Unit";"Marine";"Barracks";149;1
"Unit";"Marauder";"Barracks";149;2
"Building";"CommandCenter";NA;129;0
"Unit";"Marine";"Barracks";152;1
"Unit";"Marine";"Barracks";152;1
"Unit";"Marine";"Barracks";152;1
"Unit";"SCV";"Command Center";160;1
"Unit";"SCV";"Command Center";160;1
"Unit";"SCV";"Command Center";160;1
"Unit";"Marine";"Barracks";158;1
"Unit";"Marine";"Barracks";158;1
"Unit";"Marine";"Barracks";158;1
"Unit";"Marine";"Barracks";160;1
"Unit";"Marine";"Barracks";160;1
"Unit";"Marauder";"Barracks";158;2
"Unit";"SCV";"Command Center";163;1
"Unit";"Marine";"Barracks";160;1
"Unit";"Marine";"Barracks";161;1
"Unit";"Marine";"Barracks";162;1
"Unit";"Marine";"Barracks";177;1
"Unit";"Marine";"Barracks";177;1
"Unit";"Marine";"Barracks";177;1
"Unit";"Marine";"Barracks";177;1
"Unit";"Marine";"Barracks";177;1
"Unit";"Marine";"Barracks";177;1
"Unit";"Marine";"Barracks";177;1
"Unit";"Marine";"Barracks";177;1
"Unit";"Marauder";"Barracks";177;2
"Unit";"Marine";"Barracks";177;1
"Unit";"Marine";"Barracks";178;1
"Unit";"Marine";"Barracks";178;1
"Unit";"Marine";"Barracks";180;1
"Unit";"Marine";"Barracks";180;1
"Unit";"SCV";"Command Center";185;1
"Unit";"SCV";"Command Center";185;1
"Unit";"SCV";"Command Center";185;1
"Unit";"Marine";"Barracks";182;1
"Unit";"Marine";"Barracks";183;1
"Unit";"Marine";"Barracks";184;1
"Upgrade";"TerranInfantryArmorsLevel2";"EngineeringBay";151;0
"Upgrade";"TerranInfantryWeaponsLevel2";"EngineeringBay";151;0
"Unit";"SCV";"Command Center";192;1
"Unit";"SCV";"Command Center";193;1
"Unit";"Marauder";"Barracks";185;2
"Unit";"SCV";"Command Center";194;1
"Unit";"Marine";"Barracks";187;1
"Unit";"Marine";"Barracks";188;1
"Unit";"Marine";"Barracks";188;1
"Unit";"Marine";"Barracks";190;1
"Unit";"Marine";"Barracks";190;1
"Unit";"Marine";"Barracks";195;1
"Unit";"Marine";"Barracks";196;1
"Unit";"Marine";"Barracks";197;1
"Unit";"SCV";"Command Center";208;1
"Unit";"Marauder";"Barracks";199;2
"Unit";"SCV";"Command Center";208;1
"Unit";"Marine";"Barracks";203;1
"Unit";"Marine";"Barracks";204;1
"Unit";"SCV";"Command Center";211;1
"Unit";"Marine";"Barracks";211;1
"Unit";"Marine";"Barracks";211;1
"Unit";"Marine";"Barracks";211;1
"Unit";"Marine";"Barracks";211;1
"Unit";"Marine";"Barracks";211;1
"Unit";"Marine";"Barracks";211;1
"Unit";"Marine";"Barracks";212;1
"Unit";"Marine";"Barracks";217;1
"Unit";"Marine";"Barracks";217;1
"Building";"Factory";NA;208;0
"Building";"Barracks";NA;208;0
"Building";"Barracks";NA;208;0
"Unit";"Marine";"Barracks";224;1
"Unit";"Marine";"Barracks";224;1
"Unit";"Marine";"Barracks";225;1
"Unit";"Marine";"Barracks";225;1
"Unit";"Marine";"Barracks";225;1
"Unit";"Marine";"Barracks";225;1
"Unit";"Medivac";"Starport";217;2
"Unit";"Marine";"Barracks";227;1
"Unit";"SCV";"Command Center";227;1
"Unit";"Marine";"Barracks";227;1
"Unit";"Marine";"Barracks";227;1
"Unit";"SCV";"Command Center";232;1
"Unit";"SCV";"Command Center";232;1
"Unit";"SCV";"Command Center";236;1
"Unit";"Marine";"Barracks";235;1
"Unit";"Marine";"Barracks";235;1
"Unit";"Marine";"Barracks";235;1
"Unit";"SCV";"Command Center";239;1
"Unit";"SCV";"Command Center";240;1
"Unit";"Marine";"Barracks";239;1
"Unit";"Marine";"Barracks";239;1
"Unit";"Marine";"Barracks";239;1
"Unit";"Marine";"Barracks";239;1
"Unit";"Marine";"Barracks";241;1
"Unit";"SCV";"Command Center";241;1
"Unit";"SCV";"Command Center";245;1
"Unit";"SCV";"Command Center";246;1
"Unit";"Marine";"Barracks";245;1
"Unit";"Marine";"Barracks";245;1
"Unit";"Marine";"Barracks";245;1
"Unit";"Marine";"Barracks";245;1
"Unit";"Marine";"Barracks";247;1
"Unit";"SCV";"Command Center";252;1
"Upgrade";"TerranVehicleWeaponsLevel1";"Armory";211;0
"Building";"FactoryTechLab";NA;249;0
"Unit";"SCV";"Command Center";253;1
"Unit";"SCV";"Command Center";254;1
"Unit";"Marine";"Barracks";255;1
"Unit";"Marine";"Barracks";255;1
"Unit";"Marine";"Barracks";255;1
"Unit";"Marine";"Barracks";257;1
"Unit";"Marine";"Barracks";257;1
"Unit";"Marine";"Barracks";266;1
"Unit";"Marine";"Barracks";266;1
"Unit";"Marine";"Barracks";266;1
"Unit";"Marauder";"Barracks";266;2
"Unit";"Marine";"Barracks";268;1
"Unit";"Marine";"Barracks";268;1
"Unit";"Marine";"Barracks";268;1
"Unit";"SCV";"Command Center";271;1
"Unit";"SCV";"Command Center";271;1
"Unit";"SCV";"Command Center";273;1
"Unit";"SCV";"Command Center";273;1
"Unit";"Marine";"Barracks";268;1
"Unit";"Marine";"Barracks";268;1
"Building";"BarracksTechLab";NA;270;0
"Building";"BarracksTechLab";NA;270;0
"Unit";"Marine";"Barracks";271;1
"Unit";"Marine";"Barracks";271;1
"Unit";"Marine";"Barracks";271;1
"Unit";"Marauder";"Barracks";271;2
"Upgrade";"TerranInfantryArmorsLevel3";"EngineeringBay";227;0
"Unit";"Marine";"Barracks";276;1
"Unit";"Marine";"Barracks";276;1
"Unit";"Marine";"Barracks";276;1
"Unit";"Marine";"Barracks";280;1
"Unit";"SCV";"Command Center";290;1
"Unit";"SCV";"Command Center";290;1
"Unit";"Marauder";"Barracks";285;2
"Unit";"Marauder";"Barracks";287;2
"Unit";"Marauder";"Barracks";287;2
"Unit";"Marine";"Barracks";290;1
"Unit";"Marine";"Barracks";291;1
"Unit";"Marine";"Barracks";291;1
"Unit";"Liberator";"Starport";280;3
"Unit";"Marine";"Barracks";291;1
"Upgrade";"TerranInfantryWeaponsLevel3";"EngineeringBay";245;0
"Unit";"Marine";"Barracks";291;1
"Unit";"Marine";"Barracks";291;1
"Unit";"Marine";"Barracks";291;1
"Unit";"Marine";"Barracks";291;1
"Unit";"Marine";"Barracks";293;1
"Unit";"SCV";"Command Center";310;1
"Unit";"SCV";"Command Center";310;1
"Unit";"SCV";"Command Center";310;1
"Unit";"SCV";"Command Center";310;1
"Unit";"Marauder";"Barracks";302;2
"Building";"Starport";NA;291;0
"Building";"Starport";NA;291;0
"Unit";"SCV";"Command Center";311;1
"Unit";"Liberator";"Starport";302;3
"Unit";"Marauder";"Barracks";317;2
"Unit";"Marauder";"Barracks";318;2
"Building";"StarportTechLab";NA;318;0
"Unit";"Marine";"Barracks";321;1
"Unit";"Marine";"Barracks";325;1
"Unit";"Marine";"Barracks";325;1
"Unit";"Marine";"Barracks";325;1
"Unit";"Marine";"Barracks";325;1
"Unit";"Marine";"Barracks";325;1
"Unit";"Marine";"Barracks";325;1
"Unit";"Marine";"Barracks";325;1
"Unit";"Marauder";"Barracks";321;2
"Unit";"Marauder";"Barracks";321;2
"Unit";"Marauder";"Barracks";325;2
"Unit";"Liberator";"Starport";318;3
"Unit";"Marauder";"Barracks";333;2
"Unit";"Marauder";"Barracks";335;2
"Unit";"Liberator";"Starport";325;3
"Unit";"Cyclone";"Factory";342;3
"Building";"StarportReactor";NA;326;0
"Unit";"Liberator";"Starport";325;3
"Unit";"Marine";"Barracks";346;1
"Unit";"Marauder";"Barracks";346;2
"Unit";"Liberator";"Starport";342;3
"Upgrade";"TerranShipWeaponsLevel1";"Armory";339;0
"Building";"CommandCenter";NA;342;0
"Unit";"Marine";"Barracks";361;1
"Unit";"Marine";"Barracks";361;1
"Unit";"Marine";"Barracks";361;1
"Unit";"Marauder";"Barracks";361;2
"Unit";"Marauder";"Barracks";361;2
"Unit";"Marauder";"Barracks";361;2
"Unit";"Marine";"Barracks";361;1
"Unit";"Marine";"Barracks";361;1
"Unit";"Marine";"Barracks";361;1
"Unit";"Marine";"Barracks";361;1
"Unit";"Marine";"Barracks";361;1
"Unit";"Marine";"Barracks";362;1
"Unit";"Marine";"Barracks";364;1
"Unit";"Marine";"Barracks";364;1
"Unit";"Marauder";"Barracks";364;2
"Unit";"Marine";"Barracks";370;1
"Unit";"Marine";"Barracks";375;1
"Unit";"Marine";"Barracks";375;1
"Unit";"Marine";"Barracks";375;1
"Unit";"Marine";"Barracks";375;1
"Unit";"Marauder";"Barracks";375;2
"Unit";"Liberator";"Starport";361;3
"Unit";"Liberator";"Starport";361;3
"Unit";"Liberator";"Starport";361;3
"Unit";"Liberator";"Starport";361;3
"Unit";"Marauder";"Barracks";378;2
"Unit";"Liberator";"Starport";361;3
"Unit";"Marine";"Barracks";380;1
"Unit";"Marine";"Barracks";380;1
"Unit";"Marine";"Barracks";380;1
"Unit";"Marauder";"Barracks";378;2
"Unit";"Marine";"Barracks";380;1
"Unit";"Marine";"Barracks";381;1
"Unit";"Marine";"Barracks";381;1
"Unit";"Marine";"Barracks";399;1
"Unit";"Marauder";"Barracks";385;2
"Unit";"Marauder";"Barracks";399;2
"Unit";"Marauder";"Barracks";407;2
"Unit";"Marine";"Barracks";412;1
"Unit";"Marine";"Barracks";412;1
"Unit";"Marine";"Barracks";412;1
"Unit";"Marine";"Barracks";412;1
"Unit";"Marine";"Barracks";412;1
"Unit";"Marine";"Barracks";412;1
"Unit";"Marauder";"Barracks";413;2
"Unit";"Liberator";"Starport";387;3
"Unit";"Marauder";"Barracks";415;2
"Unit";"Marauder";"Barracks";417;2
"Unit";"Marine";"Barracks";425;1
"Unit";"Marine";"Barracks";425;1
"Unit";"Marine";"Barracks";425;1
"Unit";"Marine";"Barracks";425;1
"Unit";"Marine";"Barracks";425;1
"Unit";"Marine";"Barracks";425;1
"Unit";"Marine";"Barracks";425;1
"Unit";"Marine";"Barracks";425;1
"Unit";"Marauder";"Barracks";425;2
"Unit";"Marauder";"Barracks";430;2
"Unit";"Marine";"Barracks";434;1
"Unit";"Marine";"Barracks";434;1
"Unit";"Marine";"Barracks";435;1
"Unit";"Marine";"Barracks";442;1
"Unit";"Marine";"Barracks";442;1
"Unit";"Marine";"Barracks";442;1
"Unit";"Marauder";"Barracks";442;2
"Unit";"Marauder";"Barracks";444;2
"Unit";"Marine";"Barracks";447;1
"Unit";"Marine";"Barracks";448;1
"Unit";"Marine";"Barracks";449;1
"Unit";"Marine";"Barracks";449;1
"Unit";"Marine";"Barracks";449;1
"Unit";"Marine";"Barracks";449;1
"Unit";"SCV";"Command Center";462;1
"Unit";"SCV";"Command Center";462;1
"Unit";"SCV";"Command Center";462;1
"Unit";"SCV";"Command Center";463;1
"Unit";"Marine";"Barracks";464;1
"Unit";"Marine";"Barracks";464;1
"Unit";"Marine";"Barracks";464;1
"Unit";"Marine";"Barracks";464;1
"Unit";"Marine";"Barracks";464;1
"Unit";"Marine";"Barracks";464;1
"Unit";"Marine";"Barracks";464;1
"Unit";"Marine";"Barracks";464;1
"Unit";"Marine";"Barracks";464;1
