"type";"unit_name";"on_building";"total_supply";"supply"
"Building";"Refinery";NA;15;0
"Building";"Barracks";NA;15;0
"Unit";"Reaper";"Barracks";18;1
"Unit";"Marine";"Barracks";20;1
"Building";"Refinery";NA;22;0
"Building";"Factory";NA;21;0
"Building";"CommandCenter";NA;19;0
"Building";"BarracksReactor";NA;22;0
"Unit";"Marine";"Barracks";26;1
"Unit";"Hellion";"Factory";25;2
"Unit";"Hellion";"Factory";25;2
"Building";"Starport";NA;25;0
"Unit";"Marine";"Barracks";27;1
"Unit";"Hellion";"Factory";33;2
"Unit";"Hellion";"Factory";33;2
"Unit";"Marine";"Barracks";33;1
"Unit";"Medivac";"Starport";33;2
"Unit";"Hellion";"Factory";40;2
"Unit";"Hellion";"Factory";40;2
"Building";"BarracksTechLab";NA;41;0
"Building";"Armory";NA;35;0
"Unit";"Liberator";"Starport";45;3
"Unit";"Hellion";"Factory";53;2
"Unit";"Hellion";"Factory";53;2
"Unit";"Hellion";"Factory";59;2
"Unit";"Hellion";"Factory";63;2
"Building";"Refinery";NA;64;0
"Building";"Refinery";NA;64;0
"Unit";"Marine";"Barracks";72;1
"Unit";"Hellion";"Factory";72;2
"Unit";"Hellion";"Factory";72;2
"Building";"CommandCenter";NA;53;0
"Unit";"Banshee";"Starport";66;3
"Unit";"Hellion";"Factory";80;2
"Unit";"Hellion";"Factory";80;2
"Unit";"Hellion";"Factory";91;2
"Unit";"Hellion";"Factory";91;2
"Building";"BarracksTechLab";NA;92;0
"Building";"EngineeringBay";NA;92;0
"Unit";"Banshee";"Starport";86;3
"Building";"Factory";NA;91;0
"Building";"Factory";NA;92;0
"Building";"Armory";NA;92;0
"Building";"Refinery";NA;101;0
"Building";"Refinery";NA;101;0
"Unit";"Cyclone";"Factory";105;3
"Unit";"Cyclone";"Factory";105;3
"Upgrade";"TerranVehicleWeaponsLevel1";"Armory";85;0
"Building";"StarportReactor";NA;108;0
"Unit";"Hellion";"Factory";118;2
"Unit";"Hellion";"Factory";118;2
"Unit";"Hellion";"Factory";128;2
"Unit";"Hellion";"Factory";129;2
"Building";"Factory";NA;122;0
"Building";"Factory";NA;122;0
"Building";"BarracksReactor";NA;130;0
"Unit";"Hellion";"Factory";136;2
"Unit";"Hellion";"Factory";136;2
"Building";"FactoryTechLab";NA;139;0
"Building";"CommandCenter";NA;123;0
"Unit";"Hellion";"Factory";146;2
"Unit";"Hellion";"Factory";146;2
"Building";"FactoryReactor";NA;139;0
"Building";"Refinery";NA;146;0
"Building";"Refinery";NA;146;0
"Unit";"Hellion";"Factory";147;2
"Unit";"Hellion";"Factory";151;2
"Unit";"Hellion";"Factory";151;2
"Unit";"Hellion";"Factory";151;2
"Upgrade";"TerranVehicleWeaponsLevel2";"Armory";136;0
"Building";"Factory";NA;152;0
"Building";"Factory";NA;152;0
"Building";"Factory";NA;152;0
"Unit";"Hellion";"Factory";162;2
"Unit";"Hellion";"Factory";162;2
"Unit";"Hellion";"Factory";162;2
"Building";"MissileTurret";NA;170;0
"Building";"SensorTower";NA;171;0
"Building";"MissileTurret";NA;171;0
"Building";"CommandCenter";NA;162;0
"Building";"FactoryTechLab";NA;171;0
"Building";"FactoryTechLab";NA;171;0
"Unit";"Hellion";"Factory";171;2
"Unit";"Hellion";"Factory";171;2
"Unit";"Hellion";"Factory";171;2
"Unit";"Hellion";"Factory";171;2
"Unit";"Hellion";"Factory";171;2
"Building";"CommandCenter";NA;171;0
"Unit";"Hellion";"Factory";181;2
"Unit";"Hellion";"Factory";181;2
"Unit";"Hellion";"Factory";181;2
"Building";"Refinery";NA;181;0
"Building";"Refinery";NA;181;0
"Unit";"Hellion";"Factory";181;2
"Unit";"Hellion";"Factory";181;2
"Unit";"Hellion";"Factory";187;2
"Unit";"Hellion";"Factory";187;2
"Unit";"Hellion";"Factory";187;2
"Upgrade";"TerranVehicleWeaponsLevel3";"Armory";171;0
"Unit";"Hellion";"Factory";191;2
"Unit";"Hellion";"Factory";191;2
"Unit";"Hellion";"Factory";191;2
"Unit";"Hellion";"Factory";191;2
"Unit";"Hellion";"Factory";197;2
"Unit";"Hellion";"Factory";197;2
"Unit";"Hellion";"Factory";199;2
