"Type";"UnitName";"OnBuilding";"TotalSupply";"Supply"
"Unit";"SCV";"Command Center";12;1
"Unit";"SCV";"Command Center";12;1
"Unit";"SCV";"Command Center";13;1
"Building";"SupplyDepot";NA;13;0
"Building";"Refinery";NA;14;0
"Unit";"SCV";"Command Center";15;1
"Unit";"SCV";"Command Center";15;1
"Unit";"SCV";"Command Center";17;1
"Unit";"SCV";"Command Center";17;1
"Building";"Barracks";NA;15;0
"Unit";"Reaper";"Barracks";19;1
"Unit";"SCV";"Command Center";19;1
"Unit";"SCV";"Command Center";20;1
"Unit";"SCV";"Command Center";21;1
"Building";"SupplyDepot";NA;21;0
"Building";"Factory";NA;19;0
"Building";"Refinery";NA;21;0
"Building";"BarracksReactor";NA;20;0
"Unit";"SCV";"Command Center";23;1
"Building";"CommandCenter";NA;19;0
"Unit";"SCV";"Command Center";23;1
"Unit";"SCV";"Command Center";24;1
"Unit";"Hellion";"Factory";24;2
"Unit";"Hellion";"Factory";24;2
"Building";"Starport";NA;23;0
"Unit";"SCV";"Command Center";25;1
"Unit";"Hellion";"Factory";26;2
"Unit";"Hellion";"Factory";28;2
"Unit";"SCV";"Command Center";30;1
"Unit";"SCV";"Command Center";31;1
"Unit";"SCV";"Command Center";36;1
"Building";"SupplyDepot";NA;31;0
"Unit";"Hellion";"Factory";36;2
"Unit";"SCV";"Command Center";37;1
"Unit";"Hellion";"Factory";36;2
"Unit";"SCV";"Command Center";37;1
"Unit";"SCV";"Command Center";40;1
"Building";"BarracksTechLab";NA;38;0
"Unit";"SCV";"Command Center";43;1
"Unit";"SCV";"Command Center";45;1
"Building";"FactoryTechLab";NA;44;0
"Unit";"SCV";"Command Center";45;1
"Building";"SupplyDepot";NA;45;0
"Unit";"Liberator";"Starport";38;3
"Unit";"SCV";"Command Center";47;1
"Building";"Barracks";NA;43;0
"Unit";"SCV";"Command Center";51;1
"Building";"SupplyDepot";NA;48;0
"Building";"EngineeringBay";NA;48;0
"Unit";"SCV";"Command Center";53;1
"Unit";"SCV";"Command Center";54;1
"Unit";"SCV";"Command Center";54;1
"Unit";"Marine";"Barracks";54;1
"Unit";"Marine";"Barracks";54;1
"Unit";"Marine";"Barracks";54;1
"Unit";"SCV";"Command Center";54;1
"Unit";"SCV";"Command Center";55;1
"Building";"Refinery";NA;56;0
"Building";"CommandCenter";NA;48;0
"Unit";"SCV";"Command Center";59;1
"Building";"Bunker";NA;54;0
"Building";"Refinery";NA;56;0
"Building";"StarportReactor";NA;54;0
"Unit";"Marine";"Barracks";61;1
"Unit";"Marine";"Barracks";61;1
"Unit";"SCV";"Command Center";61;1
"Unit";"Marauder";"Barracks";61;2
"Unit";"SCV";"Command Center";61;1
"Building";"Bunker";NA;61;0
"Building";"Barracks";NA;54;0
"Unit";"SCV";"Command Center";64;1
"Building";"Barracks";NA;54;0
"Building";"Barracks";NA;54;0
"Unit";"SCV";"Command Center";67;1
"Unit";"SCV";"Command Center";68;1
"Unit";"Marine";"Barracks";68;1
"Unit";"Marine";"Barracks";68;1
"Unit";"Marauder";"Barracks";68;2
"Building";"SupplyDepot";NA;68;0
"Unit";"SCV";"Command Center";70;1
"Building";"BarracksTechLab";NA;69;0
"Unit";"SCV";"Command Center";70;1
"Unit";"Medivac";"Starport";68;2
"Unit";"Medivac";"Starport";68;2
"Unit";"SCV";"Command Center";75;1
"Unit";"SCV";"Command Center";76;1
"Unit";"Marine";"Barracks";76;1
"Unit";"Marine";"Barracks";76;1
"Building";"SupplyDepot";NA;75;0
"Building";"BarracksReactor";NA;69;0
"Building";"BarracksReactor";NA;70;0
"Unit";"SCV";"Command Center";81;1
"Unit";"Marauder";"Barracks";76;2
"Building";"SupplyDepot";NA;76;0
"Unit";"Marauder";"Barracks";76;2
"Unit";"SCV";"Command Center";82;1
"Unit";"SCV";"Command Center";82;1
"Unit";"SCV";"Command Center";85;1
"Unit";"Marine";"Barracks";83;1
"Unit";"SCV";"Command Center";90;1
"Upgrade";"TerranInfantryWeaponsLevel1";"EngineeringBay";61;0
"Unit";"Marine";"Barracks";91;1
"Unit";"Marine";"Barracks";91;1
"Unit";"Marine";"Barracks";91;1
"Unit";"Marine";"Barracks";91;1
"Unit";"Marine";"Barracks";92;1
"Unit";"SCV";"Command Center";94;1
"Unit";"SCV";"Command Center";94;1
"Unit";"Marauder";"Barracks";91;2
"Unit";"Marauder";"Barracks";91;2
"Upgrade";"Stimpack";"TechLab";62;0
"Unit";"SCV";"Command Center";95;1
"Unit";"Marine";"Barracks";93;1
"Unit";"SCV";"Command Center";100;1
"Unit";"SCV";"Command Center";101;1
"Unit";"Marine";"Barracks";95;1
"Unit";"Marine";"Barracks";96;1
"Unit";"Marauder";"Barracks";102;2
"Unit";"Marauder";"Barracks";104;2
"Unit";"SCV";"Command Center";112;1
"Unit";"Marine";"Barracks";108;1
"Building";"SupplyDepot";NA;108;0
"Building";"SupplyDepot";NA;112;0
"Building";"EngineeringBay";NA;112;0
"Unit";"SCV";"Command Center";118;1
"Unit";"Marine";"Barracks";118;1
"Unit";"Marine";"Barracks";118;1
"Unit";"Marine";"Barracks";118;1
"Unit";"Marine";"Barracks";118;1
"Unit";"Marine";"Barracks";118;1
"Unit";"SCV";"Command Center";118;1
"Unit";"SCV";"Command Center";118;1
"Building";"SupplyDepot";NA;118;0
"Unit";"Marauder";"Barracks";118;2
"Unit";"SCV";"Command Center";118;1
"Unit";"Marine";"Barracks";118;1
"Building";"SupplyDepot";NA;118;0
"Unit";"Marauder";"Barracks";118;2
"Building";"Armory";NA;112;0
"Unit";"SCV";"Command Center";124;1
"Unit";"SCV";"Command Center";124;1
"Building";"SupplyDepot";NA;119;0
"Unit";"Marine";"Barracks";119;1
