"type";"unit_name";"on_building";"total_supply";"supply"
"Building";"Refinery";NA;14;0
"Building";"Barracks";NA;15;0
"Unit";"Reaper";"Barracks";19;1
"Building";"Refinery";NA;21;0
"Building";"BarracksReactor";NA;20;0
"Building";"Factory";NA;19;0
"Building";"CommandCenter";NA;19;0
"Building";"BarracksTechLab";NA;23;0
"Unit";"Hellion";"Factory";23;2
"Unit";"Hellion";"Factory";23;2
"Building";"Starport";NA;23;0
"Unit";"Hellion";"Factory";29;2
"Unit";"Hellion";"Factory";29;2
"Unit";"Hellion";"Factory";36;2
"Unit";"Hellion";"Factory";37;2
"Unit";"Hellion";"Factory";44;2
"Unit";"Liberator";"Starport";41;3
"Building";"Refinery";NA;50;0
"Building";"Refinery";NA;51;0
"Unit";"Cyclone";"Factory";52;3
"Unit";"Cyclone";"Factory";52;3
"Unit";"Banshee";"Starport";55;3
"Unit";"Cyclone";"Factory";65;3
"Unit";"Cyclone";"Factory";65;3
"Building";"CommandCenter";NA;55;0
"Unit";"Hellion";"Factory";71;2
"Unit";"Hellion";"Factory";71;2
"Building";"Armory";NA;65;0
"Building";"Armory";NA;65;0
"Building";"BarracksTechLab";NA;85;0
"Building";"StarportReactor";NA;79;0
"Building";"Refinery";NA;85;0
"Building";"Refinery";NA;85;0
"Building";"Factory";NA;79;0
"Building";"Factory";NA;79;0
"Unit";"Hellion";"Factory";86;2
"Unit";"Hellion";"Factory";86;2
"Unit";"Hellion";"Factory";97;2
"Unit";"Hellion";"Factory";97;2
"Unit";"Thor";"Factory";92;6
"Unit";"Thor";"Factory";94;6
"Unit";"Medivac";"Starport";99;2
"Unit";"Medivac";"Starport";99;2
"Building";"EngineeringBay";NA;99;0
"Unit";"Hellion";"Factory";119;2
"Upgrade";"TerranVehicleWeaponsLevel1";"Armory";94;0
"Unit";"Hellion";"Factory";126;2
"Building";"Factory";NA;112;0
"Building";"Factory";NA;112;0
"Unit";"Hellion";"Factory";130;2
"Unit";"Medivac";"Starport";127;2
"Unit";"Medivac";"Starport";127;2
"Unit";"Hellion";"Factory";131;2
"Unit";"Hellion";"Factory";135;2
"Unit";"Hellion";"Factory";135;2
"Unit";"Hellion";"Factory";135;2
"Unit";"Hellion";"Factory";141;2
"Unit";"Hellion";"Factory";143;2
"Unit";"Hellion";"Factory";145;2
"Unit";"Hellion";"Factory";147;2
"Building";"SensorTower";NA;149;0
"Unit";"Medivac";"Starport";145;2
"Unit";"Medivac";"Starport";145;2
"Unit";"Hellion";"Factory";149;2
"Unit";"Hellion";"Factory";151;2
"Unit";"Hellion";"Factory";153;2
"Unit";"Hellion";"Factory";155;2
"Unit";"Hellion";"Factory";165;2
"Building";"FactoryTechLab";NA;169;0
"Unit";"Hellion";"Factory";169;2
"Unit";"Hellion";"Factory";169;2
"Unit";"Medivac";"Starport";165;2
"Building";"CommandCenter";NA;149;0
"Unit";"Hellion";"Factory";171;2
"Unit";"Hellion";"Factory";179;2
"Unit";"Hellion";"Factory";179;2
"Unit";"Hellion";"Factory";179;2
"Building";"Refinery";NA;179;0
"Building";"Refinery";NA;179;0
"Unit";"Hellion";"Factory";179;2
"Unit";"Hellion";"Factory";179;2
"Building";"SensorTower";NA;185;0
"Upgrade";"TerranVehicleWeaponsLevel2";"Armory";169;0
"Unit";"Hellion";"Factory";185;2
"Unit";"Hellion";"Factory";191;2
"Unit";"Hellion";"Factory";191;2
"Unit";"Hellion";"Factory";191;2
"Unit";"Hellion";"Factory";191;2
"Building";"CommandCenter";NA;183;0
"Unit";"Hellion";"Factory";193;2
"Unit";"Hellion";"Factory";193;2
"Building";"FactoryTechLab";NA;202;0
"Building";"Factory";NA;193;0
"Building";"Factory";NA;193;0
"Unit";"Hellion";"Factory";202;2
"Unit";"Hellion";"Factory";206;2
"Unit";"Hellion";"Factory";206;2
"Unit";"Thor";"Factory";197;6
"Unit";"Thor";"Factory";199;6
"Building";"Factory";NA;202;0
"Unit";"Hellion";"Factory";206;2
"Building";"FactoryTechLab";NA;212;0
"Building";"FactoryTechLab";NA;212;0
"Unit";"Hellion";"Factory";208;2
"Unit";"Hellion";"Factory";210;2
"Unit";"Hellion";"Factory";212;2
"Unit";"Hellion";"Factory";212;2
"Unit";"Hellion";"Factory";218;2
"Building";"MissileTurret";NA;224;0
"Unit";"Hellion";"Factory";226;2
"Unit";"Hellion";"Factory";236;2
"Unit";"Thor";"Factory";228;6
"Unit";"Thor";"Factory";236;6
"Building";"SensorTower";NA;238;0
"Upgrade";"TerranShipWeaponsLevel1";"Armory";206;0
"Unit";"Hellion";"Factory";240;2
"Building";"FactoryTechLab";NA;252;0
"Unit";"Hellion";"Factory";254;2
"Unit";"Hellion";"Factory";254;2
"Unit";"Hellion";"Factory";254;2
"Unit";"Hellion";"Factory";254;2
"Unit";"Hellion";"Factory";254;2
"Unit";"Hellion";"Factory";254;2
"Building";"Refinery";NA;254;0
"Building";"Refinery";NA;254;0
"Unit";"Hellion";"Factory";254;2
"Unit";"Hellion";"Factory";256;2
"Unit";"Hellion";"Factory";264;2
"Unit";"Hellion";"Factory";266;2
"Unit";"Hellion";"Factory";266;2
"Unit";"Hellion";"Factory";266;2
"Unit";"Hellion";"Factory";268;2
"Unit";"Hellion";"Factory";270;2
"Unit";"Hellion";"Factory";274;2
"Unit";"Hellion";"Factory";274;2
"Unit";"Hellion";"Factory";274;2
"Building";"CommandCenter";NA;254;0
"Unit";"Hellion";"Factory";278;2
"Unit";"Hellion";"Factory";280;2
