"Type";"UnitName";"OnBuilding";"TotalSupply";"Supply"
"Unit";"SCV";"Command Center";12;1
"Unit";"SCV";"Command Center";12;1
"Unit";"SCV";"Command Center";13;1
"Building";"SupplyDepot";NA;13;0
"Unit";"SCV";"Command Center";15;1
"Unit";"SCV";"Command Center";15;1
"Unit";"SCV";"Command Center";16;1
"Unit";"SCV";"Command Center";17;1
"Building";"Barracks";NA;15;0
"Unit";"Marine";"Barracks";19;1
"Building";"Refinery";NA;19;0
"Unit";"Marine";"Barracks";19;1
"Unit";"SCV";"Command Center";20;1
"Building";"Refinery";NA;20;0
"Unit";"SCV";"Command Center";21;1
"Building";"SupplyDepot";NA;20;0
"Unit";"SCV";"Command Center";23;1
"Building";"BarracksReactor";NA;22;0
"Building";"CommandCenter";NA;19;0
"Unit";"SCV";"Command Center";23;1
"Unit";"SCV";"Command Center";24;1
"Unit";"SCV";"Command Center";25;1
"Building";"Factory";NA;23;0
"Building";"SupplyDepot";NA;25;0
"Unit";"SCV";"Command Center";26;1
"Unit";"SCV";"Command Center";28;1
"Unit";"SCV";"Command Center";28;1
"Building";"SupplyDepot";NA;28;0
"Unit";"Hellion";"Factory";28;2
"Unit";"Hellion";"Factory";28;2
"Building";"SupplyDepot";NA;28;0
"Building";"SupplyDepot";NA;28;0
"Unit";"SCV";"Command Center";28;1
"Unit";"SCV";"Command Center";29;1
"Building";"BarracksTechLab";NA;28;0
"Building";"SupplyDepot";NA;27;0
"Unit";"SCV";"Command Center";34;1
"Unit";"SCV";"Command Center";35;1
"Building";"Starport";NA;28;0
"Unit";"SCV";"Command Center";36;1
"Unit";"SCV";"Command Center";37;1
"Unit";"Hellion";"Factory";36;2
"Unit";"Hellion";"Factory";36;2
"Unit";"SCV";"Command Center";38;1
"Unit";"SCV";"Command Center";39;1
"Building";"Armory";NA;35;0
"Unit";"SCV";"Command Center";44;1
"Unit";"SCV";"Command Center";45;1
"Unit";"Hellion";"Factory";44;2
"Unit";"Hellion";"Factory";44;2
"Unit";"Medivac";"Starport";44;2
"Unit";"SCV";"Command Center";46;1
"Unit";"SCV";"Command Center";47;1
"Building";"Refinery";NA;46;0
"Building";"Refinery";NA;46;0
"Unit";"SCV";"Command Center";54;1
"Unit";"SCV";"Command Center";55;1
"Unit";"Hellion";"Factory";48;2
"Unit";"Hellion";"Factory";50;2
"Unit";"SCV";"Command Center";56;1
"Unit";"SCV";"Command Center";57;1
"Unit";"Hellion";"Factory";58;2
"Unit";"Hellion";"Factory";60;2
"Unit";"SCV";"Command Center";62;1
"Unit";"SCV";"Command Center";63;1
"Building";"BarracksReactor";NA;58;0
"Unit";"SCV";"Command Center";68;1
"Building";"Factory";NA;62;0
"Building";"Factory";NA;62;0
"Unit";"Banshee";"Starport";62;3
"Unit";"SCV";"Command Center";74;1
"Unit";"SCV";"Command Center";74;1
"Building";"Armory";NA;64;0
"Building";"FactoryTechLab";NA;74;0
"Building";"FactoryTechLab";NA;74;0
"Unit";"SCV";"Command Center";74;1
"Unit";"SCV";"Command Center";75;1
"Building";"CommandCenter";NA;64;0
"Building";"Refinery";NA;76;0
"Unit";"Hellion";"Factory";76;2
"Unit";"Hellion";"Factory";76;2
"Building";"Refinery";NA;76;0
"Upgrade";"TerranVehicleWeaponsLevel1";"Armory";64;0
"Building";"SupplyDepot";NA;76;0
"Building";"SupplyDepot";NA;76;0
"Building";"SupplyDepot";NA;76;0
"Unit";"Hellion";"Factory";78;2
"Unit";"Hellion";"Factory";80;2
"Unit";"Medivac";"Starport";78;2
"Unit";"Medivac";"Starport";78;2
"Unit";"Thor";"Factory";78;6
"Unit";"Hellion";"Factory";82;2
"Unit";"Hellion";"Factory";82;2
"Unit";"Hellion";"Factory";84;2
"Building";"Factory";NA;82;0
"Building";"Factory";NA;82;0
"Unit";"SCV";"Command Center";102;1
"Unit";"SCV";"Command Center";102;1
"Unit";"Hellion";"Factory";102;2
"Unit";"Hellion";"Factory";102;2
"Building";"FactoryTechLab";NA;102;0
"Building";"FactoryTechLab";NA;102;0
"Unit";"Liberator";"Starport";98;3
"Unit";"Liberator";"Starport";98;3
"Unit";"SCV";"Command Center";102;1
"Unit";"SCV";"Command Center";103;1
"Upgrade";"TerranVehicleAndShipArmorsLevel1";"Armory";82;0
"Building";"Factory";NA;102;0
"Unit";"SCV";"Command Center";116;1
"Unit";"SCV";"Command Center";116;1
"Unit";"SCV";"Command Center";116;1
"Unit";"Hellion";"Factory";116;2
"Unit";"Hellion";"Factory";116;2
"Unit";"SCV";"Command Center";116;1
"Unit";"SCV";"Command Center";117;1
"Unit";"SCV";"Command Center";118;1
"Building";"SupplyDepot";NA;116;0
"Building";"SupplyDepot";NA;116;0
"Building";"SupplyDepot";NA;116;0
"Unit";"Hellion";"Factory";123;2
"Unit";"Hellion";"Factory";123;2
"Building";"FactoryTechLab";NA;126;0
"Unit";"Hellion";"Factory";126;2
"Unit";"Hellion";"Factory";128;2
"Unit";"SCV";"Command Center";130;1
"Unit";"SCV";"Command Center";130;1
"Unit";"Hellion";"Factory";130;2
"Unit";"Hellion";"Factory";132;2
"Unit";"Hellion";"Factory";136;2
"Unit";"Hellion";"Factory";136;2
"Upgrade";"TerranVehicleWeaponsLevel2";"Armory";116;0
"Unit";"Hellion";"Factory";136;2
"Unit";"Hellion";"Factory";136;2
"Unit";"Hellion";"Factory";138;2
"Unit";"Hellion";"Factory";150;2
"Unit";"Hellion";"Factory";150;2
"Unit";"Hellion";"Factory";150;2
"Building";"CommandCenter";NA;136;0
"Unit";"Hellion";"Factory";150;2
"Unit";"Hellion";"Factory";152;2
"Upgrade";"TerranVehicleAndShipArmorsLevel2";"Armory";130;0
"Unit";"Hellion";"Factory";154;2
"Unit";"Hellion";"Factory";156;2
"Unit";"Hellion";"Factory";156;2
"Unit";"Hellion";"Factory";156;2
"Unit";"Hellion";"Factory";156;2
"Unit";"Hellion";"Factory";158;2
"Unit";"Hellion";"Factory";160;2
"Unit";"Hellion";"Factory";162;2
"Unit";"Hellion";"Factory";168;2
"Unit";"Hellion";"Factory";170;2
"Unit";"Hellion";"Factory";174;2
"Unit";"Hellion";"Factory";182;2
"Unit";"Hellion";"Factory";182;2
"Unit";"Hellion";"Factory";182;2
"Unit";"Hellion";"Factory";182;2
"Unit";"Hellion";"Factory";182;2
"Unit";"Hellion";"Factory";182;2
