"type";"unit_name";"on_building";"total_supply";"supply"
"Building";"Refinery";NA;14;0
"Building";"Barracks";NA;15;0
"Building";"BarracksTechLab";NA;19;0
"Building";"Refinery";NA;19;0
"Building";"Factory";NA;19;0
"Unit";"Marine";"Barracks";19;1
"Building";"Bunker";NA;20;0
"Unit";"Marine";"Barracks";23;1
"Building";"Starport";NA;23;0
"Unit";"Marine";"Barracks";24;1
"Unit";"Marine";"Barracks";25;1
"Unit";"Marine";"Barracks";27;1
"Unit";"Marine";"Barracks";32;1
"Building";"BarracksTechLab";NA;35;0
"Building";"CommandCenter";NA;32;0
"Unit";"Liberator";"Starport";35;3
"Building";"Factory";NA;37;0
"Building";"StarportReactor";NA;41;0
"Building";"BarracksReactor";NA;44;0
"Building";"Factory";NA;44;0
"Building";"Refinery";NA;49;0
"Building";"Refinery";NA;49;0
"Unit";"Hellion";"Factory";51;2
"Unit";"Hellion";"Factory";51;2
"Unit";"Hellion";"Factory";51;2
"Unit";"Hellion";"Factory";59;2
"Unit";"Hellion";"Factory";59;2
"Unit";"Hellion";"Factory";59;2
"Building";"Armory";NA;57;0
"Building";"Armory";NA;57;0
"Building";"CommandCenter";NA;51;0
"Unit";"Hellion";"Factory";61;2
"Unit";"Hellion";"Factory";61;2
"Unit";"Hellion";"Factory";67;2
"Unit";"Hellion";"Factory";67;2
"Building";"EngineeringBay";NA;79;0
"Unit";"Hellion";"Factory";79;2
"Unit";"Hellion";"Factory";79;2
"Unit";"Hellion";"Factory";88;2
"Unit";"Hellion";"Factory";89;2
"Building";"Refinery";NA;89;0
"Building";"Refinery";NA;89;0
"Unit";"Hellion";"Factory";89;2
"Upgrade";"TerranVehicleWeaponsLevel1";"Armory";89;0
"Unit";"Hellion";"Factory";97;2
"Unit";"Hellion";"Factory";97;2
"Unit";"Hellion";"Factory";102;2
"Unit";"Hellion";"Factory";104;2
"Unit";"Hellion";"Factory";108;2
"Unit";"Hellion";"Factory";108;2
"Building";"Factory";NA;100;0
"Building";"Factory";NA;102;0
"Building";"Refinery";NA;112;0
"Building";"Refinery";NA;112;0
"Building";"SensorTower";NA;112;0
"Building";"CommandCenter";NA;97;0
"Unit";"Cyclone";"Factory";112;3
"Unit";"Hellion";"Factory";128;2
"Unit";"Hellion";"Factory";128;2
"Building";"FactoryTechLab";NA;132;0
"Building";"FactoryTechLab";NA;132;0
"Unit";"Hellion";"Factory";128;2
"Unit";"Hellion";"Factory";130;2
"Building";"Refinery";NA;135;0
"Unit";"Hellion";"Factory";138;2
"Unit";"Hellion";"Factory";142;2
"Building";"Refinery";NA;145;0
"Building";"Refinery";NA;145;0
"Unit";"Hellion";"Factory";147;2
"Upgrade";"TerranVehicleWeaponsLevel2";"Armory";126;0
"Unit";"Hellion";"Factory";152;2
"Unit";"Hellion";"Factory";157;2
"Unit";"Hellion";"Factory";157;2
"Building";"Starport";NA;165;0
"Unit";"Thor";"Factory";165;6
"Unit";"Hellion";"Factory";165;2
"Unit";"Hellion";"Factory";165;2
"Unit";"Thor";"Factory";165;6
"Building";"StarportTechLab";NA;171;0
"Unit";"Hellion";"Factory";177;2
"Unit";"Hellion";"Factory";177;2
"Unit";"Hellion";"Factory";186;2
"Unit";"Hellion";"Factory";187;2
"Unit";"Thor";"Factory";165;6
"Unit";"Hellion";"Factory";187;2
"Unit";"Hellion";"Factory";189;2
"Unit";"Hellion";"Factory";193;2
"Unit";"Hellion";"Factory";205;2
"Unit";"Hellion";"Factory";205;2
"Building";"MissileTurret";NA;210;0
"Upgrade";"TerranVehicleWeaponsLevel3";"Armory";165;0
"Unit";"Raven";"Starport";205;2
"Unit";"Hellion";"Factory";214;2
"Unit";"Hellion";"Factory";216;2
"Unit";"Hellion";"Factory";216;2
"Unit";"Hellion";"Factory";216;2
"Building";"CommandCenter";NA;210;0
"Unit";"Raven";"Starport";214;2
"Unit";"Hellion";"Factory";224;2
"Unit";"Hellion";"Factory";224;2
"Building";"MissileTurret";NA;230;0
"Building";"MissileTurret";NA;230;0
"Unit";"Thor";"Factory";226;6
"Unit";"Thor";"Factory";226;6
"Building";"MissileTurret";NA;230;0
"Unit";"Thor";"Factory";226;6
"Building";"MissileTurret";NA;230;0
"Building";"MissileTurret";NA;230;0
"Building";"MissileTurret";NA;230;0
"Building";"MissileTurret";NA;230;0
"Building";"MissileTurret";NA;230;0
"Building";"MissileTurret";NA;230;0
"Unit";"Thor";"Factory";230;6
"Building";"MissileTurret";NA;230;0
"Building";"MissileTurret";NA;248;0
"Unit";"Thor";"Factory";230;6
"Unit";"Hellion";"Factory";254;2
"Unit";"Hellion";"Factory";263;2
"Unit";"Hellion";"Factory";263;2
"Unit";"Hellion";"Factory";263;2
"Unit";"Hellion";"Factory";265;2
"Unit";"Hellion";"Factory";267;2
"Unit";"Hellion";"Factory";269;2
"Unit";"Hellion";"Factory";269;2
"Unit";"Hellion";"Factory";270;2
"Unit";"Hellion";"Factory";272;2
"Unit";"Hellion";"Factory";274;2
"Unit";"Hellion";"Factory";276;2
"Unit";"Hellion";"Factory";280;2
"Unit";"Hellion";"Factory";281;2
"Unit";"Hellion";"Factory";281;2
"Unit";"Hellion";"Factory";283;2
"Unit";"Hellion";"Factory";287;2
"Unit";"Hellion";"Factory";289;2
"Unit";"Hellion";"Factory";291;2
"Unit";"Hellion";"Factory";301;2
