"type";"unit_name";"on_building";"total_supply";"supply"
"Building";"Refinery";NA;15;0
"Building";"Barracks";NA;15;0
"Unit";"Reaper";"Barracks";19;1
"Unit";"Marine";"Barracks";19;1
"Building";"Refinery";NA;23;0
"Building";"Factory";NA;21;0
"Building";"CommandCenter";NA;19;0
"Building";"BarracksReactor";NA;23;0
"Building";"BarracksTechLab";NA;26;0
"Unit";"Hellion";"Factory";26;2
"Unit";"Hellion";"Factory";26;2
"Building";"Starport";NA;26;0
"Unit";"Hellion";"Factory";27;2
"Unit";"Hellion";"Factory";29;2
"Unit";"Hellion";"Factory";36;2
"Unit";"Hellion";"Factory";38;2
"Unit";"Banshee";"Starport";32;3
"Unit";"Hellion";"Factory";41;2
"Unit";"Hellion";"Factory";46;2
"Unit";"Banshee";"Starport";47;3
"Unit";"Cyclone";"Factory";57;3
"Unit";"Cyclone";"Factory";57;3
"Building";"Refinery";NA;59;0
"Building";"Refinery";NA;59;0
"Building";"Armory";NA;59;0
"Unit";"Hellion";"Factory";73;2
"Unit";"Hellion";"Factory";73;2
"Building";"BarracksTechLab";NA;74;0
"Building";"CommandCenter";NA;61;0
"Building";"Factory";NA;74;0
"Building";"Factory";NA;74;0
"Unit";"Hellion";"Factory";83;2
"Unit";"Hellion";"Factory";83;2
"Building";"StarportReactor";NA;85;0
"Building";"EngineeringBay";NA;92;0
"Building";"Factory";NA;86;0
"Building";"Factory";NA;86;0
"Unit";"Hellion";"Factory";95;2
"Unit";"Hellion";"Factory";95;2
"Unit";"Thor";"Factory";93;6
"Unit";"Thor";"Factory";94;6
"Building";"Refinery";NA;97;0
"Building";"Refinery";NA;97;0
"Building";"FactoryTechLab";NA;98;0
"Building";"FactoryTechLab";NA;98;0
"Building";"MissileTurret";NA;99;0
"Building";"MissileTurret";NA;104;0
"Unit";"Medivac";"Starport";97;2
"Unit";"Medivac";"Starport";97;2
"Building";"MissileTurret";NA;105;0
"Upgrade";"TerranVehicleWeaponsLevel1";"Armory";92;0
"Unit";"Hellion";"Factory";124;2
"Unit";"Hellion";"Factory";124;2
"Unit";"Hellion";"Factory";124;2
"Unit";"Medivac";"Starport";124;2
"Unit";"Medivac";"Starport";124;2
