"type";"unit_name";"on_building";"total_supply";"supply"
"Building";"Refinery";NA;15;0
"Building";"Barracks";NA;15;0
"Unit";"Reaper";"Barracks";19;1
"Unit";"Marine";"Barracks";19;1
"Building";"Refinery";NA;21;0
"Building";"Factory";NA;21;0
"Building";"BarracksReactor";NA;23;0
"Building";"CommandCenter";NA;19;0
"Unit";"Hellion";"Factory";26;2
"Unit";"Hellion";"Factory";26;2
"Building";"BarracksTechLab";NA;27;0
"Building";"Starport";NA;26;0
"Unit";"Hellion";"Factory";28;2
"Unit";"Hellion";"Factory";30;2
"Unit";"Hellion";"Factory";35;2
"Unit";"Hellion";"Factory";39;2
"Unit";"Hellion";"Factory";47;2
"Unit";"Hellion";"Factory";49;2
"Unit";"Banshee";"Starport";49;3
"Unit";"Hellion";"Factory";56;2
"Building";"CommandCenter";NA;47;0
"Unit";"Hellion";"Factory";57;2
"Building";"Armory";NA;54;0
"Building";"Refinery";NA;62;0
"Building";"Refinery";NA;62;0
"Building";"Armory";NA;56;0
"Unit";"Hellion";"Factory";64;2
"Unit";"Raven";"Starport";64;2
"Unit";"Hellion";"Factory";72;2
"Unit";"Hellion";"Factory";72;2
"Building";"Factory";NA;68;0
"Building";"Factory";NA;68;0
"Building";"EngineeringBay";NA;77;0
"Building";"Refinery";NA;82;0
"Building";"Refinery";NA;83;0
"Building";"FactoryTechLab";NA;84;0
"Unit";"Hellion";"Factory";84;2
"Building";"StarportReactor";NA;78;0
"Unit";"Hellion";"Factory";92;2
"Unit";"Hellion";"Factory";92;2
"Unit";"Thor";"Factory";88;6
"Unit";"Thor";"Factory";90;6
"Unit";"Medivac";"Starport";92;2
"Unit";"Medivac";"Starport";92;2
"Upgrade";"TerranVehicleWeaponsLevel1";"Armory";84;0
"Unit";"Hellion";"Factory";105;2
"Unit";"Hellion";"Factory";105;2
"Building";"Factory";NA;105;0
"Building";"Factory";NA;113;0
"Building";"MissileTurret";NA;129;0
"Building";"MissileTurret";NA;130;0
"Building";"MissileTurret";NA;130;0
"Building";"MissileTurret";NA;130;0
"Building";"MissileTurret";NA;130;0
"Building";"MissileTurret";NA;130;0
"Building";"MissileTurret";NA;130;0
"Building";"CommandCenter";NA;111;0
"Building";"MissileTurret";NA;130;0
"Building";"FactoryTechLab";NA;130;0
"Building";"MissileTurret";NA;130;0
"Building";"FactoryReactor";NA;130;0
"Unit";"Thor";"Factory";130;6
"Building";"MissileTurret";NA;133;0
"Building";"Refinery";NA;136;0
"Building";"Refinery";NA;136;0
"Building";"MissileTurret";NA;143;0
"Building";"SensorTower";NA;143;0
"Building";"MissileTurret";NA;146;0
"Unit";"Thor";"Factory";143;6
"Unit";"Thor";"Factory";143;6
"Building";"MissileTurret";NA;146;0
"Building";"MissileTurret";NA;146;0
"Upgrade";"TerranVehicleWeaponsLevel2";"Armory";130;0
"Unit";"Hellion";"Factory";146;2
"Unit";"Hellion";"Factory";146;2
"Unit";"Hellion";"Factory";146;2
"Unit";"Hellion";"Factory";146;2
"Building";"MissileTurret";NA;158;0
"Building";"MissileTurret";NA;158;0
"Building";"MissileTurret";NA;166;0
"Building";"SensorTower";NA;166;0
"Unit";"Hellion";"Factory";166;2
"Unit";"Hellion";"Factory";166;2
"Unit";"Hellion";"Factory";166;2
"Unit";"Hellion";"Factory";166;2
"Building";"Factory";NA;158;0
"Building";"CommandCenter";NA;146;0
"Building";"Factory";NA;158;0
"Building";"FactoryTechLab";NA;174;0
"Unit";"Hellion";"Factory";174;2
"Unit";"Hellion";"Factory";174;2
"Unit";"Hellion";"Factory";174;2
"Building";"FactoryReactor";NA;174;0
"Unit";"Hellion";"Factory";174;2
"Unit";"Hellion";"Factory";174;2
"Building";"Starport";NA;184;0
"Building";"Starport";NA;184;0
"Building";"StarportTechLab";NA;184;0
"Building";"StarportTechLab";NA;184;0
"Upgrade";"TerranVehicleWeaponsLevel3";"Armory";174;0
"Building";"SensorTower";NA;184;0
"Building";"Starport";NA;184;0
"Building";"MissileTurret";NA;184;0
"Building";"Starport";NA;184;0
"Building";"Refinery";NA;184;0
"Building";"Refinery";NA;184;0
