"type";"unit_name";"on_building";"total_supply";"supply"
"Building";"Refinery";NA;15;0
"Building";"Barracks";NA;15;0
"Unit";"Reaper";"Barracks";19;1
"Building";"Factory";NA;19;0
"Building";"Refinery";NA;22;0
"Building";"BarracksReactor";NA;21;0
"Building";"CommandCenter";NA;19;0
"Unit";"Hellion";"Factory";24;2
"Unit";"Hellion";"Factory";24;2
"Building";"BarracksTechLab";NA;24;0
"Building";"Starport";NA;24;0
"Unit";"Hellion";"Factory";29;2
"Unit";"Hellion";"Factory";29;2
"Unit";"Hellion";"Factory";32;2
"Unit";"Hellion";"Factory";34;2
"Building";"BarracksReactor";NA;31;0
"Building";"FactoryTechLab";NA;43;0
"Unit";"Marine";"Barracks";43;1
"Unit";"Marine";"Barracks";43;1
"Unit";"Banshee";"Starport";43;3
"Unit";"Marine";"Barracks";49;1
"Building";"EngineeringBay";NA;45;0
"Unit";"Marine";"Barracks";49;1
"Building";"EngineeringBay";NA;45;0
"Building";"CommandCenter";NA;43;0
"Building";"BarracksTechLab";NA;58;0
"Building";"Refinery";NA;58;0
"Building";"Refinery";NA;58;0
"Unit";"Marine";"Barracks";62;1
"Unit";"Banshee";"Starport";58;3
"Building";"Barracks";NA;58;0
"Building";"Barracks";NA;58;0
"Unit";"Marine";"Barracks";64;1
"Building";"StarportReactor";NA;70;0
"Upgrade";"TerranInfantryWeaponsLevel1";"EngineeringBay";60;0
"Unit";"Marine";"Barracks";77;1
"Unit";"Marine";"Barracks";77;1
"Unit";"Marine";"Barracks";77;1
"Upgrade";"TerranInfantryArmorsLevel1";"EngineeringBay";60;0
"Unit";"Marine";"Barracks";77;1
"Unit";"Marine";"Barracks";77;1
"Building";"Barracks";NA;74;0
"Building";"Barracks";NA;74;0
"Unit";"Marine";"Barracks";77;1
"Building";"Bunker";NA;77;0
"Building";"Refinery";NA;83;0
"Building";"Refinery";NA;83;0
"Unit";"Marine";"Barracks";85;1
"Unit";"Marine";"Barracks";85;1
"Unit";"Marine";"Barracks";85;1
"Building";"Armory";NA;77;0
"Unit";"Marine";"Barracks";89;1
"Unit";"Marine";"Barracks";89;1
"Unit";"Marine";"Barracks";90;1
"Upgrade";"Stimpack";"TechLab";74;0
"Building";"BarracksReactor";NA;86;0
"Unit";"Marine";"Barracks";95;1
"Unit";"Marine";"Barracks";95;1
"Building";"BarracksReactor";NA;88;0
"Unit";"Marine";"Barracks";96;1
"Unit";"Marine";"Barracks";97;1
"Unit";"Marine";"Barracks";98;1
"Unit";"Marine";"Barracks";99;1
"Unit";"Marine";"Barracks";100;1
"Unit";"Marine";"Barracks";104;1
"Unit";"Marine";"Barracks";104;1
"Unit";"Marine";"Barracks";104;1
"Building";"Factory";NA;96;0
"Unit";"Marine";"Barracks";108;1
"Unit";"Marine";"Barracks";108;1
"Unit";"Marine";"Barracks";108;1
"Unit";"Medivac";"Starport";104;2
"Unit";"Medivac";"Starport";104;2
"Unit";"Marine";"Barracks";111;1
"Unit";"Marine";"Barracks";113;1
"Unit";"Marine";"Barracks";113;1
"Unit";"Marine";"Barracks";113;1
"Unit";"Marine";"Barracks";113;1
"Unit";"Marine";"Barracks";113;1
"Unit";"Marine";"Barracks";113;1
"Building";"SensorTower";NA;116;0
"Unit";"Marine";"Barracks";123;1
"Unit";"Marine";"Barracks";123;1
"Unit";"Marine";"Barracks";123;1
"Unit";"Marine";"Barracks";124;1
"Unit";"Marine";"Barracks";128;1
"Unit";"Marine";"Barracks";128;1
"Unit";"Medivac";"Starport";116;2
"Unit";"Marine";"Barracks";130;1
"Unit";"Marine";"Barracks";130;1
"Unit";"Marine";"Barracks";130;1
"Building";"CommandCenter";NA;102;0
"Unit";"Marine";"Barracks";130;1
"Unit";"Marine";"Barracks";131;1
"Unit";"Marine";"Barracks";134;1
"Unit";"Marine";"Barracks";139;1
"Unit";"Marine";"Barracks";139;1
"Unit";"Marine";"Barracks";142;1
"Unit";"Marine";"Barracks";142;1
"Unit";"Marine";"Barracks";142;1
"Unit";"Marine";"Barracks";144;1
"Unit";"Marine";"Barracks";144;1
"Unit";"Marine";"Barracks";147;1
"Unit";"Marine";"Barracks";148;1
"Upgrade";"TerranVehicleWeaponsLevel1";"Armory";113;0
"Unit";"Marine";"Barracks";155;1
"Upgrade";"TerranInfantryWeaponsLevel2";"EngineeringBay";113;0
"Upgrade";"TerranInfantryArmorsLevel2";"EngineeringBay";113;0
"Unit";"Marine";"Barracks";157;1
"Unit";"Marine";"Barracks";157;1
"Unit";"Marine";"Barracks";157;1
"Unit";"Marine";"Barracks";157;1
"Unit";"Marine";"Barracks";157;1
"Unit";"Marine";"Barracks";157;1
"Unit";"Marine";"Barracks";157;1
"Unit";"Marine";"Barracks";158;1
"Unit";"Marine";"Barracks";158;1
"Unit";"Marine";"Barracks";158;1
"Unit";"Marine";"Barracks";163;1
"Building";"SensorTower";NA;171;0
"Building";"Barracks";NA;169;0
"Building";"Factory";NA;169;0
"Building";"Barracks";NA;169;0
"Building";"Factory";NA;169;0
"Building";"Factory";NA;169;0
"Building";"Barracks";NA;169;0
"Unit";"Marine";"Barracks";171;1
"Unit";"Marine";"Barracks";171;1
"Unit";"Marine";"Barracks";171;1
"Unit";"Marine";"Barracks";171;1
"Unit";"Marine";"Barracks";171;1
"Unit";"Marine";"Barracks";171;1
"Unit";"Marine";"Barracks";171;1
"Unit";"Marauder";"Barracks";171;2
"Unit";"Marine";"Barracks";171;1
"Unit";"Marine";"Barracks";171;1
"Unit";"Marine";"Barracks";172;1
"Unit";"Marine";"Barracks";173;1
"Unit";"Marine";"Barracks";174;1
"Unit";"Marine";"Barracks";178;1
"Unit";"Marine";"Barracks";178;1
"Unit";"Marine";"Barracks";178;1
"Building";"BarracksTechLab";NA;180;0
"Building";"BarracksTechLab";NA;180;0
"Unit";"Marine";"Barracks";181;1
"Unit";"Liberator";"Starport";171;3
"Unit";"Liberator";"Starport";171;3
"Unit";"Marine";"Barracks";181;1
"Unit";"Marine";"Barracks";181;1
"Building";"FactoryTechLab";NA;181;0
"Building";"FactoryTechLab";NA;181;0
"Building";"FactoryTechLab";NA;181;0
"Unit";"Marine";"Barracks";181;1
"Unit";"Marine";"Barracks";182;1
"Unit";"Marine";"Barracks";186;1
"Unit";"Marine";"Barracks";186;1
"Unit";"Marine";"Barracks";187;1
"Unit";"Marine";"Barracks";188;1
"Unit";"Marine";"Barracks";188;1
"Unit";"Marine";"Barracks";188;1
"Unit";"Marine";"Barracks";195;1
"Unit";"Marine";"Barracks";195;1
"Unit";"Marine";"Barracks";197;1
"Unit";"Marine";"Barracks";197;1
"Unit";"Marine";"Barracks";198;1
"Unit";"Marauder";"Barracks";196;2
"Unit";"Marine";"Barracks";199;1
"Unit";"Medivac";"Starport";189;2
"Unit";"Medivac";"Starport";192;2
"Upgrade";"TerranVehicleWeaponsLevel2";"Armory";171;0
"Unit";"Marine";"Barracks";217;1
"Unit";"Marine";"Barracks";217;1
"Unit";"Marine";"Barracks";217;1
