"type";"unit_name";"on_building";"total_supply";"supply"
"Building";"Refinery";NA;14;0
"Building";"Barracks";NA;15;0
"Unit";"Reaper";"Barracks";19;1
"Building";"Refinery";NA;20;0
"Building";"Factory";NA;19;0
"Building";"BarracksReactor";NA;20;0
"Building";"CommandCenter";NA;19;0
"Building";"BarracksTechLab";NA;24;0
"Unit";"Hellion";"Factory";24;2
"Unit";"Hellion";"Factory";24;2
"Building";"Starport";NA;23;0
"Unit";"Hellion";"Factory";29;2
"Unit";"Hellion";"Factory";29;2
"Unit";"Hellion";"Factory";35;2
"Unit";"Hellion";"Factory";35;2
"Unit";"Hellion";"Factory";43;2
"Unit";"Hellion";"Factory";43;2
"Unit";"Liberator";"Starport";45;3
"Unit";"Cyclone";"Factory";55;3
"Building";"Refinery";NA;56;0
"Building";"Refinery";NA;59;0
"Unit";"Cyclone";"Factory";59;3
"Building";"CommandCenter";NA;51;0
"Unit";"Hellion";"Factory";69;2
"Unit";"Hellion";"Factory";69;2
"Building";"StarportReactor";NA;66;0
"Building";"Factory";NA;64;0
"Building";"Factory";NA;65;0
"Unit";"Hellion";"Factory";77;2
"Unit";"Hellion";"Factory";77;2
"Building";"FactoryTechLab";NA;79;0
"Unit";"Hellion";"Factory";80;2
"Unit";"Hellion";"Factory";82;2
"Building";"Armory";NA;78;0
"Building";"Armory";NA;78;0
"Unit";"Medivac";"Starport";85;2
"Unit";"Medivac";"Starport";85;2
"Building";"Refinery";NA;90;0
"Building";"Refinery";NA;90;0
"Unit";"Hellion";"Factory";92;2
"Unit";"Hellion";"Factory";92;2
"Unit";"Thor";"Factory";92;6
"Unit";"Thor";"Factory";92;6
"Unit";"Hellion";"Factory";108;2
"Unit";"Hellion";"Factory";108;2
"Building";"Factory";NA;106;0
"Building";"Factory";NA;106;0
"Unit";"Hellion";"Factory";129;2
"Unit";"Hellion";"Factory";129;2
"Building";"FactoryTechLab";NA;130;0
"Building";"FactoryTechLab";NA;130;0
"Unit";"Hellion";"Factory";136;2
"Unit";"Hellion";"Factory";136;2
"Unit";"Medivac";"Starport";132;2
"Unit";"Medivac";"Starport";132;2
"Building";"EngineeringBay";NA;138;0
"Unit";"Hellion";"Factory";138;2
"Unit";"Hellion";"Factory";138;2
"Building";"CommandCenter";NA;129;0
"Unit";"Hellion";"Factory";138;2
"Upgrade";"TerranVehicleWeaponsLevel1";"Armory";124;0
"Unit";"Hellion";"Factory";142;2
"Unit";"Hellion";"Factory";146;2
"Unit";"Medivac";"Starport";142;2
"Unit";"Medivac";"Starport";144;2
"Building";"SensorTower";NA;153;0
"Unit";"Hellion";"Factory";153;2
"Unit";"Hellion";"Factory";155;2
"Unit";"Hellion";"Factory";157;2
"Unit";"Hellion";"Factory";157;2
"Unit";"Hellion";"Factory";157;2
"Unit";"Medivac";"Starport";163;2
"Unit";"Medivac";"Starport";163;2
"Unit";"Hellion";"Factory";171;2
"Unit";"Hellion";"Factory";173;2
"Unit";"Hellion";"Factory";173;2
"Unit";"Hellion";"Factory";173;2
"Unit";"Hellion";"Factory";173;2
"Building";"SensorTower";NA;173;0
"Unit";"Hellion";"Factory";177;2
"Unit";"Hellion";"Factory";179;2
"Unit";"Hellion";"Factory";179;2
"Unit";"Hellion";"Factory";190;2
"Unit";"Hellion";"Factory";190;2
"Unit";"Hellion";"Factory";190;2
"Unit";"Hellion";"Factory";191;2
"Unit";"Hellion";"Factory";193;2
"Building";"Refinery";NA;196;0
"Building";"Refinery";NA;198;0
"Unit";"Hellion";"Factory";198;2
"Unit";"Hellion";"Factory";198;2
"Unit";"Hellion";"Factory";200;2
"Unit";"Hellion";"Factory";202;2
"Unit";"Hellion";"Factory";204;2
"Unit";"Hellion";"Factory";206;2
"Unit";"Hellion";"Factory";208;2
"Unit";"Hellion";"Factory";210;2
"Unit";"Hellion";"Factory";212;2
"Unit";"Hellion";"Factory";214;2
"Unit";"Hellion";"Factory";216;2
"Unit";"Hellion";"Factory";220;2
"Unit";"Hellion";"Factory";222;2
"Unit";"Hellion";"Factory";224;2
"Unit";"Hellion";"Factory";228;2
"Unit";"Hellion";"Factory";230;2
"Unit";"Hellion";"Factory";232;2
"Building";"CommandCenter";NA;208;0
"Unit";"Hellion";"Factory";234;2
"Unit";"Hellion";"Factory";236;2
"Unit";"Hellion";"Factory";238;2
"Unit";"Hellion";"Factory";240;2
"Upgrade";"TerranVehicleWeaponsLevel2";"Armory";200;0
"Building";"CommandCenter";NA;222;0
