"Type";"UnitName";"OnBuilding";"TotalSupply";"Supply"
"Unit";"SCV";"Command Center";12;1
"Unit";"SCV";"Command Center";12;1
"Unit";"SCV";"Command Center";13;1
"Building";"SupplyDepot";NA;13;0
"Unit";"SCV";"Command Center";15;1
"Unit";"SCV";"Command Center";15;1
"Building";"Refinery";NA;15;0
"Unit";"SCV";"Command Center";16;1
"Building";"Barracks";NA;15;0
"Unit";"SCV";"Command Center";17;1
"Unit";"Reaper";"Barracks";19;1
"Unit";"SCV";"Command Center";19;1
"Building";"SupplyDepot";NA;19;0
"Unit";"Marine";"Barracks";19;1
"Unit";"SCV";"Command Center";21;1
"Unit";"SCV";"Command Center";22;1
"Building";"Refinery";NA;22;0
"Unit";"SCV";"Command Center";23;1
"Building";"Factory";NA;21;0
"Building";"CommandCenter";NA;19;0
"Unit";"SCV";"Command Center";24;1
"Building";"BarracksReactor";NA;23;0
"Unit";"SCV";"Command Center";25;1
"Unit";"SCV";"Command Center";26;1
"Unit";"Marine";"Barracks";26;1
"Unit";"Marine";"Barracks";26;1
"Building";"FactoryTechLab";NA;26;0
"Building";"Bunker";NA;26;0
"Unit";"SCV";"Command Center";27;1
"Unit";"SCV";"Command Center";28;1
"Unit";"SCV";"Command Center";30;1
"Unit";"SCV";"Command Center";31;1
"Unit";"Marine";"Barracks";32;1
"Unit";"Marine";"Barracks";32;1
"Building";"Bunker";NA;30;0
"Unit";"SCV";"Command Center";32;1
"Building";"SupplyDepot";NA;32;0
"Unit";"SCV";"Command Center";37;1
"Unit";"SCV";"Command Center";37;1
"Unit";"SCV";"Command Center";37;1
"Unit";"SCV";"Command Center";38;1
"Building";"Starport";NA;37;0
"Unit";"Marine";"Barracks";39;1
"Unit";"SCV";"Command Center";39;1
"Unit";"SCV";"Command Center";40;1
"Unit";"SCV";"Command Center";42;1
"Unit";"SCV";"Command Center";43;1
"Building";"FactoryReactor";NA;39;0
"Building";"SupplyDepot";NA;41;0
"Unit";"Marine";"Barracks";41;1
"Unit";"Marine";"Barracks";47;1
"Unit";"SCV";"Command Center";47;1
"Unit";"SCV";"Command Center";47;1
"Building";"FactoryTechLab";NA;47;0
"Building";"SupplyDepot";NA;47;0
"Building";"SupplyDepot";NA;47;0
"Building";"Barracks";NA;46;0
"Unit";"Marine";"Barracks";50;1
"Unit";"SCV";"Command Center";50;1
"Unit";"SCV";"Command Center";50;1
"Building";"Barracks";NA;47;0
"Building";"EngineeringBay";NA;50;0
"Building";"EngineeringBay";NA;50;0
"Building";"StarportReactor";NA;50;0
"Building";"CommandCenter";NA;44;0
"Building";"Refinery";NA;50;0
"Unit";"SCV";"Command Center";53;1
"Unit";"SCV";"Command Center";53;1
"Building";"Refinery";NA;50;0
"Unit";"Marine";"Barracks";53;1
"Unit";"Marine";"Barracks";53;1
"Unit";"Marine";"Barracks";53;1
"Building";"SupplyDepot";NA;51;0
"Building";"SupplyDepot";NA;51;0
"Unit";"SCV";"Command Center";53;1
"Unit";"SCV";"Command Center";54;1
"Upgrade";"Stimpack";"TechLab";47;0
"Unit";"SCV";"Command Center";58;1
"Unit";"SCV";"Command Center";59;1
"Unit";"Marine";"Barracks";58;1
"Unit";"Marine";"Barracks";58;1
"Unit";"Marine";"Barracks";58;1
"Unit";"Marine";"Barracks";58;1
"Building";"FactoryTechLab";NA;60;0
"Unit";"Medivac";"Starport";58;2
"Unit";"Medivac";"Starport";58;2
"Unit";"Marine";"Barracks";62;1
"Building";"MissileTurret";NA;66;0
"Unit";"Marine";"Barracks";66;1
"Unit";"Marine";"Barracks";66;1
"Building";"MissileTurret";NA;66;0
"Unit";"Marine";"Barracks";71;1
"Unit";"Marine";"Barracks";71;1
"Unit";"Marine";"Barracks";73;1
"Unit";"Marine";"Barracks";73;1
"Unit";"Marine";"Barracks";73;1
"Unit";"Marine";"Barracks";73;1
"Unit";"Marine";"Barracks";75;1
"Building";"SupplyDepot";NA;75;0
"Building";"SupplyDepot";NA;75;0
"Unit";"Marine";"Barracks";75;1
"Unit";"Marine";"Barracks";75;1
"Unit";"Marine";"Barracks";77;1
"Unit";"Marine";"Barracks";78;1
"Unit";"SCV";"Command Center";80;1
"Unit";"SCV";"Command Center";80;1
"Unit";"Marine";"Barracks";79;1
"Unit";"SCV";"Command Center";80;1
"Unit";"Medivac";"Starport";77;2
"Unit";"Medivac";"Starport";77;2
"Building";"Barracks";NA;73;0
"Building";"Barracks";NA;73;0
"Unit";"Marine";"Barracks";80;1
"Unit";"Marine";"Barracks";80;1
"Unit";"SCV";"Command Center";84;1
"Unit";"SCV";"Command Center";85;1
"Unit";"SCV";"Command Center";87;1
"Unit";"Marine";"Barracks";83;1
"Unit";"Marine";"Barracks";83;1
"Unit";"Marine";"Barracks";86;1
"Unit";"SCV";"Command Center";94;1
"Unit";"Marine";"Barracks";92;1
"Unit";"Marine";"Barracks";92;1
"Unit";"SCV";"Command Center";97;1
"Unit";"SCV";"Command Center";98;1
"Building";"Armory";NA;79;0
"Upgrade";"TerranInfantryWeaponsLevel1";"EngineeringBay";71;0
"Unit";"Marine";"Barracks";97;1
"Upgrade";"TerranInfantryArmorsLevel1";"EngineeringBay";71;0
"Building";"MissileTurret";NA;99;0
"Unit";"Marine";"Barracks";100;1
"Unit";"Medivac";"Starport";92;2
"Unit";"Marine";"Barracks";101;1
"Unit";"Medivac";"Starport";96;2
"Unit";"SCV";"Command Center";105;1
"Unit";"SCV";"Command Center";105;1
"Unit";"SCV";"Command Center";105;1
"Building";"SupplyDepot";NA;105;0
"Building";"SupplyDepot";NA;106;0
"Unit";"Marine";"Barracks";109;1
"Unit";"Marine";"Barracks";109;1
"Building";"BarracksReactor";NA;100;0
"Building";"SupplyDepot";NA;106;0
"Building";"BarracksReactor";NA;101;0
"Unit";"Marine";"Barracks";114;1
"Unit";"Marine";"Barracks";114;1
"Unit";"Marine";"Barracks";115;1
"Unit";"Marine";"Barracks";115;1
"Unit";"Marine";"Barracks";116;1
"Unit";"Marine";"Barracks";117;1
"Unit";"Marine";"Barracks";117;1
"Unit";"Marine";"Barracks";120;1
"Unit";"Marine";"Barracks";120;1
"Unit";"Marine";"Barracks";120;1
"Unit";"Marine";"Barracks";120;1
"Building";"SupplyDepot";NA;122;0
"Building";"SupplyDepot";NA;122;0
"Unit";"Medivac";"Starport";120;2
"Unit";"Medivac";"Starport";120;2
"Unit";"Marine";"Barracks";124;1
"Unit";"Marine";"Barracks";124;1
"Unit";"SCV";"Command Center";134;1
"Unit";"SCV";"Command Center";134;1
"Unit";"SCV";"Command Center";134;1
"Building";"Refinery";NA;134;0
"Building";"Refinery";NA;134;0
"Unit";"Marine";"Barracks";134;1
"Unit";"Marine";"Barracks";134;1
"Unit";"Marine";"Barracks";134;1
"Unit";"Marine";"Barracks";134;1
"Unit";"SCV";"Command Center";134;1
"Unit";"Medivac";"Starport";128;2
"Unit";"Medivac";"Starport";130;2
"Unit";"Marine";"Barracks";137;1
"Unit";"Marine";"Barracks";137;1
"Unit";"Marine";"Barracks";137;1
"Unit";"Marine";"Barracks";137;1
"Unit";"Marine";"Barracks";137;1
"Unit";"SCV";"Command Center";137;1
"Unit";"SCV";"Command Center";139;1
"Unit";"Marine";"Barracks";137;1
"Unit";"Marine";"Barracks";137;1
"Unit";"Marine";"Barracks";139;1
"Unit";"Marine";"Barracks";139;1
"Building";"SensorTower";NA;146;0
"Unit";"Marine";"Barracks";146;1
"Unit";"Marine";"Barracks";147;1
"Unit";"Marine";"Barracks";148;1
"Unit";"Marine";"Barracks";148;1
"Unit";"Marine";"Barracks";150;1
"Unit";"Medivac";"Starport";142;2
"Unit";"Marine";"Barracks";153;1
"Unit";"Marine";"Barracks";153;1
"Unit";"Marine";"Barracks";155;1
"Unit";"Marine";"Barracks";155;1
"Building";"Factory";NA;146;0
"Upgrade";"TerranInfantryWeaponsLevel2";"EngineeringBay";124;0
"Upgrade";"TerranInfantryArmorsLevel2";"EngineeringBay";124;0
"Building";"CommandCenter";NA;134;0
"Unit";"Marine";"Barracks";168;1
"Unit";"Marine";"Barracks";168;1
"Unit";"Marine";"Barracks";168;1
"Unit";"Liberator";"Starport";153;3
"Unit";"Marine";"Barracks";168;1
"Unit";"Marine";"Barracks";168;1
"Unit";"Marine";"Barracks";168;1
"Unit";"Marine";"Barracks";168;1
"Unit";"Marine";"Barracks";168;1
"Unit";"Marine";"Barracks";168;1
"Unit";"Marine";"Barracks";168;1
"Unit";"Marine";"Barracks";169;1
"Unit";"Marine";"Barracks";170;1
"Unit";"Liberator";"Starport";168;3
"Unit";"Marine";"Barracks";174;1
"Unit";"Marine";"Barracks";175;1
"Unit";"Marine";"Barracks";175;1
"Unit";"Marine";"Barracks";177;1
"Unit";"Marine";"Barracks";178;1
"Unit";"Marine";"Barracks";178;1
"Unit";"Marine";"Barracks";180;1
"Unit";"Marine";"Barracks";181;1
"Unit";"Marine";"Barracks";182;1
"Building";"FactoryTechLab";NA;186;0
"Unit";"Marine";"Barracks";186;1
"Unit";"Medivac";"Starport";180;2
"Unit";"Marine";"Barracks";187;1
"Unit";"Marine";"Barracks";187;1
"Unit";"Marine";"Barracks";189;1
"Unit";"Marine";"Barracks";190;1
"Unit";"Marine";"Barracks";190;1
"Unit";"Marine";"Barracks";192;1
"Unit";"Marine";"Barracks";193;1
"Unit";"Medivac";"Starport";186;2
"Unit";"Marine";"Barracks";194;1
"Unit";"Marine";"Barracks";195;1
"Unit";"Marine";"Barracks";198;1
"Unit";"Marine";"Barracks";198;1
"Unit";"Marine";"Barracks";200;1
"Building";"Refinery";NA;195;0
"Building";"Refinery";NA;201;0
"Unit";"Marine";"Barracks";208;1
"Unit";"Marine";"Barracks";208;1
"Unit";"Marine";"Barracks";208;1
"Unit";"Marine";"Barracks";208;1
"Unit";"Marine";"Barracks";208;1
"Unit";"Medivac";"Starport";196;2
"Unit";"Marine";"Barracks";208;1
"Unit";"Medivac";"Starport";208;2
"Unit";"Medivac";"Starport";217;2
"Unit";"Marine";"Barracks";222;1
"Unit";"Marine";"Barracks";222;1
"Unit";"Marine";"Barracks";222;1
"Unit";"Marine";"Barracks";222;1
"Unit";"Marine";"Barracks";222;1
"Unit";"Marine";"Barracks";222;1
"Unit";"Marine";"Barracks";222;1
"Unit";"Marine";"Barracks";222;1
"Unit";"Marine";"Barracks";222;1
"Unit";"Medivac";"Starport";222;2
"Building";"GhostAcademy";NA;224;0
"Unit";"Marine";"Barracks";233;1
"Unit";"Marine";"Barracks";233;1
"Unit";"Marine";"Barracks";233;1
"Unit";"Marine";"Barracks";233;1
"Unit";"Marine";"Barracks";233;1
"Unit";"Marine";"Barracks";233;1
"Unit";"Marine";"Barracks";235;1
"Unit";"Marine";"Barracks";235;1
"Unit";"Marine";"Barracks";235;1
"Unit";"Marine";"Barracks";235;1
"Unit";"Marine";"Barracks";236;1
"Unit";"Marine";"Barracks";237;1
"Building";"CommandCenter";NA;222;0
"Upgrade";"TerranInfantryWeaponsLevel3";"EngineeringBay";208;0
"Upgrade";"TerranInfantryArmorsLevel3";"EngineeringBay";209;0
"Unit";"Marine";"Barracks";247;1
"Unit";"Marine";"Barracks";247;1
"Unit";"Marine";"Barracks";247;1
"Unit";"Marine";"Barracks";247;1
"Unit";"Ghost";"Barracks";247;2
"Building";"Barracks";NA;243;0
"Building";"Barracks";NA;243;0
"Building";"Barracks";NA;243;0
"Upgrade";"TerranVehicleWeaponsLevel1";"Armory";235;0
"Unit";"Marine";"Barracks";253;1
"Unit";"Marine";"Barracks";253;1
"Unit";"Marine";"Barracks";253;1
"Unit";"Marine";"Barracks";253;1
"Unit";"Ghost";"Barracks";251;2
"Unit";"Marine";"Barracks";253;1
"Unit";"Marine";"Barracks";253;1
"Unit";"Marine";"Barracks";253;1
"Unit";"Marine";"Barracks";253;1
"Unit";"Marine";"Barracks";253;1
"Unit";"Marine";"Barracks";253;1
"Unit";"Medivac";"Starport";253;2
"Unit";"Marauder";"Barracks";257;2
"Building";"BarracksTechLab";NA;263;0
"Building";"BarracksTechLab";NA;263;0
"Building";"BarracksTechLab";NA;263;0
"Unit";"Marine";"Barracks";269;1
"Unit";"Marine";"Barracks";269;1
"Unit";"Marauder";"Barracks";267;2
"Building";"Refinery";NA;273;0
"Unit";"Ghost";"Barracks";271;2
"Building";"Refinery";NA;273;0
"Unit";"Ghost";"Barracks";273;2
"Unit";"Marine";"Barracks";273;1
"Unit";"Marine";"Barracks";273;1
"Unit";"Marine";"Barracks";273;1
"Unit";"Marine";"Barracks";273;1
"Building";"CommandCenter";NA;265;0
"Unit";"Ghost";"Barracks";273;2
"Unit";"Ghost";"Barracks";273;2
"Unit";"Ghost";"Barracks";273;2
"Unit";"Marauder";"Barracks";275;2
"Upgrade";"PersonalCloaking";"GhostAcademy";271;0
