"type";"unit_name";"on_building";"total_supply";"supply"
"Building";"Refinery";NA;15;0
"Building";"Barracks";NA;15;0
"Unit";"Reaper";"Barracks";19;1
"Building";"Refinery";NA;19;0
"Building";"Factory";NA;20;0
"Building";"BarracksReactor";NA;21;0
"Building";"CommandCenter";NA;19;0
"Building";"GhostAcademy";NA;23;0
"Building";"BarracksTechLab";NA;25;0
"Unit";"Hellion";"Factory";24;2
"Unit";"Hellion";"Factory";24;2
"Unit";"Ghost";"Barracks";26;2
"Unit";"Hellion";"Factory";30;2
"Unit";"Hellion";"Factory";30;2
"Unit";"Ghost";"Barracks";32;2
"Unit";"Hellion";"Factory";35;2
"Unit";"Hellion";"Factory";39;2
"Unit";"Hellion";"Factory";47;2
"Unit";"Hellion";"Factory";47;2
"Building";"Armory";NA;39;0
"Unit";"Ghost";"Barracks";48;2
"Unit";"Hellion";"Factory";56;2
"Unit";"Hellion";"Factory";56;2
"Building";"Refinery";NA;65;0
"Building";"Refinery";NA;65;0
"Unit";"Cyclone";"Factory";66;3
"Unit";"Cyclone";"Factory";66;3
"Unit";"Ghost";"Barracks";65;2
"Building";"Factory";NA;65;0
"Building";"Factory";NA;65;0
"Building";"EngineeringBay";NA;74;0
"Building";"CommandCenter";NA;60;0
"Unit";"Hellion";"Factory";76;2
"Unit";"Hellion";"Factory";76;2
"Unit";"Cyclone";"Factory";78;3
"Unit";"Cyclone";"Factory";78;3
"Unit";"Ghost";"Barracks";79;2
"Building";"FactoryTechLab";NA;90;0
"Building";"FactoryTechLab";NA;90;0
"Unit";"Hellion";"Factory";90;2
"Unit";"Hellion";"Factory";90;2
"Unit";"Hellion";"Factory";96;2
"Unit";"Ghost";"Barracks";96;2
"Upgrade";"TerranVehicleWeaponsLevel1";"Armory";79;0
"Unit";"Hellion";"Factory";103;2
"Unit";"Hellion";"Factory";111;2
"Unit";"Hellion";"Factory";111;2
"Building";"CommandCenter";NA;100;0
"Unit";"Ghost";"Barracks";111;2
"Upgrade";"TerranInfantryArmorsLevel1";"EngineeringBay";100;0
"Building";"Refinery";NA;120;0
"Building";"Refinery";NA;120;0
"Unit";"Hellion";"Factory";125;2
"Unit";"Ghost";"Barracks";125;2
"Unit";"Hellion";"Factory";133;2
"Unit";"Hellion";"Factory";133;2
"Unit";"Hellion";"Factory";138;2
"Unit";"Hellion";"Factory";138;2
"Building";"GhostAcademy";NA;138;0
"Unit";"Hellion";"Factory";138;2
"Building";"Factory";NA;134;0
"Building";"Factory";NA;134;0
"Building";"MissileTurret";NA;138;0
"Building";"GhostAcademy";NA;138;0
"Unit";"Ghost";"Barracks";138;2
"Building";"Barracks";NA;134;0
"Building";"Barracks";NA;138;0
"Building";"Barracks";NA;138;0
"Building";"Barracks";NA;138;0
"Building";"Barracks";NA;138;0
"Building";"SensorTower";NA;148;0
"Upgrade";"TerranVehicleWeaponsLevel2";"Armory";133;0
"Building";"BarracksTechLab";NA;153;0
"Building";"BarracksTechLab";NA;153;0
"Building";"BarracksTechLab";NA;153;0
"Building";"BarracksTechLab";NA;153;0
"Building";"BarracksTechLab";NA;153;0
"Building";"FactoryTechLab";NA;153;0
"Building";"FactoryTechLab";NA;153;0
"Upgrade";"PersonalCloaking";"GhostAcademy";140;0
"Building";"Refinery";NA;153;0
"Building";"Refinery";NA;153;0
"Building";"MissileTurret";NA;153;0
"Building";"SensorTower";NA;153;0
"Building";"MissileTurret";NA;153;0
"Unit";"Ghost";"Barracks";153;2
"Unit";"Ghost";"Barracks";153;2
"Unit";"Ghost";"Barracks";153;2
"Unit";"Ghost";"Barracks";153;2
"Unit";"Ghost";"Barracks";153;2
"Building";"CommandCenter";NA;153;0
"Upgrade";"TerranInfantryArmorsLevel2";"EngineeringBay";140;0
"Unit";"Hellion";"Factory";167;2
"Unit";"Hellion";"Factory";167;2
"Unit";"Ghost";"Barracks";167;2
"Unit";"Ghost";"Barracks";167;2
"Unit";"Hellion";"Factory";169;2
"Unit";"Hellion";"Factory";171;2
"Building";"FactoryTechLab";NA;181;0
"Building";"BarracksTechLab";NA;181;0
"Building";"CommandCenter";NA;177;0
"Unit";"Ghost";"Barracks";181;2
"Unit";"Ghost";"Barracks";181;2
"Unit";"Ghost";"Barracks";181;2
"Unit";"Ghost";"Barracks";181;2
"Unit";"Ghost";"Barracks";181;2
"Building";"MissileTurret";NA;192;0
"Building";"MissileTurret";NA;192;0
"Building";"MissileTurret";NA;192;0
"Building";"SensorTower";NA;192;0
"Unit";"Ghost";"Barracks";184;2
"Unit";"Ghost";"Barracks";184;2
"Building";"MissileTurret";NA;192;0
"Building";"BarracksTechLab";NA;196;0
"Unit";"Hellion";"Factory";196;2
"Unit";"Ghost";"Barracks";196;2
"Unit";"Ghost";"Barracks";196;2
"Unit";"Ghost";"Barracks";196;2
"Unit";"Ghost";"Barracks";196;2
"Unit";"Ghost";"Barracks";196;2
"Upgrade";"TerranVehicleWeaponsLevel3";"Armory";181;0
"Upgrade";"TerranInfantryArmorsLevel3";"EngineeringBay";181;0
"Unit";"Ghost";"Barracks";208;2
"Building";"MissileTurret";NA;210;0
"Building";"MissileTurret";NA;210;0
"Building";"MissileTurret";NA;210;0
"Building";"Refinery";NA;210;0
"Building";"Refinery";NA;210;0
"Building";"MissileTurret";NA;210;0
"Building";"MissileTurret";NA;210;0
"Building";"SensorTower";NA;210;0
"Building";"MissileTurret";NA;210;0
"Building";"CommandCenter";NA;210;0
"Building";"CommandCenter";NA;210;0
"Building";"CommandCenter";NA;210;0
"Unit";"Ghost";"Barracks";210;2
"Building";"CommandCenter";NA;210;0
"Building";"Starport";NA;210;0
"Building";"Starport";NA;210;0
"Building";"Starport";NA;210;0
"Unit";"Ghost";"Barracks";210;2
"Unit";"Ghost";"Barracks";212;2
"Building";"MissileTurret";NA;212;0
"Unit";"Ghost";"Barracks";216;2
"Unit";"Ghost";"Barracks";216;2
"Unit";"Ghost";"Barracks";216;2
"Unit";"Ghost";"Barracks";216;2
"Unit";"Ghost";"Barracks";216;2
"Unit";"Ghost";"Barracks";216;2
"Unit";"Hellion";"Factory";216;2
"Unit";"Hellion";"Factory";216;2
"Unit";"Hellion";"Factory";216;2
"Unit";"Ghost";"Barracks";216;2
"Unit";"Ghost";"Barracks";228;2
"Unit";"Ghost";"Barracks";228;2
"Unit";"Ghost";"Barracks";228;2
"Unit";"Ghost";"Barracks";228;2
"Unit";"Ghost";"Barracks";228;2
"Unit";"Hellion";"Factory";229;2
"Unit";"Hellion";"Factory";231;2
"Unit";"Ghost";"Barracks";235;2
"Unit";"Ghost";"Barracks";247;2
"Unit";"Ghost";"Barracks";247;2
"Unit";"Ghost";"Barracks";247;2
"Unit";"Ghost";"Barracks";247;2
"Unit";"Ghost";"Barracks";247;2
"Building";"Refinery";NA;251;0
"Building";"StarportTechLab";NA;253;0
"Building";"StarportTechLab";NA;253;0
"Unit";"Ghost";"Barracks";251;2
"Building";"StarportTechLab";NA;263;0
"Unit";"Hellion";"Factory";253;2
"Unit";"Hellion";"Factory";253;2
"Unit";"Ghost";"Barracks";253;2
"Unit";"Ghost";"Barracks";255;2
"Unit";"Hellion";"Factory";263;2
"Building";"Starport";NA;253;0
"Building";"Starport";NA;253;0
"Unit";"Ghost";"Barracks";263;2
"Unit";"Hellion";"Factory";265;2
"Unit";"Hellion";"Factory";267;2
"Unit";"Hellion";"Factory";269;2
"Unit";"Hellion";"Factory";269;2
"Unit";"Hellion";"Factory";269;2
"Building";"MissileTurret";NA;273;0
"Building";"MissileTurret";NA;273;0
"Building";"MissileTurret";NA;275;0
"Unit";"Hellion";"Factory";273;2
"Building";"Refinery";NA;277;0
"Building";"Refinery";NA;277;0
"Unit";"Hellion";"Factory";277;2
"Unit";"Hellion";"Factory";279;2
"Unit";"Hellion";"Factory";281;2
"Unit";"Hellion";"Factory";283;2
"Building";"MissileTurret";NA;295;0
"Building";"StarportTechLab";NA;297;0
"Building";"StarportTechLab";NA;297;0
"Unit";"Hellion";"Factory";297;2
"Unit";"Hellion";"Factory";297;2
"Unit";"Hellion";"Factory";297;2
"Unit";"Hellion";"Factory";297;2
"Unit";"Hellion";"Factory";297;2
"Unit";"Hellion";"Factory";297;2
"Unit";"Ghost";"Barracks";297;2
"Unit";"Raven";"Starport";297;2
"Unit";"Raven";"Starport";297;2
"Unit";"Raven";"Starport";297;2
"Unit";"Hellion";"Factory";322;2
"Unit";"Hellion";"Factory";322;2
"Unit";"Hellion";"Factory";322;2
"Unit";"Hellion";"Factory";322;2
"Unit";"Hellion";"Factory";322;2
"Building";"MissileTurret";NA;322;0
"Building";"SensorTower";NA;322;0
"Building";"MissileTurret";NA;322;0
"Unit";"Raven";"Starport";322;2
"Unit";"Raven";"Starport";322;2
"Unit";"Raven";"Starport";322;2
"Unit";"Raven";"Starport";322;2
"Unit";"Hellion";"Factory";332;2
"Unit";"Hellion";"Factory";332;2
"Unit";"Hellion";"Factory";332;2
"Unit";"Hellion";"Factory";346;2
"Unit";"Hellion";"Factory";346;2
"Unit";"Hellion";"Factory";346;2
"Building";"MissileTurret";NA;346;0
"Unit";"Hellion";"Factory";346;2
"Building";"MissileTurret";NA;346;0
"Building";"MissileTurret";NA;346;0
"Building";"CommandCenter";NA;346;0
"Building";"CommandCenter";NA;346;0
"Unit";"Raven";"Starport";346;2
"Unit";"Raven";"Starport";346;2
"Unit";"Raven";"Starport";346;2
