"type";"unit_name";"on_building";"total_supply";"supply"
"Building";"Barracks";NA;16;0
"Building";"Barracks";NA;16;0
"Building";"Barracks";NA;16;0
"Unit";"Marine";"Barracks";18;1
"Unit";"Marine";"Barracks";19;1
"Unit";"Marine";"Barracks";19;1
"Unit";"Marine";"Barracks";19;1
"Unit";"Marine";"Barracks";20;1
"Unit";"Marine";"Barracks";21;1
"Unit";"Marine";"Barracks";23;1
"Building";"Bunker";NA;22;0
"Unit";"Marine";"Barracks";24;1
"Unit";"Marine";"Barracks";24;1
"Building";"Bunker";NA;24;0
"Unit";"Marine";"Barracks";25;1
"Unit";"Marine";"Barracks";26;1
"Unit";"Marine";"Barracks";29;1
"Unit";"Marine";"Barracks";29;1
"Unit";"Marine";"Barracks";33;1
"Unit";"Marine";"Barracks";33;1
"Unit";"Marine";"Barracks";33;1
"Unit";"Marine";"Barracks";33;1
"Unit";"Marine";"Barracks";34;1
"Unit";"Marine";"Barracks";35;1
"Building";"Refinery";NA;36;0
"Building";"Refinery";NA;36;0
"Unit";"Marine";"Barracks";37;1
"Unit";"Marine";"Barracks";38;1
"Unit";"Marine";"Barracks";39;1
"Unit";"Marine";"Barracks";41;1
"Unit";"Marine";"Barracks";42;1
"Unit";"Marine";"Barracks";43;1
"Unit";"Marine";"Barracks";46;1
"Unit";"Marine";"Barracks";47;1
"Unit";"Marine";"Barracks";48;1
"Unit";"Marine";"Barracks";50;1
"Unit";"Marine";"Barracks";51;1
"Unit";"Marine";"Barracks";53;1
"Building";"Factory";NA;49;0
"Unit";"Marine";"Barracks";54;1
"Unit";"Marine";"Barracks";56;1
"Unit";"Marine";"Barracks";56;1
"Building";"FactoryTechLab";NA;61;0
"Building";"Starport";NA;61;0
"Unit";"Banshee";"Starport";64;3
"Building";"CommandCenter";NA;63;0
"Unit";"Marine";"Barracks";64;1
"Unit";"Marine";"Barracks";64;1
"Unit";"Banshee";"Starport";64;3
"Building";"FactoryTechLab";NA;70;0
"Unit";"Marine";"Barracks";73;1
"Unit";"Marine";"Barracks";73;1
"Unit";"Marine";"Barracks";73;1
"Unit";"Marine";"Barracks";74;1
"Unit";"Banshee";"Starport";70;3
"Unit";"Marine";"Barracks";75;1
"Building";"Factory";NA;75;0
"Building";"Factory";NA;75;0
"Building";"Armory";NA;77;0
"Building";"FactoryTechLab";NA;87;0
"Building";"FactoryReactor";NA;87;0
