"Type";"UnitName";"OnBuilding";"TotalSupply";"Supply"
"Unit";"SCV";"Command Center";12;1
"Unit";"SCV";"Command Center";12;1
"Unit";"SCV";"Command Center";13;1
"Building";"SupplyDepot";NA;13;0
"Building";"Refinery";NA;14;0
"Unit";"SCV";"Command Center";15;1
"Unit";"SCV";"Command Center";15;1
"Unit";"SCV";"Command Center";16;1
"Unit";"SCV";"Command Center";17;1
"Building";"Barracks";NA;15;0
"Unit";"Reaper";"Barracks";19;1
"Unit";"SCV";"Command Center";19;1
"Unit";"SCV";"Command Center";20;1
"Building";"SupplyDepot";NA;20;0
"Unit";"SCV";"Command Center";21;1
"Building";"Refinery";NA;21;0
"Building";"Factory";NA;19;0
"Building";"BarracksReactor";NA;20;0
"Unit";"SCV";"Command Center";23;1
"Building";"CommandCenter";NA;19;0
"Unit";"SCV";"Command Center";24;1
"Unit";"Hellion";"Factory";23;2
"Building";"BarracksTechLab";NA;24;0
"Unit";"Hellion";"Factory";24;2
"Building";"Starport";NA;23;0
"Unit";"SCV";"Command Center";24;1
"Unit";"SCV";"Command Center";29;1
"Unit";"Hellion";"Factory";29;2
"Unit";"Hellion";"Factory";29;2
"Unit";"SCV";"Command Center";30;1
"Building";"BarracksTechLab";NA;30;0
"Unit";"SCV";"Command Center";36;1
"Unit";"SCV";"Command Center";36;1
"Building";"SupplyDepot";NA;33;0
"Unit";"SCV";"Command Center";36;1
"Building";"SupplyDepot";NA;36;0
"Unit";"SCV";"Command Center";38;1
"Unit";"SCV";"Command Center";38;1
"Unit";"Marine";"Barracks";38;1
"Unit";"SCV";"Command Center";41;1
"Unit";"SCV";"Command Center";41;1
"Building";"SupplyDepot";NA;40;0
"Unit";"Liberator";"Starport";38;3
"Unit";"SCV";"Command Center";44;1
"Unit";"SCV";"Command Center";44;1
"Unit";"Marine";"Barracks";44;1
"Unit";"SCV";"Command Center";48;1
"Unit";"SCV";"Command Center";50;1
"Building";"Refinery";NA;50;0
"Unit";"SCV";"Command Center";50;1
"Unit";"Marine";"Barracks";50;1
"Unit";"SCV";"Command Center";51;1
"Building";"StarportReactor";NA;48;0
"Building";"Barracks";NA;44;0
"Unit";"SCV";"Command Center";54;1
"Unit";"Marine";"Barracks";53;1
"Building";"Barracks";NA;48;0
"Building";"CommandCenter";NA;42;0
"Building";"EngineeringBay";NA;52;0
"Building";"EngineeringBay";NA;52;0
"Building";"Refinery";NA;54;0
"Unit";"SCV";"Command Center";56;1
"Unit";"SCV";"Command Center";56;1
"Upgrade";"Stimpack";"TechLab";42;0
"Unit";"Marine";"Barracks";56;1
"Building";"SupplyDepot";NA;57;0
"Unit";"SCV";"Command Center";59;1
"Unit";"Marine";"Barracks";59;1
"Unit";"Marine";"Barracks";59;1
"Unit";"Marine";"Barracks";59;1
"Building";"StarportReactor";NA;57;0
"Unit";"SCV";"Command Center";61;1
"Building";"SupplyDepot";NA;59;0
"Unit";"SCV";"Command Center";62;1
"Unit";"Marine";"Barracks";60;1
"Unit";"Marine";"Barracks";60;1
"Unit";"Marine";"Barracks";63;1
"Unit";"Marine";"Barracks";64;1
"Unit";"Marine";"Barracks";64;1
"Unit";"SCV";"Command Center";69;1
"Unit";"Marine";"Barracks";68;1
"Unit";"Medivac";"Starport";66;2
"Unit";"SCV";"Command Center";71;1
"Unit";"SCV";"Command Center";71;1
"Unit";"Marine";"Barracks";71;1
"Unit";"Marine";"Barracks";71;1
"Unit";"Marine";"Barracks";71;1
"Unit";"Marine";"Barracks";71;1
"Unit";"SCV";"Command Center";72;1
"Unit";"Marine";"Barracks";72;1
"Unit";"SCV";"Command Center";77;1
"Unit";"SCV";"Command Center";82;1
"Unit";"SCV";"Command Center";82;1
"Unit";"Marine";"Barracks";77;1
"Building";"Barracks";NA;68;0
"Building";"SupplyDepot";NA;77;0
"Building";"Barracks";NA;69;0
"Unit";"SCV";"Command Center";83;1
"Unit";"Marine";"Barracks";84;1
"Unit";"Marine";"Barracks";84;1
"Unit";"SCV";"Command Center";87;1
"Unit";"SCV";"Command Center";87;1
"Building";"SupplyDepot";NA;83;0
"Building";"SupplyDepot";NA;84;0
"Building";"Refinery";NA;84;0
"Building";"SupplyDepot";NA;84;0
"Unit";"Marine";"Barracks";84;1
"Unit";"Marine";"Barracks";84;1
"Unit";"SCV";"Command Center";87;1
"Upgrade";"TerranInfantryWeaponsLevel1";"EngineeringBay";65;0
"Upgrade";"TerranInfantryArmorsLevel1";"EngineeringBay";66;0
"Building";"Armory";NA;77;0
"Unit";"SCV";"Command Center";92;1
"Unit";"SCV";"Command Center";92;1
"Unit";"Marine";"Barracks";88;1
"Unit";"Medivac";"Starport";87;2
"Unit";"Medivac";"Starport";87;2
"Unit";"Marine";"Barracks";92;1
"Unit";"SCV";"Command Center";95;1
"Unit";"Marauder";"Barracks";93;2
"Unit";"SCV";"Command Center";95;1
"Building";"SupplyDepot";NA;95;0
"Building";"BarracksReactor";NA;88;0
"Building";"BarracksReactor";NA;88;0
"Building";"SupplyDepot";NA;95;0
"Unit";"Marine";"Barracks";95;1
"Unit";"Marine";"Barracks";95;1
"Building";"SupplyDepot";NA;103;0
"Unit";"Marine";"Barracks";107;1
"Unit";"SCV";"Command Center";109;1
"Unit";"Marine";"Barracks";107;1
"Unit";"Marine";"Barracks";107;1
"Unit";"Marauder";"Barracks";107;2
"Unit";"Marine";"Barracks";109;1
"Unit";"Marine";"Barracks";109;1
"Unit";"SCV";"Command Center";109;1
"Unit";"SCV";"Command Center";109;1
"Building";"Refinery";NA;109;0
"Unit";"SCV";"Command Center";110;1
"Unit";"Marine";"Barracks";109;1
"Building";"SupplyDepot";NA;109;0
"Unit";"SCV";"Command Center";119;1
"Building";"MissileTurret";NA;115;0
"Building";"MissileTurret";NA;115;0
"Building";"MissileTurret";NA;115;0
"Unit";"Marine";"Barracks";115;1
"Unit";"Marine";"Barracks";116;1
"Building";"MissileTurret";NA;119;0
"Unit";"Marine";"Barracks";120;1
"Unit";"Marine";"Barracks";120;1
"Unit";"Marine";"Barracks";120;1
"Unit";"Marine";"Barracks";120;1
"Unit";"Marine";"Barracks";121;1
"Building";"MissileTurret";NA;121;0
"Unit";"Marine";"Barracks";128;1
"Unit";"Marine";"Barracks";128;1
"Unit";"Marine";"Barracks";128;1
"Unit";"Marine";"Barracks";128;1
"Unit";"Marine";"Barracks";128;1
"Unit";"Marine";"Barracks";128;1
"Unit";"Marauder";"Barracks";128;2
"Unit";"SCV";"Command Center";129;1
"Unit";"SCV";"Command Center";129;1
"Unit";"Medivac";"Starport";128;2
"Unit";"SCV";"Command Center";137;1
"Unit";"Marine";"Barracks";135;1
"Unit";"Marine";"Barracks";135;1
"Building";"CommandCenter";NA;113;0
"Unit";"Marine";"Barracks";137;1
"Unit";"Marine";"Barracks";137;1
"Unit";"Marine";"Barracks";137;1
"Unit";"Marine";"Barracks";137;1
"Unit";"Marine";"Barracks";137;1
"Unit";"Marine";"Barracks";137;1
"Unit";"Marine";"Barracks";137;1
"Building";"SupplyDepot";NA;137;0
"Unit";"Medivac";"Starport";137;2
"Unit";"Marine";"Barracks";142;1
"Unit";"Marine";"Barracks";143;1
"Unit";"Marine";"Barracks";144;1
"Unit";"Marine";"Barracks";145;1
"Unit";"Medivac";"Starport";139;2
"Unit";"Marine";"Barracks";151;1
"Unit";"Marauder";"Barracks";150;2
"Unit";"Marine";"Barracks";151;1
"Building";"Factory";NA;137;0
"Building";"SensorTower";NA;151;0
"Unit";"Marine";"Barracks";153;1
"Upgrade";"TerranInfantryWeaponsLevel2";"EngineeringBay";120;0
"Building";"FactoryTechLab";NA;163;0
"Unit";"Marauder";"Barracks";160;2
"Building";"Barracks";NA;145;0
"Building";"Barracks";NA;151;0
"Building";"MissileTurret";NA;164;0
"Unit";"Marine";"Barracks";164;1
"Unit";"Marine";"Barracks";164;1
"Unit";"Marauder";"Barracks";164;2
"Unit";"Marine";"Barracks";166;1
"Building";"BarracksTechLab";NA;166;0
"Upgrade";"TerranInfantryArmorsLevel2";"EngineeringBay";134;0
"Building";"BarracksTechLab";NA;166;0
"Unit";"Marine";"Barracks";166;1
"Unit";"Marine";"Barracks";166;1
"Unit";"Marine";"Barracks";166;1
"Building";"SupplyDepot";NA;166;0
"Building";"SupplyDepot";NA;168;0
"Unit";"Marauder";"Barracks";168;2
"Unit";"Marine";"Barracks";174;1
"Unit";"Marine";"Barracks";174;1
"Unit";"Marine";"Barracks";174;1
"Unit";"Marine";"Barracks";174;1
"Unit";"Marine";"Barracks";174;1
"Unit";"Marauder";"Barracks";174;2
"Unit";"Marine";"Barracks";174;1
"Unit";"Marine";"Barracks";174;1
"Unit";"Marine";"Barracks";174;1
"Unit";"Marauder";"Barracks";174;2
