"type";"unit_name";"on_building";"total_supply";"supply"
"Building";"Refinery";NA;15;0
"Building";"Barracks";NA;15;0
"Unit";"Reaper";"Barracks";19;1
"Unit";"Marine";"Barracks";19;1
"Building";"Refinery";NA;21;0
"Building";"CommandCenter";NA;19;0
"Building";"Factory";NA;21;0
"Building";"BarracksReactor";NA;23;0
"Building";"BarracksTechLab";NA;26;0
"Unit";"Hellion";"Factory";26;2
"Unit";"Hellion";"Factory";26;2
"Building";"Starport";NA;25;0
"Unit";"Hellion";"Factory";34;2
"Unit";"Hellion";"Factory";34;2
"Building";"BarracksTechLab";NA;34;0
"Unit";"Banshee";"Starport";34;3
"Building";"FactoryReactor";NA;42;0
"Building";"CommandCenter";NA;34;0
"Unit";"Marine";"Barracks";49;1
"Building";"Barracks";NA;42;0
"Building";"Barracks";NA;43;0
"Building";"EngineeringBay";NA;54;0
"Building";"EngineeringBay";NA;54;0
"Building";"Refinery";NA;56;0
"Unit";"Marine";"Barracks";56;1
"Building";"Refinery";NA;56;0
"Unit";"Marine";"Barracks";56;1
"Unit";"Marine";"Barracks";56;1
"Unit";"Marine";"Barracks";56;1
"Building";"StarportReactor";NA;54;0
"Unit";"Marine";"Barracks";58;1
"Unit";"Marine";"Barracks";58;1
"Unit";"Marine";"Barracks";60;1
"Unit";"Marine";"Barracks";65;1
"Unit";"Marine";"Barracks";65;1
"Upgrade";"Stimpack";"TechLab";49;0
"Unit";"Marine";"Barracks";65;1
"Unit";"Marine";"Barracks";71;1
"Unit";"Marine";"Barracks";71;1
"Unit";"Marine";"Barracks";71;1
"Unit";"Marine";"Barracks";73;1
"Unit";"Marine";"Barracks";73;1
"Unit";"Medivac";"Starport";71;2
"Unit";"Medivac";"Starport";71;2
"Unit";"Marine";"Barracks";77;1
"Unit";"Marine";"Barracks";84;1
"Unit";"Marine";"Barracks";84;1
"Unit";"Marine";"Barracks";84;1
"Unit";"Marine";"Barracks";84;1
"Unit";"Marine";"Barracks";89;1
"Building";"Barracks";NA;79;0
"Building";"Barracks";NA;79;0
"Unit";"Marine";"Barracks";97;1
"Building";"Bunker";NA;96;0
"Upgrade";"TerranInfantryWeaponsLevel1";"EngineeringBay";71;0
"Upgrade";"TerranInfantryArmorsLevel1";"EngineeringBay";71;0
"Building";"Armory";NA;90;0
"Unit";"Medivac";"Starport";97;2
"Unit";"Medivac";"Starport";97;2
"Unit";"Marine";"Barracks";100;1
"Unit";"Marine";"Barracks";100;1
"Unit";"Marine";"Barracks";100;1
"Building";"MissileTurret";NA;100;0
"Unit";"Marine";"Barracks";102;1
"Unit";"Marine";"Barracks";109;1
"Unit";"Marine";"Barracks";109;1
"Unit";"Marine";"Barracks";109;1
"Unit";"Marine";"Barracks";109;1
"Building";"BarracksReactor";NA;100;0
"Building";"BarracksReactor";NA;100;0
"Unit";"Marine";"Barracks";109;1
"Unit";"Marine";"Barracks";110;1
"Unit";"Marine";"Barracks";111;1
"Unit";"Marine";"Barracks";112;1
"Unit";"Marine";"Barracks";113;1
"Building";"Barracks";NA;102;0
"Building";"Barracks";NA;102;0
"Unit";"Marine";"Barracks";114;1
"Unit";"Marine";"Barracks";114;1
"Unit";"Medivac";"Starport";110;2
"Unit";"Medivac";"Starport";110;2
"Building";"Barracks";NA;102;0
"Unit";"Marine";"Barracks";114;1
"Unit";"Marine";"Barracks";114;1
"Building";"Refinery";NA;114;0
"Unit";"Marine";"Barracks";114;1
"Unit";"Marine";"Barracks";115;1
"Unit";"Marine";"Barracks";116;1
"Unit";"Marine";"Barracks";117;1
"Unit";"Marine";"Barracks";118;1
"Unit";"Marine";"Barracks";119;1
"Unit";"Marine";"Barracks";130;1
"Unit";"Marine";"Barracks";130;1
"Unit";"Marine";"Barracks";131;1
"Unit";"Marine";"Barracks";131;1
"Unit";"Marine";"Barracks";136;1
"Unit";"Medivac";"Starport";131;2
"Unit";"Marine";"Barracks";136;1
"Unit";"Marine";"Barracks";136;1
"Unit";"Marine";"Barracks";136;1
"Building";"BarracksTechLab";NA;136;0
"Building";"BarracksTechLab";NA;136;0
"Building";"BarracksTechLab";NA;138;0
"Unit";"Marine";"Barracks";142;1
"Unit";"Marine";"Barracks";142;1
"Unit";"Marauder";"Barracks";142;2
"Unit";"Medivac";"Starport";140;2
"Building";"SensorTower";NA;149;0
"Unit";"Marine";"Barracks";151;1
"Unit";"Medivac";"Starport";144;2
"Unit";"Marine";"Barracks";153;1
"Unit";"Marauder";"Barracks";151;2
"Unit";"Marauder";"Barracks";151;2
"Unit";"Marine";"Barracks";153;1
"Unit";"Marine";"Barracks";153;1
"Unit";"Marine";"Barracks";153;1
"Unit";"Marine";"Barracks";153;1
"Unit";"Marine";"Barracks";155;1
"Building";"Refinery";NA;156;0
"Unit";"Medivac";"Starport";155;2
"Unit";"Marine";"Barracks";167;1
"Unit";"Marine";"Barracks";167;1
"Unit";"Marauder";"Barracks";167;2
"Unit";"Marauder";"Barracks";167;2
"Unit";"Marauder";"Barracks";167;2
"Unit";"Medivac";"Starport";156;2
"Unit";"Marauder";"Barracks";167;2
"Unit";"Marine";"Barracks";167;1
"Unit";"Marine";"Barracks";167;1
"Upgrade";"TerranInfantryWeaponsLevel2";"EngineeringBay";135;0
"Upgrade";"TerranVehicleWeaponsLevel1";"Armory";142;0
"Upgrade";"TerranInfantryArmorsLevel2";"EngineeringBay";135;0
"Unit";"Marine";"Barracks";184;1
"Unit";"Marauder";"Barracks";172;2
"Unit";"Marine";"Barracks";184;1
"Unit";"Marauder";"Barracks";178;2
"Unit";"Marauder";"Barracks";178;2
"Unit";"Marauder";"Barracks";180;2
"Unit";"Marine";"Barracks";194;1
"Unit";"Marine";"Barracks";194;1
"Unit";"Marine";"Barracks";194;1
"Unit";"Marine";"Barracks";194;1
"Unit";"Marine";"Barracks";194;1
"Unit";"Marauder";"Barracks";194;2
"Unit";"Marauder";"Barracks";194;2
"Unit";"Marauder";"Barracks";194;2
"Unit";"Marauder";"Barracks";194;2
"Unit";"Marine";"Barracks";194;1
"Unit";"Marine";"Barracks";194;1
"Unit";"Marine";"Barracks";195;1
"Unit";"Marine";"Barracks";199;1
"Unit";"Marine";"Barracks";201;1
"Unit";"Marine";"Barracks";201;1
"Unit";"Marauder";"Barracks";199;2
"Unit";"Marine";"Barracks";207;1
"Unit";"Marine";"Barracks";207;1
"Building";"CommandCenter";NA;183;0
"Unit";"Marine";"Barracks";207;1
"Unit";"Marauder";"Barracks";207;2
"Unit";"Marauder";"Barracks";207;2
"Unit";"Marine";"Barracks";208;1
"Unit";"Marauder";"Barracks";207;2
"Unit";"Marine";"Barracks";209;1
"Unit";"Marine";"Barracks";210;1
"Unit";"Marine";"Barracks";211;1
"Unit";"Marine";"Barracks";213;1
"Unit";"Marine";"Barracks";213;1
"Unit";"Marine";"Barracks";215;1
"Unit";"Marine";"Barracks";216;1
