"Type";"UnitName";"OnBuilding";"TotalSupply";"Supply"
"Unit";"SCV";"Command Center";12;1
"Unit";"SCV";"Command Center";13;1
"Unit";"SCV";"Command Center";13;1
"Building";"SupplyDepot";NA;13;0
"Unit";"SCV";"Command Center";15;1
"Unit";"SCV";"Command Center";16;1
"Building";"Refinery";NA;15;0
"Unit";"SCV";"Command Center";16;1
"Building";"Barracks";NA;15;0
"Unit";"SCV";"Command Center";18;1
"Unit";"Reaper";"Barracks";19;1
"Unit";"SCV";"Command Center";19;1
"Unit";"SCV";"Command Center";21;1
"Building";"SupplyDepot";NA;20;0
"Unit";"SCV";"Command Center";21;1
"Building";"Refinery";NA;21;0
"Building";"Barracks";NA;19;0
"Building";"BarracksReactor";NA;20;0
"Unit";"SCV";"Command Center";22;1
"Building";"CommandCenter";NA;19;0
"Unit";"SCV";"Command Center";24;1
"Unit";"Marine";"Barracks";23;1
"Unit";"Marine";"Barracks";23;1
"Building";"BarracksTechLab";NA;23;0
"Building";"Factory";NA;22;0
"Unit";"SCV";"Command Center";26;1
"Unit";"Marine";"Barracks";25;1
"Unit";"Marine";"Barracks";26;1
"Unit";"Marine";"Barracks";27;1
"Unit";"SCV";"Command Center";27;1
"Unit";"Marine";"Barracks";31;1
"Unit";"Marine";"Barracks";31;1
"Unit";"Marine";"Barracks";32;1
"Unit";"SCV";"Command Center";32;1
"Unit";"SCV";"Command Center";32;1
"Unit";"SCV";"Command Center";35;1
"Building";"Starport";NA;31;0
"Unit";"Marine";"Barracks";34;1
"Unit";"Marine";"Barracks";34;1
"Unit";"SCV";"Command Center";37;1
"Building";"SupplyDepot";NA;34;0
"Building";"FactoryReactor";NA;32;0
"Unit";"Marine";"Barracks";37;1
"Unit";"SCV";"Command Center";37;1
"Unit";"SCV";"Command Center";40;1
"Unit";"Marine";"Barracks";41;1
"Unit";"SCV";"Command Center";42;1
"Unit";"Marine";"Barracks";41;1
"Unit";"SCV";"Command Center";43;1
"Building";"SupplyDepot";NA;41;0
"Unit";"Marine";"Barracks";43;1
"Unit";"SCV";"Command Center";45;1
"Unit";"SCV";"Command Center";48;1
"Unit";"Marine";"Barracks";47;1
"Unit";"Marine";"Barracks";48;1
"Unit";"SCV";"Command Center";50;1
"Unit";"Medivac";"Starport";44;2
"Unit";"Medivac";"Starport";44;2
"Building";"SupplyDepot";NA;49;0
"Building";"FactoryTechLab";NA;49;0
"Unit";"Marine";"Barracks";49;1
"Unit";"SCV";"Command Center";50;1
"Unit";"Marine";"Barracks";52;1
"Unit";"SCV";"Command Center";60;1
"Upgrade";"Stimpack";"TechLab";34;0
"Unit";"Marine";"Barracks";60;1
"Unit";"Marine";"Barracks";60;1
"Unit";"SCV";"Command Center";60;1
"Building";"EngineeringBay";NA;60;0
"Building";"EngineeringBay";NA;60;0
"Unit";"SCV";"Command Center";61;1
"Unit";"Marine";"Barracks";61;1
"Unit";"SCV";"Command Center";64;1
"Unit";"Marine";"Barracks";62;1
"Building";"SupplyDepot";NA;65;0
"Unit";"SCV";"Command Center";67;1
"Building";"Refinery";NA;68;0
"Unit";"SCV";"Command Center";70;1
"Unit";"Marine";"Barracks";69;1
"Unit";"Marine";"Barracks";69;1
"Unit";"Marine";"Barracks";69;1
"Unit";"SCV";"Command Center";74;1
"Unit";"Marine";"Barracks";71;1
"Unit";"Marine";"Barracks";72;1
"Unit";"Medivac";"Starport";70;2
"Building";"CommandCenter";NA;61;0
"Unit";"Marine";"Barracks";74;1
"Unit";"Marine";"Barracks";75;1
"Unit";"Marine";"Barracks";76;1
"Building";"Barracks";NA;70;0
"Unit";"Marine";"Barracks";79;1
"Unit";"SCV";"Command Center";83;1
"Unit";"Marine";"Barracks";83;1
"Unit";"Marine";"Barracks";83;1
"Unit";"Marine";"Barracks";83;1
"Unit";"Marine";"Barracks";83;1
"Building";"Barracks";NA;80;0
"Unit";"SCV";"Command Center";86;1
"Unit";"SCV";"Command Center";86;1
"Building";"Barracks";NA;80;0
"Unit";"SCV";"Command Center";86;1
"Unit";"Marine";"Barracks";84;1
"Unit";"Marine";"Barracks";86;1
"Unit";"Marine";"Barracks";86;1
"Unit";"SCV";"Command Center";88;1
"Unit";"SCV";"Command Center";89;1
"Unit";"SCV";"Command Center";90;1
"Unit";"Marine";"Barracks";87;1
"Upgrade";"TerranInfantryWeaponsLevel1";"EngineeringBay";74;0
"Upgrade";"TerranInfantryArmorsLevel1";"EngineeringBay";74;0
"Unit";"Marine";"Barracks";91;1
"Unit";"Marine";"Barracks";92;1
"Unit";"Marine";"Barracks";93;1
"Unit";"SCV";"Command Center";94;1
"Unit";"SCV";"Command Center";95;1
"Unit";"SCV";"Command Center";96;1
"Building";"SupplyDepot";NA;93;0
"Unit";"Marine";"Barracks";98;1
"Unit";"SCV";"Command Center";101;1
"Unit";"SCV";"Command Center";102;1
"Unit";"SCV";"Command Center";103;1
"Unit";"Marine";"Barracks";100;1
"Unit";"Marine";"Barracks";100;1
"Unit";"Marine";"Barracks";101;1
"Unit";"SCV";"Command Center";105;1
"Building";"BarracksReactor";NA;97;0
"Unit";"SCV";"Command Center";106;1
"Unit";"SCV";"Command Center";107;1
"Unit";"Marine";"Barracks";104;1
"Building";"SupplyDepot";NA;104;0
"Unit";"Marine";"Barracks";111;1
"Unit";"Marine";"Barracks";111;1
"Unit";"Marine";"Barracks";111;1
"Unit";"SCV";"Command Center";111;1
"Unit";"SCV";"Command Center";112;1
"Building";"Armory";NA;98;0
"Unit";"Marine";"Barracks";114;1
"Unit";"Marine";"Barracks";114;1
"Unit";"Marine";"Barracks";114;1
"Unit";"Medivac";"Starport";111;2
"Unit";"Medivac";"Starport";111;2
"Unit";"Marine";"Barracks";115;1
"Unit";"Marine";"Barracks";119;1
"Unit";"Marine";"Barracks";119;1
"Building";"BarracksReactor";NA;111;0
"Unit";"Marine";"Barracks";120;1
"Unit";"Marine";"Barracks";121;1
"Unit";"SCV";"Command Center";132;1
"Unit";"Marine";"Barracks";132;1
"Unit";"Marine";"Barracks";132;1
"Unit";"Marine";"Barracks";132;1
"Unit";"Marine";"Barracks";132;1
"Unit";"SCV";"Command Center";132;1
"Unit";"SCV";"Command Center";132;1
"Unit";"Marine";"Barracks";132;1
"Unit";"Marine";"Barracks";132;1
"Unit";"Marine";"Barracks";132;1
"Unit";"Marine";"Barracks";132;1
"Unit";"Marine";"Barracks";133;1
"Unit";"Marine";"Barracks";134;1
"Unit";"Marine";"Barracks";135;1
"Unit";"Marine";"Barracks";143;1
"Unit";"Marine";"Barracks";143;1
"Unit";"Marine";"Barracks";143;1
"Unit";"Marine";"Barracks";143;1
"Unit";"Marine";"Barracks";143;1
"Unit";"SCV";"Command Center";146;1
"Unit";"SCV";"Command Center";146;1
"Unit";"Marine";"Barracks";146;1
"Unit";"Marine";"Barracks";146;1
"Unit";"Marine";"Barracks";146;1
"Unit";"Medivac";"Starport";145;2
"Unit";"Medivac";"Starport";146;2
"Building";"SupplyDepot";NA;148;0
"Building";"SupplyDepot";NA;151;0
"Unit";"SCV";"Command Center";160;1
"Unit";"SCV";"Command Center";160;1
"Unit";"SCV";"Command Center";160;1
"Unit";"Marine";"Barracks";160;1
"Unit";"Marine";"Barracks";160;1
"Unit";"Marine";"Barracks";160;1
"Unit";"Marine";"Barracks";160;1
"Unit";"Marine";"Barracks";160;1
"Unit";"Marine";"Barracks";160;1
"Building";"Bunker";NA;156;0
"Building";"Bunker";NA;158;0
"Building";"SupplyDepot";NA;160;0
"Unit";"SCV";"Command Center";160;1
"Unit";"SCV";"Command Center";160;1
"Unit";"SCV";"Command Center";160;1
"Unit";"Marine";"Barracks";160;1
"Unit";"SCV";"Command Center";169;1
"Unit";"SCV";"Command Center";173;1
"Unit";"Marine";"Barracks";169;1
"Unit";"Marine";"Barracks";169;1
"Unit";"Marine";"Barracks";169;1
"Unit";"Marine";"Barracks";169;1
"Unit";"Marine";"Barracks";169;1
"Unit";"Marine";"Barracks";169;1
"Unit";"Marine";"Barracks";169;1
"Unit";"SCV";"Command Center";173;1
"Unit";"SCV";"Command Center";173;1
"Unit";"SCV";"Command Center";174;1
"Building";"SensorTower";NA;174;0
"Unit";"SCV";"Command Center";183;1
"Unit";"Marine";"Barracks";182;1
"Unit";"Marine";"Barracks";182;1
"Unit";"Marine";"Barracks";183;1
"Unit";"Marine";"Barracks";183;1
"Unit";"Marine";"Barracks";183;1
"Building";"Refinery";NA;182;0
"Unit";"Marine";"Barracks";185;1
"Unit";"Marine";"Barracks";185;1
