"type";"unit_name";"on_building";"total_supply";"supply"
"Building";"Refinery";NA;15;0
"Building";"Barracks";NA;15;0
"Unit";"Reaper";"Barracks";19;1
"Building";"Refinery";NA;21;0
"Building";"CommandCenter";NA;19;0
"Building";"BarracksReactor";NA;21;0
"Building";"Factory";NA;22;0
"Unit";"Hellion";"Factory";26;2
"Unit";"Hellion";"Factory";26;2
"Building";"Starport";NA;25;0
"Unit";"Hellion";"Factory";34;2
"Unit";"Hellion";"Factory";34;2
"Building";"StarportTechLab";NA;36;0
"Unit";"Hellion";"Factory";43;2
"Unit";"Hellion";"Factory";43;2
"Building";"Refinery";NA;44;0
"Building";"Refinery";NA;44;0
"Unit";"Banshee";"Starport";44;3
"Unit";"Hellion";"Factory";53;2
"Unit";"Hellion";"Factory";53;2
"Unit";"Hellion";"Factory";59;2
"Unit";"Hellion";"Factory";61;2
"Unit";"Banshee";"Starport";58;3
"Unit";"Hellion";"Factory";64;2
"Unit";"Hellion";"Factory";76;2
"Unit";"Hellion";"Factory";76;2
"Unit";"Hellion";"Factory";80;2
"Unit";"Hellion";"Factory";82;2
"Building";"CommandCenter";NA;46;0
"Unit";"Hellion";"Factory";94;2
"Unit";"Hellion";"Factory";94;2
"Building";"Factory";NA;100;0
"Building";"Factory";NA;101;0
"Building";"Armory";NA;101;0
"Building";"Armory";NA;101;0
"Building";"EngineeringBay";NA;102;0
"Unit";"Marine";"Barracks";106;1
"Building";"FactoryTechLab";NA;106;0
"Building";"FactoryTechLab";NA;106;0
"Building";"MissileTurret";NA;109;0
"Building";"MissileTurret";NA;109;0
"Building";"MissileTurret";NA;109;0
"Building";"MissileTurret";NA;109;0
"Building";"StarportReactor";NA;106;0
"Unit";"Thor";"Factory";113;6
"Unit";"Medivac";"Starport";113;2
"Unit";"Medivac";"Starport";113;2
"Unit";"Hellion";"Factory";113;2
"Unit";"Hellion";"Factory";113;2
"Unit";"Thor";"Factory";113;6
"Unit";"Hellion";"Factory";126;2
"Unit";"Hellion";"Factory";128;2
"Building";"MissileTurret";NA;130;0
"Upgrade";"TerranVehicleWeaponsLevel1";"Armory";113;0
"Building";"Refinery";NA;140;0
"Building";"Refinery";NA;142;0
"Unit";"Thor";"Factory";142;6
"Unit";"Thor";"Factory";142;6
"Unit";"Hellion";"Factory";143;2
"Unit";"Hellion";"Factory";143;2
"Unit";"Hellion";"Factory";158;2
"Unit";"Hellion";"Factory";160;2
"Building";"Factory";NA;143;0
"Building";"Factory";NA;143;0
"Building";"Factory";NA;143;0
"Building";"FactoryTechLab";NA;166;0
"Building";"FactoryTechLab";NA;166;0
"Building";"CommandCenter";NA;143;0
"Unit";"Medivac";"Starport";166;2
"Unit";"Medivac";"Starport";166;2
"Unit";"Hellion";"Factory";176;2
"Unit";"Hellion";"Factory";176;2
"Unit";"Hellion";"Factory";176;2
"Unit";"Hellion";"Factory";178;2
"Unit";"Hellion";"Factory";180;2
"Unit";"Hellion";"Factory";180;2
"Unit";"Hellion";"Factory";182;2
"Upgrade";"TerranVehicleWeaponsLevel2";"Armory";166;0
"Unit";"Hellion";"Factory";186;2
"Unit";"Hellion";"Factory";188;2
"Building";"Refinery";NA;193;0
"Building";"Refinery";NA;193;0
"Unit";"Hellion";"Factory";193;2
"Unit";"Hellion";"Factory";194;2
"Unit";"Hellion";"Factory";196;2
"Unit";"Hellion";"Factory";200;2
"Unit";"Hellion";"Factory";202;2
"Building";"CommandCenter";NA;186;0
"Unit";"Hellion";"Factory";204;2
"Unit";"Hellion";"Factory";204;2
"Unit";"Hellion";"Factory";204;2
"Unit";"Hellion";"Factory";204;2
"Unit";"Hellion";"Factory";204;2
"Unit";"Hellion";"Factory";206;2
"Unit";"Hellion";"Factory";208;2
"Unit";"Hellion";"Factory";210;2
"Unit";"Hellion";"Factory";214;2
"Unit";"Hellion";"Factory";216;2
"Unit";"Hellion";"Factory";218;2
"Unit";"Hellion";"Factory";226;2
"Unit";"Hellion";"Factory";230;2
"Unit";"Hellion";"Factory";230;2
"Unit";"Hellion";"Factory";232;2
"Unit";"Hellion";"Factory";234;2
"Unit";"Hellion";"Factory";234;2
"Unit";"Hellion";"Factory";236;2
"Unit";"Hellion";"Factory";242;2
"Upgrade";"TerranVehicleWeaponsLevel3";"Armory";204;0
"Unit";"Hellion";"Factory";244;2
"Unit";"Hellion";"Factory";246;2
"Unit";"Hellion";"Factory";246;2
"Unit";"Hellion";"Factory";248;2
"Unit";"Hellion";"Factory";252;2
"Building";"MissileTurret";NA;256;0
"Building";"MissileTurret";NA;256;0
"Unit";"Hellion";"Factory";256;2
"Building";"SensorTower";NA;260;0
"Unit";"Hellion";"Factory";266;2
"Unit";"Hellion";"Factory";266;2
"Building";"Refinery";NA;266;0
"Unit";"Thor";"Factory";266;6
"Unit";"Thor";"Factory";266;6
"Building";"Refinery";NA;270;0
"Building";"Starport";NA;270;0
"Building";"Starport";NA;270;0
"Unit";"Thor";"Factory";270;6
"Unit";"Thor";"Factory";270;6
"Unit";"Thor";"Factory";283;6
"Unit";"Thor";"Factory";283;6
"Unit";"Thor";"Factory";283;6
"Unit";"Thor";"Factory";283;6
"Unit";"Hellion";"Factory";295;2
"Unit";"Hellion";"Factory";295;2
"Unit";"Thor";"Factory";289;6
"Upgrade";"TerranShipWeaponsLevel1";"Armory";283;0
"Unit";"Hellion";"Factory";313;2
"Building";"SensorTower";NA;329;0
"Unit";"Hellion";"Factory";319;2
"Unit";"Hellion";"Factory";321;2
"Unit";"Hellion";"Factory";323;2
"Unit";"Thor";"Factory";295;6
"Unit";"Hellion";"Factory";335;2
"Unit";"Hellion";"Factory";345;2
"Unit";"Hellion";"Factory";345;2
"Unit";"Hellion";"Factory";345;2
"Unit";"Hellion";"Factory";345;2
"Unit";"Hellion";"Factory";345;2
"Unit";"Hellion";"Factory";345;2
"Building";"CommandCenter";NA;337;0
"Building";"CommandCenter";NA;343;0
"Unit";"Thor";"Factory";357;6
"Unit";"Thor";"Factory";357;6
