"Type";"UnitName";"OnBuilding";"TotalSupply";"Supply"
"Unit";"SCV";"Command Center";12;1
"Unit";"SCV";"Command Center";12;1
"Unit";"SCV";"Command Center";13;1
"Building";"SupplyDepot";NA;13;0
"Unit";"SCV";"Command Center";15;1
"Unit";"SCV";"Command Center";15;1
"Building";"Refinery";NA;15;0
"Unit";"SCV";"Command Center";16;1
"Building";"Barracks";NA;15;0
"Unit";"SCV";"Command Center";18;1
"Unit";"Reaper";"Barracks";18;1
"Unit";"SCV";"Command Center";19;1
"Building";"SupplyDepot";NA;19;0
"Unit";"SCV";"Command Center";21;1
"Unit";"SCV";"Command Center";21;1
"Building";"BarracksReactor";NA;20;0
"Building";"Refinery";NA;21;0
"Unit";"SCV";"Command Center";22;1
"Building";"Barracks";NA;21;0
"Building";"CommandCenter";NA;19;0
"Unit";"SCV";"Command Center";23;1
"Unit";"Marine";"Barracks";24;1
"Unit";"Marine";"Barracks";24;1
"Unit";"SCV";"Command Center";24;1
"Building";"Factory";NA;22;0
"Building";"BarracksTechLab";NA;24;0
"Unit";"SCV";"Command Center";27;1
"Unit";"Marine";"Barracks";27;1
"Unit";"Marine";"Barracks";27;1
"Unit";"SCV";"Command Center";28;1
"Unit";"Marine";"Barracks";28;1
"Unit";"SCV";"Command Center";31;1
"Unit";"Marine";"Barracks";31;1
"Unit";"SCV";"Command Center";31;1
"Unit";"SCV";"Command Center";34;1
"Unit";"Marine";"Barracks";34;1
"Unit";"Marine";"Barracks";34;1
"Building";"Starport";NA;28;0
"Unit";"SCV";"Command Center";35;1
"Unit";"Marine";"Barracks";34;1
"Unit";"SCV";"Command Center";37;1
"Unit";"SCV";"Command Center";39;1
"Unit";"Marine";"Barracks";37;1
"Building";"FactoryReactor";NA;34;0
"Unit";"SCV";"Command Center";41;1
"Unit";"Marine";"Barracks";42;1
"Unit";"Marine";"Barracks";42;1
"Building";"SupplyDepot";NA;42;0
"Building";"SupplyDepot";NA;42;0
"Unit";"SCV";"Command Center";47;1
"Unit";"SCV";"Command Center";47;1
"Unit";"Marine";"Barracks";47;1
"Unit";"Marine";"Barracks";47;1
"Unit";"SCV";"Command Center";47;1
"Unit";"SCV";"Command Center";48;1
"Unit";"Marine";"Barracks";47;1
"Unit";"Medivac";"Starport";47;2
"Unit";"Medivac";"Starport";47;2
"Building";"SupplyDepot";NA;47;0
"Building";"SupplyDepot";NA;47;0
"Unit";"SCV";"Command Center";51;1
"Unit";"SCV";"Command Center";52;1
"Unit";"Marine";"Barracks";51;1
"Unit";"Marine";"Barracks";51;1
"Building";"SupplyDepot";NA;53;0
"Unit";"SCV";"Command Center";58;1
"Unit";"SCV";"Command Center";60;1
"Upgrade";"Stimpack";"TechLab";37;0
"Unit";"Medivac";"Starport";54;2
"Unit";"SCV";"Command Center";62;1
"Unit";"Medivac";"Starport";58;2
"Building";"EngineeringBay";NA;62;0
"Unit";"Marine";"Barracks";63;1
"Unit";"Marine";"Barracks";63;1
"Building";"Refinery";NA;62;0
"Unit";"Marine";"Barracks";63;1
"Building";"Refinery";NA;62;0
"Building";"EngineeringBay";NA;62;0
"Unit";"SCV";"Command Center";64;1
"Unit";"Marine";"Barracks";69;1
"Unit";"Marine";"Barracks";70;1
"Unit";"SCV";"Command Center";73;1
"Unit";"SCV";"Command Center";73;1
"Unit";"Marine";"Barracks";73;1
"Unit";"SCV";"Command Center";75;1
"Unit";"SCV";"Command Center";76;1
"Building";"FactoryReactor";NA;69;0
"Unit";"Marine";"Barracks";77;1
"Unit";"Marine";"Barracks";77;1
"Building";"SupplyDepot";NA;77;0
"Building";"Barracks";NA;70;0
"Building";"Barracks";NA;72;0
"Unit";"SCV";"Command Center";82;1
"Building";"CommandCenter";NA;64;0
"Unit";"Marine";"Barracks";82;1
"Unit";"Marine";"Barracks";82;1
"Unit";"Marauder";"Barracks";82;2
"Unit";"SCV";"Command Center";87;1
"Unit";"SCV";"Command Center";87;1
"Unit";"Marine";"Barracks";83;1
"Building";"SupplyDepot";NA;83;0
"Building";"SupplyDepot";NA;85;0
"Building";"BarracksReactor";NA;82;0
"Building";"BarracksReactor";NA;82;0
"Unit";"SCV";"Command Center";87;1
"Unit";"SCV";"Command Center";88;1
"Unit";"Marine";"Barracks";90;1
"Unit";"Marine";"Barracks";90;1
"Building";"Barracks";NA;82;0
"Unit";"SCV";"Command Center";90;1
"Unit";"SCV";"Command Center";91;1
"Unit";"Marauder";"Barracks";90;2
"Unit";"SCV";"Command Center";92;1
"Unit";"SCV";"Command Center";94;1
"Unit";"SCV";"Command Center";95;1
"Unit";"Marine";"Barracks";92;1
"Unit";"Marine";"Barracks";94;1
"Unit";"Marine";"Barracks";94;1
"Unit";"Marine";"Barracks";94;1
"Unit";"Marine";"Barracks";94;1
"Upgrade";"TerranInfantryWeaponsLevel1";"EngineeringBay";80;0
"Upgrade";"TerranInfantryArmorsLevel1";"EngineeringBay";80;0
"Building";"BarracksTechLab";NA;98;0
"Unit";"Medivac";"Starport";95;2
"Unit";"Medivac";"Starport";96;2
"Building";"Armory";NA;90;0
"Unit";"Marine";"Barracks";106;1
"Unit";"Marine";"Barracks";106;1
"Unit";"Marine";"Barracks";106;1
"Unit";"Marine";"Barracks";106;1
"Unit";"Marine";"Barracks";106;1
"Unit";"Marine";"Barracks";106;1
"Unit";"Marauder";"Barracks";106;2
"Building";"Barracks";NA;98;0
"Building";"Barracks";NA;99;0
"Unit";"Marine";"Barracks";110;1
"Unit";"Marine";"Barracks";111;1
"Unit";"Marine";"Barracks";112;1
"Unit";"Marine";"Barracks";113;1
"Unit";"Marine";"Barracks";114;1
"Unit";"SCV";"Command Center";118;1
"Unit";"SCV";"Command Center";118;1
"Unit";"Marauder";"Barracks";118;2
"Building";"BarracksTechLab";NA;123;0
"Building";"SupplyDepot";NA;118;0
"Unit";"Marine";"Barracks";123;1
"Unit";"Marine";"Barracks";123;1
"Unit";"Marine";"Barracks";123;1
"Unit";"Marine";"Barracks";123;1
"Building";"BarracksTechLab";NA;123;0
"Building";"SupplyDepot";NA;118;0
"Building";"SupplyDepot";NA;119;0
"Unit";"Marauder";"Barracks";123;2
"Unit";"SCV";"Command Center";127;1
"Unit";"SCV";"Command Center";127;1
"Building";"Barracks";NA;116;0
"Unit";"Marauder";"Barracks";127;2
"Unit";"Marine";"Barracks";133;1
"Unit";"Marine";"Barracks";133;1
"Unit";"Medivac";"Starport";127;2
"Unit";"Medivac";"Starport";127;2
"Unit";"Marauder";"Barracks";133;2
"Unit";"Marine";"Barracks";135;1
"Unit";"Marine";"Barracks";135;1
"Unit";"Marine";"Barracks";135;1
"Unit";"Marauder";"Barracks";135;2
"Building";"BarracksTechLab";NA;137;0
"Building";"Factory";NA;127;0
"Unit";"Marine";"Barracks";150;1
"Unit";"Marine";"Barracks";150;1
"Unit";"Marine";"Barracks";150;1
"Unit";"Marine";"Barracks";150;1
"Unit";"Marine";"Barracks";150;1
"Unit";"Marine";"Barracks";150;1
"Unit";"Marauder";"Barracks";150;2
"Unit";"Marauder";"Barracks";150;2
"Unit";"Marauder";"Barracks";150;2
"Building";"FactoryTechLab";NA;150;0
"Unit";"Marine";"Barracks";150;1
"Unit";"Marine";"Barracks";150;1
"Unit";"Marine";"Barracks";151;1
"Unit";"Marine";"Barracks";152;1
"Unit";"Marine";"Barracks";153;1
"Unit";"Marine";"Barracks";154;1
"Unit";"Marauder";"Barracks";156;2
"Unit";"Marine";"Barracks";163;1
"Unit";"Marine";"Barracks";163;1
"Unit";"Marauder";"Barracks";163;2
"Unit";"Marauder";"Barracks";163;2
"Unit";"Marine";"Barracks";163;1
"Unit";"Marine";"Barracks";164;1
"Unit";"Marine";"Barracks";165;1
"Unit";"Marine";"Barracks";168;1
"Building";"CommandCenter";NA;137;0
"Upgrade";"TerranShipWeaponsLevel1";"Armory";135;0
"Building";"SupplyDepot";NA;170;0
"Building";"SupplyDepot";NA;170;0
"Unit";"Marine";"Barracks";176;1
"Unit";"Marine";"Barracks";177;1
"Unit";"Marine";"Barracks";177;1
"Unit";"Marauder";"Barracks";178;2
"Unit";"Marine";"Barracks";180;1
"Unit";"Marine";"Barracks";180;1
"Unit";"Marine";"Barracks";180;1
"Unit";"Marine";"Barracks";180;1
"Unit";"Marine";"Barracks";180;1
"Upgrade";"TerranInfantryWeaponsLevel2";"EngineeringBay";137;0
"Upgrade";"TerranInfantryArmorsLevel2";"EngineeringBay";137;0
"Unit";"Marauder";"Barracks";180;2
"Unit";"Marine";"Barracks";185;1
"Unit";"Marine";"Barracks";185;1
"Unit";"Marine";"Barracks";185;1
"Unit";"Marauder";"Barracks";185;2
"Unit";"Marine";"Barracks";185;1
"Unit";"Marine";"Barracks";186;1
"Unit";"Marine";"Barracks";187;1
"Unit";"Marine";"Barracks";192;1
"Unit";"Marine";"Barracks";192;1
"Unit";"Marine";"Barracks";192;1
"Unit";"Marine";"Barracks";193;1
"Unit";"Marine";"Barracks";194;1
"Unit";"Marauder";"Barracks";192;2
"Unit";"Marine";"Barracks";195;1
"Unit";"Marine";"Barracks";205;1
"Unit";"Marine";"Barracks";205;1
"Unit";"Marine";"Barracks";205;1
"Unit";"Marine";"Barracks";207;1
"Unit";"Marine";"Barracks";207;1
"Unit";"Marine";"Barracks";207;1
"Unit";"Marine";"Barracks";207;1
"Unit";"Marauder";"Barracks";205;2
"Unit";"Marauder";"Barracks";207;2
"Unit";"Marauder";"Barracks";208;2
"Unit";"Marine";"Barracks";208;1
"Unit";"Marine";"Barracks";217;1
"Unit";"Marine";"Barracks";217;1
"Unit";"Marine";"Barracks";217;1
"Unit";"Medivac";"Starport";208;2
"Unit";"Marine";"Barracks";217;1
"Unit";"Medivac";"Starport";208;2
"Unit";"Marine";"Barracks";219;1
"Unit";"Marine";"Barracks";219;1
"Unit";"Marine";"Barracks";219;1
"Unit";"Marine";"Barracks";219;1
"Unit";"Marauder";"Barracks";219;2
"Unit";"Marine";"Barracks";221;1
"Unit";"Marine";"Barracks";222;1
"Unit";"Marine";"Barracks";223;1
"Unit";"Marine";"Barracks";224;1
"Unit";"Marine";"Barracks";227;1
"Unit";"Marine";"Barracks";230;1
"Unit";"Marine";"Barracks";233;1
"Unit";"Marauder";"Barracks";231;2
"Unit";"Marauder";"Barracks";232;2
"Unit";"Marine";"Barracks";237;1
"Unit";"Marine";"Barracks";237;1
"Unit";"Marauder";"Barracks";237;2
"Unit";"Marine";"Barracks";247;1
"Unit";"Marine";"Barracks";247;1
"Unit";"Marine";"Barracks";247;1
"Unit";"Marine";"Barracks";247;1
"Unit";"Marine";"Barracks";248;1
"Unit";"Marine";"Barracks";248;1
"Unit";"Marauder";"Barracks";247;2
"Unit";"Marauder";"Barracks";248;2
"Unit";"Marine";"Barracks";251;1
"Unit";"Marauder";"Barracks";251;2
"Unit";"Marine";"Barracks";251;1
"Unit";"Marine";"Barracks";252;1
"Unit";"Marine";"Barracks";253;1
"Unit";"Marine";"Barracks";254;1
"Unit";"Marine";"Barracks";255;1
"Unit";"Marine";"Barracks";257;1
"Unit";"Marine";"Barracks";259;1
"Unit";"Marauder";"Barracks";256;2
"Unit";"Marine";"Barracks";261;1
"Unit";"Marine";"Barracks";264;1
"Unit";"Marine";"Barracks";265;1
"Unit";"Marine";"Barracks";266;1
"Unit";"Marine";"Barracks";267;1
"Unit";"Marauder";"Barracks";262;2
"Unit";"Marine";"Barracks";270;1
"Unit";"Marine";"Barracks";271;1
"Unit";"Marauder";"Barracks";270;2
"Unit";"Medivac";"Starport";262;2
"Unit";"Marauder";"Barracks";270;2
"Unit";"Medivac";"Starport";264;2
"Unit";"Marine";"Barracks";273;1
"Upgrade";"TerranInfantryWeaponsLevel3";"EngineeringBay";219;0
"Upgrade";"TerranInfantryArmorsLevel3";"EngineeringBay";219;0
"Unit";"Marine";"Barracks";274;1
"Unit";"Marine";"Barracks";275;1
"Unit";"Marine";"Barracks";276;1
"Unit";"Marine";"Barracks";280;1
"Unit";"Marauder";"Barracks";278;2
"Unit";"Marine";"Barracks";280;1
"Unit";"Marauder";"Barracks";281;2
"Unit";"Marine";"Barracks";290;1
"Unit";"Marauder";"Barracks";282;2
"Unit";"Marauder";"Barracks";286;2
"Building";"Starport";NA;274;0
"Unit";"Marine";"Barracks";291;1
"Unit";"Medivac";"Starport";284;2
"Unit";"Medivac";"Starport";288;2
"Unit";"Marine";"Barracks";297;1
"Unit";"Marine";"Barracks";298;1
"Unit";"Marine";"Barracks";298;1
"Unit";"Marine";"Barracks";298;1
"Unit";"Marauder";"Barracks";297;2
"Unit";"Marine";"Barracks";300;1
"Unit";"Marine";"Barracks";301;1
"Building";"Barracks";NA;280;0
"Building";"Barracks";NA;280;0
"Unit";"Marine";"Barracks";303;1
"Unit";"Marauder";"Barracks";298;2
"Unit";"Marine";"Barracks";305;1
"Unit";"Marine";"Barracks";314;1
"Unit";"Marine";"Barracks";314;1
"Unit";"Marine";"Barracks";314;1
"Unit";"Marine";"Barracks";316;1
"Unit";"Marine";"Barracks";316;1
"Unit";"Marauder";"Barracks";314;2
"Building";"CommandCenter";NA;274;0
"Unit";"Marine";"Barracks";318;1
"Unit";"Marauder";"Barracks";317;2
"Unit";"Medivac";"Starport";306;2
"Building";"StarportReactor";NA;306;0
"Unit";"Marine";"Barracks";325;1
"Building";"BarracksTechLab";NA;325;0
"Building";"BarracksTechLab";NA;325;0
"Unit";"SCV";"Command Center";330;1
"Unit";"Marine";"Barracks";325;1
"Unit";"SCV";"Command Center";330;1
"Unit";"Marine";"Barracks";325;1
"Unit";"SCV";"Command Center";330;1
"Unit";"Marine";"Barracks";326;1
"Unit";"SCV";"Command Center";330;1
"Unit";"Marauder";"Barracks";325;2
"Unit";"Marauder";"Barracks";327;2
"Unit";"Marine";"Barracks";334;1
"Unit";"SCV";"Command Center";335;1
"Unit";"SCV";"Command Center";337;1
"Unit";"SCV";"Command Center";339;1
"Unit";"SCV";"Command Center";341;1
"Unit";"SCV";"Command Center";347;1
"Unit";"SCV";"Command Center";348;1
"Unit";"SCV";"Command Center";351;1
"Unit";"SCV";"Command Center";351;1
"Unit";"Marine";"Barracks";346;1
"Unit";"Marine";"Barracks";347;1
"Unit";"Marine";"Barracks";347;1
"Unit";"Marine";"Barracks";347;1
"Unit";"Marine";"Barracks";347;1
"Unit";"Marauder";"Barracks";346;2
"Unit";"Marine";"Barracks";362;1
"Unit";"Marine";"Barracks";362;1
"Unit";"Marine";"Barracks";362;1
"Unit";"Marauder";"Barracks";362;2
"Unit";"Marine";"Barracks";362;1
"Unit";"Marine";"Barracks";362;1
"Unit";"Marauder";"Barracks";362;2
