"Type";"UnitName";"OnBuilding";"TotalSupply";"Supply"
"Unit";"SCV";"Command Center";12;1
"Unit";"SCV";"Command Center";12;1
"Unit";"SCV";"Command Center";13;1
"Building";"SupplyDepot";NA;13;0
"Unit";"SCV";"Command Center";15;1
"Unit";"SCV";"Command Center";15;1
"Building";"Refinery";NA;15;0
"Unit";"SCV";"Command Center";16;1
"Building";"Barracks";NA;15;0
"Unit";"SCV";"Command Center";17;1
"Unit";"Reaper";"Barracks";19;1
"Unit";"SCV";"Command Center";19;1
"Building";"SupplyDepot";NA;19;0
"Unit";"Marine";"Barracks";19;1
"Unit";"SCV";"Command Center";21;1
"Unit";"SCV";"Command Center";23;1
"Building";"Refinery";NA;23;0
"Unit";"SCV";"Command Center";23;1
"Building";"Factory";NA;20;0
"Building";"CommandCenter";NA;19;0
"Building";"BarracksReactor";NA;23;0
"Unit";"SCV";"Command Center";24;1
"Unit";"SCV";"Command Center";26;1
"Building";"Starport";NA;25;0
"Unit";"SCV";"Command Center";26;1
"Unit";"Hellion";"Factory";26;2
"Unit";"Hellion";"Factory";26;2
"Unit";"SCV";"Command Center";27;1
"Building";"BarracksTechLab";NA;27;0
"Unit";"SCV";"Command Center";27;1
"Unit";"SCV";"Command Center";33;1
"Unit";"Hellion";"Factory";28;2
"Unit";"Hellion";"Factory";30;2
"Unit";"SCV";"Command Center";33;1
"Unit";"SCV";"Command Center";34;1
"Unit";"SCV";"Command Center";39;1
"Building";"SupplyDepot";NA;34;0
"Unit";"SCV";"Command Center";40;1
"Unit";"SCV";"Command Center";41;1
"Unit";"Hellion";"Factory";40;2
"Unit";"Hellion";"Factory";40;2
"Unit";"SCV";"Command Center";42;1
"Building";"SupplyDepot";NA;42;0
"Unit";"SCV";"Command Center";43;1
"Unit";"SCV";"Command Center";48;1
"Unit";"SCV";"Command Center";49;1
"Building";"FactoryTechLab";NA;50;0
"Unit";"SCV";"Command Center";50;1
"Unit";"SCV";"Command Center";51;1
"Building";"SupplyDepot";NA;50;0
"Unit";"Liberator";"Starport";43;3
"Unit";"SCV";"Command Center";52;1
"Unit";"SCV";"Command Center";53;1
"Unit";"SCV";"Command Center";57;1
"Unit";"SCV";"Command Center";59;1
"Unit";"SCV";"Command Center";59;1
"Building";"Barracks";NA;52;0
"Unit";"SCV";"Command Center";61;1
"Building";"StarportReactor";NA;57;0
"Building";"Barracks";NA;52;0
"Unit";"SCV";"Command Center";61;1
"Unit";"Marine";"Barracks";61;1
"Building";"CommandCenter";NA;50;0
"Unit";"SCV";"Command Center";62;1
"Upgrade";"Stimpack";"TechLab";48;0
"Unit";"Marine";"Barracks";64;1
"Unit";"Marine";"Barracks";65;1
"Unit";"Marine";"Barracks";65;1
"Building";"EngineeringBay";NA;63;0
"Building";"EngineeringBay";NA;63;0
"Building";"SupplyDepot";NA;66;0
"Building";"SupplyDepot";NA;66;0
"Building";"Refinery";NA;66;0
"Unit";"Marine";"Barracks";66;1
"Building";"Refinery";NA;66;0
"Unit";"Marine";"Barracks";69;1
"Unit";"Marine";"Barracks";69;1
"Unit";"Marine";"Barracks";69;1
"Unit";"Marine";"Barracks";69;1
"Building";"StarportReactor";NA;66;0
"Unit";"Marine";"Barracks";69;1
"Unit";"Marine";"Barracks";70;1
"Building";"SupplyDepot";NA;70;0
"Building";"SupplyDepot";NA;70;0
"Unit";"SCV";"Command Center";75;1
"Unit";"SCV";"Command Center";75;1
"Unit";"Marine";"Barracks";74;1
"Unit";"Marine";"Barracks";76;1
"Unit";"Marine";"Barracks";76;1
"Unit";"SCV";"Command Center";76;1
"Building";"Barracks";NA;69;0
"Unit";"SCV";"Command Center";76;1
"Building";"SupplyDepot";NA;76;0
"Building";"Barracks";NA;70;0
"Unit";"Marine";"Barracks";79;1
"Unit";"Marine";"Barracks";79;1
"Unit";"Marine";"Barracks";79;1
"Unit";"Marine";"Barracks";79;1
"Unit";"Marine";"Barracks";80;1
"Building";"Armory";NA;74;0
"Unit";"SCV";"Command Center";86;1
"Unit";"SCV";"Command Center";86;1
"Unit";"SCV";"Command Center";86;1
"Unit";"Medivac";"Starport";79;2
"Unit";"Medivac";"Starport";79;2
"Building";"BarracksTechLab";NA;83;0
"Unit";"Marine";"Barracks";83;1
"Unit";"Marine";"Barracks";84;1
"Unit";"Marine";"Barracks";88;1
"Unit";"Marine";"Barracks";88;1
"Unit";"SCV";"Command Center";88;1
"Unit";"SCV";"Command Center";89;1
"Unit";"SCV";"Command Center";90;1
"Unit";"Marauder";"Barracks";88;2
"Building";"SupplyDepot";NA;88;0
"Building";"SupplyDepot";NA;88;0
"Building";"SupplyDepot";NA;88;0
"Building";"BarracksReactor";NA;83;0
"Unit";"Marine";"Barracks";95;1
"Unit";"Marine";"Barracks";96;1
"Unit";"SCV";"Command Center";99;1
"Unit";"Marine";"Barracks";97;1
"Unit";"Marine";"Barracks";98;1
"Unit";"SCV";"Command Center";104;1
"Unit";"SCV";"Command Center";104;1
"Unit";"Marauder";"Barracks";102;2
"Unit";"SCV";"Command Center";106;1
"Unit";"Medivac";"Starport";97;2
"Unit";"Medivac";"Starport";97;2
"Unit";"Marine";"Barracks";104;1
"Unit";"Marine";"Barracks";105;1
"Upgrade";"TerranInfantryWeaponsLevel1";"EngineeringBay";76;0
"Upgrade";"TerranInfantryArmorsLevel1";"EngineeringBay";76;0
"Unit";"SCV";"Command Center";109;1
"Unit";"Marine";"Barracks";107;1
"Building";"SupplyDepot";NA;104;0
"Unit";"Marine";"Barracks";107;1
"Building";"Refinery";NA;106;0
"Building";"SupplyDepot";NA;107;0
"Building";"SupplyDepot";NA;107;0
"Unit";"Marine";"Barracks";119;1
"Unit";"Marauder";"Barracks";118;2
"Unit";"Marauder";"Barracks";119;2
"Unit";"Marine";"Barracks";123;1
"Unit";"Marine";"Barracks";123;1
"Unit";"Marine";"Barracks";123;1
"Unit";"Marine";"Barracks";123;1
"Building";"MissileTurret";NA;123;0
"Building";"MissileTurret";NA;123;0
"Unit";"Marine";"Barracks";123;1
"Building";"MissileTurret";NA;123;0
"Building";"MissileTurret";NA;123;0
"Unit";"Marine";"Barracks";123;1
"Building";"MissileTurret";NA;124;0
"Unit";"Marine";"Barracks";124;1
"Unit";"Marine";"Barracks";126;1
"Unit";"Marine";"Barracks";128;1
"Unit";"Marine";"Barracks";129;1
"Unit";"Marine";"Barracks";130;1
"Unit";"Marine";"Barracks";133;1
"Unit";"Marine";"Barracks";133;1
"Unit";"Marine";"Barracks";133;1
"Unit";"Marauder";"Barracks";134;2
"Unit";"Marauder";"Barracks";135;2
"Unit";"Marine";"Barracks";136;1
"Unit";"Medivac";"Starport";133;2
"Unit";"Medivac";"Starport";133;2
"Unit";"Marine";"Barracks";142;1
"Unit";"Marine";"Barracks";142;1
"Unit";"Marine";"Barracks";142;1
"Unit";"Marine";"Barracks";144;1
"Unit";"Marine";"Barracks";146;1
"Unit";"Marine";"Barracks";146;1
"Unit";"Marine";"Barracks";146;1
"Unit";"Thor";"Factory";134;6
"Upgrade";"TerranVehicleWeaponsLevel1";"Armory";123;0
"Unit";"Marine";"Barracks";164;1
"Unit";"Marine";"Barracks";164;1
"Unit";"Marine";"Barracks";164;1
"Unit";"Marine";"Barracks";164;1
"Unit";"Marine";"Barracks";164;1
"Unit";"Marine";"Barracks";164;1
"Unit";"Marine";"Barracks";164;1
"Unit";"Marine";"Barracks";171;1
"Unit";"Marine";"Barracks";171;1
"Unit";"Marine";"Barracks";171;1
"Unit";"Marine";"Barracks";171;1
"Unit";"Marine";"Barracks";171;1
"Unit";"Marine";"Barracks";171;1
"Unit";"Marine";"Barracks";171;1
"Unit";"Marine";"Barracks";171;1
"Building";"CommandCenter";NA;151;0
"Building";"Barracks";NA;164;0
"Building";"Barracks";NA;164;0
"Building";"Barracks";NA;164;0
"Unit";"Marine";"Barracks";171;1
"Unit";"Marine";"Barracks";172;1
"Unit";"Marine";"Barracks";173;1
"Unit";"Marine";"Barracks";174;1
"Unit";"Marine";"Barracks";175;1
"Unit";"Marine";"Barracks";176;1
"Unit";"Marine";"Barracks";177;1
"Unit";"Marine";"Barracks";178;1
"Unit";"Medivac";"Starport";171;2
"Unit";"Medivac";"Starport";171;2
"Unit";"Marine";"Barracks";179;1
"Unit";"Marine";"Barracks";180;1
"Building";"SupplyDepot";NA;179;0
"Unit";"Marine";"Barracks";181;1
"Building";"SupplyDepot";NA;179;0
"Unit";"Marine";"Barracks";182;1
"Unit";"Marine";"Barracks";183;1
"Unit";"Marine";"Barracks";184;1
"Unit";"Marine";"Barracks";185;1
"Building";"SupplyDepot";NA;179;0
"Unit";"Marine";"Barracks";186;1
"Unit";"Thor";"Factory";171;6
"Building";"MissileTurret";NA;187;0
"Building";"SensorTower";NA;187;0
"Building";"BarracksTechLab";NA;191;0
"Building";"BarracksTechLab";NA;191;0
"Building";"MissileTurret";NA;187;0
"Building";"BarracksTechLab";NA;191;0
"Unit";"Marine";"Barracks";191;1
"Unit";"Marine";"Barracks";192;1
"Unit";"Marine";"Barracks";193;1
"Building";"SensorTower";NA;199;0
"Unit";"Marine";"Barracks";205;1
"Unit";"Marine";"Barracks";205;1
"Unit";"Marine";"Barracks";205;1
"Upgrade";"TerranInfantryWeaponsLevel2";"EngineeringBay";164;0
"Unit";"Marauder";"Barracks";205;2
"Unit";"Marauder";"Barracks";205;2
"Upgrade";"TerranInfantryArmorsLevel2";"EngineeringBay";164;0
"Unit";"Medivac";"Starport";205;2
"Unit";"Marine";"Barracks";205;1
"Unit";"Marine";"Barracks";206;1
"Unit";"Marine";"Barracks";215;1
"Unit";"Marine";"Barracks";215;1
"Unit";"Marine";"Barracks";215;1
"Unit";"Marine";"Barracks";215;1
"Unit";"Thor";"Factory";205;6
"Unit";"Marine";"Barracks";215;1
"Unit";"Marine";"Barracks";215;1
"Unit";"Marine";"Barracks";215;1
"Unit";"Marine";"Barracks";215;1
"Unit";"Marine";"Barracks";215;1
"Unit";"Marine";"Barracks";217;1
"Unit";"Marine";"Barracks";218;1
"Unit";"Marine";"Barracks";219;1
"Unit";"Marine";"Barracks";220;1
"Unit";"Marine";"Barracks";221;1
"Unit";"Marine";"Barracks";222;1
"Unit";"Marine";"Barracks";229;1
"Unit";"SCV";"Command Center";240;1
"Unit";"SCV";"Command Center";240;1
"Unit";"SCV";"Command Center";240;1
"Unit";"Marine";"Barracks";241;1
"Unit";"Marine";"Barracks";244;1
"Unit";"Marine";"Barracks";244;1
"Unit";"Marine";"Barracks";244;1
"Building";"EngineeringBay";NA;241;0
"Building";"EngineeringBay";NA;241;0
"Unit";"Marine";"Barracks";244;1
"Unit";"Marine";"Barracks";244;1
"Unit";"Marine";"Barracks";244;1
"Unit";"Marine";"Barracks";244;1
"Unit";"Marine";"Barracks";244;1
"Unit";"Marine";"Barracks";248;1
"Unit";"Marine";"Barracks";248;1
"Unit";"Marine";"Barracks";248;1
