"type";"unit_name";"on_building";"total_supply";"supply"
"Building";"Refinery";NA;14;0
"Building";"Barracks";NA;15;0
"Unit";"Marine";"Barracks";19;1
"Building";"Factory";NA;19;0
"Building";"BarracksReactor";NA;20;0
"Unit";"Hellion";"Factory";22;2
"Unit";"Hellion";"Factory";22;2
"Building";"Starport";NA;22;0
"Building";"CommandCenter";NA;20;0
"Unit";"Hellion";"Factory";23;2
"Unit";"Hellion";"Factory";25;2
"Unit";"Medivac";"Starport";27;2
"Building";"Refinery";NA;32;0
"Building";"StarportTechLab";NA;38;0
"Unit";"Hellion";"Factory";39;2
"Unit";"Hellion";"Factory";39;2
"Building";"Armory";NA;39;0
"Unit";"Hellion";"Factory";46;2
"Unit";"Hellion";"Factory";46;2
"Building";"CommandCenter";NA;37;0
"Unit";"Banshee";"Starport";41;3
"Unit";"Hellion";"Factory";49;2
"Unit";"Hellion";"Factory";51;2
"Building";"Refinery";NA;63;0
"Unit";"Hellion";"Factory";63;2
"Unit";"Hellion";"Factory";63;2
"Building";"Refinery";NA;63;0
"Unit";"Banshee";"Starport";54;3
"Unit";"Hellion";"Factory";65;2
"Unit";"Hellion";"Factory";67;2
"Building";"Factory";NA;73;0
"Building";"Factory";NA;74;0
"Unit";"Hellion";"Factory";84;2
"Unit";"Hellion";"Factory";84;2
"Upgrade";"TerranVehicleWeaponsLevel1";"Armory";65;0
"Unit";"Raven";"Starport";82;2
"Building";"FactoryTechLab";NA;92;0
"Building";"FactoryTechLab";NA;92;0
"Unit";"Hellion";"Factory";92;2
"Unit";"Hellion";"Factory";92;2
"Unit";"Thor";"Factory";96;6
"Unit";"Thor";"Factory";102;6
"Building";"FactoryReactor";NA;102;0
"Unit";"Medivac";"Starport";102;2
"Unit";"Medivac";"Starport";103;2
"Building";"Refinery";NA;113;0
"Building";"Refinery";NA;114;0
"Building";"EngineeringBay";NA;114;0
"Building";"BarracksReactor";NA;105;0
"Unit";"Hellion";"Factory";120;2
"Unit";"Hellion";"Factory";120;2
"Unit";"Hellion";"Factory";134;2
"Unit";"Hellion";"Factory";134;2
"Building";"SensorTower";NA;137;0
"Upgrade";"TerranVehicleWeaponsLevel2";"Armory";102;0
"Unit";"Medivac";"Starport";138;2
"Unit";"Medivac";"Starport";138;2
"Unit";"Hellion";"Factory";144;2
"Unit";"Hellion";"Factory";144;2
"Building";"Factory";NA;135;0
"Building";"Factory";NA;137;0
"Unit";"Hellion";"Factory";160;2
"Unit";"Hellion";"Factory";160;2
"Unit";"Hellion";"Factory";160;2
"Unit";"Hellion";"Factory";160;2
"Unit";"Hellion";"Factory";170;2
"Unit";"Hellion";"Factory";170;2
"Unit";"Hellion";"Factory";170;2
"Unit";"Hellion";"Factory";170;2
"Building";"CommandCenter";NA;160;0
"Unit";"Hellion";"Factory";178;2
"Unit";"Hellion";"Factory";178;2
"Unit";"Hellion";"Factory";182;2
"Unit";"Hellion";"Factory";182;2
"Unit";"Hellion";"Factory";182;2
"Unit";"Hellion";"Factory";182;2
"Upgrade";"TerranVehicleWeaponsLevel3";"Armory";160;0
"Building";"Refinery";NA;182;0
"Building";"Refinery";NA;182;0
"Building";"CommandCenter";NA;172;0
"Unit";"Hellion";"Factory";190;2
"Unit";"Hellion";"Factory";190;2
"Unit";"Hellion";"Factory";190;2
"Unit";"Hellion";"Factory";190;2
"Unit";"Hellion";"Factory";198;2
"Unit";"Hellion";"Factory";198;2
"Unit";"Hellion";"Factory";198;2
"Unit";"Hellion";"Factory";198;2
"Building";"Factory";NA;190;0
"Building";"FactoryTechLab";NA;209;0
"Unit";"Hellion";"Factory";209;2
"Unit";"Hellion";"Factory";209;2
"Unit";"Hellion";"Factory";209;2
"Unit";"Hellion";"Factory";209;2
"Unit";"Hellion";"Factory";209;2
"Unit";"Hellion";"Factory";211;2
"Unit";"Hellion";"Factory";213;2
"Unit";"Hellion";"Factory";215;2
"Building";"CommandCenter";NA;198;0
"Building";"Refinery";NA;217;0
"Building";"Refinery";NA;217;0
"Unit";"Hellion";"Factory";217;2
"Unit";"Hellion";"Factory";219;2
"Unit";"Hellion";"Factory";223;2
"Unit";"Thor";"Factory";217;6
"Unit";"Thor";"Factory";217;6
"Unit";"Thor";"Factory";217;6
"Unit";"Thor";"Factory";217;6
"Unit";"Hellion";"Factory";255;2
"Unit";"Hellion";"Factory";255;2
"Unit";"Thor";"Factory";255;6
"Unit";"Thor";"Factory";255;6
"Unit";"Thor";"Factory";255;6
"Building";"CommandCenter";NA;255;0
"Building";"CommandCenter";NA;255;0
"Building";"CommandCenter";NA;255;0
"Building";"Starport";NA;277;0
"Building";"Barracks";NA;277;0
"Unit";"Hellion";"Factory";277;2
"Unit";"Hellion";"Factory";277;2
"Unit";"Hellion";"Factory";277;2
"Unit";"Hellion";"Factory";277;2
"Building";"StarportTechLab";NA;277;0
"Unit";"Thor";"Factory";277;6
"Unit";"Thor";"Factory";277;6
"Unit";"Thor";"Factory";277;6
"Unit";"Hellion";"Factory";277;2
"Unit";"Thor";"Factory";277;6
"Unit";"Liberator";"Starport";277;3
"Unit";"Liberator";"Starport";277;3
"Unit";"Hellion";"Factory";285;2
"Unit";"Hellion";"Factory";285;2
"Unit";"Hellion";"Factory";285;2
