"type";"unit_name";"on_building";"total_supply";"supply"
"Building";"Refinery";NA;14;0
"Building";"Barracks";NA;15;0
"Unit";"Reaper";"Barracks";19;1
"Building";"Refinery";NA;20;0
"Building";"Factory";NA;20;0
"Building";"BarracksReactor";NA;20;0
"Building";"CommandCenter";NA;19;0
"Unit";"Hellion";"Factory";24;2
"Unit";"Hellion";"Factory";24;2
"Building";"Factory";NA;23;0
"Building";"BarracksReactor";NA;24;0
"Unit";"Hellion";"Factory";26;2
"Unit";"Hellion";"Factory";28;2
"Unit";"Hellion";"Factory";36;2
"Unit";"Hellion";"Factory";36;2
"Unit";"Hellion";"Factory";37;2
"Unit";"Hellion";"Factory";38;2
"Unit";"Hellion";"Factory";45;2
"Unit";"Hellion";"Factory";45;2
"Unit";"Cyclone";"Factory";45;3
"Building";"BarracksTechLab";NA;47;0
"Unit";"Cyclone";"Factory";51;3
"Building";"FactoryTechLab";NA;55;0
"Building";"Factory";NA;51;0
"Unit";"Hellion";"Factory";64;2
"Unit";"Hellion";"Factory";64;2
"Building";"Refinery";NA;64;0
"Building";"Refinery";NA;64;0
"Unit";"Hellion";"Factory";68;2
"Building";"Factory";NA;66;0
"Unit";"Hellion";"Factory";79;2
"Unit";"Hellion";"Factory";79;2
"Building";"Factory";NA;74;0
"Building";"FactoryTechLab";NA;87;0
"Unit";"Hellion";"Factory";87;2
"Unit";"Hellion";"Factory";88;2
"Building";"Armory";NA;82;0
"Building";"Armory";NA;82;0
"Building";"CommandCenter";NA;80;0
"Unit";"Hellion";"Factory";90;2
"Unit";"Hellion";"Factory";92;2
"Unit";"Hellion";"Factory";92;2
"Unit";"Hellion";"Factory";100;2
"Unit";"Hellion";"Factory";100;2
"Unit";"Hellion";"Factory";105;2
"Unit";"Hellion";"Factory";105;2
"Unit";"Hellion";"Factory";105;2
"Unit";"Hellion";"Factory";110;2
"Upgrade";"TerranVehicleWeaponsLevel1";"Armory";100;0
"Unit";"Hellion";"Factory";112;2
"Building";"EngineeringBay";NA;112;0
"Unit";"Hellion";"Factory";116;2
"Unit";"Hellion";"Factory";116;2
"Unit";"Hellion";"Factory";116;2
"Unit";"Hellion";"Factory";116;2
"Unit";"Hellion";"Factory";117;2
"Unit";"Hellion";"Factory";119;2
"Building";"SensorTower";NA;126;0
"Building";"Refinery";NA;126;0
"Building";"Refinery";NA;126;0
"Unit";"Hellion";"Factory";130;2
"Unit";"Hellion";"Factory";130;2
"Unit";"Hellion";"Factory";130;2
"Unit";"Hellion";"Factory";140;2
"Unit";"Hellion";"Factory";140;2
"Unit";"Hellion";"Factory";140;2
