"Type";"UnitName";"OnBuilding";"TotalSupply";"Supply"
"Unit";"SCV";"Command Center";12;1
"Unit";"SCV";"Command Center";12;1
"Unit";"SCV";"Command Center";13;1
"Building";"SupplyDepot";NA;13;0
"Building";"Refinery";NA;14;0
"Unit";"SCV";"Command Center";15;1
"Unit";"SCV";"Command Center";15;1
"Unit";"SCV";"Command Center";17;1
"Unit";"SCV";"Command Center";17;1
"Building";"Barracks";NA;15;0
"Unit";"Reaper";"Barracks";19;1
"Unit";"SCV";"Command Center";19;1
"Unit";"SCV";"Command Center";20;1
"Unit";"SCV";"Command Center";21;1
"Building";"Refinery";NA;21;0
"Building";"SupplyDepot";NA;21;0
"Building";"Factory";NA;19;0
"Building";"BarracksReactor";NA;20;0
"Unit";"SCV";"Command Center";23;1
"Building";"CommandCenter";NA;19;0
"Unit";"SCV";"Command Center";23;1
"Building";"BarracksTechLab";NA;24;0
"Unit";"Hellion";"Factory";24;2
"Unit";"Hellion";"Factory";24;2
"Unit";"SCV";"Command Center";25;1
"Building";"Starport";NA;23;0
"Unit";"SCV";"Command Center";29;1
"Building";"SupplyDepot";NA;25;0
"Unit";"SCV";"Command Center";30;1
"Unit";"Hellion";"Factory";30;2
"Unit";"SCV";"Command Center";31;1
"Unit";"Hellion";"Factory";30;2
"Unit";"SCV";"Command Center";32;1
"Unit";"SCV";"Command Center";34;1
"Building";"SupplyDepot";NA;34;0
"Unit";"SCV";"Command Center";38;1
"Unit";"SCV";"Command Center";39;1
"Unit";"Hellion";"Factory";37;2
"Unit";"Hellion";"Factory";37;2
"Unit";"SCV";"Command Center";39;1
"Unit";"SCV";"Command Center";41;1
"Building";"SupplyDepot";NA;40;0
"Unit";"SCV";"Command Center";45;1
"Unit";"Hellion";"Factory";41;2
"Unit";"Hellion";"Factory";43;2
"Unit";"SCV";"Command Center";46;1
"Unit";"SCV";"Command Center";47;1
"Unit";"SCV";"Command Center";52;1
"Unit";"SCV";"Command Center";54;1
"Unit";"Liberator";"Starport";46;3
"Unit";"SCV";"Command Center";55;1
"Unit";"SCV";"Command Center";55;1
"Building";"Refinery";NA;55;0
"Building";"Refinery";NA;55;0
"Unit";"Cyclone";"Factory";55;3
"Unit";"Cyclone";"Factory";55;3
"Unit";"SCV";"Command Center";67;1
"Unit";"SCV";"Command Center";67;1
"Unit";"SCV";"Command Center";69;1
"Unit";"Hellion";"Factory";67;2
"Unit";"Banshee";"Starport";60;3
"Unit";"SCV";"Command Center";69;1
"Building";"CommandCenter";NA;53;0
"Unit";"Hellion";"Factory";67;2
"Unit";"SCV";"Command Center";69;1
"Unit";"SCV";"Command Center";75;1
"Building";"Armory";NA;67;0
"Building";"Armory";NA;67;0
"Building";"BarracksTechLab";NA;76;0
"Building";"SupplyDepot";NA;75;0
"Building";"SupplyDepot";NA;76;0
"Unit";"SCV";"Command Center";80;1
"Unit";"SCV";"Command Center";80;1
"Building";"SupplyDepot";NA;78;0
"Building";"Factory";NA;69;0
"Building";"Factory";NA;69;0
"Unit";"Hellion";"Factory";80;2
"Unit";"Hellion";"Factory";80;2
"Unit";"SCV";"Command Center";80;1
"Building";"StarportReactor";NA;79;0
"Unit";"SCV";"Command Center";86;1
"Unit";"Hellion";"Factory";87;2
"Unit";"Hellion";"Factory";87;2
"Unit";"SCV";"Command Center";88;1
"Unit";"SCV";"Command Center";88;1
"Building";"SupplyDepot";NA;88;0
"Building";"SupplyDepot";NA;88;0
"Unit";"SCV";"Command Center";94;1
"Unit";"Thor";"Factory";87;6
"Unit";"Hellion";"Factory";93;2
"Building";"Refinery";NA;94;0
"Building";"Refinery";NA;94;0
"Unit";"SCV";"Command Center";94;1
"Unit";"Thor";"Factory";88;6
"Unit";"SCV";"Command Center";94;1
"Unit";"SCV";"Command Center";95;1
"Unit";"Medivac";"Starport";93;2
"Unit";"Medivac";"Starport";94;2
"Building";"SupplyDepot";NA;94;0
"Building";"SupplyDepot";NA;94;0
"Unit";"SCV";"Command Center";103;1
"Unit";"SCV";"Command Center";110;1
"Unit";"SCV";"Command Center";116;1
"Unit";"Hellion";"Factory";110;2
"Unit";"SCV";"Command Center";118;1
"Unit";"SCV";"Command Center";118;1
"Unit";"Hellion";"Factory";117;2
"Unit";"SCV";"Command Center";118;1
"Upgrade";"TerranVehicleWeaponsLevel1";"Armory";87;0
"Upgrade";"TerranVehicleAndShipArmorsLevel1";"Armory";88;0
"Unit";"SCV";"Command Center";123;1
"Unit";"SCV";"Command Center";123;1
"Unit";"Hellion";"Factory";121;2
"Building";"Factory";NA;118;0
"Unit";"Hellion";"Factory";126;2
"Unit";"SCV";"Command Center";130;1
"Unit";"SCV";"Command Center";130;1
"Unit";"Hellion";"Factory";130;2
"Unit";"Hellion";"Factory";130;2
"Building";"SupplyDepot";NA;130;0
"Building";"SupplyDepot";NA;130;0
"Building";"Factory";NA;126;0
"Unit";"Hellion";"Factory";130;2
"Unit";"Hellion";"Factory";134;2
"Unit";"Hellion";"Factory";138;2
"Unit";"Medivac";"Starport";138;2
"Unit";"Medivac";"Starport";138;2
"Unit";"Hellion";"Factory";138;2
"Building";"FactoryTechLab";NA;140;0
"Building";"FactoryTechLab";NA;142;0
"Unit";"Hellion";"Factory";140;2
"Building";"SupplyDepot";NA;142;0
"Building";"SupplyDepot";NA;142;0
"Unit";"Hellion";"Factory";142;2
"Building";"CommandCenter";NA;130;0
"Unit";"Hellion";"Factory";150;2
"Building";"EngineeringBay";NA;148;0
"Unit";"Hellion";"Factory";150;2
"Unit";"Medivac";"Starport";152;2
"Unit";"Medivac";"Starport";152;2
"Building";"Refinery";NA;156;0
"Building";"Refinery";NA;156;0
"Unit";"Hellion";"Factory";156;2
"Unit";"Hellion";"Factory";158;2
"Unit";"SCV";"Command Center";160;1
"Unit";"SCV";"Command Center";160;1
"Unit";"Hellion";"Factory";158;2
"Unit";"SCV";"Command Center";166;1
"Unit";"SCV";"Command Center";166;1
"Building";"SensorTower";NA;166;0
"Unit";"Hellion";"Factory";164;2
"Building";"Refinery";NA;168;0
"Building";"CommandCenter";NA;152;0
"Unit";"SCV";"Command Center";174;1
"Unit";"Hellion";"Factory";170;2
"Unit";"SCV";"Command Center";174;1
"Unit";"Hellion";"Factory";172;2
"Unit";"Hellion";"Factory";172;2
"Unit";"Medivac";"Starport";172;2
"Unit";"Medivac";"Starport";172;2
"Unit";"Hellion";"Factory";174;2
"Unit";"Hellion";"Factory";174;2
"Upgrade";"TerranVehicleWeaponsLevel2";"Armory";152;0
"Upgrade";"TerranVehicleAndShipArmorsLevel2";"Armory";152;0
"Unit";"Hellion";"Factory";182;2
"Unit";"Hellion";"Factory";182;2
"Unit";"Hellion";"Factory";182;2
"Unit";"Hellion";"Factory";182;2
"Unit";"Hellion";"Factory";190;2
"Unit";"SCV";"Command Center";194;1
"Unit";"SCV";"Command Center";194;1
"Building";"SensorTower";NA;190;0
"Unit";"Hellion";"Factory";190;2
"Unit";"Hellion";"Factory";192;2
