"type";"unit_name";"on_building";"total_supply";"supply"
"Building";"Refinery";NA;14;0
"Building";"Barracks";NA;15;0
"Unit";"Reaper";"Barracks";19;1
"Building";"Refinery";NA;21;0
"Building";"Factory";NA;19;0
"Building";"BarracksReactor";NA;20;0
"Building";"CommandCenter";NA;19;0
"Building";"BarracksTechLab";NA;24;0
"Unit";"Hellion";"Factory";24;2
"Unit";"Hellion";"Factory";24;2
"Building";"Starport";NA;23;0
"Unit";"Hellion";"Factory";30;2
"Unit";"Hellion";"Factory";30;2
"Unit";"Hellion";"Factory";37;2
"Unit";"Hellion";"Factory";37;2
"Unit";"Hellion";"Factory";41;2
"Unit";"Hellion";"Factory";43;2
"Unit";"Liberator";"Starport";46;3
"Building";"Refinery";NA;55;0
"Building";"Refinery";NA;55;0
"Unit";"Cyclone";"Factory";55;3
"Unit";"Cyclone";"Factory";55;3
"Unit";"Hellion";"Factory";67;2
"Unit";"Banshee";"Starport";60;3
"Building";"CommandCenter";NA;53;0
"Unit";"Hellion";"Factory";67;2
"Building";"Armory";NA;67;0
"Building";"Armory";NA;67;0
"Building";"BarracksTechLab";NA;76;0
"Building";"Factory";NA;69;0
"Building";"Factory";NA;69;0
"Unit";"Hellion";"Factory";80;2
"Unit";"Hellion";"Factory";80;2
"Building";"StarportReactor";NA;79;0
"Unit";"Hellion";"Factory";87;2
"Unit";"Hellion";"Factory";87;2
"Unit";"Thor";"Factory";87;6
"Unit";"Hellion";"Factory";93;2
"Building";"Refinery";NA;94;0
"Building";"Refinery";NA;94;0
"Unit";"Thor";"Factory";88;6
"Unit";"Medivac";"Starport";93;2
"Unit";"Medivac";"Starport";94;2
"Unit";"Hellion";"Factory";110;2
"Unit";"Hellion";"Factory";117;2
"Upgrade";"TerranVehicleWeaponsLevel1";"Armory";87;0
"Unit";"Hellion";"Factory";121;2
"Building";"Factory";NA;118;0
"Unit";"Hellion";"Factory";126;2
"Unit";"Hellion";"Factory";130;2
"Unit";"Hellion";"Factory";130;2
"Building";"Factory";NA;126;0
"Unit";"Hellion";"Factory";130;2
"Unit";"Hellion";"Factory";134;2
"Unit";"Hellion";"Factory";138;2
"Unit";"Medivac";"Starport";138;2
"Unit";"Medivac";"Starport";138;2
"Unit";"Hellion";"Factory";138;2
"Building";"FactoryTechLab";NA;140;0
"Building";"FactoryTechLab";NA;142;0
"Unit";"Hellion";"Factory";140;2
"Unit";"Hellion";"Factory";142;2
"Building";"CommandCenter";NA;130;0
"Unit";"Hellion";"Factory";150;2
"Building";"EngineeringBay";NA;148;0
"Unit";"Hellion";"Factory";150;2
"Unit";"Medivac";"Starport";152;2
"Unit";"Medivac";"Starport";152;2
"Building";"Refinery";NA;156;0
"Building";"Refinery";NA;156;0
"Unit";"Hellion";"Factory";156;2
"Unit";"Hellion";"Factory";158;2
"Unit";"Hellion";"Factory";158;2
"Building";"SensorTower";NA;166;0
"Unit";"Hellion";"Factory";164;2
"Building";"Refinery";NA;168;0
"Building";"CommandCenter";NA;152;0
"Unit";"Hellion";"Factory";170;2
"Unit";"Hellion";"Factory";172;2
"Unit";"Hellion";"Factory";172;2
"Unit";"Medivac";"Starport";172;2
"Unit";"Medivac";"Starport";172;2
"Unit";"Hellion";"Factory";174;2
"Unit";"Hellion";"Factory";174;2
"Upgrade";"TerranVehicleWeaponsLevel2";"Armory";152;0
"Unit";"Hellion";"Factory";182;2
"Unit";"Hellion";"Factory";182;2
"Unit";"Hellion";"Factory";182;2
"Unit";"Hellion";"Factory";182;2
"Unit";"Hellion";"Factory";190;2
"Building";"SensorTower";NA;190;0
"Unit";"Hellion";"Factory";190;2
"Unit";"Hellion";"Factory";192;2
