"type";"unit_name";"on_building";"total_supply";"supply"
"Building";"Refinery";NA;15;0
"Building";"Barracks";NA;15;0
"Unit";"Reaper";"Barracks";19;1
"Unit";"Marine";"Barracks";21;1
"Building";"Refinery";NA;21;0
"Building";"Factory";NA;20;0
"Building";"CommandCenter";NA;19;0
"Building";"BarracksReactor";NA;23;0
"Building";"BarracksTechLab";NA;26;0
"Building";"Starport";NA;25;0
"Unit";"Hellion";"Factory";26;2
"Unit";"Hellion";"Factory";26;2
"Unit";"Marauder";"Barracks";27;2
"Unit";"Hellion";"Factory";33;2
"Unit";"Hellion";"Factory";33;2
"Unit";"Marauder";"Barracks";37;2
"Unit";"Hellion";"Factory";37;2
"Unit";"Hellion";"Factory";39;2
"Unit";"Medivac";"Starport";41;2
"Unit";"Marauder";"Barracks";50;2
"Unit";"Hellion";"Factory";50;2
"Unit";"Hellion";"Factory";50;2
"Building";"Armory";NA;45;0
"Unit";"Cyclone";"Factory";62;3
"Unit";"Cyclone";"Factory";62;3
"Building";"Refinery";NA;62;0
"Building";"Refinery";NA;62;0
"Building";"CommandCenter";NA;60;0
"Unit";"Hellion";"Factory";68;2
"Unit";"Hellion";"Factory";68;2
"Unit";"Banshee";"Starport";68;3
"Unit";"Hellion";"Factory";74;2
"Unit";"Hellion";"Factory";74;2
"Unit";"Hellion";"Factory";79;2
"Unit";"Hellion";"Factory";83;2
"Building";"Factory";NA;74;0
"Building";"Factory";NA;74;0
"Building";"Factory";NA;74;0
"Building";"Factory";NA;74;0
"Unit";"Raven";"Starport";79;2
"Unit";"Hellion";"Factory";87;2
"Building";"FactoryTechLab";NA;91;0
"Building";"FactoryTechLab";NA;91;0
"Building";"FactoryTechLab";NA;91;0
"Building";"FactoryReactor";NA;91;0
"Unit";"Hellion";"Factory";95;2
"Unit";"Hellion";"Factory";95;2
"Unit";"Thor";"Factory";95;6
"Unit";"Hellion";"Factory";95;2
"Unit";"Hellion";"Factory";95;2
"Unit";"Hellion";"Factory";95;2
"Unit";"Hellion";"Factory";95;2
"Unit";"Hellion";"Factory";97;2
"Upgrade";"TerranVehicleWeaponsLevel1";"Armory";91;0
"Unit";"Hellion";"Factory";102;2
"Unit";"Hellion";"Factory";108;2
"Unit";"Hellion";"Factory";110;2
"Unit";"Medivac";"Starport";102;2
"Unit";"Medivac";"Starport";102;2
"Unit";"Hellion";"Factory";121;2
"Unit";"Hellion";"Factory";121;2
"Unit";"Hellion";"Factory";124;2
"Unit";"Hellion";"Factory";126;2
"Unit";"Thor";"Factory";112;6
"Building";"Refinery";NA;132;0
"Building";"Refinery";NA;134;0
"Unit";"Hellion";"Factory";138;2
"Unit";"Hellion";"Factory";138;2
"Unit";"Hellion";"Factory";138;2
"Unit";"Hellion";"Factory";141;2
"Unit";"Cyclone";"Factory";152;3
"Unit";"Hellion";"Factory";160;2
"Unit";"Hellion";"Factory";160;2
"Unit";"Hellion";"Factory";163;2
"Unit";"Hellion";"Factory";165;2
"Unit";"Hellion";"Factory";170;2
"Unit";"Hellion";"Factory";170;2
"Unit";"Hellion";"Factory";170;2
"Unit";"Marine";"Barracks";177;1
"Unit";"Hellion";"Factory";177;2
"Unit";"Marine";"Barracks";183;1
"Unit";"Hellion";"Factory";183;2
"Unit";"Hellion";"Factory";186;2
"Unit";"Hellion";"Factory";187;2
"Building";"CommandCenter";NA;173;0
"Unit";"Hellion";"Factory";195;2
"Unit";"Hellion";"Factory";195;2
"Building";"Armory";NA;191;0
"Unit";"Cyclone";"Factory";195;3
"Unit";"Cyclone";"Factory";195;3
"Unit";"Cyclone";"Factory";195;3
"Building";"EngineeringBay";NA;195;0
"Unit";"Hellion";"Factory";195;2
"Unit";"Hellion";"Factory";195;2
"Unit";"Cyclone";"Factory";199;3
"Unit";"Cyclone";"Factory";210;3
"Unit";"Hellion";"Factory";212;2
"Unit";"Hellion";"Factory";215;2
