"Type";"UnitName";"OnBuilding";"TotalSupply";"Supply"
"Unit";"SCV";"Command Center";12;1
"Unit";"SCV";"Command Center";12;1
"Unit";"SCV";"Command Center";13;1
"Building";"SupplyDepot";NA;13;0
"Unit";"SCV";"Command Center";15;1
"Building";"Refinery";NA;14;0
"Unit";"SCV";"Command Center";15;1
"Unit";"SCV";"Command Center";16;1
"Unit";"SCV";"Command Center";17;1
"Building";"Barracks";NA;15;0
"Unit";"Reaper";"Barracks";19;1
"Unit";"SCV";"Command Center";19;1
"Unit";"SCV";"Command Center";21;1
"Building";"SupplyDepot";NA;20;0
"Unit";"SCV";"Command Center";21;1
"Building";"Refinery";NA;21;0
"Building";"Factory";NA;19;0
"Building";"BarracksReactor";NA;20;0
"Unit";"SCV";"Command Center";22;1
"Building";"CommandCenter";NA;19;0
"Unit";"SCV";"Command Center";24;1
"Unit";"Marine";"Barracks";23;1
"Unit";"Marine";"Barracks";23;1
"Unit";"Cyclone";"Factory";24;3
"Unit";"Marine";"Barracks";25;1
"Unit";"Marine";"Barracks";26;1
"Unit";"SCV";"Command Center";27;1
"Building";"Bunker";NA;23;0
"Building";"Bunker";NA;25;0
"Unit";"SCV";"Command Center";32;1
"Unit";"SCV";"Command Center";33;1
"Unit";"SCV";"Command Center";33;1
"Unit";"SCV";"Command Center";34;1
"Unit";"SCV";"Command Center";35;1
"Building";"BarracksTechLab";NA;35;0
"Unit";"Hellion";"Factory";35;2
"Unit";"Hellion";"Factory";35;2
"Unit";"SCV";"Command Center";37;1
"Unit";"SCV";"Command Center";37;1
"Building";"SupplyDepot";NA;36;0
"Building";"Starport";NA;34;0
"Unit";"SCV";"Command Center";43;1
"Unit";"SCV";"Command Center";43;1
"Unit";"SCV";"Command Center";46;1
"Unit";"SCV";"Command Center";46;1
"Building";"SupplyDepot";NA;46;0
"Unit";"SCV";"Command Center";48;1
"Unit";"SCV";"Command Center";48;1
"Unit";"Hellion";"Factory";46;2
"Unit";"Hellion";"Factory";46;2
"Building";"SupplyDepot";NA;48;0
"Unit";"SCV";"Command Center";48;1
"Unit";"SCV";"Command Center";49;1
"Unit";"SCV";"Command Center";54;1
"Unit";"SCV";"Command Center";55;1
"Unit";"Hellion";"Factory";56;2
"Unit";"Hellion";"Factory";56;2
"Building";"CommandCenter";NA;44;0
"Unit";"SCV";"Command Center";57;1
"Unit";"SCV";"Command Center";58;1
"Unit";"Marine";"Barracks";56;1
"Unit";"Liberator";"Starport";48;3
"Building";"Refinery";NA;58;0
"Building";"Refinery";NA;58;0
"Unit";"SCV";"Command Center";62;1
"Unit";"SCV";"Command Center";63;1
"Building";"EngineeringBay";NA;58;0
"Building";"EngineeringBay";NA;58;0
"Unit";"SCV";"Command Center";68;1
"Unit";"SCV";"Command Center";69;1
"Unit";"SCV";"Command Center";70;1
"Unit";"SCV";"Command Center";71;1
"Building";"StarportReactor";NA;68;0
"Building";"FactoryReactor";NA;70;0
"Unit";"SCV";"Command Center";74;1
"Unit";"SCV";"Command Center";74;1
"Unit";"Marine";"Barracks";74;1
"Building";"Barracks";NA;68;0
"Building";"Barracks";NA;70;0
"Unit";"SCV";"Command Center";76;1
"Building";"FactoryTechLab";NA;77;0
"Unit";"SCV";"Command Center";78;1
"Unit";"SCV";"Command Center";78;1
"Unit";"Marine";"Barracks";78;1
"Unit";"Marine";"Barracks";78;1
"Unit";"Marine";"Barracks";78;1
"Unit";"Marine";"Barracks";78;1
"Unit";"Marine";"Barracks";78;1
"Building";"SupplyDepot";NA;78;0
"Unit";"SCV";"Command Center";81;1
"Unit";"Medivac";"Starport";78;2
"Unit";"Medivac";"Starport";78;2
"Upgrade";"Stimpack";"TechLab";70;0
"Unit";"Marine";"Barracks";80;1
"Unit";"Marine";"Barracks";81;1
"Unit";"Marine";"Barracks";82;1
"Unit";"Marine";"Barracks";83;1
"Unit";"Marine";"Barracks";84;1
"Building";"Armory";NA;78;0
"Unit";"Marine";"Barracks";95;1
"Unit";"Marine";"Barracks";95;1
"Unit";"Marine";"Barracks";95;1
"Unit";"Marine";"Barracks";95;1
"Unit";"Marine";"Barracks";95;1
"Upgrade";"TerranInfantryWeaponsLevel1";"EngineeringBay";77;0
"Upgrade";"TerranInfantryArmorsLevel1";"EngineeringBay";77;0
"Building";"SupplyDepot";NA;97;0
"Building";"SupplyDepot";NA;97;0
"Building";"SupplyDepot";NA;97;0
"Building";"SupplyDepot";NA;97;0
"Building";"SupplyDepot";NA;100;0
"Unit";"SCV";"Command Center";100;1
"Unit";"Marine";"Barracks";100;1
"Unit";"Marine";"Barracks";100;1
"Unit";"Marine";"Barracks";100;1
"Unit";"SCV";"Command Center";100;1
"Unit";"SCV";"Command Center";105;1
"Unit";"SCV";"Command Center";105;1
"Building";"Refinery";NA;105;0
"Building";"Refinery";NA;105;0
"Building";"SupplyDepot";NA;105;0
"Building";"SupplyDepot";NA;105;0
"Unit";"SCV";"Command Center";107;1
"Unit";"SCV";"Command Center";107;1
"Unit";"SCV";"Command Center";107;1
"Unit";"SCV";"Command Center";107;1
"Unit";"SCV";"Command Center";108;1
"Unit";"SCV";"Command Center";109;1
"Building";"SupplyDepot";NA;107;0
"Building";"SupplyDepot";NA;107;0
"Building";"SupplyDepot";NA;107;0
"Unit";"Marine";"Barracks";110;1
"Unit";"Marine";"Barracks";110;1
"Unit";"Marine";"Barracks";110;1
"Unit";"Marine";"Barracks";110;1
"Building";"Bunker";NA;107;0
"Unit";"Marine";"Barracks";110;1
"Unit";"SCV";"Command Center";115;1
"Unit";"SCV";"Command Center";115;1
"Unit";"Marine";"Barracks";113;1
"Unit";"Marine";"Barracks";114;1
"Unit";"Marine";"Barracks";115;1
"Unit";"Marine";"Barracks";116;1
"Unit";"Marine";"Barracks";117;1
"Building";"Refinery";NA;118;0
"Building";"SupplyDepot";NA;120;0
"Building";"StarportReactor";NA;113;0
"Unit";"Marine";"Barracks";125;1
"Unit";"Marine";"Barracks";125;1
"Unit";"Marine";"Barracks";125;1
"Unit";"Marine";"Barracks";125;1
"Unit";"Marine";"Barracks";125;1
"Building";"Barracks";NA;113;0
"Unit";"SCV";"Command Center";125;1
"Unit";"SCV";"Command Center";125;1
"Unit";"SCV";"Command Center";125;1
"Building";"SupplyDepot";NA;125;0
"Building";"Barracks";NA;113;0
"Building";"SupplyDepot";NA;125;0
"Unit";"SCV";"Command Center";130;1
"Unit";"SCV";"Command Center";131;1
"Unit";"SCV";"Command Center";132;1
"Unit";"Marine";"Barracks";132;1
"Unit";"Marine";"Barracks";132;1
"Unit";"Marine";"Barracks";132;1
"Unit";"Marine";"Barracks";133;1
"Unit";"Marine";"Barracks";133;1
"Unit";"Marine";"Barracks";133;1
"Upgrade";"TerranVehicleWeaponsLevel1";"Armory";110;0
"Building";"SupplyDepot";NA;133;0
"Building";"Refinery";NA;133;0
"Building";"BarracksReactor";NA;133;0
"Upgrade";"TerranInfantryWeaponsLevel2";"EngineeringBay";112;0
"Upgrade";"TerranInfantryArmorsLevel2";"EngineeringBay";113;0
"Building";"CommandCenter";NA;120;0
"Unit";"Marine";"Barracks";142;1
"Unit";"Marine";"Barracks";142;1
"Unit";"Marine";"Barracks";142;1
"Unit";"Marine";"Barracks";142;1
"Unit";"Marine";"Barracks";142;1
"Unit";"Marine";"Barracks";142;1
"Unit";"Marine";"Barracks";142;1
"Unit";"SCV";"Command Center";142;1
"Unit";"SCV";"Command Center";142;1
"Unit";"SCV";"Command Center";142;1
"Building";"SupplyDepot";NA;142;0
"Unit";"Medivac";"Starport";142;2
"Unit";"Medivac";"Starport";142;2
"Unit";"Marine";"Barracks";142;1
"Unit";"Marine";"Barracks";143;1
"Unit";"Marine";"Barracks";143;1
"Unit";"SCV";"Command Center";156;1
"Unit";"SCV";"Command Center";156;1
"Unit";"SCV";"Command Center";156;1
"Building";"Factory";NA;142;0
"Building";"Factory";NA;142;0
"Unit";"Medivac";"Starport";152;2
"Building";"SensorTower";NA;159;0
"Unit";"Medivac";"Starport";154;2
"Unit";"Marine";"Barracks";159;1
"Unit";"Marine";"Barracks";159;1
"Unit";"Marine";"Barracks";159;1
"Unit";"Marine";"Barracks";159;1
"Unit";"Marine";"Barracks";159;1
"Building";"SensorTower";NA;162;0
"Unit";"Marine";"Barracks";162;1
"Unit";"Marine";"Barracks";162;1
"Unit";"Marine";"Barracks";162;1
"Unit";"Marine";"Barracks";162;1
"Building";"FactoryTechLab";NA;162;0
"Building";"FactoryTechLab";NA;162;0
"Unit";"Marine";"Barracks";166;1
"Unit";"SCV";"Command Center";171;1
"Unit";"SCV";"Command Center";172;1
"Unit";"SCV";"Command Center";172;1
"Building";"CommandCenter";NA;149;0
"Building";"Refinery";NA;175;0
"Building";"Refinery";NA;175;0
"Unit";"Medivac";"Starport";171;2
"Unit";"Medivac";"Starport";171;2
"Unit";"Marine";"Barracks";179;1
"Unit";"Marine";"Barracks";179;1
"Unit";"Marine";"Barracks";179;1
"Unit";"Marine";"Barracks";179;1
"Unit";"Marine";"Barracks";179;1
"Unit";"Marine";"Barracks";179;1
"Unit";"Marine";"Barracks";179;1
"Unit";"Marine";"Barracks";179;1
"Unit";"Marine";"Barracks";179;1
"Building";"Factory";NA;166;0
"Unit";"Marine";"Barracks";183;1
"Unit";"Marine";"Barracks";184;1
"Unit";"Marine";"Barracks";184;1
"Unit";"Marine";"Barracks";184;1
"Unit";"Marine";"Barracks";187;1
"Unit";"Marine";"Barracks";188;1
"Unit";"Marine";"Barracks";188;1
"Unit";"Marine";"Barracks";190;1
"Unit";"Marine";"Barracks";192;1
"Building";"Barracks";NA;179;0
"Building";"Barracks";NA;179;0
"Building";"Barracks";NA;179;0
"Unit";"Marine";"Barracks";192;1
"Unit";"Marine";"Barracks";193;1
"Unit";"Marine";"Barracks";193;1
"Unit";"Marine";"Barracks";193;1
"Unit";"Marine";"Barracks";196;1
"Unit";"Marine";"Barracks";197;1
"Unit";"Marine";"Barracks";197;1
"Unit";"Marine";"Barracks";199;1
"Upgrade";"TerranVehicleWeaponsLevel2";"Armory";159;0
"Unit";"Marine";"Barracks";200;1
"Building";"FactoryTechLab";NA;201;0
"Unit";"Marine";"Barracks";201;1
"Unit";"SCV";"Command Center";210;1
"Unit";"SCV";"Command Center";210;1
"Unit";"Marine";"Barracks";202;1
"Unit";"Marine";"Barracks";202;1
"Unit";"Marine";"Barracks";202;1
"Unit";"Marine";"Barracks";205;1
"Unit";"Marine";"Barracks";206;1
"Unit";"Marine";"Barracks";206;1
"Unit";"Marine";"Barracks";208;1
"Building";"BarracksTechLab";NA;209;0
"Building";"BarracksTechLab";NA;209;0
"Building";"BarracksTechLab";NA;209;0
"Unit";"Marine";"Barracks";209;1
"Building";"Refinery";NA;210;0
"Unit";"Marine";"Barracks";210;1
"Unit";"Marine";"Barracks";212;1
"Unit";"Marine";"Barracks";221;1
"Unit";"Marine";"Barracks";221;1
"Unit";"Marine";"Barracks";221;1
"Unit";"Marine";"Barracks";221;1
"Unit";"Marine";"Barracks";221;1
"Unit";"Marine";"Barracks";221;1
"Unit";"Marauder";"Barracks";220;2
"Unit";"Marauder";"Barracks";220;2
"Unit";"Marauder";"Barracks";220;2
"Unit";"Marauder";"Barracks";220;2
"Unit";"SCV";"Command Center";223;1
"Unit";"SCV";"Command Center";223;1
"Unit";"SCV";"Command Center";223;1
"Unit";"SCV";"Command Center";223;1
"Unit";"Medivac";"Starport";221;2
"Unit";"Medivac";"Starport";221;2
"Building";"Starport";NA;221;0
"Building";"Starport";NA;221;0
"Unit";"Marine";"Barracks";245;1
"Unit";"Marine";"Barracks";245;1
"Unit";"Marine";"Barracks";245;1
"Unit";"Marine";"Barracks";245;1
"Unit";"Marine";"Barracks";245;1
"Unit";"Marine";"Barracks";245;1
"Unit";"Marine";"Barracks";245;1
"Upgrade";"TerranInfantryArmorsLevel3";"EngineeringBay";192;0
"Unit";"Marauder";"Barracks";245;2
"Unit";"Marauder";"Barracks";245;2
"Unit";"Marauder";"Barracks";245;2
"Unit";"Marauder";"Barracks";245;2
"Upgrade";"TerranInfantryWeaponsLevel3";"EngineeringBay";192;0
"Unit";"Marine";"Barracks";260;1
"Unit";"Marine";"Barracks";260;1
"Unit";"Marine";"Barracks";260;1
"Unit";"Marine";"Barracks";260;1
"Unit";"Marine";"Barracks";260;1
"Unit";"Marine";"Barracks";260;1
"Unit";"Marine";"Barracks";260;1
"Unit";"Marine";"Barracks";260;1
"Building";"StarportTechLab";NA;260;0
"Unit";"Marauder";"Barracks";260;2
"Unit";"Marauder";"Barracks";260;2
"Unit";"Marauder";"Barracks";260;2
"Unit";"Marauder";"Barracks";260;2
"Unit";"Marine";"Barracks";260;1
"Unit";"Marine";"Barracks";261;1
"Unit";"Marine";"Barracks";261;1
"Unit";"Marine";"Barracks";263;1
"Unit";"Marine";"Barracks";268;1
"Unit";"Marine";"Barracks";268;1
"Unit";"Marine";"Barracks";268;1
"Unit";"Marine";"Barracks";268;1
"Unit";"Marauder";"Barracks";268;2
"Unit";"Marauder";"Barracks";270;2
"Unit";"Marauder";"Barracks";272;2
"Unit";"Marauder";"Barracks";274;2
"Unit";"Marine";"Barracks";276;1
"Unit";"Marine";"Barracks";277;1
"Unit";"Marine";"Barracks";277;1
"Unit";"Marine";"Barracks";279;1
"Unit";"Marine";"Barracks";280;1
"Unit";"Marine";"Barracks";281;1
"Unit";"Marine";"Barracks";282;1
"Unit";"Marine";"Barracks";284;1
"Unit";"Marine";"Barracks";288;1
"Upgrade";"TerranVehicleWeaponsLevel3";"Armory";237;0
"Unit";"Marauder";"Barracks";284;2
"Unit";"Marauder";"Barracks";286;2
