"Type";"UnitName";"OnBuilding";"TotalSupply";"Supply"
"Unit";"SCV";"Command Center";12;1
"Unit";"SCV";"Command Center";12;1
"Unit";"SCV";"Command Center";13;1
"Building";"SupplyDepot";NA;13;0
"Building";"Refinery";NA;14;0
"Unit";"SCV";"Command Center";15;1
"Unit";"SCV";"Command Center";15;1
"Unit";"SCV";"Command Center";16;1
"Unit";"SCV";"Command Center";18;1
"Building";"Barracks";NA;15;0
"Unit";"Reaper";"Barracks";19;1
"Unit";"SCV";"Command Center";19;1
"Unit";"SCV";"Command Center";21;1
"Building";"Refinery";NA;21;0
"Unit";"SCV";"Command Center";22;1
"Building";"SupplyDepot";NA;21;0
"Building";"BarracksReactor";NA;20;0
"Building";"Factory";NA;19;0
"Unit";"SCV";"Command Center";23;1
"Building";"CommandCenter";NA;19;0
"Unit";"SCV";"Command Center";23;1
"Unit";"Hellion";"Factory";24;2
"Unit";"Hellion";"Factory";24;2
"Unit";"SCV";"Command Center";25;1
"Building";"BarracksTechLab";NA;24;0
"Building";"Starport";NA;23;0
"Unit";"SCV";"Command Center";30;1
"Unit";"SCV";"Command Center";30;1
"Unit";"Cyclone";"Factory";30;3
"Unit";"SCV";"Command Center";32;1
"Unit";"SCV";"Command Center";32;1
"Building";"EngineeringBay";NA;31;0
"Building";"Refinery";NA;32;0
"Unit";"SCV";"Command Center";35;1
"Unit";"SCV";"Command Center";36;1
"Unit";"SCV";"Command Center";37;1
"Unit";"Banshee";"Starport";32;3
"Unit";"SCV";"Command Center";39;1
"Unit";"SCV";"Command Center";39;1
"Building";"SupplyDepot";NA;39;0
"Unit";"SCV";"Command Center";44;1
"Unit";"SCV";"Command Center";46;1
"Unit";"SCV";"Command Center";46;1
"Building";"MissileTurret";NA;45;0
"Unit";"Cyclone";"Factory";45;3
"Unit";"Cyclone";"Factory";45;3
"Building";"SupplyDepot";NA;45;0
"Building";"MissileTurret";NA;46;0
"Unit";"SCV";"Command Center";46;1
"Unit";"SCV";"Command Center";47;1
"Unit";"Banshee";"Starport";43;3
"Unit";"SCV";"Command Center";59;1
"Unit";"SCV";"Command Center";59;1
"Unit";"SCV";"Command Center";59;1
"Building";"Refinery";NA;59;0
"Unit";"Cyclone";"Factory";59;3
"Unit";"Cyclone";"Factory";59;3
"Unit";"SCV";"Command Center";61;1
"Building";"SupplyDepot";NA;59;0
"Building";"SupplyDepot";NA;61;0
"Unit";"SCV";"Command Center";61;1
"Unit";"Raven";"Starport";59;2
"Unit";"Hellion";"Factory";62;2
"Unit";"SCV";"Command Center";72;1
"Unit";"SCV";"Command Center";72;1
"Building";"CommandCenter";NA;54;0
"Unit";"SCV";"Command Center";74;1
"Unit";"SCV";"Command Center";75;1
"Building";"BarracksTechLab";NA;74;0
"Unit";"SCV";"Command Center";76;1
"Unit";"SCV";"Command Center";77;1
"Building";"MissileTurret";NA;78;0
"Building";"SupplyDepot";NA;78;0
"Building";"Factory";NA;76;0
"Building";"Factory";NA;76;0
"Building";"BarracksTechLab";NA;80;0
"Unit";"Cyclone";"Factory";80;3
"Unit";"Cyclone";"Factory";80;3
"Building";"SupplyDepot";NA;80;0
"Building";"SupplyDepot";NA;80;0
"Unit";"SCV";"Command Center";80;1
"Unit";"SCV";"Command Center";80;1
"Building";"MissileTurret";NA;80;0
"Unit";"Banshee";"Starport";80;3
"Building";"FactoryReactor";NA;80;0
"Building";"MissileTurret";NA;86;0
"Building";"MissileTurret";NA;86;0
"Unit";"Cyclone";"Factory";88;3
"Unit";"Cyclone";"Factory";88;3
"Building";"Factory";NA;80;0
"Unit";"Hellion";"Factory";91;2
"Unit";"Hellion";"Factory";91;2
"Unit";"Hellion";"Factory";91;2
"Unit";"Hellion";"Factory";94;2
"Unit";"SCV";"Command Center";101;1
"Unit";"SCV";"Command Center";101;1
"Unit";"Hellion";"Factory";105;2
"Unit";"Hellion";"Factory";105;2
"Unit";"Hellion";"Factory";105;2
"Unit";"Hellion";"Factory";105;2
"Unit";"SCV";"Command Center";105;1
"Unit";"SCV";"Command Center";106;1
"Building";"MissileTurret";NA;105;0
"Building";"MissileTurret";NA;105;0
"Building";"MissileTurret";NA;105;0
"Unit";"SCV";"Command Center";115;1
"Unit";"SCV";"Command Center";116;1
"Unit";"SCV";"Command Center";117;1
"Unit";"SCV";"Command Center";120;1
"Unit";"SCV";"Command Center";120;1
"Building";"MissileTurret";NA;120;0
"Building";"MissileTurret";NA;120;0
"Unit";"SCV";"Command Center";120;1
"Building";"MissileTurret";NA;120;0
"Unit";"SCV";"Command Center";120;1
"Unit";"Hellion";"Factory";120;2
"Unit";"Hellion";"Factory";120;2
"Unit";"Hellion";"Factory";120;2
"Unit";"Hellion";"Factory";128;2
"Building";"Refinery";NA;128;0
"Building";"MissileTurret";NA;130;0
"Unit";"Hellion";"Factory";130;2
"Building";"MissileTurret";NA;130;0
"Building";"MissileTurret";NA;130;0
"Building";"MissileTurret";NA;130;0
"Unit";"SCV";"Command Center";134;1
"Unit";"SCV";"Command Center";134;1
"Unit";"SCV";"Command Center";134;1
"Unit";"Hellion";"Factory";130;2
"Unit";"Hellion";"Factory";130;2
"Unit";"SCV";"Command Center";134;1
"Building";"Factory";NA;130;0
"Building";"MissileTurret";NA;137;0
"Building";"Armory";NA;130;0
"Building";"Armory";NA;132;0
"Building";"BarracksReactor";NA;141;0
"Unit";"Raven";"Starport";141;2
"Building";"Starport";NA;142;0
"Building";"FactoryTechLab";NA;142;0
"Unit";"Hellion";"Factory";142;2
"Unit";"Hellion";"Factory";142;2
"Building";"Refinery";NA;142;0
"Building";"SupplyDepot";NA;144;0
"Unit";"Hellion";"Factory";144;2
"Unit";"Hellion";"Factory";144;2
"Building";"SupplyDepot";NA;144;0
"Unit";"Raven";"Starport";144;2
"Building";"MissileTurret";NA;152;0
"Building";"SensorTower";NA;152;0
"Building";"MissileTurret";NA;152;0
"Unit";"Hellion";"Factory";152;2
"Unit";"Hellion";"Factory";152;2
"Unit";"Hellion";"Factory";152;2
"Building";"SupplyDepot";NA;152;0
"Building";"SupplyDepot";NA;152;0
"Building";"SupplyDepot";NA;152;0
"Building";"SupplyDepot";NA;154;0
"Unit";"Hellion";"Factory";160;2
"Unit";"Hellion";"Factory";160;2
"Unit";"Hellion";"Factory";160;2
"Unit";"Hellion";"Factory";160;2
"Unit";"Hellion";"Factory";160;2
"Unit";"Hellion";"Factory";170;2
"Unit";"Hellion";"Factory";170;2
"Unit";"Hellion";"Factory";170;2
"Unit";"Hellion";"Factory";170;2
"Unit";"Liberator";"Starport";170;3
"Unit";"Liberator";"Starport";170;3
"Upgrade";"TerranVehicleWeaponsLevel1";"Armory";160;0
"Unit";"Liberator";"Starport";170;3
"Unit";"Hellion";"Factory";181;2
"Unit";"Hellion";"Factory";181;2
"Unit";"Hellion";"Factory";181;2
"Unit";"Hellion";"Factory";181;2
"Building";"MissileTurret";NA;195;0
"Building";"CommandCenter";NA;170;0
"Unit";"Raven";"Starport";184;2
"Unit";"Hellion";"Factory";195;2
"Unit";"Hellion";"Factory";195;2
"Unit";"Hellion";"Factory";195;2
"Unit";"Hellion";"Factory";195;2
"Upgrade";"TerranVehicleAndShipArmorsLevel1";"Armory";178;0
"Unit";"Hellion";"Factory";197;2
"Unit";"Hellion";"Factory";197;2
"Unit";"Hellion";"Factory";201;2
"Unit";"Hellion";"Factory";201;2
"Unit";"Hellion";"Factory";205;2
"Unit";"Liberator";"Starport";195;3
