"type";"unit_name";"on_building";"total_supply";"supply"
"Building";"Refinery";NA;14;0
"Building";"Refinery";NA;16;0
"Building";"Barracks";NA;15;0
"Unit";"Reaper";"Barracks";19;1
"Building";"Factory";NA;19;0
"Unit";"Reaper";"Barracks";20;1
"Unit";"Hellion";"Factory";22;2
"Building";"Starport";NA;22;0
"Building";"BarracksTechLab";NA;27;0
"Unit";"Cyclone";"Factory";27;3
"Unit";"Raven";"Starport";29;2
"Unit";"Marine";"Barracks";34;1
"Unit";"Cyclone";"Factory";34;3
"Building";"CommandCenter";NA;32;0
"Building";"BarracksReactor";NA;41;0
"Unit";"Cyclone";"Factory";42;3
"Unit";"Raven";"Starport";41;2
"Building";"Barracks";NA;41;0
"Building";"Barracks";NA;41;0
"Unit";"Marine";"Barracks";43;1
"Unit";"Marine";"Barracks";43;1
"Unit";"Marine";"Barracks";52;1
"Unit";"Marine";"Barracks";52;1
"Building";"Refinery";NA;52;0
"Building";"BarracksTechLab";NA;52;0
"Building";"BarracksTechLab";NA;54;0
"Building";"EngineeringBay";NA;54;0
"Building";"Refinery";NA;59;0
"Unit";"Marine";"Barracks";59;1
"Unit";"Marine";"Barracks";59;1
"Unit";"Marine";"Barracks";59;1
"Unit";"Marine";"Barracks";59;1
"Unit";"Marine";"Barracks";65;1
"Unit";"Marine";"Barracks";65;1
"Unit";"Marine";"Barracks";65;1
"Unit";"Marine";"Barracks";70;1
"Unit";"Marine";"Barracks";70;1
"Building";"StarportReactor";NA;65;0
"Unit";"Marine";"Barracks";72;1
"Unit";"Marine";"Barracks";72;1
"Unit";"Marine";"Barracks";75;1
"Unit";"Marine";"Barracks";75;1
"Upgrade";"Stimpack";"TechLab";59;0
"Unit";"Marine";"Barracks";79;1
"Unit";"Medivac";"Starport";77;2
"Building";"CommandCenter";NA;67;0
"Unit";"Medivac";"Starport";79;2
"Unit";"Marine";"Barracks";83;1
"Unit";"Marine";"Barracks";83;1
"Unit";"Marine";"Barracks";83;1
"Building";"Barracks";NA;75;0
"Building";"Barracks";NA;75;0
"Upgrade";"TerranInfantryWeaponsLevel1";"EngineeringBay";67;0
"Unit";"Marine";"Barracks";88;1
"Building";"EngineeringBay";NA;86;0
"Unit";"Medivac";"Starport";88;2
"Building";"BarracksReactor";NA;94;0
"Unit";"Marine";"Barracks";99;1
"Building";"BarracksReactor";NA;94;0
"Unit";"Marine";"Barracks";99;1
"Unit";"Marine";"Barracks";99;1
"Unit";"Marine";"Barracks";99;1
"Unit";"Marine";"Barracks";101;1
"Unit";"Marine";"Barracks";109;1
"Unit";"Marine";"Barracks";109;1
"Unit";"Marine";"Barracks";109;1
"Unit";"Marine";"Barracks";109;1
"Unit";"Marine";"Barracks";109;1
"Building";"Armory";NA;107;0
"Unit";"Marine";"Barracks";118;1
"Unit";"Marine";"Barracks";118;1
"Unit";"Marine";"Barracks";118;1
"Unit";"Marine";"Barracks";118;1
"Unit";"Marine";"Barracks";118;1
"Unit";"Marine";"Barracks";118;1
"Unit";"Marine";"Barracks";118;1
"Unit";"Marine";"Barracks";118;1
"Unit";"Marine";"Barracks";118;1
"Unit";"Marine";"Barracks";119;1
"Unit";"Marine";"Barracks";128;1
"Unit";"Marine";"Barracks";128;1
"Unit";"Marine";"Barracks";128;1
"Unit";"Marine";"Barracks";132;1
"Unit";"Marine";"Barracks";132;1
"Unit";"Marine";"Barracks";132;1
"Unit";"Marine";"Barracks";132;1
"Unit";"Marine";"Barracks";132;1
"Upgrade";"TerranInfantryArmorsLevel1";"EngineeringBay";112;0
"Unit";"Marine";"Barracks";132;1
"Unit";"Marine";"Barracks";133;1
"Unit";"Marine";"Barracks";135;1
"Unit";"Marine";"Barracks";135;1
"Unit";"Marine";"Barracks";144;1
"Unit";"Marine";"Barracks";144;1
"Unit";"Marine";"Barracks";144;1
"Unit";"Marine";"Barracks";144;1
"Unit";"Marine";"Barracks";144;1
"Unit";"Marine";"Barracks";144;1
"Unit";"Marine";"Barracks";144;1
"Unit";"Marine";"Barracks";145;1
"Unit";"Marine";"Barracks";146;1
"Unit";"Marine";"Barracks";153;1
"Unit";"Marine";"Barracks";153;1
"Unit";"Marine";"Barracks";153;1
"Unit";"Marine";"Barracks";153;1
"Unit";"Marine";"Barracks";155;1
"Unit";"Marine";"Barracks";155;1
"Unit";"Marine";"Barracks";157;1
"Unit";"Marine";"Barracks";157;1
"Unit";"Marine";"Barracks";157;1
"Unit";"Marine";"Barracks";158;1
"Unit";"Marine";"Barracks";163;1
"Unit";"Marine";"Barracks";163;1
"Unit";"Marine";"Barracks";163;1
"Unit";"Marine";"Barracks";163;1
"Upgrade";"TerranVehicleWeaponsLevel1";"Armory";135;0
"Upgrade";"TerranInfantryWeaponsLevel2";"EngineeringBay";132;0
"Unit";"Marine";"Barracks";163;1
"Unit";"Marine";"Barracks";165;1
"Unit";"Marine";"Barracks";166;1
"Building";"SensorTower";NA;179;0
"Building";"Factory";NA;173;0
"Unit";"Marine";"Barracks";184;1
"Unit";"Marine";"Barracks";184;1
"Unit";"Marine";"Barracks";184;1
"Unit";"Marine";"Barracks";184;1
"Unit";"Marine";"Barracks";184;1
"Unit";"Marine";"Barracks";184;1
"Unit";"Marine";"Barracks";184;1
"Building";"FactoryTechLab";NA;185;0
"Building";"Refinery";NA;184;0
"Building";"Refinery";NA;185;0
"Upgrade";"TerranInfantryArmorsLevel2";"EngineeringBay";161;0
"Unit";"Marine";"Barracks";192;1
"Unit";"Marine";"Barracks";192;1
"Unit";"Marine";"Barracks";192;1
"Unit";"Marine";"Barracks";192;1
"Unit";"Marine";"Barracks";192;1
"Unit";"Marine";"Barracks";192;1
"Unit";"Marine";"Barracks";192;1
"Unit";"Marine";"Barracks";192;1
"Unit";"Marine";"Barracks";200;1
"Unit";"Marine";"Barracks";200;1
"Unit";"Marine";"Barracks";200;1
"Unit";"Marine";"Barracks";200;1
"Building";"CommandCenter";NA;184;0
"Unit";"Marine";"Barracks";200;1
"Unit";"Marine";"Barracks";200;1
"Unit";"Marine";"Barracks";200;1
"Unit";"Marine";"Barracks";200;1
"Unit";"Marine";"Barracks";200;1
"Unit";"Marine";"Barracks";201;1
"Unit";"Marine";"Barracks";202;1
"Unit";"Marine";"Barracks";203;1
"Unit";"Marine";"Barracks";204;1
"Unit";"Marine";"Barracks";205;1
"Unit";"Marine";"Barracks";206;1
"Unit";"Marine";"Barracks";208;1
"Unit";"Marine";"Barracks";209;1
"Unit";"Marine";"Barracks";210;1
"Upgrade";"TerranVehicleWeaponsLevel2";"Armory";185;0
"Unit";"Marine";"Barracks";211;1
"Unit";"Marine";"Barracks";215;1
"Unit";"Marine";"Barracks";215;1
"Unit";"Marine";"Barracks";215;1
"Upgrade";"TerranInfantryWeaponsLevel3";"EngineeringBay";192;0
"Unit";"Medivac";"Starport";222;2
"Unit";"Medivac";"Starport";222;2
"Unit";"Marine";"Barracks";231;1
"Unit";"Marine";"Barracks";231;1
"Unit";"Marine";"Barracks";231;1
"Unit";"Marine";"Barracks";231;1
"Unit";"Marine";"Barracks";231;1
"Unit";"Marine";"Barracks";231;1
"Unit";"Medivac";"Starport";231;2
"Unit";"Medivac";"Starport";233;2
"Unit";"Marine";"Barracks";241;1
"Unit";"Marine";"Barracks";241;1
"Unit";"Marine";"Barracks";241;1
"Unit";"Marine";"Barracks";241;1
"Unit";"Marine";"Barracks";241;1
"Unit";"Marine";"Barracks";241;1
"Unit";"Marine";"Barracks";242;1
"Unit";"Marine";"Barracks";242;1
"Unit";"Marine";"Barracks";255;1
"Building";"SensorTower";NA;255;0
"Unit";"Marine";"Barracks";255;1
"Unit";"Marine";"Barracks";255;1
"Unit";"Marine";"Barracks";255;1
"Unit";"Marine";"Barracks";255;1
"Unit";"Marine";"Barracks";255;1
"Unit";"Marine";"Barracks";255;1
"Unit";"Marine";"Barracks";255;1
"Building";"Refinery";NA;255;0
"Building";"Refinery";NA;255;0
"Unit";"Marine";"Barracks";255;1
"Building";"MissileTurret";NA;256;0
"Unit";"Marine";"Barracks";256;1
"Unit";"Marine";"Barracks";265;1
"Building";"Barracks";NA;255;0
"Building";"Barracks";NA;255;0
"Upgrade";"TerranInfantryArmorsLevel3";"EngineeringBay";235;0
"Unit";"Marine";"Barracks";266;1
"Unit";"Marine";"Barracks";266;1
"Unit";"Marine";"Barracks";266;1
"Unit";"Marine";"Barracks";266;1
"Unit";"Marine";"Barracks";266;1
"Unit";"Marine";"Barracks";266;1
"Unit";"Marine";"Barracks";267;1
"Unit";"Marine";"Barracks";267;1
"Unit";"Marine";"Barracks";267;1
"Building";"MissileTurret";NA;273;0
"Building";"MissileTurret";NA;273;0
"Building";"MissileTurret";NA;273;0
"Building";"MissileTurret";NA;273;0
"Upgrade";"TerranVehicleWeaponsLevel3";"Armory";255;0
"Unit";"Marine";"Barracks";276;1
"Unit";"Marine";"Barracks";276;1
"Unit";"Marine";"Barracks";276;1
"Unit";"Marine";"Barracks";276;1
"Unit";"Marine";"Barracks";276;1
"Unit";"Marine";"Barracks";276;1
"Unit";"Marine";"Barracks";276;1
"Unit";"Marine";"Barracks";276;1
"Building";"MissileTurret";NA;276;0
"Unit";"Marine";"Barracks";276;1
"Unit";"Marine";"Barracks";277;1
"Unit";"Marine";"Barracks";278;1
"Unit";"Marine";"Barracks";278;1
"Unit";"Marine";"Barracks";284;1
"Unit";"Marine";"Barracks";285;1
"Unit";"Marine";"Barracks";285;1
"Unit";"Marine";"Barracks";286;1
"Unit";"Marine";"Barracks";286;1
"Unit";"Marine";"Barracks";286;1
"Unit";"Marine";"Barracks";287;1
"Unit";"Marine";"Barracks";287;1
"Unit";"Marine";"Barracks";289;1
"Unit";"Marine";"Barracks";290;1
"Unit";"Marine";"Barracks";292;1
"Unit";"Marine";"Barracks";293;1
"Unit";"Marine";"Barracks";294;1
"Unit";"Marine";"Barracks";295;1
"Unit";"Marine";"Barracks";296;1
"Unit";"Marine";"Barracks";296;1
"Unit";"Marine";"Barracks";298;1
"Unit";"Marine";"Barracks";299;1
"Unit";"Marine";"Barracks";300;1
"Unit";"Marine";"Barracks";301;1
"Unit";"Marine";"Barracks";303;1
"Unit";"Marine";"Barracks";304;1
"Unit";"Marine";"Barracks";305;1
"Unit";"Marine";"Barracks";305;1
"Unit";"Marine";"Barracks";307;1
"Unit";"Marine";"Barracks";308;1
"Unit";"Marine";"Barracks";309;1
"Unit";"Marine";"Barracks";310;1
"Unit";"Marine";"Barracks";311;1
"Unit";"Marine";"Barracks";312;1
"Unit";"Marine";"Barracks";313;1
"Unit";"Marine";"Barracks";313;1
"Unit";"Marine";"Barracks";315;1
"Unit";"Liberator";"Starport";301;3
"Unit";"Marine";"Barracks";317;1
"Unit";"Marine";"Barracks";317;1
"Unit";"Marine";"Barracks";327;1
"Unit";"Marine";"Barracks";327;1
"Unit";"Marine";"Barracks";327;1
"Unit";"Marine";"Barracks";327;1
"Unit";"Liberator";"Starport";317;3
"Unit";"Marine";"Barracks";329;1
"Unit";"Marine";"Barracks";329;1
"Unit";"Marine";"Barracks";329;1
"Unit";"Marine";"Barracks";339;1
"Unit";"Marine";"Barracks";339;1
"Unit";"Marine";"Barracks";339;1
"Unit";"Marine";"Barracks";339;1
"Unit";"Marine";"Barracks";339;1
"Unit";"Marine";"Barracks";339;1
"Unit";"Marine";"Barracks";339;1
"Unit";"Marine";"Barracks";339;1
"Unit";"Marine";"Barracks";339;1
"Unit";"Marine";"Barracks";340;1
"Unit";"Marine";"Barracks";341;1
"Unit";"Liberator";"Starport";347;3
"Unit";"Marine";"Barracks";351;1
"Unit";"Liberator";"Starport";347;3
"Unit";"Marine";"Barracks";351;1
"Unit";"Marine";"Barracks";353;1
"Unit";"Marine";"Barracks";353;1
"Unit";"Marine";"Barracks";353;1
"Unit";"Medivac";"Starport";365;2
"Unit";"Marine";"Barracks";367;1
"Unit";"Marine";"Barracks";367;1
"Unit";"Marine";"Barracks";367;1
"Unit";"Marine";"Barracks";367;1
"Unit";"Marine";"Barracks";369;1
"Unit";"Marine";"Barracks";374;1
