"Type";"UnitName";"OnBuilding";"TotalSupply";"Supply"
"Unit";"SCV";"Command Center";12;1
"Unit";"SCV";"Command Center";12;1
"Building";"SupplyDepot";NA;13;0
"Unit";"SCV";"Command Center";14;1
"Unit";"SCV";"Command Center";15;1
"Building";"Refinery";NA;14;0
"Unit";"SCV";"Command Center";15;1
"Unit";"SCV";"Command Center";16;1
"Building";"Barracks";NA;15;0
"Unit";"SCV";"Command Center";17;1
"Unit";"Reaper";"Barracks";19;1
"Unit";"SCV";"Command Center";19;1
"Unit";"SCV";"Command Center";21;1
"Building";"SupplyDepot";NA;20;0
"Building";"Refinery";NA;21;0
"Unit";"SCV";"Command Center";22;1
"Unit";"Reaper";"Barracks";21;1
"Building";"Factory";NA;20;0
"Unit";"SCV";"Command Center";23;1
"Building";"CommandCenter";NA;19;0
"Unit";"Marine";"Barracks";23;1
"Unit";"SCV";"Command Center";25;1
"Unit";"Hellion";"Factory";24;2
"Unit";"SCV";"Command Center";26;1
"Unit";"Marine";"Barracks";26;1
"Building";"Starport";NA;24;0
"Unit";"SCV";"Command Center";29;1
"Unit";"SCV";"Command Center";31;1
"Unit";"Cyclone";"Factory";31;3
"Unit";"SCV";"Command Center";33;1
"Unit";"SCV";"Command Center";33;1
"Unit";"Marine";"Barracks";32;1
"Building";"EngineeringBay";NA;32;0
"Unit";"SCV";"Command Center";37;1
"Building";"SupplyDepot";NA;33;0
"Unit";"Liberator";"Starport";32;3
"Unit";"SCV";"Command Center";40;1
"Unit";"SCV";"Command Center";40;1
"Building";"MissileTurret";NA;39;0
"Building";"MissileTurret";NA;40;0
"Unit";"Cyclone";"Factory";40;3
"Unit";"SCV";"Command Center";45;1
"Unit";"SCV";"Command Center";45;1
"Building";"MissileTurret";NA;43;0
"Unit";"SCV";"Command Center";48;1
"Unit";"SCV";"Command Center";49;1
"Building";"BarracksReactor";NA;45;0
"Unit";"SCV";"Command Center";52;1
"Unit";"SCV";"Command Center";52;1
"Building";"MissileTurret";NA;52;0
"Building";"FactoryTechLab";NA;52;0
"Unit";"SCV";"Command Center";52;1
"Building";"StarportTechLab";NA;52;0
"Unit";"SCV";"Command Center";53;1
"Unit";"SCV";"Command Center";55;1
"Unit";"SCV";"Command Center";55;1
"Building";"SupplyDepot";NA;56;0
"Building";"SupplyDepot";NA;58;0
"Unit";"SCV";"Command Center";58;1
"Unit";"SCV";"Command Center";58;1
"Unit";"Marine";"Barracks";58;1
"Unit";"SCV";"Command Center";58;1
"Unit";"SCV";"Command Center";59;1
"Building";"Refinery";NA;58;0
"Unit";"Marine";"Barracks";58;1
"Building";"Refinery";NA;58;0
"Building";"EngineeringBay";NA;58;0
"Unit";"SCV";"Command Center";61;1
"Unit";"SCV";"Command Center";62;1
"Unit";"Marine";"Barracks";61;1
"Unit";"Raven";"Starport";58;2
"Unit";"Marine";"Barracks";64;1
"Unit";"SCV";"Command Center";64;1
"Unit";"SCV";"Command Center";67;1
"Building";"CommandCenter";NA;56;0
"Unit";"SCV";"Command Center";70;1
"Unit";"SCV";"Command Center";72;1
"Unit";"Marine";"Barracks";70;1
"Building";"SupplyDepot";NA;67;0
"Building";"SupplyDepot";NA;69;0
"Building";"Barracks";NA;62;0
"Building";"FactoryTechLab";NA;72;0
"Unit";"SCV";"Command Center";72;1
"Building";"Barracks";NA;63;0
"Unit";"SCV";"Command Center";74;1
"Unit";"Marine";"Barracks";73;1
"Unit";"Marine";"Barracks";75;1
"Unit";"SCV";"Command Center";75;1
"Building";"StarportReactor";NA;72;0
"Unit";"SCV";"Command Center";78;1
"Unit";"SCV";"Command Center";78;1
"Unit";"SCV";"Command Center";79;1
"Unit";"Marine";"Barracks";78;1
"Unit";"Marine";"Barracks";78;1
"Unit";"Marine";"Barracks";80;1
"Unit";"Marine";"Barracks";80;1
"Building";"Barracks";NA;73;0
"Building";"Barracks";NA;73;0
"Unit";"SCV";"Command Center";84;1
"Unit";"SCV";"Command Center";85;1
"Unit";"Medivac";"Starport";81;2
"Unit";"Medivac";"Starport";82;2
"Unit";"SCV";"Command Center";87;1
"Unit";"SCV";"Command Center";88;1
"Unit";"Marine";"Barracks";89;1
"Unit";"Marine";"Barracks";89;1
"Unit";"Marine";"Barracks";89;1
"Unit";"Marine";"Barracks";89;1
"Upgrade";"TerranInfantryWeaponsLevel1";"EngineeringBay";75;0
"Upgrade";"TerranInfantryArmorsLevel1";"EngineeringBay";75;0
"Building";"Armory";NA;85;0
"Building";"BarracksReactor";NA;89;0
"Building";"BarracksReactor";NA;89;0
"Building";"SupplyDepot";NA;99;0
"Building";"SupplyDepot";NA;99;0
"Building";"SensorTower";NA;99;0
"Unit";"SCV";"Command Center";99;1
"Unit";"SCV";"Command Center";99;1
"Unit";"SCV";"Command Center";99;1
"Building";"Refinery";NA;99;0
"Unit";"Marine";"Barracks";99;1
"Unit";"Marine";"Barracks";99;1
"Unit";"Marine";"Barracks";99;1
"Unit";"Marine";"Barracks";99;1
"Unit";"Marine";"Barracks";99;1
"Unit";"Marine";"Barracks";99;1
"Unit";"Marine";"Barracks";99;1
"Building";"Refinery";NA;99;0
"Building";"SensorTower";NA;99;0
"Unit";"SCV";"Command Center";99;1
"Unit";"SCV";"Command Center";100;1
"Unit";"Medivac";"Starport";99;2
"Unit";"Medivac";"Starport";99;2
"Building";"SupplyDepot";NA;99;0
"Building";"SupplyDepot";NA;99;0
"Building";"SupplyDepot";NA;100;0
"Unit";"SCV";"Command Center";111;1
"Unit";"Marine";"Barracks";111;1
"Unit";"Marine";"Barracks";111;1
"Unit";"Marine";"Barracks";111;1
"Unit";"Marine";"Barracks";111;1
"Unit";"Marine";"Barracks";111;1
"Unit";"Marine";"Barracks";111;1
"Upgrade";"Stimpack";"TechLab";89;0
"Unit";"SCV";"Command Center";115;1
"Unit";"Marine";"Barracks";115;1
"Unit";"SCV";"Command Center";116;1
"Unit";"SCV";"Command Center";116;1
"Building";"BarracksReactor";NA;109;0
"Building";"Factory";NA;102;0
"Unit";"Marine";"Barracks";116;1
"Unit";"Marine";"Barracks";116;1
"Unit";"Medivac";"Starport";115;2
"Unit";"Medivac";"Starport";115;2
"Unit";"Marine";"Barracks";126;1
"Unit";"Marine";"Barracks";126;1
"Unit";"Marine";"Barracks";126;1
"Unit";"Marine";"Barracks";126;1
"Unit";"Marine";"Barracks";126;1
"Unit";"Marine";"Barracks";126;1
"Unit";"Marine";"Barracks";128;1
"Unit";"Marine";"Barracks";128;1
"Unit";"Marine";"Barracks";128;1
"Unit";"SCV";"Command Center";137;1
"Unit";"SCV";"Command Center";137;1
"Unit";"SCV";"Command Center";137;1
"Unit";"Marine";"Barracks";132;1
"Unit";"Marine";"Barracks";133;1
"Building";"Barracks";NA;122;0
"Building";"Barracks";NA;122;0
"Unit";"Marine";"Barracks";141;1
"Unit";"Marine";"Barracks";141;1
"Unit";"Marine";"Barracks";141;1
"Unit";"Marine";"Barracks";141;1
"Unit";"Marine";"Barracks";141;1
"Building";"Refinery";NA;144;0
"Unit";"Marine";"Barracks";146;1
"Unit";"Marine";"Barracks";146;1
"Unit";"Marine";"Barracks";146;1
"Unit";"Marine";"Barracks";146;1
"Building";"Refinery";NA;146;0
"Unit";"Marine";"Barracks";146;1
"Unit";"Marine";"Barracks";151;1
"Unit";"Marine";"Barracks";151;1
"Unit";"Marine";"Barracks";151;1
"Unit";"Marine";"Barracks";151;1
"Unit";"Marine";"Barracks";151;1
"Unit";"Marine";"Barracks";152;1
"Unit";"Marine";"Barracks";162;1
"Unit";"Marine";"Barracks";162;1
"Unit";"Marine";"Barracks";162;1
"Unit";"Marine";"Barracks";162;1
"Unit";"Marine";"Barracks";162;1
"Unit";"Marine";"Barracks";162;1
"Building";"CommandCenter";NA;146;0
"Unit";"Marine";"Barracks";163;1
"Unit";"Marine";"Barracks";163;1
"Unit";"Marine";"Barracks";166;1
"Unit";"Marine";"Barracks";168;1
