"type";"unit_name";"on_building";"total_supply";"supply"
"Building";"Refinery";NA;14;0
"Building";"Barracks";NA;15;0
"Unit";"Reaper";"Barracks";19;1
"Unit";"Marine";"Barracks";19;1
"Building";"Bunker";NA;20;0
"Unit";"Marine";"Barracks";21;1
"Building";"Refinery";NA;23;0
"Building";"CommandCenter";NA;19;0
"Building";"Factory";NA;23;0
"Building";"BarracksReactor";NA;25;0
"Building";"FactoryTechLab";NA;27;0
"Unit";"Marine";"Barracks";27;1
"Unit";"Marine";"Barracks";27;1
"Building";"Starport";NA;27;0
"Unit";"Marine";"Barracks";29;1
"Unit";"Marine";"Barracks";30;1
"Building";"StarportTechLab";NA;33;0
"Unit";"Marine";"Barracks";35;1
"Unit";"Marine";"Barracks";35;1
"Unit";"Marine";"Barracks";41;1
"Unit";"Marine";"Barracks";41;1
"Building";"Refinery";NA;41;0
"Building";"CommandCenter";NA;28;0
"Unit";"Marine";"Barracks";45;1
"Unit";"Marine";"Barracks";45;1
"Building";"EngineeringBay";NA;41;0
"Building";"Refinery";NA;45;0
"Unit";"Raven";"Starport";41;2
"Unit";"Marine";"Barracks";47;1
"Unit";"Marine";"Barracks";48;1
"Unit";"Marine";"Barracks";58;1
"Unit";"Marine";"Barracks";62;1
"Unit";"Marine";"Barracks";67;1
"Unit";"Marine";"Barracks";71;1
"Building";"EngineeringBay";NA;72;0
"Unit";"Marine";"Barracks";75;1
"Building";"Refinery";NA;78;0
"Building";"Barracks";NA;72;0
"Building";"Refinery";NA;78;0
"Building";"Barracks";NA;72;0
"Unit";"Marine";"Barracks";80;1
"Building";"StarportReactor";NA;75;0
"Upgrade";"Stimpack";"TechLab";64;0
"Building";"Barracks";NA;74;0
"Building";"Barracks";NA;74;0
"Unit";"Marine";"Barracks";85;1
"Building";"BarracksTechLab";NA;86;0
"Unit";"Medivac";"Starport";86;2
"Unit";"Medivac";"Starport";86;2
"Building";"BarracksReactor";NA;86;0
"Unit";"Marine";"Barracks";94;1
"Unit";"Marine";"Barracks";94;1
"Unit";"Marine";"Barracks";94;1
"Unit";"Marine";"Barracks";94;1
"Building";"BarracksReactor";NA;87;0
"Unit";"Marine";"Barracks";94;1
"Unit";"Marine";"Barracks";94;1
"Building";"Armory";NA;86;0
"Unit";"Marine";"Barracks";97;1
"Unit";"Marine";"Barracks";97;1
"Unit";"Marine";"Barracks";99;1
"Unit";"Marine";"Barracks";99;1
"Unit";"Medivac";"Starport";94;2
"Unit";"Medivac";"Starport";94;2
"Unit";"Marine";"Barracks";101;1
"Unit";"Marine";"Barracks";101;1
"Unit";"Marine";"Barracks";101;1
"Unit";"Marine";"Barracks";102;1
"Unit";"Marine";"Barracks";104;1
"Unit";"Marine";"Barracks";104;1
"Unit";"Marine";"Barracks";108;1
"Building";"MissileTurret";NA;108;0
"Unit";"Marine";"Barracks";108;1
"Building";"MissileTurret";NA;108;0
"Building";"MissileTurret";NA;110;0
"Upgrade";"TerranInfantryArmorsLevel1";"EngineeringBay";86;0
"Building";"MissileTurret";NA;112;0
"Upgrade";"TerranInfantryWeaponsLevel1";"EngineeringBay";86;0
"Unit";"Marine";"Barracks";116;1
"Unit";"Marine";"Barracks";116;1
"Unit";"Marine";"Barracks";116;1
"Unit";"Marine";"Barracks";116;1
"Unit";"Marine";"Barracks";116;1
"Unit";"Marine";"Barracks";116;1
"Unit";"Marine";"Barracks";118;1
"Unit";"Marine";"Barracks";119;1
