"type";"unit_name";"on_building";"total_supply";"supply"
"Building";"Refinery";NA;14;0
"Building";"Barracks";NA;15;0
"Unit";"Reaper";"Barracks";19;1
"Building";"Refinery";NA;21;0
"Building";"BarracksReactor";NA;20;0
"Building";"Factory";NA;20;0
"Building";"CommandCenter";NA;19;0
"Unit";"Hellion";"Factory";24;2
"Unit";"Hellion";"Factory";24;2
"Building";"Starport";NA;24;0
"Building";"BarracksTechLab";NA;26;0
"Unit";"Hellion";"Factory";26;2
"Unit";"Hellion";"Factory";28;2
"Unit";"Hellion";"Factory";36;2
"Unit";"Hellion";"Factory";36;2
"Unit";"Raven";"Starport";32;2
"Unit";"Cyclone";"Factory";45;3
"Unit";"Cyclone";"Factory";45;3
"Unit";"Cyclone";"Factory";60;3
"Unit";"Cyclone";"Factory";61;3
"Building";"Refinery";NA;61;0
"Building";"Refinery";NA;61;0
"Building";"BarracksReactor";NA;62;0
"Building";"Factory";NA;63;0
"Building";"CommandCenter";NA;59;0
"Building";"BarracksTechLab";NA;77;0
"Building";"Refinery";NA;77;0
"Building";"Refinery";NA;77;0
"Building";"Factory";NA;74;0
"Unit";"Hellion";"Factory";77;2
"Unit";"Hellion";"Factory";77;2
"Building";"EngineeringBay";NA;79;0
"Unit";"Hellion";"Factory";85;2
"Unit";"Hellion";"Factory";85;2
"Building";"SensorTower";NA;90;0
"Building";"MissileTurret";NA;92;0
"Building";"MissileTurret";NA;94;0
"Unit";"Hellion";"Factory";97;2
"Unit";"Hellion";"Factory";103;2
"Unit";"Hellion";"Factory";103;2
"Building";"MissileTurret";NA;111;0
"Building";"MissileTurret";NA;111;0
"Unit";"Hellion";"Factory";111;2
"Unit";"Hellion";"Factory";111;2
"Unit";"Liberator";"Starport";106;3
"Unit";"Liberator";"Starport";106;3
"Building";"Armory";NA;107;0
"Building";"Armory";NA;107;0
"Unit";"Hellion";"Factory";113;2
"Unit";"Hellion";"Factory";113;2
"Building";"BarracksReactor";NA;121;0
"Building";"CommandCenter";NA;111;0
"Unit";"Hellion";"Factory";121;2
"Building";"Factory";NA;121;0
"Building";"Factory";NA;121;0
"Unit";"Hellion";"Factory";125;2
"Building";"MissileTurret";NA;125;0
"Building";"MissileTurret";NA;127;0
"Building";"MissileTurret";NA;127;0
"Building";"MissileTurret";NA;127;0
"Building";"MissileTurret";NA;127;0
"Unit";"Hellion";"Factory";129;2
"Building";"MissileTurret";NA;129;0
"Building";"MissileTurret";NA;129;0
"Unit";"Hellion";"Factory";129;2
"Building";"FactoryReactor";NA;129;0
"Unit";"Hellion";"Factory";129;2
"Unit";"Hellion";"Factory";129;2
"Unit";"Hellion";"Factory";131;2
"Unit";"Hellion";"Factory";133;2
"Unit";"Hellion";"Factory";133;2
"Unit";"Hellion";"Factory";133;2
"Unit";"Hellion";"Factory";133;2
"Unit";"Hellion";"Factory";137;2
"Upgrade";"TerranVehicleWeaponsLevel1";"Armory";127;0
"Unit";"Hellion";"Factory";137;2
"Building";"Starport";NA;133;0
"Building";"Starport";NA;133;0
"Unit";"Hellion";"Factory";139;2
"Unit";"Hellion";"Factory";145;2
"Unit";"Hellion";"Factory";145;2
"Building";"StarportTechLab";NA;157;0
"Unit";"Hellion";"Factory";157;2
"Unit";"Hellion";"Factory";157;2
"Unit";"Hellion";"Factory";157;2
"Unit";"Hellion";"Factory";157;2
"Unit";"Hellion";"Factory";157;2
"Building";"StarportReactor";NA;157;0
