"Type";"UnitName";"OnBuilding";"TotalSupply";"Supply"
"Unit";"SCV";"Command Center";12;1
"Unit";"SCV";"Command Center";12;1
"Unit";"SCV";"Command Center";13;1
"Building";"SupplyDepot";NA;13;0
"Building";"Refinery";NA;14;0
"Unit";"SCV";"Command Center";15;1
"Unit";"SCV";"Command Center";15;1
"Unit";"SCV";"Command Center";16;1
"Unit";"SCV";"Command Center";17;1
"Building";"Barracks";NA;15;0
"Unit";"Reaper";"Barracks";19;1
"Unit";"SCV";"Command Center";19;1
"Unit";"SCV";"Command Center";20;1
"Unit";"SCV";"Command Center";22;1
"Building";"SupplyDepot";NA;21;0
"Unit";"Reaper";"Barracks";20;1
"Building";"Factory";NA;19;0
"Building";"Refinery";NA;21;0
"Unit";"SCV";"Command Center";23;1
"Building";"CommandCenter";NA;19;0
"Unit";"SCV";"Command Center";24;1
"Unit";"Hellion";"Factory";24;2
"Unit";"SCV";"Command Center";25;1
"Building";"BarracksReactor";NA;24;0
"Unit";"SCV";"Command Center";28;1
"Building";"Starport";NA;25;0
"Unit";"SCV";"Command Center";30;1
"Unit";"SCV";"Command Center";30;1
"Unit";"Marine";"Barracks";29;1
"Unit";"Marine";"Barracks";29;1
"Unit";"SCV";"Command Center";31;1
"Unit";"SCV";"Command Center";32;1
"Building";"SupplyDepot";NA;30;0
"Unit";"Cyclone";"Factory";30;3
"Unit";"Marine";"Barracks";34;1
"Unit";"Marine";"Barracks";34;1
"Unit";"SCV";"Command Center";35;1
"Unit";"SCV";"Command Center";36;1
"Building";"EngineeringBay";NA;34;0
"Unit";"SCV";"Command Center";41;1
"Unit";"SCV";"Command Center";43;1
"Unit";"Marine";"Barracks";43;1
"Unit";"Marine";"Barracks";43;1
"Unit";"Cyclone";"Factory";43;3
"Building";"MissileTurret";NA;44;0
"Building";"MissileTurret";NA;44;0
"Unit";"SCV";"Command Center";50;1
"Unit";"SCV";"Command Center";50;1
"Building";"SupplyDepot";NA;45;0
"Unit";"Liberator";"Starport";43;3
"Building";"BarracksTechLab";NA;50;0
"Unit";"SCV";"Command Center";52;1
"Unit";"SCV";"Command Center";52;1
"Building";"FactoryTechLab";NA;52;0
"Building";"Refinery";NA;52;0
"Unit";"SCV";"Command Center";57;1
"Unit";"SCV";"Command Center";57;1
"Building";"Barracks";NA;50;0
"Building";"SupplyDepot";NA;57;0
"Building";"StarportReactor";NA;57;0
"Building";"Barracks";NA;52;0
"Unit";"Marine";"Barracks";59;1
"Unit";"Marine";"Barracks";59;1
"Unit";"SCV";"Command Center";59;1
"Unit";"SCV";"Command Center";59;1
"Unit";"SCV";"Command Center";61;1
"Unit";"SCV";"Command Center";62;1
"Building";"SupplyDepot";NA;59;0
"Building";"SupplyDepot";NA;59;0
"Building";"SupplyDepot";NA;59;0
"Unit";"Medivac";"Starport";59;2
"Building";"SupplyDepot";NA;63;0
"Building";"SupplyDepot";NA;63;0
"Building";"SupplyDepot";NA;63;0
"Unit";"SCV";"Command Center";67;1
"Building";"BarracksReactor";NA;63;0
"Unit";"SCV";"Command Center";67;1
"Unit";"Marine";"Barracks";67;1
"Unit";"Marine";"Barracks";67;1
"Unit";"Marine";"Barracks";67;1
"Unit";"SCV";"Command Center";67;1
"Unit";"Medivac";"Starport";67;2
"Unit";"SCV";"Command Center";72;1
"Unit";"SCV";"Command Center";73;1
"Unit";"Marine";"Barracks";72;1
"Unit";"Marine";"Barracks";72;1
"Unit";"Marine";"Barracks";72;1
"Unit";"Marine";"Barracks";72;1
"Unit";"Marine";"Barracks";72;1
"Building";"MissileTurret";NA;73;0
"Upgrade";"Stimpack";"TechLab";59;0
"Unit";"SCV";"Command Center";78;1
"Unit";"SCV";"Command Center";78;1
"Unit";"Medivac";"Starport";72;2
"Unit";"Marine";"Barracks";77;1
"Unit";"Marine";"Barracks";78;1
"Unit";"Marine";"Barracks";79;1
"Unit";"SCV";"Command Center";82;1
"Unit";"SCV";"Command Center";89;1
"Unit";"Marine";"Barracks";86;1
"Unit";"Marine";"Barracks";86;1
"Unit";"Marine";"Barracks";86;1
"Unit";"SCV";"Command Center";89;1
"Unit";"Marine";"Barracks";89;1
"Unit";"Marine";"Barracks";89;1
"Building";"Refinery";NA;89;0
"Unit";"SCV";"Command Center";90;1
"Unit";"Medivac";"Starport";86;2
"Unit";"SCV";"Command Center";94;1
"Unit";"Marine";"Barracks";91;1
"Unit";"Marine";"Barracks";92;1
"Unit";"SCV";"Command Center";97;1
"Unit";"SCV";"Command Center";100;1
"Unit";"Marine";"Barracks";103;1
"Unit";"Marine";"Barracks";103;1
"Unit";"Marine";"Barracks";103;1
"Unit";"Marine";"Barracks";103;1
"Unit";"Marine";"Barracks";103;1
"Unit";"SCV";"Command Center";105;1
"Unit";"Marine";"Barracks";105;1
"Unit";"Marine";"Barracks";106;1
"Unit";"Marine";"Barracks";107;1
"Unit";"Marine";"Barracks";114;1
"Unit";"Marine";"Barracks";114;1
"Unit";"Marine";"Barracks";114;1
"Unit";"Marine";"Barracks";114;1
"Unit";"Marine";"Barracks";114;1
"Building";"CommandCenter";NA;101;0
"Unit";"Medivac";"Starport";114;2
"Unit";"Medivac";"Starport";114;2
"Unit";"Marine";"Barracks";114;1
"Unit";"Marine";"Barracks";115;1
"Unit";"Marine";"Barracks";116;1
"Unit";"Marine";"Barracks";117;1
"Unit";"Marine";"Barracks";118;1
"Unit";"Medivac";"Starport";119;2
"Unit";"Marine";"Barracks";128;1
"Unit";"Marine";"Barracks";128;1
"Unit";"Marine";"Barracks";128;1
"Unit";"Marine";"Barracks";128;1
"Unit";"Marine";"Barracks";128;1
"Unit";"Medivac";"Starport";128;2
"Building";"Factory";NA;128;0
"Unit";"SCV";"Command Center";134;1
"Unit";"Marine";"Barracks";130;1
"Building";"Barracks";NA;128;0
"Unit";"Marine";"Barracks";134;1
"Unit";"Marine";"Barracks";134;1
"Unit";"Marine";"Barracks";134;1
"Building";"Barracks";NA;128;0
"Unit";"Medivac";"Starport";128;2
"Unit";"Marine";"Barracks";138;1
"Unit";"Marine";"Barracks";139;1
"Unit";"Marine";"Barracks";144;1
"Building";"EngineeringBay";NA;144;0
"Unit";"SCV";"Command Center";146;1
"Unit";"SCV";"Command Center";146;1
"Unit";"SCV";"Command Center";146;1
"Building";"SensorTower";NA;146;0
"Building";"SensorTower";NA;146;0
"Building";"BarracksReactor";NA;144;0
"Building";"BarracksReactor";NA;144;0
"Building";"Armory";NA;144;0
"Building";"Refinery";NA;147;0
"Unit";"SCV";"Command Center";150;1
"Unit";"SCV";"Command Center";150;1
"Unit";"Marine";"Barracks";150;1
"Unit";"Marine";"Barracks";150;1
"Unit";"Marine";"Barracks";150;1
"Unit";"Marine";"Barracks";150;1
"Unit";"Marine";"Barracks";150;1
"Unit";"Marine";"Barracks";150;1
"Building";"FactoryTechLab";NA;150;0
"Unit";"Marine";"Barracks";150;1
"Unit";"Marine";"Barracks";150;1
"Unit";"Marine";"Barracks";150;1
"Unit";"Marine";"Barracks";158;1
"Unit";"Marine";"Barracks";158;1
