"type";"unit_name";"on_building";"total_supply";"supply"
"Building";"Barracks";NA;12;0
"Building";"Barracks";NA;12;0
"Unit";"Marine";"Barracks";13;1
"Building";"Barracks";NA;12;0
"Unit";"Marine";"Barracks";13;1
"Unit";"Marine";"Barracks";14;1
"Unit";"Marine";"Barracks";16;1
"Unit";"Marine";"Barracks";16;1
"Unit";"Marine";"Barracks";16;1
