"Type";"UnitName";"OnBuilding";"TotalSupply";"Supply"
"Building";"SupplyDepot";NA;12;0
"Unit";"SCV";"Command Center";12;1
"Building";"Barracks";NA;12;0
"Building";"Barracks";NA;12;0
"Unit";"SCV";"Command Center";12;1
"Unit";"Marine";"Barracks";13;1
"Building";"Barracks";NA;12;0
"Unit";"Marine";"Barracks";13;1
"Unit";"Marine";"Barracks";14;1
"Building";"SupplyDepot";NA;15;0
"Unit";"Marine";"Barracks";16;1
"Unit";"Marine";"Barracks";16;1
"Unit";"Marine";"Barracks";16;1
