"type";"unit_name";"on_building";"total_supply";"supply"
"Building";"Refinery";NA;14;0
"Building";"Refinery";NA;16;0
"Building";"Barracks";NA;15;0
"Unit";"Reaper";"Barracks";19;1
"Building";"Factory";NA;19;0
"Unit";"Reaper";"Barracks";20;1
"Unit";"Cyclone";"Factory";22;3
"Building";"Starport";NA;22;0
"Unit";"Cyclone";"Factory";29;3
"Unit";"Medivac";"Starport";29;2
"Building";"BarracksTechLab";NA;29;0
"Unit";"Marine";"Barracks";36;1
"Building";"FactoryTechLab";NA;36;0
"Unit";"Banshee";"Starport";36;3
"Building";"CommandCenter";NA;30;0
"Building";"BarracksReactor";NA;38;0
"Unit";"Marine";"Barracks";43;1
"Unit";"Banshee";"Starport";42;3
"Building";"Refinery";NA;49;0
"Building";"Refinery";NA;49;0
"Unit";"Marine";"Barracks";50;1
"Unit";"Marine";"Barracks";50;1
"Building";"CommandCenter";NA;43;0
"Unit";"Marine";"Barracks";56;1
"Unit";"Marine";"Barracks";58;1
"Unit";"Marine";"Barracks";58;1
"Unit";"Banshee";"Starport";56;3
"Building";"EngineeringBay";NA;72;0
"Building";"Factory";NA;70;0
"Building";"Factory";NA;70;0
"Building";"BarracksReactor";NA;70;0
"Unit";"Raven";"Starport";70;2
"Building";"MissileTurret";NA;78;0
"Building";"FactoryTechLab";NA;78;0
"Building";"MissileTurret";NA;80;0
"Unit";"Hellion";"Factory";82;2
"Unit";"Hellion";"Factory";82;2
"Building";"MissileTurret";NA;82;0
"Building";"MissileTurret";NA;82;0
"Building";"MissileTurret";NA;82;0
"Unit";"Hellion";"Factory";83;2
"Unit";"Hellion";"Factory";85;2
"Unit";"Hellion";"Factory";87;2
"Unit";"Hellion";"Factory";87;2
"Building";"Refinery";NA;97;0
"Building";"SensorTower";NA;98;0
"Unit";"Hellion";"Factory";98;2
"Unit";"Hellion";"Factory";98;2
"Building";"SensorTower";NA;99;0
"Building";"MissileTurret";NA;100;0
"Building";"Factory";NA;99;0
"Building";"Armory";NA;99;0
"Building";"Armory";NA;99;0
"Building";"Factory";NA;99;0
"Building";"MissileTurret";NA;106;0
"Building";"Refinery";NA;106;0
"Building";"CommandCenter";NA;99;0
"Building";"FactoryTechLab";NA;109;0
"Unit";"Hellion";"Factory";109;2
"Building";"MissileTurret";NA;109;0
"Building";"FactoryReactor";NA;109;0
"Building";"Starport";NA;112;0
"Building";"Starport";NA;112;0
"Unit";"Hellion";"Factory";117;2
"Unit";"Hellion";"Factory";117;2
"Building";"MissileTurret";NA;118;0
"Building";"MissileTurret";NA;118;0
"Building";"MissileTurret";NA;125;0
"Building";"MissileTurret";NA;125;0
"Unit";"Liberator";"Starport";125;3
"Building";"StarportTechLab";NA;125;0
"Building";"StarportTechLab";NA;125;0
"Building";"CommandCenter";NA;118;0
"Upgrade";"TerranVehicleWeaponsLevel1";"Armory";118;0
"Building";"MissileTurret";NA;128;0
"Building";"SensorTower";NA;128;0
"Building";"Refinery";NA;128;0
"Building";"Refinery";NA;128;0
"Building";"MissileTurret";NA;128;0
"Building";"MissileTurret";NA;128;0
"Unit";"Raven";"Starport";128;2
"Unit";"Raven";"Starport";128;2
"Unit";"Hellion";"Factory";138;2
"Building";"CommandCenter";NA;128;0
"Building";"CommandCenter";NA;131;0
"Unit";"Thor";"Factory";138;6
"Unit";"Raven";"Starport";138;2
"Unit";"Raven";"Starport";138;2
"Unit";"Hellion";"Factory";140;2
"Unit";"Hellion";"Factory";140;2
"Unit";"Hellion";"Factory";140;2
"Unit";"Hellion";"Factory";140;2
"Unit";"Hellion";"Factory";140;2
"Unit";"Hellion";"Factory";140;2
"Building";"MissileTurret";NA;150;0
"Building";"SensorTower";NA;150;0
"Building";"MissileTurret";NA;150;0
"Building";"MissileTurret";NA;150;0
"Unit";"Raven";"Starport";148;2
"Building";"MissileTurret";NA;162;0
"Building";"Refinery";NA;162;0
"Unit";"Raven";"Starport";162;2
"Upgrade";"TerranVehicleWeaponsLevel2";"Armory";138;0
"Building";"Refinery";NA;162;0
"Building";"CommandCenter";NA;150;0
"Unit";"Raven";"Starport";164;2
"Building";"CommandCenter";NA;162;0
"Building";"CommandCenter";NA;162;0
"Unit";"Liberator";"Starport";166;3
"Unit";"Raven";"Starport";166;2
"Unit";"Thor";"Factory";173;6
"Unit";"Raven";"Starport";173;2
"Unit";"Raven";"Starport";173;2
"Building";"MissileTurret";NA;173;0
"Unit";"Thor";"Factory";173;6
"Unit";"Thor";"Factory";185;6
"Unit";"Thor";"Factory";185;6
"Building";"Refinery";NA;191;0
"Unit";"Raven";"Starport";185;2
"Unit";"Raven";"Starport";185;2
"Building";"Starport";NA;191;0
"Building";"Starport";NA;191;0
"Building";"SensorTower";NA;203;0
"Unit";"Thor";"Factory";191;6
"Building";"StarportTechLab";NA;214;0
"Building";"StarportTechLab";NA;214;0
"Upgrade";"TerranVehicleWeaponsLevel3";"Armory";185;0
"Unit";"Raven";"Starport";214;2
"Unit";"Raven";"Starport";214;2
"Unit";"Liberator";"Starport";214;3
"Unit";"Liberator";"Starport";216;3
"Building";"CommandCenter";NA;214;0
"Building";"CommandCenter";NA;214;0
"Building";"CommandCenter";NA;218;0
"Unit";"Raven";"Starport";218;2
"Unit";"Raven";"Starport";218;2
"Building";"CommandCenter";NA;218;0
"Building";"CommandCenter";NA;218;0
"Unit";"Raven";"Starport";224;2
"Unit";"Raven";"Starport";224;2
"Upgrade";"TerranShipWeaponsLevel1";"Armory";218;0
"Unit";"Raven";"Starport";232;2
"Unit";"Raven";"Starport";232;2
"Unit";"Raven";"Starport";232;2
"Unit";"Raven";"Starport";232;2
"Building";"FusionCore";NA;232;0
"Unit";"Raven";"Starport";232;2
"Unit";"Raven";"Starport";234;2
"Unit";"Raven";"Starport";236;2
"Building";"CommandCenter";NA;232;0
"Building";"Refinery";NA;246;0
"Unit";"Banshee";"Starport";240;3
"Building";"Refinery";NA;246;0
"Building";"FusionCore";NA;240;0
"Unit";"Raven";"Starport";240;2
"Unit";"Raven";"Starport";242;2
"Unit";"Raven";"Starport";244;2
"Building";"Refinery";NA;249;0
"Building";"MissileTurret";NA;249;0
"Building";"CommandCenter";NA;240;0
"Building";"MissileTurret";NA;249;0
"Building";"SensorTower";NA;255;0
"Unit";"Raven";"Starport";246;2
"Building";"MissileTurret";NA;255;0
"Unit";"Thor";"Factory";249;6
"Unit";"Thor";"Factory";249;6
"Unit";"Thor";"Factory";249;6
"Unit";"Battlecruiser";"Starport";255;6
"Unit";"Battlecruiser";"Starport";255;6
"Unit";"Battlecruiser";"Starport";255;6
"Building";"MissileTurret";NA;275;0
"Building";"SensorTower";NA;275;0
"Building";"MissileTurret";NA;275;0
"Building";"MissileTurret";NA;287;0
