"type";"unit_name";"on_building";"total_supply";"supply"
"Building";"Refinery";NA;14;0
"Building";"Barracks";NA;15;0
"Unit";"Reaper";"Barracks";19;1
"Unit";"Reaper";"Barracks";20;1
"Building";"Factory";NA;19;0
"Building";"Refinery";NA;21;0
"Unit";"Marine";"Barracks";24;1
"Unit";"Hellion";"Factory";24;2
"Building";"CommandCenter";NA;19;0
"Building";"Starport";NA;24;0
"Unit";"Marine";"Barracks";26;1
