"Type";"UnitName";"OnBuilding";"TotalSupply";"Supply"
"Unit";"SCV";"Command Center";12;1
"Unit";"SCV";"Command Center";12;1
"Unit";"SCV";"Command Center";13;1
"Building";"SupplyDepot";NA;13;0
"Building";"Refinery";NA;14;0
"Unit";"SCV";"Command Center";15;1
"Unit";"SCV";"Command Center";15;1
"Unit";"SCV";"Command Center";16;1
"Unit";"SCV";"Command Center";17;1
"Building";"Barracks";NA;15;0
"Unit";"Reaper";"Barracks";19;1
"Unit";"SCV";"Command Center";19;1
"Unit";"SCV";"Command Center";21;1
"Building";"SupplyDepot";NA;21;0
"Unit";"Reaper";"Barracks";20;1
"Unit";"SCV";"Command Center";22;1
"Building";"Factory";NA;19;0
"Building";"Bunker";NA;22;0
"Unit";"SCV";"Command Center";23;1
"Building";"CommandCenter";NA;19;0
"Unit";"SCV";"Command Center";24;1
"Building";"EngineeringBay";NA;24;0
"Unit";"Hellion";"Factory";24;2
"Building";"Refinery";NA;24;0
"Building";"BarracksReactor";NA;24;0
"Unit";"Hellion";"Factory";28;2
"Building";"Starport";NA;25;0
"Unit";"SCV";"Command Center";28;1
"Building";"MissileTurret";NA;28;0
"Unit";"SCV";"Command Center";28;1
"Unit";"Marine";"Barracks";28;1
"Unit";"Marine";"Barracks";28;1
"Unit";"SCV";"Command Center";31;1
"Building";"MissileTurret";NA;31;0
"Unit";"SCV";"Command Center";34;1
"Unit";"Marine";"Barracks";34;1
"Unit";"Marine";"Barracks";34;1
"Unit";"SCV";"Command Center";35;1
"Unit";"SCV";"Command Center";36;1
"Unit";"SCV";"Command Center";39;1
"Unit";"Marine";"Barracks";38;1
"Unit";"Marine";"Barracks";38;1
"Building";"SupplyDepot";NA;40;0
"Unit";"Cyclone";"Factory";40;3
"Building";"SupplyDepot";NA;40;0
"Unit";"SCV";"Command Center";43;1
"Unit";"SCV";"Command Center";43;1
"Unit";"Marine";"Barracks";43;1
"Unit";"Marine";"Barracks";43;1
"Unit";"SCV";"Command Center";46;1
"Unit";"SCV";"Command Center";46;1
"Building";"FactoryTechLab";NA;46;0
"Unit";"SCV";"Command Center";50;1
"Unit";"Marine";"Barracks";50;1
"Unit";"Marine";"Barracks";50;1
"Unit";"SCV";"Command Center";52;1
"Unit";"SCV";"Command Center";53;1
"Unit";"Marine";"Barracks";53;1
"Unit";"SCV";"Command Center";56;1
"Building";"Refinery";NA;55;0
"Building";"Refinery";NA;55;0
"Unit";"SCV";"Command Center";57;1
"Building";"StarportReactor";NA;52;0
"Building";"SupplyDepot";NA;57;0
"Building";"SupplyDepot";NA;58;0
"Unit";"SCV";"Command Center";60;1
"Unit";"SCV";"Command Center";60;1
"Building";"Barracks";NA;56;0
"Unit";"Marine";"Barracks";60;1
"Unit";"Marine";"Barracks";60;1
"Building";"Barracks";NA;56;0
"Unit";"SCV";"Command Center";60;1
"Unit";"SCV";"Command Center";61;1
"Building";"CommandCenter";NA;50;0
"Building";"SupplyDepot";NA;60;0
"Unit";"SCV";"Command Center";64;1
"Upgrade";"TerranInfantryWeaponsLevel1";"EngineeringBay";52;0
"Unit";"Marine";"Barracks";62;1
"Building";"BarracksTechLab";NA;66;0
"Building";"BarracksTechLab";NA;66;0
"Building";"StarportReactor";NA;60;0
"Unit";"SCV";"Command Center";66;1
"Unit";"Marine";"Barracks";66;1
"Unit";"SCV";"Command Center";68;1
"Building";"SupplyDepot";NA;66;0
"Unit";"SCV";"Command Center";69;1
"Unit";"Marine";"Barracks";69;1
"Unit";"Marine";"Barracks";69;1
"Unit";"Marine";"Barracks";69;1
"Unit";"Marine";"Barracks";71;1
"Building";"Barracks";NA;66;0
"Unit";"SCV";"Command Center";75;1
"Unit";"SCV";"Command Center";75;1
"Unit";"SCV";"Command Center";75;1
"Building";"Barracks";NA;66;0
"Unit";"Marine";"Barracks";72;1
"Unit";"Marine";"Barracks";75;1
"Unit";"Medivac";"Starport";71;2
"Unit";"Medivac";"Starport";72;2
"Unit";"SCV";"Command Center";79;1
"Unit";"SCV";"Command Center";80;1
"Unit";"Marine";"Barracks";83;1
"Unit";"Marine";"Barracks";83;1
"Unit";"Marine";"Barracks";83;1
"Unit";"Marine";"Barracks";85;1
"Unit";"SCV";"Command Center";87;1
"Unit";"SCV";"Command Center";87;1
"Building";"Armory";NA;77;0
"Building";"BarracksReactor";NA;83;0
"Unit";"Marine";"Barracks";93;1
"Unit";"Marine";"Barracks";93;1
"Unit";"Marine";"Barracks";93;1
"Building";"Factory";NA;85;0
"Unit";"SCV";"Command Center";93;1
"Unit";"SCV";"Command Center";93;1
"Unit";"Marine";"Barracks";93;1
"Unit";"Marine";"Barracks";93;1
"Unit";"Medivac";"Starport";93;2
"Unit";"Medivac";"Starport";93;2
"Unit";"Marine";"Barracks";93;1
"Unit";"Marine";"Barracks";93;1
"Unit";"Marine";"Barracks";93;1
"Unit";"Marine";"Barracks";100;1
"Unit";"Marine";"Barracks";100;1
"Unit";"Marine";"Barracks";100;1
"Upgrade";"Stimpack";"TechLab";79;0
"Upgrade";"TerranInfantryArmorsLevel1";"EngineeringBay";89;0
"Unit";"Marine";"Barracks";110;1
"Unit";"Marine";"Barracks";110;1
"Building";"BarracksReactor";NA;107;0
"Unit";"Marine";"Barracks";110;1
"Unit";"Marine";"Barracks";110;1
"Unit";"Marine";"Barracks";110;1
"Unit";"Marine";"Barracks";110;1
"Unit";"Liberator";"Starport";107;3
"Unit";"Liberator";"Starport";107;3
"Unit";"Marine";"Barracks";110;1
"Unit";"Marine";"Barracks";110;1
"Unit";"Marine";"Barracks";111;1
"Building";"CommandCenter";NA;100;0
"Unit";"Marine";"Barracks";125;1
"Unit";"Marine";"Barracks";125;1
"Unit";"Marine";"Barracks";125;1
"Unit";"Marine";"Barracks";125;1
"Unit";"Marine";"Barracks";125;1
"Building";"Refinery";NA;125;0
"Unit";"Marine";"Barracks";125;1
"Unit";"Marine";"Barracks";125;1
"Unit";"Marine";"Barracks";125;1
"Unit";"Marine";"Barracks";125;1
"Unit";"Marine";"Barracks";130;1
"Unit";"Marine";"Barracks";130;1
"Unit";"Marine";"Barracks";130;1
"Unit";"Marine";"Barracks";130;1
"Unit";"Marine";"Barracks";130;1
"Unit";"SCV";"Command Center";132;1
"Unit";"SCV";"Command Center";133;1
"Unit";"Marine";"Barracks";130;1
"Unit";"Marine";"Barracks";134;1
"Unit";"Marine";"Barracks";134;1
"Unit";"Marine";"Barracks";134;1
"Building";"EngineeringBay";NA;130;0
"Unit";"SCV";"Command Center";139;1
"Unit";"SCV";"Command Center";141;1
"Unit";"Marine";"Barracks";134;1
"Unit";"Marine";"Barracks";135;1
"Building";"SupplyDepot";NA;149;0
"Unit";"SCV";"Command Center";149;1
"Unit";"SCV";"Command Center";149;1
"Unit";"Marine";"Barracks";149;1
"Unit";"Marine";"Barracks";149;1
"Unit";"Marine";"Barracks";149;1
"Unit";"Marine";"Barracks";149;1
"Unit";"Marine";"Barracks";149;1
"Unit";"Marine";"Barracks";149;1
"Building";"MissileTurret";NA;149;0
"Unit";"SCV";"Command Center";149;1
"Building";"SupplyDepot";NA;149;0
"Unit";"Marine";"Barracks";149;1
"Unit";"Marine";"Barracks";149;1
"Unit";"Marine";"Barracks";149;1
"Unit";"SCV";"Command Center";158;1
"Unit";"SCV";"Command Center";158;1
"Unit";"Medivac";"Starport";149;2
"Unit";"Medivac";"Starport";149;2
"Unit";"Marine";"Barracks";158;1
"Unit";"Marine";"Barracks";158;1
"Building";"Barracks";NA;149;0
"Building";"Barracks";NA;149;0
"Building";"Refinery";NA;158;0
"Building";"Refinery";NA;158;0
"Building";"Barracks";NA;149;0
"Building";"SupplyDepot";NA;158;0
"Building";"SupplyDepot";NA;158;0
"Building";"SupplyDepot";NA;158;0
"Unit";"Marine";"Barracks";161;1
"Building";"SupplyDepot";NA;161;0
"Unit";"Marine";"Barracks";169;1
"Unit";"Marine";"Barracks";169;1
"Unit";"Marine";"Barracks";169;1
"Unit";"Marine";"Barracks";169;1
"Unit";"Marine";"Barracks";169;1
"Unit";"Marine";"Barracks";169;1
"Unit";"Marine";"Barracks";169;1
"Unit";"Marine";"Barracks";170;1
"Unit";"Marine";"Barracks";170;1
"Upgrade";"TerranVehicleWeaponsLevel1";"Armory";147;0
"Unit";"Marine";"Barracks";170;1
"Building";"BarracksReactor";NA;169;0
"Building";"BarracksReactor";NA;169;0
"Building";"BarracksReactor";NA;169;0
"Unit";"Marine";"Barracks";171;1
"Unit";"Marine";"Barracks";171;1
"Unit";"Marine";"Barracks";179;1
"Unit";"Marine";"Barracks";179;1
"Unit";"Marine";"Barracks";179;1
"Unit";"Marine";"Barracks";179;1
"Upgrade";"TerranInfantryWeaponsLevel2";"EngineeringBay";149;0
"Unit";"SCV";"Command Center";179;1
"Unit";"SCV";"Command Center";179;1
"Unit";"SCV";"Command Center";179;1
"Unit";"Marine";"Barracks";179;1
"Unit";"Marine";"Barracks";179;1
"Unit";"Marine";"Barracks";179;1
"Unit";"Marine";"Barracks";180;1
"Unit";"Marine";"Barracks";180;1
"Unit";"Marine";"Barracks";182;1
"Upgrade";"TerranInfantryArmorsLevel2";"EngineeringBay";158;0
"Unit";"Marine";"Barracks";195;1
"Unit";"SCV";"Command Center";195;1
"Unit";"Marine";"Barracks";195;1
"Unit";"Marine";"Barracks";195;1
"Unit";"Marine";"Barracks";195;1
"Unit";"Marine";"Barracks";195;1
"Unit";"Marine";"Barracks";195;1
"Unit";"Marine";"Barracks";195;1
"Unit";"Marine";"Barracks";195;1
"Unit";"Marine";"Barracks";195;1
"Unit";"Marine";"Barracks";195;1
"Unit";"SCV";"Command Center";195;1
"Unit";"SCV";"Command Center";195;1
"Unit";"SCV";"Command Center";195;1
"Unit";"SCV";"Command Center";196;1
"Unit";"Marine";"Barracks";195;1
"Unit";"Marine";"Barracks";195;1
"Building";"SupplyDepot";NA;195;0
"Building";"SupplyDepot";NA;195;0
"Building";"SupplyDepot";NA;195;0
"Building";"SupplyDepot";NA;195;0
"Unit";"Marine";"Barracks";195;1
"Unit";"Marine";"Barracks";204;1
"Unit";"Marine";"Barracks";204;1
