"type";"unit_name";"on_building";"total_supply";"supply"
"Building";"Barracks";NA;15;0
"Unit";"Marine";"Barracks";19;1
"Unit";"Marine";"Barracks";19;1
"Building";"Bunker";NA;19;0
"Building";"Refinery";NA;20;0
"Building";"Refinery";NA;20;0
"Unit";"Marine";"Barracks";21;1
"Building";"Refinery";NA;21;0
"Unit";"Marine";"Barracks";22;1
"Building";"CommandCenter";NA;19;0
"Building";"BarracksTechLab";NA;26;0
"Building";"Factory";NA;26;0
"Building";"BarracksReactor";NA;28;0
"Building";"Starport";NA;31;0
"Unit";"Marine";"Barracks";38;1
"Unit";"Marine";"Barracks";39;1
"Unit";"Marine";"Barracks";43;1
"Building";"Refinery";NA;46;0
"Building";"Factory";NA;46;0
"Building";"BarracksReactor";NA;48;0
"Unit";"Marine";"Barracks";55;1
"Unit";"Marine";"Barracks";55;1
"Unit";"Marine";"Barracks";55;1
"Unit";"Marine";"Barracks";56;1
"Unit";"Marine";"Barracks";57;1
"Unit";"Marine";"Barracks";58;1
"Building";"Refinery";NA;65;0
"Unit";"Marine";"Barracks";66;1
"Building";"EngineeringBay";NA;67;0
"Building";"CommandCenter";NA;63;0
"Building";"MissileTurret";NA;76;0
"Building";"MissileTurret";NA;76;0
"Building";"MissileTurret";NA;76;0
"Building";"BarracksTechLab";NA;76;0
"Building";"MissileTurret";NA;78;0
"Building";"Factory";NA;76;0
"Building";"Factory";NA;78;0
"Building";"Refinery";NA;81;0
"Building";"Refinery";NA;84;0
"Building";"StarportReactor";NA;82;0
"Unit";"Hellion";"Factory";86;2
"Unit";"Hellion";"Factory";86;2
"Building";"SensorTower";NA;88;0
"Building";"CommandCenter";NA;88;0
"Building";"Factory";NA;106;0
"Building";"Factory";NA;106;0
"Building";"MissileTurret";NA;115;0
"Building";"MissileTurret";NA;115;0
"Building";"Refinery";NA;115;0
"Building";"FactoryTechLab";NA;118;0
"Building";"FactoryTechLab";NA;118;0
"Building";"Refinery";NA;118;0
"Building";"MissileTurret";NA;124;0
"Building";"MissileTurret";NA;127;0
"Building";"MissileTurret";NA;127;0
"Building";"SensorTower";NA;132;0
"Unit";"Hellion";"Factory";132;2
"Unit";"Hellion";"Factory";136;2
"Building";"Armory";NA;132;0
"Unit";"Hellion";"Factory";136;2
"Building";"Armory";NA;132;0
"Building";"MissileTurret";NA;144;0
"Unit";"Hellion";"Factory";144;2
"Building";"CommandCenter";NA;138;0
"Unit";"Hellion";"Factory";144;2
"Building";"MissileTurret";NA;146;0
"Building";"MissileTurret";NA;146;0
"Building";"MissileTurret";NA;146;0
"Building";"MissileTurret";NA;146;0
"Unit";"Hellion";"Factory";148;2
"Upgrade";"TerranVehicleWeaponsLevel1";"Armory";144;0
"Unit";"Hellion";"Factory";150;2
"Building";"Refinery";NA;152;0
"Building";"Refinery";NA;152;0
"Building";"MissileTurret";NA;152;0
"Building";"CommandCenter";NA;150;0
"Building";"MissileTurret";NA;152;0
"Building";"MissileTurret";NA;156;0
"Building";"Barracks";NA;157;0
"Building";"EngineeringBay";NA;157;0
"Building";"FactoryTechLab";NA;157;0
"Building";"FactoryTechLab";NA;157;0
"Building";"FactoryTechLab";NA;157;0
"Building";"FactoryTechLab";NA;157;0
"Upgrade";"TerranVehicleWeaponsLevel2";"Armory";157;0
"Building";"Factory";NA;157;0
"Building";"CommandCenter";NA;157;0
"Building";"Factory";NA;157;0
"Building";"Starport";NA;157;0
"Building";"Factory";NA;157;0
"Building";"BarracksReactor";NA;157;0
"Building";"FactoryTechLab";NA;157;0
"Building";"FactoryTechLab";NA;157;0
"Building";"CommandCenter";NA;157;0
"Building";"MissileTurret";NA;157;0
"Building";"MissileTurret";NA;157;0
"Building";"StarportReactor";NA;157;0
"Building";"CommandCenter";NA;157;0
"Unit";"Hellion";"Factory";158;2
"Building";"Armory";NA;157;0
"Building";"Armory";NA;157;0
"Building";"MissileTurret";NA;159;0
"Building";"MissileTurret";NA;159;0
"Unit";"Hellion";"Factory";164;2
"Building";"Refinery";NA;166;0
"Building";"Refinery";NA;166;0
"Unit";"Hellion";"Factory";166;2
"Building";"MissileTurret";NA;168;0
"Building";"MissileTurret";NA;168;0
