"Type";"UnitName";"OnBuilding";"TotalSupply";"Supply"
"Unit";"SCV";"Command Center";12;1
"Unit";"SCV";"Command Center";12;1
"Unit";"SCV";"Command Center";13;1
"Building";"SupplyDepot";NA;13;0
"Unit";"SCV";"Command Center";15;1
"Building";"Refinery";NA;14;0
"Unit";"SCV";"Command Center";15;1
"Unit";"SCV";"Command Center";16;1
"Building";"Refinery";NA;16;0
"Unit";"SCV";"Command Center";17;1
"Building";"Barracks";NA;15;0
"Unit";"Reaper";"Barracks";19;1
"Building";"SupplyDepot";NA;19;0
"Unit";"SCV";"Command Center";19;1
"Building";"Factory";NA;19;0
"Unit";"Reaper";"Barracks";19;1
"Unit";"Hellion";"Factory";21;2
"Unit";"SCV";"Command Center";21;1
"Unit";"SCV";"Command Center";25;1
"Unit";"SCV";"Command Center";25;1
"Building";"Starport";NA;22;0
"Building";"SupplyDepot";NA;25;0
"Unit";"Cyclone";"Factory";26;3
"Unit";"SCV";"Command Center";27;1
"Building";"BarracksReactor";NA;26;0
"Building";"StarportTechLab";NA;27;0
"Unit";"SCV";"Command Center";30;1
"Unit";"Marine";"Barracks";31;1
"Unit";"Marine";"Barracks";31;1
"Unit";"SCV";"Command Center";31;1
"Building";"CommandCenter";NA;21;0
"Unit";"SCV";"Command Center";34;1
"Unit";"Marine";"Barracks";35;1
"Unit";"Marine";"Barracks";35;1
"Unit";"Raven";"Starport";31;2
"Unit";"SCV";"Command Center";35;1
"Unit";"Cyclone";"Factory";35;3
"Unit";"SCV";"Command Center";40;1
"Unit";"SCV";"Command Center";41;1
"Unit";"SCV";"Command Center";44;1
"Building";"FactoryTechLab";NA;44;0
"Unit";"SCV";"Command Center";45;1
"Unit";"SCV";"Command Center";46;1
"Building";"EngineeringBay";NA;44;0
"Building";"StarportReactor";NA;41;0
"Unit";"Marine";"Barracks";47;1
"Building";"Refinery";NA;46;0
"Building";"SupplyDepot";NA;47;0
"Unit";"SCV";"Command Center";48;1
"Unit";"SCV";"Command Center";49;1
"Building";"Barracks";NA;41;0
"Building";"Barracks";NA;41;0
"Building";"SupplyDepot";NA;49;0
"Unit";"SCV";"Command Center";51;1
"Unit";"SCV";"Command Center";51;1
"Unit";"Marine";"Barracks";51;1
"Unit";"Marine";"Barracks";52;1
"Unit";"Marine";"Barracks";52;1
"Unit";"SCV";"Command Center";52;1
"Unit";"SCV";"Command Center";53;1
"Unit";"Marine";"Barracks";54;1
"Unit";"Marine";"Barracks";54;1
"Unit";"SCV";"Command Center";57;1
"Unit";"SCV";"Command Center";59;1
"Building";"StarportReactor";NA;52;0
"Unit";"SCV";"Command Center";63;1
"Unit";"SCV";"Command Center";63;1
"Building";"Bunker";NA;59;0
"Unit";"Marine";"Barracks";63;1
"Unit";"Marine";"Barracks";63;1
"Unit";"Marine";"Barracks";63;1
"Unit";"Marine";"Barracks";63;1
"Unit";"Marine";"Barracks";63;1
"Building";"SupplyDepot";NA;63;0
"Building";"SupplyDepot";NA;63;0
"Unit";"SCV";"Command Center";65;1
"Unit";"SCV";"Command Center";70;1
"Unit";"Medivac";"Starport";63;2
"Unit";"Marine";"Barracks";70;1
"Unit";"Marine";"Barracks";70;1
"Unit";"Marine";"Barracks";70;1
"Unit";"SCV";"Command Center";70;1
"Upgrade";"Stimpack";"TechLab";51;0
"Unit";"Marine";"Barracks";70;1
"Unit";"SCV";"Command Center";72;1
"Unit";"Marine";"Barracks";71;1
"Building";"SupplyDepot";NA;72;0
"Unit";"Medivac";"Starport";70;2
"Unit";"SCV";"Command Center";81;1
"Unit";"SCV";"Command Center";81;1
"Unit";"Marine";"Barracks";78;1
"Unit";"Marine";"Barracks";78;1
"Unit";"Marine";"Barracks";78;1
"Unit";"Marauder";"Barracks";80;2
"Building";"SupplyDepot";NA;81;0
"Building";"SupplyDepot";NA;81;0
"Unit";"SCV";"Command Center";88;1
"Unit";"SCV";"Command Center";88;1
"Unit";"Marine";"Barracks";87;1
"Unit";"Marine";"Barracks";88;1
"Unit";"Marine";"Barracks";88;1
"Unit";"Marine";"Barracks";88;1
"Upgrade";"TerranInfantryWeaponsLevel1";"EngineeringBay";63;0
"Unit";"Marine";"Barracks";96;1
"Unit";"Marine";"Barracks";96;1
"Unit";"Marine";"Barracks";96;1
"Unit";"Marine";"Barracks";96;1
"Unit";"Marauder";"Barracks";96;2
"Unit";"Marine";"Barracks";102;1
"Unit";"Marine";"Barracks";102;1
"Unit";"Marine";"Barracks";102;1
"Unit";"Marine";"Barracks";102;1
"Unit";"SCV";"Command Center";102;1
"Unit";"Marauder";"Barracks";102;2
"Building";"Refinery";NA;102;0
"Building";"EngineeringBay";NA;102;0
"Unit";"Marine";"Barracks";107;1
"Unit";"Marine";"Barracks";109;1
"Unit";"Marine";"Barracks";109;1
"Unit";"Marine";"Barracks";109;1
"Building";"Barracks";NA;102;0
"Building";"Barracks";NA;102;0
"Unit";"Marauder";"Barracks";109;2
"Building";"CommandCenter";NA;96;0
"Building";"Armory";NA;102;0
"Unit";"Marine";"Barracks";109;1
"Unit";"SCV";"Command Center";112;1
"Unit";"SCV";"Command Center";113;1
"Unit";"Marine";"Barracks";113;1
"Unit";"Marine";"Barracks";113;1
"Unit";"SCV";"Command Center";116;1
"Unit";"Marauder";"Barracks";113;2
"Unit";"Marine";"Barracks";115;1
"Building";"BarracksTechLab";NA;116;0
"Building";"BarracksTechLab";NA;116;0
"Unit";"Marine";"Barracks";118;1
"Unit";"Marine";"Barracks";118;1
"Unit";"Marine";"Barracks";121;1
"Unit";"Marine";"Barracks";124;1
"Unit";"Marine";"Barracks";124;1
"Unit";"Marauder";"Barracks";121;2
"Unit";"Marauder";"Barracks";124;2
"Unit";"SCV";"Command Center";127;1
"Unit";"SCV";"Command Center";127;1
"Unit";"Marine";"Barracks";126;1
"Unit";"Marine";"Barracks";126;1
"Unit";"Marine";"Barracks";131;1
"Unit";"Marauder";"Barracks";128;2
"Unit";"Marine";"Barracks";133;1
"Unit";"Marauder";"Barracks";129;2
"Upgrade";"TerranInfantryArmorsLevel1";"EngineeringBay";109;0
"Unit";"Marauder";"Barracks";133;2
"Unit";"Marine";"Barracks";135;1
"Unit";"SCV";"Command Center";138;1
"Unit";"SCV";"Command Center";141;1
"Unit";"Marine";"Barracks";137;1
"Unit";"Marine";"Barracks";137;1
"Unit";"Medivac";"Starport";135;2
"Unit";"Medivac";"Starport";135;2
"Unit";"Marauder";"Barracks";138;2
"Unit";"SCV";"Command Center";146;1
"Unit";"SCV";"Command Center";147;1
"Building";"SupplyDepot";NA;146;0
"Building";"SupplyDepot";NA;146;0
"Building";"SupplyDepot";NA;148;0
