"type";"unit_name";"on_building";"total_supply";"supply"
"Building";"Refinery";NA;14;0
"Building";"Refinery";NA;16;0
"Building";"Barracks";NA;15;0
"Unit";"Reaper";"Barracks";19;1
"Building";"Factory";NA;19;0
"Building";"BarracksReactor";NA;20;0
"Unit";"Cyclone";"Factory";24;3
"Unit";"Cyclone";"Factory";24;3
"Building";"CommandCenter";NA;21;0
"Unit";"Cyclone";"Factory";33;3
"Unit";"Cyclone";"Factory";33;3
"Unit";"Cyclone";"Factory";42;3
"Building";"Refinery";NA;42;0
"Unit";"Cyclone";"Factory";42;3
"Building";"Refinery";NA;42;0
"Unit";"Cyclone";"Factory";51;3
"Building";"CommandCenter";NA;41;0
"Unit";"Cyclone";"Factory";52;3
"Building";"Factory";NA;52;0
"Building";"BarracksTechLab";NA;59;0
"Building";"Factory";NA;54;0
"Unit";"Hellion";"Factory";62;2
"Unit";"Hellion";"Factory";62;2
"Building";"FactoryTechLab";NA;70;0
"Unit";"Hellion";"Factory";74;2
"Unit";"Hellion";"Factory";74;2
"Building";"Starport";NA;70;0
"Building";"BarracksReactor";NA;72;0
"Unit";"Hellion";"Factory";84;2
"Unit";"Hellion";"Factory";84;2
"Building";"Refinery";NA;87;0
"Building";"Refinery";NA;87;0
"Unit";"Medivac";"Starport";87;2
"Unit";"Medivac";"Starport";87;2
"Unit";"Hellion";"Factory";93;2
"Unit";"Hellion";"Factory";95;2
"Building";"Armory";NA;93;0
"Building";"Armory";NA;93;0
"Unit";"Hellion";"Factory";107;2
"Unit";"Hellion";"Factory";107;2
"Unit";"Hellion";"Factory";116;2
"Unit";"Hellion";"Factory";116;2
"Building";"Refinery";NA;116;0
"Unit";"Medivac";"Starport";116;2
"Unit";"Medivac";"Starport";116;2
"Building";"EngineeringBay";NA;123;0
"Unit";"Hellion";"Factory";125;2
"Unit";"Hellion";"Factory";126;2
"Building";"Factory";NA;117;0
"Building";"Factory";NA;118;0
"Unit";"Medivac";"Starport";128;2
"Unit";"Hellion";"Factory";135;2
"Unit";"Hellion";"Factory";137;2
"Unit";"Medivac";"Starport";133;2
"Unit";"Hellion";"Factory";142;2
"Unit";"Hellion";"Factory";142;2
"Unit";"Hellion";"Factory";145;2
"Unit";"Hellion";"Factory";149;2
"Unit";"Medivac";"Starport";143;2
"Unit";"Hellion";"Factory";159;2
"Unit";"Hellion";"Factory";159;2
"Unit";"Hellion";"Factory";160;2
"Unit";"Hellion";"Factory";166;2
"Building";"Armory";NA;153;0
"Building";"Armory";NA;153;0
"Unit";"Hellion";"Factory";170;2
"Building";"FactoryTechLab";NA;172;0
"Building";"SensorTower";NA;176;0
"Unit";"Hellion";"Factory";176;2
"Unit";"Hellion";"Factory";176;2
"Building";"CommandCenter";NA;170;0
"Unit";"Hellion";"Factory";182;2
"Unit";"Hellion";"Factory";182;2
"Building";"SensorTower";NA;184;0
"Unit";"Hellion";"Factory";186;2
"Unit";"Hellion";"Factory";186;2
"Building";"FactoryReactor";NA;182;0
"Unit";"Hellion";"Factory";188;2
"Building";"MissileTurret";NA;190;0
"Building";"MissileTurret";NA;190;0
"Building";"MissileTurret";NA;190;0
"Building";"MissileTurret";NA;190;0
"Building";"Refinery";NA;190;0
"Upgrade";"TerranVehicleWeaponsLevel1";"Armory";176;0
"Building";"Refinery";NA;190;0
"Unit";"Hellion";"Factory";192;2
"Unit";"Hellion";"Factory";194;2
"Unit";"Hellion";"Factory";200;2
"Unit";"Hellion";"Factory";200;2
"Unit";"Hellion";"Factory";202;2
"Unit";"Hellion";"Factory";213;2
"Unit";"Hellion";"Factory";213;2
"Unit";"Hellion";"Factory";213;2
"Building";"SensorTower";NA;213;0
"Building";"Refinery";NA;216;0
"Building";"MissileTurret";NA;217;0
"Building";"MissileTurret";NA;219;0
"Building";"MissileTurret";NA;223;0
"Unit";"Hellion";"Factory";223;2
"Unit";"Hellion";"Factory";223;2
"Unit";"Hellion";"Factory";228;2
"Unit";"Hellion";"Factory";228;2
"Unit";"Hellion";"Factory";228;2
"Unit";"Hellion";"Factory";228;2
"Unit";"Hellion";"Factory";236;2
"Unit";"Hellion";"Factory";236;2
"Unit";"Hellion";"Factory";236;2
"Unit";"Liberator";"Starport";242;3
"Building";"CommandCenter";NA;236;0
"Building";"CommandCenter";NA;242;0
"Upgrade";"TerranVehicleWeaponsLevel2";"Armory";236;0
"Unit";"Hellion";"Factory";247;2
"Unit";"Hellion";"Factory";247;2
"Unit";"Liberator";"Starport";247;3
"Unit";"Hellion";"Factory";266;2
"Unit";"Hellion";"Factory";266;2
"Building";"Refinery";NA;277;0
"Unit";"Hellion";"Factory";279;2
"Unit";"Hellion";"Factory";287;2
"Building";"Refinery";NA;277;0
"Unit";"Hellion";"Factory";295;2
"Unit";"Hellion";"Factory";295;2
"Unit";"Hellion";"Factory";303;2
"Unit";"Hellion";"Factory";303;2
"Unit";"Hellion";"Factory";315;2
"Unit";"Hellion";"Factory";315;2
"Unit";"Hellion";"Factory";315;2
"Unit";"Hellion";"Factory";315;2
"Unit";"Hellion";"Factory";315;2
"Unit";"Hellion";"Factory";315;2
"Building";"Refinery";NA;315;0
"Unit";"Hellion";"Factory";315;2
"Building";"Refinery";NA;319;0
"Unit";"Hellion";"Factory";319;2
"Unit";"Hellion";"Factory";331;2
"Unit";"Hellion";"Factory";331;2
"Unit";"Hellion";"Factory";331;2
"Unit";"Hellion";"Factory";331;2
"Unit";"Hellion";"Factory";331;2
"Building";"CommandCenter";NA;319;0
"Unit";"Hellion";"Factory";331;2
"Unit";"Hellion";"Factory";333;2
"Unit";"Hellion";"Factory";335;2
"Unit";"Hellion";"Factory";337;2
"Unit";"Hellion";"Factory";339;2
"Unit";"Hellion";"Factory";341;2
"Unit";"Hellion";"Factory";341;2
"Unit";"Hellion";"Factory";343;2
"Unit";"Hellion";"Factory";343;2
"Unit";"Hellion";"Factory";345;2
"Unit";"Hellion";"Factory";347;2
"Building";"MissileTurret";NA;353;0
"Building";"MissileTurret";NA;353;0
"Building";"MissileTurret";NA;355;0
"Building";"MissileTurret";NA;357;0
"Building";"MissileTurret";NA;357;0
"Unit";"Hellion";"Factory";357;2
"Unit";"Hellion";"Factory";357;2
"Unit";"Hellion";"Factory";357;2
"Unit";"Hellion";"Factory";357;2
"Building";"MissileTurret";NA;363;0
"Unit";"Hellion";"Factory";357;2
"Building";"Refinery";NA;365;0
"Building";"Refinery";NA;373;0
"Building";"CommandCenter";NA;343;0
"Unit";"Hellion";"Factory";373;2
"Unit";"Hellion";"Factory";379;2
"Unit";"Hellion";"Factory";379;2
"Unit";"Hellion";"Factory";379;2
"Unit";"Hellion";"Factory";379;2
"Unit";"Hellion";"Factory";379;2
"Unit";"Liberator";"Starport";389;3
"Unit";"Liberator";"Starport";389;3
"Building";"Refinery";NA;390;0
"Building";"Refinery";NA;390;0
"Unit";"Hellion";"Factory";398;2
"Unit";"Hellion";"Factory";398;2
"Unit";"Hellion";"Factory";398;2
"Upgrade";"TerranVehicleWeaponsLevel3";"Armory";379;0
"Unit";"Hellion";"Factory";406;2
"Unit";"Hellion";"Factory";406;2
"Unit";"Hellion";"Factory";410;2
"Unit";"Hellion";"Factory";410;2
"Unit";"Hellion";"Factory";410;2
"Unit";"Hellion";"Factory";410;2
"Unit";"Hellion";"Factory";410;2
"Unit";"Hellion";"Factory";410;2
"Unit";"Hellion";"Factory";412;2
"Building";"Refinery";NA;424;0
"Unit";"Hellion";"Factory";424;2
"Unit";"Hellion";"Factory";424;2
"Unit";"Hellion";"Factory";424;2
"Unit";"Hellion";"Factory";424;2
"Building";"CommandCenter";NA;410;0
"Upgrade";"TerranShipWeaponsLevel1";"Armory";410;0
