"type";"unit_name";"on_building";"total_supply";"supply"
"Building";"Refinery";NA;14;0
"Building";"Barracks";NA;15;0
"Unit";"Marine";"Barracks";19;1
"Building";"Refinery";NA;20;0
"Building";"BarracksReactor";NA;20;0
"Building";"Factory";NA;20;0
"Building";"CommandCenter";NA;19;0
"Unit";"Cyclone";"Factory";23;3
"Unit";"Cyclone";"Factory";24;3
"Unit";"Cyclone";"Factory";31;3
"Unit";"Cyclone";"Factory";31;3
"Building";"Refinery";NA;32;0
"Building";"BarracksTechLab";NA;36;0
"Unit";"Cyclone";"Factory";36;3
"Building";"FactoryTechLab";NA;49;0
"Building";"EngineeringBay";NA;51;0
"Unit";"Marine";"Barracks";53;1
"Building";"Starport";NA;51;0
"Building";"Barracks";NA;49;0
"Building";"Barracks";NA;49;0
"Unit";"Marine";"Barracks";55;1
"Unit";"Marine";"Barracks";58;1
"Unit";"Marine";"Barracks";58;1
"Unit";"Marine";"Barracks";60;1
"Building";"StarportReactor";NA;58;0
"Unit";"Marine";"Barracks";65;1
"Unit";"Marine";"Barracks";65;1
"Unit";"Marine";"Barracks";65;1
"Upgrade";"Stimpack";"TechLab";49;0
"Unit";"Marine";"Barracks";65;1
"Unit";"Marine";"Barracks";68;1
"Unit";"Medivac";"Starport";71;2
"Unit";"Medivac";"Starport";71;2
"Building";"BarracksReactor";NA;73;0
"Unit";"Marine";"Barracks";78;1
"Unit";"Marine";"Barracks";78;1
"Unit";"Marine";"Barracks";78;1
"Upgrade";"TerranInfantryWeaponsLevel1";"EngineeringBay";63;0
"Unit";"Marine";"Barracks";83;1
"Building";"CommandCenter";NA;68;0
"Unit";"Marine";"Barracks";88;1
"Unit";"Marine";"Barracks";88;1
"Unit";"Marine";"Barracks";88;1
"Unit";"Marine";"Barracks";88;1
"Unit";"Marine";"Barracks";88;1
"Unit";"Medivac";"Starport";88;2
"Unit";"Medivac";"Starport";88;2
"Building";"MissileTurret";NA;96;0
"Building";"MissileTurret";NA;96;0
"Building";"MissileTurret";NA;98;0
"Unit";"Marine";"Barracks";98;1
"Unit";"Marine";"Barracks";98;1
"Unit";"Marine";"Barracks";98;1
"Building";"MissileTurret";NA;98;0
"Unit";"Marine";"Barracks";105;1
"Unit";"Marine";"Barracks";105;1
"Unit";"Marine";"Barracks";105;1
"Unit";"Marine";"Barracks";105;1
"Unit";"Marine";"Barracks";105;1
"Building";"Refinery";NA;105;0
"Unit";"Marine";"Barracks";113;1
"Unit";"Marine";"Barracks";113;1
"Unit";"Marine";"Barracks";113;1
"Unit";"Marine";"Barracks";113;1
"Unit";"Marine";"Barracks";113;1
"Building";"EngineeringBay";NA;105;0
"Unit";"Medivac";"Starport";105;2
"Building";"Armory";NA;105;0
"Unit";"Marine";"Barracks";120;1
"Unit";"Marine";"Barracks";120;1
"Unit";"Marine";"Barracks";120;1
"Unit";"Marine";"Barracks";120;1
"Unit";"Marine";"Barracks";120;1
"Upgrade";"TerranInfantryArmorsLevel1";"EngineeringBay";113;0
"Unit";"Marine";"Barracks";120;1
"Unit";"Marine";"Barracks";125;1
"Unit";"Marine";"Barracks";125;1
"Unit";"Marine";"Barracks";128;1
"Unit";"Marine";"Barracks";128;1
"Unit";"Marine";"Barracks";128;1
"Unit";"Marine";"Barracks";128;1
"Unit";"Marine";"Barracks";128;1
"Building";"Barracks";NA;128;0
"Building";"Barracks";NA;128;0
"Unit";"Marine";"Barracks";128;1
"Unit";"Marine";"Barracks";128;1
"Unit";"Marine";"Barracks";128;1
"Unit";"Marine";"Barracks";136;1
"Unit";"Marine";"Barracks";136;1
"Unit";"Marine";"Barracks";136;1
"Unit";"Marine";"Barracks";136;1
"Unit";"Marine";"Barracks";136;1
"Unit";"Marine";"Barracks";141;1
"Building";"CommandCenter";NA;133;0
"Unit";"Marine";"Barracks";141;1
"Unit";"Marine";"Barracks";141;1
"Unit";"Marine";"Barracks";144;1
"Unit";"Marine";"Barracks";144;1
"Unit";"Marine";"Barracks";144;1
"Unit";"Marine";"Barracks";144;1
"Unit";"Marine";"Barracks";144;1
"Building";"CommandCenter";NA;141;0
"Unit";"Medivac";"Starport";144;2
"Unit";"Medivac";"Starport";144;2
"Unit";"Marine";"Barracks";149;1
"Unit";"Marine";"Barracks";149;1
"Unit";"Marine";"Barracks";149;1
"Unit";"Marine";"Barracks";149;1
"Unit";"Marine";"Barracks";149;1
"Unit";"Marine";"Barracks";158;1
"Unit";"Marine";"Barracks";158;1
"Unit";"Marine";"Barracks";158;1
"Unit";"Marine";"Barracks";158;1
"Unit";"Marine";"Barracks";158;1
"Unit";"Marine";"Barracks";158;1
"Unit";"Marine";"Barracks";159;1
"Unit";"Marine";"Barracks";160;1
"Unit";"Marine";"Barracks";160;1
"Unit";"Marine";"Barracks";165;1
"Unit";"Marine";"Barracks";165;1
"Unit";"Marine";"Barracks";166;1
"Unit";"Marine";"Barracks";167;1
"Unit";"Marine";"Barracks";167;1
"Building";"Barracks";NA;158;0
"Building";"Barracks";NA;158;0
"Unit";"Marine";"Barracks";170;1
"Unit";"Marine";"Barracks";171;1
"Unit";"Marine";"Barracks";172;1
"Unit";"Marine";"Barracks";173;1
"Unit";"Marine";"Barracks";173;1
"Unit";"Marine";"Barracks";177;1
"Unit";"Marine";"Barracks";182;1
"Unit";"Marine";"Barracks";182;1
"Unit";"Marine";"Barracks";182;1
"Unit";"Marine";"Barracks";182;1
"Building";"BarracksReactor";NA;175;0
"Building";"BarracksReactor";NA;175;0
"Unit";"Marine";"Barracks";182;1
"Unit";"Marine";"Barracks";185;1
"Unit";"Marine";"Barracks";186;1
"Unit";"Marine";"Barracks";187;1
"Unit";"Marine";"Barracks";188;1
"Unit";"Marine";"Barracks";189;1
"Unit";"Marine";"Barracks";189;1
"Unit";"Marine";"Barracks";189;1
"Unit";"Marine";"Barracks";189;1
"Unit";"Marine";"Barracks";189;1
