"Type";"UnitName";"OnBuilding";"TotalSupply";"Supply"
"Unit";"SCV";"Command Center";12;1
"Unit";"SCV";"Command Center";12;1
"Unit";"SCV";"Command Center";13;1
"Building";"SupplyDepot";NA;13;0
"Unit";"SCV";"Command Center";15;1
"Building";"Refinery";NA;14;0
"Unit";"SCV";"Command Center";15;1
"Unit";"SCV";"Command Center";16;1
"Building";"Refinery";NA;16;0
"Unit";"SCV";"Command Center";17;1
"Building";"Barracks";NA;15;0
"Unit";"Reaper";"Barracks";19;1
"Unit";"SCV";"Command Center";19;1
"Building";"SupplyDepot";NA;19;0
"Building";"Factory";NA;19;0
"Unit";"SCV";"Command Center";20;1
"Unit";"SCV";"Command Center";21;1
"Unit";"Reaper";"Barracks";19;1
"Unit";"SCV";"Command Center";23;1
"Unit";"Cyclone";"Factory";22;3
"Building";"SupplyDepot";NA;23;0
"Building";"BarracksTechLab";NA;24;0
"Unit";"SCV";"Command Center";24;1
"Building";"Starport";NA;22;0
"Unit";"SCV";"Command Center";28;1
"Unit";"Hellion";"Factory";28;2
"Unit";"SCV";"Command Center";29;1
"Building";"FactoryTechLab";NA;32;0
"Building";"BarracksReactor";NA;29;0
"Unit";"SCV";"Command Center";33;1
"Unit";"Marine";"Barracks";33;1
"Unit";"Marine";"Barracks";33;1
"Unit";"Raven";"Starport";33;2
"Unit";"SCV";"Command Center";36;1
"Unit";"Marine";"Barracks";36;1
"Unit";"Marine";"Barracks";36;1
"Building";"SupplyDepot";NA;36;0
"Building";"CommandCenter";NA;33;0
"Unit";"SCV";"Command Center";41;1
"Unit";"SCV";"Command Center";42;1
"Unit";"SCV";"Command Center";42;1
"Unit";"SCV";"Command Center";42;1
"Unit";"Marine";"Barracks";43;1
"Unit";"SCV";"Command Center";43;1
"Unit";"SCV";"Command Center";44;1
"Building";"Barracks";NA;42;0
"Unit";"SCV";"Command Center";46;1
"Unit";"SCV";"Command Center";47;1
"Unit";"Marine";"Barracks";47;1
"Unit";"SCV";"Command Center";48;1
"Unit";"SCV";"Command Center";49;1
"Building";"EngineeringBay";NA;48;0
"Building";"EngineeringBay";NA;48;0
"Unit";"SCV";"Command Center";51;1
"Unit";"Marine";"Barracks";51;1
"Unit";"SCV";"Command Center";52;1
"Unit";"SCV";"Command Center";53;1
"Building";"Refinery";NA;53;0
"Building";"SupplyDepot";NA;53;0
"Building";"BarracksReactor";NA;50;0
"Unit";"SCV";"Command Center";55;1
"Building";"Barracks";NA;48;0
"Unit";"SCV";"Command Center";56;1
"Building";"SupplyDepot";NA;56;0
"Building";"Refinery";NA;56;0
"Unit";"SCV";"Command Center";59;1
"Unit";"SCV";"Command Center";59;1
"Unit";"Marine";"Barracks";59;1
"Unit";"Marine";"Barracks";59;1
"Unit";"SCV";"Command Center";60;1
"Unit";"Marine";"Barracks";59;1
"Building";"SupplyDepot";NA;59;0
"Building";"SupplyDepot";NA;59;0
"Building";"BarracksReactor";NA;59;0
"Unit";"Medivac";"Starport";59;2
"Unit";"Marine";"Barracks";63;1
"Unit";"Marine";"Barracks";63;1
"Upgrade";"Stimpack";"TechLab";50;0
"Unit";"Marine";"Barracks";64;1
"Unit";"SCV";"Command Center";65;1
"Building";"MissileTurret";NA;65;0
"Unit";"SCV";"Command Center";70;1
"Unit";"Marine";"Barracks";67;1
"Building";"MissileTurret";NA;67;0
"Unit";"Marine";"Barracks";67;1
"Unit";"Marine";"Barracks";69;1
"Building";"SupplyDepot";NA;69;0
"Unit";"Liberator";"Starport";63;3
"Unit";"SCV";"Command Center";71;1
"Unit";"Marine";"Barracks";71;1
"Unit";"Marine";"Barracks";71;1
"Unit";"Marine";"Barracks";81;1
"Unit";"Marine";"Barracks";81;1
"Unit";"Marine";"Barracks";81;1
"Unit";"Marine";"Barracks";81;1
"Unit";"Marine";"Barracks";81;1
"Unit";"Marine";"Barracks";81;1
"Unit";"SCV";"Command Center";86;1
"Upgrade";"TerranInfantryWeaponsLevel1";"EngineeringBay";65;0
"Unit";"Marine";"Barracks";86;1
"Unit";"Marine";"Barracks";86;1
"Unit";"Marine";"Barracks";86;1
"Building";"Barracks";NA;86;0
"Building";"Barracks";NA;86;0
"Unit";"Marine";"Barracks";91;1
"Unit";"Marine";"Barracks";91;1
"Unit";"Marine";"Barracks";91;1
"Unit";"Marine";"Barracks";91;1
"Unit";"Marine";"Barracks";91;1
"Upgrade";"TerranInfantryArmorsLevel1";"EngineeringBay";80;0
"Building";"Armory";NA;86;0
"Unit";"SCV";"Command Center";91;1
"Unit";"SCV";"Command Center";91;1
"Unit";"Marine";"Barracks";91;1
"Unit";"Marine";"Barracks";92;1
"Unit";"Marine";"Barracks";93;1
"Building";"CommandCenter";NA;86;0
"Unit";"Marine";"Barracks";96;1
"Unit";"SCV";"Command Center";98;1
"Unit";"SCV";"Command Center";98;1
"Unit";"Medivac";"Starport";96;2
"Unit";"Medivac";"Starport";96;2
"Building";"BarracksReactor";NA;96;0
"Building";"BarracksReactor";NA;96;0
"Unit";"SCV";"Command Center";104;1
"Unit";"Marine";"Barracks";101;1
"Unit";"Marine";"Barracks";101;1
"Unit";"Marine";"Barracks";104;1
"Unit";"Marine";"Barracks";108;1
"Unit";"Marine";"Barracks";108;1
"Building";"Factory";NA;98;0
"Unit";"SCV";"Command Center";112;1
"Unit";"Medivac";"Starport";104;2
"Unit";"Medivac";"Starport";108;2
"Building";"Starport";NA;106;0
"Building";"FactoryTechLab";NA;114;0
"Unit";"SCV";"Command Center";119;1
"Unit";"SCV";"Command Center";119;1
"Unit";"Marine";"Barracks";117;1
"Unit";"Marine";"Barracks";117;1
"Unit";"Marine";"Barracks";117;1
"Unit";"Marine";"Barracks";117;1
"Unit";"Marine";"Barracks";117;1
"Unit";"SCV";"Command Center";119;1
"Unit";"SCV";"Command Center";120;1
"Building";"MissileTurret";NA;119;0
"Unit";"Marine";"Barracks";119;1
"Building";"MissileTurret";NA;126;0
"Unit";"SCV";"Command Center";126;1
"Building";"MissileTurret";NA;126;0
"Building";"SensorTower";NA;126;0
"Building";"StarportTechLab";NA;126;0
"Unit";"Marine";"Barracks";126;1
"Unit";"Marine";"Barracks";126;1
"Unit";"Marine";"Barracks";126;1
"Unit";"SCV";"Command Center";130;1
"Unit";"SCV";"Command Center";130;1
"Unit";"Marine";"Barracks";130;1
"Unit";"Marine";"Barracks";130;1
"Unit";"Marine";"Barracks";130;1
"Building";"Refinery";NA;130;0
"Building";"Refinery";NA;130;0
"Building";"SupplyDepot";NA;130;0
"Building";"SupplyDepot";NA;130;0
"Building";"SupplyDepot";NA;130;0
"Building";"SupplyDepot";NA;133;0
"Unit";"Marine";"Barracks";138;1
"Unit";"Marine";"Barracks";138;1
"Unit";"Marine";"Barracks";138;1
"Unit";"Marine";"Barracks";138;1
"Unit";"Marine";"Barracks";138;1
"Unit";"Marine";"Barracks";138;1
"Unit";"Marine";"Barracks";138;1
"Unit";"Marine";"Barracks";138;1
"Unit";"SCV";"Command Center";138;1
"Unit";"Marine";"Barracks";138;1
"Building";"SupplyDepot";NA;138;0
"Building";"SupplyDepot";NA;138;0
"Upgrade";"TerranVehicleWeaponsLevel1";"Armory";119;0
"Unit";"Marine";"Barracks";138;1
"Unit";"Marine";"Barracks";147;1
"Unit";"Marine";"Barracks";147;1
"Unit";"Marine";"Barracks";147;1
"Unit";"Marine";"Barracks";147;1
"Unit";"Marine";"Barracks";147;1
"Upgrade";"TerranInfantryWeaponsLevel2";"EngineeringBay";125;0
"Upgrade";"TerranInfantryArmorsLevel2";"EngineeringBay";126;0
"Unit";"Marine";"Barracks";149;1
"Unit";"Marine";"Barracks";149;1
"Unit";"Marine";"Barracks";149;1
"Unit";"Marine";"Barracks";149;1
"Building";"SupplyDepot";NA;154;0
"Building";"SupplyDepot";NA;154;0
"Unit";"Marine";"Barracks";158;1
"Unit";"Marine";"Barracks";158;1
"Unit";"Marine";"Barracks";158;1
"Unit";"Marine";"Barracks";158;1
"Unit";"Marauder";"Barracks";158;2
"Unit";"Marine";"Barracks";158;1
"Unit";"Marine";"Barracks";158;1
"Unit";"Marine";"Barracks";158;1
"Unit";"Marine";"Barracks";158;1
"Unit";"Marine";"Barracks";158;1
