"Type";"UnitName";"OnBuilding";"TotalSupply";"Supply"
"Unit";"SCV";"Command Center";12;1
"Unit";"SCV";"Command Center";12;1
"Unit";"SCV";"Command Center";13;1
"Building";"SupplyDepot";NA;13;0
"Unit";"SCV";"Command Center";15;1
"Building";"Refinery";NA;14;0
"Unit";"SCV";"Command Center";15;1
"Unit";"SCV";"Command Center";16;1
"Unit";"SCV";"Command Center";17;1
"Building";"Barracks";NA;15;0
"Unit";"Reaper";"Barracks";19;1
"Unit";"SCV";"Command Center";20;1
"Building";"SupplyDepot";NA;20;0
"Unit";"Reaper";"Barracks";20;1
"Unit";"SCV";"Command Center";21;1
"Building";"Refinery";NA;21;0
"Building";"Factory";NA;19;0
"Unit";"SCV";"Command Center";22;1
"Unit";"Marine";"Barracks";23;1
"Building";"CommandCenter";NA;19;0
"Unit";"SCV";"Command Center";23;1
"Unit";"Hellion";"Factory";23;2
"Building";"Starport";NA;23;0
"Unit";"SCV";"Command Center";28;1
"Unit";"SCV";"Command Center";28;1
"Unit";"Cyclone";"Factory";28;3
"Unit";"SCV";"Command Center";29;1
"Unit";"SCV";"Command Center";29;1
"Unit";"Marine";"Barracks";29;1
"Building";"SupplyDepot";NA;30;0
"Unit";"SCV";"Command Center";35;1
"Unit";"SCV";"Command Center";35;1
"Unit";"SCV";"Command Center";36;1
"Unit";"SCV";"Command Center";37;1
"Unit";"Liberator";"Starport";29;3
"Unit";"Marine";"Barracks";36;1
"Unit";"Cyclone";"Factory";36;3
"Building";"SupplyDepot";NA;36;0
"Unit";"SCV";"Command Center";38;1
"Unit";"SCV";"Command Center";39;1
"Building";"StarportTechLab";NA;43;0
"Unit";"SCV";"Command Center";49;1
"Unit";"SCV";"Command Center";49;1
"Unit";"SCV";"Command Center";49;1
"Building";"BarracksReactor";NA;44;0
"Unit";"SCV";"Command Center";51;1
"Unit";"SCV";"Command Center";52;1
"Unit";"Cyclone";"Factory";50;3
"Building";"Refinery";NA;51;0
"Building";"Refinery";NA;51;0
"Building";"SupplyDepot";NA;51;0
"Unit";"Marine";"Barracks";52;1
"Unit";"Marine";"Barracks";52;1
"Unit";"SCV";"Command Center";57;1
"Unit";"SCV";"Command Center";57;1
"Building";"FactoryTechLab";NA;57;0
"Unit";"SCV";"Command Center";59;1
"Unit";"SCV";"Command Center";61;1
"Building";"CommandCenter";NA;49;0
"Unit";"SCV";"Command Center";63;1
"Unit";"SCV";"Command Center";63;1
"Unit";"Marine";"Barracks";63;1
"Building";"Barracks";NA;60;0
"Building";"Barracks";NA;61;0
"Unit";"SCV";"Command Center";66;1
"Unit";"SCV";"Command Center";66;1
"Unit";"Raven";"Starport";61;2
"Unit";"Marine";"Barracks";66;1
"Unit";"Marine";"Barracks";66;1
"Building";"EngineeringBay";NA;63;0
"Unit";"SCV";"Command Center";66;1
"Unit";"SCV";"Command Center";72;1
"Building";"EngineeringBay";NA;66;0
"Unit";"SCV";"Command Center";73;1
"Unit";"SCV";"Command Center";73;1
"Unit";"Marine";"Barracks";72;1
"Unit";"Marine";"Barracks";73;1
"Unit";"SCV";"Command Center";74;1
"Unit";"Marine";"Barracks";73;1
"Building";"BarracksReactor";NA;67;0
"Unit";"SCV";"Command Center";76;1
"Building";"StarportReactor";NA;72;0
"Unit";"SCV";"Command Center";80;1
"Building";"SupplyDepot";NA;76;0
"Unit";"Marine";"Barracks";80;1
"Unit";"Marine";"Barracks";80;1
"Unit";"Marine";"Barracks";80;1
"Unit";"SCV";"Command Center";81;1
"Unit";"Marine";"Barracks";81;1
"Unit";"Marine";"Barracks";81;1
"Building";"SupplyDepot";NA;81;0
"Unit";"SCV";"Command Center";85;1
"Unit";"SCV";"Command Center";86;1
"Unit";"Marine";"Barracks";88;1
"Unit";"Marine";"Barracks";88;1
"Unit";"SCV";"Command Center";88;1
"Unit";"Marine";"Barracks";88;1
"Unit";"Medivac";"Starport";82;2
"Unit";"Marine";"Barracks";88;1
"Unit";"Medivac";"Starport";83;2
"Unit";"Marine";"Barracks";89;1
"Unit";"SCV";"Command Center";90;1
"Building";"Barracks";NA;82;0
"Building";"Barracks";NA;82;0
"Building";"SupplyDepot";NA;90;0
"Unit";"Marine";"Barracks";97;1
"Building";"SupplyDepot";NA;97;0
"Unit";"SCV";"Command Center";101;1
"Unit";"Marine";"Barracks";101;1
"Unit";"Marine";"Barracks";101;1
"Unit";"SCV";"Command Center";102;1
"Unit";"SCV";"Command Center";102;1
"Unit";"Marine";"Barracks";101;1
"Upgrade";"TerranInfantryWeaponsLevel1";"EngineeringBay";80;0
"Building";"SupplyDepot";NA;101;0
"Unit";"SCV";"Command Center";102;1
"Unit";"SCV";"Command Center";105;1
"Unit";"Medivac";"Starport";101;2
"Unit";"Medivac";"Starport";101;2
"Building";"Armory";NA;97;0
"Unit";"Marine";"Barracks";105;1
"Unit";"Marine";"Barracks";105;1
"Unit";"Marine";"Barracks";107;1
"Building";"BarracksReactor";NA;101;0
"Building";"BarracksReactor";NA;101;0
"Unit";"Marine";"Barracks";107;1
"Upgrade";"Stimpack";"TechLab";82;0
"Unit";"SCV";"Command Center";110;1
"Upgrade";"TerranInfantryArmorsLevel1";"EngineeringBay";86;0
"Unit";"Marine";"Barracks";109;1
"Unit";"Marine";"Barracks";114;1
"Unit";"Marine";"Barracks";118;1
"Unit";"Marine";"Barracks";118;1
"Unit";"Marine";"Barracks";118;1
"Unit";"Marine";"Barracks";118;1
"Unit";"Marine";"Barracks";118;1
"Unit";"Marine";"Barracks";118;1
"Unit";"SCV";"Command Center";127;1
"Unit";"SCV";"Command Center";127;1
"Unit";"SCV";"Command Center";127;1
"Unit";"Marine";"Barracks";127;1
"Unit";"Marine";"Barracks";127;1
"Unit";"Marine";"Barracks";127;1
"Unit";"Marine";"Barracks";127;1
"Unit";"Marine";"Barracks";127;1
"Unit";"Marine";"Barracks";127;1
"Unit";"Marine";"Barracks";127;1
"Unit";"Marine";"Barracks";127;1
"Unit";"SCV";"Command Center";127;1
"Unit";"SCV";"Command Center";129;1
"Unit";"SCV";"Command Center";129;1
"Unit";"Marine";"Barracks";129;1
"Building";"Refinery";NA;130;0
"Building";"Refinery";NA;133;0
"Unit";"Marine";"Barracks";142;1
"Unit";"Marine";"Barracks";142;1
"Unit";"Marine";"Barracks";142;1
"Unit";"Marine";"Barracks";142;1
"Unit";"Marine";"Barracks";142;1
"Unit";"Marine";"Barracks";142;1
"Unit";"Marine";"Barracks";142;1
"Building";"Factory";NA;139;0
"Building";"Barracks";NA;138;0
"Unit";"Medivac";"Starport";142;2
"Unit";"Marine";"Barracks";142;1
"Unit";"Marine";"Barracks";142;1
"Building";"Barracks";NA;139;0
"Unit";"Medivac";"Starport";142;2
"Unit";"Marine";"Barracks";142;1
"Unit";"SCV";"Command Center";149;1
"Unit";"Marine";"Barracks";143;1
"Unit";"SCV";"Command Center";149;1
"Unit";"Marine";"Barracks";144;1
"Unit";"Marine";"Barracks";144;1
"Unit";"Marine";"Barracks";146;1
"Unit";"Marine";"Barracks";149;1
"Unit";"Marine";"Barracks";149;1
"Unit";"SCV";"Command Center";156;1
"Unit";"Marine";"Barracks";151;1
"Unit";"Marine";"Barracks";152;1
"Unit";"Marine";"Barracks";155;1
"Unit";"Marine";"Barracks";157;1
"Unit";"Marine";"Barracks";158;1
"Upgrade";"TerranInfantryWeaponsLevel2";"EngineeringBay";127;0
"Building";"FactoryTechLab";NA;162;0
"Unit";"Marine";"Barracks";162;1
"Unit";"Marine";"Barracks";162;1
"Unit";"Marine";"Barracks";162;1
"Unit";"Marine";"Barracks";163;1
"Unit";"Medivac";"Starport";155;2
"Unit";"Medivac";"Starport";155;2
"Unit";"Marine";"Barracks";164;1
"Building";"BarracksReactor";NA;161;0
"Building";"BarracksReactor";NA;161;0
"Unit";"Marine";"Barracks";174;1
"Unit";"Marine";"Barracks";174;1
"Unit";"Marine";"Barracks";174;1
"Unit";"Marine";"Barracks";174;1
"Unit";"Marine";"Barracks";174;1
"Unit";"Marine";"Barracks";174;1
"Unit";"Marine";"Barracks";174;1
"Unit";"Marine";"Barracks";174;1
"Unit";"Marine";"Barracks";178;1
"Building";"SupplyDepot";NA;179;0
"Building";"SupplyDepot";NA;179;0
"Unit";"SCV";"Command Center";179;1
"Unit";"SCV";"Command Center";179;1
"Unit";"Marine";"Barracks";179;1
"Unit";"Marine";"Barracks";179;1
"Unit";"Marine";"Barracks";179;1
"Unit";"Medivac";"Starport";174;2
"Upgrade";"TerranVehicleWeaponsLevel1";"Armory";142;0
"Building";"Refinery";NA;179;0
"Building";"Refinery";NA;179;0
"Unit";"SCV";"Command Center";188;1
"Unit";"Marine";"Barracks";188;1
"Unit";"Marine";"Barracks";188;1
"Unit";"Marine";"Barracks";188;1
"Unit";"Marine";"Barracks";188;1
"Unit";"Marine";"Barracks";188;1
"Unit";"Marine";"Barracks";188;1
"Unit";"Marine";"Barracks";188;1
"Unit";"Marine";"Barracks";188;1
"Unit";"Marine";"Barracks";188;1
"Unit";"Marine";"Barracks";193;1
"Unit";"Marine";"Barracks";193;1
"Unit";"Marine";"Barracks";193;1
"Unit";"SCV";"Command Center";208;1
"Unit";"SCV";"Command Center";208;1
"Unit";"Marine";"Barracks";208;1
"Unit";"Marine";"Barracks";208;1
"Unit";"Marine";"Barracks";208;1
"Unit";"Marine";"Barracks";208;1
"Unit";"SCV";"Command Center";208;1
"Unit";"Marine";"Barracks";208;1
"Unit";"Marine";"Barracks";208;1
"Unit";"Marine";"Barracks";208;1
"Unit";"Marine";"Barracks";208;1
"Unit";"Marine";"Barracks";208;1
"Unit";"Marine";"Barracks";208;1
"Unit";"Marine";"Barracks";208;1
"Unit";"Marine";"Barracks";208;1
"Unit";"Marine";"Barracks";208;1
"Unit";"Marine";"Barracks";210;1
"Unit";"Marine";"Barracks";211;1
"Upgrade";"TerranInfantryArmorsLevel2";"EngineeringBay";170;0
"Unit";"Marine";"Barracks";215;1
"Unit";"Marine";"Barracks";215;1
"Unit";"Medivac";"Starport";210;2
"Unit";"Medivac";"Starport";210;2
"Unit";"Marine";"Barracks";215;1
"Unit";"Marine";"Barracks";216;1
"Unit";"Marine";"Barracks";217;1
"Unit";"Marine";"Barracks";224;1
"Unit";"Marine";"Barracks";224;1
"Unit";"Marine";"Barracks";224;1
"Unit";"Marine";"Barracks";224;1
"Unit";"Marine";"Barracks";224;1
"Unit";"Marine";"Barracks";224;1
"Unit";"Marine";"Barracks";224;1
"Unit";"Marine";"Barracks";225;1
"Building";"CommandCenter";NA;179;0
"Building";"SupplyDepot";NA;228;0
"Building";"SupplyDepot";NA;232;0
"Unit";"Marine";"Barracks";243;1
"Unit";"Marine";"Barracks";243;1
"Unit";"Marine";"Barracks";243;1
"Unit";"Marine";"Barracks";243;1
"Unit";"Marine";"Barracks";243;1
"Unit";"Marine";"Barracks";243;1
"Unit";"Marine";"Barracks";243;1
"Unit";"Marine";"Barracks";243;1
"Unit";"Marine";"Barracks";243;1
