"Type";"UnitName";"OnBuilding";"TotalSupply";"Supply"
"Unit";"SCV";"Command Center";12;1
"Unit";"SCV";"Command Center";12;1
"Unit";"SCV";"Command Center";13;1
"Building";"SupplyDepot";NA;13;0
"Unit";"SCV";"Command Center";15;1
"Unit";"SCV";"Command Center";15;1
"Building";"Refinery";NA;15;0
"Unit";"SCV";"Command Center";16;1
"Building";"Barracks";NA;15;0
"Unit";"SCV";"Command Center";17;1
"Unit";"Reaper";"Barracks";19;1
"Unit";"SCV";"Command Center";19;1
"Unit";"SCV";"Command Center";20;1
"Unit";"SCV";"Command Center";21;1
"Building";"SupplyDepot";NA;21;0
"Building";"Refinery";NA;21;0
"Building";"Barracks";NA;19;0
"Building";"BarracksReactor";NA;21;0
"Unit";"SCV";"Command Center";23;1
"Unit";"SCV";"Command Center";23;1
"Building";"BarracksTechLab";NA;23;0
"Unit";"SCV";"Command Center";24;1
"Building";"CommandCenter";NA;19;0
"Unit";"SCV";"Command Center";25;1
"Building";"Factory";NA;23;0
"Building";"SupplyDepot";NA;25;0
"Unit";"Reaper";"Barracks";25;1
"Unit";"Reaper";"Barracks";25;1
"Unit";"Reaper";"Barracks";25;1
"Unit";"SCV";"Command Center";27;1
"Unit";"SCV";"Command Center";31;1
"Unit";"SCV";"Command Center";31;1
"Unit";"Reaper";"Barracks";28;1
"Unit";"Reaper";"Barracks";29;1
"Unit";"SCV";"Command Center";31;1
"Unit";"SCV";"Command Center";32;1
"Unit";"SCV";"Command Center";35;1
"Unit";"Cyclone";"Factory";36;3
"Unit";"SCV";"Command Center";38;1
"Unit";"SCV";"Command Center";38;1
"Unit";"Marine";"Barracks";38;1
"Unit";"Marine";"Barracks";38;1
"Unit";"Marine";"Barracks";38;1
"Unit";"SCV";"Command Center";41;1
"Unit";"SCV";"Command Center";42;1
"Unit";"SCV";"Command Center";46;1
"Unit";"SCV";"Command Center";47;1
"Unit";"Marine";"Barracks";43;1
"Unit";"Marine";"Barracks";44;1
"Unit";"Marine";"Barracks";45;1
"Unit";"SCV";"Command Center";48;1
"Unit";"SCV";"Command Center";49;1
"Building";"Starport";NA;43;0
"Unit";"Marine";"Barracks";50;1
"Unit";"Marine";"Barracks";51;1
"Building";"EngineeringBay";NA;48;0
"Unit";"Marine";"Barracks";52;1
"Building";"SupplyDepot";NA;53;0
"Unit";"SCV";"Command Center";53;1
"Unit";"SCV";"Command Center";54;1
"Building";"FactoryReactor";NA;48;0
"Building";"SupplyDepot";NA;55;0
"Unit";"SCV";"Command Center";58;1
"Unit";"SCV";"Command Center";59;1
"Unit";"Marine";"Barracks";55;1
"Unit";"Marine";"Barracks";56;1
"Unit";"Marine";"Barracks";57;1
"Unit";"SCV";"Command Center";60;1
"Unit";"SCV";"Command Center";61;1
"Building";"EngineeringBay";NA;58;0
"Building";"Refinery";NA;60;0
"Building";"Refinery";NA;60;0
"Unit";"Marine";"Barracks";64;1
"Unit";"Marine";"Barracks";65;1
"Unit";"Marine";"Barracks";65;1
"Building";"FactoryTechLab";NA;65;0
"Building";"SupplyDepot";NA;65;0
"Unit";"Medivac";"Starport";65;2
"Unit";"Medivac";"Starport";65;2
"Unit";"SCV";"Command Center";70;1
"Unit";"Marine";"Barracks";70;1
"Unit";"Marine";"Barracks";70;1
"Unit";"Marine";"Barracks";70;1
"Unit";"SCV";"Command Center";75;1
"Unit";"SCV";"Command Center";75;1
"Building";"SupplyDepot";NA;70;0
"Upgrade";"Stimpack";"TechLab";55;0
"Building";"SupplyDepot";NA;75;0
"Unit";"SCV";"Command Center";80;1
"Unit";"SCV";"Command Center";80;1
"Unit";"Marine";"Barracks";80;1
"Unit";"Marine";"Barracks";80;1
"Unit";"Marine";"Barracks";80;1
"Unit";"SCV";"Command Center";80;1
"Unit";"SCV";"Command Center";81;1
"Unit";"Marine";"Barracks";82;1
"Unit";"Marine";"Barracks";83;1
"Unit";"Marine";"Barracks";84;1
"Unit";"SCV";"Command Center";85;1
"Upgrade";"TerranInfantryWeaponsLevel1";"EngineeringBay";67;0
"Unit";"SCV";"Command Center";87;1
"Unit";"SCV";"Command Center";90;1
"Unit";"Marine";"Barracks";87;1
"Unit";"Marine";"Barracks";90;1
"Unit";"Marine";"Barracks";90;1
"Unit";"SCV";"Command Center";91;1
"Unit";"SCV";"Command Center";92;1
"Unit";"SCV";"Command Center";96;1
"Unit";"Marine";"Barracks";93;1
"Unit";"Marine";"Barracks";94;1
"Unit";"Medivac";"Starport";94;2
"Unit";"Medivac";"Starport";94;2
"Building";"Barracks";NA;91;0
"Building";"Barracks";NA;91;0
"Upgrade";"TerranInfantryArmorsLevel1";"EngineeringBay";80;0
"Unit";"SCV";"Command Center";101;1
"Unit";"Marine";"Barracks";101;1
"Unit";"Marine";"Barracks";101;1
"Unit";"SCV";"Command Center";101;1
"Unit";"Marine";"Barracks";101;1
"Building";"Armory";NA;93;0
"Unit";"SCV";"Command Center";110;1
"Building";"SupplyDepot";NA;110;0
"Building";"SupplyDepot";NA;110;0
"Unit";"SCV";"Command Center";110;1
"Unit";"SCV";"Command Center";111;1
"Building";"BarracksReactor";NA;110;0
"Building";"BarracksReactor";NA;110;0
"Building";"CommandCenter";NA;101;0
"Unit";"Marine";"Barracks";113;1
"Unit";"SCV";"Command Center";113;1
"Unit";"SCV";"Command Center";113;1
"Unit";"Marine";"Barracks";113;1
"Unit";"Marine";"Barracks";113;1
"Unit";"Marine";"Barracks";113;1
"Unit";"Marine";"Barracks";113;1
"Unit";"SCV";"Command Center";114;1
"Unit";"SCV";"Command Center";115;1
"Unit";"Marine";"Barracks";114;1
"Unit";"Medivac";"Starport";113;2
"Unit";"Medivac";"Starport";113;2
"Unit";"Marine";"Barracks";120;1
"Unit";"Marine";"Barracks";120;1
"Unit";"Marine";"Barracks";120;1
"Unit";"Marine";"Barracks";120;1
"Unit";"Marine";"Barracks";120;1
"Unit";"SCV";"Command Center";120;1
"Unit";"SCV";"Command Center";121;1
"Unit";"SCV";"Command Center";132;1
"Unit";"SCV";"Command Center";132;1
"Unit";"SCV";"Command Center";133;1
"Unit";"Marine";"Barracks";127;1
"Unit";"Marine";"Barracks";127;1
"Building";"SupplyDepot";NA;127;0
"Building";"SupplyDepot";NA;127;0
"Unit";"Marine";"Barracks";127;1
"Unit";"Marine";"Barracks";128;1
"Unit";"SCV";"Command Center";134;1
"Unit";"SCV";"Command Center";135;1
"Unit";"SCV";"Command Center";136;1
"Unit";"Marine";"Barracks";137;1
"Unit";"Marine";"Barracks";137;1
"Unit";"Marine";"Barracks";137;1
"Unit";"Marine";"Barracks";137;1
"Unit";"Marine";"Barracks";138;1
"Unit";"Marine";"Barracks";139;1
"Upgrade";"TerranVehicleWeaponsLevel1";"Armory";113;0
"Building";"SensorTower";NA;141;0
"Unit";"SCV";"Command Center";144;1
"Unit";"SCV";"Command Center";144;1
"Unit";"Marine";"Barracks";144;1
"Building";"SensorTower";NA;144;0
"Upgrade";"TerranInfantryWeaponsLevel2";"EngineeringBay";113;0
"Building";"MissileTurret";NA;144;0
"Unit";"Marine";"Barracks";144;1
"Unit";"Marine";"Barracks";145;1
"Unit";"Marine";"Barracks";146;1
"Unit";"Marine";"Barracks";150;1
"Unit";"Marine";"Barracks";150;1
"Unit";"Marine";"Barracks";150;1
"Building";"Barracks";NA;134;0
"Building";"Barracks";NA;134;0
"Unit";"SCV";"Command Center";153;1
"Unit";"SCV";"Command Center";153;1
"Unit";"Marine";"Barracks";152;1
"Upgrade";"TerranInfantryArmorsLevel2";"EngineeringBay";113;0
"Building";"Refinery";NA;153;0
"Unit";"Marine";"Barracks";153;1
"Unit";"Marine";"Barracks";154;1
"Unit";"Marine";"Barracks";155;1
"Unit";"Marine";"Barracks";156;1
"Unit";"Marine";"Barracks";157;1
"Building";"BarracksTechLab";NA;161;0
"Unit";"Marine";"Barracks";162;1
"Unit";"Marine";"Barracks";162;1
"Unit";"Marine";"Barracks";162;1
"Unit";"Marine";"Barracks";163;1
"Unit";"Marine";"Barracks";164;1
"Unit";"Marine";"Barracks";165;1
"Unit";"Marine";"Barracks";166;1
"Building";"BarracksReactor";NA;161;0
"Unit";"Marine";"Barracks";167;1
"Unit";"Marine";"Barracks";167;1
"Building";"Refinery";NA;167;0
"Unit";"Marine";"Barracks";168;1
"Building";"MissileTurret";NA;169;0
"Unit";"Marine";"Barracks";169;1
"Unit";"Marine";"Barracks";170;1
"Unit";"Marine";"Barracks";171;1
"Building";"Factory";NA;162;0
"Unit";"Marine";"Barracks";172;1
"Unit";"Marine";"Barracks";174;1
"Building";"CommandCenter";NA;153;0
"Unit";"Marine";"Barracks";174;1
"Unit";"Marine";"Barracks";175;1
"Unit";"Marine";"Barracks";176;1
"Building";"SupplyDepot";NA;175;0
"Building";"SupplyDepot";NA;176;0
"Building";"SupplyDepot";NA;177;0
"Unit";"Marine";"Barracks";181;1
"Building";"FactoryTechLab";NA;181;0
"Unit";"Marine";"Barracks";182;1
"Unit";"Marine";"Barracks";182;1
"Unit";"Marine";"Barracks";182;1
"Unit";"Marine";"Barracks";182;1
"Unit";"Marine";"Barracks";184;1
"Unit";"Marine";"Barracks";184;1
"Unit";"Marine";"Barracks";184;1
"Unit";"Marine";"Barracks";190;1
"Unit";"Marine";"Barracks";190;1
"Building";"Starport";NA;182;0
"Unit";"Marine";"Barracks";193;1
"Unit";"Marine";"Barracks";193;1
"Unit";"Marine";"Barracks";193;1
"Unit";"Marine";"Barracks";193;1
"Unit";"Marine";"Barracks";195;1
"Unit";"Marine";"Barracks";195;1
"Unit";"Marine";"Barracks";195;1
"Unit";"Marine";"Barracks";195;1
"Unit";"Medivac";"Starport";193;2
"Upgrade";"TerranVehicleWeaponsLevel2";"Armory";167;0
"Building";"Starport";NA;193;0
"Building";"Starport";NA;193;0
"Building";"Starport";NA;193;0
"Building";"Starport";NA;193;0
"Unit";"Marine";"Barracks";199;1
"Unit";"Marine";"Barracks";199;1
"Unit";"Marine";"Barracks";199;1
"Unit";"Marine";"Barracks";199;1
"Building";"SupplyDepot";NA;199;0
"Building";"FusionCore";NA;193;0
"Building";"StarportReactor";NA;195;0
"Unit";"Marine";"Barracks";205;1
"Unit";"Marine";"Barracks";205;1
"Unit";"Marine";"Barracks";205;1
"Unit";"Marine";"Barracks";205;1
"Unit";"Marine";"Barracks";205;1
"Unit";"Marine";"Barracks";209;1
"Unit";"Marine";"Barracks";209;1
"Unit";"Marine";"Barracks";209;1
"Upgrade";"TerranInfantryWeaponsLevel3";"EngineeringBay";174;0
"Unit";"Marine";"Barracks";209;1
"Unit";"Marine";"Barracks";209;1
"Unit";"Marine";"Barracks";209;1
"Unit";"Marine";"Barracks";210;1
"Unit";"Marine";"Barracks";214;1
"Unit";"Marine";"Barracks";214;1
"Unit";"Marine";"Barracks";214;1
"Building";"StarportTechLab";NA;214;0
"Building";"StarportTechLab";NA;214;0
"Unit";"Marine";"Barracks";214;1
"Unit";"Marine";"Barracks";215;1
"Unit";"Marine";"Barracks";216;1
"Unit";"Marine";"Barracks";217;1
"Unit";"Marine";"Barracks";219;1
"Building";"StarportTechLab";NA;219;0
"Unit";"Marine";"Barracks";219;1
"Unit";"Marine";"Barracks";220;1
"Unit";"Marine";"Barracks";221;1
"Unit";"Marine";"Barracks";222;1
"Upgrade";"TerranInfantryArmorsLevel3";"EngineeringBay";185;0
"Unit";"Marine";"Barracks";224;1
"Unit";"Marine";"Barracks";224;1
"Building";"Refinery";NA;235;0
