"Type";"UnitName";"OnBuilding";"TotalSupply";"Supply"
"Unit";"SCV";"Command Center";12;1
"Unit";"SCV";"Command Center";12;1
"Unit";"SCV";"Command Center";13;1
"Building";"SupplyDepot";NA;13;0
"Unit";"SCV";"Command Center";15;1
"Building";"Refinery";NA;14;0
"Unit";"SCV";"Command Center";15;1
"Unit";"SCV";"Command Center";16;1
"Unit";"SCV";"Command Center";17;1
"Building";"Barracks";NA;15;0
"Unit";"Reaper";"Barracks";19;1
"Unit";"SCV";"Command Center";19;1
"Unit";"SCV";"Command Center";21;1
"Building";"Refinery";NA;21;0
"Unit";"SCV";"Command Center";22;1
"Unit";"Reaper";"Barracks";20;1
"Building";"SupplyDepot";NA;21;0
"Building";"Factory";NA;19;0
"Unit";"SCV";"Command Center";24;1
"Building";"CommandCenter";NA;19;0
"Unit";"Hellion";"Factory";24;2
"Unit";"SCV";"Command Center";24;1
"Unit";"SCV";"Command Center";27;1
"Building";"BarracksReactor";NA;24;0
"Unit";"SCV";"Command Center";28;1
"Building";"Starport";NA;25;0
"Unit";"SCV";"Command Center";29;1
"Unit";"Cyclone";"Factory";29;3
"Unit";"SCV";"Command Center";30;1
"Unit";"Marine";"Barracks";29;1
"Unit";"Marine";"Barracks";29;1
"Unit";"SCV";"Command Center";31;1
"Unit";"SCV";"Command Center";34;1
"Unit";"Medivac";"Starport";30;2
"Building";"FactoryTechLab";NA;35;0
"Unit";"Marine";"Barracks";35;1
"Unit";"Marine";"Barracks";36;1
"Unit";"SCV";"Command Center";37;1
"Building";"Bunker";NA;31;0
"Unit";"SCV";"Command Center";39;1
"Unit";"SCV";"Command Center";43;1
"Building";"EngineeringBay";NA;38;0
"Unit";"Marine";"Barracks";41;1
"Unit";"Marine";"Barracks";42;1
"Unit";"SCV";"Command Center";44;1
"Unit";"SCV";"Command Center";45;1
"Unit";"SCV";"Command Center";50;1
"Unit";"SCV";"Command Center";50;1
"Building";"SupplyDepot";NA;49;0
"Unit";"Marine";"Barracks";50;1
"Unit";"Marine";"Barracks";50;1
"Unit";"SCV";"Command Center";50;1
"Unit";"SCV";"Command Center";50;1
"Unit";"Marine";"Barracks";52;1
"Unit";"Marine";"Barracks";52;1
"Unit";"SCV";"Command Center";54;1
"Unit";"SCV";"Command Center";54;1
"Unit";"SCV";"Command Center";60;1
"Unit";"SCV";"Command Center";60;1
"Building";"Refinery";NA;60;0
"Building";"Barracks";NA;52;0
"Building";"SupplyDepot";NA;60;0
"Building";"Barracks";NA;52;0
"Unit";"SCV";"Command Center";60;1
"Unit";"SCV";"Command Center";61;1
"Building";"StarportReactor";NA;56;0
"Building";"BarracksTechLab";NA;60;0
"Unit";"SCV";"Command Center";62;1
"Unit";"SCV";"Command Center";63;1
"Building";"SupplyDepot";NA;62;0
"Unit";"Marine";"Barracks";64;1
"Unit";"Marine";"Barracks";64;1
"Unit";"Marine";"Barracks";64;1
"Unit";"SCV";"Command Center";64;1
"Unit";"SCV";"Command Center";65;1
"Building";"BarracksReactor";NA;62;0
"Unit";"SCV";"Command Center";69;1
"Unit";"SCV";"Command Center";71;1
"Unit";"Marine";"Barracks";71;1
"Unit";"Marine";"Barracks";71;1
"Unit";"Marine";"Barracks";71;1
"Upgrade";"TerranInfantryWeaponsLevel1";"EngineeringBay";56;0
"Unit";"SCV";"Command Center";72;1
"Unit";"Marine";"Barracks";72;1
"Building";"Refinery";NA;72;0
"Unit";"Marine";"Barracks";73;1
"Building";"CommandCenter";NA;62;0
"Unit";"Marine";"Barracks";77;1
"Unit";"Marine";"Barracks";77;1
"Building";"Barracks";NA;70;0
"Building";"Barracks";NA;71;0
"Building";"SupplyDepot";NA;77;0
"Unit";"SCV";"Command Center";79;1
"Unit";"SCV";"Command Center";79;1
"Building";"SupplyDepot";NA;79;0
"Unit";"Marine";"Barracks";79;1
"Unit";"Marine";"Barracks";79;1
"Unit";"Marine";"Barracks";79;1
"Unit";"SCV";"Command Center";81;1
"Unit";"Marine";"Barracks";81;1
"Unit";"Marine";"Barracks";81;1
"Unit";"SCV";"Command Center";83;1
"Unit";"Medivac";"Starport";79;2
"Unit";"Medivac";"Starport";79;2
"Building";"SupplyDepot";NA;83;0
"Unit";"Marine";"Barracks";83;1
"Unit";"Marine";"Barracks";84;1
"Building";"SupplyDepot";NA;83;0
"Unit";"SCV";"Command Center";86;1
"Unit";"SCV";"Command Center";89;1
"Unit";"SCV";"Command Center";96;1
"Unit";"Marine";"Barracks";94;1
"Unit";"Marine";"Barracks";94;1
"Building";"BarracksReactor";NA;83;0
"Building";"BarracksReactor";NA;83;0
"Building";"SensorTower";NA;97;0
"Unit";"SCV";"Command Center";98;1
"Unit";"SCV";"Command Center";98;1
"Unit";"Marine";"Barracks";98;1
"Unit";"Marine";"Barracks";98;1
"Unit";"Marine";"Barracks";98;1
"Unit";"Marine";"Barracks";101;1
"Unit";"Marine";"Barracks";101;1
"Unit";"SCV";"Command Center";101;1
"Unit";"Marine";"Barracks";101;1
"Unit";"Marine";"Barracks";101;1
"Unit";"SCV";"Command Center";106;1
"Unit";"Marine";"Barracks";101;1
"Upgrade";"Stimpack";"TechLab";79;0
"Unit";"SCV";"Command Center";108;1
"Unit";"Marine";"Barracks";106;1
"Unit";"Marine";"Barracks";106;1
"Unit";"SCV";"Command Center";113;1
"Building";"SupplyDepot";NA;106;0
"Unit";"Marine";"Barracks";107;1
"Unit";"Marine";"Barracks";107;1
"Unit";"SCV";"Command Center";113;1
"Unit";"Marine";"Barracks";113;1
"Unit";"Marine";"Barracks";113;1
"Building";"Refinery";NA;116;0
"Building";"Refinery";NA;116;0
"Unit";"Marine";"Barracks";122;1
"Unit";"Marine";"Barracks";122;1
"Building";"Factory";NA;109;0
"Unit";"Marine";"Barracks";122;1
"Unit";"Marine";"Barracks";122;1
"Unit";"Marine";"Barracks";122;1
"Unit";"Marine";"Barracks";122;1
"Unit";"Marine";"Barracks";122;1
"Unit";"Marine";"Barracks";122;1
"Unit";"SCV";"Command Center";122;1
"Unit";"Marine";"Barracks";122;1
"Unit";"SCV";"Command Center";125;1
"Unit";"SCV";"Command Center";125;1
"Unit";"Marine";"Barracks";122;1
"Unit";"Marine";"Barracks";123;1
"Unit";"Medivac";"Starport";122;2
"Unit";"Medivac";"Starport";122;2
"Unit";"Marine";"Barracks";124;1
"Unit";"Marine";"Barracks";125;1
"Unit";"Marine";"Barracks";126;1
"Unit";"Marine";"Barracks";127;1
"Unit";"Marine";"Barracks";128;1
"Building";"EngineeringBay";NA;123;0
"Building";"FactoryTechLab";NA;132;0
"Unit";"Marine";"Barracks";132;1
"Unit";"Marine";"Barracks";132;1
"Unit";"Marine";"Barracks";134;1
"Unit";"Marine";"Barracks";135;1
"Building";"SupplyDepot";NA;132;0
"Building";"SupplyDepot";NA;132;0
"Unit";"Marine";"Barracks";140;1
"Unit";"Marine";"Barracks";141;1
"Unit";"Marine";"Barracks";142;1
"Unit";"Marine";"Barracks";143;1
"Unit";"Marine";"Barracks";145;1
"Unit";"Marine";"Barracks";145;1
"Unit";"Marine";"Barracks";146;1
"Building";"Armory";NA;124;0
"Upgrade";"TerranInfantryArmorsLevel1";"EngineeringBay";116;0
"Unit";"Marine";"Barracks";147;1
"Unit";"Marine";"Barracks";148;1
"Unit";"Marine";"Barracks";149;1
"Unit";"Marine";"Barracks";150;1
"Building";"SupplyDepot";NA;150;0
"Building";"SupplyDepot";NA;153;0
"Unit";"Marine";"Barracks";156;1
"Unit";"Marine";"Barracks";156;1
"Unit";"Marauder";"Barracks";156;2
"Unit";"SCV";"Command Center";160;1
"Unit";"SCV";"Command Center";160;1
"Unit";"SCV";"Command Center";160;1
"Unit";"Medivac";"Starport";156;2
"Unit";"Medivac";"Starport";156;2
"Unit";"SCV";"Command Center";167;1
"Unit";"SCV";"Command Center";167;1
"Unit";"Marine";"Barracks";164;1
"Unit";"Marauder";"Barracks";164;2
"Unit";"SCV";"Command Center";171;1
"Unit";"Marine";"Barracks";167;1
"Unit";"SCV";"Command Center";172;1
"Unit";"Marine";"Barracks";171;1
"Unit";"Marine";"Barracks";171;1
"Unit";"Marauder";"Barracks";174;2
"Unit";"Marine";"Barracks";181;1
"Unit";"Marine";"Barracks";181;1
"Unit";"Marine";"Barracks";181;1
"Unit";"Marine";"Barracks";181;1
"Unit";"Marine";"Barracks";183;1
"Unit";"Marine";"Barracks";183;1
"Unit";"Marine";"Barracks";183;1
"Building";"SensorTower";NA;183;0
"Unit";"Marine";"Barracks";183;1
"Unit";"Marauder";"Barracks";181;2
"Building";"CommandCenter";NA;162;0
"Unit";"Marine";"Barracks";183;1
"Unit";"Marine";"Barracks";184;1
"Unit";"Marine";"Barracks";185;1
"Unit";"Marine";"Barracks";193;1
"Unit";"Marine";"Barracks";193;1
"Unit";"Marine";"Barracks";193;1
"Unit";"Marine";"Barracks";193;1
"Building";"MissileTurret";NA;196;0
"Building";"Starport";NA;193;0
"Building";"Starport";NA;193;0
"Building";"Starport";NA;193;0
"Unit";"Marine";"Barracks";200;1
"Unit";"Marine";"Barracks";200;1
"Unit";"Marine";"Barracks";200;1
"Unit";"Marine";"Barracks";200;1
"Unit";"Marine";"Barracks";200;1
"Unit";"Marine";"Barracks";200;1
"Unit";"Marine";"Barracks";200;1
"Unit";"Marine";"Barracks";200;1
"Unit";"Marauder";"Barracks";200;2
"Building";"CommandCenter";NA;183;0
"Unit";"Marine";"Barracks";200;1
"Unit";"Marine";"Barracks";201;1
"Unit";"Marine";"Barracks";202;1
"Unit";"Marine";"Barracks";203;1
"Unit";"Marine";"Barracks";210;1
"Unit";"Marine";"Barracks";210;1
"Unit";"Marauder";"Barracks";210;2
"Upgrade";"TerranInfantryArmorsLevel2";"EngineeringBay";183;0
"Upgrade";"TerranInfantryWeaponsLevel2";"EngineeringBay";186;0
"Unit";"Marine";"Barracks";218;1
"Unit";"Marine";"Barracks";218;1
"Unit";"Marine";"Barracks";218;1
"Unit";"Marine";"Barracks";218;1
"Unit";"Marine";"Barracks";218;1
"Unit";"Marauder";"Barracks";218;2
"Unit";"Marine";"Barracks";218;1
"Unit";"Marine";"Barracks";218;1
"Unit";"Marine";"Barracks";218;1
"Unit";"Marine";"Barracks";218;1
"Unit";"Marine";"Barracks";219;1
"Unit";"Marine";"Barracks";227;1
"Unit";"Marine";"Barracks";227;1
"Unit";"Marauder";"Barracks";227;2
"Upgrade";"TerranShipWeaponsLevel1";"Armory";200;0
"Unit";"Marine";"Barracks";228;1
"Unit";"Marine";"Barracks";230;1
"Unit";"Marine";"Barracks";230;1
"Unit";"Marine";"Barracks";234;1
"Unit";"Liberator";"Starport";228;3
"Unit";"Liberator";"Starport";228;3
"Unit";"Liberator";"Starport";228;3
"Unit";"Marine";"Barracks";235;1
"Unit";"Marine";"Barracks";235;1
"Unit";"Liberator";"Starport";228;3
"Unit";"Liberator";"Starport";228;3
"Unit";"Marauder";"Barracks";235;2
"Unit";"Marine";"Barracks";238;1
"Unit";"Marine";"Barracks";238;1
"Unit";"Marine";"Barracks";255;1
"Unit";"Marine";"Barracks";255;1
"Unit";"Marine";"Barracks";255;1
"Unit";"Marine";"Barracks";257;1
"Unit";"Marauder";"Barracks";257;2
"Unit";"Marine";"Barracks";257;1
"Unit";"Marine";"Barracks";258;1
"Unit";"Marine";"Barracks";259;1
"Unit";"Liberator";"Starport";244;3
"Unit";"Marauder";"Barracks";263;2
"Unit";"Medivac";"Starport";259;2
"Unit";"Medivac";"Starport";259;2
"Unit";"Marine";"Barracks";267;1
"Unit";"Marine";"Barracks";267;1
"Unit";"Marine";"Barracks";267;1
"Unit";"Marine";"Barracks";267;1
"Unit";"SCV";"Command Center";271;1
"Unit";"SCV";"Command Center";271;1
"Unit";"SCV";"Command Center";271;1
"Unit";"Marine";"Barracks";277;1
"Unit";"Marine";"Barracks";277;1
"Unit";"Marauder";"Barracks";271;2
"Unit";"Marine";"Barracks";277;1
"Building";"FactoryTechLab";NA;280;0
"Unit";"SCV";"Command Center";281;1
"Unit";"SCV";"Command Center";284;1
"Unit";"Marine";"Barracks";284;1
"Unit";"Marine";"Barracks";284;1
"Unit";"Liberator";"Starport";268;3
"Unit";"Marine";"Barracks";284;1
"Unit";"Marine";"Barracks";284;1
"Unit";"Marine";"Barracks";289;1
"Unit";"Marine";"Barracks";289;1
"Unit";"Marine";"Barracks";290;1
"Unit";"Marine";"Barracks";299;1
"Unit";"Marine";"Barracks";301;1
"Unit";"SCV";"Command Center";301;1
"Unit";"SCV";"Command Center";301;1
"Unit";"SCV";"Command Center";301;1
"Unit";"Marine";"Barracks";301;1
"Unit";"Marine";"Barracks";301;1
"Unit";"Marine";"Barracks";301;1
"Unit";"Liberator";"Starport";290;3
"Unit";"Marine";"Barracks";301;1
"Unit";"Marauder";"Barracks";301;2
