"type";"unit_name";"on_building";"total_supply_lag"
"Unit";"Overlord";"Larva";13
"Building";"SpawningPool";NA;17
"Building";"Hatchery";NA;19
"Building";"Extractor";NA;20
"Unit";"Zergling";"Larva";20
"Unit";"Zergling";"Larva";21
"Unit";"Zergling";"Larva";22
"Unit";"Zergling";"Larva";23
"Unit";"Queen";"Hatchery";24
"Unit";"Overlord";"Larva";27
"Unit";"Queen";"Hatchery";28
"Unit";"Queen";"Hatchery";32
"Building";"CreepTumorQueen";NA;39
"Building";"Hatchery";NA;41
"Unit";"Overlord";"Larva";41
"Unit";"Overlord";"Larva";42
"Building";"CreepTumorQueen";NA;42
"Unit";"Overlord";"Larva";42
"Building";"CreepTumor";NA;42
"Unit";"Queen";"Hatchery";48
"Unit";"Overlord";"Larva";52
"Unit";"Zergling";"Larva";52
"Unit";"Zergling";"Larva";53
"Unit";"Zergling";"Larva";54
"Unit";"Zergling";"Larva";55
"Unit";"Zergling";"Larva";56
"Unit";"Zergling";"Larva";57
"Building";"CreepTumor";NA;58
"Building";"CreepTumor";NA;58
"Unit";"Zergling";"Larva";58
"Unit";"Zergling";"Larva";59
"Building";"CreepTumorQueen";NA;60
"Unit";"Queen";"Hatchery";68
"Building";"Extractor";NA;70
"Building";"EvolutionChamber";NA;70
"Building";"CreepTumor";NA;70
"Building";"EvolutionChamber";NA;70
"Building";"CreepTumor";NA;70
"Unit";"Queen";"Hatchery";70
"Unit";"Overlord";"Larva";75
"Unit";"Zergling";"Larva";75
"Unit";"Zergling";"Larva";76
"Unit";"Zergling";"Larva";77
"Unit";"Zergling";"Larva";78
"Unit";"Zergling";"Larva";79
"Unit";"Zergling";"Larva";80
"Unit";"Zergling";"Larva";81
"Unit";"Zergling";"Larva";82
"Unit";"Zergling";"Larva";83
"Unit";"Zergling";"Larva";84
"Unit";"Zergling";"Larva";85
"Unit";"Zergling";"Larva";86
"Unit";"Zergling";"Larva";87
"Unit";"Zergling";"Larva";88
"Unit";"Zergling";"Larva";89
"Unit";"Zergling";"Larva";90
"Unit";"Zergling";"Larva";91
"Unit";"Zergling";"Larva";92
"Unit";"Zergling";"Larva";93
"Unit";"Zergling";"Larva";94
"Unit";"Zergling";"Larva";95
"Unit";"Zergling";"Larva";96
"Unit";"Zergling";"Larva";97
"Unit";"Zergling";"Larva";98
"Unit";"Zergling";"Larva";99
"Unit";"Zergling";"Larva";100
"Unit";"Zergling";"Larva";101
"Unit";"Zergling";"Larva";102
"Unit";"Overlord";"Larva";106
"Building";"SporeCrawler";NA;106
"Unit";"Overlord";"Larva";106
"Building";"CreepTumorQueen";NA;106
"Building";"CreepTumorQueen";NA;106
"Building";"CreepTumor";NA;106
"Building";"SporeCrawler";NA;107
"Building";"SporeCrawler";NA;107
"Unit";"Zergling";"Larva";107
"Unit";"Zergling";"Larva";108
"Unit";"Zergling";"Larva";109
"Unit";"Zergling";"Larva";110
"Building";"Extractor";NA;115
"Building";"BanelingNest";NA;116
"Building";"Extractor";NA;116
"Unit";"Zergling";"Larva";125
"Unit";"Zergling";"Larva";126
"Unit";"Zergling";"Larva";127
"Unit";"Zergling";"Larva";128
"Unit";"Queen";"Hatchery";129
"Unit";"Zergling";"Larva";131
"Unit";"Zergling";"Larva";132
"Unit";"Zergling";"Larva";133
"Unit";"Zergling";"Larva";134
"Unit";"Zergling";"Larva";135
"Unit";"Zergling";"Larva";136
"Unit";"Zergling";"Larva";137
"Unit";"Zergling";"Larva";138
"Unit";"Zergling";"Larva";139
"Unit";"Zergling";"Larva";140
"Unit";"Zergling";"Larva";141
"Unit";"Zergling";"Larva";142
"Unit";"Zergling";"Larva";143
"Unit";"Zergling";"Larva";144
"Unit";"Zergling";"Larva";145
"Unit";"Zergling";"Larva";146
"Unit";"Zergling";"Larva";147
"Unit";"Zergling";"Larva";148
"Unit";"Zergling";"Larva";149
"Unit";"Zergling";"Larva";150
"Unit";"Zergling";"Larva";151
"Unit";"Zergling";"Larva";152
"Unit";"Zergling";"Larva";153
"Unit";"Zergling";"Larva";154
"Unit";"Zergling";"Larva";155
"Unit";"Zergling";"Larva";156
"Unit";"Baneling";"Zergling";157
"Unit";"Baneling";"Zergling";157
"Unit";"Baneling";"Zergling";157
"Unit";"Baneling";"Zergling";157
"Unit";"Baneling";"Zergling";157
"Building";"CreepTumor";NA;165
"Building";"CreepTumor";NA;165
"Building";"HydraliskDen";NA;165
"Building";"Extractor";NA;169
"Unit";"Overlord";"Larva";169
"Building";"Extractor";NA;169
"Unit";"Zergling";"Larva";169
"Unit";"Zergling";"Larva";170
"Unit";"Zergling";"Larva";171
"Unit";"Zergling";"Larva";172
"Unit";"Zergling";"Larva";173
"Unit";"Zergling";"Larva";174
"Unit";"Zergling";"Larva";175
"Unit";"Zergling";"Larva";176
"Unit";"Zergling";"Larva";177
"Unit";"Zergling";"Larva";178
"Unit";"Zergling";"Larva";179
"Unit";"Zergling";"Larva";180
"Unit";"Queen";"Hatchery";181
"Building";"CreepTumorQueen";NA;183
"Unit";"Queen";"Hatchery";183
"Building";"CreepTumorQueen";NA;185
"Unit";"Overlord";"Larva";185
"Unit";"Overlord";"Larva";185
"Unit";"Hydralisk";"Larva";185
"Unit";"Hydralisk";"Larva";187
"Unit";"Hydralisk";"Larva";189
"Building";"CreepTumor";NA;191
"Building";"CreepTumor";NA;191
"Unit";"Baneling";"Zergling";191
"Unit";"Baneling";"Zergling";191
"Unit";"Baneling";"Zergling";191
"Unit";"Baneling";"Zergling";191
"Unit";"Zergling";"Larva";191
"Unit";"Zergling";"Larva";192
"Unit";"Zergling";"Larva";193
"Unit";"Zergling";"Larva";194
"Unit";"Zergling";"Larva";195
"Unit";"Zergling";"Larva";196
"Unit";"Zergling";"Larva";197
"Unit";"Zergling";"Larva";198
"Unit";"Zergling";"Larva";199
"Unit";"Zergling";"Larva";200
"Unit";"Zergling";"Larva";201
"Unit";"Zergling";"Larva";202
"Unit";"Zergling";"Larva";203
"Unit";"Zergling";"Larva";204
"Unit";"Zergling";"Larva";205
"Unit";"Zergling";"Larva";206
"Unit";"Zergling";"Larva";207
"Unit";"Zergling";"Larva";208
"Unit";"Zergling";"Larva";209
"Unit";"Zergling";"Larva";210
"Unit";"Zergling";"Larva";211
"Unit";"Zergling";"Larva";212
"Unit";"Zergling";"Larva";213
"Unit";"Zergling";"Larva";214
"Unit";"Hydralisk";"Larva";215
"Unit";"Hydralisk";"Larva";217
"Unit";"Zergling";"Larva";219
"Unit";"Zergling";"Larva";220
"Building";"CreepTumorQueen";NA;221
"Building";"CreepTumorQueen";NA;221
"Building";"CreepTumorQueen";NA;221
"Building";"Hatchery";NA;221
"Building";"Hatchery";NA;221
"Building";"CreepTumor";NA;227
"Building";"CreepTumor";NA;227
"Unit";"Hydralisk";"Larva";228
"Unit";"Hydralisk";"Larva";230
"Unit";"Hydralisk";"Larva";232
"Unit";"Baneling";"Zergling";234
"Unit";"Baneling";"Zergling";234
"Unit";"Baneling";"Zergling";234
"Unit";"Baneling";"Zergling";234
"Unit";"Baneling";"Zergling";234
"Building";"CreepTumor";NA;234
"Unit";"Hydralisk";"Larva";234
"Unit";"Hydralisk";"Larva";236
"Building";"CreepTumor";NA;238
"Building";"CreepTumor";NA;238
"Unit";"Baneling";"Zergling";238
"Unit";"Baneling";"Zergling";238
"Unit";"Baneling";"Zergling";238
"Unit";"Baneling";"Zergling";238
"Unit";"Hydralisk";"Larva";238
"Unit";"Zergling";"Larva";240
"Unit";"Zergling";"Larva";241
"Unit";"Hydralisk";"Larva";242
"Unit";"Hydralisk";"Larva";244
"Unit";"Hydralisk";"Larva";247
"Unit";"Baneling";"Zergling";249
"Unit";"Baneling";"Zergling";249
"Unit";"Baneling";"Zergling";249
"Unit";"Zergling";"Larva";249
"Unit";"Zergling";"Larva";250
"Unit";"Zergling";"Larva";251
"Unit";"Zergling";"Larva";252
"Unit";"Zergling";"Larva";253
"Unit";"Zergling";"Larva";254
"Unit";"Zergling";"Larva";255
"Unit";"Zergling";"Larva";256
"Unit";"Zergling";"Larva";257
"Unit";"Zergling";"Larva";258
"Unit";"Zergling";"Larva";259
"Unit";"Zergling";"Larva";260
"Unit";"Zergling";"Larva";261
"Unit";"Zergling";"Larva";262
"Unit";"Zergling";"Larva";263
"Unit";"Zergling";"Larva";264
"Unit";"Hydralisk";"Larva";265
"Unit";"Hydralisk";"Larva";267
"Unit";"Zergling";"Larva";269
"Unit";"Zergling";"Larva";270
"Unit";"Hydralisk";"Larva";271
"Unit";"Hydralisk";"Larva";273
"Unit";"Hydralisk";"Larva";275
"Unit";"Zergling";"Larva";277
"Unit";"Zergling";"Larva";278
"Unit";"Overlord";"Larva";279
"Unit";"Overlord";"Larva";279
"Unit";"Overlord";"Larva";279
"Building";"CreepTumorQueen";NA;279
"Unit";"Overlord";"Larva";279
"Unit";"Overlord";"Larva";279
"Unit";"Zergling";"Larva";279
"Unit";"Zergling";"Larva";280
"Building";"CreepTumorQueen";NA;281
"Building";"CreepTumorQueen";NA;281
"Building";"CreepTumor";NA;281
"Building";"CreepTumor";NA;281
"Unit";"Zergling";"Larva";281
"Unit";"Zergling";"Larva";282
"Unit";"Zergling";"Larva";283
"Unit";"Zergling";"Larva";284
"Unit";"Zergling";"Larva";285
"Unit";"Zergling";"Larva";286
"Unit";"Zergling";"Larva";287
"Unit";"Zergling";"Larva";288
"Unit";"Zergling";"Larva";289
"Unit";"Zergling";"Larva";290
"Unit";"Zergling";"Larva";291
"Unit";"Zergling";"Larva";292
"Unit";"Zergling";"Larva";293
"Unit";"Zergling";"Larva";294
"Unit";"Zergling";"Larva";295
"Unit";"Zergling";"Larva";296
"Unit";"Zergling";"Larva";297
"Unit";"Zergling";"Larva";298
"Unit";"Zergling";"Larva";299
"Unit";"Zergling";"Larva";300
"Building";"CreepTumorQueen";NA;301
"Unit";"Hydralisk";"Larva";301
"Unit";"Hydralisk";"Larva";303
"Unit";"Hydralisk";"Larva";305
"Building";"InfestationPit";NA;307
"Unit";"Zergling";"Larva";307
"Unit";"Zergling";"Larva";308
"Unit";"Zergling";"Larva";309
"Unit";"Zergling";"Larva";310
"Unit";"Zergling";"Larva";311
"Unit";"Zergling";"Larva";312
"Unit";"Zergling";"Larva";313
"Unit";"Zergling";"Larva";314
"Unit";"Zergling";"Larva";315
"Unit";"Zergling";"Larva";316
"Unit";"Zergling";"Larva";317
"Unit";"Zergling";"Larva";318
"Unit";"Zergling";"Larva";319
"Unit";"Zergling";"Larva";320
"Building";"CreepTumor";NA;321
"Building";"CreepTumor";NA;321
"Unit";"Baneling";"Zergling";321
"Unit";"Baneling";"Zergling";321
"Unit";"Baneling";"Zergling";321
"Unit";"Baneling";"Zergling";321
"Unit";"Zergling";"Larva";321
"Unit";"Zergling";"Larva";322
"Unit";"Zergling";"Larva";323
"Unit";"Zergling";"Larva";324
"Unit";"Zergling";"Larva";325
"Unit";"Zergling";"Larva";326
"Unit";"Zergling";"Larva";327
"Unit";"Zergling";"Larva";328
"Unit";"Zergling";"Larva";329
"Unit";"Zergling";"Larva";330
"Unit";"Zergling";"Larva";331
"Unit";"Zergling";"Larva";332
"Unit";"Zergling";"Larva";333
"Unit";"Zergling";"Larva";334
"Unit";"Zergling";"Larva";335
"Unit";"Zergling";"Larva";336
"Unit";"Zergling";"Larva";337
"Unit";"Zergling";"Larva";338
"Unit";"Zergling";"Larva";339
"Unit";"Zergling";"Larva";340
"Unit";"Baneling";"Zergling";341
"Unit";"Baneling";"Zergling";341
"Unit";"Hydralisk";"Larva";341
"Unit";"Hydralisk";"Larva";343
"Unit";"Hydralisk";"Larva";345
"Unit";"Hydralisk";"Larva";347
"Unit";"Baneling";"Zergling";349
"Unit";"Baneling";"Zergling";349
"Unit";"Baneling";"Zergling";349
"Unit";"Baneling";"Zergling";349
"Unit";"Baneling";"Zergling";349
"Unit";"Baneling";"Zergling";349
"Unit";"Baneling";"Zergling";349
"Unit";"Hydralisk";"Larva";349
"Unit";"Hydralisk";"Larva";351
"Unit";"Hydralisk";"Larva";353
"Unit";"Zergling";"Larva";355
"Unit";"Zergling";"Larva";356
"Building";"CreepTumorQueen";NA;357
"Unit";"Overlord";"Larva";357
"Unit";"Overlord";"Larva";357
"Unit";"Overlord";"Larva";357
"Unit";"Overlord";"Larva";357
"Building";"CreepTumor";NA;357
"Unit";"Baneling";"Zergling";357
"Unit";"Baneling";"Zergling";357
"Unit";"Baneling";"Zergling";357
"Unit";"Baneling";"Zergling";357
"Unit";"Baneling";"Zergling";357
"Unit";"Baneling";"Zergling";357
"Unit";"Zergling";"Larva";357
"Unit";"Zergling";"Larva";358
"Unit";"Zergling";"Larva";359
"Unit";"Zergling";"Larva";360
"Unit";"Zergling";"Larva";361
"Unit";"Zergling";"Larva";362
"Unit";"Baneling";"Zergling";363
"Unit";"Baneling";"Zergling";363
"Unit";"Baneling";"Zergling";363
"Unit";"Baneling";"Zergling";363
"Unit";"Baneling";"Zergling";363
"Unit";"Zergling";"Larva";363
"Unit";"Zergling";"Larva";364
"Unit";"Zergling";"Larva";365
"Unit";"Zergling";"Larva";366
"Unit";"Zergling";"Larva";367
"Unit";"Zergling";"Larva";368
"Unit";"Zergling";"Larva";369
"Unit";"Zergling";"Larva";370
"Unit";"Baneling";"Zergling";371
"Unit";"Baneling";"Zergling";371
"Unit";"Baneling";"Zergling";371
"Unit";"Baneling";"Zergling";371
"Unit";"Baneling";"Zergling";371
"Unit";"Baneling";"Zergling";371
"Unit";"Zergling";"Larva";371
"Unit";"Zergling";"Larva";372
"Unit";"Zergling";"Larva";373
"Unit";"Zergling";"Larva";374
"Unit";"Zergling";"Larva";375
"Unit";"Zergling";"Larva";376
"Unit";"Zergling";"Larva";377
"Unit";"Zergling";"Larva";378
"Unit";"Zergling";"Larva";379
"Unit";"Zergling";"Larva";380
"Unit";"Zergling";"Larva";381
"Unit";"Zergling";"Larva";382
"Unit";"Hydralisk";"Larva";383
"Unit";"Hydralisk";"Larva";385
"Unit";"Hydralisk";"Larva";387
"Unit";"Hydralisk";"Larva";389
"Unit";"Zergling";"Larva";391
"Unit";"Zergling";"Larva";392
"Unit";"Zergling";"Larva";393
"Unit";"Zergling";"Larva";394
"Unit";"Hydralisk";"Larva";395
"Unit";"Hydralisk";"Larva";397
"Unit";"Hydralisk";"Larva";399
"Unit";"Hydralisk";"Larva";401
"Unit";"Zergling";"Larva";403
"Unit";"Zergling";"Larva";404
"Unit";"Zergling";"Larva";405
"Unit";"Zergling";"Larva";406
"Unit";"Hydralisk";"Larva";407
"Unit";"Hydralisk";"Larva";409
"Unit";"Hydralisk";"Larva";411
"Unit";"Zergling";"Larva";413
"Unit";"Zergling";"Larva";414
"Unit";"Zergling";"Larva";415
"Unit";"Zergling";"Larva";416
"Unit";"Zergling";"Larva";417
"Unit";"Zergling";"Larva";418
"Unit";"Zergling";"Larva";419
"Unit";"Zergling";"Larva";420
"Unit";"Zergling";"Larva";421
"Unit";"Zergling";"Larva";422
"Unit";"Zergling";"Larva";423
"Unit";"Zergling";"Larva";424
"Unit";"Zergling";"Larva";425
"Unit";"Zergling";"Larva";426
"Building";"CreepTumorQueen";NA;427
"Unit";"Zergling";"Larva";427
"Unit";"Zergling";"Larva";428
"Unit";"Zergling";"Larva";429
"Unit";"Zergling";"Larva";430
"Unit";"Zergling";"Larva";431
"Unit";"Zergling";"Larva";432
"Unit";"Hydralisk";"Larva";433
"Unit";"Hydralisk";"Larva";435
"Unit";"Hydralisk";"Larva";437
"Unit";"Hydralisk";"Larva";439
"Unit";"Hydralisk";"Larva";441
"Unit";"Hydralisk";"Larva";443
"Unit";"Hydralisk";"Larva";445
"Unit";"Zergling";"Larva";447
"Unit";"Zergling";"Larva";448
"Unit";"Zergling";"Larva";449
"Unit";"Zergling";"Larva";450
"Unit";"Zergling";"Larva";451
"Unit";"Zergling";"Larva";452
"Unit";"Zergling";"Larva";453
"Unit";"Zergling";"Larva";454
"Unit";"Zergling";"Larva";455
"Unit";"Zergling";"Larva";456
"Unit";"Baneling";"Zergling";457
"Unit";"Baneling";"Zergling";457
"Unit";"Baneling";"Zergling";457
"Unit";"Baneling";"Zergling";457
"Unit";"Baneling";"Zergling";457
"Unit";"Baneling";"Zergling";457
"Unit";"Baneling";"Zergling";457
"Unit";"Baneling";"Zergling";457
"Unit";"Baneling";"Zergling";457
"Building";"Hatchery";NA;457
"Unit";"Zergling";"Larva";457
"Unit";"Zergling";"Larva";458
"Unit";"Zergling";"Larva";459
"Unit";"Zergling";"Larva";460
"Unit";"Zergling";"Larva";461
"Unit";"Zergling";"Larva";462
"Building";"CreepTumor";NA;463
"Unit";"Hydralisk";"Larva";463
"Unit";"Hydralisk";"Larva";465
"Unit";"Hydralisk";"Larva";467
"Unit";"Zergling";"Larva";469
"Unit";"Zergling";"Larva";470
"Unit";"Zergling";"Larva";471
"Unit";"Zergling";"Larva";472
"Unit";"Baneling";"Zergling";478
"Unit";"Baneling";"Zergling";478
"Unit";"Baneling";"Zergling";478
"Unit";"Baneling";"Zergling";478
"Unit";"Baneling";"Zergling";478
"Unit";"Baneling";"Zergling";478
"Unit";"Baneling";"Zergling";478
"Unit";"Zergling";"Larva";478
"Unit";"Zergling";"Larva";479
"Unit";"Zergling";"Larva";480
"Unit";"Zergling";"Larva";481
"Unit";"Zergling";"Larva";482
"Unit";"Zergling";"Larva";483
"Unit";"Zergling";"Larva";484
"Unit";"Zergling";"Larva";485
"Unit";"Zergling";"Larva";486
"Unit";"Zergling";"Larva";487
"Unit";"Zergling";"Larva";488
"Unit";"Zergling";"Larva";489
"Unit";"Zergling";"Larva";490
"Unit";"Zergling";"Larva";491
"Unit";"Zergling";"Larva";492
"Unit";"Zergling";"Larva";493
"Unit";"Zergling";"Larva";494
"Unit";"Zergling";"Larva";495
"Unit";"Zergling";"Larva";496
"Unit";"Zergling";"Larva";497
"Unit";"Zergling";"Larva";498
"Unit";"Zergling";"Larva";499
"Unit";"Zergling";"Larva";500
"Unit";"Zergling";"Larva";501
"Unit";"Zergling";"Larva";502
"Unit";"Zergling";"Larva";503
"Unit";"Hydralisk";"Larva";504
"Unit";"Hydralisk";"Larva";506
"Unit";"Hydralisk";"Larva";508
"Unit";"Hydralisk";"Larva";510
"Unit";"Hydralisk";"Larva";512
"Unit";"Zergling";"Larva";514
"Unit";"Zergling";"Larva";515
"Unit";"Zergling";"Larva";516
"Unit";"Zergling";"Larva";517
"Unit";"Hydralisk";"Larva";518
"Unit";"Hydralisk";"Larva";520
"Unit";"Hydralisk";"Larva";522
"Unit";"Zergling";"Larva";524
"Unit";"Zergling";"Larva";525
"Unit";"Zergling";"Larva";526
"Unit";"Zergling";"Larva";527
"Unit";"Zergling";"Larva";528
"Unit";"Zergling";"Larva";529
"Unit";"Zergling";"Larva";530
"Unit";"Zergling";"Larva";531
"Unit";"Baneling";"Zergling";532
"Unit";"Baneling";"Zergling";532
"Unit";"Baneling";"Zergling";532
"Unit";"Baneling";"Zergling";532
"Unit";"Baneling";"Zergling";532
"Unit";"Hydralisk";"Larva";532
"Unit";"Hydralisk";"Larva";534
"Unit";"Hydralisk";"Larva";536
"Unit";"Zergling";"Larva";538
"Unit";"Zergling";"Larva";539
"Unit";"Zergling";"Larva";540
"Unit";"Zergling";"Larva";541
"Unit";"Zergling";"Larva";542
"Unit";"Zergling";"Larva";543
"Unit";"Zergling";"Larva";544
"Unit";"Zergling";"Larva";545
"Unit";"Zergling";"Larva";546
"Unit";"Zergling";"Larva";547
"Unit";"Zergling";"Larva";548
"Unit";"Zergling";"Larva";549
"Unit";"Zergling";"Larva";550
"Unit";"Zergling";"Larva";551
"Unit";"Zergling";"Larva";552
"Unit";"Zergling";"Larva";553
"Unit";"Zergling";"Larva";554
"Unit";"Zergling";"Larva";555
"Unit";"Baneling";"Zergling";556
"Unit";"Baneling";"Zergling";556
"Unit";"Baneling";"Zergling";556
"Unit";"Hydralisk";"Larva";556
"Unit";"Hydralisk";"Larva";558
"Unit";"Hydralisk";"Larva";560
"Unit";"Hydralisk";"Larva";562
"Unit";"Zergling";"Larva";564
"Unit";"Zergling";"Larva";565
"Unit";"Overlord";"Larva";566
"Building";"SpineCrawler";NA;566
"Unit";"Zergling";"Larva";570
"Unit";"Zergling";"Larva";571
"Unit";"Zergling";"Larva";572
"Unit";"Zergling";"Larva";573
"Unit";"Zergling";"Larva";574
"Unit";"Zergling";"Larva";575
"Unit";"Zergling";"Larva";576
"Unit";"Zergling";"Larva";577
"Unit";"Zergling";"Larva";578
"Unit";"Zergling";"Larva";579
"Unit";"Zergling";"Larva";580
"Unit";"Zergling";"Larva";581
"Unit";"Baneling";"Zergling";582
"Unit";"Baneling";"Zergling";582
"Unit";"Baneling";"Zergling";582
"Unit";"Baneling";"Zergling";582
"Unit";"Baneling";"Zergling";582
"Unit";"Baneling";"Zergling";582
"Unit";"Baneling";"Zergling";582
"Unit";"Baneling";"Zergling";582
"Unit";"Baneling";"Zergling";582
"Unit";"Hydralisk";"Larva";582
"Unit";"Hydralisk";"Larva";584
"Unit";"Hydralisk";"Larva";586
"Unit";"Hydralisk";"Larva";588
"Unit";"Hydralisk";"Larva";590
"Unit";"Zergling";"Larva";592
"Unit";"Zergling";"Larva";593
"Unit";"Zergling";"Larva";594
"Unit";"Zergling";"Larva";595
"Unit";"Baneling";"Zergling";596
"Unit";"Baneling";"Zergling";596
"Unit";"Baneling";"Zergling";596
"Unit";"Baneling";"Zergling";596
"Unit";"Zergling";"Larva";596
"Unit";"Zergling";"Larva";597
"Unit";"Zergling";"Larva";598
"Unit";"Zergling";"Larva";599
"Unit";"Zergling";"Larva";600
"Unit";"Zergling";"Larva";601
"Unit";"Zergling";"Larva";602
"Unit";"Zergling";"Larva";603
"Unit";"Zergling";"Larva";604
"Unit";"Zergling";"Larva";605
"Unit";"Zergling";"Larva";606
"Unit";"Zergling";"Larva";607
"Unit";"Zergling";"Larva";608
"Unit";"Zergling";"Larva";609
"Unit";"Zergling";"Larva";610
"Unit";"Zergling";"Larva";611
"Unit";"Zergling";"Larva";612
"Unit";"Zergling";"Larva";613
"Unit";"Zergling";"Larva";614
"Unit";"Zergling";"Larva";615
"Unit";"Zergling";"Larva";616
"Unit";"Zergling";"Larva";617
"Unit";"Zergling";"Larva";624
"Unit";"Zergling";"Larva";625
"Building";"Hatchery";NA;626
"Unit";"Zergling";"Larva";626
"Unit";"Zergling";"Larva";627
"Unit";"Zergling";"Larva";628
"Unit";"Zergling";"Larva";629
"Unit";"Zergling";"Larva";630
"Unit";"Zergling";"Larva";631
"Unit";"Zergling";"Larva";632
"Unit";"Zergling";"Larva";633
"Unit";"Zergling";"Larva";634
"Unit";"Zergling";"Larva";635
"Unit";"Zergling";"Larva";636
"Unit";"Zergling";"Larva";637
"Unit";"Zergling";"Larva";638
"Unit";"Zergling";"Larva";639
"Unit";"Baneling";"Zergling";640
"Unit";"Baneling";"Zergling";640
"Unit";"Baneling";"Zergling";640
"Unit";"Baneling";"Zergling";640
"Unit";"Zergling";"Larva";640
"Unit";"Zergling";"Larva";641
"Unit";"Zergling";"Larva";642
"Unit";"Zergling";"Larva";643
"Unit";"Hydralisk";"Larva";644
"Unit";"Hydralisk";"Larva";646
"Unit";"Hydralisk";"Larva";648
"Unit";"Hydralisk";"Larva";650
"Unit";"Hydralisk";"Larva";652
"Unit";"Zergling";"Larva";654
"Unit";"Zergling";"Larva";655
"Unit";"Zergling";"Larva";656
"Unit";"Zergling";"Larva";657
"Unit";"Zergling";"Larva";658
"Unit";"Zergling";"Larva";659
"Unit";"Zergling";"Larva";660
"Unit";"Zergling";"Larva";661
"Unit";"Zergling";"Larva";662
"Unit";"Zergling";"Larva";663
"Building";"CreepTumor";NA;664
"Unit";"Baneling";"Zergling";664
"Unit";"Baneling";"Zergling";664
"Unit";"Baneling";"Zergling";664
"Unit";"Baneling";"Zergling";664
"Unit";"Baneling";"Zergling";664
"Unit";"Baneling";"Zergling";664
"Unit";"Baneling";"Zergling";664
"Building";"Hatchery";NA;664
"Building";"Extractor";NA;664
"Unit";"Zergling";"Larva";671
"Unit";"Zergling";"Larva";672
"Unit";"Zergling";"Larva";673
"Unit";"Zergling";"Larva";674
"Unit";"Zergling";"Larva";675
"Unit";"Zergling";"Larva";676
"Unit";"Zergling";"Larva";677
"Unit";"Zergling";"Larva";678
"Unit";"Zergling";"Larva";679
"Unit";"Zergling";"Larva";680
"Unit";"Zergling";"Larva";681
"Unit";"Zergling";"Larva";682
"Unit";"Zergling";"Larva";683
"Unit";"Zergling";"Larva";684
"Unit";"Overlord";"Larva";685
"Unit";"Overlord";"Larva";685
"Building";"CreepTumor";NA;685
"Unit";"Baneling";"Zergling";685
"Unit";"Baneling";"Zergling";685
"Unit";"Baneling";"Zergling";685
"Unit";"Baneling";"Zergling";685
"Unit";"Baneling";"Zergling";685
"Unit";"Baneling";"Zergling";685
"Unit";"Baneling";"Zergling";685
"Unit";"Baneling";"Zergling";685
"Unit";"Baneling";"Zergling";685
"Unit";"Baneling";"Zergling";685
"Unit";"Baneling";"Zergling";685
"Unit";"Baneling";"Zergling";685
"Building";"CreepTumor";NA;685
"Building";"Extractor";NA;685
"Building";"Extractor";NA;688
"Building";"CreepTumorQueen";NA;689
"Building";"CreepTumorQueen";NA;689
"Building";"CreepTumorQueen";NA;689
"Unit";"Baneling";"Zergling";689
"Unit";"Baneling";"Zergling";689
"Unit";"Baneling";"Zergling";689
"Unit";"Baneling";"Zergling";689
"Unit";"Baneling";"Zergling";689
"Unit";"Baneling";"Zergling";689
"Building";"Extractor";NA;689
"Unit";"Zergling";"Larva";689
"Unit";"Zergling";"Larva";690
"Unit";"Zergling";"Larva";691
"Unit";"Zergling";"Larva";692
"Unit";"Zergling";"Larva";693
"Unit";"Zergling";"Larva";694
"Unit";"Zergling";"Larva";695
"Unit";"Zergling";"Larva";696
"Unit";"Zergling";"Larva";697
"Unit";"Zergling";"Larva";698
"Unit";"Zergling";"Larva";699
"Unit";"Zergling";"Larva";700
"Unit";"Zergling";"Larva";701
"Unit";"Zergling";"Larva";702
"Unit";"Zergling";"Larva";703
"Unit";"Zergling";"Larva";704
"Unit";"Zergling";"Larva";705
"Unit";"Zergling";"Larva";706
"Unit";"Zergling";"Larva";707
"Unit";"Zergling";"Larva";708
"Unit";"Zergling";"Larva";709
"Unit";"Zergling";"Larva";710
"Unit";"Zergling";"Larva";711
"Unit";"Zergling";"Larva";712
"Unit";"Zergling";"Larva";713
"Unit";"Zergling";"Larva";714
"Unit";"Zergling";"Larva";715
"Unit";"Zergling";"Larva";716
"Unit";"Zergling";"Larva";717
"Unit";"Zergling";"Larva";718
"Unit";"Zergling";"Larva";719
"Unit";"Zergling";"Larva";720
"Unit";"Hydralisk";"Larva";721
"Unit";"Hydralisk";"Larva";723
"Unit";"Hydralisk";"Larva";725
"Unit";"Hydralisk";"Larva";727
"Unit";"Zergling";"Larva";729
"Unit";"Zergling";"Larva";730
"Unit";"Hydralisk";"Larva";731
"Unit";"Hydralisk";"Larva";733
"Unit";"Zergling";"Larva";735
"Unit";"Zergling";"Larva";736
"Unit";"Zergling";"Larva";737
"Unit";"Zergling";"Larva";738
"Unit";"Zergling";"Larva";739
"Unit";"Zergling";"Larva";740
"Unit";"Zergling";"Larva";741
"Unit";"Zergling";"Larva";742
"Unit";"Zergling";"Larva";743
"Unit";"Zergling";"Larva";744
"Unit";"Zergling";"Larva";745
"Unit";"Zergling";"Larva";746
"Unit";"Zergling";"Larva";747
"Unit";"Zergling";"Larva";748
"Unit";"Zergling";"Larva";749
"Unit";"Zergling";"Larva";750
"Unit";"Zergling";"Larva";751
"Unit";"Zergling";"Larva";752
"Unit";"Zergling";"Larva";753
"Unit";"Zergling";"Larva";754
"Unit";"Zergling";"Larva";755
"Unit";"Zergling";"Larva";756
"Building";"Extractor";NA;757
"Building";"Extractor";NA;757
"Building";"SporeCrawler";NA;757
"Building";"SpineCrawler";NA;757
"Building";"SpineCrawler";NA;757
"Unit";"Baneling";"Zergling";757
"Unit";"Baneling";"Zergling";757
"Unit";"Baneling";"Zergling";757
"Unit";"Baneling";"Zergling";757
"Unit";"Baneling";"Zergling";757
"Unit";"Baneling";"Zergling";757
"Unit";"Hydralisk";"Larva";757
"Unit";"Zergling";"Larva";759
"Unit";"Zergling";"Larva";760
"Unit";"Zergling";"Larva";761
"Unit";"Zergling";"Larva";762
"Unit";"Zergling";"Larva";763
"Unit";"Zergling";"Larva";764
"Unit";"Zergling";"Larva";765
"Unit";"Zergling";"Larva";766
"Unit";"Zergling";"Larva";767
"Unit";"Zergling";"Larva";768
"Unit";"Zergling";"Larva";769
"Unit";"Zergling";"Larva";770
"Unit";"Zergling";"Larva";771
"Unit";"Zergling";"Larva";772
"Unit";"Zergling";"Larva";773
"Unit";"Zergling";"Larva";774
"Unit";"Zergling";"Larva";775
"Unit";"Zergling";"Larva";776
"Unit";"Zergling";"Larva";777
"Unit";"Zergling";"Larva";778
"Unit";"Zergling";"Larva";779
"Unit";"Zergling";"Larva";780
"Unit";"Zergling";"Larva";781
"Unit";"Zergling";"Larva";782
"Unit";"Zergling";"Larva";783
"Unit";"Zergling";"Larva";784
"Unit";"Zergling";"Larva";785
"Unit";"Zergling";"Larva";786
"Unit";"Zergling";"Larva";787
"Unit";"Zergling";"Larva";788
"Unit";"Zergling";"Larva";789
"Unit";"Zergling";"Larva";790
"Unit";"Baneling";"Zergling";791
"Unit";"Baneling";"Zergling";791
"Unit";"Hydralisk";"Larva";791
"Unit";"Zergling";"Larva";793
"Unit";"Zergling";"Larva";794
"Unit";"Zergling";"Larva";795
"Unit";"Zergling";"Larva";796
"Unit";"Zergling";"Larva";797
"Unit";"Zergling";"Larva";798
"Unit";"Zergling";"Larva";799
"Unit";"Zergling";"Larva";800
"Unit";"Zergling";"Larva";801
"Unit";"Zergling";"Larva";802
"Unit";"Zergling";"Larva";803
"Unit";"Zergling";"Larva";804
"Unit";"Zergling";"Larva";805
"Unit";"Zergling";"Larva";806
"Unit";"Zergling";"Larva";807
"Unit";"Zergling";"Larva";808
"Unit";"Zergling";"Larva";809
"Unit";"Zergling";"Larva";810
"Unit";"Zergling";"Larva";811
"Unit";"Zergling";"Larva";812
"Unit";"Zergling";"Larva";813
"Unit";"Zergling";"Larva";814
"Unit";"Zergling";"Larva";815
"Unit";"Zergling";"Larva";816
"Unit";"Hydralisk";"Larva";817
"Unit";"Hydralisk";"Larva";819
"Unit";"Hydralisk";"Larva";821
"Unit";"Hydralisk";"Larva";823
"Unit";"Hydralisk";"Larva";825
"Unit";"Zergling";"Larva";827
"Unit";"Zergling";"Larva";828
"Unit";"Zergling";"Larva";829
"Unit";"Zergling";"Larva";830
"Unit";"Zergling";"Larva";831
"Unit";"Zergling";"Larva";832
"Unit";"Zergling";"Larva";833
"Unit";"Zergling";"Larva";834
"Unit";"Zergling";"Larva";835
"Unit";"Zergling";"Larva";836
"Unit";"Zergling";"Larva";837
"Unit";"Zergling";"Larva";838
"Unit";"Baneling";"Zergling";839
"Unit";"Baneling";"Zergling";839
"Unit";"Baneling";"Zergling";839
"Unit";"Baneling";"Zergling";839
"Unit";"Baneling";"Zergling";839
"Unit";"Baneling";"Zergling";839
"Unit";"Baneling";"Zergling";839
"Unit";"Baneling";"Zergling";839
"Unit";"Baneling";"Zergling";839
"Unit";"Queen";"Hatchery";839
"Building";"Hatchery";NA;841
"Unit";"Hydralisk";"Larva";841
"Unit";"Hydralisk";"Larva";843
"Unit";"Baneling";"Zergling";845
"Unit";"Baneling";"Zergling";845
"Unit";"Baneling";"Zergling";845
"Unit";"Baneling";"Zergling";845
"Building";"CreepTumorQueen";NA;848
"Building";"CreepTumorQueen";NA;848
"Building";"CreepTumorQueen";NA;848
"Building";"CreepTumorQueen";NA;848
"Unit";"Zergling";"Larva";848
"Unit";"Zergling";"Larva";849
"Unit";"Zergling";"Larva";850
"Unit";"Zergling";"Larva";851
"Unit";"Zergling";"Larva";852
"Unit";"Zergling";"Larva";853
"Unit";"Zergling";"Larva";854
"Unit";"Zergling";"Larva";855
"Unit";"Zergling";"Larva";856
"Unit";"Zergling";"Larva";857
"Unit";"Zergling";"Larva";858
"Unit";"Zergling";"Larva";859
"Unit";"Zergling";"Larva";860
"Unit";"Zergling";"Larva";861
"Unit";"Zergling";"Larva";862
"Unit";"Zergling";"Larva";863
"Unit";"Zergling";"Larva";864
"Unit";"Zergling";"Larva";865
"Unit";"Zergling";"Larva";866
"Unit";"Zergling";"Larva";867
"Unit";"Zergling";"Larva";868
"Unit";"Zergling";"Larva";869
"Unit";"Hydralisk";"Larva";870
"Unit";"Hydralisk";"Larva";872
"Unit";"Hydralisk";"Larva";874
"Unit";"Zergling";"Larva";876
"Unit";"Zergling";"Larva";877
"Unit";"Zergling";"Larva";878
"Unit";"Zergling";"Larva";879
"Unit";"Zergling";"Larva";880
"Unit";"Zergling";"Larva";881
"Unit";"Zergling";"Larva";882
"Unit";"Zergling";"Larva";883
"Unit";"Zergling";"Larva";884
"Unit";"Zergling";"Larva";885
"Unit";"Zergling";"Larva";886
"Unit";"Zergling";"Larva";887
"Unit";"Zergling";"Larva";888
"Unit";"Zergling";"Larva";889
"Unit";"Zergling";"Larva";890
"Unit";"Zergling";"Larva";891
"Unit";"Zergling";"Larva";892
"Unit";"Zergling";"Larva";893
"Unit";"Zergling";"Larva";894
"Unit";"Zergling";"Larva";895
"Unit";"Zergling";"Larva";896
"Unit";"Zergling";"Larva";897
"Unit";"Zergling";"Larva";898
"Unit";"Zergling";"Larva";899
"Unit";"Zergling";"Larva";900
"Unit";"Zergling";"Larva";901
"Unit";"Zergling";"Larva";902
"Unit";"Zergling";"Larva";903
"Unit";"Zergling";"Larva";904
"Unit";"Zergling";"Larva";905
"Unit";"Zergling";"Larva";906
"Unit";"Zergling";"Larva";907
"Unit";"Zergling";"Larva";908
"Unit";"Zergling";"Larva";909
"Unit";"Zergling";"Larva";910
"Unit";"Zergling";"Larva";911
"Unit";"Zergling";"Larva";912
"Unit";"Zergling";"Larva";913
"Unit";"Zergling";"Larva";914
"Unit";"Zergling";"Larva";915
"Unit";"Zergling";"Larva";916
"Unit";"Zergling";"Larva";917
"Unit";"Baneling";"Zergling";918
"Unit";"Baneling";"Zergling";918
"Unit";"Baneling";"Zergling";918
"Unit";"Baneling";"Zergling";918
"Unit";"Baneling";"Zergling";918
"Building";"CreepTumor";NA;918
"Building";"CreepTumor";NA;918
"Unit";"Zergling";"Larva";918
"Unit";"Zergling";"Larva";919
"Unit";"Baneling";"Zergling";920
"Unit";"Baneling";"Zergling";920
"Unit";"Baneling";"Zergling";920
"Unit";"Baneling";"Zergling";920
"Unit";"Baneling";"Zergling";920
"Unit";"Baneling";"Zergling";920
"Unit";"Baneling";"Zergling";920
"Unit";"Zergling";"Larva";920
"Unit";"Zergling";"Larva";921
"Unit";"Zergling";"Larva";922
"Unit";"Zergling";"Larva";923
"Unit";"Zergling";"Larva";924
"Unit";"Zergling";"Larva";925
"Unit";"Zergling";"Larva";926
"Unit";"Zergling";"Larva";927
"Unit";"Zergling";"Larva";928
"Unit";"Zergling";"Larva";929
"Unit";"Zergling";"Larva";930
"Unit";"Zergling";"Larva";931
"Unit";"Zergling";"Larva";932
"Unit";"Zergling";"Larva";933
"Unit";"Zergling";"Larva";934
"Unit";"Zergling";"Larva";935
"Unit";"Hydralisk";"Larva";936
"Unit";"Hydralisk";"Larva";938
"Unit";"Hydralisk";"Larva";940
"Unit";"Hydralisk";"Larva";942
"Unit";"Hydralisk";"Larva";944
"Unit";"Hydralisk";"Larva";946
"Unit";"Hydralisk";"Larva";948
"Unit";"Hydralisk";"Larva";950
"Unit";"Hydralisk";"Larva";952
"Unit";"Hydralisk";"Larva";954
"Unit";"Hydralisk";"Larva";956
"Unit";"Hydralisk";"Larva";958
"Unit";"Zergling";"Larva";960
"Unit";"Zergling";"Larva";961
"Unit";"Zergling";"Larva";962
"Unit";"Zergling";"Larva";963
"Unit";"Zergling";"Larva";964
"Unit";"Zergling";"Larva";965
"Unit";"Zergling";"Larva";966
"Unit";"Zergling";"Larva";967
"Unit";"Zergling";"Larva";968
"Unit";"Zergling";"Larva";969
"Unit";"Baneling";"Zergling";970
"Unit";"Baneling";"Zergling";970
"Unit";"Baneling";"Zergling";970
"Unit";"Baneling";"Zergling";970
"Building";"Extractor";NA;970
"Unit";"Zergling";"Larva";970
"Unit";"Zergling";"Larva";971
"Unit";"Zergling";"Larva";972
"Unit";"Zergling";"Larva";973
"Unit";"Zergling";"Larva";974
"Unit";"Zergling";"Larva";975
"Building";"Extractor";NA;976
"Unit";"Zergling";"Larva";976
"Unit";"Zergling";"Larva";977
"Unit";"Zergling";"Larva";978
"Unit";"Zergling";"Larva";979
"Unit";"Zergling";"Larva";980
"Unit";"Zergling";"Larva";981
"Unit";"Zergling";"Larva";982
"Unit";"Zergling";"Larva";983
"Unit";"Zergling";"Larva";984
"Unit";"Zergling";"Larva";985
"Unit";"Zergling";"Larva";986
"Unit";"Zergling";"Larva";987
"Unit";"Zergling";"Larva";988
"Unit";"Zergling";"Larva";989
"Unit";"Zergling";"Larva";990
"Unit";"Zergling";"Larva";991
"Unit";"Zergling";"Larva";992
"Unit";"Zergling";"Larva";993
"Unit";"Zergling";"Larva";994
"Unit";"Zergling";"Larva";995
"Unit";"Zergling";"Larva";996
"Unit";"Zergling";"Larva";997
"Unit";"Zergling";"Larva";998
"Unit";"Zergling";"Larva";999
"Unit";"Hydralisk";"Larva";1000
"Unit";"Hydralisk";"Larva";1002
"Unit";"Hydralisk";"Larva";1004
"Unit";"Zergling";"Larva";1006
"Unit";"Zergling";"Larva";1007
"Unit";"Hydralisk";"Larva";1008
"Unit";"Hydralisk";"Larva";1010
"Unit";"Hydralisk";"Larva";1012
"Unit";"Hydralisk";"Larva";1014
"Unit";"Hydralisk";"Larva";1016
"Unit";"Hydralisk";"Larva";1018
"Unit";"Hydralisk";"Larva";1020
"Unit";"Zergling";"Larva";1022
"Unit";"Zergling";"Larva";1023
"Unit";"Zergling";"Larva";1024
"Unit";"Zergling";"Larva";1025
"Unit";"Zergling";"Larva";1026
"Unit";"Zergling";"Larva";1027
"Unit";"Zergling";"Larva";1028
"Unit";"Zergling";"Larva";1029
"Unit";"Zergling";"Larva";1030
"Unit";"Zergling";"Larva";1031
"Unit";"Zergling";"Larva";1032
"Unit";"Zergling";"Larva";1033
"Unit";"Zergling";"Larva";1034
"Unit";"Zergling";"Larva";1035
"Unit";"Zergling";"Larva";1036
"Unit";"Zergling";"Larva";1037
"Unit";"Zergling";"Larva";1038
"Unit";"Zergling";"Larva";1039
"Unit";"Zergling";"Larva";1040
"Unit";"Zergling";"Larva";1041
"Unit";"Zergling";"Larva";1042
"Unit";"Zergling";"Larva";1043
"Unit";"Zergling";"Larva";1044
"Unit";"Zergling";"Larva";1045
"Unit";"Zergling";"Larva";1046
"Unit";"Zergling";"Larva";1047
"Unit";"Zergling";"Larva";1048
"Unit";"Zergling";"Larva";1049
"Unit";"Zergling";"Larva";1050
"Unit";"Zergling";"Larva";1051
"Unit";"Zergling";"Larva";1052
"Unit";"Zergling";"Larva";1053
"Unit";"Baneling";"Zergling";1054
"Unit";"Baneling";"Zergling";1054
"Unit";"Baneling";"Zergling";1054
"Unit";"Baneling";"Zergling";1054
"Unit";"Baneling";"Zergling";1054
"Unit";"Baneling";"Zergling";1054
"Unit";"Baneling";"Zergling";1054
"Unit";"Baneling";"Zergling";1054
"Unit";"Baneling";"Zergling";1054
"Unit";"Baneling";"Zergling";1054
"Unit";"Baneling";"Zergling";1054
"Unit";"Baneling";"Zergling";1054
"Unit";"Baneling";"Zergling";1054
"Unit";"Zergling";"Larva";1054
"Unit";"Zergling";"Larva";1055
"Unit";"Zergling";"Larva";1056
"Unit";"Zergling";"Larva";1057
"Upgrade";"SprayZerg";NA;1058
"Upgrade";"SprayZerg";NA;1058
"Upgrade";"SprayZerg";NA;1058
"Upgrade";"zerglingmovementspeed";NA;1058
"Upgrade";"SprayZerg";NA;1058
"Upgrade";"ZergMeleeWeaponsLevel1";NA;1058
"Upgrade";"ZergGroundArmorsLevel1";NA;1058
"Upgrade";"SprayZerg";NA;1058
"Upgrade";"CentrificalHooks";NA;1058
"Upgrade";"SprayZerg";NA;1058
"Upgrade";"SprayZerg";NA;1058
"Upgrade";"EvolveMuscularAugments";NA;1058
"Upgrade";"ZergMissileWeaponsLevel1";NA;1058
"Upgrade";"SprayZerg";NA;1058
"Upgrade";"SprayZerg";NA;1058
"Upgrade";"ZergMeleeWeaponsLevel2";NA;1058
"Upgrade";"ZergMissileWeaponsLevel2";NA;1058
"Upgrade";"ZergGroundArmorsLevel2";NA;1058
"Upgrade";"SprayZerg";NA;1058
"Upgrade";"SprayZerg";NA;1058
"Upgrade";"SprayZerg";NA;1058
"Upgrade";"SprayZerg";NA;1058
"Upgrade";"SprayZerg";NA;1058
"Upgrade";"SprayZerg";NA;1058
"Upgrade";"SprayZerg";NA;1058
"Upgrade";"ZergMissileWeaponsLevel3";NA;1058
"Upgrade";"ZergGroundArmorsLevel3";NA;1058
"Upgrade";"SprayZerg";NA;1058
