"type";"unit_name";"on_building";"total_supply_lag";"supply"
"Unit";"Overlord";"Larva";13;0
"Building";"Extractor";NA;17;0
"Building";"SpawningPool";NA;18;0
"Building";"Hatchery";NA;19;0
"Unit";"Queen";"Hatchery";21;2
"Unit";"Zergling";"Larva";23;1
"Unit";"Zergling";"Larva";24;1
"Unit";"Overlord";"Larva";25;0
"Unit";"Queen";"Hatchery";28;2
"Building";"Hatchery";NA;34;0
"Building";"CreepTumorQueen";NA;34;0
"Unit";"Overlord";"Larva";38;0
"Building";"CreepTumor";NA;41;0
"Unit";"Queen";"Hatchery";41;2
"Unit";"Overlord";"Larva";49;0
"Unit";"Overlord";"Larva";49;0
"Building";"Extractor";NA;49;0
"Building";"CreepTumor";NA;49;0
"Unit";"Overlord";"Larva";50;0
"Unit";"Overlord";"Larva";50;0
"Unit";"Queen";"Hatchery";50;2
"Unit";"Queen";"Hatchery";52;2
"Building";"CreepTumorQueen";NA;55;0
"Building";"CreepTumorQueen";NA;56;0
"Unit";"Queen";"Hatchery";63;2
"Building";"CreepTumor";NA;65;0
"Unit";"Zergling";"Larva";65;1
"Unit";"Zergling";"Larva";66;1
"Unit";"Zergling";"Larva";67;1
"Unit";"Zergling";"Larva";68;1
"Building";"CreepTumor";NA;69;0
"Building";"BanelingNest";NA;69;0
"Building";"CreepTumor";NA;69;0
"Unit";"Zergling";"Larva";69;1
"Unit";"Zergling";"Larva";70;1
"Unit";"Zergling";"Larva";71;1
"Unit";"Zergling";"Larva";72;1
"Unit";"Zergling";"Larva";73;1
"Unit";"Zergling";"Larva";74;1
"Unit";"Zergling";"Larva";75;1
"Unit";"Zergling";"Larva";76;1
"Unit";"Zergling";"Larva";77;1
"Unit";"Zergling";"Larva";78;1
"Unit";"Zergling";"Larva";79;1
"Unit";"Zergling";"Larva";80;1
"Unit";"Zergling";"Larva";81;1
"Unit";"Zergling";"Larva";82;1
"Building";"Extractor";NA;83;0
"Building";"EvolutionChamber";NA;83;0
"Building";"EvolutionChamber";NA;84;0
"Unit";"Overlord";"Larva";86;0
"Building";"CreepTumorQueen";NA;91;0
"Building";"CreepTumorQueen";NA;91;0
"Building";"CreepTumor";NA;91;0
"Building";"CreepTumorQueen";NA;91;0
"Building";"SporeCrawler";NA;97;0
"Building";"SporeCrawler";NA;97;0
"Building";"SporeCrawler";NA;97;0
"Unit";"Overlord";"Larva";100;0
"Building";"CreepTumor";NA;102;0
"Building";"CreepTumor";NA;102;0
"Building";"CreepTumor";NA;102;0
"Building";"CreepTumor";NA;102;0
"Unit";"Overlord";"Larva";102;0
"Unit";"Overlord";"Larva";109;0
"Building";"CreepTumor";NA;111;0
"Building";"CreepTumor";NA;111;0
"Building";"CreepTumor";NA;111;0
"Building";"Extractor";NA;113;0
"Building";"HydraliskDen";NA;115;0
"Building";"CreepTumor";NA;117;0
"Building";"Extractor";NA;119;0
"Building";"Extractor";NA;119;0
"Unit";"Overlord";"Larva";126;0
"Unit";"Overlord";"Larva";126;0
"Unit";"Overlord";"Larva";126;0
"Building";"CreepTumor";NA;126;0
"Building";"CreepTumor";NA;126;0
"Building";"CreepTumor";NA;126;0
"Building";"CreepTumor";NA;126;0
"Unit";"Hydralisk";"Larva";126;2
"Building";"CreepTumor";NA;128;0
"Unit";"Hydralisk";"Larva";128;2
"Unit";"Hydralisk";"Larva";130;2
"Building";"Hatchery";NA;132;0
"Unit";"Hydralisk";"Larva";132;2
"Unit";"Hydralisk";"Larva";134;2
"Unit";"Hydralisk";"Larva";136;2
"Unit";"Hydralisk";"Larva";138;2
"Unit";"Hydralisk";"Larva";140;2
"Unit";"Hydralisk";"Larva";142;2
"Unit";"Overlord";"Larva";144;0
"Building";"CreepTumor";NA;144;0
"Building";"CreepTumor";NA;144;0
"Unit";"Hydralisk";"Larva";144;2
"Unit";"Hydralisk";"Larva";146;2
"Building";"CreepTumor";NA;148;0
"Unit";"Overlord";"Larva";148;0
"Building";"CreepTumor";NA;148;0
"Unit";"Overlord";"Larva";148;0
"Unit";"Hydralisk";"Larva";148;2
"Unit";"Hydralisk";"Larva";150;2
"Unit";"Overlord";"Larva";152;0
"Building";"InfestationPit";NA;152;0
"Building";"CreepTumor";NA;155;0
"Unit";"Overlord";"Larva";155;0
"Building";"SporeCrawler";NA;155;0
"Building";"CreepTumor";NA;155;0
"Building";"CreepTumor";NA;155;0
"Building";"CreepTumor";NA;155;0
"Unit";"Hydralisk";"Larva";155;2
"Unit";"Hydralisk";"Larva";157;2
"Unit";"Hydralisk";"Larva";159;2
"Unit";"Hydralisk";"Larva";161;2
"Unit";"Zergling";"Larva";163;1
"Unit";"Zergling";"Larva";164;1
"Unit";"Zergling";"Larva";165;1
"Unit";"Zergling";"Larva";166;1
"Unit";"Zergling";"Larva";167;1
"Unit";"Zergling";"Larva";168;1
"Unit";"Zergling";"Larva";169;1
"Unit";"Zergling";"Larva";170;1
"Unit";"Zergling";"Larva";171;1
"Unit";"Zergling";"Larva";172;1
"Unit";"Baneling";"Zergling";173;0
"Unit";"Baneling";"Zergling";173;0
"Unit";"Baneling";"Zergling";173;0
"Unit";"Baneling";"Zergling";173;0
"Unit";"Baneling";"Zergling";173;0
"Unit";"Baneling";"Zergling";173;0
"Unit";"Baneling";"Zergling";173;0
"Unit";"Overlord";"Larva";173;0
"Building";"CreepTumor";NA;173;0
"Building";"CreepTumor";NA;173;0
"Building";"CreepTumor";NA;173;0
"Building";"CreepTumor";NA;173;0
"Unit";"Queen";"Hatchery";173;2
"Building";"Extractor";NA;175;0
"Building";"Extractor";NA;175;0
"Unit";"Overlord";"Larva";181;0
"Unit";"Overlord";"Larva";181;0
"Unit";"Overlord";"Larva";181;0
"Unit";"Hydralisk";"Larva";181;2
"Unit";"Hydralisk";"Larva";183;2
"Unit";"Hydralisk";"Larva";185;2
"Unit";"Hydralisk";"Larva";187;2
"Building";"CreepTumor";NA;189;0
"Unit";"Overlord";"Larva";189;0
"Building";"CreepTumor";NA;189;0
"Building";"CreepTumor";NA;189;0
"Building";"CreepTumor";NA;189;0
"Unit";"Overlord";"Larva";189;0
"Building";"CreepTumor";NA;189;0
"Building";"Hatchery";NA;189;0
"Unit";"Zergling";"Larva";189;1
"Unit";"Zergling";"Larva";190;1
"Unit";"Zergling";"Larva";191;1
"Unit";"Zergling";"Larva";192;1
"Unit";"Zergling";"Larva";193;1
"Unit";"Zergling";"Larva";194;1
"Unit";"Zergling";"Larva";195;1
"Unit";"Zergling";"Larva";196;1
"Unit";"Zergling";"Larva";197;1
"Unit";"Zergling";"Larva";198;1
"Unit";"Zergling";"Larva";199;1
"Unit";"Zergling";"Larva";200;1
"Unit";"Zergling";"Larva";201;1
"Unit";"Zergling";"Larva";202;1
"Unit";"Zergling";"Larva";203;1
"Unit";"Zergling";"Larva";204;1
"Unit";"Zergling";"Larva";205;1
"Unit";"Zergling";"Larva";206;1
"Unit";"Zergling";"Larva";207;1
"Unit";"Zergling";"Larva";208;1
"Unit";"Zergling";"Larva";209;1
"Unit";"Zergling";"Larva";210;1
"Building";"CreepTumor";NA;211;0
"Building";"CreepTumor";NA;211;0
"Building";"CreepTumor";NA;211;0
"Unit";"Hydralisk";"Larva";211;2
"Unit";"Hydralisk";"Larva";213;2
"Unit";"Hydralisk";"Larva";215;2
"Unit";"Hydralisk";"Larva";217;2
"Building";"CreepTumor";NA;219;0
"Building";"CreepTumor";NA;219;0
"Building";"CreepTumor";NA;219;0
"Building";"CreepTumor";NA;219;0
"Unit";"Hydralisk";"Larva";219;2
"Unit";"Hydralisk";"Larva";221;2
"Building";"CreepTumor";NA;223;0
"Building";"CreepTumor";NA;223;0
"Unit";"Queen";"Hatchery";223;2
"Building";"Extractor";NA;225;0
"Building";"Extractor";NA;225;0
"Building";"CreepTumor";NA;225;0
"Unit";"Overlord";"Larva";225;0
"Building";"EvolutionChamber";NA;225;0
"Building";"CreepTumor";NA;225;0
"Building";"CreepTumor";NA;225;0
"Building";"CreepTumor";NA;225;0
"Building";"SporeCrawler";NA;225;0
"Unit";"Zergling";"Larva";225;1
"Unit";"Zergling";"Larva";226;1
"Unit";"Zergling";"Larva";227;1
"Unit";"Zergling";"Larva";228;1
"Upgrade";"SprayZerg";NA;229;0
"Upgrade";"SprayZerg";NA;229;0
"Upgrade";"SprayZerg";NA;229;0
"Upgrade";"zerglingmovementspeed";NA;229;0
"Upgrade";"SprayZerg";NA;229;0
"Upgrade";"SprayZerg";NA;229;0
"Upgrade";"CentrificalHooks";NA;229;0
"Upgrade";"ZergGroundArmorsLevel1";NA;229;0
"Upgrade";"ZergMeleeWeaponsLevel1";NA;229;0
"Upgrade";"SprayZerg";NA;229;0
"Upgrade";"overlordspeed";NA;229;0
"Upgrade";"EvolveMuscularAugments";NA;229;0
"Upgrade";"SprayZerg";NA;229;0
"Upgrade";"ZergMissileWeaponsLevel1";NA;229;0
"Upgrade";"SprayZerg";NA;229;0
"Upgrade";"ZergGroundArmorsLevel2";NA;229;0
