"type";"unit_name";"on_building";"total_supply_lag";"supply"
"Unit";"Overlord";"Larva";13;0
"Building";"Hatchery";NA;17;0
"Building";"Extractor";NA;19;0
"Building";"SpawningPool";NA;19;0
"Unit";"Overlord";"Larva";22;0
"Unit";"Queen";"Hatchery";22;2
"Unit";"Zergling";"Larva";24;1
"Unit";"Zergling";"Larva";25;1
"Unit";"Zergling";"Larva";26;1
"Unit";"Zergling";"Larva";27;1
"Unit";"Queen";"Hatchery";28;2
"Unit";"Zergling";"Larva";30;1
"Unit";"Zergling";"Larva";31;1
"Unit";"Overlord";"Larva";36;0
"Unit";"Queen";"Hatchery";36;2
"Building";"Hatchery";NA;44;0
"Unit";"Zergling";"Larva";44;1
"Unit";"Zergling";"Larva";45;1
"Unit";"Zergling";"Larva";46;1
"Unit";"Zergling";"Larva";47;1
"Unit";"Zergling";"Larva";48;1
"Unit";"Zergling";"Larva";49;1
"Unit";"Zergling";"Larva";50;1
"Unit";"Zergling";"Larva";51;1
"Unit";"Zergling";"Larva";52;1
"Unit";"Zergling";"Larva";53;1
"Building";"CreepTumorQueen";NA;54;0
"Unit";"Zergling";"Larva";54;1
"Unit";"Zergling";"Larva";55;1
"Unit";"Zergling";"Larva";56;1
"Unit";"Zergling";"Larva";57;1
"Unit";"Overlord";"Larva";58;0
"Unit";"Overlord";"Larva";58;0
"Unit";"Overlord";"Larva";58;0
"Unit";"Queen";"Hatchery";58;2
"Building";"CreepTumor";NA;62;0
"Unit";"Zergling";"Larva";64;1
"Unit";"Zergling";"Larva";65;1
"Unit";"Zergling";"Larva";66;1
"Unit";"Zergling";"Larva";67;1
"Unit";"Zergling";"Larva";68;1
"Unit";"Zergling";"Larva";69;1
"Unit";"Zergling";"Larva";70;1
"Unit";"Zergling";"Larva";71;1
"Unit";"Queen";"Hatchery";81;2
"Building";"Extractor";NA;84;0
"Building";"Extractor";NA;84;0
"Building";"CreepTumorQueen";NA;84;0
"Building";"CreepTumor";NA;84;0
"Building";"CreepTumorQueen";NA;84;0
"Building";"BanelingNest";NA;93;0
"Unit";"Overlord";"Larva";97;0
"Unit";"Overlord";"Larva";97;0
"Unit";"Zergling";"Larva";97;1
"Unit";"Zergling";"Larva";98;1
"Unit";"Zergling";"Larva";99;1
"Unit";"Zergling";"Larva";100;1
"Unit";"Zergling";"Larva";101;1
"Unit";"Zergling";"Larva";102;1
"Unit";"Overlord";"Larva";107;0
"Unit";"Overlord";"Larva";108;0
"Building";"EvolutionChamber";NA;112;0
"Building";"EvolutionChamber";NA;112;0
"Building";"HydraliskDen";NA;116;0
"Building";"CreepTumorQueen";NA;116;0
"Building";"CreepTumorQueen";NA;116;0
"Building";"Extractor";NA;119;0
"Building";"Extractor";NA;119;0
"Unit";"Overlord";"Larva";119;0
"Building";"CreepTumor";NA;124;0
"Building";"CreepTumor";NA;124;0
"Building";"CreepTumor";NA;124;0
"Building";"CreepTumorQueen";NA;124;0
"Building";"CreepTumorQueen";NA;124;0
"Unit";"Hydralisk";"Larva";124;2
"Unit";"Zergling";"Larva";126;1
"Unit";"Zergling";"Larva";127;1
"Unit";"Zergling";"Larva";128;1
"Unit";"Zergling";"Larva";129;1
"Unit";"Zergling";"Larva";130;1
"Unit";"Zergling";"Larva";131;1
"Unit";"Hydralisk";"Larva";132;2
"Unit";"Hydralisk";"Larva";134;2
"Unit";"Zergling";"Larva";136;1
"Unit";"Zergling";"Larva";137;1
"Unit";"Zergling";"Larva";138;1
"Unit";"Zergling";"Larva";139;1
"Building";"CreepTumor";NA;153;0
"Building";"CreepTumor";NA;153;0
"Building";"CreepTumor";NA;153;0
"Building";"CreepTumor";NA;153;0
"Building";"CreepTumorQueen";NA;154;0
"Building";"Extractor";NA;157;0
"Unit";"Hydralisk";"Larva";157;2
"Unit";"Hydralisk";"Larva";159;2
"Building";"Hatchery";NA;161;0
"Unit";"Hydralisk";"Larva";161;2
"Unit";"Hydralisk";"Larva";163;2
"Unit";"Overlord";"Larva";165;0
"Building";"CreepTumorQueen";NA;165;0
"Building";"CreepTumorQueen";NA;165;0
"Building";"CreepTumorQueen";NA;165;0
"Building";"CreepTumor";NA;165;0
"Building";"CreepTumorQueen";NA;165;0
"Building";"CreepTumorQueen";NA;165;0
"Unit";"Baneling";"Zergling";165;0
"Unit";"Baneling";"Zergling";165;0
"Unit";"Baneling";"Zergling";165;0
"Building";"CreepTumor";NA;165;0
"Unit";"Overlord";"Larva";165;0
"Unit";"Overlord";"Larva";165;0
"Unit";"Overlord";"Larva";165;0
"Unit";"Overlord";"Larva";165;0
"Unit";"Overlord";"Larva";165;0
"Unit";"Hydralisk";"Larva";165;2
"Unit";"Hydralisk";"Larva";167;2
"Unit";"Hydralisk";"Larva";169;2
"Unit";"Zergling";"Larva";171;1
"Unit";"Zergling";"Larva";172;1
"Unit";"Hydralisk";"Larva";173;2
"Unit";"Overlord";"Larva";175;0
"Unit";"Hydralisk";"Larva";175;2
"Unit";"Hydralisk";"Larva";177;2
"Unit";"Zergling";"Larva";179;1
"Unit";"Zergling";"Larva";180;1
"Building";"CreepTumor";NA;181;0
"Building";"CreepTumor";NA;181;0
"Building";"CreepTumor";NA;181;0
"Building";"CreepTumor";NA;181;0
"Building";"CreepTumor";NA;181;0
"Building";"CreepTumor";NA;181;0
"Unit";"Hydralisk";"Larva";181;2
"Unit";"Hydralisk";"Larva";183;2
"Unit";"Zergling";"Larva";185;1
"Unit";"Zergling";"Larva";186;1
"Building";"CreepTumorQueen";NA;187;0
"Unit";"Zergling";"Larva";187;1
"Unit";"Zergling";"Larva";188;1
"Unit";"Zergling";"Larva";189;1
"Unit";"Zergling";"Larva";190;1
"Building";"CreepTumor";NA;191;0
"Building";"CreepTumor";NA;191;0
"Building";"CreepTumorQueen";NA;191;0
"Unit";"Hydralisk";"Larva";191;2
"Unit";"Hydralisk";"Larva";193;2
"Unit";"Hydralisk";"Larva";195;2
"Unit";"Hydralisk";"Larva";197;2
"Unit";"Hydralisk";"Larva";199;2
"Unit";"Zergling";"Larva";201;1
"Unit";"Zergling";"Larva";202;1
"Unit";"Zergling";"Larva";203;1
"Unit";"Zergling";"Larva";204;1
"Unit";"Zergling";"Larva";205;1
"Unit";"Zergling";"Larva";206;1
"Unit";"Overlord";"Larva";207;0
"Building";"CreepTumor";NA;207;0
"Building";"CreepTumor";NA;207;0
"Building";"CreepTumor";NA;207;0
"Unit";"Hydralisk";"Larva";207;2
"Unit";"Hydralisk";"Larva";209;2
"Unit";"Hydralisk";"Larva";211;2
"Unit";"Hydralisk";"Larva";213;2
"Unit";"Overlord";"Larva";215;0
"Unit";"Zergling";"Larva";215;1
"Unit";"Zergling";"Larva";216;1
"Unit";"Zergling";"Larva";217;1
"Unit";"Zergling";"Larva";218;1
"Unit";"Zergling";"Larva";219;1
"Unit";"Zergling";"Larva";220;1
"Unit";"Zergling";"Larva";221;1
"Unit";"Zergling";"Larva";222;1
"Unit";"Zergling";"Larva";223;1
"Unit";"Zergling";"Larva";224;1
"Unit";"Zergling";"Larva";225;1
"Unit";"Zergling";"Larva";226;1
"Unit";"Overlord";"Larva";227;0
"Unit";"Overlord";"Larva";227;0
"Unit";"Zergling";"Larva";227;1
"Unit";"Zergling";"Larva";228;1
"Unit";"Zergling";"Larva";229;1
"Unit";"Zergling";"Larva";230;1
"Unit";"Zergling";"Larva";231;1
"Unit";"Zergling";"Larva";232;1
"Unit";"Zergling";"Larva";233;1
"Unit";"Zergling";"Larva";234;1
"Unit";"Zergling";"Larva";235;1
"Unit";"Zergling";"Larva";236;1
"Unit";"Zergling";"Larva";237;1
"Unit";"Zergling";"Larva";238;1
"Unit";"Zergling";"Larva";239;1
"Unit";"Zergling";"Larva";240;1
"Unit";"Zergling";"Larva";241;1
"Unit";"Zergling";"Larva";242;1
"Unit";"Zergling";"Larva";243;1
"Unit";"Zergling";"Larva";244;1
"Unit";"Zergling";"Larva";245;1
"Unit";"Zergling";"Larva";246;1
"Unit";"Zergling";"Larva";247;1
"Unit";"Zergling";"Larva";248;1
"Unit";"Zergling";"Larva";249;1
"Unit";"Zergling";"Larva";250;1
"Unit";"Zergling";"Larva";251;1
"Unit";"Zergling";"Larva";252;1
"Unit";"Baneling";"Zergling";253;0
"Unit";"Baneling";"Zergling";253;0
"Unit";"Baneling";"Zergling";253;0
"Unit";"Baneling";"Zergling";253;0
"Unit";"Baneling";"Zergling";253;0
"Unit";"Baneling";"Zergling";253;0
"Unit";"Baneling";"Zergling";253;0
"Unit";"Baneling";"Zergling";253;0
"Unit";"Baneling";"Zergling";253;0
"Unit";"Baneling";"Zergling";253;0
"Unit";"Baneling";"Zergling";253;0
"Unit";"Baneling";"Zergling";253;0
"Unit";"Baneling";"Zergling";253;0
"Unit";"Baneling";"Zergling";253;0
"Unit";"Zergling";"Larva";253;1
"Unit";"Zergling";"Larva";254;1
"Unit";"Zergling";"Larva";255;1
"Unit";"Zergling";"Larva";256;1
"Building";"InfestationPit";NA;268;0
"Building";"CreepTumor";NA;268;0
"Building";"CreepTumor";NA;268;0
"Building";"CreepTumor";NA;268;0
"Building";"CreepTumor";NA;268;0
"Building";"CreepTumor";NA;268;0
"Building";"CreepTumor";NA;268;0
"Building";"EvolutionChamber";NA;270;0
"Building";"CreepTumorQueen";NA;270;0
"Building";"CreepTumorQueen";NA;270;0
"Unit";"Overlord";"Larva";270;0
"Building";"Extractor";NA;271;0
"Building";"Extractor";NA;271;0
"Building";"CreepTumorQueen";NA;271;0
"Building";"CreepTumorQueen";NA;271;0
"Building";"CreepTumor";NA;271;0
"Building";"CreepTumor";NA;271;0
"Unit";"Overlord";"Larva";271;0
"Building";"CreepTumor";NA;271;0
"Building";"Hatchery";NA;271;0
"Unit";"Hydralisk";"Larva";282;2
"Unit";"Hydralisk";"Larva";284;2
"Unit";"Hydralisk";"Larva";286;2
"Unit";"Hydralisk";"Larva";288;2
"Unit";"Hydralisk";"Larva";290;2
"Unit";"Zergling";"Larva";292;1
"Unit";"Zergling";"Larva";293;1
"Unit";"Zergling";"Larva";294;1
"Unit";"Zergling";"Larva";295;1
"Unit";"Zergling";"Larva";296;1
"Unit";"Zergling";"Larva";297;1
"Unit";"Zergling";"Larva";298;1
"Unit";"Zergling";"Larva";299;1
"Unit";"Zergling";"Larva";300;1
"Unit";"Zergling";"Larva";301;1
"Unit";"Baneling";"Zergling";302;0
"Unit";"Baneling";"Zergling";302;0
"Unit";"Baneling";"Zergling";302;0
"Building";"CreepTumor";NA;302;0
"Building";"CreepTumor";NA;302;0
"Building";"CreepTumor";NA;302;0
"Building";"CreepTumor";NA;302;0
"Unit";"Overlord";"Larva";302;0
"Unit";"Overlord";"Larva";304;0
"Building";"CreepTumor";NA;304;0
"Unit";"Viper";"Larva";304;3
"Unit";"Viper";"Larva";307;3
"Unit";"Viper";"Larva";310;3
"Unit";"Zergling";"Larva";313;1
"Unit";"Zergling";"Larva";314;1
"Unit";"Zergling";"Larva";315;1
"Unit";"Zergling";"Larva";316;1
"Unit";"Zergling";"Larva";317;1
"Unit";"Zergling";"Larva";318;1
"Unit";"Zergling";"Larva";319;1
"Unit";"Zergling";"Larva";320;1
"Unit";"Zergling";"Larva";321;1
"Unit";"Zergling";"Larva";322;1
"Unit";"Zergling";"Larva";323;1
"Unit";"Zergling";"Larva";324;1
"Unit";"Zergling";"Larva";325;1
"Unit";"Zergling";"Larva";326;1
"Unit";"Zergling";"Larva";327;1
"Unit";"Zergling";"Larva";328;1
"Unit";"Zergling";"Larva";329;1
"Unit";"Zergling";"Larva";330;1
"Unit";"Zergling";"Larva";331;1
"Unit";"Zergling";"Larva";332;1
"Unit";"Zergling";"Larva";333;1
"Unit";"Zergling";"Larva";334;1
"Unit";"Zergling";"Larva";335;1
"Unit";"Zergling";"Larva";336;1
"Unit";"Zergling";"Larva";337;1
"Unit";"Zergling";"Larva";338;1
"Unit";"Zergling";"Larva";339;1
"Unit";"Zergling";"Larva";340;1
"Unit";"Hydralisk";"Larva";341;2
"Unit";"Hydralisk";"Larva";343;2
"Unit";"Hydralisk";"Larva";345;2
"Unit";"Hydralisk";"Larva";347;2
"Unit";"Hydralisk";"Larva";349;2
"Unit";"Hydralisk";"Larva";351;2
"Unit";"Hydralisk";"Larva";353;2
"Unit";"Hydralisk";"Larva";355;2
"Unit";"Hydralisk";"Larva";357;2
"Unit";"Hydralisk";"Larva";359;2
"Unit";"Hydralisk";"Larva";361;2
"Unit";"Hydralisk";"Larva";363;2
"Unit";"Hydralisk";"Larva";365;2
"Unit";"Hydralisk";"Larva";367;2
"Unit";"Hydralisk";"Larva";369;2
"Unit";"Baneling";"Zergling";371;0
"Unit";"Baneling";"Zergling";371;0
"Unit";"Baneling";"Zergling";371;0
"Unit";"Baneling";"Zergling";371;0
"Unit";"Baneling";"Zergling";371;0
"Unit";"Baneling";"Zergling";371;0
"Unit";"Baneling";"Zergling";371;0
"Unit";"Baneling";"Zergling";371;0
"Unit";"Baneling";"Zergling";371;0
"Unit";"Baneling";"Zergling";371;0
"Unit";"Baneling";"Zergling";371;0
"Unit";"Baneling";"Zergling";371;0
"Unit";"Baneling";"Zergling";371;0
"Unit";"Baneling";"Zergling";371;0
"Unit";"Hydralisk";"Larva";371;2
"Unit";"Zergling";"Larva";373;1
"Unit";"Zergling";"Larva";374;1
"Unit";"Zergling";"Larva";375;1
"Unit";"Zergling";"Larva";376;1
"Building";"Extractor";NA;377;0
"Building";"Extractor";NA;377;0
"Unit";"Baneling";"Zergling";377;0
"Unit";"Baneling";"Zergling";377;0
"Unit";"Baneling";"Zergling";377;0
"Unit";"Baneling";"Zergling";377;0
"Unit";"Baneling";"Zergling";377;0
"Unit";"Baneling";"Zergling";377;0
"Unit";"Baneling";"Zergling";377;0
"Unit";"Baneling";"Zergling";377;0
"Unit";"Baneling";"Zergling";377;0
"Unit";"Baneling";"Zergling";377;0
"Unit";"Zergling";"Larva";377;1
"Unit";"Zergling";"Larva";378;1
"Unit";"Zergling";"Larva";379;1
"Unit";"Zergling";"Larva";380;1
"Unit";"Zergling";"Larva";381;1
"Unit";"Zergling";"Larva";382;1
"Unit";"Baneling";"Zergling";383;0
"Unit";"Overlord";"Larva";383;0
"Unit";"Overlord";"Larva";383;0
"Unit";"Overlord";"Larva";383;0
"Unit";"Overlord";"Larva";383;0
"Unit";"Overlord";"Larva";383;0
"Building";"Hatchery";NA;383;0
"Unit";"Baneling";"Zergling";383;0
"Unit";"Baneling";"Zergling";383;0
"Unit";"Baneling";"Zergling";383;0
"Unit";"Baneling";"Zergling";383;0
"Unit";"Baneling";"Zergling";383;0
"Unit";"Baneling";"Zergling";383;0
"Unit";"Baneling";"Zergling";383;0
"Unit";"Zergling";"Larva";383;1
"Unit";"Zergling";"Larva";384;1
"Unit";"Zergling";"Larva";385;1
"Unit";"Zergling";"Larva";386;1
"Unit";"Zergling";"Larva";387;1
"Unit";"Zergling";"Larva";388;1
"Unit";"Zergling";"Larva";389;1
"Unit";"Zergling";"Larva";390;1
"Unit";"Zergling";"Larva";391;1
"Unit";"Zergling";"Larva";392;1
"Unit";"Zergling";"Larva";393;1
"Unit";"Zergling";"Larva";394;1
"Unit";"Zergling";"Larva";395;1
"Unit";"Zergling";"Larva";396;1
"Unit";"Zergling";"Larva";397;1
"Unit";"Zergling";"Larva";398;1
"Unit";"Zergling";"Larva";399;1
"Unit";"Zergling";"Larva";400;1
"Unit";"Zergling";"Larva";401;1
"Unit";"Zergling";"Larva";402;1
"Unit";"Zergling";"Larva";403;1
"Unit";"Zergling";"Larva";404;1
"Unit";"Zergling";"Larva";405;1
"Unit";"Zergling";"Larva";406;1
"Unit";"Zergling";"Larva";407;1
"Unit";"Zergling";"Larva";408;1
"Unit";"Zergling";"Larva";409;1
"Unit";"Zergling";"Larva";410;1
"Unit";"Zergling";"Larva";411;1
"Unit";"Zergling";"Larva";412;1
"Unit";"Zergling";"Larva";413;1
"Unit";"Zergling";"Larva";414;1
"Building";"CreepTumorQueen";NA;415;0
"Building";"CreepTumorQueen";NA;415;0
"Unit";"Hydralisk";"Larva";415;2
"Building";"Hatchery";NA;417;0
"Unit";"Baneling";"Zergling";419;0
"Unit";"Baneling";"Zergling";419;0
"Building";"CreepTumor";NA;419;0
"Building";"CreepTumor";NA;419;0
"Building";"CreepTumorQueen";NA;419;0
"Building";"Spire";NA;419;0
"Unit";"Baneling";"Zergling";419;0
"Unit";"Baneling";"Zergling";419;0
"Unit";"Baneling";"Zergling";419;0
"Unit";"Baneling";"Zergling";419;0
"Unit";"Baneling";"Zergling";419;0
"Unit";"Baneling";"Zergling";419;0
"Building";"CreepTumor";NA;419;0
"Building";"CreepTumor";NA;420;0
"Building";"CreepTumor";NA;420;0
"Building";"CreepTumor";NA;420;0
"Unit";"Baneling";"Zergling";420;0
"Unit";"Baneling";"Zergling";420;0
"Unit";"Baneling";"Zergling";420;0
"Unit";"Baneling";"Zergling";420;0
"Unit";"Baneling";"Zergling";420;0
"Unit";"Baneling";"Zergling";420;0
"Unit";"Baneling";"Zergling";420;0
"Unit";"Baneling";"Zergling";420;0
"Unit";"Baneling";"Zergling";420;0
"Unit";"Baneling";"Zergling";420;0
"Unit";"Baneling";"Zergling";420;0
"Unit";"Baneling";"Zergling";420;0
"Unit";"Baneling";"Zergling";420;0
"Unit";"Baneling";"Zergling";420;0
"Unit";"Baneling";"Zergling";420;0
"Unit";"Baneling";"Zergling";420;0
"Unit";"Baneling";"Zergling";420;0
"Unit";"Baneling";"Zergling";420;0
"Unit";"Baneling";"Zergling";420;0
"Unit";"Baneling";"Zergling";420;0
"Unit";"Baneling";"Zergling";420;0
"Unit";"Baneling";"Zergling";420;0
"Building";"SpineCrawler";NA;420;0
"Building";"SpineCrawler";NA;420;0
"Unit";"Zergling";"Larva";420;1
"Unit";"Zergling";"Larva";421;1
"Unit";"Zergling";"Larva";422;1
"Unit";"Zergling";"Larva";423;1
"Unit";"Zergling";"Larva";424;1
"Unit";"Zergling";"Larva";425;1
"Unit";"Zergling";"Larva";426;1
"Unit";"Zergling";"Larva";427;1
"Building";"CreepTumor";NA;428;0
"Unit";"Hydralisk";"Larva";428;2
"Unit";"Hydralisk";"Larva";430;2
"Unit";"Hydralisk";"Larva";432;2
"Unit";"Zergling";"Larva";434;1
"Unit";"Zergling";"Larva";435;1
"Unit";"Zergling";"Larva";436;1
"Unit";"Zergling";"Larva";437;1
"Unit";"Zergling";"Larva";438;1
"Unit";"Zergling";"Larva";439;1
"Unit";"Zergling";"Larva";440;1
"Unit";"Zergling";"Larva";441;1
"Unit";"Zergling";"Larva";442;1
"Unit";"Zergling";"Larva";443;1
"Unit";"Zergling";"Larva";444;1
"Unit";"Zergling";"Larva";445;1
"Unit";"Zergling";"Larva";446;1
"Unit";"Zergling";"Larva";447;1
"Unit";"Zergling";"Larva";448;1
"Unit";"Zergling";"Larva";449;1
"Unit";"Zergling";"Larva";450;1
"Unit";"Zergling";"Larva";451;1
"Unit";"Zergling";"Larva";452;1
"Unit";"Zergling";"Larva";453;1
"Unit";"Zergling";"Larva";454;1
"Unit";"Zergling";"Larva";455;1
"Unit";"Hydralisk";"Larva";456;2
"Unit";"Hydralisk";"Larva";458;2
"Unit";"Hydralisk";"Larva";460;2
"Unit";"Hydralisk";"Larva";462;2
"Unit";"Zergling";"Larva";464;1
"Unit";"Zergling";"Larva";465;1
"Unit";"Zergling";"Larva";466;1
"Unit";"Zergling";"Larva";467;1
"Unit";"Zergling";"Larva";468;1
"Unit";"Zergling";"Larva";469;1
"Unit";"Zergling";"Larva";470;1
"Unit";"Zergling";"Larva";471;1
"Unit";"Zergling";"Larva";472;1
"Unit";"Zergling";"Larva";473;1
"Unit";"Zergling";"Larva";474;1
"Unit";"Zergling";"Larva";475;1
"Unit";"Zergling";"Larva";476;1
"Unit";"Zergling";"Larva";477;1
"Unit";"Baneling";"Zergling";478;0
"Unit";"Baneling";"Zergling";478;0
"Unit";"Baneling";"Zergling";478;0
"Unit";"Baneling";"Zergling";478;0
"Unit";"Baneling";"Zergling";478;0
"Building";"SpineCrawler";NA;478;0
"Unit";"Baneling";"Zergling";478;0
"Unit";"Baneling";"Zergling";478;0
"Unit";"Baneling";"Zergling";478;0
"Unit";"Baneling";"Zergling";478;0
"Unit";"Baneling";"Zergling";478;0
"Unit";"Baneling";"Zergling";478;0
"Unit";"Baneling";"Zergling";478;0
"Unit";"Baneling";"Zergling";478;0
"Unit";"Baneling";"Zergling";478;0
"Unit";"Baneling";"Zergling";478;0
"Unit";"Baneling";"Zergling";478;0
"Unit";"Baneling";"Zergling";478;0
"Unit";"Baneling";"Zergling";478;0
"Unit";"Baneling";"Zergling";478;0
"Unit";"Baneling";"Zergling";478;0
"Unit";"Baneling";"Zergling";478;0
"Unit";"Baneling";"Zergling";478;0
"Unit";"Baneling";"Zergling";478;0
"Unit";"Baneling";"Zergling";478;0
"Unit";"Baneling";"Zergling";478;0
"Unit";"Baneling";"Zergling";478;0
"Unit";"Baneling";"Zergling";478;0
"Unit";"Baneling";"Zergling";478;0
"Unit";"Baneling";"Zergling";478;0
"Unit";"Baneling";"Zergling";478;0
"Unit";"Baneling";"Zergling";478;0
"Unit";"Baneling";"Zergling";478;0
"Unit";"Baneling";"Zergling";478;0
"Unit";"Baneling";"Zergling";478;0
"Unit";"Baneling";"Zergling";478;0
"Unit";"Baneling";"Zergling";478;0
"Unit";"Baneling";"Zergling";478;0
"Unit";"Baneling";"Zergling";478;0
"Unit";"Baneling";"Zergling";478;0
"Unit";"Viper";"Larva";478;3
"Unit";"Viper";"Larva";481;3
"Unit";"Hydralisk";"Larva";484;2
"Unit";"Hydralisk";"Larva";486;2
"Unit";"Hydralisk";"Larva";488;2
"Unit";"Hydralisk";"Larva";490;2
"Unit";"Hydralisk";"Larva";492;2
"Unit";"Hydralisk";"Larva";494;2
"Unit";"Hydralisk";"Larva";496;2
"Unit";"Hydralisk";"Larva";498;2
"Unit";"Corruptor";"Larva";507;2
"Unit";"Corruptor";"Larva";509;2
"Unit";"Corruptor";"Larva";511;2
"Building";"CreepTumor";NA;513;0
"Unit";"Corruptor";"Larva";513;2
"Unit";"Corruptor";"Larva";515;2
"Unit";"Corruptor";"Larva";522;2
"Unit";"Corruptor";"Larva";524;2
"Unit";"Corruptor";"Larva";526;2
"Unit";"Corruptor";"Larva";528;2
"Unit";"Corruptor";"Larva";530;2
"Building";"CreepTumor";NA;532;0
"Building";"CreepTumor";NA;532;0
"Building";"Extractor";NA;532;0
"Building";"Spire";NA;532;0
"Building";"Extractor";NA;532;0
"Building";"CreepTumor";NA;537;0
"Building";"CreepTumor";NA;537;0
"Unit";"Corruptor";"Larva";537;2
"Building";"Hatchery";NA;539;0
"Unit";"Corruptor";"Larva";539;2
"Building";"Extractor";NA;541;0
"Building";"CreepTumor";NA;541;0
"Building";"CreepTumor";NA;541;0
"Building";"CreepTumor";NA;541;0
"Building";"CreepTumor";NA;541;0
"Building";"CreepTumor";NA;541;0
"Building";"SporeCrawler";NA;542;0
"Building";"CreepTumor";NA;542;0
"Building";"CreepTumor";NA;542;0
"Building";"CreepTumor";NA;542;0
"Unit";"Corruptor";"Larva";543;2
"Building";"CreepTumor";NA;545;0
"Unit";"Zergling";"Larva";545;1
"Unit";"Zergling";"Larva";546;1
"Unit";"Zergling";"Larva";547;1
"Unit";"Zergling";"Larva";548;1
"Unit";"Zergling";"Larva";549;1
"Unit";"Zergling";"Larva";550;1
"Unit";"Zergling";"Larva";551;1
"Unit";"Zergling";"Larva";552;1
"Unit";"Zergling";"Larva";553;1
"Unit";"Zergling";"Larva";554;1
"Unit";"Zergling";"Larva";555;1
"Unit";"Zergling";"Larva";556;1
"Unit";"Zergling";"Larva";557;1
"Unit";"Zergling";"Larva";558;1
"Unit";"Zergling";"Larva";559;1
"Unit";"Zergling";"Larva";560;1
"Unit";"Zergling";"Larva";561;1
"Unit";"Zergling";"Larva";562;1
"Unit";"Zergling";"Larva";563;1
"Unit";"Zergling";"Larva";564;1
"Unit";"Zergling";"Larva";565;1
"Unit";"Zergling";"Larva";566;1
"Unit";"Zergling";"Larva";567;1
"Unit";"Zergling";"Larva";568;1
"Unit";"Zergling";"Larva";569;1
"Unit";"Zergling";"Larva";570;1
"Unit";"Zergling";"Larva";571;1
"Unit";"Zergling";"Larva";572;1
"Unit";"Zergling";"Larva";573;1
"Unit";"Zergling";"Larva";574;1
"Unit";"Zergling";"Larva";575;1
"Unit";"Zergling";"Larva";576;1
"Unit";"Zergling";"Larva";577;1
"Unit";"Zergling";"Larva";578;1
"Building";"CreepTumor";NA;579;0
"Unit";"Baneling";"Zergling";584;0
"Unit";"Baneling";"Zergling";584;0
"Unit";"Baneling";"Zergling";584;0
"Unit";"Baneling";"Zergling";584;0
"Unit";"Baneling";"Zergling";584;0
"Unit";"Baneling";"Zergling";584;0
"Unit";"Baneling";"Zergling";584;0
"Unit";"Baneling";"Zergling";584;0
"Unit";"Baneling";"Zergling";584;0
"Unit";"Baneling";"Zergling";584;0
"Unit";"Baneling";"Zergling";584;0
"Unit";"Baneling";"Zergling";584;0
"Unit";"Baneling";"Zergling";584;0
"Unit";"Baneling";"Zergling";584;0
"Unit";"Baneling";"Zergling";584;0
"Unit";"Baneling";"Zergling";584;0
"Unit";"Baneling";"Zergling";584;0
"Unit";"Baneling";"Zergling";584;0
"Unit";"Baneling";"Zergling";584;0
"Unit";"Baneling";"Zergling";584;0
"Unit";"Baneling";"Zergling";584;0
"Unit";"Baneling";"Zergling";584;0
"Unit";"Baneling";"Zergling";584;0
"Unit";"Baneling";"Zergling";584;0
"Building";"CreepTumor";NA;584;0
"Unit";"Baneling";"Zergling";584;0
"Unit";"Baneling";"Zergling";584;0
"Unit";"Baneling";"Zergling";584;0
"Unit";"Baneling";"Zergling";584;0
"Unit";"Baneling";"Zergling";584;0
"Unit";"Baneling";"Zergling";584;0
"Unit";"Baneling";"Zergling";584;0
"Unit";"Baneling";"Zergling";584;0
"Building";"Hatchery";NA;584;0
"Building";"Hatchery";NA;584;0
"Building";"CreepTumor";NA;584;0
"Unit";"Hydralisk";"Larva";584;2
"Building";"CreepTumor";NA;586;0
"Building";"CreepTumor";NA;586;0
"Building";"CreepTumor";NA;586;0
"Unit";"Hydralisk";"Larva";586;2
"Unit";"Hydralisk";"Larva";588;2
"Unit";"Hydralisk";"Larva";590;2
"Unit";"Hydralisk";"Larva";592;2
"Unit";"Hydralisk";"Larva";594;2
"Unit";"Hydralisk";"Larva";596;2
"Unit";"Hydralisk";"Larva";598;2
"Unit";"Hydralisk";"Larva";600;2
"Unit";"Corruptor";"Larva";602;2
"Unit";"Corruptor";"Larva";604;2
"Unit";"Corruptor";"Larva";606;2
"Unit";"Corruptor";"Larva";608;2
"Unit";"Corruptor";"Larva";610;2
"Unit";"Hydralisk";"Larva";612;2
"Unit";"Hydralisk";"Larva";614;2
"Unit";"Hydralisk";"Larva";616;2
"Unit";"Hydralisk";"Larva";618;2
"Unit";"Hydralisk";"Larva";620;2
"Unit";"Hydralisk";"Larva";622;2
"Unit";"Hydralisk";"Larva";624;2
"Unit";"Hydralisk";"Larva";626;2
"Unit";"Hydralisk";"Larva";628;2
"Unit";"Hydralisk";"Larva";630;2
"Unit";"Zergling";"Larva";632;1
"Unit";"Zergling";"Larva";633;1
"Unit";"Zergling";"Larva";634;1
"Unit";"Zergling";"Larva";635;1
"Unit";"Zergling";"Larva";636;1
"Unit";"Zergling";"Larva";637;1
"Unit";"Zergling";"Larva";638;1
"Unit";"Zergling";"Larva";639;1
"Unit";"Zergling";"Larva";640;1
"Unit";"Zergling";"Larva";641;1
"Unit";"Zergling";"Larva";642;1
"Unit";"Zergling";"Larva";643;1
"Unit";"Zergling";"Larva";644;1
"Unit";"Zergling";"Larva";645;1
"Unit";"Zergling";"Larva";646;1
"Unit";"Zergling";"Larva";647;1
"Unit";"Zergling";"Larva";648;1
"Unit";"Zergling";"Larva";649;1
"Unit";"Hydralisk";"Larva";650;2
"Unit";"Hydralisk";"Larva";652;2
"Unit";"Hydralisk";"Larva";654;2
"Building";"SpineCrawler";NA;657;0
"Building";"SpineCrawler";NA;657;0
"Unit";"Hydralisk";"Larva";657;2
"Building";"Hatchery";NA;659;0
"Unit";"Hydralisk";"Larva";663;2
"Unit";"Hydralisk";"Larva";665;2
"Unit";"Hydralisk";"Larva";667;2
"Unit";"Zergling";"Larva";669;1
"Unit";"Zergling";"Larva";670;1
"Unit";"Zergling";"Larva";671;1
"Unit";"Zergling";"Larva";672;1
"Unit";"Zergling";"Larva";673;1
"Unit";"Zergling";"Larva";674;1
"Unit";"Zergling";"Larva";675;1
"Unit";"Zergling";"Larva";676;1
"Unit";"Zergling";"Larva";677;1
"Unit";"Zergling";"Larva";678;1
"Unit";"Zergling";"Larva";679;1
"Unit";"Zergling";"Larva";680;1
"Unit";"Zergling";"Larva";681;1
"Unit";"Zergling";"Larva";682;1
"Unit";"Zergling";"Larva";683;1
"Unit";"Zergling";"Larva";684;1
"Unit";"Hydralisk";"Larva";685;2
"Unit";"Hydralisk";"Larva";687;2
"Unit";"Hydralisk";"Larva";689;2
"Unit";"Zergling";"Larva";691;1
"Unit";"Zergling";"Larva";692;1
"Unit";"Zergling";"Larva";693;1
"Unit";"Zergling";"Larva";694;1
"Unit";"Zergling";"Larva";695;1
"Unit";"Zergling";"Larva";696;1
"Unit";"Zergling";"Larva";697;1
"Unit";"Zergling";"Larva";698;1
"Unit";"Zergling";"Larva";699;1
"Unit";"Zergling";"Larva";700;1
"Unit";"Zergling";"Larva";701;1
"Unit";"Zergling";"Larva";702;1
"Unit";"Zergling";"Larva";703;1
"Unit";"Zergling";"Larva";704;1
"Unit";"Zergling";"Larva";705;1
"Unit";"Zergling";"Larva";706;1
"Unit";"Zergling";"Larva";707;1
"Unit";"Zergling";"Larva";708;1
"Unit";"Zergling";"Larva";709;1
"Unit";"Zergling";"Larva";710;1
"Unit";"Zergling";"Larva";711;1
"Unit";"Zergling";"Larva";712;1
"Unit";"Zergling";"Larva";713;1
"Unit";"Zergling";"Larva";714;1
"Unit";"Baneling";"Zergling";715;0
"Unit";"Baneling";"Zergling";715;0
"Unit";"Baneling";"Zergling";715;0
"Unit";"Baneling";"Zergling";715;0
"Unit";"Baneling";"Zergling";715;0
"Unit";"Baneling";"Zergling";715;0
"Unit";"Baneling";"Zergling";715;0
"Unit";"Baneling";"Zergling";715;0
"Unit";"Baneling";"Zergling";715;0
"Unit";"Baneling";"Zergling";715;0
"Unit";"Baneling";"Zergling";715;0
"Unit";"Baneling";"Zergling";715;0
"Unit";"Baneling";"Zergling";715;0
"Unit";"Baneling";"Zergling";715;0
"Unit";"Baneling";"Zergling";715;0
"Unit";"Baneling";"Zergling";715;0
"Unit";"Baneling";"Zergling";715;0
"Unit";"Baneling";"Zergling";715;0
"Unit";"Baneling";"Zergling";715;0
"Unit";"Baneling";"Zergling";715;0
"Unit";"Baneling";"Zergling";715;0
"Unit";"Baneling";"Zergling";715;0
"Unit";"Baneling";"Zergling";715;0
"Unit";"Baneling";"Zergling";715;0
"Unit";"Baneling";"Zergling";715;0
"Unit";"Baneling";"Zergling";715;0
"Unit";"Baneling";"Zergling";715;0
"Unit";"Baneling";"Zergling";715;0
"Unit";"Baneling";"Zergling";715;0
"Unit";"Baneling";"Zergling";715;0
"Unit";"Baneling";"Zergling";715;0
"Unit";"Baneling";"Zergling";715;0
"Unit";"Baneling";"Zergling";715;0
"Unit";"Baneling";"Zergling";715;0
"Unit";"Zergling";"Larva";715;1
"Unit";"Zergling";"Larva";716;1
"Unit";"Zergling";"Larva";717;1
"Unit";"Zergling";"Larva";718;1
"Unit";"Zergling";"Larva";719;1
"Unit";"Zergling";"Larva";720;1
"Unit";"Zergling";"Larva";721;1
"Unit";"Zergling";"Larva";722;1
"Unit";"Zergling";"Larva";723;1
"Unit";"Zergling";"Larva";724;1
"Unit";"Zergling";"Larva";725;1
"Unit";"Zergling";"Larva";726;1
"Unit";"Zergling";"Larva";727;1
"Unit";"Zergling";"Larva";728;1
"Unit";"Zergling";"Larva";729;1
"Unit";"Zergling";"Larva";730;1
"Unit";"Zergling";"Larva";731;1
"Unit";"Zergling";"Larva";732;1
"Unit";"Zergling";"Larva";733;1
"Unit";"Zergling";"Larva";734;1
"Unit";"Zergling";"Larva";735;1
"Unit";"Zergling";"Larva";736;1
"Unit";"Zergling";"Larva";737;1
"Unit";"Zergling";"Larva";738;1
"Unit";"Zergling";"Larva";739;1
"Unit";"Zergling";"Larva";740;1
"Unit";"Zergling";"Larva";741;1
"Unit";"Zergling";"Larva";742;1
"Unit";"Zergling";"Larva";743;1
"Unit";"Zergling";"Larva";744;1
"Unit";"Zergling";"Larva";745;1
"Unit";"Zergling";"Larva";746;1
"Unit";"Zergling";"Larva";747;1
"Unit";"Zergling";"Larva";748;1
"Unit";"Zergling";"Larva";749;1
"Unit";"Zergling";"Larva";750;1
"Unit";"Zergling";"Larva";751;1
"Unit";"Zergling";"Larva";752;1
"Unit";"Zergling";"Larva";753;1
"Unit";"Zergling";"Larva";754;1
"Unit";"Zergling";"Larva";755;1
"Unit";"Zergling";"Larva";756;1
"Unit";"Zergling";"Larva";757;1
"Unit";"Zergling";"Larva";758;1
"Unit";"Baneling";"Zergling";759;0
"Unit";"Baneling";"Zergling";759;0
"Unit";"Baneling";"Zergling";759;0
"Unit";"Baneling";"Zergling";759;0
"Unit";"Baneling";"Zergling";759;0
"Unit";"Baneling";"Zergling";759;0
"Unit";"Baneling";"Zergling";759;0
"Unit";"Baneling";"Zergling";759;0
"Unit";"Mutalisk";"Larva";759;2
"Unit";"Mutalisk";"Larva";761;2
"Unit";"Mutalisk";"Larva";763;2
"Unit";"Mutalisk";"Larva";765;2
"Unit";"Mutalisk";"Larva";767;2
"Unit";"Mutalisk";"Larva";769;2
"Unit";"Mutalisk";"Larva";771;2
"Unit";"Mutalisk";"Larva";773;2
"Unit";"Mutalisk";"Larva";775;2
"Unit";"Mutalisk";"Larva";777;2
"Unit";"Mutalisk";"Larva";779;2
"Unit";"Mutalisk";"Larva";781;2
"Unit";"Mutalisk";"Larva";783;2
"Unit";"Mutalisk";"Larva";785;2
"Unit";"Mutalisk";"Larva";787;2
"Unit";"Mutalisk";"Larva";789;2
"Unit";"Mutalisk";"Larva";791;2
"Unit";"Mutalisk";"Larva";793;2
"Unit";"Mutalisk";"Larva";795;2
"Unit";"Mutalisk";"Larva";797;2
"Unit";"Mutalisk";"Larva";799;2
"Unit";"Mutalisk";"Larva";801;2
"Unit";"Zergling";"Larva";803;1
"Unit";"Zergling";"Larva";804;1
"Unit";"Zergling";"Larva";805;1
"Unit";"Zergling";"Larva";806;1
"Unit";"Zergling";"Larva";807;1
"Unit";"Zergling";"Larva";808;1
"Unit";"Zergling";"Larva";809;1
"Unit";"Zergling";"Larva";810;1
"Unit";"Zergling";"Larva";811;1
"Unit";"Zergling";"Larva";812;1
"Unit";"Zergling";"Larva";813;1
"Unit";"Zergling";"Larva";814;1
"Unit";"Zergling";"Larva";815;1
"Unit";"Zergling";"Larva";816;1
"Building";"CreepTumorQueen";NA;817;0
"Building";"CreepTumorQueen";NA;817;0
"Building";"CreepTumorQueen";NA;817;0
"Upgrade";"SprayZerg";NA;817;0
"Upgrade";"SprayZerg";NA;817;0
"Upgrade";"SprayZerg";NA;817;0
"Upgrade";"zerglingmovementspeed";NA;817;0
"Upgrade";"SprayZerg";NA;817;0
"Upgrade";"SprayZerg";NA;817;0
"Upgrade";"EvolveMuscularAugments";NA;817;0
"Upgrade";"ZergMissileWeaponsLevel1";NA;817;0
"Upgrade";"ZergGroundArmorsLevel1";NA;817;0
"Upgrade";"CentrificalHooks";NA;817;0
"Upgrade";"SprayZerg";NA;817;0
"Upgrade";"SprayZerg";NA;817;0
"Upgrade";"ZergMissileWeaponsLevel2";NA;817;0
"Upgrade";"ZergGroundArmorsLevel2";NA;817;0
"Upgrade";"SprayZerg";NA;817;0
"Upgrade";"ZergMeleeWeaponsLevel1";NA;817;0
"Upgrade";"SprayZerg";NA;817;0
"Upgrade";"SprayZerg";NA;817;0
"Upgrade";"ZergMissileWeaponsLevel3";NA;817;0
"Upgrade";"ZergGroundArmorsLevel3";NA;817;0
"Upgrade";"SprayZerg";NA;817;0
"Upgrade";"ZergMeleeWeaponsLevel2";NA;817;0
"Upgrade";"SprayZerg";NA;817;0
"Upgrade";"ZergFlyerWeaponsLevel1";NA;817;0
"Upgrade";"SprayZerg";NA;817;0
"Upgrade";"SprayZerg";NA;817;0
"Upgrade";"SprayZerg";NA;817;0
"Upgrade";"SprayZerg";NA;817;0
"Upgrade";"ZergFlyerWeaponsLevel2";NA;817;0
"Upgrade";"ZergFlyerArmorsLevel1";NA;817;0
"Upgrade";"SprayZerg";NA;817;0
"Upgrade";"SprayZerg";NA;817;0
"Upgrade";"SprayZerg";NA;817;0
"Upgrade";"ZergFlyerWeaponsLevel3";NA;817;0
"Upgrade";"ZergFlyerArmorsLevel2";NA;817;0
"Upgrade";"SprayZerg";NA;817;0
"Upgrade";"SprayZerg";NA;817;0
