"type";"unit_name";"on_building";"total_supply_lag";"supply"
"Unit";"Overlord";"Larva";14;0
"Building";"SpawningPool";NA;14;0
"Building";"Hatchery";NA;18;0
"Unit";"Zergling";"Larva";19;1
"Unit";"Zergling";"Larva";20;1
"Unit";"Zergling";"Larva";21;1
"Unit";"Zergling";"Larva";22;1
"Unit";"Queen";"Hatchery";23;2
"Unit";"Overlord";"Larva";25;0
"Building";"Extractor";NA;25;0
"Unit";"Queen";"Hatchery";28;2
"Unit";"Zergling";"Larva";31;1
"Unit";"Zergling";"Larva";32;1
"Unit";"Zergling";"Larva";33;1
"Unit";"Zergling";"Larva";34;1
"Unit";"Zergling";"Larva";35;1
"Unit";"Zergling";"Larva";36;1
"Unit";"Zergling";"Larva";37;1
"Unit";"Zergling";"Larva";38;1
"Unit";"Zergling";"Larva";39;1
"Unit";"Zergling";"Larva";40;1
"Unit";"Zergling";"Larva";41;1
"Unit";"Zergling";"Larva";42;1
"Unit";"Queen";"Hatchery";47;2
"Unit";"Overlord";"Larva";49;0
"Unit";"Overlord";"Larva";52;0
"Building";"EvolutionChamber";NA;62;0
"Building";"RoachWarren";NA;62;0
"Building";"Spire";NA;62;0
"Building";"SpineCrawler";NA;62;0
"Building";"EvolutionChamber";NA;70;0
"Unit";"Queen";"Hatchery";70;2
"Unit";"Queen";"Hatchery";72;2
"Building";"Extractor";NA;74;0
"Building";"Extractor";NA;74;0
"Unit";"Overlord";"Larva";74;0
"Building";"Extractor";NA;78;0
"Unit";"Mutalisk";"Larva";80;2
"Unit";"Mutalisk";"Larva";82;2
"Unit";"Mutalisk";"Larva";84;2
"Building";"CreepTumorQueen";NA;86;0
"Unit";"Overlord";"Larva";86;0
"Unit";"Mutalisk";"Larva";90;2
"Unit";"Mutalisk";"Larva";96;2
"Unit";"Mutalisk";"Larva";98;2
"Building";"Hatchery";NA;100;0
"Building";"CreepTumor";NA;102;0
"Building";"CreepTumorQueen";NA;102;0
"Unit";"Overlord";"Larva";102;0
"Building";"HydraliskDen";NA;102;0
"Unit";"Overlord";"Larva";107;0
"Unit";"Overlord";"Larva";107;0
"Building";"CreepTumor";NA;107;0
"Building";"CreepTumorQueen";NA;107;0
"Building";"SpineCrawler";NA;107;0
"Building";"CreepTumor";NA;107;0
"Building";"SpineCrawler";NA;107;0
"Building";"Extractor";NA;112;0
"Building";"Extractor";NA;112;0
"Unit";"Hydralisk";"Larva";112;2
"Unit";"Hydralisk";"Larva";114;2
"Unit";"Hydralisk";"Larva";116;2
"Unit";"Hydralisk";"Larva";118;2
"Unit";"Hydralisk";"Larva";120;2
"Building";"CreepTumor";NA;126;0
"Building";"CreepTumor";NA;126;0
"Building";"CreepTumorQueen";NA;126;0
"Unit";"Hydralisk";"Larva";126;2
"Unit";"Hydralisk";"Larva";128;2
"Unit";"Hydralisk";"Larva";130;2
"Unit";"Hydralisk";"Larva";132;2
"Unit";"Hydralisk";"Larva";134;2
"Building";"CreepTumor";NA;136;0
"Unit";"Overlord";"Larva";136;0
"Building";"CreepTumor";NA;136;0
"Building";"CreepTumor";NA;136;0
"Building";"CreepTumorQueen";NA;136;0
"Unit";"Overlord";"Larva";142;0
"Unit";"Overlord";"Larva";142;0
"Unit";"Overlord";"Larva";142;0
"Building";"CreepTumor";NA;142;0
"Building";"CreepTumor";NA;142;0
"Building";"CreepTumorQueen";NA;142;0
"Unit";"Overlord";"Larva";148;0
"Building";"Hatchery";NA;148;0
"Building";"SpineCrawler";NA;150;0
"Building";"SpineCrawler";NA;150;0
"Building";"CreepTumor";NA;150;0
"Unit";"Overlord";"Larva";150;0
"Unit";"Overlord";"Larva";150;0
"Unit";"Overlord";"Larva";150;0
"Unit";"Overlord";"Larva";150;0
"Unit";"Mutalisk";"Larva";150;2
"Unit";"Mutalisk";"Larva";152;2
"Unit";"Mutalisk";"Larva";154;2
"Unit";"Overlord";"Larva";156;0
"Unit";"Mutalisk";"Larva";156;2
"Unit";"Mutalisk";"Larva";158;2
"Unit";"Overlord";"Larva";160;0
"Building";"SpineCrawler";NA;160;0
"Building";"SpineCrawler";NA;160;0
"Building";"Hatchery";NA;160;0
"Unit";"Mutalisk";"Larva";160;2
"Unit";"Mutalisk";"Larva";162;2
"Unit";"Mutalisk";"Larva";164;2
"Building";"SpineCrawler";NA;166;0
"Unit";"Queen";"Hatchery";166;2
"Building";"SpineCrawler";NA;168;0
"Building";"SpineCrawler";NA;168;0
"Building";"SporeCrawler";NA;168;0
"Building";"SporeCrawler";NA;168;0
"Unit";"Mutalisk";"Larva";168;2
"Unit";"Mutalisk";"Larva";170;2
"Unit";"Zergling";"Larva";172;1
"Unit";"Zergling";"Larva";173;1
"Unit";"Zergling";"Larva";174;1
"Unit";"Zergling";"Larva";175;1
"Unit";"Zergling";"Larva";176;1
"Unit";"Zergling";"Larva";177;1
"Unit";"Zergling";"Larva";178;1
"Unit";"Zergling";"Larva";179;1
"Unit";"Zergling";"Larva";180;1
"Unit";"Zergling";"Larva";181;1
"Unit";"Zergling";"Larva";182;1
"Unit";"Zergling";"Larva";183;1
"Unit";"Zergling";"Larva";184;1
"Unit";"Zergling";"Larva";185;1
"Unit";"Zergling";"Larva";186;1
"Unit";"Zergling";"Larva";187;1
"Unit";"Zergling";"Larva";188;1
"Unit";"Zergling";"Larva";189;1
"Unit";"Zergling";"Larva";190;1
"Unit";"Zergling";"Larva";191;1
"Unit";"Mutalisk";"Larva";192;2
"Unit";"Overlord";"Larva";194;0
"Unit";"Overlord";"Larva";194;0
"Building";"InfestationPit";NA;194;0
"Unit";"Zergling";"Larva";194;1
"Unit";"Zergling";"Larva";195;1
"Unit";"Zergling";"Larva";196;1
"Unit";"Zergling";"Larva";197;1
"Unit";"Zergling";"Larva";198;1
"Unit";"Zergling";"Larva";199;1
"Unit";"Zergling";"Larva";200;1
"Unit";"Zergling";"Larva";201;1
"Unit";"Zergling";"Larva";202;1
"Unit";"Zergling";"Larva";203;1
"Unit";"Zergling";"Larva";204;1
"Unit";"Zergling";"Larva";205;1
"Unit";"Zergling";"Larva";206;1
"Unit";"Zergling";"Larva";207;1
"Unit";"Mutalisk";"Larva";208;2
"Unit";"Mutalisk";"Larva";210;2
"Unit";"Zergling";"Larva";212;1
"Unit";"Zergling";"Larva";213;1
"Unit";"Zergling";"Larva";214;1
"Unit";"Zergling";"Larva";215;1
"Unit";"Zergling";"Larva";216;1
"Unit";"Zergling";"Larva";217;1
"Unit";"Overlord";"Larva";218;0
"Unit";"Mutalisk";"Larva";218;2
"Unit";"Mutalisk";"Larva";220;2
"Unit";"Overlord";"Larva";222;0
"Unit";"Mutalisk";"Larva";222;2
"Unit";"Mutalisk";"Larva";224;2
"Unit";"Mutalisk";"Larva";226;2
"Unit";"Mutalisk";"Larva";228;2
"Unit";"Overlord";"Larva";230;0
"Unit";"Overlord";"Larva";230;0
"Unit";"Overlord";"Larva";234;0
"Unit";"Zergling";"Larva";234;1
"Unit";"Zergling";"Larva";235;1
"Unit";"Zergling";"Larva";236;1
"Unit";"Zergling";"Larva";237;1
"Unit";"Zergling";"Larva";238;1
"Unit";"Zergling";"Larva";239;1
"Unit";"Zergling";"Larva";240;1
"Unit";"Zergling";"Larva";241;1
"Unit";"Zergling";"Larva";242;1
"Unit";"Zergling";"Larva";243;1
"Unit";"Overlord";"Larva";244;0
"Unit";"Hydralisk";"Larva";244;2
"Unit";"Hydralisk";"Larva";246;2
"Unit";"Hydralisk";"Larva";248;2
"Unit";"Mutalisk";"Larva";250;2
"Unit";"Mutalisk";"Larva";252;2
"Unit";"Mutalisk";"Larva";254;2
"Unit";"Mutalisk";"Larva";256;2
"Unit";"Mutalisk";"Larva";258;2
"Unit";"Mutalisk";"Larva";260;2
"Unit";"Mutalisk";"Larva";262;2
"Unit";"Mutalisk";"Larva";264;2
"Unit";"Mutalisk";"Larva";266;2
"Unit";"Mutalisk";"Larva";268;2
"Unit";"Mutalisk";"Larva";270;2
"Unit";"Mutalisk";"Larva";272;2
"Unit";"Overlord";"Larva";274;0
"Unit";"Overlord";"Larva";281;0
"Unit";"Overlord";"Larva";281;0
"Unit";"Overlord";"Larva";281;0
"Unit";"Hydralisk";"Larva";281;2
"Unit";"Hydralisk";"Larva";283;2
"Unit";"Hydralisk";"Larva";285;2
"Unit";"Hydralisk";"Larva";287;2
"Building";"Hatchery";NA;289;0
"Building";"CreepTumorQueen";NA;289;0
"Unit";"Corruptor";"Larva";289;2
"Unit";"Corruptor";"Larva";291;2
"Building";"CreepTumorQueen";NA;293;0
"Building";"CreepTumorQueen";NA;293;0
"Unit";"Corruptor";"Larva";293;2
"Unit";"Corruptor";"Larva";295;2
"Unit";"Corruptor";"Larva";297;2
"Unit";"Corruptor";"Larva";299;2
"Building";"CreepTumor";NA;301;0
"Building";"CreepTumor";NA;301;0
"Building";"CreepTumorQueen";NA;301;0
"Building";"CreepTumorQueen";NA;301;0
"Building";"Extractor";NA;301;0
"Building";"CreepTumorQueen";NA;301;0
"Building";"CreepTumorQueen";NA;301;0
"Building";"Hatchery";NA;301;0
"Building";"Hatchery";NA;301;0
"Building";"Extractor";NA;301;0
"Building";"Extractor";NA;301;0
"Building";"CreepTumor";NA;311;0
"Building";"CreepTumor";NA;311;0
"Building";"CreepTumor";NA;311;0
"Building";"CreepTumor";NA;311;0
"Building";"CreepTumorQueen";NA;311;0
"Building";"CreepTumorQueen";NA;311;0
"Building";"CreepTumor";NA;311;0
"Building";"CreepTumorQueen";NA;311;0
"Building";"CreepTumorQueen";NA;311;0
"Building";"SporeCrawler";NA;311;0
"Unit";"Corruptor";"Larva";311;2
"Unit";"Corruptor";"Larva";313;2
"Unit";"Corruptor";"Larva";315;2
"Building";"CreepTumorQueen";NA;317;0
"Building";"CreepTumorQueen";NA;317;0
"Building";"CreepTumorQueen";NA;317;0
"Building";"CreepTumorQueen";NA;317;0
"Building";"Extractor";NA;331;0
"Building";"SpineCrawler";NA;331;0
"Building";"Extractor";NA;331;0
"Building";"SpineCrawler";NA;331;0
"Building";"CreepTumorQueen";NA;331;0
"Building";"CreepTumorQueen";NA;331;0
"Unit";"Corruptor";"Larva";331;2
"Unit";"Corruptor";"Larva";333;2
"Unit";"Corruptor";"Larva";335;2
"Unit";"Corruptor";"Larva";337;2
"Building";"CreepTumor";NA;339;0
"Building";"CreepTumor";NA;339;0
"Building";"CreepTumor";NA;339;0
"Building";"CreepTumor";NA;339;0
"Building";"CreepTumor";NA;339;0
"Building";"Hatchery";NA;339;0
"Building";"CreepTumorQueen";NA;339;0
"Building";"CreepTumorQueen";NA;339;0
"Building";"CreepTumor";NA;345;0
"Building";"SporeCrawler";NA;345;0
"Building";"SporeCrawler";NA;345;0
"Building";"SporeCrawler";NA;345;0
"Building";"SporeCrawler";NA;345;0
"Unit";"Corruptor";"Larva";345;2
"Unit";"Corruptor";"Larva";347;2
"Unit";"Corruptor";"Larva";349;2
"Unit";"Zergling";"Larva";351;1
"Unit";"Zergling";"Larva";352;1
"Unit";"Zergling";"Larva";353;1
"Unit";"Zergling";"Larva";354;1
"Unit";"Zergling";"Larva";355;1
"Unit";"Zergling";"Larva";356;1
"Unit";"Zergling";"Larva";357;1
"Unit";"Zergling";"Larva";358;1
"Unit";"Zergling";"Larva";359;1
"Unit";"Zergling";"Larva";360;1
"Unit";"Zergling";"Larva";361;1
"Unit";"Zergling";"Larva";362;1
"Unit";"Zergling";"Larva";363;1
"Unit";"Zergling";"Larva";364;1
"Unit";"Zergling";"Larva";365;1
"Unit";"Zergling";"Larva";366;1
"Unit";"Zergling";"Larva";367;1
"Unit";"Zergling";"Larva";368;1
"Unit";"Zergling";"Larva";369;1
"Unit";"Zergling";"Larva";370;1
"Unit";"Zergling";"Larva";371;1
"Unit";"Zergling";"Larva";372;1
"Unit";"Hydralisk";"Larva";373;2
"Unit";"Hydralisk";"Larva";375;2
"Unit";"Hydralisk";"Larva";377;2
"Unit";"Hydralisk";"Larva";379;2
"Unit";"Hydralisk";"Larva";381;2
"Unit";"Hydralisk";"Larva";383;2
"Unit";"Hydralisk";"Larva";385;2
"Building";"CreepTumor";NA;387;0
"Building";"CreepTumor";NA;387;0
"Building";"CreepTumor";NA;387;0
"Building";"CreepTumor";NA;387;0
"Building";"CreepTumor";NA;387;0
"Building";"CreepTumor";NA;387;0
"Unit";"Corruptor";"Larva";387;2
"Unit";"Corruptor";"Larva";389;2
"Unit";"Corruptor";"Larva";391;2
"Unit";"Corruptor";"Larva";393;2
"Unit";"Corruptor";"Larva";395;2
"Unit";"Mutalisk";"Larva";397;2
"Unit";"Mutalisk";"Larva";399;2
"Unit";"Mutalisk";"Larva";401;2
"Unit";"Mutalisk";"Larva";403;2
"Unit";"Mutalisk";"Larva";405;2
"Building";"SporeCrawler";NA;418;0
"Building";"Extractor";NA;418;0
"Building";"SporeCrawler";NA;418;0
"Building";"SporeCrawler";NA;418;0
"Building";"Extractor";NA;418;0
"Building";"SporeCrawler";NA;418;0
"Building";"SporeCrawler";NA;418;0
"Unit";"Mutalisk";"Larva";418;2
"Building";"SporeCrawler";NA;420;0
"Building";"SporeCrawler";NA;420;0
"Unit";"Mutalisk";"Larva";420;2
"Unit";"Mutalisk";"Larva";422;2
"Unit";"Mutalisk";"Larva";424;2
"Building";"SporeCrawler";NA;426;0
"Building";"SporeCrawler";NA;426;0
"Building";"SporeCrawler";NA;426;0
"Building";"CreepTumorQueen";NA;426;0
"Unit";"Mutalisk";"Larva";426;2
"Building";"CreepTumorQueen";NA;428;0
"Building";"SporeCrawler";NA;428;0
"Unit";"Zergling";"Larva";428;1
"Unit";"Zergling";"Larva";429;1
"Unit";"Zergling";"Larva";430;1
"Unit";"Zergling";"Larva";431;1
"Unit";"Zergling";"Larva";432;1
"Unit";"Zergling";"Larva";433;1
"Unit";"Zergling";"Larva";434;1
"Unit";"Zergling";"Larva";435;1
"Unit";"Infestor";"Larva";436;2
"Unit";"Infestor";"Larva";438;2
"Building";"SporeCrawler";NA;441;0
"Building";"SporeCrawler";NA;441;0
"Unit";"Infestor";"Larva";441;2
"Building";"SporeCrawler";NA;443;0
"Unit";"Infestor";"Larva";443;2
"Unit";"Infestor";"Larva";445;2
"Building";"SporeCrawler";NA;447;0
"Unit";"Zergling";"Larva";447;1
"Unit";"Zergling";"Larva";448;1
"Unit";"Zergling";"Larva";449;1
"Unit";"Zergling";"Larva";450;1
"Unit";"Zergling";"Larva";451;1
"Unit";"Zergling";"Larva";452;1
"Unit";"Zergling";"Larva";453;1
"Unit";"Zergling";"Larva";454;1
"Building";"Hatchery";NA;455;0
"Building";"SporeCrawler";NA;455;0
"Unit";"Infestor";"Larva";455;2
"Unit";"Infestor";"Larva";457;2
"Unit";"Infestor";"Larva";459;2
"Upgrade";"Burrow";"Hatchery";470;0
"Unit";"Mutalisk";"Larva";470;2
"Unit";"Zergling";"Larva";477;1
"Unit";"Zergling";"Larva";478;1
"Unit";"Zergling";"Larva";479;1
"Unit";"Zergling";"Larva";480;1
"Unit";"Corruptor";"Larva";481;2
"Unit";"Hydralisk";"Larva";493;2
"Unit";"Hydralisk";"Larva";495;2
"Unit";"Hydralisk";"Larva";497;2
"Unit";"Hydralisk";"Larva";499;2
"Unit";"Hydralisk";"Larva";506;2
"Unit";"Hydralisk";"Larva";508;2
"Unit";"Hydralisk";"Larva";510;2
"Unit";"Hydralisk";"Larva";512;2
"Unit";"Hydralisk";"Larva";514;2
"Unit";"Hydralisk";"Larva";523;2
"Unit";"Hydralisk";"Larva";525;2
"Unit";"Zergling";"Larva";535;1
"Unit";"Zergling";"Larva";536;1
"Unit";"Zergling";"Larva";537;1
"Unit";"Zergling";"Larva";538;1
"Unit";"Zergling";"Larva";539;1
"Unit";"Zergling";"Larva";540;1
"Unit";"Zergling";"Larva";541;1
"Unit";"Zergling";"Larva";542;1
"Unit";"Zergling";"Larva";543;1
"Unit";"Zergling";"Larva";544;1
"Unit";"Zergling";"Larva";545;1
"Unit";"Zergling";"Larva";546;1
"Unit";"Zergling";"Larva";547;1
"Unit";"Zergling";"Larva";548;1
"Unit";"Zergling";"Larva";549;1
"Unit";"Zergling";"Larva";550;1
"Unit";"Zergling";"Larva";551;1
"Unit";"Zergling";"Larva";552;1
"Unit";"Zergling";"Larva";553;1
"Unit";"Zergling";"Larva";554;1
"Building";"Extractor";NA;555;0
"Building";"SpineCrawler";NA;555;0
"Building";"SpineCrawler";NA;555;0
"Unit";"Hydralisk";"Larva";555;2
"Unit";"Hydralisk";"Larva";557;2
"Unit";"Hydralisk";"Larva";559;2
"Unit";"Hydralisk";"Larva";561;2
"Unit";"Hydralisk";"Larva";563;2
"Unit";"Hydralisk";"Larva";565;2
"Unit";"Hydralisk";"Larva";567;2
"Building";"SporeCrawler";NA;578;0
"Building";"SporeCrawler";NA;578;0
"Building";"Hatchery";NA;583;0
"Building";"Extractor";NA;583;0
"Unit";"Zergling";"Larva";583;1
"Unit";"Zergling";"Larva";584;1
"Unit";"Zergling";"Larva";585;1
"Unit";"Zergling";"Larva";586;1
"Unit";"Zergling";"Larva";587;1
"Unit";"Zergling";"Larva";588;1
"Unit";"Zergling";"Larva";589;1
"Unit";"Zergling";"Larva";590;1
"Unit";"Zergling";"Larva";591;1
"Unit";"Zergling";"Larva";592;1
"Unit";"Zergling";"Larva";593;1
"Unit";"Zergling";"Larva";594;1
"Unit";"Zergling";"Larva";595;1
"Unit";"Zergling";"Larva";596;1
"Unit";"Zergling";"Larva";597;1
"Unit";"Zergling";"Larva";598;1
"Unit";"Zergling";"Larva";599;1
"Unit";"Zergling";"Larva";600;1
"Unit";"Zergling";"Larva";601;1
"Unit";"Zergling";"Larva";602;1
"Unit";"Zergling";"Larva";603;1
"Unit";"Zergling";"Larva";604;1
"Unit";"Zergling";"Larva";605;1
"Unit";"Zergling";"Larva";606;1
"Unit";"Zergling";"Larva";607;1
"Unit";"Zergling";"Larva";608;1
"Unit";"Zergling";"Larva";609;1
"Unit";"Zergling";"Larva";610;1
"Unit";"Zergling";"Larva";611;1
"Unit";"Zergling";"Larva";612;1
"Unit";"Zergling";"Larva";613;1
"Unit";"Zergling";"Larva";614;1
"Unit";"Zergling";"Larva";615;1
"Unit";"Zergling";"Larva";616;1
"Building";"SpineCrawler";NA;617;0
"Unit";"Hydralisk";"Larva";617;2
"Unit";"Hydralisk";"Larva";619;2
"Unit";"Hydralisk";"Larva";621;2
"Unit";"Hydralisk";"Larva";623;2
"Unit";"Hydralisk";"Larva";625;2
"Unit";"Hydralisk";"Larva";627;2
"Unit";"Hydralisk";"Larva";629;2
"Unit";"Hydralisk";"Larva";631;2
"Unit";"Hydralisk";"Larva";633;2
"Unit";"Hydralisk";"Larva";635;2
"Unit";"Hydralisk";"Larva";637;2
"Unit";"Hydralisk";"Larva";639;2
"Unit";"Hydralisk";"Larva";641;2
"Unit";"Hydralisk";"Larva";643;2
"Unit";"Hydralisk";"Larva";645;2
"Unit";"Hydralisk";"Larva";647;2
"Unit";"Hydralisk";"Larva";649;2
"Unit";"Hydralisk";"Larva";651;2
"Unit";"Hydralisk";"Larva";653;2
"Unit";"Hydralisk";"Larva";655;2
"Unit";"Hydralisk";"Larva";657;2
"Unit";"Hydralisk";"Larva";659;2
"Unit";"Zergling";"Larva";661;1
"Unit";"Zergling";"Larva";662;1
"Unit";"Zergling";"Larva";663;1
"Unit";"Zergling";"Larva";664;1
"Unit";"Zergling";"Larva";665;1
"Unit";"Zergling";"Larva";666;1
"Unit";"Zergling";"Larva";667;1
"Unit";"Zergling";"Larva";668;1
"Unit";"Zergling";"Larva";669;1
"Unit";"Zergling";"Larva";670;1
"Unit";"Zergling";"Larva";671;1
"Unit";"Zergling";"Larva";672;1
"Unit";"Zergling";"Larva";673;1
"Unit";"Zergling";"Larva";674;1
"Unit";"Zergling";"Larva";675;1
"Unit";"Zergling";"Larva";676;1
"Unit";"Zergling";"Larva";677;1
"Unit";"Zergling";"Larva";678;1
"Unit";"Zergling";"Larva";679;1
"Unit";"Zergling";"Larva";680;1
"Unit";"Zergling";"Larva";681;1
"Unit";"Zergling";"Larva";682;1
"Unit";"Zergling";"Larva";683;1
"Unit";"Zergling";"Larva";684;1
"Unit";"Zergling";"Larva";685;1
"Unit";"Zergling";"Larva";686;1
"Unit";"Zergling";"Larva";687;1
"Unit";"Zergling";"Larva";688;1
"Unit";"Zergling";"Larva";689;1
"Unit";"Zergling";"Larva";690;1
"Unit";"Zergling";"Larva";691;1
"Unit";"Zergling";"Larva";692;1
"Unit";"Zergling";"Larva";693;1
"Unit";"Zergling";"Larva";694;1
"Unit";"Zergling";"Larva";695;1
"Unit";"Zergling";"Larva";696;1
"Unit";"Zergling";"Larva";697;1
"Unit";"Zergling";"Larva";698;1
"Unit";"Zergling";"Larva";699;1
"Unit";"Zergling";"Larva";700;1
"Unit";"Zergling";"Larva";701;1
"Unit";"Zergling";"Larva";702;1
"Unit";"Zergling";"Larva";703;1
"Unit";"Zergling";"Larva";704;1
"Unit";"Zergling";"Larva";705;1
"Unit";"Zergling";"Larva";706;1
"Unit";"Zergling";"Larva";707;1
"Unit";"Zergling";"Larva";708;1
"Unit";"Zergling";"Larva";709;1
"Unit";"Zergling";"Larva";710;1
"Unit";"Zergling";"Larva";711;1
"Unit";"Zergling";"Larva";712;1
"Unit";"Zergling";"Larva";713;1
"Unit";"Zergling";"Larva";714;1
"Unit";"Zergling";"Larva";715;1
"Unit";"Zergling";"Larva";716;1
"Building";"Hatchery";NA;717;0
"Building";"BanelingNest";NA;717;0
"Unit";"Hydralisk";"Larva";717;2
"Unit";"Hydralisk";"Larva";719;2
"Unit";"Hydralisk";"Larva";721;2
"Unit";"Hydralisk";"Larva";723;2
"Unit";"Hydralisk";"Larva";725;2
"Unit";"Hydralisk";"Larva";727;2
"Unit";"Hydralisk";"Larva";729;2
"Unit";"Zergling";"Larva";731;1
"Unit";"Zergling";"Larva";732;1
"Unit";"Zergling";"Larva";733;1
"Unit";"Zergling";"Larva";734;1
"Unit";"Zergling";"Larva";735;1
"Unit";"Zergling";"Larva";736;1
"Unit";"Zergling";"Larva";737;1
"Unit";"Zergling";"Larva";738;1
"Unit";"Zergling";"Larva";739;1
"Unit";"Zergling";"Larva";740;1
"Unit";"Zergling";"Larva";741;1
"Unit";"Zergling";"Larva";742;1
"Unit";"Zergling";"Larva";743;1
"Unit";"Zergling";"Larva";744;1
"Unit";"Zergling";"Larva";745;1
"Unit";"Zergling";"Larva";746;1
"Unit";"Zergling";"Larva";747;1
"Unit";"Zergling";"Larva";748;1
"Building";"CreepTumor";NA;752;0
"Unit";"Hydralisk";"Larva";752;2
"Unit";"Hydralisk";"Larva";754;2
"Unit";"Hydralisk";"Larva";756;2
"Unit";"Hydralisk";"Larva";758;2
"Unit";"Hydralisk";"Larva";760;2
"Unit";"Hydralisk";"Larva";762;2
"Unit";"Hydralisk";"Larva";764;2
"Unit";"Hydralisk";"Larva";766;2
"Unit";"Zergling";"Larva";768;1
"Unit";"Zergling";"Larva";769;1
"Unit";"Zergling";"Larva";770;1
"Unit";"Zergling";"Larva";771;1
"Unit";"Zergling";"Larva";772;1
"Unit";"Zergling";"Larva";773;1
"Unit";"Zergling";"Larva";774;1
"Unit";"Zergling";"Larva";775;1
"Unit";"Zergling";"Larva";776;1
"Unit";"Zergling";"Larva";777;1
"Unit";"Zergling";"Larva";778;1
"Unit";"Zergling";"Larva";779;1
"Unit";"Zergling";"Larva";780;1
"Unit";"Zergling";"Larva";781;1
"Unit";"Zergling";"Larva";782;1
"Unit";"Zergling";"Larva";783;1
"Unit";"Zergling";"Larva";784;1
"Unit";"Zergling";"Larva";785;1
"Unit";"Zergling";"Larva";786;1
"Unit";"Zergling";"Larva";787;1
"Unit";"Zergling";"Larva";788;1
"Unit";"Zergling";"Larva";789;1
"Unit";"Zergling";"Larva";790;1
"Unit";"Zergling";"Larva";791;1
"Unit";"Baneling";"Zergling";792;0
"Unit";"Baneling";"Zergling";792;0
"Unit";"Baneling";"Zergling";792;0
"Unit";"Baneling";"Zergling";792;0
"Unit";"Baneling";"Zergling";792;0
"Unit";"Baneling";"Zergling";792;0
"Unit";"Baneling";"Zergling";792;0
"Unit";"Baneling";"Zergling";792;0
"Unit";"Baneling";"Zergling";792;0
"Unit";"Baneling";"Zergling";792;0
"Unit";"Baneling";"Zergling";792;0
"Unit";"Baneling";"Zergling";792;0
"Upgrade";"SprayZerg";NA;792;0
"Upgrade";"SprayZerg";NA;792;0
"Upgrade";"SprayZerg";NA;792;0
"Upgrade";"SprayZerg";NA;792;0
"Upgrade";"ZergMissileWeaponsLevel1";NA;792;0
"Upgrade";"ZergGroundArmorsLevel1";NA;792;0
"Upgrade";"SprayZerg";NA;792;0
"Upgrade";"ZergFlyerArmorsLevel1";NA;792;0
"Upgrade";"SprayZerg";NA;792;0
"Upgrade";"SprayZerg";NA;792;0
"Upgrade";"ZergMissileWeaponsLevel2";NA;792;0
"Upgrade";"SprayZerg";NA;792;0
"Upgrade";"ZergFlyerWeaponsLevel1";NA;792;0
"Upgrade";"zerglingmovementspeed";NA;792;0
"Upgrade";"SprayZerg";NA;792;0
"Upgrade";"SprayZerg";NA;792;0
"Upgrade";"ZergFlyerWeaponsLevel2";NA;792;0
"Upgrade";"SprayZerg";NA;792;0
"Upgrade";"overlordspeed";NA;792;0
"Upgrade";"SprayZerg";NA;792;0
"Upgrade";"SprayZerg";NA;792;0
"Upgrade";"SprayZerg";NA;792;0
"Upgrade";"SprayZerg";NA;792;0
"Upgrade";"SprayZerg";NA;792;0
"Upgrade";"SprayZerg";NA;792;0
"Upgrade";"ZergFlyerArmorsLevel2";NA;792;0
"Upgrade";"SprayZerg";NA;792;0
"Upgrade";"ZergFlyerWeaponsLevel3";NA;792;0
"Upgrade";"SprayZerg";NA;792;0
"Upgrade";"SprayZerg";NA;792;0
"Upgrade";"SprayZerg";NA;792;0
"Upgrade";"SprayZerg";NA;792;0
"Upgrade";"SprayZerg";NA;792;0
"Upgrade";"SprayZerg";NA;792;0
"Upgrade";"EvolveMuscularAugments";NA;792;0
"Upgrade";"SprayZerg";NA;792;0
