"type";"unit_name";"on_building";"total_supply";"supply"
"Unit";"Overlord";"Larva";14;0
"Building";"Extractor";NA;18;0
"Building";"SpawningPool";NA;19;0
"Building";"Hatchery";NA;17;0
"Unit";"Overlord";"Larva";22;0
"Unit";"Zergling";"Larva";23;1
"Unit";"Zergling";"Larva";23;1
"Unit";"Zergling";"Larva";23;1
"Unit";"Zergling";"Larva";23;1
"Unit";"Queen";"Hatchery";23;2
"Unit";"Queen";"Hatchery";23;2
"Unit";"Overlord";"Larva";34;0
"Unit";"Overlord";"Larva";34;0
"Unit";"Overlord";"Larva";38;0
"Unit";"Zergling";"Larva";38;1
"Unit";"Zergling";"Larva";38;1
"Unit";"Zergling";"Larva";40;1
"Unit";"Zergling";"Larva";40;1
"Building";"Hatchery";NA;27;0
"Unit";"Zergling";"Larva";40;1
"Unit";"Zergling";"Larva";40;1
"Unit";"Zergling";"Larva";40;1
"Unit";"Zergling";"Larva";40;1
"Unit";"Zergling";"Larva";40;1
"Unit";"Zergling";"Larva";40;1
"Unit";"Zergling";"Larva";40;1
"Unit";"Zergling";"Larva";40;1
"Unit";"Queen";"Hatchery";37;2
"Unit";"Overlord";"Larva";40;0
"Building";"CreepTumorQueen";NA;46;0
"Unit";"Zergling";"Larva";57;1
"Unit";"Zergling";"Larva";57;1
"Unit";"Zergling";"Larva";57;1
"Unit";"Zergling";"Larva";57;1
"Unit";"Zergling";"Larva";57;1
"Unit";"Zergling";"Larva";57;1
"Unit";"Zergling";"Larva";57;1
"Unit";"Zergling";"Larva";57;1
"Unit";"Zergling";"Larva";61;1
"Unit";"Zergling";"Larva";61;1
"Unit";"Zergling";"Larva";61;1
"Unit";"Zergling";"Larva";61;1
"Unit";"Queen";"Hatchery";63;2
"Building";"CreepTumorQueen";NA;77;0
"Building";"SporeCrawler";NA;77;0
"Building";"SporeCrawler";NA;77;0
"Building";"SporeCrawler";NA;77;0
"Unit";"Zergling";"Larva";87;1
"Unit";"Zergling";"Larva";87;1
"Unit";"Zergling";"Larva";87;1
"Unit";"Zergling";"Larva";87;1
"Unit";"Zergling";"Larva";87;1
"Unit";"Zergling";"Larva";87;1
"Building";"CreepTumorQueen";NA;89;0
"Unit";"Overlord";"Larva";87;0
"Unit";"Overlord";"Larva";87;0
"Unit";"Overlord";"Larva";87;0
"Unit";"Queen";"Hatchery";77;2
"Unit";"Overlord";"Larva";89;0
"Unit";"Zergling";"Larva";89;1
"Unit";"Zergling";"Larva";89;1
"Unit";"Zergling";"Larva";89;1
"Unit";"Zergling";"Larva";89;1
"Unit";"Zergling";"Larva";89;1
"Unit";"Zergling";"Larva";89;1
"Unit";"Overlord";"Larva";95;0
"Unit";"Zergling";"Larva";95;1
"Unit";"Zergling";"Larva";95;1
"Unit";"Zergling";"Larva";95;1
"Unit";"Zergling";"Larva";95;1
"Unit";"Zergling";"Larva";95;1
"Unit";"Zergling";"Larva";95;1
"Unit";"Zergling";"Larva";95;1
"Unit";"Zergling";"Larva";95;1
"Building";"SpineCrawler";NA;89;0
"Building";"Extractor";NA;95;0
"Building";"SpineCrawler";NA;89;0
"Building";"Extractor";NA;95;0
"Building";"CreepTumorQueen";NA;103;0
"Building";"CreepTumor";NA;103;0
"Building";"CreepTumor";NA;103;0
"Building";"EvolutionChamber";NA;103;0
"Building";"EvolutionChamber";NA;103;0
"Building";"SporeCrawler";NA;111;0
"Building";"SporeCrawler";NA;117;0
"Unit";"Overlord";"Larva";119;0
"Unit";"Queen";"Hatchery";121;2
"Building";"Extractor";NA;129;0
"Building";"CreepTumorQueen";NA;144;0
"Building";"CreepTumor";NA;135;0
"Unit";"Overlord";"Larva";143;0
"Building";"CreepTumorQueen";NA;144;0
"Building";"CreepTumorQueen";NA;144;0
"Building";"Extractor";NA;144;0
"Building";"Extractor";NA;144;0
"Building";"CreepTumorQueen";NA;144;0
"Building";"CreepTumor";NA;144;0
"Building";"CreepTumor";NA;144;0
"Building";"CreepTumorQueen";NA;144;0
"Building";"CreepTumor";NA;144;0
"Unit";"Overlord";"Larva";144;0
"Unit";"Overlord";"Larva";144;0
"Building";"CreepTumor";NA;156;0
"Building";"CreepTumorQueen";NA;157;0
"Building";"CreepTumor";NA;157;0
"Building";"CreepTumor";NA;157;0
"Building";"CreepTumorQueen";NA;157;0
"Building";"CreepTumor";NA;157;0
"Building";"CreepTumor";NA;157;0
"Unit";"Overlord";"Larva";157;0
"Unit";"Zergling";"Larva";168;1
"Unit";"Zergling";"Larva";168;1
"Unit";"Zergling";"Larva";168;1
"Unit";"Zergling";"Larva";168;1
"Building";"HydraliskDen";NA;157;0
"Upgrade";"ZergMeleeWeaponsLevel1";"EvolutionChamber";135;0
"Building";"CreepTumor";NA;168;0
"Unit";"Overlord";"Larva";168;0
"Unit";"Zergling";"Larva";168;1
"Unit";"Zergling";"Larva";168;1
"Unit";"Zergling";"Larva";168;1
"Unit";"Zergling";"Larva";168;1
"Unit";"Zergling";"Larva";168;1
"Unit";"Zergling";"Larva";168;1
"Unit";"Zergling";"Larva";168;1
"Unit";"Zergling";"Larva";168;1
"Unit";"Zergling";"Larva";168;1
"Unit";"Zergling";"Larva";168;1
"Unit";"Zergling";"Larva";168;1
"Unit";"Zergling";"Larva";168;1
"Building";"CreepTumorQueen";NA;168;0
"Unit";"Overlord";"Larva";168;0
"Building";"CreepTumor";NA;168;0
"Building";"Hatchery";NA;144;0
"Building";"CreepTumorQueen";NA;172;0
"Upgrade";"ZergGroundArmorsLevel1";"EvolutionChamber";144;0
"Building";"CreepTumorQueen";NA;172;0
"Building";"CreepTumor";NA;172;0
"Building";"CreepTumor";NA;172;0
"Building";"CreepTumor";NA;172;0
"Building";"CreepTumorQueen";NA;172;0
"Building";"CreepTumor";NA;172;0
"Unit";"Zergling";"Larva";172;1
"Unit";"Zergling";"Larva";172;1
"Unit";"Zergling";"Larva";172;1
"Unit";"Zergling";"Larva";172;1
"Unit";"Zergling";"Larva";172;1
"Unit";"Zergling";"Larva";172;1
"Unit";"Zergling";"Larva";172;1
"Unit";"Zergling";"Larva";172;1
"Building";"BanelingNest";NA;157;0
"Building";"CreepTumorQueen";NA;184;0
"Building";"Hatchery";NA;157;0
"Unit";"Hydralisk";"Larva";195;2
"Unit";"Hydralisk";"Larva";195;2
"Unit";"Hydralisk";"Larva";195;2
"Unit";"Hydralisk";"Larva";195;2
"Unit";"Hydralisk";"Larva";195;2
"Unit";"Hydralisk";"Larva";195;2
"Unit";"Hydralisk";"Larva";195;2
"Unit";"Hydralisk";"Larva";195;2
"Unit";"Hydralisk";"Larva";195;2
"Unit";"Hydralisk";"Larva";195;2
"Building";"CreepTumorQueen";NA;195;0
"Building";"SporeCrawler";NA;195;0
"Building";"CreepTumorQueen";NA;195;0
"Building";"CreepTumorQueen";NA;195;0
"Building";"Extractor";NA;195;0
"Building";"CreepTumor";NA;195;0
"Building";"Extractor";NA;195;0
"Building";"CreepTumor";NA;195;0
"Building";"CreepTumor";NA;195;0
"Building";"SporeCrawler";NA;195;0
"Building";"CreepTumorQueen";NA;195;0
"Building";"CreepTumor";NA;215;0
"Building";"CreepTumor";NA;215;0
"Unit";"Overlord";"Larva";215;0
"Unit";"Overlord";"Larva";215;0
"Building";"SpineCrawler";NA;195;0
"Unit";"Hydralisk";"Larva";195;2
"Unit";"Hydralisk";"Larva";195;2
"Unit";"Hydralisk";"Larva";195;2
"Unit";"Hydralisk";"Larva";195;2
"Unit";"Hydralisk";"Larva";195;2
"Unit";"Hydralisk";"Larva";195;2
"Unit";"Hydralisk";"Larva";195;2
"Unit";"Hydralisk";"Larva";195;2
"Unit";"Hydralisk";"Larva";195;2
"Unit";"Overlord";"Larva";215;0
"Building";"SpineCrawler";NA;195;0
"Building";"CreepTumorQueen";NA;215;0
"Building";"CreepTumorQueen";NA;223;0
"Building";"CreepTumor";NA;233;0
"Building";"CreepTumor";NA;233;0
"Building";"CreepTumor";NA;233;0
"Building";"CreepTumor";NA;233;0
"Building";"CreepTumor";NA;233;0
"Unit";"Overlord";"Larva";217;0
"Building";"CreepTumorQueen";NA;233;0
"Building";"CreepTumor";NA;233;0
"Building";"CreepTumor";NA;233;0
"Upgrade";"EvolveMuscularAugments";"HydraliskDen";195;0
"Unit";"Zergling";"Larva";233;1
"Unit";"Zergling";"Larva";233;1
"Unit";"Zergling";"Larva";233;1
"Unit";"Zergling";"Larva";233;1
"Unit";"Zergling";"Larva";233;1
"Unit";"Zergling";"Larva";233;1
"Unit";"Zergling";"Larva";233;1
"Unit";"Zergling";"Larva";233;1
"Unit";"Zergling";"Larva";233;1
"Unit";"Zergling";"Larva";233;1
"Unit";"Zergling";"Larva";233;1
"Unit";"Zergling";"Larva";233;1
"Unit";"Zergling";"Larva";233;1
"Unit";"Zergling";"Larva";233;1
"Unit";"Zergling";"Larva";233;1
"Unit";"Zergling";"Larva";233;1
"Unit";"Zergling";"Larva";233;1
"Unit";"Zergling";"Larva";233;1
"Unit";"Zergling";"Larva";233;1
"Unit";"Zergling";"Larva";233;1
"Unit";"Zergling";"Larva";233;1
"Unit";"Zergling";"Larva";233;1
"Unit";"Zergling";"Larva";233;1
"Unit";"Zergling";"Larva";233;1
"Unit";"Zergling";"Larva";233;1
"Unit";"Zergling";"Larva";233;1
"Unit";"Zergling";"Larva";233;1
"Unit";"Zergling";"Larva";233;1
"Unit";"Zergling";"Larva";233;1
"Unit";"Zergling";"Larva";233;1
"Unit";"Zergling";"Larva";233;1
"Unit";"Zergling";"Larva";233;1
"Unit";"Zergling";"Larva";233;1
"Unit";"Zergling";"Larva";233;1
"Unit";"Zergling";"Larva";233;1
"Unit";"Zergling";"Larva";233;1
"Unit";"Zergling";"Larva";233;1
"Unit";"Zergling";"Larva";233;1
"Unit";"Zergling";"Larva";233;1
"Unit";"Zergling";"Larva";233;1
"Building";"CreepTumor";NA;233;0
"Building";"CreepTumor";NA;233;0
"Building";"CreepTumor";NA;273;0
"Building";"CreepTumor";NA;273;0
"Building";"CreepTumor";NA;273;0
"Building";"InfestationPit";NA;233;0
"Building";"CreepTumor";NA;273;0
"Unit";"Hydralisk";"Larva";233;2
"Unit";"Hydralisk";"Larva";233;2
"Unit";"Hydralisk";"Larva";233;2
"Unit";"Hydralisk";"Larva";233;2
"Unit";"Hydralisk";"Larva";233;2
"Unit";"Hydralisk";"Larva";233;2
"Unit";"Hydralisk";"Larva";233;2
"Unit";"Hydralisk";"Larva";233;2
"Unit";"Zergling";"Larva";273;1
"Unit";"Zergling";"Larva";273;1
"Unit";"Zergling";"Larva";273;1
"Unit";"Zergling";"Larva";273;1
"Unit";"Zergling";"Larva";273;1
"Unit";"Zergling";"Larva";273;1
"Unit";"Zergling";"Larva";273;1
"Unit";"Zergling";"Larva";273;1
"Unit";"Zergling";"Larva";273;1
"Unit";"Zergling";"Larva";273;1
"Building";"CreepTumor";NA;273;0
"Building";"CreepTumor";NA;273;0
"Building";"CreepTumor";NA;273;0
"Building";"CreepTumor";NA;273;0
"Building";"SporeCrawler";NA;273;0
"Building";"SporeCrawler";NA;273;0
"Building";"SporeCrawler";NA;273;0
"Upgrade";"ZergMeleeWeaponsLevel2";"EvolutionChamber";195;0
"Upgrade";"ZergGroundArmorsLevel2";"EvolutionChamber";215;0
"Building";"Hatchery";NA;233;0
"Building";"CreepTumor";NA;308;0
"Building";"CreepTumor";NA;308;0
"Building";"CreepTumor";NA;308;0
"Building";"CreepTumor";NA;308;0
"Building";"CreepTumor";NA;308;0
"Upgrade";"EvolveGroovedSpines";"HydraliskDen";273;0
"Building";"CreepTumor";NA;308;0
"Building";"CreepTumor";NA;308;0
"Building";"CreepTumorQueen";NA;308;0
"Building";"CreepTumorQueen";NA;308;0
"Building";"CreepTumorQueen";NA;308;0
"Building";"EvolutionChamber";NA;308;0
"Building";"CreepTumor";NA;308;0
"Building";"CreepTumor";NA;308;0
"Building";"CreepTumor";NA;308;0
"Building";"CreepTumor";NA;308;0
"Building";"CreepTumor";NA;308;0
"Building";"CreepTumor";NA;308;0
"Building";"CreepTumor";NA;308;0
"Building";"CreepTumor";NA;308;0
"Building";"Extractor";NA;308;0
"Building";"Extractor";NA;308;0
"Building";"SporeCrawler";NA;308;0
"Building";"SporeCrawler";NA;308;0
"Building";"Hatchery";NA;308;0
"Unit";"Overlord";"Larva";309;0
"Unit";"Overlord";"Larva";309;0
"Building";"CreepTumor";NA;309;0
"Unit";"Baneling";"Zergling";309;0
"Unit";"Baneling";"Zergling";309;0
"Unit";"Baneling";"Zergling";309;0
"Unit";"Baneling";"Zergling";309;0
"Unit";"Baneling";"Zergling";309;0
"Unit";"Baneling";"Zergling";309;0
"Unit";"Baneling";"Zergling";309;0
"Unit";"Baneling";"Zergling";309;0
"Unit";"Baneling";"Zergling";309;0
"Unit";"Baneling";"Zergling";309;0
"Unit";"Baneling";"Zergling";309;0
"Unit";"Baneling";"Zergling";309;0
"Unit";"Baneling";"Zergling";309;0
"Unit";"Baneling";"Zergling";309;0
"Unit";"Baneling";"Zergling";309;0
"Unit";"Baneling";"Zergling";309;0
"Unit";"Baneling";"Zergling";309;0
"Unit";"Baneling";"Zergling";309;0
"Unit";"Baneling";"Zergling";309;0
"Unit";"Baneling";"Zergling";309;0
"Unit";"Baneling";"Zergling";309;0
"Unit";"Baneling";"Zergling";309;0
"Unit";"Baneling";"Zergling";309;0
"Unit";"Baneling";"Zergling";309;0
"Unit";"Baneling";"Zergling";309;0
"Unit";"Baneling";"Zergling";309;0
"Unit";"Baneling";"Zergling";309;0
"Unit";"Baneling";"Zergling";309;0
"Unit";"Baneling";"Zergling";309;0
"Unit";"Baneling";"Zergling";309;0
"Unit";"Zergling";"Larva";309;1
"Unit";"Zergling";"Larva";309;1
"Unit";"Zergling";"Larva";309;1
"Unit";"Zergling";"Larva";309;1
"Unit";"Zergling";"Larva";309;1
"Unit";"Zergling";"Larva";309;1
"Unit";"Zergling";"Larva";309;1
"Unit";"Zergling";"Larva";309;1
"Unit";"Zergling";"Larva";309;1
"Unit";"Zergling";"Larva";309;1
"Unit";"Zergling";"Larva";309;1
"Unit";"Zergling";"Larva";309;1
"Unit";"Zergling";"Larva";309;1
"Unit";"Zergling";"Larva";309;1
"Unit";"Zergling";"Larva";309;1
"Unit";"Zergling";"Larva";309;1
"Unit";"Zergling";"Larva";309;1
"Unit";"Zergling";"Larva";309;1
"Unit";"Zergling";"Larva";309;1
"Unit";"Zergling";"Larva";309;1
"Unit";"Zergling";"Larva";309;1
"Unit";"Zergling";"Larva";309;1
"Unit";"Zergling";"Larva";309;1
"Unit";"Zergling";"Larva";309;1
"Unit";"Zergling";"Larva";309;1
"Unit";"Zergling";"Larva";309;1
"Unit";"Zergling";"Larva";309;1
"Unit";"Zergling";"Larva";309;1
"Unit";"Zergling";"Larva";309;1
"Unit";"Zergling";"Larva";309;1
"Unit";"Zergling";"Larva";309;1
"Unit";"Zergling";"Larva";309;1
"Unit";"Zergling";"Larva";309;1
"Unit";"Zergling";"Larva";309;1
"Unit";"Zergling";"Larva";309;1
"Unit";"Zergling";"Larva";309;1
"Unit";"Zergling";"Larva";309;1
"Unit";"Zergling";"Larva";309;1
"Unit";"Zergling";"Larva";309;1
"Unit";"Zergling";"Larva";309;1
"Unit";"Zergling";"Larva";309;1
"Unit";"Zergling";"Larva";309;1
"Unit";"Zergling";"Larva";309;1
"Unit";"Zergling";"Larva";309;1
"Unit";"Zergling";"Larva";309;1
"Unit";"Zergling";"Larva";309;1
"Unit";"Zergling";"Larva";309;1
"Unit";"Zergling";"Larva";309;1
"Unit";"Zergling";"Larva";309;1
"Unit";"Zergling";"Larva";309;1
"Building";"CreepTumor";NA;359;0
"Building";"CreepTumor";NA;359;0
"Building";"CreepTumor";NA;359;0
"Building";"UltraliskCavern";NA;309;0
"Building";"CreepTumorQueen";NA;359;0
"Unit";"Zergling";"Larva";359;1
"Unit";"Zergling";"Larva";359;1
"Unit";"Zergling";"Larva";359;1
"Unit";"Zergling";"Larva";359;1
"Unit";"Zergling";"Larva";359;1
"Unit";"Zergling";"Larva";359;1
"Unit";"Zergling";"Larva";359;1
"Unit";"Zergling";"Larva";359;1
"Unit";"Zergling";"Larva";359;1
"Unit";"Zergling";"Larva";359;1
"Unit";"Zergling";"Larva";359;1
"Unit";"Zergling";"Larva";359;1
"Unit";"Zergling";"Larva";359;1
"Unit";"Zergling";"Larva";359;1
"Unit";"Zergling";"Larva";359;1
"Unit";"Zergling";"Larva";359;1
"Unit";"Zergling";"Larva";359;1
"Unit";"Zergling";"Larva";359;1
"Unit";"Zergling";"Larva";359;1
"Unit";"Zergling";"Larva";359;1
"Unit";"Zergling";"Larva";359;1
"Unit";"Zergling";"Larva";359;1
"Unit";"Zergling";"Larva";359;1
"Unit";"Zergling";"Larva";359;1
"Unit";"Zergling";"Larva";359;1
"Unit";"Zergling";"Larva";359;1
"Unit";"Zergling";"Larva";359;1
"Unit";"Zergling";"Larva";359;1
"Unit";"Zergling";"Larva";359;1
"Unit";"Zergling";"Larva";359;1
"Unit";"Zergling";"Larva";359;1
"Unit";"Zergling";"Larva";359;1
"Unit";"Zergling";"Larva";359;1
"Unit";"Zergling";"Larva";359;1
"Unit";"Zergling";"Larva";359;1
"Unit";"Zergling";"Larva";359;1
"Unit";"Zergling";"Larva";359;1
"Unit";"Zergling";"Larva";359;1
"Unit";"Zergling";"Larva";359;1
"Unit";"Zergling";"Larva";359;1
"Unit";"Zergling";"Larva";359;1
"Unit";"Zergling";"Larva";359;1
"Unit";"Zergling";"Larva";359;1
"Unit";"Zergling";"Larva";359;1
"Unit";"Zergling";"Larva";359;1
"Unit";"Zergling";"Larva";359;1
"Building";"CreepTumorQueen";NA;359;0
"Building";"CreepTumorQueen";NA;359;0
"Upgrade";"ZergMissileWeaponsLevel1";"EvolutionChamber";308;0
"Unit";"Zergling";"Larva";359;1
"Unit";"Zergling";"Larva";359;1
"Unit";"Zergling";"Larva";359;1
"Unit";"Zergling";"Larva";359;1
"Unit";"Zergling";"Larva";359;1
"Unit";"Zergling";"Larva";359;1
"Unit";"Zergling";"Larva";359;1
"Unit";"Zergling";"Larva";359;1
"Unit";"Zergling";"Larva";359;1
"Unit";"Zergling";"Larva";359;1
"Unit";"Zergling";"Larva";359;1
"Unit";"Zergling";"Larva";359;1
"Unit";"Zergling";"Larva";359;1
"Unit";"Zergling";"Larva";359;1
"Unit";"Zergling";"Larva";359;1
"Unit";"Zergling";"Larva";359;1
"Unit";"Zergling";"Larva";359;1
"Unit";"Zergling";"Larva";359;1
"Unit";"Zergling";"Larva";359;1
"Unit";"Zergling";"Larva";359;1
"Unit";"Zergling";"Larva";359;1
"Unit";"Zergling";"Larva";359;1
"Unit";"Zergling";"Larva";359;1
"Unit";"Zergling";"Larva";359;1
"Unit";"Zergling";"Larva";359;1
"Unit";"Zergling";"Larva";359;1
"Unit";"Zergling";"Larva";359;1
"Unit";"Zergling";"Larva";359;1
"Unit";"Zergling";"Larva";359;1
"Unit";"Zergling";"Larva";359;1
"Unit";"Zergling";"Larva";359;1
"Unit";"Zergling";"Larva";359;1
"Unit";"Zergling";"Larva";359;1
"Unit";"Zergling";"Larva";359;1
"Unit";"Zergling";"Larva";405;1
"Unit";"Zergling";"Larva";405;1
"Unit";"Zergling";"Larva";405;1
"Unit";"Zergling";"Larva";405;1
"Unit";"Zergling";"Larva";405;1
"Unit";"Zergling";"Larva";405;1
"Unit";"Zergling";"Larva";405;1
"Unit";"Zergling";"Larva";405;1
"Unit";"Zergling";"Larva";405;1
"Unit";"Zergling";"Larva";405;1
"Unit";"Zergling";"Larva";405;1
"Unit";"Zergling";"Larva";405;1
"Unit";"Zergling";"Larva";405;1
"Unit";"Zergling";"Larva";405;1
"Unit";"Zergling";"Larva";405;1
"Unit";"Zergling";"Larva";405;1
"Unit";"Zergling";"Larva";405;1
"Unit";"Zergling";"Larva";405;1
"Unit";"Zergling";"Larva";439;1
"Unit";"Zergling";"Larva";439;1
"Unit";"Zergling";"Larva";439;1
"Unit";"Zergling";"Larva";439;1
"Unit";"Zergling";"Larva";439;1
"Unit";"Zergling";"Larva";439;1
"Unit";"Zergling";"Larva";439;1
"Unit";"Zergling";"Larva";439;1
"Unit";"Zergling";"Larva";439;1
"Unit";"Zergling";"Larva";439;1
"Unit";"Zergling";"Larva";439;1
"Unit";"Zergling";"Larva";439;1
"Unit";"Zergling";"Larva";439;1
"Unit";"Zergling";"Larva";439;1
"Unit";"Zergling";"Larva";439;1
"Unit";"Zergling";"Larva";439;1
"Unit";"Zergling";"Larva";439;1
"Unit";"Zergling";"Larva";439;1
"Unit";"Zergling";"Larva";439;1
"Unit";"Zergling";"Larva";439;1
"Unit";"Zergling";"Larva";439;1
"Unit";"Zergling";"Larva";439;1
"Unit";"Zergling";"Larva";439;1
"Unit";"Zergling";"Larva";439;1
"Building";"CreepTumor";NA;457;0
"Building";"CreepTumor";NA;457;0
"Building";"CreepTumor";NA;457;0
"Building";"CreepTumor";NA;459;0
"Building";"CreepTumor";NA;481;0
"Unit";"Overlord";"Larva";481;0
"Unit";"Overlord";"Larva";481;0
"Unit";"Ultralisk";"Larva";457;6
"Unit";"Ultralisk";"Larva";457;6
"Unit";"Ultralisk";"Larva";457;6
"Unit";"Ultralisk";"Larva";457;6
"Unit";"Ultralisk";"Larva";457;6
"Unit";"Ultralisk";"Larva";457;6
"Unit";"Overlord";"Larva";481;0
"Building";"CreepTumor";NA;481;0
"Building";"CreepTumor";NA;481;0
"Unit";"Baneling";"Zergling";481;0
"Unit";"Baneling";"Zergling";481;0
"Unit";"Baneling";"Zergling";481;0
"Unit";"Baneling";"Zergling";481;0
"Unit";"Baneling";"Zergling";481;0
"Unit";"Baneling";"Zergling";481;0
"Unit";"Baneling";"Zergling";481;0
"Unit";"Baneling";"Zergling";481;0
"Unit";"Baneling";"Zergling";481;0
"Unit";"Baneling";"Zergling";481;0
"Unit";"Baneling";"Zergling";481;0
"Unit";"Baneling";"Zergling";481;0
"Unit";"Baneling";"Zergling";481;0
"Unit";"Baneling";"Zergling";481;0
"Building";"CreepTumor";NA;481;0
"Unit";"Viper";"Larva";481;3
"Upgrade";"ChitinousPlating";"UltraliskCavern";439;0
"Unit";"Ultralisk";"Larva";481;6
"Building";"CreepTumor";NA;517;0
"Unit";"Overlord";"Larva";517;0
"Upgrade";"ZergMeleeWeaponsLevel3";"EvolutionChamber";359;0
"Upgrade";"ZergGroundArmorsLevel3";"EvolutionChamber";359;0
"Unit";"Viper";"Larva";520;3
"Unit";"Viper";"Larva";520;3
"Unit";"Zergling";"Larva";532;1
"Unit";"Zergling";"Larva";532;1
"Unit";"Zergling";"Larva";532;1
"Unit";"Zergling";"Larva";532;1
"Unit";"Zergling";"Larva";532;1
"Unit";"Zergling";"Larva";532;1
"Unit";"Zergling";"Larva";532;1
"Unit";"Zergling";"Larva";532;1
"Unit";"Zergling";"Larva";532;1
"Unit";"Zergling";"Larva";532;1
"Unit";"Zergling";"Larva";532;1
"Unit";"Zergling";"Larva";532;1
"Unit";"Zergling";"Larva";532;1
"Unit";"Zergling";"Larva";532;1
"Unit";"Zergling";"Larva";532;1
"Unit";"Zergling";"Larva";532;1
"Unit";"Zergling";"Larva";532;1
"Unit";"Zergling";"Larva";532;1
"Unit";"Zergling";"Larva";532;1
"Unit";"Zergling";"Larva";532;1
"Unit";"Zergling";"Larva";532;1
"Unit";"Zergling";"Larva";532;1
"Unit";"Zergling";"Larva";532;1
"Unit";"Zergling";"Larva";532;1
"Unit";"Zergling";"Larva";532;1
"Unit";"Zergling";"Larva";532;1
"Unit";"Zergling";"Larva";532;1
"Unit";"Zergling";"Larva";532;1
"Unit";"Zergling";"Larva";532;1
"Unit";"Zergling";"Larva";532;1
"Unit";"Zergling";"Larva";532;1
"Unit";"Zergling";"Larva";532;1
"Unit";"Zergling";"Larva";532;1
"Unit";"Zergling";"Larva";532;1
"Unit";"Zergling";"Larva";532;1
"Unit";"Zergling";"Larva";532;1
"Unit";"Zergling";"Larva";532;1
"Unit";"Zergling";"Larva";532;1
"Unit";"Zergling";"Larva";532;1
"Unit";"Zergling";"Larva";532;1
"Unit";"Zergling";"Larva";532;1
"Unit";"Zergling";"Larva";532;1
"Unit";"Zergling";"Larva";532;1
"Unit";"Zergling";"Larva";532;1
"Unit";"Zergling";"Larva";532;1
"Unit";"Zergling";"Larva";532;1
"Unit";"Zergling";"Larva";532;1
"Unit";"Zergling";"Larva";532;1
"Unit";"Zergling";"Larva";532;1
"Unit";"Zergling";"Larva";532;1
"Unit";"Zergling";"Larva";532;1
"Unit";"Zergling";"Larva";532;1
"Unit";"Zergling";"Larva";532;1
"Unit";"Zergling";"Larva";532;1
"Unit";"Zergling";"Larva";532;1
"Unit";"Zergling";"Larva";532;1
"Unit";"Zergling";"Larva";532;1
"Unit";"Zergling";"Larva";532;1
"Unit";"Zergling";"Larva";532;1
"Unit";"Zergling";"Larva";532;1
