"type";"unit_name";"on_building";"total_supply";"supply"
"Unit";"Overlord";"Larva";13;0
"Building";"Extractor";NA;17;0
"Building";"SpawningPool";NA;18;0
"Building";"Hatchery";NA;16;0
"Unit";"Overlord";"Larva";22;0
"Unit";"Zergling";"Larva";23;1
"Unit";"Zergling";"Larva";23;1
"Unit";"Queen";"Hatchery";23;2
"Unit";"Queen";"Hatchery";23;2
"Building";"CreepTumorQueen";NA;34;0
"Unit";"Overlord";"Larva";28;0
"Building";"CreepTumor";NA;37;0
"Unit";"Queen";"Hatchery";35;2
"Unit";"Overlord";"Larva";39;0
"Unit";"Queen";"Hatchery";39;2
"Building";"CreepTumor";NA;47;0
"Building";"CreepTumorQueen";NA;47;0
"Unit";"Overlord";"Larva";47;0
"Unit";"Overlord";"Larva";47;0
"Building";"CreepTumorQueen";NA;53;0
"Unit";"Queen";"Hatchery";47;2
"Unit";"Overlord";"Larva";53;0
"Building";"CreepTumorQueen";NA;56;0
"Unit";"Overlord";"Larva";56;0
"Building";"Extractor";NA;56;0
"Building";"EvolutionChamber";NA;56;0
"Building";"EvolutionChamber";NA;56;0
"Building";"CreepTumor";NA;60;0
"Building";"CreepTumor";NA;60;0
"Unit";"Overlord";"Larva";60;0
"Building";"CreepTumorQueen";NA;61;0
"Building";"Hatchery";NA;47;0
"Unit";"Overlord";"Larva";61;0
"Building";"CreepTumor";NA;66;0
"Building";"CreepTumor";NA;66;0
"Building";"CreepTumor";NA;68;0
"Unit";"Overlord";"Larva";67;0
"Building";"CreepTumor";NA;68;0
"Building";"CreepTumorQueen";NA;68;0
"Building";"CreepTumorQueen";NA;68;0
"Unit";"Overlord";"Larva";68;0
"Unit";"Zergling";"Larva";68;1
"Unit";"Zergling";"Larva";68;1
"Unit";"Zergling";"Larva";68;1
"Unit";"Zergling";"Larva";68;1
"Unit";"Zergling";"Larva";68;1
"Unit";"Zergling";"Larva";68;1
"Unit";"Zergling";"Larva";68;1
"Unit";"Zergling";"Larva";68;1
"Unit";"Zergling";"Larva";68;1
"Unit";"Zergling";"Larva";68;1
"Unit";"Zergling";"Larva";68;1
"Unit";"Zergling";"Larva";68;1
"Unit";"Zergling";"Larva";68;1
"Unit";"Zergling";"Larva";68;1
"Unit";"Zergling";"Larva";68;1
"Unit";"Zergling";"Larva";68;1
"Building";"CreepTumor";NA;68;0
"Building";"CreepTumorQueen";NA;68;0
"Unit";"Overlord";"Larva";68;0
"Building";"CreepTumor";NA;68;0
"Building";"CreepTumor";NA;68;0
"Unit";"Zergling";"Larva";68;1
"Unit";"Zergling";"Larva";68;1
"Unit";"Zergling";"Larva";68;1
"Unit";"Zergling";"Larva";68;1
"Unit";"Zergling";"Larva";68;1
"Unit";"Zergling";"Larva";68;1
"Building";"CreepTumor";NA;84;0
"Building";"CreepTumor";NA;84;0
"Unit";"Zergling";"Larva";84;1
"Unit";"Zergling";"Larva";84;1
"Unit";"Zergling";"Larva";84;1
"Unit";"Zergling";"Larva";84;1
"Building";"CreepTumor";NA;88;0
"Building";"CreepTumor";NA;90;0
"Unit";"Zergling";"Larva";84;1
"Unit";"Zergling";"Larva";84;1
"Building";"CreepTumor";NA;90;0
"Building";"CreepTumor";NA;90;0
"Unit";"Zergling";"Larva";90;1
"Unit";"Zergling";"Larva";90;1
"Unit";"Overlord";"Larva";90;0
"Unit";"Zergling";"Larva";90;1
"Unit";"Zergling";"Larva";90;1
"Unit";"Zergling";"Larva";90;1
"Unit";"Zergling";"Larva";90;1
"Unit";"Zergling";"Larva";90;1
"Unit";"Zergling";"Larva";90;1
"Unit";"Zergling";"Larva";90;1
"Unit";"Zergling";"Larva";90;1
"Unit";"Zergling";"Larva";90;1
"Unit";"Zergling";"Larva";90;1
"Unit";"Zergling";"Larva";90;1
"Unit";"Zergling";"Larva";90;1
"Building";"CreepTumor";NA;96;0
"Building";"CreepTumorQueen";NA;96;0
"Building";"CreepTumor";NA;96;0
"Building";"CreepTumor";NA;96;0
"Building";"CreepTumorQueen";NA;110;0
"Unit";"Overlord";"Larva";96;0
"Building";"CreepTumorQueen";NA;115;0
"Building";"CreepTumor";NA;115;0
"Building";"CreepTumor";NA;115;0
"Building";"CreepTumor";NA;115;0
"Building";"CreepTumor";NA;115;0
"Building";"CreepTumor";NA;115;0
"Building";"CreepTumor";NA;115;0
"Building";"BanelingNest";NA;96;0
"Unit";"Baneling";"Zergling";118;0
"Unit";"Baneling";"Zergling";118;0
"Unit";"Baneling";"Zergling";118;0
"Unit";"Baneling";"Zergling";118;0
"Unit";"Overlord";"Larva";118;0
"Upgrade";"ZergMeleeWeaponsLevel1";"EvolutionChamber";90;0
"Upgrade";"ZergGroundArmorsLevel1";"EvolutionChamber";90;0
"Unit";"Queen";"Hatchery";118;2
"Unit";"Overlord";"Larva";118;0
"Unit";"Overlord";"Larva";118;0
"Unit";"Queen";"Hatchery";118;2
"Unit";"Queen";"Hatchery";118;2
"Unit";"Overlord";"Larva";120;0
"Unit";"Zergling";"Larva";120;1
"Unit";"Zergling";"Larva";120;1
"Unit";"Overlord";"Larva";120;0
"Unit";"Zergling";"Larva";120;1
"Unit";"Zergling";"Larva";120;1
"Unit";"Zergling";"Larva";120;1
"Unit";"Zergling";"Larva";120;1
"Unit";"Zergling";"Larva";120;1
"Unit";"Zergling";"Larva";120;1
"Unit";"Zergling";"Larva";120;1
"Unit";"Zergling";"Larva";120;1
"Unit";"Zergling";"Larva";120;1
"Unit";"Zergling";"Larva";120;1
"Unit";"Zergling";"Larva";120;1
"Unit";"Zergling";"Larva";120;1
"Unit";"Zergling";"Larva";120;1
"Unit";"Zergling";"Larva";120;1
"Unit";"Zergling";"Larva";120;1
"Unit";"Zergling";"Larva";120;1
"Unit";"Zergling";"Larva";120;1
"Unit";"Zergling";"Larva";120;1
"Unit";"Zergling";"Larva";120;1
"Unit";"Zergling";"Larva";120;1
"Unit";"Zergling";"Larva";120;1
"Unit";"Zergling";"Larva";120;1
"Unit";"Zergling";"Larva";120;1
"Unit";"Zergling";"Larva";120;1
"Unit";"Zergling";"Larva";120;1
"Unit";"Zergling";"Larva";120;1
"Unit";"Zergling";"Larva";120;1
"Unit";"Zergling";"Larva";120;1
"Unit";"Queen";"Hatchery";118;2
"Building";"CreepTumor";NA;144;0
"Building";"CreepTumorQueen";NA;148;0
"Building";"CreepTumor";NA;148;0
"Building";"CreepTumor";NA;148;0
"Building";"CreepTumorQueen";NA;148;0
"Building";"CreepTumor";NA;148;0
"Building";"CreepTumor";NA;154;0
"Building";"CreepTumor";NA;154;0
"Building";"CreepTumor";NA;154;0
"Building";"CreepTumor";NA;154;0
"Building";"CreepTumor";NA;154;0
"Unit";"Overlord";"Larva";154;0
"Unit";"Queen";"Hatchery";122;2
"Building";"CreepTumor";NA;156;0
"Building";"Extractor";NA;156;0
"Unit";"Overlord";"Larva";156;0
"Building";"Extractor";NA;156;0
"Unit";"Overlord";"Larva";156;0
"Building";"Extractor";NA;156;0
"Building";"Extractor";NA;156;0
"Building";"Spire";NA;118;0
"Unit";"Overlord";"Larva";166;0
"Building";"CreepTumor";NA;168;0
"Building";"CreepTumor";NA;168;0
"Building";"CreepTumorQueen";NA;169;0
"Building";"CreepTumorQueen";NA;173;0
"Unit";"Zergling";"Larva";168;1
"Unit";"Zergling";"Larva";168;1
"Unit";"Overlord";"Larva";168;0
"Unit";"Zergling";"Larva";168;1
"Unit";"Zergling";"Larva";168;1
"Unit";"Zergling";"Larva";168;1
"Unit";"Zergling";"Larva";168;1
"Unit";"Zergling";"Larva";173;1
"Unit";"Zergling";"Larva";173;1
"Unit";"Overlord";"Larva";173;0
"Unit";"Zergling";"Larva";173;1
"Unit";"Zergling";"Larva";173;1
"Unit";"Zergling";"Larva";173;1
"Unit";"Zergling";"Larva";173;1
"Unit";"Zergling";"Larva";173;1
"Unit";"Zergling";"Larva";173;1
"Unit";"Zergling";"Larva";173;1
"Unit";"Zergling";"Larva";173;1
"Unit";"Zergling";"Larva";173;1
"Unit";"Zergling";"Larva";173;1
"Unit";"Zergling";"Larva";173;1
"Unit";"Zergling";"Larva";173;1
"Building";"Hatchery";NA;124;0
"Building";"CreepTumor";NA;179;0
"Building";"CreepTumor";NA;179;0
"Building";"CreepTumorQueen";NA;179;0
"Building";"CreepTumorQueen";NA;179;0
"Unit";"Overlord";"Larva";179;0
"Building";"CreepTumor";NA;179;0
"Building";"CreepTumorQueen";NA;179;0
"Building";"CreepTumor";NA;179;0
"Building";"CreepTumor";NA;179;0
"Building";"CreepTumor";NA;179;0
"Building";"CreepTumor";NA;179;0
"Building";"CreepTumor";NA;193;0
"Building";"CreepTumor";NA;193;0
"Building";"CreepTumorQueen";NA;193;0
"Building";"CreepTumor";NA;193;0
"Unit";"Zergling";"Larva";193;1
"Unit";"Zergling";"Larva";193;1
"Building";"CreepTumor";NA;193;0
"Unit";"Zergling";"Larva";193;1
"Unit";"Zergling";"Larva";193;1
"Unit";"Zergling";"Larva";193;1
"Unit";"Zergling";"Larva";193;1
"Unit";"Zergling";"Larva";193;1
"Unit";"Zergling";"Larva";193;1
"Unit";"Zergling";"Larva";193;1
"Unit";"Zergling";"Larva";193;1
"Unit";"Zergling";"Larva";193;1
"Unit";"Zergling";"Larva";193;1
"Building";"CreepTumor";NA;193;0
"Building";"CreepTumor";NA;193;0
"Building";"CreepTumor";NA;193;0
"Unit";"Overlord";"Larva";193;0
"Building";"InfestationPit";NA;179;0
"Building";"CreepTumor";NA;205;0
"Building";"CreepTumor";NA;205;0
"Building";"CreepTumor";NA;205;0
"Building";"CreepTumor";NA;206;0
"Unit";"Zergling";"Larva";209;1
"Unit";"Zergling";"Larva";209;1
"Unit";"Zergling";"Larva";209;1
"Unit";"Zergling";"Larva";209;1
"Unit";"Overlord";"Larva";209;0
"Unit";"Zergling";"Larva";209;1
"Unit";"Zergling";"Larva";209;1
"Unit";"Zergling";"Larva";209;1
"Unit";"Zergling";"Larva";209;1
"Unit";"Overlord";"Larva";215;0
"Unit";"Mutalisk";"Larva";215;2
"Unit";"Mutalisk";"Larva";215;2
"Unit";"Mutalisk";"Larva";215;2
"Unit";"Mutalisk";"Larva";215;2
"Unit";"Mutalisk";"Larva";215;2
"Unit";"Mutalisk";"Larva";215;2
"Building";"CreepTumor";NA;223;0
"Building";"CreepTumor";NA;223;0
"Building";"CreepTumor";NA;223;0
"Building";"CreepTumor";NA;223;0
"Building";"CreepTumorQueen";NA;223;0
"Building";"CreepTumor";NA;223;0
"Building";"CreepTumor";NA;223;0
"Building";"CreepTumor";NA;223;0
"Building";"CreepTumorQueen";NA;223;0
"Building";"CreepTumorQueen";NA;223;0
"Building";"CreepTumor";NA;235;0
"Building";"CreepTumor";NA;235;0
"Building";"CreepTumor";NA;235;0
"Building";"CreepTumorQueen";NA;235;0
"Unit";"Overlord";"Larva";235;0
"Unit";"Zergling";"Larva";235;1
"Unit";"Zergling";"Larva";235;1
"Unit";"Zergling";"Larva";235;1
"Unit";"Zergling";"Larva";235;1
"Unit";"Zergling";"Larva";235;1
"Unit";"Zergling";"Larva";235;1
"Unit";"Zergling";"Larva";235;1
"Unit";"Zergling";"Larva";235;1
"Upgrade";"ZergMeleeWeaponsLevel2";"EvolutionChamber";173;0
"Unit";"Zergling";"Larva";235;1
"Unit";"Zergling";"Larva";235;1
"Unit";"Zergling";"Larva";235;1
"Unit";"Zergling";"Larva";235;1
"Unit";"Zergling";"Larva";235;1
"Unit";"Zergling";"Larva";235;1
"Unit";"Zergling";"Larva";235;1
"Unit";"Zergling";"Larva";235;1
"Unit";"Zergling";"Larva";235;1
"Unit";"Zergling";"Larva";235;1
"Unit";"Zergling";"Larva";235;1
"Unit";"Zergling";"Larva";235;1
"Unit";"Zergling";"Larva";235;1
"Unit";"Zergling";"Larva";235;1
"Unit";"Zergling";"Larva";235;1
"Unit";"Zergling";"Larva";235;1
"Building";"CreepTumor";NA;235;0
"Building";"CreepTumor";NA;235;0
"Building";"Extractor";NA;235;0
"Building";"CreepTumor";NA;259;0
"Building";"CreepTumor";NA;259;0
"Building";"CreepTumor";NA;259;0
"Unit";"Baneling";"Zergling";259;0
"Building";"CreepTumor";NA;259;0
"Building";"CreepTumor";NA;259;0
"Unit";"Baneling";"Zergling";259;0
"Unit";"Baneling";"Zergling";259;0
"Unit";"Baneling";"Zergling";259;0
"Unit";"Baneling";"Zergling";259;0
"Unit";"Baneling";"Zergling";259;0
"Unit";"Baneling";"Zergling";259;0
"Unit";"Baneling";"Zergling";259;0
"Unit";"Baneling";"Zergling";259;0
"Unit";"Baneling";"Zergling";259;0
"Unit";"Baneling";"Zergling";259;0
"Unit";"Baneling";"Zergling";259;0
"Unit";"Baneling";"Zergling";259;0
"Unit";"Baneling";"Zergling";259;0
"Unit";"Baneling";"Zergling";259;0
"Unit";"Baneling";"Zergling";259;0
"Unit";"Baneling";"Zergling";259;0
"Unit";"Baneling";"Zergling";259;0
"Unit";"Zergling";"Larva";259;1
"Unit";"Zergling";"Larva";259;1
"Unit";"Baneling";"Zergling";259;0
"Unit";"Baneling";"Zergling";259;0
"Building";"CreepTumor";NA;259;0
"Unit";"Baneling";"Zergling";259;0
"Unit";"Baneling";"Zergling";259;0
"Unit";"Overlord";"Larva";259;0
"Unit";"Baneling";"Zergling";259;0
"Unit";"Baneling";"Zergling";259;0
"Unit";"Zergling";"Larva";259;1
"Unit";"Zergling";"Larva";259;1
"Unit";"Zergling";"Larva";259;1
"Unit";"Zergling";"Larva";259;1
"Unit";"Zergling";"Larva";259;1
"Unit";"Zergling";"Larva";259;1
"Upgrade";"ZergGroundArmorsLevel2";"EvolutionChamber";193;0
"Building";"CreepTumor";NA;259;0
"Unit";"Zergling";"Larva";259;1
"Unit";"Zergling";"Larva";259;1
"Unit";"Zergling";"Larva";259;1
"Unit";"Zergling";"Larva";259;1
"Unit";"Zergling";"Larva";259;1
"Unit";"Zergling";"Larva";259;1
"Unit";"Zergling";"Larva";259;1
"Unit";"Zergling";"Larva";259;1
"Unit";"Zergling";"Larva";259;1
"Unit";"Zergling";"Larva";259;1
"Unit";"Zergling";"Larva";259;1
"Unit";"Zergling";"Larva";259;1
"Unit";"Zergling";"Larva";259;1
"Unit";"Zergling";"Larva";259;1
"Unit";"Zergling";"Larva";259;1
"Unit";"Zergling";"Larva";259;1
"Unit";"Zergling";"Larva";259;1
"Unit";"Zergling";"Larva";259;1
"Unit";"Zergling";"Larva";259;1
"Unit";"Zergling";"Larva";259;1
"Building";"CreepTumor";NA;259;0
"Building";"CreepTumor";NA;259;0
"Building";"CreepTumorQueen";NA;259;0
"Building";"CreepTumor";NA;259;0
"Building";"CreepTumorQueen";NA;259;0
"Building";"CreepTumor";NA;259;0
"Building";"CreepTumorQueen";NA;259;0
"Building";"CreepTumor";NA;259;0
"Building";"CreepTumor";NA;259;0
"Building";"CreepTumor";NA;259;0
"Building";"CreepTumor";NA;259;0
"Building";"CreepTumor";NA;259;0
"Building";"CreepTumor";NA;259;0
"Building";"SporeCrawler";NA;287;0
"Building";"Extractor";NA;287;0
"Unit";"Baneling";"Zergling";287;0
"Unit";"Baneling";"Zergling";287;0
"Unit";"Baneling";"Zergling";287;0
"Unit";"Baneling";"Zergling";287;0
"Unit";"Baneling";"Zergling";287;0
"Unit";"Overlord";"Larva";288;0
"Building";"CreepTumor";NA;294;0
"Building";"CreepTumor";NA;294;0
"Building";"CreepTumor";NA;294;0
"Building";"CreepTumor";NA;294;0
"Building";"CreepTumor";NA;294;0
"Unit";"Zergling";"Larva";294;1
"Unit";"Zergling";"Larva";294;1
"Building";"CreepTumor";NA;294;0
"Unit";"Overlord";"Larva";294;0
"Unit";"Zergling";"Larva";294;1
"Unit";"Zergling";"Larva";294;1
"Unit";"Zergling";"Larva";294;1
"Unit";"Zergling";"Larva";294;1
"Unit";"Zergling";"Larva";294;1
"Unit";"Zergling";"Larva";294;1
"Unit";"Zergling";"Larva";294;1
"Unit";"Zergling";"Larva";294;1
"Unit";"Zergling";"Larva";294;1
"Unit";"Zergling";"Larva";294;1
"Unit";"Zergling";"Larva";294;1
"Unit";"Zergling";"Larva";294;1
"Unit";"Zergling";"Larva";294;1
"Unit";"Zergling";"Larva";294;1
"Unit";"Zergling";"Larva";294;1
"Unit";"Zergling";"Larva";294;1
"Unit";"Zergling";"Larva";294;1
"Unit";"Zergling";"Larva";294;1
"Building";"CreepTumor";NA;294;0
"Building";"CreepTumor";NA;294;0
"Building";"CreepTumor";NA;294;0
"Building";"CreepTumor";NA;294;0
"Building";"CreepTumor";NA;294;0
"Building";"CreepTumor";NA;294;0
"Unit";"Mutalisk";"Larva";294;2
"Unit";"Mutalisk";"Larva";294;2
"Building";"CreepTumor";NA;294;0
"Building";"CreepTumor";NA;294;0
"Building";"CreepTumor";NA;294;0
"Building";"CreepTumor";NA;294;0
"Building";"CreepTumor";NA;294;0
"Building";"CreepTumor";NA;314;0
"Building";"CreepTumorQueen";NA;314;0
"Building";"CreepTumor";NA;314;0
"Building";"CreepTumorQueen";NA;314;0
"Unit";"Baneling";"Zergling";318;0
"Unit";"Baneling";"Zergling";318;0
"Unit";"Baneling";"Zergling";318;0
"Unit";"Baneling";"Zergling";318;0
"Unit";"Baneling";"Zergling";318;0
"Unit";"Baneling";"Zergling";318;0
"Unit";"Baneling";"Zergling";318;0
"Unit";"Baneling";"Zergling";318;0
"Unit";"Baneling";"Zergling";318;0
"Unit";"Zergling";"Larva";318;1
"Unit";"Zergling";"Larva";318;1
"Unit";"Overlord";"Larva";318;0
"Unit";"Zergling";"Larva";318;1
"Unit";"Zergling";"Larva";318;1
"Unit";"Zergling";"Larva";318;1
"Unit";"Zergling";"Larva";318;1
"Unit";"Zergling";"Larva";318;1
"Unit";"Zergling";"Larva";318;1
"Unit";"Zergling";"Larva";318;1
"Unit";"Zergling";"Larva";318;1
"Unit";"Zergling";"Larva";318;1
"Unit";"Zergling";"Larva";318;1
"Unit";"Zergling";"Larva";318;1
"Unit";"Zergling";"Larva";318;1
"Unit";"Zergling";"Larva";318;1
"Unit";"Zergling";"Larva";318;1
"Unit";"Zergling";"Larva";318;1
"Unit";"Zergling";"Larva";318;1
"Unit";"Zergling";"Larva";318;1
"Unit";"Zergling";"Larva";318;1
"Unit";"Zergling";"Larva";318;1
"Unit";"Zergling";"Larva";318;1
"Unit";"Zergling";"Larva";318;1
"Unit";"Zergling";"Larva";318;1
"Building";"UltraliskCavern";NA;294;0
"Unit";"Overlord";"Larva";318;0
"Building";"CreepTumor";NA;342;0
"Building";"CreepTumor";NA;342;0
"Building";"CreepTumor";NA;342;0
"Building";"CreepTumor";NA;342;0
"Building";"CreepTumorQueen";NA;342;0
"Building";"SpineCrawler";NA;318;0
"Unit";"Overlord";"Larva";342;0
"Building";"CreepTumorQueen";NA;342;0
"Building";"CreepTumor";NA;342;0
"Building";"CreepTumorQueen";NA;342;0
"Building";"SpineCrawler";NA;342;0
"Building";"CreepTumor";NA;342;0
"Building";"CreepTumor";NA;342;0
"Building";"CreepTumor";NA;342;0
"Building";"Hatchery";NA;318;0
"Building";"CreepTumor";NA;349;0
"Unit";"Baneling";"Zergling";349;0
"Unit";"Baneling";"Zergling";349;0
"Unit";"Baneling";"Zergling";349;0
"Unit";"Baneling";"Zergling";349;0
"Unit";"Baneling";"Zergling";349;0
"Unit";"Baneling";"Zergling";349;0
"Unit";"Baneling";"Zergling";349;0
"Unit";"Baneling";"Zergling";349;0
"Unit";"Baneling";"Zergling";349;0
"Unit";"Baneling";"Zergling";349;0
"Unit";"Baneling";"Zergling";349;0
"Unit";"Baneling";"Zergling";349;0
"Unit";"Baneling";"Zergling";349;0
"Unit";"Baneling";"Zergling";349;0
"Unit";"Baneling";"Zergling";349;0
"Unit";"Baneling";"Zergling";349;0
"Unit";"Baneling";"Zergling";349;0
"Unit";"Baneling";"Zergling";349;0
"Unit";"Baneling";"Zergling";349;0
"Unit";"Baneling";"Zergling";349;0
"Building";"CreepTumor";NA;349;0
"Building";"Extractor";NA;349;0
"Building";"CreepTumor";NA;349;0
"Unit";"Zergling";"Larva";349;1
"Unit";"Zergling";"Larva";349;1
"Unit";"Zergling";"Larva";349;1
"Unit";"Zergling";"Larva";349;1
"Unit";"Zergling";"Larva";349;1
"Unit";"Zergling";"Larva";349;1
"Unit";"Zergling";"Larva";349;1
"Unit";"Zergling";"Larva";349;1
"Unit";"Ultralisk";"Larva";342;6
"Unit";"Ultralisk";"Larva";342;6
"Unit";"Ultralisk";"Larva";342;6
"Unit";"Baneling";"Zergling";349;0
"Unit";"Baneling";"Zergling";349;0
"Unit";"Baneling";"Zergling";349;0
"Unit";"Baneling";"Zergling";349;0
"Unit";"Baneling";"Zergling";349;0
"Unit";"Baneling";"Zergling";349;0
"Unit";"Baneling";"Zergling";349;0
"Unit";"Baneling";"Zergling";349;0
"Unit";"Baneling";"Zergling";349;0
"Unit";"Baneling";"Zergling";349;0
"Unit";"Baneling";"Zergling";349;0
"Unit";"Baneling";"Zergling";349;0
"Unit";"Baneling";"Zergling";349;0
"Unit";"Baneling";"Zergling";349;0
"Unit";"Baneling";"Zergling";349;0
"Upgrade";"ChitinousPlating";"UltraliskCavern";342;0
"Unit";"Ultralisk";"Larva";349;6
"Building";"CreepTumorQueen";NA;375;0
"Unit";"Zergling";"Larva";375;1
"Unit";"Zergling";"Larva";375;1
"Unit";"Zergling";"Larva";375;1
"Unit";"Zergling";"Larva";375;1
"Unit";"Zergling";"Larva";375;1
"Unit";"Zergling";"Larva";375;1
"Unit";"Zergling";"Larva";375;1
"Unit";"Zergling";"Larva";375;1
"Unit";"Zergling";"Larva";375;1
"Unit";"Zergling";"Larva";375;1
"Building";"CreepTumorQueen";NA;381;0
"Building";"CreepTumor";NA;381;0
"Building";"CreepTumor";NA;381;0
"Unit";"Mutalisk";"Larva";375;2
"Unit";"Mutalisk";"Larva";375;2
"Building";"CreepTumor";NA;381;0
"Building";"CreepTumor";NA;381;0
"Building";"CreepTumor";NA;381;0
"Building";"CreepTumor";NA;381;0
"Building";"CreepTumor";NA;381;0
"Building";"CreepTumor";NA;381;0
"Building";"Extractor";NA;395;0
"Building";"Extractor";NA;395;0
"Building";"Hatchery";NA;357;0
"Unit";"Overlord";"Larva";395;0
"Unit";"Ultralisk";"Larva";395;6
"Unit";"Ultralisk";"Larva";395;6
"Building";"CreepTumor";NA;395;0
"Building";"CreepTumor";NA;395;0
"Building";"CreepTumor";NA;395;0
"Building";"CreepTumor";NA;395;0
"Building";"CreepTumor";NA;395;0
"Building";"CreepTumor";NA;395;0
"Building";"CreepTumor";NA;395;0
"Building";"CreepTumor";NA;395;0
"Building";"CreepTumor";NA;395;0
"Upgrade";"ZergMeleeWeaponsLevel3";"EvolutionChamber";349;0
"Upgrade";"ZergGroundArmorsLevel3";"EvolutionChamber";349;0
"Unit";"Zergling";"Larva";407;1
"Unit";"Zergling";"Larva";407;1
"Unit";"Overlord";"Larva";407;0
"Unit";"Zergling";"Larva";407;1
"Unit";"Zergling";"Larva";407;1
"Unit";"Zergling";"Larva";407;1
"Unit";"Zergling";"Larva";407;1
"Unit";"Zergling";"Larva";407;1
"Unit";"Zergling";"Larva";407;1
"Unit";"Zergling";"Larva";407;1
"Unit";"Zergling";"Larva";407;1
"Unit";"Zergling";"Larva";407;1
"Unit";"Zergling";"Larva";407;1
"Unit";"Zergling";"Larva";407;1
"Unit";"Zergling";"Larva";407;1
"Unit";"Zergling";"Larva";407;1
"Unit";"Zergling";"Larva";407;1
"Unit";"Zergling";"Larva";407;1
"Unit";"Zergling";"Larva";407;1
"Unit";"Zergling";"Larva";407;1
"Unit";"Zergling";"Larva";407;1
"Unit";"Zergling";"Larva";407;1
"Unit";"Zergling";"Larva";407;1
"Unit";"Zergling";"Larva";407;1
"Unit";"Zergling";"Larva";407;1
"Unit";"Mutalisk";"Larva";407;2
"Unit";"Mutalisk";"Larva";407;2
"Unit";"Mutalisk";"Larva";407;2
"Unit";"Mutalisk";"Larva";407;2
"Unit";"Mutalisk";"Larva";407;2
"Unit";"Mutalisk";"Larva";407;2
"Unit";"Mutalisk";"Larva";407;2
"Unit";"Mutalisk";"Larva";407;2
"Building";"SpineCrawler";NA;407;0
"Unit";"Mutalisk";"Larva";407;2
"Unit";"Mutalisk";"Larva";407;2
"Unit";"Mutalisk";"Larva";407;2
"Unit";"Mutalisk";"Larva";407;2
"Unit";"Mutalisk";"Larva";407;2
"Unit";"Mutalisk";"Larva";407;2
"Building";"CreepTumor";NA;447;0
"Building";"CreepTumor";NA;447;0
"Building";"CreepTumor";NA;447;0
"Building";"CreepTumor";NA;447;0
"Building";"CreepTumor";NA;447;0
"Building";"CreepTumor";NA;447;0
"Building";"CreepTumor";NA;447;0
"Unit";"Mutalisk";"Larva";447;2
"Unit";"Mutalisk";"Larva";447;2
"Unit";"Mutalisk";"Larva";447;2
"Unit";"Queen";"Hatchery";431;2
"Unit";"Zergling";"Larva";459;1
"Unit";"Zergling";"Larva";459;1
"Unit";"Overlord";"Larva";459;0
"Unit";"Zergling";"Larva";459;1
"Unit";"Zergling";"Larva";459;1
"Unit";"Zergling";"Larva";459;1
"Unit";"Zergling";"Larva";459;1
"Unit";"Zergling";"Larva";459;1
"Unit";"Zergling";"Larva";459;1
"Unit";"Zergling";"Larva";459;1
"Unit";"Zergling";"Larva";459;1
"Unit";"Zergling";"Larva";459;1
"Unit";"Zergling";"Larva";459;1
"Unit";"Zergling";"Larva";459;1
"Unit";"Zergling";"Larva";459;1
"Unit";"Mutalisk";"Larva";447;2
"Unit";"Mutalisk";"Larva";447;2
"Unit";"Mutalisk";"Larva";447;2
"Unit";"Mutalisk";"Larva";447;2
"Building";"CreepTumor";NA;489;0
"Building";"CreepTumor";NA;489;0
"Building";"CreepTumor";NA;489;0
"Building";"CreepTumor";NA;489;0
"Building";"CreepTumor";NA;489;0
"Building";"CreepTumor";NA;489;0
"Unit";"Baneling";"Zergling";489;0
"Unit";"Baneling";"Zergling";489;0
"Unit";"Baneling";"Zergling";489;0
"Unit";"Zergling";"Larva";489;1
"Unit";"Zergling";"Larva";489;1
"Unit";"Zergling";"Larva";489;1
"Unit";"Zergling";"Larva";489;1
"Unit";"Zergling";"Larva";489;1
"Unit";"Zergling";"Larva";489;1
"Unit";"Zergling";"Larva";489;1
"Unit";"Zergling";"Larva";489;1
"Unit";"Zergling";"Larva";489;1
"Unit";"Zergling";"Larva";489;1
"Unit";"Mutalisk";"Larva";489;2
"Unit";"Mutalisk";"Larva";489;2
"Unit";"Mutalisk";"Larva";489;2
"Unit";"Mutalisk";"Larva";489;2
"Unit";"Mutalisk";"Larva";489;2
"Unit";"Mutalisk";"Larva";489;2
"Unit";"Mutalisk";"Larva";489;2
"Unit";"Mutalisk";"Larva";489;2
"Building";"CreepTumorQueen";NA;515;0
"Building";"CreepTumorQueen";NA;515;0
"Building";"Hatchery";NA;489;0
"Building";"CreepTumor";NA;515;0
"Building";"CreepTumor";NA;515;0
"Building";"CreepTumor";NA;515;0
"Building";"CreepTumor";NA;515;0
"Building";"CreepTumor";NA;515;0
"Building";"CreepTumor";NA;515;0
"Building";"CreepTumorQueen";NA;515;0
"Building";"Extractor";NA;515;0
"Building";"Extractor";NA;515;0
"Building";"SporeCrawler";NA;515;0
"Building";"CreepTumor";NA;515;0
"Unit";"Corruptor";"Larva";515;2
"Unit";"Mutalisk";"Larva";515;2
"Unit";"Mutalisk";"Larva";515;2
"Upgrade";"Burrow";"Hatchery";515;0
"Building";"CreepTumorQueen";NA;521;0
"Building";"CreepTumorQueen";NA;521;0
"Unit";"Zergling";"Larva";521;1
"Unit";"Zergling";"Larva";521;1
"Unit";"Overlord";"Larva";521;0
"Unit";"Zergling";"Larva";521;1
"Unit";"Zergling";"Larva";521;1
"Unit";"Zergling";"Larva";521;1
"Unit";"Zergling";"Larva";521;1
"Unit";"Zergling";"Larva";521;1
"Unit";"Zergling";"Larva";521;1
"Unit";"Zergling";"Larva";521;1
"Unit";"Zergling";"Larva";521;1
"Unit";"Zergling";"Larva";521;1
"Unit";"Zergling";"Larva";521;1
"Unit";"Mutalisk";"Larva";521;2
"Unit";"Mutalisk";"Larva";521;2
"Unit";"Mutalisk";"Larva";521;2
"Unit";"Mutalisk";"Larva";521;2
"Unit";"Mutalisk";"Larva";521;2
"Unit";"Mutalisk";"Larva";521;2
"Unit";"Mutalisk";"Larva";521;2
"Unit";"Mutalisk";"Larva";521;2
"Building";"CreepTumor";NA;521;0
"Building";"CreepTumor";NA;521;0
"Building";"CreepTumor";NA;521;0
"Unit";"Baneling";"Zergling";521;0
"Unit";"Mutalisk";"Larva";545;2
"Unit";"Mutalisk";"Larva";545;2
"Unit";"Mutalisk";"Larva";545;2
"Unit";"Mutalisk";"Larva";545;2
"Unit";"Mutalisk";"Larva";549;2
"Building";"CreepTumor";NA;559;0
"Building";"CreepTumor";NA;559;0
"Building";"CreepTumor";NA;559;0
"Building";"CreepTumor";NA;559;0
"Building";"SporeCrawler";NA;559;0
"Building";"SpineCrawler";NA;559;0
"Building";"SpineCrawler";NA;559;0
"Unit";"Corruptor";"Larva";559;2
"Unit";"Corruptor";"Larva";559;2
"Unit";"Corruptor";"Larva";559;2
"Unit";"Corruptor";"Larva";559;2
"Unit";"Corruptor";"Larva";559;2
"Unit";"Corruptor";"Larva";565;2
"Unit";"Corruptor";"Larva";565;2
"Unit";"Corruptor";"Larva";565;2
"Unit";"Corruptor";"Larva";565;2
"Unit";"Viper";"Larva";565;3
"Unit";"Viper";"Larva";565;3
"Unit";"Viper";"Larva";565;3
"Unit";"Viper";"Larva";565;3
"Unit";"Viper";"Larva";565;3
"Unit";"Viper";"Larva";565;3
"Unit";"Viper";"Larva";565;3
"Building";"CreepTumor";NA;577;0
"Building";"SporeCrawler";NA;569;0
"Building";"CreepTumor";NA;598;0
"Building";"CreepTumor";NA;598;0
"Building";"CreepTumor";NA;598;0
"Building";"SporeCrawler";NA;569;0
"Building";"SporeCrawler";NA;577;0
"Building";"SporeCrawler";NA;586;0
"Building";"SpineCrawler";NA;569;0
"Building";"SpineCrawler";NA;569;0
"Unit";"Overlord";"Larva";598;0
"Building";"SpineCrawler";NA;577;0
"Building";"SpineCrawler";NA;577;0
"Unit";"Corruptor";"Larva";598;2
"Unit";"Corruptor";"Larva";598;2
"Building";"CreepTumor";NA;598;0
"Building";"CreepTumor";NA;598;0
"Building";"CreepTumor";NA;598;0
"Unit";"Mutalisk";"Larva";602;2
"Unit";"Mutalisk";"Larva";602;2
"Unit";"Mutalisk";"Larva";602;2
"Unit";"Mutalisk";"Larva";602;2
"Unit";"Mutalisk";"Larva";602;2
"Building";"CreepTumor";NA;602;0
"Unit";"Corruptor";"Larva";612;2
"Unit";"Corruptor";"Larva";612;2
"Unit";"Corruptor";"Larva";612;2
"Unit";"Corruptor";"Larva";612;2
"Unit";"Corruptor";"Larva";612;2
"Unit";"Corruptor";"Larva";612;2
"Unit";"Viper";"Larva";612;3
"Unit";"Viper";"Larva";612;3
"Unit";"Viper";"Larva";612;3
"Unit";"Viper";"Larva";612;3
"Building";"Hatchery";NA;612;0
"Unit";"Corruptor";"Larva";624;2
"Unit";"Corruptor";"Larva";624;2
"Unit";"Corruptor";"Larva";624;2
"Unit";"Corruptor";"Larva";642;2
"Unit";"Corruptor";"Larva";642;2
"Unit";"Viper";"Larva";646;3
"Unit";"Viper";"Larva";646;3
"Unit";"Viper";"Larva";646;3
"Unit";"Viper";"Larva";646;3
"Building";"CreepTumorQueen";NA;646;0
"Unit";"Queen";"Hatchery";646;2
"Unit";"Queen";"Hatchery";646;2
"Unit";"Queen";"Hatchery";646;2
"Unit";"Queen";"Hatchery";646;2
"Unit";"Queen";"Hatchery";646;2
"Building";"Extractor";NA;658;0
"Building";"SporeCrawler";NA;658;0
"Building";"Extractor";NA;658;0
"Building";"SporeCrawler";NA;668;0
"Building";"Hatchery";NA;668;0
"Building";"Hatchery";NA;668;0
"Building";"CreepTumorQueen";NA;671;0
"Building";"CreepTumorQueen";NA;671;0
"Building";"CreepTumor";NA;671;0
"Unit";"Queen";"Hatchery";671;2
"Unit";"Queen";"Hatchery";671;2
"Unit";"Queen";"Hatchery";671;2
"Unit";"Queen";"Hatchery";671;2
"Unit";"Queen";"Hatchery";671;2
"Unit";"Corruptor";"Larva";681;2
"Unit";"Corruptor";"Larva";681;2
"Unit";"Corruptor";"Larva";681;2
"Unit";"Corruptor";"Larva";681;2
"Unit";"Corruptor";"Larva";681;2
"Unit";"Corruptor";"Larva";681;2
"Unit";"Corruptor";"Larva";681;2
"Building";"Hatchery";NA;671;0
"Unit";"Corruptor";"Larva";695;2
"Unit";"Corruptor";"Larva";695;2
"Unit";"Corruptor";"Larva";695;2
"Unit";"Corruptor";"Larva";695;2
"Building";"SporeCrawler";NA;695;0
"Building";"Hatchery";NA;681;0
"Building";"SpineCrawler";NA;695;0
"Building";"SpineCrawler";NA;695;0
"Building";"CreepTumor";NA;710;0
"Building";"CreepTumor";NA;710;0
"Building";"CreepTumorQueen";NA;710;0
"Unit";"Infestor";"Larva";710;2
"Unit";"Infestor";"Larva";710;2
"Unit";"Infestor";"Larva";710;2
"Unit";"Infestor";"Larva";710;2
"Unit";"Infestor";"Larva";710;2
"Unit";"Infestor";"Larva";710;2
"Unit";"Infestor";"Larva";710;2
"Building";"CreepTumorQueen";NA;724;0
"Building";"CreepTumorQueen";NA;724;0
"Unit";"Corruptor";"Larva";724;2
"Unit";"Corruptor";"Larva";724;2
"Unit";"Corruptor";"Larva";724;2
"Unit";"Corruptor";"Larva";724;2
"Unit";"Corruptor";"Larva";724;2
"Building";"CreepTumor";NA;724;0
"Building";"CreepTumor";NA;724;0
"Building";"CreepTumor";NA;734;0
"Building";"CreepTumor";NA;734;0
"Building";"CreepTumorQueen";NA;734;0
"Building";"CreepTumorQueen";NA;734;0
"Building";"CreepTumor";NA;734;0
"Building";"CreepTumor";NA;734;0
"Building";"SporeCrawler";NA;743;0
"Building";"Extractor";NA;743;0
"Building";"Extractor";NA;743;0
"Unit";"Queen";"Hatchery";743;2
"Unit";"Queen";"Hatchery";743;2
"Unit";"Queen";"Hatchery";743;2
"Building";"SporeCrawler";NA;743;0
"Unit";"Queen";"Hatchery";743;2
"Building";"SporeCrawler";NA;744;0
"Building";"SpineCrawler";NA;744;0
"Building";"CreepTumor";NA;752;0
"Unit";"Infestor";"Larva";752;2
"Unit";"Infestor";"Larva";752;2
"Unit";"Infestor";"Larva";752;2
"Building";"CreepTumorQueen";NA;758;0
"Building";"CreepTumorQueen";NA;758;0
"Unit";"Corruptor";"Larva";758;2
"Unit";"Corruptor";"Larva";758;2
"Unit";"Corruptor";"Larva";758;2
"Building";"SporeCrawler";NA;767;0
"Building";"SporeCrawler";NA;767;0
"Building";"SporeCrawler";NA;773;0
"Building";"SpineCrawler";NA;767;0
"Building";"SpineCrawler";NA;767;0
"Unit";"Infestor";"Larva";773;2
"Unit";"Infestor";"Larva";773;2
"Unit";"Infestor";"Larva";773;2
"Building";"CreepTumor";NA;773;0
"Building";"CreepTumor";NA;773;0
"Unit";"Queen";"Hatchery";773;2
"Unit";"Queen";"Hatchery";773;2
"Unit";"Queen";"Hatchery";773;2
"Unit";"Queen";"Hatchery";773;2
"Unit";"Queen";"Hatchery";773;2
"Building";"CreepTumor";NA;789;0
