"type";"unit_name";"on_building";"total_supply";"supply"
"Unit";"Overlord";"Larva";13;0
"Building";"Extractor";NA;17;0
"Unit";"Overlord";"Larva";21;0
"Building";"SpawningPool";NA;19;0
"Building";"Hatchery";NA;17;0
"Unit";"Zergling";"Larva";22;1
"Unit";"Zergling";"Larva";22;1
"Unit";"Zergling";"Larva";23;1
"Unit";"Zergling";"Larva";23;1
"Unit";"Queen";"Hatchery";22;2
"Unit";"Queen";"Hatchery";23;2
"Unit";"Overlord";"Larva";34;0
"Unit";"Overlord";"Larva";37;0
"Building";"Hatchery";NA;29;0
"Unit";"Overlord";"Larva";47;0
"Building";"Extractor";NA;48;0
"Unit";"Queen";"Hatchery";48;2
"Unit";"Queen";"Hatchery";48;2
"Unit";"Zergling";"Larva";50;1
"Unit";"Zergling";"Larva";50;1
"Unit";"Zergling";"Larva";50;1
"Unit";"Zergling";"Larva";50;1
"Unit";"Zergling";"Larva";50;1
"Unit";"Zergling";"Larva";50;1
"Unit";"Zergling";"Larva";50;1
"Unit";"Zergling";"Larva";50;1
"Unit";"Zergling";"Larva";50;1
"Unit";"Zergling";"Larva";50;1
"Unit";"Zergling";"Larva";50;1
"Unit";"Zergling";"Larva";50;1
"Unit";"Zergling";"Larva";50;1
"Unit";"Zergling";"Larva";50;1
"Unit";"Zergling";"Larva";50;1
"Unit";"Zergling";"Larva";50;1
"Unit";"Queen";"Hatchery";48;2
"Building";"CreepTumorQueen";NA;70;0
"Building";"CreepTumorQueen";NA;70;0
"Building";"BanelingNest";NA;50;0
"Building";"CreepTumor";NA;79;0
"Unit";"Overlord";"Larva";79;0
"Unit";"Overlord";"Larva";86;0
"Unit";"Queen";"Hatchery";79;2
"Unit";"Queen";"Hatchery";79;2
"Unit";"Overlord";"Larva";88;0
"Unit";"Overlord";"Larva";88;0
"Building";"EvolutionChamber";NA;88;0
"Building";"CreepTumorQueen";NA;94;0
"Building";"CreepTumorQueen";NA;94;0
"Building";"CreepTumorQueen";NA;94;0
"Building";"EvolutionChamber";NA;88;0
"Building";"CreepTumor";NA;94;0
"Building";"CreepTumorQueen";NA;94;0
"Building";"Extractor";NA;90;0
"Unit";"Overlord";"Larva";94;0
"Unit";"Zergling";"Larva";94;1
"Unit";"Zergling";"Larva";94;1
"Unit";"Zergling";"Larva";94;1
"Unit";"Zergling";"Larva";94;1
"Unit";"Zergling";"Larva";94;1
"Unit";"Zergling";"Larva";94;1
"Unit";"Zergling";"Larva";94;1
"Unit";"Zergling";"Larva";94;1
"Unit";"Zergling";"Larva";94;1
"Unit";"Zergling";"Larva";94;1
"Unit";"Zergling";"Larva";94;1
"Unit";"Zergling";"Larva";94;1
"Unit";"Zergling";"Larva";94;1
"Unit";"Zergling";"Larva";94;1
"Unit";"Zergling";"Larva";94;1
"Unit";"Zergling";"Larva";94;1
"Building";"CreepTumor";NA;94;0
"Building";"CreepTumorQueen";NA;110;0
"Building";"CreepTumorQueen";NA;110;0
"Building";"CreepTumor";NA;110;0
"Building";"CreepTumor";NA;110;0
"Building";"CreepTumor";NA;110;0
"Building";"CreepTumor";NA;110;0
"Building";"HydraliskDen";NA;94;0
"Building";"CreepTumorQueen";NA;110;0
"Building";"CreepTumorQueen";NA;110;0
"Building";"CreepTumorQueen";NA;119;0
"Building";"Extractor";NA;119;0
"Building";"Extractor";NA;119;0
"Building";"Extractor";NA;119;0
"Unit";"Zergling";"Larva";119;1
"Unit";"Zergling";"Larva";119;1
"Unit";"Zergling";"Larva";119;1
"Unit";"Zergling";"Larva";119;1
"Unit";"Zergling";"Larva";119;1
"Unit";"Zergling";"Larva";119;1
"Unit";"Zergling";"Larva";119;1
"Unit";"Zergling";"Larva";119;1
"Unit";"Zergling";"Larva";119;1
"Unit";"Zergling";"Larva";119;1
"Building";"CreepTumor";NA;130;0
"Building";"CreepTumor";NA;130;0
"Building";"CreepTumor";NA;130;0
"Building";"CreepTumor";NA;130;0
"Building";"CreepTumor";NA;130;0
"Building";"CreepTumor";NA;130;0
"Building";"CreepTumor";NA;130;0
"Building";"SporeCrawler";NA;128;0
"Building";"SporeCrawler";NA;128;0
"Building";"SporeCrawler";NA;128;0
"Building";"CreepTumor";NA;141;0
"Building";"CreepTumorQueen";NA;143;0
"Unit";"Overlord";"Larva";140;0
"Unit";"Overlord";"Larva";140;0
"Unit";"Overlord";"Larva";140;0
"Building";"CreepTumor";NA;143;0
"Building";"CreepTumorQueen";NA;143;0
"Building";"CreepTumorQueen";NA;143;0
"Building";"CreepTumorQueen";NA;143;0
"Building";"CreepTumor";NA;143;0
"Unit";"Hydralisk";"Larva";140;2
"Building";"CreepTumor";NA;143;0
"Unit";"Hydralisk";"Larva";140;2
"Building";"CreepTumor";NA;143;0
"Unit";"Hydralisk";"Larva";140;2
"Unit";"Hydralisk";"Larva";140;2
"Unit";"Hydralisk";"Larva";140;2
"Unit";"Hydralisk";"Larva";140;2
"Building";"CreepTumor";NA;143;0
"Building";"CreepTumor";NA;143;0
"Building";"CreepTumor";NA;143;0
"Building";"CreepTumorQueen";NA;143;0
"Building";"CreepTumor";NA;143;0
"Building";"CreepTumorQueen";NA;143;0
"Building";"CreepTumorQueen";NA;143;0
"Building";"CreepTumorQueen";NA;143;0
"Upgrade";"EvolveGroovedSpines";"HydraliskDen";128;0
"Upgrade";"ZergMeleeWeaponsLevel1";"EvolutionChamber";119;0
"Upgrade";"ZergGroundArmorsLevel1";"EvolutionChamber";119;0
"Unit";"Overlord";"Larva";143;0
"Unit";"Overlord";"Larva";143;0
"Unit";"Overlord";"Larva";143;0
"Unit";"Overlord";"Larva";143;0
"Building";"Hatchery";NA;119;0
"Building";"CreepTumor";NA;155;0
"Unit";"Hydralisk";"Larva";155;2
"Building";"CreepTumor";NA;155;0
"Building";"CreepTumor";NA;155;0
"Building";"CreepTumor";NA;155;0
"Building";"CreepTumor";NA;155;0
"Building";"CreepTumor";NA;155;0
"Unit";"Hydralisk";"Larva";155;2
"Unit";"Hydralisk";"Larva";155;2
"Unit";"Hydralisk";"Larva";155;2
"Unit";"Hydralisk";"Larva";155;2
"Unit";"Hydralisk";"Larva";155;2
"Unit";"Hydralisk";"Larva";155;2
"Unit";"Hydralisk";"Larva";155;2
"Unit";"Hydralisk";"Larva";155;2
"Unit";"Hydralisk";"Larva";155;2
"Unit";"Zergling";"Larva";155;1
"Unit";"Zergling";"Larva";155;1
"Unit";"Zergling";"Larva";155;1
"Unit";"Zergling";"Larva";155;1
"Unit";"Zergling";"Larva";155;1
"Unit";"Zergling";"Larva";155;1
"Unit";"Zergling";"Larva";155;1
"Unit";"Zergling";"Larva";155;1
"Unit";"Zergling";"Larva";155;1
"Unit";"Zergling";"Larva";155;1
"Unit";"Zergling";"Larva";155;1
"Unit";"Zergling";"Larva";155;1
"Unit";"Zergling";"Larva";155;1
"Unit";"Zergling";"Larva";155;1
"Unit";"Zergling";"Larva";155;1
"Unit";"Zergling";"Larva";155;1
"Unit";"Zergling";"Larva";155;1
"Unit";"Zergling";"Larva";155;1
"Unit";"Baneling";"Zergling";175;0
"Unit";"Baneling";"Zergling";175;0
"Unit";"Baneling";"Zergling";175;0
"Unit";"Baneling";"Zergling";175;0
"Unit";"Baneling";"Zergling";175;0
"Unit";"Baneling";"Zergling";175;0
"Unit";"Baneling";"Zergling";175;0
"Unit";"Baneling";"Zergling";175;0
"Building";"InfestationPit";NA;155;0
"Unit";"Baneling";"Zergling";193;0
"Unit";"Baneling";"Zergling";193;0
"Unit";"Baneling";"Zergling";193;0
"Unit";"Baneling";"Zergling";193;0
"Unit";"Baneling";"Zergling";193;0
"Unit";"Baneling";"Zergling";193;0
"Unit";"Baneling";"Zergling";193;0
"Unit";"Baneling";"Zergling";193;0
"Building";"CreepTumor";NA;193;0
"Building";"CreepTumor";NA;193;0
"Building";"CreepTumor";NA;193;0
"Building";"CreepTumor";NA;193;0
"Building";"CreepTumor";NA;193;0
"Unit";"Baneling";"Zergling";193;0
"Building";"CreepTumor";NA;193;0
"Building";"CreepTumor";NA;193;0
"Building";"CreepTumor";NA;193;0
"Building";"CreepTumor";NA;193;0
"Building";"CreepTumor";NA;193;0
"Building";"CreepTumor";NA;193;0
"Building";"CreepTumor";NA;193;0
"Building";"CreepTumor";NA;193;0
"Building";"CreepTumor";NA;193;0
"Building";"CreepTumor";NA;193;0
"Building";"CreepTumor";NA;193;0
"Building";"CreepTumor";NA;193;0
"Unit";"Overlord";"Larva";193;0
"Unit";"Overlord";"Larva";193;0
"Unit";"Overlord";"Larva";193;0
"Unit";"Baneling";"Zergling";193;0
"Unit";"Baneling";"Zergling";193;0
"Unit";"Baneling";"Zergling";193;0
"Unit";"Baneling";"Zergling";193;0
"Unit";"Baneling";"Zergling";193;0
"Unit";"Baneling";"Zergling";193;0
"Unit";"Baneling";"Zergling";193;0
"Unit";"Baneling";"Zergling";193;0
"Unit";"Baneling";"Zergling";193;0
"Unit";"Baneling";"Zergling";193;0
"Unit";"Baneling";"Zergling";193;0
"Unit";"Baneling";"Zergling";193;0
"Unit";"Baneling";"Zergling";193;0
"Unit";"Zergling";"Larva";193;1
"Unit";"Zergling";"Larva";193;1
"Unit";"Zergling";"Larva";193;1
"Unit";"Zergling";"Larva";193;1
"Unit";"Zergling";"Larva";193;1
"Unit";"Zergling";"Larva";193;1
"Unit";"Zergling";"Larva";193;1
"Unit";"Zergling";"Larva";193;1
"Unit";"Zergling";"Larva";193;1
"Unit";"Zergling";"Larva";193;1
"Unit";"Zergling";"Larva";193;1
"Unit";"Zergling";"Larva";193;1
"Unit";"Zergling";"Larva";193;1
"Unit";"Zergling";"Larva";193;1
"Unit";"Zergling";"Larva";193;1
"Unit";"Zergling";"Larva";193;1
"Unit";"Zergling";"Larva";193;1
"Unit";"Zergling";"Larva";193;1
"Unit";"Zergling";"Larva";193;1
"Unit";"Zergling";"Larva";193;1
"Unit";"Zergling";"Larva";193;1
"Unit";"Zergling";"Larva";193;1
"Unit";"Zergling";"Larva";193;1
"Unit";"Zergling";"Larva";193;1
"Unit";"Zergling";"Larva";193;1
"Unit";"Zergling";"Larva";193;1
"Unit";"Zergling";"Larva";193;1
"Unit";"Zergling";"Larva";193;1
"Unit";"Zergling";"Larva";193;1
"Unit";"Zergling";"Larva";193;1
"Unit";"Zergling";"Larva";193;1
"Unit";"Zergling";"Larva";193;1
"Unit";"Zergling";"Larva";193;1
"Unit";"Zergling";"Larva";193;1
"Building";"LurkerDenMP";NA;155;0
"Building";"Hatchery";NA;193;0
"Upgrade";"ZergMeleeWeaponsLevel2";"EvolutionChamber";175;0
"Upgrade";"ZergGroundArmorsLevel2";"EvolutionChamber";175;0
"Upgrade";"EvolveMuscularAugments";"HydraliskDen";193;0
"Building";"CreepTumor";NA;227;0
"Building";"CreepTumor";NA;227;0
"Building";"CreepTumor";NA;227;0
"Building";"CreepTumor";NA;227;0
"Building";"CreepTumor";NA;227;0
"Building";"CreepTumor";NA;227;0
"Building";"CreepTumor";NA;227;0
"Building";"CreepTumor";NA;227;0
"Building";"CreepTumor";NA;227;0
"Building";"CreepTumor";NA;227;0
"Building";"CreepTumor";NA;240;0
"Building";"CreepTumor";NA;240;0
"Building";"CreepTumor";NA;240;0
"Building";"CreepTumor";NA;240;0
"Building";"CreepTumor";NA;240;0
"Building";"CreepTumor";NA;240;0
"Building";"CreepTumor";NA;240;0
"Building";"CreepTumorQueen";NA;240;0
"Building";"CreepTumorQueen";NA;240;0
"Building";"CreepTumorQueen";NA;240;0
"Building";"CreepTumorQueen";NA;240;0
"Building";"Extractor";NA;240;0
"Building";"CreepTumorQueen";NA;240;0
"Building";"Extractor";NA;240;0
"Building";"CreepTumor";NA;240;0
"Building";"CreepTumor";NA;240;0
"Building";"UltraliskCavern";NA;240;0
"Building";"CreepTumor";NA;240;0
"Building";"CreepTumor";NA;240;0
"Building";"CreepTumor";NA;240;0
"Building";"CreepTumor";NA;240;0
"Unit";"Overlord";"Larva";240;0
"Unit";"Overlord";"Larva";240;0
"Unit";"Overlord";"Larva";240;0
"Unit";"Zergling";"Larva";240;1
"Unit";"Zergling";"Larva";240;1
"Unit";"Zergling";"Larva";240;1
"Unit";"Zergling";"Larva";240;1
"Unit";"Zergling";"Larva";240;1
"Unit";"Zergling";"Larva";240;1
"Unit";"Zergling";"Larva";240;1
"Unit";"Zergling";"Larva";240;1
"Unit";"Zergling";"Larva";240;1
"Unit";"Zergling";"Larva";240;1
"Unit";"Zergling";"Larva";240;1
"Unit";"Zergling";"Larva";240;1
"Unit";"Zergling";"Larva";240;1
"Unit";"Zergling";"Larva";240;1
"Unit";"Zergling";"Larva";240;1
"Unit";"Zergling";"Larva";240;1
"Unit";"Zergling";"Larva";240;1
"Unit";"Zergling";"Larva";240;1
"Unit";"Zergling";"Larva";240;1
"Unit";"Zergling";"Larva";240;1
"Unit";"Zergling";"Larva";240;1
"Unit";"Zergling";"Larva";240;1
"Unit";"Zergling";"Larva";240;1
"Unit";"Zergling";"Larva";240;1
"Unit";"Zergling";"Larva";240;1
"Unit";"Zergling";"Larva";240;1
"Unit";"Zergling";"Larva";240;1
"Unit";"Zergling";"Larva";240;1
"Unit";"Zergling";"Larva";240;1
"Unit";"Zergling";"Larva";240;1
"Unit";"Zergling";"Larva";240;1
"Unit";"Zergling";"Larva";240;1
"Unit";"Zergling";"Larva";240;1
"Unit";"Zergling";"Larva";240;1
"Unit";"Zergling";"Larva";240;1
"Unit";"Zergling";"Larva";240;1
"Unit";"Zergling";"Larva";240;1
"Unit";"Zergling";"Larva";240;1
"Unit";"Baneling";"Zergling";240;0
"Unit";"Baneling";"Zergling";240;0
"Unit";"Baneling";"Zergling";240;0
"Unit";"Baneling";"Zergling";240;0
"Unit";"Baneling";"Zergling";240;0
"Unit";"Baneling";"Zergling";240;0
"Unit";"Baneling";"Zergling";240;0
"Unit";"Baneling";"Zergling";240;0
"Unit";"Hydralisk";"Larva";240;2
"Unit";"Hydralisk";"Larva";240;2
"Unit";"Hydralisk";"Larva";240;2
"Unit";"Hydralisk";"Larva";240;2
"Unit";"Hydralisk";"Larva";240;2
"Unit";"Hydralisk";"Larva";240;2
"Unit";"Baneling";"Zergling";240;0
"Unit";"Hydralisk";"Larva";240;2
"Unit";"Hydralisk";"Larva";240;2
"Unit";"Hydralisk";"Larva";240;2
"Unit";"Hydralisk";"Larva";240;2
"Unit";"Hydralisk";"Larva";240;2
"Unit";"Baneling";"Zergling";240;0
"Unit";"Viper";"Larva";240;3
"Unit";"Viper";"Larva";240;3
"Unit";"Viper";"Larva";240;3
"Building";"CreepTumor";NA;240;0
"Building";"CreepTumor";NA;240;0
"Building";"CreepTumor";NA;242;0
"Building";"CreepTumor";NA;242;0
"Building";"CreepTumor";NA;242;0
"Unit";"Overlord";"Larva";280;0
"Unit";"Overlord";"Larva";292;0
"Unit";"Overlord";"Larva";300;0
"Unit";"Overlord";"Larva";309;0
"Unit";"Overlord";"Larva";309;0
"Unit";"Overlord";"Larva";309;0
"Unit";"Baneling";"Zergling";309;0
"Unit";"Baneling";"Zergling";309;0
"Unit";"Baneling";"Zergling";309;0
"Unit";"Zergling";"Larva";309;1
"Unit";"Zergling";"Larva";309;1
"Unit";"Zergling";"Larva";309;1
"Unit";"Zergling";"Larva";309;1
"Unit";"Zergling";"Larva";309;1
"Unit";"Zergling";"Larva";309;1
"Unit";"Zergling";"Larva";309;1
"Unit";"Zergling";"Larva";309;1
"Unit";"Zergling";"Larva";309;1
"Unit";"Zergling";"Larva";309;1
"Unit";"Zergling";"Larva";309;1
"Unit";"Zergling";"Larva";309;1
"Unit";"Zergling";"Larva";309;1
"Unit";"Zergling";"Larva";309;1
"Unit";"Zergling";"Larva";309;1
"Unit";"Zergling";"Larva";309;1
"Unit";"Zergling";"Larva";309;1
"Unit";"Zergling";"Larva";309;1
"Unit";"Zergling";"Larva";309;1
"Unit";"Zergling";"Larva";309;1
"Unit";"Zergling";"Larva";309;1
"Unit";"Zergling";"Larva";309;1
"Unit";"Zergling";"Larva";309;1
"Unit";"Zergling";"Larva";309;1
"Unit";"Zergling";"Larva";309;1
"Unit";"Zergling";"Larva";309;1
"Upgrade";"ZergMeleeWeaponsLevel3";"EvolutionChamber";240;0
"Upgrade";"ZergGroundArmorsLevel3";"EvolutionChamber";240;0
"Unit";"Baneling";"Zergling";335;0
"Unit";"Baneling";"Zergling";335;0
"Unit";"Baneling";"Zergling";335;0
"Unit";"Baneling";"Zergling";335;0
"Unit";"Baneling";"Zergling";335;0
"Unit";"Baneling";"Zergling";335;0
"Unit";"Baneling";"Zergling";335;0
"Unit";"Baneling";"Zergling";335;0
"Unit";"Baneling";"Zergling";335;0
"Unit";"Baneling";"Zergling";335;0
"Unit";"Baneling";"Zergling";335;0
"Unit";"Baneling";"Zergling";335;0
"Unit";"Baneling";"Zergling";335;0
"Unit";"Baneling";"Zergling";335;0
"Unit";"Baneling";"Zergling";335;0
"Unit";"Baneling";"Zergling";335;0
"Unit";"Baneling";"Zergling";335;0
"Unit";"Baneling";"Zergling";335;0
"Unit";"Baneling";"Zergling";335;0
"Unit";"Ultralisk";"Larva";309;6
"Unit";"Ultralisk";"Larva";309;6
"Unit";"Ultralisk";"Larva";309;6
"Unit";"Ultralisk";"Larva";309;6
"Unit";"Ultralisk";"Larva";309;6
"Unit";"Ultralisk";"Larva";309;6
"Unit";"Zergling";"Larva";335;1
"Unit";"Zergling";"Larva";335;1
"Unit";"Zergling";"Larva";335;1
"Unit";"Zergling";"Larva";335;1
"Unit";"Zergling";"Larva";335;1
"Unit";"Zergling";"Larva";335;1
"Unit";"Zergling";"Larva";335;1
"Unit";"Zergling";"Larva";335;1
"Unit";"Zergling";"Larva";335;1
"Unit";"Zergling";"Larva";335;1
"Unit";"Zergling";"Larva";335;1
"Unit";"Zergling";"Larva";335;1
"Unit";"Zergling";"Larva";335;1
"Unit";"Zergling";"Larva";335;1
"Unit";"Zergling";"Larva";335;1
"Unit";"Zergling";"Larva";335;1
"Unit";"Zergling";"Larva";335;1
"Unit";"Zergling";"Larva";335;1
"Unit";"Zergling";"Larva";335;1
"Unit";"Zergling";"Larva";335;1
"Unit";"Zergling";"Larva";335;1
"Unit";"Zergling";"Larva";335;1
"Building";"CreepTumor";NA;335;0
"Building";"CreepTumor";NA;335;0
"Building";"CreepTumor";NA;335;0
"Building";"CreepTumor";NA;335;0
"Building";"CreepTumor";NA;335;0
"Building";"CreepTumor";NA;371;0
"Building";"CreepTumor";NA;371;0
"Building";"CreepTumor";NA;371;0
"Building";"CreepTumor";NA;371;0
"Unit";"Zergling";"Larva";371;1
"Unit";"Zergling";"Larva";371;1
"Unit";"Zergling";"Larva";371;1
"Unit";"Zergling";"Larva";371;1
"Unit";"Zergling";"Larva";371;1
"Unit";"Zergling";"Larva";371;1
"Unit";"Zergling";"Larva";371;1
"Unit";"Zergling";"Larva";371;1
"Unit";"Zergling";"Larva";371;1
"Unit";"Zergling";"Larva";371;1
"Unit";"Zergling";"Larva";371;1
"Unit";"Zergling";"Larva";371;1
"Unit";"Zergling";"Larva";371;1
"Unit";"Zergling";"Larva";371;1
"Unit";"Zergling";"Larva";371;1
"Unit";"Zergling";"Larva";371;1
"Building";"CreepTumor";NA;409;0
"Building";"CreepTumor";NA;409;0
"Building";"CreepTumor";NA;409;0
"Building";"CreepTumor";NA;409;0
"Building";"CreepTumor";NA;409;0
"Building";"Hatchery";NA;335;0
"Unit";"Zergling";"Larva";409;1
"Unit";"Zergling";"Larva";409;1
"Unit";"Zergling";"Larva";409;1
"Unit";"Zergling";"Larva";409;1
"Unit";"Zergling";"Larva";409;1
"Unit";"Zergling";"Larva";409;1
"Unit";"Zergling";"Larva";409;1
"Unit";"Zergling";"Larva";409;1
"Unit";"Zergling";"Larva";409;1
"Unit";"Zergling";"Larva";409;1
"Unit";"Zergling";"Larva";409;1
"Unit";"Zergling";"Larva";409;1
"Unit";"Zergling";"Larva";409;1
"Unit";"Zergling";"Larva";409;1
"Unit";"Zergling";"Larva";409;1
"Unit";"Zergling";"Larva";409;1
"Unit";"Zergling";"Larva";409;1
"Unit";"Zergling";"Larva";409;1
"Unit";"Zergling";"Larva";409;1
"Unit";"Zergling";"Larva";409;1
"Unit";"Zergling";"Larva";409;1
"Unit";"Zergling";"Larva";409;1
"Unit";"Zergling";"Larva";409;1
"Unit";"Zergling";"Larva";409;1
"Unit";"Zergling";"Larva";409;1
"Unit";"Zergling";"Larva";409;1
"Unit";"Zergling";"Larva";409;1
"Unit";"Zergling";"Larva";409;1
"Unit";"Zergling";"Larva";409;1
"Unit";"Zergling";"Larva";409;1
"Unit";"Zergling";"Larva";409;1
"Unit";"Zergling";"Larva";409;1
"Unit";"Zergling";"Larva";409;1
"Unit";"Zergling";"Larva";409;1
"Unit";"Zergling";"Larva";409;1
"Unit";"Zergling";"Larva";409;1
"Unit";"Zergling";"Larva";409;1
"Unit";"Zergling";"Larva";409;1
"Unit";"Zergling";"Larva";409;1
"Unit";"Zergling";"Larva";409;1
"Upgrade";"ChitinousPlating";"UltraliskCavern";393;0
"Unit";"Ultralisk";"Larva";409;6
"Unit";"Ultralisk";"Larva";409;6
"Unit";"Ultralisk";"Larva";409;6
"Unit";"Ultralisk";"Larva";409;6
"Unit";"Queen";"Hatchery";409;2
"Unit";"Baneling";"Zergling";475;0
"Unit";"Baneling";"Zergling";475;0
"Unit";"Baneling";"Zergling";475;0
"Unit";"Baneling";"Zergling";475;0
"Unit";"Baneling";"Zergling";475;0
"Unit";"Baneling";"Zergling";475;0
"Unit";"Baneling";"Zergling";475;0
"Unit";"Baneling";"Zergling";475;0
"Unit";"Baneling";"Zergling";475;0
"Unit";"Baneling";"Zergling";475;0
"Unit";"Baneling";"Zergling";475;0
"Unit";"Baneling";"Zergling";475;0
"Unit";"Baneling";"Zergling";475;0
"Unit";"Baneling";"Zergling";475;0
"Unit";"Baneling";"Zergling";475;0
"Unit";"Baneling";"Zergling";475;0
"Unit";"Baneling";"Zergling";475;0
"Building";"CreepTumor";NA;475;0
"Building";"CreepTumor";NA;475;0
"Building";"CreepTumor";NA;475;0
"Unit";"Zergling";"Larva";475;1
"Unit";"Zergling";"Larva";475;1
"Building";"CreepTumor";NA;475;0
"Building";"CreepTumor";NA;475;0
"Building";"CreepTumor";NA;475;0
"Building";"CreepTumor";NA;475;0
"Building";"CreepTumor";NA;475;0
"Unit";"Hydralisk";"Larva";475;2
"Unit";"Hydralisk";"Larva";475;2
"Unit";"Hydralisk";"Larva";475;2
"Unit";"Hydralisk";"Larva";475;2
"Unit";"Hydralisk";"Larva";475;2
"Unit";"Hydralisk";"Larva";475;2
"Building";"Extractor";NA;489;0
