"type";"unit_name";"on_building";"total_supply";"supply"
"Unit";"Overlord";"Larva";13;0
"Building";"SpawningPool";NA;18;0
"Building";"Hatchery";NA;16;0
"Unit";"Zergling";"Larva";24;1
"Unit";"Zergling";"Larva";24;1
"Unit";"Zergling";"Larva";24;1
"Unit";"Zergling";"Larva";24;1
"Unit";"Overlord";"Larva";24;0
"Unit";"Queen";"Hatchery";23;2
"Unit";"Queen";"Hatchery";24;2
"Unit";"Overlord";"Larva";24;0
"Building";"Hatchery";NA;22;0
"Unit";"Overlord";"Larva";36;0
"Unit";"Queen";"Hatchery";31;2
"Unit";"Queen";"Hatchery";33;2
"Building";"CreepTumorQueen";NA;40;0
"Building";"CreepTumorQueen";NA;42;0
"Unit";"Queen";"Hatchery";38;2
"Unit";"Overlord";"Larva";47;0
"Unit";"Overlord";"Larva";47;0
"Building";"CreepTumor";NA;50;0
"Building";"Extractor";NA;56;0
"Building";"Extractor";NA;58;0
"Unit";"Queen";"Hatchery";56;2
"Unit";"Queen";"Hatchery";56;2
"Unit";"Overlord";"Larva";58;0
"Building";"SpineCrawler";NA;58;0
"Building";"SpineCrawler";NA;58;0
"Building";"CreepTumorQueen";NA;64;0
"Building";"SporeCrawler";NA;58;0
"Building";"SporeCrawler";NA;58;0
"Building";"CreepTumorQueen";NA;64;0
"Building";"SporeCrawler";NA;58;0
"Unit";"Overlord";"Larva";64;0
"Unit";"Overlord";"Larva";70;0
"Building";"CreepTumor";NA;91;0
"Building";"CreepTumor";NA;91;0
"Unit";"Overlord";"Larva";91;0
"Building";"Extractor";NA;91;0
"Building";"Extractor";NA;91;0
"Unit";"Overlord";"Larva";91;0
"Building";"CreepTumorQueen";NA;99;0
"Unit";"Overlord";"Larva";99;0
"Unit";"Overlord";"Larva";99;0
"Unit";"Overlord";"Larva";99;0
"Building";"Extractor";NA;99;0
"Building";"Extractor";NA;99;0
"Building";"CreepTumor";NA;99;0
"Building";"CreepTumor";NA;99;0
"Unit";"Overlord";"Larva";99;0
"Unit";"Overlord";"Larva";99;0
"Building";"CreepTumorQueen";NA;108;0
"Building";"CreepTumorQueen";NA;108;0
"Unit";"Zergling";"Larva";108;1
"Unit";"Zergling";"Larva";108;1
"Unit";"Zergling";"Larva";108;1
"Unit";"Zergling";"Larva";108;1
"Unit";"Zergling";"Larva";108;1
"Unit";"Zergling";"Larva";108;1
"Unit";"Zergling";"Larva";108;1
"Unit";"Zergling";"Larva";108;1
"Unit";"Zergling";"Larva";108;1
"Unit";"Zergling";"Larva";108;1
"Unit";"Zergling";"Larva";108;1
"Unit";"Zergling";"Larva";108;1
"Unit";"Zergling";"Larva";108;1
"Unit";"Zergling";"Larva";108;1
"Unit";"Zergling";"Larva";108;1
"Unit";"Zergling";"Larva";108;1
"Unit";"Zergling";"Larva";108;1
"Unit";"Zergling";"Larva";108;1
"Building";"EvolutionChamber";NA;99;0
"Building";"CreepTumorQueen";NA;108;0
"Building";"EvolutionChamber";NA;99;0
"Building";"CreepTumorQueen";NA;108;0
"Building";"CreepTumor";NA;108;0
"Unit";"Zergling";"Larva";108;1
"Unit";"Zergling";"Larva";108;1
"Unit";"Zergling";"Larva";108;1
"Unit";"Zergling";"Larva";108;1
"Unit";"Zergling";"Larva";108;1
"Unit";"Zergling";"Larva";108;1
"Unit";"Zergling";"Larva";108;1
"Unit";"Zergling";"Larva";108;1
"Unit";"Zergling";"Larva";108;1
"Unit";"Zergling";"Larva";108;1
"Building";"HydraliskDen";NA;108;0
"Building";"CreepTumor";NA;126;0
"Building";"BanelingNest";NA;99;0
"Building";"CreepTumor";NA;141;0
"Building";"CreepTumor";NA;141;0
"Building";"CreepTumor";NA;141;0
"Building";"CreepTumor";NA;141;0
"Building";"CreepTumorQueen";NA;141;0
"Building";"CreepTumor";NA;141;0
"Unit";"Overlord";"Larva";141;0
"Unit";"Overlord";"Larva";141;0
"Unit";"Overlord";"Larva";141;0
"Building";"CreepTumorQueen";NA;141;0
"Unit";"Zergling";"Larva";141;1
"Unit";"Zergling";"Larva";141;1
"Unit";"Zergling";"Larva";141;1
"Unit";"Zergling";"Larva";141;1
"Unit";"Zergling";"Larva";141;1
"Unit";"Zergling";"Larva";141;1
"Unit";"Zergling";"Larva";141;1
"Unit";"Zergling";"Larva";141;1
"Unit";"Zergling";"Larva";141;1
"Unit";"Zergling";"Larva";141;1
"Unit";"Zergling";"Larva";141;1
"Unit";"Zergling";"Larva";141;1
"Unit";"Zergling";"Larva";141;1
"Unit";"Zergling";"Larva";141;1
"Unit";"Zergling";"Larva";141;1
"Unit";"Zergling";"Larva";141;1
"Unit";"Zergling";"Larva";141;1
"Unit";"Zergling";"Larva";141;1
"Unit";"Zergling";"Larva";141;1
"Unit";"Zergling";"Larva";141;1
"Unit";"Zergling";"Larva";141;1
"Unit";"Zergling";"Larva";141;1
"Unit";"Zergling";"Larva";141;1
"Unit";"Zergling";"Larva";141;1
"Unit";"Zergling";"Larva";141;1
"Unit";"Zergling";"Larva";141;1
"Unit";"Zergling";"Larva";141;1
"Unit";"Zergling";"Larva";141;1
"Unit";"Zergling";"Larva";141;1
"Unit";"Zergling";"Larva";141;1
"Unit";"Zergling";"Larva";141;1
"Unit";"Zergling";"Larva";141;1
"Building";"Hatchery";NA;108;0
"Unit";"Baneling";"Zergling";141;0
"Unit";"Baneling";"Zergling";141;0
"Unit";"Baneling";"Zergling";141;0
"Unit";"Baneling";"Zergling";141;0
"Unit";"Baneling";"Zergling";141;0
"Unit";"Baneling";"Zergling";141;0
"Unit";"Baneling";"Zergling";141;0
"Unit";"Baneling";"Zergling";141;0
"Unit";"Baneling";"Zergling";141;0
"Unit";"Baneling";"Zergling";141;0
"Unit";"Baneling";"Zergling";141;0
"Unit";"Baneling";"Zergling";141;0
"Unit";"Baneling";"Zergling";141;0
"Unit";"Baneling";"Zergling";141;0
"Unit";"Baneling";"Zergling";141;0
"Unit";"Baneling";"Zergling";141;0
"Unit";"Baneling";"Zergling";141;0
"Unit";"Baneling";"Zergling";141;0
"Unit";"Hydralisk";"Larva";141;2
"Unit";"Hydralisk";"Larva";141;2
"Unit";"Hydralisk";"Larva";173;2
"Unit";"Hydralisk";"Larva";173;2
"Unit";"Hydralisk";"Larva";173;2
"Building";"CreepTumorQueen";NA;177;0
"Building";"CreepTumorQueen";NA;177;0
"Upgrade";"EvolveMuscularAugments";"HydraliskDen";141;0
"Building";"CreepTumorQueen";NA;177;0
"Building";"Hatchery";NA;141;0
"Unit";"Overlord";"Larva";177;0
"Unit";"Overlord";"Larva";177;0
"Building";"CreepTumor";NA;183;0
"Building";"CreepTumorQueen";NA;183;0
"Building";"CreepTumorQueen";NA;199;0
"Building";"CreepTumorQueen";NA;199;0
"Unit";"Hydralisk";"Larva";199;2
"Unit";"Hydralisk";"Larva";199;2
"Unit";"Hydralisk";"Larva";199;2
"Upgrade";"ZergMeleeWeaponsLevel1";"EvolutionChamber";141;0
"Upgrade";"ZergGroundArmorsLevel1";"EvolutionChamber";141;0
"Building";"InfestationPit";NA;183;0
"Unit";"Hydralisk";"Larva";206;2
"Unit";"Hydralisk";"Larva";206;2
"Unit";"Hydralisk";"Larva";206;2
"Unit";"Hydralisk";"Larva";206;2
"Unit";"Hydralisk";"Larva";206;2
"Unit";"Hydralisk";"Larva";206;2
"Unit";"Zergling";"Larva";212;1
"Unit";"Zergling";"Larva";212;1
"Unit";"Zergling";"Larva";212;1
"Unit";"Zergling";"Larva";212;1
"Unit";"Zergling";"Larva";212;1
"Unit";"Zergling";"Larva";212;1
"Unit";"Zergling";"Larva";212;1
"Unit";"Zergling";"Larva";212;1
"Unit";"Zergling";"Larva";212;1
"Unit";"Zergling";"Larva";212;1
"Unit";"Zergling";"Larva";212;1
"Unit";"Zergling";"Larva";212;1
"Unit";"Zergling";"Larva";212;1
"Unit";"Zergling";"Larva";212;1
"Unit";"Zergling";"Larva";212;1
"Unit";"Zergling";"Larva";212;1
"Unit";"Zergling";"Larva";212;1
"Unit";"Zergling";"Larva";212;1
"Unit";"Zergling";"Larva";212;1
"Unit";"Zergling";"Larva";212;1
"Unit";"Zergling";"Larva";212;1
"Unit";"Zergling";"Larva";212;1
"Unit";"Zergling";"Larva";212;1
"Unit";"Zergling";"Larva";212;1
"Unit";"Zergling";"Larva";212;1
"Unit";"Zergling";"Larva";212;1
"Building";"Extractor";NA;212;0
"Building";"Extractor";NA;212;0
"Unit";"Baneling";"Zergling";224;0
"Unit";"Baneling";"Zergling";224;0
"Unit";"Baneling";"Zergling";224;0
"Unit";"Baneling";"Zergling";224;0
"Unit";"Baneling";"Zergling";224;0
"Unit";"Baneling";"Zergling";224;0
"Building";"CreepTumorQueen";NA;224;0
"Building";"CreepTumor";NA;224;0
"Building";"CreepTumorQueen";NA;224;0
"Building";"CreepTumor";NA;224;0
"Building";"CreepTumor";NA;224;0
"Upgrade";"EvolveGroovedSpines";"HydraliskDen";199;0
"Building";"CreepTumorQueen";NA;224;0
"Building";"CreepTumorQueen";NA;224;0
"Building";"CreepTumor";NA;224;0
"Building";"CreepTumor";NA;224;0
"Unit";"Overlord";"Larva";224;0
"Unit";"Overlord";"Larva";224;0
"Unit";"Overlord";"Larva";224;0
"Unit";"Overlord";"Larva";250;0
"Unit";"Zergling";"Larva";250;1
"Unit";"Zergling";"Larva";250;1
"Building";"SporeCrawler";NA;250;0
"Unit";"Zergling";"Larva";250;1
"Unit";"Zergling";"Larva";250;1
"Unit";"Zergling";"Larva";250;1
"Unit";"Zergling";"Larva";250;1
"Unit";"Zergling";"Larva";250;1
"Unit";"Zergling";"Larva";250;1
"Building";"CreepTumor";NA;250;0
"Unit";"Zergling";"Larva";250;1
"Unit";"Zergling";"Larva";250;1
"Unit";"Zergling";"Larva";250;1
"Unit";"Zergling";"Larva";250;1
"Unit";"Zergling";"Larva";250;1
"Unit";"Zergling";"Larva";250;1
"Unit";"Zergling";"Larva";250;1
"Unit";"Zergling";"Larva";250;1
"Unit";"Zergling";"Larva";250;1
"Unit";"Zergling";"Larva";250;1
"Unit";"Zergling";"Larva";250;1
"Unit";"Zergling";"Larva";250;1
"Unit";"Zergling";"Larva";250;1
"Unit";"Zergling";"Larva";250;1
"Unit";"Zergling";"Larva";250;1
"Unit";"Zergling";"Larva";250;1
"Unit";"Zergling";"Larva";250;1
"Unit";"Zergling";"Larva";250;1
"Unit";"Zergling";"Larva";250;1
"Unit";"Zergling";"Larva";250;1
"Unit";"Zergling";"Larva";250;1
"Unit";"Zergling";"Larva";250;1
"Unit";"Zergling";"Larva";250;1
"Unit";"Zergling";"Larva";250;1
"Unit";"Zergling";"Larva";250;1
"Unit";"Zergling";"Larva";250;1
"Unit";"Zergling";"Larva";250;1
"Unit";"Zergling";"Larva";250;1
"Unit";"Zergling";"Larva";250;1
"Unit";"Zergling";"Larva";250;1
"Unit";"Zergling";"Larva";250;1
"Unit";"Zergling";"Larva";250;1
"Unit";"Zergling";"Larva";250;1
"Unit";"Zergling";"Larva";250;1
"Unit";"Zergling";"Larva";250;1
"Unit";"Zergling";"Larva";250;1
"Building";"CreepTumorQueen";NA;256;0
"Building";"CreepTumorQueen";NA;256;0
"Building";"SporeCrawler";NA;250;0
"Building";"SporeCrawler";NA;250;0
"Building";"CreepTumorQueen";NA;256;0
"Building";"SporeCrawler";NA;252;0
"Building";"SporeCrawler";NA;256;0
"Building";"SpineCrawler";NA;250;0
"Unit";"Hydralisk";"Larva";256;2
"Unit";"Hydralisk";"Larva";256;2
"Unit";"Hydralisk";"Larva";256;2
"Unit";"Hydralisk";"Larva";256;2
"Unit";"Hydralisk";"Larva";256;2
"Unit";"Hydralisk";"Larva";256;2
"Unit";"Hydralisk";"Larva";256;2
"Unit";"Zergling";"Larva";300;1
"Unit";"Zergling";"Larva";300;1
"Unit";"Zergling";"Larva";300;1
"Unit";"Zergling";"Larva";300;1
"Unit";"Zergling";"Larva";300;1
"Unit";"Zergling";"Larva";300;1
"Unit";"Zergling";"Larva";300;1
"Unit";"Zergling";"Larva";300;1
"Unit";"Zergling";"Larva";300;1
"Unit";"Zergling";"Larva";300;1
"Unit";"Zergling";"Larva";300;1
"Unit";"Zergling";"Larva";300;1
"Unit";"Zergling";"Larva";300;1
"Unit";"Zergling";"Larva";300;1
"Unit";"Zergling";"Larva";300;1
"Unit";"Zergling";"Larva";300;1
"Unit";"Zergling";"Larva";300;1
"Unit";"Zergling";"Larva";300;1
"Unit";"Overlord";"Larva";300;0
"Unit";"Overlord";"Larva";300;0
"Unit";"Zergling";"Larva";332;1
"Unit";"Zergling";"Larva";332;1
"Unit";"Zergling";"Larva";332;1
"Unit";"Zergling";"Larva";332;1
"Unit";"Zergling";"Larva";332;1
"Unit";"Zergling";"Larva";332;1
"Unit";"Zergling";"Larva";332;1
"Unit";"Zergling";"Larva";332;1
"Unit";"Zergling";"Larva";332;1
"Unit";"Zergling";"Larva";332;1
"Unit";"Zergling";"Larva";332;1
"Unit";"Zergling";"Larva";332;1
"Unit";"Zergling";"Larva";332;1
"Unit";"Zergling";"Larva";332;1
"Unit";"Zergling";"Larva";332;1
"Unit";"Zergling";"Larva";332;1
"Unit";"Zergling";"Larva";332;1
"Unit";"Zergling";"Larva";332;1
"Unit";"Zergling";"Larva";332;1
"Unit";"Zergling";"Larva";332;1
"Unit";"Zergling";"Larva";332;1
"Unit";"Zergling";"Larva";332;1
"Unit";"Zergling";"Larva";332;1
"Unit";"Zergling";"Larva";332;1
"Unit";"Zergling";"Larva";332;1
"Unit";"Zergling";"Larva";332;1
"Unit";"Zergling";"Larva";332;1
"Unit";"Zergling";"Larva";332;1
"Building";"CreepTumor";NA;334;0
"Upgrade";"ZergMeleeWeaponsLevel2";"EvolutionChamber";250;0
"Upgrade";"ZergGroundArmorsLevel2";"EvolutionChamber";250;0
"Unit";"Baneling";"Zergling";360;0
"Unit";"Baneling";"Zergling";360;0
"Unit";"Baneling";"Zergling";360;0
"Unit";"Baneling";"Zergling";360;0
"Unit";"Baneling";"Zergling";360;0
"Unit";"Baneling";"Zergling";360;0
"Unit";"Baneling";"Zergling";360;0
"Unit";"Baneling";"Zergling";360;0
"Unit";"Baneling";"Zergling";360;0
"Unit";"Baneling";"Zergling";360;0
"Unit";"Baneling";"Zergling";360;0
"Unit";"Baneling";"Zergling";360;0
"Unit";"Baneling";"Zergling";360;0
"Unit";"Baneling";"Zergling";360;0
"Unit";"Baneling";"Zergling";360;0
"Unit";"Baneling";"Zergling";360;0
"Unit";"Baneling";"Zergling";360;0
"Unit";"Baneling";"Zergling";360;0
"Unit";"Baneling";"Zergling";360;0
"Unit";"Baneling";"Zergling";360;0
"Unit";"Baneling";"Zergling";360;0
"Unit";"Baneling";"Zergling";360;0
"Unit";"Baneling";"Zergling";360;0
"Unit";"Baneling";"Zergling";360;0
"Unit";"Baneling";"Zergling";360;0
"Unit";"Baneling";"Zergling";360;0
"Unit";"Baneling";"Zergling";360;0
"Unit";"Baneling";"Zergling";360;0
"Unit";"Baneling";"Zergling";360;0
"Unit";"Baneling";"Zergling";360;0
"Unit";"Baneling";"Zergling";360;0
"Unit";"Baneling";"Zergling";360;0
"Unit";"Viper";"Larva";332;3
"Unit";"Viper";"Larva";332;3
"Unit";"Viper";"Larva";332;3
"Unit";"Viper";"Larva";332;3
"Unit";"Viper";"Larva";332;3
"Building";"CreepTumorQueen";NA;360;0
"Unit";"Zergling";"Larva";360;1
"Unit";"Zergling";"Larva";360;1
"Unit";"Zergling";"Larva";360;1
"Unit";"Zergling";"Larva";360;1
"Unit";"Zergling";"Larva";360;1
"Unit";"Zergling";"Larva";360;1
"Unit";"Zergling";"Larva";360;1
"Unit";"Zergling";"Larva";360;1
"Unit";"Zergling";"Larva";360;1
"Unit";"Zergling";"Larva";360;1
"Unit";"Zergling";"Larva";360;1
"Unit";"Zergling";"Larva";360;1
"Unit";"Zergling";"Larva";360;1
"Unit";"Zergling";"Larva";360;1
"Unit";"Zergling";"Larva";360;1
"Unit";"Zergling";"Larva";360;1
"Building";"UltraliskCavern";NA;332;0
"Unit";"Zergling";"Larva";375;1
"Unit";"Zergling";"Larva";375;1
"Unit";"Zergling";"Larva";375;1
"Unit";"Zergling";"Larva";375;1
"Unit";"Zergling";"Larva";375;1
"Unit";"Zergling";"Larva";375;1
"Unit";"Zergling";"Larva";375;1
"Unit";"Zergling";"Larva";375;1
"Unit";"Zergling";"Larva";375;1
"Unit";"Zergling";"Larva";375;1
"Unit";"Zergling";"Larva";375;1
"Unit";"Zergling";"Larva";375;1
"Unit";"Zergling";"Larva";375;1
"Unit";"Zergling";"Larva";375;1
"Unit";"Zergling";"Larva";375;1
"Unit";"Zergling";"Larva";375;1
"Unit";"Zergling";"Larva";375;1
"Unit";"Zergling";"Larva";375;1
"Unit";"Zergling";"Larva";375;1
"Unit";"Zergling";"Larva";375;1
"Unit";"Zergling";"Larva";375;1
"Unit";"Zergling";"Larva";375;1
"Building";"CreepTumorQueen";NA;391;0
"Building";"CreepTumor";NA;413;0
"Unit";"Zergling";"Larva";413;1
"Unit";"Zergling";"Larva";413;1
"Unit";"Zergling";"Larva";413;1
"Unit";"Zergling";"Larva";413;1
"Unit";"Zergling";"Larva";413;1
"Unit";"Zergling";"Larva";413;1
"Unit";"Zergling";"Larva";413;1
"Unit";"Zergling";"Larva";413;1
"Unit";"Zergling";"Larva";413;1
"Unit";"Zergling";"Larva";413;1
"Unit";"Zergling";"Larva";413;1
"Unit";"Zergling";"Larva";413;1
"Unit";"Zergling";"Larva";413;1
"Unit";"Zergling";"Larva";413;1
"Unit";"Zergling";"Larva";413;1
"Unit";"Zergling";"Larva";413;1
"Unit";"Zergling";"Larva";413;1
"Unit";"Zergling";"Larva";413;1
"Unit";"Zergling";"Larva";413;1
"Unit";"Zergling";"Larva";413;1
"Unit";"Zergling";"Larva";413;1
"Unit";"Zergling";"Larva";413;1
"Unit";"Zergling";"Larva";413;1
"Unit";"Zergling";"Larva";413;1
"Unit";"Zergling";"Larva";413;1
"Unit";"Zergling";"Larva";413;1
"Unit";"Zergling";"Larva";413;1
"Unit";"Zergling";"Larva";413;1
"Unit";"Zergling";"Larva";413;1
"Unit";"Zergling";"Larva";413;1
"Unit";"Zergling";"Larva";413;1
"Unit";"Zergling";"Larva";413;1
"Unit";"Zergling";"Larva";413;1
"Unit";"Zergling";"Larva";413;1
"Unit";"Zergling";"Larva";413;1
"Unit";"Zergling";"Larva";413;1
"Unit";"Zergling";"Larva";413;1
"Unit";"Zergling";"Larva";413;1
"Unit";"Zergling";"Larva";413;1
"Unit";"Zergling";"Larva";413;1
"Unit";"Zergling";"Larva";413;1
"Unit";"Zergling";"Larva";413;1
"Unit";"Zergling";"Larva";413;1
"Unit";"Zergling";"Larva";413;1
"Unit";"Ultralisk";"Larva";413;6
"Unit";"Overlord";"Larva";463;0
"Unit";"Overlord";"Larva";463;0
"Unit";"Ultralisk";"Larva";463;6
"Unit";"Ultralisk";"Larva";463;6
"Unit";"Zergling";"Larva";463;1
"Unit";"Zergling";"Larva";463;1
"Unit";"Zergling";"Larva";463;1
"Unit";"Zergling";"Larva";463;1
"Unit";"Zergling";"Larva";463;1
"Unit";"Zergling";"Larva";463;1
"Unit";"Zergling";"Larva";463;1
"Unit";"Zergling";"Larva";463;1
"Unit";"Zergling";"Larva";463;1
"Unit";"Zergling";"Larva";463;1
"Unit";"Zergling";"Larva";463;1
"Unit";"Zergling";"Larva";463;1
"Unit";"Zergling";"Larva";463;1
"Unit";"Zergling";"Larva";463;1
"Unit";"Zergling";"Larva";463;1
"Unit";"Zergling";"Larva";463;1
"Unit";"Zergling";"Larva";463;1
"Unit";"Zergling";"Larva";463;1
"Unit";"Zergling";"Larva";463;1
"Unit";"Zergling";"Larva";463;1
"Unit";"Zergling";"Larva";463;1
"Unit";"Zergling";"Larva";463;1
"Unit";"Zergling";"Larva";463;1
"Unit";"Zergling";"Larva";463;1
"Unit";"Zergling";"Larva";463;1
"Unit";"Zergling";"Larva";463;1
"Unit";"Zergling";"Larva";463;1
"Unit";"Zergling";"Larva";463;1
"Unit";"Zergling";"Larva";463;1
"Unit";"Zergling";"Larva";463;1
"Unit";"Zergling";"Larva";463;1
"Unit";"Zergling";"Larva";463;1
"Unit";"Zergling";"Larva";463;1
"Unit";"Zergling";"Larva";463;1
"Unit";"Zergling";"Larva";463;1
"Unit";"Zergling";"Larva";463;1
"Unit";"Zergling";"Larva";463;1
"Unit";"Zergling";"Larva";463;1
