"type";"unit_name";"on_building";"total_supply";"supply"
"Unit";"Overlord";"Larva";13;0
"Building";"Extractor";NA;18;0
"Unit";"Overlord";"Larva";21;0
"Building";"SpawningPool";NA;19;0
"Building";"Hatchery";NA;17;0
"Unit";"Zergling";"Larva";22;1
"Unit";"Zergling";"Larva";22;1
"Unit";"Queen";"Hatchery";22;2
"Unit";"Queen";"Hatchery";23;2
"Building";"CreepTumorQueen";NA;34;0
"Unit";"Overlord";"Larva";36;0
"Unit";"Overlord";"Larva";36;0
"Building";"CreepTumorQueen";NA;39;0
"Building";"CreepTumor";NA;39;0
"Unit";"Queen";"Hatchery";38;2
"Building";"CreepTumorQueen";NA;49;0
"Unit";"Zergling";"Larva";47;1
"Unit";"Zergling";"Larva";47;1
"Unit";"Zergling";"Larva";47;1
"Unit";"Zergling";"Larva";47;1
"Unit";"Zergling";"Larva";47;1
"Unit";"Zergling";"Larva";47;1
"Unit";"Zergling";"Larva";47;1
"Unit";"Zergling";"Larva";47;1
"Building";"EvolutionChamber";NA;45;0
"Building";"Hatchery";NA;36;0
"Unit";"Overlord";"Larva";49;0
"Building";"Extractor";NA;49;0
"Unit";"Overlord";"Larva";49;0
"Unit";"Queen";"Hatchery";45;2
"Unit";"Zergling";"Larva";57;1
"Unit";"Zergling";"Larva";57;1
"Building";"EvolutionChamber";NA;49;0
"Unit";"Zergling";"Larva";57;1
"Unit";"Zergling";"Larva";57;1
"Building";"CreepTumorQueen";NA;59;0
"Building";"CreepTumor";NA;57;0
"Building";"CreepTumor";NA;59;0
"Unit";"Queen";"Hatchery";57;2
"Unit";"Overlord";"Larva";76;0
"Unit";"Overlord";"Larva";79;0
"Unit";"Overlord";"Larva";79;0
"Building";"CreepTumor";NA;80;0
"Building";"CreepTumor";NA;80;0
"Unit";"Overlord";"Larva";79;0
"Building";"CreepTumor";NA;80;0
"Building";"CreepTumorQueen";NA;80;0
"Building";"CreepTumorQueen";NA;80;0
"Building";"Extractor";NA;80;0
"Unit";"Zergling";"Larva";94;1
"Unit";"Zergling";"Larva";94;1
"Unit";"Zergling";"Larva";95;1
"Unit";"Zergling";"Larva";95;1
"Unit";"Zergling";"Larva";96;1
"Unit";"Zergling";"Larva";96;1
"Unit";"Zergling";"Larva";96;1
"Unit";"Zergling";"Larva";96;1
"Unit";"Zergling";"Larva";96;1
"Unit";"Zergling";"Larva";96;1
"Unit";"Zergling";"Larva";96;1
"Unit";"Zergling";"Larva";96;1
"Unit";"Zergling";"Larva";96;1
"Unit";"Zergling";"Larva";96;1
"Unit";"Zergling";"Larva";96;1
"Unit";"Zergling";"Larva";96;1
"Unit";"Zergling";"Larva";96;1
"Unit";"Zergling";"Larva";96;1
"Building";"Extractor";NA;96;0
"Building";"Extractor";NA;96;0
"Building";"Extractor";NA;96;0
"Unit";"Overlord";"Larva";96;0
"Building";"CreepTumorQueen";NA;108;0
"Unit";"Overlord";"Larva";108;0
"Unit";"Overlord";"Larva";108;0
"Unit";"Overlord";"Larva";108;0
"Unit";"Overlord";"Larva";108;0
"Unit";"Overlord";"Larva";114;0
"Unit";"Overlord";"Larva";114;0
"Unit";"Zergling";"Larva";114;1
"Unit";"Zergling";"Larva";114;1
"Unit";"Zergling";"Larva";114;1
"Unit";"Zergling";"Larva";114;1
"Unit";"Zergling";"Larva";114;1
"Unit";"Zergling";"Larva";114;1
"Unit";"Zergling";"Larva";114;1
"Unit";"Zergling";"Larva";114;1
"Unit";"Zergling";"Larva";114;1
"Unit";"Zergling";"Larva";114;1
"Unit";"Zergling";"Larva";114;1
"Unit";"Zergling";"Larva";114;1
"Unit";"Zergling";"Larva";114;1
"Unit";"Zergling";"Larva";114;1
"Unit";"Zergling";"Larva";114;1
"Unit";"Zergling";"Larva";114;1
"Unit";"Zergling";"Larva";114;1
"Unit";"Zergling";"Larva";114;1
"Unit";"Zergling";"Larva";114;1
"Unit";"Zergling";"Larva";114;1
"Unit";"Zergling";"Larva";114;1
"Unit";"Zergling";"Larva";114;1
"Unit";"Zergling";"Larva";114;1
"Unit";"Zergling";"Larva";114;1
"Upgrade";"ZergGroundArmorsLevel1";"EvolutionChamber";91;0
"Upgrade";"ZergMeleeWeaponsLevel1";"EvolutionChamber";93;0
"Unit";"Zergling";"Larva";116;1
"Unit";"Zergling";"Larva";116;1
"Unit";"Zergling";"Larva";116;1
"Unit";"Zergling";"Larva";116;1
"Unit";"Zergling";"Larva";124;1
"Unit";"Zergling";"Larva";124;1
"Unit";"Zergling";"Larva";132;1
"Unit";"Zergling";"Larva";132;1
"Unit";"Zergling";"Larva";138;1
"Unit";"Zergling";"Larva";138;1
"Unit";"Zergling";"Larva";138;1
"Unit";"Zergling";"Larva";138;1
"Unit";"Zergling";"Larva";138;1
"Unit";"Zergling";"Larva";138;1
"Unit";"Zergling";"Larva";138;1
"Unit";"Zergling";"Larva";138;1
"Unit";"Overlord";"Larva";138;0
"Unit";"Zergling";"Larva";157;1
"Unit";"Zergling";"Larva";157;1
"Unit";"Zergling";"Larva";157;1
"Unit";"Zergling";"Larva";157;1
"Unit";"Zergling";"Larva";157;1
"Unit";"Zergling";"Larva";157;1
"Unit";"Zergling";"Larva";157;1
"Unit";"Zergling";"Larva";157;1
"Unit";"Zergling";"Larva";157;1
"Unit";"Zergling";"Larva";157;1
"Unit";"Zergling";"Larva";157;1
"Unit";"Zergling";"Larva";157;1
"Unit";"Zergling";"Larva";157;1
"Unit";"Zergling";"Larva";157;1
"Building";"CreepTumor";NA;157;0
"Unit";"Zergling";"Larva";157;1
"Unit";"Zergling";"Larva";157;1
"Unit";"Zergling";"Larva";157;1
"Unit";"Zergling";"Larva";157;1
"Unit";"Zergling";"Larva";157;1
"Unit";"Zergling";"Larva";157;1
"Building";"CreepTumor";NA;157;0
"Unit";"Zergling";"Larva";157;1
"Unit";"Zergling";"Larva";157;1
"Building";"CreepTumorQueen";NA;157;0
"Building";"CreepTumor";NA;157;0
"Building";"Spire";NA;114;0
"Unit";"Overlord";"Larva";157;0
"Building";"InfestationPit";NA;157;0
"Building";"Hatchery";NA;138;0
"Unit";"Mutalisk";"Larva";179;2
"Unit";"Mutalisk";"Larva";179;2
"Unit";"Mutalisk";"Larva";179;2
"Unit";"Mutalisk";"Larva";179;2
"Unit";"Mutalisk";"Larva";179;2
"Unit";"Mutalisk";"Larva";179;2
"Unit";"Mutalisk";"Larva";179;2
"Unit";"Mutalisk";"Larva";179;2
"Unit";"Mutalisk";"Larva";179;2
"Unit";"Mutalisk";"Larva";179;2
"Unit";"Mutalisk";"Larva";179;2
"Unit";"Mutalisk";"Larva";179;2
"Unit";"Mutalisk";"Larva";179;2
"Unit";"Zergling";"Larva";179;1
"Unit";"Zergling";"Larva";179;1
"Unit";"Zergling";"Larva";179;1
"Unit";"Zergling";"Larva";179;1
"Unit";"Zergling";"Larva";179;1
"Unit";"Zergling";"Larva";179;1
"Unit";"Zergling";"Larva";179;1
"Unit";"Zergling";"Larva";179;1
"Building";"Hatchery";NA;157;0
"Unit";"Zergling";"Larva";211;1
"Unit";"Zergling";"Larva";211;1
"Unit";"Zergling";"Larva";213;1
"Unit";"Zergling";"Larva";213;1
"Unit";"Zergling";"Larva";213;1
"Unit";"Zergling";"Larva";213;1
"Unit";"Zergling";"Larva";215;1
"Unit";"Zergling";"Larva";215;1
"Unit";"Zergling";"Larva";217;1
"Unit";"Zergling";"Larva";217;1
"Building";"BanelingNest";NA;179;0
"Unit";"Zergling";"Larva";223;1
"Unit";"Zergling";"Larva";223;1
"Unit";"Zergling";"Larva";223;1
"Unit";"Zergling";"Larva";223;1
"Unit";"Zergling";"Larva";223;1
"Unit";"Zergling";"Larva";223;1
"Unit";"Zergling";"Larva";225;1
"Unit";"Zergling";"Larva";225;1
"Unit";"Zergling";"Larva";225;1
"Unit";"Zergling";"Larva";225;1
"Unit";"Zergling";"Larva";233;1
"Unit";"Zergling";"Larva";233;1
"Upgrade";"ZergGroundArmorsLevel2";"EvolutionChamber";157;0
"Upgrade";"ZergMeleeWeaponsLevel2";"EvolutionChamber";157;0
"Unit";"Zergling";"Larva";234;1
"Unit";"Zergling";"Larva";234;1
"Unit";"Zergling";"Larva";234;1
"Unit";"Zergling";"Larva";234;1
"Unit";"Zergling";"Larva";234;1
"Unit";"Zergling";"Larva";234;1
"Unit";"Zergling";"Larva";234;1
"Unit";"Zergling";"Larva";234;1
"Unit";"Zergling";"Larva";234;1
"Unit";"Zergling";"Larva";234;1
"Unit";"Zergling";"Larva";234;1
"Unit";"Zergling";"Larva";234;1
"Unit";"Zergling";"Larva";234;1
"Unit";"Zergling";"Larva";234;1
"Unit";"Zergling";"Larva";234;1
"Unit";"Zergling";"Larva";234;1
"Unit";"Zergling";"Larva";234;1
"Unit";"Zergling";"Larva";234;1
"Unit";"Zergling";"Larva";234;1
"Unit";"Zergling";"Larva";234;1
"Unit";"Zergling";"Larva";234;1
"Unit";"Zergling";"Larva";234;1
"Unit";"Queen";"Hatchery";229;2
"Building";"SpineCrawler";NA;229;0
"Unit";"Zergling";"Larva";270;1
"Unit";"Zergling";"Larva";270;1
"Unit";"Zergling";"Larva";270;1
"Unit";"Zergling";"Larva";270;1
"Unit";"Zergling";"Larva";270;1
"Unit";"Zergling";"Larva";270;1
"Unit";"Zergling";"Larva";270;1
"Unit";"Zergling";"Larva";270;1
"Unit";"Zergling";"Larva";270;1
"Unit";"Zergling";"Larva";270;1
"Unit";"Zergling";"Larva";270;1
"Unit";"Zergling";"Larva";270;1
"Unit";"Overlord";"Larva";270;0
"Unit";"Mutalisk";"Larva";268;2
"Unit";"Overlord";"Larva";270;0
"Unit";"Overlord";"Larva";270;0
"Unit";"Overlord";"Larva";270;0
"Unit";"Overlord";"Larva";270;0
"Unit";"Baneling";"Zergling";282;0
"Unit";"Baneling";"Zergling";282;0
"Unit";"Baneling";"Zergling";282;0
"Unit";"Baneling";"Zergling";282;0
"Unit";"Baneling";"Zergling";284;0
"Unit";"Baneling";"Zergling";284;0
"Unit";"Baneling";"Zergling";284;0
"Building";"Extractor";NA;284;0
"Unit";"Baneling";"Zergling";284;0
"Unit";"Baneling";"Zergling";284;0
"Building";"Extractor";NA;284;0
"Unit";"Baneling";"Zergling";284;0
"Building";"CreepTumorQueen";NA;294;0
"Building";"CreepTumor";NA;294;0
"Building";"CreepTumor";NA;294;0
"Building";"CreepTumorQueen";NA;298;0
"Unit";"Overlord";"Larva";294;0
"Unit";"Infestor";"Larva";284;2
"Building";"CreepTumor";NA;298;0
"Building";"CreepTumor";NA;301;0
"Unit";"Overlord";"Larva";294;0
"Building";"CreepTumor";NA;301;0
"Building";"UltraliskCavern";NA;270;0
"Building";"CreepTumorQueen";NA;301;0
"Unit";"Overlord";"Larva";298;0
"Building";"CreepTumorQueen";NA;301;0
"Unit";"Overlord";"Larva";301;0
"Building";"CreepTumorQueen";NA;301;0
"Building";"CreepTumorQueen";NA;303;0
"Unit";"Overlord";"Larva";301;0
"Building";"CreepTumorQueen";NA;303;0
"Unit";"Zergling";"Larva";303;1
"Unit";"Zergling";"Larva";303;1
"Unit";"Zergling";"Larva";303;1
"Unit";"Zergling";"Larva";303;1
"Unit";"Zergling";"Larva";303;1
"Unit";"Zergling";"Larva";303;1
"Unit";"Zergling";"Larva";303;1
"Unit";"Zergling";"Larva";303;1
"Unit";"Zergling";"Larva";303;1
"Unit";"Zergling";"Larva";303;1
"Unit";"Zergling";"Larva";303;1
"Unit";"Zergling";"Larva";303;1
"Unit";"Zergling";"Larva";303;1
"Unit";"Zergling";"Larva";303;1
"Unit";"Zergling";"Larva";303;1
"Unit";"Zergling";"Larva";303;1
"Unit";"Zergling";"Larva";303;1
"Unit";"Zergling";"Larva";303;1
"Unit";"Zergling";"Larva";303;1
"Unit";"Zergling";"Larva";303;1
"Unit";"Zergling";"Larva";303;1
"Unit";"Zergling";"Larva";303;1
"Unit";"Zergling";"Larva";303;1
"Unit";"Zergling";"Larva";303;1
"Unit";"Zergling";"Larva";303;1
"Unit";"Zergling";"Larva";303;1
"Unit";"Zergling";"Larva";303;1
"Unit";"Zergling";"Larva";303;1
"Unit";"Zergling";"Larva";303;1
"Unit";"Zergling";"Larva";303;1
"Unit";"Zergling";"Larva";303;1
"Unit";"Zergling";"Larva";303;1
"Unit";"Zergling";"Larva";303;1
"Unit";"Zergling";"Larva";303;1
"Unit";"Zergling";"Larva";303;1
"Unit";"Zergling";"Larva";303;1
"Unit";"Zergling";"Larva";303;1
"Unit";"Zergling";"Larva";303;1
"Unit";"Zergling";"Larva";303;1
"Unit";"Zergling";"Larva";303;1
"Unit";"Zergling";"Larva";303;1
"Unit";"Zergling";"Larva";303;1
"Building";"CreepTumor";NA;327;0
"Unit";"Baneling";"Zergling";345;0
"Unit";"Baneling";"Zergling";345;0
"Unit";"Baneling";"Zergling";345;0
"Unit";"Baneling";"Zergling";345;0
"Unit";"Baneling";"Zergling";345;0
"Unit";"Baneling";"Zergling";345;0
"Unit";"Baneling";"Zergling";345;0
"Unit";"Baneling";"Zergling";345;0
"Unit";"Baneling";"Zergling";345;0
"Unit";"Baneling";"Zergling";345;0
"Unit";"Baneling";"Zergling";345;0
"Unit";"Baneling";"Zergling";345;0
"Unit";"Baneling";"Zergling";345;0
"Unit";"Baneling";"Zergling";345;0
"Unit";"Baneling";"Zergling";345;0
"Unit";"Baneling";"Zergling";345;0
"Unit";"Baneling";"Zergling";345;0
"Unit";"Baneling";"Zergling";345;0
"Unit";"Baneling";"Zergling";345;0
"Unit";"Zergling";"Larva";345;1
"Unit";"Zergling";"Larva";345;1
"Unit";"Zergling";"Larva";345;1
"Unit";"Zergling";"Larva";345;1
"Unit";"Ultralisk";"Larva";303;6
"Unit";"Zergling";"Larva";345;1
"Unit";"Zergling";"Larva";345;1
"Unit";"Zergling";"Larva";345;1
"Unit";"Zergling";"Larva";345;1
"Unit";"Zergling";"Larva";345;1
"Unit";"Zergling";"Larva";345;1
"Unit";"Zergling";"Larva";345;1
"Unit";"Zergling";"Larva";345;1
"Unit";"Zergling";"Larva";345;1
"Unit";"Zergling";"Larva";345;1
"Unit";"Zergling";"Larva";345;1
"Unit";"Zergling";"Larva";345;1
"Unit";"Zergling";"Larva";345;1
"Unit";"Zergling";"Larva";345;1
"Unit";"Zergling";"Larva";345;1
"Unit";"Zergling";"Larva";345;1
"Unit";"Zergling";"Larva";345;1
"Unit";"Zergling";"Larva";345;1
"Unit";"Zergling";"Larva";345;1
"Unit";"Zergling";"Larva";345;1
"Unit";"Zergling";"Larva";345;1
"Unit";"Zergling";"Larva";345;1
"Building";"CreepTumorQueen";NA;377;0
"Building";"CreepTumorQueen";NA;377;0
"Unit";"Baneling";"Zergling";377;0
"Unit";"Baneling";"Zergling";377;0
"Unit";"Zergling";"Larva";377;1
"Unit";"Zergling";"Larva";377;1
"Unit";"Zergling";"Larva";377;1
"Unit";"Zergling";"Larva";377;1
"Unit";"Zergling";"Larva";377;1
"Unit";"Zergling";"Larva";377;1
"Unit";"Zergling";"Larva";377;1
"Unit";"Zergling";"Larva";377;1
"Unit";"Zergling";"Larva";377;1
"Unit";"Zergling";"Larva";377;1
"Unit";"Zergling";"Larva";377;1
"Unit";"Zergling";"Larva";377;1
"Unit";"Zergling";"Larva";377;1
"Unit";"Zergling";"Larva";377;1
"Unit";"Zergling";"Larva";377;1
"Unit";"Zergling";"Larva";377;1
"Unit";"Zergling";"Larva";377;1
"Unit";"Zergling";"Larva";377;1
"Unit";"Zergling";"Larva";377;1
"Unit";"Zergling";"Larva";377;1
"Building";"CreepTumorQueen";NA;377;0
"Building";"CreepTumorQueen";NA;377;0
"Building";"CreepTumor";NA;377;0
"Building";"CreepTumor";NA;377;0
"Building";"CreepTumorQueen";NA;377;0
"Building";"CreepTumor";NA;377;0
"Building";"CreepTumor";NA;377;0
"Building";"CreepTumor";NA;377;0
"Building";"CreepTumor";NA;377;0
"Upgrade";"ChitinousPlating";"UltraliskCavern";345;0
"Building";"CreepTumor";NA;377;0
"Building";"CreepTumorQueen";NA;377;0
"Upgrade";"ZergGroundArmorsLevel3";"EvolutionChamber";301;0
"Upgrade";"ZergMeleeWeaponsLevel3";"EvolutionChamber";301;0
"Building";"CreepTumorQueen";NA;377;0
"Unit";"Ultralisk";"Larva";377;6
"Unit";"Ultralisk";"Larva";377;6
"Unit";"Ultralisk";"Larva";377;6
"Unit";"Ultralisk";"Larva";377;6
"Unit";"Ultralisk";"Larva";377;6
"Unit";"Ultralisk";"Larva";377;6
"Unit";"Baneling";"Zergling";397;0
"Unit";"Baneling";"Zergling";397;0
"Unit";"Infestor";"Larva";397;2
"Unit";"Infestor";"Larva";397;2
