"type";"unit_name";"on_building";"total_supply";"supply"
"Unit";"Overlord";"Larva";12;0
"Building";"Extractor";NA;19;0
"Unit";"Overlord";"Larva";21;0
"Building";"SpawningPool";NA;19;0
"Building";"Hatchery";NA;17;0
"Unit";"Zergling";"Larva";22;1
"Unit";"Zergling";"Larva";22;1
"Unit";"Zergling";"Larva";22;1
"Unit";"Zergling";"Larva";22;1
"Unit";"Queen";"Hatchery";22;2
"Unit";"Queen";"Hatchery";22;2
"Unit";"Overlord";"Larva";35;0
"Building";"CreepTumorQueen";NA;35;0
"Unit";"Queen";"Hatchery";35;2
"Building";"CreepTumor";NA;43;0
"Building";"CreepTumorQueen";NA;44;0
"Unit";"Overlord";"Larva";44;0
"Building";"Hatchery";NA;32;0
"Building";"CreepTumor";NA;50;0
"Unit";"Zergling";"Larva";49;1
"Unit";"Zergling";"Larva";49;1
"Unit";"Zergling";"Larva";49;1
"Unit";"Zergling";"Larva";49;1
"Unit";"Zergling";"Larva";49;1
"Unit";"Zergling";"Larva";49;1
"Unit";"Zergling";"Larva";49;1
"Unit";"Zergling";"Larva";49;1
"Building";"CreepTumorQueen";NA;50;0
"Building";"CreepTumor";NA;50;0
"Unit";"Overlord";"Larva";50;0
"Unit";"Zergling";"Larva";58;1
"Unit";"Zergling";"Larva";58;1
"Unit";"Queen";"Hatchery";49;2
"Unit";"Zergling";"Larva";58;1
"Unit";"Zergling";"Larva";58;1
"Unit";"Zergling";"Larva";58;1
"Unit";"Zergling";"Larva";58;1
"Unit";"Zergling";"Larva";58;1
"Unit";"Zergling";"Larva";58;1
"Unit";"Zergling";"Larva";58;1
"Unit";"Zergling";"Larva";58;1
"Building";"BanelingNest";NA;49;0
"Unit";"Overlord";"Larva";60;0
"Unit";"Queen";"Hatchery";50;2
"Unit";"Zergling";"Larva";60;1
"Unit";"Zergling";"Larva";60;1
"Unit";"Zergling";"Larva";60;1
"Unit";"Zergling";"Larva";60;1
"Unit";"Zergling";"Larva";60;1
"Unit";"Zergling";"Larva";60;1
"Unit";"Zergling";"Larva";60;1
"Unit";"Zergling";"Larva";60;1
"Unit";"Zergling";"Larva";60;1
"Unit";"Zergling";"Larva";60;1
"Unit";"Zergling";"Larva";60;1
"Unit";"Zergling";"Larva";60;1
"Unit";"Zergling";"Larva";74;1
"Unit";"Zergling";"Larva";74;1
"Unit";"Zergling";"Larva";76;1
"Unit";"Zergling";"Larva";76;1
"Unit";"Zergling";"Larva";76;1
"Unit";"Zergling";"Larva";76;1
"Unit";"Zergling";"Larva";78;1
"Unit";"Zergling";"Larva";78;1
"Unit";"Zergling";"Larva";78;1
"Unit";"Zergling";"Larva";78;1
"Unit";"Zergling";"Larva";80;1
"Unit";"Zergling";"Larva";80;1
"Building";"CreepTumorQueen";NA;86;0
"Building";"CreepTumorQueen";NA;86;0
"Building";"CreepTumorQueen";NA;86;0
"Unit";"Baneling";"Zergling";98;0
"Unit";"Baneling";"Zergling";98;0
"Unit";"Baneling";"Zergling";98;0
"Unit";"Baneling";"Zergling";98;0
"Unit";"Baneling";"Zergling";98;0
"Unit";"Baneling";"Zergling";98;0
"Unit";"Baneling";"Zergling";98;0
"Unit";"Baneling";"Zergling";98;0
"Unit";"Baneling";"Zergling";98;0
"Unit";"Baneling";"Zergling";103;0
"Unit";"Queen";"Hatchery";86;2
"Unit";"Overlord";"Larva";103;0
"Building";"CreepTumorQueen";NA;104;0
"Building";"CreepTumorQueen";NA;104;0
"Building";"CreepTumorQueen";NA;104;0
"Building";"CreepTumor";NA;104;0
"Building";"CreepTumor";NA;104;0
"Building";"CreepTumor";NA;104;0
"Building";"Extractor";NA;107;0
"Building";"Extractor";NA;107;0
"Building";"CreepTumor";NA;116;0
"Building";"CreepTumor";NA;116;0
"Building";"CreepTumor";NA;116;0
"Building";"CreepTumor";NA;116;0
"Building";"CreepTumor";NA;116;0
"Unit";"Zergling";"Larva";116;1
"Unit";"Zergling";"Larva";116;1
"Unit";"Zergling";"Larva";116;1
"Unit";"Zergling";"Larva";116;1
"Unit";"Zergling";"Larva";116;1
"Unit";"Zergling";"Larva";116;1
"Building";"CreepTumor";NA;127;0
"Building";"CreepTumor";NA;127;0
"Building";"CreepTumor";NA;127;0
"Building";"Extractor";NA;121;0
"Unit";"Zergling";"Larva";121;1
"Unit";"Zergling";"Larva";121;1
"Unit";"Zergling";"Larva";121;1
"Unit";"Zergling";"Larva";121;1
"Unit";"Zergling";"Larva";121;1
"Unit";"Zergling";"Larva";121;1
"Unit";"Zergling";"Larva";121;1
"Unit";"Zergling";"Larva";121;1
"Building";"EvolutionChamber";NA;121;0
"Building";"SporeCrawler";NA;121;0
"Unit";"Overlord";"Larva";127;0
"Unit";"Baneling";"Zergling";139;0
"Unit";"Baneling";"Zergling";139;0
"Unit";"Baneling";"Zergling";139;0
"Unit";"Baneling";"Zergling";139;0
"Unit";"Baneling";"Zergling";139;0
"Unit";"Baneling";"Zergling";139;0
"Unit";"Baneling";"Zergling";139;0
"Unit";"Zergling";"Larva";139;1
"Unit";"Zergling";"Larva";139;1
"Unit";"Zergling";"Larva";139;1
"Unit";"Zergling";"Larva";139;1
"Unit";"Zergling";"Larva";139;1
"Unit";"Zergling";"Larva";139;1
"Unit";"Zergling";"Larva";139;1
"Unit";"Zergling";"Larva";139;1
"Unit";"Zergling";"Larva";139;1
"Unit";"Zergling";"Larva";139;1
"Building";"EvolutionChamber";NA;131;0
"Building";"Extractor";NA;139;0
"Building";"Hatchery";NA;116;0
"Building";"Extractor";NA;139;0
"Building";"CreepTumor";NA;160;0
"Building";"CreepTumor";NA;160;0
"Building";"CreepTumor";NA;160;0
"Unit";"Queen";"Hatchery";154;2
"Building";"CreepTumor";NA;160;0
"Unit";"Overlord";"Larva";160;0
"Building";"CreepTumor";NA;160;0
"Building";"CreepTumor";NA;161;0
"Building";"CreepTumor";NA;161;0
"Building";"CreepTumor";NA;161;0
"Unit";"Overlord";"Larva";161;0
"Unit";"Overlord";"Larva";161;0
"Unit";"Zergling";"Larva";168;1
"Unit";"Zergling";"Larva";168;1
"Unit";"Zergling";"Larva";168;1
"Unit";"Zergling";"Larva";168;1
"Unit";"Zergling";"Larva";168;1
"Unit";"Zergling";"Larva";168;1
"Unit";"Zergling";"Larva";168;1
"Unit";"Zergling";"Larva";168;1
"Unit";"Zergling";"Larva";168;1
"Unit";"Zergling";"Larva";168;1
"Unit";"Zergling";"Larva";168;1
"Unit";"Zergling";"Larva";168;1
"Unit";"Zergling";"Larva";168;1
"Unit";"Zergling";"Larva";168;1
"Unit";"Zergling";"Larva";168;1
"Unit";"Zergling";"Larva";168;1
"Unit";"Zergling";"Larva";168;1
"Unit";"Zergling";"Larva";168;1
"Unit";"Zergling";"Larva";168;1
"Unit";"Zergling";"Larva";168;1
"Unit";"Zergling";"Larva";168;1
"Unit";"Zergling";"Larva";168;1
"Unit";"Baneling";"Zergling";168;0
"Unit";"Zergling";"Larva";168;1
"Unit";"Zergling";"Larva";168;1
"Unit";"Zergling";"Larva";168;1
"Unit";"Zergling";"Larva";168;1
"Unit";"Zergling";"Larva";168;1
"Unit";"Zergling";"Larva";168;1
"Unit";"Zergling";"Larva";168;1
"Unit";"Zergling";"Larva";168;1
"Unit";"Baneling";"Zergling";168;0
"Unit";"Baneling";"Zergling";168;0
"Unit";"Baneling";"Zergling";168;0
"Unit";"Baneling";"Zergling";168;0
"Unit";"Baneling";"Zergling";168;0
"Unit";"Baneling";"Zergling";168;0
"Building";"CreepTumorQueen";NA;171;0
"Building";"CreepTumorQueen";NA;171;0
"Building";"CreepTumor";NA;171;0
"Building";"CreepTumorQueen";NA;171;0
"Building";"CreepTumor";NA;171;0
"Building";"CreepTumorQueen";NA;171;0
"Building";"HydraliskDen";NA;168;0
"Building";"CreepTumor";NA;171;0
"Building";"CreepTumor";NA;201;0
"Building";"CreepTumor";NA;201;0
"Building";"CreepTumor";NA;201;0
"Building";"RoachWarren";NA;168;0
"Unit";"Overlord";"Larva";201;0
"Unit";"Overlord";"Larva";201;0
"Upgrade";"ZergMeleeWeaponsLevel1";"EvolutionChamber";159;0
"Unit";"Zergling";"Larva";201;1
"Unit";"Zergling";"Larva";201;1
"Unit";"Hydralisk";"Larva";201;2
"Unit";"Hydralisk";"Larva";201;2
"Unit";"Hydralisk";"Larva";201;2
"Unit";"Hydralisk";"Larva";201;2
"Building";"CreepTumor";NA;201;0
"Building";"CreepTumor";NA;201;0
"Building";"CreepTumor";NA;201;0
"Building";"Hatchery";NA;168;0
"Building";"CreepTumor";NA;205;0
"Building";"CreepTumor";NA;203;0
"Building";"CreepTumor";NA;205;0
"Building";"CreepTumor";NA;205;0
"Building";"CreepTumor";NA;205;0
"Building";"CreepTumor";NA;209;0
"Building";"CreepTumor";NA;211;0
"Building";"CreepTumor";NA;211;0
"Building";"Extractor";NA;201;0
"Unit";"Hydralisk";"Larva";201;2
"Unit";"Hydralisk";"Larva";201;2
"Unit";"Hydralisk";"Larva";201;2
"Unit";"Hydralisk";"Larva";201;2
"Unit";"Hydralisk";"Larva";201;2
"Unit";"Hydralisk";"Larva";201;2
"Unit";"Hydralisk";"Larva";201;2
"Unit";"Hydralisk";"Larva";201;2
"Building";"InfestationPit";NA;201;0
"Building";"SporeCrawler";NA;214;0
"Unit";"Overlord";"Larva";214;0
"Unit";"Overlord";"Larva";214;0
"Unit";"Zergling";"Larva";214;1
"Unit";"Zergling";"Larva";214;1
"Unit";"Overlord";"Larva";236;0
"Unit";"Overlord";"Larva";236;0
"Upgrade";"EvolveGroovedSpines";"HydraliskDen";201;0
"Building";"CreepTumor";NA;238;0
"Building";"CreepTumor";NA;238;0
"Building";"CreepTumor";NA;238;0
"Building";"CreepTumor";NA;238;0
"Building";"CreepTumor";NA;238;0
"Building";"CreepTumor";NA;238;0
"Building";"CreepTumor";NA;238;0
"Building";"CreepTumor";NA;238;0
"Building";"CreepTumor";NA;238;0
"Building";"CreepTumor";NA;238;0
"Unit";"Overlord";"Larva";238;0
"Unit";"Overlord";"Larva";238;0
"Unit";"Roach";"Larva";238;2
"Unit";"Roach";"Larva";238;2
"Unit";"Roach";"Larva";238;2
"Unit";"Roach";"Larva";238;2
"Unit";"Roach";"Larva";238;2
"Unit";"Roach";"Larva";238;2
"Unit";"Roach";"Larva";238;2
"Unit";"Roach";"Larva";238;2
"Unit";"Roach";"Larva";238;2
"Unit";"Roach";"Larva";238;2
"Unit";"Roach";"Larva";238;2
"Unit";"Roach";"Larva";238;2
"Unit";"Roach";"Larva";238;2
"Unit";"Baneling";"Zergling";238;0
"Unit";"Roach";"Larva";238;2
"Unit";"Roach";"Larva";238;2
"Unit";"Roach";"Larva";238;2
"Unit";"Baneling";"Zergling";238;0
"Unit";"Baneling";"Zergling";238;0
"Unit";"Baneling";"Zergling";238;0
"Unit";"Baneling";"Zergling";238;0
"Unit";"Baneling";"Zergling";238;0
"Unit";"Baneling";"Zergling";238;0
"Unit";"Baneling";"Zergling";238;0
"Building";"CreepTumorQueen";NA;270;0
"Building";"CreepTumorQueen";NA;270;0
"Building";"CreepTumor";NA;270;0
"Building";"CreepTumor";NA;270;0
"Building";"CreepTumor";NA;270;0
"Building";"CreepTumor";NA;270;0
"Building";"CreepTumorQueen";NA;270;0
"Building";"CreepTumorQueen";NA;270;0
"Building";"CreepTumorQueen";NA;270;0
"Building";"CreepTumorQueen";NA;284;0
"Building";"Extractor";NA;270;0
"Building";"CreepTumorQueen";NA;285;0
"Building";"CreepTumorQueen";NA;285;0
"Building";"Extractor";NA;270;0
"Building";"CreepTumorQueen";NA;285;0
"Building";"CreepTumorQueen";NA;285;0
"Unit";"Overlord";"Larva";276;0
"Unit";"Overlord";"Larva";280;0
"Building";"CreepTumorQueen";NA;285;0
"Building";"CreepTumor";NA;285;0
"Building";"CreepTumor";NA;285;0
"Building";"CreepTumor";NA;285;0
"Building";"CreepTumor";NA;285;0
"Building";"CreepTumor";NA;285;0
"Building";"CreepTumor";NA;285;0
"Building";"CreepTumor";NA;285;0
"Building";"CreepTumor";NA;285;0
"Building";"CreepTumorQueen";NA;285;0
"Upgrade";"GlialReconstitution";"RoachWarren";238;0
"Unit";"Roach";"Larva";285;2
"Unit";"Roach";"Larva";285;2
"Unit";"Roach";"Larva";285;2
"Unit";"Roach";"Larva";285;2
"Unit";"Roach";"Larva";285;2
"Unit";"Roach";"Larva";285;2
"Building";"CreepTumorQueen";NA;285;0
"Building";"CreepTumorQueen";NA;285;0
"Building";"CreepTumorQueen";NA;285;0
"Building";"CreepTumorQueen";NA;285;0
"Building";"CreepTumorQueen";NA;285;0
"Building";"CreepTumorQueen";NA;285;0
"Building";"CreepTumor";NA;285;0
"Building";"CreepTumor";NA;285;0
"Building";"CreepTumor";NA;285;0
"Building";"CreepTumor";NA;285;0
"Building";"CreepTumor";NA;285;0
"Building";"CreepTumor";NA;285;0
"Building";"CreepTumor";NA;285;0
"Building";"CreepTumor";NA;285;0
"Building";"CreepTumor";NA;285;0
"Building";"CreepTumor";NA;297;0
"Building";"CreepTumor";NA;297;0
"Building";"CreepTumor";NA;297;0
"Building";"CreepTumor";NA;297;0
"Upgrade";"ZergMissileWeaponsLevel1";"EvolutionChamber";238;0
"Unit";"Zergling";"Larva";297;1
"Unit";"Zergling";"Larva";297;1
"Unit";"Zergling";"Larva";297;1
"Unit";"Zergling";"Larva";297;1
"Unit";"Zergling";"Larva";297;1
"Unit";"Zergling";"Larva";297;1
"Unit";"Zergling";"Larva";297;1
"Unit";"Zergling";"Larva";297;1
"Unit";"Zergling";"Larva";297;1
"Unit";"Zergling";"Larva";297;1
"Unit";"Zergling";"Larva";297;1
"Unit";"Zergling";"Larva";297;1
"Unit";"Zergling";"Larva";297;1
"Unit";"Zergling";"Larva";297;1
"Unit";"Zergling";"Larva";297;1
"Unit";"Zergling";"Larva";297;1
"Unit";"Zergling";"Larva";297;1
"Unit";"Zergling";"Larva";297;1
"Unit";"Zergling";"Larva";297;1
"Unit";"Zergling";"Larva";297;1
"Building";"CreepTumor";NA;297;0
"Building";"CreepTumor";NA;297;0
"Building";"CreepTumor";NA;297;0
"Building";"CreepTumor";NA;297;0
"Building";"CreepTumor";NA;297;0
"Building";"CreepTumor";NA;297;0
"Unit";"Hydralisk";"Larva";297;2
"Upgrade";"ZergMeleeWeaponsLevel2";"EvolutionChamber";270;0
"Unit";"Zergling";"Larva";319;1
"Unit";"Zergling";"Larva";319;1
"Unit";"Zergling";"Larva";319;1
"Unit";"Zergling";"Larva";319;1
"Unit";"Zergling";"Larva";319;1
"Unit";"Zergling";"Larva";319;1
"Unit";"Zergling";"Larva";319;1
"Unit";"Zergling";"Larva";319;1
"Unit";"Zergling";"Larva";319;1
"Unit";"Zergling";"Larva";319;1
"Unit";"Zergling";"Larva";319;1
"Unit";"Zergling";"Larva";319;1
"Unit";"Zergling";"Larva";319;1
"Unit";"Zergling";"Larva";319;1
"Unit";"Zergling";"Larva";319;1
"Unit";"Zergling";"Larva";319;1
"Unit";"Zergling";"Larva";319;1
"Unit";"Zergling";"Larva";319;1
"Building";"Spire";NA;297;0
"Unit";"Baneling";"Zergling";319;0
"Unit";"Hydralisk";"Larva";319;2
"Unit";"Baneling";"Zergling";319;0
"Unit";"Hydralisk";"Larva";319;2
"Unit";"Hydralisk";"Larva";319;2
"Unit";"Baneling";"Zergling";319;0
"Unit";"Baneling";"Zergling";319;0
"Unit";"Hydralisk";"Larva";319;2
"Unit";"Baneling";"Zergling";319;0
"Unit";"Baneling";"Zergling";319;0
"Unit";"Hydralisk";"Larva";319;2
"Unit";"Hydralisk";"Larva";319;2
"Unit";"Hydralisk";"Larva";319;2
"Unit";"Hydralisk";"Larva";319;2
"Unit";"Hydralisk";"Larva";319;2
"Unit";"Baneling";"Zergling";319;0
"Unit";"Baneling";"Zergling";319;0
"Unit";"Baneling";"Zergling";319;0
"Unit";"Baneling";"Zergling";319;0
"Unit";"Baneling";"Zergling";319;0
"Building";"CreepTumor";NA;319;0
"Building";"CreepTumor";NA;319;0
"Building";"CreepTumor";NA;319;0
"Building";"CreepTumor";NA;319;0
"Building";"CreepTumor";NA;319;0
"Building";"CreepTumor";NA;319;0
"Building";"CreepTumorQueen";NA;319;0
"Unit";"Zergling";"Larva";319;1
"Unit";"Zergling";"Larva";319;1
"Unit";"Zergling";"Larva";319;1
"Unit";"Zergling";"Larva";319;1
"Unit";"Zergling";"Larva";319;1
"Unit";"Zergling";"Larva";319;1
"Unit";"Zergling";"Larva";319;1
"Unit";"Zergling";"Larva";319;1
"Unit";"Zergling";"Larva";319;1
"Unit";"Zergling";"Larva";319;1
"Unit";"Zergling";"Larva";319;1
"Unit";"Zergling";"Larva";319;1
"Unit";"Zergling";"Larva";319;1
"Unit";"Zergling";"Larva";319;1
"Unit";"Zergling";"Larva";319;1
"Unit";"Zergling";"Larva";319;1
"Unit";"Zergling";"Larva";319;1
"Unit";"Zergling";"Larva";319;1
"Unit";"Zergling";"Larva";319;1
"Unit";"Zergling";"Larva";319;1
"Unit";"Zergling";"Larva";319;1
"Unit";"Zergling";"Larva";319;1
"Unit";"Zergling";"Larva";319;1
"Unit";"Zergling";"Larva";319;1
"Unit";"Zergling";"Larva";319;1
"Unit";"Zergling";"Larva";319;1
"Unit";"Zergling";"Larva";319;1
"Unit";"Zergling";"Larva";319;1
"Unit";"Zergling";"Larva";319;1
"Unit";"Zergling";"Larva";319;1
"Building";"CreepTumorQueen";NA;331;0
"Building";"CreepTumorQueen";NA;337;0
"Building";"CreepTumorQueen";NA;337;0
"Building";"CreepTumorQueen";NA;355;0
"Building";"CreepTumorQueen";NA;355;0
"Building";"CreepTumorQueen";NA;355;0
"Building";"CreepTumorQueen";NA;385;0
"Building";"CreepTumorQueen";NA;385;0
"Building";"CreepTumorQueen";NA;385;0
"Unit";"Zergling";"Larva";385;1
"Unit";"Zergling";"Larva";385;1
"Unit";"Zergling";"Larva";385;1
"Unit";"Zergling";"Larva";385;1
"Unit";"Zergling";"Larva";385;1
"Unit";"Zergling";"Larva";385;1
"Unit";"Baneling";"Zergling";385;0
"Unit";"Baneling";"Zergling";385;0
"Unit";"Baneling";"Zergling";385;0
"Unit";"Baneling";"Zergling";385;0
"Unit";"Baneling";"Zergling";385;0
"Unit";"Baneling";"Zergling";385;0
"Unit";"Baneling";"Zergling";385;0
"Unit";"Baneling";"Zergling";385;0
"Unit";"Baneling";"Zergling";385;0
"Unit";"Baneling";"Zergling";385;0
"Unit";"Baneling";"Zergling";385;0
"Unit";"Baneling";"Zergling";385;0
"Unit";"Baneling";"Zergling";385;0
"Unit";"Baneling";"Zergling";385;0
"Unit";"Baneling";"Zergling";385;0
"Unit";"Baneling";"Zergling";385;0
"Unit";"Baneling";"Zergling";385;0
"Unit";"Baneling";"Zergling";385;0
"Unit";"Viper";"Larva";355;3
"Building";"EvolutionChamber";NA;385;0
"Unit";"Viper";"Larva";355;3
"Unit";"Viper";"Larva";355;3
"Unit";"Viper";"Larva";355;3
"Unit";"Viper";"Larva";355;3
"Building";"EvolutionChamber";NA;385;0
"Building";"CreepTumor";NA;385;0
"Building";"CreepTumor";NA;385;0
"Building";"CreepTumor";NA;385;0
"Building";"CreepTumor";NA;385;0
"Building";"CreepTumor";NA;391;0
"Building";"CreepTumor";NA;391;0
"Building";"CreepTumor";NA;391;0
"Unit";"Zergling";"Larva";406;1
"Unit";"Zergling";"Larva";406;1
"Unit";"Zergling";"Larva";406;1
"Unit";"Zergling";"Larva";406;1
"Unit";"Zergling";"Larva";406;1
"Unit";"Zergling";"Larva";406;1
"Unit";"Zergling";"Larva";406;1
"Unit";"Zergling";"Larva";406;1
"Unit";"Zergling";"Larva";406;1
"Unit";"Zergling";"Larva";406;1
"Unit";"Zergling";"Larva";406;1
"Unit";"Zergling";"Larva";406;1
"Unit";"Zergling";"Larva";406;1
"Unit";"Zergling";"Larva";406;1
"Unit";"Zergling";"Larva";406;1
"Unit";"Zergling";"Larva";406;1
"Unit";"Zergling";"Larva";406;1
"Unit";"Zergling";"Larva";406;1
"Building";"CreepTumor";NA;406;0
"Building";"CreepTumor";NA;406;0
"Building";"CreepTumor";NA;406;0
"Building";"CreepTumor";NA;406;0
"Building";"CreepTumor";NA;406;0
"Building";"CreepTumor";NA;406;0
"Building";"CreepTumor";NA;406;0
"Building";"CreepTumor";NA;406;0
"Building";"CreepTumor";NA;406;0
"Building";"CreepTumor";NA;406;0
"Building";"CreepTumor";NA;406;0
"Building";"CreepTumor";NA;406;0
"Building";"CreepTumor";NA;406;0
"Building";"CreepTumor";NA;406;0
"Building";"CreepTumor";NA;406;0
"Building";"CreepTumor";NA;406;0
"Building";"CreepTumor";NA;406;0
"Building";"CreepTumor";NA;406;0
"Building";"CreepTumor";NA;406;0
"Building";"CreepTumor";NA;406;0
"Building";"CreepTumor";NA;406;0
"Building";"CreepTumor";NA;424;0
"Building";"CreepTumor";NA;424;0
"Building";"Hatchery";NA;385;0
"Building";"CreepTumorQueen";NA;424;0
"Building";"CreepTumorQueen";NA;424;0
"Building";"CreepTumorQueen";NA;424;0
"Building";"CreepTumorQueen";NA;424;0
"Building";"CreepTumorQueen";NA;424;0
"Building";"CreepTumorQueen";NA;424;0
"Building";"CreepTumorQueen";NA;424;0
"Building";"CreepTumorQueen";NA;424;0
"Unit";"Hydralisk";"Larva";424;2
"Building";"CreepTumor";NA;424;0
"Upgrade";"ZergMissileWeaponsLevel2";"EvolutionChamber";397;0
"Building";"CreepTumor";NA;424;0
"Building";"CreepTumor";NA;424;0
"Building";"CreepTumor";NA;424;0
"Building";"CreepTumor";NA;424;0
"Building";"CreepTumor";NA;424;0
"Building";"CreepTumor";NA;424;0
"Unit";"Zergling";"Larva";426;1
"Unit";"Zergling";"Larva";426;1
"Unit";"Zergling";"Larva";426;1
"Unit";"Zergling";"Larva";426;1
"Unit";"Zergling";"Larva";426;1
"Unit";"Zergling";"Larva";426;1
"Unit";"Zergling";"Larva";426;1
"Unit";"Zergling";"Larva";426;1
"Unit";"Zergling";"Larva";426;1
"Unit";"Zergling";"Larva";426;1
"Unit";"Zergling";"Larva";426;1
"Unit";"Zergling";"Larva";426;1
"Unit";"Zergling";"Larva";426;1
"Unit";"Zergling";"Larva";426;1
"Unit";"Zergling";"Larva";426;1
"Unit";"Zergling";"Larva";426;1
"Building";"SporeCrawler";NA;424;0
"Upgrade";"ZergMeleeWeaponsLevel3";"EvolutionChamber";406;0
"Unit";"Overlord";"Larva";426;0
"Unit";"Overlord";"Larva";426;0
"Unit";"Overlord";"Larva";426;0
"Unit";"Overlord";"Larva";426;0
"Unit";"Overlord";"Larva";426;0
"Building";"SpineCrawler";NA;426;0
"Building";"SpineCrawler";NA;426;0
"Unit";"Baneling";"Zergling";442;0
"Unit";"Baneling";"Zergling";442;0
"Unit";"Baneling";"Zergling";442;0
"Unit";"Baneling";"Zergling";442;0
"Unit";"Baneling";"Zergling";442;0
"Unit";"Baneling";"Zergling";442;0
"Unit";"Baneling";"Zergling";442;0
"Unit";"Baneling";"Zergling";442;0
"Unit";"Baneling";"Zergling";442;0
"Unit";"Baneling";"Zergling";442;0
"Unit";"Baneling";"Zergling";442;0
"Unit";"Baneling";"Zergling";442;0
"Unit";"Baneling";"Zergling";442;0
"Unit";"Baneling";"Zergling";442;0
"Unit";"Baneling";"Zergling";442;0
"Unit";"Baneling";"Zergling";442;0
"Unit";"Baneling";"Zergling";442;0
"Unit";"Baneling";"Zergling";442;0
"Unit";"Baneling";"Zergling";442;0
"Unit";"Baneling";"Zergling";442;0
"Unit";"Baneling";"Zergling";442;0
"Unit";"Hydralisk";"Larva";442;2
"Unit";"Hydralisk";"Larva";442;2
"Unit";"Hydralisk";"Larva";442;2
"Building";"Hatchery";NA;426;0
"Unit";"Zergling";"Larva";448;1
"Unit";"Zergling";"Larva";448;1
"Unit";"Zergling";"Larva";448;1
"Unit";"Zergling";"Larva";448;1
"Unit";"Zergling";"Larva";448;1
"Unit";"Zergling";"Larva";448;1
"Unit";"Zergling";"Larva";448;1
"Unit";"Zergling";"Larva";448;1
"Unit";"Zergling";"Larva";448;1
"Unit";"Zergling";"Larva";448;1
"Unit";"Zergling";"Larva";448;1
"Unit";"Zergling";"Larva";448;1
"Unit";"Zergling";"Larva";448;1
"Unit";"Zergling";"Larva";448;1
"Unit";"Zergling";"Larva";448;1
"Unit";"Zergling";"Larva";448;1
"Unit";"Zergling";"Larva";448;1
"Unit";"Zergling";"Larva";448;1
"Unit";"Zergling";"Larva";448;1
"Unit";"Zergling";"Larva";448;1
"Unit";"Zergling";"Larva";448;1
"Unit";"Zergling";"Larva";448;1
"Unit";"Zergling";"Larva";448;1
"Unit";"Zergling";"Larva";448;1
"Unit";"Zergling";"Larva";448;1
"Unit";"Zergling";"Larva";448;1
"Unit";"Zergling";"Larva";448;1
"Unit";"Zergling";"Larva";448;1
"Unit";"Zergling";"Larva";448;1
"Unit";"Zergling";"Larva";448;1
"Unit";"Zergling";"Larva";448;1
"Unit";"Zergling";"Larva";448;1
"Unit";"Zergling";"Larva";448;1
"Unit";"Zergling";"Larva";448;1
"Unit";"Zergling";"Larva";448;1
"Unit";"Zergling";"Larva";448;1
"Unit";"Zergling";"Larva";448;1
"Unit";"Zergling";"Larva";448;1
"Unit";"Zergling";"Larva";448;1
"Unit";"Zergling";"Larva";448;1
"Unit";"Zergling";"Larva";448;1
"Unit";"Zergling";"Larva";448;1
"Unit";"Zergling";"Larva";448;1
"Unit";"Zergling";"Larva";448;1
"Unit";"Zergling";"Larva";448;1
"Unit";"Zergling";"Larva";448;1
"Unit";"Zergling";"Larva";448;1
"Unit";"Zergling";"Larva";448;1
"Unit";"Zergling";"Larva";448;1
"Unit";"Zergling";"Larva";448;1
"Unit";"Zergling";"Larva";448;1
"Unit";"Zergling";"Larva";448;1
"Unit";"Zergling";"Larva";448;1
"Unit";"Zergling";"Larva";448;1
"Unit";"Zergling";"Larva";448;1
"Unit";"Zergling";"Larva";448;1
"Unit";"Zergling";"Larva";448;1
"Unit";"Zergling";"Larva";448;1
"Unit";"Zergling";"Larva";448;1
"Unit";"Zergling";"Larva";448;1
"Unit";"Zergling";"Larva";448;1
"Unit";"Zergling";"Larva";448;1
"Unit";"Zergling";"Larva";448;1
"Unit";"Zergling";"Larva";448;1
"Unit";"Zergling";"Larva";448;1
"Unit";"Zergling";"Larva";448;1
"Unit";"Zergling";"Larva";448;1
"Unit";"Zergling";"Larva";448;1
"Building";"CreepTumor";NA;480;0
"Building";"CreepTumor";NA;480;0
"Building";"CreepTumor";NA;480;0
"Building";"CreepTumor";NA;480;0
"Building";"CreepTumor";NA;480;0
"Building";"CreepTumor";NA;480;0
"Building";"CreepTumor";NA;480;0
"Building";"CreepTumor";NA;480;0
"Building";"CreepTumor";NA;480;0
"Building";"CreepTumor";NA;480;0
"Building";"CreepTumor";NA;480;0
"Building";"CreepTumor";NA;480;0
"Building";"CreepTumor";NA;480;0
"Unit";"Zergling";"Larva";516;1
"Unit";"Zergling";"Larva";516;1
"Unit";"Zergling";"Larva";516;1
"Unit";"Zergling";"Larva";516;1
"Unit";"Zergling";"Larva";520;1
"Unit";"Zergling";"Larva";520;1
"Unit";"Zergling";"Larva";520;1
"Unit";"Zergling";"Larva";520;1
"Unit";"Zergling";"Larva";520;1
"Unit";"Zergling";"Larva";520;1
"Unit";"Zergling";"Larva";520;1
"Unit";"Zergling";"Larva";520;1
"Unit";"Zergling";"Larva";520;1
"Unit";"Zergling";"Larva";520;1
"Unit";"Zergling";"Larva";520;1
"Unit";"Zergling";"Larva";520;1
"Unit";"Zergling";"Larva";520;1
"Unit";"Zergling";"Larva";520;1
"Unit";"Zergling";"Larva";520;1
"Unit";"Zergling";"Larva";520;1
"Unit";"Zergling";"Larva";520;1
"Unit";"Zergling";"Larva";520;1
"Unit";"Zergling";"Larva";520;1
"Unit";"Zergling";"Larva";520;1
"Unit";"Zergling";"Larva";520;1
"Unit";"Zergling";"Larva";520;1
"Unit";"Zergling";"Larva";520;1
"Unit";"Zergling";"Larva";520;1
"Unit";"Zergling";"Larva";520;1
"Unit";"Zergling";"Larva";520;1
"Unit";"Zergling";"Larva";520;1
"Unit";"Zergling";"Larva";520;1
"Unit";"Zergling";"Larva";520;1
"Unit";"Zergling";"Larva";520;1
"Unit";"Zergling";"Larva";520;1
"Unit";"Zergling";"Larva";520;1
"Unit";"Hydralisk";"Larva";520;2
"Unit";"Hydralisk";"Larva";520;2
"Unit";"Zergling";"Larva";552;1
"Unit";"Zergling";"Larva";552;1
"Unit";"Baneling";"Zergling";556;0
"Unit";"Zergling";"Larva";552;1
"Unit";"Zergling";"Larva";552;1
"Unit";"Zergling";"Larva";552;1
"Unit";"Zergling";"Larva";552;1
"Unit";"Zergling";"Larva";552;1
"Unit";"Zergling";"Larva";552;1
"Unit";"Baneling";"Zergling";556;0
"Unit";"Baneling";"Zergling";556;0
"Unit";"Baneling";"Zergling";556;0
"Unit";"Baneling";"Zergling";556;0
"Unit";"Baneling";"Zergling";556;0
"Unit";"Baneling";"Zergling";556;0
"Unit";"Baneling";"Zergling";556;0
"Unit";"Baneling";"Zergling";556;0
"Unit";"Baneling";"Zergling";556;0
"Unit";"Baneling";"Zergling";556;0
"Unit";"Baneling";"Zergling";556;0
"Unit";"Baneling";"Zergling";556;0
"Unit";"Baneling";"Zergling";556;0
"Unit";"Baneling";"Zergling";556;0
"Unit";"Baneling";"Zergling";556;0
"Unit";"Baneling";"Zergling";556;0
"Unit";"Baneling";"Zergling";556;0
"Unit";"Baneling";"Zergling";556;0
"Unit";"Baneling";"Zergling";556;0
"Unit";"Hydralisk";"Larva";552;2
"Unit";"Hydralisk";"Larva";552;2
"Unit";"Hydralisk";"Larva";552;2
"Unit";"Hydralisk";"Larva";552;2
"Unit";"Hydralisk";"Larva";552;2
"Building";"CreepTumorQueen";NA;564;0
"Building";"CreepTumorQueen";NA;564;0
"Building";"CreepTumorQueen";NA;564;0
"Building";"CreepTumorQueen";NA;564;0
"Unit";"Zergling";"Larva";556;1
"Unit";"Zergling";"Larva";556;1
"Unit";"Zergling";"Larva";556;1
"Unit";"Zergling";"Larva";556;1
"Unit";"Zergling";"Larva";556;1
"Unit";"Zergling";"Larva";556;1
"Unit";"Zergling";"Larva";556;1
"Unit";"Zergling";"Larva";556;1
"Unit";"Zergling";"Larva";556;1
"Unit";"Zergling";"Larva";556;1
"Unit";"Zergling";"Larva";556;1
"Unit";"Zergling";"Larva";556;1
"Unit";"Zergling";"Larva";556;1
"Unit";"Zergling";"Larva";556;1
"Unit";"Zergling";"Larva";556;1
"Unit";"Zergling";"Larva";556;1
"Unit";"Zergling";"Larva";556;1
"Unit";"Zergling";"Larva";556;1
"Unit";"Zergling";"Larva";556;1
"Unit";"Zergling";"Larva";556;1
"Unit";"Zergling";"Larva";556;1
"Unit";"Zergling";"Larva";556;1
"Unit";"Zergling";"Larva";556;1
"Unit";"Zergling";"Larva";556;1
"Unit";"Zergling";"Larva";556;1
"Unit";"Zergling";"Larva";556;1
"Unit";"Zergling";"Larva";600;1
"Unit";"Zergling";"Larva";600;1
"Unit";"Zergling";"Larva";600;1
"Unit";"Zergling";"Larva";600;1
"Unit";"Zergling";"Larva";600;1
"Unit";"Zergling";"Larva";600;1
"Unit";"Zergling";"Larva";600;1
"Unit";"Zergling";"Larva";600;1
"Unit";"Zergling";"Larva";600;1
"Unit";"Zergling";"Larva";600;1
"Unit";"Zergling";"Larva";600;1
"Unit";"Zergling";"Larva";600;1
"Unit";"Baneling";"Zergling";600;0
"Unit";"Baneling";"Zergling";600;0
"Unit";"Baneling";"Zergling";600;0
"Unit";"Baneling";"Zergling";600;0
"Unit";"Baneling";"Zergling";600;0
"Unit";"Baneling";"Zergling";600;0
"Unit";"Baneling";"Zergling";600;0
"Unit";"Baneling";"Zergling";600;0
"Unit";"Baneling";"Zergling";600;0
"Unit";"Baneling";"Zergling";600;0
"Unit";"Baneling";"Zergling";600;0
"Unit";"Baneling";"Zergling";600;0
"Unit";"Baneling";"Zergling";600;0
"Unit";"Baneling";"Zergling";600;0
"Unit";"Baneling";"Zergling";600;0
"Unit";"Baneling";"Zergling";600;0
"Unit";"Baneling";"Zergling";600;0
"Unit";"Baneling";"Zergling";600;0
"Unit";"Baneling";"Zergling";600;0
"Unit";"Baneling";"Zergling";600;0
"Unit";"Baneling";"Zergling";600;0
"Unit";"Baneling";"Zergling";600;0
"Unit";"Baneling";"Zergling";600;0
"Unit";"Baneling";"Zergling";600;0
"Unit";"Baneling";"Zergling";600;0
"Unit";"Baneling";"Zergling";600;0
"Unit";"Hydralisk";"Larva";600;2
"Unit";"Hydralisk";"Larva";600;2
"Unit";"Hydralisk";"Larva";600;2
"Unit";"Hydralisk";"Larva";600;2
"Unit";"Hydralisk";"Larva";600;2
"Unit";"Hydralisk";"Larva";600;2
"Unit";"Hydralisk";"Larva";600;2
"Unit";"Hydralisk";"Larva";600;2
"Unit";"Hydralisk";"Larva";600;2
"Unit";"Hydralisk";"Larva";600;2
"Unit";"Zergling";"Larva";600;1
"Unit";"Zergling";"Larva";600;1
"Unit";"Zergling";"Larva";600;1
"Unit";"Zergling";"Larva";600;1
"Unit";"Zergling";"Larva";600;1
"Unit";"Zergling";"Larva";600;1
"Unit";"Zergling";"Larva";600;1
"Unit";"Zergling";"Larva";600;1
"Unit";"Zergling";"Larva";600;1
"Unit";"Zergling";"Larva";600;1
"Unit";"Zergling";"Larva";600;1
"Unit";"Zergling";"Larva";600;1
"Building";"SporeCrawler";NA;612;0
"Building";"SporeCrawler";NA;612;0
"Building";"CreepTumor";NA;644;0
"Building";"CreepTumor";NA;644;0
"Building";"SpineCrawler";NA;622;0
"Building";"SpineCrawler";NA;632;0
"Upgrade";"ZergGroundArmorsLevel1";"EvolutionChamber";564;0
"Building";"CreepTumor";NA;644;0
"Building";"CreepTumor";NA;644;0
"Building";"CreepTumor";NA;644;0
"Building";"CreepTumor";NA;644;0
"Building";"CreepTumor";NA;644;0
"Building";"Extractor";NA;644;0
"Building";"CreepTumor";NA;644;0
"Unit";"Overlord";"Larva";644;0
"Unit";"Overlord";"Larva";644;0
"Unit";"Overlord";"Larva";644;0
"Unit";"Overlord";"Larva";644;0
"Unit";"Overlord";"Larva";644;0
"Unit";"Overlord";"Larva";644;0
"Unit";"Overlord";"Larva";644;0
"Unit";"Overlord";"Larva";644;0
"Unit";"Overlord";"Larva";644;0
"Unit";"Overlord";"Larva";644;0
"Unit";"Overlord";"Larva";644;0
"Unit";"Overlord";"Larva";644;0
"Upgrade";"ZergMissileWeaponsLevel3";"EvolutionChamber";600;0
"Building";"Hatchery";NA;644;0
"Building";"Spire";NA;644;0
"Unit";"Zergling";"Larva";644;1
"Unit";"Zergling";"Larva";644;1
"Unit";"Mutalisk";"Larva";644;2
"Unit";"Mutalisk";"Larva";644;2
"Unit";"Mutalisk";"Larva";644;2
"Unit";"Mutalisk";"Larva";644;2
"Unit";"Mutalisk";"Larva";644;2
"Unit";"Mutalisk";"Larva";644;2
"Unit";"Mutalisk";"Larva";644;2
"Unit";"Mutalisk";"Larva";644;2
"Unit";"Mutalisk";"Larva";644;2
"Unit";"Mutalisk";"Larva";644;2
"Unit";"Mutalisk";"Larva";644;2
"Unit";"Mutalisk";"Larva";644;2
"Unit";"Mutalisk";"Larva";644;2
"Unit";"Mutalisk";"Larva";644;2
"Unit";"Mutalisk";"Larva";644;2
"Unit";"Mutalisk";"Larva";644;2
"Unit";"Baneling";"Zergling";644;0
"Unit";"Baneling";"Zergling";644;0
"Unit";"Baneling";"Zergling";644;0
"Unit";"Baneling";"Zergling";644;0
"Unit";"Baneling";"Zergling";644;0
"Unit";"Baneling";"Zergling";644;0
"Upgrade";"ZergGroundArmorsLevel2";"EvolutionChamber";644;0
"Building";"Extractor";NA;678;0
"Building";"Extractor";NA;678;0
"Unit";"Zergling";"Larva";678;1
"Unit";"Zergling";"Larva";678;1
"Unit";"Zergling";"Larva";678;1
"Unit";"Zergling";"Larva";678;1
"Unit";"Zergling";"Larva";678;1
"Unit";"Zergling";"Larva";678;1
"Unit";"Zergling";"Larva";678;1
"Unit";"Zergling";"Larva";678;1
"Unit";"Zergling";"Larva";678;1
"Unit";"Zergling";"Larva";678;1
"Unit";"Zergling";"Larva";678;1
"Unit";"Zergling";"Larva";678;1
"Unit";"Zergling";"Larva";678;1
"Unit";"Zergling";"Larva";678;1
"Unit";"Zergling";"Larva";678;1
"Unit";"Zergling";"Larva";678;1
"Unit";"Zergling";"Larva";678;1
"Unit";"Zergling";"Larva";678;1
"Unit";"Zergling";"Larva";678;1
"Unit";"Zergling";"Larva";678;1
"Unit";"Zergling";"Larva";678;1
"Unit";"Zergling";"Larva";678;1
"Unit";"Zergling";"Larva";678;1
"Unit";"Zergling";"Larva";678;1
"Unit";"Zergling";"Larva";678;1
"Unit";"Zergling";"Larva";678;1
"Unit";"Zergling";"Larva";678;1
"Unit";"Zergling";"Larva";678;1
"Unit";"Zergling";"Larva";678;1
"Unit";"Zergling";"Larva";678;1
"Unit";"Zergling";"Larva";678;1
"Unit";"Zergling";"Larva";678;1
"Unit";"Zergling";"Larva";678;1
"Unit";"Zergling";"Larva";678;1
"Unit";"Zergling";"Larva";678;1
"Unit";"Zergling";"Larva";678;1
"Unit";"Zergling";"Larva";678;1
"Unit";"Zergling";"Larva";678;1
"Unit";"Zergling";"Larva";678;1
"Unit";"Zergling";"Larva";678;1
"Unit";"Zergling";"Larva";678;1
"Unit";"Zergling";"Larva";678;1
"Unit";"Zergling";"Larva";678;1
"Unit";"Zergling";"Larva";678;1
"Unit";"Zergling";"Larva";678;1
"Unit";"Zergling";"Larva";678;1
"Unit";"Zergling";"Larva";678;1
"Unit";"Zergling";"Larva";678;1
"Unit";"Zergling";"Larva";678;1
"Unit";"Zergling";"Larva";678;1
"Unit";"Zergling";"Larva";678;1
"Unit";"Zergling";"Larva";678;1
"Unit";"Zergling";"Larva";678;1
"Unit";"Zergling";"Larva";678;1
"Unit";"Zergling";"Larva";678;1
"Unit";"Zergling";"Larva";678;1
"Unit";"Zergling";"Larva";678;1
"Unit";"Zergling";"Larva";678;1
"Unit";"Zergling";"Larva";678;1
"Unit";"Zergling";"Larva";678;1
"Unit";"Zergling";"Larva";678;1
"Unit";"Zergling";"Larva";678;1
"Unit";"Zergling";"Larva";678;1
"Unit";"Zergling";"Larva";678;1
"Unit";"Zergling";"Larva";678;1
"Unit";"Zergling";"Larva";678;1
"Unit";"Zergling";"Larva";678;1
"Unit";"Zergling";"Larva";678;1
"Unit";"Zergling";"Larva";678;1
"Unit";"Zergling";"Larva";678;1
"Unit";"Zergling";"Larva";678;1
"Unit";"Zergling";"Larva";678;1
"Unit";"Zergling";"Larva";678;1
"Unit";"Zergling";"Larva";678;1
"Unit";"Zergling";"Larva";678;1
"Unit";"Zergling";"Larva";678;1
"Unit";"Zergling";"Larva";678;1
"Unit";"Zergling";"Larva";678;1
"Unit";"Zergling";"Larva";678;1
"Unit";"Zergling";"Larva";678;1
"Unit";"Zergling";"Larva";678;1
"Unit";"Zergling";"Larva";678;1
"Unit";"Zergling";"Larva";730;1
"Unit";"Zergling";"Larva";730;1
"Unit";"Zergling";"Larva";746;1
"Unit";"Zergling";"Larva";746;1
"Unit";"Zergling";"Larva";750;1
"Unit";"Zergling";"Larva";750;1
"Unit";"Zergling";"Larva";750;1
"Unit";"Zergling";"Larva";750;1
"Unit";"Baneling";"Zergling";760;0
"Unit";"Baneling";"Zergling";760;0
"Unit";"Baneling";"Zergling";760;0
"Unit";"Baneling";"Zergling";760;0
"Unit";"Baneling";"Zergling";760;0
"Unit";"Baneling";"Zergling";760;0
"Unit";"Baneling";"Zergling";760;0
"Unit";"Baneling";"Zergling";760;0
"Unit";"Baneling";"Zergling";760;0
"Unit";"Baneling";"Zergling";760;0
"Unit";"Baneling";"Zergling";760;0
"Unit";"Baneling";"Zergling";760;0
"Unit";"Baneling";"Zergling";760;0
"Building";"CreepTumor";NA;760;0
"Building";"CreepTumor";NA;760;0
"Building";"CreepTumor";NA;760;0
"Building";"CreepTumor";NA;760;0
"Building";"CreepTumor";NA;760;0
"Building";"CreepTumor";NA;760;0
"Unit";"Zergling";"Larva";768;1
"Unit";"Zergling";"Larva";768;1
"Unit";"Zergling";"Larva";768;1
"Unit";"Zergling";"Larva";768;1
"Unit";"Zergling";"Larva";768;1
"Unit";"Zergling";"Larva";768;1
"Unit";"Zergling";"Larva";768;1
"Unit";"Zergling";"Larva";768;1
"Unit";"Zergling";"Larva";768;1
"Unit";"Zergling";"Larva";768;1
"Unit";"Zergling";"Larva";768;1
"Unit";"Zergling";"Larva";768;1
"Unit";"Zergling";"Larva";768;1
"Unit";"Zergling";"Larva";768;1
"Unit";"Zergling";"Larva";768;1
"Unit";"Zergling";"Larva";768;1
"Unit";"Zergling";"Larva";768;1
"Unit";"Zergling";"Larva";768;1
"Unit";"Zergling";"Larva";768;1
"Unit";"Zergling";"Larva";768;1
"Unit";"Zergling";"Larva";768;1
"Unit";"Zergling";"Larva";768;1
"Unit";"Zergling";"Larva";768;1
"Unit";"Zergling";"Larva";768;1
"Unit";"Zergling";"Larva";768;1
"Unit";"Zergling";"Larva";768;1
"Unit";"Zergling";"Larva";768;1
"Unit";"Zergling";"Larva";768;1
"Unit";"Zergling";"Larva";768;1
"Unit";"Zergling";"Larva";768;1
"Unit";"Zergling";"Larva";768;1
"Unit";"Zergling";"Larva";768;1
"Unit";"Zergling";"Larva";768;1
"Unit";"Zergling";"Larva";768;1
"Unit";"Zergling";"Larva";768;1
"Unit";"Zergling";"Larva";768;1
"Building";"Hatchery";NA;678;0
"Unit";"Hydralisk";"Larva";768;2
"Unit";"Hydralisk";"Larva";768;2
"Unit";"Hydralisk";"Larva";768;2
"Unit";"Hydralisk";"Larva";768;2
"Unit";"Hydralisk";"Larva";768;2
"Unit";"Hydralisk";"Larva";768;2
"Unit";"Hydralisk";"Larva";768;2
"Unit";"Zergling";"Larva";768;1
"Unit";"Zergling";"Larva";768;1
"Unit";"Zergling";"Larva";768;1
"Unit";"Zergling";"Larva";768;1
"Unit";"Zergling";"Larva";768;1
"Unit";"Zergling";"Larva";768;1
"Unit";"Zergling";"Larva";768;1
"Unit";"Zergling";"Larva";768;1
"Unit";"Zergling";"Larva";768;1
"Unit";"Zergling";"Larva";768;1
"Unit";"Zergling";"Larva";768;1
"Unit";"Zergling";"Larva";768;1
"Unit";"Zergling";"Larva";768;1
"Unit";"Zergling";"Larva";768;1
"Unit";"Baneling";"Zergling";818;0
"Unit";"Baneling";"Zergling";818;0
"Unit";"Baneling";"Zergling";818;0
"Unit";"Baneling";"Zergling";818;0
"Unit";"Baneling";"Zergling";818;0
"Unit";"Baneling";"Zergling";818;0
"Unit";"Baneling";"Zergling";818;0
"Unit";"Baneling";"Zergling";818;0
"Unit";"Baneling";"Zergling";818;0
"Unit";"Baneling";"Zergling";818;0
"Unit";"Baneling";"Zergling";818;0
"Unit";"Baneling";"Zergling";818;0
"Unit";"Baneling";"Zergling";818;0
"Unit";"Baneling";"Zergling";818;0
"Unit";"Zergling";"Larva";832;1
"Unit";"Zergling";"Larva";832;1
"Unit";"Zergling";"Larva";832;1
"Unit";"Zergling";"Larva";832;1
"Unit";"Zergling";"Larva";832;1
"Unit";"Zergling";"Larva";832;1
"Unit";"Zergling";"Larva";832;1
"Unit";"Zergling";"Larva";832;1
"Unit";"Zergling";"Larva";832;1
"Unit";"Zergling";"Larva";832;1
"Unit";"Zergling";"Larva";832;1
"Unit";"Zergling";"Larva";832;1
"Unit";"Zergling";"Larva";832;1
"Unit";"Zergling";"Larva";832;1
"Unit";"Zergling";"Larva";832;1
"Unit";"Zergling";"Larva";832;1
"Unit";"Zergling";"Larva";832;1
"Unit";"Zergling";"Larva";832;1
"Unit";"Zergling";"Larva";832;1
"Unit";"Zergling";"Larva";832;1
"Unit";"Zergling";"Larva";832;1
"Unit";"Zergling";"Larva";832;1
"Unit";"Zergling";"Larva";832;1
"Unit";"Zergling";"Larva";832;1
"Unit";"Zergling";"Larva";832;1
"Unit";"Zergling";"Larva";832;1
"Unit";"Zergling";"Larva";832;1
"Unit";"Zergling";"Larva";832;1
"Unit";"Zergling";"Larva";832;1
"Unit";"Zergling";"Larva";832;1
"Unit";"Zergling";"Larva";832;1
"Unit";"Zergling";"Larva";832;1
"Unit";"Zergling";"Larva";864;1
"Unit";"Zergling";"Larva";864;1
"Unit";"Zergling";"Larva";864;1
"Unit";"Zergling";"Larva";864;1
"Unit";"Zergling";"Larva";864;1
"Unit";"Zergling";"Larva";864;1
"Unit";"Zergling";"Larva";864;1
"Unit";"Zergling";"Larva";864;1
"Unit";"Zergling";"Larva";864;1
"Unit";"Zergling";"Larva";864;1
"Unit";"Zergling";"Larva";864;1
"Unit";"Zergling";"Larva";864;1
"Unit";"Zergling";"Larva";864;1
"Unit";"Zergling";"Larva";864;1
"Unit";"Zergling";"Larva";864;1
"Unit";"Zergling";"Larva";864;1
"Unit";"Zergling";"Larva";864;1
"Unit";"Zergling";"Larva";864;1
"Unit";"Zergling";"Larva";864;1
"Unit";"Zergling";"Larva";864;1
"Unit";"Zergling";"Larva";864;1
"Unit";"Zergling";"Larva";864;1
"Unit";"Zergling";"Larva";864;1
"Unit";"Zergling";"Larva";864;1
"Unit";"Zergling";"Larva";864;1
"Unit";"Zergling";"Larva";864;1
"Unit";"Zergling";"Larva";864;1
"Unit";"Zergling";"Larva";864;1
"Unit";"Zergling";"Larva";864;1
"Unit";"Zergling";"Larva";864;1
"Unit";"Zergling";"Larva";864;1
"Unit";"Zergling";"Larva";864;1
"Unit";"Zergling";"Larva";864;1
"Unit";"Zergling";"Larva";864;1
"Unit";"Zergling";"Larva";864;1
"Unit";"Zergling";"Larva";864;1
"Unit";"Zergling";"Larva";864;1
"Unit";"Zergling";"Larva";864;1
"Unit";"Zergling";"Larva";864;1
"Unit";"Zergling";"Larva";864;1
"Unit";"Zergling";"Larva";864;1
"Unit";"Zergling";"Larva";864;1
"Unit";"Zergling";"Larva";864;1
"Unit";"Zergling";"Larva";864;1
"Unit";"Zergling";"Larva";864;1
"Unit";"Zergling";"Larva";864;1
"Unit";"Zergling";"Larva";864;1
"Unit";"Zergling";"Larva";864;1
"Unit";"Zergling";"Larva";864;1
"Unit";"Zergling";"Larva";864;1
"Unit";"Zergling";"Larva";864;1
"Unit";"Zergling";"Larva";864;1
"Unit";"Zergling";"Larva";864;1
"Unit";"Zergling";"Larva";864;1
"Unit";"Zergling";"Larva";864;1
"Unit";"Zergling";"Larva";864;1
"Unit";"Zergling";"Larva";864;1
"Unit";"Zergling";"Larva";864;1
"Unit";"Zergling";"Larva";864;1
"Unit";"Zergling";"Larva";864;1
"Unit";"Zergling";"Larva";864;1
"Unit";"Zergling";"Larva";864;1
"Unit";"Zergling";"Larva";864;1
"Unit";"Zergling";"Larva";864;1
"Unit";"Zergling";"Larva";864;1
"Unit";"Zergling";"Larva";864;1
"Unit";"Zergling";"Larva";864;1
"Unit";"Zergling";"Larva";864;1
"Unit";"Zergling";"Larva";864;1
"Unit";"Zergling";"Larva";864;1
"Building";"CreepTumor";NA;900;0
"Building";"CreepTumor";NA;900;0
"Unit";"Zergling";"Larva";900;1
"Unit";"Zergling";"Larva";900;1
"Unit";"Zergling";"Larva";900;1
"Unit";"Zergling";"Larva";900;1
"Unit";"Zergling";"Larva";900;1
"Unit";"Zergling";"Larva";900;1
"Unit";"Zergling";"Larva";900;1
"Unit";"Zergling";"Larva";900;1
"Unit";"Zergling";"Larva";900;1
"Unit";"Zergling";"Larva";900;1
"Unit";"Zergling";"Larva";900;1
"Unit";"Zergling";"Larva";900;1
"Unit";"Zergling";"Larva";900;1
"Unit";"Zergling";"Larva";900;1
"Unit";"Zergling";"Larva";900;1
"Unit";"Zergling";"Larva";900;1
"Unit";"Zergling";"Larva";900;1
"Unit";"Zergling";"Larva";900;1
"Unit";"Zergling";"Larva";900;1
"Unit";"Zergling";"Larva";900;1
"Unit";"Zergling";"Larva";900;1
"Unit";"Zergling";"Larva";900;1
"Building";"CreepTumor";NA;934;0
"Unit";"Zergling";"Larva";956;1
"Unit";"Zergling";"Larva";956;1
"Unit";"Zergling";"Larva";956;1
"Unit";"Zergling";"Larva";956;1
"Unit";"Zergling";"Larva";956;1
"Unit";"Zergling";"Larva";956;1
"Unit";"Zergling";"Larva";956;1
"Unit";"Zergling";"Larva";956;1
"Unit";"Zergling";"Larva";956;1
"Unit";"Zergling";"Larva";956;1
"Unit";"Zergling";"Larva";956;1
"Unit";"Zergling";"Larva";956;1
"Unit";"Zergling";"Larva";956;1
"Unit";"Zergling";"Larva";956;1
"Unit";"Zergling";"Larva";956;1
"Unit";"Zergling";"Larva";956;1
"Unit";"Zergling";"Larva";956;1
"Unit";"Zergling";"Larva";956;1
"Unit";"Zergling";"Larva";956;1
"Unit";"Zergling";"Larva";956;1
"Unit";"Zergling";"Larva";956;1
"Unit";"Zergling";"Larva";956;1
"Unit";"Zergling";"Larva";956;1
"Unit";"Zergling";"Larva";956;1
"Unit";"Zergling";"Larva";956;1
"Unit";"Zergling";"Larva";956;1
"Unit";"Zergling";"Larva";956;1
"Unit";"Zergling";"Larva";956;1
"Unit";"Zergling";"Larva";956;1
"Unit";"Zergling";"Larva";956;1
"Unit";"Zergling";"Larva";956;1
"Unit";"Zergling";"Larva";956;1
"Unit";"Zergling";"Larva";956;1
"Unit";"Zergling";"Larva";956;1
"Unit";"Baneling";"Zergling";956;0
"Unit";"Baneling";"Zergling";956;0
"Unit";"Baneling";"Zergling";956;0
"Unit";"Baneling";"Zergling";956;0
"Unit";"Baneling";"Zergling";956;0
"Unit";"Baneling";"Zergling";956;0
"Unit";"Baneling";"Zergling";956;0
"Unit";"Baneling";"Zergling";956;0
"Unit";"Baneling";"Zergling";956;0
"Unit";"Baneling";"Zergling";956;0
"Unit";"Baneling";"Zergling";956;0
"Unit";"Baneling";"Zergling";956;0
"Unit";"Baneling";"Zergling";956;0
"Unit";"Baneling";"Zergling";956;0
"Unit";"Baneling";"Zergling";956;0
"Unit";"Baneling";"Zergling";956;0
"Unit";"Baneling";"Zergling";956;0
"Unit";"Baneling";"Zergling";956;0
"Unit";"Baneling";"Zergling";956;0
"Unit";"Infestor";"Larva";956;2
"Unit";"Infestor";"Larva";956;2
"Unit";"Infestor";"Larva";956;2
"Unit";"Infestor";"Larva";956;2
"Unit";"Infestor";"Larva";956;2
"Unit";"Infestor";"Larva";956;2
"Unit";"Infestor";"Larva";956;2
"Unit";"Infestor";"Larva";956;2
"Unit";"Infestor";"Larva";956;2
"Unit";"Zergling";"Larva";990;1
"Unit";"Zergling";"Larva";990;1
"Unit";"Zergling";"Larva";990;1
"Unit";"Zergling";"Larva";990;1
"Unit";"Zergling";"Larva";990;1
"Unit";"Zergling";"Larva";990;1
"Unit";"Zergling";"Larva";990;1
"Unit";"Zergling";"Larva";990;1
"Unit";"Zergling";"Larva";990;1
"Unit";"Zergling";"Larva";990;1
"Unit";"Zergling";"Larva";990;1
"Unit";"Zergling";"Larva";990;1
"Building";"SporeCrawler";NA;990;0
"Building";"SporeCrawler";NA;990;0
"Upgrade";"Burrow";"Hatchery";990;0
"Upgrade";"ZergGroundArmorsLevel3";"EvolutionChamber";900;0
"Unit";"Zergling";"Larva";1020;1
"Unit";"Zergling";"Larva";1020;1
"Unit";"Zergling";"Larva";1020;1
"Unit";"Zergling";"Larva";1020;1
"Unit";"Zergling";"Larva";1020;1
"Unit";"Zergling";"Larva";1020;1
"Unit";"Zergling";"Larva";1020;1
"Unit";"Zergling";"Larva";1020;1
"Unit";"Zergling";"Larva";1020;1
"Unit";"Zergling";"Larva";1020;1
"Unit";"Zergling";"Larva";1020;1
"Unit";"Zergling";"Larva";1020;1
"Unit";"Zergling";"Larva";1020;1
"Unit";"Zergling";"Larva";1020;1
"Unit";"Zergling";"Larva";1020;1
"Unit";"Zergling";"Larva";1020;1
"Unit";"Zergling";"Larva";1020;1
"Unit";"Zergling";"Larva";1020;1
"Unit";"Zergling";"Larva";1020;1
"Unit";"Zergling";"Larva";1020;1
"Unit";"Zergling";"Larva";1020;1
"Unit";"Zergling";"Larva";1020;1
"Unit";"Zergling";"Larva";1020;1
"Unit";"Zergling";"Larva";1020;1
"Unit";"Zergling";"Larva";1020;1
"Unit";"Zergling";"Larva";1020;1
"Unit";"Zergling";"Larva";1020;1
"Unit";"Zergling";"Larva";1020;1
"Unit";"Zergling";"Larva";1020;1
"Unit";"Zergling";"Larva";1020;1
"Unit";"Zergling";"Larva";1020;1
"Unit";"Zergling";"Larva";1020;1
"Unit";"Zergling";"Larva";1020;1
"Unit";"Zergling";"Larva";1020;1
"Unit";"Zergling";"Larva";1020;1
"Unit";"Zergling";"Larva";1020;1
"Unit";"Zergling";"Larva";1020;1
"Unit";"Zergling";"Larva";1020;1
"Unit";"Zergling";"Larva";1020;1
"Unit";"Zergling";"Larva";1020;1
"Unit";"Zergling";"Larva";1020;1
"Unit";"Zergling";"Larva";1020;1
"Unit";"Zergling";"Larva";1020;1
"Unit";"Zergling";"Larva";1020;1
"Unit";"Zergling";"Larva";1020;1
"Unit";"Zergling";"Larva";1020;1
"Unit";"Zergling";"Larva";1020;1
"Unit";"Zergling";"Larva";1020;1
"Unit";"Zergling";"Larva";1020;1
"Unit";"Zergling";"Larva";1020;1
"Unit";"Zergling";"Larva";1020;1
"Unit";"Zergling";"Larva";1020;1
"Unit";"Zergling";"Larva";1020;1
"Unit";"Zergling";"Larva";1020;1
"Building";"CreepTumor";NA;1021;0
"Upgrade";"NeuralParasite";"InfestationPit";1020;0
"Unit";"Zergling";"Larva";1075;1
"Unit";"Zergling";"Larva";1075;1
"Unit";"Zergling";"Larva";1075;1
"Unit";"Zergling";"Larva";1075;1
"Unit";"Zergling";"Larva";1075;1
"Unit";"Zergling";"Larva";1075;1
"Unit";"Zergling";"Larva";1075;1
"Unit";"Zergling";"Larva";1075;1
"Unit";"Zergling";"Larva";1075;1
"Unit";"Zergling";"Larva";1075;1
"Unit";"Zergling";"Larva";1075;1
"Unit";"Zergling";"Larva";1075;1
"Unit";"Zergling";"Larva";1075;1
"Unit";"Zergling";"Larva";1075;1
"Unit";"Zergling";"Larva";1075;1
"Unit";"Zergling";"Larva";1075;1
"Unit";"Zergling";"Larva";1075;1
"Unit";"Zergling";"Larva";1075;1
"Unit";"Zergling";"Larva";1075;1
"Unit";"Zergling";"Larva";1075;1
"Unit";"Zergling";"Larva";1075;1
"Unit";"Zergling";"Larva";1075;1
"Unit";"Zergling";"Larva";1075;1
"Unit";"Zergling";"Larva";1075;1
"Unit";"Zergling";"Larva";1075;1
"Unit";"Zergling";"Larva";1075;1
"Unit";"Zergling";"Larva";1075;1
"Unit";"Zergling";"Larva";1075;1
"Unit";"Zergling";"Larva";1075;1
"Unit";"Zergling";"Larva";1075;1
"Unit";"Zergling";"Larva";1075;1
"Unit";"Zergling";"Larva";1075;1
"Unit";"Zergling";"Larva";1075;1
"Unit";"Zergling";"Larva";1075;1
"Unit";"Zergling";"Larva";1075;1
"Unit";"Zergling";"Larva";1075;1
"Unit";"Zergling";"Larva";1075;1
"Unit";"Zergling";"Larva";1075;1
