"type";"unit_name";"on_building";"total_supply";"supply"
"Unit";"Overlord";"Larva";12;0
"Building";"Extractor";NA;18;0
"Building";"SpawningPool";NA;18;0
"Unit";"Overlord";"Larva";22;0
"Building";"Hatchery";NA;17;0
"Unit";"Zergling";"Larva";22;1
"Unit";"Zergling";"Larva";22;1
"Unit";"Queen";"Hatchery";22;2
"Building";"RoachWarren";NA;22;0
"Unit";"Queen";"Hatchery";23;2
"Unit";"Overlord";"Larva";35;0
"Unit";"Queen";"Hatchery";32;2
"Unit";"Queen";"Hatchery";35;2
"Building";"CreepTumorQueen";NA;39;0
"Building";"CreepTumorQueen";NA;39;0
"Unit";"Zergling";"Larva";41;1
"Unit";"Zergling";"Larva";41;1
"Unit";"Zergling";"Larva";41;1
"Unit";"Zergling";"Larva";41;1
"Unit";"Zergling";"Larva";43;1
"Unit";"Zergling";"Larva";43;1
"Unit";"Overlord";"Larva";45;0
"Building";"CreepTumor";NA;51;0
"Building";"Extractor";NA;48;0
"Building";"CreepTumor";NA;53;0
"Building";"EvolutionChamber";NA;51;0
"Building";"CreepTumorQueen";NA;53;0
"Unit";"Roach";"Larva";53;2
"Unit";"Roach";"Larva";53;2
"Unit";"Roach";"Larva";53;2
"Unit";"Roach";"Larva";53;2
"Unit";"Roach";"Larva";53;2
"Unit";"Overlord";"Larva";53;0
"Unit";"Overlord";"Larva";53;0
"Building";"Hatchery";NA;37;0
"Building";"CreepTumor";NA;53;0
"Building";"CreepTumorQueen";NA;61;0
"Building";"CreepTumor";NA;76;0
"Building";"CreepTumor";NA;76;0
"Building";"Extractor";NA;72;0
"Building";"CreepTumor";NA;76;0
"Building";"CreepTumorQueen";NA;76;0
"Unit";"Roach";"Larva";76;2
"Unit";"Roach";"Larva";76;2
"Unit";"Queen";"Hatchery";75;2
"Unit";"Overlord";"Larva";80;0
"Unit";"Overlord";"Larva";80;0
"Unit";"Overlord";"Larva";80;0
"Unit";"Overlord";"Larva";80;0
"Unit";"Overlord";"Larva";82;0
"Building";"CreepTumor";NA;86;0
"Building";"CreepTumor";NA;86;0
"Unit";"Roach";"Larva";86;2
"Unit";"Roach";"Larva";86;2
"Unit";"Roach";"Larva";86;2
"Unit";"Roach";"Larva";86;2
"Unit";"Roach";"Larva";86;2
"Upgrade";"ZergMissileWeaponsLevel1";"EvolutionChamber";72;0
"Building";"Extractor";NA;86;0
"Unit";"Roach";"Larva";96;2
"Unit";"Roach";"Larva";96;2
"Building";"CreepTumorQueen";NA;96;0
"Building";"HydraliskDen";NA;96;0
"Building";"CreepTumorQueen";NA;100;0
"Building";"CreepTumor";NA;100;0
"Unit";"Overlord";"Larva";100;0
"Unit";"Overlord";"Larva";100;0
"Unit";"Overlord";"Larva";100;0
"Unit";"Overlord";"Larva";100;0
"Unit";"Hydralisk";"Larva";100;2
"Unit";"Hydralisk";"Larva";100;2
"Unit";"Hydralisk";"Larva";100;2
"Unit";"Hydralisk";"Larva";100;2
"Unit";"Hydralisk";"Larva";100;2
"Unit";"Zergling";"Larva";100;1
"Unit";"Zergling";"Larva";100;1
"Unit";"Zergling";"Larva";100;1
"Unit";"Zergling";"Larva";100;1
"Unit";"Zergling";"Larva";100;1
"Unit";"Zergling";"Larva";100;1
"Unit";"Zergling";"Larva";100;1
"Unit";"Zergling";"Larva";100;1
"Unit";"Hydralisk";"Larva";100;2
"Building";"CreepTumor";NA;108;0
"Building";"CreepTumor";NA;109;0
"Building";"Hatchery";NA;96;0
"Building";"Extractor";NA;126;0
"Building";"Extractor";NA;132;0
"Unit";"Hydralisk";"Larva";136;2
"Upgrade";"ZergGroundArmorsLevel1";"EvolutionChamber";100;0
"Unit";"Hydralisk";"Larva";136;2
"Unit";"Zergling";"Larva";136;1
"Unit";"Zergling";"Larva";136;1
"Unit";"Zergling";"Larva";136;1
"Unit";"Zergling";"Larva";136;1
"Unit";"Zergling";"Larva";136;1
"Unit";"Zergling";"Larva";136;1
"Unit";"Zergling";"Larva";136;1
"Unit";"Zergling";"Larva";136;1
"Unit";"Zergling";"Larva";136;1
"Unit";"Zergling";"Larva";136;1
"Unit";"Zergling";"Larva";136;1
"Unit";"Zergling";"Larva";136;1
"Building";"InfestationPit";NA;136;0
"Unit";"Zergling";"Larva";136;1
"Unit";"Zergling";"Larva";136;1
"Unit";"Zergling";"Larva";136;1
"Unit";"Zergling";"Larva";136;1
"Unit";"Zergling";"Larva";136;1
"Unit";"Zergling";"Larva";136;1
"Unit";"Zergling";"Larva";136;1
"Unit";"Zergling";"Larva";136;1
"Building";"Hatchery";NA;100;0
"Unit";"Zergling";"Larva";136;1
"Unit";"Zergling";"Larva";136;1
"Unit";"Zergling";"Larva";136;1
"Unit";"Zergling";"Larva";136;1
"Unit";"Zergling";"Larva";136;1
"Unit";"Zergling";"Larva";136;1
"Unit";"Zergling";"Larva";136;1
"Unit";"Zergling";"Larva";136;1
"Upgrade";"EvolveGroovedSpines";"HydraliskDen";136;0
"Building";"CreepTumor";NA;170;0
"Building";"CreepTumor";NA;170;0
"Unit";"Hydralisk";"Larva";170;2
"Unit";"Hydralisk";"Larva";170;2
"Unit";"Hydralisk";"Larva";170;2
"Unit";"Hydralisk";"Larva";170;2
"Unit";"Hydralisk";"Larva";170;2
"Unit";"Hydralisk";"Larva";170;2
"Unit";"Hydralisk";"Larva";170;2
"Unit";"Hydralisk";"Larva";170;2
"Unit";"Hydralisk";"Larva";170;2
"Unit";"Hydralisk";"Larva";170;2
"Unit";"Hydralisk";"Larva";170;2
"Unit";"Hydralisk";"Larva";170;2
"Unit";"Hydralisk";"Larva";170;2
"Unit";"Hydralisk";"Larva";170;2
"Unit";"Hydralisk";"Larva";170;2
"Upgrade";"EvolveMuscularAugments";"HydraliskDen";170;0
"Building";"CreepTumor";NA;215;0
"Building";"CreepTumor";NA;215;0
"Unit";"Overlord";"Larva";215;0
"Unit";"Overlord";"Larva";215;0
"Unit";"Overlord";"Larva";215;0
"Unit";"Overlord";"Larva";215;0
"Building";"CreepTumorQueen";NA;215;0
"Building";"Extractor";NA;215;0
"Building";"Extractor";NA;215;0
"Building";"Extractor";NA;215;0
"Building";"Extractor";NA;215;0
"Unit";"Zergling";"Larva";215;1
"Unit";"Zergling";"Larva";215;1
"Unit";"Zergling";"Larva";215;1
"Unit";"Zergling";"Larva";215;1
"Unit";"Zergling";"Larva";215;1
"Unit";"Zergling";"Larva";215;1
"Unit";"Zergling";"Larva";215;1
"Unit";"Zergling";"Larva";215;1
"Unit";"Zergling";"Larva";215;1
"Unit";"Zergling";"Larva";215;1
"Unit";"Zergling";"Larva";215;1
"Unit";"Zergling";"Larva";215;1
"Unit";"Hydralisk";"Larva";215;2
"Unit";"Hydralisk";"Larva";215;2
"Unit";"Hydralisk";"Larva";215;2
"Unit";"Hydralisk";"Larva";215;2
"Unit";"Hydralisk";"Larva";215;2
"Unit";"Hydralisk";"Larva";215;2
"Building";"Spire";NA;215;0
"Building";"CreepTumor";NA;239;0
"Building";"CreepTumor";NA;239;0
"Building";"CreepTumor";NA;239;0
"Building";"CreepTumor";NA;239;0
