"type";"unit_name";"on_building";"total_supply";"supply"
"Unit";"Overlord";"Larva";12;0
"Building";"SpawningPool";NA;19;0
"Building";"Hatchery";NA;17;0
"Building";"Extractor";NA;21;0
"Unit";"Zergling";"Larva";23;1
"Unit";"Zergling";"Larva";23;1
"Unit";"Zergling";"Larva";23;1
"Unit";"Zergling";"Larva";23;1
"Unit";"Overlord";"Larva";23;0
"Unit";"Queen";"Hatchery";23;2
"Building";"Hatchery";NA;21;0
"Unit";"Overlord";"Larva";32;0
"Unit";"Queen";"Hatchery";29;2
"Unit";"Overlord";"Larva";38;0
"Unit";"Queen";"Hatchery";42;2
"Unit";"Overlord";"Larva";55;0
"Unit";"Overlord";"Larva";55;0
"Unit";"Zergling";"Larva";55;1
"Unit";"Zergling";"Larva";55;1
"Unit";"Zergling";"Larva";55;1
"Unit";"Zergling";"Larva";55;1
"Unit";"Zergling";"Larva";55;1
"Unit";"Zergling";"Larva";55;1
"Unit";"Zergling";"Larva";55;1
"Unit";"Zergling";"Larva";55;1
"Building";"CreepTumorQueen";NA;55;0
"Unit";"Queen";"Hatchery";53;2
"Unit";"Queen";"Hatchery";53;2
"Unit";"Overlord";"Larva";63;0
"Unit";"Zergling";"Larva";63;1
"Unit";"Zergling";"Larva";63;1
"Unit";"Zergling";"Larva";63;1
"Unit";"Zergling";"Larva";63;1
"Unit";"Zergling";"Larva";63;1
"Unit";"Zergling";"Larva";63;1
"Unit";"Zergling";"Larva";63;1
"Unit";"Zergling";"Larva";63;1
"Unit";"Zergling";"Larva";63;1
"Unit";"Zergling";"Larva";63;1
"Unit";"Zergling";"Larva";63;1
"Unit";"Zergling";"Larva";63;1
"Unit";"Zergling";"Larva";63;1
"Unit";"Zergling";"Larva";63;1
"Unit";"Zergling";"Larva";63;1
"Unit";"Zergling";"Larva";63;1
"Unit";"Zergling";"Larva";63;1
"Unit";"Zergling";"Larva";63;1
"Building";"CreepTumor";NA;69;0
"Building";"BanelingNest";NA;55;0
"Building";"CreepTumorQueen";NA;85;0
"Unit";"Overlord";"Larva";85;0
"Unit";"Baneling";"Zergling";85;0
"Unit";"Baneling";"Zergling";85;0
"Unit";"Baneling";"Zergling";85;0
"Unit";"Baneling";"Zergling";85;0
"Unit";"Baneling";"Zergling";85;0
"Unit";"Baneling";"Zergling";85;0
"Unit";"Queen";"Hatchery";67;2
"Unit";"Queen";"Hatchery";67;2
"Unit";"Queen";"Hatchery";67;2
"Unit";"Overlord";"Larva";85;0
"Unit";"Baneling";"Zergling";85;0
"Unit";"Overlord";"Larva";85;0
"Unit";"Zergling";"Larva";95;1
"Unit";"Zergling";"Larva";95;1
"Unit";"Zergling";"Larva";95;1
"Unit";"Zergling";"Larva";95;1
"Unit";"Zergling";"Larva";95;1
"Unit";"Zergling";"Larva";95;1
"Unit";"Zergling";"Larva";95;1
"Unit";"Zergling";"Larva";95;1
"Unit";"Zergling";"Larva";95;1
"Unit";"Zergling";"Larva";95;1
"Unit";"Zergling";"Larva";95;1
"Unit";"Zergling";"Larva";95;1
"Unit";"Zergling";"Larva";95;1
"Unit";"Zergling";"Larva";95;1
"Unit";"Zergling";"Larva";95;1
"Unit";"Zergling";"Larva";95;1
"Unit";"Zergling";"Larva";95;1
"Unit";"Zergling";"Larva";95;1
"Unit";"Queen";"Hatchery";85;2
"Building";"CreepTumorQueen";NA;97;0
"Building";"CreepTumorQueen";NA;97;0
"Building";"CreepTumorQueen";NA;111;0
"Building";"CreepTumor";NA;115;0
"Building";"CreepTumorQueen";NA;119;0
"Building";"Extractor";NA;119;0
"Building";"Extractor";NA;119;0
"Building";"EvolutionChamber";NA;119;0
"Building";"CreepTumor";NA;128;0
"Building";"EvolutionChamber";NA;119;0
"Unit";"Queen";"Hatchery";115;2
"Building";"CreepTumor";NA;128;0
"Building";"CreepTumor";NA;128;0
"Building";"CreepTumor";NA;128;0
"Building";"CreepTumor";NA;128;0
"Building";"CreepTumorQueen";NA;135;0
"Unit";"Overlord";"Larva";132;0
"Building";"CreepTumorQueen";NA;137;0
"Building";"CreepTumor";NA;143;0
"Building";"CreepTumor";NA;143;0
"Building";"Hatchery";NA;113;0
"Building";"CreepTumor";NA;147;0
"Building";"Extractor";NA;143;0
"Building";"Extractor";NA;143;0
"Building";"CreepTumor";NA;147;0
"Building";"CreepTumor";NA;147;0
"Building";"Extractor";NA;147;0
"Building";"CreepTumorQueen";NA;155;0
"Building";"CreepTumorQueen";NA;155;0
"Building";"CreepTumorQueen";NA;155;0
"Building";"CreepTumorQueen";NA;155;0
"Building";"CreepTumor";NA;155;0
"Unit";"Overlord";"Larva";153;0
"Building";"CreepTumor";NA;155;0
"Building";"CreepTumor";NA;155;0
"Unit";"Zergling";"Larva";155;1
"Unit";"Zergling";"Larva";155;1
"Unit";"Zergling";"Larva";155;1
"Unit";"Zergling";"Larva";155;1
"Unit";"Zergling";"Larva";155;1
"Unit";"Zergling";"Larva";155;1
"Unit";"Zergling";"Larva";155;1
"Unit";"Zergling";"Larva";155;1
"Unit";"Zergling";"Larva";155;1
"Unit";"Zergling";"Larva";155;1
"Unit";"Zergling";"Larva";155;1
"Unit";"Zergling";"Larva";155;1
"Unit";"Zergling";"Larva";155;1
"Unit";"Zergling";"Larva";155;1
"Unit";"Zergling";"Larva";155;1
"Unit";"Zergling";"Larva";155;1
"Unit";"Zergling";"Larva";155;1
"Unit";"Zergling";"Larva";155;1
"Unit";"Zergling";"Larva";155;1
"Unit";"Zergling";"Larva";155;1
"Unit";"Zergling";"Larva";155;1
"Unit";"Zergling";"Larva";155;1
"Unit";"Zergling";"Larva";155;1
"Unit";"Zergling";"Larva";155;1
"Unit";"Zergling";"Larva";155;1
"Unit";"Zergling";"Larva";155;1
"Unit";"Zergling";"Larva";173;1
"Unit";"Zergling";"Larva";173;1
"Unit";"Zergling";"Larva";173;1
"Unit";"Zergling";"Larva";173;1
"Unit";"Zergling";"Larva";173;1
"Unit";"Zergling";"Larva";173;1
"Unit";"Zergling";"Larva";173;1
"Unit";"Zergling";"Larva";173;1
"Unit";"Zergling";"Larva";173;1
"Unit";"Zergling";"Larva";173;1
"Unit";"Zergling";"Larva";173;1
"Unit";"Zergling";"Larva";173;1
"Unit";"Zergling";"Larva";173;1
"Unit";"Zergling";"Larva";173;1
"Unit";"Zergling";"Larva";173;1
"Unit";"Zergling";"Larva";173;1
"Unit";"Zergling";"Larva";173;1
"Unit";"Zergling";"Larva";173;1
"Unit";"Zergling";"Larva";173;1
"Unit";"Zergling";"Larva";173;1
"Unit";"Zergling";"Larva";173;1
"Unit";"Zergling";"Larva";173;1
"Unit";"Overlord";"Larva";181;0
"Unit";"Overlord";"Larva";181;0
"Unit";"Baneling";"Zergling";203;0
"Unit";"Baneling";"Zergling";203;0
"Unit";"Baneling";"Zergling";203;0
"Unit";"Baneling";"Zergling";203;0
"Unit";"Baneling";"Zergling";203;0
"Unit";"Baneling";"Zergling";203;0
"Unit";"Baneling";"Zergling";203;0
"Unit";"Baneling";"Zergling";203;0
"Building";"CreepTumor";NA;203;0
"Unit";"Overlord";"Larva";203;0
"Unit";"Overlord";"Larva";203;0
"Unit";"Queen";"Hatchery";181;2
"Unit";"Queen";"Hatchery";181;2
"Unit";"Queen";"Hatchery";181;2
"Unit";"Zergling";"Larva";207;1
"Unit";"Zergling";"Larva";207;1
"Unit";"Zergling";"Larva";207;1
"Unit";"Zergling";"Larva";207;1
"Unit";"Zergling";"Larva";207;1
"Unit";"Zergling";"Larva";207;1
"Unit";"Zergling";"Larva";207;1
"Unit";"Zergling";"Larva";207;1
"Unit";"Zergling";"Larva";207;1
"Unit";"Zergling";"Larva";207;1
"Unit";"Zergling";"Larva";207;1
"Unit";"Zergling";"Larva";207;1
"Unit";"Zergling";"Larva";207;1
"Unit";"Zergling";"Larva";207;1
"Unit";"Zergling";"Larva";207;1
"Unit";"Zergling";"Larva";207;1
"Unit";"Zergling";"Larva";207;1
"Unit";"Zergling";"Larva";207;1
"Unit";"Zergling";"Larva";207;1
"Unit";"Zergling";"Larva";207;1
"Unit";"Zergling";"Larva";207;1
"Unit";"Zergling";"Larva";207;1
"Unit";"Zergling";"Larva";207;1
"Unit";"Zergling";"Larva";207;1
"Unit";"Zergling";"Larva";207;1
"Unit";"Zergling";"Larva";207;1
"Unit";"Zergling";"Larva";207;1
"Unit";"Zergling";"Larva";207;1
"Unit";"Zergling";"Larva";207;1
"Unit";"Zergling";"Larva";207;1
"Unit";"Zergling";"Larva";207;1
"Unit";"Zergling";"Larva";207;1
"Unit";"Zergling";"Larva";207;1
"Unit";"Zergling";"Larva";207;1
"Unit";"Zergling";"Larva";207;1
"Unit";"Zergling";"Larva";207;1
"Unit";"Zergling";"Larva";207;1
"Unit";"Zergling";"Larva";207;1
"Unit";"Zergling";"Larva";207;1
"Unit";"Zergling";"Larva";207;1
"Unit";"Zergling";"Larva";207;1
"Unit";"Zergling";"Larva";207;1
"Upgrade";"ZergGroundArmorsLevel1";"EvolutionChamber";155;0
"Unit";"Zergling";"Larva";207;1
"Unit";"Zergling";"Larva";207;1
"Unit";"Zergling";"Larva";207;1
"Unit";"Zergling";"Larva";207;1
"Unit";"Zergling";"Larva";209;1
"Unit";"Zergling";"Larva";209;1
"Upgrade";"ZergMeleeWeaponsLevel1";"EvolutionChamber";155;0
"Unit";"Zergling";"Larva";209;1
"Unit";"Zergling";"Larva";209;1
"Unit";"Zergling";"Larva";209;1
"Unit";"Zergling";"Larva";209;1
"Unit";"Zergling";"Larva";209;1
"Unit";"Zergling";"Larva";209;1
"Unit";"Zergling";"Larva";209;1
"Unit";"Zergling";"Larva";209;1
"Unit";"Zergling";"Larva";209;1
"Unit";"Zergling";"Larva";209;1
"Unit";"Zergling";"Larva";209;1
"Unit";"Zergling";"Larva";209;1
"Unit";"Zergling";"Larva";209;1
"Unit";"Zergling";"Larva";209;1
"Unit";"Baneling";"Zergling";257;0
"Unit";"Baneling";"Zergling";257;0
"Unit";"Baneling";"Zergling";257;0
"Unit";"Baneling";"Zergling";257;0
"Unit";"Baneling";"Zergling";257;0
"Unit";"Baneling";"Zergling";257;0
"Unit";"Baneling";"Zergling";257;0
"Unit";"Baneling";"Zergling";257;0
"Unit";"Baneling";"Zergling";257;0
"Building";"CreepTumorQueen";NA;265;0
"Building";"CreepTumorQueen";NA;265;0
"Unit";"Queen";"Hatchery";209;2
"Unit";"Zergling";"Larva";257;1
"Unit";"Zergling";"Larva";257;1
"Unit";"Zergling";"Larva";257;1
"Unit";"Zergling";"Larva";257;1
"Unit";"Zergling";"Larva";257;1
"Unit";"Zergling";"Larva";257;1
"Unit";"Zergling";"Larva";257;1
"Unit";"Zergling";"Larva";257;1
"Building";"CreepTumorQueen";NA;271;0
"Building";"CreepTumorQueen";NA;271;0
"Unit";"Queen";"Hatchery";265;2
"Unit";"Zergling";"Larva";281;1
"Unit";"Zergling";"Larva";281;1
"Unit";"Zergling";"Larva";281;1
"Unit";"Zergling";"Larva";281;1
"Unit";"Zergling";"Larva";281;1
"Unit";"Zergling";"Larva";281;1
"Unit";"Zergling";"Larva";281;1
"Unit";"Zergling";"Larva";281;1
"Unit";"Zergling";"Larva";281;1
"Unit";"Zergling";"Larva";281;1
"Unit";"Zergling";"Larva";281;1
"Unit";"Zergling";"Larva";281;1
"Unit";"Zergling";"Larva";281;1
"Unit";"Zergling";"Larva";281;1
"Unit";"Zergling";"Larva";281;1
"Unit";"Zergling";"Larva";281;1
"Unit";"Zergling";"Larva";281;1
"Unit";"Zergling";"Larva";281;1
"Unit";"Zergling";"Larva";281;1
"Unit";"Zergling";"Larva";281;1
"Unit";"Zergling";"Larva";281;1
"Unit";"Zergling";"Larva";281;1
"Unit";"Zergling";"Larva";281;1
"Unit";"Zergling";"Larva";281;1
"Unit";"Zergling";"Larva";281;1
"Unit";"Zergling";"Larva";281;1
"Unit";"Zergling";"Larva";281;1
"Unit";"Zergling";"Larva";281;1
"Unit";"Zergling";"Larva";283;1
"Unit";"Zergling";"Larva";283;1
"Unit";"Zergling";"Larva";283;1
"Unit";"Zergling";"Larva";283;1
"Unit";"Zergling";"Larva";283;1
"Unit";"Zergling";"Larva";283;1
"Unit";"Zergling";"Larva";283;1
"Unit";"Zergling";"Larva";283;1
"Unit";"Zergling";"Larva";283;1
"Unit";"Zergling";"Larva";283;1
"Unit";"Zergling";"Larva";311;1
"Unit";"Zergling";"Larva";311;1
"Unit";"Zergling";"Larva";311;1
"Unit";"Zergling";"Larva";311;1
"Unit";"Zergling";"Larva";311;1
"Unit";"Zergling";"Larva";311;1
"Unit";"Zergling";"Larva";311;1
"Unit";"Zergling";"Larva";311;1
"Unit";"Zergling";"Larva";311;1
"Unit";"Zergling";"Larva";311;1
"Unit";"Zergling";"Larva";311;1
"Unit";"Zergling";"Larva";311;1
"Unit";"Zergling";"Larva";311;1
"Unit";"Zergling";"Larva";311;1
"Unit";"Queen";"Hatchery";283;2
"Unit";"Zergling";"Larva";321;1
"Unit";"Zergling";"Larva";321;1
"Unit";"Zergling";"Larva";321;1
"Unit";"Zergling";"Larva";321;1
"Unit";"Zergling";"Larva";321;1
"Unit";"Zergling";"Larva";321;1
"Unit";"Zergling";"Larva";321;1
"Unit";"Zergling";"Larva";321;1
"Unit";"Zergling";"Larva";321;1
"Unit";"Zergling";"Larva";321;1
"Unit";"Zergling";"Larva";321;1
"Unit";"Zergling";"Larva";321;1
"Unit";"Zergling";"Larva";321;1
"Unit";"Zergling";"Larva";321;1
"Unit";"Zergling";"Larva";321;1
"Unit";"Zergling";"Larva";321;1
"Unit";"Zergling";"Larva";321;1
"Unit";"Zergling";"Larva";321;1
"Unit";"Zergling";"Larva";321;1
"Unit";"Zergling";"Larva";321;1
"Unit";"Zergling";"Larva";321;1
"Unit";"Zergling";"Larva";321;1
"Unit";"Baneling";"Zergling";359;0
"Unit";"Baneling";"Zergling";359;0
"Unit";"Baneling";"Zergling";359;0
"Unit";"Baneling";"Zergling";359;0
"Unit";"Baneling";"Zergling";359;0
"Unit";"Baneling";"Zergling";359;0
"Unit";"Baneling";"Zergling";359;0
"Unit";"Baneling";"Zergling";359;0
"Unit";"Zergling";"Larva";359;1
"Unit";"Zergling";"Larva";359;1
"Unit";"Zergling";"Larva";359;1
"Unit";"Zergling";"Larva";359;1
"Unit";"Zergling";"Larva";359;1
"Unit";"Zergling";"Larva";359;1
"Unit";"Zergling";"Larva";359;1
"Unit";"Zergling";"Larva";359;1
"Unit";"Zergling";"Larva";359;1
"Unit";"Zergling";"Larva";359;1
"Unit";"Zergling";"Larva";359;1
"Unit";"Zergling";"Larva";359;1
"Unit";"Zergling";"Larva";359;1
"Unit";"Zergling";"Larva";359;1
"Unit";"Zergling";"Larva";359;1
"Unit";"Zergling";"Larva";359;1
"Unit";"Zergling";"Larva";359;1
"Unit";"Zergling";"Larva";359;1
"Unit";"Zergling";"Larva";359;1
"Unit";"Zergling";"Larva";359;1
"Unit";"Zergling";"Larva";359;1
"Unit";"Zergling";"Larva";359;1
"Unit";"Zergling";"Larva";359;1
"Unit";"Zergling";"Larva";359;1
"Unit";"Zergling";"Larva";359;1
"Unit";"Zergling";"Larva";359;1
"Unit";"Zergling";"Larva";359;1
"Unit";"Zergling";"Larva";359;1
"Unit";"Zergling";"Larva";359;1
"Unit";"Zergling";"Larva";359;1
"Unit";"Zergling";"Larva";359;1
"Unit";"Zergling";"Larva";359;1
"Building";"CreepTumorQueen";NA;383;0
"Unit";"Zergling";"Larva";383;1
"Unit";"Zergling";"Larva";383;1
"Unit";"Zergling";"Larva";383;1
"Unit";"Zergling";"Larva";383;1
"Unit";"Zergling";"Larva";383;1
"Unit";"Zergling";"Larva";383;1
"Unit";"Zergling";"Larva";383;1
"Unit";"Zergling";"Larva";383;1
"Building";"CreepTumorQueen";NA;391;0
"Unit";"Baneling";"Zergling";383;0
"Unit";"Baneling";"Zergling";383;0
"Building";"CreepTumorQueen";NA;391;0
"Building";"CreepTumorQueen";NA;391;0
"Upgrade";"ZergGroundArmorsLevel2";"EvolutionChamber";281;0
"Upgrade";"ZergMeleeWeaponsLevel2";"EvolutionChamber";281;0
"Unit";"Zergling";"Larva";399;1
"Unit";"Zergling";"Larva";399;1
"Unit";"Zergling";"Larva";399;1
"Unit";"Zergling";"Larva";399;1
"Unit";"Zergling";"Larva";399;1
"Unit";"Zergling";"Larva";399;1
"Unit";"Zergling";"Larva";399;1
"Unit";"Zergling";"Larva";399;1
"Unit";"Zergling";"Larva";399;1
"Unit";"Zergling";"Larva";399;1
"Unit";"Zergling";"Larva";399;1
"Unit";"Zergling";"Larva";399;1
"Unit";"Zergling";"Larva";399;1
"Unit";"Zergling";"Larva";399;1
"Unit";"Zergling";"Larva";399;1
"Unit";"Zergling";"Larva";399;1
"Building";"CreepTumorQueen";NA;399;0
"Building";"CreepTumorQueen";NA;399;0
"Building";"CreepTumorQueen";NA;399;0
"Building";"CreepTumorQueen";NA;399;0
"Unit";"Zergling";"Larva";399;1
"Unit";"Zergling";"Larva";399;1
"Building";"CreepTumorQueen";NA;415;0
"Unit";"Zergling";"Larva";399;1
"Unit";"Zergling";"Larva";399;1
"Unit";"Zergling";"Larva";399;1
"Unit";"Zergling";"Larva";399;1
"Unit";"Zergling";"Larva";399;1
"Unit";"Zergling";"Larva";399;1
"Unit";"Zergling";"Larva";399;1
"Unit";"Zergling";"Larva";399;1
"Unit";"Zergling";"Larva";399;1
"Unit";"Zergling";"Larva";399;1
"Building";"CreepTumor";NA;415;0
"Building";"CreepTumor";NA;415;0
"Building";"CreepTumor";NA;415;0
"Unit";"Zergling";"Larva";415;1
"Unit";"Zergling";"Larva";415;1
"Unit";"Zergling";"Larva";415;1
"Unit";"Zergling";"Larva";415;1
"Unit";"Zergling";"Larva";415;1
"Unit";"Zergling";"Larva";415;1
"Building";"CreepTumorQueen";NA;415;0
"Unit";"Overlord";"Larva";415;0
"Building";"CreepTumor";NA;433;0
"Building";"CreepTumor";NA;433;0
"Building";"CreepTumor";NA;433;0
"Building";"CreepTumor";NA;433;0
"Building";"CreepTumorQueen";NA;433;0
"Unit";"Zergling";"Larva";427;1
"Unit";"Zergling";"Larva";427;1
"Unit";"Zergling";"Larva";427;1
"Unit";"Zergling";"Larva";427;1
"Unit";"Zergling";"Larva";427;1
"Unit";"Zergling";"Larva";427;1
"Unit";"Zergling";"Larva";427;1
"Unit";"Zergling";"Larva";427;1
"Unit";"Zergling";"Larva";427;1
"Unit";"Zergling";"Larva";427;1
"Unit";"Zergling";"Larva";427;1
"Unit";"Zergling";"Larva";427;1
"Unit";"Zergling";"Larva";427;1
"Unit";"Zergling";"Larva";427;1
"Unit";"Zergling";"Larva";427;1
"Unit";"Zergling";"Larva";427;1
"Unit";"Zergling";"Larva";427;1
"Unit";"Zergling";"Larva";427;1
"Building";"CreepTumorQueen";NA;433;0
"Building";"InfestationPit";NA;415;0
"Building";"CreepTumorQueen";NA;433;0
"Building";"SporeCrawler";NA;427;0
"Building";"CreepTumor";NA;433;0
"Building";"CreepTumor";NA;433;0
"Unit";"Queen";"Hatchery";415;2
"Unit";"Queen";"Hatchery";415;2
"Building";"CreepTumor";NA;451;0
"Building";"CreepTumorQueen";NA;451;0
"Building";"CreepTumorQueen";NA;451;0
"Building";"CreepTumorQueen";NA;458;0
"Unit";"Zergling";"Larva";458;1
"Unit";"Zergling";"Larva";458;1
"Unit";"Zergling";"Larva";458;1
"Unit";"Zergling";"Larva";458;1
"Unit";"Zergling";"Larva";458;1
"Unit";"Zergling";"Larva";458;1
"Unit";"Zergling";"Larva";458;1
"Unit";"Zergling";"Larva";458;1
"Unit";"Zergling";"Larva";458;1
"Unit";"Zergling";"Larva";458;1
"Unit";"Zergling";"Larva";458;1
"Unit";"Zergling";"Larva";458;1
"Unit";"Zergling";"Larva";458;1
"Unit";"Zergling";"Larva";458;1
"Unit";"Zergling";"Larva";458;1
"Unit";"Zergling";"Larva";458;1
"Unit";"Baneling";"Zergling";458;0
"Unit";"Baneling";"Zergling";458;0
"Unit";"Baneling";"Zergling";458;0
"Unit";"Baneling";"Zergling";458;0
"Unit";"Overlord";"Larva";458;0
"Unit";"Overlord";"Larva";458;0
"Unit";"Overlord";"Larva";458;0
"Unit";"Overlord";"Larva";458;0
"Building";"CreepTumor";NA;458;0
"Building";"CreepTumor";NA;458;0
"Building";"CreepTumor";NA;458;0
"Building";"CreepTumor";NA;458;0
"Building";"CreepTumorQueen";NA;458;0
"Building";"Hatchery";NA;415;0
"Building";"CreepTumor";NA;474;0
"Building";"CreepTumor";NA;474;0
"Building";"CreepTumorQueen";NA;474;0
"Building";"CreepTumor";NA;474;0
"Building";"CreepTumor";NA;474;0
"Building";"CreepTumor";NA;474;0
"Building";"HydraliskDen";NA;474;0
"Building";"CreepTumor";NA;483;0
"Building";"Extractor";NA;474;0
"Building";"Extractor";NA;483;0
"Unit";"Queen";"Hatchery";474;2
"Unit";"Overlord";"Larva";489;0
"Building";"CreepTumorQueen";NA;491;0
"Building";"CreepTumor";NA;491;0
"Building";"CreepTumor";NA;493;0
"Building";"CreepTumor";NA;493;0
"Building";"CreepTumor";NA;493;0
"Building";"CreepTumor";NA;493;0
"Building";"CreepTumor";NA;493;0
"Building";"CreepTumor";NA;493;0
"Building";"CreepTumor";NA;493;0
"Unit";"Hydralisk";"Larva";491;2
"Unit";"Hydralisk";"Larva";491;2
"Unit";"Hydralisk";"Larva";491;2
"Unit";"Zergling";"Larva";499;1
"Unit";"Zergling";"Larva";499;1
"Unit";"Zergling";"Larva";499;1
"Unit";"Zergling";"Larva";499;1
"Unit";"Zergling";"Larva";499;1
"Unit";"Zergling";"Larva";499;1
"Unit";"Zergling";"Larva";499;1
"Unit";"Zergling";"Larva";499;1
"Unit";"Zergling";"Larva";499;1
"Unit";"Zergling";"Larva";499;1
"Unit";"Zergling";"Larva";499;1
"Unit";"Zergling";"Larva";499;1
"Unit";"Zergling";"Larva";499;1
"Unit";"Zergling";"Larva";499;1
"Unit";"Zergling";"Larva";499;1
"Unit";"Zergling";"Larva";499;1
"Unit";"Zergling";"Larva";499;1
"Unit";"Zergling";"Larva";499;1
"Unit";"Zergling";"Larva";499;1
"Unit";"Zergling";"Larva";499;1
"Unit";"Zergling";"Larva";499;1
"Unit";"Zergling";"Larva";499;1
"Unit";"Zergling";"Larva";499;1
"Unit";"Zergling";"Larva";499;1
"Unit";"Zergling";"Larva";499;1
"Unit";"Zergling";"Larva";499;1
"Unit";"Zergling";"Larva";499;1
"Unit";"Zergling";"Larva";499;1
"Unit";"Zergling";"Larva";499;1
"Unit";"Zergling";"Larva";499;1
"Unit";"Zergling";"Larva";499;1
"Unit";"Zergling";"Larva";499;1
"Unit";"Zergling";"Larva";499;1
"Unit";"Zergling";"Larva";499;1
"Unit";"Baneling";"Zergling";499;0
"Unit";"Baneling";"Zergling";499;0
"Unit";"Baneling";"Zergling";499;0
"Unit";"Baneling";"Zergling";499;0
"Unit";"Baneling";"Zergling";499;0
"Unit";"Baneling";"Zergling";499;0
"Unit";"Viper";"Larva";499;3
"Unit";"Viper";"Larva";499;3
"Unit";"Viper";"Larva";499;3
"Unit";"Viper";"Larva";499;3
"Upgrade";"EvolveGroovedSpines";"HydraliskDen";493;0
"Unit";"Overlord";"Larva";546;0
"Building";"CreepTumor";NA;546;0
"Unit";"Baneling";"Zergling";546;0
"Unit";"Baneling";"Zergling";546;0
"Unit";"Baneling";"Zergling";546;0
"Unit";"Baneling";"Zergling";546;0
"Unit";"Baneling";"Zergling";546;0
"Unit";"Baneling";"Zergling";546;0
"Unit";"Baneling";"Zergling";546;0
"Building";"CreepTumor";NA;546;0
"Building";"CreepTumor";NA;546;0
"Unit";"Overlord";"Larva";546;0
"Unit";"Hydralisk";"Larva";546;2
"Unit";"Hydralisk";"Larva";546;2
"Unit";"Hydralisk";"Larva";546;2
"Unit";"Hydralisk";"Larva";546;2
"Building";"CreepTumor";NA;554;0
"Building";"CreepTumor";NA;554;0
"Upgrade";"EvolveMuscularAugments";"HydraliskDen";546;0
"Building";"Hatchery";NA;546;0
"Building";"CreepTumor";NA;554;0
"Building";"CreepTumorQueen";NA;554;0
"Building";"CreepTumor";NA;554;0
"Building";"CreepTumorQueen";NA;554;0
"Building";"CreepTumorQueen";NA;554;0
"Building";"CreepTumorQueen";NA;554;0
"Building";"CreepTumorQueen";NA;554;0
"Building";"CreepTumorQueen";NA;554;0
"Building";"CreepTumorQueen";NA;554;0
"Unit";"Zergling";"Larva";554;1
"Unit";"Zergling";"Larva";554;1
"Unit";"Zergling";"Larva";554;1
"Unit";"Zergling";"Larva";554;1
"Unit";"Zergling";"Larva";554;1
"Unit";"Zergling";"Larva";554;1
"Unit";"Zergling";"Larva";554;1
"Unit";"Zergling";"Larva";554;1
"Unit";"Zergling";"Larva";554;1
"Unit";"Zergling";"Larva";554;1
"Unit";"Zergling";"Larva";554;1
"Unit";"Zergling";"Larva";554;1
"Unit";"Zergling";"Larva";554;1
"Unit";"Zergling";"Larva";554;1
"Unit";"Zergling";"Larva";554;1
"Unit";"Zergling";"Larva";554;1
"Unit";"Zergling";"Larva";554;1
"Unit";"Zergling";"Larva";554;1
"Unit";"Zergling";"Larva";554;1
"Unit";"Zergling";"Larva";554;1
"Unit";"Zergling";"Larva";554;1
"Unit";"Zergling";"Larva";554;1
"Unit";"Zergling";"Larva";554;1
"Unit";"Zergling";"Larva";554;1
"Unit";"Zergling";"Larva";554;1
"Unit";"Zergling";"Larva";554;1
"Unit";"Zergling";"Larva";554;1
"Unit";"Zergling";"Larva";554;1
"Unit";"Zergling";"Larva";554;1
"Unit";"Zergling";"Larva";554;1
"Unit";"Zergling";"Larva";554;1
"Unit";"Zergling";"Larva";554;1
"Building";"Extractor";NA;554;0
"Building";"Extractor";NA;554;0
"Building";"CreepTumor";NA;554;0
"Building";"CreepTumor";NA;554;0
"Building";"Hatchery";NA;554;0
"Building";"Spire";NA;554;0
"Building";"CreepTumor";NA;586;0
"Building";"CreepTumor";NA;586;0
"Unit";"Overlord";"Larva";586;0
"Building";"CreepTumorQueen";NA;586;0
"Building";"CreepTumorQueen";NA;586;0
"Building";"CreepTumor";NA;586;0
"Building";"CreepTumor";NA;586;0
"Unit";"Hydralisk";"Larva";586;2
"Unit";"Hydralisk";"Larva";586;2
"Unit";"Hydralisk";"Larva";586;2
"Unit";"Hydralisk";"Larva";586;2
"Unit";"Hydralisk";"Larva";586;2
"Unit";"Hydralisk";"Larva";586;2
"Unit";"Hydralisk";"Larva";586;2
"Unit";"Hydralisk";"Larva";586;2
"Unit";"Hydralisk";"Larva";586;2
"Unit";"Hydralisk";"Larva";586;2
"Building";"CreepTumor";NA;586;0
"Building";"CreepTumor";NA;586;0
"Building";"CreepTumor";NA;586;0
"Building";"CreepTumor";NA;586;0
"Building";"CreepTumor";NA;586;0
"Building";"CreepTumor";NA;586;0
"Building";"CreepTumor";NA;586;0
"Building";"CreepTumor";NA;606;0
"Building";"CreepTumor";NA;606;0
"Building";"CreepTumorQueen";NA;606;0
"Unit";"Corruptor";"Larva";586;2
"Unit";"Corruptor";"Larva";586;2
"Unit";"Corruptor";"Larva";586;2
"Building";"CreepTumor";NA;606;0
"Building";"CreepTumorQueen";NA;606;0
"Building";"CreepTumorQueen";NA;606;0
"Building";"CreepTumor";NA;606;0
"Building";"CreepTumorQueen";NA;606;0
"Building";"CreepTumor";NA;606;0
"Building";"CreepTumor";NA;606;0
"Unit";"Corruptor";"Larva";612;2
"Unit";"Corruptor";"Larva";612;2
"Unit";"Corruptor";"Larva";612;2
"Unit";"Corruptor";"Larva";612;2
"Building";"CreepTumor";NA;618;0
"Building";"CreepTumor";NA;618;0
"Building";"CreepTumor";NA;618;0
"Building";"CreepTumor";NA;618;0
"Building";"CreepTumor";NA;618;0
"Unit";"Corruptor";"Larva";612;2
"Unit";"Corruptor";"Larva";612;2
"Unit";"Corruptor";"Larva";612;2
"Building";"CreepTumor";NA;618;0
"Building";"CreepTumor";NA;618;0
"Building";"CreepTumor";NA;618;0
"Building";"CreepTumor";NA;618;0
"Building";"CreepTumor";NA;618;0
"Building";"CreepTumor";NA;618;0
"Building";"CreepTumor";NA;618;0
"Building";"CreepTumor";NA;618;0
"Building";"CreepTumor";NA;618;0
"Building";"CreepTumor";NA;618;0
"Building";"CreepTumor";NA;626;0
"Building";"CreepTumor";NA;626;0
"Upgrade";"ZergGroundArmorsLevel3";"EvolutionChamber";554;0
"Upgrade";"ZergMeleeWeaponsLevel3";"EvolutionChamber";554;0
"Building";"CreepTumor";NA;632;0
"Building";"CreepTumor";NA;632;0
"Building";"CreepTumor";NA;632;0
"Building";"CreepTumor";NA;632;0
"Building";"CreepTumor";NA;632;0
"Building";"CreepTumor";NA;632;0
"Building";"CreepTumor";NA;632;0
"Building";"CreepTumor";NA;632;0
"Building";"CreepTumor";NA;632;0
"Building";"CreepTumor";NA;632;0
"Building";"CreepTumor";NA;632;0
"Building";"CreepTumor";NA;632;0
"Building";"CreepTumorQueen";NA;632;0
"Building";"CreepTumorQueen";NA;632;0
"Building";"Hatchery";NA;618;0
"Building";"CreepTumor";NA;632;0
"Building";"CreepTumor";NA;632;0
"Building";"CreepTumor";NA;632;0
"Building";"CreepTumor";NA;632;0
"Building";"CreepTumor";NA;632;0
"Building";"CreepTumor";NA;632;0
"Building";"CreepTumor";NA;632;0
"Building";"CreepTumor";NA;632;0
"Building";"CreepTumor";NA;632;0
"Building";"CreepTumor";NA;632;0
"Building";"CreepTumor";NA;632;0
"Building";"CreepTumor";NA;632;0
"Building";"CreepTumor";NA;632;0
"Building";"CreepTumor";NA;632;0
"Building";"CreepTumor";NA;632;0
"Building";"CreepTumor";NA;632;0
"Building";"CreepTumor";NA;632;0
"Building";"CreepTumor";NA;632;0
"Building";"CreepTumor";NA;632;0
"Building";"CreepTumor";NA;632;0
"Building";"CreepTumor";NA;632;0
"Building";"CreepTumor";NA;632;0
"Building";"CreepTumor";NA;632;0
"Building";"CreepTumor";NA;632;0
"Building";"CreepTumor";NA;632;0
"Building";"UltraliskCavern";NA;632;0
"Upgrade";"ZergMissileWeaponsLevel1";"EvolutionChamber";632;0
"Building";"CreepTumor";NA;632;0
"Building";"CreepTumor";NA;632;0
"Building";"CreepTumor";NA;632;0
"Unit";"Corruptor";"Larva";632;2
"Building";"CreepTumor";NA;632;0
"Unit";"Corruptor";"Larva";632;2
"Unit";"Corruptor";"Larva";632;2
"Unit";"Corruptor";"Larva";632;2
"Unit";"Corruptor";"Larva";632;2
"Unit";"Corruptor";"Larva";632;2
"Building";"CreepTumor";NA;635;0
"Building";"CreepTumor";NA;637;0
"Building";"CreepTumor";NA;645;0
"Building";"CreepTumor";NA;647;0
"Building";"CreepTumor";NA;647;0
"Building";"CreepTumor";NA;647;0
"Building";"CreepTumor";NA;647;0
"Unit";"Zergling";"Larva";647;1
"Unit";"Zergling";"Larva";647;1
"Unit";"Zergling";"Larva";647;1
"Unit";"Zergling";"Larva";647;1
"Unit";"Zergling";"Larva";647;1
"Unit";"Zergling";"Larva";647;1
"Unit";"Zergling";"Larva";647;1
"Unit";"Zergling";"Larva";647;1
"Unit";"Zergling";"Larva";647;1
"Unit";"Zergling";"Larva";647;1
"Unit";"Zergling";"Larva";647;1
"Unit";"Zergling";"Larva";647;1
"Unit";"Zergling";"Larva";647;1
"Unit";"Zergling";"Larva";647;1
"Unit";"Zergling";"Larva";647;1
"Unit";"Zergling";"Larva";647;1
"Unit";"Zergling";"Larva";647;1
"Unit";"Zergling";"Larva";647;1
"Unit";"Zergling";"Larva";647;1
"Unit";"Zergling";"Larva";647;1
"Unit";"Zergling";"Larva";647;1
"Unit";"Zergling";"Larva";647;1
"Unit";"Zergling";"Larva";647;1
"Unit";"Zergling";"Larva";647;1
"Unit";"Zergling";"Larva";647;1
"Unit";"Zergling";"Larva";647;1
"Unit";"Zergling";"Larva";647;1
"Unit";"Zergling";"Larva";647;1
"Unit";"Zergling";"Larva";647;1
"Unit";"Zergling";"Larva";647;1
"Unit";"Zergling";"Larva";647;1
"Unit";"Zergling";"Larva";647;1
"Unit";"Zergling";"Larva";647;1
"Unit";"Zergling";"Larva";647;1
"Unit";"Zergling";"Larva";647;1
"Unit";"Zergling";"Larva";647;1
"Unit";"Zergling";"Larva";647;1
"Unit";"Zergling";"Larva";647;1
"Unit";"Zergling";"Larva";647;1
"Unit";"Zergling";"Larva";647;1
"Unit";"Zergling";"Larva";647;1
"Unit";"Zergling";"Larva";647;1
"Unit";"Zergling";"Larva";647;1
"Unit";"Zergling";"Larva";647;1
"Unit";"Zergling";"Larva";647;1
"Unit";"Zergling";"Larva";647;1
"Unit";"Zergling";"Larva";647;1
"Unit";"Zergling";"Larva";647;1
"Unit";"Zergling";"Larva";647;1
"Unit";"Zergling";"Larva";647;1
"Unit";"Zergling";"Larva";647;1
"Unit";"Zergling";"Larva";647;1
"Unit";"Zergling";"Larva";647;1
"Unit";"Zergling";"Larva";647;1
"Unit";"Zergling";"Larva";647;1
"Unit";"Zergling";"Larva";647;1
"Unit";"Zergling";"Larva";647;1
"Unit";"Zergling";"Larva";647;1
"Unit";"Zergling";"Larva";647;1
"Unit";"Zergling";"Larva";647;1
"Upgrade";"ChitinousPlating";"UltraliskCavern";635;0
"Building";"CreepTumor";NA;683;0
"Unit";"Corruptor";"Larva";647;2
"Unit";"Corruptor";"Larva";647;2
"Unit";"Corruptor";"Larva";647;2
"Unit";"Corruptor";"Larva";647;2
"Unit";"Corruptor";"Larva";647;2
"Unit";"Corruptor";"Larva";647;2
"Unit";"Corruptor";"Larva";647;2
"Building";"CreepTumor";NA;683;0
"Unit";"Baneling";"Zergling";683;0
"Building";"CreepTumor";NA;683;0
"Unit";"Baneling";"Zergling";683;0
"Unit";"Baneling";"Zergling";683;0
"Unit";"Baneling";"Zergling";683;0
"Building";"CreepTumor";NA;683;0
"Unit";"Baneling";"Zergling";683;0
"Unit";"Baneling";"Zergling";683;0
"Unit";"Baneling";"Zergling";683;0
"Unit";"Baneling";"Zergling";683;0
"Unit";"Baneling";"Zergling";683;0
"Unit";"Baneling";"Zergling";683;0
"Unit";"Baneling";"Zergling";683;0
"Building";"CreepTumor";NA;683;0
"Building";"CreepTumor";NA;707;0
"Building";"CreepTumor";NA;707;0
"Building";"CreepTumor";NA;707;0
"Building";"CreepTumor";NA;707;0
"Building";"CreepTumor";NA;707;0
"Building";"CreepTumor";NA;721;0
"Building";"CreepTumor";NA;721;0
"Building";"CreepTumor";NA;721;0
"Building";"CreepTumor";NA;721;0
"Building";"CreepTumor";NA;721;0
"Building";"CreepTumor";NA;721;0
"Building";"CreepTumor";NA;721;0
"Unit";"Zergling";"Larva";721;1
"Unit";"Zergling";"Larva";721;1
"Unit";"Zergling";"Larva";721;1
"Unit";"Zergling";"Larva";721;1
"Unit";"Zergling";"Larva";721;1
"Unit";"Zergling";"Larva";721;1
"Unit";"Zergling";"Larva";721;1
"Unit";"Zergling";"Larva";721;1
"Building";"CreepTumor";NA;729;0
