"type";"unit_name";"on_building";"total_supply";"supply"
"Unit";"Overlord";"Larva";13;0
"Building";"SpawningPool";NA;19;0
"Building";"Hatchery";NA;15;0
"Building";"Extractor";NA;23;0
"Unit";"Zergling";"Larva";24;1
"Unit";"Zergling";"Larva";24;1
"Unit";"Zergling";"Larva";24;1
"Unit";"Zergling";"Larva";24;1
"Unit";"Queen";"Hatchery";24;2
"Unit";"Overlord";"Larva";24;0
"Unit";"Queen";"Hatchery";24;2
"Building";"Hatchery";NA;22;0
"Unit";"Overlord";"Larva";29;0
"Unit";"Queen";"Hatchery";35;2
"Unit";"Overlord";"Larva";48;0
"Unit";"Overlord";"Larva";51;0
"Building";"CreepTumorQueen";NA;51;0
"Unit";"Queen";"Hatchery";51;2
"Unit";"Queen";"Hatchery";51;2
"Building";"CreepTumorQueen";NA;56;0
"Building";"CreepTumorQueen";NA;56;0
"Unit";"Overlord";"Larva";52;0
"Building";"CreepTumorQueen";NA;62;0
"Unit";"Queen";"Hatchery";51;2
"Unit";"Zergling";"Larva";62;1
"Unit";"Zergling";"Larva";62;1
"Unit";"Zergling";"Larva";62;1
"Unit";"Zergling";"Larva";62;1
"Unit";"Zergling";"Larva";62;1
"Unit";"Zergling";"Larva";62;1
"Building";"SporeCrawler";NA;67;0
"Building";"SporeCrawler";NA;67;0
"Building";"CreepTumor";NA;75;0
"Building";"CreepTumor";NA;75;0
"Building";"CreepTumor";NA;75;0
"Building";"CreepTumor";NA;75;0
"Building";"CreepTumorQueen";NA;79;0
"Building";"CreepTumorQueen";NA;79;0
"Building";"SporeCrawler";NA;75;0
"Building";"CreepTumorQueen";NA;79;0
"Building";"CreepTumorQueen";NA;79;0
"Unit";"Zergling";"Larva";79;1
"Unit";"Zergling";"Larva";79;1
"Unit";"Overlord";"Larva";79;0
"Unit";"Zergling";"Larva";79;1
"Unit";"Zergling";"Larva";79;1
"Unit";"Zergling";"Larva";79;1
"Unit";"Zergling";"Larva";79;1
"Unit";"Zergling";"Larva";79;1
"Unit";"Zergling";"Larva";79;1
"Unit";"Zergling";"Larva";79;1
"Unit";"Zergling";"Larva";79;1
"Unit";"Queen";"Hatchery";67;2
"Building";"CreepTumorQueen";NA;79;0
"Unit";"Overlord";"Larva";79;0
"Unit";"Overlord";"Larva";79;0
"Building";"Extractor";NA;79;0
"Unit";"Zergling";"Larva";91;1
"Unit";"Zergling";"Larva";91;1
"Unit";"Zergling";"Larva";91;1
"Unit";"Zergling";"Larva";91;1
"Unit";"Zergling";"Larva";91;1
"Unit";"Zergling";"Larva";91;1
"Unit";"Zergling";"Larva";91;1
"Unit";"Zergling";"Larva";91;1
"Unit";"Zergling";"Larva";91;1
"Unit";"Zergling";"Larva";91;1
"Unit";"Zergling";"Larva";91;1
"Unit";"Zergling";"Larva";91;1
"Building";"CreepTumor";NA;103;0
"Building";"CreepTumor";NA;103;0
"Building";"CreepTumor";NA;103;0
"Building";"CreepTumor";NA;103;0
"Building";"CreepTumorQueen";NA;103;0
"Building";"CreepTumor";NA;103;0
"Building";"CreepTumorQueen";NA;103;0
"Building";"Extractor";NA;103;0
"Building";"Extractor";NA;106;0
"Unit";"Queen";"Hatchery";103;2
"Building";"HydraliskDen";NA;103;0
"Building";"EvolutionChamber";NA;106;0
"Building";"CreepTumor";NA;119;0
"Building";"CreepTumor";NA;119;0
"Building";"CreepTumor";NA;119;0
"Building";"CreepTumor";NA;119;0
"Unit";"Queen";"Hatchery";106;2
"Building";"CreepTumor";NA;119;0
"Building";"CreepTumor";NA;119;0
"Building";"CreepTumor";NA;119;0
"Building";"CreepTumor";NA;121;0
"Building";"CreepTumor";NA;121;0
"Building";"CreepTumor";NA;121;0
"Building";"Hatchery";NA;91;0
"Building";"CreepTumorQueen";NA;131;0
"Building";"Extractor";NA;131;0
"Building";"Extractor";NA;131;0
"Building";"CreepTumorQueen";NA;131;0
"Building";"CreepTumorQueen";NA;131;0
"Building";"CreepTumor";NA;131;0
"Building";"CreepTumor";NA;131;0
"Building";"EvolutionChamber";NA;131;0
"Building";"Hatchery";NA;103;0
"Building";"CreepTumorQueen";NA;131;0
"Building";"CreepTumorQueen";NA;131;0
"Building";"CreepTumor";NA;134;0
"Building";"CreepTumor";NA;131;0
"Building";"SporeCrawler";NA;131;0
"Building";"CreepTumor";NA;140;0
"Building";"CreepTumor";NA;140;0
"Building";"CreepTumor";NA;140;0
"Building";"CreepTumor";NA;140;0
"Unit";"Zergling";"Larva";140;1
"Unit";"Zergling";"Larva";140;1
"Unit";"Zergling";"Larva";140;1
"Unit";"Zergling";"Larva";140;1
"Unit";"Zergling";"Larva";140;1
"Unit";"Zergling";"Larva";140;1
"Unit";"Zergling";"Larva";140;1
"Unit";"Zergling";"Larva";140;1
"Unit";"Zergling";"Larva";140;1
"Unit";"Zergling";"Larva";140;1
"Building";"CreepTumor";NA;144;0
"Building";"BanelingNest";NA;131;0
"Upgrade";"EvolveGroovedSpines";"HydraliskDen";131;0
"Building";"CreepTumor";NA;159;0
"Unit";"Queen";"Hatchery";140;2
"Building";"CreepTumor";NA;159;0
"Building";"CreepTumor";NA;159;0
"Building";"CreepTumor";NA;159;0
"Unit";"Zergling";"Larva";159;1
"Unit";"Zergling";"Larva";159;1
"Unit";"Zergling";"Larva";159;1
"Unit";"Zergling";"Larva";159;1
"Building";"CreepTumor";NA;159;0
"Unit";"Overlord";"Larva";159;0
"Unit";"Overlord";"Larva";159;0
"Unit";"Overlord";"Larva";159;0
"Unit";"Overlord";"Larva";159;0
"Building";"CreepTumor";NA;159;0
"Building";"CreepTumor";NA;161;0
"Building";"InfestationPit";NA;149;0
"Unit";"Zergling";"Larva";165;1
"Unit";"Zergling";"Larva";165;1
"Unit";"Zergling";"Larva";165;1
"Unit";"Zergling";"Larva";165;1
"Unit";"Zergling";"Larva";165;1
"Unit";"Zergling";"Larva";165;1
"Unit";"Zergling";"Larva";165;1
"Unit";"Zergling";"Larva";165;1
"Unit";"Zergling";"Larva";165;1
"Unit";"Zergling";"Larva";165;1
"Unit";"Zergling";"Larva";165;1
"Unit";"Zergling";"Larva";165;1
"Unit";"Zergling";"Larva";165;1
"Unit";"Zergling";"Larva";165;1
"Unit";"Zergling";"Larva";165;1
"Unit";"Zergling";"Larva";165;1
"Unit";"Zergling";"Larva";165;1
"Unit";"Zergling";"Larva";165;1
"Unit";"Zergling";"Larva";165;1
"Unit";"Zergling";"Larva";165;1
"Unit";"Zergling";"Larva";165;1
"Unit";"Zergling";"Larva";165;1
"Unit";"Zergling";"Larva";165;1
"Unit";"Zergling";"Larva";165;1
"Unit";"Baneling";"Zergling";165;0
"Unit";"Baneling";"Zergling";165;0
"Unit";"Baneling";"Zergling";165;0
"Unit";"Baneling";"Zergling";165;0
"Unit";"Baneling";"Zergling";165;0
"Unit";"Baneling";"Zergling";165;0
"Unit";"Hydralisk";"Larva";165;2
"Unit";"Hydralisk";"Larva";165;2
"Unit";"Hydralisk";"Larva";165;2
"Unit";"Hydralisk";"Larva";165;2
"Unit";"Hydralisk";"Larva";165;2
"Unit";"Hydralisk";"Larva";165;2
"Unit";"Hydralisk";"Larva";165;2
"Unit";"Hydralisk";"Larva";165;2
"Unit";"Hydralisk";"Larva";165;2
"Building";"CreepTumorQueen";NA;189;0
"Upgrade";"ZergGroundArmorsLevel1";"EvolutionChamber";140;0
"Building";"Extractor";NA;165;0
"Building";"Extractor";NA;165;0
"Building";"CreepTumorQueen";NA;189;0
"Building";"SporeCrawler";NA;189;0
"Building";"CreepTumor";NA;207;0
"Building";"SporeCrawler";NA;189;0
"Building";"CreepTumor";NA;207;0
"Building";"CreepTumor";NA;207;0
"Building";"CreepTumor";NA;207;0
"Building";"SporeCrawler";NA;189;0
"Building";"CreepTumor";NA;207;0
"Building";"CreepTumor";NA;207;0
"Unit";"Overlord";"Larva";207;0
"Unit";"Overlord";"Larva";207;0
"Unit";"Overlord";"Larva";207;0
"Unit";"Overlord";"Larva";207;0
"Building";"CreepTumor";NA;207;0
"Building";"CreepTumor";NA;207;0
"Building";"CreepTumor";NA;207;0
"Upgrade";"EvolveMuscularAugments";"HydraliskDen";165;0
"Unit";"Overlord";"Larva";207;0
"Unit";"Overlord";"Larva";207;0
"Unit";"Overlord";"Larva";207;0
"Unit";"Overlord";"Larva";207;0
"Building";"CreepTumorQueen";NA;207;0
"Building";"CreepTumorQueen";NA;207;0
"Building";"CreepTumorQueen";NA;207;0
"Building";"CreepTumor";NA;207;0
"Building";"CreepTumor";NA;207;0
"Building";"CreepTumorQueen";NA;207;0
"Upgrade";"ZergMeleeWeaponsLevel1";"EvolutionChamber";165;0
"Building";"CreepTumorQueen";NA;207;0
"Building";"CreepTumorQueen";NA;207;0
"Building";"CreepTumorQueen";NA;207;0
"Building";"CreepTumorQueen";NA;207;0
"Unit";"Queen";"Hatchery";207;2
"Building";"CreepTumor";NA;207;0
"Building";"CreepTumor";NA;207;0
"Building";"CreepTumor";NA;215;0
"Building";"CreepTumor";NA;217;0
"Unit";"Zergling";"Larva";207;1
"Unit";"Zergling";"Larva";207;1
"Unit";"Zergling";"Larva";207;1
"Unit";"Zergling";"Larva";207;1
"Unit";"Zergling";"Larva";207;1
"Unit";"Zergling";"Larva";207;1
"Unit";"Zergling";"Larva";207;1
"Unit";"Zergling";"Larva";207;1
"Unit";"Zergling";"Larva";207;1
"Unit";"Zergling";"Larva";207;1
"Unit";"Zergling";"Larva";207;1
"Unit";"Zergling";"Larva";207;1
"Unit";"Zergling";"Larva";207;1
"Unit";"Zergling";"Larva";207;1
"Unit";"Zergling";"Larva";207;1
"Unit";"Zergling";"Larva";207;1
"Unit";"Zergling";"Larva";207;1
"Unit";"Zergling";"Larva";207;1
"Unit";"Zergling";"Larva";207;1
"Unit";"Zergling";"Larva";207;1
"Building";"Hatchery";NA;189;0
"Building";"CreepTumor";NA;217;0
"Building";"CreepTumor";NA;217;0
"Building";"CreepTumor";NA;217;0
"Building";"CreepTumor";NA;217;0
"Unit";"Hydralisk";"Larva";207;2
"Unit";"Hydralisk";"Larva";207;2
"Unit";"Hydralisk";"Larva";207;2
"Unit";"Hydralisk";"Larva";207;2
"Building";"CreepTumor";NA;245;0
"Building";"CreepTumor";NA;245;0
"Unit";"Zergling";"Larva";245;1
"Unit";"Zergling";"Larva";245;1
"Unit";"Zergling";"Larva";245;1
"Unit";"Zergling";"Larva";245;1
"Unit";"Zergling";"Larva";245;1
"Unit";"Zergling";"Larva";245;1
"Unit";"Zergling";"Larva";245;1
"Unit";"Zergling";"Larva";245;1
"Unit";"Zergling";"Larva";245;1
"Unit";"Zergling";"Larva";245;1
"Unit";"Zergling";"Larva";245;1
"Unit";"Zergling";"Larva";245;1
"Unit";"Zergling";"Larva";245;1
"Unit";"Zergling";"Larva";245;1
"Unit";"Zergling";"Larva";245;1
"Unit";"Zergling";"Larva";245;1
"Unit";"Zergling";"Larva";245;1
"Unit";"Zergling";"Larva";245;1
"Unit";"Zergling";"Larva";245;1
"Unit";"Zergling";"Larva";245;1
"Unit";"Zergling";"Larva";245;1
"Unit";"Zergling";"Larva";245;1
"Unit";"Zergling";"Larva";245;1
"Unit";"Zergling";"Larva";245;1
"Unit";"Zergling";"Larva";245;1
"Unit";"Zergling";"Larva";245;1
"Unit";"Zergling";"Larva";245;1
"Unit";"Zergling";"Larva";245;1
"Unit";"Zergling";"Larva";245;1
"Unit";"Zergling";"Larva";245;1
"Unit";"Zergling";"Larva";245;1
"Unit";"Zergling";"Larva";245;1
"Unit";"Zergling";"Larva";245;1
"Unit";"Zergling";"Larva";245;1
"Unit";"Zergling";"Larva";245;1
"Unit";"Zergling";"Larva";245;1
"Unit";"Baneling";"Zergling";245;0
"Unit";"Baneling";"Zergling";245;0
"Unit";"Baneling";"Zergling";245;0
"Unit";"Baneling";"Zergling";245;0
"Unit";"Baneling";"Zergling";245;0
"Unit";"Baneling";"Zergling";245;0
"Unit";"Baneling";"Zergling";245;0
"Unit";"Baneling";"Zergling";245;0
"Unit";"Baneling";"Zergling";245;0
"Unit";"Baneling";"Zergling";245;0
"Unit";"Baneling";"Zergling";245;0
"Unit";"Baneling";"Zergling";245;0
"Unit";"Baneling";"Zergling";245;0
"Unit";"Baneling";"Zergling";245;0
"Unit";"Baneling";"Zergling";245;0
"Unit";"Zergling";"Larva";245;1
"Unit";"Zergling";"Larva";245;1
"Unit";"Baneling";"Zergling";245;0
"Unit";"Baneling";"Zergling";245;0
"Unit";"Baneling";"Zergling";245;0
"Unit";"Baneling";"Zergling";245;0
"Unit";"Zergling";"Larva";245;1
"Unit";"Zergling";"Larva";245;1
"Unit";"Zergling";"Larva";245;1
"Unit";"Zergling";"Larva";245;1
"Unit";"Zergling";"Larva";245;1
"Unit";"Zergling";"Larva";245;1
"Unit";"Zergling";"Larva";245;1
"Unit";"Zergling";"Larva";245;1
"Unit";"Zergling";"Larva";245;1
"Unit";"Zergling";"Larva";245;1
"Unit";"Zergling";"Larva";245;1
"Unit";"Zergling";"Larva";245;1
"Unit";"Zergling";"Larva";245;1
"Unit";"Zergling";"Larva";245;1
"Unit";"Zergling";"Larva";245;1
"Unit";"Zergling";"Larva";245;1
"Building";"CreepTumor";NA;299;0
"Building";"CreepTumor";NA;299;0
"Unit";"Zergling";"Larva";299;1
"Unit";"Zergling";"Larva";299;1
"Unit";"Zergling";"Larva";299;1
"Unit";"Zergling";"Larva";299;1
"Unit";"Zergling";"Larva";299;1
"Unit";"Zergling";"Larva";299;1
"Unit";"Zergling";"Larva";299;1
"Unit";"Zergling";"Larva";299;1
"Unit";"Zergling";"Larva";299;1
"Unit";"Zergling";"Larva";299;1
"Unit";"Zergling";"Larva";299;1
"Unit";"Zergling";"Larva";299;1
"Unit";"Zergling";"Larva";299;1
"Unit";"Zergling";"Larva";299;1
"Unit";"Zergling";"Larva";299;1
"Unit";"Zergling";"Larva";299;1
"Unit";"Zergling";"Larva";299;1
"Unit";"Zergling";"Larva";299;1
"Unit";"Zergling";"Larva";299;1
"Unit";"Zergling";"Larva";299;1
"Unit";"Zergling";"Larva";299;1
"Unit";"Zergling";"Larva";299;1
"Unit";"Zergling";"Larva";299;1
"Unit";"Zergling";"Larva";299;1
"Unit";"Zergling";"Larva";299;1
"Unit";"Zergling";"Larva";299;1
"Unit";"Zergling";"Larva";299;1
"Unit";"Zergling";"Larva";299;1
"Unit";"Zergling";"Larva";299;1
"Unit";"Zergling";"Larva";299;1
"Unit";"Zergling";"Larva";299;1
"Unit";"Zergling";"Larva";299;1
"Unit";"Zergling";"Larva";299;1
"Unit";"Zergling";"Larva";299;1
"Unit";"Zergling";"Larva";299;1
"Unit";"Zergling";"Larva";299;1
"Building";"CreepTumor";NA;299;0
"Building";"CreepTumor";NA;299;0
"Building";"CreepTumorQueen";NA;299;0
"Building";"CreepTumorQueen";NA;299;0
"Building";"CreepTumorQueen";NA;299;0
"Building";"CreepTumor";NA;299;0
"Building";"CreepTumor";NA;299;0
"Building";"CreepTumorQueen";NA;299;0
"Unit";"Zergling";"Larva";299;1
"Unit";"Zergling";"Larva";299;1
"Unit";"Zergling";"Larva";299;1
"Unit";"Zergling";"Larva";299;1
"Unit";"Zergling";"Larva";299;1
"Unit";"Zergling";"Larva";299;1
"Unit";"Zergling";"Larva";299;1
"Unit";"Zergling";"Larva";299;1
"Unit";"Zergling";"Larva";299;1
"Unit";"Zergling";"Larva";299;1
"Unit";"Zergling";"Larva";299;1
"Unit";"Zergling";"Larva";299;1
"Unit";"Zergling";"Larva";299;1
"Unit";"Zergling";"Larva";299;1
"Unit";"Zergling";"Larva";299;1
"Unit";"Zergling";"Larva";299;1
"Unit";"Zergling";"Larva";299;1
"Unit";"Zergling";"Larva";299;1
"Unit";"Zergling";"Larva";299;1
"Unit";"Zergling";"Larva";299;1
"Unit";"Zergling";"Larva";299;1
"Unit";"Zergling";"Larva";299;1
"Unit";"Zergling";"Larva";299;1
"Unit";"Zergling";"Larva";299;1
"Building";"CreepTumor";NA;335;0
"Building";"CreepTumor";NA;335;0
"Building";"CreepTumor";NA;335;0
"Building";"CreepTumorQueen";NA;359;0
"Unit";"Queen";"Hatchery";299;2
"Building";"CreepTumorQueen";NA;359;0
"Building";"CreepTumorQueen";NA;359;0
"Building";"CreepTumorQueen";NA;359;0
"Building";"CreepTumor";NA;359;0
"Building";"CreepTumor";NA;359;0
"Building";"CreepTumor";NA;359;0
"Building";"CreepTumor";NA;359;0
"Building";"CreepTumor";NA;359;0
"Building";"CreepTumor";NA;359;0
"Building";"CreepTumor";NA;359;0
"Building";"CreepTumor";NA;359;0
"Building";"CreepTumor";NA;359;0
"Building";"Extractor";NA;359;0
"Upgrade";"ZergGroundArmorsLevel2";"EvolutionChamber";245;0
"Building";"Extractor";NA;359;0
"Building";"CreepTumor";NA;361;0
"Building";"CreepTumor";NA;361;0
"Building";"CreepTumor";NA;361;0
"Building";"CreepTumor";NA;361;0
"Building";"CreepTumor";NA;361;0
"Building";"CreepTumor";NA;361;0
"Unit";"Viper";"Larva";361;3
"Unit";"Viper";"Larva";361;3
"Unit";"Viper";"Larva";361;3
"Unit";"Viper";"Larva";361;3
"Upgrade";"ZergMeleeWeaponsLevel2";"EvolutionChamber";245;0
"Unit";"Overlord";"Larva";361;0
"Unit";"Overlord";"Larva";361;0
"Unit";"Zergling";"Larva";361;1
"Unit";"Zergling";"Larva";361;1
"Unit";"Overlord";"Larva";361;0
"Unit";"Overlord";"Larva";361;0
"Unit";"Zergling";"Larva";361;1
"Unit";"Zergling";"Larva";361;1
"Unit";"Overlord";"Larva";361;0
"Unit";"Zergling";"Larva";361;1
"Unit";"Zergling";"Larva";361;1
"Unit";"Zergling";"Larva";361;1
"Unit";"Zergling";"Larva";361;1
"Unit";"Zergling";"Larva";361;1
"Unit";"Zergling";"Larva";361;1
"Unit";"Zergling";"Larva";361;1
"Unit";"Zergling";"Larva";361;1
"Unit";"Zergling";"Larva";361;1
"Unit";"Zergling";"Larva";361;1
"Unit";"Overlord";"Larva";367;0
"Unit";"Overlord";"Larva";370;0
"Unit";"Overlord";"Larva";373;0
"Unit";"Overlord";"Larva";373;0
"Building";"UltraliskCavern";NA;361;0
"Building";"Hatchery";NA;359;0
"Building";"Hatchery";NA;359;0
"Unit";"Baneling";"Zergling";387;0
"Unit";"Baneling";"Zergling";387;0
"Unit";"Baneling";"Zergling";387;0
"Unit";"Baneling";"Zergling";387;0
"Unit";"Baneling";"Zergling";387;0
"Unit";"Baneling";"Zergling";387;0
"Unit";"Baneling";"Zergling";387;0
"Unit";"Baneling";"Zergling";387;0
"Unit";"Baneling";"Zergling";387;0
"Unit";"Baneling";"Zergling";387;0
"Unit";"Baneling";"Zergling";387;0
"Unit";"Baneling";"Zergling";387;0
"Unit";"Baneling";"Zergling";387;0
"Unit";"Baneling";"Zergling";387;0
"Unit";"Baneling";"Zergling";387;0
"Unit";"Baneling";"Zergling";387;0
"Unit";"Baneling";"Zergling";387;0
"Unit";"Baneling";"Zergling";387;0
"Unit";"Baneling";"Zergling";387;0
"Unit";"Baneling";"Zergling";387;0
"Unit";"Baneling";"Zergling";387;0
"Unit";"Baneling";"Zergling";387;0
"Unit";"Ultralisk";"Larva";387;6
"Unit";"Ultralisk";"Larva";387;6
"Unit";"Ultralisk";"Larva";387;6
"Unit";"Zergling";"Larva";387;1
"Unit";"Zergling";"Larva";387;1
"Unit";"Zergling";"Larva";387;1
"Unit";"Zergling";"Larva";387;1
"Unit";"Zergling";"Larva";387;1
"Unit";"Zergling";"Larva";387;1
"Unit";"Zergling";"Larva";387;1
"Unit";"Zergling";"Larva";387;1
"Unit";"Zergling";"Larva";387;1
"Unit";"Zergling";"Larva";387;1
"Unit";"Zergling";"Larva";387;1
"Unit";"Zergling";"Larva";387;1
"Unit";"Zergling";"Larva";387;1
"Unit";"Zergling";"Larva";387;1
"Unit";"Zergling";"Larva";387;1
"Unit";"Zergling";"Larva";387;1
"Unit";"Zergling";"Larva";387;1
"Unit";"Zergling";"Larva";387;1
"Unit";"Zergling";"Larva";387;1
"Unit";"Zergling";"Larva";387;1
"Unit";"Zergling";"Larva";387;1
"Unit";"Zergling";"Larva";387;1
"Building";"CreepTumorQueen";NA;405;0
"Building";"CreepTumor";NA;405;0
"Building";"CreepTumor";NA;405;0
"Building";"CreepTumor";NA;405;0
"Building";"CreepTumor";NA;405;0
"Building";"CreepTumor";NA;405;0
"Building";"CreepTumor";NA;405;0
"Building";"CreepTumor";NA;410;0
"Building";"CreepTumorQueen";NA;432;0
"Building";"CreepTumor";NA;432;0
"Building";"CreepTumor";NA;432;0
"Unit";"Zergling";"Larva";432;1
"Unit";"Zergling";"Larva";432;1
"Unit";"Zergling";"Larva";432;1
"Unit";"Zergling";"Larva";432;1
"Unit";"Zergling";"Larva";432;1
"Unit";"Zergling";"Larva";432;1
"Unit";"Zergling";"Larva";432;1
"Unit";"Zergling";"Larva";432;1
"Unit";"Zergling";"Larva";432;1
"Unit";"Zergling";"Larva";432;1
"Unit";"Zergling";"Larva";432;1
"Unit";"Zergling";"Larva";432;1
"Unit";"Zergling";"Larva";432;1
"Unit";"Zergling";"Larva";432;1
"Unit";"Zergling";"Larva";432;1
"Unit";"Zergling";"Larva";432;1
"Unit";"Zergling";"Larva";432;1
"Unit";"Zergling";"Larva";432;1
"Building";"CreepTumorQueen";NA;432;0
"Building";"CreepTumorQueen";NA;432;0
"Unit";"Ultralisk";"Larva";387;6
"Unit";"Ultralisk";"Larva";387;6
"Building";"CreepTumor";NA;432;0
"Building";"CreepTumor";NA;432;0
"Building";"CreepTumor";NA;432;0
"Building";"CreepTumorQueen";NA;432;0
"Building";"CreepTumorQueen";NA;450;0
"Unit";"Zergling";"Larva";455;1
"Unit";"Zergling";"Larva";455;1
"Unit";"Zergling";"Larva";455;1
"Unit";"Zergling";"Larva";455;1
"Unit";"Zergling";"Larva";455;1
"Unit";"Zergling";"Larva";455;1
"Unit";"Zergling";"Larva";455;1
"Unit";"Zergling";"Larva";455;1
"Unit";"Zergling";"Larva";455;1
"Unit";"Zergling";"Larva";455;1
"Unit";"Zergling";"Larva";455;1
"Unit";"Zergling";"Larva";455;1
"Unit";"Zergling";"Larva";455;1
"Unit";"Zergling";"Larva";455;1
"Unit";"Zergling";"Larva";455;1
"Unit";"Zergling";"Larva";455;1
"Unit";"Zergling";"Larva";455;1
"Unit";"Zergling";"Larva";455;1
"Unit";"Zergling";"Larva";455;1
"Unit";"Zergling";"Larva";455;1
"Building";"CreepTumor";NA;467;0
"Building";"CreepTumor";NA;467;0
"Building";"CreepTumor";NA;467;0
"Building";"CreepTumor";NA;467;0
"Building";"CreepTumorQueen";NA;487;0
"Building";"CreepTumorQueen";NA;487;0
"Upgrade";"ChitinousPlating";"UltraliskCavern";432;0
"Building";"CreepTumorQueen";NA;487;0
"Building";"CreepTumor";NA;487;0
"Building";"CreepTumor";NA;487;0
"Upgrade";"ZergGroundArmorsLevel3";"EvolutionChamber";387;0
"Upgrade";"ZergMeleeWeaponsLevel3";"EvolutionChamber";387;0
"Unit";"Zergling";"Larva";487;1
"Unit";"Zergling";"Larva";487;1
"Unit";"Zergling";"Larva";487;1
"Unit";"Zergling";"Larva";487;1
"Unit";"Zergling";"Larva";487;1
"Unit";"Zergling";"Larva";487;1
"Unit";"Zergling";"Larva";487;1
"Unit";"Zergling";"Larva";487;1
"Unit";"Zergling";"Larva";487;1
"Unit";"Zergling";"Larva";487;1
"Unit";"Zergling";"Larva";487;1
"Unit";"Zergling";"Larva";487;1
"Unit";"Zergling";"Larva";487;1
"Unit";"Zergling";"Larva";487;1
"Unit";"Zergling";"Larva";487;1
"Unit";"Zergling";"Larva";487;1
"Unit";"Zergling";"Larva";487;1
"Unit";"Zergling";"Larva";487;1
"Unit";"Zergling";"Larva";487;1
"Unit";"Zergling";"Larva";487;1
"Unit";"Zergling";"Larva";487;1
"Unit";"Zergling";"Larva";487;1
"Unit";"Zergling";"Larva";487;1
"Unit";"Zergling";"Larva";487;1
"Unit";"Zergling";"Larva";487;1
"Unit";"Zergling";"Larva";487;1
"Unit";"Zergling";"Larva";487;1
"Unit";"Zergling";"Larva";487;1
"Building";"CreepTumor";NA;487;0
"Building";"CreepTumor";NA;487;0
"Building";"CreepTumor";NA;487;0
"Building";"CreepTumor";NA;487;0
"Building";"CreepTumor";NA;487;0
"Building";"CreepTumor";NA;487;0
"Building";"CreepTumor";NA;487;0
"Building";"CreepTumor";NA;487;0
"Building";"CreepTumorQueen";NA;515;0
"Building";"CreepTumor";NA;515;0
"Unit";"Zergling";"Larva";515;1
"Unit";"Zergling";"Larva";515;1
"Unit";"Zergling";"Larva";515;1
"Unit";"Zergling";"Larva";515;1
"Unit";"Zergling";"Larva";515;1
"Unit";"Zergling";"Larva";515;1
"Unit";"Zergling";"Larva";515;1
"Unit";"Zergling";"Larva";515;1
"Unit";"Zergling";"Larva";515;1
"Unit";"Zergling";"Larva";515;1
"Unit";"Zergling";"Larva";515;1
"Unit";"Zergling";"Larva";515;1
"Unit";"Zergling";"Larva";515;1
"Unit";"Zergling";"Larva";515;1
"Unit";"Zergling";"Larva";515;1
"Unit";"Zergling";"Larva";515;1
"Unit";"Zergling";"Larva";515;1
"Unit";"Zergling";"Larva";515;1
"Unit";"Zergling";"Larva";515;1
"Unit";"Zergling";"Larva";515;1
"Unit";"Zergling";"Larva";515;1
"Unit";"Zergling";"Larva";515;1
"Unit";"Zergling";"Larva";515;1
"Unit";"Zergling";"Larva";515;1
"Unit";"Zergling";"Larva";515;1
"Unit";"Zergling";"Larva";515;1
"Unit";"Zergling";"Larva";515;1
"Unit";"Zergling";"Larva";515;1
"Unit";"Zergling";"Larva";515;1
"Unit";"Zergling";"Larva";515;1
"Building";"CreepTumorQueen";NA;545;0
"Building";"CreepTumorQueen";NA;545;0
"Unit";"Zergling";"Larva";515;1
"Unit";"Zergling";"Larva";515;1
"Unit";"Zergling";"Larva";515;1
"Unit";"Zergling";"Larva";515;1
"Unit";"Zergling";"Larva";515;1
"Unit";"Zergling";"Larva";515;1
"Unit";"Zergling";"Larva";515;1
"Unit";"Zergling";"Larva";515;1
"Unit";"Zergling";"Larva";515;1
"Unit";"Zergling";"Larva";515;1
"Unit";"Zergling";"Larva";515;1
"Unit";"Zergling";"Larva";515;1
"Unit";"Zergling";"Larva";515;1
"Unit";"Zergling";"Larva";515;1
"Unit";"Zergling";"Larva";515;1
"Unit";"Zergling";"Larva";515;1
"Unit";"Zergling";"Larva";515;1
"Unit";"Zergling";"Larva";515;1
"Unit";"Zergling";"Larva";515;1
"Unit";"Zergling";"Larva";515;1
"Unit";"Zergling";"Larva";515;1
"Unit";"Zergling";"Larva";515;1
"Unit";"Zergling";"Larva";515;1
"Unit";"Zergling";"Larva";515;1
"Unit";"Zergling";"Larva";515;1
"Unit";"Zergling";"Larva";515;1
"Building";"CreepTumor";NA;545;0
"Building";"CreepTumor";NA;545;0
"Unit";"Baneling";"Zergling";571;0
"Unit";"Zergling";"Larva";571;1
"Unit";"Zergling";"Larva";571;1
"Unit";"Baneling";"Zergling";571;0
"Unit";"Zergling";"Larva";571;1
"Unit";"Zergling";"Larva";571;1
"Unit";"Baneling";"Zergling";571;0
"Unit";"Baneling";"Zergling";571;0
"Unit";"Baneling";"Zergling";571;0
"Unit";"Baneling";"Zergling";571;0
"Unit";"Zergling";"Larva";571;1
"Unit";"Zergling";"Larva";571;1
"Unit";"Baneling";"Zergling";571;0
"Unit";"Baneling";"Zergling";571;0
"Unit";"Zergling";"Larva";571;1
"Unit";"Zergling";"Larva";571;1
"Unit";"Zergling";"Larva";571;1
"Unit";"Zergling";"Larva";571;1
"Unit";"Baneling";"Zergling";571;0
"Unit";"Baneling";"Zergling";571;0
"Unit";"Zergling";"Larva";571;1
"Unit";"Zergling";"Larva";571;1
"Unit";"Zergling";"Larva";571;1
"Unit";"Zergling";"Larva";571;1
"Unit";"Baneling";"Zergling";571;0
"Unit";"Baneling";"Zergling";571;0
"Unit";"Zergling";"Larva";571;1
"Unit";"Zergling";"Larva";571;1
"Unit";"Zergling";"Larva";571;1
"Unit";"Zergling";"Larva";571;1
"Unit";"Zergling";"Larva";571;1
"Unit";"Zergling";"Larva";571;1
"Unit";"Baneling";"Zergling";571;0
"Unit";"Baneling";"Zergling";571;0
"Unit";"Baneling";"Zergling";571;0
"Unit";"Zergling";"Larva";571;1
"Unit";"Zergling";"Larva";571;1
"Unit";"Baneling";"Zergling";571;0
"Unit";"Baneling";"Zergling";571;0
"Unit";"Baneling";"Zergling";571;0
"Building";"Hatchery";NA;515;0
"Unit";"Baneling";"Zergling";593;0
"Unit";"Baneling";"Zergling";593;0
"Unit";"Baneling";"Zergling";593;0
"Unit";"Zergling";"Larva";593;1
"Unit";"Zergling";"Larva";593;1
"Unit";"Zergling";"Larva";593;1
"Unit";"Zergling";"Larva";593;1
"Unit";"Zergling";"Larva";593;1
"Unit";"Zergling";"Larva";593;1
"Unit";"Zergling";"Larva";593;1
"Unit";"Zergling";"Larva";593;1
"Unit";"Zergling";"Larva";593;1
"Unit";"Zergling";"Larva";593;1
"Unit";"Zergling";"Larva";593;1
"Unit";"Zergling";"Larva";593;1
"Unit";"Zergling";"Larva";593;1
"Unit";"Zergling";"Larva";593;1
"Unit";"Zergling";"Larva";593;1
"Unit";"Zergling";"Larva";593;1
"Unit";"Zergling";"Larva";593;1
"Unit";"Zergling";"Larva";593;1
"Unit";"Zergling";"Larva";593;1
"Unit";"Zergling";"Larva";593;1
"Unit";"Zergling";"Larva";593;1
"Unit";"Zergling";"Larva";593;1
"Unit";"Zergling";"Larva";593;1
"Unit";"Zergling";"Larva";593;1
"Unit";"Zergling";"Larva";593;1
"Unit";"Zergling";"Larva";593;1
"Unit";"Zergling";"Larva";593;1
"Unit";"Zergling";"Larva";593;1
"Unit";"Zergling";"Larva";593;1
"Unit";"Zergling";"Larva";593;1
"Unit";"Zergling";"Larva";593;1
"Unit";"Zergling";"Larva";593;1
"Unit";"Zergling";"Larva";593;1
"Unit";"Zergling";"Larva";593;1
"Unit";"Zergling";"Larva";593;1
"Unit";"Zergling";"Larva";593;1
"Unit";"Zergling";"Larva";593;1
"Unit";"Zergling";"Larva";593;1
"Unit";"Zergling";"Larva";593;1
"Unit";"Zergling";"Larva";593;1
"Unit";"Zergling";"Larva";593;1
"Unit";"Zergling";"Larva";593;1
"Building";"CreepTumor";NA;635;0
"Building";"CreepTumor";NA;635;0
"Building";"CreepTumor";NA;635;0
"Building";"BanelingNest";NA;593;0
"Building";"CreepTumor";NA;635;0
"Building";"CreepTumor";NA;635;0
"Building";"CreepTumor";NA;635;0
"Unit";"Zergling";"Larva";635;1
"Unit";"Zergling";"Larva";635;1
"Unit";"Zergling";"Larva";635;1
"Unit";"Zergling";"Larva";635;1
"Unit";"Zergling";"Larva";635;1
"Unit";"Zergling";"Larva";635;1
"Unit";"Zergling";"Larva";635;1
"Unit";"Zergling";"Larva";635;1
"Unit";"Zergling";"Larva";635;1
"Unit";"Zergling";"Larva";635;1
"Unit";"Zergling";"Larva";635;1
"Unit";"Zergling";"Larva";635;1
"Unit";"Zergling";"Larva";635;1
"Unit";"Zergling";"Larva";635;1
"Unit";"Zergling";"Larva";635;1
"Unit";"Zergling";"Larva";635;1
"Unit";"Zergling";"Larva";635;1
"Unit";"Zergling";"Larva";635;1
"Unit";"Zergling";"Larva";635;1
"Unit";"Zergling";"Larva";635;1
"Unit";"Zergling";"Larva";635;1
"Unit";"Zergling";"Larva";635;1
"Unit";"Zergling";"Larva";635;1
"Unit";"Zergling";"Larva";635;1
"Unit";"Zergling";"Larva";635;1
"Unit";"Zergling";"Larva";635;1
"Unit";"Zergling";"Larva";635;1
"Unit";"Zergling";"Larva";635;1
"Unit";"Zergling";"Larva";635;1
"Unit";"Zergling";"Larva";635;1
"Building";"CreepTumor";NA;635;0
"Unit";"Zergling";"Larva";635;1
"Unit";"Zergling";"Larva";635;1
"Unit";"Zergling";"Larva";635;1
"Unit";"Zergling";"Larva";635;1
"Unit";"Zergling";"Larva";635;1
"Unit";"Zergling";"Larva";635;1
"Building";"CreepTumor";NA;671;0
"Building";"CreepTumor";NA;671;0
"Building";"Extractor";NA;653;0
"Building";"CreepTumorQueen";NA;677;0
"Building";"CreepTumorQueen";NA;677;0
"Building";"CreepTumorQueen";NA;677;0
"Unit";"Zergling";"Larva";677;1
"Unit";"Zergling";"Larva";677;1
"Unit";"Zergling";"Larva";677;1
"Unit";"Zergling";"Larva";677;1
"Unit";"Zergling";"Larva";677;1
"Unit";"Zergling";"Larva";677;1
"Unit";"Zergling";"Larva";677;1
"Unit";"Zergling";"Larva";677;1
"Unit";"Zergling";"Larva";677;1
"Unit";"Zergling";"Larva";677;1
"Unit";"Zergling";"Larva";677;1
"Unit";"Zergling";"Larva";677;1
"Unit";"Zergling";"Larva";677;1
"Unit";"Zergling";"Larva";677;1
"Unit";"Zergling";"Larva";677;1
"Unit";"Zergling";"Larva";677;1
"Unit";"Zergling";"Larva";677;1
"Unit";"Zergling";"Larva";677;1
"Unit";"Zergling";"Larva";677;1
"Unit";"Zergling";"Larva";677;1
"Building";"CreepTumorQueen";NA;677;0
"Building";"CreepTumor";NA;677;0
"Building";"CreepTumor";NA;679;0
"Building";"CreepTumor";NA;689;0
"Building";"CreepTumor";NA;697;0
"Building";"Hatchery";NA;635;0
"Building";"CreepTumorQueen";NA;697;0
"Building";"CreepTumorQueen";NA;697;0
"Building";"CreepTumorQueen";NA;697;0
"Building";"CreepTumor";NA;697;0
"Building";"CreepTumor";NA;697;0
"Building";"CreepTumor";NA;697;0
"Building";"CreepTumor";NA;697;0
"Building";"CreepTumor";NA;697;0
"Unit";"Zergling";"Larva";697;1
"Unit";"Zergling";"Larva";697;1
"Unit";"Zergling";"Larva";697;1
"Unit";"Zergling";"Larva";697;1
"Unit";"Zergling";"Larva";697;1
"Unit";"Zergling";"Larva";697;1
"Unit";"Zergling";"Larva";697;1
"Unit";"Zergling";"Larva";697;1
"Unit";"Zergling";"Larva";697;1
"Unit";"Zergling";"Larva";697;1
"Unit";"Zergling";"Larva";697;1
"Unit";"Zergling";"Larva";697;1
"Unit";"Zergling";"Larva";697;1
"Unit";"Zergling";"Larva";697;1
"Unit";"Zergling";"Larva";697;1
"Unit";"Zergling";"Larva";697;1
"Unit";"Zergling";"Larva";697;1
"Unit";"Zergling";"Larva";697;1
"Unit";"Zergling";"Larva";697;1
"Unit";"Zergling";"Larva";697;1
"Unit";"Zergling";"Larva";697;1
"Unit";"Zergling";"Larva";697;1
"Unit";"Zergling";"Larva";697;1
"Unit";"Zergling";"Larva";697;1
"Unit";"Zergling";"Larva";697;1
"Unit";"Zergling";"Larva";697;1
"Unit";"Zergling";"Larva";697;1
"Unit";"Zergling";"Larva";697;1
"Unit";"Zergling";"Larva";697;1
"Unit";"Zergling";"Larva";697;1
"Unit";"Zergling";"Larva";697;1
"Unit";"Zergling";"Larva";697;1
"Unit";"Zergling";"Larva";697;1
"Unit";"Zergling";"Larva";697;1
"Unit";"Zergling";"Larva";697;1
"Unit";"Zergling";"Larva";697;1
"Unit";"Zergling";"Larva";697;1
"Unit";"Zergling";"Larva";697;1
"Building";"CreepTumorQueen";NA;697;0
"Building";"CreepTumorQueen";NA;697;0
"Building";"CreepTumorQueen";NA;697;0
"Unit";"Baneling";"Zergling";735;0
"Unit";"Baneling";"Zergling";735;0
"Unit";"Baneling";"Zergling";735;0
"Unit";"Baneling";"Zergling";735;0
"Building";"Extractor";NA;735;0
"Building";"Extractor";NA;735;0
"Unit";"Viper";"Larva";735;3
"Unit";"Ultralisk";"Larva";735;6
"Unit";"Ultralisk";"Larva";735;6
"Unit";"Ultralisk";"Larva";735;6
"Unit";"Ultralisk";"Larva";735;6
"Unit";"Zergling";"Larva";735;1
"Unit";"Zergling";"Larva";735;1
"Unit";"Zergling";"Larva";735;1
"Unit";"Zergling";"Larva";735;1
"Unit";"Zergling";"Larva";735;1
"Unit";"Zergling";"Larva";735;1
"Unit";"Zergling";"Larva";735;1
"Unit";"Zergling";"Larva";735;1
"Unit";"Zergling";"Larva";735;1
"Unit";"Zergling";"Larva";735;1
"Unit";"Zergling";"Larva";735;1
"Unit";"Zergling";"Larva";735;1
"Unit";"Zergling";"Larva";735;1
"Unit";"Zergling";"Larva";735;1
"Unit";"Zergling";"Larva";735;1
"Unit";"Zergling";"Larva";735;1
"Unit";"Zergling";"Larva";735;1
"Unit";"Zergling";"Larva";735;1
"Unit";"Zergling";"Larva";735;1
"Unit";"Zergling";"Larva";735;1
"Unit";"Zergling";"Larva";735;1
"Unit";"Zergling";"Larva";735;1
"Unit";"Zergling";"Larva";735;1
"Unit";"Zergling";"Larva";735;1
"Unit";"Zergling";"Larva";735;1
"Unit";"Zergling";"Larva";735;1
"Unit";"Zergling";"Larva";735;1
"Unit";"Zergling";"Larva";735;1
"Unit";"Zergling";"Larva";735;1
"Unit";"Zergling";"Larva";735;1
"Unit";"Zergling";"Larva";744;1
"Unit";"Zergling";"Larva";744;1
"Unit";"Zergling";"Larva";762;1
"Unit";"Zergling";"Larva";762;1
"Unit";"Zergling";"Larva";762;1
"Unit";"Zergling";"Larva";762;1
"Unit";"Zergling";"Larva";762;1
"Unit";"Zergling";"Larva";762;1
"Unit";"Zergling";"Larva";762;1
"Unit";"Zergling";"Larva";762;1
"Unit";"Zergling";"Larva";762;1
"Unit";"Zergling";"Larva";762;1
"Unit";"Zergling";"Larva";762;1
"Unit";"Zergling";"Larva";762;1
"Unit";"Zergling";"Larva";762;1
"Unit";"Zergling";"Larva";762;1
"Unit";"Zergling";"Larva";762;1
"Unit";"Zergling";"Larva";762;1
"Building";"CreepTumor";NA;810;0
"Unit";"Ultralisk";"Larva";810;6
"Unit";"Ultralisk";"Larva";810;6
"Unit";"Ultralisk";"Larva";810;6
"Unit";"Ultralisk";"Larva";810;6
"Unit";"Ultralisk";"Larva";810;6
"Unit";"Zergling";"Larva";810;1
"Unit";"Zergling";"Larva";810;1
"Unit";"Zergling";"Larva";810;1
"Unit";"Zergling";"Larva";810;1
"Unit";"Zergling";"Larva";810;1
"Unit";"Zergling";"Larva";810;1
"Unit";"Zergling";"Larva";810;1
"Unit";"Zergling";"Larva";810;1
"Unit";"Zergling";"Larva";810;1
"Unit";"Zergling";"Larva";810;1
"Unit";"Zergling";"Larva";810;1
"Unit";"Zergling";"Larva";810;1
"Unit";"Zergling";"Larva";810;1
"Unit";"Zergling";"Larva";810;1
"Unit";"Zergling";"Larva";810;1
"Unit";"Zergling";"Larva";810;1
"Unit";"Zergling";"Larva";810;1
"Unit";"Zergling";"Larva";810;1
"Unit";"Zergling";"Larva";810;1
"Unit";"Zergling";"Larva";810;1
"Unit";"Zergling";"Larva";810;1
"Unit";"Zergling";"Larva";810;1
"Unit";"Zergling";"Larva";810;1
"Unit";"Zergling";"Larva";810;1
"Unit";"Zergling";"Larva";810;1
"Unit";"Zergling";"Larva";810;1
"Unit";"Zergling";"Larva";810;1
"Unit";"Zergling";"Larva";810;1
"Unit";"Zergling";"Larva";810;1
"Unit";"Zergling";"Larva";810;1
"Unit";"Zergling";"Larva";810;1
"Unit";"Zergling";"Larva";810;1
"Unit";"Zergling";"Larva";810;1
"Unit";"Zergling";"Larva";810;1
"Building";"CreepTumor";NA;840;0
"Unit";"Zergling";"Larva";840;1
"Unit";"Zergling";"Larva";840;1
"Unit";"Zergling";"Larva";840;1
"Unit";"Zergling";"Larva";840;1
"Unit";"Zergling";"Larva";840;1
"Unit";"Zergling";"Larva";840;1
"Unit";"Zergling";"Larva";840;1
"Unit";"Zergling";"Larva";840;1
"Unit";"Zergling";"Larva";840;1
"Unit";"Zergling";"Larva";840;1
"Unit";"Zergling";"Larva";840;1
"Unit";"Zergling";"Larva";840;1
"Unit";"Zergling";"Larva";840;1
"Unit";"Zergling";"Larva";840;1
"Building";"CreepTumor";NA;840;0
"Building";"CreepTumor";NA;840;0
"Building";"CreepTumor";NA;850;0
"Unit";"Zergling";"Larva";888;1
"Unit";"Zergling";"Larva";888;1
"Unit";"Zergling";"Larva";888;1
"Unit";"Zergling";"Larva";888;1
"Unit";"Zergling";"Larva";888;1
"Unit";"Zergling";"Larva";888;1
"Unit";"Zergling";"Larva";888;1
"Unit";"Zergling";"Larva";888;1
"Unit";"Zergling";"Larva";888;1
"Unit";"Zergling";"Larva";888;1
"Unit";"Zergling";"Larva";888;1
"Unit";"Zergling";"Larva";888;1
"Unit";"Zergling";"Larva";888;1
"Unit";"Zergling";"Larva";888;1
"Unit";"Zergling";"Larva";888;1
"Unit";"Zergling";"Larva";888;1
"Unit";"Zergling";"Larva";888;1
"Unit";"Zergling";"Larva";888;1
"Unit";"Zergling";"Larva";888;1
"Unit";"Zergling";"Larva";888;1
"Unit";"Zergling";"Larva";888;1
"Unit";"Zergling";"Larva";888;1
"Unit";"Zergling";"Larva";888;1
"Unit";"Zergling";"Larva";888;1
"Unit";"Zergling";"Larva";888;1
"Unit";"Zergling";"Larva";888;1
"Unit";"Zergling";"Larva";888;1
"Unit";"Zergling";"Larva";888;1
"Unit";"Zergling";"Larva";888;1
"Unit";"Zergling";"Larva";888;1
"Unit";"Zergling";"Larva";888;1
"Unit";"Zergling";"Larva";888;1
"Building";"CreepTumorQueen";NA;920;0
"Building";"CreepTumor";NA;920;0
"Building";"Hatchery";NA;888;0
"Building";"CreepTumorQueen";NA;920;0
"Building";"CreepTumorQueen";NA;920;0
"Unit";"Zergling";"Larva";920;1
"Unit";"Zergling";"Larva";920;1
"Unit";"Zergling";"Larva";920;1
"Unit";"Zergling";"Larva";920;1
"Unit";"Zergling";"Larva";920;1
"Unit";"Zergling";"Larva";920;1
"Unit";"Zergling";"Larva";920;1
"Unit";"Zergling";"Larva";920;1
"Unit";"Zergling";"Larva";920;1
"Unit";"Zergling";"Larva";920;1
"Unit";"Zergling";"Larva";920;1
"Unit";"Zergling";"Larva";920;1
"Unit";"Zergling";"Larva";920;1
"Unit";"Zergling";"Larva";920;1
"Unit";"Zergling";"Larva";920;1
"Unit";"Zergling";"Larva";920;1
"Unit";"Zergling";"Larva";920;1
"Unit";"Zergling";"Larva";920;1
"Unit";"Zergling";"Larva";920;1
"Unit";"Zergling";"Larva";920;1
"Unit";"Zergling";"Larva";920;1
"Unit";"Zergling";"Larva";920;1
"Unit";"Zergling";"Larva";920;1
"Unit";"Zergling";"Larva";920;1
"Unit";"Zergling";"Larva";920;1
"Unit";"Zergling";"Larva";920;1
"Unit";"Zergling";"Larva";920;1
"Unit";"Zergling";"Larva";920;1
"Unit";"Zergling";"Larva";920;1
"Unit";"Zergling";"Larva";920;1
"Unit";"Zergling";"Larva";920;1
"Unit";"Zergling";"Larva";920;1
"Unit";"Zergling";"Larva";920;1
"Unit";"Zergling";"Larva";920;1
"Unit";"Zergling";"Larva";920;1
"Unit";"Zergling";"Larva";920;1
"Unit";"Zergling";"Larva";920;1
"Unit";"Zergling";"Larva";920;1
"Unit";"Zergling";"Larva";920;1
"Unit";"Zergling";"Larva";920;1
"Building";"CreepTumor";NA;920;0
"Building";"CreepTumor";NA;920;0
"Unit";"Zergling";"Larva";920;1
"Unit";"Zergling";"Larva";920;1
"Unit";"Zergling";"Larva";920;1
"Unit";"Zergling";"Larva";920;1
"Unit";"Zergling";"Larva";920;1
"Unit";"Zergling";"Larva";920;1
"Unit";"Zergling";"Larva";920;1
"Unit";"Zergling";"Larva";920;1
"Unit";"Baneling";"Zergling";960;0
"Unit";"Baneling";"Zergling";960;0
"Unit";"Baneling";"Zergling";960;0
"Unit";"Baneling";"Zergling";960;0
"Unit";"Baneling";"Zergling";960;0
"Unit";"Baneling";"Zergling";960;0
"Unit";"Baneling";"Zergling";960;0
"Unit";"Baneling";"Zergling";960;0
"Unit";"Baneling";"Zergling";960;0
"Unit";"Baneling";"Zergling";960;0
"Unit";"Baneling";"Zergling";960;0
"Unit";"Baneling";"Zergling";960;0
"Unit";"Baneling";"Zergling";960;0
"Unit";"Baneling";"Zergling";960;0
"Unit";"Baneling";"Zergling";960;0
"Unit";"Baneling";"Zergling";960;0
"Unit";"Baneling";"Zergling";960;0
"Unit";"Baneling";"Zergling";960;0
"Unit";"Baneling";"Zergling";960;0
"Unit";"Baneling";"Zergling";960;0
"Unit";"Baneling";"Zergling";960;0
"Unit";"Baneling";"Zergling";960;0
"Unit";"Baneling";"Zergling";960;0
"Unit";"Baneling";"Zergling";960;0
"Unit";"Baneling";"Zergling";960;0
"Unit";"Baneling";"Zergling";960;0
"Unit";"Baneling";"Zergling";960;0
"Unit";"Baneling";"Zergling";960;0
"Unit";"Baneling";"Zergling";968;0
"Unit";"Baneling";"Zergling";968;0
"Unit";"Baneling";"Zergling";968;0
"Unit";"Baneling";"Zergling";968;0
"Unit";"Baneling";"Zergling";968;0
"Unit";"Baneling";"Zergling";968;0
"Unit";"Baneling";"Zergling";968;0
"Unit";"Baneling";"Zergling";968;0
"Unit";"Baneling";"Zergling";968;0
"Unit";"Baneling";"Zergling";968;0
"Unit";"Baneling";"Zergling";968;0
"Unit";"Baneling";"Zergling";968;0
"Unit";"Baneling";"Zergling";968;0
"Unit";"Baneling";"Zergling";968;0
"Unit";"Baneling";"Zergling";968;0
"Unit";"Baneling";"Zergling";968;0
"Unit";"Baneling";"Zergling";968;0
"Unit";"Baneling";"Zergling";968;0
"Unit";"Baneling";"Zergling";968;0
"Unit";"Baneling";"Zergling";968;0
"Unit";"Baneling";"Zergling";968;0
"Unit";"Baneling";"Zergling";968;0
"Unit";"Baneling";"Zergling";968;0
"Unit";"Baneling";"Zergling";968;0
"Unit";"Baneling";"Zergling";968;0
"Unit";"Baneling";"Zergling";968;0
"Unit";"Baneling";"Zergling";968;0
"Unit";"Baneling";"Zergling";968;0
"Unit";"Ultralisk";"Larva";960;6
"Unit";"Ultralisk";"Larva";960;6
"Building";"CreepTumorQueen";NA;968;0
"Building";"CreepTumorQueen";NA;968;0
"Building";"CreepTumor";NA;968;0
"Building";"CreepTumorQueen";NA;968;0
"Building";"CreepTumorQueen";NA;980;0
"Building";"CreepTumorQueen";NA;980;0
"Building";"CreepTumorQueen";NA;980;0
"Building";"CreepTumorQueen";NA;980;0
"Unit";"Zergling";"Larva";980;1
"Unit";"Zergling";"Larva";980;1
"Unit";"Zergling";"Larva";980;1
"Unit";"Zergling";"Larva";980;1
"Unit";"Zergling";"Larva";980;1
"Unit";"Zergling";"Larva";980;1
"Unit";"Zergling";"Larva";980;1
"Unit";"Zergling";"Larva";980;1
"Unit";"Zergling";"Larva";980;1
"Unit";"Zergling";"Larva";980;1
"Unit";"Zergling";"Larva";980;1
"Unit";"Zergling";"Larva";980;1
"Unit";"Zergling";"Larva";980;1
"Unit";"Zergling";"Larva";980;1
"Unit";"Zergling";"Larva";980;1
"Unit";"Zergling";"Larva";980;1
"Unit";"Zergling";"Larva";980;1
"Unit";"Zergling";"Larva";980;1
"Unit";"Zergling";"Larva";980;1
"Unit";"Zergling";"Larva";980;1
"Unit";"Zergling";"Larva";980;1
"Unit";"Zergling";"Larva";980;1
"Unit";"Zergling";"Larva";980;1
"Unit";"Zergling";"Larva";980;1
"Unit";"Zergling";"Larva";980;1
"Unit";"Zergling";"Larva";980;1
"Unit";"Zergling";"Larva";980;1
"Unit";"Zergling";"Larva";980;1
"Unit";"Zergling";"Larva";980;1
"Unit";"Zergling";"Larva";980;1
"Unit";"Zergling";"Larva";980;1
"Unit";"Zergling";"Larva";980;1
"Unit";"Zergling";"Larva";980;1
"Unit";"Zergling";"Larva";980;1
"Building";"CreepTumor";NA;980;0
"Unit";"Zergling";"Larva";980;1
"Unit";"Zergling";"Larva";980;1
"Unit";"Zergling";"Larva";980;1
"Unit";"Zergling";"Larva";980;1
"Unit";"Zergling";"Larva";980;1
"Unit";"Zergling";"Larva";980;1
"Unit";"Zergling";"Larva";980;1
"Unit";"Zergling";"Larva";980;1
"Unit";"Zergling";"Larva";980;1
"Unit";"Zergling";"Larva";980;1
"Unit";"Zergling";"Larva";980;1
"Unit";"Zergling";"Larva";980;1
"Unit";"Zergling";"Larva";980;1
"Unit";"Zergling";"Larva";980;1
"Unit";"Zergling";"Larva";980;1
"Unit";"Zergling";"Larva";980;1
"Unit";"Zergling";"Larva";980;1
"Unit";"Zergling";"Larva";980;1
"Building";"CreepTumor";NA;1032;0
"Building";"CreepTumor";NA;1032;0
"Building";"CreepTumor";NA;1032;0
"Building";"CreepTumor";NA;1032;0
"Building";"CreepTumor";NA;1032;0
"Building";"CreepTumor";NA;1032;0
"Building";"CreepTumor";NA;1032;0
"Building";"CreepTumor";NA;1032;0
"Unit";"Queen";"Hatchery";1014;2
"Unit";"Queen";"Hatchery";1014;2
"Unit";"Queen";"Hatchery";1014;2
"Unit";"Queen";"Hatchery";1014;2
"Unit";"Queen";"Hatchery";1014;2
"Unit";"Queen";"Hatchery";1014;2
"Unit";"Ultralisk";"Larva";1032;6
"Unit";"Ultralisk";"Larva";1032;6
"Unit";"Ultralisk";"Larva";1032;6
"Building";"CreepTumor";NA;1044;0
"Building";"CreepTumor";NA;1044;0
"Building";"CreepTumor";NA;1044;0
"Building";"CreepTumor";NA;1044;0
"Building";"CreepTumor";NA;1044;0
"Building";"CreepTumor";NA;1062;0
"Building";"CreepTumor";NA;1062;0
"Building";"CreepTumor";NA;1062;0
"Building";"CreepTumor";NA;1062;0
"Building";"CreepTumor";NA;1062;0
"Building";"CreepTumor";NA;1062;0
"Building";"CreepTumor";NA;1062;0
"Building";"CreepTumor";NA;1062;0
"Building";"CreepTumor";NA;1062;0
"Building";"CreepTumor";NA;1062;0
"Building";"CreepTumor";NA;1062;0
"Building";"CreepTumor";NA;1062;0
"Building";"CreepTumor";NA;1062;0
"Building";"Hatchery";NA;1032;0
"Building";"Hatchery";NA;1032;0
"Building";"CreepTumor";NA;1062;0
"Building";"CreepTumor";NA;1062;0
"Building";"CreepTumor";NA;1062;0
"Building";"CreepTumor";NA;1062;0
"Building";"CreepTumor";NA;1062;0
"Building";"CreepTumor";NA;1062;0
