"type";"unit_name";"on_building";"total_supply";"supply"
"Unit";"Overlord";"Larva";13;0
"Building";"Extractor";NA;19;0
"Unit";"Overlord";"Larva";21;0
"Building";"SpawningPool";NA;19;0
"Building";"Hatchery";NA;17;0
"Unit";"Zergling";"Larva";22;1
"Unit";"Zergling";"Larva";22;1
"Unit";"Zergling";"Larva";22;1
"Unit";"Zergling";"Larva";22;1
"Unit";"Zergling";"Larva";22;1
"Unit";"Zergling";"Larva";22;1
"Unit";"Queen";"Hatchery";22;2
"Unit";"Queen";"Hatchery";22;2
"Building";"CreepTumorQueen";NA;36;0
"Unit";"Overlord";"Larva";36;0
"Unit";"Queen";"Hatchery";36;2
"Unit";"Overlord";"Larva";36;0
"Building";"CreepTumor";NA;40;0
"Building";"CreepTumorQueen";NA;45;0
"Unit";"Zergling";"Larva";46;1
"Unit";"Zergling";"Larva";46;1
"Unit";"Zergling";"Larva";46;1
"Unit";"Zergling";"Larva";46;1
"Building";"Hatchery";NA;33;0
"Unit";"Zergling";"Larva";48;1
"Unit";"Zergling";"Larva";48;1
"Building";"SporeCrawler";NA;48;0
"Building";"CreepTumor";NA;48;0
"Unit";"Queen";"Hatchery";45;2
"Building";"CreepTumorQueen";NA;52;0
"Unit";"Zergling";"Larva";48;1
"Unit";"Zergling";"Larva";48;1
"Unit";"Zergling";"Larva";48;1
"Unit";"Zergling";"Larva";48;1
"Building";"SporeCrawler";NA;48;0
"Building";"CreepTumor";NA;54;0
"Building";"SporeCrawler";NA;63;0
"Unit";"Queen";"Hatchery";54;2
"Unit";"Overlord";"Larva";66;0
"Unit";"Overlord";"Larva";66;0
"Building";"Extractor";NA;66;0
"Unit";"Zergling";"Larva";72;1
"Unit";"Zergling";"Larva";72;1
"Unit";"Zergling";"Larva";72;1
"Unit";"Zergling";"Larva";72;1
"Unit";"Zergling";"Larva";72;1
"Unit";"Zergling";"Larva";72;1
"Unit";"Zergling";"Larva";72;1
"Unit";"Zergling";"Larva";72;1
"Unit";"Zergling";"Larva";72;1
"Unit";"Zergling";"Larva";72;1
"Building";"CreepTumorQueen";NA;72;0
"Building";"BanelingNest";NA;70;0
"Unit";"Overlord";"Larva";72;0
"Building";"Extractor";NA;72;0
"Unit";"Overlord";"Larva";85;0
"Unit";"Overlord";"Larva";85;0
"Building";"CreepTumorQueen";NA;85;0
"Building";"EvolutionChamber";NA;85;0
"Building";"EvolutionChamber";NA;85;0
"Building";"Extractor";NA;92;0
"Unit";"Queen";"Hatchery";85;2
"Unit";"Queen";"Hatchery";85;2
"Unit";"Overlord";"Larva";102;0
"Unit";"Overlord";"Larva";103;0
"Building";"CreepTumorQueen";NA;110;0
"Building";"CreepTumorQueen";NA;111;0
"Building";"CreepTumorQueen";NA;111;0
"Unit";"Overlord";"Larva";111;0
"Unit";"Queen";"Hatchery";111;2
"Unit";"Queen";"Hatchery";111;2
"Building";"CreepTumor";NA;115;0
"Unit";"Overlord";"Larva";115;0
"Unit";"Overlord";"Larva";115;0
"Unit";"Overlord";"Larva";115;0
"Building";"Extractor";NA;115;0
"Building";"Extractor";NA;115;0
"Unit";"Overlord";"Larva";122;0
"Unit";"Overlord";"Larva";122;0
"Unit";"Overlord";"Larva";122;0
"Unit";"Overlord";"Larva";127;0
"Unit";"Overlord";"Larva";127;0
"Building";"HydraliskDen";NA;127;0
"Building";"CreepTumorQueen";NA;128;0
"Building";"CreepTumorQueen";NA;128;0
"Building";"CreepTumorQueen";NA;128;0
"Unit";"Zergling";"Larva";128;1
"Unit";"Zergling";"Larva";128;1
"Unit";"Zergling";"Larva";128;1
"Unit";"Zergling";"Larva";128;1
"Unit";"Zergling";"Larva";128;1
"Unit";"Zergling";"Larva";128;1
"Unit";"Zergling";"Larva";128;1
"Unit";"Zergling";"Larva";128;1
"Unit";"Zergling";"Larva";128;1
"Unit";"Zergling";"Larva";128;1
"Unit";"Zergling";"Larva";128;1
"Unit";"Zergling";"Larva";128;1
"Unit";"Zergling";"Larva";128;1
"Unit";"Zergling";"Larva";128;1
"Building";"CreepTumor";NA;128;0
"Unit";"Zergling";"Larva";128;1
"Unit";"Zergling";"Larva";128;1
"Unit";"Zergling";"Larva";128;1
"Unit";"Zergling";"Larva";128;1
"Building";"CreepTumorQueen";NA;128;0
"Building";"CreepTumorQueen";NA;128;0
"Building";"InfestationPit";NA;128;0
"Building";"CreepTumor";NA;128;0
"Building";"CreepTumor";NA;146;0
"Unit";"Hydralisk";"Larva";128;2
"Unit";"Hydralisk";"Larva";128;2
"Unit";"Hydralisk";"Larva";128;2
"Unit";"Hydralisk";"Larva";128;2
"Unit";"Hydralisk";"Larva";128;2
"Unit";"Hydralisk";"Larva";128;2
"Building";"CreepTumorQueen";NA;147;0
"Building";"CreepTumor";NA;147;0
"Building";"CreepTumor";NA;147;0
"Unit";"Baneling";"Zergling";147;0
"Unit";"Baneling";"Zergling";147;0
"Unit";"Baneling";"Zergling";147;0
"Unit";"Baneling";"Zergling";147;0
"Unit";"Baneling";"Zergling";147;0
"Unit";"Baneling";"Zergling";147;0
"Unit";"Baneling";"Zergling";147;0
"Unit";"Baneling";"Zergling";147;0
"Unit";"Baneling";"Zergling";147;0
"Unit";"Baneling";"Zergling";147;0
"Building";"Hatchery";NA;127;0
"Upgrade";"ZergMeleeWeaponsLevel1";"EvolutionChamber";122;0
"Upgrade";"ZergGroundArmorsLevel1";"EvolutionChamber";122;0
"Building";"CreepTumor";NA;162;0
"Building";"CreepTumor";NA;162;0
"Building";"CreepTumor";NA;162;0
"Building";"CreepTumor";NA;162;0
"Building";"CreepTumor";NA;162;0
"Building";"CreepTumor";NA;173;0
"Building";"CreepTumor";NA;173;0
"Building";"CreepTumor";NA;173;0
"Unit";"Hydralisk";"Larva";171;2
"Unit";"Hydralisk";"Larva";171;2
"Unit";"Hydralisk";"Larva";171;2
"Unit";"Hydralisk";"Larva";171;2
"Unit";"Hydralisk";"Larva";172;2
"Upgrade";"EvolveGroovedSpines";"HydraliskDen";147;0
"Unit";"Overlord";"Larva";173;0
"Unit";"Overlord";"Larva";173;0
"Unit";"Zergling";"Larva";173;1
"Unit";"Zergling";"Larva";173;1
"Unit";"Zergling";"Larva";173;1
"Unit";"Zergling";"Larva";173;1
"Unit";"Zergling";"Larva";173;1
"Unit";"Zergling";"Larva";173;1
"Unit";"Zergling";"Larva";173;1
"Unit";"Zergling";"Larva";173;1
"Unit";"Zergling";"Larva";173;1
"Unit";"Zergling";"Larva";173;1
"Unit";"Zergling";"Larva";173;1
"Unit";"Zergling";"Larva";173;1
"Unit";"Zergling";"Larva";173;1
"Unit";"Zergling";"Larva";173;1
"Unit";"Zergling";"Larva";173;1
"Unit";"Zergling";"Larva";173;1
"Unit";"Overlord";"Larva";183;0
"Building";"Extractor";NA;183;0
"Building";"CreepTumorQueen";NA;199;0
"Building";"Extractor";NA;183;0
"Building";"CreepTumor";NA;199;0
"Building";"CreepTumorQueen";NA;199;0
"Building";"Hatchery";NA;159;0
"Unit";"Zergling";"Larva";199;1
"Unit";"Zergling";"Larva";199;1
"Unit";"Zergling";"Larva";199;1
"Unit";"Zergling";"Larva";199;1
"Unit";"Zergling";"Larva";199;1
"Unit";"Zergling";"Larva";199;1
"Unit";"Zergling";"Larva";199;1
"Unit";"Zergling";"Larva";199;1
"Unit";"Zergling";"Larva";199;1
"Unit";"Zergling";"Larva";199;1
"Unit";"Zergling";"Larva";199;1
"Unit";"Zergling";"Larva";199;1
"Building";"CreepTumor";NA;199;0
"Building";"CreepTumor";NA;199;0
"Building";"CreepTumor";NA;199;0
"Building";"CreepTumor";NA;199;0
"Building";"CreepTumor";NA;211;0
"Building";"CreepTumor";NA;211;0
"Unit";"Zergling";"Larva";199;1
"Unit";"Zergling";"Larva";199;1
"Unit";"Zergling";"Larva";199;1
"Unit";"Zergling";"Larva";199;1
"Unit";"Zergling";"Larva";199;1
"Unit";"Zergling";"Larva";199;1
"Unit";"Zergling";"Larva";199;1
"Unit";"Zergling";"Larva";199;1
"Unit";"Zergling";"Larva";199;1
"Unit";"Zergling";"Larva";199;1
"Unit";"Zergling";"Larva";199;1
"Unit";"Zergling";"Larva";199;1
"Unit";"Zergling";"Larva";199;1
"Unit";"Zergling";"Larva";199;1
"Unit";"Zergling";"Larva";199;1
"Unit";"Zergling";"Larva";199;1
"Unit";"Zergling";"Larva";199;1
"Unit";"Zergling";"Larva";199;1
"Unit";"Zergling";"Larva";199;1
"Unit";"Zergling";"Larva";199;1
"Unit";"Zergling";"Larva";199;1
"Unit";"Zergling";"Larva";199;1
"Building";"CreepTumorQueen";NA;211;0
"Building";"CreepTumorQueen";NA;211;0
"Unit";"Viper";"Larva";199;3
"Unit";"Viper";"Larva";199;3
"Unit";"Viper";"Larva";199;3
"Building";"Extractor";NA;211;0
"Upgrade";"EvolveMuscularAugments";"HydraliskDen";199;0
"Building";"Extractor";NA;242;0
"Unit";"Hydralisk";"Larva";242;2
"Unit";"Hydralisk";"Larva";242;2
"Unit";"Hydralisk";"Larva";242;2
"Unit";"Hydralisk";"Larva";242;2
"Unit";"Hydralisk";"Larva";242;2
"Unit";"Hydralisk";"Larva";242;2
"Unit";"Hydralisk";"Larva";242;2
"Unit";"Hydralisk";"Larva";242;2
"Unit";"Hydralisk";"Larva";242;2
"Unit";"Baneling";"Zergling";242;0
"Unit";"Baneling";"Zergling";242;0
"Unit";"Baneling";"Zergling";242;0
"Unit";"Baneling";"Zergling";242;0
"Unit";"Baneling";"Zergling";242;0
"Unit";"Baneling";"Zergling";242;0
"Unit";"Baneling";"Zergling";242;0
"Unit";"Baneling";"Zergling";242;0
"Unit";"Baneling";"Zergling";242;0
"Unit";"Baneling";"Zergling";242;0
"Unit";"Baneling";"Zergling";242;0
"Unit";"Baneling";"Zergling";242;0
"Unit";"Baneling";"Zergling";242;0
"Unit";"Baneling";"Zergling";242;0
"Unit";"Baneling";"Zergling";242;0
"Unit";"Baneling";"Zergling";242;0
"Unit";"Baneling";"Zergling";242;0
"Unit";"Baneling";"Zergling";242;0
"Unit";"Baneling";"Zergling";242;0
"Unit";"Baneling";"Zergling";242;0
"Unit";"Baneling";"Zergling";242;0
"Unit";"Zergling";"Larva";242;1
"Unit";"Zergling";"Larva";242;1
"Unit";"Zergling";"Larva";242;1
"Unit";"Zergling";"Larva";242;1
"Unit";"Zergling";"Larva";242;1
"Unit";"Zergling";"Larva";242;1
"Unit";"Zergling";"Larva";242;1
"Unit";"Zergling";"Larva";242;1
"Unit";"Zergling";"Larva";242;1
"Unit";"Zergling";"Larva";242;1
"Unit";"Zergling";"Larva";242;1
"Unit";"Zergling";"Larva";242;1
"Unit";"Zergling";"Larva";242;1
"Unit";"Zergling";"Larva";242;1
"Unit";"Zergling";"Larva";242;1
"Unit";"Zergling";"Larva";242;1
"Unit";"Zergling";"Larva";242;1
"Unit";"Zergling";"Larva";242;1
"Building";"CreepTumor";NA;284;0
"Building";"CreepTumor";NA;284;0
"Building";"CreepTumor";NA;284;0
"Building";"CreepTumor";NA;284;0
"Building";"UltraliskCavern";NA;242;0
"Unit";"Overlord";"Larva";284;0
"Unit";"Overlord";"Larva";284;0
"Unit";"Overlord";"Larva";284;0
"Building";"CreepTumor";NA;284;0
"Upgrade";"ZergMeleeWeaponsLevel2";"EvolutionChamber";211;0
"Upgrade";"ZergGroundArmorsLevel2";"EvolutionChamber";211;0
"Building";"CreepTumorQueen";NA;284;0
"Unit";"Overlord";"Larva";284;0
"Building";"CreepTumor";NA;284;0
"Building";"CreepTumor";NA;284;0
"Building";"CreepTumorQueen";NA;284;0
"Building";"CreepTumorQueen";NA;284;0
"Building";"CreepTumorQueen";NA;284;0
"Building";"Spire";NA;284;0
"Unit";"Ultralisk";"Larva";284;6
"Unit";"Ultralisk";"Larva";284;6
"Unit";"Ultralisk";"Larva";284;6
"Unit";"Overlord";"Larva";284;0
"Unit";"Overlord";"Larva";284;0
"Unit";"Overlord";"Larva";284;0
"Unit";"Overlord";"Larva";284;0
"Unit";"Overlord";"Larva";302;0
"Unit";"Overlord";"Larva";302;0
"Unit";"Overlord";"Larva";302;0
"Upgrade";"ChitinousPlating";"UltraliskCavern";284;0
