"type";"unit_name";"on_building";"total_supply";"supply"
"Unit";"Overlord";"Larva";12;0
"Building";"SpawningPool";NA;19;0
"Building";"Hatchery";NA;17;0
"Building";"Extractor";NA;23;0
"Unit";"Zergling";"Larva";24;1
"Unit";"Zergling";"Larva";24;1
"Unit";"Zergling";"Larva";25;1
"Unit";"Zergling";"Larva";25;1
"Unit";"Overlord";"Larva";25;0
"Unit";"Queen";"Hatchery";24;2
"Unit";"Overlord";"Larva";27;0
"Building";"Hatchery";NA;21;0
"Unit";"Queen";"Hatchery";25;2
"Unit";"Overlord";"Larva";31;0
"Unit";"Overlord";"Larva";31;0
"Unit";"Queen";"Hatchery";54;2
"Building";"CreepTumorQueen";NA;63;0
"Unit";"Overlord";"Larva";63;0
"Unit";"Overlord";"Larva";63;0
"Unit";"Zergling";"Larva";63;1
"Unit";"Zergling";"Larva";63;1
"Unit";"Zergling";"Larva";63;1
"Unit";"Zergling";"Larva";63;1
"Unit";"Zergling";"Larva";63;1
"Unit";"Zergling";"Larva";63;1
"Unit";"Zergling";"Larva";63;1
"Unit";"Zergling";"Larva";63;1
"Unit";"Zergling";"Larva";63;1
"Unit";"Zergling";"Larva";63;1
"Building";"CreepTumorQueen";NA;65;0
"Unit";"Queen";"Hatchery";57;2
"Unit";"Queen";"Hatchery";57;2
"Unit";"Overlord";"Larva";65;0
"Building";"BanelingNest";NA;63;0
"Building";"CreepTumor";NA;79;0
"Building";"CreepTumorQueen";NA;79;0
"Building";"CreepTumorQueen";NA;79;0
"Unit";"Zergling";"Larva";79;1
"Unit";"Zergling";"Larva";79;1
"Unit";"Zergling";"Larva";79;1
"Unit";"Zergling";"Larva";79;1
"Unit";"Zergling";"Larva";79;1
"Unit";"Zergling";"Larva";79;1
"Unit";"Zergling";"Larva";79;1
"Unit";"Zergling";"Larva";79;1
"Unit";"Zergling";"Larva";79;1
"Unit";"Zergling";"Larva";79;1
"Building";"CreepTumorQueen";NA;79;0
"Building";"CreepTumor";NA;79;0
"Building";"CreepTumorQueen";NA;79;0
"Unit";"Queen";"Hatchery";65;2
"Unit";"Overlord";"Larva";79;0
"Unit";"Queen";"Hatchery";79;2
"Unit";"Baneling";"Zergling";84;0
"Unit";"Baneling";"Zergling";84;0
"Unit";"Baneling";"Zergling";84;0
"Unit";"Baneling";"Zergling";84;0
"Unit";"Baneling";"Zergling";84;0
"Building";"CreepTumor";NA;94;0
"Unit";"Zergling";"Larva";84;1
"Unit";"Zergling";"Larva";84;1
"Unit";"Queen";"Hatchery";79;2
"Unit";"Zergling";"Larva";84;1
"Unit";"Zergling";"Larva";84;1
"Unit";"Zergling";"Larva";84;1
"Unit";"Zergling";"Larva";84;1
"Building";"CreepTumor";NA;96;0
"Building";"CreepTumor";NA;96;0
"Building";"Extractor";NA;98;0
"Unit";"Zergling";"Larva";106;1
"Unit";"Zergling";"Larva";106;1
"Unit";"Zergling";"Larva";106;1
"Unit";"Zergling";"Larva";106;1
"Unit";"Zergling";"Larva";106;1
"Unit";"Zergling";"Larva";106;1
"Unit";"Zergling";"Larva";106;1
"Unit";"Zergling";"Larva";106;1
"Unit";"Zergling";"Larva";106;1
"Unit";"Zergling";"Larva";106;1
"Unit";"Baneling";"Zergling";106;0
"Building";"Extractor";NA;106;0
"Building";"SporeCrawler";NA;106;0
"Building";"CreepTumorQueen";NA;121;0
"Building";"CreepTumorQueen";NA;121;0
"Unit";"Zergling";"Larva";121;1
"Unit";"Zergling";"Larva";121;1
"Unit";"Zergling";"Larva";121;1
"Unit";"Zergling";"Larva";121;1
"Unit";"Zergling";"Larva";121;1
"Unit";"Zergling";"Larva";121;1
"Unit";"Zergling";"Larva";121;1
"Unit";"Zergling";"Larva";121;1
"Unit";"Zergling";"Larva";121;1
"Unit";"Zergling";"Larva";121;1
"Unit";"Zergling";"Larva";121;1
"Unit";"Zergling";"Larva";121;1
"Unit";"Zergling";"Larva";121;1
"Unit";"Zergling";"Larva";121;1
"Unit";"Zergling";"Larva";121;1
"Unit";"Zergling";"Larva";121;1
"Unit";"Queen";"Hatchery";106;2
"Building";"CreepTumorQueen";NA;121;0
"Building";"CreepTumorQueen";NA;121;0
"Building";"CreepTumorQueen";NA;137;0
"Building";"CreepTumorQueen";NA;137;0
"Building";"CreepTumorQueen";NA;137;0
"Building";"CreepTumor";NA;144;0
"Unit";"Queen";"Hatchery";121;2
"Unit";"Overlord";"Larva";144;0
"Unit";"Overlord";"Larva";144;0
"Unit";"Overlord";"Larva";144;0
"Unit";"Overlord";"Larva";144;0
"Building";"CreepTumorQueen";NA;146;0
"Building";"CreepTumorQueen";NA;146;0
"Building";"CreepTumor";NA;146;0
"Building";"EvolutionChamber";NA;144;0
"Unit";"Baneling";"Zergling";148;0
"Unit";"Baneling";"Zergling";148;0
"Unit";"Baneling";"Zergling";148;0
"Unit";"Baneling";"Zergling";148;0
"Building";"Extractor";NA;148;0
"Building";"Extractor";NA;148;0
"Building";"CreepTumorQueen";NA;148;0
"Building";"Extractor";NA;148;0
"Building";"CreepTumor";NA;148;0
"Building";"CreepTumor";NA;148;0
"Building";"CreepTumor";NA;153;0
"Building";"CreepTumor";NA;153;0
"Building";"CreepTumor";NA;153;0
"Building";"CreepTumor";NA;153;0
"Building";"CreepTumor";NA;153;0
"Building";"CreepTumor";NA;153;0
"Building";"CreepTumor";NA;157;0
"Building";"CreepTumor";NA;157;0
"Building";"CreepTumor";NA;157;0
"Building";"SporeCrawler";NA;148;0
"Building";"CreepTumorQueen";NA;157;0
"Building";"CreepTumorQueen";NA;157;0
"Building";"CreepTumor";NA;157;0
"Building";"EvolutionChamber";NA;148;0
"Building";"CreepTumorQueen";NA;157;0
"Building";"CreepTumorQueen";NA;157;0
"Building";"Hatchery";NA;121;0
"Unit";"Zergling";"Larva";159;1
"Unit";"Zergling";"Larva";159;1
"Unit";"Zergling";"Larva";159;1
"Unit";"Zergling";"Larva";159;1
"Building";"SporeCrawler";NA;159;0
"Building";"HydraliskDen";NA;157;0
"Unit";"Zergling";"Larva";164;1
"Unit";"Zergling";"Larva";164;1
"Unit";"Zergling";"Larva";164;1
"Unit";"Zergling";"Larva";164;1
"Unit";"Zergling";"Larva";164;1
"Unit";"Zergling";"Larva";164;1
"Unit";"Zergling";"Larva";164;1
"Unit";"Zergling";"Larva";164;1
"Unit";"Zergling";"Larva";164;1
"Unit";"Zergling";"Larva";164;1
"Building";"SporeCrawler";NA;162;0
"Building";"CreepTumor";NA;164;0
"Building";"CreepTumor";NA;164;0
"Building";"CreepTumor";NA;164;0
"Building";"CreepTumor";NA;168;0
"Building";"CreepTumor";NA;168;0
"Building";"CreepTumor";NA;168;0
"Building";"CreepTumor";NA;168;0
"Building";"CreepTumor";NA;168;0
"Building";"CreepTumor";NA;168;0
"Building";"Hatchery";NA;148;0
"Building";"CreepTumor";NA;168;0
"Building";"CreepTumor";NA;169;0
"Building";"CreepTumor";NA;169;0
"Building";"CreepTumor";NA;169;0
"Building";"CreepTumor";NA;169;0
"Unit";"Queen";"Hatchery";159;2
"Unit";"Overlord";"Larva";179;0
"Unit";"Overlord";"Larva";179;0
"Unit";"Overlord";"Larva";179;0
"Unit";"Overlord";"Larva";179;0
"Unit";"Overlord";"Larva";179;0
"Unit";"Overlord";"Larva";179;0
"Unit";"Hydralisk";"Larva";179;2
"Unit";"Hydralisk";"Larva";179;2
"Unit";"Hydralisk";"Larva";179;2
"Unit";"Hydralisk";"Larva";179;2
"Unit";"Hydralisk";"Larva";179;2
"Building";"CreepTumor";NA;181;0
"Building";"CreepTumor";NA;181;0
"Building";"CreepTumor";NA;181;0
"Unit";"Baneling";"Zergling";181;0
"Building";"SporeCrawler";NA;179;0
"Unit";"Baneling";"Zergling";181;0
"Building";"CreepTumor";NA;181;0
"Building";"CreepTumor";NA;181;0
"Building";"CreepTumor";NA;181;0
"Building";"CreepTumor";NA;181;0
"Building";"CreepTumor";NA;181;0
"Building";"CreepTumorQueen";NA;191;0
"Building";"CreepTumor";NA;197;0
"Building";"CreepTumorQueen";NA;197;0
"Building";"CreepTumor";NA;197;0
"Building";"CreepTumor";NA;197;0
"Unit";"Overlord";"Larva";197;0
"Unit";"Overlord";"Larva";197;0
"Unit";"Zergling";"Larva";197;1
"Unit";"Zergling";"Larva";197;1
"Unit";"Zergling";"Larva";197;1
"Unit";"Zergling";"Larva";197;1
"Unit";"Zergling";"Larva";197;1
"Unit";"Zergling";"Larva";197;1
"Unit";"Queen";"Hatchery";181;2
"Unit";"Zergling";"Larva";197;1
"Unit";"Zergling";"Larva";197;1
"Unit";"Zergling";"Larva";197;1
"Unit";"Zergling";"Larva";197;1
"Unit";"Zergling";"Larva";197;1
"Unit";"Zergling";"Larva";197;1
"Unit";"Zergling";"Larva";197;1
"Unit";"Zergling";"Larva";197;1
"Unit";"Zergling";"Larva";197;1
"Unit";"Zergling";"Larva";197;1
"Unit";"Zergling";"Larva";197;1
"Unit";"Zergling";"Larva";197;1
"Unit";"Zergling";"Larva";197;1
"Unit";"Zergling";"Larva";197;1
"Unit";"Zergling";"Larva";197;1
"Unit";"Zergling";"Larva";197;1
"Building";"InfestationPit";NA;181;0
"Upgrade";"ZergGroundArmorsLevel1";"EvolutionChamber";164;0
"Unit";"Baneling";"Zergling";222;0
"Unit";"Baneling";"Zergling";222;0
"Unit";"Baneling";"Zergling";222;0
"Unit";"Baneling";"Zergling";222;0
"Unit";"Baneling";"Zergling";222;0
"Unit";"Baneling";"Zergling";222;0
"Unit";"Baneling";"Zergling";222;0
"Upgrade";"EvolveGroovedSpines";"HydraliskDen";181;0
"Unit";"Baneling";"Zergling";222;0
"Unit";"Baneling";"Zergling";222;0
"Unit";"Zergling";"Larva";222;1
"Unit";"Zergling";"Larva";222;1
"Unit";"Zergling";"Larva";222;1
"Unit";"Zergling";"Larva";222;1
"Unit";"Zergling";"Larva";222;1
"Unit";"Zergling";"Larva";222;1
"Unit";"Zergling";"Larva";222;1
"Unit";"Zergling";"Larva";222;1
"Unit";"Zergling";"Larva";222;1
"Unit";"Zergling";"Larva";222;1
"Unit";"Zergling";"Larva";222;1
"Unit";"Zergling";"Larva";222;1
"Unit";"Zergling";"Larva";222;1
"Unit";"Zergling";"Larva";222;1
"Unit";"Hydralisk";"Larva";222;2
"Unit";"Hydralisk";"Larva";222;2
"Unit";"Hydralisk";"Larva";222;2
"Unit";"Hydralisk";"Larva";222;2
"Unit";"Hydralisk";"Larva";222;2
"Unit";"Hydralisk";"Larva";222;2
"Unit";"Hydralisk";"Larva";222;2
"Unit";"Zergling";"Larva";222;1
"Unit";"Zergling";"Larva";222;1
"Unit";"Zergling";"Larva";222;1
"Unit";"Zergling";"Larva";222;1
"Unit";"Zergling";"Larva";222;1
"Unit";"Zergling";"Larva";222;1
"Unit";"Zergling";"Larva";222;1
"Unit";"Zergling";"Larva";222;1
"Unit";"Zergling";"Larva";222;1
"Unit";"Zergling";"Larva";222;1
"Unit";"Zergling";"Larva";222;1
"Unit";"Zergling";"Larva";222;1
"Upgrade";"ZergMeleeWeaponsLevel1";"EvolutionChamber";179;0
"Unit";"Zergling";"Larva";250;1
"Unit";"Zergling";"Larva";250;1
"Unit";"Zergling";"Larva";250;1
"Unit";"Zergling";"Larva";250;1
"Unit";"Zergling";"Larva";250;1
"Unit";"Zergling";"Larva";250;1
"Unit";"Zergling";"Larva";250;1
"Unit";"Zergling";"Larva";250;1
"Building";"CreepTumor";NA;262;0
"Building";"CreepTumor";NA;262;0
"Building";"CreepTumor";NA;262;0
"Building";"CreepTumor";NA;264;0
"Building";"CreepTumor";NA;264;0
"Building";"CreepTumor";NA;264;0
"Building";"CreepTumor";NA;270;0
"Building";"CreepTumor";NA;270;0
"Unit";"Hydralisk";"Larva";262;2
"Unit";"Hydralisk";"Larva";262;2
"Unit";"Hydralisk";"Larva";262;2
"Building";"CreepTumor";NA;270;0
"Building";"CreepTumor";NA;270;0
"Building";"CreepTumor";NA;270;0
"Building";"CreepTumor";NA;270;0
"Building";"CreepTumor";NA;270;0
"Building";"CreepTumor";NA;270;0
"Unit";"Queen";"Hatchery";262;2
"Unit";"Queen";"Hatchery";262;2
"Building";"CreepTumor";NA;276;0
"Building";"CreepTumor";NA;276;0
"Building";"CreepTumor";NA;276;0
"Building";"CreepTumor";NA;276;0
"Building";"CreepTumor";NA;276;0
"Building";"CreepTumor";NA;276;0
"Unit";"Hydralisk";"Larva";276;2
"Unit";"Hydralisk";"Larva";276;2
"Unit";"Hydralisk";"Larva";276;2
"Unit";"Hydralisk";"Larva";276;2
"Unit";"Hydralisk";"Larva";276;2
"Unit";"Hydralisk";"Larva";276;2
"Unit";"Hydralisk";"Larva";276;2
"Building";"CreepTumor";NA;280;0
"Upgrade";"EvolveMuscularAugments";"HydraliskDen";262;0
"Unit";"Queen";"Hatchery";270;2
"Unit";"Zergling";"Larva";280;1
"Unit";"Zergling";"Larva";280;1
"Unit";"Zergling";"Larva";280;1
"Unit";"Zergling";"Larva";280;1
"Unit";"Zergling";"Larva";280;1
"Unit";"Zergling";"Larva";280;1
"Unit";"Zergling";"Larva";280;1
"Unit";"Zergling";"Larva";280;1
"Unit";"Zergling";"Larva";280;1
"Unit";"Zergling";"Larva";280;1
"Unit";"Zergling";"Larva";280;1
"Unit";"Zergling";"Larva";280;1
"Unit";"Zergling";"Larva";280;1
"Unit";"Zergling";"Larva";280;1
"Unit";"Zergling";"Larva";280;1
"Unit";"Zergling";"Larva";280;1
"Unit";"Baneling";"Zergling";280;0
"Unit";"Baneling";"Zergling";280;0
"Unit";"Baneling";"Zergling";280;0
"Unit";"Baneling";"Zergling";280;0
"Unit";"Baneling";"Zergling";280;0
"Unit";"Baneling";"Zergling";280;0
"Unit";"Baneling";"Zergling";280;0
"Unit";"Baneling";"Zergling";280;0
"Unit";"Baneling";"Zergling";280;0
"Unit";"Hydralisk";"Larva";280;2
"Unit";"Hydralisk";"Larva";280;2
"Unit";"Hydralisk";"Larva";280;2
"Unit";"Hydralisk";"Larva";280;2
"Building";"Extractor";NA;304;0
"Unit";"Zergling";"Larva";320;1
"Unit";"Zergling";"Larva";320;1
"Unit";"Zergling";"Larva";320;1
"Unit";"Zergling";"Larva";320;1
"Unit";"Zergling";"Larva";320;1
"Unit";"Zergling";"Larva";320;1
"Unit";"Zergling";"Larva";320;1
"Unit";"Zergling";"Larva";320;1
"Unit";"Zergling";"Larva";320;1
"Unit";"Zergling";"Larva";320;1
"Unit";"Zergling";"Larva";320;1
"Unit";"Zergling";"Larva";320;1
"Unit";"Zergling";"Larva";320;1
"Unit";"Zergling";"Larva";320;1
"Building";"Extractor";NA;312;0
"Unit";"Viper";"Larva";296;3
"Unit";"Zergling";"Larva";343;1
"Unit";"Zergling";"Larva";343;1
"Unit";"Zergling";"Larva";343;1
"Unit";"Zergling";"Larva";343;1
"Unit";"Zergling";"Larva";343;1
"Unit";"Zergling";"Larva";343;1
"Unit";"Zergling";"Larva";343;1
"Unit";"Zergling";"Larva";343;1
"Unit";"Zergling";"Larva";343;1
"Unit";"Zergling";"Larva";343;1
"Unit";"Zergling";"Larva";343;1
"Unit";"Zergling";"Larva";343;1
"Unit";"Zergling";"Larva";343;1
"Unit";"Zergling";"Larva";343;1
"Unit";"Hydralisk";"Larva";340;2
"Unit";"Hydralisk";"Larva";340;2
"Unit";"Hydralisk";"Larva";340;2
"Unit";"Hydralisk";"Larva";340;2
"Unit";"Hydralisk";"Larva";340;2
"Unit";"Hydralisk";"Larva";340;2
"Unit";"Zergling";"Larva";343;1
"Unit";"Zergling";"Larva";343;1
"Unit";"Zergling";"Larva";343;1
"Unit";"Zergling";"Larva";343;1
"Unit";"Zergling";"Larva";343;1
"Unit";"Zergling";"Larva";343;1
"Unit";"Zergling";"Larva";343;1
"Unit";"Zergling";"Larva";343;1
"Unit";"Zergling";"Larva";343;1
"Unit";"Zergling";"Larva";343;1
"Upgrade";"ZergGroundArmorsLevel2";"EvolutionChamber";276;0
"Unit";"Zergling";"Larva";379;1
"Unit";"Zergling";"Larva";379;1
"Unit";"Zergling";"Larva";379;1
"Unit";"Zergling";"Larva";379;1
"Unit";"Zergling";"Larva";379;1
"Unit";"Zergling";"Larva";379;1
"Unit";"Zergling";"Larva";379;1
"Unit";"Zergling";"Larva";379;1
"Unit";"Zergling";"Larva";379;1
"Unit";"Zergling";"Larva";379;1
"Unit";"Zergling";"Larva";379;1
"Unit";"Zergling";"Larva";379;1
"Unit";"Zergling";"Larva";379;1
"Unit";"Zergling";"Larva";379;1
"Unit";"Zergling";"Larva";379;1
"Unit";"Zergling";"Larva";379;1
"Unit";"Zergling";"Larva";379;1
"Unit";"Zergling";"Larva";379;1
"Unit";"Zergling";"Larva";379;1
"Unit";"Zergling";"Larva";379;1
"Unit";"Zergling";"Larva";379;1
"Unit";"Zergling";"Larva";379;1
"Unit";"Viper";"Larva";343;3
"Unit";"Viper";"Larva";345;3
"Unit";"Viper";"Larva";379;3
"Unit";"Zergling";"Larva";407;1
"Unit";"Zergling";"Larva";407;1
"Unit";"Zergling";"Larva";407;1
"Unit";"Zergling";"Larva";407;1
"Unit";"Zergling";"Larva";407;1
"Unit";"Zergling";"Larva";407;1
"Unit";"Zergling";"Larva";407;1
"Unit";"Zergling";"Larva";407;1
"Unit";"Zergling";"Larva";407;1
"Unit";"Zergling";"Larva";407;1
"Unit";"Zergling";"Larva";407;1
"Unit";"Zergling";"Larva";407;1
"Unit";"Zergling";"Larva";407;1
"Unit";"Zergling";"Larva";407;1
"Unit";"Zergling";"Larva";407;1
"Unit";"Zergling";"Larva";407;1
"Unit";"Zergling";"Larva";407;1
"Unit";"Zergling";"Larva";407;1
"Unit";"Zergling";"Larva";407;1
"Unit";"Zergling";"Larva";407;1
"Unit";"Zergling";"Larva";407;1
"Unit";"Zergling";"Larva";407;1
"Unit";"Zergling";"Larva";407;1
"Unit";"Zergling";"Larva";407;1
"Unit";"Zergling";"Larva";407;1
"Unit";"Zergling";"Larva";407;1
"Unit";"Zergling";"Larva";407;1
"Unit";"Zergling";"Larva";407;1
"Unit";"Zergling";"Larva";407;1
"Unit";"Zergling";"Larva";407;1
"Unit";"Zergling";"Larva";407;1
"Unit";"Zergling";"Larva";407;1
"Unit";"Zergling";"Larva";407;1
"Unit";"Zergling";"Larva";407;1
"Unit";"Zergling";"Larva";407;1
"Unit";"Zergling";"Larva";407;1
"Unit";"Zergling";"Larva";407;1
"Unit";"Zergling";"Larva";407;1
"Upgrade";"ZergMeleeWeaponsLevel2";"EvolutionChamber";320;0
"Unit";"Zergling";"Larva";410;1
"Unit";"Zergling";"Larva";410;1
"Unit";"Zergling";"Larva";410;1
"Unit";"Zergling";"Larva";410;1
"Unit";"Zergling";"Larva";410;1
"Unit";"Zergling";"Larva";410;1
"Unit";"Queen";"Hatchery";410;2
"Unit";"Queen";"Hatchery";410;2
"Unit";"Queen";"Hatchery";410;2
"Unit";"Queen";"Hatchery";410;2
"Unit";"Zergling";"Larva";448;1
"Unit";"Zergling";"Larva";448;1
"Unit";"Zergling";"Larva";448;1
"Unit";"Zergling";"Larva";448;1
"Unit";"Zergling";"Larva";448;1
"Unit";"Zergling";"Larva";448;1
"Unit";"Zergling";"Larva";448;1
"Unit";"Zergling";"Larva";448;1
"Unit";"Zergling";"Larva";448;1
"Unit";"Zergling";"Larva";448;1
"Unit";"Zergling";"Larva";448;1
"Unit";"Zergling";"Larva";448;1
"Unit";"Zergling";"Larva";448;1
"Unit";"Zergling";"Larva";448;1
"Building";"CreepTumorQueen";NA;454;0
"Building";"CreepTumorQueen";NA;454;0
"Building";"CreepTumorQueen";NA;454;0
"Building";"CreepTumor";NA;462;0
"Building";"CreepTumor";NA;462;0
"Building";"CreepTumor";NA;462;0
"Building";"CreepTumor";NA;476;0
"Building";"CreepTumor";NA;476;0
"Building";"SporeCrawler";NA;462;0
"Unit";"Queen";"Hatchery";454;2
"Building";"CreepTumor";NA;476;0
"Building";"CreepTumor";NA;476;0
"Building";"CreepTumor";NA;476;0
"Building";"CreepTumor";NA;476;0
"Building";"CreepTumor";NA;476;0
"Building";"CreepTumor";NA;476;0
"Building";"CreepTumor";NA;476;0
"Building";"CreepTumor";NA;476;0
"Building";"Extractor";NA;476;0
"Building";"Extractor";NA;476;0
"Unit";"Zergling";"Larva";478;1
"Unit";"Zergling";"Larva";478;1
"Unit";"Zergling";"Larva";478;1
"Unit";"Zergling";"Larva";478;1
"Unit";"Zergling";"Larva";478;1
"Unit";"Zergling";"Larva";478;1
"Unit";"Zergling";"Larva";478;1
"Unit";"Zergling";"Larva";478;1
"Unit";"Zergling";"Larva";478;1
"Unit";"Zergling";"Larva";478;1
"Unit";"Zergling";"Larva";478;1
"Unit";"Zergling";"Larva";478;1
"Unit";"Zergling";"Larva";478;1
"Unit";"Zergling";"Larva";478;1
"Unit";"Zergling";"Larva";478;1
"Unit";"Zergling";"Larva";478;1
"Unit";"Zergling";"Larva";478;1
"Unit";"Zergling";"Larva";478;1
"Unit";"Zergling";"Larva";478;1
"Unit";"Zergling";"Larva";478;1
"Unit";"Zergling";"Larva";478;1
"Unit";"Zergling";"Larva";478;1
"Unit";"Zergling";"Larva";478;1
"Unit";"Zergling";"Larva";478;1
"Unit";"Zergling";"Larva";478;1
"Unit";"Zergling";"Larva";478;1
"Unit";"Zergling";"Larva";478;1
"Unit";"Zergling";"Larva";478;1
"Building";"CreepTumor";NA;478;0
"Unit";"Zergling";"Larva";478;1
"Unit";"Zergling";"Larva";478;1
"Unit";"Zergling";"Larva";478;1
"Unit";"Zergling";"Larva";478;1
"Unit";"Zergling";"Larva";478;1
"Unit";"Zergling";"Larva";478;1
"Unit";"Zergling";"Larva";478;1
"Unit";"Zergling";"Larva";478;1
"Building";"CreepTumor";NA;478;0
"Building";"CreepTumor";NA;478;0
"Building";"CreepTumor";NA;478;0
"Building";"CreepTumor";NA;478;0
"Building";"CreepTumor";NA;478;0
"Unit";"Viper";"Larva";478;3
"Building";"CreepTumor";NA;478;0
"Building";"CreepTumor";NA;478;0
"Building";"CreepTumor";NA;478;0
"Building";"CreepTumor";NA;478;0
"Unit";"Overlord";"Larva";514;0
"Unit";"Overlord";"Larva";514;0
"Unit";"Overlord";"Larva";514;0
"Unit";"Overlord";"Larva";514;0
"Unit";"Baneling";"Zergling";517;0
"Unit";"Baneling";"Zergling";517;0
"Unit";"Baneling";"Zergling";517;0
"Unit";"Baneling";"Zergling";517;0
"Unit";"Baneling";"Zergling";517;0
"Unit";"Baneling";"Zergling";517;0
"Unit";"Baneling";"Zergling";517;0
"Unit";"Baneling";"Zergling";517;0
"Unit";"Baneling";"Zergling";517;0
"Unit";"Baneling";"Zergling";517;0
"Unit";"Baneling";"Zergling";517;0
"Unit";"Baneling";"Zergling";517;0
"Unit";"Baneling";"Zergling";517;0
"Unit";"Baneling";"Zergling";517;0
"Building";"Spire";NA;476;0
"Building";"SpineCrawler";NA;514;0
"Building";"Hatchery";NA;476;0
"Building";"CreepTumor";NA;520;0
"Building";"CreepTumor";NA;520;0
"Building";"CreepTumorQueen";NA;520;0
"Building";"CreepTumor";NA;520;0
"Building";"CreepTumorQueen";NA;520;0
"Building";"CreepTumor";NA;520;0
"Building";"CreepTumor";NA;520;0
"Building";"CreepTumor";NA;520;0
"Building";"CreepTumor";NA;520;0
"Building";"CreepTumor";NA;520;0
"Building";"CreepTumor";NA;520;0
"Building";"CreepTumor";NA;520;0
"Building";"CreepTumor";NA;520;0
"Building";"CreepTumor";NA;520;0
"Building";"CreepTumor";NA;520;0
"Unit";"Corruptor";"Larva";520;2
"Unit";"Corruptor";"Larva";520;2
"Unit";"Corruptor";"Larva";520;2
"Unit";"Corruptor";"Larva";520;2
"Unit";"Corruptor";"Larva";520;2
"Unit";"Corruptor";"Larva";520;2
"Upgrade";"ZergGroundArmorsLevel3";"EvolutionChamber";476;0
"Building";"CreepTumor";NA;520;0
"Building";"CreepTumorQueen";NA;532;0
"Unit";"Corruptor";"Larva";520;2
"Unit";"Corruptor";"Larva";520;2
"Upgrade";"ZergMeleeWeaponsLevel3";"EvolutionChamber";478;0
"Building";"UltraliskCavern";NA;520;0
"Unit";"Hydralisk";"Larva";532;2
"Unit";"Hydralisk";"Larva";532;2
"Unit";"Hydralisk";"Larva";532;2
"Unit";"Hydralisk";"Larva";532;2
"Unit";"Hydralisk";"Larva";532;2
"Unit";"Zergling";"Larva";536;1
"Unit";"Zergling";"Larva";536;1
"Unit";"Zergling";"Larva";536;1
"Unit";"Zergling";"Larva";536;1
"Unit";"Zergling";"Larva";536;1
"Unit";"Zergling";"Larva";536;1
"Unit";"Zergling";"Larva";536;1
"Unit";"Zergling";"Larva";536;1
"Unit";"Zergling";"Larva";536;1
"Unit";"Zergling";"Larva";536;1
"Unit";"Zergling";"Larva";536;1
"Unit";"Zergling";"Larva";536;1
"Unit";"Zergling";"Larva";536;1
"Unit";"Zergling";"Larva";536;1
"Unit";"Zergling";"Larva";536;1
"Unit";"Zergling";"Larva";536;1
"Unit";"Zergling";"Larva";536;1
"Unit";"Zergling";"Larva";536;1
"Unit";"Zergling";"Larva";536;1
"Unit";"Zergling";"Larva";536;1
"Unit";"Zergling";"Larva";536;1
"Unit";"Zergling";"Larva";536;1
"Unit";"Zergling";"Larva";546;1
"Unit";"Zergling";"Larva";546;1
"Unit";"Zergling";"Larva";546;1
"Unit";"Zergling";"Larva";546;1
"Unit";"Zergling";"Larva";546;1
"Unit";"Zergling";"Larva";546;1
"Unit";"Zergling";"Larva";546;1
"Unit";"Zergling";"Larva";546;1
"Unit";"Zergling";"Larva";546;1
"Unit";"Zergling";"Larva";546;1
"Unit";"Zergling";"Larva";546;1
"Unit";"Zergling";"Larva";546;1
"Unit";"Zergling";"Larva";546;1
"Unit";"Zergling";"Larva";546;1
"Unit";"Zergling";"Larva";546;1
"Unit";"Zergling";"Larva";546;1
"Unit";"Zergling";"Larva";546;1
"Unit";"Zergling";"Larva";546;1
"Unit";"Corruptor";"Larva";546;2
"Unit";"Corruptor";"Larva";546;2
"Unit";"Corruptor";"Larva";546;2
"Building";"CreepTumor";NA;568;0
"Unit";"Zergling";"Larva";568;1
"Unit";"Zergling";"Larva";568;1
"Unit";"Zergling";"Larva";568;1
"Unit";"Zergling";"Larva";568;1
"Unit";"Zergling";"Larva";568;1
"Unit";"Zergling";"Larva";568;1
"Unit";"Zergling";"Larva";568;1
"Unit";"Zergling";"Larva";568;1
"Unit";"Zergling";"Larva";568;1
"Unit";"Zergling";"Larva";568;1
"Unit";"Zergling";"Larva";568;1
"Unit";"Zergling";"Larva";568;1
"Building";"CreepTumor";NA;592;0
"Building";"CreepTumor";NA;592;0
"Building";"CreepTumor";NA;592;0
"Building";"CreepTumor";NA;598;0
