"type";"unit_name";"on_building";"total_supply";"supply"
"Unit";"Overlord";"Larva";13;0
"Building";"Extractor";NA;17;0
"Building";"SpawningPool";NA;18;0
"Building";"Hatchery";NA;16;0
"Unit";"Overlord";"Larva";22;0
"Unit";"Zergling";"Larva";23;1
"Unit";"Zergling";"Larva";23;1
"Unit";"Queen";"Hatchery";23;2
"Unit";"Queen";"Hatchery";23;2
"Building";"CreepTumorQueen";NA;34;0
"Unit";"Overlord";"Larva";34;0
"Unit";"Overlord";"Larva";34;0
"Unit";"Queen";"Hatchery";34;2
"Building";"CreepTumor";NA;46;0
"Building";"CreepTumorQueen";NA;47;0
"Unit";"Overlord";"Larva";47;0
"Building";"CreepTumor";NA;50;0
"Building";"CreepTumorQueen";NA;53;0
"Building";"CreepTumor";NA;53;0
"Building";"Extractor";NA;49;0
"Unit";"Queen";"Hatchery";47;2
"Unit";"Queen";"Hatchery";47;2
"Unit";"Zergling";"Larva";53;1
"Unit";"Zergling";"Larva";53;1
"Building";"EvolutionChamber";NA;50;0
"Unit";"Zergling";"Larva";53;1
"Unit";"Zergling";"Larva";53;1
"Unit";"Zergling";"Larva";53;1
"Unit";"Zergling";"Larva";53;1
"Building";"EvolutionChamber";NA;50;0
"Unit";"Overlord";"Larva";53;0
"Building";"Hatchery";NA;38;0
"Building";"CreepTumorQueen";NA;59;0
"Unit";"Zergling";"Larva";55;1
"Unit";"Zergling";"Larva";55;1
"Unit";"Zergling";"Larva";59;1
"Unit";"Zergling";"Larva";59;1
"Unit";"Zergling";"Larva";59;1
"Unit";"Zergling";"Larva";59;1
"Unit";"Zergling";"Larva";59;1
"Unit";"Zergling";"Larva";59;1
"Unit";"Zergling";"Larva";59;1
"Unit";"Zergling";"Larva";59;1
"Unit";"Zergling";"Larva";59;1
"Unit";"Zergling";"Larva";59;1
"Building";"CreepTumor";NA;65;0
"Building";"CreepTumor";NA;65;0
"Unit";"Zergling";"Larva";65;1
"Unit";"Zergling";"Larva";65;1
"Unit";"Zergling";"Larva";65;1
"Unit";"Zergling";"Larva";65;1
"Unit";"Zergling";"Larva";65;1
"Unit";"Zergling";"Larva";65;1
"Unit";"Zergling";"Larva";65;1
"Unit";"Zergling";"Larva";65;1
"Building";"CreepTumorQueen";NA;77;0
"Unit";"Overlord";"Larva";77;0
"Building";"CreepTumor";NA;85;0
"Unit";"Overlord";"Larva";85;0
"Building";"Extractor";NA;85;0
"Unit";"Zergling";"Larva";85;1
"Unit";"Zergling";"Larva";85;1
"Unit";"Zergling";"Larva";85;1
"Unit";"Zergling";"Larva";85;1
"Unit";"Zergling";"Larva";85;1
"Unit";"Zergling";"Larva";85;1
"Building";"CreepTumor";NA;99;0
"Building";"CreepTumor";NA;99;0
"Building";"CreepTumorQueen";NA;99;0
"Unit";"Zergling";"Larva";99;1
"Unit";"Zergling";"Larva";99;1
"Unit";"Overlord";"Larva";93;0
"Unit";"Zergling";"Larva";99;1
"Unit";"Zergling";"Larva";99;1
"Unit";"Zergling";"Larva";99;1
"Unit";"Zergling";"Larva";99;1
"Unit";"Zergling";"Larva";99;1
"Unit";"Zergling";"Larva";99;1
"Building";"CreepTumor";NA;99;0
"Building";"CreepTumorQueen";NA;99;0
"Unit";"Overlord";"Larva";99;0
"Building";"BanelingNest";NA;89;0
"Building";"CreepTumorQueen";NA;107;0
"Unit";"Overlord";"Larva";113;0
"Building";"CreepTumorQueen";NA;119;0
"Building";"CreepTumor";NA;119;0
"Building";"CreepTumorQueen";NA;119;0
"Building";"CreepTumor";NA;119;0
"Building";"CreepTumor";NA;119;0
"Building";"CreepTumor";NA;119;0
"Building";"CreepTumor";NA;122;0
"Unit";"Overlord";"Larva";122;0
"Building";"CreepTumorQueen";NA;125;0
"Building";"CreepTumor";NA;125;0
"Building";"CreepTumor";NA;126;0
"Upgrade";"ZergMeleeWeaponsLevel1";"EvolutionChamber";93;0
"Building";"CreepTumor";NA;126;0
"Building";"SporeCrawler";NA;124;0
"Unit";"Overlord";"Larva";127;0
"Upgrade";"ZergGroundArmorsLevel1";"EvolutionChamber";99;0
"Unit";"Overlord";"Larva";132;0
"Building";"CreepTumor";NA;132;0
"Unit";"Overlord";"Larva";137;0
"Building";"Extractor";NA;137;0
"Building";"Hatchery";NA;124;0
"Building";"Extractor";NA;139;0
"Building";"CreepTumor";NA;141;0
"Building";"Extractor";NA;141;0
"Building";"CreepTumor";NA;141;0
"Building";"CreepTumorQueen";NA;141;0
"Building";"CreepTumor";NA;141;0
"Building";"CreepTumor";NA;141;0
"Building";"CreepTumor";NA;142;0
"Building";"CreepTumor";NA;144;0
"Upgrade";"Burrow";"Hatchery";137;0
"Building";"CreepTumor";NA;150;0
"Building";"CreepTumor";NA;150;0
"Building";"CreepTumorQueen";NA;150;0
"Building";"CreepTumor";NA;150;0
"Building";"CreepTumorQueen";NA;150;0
"Building";"CreepTumor";NA;150;0
"Unit";"Zergling";"Larva";150;1
"Unit";"Zergling";"Larva";150;1
"Unit";"Overlord";"Larva";150;0
"Unit";"Zergling";"Larva";150;1
"Unit";"Zergling";"Larva";150;1
"Unit";"Zergling";"Larva";150;1
"Unit";"Zergling";"Larva";150;1
"Unit";"Zergling";"Larva";150;1
"Unit";"Zergling";"Larva";150;1
"Unit";"Zergling";"Larva";150;1
"Unit";"Zergling";"Larva";150;1
"Building";"CreepTumorQueen";NA;150;0
"Unit";"Zergling";"Larva";150;1
"Unit";"Zergling";"Larva";150;1
"Unit";"Zergling";"Larva";150;1
"Unit";"Zergling";"Larva";150;1
"Unit";"Zergling";"Larva";150;1
"Unit";"Zergling";"Larva";150;1
"Unit";"Zergling";"Larva";150;1
"Unit";"Zergling";"Larva";150;1
"Unit";"Zergling";"Larva";150;1
"Unit";"Zergling";"Larva";150;1
"Building";"InfestationPit";NA;141;0
"Building";"CreepTumor";NA;150;0
"Unit";"Zergling";"Larva";150;1
"Unit";"Zergling";"Larva";150;1
"Unit";"Zergling";"Larva";150;1
"Unit";"Zergling";"Larva";150;1
"Unit";"Zergling";"Larva";150;1
"Unit";"Zergling";"Larva";150;1
"Unit";"Zergling";"Larva";150;1
"Unit";"Zergling";"Larva";150;1
"Unit";"Zergling";"Larva";150;1
"Unit";"Zergling";"Larva";150;1
"Building";"CreepTumor";NA;170;0
"Unit";"Overlord";"Larva";150;0
"Building";"CreepTumor";NA;170;0
"Building";"CreepTumor";NA;170;0
"Building";"CreepTumor";NA;170;0
"Building";"CreepTumor";NA;170;0
"Unit";"Zergling";"Larva";170;1
"Unit";"Zergling";"Larva";170;1
"Unit";"Zergling";"Larva";170;1
"Unit";"Zergling";"Larva";170;1
"Unit";"Zergling";"Larva";170;1
"Unit";"Zergling";"Larva";170;1
"Building";"CreepTumor";NA;185;0
"Building";"CreepTumor";NA;185;0
"Building";"Extractor";NA;170;0
"Unit";"Zergling";"Larva";176;1
"Unit";"Zergling";"Larva";176;1
"Unit";"Zergling";"Larva";180;1
"Unit";"Zergling";"Larva";180;1
"Unit";"Overlord";"Larva";192;0
"Unit";"Overlord";"Larva";196;0
"Building";"CreepTumor";NA;196;0
"Building";"CreepTumor";NA;196;0
"Unit";"Zergling";"Larva";196;1
"Unit";"Zergling";"Larva";196;1
"Unit";"Overlord";"Larva";196;0
"Unit";"Zergling";"Larva";196;1
"Unit";"Zergling";"Larva";196;1
"Unit";"Zergling";"Larva";196;1
"Unit";"Zergling";"Larva";196;1
"Unit";"Zergling";"Larva";196;1
"Unit";"Zergling";"Larva";196;1
"Unit";"Zergling";"Larva";196;1
"Unit";"Zergling";"Larva";196;1
"Unit";"Zergling";"Larva";196;1
"Unit";"Zergling";"Larva";196;1
"Unit";"Zergling";"Larva";196;1
"Unit";"Zergling";"Larva";196;1
"Unit";"Zergling";"Larva";196;1
"Unit";"Zergling";"Larva";196;1
"Unit";"Zergling";"Larva";196;1
"Unit";"Zergling";"Larva";196;1
"Unit";"Zergling";"Larva";196;1
"Unit";"Zergling";"Larva";196;1
"Unit";"Zergling";"Larva";196;1
"Unit";"Zergling";"Larva";196;1
"Unit";"Zergling";"Larva";196;1
"Unit";"Zergling";"Larva";196;1
"Building";"SporeCrawler";NA;196;0
"Building";"CreepTumor";NA;196;0
"Building";"CreepTumor";NA;196;0
"Building";"CreepTumor";NA;196;0
"Building";"CreepTumor";NA;196;0
"Unit";"Baneling";"Zergling";196;0
"Unit";"Baneling";"Zergling";196;0
"Unit";"Baneling";"Zergling";196;0
"Unit";"Baneling";"Zergling";196;0
"Unit";"Baneling";"Zergling";196;0
"Unit";"Baneling";"Zergling";196;0
"Unit";"Baneling";"Zergling";196;0
"Unit";"Baneling";"Zergling";196;0
"Unit";"Baneling";"Zergling";196;0
"Unit";"Baneling";"Zergling";196;0
"Unit";"Baneling";"Zergling";196;0
"Unit";"Baneling";"Zergling";196;0
"Unit";"Baneling";"Zergling";196;0
"Unit";"Baneling";"Zergling";196;0
"Unit";"Baneling";"Zergling";196;0
"Unit";"Baneling";"Zergling";196;0
"Unit";"Baneling";"Zergling";196;0
"Unit";"Baneling";"Zergling";196;0
"Unit";"Baneling";"Zergling";196;0
"Unit";"Baneling";"Zergling";196;0
"Unit";"Baneling";"Zergling";196;0
"Unit";"Baneling";"Zergling";196;0
"Unit";"Baneling";"Zergling";196;0
"Unit";"Baneling";"Zergling";196;0
"Unit";"Baneling";"Zergling";196;0
"Unit";"Baneling";"Zergling";196;0
"Unit";"Baneling";"Zergling";196;0
"Unit";"Zergling";"Larva";196;1
"Unit";"Zergling";"Larva";196;1
"Unit";"Overlord";"Larva";196;0
"Unit";"Zergling";"Larva";196;1
"Unit";"Zergling";"Larva";196;1
"Unit";"Zergling";"Larva";196;1
"Unit";"Zergling";"Larva";196;1
"Unit";"Zergling";"Larva";196;1
"Unit";"Zergling";"Larva";196;1
"Unit";"Zergling";"Larva";196;1
"Unit";"Zergling";"Larva";196;1
"Building";"CreepTumor";NA;220;0
"Unit";"Zergling";"Larva";220;1
"Unit";"Zergling";"Larva";220;1
"Unit";"Overlord";"Larva";220;0
"Unit";"Zergling";"Larva";220;1
"Unit";"Zergling";"Larva";220;1
"Unit";"Zergling";"Larva";220;1
"Unit";"Zergling";"Larva";220;1
"Unit";"Zergling";"Larva";220;1
"Unit";"Zergling";"Larva";220;1
"Unit";"Zergling";"Larva";220;1
"Unit";"Zergling";"Larva";220;1
"Unit";"Zergling";"Larva";220;1
"Unit";"Zergling";"Larva";220;1
"Unit";"Zergling";"Larva";220;1
"Unit";"Zergling";"Larva";220;1
"Unit";"Zergling";"Larva";220;1
"Unit";"Zergling";"Larva";220;1
"Unit";"Zergling";"Larva";220;1
"Unit";"Zergling";"Larva";220;1
"Unit";"Zergling";"Larva";220;1
"Unit";"Zergling";"Larva";220;1
"Upgrade";"ZergGroundArmorsLevel2";"EvolutionChamber";150;0
"Building";"CreepTumor";NA;230;0
"Building";"CreepTumor";NA;230;0
"Building";"CreepTumor";NA;230;0
"Building";"CreepTumorQueen";NA;230;0
"Building";"CreepTumor";NA;230;0
"Building";"CreepTumor";NA;230;0
"Building";"CreepTumor";NA;230;0
"Building";"CreepTumorQueen";NA;250;0
"Building";"CreepTumorQueen";NA;250;0
"Upgrade";"ZergMeleeWeaponsLevel2";"EvolutionChamber";150;0
"Unit";"Zergling";"Larva";250;1
"Unit";"Zergling";"Larva";250;1
"Unit";"Zergling";"Larva";250;1
"Unit";"Zergling";"Larva";250;1
"Unit";"Zergling";"Larva";250;1
"Unit";"Zergling";"Larva";250;1
"Unit";"Zergling";"Larva";250;1
"Unit";"Zergling";"Larva";250;1
"Unit";"Zergling";"Larva";250;1
"Unit";"Zergling";"Larva";250;1
"Unit";"Zergling";"Larva";250;1
"Unit";"Zergling";"Larva";250;1
"Unit";"Zergling";"Larva";250;1
"Unit";"Zergling";"Larva";250;1
"Unit";"Zergling";"Larva";250;1
"Unit";"Zergling";"Larva";250;1
"Unit";"Zergling";"Larva";250;1
"Unit";"Zergling";"Larva";250;1
"Unit";"Zergling";"Larva";250;1
"Unit";"Zergling";"Larva";250;1
"Building";"CreepTumor";NA;250;0
"Building";"CreepTumor";NA;250;0
"Building";"CreepTumor";NA;250;0
"Unit";"Baneling";"Zergling";250;0
"Unit";"Baneling";"Zergling";250;0
"Unit";"Baneling";"Zergling";250;0
"Unit";"Baneling";"Zergling";250;0
"Unit";"Baneling";"Zergling";250;0
"Unit";"Baneling";"Zergling";250;0
"Unit";"Baneling";"Zergling";250;0
"Unit";"Baneling";"Zergling";250;0
"Unit";"Baneling";"Zergling";250;0
"Unit";"Baneling";"Zergling";250;0
"Unit";"Baneling";"Zergling";250;0
"Unit";"Baneling";"Zergling";250;0
"Unit";"Baneling";"Zergling";250;0
"Unit";"Baneling";"Zergling";250;0
"Unit";"Baneling";"Zergling";250;0
"Unit";"Baneling";"Zergling";250;0
"Unit";"Baneling";"Zergling";270;0
"Unit";"Baneling";"Zergling";270;0
"Unit";"Baneling";"Zergling";270;0
"Unit";"Baneling";"Zergling";270;0
"Unit";"Baneling";"Zergling";270;0
"Unit";"Baneling";"Zergling";270;0
"Unit";"Baneling";"Zergling";270;0
"Unit";"Baneling";"Zergling";270;0
"Unit";"Baneling";"Zergling";270;0
"Unit";"Baneling";"Zergling";270;0
"Unit";"Baneling";"Zergling";270;0
"Unit";"Baneling";"Zergling";270;0
"Unit";"Zergling";"Larva";270;1
"Unit";"Zergling";"Larva";270;1
"Unit";"Baneling";"Zergling";270;0
"Unit";"Baneling";"Zergling";270;0
"Unit";"Baneling";"Zergling";270;0
"Unit";"Baneling";"Zergling";270;0
"Unit";"Zergling";"Larva";270;1
"Unit";"Zergling";"Larva";270;1
"Unit";"Zergling";"Larva";270;1
"Unit";"Zergling";"Larva";270;1
"Unit";"Zergling";"Larva";270;1
"Unit";"Zergling";"Larva";270;1
"Unit";"Zergling";"Larva";270;1
"Unit";"Zergling";"Larva";270;1
"Unit";"Zergling";"Larva";270;1
"Unit";"Zergling";"Larva";270;1
"Unit";"Zergling";"Larva";270;1
"Unit";"Zergling";"Larva";270;1
"Unit";"Zergling";"Larva";270;1
"Unit";"Zergling";"Larva";270;1
"Unit";"Zergling";"Larva";270;1
"Unit";"Zergling";"Larva";270;1
"Unit";"Zergling";"Larva";270;1
"Unit";"Zergling";"Larva";270;1
"Unit";"Zergling";"Larva";270;1
"Unit";"Zergling";"Larva";270;1
"Unit";"Zergling";"Larva";270;1
"Unit";"Zergling";"Larva";270;1
"Unit";"Zergling";"Larva";270;1
"Unit";"Zergling";"Larva";270;1
"Building";"UltraliskCavern";NA;250;0
"Building";"Extractor";NA;270;0
"Unit";"Zergling";"Larva";299;1
"Unit";"Zergling";"Larva";299;1
"Unit";"Overlord";"Larva";299;0
"Unit";"Zergling";"Larva";299;1
"Unit";"Zergling";"Larva";299;1
"Unit";"Zergling";"Larva";299;1
"Unit";"Zergling";"Larva";299;1
"Unit";"Zergling";"Larva";299;1
"Unit";"Zergling";"Larva";299;1
"Unit";"Zergling";"Larva";299;1
"Unit";"Zergling";"Larva";299;1
"Unit";"Zergling";"Larva";299;1
"Unit";"Zergling";"Larva";299;1
"Unit";"Zergling";"Larva";299;1
"Unit";"Zergling";"Larva";299;1
"Unit";"Zergling";"Larva";299;1
"Unit";"Zergling";"Larva";299;1
"Unit";"Zergling";"Larva";299;1
"Unit";"Zergling";"Larva";299;1
"Unit";"Zergling";"Larva";299;1
"Unit";"Zergling";"Larva";299;1
"Unit";"Zergling";"Larva";299;1
"Unit";"Zergling";"Larva";299;1
"Unit";"Zergling";"Larva";299;1
"Unit";"Zergling";"Larva";299;1
"Unit";"Zergling";"Larva";299;1
"Unit";"Zergling";"Larva";299;1
"Unit";"Zergling";"Larva";299;1
"Unit";"Zergling";"Larva";299;1
"Unit";"Zergling";"Larva";299;1
"Unit";"Zergling";"Larva";299;1
"Unit";"Zergling";"Larva";299;1
"Unit";"Zergling";"Larva";299;1
"Unit";"Zergling";"Larva";299;1
"Unit";"Zergling";"Larva";299;1
"Building";"CreepTumor";NA;299;0
"Unit";"Infestor";"Larva";299;2
"Unit";"Infestor";"Larva";299;2
"Unit";"Infestor";"Larva";299;2
"Unit";"Infestor";"Larva";299;2
"Unit";"Infestor";"Larva";299;2
"Unit";"Zergling";"Larva";299;1
"Unit";"Zergling";"Larva";299;1
"Unit";"Zergling";"Larva";299;1
"Unit";"Zergling";"Larva";299;1
"Unit";"Zergling";"Larva";299;1
"Unit";"Zergling";"Larva";299;1
"Unit";"Zergling";"Larva";299;1
"Unit";"Zergling";"Larva";299;1
"Unit";"Zergling";"Larva";299;1
"Unit";"Zergling";"Larva";299;1
"Building";"CreepTumor";NA;333;0
"Unit";"Zergling";"Larva";333;1
"Unit";"Zergling";"Larva";333;1
"Unit";"Zergling";"Larva";333;1
"Unit";"Zergling";"Larva";333;1
"Unit";"Zergling";"Larva";333;1
"Unit";"Zergling";"Larva";333;1
"Unit";"Zergling";"Larva";333;1
"Unit";"Zergling";"Larva";333;1
"Unit";"Zergling";"Larva";333;1
"Unit";"Zergling";"Larva";333;1
"Unit";"Zergling";"Larva";333;1
"Unit";"Zergling";"Larva";333;1
"Building";"CreepTumor";NA;353;0
"Building";"CreepTumor";NA;353;0
"Building";"CreepTumor";NA;353;0
"Building";"CreepTumor";NA;353;0
"Unit";"Ultralisk";"Larva";299;6
"Upgrade";"ChitinousPlating";"UltraliskCavern";299;0
"Building";"CreepTumorQueen";NA;365;0
"Building";"CreepTumor";NA;365;0
"Unit";"Ultralisk";"Larva";333;6
"Unit";"Ultralisk";"Larva";333;6
"Building";"CreepTumor";NA;371;0
"Building";"CreepTumor";NA;371;0
"Building";"CreepTumor";NA;371;0
"Building";"CreepTumor";NA;371;0
"Building";"CreepTumor";NA;371;0
"Building";"CreepTumor";NA;383;0
"Unit";"Ultralisk";"Larva";365;6
"Unit";"Ultralisk";"Larva";365;6
"Unit";"Ultralisk";"Larva";365;6
"Building";"CreepTumor";NA;401;0
"Unit";"Ultralisk";"Larva";383;6
"Building";"CreepTumor";NA;401;0
"Building";"Hatchery";NA;353;0
"Building";"CreepTumor";NA;401;0
"Building";"CreepTumor";NA;401;0
"Building";"CreepTumor";NA;407;0
"Building";"SpineCrawler";NA;395;0
"Upgrade";"ZergMeleeWeaponsLevel3";"EvolutionChamber";353;0
"Upgrade";"ZergGroundArmorsLevel3";"EvolutionChamber";353;0
"Building";"Spire";NA;383;0
"Unit";"Zergling";"Larva";413;1
"Unit";"Zergling";"Larva";413;1
"Unit";"Zergling";"Larva";413;1
"Unit";"Zergling";"Larva";413;1
"Unit";"Zergling";"Larva";413;1
"Unit";"Zergling";"Larva";413;1
"Unit";"Zergling";"Larva";413;1
"Unit";"Zergling";"Larva";413;1
"Building";"CreepTumor";NA;413;0
"Building";"CreepTumor";NA;421;0
"Building";"Spire";NA;413;0
"Unit";"Ultralisk";"Larva";413;6
"Unit";"Ultralisk";"Larva";413;6
"Unit";"Corruptor";"Larva";413;2
"Unit";"Corruptor";"Larva";413;2
"Unit";"Corruptor";"Larva";413;2
"Unit";"Corruptor";"Larva";413;2
"Unit";"Corruptor";"Larva";413;2
"Unit";"Zergling";"Larva";421;1
"Unit";"Zergling";"Larva";421;1
"Unit";"Zergling";"Larva";421;1
"Unit";"Zergling";"Larva";421;1
"Unit";"Zergling";"Larva";421;1
"Unit";"Zergling";"Larva";421;1
"Building";"Hatchery";NA;413;0
"Unit";"Zergling";"Larva";421;1
"Unit";"Zergling";"Larva";421;1
"Unit";"Zergling";"Larva";421;1
"Unit";"Zergling";"Larva";421;1
"Unit";"Zergling";"Larva";421;1
"Unit";"Zergling";"Larva";421;1
"Unit";"Zergling";"Larva";421;1
"Unit";"Zergling";"Larva";421;1
"Unit";"Zergling";"Larva";421;1
"Unit";"Zergling";"Larva";421;1
"Unit";"Zergling";"Larva";421;1
"Unit";"Zergling";"Larva";421;1
"Unit";"Zergling";"Larva";421;1
"Unit";"Zergling";"Larva";421;1
"Unit";"Corruptor";"Larva";421;2
"Unit";"Corruptor";"Larva";421;2
"Unit";"Corruptor";"Larva";421;2
"Unit";"Corruptor";"Larva";421;2
"Building";"CreepTumor";NA;463;0
"Building";"CreepTumor";NA;463;0
"Unit";"Infestor";"Larva";421;2
"Unit";"Infestor";"Larva";421;2
"Unit";"Ultralisk";"Larva";421;6
"Unit";"Baneling";"Zergling";463;0
"Unit";"Baneling";"Zergling";463;0
"Unit";"Baneling";"Zergling";463;0
"Unit";"Baneling";"Zergling";463;0
"Building";"CreepTumorQueen";NA;481;0
"Building";"Extractor";NA;481;0
"Building";"Extractor";NA;481;0
"Unit";"Zergling";"Larva";481;1
"Unit";"Zergling";"Larva";481;1
"Unit";"Zergling";"Larva";481;1
"Unit";"Zergling";"Larva";481;1
"Unit";"Zergling";"Larva";481;1
"Unit";"Zergling";"Larva";481;1
"Unit";"Zergling";"Larva";481;1
"Unit";"Zergling";"Larva";481;1
"Unit";"Zergling";"Larva";481;1
"Unit";"Zergling";"Larva";481;1
"Unit";"Zergling";"Larva";481;1
"Unit";"Zergling";"Larva";481;1
"Unit";"Zergling";"Larva";481;1
"Unit";"Zergling";"Larva";481;1
"Unit";"Zergling";"Larva";481;1
"Unit";"Zergling";"Larva";481;1
"Unit";"Zergling";"Larva";481;1
"Unit";"Zergling";"Larva";481;1
"Building";"CreepTumor";NA;499;0
"Building";"Hatchery";NA;475;0
"Building";"CreepTumorQueen";NA;499;0
"Unit";"Ultralisk";"Larva";481;6
"Unit";"Baneling";"Zergling";499;0
"Unit";"Baneling";"Zergling";499;0
"Unit";"Baneling";"Zergling";499;0
"Unit";"Baneling";"Zergling";499;0
"Building";"CreepTumorQueen";NA;499;0
"Building";"CreepTumor";NA;499;0
"Unit";"Corruptor";"Larva";499;2
"Unit";"Corruptor";"Larva";499;2
"Unit";"Corruptor";"Larva";499;2
"Unit";"Corruptor";"Larva";499;2
"Unit";"Infestor";"Larva";499;2
"Unit";"Infestor";"Larva";499;2
"Unit";"Infestor";"Larva";499;2
"Building";"SpineCrawler";NA;513;0
"Building";"SpineCrawler";NA;513;0
"Building";"Hatchery";NA;499;0
"Unit";"Zergling";"Larva";519;1
"Unit";"Zergling";"Larva";519;1
"Unit";"Zergling";"Larva";519;1
"Unit";"Zergling";"Larva";519;1
"Unit";"Zergling";"Larva";519;1
"Unit";"Zergling";"Larva";519;1
"Unit";"Zergling";"Larva";519;1
"Unit";"Zergling";"Larva";519;1
"Unit";"Zergling";"Larva";519;1
"Unit";"Zergling";"Larva";519;1
"Unit";"Corruptor";"Larva";519;2
"Unit";"Corruptor";"Larva";519;2
"Unit";"Ultralisk";"Larva";519;6
"Unit";"Zergling";"Larva";540;1
"Unit";"Zergling";"Larva";540;1
"Unit";"Zergling";"Larva";540;1
"Unit";"Zergling";"Larva";540;1
"Unit";"Zergling";"Larva";540;1
"Unit";"Zergling";"Larva";540;1
"Unit";"Zergling";"Larva";540;1
"Unit";"Zergling";"Larva";540;1
"Unit";"Zergling";"Larva";540;1
"Unit";"Zergling";"Larva";540;1
"Unit";"Ultralisk";"Larva";540;6
"Unit";"Zergling";"Larva";560;1
"Unit";"Zergling";"Larva";560;1
"Unit";"Queen";"Hatchery";550;2
"Unit";"Queen";"Hatchery";550;2
"Unit";"Queen";"Hatchery";550;2
"Unit";"Queen";"Hatchery";550;2
"Unit";"Infestor";"Larva";560;2
"Unit";"Infestor";"Larva";560;2
"Unit";"Infestor";"Larva";560;2
"Unit";"Corruptor";"Larva";560;2
"Unit";"Corruptor";"Larva";560;2
"Unit";"Corruptor";"Larva";560;2
"Unit";"Corruptor";"Larva";560;2
"Unit";"Corruptor";"Larva";560;2
"Unit";"Corruptor";"Larva";560;2
"Unit";"Corruptor";"Larva";560;2
"Building";"Extractor";NA;566;0
"Building";"Extractor";NA;566;0
"Building";"CreepTumor";NA;576;0
"Building";"SpineCrawler";NA;566;0
"Building";"SpineCrawler";NA;568;0
"Unit";"Queen";"Hatchery";572;2
"Unit";"Queen";"Hatchery";574;2
"Building";"CreepTumorQueen";NA;601;0
"Building";"CreepTumorQueen";NA;605;0
"Building";"CreepTumorQueen";NA;605;0
"Building";"CreepTumor";NA;605;0
"Building";"CreepTumorQueen";NA;605;0
"Unit";"Zergling";"Larva";605;1
"Unit";"Zergling";"Larva";605;1
"Unit";"Zergling";"Larva";605;1
"Unit";"Zergling";"Larva";605;1
"Unit";"Zergling";"Larva";605;1
"Unit";"Zergling";"Larva";605;1
"Unit";"Zergling";"Larva";605;1
"Unit";"Zergling";"Larva";605;1
"Building";"CreepTumorQueen";NA;613;0
"Building";"CreepTumorQueen";NA;613;0
"Building";"CreepTumorQueen";NA;613;0
"Unit";"Corruptor";"Larva";613;2
"Building";"CreepTumor";NA;613;0
"Building";"Hatchery";NA;605;0
"Building";"CreepTumor";NA;615;0
"Building";"CreepTumorQueen";NA;615;0
"Unit";"Corruptor";"Larva";613;2
"Unit";"Corruptor";"Larva";613;2
"Building";"CreepTumorQueen";NA;615;0
"Building";"CreepTumor";NA;620;0
"Building";"CreepTumor";NA;620;0
"Unit";"Corruptor";"Larva";620;2
"Building";"CreepTumor";NA;622;0
"Building";"CreepTumor";NA;622;0
"Building";"SporeCrawler";NA;622;0
"Building";"CreepTumorQueen";NA;622;0
"Building";"SporeCrawler";NA;622;0
"Building";"SporeCrawler";NA;622;0
"Building";"SporeCrawler";NA;622;0
"Building";"Extractor";NA;622;0
"Building";"CreepTumor";NA;629;0
"Building";"CreepTumorQueen";NA;629;0
"Building";"SporeCrawler";NA;629;0
"Unit";"Zergling";"Larva";629;1
"Unit";"Zergling";"Larva";629;1
"Building";"Hatchery";NA;622;0
"Building";"Hatchery";NA;622;0
"Unit";"Corruptor";"Larva";634;2
"Unit";"Corruptor";"Larva";634;2
"Unit";"Corruptor";"Larva";634;2
"Building";"CreepTumor";NA;636;0
"Building";"CreepTumor";NA;648;0
"Building";"CreepTumor";NA;648;0
"Building";"CreepTumor";NA;648;0
"Building";"Hatchery";NA;632;0
"Building";"Extractor";NA;648;0
"Building";"SpineCrawler";NA;648;0
"Building";"SpineCrawler";NA;648;0
"Building";"SpineCrawler";NA;648;0
"Unit";"Queen";"Hatchery";648;2
"Unit";"Queen";"Hatchery";648;2
"Unit";"Viper";"Larva";648;3
"Unit";"Viper";"Larva";648;3
"Unit";"Viper";"Larva";648;3
"Unit";"Viper";"Larva";648;3
"Unit";"Viper";"Larva";648;3
"Building";"CreepTumor";NA;670;0
"Building";"CreepTumor";NA;670;0
"Building";"Extractor";NA;670;0
"Building";"CreepTumor";NA;670;0
"Building";"CreepTumor";NA;670;0
"Building";"Extractor";NA;670;0
"Building";"SporeCrawler";NA;670;0
"Building";"SpineCrawler";NA;670;0
"Building";"SporeCrawler";NA;670;0
"Building";"SpineCrawler";NA;670;0
"Building";"Extractor";NA;673;0
"Unit";"Infestor";"Larva";673;2
"Unit";"Infestor";"Larva";673;2
"Unit";"Infestor";"Larva";673;2
"Unit";"Infestor";"Larva";673;2
"Building";"CreepTumor";NA;673;0
"Building";"CreepTumor";NA;681;0
"Unit";"Corruptor";"Larva";681;2
"Unit";"Corruptor";"Larva";681;2
"Unit";"Corruptor";"Larva";681;2
"Unit";"Corruptor";"Larva";681;2
"Unit";"Zergling";"Larva";681;1
"Unit";"Zergling";"Larva";681;1
"Unit";"Zergling";"Larva";681;1
"Unit";"Zergling";"Larva";681;1
"Unit";"Zergling";"Larva";681;1
"Unit";"Zergling";"Larva";681;1
"Unit";"Zergling";"Larva";681;1
"Unit";"Zergling";"Larva";681;1
"Unit";"Zergling";"Larva";681;1
"Unit";"Zergling";"Larva";681;1
"Unit";"Zergling";"Larva";681;1
"Unit";"Zergling";"Larva";681;1
"Building";"Hatchery";NA;673;0
"Building";"SpineCrawler";NA;681;0
"Building";"SpineCrawler";NA;681;0
"Building";"SpineCrawler";NA;681;0
"Unit";"Viper";"Larva";684;3
"Unit";"Viper";"Larva";688;3
"Building";"SpineCrawler";NA;681;0
"Building";"SpineCrawler";NA;681;0
"Building";"SpineCrawler";NA;681;0
"Unit";"Queen";"Hatchery";689;2
"Unit";"Queen";"Hatchery";689;2
"Unit";"Queen";"Hatchery";689;2
"Unit";"Queen";"Hatchery";689;2
"Unit";"Viper";"Larva";709;3
"Unit";"Viper";"Larva";709;3
"Unit";"Viper";"Larva";709;3
"Unit";"Corruptor";"Larva";709;2
"Unit";"Corruptor";"Larva";709;2
"Unit";"Corruptor";"Larva";709;2
"Unit";"Queen";"Hatchery";715;2
"Unit";"Corruptor";"Larva";742;2
"Unit";"Corruptor";"Larva";742;2
"Unit";"Corruptor";"Larva";742;2
"Unit";"Corruptor";"Larva";742;2
"Unit";"Corruptor";"Larva";742;2
"Unit";"Corruptor";"Larva";742;2
"Unit";"Corruptor";"Larva";742;2
"Unit";"Corruptor";"Larva";744;2
"Unit";"Corruptor";"Larva";744;2
"Unit";"Corruptor";"Larva";744;2
"Unit";"Corruptor";"Larva";758;2
"Unit";"Corruptor";"Larva";758;2
"Unit";"Corruptor";"Larva";758;2
"Building";"CreepTumor";NA;770;0
"Building";"CreepTumorQueen";NA;770;0
"Unit";"Queen";"Hatchery";770;2
"Building";"Hatchery";NA;758;0
"Unit";"Queen";"Hatchery";770;2
"Building";"CreepTumorQueen";NA;770;0
"Building";"SporeCrawler";NA;770;0
"Building";"SporeCrawler";NA;770;0
"Building";"SporeCrawler";NA;770;0
"Building";"CreepTumorQueen";NA;778;0
"Building";"CreepTumorQueen";NA;780;0
"Building";"CreepTumorQueen";NA;780;0
"Building";"Hatchery";NA;764;0
"Building";"CreepTumor";NA;780;0
"Building";"SpineCrawler";NA;770;0
"Building";"CreepTumorQueen";NA;780;0
"Unit";"Queen";"Hatchery";770;2
"Unit";"Queen";"Hatchery";770;2
"Building";"CreepTumorQueen";NA;782;0
"Building";"CreepTumorQueen";NA;782;0
"Building";"SporeCrawler";NA;784;0
"Building";"SpineCrawler";NA;784;0
"Building";"SpineCrawler";NA;784;0
"Building";"CreepTumor";NA;787;0
"Building";"CreepTumor";NA;787;0
"Building";"SpineCrawler";NA;784;0
"Building";"CreepTumor";NA;787;0
"Building";"CreepTumor";NA;787;0
"Building";"CreepTumorQueen";NA;787;0
"Building";"CreepTumor";NA;787;0
"Building";"SpineCrawler";NA;787;0
"Building";"SpineCrawler";NA;787;0
"Unit";"Corruptor";"Larva";787;2
"Unit";"Corruptor";"Larva";787;2
"Unit";"Corruptor";"Larva";787;2
"Building";"CreepTumorQueen";NA;793;0
"Building";"CreepTumorQueen";NA;793;0
"Building";"CreepTumorQueen";NA;793;0
"Building";"SpineCrawler";NA;793;0
"Unit";"Infestor";"Larva";793;2
"Unit";"Infestor";"Larva";793;2
"Unit";"Infestor";"Larva";793;2
"Building";"Hatchery";NA;787;0
"Unit";"Corruptor";"Larva";799;2
"Unit";"Corruptor";"Larva";799;2
"Unit";"Corruptor";"Larva";799;2
"Unit";"Corruptor";"Larva";799;2
"Unit";"Corruptor";"Larva";799;2
"Unit";"Corruptor";"Larva";799;2
"Unit";"Corruptor";"Larva";799;2
"Building";"Hatchery";NA;799;0
"Unit";"Corruptor";"Larva";803;2
"Unit";"Corruptor";"Larva";803;2
"Unit";"Corruptor";"Larva";803;2
"Unit";"Corruptor";"Larva";803;2
"Unit";"Corruptor";"Larva";803;2
"Unit";"Corruptor";"Larva";803;2
"Unit";"Corruptor";"Larva";803;2
"Unit";"Corruptor";"Larva";803;2
"Building";"CreepTumorQueen";NA;813;0
"Unit";"Viper";"Larva";813;3
"Unit";"Viper";"Larva";813;3
"Unit";"Viper";"Larva";813;3
"Unit";"Corruptor";"Larva";829;2
"Unit";"Corruptor";"Larva";829;2
"Unit";"Corruptor";"Larva";829;2
"Building";"CreepTumor";NA;838;0
"Unit";"Queen";"Hatchery";838;2
"Unit";"Queen";"Hatchery";838;2
"Unit";"Queen";"Hatchery";838;2
"Building";"CreepTumor";NA;850;0
"Unit";"Corruptor";"Larva";844;2
"Unit";"Corruptor";"Larva";844;2
"Unit";"Corruptor";"Larva";844;2
"Unit";"Corruptor";"Larva";844;2
"Unit";"Corruptor";"Larva";846;2
"Unit";"Corruptor";"Larva";848;2
"Unit";"Corruptor";"Larva";850;2
"Unit";"Corruptor";"Larva";850;2
"Unit";"Corruptor";"Larva";850;2
"Unit";"Corruptor";"Larva";850;2
"Unit";"Corruptor";"Larva";850;2
"Unit";"Corruptor";"Larva";850;2
"Unit";"Corruptor";"Larva";850;2
"Unit";"Viper";"Larva";850;3
"Unit";"Viper";"Larva";850;3
"Unit";"Queen";"Hatchery";850;2
"Unit";"Queen";"Hatchery";850;2
"Unit";"Queen";"Hatchery";850;2
"Building";"CreepTumorQueen";NA;888;0
"Unit";"Queen";"Hatchery";882;2
"Building";"CreepTumor";NA;890;0
"Building";"CreepTumorQueen";NA;890;0
"Building";"CreepTumorQueen";NA;890;0
"Building";"CreepTumorQueen";NA;890;0
"Building";"CreepTumorQueen";NA;890;0
"Building";"CreepTumorQueen";NA;890;0
"Unit";"Viper";"Larva";890;3
"Unit";"Viper";"Larva";890;3
"Unit";"Viper";"Larva";890;3
"Building";"Hatchery";NA;890;0
"Building";"CreepTumorQueen";NA;899;0
"Building";"CreepTumor";NA;899;0
"Building";"CreepTumorQueen";NA;899;0
"Building";"CreepTumorQueen";NA;899;0
"Building";"CreepTumor";NA;899;0
"Building";"CreepTumorQueen";NA;899;0
"Building";"CreepTumorQueen";NA;899;0
"Building";"CreepTumor";NA;899;0
"Building";"CreepTumor";NA;899;0
"Building";"CreepTumor";NA;899;0
"Building";"CreepTumor";NA;899;0
"Building";"CreepTumor";NA;899;0
"Unit";"Queen";"Hatchery";899;2
"Unit";"Queen";"Hatchery";899;2
"Unit";"Queen";"Hatchery";899;2
"Building";"CreepTumorQueen";NA;906;0
"Building";"CreepTumor";NA;906;0
"Building";"CreepTumor";NA;912;0
"Building";"CreepTumorQueen";NA;912;0
"Building";"CreepTumorQueen";NA;912;0
"Building";"CreepTumor";NA;912;0
"Building";"CreepTumor";NA;912;0
"Building";"CreepTumor";NA;912;0
"Building";"CreepTumor";NA;912;0
"Unit";"Ultralisk";"Larva";912;6
"Building";"Hatchery";NA;899;0
