"type";"unit_name";"on_building";"total_supply";"supply"
"Unit";"Overlord";"Larva";13;0
"Building";"Extractor";NA;18;0
"Unit";"Overlord";"Larva";21;0
"Building";"SpawningPool";NA;19;0
"Building";"Hatchery";NA;17;0
"Unit";"Zergling";"Larva";22;1
"Unit";"Zergling";"Larva";22;1
"Unit";"Zergling";"Larva";23;1
"Unit";"Zergling";"Larva";23;1
"Unit";"Queen";"Hatchery";22;2
"Unit";"Queen";"Hatchery";23;2
"Unit";"Overlord";"Larva";33;0
"Unit";"Overlord";"Larva";38;0
"Unit";"Zergling";"Larva";39;1
"Unit";"Zergling";"Larva";39;1
"Building";"Hatchery";NA;25;0
"Unit";"Zergling";"Larva";39;1
"Unit";"Zergling";"Larva";39;1
"Unit";"Zergling";"Larva";39;1
"Unit";"Zergling";"Larva";39;1
"Unit";"Zergling";"Larva";39;1
"Unit";"Zergling";"Larva";39;1
"Unit";"Zergling";"Larva";39;1
"Unit";"Zergling";"Larva";39;1
"Unit";"Zergling";"Larva";39;1
"Unit";"Zergling";"Larva";39;1
"Unit";"Zergling";"Larva";39;1
"Unit";"Zergling";"Larva";39;1
"Unit";"Zergling";"Larva";39;1
"Unit";"Zergling";"Larva";39;1
"Unit";"Zergling";"Larva";39;1
"Unit";"Zergling";"Larva";39;1
"Unit";"Zergling";"Larva";41;1
"Unit";"Zergling";"Larva";41;1
"Unit";"Queen";"Hatchery";39;2
"Unit";"Queen";"Hatchery";41;2
"Unit";"Overlord";"Larva";70;0
"Unit";"Overlord";"Larva";70;0
"Building";"CreepTumorQueen";NA;71;0
"Unit";"Queen";"Hatchery";74;2
"Building";"CreepTumorQueen";NA;82;0
"Unit";"Overlord";"Larva";81;0
"Building";"EvolutionChamber";NA;82;0
"Building";"EvolutionChamber";NA;82;0
"Building";"CreepTumorQueen";NA;91;0
"Building";"CreepTumorQueen";NA;91;0
"Unit";"Overlord";"Larva";91;0
"Building";"CreepTumor";NA;94;0
"Building";"Extractor";NA;91;0
"Building";"Extractor";NA;91;0
"Building";"Extractor";NA;91;0
"Building";"CreepTumor";NA;94;0
"Building";"CreepTumorQueen";NA;94;0
"Building";"Extractor";NA;91;0
"Building";"Extractor";NA;91;0
"Unit";"Queen";"Hatchery";85;2
"Unit";"Queen";"Hatchery";94;2
"Building";"CreepTumor";NA;111;0
"Building";"CreepTumor";NA;111;0
"Building";"CreepTumor";NA;111;0
"Unit";"Zergling";"Larva";111;1
"Unit";"Zergling";"Larva";111;1
"Unit";"Zergling";"Larva";112;1
"Unit";"Zergling";"Larva";112;1
"Unit";"Zergling";"Larva";113;1
"Unit";"Zergling";"Larva";113;1
"Building";"CreepTumor";NA;117;0
"Building";"CreepTumor";NA;117;0
"Building";"CreepTumorQueen";NA;117;0
"Building";"CreepTumorQueen";NA;117;0
"Unit";"Overlord";"Larva";117;0
"Unit";"Overlord";"Larva";117;0
"Unit";"Zergling";"Larva";117;1
"Unit";"Zergling";"Larva";117;1
"Unit";"Zergling";"Larva";117;1
"Unit";"Zergling";"Larva";117;1
"Unit";"Zergling";"Larva";117;1
"Unit";"Zergling";"Larva";117;1
"Unit";"Zergling";"Larva";123;1
"Unit";"Zergling";"Larva";123;1
"Unit";"Zergling";"Larva";123;1
"Unit";"Zergling";"Larva";123;1
"Unit";"Zergling";"Larva";123;1
"Unit";"Zergling";"Larva";123;1
"Unit";"Overlord";"Larva";123;0
"Unit";"Overlord";"Larva";123;0
"Unit";"Overlord";"Larva";124;0
"Building";"CreepTumor";NA;130;0
"Building";"CreepTumor";NA;130;0
"Building";"CreepTumor";NA;130;0
"Unit";"Zergling";"Larva";130;1
"Unit";"Zergling";"Larva";130;1
"Unit";"Zergling";"Larva";130;1
"Unit";"Zergling";"Larva";130;1
"Unit";"Zergling";"Larva";130;1
"Unit";"Zergling";"Larva";130;1
"Unit";"Zergling";"Larva";130;1
"Unit";"Zergling";"Larva";130;1
"Unit";"Zergling";"Larva";130;1
"Unit";"Zergling";"Larva";130;1
"Unit";"Zergling";"Larva";130;1
"Unit";"Zergling";"Larva";130;1
"Building";"BanelingNest";NA;115;0
"Building";"CreepTumor";NA;136;0
"Building";"CreepTumor";NA;136;0
"Building";"CreepTumor";NA;136;0
"Building";"CreepTumorQueen";NA;136;0
"Building";"CreepTumorQueen";NA;136;0
"Unit";"Overlord";"Larva";136;0
"Unit";"Overlord";"Larva";148;0
"Unit";"Baneling";"Zergling";149;0
"Unit";"Baneling";"Zergling";149;0
"Unit";"Baneling";"Zergling";149;0
"Unit";"Zergling";"Larva";148;1
"Unit";"Zergling";"Larva";148;1
"Unit";"Baneling";"Zergling";149;0
"Unit";"Baneling";"Zergling";149;0
"Unit";"Baneling";"Zergling";149;0
"Unit";"Zergling";"Larva";148;1
"Unit";"Zergling";"Larva";148;1
"Unit";"Baneling";"Zergling";149;0
"Unit";"Zergling";"Larva";148;1
"Unit";"Zergling";"Larva";148;1
"Unit";"Zergling";"Larva";148;1
"Unit";"Zergling";"Larva";148;1
"Unit";"Zergling";"Larva";148;1
"Unit";"Zergling";"Larva";148;1
"Unit";"Zergling";"Larva";148;1
"Unit";"Zergling";"Larva";148;1
"Building";"HydraliskDen";NA;136;0
"Building";"Hatchery";NA;111;0
"Unit";"Overlord";"Larva";149;0
"Building";"CreepTumor";NA;150;0
"Unit";"Overlord";"Larva";149;0
"Building";"CreepTumor";NA;163;0
"Building";"CreepTumor";NA;163;0
"Building";"CreepTumorQueen";NA;163;0
"Building";"CreepTumor";NA;163;0
"Building";"CreepTumor";NA;163;0
"Building";"CreepTumor";NA;163;0
"Building";"CreepTumorQueen";NA;163;0
"Unit";"Overlord";"Larva";166;0
"Building";"CreepTumor";NA;168;0
"Unit";"Hydralisk";"Larva";164;2
"Unit";"Hydralisk";"Larva";164;2
"Unit";"Hydralisk";"Larva";165;2
"Unit";"Hydralisk";"Larva";166;2
"Building";"CreepTumor";NA;168;0
"Building";"CreepTumor";NA;168;0
"Unit";"Hydralisk";"Larva";166;2
"Upgrade";"ZergGroundArmorsLevel1";"EvolutionChamber";124;0
"Unit";"Hydralisk";"Larva";168;2
"Unit";"Hydralisk";"Larva";168;2
"Upgrade";"ZergMeleeWeaponsLevel1";"EvolutionChamber";130;0
"Unit";"Hydralisk";"Larva";168;2
"Unit";"Overlord";"Larva";168;0
"Unit";"Hydralisk";"Larva";168;2
"Building";"CreepTumor";NA;176;0
"Building";"CreepTumor";NA;176;0
"Unit";"Hydralisk";"Larva";168;2
"Building";"CreepTumor";NA;176;0
"Building";"CreepTumor";NA;176;0
"Building";"CreepTumor";NA;178;0
"Unit";"Overlord";"Larva";184;0
"Unit";"Zergling";"Larva";191;1
"Unit";"Zergling";"Larva";191;1
"Unit";"Zergling";"Larva";191;1
"Unit";"Zergling";"Larva";191;1
"Unit";"Zergling";"Larva";191;1
"Unit";"Zergling";"Larva";191;1
"Unit";"Zergling";"Larva";191;1
"Unit";"Zergling";"Larva";191;1
"Unit";"Zergling";"Larva";191;1
"Unit";"Zergling";"Larva";191;1
"Unit";"Zergling";"Larva";191;1
"Unit";"Zergling";"Larva";191;1
"Unit";"Zergling";"Larva";191;1
"Unit";"Zergling";"Larva";191;1
"Unit";"Zergling";"Larva";191;1
"Unit";"Zergling";"Larva";191;1
"Building";"CreepTumorQueen";NA;193;0
"Building";"CreepTumorQueen";NA;193;0
"Building";"SporeCrawler";NA;193;0
"Upgrade";"EvolveGroovedSpines";"HydraliskDen";168;0
"Building";"CreepTumor";NA;213;0
"Building";"InfestationPit";NA;213;0
"Unit";"Overlord";"Larva";214;0
"Unit";"Hydralisk";"Larva";214;2
"Unit";"Hydralisk";"Larva";214;2
"Unit";"Hydralisk";"Larva";214;2
"Unit";"Hydralisk";"Larva";214;2
"Unit";"Hydralisk";"Larva";214;2
"Building";"SpineCrawler";NA;213;0
"Unit";"Queen";"Hatchery";213;2
"Unit";"Overlord";"Larva";218;0
"Unit";"Baneling";"Zergling";218;0
"Unit";"Baneling";"Zergling";218;0
"Unit";"Baneling";"Zergling";218;0
"Unit";"Baneling";"Zergling";218;0
"Unit";"Baneling";"Zergling";218;0
"Unit";"Baneling";"Zergling";218;0
"Unit";"Baneling";"Zergling";218;0
"Unit";"Baneling";"Zergling";218;0
"Unit";"Baneling";"Zergling";218;0
"Unit";"Baneling";"Zergling";218;0
"Unit";"Baneling";"Zergling";218;0
"Unit";"Baneling";"Zergling";218;0
"Unit";"Baneling";"Zergling";218;0
"Unit";"Baneling";"Zergling";218;0
"Unit";"Baneling";"Zergling";218;0
"Unit";"Baneling";"Zergling";218;0
"Unit";"Baneling";"Zergling";218;0
"Unit";"Baneling";"Zergling";218;0
"Unit";"Baneling";"Zergling";218;0
"Unit";"Baneling";"Zergling";218;0
"Unit";"Baneling";"Zergling";218;0
"Unit";"Baneling";"Zergling";218;0
"Unit";"Baneling";"Zergling";218;0
"Unit";"Baneling";"Zergling";218;0
"Unit";"Baneling";"Zergling";218;0
"Unit";"Baneling";"Zergling";218;0
"Unit";"Baneling";"Zergling";218;0
"Unit";"Baneling";"Zergling";218;0
"Unit";"Baneling";"Zergling";218;0
"Unit";"Baneling";"Zergling";218;0
"Building";"CreepTumor";NA;230;0
"Building";"CreepTumor";NA;230;0
"Building";"CreepTumor";NA;230;0
"Building";"CreepTumor";NA;230;0
"Building";"CreepTumor";NA;230;0
"Unit";"Hydralisk";"Larva";228;2
"Unit";"Hydralisk";"Larva";228;2
"Unit";"Hydralisk";"Larva";228;2
"Building";"CreepTumor";NA;230;0
"Unit";"Zergling";"Larva";230;1
"Unit";"Zergling";"Larva";230;1
"Unit";"Zergling";"Larva";230;1
"Unit";"Zergling";"Larva";230;1
"Unit";"Zergling";"Larva";230;1
"Unit";"Zergling";"Larva";230;1
"Unit";"Zergling";"Larva";230;1
"Unit";"Zergling";"Larva";230;1
"Unit";"Zergling";"Larva";230;1
"Unit";"Zergling";"Larva";230;1
"Unit";"Zergling";"Larva";230;1
"Unit";"Zergling";"Larva";230;1
"Unit";"Zergling";"Larva";230;1
"Unit";"Zergling";"Larva";230;1
"Unit";"Zergling";"Larva";231;1
"Unit";"Zergling";"Larva";231;1
"Unit";"Zergling";"Larva";239;1
"Unit";"Zergling";"Larva";239;1
"Unit";"Zergling";"Larva";239;1
"Unit";"Zergling";"Larva";239;1
"Unit";"Zergling";"Larva";239;1
"Unit";"Zergling";"Larva";239;1
"Upgrade";"EvolveMuscularAugments";"HydraliskDen";218;0
"Building";"Hatchery";NA;214;0
"Unit";"Zergling";"Larva";259;1
"Unit";"Zergling";"Larva";259;1
"Unit";"Zergling";"Larva";259;1
"Unit";"Zergling";"Larva";259;1
"Unit";"Zergling";"Larva";259;1
"Unit";"Zergling";"Larva";259;1
"Unit";"Zergling";"Larva";259;1
"Unit";"Zergling";"Larva";259;1
"Unit";"Zergling";"Larva";259;1
"Unit";"Zergling";"Larva";259;1
"Unit";"Overlord";"Larva";259;0
"Unit";"Overlord";"Larva";259;0
"Unit";"Overlord";"Larva";259;0
"Unit";"Overlord";"Larva";259;0
"Unit";"Overlord";"Larva";259;0
"Unit";"Zergling";"Larva";267;1
"Unit";"Zergling";"Larva";267;1
"Unit";"Zergling";"Larva";267;1
"Unit";"Zergling";"Larva";267;1
"Unit";"Zergling";"Larva";267;1
"Unit";"Zergling";"Larva";267;1
"Unit";"Baneling";"Zergling";277;0
"Unit";"Baneling";"Zergling";277;0
"Unit";"Baneling";"Zergling";277;0
