"type";"unit_name";"on_building";"total_supply_lag";"supply"
"Unit";"Overlord";"Larva";13;0
"Building";"SpawningPool";NA;17;0
"Building";"Hatchery";NA;18;0
"Building";"Extractor";NA;19;0
"Unit";"Zergling";"Larva";19;1
"Unit";"Zergling";"Larva";20;1
"Unit";"Zergling";"Larva";21;1
"Unit";"Zergling";"Larva";22;1
"Unit";"Zergling";"Larva";23;1
"Unit";"Zergling";"Larva";24;1
"Unit";"Queen";"Hatchery";25;2
"Unit";"Overlord";"Larva";27;0
"Unit";"Queen";"Hatchery";29;2
"Unit";"Queen";"Hatchery";32;2
"Building";"CreepTumorQueen";NA;42;0
"Unit";"Overlord";"Larva";42;0
"Building";"Hatchery";NA;45;0
"Unit";"Zergling";"Larva";45;1
"Unit";"Zergling";"Larva";46;1
"Unit";"Zergling";"Larva";47;1
"Unit";"Zergling";"Larva";48;1
"Building";"CreepTumor";NA;49;0
"Building";"CreepTumorQueen";NA;49;0
"Unit";"Overlord";"Larva";53;0
"Unit";"Queen";"Hatchery";53;2
"Unit";"Zergling";"Larva";55;1
"Unit";"Zergling";"Larva";56;1
"Unit";"Overlord";"Larva";57;0
"Unit";"Zergling";"Larva";57;1
"Unit";"Zergling";"Larva";58;1
"Unit";"Zergling";"Larva";59;1
"Unit";"Zergling";"Larva";60;1
"Unit";"Zergling";"Larva";61;1
"Unit";"Zergling";"Larva";62;1
"Unit";"Zergling";"Larva";63;1
"Unit";"Zergling";"Larva";64;1
"Building";"CreepTumorQueen";NA;68;0
"Building";"CreepTumor";NA;68;0
"Unit";"Overlord";"Larva";68;0
"Building";"CreepTumor";NA;68;0
"Building";"SporeCrawler";NA;68;0
"Unit";"Zergling";"Larva";68;1
"Unit";"Zergling";"Larva";69;1
"Unit";"Zergling";"Larva";70;1
"Unit";"Zergling";"Larva";71;1
"Unit";"Zergling";"Larva";72;1
"Unit";"Zergling";"Larva";73;1
"Building";"SporeCrawler";NA;80;0
"Building";"CreepTumor";NA;80;0
"Building";"SporeCrawler";NA;81;0
"Unit";"Queen";"Hatchery";81;2
"Building";"CreepTumorQueen";NA;84;0
"Building";"CreepTumorQueen";NA;85;0
"Unit";"Overlord";"Larva";89;0
"Building";"Extractor";NA;91;0
"Building";"Extractor";NA;93;0
"Building";"CreepTumor";NA;93;0
"Building";"BanelingNest";NA;96;0
"Building";"CreepTumor";NA;97;0
"Building";"CreepTumor";NA;97;0
"Building";"CreepTumorQueen";NA;98;0
"Building";"CreepTumorQueen";NA;98;0
"Unit";"Overlord";"Larva";98;0
"Unit";"Overlord";"Larva";107;0
"Unit";"Overlord";"Larva";107;0
"Building";"CreepTumor";NA;107;0
"Building";"CreepTumor";NA;107;0
"Building";"EvolutionChamber";NA;107;0
"Building";"EvolutionChamber";NA;107;0
"Building";"CreepTumor";NA;111;0
"Unit";"Overlord";"Larva";120;0
"Building";"Extractor";NA;120;0
"Building";"HydraliskDen";NA;120;0
"Building";"Extractor";NA;120;0
"Unit";"Zergling";"Larva";120;1
"Unit";"Zergling";"Larva";121;1
"Unit";"Zergling";"Larva";122;1
"Unit";"Zergling";"Larva";123;1
"Unit";"Zergling";"Larva";124;1
"Unit";"Zergling";"Larva";125;1
"Unit";"Zergling";"Larva";126;1
"Unit";"Zergling";"Larva";127;1
"Unit";"Zergling";"Larva";128;1
"Unit";"Zergling";"Larva";129;1
"Unit";"Zergling";"Larva";130;1
"Unit";"Zergling";"Larva";131;1
"Unit";"Zergling";"Larva";132;1
"Unit";"Zergling";"Larva";133;1
"Unit";"Zergling";"Larva";134;1
"Unit";"Zergling";"Larva";135;1
"Unit";"Zergling";"Larva";136;1
"Unit";"Zergling";"Larva";137;1
"Building";"CreepTumor";NA;139;0
"Building";"CreepTumor";NA;139;0
"Building";"CreepTumor";NA;139;0
"Building";"CreepTumor";NA;139;0
"Unit";"Baneling";"Zergling";139;0
"Unit";"Baneling";"Zergling";139;0
"Unit";"Overlord";"Larva";139;0
"Unit";"Zergling";"Larva";139;1
"Unit";"Zergling";"Larva";140;1
"Unit";"Zergling";"Larva";141;1
"Unit";"Zergling";"Larva";142;1
"Unit";"Zergling";"Larva";143;1
"Unit";"Zergling";"Larva";144;1
"Unit";"Baneling";"Zergling";145;0
"Unit";"Baneling";"Zergling";145;0
"Unit";"Baneling";"Zergling";145;0
"Unit";"Baneling";"Zergling";145;0
"Unit";"Zergling";"Larva";146;1
"Unit";"Zergling";"Larva";147;1
"Unit";"Zergling";"Larva";148;1
"Unit";"Zergling";"Larva";149;1
"Unit";"Zergling";"Larva";150;1
"Unit";"Zergling";"Larva";151;1
"Unit";"Baneling";"Zergling";152;0
"Unit";"Baneling";"Zergling";152;0
"Unit";"Zergling";"Larva";153;1
"Unit";"Zergling";"Larva";154;1
"Unit";"Zergling";"Larva";155;1
"Unit";"Zergling";"Larva";156;1
"Unit";"Zergling";"Larva";157;1
"Unit";"Zergling";"Larva";158;1
"Unit";"Baneling";"Zergling";159;0
"Unit";"Baneling";"Zergling";159;0
"Unit";"Baneling";"Zergling";159;0
"Unit";"Baneling";"Zergling";159;0
"Building";"Hatchery";NA;159;0
"Unit";"Zergling";"Larva";159;1
"Unit";"Zergling";"Larva";160;1
"Unit";"Zergling";"Larva";161;1
"Unit";"Zergling";"Larva";162;1
"Unit";"Overlord";"Larva";163;0
"Unit";"Zergling";"Larva";163;1
"Unit";"Zergling";"Larva";164;1
"Unit";"Zergling";"Larva";165;1
"Unit";"Zergling";"Larva";166;1
"Unit";"Zergling";"Larva";167;1
"Unit";"Zergling";"Larva";168;1
"Unit";"Zergling";"Larva";169;1
"Unit";"Zergling";"Larva";170;1
"Unit";"Zergling";"Larva";171;1
"Unit";"Zergling";"Larva";172;1
"Building";"CreepTumor";NA;173;0
"Unit";"Zergling";"Larva";173;1
"Unit";"Zergling";"Larva";174;1
"Unit";"Overlord";"Larva";175;0
"Unit";"Zergling";"Larva";175;1
"Unit";"Zergling";"Larva";176;1
"Unit";"Zergling";"Larva";177;1
"Unit";"Zergling";"Larva";178;1
"Unit";"Zergling";"Larva";179;1
"Unit";"Zergling";"Larva";180;1
"Unit";"Zergling";"Larva";181;1
"Unit";"Zergling";"Larva";182;1
"Unit";"Hydralisk";"Larva";185;2
"Unit";"Hydralisk";"Larva";187;2
"Unit";"Hydralisk";"Larva";189;2
"Building";"CreepTumor";NA;191;0
"Building";"CreepTumorQueen";NA;191;0
"Building";"CreepTumorQueen";NA;191;0
"Building";"CreepTumor";NA;191;0
"Unit";"Hydralisk";"Larva";191;2
"Unit";"Hydralisk";"Larva";193;2
"Unit";"Hydralisk";"Larva";195;2
"Building";"CreepTumor";NA;200;0
"Unit";"Overlord";"Larva";200;0
"Unit";"Overlord";"Larva";200;0
"Unit";"Hydralisk";"Larva";200;2
"Building";"CreepTumorQueen";NA;203;0
"Building";"CreepTumorQueen";NA;203;0
"Unit";"Overlord";"Larva";203;0
"Unit";"Overlord";"Larva";203;0
"Unit";"Baneling";"Zergling";203;0
"Unit";"Baneling";"Zergling";203;0
"Unit";"Baneling";"Zergling";203;0
"Unit";"Baneling";"Zergling";203;0
"Unit";"Zergling";"Larva";203;1
"Unit";"Zergling";"Larva";204;1
"Unit";"Zergling";"Larva";205;1
"Unit";"Zergling";"Larva";206;1
"Unit";"Zergling";"Larva";207;1
"Unit";"Zergling";"Larva";208;1
"Unit";"Zergling";"Larva";209;1
"Unit";"Zergling";"Larva";210;1
"Unit";"Zergling";"Larva";211;1
"Unit";"Zergling";"Larva";212;1
"Unit";"Zergling";"Larva";213;1
"Unit";"Zergling";"Larva";214;1
"Unit";"Zergling";"Larva";215;1
"Unit";"Zergling";"Larva";216;1
"Unit";"Zergling";"Larva";217;1
"Unit";"Zergling";"Larva";218;1
"Unit";"Zergling";"Larva";219;1
"Unit";"Zergling";"Larva";220;1
"Unit";"Queen";"Hatchery";221;2
"Unit";"Zergling";"Larva";223;1
"Unit";"Zergling";"Larva";224;1
"Unit";"Zergling";"Larva";225;1
"Unit";"Zergling";"Larva";226;1
"Unit";"Zergling";"Larva";227;1
"Unit";"Zergling";"Larva";228;1
"Unit";"Zergling";"Larva";229;1
"Unit";"Zergling";"Larva";230;1
"Unit";"Zergling";"Larva";231;1
"Unit";"Zergling";"Larva";232;1
"Unit";"Zergling";"Larva";233;1
"Unit";"Zergling";"Larva";234;1
"Unit";"Zergling";"Larva";235;1
"Unit";"Zergling";"Larva";236;1
"Unit";"Hydralisk";"Larva";237;2
"Unit";"Hydralisk";"Larva";239;2
"Unit";"Zergling";"Larva";241;1
"Unit";"Zergling";"Larva";242;1
"Unit";"Zergling";"Larva";243;1
"Unit";"Zergling";"Larva";244;1
"Unit";"Zergling";"Larva";245;1
"Unit";"Zergling";"Larva";246;1
"Unit";"Zergling";"Larva";247;1
"Unit";"Zergling";"Larva";248;1
"Unit";"Zergling";"Larva";249;1
"Unit";"Zergling";"Larva";250;1
"Unit";"Zergling";"Larva";251;1
"Unit";"Zergling";"Larva";252;1
"Unit";"Baneling";"Zergling";253;0
"Unit";"Baneling";"Zergling";253;0
"Unit";"Baneling";"Zergling";253;0
"Unit";"Baneling";"Zergling";253;0
"Building";"CreepTumorQueen";NA;253;0
"Unit";"Baneling";"Zergling";253;0
"Building";"CreepTumorQueen";NA;253;0
"Building";"CreepTumor";NA;256;0
"Building";"CreepTumor";NA;256;0
"Building";"Extractor";NA;261;0
"Unit";"Baneling";"Zergling";261;0
"Unit";"Baneling";"Zergling";261;0
"Unit";"Baneling";"Zergling";261;0
"Unit";"Baneling";"Zergling";261;0
"Unit";"Baneling";"Zergling";261;0
"Building";"InfestationPit";NA;261;0
"Building";"Extractor";NA;261;0
"Unit";"Hydralisk";"Larva";261;2
"Unit";"Overlord";"Larva";263;0
"Unit";"Hydralisk";"Larva";263;2
"Unit";"Hydralisk";"Larva";265;2
"Unit";"Zergling";"Larva";267;1
"Unit";"Zergling";"Larva";268;1
"Unit";"Zergling";"Larva";269;1
"Unit";"Zergling";"Larva";270;1
"Unit";"Zergling";"Larva";271;1
"Unit";"Zergling";"Larva";272;1
"Unit";"Zergling";"Larva";273;1
"Unit";"Zergling";"Larva";274;1
"Unit";"Zergling";"Larva";275;1
"Unit";"Zergling";"Larva";276;1
"Building";"CreepTumorQueen";NA;281;0
"Building";"CreepTumorQueen";NA;281;0
"Unit";"Overlord";"Larva";282;0
"Unit";"Hydralisk";"Larva";282;2
"Unit";"Hydralisk";"Larva";284;2
"Unit";"Hydralisk";"Larva";286;2
"Unit";"Overlord";"Larva";288;0
"Unit";"Overlord";"Larva";288;0
"Unit";"Zergling";"Larva";288;1
"Unit";"Zergling";"Larva";289;1
"Unit";"Zergling";"Larva";290;1
"Unit";"Zergling";"Larva";291;1
"Unit";"Zergling";"Larva";292;1
"Unit";"Zergling";"Larva";293;1
"Unit";"Zergling";"Larva";294;1
"Unit";"Zergling";"Larva";295;1
"Unit";"Zergling";"Larva";296;1
"Unit";"Zergling";"Larva";297;1
"Unit";"Zergling";"Larva";298;1
"Unit";"Zergling";"Larva";299;1
"Unit";"Zergling";"Larva";300;1
"Unit";"Zergling";"Larva";301;1
"Building";"CreepTumorQueen";NA;302;0
"Building";"Spire";NA;302;0
"Unit";"Baneling";"Zergling";302;0
"Unit";"Baneling";"Zergling";302;0
"Unit";"Baneling";"Zergling";302;0
"Unit";"Baneling";"Zergling";302;0
"Unit";"Baneling";"Zergling";302;0
"Unit";"Hydralisk";"Larva";302;2
"Unit";"Hydralisk";"Larva";304;2
"Unit";"Zergling";"Larva";306;1
"Unit";"Zergling";"Larva";307;1
"Unit";"Zergling";"Larva";308;1
"Unit";"Zergling";"Larva";309;1
"Unit";"Zergling";"Larva";310;1
"Unit";"Zergling";"Larva";311;1
"Unit";"Zergling";"Larva";312;1
"Unit";"Zergling";"Larva";313;1
"Unit";"Hydralisk";"Larva";314;2
"Unit";"Hydralisk";"Larva";316;2
"Unit";"Zergling";"Larva";318;1
"Unit";"Zergling";"Larva";319;1
"Unit";"Zergling";"Larva";320;1
"Unit";"Zergling";"Larva";321;1
"Unit";"Zergling";"Larva";322;1
"Unit";"Zergling";"Larva";323;1
"Unit";"Zergling";"Larva";324;1
"Unit";"Zergling";"Larva";325;1
"Unit";"Zergling";"Larva";326;1
"Unit";"Zergling";"Larva";327;1
"Unit";"Zergling";"Larva";328;1
"Unit";"Zergling";"Larva";329;1
"Unit";"Zergling";"Larva";330;1
"Unit";"Zergling";"Larva";331;1
"Unit";"Zergling";"Larva";332;1
"Unit";"Zergling";"Larva";333;1
"Unit";"Baneling";"Zergling";334;0
"Unit";"Baneling";"Zergling";334;0
"Unit";"Baneling";"Zergling";334;0
"Unit";"Baneling";"Zergling";334;0
"Unit";"Baneling";"Zergling";334;0
"Unit";"Baneling";"Zergling";334;0
"Building";"CreepTumor";NA;334;0
"Building";"CreepTumor";NA;334;0
"Building";"CreepTumor";NA;334;0
"Building";"CreepTumorQueen";NA;334;0
"Unit";"Zergling";"Larva";334;1
"Unit";"Zergling";"Larva";335;1
"Unit";"Zergling";"Larva";336;1
"Unit";"Zergling";"Larva";337;1
"Unit";"Zergling";"Larva";338;1
"Unit";"Zergling";"Larva";339;1
"Unit";"Zergling";"Larva";340;1
"Unit";"Zergling";"Larva";341;1
"Unit";"Zergling";"Larva";342;1
"Unit";"Zergling";"Larva";343;1
"Unit";"Zergling";"Larva";344;1
"Unit";"Zergling";"Larva";345;1
"Building";"CreepTumorQueen";NA;346;0
"Unit";"Hydralisk";"Larva";346;2
"Unit";"Hydralisk";"Larva";348;2
"Unit";"Baneling";"Zergling";350;0
"Building";"Hatchery";NA;350;0
"Unit";"Baneling";"Zergling";350;0
"Unit";"Baneling";"Zergling";350;0
"Unit";"Baneling";"Zergling";350;0
"Unit";"Zergling";"Larva";350;1
"Unit";"Zergling";"Larva";351;1
"Unit";"Zergling";"Larva";352;1
"Unit";"Zergling";"Larva";353;1
"Unit";"Zergling";"Larva";354;1
"Unit";"Zergling";"Larva";355;1
"Unit";"Zergling";"Larva";356;1
"Unit";"Zergling";"Larva";357;1
"Unit";"Zergling";"Larva";358;1
"Unit";"Zergling";"Larva";359;1
"Unit";"Zergling";"Larva";360;1
"Unit";"Zergling";"Larva";361;1
"Unit";"Zergling";"Larva";362;1
"Unit";"Zergling";"Larva";363;1
"Unit";"Overlord";"Larva";364;0
"Unit";"Zergling";"Larva";364;1
"Unit";"Zergling";"Larva";365;1
"Unit";"Zergling";"Larva";366;1
"Unit";"Zergling";"Larva";367;1
"Unit";"Zergling";"Larva";368;1
"Unit";"Zergling";"Larva";369;1
"Unit";"Zergling";"Larva";370;1
"Unit";"Zergling";"Larva";371;1
"Unit";"Zergling";"Larva";372;1
"Unit";"Zergling";"Larva";373;1
"Unit";"Zergling";"Larva";374;1
"Unit";"Zergling";"Larva";375;1
"Unit";"Zergling";"Larva";376;1
"Unit";"Zergling";"Larva";377;1
"Unit";"Zergling";"Larva";378;1
"Unit";"Zergling";"Larva";379;1
"Unit";"Zergling";"Larva";380;1
"Unit";"Zergling";"Larva";381;1
"Unit";"Baneling";"Zergling";382;0
"Unit";"Baneling";"Zergling";382;0
"Unit";"Baneling";"Zergling";382;0
"Unit";"Baneling";"Zergling";382;0
"Unit";"Baneling";"Zergling";382;0
"Unit";"Baneling";"Zergling";382;0
"Unit";"Zergling";"Larva";382;1
"Unit";"Zergling";"Larva";383;1
"Unit";"Zergling";"Larva";384;1
"Unit";"Zergling";"Larva";385;1
"Unit";"Zergling";"Larva";386;1
"Unit";"Zergling";"Larva";387;1
"Unit";"Zergling";"Larva";388;1
"Unit";"Zergling";"Larva";389;1
"Unit";"Zergling";"Larva";390;1
"Unit";"Zergling";"Larva";391;1
"Unit";"Zergling";"Larva";392;1
"Unit";"Zergling";"Larva";393;1
"Unit";"Zergling";"Larva";394;1
"Unit";"Zergling";"Larva";395;1
"Unit";"Viper";"Larva";396;3
"Unit";"Viper";"Larva";399;3
"Unit";"Zergling";"Larva";402;1
"Unit";"Zergling";"Larva";403;1
"Unit";"Zergling";"Larva";404;1
"Unit";"Zergling";"Larva";405;1
"Unit";"Zergling";"Larva";406;1
"Unit";"Zergling";"Larva";407;1
"Unit";"Zergling";"Larva";408;1
"Unit";"Zergling";"Larva";409;1
"Building";"Extractor";NA;410;0
"Building";"CreepTumor";NA;410;0
"Building";"CreepTumor";NA;410;0
"Unit";"Zergling";"Larva";410;1
"Unit";"Zergling";"Larva";411;1
"Unit";"Baneling";"Zergling";412;0
"Unit";"Baneling";"Zergling";412;0
"Unit";"Baneling";"Zergling";412;0
"Unit";"Baneling";"Zergling";412;0
"Unit";"Baneling";"Zergling";412;0
"Unit";"Baneling";"Zergling";412;0
"Unit";"Baneling";"Zergling";412;0
"Unit";"Baneling";"Zergling";412;0
"Unit";"Baneling";"Zergling";412;0
"Unit";"Baneling";"Zergling";412;0
"Unit";"Baneling";"Zergling";412;0
"Building";"CreepTumor";NA;412;0
"Building";"CreepTumor";NA;412;0
"Unit";"Baneling";"Zergling";412;0
"Unit";"Baneling";"Zergling";412;0
"Unit";"Baneling";"Zergling";412;0
"Unit";"Zergling";"Larva";412;1
"Unit";"Zergling";"Larva";413;1
"Unit";"Zergling";"Larva";414;1
"Unit";"Zergling";"Larva";415;1
"Unit";"Zergling";"Larva";416;1
"Unit";"Zergling";"Larva";417;1
"Unit";"Zergling";"Larva";418;1
"Unit";"Zergling";"Larva";419;1
"Unit";"Zergling";"Larva";420;1
"Unit";"Zergling";"Larva";421;1
"Unit";"Zergling";"Larva";422;1
"Unit";"Zergling";"Larva";423;1
"Unit";"Zergling";"Larva";424;1
"Unit";"Zergling";"Larva";425;1
"Unit";"Zergling";"Larva";426;1
"Unit";"Zergling";"Larva";427;1
"Unit";"Zergling";"Larva";428;1
"Unit";"Zergling";"Larva";429;1
"Unit";"Zergling";"Larva";430;1
"Unit";"Zergling";"Larva";431;1
"Unit";"Zergling";"Larva";432;1
"Unit";"Zergling";"Larva";433;1
"Unit";"Zergling";"Larva";434;1
"Unit";"Zergling";"Larva";435;1
"Unit";"Zergling";"Larva";436;1
"Unit";"Zergling";"Larva";437;1
"Unit";"Zergling";"Larva";438;1
"Unit";"Zergling";"Larva";439;1
"Unit";"Zergling";"Larva";440;1
"Unit";"Zergling";"Larva";441;1
"Unit";"Zergling";"Larva";442;1
"Unit";"Zergling";"Larva";443;1
"Unit";"Zergling";"Larva";444;1
"Unit";"Zergling";"Larva";445;1
"Unit";"Zergling";"Larva";446;1
"Unit";"Zergling";"Larva";447;1
"Unit";"Zergling";"Larva";448;1
"Unit";"Zergling";"Larva";449;1
"Unit";"Zergling";"Larva";450;1
"Unit";"Zergling";"Larva";451;1
"Unit";"Zergling";"Larva";452;1
"Unit";"Zergling";"Larva";453;1
"Unit";"Zergling";"Larva";454;1
"Unit";"Zergling";"Larva";455;1
"Unit";"Zergling";"Larva";456;1
"Unit";"Zergling";"Larva";457;1
"Unit";"Zergling";"Larva";458;1
"Unit";"Zergling";"Larva";459;1
"Unit";"Zergling";"Larva";460;1
"Unit";"Zergling";"Larva";461;1
"Unit";"Zergling";"Larva";462;1
"Unit";"Zergling";"Larva";463;1
"Unit";"Zergling";"Larva";464;1
"Unit";"Zergling";"Larva";465;1
"Unit";"Zergling";"Larva";466;1
"Unit";"Zergling";"Larva";467;1
"Unit";"Zergling";"Larva";468;1
"Unit";"Zergling";"Larva";469;1
"Unit";"Baneling";"Zergling";470;0
"Unit";"Baneling";"Zergling";470;0
"Unit";"Baneling";"Zergling";470;0
"Unit";"Baneling";"Zergling";470;0
"Unit";"Baneling";"Zergling";470;0
"Unit";"Baneling";"Zergling";470;0
"Unit";"Baneling";"Zergling";470;0
"Unit";"Baneling";"Zergling";470;0
"Unit";"Baneling";"Zergling";470;0
"Unit";"Baneling";"Zergling";470;0
"Unit";"Baneling";"Zergling";470;0
"Unit";"Baneling";"Zergling";470;0
"Unit";"Baneling";"Zergling";470;0
"Unit";"Baneling";"Zergling";470;0
"Unit";"Zergling";"Larva";470;1
"Unit";"Zergling";"Larva";471;1
"Unit";"Zergling";"Larva";472;1
"Unit";"Zergling";"Larva";473;1
"Building";"Hatchery";NA;474;0
"Unit";"Corruptor";"Larva";474;2
"Unit";"Corruptor";"Larva";476;2
"Building";"CreepTumor";NA;478;0
"Unit";"Corruptor";"Larva";478;2
"Unit";"Corruptor";"Larva";480;2
"Unit";"Corruptor";"Larva";482;2
"Unit";"Corruptor";"Larva";484;2
"Building";"CreepTumor";NA;486;0
"Unit";"Baneling";"Zergling";486;0
"Unit";"Baneling";"Zergling";486;0
"Building";"CreepTumor";NA;486;0
"Unit";"Zergling";"Larva";486;1
"Unit";"Zergling";"Larva";487;1
"Unit";"Zergling";"Larva";488;1
"Unit";"Zergling";"Larva";489;1
"Unit";"Zergling";"Larva";490;1
"Unit";"Zergling";"Larva";491;1
"Unit";"Zergling";"Larva";492;1
"Unit";"Zergling";"Larva";493;1
"Unit";"Zergling";"Larva";494;1
"Unit";"Zergling";"Larva";495;1
"Unit";"Zergling";"Larva";496;1
"Unit";"Zergling";"Larva";497;1
"Unit";"Zergling";"Larva";498;1
"Unit";"Zergling";"Larva";499;1
"Unit";"Baneling";"Zergling";505;0
"Building";"Extractor";NA;505;0
"Unit";"Zergling";"Larva";505;1
"Unit";"Zergling";"Larva";506;1
"Unit";"Zergling";"Larva";507;1
"Unit";"Zergling";"Larva";508;1
"Unit";"Zergling";"Larva";509;1
"Unit";"Zergling";"Larva";510;1
"Unit";"Zergling";"Larva";511;1
"Unit";"Zergling";"Larva";512;1
"Unit";"Zergling";"Larva";513;1
"Unit";"Zergling";"Larva";514;1
"Unit";"Zergling";"Larva";515;1
"Unit";"Zergling";"Larva";516;1
"Unit";"Zergling";"Larva";517;1
"Unit";"Zergling";"Larva";518;1
"Unit";"Zergling";"Larva";519;1
"Unit";"Zergling";"Larva";520;1
"Unit";"Zergling";"Larva";521;1
"Unit";"Zergling";"Larva";522;1
"Unit";"Corruptor";"Larva";523;2
"Unit";"Zergling";"Larva";525;1
"Unit";"Zergling";"Larva";526;1
"Unit";"Zergling";"Larva";527;1
"Unit";"Zergling";"Larva";528;1
"Unit";"Zergling";"Larva";529;1
"Unit";"Zergling";"Larva";530;1
"Unit";"Zergling";"Larva";531;1
"Unit";"Zergling";"Larva";532;1
"Unit";"Zergling";"Larva";533;1
"Unit";"Zergling";"Larva";534;1
"Unit";"Zergling";"Larva";535;1
"Unit";"Zergling";"Larva";536;1
"Unit";"Zergling";"Larva";537;1
"Unit";"Zergling";"Larva";538;1
"Unit";"Zergling";"Larva";539;1
"Unit";"Zergling";"Larva";540;1
"Unit";"Zergling";"Larva";541;1
"Unit";"Zergling";"Larva";542;1
"Unit";"Zergling";"Larva";543;1
"Unit";"Zergling";"Larva";544;1
"Unit";"Zergling";"Larva";545;1
"Unit";"Zergling";"Larva";546;1
"Unit";"Zergling";"Larva";547;1
"Unit";"Zergling";"Larva";548;1
"Unit";"Zergling";"Larva";549;1
"Unit";"Zergling";"Larva";550;1
"Unit";"Hydralisk";"Larva";551;2
"Unit";"Hydralisk";"Larva";553;2
"Unit";"Hydralisk";"Larva";555;2
"Unit";"Hydralisk";"Larva";557;2
"Building";"CreepTumor";NA;559;0
"Building";"CreepTumor";NA;559;0
"Building";"CreepTumor";NA;559;0
"Unit";"Zergling";"Larva";559;1
"Unit";"Zergling";"Larva";560;1
"Unit";"Baneling";"Zergling";561;0
"Unit";"Baneling";"Zergling";561;0
"Unit";"Baneling";"Zergling";561;0
"Unit";"Baneling";"Zergling";561;0
"Unit";"Baneling";"Zergling";561;0
"Unit";"Baneling";"Zergling";561;0
"Unit";"Baneling";"Zergling";561;0
"Unit";"Baneling";"Zergling";561;0
"Unit";"Baneling";"Zergling";561;0
"Unit";"Baneling";"Zergling";561;0
"Unit";"Baneling";"Zergling";561;0
"Unit";"Baneling";"Zergling";561;0
"Unit";"Baneling";"Zergling";561;0
"Unit";"Baneling";"Zergling";561;0
"Unit";"Baneling";"Zergling";561;0
"Unit";"Baneling";"Zergling";561;0
"Unit";"Baneling";"Zergling";561;0
"Building";"Hatchery";NA;561;0
"Building";"SporeCrawler";NA;561;0
"Building";"SporeCrawler";NA;561;0
"Unit";"Baneling";"Zergling";561;0
"Unit";"Baneling";"Zergling";561;0
"Unit";"Baneling";"Zergling";561;0
"Unit";"Baneling";"Zergling";561;0
"Unit";"Baneling";"Zergling";561;0
"Unit";"Baneling";"Zergling";561;0
"Unit";"Zergling";"Larva";561;1
"Unit";"Zergling";"Larva";562;1
"Unit";"Zergling";"Larva";563;1
"Unit";"Zergling";"Larva";564;1
"Unit";"Zergling";"Larva";565;1
"Unit";"Zergling";"Larva";566;1
"Unit";"Zergling";"Larva";567;1
"Unit";"Zergling";"Larva";568;1
"Unit";"Zergling";"Larva";569;1
"Unit";"Zergling";"Larva";570;1
"Unit";"Zergling";"Larva";571;1
"Unit";"Zergling";"Larva";572;1
"Unit";"Zergling";"Larva";573;1
"Unit";"Zergling";"Larva";574;1
"Unit";"Zergling";"Larva";575;1
"Unit";"Zergling";"Larva";576;1
"Unit";"Zergling";"Larva";577;1
"Unit";"Zergling";"Larva";578;1
"Unit";"Zergling";"Larva";579;1
"Unit";"Zergling";"Larva";580;1
"Unit";"Zergling";"Larva";581;1
"Unit";"Zergling";"Larva";582;1
"Unit";"Zergling";"Larva";583;1
"Unit";"Zergling";"Larva";584;1
"Unit";"Zergling";"Larva";585;1
"Unit";"Zergling";"Larva";586;1
"Unit";"Zergling";"Larva";587;1
"Unit";"Zergling";"Larva";588;1
"Unit";"Zergling";"Larva";589;1
"Unit";"Zergling";"Larva";590;1
"Unit";"Zergling";"Larva";591;1
"Unit";"Zergling";"Larva";592;1
"Unit";"Zergling";"Larva";593;1
"Unit";"Zergling";"Larva";594;1
"Unit";"Zergling";"Larva";595;1
"Unit";"Zergling";"Larva";596;1
"Unit";"Zergling";"Larva";597;1
"Unit";"Zergling";"Larva";598;1
"Unit";"Zergling";"Larva";599;1
"Unit";"Zergling";"Larva";600;1
"Unit";"Zergling";"Larva";601;1
"Unit";"Zergling";"Larva";602;1
"Unit";"Zergling";"Larva";603;1
"Unit";"Zergling";"Larva";604;1
"Unit";"Zergling";"Larva";605;1
"Unit";"Zergling";"Larva";606;1
"Unit";"Zergling";"Larva";607;1
"Unit";"Zergling";"Larva";608;1
"Unit";"Overlord";"Larva";609;0
"Unit";"Overlord";"Larva";609;0
"Unit";"Hydralisk";"Larva";609;2
"Unit";"Zergling";"Larva";611;1
"Unit";"Zergling";"Larva";612;1
"Unit";"Hydralisk";"Larva";613;2
"Unit";"Hydralisk";"Larva";615;2
"Unit";"Zergling";"Larva";617;1
"Unit";"Zergling";"Larva";618;1
"Unit";"Zergling";"Larva";619;1
"Unit";"Zergling";"Larva";620;1
"Unit";"Zergling";"Larva";621;1
"Unit";"Zergling";"Larva";622;1
"Unit";"Zergling";"Larva";623;1
"Unit";"Zergling";"Larva";624;1
"Unit";"Zergling";"Larva";625;1
"Unit";"Zergling";"Larva";626;1
"Unit";"Hydralisk";"Larva";627;2
"Unit";"Queen";"Hatchery";629;2
"Unit";"Overlord";"Larva";631;0
"Unit";"Hydralisk";"Larva";631;2
"Unit";"Hydralisk";"Larva";633;2
"Unit";"Hydralisk";"Larva";635;2
"Unit";"Hydralisk";"Larva";637;2
"Unit";"Hydralisk";"Larva";639;2
"Unit";"Hydralisk";"Larva";641;2
"Unit";"Hydralisk";"Larva";643;2
"Unit";"Hydralisk";"Larva";645;2
"Unit";"Hydralisk";"Larva";647;2
"Building";"CreepTumor";NA;649;0
"Building";"CreepTumor";NA;649;0
"Unit";"Baneling";"Zergling";649;0
"Unit";"Baneling";"Zergling";649;0
"Unit";"Baneling";"Zergling";649;0
"Unit";"Baneling";"Zergling";649;0
"Unit";"Baneling";"Zergling";649;0
"Unit";"Baneling";"Zergling";649;0
"Unit";"Baneling";"Zergling";649;0
"Unit";"Baneling";"Zergling";649;0
"Unit";"Baneling";"Zergling";649;0
"Unit";"Baneling";"Zergling";649;0
"Unit";"Baneling";"Zergling";649;0
"Unit";"Baneling";"Zergling";649;0
"Unit";"Baneling";"Zergling";649;0
"Unit";"Baneling";"Zergling";649;0
"Unit";"Baneling";"Zergling";649;0
"Unit";"Baneling";"Zergling";649;0
"Unit";"Baneling";"Zergling";649;0
"Unit";"Baneling";"Zergling";649;0
"Unit";"Baneling";"Zergling";649;0
"Unit";"Baneling";"Zergling";649;0
"Unit";"Baneling";"Zergling";649;0
"Unit";"Baneling";"Zergling";649;0
"Unit";"Baneling";"Zergling";649;0
"Unit";"Baneling";"Zergling";649;0
"Unit";"Baneling";"Zergling";649;0
"Unit";"Baneling";"Zergling";649;0
"Unit";"Baneling";"Zergling";649;0
"Unit";"Baneling";"Zergling";649;0
"Unit";"Zergling";"Larva";649;1
"Unit";"Zergling";"Larva";650;1
"Unit";"Zergling";"Larva";651;1
"Unit";"Zergling";"Larva";652;1
"Unit";"Zergling";"Larva";653;1
"Unit";"Zergling";"Larva";654;1
"Unit";"Zergling";"Larva";655;1
"Unit";"Zergling";"Larva";656;1
"Unit";"Zergling";"Larva";657;1
"Unit";"Zergling";"Larva";658;1
"Unit";"Zergling";"Larva";659;1
"Unit";"Zergling";"Larva";660;1
"Unit";"Zergling";"Larva";661;1
"Unit";"Zergling";"Larva";662;1
"Unit";"Zergling";"Larva";663;1
"Unit";"Zergling";"Larva";664;1
"Unit";"Baneling";"Zergling";665;0
"Unit";"Baneling";"Zergling";665;0
"Unit";"Baneling";"Zergling";665;0
"Unit";"Baneling";"Zergling";665;0
"Unit";"Baneling";"Zergling";665;0
"Unit";"Baneling";"Zergling";665;0
"Unit";"Baneling";"Zergling";665;0
"Unit";"Baneling";"Zergling";665;0
"Unit";"Baneling";"Zergling";665;0
"Unit";"Baneling";"Zergling";665;0
"Unit";"Baneling";"Zergling";665;0
"Unit";"Baneling";"Zergling";665;0
"Unit";"Zergling";"Larva";665;1
"Unit";"Zergling";"Larva";666;1
"Unit";"Zergling";"Larva";667;1
"Unit";"Zergling";"Larva";668;1
"Unit";"Zergling";"Larva";669;1
"Unit";"Zergling";"Larva";670;1
"Unit";"Zergling";"Larva";671;1
"Unit";"Zergling";"Larva";672;1
"Unit";"Zergling";"Larva";673;1
"Unit";"Zergling";"Larva";674;1
"Unit";"Zergling";"Larva";675;1
"Unit";"Zergling";"Larva";676;1
"Unit";"Zergling";"Larva";677;1
"Unit";"Zergling";"Larva";678;1
"Unit";"Zergling";"Larva";679;1
"Unit";"Zergling";"Larva";680;1
"Unit";"Zergling";"Larva";681;1
"Unit";"Zergling";"Larva";682;1
"Unit";"Zergling";"Larva";683;1
"Unit";"Zergling";"Larva";684;1
"Unit";"Zergling";"Larva";685;1
"Unit";"Zergling";"Larva";686;1
"Unit";"Zergling";"Larva";687;1
"Unit";"Zergling";"Larva";688;1
"Unit";"Zergling";"Larva";689;1
"Unit";"Zergling";"Larva";690;1
"Unit";"Zergling";"Larva";691;1
"Unit";"Zergling";"Larva";692;1
"Unit";"Zergling";"Larva";693;1
"Unit";"Zergling";"Larva";694;1
"Unit";"Zergling";"Larva";695;1
"Unit";"Zergling";"Larva";696;1
"Unit";"Hydralisk";"Larva";697;2
"Unit";"Hydralisk";"Larva";699;2
"Unit";"Hydralisk";"Larva";701;2
"Unit";"Hydralisk";"Larva";703;2
"Unit";"Hydralisk";"Larva";705;2
"Unit";"Hydralisk";"Larva";707;2
"Unit";"Hydralisk";"Larva";709;2
"Unit";"Hydralisk";"Larva";711;2
"Unit";"Hydralisk";"Larva";713;2
"Unit";"Zergling";"Larva";715;1
"Unit";"Zergling";"Larva";716;1
"Unit";"Zergling";"Larva";717;1
"Unit";"Zergling";"Larva";718;1
"Unit";"Zergling";"Larva";719;1
"Unit";"Zergling";"Larva";720;1
"Unit";"Zergling";"Larva";721;1
"Unit";"Zergling";"Larva";722;1
"Unit";"Zergling";"Larva";723;1
"Unit";"Zergling";"Larva";724;1
"Unit";"Zergling";"Larva";725;1
"Unit";"Zergling";"Larva";726;1
"Unit";"Zergling";"Larva";727;1
"Unit";"Zergling";"Larva";728;1
"Unit";"Zergling";"Larva";729;1
"Unit";"Zergling";"Larva";730;1
"Unit";"Zergling";"Larva";731;1
"Unit";"Zergling";"Larva";732;1
"Unit";"Baneling";"Zergling";733;0
"Unit";"Baneling";"Zergling";733;0
"Unit";"Baneling";"Zergling";733;0
"Unit";"Baneling";"Zergling";733;0
"Unit";"Baneling";"Zergling";733;0
"Unit";"Baneling";"Zergling";733;0
"Unit";"Baneling";"Zergling";733;0
"Unit";"Baneling";"Zergling";733;0
"Unit";"Baneling";"Zergling";733;0
"Unit";"Baneling";"Zergling";733;0
"Unit";"Baneling";"Zergling";733;0
"Unit";"Baneling";"Zergling";733;0
"Unit";"Baneling";"Zergling";733;0
"Unit";"Baneling";"Zergling";733;0
"Unit";"Baneling";"Zergling";733;0
"Unit";"Baneling";"Zergling";733;0
"Unit";"Hydralisk";"Larva";733;2
"Unit";"Hydralisk";"Larva";735;2
"Unit";"Baneling";"Zergling";737;0
"Unit";"Baneling";"Zergling";737;0
"Unit";"Baneling";"Zergling";737;0
"Unit";"Baneling";"Zergling";737;0
"Unit";"Zergling";"Larva";737;1
"Unit";"Zergling";"Larva";738;1
"Unit";"Zergling";"Larva";739;1
"Unit";"Zergling";"Larva";740;1
"Unit";"Zergling";"Larva";741;1
"Unit";"Zergling";"Larva";742;1
"Unit";"Zergling";"Larva";743;1
"Unit";"Zergling";"Larva";744;1
"Unit";"Zergling";"Larva";745;1
"Unit";"Zergling";"Larva";746;1
"Unit";"Zergling";"Larva";747;1
"Unit";"Zergling";"Larva";748;1
"Unit";"Zergling";"Larva";749;1
"Unit";"Zergling";"Larva";750;1
"Unit";"Zergling";"Larva";751;1
"Unit";"Zergling";"Larva";752;1
"Unit";"Hydralisk";"Larva";753;2
"Unit";"Hydralisk";"Larva";755;2
"Unit";"Zergling";"Larva";757;1
"Unit";"Zergling";"Larva";758;1
"Unit";"Zergling";"Larva";759;1
"Unit";"Zergling";"Larva";760;1
"Unit";"Zergling";"Larva";761;1
"Unit";"Zergling";"Larva";762;1
"Unit";"Zergling";"Larva";763;1
"Unit";"Zergling";"Larva";764;1
"Unit";"Hydralisk";"Larva";765;2
"Unit";"Zergling";"Larva";767;1
"Unit";"Zergling";"Larva";768;1
"Unit";"Zergling";"Larva";769;1
"Unit";"Zergling";"Larva";770;1
"Unit";"Zergling";"Larva";771;1
"Unit";"Zergling";"Larva";772;1
"Unit";"Zergling";"Larva";773;1
"Unit";"Zergling";"Larva";774;1
"Unit";"Zergling";"Larva";775;1
"Unit";"Zergling";"Larva";776;1
"Unit";"Zergling";"Larva";777;1
"Unit";"Zergling";"Larva";778;1
"Unit";"Zergling";"Larva";779;1
"Unit";"Zergling";"Larva";780;1
"Building";"CreepTumor";NA;781;0
"Building";"CreepTumor";NA;781;0
"Unit";"Viper";"Larva";781;3
"Unit";"Viper";"Larva";784;3
"Unit";"Hydralisk";"Larva";787;2
"Unit";"Hydralisk";"Larva";789;2
"Unit";"Zergling";"Larva";791;1
"Unit";"Zergling";"Larva";792;1
"Unit";"Baneling";"Zergling";793;0
"Unit";"Baneling";"Zergling";793;0
"Unit";"Zergling";"Larva";793;1
"Unit";"Zergling";"Larva";794;1
"Unit";"Zergling";"Larva";795;1
"Unit";"Zergling";"Larva";796;1
"Unit";"Zergling";"Larva";797;1
"Unit";"Zergling";"Larva";798;1
"Unit";"Baneling";"Zergling";799;0
"Unit";"Baneling";"Zergling";799;0
"Unit";"Zergling";"Larva";799;1
"Unit";"Zergling";"Larva";800;1
"Unit";"Baneling";"Zergling";801;0
"Unit";"Baneling";"Zergling";801;0
"Unit";"Baneling";"Zergling";801;0
"Unit";"Zergling";"Larva";801;1
"Unit";"Zergling";"Larva";802;1
"Unit";"Zergling";"Larva";803;1
"Unit";"Zergling";"Larva";804;1
"Unit";"Zergling";"Larva";805;1
"Unit";"Zergling";"Larva";806;1
"Unit";"Zergling";"Larva";807;1
"Unit";"Zergling";"Larva";808;1
"Unit";"Zergling";"Larva";809;1
"Unit";"Zergling";"Larva";810;1
"Unit";"Zergling";"Larva";811;1
"Unit";"Zergling";"Larva";812;1
"Unit";"Zergling";"Larva";813;1
"Unit";"Zergling";"Larva";814;1
"Unit";"Baneling";"Zergling";815;0
"Unit";"Baneling";"Zergling";815;0
"Unit";"Baneling";"Zergling";815;0
"Unit";"Baneling";"Zergling";815;0
"Unit";"Baneling";"Zergling";815;0
"Unit";"Baneling";"Zergling";815;0
"Unit";"Baneling";"Zergling";815;0
"Unit";"Baneling";"Zergling";815;0
"Unit";"Baneling";"Zergling";815;0
"Unit";"Baneling";"Zergling";815;0
"Unit";"Zergling";"Larva";815;1
"Unit";"Zergling";"Larva";816;1
"Unit";"Zergling";"Larva";817;1
"Unit";"Zergling";"Larva";818;1
"Unit";"Zergling";"Larva";819;1
"Unit";"Zergling";"Larva";820;1
"Unit";"Zergling";"Larva";821;1
"Unit";"Zergling";"Larva";822;1
"Unit";"Zergling";"Larva";823;1
"Unit";"Zergling";"Larva";824;1
"Unit";"Zergling";"Larva";825;1
"Unit";"Zergling";"Larva";826;1
"Unit";"Zergling";"Larva";827;1
"Unit";"Zergling";"Larva";828;1
"Unit";"Zergling";"Larva";829;1
"Unit";"Zergling";"Larva";830;1
"Unit";"Zergling";"Larva";831;1
"Unit";"Zergling";"Larva";832;1
"Unit";"Zergling";"Larva";833;1
"Unit";"Zergling";"Larva";834;1
"Unit";"Zergling";"Larva";835;1
"Unit";"Zergling";"Larva";836;1
"Unit";"Zergling";"Larva";837;1
"Unit";"Zergling";"Larva";838;1
"Unit";"Hydralisk";"Larva";839;2
"Unit";"Baneling";"Zergling";841;0
"Unit";"Baneling";"Zergling";841;0
"Unit";"Zergling";"Larva";841;1
"Unit";"Zergling";"Larva";842;1
"Unit";"Zergling";"Larva";843;1
"Unit";"Zergling";"Larva";844;1
"Unit";"Zergling";"Larva";845;1
"Unit";"Zergling";"Larva";846;1
"Unit";"Zergling";"Larva";847;1
"Unit";"Zergling";"Larva";848;1
"Unit";"Baneling";"Zergling";849;0
"Unit";"Baneling";"Zergling";849;0
"Unit";"Baneling";"Zergling";849;0
"Unit";"Baneling";"Zergling";849;0
"Unit";"Baneling";"Zergling";849;0
"Unit";"Baneling";"Zergling";849;0
"Unit";"Baneling";"Zergling";849;0
"Unit";"Baneling";"Zergling";849;0
"Unit";"Baneling";"Zergling";849;0
"Unit";"Baneling";"Zergling";849;0
"Unit";"Zergling";"Larva";849;1
"Unit";"Zergling";"Larva";850;1
"Unit";"Zergling";"Larva";851;1
"Unit";"Zergling";"Larva";852;1
"Unit";"Zergling";"Larva";853;1
"Unit";"Zergling";"Larva";854;1
"Unit";"Zergling";"Larva";855;1
"Unit";"Zergling";"Larva";856;1
"Unit";"Zergling";"Larva";857;1
"Unit";"Zergling";"Larva";858;1
"Unit";"Zergling";"Larva";859;1
"Unit";"Zergling";"Larva";860;1
"Unit";"Zergling";"Larva";861;1
"Unit";"Zergling";"Larva";862;1
"Unit";"Zergling";"Larva";863;1
"Unit";"Zergling";"Larva";864;1
"Unit";"Zergling";"Larva";865;1
"Unit";"Zergling";"Larva";866;1
"Unit";"Zergling";"Larva";867;1
"Unit";"Zergling";"Larva";868;1
"Unit";"Baneling";"Zergling";869;0
"Unit";"Baneling";"Zergling";869;0
"Unit";"Zergling";"Larva";869;1
"Unit";"Zergling";"Larva";870;1
"Unit";"Zergling";"Larva";871;1
"Unit";"Zergling";"Larva";872;1
"Unit";"Zergling";"Larva";873;1
"Unit";"Zergling";"Larva";874;1
"Unit";"Zergling";"Larva";875;1
"Unit";"Zergling";"Larva";876;1
"Unit";"Zergling";"Larva";877;1
"Unit";"Zergling";"Larva";878;1
"Unit";"Zergling";"Larva";879;1
"Unit";"Zergling";"Larva";880;1
"Unit";"Zergling";"Larva";881;1
"Unit";"Zergling";"Larva";882;1
"Unit";"Zergling";"Larva";883;1
"Unit";"Zergling";"Larva";884;1
"Unit";"Zergling";"Larva";885;1
"Unit";"Zergling";"Larva";886;1
"Unit";"Zergling";"Larva";887;1
"Unit";"Zergling";"Larva";888;1
"Unit";"Zergling";"Larva";889;1
"Unit";"Zergling";"Larva";890;1
"Unit";"Zergling";"Larva";891;1
"Unit";"Zergling";"Larva";892;1
"Unit";"Zergling";"Larva";893;1
"Unit";"Zergling";"Larva";894;1
"Unit";"Zergling";"Larva";895;1
"Unit";"Zergling";"Larva";896;1
"Unit";"Zergling";"Larva";897;1
"Unit";"Zergling";"Larva";898;1
"Unit";"Hydralisk";"Larva";899;2
"Unit";"Hydralisk";"Larva";901;2
"Unit";"Zergling";"Larva";903;1
"Unit";"Zergling";"Larva";904;1
"Unit";"Zergling";"Larva";905;1
"Unit";"Zergling";"Larva";906;1
"Unit";"Zergling";"Larva";907;1
"Unit";"Zergling";"Larva";908;1
"Unit";"Zergling";"Larva";909;1
"Unit";"Zergling";"Larva";910;1
"Unit";"Hydralisk";"Larva";911;2
"Unit";"Hydralisk";"Larva";913;2
"Unit";"Hydralisk";"Larva";915;2
"Unit";"Zergling";"Larva";917;1
"Unit";"Zergling";"Larva";918;1
"Unit";"Baneling";"Zergling";919;0
"Unit";"Baneling";"Zergling";919;0
"Unit";"Baneling";"Zergling";919;0
"Unit";"Baneling";"Zergling";919;0
"Unit";"Baneling";"Zergling";919;0
"Unit";"Baneling";"Zergling";919;0
"Unit";"Baneling";"Zergling";919;0
"Unit";"Baneling";"Zergling";919;0
"Unit";"Baneling";"Zergling";919;0
"Unit";"Baneling";"Zergling";919;0
"Unit";"Baneling";"Zergling";919;0
"Unit";"Baneling";"Zergling";919;0
"Unit";"Baneling";"Zergling";919;0
"Unit";"Baneling";"Zergling";919;0
"Unit";"Baneling";"Zergling";919;0
"Unit";"Baneling";"Zergling";919;0
"Unit";"Baneling";"Zergling";919;0
"Unit";"Baneling";"Zergling";919;0
"Unit";"Baneling";"Zergling";919;0
"Unit";"Baneling";"Zergling";919;0
"Unit";"Baneling";"Zergling";919;0
"Unit";"Baneling";"Zergling";919;0
"Unit";"Baneling";"Zergling";919;0
"Unit";"Baneling";"Zergling";919;0
"Unit";"Baneling";"Zergling";919;0
"Unit";"Baneling";"Zergling";919;0
"Unit";"Baneling";"Zergling";919;0
"Unit";"Baneling";"Zergling";919;0
"Unit";"Baneling";"Zergling";919;0
"Unit";"Baneling";"Zergling";919;0
"Unit";"Baneling";"Zergling";919;0
"Unit";"Baneling";"Zergling";919;0
"Unit";"Baneling";"Zergling";919;0
"Unit";"Baneling";"Zergling";919;0
"Unit";"Zergling";"Larva";919;1
"Unit";"Zergling";"Larva";920;1
"Unit";"Zergling";"Larva";921;1
"Unit";"Zergling";"Larva";922;1
"Unit";"Zergling";"Larva";923;1
"Unit";"Zergling";"Larva";924;1
"Unit";"Zergling";"Larva";925;1
"Unit";"Zergling";"Larva";926;1
"Unit";"Zergling";"Larva";927;1
"Unit";"Zergling";"Larva";928;1
"Unit";"Zergling";"Larva";929;1
"Unit";"Zergling";"Larva";930;1
"Unit";"Zergling";"Larva";931;1
"Unit";"Zergling";"Larva";932;1
"Upgrade";"SprayZerg";NA;933;0
"Upgrade";"SprayZerg";NA;933;0
"Upgrade";"SprayZerg";NA;933;0
"Upgrade";"zerglingmovementspeed";NA;933;0
"Upgrade";"SprayZerg";NA;933;0
"Upgrade";"SprayZerg";NA;933;0
"Upgrade";"CentrificalHooks";NA;933;0
"Upgrade";"ZergGroundArmorsLevel1";NA;933;0
"Upgrade";"ZergMeleeWeaponsLevel1";NA;933;0
"Upgrade";"SprayZerg";NA;933;0
"Upgrade";"overlordspeed";NA;933;0
"Upgrade";"EvolveGroovedSpines";NA;933;0
"Upgrade";"EvolveMuscularAugments";NA;933;0
"Upgrade";"SprayZerg";NA;933;0
"Upgrade";"ZergGroundArmorsLevel2";NA;933;0
"Upgrade";"ZergMeleeWeaponsLevel2";NA;933;0
"Upgrade";"SprayZerg";NA;933;0
"Upgrade";"SprayZerg";NA;933;0
"Upgrade";"zerglingattackspeed";NA;933;0
"Upgrade";"ZergMissileWeaponsLevel1";NA;933;0
"Upgrade";"SprayZerg";NA;933;0
"Upgrade";"SprayZerg";NA;933;0
"Upgrade";"ZergFlyerWeaponsLevel1";NA;933;0
"Upgrade";"SprayZerg";NA;933;0
"Upgrade";"ZergFlyerWeaponsLevel2";NA;933;0
"Upgrade";"ZergGroundArmorsLevel3";NA;933;0
"Upgrade";"ZergMeleeWeaponsLevel3";NA;933;0
