"type";"unit_name";"on_building";"total_supply";"supply"
"Unit";"Overlord";"Larva";12;0
"Building";"Extractor";NA;18;0
"Unit";"Overlord";"Larva";21;0
"Building";"SpawningPool";NA;19;0
"Building";"Hatchery";NA;17;0
"Unit";"Zergling";"Larva";23;1
"Unit";"Zergling";"Larva";23;1
"Unit";"Zergling";"Larva";23;1
"Unit";"Zergling";"Larva";23;1
"Unit";"Queen";"Hatchery";23;2
"Unit";"Queen";"Hatchery";23;2
"Building";"CreepTumorQueen";NA;36;0
"Unit";"Overlord";"Larva";36;0
"Unit";"Queen";"Hatchery";36;2
"Building";"CreepTumor";NA;40;0
"Unit";"Overlord";"Larva";44;0
"Building";"CreepTumor";NA;49;0
"Building";"CreepTumorQueen";NA;49;0
"Unit";"Overlord";"Larva";49;0
"Unit";"Overlord";"Larva";49;0
"Unit";"Overlord";"Larva";49;0
"Unit";"Zergling";"Larva";49;1
"Unit";"Zergling";"Larva";49;1
"Unit";"Zergling";"Larva";49;1
"Unit";"Zergling";"Larva";49;1
"Unit";"Zergling";"Larva";49;1
"Unit";"Zergling";"Larva";49;1
"Unit";"Overlord";"Larva";49;0
"Unit";"Overlord";"Larva";49;0
"Building";"Hatchery";NA;44;0
"Unit";"Zergling";"Larva";56;1
"Unit";"Zergling";"Larva";56;1
"Unit";"Zergling";"Larva";56;1
"Unit";"Zergling";"Larva";56;1
"Unit";"Zergling";"Larva";56;1
"Unit";"Zergling";"Larva";56;1
"Unit";"Zergling";"Larva";56;1
"Unit";"Zergling";"Larva";56;1
"Unit";"Queen";"Hatchery";49;2
"Building";"EvolutionChamber";NA;60;0
"Building";"EvolutionChamber";NA;60;0
"Building";"CreepTumorQueen";NA;70;0
"Unit";"Overlord";"Larva";68;0
"Building";"CreepTumorQueen";NA;70;0
"Building";"CreepTumor";NA;70;0
"Building";"CreepTumor";NA;70;0
"Unit";"Zergling";"Larva";76;1
"Unit";"Zergling";"Larva";76;1
"Unit";"Zergling";"Larva";76;1
"Unit";"Zergling";"Larva";76;1
"Unit";"Zergling";"Larva";76;1
"Unit";"Zergling";"Larva";76;1
"Unit";"Zergling";"Larva";76;1
"Unit";"Zergling";"Larva";76;1
"Unit";"Zergling";"Larva";76;1
"Unit";"Zergling";"Larva";76;1
"Unit";"Zergling";"Larva";76;1
"Unit";"Zergling";"Larva";76;1
"Unit";"Queen";"Hatchery";70;2
"Unit";"Queen";"Hatchery";70;2
"Building";"CreepTumor";NA;97;0
"Building";"CreepTumor";NA;101;0
"Building";"CreepTumor";NA;108;0
"Building";"CreepTumor";NA;108;0
"Building";"Extractor";NA;97;0
"Building";"CreepTumorQueen";NA;110;0
"Building";"CreepTumorQueen";NA;113;0
"Building";"Extractor";NA;108;0
"Building";"CreepTumorQueen";NA;114;0
"Building";"Extractor";NA;108;0
"Unit";"Queen";"Hatchery";97;2
"Building";"CreepTumor";NA;114;0
"Building";"Extractor";NA;114;0
"Unit";"Zergling";"Larva";119;1
"Unit";"Zergling";"Larva";119;1
"Unit";"Zergling";"Larva";119;1
"Unit";"Zergling";"Larva";119;1
"Unit";"Zergling";"Larva";119;1
"Unit";"Zergling";"Larva";119;1
"Unit";"Zergling";"Larva";119;1
"Unit";"Zergling";"Larva";119;1
"Unit";"Zergling";"Larva";119;1
"Unit";"Zergling";"Larva";119;1
"Unit";"Zergling";"Larva";119;1
"Unit";"Zergling";"Larva";119;1
"Unit";"Zergling";"Larva";119;1
"Unit";"Zergling";"Larva";119;1
"Unit";"Zergling";"Larva";119;1
"Unit";"Zergling";"Larva";119;1
"Building";"CreepTumor";NA;123;0
"Building";"CreepTumor";NA;123;0
"Building";"CreepTumor";NA;123;0
"Building";"CreepTumor";NA;123;0
"Building";"CreepTumor";NA;123;0
"Building";"CreepTumor";NA;123;0
"Unit";"Overlord";"Larva";123;0
"Unit";"Overlord";"Larva";123;0
"Building";"Extractor";NA;123;0
"Unit";"Overlord";"Larva";123;0
"Unit";"Overlord";"Larva";123;0
"Unit";"Overlord";"Larva";123;0
"Unit";"Overlord";"Larva";139;0
"Unit";"Overlord";"Larva";139;0
"Unit";"Overlord";"Larva";139;0
"Upgrade";"ZergGroundArmorsLevel1";"EvolutionChamber";97;0
"Upgrade";"ZergMeleeWeaponsLevel1";"EvolutionChamber";97;0
"Building";"SporeCrawler";NA;140;0
"Building";"BanelingNest";NA;123;0
"Building";"Hatchery";NA;114;0
"Building";"CreepTumor";NA;140;0
"Building";"CreepTumor";NA;147;0
"Building";"CreepTumor";NA;147;0
"Building";"CreepTumor";NA;147;0
"Building";"CreepTumor";NA;147;0
"Building";"CreepTumor";NA;147;0
"Building";"HydraliskDen";NA;140;0
"Building";"CreepTumor";NA;147;0
"Unit";"Zergling";"Larva";147;1
"Unit";"Zergling";"Larva";147;1
"Unit";"Zergling";"Larva";147;1
"Unit";"Zergling";"Larva";147;1
"Unit";"Zergling";"Larva";147;1
"Unit";"Zergling";"Larva";147;1
"Unit";"Zergling";"Larva";147;1
"Unit";"Zergling";"Larva";147;1
"Unit";"Zergling";"Larva";154;1
"Unit";"Zergling";"Larva";154;1
"Unit";"Zergling";"Larva";154;1
"Unit";"Zergling";"Larva";154;1
"Unit";"Zergling";"Larva";154;1
"Unit";"Zergling";"Larva";154;1
"Building";"CreepTumorQueen";NA;154;0
"Building";"CreepTumorQueen";NA;154;0
"Building";"CreepTumor";NA;154;0
"Unit";"Zergling";"Larva";154;1
"Unit";"Zergling";"Larva";154;1
"Unit";"Zergling";"Larva";154;1
"Unit";"Zergling";"Larva";154;1
"Unit";"Baneling";"Zergling";162;0
"Unit";"Baneling";"Zergling";162;0
"Unit";"Baneling";"Zergling";162;0
"Unit";"Baneling";"Zergling";162;0
"Unit";"Baneling";"Zergling";162;0
"Unit";"Baneling";"Zergling";162;0
"Unit";"Baneling";"Zergling";162;0
"Unit";"Baneling";"Zergling";162;0
"Unit";"Baneling";"Zergling";162;0
"Building";"CreepTumor";NA;168;0
"Unit";"Baneling";"Zergling";162;0
"Unit";"Baneling";"Zergling";162;0
"Unit";"Baneling";"Zergling";162;0
"Building";"CreepTumor";NA;172;0
"Unit";"Zergling";"Larva";168;1
"Unit";"Zergling";"Larva";168;1
"Unit";"Zergling";"Larva";168;1
"Unit";"Zergling";"Larva";168;1
"Unit";"Zergling";"Larva";168;1
"Unit";"Zergling";"Larva";168;1
"Unit";"Zergling";"Larva";168;1
"Unit";"Zergling";"Larva";168;1
"Unit";"Queen";"Hatchery";154;2
"Unit";"Baneling";"Zergling";186;0
"Unit";"Baneling";"Zergling";186;0
"Building";"CreepTumor";NA;186;0
"Unit";"Hydralisk";"Larva";182;2
"Building";"CreepTumor";NA;186;0
"Building";"CreepTumor";NA;186;0
"Unit";"Hydralisk";"Larva";182;2
"Unit";"Hydralisk";"Larva";184;2
"Unit";"Hydralisk";"Larva";184;2
"Unit";"Hydralisk";"Larva";184;2
"Unit";"Hydralisk";"Larva";184;2
"Unit";"Hydralisk";"Larva";184;2
"Unit";"Hydralisk";"Larva";184;2
"Building";"CreepTumor";NA;186;0
"Unit";"Hydralisk";"Larva";184;2
"Building";"CreepTumor";NA;186;0
"Building";"CreepTumor";NA;186;0
"Unit";"Hydralisk";"Larva";184;2
"Unit";"Zergling";"Larva";186;1
"Unit";"Zergling";"Larva";186;1
"Unit";"Zergling";"Larva";186;1
"Unit";"Zergling";"Larva";186;1
"Unit";"Zergling";"Larva";186;1
"Unit";"Zergling";"Larva";186;1
"Unit";"Zergling";"Larva";186;1
"Unit";"Zergling";"Larva";186;1
"Unit";"Zergling";"Larva";186;1
"Unit";"Zergling";"Larva";186;1
"Unit";"Zergling";"Larva";186;1
"Unit";"Zergling";"Larva";186;1
"Unit";"Zergling";"Larva";202;1
"Unit";"Zergling";"Larva";202;1
"Unit";"Zergling";"Larva";202;1
"Unit";"Zergling";"Larva";202;1
"Unit";"Zergling";"Larva";202;1
"Unit";"Zergling";"Larva";202;1
"Unit";"Zergling";"Larva";202;1
"Unit";"Zergling";"Larva";202;1
"Unit";"Zergling";"Larva";202;1
"Unit";"Zergling";"Larva";202;1
"Upgrade";"EvolveGroovedSpines";"HydraliskDen";176;0
"Unit";"Zergling";"Larva";218;1
"Unit";"Zergling";"Larva";218;1
"Unit";"Zergling";"Larva";218;1
"Unit";"Zergling";"Larva";218;1
"Unit";"Zergling";"Larva";218;1
"Unit";"Zergling";"Larva";218;1
"Unit";"Zergling";"Larva";218;1
"Unit";"Zergling";"Larva";218;1
"Unit";"Zergling";"Larva";218;1
"Unit";"Zergling";"Larva";218;1
"Building";"CreepTumorQueen";NA;238;0
"Building";"CreepTumor";NA;238;0
"Building";"CreepTumorQueen";NA;238;0
"Building";"CreepTumor";NA;238;0
"Building";"CreepTumor";NA;238;0
"Building";"CreepTumor";NA;238;0
"Building";"Extractor";NA;238;0
"Building";"Extractor";NA;238;0
"Building";"CreepTumor";NA;243;0
"Building";"CreepTumor";NA;243;0
"Upgrade";"ZergGroundArmorsLevel2";"EvolutionChamber";172;0
"Building";"CreepTumor";NA;243;0
"Upgrade";"ZergMeleeWeaponsLevel2";"EvolutionChamber";172;0
"Unit";"Hydralisk";"Larva";238;2
"Unit";"Hydralisk";"Larva";238;2
"Unit";"Hydralisk";"Larva";238;2
"Unit";"Hydralisk";"Larva";238;2
"Unit";"Hydralisk";"Larva";238;2
"Unit";"Hydralisk";"Larva";238;2
"Unit";"Hydralisk";"Larva";238;2
"Unit";"Hydralisk";"Larva";238;2
"Unit";"Hydralisk";"Larva";238;2
"Unit";"Hydralisk";"Larva";243;2
"Unit";"Hydralisk";"Larva";243;2
"Unit";"Hydralisk";"Larva";243;2
"Building";"InfestationPit";NA;238;0
"Building";"CreepTumor";NA;263;0
"Unit";"Baneling";"Zergling";263;0
"Unit";"Zergling";"Larva";262;1
"Unit";"Zergling";"Larva";262;1
"Unit";"Zergling";"Larva";262;1
"Unit";"Zergling";"Larva";262;1
"Unit";"Zergling";"Larva";263;1
"Unit";"Zergling";"Larva";263;1
"Unit";"Zergling";"Larva";263;1
"Unit";"Zergling";"Larva";263;1
"Unit";"Baneling";"Zergling";263;0
"Unit";"Baneling";"Zergling";263;0
"Unit";"Zergling";"Larva";263;1
"Unit";"Zergling";"Larva";263;1
"Unit";"Baneling";"Zergling";263;0
"Unit";"Baneling";"Zergling";263;0
"Unit";"Baneling";"Zergling";263;0
"Unit";"Baneling";"Zergling";263;0
"Unit";"Zergling";"Larva";263;1
"Unit";"Zergling";"Larva";263;1
"Unit";"Baneling";"Zergling";263;0
"Unit";"Baneling";"Zergling";263;0
"Unit";"Baneling";"Zergling";263;0
"Unit";"Baneling";"Zergling";263;0
"Unit";"Zergling";"Larva";263;1
"Unit";"Zergling";"Larva";263;1
"Unit";"Baneling";"Zergling";263;0
"Unit";"Baneling";"Zergling";263;0
"Unit";"Baneling";"Zergling";263;0
"Unit";"Baneling";"Zergling";263;0
"Unit";"Zergling";"Larva";263;1
"Unit";"Zergling";"Larva";263;1
"Unit";"Baneling";"Zergling";263;0
"Building";"CreepTumor";NA;269;0
"Building";"CreepTumor";NA;269;0
"Building";"CreepTumor";NA;269;0
"Unit";"Zergling";"Larva";269;1
"Unit";"Zergling";"Larva";269;1
"Unit";"Zergling";"Larva";269;1
"Unit";"Zergling";"Larva";269;1
"Unit";"Zergling";"Larva";269;1
"Unit";"Zergling";"Larva";269;1
"Unit";"Zergling";"Larva";269;1
"Unit";"Zergling";"Larva";269;1
"Unit";"Zergling";"Larva";269;1
"Unit";"Zergling";"Larva";269;1
"Unit";"Zergling";"Larva";269;1
"Unit";"Zergling";"Larva";269;1
"Unit";"Zergling";"Larva";269;1
"Unit";"Zergling";"Larva";269;1
"Building";"CreepTumorQueen";NA;285;0
"Upgrade";"EvolveMuscularAugments";"HydraliskDen";244;0
"Building";"CreepTumorQueen";NA;299;0
"Building";"CreepTumorQueen";NA;299;0
"Building";"CreepTumor";NA;299;0
"Unit";"Overlord";"Larva";299;0
"Unit";"Overlord";"Larva";299;0
"Unit";"Overlord";"Larva";299;0
"Unit";"Overlord";"Larva";299;0
"Building";"Hatchery";NA;244;0
"Building";"Hatchery";NA;244;0
"Building";"SpawningPool";NA;299;0
"Unit";"Hydralisk";"Larva";299;2
"Unit";"Hydralisk";"Larva";299;2
"Unit";"Hydralisk";"Larva";299;2
"Unit";"Hydralisk";"Larva";299;2
"Unit";"Hydralisk";"Larva";299;2
"Unit";"Hydralisk";"Larva";299;2
"Unit";"Hydralisk";"Larva";299;2
"Unit";"Hydralisk";"Larva";299;2
"Unit";"Hydralisk";"Larva";299;2
"Unit";"Hydralisk";"Larva";299;2
"Unit";"Overlord";"Larva";299;0
"Building";"CreepTumor";NA;319;0
"Unit";"Zergling";"Larva";319;1
"Unit";"Zergling";"Larva";319;1
"Unit";"Zergling";"Larva";319;1
"Unit";"Zergling";"Larva";319;1
"Unit";"Zergling";"Larva";319;1
"Unit";"Zergling";"Larva";319;1
"Unit";"Zergling";"Larva";319;1
"Unit";"Zergling";"Larva";319;1
"Unit";"Zergling";"Larva";319;1
"Unit";"Zergling";"Larva";319;1
"Unit";"Zergling";"Larva";319;1
"Unit";"Zergling";"Larva";319;1
"Unit";"Zergling";"Larva";319;1
"Unit";"Zergling";"Larva";319;1
"Unit";"Zergling";"Larva";319;1
"Unit";"Zergling";"Larva";319;1
"Unit";"Zergling";"Larva";319;1
"Unit";"Zergling";"Larva";319;1
"Unit";"Zergling";"Larva";319;1
"Unit";"Zergling";"Larva";319;1
"Unit";"Zergling";"Larva";319;1
"Unit";"Zergling";"Larva";319;1
"Unit";"Zergling";"Larva";319;1
"Unit";"Zergling";"Larva";319;1
"Unit";"Zergling";"Larva";319;1
"Unit";"Zergling";"Larva";319;1
"Unit";"Zergling";"Larva";319;1
"Unit";"Zergling";"Larva";319;1
"Unit";"Zergling";"Larva";319;1
"Unit";"Zergling";"Larva";319;1
"Unit";"Zergling";"Larva";319;1
"Unit";"Zergling";"Larva";319;1
"Unit";"Zergling";"Larva";319;1
"Unit";"Zergling";"Larva";319;1
"Unit";"Zergling";"Larva";319;1
"Unit";"Zergling";"Larva";319;1
"Unit";"Zergling";"Larva";330;1
"Unit";"Zergling";"Larva";330;1
"Unit";"Zergling";"Larva";358;1
"Unit";"Zergling";"Larva";358;1
"Unit";"Zergling";"Larva";364;1
"Unit";"Zergling";"Larva";364;1
"Unit";"Zergling";"Larva";364;1
"Unit";"Zergling";"Larva";364;1
"Unit";"Zergling";"Larva";364;1
"Unit";"Zergling";"Larva";364;1
"Unit";"Zergling";"Larva";364;1
"Unit";"Zergling";"Larva";364;1
"Unit";"Zergling";"Larva";364;1
"Unit";"Zergling";"Larva";364;1
"Unit";"Zergling";"Larva";364;1
"Unit";"Zergling";"Larva";364;1
"Unit";"Zergling";"Larva";364;1
"Unit";"Zergling";"Larva";364;1
"Unit";"Zergling";"Larva";364;1
"Unit";"Zergling";"Larva";364;1
"Unit";"Zergling";"Larva";364;1
"Unit";"Zergling";"Larva";364;1
"Unit";"Zergling";"Larva";364;1
"Unit";"Zergling";"Larva";364;1
"Unit";"Zergling";"Larva";364;1
"Unit";"Zergling";"Larva";364;1
"Unit";"Zergling";"Larva";364;1
"Unit";"Zergling";"Larva";364;1
"Unit";"Zergling";"Larva";364;1
"Unit";"Zergling";"Larva";364;1
"Unit";"Zergling";"Larva";364;1
"Unit";"Zergling";"Larva";364;1
"Unit";"Zergling";"Larva";364;1
"Unit";"Zergling";"Larva";364;1
"Unit";"Zergling";"Larva";364;1
"Unit";"Zergling";"Larva";364;1
"Unit";"Zergling";"Larva";364;1
"Unit";"Zergling";"Larva";364;1
"Unit";"Zergling";"Larva";364;1
"Unit";"Zergling";"Larva";364;1
"Unit";"Zergling";"Larva";364;1
"Unit";"Zergling";"Larva";364;1
"Unit";"Zergling";"Larva";392;1
"Unit";"Zergling";"Larva";392;1
"Unit";"Zergling";"Larva";392;1
"Unit";"Zergling";"Larva";392;1
"Unit";"Zergling";"Larva";392;1
"Unit";"Zergling";"Larva";392;1
"Unit";"Zergling";"Larva";392;1
"Unit";"Zergling";"Larva";392;1
"Unit";"Zergling";"Larva";392;1
"Unit";"Zergling";"Larva";392;1
"Unit";"Zergling";"Larva";392;1
"Unit";"Zergling";"Larva";392;1
"Unit";"Zergling";"Larva";392;1
"Unit";"Zergling";"Larva";392;1
"Unit";"Zergling";"Larva";392;1
"Unit";"Zergling";"Larva";392;1
"Unit";"Zergling";"Larva";392;1
"Unit";"Zergling";"Larva";392;1
"Unit";"Hydralisk";"Larva";424;2
"Unit";"Hydralisk";"Larva";424;2
"Unit";"Hydralisk";"Larva";424;2
"Unit";"Hydralisk";"Larva";424;2
"Unit";"Hydralisk";"Larva";424;2
"Unit";"Hydralisk";"Larva";424;2
"Unit";"Hydralisk";"Larva";424;2
"Unit";"Hydralisk";"Larva";424;2
"Unit";"Hydralisk";"Larva";424;2
"Unit";"Hydralisk";"Larva";424;2
"Unit";"Hydralisk";"Larva";424;2
"Unit";"Hydralisk";"Larva";424;2
"Unit";"Hydralisk";"Larva";424;2
"Unit";"Hydralisk";"Larva";424;2
"Unit";"Hydralisk";"Larva";424;2
"Unit";"Hydralisk";"Larva";424;2
"Building";"CreepTumor";NA;457;0
"Building";"CreepTumor";NA;457;0
"Unit";"Queen";"Hatchery";424;2
"Unit";"Queen";"Hatchery";424;2
"Building";"CreepTumorQueen";NA;459;0
"Unit";"Zergling";"Larva";457;1
"Unit";"Zergling";"Larva";457;1
"Building";"CreepTumorQueen";NA;460;0
"Unit";"Zergling";"Larva";457;1
"Unit";"Zergling";"Larva";457;1
"Unit";"Zergling";"Larva";457;1
"Unit";"Zergling";"Larva";457;1
"Unit";"Zergling";"Larva";457;1
"Unit";"Zergling";"Larva";457;1
"Unit";"Zergling";"Larva";457;1
"Unit";"Zergling";"Larva";457;1
"Unit";"Zergling";"Larva";457;1
"Unit";"Zergling";"Larva";457;1
"Unit";"Zergling";"Larva";457;1
"Unit";"Zergling";"Larva";457;1
"Unit";"Zergling";"Larva";457;1
"Unit";"Zergling";"Larva";457;1
"Unit";"Zergling";"Larva";457;1
"Unit";"Zergling";"Larva";457;1
"Unit";"Zergling";"Larva";457;1
"Unit";"Zergling";"Larva";457;1
"Unit";"Zergling";"Larva";457;1
"Unit";"Zergling";"Larva";457;1
"Unit";"Zergling";"Larva";457;1
"Unit";"Zergling";"Larva";457;1
"Unit";"Zergling";"Larva";457;1
"Unit";"Zergling";"Larva";457;1
"Unit";"Zergling";"Larva";457;1
"Unit";"Zergling";"Larva";457;1
"Unit";"Zergling";"Larva";457;1
"Unit";"Zergling";"Larva";457;1
"Unit";"Zergling";"Larva";457;1
"Unit";"Zergling";"Larva";457;1
"Building";"UltraliskCavern";NA;424;0
"Unit";"Queen";"Hatchery";457;2
"Unit";"Zergling";"Larva";463;1
"Unit";"Zergling";"Larva";463;1
"Unit";"Zergling";"Larva";463;1
"Unit";"Zergling";"Larva";463;1
"Unit";"Zergling";"Larva";463;1
"Unit";"Zergling";"Larva";463;1
"Unit";"Zergling";"Larva";463;1
"Unit";"Zergling";"Larva";463;1
"Unit";"Zergling";"Larva";463;1
"Unit";"Zergling";"Larva";463;1
"Unit";"Zergling";"Larva";463;1
"Unit";"Zergling";"Larva";463;1
"Unit";"Zergling";"Larva";463;1
"Unit";"Zergling";"Larva";463;1
"Unit";"Zergling";"Larva";463;1
"Unit";"Zergling";"Larva";463;1
"Unit";"Baneling";"Zergling";497;0
"Unit";"Baneling";"Zergling";499;0
"Unit";"Baneling";"Zergling";499;0
"Unit";"Baneling";"Zergling";499;0
"Unit";"Baneling";"Zergling";501;0
"Unit";"Baneling";"Zergling";501;0
"Unit";"Baneling";"Zergling";501;0
"Unit";"Baneling";"Zergling";503;0
"Unit";"Baneling";"Zergling";503;0
"Unit";"Baneling";"Zergling";503;0
"Unit";"Baneling";"Zergling";503;0
"Unit";"Baneling";"Zergling";505;0
"Unit";"Baneling";"Zergling";505;0
"Unit";"Baneling";"Zergling";505;0
"Unit";"Baneling";"Zergling";507;0
"Unit";"Baneling";"Zergling";507;0
"Unit";"Baneling";"Zergling";507;0
"Unit";"Baneling";"Zergling";507;0
"Unit";"Baneling";"Zergling";509;0
"Unit";"Baneling";"Zergling";509;0
"Unit";"Baneling";"Zergling";509;0
"Unit";"Baneling";"Zergling";509;0
"Unit";"Baneling";"Zergling";511;0
"Unit";"Baneling";"Zergling";511;0
"Unit";"Overlord";"Larva";513;0
"Unit";"Overlord";"Larva";513;0
"Unit";"Overlord";"Larva";513;0
"Unit";"Overlord";"Larva";513;0
"Building";"CreepTumor";NA;513;0
"Unit";"Ultralisk";"Larva";513;6
"Unit";"Ultralisk";"Larva";513;6
"Unit";"Zergling";"Larva";513;1
"Unit";"Zergling";"Larva";513;1
"Unit";"Ultralisk";"Larva";513;6
"Unit";"Zergling";"Larva";513;1
"Unit";"Zergling";"Larva";513;1
"Unit";"Zergling";"Larva";513;1
"Unit";"Zergling";"Larva";513;1
"Unit";"Zergling";"Larva";513;1
"Unit";"Zergling";"Larva";513;1
"Unit";"Zergling";"Larva";513;1
"Unit";"Zergling";"Larva";513;1
"Unit";"Zergling";"Larva";513;1
"Unit";"Zergling";"Larva";513;1
"Unit";"Zergling";"Larva";513;1
"Unit";"Zergling";"Larva";513;1
"Unit";"Zergling";"Larva";513;1
"Unit";"Zergling";"Larva";513;1
"Unit";"Zergling";"Larva";513;1
"Unit";"Zergling";"Larva";513;1
"Upgrade";"ChitinousPlating";"UltraliskCavern";513;0
"Unit";"Ultralisk";"Larva";513;6
"Unit";"Ultralisk";"Larva";513;6
"Unit";"Zergling";"Larva";549;1
"Unit";"Zergling";"Larva";549;1
"Unit";"Zergling";"Larva";549;1
"Unit";"Zergling";"Larva";549;1
"Unit";"Zergling";"Larva";549;1
"Unit";"Zergling";"Larva";549;1
"Unit";"Zergling";"Larva";549;1
"Unit";"Zergling";"Larva";549;1
"Unit";"Zergling";"Larva";549;1
"Unit";"Zergling";"Larva";549;1
"Unit";"Zergling";"Larva";549;1
"Unit";"Zergling";"Larva";549;1
"Unit";"Zergling";"Larva";549;1
"Unit";"Zergling";"Larva";549;1
"Unit";"Zergling";"Larva";549;1
"Unit";"Zergling";"Larva";549;1
"Unit";"Zergling";"Larva";549;1
"Unit";"Zergling";"Larva";549;1
"Unit";"Zergling";"Larva";549;1
"Unit";"Zergling";"Larva";549;1
"Unit";"Zergling";"Larva";549;1
"Unit";"Zergling";"Larva";549;1
"Unit";"Zergling";"Larva";549;1
"Unit";"Zergling";"Larva";549;1
"Unit";"Zergling";"Larva";549;1
"Unit";"Zergling";"Larva";549;1
"Unit";"Zergling";"Larva";549;1
"Unit";"Zergling";"Larva";549;1
"Building";"Hatchery";NA;513;0
"Upgrade";"ZergGroundArmorsLevel3";"EvolutionChamber";495;0
"Upgrade";"ZergMeleeWeaponsLevel3";"EvolutionChamber";495;0
"Building";"CreepTumorQueen";NA;592;0
"Building";"CreepTumorQueen";NA;592;0
"Unit";"Zergling";"Larva";592;1
"Unit";"Zergling";"Larva";592;1
"Building";"CreepTumorQueen";NA;592;0
"Unit";"Zergling";"Larva";592;1
"Unit";"Zergling";"Larva";592;1
"Unit";"Zergling";"Larva";592;1
"Unit";"Zergling";"Larva";592;1
"Unit";"Zergling";"Larva";592;1
"Unit";"Zergling";"Larva";592;1
"Unit";"Zergling";"Larva";592;1
"Unit";"Zergling";"Larva";592;1
"Unit";"Zergling";"Larva";592;1
"Unit";"Zergling";"Larva";592;1
"Unit";"Zergling";"Larva";592;1
"Unit";"Zergling";"Larva";592;1
"Unit";"Zergling";"Larva";592;1
"Unit";"Zergling";"Larva";592;1
"Unit";"Zergling";"Larva";592;1
"Unit";"Zergling";"Larva";592;1
"Unit";"Zergling";"Larva";592;1
"Unit";"Zergling";"Larva";592;1
"Unit";"Zergling";"Larva";592;1
"Unit";"Zergling";"Larva";592;1
"Unit";"Zergling";"Larva";592;1
"Unit";"Zergling";"Larva";592;1
"Unit";"Zergling";"Larva";592;1
"Unit";"Zergling";"Larva";592;1
"Unit";"Zergling";"Larva";592;1
"Unit";"Zergling";"Larva";592;1
"Unit";"Zergling";"Larva";592;1
"Unit";"Zergling";"Larva";592;1
"Unit";"Zergling";"Larva";592;1
"Unit";"Zergling";"Larva";592;1
"Unit";"Zergling";"Larva";592;1
"Unit";"Zergling";"Larva";592;1
