"type";"unit_name";"on_building";"total_supply";"supply"
"Unit";"Overlord";"Larva";13;0
"Building";"Extractor";NA;19;0
"Building";"SpawningPool";NA;19;0
"Building";"Hatchery";NA;17;0
"Unit";"Overlord";"Larva";22;0
"Unit";"Zergling";"Larva";23;1
"Unit";"Zergling";"Larva";23;1
"Unit";"Zergling";"Larva";23;1
"Unit";"Zergling";"Larva";23;1
"Unit";"Queen";"Hatchery";23;2
"Unit";"Queen";"Hatchery";23;2
"Unit";"Overlord";"Larva";35;0
"Unit";"Queen";"Hatchery";33;2
"Building";"Hatchery";NA;25;0
"Unit";"Overlord";"Larva";38;0
"Building";"CreepTumorQueen";NA;42;0
"Unit";"Zergling";"Larva";46;1
"Unit";"Zergling";"Larva";46;1
"Unit";"Zergling";"Larva";46;1
"Unit";"Zergling";"Larva";46;1
"Building";"CreepTumorQueen";NA;50;0
"Building";"CreepTumor";NA;50;0
"Unit";"Zergling";"Larva";50;1
"Unit";"Zergling";"Larva";50;1
"Unit";"Zergling";"Larva";50;1
"Unit";"Zergling";"Larva";50;1
"Unit";"Zergling";"Larva";50;1
"Unit";"Zergling";"Larva";50;1
"Unit";"Zergling";"Larva";50;1
"Unit";"Zergling";"Larva";50;1
"Unit";"Queen";"Hatchery";50;2
"Building";"Extractor";NA;62;0
"Unit";"Queen";"Hatchery";50;2
"Unit";"Zergling";"Larva";62;1
"Unit";"Zergling";"Larva";62;1
"Unit";"Queen";"Hatchery";54;2
"Building";"CreepTumorQueen";NA;73;0
"Building";"BanelingNest";NA;62;0
"Building";"CreepTumor";NA;73;0
"Unit";"Overlord";"Larva";73;0
"Unit";"Overlord";"Larva";73;0
"Building";"CreepTumor";NA;73;0
"Unit";"Overlord";"Larva";73;0
"Building";"EvolutionChamber";NA;73;0
"Building";"EvolutionChamber";NA;73;0
"Building";"CreepTumorQueen";NA;73;0
"Unit";"Zergling";"Larva";73;1
"Unit";"Zergling";"Larva";73;1
"Unit";"Zergling";"Larva";73;1
"Unit";"Zergling";"Larva";73;1
"Unit";"Zergling";"Larva";73;1
"Unit";"Zergling";"Larva";73;1
"Unit";"Zergling";"Larva";73;1
"Unit";"Zergling";"Larva";73;1
"Unit";"Zergling";"Larva";73;1
"Unit";"Zergling";"Larva";73;1
"Unit";"Queen";"Hatchery";73;2
"Unit";"Zergling";"Larva";73;1
"Unit";"Zergling";"Larva";73;1
"Unit";"Zergling";"Larva";73;1
"Unit";"Zergling";"Larva";73;1
"Building";"CreepTumor";NA;85;0
"Building";"CreepTumorQueen";NA;85;0
"Unit";"Zergling";"Larva";85;1
"Unit";"Zergling";"Larva";85;1
"Building";"CreepTumor";NA;85;0
"Building";"CreepTumorQueen";NA;99;0
"Building";"CreepTumorQueen";NA;103;0
"Building";"CreepTumor";NA;103;0
"Unit";"Overlord";"Larva";103;0
"Unit";"Overlord";"Larva";103;0
"Unit";"Queen";"Hatchery";97;2
"Building";"CreepTumorQueen";NA;105;0
"Building";"CreepTumorQueen";NA;105;0
"Unit";"Zergling";"Larva";105;1
"Unit";"Zergling";"Larva";105;1
"Unit";"Zergling";"Larva";105;1
"Unit";"Zergling";"Larva";105;1
"Unit";"Zergling";"Larva";105;1
"Unit";"Zergling";"Larva";105;1
"Unit";"Zergling";"Larva";105;1
"Unit";"Zergling";"Larva";105;1
"Unit";"Zergling";"Larva";105;1
"Unit";"Zergling";"Larva";105;1
"Building";"CreepTumorQueen";NA;105;0
"Building";"CreepTumor";NA;105;0
"Building";"CreepTumor";NA;105;0
"Building";"CreepTumor";NA;105;0
"Building";"CreepTumorQueen";NA;105;0
"Building";"Extractor";NA;105;0
"Building";"Extractor";NA;107;0
"Building";"Extractor";NA;117;0
"Building";"Extractor";NA;117;0
"Building";"CreepTumor";NA;130;0
"Building";"CreepTumor";NA;131;0
"Building";"CreepTumor";NA;131;0
"Unit";"Overlord";"Larva";117;0
"Unit";"Baneling";"Zergling";129;0
"Unit";"Baneling";"Zergling";129;0
"Building";"CreepTumor";NA;131;0
"Unit";"Baneling";"Zergling";129;0
"Building";"CreepTumor";NA;131;0
"Unit";"Baneling";"Zergling";129;0
"Building";"CreepTumor";NA;133;0
"Building";"CreepTumor";NA;133;0
"Building";"CreepTumor";NA;133;0
"Building";"CreepTumorQueen";NA;133;0
"Building";"CreepTumorQueen";NA;133;0
"Unit";"Baneling";"Zergling";133;0
"Unit";"Baneling";"Zergling";133;0
"Unit";"Baneling";"Zergling";133;0
"Unit";"Baneling";"Zergling";133;0
"Unit";"Baneling";"Zergling";133;0
"Unit";"Zergling";"Larva";133;1
"Unit";"Zergling";"Larva";133;1
"Unit";"Zergling";"Larva";133;1
"Unit";"Zergling";"Larva";133;1
"Unit";"Zergling";"Larva";133;1
"Unit";"Zergling";"Larva";133;1
"Unit";"Zergling";"Larva";133;1
"Unit";"Zergling";"Larva";133;1
"Unit";"Zergling";"Larva";133;1
"Unit";"Zergling";"Larva";133;1
"Unit";"Zergling";"Larva";133;1
"Unit";"Zergling";"Larva";133;1
"Building";"HydraliskDen";NA;133;0
"Unit";"Zergling";"Larva";133;1
"Unit";"Zergling";"Larva";133;1
"Upgrade";"ZergGroundArmorsLevel1";"EvolutionChamber";103;0
"Upgrade";"ZergMeleeWeaponsLevel1";"EvolutionChamber";103;0
"Building";"CreepTumorQueen";NA;138;0
"Building";"CreepTumorQueen";NA;150;0
"Building";"CreepTumor";NA;152;0
"Building";"CreepTumor";NA;152;0
"Building";"CreepTumor";NA;152;0
"Building";"CreepTumor";NA;152;0
"Building";"CreepTumorQueen";NA;152;0
"Unit";"Overlord";"Larva";152;0
"Unit";"Overlord";"Larva";152;0
"Unit";"Overlord";"Larva";152;0
"Unit";"Overlord";"Larva";152;0
"Building";"Hatchery";NA;117;0
"Building";"CreepTumorQueen";NA;152;0
"Building";"CreepTumorQueen";NA;152;0
"Unit";"Zergling";"Larva";152;1
"Unit";"Zergling";"Larva";152;1
"Unit";"Zergling";"Larva";152;1
"Unit";"Zergling";"Larva";152;1
"Unit";"Zergling";"Larva";152;1
"Unit";"Zergling";"Larva";152;1
"Unit";"Zergling";"Larva";152;1
"Unit";"Zergling";"Larva";152;1
"Unit";"Zergling";"Larva";152;1
"Unit";"Zergling";"Larva";152;1
"Unit";"Zergling";"Larva";152;1
"Unit";"Zergling";"Larva";152;1
"Unit";"Zergling";"Larva";152;1
"Unit";"Zergling";"Larva";152;1
"Unit";"Zergling";"Larva";152;1
"Unit";"Zergling";"Larva";152;1
"Unit";"Zergling";"Larva";152;1
"Unit";"Zergling";"Larva";152;1
"Unit";"Zergling";"Larva";153;1
"Unit";"Zergling";"Larva";153;1
"Unit";"Zergling";"Larva";153;1
"Unit";"Zergling";"Larva";153;1
"Unit";"Zergling";"Larva";153;1
"Unit";"Zergling";"Larva";153;1
"Unit";"Zergling";"Larva";154;1
"Unit";"Zergling";"Larva";154;1
"Unit";"Zergling";"Larva";154;1
"Unit";"Zergling";"Larva";154;1
"Building";"CreepTumor";NA;154;0
"Building";"CreepTumor";NA;154;0
"Building";"CreepTumor";NA;182;0
"Building";"CreepTumor";NA;182;0
"Building";"CreepTumor";NA;182;0
"Building";"CreepTumor";NA;182;0
"Building";"CreepTumor";NA;182;0
"Building";"CreepTumorQueen";NA;182;0
"Unit";"Hydralisk";"Larva";154;2
"Unit";"Hydralisk";"Larva";154;2
"Unit";"Hydralisk";"Larva";154;2
"Building";"CreepTumorQueen";NA;182;0
"Unit";"Hydralisk";"Larva";154;2
"Building";"CreepTumorQueen";NA;182;0
"Unit";"Overlord";"Larva";182;0
"Unit";"Overlord";"Larva";182;0
"Unit";"Overlord";"Larva";182;0
"Building";"InfestationPit";NA;154;0
"Building";"CreepTumor";NA;190;0
"Building";"CreepTumor";NA;190;0
"Building";"CreepTumor";NA;190;0
"Building";"CreepTumor";NA;190;0
"Building";"CreepTumor";NA;190;0
"Building";"CreepTumor";NA;190;0
"Unit";"Queen";"Hatchery";182;2
"Building";"CreepTumor";NA;199;0
"Building";"CreepTumor";NA;199;0
"Building";"CreepTumorQueen";NA;201;0
"Unit";"Baneling";"Zergling";201;0
"Unit";"Baneling";"Zergling";201;0
"Unit";"Baneling";"Zergling";201;0
"Unit";"Baneling";"Zergling";201;0
"Unit";"Baneling";"Zergling";201;0
"Building";"CreepTumorQueen";NA;201;0
"Unit";"Baneling";"Zergling";201;0
"Unit";"Baneling";"Zergling";201;0
"Upgrade";"EvolveGroovedSpines";"HydraliskDen";182;0
"Unit";"Hydralisk";"Larva";201;2
"Unit";"Hydralisk";"Larva";201;2
"Unit";"Hydralisk";"Larva";201;2
"Unit";"Hydralisk";"Larva";201;2
"Unit";"Hydralisk";"Larva";201;2
"Unit";"Hydralisk";"Larva";201;2
"Unit";"Hydralisk";"Larva";201;2
"Unit";"Hydralisk";"Larva";201;2
"Unit";"Zergling";"Larva";201;1
"Unit";"Zergling";"Larva";201;1
"Unit";"Zergling";"Larva";201;1
"Unit";"Zergling";"Larva";201;1
"Unit";"Zergling";"Larva";201;1
"Unit";"Zergling";"Larva";201;1
"Unit";"Zergling";"Larva";201;1
"Unit";"Zergling";"Larva";201;1
"Building";"Extractor";NA;201;0
"Building";"Extractor";NA;201;0
"Building";"CreepTumorQueen";NA;226;0
"Building";"CreepTumor";NA;225;0
"Unit";"Zergling";"Larva";225;1
"Unit";"Zergling";"Larva";225;1
"Building";"CreepTumor";NA;228;0
"Building";"CreepTumor";NA;228;0
"Unit";"Zergling";"Larva";225;1
"Unit";"Zergling";"Larva";225;1
"Building";"CreepTumor";NA;232;0
"Building";"CreepTumor";NA;233;0
"Unit";"Hydralisk";"Larva";217;2
"Unit";"Hydralisk";"Larva";217;2
"Unit";"Hydralisk";"Larva";217;2
"Unit";"Hydralisk";"Larva";219;2
"Building";"CreepTumor";NA;233;0
"Building";"CreepTumor";NA;233;0
"Building";"CreepTumor";NA;233;0
"Building";"CreepTumor";NA;233;0
"Building";"CreepTumor";NA;233;0
"Building";"CreepTumor";NA;233;0
"Building";"CreepTumor";NA;233;0
"Unit";"Overlord";"Larva";233;0
"Unit";"Overlord";"Larva";233;0
"Unit";"Overlord";"Larva";233;0
"Unit";"Overlord";"Larva";233;0
"Unit";"Zergling";"Larva";233;1
"Unit";"Zergling";"Larva";233;1
"Unit";"Zergling";"Larva";235;1
"Unit";"Zergling";"Larva";235;1
"Unit";"Zergling";"Larva";235;1
"Unit";"Zergling";"Larva";235;1
"Unit";"Zergling";"Larva";235;1
"Unit";"Zergling";"Larva";235;1
"Unit";"Zergling";"Larva";235;1
"Unit";"Zergling";"Larva";235;1
"Unit";"Zergling";"Larva";235;1
"Unit";"Zergling";"Larva";235;1
"Unit";"Zergling";"Larva";235;1
"Unit";"Zergling";"Larva";235;1
"Unit";"Zergling";"Larva";235;1
"Unit";"Zergling";"Larva";235;1
"Unit";"Zergling";"Larva";235;1
"Unit";"Zergling";"Larva";235;1
"Unit";"Baneling";"Zergling";263;0
"Unit";"Zergling";"Larva";245;1
"Unit";"Zergling";"Larva";245;1
"Unit";"Baneling";"Zergling";263;0
"Unit";"Baneling";"Zergling";263;0
"Unit";"Baneling";"Zergling";263;0
"Unit";"Zergling";"Larva";245;1
"Unit";"Zergling";"Larva";245;1
"Unit";"Baneling";"Zergling";263;0
"Unit";"Baneling";"Zergling";263;0
"Unit";"Baneling";"Zergling";263;0
"Unit";"Baneling";"Zergling";263;0
"Unit";"Zergling";"Larva";245;1
"Unit";"Zergling";"Larva";245;1
"Unit";"Zergling";"Larva";245;1
"Unit";"Zergling";"Larva";245;1
"Unit";"Zergling";"Larva";245;1
"Unit";"Zergling";"Larva";245;1
"Unit";"Zergling";"Larva";245;1
"Unit";"Zergling";"Larva";245;1
"Unit";"Baneling";"Zergling";263;0
"Unit";"Baneling";"Zergling";263;0
"Unit";"Baneling";"Zergling";263;0
"Unit";"Baneling";"Zergling";263;0
"Unit";"Zergling";"Larva";245;1
"Unit";"Zergling";"Larva";245;1
"Unit";"Zergling";"Larva";245;1
"Unit";"Zergling";"Larva";245;1
"Unit";"Zergling";"Larva";245;1
"Unit";"Zergling";"Larva";245;1
"Unit";"Zergling";"Larva";245;1
"Unit";"Zergling";"Larva";245;1
"Unit";"Baneling";"Zergling";263;0
"Upgrade";"ZergMeleeWeaponsLevel2";"EvolutionChamber";199;0
"Upgrade";"ZergGroundArmorsLevel2";"EvolutionChamber";199;0
"Upgrade";"EvolveMuscularAugments";"HydraliskDen";233;0
"Building";"CreepTumorQueen";NA;283;0
"Unit";"Viper";"Larva";263;3
"Unit";"Viper";"Larva";263;3
"Building";"CreepTumor";NA;283;0
"Unit";"Viper";"Larva";263;3
"Unit";"Zergling";"Larva";283;1
"Unit";"Zergling";"Larva";283;1
"Building";"CreepTumorQueen";NA;283;0
"Unit";"Zergling";"Larva";283;1
"Unit";"Zergling";"Larva";283;1
"Unit";"Zergling";"Larva";283;1
"Unit";"Zergling";"Larva";283;1
"Unit";"Zergling";"Larva";283;1
"Unit";"Zergling";"Larva";283;1
"Unit";"Zergling";"Larva";283;1
"Unit";"Zergling";"Larva";283;1
"Unit";"Zergling";"Larva";283;1
"Unit";"Zergling";"Larva";283;1
"Building";"CreepTumor";NA;283;0
"Unit";"Zergling";"Larva";283;1
"Unit";"Zergling";"Larva";283;1
"Unit";"Zergling";"Larva";283;1
"Unit";"Zergling";"Larva";283;1
"Unit";"Zergling";"Larva";283;1
"Unit";"Zergling";"Larva";283;1
"Building";"CreepTumor";NA;310;0
"Building";"CreepTumor";NA;310;0
"Unit";"Zergling";"Larva";310;1
"Unit";"Zergling";"Larva";310;1
"Unit";"Zergling";"Larva";310;1
"Unit";"Zergling";"Larva";310;1
"Unit";"Zergling";"Larva";310;1
"Unit";"Zergling";"Larva";310;1
"Unit";"Zergling";"Larva";310;1
"Unit";"Zergling";"Larva";310;1
"Unit";"Zergling";"Larva";310;1
"Unit";"Zergling";"Larva";310;1
"Unit";"Zergling";"Larva";310;1
"Unit";"Zergling";"Larva";310;1
"Unit";"Zergling";"Larva";310;1
"Unit";"Zergling";"Larva";310;1
"Unit";"Zergling";"Larva";310;1
"Unit";"Zergling";"Larva";310;1
"Unit";"Zergling";"Larva";310;1
"Unit";"Zergling";"Larva";310;1
"Unit";"Zergling";"Larva";310;1
"Unit";"Zergling";"Larva";310;1
"Unit";"Zergling";"Larva";310;1
"Unit";"Zergling";"Larva";310;1
"Unit";"Zergling";"Larva";310;1
"Unit";"Zergling";"Larva";310;1
"Unit";"Zergling";"Larva";310;1
"Unit";"Zergling";"Larva";310;1
"Unit";"Zergling";"Larva";310;1
"Unit";"Zergling";"Larva";310;1
"Unit";"Zergling";"Larva";310;1
"Unit";"Zergling";"Larva";310;1
"Unit";"Zergling";"Larva";310;1
"Unit";"Zergling";"Larva";310;1
"Unit";"Zergling";"Larva";310;1
"Unit";"Zergling";"Larva";310;1
"Building";"UltraliskCavern";NA;283;0
"Unit";"Baneling";"Zergling";310;0
"Unit";"Baneling";"Zergling";310;0
"Unit";"Baneling";"Zergling";310;0
"Unit";"Baneling";"Zergling";310;0
"Unit";"Baneling";"Zergling";310;0
"Unit";"Baneling";"Zergling";310;0
"Unit";"Baneling";"Zergling";310;0
"Unit";"Baneling";"Zergling";310;0
"Building";"CreepTumor";NA;344;0
"Building";"CreepTumor";NA;344;0
"Building";"CreepTumor";NA;344;0
"Building";"CreepTumor";NA;344;0
"Unit";"Zergling";"Larva";310;1
"Unit";"Zergling";"Larva";310;1
"Building";"CreepTumor";NA;344;0
"Building";"CreepTumor";NA;344;0
"Unit";"Zergling";"Larva";310;1
"Unit";"Zergling";"Larva";310;1
"Unit";"Zergling";"Larva";310;1
"Unit";"Zergling";"Larva";310;1
"Unit";"Zergling";"Larva";310;1
"Unit";"Zergling";"Larva";310;1
"Unit";"Zergling";"Larva";310;1
"Unit";"Zergling";"Larva";310;1
"Unit";"Zergling";"Larva";310;1
"Unit";"Zergling";"Larva";310;1
"Unit";"Zergling";"Larva";310;1
"Unit";"Zergling";"Larva";310;1
"Unit";"Zergling";"Larva";310;1
"Unit";"Zergling";"Larva";310;1
"Unit";"Zergling";"Larva";310;1
"Unit";"Zergling";"Larva";310;1
"Unit";"Zergling";"Larva";310;1
"Unit";"Zergling";"Larva";310;1
"Unit";"Zergling";"Larva";310;1
"Unit";"Zergling";"Larva";310;1
"Unit";"Zergling";"Larva";310;1
"Unit";"Zergling";"Larva";310;1
"Building";"CreepTumor";NA;344;0
"Building";"CreepTumor";NA;344;0
"Building";"CreepTumor";NA;344;0
"Building";"CreepTumor";NA;344;0
"Building";"CreepTumor";NA;344;0
"Unit";"Zergling";"Larva";344;1
"Unit";"Zergling";"Larva";344;1
"Unit";"Zergling";"Larva";344;1
"Unit";"Zergling";"Larva";344;1
"Unit";"Zergling";"Larva";344;1
"Unit";"Zergling";"Larva";344;1
"Unit";"Zergling";"Larva";344;1
"Unit";"Zergling";"Larva";344;1
"Unit";"Zergling";"Larva";344;1
"Unit";"Zergling";"Larva";344;1
"Unit";"Zergling";"Larva";344;1
"Unit";"Zergling";"Larva";344;1
"Unit";"Zergling";"Larva";344;1
"Unit";"Zergling";"Larva";344;1
"Unit";"Zergling";"Larva";344;1
"Unit";"Zergling";"Larva";344;1
"Building";"CreepTumor";NA;368;0
"Building";"CreepTumor";NA;368;0
"Building";"CreepTumor";NA;368;0
"Building";"CreepTumor";NA;368;0
"Unit";"Zergling";"Larva";384;1
"Unit";"Zergling";"Larva";384;1
"Unit";"Zergling";"Larva";384;1
"Unit";"Zergling";"Larva";384;1
"Unit";"Zergling";"Larva";384;1
"Unit";"Zergling";"Larva";384;1
"Unit";"Zergling";"Larva";384;1
"Unit";"Zergling";"Larva";384;1
"Unit";"Zergling";"Larva";384;1
"Unit";"Zergling";"Larva";384;1
"Unit";"Zergling";"Larva";384;1
"Unit";"Zergling";"Larva";384;1
"Unit";"Zergling";"Larva";384;1
"Unit";"Zergling";"Larva";384;1
"Unit";"Zergling";"Larva";384;1
"Unit";"Zergling";"Larva";384;1
"Unit";"Ultralisk";"Larva";344;6
"Building";"CreepTumor";NA;406;0
"Building";"CreepTumor";NA;406;0
"Building";"CreepTumorQueen";NA;406;0
"Building";"CreepTumorQueen";NA;406;0
"Unit";"Ultralisk";"Larva";384;6
"Unit";"Ultralisk";"Larva";384;6
"Upgrade";"ChitinousPlating";"UltraliskCavern";384;0
"Unit";"Zergling";"Larva";406;1
"Unit";"Zergling";"Larva";406;1
"Unit";"Zergling";"Larva";406;1
"Unit";"Zergling";"Larva";406;1
"Unit";"Zergling";"Larva";406;1
"Unit";"Zergling";"Larva";406;1
"Unit";"Zergling";"Larva";406;1
"Unit";"Zergling";"Larva";406;1
"Unit";"Zergling";"Larva";406;1
"Unit";"Zergling";"Larva";406;1
"Unit";"Zergling";"Larva";406;1
"Unit";"Zergling";"Larva";406;1
"Unit";"Zergling";"Larva";406;1
"Unit";"Zergling";"Larva";406;1
"Unit";"Zergling";"Larva";406;1
"Unit";"Zergling";"Larva";406;1
"Unit";"Zergling";"Larva";406;1
"Unit";"Zergling";"Larva";406;1
"Unit";"Zergling";"Larva";406;1
"Unit";"Zergling";"Larva";406;1
"Unit";"Zergling";"Larva";406;1
"Unit";"Zergling";"Larva";406;1
"Unit";"Zergling";"Larva";406;1
"Unit";"Zergling";"Larva";406;1
"Unit";"Zergling";"Larva";406;1
"Unit";"Zergling";"Larva";406;1
"Unit";"Zergling";"Larva";406;1
"Unit";"Zergling";"Larva";406;1
"Unit";"Zergling";"Larva";406;1
"Unit";"Zergling";"Larva";406;1
"Unit";"Zergling";"Larva";406;1
"Unit";"Zergling";"Larva";406;1
"Unit";"Zergling";"Larva";406;1
"Unit";"Zergling";"Larva";406;1
"Unit";"Zergling";"Larva";406;1
"Unit";"Zergling";"Larva";406;1
"Unit";"Zergling";"Larva";406;1
"Unit";"Zergling";"Larva";406;1
"Unit";"Zergling";"Larva";406;1
"Unit";"Zergling";"Larva";406;1
"Unit";"Zergling";"Larva";406;1
"Unit";"Zergling";"Larva";406;1
"Unit";"Zergling";"Larva";406;1
"Unit";"Zergling";"Larva";406;1
"Unit";"Zergling";"Larva";406;1
"Unit";"Zergling";"Larva";406;1
"Unit";"Zergling";"Larva";406;1
"Unit";"Zergling";"Larva";406;1
"Unit";"Zergling";"Larva";406;1
"Unit";"Zergling";"Larva";406;1
"Unit";"Zergling";"Larva";406;1
"Unit";"Zergling";"Larva";406;1
"Unit";"Baneling";"Zergling";460;0
"Unit";"Baneling";"Zergling";460;0
"Unit";"Baneling";"Zergling";460;0
"Unit";"Baneling";"Zergling";460;0
"Unit";"Baneling";"Zergling";464;0
"Unit";"Baneling";"Zergling";468;0
"Unit";"Baneling";"Zergling";468;0
"Unit";"Baneling";"Zergling";468;0
"Unit";"Baneling";"Zergling";470;0
"Unit";"Baneling";"Zergling";470;0
"Unit";"Baneling";"Zergling";470;0
"Unit";"Baneling";"Zergling";470;0
"Unit";"Baneling";"Zergling";470;0
"Unit";"Baneling";"Zergling";470;0
"Unit";"Baneling";"Zergling";470;0
"Unit";"Baneling";"Zergling";470;0
"Unit";"Baneling";"Zergling";470;0
"Unit";"Baneling";"Zergling";470;0
"Unit";"Baneling";"Zergling";470;0
"Unit";"Baneling";"Zergling";470;0
"Upgrade";"ZergMeleeWeaponsLevel3";"EvolutionChamber";368;0
"Upgrade";"ZergGroundArmorsLevel3";"EvolutionChamber";368;0
"Unit";"Ultralisk";"Larva";470;6
"Unit";"Ultralisk";"Larva";470;6
"Unit";"Hydralisk";"Larva";470;2
"Unit";"Hydralisk";"Larva";470;2
"Unit";"Hydralisk";"Larva";470;2
"Unit";"Hydralisk";"Larva";470;2
"Unit";"Hydralisk";"Larva";470;2
"Unit";"Hydralisk";"Larva";470;2
"Unit";"Ultralisk";"Larva";470;6
"Unit";"Ultralisk";"Larva";470;6
"Unit";"Hydralisk";"Larva";482;2
"Unit";"Hydralisk";"Larva";482;2
"Unit";"Hydralisk";"Larva";482;2
"Unit";"Hydralisk";"Larva";482;2
"Unit";"Hydralisk";"Larva";482;2
"Unit";"Hydralisk";"Larva";482;2
"Building";"Hatchery";NA;470;0
"Building";"CreepTumorQueen";NA;518;0
"Building";"CreepTumorQueen";NA;518;0
"Building";"CreepTumorQueen";NA;518;0
"Building";"CreepTumorQueen";NA;518;0
"Unit";"Hydralisk";"Larva";518;2
"Unit";"Hydralisk";"Larva";518;2
"Unit";"Hydralisk";"Larva";518;2
"Unit";"Zergling";"Larva";518;1
"Unit";"Zergling";"Larva";518;1
"Unit";"Zergling";"Larva";518;1
"Unit";"Zergling";"Larva";518;1
"Unit";"Hydralisk";"Larva";518;2
"Unit";"Hydralisk";"Larva";518;2
"Unit";"Hydralisk";"Larva";518;2
"Building";"Extractor";NA;524;0
"Building";"Extractor";NA;524;0
"Unit";"Queen";"Hatchery";524;2
"Building";"Hatchery";NA;518;0
"Unit";"Zergling";"Larva";539;1
"Unit";"Zergling";"Larva";539;1
"Unit";"Zergling";"Larva";539;1
"Unit";"Zergling";"Larva";539;1
"Unit";"Zergling";"Larva";539;1
"Unit";"Zergling";"Larva";539;1
"Unit";"Zergling";"Larva";539;1
"Unit";"Zergling";"Larva";539;1
"Unit";"Zergling";"Larva";541;1
"Unit";"Zergling";"Larva";541;1
"Unit";"Zergling";"Larva";541;1
"Unit";"Zergling";"Larva";541;1
"Unit";"Zergling";"Larva";541;1
"Unit";"Zergling";"Larva";541;1
"Unit";"Zergling";"Larva";541;1
"Unit";"Zergling";"Larva";541;1
"Unit";"Zergling";"Larva";541;1
"Unit";"Zergling";"Larva";541;1
"Unit";"Zergling";"Larva";541;1
"Unit";"Zergling";"Larva";541;1
"Unit";"Zergling";"Larva";541;1
"Unit";"Zergling";"Larva";541;1
"Unit";"Zergling";"Larva";541;1
"Unit";"Zergling";"Larva";541;1
"Unit";"Zergling";"Larva";549;1
"Unit";"Zergling";"Larva";549;1
"Unit";"Zergling";"Larva";549;1
"Unit";"Zergling";"Larva";549;1
"Upgrade";"ZergMissileWeaponsLevel1";"EvolutionChamber";524;0
"Unit";"Zergling";"Larva";549;1
"Unit";"Zergling";"Larva";549;1
"Unit";"Zergling";"Larva";549;1
"Unit";"Zergling";"Larva";549;1
"Unit";"Zergling";"Larva";549;1
"Unit";"Zergling";"Larva";549;1
"Unit";"Zergling";"Larva";549;1
"Unit";"Zergling";"Larva";549;1
"Unit";"Zergling";"Larva";549;1
"Unit";"Zergling";"Larva";549;1
"Unit";"Zergling";"Larva";549;1
"Unit";"Zergling";"Larva";549;1
"Unit";"Zergling";"Larva";549;1
"Unit";"Zergling";"Larva";549;1
"Unit";"Zergling";"Larva";549;1
"Unit";"Zergling";"Larva";549;1
"Unit";"Zergling";"Larva";549;1
"Unit";"Zergling";"Larva";549;1
"Unit";"Zergling";"Larva";549;1
"Unit";"Zergling";"Larva";549;1
"Unit";"Zergling";"Larva";549;1
"Unit";"Zergling";"Larva";549;1
"Unit";"Zergling";"Larva";549;1
"Unit";"Zergling";"Larva";549;1
"Unit";"Zergling";"Larva";549;1
"Unit";"Zergling";"Larva";549;1
"Unit";"Zergling";"Larva";549;1
"Unit";"Zergling";"Larva";549;1
"Unit";"Zergling";"Larva";549;1
"Unit";"Zergling";"Larva";549;1
"Unit";"Zergling";"Larva";549;1
"Unit";"Zergling";"Larva";549;1
"Unit";"Zergling";"Larva";549;1
"Unit";"Zergling";"Larva";549;1
"Unit";"Zergling";"Larva";549;1
"Unit";"Zergling";"Larva";549;1
"Unit";"Zergling";"Larva";549;1
"Unit";"Zergling";"Larva";549;1
"Unit";"Zergling";"Larva";549;1
"Unit";"Zergling";"Larva";549;1
"Unit";"Zergling";"Larva";549;1
"Unit";"Zergling";"Larva";549;1
"Unit";"Zergling";"Larva";549;1
"Unit";"Zergling";"Larva";549;1
"Unit";"Zergling";"Larva";549;1
"Unit";"Zergling";"Larva";549;1
"Unit";"Zergling";"Larva";549;1
"Unit";"Zergling";"Larva";549;1
"Building";"Spire";NA;535;0
"Building";"CreepTumor";NA;569;0
"Building";"CreepTumor";NA;569;0
"Building";"CreepTumor";NA;569;0
"Building";"CreepTumor";NA;569;0
"Unit";"Overlord";"Larva";569;0
"Unit";"Overlord";"Larva";569;0
"Unit";"Overlord";"Larva";569;0
"Unit";"Overlord";"Larva";569;0
"Unit";"Baneling";"Zergling";617;0
"Unit";"Baneling";"Zergling";617;0
"Unit";"Baneling";"Zergling";617;0
"Unit";"Baneling";"Zergling";617;0
"Unit";"Baneling";"Zergling";617;0
"Unit";"Baneling";"Zergling";617;0
"Unit";"Baneling";"Zergling";617;0
"Unit";"Baneling";"Zergling";617;0
"Unit";"Baneling";"Zergling";617;0
"Unit";"Baneling";"Zergling";617;0
"Unit";"Baneling";"Zergling";617;0
"Unit";"Baneling";"Zergling";617;0
"Unit";"Baneling";"Zergling";617;0
"Unit";"Baneling";"Zergling";617;0
"Unit";"Baneling";"Zergling";617;0
"Unit";"Baneling";"Zergling";617;0
"Unit";"Baneling";"Zergling";617;0
"Unit";"Baneling";"Zergling";617;0
"Unit";"Baneling";"Zergling";617;0
"Unit";"Baneling";"Zergling";617;0
"Unit";"Baneling";"Zergling";617;0
"Unit";"Baneling";"Zergling";617;0
"Unit";"Baneling";"Zergling";617;0
"Unit";"Baneling";"Zergling";617;0
"Unit";"Baneling";"Zergling";617;0
"Unit";"Baneling";"Zergling";617;0
"Unit";"Baneling";"Zergling";617;0
"Unit";"Baneling";"Zergling";617;0
"Unit";"Baneling";"Zergling";617;0
"Unit";"Baneling";"Zergling";617;0
"Unit";"Baneling";"Zergling";617;0
"Unit";"Baneling";"Zergling";617;0
"Unit";"Baneling";"Zergling";617;0
"Unit";"Baneling";"Zergling";617;0
"Unit";"Baneling";"Zergling";617;0
"Unit";"Baneling";"Zergling";617;0
"Unit";"Baneling";"Zergling";617;0
"Building";"CreepTumor";NA;617;0
"Building";"CreepTumor";NA;617;0
"Building";"CreepTumor";NA;617;0
"Building";"CreepTumor";NA;617;0
"Building";"SpineCrawler";NA;617;0
"Building";"SpineCrawler";NA;617;0
"Building";"SpineCrawler";NA;617;0
"Unit";"Hydralisk";"Larva";617;2
"Unit";"Hydralisk";"Larva";617;2
"Unit";"Ultralisk";"Larva";617;6
"Unit";"Ultralisk";"Larva";617;6
"Unit";"Ultralisk";"Larva";617;6
"Unit";"Zergling";"Larva";639;1
"Unit";"Zergling";"Larva";639;1
"Unit";"Zergling";"Larva";639;1
"Unit";"Zergling";"Larva";639;1
"Unit";"Zergling";"Larva";639;1
"Unit";"Zergling";"Larva";639;1
"Unit";"Zergling";"Larva";639;1
"Unit";"Zergling";"Larva";639;1
"Unit";"Zergling";"Larva";639;1
"Unit";"Zergling";"Larva";639;1
"Unit";"Zergling";"Larva";639;1
"Unit";"Zergling";"Larva";639;1
"Unit";"Zergling";"Larva";639;1
"Unit";"Zergling";"Larva";639;1
"Unit";"Zergling";"Larva";639;1
"Unit";"Zergling";"Larva";639;1
"Unit";"Zergling";"Larva";639;1
"Unit";"Zergling";"Larva";639;1
"Unit";"Zergling";"Larva";639;1
"Unit";"Zergling";"Larva";639;1
"Unit";"Zergling";"Larva";639;1
"Unit";"Zergling";"Larva";639;1
"Unit";"Zergling";"Larva";639;1
"Unit";"Zergling";"Larva";639;1
"Unit";"Zergling";"Larva";639;1
"Unit";"Zergling";"Larva";639;1
"Unit";"Zergling";"Larva";639;1
"Unit";"Zergling";"Larva";639;1
"Unit";"Zergling";"Larva";639;1
"Unit";"Zergling";"Larva";639;1
"Unit";"Zergling";"Larva";639;1
"Unit";"Zergling";"Larva";639;1
"Unit";"Zergling";"Larva";639;1
"Unit";"Zergling";"Larva";639;1
"Unit";"Zergling";"Larva";639;1
"Unit";"Zergling";"Larva";639;1
"Unit";"Zergling";"Larva";639;1
"Unit";"Zergling";"Larva";639;1
