"type";"unit_name";"on_building";"total_supply_lag";"supply"
"Unit";"Overlord";"Larva";13;0
"Building";"Extractor";NA;17;0
"Building";"SpawningPool";NA;18;0
"Building";"Hatchery";NA;20;0
"Unit";"Zergling";"Larva";22;1
"Unit";"Zergling";"Larva";23;1
"Building";"RoachWarren";NA;24;0
"Unit";"Queen";"Hatchery";24;2
"Unit";"Overlord";"Larva";27;0
"Unit";"Zergling";"Larva";27;1
"Unit";"Zergling";"Larva";28;1
"Unit";"Overlord";"Larva";29;0
"Unit";"Queen";"Hatchery";29;2
"Unit";"Roach";"Larva";31;2
"Unit";"Roach";"Larva";33;2
"Unit";"Roach";"Larva";35;2
"Unit";"Roach";"Larva";37;2
"Unit";"Roach";"Larva";39;2
"Unit";"Roach";"Larva";41;2
"Building";"CreepTumorQueen";NA;45;0
"Unit";"Overlord";"Larva";46;0
"Unit";"Overlord";"Larva";49;0
"Building";"CreepTumor";NA;49;0
"Unit";"Queen";"Hatchery";58;2
"Unit";"Overlord";"Larva";63;0
"Unit";"Overlord";"Larva";64;0
"Building";"CreepTumor";NA;67;0
"Building";"Extractor";NA;67;0
"Building";"Extractor";NA;67;0
"Unit";"Roach";"Larva";67;2
"Unit";"Queen";"Hatchery";69;2
"Building";"SporeCrawler";NA;71;0
"Building";"SporeCrawler";NA;71;0
"Building";"SporeCrawler";NA;71;0
"Building";"CreepTumor";NA;78;0
"Building";"CreepTumorQueen";NA;79;0
"Unit";"Overlord";"Larva";79;0
"Unit";"Roach";"Larva";79;2
"Unit";"Roach";"Larva";81;2
"Building";"EvolutionChamber";NA;83;0
"Unit";"Roach";"Larva";83;2
"Unit";"Roach";"Larva";85;2
"Unit";"Roach";"Larva";87;2
"Building";"CreepTumor";NA;89;0
"Unit";"Queen";"Hatchery";89;2
"Unit";"Overlord";"Larva";91;0
"Building";"CreepTumor";NA;91;0
"Building";"CreepTumorQueen";NA;91;0
"Unit";"Roach";"Larva";91;2
"Unit";"Roach";"Larva";93;2
"Unit";"Overlord";"Larva";95;0
"Unit";"Overlord";"Larva";95;0
"Unit";"Roach";"Larva";95;2
"Unit";"Roach";"Larva";97;2
"Unit";"Roach";"Larva";99;2
"Unit";"Roach";"Larva";101;2
"Unit";"Roach";"Larva";103;2
"Unit";"Roach";"Larva";105;2
"Building";"Hatchery";NA;107;0
"Unit";"Zergling";"Larva";107;1
"Unit";"Zergling";"Larva";108;1
"Unit";"Zergling";"Larva";109;1
"Unit";"Zergling";"Larva";110;1
"Unit";"Zergling";"Larva";111;1
"Unit";"Zergling";"Larva";112;1
"Unit";"Zergling";"Larva";113;1
"Unit";"Zergling";"Larva";114;1
"Unit";"Zergling";"Larva";115;1
"Unit";"Zergling";"Larva";116;1
"Unit";"Overlord";"Larva";117;0
"Building";"CreepTumor";NA;117;0
"Unit";"Zergling";"Larva";117;1
"Unit";"Zergling";"Larva";118;1
"Unit";"Zergling";"Larva";119;1
"Unit";"Zergling";"Larva";120;1
"Unit";"Zergling";"Larva";121;1
"Unit";"Zergling";"Larva";122;1
"Unit";"Zergling";"Larva";123;1
"Unit";"Zergling";"Larva";124;1
"Unit";"Zergling";"Larva";125;1
"Unit";"Zergling";"Larva";126;1
"Unit";"Queen";"Hatchery";127;2
"Unit";"Roach";"Larva";129;2
"Unit";"Roach";"Larva";131;2
"Unit";"Zergling";"Larva";133;1
"Unit";"Zergling";"Larva";134;1
"Unit";"Zergling";"Larva";135;1
"Unit";"Zergling";"Larva";136;1
"Unit";"Zergling";"Larva";137;1
"Unit";"Zergling";"Larva";138;1
"Unit";"Roach";"Larva";139;2
"Unit";"Roach";"Larva";141;2
"Unit";"Roach";"Larva";143;2
"Unit";"Roach";"Larva";145;2
"Unit";"Roach";"Larva";147;2
"Unit";"Overlord";"Larva";149;0
"Unit";"Roach";"Larva";149;2
"Unit";"Roach";"Larva";151;2
"Unit";"Roach";"Larva";153;2
"Unit";"Roach";"Larva";155;2
"Unit";"Roach";"Larva";157;2
"Unit";"Roach";"Larva";159;2
"Unit";"Roach";"Larva";161;2
"Unit";"Roach";"Larva";163;2
"Unit";"Roach";"Larva";165;2
"Unit";"Roach";"Larva";167;2
"Unit";"Roach";"Larva";169;2
"Unit";"Queen";"Hatchery";171;2
"Unit";"Zergling";"Larva";173;1
"Unit";"Zergling";"Larva";174;1
"Unit";"Zergling";"Larva";175;1
"Unit";"Zergling";"Larva";176;1
"Unit";"Queen";"Hatchery";177;2
"Unit";"Queen";"Hatchery";179;2
"Unit";"Zergling";"Larva";181;1
"Unit";"Zergling";"Larva";182;1
"Unit";"Zergling";"Larva";183;1
"Unit";"Zergling";"Larva";184;1
"Unit";"Zergling";"Larva";185;1
"Unit";"Zergling";"Larva";186;1
"Unit";"Overlord";"Larva";187;0
"Unit";"Zergling";"Larva";187;1
"Unit";"Zergling";"Larva";188;1
"Unit";"Zergling";"Larva";189;1
"Unit";"Zergling";"Larva";190;1
"Unit";"Overlord";"Larva";191;0
"Unit";"Overlord";"Larva";191;0
"Unit";"Overlord";"Larva";191;0
"Unit";"Overlord";"Larva";191;0
"Unit";"Zergling";"Larva";191;1
"Unit";"Zergling";"Larva";192;1
"Unit";"Zergling";"Larva";193;1
"Unit";"Zergling";"Larva";194;1
"Upgrade";"GlialReconstitution";"RoachWarren";195;0
"Unit";"Overlord";"Larva";195;0
"Unit";"Zergling";"Larva";195;1
"Unit";"Zergling";"Larva";196;1
"Unit";"Zergling";"Larva";197;1
"Unit";"Zergling";"Larva";198;1
"Unit";"Zergling";"Larva";199;1
"Unit";"Zergling";"Larva";200;1
"Unit";"Zergling";"Larva";201;1
"Unit";"Zergling";"Larva";202;1
"Unit";"Zergling";"Larva";203;1
"Unit";"Zergling";"Larva";204;1
"Unit";"Zergling";"Larva";205;1
"Unit";"Zergling";"Larva";206;1
"Unit";"Zergling";"Larva";207;1
"Unit";"Zergling";"Larva";208;1
"Unit";"Zergling";"Larva";209;1
"Unit";"Zergling";"Larva";210;1
"Unit";"Zergling";"Larva";211;1
"Unit";"Zergling";"Larva";212;1
"Unit";"Zergling";"Larva";213;1
"Unit";"Zergling";"Larva";214;1
"Unit";"Zergling";"Larva";215;1
"Unit";"Zergling";"Larva";216;1
"Unit";"Zergling";"Larva";217;1
"Unit";"Zergling";"Larva";218;1
"Unit";"Zergling";"Larva";219;1
"Unit";"Zergling";"Larva";220;1
"Unit";"Zergling";"Larva";221;1
"Unit";"Zergling";"Larva";222;1
"Unit";"Zergling";"Larva";223;1
"Unit";"Zergling";"Larva";224;1
"Unit";"Zergling";"Larva";225;1
"Unit";"Zergling";"Larva";226;1
"Unit";"Zergling";"Larva";227;1
"Unit";"Zergling";"Larva";228;1
"Upgrade";"SprayZerg";NA;229;0
"Upgrade";"SprayZerg";NA;229;0
"Upgrade";"SprayZerg";NA;229;0
"Upgrade";"overlordspeed";NA;229;0
"Upgrade";"SprayZerg";NA;229;0
"Upgrade";"SprayZerg";NA;229;0
"Upgrade";"SprayZerg";NA;229;0
"Upgrade";"zerglingmovementspeed";NA;229;0
