"type";"unit_name";"on_building";"total_supply";"supply"
"Unit";"Overlord";"Larva";13;0
"Building";"Extractor";NA;18;0
"Unit";"Overlord";"Larva";21;0
"Building";"SpawningPool";NA;19;0
"Building";"Hatchery";NA;17;0
"Unit";"Zergling";"Larva";23;1
"Unit";"Zergling";"Larva";23;1
"Unit";"Zergling";"Larva";23;1
"Unit";"Zergling";"Larva";23;1
"Unit";"Queen";"Hatchery";23;2
"Unit";"Queen";"Hatchery";23;2
"Unit";"Zergling";"Larva";32;1
"Unit";"Zergling";"Larva";32;1
"Unit";"Overlord";"Larva";35;0
"Unit";"Queen";"Hatchery";35;2
"Building";"CreepTumorQueen";NA;40;0
"Unit";"Overlord";"Larva";46;0
"Unit";"Queen";"Hatchery";42;2
"Unit";"Overlord";"Larva";49;0
"Building";"CreepTumor";NA;50;0
"Building";"CreepTumorQueen";NA;50;0
"Building";"CreepTumorQueen";NA;53;0
"Building";"Hatchery";NA;39;0
"Unit";"Overlord";"Larva";59;0
"Unit";"Queen";"Hatchery";51;2
"Unit";"Overlord";"Larva";59;0
"Unit";"Overlord";"Larva";59;0
"Building";"CreepTumor";NA;59;0
"Building";"CreepTumor";NA;59;0
"Building";"CreepTumorQueen";NA;61;0
"Unit";"Overlord";"Larva";59;0
"Unit";"Overlord";"Larva";59;0
"Building";"CreepTumor";NA;63;0
"Unit";"Zergling";"Larva";61;1
"Unit";"Zergling";"Larva";61;1
"Unit";"Zergling";"Larva";61;1
"Unit";"Zergling";"Larva";61;1
"Unit";"Zergling";"Larva";61;1
"Unit";"Zergling";"Larva";61;1
"Unit";"Zergling";"Larva";61;1
"Unit";"Zergling";"Larva";61;1
"Unit";"Zergling";"Larva";61;1
"Unit";"Zergling";"Larva";61;1
"Unit";"Zergling";"Larva";61;1
"Unit";"Zergling";"Larva";61;1
"Unit";"Zergling";"Larva";61;1
"Unit";"Zergling";"Larva";61;1
"Unit";"Zergling";"Larva";61;1
"Unit";"Zergling";"Larva";61;1
"Building";"BanelingNest";NA;59;0
"Building";"Extractor";NA;63;0
"Building";"CreepTumorQueen";NA;79;0
"Building";"Extractor";NA;63;0
"Building";"CreepTumor";NA;82;0
"Building";"CreepTumor";NA;82;0
"Building";"CreepTumor";NA;84;0
"Unit";"Baneling";"Zergling";85;0
"Unit";"Baneling";"Zergling";85;0
"Unit";"Baneling";"Zergling";85;0
"Building";"CreepTumorQueen";NA;90;0
"Building";"CreepTumorQueen";NA;90;0
"Building";"Extractor";NA;90;0
"Unit";"Overlord";"Larva";94;0
"Unit";"Overlord";"Larva";94;0
"Building";"CreepTumor";NA;99;0
"Building";"CreepTumor";NA;99;0
"Building";"EvolutionChamber";NA;94;0
"Building";"EvolutionChamber";NA;94;0
"Unit";"Baneling";"Zergling";99;0
"Unit";"Baneling";"Zergling";99;0
"Building";"CreepTumor";NA;99;0
"Unit";"Overlord";"Larva";99;0
"Building";"Extractor";NA;99;0
"Unit";"Zergling";"Larva";107;1
"Unit";"Zergling";"Larva";107;1
"Unit";"Baneling";"Zergling";107;0
"Unit";"Zergling";"Larva";107;1
"Unit";"Zergling";"Larva";107;1
"Unit";"Zergling";"Larva";107;1
"Unit";"Zergling";"Larva";107;1
"Unit";"Zergling";"Larva";107;1
"Unit";"Zergling";"Larva";107;1
"Unit";"Zergling";"Larva";107;1
"Unit";"Zergling";"Larva";107;1
"Unit";"Baneling";"Zergling";107;0
"Unit";"Zergling";"Larva";107;1
"Unit";"Zergling";"Larva";107;1
"Unit";"Zergling";"Larva";107;1
"Unit";"Zergling";"Larva";107;1
"Unit";"Zergling";"Larva";107;1
"Unit";"Zergling";"Larva";107;1
"Unit";"Zergling";"Larva";107;1
"Unit";"Zergling";"Larva";107;1
"Unit";"Zergling";"Larva";107;1
"Unit";"Zergling";"Larva";107;1
"Building";"CreepTumorQueen";NA;127;0
"Building";"CreepTumorQueen";NA;127;0
"Unit";"Overlord";"Larva";127;0
"Unit";"Zergling";"Larva";127;1
"Unit";"Zergling";"Larva";127;1
"Unit";"Zergling";"Larva";127;1
"Unit";"Zergling";"Larva";127;1
"Unit";"Zergling";"Larva";127;1
"Unit";"Zergling";"Larva";127;1
"Unit";"Zergling";"Larva";127;1
"Unit";"Zergling";"Larva";127;1
"Unit";"Zergling";"Larva";127;1
"Unit";"Zergling";"Larva";127;1
"Unit";"Zergling";"Larva";127;1
"Unit";"Zergling";"Larva";127;1
"Unit";"Zergling";"Larva";127;1
"Unit";"Zergling";"Larva";127;1
"Unit";"Zergling";"Larva";127;1
"Unit";"Zergling";"Larva";127;1
"Unit";"Zergling";"Larva";127;1
"Unit";"Zergling";"Larva";127;1
"Building";"CreepTumorQueen";NA;127;0
"Building";"CreepTumorQueen";NA;127;0
"Unit";"Baneling";"Zergling";127;0
"Unit";"Baneling";"Zergling";127;0
"Unit";"Baneling";"Zergling";127;0
"Unit";"Baneling";"Zergling";127;0
"Unit";"Baneling";"Zergling";127;0
"Unit";"Baneling";"Zergling";127;0
"Unit";"Baneling";"Zergling";127;0
"Unit";"Baneling";"Zergling";127;0
"Unit";"Baneling";"Zergling";127;0
"Unit";"Baneling";"Zergling";127;0
"Unit";"Zergling";"Larva";127;1
"Unit";"Zergling";"Larva";127;1
"Unit";"Overlord";"Larva";145;0
"Building";"CreepTumor";NA;152;0
"Building";"Extractor";NA;145;0
"Building";"CreepTumorQueen";NA;152;0
"Building";"CreepTumorQueen";NA;152;0
"Building";"CreepTumorQueen";NA;162;0
"Building";"CreepTumorQueen";NA;162;0
"Unit";"Overlord";"Larva";152;0
"Building";"Hatchery";NA;127;0
"Building";"HydraliskDen";NA;152;0
"Building";"CreepTumor";NA;162;0
"Building";"CreepTumor";NA;162;0
"Building";"CreepTumor";NA;162;0
"Building";"CreepTumor";NA;162;0
"Building";"CreepTumor";NA;162;0
"Building";"CreepTumor";NA;162;0
"Upgrade";"ZergGroundArmorsLevel1";"EvolutionChamber";127;0
"Unit";"Overlord";"Larva";166;0
"Unit";"Overlord";"Larva";166;0
"Unit";"Overlord";"Larva";166;0
"Unit";"Zergling";"Larva";170;1
"Unit";"Zergling";"Larva";170;1
"Building";"CreepTumor";NA;172;0
"Unit";"Hydralisk";"Larva";170;2
"Unit";"Hydralisk";"Larva";170;2
"Unit";"Hydralisk";"Larva";170;2
"Unit";"Hydralisk";"Larva";170;2
"Unit";"Hydralisk";"Larva";170;2
"Unit";"Hydralisk";"Larva";170;2
"Unit";"Hydralisk";"Larva";170;2
"Unit";"Hydralisk";"Larva";170;2
"Upgrade";"ZergMeleeWeaponsLevel1";"EvolutionChamber";145;0
"Unit";"Hydralisk";"Larva";170;2
"Unit";"Hydralisk";"Larva";170;2
"Unit";"Baneling";"Zergling";172;0
"Unit";"Baneling";"Zergling";172;0
"Building";"InfestationPit";NA;170;0
"Unit";"Queen";"Hatchery";170;2
"Unit";"Zergling";"Larva";172;1
"Unit";"Zergling";"Larva";172;1
"Unit";"Zergling";"Larva";172;1
"Unit";"Zergling";"Larva";172;1
"Unit";"Zergling";"Larva";172;1
"Unit";"Zergling";"Larva";172;1
"Unit";"Zergling";"Larva";172;1
"Unit";"Zergling";"Larva";172;1
"Unit";"Zergling";"Larva";172;1
"Unit";"Zergling";"Larva";172;1
"Unit";"Zergling";"Larva";172;1
"Unit";"Zergling";"Larva";172;1
"Unit";"Overlord";"Larva";172;0
"Unit";"Zergling";"Larva";192;1
"Unit";"Zergling";"Larva";192;1
"Unit";"Zergling";"Larva";192;1
"Unit";"Zergling";"Larva";192;1
"Building";"CreepTumorQueen";NA;206;0
"Unit";"Zergling";"Larva";192;1
"Unit";"Zergling";"Larva";192;1
"Unit";"Zergling";"Larva";192;1
"Unit";"Zergling";"Larva";192;1
"Unit";"Zergling";"Larva";192;1
"Unit";"Zergling";"Larva";192;1
"Building";"Extractor";NA;172;0
"Building";"Hatchery";NA;154;0
"Building";"CreepTumorQueen";NA;206;0
"Building";"CreepTumorQueen";NA;206;0
"Unit";"Zergling";"Larva";206;1
"Unit";"Zergling";"Larva";206;1
"Unit";"Zergling";"Larva";206;1
"Unit";"Zergling";"Larva";206;1
"Unit";"Zergling";"Larva";206;1
"Unit";"Zergling";"Larva";206;1
"Building";"CreepTumor";NA;206;0
"Unit";"Hydralisk";"Larva";206;2
"Unit";"Hydralisk";"Larva";206;2
"Unit";"Hydralisk";"Larva";206;2
"Unit";"Hydralisk";"Larva";206;2
"Unit";"Hydralisk";"Larva";206;2
"Unit";"Baneling";"Zergling";216;0
"Unit";"Baneling";"Zergling";216;0
"Unit";"Baneling";"Zergling";216;0
"Unit";"Baneling";"Zergling";216;0
"Unit";"Baneling";"Zergling";216;0
"Unit";"Baneling";"Zergling";216;0
"Building";"CreepTumor";NA;216;0
"Upgrade";"EvolveGroovedSpines";"HydraliskDen";172;0
"Building";"CreepTumor";NA;218;0
"Unit";"Baneling";"Zergling";216;0
"Unit";"Zergling";"Larva";216;1
"Unit";"Zergling";"Larva";216;1
"Unit";"Baneling";"Zergling";216;0
"Unit";"Zergling";"Larva";216;1
"Unit";"Zergling";"Larva";216;1
"Unit";"Baneling";"Zergling";216;0
"Unit";"Zergling";"Larva";216;1
"Unit";"Zergling";"Larva";216;1
"Unit";"Zergling";"Larva";216;1
"Unit";"Zergling";"Larva";216;1
"Unit";"Zergling";"Larva";216;1
"Unit";"Zergling";"Larva";216;1
"Unit";"Zergling";"Larva";216;1
"Unit";"Zergling";"Larva";216;1
"Unit";"Baneling";"Zergling";222;0
"Building";"CreepTumorQueen";NA;232;0
"Building";"CreepTumorQueen";NA;232;0
"Building";"CreepTumor";NA;232;0
"Building";"CreepTumor";NA;232;0
"Building";"CreepTumor";NA;232;0
"Unit";"Overlord";"Larva";224;0
"Unit";"Overlord";"Larva";230;0
"Unit";"Zergling";"Larva";232;1
"Unit";"Zergling";"Larva";232;1
"Unit";"Zergling";"Larva";232;1
"Unit";"Zergling";"Larva";232;1
"Unit";"Zergling";"Larva";232;1
"Unit";"Zergling";"Larva";232;1
"Unit";"Zergling";"Larva";232;1
"Unit";"Zergling";"Larva";232;1
"Unit";"Zergling";"Larva";232;1
"Unit";"Zergling";"Larva";232;1
"Unit";"Zergling";"Larva";232;1
"Unit";"Zergling";"Larva";232;1
"Unit";"Zergling";"Larva";232;1
"Unit";"Zergling";"Larva";232;1
"Unit";"Zergling";"Larva";232;1
"Unit";"Zergling";"Larva";232;1
"Unit";"Hydralisk";"Larva";232;2
"Unit";"Hydralisk";"Larva";232;2
"Unit";"Hydralisk";"Larva";232;2
"Unit";"Overlord";"Larva";244;0
"Unit";"Zergling";"Larva";244;1
"Unit";"Zergling";"Larva";244;1
"Unit";"Zergling";"Larva";244;1
"Unit";"Zergling";"Larva";244;1
"Unit";"Zergling";"Larva";244;1
"Unit";"Zergling";"Larva";244;1
"Building";"CreepTumor";NA;266;0
"Unit";"Hydralisk";"Larva";244;2
"Unit";"Hydralisk";"Larva";244;2
"Unit";"Queen";"Hatchery";232;2
"Unit";"Zergling";"Larva";272;1
"Unit";"Zergling";"Larva";272;1
"Unit";"Zergling";"Larva";272;1
"Unit";"Zergling";"Larva";272;1
"Unit";"Zergling";"Larva";272;1
"Unit";"Zergling";"Larva";272;1
"Unit";"Zergling";"Larva";272;1
"Unit";"Zergling";"Larva";272;1
"Unit";"Zergling";"Larva";272;1
"Unit";"Zergling";"Larva";272;1
"Unit";"Zergling";"Larva";272;1
"Unit";"Zergling";"Larva";272;1
"Unit";"Zergling";"Larva";272;1
"Unit";"Zergling";"Larva";272;1
"Unit";"Zergling";"Larva";272;1
"Unit";"Zergling";"Larva";272;1
"Unit";"Zergling";"Larva";272;1
"Unit";"Zergling";"Larva";272;1
"Unit";"Zergling";"Larva";272;1
"Unit";"Zergling";"Larva";272;1
"Unit";"Zergling";"Larva";272;1
"Unit";"Zergling";"Larva";272;1
"Unit";"Zergling";"Larva";272;1
"Unit";"Zergling";"Larva";272;1
"Unit";"Zergling";"Larva";272;1
"Unit";"Zergling";"Larva";272;1
"Unit";"Zergling";"Larva";272;1
"Unit";"Zergling";"Larva";272;1
"Unit";"Zergling";"Larva";272;1
"Unit";"Zergling";"Larva";272;1
"Unit";"Zergling";"Larva";278;1
"Unit";"Zergling";"Larva";278;1
"Unit";"Zergling";"Larva";278;1
"Unit";"Zergling";"Larva";278;1
"Unit";"Zergling";"Larva";278;1
"Unit";"Zergling";"Larva";278;1
"Unit";"Zergling";"Larva";278;1
"Unit";"Zergling";"Larva";278;1
"Unit";"Zergling";"Larva";278;1
"Unit";"Zergling";"Larva";278;1
"Unit";"Zergling";"Larva";278;1
"Unit";"Zergling";"Larva";278;1
"Unit";"Zergling";"Larva";278;1
"Unit";"Zergling";"Larva";278;1
"Unit";"Zergling";"Larva";278;1
"Unit";"Zergling";"Larva";278;1
"Unit";"Zergling";"Larva";278;1
"Unit";"Zergling";"Larva";278;1
"Unit";"Zergling";"Larva";278;1
"Unit";"Zergling";"Larva";278;1
"Unit";"Zergling";"Larva";278;1
"Unit";"Zergling";"Larva";278;1
"Unit";"Zergling";"Larva";278;1
"Unit";"Zergling";"Larva";278;1
"Unit";"Zergling";"Larva";278;1
"Unit";"Zergling";"Larva";278;1
"Unit";"Baneling";"Zergling";308;0
"Unit";"Baneling";"Zergling";308;0
"Unit";"Baneling";"Zergling";308;0
"Unit";"Baneling";"Zergling";308;0
"Unit";"Baneling";"Zergling";308;0
"Upgrade";"EvolveMuscularAugments";"HydraliskDen";266;0
"Unit";"Baneling";"Zergling";308;0
"Unit";"Baneling";"Zergling";308;0
"Unit";"Baneling";"Zergling";308;0
"Unit";"Baneling";"Zergling";308;0
"Unit";"Baneling";"Zergling";308;0
"Unit";"Baneling";"Zergling";308;0
"Unit";"Baneling";"Zergling";308;0
"Unit";"Baneling";"Zergling";308;0
"Unit";"Baneling";"Zergling";308;0
"Building";"CreepTumor";NA;308;0
"Building";"CreepTumor";NA;308;0
"Building";"CreepTumor";NA;308;0
"Building";"CreepTumor";NA;308;0
"Unit";"Zergling";"Larva";308;1
"Unit";"Zergling";"Larva";308;1
"Unit";"Zergling";"Larva";308;1
"Unit";"Zergling";"Larva";308;1
"Unit";"Zergling";"Larva";308;1
"Unit";"Zergling";"Larva";308;1
"Unit";"Zergling";"Larva";308;1
"Unit";"Zergling";"Larva";308;1
"Unit";"Zergling";"Larva";308;1
"Unit";"Zergling";"Larva";308;1
"Unit";"Zergling";"Larva";308;1
"Unit";"Zergling";"Larva";308;1
"Unit";"Zergling";"Larva";308;1
"Unit";"Zergling";"Larva";308;1
"Unit";"Zergling";"Larva";308;1
"Unit";"Zergling";"Larva";308;1
"Building";"CreepTumor";NA;308;0
"Building";"CreepTumor";NA;334;0
"Unit";"Queen";"Hatchery";278;2
"Building";"Spire";NA;260;0
"Upgrade";"ZergGroundArmorsLevel2";"EvolutionChamber";244;0
"Upgrade";"ZergMeleeWeaponsLevel2";"EvolutionChamber";244;0
"Unit";"Zergling";"Larva";352;1
"Unit";"Zergling";"Larva";352;1
"Unit";"Zergling";"Larva";352;1
"Unit";"Zergling";"Larva";352;1
"Unit";"Zergling";"Larva";352;1
"Unit";"Zergling";"Larva";352;1
"Unit";"Zergling";"Larva";352;1
"Unit";"Zergling";"Larva";352;1
"Unit";"Zergling";"Larva";352;1
"Unit";"Zergling";"Larva";352;1
"Unit";"Zergling";"Larva";352;1
"Unit";"Zergling";"Larva";352;1
"Unit";"Zergling";"Larva";352;1
"Unit";"Zergling";"Larva";352;1
"Unit";"Zergling";"Larva";352;1
"Unit";"Zergling";"Larva";352;1
"Unit";"Zergling";"Larva";352;1
"Unit";"Zergling";"Larva";352;1
"Unit";"Zergling";"Larva";352;1
"Unit";"Zergling";"Larva";352;1
"Unit";"Zergling";"Larva";352;1
"Unit";"Zergling";"Larva";352;1
"Unit";"Zergling";"Larva";352;1
"Unit";"Zergling";"Larva";352;1
"Unit";"Zergling";"Larva";352;1
"Unit";"Zergling";"Larva";352;1
"Unit";"Zergling";"Larva";352;1
"Unit";"Zergling";"Larva";352;1
"Unit";"Zergling";"Larva";352;1
"Unit";"Zergling";"Larva";352;1
"Building";"UltraliskCavern";NA;334;0
"Unit";"Zergling";"Larva";382;1
"Unit";"Zergling";"Larva";382;1
"Unit";"Zergling";"Larva";382;1
"Unit";"Zergling";"Larva";382;1
"Unit";"Zergling";"Larva";382;1
"Unit";"Zergling";"Larva";382;1
"Unit";"Zergling";"Larva";382;1
"Unit";"Zergling";"Larva";382;1
"Unit";"Zergling";"Larva";382;1
"Unit";"Zergling";"Larva";382;1
"Unit";"Zergling";"Larva";382;1
"Unit";"Zergling";"Larva";382;1
"Unit";"Zergling";"Larva";382;1
"Unit";"Zergling";"Larva";382;1
"Unit";"Zergling";"Larva";382;1
"Unit";"Zergling";"Larva";382;1
"Unit";"Zergling";"Larva";382;1
"Unit";"Zergling";"Larva";382;1
"Unit";"Zergling";"Larva";382;1
"Unit";"Zergling";"Larva";382;1
"Unit";"Zergling";"Larva";382;1
"Unit";"Zergling";"Larva";382;1
"Unit";"Zergling";"Larva";382;1
"Unit";"Zergling";"Larva";382;1
"Unit";"Zergling";"Larva";382;1
"Unit";"Zergling";"Larva";382;1
"Unit";"Zergling";"Larva";382;1
"Unit";"Zergling";"Larva";382;1
"Unit";"Baneling";"Zergling";382;0
"Unit";"Baneling";"Zergling";382;0
"Unit";"Baneling";"Zergling";382;0
"Unit";"Baneling";"Zergling";382;0
"Unit";"Baneling";"Zergling";382;0
"Unit";"Baneling";"Zergling";382;0
"Unit";"Baneling";"Zergling";382;0
"Unit";"Baneling";"Zergling";382;0
"Unit";"Baneling";"Zergling";382;0
"Unit";"Baneling";"Zergling";382;0
"Unit";"Baneling";"Zergling";382;0
"Unit";"Baneling";"Zergling";382;0
"Unit";"Baneling";"Zergling";382;0
"Unit";"Baneling";"Zergling";382;0
"Unit";"Hydralisk";"Larva";382;2
"Unit";"Hydralisk";"Larva";382;2
"Unit";"Hydralisk";"Larva";382;2
"Unit";"Baneling";"Zergling";382;0
"Unit";"Baneling";"Zergling";382;0
"Unit";"Baneling";"Zergling";382;0
"Unit";"Baneling";"Zergling";382;0
"Unit";"Baneling";"Zergling";382;0
"Unit";"Baneling";"Zergling";382;0
"Unit";"Baneling";"Zergling";382;0
"Unit";"Baneling";"Zergling";382;0
"Unit";"Zergling";"Larva";382;1
"Unit";"Zergling";"Larva";382;1
"Unit";"Zergling";"Larva";382;1
"Unit";"Zergling";"Larva";382;1
"Unit";"Zergling";"Larva";382;1
"Unit";"Zergling";"Larva";382;1
"Unit";"Zergling";"Larva";382;1
"Unit";"Zergling";"Larva";382;1
"Unit";"Zergling";"Larva";382;1
"Unit";"Zergling";"Larva";382;1
"Unit";"Zergling";"Larva";382;1
"Unit";"Zergling";"Larva";382;1
"Unit";"Zergling";"Larva";382;1
"Unit";"Zergling";"Larva";382;1
"Unit";"Zergling";"Larva";382;1
"Unit";"Zergling";"Larva";382;1
"Unit";"Baneling";"Zergling";432;0
"Unit";"Baneling";"Zergling";432;0
"Unit";"Zergling";"Larva";432;1
"Unit";"Zergling";"Larva";432;1
"Unit";"Zergling";"Larva";432;1
"Unit";"Zergling";"Larva";432;1
"Unit";"Zergling";"Larva";432;1
"Unit";"Zergling";"Larva";432;1
"Unit";"Zergling";"Larva";432;1
"Unit";"Zergling";"Larva";432;1
"Unit";"Zergling";"Larva";432;1
"Unit";"Zergling";"Larva";432;1
"Unit";"Zergling";"Larva";432;1
"Unit";"Zergling";"Larva";432;1
"Unit";"Zergling";"Larva";432;1
"Unit";"Zergling";"Larva";432;1
"Unit";"Zergling";"Larva";432;1
"Unit";"Zergling";"Larva";432;1
"Unit";"Zergling";"Larva";432;1
"Unit";"Zergling";"Larva";432;1
"Unit";"Zergling";"Larva";432;1
"Unit";"Zergling";"Larva";432;1
"Unit";"Zergling";"Larva";432;1
"Unit";"Zergling";"Larva";432;1
"Unit";"Zergling";"Larva";432;1
"Unit";"Zergling";"Larva";432;1
"Unit";"Zergling";"Larva";432;1
"Unit";"Zergling";"Larva";432;1
"Unit";"Zergling";"Larva";432;1
"Unit";"Zergling";"Larva";432;1
"Unit";"Zergling";"Larva";432;1
"Unit";"Zergling";"Larva";432;1
"Unit";"Baneling";"Zergling";432;0
"Unit";"Baneling";"Zergling";432;0
"Building";"CreepTumor";NA;432;0
"Unit";"Baneling";"Zergling";462;0
"Unit";"Baneling";"Zergling";462;0
"Unit";"Baneling";"Zergling";462;0
"Building";"CreepTumor";NA;466;0
"Building";"CreepTumor";NA;466;0
"Building";"CreepTumor";NA;466;0
"Building";"CreepTumor";NA;466;0
"Building";"CreepTumor";NA;466;0
"Unit";"Viper";"Larva";462;3
"Unit";"Viper";"Larva";462;3
"Unit";"Viper";"Larva";462;3
"Unit";"Viper";"Larva";462;3
"Building";"CreepTumorQueen";NA;466;0
"Building";"CreepTumorQueen";NA;466;0
"Building";"CreepTumorQueen";NA;466;0
"Building";"CreepTumorQueen";NA;466;0
"Building";"CreepTumorQueen";NA;466;0
"Building";"CreepTumorQueen";NA;466;0
"Building";"CreepTumor";NA;466;0
"Building";"CreepTumorQueen";NA;466;0
"Unit";"Overlord";"Larva";466;0
"Unit";"Overlord";"Larva";466;0
"Building";"CreepTumor";NA;475;0
"Building";"Extractor";NA;466;0
"Building";"Hatchery";NA;432;0
"Building";"Extractor";NA;466;0
"Building";"CreepTumor";NA;480;0
"Building";"CreepTumor";NA;480;0
"Building";"CreepTumor";NA;480;0
"Building";"CreepTumor";NA;480;0
"Building";"CreepTumor";NA;480;0
"Building";"CreepTumor";NA;480;0
"Building";"CreepTumor";NA;480;0
"Building";"CreepTumor";NA;480;0
"Building";"CreepTumor";NA;480;0
"Building";"CreepTumorQueen";NA;480;0
"Building";"CreepTumorQueen";NA;480;0
"Unit";"Baneling";"Zergling";480;0
"Unit";"Baneling";"Zergling";480;0
"Unit";"Zergling";"Larva";480;1
"Unit";"Zergling";"Larva";480;1
"Unit";"Baneling";"Zergling";480;0
"Building";"CreepTumorQueen";NA;480;0
"Unit";"Zergling";"Larva";480;1
"Unit";"Zergling";"Larva";480;1
"Unit";"Zergling";"Larva";480;1
"Unit";"Zergling";"Larva";480;1
"Unit";"Zergling";"Larva";480;1
"Unit";"Zergling";"Larva";480;1
"Unit";"Zergling";"Larva";480;1
"Unit";"Zergling";"Larva";480;1
"Upgrade";"ChitinousPlating";"UltraliskCavern";466;0
"Building";"CreepTumor";NA;480;0
"Building";"CreepTumor";NA;480;0
"Building";"CreepTumor";NA;480;0
"Building";"CreepTumor";NA;480;0
"Building";"CreepTumor";NA;480;0
"Building";"CreepTumor";NA;480;0
"Building";"CreepTumor";NA;480;0
"Building";"CreepTumor";NA;480;0
"Building";"CreepTumor";NA;480;0
"Building";"CreepTumor";NA;480;0
"Building";"CreepTumor";NA;480;0
"Building";"CreepTumor";NA;480;0
"Building";"CreepTumorQueen";NA;490;0
"Building";"Hatchery";NA;466;0
"Upgrade";"ZergGroundArmorsLevel3";"EvolutionChamber";432;0
"Upgrade";"ZergMeleeWeaponsLevel3";"EvolutionChamber";432;0
"Unit";"Baneling";"Zergling";490;0
"Unit";"Baneling";"Zergling";490;0
"Unit";"Baneling";"Zergling";490;0
"Unit";"Baneling";"Zergling";490;0
"Unit";"Baneling";"Zergling";490;0
"Unit";"Baneling";"Zergling";490;0
"Unit";"Baneling";"Zergling";490;0
"Unit";"Baneling";"Zergling";490;0
"Unit";"Baneling";"Zergling";490;0
"Unit";"Baneling";"Zergling";490;0
"Building";"Extractor";NA;490;0
"Unit";"Baneling";"Zergling";490;0
"Unit";"Baneling";"Zergling";490;0
"Unit";"Baneling";"Zergling";490;0
"Unit";"Baneling";"Zergling";490;0
"Unit";"Baneling";"Zergling";490;0
"Building";"CreepTumor";NA;490;0
"Building";"CreepTumor";NA;490;0
"Unit";"Zergling";"Larva";490;1
"Unit";"Zergling";"Larva";490;1
"Unit";"Zergling";"Larva";490;1
"Unit";"Zergling";"Larva";490;1
"Building";"CreepTumor";NA;490;0
"Building";"CreepTumor";NA;490;0
"Building";"CreepTumor";NA;490;0
"Building";"CreepTumor";NA;490;0
"Building";"CreepTumor";NA;490;0
"Building";"CreepTumor";NA;490;0
"Building";"CreepTumor";NA;490;0
"Building";"CreepTumor";NA;490;0
"Building";"CreepTumor";NA;490;0
"Building";"CreepTumor";NA;490;0
"Building";"CreepTumorQueen";NA;490;0
"Building";"CreepTumor";NA;490;0
"Building";"CreepTumorQueen";NA;494;0
"Building";"CreepTumor";NA;490;0
"Building";"CreepTumor";NA;490;0
"Building";"CreepTumor";NA;494;0
"Building";"Spire";NA;490;0
"Building";"CreepTumor";NA;494;0
"Building";"CreepTumor";NA;494;0
"Building";"CreepTumor";NA;494;0
"Building";"CreepTumor";NA;494;0
"Building";"CreepTumor";NA;494;0
"Unit";"Baneling";"Zergling";497;0
"Unit";"Baneling";"Zergling";497;0
"Unit";"Baneling";"Zergling";497;0
"Unit";"Baneling";"Zergling";497;0
"Unit";"Baneling";"Zergling";497;0
"Unit";"Baneling";"Zergling";497;0
"Unit";"Baneling";"Zergling";497;0
"Unit";"Baneling";"Zergling";497;0
"Building";"SpineCrawler";NA;494;0
"Building";"SpineCrawler";NA;494;0
"Building";"SpineCrawler";NA;494;0
"Unit";"Baneling";"Zergling";497;0
"Unit";"Baneling";"Zergling";497;0
"Unit";"Baneling";"Zergling";497;0
"Unit";"Baneling";"Zergling";497;0
"Unit";"Baneling";"Zergling";497;0
"Building";"CreepTumor";NA;497;0
"Building";"CreepTumor";NA;497;0
"Unit";"Overlord";"Larva";497;0
"Unit";"Overlord";"Larva";497;0
"Unit";"Overlord";"Larva";497;0
"Upgrade";"ZergMissileWeaponsLevel1";"EvolutionChamber";490;0
"Building";"Extractor";NA;497;0
"Building";"Extractor";NA;497;0
"Unit";"Baneling";"Zergling";497;0
"Unit";"Baneling";"Zergling";497;0
"Building";"Hatchery";NA;497;0
"Unit";"Ultralisk";"Larva";497;6
"Unit";"Ultralisk";"Larva";497;6
"Unit";"Ultralisk";"Larva";497;6
"Unit";"Ultralisk";"Larva";497;6
"Unit";"Ultralisk";"Larva";497;6
"Unit";"Ultralisk";"Larva";497;6
"Unit";"Ultralisk";"Larva";497;6
"Unit";"Ultralisk";"Larva";497;6
"Unit";"Ultralisk";"Larva";497;6
"Unit";"Ultralisk";"Larva";497;6
"Unit";"Ultralisk";"Larva";497;6
"Unit";"Ultralisk";"Larva";497;6
"Unit";"Ultralisk";"Larva";497;6
"Unit";"Ultralisk";"Larva";497;6
"Unit";"Ultralisk";"Larva";497;6
"Building";"Hatchery";NA;497;0
"Building";"CreepTumor";NA;590;0
"Unit";"Zergling";"Larva";590;1
"Unit";"Zergling";"Larva";590;1
"Unit";"Zergling";"Larva";590;1
"Unit";"Zergling";"Larva";590;1
"Unit";"Zergling";"Larva";590;1
"Unit";"Zergling";"Larva";590;1
"Unit";"Zergling";"Larva";590;1
"Unit";"Zergling";"Larva";590;1
"Unit";"Zergling";"Larva";590;1
"Unit";"Zergling";"Larva";590;1
"Unit";"Zergling";"Larva";590;1
"Unit";"Zergling";"Larva";590;1
"Unit";"Zergling";"Larva";590;1
"Unit";"Zergling";"Larva";590;1
"Unit";"Zergling";"Larva";590;1
"Unit";"Zergling";"Larva";590;1
"Unit";"Zergling";"Larva";590;1
"Unit";"Zergling";"Larva";590;1
"Unit";"Zergling";"Larva";590;1
"Unit";"Zergling";"Larva";590;1
"Unit";"Zergling";"Larva";590;1
"Unit";"Zergling";"Larva";590;1
"Unit";"Zergling";"Larva";590;1
"Unit";"Zergling";"Larva";590;1
"Unit";"Zergling";"Larva";590;1
"Unit";"Zergling";"Larva";590;1
"Unit";"Infestor";"Larva";590;2
"Unit";"Infestor";"Larva";590;2
"Unit";"Infestor";"Larva";590;2
"Unit";"Infestor";"Larva";590;2
"Unit";"Infestor";"Larva";590;2
"Unit";"Infestor";"Larva";590;2
"Unit";"Viper";"Larva";590;3
"Unit";"Corruptor";"Larva";590;2
"Unit";"Corruptor";"Larva";590;2
"Unit";"Corruptor";"Larva";590;2
"Unit";"Corruptor";"Larva";590;2
"Unit";"Corruptor";"Larva";590;2
"Unit";"Corruptor";"Larva";590;2
"Unit";"Corruptor";"Larva";590;2
"Unit";"Corruptor";"Larva";590;2
"Building";"SporeCrawler";NA;590;0
"Unit";"Ultralisk";"Larva";590;6
"Unit";"Ultralisk";"Larva";590;6
"Unit";"Ultralisk";"Larva";590;6
"Unit";"Ultralisk";"Larva";590;6
"Unit";"Ultralisk";"Larva";590;6
"Unit";"Ultralisk";"Larva";590;6
"Building";"CreepTumor";NA;630;0
"Building";"CreepTumor";NA;630;0
"Unit";"Baneling";"Zergling";633;0
"Unit";"Baneling";"Zergling";633;0
"Unit";"Baneling";"Zergling";633;0
"Unit";"Baneling";"Zergling";633;0
"Unit";"Baneling";"Zergling";633;0
"Unit";"Baneling";"Zergling";633;0
"Unit";"Baneling";"Zergling";633;0
"Unit";"Baneling";"Zergling";633;0
"Unit";"Baneling";"Zergling";633;0
"Unit";"Baneling";"Zergling";633;0
"Unit";"Baneling";"Zergling";633;0
"Unit";"Baneling";"Zergling";633;0
"Building";"Hatchery";NA;590;0
"Building";"SpineCrawler";NA;590;0
"Unit";"Baneling";"Zergling";685;0
"Unit";"Baneling";"Zergling";685;0
"Unit";"Baneling";"Zergling";685;0
