"type";"unit_name";"on_building";"total_supply_lag";"supply"
"Unit";"Overlord";"Larva";13;0
"Building";"Hatchery";NA;17;0
"Building";"Extractor";NA;19;0
"Building";"SpawningPool";NA;19;0
"Unit";"Overlord";"Larva";22;0
"Unit";"Queen";"Hatchery";23;2
"Unit";"Zergling";"Larva";25;1
"Unit";"Zergling";"Larva";26;1
"Unit";"Queen";"Hatchery";27;2
"Unit";"Zergling";"Larva";29;1
"Unit";"Zergling";"Larva";30;1
"Building";"Hatchery";NA;33;0
"Building";"CreepTumorQueen";NA;36;0
"Unit";"Queen";"Hatchery";36;2
"Unit";"Overlord";"Larva";39;0
"Unit";"Overlord";"Larva";45;0
"Building";"CreepTumor";NA;45;0
"Building";"CreepTumorQueen";NA;46;0
"Unit";"Queen";"Hatchery";47;2
"Unit";"Queen";"Hatchery";50;2
"Building";"CreepTumor";NA;55;0
"Building";"CreepTumor";NA;55;0
"Unit";"Overlord";"Larva";57;0
"Unit";"Zergling";"Larva";57;1
"Unit";"Zergling";"Larva";58;1
"Unit";"Zergling";"Larva";59;1
"Unit";"Zergling";"Larva";60;1
"Unit";"Zergling";"Larva";61;1
"Unit";"Zergling";"Larva";62;1
"Unit";"Zergling";"Larva";63;1
"Unit";"Zergling";"Larva";64;1
"Unit";"Zergling";"Larva";65;1
"Unit";"Zergling";"Larva";66;1
"Unit";"Queen";"Hatchery";67;2
"Unit";"Queen";"Hatchery";69;2
"Building";"CreepTumor";NA;72;0
"Building";"CreepTumor";NA;72;0
"Unit";"Overlord";"Larva";74;0
"Building";"CreepTumorQueen";NA;74;0
"Unit";"Overlord";"Larva";74;0
"Building";"BanelingNest";NA;76;0
"Unit";"Overlord";"Larva";76;0
"Unit";"Overlord";"Larva";76;0
"Building";"CreepTumor";NA;76;0
"Building";"CreepTumorQueen";NA;76;0
"Building";"CreepTumor";NA;76;0
"Unit";"Overlord";"Larva";76;0
"Building";"CreepTumorQueen";NA;92;0
"Building";"CreepTumor";NA;92;0
"Building";"CreepTumorQueen";NA;92;0
"Building";"CreepTumor";NA;92;0
"Building";"SporeCrawler";NA;92;0
"Building";"SporeCrawler";NA;92;0
"Building";"SporeCrawler";NA;92;0
"Building";"CreepTumor";NA;94;0
"Building";"EvolutionChamber";NA;96;0
"Building";"EvolutionChamber";NA;96;0
"Unit";"Overlord";"Larva";96;0
"Building";"Extractor";NA;97;0
"Building";"Extractor";NA;97;0
"Building";"Extractor";NA;97;0
"Building";"CreepTumor";NA;100;0
"Building";"CreepTumor";NA;100;0
"Building";"Extractor";NA;103;0
"Building";"CreepTumor";NA;103;0
"Building";"Extractor";NA;103;0
"Building";"CreepTumor";NA;105;0
"Unit";"Overlord";"Larva";106;0
"Building";"Hatchery";NA;106;0
"Unit";"Baneling";"Zergling";106;0
"Unit";"Baneling";"Zergling";106;0
"Unit";"Baneling";"Zergling";106;0
"Unit";"Zergling";"Larva";106;1
"Unit";"Zergling";"Larva";107;1
"Unit";"Zergling";"Larva";108;1
"Unit";"Zergling";"Larva";109;1
"Unit";"Zergling";"Larva";110;1
"Unit";"Zergling";"Larva";111;1
"Unit";"Zergling";"Larva";112;1
"Unit";"Zergling";"Larva";113;1
"Unit";"Overlord";"Larva";114;0
"Building";"CreepTumor";NA;114;0
"Unit";"Overlord";"Larva";114;0
"Building";"CreepTumorQueen";NA;115;0
"Building";"CreepTumorQueen";NA;121;0
"Building";"CreepTumor";NA;121;0
"Unit";"Overlord";"Larva";121;0
"Unit";"Overlord";"Larva";121;0
"Unit";"Baneling";"Zergling";121;0
"Unit";"Zergling";"Larva";121;1
"Unit";"Zergling";"Larva";122;1
"Unit";"Zergling";"Larva";123;1
"Unit";"Zergling";"Larva";124;1
"Unit";"Zergling";"Larva";125;1
"Unit";"Zergling";"Larva";126;1
"Unit";"Zergling";"Larva";127;1
"Unit";"Zergling";"Larva";128;1
"Unit";"Zergling";"Larva";129;1
"Unit";"Zergling";"Larva";130;1
"Unit";"Zergling";"Larva";131;1
"Unit";"Zergling";"Larva";132;1
"Building";"CreepTumorQueen";NA;133;0
"Building";"CreepTumor";NA;138;0
"Building";"CreepTumor";NA;138;0
"Building";"HydraliskDen";NA;141;0
"Building";"CreepTumor";NA;141;0
"Building";"CreepTumor";NA;144;0
"Building";"CreepTumor";NA;144;0
"Unit";"Queen";"Hatchery";144;2
"Unit";"Overlord";"Larva";146;0
"Building";"CreepTumor";NA;146;0
"Building";"CreepTumor";NA;146;0
"Building";"CreepTumor";NA;146;0
"Building";"CreepTumor";NA;146;0
"Unit";"Zergling";"Larva";146;1
"Unit";"Zergling";"Larva";147;1
"Building";"Extractor";NA;151;0
"Building";"InfestationPit";NA;155;0
"Unit";"Queen";"Hatchery";155;2
"Building";"Extractor";NA;157;0
"Building";"CreepTumor";NA;157;0
"Building";"CreepTumor";NA;157;0
"Building";"CreepTumor";NA;157;0
"Unit";"Zergling";"Larva";157;1
"Unit";"Zergling";"Larva";158;1
"Unit";"Zergling";"Larva";159;1
"Unit";"Zergling";"Larva";160;1
"Unit";"Zergling";"Larva";161;1
"Unit";"Zergling";"Larva";162;1
"Unit";"Zergling";"Larva";163;1
"Unit";"Zergling";"Larva";164;1
"Unit";"Zergling";"Larva";165;1
"Unit";"Zergling";"Larva";166;1
"Unit";"Zergling";"Larva";167;1
"Unit";"Zergling";"Larva";168;1
"Unit";"Zergling";"Larva";169;1
"Unit";"Zergling";"Larva";170;1
"Unit";"Hydralisk";"Larva";171;2
"Unit";"Hydralisk";"Larva";173;2
"Unit";"Hydralisk";"Larva";175;2
"Unit";"Hydralisk";"Larva";177;2
"Unit";"Baneling";"Zergling";179;0
"Unit";"Baneling";"Zergling";179;0
"Building";"CreepTumor";NA;179;0
"Building";"CreepTumorQueen";NA;179;0
"Building";"CreepTumor";NA;179;0
"Building";"CreepTumor";NA;179;0
"Building";"CreepTumorQueen";NA;179;0
"Unit";"Hydralisk";"Larva";179;2
"Unit";"Hydralisk";"Larva";181;2
"Unit";"Hydralisk";"Larva";183;2
"Unit";"Hydralisk";"Larva";185;2
"Unit";"Zergling";"Larva";187;1
"Unit";"Zergling";"Larva";188;1
"Unit";"Hydralisk";"Larva";189;2
"Unit";"Overlord";"Larva";191;0
"Unit";"Overlord";"Larva";191;0
"Unit";"Overlord";"Larva";191;0
"Building";"CreepTumor";NA;191;0
"Building";"CreepTumor";NA;191;0
"Building";"CreepTumor";NA;191;0
"Unit";"Queen";"Hatchery";191;2
"Unit";"Queen";"Hatchery";193;2
"Unit";"Queen";"Hatchery";195;2
"Unit";"Overlord";"Larva";197;0
"Building";"CreepTumor";NA;197;0
"Building";"CreepTumor";NA;197;0
"Unit";"Overlord";"Larva";197;0
"Unit";"Overlord";"Larva";197;0
"Unit";"Hydralisk";"Larva";197;2
"Unit";"Hydralisk";"Larva";199;2
"Unit";"Hydralisk";"Larva";201;2
"Unit";"Hydralisk";"Larva";203;2
"Unit";"Hydralisk";"Larva";205;2
"Unit";"Hydralisk";"Larva";207;2
"Unit";"Hydralisk";"Larva";209;2
"Unit";"Hydralisk";"Larva";211;2
"Unit";"Hydralisk";"Larva";213;2
"Unit";"Zergling";"Larva";215;1
"Unit";"Zergling";"Larva";216;1
"Unit";"Baneling";"Zergling";217;0
"Unit";"Baneling";"Zergling";217;0
"Unit";"Baneling";"Zergling";217;0
"Unit";"Baneling";"Zergling";217;0
"Unit";"Baneling";"Zergling";217;0
"Unit";"Baneling";"Zergling";217;0
"Unit";"Baneling";"Zergling";217;0
"Unit";"Zergling";"Larva";217;1
"Unit";"Zergling";"Larva";218;1
"Unit";"Overlord";"Larva";219;0
"Unit";"Overlord";"Larva";219;0
"Unit";"Overlord";"Larva";219;0
"Unit";"Overlord";"Larva";219;0
"Unit";"Hydralisk";"Larva";219;2
"Unit";"Hydralisk";"Larva";221;2
"Unit";"Hydralisk";"Larva";223;2
"Unit";"Zergling";"Larva";225;1
"Unit";"Zergling";"Larva";226;1
"Unit";"Zergling";"Larva";227;1
"Unit";"Zergling";"Larva";228;1
"Unit";"Zergling";"Larva";229;1
"Unit";"Zergling";"Larva";230;1
"Unit";"Hydralisk";"Larva";231;2
"Unit";"Zergling";"Larva";233;1
"Unit";"Zergling";"Larva";234;1
"Unit";"Zergling";"Larva";235;1
"Unit";"Zergling";"Larva";236;1
"Unit";"Hydralisk";"Larva";237;2
"Unit";"Zergling";"Larva";239;1
"Unit";"Zergling";"Larva";240;1
"Unit";"Hydralisk";"Larva";241;2
"Unit";"Hydralisk";"Larva";243;2
"Unit";"Zergling";"Larva";245;1
"Unit";"Zergling";"Larva";246;1
"Unit";"Hydralisk";"Larva";247;2
"Unit";"Hydralisk";"Larva";249;2
"Unit";"Hydralisk";"Larva";251;2
"Unit";"Queen";"Hatchery";253;2
"Building";"CreepTumorQueen";NA;255;0
"Building";"CreepTumor";NA;255;0
"Building";"CreepTumor";NA;255;0
"Building";"CreepTumor";NA;255;0
"Building";"CreepTumor";NA;255;0
"Building";"Spire";NA;255;0
"Unit";"Hydralisk";"Larva";255;2
"Unit";"Hydralisk";"Larva";257;2
"Unit";"Hydralisk";"Larva";259;2
"Building";"Hatchery";NA;261;0
"Unit";"Zergling";"Larva";261;1
"Unit";"Zergling";"Larva";262;1
"Unit";"Zergling";"Larva";263;1
"Unit";"Zergling";"Larva";264;1
"Unit";"Zergling";"Larva";265;1
"Unit";"Zergling";"Larva";266;1
"Unit";"Zergling";"Larva";267;1
"Unit";"Zergling";"Larva";268;1
"Unit";"Zergling";"Larva";269;1
"Unit";"Zergling";"Larva";270;1
"Unit";"Zergling";"Larva";271;1
"Unit";"Zergling";"Larva";272;1
"Building";"CreepTumorQueen";NA;273;0
"Building";"CreepTumorQueen";NA;273;0
"Unit";"Viper";"Larva";273;3
"Unit";"Queen";"Hatchery";276;2
"Unit";"Queen";"Hatchery";278;2
"Unit";"Queen";"Hatchery";280;2
"Building";"CreepTumor";NA;282;0
"Building";"EvolutionChamber";NA;282;0
"Unit";"Viper";"Larva";282;3
"Unit";"Overlord";"Larva";285;0
"Unit";"Overlord";"Larva";285;0
"Unit";"Viper";"Larva";285;3
"Unit";"Queen";"Hatchery";293;2
"Building";"CreepTumor";NA;295;0
"Unit";"Zergling";"Larva";295;1
"Unit";"Zergling";"Larva";296;1
"Unit";"Zergling";"Larva";297;1
"Unit";"Zergling";"Larva";298;1
"Unit";"Zergling";"Larva";299;1
"Unit";"Zergling";"Larva";300;1
"Unit";"Zergling";"Larva";301;1
"Unit";"Zergling";"Larva";302;1
"Unit";"Hydralisk";"Larva";303;2
"Building";"CreepTumor";NA;305;0
"Building";"CreepTumorQueen";NA;305;0
"Building";"CreepTumor";NA;305;0
"Building";"CreepTumor";NA;305;0
"Building";"CreepTumor";NA;305;0
"Building";"CreepTumor";NA;305;0
"Building";"CreepTumor";NA;305;0
"Building";"CreepTumor";NA;305;0
"Building";"Extractor";NA;305;0
"Unit";"Queen";"Hatchery";305;2
"Unit";"Queen";"Hatchery";307;2
"Unit";"Queen";"Hatchery";309;2
"Building";"Extractor";NA;311;0
"Unit";"Hydralisk";"Larva";311;2
"Unit";"Hydralisk";"Larva";313;2
"Unit";"Hydralisk";"Larva";315;2
"Unit";"Hydralisk";"Larva";317;2
"Unit";"Hydralisk";"Larva";319;2
"Unit";"Hydralisk";"Larva";321;2
"Unit";"Hydralisk";"Larva";323;2
"Unit";"Hydralisk";"Larva";325;2
"Unit";"Hydralisk";"Larva";327;2
"Building";"SpineCrawler";NA;333;0
"Building";"CreepTumor";NA;333;0
"Building";"CreepTumor";NA;333;0
"Building";"CreepTumor";NA;333;0
"Unit";"Hydralisk";"Larva";333;2
"Unit";"Hydralisk";"Larva";335;2
"Unit";"Hydralisk";"Larva";337;2
"Unit";"Baneling";"Zergling";339;0
"Unit";"Baneling";"Zergling";339;0
"Unit";"Baneling";"Zergling";339;0
"Unit";"Baneling";"Zergling";339;0
"Unit";"Baneling";"Zergling";339;0
"Building";"SpineCrawler";NA;339;0
"Unit";"Hydralisk";"Larva";339;2
"Building";"EvolutionChamber";NA;341;0
"Unit";"Hydralisk";"Larva";341;2
"Unit";"Hydralisk";"Larva";343;2
"Unit";"Hydralisk";"Larva";345;2
"Building";"EvolutionChamber";NA;347;0
"Unit";"Hydralisk";"Larva";347;2
"Building";"EvolutionChamber";NA;349;0
"Unit";"Baneling";"Zergling";349;0
"Unit";"Baneling";"Zergling";349;0
"Unit";"Baneling";"Zergling";349;0
"Unit";"Baneling";"Zergling";349;0
"Building";"CreepTumorQueen";NA;349;0
"Unit";"Hydralisk";"Larva";349;2
"Unit";"Overlord";"Larva";351;0
"Unit";"Hydralisk";"Larva";351;2
"Unit";"Corruptor";"Larva";353;2
"Unit";"Corruptor";"Larva";355;2
"Unit";"Corruptor";"Larva";357;2
"Unit";"Corruptor";"Larva";359;2
"Unit";"Corruptor";"Larva";361;2
"Unit";"Corruptor";"Larva";363;2
"Unit";"Corruptor";"Larva";365;2
"Unit";"Corruptor";"Larva";367;2
"Unit";"Queen";"Hatchery";369;2
"Unit";"Queen";"Hatchery";371;2
"Unit";"Queen";"Hatchery";373;2
"Unit";"Queen";"Hatchery";375;2
"Unit";"Corruptor";"Larva";377;2
"Unit";"Corruptor";"Larva";379;2
"Unit";"Corruptor";"Larva";381;2
"Unit";"Corruptor";"Larva";383;2
"Unit";"Corruptor";"Larva";385;2
"Unit";"Corruptor";"Larva";387;2
"Unit";"Overlord";"Larva";389;0
"Unit";"Overlord";"Larva";389;0
"Unit";"Overlord";"Larva";389;0
"Unit";"Corruptor";"Larva";389;2
"Unit";"Corruptor";"Larva";391;2
"Unit";"Corruptor";"Larva";393;2
"Unit";"Corruptor";"Larva";395;2
"Unit";"Corruptor";"Larva";397;2
"Unit";"Corruptor";"Larva";399;2
"Unit";"Corruptor";"Larva";401;2
"Unit";"Hydralisk";"Larva";403;2
"Unit";"Hydralisk";"Larva";405;2
"Unit";"Hydralisk";"Larva";407;2
"Building";"CreepTumor";NA;409;0
"Building";"CreepTumorQueen";NA;409;0
"Unit";"Queen";"Hatchery";409;2
"Unit";"Queen";"Hatchery";411;2
"Unit";"Queen";"Hatchery";413;2
"Unit";"Corruptor";"Larva";415;2
"Unit";"Corruptor";"Larva";417;2
"Building";"Hatchery";NA;419;0
"Building";"CreepTumorQueen";NA;419;0
"Unit";"Corruptor";"Larva";419;2
"Unit";"Corruptor";"Larva";421;2
"Unit";"Hydralisk";"Larva";423;2
"Unit";"Hydralisk";"Larva";425;2
"Unit";"Hydralisk";"Larva";427;2
"Unit";"Hydralisk";"Larva";429;2
"Unit";"Corruptor";"Larva";431;2
"Unit";"Corruptor";"Larva";433;2
"Unit";"Overlord";"Larva";435;0
"Unit";"Queen";"Hatchery";437;2
"Unit";"Queen";"Hatchery";439;2
"Unit";"Hydralisk";"Larva";441;2
"Unit";"Hydralisk";"Larva";443;2
"Unit";"Hydralisk";"Larva";445;2
"Unit";"Hydralisk";"Larva";447;2
"Unit";"Hydralisk";"Larva";449;2
"Unit";"Hydralisk";"Larva";451;2
"Unit";"Hydralisk";"Larva";453;2
"Unit";"Hydralisk";"Larva";455;2
"Unit";"Hydralisk";"Larva";457;2
"Unit";"Hydralisk";"Larva";459;2
"Unit";"Hydralisk";"Larva";461;2
"Unit";"Hydralisk";"Larva";463;2
"Unit";"Hydralisk";"Larva";465;2
"Unit";"Hydralisk";"Larva";467;2
"Unit";"Hydralisk";"Larva";469;2
"Unit";"Hydralisk";"Larva";471;2
"Unit";"Hydralisk";"Larva";473;2
"Unit";"Hydralisk";"Larva";475;2
"Unit";"Hydralisk";"Larva";477;2
"Unit";"Zergling";"Larva";479;1
"Unit";"Zergling";"Larva";480;1
"Unit";"Zergling";"Larva";481;1
"Unit";"Zergling";"Larva";482;1
"Unit";"Zergling";"Larva";483;1
"Unit";"Zergling";"Larva";484;1
"Unit";"Zergling";"Larva";485;1
"Unit";"Zergling";"Larva";486;1
"Unit";"Zergling";"Larva";487;1
"Unit";"Zergling";"Larva";488;1
"Unit";"Zergling";"Larva";489;1
"Unit";"Zergling";"Larva";490;1
"Unit";"Zergling";"Larva";491;1
"Unit";"Zergling";"Larva";492;1
"Upgrade";"SprayZerg";NA;493;0
"Upgrade";"SprayZerg";NA;493;0
"Upgrade";"SprayZerg";NA;493;0
"Upgrade";"SprayZerg";NA;493;0
"Upgrade";"zerglingmovementspeed";NA;493;0
"Upgrade";"SprayZerg";NA;493;0
"Upgrade";"CentrificalHooks";NA;493;0
"Upgrade";"SprayZerg";NA;493;0
"Upgrade";"ZergGroundArmorsLevel1";NA;493;0
"Upgrade";"EvolveMuscularAugments";NA;493;0
"Upgrade";"ZergMissileWeaponsLevel1";NA;493;0
"Upgrade";"SprayZerg";NA;493;0
"Upgrade";"SprayZerg";NA;493;0
"Upgrade";"ZergMissileWeaponsLevel2";NA;493;0
"Upgrade";"ZergGroundArmorsLevel2";NA;493;0
"Upgrade";"SprayZerg";NA;493;0
"Upgrade";"SprayZerg";NA;493;0
