"type";"unit_name";"on_building";"total_supply";"supply"
"Unit";"Overlord";"Larva";13;0
"Building";"Extractor";NA;18;0
"Unit";"Overlord";"Larva";21;0
"Building";"SpawningPool";NA;19;0
"Building";"Hatchery";NA;17;0
"Unit";"Zergling";"Larva";22;1
"Unit";"Zergling";"Larva";22;1
"Unit";"Zergling";"Larva";23;1
"Unit";"Zergling";"Larva";23;1
"Unit";"Queen";"Hatchery";22;2
"Unit";"Queen";"Hatchery";23;2
"Unit";"Overlord";"Larva";34;0
"Unit";"Overlord";"Larva";38;0
"Building";"Hatchery";NA;27;0
"Unit";"Queen";"Hatchery";37;2
"Unit";"Overlord";"Larva";40;0
"Unit";"Overlord";"Larva";46;0
"Building";"CreepTumorQueen";NA;50;0
"Unit";"Overlord";"Larva";50;0
"Unit";"Queen";"Hatchery";50;2
"Building";"CreepTumorQueen";NA;67;0
"Building";"CreepTumor";NA;67;0
"Unit";"Zergling";"Larva";67;1
"Unit";"Zergling";"Larva";67;1
"Unit";"Zergling";"Larva";68;1
"Unit";"Zergling";"Larva";68;1
"Unit";"Zergling";"Larva";68;1
"Unit";"Zergling";"Larva";68;1
"Unit";"Zergling";"Larva";68;1
"Unit";"Zergling";"Larva";68;1
"Unit";"Zergling";"Larva";68;1
"Unit";"Zergling";"Larva";68;1
"Unit";"Zergling";"Larva";68;1
"Unit";"Zergling";"Larva";68;1
"Unit";"Zergling";"Larva";68;1
"Unit";"Zergling";"Larva";68;1
"Unit";"Queen";"Hatchery";61;2
"Unit";"Overlord";"Larva";68;0
"Unit";"Overlord";"Larva";70;0
"Building";"Extractor";NA;70;0
"Building";"CreepTumor";NA;86;0
"Building";"BanelingNest";NA;68;0
"Building";"CreepTumorQueen";NA;86;0
"Unit";"Zergling";"Larva";86;1
"Unit";"Zergling";"Larva";86;1
"Unit";"Zergling";"Larva";86;1
"Unit";"Zergling";"Larva";86;1
"Unit";"Zergling";"Larva";86;1
"Unit";"Zergling";"Larva";86;1
"Unit";"Zergling";"Larva";86;1
"Unit";"Zergling";"Larva";86;1
"Unit";"Zergling";"Larva";86;1
"Unit";"Zergling";"Larva";86;1
"Unit";"Zergling";"Larva";86;1
"Unit";"Zergling";"Larva";86;1
"Unit";"Zergling";"Larva";86;1
"Unit";"Zergling";"Larva";86;1
"Unit";"Zergling";"Larva";86;1
"Unit";"Zergling";"Larva";86;1
"Unit";"Zergling";"Larva";86;1
"Unit";"Zergling";"Larva";86;1
"Unit";"Overlord";"Larva";86;0
"Unit";"Overlord";"Larva";86;0
"Unit";"Queen";"Hatchery";70;2
"Unit";"Zergling";"Larva";86;1
"Unit";"Zergling";"Larva";86;1
"Unit";"Zergling";"Larva";86;1
"Unit";"Zergling";"Larva";86;1
"Unit";"Zergling";"Larva";86;1
"Unit";"Zergling";"Larva";86;1
"Unit";"Zergling";"Larva";86;1
"Unit";"Zergling";"Larva";86;1
"Unit";"Zergling";"Larva";86;1
"Unit";"Zergling";"Larva";86;1
"Unit";"Zergling";"Larva";86;1
"Unit";"Zergling";"Larva";86;1
"Unit";"Zergling";"Larva";106;1
"Unit";"Zergling";"Larva";106;1
"Unit";"Zergling";"Larva";106;1
"Unit";"Zergling";"Larva";106;1
"Unit";"Zergling";"Larva";106;1
"Unit";"Zergling";"Larva";106;1
"Unit";"Zergling";"Larva";106;1
"Unit";"Zergling";"Larva";106;1
"Unit";"Zergling";"Larva";106;1
"Unit";"Zergling";"Larva";106;1
"Unit";"Zergling";"Larva";106;1
"Unit";"Zergling";"Larva";106;1
"Unit";"Zergling";"Larva";106;1
"Unit";"Zergling";"Larva";106;1
"Building";"CreepTumorQueen";NA;118;0
"Building";"EvolutionChamber";NA;118;0
"Building";"EvolutionChamber";NA;118;0
"Building";"Extractor";NA;132;0
"Building";"Extractor";NA;132;0
"Unit";"Baneling";"Zergling";140;0
"Unit";"Baneling";"Zergling";140;0
"Building";"CreepTumorQueen";NA;141;0
"Building";"CreepTumor";NA;141;0
"Building";"CreepTumor";NA;141;0
"Building";"Extractor";NA;140;0
"Building";"CreepTumor";NA;141;0
"Building";"CreepTumorQueen";NA;143;0
"Building";"CreepTumorQueen";NA;143;0
"Building";"HydraliskDen";NA;136;0
"Unit";"Overlord";"Larva";141;0
"Unit";"Overlord";"Larva";141;0
"Building";"CreepTumorQueen";NA;143;0
"Unit";"Overlord";"Larva";143;0
"Building";"CreepTumor";NA;148;0
"Unit";"Overlord";"Larva";148;0
"Unit";"Baneling";"Zergling";148;0
"Unit";"Baneling";"Zergling";148;0
"Unit";"Baneling";"Zergling";148;0
"Unit";"Baneling";"Zergling";148;0
"Unit";"Baneling";"Zergling";148;0
"Unit";"Baneling";"Zergling";148;0
"Unit";"Zergling";"Larva";148;1
"Unit";"Zergling";"Larva";148;1
"Building";"CreepTumor";NA;151;0
"Unit";"Zergling";"Larva";148;1
"Unit";"Zergling";"Larva";148;1
"Unit";"Zergling";"Larva";148;1
"Unit";"Zergling";"Larva";148;1
"Unit";"Zergling";"Larva";148;1
"Unit";"Zergling";"Larva";148;1
"Unit";"Zergling";"Larva";148;1
"Unit";"Zergling";"Larva";148;1
"Building";"CreepTumorQueen";NA;151;0
"Building";"CreepTumorQueen";NA;151;0
"Building";"Extractor";NA;151;0
"Unit";"Zergling";"Larva";151;1
"Unit";"Zergling";"Larva";151;1
"Unit";"Zergling";"Larva";151;1
"Unit";"Zergling";"Larva";151;1
"Unit";"Zergling";"Larva";151;1
"Unit";"Zergling";"Larva";151;1
"Unit";"Zergling";"Larva";151;1
"Unit";"Zergling";"Larva";151;1
"Unit";"Zergling";"Larva";161;1
"Unit";"Zergling";"Larva";161;1
"Unit";"Zergling";"Larva";161;1
"Unit";"Zergling";"Larva";161;1
"Unit";"Zergling";"Larva";161;1
"Unit";"Zergling";"Larva";161;1
"Unit";"Zergling";"Larva";161;1
"Unit";"Zergling";"Larva";161;1
"Unit";"Zergling";"Larva";161;1
"Unit";"Zergling";"Larva";161;1
"Unit";"Overlord";"Larva";161;0
"Unit";"Overlord";"Larva";161;0
"Building";"Hatchery";NA;145;0
"Unit";"Overlord";"Larva";169;0
"Unit";"Overlord";"Larva";169;0
"Unit";"Overlord";"Larva";169;0
"Unit";"Hydralisk";"Larva";169;2
"Unit";"Hydralisk";"Larva";169;2
"Unit";"Hydralisk";"Larva";169;2
"Unit";"Hydralisk";"Larva";169;2
"Unit";"Hydralisk";"Larva";169;2
"Unit";"Hydralisk";"Larva";169;2
"Unit";"Hydralisk";"Larva";169;2
"Unit";"Queen";"Hatchery";179;2
"Unit";"Hydralisk";"Larva";191;2
"Unit";"Hydralisk";"Larva";193;2
"Unit";"Hydralisk";"Larva";193;2
"Unit";"Baneling";"Zergling";201;0
"Unit";"Baneling";"Zergling";201;0
"Unit";"Overlord";"Larva";201;0
"Upgrade";"ZergMeleeWeaponsLevel1";"EvolutionChamber";153;0
"Upgrade";"EvolveGroovedSpines";"HydraliskDen";179;0
"Building";"Hatchery";NA;179;0
"Building";"CreepTumor";NA;209;0
"Building";"CreepTumorQueen";NA;209;0
"Unit";"Hydralisk";"Larva";209;2
"Unit";"Hydralisk";"Larva";209;2
"Unit";"Hydralisk";"Larva";209;2
"Unit";"Hydralisk";"Larva";209;2
"Unit";"Hydralisk";"Larva";209;2
"Unit";"Hydralisk";"Larva";209;2
"Unit";"Hydralisk";"Larva";209;2
"Unit";"Hydralisk";"Larva";209;2
"Unit";"Hydralisk";"Larva";209;2
"Building";"InfestationPit";NA;209;0
"Building";"CreepTumorQueen";NA;209;0
"Building";"CreepTumorQueen";NA;209;0
"Building";"CreepTumor";NA;209;0
"Building";"CreepTumor";NA;209;0
"Building";"CreepTumor";NA;209;0
"Unit";"Baneling";"Zergling";209;0
"Unit";"Baneling";"Zergling";209;0
"Unit";"Baneling";"Zergling";209;0
"Unit";"Baneling";"Zergling";209;0
"Unit";"Baneling";"Zergling";209;0
"Unit";"Baneling";"Zergling";209;0
"Unit";"Baneling";"Zergling";209;0
"Unit";"Baneling";"Zergling";209;0
"Unit";"Queen";"Hatchery";209;2
"Upgrade";"ZergGroundArmorsLevel1";"EvolutionChamber";201;0
"Unit";"Zergling";"Larva";239;1
"Unit";"Zergling";"Larva";239;1
"Unit";"Zergling";"Larva";239;1
"Unit";"Zergling";"Larva";239;1
"Unit";"Zergling";"Larva";239;1
"Unit";"Zergling";"Larva";239;1
"Unit";"Zergling";"Larva";239;1
"Unit";"Zergling";"Larva";239;1
"Unit";"Zergling";"Larva";239;1
"Unit";"Zergling";"Larva";239;1
"Unit";"Zergling";"Larva";239;1
"Unit";"Zergling";"Larva";239;1
"Unit";"Zergling";"Larva";239;1
"Unit";"Zergling";"Larva";239;1
"Unit";"Zergling";"Larva";239;1
"Unit";"Zergling";"Larva";239;1
"Unit";"Zergling";"Larva";239;1
"Unit";"Zergling";"Larva";239;1
"Unit";"Zergling";"Larva";239;1
"Unit";"Zergling";"Larva";239;1
"Unit";"Zergling";"Larva";239;1
"Unit";"Zergling";"Larva";239;1
"Unit";"Zergling";"Larva";239;1
"Unit";"Zergling";"Larva";239;1
"Unit";"Zergling";"Larva";239;1
"Unit";"Zergling";"Larva";239;1
"Unit";"Zergling";"Larva";239;1
"Unit";"Zergling";"Larva";239;1
"Unit";"Zergling";"Larva";239;1
"Unit";"Zergling";"Larva";239;1
"Unit";"Zergling";"Larva";239;1
"Unit";"Zergling";"Larva";239;1
"Unit";"Zergling";"Larva";239;1
"Unit";"Zergling";"Larva";239;1
"Unit";"Baneling";"Zergling";239;0
"Unit";"Zergling";"Larva";239;1
"Unit";"Zergling";"Larva";239;1
"Unit";"Baneling";"Zergling";239;0
"Unit";"Baneling";"Zergling";239;0
"Unit";"Baneling";"Zergling";239;0
"Unit";"Baneling";"Zergling";239;0
"Unit";"Baneling";"Zergling";239;0
"Building";"CreepTumorQueen";NA;239;0
"Building";"CreepTumor";NA;239;0
"Building";"CreepTumorQueen";NA;239;0
"Unit";"Zergling";"Larva";239;1
"Unit";"Zergling";"Larva";239;1
"Building";"CreepTumorQueen";NA;239;0
"Building";"CreepTumorQueen";NA;259;0
"Building";"Extractor";NA;239;0
"Building";"Extractor";NA;239;0
"Building";"CreepTumorQueen";NA;277;0
"Unit";"Overlord";"Larva";277;0
"Building";"Hatchery";NA;239;0
"Unit";"Zergling";"Larva";294;1
"Unit";"Zergling";"Larva";294;1
"Unit";"Zergling";"Larva";294;1
"Unit";"Zergling";"Larva";294;1
"Unit";"Zergling";"Larva";294;1
"Unit";"Zergling";"Larva";294;1
"Unit";"Zergling";"Larva";294;1
"Unit";"Zergling";"Larva";294;1
"Unit";"Hydralisk";"Larva";294;2
"Unit";"Hydralisk";"Larva";294;2
"Unit";"Hydralisk";"Larva";294;2
"Unit";"Hydralisk";"Larva";294;2
"Unit";"Hydralisk";"Larva";294;2
"Unit";"Hydralisk";"Larva";294;2
"Unit";"Hydralisk";"Larva";294;2
"Unit";"Hydralisk";"Larva";294;2
"Unit";"Hydralisk";"Larva";294;2
"Unit";"Hydralisk";"Larva";294;2
"Unit";"Hydralisk";"Larva";294;2
"Building";"CreepTumor";NA;324;0
"Building";"CreepTumor";NA;324;0
"Unit";"Viper";"Larva";294;3
"Unit";"Viper";"Larva";294;3
"Unit";"Baneling";"Zergling";325;0
"Unit";"Baneling";"Zergling";325;0
"Unit";"Baneling";"Zergling";325;0
"Unit";"Baneling";"Zergling";325;0
"Unit";"Baneling";"Zergling";325;0
"Unit";"Baneling";"Zergling";325;0
"Unit";"Baneling";"Zergling";325;0
"Unit";"Baneling";"Zergling";325;0
"Unit";"Baneling";"Zergling";325;0
"Unit";"Baneling";"Zergling";325;0
"Unit";"Baneling";"Zergling";325;0
"Unit";"Baneling";"Zergling";325;0
"Unit";"Baneling";"Zergling";325;0
"Unit";"Baneling";"Zergling";325;0
"Unit";"Baneling";"Zergling";325;0
"Unit";"Zergling";"Larva";324;1
"Unit";"Zergling";"Larva";324;1
"Unit";"Zergling";"Larva";324;1
"Unit";"Zergling";"Larva";324;1
"Unit";"Zergling";"Larva";324;1
"Unit";"Zergling";"Larva";324;1
"Unit";"Zergling";"Larva";324;1
"Unit";"Zergling";"Larva";324;1
"Unit";"Zergling";"Larva";324;1
"Unit";"Zergling";"Larva";324;1
"Unit";"Zergling";"Larva";324;1
"Unit";"Zergling";"Larva";324;1
"Unit";"Zergling";"Larva";324;1
"Unit";"Zergling";"Larva";324;1
"Unit";"Zergling";"Larva";324;1
"Unit";"Zergling";"Larva";324;1
"Unit";"Zergling";"Larva";324;1
"Unit";"Zergling";"Larva";324;1
"Unit";"Zergling";"Larva";324;1
"Unit";"Zergling";"Larva";324;1
"Unit";"Zergling";"Larva";324;1
"Unit";"Zergling";"Larva";324;1
"Upgrade";"EvolveMuscularAugments";"HydraliskDen";294;0
"Building";"UltraliskCavern";NA;294;0
"Unit";"Zergling";"Larva";331;1
"Unit";"Zergling";"Larva";331;1
"Unit";"Zergling";"Larva";331;1
"Unit";"Zergling";"Larva";331;1
"Unit";"Zergling";"Larva";331;1
"Unit";"Zergling";"Larva";331;1
"Unit";"Zergling";"Larva";331;1
"Unit";"Zergling";"Larva";331;1
"Unit";"Zergling";"Larva";331;1
"Unit";"Zergling";"Larva";331;1
"Unit";"Zergling";"Larva";331;1
"Unit";"Zergling";"Larva";331;1
"Unit";"Zergling";"Larva";331;1
"Unit";"Zergling";"Larva";331;1
"Unit";"Zergling";"Larva";331;1
"Unit";"Zergling";"Larva";331;1
"Unit";"Zergling";"Larva";331;1
"Unit";"Zergling";"Larva";331;1
"Unit";"Zergling";"Larva";331;1
"Unit";"Zergling";"Larva";331;1
"Unit";"Zergling";"Larva";331;1
"Unit";"Zergling";"Larva";331;1
"Upgrade";"ZergMeleeWeaponsLevel2";"EvolutionChamber";294;0
"Building";"CreepTumor";NA;375;0
"Building";"CreepTumor";NA;375;0
"Building";"CreepTumor";NA;375;0
"Upgrade";"ZergGroundArmorsLevel2";"EvolutionChamber";294;0
"Unit";"Ultralisk";"Larva";353;6
"Unit";"Ultralisk";"Larva";353;6
"Unit";"Ultralisk";"Larva";353;6
"Unit";"Queen";"Hatchery";375;2
"Unit";"Baneling";"Zergling";375;0
"Unit";"Baneling";"Zergling";375;0
"Unit";"Baneling";"Zergling";375;0
"Unit";"Baneling";"Zergling";375;0
"Unit";"Baneling";"Zergling";375;0
"Unit";"Baneling";"Zergling";375;0
"Unit";"Queen";"Hatchery";375;2
