"type";"unit_name";"on_building";"total_supply";"supply"
"Unit";"Overlord";"Larva";12;0
"Building";"Extractor";NA;17;0
"Building";"SpawningPool";NA;19;0
"Building";"Hatchery";NA;17;0
"Unit";"Overlord";"Larva";23;0
"Unit";"Zergling";"Larva";23;1
"Unit";"Zergling";"Larva";23;1
"Unit";"Zergling";"Larva";23;1
"Unit";"Zergling";"Larva";23;1
"Unit";"Queen";"Hatchery";23;2
"Unit";"Queen";"Hatchery";23;2
"Unit";"Overlord";"Larva";35;0
"Unit";"Overlord";"Larva";39;0
"Unit";"Queen";"Hatchery";37;2
"Unit";"Queen";"Hatchery";38;2
"Building";"CreepTumorQueen";NA;51;0
"Building";"Hatchery";NA;33;0
"Building";"CreepTumorQueen";NA;52;0
"Building";"Extractor";NA;52;0
"Building";"Extractor";NA;54;0
"Building";"Extractor";NA;54;0
"Unit";"Overlord";"Larva";54;0
"Unit";"Queen";"Hatchery";54;2
"Unit";"Zergling";"Larva";62;1
"Unit";"Zergling";"Larva";62;1
"Unit";"Zergling";"Larva";62;1
"Unit";"Zergling";"Larva";62;1
"Unit";"Overlord";"Larva";65;0
"Unit";"Overlord";"Larva";65;0
"Building";"CreepTumorQueen";NA;67;0
"Building";"CreepTumorQueen";NA;71;0
"Unit";"Zergling";"Larva";65;1
"Unit";"Zergling";"Larva";65;1
"Unit";"Zergling";"Larva";65;1
"Unit";"Zergling";"Larva";65;1
"Building";"CreepTumor";NA;71;0
"Unit";"Zergling";"Larva";65;1
"Unit";"Zergling";"Larva";65;1
"Building";"EvolutionChamber";NA;65;0
"Building";"EvolutionChamber";NA;65;0
"Unit";"Zergling";"Larva";71;1
"Unit";"Zergling";"Larva";71;1
"Unit";"Zergling";"Larva";72;1
"Unit";"Zergling";"Larva";72;1
"Unit";"Overlord";"Larva";71;0
"Unit";"Zergling";"Larva";72;1
"Unit";"Zergling";"Larva";72;1
"Building";"CreepTumor";NA;72;0
"Unit";"Zergling";"Larva";72;1
"Unit";"Zergling";"Larva";72;1
"Unit";"Zergling";"Larva";72;1
"Unit";"Zergling";"Larva";72;1
"Unit";"Zergling";"Larva";72;1
"Unit";"Zergling";"Larva";72;1
"Building";"CreepTumor";NA;95;0
"Building";"CreepTumor";NA;95;0
"Unit";"Zergling";"Larva";95;1
"Unit";"Zergling";"Larva";95;1
"Unit";"Zergling";"Larva";95;1
"Unit";"Zergling";"Larva";95;1
"Building";"CreepTumorQueen";NA;95;0
"Building";"CreepTumor";NA;95;0
"Unit";"Zergling";"Larva";95;1
"Unit";"Zergling";"Larva";95;1
"Building";"CreepTumor";NA;96;0
"Unit";"Zergling";"Larva";102;1
"Unit";"Zergling";"Larva";102;1
"Unit";"Zergling";"Larva";102;1
"Unit";"Zergling";"Larva";102;1
"Unit";"Zergling";"Larva";102;1
"Unit";"Zergling";"Larva";102;1
"Unit";"Zergling";"Larva";102;1
"Unit";"Zergling";"Larva";102;1
"Unit";"Zergling";"Larva";102;1
"Unit";"Zergling";"Larva";102;1
"Unit";"Zergling";"Larva";102;1
"Unit";"Zergling";"Larva";102;1
"Building";"BanelingNest";NA;90;0
"Building";"CreepTumor";NA;104;0
"Building";"HydraliskDen";NA;102;0
"Building";"CreepTumor";NA;120;0
"Building";"CreepTumor";NA;120;0
"Building";"CreepTumor";NA;121;0
"Building";"CreepTumorQueen";NA;129;0
"Building";"CreepTumorQueen";NA;129;0
"Building";"CreepTumor";NA;129;0
"Building";"Extractor";NA;129;0
"Building";"Extractor";NA;129;0
"Unit";"Zergling";"Larva";129;1
"Unit";"Zergling";"Larva";129;1
"Unit";"Zergling";"Larva";129;1
"Unit";"Zergling";"Larva";129;1
"Upgrade";"ZergMeleeWeaponsLevel1";"EvolutionChamber";102;0
"Upgrade";"ZergGroundArmorsLevel1";"EvolutionChamber";102;0
"Unit";"Overlord";"Larva";134;0
"Unit";"Overlord";"Larva";134;0
"Unit";"Overlord";"Larva";134;0
"Unit";"Overlord";"Larva";134;0
"Building";"SporeCrawler";NA;129;0
"Unit";"Overlord";"Larva";139;0
"Unit";"Overlord";"Larva";139;0
"Unit";"Overlord";"Larva";139;0
"Unit";"Overlord";"Larva";139;0
"Unit";"Baneling";"Zergling";139;0
"Building";"Hatchery";NA;121;0
"Unit";"Baneling";"Zergling";139;0
"Unit";"Baneling";"Zergling";139;0
"Unit";"Baneling";"Zergling";139;0
"Unit";"Baneling";"Zergling";139;0
"Unit";"Baneling";"Zergling";139;0
"Unit";"Baneling";"Zergling";139;0
"Unit";"Baneling";"Zergling";139;0
"Unit";"Baneling";"Zergling";139;0
"Unit";"Baneling";"Zergling";139;0
"Unit";"Baneling";"Zergling";139;0
"Building";"CreepTumor";NA;140;0
"Building";"CreepTumor";NA;140;0
"Building";"CreepTumor";NA;140;0
"Building";"CreepTumor";NA;140;0
"Unit";"Hydralisk";"Larva";139;2
"Building";"CreepTumor";NA;140;0
"Unit";"Hydralisk";"Larva";139;2
"Unit";"Hydralisk";"Larva";139;2
"Unit";"Hydralisk";"Larva";139;2
"Unit";"Hydralisk";"Larva";139;2
"Unit";"Hydralisk";"Larva";139;2
"Upgrade";"EvolveGroovedSpines";"HydraliskDen";134;0
"Unit";"Zergling";"Larva";140;1
"Unit";"Zergling";"Larva";140;1
"Unit";"Zergling";"Larva";140;1
"Unit";"Zergling";"Larva";140;1
"Unit";"Zergling";"Larva";140;1
"Unit";"Zergling";"Larva";140;1
"Unit";"Zergling";"Larva";140;1
"Unit";"Zergling";"Larva";140;1
"Unit";"Zergling";"Larva";140;1
"Unit";"Zergling";"Larva";140;1
"Unit";"Hydralisk";"Larva";140;2
"Unit";"Hydralisk";"Larva";140;2
"Unit";"Hydralisk";"Larva";140;2
"Unit";"Hydralisk";"Larva";140;2
"Unit";"Zergling";"Larva";152;1
"Unit";"Zergling";"Larva";152;1
"Unit";"Zergling";"Larva";152;1
"Unit";"Zergling";"Larva";152;1
"Unit";"Zergling";"Larva";152;1
"Unit";"Zergling";"Larva";152;1
"Unit";"Zergling";"Larva";152;1
"Unit";"Zergling";"Larva";152;1
"Unit";"Zergling";"Larva";152;1
"Unit";"Zergling";"Larva";152;1
"Unit";"Zergling";"Larva";152;1
"Unit";"Zergling";"Larva";152;1
"Building";"CreepTumor";NA;170;0
"Building";"CreepTumor";NA;180;0
"Building";"CreepTumor";NA;182;0
"Unit";"Queen";"Hatchery";148;2
"Building";"CreepTumor";NA;182;0
"Building";"CreepTumor";NA;182;0
"Building";"CreepTumorQueen";NA;182;0
"Building";"CreepTumorQueen";NA;182;0
"Building";"CreepTumorQueen";NA;182;0
"Unit";"Baneling";"Zergling";182;0
"Unit";"Baneling";"Zergling";182;0
"Unit";"Baneling";"Zergling";182;0
"Unit";"Baneling";"Zergling";182;0
"Unit";"Baneling";"Zergling";182;0
"Unit";"Baneling";"Zergling";182;0
"Unit";"Baneling";"Zergling";182;0
"Unit";"Baneling";"Zergling";182;0
"Unit";"Baneling";"Zergling";182;0
"Unit";"Baneling";"Zergling";182;0
"Unit";"Baneling";"Zergling";182;0
"Unit";"Baneling";"Zergling";182;0
"Unit";"Baneling";"Zergling";182;0
"Unit";"Baneling";"Zergling";182;0
"Unit";"Baneling";"Zergling";182;0
"Unit";"Baneling";"Zergling";182;0
"Unit";"Baneling";"Zergling";182;0
"Unit";"Baneling";"Zergling";182;0
"Unit";"Baneling";"Zergling";182;0
"Unit";"Baneling";"Zergling";182;0
"Unit";"Zergling";"Larva";182;1
"Unit";"Zergling";"Larva";182;1
"Unit";"Zergling";"Larva";182;1
"Unit";"Zergling";"Larva";182;1
"Unit";"Zergling";"Larva";182;1
"Unit";"Zergling";"Larva";182;1
"Unit";"Zergling";"Larva";182;1
"Unit";"Zergling";"Larva";182;1
"Unit";"Zergling";"Larva";182;1
"Unit";"Zergling";"Larva";182;1
"Unit";"Zergling";"Larva";182;1
"Unit";"Zergling";"Larva";182;1
"Unit";"Zergling";"Larva";182;1
"Unit";"Zergling";"Larva";182;1
"Unit";"Zergling";"Larva";182;1
"Unit";"Zergling";"Larva";182;1
"Unit";"Zergling";"Larva";182;1
"Unit";"Zergling";"Larva";182;1
"Unit";"Zergling";"Larva";182;1
"Unit";"Zergling";"Larva";182;1
"Unit";"Zergling";"Larva";182;1
"Unit";"Zergling";"Larva";182;1
"Unit";"Zergling";"Larva";182;1
"Unit";"Zergling";"Larva";182;1
"Unit";"Zergling";"Larva";182;1
"Unit";"Zergling";"Larva";182;1
"Unit";"Zergling";"Larva";210;1
"Unit";"Zergling";"Larva";210;1
"Unit";"Zergling";"Larva";210;1
"Unit";"Zergling";"Larva";210;1
"Unit";"Zergling";"Larva";210;1
"Unit";"Zergling";"Larva";210;1
"Unit";"Zergling";"Larva";210;1
"Unit";"Zergling";"Larva";210;1
"Unit";"Zergling";"Larva";210;1
"Unit";"Zergling";"Larva";210;1
"Upgrade";"EvolveMuscularAugments";"HydraliskDen";182;0
"Unit";"Hydralisk";"Larva";210;2
"Unit";"Hydralisk";"Larva";210;2
"Unit";"Hydralisk";"Larva";210;2
"Unit";"Hydralisk";"Larva";210;2
"Unit";"Hydralisk";"Larva";210;2
"Unit";"Overlord";"Larva";210;0
"Building";"CreepTumor";NA;210;0
"Unit";"Overlord";"Larva";210;0
"Unit";"Overlord";"Larva";210;0
"Unit";"Zergling";"Larva";210;1
"Unit";"Zergling";"Larva";210;1
"Unit";"Zergling";"Larva";210;1
"Unit";"Zergling";"Larva";210;1
"Unit";"Zergling";"Larva";210;1
"Unit";"Zergling";"Larva";210;1
"Building";"CreepTumor";NA;220;0
"Building";"CreepTumor";NA;226;0
"Building";"CreepTumor";NA;230;0
"Unit";"Zergling";"Larva";230;1
"Unit";"Zergling";"Larva";230;1
"Unit";"Overlord";"Larva";230;0
"Unit";"Overlord";"Larva";230;0
"Unit";"Zergling";"Larva";230;1
"Unit";"Zergling";"Larva";230;1
"Unit";"Zergling";"Larva";230;1
"Unit";"Zergling";"Larva";230;1
"Unit";"Zergling";"Larva";230;1
"Unit";"Zergling";"Larva";230;1
"Unit";"Zergling";"Larva";230;1
"Unit";"Zergling";"Larva";230;1
"Unit";"Zergling";"Larva";230;1
"Unit";"Zergling";"Larva";230;1
"Unit";"Zergling";"Larva";232;1
"Unit";"Zergling";"Larva";232;1
"Unit";"Zergling";"Larva";232;1
"Unit";"Zergling";"Larva";232;1
"Unit";"Zergling";"Larva";232;1
"Unit";"Zergling";"Larva";232;1
"Unit";"Zergling";"Larva";232;1
"Unit";"Zergling";"Larva";232;1
"Unit";"Zergling";"Larva";232;1
"Unit";"Zergling";"Larva";232;1
"Unit";"Zergling";"Larva";234;1
"Unit";"Zergling";"Larva";234;1
"Building";"InfestationPit";NA;210;0
"Upgrade";"ZergMeleeWeaponsLevel2";"EvolutionChamber";162;0
"Upgrade";"ZergGroundArmorsLevel2";"EvolutionChamber";162;0
"Unit";"Zergling";"Larva";260;1
"Unit";"Zergling";"Larva";260;1
"Unit";"Zergling";"Larva";260;1
"Unit";"Zergling";"Larva";260;1
"Unit";"Zergling";"Larva";260;1
"Unit";"Zergling";"Larva";260;1
"Unit";"Zergling";"Larva";260;1
"Unit";"Zergling";"Larva";260;1
"Unit";"Zergling";"Larva";260;1
"Unit";"Zergling";"Larva";260;1
"Unit";"Zergling";"Larva";260;1
"Unit";"Zergling";"Larva";260;1
"Unit";"Zergling";"Larva";260;1
"Unit";"Zergling";"Larva";260;1
"Unit";"Zergling";"Larva";260;1
"Unit";"Zergling";"Larva";260;1
"Unit";"Zergling";"Larva";260;1
"Unit";"Zergling";"Larva";260;1
"Unit";"Zergling";"Larva";260;1
"Unit";"Zergling";"Larva";260;1
"Unit";"Zergling";"Larva";260;1
"Unit";"Zergling";"Larva";260;1
"Unit";"Zergling";"Larva";260;1
"Unit";"Zergling";"Larva";260;1
"Unit";"Zergling";"Larva";260;1
"Unit";"Zergling";"Larva";260;1
