"type";"unit_name";"on_building";"total_supply";"supply"
"Unit";"Overlord";"Larva";12;0
"Building";"Extractor";NA;18;0
"Unit";"Overlord";"Larva";21;0
"Building";"SpawningPool";NA;19;0
"Building";"Hatchery";NA;17;0
"Unit";"Zergling";"Larva";23;1
"Unit";"Zergling";"Larva";23;1
"Unit";"Zergling";"Larva";23;1
"Unit";"Zergling";"Larva";23;1
"Unit";"Queen";"Hatchery";22;2
"Unit";"Queen";"Hatchery";23;2
"Unit";"Overlord";"Larva";36;0
"Building";"CreepTumorQueen";NA;39;0
"Unit";"Queen";"Hatchery";36;2
"Unit";"Overlord";"Larva";40;0
"Building";"Hatchery";NA;36;0
"Unit";"Overlord";"Larva";49;0
"Unit";"Zergling";"Larva";50;1
"Unit";"Zergling";"Larva";50;1
"Unit";"Zergling";"Larva";50;1
"Unit";"Zergling";"Larva";50;1
"Unit";"Zergling";"Larva";50;1
"Unit";"Zergling";"Larva";50;1
"Unit";"Zergling";"Larva";50;1
"Unit";"Zergling";"Larva";50;1
"Building";"CreepTumorQueen";NA;50;0
"Unit";"Zergling";"Larva";50;1
"Unit";"Zergling";"Larva";50;1
"Building";"CreepTumor";NA;50;0
"Unit";"Overlord";"Larva";50;0
"Building";"CreepTumorQueen";NA;58;0
"Unit";"Zergling";"Larva";50;1
"Unit";"Zergling";"Larva";50;1
"Unit";"Queen";"Hatchery";49;2
"Unit";"Overlord";"Larva";60;0
"Unit";"Queen";"Hatchery";52;2
"Unit";"Overlord";"Larva";64;0
"Building";"SporeCrawler";NA;71;0
"Building";"Extractor";NA;71;0
"Building";"Extractor";NA;71;0
"Building";"SporeCrawler";NA;71;0
"Building";"CreepTumorQueen";NA;79;0
"Building";"CreepTumorQueen";NA;79;0
"Unit";"Zergling";"Larva";79;1
"Unit";"Zergling";"Larva";79;1
"Unit";"Zergling";"Larva";79;1
"Unit";"Zergling";"Larva";79;1
"Unit";"Zergling";"Larva";79;1
"Unit";"Zergling";"Larva";79;1
"Unit";"Zergling";"Larva";79;1
"Unit";"Zergling";"Larva";79;1
"Unit";"Zergling";"Larva";79;1
"Unit";"Zergling";"Larva";79;1
"Unit";"Zergling";"Larva";79;1
"Unit";"Zergling";"Larva";79;1
"Unit";"Zergling";"Larva";79;1
"Unit";"Zergling";"Larva";79;1
"Unit";"Zergling";"Larva";79;1
"Unit";"Zergling";"Larva";79;1
"Unit";"Zergling";"Larva";79;1
"Unit";"Zergling";"Larva";79;1
"Unit";"Zergling";"Larva";79;1
"Unit";"Zergling";"Larva";79;1
"Building";"EvolutionChamber";NA;79;0
"Building";"CreepTumor";NA;87;0
"Building";"CreepTumor";NA;87;0
"Building";"CreepTumor";NA;87;0
"Building";"EvolutionChamber";NA;79;0
"Building";"CreepTumorQueen";NA;87;0
"Building";"CreepTumorQueen";NA;87;0
"Building";"BanelingNest";NA;73;0
"Unit";"Overlord";"Larva";89;0
"Unit";"Overlord";"Larva";89;0
"Unit";"Overlord";"Larva";89;0
"Unit";"Zergling";"Larva";101;1
"Unit";"Zergling";"Larva";101;1
"Unit";"Zergling";"Larva";101;1
"Unit";"Zergling";"Larva";101;1
"Building";"CreepTumor";NA;101;0
"Unit";"Zergling";"Larva";101;1
"Unit";"Zergling";"Larva";101;1
"Unit";"Zergling";"Larva";101;1
"Unit";"Zergling";"Larva";101;1
"Building";"CreepTumor";NA;105;0
"Unit";"Zergling";"Larva";101;1
"Unit";"Zergling";"Larva";101;1
"Building";"CreepTumor";NA;105;0
"Building";"CreepTumor";NA;105;0
"Building";"CreepTumor";NA;105;0
"Building";"CreepTumor";NA;105;0
"Building";"CreepTumorQueen";NA;105;0
"Building";"CreepTumorQueen";NA;105;0
"Unit";"Zergling";"Larva";105;1
"Unit";"Zergling";"Larva";105;1
"Unit";"Zergling";"Larva";105;1
"Unit";"Zergling";"Larva";105;1
"Unit";"Zergling";"Larva";105;1
"Unit";"Zergling";"Larva";105;1
"Unit";"Zergling";"Larva";105;1
"Unit";"Zergling";"Larva";105;1
"Unit";"Zergling";"Larva";105;1
"Unit";"Zergling";"Larva";105;1
"Unit";"Zergling";"Larva";105;1
"Unit";"Zergling";"Larva";105;1
"Unit";"Zergling";"Larva";105;1
"Unit";"Zergling";"Larva";105;1
"Unit";"Zergling";"Larva";105;1
"Unit";"Zergling";"Larva";105;1
"Unit";"Baneling";"Zergling";111;0
"Unit";"Baneling";"Zergling";111;0
"Unit";"Baneling";"Zergling";111;0
"Unit";"Baneling";"Zergling";111;0
"Unit";"Baneling";"Zergling";111;0
"Unit";"Baneling";"Zergling";111;0
"Unit";"Baneling";"Zergling";111;0
"Unit";"Baneling";"Zergling";111;0
"Unit";"Zergling";"Larva";111;1
"Unit";"Zergling";"Larva";111;1
"Unit";"Zergling";"Larva";111;1
"Unit";"Zergling";"Larva";111;1
"Unit";"Zergling";"Larva";111;1
"Unit";"Zergling";"Larva";111;1
"Unit";"Zergling";"Larva";111;1
"Unit";"Zergling";"Larva";111;1
"Unit";"Zergling";"Larva";111;1
"Unit";"Zergling";"Larva";111;1
"Unit";"Zergling";"Larva";111;1
"Unit";"Zergling";"Larva";111;1
"Unit";"Overlord";"Larva";127;0
"Unit";"Overlord";"Larva";127;0
"Building";"CreepTumor";NA;127;0
"Building";"CreepTumor";NA;139;0
"Building";"CreepTumor";NA;139;0
"Building";"Extractor";NA;139;0
"Building";"CreepTumorQueen";NA;143;0
"Building";"CreepTumor";NA;143;0
"Building";"CreepTumor";NA;143;0
"Building";"CreepTumorQueen";NA;143;0
"Building";"CreepTumorQueen";NA;143;0
"Unit";"Overlord";"Larva";147;0
"Building";"CreepTumor";NA;147;0
"Unit";"Overlord";"Larva";147;0
"Unit";"Overlord";"Larva";147;0
"Unit";"Overlord";"Larva";147;0
"Building";"CreepTumor";NA;147;0
"Building";"CreepTumor";NA;147;0
"Building";"CreepTumor";NA;147;0
"Unit";"Zergling";"Larva";147;1
"Unit";"Zergling";"Larva";147;1
"Unit";"Zergling";"Larva";147;1
"Unit";"Zergling";"Larva";147;1
"Unit";"Zergling";"Larva";147;1
"Unit";"Zergling";"Larva";147;1
"Unit";"Zergling";"Larva";147;1
"Unit";"Zergling";"Larva";147;1
"Unit";"Zergling";"Larva";147;1
"Unit";"Zergling";"Larva";147;1
"Unit";"Zergling";"Larva";147;1
"Unit";"Zergling";"Larva";147;1
"Unit";"Zergling";"Larva";147;1
"Unit";"Zergling";"Larva";147;1
"Unit";"Zergling";"Larva";147;1
"Unit";"Zergling";"Larva";147;1
"Unit";"Zergling";"Larva";147;1
"Unit";"Zergling";"Larva";147;1
"Unit";"Zergling";"Larva";147;1
"Unit";"Zergling";"Larva";147;1
"Unit";"Baneling";"Zergling";147;0
"Unit";"Baneling";"Zergling";147;0
"Unit";"Baneling";"Zergling";147;0
"Unit";"Baneling";"Zergling";147;0
"Unit";"Baneling";"Zergling";147;0
"Unit";"Baneling";"Zergling";147;0
"Unit";"Baneling";"Zergling";147;0
"Unit";"Baneling";"Zergling";147;0
"Unit";"Baneling";"Zergling";147;0
"Unit";"Baneling";"Zergling";147;0
"Unit";"Baneling";"Zergling";147;0
"Unit";"Baneling";"Zergling";147;0
"Unit";"Baneling";"Zergling";147;0
"Unit";"Baneling";"Zergling";147;0
"Unit";"Baneling";"Zergling";147;0
"Upgrade";"ZergMeleeWeaponsLevel1";"EvolutionChamber";111;0
"Upgrade";"ZergGroundArmorsLevel1";"EvolutionChamber";113;0
"Unit";"Zergling";"Larva";167;1
"Unit";"Zergling";"Larva";167;1
"Unit";"Zergling";"Larva";167;1
"Unit";"Zergling";"Larva";167;1
"Unit";"Zergling";"Larva";167;1
"Unit";"Zergling";"Larva";167;1
"Unit";"Zergling";"Larva";167;1
"Unit";"Zergling";"Larva";167;1
"Unit";"Zergling";"Larva";167;1
"Unit";"Zergling";"Larva";167;1
"Unit";"Zergling";"Larva";167;1
"Unit";"Zergling";"Larva";167;1
"Unit";"Zergling";"Larva";167;1
"Unit";"Zergling";"Larva";167;1
"Unit";"Zergling";"Larva";167;1
"Unit";"Zergling";"Larva";167;1
"Unit";"Zergling";"Larva";167;1
"Unit";"Zergling";"Larva";167;1
"Unit";"Zergling";"Larva";167;1
"Unit";"Zergling";"Larva";167;1
"Unit";"Zergling";"Larva";167;1
"Unit";"Zergling";"Larva";167;1
"Unit";"Zergling";"Larva";167;1
"Unit";"Zergling";"Larva";167;1
"Unit";"Zergling";"Larva";167;1
"Unit";"Zergling";"Larva";167;1
"Building";"Extractor";NA;200;0
"Building";"Extractor";NA;202;0
"Unit";"Zergling";"Larva";211;1
"Unit";"Zergling";"Larva";211;1
"Unit";"Zergling";"Larva";211;1
"Unit";"Zergling";"Larva";211;1
"Unit";"Zergling";"Larva";211;1
"Unit";"Zergling";"Larva";211;1
"Unit";"Zergling";"Larva";211;1
"Unit";"Zergling";"Larva";211;1
"Unit";"Zergling";"Larva";211;1
"Unit";"Zergling";"Larva";211;1
"Unit";"Zergling";"Larva";211;1
"Unit";"Zergling";"Larva";211;1
"Unit";"Zergling";"Larva";211;1
"Unit";"Zergling";"Larva";211;1
"Unit";"Zergling";"Larva";211;1
"Unit";"Zergling";"Larva";211;1
"Unit";"Zergling";"Larva";211;1
"Unit";"Zergling";"Larva";211;1
"Unit";"Zergling";"Larva";211;1
"Unit";"Zergling";"Larva";211;1
"Unit";"Zergling";"Larva";211;1
"Unit";"Zergling";"Larva";211;1
"Unit";"Zergling";"Larva";211;1
"Unit";"Zergling";"Larva";211;1
"Building";"SporeCrawler";NA;211;0
"Building";"CreepTumor";NA;217;0
"Building";"CreepTumor";NA;217;0
"Building";"CreepTumor";NA;217;0
"Building";"CreepTumor";NA;217;0
"Building";"CreepTumor";NA;235;0
"Building";"CreepTumor";NA;235;0
"Building";"CreepTumor";NA;235;0
"Building";"CreepTumor";NA;235;0
"Building";"CreepTumor";NA;235;0
"Building";"CreepTumor";NA;235;0
"Building";"Spire";NA;200;0
"Building";"Hatchery";NA;201;0
"Building";"CreepTumorQueen";NA;235;0
"Building";"CreepTumorQueen";NA;235;0
"Building";"CreepTumorQueen";NA;235;0
"Building";"CreepTumorQueen";NA;235;0
"Unit";"Baneling";"Zergling";235;0
"Unit";"Baneling";"Zergling";235;0
"Unit";"Baneling";"Zergling";235;0
"Unit";"Baneling";"Zergling";235;0
"Unit";"Baneling";"Zergling";235;0
"Unit";"Baneling";"Zergling";235;0
"Unit";"Baneling";"Zergling";235;0
"Unit";"Baneling";"Zergling";235;0
"Unit";"Baneling";"Zergling";235;0
"Unit";"Baneling";"Zergling";235;0
"Unit";"Baneling";"Zergling";235;0
"Unit";"Baneling";"Zergling";235;0
"Upgrade";"Burrow";"Hatchery";211;0
"Building";"CreepTumorQueen";NA;235;0
"Building";"CreepTumorQueen";NA;235;0
"Building";"CreepTumorQueen";NA;235;0
"Building";"CreepTumorQueen";NA;235;0
"Building";"CreepTumorQueen";NA;235;0
"Upgrade";"ZergMeleeWeaponsLevel2";"EvolutionChamber";201;0
"Upgrade";"ZergGroundArmorsLevel2";"EvolutionChamber";201;0
"Building";"InfestationPit";NA;235;0
"Unit";"Overlord";"Larva";235;0
"Unit";"Overlord";"Larva";235;0
"Unit";"Overlord";"Larva";235;0
"Unit";"Overlord";"Larva";235;0
"Unit";"Overlord";"Larva";235;0
"Unit";"Queen";"Hatchery";235;2
"Unit";"Mutalisk";"Larva";241;2
"Unit";"Mutalisk";"Larva";241;2
"Unit";"Mutalisk";"Larva";241;2
"Unit";"Mutalisk";"Larva";241;2
"Unit";"Mutalisk";"Larva";241;2
"Unit";"Mutalisk";"Larva";241;2
"Unit";"Mutalisk";"Larva";241;2
"Unit";"Mutalisk";"Larva";241;2
"Unit";"Mutalisk";"Larva";241;2
"Unit";"Mutalisk";"Larva";241;2
"Building";"CreepTumorQueen";NA;241;0
"Building";"CreepTumor";NA;241;0
"Building";"CreepTumorQueen";NA;241;0
"Building";"CreepTumor";NA;241;0
"Unit";"Zergling";"Larva";241;1
"Unit";"Zergling";"Larva";241;1
"Building";"CreepTumor";NA;241;0
"Unit";"Zergling";"Larva";241;1
"Unit";"Zergling";"Larva";241;1
"Unit";"Zergling";"Larva";241;1
"Unit";"Zergling";"Larva";241;1
"Unit";"Zergling";"Larva";241;1
"Unit";"Zergling";"Larva";241;1
"Unit";"Zergling";"Larva";241;1
"Unit";"Zergling";"Larva";241;1
"Unit";"Zergling";"Larva";241;1
"Unit";"Zergling";"Larva";241;1
"Unit";"Zergling";"Larva";241;1
"Unit";"Zergling";"Larva";241;1
"Building";"CreepTumor";NA;241;0
"Building";"CreepTumor";NA;241;0
"Building";"CreepTumor";NA;241;0
"Building";"CreepTumor";NA;241;0
"Building";"CreepTumor";NA;241;0
"Building";"CreepTumor";NA;241;0
"Building";"Extractor";NA;241;0
"Building";"CreepTumor";NA;241;0
"Building";"CreepTumor";NA;241;0
"Unit";"Mutalisk";"Larva";241;2
"Unit";"Mutalisk";"Larva";241;2
"Building";"CreepTumor";NA;241;0
"Building";"CreepTumor";NA;243;0
"Building";"Extractor";NA;241;0
"Building";"CreepTumor";NA;243;0
"Building";"CreepTumor";NA;243;0
"Building";"CreepTumor";NA;243;0
"Building";"CreepTumor";NA;243;0
"Unit";"Mutalisk";"Larva";277;2
"Unit";"Mutalisk";"Larva";277;2
"Unit";"Mutalisk";"Larva";277;2
"Building";"Hatchery";NA;235;0
"Unit";"Mutalisk";"Larva";287;2
"Unit";"Mutalisk";"Larva";287;2
"Unit";"Mutalisk";"Larva";287;2
"Unit";"Mutalisk";"Larva";287;2
"Unit";"Overlord";"Larva";287;0
"Unit";"Overlord";"Larva";287;0
"Unit";"Overlord";"Larva";287;0
"Building";"CreepTumor";NA;310;0
"Building";"CreepTumor";NA;310;0
"Building";"CreepTumor";NA;310;0
"Unit";"Overlord";"Larva";310;0
"Unit";"Zergling";"Larva";310;1
"Unit";"Zergling";"Larva";310;1
"Unit";"Zergling";"Larva";310;1
"Unit";"Zergling";"Larva";310;1
"Unit";"Zergling";"Larva";310;1
"Unit";"Zergling";"Larva";310;1
"Unit";"Zergling";"Larva";310;1
"Unit";"Zergling";"Larva";310;1
"Unit";"Zergling";"Larva";310;1
"Unit";"Zergling";"Larva";310;1
"Unit";"Zergling";"Larva";310;1
"Unit";"Zergling";"Larva";310;1
"Unit";"Zergling";"Larva";310;1
"Unit";"Zergling";"Larva";310;1
"Unit";"Zergling";"Larva";310;1
"Unit";"Zergling";"Larva";310;1
"Unit";"Zergling";"Larva";310;1
"Unit";"Zergling";"Larva";310;1
"Unit";"Zergling";"Larva";310;1
"Unit";"Zergling";"Larva";310;1
"Building";"Extractor";NA;310;0
"Building";"Extractor";NA;310;0
"Building";"CreepTumor";NA;330;0
"Building";"CreepTumor";NA;330;0
"Building";"CreepTumor";NA;330;0
"Building";"CreepTumor";NA;333;0
"Building";"CreepTumor";NA;333;0
"Building";"CreepTumor";NA;333;0
"Building";"CreepTumor";NA;333;0
"Building";"CreepTumor";NA;333;0
"Building";"CreepTumor";NA;333;0
"Unit";"Zergling";"Larva";333;1
"Unit";"Zergling";"Larva";333;1
"Unit";"Zergling";"Larva";333;1
"Unit";"Zergling";"Larva";333;1
"Unit";"Zergling";"Larva";333;1
"Unit";"Zergling";"Larva";333;1
"Unit";"Zergling";"Larva";333;1
"Unit";"Zergling";"Larva";333;1
"Building";"CreepTumor";NA;333;0
"Unit";"Zergling";"Larva";333;1
"Unit";"Zergling";"Larva";333;1
"Unit";"Zergling";"Larva";333;1
"Unit";"Zergling";"Larva";333;1
"Unit";"Zergling";"Larva";333;1
"Unit";"Zergling";"Larva";333;1
"Unit";"Zergling";"Larva";333;1
"Unit";"Zergling";"Larva";333;1
"Unit";"Zergling";"Larva";333;1
"Unit";"Zergling";"Larva";333;1
"Unit";"Zergling";"Larva";333;1
"Unit";"Zergling";"Larva";333;1
"Unit";"Zergling";"Larva";333;1
"Unit";"Zergling";"Larva";333;1
"Unit";"Zergling";"Larva";333;1
"Unit";"Zergling";"Larva";333;1
"Unit";"Zergling";"Larva";333;1
"Unit";"Zergling";"Larva";333;1
"Unit";"Zergling";"Larva";333;1
"Unit";"Zergling";"Larva";333;1
"Unit";"Baneling";"Zergling";333;0
"Unit";"Baneling";"Zergling";333;0
"Unit";"Baneling";"Zergling";333;0
"Unit";"Baneling";"Zergling";333;0
"Unit";"Baneling";"Zergling";333;0
"Unit";"Baneling";"Zergling";333;0
"Unit";"Baneling";"Zergling";333;0
"Unit";"Baneling";"Zergling";333;0
"Unit";"Baneling";"Zergling";333;0
"Unit";"Baneling";"Zergling";333;0
"Unit";"Baneling";"Zergling";333;0
"Unit";"Baneling";"Zergling";333;0
"Unit";"Baneling";"Zergling";333;0
"Unit";"Baneling";"Zergling";333;0
"Unit";"Baneling";"Zergling";333;0
"Building";"SpineCrawler";NA;330;0
"Building";"SpineCrawler";NA;330;0
"Building";"CreepTumor";NA;361;0
"Building";"CreepTumor";NA;361;0
"Building";"CreepTumor";NA;361;0
"Building";"UltraliskCavern";NA;330;0
"Building";"CreepTumor";NA;361;0
"Building";"CreepTumor";NA;361;0
"Building";"CreepTumorQueen";NA;361;0
"Building";"CreepTumorQueen";NA;361;0
"Building";"CreepTumorQueen";NA;361;0
"Building";"CreepTumorQueen";NA;361;0
"Building";"CreepTumorQueen";NA;361;0
"Building";"CreepTumorQueen";NA;361;0
"Building";"CreepTumorQueen";NA;361;0
"Building";"CreepTumorQueen";NA;361;0
"Building";"CreepTumor";NA;361;0
"Building";"CreepTumor";NA;361;0
"Building";"CreepTumorQueen";NA;361;0
"Building";"CreepTumor";NA;361;0
"Building";"CreepTumor";NA;361;0
"Building";"CreepTumor";NA;361;0
"Building";"CreepTumorQueen";NA;361;0
"Building";"CreepTumor";NA;361;0
"Building";"CreepTumorQueen";NA;361;0
"Building";"CreepTumorQueen";NA;361;0
"Building";"CreepTumor";NA;361;0
"Building";"CreepTumor";NA;361;0
"Building";"CreepTumorQueen";NA;361;0
"Unit";"Ultralisk";"Larva";361;6
"Unit";"Ultralisk";"Larva";361;6
"Unit";"Ultralisk";"Larva";361;6
"Unit";"Ultralisk";"Larva";361;6
"Building";"CreepTumor";NA;385;0
"Building";"CreepTumor";NA;385;0
"Building";"CreepTumor";NA;385;0
"Building";"CreepTumor";NA;385;0
"Building";"CreepTumor";NA;385;0
"Building";"CreepTumor";NA;385;0
"Building";"CreepTumor";NA;385;0
"Building";"CreepTumor";NA;385;0
"Building";"CreepTumor";NA;385;0
"Building";"CreepTumor";NA;385;0
"Building";"CreepTumor";NA;385;0
"Building";"CreepTumor";NA;385;0
"Building";"CreepTumorQueen";NA;385;0
"Building";"CreepTumor";NA;385;0
"Building";"CreepTumor";NA;385;0
"Building";"CreepTumor";NA;385;0
"Unit";"Ultralisk";"Larva";361;6
"Unit";"Ultralisk";"Larva";361;6
"Unit";"Ultralisk";"Larva";361;6
"Unit";"Ultralisk";"Larva";361;6
"Unit";"Ultralisk";"Larva";361;6
"Building";"CreepTumorQueen";NA;385;0
"Upgrade";"ChitinousPlating";"UltraliskCavern";361;0
"Unit";"Baneling";"Zergling";385;0
"Unit";"Baneling";"Zergling";385;0
"Unit";"Baneling";"Zergling";385;0
"Unit";"Baneling";"Zergling";385;0
"Unit";"Baneling";"Zergling";385;0
"Unit";"Baneling";"Zergling";385;0
"Unit";"Baneling";"Zergling";385;0
"Unit";"Zergling";"Larva";385;1
"Unit";"Zergling";"Larva";385;1
"Unit";"Zergling";"Larva";385;1
"Unit";"Zergling";"Larva";385;1
"Unit";"Zergling";"Larva";385;1
"Unit";"Zergling";"Larva";385;1
"Unit";"Zergling";"Larva";385;1
"Unit";"Zergling";"Larva";385;1
"Unit";"Zergling";"Larva";385;1
"Unit";"Zergling";"Larva";385;1
"Unit";"Zergling";"Larva";385;1
"Unit";"Zergling";"Larva";385;1
"Unit";"Zergling";"Larva";385;1
"Unit";"Zergling";"Larva";385;1
"Unit";"Zergling";"Larva";385;1
"Unit";"Zergling";"Larva";385;1
"Unit";"Zergling";"Larva";385;1
"Unit";"Zergling";"Larva";385;1
"Unit";"Zergling";"Larva";385;1
"Unit";"Zergling";"Larva";385;1
"Unit";"Zergling";"Larva";385;1
"Unit";"Zergling";"Larva";385;1
"Unit";"Zergling";"Larva";385;1
"Unit";"Zergling";"Larva";385;1
"Unit";"Zergling";"Larva";385;1
"Unit";"Zergling";"Larva";385;1
"Unit";"Zergling";"Larva";385;1
"Unit";"Zergling";"Larva";385;1
"Unit";"Zergling";"Larva";385;1
"Unit";"Zergling";"Larva";385;1
"Unit";"Zergling";"Larva";385;1
"Unit";"Zergling";"Larva";385;1
"Unit";"Zergling";"Larva";385;1
"Unit";"Zergling";"Larva";385;1
"Unit";"Zergling";"Larva";385;1
"Unit";"Zergling";"Larva";385;1
"Unit";"Zergling";"Larva";385;1
"Unit";"Zergling";"Larva";385;1
"Unit";"Zergling";"Larva";385;1
"Unit";"Zergling";"Larva";385;1
"Unit";"Zergling";"Larva";385;1
"Unit";"Zergling";"Larva";385;1
"Unit";"Zergling";"Larva";385;1
"Unit";"Zergling";"Larva";385;1
"Unit";"Zergling";"Larva";385;1
"Unit";"Zergling";"Larva";385;1
"Building";"CreepTumor";NA;415;0
"Building";"CreepTumor";NA;415;0
"Building";"CreepTumor";NA;415;0
"Building";"CreepTumor";NA;415;0
"Building";"CreepTumor";NA;415;0
"Building";"CreepTumor";NA;415;0
"Building";"CreepTumor";NA;415;0
"Building";"CreepTumor";NA;415;0
"Building";"CreepTumor";NA;415;0
"Building";"CreepTumor";NA;415;0
"Building";"CreepTumor";NA;443;0
"Building";"CreepTumor";NA;447;0
"Building";"CreepTumor";NA;447;0
"Building";"CreepTumor";NA;461;0
"Building";"CreepTumor";NA;461;0
"Building";"CreepTumor";NA;461;0
"Building";"CreepTumor";NA;461;0
"Building";"CreepTumor";NA;461;0
"Upgrade";"ZergMeleeWeaponsLevel3";"EvolutionChamber";361;0
"Upgrade";"ZergGroundArmorsLevel3";"EvolutionChamber";361;0
"Building";"CreepTumor";NA;461;0
"Building";"CreepTumorQueen";NA;461;0
"Building";"CreepTumorQueen";NA;461;0
"Building";"CreepTumorQueen";NA;461;0
"Unit";"Baneling";"Zergling";461;0
"Unit";"Baneling";"Zergling";461;0
"Unit";"Baneling";"Zergling";461;0
"Unit";"Baneling";"Zergling";461;0
"Unit";"Baneling";"Zergling";461;0
"Unit";"Baneling";"Zergling";461;0
"Unit";"Baneling";"Zergling";461;0
"Unit";"Baneling";"Zergling";461;0
"Unit";"Baneling";"Zergling";461;0
"Unit";"Baneling";"Zergling";461;0
"Unit";"Baneling";"Zergling";461;0
"Unit";"Baneling";"Zergling";461;0
"Unit";"Baneling";"Zergling";461;0
"Unit";"Baneling";"Zergling";461;0
"Unit";"Baneling";"Zergling";461;0
"Unit";"Baneling";"Zergling";461;0
"Unit";"Baneling";"Zergling";461;0
"Unit";"Baneling";"Zergling";461;0
"Unit";"Baneling";"Zergling";461;0
"Unit";"Baneling";"Zergling";461;0
"Unit";"Baneling";"Zergling";461;0
"Unit";"Baneling";"Zergling";461;0
"Unit";"Baneling";"Zergling";461;0
"Unit";"Baneling";"Zergling";461;0
"Unit";"Baneling";"Zergling";461;0
"Unit";"Baneling";"Zergling";461;0
"Unit";"Baneling";"Zergling";461;0
"Unit";"Baneling";"Zergling";461;0
"Unit";"Baneling";"Zergling";461;0
"Unit";"Baneling";"Zergling";461;0
"Unit";"Baneling";"Zergling";461;0
"Unit";"Baneling";"Zergling";461;0
"Unit";"Baneling";"Zergling";461;0
"Unit";"Baneling";"Zergling";461;0
"Building";"CreepTumor";NA;461;0
"Building";"CreepTumor";NA;461;0
"Building";"CreepTumor";NA;461;0
"Building";"CreepTumor";NA;461;0
"Building";"CreepTumor";NA;461;0
"Building";"CreepTumor";NA;461;0
"Building";"CreepTumor";NA;461;0
