"type";"unit_name";"on_building";"total_supply";"supply"
"Unit";"Overlord";"Larva";13;0
"Building";"Extractor";NA;18;0
"Unit";"Overlord";"Larva";22;0
"Building";"SpawningPool";NA;19;0
"Building";"Hatchery";NA;17;0
"Unit";"Zergling";"Larva";22;1
"Unit";"Zergling";"Larva";22;1
"Unit";"Zergling";"Larva";23;1
"Unit";"Zergling";"Larva";23;1
"Unit";"Queen";"Hatchery";22;2
"Unit";"Queen";"Hatchery";23;2
"Unit";"Overlord";"Larva";31;0
"Unit";"Zergling";"Larva";38;1
"Unit";"Zergling";"Larva";38;1
"Unit";"Zergling";"Larva";38;1
"Unit";"Zergling";"Larva";38;1
"Unit";"Queen";"Hatchery";36;2
"Unit";"Queen";"Hatchery";36;2
"Unit";"Overlord";"Larva";46;0
"Unit";"Overlord";"Larva";46;0
"Building";"CreepTumorQueen";NA;53;0
"Building";"CreepTumorQueen";NA;53;0
"Building";"Extractor";NA;53;0
"Unit";"Overlord";"Larva";53;0
"Building";"Hatchery";NA;36;0
"Building";"CreepTumorQueen";NA;60;0
"Building";"CreepTumor";NA;59;0
"Building";"CreepTumorQueen";NA;60;0
"Unit";"Queen";"Hatchery";53;2
"Unit";"Queen";"Hatchery";53;2
"Unit";"Overlord";"Larva";66;0
"Building";"EvolutionChamber";NA;62;0
"Building";"EvolutionChamber";NA;62;0
"Building";"BanelingNest";NA;60;0
"Unit";"Queen";"Hatchery";62;2
"Unit";"Overlord";"Larva";67;0
"Unit";"Queen";"Hatchery";66;2
"Building";"Extractor";NA;72;0
"Building";"CreepTumor";NA;75;0
"Building";"CreepTumor";NA;77;0
"Building";"CreepTumorQueen";NA;78;0
"Building";"CreepTumorQueen";NA;78;0
"Building";"CreepTumorQueen";NA;78;0
"Building";"CreepTumorQueen";NA;78;0
"Unit";"Overlord";"Larva";78;0
"Building";"Extractor";NA;91;0
"Unit";"Zergling";"Larva";92;1
"Unit";"Zergling";"Larva";92;1
"Building";"HydraliskDen";NA;91;0
"Unit";"Zergling";"Larva";92;1
"Unit";"Zergling";"Larva";92;1
"Unit";"Zergling";"Larva";92;1
"Unit";"Zergling";"Larva";92;1
"Unit";"Zergling";"Larva";92;1
"Unit";"Zergling";"Larva";92;1
"Unit";"Zergling";"Larva";92;1
"Unit";"Zergling";"Larva";92;1
"Unit";"Zergling";"Larva";92;1
"Unit";"Zergling";"Larva";92;1
"Unit";"Zergling";"Larva";92;1
"Unit";"Zergling";"Larva";92;1
"Unit";"Zergling";"Larva";92;1
"Unit";"Zergling";"Larva";92;1
"Unit";"Zergling";"Larva";92;1
"Unit";"Zergling";"Larva";92;1
"Building";"CreepTumor";NA;93;0
"Building";"CreepTumor";NA;93;0
"Building";"CreepTumor";NA;93;0
"Building";"CreepTumor";NA;93;0
"Building";"CreepTumor";NA;105;0
"Building";"CreepTumor";NA;111;0
"Building";"CreepTumorQueen";NA;114;0
"Building";"CreepTumorQueen";NA;114;0
"Building";"SporeCrawler";NA;114;0
"Building";"SporeCrawler";NA;114;0
"Unit";"Overlord";"Larva";114;0
"Unit";"Overlord";"Larva";114;0
"Unit";"Overlord";"Larva";114;0
"Building";"SporeCrawler";NA;114;0
"Unit";"Hydralisk";"Larva";114;2
"Unit";"Hydralisk";"Larva";114;2
"Unit";"Hydralisk";"Larva";114;2
"Unit";"Hydralisk";"Larva";114;2
"Building";"CreepTumor";NA;115;0
"Building";"CreepTumor";NA;115;0
"Building";"CreepTumor";NA;115;0
"Building";"CreepTumor";NA;115;0
"Building";"CreepTumor";NA;115;0
"Building";"CreepTumor";NA;115;0
"Building";"CreepTumor";NA;115;0
"Building";"CreepTumor";NA;115;0
"Building";"CreepTumorQueen";NA;123;0
"Building";"CreepTumorQueen";NA;123;0
"Building";"CreepTumor";NA;123;0
"Building";"Extractor";NA;115;0
"Unit";"Overlord";"Larva";123;0
"Upgrade";"ZergMeleeWeaponsLevel1";"EvolutionChamber";93;0
"Upgrade";"ZergGroundArmorsLevel1";"EvolutionChamber";93;0
"Unit";"Hydralisk";"Larva";123;2
"Unit";"Hydralisk";"Larva";123;2
"Building";"Hatchery";NA;114;0
"Upgrade";"EvolveGroovedSpines";"HydraliskDen";115;0
"Building";"InfestationPit";NA;130;0
"Unit";"Overlord";"Larva";135;0
"Unit";"Overlord";"Larva";135;0
"Unit";"Overlord";"Larva";135;0
"Unit";"Zergling";"Larva";135;1
"Unit";"Zergling";"Larva";135;1
"Unit";"Zergling";"Larva";135;1
"Unit";"Zergling";"Larva";135;1
"Unit";"Zergling";"Larva";135;1
"Unit";"Zergling";"Larva";135;1
"Unit";"Zergling";"Larva";135;1
"Unit";"Zergling";"Larva";135;1
"Unit";"Zergling";"Larva";135;1
"Unit";"Zergling";"Larva";135;1
"Unit";"Zergling";"Larva";135;1
"Unit";"Zergling";"Larva";135;1
"Unit";"Zergling";"Larva";135;1
"Unit";"Zergling";"Larva";135;1
"Unit";"Zergling";"Larva";135;1
"Unit";"Zergling";"Larva";135;1
"Unit";"Zergling";"Larva";135;1
"Unit";"Zergling";"Larva";135;1
"Unit";"Zergling";"Larva";135;1
"Unit";"Zergling";"Larva";135;1
"Unit";"Zergling";"Larva";135;1
"Unit";"Zergling";"Larva";135;1
"Unit";"Zergling";"Larva";135;1
"Unit";"Zergling";"Larva";135;1
"Unit";"Zergling";"Larva";135;1
"Unit";"Zergling";"Larva";135;1
"Building";"CreepTumor";NA;135;0
"Building";"CreepTumor";NA;135;0
"Building";"CreepTumor";NA;135;0
"Building";"CreepTumor";NA;135;0
"Building";"CreepTumor";NA;135;0
"Unit";"Baneling";"Zergling";135;0
"Unit";"Baneling";"Zergling";135;0
"Unit";"Baneling";"Zergling";135;0
"Unit";"Baneling";"Zergling";135;0
"Unit";"Baneling";"Zergling";135;0
"Unit";"Baneling";"Zergling";135;0
"Unit";"Zergling";"Larva";135;1
"Unit";"Zergling";"Larva";135;1
"Unit";"Zergling";"Larva";135;1
"Unit";"Zergling";"Larva";135;1
"Unit";"Zergling";"Larva";135;1
"Unit";"Zergling";"Larva";135;1
"Unit";"Zergling";"Larva";135;1
"Unit";"Zergling";"Larva";135;1
"Unit";"Zergling";"Larva";135;1
"Unit";"Zergling";"Larva";135;1
"Unit";"Zergling";"Larva";135;1
"Unit";"Zergling";"Larva";135;1
"Unit";"Zergling";"Larva";135;1
"Unit";"Zergling";"Larva";135;1
"Unit";"Zergling";"Larva";135;1
"Unit";"Zergling";"Larva";135;1
"Unit";"Zergling";"Larva";135;1
"Unit";"Zergling";"Larva";135;1
"Unit";"Zergling";"Larva";135;1
"Unit";"Zergling";"Larva";135;1
"Unit";"Zergling";"Larva";135;1
"Unit";"Zergling";"Larva";135;1
"Unit";"Zergling";"Larva";135;1
"Unit";"Zergling";"Larva";135;1
"Unit";"Overlord";"Larva";135;0
"Unit";"Zergling";"Larva";161;1
"Unit";"Zergling";"Larva";161;1
"Unit";"Zergling";"Larva";161;1
"Unit";"Zergling";"Larva";161;1
"Unit";"Zergling";"Larva";161;1
"Unit";"Zergling";"Larva";161;1
"Building";"Hatchery";NA;130;0
"Building";"LurkerDenMP";NA;130;0
"Building";"CreepTumor";NA;191;0
"Unit";"Hydralisk";"Larva";185;2
"Unit";"Hydralisk";"Larva";185;2
"Unit";"Hydralisk";"Larva";185;2
"Unit";"Hydralisk";"Larva";185;2
"Unit";"Hydralisk";"Larva";185;2
"Unit";"Hydralisk";"Larva";185;2
"Building";"CreepTumor";NA;191;0
"Building";"CreepTumor";NA;191;0
"Building";"CreepTumor";NA;191;0
"Building";"CreepTumor";NA;191;0
"Building";"CreepTumor";NA;191;0
"Building";"CreepTumor";NA;191;0
"Building";"Extractor";NA;203;0
"Unit";"Overlord";"Larva";203;0
"Unit";"Overlord";"Larva";203;0
"Building";"CreepTumor";NA;208;0
"Building";"CreepTumor";NA;208;0
"Building";"CreepTumor";NA;216;0
"Unit";"Overlord";"Larva";203;0
"Unit";"Overlord";"Larva";205;0
"Unit";"Baneling";"Zergling";216;0
"Unit";"Baneling";"Zergling";216;0
"Unit";"Baneling";"Zergling";216;0
"Unit";"Baneling";"Zergling";216;0
"Unit";"Baneling";"Zergling";216;0
"Unit";"Baneling";"Zergling";216;0
"Unit";"Baneling";"Zergling";216;0
"Unit";"Baneling";"Zergling";216;0
"Unit";"Baneling";"Zergling";216;0
"Unit";"Baneling";"Zergling";216;0
"Unit";"Baneling";"Zergling";216;0
"Building";"CreepTumor";NA;216;0
"Building";"CreepTumor";NA;216;0
"Building";"Extractor";NA;216;0
"Upgrade";"ZergMeleeWeaponsLevel2";"EvolutionChamber";161;0
"Unit";"Queen";"Hatchery";216;2
"Unit";"Queen";"Hatchery";216;2
"Unit";"Queen";"Hatchery";216;2
"Upgrade";"EvolveMuscularAugments";"HydraliskDen";216;0
"Upgrade";"ZergGroundArmorsLevel2";"EvolutionChamber";185;0
"Unit";"Queen";"Hatchery";216;2
"Unit";"Hydralisk";"Larva";216;2
"Unit";"Hydralisk";"Larva";216;2
"Unit";"Hydralisk";"Larva";216;2
"Unit";"Hydralisk";"Larva";216;2
"Unit";"Hydralisk";"Larva";216;2
"Unit";"Hydralisk";"Larva";216;2
"Unit";"Hydralisk";"Larva";216;2
"Unit";"Hydralisk";"Larva";216;2
"Unit";"Hydralisk";"Larva";216;2
"Unit";"Hydralisk";"Larva";216;2
"Unit";"Hydralisk";"Larva";216;2
"Unit";"Hydralisk";"Larva";216;2
"Unit";"Queen";"Hatchery";216;2
"Unit";"Overlord";"Larva";248;0
"Unit";"Overlord";"Larva";248;0
"Unit";"Overlord";"Larva";248;0
"Unit";"Overlord";"Larva";248;0
"Unit";"Overlord";"Larva";248;0
"Unit";"Queen";"Hatchery";216;2
"Unit";"Queen";"Hatchery";218;2
"Unit";"Queen";"Hatchery";220;2
"Building";"CreepTumorQueen";NA;256;0
"Building";"UltraliskCavern";NA;248;0
"Building";"CreepTumorQueen";NA;256;0
"Building";"CreepTumorQueen";NA;256;0
"Unit";"Zergling";"Larva";256;1
"Unit";"Zergling";"Larva";256;1
"Unit";"Zergling";"Larva";256;1
"Unit";"Zergling";"Larva";256;1
"Unit";"Zergling";"Larva";256;1
"Unit";"Zergling";"Larva";256;1
"Unit";"Zergling";"Larva";256;1
"Unit";"Zergling";"Larva";256;1
"Unit";"Zergling";"Larva";256;1
"Unit";"Zergling";"Larva";256;1
"Unit";"Zergling";"Larva";256;1
"Unit";"Zergling";"Larva";256;1
"Unit";"Zergling";"Larva";256;1
"Unit";"Zergling";"Larva";256;1
"Unit";"Zergling";"Larva";256;1
"Unit";"Zergling";"Larva";256;1
"Unit";"Zergling";"Larva";256;1
"Unit";"Zergling";"Larva";256;1
"Unit";"Zergling";"Larva";256;1
"Unit";"Zergling";"Larva";256;1
"Unit";"Zergling";"Larva";256;1
"Unit";"Zergling";"Larva";256;1
"Unit";"Zergling";"Larva";256;1
"Unit";"Zergling";"Larva";256;1
"Unit";"Zergling";"Larva";256;1
"Unit";"Zergling";"Larva";256;1
"Unit";"Zergling";"Larva";256;1
"Unit";"Zergling";"Larva";256;1
"Unit";"Zergling";"Larva";256;1
"Unit";"Zergling";"Larva";256;1
"Building";"CreepTumor";NA;256;0
"Unit";"Zergling";"Larva";256;1
"Unit";"Zergling";"Larva";256;1
"Unit";"Zergling";"Larva";256;1
"Unit";"Zergling";"Larva";256;1
"Unit";"Zergling";"Larva";256;1
"Unit";"Zergling";"Larva";256;1
"Unit";"Zergling";"Larva";256;1
"Unit";"Zergling";"Larva";256;1
"Unit";"Zergling";"Larva";256;1
"Unit";"Zergling";"Larva";256;1
"Unit";"Zergling";"Larva";256;1
"Unit";"Zergling";"Larva";256;1
"Unit";"Zergling";"Larva";256;1
"Unit";"Zergling";"Larva";256;1
"Unit";"Overlord";"Larva";256;0
"Building";"CreepTumorQueen";NA;300;0
"Building";"CreepTumor";NA;300;0
"Building";"CreepTumorQueen";NA;300;0
"Building";"CreepTumor";NA;300;0
"Building";"CreepTumor";NA;300;0
"Building";"CreepTumorQueen";NA;300;0
"Building";"CreepTumorQueen";NA;300;0
"Building";"CreepTumorQueen";NA;300;0
"Building";"CreepTumorQueen";NA;300;0
"Building";"CreepTumorQueen";NA;300;0
"Building";"CreepTumorQueen";NA;300;0
"Building";"CreepTumor";NA;300;0
"Building";"CreepTumor";NA;300;0
"Building";"CreepTumor";NA;300;0
"Building";"CreepTumorQueen";NA;300;0
"Building";"CreepTumorQueen";NA;300;0
"Unit";"Ultralisk";"Larva";300;6
"Unit";"Ultralisk";"Larva";300;6
"Unit";"Ultralisk";"Larva";300;6
"Building";"CreepTumor";NA;300;0
"Building";"CreepTumor";NA;300;0
"Building";"CreepTumor";NA;300;0
"Building";"CreepTumor";NA;300;0
"Building";"CreepTumor";NA;300;0
"Unit";"Baneling";"Zergling";318;0
"Upgrade";"ChitinousPlating";"UltraliskCavern";300;0
"Unit";"Baneling";"Zergling";318;0
"Unit";"Baneling";"Zergling";318;0
"Unit";"Baneling";"Zergling";318;0
"Unit";"Baneling";"Zergling";318;0
"Unit";"Baneling";"Zergling";318;0
"Unit";"Baneling";"Zergling";318;0
"Unit";"Baneling";"Zergling";318;0
"Unit";"Baneling";"Zergling";318;0
"Unit";"Baneling";"Zergling";318;0
"Unit";"Baneling";"Zergling";318;0
"Unit";"Baneling";"Zergling";318;0
"Unit";"Baneling";"Zergling";318;0
"Unit";"Baneling";"Zergling";318;0
"Unit";"Baneling";"Zergling";318;0
"Building";"CreepTumor";NA;318;0
"Building";"CreepTumor";NA;318;0
"Building";"CreepTumor";NA;318;0
"Building";"CreepTumor";NA;318;0
"Building";"CreepTumor";NA;318;0
"Building";"Spire";NA;300;0
"Building";"CreepTumor";NA;318;0
"Building";"CreepTumor";NA;318;0
"Building";"CreepTumor";NA;318;0
"Building";"CreepTumorQueen";NA;318;0
"Building";"CreepTumorQueen";NA;318;0
"Building";"CreepTumorQueen";NA;318;0
"Building";"CreepTumorQueen";NA;318;0
"Building";"Hatchery";NA;300;0
"Upgrade";"ZergMeleeWeaponsLevel3";"EvolutionChamber";300;0
"Upgrade";"ZergGroundArmorsLevel3";"EvolutionChamber";300;0
"Building";"Extractor";NA;318;0
"Unit";"Zergling";"Larva";318;1
"Unit";"Zergling";"Larva";318;1
"Unit";"Zergling";"Larva";318;1
"Unit";"Zergling";"Larva";318;1
"Unit";"Zergling";"Larva";318;1
"Unit";"Zergling";"Larva";318;1
"Unit";"Zergling";"Larva";318;1
"Unit";"Zergling";"Larva";318;1
"Unit";"Zergling";"Larva";318;1
"Unit";"Zergling";"Larva";318;1
"Unit";"Zergling";"Larva";318;1
"Unit";"Zergling";"Larva";318;1
"Unit";"Zergling";"Larva";318;1
"Unit";"Zergling";"Larva";318;1
"Unit";"Zergling";"Larva";318;1
"Unit";"Zergling";"Larva";318;1
"Unit";"Zergling";"Larva";318;1
"Unit";"Zergling";"Larva";318;1
"Unit";"Zergling";"Larva";318;1
"Unit";"Zergling";"Larva";318;1
"Unit";"Zergling";"Larva";318;1
"Unit";"Zergling";"Larva";318;1
"Unit";"Zergling";"Larva";318;1
"Unit";"Zergling";"Larva";318;1
"Unit";"Zergling";"Larva";318;1
"Unit";"Zergling";"Larva";318;1
"Unit";"Zergling";"Larva";318;1
"Unit";"Zergling";"Larva";318;1
"Unit";"Zergling";"Larva";318;1
"Unit";"Zergling";"Larva";318;1
"Unit";"Zergling";"Larva";318;1
"Unit";"Zergling";"Larva";318;1
"Unit";"Zergling";"Larva";318;1
"Unit";"Zergling";"Larva";318;1
"Unit";"Zergling";"Larva";318;1
"Unit";"Zergling";"Larva";318;1
"Unit";"Zergling";"Larva";318;1
"Unit";"Zergling";"Larva";318;1
"Unit";"Zergling";"Larva";318;1
"Unit";"Zergling";"Larva";318;1
"Unit";"Zergling";"Larva";318;1
"Unit";"Zergling";"Larva";318;1
"Unit";"Zergling";"Larva";318;1
"Unit";"Zergling";"Larva";318;1
"Unit";"Zergling";"Larva";318;1
"Unit";"Zergling";"Larva";318;1
"Unit";"Zergling";"Larva";318;1
"Unit";"Zergling";"Larva";318;1
"Unit";"Zergling";"Larva";318;1
"Unit";"Zergling";"Larva";318;1
"Unit";"Zergling";"Larva";318;1
"Unit";"Zergling";"Larva";318;1
"Unit";"Zergling";"Larva";318;1
"Unit";"Zergling";"Larva";318;1
"Unit";"Zergling";"Larva";318;1
"Unit";"Zergling";"Larva";318;1
"Unit";"Zergling";"Larva";318;1
"Unit";"Zergling";"Larva";318;1
"Unit";"Zergling";"Larva";318;1
"Unit";"Zergling";"Larva";318;1
"Unit";"Zergling";"Larva";318;1
"Unit";"Zergling";"Larva";318;1
"Unit";"Zergling";"Larva";318;1
"Unit";"Zergling";"Larva";318;1
"Unit";"Hydralisk";"Larva";318;2
"Unit";"Viper";"Larva";318;3
"Unit";"Viper";"Larva";318;3
"Unit";"Hydralisk";"Larva";318;2
"Unit";"Viper";"Larva";318;3
"Unit";"Viper";"Larva";318;3
"Unit";"Viper";"Larva";318;3
"Unit";"Ultralisk";"Larva";318;6
"Unit";"Ultralisk";"Larva";318;6
"Building";"Spire";NA;318;0
"Unit";"Baneling";"Zergling";401;0
"Unit";"Baneling";"Zergling";401;0
"Unit";"Baneling";"Zergling";401;0
"Unit";"Baneling";"Zergling";401;0
"Unit";"Baneling";"Zergling";401;0
"Unit";"Baneling";"Zergling";401;0
"Unit";"Baneling";"Zergling";401;0
"Unit";"Baneling";"Zergling";401;0
"Unit";"Baneling";"Zergling";401;0
"Unit";"Baneling";"Zergling";401;0
"Unit";"Baneling";"Zergling";401;0
"Unit";"Baneling";"Zergling";401;0
"Unit";"Baneling";"Zergling";401;0
"Unit";"Baneling";"Zergling";401;0
"Unit";"Baneling";"Zergling";401;0
"Unit";"Baneling";"Zergling";401;0
"Unit";"Baneling";"Zergling";401;0
"Unit";"Baneling";"Zergling";401;0
"Unit";"Baneling";"Zergling";401;0
"Unit";"Baneling";"Zergling";401;0
"Unit";"Baneling";"Zergling";401;0
"Unit";"Baneling";"Zergling";401;0
"Unit";"Baneling";"Zergling";401;0
"Unit";"Baneling";"Zergling";401;0
"Unit";"Baneling";"Zergling";401;0
"Building";"CreepTumorQueen";NA;413;0
"Building";"CreepTumorQueen";NA;413;0
"Building";"CreepTumorQueen";NA;413;0
"Building";"CreepTumorQueen";NA;413;0
"Building";"CreepTumorQueen";NA;413;0
"Building";"CreepTumorQueen";NA;413;0
"Building";"CreepTumorQueen";NA;413;0
"Building";"CreepTumorQueen";NA;413;0
"Building";"CreepTumorQueen";NA;413;0
"Building";"CreepTumor";NA;413;0
"Building";"CreepTumor";NA;413;0
"Building";"CreepTumor";NA;413;0
"Building";"CreepTumor";NA;413;0
"Building";"CreepTumor";NA;413;0
"Building";"CreepTumor";NA;413;0
"Building";"CreepTumor";NA;413;0
"Building";"CreepTumor";NA;413;0
"Building";"CreepTumor";NA;413;0
"Building";"CreepTumor";NA;413;0
"Building";"CreepTumor";NA;413;0
"Building";"CreepTumor";NA;413;0
"Building";"CreepTumor";NA;413;0
"Building";"CreepTumor";NA;413;0
"Building";"CreepTumor";NA;413;0
"Building";"Extractor";NA;413;0
"Building";"Extractor";NA;413;0
"Building";"CreepTumor";NA;413;0
"Building";"CreepTumor";NA;413;0
"Building";"CreepTumor";NA;413;0
"Building";"CreepTumor";NA;413;0
"Building";"CreepTumor";NA;413;0
"Building";"CreepTumor";NA;413;0
"Unit";"Zergling";"Larva";413;1
"Unit";"Zergling";"Larva";413;1
"Unit";"Zergling";"Larva";413;1
"Unit";"Zergling";"Larva";413;1
"Unit";"Zergling";"Larva";413;1
"Unit";"Zergling";"Larva";413;1
"Unit";"Zergling";"Larva";413;1
"Unit";"Zergling";"Larva";413;1
"Unit";"Zergling";"Larva";413;1
"Unit";"Zergling";"Larva";413;1
"Unit";"Zergling";"Larva";413;1
"Unit";"Zergling";"Larva";413;1
"Unit";"Zergling";"Larva";413;1
"Unit";"Zergling";"Larva";413;1
"Unit";"Zergling";"Larva";413;1
"Unit";"Zergling";"Larva";413;1
"Unit";"Zergling";"Larva";413;1
"Unit";"Zergling";"Larva";413;1
"Unit";"Zergling";"Larva";413;1
"Unit";"Zergling";"Larva";413;1
"Unit";"Zergling";"Larva";413;1
"Unit";"Zergling";"Larva";413;1
"Unit";"Zergling";"Larva";413;1
"Unit";"Zergling";"Larva";413;1
"Unit";"Zergling";"Larva";413;1
"Unit";"Zergling";"Larva";413;1
"Unit";"Zergling";"Larva";413;1
"Unit";"Zergling";"Larva";413;1
"Unit";"Zergling";"Larva";413;1
"Unit";"Zergling";"Larva";413;1
"Unit";"Zergling";"Larva";413;1
"Unit";"Zergling";"Larva";413;1
"Unit";"Zergling";"Larva";413;1
"Unit";"Zergling";"Larva";413;1
"Unit";"Zergling";"Larva";413;1
"Unit";"Zergling";"Larva";413;1
"Unit";"Zergling";"Larva";413;1
"Unit";"Zergling";"Larva";413;1
"Unit";"Zergling";"Larva";413;1
"Unit";"Zergling";"Larva";413;1
"Unit";"Zergling";"Larva";413;1
"Unit";"Zergling";"Larva";413;1
"Unit";"Zergling";"Larva";413;1
"Unit";"Zergling";"Larva";413;1
"Unit";"Zergling";"Larva";413;1
"Unit";"Zergling";"Larva";413;1
"Unit";"Zergling";"Larva";413;1
"Unit";"Zergling";"Larva";413;1
"Unit";"Zergling";"Larva";413;1
"Unit";"Zergling";"Larva";413;1
"Unit";"Zergling";"Larva";413;1
"Unit";"Zergling";"Larva";413;1
"Unit";"Zergling";"Larva";413;1
"Unit";"Zergling";"Larva";413;1
"Unit";"Zergling";"Larva";413;1
"Unit";"Zergling";"Larva";413;1
"Unit";"Zergling";"Larva";413;1
"Unit";"Zergling";"Larva";413;1
"Unit";"Zergling";"Larva";413;1
"Unit";"Zergling";"Larva";413;1
"Unit";"Zergling";"Larva";413;1
"Unit";"Zergling";"Larva";413;1
"Unit";"Zergling";"Larva";413;1
"Unit";"Zergling";"Larva";413;1
"Unit";"Zergling";"Larva";413;1
"Unit";"Zergling";"Larva";413;1
"Unit";"Zergling";"Larva";413;1
"Unit";"Zergling";"Larva";413;1
"Unit";"Zergling";"Larva";413;1
"Unit";"Zergling";"Larva";413;1
"Unit";"Zergling";"Larva";413;1
"Unit";"Zergling";"Larva";413;1
"Unit";"Zergling";"Larva";413;1
"Unit";"Zergling";"Larva";413;1
"Unit";"Zergling";"Larva";413;1
"Unit";"Zergling";"Larva";413;1
"Unit";"Zergling";"Larva";413;1
"Unit";"Zergling";"Larva";413;1
"Unit";"Zergling";"Larva";413;1
"Unit";"Zergling";"Larva";413;1
"Unit";"Zergling";"Larva";413;1
"Unit";"Zergling";"Larva";413;1
"Unit";"Zergling";"Larva";413;1
"Unit";"Zergling";"Larva";413;1
"Unit";"Zergling";"Larva";413;1
"Unit";"Zergling";"Larva";413;1
"Unit";"Zergling";"Larva";413;1
"Unit";"Zergling";"Larva";413;1
"Unit";"Zergling";"Larva";413;1
"Unit";"Zergling";"Larva";413;1
"Unit";"Hydralisk";"Larva";413;2
"Unit";"Hydralisk";"Larva";413;2
"Unit";"Hydralisk";"Larva";413;2
"Unit";"Hydralisk";"Larva";413;2
"Unit";"Hydralisk";"Larva";413;2
"Unit";"Hydralisk";"Larva";413;2
"Unit";"Hydralisk";"Larva";413;2
"Unit";"Hydralisk";"Larva";413;2
"Unit";"Hydralisk";"Larva";413;2
"Building";"CreepTumor";NA;503;0
"Unit";"Ultralisk";"Larva";413;6
"Building";"CreepTumor";NA;521;0
"Unit";"Ultralisk";"Larva";413;6
"Unit";"Ultralisk";"Larva";413;6
"Unit";"Ultralisk";"Larva";413;6
"Building";"CreepTumorQueen";NA;521;0
"Building";"CreepTumorQueen";NA;521;0
"Building";"CreepTumor";NA;521;0
"Building";"CreepTumor";NA;521;0
"Building";"CreepTumor";NA;521;0
"Building";"CreepTumor";NA;521;0
"Building";"CreepTumor";NA;521;0
"Building";"CreepTumor";NA;521;0
"Unit";"Baneling";"Zergling";545;0
"Building";"CreepTumorQueen";NA;545;0
"Unit";"Baneling";"Zergling";545;0
"Unit";"Baneling";"Zergling";545;0
"Unit";"Baneling";"Zergling";545;0
"Unit";"Baneling";"Zergling";545;0
"Building";"CreepTumorQueen";NA;545;0
"Unit";"Baneling";"Zergling";545;0
"Unit";"Baneling";"Zergling";545;0
"Unit";"Baneling";"Zergling";545;0
"Unit";"Baneling";"Zergling";545;0
"Unit";"Baneling";"Zergling";545;0
"Unit";"Baneling";"Zergling";545;0
"Unit";"Baneling";"Zergling";545;0
"Unit";"Baneling";"Zergling";545;0
"Unit";"Baneling";"Zergling";545;0
"Unit";"Baneling";"Zergling";545;0
"Unit";"Baneling";"Zergling";545;0
"Unit";"Baneling";"Zergling";545;0
"Unit";"Baneling";"Zergling";545;0
"Building";"CreepTumorQueen";NA;545;0
"Unit";"Baneling";"Zergling";545;0
"Unit";"Baneling";"Zergling";545;0
"Unit";"Baneling";"Zergling";545;0
"Unit";"Baneling";"Zergling";545;0
"Unit";"Baneling";"Zergling";545;0
"Unit";"Baneling";"Zergling";545;0
"Unit";"Baneling";"Zergling";545;0
"Unit";"Baneling";"Zergling";545;0
"Unit";"Baneling";"Zergling";545;0
"Unit";"Baneling";"Zergling";545;0
"Unit";"Baneling";"Zergling";545;0
"Unit";"Baneling";"Zergling";545;0
"Unit";"Baneling";"Zergling";545;0
"Unit";"Baneling";"Zergling";545;0
"Unit";"Baneling";"Zergling";545;0
"Unit";"Baneling";"Zergling";545;0
"Building";"CreepTumor";NA;545;0
"Building";"CreepTumor";NA;545;0
"Building";"CreepTumor";NA;545;0
"Building";"CreepTumor";NA;545;0
"Building";"CreepTumor";NA;545;0
"Building";"CreepTumor";NA;545;0
"Building";"CreepTumor";NA;545;0
"Building";"CreepTumor";NA;545;0
"Building";"CreepTumorQueen";NA;545;0
"Building";"CreepTumorQueen";NA;545;0
"Building";"CreepTumorQueen";NA;545;0
"Building";"CreepTumorQueen";NA;545;0
"Building";"CreepTumorQueen";NA;545;0
"Building";"CreepTumor";NA;545;0
"Building";"CreepTumor";NA;545;0
"Building";"CreepTumor";NA;545;0
"Building";"CreepTumor";NA;545;0
"Building";"CreepTumor";NA;545;0
"Building";"CreepTumor";NA;545;0
"Building";"CreepTumor";NA;545;0
"Building";"CreepTumor";NA;545;0
"Building";"CreepTumor";NA;545;0
"Building";"CreepTumor";NA;545;0
"Building";"CreepTumorQueen";NA;545;0
"Building";"CreepTumorQueen";NA;545;0
"Unit";"Overlord";"Larva";545;0
"Building";"CreepTumorQueen";NA;545;0
"Unit";"Overlord";"Larva";545;0
"Unit";"Overlord";"Larva";545;0
"Unit";"Overlord";"Larva";545;0
"Unit";"Overlord";"Larva";545;0
"Upgrade";"ZergMissileWeaponsLevel1";"EvolutionChamber";545;0
"Building";"Extractor";NA;545;0
"Building";"Extractor";NA;545;0
"Unit";"Mutalisk";"Larva";545;2
"Unit";"Mutalisk";"Larva";545;2
"Unit";"Mutalisk";"Larva";545;2
"Unit";"Mutalisk";"Larva";545;2
"Unit";"Mutalisk";"Larva";545;2
"Unit";"Mutalisk";"Larva";545;2
"Unit";"Mutalisk";"Larva";545;2
"Unit";"Mutalisk";"Larva";545;2
"Unit";"Mutalisk";"Larva";545;2
"Unit";"Mutalisk";"Larva";545;2
"Unit";"Mutalisk";"Larva";545;2
"Unit";"Mutalisk";"Larva";545;2
"Unit";"Mutalisk";"Larva";545;2
"Unit";"Mutalisk";"Larva";545;2
"Unit";"Mutalisk";"Larva";545;2
"Unit";"Mutalisk";"Larva";545;2
"Unit";"Mutalisk";"Larva";545;2
"Unit";"Mutalisk";"Larva";545;2
"Unit";"Mutalisk";"Larva";545;2
"Unit";"Mutalisk";"Larva";545;2
"Unit";"Mutalisk";"Larva";545;2
"Unit";"Mutalisk";"Larva";545;2
"Unit";"Mutalisk";"Larva";545;2
"Unit";"Mutalisk";"Larva";545;2
"Unit";"Mutalisk";"Larva";545;2
"Unit";"Mutalisk";"Larva";545;2
"Unit";"Mutalisk";"Larva";545;2
"Unit";"Mutalisk";"Larva";545;2
"Unit";"Mutalisk";"Larva";545;2
"Unit";"Mutalisk";"Larva";545;2
"Unit";"Mutalisk";"Larva";545;2
"Unit";"Mutalisk";"Larva";545;2
"Unit";"Mutalisk";"Larva";545;2
"Building";"Hatchery";NA;545;0
