"type";"unit_name";"on_building";"total_supply";"supply"
"Unit";"Overlord";"Larva";13;0
"Building";"Extractor";NA;17;0
"Building";"SpawningPool";NA;19;0
"Unit";"Overlord";"Larva";21;0
"Building";"Hatchery";NA;17;0
"Unit";"Zergling";"Larva";22;1
"Unit";"Zergling";"Larva";22;1
"Unit";"Zergling";"Larva";22;1
"Unit";"Zergling";"Larva";22;1
"Unit";"Queen";"Hatchery";22;2
"Unit";"Queen";"Hatchery";22;2
"Unit";"Overlord";"Larva";38;0
"Unit";"Queen";"Hatchery";35;2
"Unit";"Queen";"Hatchery";37;2
"Building";"CreepTumorQueen";NA;40;0
"Unit";"Overlord";"Larva";38;0
"Building";"CreepTumorQueen";NA;40;0
"Unit";"Overlord";"Larva";48;0
"Building";"Extractor";NA;52;0
"Building";"EvolutionChamber";NA;52;0
"Unit";"Zergling";"Larva";52;1
"Unit";"Zergling";"Larva";52;1
"Unit";"Zergling";"Larva";52;1
"Unit";"Zergling";"Larva";52;1
"Unit";"Zergling";"Larva";52;1
"Unit";"Zergling";"Larva";52;1
"Unit";"Zergling";"Larva";52;1
"Unit";"Zergling";"Larva";52;1
"Unit";"Zergling";"Larva";52;1
"Unit";"Zergling";"Larva";52;1
"Unit";"Zergling";"Larva";52;1
"Unit";"Zergling";"Larva";52;1
"Unit";"Zergling";"Larva";52;1
"Unit";"Zergling";"Larva";52;1
"Unit";"Queen";"Hatchery";48;2
"Building";"CreepTumor";NA;52;0
"Building";"RoachWarren";NA;52;0
"Building";"Hatchery";NA;40;0
"Unit";"Queen";"Hatchery";52;2
"Building";"EvolutionChamber";NA;68;0
"Unit";"Overlord";"Larva";68;0
"Building";"CreepTumor";NA;75;0
"Unit";"Overlord";"Larva";75;0
"Unit";"Overlord";"Larva";75;0
"Unit";"Overlord";"Larva";75;0
"Unit";"Roach";"Larva";76;2
"Building";"Extractor";NA;82;0
"Building";"Extractor";NA;82;0
"Unit";"Roach";"Larva";88;2
"Unit";"Roach";"Larva";88;2
"Unit";"Roach";"Larva";88;2
"Unit";"Roach";"Larva";88;2
"Unit";"Roach";"Larva";88;2
"Unit";"Roach";"Larva";88;2
"Unit";"Roach";"Larva";88;2
"Unit";"Roach";"Larva";88;2
"Unit";"Roach";"Larva";88;2
"Upgrade";"ZergGroundArmorsLevel1";"EvolutionChamber";75;0
"Unit";"Zergling";"Larva";106;1
"Unit";"Zergling";"Larva";106;1
"Unit";"Roach";"Larva";106;2
"Unit";"Roach";"Larva";106;2
"Unit";"Queen";"Hatchery";96;2
"Unit";"Overlord";"Larva";106;0
"Unit";"Overlord";"Larva";106;0
"Unit";"Overlord";"Larva";106;0
"Unit";"Overlord";"Larva";106;0
"Unit";"Roach";"Larva";114;2
"Unit";"Roach";"Larva";114;2
"Unit";"Roach";"Larva";114;2
"Building";"EvolutionChamber";NA;114;0
"Unit";"Overlord";"Larva";114;0
"Building";"CreepTumorQueen";NA;114;0
"Building";"CreepTumor";NA;114;0
"Building";"CreepTumorQueen";NA;124;0
"Unit";"Queen";"Hatchery";114;2
"Unit";"Queen";"Hatchery";114;2
"Unit";"Overlord";"Larva";125;0
"Building";"Hatchery";NA;106;0
"Unit";"Overlord";"Larva";125;0
"Building";"CreepTumor";NA;131;0
"Building";"CreepTumorQueen";NA;134;0
"Building";"CreepTumor";NA;134;0
"Building";"CreepTumor";NA;134;0
"Building";"CreepTumorQueen";NA;134;0
"Upgrade";"GlialReconstitution";"RoachWarren";114;0
"Unit";"Overlord";"Larva";134;0
"Unit";"Queen";"Hatchery";134;2
"Building";"CreepTumor";NA;138;0
"Building";"CreepTumor";NA;138;0
"Building";"CreepTumor";NA;138;0
"Unit";"Roach";"Larva";138;2
"Unit";"Roach";"Larva";138;2
"Unit";"Roach";"Larva";145;2
"Unit";"Roach";"Larva";145;2
"Unit";"Roach";"Larva";145;2
"Building";"Extractor";NA;145;0
"Unit";"Overlord";"Larva";145;0
"Unit";"Overlord";"Larva";145;0
"Unit";"Roach";"Larva";147;2
"Building";"CreepTumorQueen";NA;157;0
"Unit";"Roach";"Larva";157;2
"Unit";"Roach";"Larva";157;2
"Unit";"Roach";"Larva";157;2
"Unit";"Roach";"Larva";157;2
"Unit";"Roach";"Larva";157;2
"Unit";"Roach";"Larva";157;2
"Unit";"Roach";"Larva";157;2
"Unit";"Roach";"Larva";157;2
"Unit";"Overlord";"Larva";159;0
"Upgrade";"ZergMissileWeaponsLevel1";"EvolutionChamber";134;0
"Unit";"Overlord";"Larva";175;0
"Unit";"Overlord";"Larva";175;0
"Unit";"Overlord";"Larva";175;0
"Unit";"Queen";"Hatchery";175;2
"Unit";"Roach";"Larva";185;2
"Unit";"Roach";"Larva";185;2
"Unit";"Roach";"Larva";185;2
"Unit";"Roach";"Larva";185;2
"Unit";"Roach";"Larva";185;2
"Unit";"Roach";"Larva";185;2
"Unit";"Roach";"Larva";187;2
"Unit";"Roach";"Larva";187;2
"Unit";"Roach";"Larva";187;2
"Unit";"Roach";"Larva";210;2
"Unit";"Roach";"Larva";210;2
"Unit";"Roach";"Larva";210;2
"Unit";"Roach";"Larva";210;2
"Unit";"Roach";"Larva";210;2
"Unit";"Roach";"Larva";210;2
"Unit";"Roach";"Larva";210;2
"Unit";"Roach";"Larva";210;2
"Unit";"Roach";"Larva";210;2
"Unit";"Roach";"Larva";210;2
"Unit";"Roach";"Larva";210;2
"Unit";"Roach";"Larva";210;2
"Unit";"Roach";"Larva";210;2
"Unit";"Roach";"Larva";210;2
"Building";"Hatchery";NA;185;0
"Building";"HydraliskDen";NA;238;0
"Building";"Extractor";NA;245;0
"Building";"Extractor";NA;245;0
"Building";"Extractor";NA;245;0
"Upgrade";"ZergMissileWeaponsLevel2";"EvolutionChamber";199;0
"Building";"SpineCrawler";NA;245;0
"Building";"SpineCrawler";NA;245;0
"Building";"SpineCrawler";NA;245;0
"Building";"SpineCrawler";NA;245;0
"Unit";"Roach";"Larva";249;2
"Unit";"Roach";"Larva";249;2
"Unit";"Roach";"Larva";249;2
"Unit";"Roach";"Larva";249;2
"Unit";"Roach";"Larva";249;2
"Unit";"Roach";"Larva";249;2
"Unit";"Roach";"Larva";249;2
"Unit";"Roach";"Larva";249;2
"Unit";"Roach";"Larva";249;2
"Unit";"Roach";"Larva";249;2
"Unit";"Roach";"Larva";249;2
"Unit";"Roach";"Larva";249;2
"Unit";"Roach";"Larva";249;2
"Unit";"Roach";"Larva";249;2
"Unit";"Roach";"Larva";249;2
"Unit";"Roach";"Larva";249;2
"Unit";"Roach";"Larva";249;2
"Building";"CreepTumor";NA;283;0
"Building";"CreepTumor";NA;291;0
"Unit";"Hydralisk";"Larva";283;2
"Unit";"Hydralisk";"Larva";283;2
"Unit";"Hydralisk";"Larva";283;2
"Unit";"Hydralisk";"Larva";283;2
"Unit";"Hydralisk";"Larva";283;2
"Unit";"Hydralisk";"Larva";283;2
"Unit";"Hydralisk";"Larva";291;2
"Unit";"Hydralisk";"Larva";291;2
"Building";"CreepTumorQueen";NA;308;0
"Building";"CreepTumorQueen";NA;308;0
"Building";"SpineCrawler";NA;291;0
"Upgrade";"EvolveMuscularAugments";"HydraliskDen";291;0
"Building";"SpineCrawler";NA;291;0
"Building";"SpineCrawler";NA;291;0
"Building";"SpineCrawler";NA;303;0
"Building";"CreepTumorQueen";NA;315;0
"Building";"CreepTumorQueen";NA;315;0
"Building";"CreepTumor";NA;315;0
"Building";"CreepTumor";NA;315;0
"Unit";"Hydralisk";"Larva";308;2
"Unit";"Hydralisk";"Larva";308;2
"Unit";"Hydralisk";"Larva";308;2
"Unit";"Hydralisk";"Larva";308;2
"Unit";"Overlord";"Larva";315;0
"Building";"CreepTumorQueen";NA;323;0
"Building";"CreepTumor";NA;315;0
"Building";"CreepTumorQueen";NA;323;0
"Building";"CreepTumor";NA;323;0
"Building";"CreepTumorQueen";NA;323;0
"Unit";"Hydralisk";"Larva";315;2
"Unit";"Hydralisk";"Larva";315;2
"Unit";"Hydralisk";"Larva";315;2
"Building";"CreepTumorQueen";NA;323;0
"Unit";"Overlord";"Larva";323;0
"Unit";"Overlord";"Larva";323;0
"Unit";"Hydralisk";"Larva";323;2
"Unit";"Hydralisk";"Larva";323;2
"Unit";"Hydralisk";"Larva";323;2
"Upgrade";"ZergGroundArmorsLevel2";"EvolutionChamber";291;0
"Unit";"Overlord";"Larva";329;0
"Unit";"Overlord";"Larva";329;0
"Unit";"Zergling";"Larva";329;1
"Unit";"Zergling";"Larva";329;1
"Unit";"Zergling";"Larva";329;1
"Unit";"Zergling";"Larva";329;1
"Unit";"Zergling";"Larva";329;1
"Unit";"Zergling";"Larva";329;1
"Unit";"Zergling";"Larva";329;1
"Unit";"Zergling";"Larva";329;1
"Unit";"Zergling";"Larva";329;1
"Unit";"Zergling";"Larva";329;1
"Unit";"Zergling";"Larva";329;1
"Unit";"Zergling";"Larva";329;1
"Unit";"Zergling";"Larva";329;1
"Unit";"Zergling";"Larva";329;1
"Upgrade";"EvolveGroovedSpines";"HydraliskDen";323;0
"Building";"Hatchery";NA;315;0
"Unit";"Roach";"Larva";349;2
"Unit";"Roach";"Larva";349;2
"Unit";"Roach";"Larva";349;2
"Unit";"Roach";"Larva";349;2
"Unit";"Roach";"Larva";349;2
"Unit";"Roach";"Larva";349;2
"Unit";"Roach";"Larva";349;2
"Unit";"Roach";"Larva";349;2
"Unit";"Roach";"Larva";349;2
"Unit";"Roach";"Larva";349;2
"Unit";"Roach";"Larva";349;2
"Unit";"Roach";"Larva";349;2
"Unit";"Roach";"Larva";349;2
"Unit";"Roach";"Larva";349;2
"Building";"CreepTumor";NA;349;0
"Building";"CreepTumor";NA;377;0
"Building";"CreepTumor";NA;377;0
"Unit";"Hydralisk";"Larva";349;2
"Building";"CreepTumor";NA;377;0
"Unit";"Hydralisk";"Larva";349;2
"Unit";"Hydralisk";"Larva";349;2
"Unit";"Hydralisk";"Larva";349;2
"Unit";"Hydralisk";"Larva";349;2
"Unit";"Hydralisk";"Larva";349;2
"Building";"CreepTumor";NA;377;0
"Building";"CreepTumor";NA;399;0
"Building";"CreepTumor";NA;399;0
"Building";"CreepTumor";NA;399;0
"Building";"CreepTumorQueen";NA;399;0
"Building";"CreepTumorQueen";NA;399;0
"Building";"CreepTumor";NA;399;0
"Building";"CreepTumor";NA;399;0
"Building";"CreepTumor";NA;399;0
"Building";"CreepTumor";NA;399;0
"Unit";"Hydralisk";"Larva";399;2
"Unit";"Hydralisk";"Larva";399;2
"Unit";"Hydralisk";"Larva";399;2
"Unit";"Hydralisk";"Larva";399;2
"Unit";"Hydralisk";"Larva";399;2
"Unit";"Hydralisk";"Larva";399;2
"Unit";"Hydralisk";"Larva";399;2
"Unit";"Hydralisk";"Larva";399;2
"Building";"InfestationPit";NA;399;0
"Unit";"Zergling";"Larva";415;1
"Unit";"Zergling";"Larva";415;1
"Unit";"Zergling";"Larva";415;1
"Unit";"Zergling";"Larva";415;1
"Unit";"Zergling";"Larva";415;1
"Unit";"Zergling";"Larva";415;1
"Unit";"Zergling";"Larva";415;1
"Unit";"Zergling";"Larva";415;1
"Unit";"Zergling";"Larva";415;1
"Unit";"Zergling";"Larva";415;1
"Unit";"Zergling";"Larva";415;1
"Unit";"Zergling";"Larva";415;1
"Unit";"Zergling";"Larva";415;1
"Unit";"Zergling";"Larva";415;1
"Unit";"Zergling";"Larva";415;1
"Unit";"Zergling";"Larva";415;1
"Unit";"Zergling";"Larva";415;1
"Unit";"Zergling";"Larva";415;1
"Unit";"Zergling";"Larva";415;1
"Unit";"Zergling";"Larva";415;1
"Unit";"Zergling";"Larva";415;1
"Unit";"Zergling";"Larva";415;1
"Unit";"Zergling";"Larva";415;1
"Unit";"Zergling";"Larva";415;1
"Unit";"Zergling";"Larva";415;1
"Unit";"Zergling";"Larva";415;1
"Unit";"Zergling";"Larva";415;1
"Unit";"Zergling";"Larva";415;1
"Unit";"Zergling";"Larva";415;1
"Unit";"Zergling";"Larva";415;1
"Unit";"Roach";"Larva";415;2
"Unit";"Roach";"Larva";415;2
"Unit";"Roach";"Larva";415;2
"Unit";"Roach";"Larva";415;2
"Unit";"Roach";"Larva";415;2
"Unit";"Roach";"Larva";415;2
"Unit";"Roach";"Larva";415;2
"Unit";"Roach";"Larva";415;2
"Unit";"Hydralisk";"Larva";415;2
"Unit";"Hydralisk";"Larva";415;2
"Unit";"Hydralisk";"Larva";415;2
"Unit";"Hydralisk";"Larva";415;2
"Unit";"Hydralisk";"Larva";415;2
"Unit";"Hydralisk";"Larva";415;2
"Upgrade";"ZergMeleeWeaponsLevel1";"EvolutionChamber";399;0
"Unit";"Zergling";"Larva";445;1
"Unit";"Zergling";"Larva";445;1
"Unit";"Zergling";"Larva";445;1
"Unit";"Zergling";"Larva";445;1
"Unit";"Zergling";"Larva";445;1
"Unit";"Zergling";"Larva";445;1
"Unit";"Zergling";"Larva";445;1
"Unit";"Zergling";"Larva";445;1
"Unit";"Hydralisk";"Larva";445;2
"Unit";"Hydralisk";"Larva";445;2
"Unit";"Hydralisk";"Larva";445;2
"Unit";"Hydralisk";"Larva";445;2
"Building";"CreepTumor";NA;473;0
"Unit";"Queen";"Hatchery";415;2
"Unit";"Queen";"Hatchery";415;2
"Unit";"Queen";"Hatchery";473;2
"Building";"CreepTumor";NA;493;0
"Unit";"Zergling";"Larva";491;1
"Unit";"Zergling";"Larva";491;1
"Unit";"Zergling";"Larva";493;1
"Unit";"Zergling";"Larva";493;1
"Unit";"Zergling";"Larva";493;1
"Unit";"Zergling";"Larva";493;1
"Unit";"Zergling";"Larva";493;1
"Unit";"Zergling";"Larva";493;1
"Unit";"Zergling";"Larva";503;1
"Unit";"Zergling";"Larva";503;1
"Unit";"Zergling";"Larva";503;1
"Unit";"Zergling";"Larva";503;1
"Unit";"Zergling";"Larva";503;1
"Unit";"Zergling";"Larva";503;1
"Unit";"Zergling";"Larva";503;1
"Unit";"Zergling";"Larva";503;1
"Unit";"Zergling";"Larva";503;1
"Unit";"Zergling";"Larva";503;1
"Unit";"Zergling";"Larva";503;1
"Unit";"Zergling";"Larva";503;1
"Unit";"Zergling";"Larva";503;1
"Unit";"Zergling";"Larva";503;1
"Unit";"Zergling";"Larva";503;1
"Unit";"Zergling";"Larva";503;1
"Unit";"Zergling";"Larva";503;1
"Unit";"Zergling";"Larva";503;1
"Unit";"Zergling";"Larva";503;1
"Unit";"Zergling";"Larva";503;1
"Unit";"Zergling";"Larva";503;1
"Unit";"Zergling";"Larva";503;1
"Unit";"Zergling";"Larva";503;1
"Unit";"Zergling";"Larva";503;1
"Unit";"Zergling";"Larva";503;1
"Unit";"Zergling";"Larva";503;1
"Unit";"Zergling";"Larva";503;1
"Unit";"Zergling";"Larva";503;1
"Unit";"Zergling";"Larva";503;1
"Unit";"Zergling";"Larva";503;1
"Unit";"Hydralisk";"Larva";503;2
"Unit";"Hydralisk";"Larva";503;2
"Unit";"Hydralisk";"Larva";503;2
"Unit";"Hydralisk";"Larva";503;2
"Unit";"Hydralisk";"Larva";503;2
"Unit";"Zergling";"Larva";503;1
"Unit";"Zergling";"Larva";503;1
"Unit";"Zergling";"Larva";503;1
"Unit";"Zergling";"Larva";503;1
"Unit";"Zergling";"Larva";503;1
"Unit";"Zergling";"Larva";503;1
"Unit";"Zergling";"Larva";503;1
"Unit";"Zergling";"Larva";503;1
"Building";"Extractor";NA;533;0
"Building";"CreepTumor";NA;551;0
"Building";"CreepTumor";NA;551;0
"Building";"CreepTumor";NA;551;0
"Building";"CreepTumor";NA;551;0
"Building";"CreepTumor";NA;551;0
"Unit";"Roach";"Larva";551;2
"Unit";"Roach";"Larva";551;2
"Unit";"Roach";"Larva";551;2
"Unit";"Roach";"Larva";551;2
"Unit";"Roach";"Larva";551;2
"Unit";"Roach";"Larva";551;2
"Building";"CreepTumor";NA;551;0
"Building";"CreepTumor";NA;563;0
"Building";"CreepTumor";NA;563;0
"Building";"CreepTumor";NA;567;0
"Building";"CreepTumorQueen";NA;570;0
"Building";"CreepTumorQueen";NA;570;0
"Building";"CreepTumorQueen";NA;570;0
"Building";"CreepTumor";NA;570;0
"Building";"CreepTumorQueen";NA;570;0
"Building";"CreepTumorQueen";NA;570;0
"Building";"CreepTumorQueen";NA;570;0
"Unit";"Hydralisk";"Larva";567;2
"Building";"CreepTumorQueen";NA;570;0
"Unit";"Hydralisk";"Larva";567;2
"Unit";"Hydralisk";"Larva";567;2
"Unit";"Hydralisk";"Larva";567;2
"Unit";"Hydralisk";"Larva";567;2
"Unit";"Hydralisk";"Larva";567;2
