"type";"unit_name";"on_building";"total_supply";"supply"
"Unit";"Overlord";"Larva";13;0
"Building";"Extractor";NA;18;0
"Unit";"Overlord";"Larva";21;0
"Building";"SpawningPool";NA;19;0
"Building";"Hatchery";NA;17;0
"Unit";"Zergling";"Larva";23;1
"Unit";"Zergling";"Larva";23;1
"Unit";"Zergling";"Larva";23;1
"Unit";"Zergling";"Larva";23;1
"Unit";"Queen";"Hatchery";22;2
"Unit";"Queen";"Hatchery";23;2
"Unit";"Overlord";"Larva";36;0
"Unit";"Queen";"Hatchery";36;2
"Unit";"Overlord";"Larva";40;0
"Building";"CreepTumorQueen";NA;40;0
"Building";"Hatchery";NA;28;0
"Unit";"Overlord";"Larva";44;0
"Unit";"Zergling";"Larva";48;1
"Unit";"Zergling";"Larva";48;1
"Unit";"Zergling";"Larva";48;1
"Unit";"Zergling";"Larva";48;1
"Unit";"Zergling";"Larva";48;1
"Unit";"Zergling";"Larva";48;1
"Unit";"Zergling";"Larva";50;1
"Unit";"Zergling";"Larva";50;1
"Unit";"Overlord";"Larva";50;0
"Building";"CreepTumorQueen";NA;61;0
"Unit";"Queen";"Hatchery";50;2
"Building";"CreepTumor";NA;63;0
"Building";"CreepTumorQueen";NA;66;0
"Unit";"Zergling";"Larva";64;1
"Unit";"Zergling";"Larva";64;1
"Unit";"Zergling";"Larva";64;1
"Unit";"Zergling";"Larva";64;1
"Unit";"Queen";"Hatchery";59;2
"Building";"CreepTumor";NA;71;0
"Building";"CreepTumor";NA;75;0
"Unit";"Zergling";"Larva";71;1
"Unit";"Zergling";"Larva";71;1
"Unit";"Zergling";"Larva";71;1
"Unit";"Zergling";"Larva";71;1
"Unit";"Zergling";"Larva";71;1
"Unit";"Zergling";"Larva";71;1
"Unit";"Zergling";"Larva";71;1
"Unit";"Zergling";"Larva";71;1
"Unit";"Queen";"Hatchery";66;2
"Unit";"Overlord";"Larva";77;0
"Unit";"Overlord";"Larva";77;0
"Building";"BanelingNest";NA;64;0
"Unit";"Queen";"Hatchery";71;2
"Building";"Extractor";NA;79;0
"Building";"Extractor";NA;79;0
"Building";"EvolutionChamber";NA;87;0
"Building";"EvolutionChamber";NA;87;0
"Building";"CreepTumor";NA;95;0
"Building";"SporeCrawler";NA;89;0
"Building";"SporeCrawler";NA;89;0
"Building";"SporeCrawler";NA;89;0
"Unit";"Overlord";"Larva";97;0
"Building";"CreepTumorQueen";NA;104;0
"Unit";"Overlord";"Larva";97;0
"Building";"CreepTumorQueen";NA;104;0
"Building";"CreepTumor";NA;104;0
"Building";"Extractor";NA;104;0
"Building";"CreepTumorQueen";NA;111;0
"Building";"CreepTumorQueen";NA;111;0
"Building";"CreepTumorQueen";NA;111;0
"Building";"CreepTumorQueen";NA;111;0
"Building";"Extractor";NA;111;0
"Building";"CreepTumor";NA;111;0
"Building";"CreepTumor";NA;111;0
"Building";"Extractor";NA;111;0
"Unit";"Baneling";"Zergling";111;0
"Unit";"Baneling";"Zergling";111;0
"Unit";"Baneling";"Zergling";111;0
"Unit";"Baneling";"Zergling";111;0
"Unit";"Baneling";"Zergling";111;0
"Unit";"Zergling";"Larva";111;1
"Unit";"Zergling";"Larva";111;1
"Unit";"Zergling";"Larva";111;1
"Unit";"Zergling";"Larva";111;1
"Unit";"Zergling";"Larva";111;1
"Unit";"Zergling";"Larva";111;1
"Building";"CreepTumor";NA;111;0
"Unit";"Zergling";"Larva";111;1
"Unit";"Zergling";"Larva";111;1
"Building";"CreepTumor";NA;111;0
"Building";"RoachWarren";NA;111;0
"Building";"CreepTumorQueen";NA;119;0
"Unit";"Overlord";"Larva";131;0
"Unit";"Overlord";"Larva";131;0
"Building";"HydraliskDen";NA;131;0
"Building";"CreepTumor";NA;131;0
"Building";"CreepTumor";NA;131;0
"Building";"CreepTumor";NA;131;0
"Building";"CreepTumor";NA;137;0
"Building";"CreepTumor";NA;137;0
"Building";"CreepTumor";NA;137;0
"Building";"CreepTumor";NA;137;0
"Building";"CreepTumorQueen";NA;137;0
"Building";"CreepTumorQueen";NA;137;0
"Building";"Hatchery";NA;111;0
"Building";"CreepTumorQueen";NA;137;0
"Building";"CreepTumorQueen";NA;137;0
"Building";"CreepTumorQueen";NA;137;0
"Unit";"Roach";"Larva";137;2
"Unit";"Roach";"Larva";137;2
"Unit";"Overlord";"Larva";137;0
"Unit";"Roach";"Larva";137;2
"Unit";"Overlord";"Larva";137;0
"Unit";"Overlord";"Larva";137;0
"Unit";"Roach";"Larva";137;2
"Unit";"Overlord";"Larva";137;0
"Upgrade";"ZergGroundArmorsLevel1";"EvolutionChamber";111;0
"Building";"Hatchery";NA;124;0
"Upgrade";"ZergMissileWeaponsLevel1";"EvolutionChamber";111;0
"Building";"InfestationPit";NA;137;0
"Building";"CreepTumorQueen";NA;153;0
"Upgrade";"GlialReconstitution";"RoachWarren";137;0
"Unit";"Queen";"Hatchery";137;2
"Building";"CreepTumor";NA;153;0
"Building";"CreepTumor";NA;153;0
"Building";"CreepTumor";NA;153;0
"Building";"CreepTumor";NA;153;0
"Building";"CreepTumor";NA;153;0
"Building";"CreepTumor";NA;153;0
"Building";"CreepTumor";NA;153;0
"Building";"CreepTumor";NA;153;0
"Building";"CreepTumor";NA;153;0
"Building";"CreepTumorQueen";NA;161;0
"Building";"CreepTumor";NA;159;0
"Building";"CreepTumor";NA;159;0
"Building";"CreepTumor";NA;161;0
"Unit";"Overlord";"Larva";161;0
"Building";"SpineCrawler";NA;153;0
"Unit";"Hydralisk";"Larva";161;2
"Building";"SpineCrawler";NA;153;0
"Unit";"Hydralisk";"Larva";161;2
"Unit";"Hydralisk";"Larva";161;2
"Unit";"Hydralisk";"Larva";161;2
"Unit";"Hydralisk";"Larva";161;2
"Unit";"Hydralisk";"Larva";161;2
"Unit";"Hydralisk";"Larva";161;2
"Building";"SpineCrawler";NA;153;0
"Unit";"Hydralisk";"Larva";161;2
"Building";"CreepTumor";NA;161;0
"Building";"CreepTumor";NA;161;0
"Building";"CreepTumor";NA;161;0
"Building";"Extractor";NA;161;0
"Building";"Extractor";NA;161;0
"Building";"Hatchery";NA;137;0
"Building";"Hatchery";NA;137;0
"Building";"CreepTumor";NA;181;0
"Building";"CreepTumor";NA;181;0
"Building";"CreepTumor";NA;181;0
"Unit";"Roach";"Larva";181;2
"Building";"CreepTumor";NA;181;0
"Unit";"Roach";"Larva";181;2
"Unit";"Roach";"Larva";181;2
"Unit";"Roach";"Larva";181;2
"Unit";"Roach";"Larva";181;2
"Building";"CreepTumor";NA;181;0
"Building";"CreepTumor";NA;181;0
"Building";"CreepTumor";NA;181;0
"Building";"CreepTumor";NA;187;0
"Building";"CreepTumor";NA;187;0
"Building";"CreepTumor";NA;187;0
"Building";"CreepTumorQueen";NA;197;0
"Building";"CreepTumor";NA;189;0
"Building";"CreepTumor";NA;189;0
"Building";"CreepTumorQueen";NA;197;0
"Building";"CreepTumor";NA;197;0
"Building";"CreepTumor";NA;197;0
"Building";"CreepTumor";NA;197;0
"Building";"CreepTumor";NA;197;0
"Upgrade";"EvolveGroovedSpines";"HydraliskDen";181;0
"Building";"CreepTumor";NA;197;0
"Building";"CreepTumor";NA;197;0
"Building";"CreepTumor";NA;197;0
"Building";"SporeCrawler";NA;197;0
"Building";"SporeCrawler";NA;197;0
"Building";"CreepTumor";NA;197;0
"Building";"CreepTumor";NA;197;0
"Building";"CreepTumor";NA;197;0
"Unit";"Overlord";"Larva";197;0
"Unit";"Overlord";"Larva";197;0
"Unit";"Overlord";"Larva";197;0
"Unit";"Overlord";"Larva";197;0
"Unit";"Overlord";"Larva";197;0
"Unit";"Overlord";"Larva";197;0
"Unit";"Overlord";"Larva";197;0
"Building";"CreepTumor";NA;197;0
"Building";"CreepTumor";NA;197;0
"Building";"CreepTumor";NA;197;0
"Building";"Spire";NA;181;0
"Building";"CreepTumor";NA;197;0
"Building";"CreepTumor";NA;197;0
"Building";"CreepTumor";NA;197;0
"Building";"Extractor";NA;197;0
"Building";"Extractor";NA;197;0
"Unit";"Hydralisk";"Larva";197;2
"Unit";"Hydralisk";"Larva";197;2
"Unit";"Hydralisk";"Larva";197;2
"Unit";"Hydralisk";"Larva";197;2
"Unit";"Hydralisk";"Larva";197;2
"Unit";"Hydralisk";"Larva";197;2
"Unit";"Hydralisk";"Larva";197;2
"Unit";"Hydralisk";"Larva";197;2
"Building";"CreepTumor";NA;197;0
"Building";"CreepTumor";NA;197;0
"Building";"SporeCrawler";NA;197;0
"Building";"CreepTumor";NA;213;0
"Building";"CreepTumor";NA;213;0
"Building";"CreepTumor";NA;213;0
"Building";"CreepTumor";NA;213;0
"Building";"CreepTumor";NA;213;0
"Unit";"Viper";"Larva";197;3
"Unit";"Viper";"Larva";197;3
"Unit";"Viper";"Larva";197;3
"Unit";"Viper";"Larva";197;3
"Unit";"Viper";"Larva";197;3
"Unit";"Viper";"Larva";197;3
"Building";"CreepTumor";NA;213;0
"Building";"CreepTumor";NA;213;0
"Building";"CreepTumor";NA;213;0
"Building";"SpineCrawler";NA;197;0
"Unit";"Overlord";"Larva";213;0
"Upgrade";"ZergMissileWeaponsLevel2";"EvolutionChamber";197;0
"Upgrade";"ZergGroundArmorsLevel2";"EvolutionChamber";197;0
"Unit";"Roach";"Larva";231;2
"Unit";"Roach";"Larva";231;2
"Unit";"Roach";"Larva";231;2
"Unit";"Roach";"Larva";231;2
"Unit";"Hydralisk";"Larva";231;2
"Unit";"Hydralisk";"Larva";231;2
"Unit";"Hydralisk";"Larva";231;2
"Unit";"Hydralisk";"Larva";231;2
"Unit";"Hydralisk";"Larva";231;2
"Unit";"Hydralisk";"Larva";231;2
"Unit";"Hydralisk";"Larva";231;2
"Unit";"Hydralisk";"Larva";231;2
"Unit";"Overlord";"Larva";231;0
"Unit";"Roach";"Larva";255;2
"Unit";"Roach";"Larva";255;2
"Unit";"Roach";"Larva";255;2
"Unit";"Roach";"Larva";255;2
"Unit";"Roach";"Larva";255;2
"Unit";"Roach";"Larva";255;2
"Unit";"Roach";"Larva";255;2
"Unit";"Roach";"Larva";255;2
"Unit";"Roach";"Larva";255;2
"Unit";"Roach";"Larva";255;2
"Unit";"Roach";"Larva";255;2
"Unit";"Roach";"Larva";255;2
"Unit";"Roach";"Larva";255;2
"Unit";"Roach";"Larva";255;2
"Unit";"Roach";"Larva";255;2
"Unit";"Roach";"Larva";255;2
"Unit";"Roach";"Larva";255;2
"Unit";"Roach";"Larva";255;2
"Unit";"Roach";"Larva";255;2
"Unit";"Roach";"Larva";255;2
"Unit";"Roach";"Larva";255;2
"Unit";"Roach";"Larva";255;2
"Unit";"Roach";"Larva";255;2
"Unit";"Roach";"Larva";255;2
"Unit";"Roach";"Larva";255;2
"Unit";"Roach";"Larva";255;2
"Unit";"Roach";"Larva";255;2
"Unit";"Roach";"Larva";255;2
"Unit";"Roach";"Larva";255;2
"Unit";"Roach";"Larva";255;2
"Unit";"Roach";"Larva";255;2
"Unit";"Roach";"Larva";255;2
"Unit";"Roach";"Larva";255;2
"Unit";"Roach";"Larva";255;2
"Unit";"Hydralisk";"Larva";255;2
"Unit";"Hydralisk";"Larva";255;2
"Unit";"Hydralisk";"Larva";255;2
"Unit";"Hydralisk";"Larva";255;2
"Unit";"Hydralisk";"Larva";255;2
"Unit";"Hydralisk";"Larva";255;2
"Unit";"Roach";"Larva";301;2
"Unit";"Roach";"Larva";301;2
"Unit";"Roach";"Larva";301;2
"Unit";"Hydralisk";"Larva";323;2
"Unit";"Hydralisk";"Larva";323;2
"Unit";"Hydralisk";"Larva";323;2
"Unit";"Hydralisk";"Larva";323;2
"Unit";"Corruptor";"Larva";341;2
"Unit";"Corruptor";"Larva";341;2
"Unit";"Corruptor";"Larva";341;2
"Unit";"Corruptor";"Larva";341;2
"Unit";"Corruptor";"Larva";341;2
"Unit";"Corruptor";"Larva";341;2
"Unit";"Corruptor";"Larva";341;2
"Unit";"Corruptor";"Larva";341;2
"Unit";"Corruptor";"Larva";341;2
"Building";"CreepTumor";NA;367;0
"Building";"CreepTumor";NA;367;0
"Unit";"Corruptor";"Larva";349;2
"Unit";"Corruptor";"Larva";349;2
"Unit";"Corruptor";"Larva";349;2
"Unit";"Corruptor";"Larva";349;2
"Building";"Extractor";NA;375;0
"Building";"Extractor";NA;375;0
"Building";"CreepTumor";NA;375;0
"Building";"CreepTumor";NA;375;0
"Building";"CreepTumor";NA;375;0
"Building";"CreepTumor";NA;375;0
"Building";"Hatchery";NA;349;0
"Building";"Spire";NA;349;0
"Building";"Hatchery";NA;367;0
"Upgrade";"ZergMissileWeaponsLevel3";"EvolutionChamber";341;0
"Upgrade";"ZergGroundArmorsLevel3";"EvolutionChamber";341;0
"Upgrade";"EvolveMuscularAugments";"HydraliskDen";375;0
"Unit";"Corruptor";"Larva";375;2
"Unit";"Corruptor";"Larva";375;2
"Unit";"Queen";"Hatchery";375;2
"Unit";"Hydralisk";"Larva";382;2
"Unit";"Hydralisk";"Larva";382;2
"Unit";"Hydralisk";"Larva";382;2
"Unit";"Hydralisk";"Larva";382;2
"Unit";"Hydralisk";"Larva";382;2
"Unit";"Hydralisk";"Larva";382;2
"Unit";"Hydralisk";"Larva";382;2
"Unit";"Hydralisk";"Larva";382;2
"Unit";"Hydralisk";"Larva";382;2
"Unit";"Hydralisk";"Larva";382;2
"Unit";"Hydralisk";"Larva";382;2
"Unit";"Hydralisk";"Larva";382;2
"Unit";"Hydralisk";"Larva";382;2
"Unit";"Hydralisk";"Larva";382;2
"Building";"SpineCrawler";NA;382;0
"Unit";"Corruptor";"Larva";382;2
"Unit";"Corruptor";"Larva";382;2
"Unit";"Corruptor";"Larva";382;2
"Unit";"Corruptor";"Larva";382;2
"Unit";"Corruptor";"Larva";382;2
"Unit";"Corruptor";"Larva";382;2
"Unit";"Roach";"Larva";428;2
"Unit";"Roach";"Larva";428;2
"Unit";"Roach";"Larva";436;2
"Unit";"Roach";"Larva";440;2
"Unit";"Roach";"Larva";440;2
"Unit";"Roach";"Larva";440;2
"Unit";"Roach";"Larva";440;2
"Unit";"Roach";"Larva";440;2
"Unit";"Roach";"Larva";440;2
"Unit";"Roach";"Larva";440;2
"Unit";"Roach";"Larva";440;2
"Unit";"Roach";"Larva";440;2
"Upgrade";"ZergMeleeWeaponsLevel1";"EvolutionChamber";416;0
"Unit";"Corruptor";"Larva";458;2
"Unit";"Corruptor";"Larva";458;2
"Unit";"Corruptor";"Larva";458;2
"Unit";"Corruptor";"Larva";458;2
"Unit";"Corruptor";"Larva";458;2
"Unit";"Corruptor";"Larva";458;2
"Unit";"Corruptor";"Larva";458;2
"Unit";"Corruptor";"Larva";458;2
"Unit";"Corruptor";"Larva";458;2
"Unit";"Corruptor";"Larva";458;2
"Unit";"Corruptor";"Larva";458;2
"Unit";"Corruptor";"Larva";458;2
"Unit";"Corruptor";"Larva";458;2
"Unit";"Corruptor";"Larva";458;2
"Unit";"Corruptor";"Larva";458;2
"Unit";"Corruptor";"Larva";458;2
"Unit";"Corruptor";"Larva";458;2
"Unit";"Corruptor";"Larva";458;2
"Unit";"Corruptor";"Larva";458;2
"Unit";"Hydralisk";"Larva";458;2
"Unit";"Hydralisk";"Larva";458;2
"Unit";"Hydralisk";"Larva";458;2
"Unit";"Hydralisk";"Larva";458;2
"Unit";"Hydralisk";"Larva";458;2
"Unit";"Hydralisk";"Larva";458;2
"Unit";"Hydralisk";"Larva";458;2
"Unit";"Hydralisk";"Larva";458;2
"Unit";"Hydralisk";"Larva";458;2
"Unit";"Hydralisk";"Larva";458;2
"Unit";"Hydralisk";"Larva";458;2
"Unit";"Hydralisk";"Larva";458;2
"Unit";"Hydralisk";"Larva";520;2
"Unit";"Hydralisk";"Larva";520;2
"Unit";"Hydralisk";"Larva";520;2
"Unit";"Hydralisk";"Larva";520;2
"Unit";"Hydralisk";"Larva";520;2
"Unit";"Hydralisk";"Larva";520;2
"Unit";"Hydralisk";"Larva";520;2
"Unit";"Hydralisk";"Larva";520;2
"Unit";"Roach";"Larva";520;2
"Unit";"Roach";"Larva";520;2
"Unit";"Roach";"Larva";520;2
