"type";"unit_name";"on_building";"total_supply";"supply"
"Unit";"Overlord";"Larva";12;0
"Building";"Extractor";NA;18;0
"Unit";"Overlord";"Larva";21;0
"Building";"SpawningPool";NA;19;0
"Building";"Hatchery";NA;17;0
"Unit";"Zergling";"Larva";22;1
"Unit";"Zergling";"Larva";22;1
"Unit";"Zergling";"Larva";22;1
"Unit";"Zergling";"Larva";22;1
"Unit";"Queen";"Hatchery";22;2
"Unit";"Queen";"Hatchery";22;2
"Unit";"Overlord";"Larva";37;0
"Building";"CreepTumorQueen";NA;39;0
"Building";"CreepTumorQueen";NA;39;0
"Unit";"Overlord";"Larva";40;0
"Unit";"Queen";"Hatchery";39;2
"Unit";"Queen";"Hatchery";39;2
"Building";"Hatchery";NA;35;0
"Building";"CreepTumorQueen";NA;48;0
"Building";"CreepTumor";NA;48;0
"Building";"CreepTumorQueen";NA;50;0
"Building";"CreepTumor";NA;50;0
"Building";"RoachWarren";NA;42;0
"Building";"SporeCrawler";NA;50;0
"Building";"SporeCrawler";NA;54;0
"Building";"Extractor";NA;55;0
"Building";"CreepTumorQueen";NA;57;0
"Building";"CreepTumorQueen";NA;57;0
"Building";"CreepTumor";NA;57;0
"Building";"CreepTumor";NA;57;0
"Building";"CreepTumorQueen";NA;57;0
"Building";"CreepTumor";NA;57;0
"Unit";"Queen";"Hatchery";54;2
"Unit";"Roach";"Larva";58;2
"Unit";"Roach";"Larva";58;2
"Unit";"Roach";"Larva";58;2
"Building";"SporeCrawler";NA;59;0
"Unit";"Overlord";"Larva";62;0
"Unit";"Overlord";"Larva";71;0
"Building";"CreepTumor";NA;71;0
"Building";"CreepTumor";NA;71;0
"Building";"EvolutionChamber";NA;62;0
"Building";"CreepTumor";NA;71;0
"Building";"CreepTumor";NA;71;0
"Building";"CreepTumor";NA;71;0
"Unit";"Queen";"Hatchery";62;2
"Unit";"Roach";"Larva";71;2
"Unit";"Roach";"Larva";71;2
"Unit";"Roach";"Larva";71;2
"Unit";"Overlord";"Larva";71;0
"Unit";"Overlord";"Larva";71;0
"Building";"CreepTumor";NA;73;0
"Building";"CreepTumor";NA;73;0
"Building";"CreepTumor";NA;73;0
"Building";"CreepTumor";NA;73;0
"Building";"CreepTumorQueen";NA;77;0
"Building";"CreepTumorQueen";NA;77;0
"Building";"CreepTumorQueen";NA;83;0
"Building";"CreepTumorQueen";NA;83;0
"Building";"CreepTumor";NA;85;0
"Building";"Extractor";NA;85;0
"Building";"CreepTumor";NA;92;0
"Building";"CreepTumor";NA;92;0
"Building";"CreepTumor";NA;92;0
"Unit";"Roach";"Larva";88;2
"Building";"CreepTumor";NA;96;0
"Unit";"Roach";"Larva";88;2
"Unit";"Roach";"Larva";88;2
"Unit";"Overlord";"Larva";96;0
"Unit";"Overlord";"Larva";96;0
"Building";"CreepTumorQueen";NA;100;0
"Building";"CreepTumorQueen";NA;102;0
"Building";"CreepTumorQueen";NA;102;0
"Building";"CreepTumorQueen";NA;102;0
"Unit";"Queen";"Hatchery";85;2
"Unit";"Overlord";"Larva";102;0
"Unit";"Overlord";"Larva";102;0
"Building";"CreepTumorQueen";NA;104;0
"Building";"Extractor";NA;102;0
"Building";"Extractor";NA;102;0
"Building";"CreepTumorQueen";NA;113;0
"Unit";"Overlord";"Larva";112;0
"Unit";"Overlord";"Larva";112;0
"Building";"CreepTumorQueen";NA;113;0
"Building";"CreepTumor";NA;113;0
"Building";"CreepTumor";NA;114;0
"Building";"CreepTumor";NA;115;0
"Building";"CreepTumor";NA;114;0
"Building";"CreepTumor";NA;115;0
"Building";"CreepTumorQueen";NA;117;0
"Building";"Extractor";NA;112;0
"Building";"CreepTumor";NA;117;0
"Building";"CreepTumor";NA;117;0
"Building";"CreepTumor";NA;117;0
"Building";"CreepTumor";NA;117;0
"Building";"CreepTumor";NA;117;0
"Building";"CreepTumorQueen";NA;122;0
"Building";"EvolutionChamber";NA;119;0
"Unit";"Roach";"Larva";120;2
"Unit";"Roach";"Larva";120;2
"Unit";"Roach";"Larva";120;2
"Unit";"Roach";"Larva";120;2
"Building";"CreepTumor";NA;124;0
"Building";"CreepTumor";NA;124;0
"Building";"CreepTumor";NA;124;0
"Building";"CreepTumor";NA;124;0
"Unit";"Overlord";"Larva";122;0
"Unit";"Overlord";"Larva";122;0
"Building";"CreepTumor";NA;124;0
"Building";"CreepTumor";NA;124;0
"Building";"CreepTumor";NA;124;0
"Building";"CreepTumor";NA;124;0
"Building";"CreepTumor";NA;124;0
"Unit";"Roach";"Larva";122;2
"Unit";"Roach";"Larva";122;2
"Unit";"Roach";"Larva";122;2
"Building";"CreepTumor";NA;124;0
"Building";"CreepTumor";NA;124;0
"Building";"CreepTumor";NA;124;0
"Building";"CreepTumor";NA;124;0
"Building";"BanelingNest";NA;118;0
"Building";"Hatchery";NA;104;0
"Unit";"Roach";"Larva";134;2
"Unit";"Roach";"Larva";134;2
"Unit";"Roach";"Larva";134;2
"Unit";"Zergling";"Larva";138;1
"Unit";"Zergling";"Larva";138;1
"Unit";"Zergling";"Larva";140;1
"Unit";"Zergling";"Larva";140;1
"Unit";"Zergling";"Larva";140;1
"Unit";"Zergling";"Larva";140;1
"Building";"CreepTumorQueen";NA;140;0
"Unit";"Zergling";"Larva";140;1
"Unit";"Zergling";"Larva";140;1
"Unit";"Zergling";"Larva";140;1
"Unit";"Zergling";"Larva";140;1
"Unit";"Zergling";"Larva";140;1
"Unit";"Zergling";"Larva";140;1
"Unit";"Zergling";"Larva";140;1
"Unit";"Zergling";"Larva";140;1
"Unit";"Zergling";"Larva";140;1
"Unit";"Zergling";"Larva";140;1
"Upgrade";"ZergMissileWeaponsLevel1";"EvolutionChamber";111;0
"Unit";"Overlord";"Larva";140;0
"Unit";"Overlord";"Larva";140;0
"Unit";"Baneling";"Zergling";152;0
"Unit";"Baneling";"Zergling";152;0
"Unit";"Baneling";"Zergling";152;0
"Unit";"Baneling";"Zergling";152;0
"Unit";"Baneling";"Zergling";152;0
"Unit";"Baneling";"Zergling";152;0
"Unit";"Zergling";"Larva";158;1
"Unit";"Zergling";"Larva";158;1
"Unit";"Zergling";"Larva";160;1
"Unit";"Zergling";"Larva";160;1
"Unit";"Baneling";"Zergling";162;0
"Unit";"Zergling";"Larva";162;1
"Unit";"Zergling";"Larva";162;1
"Unit";"Zergling";"Larva";162;1
"Unit";"Zergling";"Larva";162;1
"Upgrade";"GlialReconstitution";"RoachWarren";134;0
"Unit";"Roach";"Larva";162;2
"Unit";"Roach";"Larva";162;2
"Unit";"Roach";"Larva";162;2
"Unit";"Roach";"Larva";162;2
"Unit";"Roach";"Larva";162;2
"Building";"CreepTumorQueen";NA;180;0
"Building";"CreepTumorQueen";NA;180;0
"Building";"CreepTumorQueen";NA;180;0
"Building";"CreepTumor";NA;180;0
"Unit";"Roach";"Larva";166;2
"Unit";"Roach";"Larva";180;2
"Unit";"Roach";"Larva";180;2
"Unit";"Zergling";"Larva";180;1
"Unit";"Zergling";"Larva";180;1
"Unit";"Zergling";"Larva";180;1
"Unit";"Zergling";"Larva";180;1
"Building";"CreepTumor";NA;197;0
"Building";"CreepTumor";NA;197;0
"Building";"CreepTumor";NA;197;0
"Unit";"Zergling";"Larva";189;1
"Unit";"Zergling";"Larva";189;1
"Building";"HydraliskDen";NA;180;0
"Unit";"Zergling";"Larva";189;1
"Unit";"Zergling";"Larva";189;1
"Unit";"Zergling";"Larva";191;1
"Unit";"Zergling";"Larva";191;1
"Unit";"Zergling";"Larva";191;1
"Unit";"Zergling";"Larva";191;1
"Unit";"Zergling";"Larva";191;1
"Unit";"Zergling";"Larva";191;1
"Unit";"Zergling";"Larva";191;1
"Unit";"Zergling";"Larva";191;1
"Unit";"Zergling";"Larva";191;1
"Unit";"Zergling";"Larva";191;1
"Unit";"Zergling";"Larva";191;1
"Unit";"Zergling";"Larva";191;1
"Building";"CreepTumor";NA;197;0
"Building";"CreepTumor";NA;197;0
"Building";"CreepTumor";NA;197;0
"Building";"CreepTumor";NA;197;0
"Building";"CreepTumor";NA;197;0
"Building";"CreepTumor";NA;197;0
"Building";"CreepTumor";NA;197;0
"Building";"CreepTumor";NA;197;0
"Building";"Extractor";NA;193;0
"Building";"CreepTumor";NA;197;0
"Building";"CreepTumor";NA;197;0
"Building";"CreepTumorQueen";NA;197;0
"Building";"InfestationPit";NA;180;0
"Unit";"Overlord";"Larva";205;0
"Unit";"Overlord";"Larva";213;0
"Unit";"Baneling";"Zergling";213;0
"Unit";"Baneling";"Zergling";213;0
"Upgrade";"ZergGroundArmorsLevel1";"EvolutionChamber";162;0
"Unit";"Hydralisk";"Larva";213;2
"Unit";"Hydralisk";"Larva";213;2
"Unit";"Hydralisk";"Larva";213;2
"Unit";"Hydralisk";"Larva";213;2
"Unit";"Hydralisk";"Larva";213;2
"Unit";"Hydralisk";"Larva";213;2
"Building";"CreepTumor";NA;217;0
"Building";"CreepTumor";NA;217;0
"Unit";"Overlord";"Larva";217;0
"Unit";"Overlord";"Larva";217;0
"Unit";"Overlord";"Larva";217;0
"Unit";"Zergling";"Larva";217;1
"Unit";"Zergling";"Larva";217;1
"Unit";"Zergling";"Larva";217;1
"Unit";"Zergling";"Larva";217;1
"Unit";"Zergling";"Larva";217;1
"Unit";"Zergling";"Larva";217;1
"Unit";"Zergling";"Larva";217;1
"Unit";"Zergling";"Larva";217;1
"Unit";"Zergling";"Larva";217;1
"Unit";"Zergling";"Larva";217;1
"Unit";"Zergling";"Larva";217;1
"Unit";"Zergling";"Larva";217;1
"Unit";"Zergling";"Larva";229;1
"Unit";"Zergling";"Larva";229;1
"Unit";"Zergling";"Larva";229;1
"Unit";"Zergling";"Larva";229;1
"Unit";"Zergling";"Larva";229;1
"Unit";"Zergling";"Larva";229;1
"Unit";"Zergling";"Larva";229;1
"Unit";"Zergling";"Larva";229;1
"Unit";"Zergling";"Larva";229;1
"Unit";"Zergling";"Larva";229;1
"Unit";"Zergling";"Larva";229;1
"Unit";"Zergling";"Larva";229;1
"Unit";"Zergling";"Larva";229;1
"Unit";"Zergling";"Larva";229;1
"Unit";"Zergling";"Larva";229;1
"Unit";"Zergling";"Larva";229;1
"Unit";"Zergling";"Larva";229;1
"Unit";"Zergling";"Larva";229;1
"Unit";"Zergling";"Larva";229;1
"Unit";"Zergling";"Larva";229;1
"Building";"CreepTumor";NA;241;0
"Building";"CreepTumor";NA;241;0
"Building";"CreepTumor";NA;241;0
"Building";"CreepTumor";NA;241;0
"Building";"CreepTumor";NA;241;0
"Building";"CreepTumor";NA;241;0
"Building";"CreepTumor";NA;241;0
"Building";"CreepTumor";NA;241;0
"Building";"Hatchery";NA;197;0
"Building";"CreepTumor";NA;241;0
"Building";"CreepTumor";NA;241;0
"Building";"CreepTumor";NA;241;0
"Building";"CreepTumor";NA;241;0
"Building";"CreepTumor";NA;241;0
"Building";"CreepTumorQueen";NA;241;0
"Unit";"Zergling";"Larva";241;1
"Unit";"Zergling";"Larva";241;1
"Unit";"Zergling";"Larva";241;1
"Unit";"Zergling";"Larva";241;1
"Unit";"Zergling";"Larva";241;1
"Unit";"Zergling";"Larva";241;1
"Unit";"Zergling";"Larva";241;1
"Unit";"Zergling";"Larva";241;1
"Unit";"Zergling";"Larva";241;1
"Unit";"Zergling";"Larva";241;1
"Unit";"Zergling";"Larva";241;1
"Unit";"Zergling";"Larva";241;1
"Building";"CreepTumor";NA;261;0
"Upgrade";"EvolveMuscularAugments";"HydraliskDen";217;0
"Unit";"Zergling";"Larva";261;1
"Unit";"Zergling";"Larva";261;1
"Unit";"Zergling";"Larva";261;1
"Unit";"Zergling";"Larva";261;1
"Unit";"Zergling";"Larva";261;1
"Unit";"Zergling";"Larva";261;1
"Unit";"Baneling";"Zergling";261;0
"Unit";"Baneling";"Zergling";261;0
"Unit";"Baneling";"Zergling";261;0
"Unit";"Baneling";"Zergling";261;0
"Unit";"Baneling";"Zergling";261;0
"Unit";"Baneling";"Zergling";261;0
"Unit";"Baneling";"Zergling";261;0
"Unit";"Baneling";"Zergling";261;0
"Unit";"Baneling";"Zergling";261;0
"Unit";"Baneling";"Zergling";261;0
"Unit";"Baneling";"Zergling";261;0
"Unit";"Baneling";"Zergling";261;0
"Unit";"Baneling";"Zergling";261;0
"Unit";"Baneling";"Zergling";261;0
"Unit";"Baneling";"Zergling";261;0
"Unit";"Zergling";"Larva";261;1
"Unit";"Zergling";"Larva";261;1
"Unit";"Zergling";"Larva";261;1
"Unit";"Zergling";"Larva";261;1
"Building";"CreepTumor";NA;273;0
"Building";"CreepTumor";NA;273;0
"Building";"CreepTumor";NA;273;0
"Building";"CreepTumor";NA;273;0
"Building";"CreepTumor";NA;273;0
"Building";"CreepTumor";NA;273;0
"Building";"CreepTumor";NA;273;0
"Building";"CreepTumor";NA;273;0
"Unit";"Zergling";"Larva";273;1
"Unit";"Zergling";"Larva";273;1
"Unit";"Zergling";"Larva";273;1
"Unit";"Zergling";"Larva";273;1
"Building";"SporeCrawler";NA;273;0
"Building";"SporeCrawler";NA;273;0
"Upgrade";"ZergMeleeWeaponsLevel1";"EvolutionChamber";217;0
"Unit";"Baneling";"Zergling";287;0
"Unit";"Baneling";"Zergling";287;0
"Unit";"Baneling";"Zergling";287;0
"Unit";"Baneling";"Zergling";287;0
"Unit";"Baneling";"Zergling";287;0
"Unit";"Baneling";"Zergling";287;0
"Unit";"Baneling";"Zergling";287;0
"Unit";"Baneling";"Zergling";287;0
"Unit";"Baneling";"Zergling";287;0
"Building";"SpineCrawler";NA;263;0
"Building";"SpineCrawler";NA;273;0
"Unit";"Overlord";"Larva";291;0
"Building";"Hatchery";NA;229;0
"Building";"CreepTumorQueen";NA;291;0
"Building";"CreepTumor";NA;291;0
"Building";"CreepTumor";NA;291;0
"Building";"CreepTumor";NA;291;0
"Building";"CreepTumor";NA;291;0
"Building";"CreepTumor";NA;291;0
"Building";"CreepTumor";NA;291;0
"Building";"CreepTumor";NA;291;0
"Building";"CreepTumor";NA;291;0
"Building";"CreepTumor";NA;291;0
"Building";"CreepTumor";NA;291;0
"Building";"CreepTumor";NA;291;0
"Building";"CreepTumor";NA;291;0
"Building";"CreepTumor";NA;291;0
"Building";"CreepTumor";NA;291;0
"Building";"CreepTumor";NA;291;0
"Building";"Extractor";NA;291;0
"Building";"CreepTumor";NA;291;0
"Building";"UltraliskCavern";NA;291;0
"Building";"Extractor";NA;291;0
"Upgrade";"EvolveGroovedSpines";"HydraliskDen";291;0
"Building";"Spire";NA;283;0
"Building";"CreepTumor";NA;291;0
"Building";"CreepTumor";NA;291;0
"Building";"CreepTumor";NA;291;0
"Building";"CreepTumor";NA;291;0
"Building";"CreepTumor";NA;291;0
"Building";"CreepTumor";NA;291;0
"Building";"CreepTumor";NA;291;0
"Building";"CreepTumor";NA;291;0
"Unit";"Overlord";"Larva";291;0
"Unit";"Overlord";"Larva";291;0
"Building";"CreepTumorQueen";NA;291;0
"Building";"CreepTumorQueen";NA;291;0
"Unit";"Ultralisk";"Larva";291;6
"Unit";"Ultralisk";"Larva";291;6
"Unit";"Ultralisk";"Larva";291;6
"Unit";"Ultralisk";"Larva";291;6
"Building";"CreepTumorQueen";NA;291;0
"Upgrade";"ZergGroundArmorsLevel2";"EvolutionChamber";291;0
"Unit";"Zergling";"Larva";291;1
"Unit";"Zergling";"Larva";291;1
"Unit";"Zergling";"Larva";291;1
"Unit";"Zergling";"Larva";291;1
"Unit";"Zergling";"Larva";291;1
"Unit";"Zergling";"Larva";291;1
"Unit";"Zergling";"Larva";291;1
"Unit";"Zergling";"Larva";291;1
"Unit";"Zergling";"Larva";291;1
"Unit";"Zergling";"Larva";291;1
"Unit";"Zergling";"Larva";291;1
"Unit";"Zergling";"Larva";291;1
"Unit";"Zergling";"Larva";291;1
"Unit";"Zergling";"Larva";291;1
"Unit";"Zergling";"Larva";291;1
"Unit";"Zergling";"Larva";291;1
"Unit";"Zergling";"Larva";291;1
"Unit";"Zergling";"Larva";291;1
"Unit";"Zergling";"Larva";291;1
"Unit";"Zergling";"Larva";291;1
"Unit";"Zergling";"Larva";291;1
"Unit";"Zergling";"Larva";291;1
"Unit";"Zergling";"Larva";291;1
"Unit";"Zergling";"Larva";291;1
"Unit";"Zergling";"Larva";291;1
"Unit";"Zergling";"Larva";291;1
"Unit";"Zergling";"Larva";291;1
"Unit";"Zergling";"Larva";291;1
"Unit";"Zergling";"Larva";291;1
"Unit";"Zergling";"Larva";291;1
"Unit";"Zergling";"Larva";291;1
"Unit";"Zergling";"Larva";291;1
"Unit";"Zergling";"Larva";291;1
"Unit";"Zergling";"Larva";291;1
"Unit";"Zergling";"Larva";291;1
"Unit";"Zergling";"Larva";291;1
"Unit";"Zergling";"Larva";291;1
"Unit";"Zergling";"Larva";291;1
"Unit";"Zergling";"Larva";291;1
"Unit";"Zergling";"Larva";291;1
"Unit";"Zergling";"Larva";291;1
"Unit";"Zergling";"Larva";291;1
"Unit";"Zergling";"Larva";291;1
"Unit";"Zergling";"Larva";291;1
"Unit";"Zergling";"Larva";291;1
"Unit";"Zergling";"Larva";291;1
"Unit";"Zergling";"Larva";291;1
"Unit";"Zergling";"Larva";291;1
"Unit";"Zergling";"Larva";291;1
"Unit";"Zergling";"Larva";291;1
"Unit";"Zergling";"Larva";291;1
"Unit";"Zergling";"Larva";291;1
"Unit";"Zergling";"Larva";291;1
"Unit";"Zergling";"Larva";291;1
"Unit";"Zergling";"Larva";291;1
"Unit";"Zergling";"Larva";291;1
"Unit";"Zergling";"Larva";291;1
"Unit";"Zergling";"Larva";291;1
"Unit";"Zergling";"Larva";291;1
"Unit";"Zergling";"Larva";291;1
"Unit";"Zergling";"Larva";291;1
"Unit";"Zergling";"Larva";291;1
"Unit";"Zergling";"Larva";291;1
"Unit";"Zergling";"Larva";291;1
"Unit";"Zergling";"Larva";291;1
"Unit";"Zergling";"Larva";291;1
"Unit";"Zergling";"Larva";291;1
"Unit";"Zergling";"Larva";291;1
"Unit";"Zergling";"Larva";291;1
"Unit";"Zergling";"Larva";291;1
"Unit";"Zergling";"Larva";291;1
"Unit";"Zergling";"Larva";291;1
"Unit";"Zergling";"Larva";291;1
"Unit";"Zergling";"Larva";291;1
"Unit";"Zergling";"Larva";291;1
"Unit";"Zergling";"Larva";291;1
"Unit";"Zergling";"Larva";291;1
"Unit";"Zergling";"Larva";291;1
"Unit";"Zergling";"Larva";291;1
"Unit";"Zergling";"Larva";291;1
"Unit";"Zergling";"Larva";291;1
"Unit";"Zergling";"Larva";291;1
"Building";"CreepTumor";NA;315;0
"Building";"Extractor";NA;315;0
"Building";"CreepTumor";NA;368;0
"Building";"CreepTumor";NA;369;0
"Building";"CreepTumor";NA;369;0
"Building";"CreepTumor";NA;369;0
"Unit";"Baneling";"Zergling";401;0
"Unit";"Baneling";"Zergling";401;0
"Unit";"Baneling";"Zergling";401;0
"Unit";"Baneling";"Zergling";401;0
"Unit";"Baneling";"Zergling";401;0
"Unit";"Baneling";"Zergling";401;0
"Unit";"Baneling";"Zergling";401;0
"Unit";"Baneling";"Zergling";401;0
"Unit";"Baneling";"Zergling";401;0
"Unit";"Baneling";"Zergling";401;0
"Unit";"Baneling";"Zergling";401;0
"Unit";"Baneling";"Zergling";401;0
"Unit";"Baneling";"Zergling";401;0
"Unit";"Baneling";"Zergling";401;0
"Unit";"Baneling";"Zergling";401;0
"Unit";"Baneling";"Zergling";401;0
"Unit";"Baneling";"Zergling";401;0
"Unit";"Baneling";"Zergling";401;0
"Unit";"Baneling";"Zergling";401;0
"Unit";"Baneling";"Zergling";401;0
"Unit";"Baneling";"Zergling";401;0
"Unit";"Ultralisk";"Larva";291;6
"Unit";"Ultralisk";"Larva";291;6
"Unit";"Ultralisk";"Larva";291;6
"Building";"CreepTumor";NA;401;0
"Building";"CreepTumor";NA;401;0
"Building";"CreepTumor";NA;421;0
"Upgrade";"ChitinousPlating";"UltraliskCavern";291;0
"Upgrade";"ZergMeleeWeaponsLevel2";"EvolutionChamber";291;0
"Unit";"Zergling";"Larva";421;1
"Unit";"Zergling";"Larva";421;1
"Unit";"Zergling";"Larva";421;1
"Unit";"Zergling";"Larva";421;1
"Unit";"Zergling";"Larva";421;1
"Unit";"Zergling";"Larva";421;1
"Unit";"Zergling";"Larva";421;1
"Unit";"Zergling";"Larva";421;1
"Unit";"Zergling";"Larva";421;1
"Unit";"Zergling";"Larva";421;1
"Unit";"Zergling";"Larva";421;1
"Unit";"Zergling";"Larva";421;1
"Unit";"Zergling";"Larva";421;1
"Unit";"Zergling";"Larva";421;1
"Unit";"Zergling";"Larva";421;1
"Unit";"Zergling";"Larva";421;1
"Unit";"Zergling";"Larva";421;1
"Unit";"Zergling";"Larva";421;1
"Unit";"Corruptor";"Larva";421;2
"Unit";"Corruptor";"Larva";421;2
"Unit";"Corruptor";"Larva";421;2
"Unit";"Corruptor";"Larva";421;2
"Unit";"Corruptor";"Larva";421;2
"Unit";"Corruptor";"Larva";421;2
"Unit";"Corruptor";"Larva";421;2
"Building";"CreepTumor";NA;423;0
"Building";"CreepTumor";NA;431;0
"Building";"CreepTumor";NA;439;0
"Building";"CreepTumor";NA;439;0
"Building";"CreepTumor";NA;439;0
"Building";"CreepTumor";NA;439;0
"Building";"CreepTumor";NA;445;0
"Building";"CreepTumor";NA;445;0
"Building";"CreepTumor";NA;445;0
