"type";"unit_name";"on_building";"total_supply";"supply"
"Unit";"Overlord";"Larva";13;0
"Building";"Extractor";NA;17;0
"Unit";"Overlord";"Larva";21;0
"Building";"SpawningPool";NA;19;0
"Building";"Hatchery";NA;17;0
"Unit";"Zergling";"Larva";22;1
"Unit";"Zergling";"Larva";22;1
"Unit";"Zergling";"Larva";22;1
"Unit";"Zergling";"Larva";22;1
"Unit";"Queen";"Hatchery";22;2
"Unit";"Queen";"Hatchery";22;2
"Unit";"Zergling";"Larva";32;1
"Unit";"Zergling";"Larva";32;1
"Building";"CreepTumorQueen";NA;35;0
"Unit";"Overlord";"Larva";35;0
"Unit";"Queen";"Hatchery";33;2
"Building";"CreepTumor";NA;40;0
"Building";"CreepTumorQueen";NA;40;0
"Unit";"Zergling";"Larva";40;1
"Unit";"Zergling";"Larva";40;1
"Unit";"Overlord";"Larva";46;0
"Unit";"Zergling";"Larva";48;1
"Unit";"Zergling";"Larva";48;1
"Building";"CreepTumor";NA;50;0
"Building";"CreepTumorQueen";NA;50;0
"Building";"CreepTumorQueen";NA;50;0
"Unit";"Queen";"Hatchery";50;2
"Unit";"Overlord";"Larva";52;0
"Unit";"Zergling";"Larva";55;1
"Unit";"Zergling";"Larva";55;1
"Unit";"Overlord";"Larva";55;0
"Building";"CreepTumor";NA;58;0
"Building";"RoachWarren";NA;50;0
"Building";"CreepTumor";NA;58;0
"Building";"Extractor";NA;58;0
"Unit";"Overlord";"Larva";62;0
"Building";"Hatchery";NA;45;0
"Building";"CreepTumor";NA;64;0
"Unit";"Roach";"Larva";64;2
"Unit";"Roach";"Larva";64;2
"Building";"SporeCrawler";NA;64;0
"Unit";"Roach";"Larva";65;2
"Unit";"Roach";"Larva";65;2
"Unit";"Overlord";"Larva";65;0
"Building";"CreepTumor";NA;67;0
"Unit";"Roach";"Larva";65;2
"Building";"SporeCrawler";NA;65;0
"Building";"CreepTumor";NA;89;0
"Unit";"Zergling";"Larva";89;1
"Unit";"Zergling";"Larva";89;1
"Unit";"Zergling";"Larva";89;1
"Unit";"Zergling";"Larva";89;1
"Building";"CreepTumor";NA;92;0
"Building";"SporeCrawler";NA;83;0
"Building";"CreepTumorQueen";NA;92;0
"Unit";"Roach";"Larva";97;2
"Building";"CreepTumor";NA;105;0
"Building";"CreepTumor";NA;107;0
"Unit";"Overlord";"Larva";105;0
"Unit";"Overlord";"Larva";105;0
"Building";"Extractor";NA;107;0
"Building";"Extractor";NA;107;0
"Unit";"Queen";"Hatchery";99;2
"Building";"CreepTumor";NA;110;0
"Building";"CreepTumorQueen";NA;110;0
"Building";"Extractor";NA;110;0
"Building";"Extractor";NA;110;0
"Building";"CreepTumorQueen";NA;110;0
"Building";"EvolutionChamber";NA;110;0
"Unit";"Roach";"Larva";112;2
"Unit";"Roach";"Larva";113;2
"Unit";"Roach";"Larva";118;2
"Unit";"Roach";"Larva";118;2
"Building";"CreepTumor";NA;123;0
"Building";"CreepTumor";NA;131;0
"Building";"CreepTumor";NA;131;0
"Building";"CreepTumor";NA;131;0
"Building";"CreepTumor";NA;131;0
"Unit";"Roach";"Larva";131;2
"Unit";"Overlord";"Larva";131;0
"Unit";"Overlord";"Larva";131;0
"Building";"InfestationPit";NA;123;0
"Unit";"Overlord";"Larva";131;0
"Unit";"Overlord";"Larva";131;0
"Unit";"Overlord";"Larva";131;0
"Unit";"Overlord";"Larva";131;0
"Building";"CreepTumor";NA;131;0
"Upgrade";"GlialReconstitution";"RoachWarren";115;0
"Building";"CreepTumorQueen";NA;134;0
"Building";"CreepTumor";NA;134;0
"Unit";"Overlord";"Larva";131;0
"Unit";"Overlord";"Larva";131;0
"Unit";"Overlord";"Larva";131;0
"Building";"CreepTumor";NA;134;0
"Building";"CreepTumor";NA;134;0
"Building";"CreepTumor";NA;134;0
"Unit";"Roach";"Larva";134;2
"Unit";"Roach";"Larva";134;2
"Unit";"Roach";"Larva";134;2
"Unit";"Zergling";"Larva";134;1
"Unit";"Zergling";"Larva";134;1
"Unit";"Zergling";"Larva";134;1
"Unit";"Zergling";"Larva";134;1
"Building";"CreepTumorQueen";NA;137;0
"Unit";"Overlord";"Larva";137;0
"Unit";"Overlord";"Larva";143;0
"Building";"CreepTumor";NA;147;0
"Building";"CreepTumor";NA;147;0
"Building";"CreepTumor";NA;147;0
"Building";"CreepTumor";NA;147;0
"Building";"CreepTumor";NA;147;0
"Building";"Hatchery";NA;131;0
"Unit";"Roach";"Larva";151;2
"Unit";"Roach";"Larva";151;2
"Unit";"Roach";"Larva";151;2
"Unit";"Roach";"Larva";151;2
"Unit";"Roach";"Larva";151;2
"Unit";"Roach";"Larva";151;2
"Building";"CreepTumor";NA;151;0
"Building";"CreepTumor";NA;151;0
"Building";"CreepTumor";NA;151;0
"Building";"Extractor";NA;151;0
"Upgrade";"ZergMissileWeaponsLevel1";"EvolutionChamber";131;0
"Unit";"Roach";"Larva";159;2
"Unit";"Roach";"Larva";159;2
"Unit";"Roach";"Larva";159;2
"Unit";"Roach";"Larva";159;2
"Unit";"Roach";"Larva";163;2
"Unit";"Roach";"Larva";163;2
"Unit";"Roach";"Larva";163;2
"Unit";"Roach";"Larva";163;2
"Unit";"Roach";"Larva";163;2
"Unit";"Roach";"Larva";163;2
"Unit";"Roach";"Larva";163;2
"Unit";"Roach";"Larva";163;2
"Unit";"Roach";"Larva";163;2
"Unit";"Roach";"Larva";163;2
"Building";"Extractor";NA;171;0
"Building";"CreepTumor";NA;194;0
"Building";"CreepTumor";NA;194;0
"Building";"CreepTumor";NA;194;0
"Building";"CreepTumor";NA;194;0
"Unit";"Overlord";"Larva";197;0
"Unit";"Overlord";"Larva";197;0
"Unit";"Overlord";"Larva";197;0
"Building";"CreepTumor";NA;201;0
"Building";"CreepTumorQueen";NA;201;0
"Building";"EvolutionChamber";NA;201;0
"Building";"CreepTumor";NA;201;0
"Building";"CreepTumor";NA;201;0
"Building";"CreepTumor";NA;201;0
"Unit";"Roach";"Larva";201;2
"Unit";"Roach";"Larva";201;2
"Unit";"Roach";"Larva";201;2
"Unit";"Roach";"Larva";201;2
"Building";"BanelingNest";NA;201;0
"Building";"SporeCrawler";NA;201;0
"Building";"CreepTumor";NA;214;0
"Building";"CreepTumor";NA;214;0
"Building";"CreepTumor";NA;214;0
"Building";"CreepTumor";NA;214;0
"Building";"CreepTumor";NA;214;0
"Building";"CreepTumor";NA;214;0
"Unit";"Roach";"Larva";214;2
"Unit";"Roach";"Larva";214;2
"Unit";"Roach";"Larva";214;2
"Unit";"Roach";"Larva";214;2
"Unit";"Zergling";"Larva";214;1
"Unit";"Zergling";"Larva";214;1
"Unit";"Queen";"Hatchery";214;2
"Unit";"Queen";"Hatchery";214;2
"Building";"Spire";NA;202;0
"Unit";"Zergling";"Larva";228;1
"Unit";"Zergling";"Larva";228;1
"Unit";"Zergling";"Larva";228;1
"Unit";"Zergling";"Larva";228;1
"Unit";"Zergling";"Larva";228;1
"Unit";"Zergling";"Larva";228;1
"Unit";"Zergling";"Larva";228;1
"Unit";"Zergling";"Larva";228;1
"Upgrade";"ZergMissileWeaponsLevel2";"EvolutionChamber";201;0
"Building";"Hatchery";NA;214;0
"Building";"CreepTumor";NA;236;0
"Unit";"Baneling";"Zergling";236;0
"Unit";"Baneling";"Zergling";236;0
"Unit";"Baneling";"Zergling";236;0
"Unit";"Baneling";"Zergling";236;0
"Unit";"Baneling";"Zergling";236;0
"Unit";"Baneling";"Zergling";236;0
"Unit";"Baneling";"Zergling";236;0
"Unit";"Baneling";"Zergling";236;0
"Unit";"Baneling";"Zergling";236;0
"Unit";"Baneling";"Zergling";236;0
"Building";"CreepTumor";NA;236;0
"Building";"CreepTumor";NA;236;0
"Building";"NydusNetwork";NA;228;0
"Building";"CreepTumorQueen";NA;236;0
"Building";"CreepTumorQueen";NA;236;0
"Building";"Extractor";NA;236;0
"Upgrade";"ZergMeleeWeaponsLevel1";"EvolutionChamber";214;0
"Building";"Extractor";NA;236;0
"Unit";"Zergling";"Larva";236;1
"Unit";"Zergling";"Larva";236;1
"Unit";"Zergling";"Larva";236;1
"Unit";"Zergling";"Larva";236;1
"Unit";"Zergling";"Larva";236;1
"Unit";"Zergling";"Larva";236;1
"Unit";"Zergling";"Larva";236;1
"Unit";"Zergling";"Larva";236;1
"Unit";"Zergling";"Larva";236;1
"Unit";"Zergling";"Larva";236;1
"Building";"NydusCanal";NA;236;0
"Unit";"Zergling";"Larva";238;1
"Unit";"Zergling";"Larva";238;1
"Unit";"Zergling";"Larva";238;1
"Unit";"Zergling";"Larva";238;1
"Unit";"Zergling";"Larva";238;1
"Unit";"Zergling";"Larva";238;1
"Unit";"Roach";"Larva";246;2
"Unit";"Roach";"Larva";246;2
"Unit";"Roach";"Larva";246;2
"Building";"CreepTumor";NA;246;0
"Building";"CreepTumor";NA;246;0
"Unit";"Zergling";"Larva";258;1
"Unit";"Zergling";"Larva";258;1
"Unit";"Zergling";"Larva";258;1
"Unit";"Zergling";"Larva";258;1
"Unit";"Zergling";"Larva";258;1
"Unit";"Zergling";"Larva";258;1
"Unit";"Zergling";"Larva";258;1
"Unit";"Zergling";"Larva";258;1
"Unit";"Zergling";"Larva";258;1
"Unit";"Zergling";"Larva";258;1
"Unit";"Zergling";"Larva";258;1
"Unit";"Zergling";"Larva";258;1
"Unit";"Zergling";"Larva";258;1
"Unit";"Zergling";"Larva";258;1
"Unit";"Zergling";"Larva";258;1
"Unit";"Zergling";"Larva";258;1
"Unit";"Zergling";"Larva";258;1
"Unit";"Zergling";"Larva";258;1
"Unit";"Zergling";"Larva";258;1
"Unit";"Zergling";"Larva";258;1
"Unit";"Zergling";"Larva";258;1
"Unit";"Zergling";"Larva";258;1
"Unit";"Roach";"Larva";258;2
"Unit";"Roach";"Larva";258;2
"Unit";"Roach";"Larva";258;2
"Unit";"Roach";"Larva";258;2
"Unit";"Baneling";"Zergling";258;0
"Unit";"Baneling";"Zergling";258;0
"Unit";"Baneling";"Zergling";258;0
"Unit";"Baneling";"Zergling";258;0
"Unit";"Baneling";"Zergling";258;0
"Unit";"Baneling";"Zergling";258;0
"Unit";"Overlord";"Larva";288;0
"Unit";"Overlord";"Larva";288;0
"Unit";"Overlord";"Larva";294;0
"Unit";"Overlord";"Larva";294;0
"Upgrade";"Burrow";"Hatchery";258;0
"Upgrade";"ZergGroundArmorsLevel1";"EvolutionChamber";252;0
"Building";"NydusCanal";NA;294;0
"Unit";"Roach";"Larva";294;2
"Unit";"Roach";"Larva";294;2
"Unit";"Roach";"Larva";294;2
"Unit";"Roach";"Larva";294;2
"Building";"CreepTumor";NA;294;0
"Unit";"Roach";"Larva";294;2
"Unit";"Roach";"Larva";294;2
"Unit";"Roach";"Larva";294;2
"Building";"CreepTumorQueen";NA;294;0
"Building";"CreepTumor";NA;308;0
"Building";"CreepTumorQueen";NA;308;0
"Building";"CreepTumorQueen";NA;308;0
"Upgrade";"ZergMeleeWeaponsLevel2";"EvolutionChamber";258;0
"Unit";"Roach";"Larva";308;2
"Unit";"Roach";"Larva";308;2
"Unit";"Roach";"Larva";308;2
"Unit";"Roach";"Larva";308;2
"Unit";"Roach";"Larva";308;2
"Unit";"Roach";"Larva";308;2
"Unit";"Roach";"Larva";308;2
"Unit";"Roach";"Larva";308;2
"Unit";"Roach";"Larva";308;2
"Unit";"Zergling";"Larva";308;1
"Unit";"Zergling";"Larva";308;1
"Unit";"Roach";"Larva";308;2
"Unit";"Roach";"Larva";308;2
"Unit";"Zergling";"Larva";308;1
"Unit";"Zergling";"Larva";308;1
"Unit";"Zergling";"Larva";308;1
"Unit";"Zergling";"Larva";308;1
"Unit";"Zergling";"Larva";308;1
"Unit";"Zergling";"Larva";308;1
"Unit";"Zergling";"Larva";308;1
"Unit";"Zergling";"Larva";308;1
"Unit";"Zergling";"Larva";308;1
"Unit";"Zergling";"Larva";308;1
"Unit";"Zergling";"Larva";308;1
"Unit";"Zergling";"Larva";308;1
"Unit";"Zergling";"Larva";308;1
"Unit";"Zergling";"Larva";308;1
"Unit";"Zergling";"Larva";308;1
"Unit";"Zergling";"Larva";308;1
"Unit";"Zergling";"Larva";308;1
"Unit";"Zergling";"Larva";308;1
"Unit";"Zergling";"Larva";308;1
"Unit";"Zergling";"Larva";308;1
"Unit";"Zergling";"Larva";308;1
"Unit";"Zergling";"Larva";308;1
"Unit";"Zergling";"Larva";308;1
"Unit";"Zergling";"Larva";308;1
"Unit";"Zergling";"Larva";308;1
"Unit";"Zergling";"Larva";308;1
"Unit";"Baneling";"Zergling";358;0
"Unit";"Baneling";"Zergling";358;0
"Unit";"Baneling";"Zergling";358;0
"Unit";"Baneling";"Zergling";358;0
"Unit";"Baneling";"Zergling";358;0
"Unit";"Baneling";"Zergling";358;0
"Unit";"Baneling";"Zergling";358;0
"Unit";"Baneling";"Zergling";358;0
"Unit";"Baneling";"Zergling";358;0
"Unit";"Baneling";"Zergling";358;0
"Building";"Spire";NA;294;0
"Building";"NydusCanal";NA;358;0
"Building";"CreepTumorQueen";NA;358;0
"Unit";"Roach";"Larva";358;2
"Unit";"Roach";"Larva";358;2
"Unit";"Roach";"Larva";358;2
"Building";"CreepTumorQueen";NA;358;0
"Building";"CreepTumorQueen";NA;358;0
"Unit";"Zergling";"Larva";364;1
"Unit";"Zergling";"Larva";364;1
"Unit";"Zergling";"Larva";364;1
"Unit";"Zergling";"Larva";364;1
"Unit";"Zergling";"Larva";364;1
"Unit";"Zergling";"Larva";364;1
"Unit";"Zergling";"Larva";364;1
"Unit";"Zergling";"Larva";364;1
"Unit";"Zergling";"Larva";364;1
"Unit";"Zergling";"Larva";364;1
"Unit";"Zergling";"Larva";364;1
"Unit";"Zergling";"Larva";364;1
"Unit";"Zergling";"Larva";364;1
"Unit";"Zergling";"Larva";364;1
"Unit";"Zergling";"Larva";364;1
"Unit";"Zergling";"Larva";364;1
"Unit";"Zergling";"Larva";364;1
"Unit";"Zergling";"Larva";364;1
"Unit";"Zergling";"Larva";364;1
"Unit";"Zergling";"Larva";364;1
"Unit";"Zergling";"Larva";364;1
"Unit";"Zergling";"Larva";364;1
"Unit";"Zergling";"Larva";364;1
"Unit";"Zergling";"Larva";364;1
"Unit";"Zergling";"Larva";364;1
"Unit";"Zergling";"Larva";364;1
"Unit";"Zergling";"Larva";364;1
"Unit";"Zergling";"Larva";364;1
"Unit";"Zergling";"Larva";364;1
"Unit";"Zergling";"Larva";364;1
"Unit";"Zergling";"Larva";364;1
"Unit";"Zergling";"Larva";364;1
"Unit";"Zergling";"Larva";364;1
"Unit";"Zergling";"Larva";364;1
"Unit";"Zergling";"Larva";364;1
"Unit";"Zergling";"Larva";364;1
"Unit";"Zergling";"Larva";364;1
"Unit";"Zergling";"Larva";364;1
"Unit";"Zergling";"Larva";364;1
"Unit";"Zergling";"Larva";364;1
"Unit";"Zergling";"Larva";364;1
"Unit";"Zergling";"Larva";364;1
"Unit";"Zergling";"Larva";364;1
"Unit";"Zergling";"Larva";364;1
"Building";"CreepTumor";NA;364;0
"Unit";"Roach";"Larva";408;2
"Unit";"Roach";"Larva";408;2
"Unit";"Roach";"Larva";408;2
"Unit";"Roach";"Larva";408;2
"Building";"NydusCanal";NA;408;0
"Upgrade";"ZergMissileWeaponsLevel3";"EvolutionChamber";308;0
"Unit";"Overlord";"Larva";408;0
"Unit";"Overlord";"Larva";408;0
"Unit";"Overlord";"Larva";416;0
"Unit";"Overlord";"Larva";416;0
"Unit";"Roach";"Larva";416;2
"Unit";"Roach";"Larva";416;2
"Unit";"Roach";"Larva";416;2
"Unit";"Roach";"Larva";416;2
"Unit";"Roach";"Larva";416;2
"Unit";"Roach";"Larva";416;2
"Unit";"Roach";"Larva";416;2
"Unit";"Roach";"Larva";416;2
"Building";"CreepTumorQueen";NA;428;0
"Building";"CreepTumorQueen";NA;436;0
"Building";"CreepTumorQueen";NA;436;0
"Building";"CreepTumorQueen";NA;436;0
"Building";"Extractor";NA;428;0
"Building";"Extractor";NA;428;0
"Building";"CreepTumorQueen";NA;436;0
"Building";"CreepTumorQueen";NA;436;0
"Building";"CreepTumorQueen";NA;436;0
"Building";"CreepTumorQueen";NA;436;0
"Building";"CreepTumorQueen";NA;436;0
"Building";"CreepTumorQueen";NA;436;0
"Building";"CreepTumorQueen";NA;436;0
"Upgrade";"ZergMeleeWeaponsLevel3";"EvolutionChamber";408;0
"Building";"CreepTumorQueen";NA;436;0
"Building";"CreepTumorQueen";NA;436;0
"Building";"CreepTumorQueen";NA;436;0
"Unit";"Roach";"Larva";436;2
"Unit";"Roach";"Larva";436;2
"Unit";"Roach";"Larva";436;2
"Unit";"Roach";"Larva";436;2
"Unit";"Roach";"Larva";436;2
"Unit";"Roach";"Larva";436;2
"Unit";"Roach";"Larva";436;2
"Unit";"Roach";"Larva";436;2
"Unit";"Roach";"Larva";436;2
"Building";"Hatchery";NA;428;0
"Building";"CreepTumor";NA;436;0
"Building";"CreepTumor";NA;438;0
"Building";"CreepTumor";NA;436;0
"Building";"CreepTumor";NA;436;0
"Building";"Extractor";NA;456;0
"Upgrade";"ZergGroundArmorsLevel2";"EvolutionChamber";428;0
"Building";"SpineCrawler";NA;448;0
"Building";"SpineCrawler";NA;448;0
"Building";"SpineCrawler";NA;456;0
"Unit";"Roach";"Larva";458;2
"Unit";"Roach";"Larva";458;2
"Building";"CreepTumorQueen";NA;458;0
"Building";"CreepTumor";NA;462;0
"Building";"CreepTumor";NA;462;0
"Building";"CreepTumor";NA;462;0
"Building";"CreepTumor";NA;462;0
"Unit";"Roach";"Larva";462;2
"Unit";"Roach";"Larva";462;2
"Unit";"Roach";"Larva";462;2
"Unit";"Roach";"Larva";462;2
"Unit";"Corruptor";"Larva";462;2
"Unit";"Corruptor";"Larva";462;2
"Unit";"Corruptor";"Larva";462;2
"Unit";"Corruptor";"Larva";462;2
"Unit";"Corruptor";"Larva";462;2
"Building";"NydusCanal";NA;462;0
"Building";"SpineCrawler";NA;462;0
"Building";"SpineCrawler";NA;462;0
"Building";"SpineCrawler";NA;462;0
"Building";"SpineCrawler";NA;462;0
"Unit";"Queen";"Hatchery";462;2
"Unit";"Queen";"Hatchery";462;2
"Unit";"Corruptor";"Larva";470;2
"Unit";"Corruptor";"Larva";470;2
"Unit";"Corruptor";"Larva";470;2
"Building";"CreepTumor";NA;480;0
"Building";"CreepTumor";NA;480;0
"Building";"Hatchery";NA;458;0
"Unit";"Corruptor";"Larva";480;2
"Unit";"Corruptor";"Larva";480;2
"Unit";"Corruptor";"Larva";480;2
"Unit";"Queen";"Hatchery";480;2
"Unit";"Queen";"Hatchery";480;2
"Unit";"Corruptor";"Larva";496;2
"Unit";"Corruptor";"Larva";496;2
"Unit";"Corruptor";"Larva";496;2
"Building";"SpineCrawler";NA;490;0
"Building";"SpineCrawler";NA;490;0
"Unit";"Corruptor";"Larva";496;2
"Building";"SpineCrawler";NA;496;0
"Unit";"Corruptor";"Larva";496;2
"Building";"CreepTumorQueen";NA;503;0
"Building";"SpineCrawler";NA;496;0
"Building";"CreepTumorQueen";NA;503;0
"Building";"CreepTumorQueen";NA;503;0
"Unit";"Queen";"Hatchery";503;2
"Unit";"Corruptor";"Larva";503;2
"Unit";"Corruptor";"Larva";507;2
"Unit";"Corruptor";"Larva";507;2
"Building";"CreepTumor";NA;515;0
"Building";"CreepTumorQueen";NA;521;0
"Building";"CreepTumorQueen";NA;521;0
"Upgrade";"ZergGroundArmorsLevel3";"EvolutionChamber";480;0
"Unit";"Corruptor";"Larva";515;2
"Unit";"Zergling";"Larva";523;1
"Unit";"Zergling";"Larva";523;1
"Unit";"Zergling";"Larva";523;1
"Unit";"Zergling";"Larva";523;1
"Unit";"Zergling";"Larva";523;1
"Unit";"Zergling";"Larva";523;1
"Building";"CreepTumorQueen";NA;523;0
"Building";"CreepTumorQueen";NA;523;0
"Building";"CreepTumorQueen";NA;523;0
"Building";"CreepTumorQueen";NA;523;0
"Building";"CreepTumorQueen";NA;523;0
"Unit";"Zergling";"Larva";523;1
"Unit";"Zergling";"Larva";523;1
"Building";"CreepTumor";NA;529;0
"Building";"CreepTumor";NA;529;0
"Unit";"Zergling";"Larva";529;1
"Unit";"Zergling";"Larva";529;1
"Unit";"Zergling";"Larva";529;1
"Unit";"Zergling";"Larva";529;1
"Unit";"Zergling";"Larva";529;1
"Unit";"Zergling";"Larva";529;1
"Unit";"Zergling";"Larva";529;1
"Unit";"Zergling";"Larva";529;1
"Unit";"Zergling";"Larva";529;1
"Unit";"Zergling";"Larva";529;1
"Building";"CreepTumor";NA;531;0
"Building";"CreepTumor";NA;531;0
"Building";"CreepTumor";NA;531;0
"Building";"Extractor";NA;541;0
"Building";"SpineCrawler";NA;541;0
"Building";"SpineCrawler";NA;541;0
"Building";"SpineCrawler";NA;541;0
"Unit";"Corruptor";"Larva";541;2
"Unit";"Corruptor";"Larva";541;2
"Building";"Extractor";NA;546;0
"Unit";"Corruptor";"Larva";542;2
"Building";"SpineCrawler";NA;541;0
"Building";"Hatchery";NA;529;0
"Unit";"Queen";"Hatchery";541;2
"Unit";"Queen";"Hatchery";541;2
"Unit";"Queen";"Hatchery";541;2
"Building";"CreepTumor";NA;552;0
"Building";"SpineCrawler";NA;546;0
"Building";"CreepTumor";NA;552;0
"Building";"CreepTumor";NA;554;0
"Building";"SpineCrawler";NA;546;0
"Building";"SpineCrawler";NA;546;0
"Building";"SpineCrawler";NA;546;0
"Building";"SpineCrawler";NA;546;0
