"type";"unit_name";"on_building";"total_supply";"supply"
"Unit";"Overlord";"Larva";13;0
"Building";"Extractor";NA;17;0
"Building";"SpawningPool";NA;19;0
"Building";"Hatchery";NA;17;0
"Unit";"Overlord";"Larva";22;0
"Unit";"Zergling";"Larva";22;1
"Unit";"Zergling";"Larva";22;1
"Unit";"Zergling";"Larva";22;1
"Unit";"Zergling";"Larva";22;1
"Unit";"Zergling";"Larva";22;1
"Unit";"Zergling";"Larva";22;1
"Unit";"Queen";"Hatchery";22;2
"Unit";"Queen";"Hatchery";22;2
"Unit";"Overlord";"Larva";35;0
"Unit";"Overlord";"Larva";40;0
"Building";"CreepTumorQueen";NA;44;0
"Unit";"Queen";"Hatchery";39;2
"Unit";"Zergling";"Larva";44;1
"Unit";"Zergling";"Larva";44;1
"Unit";"Zergling";"Larva";44;1
"Unit";"Zergling";"Larva";44;1
"Unit";"Zergling";"Larva";44;1
"Unit";"Zergling";"Larva";44;1
"Unit";"Zergling";"Larva";44;1
"Unit";"Zergling";"Larva";44;1
"Building";"Hatchery";NA;33;0
"Building";"CreepTumor";NA;57;0
"Building";"CreepTumorQueen";NA;57;0
"Unit";"Overlord";"Larva";57;0
"Unit";"Queen";"Hatchery";47;2
"Unit";"Queen";"Hatchery";49;2
"Unit";"Overlord";"Larva";59;0
"Building";"CreepTumorQueen";NA;65;0
"Building";"CreepTumor";NA;67;0
"Building";"CreepTumor";NA;67;0
"Unit";"Overlord";"Larva";69;0
"Unit";"Queen";"Hatchery";59;2
"Unit";"Overlord";"Larva";73;0
"Building";"CreepTumorQueen";NA;74;0
"Building";"CreepTumor";NA;74;0
"Building";"CreepTumor";NA;75;0
"Building";"CreepTumor";NA;75;0
"Building";"EvolutionChamber";NA;74;0
"Building";"EvolutionChamber";NA;74;0
"Building";"Extractor";NA;79;0
"Unit";"Overlord";"Larva";83;0
"Unit";"Queen";"Hatchery";78;2
"Unit";"Zergling";"Larva";83;1
"Unit";"Zergling";"Larva";83;1
"Unit";"Zergling";"Larva";83;1
"Unit";"Zergling";"Larva";83;1
"Unit";"Zergling";"Larva";83;1
"Unit";"Zergling";"Larva";83;1
"Unit";"Queen";"Hatchery";78;2
"Unit";"Zergling";"Larva";89;1
"Unit";"Zergling";"Larva";89;1
"Unit";"Zergling";"Larva";89;1
"Unit";"Zergling";"Larva";89;1
"Unit";"Zergling";"Larva";89;1
"Unit";"Zergling";"Larva";89;1
"Unit";"Zergling";"Larva";89;1
"Unit";"Zergling";"Larva";89;1
"Unit";"Zergling";"Larva";89;1
"Unit";"Zergling";"Larva";89;1
"Building";"CreepTumor";NA;111;0
"Building";"CreepTumor";NA;115;0
"Building";"CreepTumor";NA;118;0
"Building";"CreepTumor";NA;122;0
"Building";"Extractor";NA;122;0
"Building";"CreepTumor";NA;125;0
"Building";"Extractor";NA;122;0
"Unit";"Overlord";"Larva";124;0
"Building";"RoachWarren";NA;118;0
"Building";"CreepTumor";NA;131;0
"Building";"CreepTumor";NA;137;0
"Building";"CreepTumor";NA;137;0
"Building";"CreepTumor";NA;139;0
"Unit";"Overlord";"Larva";135;0
"Unit";"Overlord";"Larva";135;0
"Building";"Extractor";NA;132;0
"Building";"Extractor";NA;132;0
"Unit";"Roach";"Larva";137;2
"Unit";"Roach";"Larva";137;2
"Unit";"Roach";"Larva";137;2
"Unit";"Overlord";"Larva";139;0
"Unit";"Roach";"Larva";139;2
"Building";"CreepTumor";NA;145;0
"Unit";"Roach";"Larva";139;2
"Unit";"Roach";"Larva";139;2
"Unit";"Roach";"Larva";139;2
"Unit";"Roach";"Larva";139;2
"Unit";"Overlord";"Larva";139;0
"Unit";"Roach";"Larva";139;2
"Unit";"Overlord";"Larva";139;0
"Unit";"Roach";"Larva";139;2
"Building";"CreepTumor";NA;145;0
"Building";"CreepTumor";NA;145;0
"Building";"CreepTumorQueen";NA;145;0
"Unit";"Roach";"Larva";145;2
"Building";"CreepTumorQueen";NA;145;0
"Building";"CreepTumorQueen";NA;147;0
"Building";"CreepTumor";NA;147;0
"Unit";"Roach";"Larva";145;2
"Unit";"Roach";"Larva";145;2
"Unit";"Roach";"Larva";145;2
"Unit";"Roach";"Larva";147;2
"Unit";"Roach";"Larva";147;2
"Unit";"Overlord";"Larva";147;0
"Unit";"Roach";"Larva";159;2
"Unit";"Roach";"Larva";159;2
"Unit";"Roach";"Larva";159;2
"Unit";"Overlord";"Larva";161;0
"Building";"CreepTumor";NA;167;0
"Unit";"Roach";"Larva";161;2
"Unit";"Roach";"Larva";161;2
"Building";"CreepTumor";NA;171;0
"Building";"CreepTumor";NA;171;0
"Building";"CreepTumor";NA;171;0
"Unit";"Roach";"Larva";167;2
"Unit";"Overlord";"Larva";171;0
"Building";"CreepTumor";NA;177;0
"Building";"CreepTumor";NA;177;0
"Upgrade";"GlialReconstitution";"RoachWarren";145;0
"Unit";"Roach";"Larva";171;2
"Unit";"Roach";"Larva";171;2
"Unit";"Roach";"Larva";171;2
"Unit";"Roach";"Larva";171;2
"Unit";"Roach";"Larva";177;2
"Unit";"Overlord";"Larva";177;0
"Unit";"Roach";"Larva";177;2
"Unit";"Roach";"Larva";183;2
"Unit";"Roach";"Larva";183;2
"Unit";"Roach";"Larva";183;2
"Unit";"Roach";"Larva";189;2
"Building";"CreepTumorQueen";NA;201;0
"Building";"CreepTumorQueen";NA;203;0
"Unit";"Roach";"Larva";195;2
"Unit";"Roach";"Larva";197;2
"Unit";"Roach";"Larva";197;2
"Unit";"Roach";"Larva";199;2
"Unit";"Roach";"Larva";199;2
"Unit";"Roach";"Larva";199;2
"Unit";"Roach";"Larva";199;2
"Unit";"Roach";"Larva";199;2
"Unit";"Roach";"Larva";203;2
"Unit";"Roach";"Larva";203;2
"Unit";"Roach";"Larva";203;2
"Unit";"Roach";"Larva";203;2
"Unit";"Roach";"Larva";203;2
"Unit";"Roach";"Larva";207;2
"Unit";"Roach";"Larva";219;2
"Unit";"Roach";"Larva";219;2
"Unit";"Roach";"Larva";221;2
"Unit";"Roach";"Larva";221;2
"Unit";"Roach";"Larva";231;2
"Unit";"Roach";"Larva";231;2
"Unit";"Roach";"Larva";231;2
"Unit";"Roach";"Larva";231;2
"Unit";"Roach";"Larva";231;2
"Unit";"Roach";"Larva";231;2
"Unit";"Roach";"Larva";231;2
"Unit";"Roach";"Larva";231;2
"Unit";"Roach";"Larva";231;2
"Unit";"Roach";"Larva";231;2
"Unit";"Roach";"Larva";259;2
"Unit";"Roach";"Larva";259;2
"Unit";"Roach";"Larva";259;2
"Unit";"Roach";"Larva";259;2
"Unit";"Roach";"Larva";259;2
"Unit";"Roach";"Larva";259;2
"Unit";"Roach";"Larva";259;2
"Unit";"Roach";"Larva";259;2
"Unit";"Roach";"Larva";259;2
"Unit";"Roach";"Larva";259;2
"Unit";"Roach";"Larva";259;2
"Unit";"Roach";"Larva";259;2
"Unit";"Roach";"Larva";259;2
"Building";"CreepTumor";NA;267;0
"Building";"CreepTumor";NA;267;0
"Building";"CreepTumor";NA;267;0
"Building";"CreepTumor";NA;269;0
"Building";"CreepTumor";NA;271;0
"Unit";"Roach";"Larva";263;2
"Unit";"Roach";"Larva";263;2
"Unit";"Roach";"Larva";263;2
"Unit";"Overlord";"Larva";275;0
"Unit";"Overlord";"Larva";277;0
