"type";"unit_name";"on_building";"total_supply_lag";"supply"
"Unit";"Overlord";"Larva";13;0
"Building";"SpawningPool";NA;17;0
"Building";"Hatchery";NA;18;0
"Building";"Extractor";NA;20;0
"Unit";"Queen";"Hatchery";21;2
"Unit";"Zergling";"Larva";23;1
"Unit";"Zergling";"Larva";24;1
"Unit";"Overlord";"Larva";25;0
"Unit";"Queen";"Hatchery";27;2
"Unit";"Queen";"Hatchery";30;2
"Unit";"Zergling";"Larva";33;1
"Unit";"Zergling";"Larva";34;1
"Unit";"Zergling";"Larva";35;1
"Unit";"Zergling";"Larva";36;1
"Unit";"Overlord";"Larva";37;0
"Unit";"Zergling";"Larva";37;1
"Unit";"Zergling";"Larva";38;1
"Unit";"Zergling";"Larva";39;1
"Unit";"Zergling";"Larva";40;1
"Unit";"Zergling";"Larva";41;1
"Unit";"Zergling";"Larva";42;1
"Unit";"Overlord";"Larva";43;0
"Unit";"Zergling";"Larva";43;1
"Unit";"Zergling";"Larva";44;1
"Unit";"Zergling";"Larva";45;1
"Unit";"Zergling";"Larva";46;1
"Unit";"Zergling";"Larva";47;1
"Unit";"Zergling";"Larva";48;1
"Unit";"Zergling";"Larva";49;1
"Unit";"Zergling";"Larva";50;1
"Unit";"Zergling";"Larva";51;1
"Unit";"Zergling";"Larva";52;1
"Unit";"Zergling";"Larva";53;1
"Unit";"Zergling";"Larva";54;1
"Unit";"Zergling";"Larva";55;1
"Unit";"Zergling";"Larva";56;1
"Unit";"Zergling";"Larva";57;1
"Unit";"Zergling";"Larva";58;1
"Unit";"Zergling";"Larva";59;1
"Unit";"Zergling";"Larva";60;1
"Unit";"Zergling";"Larva";61;1
"Unit";"Zergling";"Larva";62;1
"Unit";"Zergling";"Larva";63;1
"Unit";"Zergling";"Larva";64;1
"Unit";"Zergling";"Larva";65;1
"Unit";"Zergling";"Larva";66;1
"Unit";"Zergling";"Larva";67;1
"Unit";"Zergling";"Larva";68;1
"Unit";"Overlord";"Larva";69;0
"Unit";"Queen";"Hatchery";69;2
"Unit";"Zergling";"Larva";71;1
"Unit";"Zergling";"Larva";72;1
"Unit";"Queen";"Hatchery";82;2
"Building";"Hatchery";NA;87;0
"Unit";"Overlord";"Larva";87;0
"Unit";"Zergling";"Larva";87;1
"Unit";"Zergling";"Larva";88;1
"Unit";"Zergling";"Larva";89;1
"Unit";"Zergling";"Larva";90;1
"Building";"CreepTumorQueen";NA;91;0
"Building";"CreepTumorQueen";NA;91;0
"Unit";"Zergling";"Larva";94;1
"Unit";"Zergling";"Larva";95;1
"Unit";"Zergling";"Larva";96;1
"Unit";"Zergling";"Larva";97;1
"Unit";"Zergling";"Larva";98;1
"Unit";"Zergling";"Larva";99;1
"Building";"CreepTumorQueen";NA;100;0
"Unit";"Zergling";"Larva";100;1
"Unit";"Zergling";"Larva";101;1
"Building";"Hatchery";NA;102;0
"Unit";"Zergling";"Larva";102;1
"Unit";"Zergling";"Larva";103;1
"Building";"EvolutionChamber";NA;104;0
"Unit";"Queen";"Hatchery";104;2
"Building";"Extractor";NA;106;0
"Building";"RoachWarren";NA;106;0
"Unit";"Zergling";"Larva";106;1
"Unit";"Zergling";"Larva";107;1
"Unit";"Zergling";"Larva";108;1
"Unit";"Zergling";"Larva";109;1
"Unit";"Overlord";"Larva";110;0
"Unit";"Overlord";"Larva";110;0
"Building";"CreepTumorQueen";NA;117;0
"Building";"CreepTumorQueen";NA;117;0
"Building";"CreepTumorQueen";NA;117;0
"Unit";"Overlord";"Larva";136;0
"Unit";"Roach";"Larva";136;2
"Unit";"Roach";"Larva";138;2
"Unit";"Roach";"Larva";140;2
"Unit";"Roach";"Larva";142;2
"Unit";"Roach";"Larva";144;2
"Unit";"Roach";"Larva";146;2
"Building";"CreepTumor";NA;148;0
"Building";"CreepTumorQueen";NA;148;0
"Unit";"Overlord";"Larva";148;0
"Unit";"Roach";"Larva";148;2
"Unit";"Roach";"Larva";150;2
"Building";"CreepTumorQueen";NA;152;0
"Building";"CreepTumorQueen";NA;152;0
"Building";"CreepTumor";NA;152;0
"Building";"CreepTumor";NA;152;0
"Unit";"Roach";"Larva";152;2
"Unit";"Roach";"Larva";154;2
"Unit";"Roach";"Larva";156;2
"Unit";"Overlord";"Larva";158;0
"Unit";"Zergling";"Larva";158;1
"Unit";"Zergling";"Larva";159;1
"Unit";"Zergling";"Larva";160;1
"Unit";"Zergling";"Larva";161;1
"Unit";"Zergling";"Larva";162;1
"Unit";"Zergling";"Larva";163;1
"Unit";"Zergling";"Larva";164;1
"Unit";"Zergling";"Larva";165;1
"Unit";"Zergling";"Larva";166;1
"Unit";"Zergling";"Larva";167;1
"Unit";"Zergling";"Larva";168;1
"Unit";"Zergling";"Larva";169;1
"Unit";"Zergling";"Larva";170;1
"Unit";"Zergling";"Larva";171;1
"Unit";"Zergling";"Larva";172;1
"Unit";"Zergling";"Larva";173;1
"Unit";"Zergling";"Larva";174;1
"Unit";"Zergling";"Larva";175;1
"Unit";"Zergling";"Larva";176;1
"Unit";"Zergling";"Larva";177;1
"Unit";"Zergling";"Larva";178;1
"Unit";"Zergling";"Larva";179;1
"Unit";"Zergling";"Larva";180;1
"Unit";"Zergling";"Larva";181;1
"Unit";"Overlord";"Larva";182;0
"Unit";"Overlord";"Larva";182;0
"Building";"Extractor";NA;182;0
"Building";"CreepTumorQueen";NA;182;0
"Building";"CreepTumorQueen";NA;182;0
"Building";"CreepTumorQueen";NA;182;0
"Unit";"Overlord";"Larva";182;0
"Unit";"Zergling";"Larva";182;1
"Unit";"Zergling";"Larva";183;1
"Unit";"Zergling";"Larva";184;1
"Unit";"Zergling";"Larva";185;1
"Unit";"Zergling";"Larva";186;1
"Unit";"Zergling";"Larva";187;1
"Unit";"Zergling";"Larva";188;1
"Unit";"Zergling";"Larva";189;1
"Unit";"Zergling";"Larva";190;1
"Unit";"Zergling";"Larva";191;1
"Unit";"Zergling";"Larva";192;1
"Unit";"Zergling";"Larva";193;1
"Unit";"Zergling";"Larva";194;1
"Unit";"Zergling";"Larva";195;1
"Unit";"Zergling";"Larva";196;1
"Unit";"Zergling";"Larva";197;1
"Unit";"Zergling";"Larva";198;1
"Unit";"Zergling";"Larva";199;1
"Unit";"Zergling";"Larva";200;1
"Unit";"Zergling";"Larva";201;1
"Unit";"Zergling";"Larva";202;1
"Unit";"Zergling";"Larva";203;1
"Unit";"Zergling";"Larva";204;1
"Unit";"Zergling";"Larva";205;1
"Upgrade";"SprayZerg";NA;206;0
"Upgrade";"SprayZerg";NA;206;0
"Upgrade";"zerglingmovementspeed";NA;206;0
"Upgrade";"SprayZerg";NA;206;0
"Upgrade";"SprayZerg";NA;206;0
"Upgrade";"SprayZerg";NA;206;0
"Upgrade";"SprayZerg";NA;206;0
