"type";"unit_name";"on_building";"total_supply";"supply"
"Unit";"Overlord";"Larva";13;0
"Building";"Extractor";NA;17;0
"Building";"Hatchery";NA;16;0
"Building";"SpawningPool";NA;19;0
"Unit";"Overlord";"Larva";22;0
"Unit";"Zergling";"Larva";23;1
"Unit";"Zergling";"Larva";23;1
"Unit";"Zergling";"Larva";23;1
"Unit";"Zergling";"Larva";23;1
"Unit";"Queen";"Hatchery";23;2
"Unit";"Queen";"Hatchery";23;2
"Unit";"Overlord";"Larva";36;0
"Building";"Hatchery";NA;27;0
"Unit";"Queen";"Hatchery";37;2
"Unit";"Queen";"Hatchery";38;2
"Unit";"Overlord";"Larva";38;0
"Unit";"Overlord";"Larva";44;0
"Unit";"Zergling";"Larva";50;1
"Unit";"Zergling";"Larva";50;1
"Unit";"Zergling";"Larva";50;1
"Unit";"Zergling";"Larva";50;1
"Unit";"Zergling";"Larva";50;1
"Unit";"Zergling";"Larva";50;1
"Unit";"Zergling";"Larva";50;1
"Unit";"Zergling";"Larva";50;1
"Unit";"Zergling";"Larva";50;1
"Unit";"Zergling";"Larva";50;1
"Unit";"Zergling";"Larva";50;1
"Unit";"Zergling";"Larva";50;1
"Building";"CreepTumorQueen";NA;50;0
"Building";"CreepTumorQueen";NA;50;0
"Unit";"Overlord";"Larva";50;0
"Unit";"Overlord";"Larva";50;0
"Unit";"Queen";"Hatchery";50;2
"Unit";"Queen";"Hatchery";50;2
"Building";"SporeCrawler";NA;63;0
"Building";"SporeCrawler";NA;64;0
"Building";"SporeCrawler";NA;64;0
"Unit";"Overlord";"Larva";75;0
"Building";"CreepTumorQueen";NA;79;0
"Building";"CreepTumor";NA;79;0
"Building";"CreepTumorQueen";NA;80;0
"Unit";"Queen";"Hatchery";75;2
"Unit";"Overlord";"Larva";80;0
"Building";"CreepTumor";NA;94;0
"Building";"CreepTumor";NA;95;0
"Building";"CreepTumorQueen";NA;95;0
"Building";"CreepTumor";NA;95;0
"Building";"CreepTumorQueen";NA;96;0
"Building";"EvolutionChamber";NA;91;0
"Building";"EvolutionChamber";NA;92;0
"Unit";"Overlord";"Larva";99;0
"Unit";"Queen";"Hatchery";95;2
"Building";"CreepTumor";NA;116;0
"Building";"CreepTumor";NA;116;0
"Building";"Extractor";NA;106;0
"Building";"CreepTumor";NA;116;0
"Unit";"Overlord";"Larva";106;0
"Building";"Extractor";NA;106;0
"Building";"Extractor";NA;106;0
"Building";"CreepTumor";NA;116;0
"Building";"CreepTumor";NA;116;0
"Building";"CreepTumorQueen";NA;116;0
"Building";"Extractor";NA;106;0
"Building";"Extractor";NA;108;0
"Building";"CreepTumorQueen";NA;122;0
"Building";"CreepTumorQueen";NA;122;0
"Unit";"Overlord";"Larva";116;0
"Unit";"Overlord";"Larva";116;0
"Building";"CreepTumorQueen";NA;122;0
"Building";"CreepTumorQueen";NA;122;0
"Building";"CreepTumor";NA;122;0
"Unit";"Zergling";"Larva";122;1
"Unit";"Zergling";"Larva";122;1
"Unit";"Zergling";"Larva";122;1
"Unit";"Zergling";"Larva";122;1
"Unit";"Zergling";"Larva";122;1
"Unit";"Zergling";"Larva";122;1
"Unit";"Zergling";"Larva";122;1
"Unit";"Zergling";"Larva";122;1
"Unit";"Zergling";"Larva";122;1
"Unit";"Zergling";"Larva";122;1
"Unit";"Overlord";"Larva";122;0
"Unit";"Overlord";"Larva";122;0
"Unit";"Zergling";"Larva";122;1
"Unit";"Zergling";"Larva";122;1
"Unit";"Zergling";"Larva";122;1
"Unit";"Zergling";"Larva";122;1
"Unit";"Zergling";"Larva";122;1
"Unit";"Zergling";"Larva";122;1
"Unit";"Zergling";"Larva";122;1
"Unit";"Zergling";"Larva";122;1
"Unit";"Zergling";"Larva";122;1
"Unit";"Zergling";"Larva";122;1
"Unit";"Zergling";"Larva";122;1
"Unit";"Zergling";"Larva";122;1
"Unit";"Zergling";"Larva";122;1
"Unit";"Zergling";"Larva";122;1
"Building";"CreepTumor";NA;132;0
"Building";"CreepTumor";NA;132;0
"Unit";"Zergling";"Larva";122;1
"Unit";"Zergling";"Larva";122;1
"Unit";"Zergling";"Larva";122;1
"Unit";"Zergling";"Larva";122;1
"Unit";"Zergling";"Larva";122;1
"Unit";"Zergling";"Larva";122;1
"Unit";"Zergling";"Larva";122;1
"Unit";"Zergling";"Larva";122;1
"Building";"CreepTumor";NA;132;0
"Building";"CreepTumor";NA;132;0
"Building";"CreepTumor";NA;132;0
"Building";"CreepTumor";NA;132;0
"Building";"CreepTumor";NA;132;0
"Building";"CreepTumor";NA;132;0
"Building";"CreepTumor";NA;132;0
"Unit";"Zergling";"Larva";132;1
"Unit";"Zergling";"Larva";132;1
"Unit";"Zergling";"Larva";132;1
"Unit";"Zergling";"Larva";132;1
"Unit";"Zergling";"Larva";132;1
"Unit";"Zergling";"Larva";132;1
"Unit";"Zergling";"Larva";154;1
"Unit";"Zergling";"Larva";154;1
"Unit";"Zergling";"Larva";154;1
"Unit";"Zergling";"Larva";154;1
"Building";"CreepTumor";NA;160;0
"Building";"CreepTumor";NA;160;0
"Building";"CreepTumor";NA;160;0
"Building";"CreepTumor";NA;160;0
"Building";"BanelingNest";NA;122;0
"Building";"CreepTumor";NA;160;0
"Building";"CreepTumor";NA;160;0
"Building";"CreepTumor";NA;160;0
"Building";"Hatchery";NA;116;0
"Building";"CreepTumor";NA;169;0
"Building";"CreepTumor";NA;174;0
"Unit";"Overlord";"Larva";164;0
"Unit";"Overlord";"Larva";164;0
"Building";"InfestationPit";NA;154;0
"Unit";"Baneling";"Zergling";174;0
"Unit";"Baneling";"Zergling";174;0
"Unit";"Baneling";"Zergling";174;0
"Unit";"Baneling";"Zergling";174;0
"Unit";"Baneling";"Zergling";174;0
"Unit";"Baneling";"Zergling";174;0
"Unit";"Baneling";"Zergling";174;0
"Unit";"Baneling";"Zergling";174;0
"Unit";"Baneling";"Zergling";174;0
"Unit";"Baneling";"Zergling";174;0
"Unit";"Baneling";"Zergling";174;0
"Unit";"Baneling";"Zergling";174;0
"Unit";"Baneling";"Zergling";174;0
"Unit";"Zergling";"Larva";174;1
"Unit";"Zergling";"Larva";174;1
"Unit";"Zergling";"Larva";174;1
"Unit";"Zergling";"Larva";174;1
"Upgrade";"ZergMeleeWeaponsLevel1";"EvolutionChamber";122;0
"Upgrade";"ZergGroundArmorsLevel1";"EvolutionChamber";122;0
"Unit";"Zergling";"Larva";174;1
"Unit";"Zergling";"Larva";174;1
"Building";"CreepTumorQueen";NA;174;0
"Unit";"Zergling";"Larva";174;1
"Unit";"Zergling";"Larva";174;1
"Unit";"Zergling";"Larva";174;1
"Unit";"Zergling";"Larva";174;1
"Unit";"Zergling";"Larva";174;1
"Unit";"Zergling";"Larva";174;1
"Unit";"Zergling";"Larva";174;1
"Unit";"Zergling";"Larva";174;1
"Unit";"Zergling";"Larva";174;1
"Unit";"Zergling";"Larva";174;1
"Unit";"Zergling";"Larva";174;1
"Unit";"Zergling";"Larva";174;1
"Unit";"Zergling";"Larva";174;1
"Unit";"Zergling";"Larva";174;1
"Unit";"Zergling";"Larva";174;1
"Unit";"Zergling";"Larva";174;1
"Unit";"Zergling";"Larva";174;1
"Unit";"Zergling";"Larva";174;1
"Unit";"Zergling";"Larva";174;1
"Unit";"Zergling";"Larva";174;1
"Building";"CreepTumorQueen";NA;174;0
"Building";"CreepTumorQueen";NA;174;0
"Building";"CreepTumor";NA;174;0
"Building";"CreepTumor";NA;174;0
"Building";"CreepTumor";NA;174;0
"Building";"CreepTumorQueen";NA;174;0
"Building";"CreepTumor";NA;174;0
"Building";"CreepTumor";NA;174;0
"Building";"CreepTumor";NA;178;0
"Building";"CreepTumor";NA;178;0
"Building";"Extractor";NA;174;0
"Unit";"Zergling";"Larva";178;1
"Unit";"Zergling";"Larva";178;1
"Unit";"Zergling";"Larva";178;1
"Unit";"Zergling";"Larva";178;1
"Unit";"Zergling";"Larva";178;1
"Unit";"Zergling";"Larva";178;1
"Unit";"Zergling";"Larva";178;1
"Unit";"Zergling";"Larva";178;1
"Unit";"Zergling";"Larva";200;1
"Unit";"Zergling";"Larva";200;1
"Unit";"Zergling";"Larva";200;1
"Unit";"Zergling";"Larva";200;1
"Building";"Extractor";NA;200;0
"Building";"CreepTumorQueen";NA;210;0
"Unit";"Baneling";"Zergling";210;0
"Unit";"Baneling";"Zergling";210;0
"Unit";"Baneling";"Zergling";210;0
"Unit";"Baneling";"Zergling";210;0
"Unit";"Baneling";"Zergling";210;0
"Unit";"Baneling";"Zergling";210;0
"Unit";"Baneling";"Zergling";210;0
"Unit";"Baneling";"Zergling";210;0
"Unit";"Baneling";"Zergling";212;0
"Unit";"Baneling";"Zergling";212;0
"Building";"CreepTumor";NA;214;0
"Building";"CreepTumor";NA;214;0
"Unit";"Zergling";"Larva";210;1
"Unit";"Zergling";"Larva";210;1
"Unit";"Baneling";"Zergling";214;0
"Unit";"Zergling";"Larva";210;1
"Unit";"Zergling";"Larva";210;1
"Unit";"Zergling";"Larva";210;1
"Unit";"Zergling";"Larva";210;1
"Unit";"Zergling";"Larva";210;1
"Unit";"Zergling";"Larva";210;1
"Unit";"Zergling";"Larva";210;1
"Unit";"Zergling";"Larva";210;1
"Unit";"Zergling";"Larva";210;1
"Unit";"Zergling";"Larva";210;1
"Unit";"Zergling";"Larva";210;1
"Unit";"Zergling";"Larva";210;1
"Unit";"Zergling";"Larva";210;1
"Unit";"Zergling";"Larva";210;1
"Unit";"Zergling";"Larva";210;1
"Unit";"Zergling";"Larva";210;1
"Unit";"Zergling";"Larva";210;1
"Unit";"Zergling";"Larva";210;1
"Unit";"Zergling";"Larva";210;1
"Unit";"Zergling";"Larva";210;1
"Unit";"Zergling";"Larva";210;1
"Unit";"Zergling";"Larva";210;1
"Unit";"Zergling";"Larva";210;1
"Unit";"Zergling";"Larva";210;1
"Unit";"Zergling";"Larva";210;1
"Unit";"Zergling";"Larva";210;1
"Unit";"Zergling";"Larva";214;1
"Unit";"Zergling";"Larva";214;1
"Unit";"Zergling";"Larva";214;1
"Unit";"Zergling";"Larva";214;1
"Unit";"Zergling";"Larva";214;1
"Unit";"Zergling";"Larva";214;1
"Building";"CreepTumor";NA;214;0
"Building";"CreepTumor";NA;214;0
"Unit";"Baneling";"Zergling";214;0
"Unit";"Baneling";"Zergling";214;0
"Unit";"Baneling";"Zergling";214;0
"Unit";"Baneling";"Zergling";214;0
"Unit";"Baneling";"Zergling";214;0
"Unit";"Baneling";"Zergling";214;0
"Unit";"Baneling";"Zergling";214;0
"Unit";"Baneling";"Zergling";214;0
"Building";"CreepTumor";NA;230;0
"Unit";"Zergling";"Larva";214;1
"Unit";"Zergling";"Larva";214;1
"Building";"CreepTumor";NA;242;0
"Unit";"Overlord";"Larva";242;0
"Unit";"Overlord";"Larva";242;0
"Unit";"Overlord";"Larva";242;0
"Building";"CreepTumor";NA;248;0
"Building";"CreepTumor";NA;248;0
"Building";"CreepTumor";NA;250;0
"Building";"CreepTumor";NA;250;0
"Unit";"Baneling";"Zergling";248;0
"Unit";"Zergling";"Larva";248;1
"Unit";"Zergling";"Larva";248;1
"Unit";"Zergling";"Larva";248;1
"Unit";"Zergling";"Larva";248;1
"Unit";"Zergling";"Larva";248;1
"Unit";"Zergling";"Larva";248;1
"Unit";"Baneling";"Zergling";248;0
"Unit";"Zergling";"Larva";248;1
"Unit";"Zergling";"Larva";248;1
"Unit";"Overlord";"Larva";250;0
"Unit";"Overlord";"Larva";250;0
"Unit";"Overlord";"Larva";250;0
"Building";"CreepTumor";NA;258;0
"Building";"CreepTumor";NA;258;0
"Building";"CreepTumor";NA;258;0
"Building";"CreepTumor";NA;258;0
"Building";"CreepTumor";NA;258;0
"Building";"CreepTumor";NA;258;0
"Building";"Hatchery";NA;210;0
"Building";"CreepTumorQueen";NA;258;0
"Unit";"Zergling";"Larva";258;1
"Unit";"Zergling";"Larva";258;1
"Unit";"Zergling";"Larva";258;1
"Unit";"Zergling";"Larva";258;1
"Unit";"Zergling";"Larva";258;1
"Unit";"Zergling";"Larva";258;1
"Building";"CreepTumorQueen";NA;258;0
"Unit";"Zergling";"Larva";258;1
"Unit";"Zergling";"Larva";258;1
"Unit";"Zergling";"Larva";258;1
"Unit";"Zergling";"Larva";258;1
"Unit";"Zergling";"Larva";258;1
"Unit";"Zergling";"Larva";258;1
"Unit";"Zergling";"Larva";258;1
"Unit";"Zergling";"Larva";258;1
"Unit";"Zergling";"Larva";258;1
"Unit";"Zergling";"Larva";258;1
"Unit";"Zergling";"Larva";258;1
"Unit";"Zergling";"Larva";258;1
"Unit";"Zergling";"Larva";258;1
"Unit";"Zergling";"Larva";258;1
"Unit";"Zergling";"Larva";258;1
"Unit";"Zergling";"Larva";258;1
"Unit";"Zergling";"Larva";258;1
"Unit";"Zergling";"Larva";258;1
"Unit";"Zergling";"Larva";258;1
"Unit";"Zergling";"Larva";258;1
"Unit";"Zergling";"Larva";258;1
"Unit";"Zergling";"Larva";258;1
"Unit";"Zergling";"Larva";258;1
"Unit";"Zergling";"Larva";258;1
"Unit";"Baneling";"Zergling";258;0
"Unit";"Baneling";"Zergling";258;0
"Unit";"Baneling";"Zergling";258;0
"Unit";"Baneling";"Zergling";258;0
"Unit";"Baneling";"Zergling";258;0
"Unit";"Baneling";"Zergling";258;0
"Unit";"Baneling";"Zergling";258;0
"Unit";"Baneling";"Zergling";258;0
"Unit";"Baneling";"Zergling";258;0
"Unit";"Baneling";"Zergling";258;0
"Unit";"Baneling";"Zergling";258;0
"Unit";"Baneling";"Zergling";258;0
"Unit";"Baneling";"Zergling";258;0
"Unit";"Baneling";"Zergling";258;0
"Unit";"Baneling";"Zergling";258;0
"Unit";"Baneling";"Zergling";258;0
"Unit";"Baneling";"Zergling";258;0
"Unit";"Baneling";"Zergling";258;0
"Unit";"Baneling";"Zergling";258;0
"Unit";"Baneling";"Zergling";258;0
"Unit";"Baneling";"Zergling";258;0
"Unit";"Baneling";"Zergling";258;0
"Unit";"Baneling";"Zergling";258;0
"Building";"CreepTumorQueen";NA;258;0
"Building";"CreepTumorQueen";NA;258;0
"Building";"CreepTumorQueen";NA;258;0
"Building";"CreepTumorQueen";NA;258;0
"Building";"Spire";NA;214;0
"Unit";"Zergling";"Larva";258;1
"Unit";"Zergling";"Larva";258;1
"Unit";"Zergling";"Larva";258;1
"Unit";"Zergling";"Larva";258;1
"Unit";"Zergling";"Larva";258;1
"Unit";"Zergling";"Larva";258;1
"Unit";"Zergling";"Larva";258;1
"Unit";"Zergling";"Larva";258;1
"Unit";"Zergling";"Larva";258;1
"Unit";"Zergling";"Larva";258;1
"Building";"CreepTumor";NA;288;0
"Building";"CreepTumorQueen";NA;288;0
"Building";"CreepTumor";NA;288;0
"Building";"UltraliskCavern";NA;258;0
"Unit";"Zergling";"Larva";307;1
"Unit";"Zergling";"Larva";307;1
"Unit";"Zergling";"Larva";307;1
"Unit";"Zergling";"Larva";307;1
"Unit";"Zergling";"Larva";307;1
"Unit";"Zergling";"Larva";307;1
"Unit";"Zergling";"Larva";307;1
"Unit";"Zergling";"Larva";307;1
"Unit";"Zergling";"Larva";307;1
"Unit";"Zergling";"Larva";307;1
"Unit";"Zergling";"Larva";307;1
"Unit";"Zergling";"Larva";307;1
"Unit";"Zergling";"Larva";307;1
"Unit";"Zergling";"Larva";307;1
"Unit";"Zergling";"Larva";307;1
"Unit";"Zergling";"Larva";307;1
"Unit";"Zergling";"Larva";307;1
"Unit";"Zergling";"Larva";307;1
"Unit";"Zergling";"Larva";307;1
"Unit";"Zergling";"Larva";307;1
"Unit";"Zergling";"Larva";307;1
"Unit";"Zergling";"Larva";307;1
"Building";"CreepTumorQueen";NA;307;0
"Building";"CreepTumorQueen";NA;307;0
"Upgrade";"ZergMeleeWeaponsLevel2";"EvolutionChamber";220;0
"Upgrade";"ZergGroundArmorsLevel2";"EvolutionChamber";230;0
"Building";"CreepTumorQueen";NA;307;0
"Building";"CreepTumorQueen";NA;307;0
"Building";"CreepTumorQueen";NA;307;0
"Building";"CreepTumorQueen";NA;307;0
"Unit";"Zergling";"Larva";307;1
"Unit";"Zergling";"Larva";307;1
"Unit";"Zergling";"Larva";307;1
"Unit";"Zergling";"Larva";307;1
"Unit";"Zergling";"Larva";307;1
"Unit";"Zergling";"Larva";307;1
"Unit";"Zergling";"Larva";307;1
"Unit";"Zergling";"Larva";307;1
"Unit";"Zergling";"Larva";307;1
"Unit";"Zergling";"Larva";307;1
"Unit";"Zergling";"Larva";307;1
"Unit";"Zergling";"Larva";307;1
"Unit";"Zergling";"Larva";307;1
"Unit";"Zergling";"Larva";307;1
"Unit";"Zergling";"Larva";307;1
"Unit";"Zergling";"Larva";307;1
"Building";"CreepTumorQueen";NA;307;0
"Unit";"Zergling";"Larva";307;1
"Unit";"Zergling";"Larva";307;1
"Unit";"Zergling";"Larva";307;1
"Unit";"Zergling";"Larva";307;1
"Unit";"Zergling";"Larva";307;1
"Unit";"Zergling";"Larva";307;1
"Building";"CreepTumorQueen";NA;329;0
"Building";"CreepTumorQueen";NA;329;0
"Building";"CreepTumorQueen";NA;329;0
"Building";"CreepTumorQueen";NA;329;0
"Unit";"Zergling";"Larva";307;1
"Unit";"Zergling";"Larva";307;1
"Unit";"Zergling";"Larva";307;1
"Unit";"Zergling";"Larva";307;1
"Unit";"Zergling";"Larva";307;1
"Unit";"Zergling";"Larva";307;1
"Unit";"Zergling";"Larva";307;1
"Unit";"Zergling";"Larva";307;1
"Unit";"Zergling";"Larva";307;1
"Unit";"Zergling";"Larva";307;1
"Unit";"Zergling";"Larva";307;1
"Unit";"Zergling";"Larva";307;1
"Building";"CreepTumorQueen";NA;329;0
"Unit";"Zergling";"Larva";329;1
"Unit";"Zergling";"Larva";329;1
"Unit";"Zergling";"Larva";329;1
"Unit";"Zergling";"Larva";329;1
"Unit";"Zergling";"Larva";329;1
"Unit";"Zergling";"Larva";329;1
"Unit";"Zergling";"Larva";329;1
"Unit";"Zergling";"Larva";329;1
"Unit";"Zergling";"Larva";347;1
"Unit";"Zergling";"Larva";347;1
"Unit";"Baneling";"Zergling";373;0
"Unit";"Baneling";"Zergling";373;0
"Unit";"Baneling";"Zergling";373;0
"Unit";"Baneling";"Zergling";373;0
"Unit";"Baneling";"Zergling";373;0
"Unit";"Baneling";"Zergling";373;0
"Unit";"Baneling";"Zergling";373;0
"Unit";"Baneling";"Zergling";373;0
"Unit";"Baneling";"Zergling";373;0
"Unit";"Baneling";"Zergling";373;0
"Unit";"Baneling";"Zergling";373;0
"Unit";"Baneling";"Zergling";373;0
"Unit";"Baneling";"Zergling";373;0
"Unit";"Baneling";"Zergling";373;0
"Unit";"Baneling";"Zergling";373;0
"Unit";"Baneling";"Zergling";373;0
"Unit";"Ultralisk";"Larva";355;6
"Unit";"Ultralisk";"Larva";355;6
"Building";"CreepTumor";NA;373;0
"Building";"CreepTumor";NA;373;0
"Building";"CreepTumor";NA;373;0
"Building";"CreepTumor";NA;373;0
"Building";"CreepTumor";NA;373;0
"Building";"CreepTumor";NA;373;0
"Building";"CreepTumor";NA;373;0
"Building";"CreepTumor";NA;373;0
"Building";"CreepTumor";NA;373;0
"Building";"CreepTumor";NA;373;0
"Building";"CreepTumor";NA;373;0
"Building";"CreepTumor";NA;378;0
"Building";"CreepTumor";NA;378;0
"Building";"SpawningPool";NA;355;0
"Unit";"Baneling";"Zergling";378;0
"Unit";"Baneling";"Zergling";390;0
"Unit";"Baneling";"Zergling";390;0
"Unit";"Baneling";"Zergling";390;0
"Unit";"Baneling";"Zergling";390;0
"Unit";"Baneling";"Zergling";390;0
"Unit";"Baneling";"Zergling";390;0
"Unit";"Baneling";"Zergling";390;0
"Unit";"Baneling";"Zergling";390;0
"Unit";"Baneling";"Zergling";390;0
"Unit";"Baneling";"Zergling";390;0
"Unit";"Baneling";"Zergling";390;0
"Unit";"Baneling";"Zergling";390;0
