"type";"unit_name";"on_building";"total_supply";"supply"
"Unit";"Overlord";"Larva";13;0
"Building";"Extractor";NA;17;0
"Unit";"Overlord";"Larva";22;0
"Building";"SpawningPool";NA;19;0
"Building";"Hatchery";NA;17;0
"Unit";"Zergling";"Larva";22;1
"Unit";"Zergling";"Larva";22;1
"Unit";"Zergling";"Larva";22;1
"Unit";"Zergling";"Larva";22;1
"Unit";"Queen";"Hatchery";22;2
"Unit";"Queen";"Hatchery";22;2
"Unit";"Overlord";"Larva";36;0
"Unit";"Zergling";"Larva";38;1
"Unit";"Zergling";"Larva";38;1
"Unit";"Queen";"Hatchery";39;2
"Unit";"Queen";"Hatchery";39;2
"Unit";"Overlord";"Larva";47;0
"Building";"Extractor";NA;47;0
"Building";"CreepTumorQueen";NA;49;0
"Building";"CreepTumorQueen";NA;53;0
"Building";"EvolutionChamber";NA;47;0
"Building";"EvolutionChamber";NA;47;0
"Unit";"Overlord";"Larva";55;0
"Building";"CreepTumor";NA;57;0
"Building";"CreepTumorQueen";NA;59;0
"Building";"CreepTumor";NA;59;0
"Building";"CreepTumorQueen";NA;59;0
"Unit";"Queen";"Hatchery";55;2
"Building";"CreepTumorQueen";NA;59;0
"Unit";"Overlord";"Larva";59;0
"Building";"Hatchery";NA;47;0
"Unit";"Queen";"Hatchery";59;2
"Building";"CreepTumor";NA;64;0
"Building";"CreepTumor";NA;64;0
"Building";"CreepTumor";NA;64;0
"Building";"CreepTumorQueen";NA;70;0
"Building";"CreepTumorQueen";NA;70;0
"Building";"BanelingNest";NA;59;0
"Unit";"Zergling";"Larva";72;1
"Unit";"Zergling";"Larva";72;1
"Unit";"Zergling";"Larva";72;1
"Unit";"Zergling";"Larva";72;1
"Unit";"Zergling";"Larva";72;1
"Unit";"Zergling";"Larva";72;1
"Unit";"Zergling";"Larva";72;1
"Unit";"Zergling";"Larva";72;1
"Unit";"Zergling";"Larva";72;1
"Unit";"Zergling";"Larva";72;1
"Building";"CreepTumorQueen";NA;73;0
"Unit";"Queen";"Hatchery";64;2
"Building";"CreepTumorQueen";NA;83;0
"Building";"CreepTumorQueen";NA;83;0
"Building";"CreepTumor";NA;83;0
"Building";"CreepTumor";NA;83;0
"Building";"CreepTumor";NA;83;0
"Building";"SporeCrawler";NA;73;0
"Building";"SporeCrawler";NA;73;0
"Building";"CreepTumorQueen";NA;85;0
"Building";"SporeCrawler";NA;73;0
"Building";"CreepTumor";NA;93;0
"Building";"Extractor";NA;93;0
"Unit";"Overlord";"Larva";93;0
"Building";"CreepTumor";NA;94;0
"Building";"Extractor";NA;93;0
"Building";"CreepTumor";NA;94;0
"Upgrade";"ZergGroundArmorsLevel1";"EvolutionChamber";64;0
"Upgrade";"ZergMeleeWeaponsLevel1";"EvolutionChamber";64;0
"Building";"CreepTumor";NA;99;0
"Building";"CreepTumor";NA;99;0
"Building";"CreepTumor";NA;99;0
"Building";"CreepTumor";NA;99;0
"Unit";"Overlord";"Larva";108;0
"Unit";"Overlord";"Larva";108;0
"Building";"CreepTumor";NA;109;0
"Building";"CreepTumor";NA;109;0
"Building";"CreepTumor";NA;109;0
"Building";"CreepTumor";NA;109;0
"Building";"HydraliskDen";NA;99;0
"Building";"Hatchery";NA;94;0
"Unit";"Zergling";"Larva";109;1
"Unit";"Zergling";"Larva";109;1
"Unit";"Overlord";"Larva";109;0
"Unit";"Zergling";"Larva";109;1
"Unit";"Zergling";"Larva";109;1
"Unit";"Zergling";"Larva";109;1
"Unit";"Zergling";"Larva";109;1
"Unit";"Zergling";"Larva";109;1
"Unit";"Zergling";"Larva";109;1
"Unit";"Zergling";"Larva";109;1
"Unit";"Zergling";"Larva";109;1
"Unit";"Zergling";"Larva";109;1
"Unit";"Zergling";"Larva";109;1
"Unit";"Hydralisk";"Larva";109;2
"Unit";"Hydralisk";"Larva";109;2
"Unit";"Hydralisk";"Larva";109;2
"Unit";"Hydralisk";"Larva";109;2
"Unit";"Hydralisk";"Larva";109;2
"Building";"CreepTumor";NA;111;0
"Building";"CreepTumor";NA;113;0
"Building";"Extractor";NA;109;0
"Building";"Extractor";NA;109;0
"Building";"CreepTumor";NA;121;0
"Building";"CreepTumor";NA;121;0
"Building";"CreepTumorQueen";NA;122;0
"Building";"CreepTumor";NA;121;0
"Building";"CreepTumorQueen";NA;133;0
"Building";"CreepTumor";NA;123;0
"Building";"CreepTumor";NA;133;0
"Building";"CreepTumor";NA;133;0
"Building";"InfestationPit";NA;109;0
"Unit";"Queen";"Hatchery";109;2
"Building";"CreepTumorQueen";NA;133;0
"Building";"CreepTumorQueen";NA;133;0
"Unit";"Zergling";"Larva";133;1
"Unit";"Zergling";"Larva";133;1
"Unit";"Zergling";"Larva";133;1
"Unit";"Zergling";"Larva";133;1
"Unit";"Zergling";"Larva";133;1
"Unit";"Zergling";"Larva";133;1
"Unit";"Zergling";"Larva";133;1
"Unit";"Zergling";"Larva";133;1
"Unit";"Overlord";"Larva";133;0
"Building";"CreepTumor";NA;135;0
"Building";"CreepTumor";NA;137;0
"Unit";"Overlord";"Larva";133;0
"Building";"CreepTumor";NA;136;0
"Unit";"Overlord";"Larva";133;0
"Unit";"Overlord";"Larva";133;0
"Building";"CreepTumor";NA;138;0
"Unit";"Hydralisk";"Larva";133;2
"Building";"Extractor";NA;133;0
"Unit";"Queen";"Hatchery";133;2
"Building";"Extractor";NA;138;0
"Upgrade";"ZergMissileWeaponsLevel1";"EvolutionChamber";109;0
"Unit";"Baneling";"Zergling";148;0
"Unit";"Baneling";"Zergling";148;0
"Unit";"Baneling";"Zergling";148;0
"Unit";"Baneling";"Zergling";148;0
"Unit";"Baneling";"Zergling";148;0
"Unit";"Baneling";"Zergling";148;0
"Unit";"Baneling";"Zergling";148;0
"Unit";"Baneling";"Zergling";148;0
"Unit";"Baneling";"Zergling";148;0
"Unit";"Baneling";"Zergling";148;0
"Unit";"Baneling";"Zergling";148;0
"Unit";"Zergling";"Larva";150;1
"Unit";"Zergling";"Larva";150;1
"Unit";"Zergling";"Larva";150;1
"Unit";"Zergling";"Larva";150;1
"Unit";"Zergling";"Larva";150;1
"Unit";"Zergling";"Larva";150;1
"Unit";"Zergling";"Larva";150;1
"Unit";"Zergling";"Larva";150;1
"Unit";"Zergling";"Larva";150;1
"Unit";"Zergling";"Larva";150;1
"Unit";"Zergling";"Larva";150;1
"Unit";"Zergling";"Larva";150;1
"Unit";"Zergling";"Larva";150;1
"Unit";"Zergling";"Larva";150;1
"Unit";"Zergling";"Larva";150;1
"Unit";"Zergling";"Larva";150;1
"Unit";"Zergling";"Larva";150;1
"Unit";"Zergling";"Larva";150;1
"Upgrade";"EvolveGroovedSpines";"HydraliskDen";133;0
"Unit";"Hydralisk";"Larva";150;2
"Unit";"Hydralisk";"Larva";150;2
"Upgrade";"ZergGroundArmorsLevel2";"EvolutionChamber";109;0
"Unit";"Zergling";"Larva";172;1
"Unit";"Zergling";"Larva";172;1
"Unit";"Zergling";"Larva";172;1
"Unit";"Zergling";"Larva";172;1
"Unit";"Zergling";"Larva";172;1
"Unit";"Zergling";"Larva";172;1
"Unit";"Zergling";"Larva";172;1
"Unit";"Zergling";"Larva";172;1
"Unit";"Zergling";"Larva";172;1
"Unit";"Zergling";"Larva";172;1
"Unit";"Hydralisk";"Larva";172;2
"Unit";"Hydralisk";"Larva";172;2
"Unit";"Hydralisk";"Larva";172;2
"Unit";"Hydralisk";"Larva";172;2
"Unit";"Zergling";"Larva";172;1
"Unit";"Zergling";"Larva";172;1
"Unit";"Zergling";"Larva";172;1
"Unit";"Zergling";"Larva";172;1
"Unit";"Baneling";"Zergling";172;0
"Unit";"Baneling";"Zergling";172;0
"Unit";"Baneling";"Zergling";172;0
"Unit";"Baneling";"Zergling";172;0
"Unit";"Baneling";"Zergling";172;0
"Unit";"Baneling";"Zergling";172;0
"Unit";"Baneling";"Zergling";172;0
"Unit";"Baneling";"Zergling";172;0
"Unit";"Zergling";"Larva";182;1
"Unit";"Zergling";"Larva";182;1
"Unit";"Zergling";"Larva";182;1
"Unit";"Zergling";"Larva";182;1
"Unit";"Zergling";"Larva";182;1
"Unit";"Zergling";"Larva";182;1
"Unit";"Zergling";"Larva";182;1
"Unit";"Zergling";"Larva";182;1
"Unit";"Hydralisk";"Larva";182;2
"Unit";"Hydralisk";"Larva";182;2
"Unit";"Hydralisk";"Larva";182;2
"Building";"CreepTumor";NA;194;0
"Building";"CreepTumor";NA;194;0
"Building";"CreepTumor";NA;194;0
"Building";"CreepTumor";NA;202;0
"Building";"CreepTumor";NA;202;0
"Building";"CreepTumor";NA;202;0
"Building";"CreepTumor";NA;202;0
"Unit";"Queen";"Hatchery";182;2
"Building";"CreepTumor";NA;208;0
"Building";"CreepTumor";NA;210;0
"Building";"CreepTumor";NA;210;0
"Building";"CreepTumor";NA;210;0
"Building";"CreepTumor";NA;210;0
"Building";"CreepTumor";NA;210;0
"Building";"CreepTumor";NA;211;0
"Building";"CreepTumor";NA;211;0
"Building";"CreepTumor";NA;214;0
"Building";"Extractor";NA;210;0
"Building";"CreepTumorQueen";NA;219;0
"Building";"Extractor";NA;210;0
"Unit";"Infestor";"Larva";208;2
"Unit";"Infestor";"Larva";208;2
"Unit";"Infestor";"Larva";208;2
"Building";"Hatchery";NA;182;0
"Building";"Hatchery";NA;182;0
"Unit";"Zergling";"Larva";219;1
"Unit";"Zergling";"Larva";219;1
"Unit";"Zergling";"Larva";219;1
"Unit";"Zergling";"Larva";219;1
"Unit";"Zergling";"Larva";219;1
"Unit";"Zergling";"Larva";219;1
"Unit";"Overlord";"Larva";219;0
"Unit";"Overlord";"Larva";219;0
"Unit";"Baneling";"Zergling";219;0
"Unit";"Baneling";"Zergling";219;0
"Building";"UltraliskCavern";NA;208;0
"Unit";"Baneling";"Zergling";219;0
"Unit";"Baneling";"Zergling";219;0
"Unit";"Baneling";"Zergling";219;0
"Unit";"Baneling";"Zergling";219;0
"Unit";"Baneling";"Zergling";219;0
"Unit";"Hydralisk";"Larva";219;2
"Unit";"Hydralisk";"Larva";219;2
"Unit";"Zergling";"Larva";231;1
"Unit";"Zergling";"Larva";231;1
"Unit";"Zergling";"Larva";231;1
"Unit";"Zergling";"Larva";231;1
"Unit";"Zergling";"Larva";231;1
"Unit";"Zergling";"Larva";231;1
"Unit";"Zergling";"Larva";231;1
"Unit";"Zergling";"Larva";231;1
"Unit";"Zergling";"Larva";231;1
"Unit";"Zergling";"Larva";231;1
"Unit";"Zergling";"Larva";231;1
"Unit";"Zergling";"Larva";231;1
"Unit";"Zergling";"Larva";231;1
"Unit";"Zergling";"Larva";231;1
"Unit";"Zergling";"Larva";231;1
"Unit";"Zergling";"Larva";231;1
"Unit";"Zergling";"Larva";231;1
"Unit";"Zergling";"Larva";231;1
"Unit";"Zergling";"Larva";231;1
"Unit";"Zergling";"Larva";231;1
"Unit";"Queen";"Hatchery";231;2
"Unit";"Infestor";"Larva";237;2
"Unit";"Zergling";"Larva";261;1
"Unit";"Zergling";"Larva";261;1
"Unit";"Zergling";"Larva";261;1
"Unit";"Zergling";"Larva";261;1
"Unit";"Zergling";"Larva";261;1
"Unit";"Zergling";"Larva";261;1
"Unit";"Zergling";"Larva";261;1
"Unit";"Zergling";"Larva";261;1
"Unit";"Zergling";"Larva";261;1
"Unit";"Zergling";"Larva";261;1
"Unit";"Zergling";"Larva";261;1
"Unit";"Zergling";"Larva";261;1
"Unit";"Zergling";"Larva";261;1
"Unit";"Zergling";"Larva";261;1
"Unit";"Zergling";"Larva";261;1
"Unit";"Zergling";"Larva";261;1
"Unit";"Zergling";"Larva";261;1
"Unit";"Zergling";"Larva";261;1
"Unit";"Zergling";"Larva";261;1
"Unit";"Zergling";"Larva";261;1
"Unit";"Zergling";"Larva";261;1
"Unit";"Zergling";"Larva";261;1
"Unit";"Overlord";"Larva";261;0
"Unit";"Overlord";"Larva";261;0
"Building";"Hatchery";NA;219;0
"Building";"CreepTumor";NA;263;0
"Building";"CreepTumor";NA;263;0
"Upgrade";"ZergMeleeWeaponsLevel2";"EvolutionChamber";210;0
"Building";"CreepTumor";NA;287;0
"Unit";"Ultralisk";"Larva";261;6
"Building";"CreepTumorQueen";NA;287;0
"Unit";"Queen";"Hatchery";287;2
"Unit";"Zergling";"Larva";293;1
"Unit";"Zergling";"Larva";293;1
"Unit";"Zergling";"Larva";293;1
"Unit";"Zergling";"Larva";293;1
"Unit";"Zergling";"Larva";293;1
"Unit";"Zergling";"Larva";293;1
"Unit";"Zergling";"Larva";293;1
"Unit";"Zergling";"Larva";293;1
"Upgrade";"ChitinousPlating";"UltraliskCavern";287;0
"Unit";"Ultralisk";"Larva";293;6
"Unit";"Ultralisk";"Larva";293;6
"Unit";"Ultralisk";"Larva";293;6
"Unit";"Ultralisk";"Larva";293;6
"Unit";"Queen";"Hatchery";293;2
"Unit";"Queen";"Hatchery";293;2
"Unit";"Ultralisk";"Larva";303;6
"Unit";"Ultralisk";"Larva";303;6
"Unit";"Zergling";"Larva";335;1
"Unit";"Zergling";"Larva";335;1
"Unit";"Zergling";"Larva";335;1
"Unit";"Zergling";"Larva";335;1
"Unit";"Zergling";"Larva";335;1
"Unit";"Zergling";"Larva";335;1
"Unit";"Zergling";"Larva";335;1
"Unit";"Zergling";"Larva";335;1
"Unit";"Zergling";"Larva";335;1
"Unit";"Zergling";"Larva";335;1
"Unit";"Zergling";"Larva";335;1
"Unit";"Zergling";"Larva";335;1
"Upgrade";"ZergGroundArmorsLevel3";"EvolutionChamber";261;0
"Unit";"Hydralisk";"Larva";335;2
"Unit";"Hydralisk";"Larva";335;2
"Unit";"Hydralisk";"Larva";335;2
"Unit";"Hydralisk";"Larva";335;2
"Unit";"Hydralisk";"Larva";335;2
"Unit";"Hydralisk";"Larva";335;2
"Unit";"Zergling";"Larva";361;1
"Unit";"Zergling";"Larva";361;1
"Unit";"Zergling";"Larva";361;1
"Unit";"Zergling";"Larva";361;1
"Unit";"Zergling";"Larva";361;1
"Unit";"Zergling";"Larva";361;1
"Unit";"Zergling";"Larva";361;1
"Unit";"Zergling";"Larva";361;1
"Unit";"Zergling";"Larva";361;1
"Unit";"Zergling";"Larva";361;1
"Unit";"Zergling";"Larva";361;1
"Unit";"Zergling";"Larva";361;1
"Unit";"Zergling";"Larva";361;1
"Unit";"Zergling";"Larva";361;1
"Unit";"Zergling";"Larva";361;1
"Unit";"Zergling";"Larva";361;1
"Unit";"Zergling";"Larva";361;1
"Unit";"Zergling";"Larva";361;1
"Unit";"Zergling";"Larva";361;1
"Unit";"Zergling";"Larva";361;1
"Unit";"Zergling";"Larva";361;1
"Unit";"Zergling";"Larva";361;1
"Unit";"Zergling";"Larva";361;1
"Unit";"Zergling";"Larva";361;1
"Unit";"Zergling";"Larva";361;1
"Unit";"Zergling";"Larva";361;1
"Unit";"Hydralisk";"Larva";361;2
"Building";"CreepTumor";NA;401;0
"Building";"CreepTumor";NA;401;0
"Unit";"Queen";"Hatchery";401;2
"Unit";"Baneling";"Zergling";401;0
"Unit";"Baneling";"Zergling";401;0
"Unit";"Baneling";"Zergling";401;0
"Unit";"Baneling";"Zergling";401;0
"Unit";"Baneling";"Zergling";401;0
"Unit";"Baneling";"Zergling";401;0
"Unit";"Baneling";"Zergling";401;0
"Unit";"Baneling";"Zergling";401;0
"Unit";"Baneling";"Zergling";401;0
"Unit";"Infestor";"Larva";401;2
"Unit";"Infestor";"Larva";401;2
"Unit";"Infestor";"Larva";401;2
"Building";"CreepTumor";NA;401;0
"Unit";"Hydralisk";"Larva";401;2
"Unit";"Hydralisk";"Larva";401;2
"Unit";"Hydralisk";"Larva";401;2
"Unit";"Hydralisk";"Larva";401;2
"Unit";"Hydralisk";"Larva";401;2
"Unit";"Hydralisk";"Larva";401;2
"Unit";"Hydralisk";"Larva";401;2
"Unit";"Hydralisk";"Larva";401;2
"Unit";"Hydralisk";"Larva";401;2
"Building";"CreepTumorQueen";NA;403;0
"Building";"CreepTumorQueen";NA;409;0
"Building";"CreepTumor";NA;427;0
"Building";"CreepTumor";NA;427;0
"Building";"CreepTumorQueen";NA;427;0
"Unit";"Ultralisk";"Larva";401;6
"Unit";"Ultralisk";"Larva";409;6
"Upgrade";"EvolveMuscularAugments";"HydraliskDen";403;0
"Unit";"Overlord";"Larva";433;0
"Unit";"Overlord";"Larva";433;0
"Building";"CreepTumor";NA;439;0
"Unit";"Queen";"Hatchery";427;2
"Building";"CreepTumor";NA;439;0
"Unit";"Queen";"Hatchery";427;2
"Building";"CreepTumor";NA;439;0
"Unit";"Queen";"Hatchery";433;2
"Unit";"Infestor";"Larva";433;2
"Unit";"Infestor";"Larva";433;2
"Unit";"Infestor";"Larva";433;2
"Unit";"Ultralisk";"Larva";433;6
"Unit";"Zergling";"Larva";439;1
"Unit";"Zergling";"Larva";439;1
"Unit";"Overlord";"Larva";439;0
"Unit";"Zergling";"Larva";439;1
"Unit";"Zergling";"Larva";439;1
"Unit";"Zergling";"Larva";439;1
"Unit";"Zergling";"Larva";439;1
"Unit";"Zergling";"Larva";439;1
"Unit";"Zergling";"Larva";439;1
"Unit";"Zergling";"Larva";439;1
"Unit";"Zergling";"Larva";439;1
"Unit";"Zergling";"Larva";439;1
"Unit";"Zergling";"Larva";439;1
"Unit";"Zergling";"Larva";439;1
"Unit";"Zergling";"Larva";439;1
"Unit";"Zergling";"Larva";439;1
"Unit";"Zergling";"Larva";439;1
"Unit";"Zergling";"Larva";439;1
"Unit";"Zergling";"Larva";439;1
"Unit";"Zergling";"Larva";439;1
"Unit";"Zergling";"Larva";439;1
"Unit";"Zergling";"Larva";439;1
"Unit";"Zergling";"Larva";439;1
"Unit";"Zergling";"Larva";439;1
"Unit";"Zergling";"Larva";439;1
"Unit";"Zergling";"Larva";439;1
"Unit";"Zergling";"Larva";439;1
"Upgrade";"ZergMissileWeaponsLevel2";"EvolutionChamber";427;0
"Building";"Spire";NA;439;0
"Upgrade";"ZergMeleeWeaponsLevel3";"EvolutionChamber";427;0
"Unit";"Zergling";"Larva";483;1
"Unit";"Zergling";"Larva";483;1
"Unit";"Zergling";"Larva";483;1
"Unit";"Zergling";"Larva";483;1
"Unit";"Zergling";"Larva";483;1
"Unit";"Zergling";"Larva";483;1
"Unit";"Zergling";"Larva";483;1
"Unit";"Zergling";"Larva";483;1
"Unit";"Zergling";"Larva";483;1
"Unit";"Zergling";"Larva";483;1
"Unit";"Zergling";"Larva";483;1
"Unit";"Zergling";"Larva";483;1
"Unit";"Zergling";"Larva";483;1
"Unit";"Zergling";"Larva";483;1
"Unit";"Zergling";"Larva";483;1
"Unit";"Zergling";"Larva";483;1
"Unit";"Zergling";"Larva";483;1
"Unit";"Zergling";"Larva";483;1
"Unit";"Zergling";"Larva";483;1
"Unit";"Zergling";"Larva";483;1
"Unit";"Zergling";"Larva";483;1
"Unit";"Zergling";"Larva";483;1
"Unit";"Zergling";"Larva";483;1
"Unit";"Zergling";"Larva";483;1
"Unit";"Zergling";"Larva";483;1
"Unit";"Zergling";"Larva";483;1
"Unit";"Zergling";"Larva";483;1
"Unit";"Zergling";"Larva";483;1
"Unit";"Zergling";"Larva";483;1
"Unit";"Zergling";"Larva";483;1
"Unit";"Zergling";"Larva";483;1
"Unit";"Zergling";"Larva";483;1
"Unit";"Zergling";"Larva";483;1
"Unit";"Zergling";"Larva";483;1
"Unit";"Zergling";"Larva";483;1
"Unit";"Zergling";"Larva";483;1
"Unit";"Zergling";"Larva";483;1
"Unit";"Zergling";"Larva";483;1
"Unit";"Hydralisk";"Larva";483;2
"Unit";"Hydralisk";"Larva";483;2
"Unit";"Hydralisk";"Larva";483;2
"Unit";"Ultralisk";"Larva";483;6
"Unit";"Ultralisk";"Larva";483;6
"Unit";"Corruptor";"Larva";483;2
"Unit";"Corruptor";"Larva";483;2
"Unit";"Corruptor";"Larva";527;2
"Unit";"Corruptor";"Larva";527;2
"Unit";"Corruptor";"Larva";527;2
"Unit";"Corruptor";"Larva";527;2
"Unit";"Corruptor";"Larva";527;2
"Unit";"Ultralisk";"Larva";543;6
"Unit";"Ultralisk";"Larva";543;6
"Unit";"Zergling";"Larva";553;1
"Unit";"Zergling";"Larva";553;1
"Unit";"Zergling";"Larva";553;1
"Unit";"Zergling";"Larva";553;1
"Unit";"Zergling";"Larva";553;1
"Unit";"Zergling";"Larva";553;1
"Unit";"Corruptor";"Larva";553;2
"Unit";"Corruptor";"Larva";553;2
"Unit";"Corruptor";"Larva";553;2
"Unit";"Hydralisk";"Larva";553;2
"Unit";"Hydralisk";"Larva";553;2
"Unit";"Hydralisk";"Larva";553;2
"Unit";"Ultralisk";"Larva";553;6
"Building";"CreepTumor";NA;589;0
"Unit";"Zergling";"Larva";583;1
"Unit";"Zergling";"Larva";583;1
"Unit";"Zergling";"Larva";583;1
"Unit";"Zergling";"Larva";583;1
"Unit";"Zergling";"Larva";583;1
"Unit";"Zergling";"Larva";583;1
"Unit";"Zergling";"Larva";583;1
"Unit";"Zergling";"Larva";583;1
"Unit";"Zergling";"Larva";583;1
"Unit";"Zergling";"Larva";583;1
"Unit";"Zergling";"Larva";583;1
"Unit";"Zergling";"Larva";583;1
"Unit";"Zergling";"Larva";583;1
"Unit";"Zergling";"Larva";583;1
"Building";"CreepTumor";NA;589;0
