"type";"unit_name";"on_building";"total_supply";"supply"
"Unit";"Overlord";"Larva";12;0
"Building";"Extractor";NA;18;0
"Unit";"Overlord";"Larva";21;0
"Building";"SpawningPool";NA;19;0
"Building";"Hatchery";NA;17;0
"Unit";"Zergling";"Larva";22;1
"Unit";"Zergling";"Larva";22;1
"Unit";"Zergling";"Larva";23;1
"Unit";"Zergling";"Larva";23;1
"Unit";"Queen";"Hatchery";22;2
"Unit";"Queen";"Hatchery";23;2
"Building";"CreepTumorQueen";NA;35;0
"Unit";"Overlord";"Larva";35;0
"Unit";"Queen";"Hatchery";32;2
"Building";"CreepTumorQueen";NA;41;0
"Building";"CreepTumor";NA;41;0
"Unit";"Overlord";"Larva";43;0
"Unit";"Overlord";"Larva";46;0
"Unit";"Overlord";"Larva";46;0
"Unit";"Queen";"Hatchery";41;2
"Unit";"Overlord";"Larva";48;0
"Unit";"Overlord";"Larva";48;0
"Building";"CreepTumor";NA;52;0
"Building";"CreepTumor";NA;52;0
"Building";"Extractor";NA;48;0
"Building";"Hatchery";NA;39;0
"Building";"EvolutionChamber";NA;51;0
"Building";"EvolutionChamber";NA;52;0
"Unit";"Zergling";"Larva";56;1
"Unit";"Zergling";"Larva";56;1
"Building";"CreepTumorQueen";NA;60;0
"Unit";"Zergling";"Larva";58;1
"Unit";"Zergling";"Larva";58;1
"Unit";"Zergling";"Larva";58;1
"Unit";"Zergling";"Larva";58;1
"Unit";"Zergling";"Larva";58;1
"Unit";"Zergling";"Larva";58;1
"Unit";"Queen";"Hatchery";52;2
"Building";"CreepTumorQueen";NA;60;0
"Building";"CreepTumor";NA;70;0
"Unit";"Zergling";"Larva";64;1
"Unit";"Zergling";"Larva";64;1
"Unit";"Zergling";"Larva";68;1
"Unit";"Zergling";"Larva";68;1
"Unit";"Zergling";"Larva";68;1
"Unit";"Zergling";"Larva";68;1
"Building";"CreepTumor";NA;70;0
"Unit";"Queen";"Hatchery";58;2
"Building";"CreepTumor";NA;80;0
"Unit";"Zergling";"Larva";82;1
"Unit";"Zergling";"Larva";82;1
"Unit";"Zergling";"Larva";82;1
"Unit";"Zergling";"Larva";82;1
"Building";"CreepTumor";NA;84;0
"Unit";"Zergling";"Larva";84;1
"Unit";"Zergling";"Larva";84;1
"Unit";"Zergling";"Larva";84;1
"Unit";"Zergling";"Larva";84;1
"Building";"CreepTumor";NA;87;0
"Unit";"Zergling";"Larva";86;1
"Unit";"Zergling";"Larva";86;1
"Unit";"Zergling";"Larva";87;1
"Unit";"Zergling";"Larva";87;1
"Unit";"Zergling";"Larva";87;1
"Unit";"Zergling";"Larva";87;1
"Unit";"Zergling";"Larva";93;1
"Unit";"Zergling";"Larva";93;1
"Unit";"Zergling";"Larva";95;1
"Unit";"Zergling";"Larva";95;1
"Unit";"Zergling";"Larva";95;1
"Unit";"Zergling";"Larva";95;1
"Unit";"Zergling";"Larva";95;1
"Unit";"Zergling";"Larva";95;1
"Unit";"Zergling";"Larva";95;1
"Unit";"Zergling";"Larva";95;1
"Unit";"Zergling";"Larva";95;1
"Unit";"Zergling";"Larva";95;1
"Unit";"Zergling";"Larva";101;1
"Unit";"Zergling";"Larva";101;1
"Unit";"Overlord";"Larva";109;0
"Unit";"Overlord";"Larva";109;0
"Unit";"Overlord";"Larva";109;0
"Unit";"Overlord";"Larva";109;0
"Unit";"Zergling";"Larva";113;1
"Unit";"Zergling";"Larva";113;1
"Unit";"Zergling";"Larva";113;1
"Unit";"Zergling";"Larva";113;1
"Unit";"Zergling";"Larva";113;1
"Unit";"Zergling";"Larva";113;1
"Unit";"Zergling";"Larva";115;1
"Unit";"Zergling";"Larva";115;1
"Building";"CreepTumor";NA;115;0
"Unit";"Overlord";"Larva";115;0
"Unit";"Overlord";"Larva";115;0
"Unit";"Overlord";"Larva";115;0
"Building";"CreepTumor";NA;115;0
"Upgrade";"ZergMeleeWeaponsLevel1";"EvolutionChamber";84;0
"Building";"CreepTumor";NA;124;0
"Building";"CreepTumor";NA;124;0
"Unit";"Zergling";"Larva";124;1
"Unit";"Zergling";"Larva";124;1
"Unit";"Zergling";"Larva";124;1
"Unit";"Zergling";"Larva";124;1
"Unit";"Zergling";"Larva";124;1
"Unit";"Zergling";"Larva";124;1
"Upgrade";"ZergGroundArmorsLevel1";"EvolutionChamber";87;0
"Unit";"Zergling";"Larva";124;1
"Unit";"Zergling";"Larva";124;1
"Unit";"Zergling";"Larva";124;1
"Unit";"Zergling";"Larva";124;1
"Unit";"Zergling";"Larva";124;1
"Unit";"Zergling";"Larva";124;1
"Building";"Extractor";NA;124;0
"Building";"Extractor";NA;124;0
"Building";"BanelingNest";NA;115;0
"Unit";"Overlord";"Larva";130;0
"Unit";"Overlord";"Larva";130;0
"Unit";"Overlord";"Larva";130;0
"Building";"HydraliskDen";NA;124;0
"Building";"CreepTumor";NA;143;0
"Building";"CreepTumor";NA;145;0
"Building";"CreepTumor";NA;148;0
"Unit";"Overlord";"Larva";145;0
"Unit";"Baneling";"Zergling";148;0
"Unit";"Baneling";"Zergling";148;0
"Unit";"Baneling";"Zergling";148;0
"Unit";"Zergling";"Larva";148;1
"Unit";"Zergling";"Larva";148;1
"Unit";"Zergling";"Larva";148;1
"Unit";"Zergling";"Larva";148;1
"Unit";"Zergling";"Larva";148;1
"Unit";"Zergling";"Larva";148;1
"Unit";"Zergling";"Larva";148;1
"Unit";"Zergling";"Larva";148;1
"Unit";"Zergling";"Larva";148;1
"Unit";"Zergling";"Larva";148;1
"Unit";"Zergling";"Larva";148;1
"Unit";"Zergling";"Larva";148;1
"Unit";"Zergling";"Larva";148;1
"Unit";"Zergling";"Larva";148;1
"Building";"Hatchery";NA;124;0
"Building";"CreepTumorQueen";NA;152;0
"Building";"CreepTumorQueen";NA;164;0
"Building";"CreepTumorQueen";NA;164;0
"Building";"CreepTumor";NA;164;0
"Unit";"Zergling";"Larva";164;1
"Unit";"Zergling";"Larva";164;1
"Unit";"Zergling";"Larva";164;1
"Unit";"Zergling";"Larva";164;1
"Unit";"Zergling";"Larva";164;1
"Unit";"Zergling";"Larva";164;1
"Unit";"Zergling";"Larva";164;1
"Unit";"Zergling";"Larva";164;1
"Unit";"Zergling";"Larva";164;1
"Unit";"Zergling";"Larva";164;1
"Unit";"Zergling";"Larva";164;1
"Unit";"Zergling";"Larva";164;1
"Building";"CreepTumorQueen";NA;186;0
"Building";"CreepTumorQueen";NA;186;0
"Unit";"Overlord";"Larva";180;0
"Unit";"Overlord";"Larva";180;0
"Building";"CreepTumor";NA;188;0
"Building";"CreepTumor";NA;188;0
"Building";"Hatchery";NA;143;0
"Building";"CreepTumor";NA;188;0
"Building";"CreepTumor";NA;195;0
"Building";"CreepTumor";NA;195;0
"Building";"Extractor";NA;188;0
"Upgrade";"EvolveGroovedSpines";"HydraliskDen";166;0
"Building";"Extractor";NA;188;0
"Unit";"Zergling";"Larva";195;1
"Unit";"Zergling";"Larva";195;1
"Unit";"Zergling";"Larva";195;1
"Unit";"Zergling";"Larva";195;1
"Unit";"Zergling";"Larva";195;1
"Unit";"Zergling";"Larva";195;1
"Unit";"Zergling";"Larva";195;1
"Unit";"Zergling";"Larva";195;1
"Unit";"Zergling";"Larva";195;1
"Unit";"Zergling";"Larva";195;1
"Unit";"Zergling";"Larva";195;1
"Unit";"Zergling";"Larva";195;1
"Unit";"Zergling";"Larva";195;1
"Unit";"Zergling";"Larva";195;1
"Unit";"Zergling";"Larva";195;1
"Unit";"Zergling";"Larva";195;1
"Unit";"Baneling";"Zergling";195;0
"Unit";"Baneling";"Zergling";195;0
"Unit";"Baneling";"Zergling";195;0
"Unit";"Baneling";"Zergling";195;0
"Unit";"Baneling";"Zergling";195;0
"Unit";"Baneling";"Zergling";195;0
"Unit";"Baneling";"Zergling";195;0
"Unit";"Baneling";"Zergling";195;0
"Building";"CreepTumor";NA;195;0
"Unit";"Zergling";"Larva";195;1
"Unit";"Zergling";"Larva";195;1
"Unit";"Zergling";"Larva";195;1
"Unit";"Zergling";"Larva";195;1
"Unit";"Zergling";"Larva";195;1
"Unit";"Zergling";"Larva";195;1
"Unit";"Zergling";"Larva";195;1
"Unit";"Zergling";"Larva";195;1
"Unit";"Zergling";"Larva";195;1
"Unit";"Zergling";"Larva";195;1
"Unit";"Zergling";"Larva";195;1
"Unit";"Zergling";"Larva";195;1
"Building";"InfestationPit";NA;188;0
"Building";"CreepTumor";NA;223;0
"Building";"CreepTumor";NA;223;0
"Unit";"Hydralisk";"Larva";211;2
"Unit";"Hydralisk";"Larva";211;2
"Unit";"Hydralisk";"Larva";211;2
"Unit";"Hydralisk";"Larva";211;2
"Unit";"Hydralisk";"Larva";211;2
"Unit";"Hydralisk";"Larva";211;2
"Unit";"Hydralisk";"Larva";211;2
"Upgrade";"ZergGroundArmorsLevel2";"EvolutionChamber";152;0
"Upgrade";"ZergMeleeWeaponsLevel2";"EvolutionChamber";152;0
"Building";"CreepTumorQueen";NA;240;0
"Building";"CreepTumorQueen";NA;240;0
"Building";"Extractor";NA;223;0
"Building";"Extractor";NA;223;0
"Building";"CreepTumorQueen";NA;240;0
"Building";"SporeCrawler";NA;223;0
"Building";"SporeCrawler";NA;223;0
"Unit";"Hydralisk";"Larva";223;2
"Unit";"Hydralisk";"Larva";223;2
"Building";"CreepTumorQueen";NA;240;0
"Building";"SpineCrawler";NA;223;0
"Building";"SpineCrawler";NA;223;0
"Building";"SpineCrawler";NA;223;0
"Building";"CreepTumor";NA;244;0
"Building";"CreepTumor";NA;244;0
"Building";"CreepTumor";NA;244;0
"Building";"CreepTumor";NA;244;0
"Building";"CreepTumor";NA;244;0
"Unit";"Hydralisk";"Larva";244;2
"Unit";"Hydralisk";"Larva";244;2
"Unit";"Hydralisk";"Larva";244;2
"Unit";"Hydralisk";"Larva";244;2
"Unit";"Hydralisk";"Larva";244;2
"Unit";"Hydralisk";"Larva";244;2
"Unit";"Hydralisk";"Larva";244;2
"Unit";"Hydralisk";"Larva";244;2
"Upgrade";"EvolveMuscularAugments";"HydraliskDen";223;0
"Building";"CreepTumor";NA;244;0
"Building";"CreepTumor";NA;244;0
"Building";"CreepTumor";NA;244;0
"Building";"CreepTumor";NA;244;0
"Unit";"Baneling";"Zergling";244;0
"Unit";"Baneling";"Zergling";244;0
"Unit";"Baneling";"Zergling";244;0
"Unit";"Baneling";"Zergling";244;0
"Unit";"Baneling";"Zergling";244;0
"Unit";"Hydralisk";"Larva";244;2
"Unit";"Hydralisk";"Larva";244;2
"Unit";"Hydralisk";"Larva";244;2
"Unit";"Hydralisk";"Larva";244;2
"Unit";"Hydralisk";"Larva";244;2
"Unit";"Overlord";"Larva";244;0
"Unit";"Overlord";"Larva";244;0
"Building";"CreepTumor";NA;270;0
"Building";"CreepTumor";NA;270;0
"Building";"CreepTumor";NA;270;0
"Unit";"Zergling";"Larva";260;1
"Unit";"Zergling";"Larva";260;1
"Unit";"Zergling";"Larva";260;1
"Unit";"Zergling";"Larva";260;1
"Unit";"Zergling";"Larva";260;1
"Unit";"Zergling";"Larva";260;1
"Unit";"Zergling";"Larva";260;1
"Unit";"Zergling";"Larva";260;1
"Unit";"Zergling";"Larva";260;1
"Unit";"Zergling";"Larva";260;1
"Unit";"Zergling";"Larva";260;1
"Unit";"Zergling";"Larva";260;1
"Building";"CreepTumor";NA;270;0
"Building";"CreepTumor";NA;270;0
"Unit";"Overlord";"Larva";260;0
"Unit";"Overlord";"Larva";260;0
"Unit";"Overlord";"Larva";260;0
"Unit";"Overlord";"Larva";260;0
"Unit";"Overlord";"Larva";260;0
"Unit";"Overlord";"Larva";260;0
"Unit";"Overlord";"Larva";260;0
"Unit";"Baneling";"Zergling";282;0
"Unit";"Zergling";"Larva";270;1
"Unit";"Zergling";"Larva";270;1
"Unit";"Baneling";"Zergling";282;0
"Unit";"Baneling";"Zergling";282;0
"Unit";"Baneling";"Zergling";282;0
"Unit";"Baneling";"Zergling";282;0
"Unit";"Baneling";"Zergling";282;0
"Unit";"Baneling";"Zergling";282;0
"Unit";"Baneling";"Zergling";282;0
"Unit";"Zergling";"Larva";270;1
"Unit";"Zergling";"Larva";270;1
"Unit";"Baneling";"Zergling";282;0
"Unit";"Zergling";"Larva";270;1
"Unit";"Zergling";"Larva";270;1
"Unit";"Zergling";"Larva";270;1
"Unit";"Zergling";"Larva";270;1
"Unit";"Zergling";"Larva";270;1
"Unit";"Zergling";"Larva";270;1
"Unit";"Zergling";"Larva";270;1
"Unit";"Zergling";"Larva";270;1
"Unit";"Zergling";"Larva";270;1
"Unit";"Zergling";"Larva";270;1
"Unit";"Zergling";"Larva";282;1
"Unit";"Zergling";"Larva";282;1
"Unit";"Zergling";"Larva";282;1
"Unit";"Zergling";"Larva";282;1
"Unit";"Zergling";"Larva";282;1
"Unit";"Zergling";"Larva";282;1
"Unit";"Zergling";"Larva";282;1
"Unit";"Zergling";"Larva";282;1
"Building";"CreepTumor";NA;282;0
"Building";"CreepTumor";NA;288;0
"Building";"Hatchery";NA;244;0
"Building";"CreepTumor";NA;296;0
"Building";"CreepTumor";NA;296;0
"Building";"CreepTumor";NA;296;0
"Building";"CreepTumor";NA;304;0
"Building";"CreepTumor";NA;304;0
"Building";"CreepTumor";NA;304;0
"Building";"UltraliskCavern";NA;304;0
"Building";"CreepTumor";NA;304;0
"Upgrade";"ZergMissileWeaponsLevel1";"EvolutionChamber";282;0
"Building";"CreepTumor";NA;304;0
"Building";"CreepTumor";NA;304;0
"Building";"CreepTumorQueen";NA;304;0
"Building";"CreepTumorQueen";NA;304;0
"Building";"CreepTumorQueen";NA;304;0
"Building";"CreepTumorQueen";NA;304;0
"Building";"CreepTumor";NA;304;0
"Unit";"Queen";"Hatchery";304;2
"Building";"CreepTumorQueen";NA;304;0
"Unit";"Queen";"Hatchery";304;2
"Unit";"Queen";"Hatchery";304;2
"Building";"CreepTumor";NA;304;0
"Building";"CreepTumor";NA;304;0
"Building";"CreepTumor";NA;304;0
"Building";"CreepTumorQueen";NA;304;0
"Building";"CreepTumor";NA;304;0
"Building";"CreepTumorQueen";NA;304;0
"Building";"CreepTumorQueen";NA;304;0
"Building";"CreepTumorQueen";NA;306;0
"Unit";"Ultralisk";"Larva";304;6
"Unit";"Ultralisk";"Larva";304;6
"Unit";"Ultralisk";"Larva";304;6
"Unit";"Ultralisk";"Larva";304;6
"Building";"SpineCrawler";NA;304;0
"Building";"SpineCrawler";NA;304;0
"Building";"SpineCrawler";NA;304;0
"Building";"CreepTumor";NA;324;0
"Building";"CreepTumor";NA;348;0
"Building";"CreepTumor";NA;348;0
"Building";"CreepTumor";NA;348;0
"Building";"CreepTumor";NA;348;0
"Building";"CreepTumor";NA;348;0
"Building";"CreepTumor";NA;348;0
"Building";"CreepTumorQueen";NA;348;0
"Building";"CreepTumorQueen";NA;348;0
"Building";"CreepTumorQueen";NA;348;0
"Building";"Spire";NA;304;0
"Upgrade";"ChitinousPlating";"UltraliskCavern";304;0
"Unit";"Infestor";"Larva";348;2
"Unit";"Infestor";"Larva";348;2
"Unit";"Infestor";"Larva";348;2
"Upgrade";"ZergGroundArmorsLevel3";"EvolutionChamber";304;0
"Building";"CreepTumorQueen";NA;348;0
"Building";"CreepTumorQueen";NA;348;0
"Building";"CreepTumorQueen";NA;354;0
"Building";"Extractor";NA;348;0
