"type";"unit_name";"on_building";"total_supply";"supply"
"Unit";"Overlord";"Larva";13;0
"Building";"Extractor";NA;18;0
"Building";"SpawningPool";NA;19;0
"Unit";"Overlord";"Larva";22;0
"Building";"Hatchery";NA;18;0
"Unit";"Zergling";"Larva";23;1
"Unit";"Zergling";"Larva";23;1
"Unit";"Zergling";"Larva";23;1
"Unit";"Zergling";"Larva";23;1
"Unit";"Queen";"Hatchery";23;2
"Unit";"Queen";"Hatchery";23;2
"Unit";"Overlord";"Larva";33;0
"Building";"RoachWarren";NA;28;0
"Unit";"Overlord";"Larva";36;0
"Unit";"Roach";"Larva";37;2
"Unit";"Roach";"Larva";37;2
"Unit";"Roach";"Larva";37;2
"Building";"CreepTumorQueen";NA;37;0
"Unit";"Roach";"Larva";37;2
"Unit";"Roach";"Larva";37;2
"Unit";"Roach";"Larva";37;2
"Unit";"Roach";"Larva";37;2
"Unit";"Roach";"Larva";37;2
"Unit";"Roach";"Larva";37;2
"Unit";"Overlord";"Larva";37;0
"Unit";"Overlord";"Larva";60;0
"Unit";"Zergling";"Larva";63;1
"Unit";"Zergling";"Larva";63;1
"Unit";"Zergling";"Larva";63;1
"Unit";"Zergling";"Larva";63;1
"Unit";"Zergling";"Larva";63;1
"Unit";"Zergling";"Larva";63;1
"Unit";"Zergling";"Larva";63;1
"Unit";"Zergling";"Larva";63;1
"Unit";"Zergling";"Larva";63;1
"Unit";"Zergling";"Larva";63;1
"Unit";"Zergling";"Larva";63;1
"Unit";"Zergling";"Larva";63;1
"Unit";"Zergling";"Larva";63;1
"Unit";"Zergling";"Larva";63;1
"Unit";"Zergling";"Larva";63;1
"Unit";"Zergling";"Larva";63;1
"Building";"CreepTumor";NA;63;0
"Unit";"Zergling";"Larva";63;1
"Unit";"Zergling";"Larva";63;1
"Unit";"Zergling";"Larva";63;1
"Unit";"Zergling";"Larva";63;1
"Building";"Hatchery";NA;60;0
"Unit";"Zergling";"Larva";63;1
"Unit";"Zergling";"Larva";63;1
"Unit";"Queen";"Hatchery";63;2
"Unit";"Queen";"Hatchery";63;2
"Unit";"Overlord";"Larva";81;0
"Building";"BanelingNest";NA;63;0
"Building";"CreepTumor";NA;85;0
"Unit";"Overlord";"Larva";85;0
"Building";"EvolutionChamber";NA;83;0
"Building";"EvolutionChamber";NA;83;0
"Unit";"Baneling";"Zergling";97;0
"Unit";"Baneling";"Zergling";97;0
"Unit";"Baneling";"Zergling";97;0
"Unit";"Baneling";"Zergling";97;0
"Building";"CreepTumorQueen";NA;97;0
"Unit";"Zergling";"Larva";97;1
"Unit";"Zergling";"Larva";97;1
"Unit";"Zergling";"Larva";97;1
"Unit";"Zergling";"Larva";97;1
"Unit";"Zergling";"Larva";97;1
"Unit";"Zergling";"Larva";97;1
"Unit";"Zergling";"Larva";97;1
"Unit";"Zergling";"Larva";97;1
"Unit";"Queen";"Hatchery";90;2
"Unit";"Overlord";"Larva";97;0
"Building";"CreepTumor";NA;108;0
"Unit";"Zergling";"Larva";108;1
"Unit";"Zergling";"Larva";108;1
"Unit";"Zergling";"Larva";108;1
"Unit";"Zergling";"Larva";108;1
"Unit";"Zergling";"Larva";108;1
"Unit";"Zergling";"Larva";108;1
"Unit";"Zergling";"Larva";108;1
"Unit";"Zergling";"Larva";108;1
"Unit";"Zergling";"Larva";108;1
"Unit";"Zergling";"Larva";108;1
"Unit";"Zergling";"Larva";108;1
"Unit";"Zergling";"Larva";108;1
"Building";"Extractor";NA;108;0
"Building";"Extractor";NA;110;0
"Building";"CreepTumor";NA;125;0
"Unit";"Baneling";"Zergling";124;0
"Unit";"Baneling";"Zergling";124;0
"Unit";"Overlord";"Larva";118;0
"Building";"CreepTumor";NA;125;0
"Building";"Extractor";NA;125;0
"Unit";"Overlord";"Larva";127;0
"Unit";"Overlord";"Larva";127;0
"Unit";"Zergling";"Larva";135;1
"Unit";"Zergling";"Larva";135;1
"Unit";"Zergling";"Larva";135;1
"Unit";"Zergling";"Larva";135;1
"Unit";"Zergling";"Larva";135;1
"Unit";"Zergling";"Larva";135;1
"Unit";"Zergling";"Larva";135;1
"Unit";"Zergling";"Larva";135;1
"Unit";"Zergling";"Larva";135;1
"Unit";"Zergling";"Larva";135;1
"Unit";"Zergling";"Larva";135;1
"Unit";"Zergling";"Larva";135;1
"Unit";"Zergling";"Larva";135;1
"Unit";"Zergling";"Larva";135;1
"Unit";"Zergling";"Larva";135;1
"Unit";"Zergling";"Larva";135;1
"Building";"CreepTumor";NA;136;0
"Unit";"Zergling";"Larva";136;1
"Unit";"Zergling";"Larva";136;1
"Unit";"Zergling";"Larva";136;1
"Unit";"Zergling";"Larva";136;1
"Unit";"Zergling";"Larva";136;1
"Unit";"Zergling";"Larva";136;1
"Unit";"Zergling";"Larva";136;1
"Unit";"Zergling";"Larva";136;1
"Unit";"Zergling";"Larva";136;1
"Unit";"Zergling";"Larva";136;1
"Upgrade";"ZergGroundArmorsLevel1";"EvolutionChamber";110;0
"Unit";"Zergling";"Larva";162;1
"Unit";"Zergling";"Larva";162;1
"Unit";"Zergling";"Larva";162;1
"Unit";"Zergling";"Larva";162;1
"Unit";"Zergling";"Larva";162;1
"Unit";"Zergling";"Larva";162;1
"Unit";"Zergling";"Larva";162;1
"Unit";"Zergling";"Larva";162;1
"Unit";"Zergling";"Larva";162;1
"Unit";"Zergling";"Larva";162;1
"Unit";"Zergling";"Larva";162;1
"Unit";"Zergling";"Larva";162;1
"Unit";"Zergling";"Larva";162;1
"Unit";"Zergling";"Larva";162;1
"Unit";"Zergling";"Larva";162;1
"Unit";"Zergling";"Larva";162;1
"Unit";"Zergling";"Larva";162;1
"Unit";"Zergling";"Larva";162;1
"Unit";"Zergling";"Larva";162;1
"Unit";"Zergling";"Larva";162;1
"Unit";"Zergling";"Larva";162;1
"Unit";"Zergling";"Larva";162;1
"Unit";"Zergling";"Larva";162;1
"Unit";"Zergling";"Larva";162;1
"Unit";"Zergling";"Larva";162;1
"Unit";"Zergling";"Larva";162;1
"Unit";"Zergling";"Larva";162;1
"Unit";"Zergling";"Larva";162;1
"Unit";"Zergling";"Larva";162;1
"Unit";"Zergling";"Larva";162;1
"Unit";"Zergling";"Larva";162;1
"Unit";"Zergling";"Larva";162;1
"Unit";"Zergling";"Larva";162;1
"Unit";"Zergling";"Larva";162;1
"Unit";"Zergling";"Larva";162;1
"Unit";"Zergling";"Larva";162;1
"Unit";"Baneling";"Zergling";162;0
"Unit";"Baneling";"Zergling";162;0
"Unit";"Baneling";"Zergling";162;0
"Unit";"Baneling";"Zergling";162;0
"Unit";"Baneling";"Zergling";162;0
"Building";"Extractor";NA;162;0
"Building";"Extractor";NA;162;0
"Building";"CreepTumorQueen";NA;198;0
"Unit";"Queen";"Hatchery";162;2
"Unit";"Zergling";"Larva";198;1
"Unit";"Zergling";"Larva";198;1
"Upgrade";"ZergMeleeWeaponsLevel1";"EvolutionChamber";152;0
"Unit";"Zergling";"Larva";198;1
"Unit";"Zergling";"Larva";198;1
"Unit";"Zergling";"Larva";198;1
"Unit";"Zergling";"Larva";198;1
"Unit";"Zergling";"Larva";198;1
"Unit";"Zergling";"Larva";198;1
"Unit";"Zergling";"Larva";198;1
"Unit";"Zergling";"Larva";198;1
"Unit";"Zergling";"Larva";198;1
"Unit";"Zergling";"Larva";198;1
"Unit";"Zergling";"Larva";198;1
"Unit";"Zergling";"Larva";198;1
"Unit";"Zergling";"Larva";198;1
"Unit";"Zergling";"Larva";198;1
"Unit";"Zergling";"Larva";198;1
"Unit";"Zergling";"Larva";198;1
"Unit";"Zergling";"Larva";198;1
"Unit";"Zergling";"Larva";198;1
"Unit";"Zergling";"Larva";198;1
"Unit";"Zergling";"Larva";198;1
"Unit";"Zergling";"Larva";198;1
"Unit";"Zergling";"Larva";198;1
"Unit";"Zergling";"Larva";200;1
"Unit";"Zergling";"Larva";200;1
"Unit";"Zergling";"Larva";200;1
"Unit";"Zergling";"Larva";200;1
"Unit";"Zergling";"Larva";200;1
"Unit";"Zergling";"Larva";200;1
"Unit";"Zergling";"Larva";200;1
"Unit";"Zergling";"Larva";200;1
"Unit";"Overlord";"Larva";200;0
"Unit";"Overlord";"Larva";200;0
"Unit";"Zergling";"Larva";200;1
"Unit";"Zergling";"Larva";200;1
"Unit";"Zergling";"Larva";202;1
"Unit";"Zergling";"Larva";202;1
"Unit";"Zergling";"Larva";202;1
"Unit";"Zergling";"Larva";202;1
"Unit";"Baneling";"Zergling";224;0
"Unit";"Baneling";"Zergling";224;0
"Unit";"Zergling";"Larva";224;1
"Unit";"Zergling";"Larva";224;1
"Unit";"Zergling";"Larva";224;1
"Unit";"Zergling";"Larva";224;1
"Unit";"Zergling";"Larva";224;1
"Unit";"Zergling";"Larva";224;1
"Unit";"Zergling";"Larva";224;1
"Unit";"Zergling";"Larva";224;1
"Unit";"Zergling";"Larva";224;1
"Unit";"Zergling";"Larva";224;1
"Building";"Spire";NA;162;0
"Building";"CreepTumorQueen";NA;248;0
"Unit";"Mutalisk";"Larva";262;2
"Unit";"Mutalisk";"Larva";262;2
"Unit";"Mutalisk";"Larva";262;2
"Unit";"Mutalisk";"Larva";262;2
"Unit";"Mutalisk";"Larva";262;2
"Unit";"Mutalisk";"Larva";262;2
"Unit";"Mutalisk";"Larva";262;2
"Unit";"Mutalisk";"Larva";262;2
"Unit";"Mutalisk";"Larva";262;2
"Unit";"Overlord";"Larva";262;0
"Building";"CreepTumor";NA;262;0
"Unit";"Overlord";"Larva";262;0
"Unit";"Zergling";"Larva";262;1
"Unit";"Zergling";"Larva";262;1
"Unit";"Zergling";"Larva";262;1
"Unit";"Zergling";"Larva";262;1
"Unit";"Baneling";"Zergling";282;0
"Unit";"Baneling";"Zergling";282;0
"Unit";"Baneling";"Zergling";282;0
"Unit";"Baneling";"Zergling";282;0
"Unit";"Baneling";"Zergling";282;0
"Unit";"Baneling";"Zergling";282;0
"Unit";"Zergling";"Larva";282;1
"Unit";"Zergling";"Larva";282;1
"Unit";"Zergling";"Larva";282;1
"Unit";"Zergling";"Larva";282;1
"Unit";"Zergling";"Larva";282;1
"Unit";"Zergling";"Larva";282;1
"Unit";"Mutalisk";"Larva";282;2
"Unit";"Mutalisk";"Larva";282;2
"Unit";"Mutalisk";"Larva";282;2
"Unit";"Baneling";"Zergling";293;0
"Unit";"Baneling";"Zergling";293;0
"Unit";"Baneling";"Zergling";293;0
"Unit";"Baneling";"Zergling";293;0
"Unit";"Overlord";"Larva";293;0
"Unit";"Overlord";"Larva";293;0
"Unit";"Mutalisk";"Larva";293;2
"Unit";"Mutalisk";"Larva";293;2
"Building";"CreepTumor";NA;299;0
"Unit";"Zergling";"Larva";299;1
"Unit";"Zergling";"Larva";299;1
"Unit";"Zergling";"Larva";299;1
"Unit";"Zergling";"Larva";299;1
"Unit";"Zergling";"Larva";299;1
"Unit";"Zergling";"Larva";299;1
"Unit";"Zergling";"Larva";299;1
"Unit";"Zergling";"Larva";299;1
"Unit";"Zergling";"Larva";299;1
"Unit";"Zergling";"Larva";299;1
"Unit";"Zergling";"Larva";299;1
"Unit";"Zergling";"Larva";299;1
"Unit";"Zergling";"Larva";299;1
"Unit";"Zergling";"Larva";299;1
"Unit";"Zergling";"Larva";299;1
"Unit";"Zergling";"Larva";299;1
"Unit";"Zergling";"Larva";299;1
"Unit";"Zergling";"Larva";299;1
"Unit";"Zergling";"Larva";299;1
"Unit";"Zergling";"Larva";299;1
"Unit";"Zergling";"Larva";299;1
"Unit";"Zergling";"Larva";299;1
"Unit";"Baneling";"Zergling";301;0
"Unit";"Baneling";"Zergling";303;0
"Unit";"Baneling";"Zergling";303;0
"Unit";"Baneling";"Zergling";303;0
"Unit";"Baneling";"Zergling";303;0
"Unit";"Baneling";"Zergling";303;0
"Unit";"Baneling";"Zergling";303;0
"Unit";"Baneling";"Zergling";303;0
"Unit";"Baneling";"Zergling";303;0
"Unit";"Baneling";"Zergling";303;0
"Unit";"Baneling";"Zergling";303;0
"Unit";"Zergling";"Larva";303;1
"Unit";"Zergling";"Larva";303;1
"Unit";"Zergling";"Larva";303;1
"Unit";"Zergling";"Larva";303;1
"Unit";"Zergling";"Larva";303;1
"Unit";"Zergling";"Larva";303;1
"Unit";"Zergling";"Larva";303;1
"Unit";"Zergling";"Larva";303;1
"Unit";"Zergling";"Larva";325;1
"Unit";"Zergling";"Larva";325;1
"Unit";"Zergling";"Larva";325;1
"Unit";"Zergling";"Larva";325;1
"Unit";"Zergling";"Larva";325;1
"Unit";"Zergling";"Larva";325;1
"Unit";"Zergling";"Larva";325;1
"Unit";"Zergling";"Larva";325;1
"Upgrade";"ZergMeleeWeaponsLevel2";"EvolutionChamber";286;0
"Upgrade";"ZergGroundArmorsLevel2";"EvolutionChamber";286;0
"Unit";"Mutalisk";"Larva";341;2
"Unit";"Mutalisk";"Larva";341;2
"Unit";"Mutalisk";"Larva";341;2
"Unit";"Mutalisk";"Larva";341;2
"Unit";"Mutalisk";"Larva";341;2
"Unit";"Mutalisk";"Larva";341;2
"Unit";"Mutalisk";"Larva";341;2
