"type";"unit_name";"on_building";"total_supply";"supply"
"Unit";"Overlord";"Larva";13;0
"Building";"Extractor";NA;18;0
"Unit";"Overlord";"Larva";21;0
"Building";"SpawningPool";NA;19;0
"Building";"Hatchery";NA;17;0
"Unit";"Zergling";"Larva";22;1
"Unit";"Zergling";"Larva";22;1
"Unit";"Zergling";"Larva";22;1
"Unit";"Zergling";"Larva";22;1
"Unit";"Queen";"Hatchery";22;2
"Unit";"Queen";"Hatchery";22;2
"Building";"CreepTumorQueen";NA;34;0
"Unit";"Overlord";"Larva";34;0
"Unit";"Queen";"Hatchery";34;2
"Building";"CreepTumorQueen";NA;39;0
"Building";"CreepTumor";NA;45;0
"Unit";"Overlord";"Larva";45;0
"Unit";"Queen";"Hatchery";45;2
"Unit";"Zergling";"Larva";48;1
"Unit";"Zergling";"Larva";48;1
"Unit";"Zergling";"Larva";48;1
"Unit";"Zergling";"Larva";48;1
"Unit";"Zergling";"Larva";48;1
"Unit";"Zergling";"Larva";48;1
"Unit";"Zergling";"Larva";48;1
"Unit";"Zergling";"Larva";48;1
"Building";"CreepTumor";NA;48;0
"Building";"CreepTumor";NA;48;0
"Building";"Extractor";NA;48;0
"Unit";"Overlord";"Larva";50;0
"Building";"Hatchery";NA;41;0
"Building";"SporeCrawler";NA;62;0
"Building";"SporeCrawler";NA;62;0
"Unit";"Overlord";"Larva";62;0
"Unit";"Overlord";"Larva";62;0
"Unit";"Overlord";"Larva";62;0
"Building";"CreepTumor";NA;63;0
"Building";"EvolutionChamber";NA;62;0
"Building";"EvolutionChamber";NA;63;0
"Building";"CreepTumor";NA;63;0
"Unit";"Overlord";"Larva";63;0
"Unit";"Overlord";"Larva";63;0
"Building";"CreepTumorQueen";NA;63;0
"Unit";"Queen";"Hatchery";63;2
"Building";"SporeCrawler";NA;71;0
"Unit";"Zergling";"Larva";71;1
"Unit";"Zergling";"Larva";71;1
"Unit";"Zergling";"Larva";71;1
"Unit";"Zergling";"Larva";71;1
"Unit";"Zergling";"Larva";71;1
"Unit";"Zergling";"Larva";71;1
"Unit";"Zergling";"Larva";79;1
"Unit";"Zergling";"Larva";79;1
"Unit";"Zergling";"Larva";79;1
"Unit";"Zergling";"Larva";79;1
"Unit";"Zergling";"Larva";79;1
"Unit";"Zergling";"Larva";79;1
"Unit";"Zergling";"Larva";79;1
"Unit";"Zergling";"Larva";79;1
"Unit";"Zergling";"Larva";79;1
"Unit";"Zergling";"Larva";79;1
"Unit";"Zergling";"Larva";79;1
"Unit";"Zergling";"Larva";79;1
"Unit";"Overlord";"Larva";85;0
"Unit";"Overlord";"Larva";85;0
"Unit";"Zergling";"Larva";97;1
"Unit";"Zergling";"Larva";97;1
"Unit";"Zergling";"Larva";97;1
"Unit";"Zergling";"Larva";97;1
"Unit";"Zergling";"Larva";97;1
"Unit";"Zergling";"Larva";97;1
"Unit";"Zergling";"Larva";97;1
"Unit";"Zergling";"Larva";97;1
"Unit";"Zergling";"Larva";97;1
"Unit";"Zergling";"Larva";97;1
"Unit";"Zergling";"Larva";99;1
"Unit";"Zergling";"Larva";99;1
"Unit";"Zergling";"Larva";99;1
"Unit";"Zergling";"Larva";99;1
"Unit";"Zergling";"Larva";99;1
"Unit";"Zergling";"Larva";99;1
"Unit";"Zergling";"Larva";99;1
"Unit";"Zergling";"Larva";99;1
"Unit";"Zergling";"Larva";99;1
"Unit";"Zergling";"Larva";99;1
"Unit";"Zergling";"Larva";103;1
"Unit";"Zergling";"Larva";103;1
"Unit";"Zergling";"Larva";105;1
"Unit";"Zergling";"Larva";105;1
"Unit";"Zergling";"Larva";105;1
"Unit";"Zergling";"Larva";105;1
"Unit";"Zergling";"Larva";105;1
"Unit";"Zergling";"Larva";105;1
"Unit";"Zergling";"Larva";105;1
"Unit";"Zergling";"Larva";105;1
"Unit";"Zergling";"Larva";105;1
"Unit";"Zergling";"Larva";105;1
"Unit";"Zergling";"Larva";105;1
"Unit";"Zergling";"Larva";105;1
"Building";"RoachWarren";NA;97;0
"Unit";"Queen";"Hatchery";97;2
"Unit";"Queen";"Hatchery";97;2
"Unit";"Queen";"Hatchery";97;2
"Unit";"Zergling";"Larva";105;1
"Unit";"Zergling";"Larva";105;1
"Unit";"Zergling";"Larva";105;1
"Unit";"Zergling";"Larva";105;1
"Unit";"Zergling";"Larva";105;1
"Unit";"Zergling";"Larva";105;1
"Unit";"Zergling";"Larva";105;1
"Unit";"Zergling";"Larva";105;1
"Upgrade";"ZergGroundArmorsLevel1";"EvolutionChamber";85;0
"Unit";"Roach";"Larva";145;2
"Unit";"Roach";"Larva";145;2
"Unit";"Roach";"Larva";145;2
"Unit";"Roach";"Larva";145;2
"Unit";"Roach";"Larva";145;2
"Unit";"Roach";"Larva";145;2
"Unit";"Roach";"Larva";145;2
"Unit";"Roach";"Larva";145;2
"Unit";"Roach";"Larva";145;2
"Unit";"Roach";"Larva";145;2
"Unit";"Roach";"Larva";145;2
"Unit";"Roach";"Larva";155;2
"Unit";"Roach";"Larva";155;2
"Unit";"Queen";"Hatchery";145;2
"Unit";"Roach";"Larva";165;2
"Building";"CreepTumorQueen";NA;183;0
"Building";"CreepTumor";NA;183;0
"Building";"CreepTumor";NA;183;0
"Building";"CreepTumor";NA;183;0
"Unit";"Zergling";"Larva";183;1
"Unit";"Zergling";"Larva";183;1
"Unit";"Zergling";"Larva";183;1
"Unit";"Zergling";"Larva";183;1
"Building";"CreepTumorQueen";NA;183;0
"Building";"CreepTumorQueen";NA;187;0
"Unit";"Overlord";"Larva";183;0
"Unit";"Overlord";"Larva";183;0
"Building";"EvolutionChamber";NA;187;0
"Building";"EvolutionChamber";NA;187;0
"Building";"CreepTumor";NA;187;0
"Building";"CreepTumor";NA;187;0
"Building";"Hatchery";NA;175;0
"Building";"Extractor";NA;187;0
"Building";"Extractor";NA;187;0
"Building";"Extractor";NA;187;0
"Building";"CreepTumor";NA;195;0
"Building";"CreepTumor";NA;195;0
"Building";"CreepTumor";NA;195;0
"Unit";"Roach";"Larva";195;2
"Building";"CreepTumor";NA;195;0
"Unit";"Roach";"Larva";195;2
"Unit";"Roach";"Larva";195;2
"Unit";"Roach";"Larva";195;2
"Unit";"Roach";"Larva";195;2
"Unit";"Roach";"Larva";195;2
"Unit";"Roach";"Larva";195;2
"Unit";"Roach";"Larva";195;2
"Building";"CreepTumorQueen";NA;195;0
"Building";"CreepTumorQueen";NA;195;0
"Unit";"Roach";"Larva";195;2
"Unit";"Roach";"Larva";195;2
"Unit";"Roach";"Larva";195;2
"Unit";"Roach";"Larva";195;2
"Unit";"Roach";"Larva";195;2
"Building";"CreepTumor";NA;211;0
"Building";"Hatchery";NA;187;0
"Unit";"Overlord";"Larva";211;0
"Unit";"Overlord";"Larva";211;0
"Unit";"Overlord";"Larva";211;0
"Building";"CreepTumor";NA;221;0
"Building";"CreepTumor";NA;221;0
"Unit";"Overlord";"Larva";226;0
"Unit";"Overlord";"Larva";226;0
"Upgrade";"Burrow";"Hatchery";211;0
"Building";"CreepTumor";NA;236;0
"Upgrade";"GlialReconstitution";"RoachWarren";211;0
"Building";"CreepTumor";NA;236;0
"Unit";"Roach";"Larva";236;2
"Upgrade";"ZergMissileWeaponsLevel1";"EvolutionChamber";195;0
"Unit";"Roach";"Larva";236;2
"Unit";"Roach";"Larva";236;2
"Unit";"Roach";"Larva";236;2
"Unit";"Roach";"Larva";236;2
"Unit";"Roach";"Larva";236;2
"Unit";"Roach";"Larva";236;2
"Unit";"Roach";"Larva";238;2
"Unit";"Roach";"Larva";238;2
"Unit";"Roach";"Larva";238;2
"Unit";"Roach";"Larva";238;2
"Unit";"Roach";"Larva";238;2
"Unit";"Roach";"Larva";238;2
"Unit";"Roach";"Larva";238;2
"Building";"CreepTumor";NA;264;0
"Unit";"Roach";"Larva";264;2
"Unit";"Roach";"Larva";264;2
"Unit";"Roach";"Larva";264;2
"Unit";"Roach";"Larva";264;2
"Unit";"Roach";"Larva";264;2
"Unit";"Roach";"Larva";264;2
"Unit";"Roach";"Larva";264;2
"Building";"Extractor";NA;264;0
"Building";"Extractor";NA;264;0
"Upgrade";"TunnelingClaws";"RoachWarren";250;0
"Unit";"Overlord";"Larva";284;0
"Unit";"Overlord";"Larva";284;0
"Unit";"Overlord";"Larva";284;0
"Unit";"Overlord";"Larva";284;0
"Unit";"Overlord";"Larva";284;0
"Building";"CreepTumor";NA;286;0
"Building";"CreepTumor";NA;286;0
"Building";"CreepTumor";NA;286;0
"Unit";"Overlord";"Larva";286;0
"Building";"Hatchery";NA;264;0
"Unit";"Roach";"Larva";286;2
"Unit";"Roach";"Larva";286;2
"Unit";"Roach";"Larva";286;2
"Unit";"Roach";"Larva";286;2
"Unit";"Roach";"Larva";286;2
"Unit";"Roach";"Larva";286;2
"Unit";"Roach";"Larva";286;2
"Unit";"Roach";"Larva";286;2
"Unit";"Roach";"Larva";286;2
"Unit";"Roach";"Larva";286;2
"Upgrade";"ZergGroundArmorsLevel2";"EvolutionChamber";240;0
"Unit";"Roach";"Larva";286;2
"Unit";"Roach";"Larva";286;2
"Unit";"Roach";"Larva";286;2
"Unit";"Roach";"Larva";286;2
"Unit";"Roach";"Larva";317;2
"Unit";"Roach";"Larva";317;2
"Unit";"Roach";"Larva";317;2
"Unit";"Roach";"Larva";317;2
"Unit";"Roach";"Larva";317;2
"Unit";"Roach";"Larva";317;2
"Unit";"Roach";"Larva";317;2
"Building";"CreepTumor";NA;317;0
"Unit";"Roach";"Larva";317;2
"Unit";"Overlord";"Larva";317;0
"Unit";"Roach";"Larva";317;2
"Unit";"Roach";"Larva";317;2
"Unit";"Overlord";"Larva";317;0
"Unit";"Roach";"Larva";337;2
"Unit";"Roach";"Larva";337;2
"Unit";"Roach";"Larva";337;2
"Unit";"Roach";"Larva";337;2
"Unit";"Roach";"Larva";337;2
"Unit";"Roach";"Larva";337;2
"Unit";"Roach";"Larva";337;2
"Unit";"Roach";"Larva";337;2
"Unit";"Roach";"Larva";337;2
"Unit";"Roach";"Larva";337;2
"Unit";"Roach";"Larva";337;2
"Unit";"Roach";"Larva";337;2
"Unit";"Roach";"Larva";337;2
"Unit";"Roach";"Larva";337;2
"Unit";"Roach";"Larva";337;2
"Unit";"Roach";"Larva";337;2
"Unit";"Roach";"Larva";337;2
"Unit";"Roach";"Larva";367;2
"Unit";"Roach";"Larva";367;2
"Unit";"Roach";"Larva";367;2
"Unit";"Roach";"Larva";367;2
"Unit";"Roach";"Larva";367;2
"Unit";"Roach";"Larva";367;2
"Unit";"Roach";"Larva";367;2
"Building";"CreepTumor";NA;385;0
"Upgrade";"ZergMissileWeaponsLevel2";"EvolutionChamber";317;0
"Unit";"Roach";"Larva";385;2
"Unit";"Roach";"Larva";385;2
"Unit";"Roach";"Larva";385;2
"Unit";"Roach";"Larva";385;2
"Unit";"Roach";"Larva";385;2
"Unit";"Roach";"Larva";385;2
"Unit";"Roach";"Larva";385;2
"Unit";"Roach";"Larva";385;2
"Unit";"Roach";"Larva";385;2
"Unit";"Roach";"Larva";385;2
"Unit";"Roach";"Larva";385;2
"Unit";"Roach";"Larva";407;2
"Unit";"Roach";"Larva";407;2
"Unit";"Roach";"Larva";407;2
"Unit";"Roach";"Larva";407;2
"Unit";"Roach";"Larva";407;2
"Unit";"Roach";"Larva";407;2
"Unit";"Roach";"Larva";407;2
"Unit";"Roach";"Larva";407;2
"Unit";"Roach";"Larva";407;2
"Unit";"Roach";"Larva";407;2
"Unit";"Queen";"Hatchery";385;2
"Unit";"Queen";"Hatchery";397;2
"Unit";"Roach";"Larva";440;2
"Unit";"Roach";"Larva";440;2
"Unit";"Roach";"Larva";440;2
"Unit";"Roach";"Larva";440;2
"Unit";"Roach";"Larva";440;2
"Unit";"Roach";"Larva";440;2
"Unit";"Roach";"Larva";440;2
"Unit";"Roach";"Larva";440;2
"Unit";"Roach";"Larva";440;2
"Unit";"Roach";"Larva";440;2
"Unit";"Roach";"Larva";440;2
"Unit";"Roach";"Larva";440;2
"Unit";"Roach";"Larva";440;2
"Unit";"Roach";"Larva";440;2
"Building";"Extractor";NA;468;0
"Unit";"Roach";"Larva";468;2
"Unit";"Roach";"Larva";468;2
"Unit";"Roach";"Larva";468;2
"Unit";"Roach";"Larva";468;2
"Unit";"Roach";"Larva";468;2
"Unit";"Roach";"Larva";468;2
"Unit";"Roach";"Larva";468;2
"Unit";"Roach";"Larva";468;2
"Unit";"Roach";"Larva";468;2
"Unit";"Roach";"Larva";468;2
"Unit";"Roach";"Larva";468;2
"Unit";"Roach";"Larva";468;2
"Unit";"Roach";"Larva";468;2
"Building";"CreepTumor";NA;471;0
"Building";"CreepTumor";NA;471;0
"Building";"CreepTumor";NA;471;0
"Building";"CreepTumor";NA;473;0
"Unit";"Roach";"Larva";471;2
"Unit";"Roach";"Larva";471;2
"Unit";"Roach";"Larva";471;2
"Unit";"Roach";"Larva";471;2
"Unit";"Roach";"Larva";471;2
"Unit";"Roach";"Larva";471;2
"Unit";"Roach";"Larva";471;2
"Unit";"Roach";"Larva";471;2
"Building";"Hatchery";NA;440;0
"Unit";"Overlord";"Larva";497;0
"Unit";"Overlord";"Larva";497;0
"Building";"InfestationPit";NA;471;0
"Building";"CreepTumor";NA;513;0
"Unit";"Roach";"Larva";513;2
"Unit";"Roach";"Larva";513;2
"Unit";"Roach";"Larva";513;2
"Unit";"Roach";"Larva";513;2
"Unit";"Roach";"Larva";513;2
"Unit";"Roach";"Larva";513;2
"Unit";"Roach";"Larva";513;2
"Unit";"Roach";"Larva";513;2
"Unit";"Roach";"Larva";513;2
"Unit";"Roach";"Larva";513;2
"Unit";"Roach";"Larva";513;2
"Building";"Extractor";NA;513;0
"Building";"Extractor";NA;513;0
"Building";"Hatchery";NA;471;0
"Unit";"Roach";"Larva";540;2
"Unit";"Roach";"Larva";540;2
"Unit";"Roach";"Larva";540;2
"Building";"CreepTumor";NA;540;0
"Building";"CreepTumor";NA;540;0
"Unit";"Roach";"Larva";546;2
"Unit";"Roach";"Larva";546;2
"Unit";"Roach";"Larva";546;2
"Unit";"Roach";"Larva";546;2
"Unit";"Roach";"Larva";546;2
"Unit";"Roach";"Larva";546;2
"Unit";"Roach";"Larva";546;2
"Unit";"Roach";"Larva";546;2
"Unit";"Roach";"Larva";546;2
"Unit";"Roach";"Larva";546;2
"Unit";"Roach";"Larva";546;2
"Unit";"Roach";"Larva";546;2
"Unit";"Roach";"Larva";546;2
"Unit";"Roach";"Larva";546;2
"Unit";"Roach";"Larva";546;2
"Unit";"Roach";"Larva";577;2
"Unit";"Roach";"Larva";582;2
"Unit";"Roach";"Larva";582;2
"Unit";"Roach";"Larva";582;2
"Unit";"Roach";"Larva";582;2
"Building";"Extractor";NA;582;0
"Unit";"Roach";"Larva";592;2
"Unit";"Roach";"Larva";592;2
"Unit";"Roach";"Larva";592;2
"Unit";"Roach";"Larva";592;2
"Unit";"Roach";"Larva";599;2
"Unit";"Roach";"Larva";599;2
"Unit";"Roach";"Larva";599;2
"Unit";"Roach";"Larva";599;2
"Unit";"Roach";"Larva";599;2
"Unit";"Roach";"Larva";599;2
"Unit";"Viper";"Larva";619;3
"Building";"Extractor";NA;619;0
"Unit";"Viper";"Larva";619;3
"Unit";"Overlord";"Larva";625;0
"Unit";"Overlord";"Larva";625;0
"Building";"Extractor";NA;625;0
"Building";"Extractor";NA;625;0
"Building";"Hatchery";NA;619;0
"Unit";"Roach";"Larva";625;2
"Unit";"Roach";"Larva";625;2
"Unit";"Roach";"Larva";625;2
"Unit";"Roach";"Larva";625;2
"Unit";"Roach";"Larva";625;2
"Unit";"Roach";"Larva";625;2
"Unit";"Roach";"Larva";625;2
"Unit";"Roach";"Larva";625;2
"Unit";"Roach";"Larva";625;2
"Unit";"Roach";"Larva";643;2
"Unit";"Roach";"Larva";643;2
"Unit";"Roach";"Larva";643;2
"Unit";"Roach";"Larva";643;2
"Unit";"Roach";"Larva";643;2
"Unit";"Roach";"Larva";643;2
"Unit";"Roach";"Larva";655;2
"Unit";"Roach";"Larva";655;2
"Unit";"Roach";"Larva";655;2
"Unit";"Roach";"Larva";655;2
"Unit";"Roach";"Larva";655;2
"Unit";"Roach";"Larva";655;2
"Unit";"Roach";"Larva";655;2
"Unit";"Roach";"Larva";655;2
"Unit";"Roach";"Larva";655;2
"Unit";"Roach";"Larva";655;2
"Unit";"Roach";"Larva";655;2
"Unit";"Roach";"Larva";655;2
"Unit";"Roach";"Larva";679;2
"Unit";"Roach";"Larva";679;2
"Unit";"Roach";"Larva";679;2
"Unit";"Roach";"Larva";679;2
"Unit";"Roach";"Larva";679;2
"Unit";"Roach";"Larva";679;2
"Unit";"Overlord";"Larva";679;0
"Unit";"Overlord";"Larva";679;0
"Unit";"Overlord";"Larva";679;0
"Unit";"Overlord";"Larva";691;0
"Unit";"Overlord";"Larva";691;0
"Unit";"Overlord";"Larva";691;0
"Unit";"Overlord";"Larva";691;0
"Unit";"Roach";"Larva";691;2
"Unit";"Roach";"Larva";691;2
"Unit";"Roach";"Larva";691;2
"Unit";"Roach";"Larva";691;2
"Unit";"Roach";"Larva";691;2
"Unit";"Roach";"Larva";691;2
"Unit";"Roach";"Larva";691;2
"Unit";"Roach";"Larva";691;2
"Unit";"Roach";"Larva";691;2
"Unit";"Roach";"Larva";691;2
"Unit";"Roach";"Larva";691;2
"Unit";"Roach";"Larva";691;2
"Unit";"Roach";"Larva";691;2
"Unit";"Roach";"Larva";691;2
"Unit";"Roach";"Larva";691;2
"Unit";"Roach";"Larva";691;2
"Unit";"Roach";"Larva";691;2
"Unit";"Roach";"Larva";691;2
"Unit";"Roach";"Larva";691;2
"Unit";"Roach";"Larva";691;2
"Unit";"Roach";"Larva";691;2
"Unit";"Roach";"Larva";691;2
"Unit";"Roach";"Larva";691;2
"Unit";"Roach";"Larva";691;2
"Unit";"Roach";"Larva";691;2
"Unit";"Roach";"Larva";691;2
