"type";"unit_name";"on_building";"total_supply";"supply"
"Unit";"Overlord";"Larva";12;0
"Building";"Extractor";NA;18;0
"Unit";"Overlord";"Larva";21;0
"Building";"SpawningPool";NA;19;0
"Building";"Hatchery";NA;17;0
"Unit";"Zergling";"Larva";22;1
"Unit";"Zergling";"Larva";22;1
"Unit";"Zergling";"Larva";23;1
"Unit";"Zergling";"Larva";23;1
"Unit";"Queen";"Hatchery";22;2
"Unit";"Queen";"Hatchery";23;2
"Unit";"Overlord";"Larva";34;0
"Unit";"Queen";"Hatchery";32;2
"Unit";"Overlord";"Larva";41;0
"Building";"CreepTumorQueen";NA;43;0
"Unit";"Queen";"Hatchery";41;2
"Unit";"Zergling";"Larva";47;1
"Unit";"Zergling";"Larva";47;1
"Unit";"Zergling";"Larva";47;1
"Unit";"Zergling";"Larva";47;1
"Unit";"Zergling";"Larva";48;1
"Unit";"Zergling";"Larva";48;1
"Unit";"Zergling";"Larva";48;1
"Unit";"Zergling";"Larva";48;1
"Unit";"Zergling";"Larva";48;1
"Unit";"Zergling";"Larva";48;1
"Building";"CreepTumorQueen";NA;54;0
"Unit";"Overlord";"Larva";48;0
"Building";"CreepTumorQueen";NA;58;0
"Building";"Hatchery";NA;39;0
"Building";"Extractor";NA;62;0
"Building";"Extractor";NA;64;0
"Unit";"Queen";"Hatchery";64;2
"Building";"CreepTumorQueen";NA;72;0
"Building";"CreepTumor";NA;72;0
"Unit";"Overlord";"Larva";67;0
"Unit";"Overlord";"Larva";67;0
"Building";"EvolutionChamber";NA;67;0
"Building";"EvolutionChamber";NA;67;0
"Building";"CreepTumorQueen";NA;75;0
"Building";"CreepTumorQueen";NA;75;0
"Building";"CreepTumor";NA;75;0
"Unit";"Overlord";"Larva";81;0
"Unit";"Overlord";"Larva";81;0
"Unit";"Queen";"Hatchery";75;2
"Building";"CreepTumorQueen";NA;85;0
"Building";"CreepTumorQueen";NA;85;0
"Building";"CreepTumor";NA;85;0
"Building";"CreepTumor";NA;85;0
"Unit";"Zergling";"Larva";85;1
"Unit";"Zergling";"Larva";85;1
"Unit";"Zergling";"Larva";85;1
"Unit";"Zergling";"Larva";85;1
"Unit";"Zergling";"Larva";85;1
"Unit";"Zergling";"Larva";85;1
"Building";"CreepTumor";NA;85;0
"Building";"CreepTumor";NA;87;0
"Unit";"Zergling";"Larva";85;1
"Unit";"Zergling";"Larva";85;1
"Unit";"Zergling";"Larva";85;1
"Unit";"Zergling";"Larva";85;1
"Unit";"Zergling";"Larva";85;1
"Unit";"Zergling";"Larva";85;1
"Unit";"Zergling";"Larva";85;1
"Unit";"Zergling";"Larva";85;1
"Unit";"Overlord";"Larva";93;0
"Unit";"Overlord";"Larva";93;0
"Building";"CreepTumor";NA;106;0
"Building";"CreepTumor";NA;106;0
"Building";"CreepTumor";NA;106;0
"Unit";"Overlord";"Larva";106;0
"Unit";"Overlord";"Larva";106;0
"Unit";"Overlord";"Larva";106;0
"Unit";"Overlord";"Larva";106;0
"Building";"CreepTumor";NA;106;0
"Building";"CreepTumor";NA;106;0
"Building";"CreepTumor";NA;106;0
"Unit";"Zergling";"Larva";106;1
"Unit";"Zergling";"Larva";106;1
"Building";"CreepTumor";NA;106;0
"Building";"CreepTumor";NA;106;0
"Building";"Extractor";NA;106;0
"Unit";"Queen";"Hatchery";106;2
"Building";"CreepTumor";NA;106;0
"Unit";"Zergling";"Larva";106;1
"Unit";"Zergling";"Larva";106;1
"Unit";"Zergling";"Larva";106;1
"Unit";"Zergling";"Larva";106;1
"Unit";"Zergling";"Larva";106;1
"Unit";"Zergling";"Larva";106;1
"Unit";"Zergling";"Larva";106;1
"Unit";"Zergling";"Larva";106;1
"Unit";"Zergling";"Larva";106;1
"Unit";"Zergling";"Larva";106;1
"Unit";"Zergling";"Larva";106;1
"Unit";"Zergling";"Larva";106;1
"Unit";"Zergling";"Larva";106;1
"Unit";"Zergling";"Larva";106;1
"Unit";"Zergling";"Larva";106;1
"Unit";"Zergling";"Larva";106;1
"Unit";"Queen";"Hatchery";106;2
"Unit";"Queen";"Hatchery";106;2
"Upgrade";"ZergGroundArmorsLevel1";"EvolutionChamber";87;0
"Unit";"Zergling";"Larva";110;1
"Unit";"Zergling";"Larva";110;1
"Unit";"Zergling";"Larva";110;1
"Unit";"Zergling";"Larva";110;1
"Unit";"Zergling";"Larva";110;1
"Unit";"Zergling";"Larva";110;1
"Unit";"Zergling";"Larva";110;1
"Unit";"Zergling";"Larva";110;1
"Unit";"Zergling";"Larva";110;1
"Unit";"Zergling";"Larva";110;1
"Unit";"Zergling";"Larva";110;1
"Unit";"Zergling";"Larva";110;1
"Building";"CreepTumor";NA;142;0
"Building";"CreepTumor";NA;142;0
"Building";"CreepTumor";NA;142;0
"Building";"CreepTumor";NA;142;0
"Upgrade";"ZergMeleeWeaponsLevel1";"EvolutionChamber";106;0
"Building";"SporeCrawler";NA;142;0
"Building";"CreepTumor";NA;146;0
"Building";"Hatchery";NA;106;0
"Building";"Spire";NA;106;0
"Building";"CreepTumor";NA;146;0
"Unit";"Overlord";"Larva";145;0
"Unit";"Overlord";"Larva";145;0
"Building";"CreepTumor";NA;146;0
"Building";"Extractor";NA;145;0
"Building";"Extractor";NA;145;0
"Building";"Hatchery";NA;106;0
"Unit";"Zergling";"Larva";146;1
"Unit";"Zergling";"Larva";146;1
"Unit";"Zergling";"Larva";146;1
"Unit";"Zergling";"Larva";146;1
"Unit";"Zergling";"Larva";146;1
"Unit";"Zergling";"Larva";146;1
"Building";"CreepTumor";NA;149;0
"Building";"CreepTumor";NA;149;0
"Building";"CreepTumor";NA;149;0
"Unit";"Zergling";"Larva";149;1
"Unit";"Zergling";"Larva";149;1
"Unit";"Zergling";"Larva";149;1
"Unit";"Zergling";"Larva";149;1
"Unit";"Zergling";"Larva";149;1
"Unit";"Zergling";"Larva";149;1
"Unit";"Zergling";"Larva";149;1
"Unit";"Zergling";"Larva";149;1
"Unit";"Zergling";"Larva";149;1
"Unit";"Zergling";"Larva";149;1
"Unit";"Zergling";"Larva";149;1
"Unit";"Zergling";"Larva";149;1
"Building";"CreepTumor";NA;167;0
"Unit";"Queen";"Hatchery";146;2
"Unit";"Queen";"Hatchery";146;2
"Unit";"Queen";"Hatchery";146;2
"Building";"BanelingNest";NA;146;0
"Building";"CreepTumor";NA;179;0
"Building";"CreepTumor";NA;179;0
"Unit";"Zergling";"Larva";179;1
"Unit";"Zergling";"Larva";179;1
"Unit";"Zergling";"Larva";179;1
"Unit";"Zergling";"Larva";179;1
"Unit";"Zergling";"Larva";179;1
"Unit";"Zergling";"Larva";179;1
"Unit";"Zergling";"Larva";179;1
"Unit";"Zergling";"Larva";179;1
"Unit";"Zergling";"Larva";179;1
"Unit";"Zergling";"Larva";179;1
"Unit";"Zergling";"Larva";179;1
"Unit";"Zergling";"Larva";179;1
"Unit";"Zergling";"Larva";179;1
"Unit";"Zergling";"Larva";179;1
"Unit";"Zergling";"Larva";179;1
"Unit";"Zergling";"Larva";179;1
"Unit";"Zergling";"Larva";179;1
"Unit";"Zergling";"Larva";179;1
"Unit";"Zergling";"Larva";179;1
"Unit";"Zergling";"Larva";179;1
"Unit";"Zergling";"Larva";179;1
"Unit";"Zergling";"Larva";179;1
"Unit";"Zergling";"Larva";179;1
"Unit";"Zergling";"Larva";179;1
"Unit";"Zergling";"Larva";179;1
"Unit";"Zergling";"Larva";179;1
"Unit";"Baneling";"Zergling";179;0
"Unit";"Baneling";"Zergling";179;0
"Unit";"Baneling";"Zergling";179;0
"Unit";"Baneling";"Zergling";179;0
"Unit";"Baneling";"Zergling";179;0
"Unit";"Baneling";"Zergling";179;0
"Unit";"Baneling";"Zergling";179;0
"Unit";"Baneling";"Zergling";179;0
"Unit";"Zergling";"Larva";205;1
"Unit";"Zergling";"Larva";205;1
"Unit";"Zergling";"Larva";205;1
"Unit";"Zergling";"Larva";205;1
"Unit";"Zergling";"Larva";205;1
"Unit";"Zergling";"Larva";205;1
"Unit";"Zergling";"Larva";205;1
"Unit";"Zergling";"Larva";205;1
"Unit";"Zergling";"Larva";205;1
"Unit";"Zergling";"Larva";205;1
"Unit";"Zergling";"Larva";205;1
"Unit";"Zergling";"Larva";205;1
"Unit";"Zergling";"Larva";205;1
"Unit";"Zergling";"Larva";205;1
"Unit";"Zergling";"Larva";205;1
"Unit";"Zergling";"Larva";205;1
"Unit";"Zergling";"Larva";205;1
"Unit";"Zergling";"Larva";205;1
"Building";"CreepTumorQueen";NA;223;0
"Unit";"Zergling";"Larva";205;1
"Unit";"Zergling";"Larva";205;1
"Unit";"Zergling";"Larva";205;1
"Unit";"Zergling";"Larva";205;1
"Unit";"Zergling";"Larva";205;1
"Unit";"Zergling";"Larva";205;1
"Unit";"Zergling";"Larva";205;1
"Unit";"Zergling";"Larva";205;1
"Unit";"Zergling";"Larva";205;1
"Unit";"Zergling";"Larva";205;1
"Unit";"Zergling";"Larva";205;1
"Unit";"Zergling";"Larva";205;1
"Unit";"Zergling";"Larva";205;1
"Unit";"Zergling";"Larva";205;1
"Unit";"Zergling";"Larva";205;1
"Unit";"Zergling";"Larva";205;1
"Unit";"Mutalisk";"Larva";223;2
"Unit";"Mutalisk";"Larva";223;2
"Unit";"Mutalisk";"Larva";223;2
"Unit";"Mutalisk";"Larva";223;2
"Unit";"Mutalisk";"Larva";223;2
"Unit";"Mutalisk";"Larva";223;2
"Unit";"Mutalisk";"Larva";223;2
"Unit";"Mutalisk";"Larva";223;2
"Unit";"Mutalisk";"Larva";223;2
"Unit";"Mutalisk";"Larva";223;2
"Unit";"Mutalisk";"Larva";223;2
"Building";"CreepTumorQueen";NA;239;0
"Building";"CreepTumor";NA;239;0
"Building";"CreepTumorQueen";NA;239;0
"Upgrade";"ZergMeleeWeaponsLevel2";"EvolutionChamber";179;0
"Upgrade";"ZergGroundArmorsLevel2";"EvolutionChamber";179;0
"Building";"CreepTumor";NA;261;0
"Unit";"Overlord";"Larva";261;0
"Unit";"Overlord";"Larva";261;0
"Unit";"Mutalisk";"Larva";261;2
"Unit";"Overlord";"Larva";261;0
"Unit";"Overlord";"Larva";261;0
"Unit";"Overlord";"Larva";261;0
"Unit";"Mutalisk";"Larva";261;2
"Unit";"Overlord";"Larva";261;0
"Unit";"Mutalisk";"Larva";261;2
"Unit";"Mutalisk";"Larva";261;2
"Unit";"Mutalisk";"Larva";261;2
"Unit";"Mutalisk";"Larva";261;2
"Building";"InfestationPit";NA;261;0
"Unit";"Zergling";"Larva";273;1
"Unit";"Zergling";"Larva";273;1
"Unit";"Zergling";"Larva";273;1
"Unit";"Zergling";"Larva";273;1
"Unit";"Zergling";"Larva";273;1
"Unit";"Zergling";"Larva";273;1
"Unit";"Zergling";"Larva";273;1
"Unit";"Zergling";"Larva";273;1
"Unit";"Zergling";"Larva";273;1
"Unit";"Zergling";"Larva";273;1
"Unit";"Zergling";"Larva";273;1
"Unit";"Zergling";"Larva";273;1
"Unit";"Zergling";"Larva";273;1
"Unit";"Zergling";"Larva";273;1
"Building";"Extractor";NA;273;0
"Building";"Extractor";NA;273;0
"Unit";"Baneling";"Zergling";289;0
"Unit";"Baneling";"Zergling";297;0
"Unit";"Baneling";"Zergling";299;0
"Unit";"Baneling";"Zergling";301;0
"Unit";"Baneling";"Zergling";301;0
"Unit";"Baneling";"Zergling";302;0
"Unit";"Baneling";"Zergling";302;0
"Unit";"Baneling";"Zergling";302;0
"Unit";"Baneling";"Zergling";302;0
"Unit";"Baneling";"Zergling";302;0
"Unit";"Baneling";"Zergling";302;0
"Unit";"Baneling";"Zergling";302;0
"Unit";"Baneling";"Zergling";302;0
"Unit";"Zergling";"Larva";287;1
"Unit";"Zergling";"Larva";287;1
"Unit";"Zergling";"Larva";287;1
"Unit";"Zergling";"Larva";287;1
"Unit";"Baneling";"Zergling";306;0
"Unit";"Baneling";"Zergling";306;0
"Unit";"Baneling";"Zergling";306;0
"Unit";"Baneling";"Zergling";306;0
"Unit";"Baneling";"Zergling";306;0
"Unit";"Baneling";"Zergling";306;0
"Unit";"Baneling";"Zergling";306;0
"Unit";"Baneling";"Zergling";306;0
"Unit";"Baneling";"Zergling";306;0
"Unit";"Baneling";"Zergling";306;0
"Unit";"Baneling";"Zergling";306;0
"Unit";"Baneling";"Zergling";306;0
"Unit";"Zergling";"Larva";302;1
"Unit";"Zergling";"Larva";302;1
"Unit";"Zergling";"Larva";302;1
"Unit";"Zergling";"Larva";302;1
"Unit";"Zergling";"Larva";304;1
"Unit";"Zergling";"Larva";304;1
"Unit";"Zergling";"Larva";304;1
"Unit";"Zergling";"Larva";304;1
"Unit";"Zergling";"Larva";304;1
"Unit";"Zergling";"Larva";304;1
"Unit";"Zergling";"Larva";304;1
"Unit";"Zergling";"Larva";304;1
"Unit";"Zergling";"Larva";304;1
"Unit";"Zergling";"Larva";304;1
"Unit";"Zergling";"Larva";304;1
"Unit";"Zergling";"Larva";304;1
"Unit";"Zergling";"Larva";304;1
"Unit";"Zergling";"Larva";304;1
"Unit";"Zergling";"Larva";304;1
"Unit";"Zergling";"Larva";304;1
"Building";"CreepTumorQueen";NA;326;0
"Building";"CreepTumorQueen";NA;326;0
"Building";"CreepTumorQueen";NA;326;0
"Unit";"Zergling";"Larva";326;1
"Unit";"Zergling";"Larva";326;1
"Unit";"Zergling";"Larva";326;1
"Unit";"Zergling";"Larva";326;1
"Unit";"Zergling";"Larva";326;1
"Unit";"Zergling";"Larva";326;1
"Unit";"Zergling";"Larva";326;1
"Unit";"Zergling";"Larva";326;1
"Unit";"Zergling";"Larva";326;1
"Unit";"Zergling";"Larva";326;1
"Unit";"Zergling";"Larva";326;1
"Unit";"Zergling";"Larva";326;1
"Unit";"Zergling";"Larva";326;1
"Unit";"Zergling";"Larva";326;1
"Unit";"Zergling";"Larva";326;1
"Unit";"Zergling";"Larva";326;1
"Unit";"Zergling";"Larva";326;1
"Unit";"Zergling";"Larva";326;1
"Unit";"Zergling";"Larva";344;1
"Unit";"Zergling";"Larva";344;1
"Unit";"Zergling";"Larva";344;1
"Unit";"Zergling";"Larva";344;1
"Unit";"Zergling";"Larva";344;1
"Unit";"Zergling";"Larva";344;1
"Unit";"Zergling";"Larva";344;1
"Unit";"Zergling";"Larva";344;1
"Unit";"Zergling";"Larva";344;1
"Unit";"Zergling";"Larva";344;1
"Unit";"Zergling";"Larva";344;1
"Unit";"Zergling";"Larva";344;1
"Unit";"Zergling";"Larva";344;1
"Unit";"Zergling";"Larva";344;1
"Unit";"Zergling";"Larva";344;1
"Unit";"Zergling";"Larva";344;1
"Unit";"Zergling";"Larva";344;1
"Unit";"Zergling";"Larva";344;1
"Unit";"Zergling";"Larva";344;1
"Unit";"Zergling";"Larva";344;1
"Unit";"Zergling";"Larva";344;1
"Unit";"Zergling";"Larva";344;1
"Unit";"Zergling";"Larva";344;1
"Unit";"Zergling";"Larva";344;1
"Unit";"Zergling";"Larva";344;1
"Unit";"Zergling";"Larva";344;1
"Unit";"Zergling";"Larva";344;1
"Unit";"Zergling";"Larva";344;1
"Building";"CreepTumor";NA;344;0
"Building";"CreepTumorQueen";NA;348;0
"Unit";"Baneling";"Zergling";348;0
"Unit";"Baneling";"Zergling";348;0
"Unit";"Baneling";"Zergling";348;0
"Unit";"Baneling";"Zergling";348;0
"Unit";"Baneling";"Zergling";348;0
"Unit";"Baneling";"Zergling";348;0
"Unit";"Baneling";"Zergling";348;0
"Unit";"Baneling";"Zergling";348;0
"Unit";"Baneling";"Zergling";348;0
"Unit";"Baneling";"Zergling";348;0
"Unit";"Baneling";"Zergling";348;0
"Building";"CreepTumorQueen";NA;348;0
"Building";"CreepTumor";NA;348;0
"Building";"CreepTumorQueen";NA;348;0
"Building";"CreepTumor";NA;376;0
"Building";"CreepTumor";NA;376;0
"Unit";"Zergling";"Larva";376;1
"Unit";"Zergling";"Larva";376;1
"Unit";"Zergling";"Larva";376;1
"Unit";"Zergling";"Larva";376;1
"Unit";"Zergling";"Larva";376;1
"Unit";"Zergling";"Larva";376;1
"Unit";"Zergling";"Larva";376;1
"Unit";"Zergling";"Larva";376;1
"Unit";"Zergling";"Larva";376;1
"Unit";"Zergling";"Larva";376;1
"Unit";"Zergling";"Larva";376;1
"Unit";"Zergling";"Larva";376;1
"Unit";"Zergling";"Larva";376;1
"Unit";"Zergling";"Larva";376;1
"Building";"UltraliskCavern";NA;344;0
"Unit";"Zergling";"Larva";390;1
"Unit";"Zergling";"Larva";390;1
"Unit";"Zergling";"Larva";390;1
"Unit";"Zergling";"Larva";390;1
"Unit";"Zergling";"Larva";390;1
"Unit";"Zergling";"Larva";390;1
"Unit";"Zergling";"Larva";390;1
"Unit";"Zergling";"Larva";390;1
"Unit";"Zergling";"Larva";390;1
"Unit";"Zergling";"Larva";390;1
"Unit";"Zergling";"Larva";390;1
"Unit";"Zergling";"Larva";390;1
"Unit";"Zergling";"Larva";390;1
"Unit";"Zergling";"Larva";390;1
"Unit";"Zergling";"Larva";390;1
"Unit";"Zergling";"Larva";390;1
"Building";"CreepTumor";NA;390;0
"Building";"CreepTumor";NA;390;0
"Building";"CreepTumor";NA;390;0
"Building";"CreepTumor";NA;390;0
"Building";"CreepTumor";NA;390;0
"Building";"CreepTumor";NA;390;0
"Building";"CreepTumor";NA;390;0
"Building";"CreepTumor";NA;390;0
"Building";"CreepTumor";NA;390;0
"Building";"CreepTumorQueen";NA;406;0
"Building";"CreepTumorQueen";NA;406;0
"Building";"CreepTumorQueen";NA;406;0
"Unit";"Baneling";"Zergling";406;0
"Unit";"Baneling";"Zergling";406;0
"Unit";"Baneling";"Zergling";406;0
"Unit";"Baneling";"Zergling";406;0
"Unit";"Baneling";"Zergling";406;0
"Unit";"Baneling";"Zergling";406;0
"Unit";"Baneling";"Zergling";406;0
"Unit";"Baneling";"Zergling";406;0
"Unit";"Baneling";"Zergling";406;0
"Unit";"Baneling";"Zergling";406;0
"Unit";"Baneling";"Zergling";406;0
"Unit";"Baneling";"Zergling";406;0
"Unit";"Baneling";"Zergling";406;0
"Unit";"Baneling";"Zergling";406;0
"Building";"CreepTumor";NA;406;0
"Building";"CreepTumorQueen";NA;406;0
"Building";"CreepTumorQueen";NA;406;0
"Building";"CreepTumor";NA;406;0
"Building";"CreepTumor";NA;406;0
"Unit";"Ultralisk";"Larva";390;6
"Unit";"Ultralisk";"Larva";390;6
"Unit";"Ultralisk";"Larva";390;6
"Unit";"Ultralisk";"Larva";390;6
"Unit";"Ultralisk";"Larva";390;6
"Unit";"Ultralisk";"Larva";390;6
"Building";"Hatchery";NA;376;0
"Building";"CreepTumor";NA;442;0
"Building";"CreepTumor";NA;442;0
"Building";"CreepTumor";NA;442;0
"Building";"CreepTumor";NA;442;0
"Upgrade";"ChitinousPlating";"UltraliskCavern";406;0
"Unit";"Zergling";"Larva";442;1
"Unit";"Zergling";"Larva";442;1
"Unit";"Zergling";"Larva";442;1
"Unit";"Zergling";"Larva";442;1
"Unit";"Zergling";"Larva";442;1
"Unit";"Zergling";"Larva";442;1
"Unit";"Zergling";"Larva";442;1
"Unit";"Zergling";"Larva";442;1
"Unit";"Zergling";"Larva";442;1
"Unit";"Zergling";"Larva";442;1
"Unit";"Zergling";"Larva";442;1
"Unit";"Zergling";"Larva";442;1
"Unit";"Zergling";"Larva";442;1
"Unit";"Zergling";"Larva";442;1
"Unit";"Zergling";"Larva";442;1
"Unit";"Zergling";"Larva";442;1
"Unit";"Zergling";"Larva";442;1
"Unit";"Zergling";"Larva";442;1
"Unit";"Zergling";"Larva";442;1
"Unit";"Zergling";"Larva";442;1
