"type";"unit_name";"on_building";"total_supply";"supply"
"Unit";"Overlord";"Larva";13;0
"Building";"Extractor";NA;17;0
"Unit";"Overlord";"Larva";21;0
"Building";"Hatchery";NA;17;0
"Building";"SpawningPool";NA;19;0
"Unit";"Zergling";"Larva";23;1
"Unit";"Zergling";"Larva";23;1
"Unit";"Zergling";"Larva";23;1
"Unit";"Zergling";"Larva";23;1
"Unit";"Queen";"Hatchery";23;2
"Unit";"Queen";"Hatchery";23;2
"Building";"EvolutionChamber";NA;36;0
"Building";"EvolutionChamber";NA;36;0
"Unit";"Overlord";"Larva";42;0
"Unit";"Overlord";"Larva";44;0
"Building";"Hatchery";NA;35;0
"Unit";"Overlord";"Larva";44;0
"Unit";"Queen";"Hatchery";44;2
"Building";"Extractor";NA;46;0
"Unit";"Zergling";"Larva";46;1
"Unit";"Zergling";"Larva";46;1
"Unit";"Zergling";"Larva";46;1
"Unit";"Zergling";"Larva";46;1
"Unit";"Zergling";"Larva";46;1
"Unit";"Zergling";"Larva";46;1
"Unit";"Zergling";"Larva";46;1
"Unit";"Zergling";"Larva";46;1
"Unit";"Queen";"Hatchery";44;2
"Unit";"Zergling";"Larva";50;1
"Unit";"Zergling";"Larva";50;1
"Building";"CreepTumorQueen";NA;58;0
"Building";"CreepTumorQueen";NA;58;0
"Unit";"Queen";"Hatchery";50;2
"Unit";"Overlord";"Larva";65;0
"Building";"CreepTumorQueen";NA;65;0
"Building";"CreepTumorQueen";NA;65;0
"Building";"CreepTumor";NA;67;0
"Building";"CreepTumor";NA;67;0
"Unit";"Overlord";"Larva";67;0
"Upgrade";"ZergMeleeWeaponsLevel1";"EvolutionChamber";46;0
"Building";"SporeCrawler";NA;67;0
"Unit";"Overlord";"Larva";72;0
"Building";"SporeCrawler";NA;72;0
"Unit";"Queen";"Hatchery";67;2
"Building";"CreepTumorQueen";NA;76;0
"Building";"CreepTumorQueen";NA;76;0
"Building";"SporeCrawler";NA;72;0
"Upgrade";"ZergGroundArmorsLevel1";"EvolutionChamber";48;0
"Unit";"Overlord";"Larva";95;0
"Unit";"Zergling";"Larva";95;1
"Unit";"Zergling";"Larva";95;1
"Unit";"Zergling";"Larva";95;1
"Unit";"Zergling";"Larva";95;1
"Unit";"Zergling";"Larva";95;1
"Unit";"Zergling";"Larva";95;1
"Unit";"Zergling";"Larva";95;1
"Unit";"Zergling";"Larva";95;1
"Unit";"Zergling";"Larva";95;1
"Unit";"Zergling";"Larva";95;1
"Building";"CreepTumor";NA;95;0
"Building";"CreepTumor";NA;95;0
"Building";"CreepTumor";NA;105;0
"Building";"CreepTumor";NA;105;0
"Building";"CreepTumor";NA;105;0
"Building";"CreepTumor";NA;105;0
"Building";"CreepTumorQueen";NA;117;0
"Unit";"Overlord";"Larva";108;0
"Unit";"Overlord";"Larva";108;0
"Unit";"Overlord";"Larva";108;0
"Building";"CreepTumorQueen";NA;117;0
"Building";"CreepTumorQueen";NA;117;0
"Building";"Hatchery";NA;93;0
"Unit";"Zergling";"Larva";117;1
"Unit";"Zergling";"Larva";117;1
"Unit";"Zergling";"Larva";117;1
"Unit";"Zergling";"Larva";117;1
"Unit";"Zergling";"Larva";117;1
"Unit";"Zergling";"Larva";117;1
"Unit";"Zergling";"Larva";117;1
"Unit";"Zergling";"Larva";117;1
"Unit";"Zergling";"Larva";117;1
"Unit";"Zergling";"Larva";117;1
"Unit";"Zergling";"Larva";117;1
"Unit";"Zergling";"Larva";117;1
"Unit";"Zergling";"Larva";117;1
"Unit";"Zergling";"Larva";117;1
"Unit";"Overlord";"Larva";117;0
"Building";"CreepTumor";NA;131;0
"Building";"CreepTumorQueen";NA;131;0
"Building";"CreepTumor";NA;131;0
"Building";"InfestationPit";NA;117;0
"Building";"CreepTumorQueen";NA;131;0
"Building";"CreepTumor";NA;131;0
"Building";"CreepTumor";NA;131;0
"Building";"CreepTumor";NA;131;0
"Building";"CreepTumor";NA;131;0
"Unit";"Queen";"Hatchery";117;2
"Unit";"Queen";"Hatchery";117;2
"Unit";"Zergling";"Larva";137;1
"Unit";"Zergling";"Larva";137;1
"Unit";"Zergling";"Larva";137;1
"Unit";"Zergling";"Larva";137;1
"Unit";"Zergling";"Larva";137;1
"Unit";"Zergling";"Larva";137;1
"Unit";"Zergling";"Larva";137;1
"Unit";"Zergling";"Larva";137;1
"Unit";"Zergling";"Larva";137;1
"Unit";"Zergling";"Larva";137;1
"Unit";"Zergling";"Larva";137;1
"Unit";"Zergling";"Larva";137;1
"Unit";"Zergling";"Larva";137;1
"Unit";"Zergling";"Larva";137;1
"Unit";"Zergling";"Larva";137;1
"Unit";"Zergling";"Larva";137;1
"Unit";"Zergling";"Larva";137;1
"Unit";"Zergling";"Larva";137;1
"Unit";"Zergling";"Larva";137;1
"Unit";"Zergling";"Larva";137;1
"Unit";"Zergling";"Larva";137;1
"Unit";"Zergling";"Larva";137;1
"Unit";"Zergling";"Larva";137;1
"Unit";"Zergling";"Larva";137;1
"Unit";"Zergling";"Larva";137;1
"Unit";"Zergling";"Larva";137;1
"Unit";"Zergling";"Larva";137;1
"Unit";"Zergling";"Larva";137;1
"Unit";"Zergling";"Larva";137;1
"Unit";"Zergling";"Larva";137;1
"Unit";"Zergling";"Larva";137;1
"Unit";"Zergling";"Larva";137;1
"Unit";"Zergling";"Larva";137;1
"Unit";"Zergling";"Larva";137;1
"Unit";"Zergling";"Larva";137;1
"Unit";"Zergling";"Larva";137;1
"Upgrade";"ZergMeleeWeaponsLevel2";"EvolutionChamber";95;0
"Upgrade";"ZergGroundArmorsLevel2";"EvolutionChamber";95;0
"Unit";"Zergling";"Larva";165;1
"Unit";"Zergling";"Larva";165;1
"Unit";"Zergling";"Larva";167;1
"Unit";"Zergling";"Larva";167;1
"Unit";"Zergling";"Larva";167;1
"Unit";"Zergling";"Larva";167;1
"Unit";"Zergling";"Larva";167;1
"Unit";"Zergling";"Larva";167;1
"Unit";"Zergling";"Larva";167;1
"Unit";"Zergling";"Larva";167;1
"Unit";"Zergling";"Larva";167;1
"Unit";"Zergling";"Larva";167;1
"Unit";"Overlord";"Larva";177;0
"Unit";"Overlord";"Larva";177;0
"Unit";"Overlord";"Larva";177;0
"Building";"CreepTumor";NA;177;0
"Building";"CreepTumor";NA;177;0
"Building";"CreepTumor";NA;177;0
"Building";"Hatchery";NA;117;0
"Building";"CreepTumor";NA;177;0
"Building";"CreepTumor";NA;177;0
"Building";"CreepTumor";NA;177;0
"Building";"Hatchery";NA;131;0
"Building";"CreepTumor";NA;189;0
"Building";"CreepTumor";NA;189;0
"Unit";"Overlord";"Larva";189;0
"Unit";"Zergling";"Larva";189;1
"Unit";"Zergling";"Larva";189;1
"Unit";"Zergling";"Larva";189;1
"Unit";"Zergling";"Larva";189;1
"Unit";"Zergling";"Larva";189;1
"Unit";"Zergling";"Larva";189;1
"Unit";"Zergling";"Larva";189;1
"Unit";"Zergling";"Larva";189;1
"Unit";"Zergling";"Larva";189;1
"Unit";"Zergling";"Larva";189;1
"Unit";"Zergling";"Larva";189;1
"Unit";"Zergling";"Larva";189;1
"Unit";"Zergling";"Larva";189;1
"Unit";"Zergling";"Larva";189;1
"Unit";"Zergling";"Larva";189;1
"Unit";"Zergling";"Larva";189;1
"Unit";"Zergling";"Larva";189;1
"Unit";"Zergling";"Larva";189;1
"Unit";"Zergling";"Larva";189;1
"Unit";"Zergling";"Larva";189;1
"Unit";"Zergling";"Larva";189;1
"Unit";"Zergling";"Larva";189;1
"Unit";"Zergling";"Larva";189;1
"Unit";"Zergling";"Larva";189;1
"Unit";"Zergling";"Larva";189;1
"Unit";"Zergling";"Larva";189;1
"Unit";"Zergling";"Larva";189;1
"Unit";"Zergling";"Larva";189;1
"Unit";"Overlord";"Larva";189;0
"Unit";"Zergling";"Larva";189;1
"Unit";"Zergling";"Larva";189;1
"Unit";"Zergling";"Larva";189;1
"Unit";"Zergling";"Larva";189;1
"Unit";"Zergling";"Larva";189;1
"Unit";"Zergling";"Larva";189;1
"Unit";"Zergling";"Larva";189;1
"Unit";"Zergling";"Larva";189;1
"Unit";"Zergling";"Larva";189;1
"Unit";"Zergling";"Larva";189;1
"Unit";"Zergling";"Larva";189;1
"Unit";"Zergling";"Larva";189;1
"Unit";"Zergling";"Larva";189;1
"Unit";"Zergling";"Larva";189;1
"Building";"CreepTumor";NA;215;0
"Building";"CreepTumor";NA;231;0
"Building";"CreepTumor";NA;231;0
"Building";"CreepTumor";NA;231;0
"Building";"CreepTumor";NA;231;0
"Building";"CreepTumor";NA;231;0
"Building";"CreepTumor";NA;231;0
"Building";"CreepTumor";NA;231;0
"Unit";"Zergling";"Larva";231;1
"Unit";"Zergling";"Larva";231;1
"Unit";"Zergling";"Larva";231;1
"Unit";"Zergling";"Larva";231;1
"Unit";"Zergling";"Larva";231;1
"Unit";"Zergling";"Larva";231;1
"Unit";"Zergling";"Larva";231;1
"Unit";"Zergling";"Larva";231;1
"Unit";"Zergling";"Larva";231;1
"Unit";"Zergling";"Larva";231;1
"Unit";"Zergling";"Larva";231;1
"Unit";"Zergling";"Larva";231;1
"Unit";"Zergling";"Larva";231;1
"Unit";"Zergling";"Larva";231;1
"Unit";"Zergling";"Larva";231;1
"Unit";"Zergling";"Larva";231;1
"Unit";"Zergling";"Larva";231;1
"Unit";"Zergling";"Larva";231;1
"Unit";"Zergling";"Larva";231;1
"Unit";"Zergling";"Larva";231;1
"Unit";"Zergling";"Larva";231;1
"Unit";"Zergling";"Larva";231;1
"Unit";"Zergling";"Larva";231;1
"Unit";"Zergling";"Larva";231;1
"Unit";"Zergling";"Larva";231;1
"Unit";"Zergling";"Larva";231;1
"Unit";"Zergling";"Larva";231;1
"Unit";"Zergling";"Larva";231;1
"Unit";"Zergling";"Larva";231;1
"Unit";"Zergling";"Larva";231;1
"Unit";"Zergling";"Larva";231;1
"Unit";"Zergling";"Larva";231;1
"Unit";"Zergling";"Larva";231;1
"Unit";"Zergling";"Larva";231;1
"Building";"CreepTumor";NA;231;0
"Unit";"Zergling";"Larva";231;1
"Unit";"Zergling";"Larva";231;1
"Unit";"Zergling";"Larva";231;1
"Unit";"Zergling";"Larva";231;1
"Unit";"Zergling";"Larva";231;1
"Unit";"Zergling";"Larva";231;1
"Unit";"Zergling";"Larva";231;1
"Unit";"Zergling";"Larva";231;1
"Unit";"Zergling";"Larva";231;1
"Unit";"Zergling";"Larva";231;1
"Unit";"Zergling";"Larva";231;1
"Unit";"Zergling";"Larva";231;1
"Unit";"Queen";"Hatchery";215;2
"Building";"CreepTumor";NA;269;0
"Building";"CreepTumor";NA;269;0
"Building";"CreepTumor";NA;269;0
"Unit";"Zergling";"Larva";269;1
"Unit";"Zergling";"Larva";269;1
"Unit";"Zergling";"Larva";269;1
"Unit";"Zergling";"Larva";269;1
"Unit";"Zergling";"Larva";269;1
"Unit";"Zergling";"Larva";269;1
"Unit";"Zergling";"Larva";269;1
"Unit";"Zergling";"Larva";269;1
"Unit";"Zergling";"Larva";269;1
"Unit";"Zergling";"Larva";269;1
"Unit";"Zergling";"Larva";269;1
"Unit";"Zergling";"Larva";269;1
"Unit";"Zergling";"Larva";269;1
"Unit";"Zergling";"Larva";269;1
"Unit";"Zergling";"Larva";269;1
"Unit";"Zergling";"Larva";269;1
"Unit";"Zergling";"Larva";269;1
"Unit";"Zergling";"Larva";269;1
"Unit";"Overlord";"Larva";269;0
"Unit";"Overlord";"Larva";269;0
"Building";"CreepTumor";NA;279;0
"Building";"CreepTumor";NA;279;0
"Building";"CreepTumor";NA;279;0
"Building";"CreepTumor";NA;297;0
"Unit";"Overlord";"Larva";297;0
"Unit";"Overlord";"Larva";297;0
"Unit";"Overlord";"Larva";297;0
"Upgrade";"Burrow";"Hatchery";231;0
"Unit";"Zergling";"Larva";297;1
"Unit";"Zergling";"Larva";297;1
"Unit";"Zergling";"Larva";297;1
"Unit";"Zergling";"Larva";297;1
"Unit";"Zergling";"Larva";297;1
"Unit";"Zergling";"Larva";297;1
"Unit";"Zergling";"Larva";297;1
"Unit";"Zergling";"Larva";297;1
"Unit";"Zergling";"Larva";297;1
"Unit";"Zergling";"Larva";297;1
"Unit";"Zergling";"Larva";297;1
"Unit";"Zergling";"Larva";297;1
"Unit";"Zergling";"Larva";297;1
"Unit";"Zergling";"Larva";297;1
"Unit";"Zergling";"Larva";297;1
"Unit";"Zergling";"Larva";297;1
"Unit";"Overlord";"Larva";297;0
"Unit";"Overlord";"Larva";297;0
"Building";"Hatchery";NA;231;0
"Unit";"Zergling";"Larva";313;1
"Unit";"Zergling";"Larva";313;1
"Unit";"Zergling";"Larva";313;1
"Unit";"Zergling";"Larva";313;1
"Unit";"Zergling";"Larva";313;1
"Unit";"Zergling";"Larva";313;1
"Unit";"Zergling";"Larva";313;1
"Unit";"Zergling";"Larva";313;1
"Unit";"Zergling";"Larva";313;1
"Unit";"Zergling";"Larva";313;1
"Unit";"Zergling";"Larva";313;1
"Unit";"Zergling";"Larva";313;1
"Unit";"Zergling";"Larva";313;1
"Unit";"Zergling";"Larva";313;1
"Unit";"Zergling";"Larva";313;1
"Unit";"Zergling";"Larva";313;1
"Unit";"Zergling";"Larva";313;1
"Unit";"Zergling";"Larva";313;1
"Unit";"Zergling";"Larva";313;1
"Unit";"Zergling";"Larva";313;1
"Unit";"Zergling";"Larva";313;1
"Unit";"Zergling";"Larva";313;1
"Unit";"Zergling";"Larva";313;1
"Unit";"Zergling";"Larva";313;1
"Unit";"Zergling";"Larva";313;1
"Unit";"Zergling";"Larva";313;1
"Unit";"Zergling";"Larva";313;1
"Unit";"Zergling";"Larva";313;1
"Unit";"Zergling";"Larva";313;1
"Unit";"Zergling";"Larva";313;1
"Unit";"Zergling";"Larva";313;1
"Unit";"Zergling";"Larva";313;1
"Unit";"Zergling";"Larva";313;1
"Unit";"Zergling";"Larva";313;1
"Unit";"Zergling";"Larva";313;1
"Unit";"Zergling";"Larva";313;1
"Unit";"Zergling";"Larva";313;1
"Unit";"Zergling";"Larva";313;1
"Unit";"Zergling";"Larva";313;1
"Unit";"Zergling";"Larva";313;1
"Unit";"Zergling";"Larva";313;1
"Unit";"Zergling";"Larva";313;1
"Unit";"Zergling";"Larva";313;1
"Unit";"Zergling";"Larva";313;1
"Unit";"Zergling";"Larva";313;1
"Unit";"Zergling";"Larva";313;1
"Unit";"Zergling";"Larva";313;1
"Unit";"Zergling";"Larva";313;1
"Unit";"Zergling";"Larva";313;1
"Unit";"Zergling";"Larva";313;1
"Unit";"Zergling";"Larva";313;1
"Unit";"Zergling";"Larva";313;1
"Unit";"Zergling";"Larva";313;1
"Unit";"Zergling";"Larva";313;1
"Unit";"Zergling";"Larva";313;1
"Unit";"Zergling";"Larva";313;1
"Unit";"Zergling";"Larva";313;1
"Unit";"Zergling";"Larva";313;1
"Unit";"Zergling";"Larva";313;1
"Unit";"Zergling";"Larva";313;1
"Unit";"Zergling";"Larva";313;1
"Unit";"Zergling";"Larva";313;1
"Unit";"Zergling";"Larva";313;1
"Unit";"Zergling";"Larva";313;1
