"type";"unit_name";"on_building";"total_supply";"supply"
"Unit";"Overlord";"Larva";13;0
"Building";"Extractor";NA;18;0
"Unit";"Overlord";"Larva";21;0
"Building";"SpawningPool";NA;19;0
"Building";"Hatchery";NA;17;0
"Unit";"Zergling";"Larva";23;1
"Unit";"Zergling";"Larva";23;1
"Unit";"Zergling";"Larva";23;1
"Unit";"Zergling";"Larva";23;1
"Unit";"Zergling";"Larva";23;1
"Unit";"Zergling";"Larva";23;1
"Unit";"Queen";"Hatchery";23;2
"Unit";"Queen";"Hatchery";23;2
"Unit";"Overlord";"Larva";30;0
"Unit";"Overlord";"Larva";36;0
"Unit";"Queen";"Hatchery";31;2
"Unit";"Queen";"Hatchery";33;2
"Building";"CreepTumorQueen";NA;39;0
"Building";"CreepTumorQueen";NA;42;0
"Building";"CreepTumor";NA;53;0
"Building";"CreepTumor";NA;53;0
"Building";"CreepTumorQueen";NA;54;0
"Unit";"Zergling";"Larva";54;1
"Unit";"Zergling";"Larva";54;1
"Unit";"Overlord";"Larva";54;0
"Unit";"Overlord";"Larva";54;0
"Building";"CreepTumorQueen";NA;54;0
"Building";"Extractor";NA;54;0
"Building";"SporeCrawler";NA;54;0
"Building";"SporeCrawler";NA;54;0
"Building";"RoachWarren";NA;53;0
"Unit";"Overlord";"Larva";54;0
"Building";"CreepTumor";NA;58;0
"Building";"CreepTumorQueen";NA;58;0
"Building";"CreepTumor";NA;58;0
"Building";"CreepTumorQueen";NA;58;0
"Building";"CreepTumor";NA;58;0
"Unit";"Overlord";"Larva";58;0
"Unit";"Roach";"Larva";58;2
"Unit";"Roach";"Larva";58;2
"Unit";"Roach";"Larva";58;2
"Unit";"Roach";"Larva";58;2
"Unit";"Roach";"Larva";58;2
"Unit";"Roach";"Larva";58;2
"Unit";"Roach";"Larva";58;2
"Building";"CreepTumor";NA;61;0
"Building";"CreepTumor";NA;61;0
"Unit";"Roach";"Larva";61;2
"Unit";"Roach";"Larva";61;2
"Unit";"Queen";"Hatchery";58;2
"Unit";"Roach";"Larva";61;2
"Building";"CreepTumor";NA;75;0
"Building";"CreepTumor";NA;83;0
"Building";"Extractor";NA;75;0
"Building";"CreepTumorQueen";NA;84;0
"Building";"CreepTumor";NA;84;0
"Building";"CreepTumor";NA;84;0
"Building";"Hatchery";NA;54;0
"Building";"CreepTumor";NA;84;0
"Building";"CreepTumorQueen";NA;92;0
"Building";"CreepTumorQueen";NA;95;0
"Building";"EvolutionChamber";NA;87;0
"Building";"EvolutionChamber";NA;88;0
"Building";"SporeCrawler";NA;95;0
"Building";"CreepTumor";NA;96;0
"Building";"CreepTumor";NA;98;0
"Building";"CreepTumor";NA;103;0
"Building";"CreepTumor";NA;103;0
"Building";"CreepTumor";NA;103;0
"Building";"CreepTumor";NA;103;0
"Unit";"Overlord";"Larva";103;0
"Unit";"Overlord";"Larva";103;0
"Unit";"Overlord";"Larva";103;0
"Unit";"Overlord";"Larva";103;0
"Unit";"Overlord";"Larva";103;0
"Building";"Extractor";NA;103;0
"Unit";"Zergling";"Larva";103;1
"Unit";"Zergling";"Larva";103;1
"Unit";"Overlord";"Larva";103;0
"Building";"CreepTumor";NA;105;0
"Building";"CreepTumor";NA;105;0
"Building";"CreepTumor";NA;105;0
"Building";"CreepTumor";NA;107;0
"Building";"Hatchery";NA;96;0
"Unit";"Overlord";"Larva";114;0
"Building";"CreepTumor";NA;114;0
"Building";"CreepTumor";NA;117;0
"Building";"Extractor";NA;114;0
"Building";"Extractor";NA;114;0
"Unit";"Zergling";"Larva";123;1
"Unit";"Zergling";"Larva";123;1
"Unit";"Zergling";"Larva";123;1
"Unit";"Zergling";"Larva";123;1
"Unit";"Zergling";"Larva";123;1
"Unit";"Zergling";"Larva";123;1
"Unit";"Zergling";"Larva";123;1
"Unit";"Zergling";"Larva";123;1
"Unit";"Zergling";"Larva";123;1
"Unit";"Zergling";"Larva";123;1
"Unit";"Zergling";"Larva";123;1
"Unit";"Zergling";"Larva";123;1
"Unit";"Zergling";"Larva";123;1
"Unit";"Zergling";"Larva";123;1
"Unit";"Zergling";"Larva";123;1
"Unit";"Zergling";"Larva";123;1
"Unit";"Zergling";"Larva";123;1
"Unit";"Zergling";"Larva";123;1
"Building";"CreepTumor";NA;141;0
"Building";"CreepTumor";NA;141;0
"Unit";"Overlord";"Larva";141;0
"Building";"HydraliskDen";NA;123;0
"Unit";"Queen";"Hatchery";123;2
"Building";"CreepTumor";NA;149;0
"Upgrade";"ZergMissileWeaponsLevel1";"EvolutionChamber";103;0
"Upgrade";"ZergGroundArmorsLevel1";"EvolutionChamber";103;0
"Building";"InfestationPit";NA;123;0
"Building";"CreepTumor";NA;151;0
"Building";"Extractor";NA;151;0
"Building";"Extractor";NA;151;0
"Unit";"Hydralisk";"Larva";153;2
"Unit";"Hydralisk";"Larva";154;2
"Unit";"Hydralisk";"Larva";154;2
"Unit";"Hydralisk";"Larva";154;2
"Unit";"Hydralisk";"Larva";154;2
"Unit";"Hydralisk";"Larva";154;2
"Unit";"Hydralisk";"Larva";154;2
"Unit";"Hydralisk";"Larva";154;2
"Unit";"Hydralisk";"Larva";154;2
"Unit";"Hydralisk";"Larva";154;2
"Unit";"Hydralisk";"Larva";154;2
"Unit";"Hydralisk";"Larva";154;2
"Unit";"Hydralisk";"Larva";159;2
"Unit";"Hydralisk";"Larva";159;2
"Unit";"Hydralisk";"Larva";159;2
"Unit";"Hydralisk";"Larva";159;2
"Unit";"Hydralisk";"Larva";183;2
"Upgrade";"GlialReconstitution";"RoachWarren";151;0
"Unit";"Overlord";"Larva";195;0
"Unit";"Overlord";"Larva";195;0
"Unit";"Overlord";"Larva";195;0
"Unit";"Overlord";"Larva";195;0
"Unit";"Overlord";"Larva";195;0
"Building";"CreepTumor";NA;197;0
"Building";"CreepTumor";NA;197;0
"Upgrade";"EvolveGroovedSpines";"HydraliskDen";159;0
"Building";"CreepTumor";NA;197;0
"Building";"CreepTumor";NA;197;0
"Unit";"Overlord";"Larva";197;0
"Unit";"Overlord";"Larva";197;0
"Unit";"Overlord";"Larva";197;0
"Unit";"Overlord";"Larva";197;0
"Building";"CreepTumor";NA;198;0
"Building";"CreepTumor";NA;198;0
"Unit";"Hydralisk";"Larva";198;2
"Unit";"Hydralisk";"Larva";198;2
"Unit";"Hydralisk";"Larva";198;2
"Unit";"Hydralisk";"Larva";198;2
"Unit";"Hydralisk";"Larva";198;2
"Unit";"Hydralisk";"Larva";198;2
"Unit";"Hydralisk";"Larva";198;2
"Unit";"Hydralisk";"Larva";198;2
"Unit";"Hydralisk";"Larva";198;2
"Unit";"Hydralisk";"Larva";198;2
"Unit";"Hydralisk";"Larva";198;2
"Unit";"Hydralisk";"Larva";198;2
"Unit";"Hydralisk";"Larva";198;2
"Unit";"Hydralisk";"Larva";198;2
"Unit";"Hydralisk";"Larva";198;2
"Unit";"Hydralisk";"Larva";198;2
"Unit";"Hydralisk";"Larva";198;2
"Building";"Extractor";NA;198;0
"Building";"Extractor";NA;198;0
"Building";"CreepTumor";NA;235;0
"Building";"CreepTumor";NA;238;0
"Upgrade";"EvolveMuscularAugments";"HydraliskDen";198;0
"Upgrade";"ZergMissileWeaponsLevel2";"EvolutionChamber";195;0
"Building";"CreepTumor";NA;243;0
"Building";"CreepTumor";NA;243;0
"Unit";"Viper";"Larva";243;3
"Unit";"Viper";"Larva";243;3
"Unit";"Viper";"Larva";243;3
"Unit";"Viper";"Larva";243;3
"Building";"Hatchery";NA;198;0
"Building";"CreepTumorQueen";NA;255;0
"Building";"Spire";NA;198;0
"Upgrade";"ZergGroundArmorsLevel2";"EvolutionChamber";198;0
"Building";"CreepTumor";NA;255;0
"Building";"CreepTumor";NA;255;0
"Building";"Extractor";NA;255;0
"Building";"Extractor";NA;255;0
"Building";"CreepTumorQueen";NA;255;0
"Unit";"Overlord";"Larva";255;0
"Building";"CreepTumorQueen";NA;255;0
"Unit";"Overlord";"Larva";255;0
"Unit";"Hydralisk";"Larva";255;2
"Unit";"Hydralisk";"Larva";255;2
"Unit";"Hydralisk";"Larva";255;2
"Building";"CreepTumor";NA;255;0
"Unit";"Infestor";"Larva";255;2
"Unit";"Infestor";"Larva";255;2
"Unit";"Infestor";"Larva";255;2
"Building";"CreepTumor";NA;267;0
"Building";"Hatchery";NA;255;0
"Building";"CreepTumor";NA;267;0
"Building";"CreepTumor";NA;267;0
"Building";"CreepTumor";NA;267;0
"Building";"CreepTumor";NA;267;0
"Building";"CreepTumor";NA;267;0
"Unit";"Corruptor";"Larva";267;2
"Unit";"Corruptor";"Larva";267;2
"Unit";"Corruptor";"Larva";267;2
"Unit";"Corruptor";"Larva";267;2
"Unit";"Corruptor";"Larva";267;2
"Unit";"Hydralisk";"Larva";267;2
"Unit";"Hydralisk";"Larva";267;2
"Unit";"Hydralisk";"Larva";267;2
"Unit";"Corruptor";"Larva";267;2
"Unit";"Corruptor";"Larva";267;2
"Unit";"Corruptor";"Larva";267;2
"Building";"Spire";NA;267;0
"Unit";"Corruptor";"Larva";267;2
"Building";"SporeCrawler";NA;276;0
"Upgrade";"ZergMissileWeaponsLevel3";"EvolutionChamber";261;0
"Building";"SporeCrawler";NA;276;0
"Building";"SpineCrawler";NA;270;0
"Building";"SpineCrawler";NA;270;0
"Building";"SpineCrawler";NA;274;0
"Unit";"Infestor";"Larva";276;2
"Unit";"Corruptor";"Larva";280;2
"Unit";"Corruptor";"Larva";280;2
"Unit";"Corruptor";"Larva";282;2
"Unit";"Corruptor";"Larva";294;2
"Unit";"Corruptor";"Larva";294;2
"Unit";"Corruptor";"Larva";294;2
"Building";"CreepTumor";NA;302;0
"Building";"CreepTumor";NA;302;0
"Building";"CreepTumor";NA;302;0
"Building";"CreepTumor";NA;302;0
"Unit";"Corruptor";"Larva";294;2
"Upgrade";"ZergGroundArmorsLevel3";"EvolutionChamber";267;0
"Building";"Extractor";NA;314;0
"Building";"Extractor";NA;314;0
"Building";"CreepTumor";NA;316;0
"Building";"CreepTumor";NA;316;0
"Building";"CreepTumor";NA;316;0
"Building";"CreepTumor";NA;319;0
"Unit";"Overlord";"Larva";319;0
"Building";"SpineCrawler";NA;316;0
"Building";"SpineCrawler";NA;316;0
"Building";"SpineCrawler";NA;316;0
"Unit";"Overlord";"Larva";319;0
"Unit";"Overlord";"Larva";319;0
"Building";"UltraliskCavern";NA;316;0
"Building";"Hatchery";NA;314;0
"Upgrade";"ZergMeleeWeaponsLevel1";"EvolutionChamber";314;0
"Unit";"Zergling";"Larva";319;1
"Unit";"Zergling";"Larva";319;1
"Unit";"Ultralisk";"Larva";319;6
"Unit";"Ultralisk";"Larva";319;6
"Unit";"Ultralisk";"Larva";319;6
"Unit";"Ultralisk";"Larva";319;6
"Unit";"Ultralisk";"Larva";319;6
"Unit";"Ultralisk";"Larva";319;6
"Unit";"Ultralisk";"Larva";319;6
"Unit";"Zergling";"Larva";321;1
"Unit";"Zergling";"Larva";321;1
"Unit";"Zergling";"Larva";321;1
"Unit";"Zergling";"Larva";321;1
"Unit";"Zergling";"Larva";321;1
"Unit";"Zergling";"Larva";321;1
"Unit";"Zergling";"Larva";321;1
"Unit";"Zergling";"Larva";321;1
"Unit";"Zergling";"Larva";321;1
"Unit";"Zergling";"Larva";321;1
"Unit";"Zergling";"Larva";321;1
"Unit";"Zergling";"Larva";321;1
"Unit";"Zergling";"Larva";321;1
"Unit";"Zergling";"Larva";321;1
"Unit";"Zergling";"Larva";321;1
"Unit";"Zergling";"Larva";321;1
"Unit";"Zergling";"Larva";321;1
"Unit";"Zergling";"Larva";321;1
"Unit";"Zergling";"Larva";321;1
"Unit";"Zergling";"Larva";321;1
"Unit";"Zergling";"Larva";321;1
"Unit";"Zergling";"Larva";321;1
"Unit";"Zergling";"Larva";321;1
"Unit";"Zergling";"Larva";321;1
"Unit";"Zergling";"Larva";321;1
"Unit";"Zergling";"Larva";321;1
"Unit";"Zergling";"Larva";321;1
"Unit";"Zergling";"Larva";321;1
"Unit";"Zergling";"Larva";321;1
"Unit";"Zergling";"Larva";321;1
"Unit";"Zergling";"Larva";321;1
"Unit";"Zergling";"Larva";321;1
"Unit";"Zergling";"Larva";321;1
"Unit";"Zergling";"Larva";321;1
"Unit";"Zergling";"Larva";321;1
"Unit";"Zergling";"Larva";321;1
"Unit";"Zergling";"Larva";321;1
"Unit";"Zergling";"Larva";321;1
"Unit";"Zergling";"Larva";321;1
"Unit";"Zergling";"Larva";321;1
"Unit";"Zergling";"Larva";321;1
"Unit";"Zergling";"Larva";321;1
"Unit";"Zergling";"Larva";321;1
"Unit";"Zergling";"Larva";321;1
"Unit";"Zergling";"Larva";321;1
"Unit";"Zergling";"Larva";321;1
"Unit";"Zergling";"Larva";321;1
"Unit";"Zergling";"Larva";321;1
"Unit";"Zergling";"Larva";321;1
"Unit";"Zergling";"Larva";321;1
"Unit";"Zergling";"Larva";321;1
"Unit";"Zergling";"Larva";321;1
"Unit";"Zergling";"Larva";321;1
"Unit";"Zergling";"Larva";321;1
"Unit";"Zergling";"Larva";321;1
"Unit";"Zergling";"Larva";321;1
"Unit";"Zergling";"Larva";321;1
"Unit";"Zergling";"Larva";321;1
"Unit";"Zergling";"Larva";321;1
"Unit";"Zergling";"Larva";321;1
"Unit";"Zergling";"Larva";321;1
"Unit";"Zergling";"Larva";321;1
"Unit";"Zergling";"Larva";321;1
"Unit";"Zergling";"Larva";321;1
"Unit";"Zergling";"Larva";321;1
"Unit";"Zergling";"Larva";321;1
"Unit";"Zergling";"Larva";321;1
"Unit";"Zergling";"Larva";321;1
"Unit";"Zergling";"Larva";321;1
"Unit";"Zergling";"Larva";321;1
"Building";"CreepTumor";NA;363;0
"Building";"CreepTumor";NA;363;0
"Building";"CreepTumor";NA;363;0
"Building";"CreepTumor";NA;363;0
"Unit";"Ultralisk";"Larva";321;6
"Unit";"Ultralisk";"Larva";321;6
"Building";"BanelingNest";NA;321;0
"Upgrade";"ChitinousPlating";"UltraliskCavern";321;0
"Building";"Extractor";NA;448;0
"Building";"Extractor";NA;448;0
"Unit";"Baneling";"Zergling";448;0
"Unit";"Baneling";"Zergling";448;0
"Unit";"Baneling";"Zergling";448;0
"Unit";"Baneling";"Zergling";448;0
"Unit";"Baneling";"Zergling";448;0
"Unit";"Baneling";"Zergling";448;0
"Unit";"Baneling";"Zergling";448;0
"Unit";"Baneling";"Zergling";448;0
"Unit";"Baneling";"Zergling";448;0
"Unit";"Baneling";"Zergling";448;0
"Unit";"Baneling";"Zergling";448;0
"Building";"CreepTumor";NA;448;0
"Building";"InfestationPit";NA;448;0
"Upgrade";"ZergMeleeWeaponsLevel2";"EvolutionChamber";363;0
"Building";"CreepTumor";NA;460;0
"Building";"CreepTumor";NA;460;0
"Building";"CreepTumor";NA;460;0
"Unit";"Infestor";"Larva";460;2
"Unit";"Infestor";"Larva";460;2
"Unit";"Infestor";"Larva";460;2
"Unit";"Corruptor";"Larva";460;2
"Unit";"Infestor";"Larva";460;2
"Unit";"Infestor";"Larva";460;2
"Unit";"Corruptor";"Larva";460;2
"Unit";"Corruptor";"Larva";460;2
"Unit";"Infestor";"Larva";460;2
"Unit";"Corruptor";"Larva";460;2
"Unit";"Corruptor";"Larva";460;2
"Unit";"Corruptor";"Larva";460;2
"Unit";"Corruptor";"Larva";460;2
"Unit";"Corruptor";"Larva";460;2
"Unit";"Corruptor";"Larva";460;2
"Building";"SporeCrawler";NA;460;0
"Building";"SpineCrawler";NA;460;0
"Building";"SpineCrawler";NA;460;0
"Building";"SpineCrawler";NA;460;0
"Building";"SpineCrawler";NA;460;0
"Unit";"Infestor";"Larva";460;2
"Building";"CreepTumorQueen";NA;495;0
"Building";"CreepTumorQueen";NA;495;0
"Building";"CreepTumorQueen";NA;495;0
"Building";"CreepTumorQueen";NA;495;0
"Building";"CreepTumorQueen";NA;495;0
"Building";"SporeCrawler";NA;495;0
"Unit";"Overlord";"Larva";495;0
"Unit";"Overlord";"Larva";495;0
"Building";"CreepTumor";NA;497;0
"Building";"SpineCrawler";NA;495;0
"Building";"Extractor";NA;497;0
"Building";"Extractor";NA;497;0
"Building";"Extractor";NA;497;0
"Building";"Extractor";NA;497;0
"Unit";"Corruptor";"Larva";497;2
"Unit";"Corruptor";"Larva";497;2
"Unit";"Corruptor";"Larva";497;2
"Unit";"Corruptor";"Larva";497;2
"Unit";"Corruptor";"Larva";497;2
"Building";"CreepTumor";NA;497;0
"Building";"CreepTumor";NA;497;0
"Building";"CreepTumor";NA;497;0
"Building";"CreepTumor";NA;497;0
"Building";"CreepTumor";NA;497;0
"Building";"CreepTumor";NA;497;0
"Unit";"Infestor";"Larva";497;2
"Unit";"Infestor";"Larva";497;2
"Unit";"Infestor";"Larva";497;2
"Unit";"Infestor";"Larva";497;2
"Unit";"Infestor";"Larva";497;2
"Building";"Hatchery";NA;497;0
"Unit";"Corruptor";"Larva";497;2
"Upgrade";"ZergMeleeWeaponsLevel3";"EvolutionChamber";495;0
"Unit";"Corruptor";"Larva";497;2
"Unit";"Corruptor";"Larva";497;2
"Unit";"Corruptor";"Larva";497;2
"Unit";"Corruptor";"Larva";497;2
"Unit";"Corruptor";"Larva";497;2
"Unit";"Corruptor";"Larva";497;2
"Unit";"Corruptor";"Larva";497;2
"Unit";"Corruptor";"Larva";497;2
"Unit";"Corruptor";"Larva";497;2
"Unit";"Corruptor";"Larva";497;2
"Building";"Hatchery";NA;497;0
"Unit";"Infestor";"Larva";507;2
