"type";"unit_name";"on_building";"total_supply";"supply"
"Unit";"Overlord";"Larva";13;0
"Building";"Extractor";NA;17;0
"Unit";"Overlord";"Larva";21;0
"Building";"SpawningPool";NA;19;0
"Building";"Hatchery";NA;17;0
"Unit";"Zergling";"Larva";22;1
"Unit";"Zergling";"Larva";22;1
"Unit";"Zergling";"Larva";23;1
"Unit";"Zergling";"Larva";23;1
"Unit";"Queen";"Hatchery";23;2
"Unit";"Queen";"Hatchery";23;2
"Unit";"Overlord";"Larva";36;0
"Unit";"Queen";"Hatchery";35;2
"Building";"CreepTumorQueen";NA;39;0
"Unit";"Overlord";"Larva";39;0
"Building";"CreepTumor";NA;50;0
"Building";"CreepTumorQueen";NA;50;0
"Unit";"Overlord";"Larva";50;0
"Building";"RoachWarren";NA;46;0
"Building";"Hatchery";NA;38;0
"Unit";"Queen";"Hatchery";50;2
"Unit";"Zergling";"Larva";51;1
"Unit";"Zergling";"Larva";51;1
"Unit";"Zergling";"Larva";51;1
"Unit";"Zergling";"Larva";51;1
"Unit";"Zergling";"Larva";51;1
"Unit";"Zergling";"Larva";51;1
"Building";"CreepTumor";NA;51;0
"Building";"Extractor";NA;50;0
"Building";"CreepTumor";NA;51;0
"Unit";"Overlord";"Larva";51;0
"Unit";"Overlord";"Larva";52;0
"Unit";"Roach";"Larva";57;2
"Unit";"Roach";"Larva";57;2
"Unit";"Roach";"Larva";57;2
"Unit";"Roach";"Larva";63;2
"Unit";"Roach";"Larva";63;2
"Building";"CreepTumor";NA;63;0
"Building";"CreepTumor";NA;63;0
"Unit";"Overlord";"Larva";69;0
"Building";"CreepTumorQueen";NA;79;0
"Building";"SporeCrawler";NA;79;0
"Building";"SporeCrawler";NA;79;0
"Unit";"Zergling";"Larva";79;1
"Unit";"Zergling";"Larva";79;1
"Unit";"Zergling";"Larva";79;1
"Unit";"Zergling";"Larva";79;1
"Unit";"Zergling";"Larva";79;1
"Unit";"Zergling";"Larva";79;1
"Unit";"Zergling";"Larva";79;1
"Unit";"Zergling";"Larva";79;1
"Building";"SporeCrawler";NA;79;0
"Building";"CreepTumor";NA;92;0
"Building";"CreepTumor";NA;92;0
"Building";"CreepTumor";NA;99;0
"Unit";"Queen";"Hatchery";83;2
"Building";"CreepTumor";NA;101;0
"Building";"CreepTumorQueen";NA;101;0
"Unit";"Overlord";"Larva";101;0
"Unit";"Overlord";"Larva";101;0
"Building";"CreepTumor";NA;106;0
"Building";"EvolutionChamber";NA;101;0
"Building";"EvolutionChamber";NA;101;0
"Building";"Extractor";NA;103;0
"Building";"Extractor";NA;103;0
"Building";"CreepTumor";NA;109;0
"Building";"BanelingNest";NA;101;0
"Unit";"Zergling";"Larva";109;1
"Unit";"Zergling";"Larva";109;1
"Unit";"Zergling";"Larva";109;1
"Unit";"Zergling";"Larva";109;1
"Unit";"Zergling";"Larva";109;1
"Unit";"Zergling";"Larva";109;1
"Unit";"Zergling";"Larva";109;1
"Unit";"Zergling";"Larva";109;1
"Unit";"Zergling";"Larva";109;1
"Unit";"Zergling";"Larva";109;1
"Building";"Extractor";NA;109;0
"Unit";"Queen";"Hatchery";107;2
"Unit";"Zergling";"Larva";115;1
"Unit";"Zergling";"Larva";115;1
"Unit";"Zergling";"Larva";115;1
"Unit";"Zergling";"Larva";115;1
"Unit";"Overlord";"Larva";115;0
"Unit";"Zergling";"Larva";115;1
"Unit";"Zergling";"Larva";115;1
"Unit";"Overlord";"Larva";115;0
"Building";"CreepTumor";NA;130;0
"Building";"CreepTumor";NA;130;0
"Building";"CreepTumor";NA;130;0
"Building";"Extractor";NA;125;0
"Unit";"Zergling";"Larva";130;1
"Unit";"Zergling";"Larva";130;1
"Unit";"Zergling";"Larva";130;1
"Unit";"Zergling";"Larva";130;1
"Building";"Hatchery";NA;101;0
"Unit";"Baneling";"Zergling";137;0
"Unit";"Baneling";"Zergling";137;0
"Unit";"Baneling";"Zergling";137;0
"Unit";"Baneling";"Zergling";138;0
"Unit";"Baneling";"Zergling";139;0
"Unit";"Baneling";"Zergling";139;0
"Unit";"Baneling";"Zergling";139;0
"Unit";"Zergling";"Larva";139;1
"Unit";"Zergling";"Larva";139;1
"Unit";"Zergling";"Larva";139;1
"Unit";"Zergling";"Larva";139;1
"Unit";"Overlord";"Larva";144;0
"Unit";"Zergling";"Larva";144;1
"Unit";"Zergling";"Larva";144;1
"Unit";"Zergling";"Larva";144;1
"Unit";"Zergling";"Larva";144;1
"Unit";"Overlord";"Larva";144;0
"Unit";"Zergling";"Larva";144;1
"Unit";"Zergling";"Larva";144;1
"Unit";"Zergling";"Larva";144;1
"Unit";"Zergling";"Larva";144;1
"Unit";"Zergling";"Larva";144;1
"Unit";"Zergling";"Larva";144;1
"Unit";"Queen";"Hatchery";140;2
"Unit";"Baneling";"Zergling";150;0
"Unit";"Baneling";"Zergling";151;0
"Unit";"Baneling";"Zergling";151;0
"Unit";"Baneling";"Zergling";151;0
"Unit";"Zergling";"Larva";148;1
"Unit";"Zergling";"Larva";148;1
"Unit";"Zergling";"Larva";148;1
"Unit";"Zergling";"Larva";148;1
"Unit";"Zergling";"Larva";148;1
"Unit";"Zergling";"Larva";148;1
"Building";"CreepTumor";NA;161;0
"Building";"CreepTumor";NA;163;0
"Unit";"Overlord";"Larva";161;0
"Building";"Spire";NA;125;0
"Unit";"Overlord";"Larva";163;0
"Building";"CreepTumor";NA;171;0
"Building";"CreepTumor";NA;171;0
"Building";"Extractor";NA;171;0
"Building";"CreepTumor";NA;171;0
"Building";"Extractor";NA;171;0
"Building";"CreepTumorQueen";NA;176;0
"Unit";"Mutalisk";"Larva";171;2
"Unit";"Mutalisk";"Larva";171;2
"Unit";"Mutalisk";"Larva";171;2
"Unit";"Mutalisk";"Larva";171;2
"Unit";"Mutalisk";"Larva";171;2
"Unit";"Mutalisk";"Larva";171;2
"Unit";"Mutalisk";"Larva";171;2
"Upgrade";"ZergGroundArmorsLevel1";"EvolutionChamber";140;0
"Upgrade";"ZergMeleeWeaponsLevel1";"EvolutionChamber";140;0
"Unit";"Mutalisk";"Larva";171;2
"Unit";"Baneling";"Zergling";179;0
"Unit";"Baneling";"Zergling";179;0
"Unit";"Baneling";"Zergling";179;0
"Unit";"Baneling";"Zergling";179;0
"Unit";"Baneling";"Zergling";179;0
"Unit";"Baneling";"Zergling";180;0
"Unit";"Baneling";"Zergling";180;0
"Unit";"Baneling";"Zergling";180;0
"Unit";"Baneling";"Zergling";180;0
"Unit";"Baneling";"Zergling";181;0
"Unit";"Baneling";"Zergling";181;0
"Unit";"Baneling";"Zergling";181;0
"Unit";"Zergling";"Larva";182;1
"Unit";"Zergling";"Larva";182;1
"Unit";"Zergling";"Larva";182;1
"Unit";"Zergling";"Larva";182;1
"Unit";"Zergling";"Larva";182;1
"Unit";"Zergling";"Larva";182;1
"Unit";"Zergling";"Larva";182;1
"Unit";"Zergling";"Larva";182;1
"Unit";"Zergling";"Larva";182;1
"Unit";"Zergling";"Larva";182;1
"Unit";"Zergling";"Larva";182;1
"Unit";"Zergling";"Larva";182;1
"Unit";"Zergling";"Larva";182;1
"Unit";"Zergling";"Larva";182;1
"Unit";"Baneling";"Zergling";198;0
"Unit";"Baneling";"Zergling";198;0
"Unit";"Baneling";"Zergling";198;0
"Unit";"Baneling";"Zergling";198;0
"Building";"Extractor";NA;182;0
"Building";"Extractor";NA;198;0
"Unit";"Baneling";"Zergling";198;0
"Unit";"Baneling";"Zergling";198;0
"Unit";"Baneling";"Zergling";198;0
"Unit";"Baneling";"Zergling";198;0
"Unit";"Zergling";"Larva";198;1
"Unit";"Zergling";"Larva";198;1
"Unit";"Zergling";"Larva";198;1
"Unit";"Zergling";"Larva";198;1
"Unit";"Zergling";"Larva";198;1
"Unit";"Zergling";"Larva";198;1
"Unit";"Zergling";"Larva";198;1
"Unit";"Zergling";"Larva";198;1
"Unit";"Zergling";"Larva";198;1
"Unit";"Zergling";"Larva";198;1
"Unit";"Zergling";"Larva";198;1
"Unit";"Zergling";"Larva";198;1
"Unit";"Overlord";"Larva";200;0
"Unit";"Overlord";"Larva";200;0
"Unit";"Overlord";"Larva";212;0
"Unit";"Overlord";"Larva";212;0
"Unit";"Overlord";"Larva";212;0
"Unit";"Zergling";"Larva";212;1
"Unit";"Zergling";"Larva";212;1
"Unit";"Mutalisk";"Larva";212;2
"Unit";"Mutalisk";"Larva";212;2
"Unit";"Zergling";"Larva";224;1
"Unit";"Zergling";"Larva";224;1
"Unit";"Zergling";"Larva";224;1
"Unit";"Zergling";"Larva";224;1
"Unit";"Zergling";"Larva";224;1
"Unit";"Zergling";"Larva";224;1
"Unit";"Zergling";"Larva";224;1
"Unit";"Zergling";"Larva";224;1
"Unit";"Zergling";"Larva";224;1
"Unit";"Zergling";"Larva";224;1
"Unit";"Zergling";"Larva";224;1
"Unit";"Zergling";"Larva";224;1
"Unit";"Zergling";"Larva";224;1
"Unit";"Zergling";"Larva";224;1
"Unit";"Zergling";"Larva";224;1
"Unit";"Zergling";"Larva";224;1
"Unit";"Zergling";"Larva";224;1
"Unit";"Zergling";"Larva";224;1
"Unit";"Zergling";"Larva";224;1
"Unit";"Zergling";"Larva";224;1
"Unit";"Zergling";"Larva";224;1
"Unit";"Zergling";"Larva";224;1
"Unit";"Baneling";"Zergling";226;0
"Unit";"Baneling";"Zergling";226;0
"Unit";"Baneling";"Zergling";226;0
"Unit";"Zergling";"Larva";226;1
"Unit";"Zergling";"Larva";226;1
"Unit";"Zergling";"Larva";226;1
"Unit";"Zergling";"Larva";226;1
"Unit";"Mutalisk";"Larva";226;2
"Unit";"Mutalisk";"Larva";226;2
"Unit";"Mutalisk";"Larva";226;2
"Building";"Hatchery";NA;196;0
"Unit";"Mutalisk";"Larva";252;2
"Unit";"Mutalisk";"Larva";252;2
"Unit";"Overlord";"Larva";260;0
"Unit";"Overlord";"Larva";262;0
"Unit";"Zergling";"Larva";262;1
"Unit";"Zergling";"Larva";262;1
"Unit";"Zergling";"Larva";262;1
"Unit";"Zergling";"Larva";262;1
"Unit";"Zergling";"Larva";262;1
"Unit";"Zergling";"Larva";262;1
"Unit";"Zergling";"Larva";262;1
"Unit";"Zergling";"Larva";262;1
"Unit";"Zergling";"Larva";262;1
"Unit";"Zergling";"Larva";262;1
"Unit";"Zergling";"Larva";262;1
"Unit";"Zergling";"Larva";262;1
"Unit";"Zergling";"Larva";262;1
"Unit";"Zergling";"Larva";262;1
"Unit";"Mutalisk";"Larva";256;2
"Unit";"Mutalisk";"Larva";256;2
"Unit";"Zergling";"Larva";262;1
"Unit";"Zergling";"Larva";262;1
"Unit";"Zergling";"Larva";262;1
"Unit";"Zergling";"Larva";262;1
"Unit";"Zergling";"Larva";262;1
"Unit";"Zergling";"Larva";262;1
"Unit";"Zergling";"Larva";262;1
"Unit";"Zergling";"Larva";262;1
"Unit";"Zergling";"Larva";269;1
"Unit";"Zergling";"Larva";269;1
"Unit";"Zergling";"Larva";269;1
"Unit";"Zergling";"Larva";269;1
"Unit";"Zergling";"Larva";269;1
"Unit";"Zergling";"Larva";269;1
"Unit";"Zergling";"Larva";269;1
"Unit";"Zergling";"Larva";269;1
"Unit";"Zergling";"Larva";269;1
"Unit";"Zergling";"Larva";269;1
"Unit";"Zergling";"Larva";295;1
"Unit";"Zergling";"Larva";295;1
"Unit";"Zergling";"Larva";295;1
"Unit";"Zergling";"Larva";295;1
"Unit";"Zergling";"Larva";295;1
"Unit";"Zergling";"Larva";295;1
"Unit";"Zergling";"Larva";295;1
"Unit";"Zergling";"Larva";295;1
"Unit";"Zergling";"Larva";295;1
"Unit";"Zergling";"Larva";295;1
"Unit";"Zergling";"Larva";318;1
"Unit";"Zergling";"Larva";318;1
"Unit";"Zergling";"Larva";318;1
"Unit";"Zergling";"Larva";318;1
"Unit";"Zergling";"Larva";318;1
"Unit";"Zergling";"Larva";318;1
"Unit";"Zergling";"Larva";318;1
"Unit";"Zergling";"Larva";318;1
"Unit";"Zergling";"Larva";318;1
"Unit";"Zergling";"Larva";318;1
"Unit";"Zergling";"Larva";318;1
"Unit";"Zergling";"Larva";318;1
"Unit";"Zergling";"Larva";318;1
"Unit";"Zergling";"Larva";318;1
"Unit";"Zergling";"Larva";318;1
"Unit";"Zergling";"Larva";318;1
"Unit";"Zergling";"Larva";318;1
"Unit";"Zergling";"Larva";318;1
"Unit";"Zergling";"Larva";318;1
"Unit";"Zergling";"Larva";318;1
"Unit";"Zergling";"Larva";318;1
"Unit";"Zergling";"Larva";318;1
"Unit";"Baneling";"Zergling";318;0
"Unit";"Baneling";"Zergling";318;0
"Unit";"Baneling";"Zergling";318;0
"Unit";"Baneling";"Zergling";318;0
"Unit";"Baneling";"Zergling";318;0
"Unit";"Baneling";"Zergling";318;0
"Unit";"Baneling";"Zergling";318;0
"Unit";"Baneling";"Zergling";318;0
"Unit";"Baneling";"Zergling";318;0
"Unit";"Baneling";"Zergling";318;0
"Building";"CreepTumorQueen";NA;318;0
"Building";"CreepTumor";NA;318;0
"Unit";"Baneling";"Zergling";340;0
"Unit";"Baneling";"Zergling";341;0
"Unit";"Baneling";"Zergling";341;0
"Unit";"Baneling";"Zergling";342;0
"Unit";"Baneling";"Zergling";342;0
"Unit";"Baneling";"Zergling";343;0
"Unit";"Baneling";"Zergling";343;0
"Unit";"Baneling";"Zergling";343;0
"Unit";"Baneling";"Zergling";343;0
"Unit";"Baneling";"Zergling";343;0
"Unit";"Baneling";"Zergling";344;0
"Unit";"Baneling";"Zergling";344;0
"Unit";"Baneling";"Zergling";344;0
"Unit";"Baneling";"Zergling";344;0
"Unit";"Baneling";"Zergling";344;0
"Unit";"Baneling";"Zergling";344;0
"Unit";"Baneling";"Zergling";344;0
"Unit";"Baneling";"Zergling";344;0
"Unit";"Baneling";"Zergling";344;0
"Unit";"Baneling";"Zergling";344;0
"Unit";"Baneling";"Zergling";344;0
"Unit";"Baneling";"Zergling";344;0
"Unit";"Zergling";"Larva";340;1
"Unit";"Zergling";"Larva";340;1
"Unit";"Baneling";"Zergling";344;0
"Unit";"Baneling";"Zergling";344;0
"Unit";"Baneling";"Zergling";344;0
"Unit";"Zergling";"Larva";340;1
"Unit";"Zergling";"Larva";340;1
"Unit";"Zergling";"Larva";340;1
"Unit";"Zergling";"Larva";340;1
"Unit";"Zergling";"Larva";340;1
"Unit";"Zergling";"Larva";340;1
"Unit";"Zergling";"Larva";340;1
"Unit";"Zergling";"Larva";340;1
"Unit";"Zergling";"Larva";340;1
"Unit";"Zergling";"Larva";340;1
"Unit";"Zergling";"Larva";340;1
"Unit";"Zergling";"Larva";340;1
"Unit";"Zergling";"Larva";340;1
"Unit";"Zergling";"Larva";340;1
"Unit";"Zergling";"Larva";340;1
"Unit";"Zergling";"Larva";340;1
"Unit";"Zergling";"Larva";344;1
"Unit";"Zergling";"Larva";344;1
"Unit";"Zergling";"Larva";344;1
"Unit";"Zergling";"Larva";344;1
"Unit";"Zergling";"Larva";344;1
"Unit";"Zergling";"Larva";344;1
"Unit";"Zergling";"Larva";344;1
"Unit";"Zergling";"Larva";344;1
"Unit";"Zergling";"Larva";344;1
"Unit";"Zergling";"Larva";344;1
"Unit";"Mutalisk";"Larva";344;2
"Unit";"Mutalisk";"Larva";344;2
"Unit";"Mutalisk";"Larva";344;2
"Upgrade";"ZergGroundArmorsLevel2";"EvolutionChamber";262;0
"Unit";"Zergling";"Larva";372;1
"Unit";"Zergling";"Larva";372;1
"Unit";"Zergling";"Larva";372;1
"Unit";"Zergling";"Larva";372;1
"Unit";"Zergling";"Larva";372;1
"Unit";"Zergling";"Larva";372;1
"Unit";"Zergling";"Larva";372;1
"Unit";"Zergling";"Larva";372;1
"Unit";"Zergling";"Larva";372;1
"Unit";"Zergling";"Larva";372;1
"Unit";"Zergling";"Larva";372;1
"Unit";"Zergling";"Larva";372;1
"Unit";"Zergling";"Larva";372;1
"Unit";"Zergling";"Larva";372;1
"Unit";"Zergling";"Larva";372;1
"Unit";"Zergling";"Larva";372;1
"Unit";"Zergling";"Larva";372;1
"Unit";"Zergling";"Larva";372;1
"Unit";"Zergling";"Larva";372;1
"Unit";"Zergling";"Larva";372;1
"Unit";"Zergling";"Larva";372;1
"Unit";"Zergling";"Larva";372;1
"Unit";"Zergling";"Larva";372;1
"Unit";"Zergling";"Larva";372;1
"Unit";"Zergling";"Larva";372;1
"Unit";"Zergling";"Larva";372;1
"Unit";"Zergling";"Larva";372;1
"Unit";"Zergling";"Larva";372;1
"Unit";"Zergling";"Larva";372;1
"Unit";"Zergling";"Larva";372;1
"Unit";"Zergling";"Larva";372;1
"Unit";"Zergling";"Larva";372;1
"Unit";"Zergling";"Larva";372;1
"Unit";"Zergling";"Larva";372;1
"Upgrade";"Burrow";"Hatchery";344;0
"Unit";"Baneling";"Zergling";412;0
"Unit";"Baneling";"Zergling";412;0
"Unit";"Baneling";"Zergling";412;0
"Unit";"Zergling";"Larva";412;1
"Unit";"Zergling";"Larva";412;1
"Unit";"Zergling";"Larva";412;1
"Unit";"Zergling";"Larva";412;1
"Unit";"Zergling";"Larva";412;1
"Unit";"Zergling";"Larva";412;1
"Unit";"Zergling";"Larva";412;1
"Unit";"Zergling";"Larva";412;1
"Unit";"Zergling";"Larva";412;1
"Unit";"Zergling";"Larva";412;1
"Unit";"Zergling";"Larva";412;1
"Unit";"Zergling";"Larva";412;1
"Unit";"Zergling";"Larva";412;1
"Unit";"Zergling";"Larva";412;1
"Unit";"Zergling";"Larva";412;1
"Unit";"Zergling";"Larva";412;1
"Unit";"Zergling";"Larva";412;1
"Unit";"Zergling";"Larva";412;1
"Unit";"Zergling";"Larva";412;1
"Unit";"Zergling";"Larva";412;1
"Unit";"Zergling";"Larva";412;1
"Unit";"Zergling";"Larva";412;1
"Unit";"Zergling";"Larva";412;1
"Unit";"Zergling";"Larva";412;1
"Unit";"Zergling";"Larva";412;1
"Unit";"Zergling";"Larva";412;1
"Unit";"Zergling";"Larva";412;1
"Unit";"Zergling";"Larva";412;1
"Building";"InfestationPit";NA;378;0
"Unit";"Overlord";"Larva";412;0
"Unit";"Overlord";"Larva";412;0
"Building";"Extractor";NA;441;0
"Building";"Extractor";NA;441;0
"Upgrade";"ZergMeleeWeaponsLevel2";"EvolutionChamber";341;0
"Unit";"Baneling";"Zergling";441;0
"Unit";"Baneling";"Zergling";441;0
"Unit";"Baneling";"Zergling";441;0
"Unit";"Baneling";"Zergling";441;0
"Unit";"Baneling";"Zergling";441;0
"Unit";"Baneling";"Zergling";441;0
"Unit";"Baneling";"Zergling";441;0
"Unit";"Baneling";"Zergling";441;0
"Unit";"Baneling";"Zergling";441;0
"Unit";"Baneling";"Zergling";441;0
"Unit";"Baneling";"Zergling";441;0
"Unit";"Baneling";"Zergling";441;0
"Unit";"Baneling";"Zergling";441;0
"Unit";"Baneling";"Zergling";441;0
"Unit";"Baneling";"Zergling";441;0
"Unit";"Baneling";"Zergling";441;0
"Unit";"Baneling";"Zergling";441;0
"Unit";"Baneling";"Zergling";441;0
"Unit";"Baneling";"Zergling";441;0
"Unit";"Baneling";"Zergling";441;0
"Unit";"Baneling";"Zergling";441;0
"Unit";"Baneling";"Zergling";441;0
"Unit";"Baneling";"Zergling";441;0
"Unit";"Baneling";"Zergling";441;0
"Unit";"Baneling";"Zergling";441;0
"Unit";"Baneling";"Zergling";441;0
"Unit";"Baneling";"Zergling";441;0
"Unit";"Baneling";"Zergling";441;0
"Unit";"Mutalisk";"Larva";441;2
"Unit";"Zergling";"Larva";441;1
"Unit";"Zergling";"Larva";441;1
"Unit";"Zergling";"Larva";441;1
"Unit";"Zergling";"Larva";441;1
"Unit";"Zergling";"Larva";441;1
"Unit";"Zergling";"Larva";441;1
"Unit";"Zergling";"Larva";441;1
"Unit";"Zergling";"Larva";441;1
"Unit";"Zergling";"Larva";441;1
"Unit";"Zergling";"Larva";441;1
"Unit";"Zergling";"Larva";441;1
"Unit";"Zergling";"Larva";441;1
"Unit";"Zergling";"Larva";441;1
"Unit";"Zergling";"Larva";441;1
"Unit";"Zergling";"Larva";441;1
"Unit";"Zergling";"Larva";441;1
"Unit";"Zergling";"Larva";441;1
"Unit";"Zergling";"Larva";441;1
"Unit";"Zergling";"Larva";441;1
"Unit";"Zergling";"Larva";441;1
"Unit";"Zergling";"Larva";441;1
"Unit";"Zergling";"Larva";441;1
"Unit";"Zergling";"Larva";441;1
"Unit";"Zergling";"Larva";441;1
"Unit";"Zergling";"Larva";441;1
"Unit";"Zergling";"Larva";441;1
"Unit";"Zergling";"Larva";441;1
"Unit";"Zergling";"Larva";441;1
"Unit";"Zergling";"Larva";441;1
"Unit";"Zergling";"Larva";441;1
"Unit";"Zergling";"Larva";441;1
"Unit";"Zergling";"Larva";441;1
"Unit";"Zergling";"Larva";441;1
"Unit";"Zergling";"Larva";441;1
"Unit";"Zergling";"Larva";441;1
"Unit";"Zergling";"Larva";441;1
"Unit";"Zergling";"Larva";441;1
"Unit";"Zergling";"Larva";441;1
"Unit";"Zergling";"Larva";441;1
"Unit";"Zergling";"Larva";441;1
"Unit";"Zergling";"Larva";441;1
"Unit";"Zergling";"Larva";441;1
"Unit";"Zergling";"Larva";441;1
"Unit";"Zergling";"Larva";441;1
"Unit";"Zergling";"Larva";443;1
"Unit";"Zergling";"Larva";443;1
"Unit";"Zergling";"Larva";443;1
"Unit";"Zergling";"Larva";443;1
"Unit";"Zergling";"Larva";443;1
"Unit";"Zergling";"Larva";443;1
"Unit";"Zergling";"Larva";443;1
"Unit";"Zergling";"Larva";443;1
"Building";"CreepTumor";NA;445;0
"Unit";"Zergling";"Larva";443;1
"Unit";"Zergling";"Larva";443;1
"Building";"CreepTumor";NA;457;0
"Unit";"Zergling";"Larva";443;1
"Unit";"Zergling";"Larva";443;1
"Unit";"Zergling";"Larva";443;1
"Unit";"Zergling";"Larva";443;1
"Unit";"Zergling";"Larva";443;1
"Unit";"Zergling";"Larva";443;1
"Unit";"Zergling";"Larva";443;1
"Unit";"Zergling";"Larva";443;1
"Building";"Hatchery";NA;441;0
"Unit";"Zergling";"Larva";495;1
"Unit";"Zergling";"Larva";495;1
"Unit";"Zergling";"Larva";495;1
"Unit";"Zergling";"Larva";495;1
"Unit";"Zergling";"Larva";495;1
"Unit";"Zergling";"Larva";495;1
"Unit";"Zergling";"Larva";495;1
"Unit";"Zergling";"Larva";495;1
"Unit";"Zergling";"Larva";495;1
"Unit";"Zergling";"Larva";495;1
"Unit";"Zergling";"Larva";495;1
"Unit";"Zergling";"Larva";495;1
"Unit";"Zergling";"Larva";495;1
"Unit";"Zergling";"Larva";495;1
"Unit";"Zergling";"Larva";505;1
"Unit";"Zergling";"Larva";505;1
"Unit";"Zergling";"Larva";505;1
"Unit";"Zergling";"Larva";505;1
"Unit";"Zergling";"Larva";505;1
"Unit";"Zergling";"Larva";505;1
"Unit";"Zergling";"Larva";505;1
"Unit";"Zergling";"Larva";505;1
"Unit";"Zergling";"Larva";505;1
"Unit";"Zergling";"Larva";505;1
"Unit";"Zergling";"Larva";505;1
"Unit";"Zergling";"Larva";505;1
"Unit";"Zergling";"Larva";505;1
"Unit";"Zergling";"Larva";505;1
"Unit";"Zergling";"Larva";505;1
"Unit";"Zergling";"Larva";505;1
"Unit";"Zergling";"Larva";505;1
"Unit";"Zergling";"Larva";505;1
"Unit";"Zergling";"Larva";505;1
"Unit";"Zergling";"Larva";505;1
"Unit";"Zergling";"Larva";505;1
"Unit";"Zergling";"Larva";505;1
"Unit";"Zergling";"Larva";505;1
"Unit";"Zergling";"Larva";505;1
"Unit";"Zergling";"Larva";505;1
"Unit";"Zergling";"Larva";505;1
"Unit";"Zergling";"Larva";505;1
"Unit";"Zergling";"Larva";505;1
"Unit";"Zergling";"Larva";505;1
"Unit";"Zergling";"Larva";505;1
"Unit";"Zergling";"Larva";505;1
"Unit";"Zergling";"Larva";505;1
"Unit";"Zergling";"Larva";519;1
"Unit";"Zergling";"Larva";519;1
"Unit";"Zergling";"Larva";519;1
"Unit";"Zergling";"Larva";519;1
"Unit";"Zergling";"Larva";556;1
"Unit";"Zergling";"Larva";556;1
"Unit";"Mutalisk";"Larva";556;2
"Unit";"Mutalisk";"Larva";556;2
"Unit";"Mutalisk";"Larva";556;2
"Unit";"Mutalisk";"Larva";556;2
"Unit";"Mutalisk";"Larva";556;2
"Unit";"Mutalisk";"Larva";556;2
"Unit";"Mutalisk";"Larva";556;2
"Unit";"Mutalisk";"Larva";556;2
"Unit";"Mutalisk";"Larva";556;2
"Unit";"Mutalisk";"Larva";556;2
"Unit";"Mutalisk";"Larva";556;2
"Unit";"Mutalisk";"Larva";556;2
"Unit";"Mutalisk";"Larva";556;2
"Unit";"Mutalisk";"Larva";556;2
"Unit";"Mutalisk";"Larva";556;2
"Unit";"Mutalisk";"Larva";556;2
"Unit";"Mutalisk";"Larva";556;2
"Unit";"Mutalisk";"Larva";556;2
"Building";"Hatchery";NA;495;0
"Unit";"Zergling";"Larva";594;1
"Unit";"Zergling";"Larva";594;1
"Unit";"Baneling";"Zergling";594;0
"Unit";"Baneling";"Zergling";594;0
"Unit";"Zergling";"Larva";594;1
"Unit";"Zergling";"Larva";594;1
"Unit";"Zergling";"Larva";594;1
"Unit";"Zergling";"Larva";594;1
"Unit";"Baneling";"Zergling";594;0
"Unit";"Baneling";"Zergling";594;0
"Unit";"Zergling";"Larva";594;1
"Unit";"Zergling";"Larva";594;1
"Unit";"Zergling";"Larva";594;1
"Unit";"Zergling";"Larva";594;1
"Unit";"Zergling";"Larva";594;1
"Unit";"Zergling";"Larva";594;1
"Unit";"Zergling";"Larva";594;1
"Unit";"Zergling";"Larva";594;1
"Unit";"Baneling";"Zergling";594;0
"Unit";"Baneling";"Zergling";594;0
"Unit";"Baneling";"Zergling";594;0
"Unit";"Zergling";"Larva";594;1
"Unit";"Zergling";"Larva";594;1
"Unit";"Zergling";"Larva";594;1
"Unit";"Zergling";"Larva";594;1
"Unit";"Zergling";"Larva";594;1
"Unit";"Zergling";"Larva";594;1
"Unit";"Zergling";"Larva";594;1
"Unit";"Zergling";"Larva";594;1
"Unit";"Zergling";"Larva";594;1
"Unit";"Zergling";"Larva";594;1
"Unit";"Zergling";"Larva";594;1
"Unit";"Zergling";"Larva";594;1
"Unit";"Zergling";"Larva";594;1
"Unit";"Zergling";"Larva";594;1
"Unit";"Zergling";"Larva";594;1
"Unit";"Zergling";"Larva";594;1
"Unit";"Zergling";"Larva";594;1
"Unit";"Zergling";"Larva";594;1
"Unit";"Zergling";"Larva";594;1
"Unit";"Zergling";"Larva";594;1
"Unit";"Zergling";"Larva";594;1
"Unit";"Zergling";"Larva";594;1
"Unit";"Zergling";"Larva";594;1
"Unit";"Zergling";"Larva";594;1
"Unit";"Zergling";"Larva";594;1
"Unit";"Zergling";"Larva";594;1
"Unit";"Zergling";"Larva";594;1
"Unit";"Zergling";"Larva";594;1
"Building";"CreepTumorQueen";NA;594;0
"Unit";"Zergling";"Larva";594;1
"Unit";"Zergling";"Larva";594;1
"Unit";"Zergling";"Larva";594;1
"Unit";"Zergling";"Larva";594;1
"Unit";"Zergling";"Larva";594;1
"Unit";"Zergling";"Larva";594;1
"Building";"CreepTumorQueen";NA;594;0
"Unit";"Zergling";"Larva";594;1
"Unit";"Zergling";"Larva";594;1
"Unit";"Zergling";"Larva";594;1
"Unit";"Zergling";"Larva";594;1
"Building";"CreepTumorQueen";NA;634;0
"Unit";"Zergling";"Larva";594;1
"Unit";"Zergling";"Larva";594;1
"Unit";"Zergling";"Larva";594;1
"Unit";"Zergling";"Larva";594;1
"Unit";"Zergling";"Larva";594;1
"Unit";"Zergling";"Larva";594;1
"Unit";"Zergling";"Larva";594;1
"Unit";"Zergling";"Larva";594;1
"Unit";"Zergling";"Larva";594;1
"Unit";"Zergling";"Larva";594;1
"Unit";"Baneling";"Zergling";640;0
"Unit";"Zergling";"Larva";636;1
"Unit";"Zergling";"Larva";636;1
"Unit";"Zergling";"Larva";636;1
"Unit";"Zergling";"Larva";636;1
"Unit";"Baneling";"Zergling";642;0
"Unit";"Baneling";"Zergling";642;0
"Unit";"Baneling";"Zergling";642;0
"Unit";"Baneling";"Zergling";642;0
"Unit";"Zergling";"Larva";636;1
"Unit";"Zergling";"Larva";636;1
"Unit";"Baneling";"Zergling";642;0
"Unit";"Baneling";"Zergling";642;0
"Unit";"Zergling";"Larva";636;1
"Unit";"Zergling";"Larva";636;1
"Unit";"Baneling";"Zergling";642;0
"Unit";"Baneling";"Zergling";642;0
"Unit";"Baneling";"Zergling";642;0
"Unit";"Baneling";"Zergling";642;0
"Unit";"Baneling";"Zergling";642;0
"Unit";"Zergling";"Larva";636;1
"Unit";"Zergling";"Larva";636;1
"Unit";"Baneling";"Zergling";642;0
"Unit";"Baneling";"Zergling";642;0
"Unit";"Baneling";"Zergling";642;0
"Unit";"Baneling";"Zergling";642;0
"Building";"UltraliskCavern";NA;594;0
"Unit";"Zergling";"Larva";666;1
"Unit";"Zergling";"Larva";666;1
"Unit";"Zergling";"Larva";666;1
"Unit";"Zergling";"Larva";666;1
"Unit";"Zergling";"Larva";666;1
"Unit";"Zergling";"Larva";666;1
"Unit";"Zergling";"Larva";666;1
"Unit";"Zergling";"Larva";666;1
"Unit";"Zergling";"Larva";666;1
"Unit";"Zergling";"Larva";666;1
"Unit";"Zergling";"Larva";666;1
"Unit";"Zergling";"Larva";666;1
"Unit";"Zergling";"Larva";666;1
"Unit";"Zergling";"Larva";666;1
"Unit";"Zergling";"Larva";666;1
"Unit";"Zergling";"Larva";666;1
"Unit";"Zergling";"Larva";666;1
"Unit";"Zergling";"Larva";666;1
"Unit";"Zergling";"Larva";666;1
"Unit";"Zergling";"Larva";666;1
"Unit";"Zergling";"Larva";666;1
"Unit";"Zergling";"Larva";666;1
"Unit";"Zergling";"Larva";666;1
"Unit";"Zergling";"Larva";666;1
"Unit";"Zergling";"Larva";666;1
"Unit";"Zergling";"Larva";666;1
"Unit";"Zergling";"Larva";666;1
"Unit";"Zergling";"Larva";666;1
"Unit";"Zergling";"Larva";666;1
"Unit";"Zergling";"Larva";666;1
"Unit";"Zergling";"Larva";666;1
"Unit";"Zergling";"Larva";666;1
"Unit";"Zergling";"Larva";666;1
"Unit";"Zergling";"Larva";666;1
"Unit";"Zergling";"Larva";666;1
"Unit";"Zergling";"Larva";666;1
"Unit";"Zergling";"Larva";666;1
"Unit";"Zergling";"Larva";666;1
"Unit";"Zergling";"Larva";666;1
"Unit";"Zergling";"Larva";666;1
"Unit";"Zergling";"Larva";666;1
"Unit";"Zergling";"Larva";666;1
"Unit";"Zergling";"Larva";666;1
"Unit";"Zergling";"Larva";666;1
"Unit";"Zergling";"Larva";666;1
"Unit";"Zergling";"Larva";666;1
"Building";"CreepTumor";NA;712;0
"Building";"CreepTumor";NA;712;0
"Building";"CreepTumor";NA;712;0
"Building";"CreepTumor";NA;712;0
"Unit";"Ultralisk";"Larva";666;6
"Unit";"Ultralisk";"Larva";712;6
"Upgrade";"ChitinousPlating";"UltraliskCavern";712;0
"Unit";"Ultralisk";"Larva";712;6
"Unit";"Ultralisk";"Larva";712;6
"Unit";"Ultralisk";"Larva";718;6
"Upgrade";"ZergGroundArmorsLevel3";"EvolutionChamber";666;0
"Upgrade";"ZergMeleeWeaponsLevel3";"EvolutionChamber";666;0
