"type";"unit_name";"on_building";"total_supply";"supply"
"Unit";"Overlord";"Larva";13;0
"Building";"Extractor";NA;17;0
"Unit";"Overlord";"Larva";21;0
"Building";"Hatchery";NA;16;0
"Building";"SpawningPool";NA;19;0
"Unit";"Zergling";"Larva";23;1
"Unit";"Zergling";"Larva";23;1
"Unit";"Queen";"Hatchery";22;2
"Unit";"Queen";"Hatchery";23;2
"Building";"CreepTumorQueen";NA;33;0
"Unit";"Zergling";"Larva";33;1
"Unit";"Zergling";"Larva";33;1
"Unit";"Overlord";"Larva";34;0
"Unit";"Overlord";"Larva";34;0
"Unit";"Queen";"Hatchery";33;2
"Building";"CreepTumorQueen";NA;38;0
"Building";"CreepTumor";NA;39;0
"Unit";"Overlord";"Larva";39;0
"Building";"CreepTumor";NA;46;0
"Unit";"Zergling";"Larva";46;1
"Unit";"Zergling";"Larva";46;1
"Building";"Hatchery";NA;29;0
"Building";"CreepTumor";NA;47;0
"Unit";"Queen";"Hatchery";46;2
"Building";"Extractor";NA;47;0
"Building";"CreepTumor";NA;52;0
"Unit";"Zergling";"Larva";52;1
"Unit";"Zergling";"Larva";52;1
"Building";"CreepTumorQueen";NA;57;0
"Building";"CreepTumor";NA;58;0
"Building";"RoachWarren";NA;47;0
"Unit";"Queen";"Hatchery";50;2
"Unit";"Overlord";"Larva";66;0
"Unit";"Overlord";"Larva";70;0
"Unit";"Roach";"Larva";71;2
"Unit";"Roach";"Larva";71;2
"Unit";"Queen";"Hatchery";64;2
"Unit";"Overlord";"Larva";71;0
"Unit";"Zergling";"Larva";71;1
"Unit";"Zergling";"Larva";71;1
"Building";"SporeCrawler";NA;71;0
"Unit";"Roach";"Larva";71;2
"Unit";"Roach";"Larva";71;2
"Unit";"Roach";"Larva";71;2
"Unit";"Zergling";"Larva";71;1
"Unit";"Zergling";"Larva";71;1
"Unit";"Zergling";"Larva";71;1
"Unit";"Zergling";"Larva";71;1
"Unit";"Zergling";"Larva";71;1
"Unit";"Zergling";"Larva";71;1
"Unit";"Zergling";"Larva";71;1
"Unit";"Zergling";"Larva";71;1
"Unit";"Zergling";"Larva";77;1
"Unit";"Zergling";"Larva";77;1
"Unit";"Zergling";"Larva";77;1
"Unit";"Zergling";"Larva";77;1
"Unit";"Zergling";"Larva";79;1
"Unit";"Zergling";"Larva";79;1
"Unit";"Roach";"Larva";85;2
"Unit";"Roach";"Larva";87;2
"Unit";"Zergling";"Larva";93;1
"Unit";"Zergling";"Larva";93;1
"Unit";"Roach";"Larva";93;2
"Building";"SporeCrawler";NA;99;0
"Building";"CreepTumor";NA;111;0
"Unit";"Queen";"Hatchery";93;2
"Unit";"Queen";"Hatchery";93;2
"Building";"CreepTumor";NA;115;0
"Building";"SporeCrawler";NA;106;0
"Building";"CreepTumorQueen";NA;116;0
"Building";"SporeCrawler";NA;111;0
"Building";"CreepTumorQueen";NA;116;0
"Building";"CreepTumorQueen";NA;118;0
"Building";"SporeCrawler";NA;116;0
"Building";"CreepTumor";NA;131;0
"Building";"CreepTumor";NA;132;0
"Building";"Extractor";NA;129;0
"Building";"CreepTumor";NA;133;0
"Building";"EvolutionChamber";NA;129;0
"Building";"CreepTumor";NA;133;0
"Building";"CreepTumor";NA;135;0
"Building";"EvolutionChamber";NA;129;0
"Unit";"Zergling";"Larva";136;1
"Unit";"Zergling";"Larva";136;1
"Unit";"Roach";"Larva";136;2
"Unit";"Roach";"Larva";136;2
"Unit";"Overlord";"Larva";136;0
"Building";"Extractor";NA;136;0
"Building";"Extractor";NA;136;0
"Building";"SporeCrawler";NA;136;0
"Unit";"Overlord";"Larva";137;0
"Unit";"Overlord";"Larva";137;0
"Unit";"Overlord";"Larva";137;0
"Unit";"Overlord";"Larva";144;0
"Unit";"Overlord";"Larva";144;0
"Building";"CreepTumor";NA;144;0
"Building";"Extractor";NA;144;0
"Building";"CreepTumor";NA;145;0
"Building";"CreepTumor";NA;145;0
"Building";"CreepTumor";NA;145;0
"Unit";"Roach";"Larva";144;2
"Unit";"Roach";"Larva";144;2
"Unit";"Roach";"Larva";145;2
"Building";"CreepTumor";NA;151;0
"Unit";"Roach";"Larva";151;2
"Building";"Hatchery";NA;133;0
"Building";"CreepTumor";NA;156;0
"Unit";"Roach";"Larva";151;2
"Building";"HydraliskDen";NA;151;0
"Unit";"Roach";"Larva";151;2
"Unit";"Roach";"Larva";156;2
"Unit";"Roach";"Larva";158;2
"Unit";"Roach";"Larva";158;2
"Building";"InfestationPit";NA;151;0
"Unit";"Overlord";"Larva";159;0
"Unit";"Roach";"Larva";159;2
"Unit";"Zergling";"Larva";161;1
"Unit";"Zergling";"Larva";161;1
"Unit";"Zergling";"Larva";161;1
"Unit";"Zergling";"Larva";161;1
"Unit";"Roach";"Larva";161;2
"Unit";"Zergling";"Larva";161;1
"Unit";"Zergling";"Larva";161;1
"Unit";"Zergling";"Larva";165;1
"Unit";"Zergling";"Larva";165;1
"Unit";"Zergling";"Larva";166;1
"Unit";"Zergling";"Larva";166;1
"Unit";"Roach";"Larva";165;2
"Unit";"Zergling";"Larva";166;1
"Unit";"Zergling";"Larva";166;1
"Unit";"Zergling";"Larva";166;1
"Unit";"Zergling";"Larva";166;1
"Unit";"Roach";"Larva";168;2
"Unit";"Queen";"Hatchery";161;2
"Unit";"Overlord";"Larva";194;0
"Building";"CreepTumor";NA;199;0
"Building";"CreepTumorQueen";NA;210;0
"Building";"CreepTumorQueen";NA;210;0
"Building";"Extractor";NA;201;0
"Upgrade";"ZergGroundArmorsLevel1";"EvolutionChamber";151;0
"Upgrade";"ZergMissileWeaponsLevel1";"EvolutionChamber";151;0
"Unit";"Overlord";"Larva";210;0
"Building";"CreepTumorQueen";NA;210;0
"Building";"CreepTumor";NA;210;0
"Unit";"Hydralisk";"Larva";210;2
"Unit";"Hydralisk";"Larva";210;2
"Unit";"Hydralisk";"Larva";210;2
"Unit";"Hydralisk";"Larva";210;2
"Building";"CreepTumor";NA;210;0
"Building";"Extractor";NA;210;0
"Unit";"Overlord";"Larva";210;0
"Building";"CreepTumor";NA;210;0
"Unit";"Overlord";"Larva";210;0
"Unit";"Hydralisk";"Larva";210;2
"Building";"CreepTumor";NA;211;0
"Unit";"Overlord";"Larva";210;0
"Unit";"Roach";"Larva";211;2
"Building";"CreepTumorQueen";NA;221;0
"Building";"CreepTumor";NA;221;0
"Building";"CreepTumor";NA;221;0
"Unit";"Hydralisk";"Larva";219;2
"Building";"CreepTumorQueen";NA;223;0
"Unit";"Hydralisk";"Larva";221;2
"Unit";"Hydralisk";"Larva";221;2
"Unit";"Overlord";"Larva";223;0
"Upgrade";"EvolveGroovedSpines";"HydraliskDen";210;0
"Unit";"Hydralisk";"Larva";221;2
"Unit";"Hydralisk";"Larva";223;2
"Unit";"Hydralisk";"Larva";223;2
"Unit";"Hydralisk";"Larva";223;2
"Unit";"Hydralisk";"Larva";223;2
"Building";"CreepTumor";NA;229;0
"Unit";"Hydralisk";"Larva";225;2
"Unit";"Hydralisk";"Larva";225;2
"Unit";"Hydralisk";"Larva";225;2
"Unit";"Hydralisk";"Larva";225;2
"Unit";"Hydralisk";"Larva";225;2
"Unit";"Hydralisk";"Larva";229;2
"Unit";"Hydralisk";"Larva";229;2
"Unit";"Hydralisk";"Larva";235;2
"Unit";"Overlord";"Larva";239;0
"Building";"CreepTumor";NA;239;0
"Building";"CreepTumor";NA;239;0
"Building";"CreepTumorQueen";NA;245;0
"Building";"CreepTumor";NA;241;0
"Building";"SpineCrawler";NA;239;0
"Unit";"Overlord";"Larva";259;0
"Building";"CreepTumor";NA;259;0
"Building";"CreepTumor";NA;259;0
"Building";"CreepTumor";NA;259;0
"Building";"CreepTumor";NA;259;0
"Building";"CreepTumor";NA;260;0
"Building";"EvolutionChamber";NA;259;0
"Building";"CreepTumor";NA;260;0
"Building";"EvolutionChamber";NA;259;0
"Building";"EvolutionChamber";NA;259;0
"Building";"CreepTumor";NA;261;0
"Unit";"Hydralisk";"Larva";261;2
"Building";"BanelingNest";NA;259;0
"Building";"CreepTumor";NA;261;0
"Upgrade";"ZergMissileWeaponsLevel2";"EvolutionChamber";235;0
"Upgrade";"GlialReconstitution";"RoachWarren";259;0
"Building";"CreepTumor";NA;263;0
"Building";"CreepTumorQueen";NA;263;0
"Building";"CreepTumorQueen";NA;263;0
"Building";"CreepTumor";NA;263;0
"Unit";"Viper";"Larva";263;3
"Unit";"Viper";"Larva";263;3
"Unit";"Viper";"Larva";263;3
"Unit";"Viper";"Larva";263;3
"Unit";"Viper";"Larva";263;3
"Unit";"Viper";"Larva";263;3
"Building";"CreepTumor";NA;263;0
"Building";"CreepTumor";NA;263;0
"Building";"EvolutionChamber";NA;263;0
"Building";"Hatchery";NA;261;0
"Upgrade";"EvolveMuscularAugments";"HydraliskDen";261;0
"Building";"EvolutionChamber";NA;263;0
"Unit";"Queen";"Hatchery";263;2
"Unit";"Queen";"Hatchery";263;2
"Building";"Spire";NA;261;0
"Unit";"Hydralisk";"Larva";281;2
"Unit";"Hydralisk";"Larva";281;2
"Unit";"Hydralisk";"Larva";281;2
"Unit";"Hydralisk";"Larva";281;2
"Unit";"Hydralisk";"Larva";281;2
"Building";"SpineCrawler";NA;281;0
"Building";"SpineCrawler";NA;285;0
