"type";"unit_name";"on_building";"total_supply";"supply"
"Unit";"Overlord";"Larva";13;0
"Building";"Extractor";NA;18;0
"Unit";"Overlord";"Larva";21;0
"Building";"Hatchery";NA;17;0
"Building";"SpawningPool";NA;20;0
"Unit";"Zergling";"Larva";23;1
"Unit";"Zergling";"Larva";23;1
"Unit";"Zergling";"Larva";23;1
"Unit";"Zergling";"Larva";23;1
"Unit";"Queen";"Hatchery";23;2
"Unit";"Queen";"Hatchery";23;2
"Unit";"Overlord";"Larva";38;0
"Unit";"Overlord";"Larva";39;0
"Unit";"Queen";"Hatchery";36;2
"Unit";"Overlord";"Larva";48;0
"Building";"Hatchery";NA;31;0
"Building";"CreepTumorQueen";NA;49;0
"Unit";"Overlord";"Larva";49;0
"Unit";"Zergling";"Larva";49;1
"Unit";"Zergling";"Larva";49;1
"Unit";"Zergling";"Larva";49;1
"Unit";"Zergling";"Larva";49;1
"Unit";"Zergling";"Larva";49;1
"Unit";"Zergling";"Larva";49;1
"Unit";"Zergling";"Larva";49;1
"Unit";"Zergling";"Larva";49;1
"Building";"RoachWarren";NA;46;0
"Unit";"Queen";"Hatchery";49;2
"Building";"CreepTumorQueen";NA;49;0
"Unit";"Queen";"Hatchery";49;2
"Building";"Extractor";NA;65;0
"Building";"Extractor";NA;65;0
"Unit";"Roach";"Larva";72;2
"Unit";"Roach";"Larva";72;2
"Unit";"Roach";"Larva";72;2
"Unit";"Overlord";"Larva";72;0
"Unit";"Overlord";"Larva";72;0
"Unit";"Overlord";"Larva";72;0
"Building";"CreepTumor";NA;72;0
"Building";"CreepTumorQueen";NA;79;0
"Building";"CreepTumorQueen";NA;79;0
"Unit";"Overlord";"Larva";79;0
"Unit";"Roach";"Larva";79;2
"Unit";"Roach";"Larva";79;2
"Unit";"Roach";"Larva";79;2
"Unit";"Roach";"Larva";79;2
"Unit";"Roach";"Larva";79;2
"Unit";"Queen";"Hatchery";79;2
"Building";"CreepTumor";NA;105;0
"Unit";"Roach";"Larva";105;2
"Unit";"Roach";"Larva";105;2
"Unit";"Roach";"Larva";105;2
"Unit";"Roach";"Larva";105;2
"Building";"EvolutionChamber";NA;102;0
"Building";"HydraliskDen";NA;102;0
"Building";"EvolutionChamber";NA;102;0
"Upgrade";"GlialReconstitution";"RoachWarren";100;0
"Building";"CreepTumor";NA;115;0
"Building";"CreepTumor";NA;115;0
"Building";"Extractor";NA;107;0
"Unit";"Overlord";"Larva";115;0
"Building";"CreepTumor";NA;115;0
"Unit";"Overlord";"Larva";115;0
"Building";"CreepTumor";NA;120;0
"Building";"CreepTumor";NA;120;0
"Building";"CreepTumor";NA;122;0
"Unit";"Overlord";"Larva";120;0
"Building";"Extractor";NA;120;0
"Building";"Extractor";NA;120;0
"Unit";"Zergling";"Larva";122;1
"Unit";"Zergling";"Larva";122;1
"Unit";"Zergling";"Larva";124;1
"Unit";"Zergling";"Larva";124;1
"Unit";"Hydralisk";"Larva";120;2
"Unit";"Hydralisk";"Larva";120;2
"Unit";"Hydralisk";"Larva";120;2
"Building";"Hatchery";NA;105;0
"Building";"CreepTumorQueen";NA;134;0
"Building";"CreepTumorQueen";NA;134;0
"Building";"CreepTumor";NA;139;0
"Unit";"Hydralisk";"Larva";139;2
"Unit";"Hydralisk";"Larva";139;2
"Unit";"Hydralisk";"Larva";139;2
"Upgrade";"EvolveGroovedSpines";"HydraliskDen";124;0
"Unit";"Queen";"Hatchery";139;2
"Unit";"Overlord";"Larva";146;0
"Unit";"Overlord";"Larva";146;0
"Unit";"Overlord";"Larva";146;0
"Unit";"Overlord";"Larva";146;0
"Unit";"Overlord";"Larva";166;0
"Unit";"Overlord";"Larva";166;0
"Building";"CreepTumorQueen";NA;166;0
"Building";"CreepTumorQueen";NA;166;0
"Building";"BanelingNest";NA;140;0
"Building";"CreepTumor";NA;166;0
"Unit";"Overlord";"Larva";166;0
"Unit";"Zergling";"Larva";166;1
"Unit";"Zergling";"Larva";166;1
"Unit";"Zergling";"Larva";166;1
"Unit";"Zergling";"Larva";166;1
"Unit";"Zergling";"Larva";166;1
"Unit";"Zergling";"Larva";166;1
"Unit";"Zergling";"Larva";166;1
"Unit";"Zergling";"Larva";166;1
"Unit";"Zergling";"Larva";166;1
"Unit";"Zergling";"Larva";166;1
"Unit";"Zergling";"Larva";166;1
"Unit";"Zergling";"Larva";166;1
"Unit";"Zergling";"Larva";166;1
"Unit";"Zergling";"Larva";166;1
"Unit";"Zergling";"Larva";166;1
"Unit";"Zergling";"Larva";166;1
"Unit";"Baneling";"Zergling";184;0
"Unit";"Baneling";"Zergling";184;0
"Unit";"Baneling";"Zergling";184;0
"Unit";"Baneling";"Zergling";184;0
"Unit";"Baneling";"Zergling";184;0
"Unit";"Hydralisk";"Larva";168;2
"Unit";"Hydralisk";"Larva";168;2
"Unit";"Hydralisk";"Larva";168;2
"Unit";"Hydralisk";"Larva";168;2
"Unit";"Hydralisk";"Larva";168;2
"Unit";"Hydralisk";"Larva";168;2
"Unit";"Baneling";"Zergling";184;0
"Unit";"Baneling";"Zergling";184;0
"Building";"CreepTumor";NA;184;0
"Building";"CreepTumor";NA;184;0
"Unit";"Hydralisk";"Larva";184;2
"Unit";"Hydralisk";"Larva";184;2
"Unit";"Hydralisk";"Larva";184;2
"Building";"CreepTumor";NA;184;0
"Unit";"Overlord";"Larva";184;0
"Unit";"Overlord";"Larva";184;0
"Upgrade";"ZergMissileWeaponsLevel1";"EvolutionChamber";146;0
"Upgrade";"ZergGroundArmorsLevel1";"EvolutionChamber";146;0
"Upgrade";"EvolveMuscularAugments";"HydraliskDen";168;0
"Unit";"Zergling";"Larva";196;1
"Unit";"Zergling";"Larva";196;1
"Unit";"Zergling";"Larva";196;1
"Unit";"Zergling";"Larva";196;1
"Unit";"Zergling";"Larva";196;1
"Unit";"Zergling";"Larva";196;1
"Unit";"Zergling";"Larva";196;1
"Unit";"Zergling";"Larva";196;1
"Unit";"Zergling";"Larva";196;1
"Unit";"Zergling";"Larva";196;1
"Unit";"Zergling";"Larva";196;1
"Unit";"Zergling";"Larva";196;1
"Unit";"Zergling";"Larva";196;1
"Unit";"Zergling";"Larva";196;1
"Unit";"Zergling";"Larva";196;1
"Unit";"Zergling";"Larva";196;1
"Unit";"Zergling";"Larva";196;1
"Unit";"Zergling";"Larva";196;1
"Unit";"Zergling";"Larva";196;1
"Unit";"Zergling";"Larva";196;1
"Unit";"Zergling";"Larva";196;1
"Unit";"Zergling";"Larva";196;1
"Unit";"Zergling";"Larva";196;1
"Unit";"Zergling";"Larva";196;1
"Unit";"Zergling";"Larva";196;1
"Unit";"Zergling";"Larva";196;1
"Unit";"Zergling";"Larva";196;1
"Unit";"Zergling";"Larva";196;1
"Unit";"Zergling";"Larva";196;1
"Unit";"Zergling";"Larva";196;1
"Building";"Hatchery";NA;166;0
"Unit";"Baneling";"Zergling";196;0
"Unit";"Baneling";"Zergling";196;0
"Unit";"Baneling";"Zergling";196;0
"Unit";"Baneling";"Zergling";196;0
"Unit";"Baneling";"Zergling";196;0
"Unit";"Baneling";"Zergling";196;0
"Unit";"Baneling";"Zergling";196;0
"Unit";"Baneling";"Zergling";196;0
"Unit";"Baneling";"Zergling";196;0
"Unit";"Zergling";"Larva";232;1
"Unit";"Zergling";"Larva";232;1
"Unit";"Zergling";"Larva";232;1
"Unit";"Zergling";"Larva";232;1
"Unit";"Zergling";"Larva";232;1
"Unit";"Zergling";"Larva";232;1
"Unit";"Zergling";"Larva";232;1
"Unit";"Zergling";"Larva";232;1
"Unit";"Zergling";"Larva";232;1
"Unit";"Zergling";"Larva";232;1
"Unit";"Zergling";"Larva";232;1
"Unit";"Zergling";"Larva";232;1
"Unit";"Zergling";"Larva";232;1
"Unit";"Zergling";"Larva";232;1
"Unit";"Zergling";"Larva";232;1
"Unit";"Zergling";"Larva";232;1
"Unit";"Zergling";"Larva";232;1
"Unit";"Zergling";"Larva";232;1
"Unit";"Zergling";"Larva";232;1
"Unit";"Zergling";"Larva";232;1
"Unit";"Zergling";"Larva";232;1
"Unit";"Zergling";"Larva";232;1
"Unit";"Zergling";"Larva";232;1
"Unit";"Zergling";"Larva";232;1
"Unit";"Zergling";"Larva";232;1
"Unit";"Zergling";"Larva";232;1
"Unit";"Zergling";"Larva";232;1
"Unit";"Zergling";"Larva";232;1
"Unit";"Zergling";"Larva";232;1
"Unit";"Zergling";"Larva";232;1
"Unit";"Zergling";"Larva";232;1
"Unit";"Zergling";"Larva";232;1
"Unit";"Zergling";"Larva";232;1
"Unit";"Zergling";"Larva";232;1
"Unit";"Zergling";"Larva";232;1
"Unit";"Zergling";"Larva";232;1
"Unit";"Queen";"Hatchery";218;2
"Unit";"Zergling";"Larva";232;1
"Unit";"Zergling";"Larva";232;1
"Unit";"Zergling";"Larva";232;1
"Unit";"Zergling";"Larva";232;1
"Unit";"Zergling";"Larva";232;1
"Unit";"Zergling";"Larva";232;1
"Unit";"Zergling";"Larva";232;1
"Unit";"Zergling";"Larva";232;1
"Unit";"Zergling";"Larva";232;1
"Unit";"Zergling";"Larva";232;1
"Unit";"Queen";"Hatchery";232;2
"Unit";"Zergling";"Larva";262;1
"Unit";"Zergling";"Larva";262;1
"Unit";"Zergling";"Larva";262;1
"Unit";"Zergling";"Larva";262;1
"Unit";"Zergling";"Larva";262;1
"Unit";"Zergling";"Larva";262;1
"Unit";"Zergling";"Larva";262;1
"Unit";"Zergling";"Larva";262;1
"Unit";"Zergling";"Larva";262;1
"Unit";"Zergling";"Larva";262;1
"Unit";"Zergling";"Larva";262;1
"Unit";"Zergling";"Larva";262;1
"Unit";"Zergling";"Larva";262;1
"Unit";"Zergling";"Larva";262;1
"Unit";"Zergling";"Larva";262;1
"Unit";"Zergling";"Larva";262;1
"Unit";"Zergling";"Larva";262;1
"Unit";"Zergling";"Larva";262;1
"Building";"CreepTumorQueen";NA;282;0
"Building";"CreepTumorQueen";NA;282;0
"Unit";"Overlord";"Larva";282;0
"Unit";"Overlord";"Larva";282;0
"Building";"Extractor";NA;282;0
"Unit";"Zergling";"Larva";300;1
"Unit";"Zergling";"Larva";300;1
"Unit";"Zergling";"Larva";300;1
"Unit";"Zergling";"Larva";300;1
"Unit";"Zergling";"Larva";300;1
"Unit";"Zergling";"Larva";300;1
"Unit";"Zergling";"Larva";300;1
"Unit";"Zergling";"Larva";300;1
"Unit";"Zergling";"Larva";300;1
"Unit";"Zergling";"Larva";300;1
"Unit";"Zergling";"Larva";300;1
"Unit";"Zergling";"Larva";300;1
"Unit";"Zergling";"Larva";300;1
"Unit";"Zergling";"Larva";300;1
"Unit";"Zergling";"Larva";300;1
"Unit";"Zergling";"Larva";300;1
"Unit";"Zergling";"Larva";300;1
"Unit";"Zergling";"Larva";300;1
"Unit";"Zergling";"Larva";300;1
"Unit";"Zergling";"Larva";300;1
"Unit";"Zergling";"Larva";300;1
"Unit";"Zergling";"Larva";300;1
"Unit";"Zergling";"Larva";300;1
"Unit";"Zergling";"Larva";300;1
"Unit";"Baneling";"Zergling";306;0
"Unit";"Baneling";"Zergling";324;0
"Unit";"Baneling";"Zergling";324;0
"Unit";"Baneling";"Zergling";324;0
"Unit";"Baneling";"Zergling";324;0
"Unit";"Baneling";"Zergling";324;0
"Unit";"Baneling";"Zergling";324;0
"Unit";"Baneling";"Zergling";324;0
"Unit";"Baneling";"Zergling";324;0
"Unit";"Baneling";"Zergling";324;0
"Unit";"Baneling";"Zergling";324;0
"Unit";"Baneling";"Zergling";324;0
"Unit";"Baneling";"Zergling";324;0
"Unit";"Baneling";"Zergling";324;0
"Unit";"Overlord";"Larva";324;0
"Unit";"Overlord";"Larva";324;0
"Unit";"Zergling";"Larva";324;1
"Unit";"Zergling";"Larva";324;1
"Unit";"Hydralisk";"Larva";324;2
"Unit";"Zergling";"Larva";324;1
"Unit";"Zergling";"Larva";324;1
"Unit";"Hydralisk";"Larva";324;2
"Unit";"Hydralisk";"Larva";324;2
"Unit";"Hydralisk";"Larva";324;2
"Unit";"Hydralisk";"Larva";324;2
"Unit";"Hydralisk";"Larva";324;2
"Unit";"Hydralisk";"Larva";324;2
"Unit";"Hydralisk";"Larva";324;2
"Unit";"Hydralisk";"Larva";324;2
"Unit";"Hydralisk";"Larva";324;2
"Unit";"Hydralisk";"Larva";324;2
"Unit";"Hydralisk";"Larva";324;2
"Building";"InfestationPit";NA;300;0
"Unit";"Zergling";"Larva";324;1
"Unit";"Zergling";"Larva";324;1
"Unit";"Zergling";"Larva";324;1
"Unit";"Zergling";"Larva";324;1
"Unit";"Zergling";"Larva";324;1
"Unit";"Zergling";"Larva";324;1
"Unit";"Zergling";"Larva";324;1
"Unit";"Zergling";"Larva";324;1
"Unit";"Zergling";"Larva";324;1
"Unit";"Zergling";"Larva";324;1
"Unit";"Zergling";"Larva";324;1
"Unit";"Zergling";"Larva";324;1
"Unit";"Zergling";"Larva";324;1
"Unit";"Zergling";"Larva";324;1
"Unit";"Baneling";"Zergling";354;0
"Unit";"Baneling";"Zergling";356;0
"Unit";"Baneling";"Zergling";356;0
"Building";"CreepTumor";NA;366;0
"Unit";"Baneling";"Zergling";360;0
"Unit";"Zergling";"Larva";352;1
"Unit";"Zergling";"Larva";352;1
"Unit";"Zergling";"Larva";352;1
"Unit";"Zergling";"Larva";352;1
"Unit";"Zergling";"Larva";352;1
"Unit";"Zergling";"Larva";352;1
"Unit";"Zergling";"Larva";352;1
"Unit";"Zergling";"Larva";352;1
"Unit";"Zergling";"Larva";352;1
"Unit";"Zergling";"Larva";352;1
"Unit";"Zergling";"Larva";352;1
"Unit";"Zergling";"Larva";352;1
"Unit";"Zergling";"Larva";352;1
"Unit";"Zergling";"Larva";352;1
"Unit";"Zergling";"Larva";352;1
"Unit";"Zergling";"Larva";352;1
"Unit";"Zergling";"Larva";352;1
"Unit";"Zergling";"Larva";352;1
"Unit";"Zergling";"Larva";352;1
"Unit";"Zergling";"Larva";352;1
"Unit";"Zergling";"Larva";352;1
"Unit";"Zergling";"Larva";352;1
"Unit";"Zergling";"Larva";352;1
"Unit";"Zergling";"Larva";352;1
"Unit";"Zergling";"Larva";352;1
"Unit";"Zergling";"Larva";352;1
"Building";"Hatchery";NA;300;0
"Building";"CreepTumorQueen";NA;366;0
"Unit";"Zergling";"Larva";366;1
"Unit";"Zergling";"Larva";366;1
"Unit";"Zergling";"Larva";366;1
"Unit";"Zergling";"Larva";366;1
"Unit";"Zergling";"Larva";366;1
"Unit";"Zergling";"Larva";366;1
"Unit";"Zergling";"Larva";366;1
"Unit";"Zergling";"Larva";366;1
"Unit";"Zergling";"Larva";366;1
"Unit";"Zergling";"Larva";366;1
"Unit";"Zergling";"Larva";366;1
"Unit";"Zergling";"Larva";366;1
"Unit";"Zergling";"Larva";366;1
"Unit";"Zergling";"Larva";366;1
"Unit";"Zergling";"Larva";366;1
"Unit";"Zergling";"Larva";366;1
"Unit";"Zergling";"Larva";366;1
"Unit";"Zergling";"Larva";366;1
"Unit";"Zergling";"Larva";366;1
"Unit";"Zergling";"Larva";366;1
"Unit";"Zergling";"Larva";366;1
"Unit";"Zergling";"Larva";366;1
"Unit";"Zergling";"Larva";366;1
"Unit";"Zergling";"Larva";366;1
"Unit";"Zergling";"Larva";366;1
"Unit";"Zergling";"Larva";366;1
"Unit";"Zergling";"Larva";366;1
"Unit";"Zergling";"Larva";366;1
"Unit";"Zergling";"Larva";366;1
"Unit";"Zergling";"Larva";366;1
"Unit";"Baneling";"Zergling";396;0
"Unit";"Baneling";"Zergling";396;0
"Unit";"Baneling";"Zergling";396;0
"Unit";"Baneling";"Zergling";396;0
"Unit";"Baneling";"Zergling";396;0
"Unit";"Baneling";"Zergling";396;0
"Unit";"Baneling";"Zergling";396;0
"Unit";"Baneling";"Zergling";396;0
"Unit";"Baneling";"Zergling";396;0
"Unit";"Baneling";"Zergling";396;0
"Unit";"Overlord";"Larva";426;0
"Unit";"Zergling";"Larva";426;1
"Unit";"Zergling";"Larva";426;1
"Upgrade";"ZergMeleeWeaponsLevel1";"EvolutionChamber";324;0
"Unit";"Zergling";"Larva";426;1
"Unit";"Zergling";"Larva";426;1
"Unit";"Zergling";"Larva";426;1
"Unit";"Zergling";"Larva";426;1
"Unit";"Zergling";"Larva";426;1
"Unit";"Zergling";"Larva";426;1
"Unit";"Zergling";"Larva";426;1
"Unit";"Zergling";"Larva";426;1
"Unit";"Zergling";"Larva";426;1
"Unit";"Zergling";"Larva";426;1
"Unit";"Zergling";"Larva";426;1
"Unit";"Zergling";"Larva";426;1
"Unit";"Zergling";"Larva";426;1
"Unit";"Zergling";"Larva";426;1
"Unit";"Zergling";"Larva";426;1
"Unit";"Zergling";"Larva";426;1
"Unit";"Zergling";"Larva";426;1
"Unit";"Zergling";"Larva";426;1
"Unit";"Zergling";"Larva";426;1
"Unit";"Zergling";"Larva";426;1
"Unit";"Zergling";"Larva";426;1
"Unit";"Zergling";"Larva";426;1
"Unit";"Zergling";"Larva";426;1
"Unit";"Zergling";"Larva";426;1
"Unit";"Zergling";"Larva";426;1
"Unit";"Zergling";"Larva";426;1
"Building";"CreepTumor";NA;428;0
"Unit";"Zergling";"Larva";428;1
"Unit";"Zergling";"Larva";428;1
"Building";"CreepTumorQueen";NA;452;0
"Building";"CreepTumor";NA;440;0
"Building";"CreepTumorQueen";NA;456;0
"Building";"CreepTumorQueen";NA;456;0
"Building";"CreepTumorQueen";NA;456;0
"Building";"CreepTumorQueen";NA;456;0
"Upgrade";"ZergGroundArmorsLevel2";"EvolutionChamber";352;0
"Building";"CreepTumor";NA;458;0
"Building";"CreepTumor";NA;458;0
"Building";"CreepTumor";NA;458;0
"Unit";"Baneling";"Zergling";458;0
"Unit";"Baneling";"Zergling";458;0
"Unit";"Baneling";"Zergling";458;0
"Unit";"Baneling";"Zergling";458;0
"Unit";"Baneling";"Zergling";458;0
"Unit";"Baneling";"Zergling";458;0
"Unit";"Baneling";"Zergling";458;0
"Unit";"Baneling";"Zergling";458;0
"Unit";"Baneling";"Zergling";458;0
"Unit";"Baneling";"Zergling";458;0
"Unit";"Baneling";"Zergling";458;0
"Unit";"Baneling";"Zergling";458;0
"Unit";"Baneling";"Zergling";458;0
"Unit";"Baneling";"Zergling";458;0
"Unit";"Baneling";"Zergling";458;0
"Unit";"Baneling";"Zergling";458;0
"Unit";"Baneling";"Zergling";458;0
"Unit";"Baneling";"Zergling";458;0
"Building";"Spire";NA;426;0
"Unit";"Viper";"Larva";458;3
"Unit";"Baneling";"Zergling";458;0
"Unit";"Viper";"Larva";458;3
"Unit";"Viper";"Larva";458;3
"Unit";"Baneling";"Zergling";458;0
"Unit";"Baneling";"Zergling";458;0
"Unit";"Baneling";"Zergling";458;0
"Unit";"Baneling";"Zergling";458;0
"Unit";"Viper";"Larva";458;3
"Unit";"Baneling";"Zergling";458;0
"Unit";"Baneling";"Zergling";458;0
"Unit";"Baneling";"Zergling";458;0
"Unit";"Baneling";"Zergling";458;0
"Unit";"Baneling";"Zergling";458;0
"Unit";"Baneling";"Zergling";458;0
"Unit";"Baneling";"Zergling";458;0
"Unit";"Baneling";"Zergling";458;0
"Unit";"Baneling";"Zergling";458;0
"Unit";"Baneling";"Zergling";458;0
"Unit";"Baneling";"Zergling";458;0
"Unit";"Zergling";"Larva";458;1
"Unit";"Zergling";"Larva";458;1
"Unit";"Hydralisk";"Larva";458;2
"Unit";"Hydralisk";"Larva";458;2
"Building";"Hatchery";NA;458;0
"Unit";"Overlord";"Larva";476;0
"Unit";"Overlord";"Larva";476;0
"Unit";"Overlord";"Larva";476;0
"Unit";"Overlord";"Larva";476;0
"Unit";"Overlord";"Larva";476;0
"Unit";"Overlord";"Larva";476;0
"Building";"Hatchery";NA;458;0
"Unit";"Zergling";"Larva";476;1
"Unit";"Zergling";"Larva";476;1
"Unit";"Zergling";"Larva";476;1
"Unit";"Zergling";"Larva";476;1
"Unit";"Zergling";"Larva";476;1
"Unit";"Zergling";"Larva";476;1
"Unit";"Zergling";"Larva";476;1
"Unit";"Zergling";"Larva";476;1
"Unit";"Zergling";"Larva";476;1
"Unit";"Zergling";"Larva";476;1
"Building";"Spire";NA;458;0
"Upgrade";"ZergMeleeWeaponsLevel2";"EvolutionChamber";458;0
"Unit";"Zergling";"Larva";486;1
"Unit";"Zergling";"Larva";486;1
"Unit";"Zergling";"Larva";486;1
"Unit";"Zergling";"Larva";486;1
"Unit";"Zergling";"Larva";486;1
"Unit";"Zergling";"Larva";486;1
"Unit";"Zergling";"Larva";486;1
"Unit";"Zergling";"Larva";486;1
"Unit";"Zergling";"Larva";486;1
"Unit";"Zergling";"Larva";486;1
"Unit";"Zergling";"Larva";486;1
"Unit";"Zergling";"Larva";486;1
"Unit";"Zergling";"Larva";486;1
"Unit";"Zergling";"Larva";486;1
"Unit";"Zergling";"Larva";486;1
"Unit";"Zergling";"Larva";486;1
"Unit";"Zergling";"Larva";486;1
"Unit";"Zergling";"Larva";486;1
"Unit";"Zergling";"Larva";486;1
"Unit";"Zergling";"Larva";486;1
"Unit";"Zergling";"Larva";486;1
"Unit";"Zergling";"Larva";486;1
"Unit";"Zergling";"Larva";486;1
"Unit";"Zergling";"Larva";486;1
"Unit";"Zergling";"Larva";486;1
"Unit";"Zergling";"Larva";486;1
"Unit";"Zergling";"Larva";486;1
"Unit";"Zergling";"Larva";486;1
"Unit";"Zergling";"Larva";486;1
"Unit";"Zergling";"Larva";486;1
"Unit";"Zergling";"Larva";486;1
"Unit";"Zergling";"Larva";486;1
"Unit";"Zergling";"Larva";486;1
"Unit";"Zergling";"Larva";486;1
"Unit";"Zergling";"Larva";486;1
"Unit";"Zergling";"Larva";486;1
"Unit";"Zergling";"Larva";486;1
"Unit";"Zergling";"Larva";486;1
"Unit";"Zergling";"Larva";486;1
"Unit";"Zergling";"Larva";486;1
"Unit";"Zergling";"Larva";486;1
"Unit";"Zergling";"Larva";486;1
"Unit";"Zergling";"Larva";486;1
"Unit";"Zergling";"Larva";486;1
"Unit";"Zergling";"Larva";486;1
"Unit";"Zergling";"Larva";486;1
"Unit";"Zergling";"Larva";486;1
"Unit";"Zergling";"Larva";486;1
"Unit";"Zergling";"Larva";486;1
"Unit";"Zergling";"Larva";486;1
"Unit";"Zergling";"Larva";486;1
"Unit";"Zergling";"Larva";486;1
"Unit";"Zergling";"Larva";486;1
"Unit";"Zergling";"Larva";486;1
"Unit";"Zergling";"Larva";486;1
"Unit";"Zergling";"Larva";486;1
"Unit";"Zergling";"Larva";486;1
"Unit";"Zergling";"Larva";486;1
"Unit";"Zergling";"Larva";486;1
"Unit";"Zergling";"Larva";486;1
"Unit";"Hydralisk";"Larva";486;2
"Unit";"Hydralisk";"Larva";486;2
"Unit";"Hydralisk";"Larva";486;2
"Unit";"Hydralisk";"Larva";486;2
"Unit";"Hydralisk";"Larva";486;2
"Unit";"Hydralisk";"Larva";486;2
"Unit";"Zergling";"Larva";486;1
"Unit";"Zergling";"Larva";486;1
"Unit";"Zergling";"Larva";486;1
"Unit";"Zergling";"Larva";486;1
"Unit";"Hydralisk";"Larva";486;2
"Unit";"Hydralisk";"Larva";486;2
"Unit";"Hydralisk";"Larva";486;2
"Unit";"Hydralisk";"Larva";486;2
"Unit";"Baneling";"Zergling";562;0
"Unit";"Baneling";"Zergling";562;0
"Unit";"Baneling";"Zergling";562;0
"Unit";"Baneling";"Zergling";562;0
"Unit";"Baneling";"Zergling";562;0
"Unit";"Baneling";"Zergling";562;0
"Unit";"Baneling";"Zergling";562;0
"Unit";"Baneling";"Zergling";576;0
"Unit";"Baneling";"Zergling";576;0
"Unit";"Baneling";"Zergling";576;0
"Unit";"Baneling";"Zergling";576;0
"Unit";"Baneling";"Zergling";576;0
"Unit";"Baneling";"Zergling";576;0
"Building";"Hatchery";NA;486;0
"Unit";"Zergling";"Larva";579;1
"Unit";"Zergling";"Larva";579;1
"Unit";"Zergling";"Larva";579;1
"Unit";"Zergling";"Larva";579;1
"Unit";"Zergling";"Larva";579;1
"Unit";"Zergling";"Larva";579;1
"Unit";"Zergling";"Larva";579;1
"Unit";"Zergling";"Larva";579;1
"Unit";"Zergling";"Larva";579;1
"Unit";"Zergling";"Larva";579;1
"Unit";"Zergling";"Larva";579;1
"Unit";"Zergling";"Larva";579;1
"Unit";"Zergling";"Larva";579;1
"Unit";"Zergling";"Larva";579;1
"Unit";"Zergling";"Larva";579;1
"Unit";"Zergling";"Larva";579;1
"Unit";"Zergling";"Larva";579;1
"Unit";"Zergling";"Larva";579;1
"Unit";"Zergling";"Larva";579;1
"Unit";"Zergling";"Larva";579;1
"Unit";"Zergling";"Larva";579;1
"Unit";"Zergling";"Larva";579;1
"Unit";"Zergling";"Larva";579;1
"Unit";"Zergling";"Larva";579;1
"Unit";"Zergling";"Larva";579;1
"Unit";"Zergling";"Larva";579;1
"Unit";"Zergling";"Larva";579;1
"Unit";"Zergling";"Larva";579;1
"Unit";"Zergling";"Larva";579;1
"Unit";"Zergling";"Larva";579;1
"Unit";"Hydralisk";"Larva";579;2
"Unit";"Hydralisk";"Larva";579;2
"Building";"CreepTumorQueen";NA;579;0
"Unit";"Baneling";"Zergling";617;0
"Unit";"Baneling";"Zergling";617;0
"Unit";"Baneling";"Zergling";617;0
"Unit";"Baneling";"Zergling";617;0
"Unit";"Baneling";"Zergling";617;0
"Unit";"Baneling";"Zergling";617;0
"Unit";"Baneling";"Zergling";617;0
"Upgrade";"ZergGroundArmorsLevel3";"EvolutionChamber";486;0
"Unit";"Queen";"Hatchery";579;2
"Unit";"Zergling";"Larva";617;1
"Unit";"Zergling";"Larva";617;1
"Unit";"Zergling";"Larva";617;1
"Unit";"Zergling";"Larva";617;1
"Unit";"Zergling";"Larva";617;1
"Unit";"Zergling";"Larva";617;1
"Unit";"Zergling";"Larva";617;1
"Unit";"Zergling";"Larva";617;1
"Unit";"Zergling";"Larva";617;1
"Unit";"Zergling";"Larva";617;1
"Unit";"Zergling";"Larva";617;1
"Unit";"Zergling";"Larva";617;1
"Unit";"Zergling";"Larva";617;1
"Unit";"Zergling";"Larva";617;1
"Unit";"Zergling";"Larva";617;1
"Unit";"Zergling";"Larva";617;1
"Unit";"Zergling";"Larva";617;1
"Unit";"Zergling";"Larva";617;1
"Unit";"Zergling";"Larva";617;1
"Unit";"Zergling";"Larva";617;1
"Unit";"Zergling";"Larva";617;1
"Unit";"Zergling";"Larva";617;1
"Unit";"Zergling";"Larva";617;1
"Unit";"Zergling";"Larva";617;1
"Unit";"Zergling";"Larva";617;1
"Unit";"Zergling";"Larva";617;1
"Unit";"Zergling";"Larva";617;1
"Unit";"Zergling";"Larva";617;1
"Unit";"Baneling";"Zergling";647;0
"Unit";"Baneling";"Zergling";647;0
"Unit";"Baneling";"Zergling";647;0
"Unit";"Baneling";"Zergling";647;0
"Unit";"Baneling";"Zergling";647;0
"Unit";"Baneling";"Zergling";647;0
"Unit";"Baneling";"Zergling";647;0
"Unit";"Baneling";"Zergling";647;0
"Unit";"Baneling";"Zergling";647;0
"Unit";"Baneling";"Zergling";647;0
"Unit";"Baneling";"Zergling";647;0
"Unit";"Baneling";"Zergling";647;0
"Unit";"Baneling";"Zergling";647;0
"Unit";"Baneling";"Zergling";647;0
"Unit";"Zergling";"Larva";647;1
"Unit";"Zergling";"Larva";647;1
"Unit";"Zergling";"Larva";647;1
"Unit";"Zergling";"Larva";647;1
"Unit";"Zergling";"Larva";647;1
"Unit";"Zergling";"Larva";647;1
"Unit";"Zergling";"Larva";647;1
"Unit";"Zergling";"Larva";647;1
"Unit";"Zergling";"Larva";647;1
"Unit";"Zergling";"Larva";647;1
"Unit";"Zergling";"Larva";647;1
"Unit";"Zergling";"Larva";647;1
"Unit";"Zergling";"Larva";647;1
"Unit";"Zergling";"Larva";647;1
"Unit";"Zergling";"Larva";647;1
"Unit";"Zergling";"Larva";647;1
"Unit";"Zergling";"Larva";647;1
"Unit";"Zergling";"Larva";647;1
"Unit";"Zergling";"Larva";647;1
"Unit";"Zergling";"Larva";647;1
"Unit";"Zergling";"Larva";647;1
"Unit";"Zergling";"Larva";647;1
"Unit";"Zergling";"Larva";647;1
"Unit";"Zergling";"Larva";647;1
"Unit";"Zergling";"Larva";647;1
"Unit";"Zergling";"Larva";647;1
"Unit";"Baneling";"Zergling";647;0
"Unit";"Baneling";"Zergling";647;0
"Unit";"Baneling";"Zergling";647;0
"Building";"CreepTumorQueen";NA;647;0
"Building";"CreepTumorQueen";NA;655;0
"Building";"Extractor";NA;655;0
"Building";"Extractor";NA;655;0
"Unit";"Zergling";"Larva";689;1
"Unit";"Zergling";"Larva";689;1
"Unit";"Zergling";"Larva";689;1
"Unit";"Zergling";"Larva";689;1
"Unit";"Zergling";"Larva";689;1
"Unit";"Zergling";"Larva";689;1
"Unit";"Zergling";"Larva";689;1
"Unit";"Zergling";"Larva";689;1
"Unit";"Zergling";"Larva";689;1
"Unit";"Zergling";"Larva";689;1
"Unit";"Zergling";"Larva";689;1
"Unit";"Zergling";"Larva";689;1
"Unit";"Zergling";"Larva";689;1
"Unit";"Zergling";"Larva";689;1
"Unit";"Zergling";"Larva";689;1
"Unit";"Zergling";"Larva";689;1
"Unit";"Zergling";"Larva";689;1
"Unit";"Zergling";"Larva";689;1
"Unit";"Zergling";"Larva";689;1
"Unit";"Zergling";"Larva";689;1
"Unit";"Zergling";"Larva";689;1
"Unit";"Zergling";"Larva";689;1
"Unit";"Zergling";"Larva";689;1
"Unit";"Zergling";"Larva";689;1
"Unit";"Zergling";"Larva";689;1
"Unit";"Zergling";"Larva";689;1
"Unit";"Zergling";"Larva";689;1
"Unit";"Zergling";"Larva";689;1
"Unit";"Hydralisk";"Larva";689;2
"Unit";"Zergling";"Larva";719;1
"Unit";"Zergling";"Larva";719;1
"Unit";"Zergling";"Larva";719;1
"Unit";"Zergling";"Larva";719;1
"Unit";"Zergling";"Larva";719;1
"Unit";"Zergling";"Larva";719;1
"Unit";"Zergling";"Larva";719;1
"Unit";"Zergling";"Larva";719;1
"Unit";"Zergling";"Larva";719;1
"Unit";"Zergling";"Larva";719;1
"Unit";"Zergling";"Larva";719;1
"Unit";"Zergling";"Larva";719;1
"Unit";"Zergling";"Larva";719;1
"Unit";"Zergling";"Larva";719;1
"Unit";"Zergling";"Larva";719;1
"Unit";"Zergling";"Larva";719;1
"Unit";"Zergling";"Larva";719;1
"Unit";"Zergling";"Larva";719;1
"Unit";"Zergling";"Larva";719;1
"Unit";"Zergling";"Larva";719;1
"Unit";"Zergling";"Larva";719;1
"Unit";"Zergling";"Larva";719;1
"Unit";"Zergling";"Larva";719;1
"Unit";"Zergling";"Larva";719;1
"Unit";"Baneling";"Zergling";719;0
"Unit";"Baneling";"Zergling";719;0
"Unit";"Baneling";"Zergling";719;0
"Unit";"Baneling";"Zergling";719;0
"Unit";"Baneling";"Zergling";719;0
"Unit";"Baneling";"Zergling";719;0
"Unit";"Baneling";"Zergling";719;0
"Unit";"Baneling";"Zergling";719;0
"Unit";"Zergling";"Larva";719;1
"Unit";"Zergling";"Larva";719;1
"Unit";"Zergling";"Larva";719;1
"Unit";"Zergling";"Larva";719;1
"Unit";"Zergling";"Larva";719;1
"Unit";"Zergling";"Larva";719;1
"Unit";"Zergling";"Larva";719;1
"Unit";"Zergling";"Larva";719;1
"Unit";"Zergling";"Larva";719;1
"Unit";"Zergling";"Larva";719;1
"Unit";"Zergling";"Larva";719;1
"Unit";"Zergling";"Larva";719;1
"Unit";"Zergling";"Larva";719;1
"Unit";"Zergling";"Larva";719;1
"Unit";"Zergling";"Larva";719;1
"Unit";"Zergling";"Larva";719;1
"Unit";"Zergling";"Larva";719;1
"Unit";"Zergling";"Larva";719;1
"Unit";"Zergling";"Larva";719;1
"Unit";"Zergling";"Larva";719;1
"Unit";"Zergling";"Larva";719;1
"Unit";"Zergling";"Larva";719;1
"Unit";"Hydralisk";"Larva";719;2
"Unit";"Hydralisk";"Larva";719;2
"Unit";"Zergling";"Larva";719;1
"Unit";"Zergling";"Larva";719;1
"Unit";"Zergling";"Larva";721;1
"Unit";"Zergling";"Larva";721;1
"Unit";"Queen";"Hatchery";719;2
"Unit";"Baneling";"Zergling";777;0
"Unit";"Baneling";"Zergling";779;0
"Unit";"Baneling";"Zergling";779;0
"Unit";"Baneling";"Zergling";779;0
"Unit";"Viper";"Larva";743;3
"Unit";"Baneling";"Zergling";779;0
"Unit";"Baneling";"Zergling";779;0
"Unit";"Baneling";"Zergling";779;0
"Unit";"Baneling";"Zergling";779;0
"Unit";"Baneling";"Zergling";779;0
"Unit";"Baneling";"Zergling";779;0
"Unit";"Baneling";"Zergling";779;0
"Unit";"Baneling";"Zergling";779;0
"Unit";"Baneling";"Zergling";779;0
"Unit";"Baneling";"Zergling";779;0
"Unit";"Baneling";"Zergling";779;0
"Unit";"Baneling";"Zergling";779;0
"Unit";"Baneling";"Zergling";779;0
