"type";"unit_name";"on_building";"total_supply";"supply"
"Unit";"Overlord";"Larva";12;0
"Building";"Extractor";NA;18;0
"Building";"SpawningPool";NA;19;0
"Unit";"Overlord";"Larva";22;0
"Building";"Hatchery";NA;17;0
"Unit";"Zergling";"Larva";22;1
"Unit";"Zergling";"Larva";22;1
"Unit";"Zergling";"Larva";22;1
"Unit";"Zergling";"Larva";22;1
"Unit";"Queen";"Hatchery";22;2
"Unit";"Queen";"Hatchery";22;2
"Unit";"Overlord";"Larva";37;0
"Unit";"Queen";"Hatchery";32;2
"Unit";"Zergling";"Larva";37;1
"Unit";"Zergling";"Larva";37;1
"Unit";"Zergling";"Larva";40;1
"Unit";"Zergling";"Larva";40;1
"Unit";"Zergling";"Larva";40;1
"Unit";"Zergling";"Larva";40;1
"Unit";"Zergling";"Larva";40;1
"Unit";"Zergling";"Larva";40;1
"Unit";"Zergling";"Larva";40;1
"Unit";"Zergling";"Larva";40;1
"Unit";"Zergling";"Larva";40;1
"Unit";"Zergling";"Larva";40;1
"Unit";"Zergling";"Larva";40;1
"Unit";"Zergling";"Larva";40;1
"Unit";"Zergling";"Larva";40;1
"Unit";"Zergling";"Larva";40;1
"Unit";"Zergling";"Larva";40;1
"Unit";"Zergling";"Larva";40;1
"Unit";"Zergling";"Larva";40;1
"Unit";"Zergling";"Larva";40;1
"Building";"CreepTumorQueen";NA;42;0
"Building";"CreepTumorQueen";NA;60;0
"Unit";"Overlord";"Larva";60;0
"Building";"SporeCrawler";NA;62;0
"Building";"SporeCrawler";NA;62;0
"Building";"CreepTumorQueen";NA;70;0
"Building";"CreepTumor";NA;70;0
"Building";"Hatchery";NA;60;0
"Unit";"Overlord";"Larva";70;0
"Unit";"Overlord";"Larva";70;0
"Unit";"Overlord";"Larva";70;0
"Unit";"Overlord";"Larva";70;0
"Unit";"Queen";"Hatchery";62;2
"Building";"Extractor";NA;73;0
"Unit";"Overlord";"Larva";73;0
"Building";"SporeCrawler";NA;73;0
"Unit";"Zergling";"Larva";73;1
"Unit";"Zergling";"Larva";73;1
"Unit";"Zergling";"Larva";73;1
"Unit";"Zergling";"Larva";73;1
"Unit";"Queen";"Hatchery";73;2
"Unit";"Queen";"Hatchery";73;2
"Building";"SporeCrawler";NA;79;0
"Building";"Extractor";NA;81;0
"Building";"Extractor";NA;83;0
"Building";"CreepTumor";NA;94;0
"Unit";"Zergling";"Larva";92;1
"Unit";"Zergling";"Larva";92;1
"Unit";"Zergling";"Larva";92;1
"Unit";"Zergling";"Larva";92;1
"Unit";"Zergling";"Larva";92;1
"Unit";"Zergling";"Larva";92;1
"Unit";"Zergling";"Larva";92;1
"Unit";"Zergling";"Larva";92;1
"Unit";"Zergling";"Larva";92;1
"Unit";"Zergling";"Larva";92;1
"Unit";"Zergling";"Larva";92;1
"Unit";"Zergling";"Larva";92;1
"Unit";"Zergling";"Larva";92;1
"Unit";"Zergling";"Larva";92;1
"Building";"CreepTumor";NA;94;0
"Unit";"Overlord";"Larva";94;0
"Unit";"Queen";"Hatchery";81;2
"Building";"NydusNetwork";NA;108;0
"Building";"Extractor";NA;124;0
"Building";"NydusCanal";NA;124;0
"Building";"Extractor";NA;124;0
"Unit";"Zergling";"Larva";124;1
"Unit";"Zergling";"Larva";124;1
"Unit";"Zergling";"Larva";124;1
"Unit";"Zergling";"Larva";124;1
"Unit";"Zergling";"Larva";124;1
"Unit";"Zergling";"Larva";124;1
"Unit";"Zergling";"Larva";124;1
"Unit";"Zergling";"Larva";124;1
"Unit";"Zergling";"Larva";124;1
"Unit";"Zergling";"Larva";124;1
"Unit";"Zergling";"Larva";124;1
"Unit";"Zergling";"Larva";124;1
"Unit";"Zergling";"Larva";124;1
"Unit";"Zergling";"Larva";124;1
"Unit";"Zergling";"Larva";124;1
"Unit";"Zergling";"Larva";124;1
"Unit";"Zergling";"Larva";124;1
"Unit";"Zergling";"Larva";124;1
"Unit";"Zergling";"Larva";124;1
"Unit";"Zergling";"Larva";124;1
"Unit";"Zergling";"Larva";124;1
"Unit";"Zergling";"Larva";124;1
"Unit";"Zergling";"Larva";124;1
"Unit";"Zergling";"Larva";124;1
"Building";"CreepTumorQueen";NA;124;0
"Building";"CreepTumorQueen";NA;148;0
"Building";"EvolutionChamber";NA;124;0
"Building";"EvolutionChamber";NA;124;0
"Building";"HydraliskDen";NA;124;0
"Unit";"Queen";"Hatchery";124;2
"Unit";"Queen";"Hatchery";124;2
"Building";"CreepTumorQueen";NA;158;0
"Building";"NydusCanal";NA;162;0
"Unit";"Zergling";"Larva";162;1
"Unit";"Zergling";"Larva";162;1
"Unit";"Zergling";"Larva";162;1
"Unit";"Zergling";"Larva";162;1
"Unit";"Zergling";"Larva";162;1
"Unit";"Zergling";"Larva";162;1
"Unit";"Zergling";"Larva";162;1
"Unit";"Zergling";"Larva";162;1
"Building";"CreepTumor";NA;162;0
"Building";"CreepTumor";NA;166;0
"Building";"InfestationPit";NA;162;0
"Unit";"Zergling";"Larva";166;1
"Unit";"Zergling";"Larva";166;1
"Unit";"Zergling";"Larva";166;1
"Unit";"Zergling";"Larva";166;1
"Unit";"Zergling";"Larva";166;1
"Unit";"Zergling";"Larva";166;1
"Unit";"Zergling";"Larva";166;1
"Unit";"Zergling";"Larva";166;1
"Unit";"Zergling";"Larva";166;1
"Unit";"Zergling";"Larva";166;1
"Unit";"Zergling";"Larva";166;1
"Unit";"Zergling";"Larva";166;1
"Building";"RoachWarren";NA;162;0
"Building";"SpineCrawler";NA;162;0
"Building";"SpineCrawler";NA;162;0
"Building";"CreepTumorQueen";NA;174;0
"Building";"CreepTumorQueen";NA;174;0
"Upgrade";"EvolveGroovedSpines";"HydraliskDen";162;0
"Unit";"Hydralisk";"Larva";186;2
"Unit";"Hydralisk";"Larva";186;2
"Unit";"Hydralisk";"Larva";186;2
"Unit";"Hydralisk";"Larva";186;2
"Unit";"Hydralisk";"Larva";186;2
"Unit";"Hydralisk";"Larva";186;2
"Building";"CreepTumor";NA;186;0
"Building";"CreepTumor";NA;186;0
"Building";"CreepTumorQueen";NA;198;0
"Building";"Hatchery";NA;166;0
"Unit";"Hydralisk";"Larva";186;2
"Unit";"Hydralisk";"Larva";188;2
"Unit";"Hydralisk";"Larva";188;2
"Unit";"Hydralisk";"Larva";188;2
"Unit";"Hydralisk";"Larva";188;2
"Unit";"Hydralisk";"Larva";190;2
"Unit";"Hydralisk";"Larva";190;2
"Unit";"Hydralisk";"Larva";194;2
"Unit";"Hydralisk";"Larva";194;2
"Building";"NydusCanal";NA;199;0
"Upgrade";"ZergGroundArmorsLevel1";"EvolutionChamber";166;0
"Upgrade";"ZergMissileWeaponsLevel1";"EvolutionChamber";166;0
"Building";"NydusCanal";NA;217;0
"Building";"CreepTumor";NA;224;0
"Building";"CreepTumor";NA;224;0
"Unit";"Hydralisk";"Larva";224;2
"Unit";"Hydralisk";"Larva";224;2
"Unit";"Hydralisk";"Larva";224;2
"Unit";"Hydralisk";"Larva";224;2
"Unit";"Hydralisk";"Larva";224;2
"Unit";"Hydralisk";"Larva";224;2
"Building";"NydusCanal";NA;224;0
"Upgrade";"EvolveMuscularAugments";"HydraliskDen";224;0
"Unit";"Overlord";"Larva";236;0
"Unit";"Overlord";"Larva";236;0
"Unit";"Overlord";"Larva";236;0
"Unit";"Overlord";"Larva";236;0
"Building";"Spire";NA;217;0
"Building";"CreepTumor";NA;236;0
"Building";"CreepTumor";NA;236;0
"Building";"NydusCanal";NA;236;0
"Building";"CreepTumor";NA;236;0
"Unit";"Overlord";"Larva";236;0
"Unit";"Overlord";"Larva";236;0
"Unit";"Overlord";"Larva";236;0
"Unit";"Overlord";"Larva";236;0
"Unit";"Overlord";"Larva";236;0
"Building";"CreepTumorQueen";NA;236;0
"Building";"CreepTumor";NA;236;0
"Unit";"Viper";"Larva";236;3
"Building";"CreepTumorQueen";NA;243;0
"Unit";"Viper";"Larva";236;3
"Building";"CreepTumorQueen";NA;245;0
"Building";"CreepTumorQueen";NA;245;0
"Building";"CreepTumorQueen";NA;251;0
"Building";"CreepTumorQueen";NA;251;0
"Unit";"Overlord";"Larva";251;0
"Unit";"Overlord";"Larva";251;0
"Unit";"Overlord";"Larva";251;0
"Unit";"Overlord";"Larva";251;0
"Upgrade";"GlialReconstitution";"RoachWarren";245;0
"Unit";"Hydralisk";"Larva";251;2
"Building";"CreepTumor";NA;251;0
"Unit";"Hydralisk";"Larva";251;2
"Unit";"Hydralisk";"Larva";251;2
"Unit";"Hydralisk";"Larva";251;2
"Unit";"Hydralisk";"Larva";251;2
"Unit";"Hydralisk";"Larva";251;2
"Unit";"Hydralisk";"Larva";251;2
"Unit";"Hydralisk";"Larva";251;2
"Unit";"Hydralisk";"Larva";251;2
"Unit";"Hydralisk";"Larva";251;2
"Unit";"Hydralisk";"Larva";251;2
"Unit";"Hydralisk";"Larva";251;2
"Unit";"Hydralisk";"Larva";251;2
"Unit";"Hydralisk";"Larva";251;2
"Unit";"Hydralisk";"Larva";251;2
"Building";"CreepTumor";NA;251;0
"Building";"CreepTumor";NA;251;0
"Building";"CreepTumor";NA;251;0
"Building";"CreepTumorQueen";NA;257;0
"Building";"CreepTumorQueen";NA;285;0
"Building";"CreepTumorQueen";NA;285;0
"Building";"CreepTumor";NA;271;0
"Building";"CreepTumor";NA;285;0
"Building";"Extractor";NA;285;0
"Building";"Extractor";NA;285;0
"Upgrade";"ZergGroundArmorsLevel2";"EvolutionChamber";244;0
"Upgrade";"ZergMissileWeaponsLevel2";"EvolutionChamber";244;0
"Unit";"Roach";"Larva";285;2
"Unit";"Roach";"Larva";285;2
"Unit";"Roach";"Larva";285;2
"Unit";"Roach";"Larva";285;2
"Unit";"Roach";"Larva";285;2
"Unit";"Roach";"Larva";285;2
"Unit";"Roach";"Larva";285;2
"Unit";"Roach";"Larva";285;2
"Unit";"Roach";"Larva";285;2
"Unit";"Roach";"Larva";285;2
"Unit";"Roach";"Larva";285;2
"Unit";"Roach";"Larva";285;2
"Unit";"Roach";"Larva";285;2
"Unit";"Roach";"Larva";285;2
"Unit";"Roach";"Larva";285;2
