"type";"unit_name";"on_building";"total_supply";"supply"
"Unit";"Overlord";"Larva";13;0
"Building";"Extractor";NA;18;0
"Unit";"Overlord";"Larva";21;0
"Building";"SpawningPool";NA;19;0
"Building";"Hatchery";NA;18;0
"Unit";"Zergling";"Larva";22;1
"Unit";"Zergling";"Larva";22;1
"Unit";"Zergling";"Larva";22;1
"Unit";"Zergling";"Larva";22;1
"Unit";"Queen";"Hatchery";22;2
"Unit";"Queen";"Hatchery";22;2
"Building";"CreepTumorQueen";NA;36;0
"Unit";"Overlord";"Larva";36;0
"Building";"CreepTumor";NA;39;0
"Unit";"Queen";"Hatchery";36;2
"Building";"CreepTumorQueen";NA;41;0
"Unit";"Overlord";"Larva";47;0
"Unit";"Overlord";"Larva";47;0
"Building";"CreepTumor";NA;47;0
"Building";"CreepTumor";NA;47;0
"Unit";"Queen";"Hatchery";43;2
"Building";"SporeCrawler";NA;47;0
"Building";"SporeCrawler";NA;47;0
"Building";"Extractor";NA;47;0
"Building";"CreepTumorQueen";NA;57;0
"Building";"CreepTumorQueen";NA;57;0
"Building";"EvolutionChamber";NA;47;0
"Building";"EvolutionChamber";NA;48;0
"Unit";"Zergling";"Larva";57;1
"Unit";"Zergling";"Larva";57;1
"Unit";"Zergling";"Larva";57;1
"Unit";"Zergling";"Larva";57;1
"Unit";"Zergling";"Larva";57;1
"Unit";"Zergling";"Larva";57;1
"Unit";"Zergling";"Larva";57;1
"Unit";"Zergling";"Larva";57;1
"Unit";"Zergling";"Larva";57;1
"Unit";"Zergling";"Larva";57;1
"Building";"CreepTumor";NA;57;0
"Building";"CreepTumorQueen";NA;57;0
"Unit";"Overlord";"Larva";57;0
"Building";"Hatchery";NA;47;0
"Unit";"Overlord";"Larva";57;0
"Unit";"Overlord";"Larva";59;0
"Building";"CreepTumor";NA;67;0
"Building";"CreepTumor";NA;67;0
"Building";"BanelingNest";NA;57;0
"Building";"CreepTumor";NA;70;0
"Building";"CreepTumor";NA;70;0
"Building";"CreepTumor";NA;70;0
"Building";"CreepTumorQueen";NA;79;0
"Building";"CreepTumorQueen";NA;79;0
"Unit";"Zergling";"Larva";79;1
"Unit";"Zergling";"Larva";79;1
"Unit";"Overlord";"Larva";79;0
"Unit";"Zergling";"Larva";79;1
"Unit";"Zergling";"Larva";79;1
"Unit";"Zergling";"Larva";79;1
"Unit";"Zergling";"Larva";79;1
"Unit";"Zergling";"Larva";79;1
"Unit";"Zergling";"Larva";79;1
"Unit";"Zergling";"Larva";79;1
"Unit";"Zergling";"Larva";79;1
"Unit";"Zergling";"Larva";79;1
"Unit";"Zergling";"Larva";79;1
"Unit";"Zergling";"Larva";79;1
"Unit";"Zergling";"Larva";79;1
"Unit";"Queen";"Hatchery";77;2
"Unit";"Zergling";"Larva";79;1
"Unit";"Zergling";"Larva";79;1
"Unit";"Zergling";"Larva";79;1
"Unit";"Zergling";"Larva";79;1
"Unit";"Zergling";"Larva";79;1
"Unit";"Zergling";"Larva";79;1
"Building";"CreepTumor";NA;79;0
"Unit";"Baneling";"Zergling";79;0
"Unit";"Baneling";"Zergling";79;0
"Unit";"Baneling";"Zergling";79;0
"Building";"CreepTumor";NA;93;0
"Building";"CreepTumor";NA;93;0
"Building";"Extractor";NA;79;0
"Building";"CreepTumor";NA;101;0
"Building";"CreepTumor";NA;101;0
"Building";"CreepTumor";NA;101;0
"Unit";"Zergling";"Larva";95;1
"Unit";"Zergling";"Larva";95;1
"Unit";"Zergling";"Larva";95;1
"Unit";"Zergling";"Larva";95;1
"Unit";"Zergling";"Larva";95;1
"Unit";"Zergling";"Larva";95;1
"Unit";"Zergling";"Larva";95;1
"Unit";"Zergling";"Larva";95;1
"Unit";"Zergling";"Larva";95;1
"Unit";"Zergling";"Larva";95;1
"Unit";"Zergling";"Larva";95;1
"Unit";"Zergling";"Larva";95;1
"Building";"CreepTumorQueen";NA;116;0
"Building";"CreepTumorQueen";NA;116;0
"Unit";"Zergling";"Larva";104;1
"Unit";"Zergling";"Larva";104;1
"Unit";"Overlord";"Larva";104;0
"Unit";"Zergling";"Larva";106;1
"Unit";"Zergling";"Larva";106;1
"Unit";"Zergling";"Larva";106;1
"Unit";"Zergling";"Larva";106;1
"Unit";"Zergling";"Larva";110;1
"Unit";"Zergling";"Larva";110;1
"Unit";"Zergling";"Larva";110;1
"Unit";"Zergling";"Larva";110;1
"Unit";"Overlord";"Larva";116;0
"Unit";"Overlord";"Larva";116;0
"Unit";"Baneling";"Zergling";118;0
"Unit";"Baneling";"Zergling";118;0
"Unit";"Baneling";"Zergling";118;0
"Unit";"Baneling";"Zergling";118;0
"Unit";"Baneling";"Zergling";118;0
"Unit";"Baneling";"Zergling";118;0
"Unit";"Baneling";"Zergling";118;0
"Unit";"Queen";"Hatchery";116;2
"Building";"CreepTumor";NA;128;0
"Building";"CreepTumor";NA;128;0
"Building";"CreepTumor";NA;128;0
"Building";"CreepTumor";NA;128;0
"Upgrade";"ZergMeleeWeaponsLevel1";"EvolutionChamber";79;0
"Building";"CreepTumor";NA;128;0
"Building";"CreepTumor";NA;128;0
"Unit";"Overlord";"Larva";130;0
"Unit";"Overlord";"Larva";133;0
"Building";"Extractor";NA;133;0
"Unit";"Overlord";"Larva";133;0
"Unit";"Overlord";"Larva";134;0
"Unit";"Zergling";"Larva";145;1
"Unit";"Zergling";"Larva";145;1
"Unit";"Zergling";"Larva";145;1
"Unit";"Zergling";"Larva";145;1
"Unit";"Baneling";"Zergling";145;0
"Unit";"Baneling";"Zergling";145;0
"Unit";"Baneling";"Zergling";145;0
"Building";"CreepTumor";NA;145;0
"Building";"CreepTumorQueen";NA;145;0
"Unit";"Zergling";"Larva";145;1
"Unit";"Zergling";"Larva";145;1
"Building";"CreepTumorQueen";NA;145;0
"Unit";"Zergling";"Larva";145;1
"Unit";"Zergling";"Larva";145;1
"Unit";"Zergling";"Larva";145;1
"Unit";"Zergling";"Larva";145;1
"Upgrade";"ZergGroundArmorsLevel1";"EvolutionChamber";116;0
"Unit";"Zergling";"Larva";149;1
"Unit";"Zergling";"Larva";149;1
"Unit";"Zergling";"Larva";149;1
"Unit";"Zergling";"Larva";149;1
"Unit";"Zergling";"Larva";149;1
"Unit";"Zergling";"Larva";149;1
"Unit";"Zergling";"Larva";149;1
"Unit";"Zergling";"Larva";149;1
"Unit";"Zergling";"Larva";149;1
"Unit";"Zergling";"Larva";149;1
"Unit";"Zergling";"Larva";149;1
"Unit";"Zergling";"Larva";149;1
"Unit";"Zergling";"Larva";149;1
"Unit";"Zergling";"Larva";149;1
"Unit";"Zergling";"Larva";149;1
"Unit";"Zergling";"Larva";149;1
"Unit";"Zergling";"Larva";149;1
"Unit";"Zergling";"Larva";149;1
"Unit";"Zergling";"Larva";149;1
"Unit";"Zergling";"Larva";149;1
"Building";"CreepTumor";NA;175;0
"Unit";"Zergling";"Larva";175;1
"Unit";"Zergling";"Larva";175;1
"Unit";"Zergling";"Larva";175;1
"Unit";"Zergling";"Larva";175;1
"Unit";"Zergling";"Larva";175;1
"Unit";"Zergling";"Larva";175;1
"Unit";"Zergling";"Larva";175;1
"Unit";"Zergling";"Larva";175;1
"Unit";"Zergling";"Larva";175;1
"Unit";"Zergling";"Larva";175;1
"Unit";"Zergling";"Larva";175;1
"Unit";"Zergling";"Larva";175;1
"Unit";"Zergling";"Larva";175;1
"Unit";"Zergling";"Larva";175;1
"Unit";"Zergling";"Larva";175;1
"Unit";"Zergling";"Larva";175;1
"Unit";"Zergling";"Larva";175;1
"Unit";"Zergling";"Larva";175;1
"Building";"CreepTumorQueen";NA;175;0
"Unit";"Zergling";"Larva";175;1
"Unit";"Zergling";"Larva";175;1
"Unit";"Zergling";"Larva";175;1
"Unit";"Zergling";"Larva";175;1
"Building";"CreepTumorQueen";NA;175;0
"Building";"InfestationPit";NA;175;0
"Building";"CreepTumor";NA;175;0
"Building";"CreepTumorQueen";NA;175;0
"Building";"CreepTumorQueen";NA;197;0
"Unit";"Overlord";"Larva";197;0
"Unit";"Zergling";"Larva";197;1
"Unit";"Zergling";"Larva";197;1
"Unit";"Zergling";"Larva";197;1
"Unit";"Zergling";"Larva";197;1
"Unit";"Zergling";"Larva";197;1
"Unit";"Zergling";"Larva";197;1
"Unit";"Zergling";"Larva";197;1
"Unit";"Zergling";"Larva";197;1
"Unit";"Zergling";"Larva";197;1
"Unit";"Zergling";"Larva";197;1
"Unit";"Zergling";"Larva";197;1
"Unit";"Zergling";"Larva";197;1
"Unit";"Zergling";"Larva";197;1
"Unit";"Zergling";"Larva";197;1
"Unit";"Zergling";"Larva";197;1
"Unit";"Zergling";"Larva";197;1
"Unit";"Zergling";"Larva";197;1
"Unit";"Zergling";"Larva";197;1
"Unit";"Zergling";"Larva";197;1
"Unit";"Zergling";"Larva";197;1
"Building";"CreepTumor";NA;197;0
"Building";"CreepTumor";NA;197;0
"Building";"CreepTumor";NA;197;0
"Building";"CreepTumor";NA;197;0
"Building";"CreepTumor";NA;197;0
"Unit";"Zergling";"Larva";217;1
"Unit";"Zergling";"Larva";217;1
"Unit";"Zergling";"Larva";217;1
"Unit";"Zergling";"Larva";217;1
"Unit";"Zergling";"Larva";217;1
"Unit";"Zergling";"Larva";217;1
"Unit";"Zergling";"Larva";217;1
"Unit";"Zergling";"Larva";217;1
"Unit";"Zergling";"Larva";217;1
"Unit";"Zergling";"Larva";217;1
"Unit";"Zergling";"Larva";217;1
"Unit";"Zergling";"Larva";217;1
"Unit";"Zergling";"Larva";217;1
"Unit";"Zergling";"Larva";217;1
"Unit";"Zergling";"Larva";217;1
"Unit";"Zergling";"Larva";217;1
"Unit";"Zergling";"Larva";217;1
"Unit";"Zergling";"Larva";217;1
"Unit";"Zergling";"Larva";217;1
"Unit";"Zergling";"Larva";217;1
"Unit";"Baneling";"Zergling";217;0
"Unit";"Baneling";"Zergling";217;0
"Unit";"Baneling";"Zergling";217;0
"Unit";"Baneling";"Zergling";217;0
"Unit";"Baneling";"Zergling";217;0
"Unit";"Baneling";"Zergling";217;0
"Unit";"Baneling";"Zergling";217;0
"Unit";"Baneling";"Zergling";217;0
"Unit";"Baneling";"Zergling";217;0
"Unit";"Baneling";"Zergling";217;0
"Unit";"Baneling";"Zergling";217;0
"Unit";"Baneling";"Zergling";217;0
"Building";"Hatchery";NA;175;0
"Unit";"Overlord";"Larva";217;0
"Upgrade";"ZergMeleeWeaponsLevel2";"EvolutionChamber";175;0
"Building";"Hatchery";NA;175;0
"Unit";"Zergling";"Larva";237;1
"Unit";"Zergling";"Larva";237;1
"Unit";"Zergling";"Larva";237;1
"Unit";"Zergling";"Larva";237;1
"Unit";"Zergling";"Larva";237;1
"Unit";"Zergling";"Larva";237;1
"Unit";"Zergling";"Larva";237;1
"Unit";"Zergling";"Larva";237;1
"Building";"CreepTumor";NA;237;0
"Building";"CreepTumor";NA;237;0
"Building";"CreepTumor";NA;237;0
"Building";"Hatchery";NA;197;0
"Upgrade";"ZergGroundArmorsLevel2";"EvolutionChamber";175;0
"Unit";"Zergling";"Larva";245;1
"Unit";"Zergling";"Larva";245;1
"Unit";"Zergling";"Larva";245;1
"Unit";"Zergling";"Larva";245;1
"Unit";"Zergling";"Larva";245;1
"Unit";"Zergling";"Larva";245;1
"Unit";"Zergling";"Larva";245;1
"Unit";"Zergling";"Larva";245;1
"Unit";"Zergling";"Larva";245;1
"Unit";"Zergling";"Larva";245;1
"Unit";"Zergling";"Larva";245;1
"Unit";"Zergling";"Larva";245;1
"Unit";"Zergling";"Larva";245;1
"Unit";"Zergling";"Larva";245;1
"Unit";"Zergling";"Larva";245;1
"Unit";"Zergling";"Larva";245;1
"Unit";"Zergling";"Larva";245;1
"Unit";"Zergling";"Larva";245;1
"Unit";"Zergling";"Larva";245;1
"Unit";"Zergling";"Larva";245;1
"Unit";"Zergling";"Larva";245;1
"Unit";"Zergling";"Larva";245;1
"Unit";"Zergling";"Larva";245;1
"Unit";"Zergling";"Larva";245;1
"Unit";"Zergling";"Larva";245;1
"Unit";"Zergling";"Larva";245;1
"Unit";"Zergling";"Larva";245;1
"Unit";"Zergling";"Larva";245;1
"Unit";"Zergling";"Larva";245;1
"Unit";"Zergling";"Larva";245;1
"Unit";"Zergling";"Larva";245;1
"Unit";"Zergling";"Larva";245;1
"Unit";"Zergling";"Larva";245;1
"Unit";"Zergling";"Larva";245;1
"Building";"CreepTumorQueen";NA;245;0
"Building";"Extractor";NA;245;0
"Building";"CreepTumor";NA;245;0
"Building";"CreepTumor";NA;245;0
"Building";"CreepTumorQueen";NA;245;0
"Building";"CreepTumorQueen";NA;279;0
"Building";"Extractor";NA;279;0
"Building";"CreepTumorQueen";NA;282;0
"Unit";"Baneling";"Zergling";279;0
"Unit";"Baneling";"Zergling";279;0
"Unit";"Baneling";"Zergling";279;0
"Unit";"Baneling";"Zergling";279;0
"Unit";"Baneling";"Zergling";279;0
"Unit";"Baneling";"Zergling";279;0
"Unit";"Baneling";"Zergling";279;0
"Unit";"Baneling";"Zergling";279;0
"Building";"UltraliskCavern";NA;279;0
"Building";"CreepTumorQueen";NA;293;0
"Building";"CreepTumor";NA;293;0
"Building";"CreepTumorQueen";NA;293;0
"Building";"CreepTumor";NA;293;0
"Building";"CreepTumor";NA;293;0
"Building";"CreepTumor";NA;293;0
"Unit";"Overlord";"Larva";298;0
"Upgrade";"Burrow";"Hatchery";293;0
"Unit";"Queen";"Hatchery";298;2
"Unit";"Queen";"Hatchery";298;2
"Unit";"Queen";"Hatchery";298;2
"Unit";"Queen";"Hatchery";298;2
"Unit";"Queen";"Hatchery";298;2
"Unit";"Ultralisk";"Larva";298;6
"Building";"CreepTumorQueen";NA;308;0
"Unit";"Ultralisk";"Larva";298;6
"Building";"CreepTumor";NA;308;0
"Building";"CreepTumor";NA;308;0
"Building";"Spire";NA;298;0
"Unit";"Ultralisk";"Larva";308;6
"Unit";"Zergling";"Larva";320;1
"Unit";"Zergling";"Larva";320;1
"Unit";"Zergling";"Larva";320;1
"Unit";"Zergling";"Larva";320;1
"Unit";"Zergling";"Larva";320;1
"Unit";"Zergling";"Larva";320;1
"Unit";"Zergling";"Larva";320;1
"Unit";"Zergling";"Larva";320;1
"Unit";"Zergling";"Larva";320;1
"Unit";"Zergling";"Larva";320;1
"Unit";"Zergling";"Larva";320;1
"Unit";"Zergling";"Larva";320;1
"Unit";"Zergling";"Larva";320;1
"Unit";"Zergling";"Larva";320;1
"Unit";"Zergling";"Larva";320;1
"Unit";"Zergling";"Larva";320;1
"Unit";"Zergling";"Larva";320;1
"Unit";"Zergling";"Larva";320;1
"Unit";"Zergling";"Larva";320;1
"Unit";"Zergling";"Larva";320;1
"Unit";"Zergling";"Larva";320;1
"Unit";"Zergling";"Larva";320;1
"Upgrade";"ChitinousPlating";"UltraliskCavern";298;0
"Unit";"Zergling";"Larva";320;1
"Unit";"Zergling";"Larva";320;1
"Unit";"Zergling";"Larva";320;1
"Unit";"Zergling";"Larva";320;1
"Unit";"Zergling";"Larva";320;1
"Unit";"Zergling";"Larva";320;1
"Unit";"Zergling";"Larva";320;1
"Unit";"Zergling";"Larva";320;1
"Unit";"Zergling";"Larva";320;1
"Unit";"Zergling";"Larva";320;1
"Unit";"Zergling";"Larva";320;1
"Unit";"Zergling";"Larva";320;1
"Unit";"Zergling";"Larva";320;1
"Unit";"Zergling";"Larva";320;1
"Unit";"Zergling";"Larva";320;1
"Unit";"Zergling";"Larva";320;1
"Unit";"Zergling";"Larva";320;1
"Unit";"Zergling";"Larva";320;1
"Unit";"Zergling";"Larva";320;1
"Unit";"Zergling";"Larva";320;1
"Unit";"Zergling";"Larva";320;1
"Unit";"Zergling";"Larva";320;1
"Unit";"Zergling";"Larva";320;1
"Unit";"Zergling";"Larva";320;1
"Unit";"Zergling";"Larva";320;1
"Unit";"Zergling";"Larva";320;1
"Unit";"Zergling";"Larva";320;1
"Unit";"Zergling";"Larva";320;1
"Unit";"Zergling";"Larva";320;1
"Unit";"Zergling";"Larva";320;1
"Unit";"Zergling";"Larva";320;1
"Unit";"Zergling";"Larva";320;1
"Unit";"Overlord";"Larva";320;0
"Unit";"Overlord";"Larva";320;0
"Unit";"Overlord";"Larva";320;0
"Unit";"Ultralisk";"Larva";314;6
"Unit";"Ultralisk";"Larva";320;6
"Upgrade";"ZergMeleeWeaponsLevel3";"EvolutionChamber";298;0
"Upgrade";"ZergGroundArmorsLevel3";"EvolutionChamber";298;0
"Unit";"Zergling";"Larva";386;1
"Unit";"Zergling";"Larva";386;1
"Unit";"Zergling";"Larva";386;1
"Unit";"Zergling";"Larva";386;1
"Unit";"Zergling";"Larva";386;1
"Unit";"Zergling";"Larva";386;1
"Unit";"Zergling";"Larva";386;1
"Unit";"Zergling";"Larva";386;1
"Unit";"Zergling";"Larva";386;1
"Unit";"Zergling";"Larva";386;1
"Unit";"Zergling";"Larva";386;1
"Unit";"Zergling";"Larva";386;1
"Unit";"Zergling";"Larva";386;1
"Unit";"Zergling";"Larva";386;1
"Unit";"Zergling";"Larva";386;1
"Unit";"Zergling";"Larva";386;1
"Unit";"Zergling";"Larva";386;1
"Unit";"Zergling";"Larva";386;1
"Unit";"Zergling";"Larva";386;1
"Unit";"Zergling";"Larva";386;1
"Unit";"Zergling";"Larva";386;1
"Unit";"Zergling";"Larva";386;1
"Unit";"Zergling";"Larva";386;1
"Unit";"Zergling";"Larva";386;1
"Unit";"Zergling";"Larva";386;1
"Unit";"Zergling";"Larva";386;1
"Unit";"Zergling";"Larva";386;1
"Unit";"Zergling";"Larva";386;1
"Unit";"Zergling";"Larva";386;1
"Unit";"Zergling";"Larva";386;1
"Unit";"Zergling";"Larva";386;1
"Unit";"Zergling";"Larva";386;1
"Unit";"Zergling";"Larva";386;1
"Unit";"Zergling";"Larva";386;1
"Unit";"Ultralisk";"Larva";326;6
"Unit";"Zergling";"Larva";426;1
"Unit";"Zergling";"Larva";426;1
"Unit";"Queen";"Hatchery";392;2
"Unit";"Zergling";"Larva";432;1
"Unit";"Zergling";"Larva";432;1
"Unit";"Zergling";"Larva";432;1
"Unit";"Zergling";"Larva";432;1
"Unit";"Zergling";"Larva";432;1
"Unit";"Zergling";"Larva";432;1
"Unit";"Zergling";"Larva";432;1
"Unit";"Zergling";"Larva";432;1
"Unit";"Zergling";"Larva";432;1
"Unit";"Zergling";"Larva";432;1
"Unit";"Zergling";"Larva";432;1
"Unit";"Zergling";"Larva";432;1
"Unit";"Zergling";"Larva";436;1
"Unit";"Zergling";"Larva";436;1
"Unit";"Zergling";"Larva";436;1
"Unit";"Zergling";"Larva";436;1
"Unit";"Zergling";"Larva";436;1
"Unit";"Zergling";"Larva";436;1
"Unit";"Zergling";"Larva";436;1
"Unit";"Zergling";"Larva";436;1
"Unit";"Zergling";"Larva";436;1
"Unit";"Zergling";"Larva";436;1
"Unit";"Zergling";"Larva";436;1
"Unit";"Zergling";"Larva";436;1
"Unit";"Ultralisk";"Larva";426;6
"Unit";"Ultralisk";"Larva";426;6
"Unit";"Ultralisk";"Larva";426;6
"Building";"Extractor";NA;448;0
"Building";"Extractor";NA;448;0
"Unit";"Overlord";"Larva";478;0
"Unit";"Overlord";"Larva";478;0
"Unit";"Overlord";"Larva";478;0
"Unit";"Overlord";"Larva";478;0
"Unit";"Overlord";"Larva";478;0
"Unit";"Overlord";"Larva";478;0
"Unit";"Overlord";"Larva";478;0
"Unit";"Overlord";"Larva";478;0
"Unit";"Overlord";"Larva";478;0
"Unit";"Corruptor";"Larva";478;2
"Unit";"Corruptor";"Larva";478;2
"Unit";"Corruptor";"Larva";478;2
"Unit";"Corruptor";"Larva";478;2
"Unit";"Corruptor";"Larva";478;2
"Unit";"Corruptor";"Larva";478;2
"Unit";"Corruptor";"Larva";478;2
"Unit";"Corruptor";"Larva";478;2
"Unit";"Corruptor";"Larva";478;2
"Unit";"Corruptor";"Larva";478;2
"Unit";"Corruptor";"Larva";478;2
"Unit";"Corruptor";"Larva";478;2
"Unit";"Corruptor";"Larva";478;2
"Unit";"Zergling";"Larva";478;1
"Unit";"Zergling";"Larva";478;1
"Unit";"Zergling";"Larva";478;1
"Unit";"Zergling";"Larva";478;1
"Unit";"Zergling";"Larva";478;1
"Unit";"Zergling";"Larva";478;1
"Unit";"Zergling";"Larva";478;1
"Unit";"Zergling";"Larva";478;1
"Unit";"Zergling";"Larva";478;1
"Unit";"Zergling";"Larva";478;1
"Unit";"Zergling";"Larva";478;1
"Unit";"Zergling";"Larva";478;1
"Unit";"Zergling";"Larva";478;1
"Unit";"Zergling";"Larva";478;1
"Unit";"Zergling";"Larva";478;1
"Unit";"Zergling";"Larva";478;1
"Unit";"Zergling";"Larva";478;1
"Unit";"Zergling";"Larva";478;1
"Unit";"Zergling";"Larva";478;1
"Unit";"Zergling";"Larva";478;1
