"type";"unit_name";"on_building";"total_supply";"supply"
"Building";"Extractor";NA;13;0
"Unit";"Overlord";"Larva";15;0
"Building";"SpawningPool";NA;15;0
"Unit";"Zergling";"Larva";18;1
"Unit";"Zergling";"Larva";18;1
"Unit";"Zergling";"Larva";18;1
"Unit";"Zergling";"Larva";18;1
"Unit";"Zergling";"Larva";18;1
"Unit";"Zergling";"Larva";18;1
"Unit";"Queen";"Hatchery";18;2
"Unit";"Overlord";"Larva";24;0
