"type";"unit_name";"on_building";"total_supply";"supply"
"Unit";"Overlord";"Larva";12;0
"Building";"Extractor";NA;18;0
"Unit";"Overlord";"Larva";22;0
"Building";"SpawningPool";NA;19;0
"Building";"Hatchery";NA;17;0
"Unit";"Zergling";"Larva";22;1
"Unit";"Zergling";"Larva";22;1
"Unit";"Zergling";"Larva";23;1
"Unit";"Zergling";"Larva";23;1
"Unit";"Queen";"Hatchery";22;2
"Unit";"Queen";"Hatchery";23;2
"Unit";"Queen";"Hatchery";32;2
"Unit";"Overlord";"Larva";36;0
"Building";"CreepTumorQueen";NA;42;0
"Unit";"Overlord";"Larva";43;0
"Unit";"Overlord";"Larva";46;0
"Unit";"Queen";"Hatchery";42;2
"Building";"CreepTumorQueen";NA;49;0
"Building";"CreepTumor";NA;49;0
"Building";"CreepTumorQueen";NA;51;0
"Unit";"Overlord";"Larva";49;0
"Building";"Hatchery";NA;39;0
"Building";"Extractor";NA;51;0
"Unit";"Zergling";"Larva";51;1
"Unit";"Zergling";"Larva";51;1
"Building";"Extractor";NA;51;0
"Unit";"Zergling";"Larva";59;1
"Unit";"Zergling";"Larva";59;1
"Unit";"Queen";"Hatchery";51;2
"Building";"CreepTumor";NA;59;0
"Unit";"Zergling";"Larva";59;1
"Unit";"Zergling";"Larva";59;1
"Unit";"Zergling";"Larva";59;1
"Unit";"Zergling";"Larva";59;1
"Building";"CreepTumor";NA;59;0
"Unit";"Zergling";"Larva";61;1
"Unit";"Zergling";"Larva";61;1
"Unit";"Zergling";"Larva";61;1
"Unit";"Zergling";"Larva";61;1
"Unit";"Zergling";"Larva";61;1
"Unit";"Zergling";"Larva";61;1
"Unit";"Overlord";"Larva";63;0
"Unit";"Overlord";"Larva";63;0
"Building";"BanelingNest";NA;51;0
"Building";"CreepTumor";NA;69;0
"Unit";"Queen";"Hatchery";59;2
"Building";"SporeCrawler";NA;69;0
"Building";"SporeCrawler";NA;70;0
"Building";"CreepTumor";NA;83;0
"Building";"CreepTumor";NA;83;0
"Building";"CreepTumor";NA;83;0
"Building";"SporeCrawler";NA;83;0
"Building";"CreepTumorQueen";NA;91;0
"Building";"CreepTumorQueen";NA;95;0
"Unit";"Overlord";"Larva";91;0
"Unit";"Overlord";"Larva";91;0
"Unit";"Baneling";"Zergling";95;0
"Unit";"Baneling";"Zergling";95;0
"Building";"CreepTumorQueen";NA;95;0
"Unit";"Baneling";"Zergling";95;0
"Unit";"Baneling";"Zergling";95;0
"Building";"CreepTumor";NA;95;0
"Unit";"Zergling";"Larva";97;1
"Unit";"Zergling";"Larva";97;1
"Unit";"Zergling";"Larva";97;1
"Unit";"Zergling";"Larva";97;1
"Unit";"Zergling";"Larva";97;1
"Unit";"Zergling";"Larva";97;1
"Unit";"Zergling";"Larva";97;1
"Unit";"Zergling";"Larva";97;1
"Unit";"Zergling";"Larva";97;1
"Unit";"Zergling";"Larva";97;1
"Unit";"Zergling";"Larva";97;1
"Unit";"Zergling";"Larva";97;1
"Building";"CreepTumor";NA;100;0
"Building";"HydraliskDen";NA;97;0
"Unit";"Zergling";"Larva";100;1
"Unit";"Zergling";"Larva";100;1
"Unit";"Zergling";"Larva";100;1
"Unit";"Zergling";"Larva";100;1
"Unit";"Zergling";"Larva";100;1
"Unit";"Zergling";"Larva";100;1
"Unit";"Zergling";"Larva";100;1
"Unit";"Zergling";"Larva";100;1
"Building";"CreepTumor";NA;100;0
"Building";"CreepTumor";NA;100;0
"Building";"EvolutionChamber";NA;100;0
"Building";"EvolutionChamber";NA;100;0
"Unit";"Zergling";"Larva";120;1
"Unit";"Zergling";"Larva";120;1
"Unit";"Zergling";"Larva";120;1
"Unit";"Zergling";"Larva";120;1
"Unit";"Zergling";"Larva";120;1
"Unit";"Zergling";"Larva";120;1
"Unit";"Zergling";"Larva";120;1
"Unit";"Zergling";"Larva";120;1
"Building";"Extractor";NA;116;0
"Building";"CreepTumorQueen";NA;125;0
"Building";"CreepTumorQueen";NA;125;0
"Building";"CreepTumorQueen";NA;125;0
"Building";"Extractor";NA;120;0
"Building";"CreepTumor";NA;125;0
"Building";"CreepTumor";NA;125;0
"Building";"CreepTumor";NA;125;0
"Building";"CreepTumor";NA;125;0
"Building";"CreepTumor";NA;125;0
"Building";"RoachWarren";NA;120;0
"Unit";"Zergling";"Larva";133;1
"Unit";"Zergling";"Larva";133;1
"Unit";"Zergling";"Larva";133;1
"Unit";"Zergling";"Larva";133;1
"Unit";"Zergling";"Larva";133;1
"Unit";"Zergling";"Larva";133;1
"Unit";"Zergling";"Larva";133;1
"Unit";"Zergling";"Larva";133;1
"Unit";"Overlord";"Larva";133;0
"Unit";"Overlord";"Larva";133;0
"Building";"CreepTumor";NA;138;0
"Building";"CreepTumor";NA;138;0
"Building";"CreepTumor";NA;138;0
"Building";"CreepTumor";NA;138;0
"Building";"CreepTumor";NA;138;0
"Building";"CreepTumor";NA;146;0
"Building";"CreepTumor";NA;146;0
"Unit";"Roach";"Larva";146;2
"Unit";"Roach";"Larva";146;2
"Unit";"Roach";"Larva";146;2
"Unit";"Roach";"Larva";146;2
"Unit";"Roach";"Larva";146;2
"Building";"CreepTumor";NA;146;0
"Building";"CreepTumorQueen";NA;146;0
"Building";"CreepTumorQueen";NA;156;0
"Building";"Hatchery";NA;125;0
"Unit";"Roach";"Larva";146;2
"Unit";"Roach";"Larva";146;2
"Unit";"Roach";"Larva";146;2
"Unit";"Roach";"Larva";146;2
"Unit";"Roach";"Larva";146;2
"Upgrade";"EvolveGroovedSpines";"HydraliskDen";138;0
"Unit";"Overlord";"Larva";156;0
"Unit";"Overlord";"Larva";156;0
"Unit";"Overlord";"Larva";156;0
"Unit";"Overlord";"Larva";156;0
"Unit";"Overlord";"Larva";156;0
"Building";"InfestationPit";NA;156;0
"Building";"CreepTumorQueen";NA;167;0
"Building";"CreepTumorQueen";NA;167;0
"Building";"CreepTumor";NA;167;0
"Building";"CreepTumor";NA;167;0
"Building";"CreepTumorQueen";NA;167;0
"Building";"Extractor";NA;167;0
"Building";"CreepTumor";NA;175;0
"Upgrade";"GlialReconstitution";"RoachWarren";156;0
"Building";"CreepTumor";NA;175;0
"Building";"CreepTumor";NA;175;0
"Building";"CreepTumor";NA;175;0
"Building";"CreepTumor";NA;175;0
"Building";"CreepTumor";NA;175;0
"Unit";"Hydralisk";"Larva";170;2
"Upgrade";"ZergMissileWeaponsLevel1";"EvolutionChamber";146;0
"Upgrade";"ZergGroundArmorsLevel1";"EvolutionChamber";146;0
"Unit";"Hydralisk";"Larva";170;2
"Unit";"Hydralisk";"Larva";170;2
"Unit";"Hydralisk";"Larva";170;2
"Unit";"Hydralisk";"Larva";170;2
"Unit";"Hydralisk";"Larva";170;2
"Unit";"Hydralisk";"Larva";170;2
"Building";"CreepTumor";NA;178;0
"Building";"CreepTumor";NA;178;0
"Building";"CreepTumor";NA;178;0
"Building";"CreepTumor";NA;178;0
"Building";"CreepTumorQueen";NA;180;0
"Unit";"Baneling";"Zergling";192;0
"Unit";"Roach";"Larva";192;2
"Unit";"Roach";"Larva";192;2
"Unit";"Hydralisk";"Larva";192;2
"Unit";"Hydralisk";"Larva";192;2
"Unit";"Hydralisk";"Larva";192;2
"Unit";"Hydralisk";"Larva";192;2
"Unit";"Hydralisk";"Larva";192;2
"Unit";"Hydralisk";"Larva";192;2
"Upgrade";"EvolveMuscularAugments";"HydraliskDen";178;0
"Building";"CreepTumor";NA;208;0
"Building";"Hatchery";NA;170;0
"Unit";"Roach";"Larva";196;2
"Unit";"Overlord";"Larva";196;0
"Unit";"Roach";"Larva";196;2
"Unit";"Roach";"Larva";196;2
"Unit";"Roach";"Larva";196;2
"Unit";"Roach";"Larva";196;2
"Unit";"Overlord";"Larva";196;0
"Unit";"Roach";"Larva";196;2
"Unit";"Roach";"Larva";196;2
"Unit";"Overlord";"Larva";196;0
"Unit";"Roach";"Larva";196;2
"Unit";"Overlord";"Larva";196;0
"Unit";"Overlord";"Larva";196;0
"Unit";"Overlord";"Larva";196;0
"Building";"CreepTumor";NA;208;0
"Building";"CreepTumorQueen";NA;208;0
"Building";"CreepTumor";NA;208;0
"Building";"CreepTumor";NA;208;0
"Building";"CreepTumorQueen";NA;208;0
"Building";"CreepTumor";NA;208;0
"Building";"CreepTumorQueen";NA;208;0
"Building";"CreepTumor";NA;208;0
"Building";"CreepTumor";NA;208;0
"Building";"CreepTumor";NA;225;0
"Building";"CreepTumor";NA;225;0
"Building";"CreepTumor";NA;225;0
"Unit";"Hydralisk";"Larva";224;2
"Unit";"Hydralisk";"Larva";224;2
"Unit";"Hydralisk";"Larva";224;2
"Unit";"Hydralisk";"Larva";224;2
"Unit";"Hydralisk";"Larva";224;2
"Unit";"Hydralisk";"Larva";224;2
"Building";"CreepTumor";NA;232;0
"Building";"CreepTumorQueen";NA;232;0
"Building";"CreepTumorQueen";NA;232;0
"Building";"CreepTumorQueen";NA;232;0
"Unit";"Roach";"Larva";232;2
"Unit";"Roach";"Larva";232;2
"Unit";"Roach";"Larva";232;2
"Unit";"Roach";"Larva";232;2
"Unit";"Hydralisk";"Larva";232;2
"Unit";"Hydralisk";"Larva";232;2
"Unit";"Hydralisk";"Larva";232;2
"Unit";"Hydralisk";"Larva";232;2
"Unit";"Roach";"Larva";244;2
"Unit";"Roach";"Larva";244;2
"Unit";"Roach";"Larva";244;2
"Unit";"Hydralisk";"Larva";244;2
"Unit";"Hydralisk";"Larva";244;2
"Unit";"Hydralisk";"Larva";244;2
"Building";"Extractor";NA;252;0
"Building";"Extractor";NA;252;0
"Building";"CreepTumor";NA;272;0
"Building";"CreepTumor";NA;272;0
"Unit";"Roach";"Larva";272;2
"Unit";"Roach";"Larva";272;2
"Unit";"Roach";"Larva";272;2
"Unit";"Roach";"Larva";272;2
"Unit";"Roach";"Larva";272;2
"Building";"CreepTumorQueen";NA;272;0
"Building";"CreepTumorQueen";NA;272;0
"Building";"CreepTumorQueen";NA;272;0
"Unit";"Hydralisk";"Larva";272;2
"Unit";"Hydralisk";"Larva";272;2
"Unit";"Hydralisk";"Larva";272;2
"Unit";"Hydralisk";"Larva";272;2
"Unit";"Hydralisk";"Larva";272;2
"Upgrade";"ZergMissileWeaponsLevel2";"EvolutionChamber";208;0
"Upgrade";"ZergGroundArmorsLevel2";"EvolutionChamber";208;0
"Unit";"Viper";"Larva";272;3
"Unit";"Roach";"Larva";272;2
"Unit";"Roach";"Larva";272;2
"Unit";"Hydralisk";"Larva";272;2
"Unit";"Hydralisk";"Larva";272;2
"Unit";"Hydralisk";"Larva";272;2
"Unit";"Zergling";"Larva";305;1
"Unit";"Zergling";"Larva";305;1
"Unit";"Zergling";"Larva";305;1
"Unit";"Zergling";"Larva";305;1
"Unit";"Zergling";"Larva";305;1
"Unit";"Zergling";"Larva";305;1
"Unit";"Zergling";"Larva";305;1
"Unit";"Zergling";"Larva";305;1
"Unit";"Zergling";"Larva";305;1
"Unit";"Zergling";"Larva";305;1
"Unit";"Zergling";"Larva";305;1
"Unit";"Zergling";"Larva";305;1
"Unit";"Zergling";"Larva";305;1
"Unit";"Zergling";"Larva";305;1
"Unit";"Zergling";"Larva";305;1
"Unit";"Zergling";"Larva";305;1
"Unit";"Zergling";"Larva";305;1
"Unit";"Zergling";"Larva";305;1
"Unit";"Zergling";"Larva";305;1
"Unit";"Zergling";"Larva";305;1
"Unit";"Zergling";"Larva";305;1
"Unit";"Zergling";"Larva";305;1
"Unit";"Zergling";"Larva";305;1
"Unit";"Zergling";"Larva";305;1
"Unit";"Zergling";"Larva";305;1
"Unit";"Zergling";"Larva";305;1
"Unit";"Zergling";"Larva";305;1
"Unit";"Zergling";"Larva";305;1
"Unit";"Zergling";"Larva";305;1
"Unit";"Zergling";"Larva";305;1
"Unit";"Zergling";"Larva";305;1
"Unit";"Zergling";"Larva";305;1
"Unit";"Zergling";"Larva";305;1
"Unit";"Zergling";"Larva";305;1
"Unit";"Zergling";"Larva";305;1
"Unit";"Zergling";"Larva";305;1
"Unit";"Viper";"Larva";305;3
"Unit";"Viper";"Larva";305;3
"Unit";"Hydralisk";"Larva";305;2
"Unit";"Hydralisk";"Larva";305;2
"Unit";"Hydralisk";"Larva";305;2
"Unit";"Hydralisk";"Larva";305;2
"Unit";"Hydralisk";"Larva";305;2
"Unit";"Hydralisk";"Larva";305;2
"Unit";"Zergling";"Larva";347;1
"Unit";"Zergling";"Larva";347;1
"Unit";"Zergling";"Larva";347;1
"Unit";"Zergling";"Larva";347;1
"Unit";"Zergling";"Larva";347;1
"Unit";"Zergling";"Larva";347;1
"Unit";"Zergling";"Larva";347;1
"Unit";"Zergling";"Larva";347;1
"Unit";"Zergling";"Larva";347;1
"Unit";"Zergling";"Larva";347;1
