"type";"unit_name";"on_building";"total_supply";"supply"
"Unit";"Overlord";"Larva";12;0
"Building";"Extractor";NA;17;0
"Building";"SpawningPool";NA;19;0
"Building";"Hatchery";NA;17;0
"Unit";"Overlord";"Larva";22;0
"Unit";"Zergling";"Larva";23;1
"Unit";"Zergling";"Larva";23;1
"Unit";"Zergling";"Larva";23;1
"Unit";"Zergling";"Larva";23;1
"Unit";"Queen";"Hatchery";22;2
"Unit";"Queen";"Hatchery";22;2
"Unit";"Overlord";"Larva";25;0
"Unit";"Overlord";"Larva";36;0
"Unit";"Queen";"Hatchery";35;2
"Building";"CreepTumorQueen";NA;39;0
"Building";"CreepTumor";NA;49;0
"Unit";"Overlord";"Larva";49;0
"Building";"CreepTumorQueen";NA;49;0
"Unit";"Overlord";"Larva";52;0
"Unit";"Overlord";"Larva";53;0
"Building";"CreepTumor";NA;58;0
"Building";"CreepTumor";NA;58;0
"Building";"CreepTumorQueen";NA;58;0
"Building";"EvolutionChamber";NA;58;0
"Building";"EvolutionChamber";NA;58;0
"Unit";"Zergling";"Larva";58;1
"Unit";"Zergling";"Larva";58;1
"Unit";"Zergling";"Larva";58;1
"Unit";"Zergling";"Larva";58;1
"Unit";"Zergling";"Larva";58;1
"Unit";"Zergling";"Larva";58;1
"Unit";"Zergling";"Larva";58;1
"Unit";"Zergling";"Larva";58;1
"Unit";"Zergling";"Larva";58;1
"Unit";"Zergling";"Larva";58;1
"Unit";"Queen";"Hatchery";58;2
"Building";"Hatchery";NA;49;0
"Unit";"Queen";"Hatchery";58;2
"Unit";"Zergling";"Larva";64;1
"Unit";"Zergling";"Larva";64;1
"Building";"CreepTumorQueen";NA;78;0
"Unit";"Zergling";"Larva";74;1
"Unit";"Zergling";"Larva";74;1
"Unit";"Zergling";"Larva";74;1
"Unit";"Zergling";"Larva";74;1
"Building";"CreepTumorQueen";NA;80;0
"Building";"CreepTumor";NA;80;0
"Building";"CreepTumor";NA;80;0
"Building";"CreepTumor";NA;84;0
"Unit";"Overlord";"Larva";80;0
"Unit";"Queen";"Hatchery";76;2
"Unit";"Overlord";"Larva";84;0
"Unit";"Queen";"Hatchery";80;2
"Unit";"Queen";"Hatchery";80;2
"Unit";"Zergling";"Larva";84;1
"Unit";"Zergling";"Larva";84;1
"Unit";"Zergling";"Larva";84;1
"Unit";"Zergling";"Larva";84;1
"Unit";"Zergling";"Larva";84;1
"Unit";"Zergling";"Larva";84;1
"Unit";"Zergling";"Larva";84;1
"Unit";"Zergling";"Larva";84;1
"Unit";"Zergling";"Larva";84;1
"Unit";"Zergling";"Larva";84;1
"Unit";"Zergling";"Larva";84;1
"Unit";"Zergling";"Larva";84;1
"Unit";"Zergling";"Larva";84;1
"Unit";"Zergling";"Larva";84;1
"Unit";"Zergling";"Larva";86;1
"Unit";"Zergling";"Larva";86;1
"Unit";"Zergling";"Larva";86;1
"Unit";"Zergling";"Larva";86;1
"Unit";"Zergling";"Larva";86;1
"Unit";"Zergling";"Larva";86;1
"Building";"BanelingNest";NA;84;0
"Building";"CreepTumor";NA;111;0
"Building";"CreepTumor";NA;111;0
"Building";"CreepTumor";NA;111;0
"Building";"CreepTumorQueen";NA;111;0
"Building";"Extractor";NA;117;0
"Building";"Extractor";NA;117;0
"Upgrade";"ZergGroundArmorsLevel1";"EvolutionChamber";84;0
"Building";"CreepTumor";NA;119;0
"Building";"CreepTumor";NA;119;0
"Upgrade";"ZergMeleeWeaponsLevel1";"EvolutionChamber";84;0
"Unit";"Overlord";"Larva";119;0
"Building";"Extractor";NA;118;0
"Building";"Extractor";NA;119;0
"Building";"CreepTumorQueen";NA;126;0
"Unit";"Queen";"Hatchery";117;2
"Unit";"Queen";"Hatchery";117;2
"Unit";"Zergling";"Larva";126;1
"Unit";"Zergling";"Larva";126;1
"Unit";"Zergling";"Larva";126;1
"Unit";"Zergling";"Larva";126;1
"Unit";"Zergling";"Larva";126;1
"Unit";"Zergling";"Larva";126;1
"Unit";"Zergling";"Larva";126;1
"Unit";"Zergling";"Larva";126;1
"Unit";"Zergling";"Larva";126;1
"Unit";"Zergling";"Larva";126;1
"Unit";"Zergling";"Larva";126;1
"Unit";"Zergling";"Larva";126;1
"Unit";"Zergling";"Larva";126;1
"Unit";"Zergling";"Larva";126;1
"Unit";"Zergling";"Larva";126;1
"Unit";"Zergling";"Larva";126;1
"Unit";"Overlord";"Larva";129;0
"Unit";"Overlord";"Larva";129;0
"Unit";"Overlord";"Larva";130;0
"Unit";"Baneling";"Zergling";132;0
"Unit";"Baneling";"Zergling";132;0
"Building";"Hatchery";NA;111;0
"Unit";"Baneling";"Zergling";132;0
"Unit";"Baneling";"Zergling";132;0
"Unit";"Baneling";"Zergling";132;0
"Unit";"Baneling";"Zergling";132;0
"Unit";"Baneling";"Zergling";132;0
"Unit";"Overlord";"Larva";136;0
"Building";"CreepTumor";NA;152;0
"Unit";"Overlord";"Larva";136;0
"Building";"CreepTumor";NA;152;0
"Building";"CreepTumor";NA;152;0
"Building";"CreepTumorQueen";NA;152;0
"Unit";"Zergling";"Larva";152;1
"Unit";"Zergling";"Larva";152;1
"Unit";"Zergling";"Larva";152;1
"Unit";"Zergling";"Larva";152;1
"Unit";"Zergling";"Larva";152;1
"Unit";"Zergling";"Larva";152;1
"Unit";"Zergling";"Larva";152;1
"Unit";"Zergling";"Larva";152;1
"Unit";"Zergling";"Larva";152;1
"Unit";"Zergling";"Larva";152;1
"Unit";"Zergling";"Larva";152;1
"Unit";"Zergling";"Larva";152;1
"Unit";"Zergling";"Larva";152;1
"Unit";"Zergling";"Larva";152;1
"Building";"Hatchery";NA;125;0
"Unit";"Zergling";"Larva";166;1
"Unit";"Zergling";"Larva";166;1
"Unit";"Zergling";"Larva";166;1
"Unit";"Zergling";"Larva";166;1
"Unit";"Zergling";"Larva";166;1
"Unit";"Zergling";"Larva";166;1
"Unit";"Zergling";"Larva";166;1
"Unit";"Zergling";"Larva";166;1
"Unit";"Zergling";"Larva";166;1
"Unit";"Zergling";"Larva";166;1
"Unit";"Zergling";"Larva";166;1
"Unit";"Zergling";"Larva";166;1
"Unit";"Zergling";"Larva";172;1
"Unit";"Zergling";"Larva";172;1
"Unit";"Zergling";"Larva";172;1
"Unit";"Zergling";"Larva";172;1
"Unit";"Zergling";"Larva";172;1
"Unit";"Zergling";"Larva";172;1
"Unit";"Baneling";"Zergling";172;0
"Unit";"Baneling";"Zergling";172;0
"Unit";"Baneling";"Zergling";172;0
"Unit";"Baneling";"Zergling";172;0
"Building";"CreepTumor";NA;184;0
"Building";"CreepTumorQueen";NA;184;0
"Building";"CreepTumor";NA;184;0
"Building";"CreepTumor";NA;190;0
"Building";"CreepTumorQueen";NA;190;0
"Unit";"Zergling";"Larva";184;1
"Unit";"Zergling";"Larva";184;1
"Unit";"Zergling";"Larva";184;1
"Unit";"Zergling";"Larva";184;1
"Unit";"Zergling";"Larva";184;1
"Unit";"Zergling";"Larva";184;1
"Unit";"Baneling";"Zergling";190;0
"Unit";"Baneling";"Zergling";190;0
"Building";"CreepTumor";NA;193;0
"Unit";"Baneling";"Zergling";193;0
"Unit";"Zergling";"Larva";190;1
"Unit";"Zergling";"Larva";190;1
"Unit";"Zergling";"Larva";190;1
"Unit";"Zergling";"Larva";190;1
"Unit";"Zergling";"Larva";190;1
"Unit";"Zergling";"Larva";190;1
"Unit";"Zergling";"Larva";190;1
"Unit";"Zergling";"Larva";190;1
"Unit";"Zergling";"Larva";190;1
"Unit";"Zergling";"Larva";190;1
"Unit";"Zergling";"Larva";190;1
"Unit";"Zergling";"Larva";190;1
"Building";"CreepTumor";NA;193;0
"Building";"InfestationPit";NA;172;0
"Unit";"Overlord";"Larva";193;0
"Unit";"Zergling";"Larva";199;1
"Unit";"Zergling";"Larva";199;1
"Unit";"Zergling";"Larva";199;1
"Unit";"Zergling";"Larva";199;1
"Unit";"Zergling";"Larva";199;1
"Unit";"Zergling";"Larva";199;1
"Unit";"Zergling";"Larva";199;1
"Unit";"Zergling";"Larva";199;1
"Unit";"Zergling";"Larva";199;1
"Unit";"Zergling";"Larva";199;1
"Unit";"Zergling";"Larva";199;1
"Unit";"Zergling";"Larva";199;1
"Unit";"Baneling";"Zergling";199;0
"Unit";"Baneling";"Zergling";199;0
"Unit";"Baneling";"Zergling";199;0
"Unit";"Baneling";"Zergling";199;0
"Unit";"Baneling";"Zergling";199;0
"Unit";"Baneling";"Zergling";199;0
"Unit";"Baneling";"Zergling";201;0
"Unit";"Zergling";"Larva";213;1
"Unit";"Zergling";"Larva";213;1
"Unit";"Zergling";"Larva";213;1
"Unit";"Zergling";"Larva";213;1
"Unit";"Zergling";"Larva";213;1
"Unit";"Zergling";"Larva";213;1
"Unit";"Zergling";"Larva";213;1
"Unit";"Zergling";"Larva";213;1
"Unit";"Zergling";"Larva";213;1
"Unit";"Zergling";"Larva";213;1
"Unit";"Zergling";"Larva";213;1
"Unit";"Zergling";"Larva";213;1
"Unit";"Zergling";"Larva";213;1
"Unit";"Zergling";"Larva";213;1
"Building";"CreepTumor";NA;225;0
"Building";"CreepTumor";NA;225;0
"Unit";"Baneling";"Zergling";225;0
"Unit";"Baneling";"Zergling";225;0
"Unit";"Baneling";"Zergling";225;0
"Unit";"Baneling";"Zergling";225;0
"Unit";"Baneling";"Zergling";225;0
"Unit";"Zergling";"Larva";225;1
"Unit";"Zergling";"Larva";225;1
"Unit";"Zergling";"Larva";225;1
"Unit";"Zergling";"Larva";225;1
"Unit";"Zergling";"Larva";225;1
"Unit";"Zergling";"Larva";225;1
"Unit";"Zergling";"Larva";225;1
"Unit";"Zergling";"Larva";225;1
"Unit";"Zergling";"Larva";225;1
"Unit";"Zergling";"Larva";225;1
"Unit";"Zergling";"Larva";225;1
"Unit";"Zergling";"Larva";225;1
"Unit";"Zergling";"Larva";225;1
"Unit";"Zergling";"Larva";225;1
"Unit";"Zergling";"Larva";225;1
"Unit";"Zergling";"Larva";225;1
"Unit";"Zergling";"Larva";225;1
"Unit";"Zergling";"Larva";225;1
"Unit";"Zergling";"Larva";225;1
"Unit";"Zergling";"Larva";225;1
"Unit";"Zergling";"Larva";225;1
"Unit";"Zergling";"Larva";225;1
"Unit";"Zergling";"Larva";225;1
"Unit";"Zergling";"Larva";225;1
"Unit";"Zergling";"Larva";225;1
"Unit";"Zergling";"Larva";225;1
"Unit";"Zergling";"Larva";225;1
"Unit";"Zergling";"Larva";225;1
"Building";"CreepTumor";NA;239;0
"Building";"CreepTumor";NA;239;0
"Building";"CreepTumor";NA;239;0
"Unit";"Baneling";"Zergling";267;0
"Unit";"Baneling";"Zergling";267;0
"Unit";"Baneling";"Zergling";267;0
"Unit";"Baneling";"Zergling";267;0
"Unit";"Baneling";"Zergling";267;0
"Unit";"Baneling";"Zergling";267;0
"Unit";"Zergling";"Larva";267;1
"Unit";"Zergling";"Larva";267;1
"Unit";"Zergling";"Larva";267;1
"Unit";"Zergling";"Larva";267;1
"Unit";"Zergling";"Larva";267;1
"Unit";"Zergling";"Larva";267;1
"Unit";"Zergling";"Larva";267;1
"Unit";"Zergling";"Larva";267;1
"Unit";"Zergling";"Larva";267;1
"Unit";"Zergling";"Larva";267;1
"Unit";"Zergling";"Larva";267;1
"Unit";"Zergling";"Larva";267;1
"Unit";"Zergling";"Larva";267;1
"Unit";"Zergling";"Larva";267;1
"Unit";"Zergling";"Larva";267;1
"Unit";"Zergling";"Larva";267;1
"Unit";"Zergling";"Larva";267;1
"Unit";"Zergling";"Larva";267;1
"Unit";"Zergling";"Larva";267;1
"Unit";"Zergling";"Larva";267;1
"Unit";"Zergling";"Larva";267;1
"Unit";"Zergling";"Larva";267;1
"Unit";"Zergling";"Larva";267;1
"Unit";"Zergling";"Larva";267;1
"Unit";"Zergling";"Larva";267;1
"Unit";"Zergling";"Larva";267;1
"Unit";"Baneling";"Zergling";267;0
"Unit";"Baneling";"Zergling";267;0
"Unit";"Baneling";"Zergling";267;0
"Unit";"Baneling";"Zergling";267;0
"Unit";"Baneling";"Zergling";267;0
"Unit";"Baneling";"Zergling";267;0
"Unit";"Baneling";"Zergling";267;0
"Unit";"Baneling";"Zergling";267;0
"Unit";"Baneling";"Zergling";267;0
"Unit";"Baneling";"Zergling";267;0
"Unit";"Baneling";"Zergling";267;0
"Upgrade";"ZergGroundArmorsLevel2";"EvolutionChamber";184;0
"Upgrade";"ZergMeleeWeaponsLevel2";"EvolutionChamber";190;0
"Unit";"Zergling";"Larva";293;1
"Unit";"Zergling";"Larva";293;1
"Unit";"Zergling";"Larva";293;1
"Unit";"Zergling";"Larva";293;1
"Unit";"Zergling";"Larva";293;1
"Unit";"Zergling";"Larva";293;1
"Unit";"Zergling";"Larva";293;1
"Unit";"Zergling";"Larva";293;1
"Unit";"Zergling";"Larva";293;1
"Unit";"Zergling";"Larva";293;1
"Unit";"Zergling";"Larva";293;1
"Unit";"Zergling";"Larva";293;1
"Unit";"Zergling";"Larva";293;1
"Unit";"Zergling";"Larva";293;1
"Unit";"Zergling";"Larva";293;1
"Unit";"Zergling";"Larva";293;1
"Unit";"Zergling";"Larva";293;1
"Unit";"Zergling";"Larva";293;1
"Unit";"Zergling";"Larva";293;1
"Unit";"Zergling";"Larva";293;1
"Unit";"Zergling";"Larva";293;1
"Unit";"Zergling";"Larva";293;1
"Unit";"Zergling";"Larva";293;1
"Unit";"Zergling";"Larva";293;1
"Unit";"Zergling";"Larva";293;1
"Unit";"Zergling";"Larva";293;1
"Unit";"Zergling";"Larva";293;1
"Unit";"Zergling";"Larva";293;1
"Unit";"Zergling";"Larva";293;1
"Unit";"Zergling";"Larva";293;1
"Unit";"Zergling";"Larva";293;1
"Unit";"Zergling";"Larva";293;1
"Building";"CreepTumor";NA;315;0
"Unit";"Zergling";"Larva";315;1
"Unit";"Zergling";"Larva";315;1
"Unit";"Zergling";"Larva";315;1
"Unit";"Zergling";"Larva";315;1
"Unit";"Zergling";"Larva";315;1
"Unit";"Zergling";"Larva";315;1
"Unit";"Zergling";"Larva";315;1
"Unit";"Zergling";"Larva";315;1
"Unit";"Zergling";"Larva";315;1
"Unit";"Zergling";"Larva";315;1
"Unit";"Zergling";"Larva";315;1
"Unit";"Zergling";"Larva";315;1
"Unit";"Zergling";"Larva";315;1
"Unit";"Zergling";"Larva";315;1
"Unit";"Zergling";"Larva";315;1
"Unit";"Zergling";"Larva";315;1
"Unit";"Zergling";"Larva";315;1
"Unit";"Zergling";"Larva";315;1
"Unit";"Zergling";"Larva";315;1
"Unit";"Zergling";"Larva";315;1
"Unit";"Zergling";"Larva";315;1
"Unit";"Zergling";"Larva";315;1
"Unit";"Baneling";"Zergling";326;0
"Unit";"Baneling";"Zergling";326;0
"Unit";"Baneling";"Zergling";326;0
"Unit";"Baneling";"Zergling";326;0
"Unit";"Baneling";"Zergling";326;0
"Unit";"Baneling";"Zergling";326;0
"Unit";"Baneling";"Zergling";326;0
"Unit";"Baneling";"Zergling";326;0
"Unit";"Baneling";"Zergling";326;0
"Unit";"Baneling";"Zergling";326;0
"Unit";"Baneling";"Zergling";326;0
"Unit";"Baneling";"Zergling";326;0
"Unit";"Baneling";"Zergling";326;0
"Unit";"Baneling";"Zergling";326;0
"Unit";"Baneling";"Zergling";326;0
"Unit";"Baneling";"Zergling";326;0
"Unit";"Baneling";"Zergling";326;0
"Unit";"Baneling";"Zergling";326;0
"Unit";"Baneling";"Zergling";326;0
"Unit";"Baneling";"Zergling";326;0
"Unit";"Baneling";"Zergling";326;0
"Unit";"Baneling";"Zergling";326;0
"Building";"Hatchery";NA;267;0
"Building";"CreepTumorQueen";NA;348;0
"Building";"CreepTumorQueen";NA;348;0
"Building";"CreepTumor";NA;348;0
"Building";"CreepTumorQueen";NA;348;0
"Unit";"Zergling";"Larva";348;1
"Unit";"Zergling";"Larva";348;1
"Building";"CreepTumor";NA;348;0
"Unit";"Zergling";"Larva";348;1
"Unit";"Zergling";"Larva";348;1
"Unit";"Zergling";"Larva";348;1
"Unit";"Zergling";"Larva";348;1
"Unit";"Zergling";"Larva";348;1
"Unit";"Zergling";"Larva";348;1
"Unit";"Zergling";"Larva";348;1
"Unit";"Zergling";"Larva";348;1
"Unit";"Zergling";"Larva";348;1
"Unit";"Zergling";"Larva";348;1
"Unit";"Zergling";"Larva";348;1
"Unit";"Zergling";"Larva";348;1
"Unit";"Zergling";"Larva";348;1
"Unit";"Zergling";"Larva";348;1
"Building";"Extractor";NA;348;0
"Building";"CreepTumor";NA;348;0
"Building";"CreepTumor";NA;348;0
"Unit";"Zergling";"Larva";348;1
"Unit";"Zergling";"Larva";348;1
"Unit";"Zergling";"Larva";348;1
"Unit";"Zergling";"Larva";348;1
"Unit";"Zergling";"Larva";348;1
"Unit";"Zergling";"Larva";348;1
"Unit";"Zergling";"Larva";348;1
"Unit";"Zergling";"Larva";348;1
"Unit";"Zergling";"Larva";348;1
"Unit";"Zergling";"Larva";348;1
"Unit";"Zergling";"Larva";348;1
"Unit";"Zergling";"Larva";348;1
"Unit";"Zergling";"Larva";348;1
"Unit";"Zergling";"Larva";348;1
"Building";"CreepTumor";NA;351;0
"Unit";"Zergling";"Larva";367;1
"Unit";"Zergling";"Larva";367;1
"Unit";"Zergling";"Larva";367;1
"Unit";"Zergling";"Larva";367;1
"Unit";"Zergling";"Larva";367;1
"Unit";"Zergling";"Larva";367;1
"Unit";"Zergling";"Larva";367;1
"Unit";"Zergling";"Larva";367;1
"Unit";"Zergling";"Larva";369;1
"Unit";"Zergling";"Larva";369;1
"Unit";"Zergling";"Larva";369;1
"Unit";"Zergling";"Larva";369;1
"Unit";"Zergling";"Larva";381;1
"Unit";"Zergling";"Larva";381;1
"Unit";"Zergling";"Larva";381;1
"Unit";"Zergling";"Larva";381;1
"Unit";"Zergling";"Larva";381;1
"Unit";"Zergling";"Larva";381;1
"Unit";"Zergling";"Larva";381;1
"Unit";"Zergling";"Larva";381;1
"Unit";"Zergling";"Larva";381;1
"Unit";"Zergling";"Larva";381;1
"Unit";"Zergling";"Larva";381;1
"Unit";"Zergling";"Larva";381;1
"Unit";"Zergling";"Larva";381;1
"Unit";"Zergling";"Larva";381;1
"Unit";"Zergling";"Larva";381;1
"Unit";"Zergling";"Larva";381;1
"Unit";"Zergling";"Larva";381;1
"Unit";"Zergling";"Larva";381;1
"Unit";"Zergling";"Larva";381;1
"Unit";"Zergling";"Larva";381;1
"Unit";"Zergling";"Larva";381;1
"Unit";"Zergling";"Larva";381;1
"Unit";"Zergling";"Larva";381;1
"Unit";"Zergling";"Larva";381;1
"Unit";"Zergling";"Larva";381;1
"Unit";"Zergling";"Larva";381;1
"Unit";"Zergling";"Larva";381;1
"Unit";"Zergling";"Larva";381;1
"Building";"CreepTumor";NA;409;0
"Building";"CreepTumor";NA;409;0
"Unit";"Zergling";"Larva";409;1
"Unit";"Zergling";"Larva";409;1
"Unit";"Zergling";"Larva";409;1
"Unit";"Zergling";"Larva";409;1
"Unit";"Zergling";"Larva";409;1
"Unit";"Zergling";"Larva";409;1
"Unit";"Zergling";"Larva";409;1
"Unit";"Zergling";"Larva";409;1
"Unit";"Zergling";"Larva";409;1
"Unit";"Zergling";"Larva";409;1
"Unit";"Zergling";"Larva";409;1
"Unit";"Zergling";"Larva";409;1
"Unit";"Zergling";"Larva";409;1
"Unit";"Zergling";"Larva";409;1
"Unit";"Zergling";"Larva";409;1
"Unit";"Zergling";"Larva";409;1
"Unit";"Baneling";"Zergling";421;0
"Unit";"Baneling";"Zergling";421;0
"Unit";"Baneling";"Zergling";421;0
"Unit";"Baneling";"Zergling";421;0
"Unit";"Baneling";"Zergling";421;0
"Unit";"Baneling";"Zergling";421;0
"Unit";"Baneling";"Zergling";421;0
"Unit";"Baneling";"Zergling";421;0
"Unit";"Baneling";"Zergling";421;0
"Unit";"Baneling";"Zergling";421;0
"Unit";"Baneling";"Zergling";421;0
"Unit";"Baneling";"Zergling";421;0
"Unit";"Baneling";"Zergling";421;0
"Unit";"Zergling";"Larva";423;1
"Unit";"Zergling";"Larva";423;1
"Unit";"Zergling";"Larva";427;1
"Unit";"Zergling";"Larva";427;1
"Unit";"Zergling";"Larva";427;1
"Unit";"Zergling";"Larva";427;1
"Unit";"Zergling";"Larva";433;1
"Unit";"Zergling";"Larva";433;1
"Unit";"Zergling";"Larva";433;1
"Unit";"Zergling";"Larva";433;1
"Unit";"Zergling";"Larva";435;1
"Unit";"Zergling";"Larva";435;1
"Unit";"Overlord";"Larva";437;0
"Unit";"Overlord";"Larva";437;0
"Unit";"Overlord";"Larva";437;0
"Unit";"Overlord";"Larva";437;0
"Unit";"Overlord";"Larva";437;0
"Unit";"Zergling";"Larva";449;1
"Unit";"Zergling";"Larva";449;1
"Unit";"Zergling";"Larva";449;1
"Unit";"Zergling";"Larva";449;1
"Unit";"Zergling";"Larva";449;1
"Unit";"Zergling";"Larva";449;1
"Unit";"Zergling";"Larva";449;1
"Unit";"Zergling";"Larva";449;1
"Unit";"Zergling";"Larva";449;1
"Unit";"Zergling";"Larva";449;1
"Unit";"Zergling";"Larva";449;1
"Unit";"Zergling";"Larva";449;1
"Unit";"Zergling";"Larva";449;1
"Unit";"Zergling";"Larva";449;1
"Unit";"Zergling";"Larva";449;1
"Unit";"Zergling";"Larva";449;1
"Unit";"Zergling";"Larva";449;1
"Unit";"Zergling";"Larva";449;1
"Unit";"Zergling";"Larva";449;1
"Unit";"Zergling";"Larva";449;1
"Unit";"Zergling";"Larva";449;1
"Unit";"Zergling";"Larva";449;1
"Unit";"Zergling";"Larva";449;1
"Unit";"Zergling";"Larva";449;1
"Unit";"Zergling";"Larva";449;1
"Unit";"Zergling";"Larva";449;1
"Unit";"Zergling";"Larva";449;1
"Unit";"Zergling";"Larva";449;1
"Unit";"Zergling";"Larva";449;1
"Unit";"Zergling";"Larva";449;1
"Unit";"Baneling";"Zergling";467;0
"Unit";"Zergling";"Larva";449;1
"Unit";"Zergling";"Larva";449;1
"Unit";"Zergling";"Larva";449;1
"Unit";"Zergling";"Larva";449;1
"Unit";"Zergling";"Larva";449;1
"Unit";"Zergling";"Larva";449;1
"Unit";"Zergling";"Larva";449;1
"Unit";"Zergling";"Larva";449;1
"Unit";"Baneling";"Zergling";467;0
"Unit";"Baneling";"Zergling";467;0
"Unit";"Zergling";"Larva";449;1
"Unit";"Zergling";"Larva";449;1
"Unit";"Zergling";"Larva";449;1
"Unit";"Zergling";"Larva";449;1
"Unit";"Zergling";"Larva";449;1
"Unit";"Zergling";"Larva";449;1
"Unit";"Zergling";"Larva";449;1
"Unit";"Zergling";"Larva";449;1
"Unit";"Baneling";"Zergling";467;0
"Unit";"Baneling";"Zergling";467;0
"Unit";"Baneling";"Zergling";467;0
"Unit";"Zergling";"Larva";449;1
"Unit";"Zergling";"Larva";449;1
"Unit";"Zergling";"Larva";449;1
"Unit";"Zergling";"Larva";449;1
"Building";"CreepTumorQueen";NA;477;0
"Building";"CreepTumor";NA;477;0
"Building";"CreepTumor";NA;477;0
"Building";"CreepTumor";NA;477;0
"Building";"Spire";NA;421;0
"Building";"CreepTumor";NA;499;0
"Building";"CreepTumor";NA;499;0
"Unit";"Zergling";"Larva";499;1
"Unit";"Zergling";"Larva";499;1
"Unit";"Zergling";"Larva";499;1
"Unit";"Zergling";"Larva";499;1
"Unit";"Zergling";"Larva";499;1
"Unit";"Zergling";"Larva";499;1
"Unit";"Zergling";"Larva";499;1
"Unit";"Zergling";"Larva";499;1
"Unit";"Zergling";"Larva";499;1
"Unit";"Zergling";"Larva";499;1
"Unit";"Zergling";"Larva";499;1
"Unit";"Zergling";"Larva";499;1
"Unit";"Baneling";"Zergling";499;0
"Unit";"Baneling";"Zergling";499;0
"Unit";"Baneling";"Zergling";499;0
"Unit";"Baneling";"Zergling";499;0
"Unit";"Baneling";"Zergling";499;0
"Unit";"Baneling";"Zergling";499;0
"Unit";"Baneling";"Zergling";499;0
"Unit";"Baneling";"Zergling";499;0
"Unit";"Baneling";"Zergling";499;0
"Unit";"Baneling";"Zergling";499;0
"Unit";"Baneling";"Zergling";499;0
"Unit";"Baneling";"Zergling";499;0
"Unit";"Baneling";"Zergling";499;0
"Unit";"Baneling";"Zergling";499;0
"Unit";"Zergling";"Larva";499;1
"Unit";"Zergling";"Larva";499;1
"Unit";"Baneling";"Zergling";499;0
"Unit";"Zergling";"Larva";499;1
"Unit";"Zergling";"Larva";499;1
"Unit";"Zergling";"Larva";499;1
"Unit";"Zergling";"Larva";499;1
"Unit";"Zergling";"Larva";499;1
"Unit";"Zergling";"Larva";499;1
"Unit";"Zergling";"Larva";499;1
"Unit";"Zergling";"Larva";499;1
"Unit";"Zergling";"Larva";499;1
"Unit";"Zergling";"Larva";499;1
"Unit";"Zergling";"Larva";499;1
"Unit";"Zergling";"Larva";499;1
"Unit";"Baneling";"Zergling";499;0
"Unit";"Baneling";"Zergling";499;0
"Unit";"Zergling";"Larva";499;1
"Unit";"Zergling";"Larva";499;1
"Unit";"Zergling";"Larva";499;1
"Unit";"Zergling";"Larva";499;1
"Unit";"Baneling";"Zergling";499;0
"Unit";"Baneling";"Zergling";499;0
"Unit";"Zergling";"Larva";499;1
"Unit";"Zergling";"Larva";499;1
"Unit";"Zergling";"Larva";499;1
"Unit";"Zergling";"Larva";499;1
"Unit";"Baneling";"Zergling";499;0
"Unit";"Baneling";"Zergling";499;0
"Unit";"Baneling";"Zergling";499;0
"Building";"CreepTumorQueen";NA;499;0
"Building";"Hatchery";NA;449;0
"Unit";"Zergling";"Larva";511;1
"Unit";"Zergling";"Larva";511;1
"Unit";"Zergling";"Larva";511;1
"Unit";"Zergling";"Larva";511;1
"Unit";"Zergling";"Larva";511;1
"Unit";"Zergling";"Larva";511;1
"Unit";"Zergling";"Larva";511;1
"Unit";"Zergling";"Larva";511;1
"Unit";"Zergling";"Larva";511;1
"Unit";"Zergling";"Larva";511;1
"Unit";"Zergling";"Larva";511;1
"Unit";"Zergling";"Larva";511;1
"Unit";"Zergling";"Larva";511;1
"Unit";"Zergling";"Larva";511;1
"Unit";"Zergling";"Larva";511;1
"Unit";"Zergling";"Larva";511;1
"Unit";"Zergling";"Larva";511;1
"Unit";"Zergling";"Larva";511;1
"Upgrade";"ZergGroundArmorsLevel3";"EvolutionChamber";421;0
"Building";"CreepTumorQueen";NA;551;0
"Unit";"Zergling";"Larva";551;1
"Unit";"Zergling";"Larva";551;1
"Unit";"Zergling";"Larva";551;1
"Unit";"Zergling";"Larva";551;1
"Unit";"Zergling";"Larva";551;1
"Unit";"Zergling";"Larva";551;1
"Unit";"Zergling";"Larva";551;1
"Unit";"Zergling";"Larva";551;1
"Unit";"Zergling";"Larva";551;1
"Unit";"Zergling";"Larva";551;1
"Unit";"Zergling";"Larva";551;1
"Unit";"Zergling";"Larva";551;1
"Unit";"Zergling";"Larva";551;1
"Unit";"Zergling";"Larva";551;1
"Upgrade";"ZergMeleeWeaponsLevel3";"EvolutionChamber";449;0
"Unit";"Zergling";"Larva";551;1
"Unit";"Zergling";"Larva";551;1
"Unit";"Zergling";"Larva";551;1
"Unit";"Zergling";"Larva";551;1
"Unit";"Zergling";"Larva";551;1
"Unit";"Zergling";"Larva";551;1
"Unit";"Zergling";"Larva";551;1
"Unit";"Zergling";"Larva";551;1
"Unit";"Zergling";"Larva";551;1
"Unit";"Zergling";"Larva";551;1
"Unit";"Zergling";"Larva";551;1
"Unit";"Zergling";"Larva";551;1
"Unit";"Zergling";"Larva";551;1
"Unit";"Zergling";"Larva";551;1
"Unit";"Zergling";"Larva";551;1
"Unit";"Zergling";"Larva";551;1
"Unit";"Zergling";"Larva";551;1
"Unit";"Zergling";"Larva";551;1
"Unit";"Zergling";"Larva";551;1
"Unit";"Zergling";"Larva";551;1
"Unit";"Zergling";"Larva";551;1
"Unit";"Zergling";"Larva";551;1
"Unit";"Zergling";"Larva";551;1
"Unit";"Zergling";"Larva";551;1
"Unit";"Zergling";"Larva";551;1
"Unit";"Zergling";"Larva";551;1
"Unit";"Zergling";"Larva";551;1
"Unit";"Zergling";"Larva";551;1
"Unit";"Zergling";"Larva";553;1
"Unit";"Zergling";"Larva";553;1
"Unit";"Zergling";"Larva";553;1
"Unit";"Zergling";"Larva";553;1
"Unit";"Zergling";"Larva";553;1
"Unit";"Zergling";"Larva";553;1
"Unit";"Zergling";"Larva";553;1
"Unit";"Zergling";"Larva";553;1
"Unit";"Zergling";"Larva";553;1
"Unit";"Zergling";"Larva";553;1
"Unit";"Zergling";"Larva";553;1
"Unit";"Zergling";"Larva";553;1
"Unit";"Zergling";"Larva";565;1
"Unit";"Zergling";"Larva";565;1
"Unit";"Zergling";"Larva";565;1
"Unit";"Zergling";"Larva";565;1
"Unit";"Zergling";"Larva";565;1
"Unit";"Zergling";"Larva";565;1
"Unit";"Zergling";"Larva";565;1
"Unit";"Zergling";"Larva";565;1
"Unit";"Zergling";"Larva";565;1
"Unit";"Zergling";"Larva";565;1
"Unit";"Zergling";"Larva";565;1
"Unit";"Zergling";"Larva";565;1
"Unit";"Zergling";"Larva";565;1
"Unit";"Zergling";"Larva";565;1
"Unit";"Zergling";"Larva";565;1
"Unit";"Zergling";"Larva";565;1
"Unit";"Zergling";"Larva";565;1
"Unit";"Zergling";"Larva";565;1
"Unit";"Zergling";"Larva";565;1
"Unit";"Zergling";"Larva";565;1
"Unit";"Zergling";"Larva";565;1
"Unit";"Zergling";"Larva";565;1
"Unit";"Zergling";"Larva";565;1
"Unit";"Zergling";"Larva";565;1
"Unit";"Zergling";"Larva";565;1
"Unit";"Zergling";"Larva";565;1
"Building";"CreepTumor";NA;565;0
"Building";"CreepTumorQueen";NA;605;0
"Unit";"Baneling";"Zergling";605;0
"Unit";"Baneling";"Zergling";605;0
"Unit";"Baneling";"Zergling";605;0
"Unit";"Baneling";"Zergling";605;0
"Unit";"Baneling";"Zergling";605;0
"Unit";"Baneling";"Zergling";605;0
"Unit";"Baneling";"Zergling";605;0
"Unit";"Baneling";"Zergling";605;0
"Unit";"Baneling";"Zergling";605;0
"Unit";"Baneling";"Zergling";605;0
"Unit";"Baneling";"Zergling";605;0
"Unit";"Baneling";"Zergling";605;0
"Unit";"Baneling";"Zergling";605;0
"Unit";"Baneling";"Zergling";605;0
"Unit";"Baneling";"Zergling";605;0
"Unit";"Baneling";"Zergling";605;0
"Unit";"Baneling";"Zergling";605;0
"Unit";"Baneling";"Zergling";605;0
"Unit";"Baneling";"Zergling";605;0
"Unit";"Baneling";"Zergling";605;0
"Unit";"Baneling";"Zergling";605;0
"Unit";"Baneling";"Zergling";605;0
"Unit";"Baneling";"Zergling";605;0
"Unit";"Baneling";"Zergling";605;0
"Unit";"Baneling";"Zergling";605;0
"Unit";"Baneling";"Zergling";605;0
"Unit";"Baneling";"Zergling";605;0
"Unit";"Baneling";"Zergling";605;0
"Unit";"Baneling";"Zergling";631;0
"Unit";"Baneling";"Zergling";631;0
"Unit";"Baneling";"Zergling";631;0
"Unit";"Baneling";"Zergling";631;0
"Unit";"Baneling";"Zergling";631;0
"Unit";"Baneling";"Zergling";631;0
"Unit";"Baneling";"Zergling";631;0
"Unit";"Baneling";"Zergling";631;0
"Unit";"Baneling";"Zergling";631;0
"Unit";"Baneling";"Zergling";631;0
"Unit";"Baneling";"Zergling";631;0
"Unit";"Baneling";"Zergling";631;0
"Unit";"Baneling";"Zergling";631;0
"Unit";"Baneling";"Zergling";631;0
"Unit";"Baneling";"Zergling";631;0
"Unit";"Baneling";"Zergling";631;0
"Unit";"Baneling";"Zergling";631;0
"Unit";"Baneling";"Zergling";631;0
"Unit";"Baneling";"Zergling";631;0
"Unit";"Baneling";"Zergling";631;0
"Unit";"Baneling";"Zergling";631;0
"Unit";"Baneling";"Zergling";631;0
"Unit";"Baneling";"Zergling";631;0
"Unit";"Baneling";"Zergling";631;0
"Unit";"Baneling";"Zergling";631;0
"Unit";"Baneling";"Zergling";631;0
"Unit";"Baneling";"Zergling";631;0
"Unit";"Baneling";"Zergling";631;0
"Unit";"Baneling";"Zergling";631;0
"Unit";"Baneling";"Zergling";631;0
"Unit";"Baneling";"Zergling";631;0
"Unit";"Baneling";"Zergling";631;0
"Unit";"Zergling";"Larva";631;1
"Unit";"Zergling";"Larva";631;1
"Unit";"Baneling";"Zergling";631;0
"Unit";"Zergling";"Larva";631;1
"Unit";"Zergling";"Larva";631;1
"Unit";"Zergling";"Larva";631;1
"Unit";"Zergling";"Larva";631;1
"Unit";"Zergling";"Larva";631;1
"Unit";"Zergling";"Larva";631;1
"Unit";"Baneling";"Zergling";631;0
"Unit";"Baneling";"Zergling";631;0
"Unit";"Baneling";"Zergling";631;0
"Unit";"Baneling";"Zergling";631;0
"Unit";"Baneling";"Zergling";631;0
"Unit";"Baneling";"Zergling";631;0
"Unit";"Baneling";"Zergling";631;0
"Unit";"Baneling";"Zergling";631;0
"Unit";"Baneling";"Zergling";631;0
"Unit";"Zergling";"Larva";639;1
"Unit";"Zergling";"Larva";639;1
"Unit";"Zergling";"Larva";639;1
"Unit";"Zergling";"Larva";639;1
"Unit";"Zergling";"Larva";639;1
"Unit";"Zergling";"Larva";639;1
"Unit";"Zergling";"Larva";639;1
"Unit";"Zergling";"Larva";639;1
"Unit";"Zergling";"Larva";639;1
"Unit";"Zergling";"Larva";639;1
"Unit";"Zergling";"Larva";639;1
"Unit";"Zergling";"Larva";639;1
"Unit";"Zergling";"Larva";639;1
"Unit";"Zergling";"Larva";639;1
"Unit";"Zergling";"Larva";639;1
"Unit";"Zergling";"Larva";639;1
"Unit";"Zergling";"Larva";639;1
"Unit";"Zergling";"Larva";639;1
"Unit";"Zergling";"Larva";639;1
"Unit";"Zergling";"Larva";639;1
"Unit";"Zergling";"Larva";639;1
"Unit";"Zergling";"Larva";639;1
"Unit";"Zergling";"Larva";639;1
"Unit";"Zergling";"Larva";639;1
"Unit";"Zergling";"Larva";639;1
"Unit";"Zergling";"Larva";639;1
"Unit";"Zergling";"Larva";639;1
"Unit";"Zergling";"Larva";639;1
"Unit";"Zergling";"Larva";639;1
"Unit";"Zergling";"Larva";639;1
"Upgrade";"Burrow";"Hatchery";631;0
"Unit";"Zergling";"Larva";639;1
"Unit";"Zergling";"Larva";639;1
"Unit";"Zergling";"Larva";639;1
"Unit";"Zergling";"Larva";639;1
"Unit";"Zergling";"Larva";639;1
"Unit";"Zergling";"Larva";639;1
"Unit";"Zergling";"Larva";639;1
"Unit";"Zergling";"Larva";639;1
"Unit";"Zergling";"Larva";639;1
"Unit";"Zergling";"Larva";639;1
"Unit";"Zergling";"Larva";639;1
"Unit";"Zergling";"Larva";639;1
"Unit";"Zergling";"Larva";639;1
"Unit";"Zergling";"Larva";639;1
"Unit";"Zergling";"Larva";639;1
"Unit";"Zergling";"Larva";639;1
"Unit";"Zergling";"Larva";639;1
"Unit";"Zergling";"Larva";639;1
"Unit";"Zergling";"Larva";639;1
"Unit";"Zergling";"Larva";639;1
"Unit";"Zergling";"Larva";639;1
"Unit";"Zergling";"Larva";639;1
"Unit";"Zergling";"Larva";639;1
"Unit";"Zergling";"Larva";639;1
"Unit";"Zergling";"Larva";639;1
"Unit";"Zergling";"Larva";639;1
"Unit";"Zergling";"Larva";639;1
"Unit";"Zergling";"Larva";639;1
"Unit";"Zergling";"Larva";639;1
"Unit";"Zergling";"Larva";639;1
"Building";"CreepTumor";NA;669;0
"Building";"CreepTumorQueen";NA;669;0
"Building";"CreepTumorQueen";NA;669;0
"Building";"CreepTumorQueen";NA;669;0
"Building";"CreepTumorQueen";NA;677;0
"Building";"CreepTumorQueen";NA;677;0
"Building";"CreepTumorQueen";NA;693;0
"Unit";"Baneling";"Zergling";677;0
"Unit";"Baneling";"Zergling";677;0
"Unit";"Baneling";"Zergling";677;0
"Unit";"Baneling";"Zergling";677;0
"Unit";"Baneling";"Zergling";677;0
"Unit";"Baneling";"Zergling";677;0
"Unit";"Baneling";"Zergling";677;0
"Unit";"Baneling";"Zergling";677;0
"Unit";"Baneling";"Zergling";677;0
"Unit";"Baneling";"Zergling";677;0
"Unit";"Baneling";"Zergling";677;0
"Unit";"Baneling";"Zergling";677;0
"Unit";"Baneling";"Zergling";677;0
"Unit";"Baneling";"Zergling";677;0
"Unit";"Baneling";"Zergling";677;0
"Unit";"Baneling";"Zergling";677;0
"Unit";"Baneling";"Zergling";677;0
"Unit";"Baneling";"Zergling";677;0
"Unit";"Baneling";"Zergling";677;0
"Building";"CreepTumor";NA;699;0
"Building";"CreepTumor";NA;699;0
"Unit";"Baneling";"Zergling";699;0
"Unit";"Baneling";"Zergling";699;0
"Unit";"Baneling";"Zergling";699;0
"Unit";"Baneling";"Zergling";699;0
"Unit";"Baneling";"Zergling";699;0
"Unit";"Baneling";"Zergling";699;0
"Unit";"Baneling";"Zergling";699;0
"Unit";"Baneling";"Zergling";699;0
"Unit";"Baneling";"Zergling";699;0
"Unit";"Baneling";"Zergling";699;0
"Unit";"Baneling";"Zergling";699;0
"Unit";"Baneling";"Zergling";699;0
"Unit";"Baneling";"Zergling";699;0
"Unit";"Baneling";"Zergling";699;0
"Building";"Extractor";NA;699;0
"Unit";"Baneling";"Zergling";699;0
"Unit";"Baneling";"Zergling";699;0
"Building";"Extractor";NA;699;0
"Unit";"Baneling";"Zergling";699;0
"Unit";"Baneling";"Zergling";699;0
"Unit";"Baneling";"Zergling";699;0
"Unit";"Baneling";"Zergling";699;0
"Unit";"Baneling";"Zergling";699;0
"Unit";"Baneling";"Zergling";699;0
"Unit";"Zergling";"Larva";709;1
"Unit";"Zergling";"Larva";709;1
"Unit";"Zergling";"Larva";709;1
"Unit";"Zergling";"Larva";709;1
"Unit";"Zergling";"Larva";709;1
"Unit";"Zergling";"Larva";709;1
"Unit";"Zergling";"Larva";709;1
"Unit";"Zergling";"Larva";709;1
"Unit";"Zergling";"Larva";709;1
"Unit";"Zergling";"Larva";709;1
"Unit";"Zergling";"Larva";709;1
"Unit";"Zergling";"Larva";709;1
"Unit";"Zergling";"Larva";709;1
"Unit";"Zergling";"Larva";709;1
"Unit";"Zergling";"Larva";709;1
"Unit";"Zergling";"Larva";709;1
"Unit";"Zergling";"Larva";709;1
"Unit";"Zergling";"Larva";709;1
"Unit";"Zergling";"Larva";709;1
"Unit";"Zergling";"Larva";709;1
"Unit";"Zergling";"Larva";709;1
"Unit";"Zergling";"Larva";709;1
"Unit";"Zergling";"Larva";709;1
"Unit";"Zergling";"Larva";709;1
"Unit";"Zergling";"Larva";709;1
"Unit";"Zergling";"Larva";709;1
"Unit";"Zergling";"Larva";709;1
"Unit";"Zergling";"Larva";709;1
"Unit";"Zergling";"Larva";709;1
"Unit";"Zergling";"Larva";709;1
"Unit";"Zergling";"Larva";709;1
"Unit";"Zergling";"Larva";709;1
"Unit";"Zergling";"Larva";709;1
"Unit";"Zergling";"Larva";709;1
"Unit";"Zergling";"Larva";709;1
"Unit";"Zergling";"Larva";709;1
"Unit";"Zergling";"Larva";709;1
"Unit";"Zergling";"Larva";709;1
"Unit";"Zergling";"Larva";709;1
"Unit";"Zergling";"Larva";709;1
"Building";"CreepTumor";NA;735;0
"Building";"CreepTumor";NA;735;0
"Building";"CreepTumor";NA;749;0
"Building";"CreepTumor";NA;749;0
"Building";"CreepTumor";NA;749;0
"Unit";"Zergling";"Larva";735;1
"Unit";"Zergling";"Larva";735;1
"Unit";"Zergling";"Larva";735;1
"Unit";"Zergling";"Larva";735;1
"Unit";"Zergling";"Larva";735;1
"Unit";"Zergling";"Larva";735;1
"Unit";"Zergling";"Larva";735;1
"Unit";"Zergling";"Larva";735;1
"Unit";"Zergling";"Larva";735;1
"Unit";"Zergling";"Larva";735;1
"Unit";"Zergling";"Larva";735;1
"Unit";"Zergling";"Larva";735;1
"Unit";"Zergling";"Larva";735;1
"Unit";"Zergling";"Larva";735;1
"Unit";"Zergling";"Larva";735;1
"Unit";"Zergling";"Larva";735;1
"Unit";"Zergling";"Larva";735;1
"Unit";"Zergling";"Larva";735;1
"Unit";"Zergling";"Larva";735;1
"Unit";"Zergling";"Larva";735;1
"Unit";"Zergling";"Larva";735;1
"Unit";"Zergling";"Larva";735;1
"Unit";"Zergling";"Larva";735;1
"Unit";"Zergling";"Larva";735;1
"Unit";"Zergling";"Larva";735;1
"Unit";"Zergling";"Larva";735;1
"Unit";"Zergling";"Larva";735;1
"Unit";"Zergling";"Larva";735;1
"Unit";"Zergling";"Larva";735;1
"Unit";"Zergling";"Larva";735;1
"Building";"CreepTumor";NA;749;0
"Building";"CreepTumor";NA;749;0
"Building";"CreepTumor";NA;749;0
"Building";"CreepTumor";NA;749;0
"Building";"CreepTumor";NA;749;0
"Unit";"Baneling";"Zergling";779;0
"Unit";"Baneling";"Zergling";779;0
"Unit";"Baneling";"Zergling";779;0
"Unit";"Baneling";"Zergling";779;0
"Unit";"Baneling";"Zergling";779;0
"Unit";"Baneling";"Zergling";779;0
"Unit";"Baneling";"Zergling";779;0
"Unit";"Baneling";"Zergling";779;0
"Unit";"Baneling";"Zergling";779;0
"Unit";"Baneling";"Zergling";779;0
"Unit";"Baneling";"Zergling";779;0
"Unit";"Baneling";"Zergling";779;0
"Unit";"Baneling";"Zergling";779;0
"Unit";"Baneling";"Zergling";779;0
"Unit";"Baneling";"Zergling";779;0
"Unit";"Baneling";"Zergling";779;0
"Unit";"Baneling";"Zergling";779;0
"Unit";"Baneling";"Zergling";779;0
"Unit";"Baneling";"Zergling";779;0
"Unit";"Baneling";"Zergling";779;0
"Unit";"Baneling";"Zergling";779;0
"Unit";"Zergling";"Larva";779;1
"Unit";"Zergling";"Larva";779;1
"Unit";"Zergling";"Larva";779;1
"Unit";"Zergling";"Larva";779;1
"Unit";"Zergling";"Larva";779;1
"Unit";"Zergling";"Larva";779;1
"Unit";"Zergling";"Larva";779;1
"Unit";"Zergling";"Larva";779;1
"Unit";"Zergling";"Larva";779;1
"Unit";"Zergling";"Larva";779;1
"Unit";"Zergling";"Larva";779;1
"Unit";"Zergling";"Larva";779;1
"Unit";"Zergling";"Larva";779;1
"Unit";"Zergling";"Larva";779;1
"Unit";"Zergling";"Larva";779;1
"Unit";"Zergling";"Larva";779;1
"Unit";"Zergling";"Larva";779;1
"Unit";"Zergling";"Larva";779;1
"Unit";"Zergling";"Larva";779;1
"Unit";"Zergling";"Larva";779;1
"Unit";"Zergling";"Larva";779;1
"Unit";"Zergling";"Larva";779;1
"Building";"Hatchery";NA;705;0
"Unit";"Baneling";"Zergling";779;0
"Unit";"Baneling";"Zergling";779;0
"Unit";"Baneling";"Zergling";779;0
"Unit";"Baneling";"Zergling";779;0
"Unit";"Baneling";"Zergling";779;0
"Unit";"Baneling";"Zergling";779;0
"Unit";"Baneling";"Zergling";779;0
"Unit";"Baneling";"Zergling";779;0
"Unit";"Baneling";"Zergling";779;0
"Unit";"Baneling";"Zergling";779;0
"Unit";"Baneling";"Zergling";779;0
"Unit";"Baneling";"Zergling";779;0
"Unit";"Baneling";"Zergling";779;0
"Unit";"Baneling";"Zergling";779;0
"Unit";"Baneling";"Zergling";779;0
"Unit";"Zergling";"Larva";801;1
"Unit";"Zergling";"Larva";801;1
"Unit";"Zergling";"Larva";801;1
"Unit";"Zergling";"Larva";801;1
"Unit";"Zergling";"Larva";801;1
"Unit";"Zergling";"Larva";801;1
"Unit";"Zergling";"Larva";801;1
"Unit";"Zergling";"Larva";801;1
"Unit";"Zergling";"Larva";801;1
"Unit";"Zergling";"Larva";801;1
"Unit";"Zergling";"Larva";801;1
"Unit";"Zergling";"Larva";801;1
"Unit";"Zergling";"Larva";801;1
"Unit";"Zergling";"Larva";801;1
"Unit";"Zergling";"Larva";801;1
"Unit";"Zergling";"Larva";801;1
"Unit";"Zergling";"Larva";801;1
"Unit";"Zergling";"Larva";801;1
"Unit";"Zergling";"Larva";801;1
"Unit";"Zergling";"Larva";801;1
"Unit";"Zergling";"Larva";801;1
"Unit";"Zergling";"Larva";801;1
"Unit";"Zergling";"Larva";801;1
"Unit";"Zergling";"Larva";801;1
"Unit";"Zergling";"Larva";801;1
"Unit";"Zergling";"Larva";801;1
"Unit";"Zergling";"Larva";801;1
"Unit";"Zergling";"Larva";801;1
"Unit";"Zergling";"Larva";801;1
"Unit";"Zergling";"Larva";801;1
"Unit";"Zergling";"Larva";801;1
"Unit";"Zergling";"Larva";801;1
"Unit";"Zergling";"Larva";801;1
"Unit";"Zergling";"Larva";801;1
"Unit";"Zergling";"Larva";801;1
"Unit";"Zergling";"Larva";801;1
"Unit";"Zergling";"Larva";801;1
"Unit";"Zergling";"Larva";801;1
"Unit";"Zergling";"Larva";801;1
"Unit";"Zergling";"Larva";801;1
"Unit";"Zergling";"Larva";801;1
"Unit";"Zergling";"Larva";801;1
"Unit";"Zergling";"Larva";801;1
"Unit";"Zergling";"Larva";801;1
"Unit";"Zergling";"Larva";801;1
"Unit";"Zergling";"Larva";801;1
"Unit";"Zergling";"Larva";801;1
"Unit";"Zergling";"Larva";801;1
"Unit";"Zergling";"Larva";801;1
"Unit";"Zergling";"Larva";801;1
"Unit";"Zergling";"Larva";801;1
"Unit";"Zergling";"Larva";801;1
"Unit";"Zergling";"Larva";801;1
"Unit";"Zergling";"Larva";801;1
"Unit";"Zergling";"Larva";801;1
"Unit";"Zergling";"Larva";801;1
"Unit";"Zergling";"Larva";801;1
"Unit";"Zergling";"Larva";801;1
"Unit";"Zergling";"Larva";801;1
"Unit";"Zergling";"Larva";801;1
"Unit";"Baneling";"Zergling";801;0
"Unit";"Baneling";"Zergling";801;0
"Unit";"Baneling";"Zergling";801;0
"Unit";"Baneling";"Zergling";801;0
"Unit";"Baneling";"Zergling";801;0
"Unit";"Baneling";"Zergling";801;0
"Unit";"Baneling";"Zergling";801;0
"Unit";"Baneling";"Zergling";803;0
"Unit";"Baneling";"Zergling";803;0
"Unit";"Baneling";"Zergling";803;0
"Unit";"Baneling";"Zergling";803;0
"Unit";"Baneling";"Zergling";803;0
"Unit";"Baneling";"Zergling";803;0
"Unit";"Baneling";"Zergling";803;0
"Unit";"Baneling";"Zergling";805;0
"Unit";"Baneling";"Zergling";805;0
"Unit";"Baneling";"Zergling";807;0
"Unit";"Baneling";"Zergling";807;0
"Unit";"Baneling";"Zergling";807;0
"Building";"CreepTumor";NA;807;0
"Building";"CreepTumor";NA;845;0
"Building";"CreepTumor";NA;845;0
"Building";"CreepTumor";NA;847;0
"Building";"CreepTumor";NA;861;0
"Building";"CreepTumor";NA;847;0
"Building";"CreepTumor";NA;853;0
"Building";"CreepTumor";NA;861;0
"Building";"CreepTumor";NA;861;0
"Unit";"Zergling";"Larva";861;1
"Unit";"Zergling";"Larva";861;1
"Unit";"Zergling";"Larva";861;1
"Unit";"Zergling";"Larva";861;1
"Unit";"Zergling";"Larva";861;1
"Unit";"Zergling";"Larva";861;1
"Unit";"Zergling";"Larva";861;1
"Unit";"Zergling";"Larva";861;1
"Unit";"Zergling";"Larva";861;1
"Unit";"Zergling";"Larva";861;1
"Unit";"Zergling";"Larva";861;1
"Unit";"Zergling";"Larva";861;1
"Unit";"Zergling";"Larva";861;1
"Unit";"Zergling";"Larva";861;1
"Unit";"Zergling";"Larva";861;1
"Unit";"Zergling";"Larva";861;1
"Unit";"Zergling";"Larva";861;1
"Unit";"Zergling";"Larva";861;1
"Unit";"Zergling";"Larva";861;1
"Unit";"Zergling";"Larva";861;1
"Unit";"Zergling";"Larva";861;1
"Unit";"Zergling";"Larva";861;1
"Unit";"Zergling";"Larva";861;1
"Unit";"Zergling";"Larva";861;1
"Unit";"Zergling";"Larva";861;1
"Unit";"Zergling";"Larva";861;1
"Unit";"Zergling";"Larva";861;1
"Unit";"Zergling";"Larva";861;1
"Unit";"Baneling";"Zergling";861;0
"Unit";"Baneling";"Zergling";861;0
"Unit";"Baneling";"Zergling";861;0
"Unit";"Baneling";"Zergling";861;0
"Unit";"Baneling";"Zergling";861;0
"Unit";"Baneling";"Zergling";861;0
"Unit";"Baneling";"Zergling";861;0
"Unit";"Baneling";"Zergling";861;0
"Unit";"Baneling";"Zergling";861;0
"Unit";"Baneling";"Zergling";861;0
"Unit";"Baneling";"Zergling";861;0
"Unit";"Zergling";"Larva";861;1
"Unit";"Zergling";"Larva";861;1
"Unit";"Zergling";"Larva";861;1
"Unit";"Zergling";"Larva";861;1
"Unit";"Zergling";"Larva";861;1
"Unit";"Zergling";"Larva";861;1
"Unit";"Zergling";"Larva";861;1
"Unit";"Zergling";"Larva";861;1
"Unit";"Zergling";"Larva";861;1
"Unit";"Zergling";"Larva";861;1
"Unit";"Baneling";"Zergling";861;0
"Unit";"Baneling";"Zergling";861;0
"Unit";"Baneling";"Zergling";861;0
"Unit";"Baneling";"Zergling";861;0
"Unit";"Baneling";"Zergling";861;0
"Unit";"Baneling";"Zergling";861;0
"Unit";"Baneling";"Zergling";861;0
"Unit";"Baneling";"Zergling";861;0
"Unit";"Zergling";"Larva";899;1
"Unit";"Zergling";"Larva";899;1
"Unit";"Zergling";"Larva";899;1
"Unit";"Zergling";"Larva";899;1
"Unit";"Zergling";"Larva";899;1
"Unit";"Zergling";"Larva";899;1
"Unit";"Zergling";"Larva";899;1
"Unit";"Zergling";"Larva";899;1
"Unit";"Zergling";"Larva";899;1
"Unit";"Zergling";"Larva";899;1
"Unit";"Zergling";"Larva";899;1
"Unit";"Zergling";"Larva";899;1
"Unit";"Zergling";"Larva";899;1
"Unit";"Zergling";"Larva";899;1
"Unit";"Zergling";"Larva";899;1
"Unit";"Zergling";"Larva";899;1
"Unit";"Zergling";"Larva";899;1
"Unit";"Zergling";"Larva";899;1
"Unit";"Zergling";"Larva";899;1
"Unit";"Zergling";"Larva";899;1
"Unit";"Zergling";"Larva";899;1
"Unit";"Zergling";"Larva";899;1
"Unit";"Zergling";"Larva";899;1
"Unit";"Zergling";"Larva";899;1
"Unit";"Zergling";"Larva";899;1
"Unit";"Zergling";"Larva";899;1
"Unit";"Zergling";"Larva";899;1
"Unit";"Zergling";"Larva";899;1
"Unit";"Zergling";"Larva";899;1
"Unit";"Zergling";"Larva";899;1
"Unit";"Zergling";"Larva";899;1
"Unit";"Zergling";"Larva";899;1
"Unit";"Zergling";"Larva";899;1
"Unit";"Zergling";"Larva";899;1
"Unit";"Zergling";"Larva";899;1
"Unit";"Zergling";"Larva";899;1
"Unit";"Zergling";"Larva";901;1
"Unit";"Zergling";"Larva";901;1
"Unit";"Zergling";"Larva";901;1
"Unit";"Zergling";"Larva";901;1
"Unit";"Zergling";"Larva";901;1
"Unit";"Zergling";"Larva";901;1
"Unit";"Zergling";"Larva";901;1
"Unit";"Zergling";"Larva";901;1
"Unit";"Zergling";"Larva";901;1
"Unit";"Zergling";"Larva";901;1
"Unit";"Zergling";"Larva";901;1
"Unit";"Zergling";"Larva";901;1
"Unit";"Zergling";"Larva";901;1
"Unit";"Zergling";"Larva";901;1
"Unit";"Zergling";"Larva";903;1
"Unit";"Zergling";"Larva";903;1
"Unit";"Zergling";"Larva";903;1
"Unit";"Zergling";"Larva";903;1
"Unit";"Zergling";"Larva";907;1
"Unit";"Zergling";"Larva";907;1
"Unit";"Zergling";"Larva";907;1
"Unit";"Zergling";"Larva";907;1
"Unit";"Zergling";"Larva";911;1
"Unit";"Zergling";"Larva";911;1
"Unit";"Zergling";"Larva";911;1
"Unit";"Zergling";"Larva";911;1
"Unit";"Zergling";"Larva";915;1
"Unit";"Zergling";"Larva";915;1
"Unit";"Zergling";"Larva";915;1
"Unit";"Zergling";"Larva";915;1
"Building";"CreepTumor";NA;933;0
"Unit";"Zergling";"Larva";965;1
"Unit";"Zergling";"Larva";965;1
"Unit";"Zergling";"Larva";965;1
"Unit";"Zergling";"Larva";965;1
"Unit";"Zergling";"Larva";965;1
"Unit";"Zergling";"Larva";965;1
"Unit";"Zergling";"Larva";965;1
"Unit";"Zergling";"Larva";965;1
"Unit";"Zergling";"Larva";965;1
"Unit";"Zergling";"Larva";965;1
"Unit";"Zergling";"Larva";965;1
"Unit";"Zergling";"Larva";965;1
"Unit";"Zergling";"Larva";965;1
"Unit";"Zergling";"Larva";965;1
"Unit";"Zergling";"Larva";965;1
"Unit";"Zergling";"Larva";965;1
"Unit";"Zergling";"Larva";965;1
"Unit";"Zergling";"Larva";965;1
"Unit";"Zergling";"Larva";965;1
"Unit";"Zergling";"Larva";965;1
"Unit";"Zergling";"Larva";965;1
"Unit";"Zergling";"Larva";965;1
"Unit";"Zergling";"Larva";965;1
"Unit";"Zergling";"Larva";965;1
"Unit";"Zergling";"Larva";965;1
"Unit";"Zergling";"Larva";965;1
"Unit";"Zergling";"Larva";965;1
"Unit";"Zergling";"Larva";965;1
"Unit";"Overlord";"Larva";965;0
"Unit";"Overlord";"Larva";965;0
"Unit";"Overlord";"Larva";965;0
"Unit";"Overlord";"Larva";965;0
"Unit";"Overlord";"Larva";965;0
"Unit";"Corruptor";"Larva";965;2
"Unit";"Corruptor";"Larva";965;2
"Unit";"Corruptor";"Larva";965;2
"Unit";"Corruptor";"Larva";965;2
"Unit";"Corruptor";"Larva";965;2
"Unit";"Corruptor";"Larva";965;2
"Unit";"Corruptor";"Larva";993;2
"Unit";"Corruptor";"Larva";993;2
"Unit";"Corruptor";"Larva";993;2
"Unit";"Corruptor";"Larva";1005;2
"Unit";"Corruptor";"Larva";1005;2
"Unit";"Corruptor";"Larva";1005;2
"Unit";"Corruptor";"Larva";1005;2
"Unit";"Corruptor";"Larva";1005;2
"Unit";"Corruptor";"Larva";1005;2
"Unit";"Zergling";"Larva";1011;1
"Unit";"Zergling";"Larva";1011;1
"Unit";"Zergling";"Larva";1011;1
"Unit";"Zergling";"Larva";1011;1
"Unit";"Zergling";"Larva";1011;1
"Unit";"Zergling";"Larva";1011;1
"Unit";"Zergling";"Larva";1011;1
"Unit";"Zergling";"Larva";1011;1
"Unit";"Zergling";"Larva";1011;1
"Unit";"Zergling";"Larva";1011;1
"Unit";"Zergling";"Larva";1011;1
"Unit";"Zergling";"Larva";1011;1
"Unit";"Zergling";"Larva";1011;1
"Unit";"Zergling";"Larva";1011;1
"Unit";"Zergling";"Larva";1011;1
"Unit";"Zergling";"Larva";1011;1
"Unit";"Zergling";"Larva";1011;1
"Unit";"Zergling";"Larva";1011;1
"Unit";"Zergling";"Larva";1011;1
"Unit";"Zergling";"Larva";1011;1
"Unit";"Zergling";"Larva";1011;1
"Unit";"Zergling";"Larva";1011;1
"Unit";"Zergling";"Larva";1011;1
"Unit";"Zergling";"Larva";1011;1
"Unit";"Zergling";"Larva";1011;1
"Unit";"Zergling";"Larva";1011;1
"Unit";"Zergling";"Larva";1011;1
"Unit";"Zergling";"Larva";1011;1
"Unit";"Zergling";"Larva";1011;1
"Unit";"Zergling";"Larva";1011;1
"Unit";"Zergling";"Larva";1011;1
"Unit";"Zergling";"Larva";1011;1
"Unit";"Zergling";"Larva";1011;1
"Unit";"Zergling";"Larva";1011;1
"Unit";"Zergling";"Larva";1011;1
"Unit";"Zergling";"Larva";1011;1
"Unit";"Zergling";"Larva";1011;1
"Unit";"Zergling";"Larva";1011;1
"Unit";"Zergling";"Larva";1011;1
"Unit";"Zergling";"Larva";1011;1
"Unit";"Zergling";"Larva";1011;1
"Unit";"Zergling";"Larva";1011;1
"Unit";"Zergling";"Larva";1011;1
"Unit";"Zergling";"Larva";1011;1
"Unit";"Zergling";"Larva";1011;1
"Unit";"Zergling";"Larva";1011;1
"Unit";"Zergling";"Larva";1011;1
"Unit";"Zergling";"Larva";1011;1
"Unit";"Zergling";"Larva";1011;1
"Unit";"Zergling";"Larva";1011;1
"Unit";"Zergling";"Larva";1011;1
"Unit";"Zergling";"Larva";1011;1
"Unit";"Zergling";"Larva";1011;1
"Unit";"Zergling";"Larva";1011;1
"Unit";"Zergling";"Larva";1011;1
"Unit";"Zergling";"Larva";1011;1
"Unit";"Zergling";"Larva";1011;1
"Unit";"Zergling";"Larva";1011;1
"Unit";"Zergling";"Larva";1061;1
"Unit";"Zergling";"Larva";1061;1
"Unit";"Zergling";"Larva";1061;1
"Unit";"Zergling";"Larva";1061;1
"Unit";"Zergling";"Larva";1061;1
"Unit";"Zergling";"Larva";1061;1
"Unit";"Zergling";"Larva";1061;1
"Unit";"Zergling";"Larva";1061;1
"Unit";"Zergling";"Larva";1061;1
"Unit";"Zergling";"Larva";1061;1
"Unit";"Zergling";"Larva";1061;1
"Unit";"Zergling";"Larva";1061;1
"Unit";"Zergling";"Larva";1061;1
"Unit";"Zergling";"Larva";1061;1
"Unit";"Zergling";"Larva";1061;1
"Unit";"Zergling";"Larva";1061;1
"Unit";"Baneling";"Zergling";1081;0
"Unit";"Baneling";"Zergling";1081;0
"Unit";"Baneling";"Zergling";1081;0
"Unit";"Baneling";"Zergling";1081;0
"Unit";"Baneling";"Zergling";1081;0
"Unit";"Baneling";"Zergling";1081;0
"Unit";"Baneling";"Zergling";1081;0
"Unit";"Baneling";"Zergling";1081;0
"Unit";"Baneling";"Zergling";1081;0
"Unit";"Baneling";"Zergling";1081;0
"Unit";"Baneling";"Zergling";1081;0
"Unit";"Baneling";"Zergling";1081;0
"Unit";"Baneling";"Zergling";1081;0
"Unit";"Baneling";"Zergling";1081;0
"Unit";"Baneling";"Zergling";1081;0
"Unit";"Baneling";"Zergling";1081;0
"Unit";"Baneling";"Zergling";1081;0
"Unit";"Baneling";"Zergling";1081;0
"Unit";"Baneling";"Zergling";1081;0
"Building";"Hatchery";NA;993;0
"Unit";"Baneling";"Zergling";1081;0
"Unit";"Baneling";"Zergling";1081;0
"Unit";"Baneling";"Zergling";1081;0
"Building";"CreepTumor";NA;1097;0
"Building";"CreepTumor";NA;1097;0
"Unit";"Zergling";"Larva";1081;1
"Unit";"Zergling";"Larva";1081;1
"Unit";"Zergling";"Larva";1081;1
"Unit";"Zergling";"Larva";1081;1
"Unit";"Zergling";"Larva";1081;1
"Unit";"Zergling";"Larva";1081;1
"Unit";"Zergling";"Larva";1081;1
"Unit";"Zergling";"Larva";1081;1
"Unit";"Zergling";"Larva";1081;1
"Unit";"Zergling";"Larva";1081;1
"Unit";"Zergling";"Larva";1081;1
"Unit";"Zergling";"Larva";1081;1
"Unit";"Zergling";"Larva";1097;1
"Unit";"Zergling";"Larva";1097;1
"Unit";"Zergling";"Larva";1097;1
"Unit";"Zergling";"Larva";1097;1
"Unit";"Zergling";"Larva";1097;1
"Unit";"Zergling";"Larva";1097;1
"Unit";"Zergling";"Larva";1097;1
"Unit";"Zergling";"Larva";1097;1
"Unit";"Zergling";"Larva";1097;1
"Unit";"Zergling";"Larva";1097;1
"Unit";"Zergling";"Larva";1097;1
"Unit";"Zergling";"Larva";1097;1
"Unit";"Zergling";"Larva";1097;1
"Unit";"Zergling";"Larva";1097;1
"Unit";"Zergling";"Larva";1097;1
"Unit";"Zergling";"Larva";1097;1
"Unit";"Zergling";"Larva";1097;1
"Unit";"Zergling";"Larva";1097;1
"Unit";"Zergling";"Larva";1127;1
"Unit";"Zergling";"Larva";1127;1
"Unit";"Zergling";"Larva";1127;1
"Unit";"Zergling";"Larva";1127;1
"Unit";"Zergling";"Larva";1127;1
"Unit";"Zergling";"Larva";1127;1
"Unit";"Zergling";"Larva";1127;1
"Unit";"Zergling";"Larva";1127;1
"Unit";"Zergling";"Larva";1127;1
"Unit";"Zergling";"Larva";1127;1
"Unit";"Zergling";"Larva";1127;1
"Unit";"Zergling";"Larva";1127;1
"Unit";"Zergling";"Larva";1127;1
"Unit";"Zergling";"Larva";1127;1
"Unit";"Zergling";"Larva";1127;1
"Unit";"Zergling";"Larva";1127;1
"Unit";"Zergling";"Larva";1127;1
"Unit";"Zergling";"Larva";1127;1
"Unit";"Zergling";"Larva";1127;1
"Unit";"Zergling";"Larva";1127;1
"Unit";"Zergling";"Larva";1127;1
"Unit";"Zergling";"Larva";1127;1
"Unit";"Zergling";"Larva";1127;1
"Unit";"Zergling";"Larva";1127;1
"Unit";"Zergling";"Larva";1127;1
"Unit";"Zergling";"Larva";1127;1
"Unit";"Zergling";"Larva";1127;1
"Unit";"Zergling";"Larva";1127;1
"Unit";"Baneling";"Zergling";1127;0
"Unit";"Baneling";"Zergling";1127;0
"Unit";"Baneling";"Zergling";1127;0
"Unit";"Baneling";"Zergling";1127;0
"Unit";"Baneling";"Zergling";1127;0
"Unit";"Baneling";"Zergling";1127;0
"Unit";"Baneling";"Zergling";1127;0
"Unit";"Baneling";"Zergling";1127;0
"Unit";"Baneling";"Zergling";1127;0
"Unit";"Baneling";"Zergling";1127;0
"Unit";"Baneling";"Zergling";1127;0
"Unit";"Baneling";"Zergling";1127;0
"Unit";"Baneling";"Zergling";1127;0
"Unit";"Baneling";"Zergling";1127;0
"Unit";"Baneling";"Zergling";1127;0
"Unit";"Baneling";"Zergling";1127;0
"Unit";"Baneling";"Zergling";1127;0
"Unit";"Baneling";"Zergling";1127;0
"Unit";"Baneling";"Zergling";1127;0
"Unit";"Baneling";"Zergling";1127;0
"Unit";"Baneling";"Zergling";1127;0
"Unit";"Baneling";"Zergling";1127;0
"Unit";"Baneling";"Zergling";1127;0
"Unit";"Baneling";"Zergling";1127;0
"Unit";"Zergling";"Larva";1155;1
"Unit";"Zergling";"Larva";1155;1
"Unit";"Zergling";"Larva";1155;1
"Unit";"Zergling";"Larva";1155;1
"Unit";"Zergling";"Larva";1155;1
"Unit";"Zergling";"Larva";1155;1
"Unit";"Zergling";"Larva";1155;1
"Unit";"Zergling";"Larva";1155;1
"Unit";"Zergling";"Larva";1155;1
"Unit";"Zergling";"Larva";1155;1
"Unit";"Zergling";"Larva";1155;1
"Unit";"Zergling";"Larva";1155;1
"Unit";"Zergling";"Larva";1155;1
"Unit";"Zergling";"Larva";1155;1
"Unit";"Zergling";"Larva";1155;1
"Unit";"Zergling";"Larva";1155;1
"Unit";"Zergling";"Larva";1155;1
"Unit";"Zergling";"Larva";1155;1
"Unit";"Zergling";"Larva";1155;1
"Unit";"Zergling";"Larva";1155;1
"Unit";"Zergling";"Larva";1155;1
"Unit";"Zergling";"Larva";1155;1
"Unit";"Zergling";"Larva";1155;1
"Unit";"Zergling";"Larva";1155;1
"Unit";"Zergling";"Larva";1155;1
"Unit";"Zergling";"Larva";1155;1
"Unit";"Zergling";"Larva";1155;1
"Unit";"Zergling";"Larva";1155;1
"Unit";"Zergling";"Larva";1155;1
"Unit";"Zergling";"Larva";1155;1
"Unit";"Zergling";"Larva";1155;1
"Unit";"Zergling";"Larva";1155;1
"Unit";"Zergling";"Larva";1155;1
"Unit";"Zergling";"Larva";1155;1
"Building";"CreepTumor";NA;1189;0
"Building";"CreepTumor";NA;1189;0
"Building";"CreepTumor";NA;1189;0
"Building";"CreepTumor";NA;1189;0
"Unit";"Corruptor";"Larva";1189;2
"Unit";"Corruptor";"Larva";1189;2
"Unit";"Corruptor";"Larva";1189;2
"Unit";"Corruptor";"Larva";1189;2
"Unit";"Corruptor";"Larva";1189;2
"Unit";"Corruptor";"Larva";1189;2
"Unit";"Corruptor";"Larva";1189;2
"Unit";"Corruptor";"Larva";1189;2
"Unit";"Corruptor";"Larva";1189;2
"Unit";"Corruptor";"Larva";1189;2
"Unit";"Corruptor";"Larva";1189;2
"Unit";"Corruptor";"Larva";1189;2
"Unit";"Corruptor";"Larva";1189;2
"Unit";"Corruptor";"Larva";1189;2
"Building";"CreepTumorQueen";NA;1217;0
"Unit";"Corruptor";"Larva";1189;2
"Unit";"Corruptor";"Larva";1189;2
"Unit";"Corruptor";"Larva";1189;2
"Unit";"Corruptor";"Larva";1189;2
"Unit";"Corruptor";"Larva";1189;2
"Unit";"Corruptor";"Larva";1189;2
"Unit";"Corruptor";"Larva";1189;2
"Unit";"Corruptor";"Larva";1189;2
"Building";"Extractor";NA;1217;0
"Building";"Extractor";NA;1217;0
"Building";"Extractor";NA;1217;0
"Building";"Extractor";NA;1217;0
"Unit";"Corruptor";"Larva";1217;2
