"type";"unit_name";"on_building";"total_supply";"supply"
"Unit";"Overlord";"Larva";12;0
"Building";"Extractor";NA;18;0
"Unit";"Overlord";"Larva";21;0
"Building";"SpawningPool";NA;19;0
"Building";"Hatchery";NA;17;0
"Unit";"Zergling";"Larva";23;1
"Unit";"Zergling";"Larva";23;1
"Unit";"Zergling";"Larva";23;1
"Unit";"Zergling";"Larva";23;1
"Unit";"Queen";"Hatchery";23;2
"Unit";"Queen";"Hatchery";23;2
"Unit";"Overlord";"Larva";36;0
"Unit";"Queen";"Hatchery";35;2
"Building";"CreepTumorQueen";NA;39;0
"Unit";"Overlord";"Larva";49;0
"Unit";"Overlord";"Larva";49;0
"Building";"CreepTumor";NA;49;0
"Building";"CreepTumorQueen";NA;49;0
"Unit";"Zergling";"Larva";51;1
"Unit";"Zergling";"Larva";51;1
"Unit";"Zergling";"Larva";51;1
"Unit";"Zergling";"Larva";51;1
"Unit";"Zergling";"Larva";51;1
"Unit";"Zergling";"Larva";51;1
"Unit";"Zergling";"Larva";51;1
"Unit";"Zergling";"Larva";51;1
"Unit";"Zergling";"Larva";51;1
"Unit";"Zergling";"Larva";51;1
"Unit";"Zergling";"Larva";51;1
"Unit";"Zergling";"Larva";51;1
"Unit";"Zergling";"Larva";51;1
"Unit";"Zergling";"Larva";51;1
"Unit";"Zergling";"Larva";51;1
"Unit";"Zergling";"Larva";51;1
"Building";"BanelingNest";NA;49;0
"Building";"Hatchery";NA;49;0
"Building";"CreepTumor";NA;67;0
"Unit";"Overlord";"Larva";67;0
"Unit";"Overlord";"Larva";67;0
"Unit";"Overlord";"Larva";67;0
"Unit";"Overlord";"Larva";67;0
"Building";"Extractor";NA;67;0
"Building";"RoachWarren";NA;67;0
"Building";"CreepTumor";NA;74;0
"Building";"Extractor";NA;74;0
"Building";"Extractor";NA;74;0
"Unit";"Roach";"Larva";74;2
"Unit";"Roach";"Larva";74;2
"Unit";"Roach";"Larva";74;2
"Unit";"Roach";"Larva";74;2
"Unit";"Roach";"Larva";74;2
"Unit";"Roach";"Larva";74;2
"Unit";"Roach";"Larva";74;2
"Unit";"Roach";"Larva";74;2
"Unit";"Roach";"Larva";74;2
"Unit";"Roach";"Larva";74;2
"Unit";"Roach";"Larva";74;2
"Unit";"Roach";"Larva";74;2
"Building";"CreepTumor";NA;74;0
"Building";"CreepTumor";NA;74;0
"Unit";"Roach";"Larva";74;2
"Unit";"Roach";"Larva";74;2
"Unit";"Roach";"Larva";74;2
"Unit";"Roach";"Larva";74;2
"Unit";"Roach";"Larva";74;2
"Unit";"Zergling";"Larva";102;1
"Unit";"Zergling";"Larva";102;1
"Unit";"Zergling";"Larva";102;1
"Unit";"Zergling";"Larva";102;1
"Unit";"Zergling";"Larva";102;1
"Unit";"Zergling";"Larva";102;1
"Unit";"Zergling";"Larva";102;1
"Unit";"Zergling";"Larva";102;1
"Unit";"Baneling";"Zergling";112;0
"Unit";"Baneling";"Zergling";112;0
"Unit";"Baneling";"Zergling";112;0
"Unit";"Baneling";"Zergling";112;0
"Unit";"Baneling";"Zergling";112;0
"Unit";"Baneling";"Zergling";112;0
"Unit";"Overlord";"Larva";102;0
"Unit";"Overlord";"Larva";104;0
"Unit";"Overlord";"Larva";106;0
"Unit";"Baneling";"Zergling";112;0
"Unit";"Baneling";"Zergling";112;0
"Unit";"Baneling";"Zergling";112;0
"Building";"CreepTumor";NA;112;0
"Building";"CreepTumor";NA;112;0
"Unit";"Baneling";"Zergling";112;0
"Unit";"Baneling";"Zergling";112;0
"Unit";"Baneling";"Zergling";112;0
"Unit";"Baneling";"Zergling";112;0
"Unit";"Baneling";"Zergling";112;0
"Unit";"Zergling";"Larva";120;1
"Unit";"Zergling";"Larva";120;1
"Unit";"Zergling";"Larva";120;1
"Unit";"Zergling";"Larva";120;1
"Unit";"Zergling";"Larva";120;1
"Unit";"Zergling";"Larva";120;1
"Unit";"Zergling";"Larva";120;1
"Unit";"Zergling";"Larva";120;1
"Unit";"Zergling";"Larva";120;1
"Unit";"Zergling";"Larva";120;1
"Unit";"Zergling";"Larva";130;1
"Unit";"Zergling";"Larva";130;1
"Unit";"Zergling";"Larva";130;1
"Unit";"Zergling";"Larva";130;1
"Unit";"Zergling";"Larva";130;1
"Unit";"Zergling";"Larva";130;1
"Unit";"Zergling";"Larva";130;1
"Unit";"Zergling";"Larva";130;1
"Unit";"Zergling";"Larva";130;1
"Unit";"Zergling";"Larva";130;1
"Unit";"Zergling";"Larva";130;1
"Unit";"Zergling";"Larva";130;1
"Unit";"Zergling";"Larva";130;1
"Unit";"Zergling";"Larva";130;1
"Unit";"Zergling";"Larva";130;1
"Unit";"Zergling";"Larva";130;1
"Unit";"Zergling";"Larva";130;1
"Unit";"Zergling";"Larva";130;1
"Unit";"Zergling";"Larva";130;1
"Unit";"Zergling";"Larva";130;1
"Unit";"Zergling";"Larva";130;1
"Unit";"Zergling";"Larva";130;1
"Unit";"Zergling";"Larva";130;1
"Unit";"Zergling";"Larva";130;1
"Unit";"Zergling";"Larva";154;1
"Unit";"Zergling";"Larva";154;1
"Unit";"Zergling";"Larva";154;1
"Unit";"Zergling";"Larva";154;1
"Unit";"Zergling";"Larva";154;1
"Unit";"Zergling";"Larva";154;1
"Building";"CreepTumorQueen";NA;159;0
"Building";"CreepTumor";NA;159;0
"Building";"CreepTumor";NA;159;0
"Unit";"Zergling";"Larva";159;1
"Unit";"Zergling";"Larva";159;1
"Unit";"Overlord";"Larva";159;0
"Unit";"Zergling";"Larva";159;1
"Unit";"Zergling";"Larva";159;1
"Unit";"Zergling";"Larva";159;1
"Unit";"Zergling";"Larva";159;1
"Unit";"Zergling";"Larva";159;1
"Unit";"Zergling";"Larva";159;1
"Unit";"Zergling";"Larva";159;1
"Unit";"Zergling";"Larva";159;1
"Unit";"Zergling";"Larva";159;1
"Unit";"Zergling";"Larva";159;1
"Building";"EvolutionChamber";NA;159;0
"Building";"EvolutionChamber";NA;159;0
"Unit";"Baneling";"Zergling";165;0
"Unit";"Baneling";"Zergling";165;0
"Unit";"Baneling";"Zergling";165;0
"Unit";"Baneling";"Zergling";165;0
"Unit";"Baneling";"Zergling";181;0
"Unit";"Baneling";"Zergling";181;0
"Unit";"Baneling";"Zergling";181;0
"Building";"HydraliskDen";NA;165;0
"Building";"CreepTumor";NA;181;0
"Building";"CreepTumor";NA;181;0
"Building";"CreepTumor";NA;185;0
"Building";"CreepTumor";NA;191;0
"Unit";"Zergling";"Larva";197;1
"Unit";"Zergling";"Larva";197;1
"Building";"CreepTumor";NA;197;0
"Unit";"Zergling";"Larva";197;1
"Unit";"Zergling";"Larva";197;1
"Unit";"Zergling";"Larva";197;1
"Unit";"Zergling";"Larva";197;1
"Unit";"Hydralisk";"Larva";191;2
"Unit";"Hydralisk";"Larva";191;2
"Unit";"Hydralisk";"Larva";191;2
"Unit";"Hydralisk";"Larva";191;2
"Unit";"Hydralisk";"Larva";191;2
"Building";"CreepTumor";NA;197;0
"Upgrade";"EvolveMuscularAugments";"HydraliskDen";191;0
"Unit";"Hydralisk";"Larva";197;2
"Unit";"Hydralisk";"Larva";197;2
"Unit";"Hydralisk";"Larva";197;2
"Unit";"Hydralisk";"Larva";199;2
"Unit";"Hydralisk";"Larva";199;2
"Unit";"Hydralisk";"Larva";199;2
"Unit";"Overlord";"Larva";213;0
"Unit";"Overlord";"Larva";213;0
"Building";"CreepTumor";NA;213;0
"Building";"CreepTumor";NA;225;0
"Upgrade";"ZergMeleeWeaponsLevel1";"EvolutionChamber";191;0
"Building";"CreepTumor";NA;225;0
"Upgrade";"ZergGroundArmorsLevel1";"EvolutionChamber";191;0
"Unit";"Hydralisk";"Larva";225;2
"Unit";"Hydralisk";"Larva";225;2
"Unit";"Hydralisk";"Larva";225;2
"Unit";"Hydralisk";"Larva";225;2
"Unit";"Baneling";"Zergling";227;0
"Unit";"Baneling";"Zergling";227;0
"Unit";"Baneling";"Zergling";227;0
"Unit";"Baneling";"Zergling";227;0
"Unit";"Baneling";"Zergling";227;0
"Unit";"Baneling";"Zergling";227;0
"Unit";"Baneling";"Zergling";227;0
"Unit";"Baneling";"Zergling";227;0
"Unit";"Baneling";"Zergling";227;0
"Building";"CreepTumor";NA;227;0
"Unit";"Baneling";"Zergling";227;0
"Unit";"Baneling";"Zergling";227;0
"Unit";"Baneling";"Zergling";227;0
"Unit";"Baneling";"Zergling";227;0
"Unit";"Baneling";"Zergling";227;0
"Building";"CreepTumor";NA;227;0
"Building";"InfestationPit";NA;225;0
"Unit";"Queen";"Hatchery";225;2
"Upgrade";"EvolveGroovedSpines";"HydraliskDen";225;0
"Building";"Hatchery";NA;213;0
"Unit";"Zergling";"Larva";236;1
"Unit";"Zergling";"Larva";236;1
"Unit";"Zergling";"Larva";236;1
"Unit";"Zergling";"Larva";236;1
"Unit";"Zergling";"Larva";236;1
"Unit";"Zergling";"Larva";236;1
"Unit";"Zergling";"Larva";236;1
"Unit";"Zergling";"Larva";236;1
"Unit";"Zergling";"Larva";236;1
"Unit";"Zergling";"Larva";236;1
"Unit";"Zergling";"Larva";236;1
"Unit";"Zergling";"Larva";236;1
"Unit";"Zergling";"Larva";236;1
"Unit";"Zergling";"Larva";236;1
"Unit";"Zergling";"Larva";236;1
"Unit";"Zergling";"Larva";236;1
"Unit";"Zergling";"Larva";236;1
"Unit";"Zergling";"Larva";236;1
"Unit";"Zergling";"Larva";236;1
"Unit";"Zergling";"Larva";236;1
"Unit";"Zergling";"Larva";236;1
"Unit";"Zergling";"Larva";236;1
"Unit";"Zergling";"Larva";236;1
"Unit";"Zergling";"Larva";236;1
"Unit";"Zergling";"Larva";236;1
"Unit";"Zergling";"Larva";236;1
"Unit";"Zergling";"Larva";236;1
"Unit";"Zergling";"Larva";236;1
"Unit";"Zergling";"Larva";266;1
"Unit";"Zergling";"Larva";266;1
"Unit";"Zergling";"Larva";266;1
"Unit";"Zergling";"Larva";266;1
"Unit";"Zergling";"Larva";266;1
"Unit";"Zergling";"Larva";266;1
"Unit";"Zergling";"Larva";266;1
"Unit";"Zergling";"Larva";266;1
"Unit";"Zergling";"Larva";266;1
"Unit";"Zergling";"Larva";266;1
"Unit";"Zergling";"Larva";266;1
"Unit";"Zergling";"Larva";266;1
"Unit";"Zergling";"Larva";266;1
"Unit";"Zergling";"Larva";266;1
"Unit";"Zergling";"Larva";266;1
"Unit";"Zergling";"Larva";266;1
"Unit";"Baneling";"Zergling";266;0
"Unit";"Baneling";"Zergling";266;0
"Unit";"Baneling";"Zergling";266;0
"Unit";"Baneling";"Zergling";266;0
"Unit";"Baneling";"Zergling";266;0
"Unit";"Baneling";"Zergling";266;0
"Unit";"Overlord";"Larva";266;0
"Unit";"Overlord";"Larva";266;0
"Unit";"Overlord";"Larva";266;0
"Unit";"Overlord";"Larva";266;0
"Unit";"Overlord";"Larva";266;0
"Building";"Hatchery";NA;225;0
"Unit";"Hydralisk";"Larva";282;2
"Unit";"Hydralisk";"Larva";282;2
"Unit";"Hydralisk";"Larva";282;2
"Unit";"Hydralisk";"Larva";282;2
"Unit";"Zergling";"Larva";282;1
"Unit";"Zergling";"Larva";282;1
"Unit";"Zergling";"Larva";282;1
"Unit";"Zergling";"Larva";282;1
"Unit";"Zergling";"Larva";282;1
"Unit";"Zergling";"Larva";282;1
"Unit";"Zergling";"Larva";282;1
"Unit";"Zergling";"Larva";282;1
"Unit";"Zergling";"Larva";282;1
"Unit";"Zergling";"Larva";282;1
"Unit";"Zergling";"Larva";282;1
"Unit";"Zergling";"Larva";282;1
"Unit";"Zergling";"Larva";282;1
"Unit";"Zergling";"Larva";282;1
"Unit";"Zergling";"Larva";282;1
"Unit";"Zergling";"Larva";282;1
"Unit";"Zergling";"Larva";282;1
"Unit";"Zergling";"Larva";282;1
"Unit";"Zergling";"Larva";282;1
"Unit";"Zergling";"Larva";282;1
"Unit";"Zergling";"Larva";282;1
"Unit";"Zergling";"Larva";282;1
"Unit";"Zergling";"Larva";282;1
"Unit";"Zergling";"Larva";282;1
"Unit";"Zergling";"Larva";282;1
"Unit";"Zergling";"Larva";282;1
"Unit";"Zergling";"Larva";282;1
"Unit";"Zergling";"Larva";282;1
"Building";"CreepTumor";NA;327;0
"Unit";"Hydralisk";"Larva";282;2
"Unit";"Hydralisk";"Larva";282;2
"Unit";"Baneling";"Zergling";327;0
"Unit";"Baneling";"Zergling";327;0
"Unit";"Baneling";"Zergling";327;0
"Unit";"Baneling";"Zergling";327;0
"Unit";"Baneling";"Zergling";327;0
"Unit";"Baneling";"Zergling";327;0
"Unit";"Baneling";"Zergling";327;0
"Unit";"Baneling";"Zergling";327;0
"Unit";"Baneling";"Zergling";327;0
"Unit";"Zergling";"Larva";327;1
"Unit";"Zergling";"Larva";327;1
"Unit";"Zergling";"Larva";327;1
"Unit";"Zergling";"Larva";327;1
"Unit";"Zergling";"Larva";327;1
"Unit";"Zergling";"Larva";327;1
"Unit";"Zergling";"Larva";327;1
"Unit";"Zergling";"Larva";327;1
"Unit";"Zergling";"Larva";327;1
"Unit";"Zergling";"Larva";327;1
"Unit";"Zergling";"Larva";327;1
"Unit";"Zergling";"Larva";327;1
"Unit";"Zergling";"Larva";327;1
"Unit";"Zergling";"Larva";327;1
"Unit";"Zergling";"Larva";327;1
"Unit";"Zergling";"Larva";327;1
"Unit";"Zergling";"Larva";327;1
"Unit";"Zergling";"Larva";327;1
"Unit";"Zergling";"Larva";327;1
"Unit";"Zergling";"Larva";327;1
"Unit";"Zergling";"Larva";327;1
"Unit";"Zergling";"Larva";327;1
"Unit";"Zergling";"Larva";327;1
"Unit";"Zergling";"Larva";327;1
"Upgrade";"ZergMeleeWeaponsLevel2";"EvolutionChamber";238;0
"Upgrade";"ZergGroundArmorsLevel2";"EvolutionChamber";266;0
"Building";"Extractor";NA;331;0
"Building";"Extractor";NA;331;0
"Unit";"Viper";"Larva";331;3
"Unit";"Viper";"Larva";331;3
"Unit";"Overlord";"Larva";355;0
"Unit";"Overlord";"Larva";355;0
"Unit";"Overlord";"Larva";355;0
"Unit";"Overlord";"Larva";355;0
"Unit";"Overlord";"Larva";355;0
"Building";"Extractor";NA;355;0
"Building";"CreepTumor";NA;355;0
"Unit";"Overlord";"Larva";355;0
"Unit";"Overlord";"Larva";355;0
"Building";"CreepTumor";NA;361;0
"Building";"CreepTumor";NA;362;0
"Unit";"Zergling";"Larva";367;1
"Unit";"Zergling";"Larva";367;1
"Unit";"Zergling";"Larva";367;1
"Unit";"Zergling";"Larva";367;1
"Unit";"Zergling";"Larva";367;1
"Unit";"Zergling";"Larva";367;1
"Unit";"Zergling";"Larva";367;1
"Unit";"Zergling";"Larva";367;1
"Unit";"Zergling";"Larva";367;1
"Unit";"Zergling";"Larva";367;1
"Unit";"Zergling";"Larva";367;1
"Unit";"Zergling";"Larva";367;1
"Unit";"Zergling";"Larva";367;1
"Unit";"Zergling";"Larva";367;1
"Unit";"Zergling";"Larva";367;1
"Unit";"Zergling";"Larva";367;1
"Unit";"Zergling";"Larva";367;1
"Unit";"Zergling";"Larva";367;1
"Unit";"Zergling";"Larva";367;1
"Unit";"Zergling";"Larva";367;1
"Unit";"Viper";"Larva";367;3
"Unit";"Viper";"Larva";367;3
"Building";"CreepTumor";NA;367;0
"Unit";"Overlord";"Larva";367;0
"Unit";"Overlord";"Larva";367;0
"Building";"Extractor";NA;387;0
"Building";"CreepTumorQueen";NA;393;0
"Unit";"Zergling";"Larva";393;1
"Unit";"Zergling";"Larva";393;1
"Unit";"Zergling";"Larva";393;1
"Unit";"Zergling";"Larva";393;1
"Unit";"Zergling";"Larva";393;1
"Unit";"Zergling";"Larva";393;1
"Unit";"Zergling";"Larva";393;1
"Unit";"Zergling";"Larva";393;1
"Unit";"Zergling";"Larva";393;1
"Unit";"Zergling";"Larva";393;1
"Unit";"Zergling";"Larva";393;1
"Unit";"Zergling";"Larva";393;1
"Unit";"Zergling";"Larva";393;1
"Unit";"Zergling";"Larva";393;1
"Unit";"Zergling";"Larva";393;1
"Unit";"Zergling";"Larva";393;1
"Unit";"Zergling";"Larva";393;1
"Unit";"Zergling";"Larva";393;1
"Unit";"Zergling";"Larva";393;1
"Unit";"Zergling";"Larva";393;1
"Unit";"Zergling";"Larva";393;1
"Unit";"Zergling";"Larva";393;1
"Unit";"Zergling";"Larva";393;1
"Unit";"Zergling";"Larva";393;1
"Unit";"Zergling";"Larva";393;1
"Unit";"Zergling";"Larva";393;1
"Unit";"Zergling";"Larva";393;1
"Unit";"Zergling";"Larva";393;1
"Unit";"Zergling";"Larva";393;1
"Unit";"Zergling";"Larva";393;1
"Unit";"Zergling";"Larva";393;1
"Unit";"Zergling";"Larva";393;1
"Unit";"Zergling";"Larva";393;1
"Unit";"Zergling";"Larva";393;1
"Unit";"Zergling";"Larva";393;1
"Unit";"Zergling";"Larva";393;1
"Unit";"Zergling";"Larva";393;1
"Unit";"Zergling";"Larva";393;1
"Unit";"Zergling";"Larva";393;1
"Unit";"Zergling";"Larva";393;1
"Unit";"Zergling";"Larva";393;1
"Unit";"Zergling";"Larva";393;1
"Unit";"Zergling";"Larva";393;1
"Unit";"Zergling";"Larva";393;1
"Unit";"Zergling";"Larva";393;1
"Unit";"Zergling";"Larva";393;1
"Unit";"Zergling";"Larva";393;1
"Unit";"Zergling";"Larva";393;1
"Unit";"Zergling";"Larva";393;1
"Unit";"Zergling";"Larva";393;1
"Unit";"Zergling";"Larva";393;1
"Unit";"Zergling";"Larva";393;1
"Unit";"Zergling";"Larva";393;1
"Unit";"Zergling";"Larva";393;1
"Unit";"Zergling";"Larva";393;1
"Unit";"Zergling";"Larva";393;1
"Unit";"Zergling";"Larva";393;1
"Unit";"Zergling";"Larva";393;1
"Unit";"Zergling";"Larva";393;1
"Unit";"Zergling";"Larva";393;1
"Unit";"Zergling";"Larva";393;1
"Unit";"Zergling";"Larva";393;1
"Unit";"Zergling";"Larva";393;1
"Unit";"Zergling";"Larva";393;1
"Unit";"Zergling";"Larva";393;1
"Unit";"Zergling";"Larva";393;1
"Unit";"Zergling";"Larva";393;1
"Unit";"Zergling";"Larva";393;1
"Unit";"Zergling";"Larva";393;1
"Unit";"Zergling";"Larva";393;1
"Upgrade";"ZergMeleeWeaponsLevel3";"EvolutionChamber";367;0
"Building";"Hatchery";NA;393;0
"Unit";"Zergling";"Larva";393;1
"Unit";"Zergling";"Larva";393;1
"Unit";"Zergling";"Larva";395;1
"Unit";"Zergling";"Larva";395;1
"Unit";"Zergling";"Larva";395;1
"Unit";"Zergling";"Larva";395;1
"Unit";"Zergling";"Larva";395;1
"Unit";"Zergling";"Larva";395;1
"Unit";"Zergling";"Larva";395;1
"Unit";"Zergling";"Larva";395;1
"Unit";"Zergling";"Larva";395;1
"Unit";"Zergling";"Larva";395;1
"Unit";"Zergling";"Larva";395;1
"Unit";"Zergling";"Larva";395;1
"Unit";"Zergling";"Larva";395;1
"Unit";"Zergling";"Larva";395;1
"Unit";"Zergling";"Larva";395;1
"Unit";"Zergling";"Larva";395;1
"Unit";"Zergling";"Larva";397;1
"Unit";"Zergling";"Larva";397;1
"Unit";"Zergling";"Larva";403;1
"Unit";"Zergling";"Larva";403;1
"Unit";"Zergling";"Larva";403;1
"Unit";"Zergling";"Larva";403;1
"Unit";"Zergling";"Larva";407;1
"Unit";"Zergling";"Larva";407;1
"Upgrade";"ZergGroundArmorsLevel3";"EvolutionChamber";367;0
"Unit";"Hydralisk";"Larva";463;2
"Unit";"Hydralisk";"Larva";463;2
"Unit";"Hydralisk";"Larva";463;2
"Unit";"Hydralisk";"Larva";463;2
"Unit";"Hydralisk";"Larva";463;2
"Unit";"Hydralisk";"Larva";463;2
"Unit";"Hydralisk";"Larva";463;2
"Unit";"Hydralisk";"Larva";463;2
"Unit";"Baneling";"Zergling";505;0
"Unit";"Baneling";"Zergling";505;0
"Unit";"Baneling";"Zergling";505;0
"Unit";"Baneling";"Zergling";505;0
"Unit";"Baneling";"Zergling";505;0
"Unit";"Baneling";"Zergling";505;0
"Unit";"Baneling";"Zergling";505;0
"Unit";"Baneling";"Zergling";505;0
"Unit";"Baneling";"Zergling";505;0
"Unit";"Baneling";"Zergling";505;0
"Unit";"Baneling";"Zergling";505;0
"Unit";"Baneling";"Zergling";505;0
"Unit";"Baneling";"Zergling";505;0
"Unit";"Baneling";"Zergling";505;0
"Unit";"Zergling";"Larva";505;1
"Unit";"Zergling";"Larva";505;1
"Unit";"Zergling";"Larva";505;1
"Unit";"Zergling";"Larva";505;1
"Unit";"Zergling";"Larva";505;1
"Unit";"Zergling";"Larva";505;1
"Unit";"Zergling";"Larva";505;1
"Unit";"Zergling";"Larva";505;1
"Unit";"Zergling";"Larva";505;1
"Unit";"Zergling";"Larva";505;1
"Unit";"Zergling";"Larva";505;1
"Unit";"Zergling";"Larva";505;1
"Unit";"Zergling";"Larva";505;1
"Unit";"Zergling";"Larva";505;1
"Unit";"Zergling";"Larva";505;1
"Unit";"Zergling";"Larva";505;1
"Unit";"Zergling";"Larva";505;1
"Unit";"Zergling";"Larva";505;1
"Unit";"Zergling";"Larva";505;1
"Unit";"Zergling";"Larva";505;1
"Unit";"Zergling";"Larva";505;1
"Unit";"Zergling";"Larva";505;1
"Unit";"Zergling";"Larva";505;1
"Unit";"Zergling";"Larva";505;1
"Unit";"Zergling";"Larva";505;1
"Unit";"Zergling";"Larva";505;1
"Unit";"Zergling";"Larva";505;1
"Unit";"Zergling";"Larva";505;1
"Unit";"Zergling";"Larva";505;1
"Unit";"Zergling";"Larva";505;1
"Unit";"Zergling";"Larva";505;1
"Unit";"Zergling";"Larva";505;1
"Unit";"Zergling";"Larva";505;1
"Unit";"Zergling";"Larva";505;1
"Unit";"Hydralisk";"Larva";489;2
"Unit";"Hydralisk";"Larva";489;2
"Unit";"Hydralisk";"Larva";489;2
"Unit";"Hydralisk";"Larva";489;2
"Unit";"Hydralisk";"Larva";489;2
"Unit";"Viper";"Larva";489;3
"Building";"CreepTumor";NA;505;0
"Building";"CreepTumorQueen";NA;505;0
"Building";"CreepTumorQueen";NA;508;0
"Building";"Spire";NA;463;0
"Unit";"Zergling";"Larva";542;1
"Unit";"Zergling";"Larva";542;1
"Unit";"Zergling";"Larva";542;1
"Unit";"Zergling";"Larva";542;1
"Unit";"Zergling";"Larva";542;1
"Unit";"Zergling";"Larva";542;1
"Unit";"Zergling";"Larva";542;1
"Unit";"Zergling";"Larva";542;1
"Unit";"Zergling";"Larva";542;1
"Unit";"Zergling";"Larva";542;1
"Unit";"Zergling";"Larva";542;1
"Unit";"Zergling";"Larva";542;1
"Unit";"Zergling";"Larva";542;1
"Unit";"Zergling";"Larva";542;1
"Unit";"Zergling";"Larva";542;1
"Unit";"Zergling";"Larva";542;1
"Unit";"Zergling";"Larva";542;1
"Unit";"Zergling";"Larva";542;1
"Building";"CreepTumorQueen";NA;555;0
"Building";"CreepTumorQueen";NA;555;0
"Building";"CreepTumorQueen";NA;555;0
"Unit";"Queen";"Hatchery";505;2
"Unit";"Zergling";"Larva";555;1
"Unit";"Zergling";"Larva";555;1
"Unit";"Zergling";"Larva";555;1
"Unit";"Zergling";"Larva";555;1
"Unit";"Zergling";"Larva";555;1
"Unit";"Zergling";"Larva";555;1
"Unit";"Zergling";"Larva";555;1
"Unit";"Zergling";"Larva";555;1
"Unit";"Zergling";"Larva";555;1
"Unit";"Zergling";"Larva";555;1
"Unit";"Zergling";"Larva";555;1
"Unit";"Zergling";"Larva";555;1
"Unit";"Zergling";"Larva";555;1
"Unit";"Zergling";"Larva";555;1
"Building";"SporeCrawler";NA;573;0
"Building";"SporeCrawler";NA;573;0
"Building";"SporeCrawler";NA;573;0
"Unit";"Zergling";"Larva";585;1
"Unit";"Zergling";"Larva";585;1
"Unit";"Zergling";"Larva";589;1
"Unit";"Zergling";"Larva";589;1
"Unit";"Zergling";"Larva";589;1
"Unit";"Zergling";"Larva";589;1
"Unit";"Zergling";"Larva";589;1
"Unit";"Zergling";"Larva";589;1
"Unit";"Zergling";"Larva";589;1
"Unit";"Zergling";"Larva";589;1
"Unit";"Zergling";"Larva";589;1
"Unit";"Zergling";"Larva";589;1
"Unit";"Zergling";"Larva";589;1
"Unit";"Zergling";"Larva";589;1
"Unit";"Zergling";"Larva";589;1
"Unit";"Zergling";"Larva";589;1
"Unit";"Zergling";"Larva";589;1
"Unit";"Zergling";"Larva";589;1
"Unit";"Zergling";"Larva";589;1
"Unit";"Zergling";"Larva";589;1
"Unit";"Zergling";"Larva";589;1
"Unit";"Zergling";"Larva";589;1
"Unit";"Zergling";"Larva";589;1
"Unit";"Zergling";"Larva";589;1
"Unit";"Zergling";"Larva";589;1
"Unit";"Zergling";"Larva";589;1
"Unit";"Zergling";"Larva";589;1
"Unit";"Zergling";"Larva";589;1
"Unit";"Zergling";"Larva";589;1
"Unit";"Zergling";"Larva";589;1
"Unit";"Zergling";"Larva";589;1
"Unit";"Zergling";"Larva";589;1
"Unit";"Zergling";"Larva";589;1
"Unit";"Zergling";"Larva";589;1
"Building";"CreepTumor";NA;601;0
"Building";"CreepTumor";NA;623;0
"Building";"CreepTumor";NA;623;0
"Building";"CreepTumor";NA;623;0
"Building";"CreepTumorQueen";NA;623;0
"Building";"CreepTumorQueen";NA;623;0
"Building";"CreepTumor";NA;623;0
"Unit";"Hydralisk";"Larva";623;2
"Unit";"Hydralisk";"Larva";623;2
"Unit";"Hydralisk";"Larva";623;2
"Unit";"Hydralisk";"Larva";623;2
"Unit";"Hydralisk";"Larva";623;2
"Unit";"Corruptor";"Larva";623;2
"Unit";"Corruptor";"Larva";623;2
"Unit";"Corruptor";"Larva";623;2
"Unit";"Corruptor";"Larva";623;2
"Unit";"Corruptor";"Larva";623;2
"Unit";"Corruptor";"Larva";623;2
"Unit";"Zergling";"Larva";633;1
"Unit";"Zergling";"Larva";633;1
"Unit";"Zergling";"Larva";633;1
"Unit";"Zergling";"Larva";633;1
"Upgrade";"ZergMissileWeaponsLevel1";"EvolutionChamber";573;0
"Unit";"Hydralisk";"Larva";633;2
"Unit";"Baneling";"Zergling";654;0
"Unit";"Baneling";"Zergling";654;0
"Unit";"Baneling";"Zergling";654;0
"Unit";"Baneling";"Zergling";654;0
"Unit";"Baneling";"Zergling";654;0
"Unit";"Baneling";"Zergling";654;0
"Unit";"Baneling";"Zergling";660;0
"Unit";"Baneling";"Zergling";660;0
"Unit";"Baneling";"Zergling";660;0
"Unit";"Baneling";"Zergling";660;0
"Unit";"Baneling";"Zergling";660;0
"Unit";"Baneling";"Zergling";660;0
"Unit";"Baneling";"Zergling";660;0
"Unit";"Baneling";"Zergling";660;0
"Unit";"Baneling";"Zergling";660;0
"Unit";"Baneling";"Zergling";660;0
"Unit";"Baneling";"Zergling";660;0
"Unit";"Baneling";"Zergling";660;0
"Unit";"Baneling";"Zergling";660;0
"Unit";"Viper";"Larva";660;3
"Unit";"Viper";"Larva";660;3
"Unit";"Zergling";"Larva";660;1
"Unit";"Zergling";"Larva";660;1
"Unit";"Zergling";"Larva";660;1
"Unit";"Zergling";"Larva";660;1
"Unit";"Zergling";"Larva";660;1
"Unit";"Zergling";"Larva";660;1
"Unit";"Zergling";"Larva";660;1
"Unit";"Zergling";"Larva";660;1
"Unit";"Zergling";"Larva";660;1
"Unit";"Zergling";"Larva";660;1
"Unit";"Zergling";"Larva";660;1
"Unit";"Zergling";"Larva";660;1
"Unit";"Zergling";"Larva";660;1
"Unit";"Zergling";"Larva";660;1
"Unit";"Zergling";"Larva";660;1
"Unit";"Zergling";"Larva";660;1
"Unit";"Zergling";"Larva";660;1
"Unit";"Zergling";"Larva";660;1
"Unit";"Zergling";"Larva";660;1
"Unit";"Zergling";"Larva";660;1
"Unit";"Zergling";"Larva";660;1
"Unit";"Zergling";"Larva";660;1
"Unit";"Zergling";"Larva";660;1
"Unit";"Zergling";"Larva";660;1
"Unit";"Zergling";"Larva";660;1
"Unit";"Zergling";"Larva";660;1
"Unit";"Zergling";"Larva";660;1
"Unit";"Zergling";"Larva";660;1
"Unit";"Zergling";"Larva";660;1
"Unit";"Zergling";"Larva";660;1
"Unit";"Zergling";"Larva";660;1
"Unit";"Zergling";"Larva";660;1
"Unit";"Zergling";"Larva";660;1
"Unit";"Zergling";"Larva";660;1
"Unit";"Zergling";"Larva";660;1
"Unit";"Zergling";"Larva";660;1
"Unit";"Zergling";"Larva";660;1
"Unit";"Zergling";"Larva";660;1
"Unit";"Zergling";"Larva";660;1
"Unit";"Zergling";"Larva";660;1
"Unit";"Zergling";"Larva";660;1
"Unit";"Zergling";"Larva";660;1
"Unit";"Zergling";"Larva";660;1
"Unit";"Zergling";"Larva";660;1
"Unit";"Zergling";"Larva";660;1
"Unit";"Zergling";"Larva";660;1
"Unit";"Zergling";"Larva";660;1
"Unit";"Zergling";"Larva";660;1
"Unit";"Zergling";"Larva";660;1
"Unit";"Zergling";"Larva";660;1
"Unit";"Zergling";"Larva";670;1
"Unit";"Zergling";"Larva";670;1
"Unit";"Zergling";"Larva";684;1
"Unit";"Zergling";"Larva";684;1
"Unit";"Zergling";"Larva";684;1
"Unit";"Zergling";"Larva";684;1
"Unit";"Zergling";"Larva";688;1
"Unit";"Zergling";"Larva";688;1
"Unit";"Zergling";"Larva";692;1
"Unit";"Zergling";"Larva";692;1
