"type";"unit_name";"on_building";"total_supply";"supply"
"Unit";"Overlord";"Larva";12;0
"Building";"Extractor";NA;18;0
"Building";"SpawningPool";NA;19;0
"Unit";"Overlord";"Larva";22;0
"Building";"Hatchery";NA;17;0
"Unit";"Zergling";"Larva";22;1
"Unit";"Zergling";"Larva";22;1
"Unit";"Zergling";"Larva";22;1
"Unit";"Zergling";"Larva";22;1
"Unit";"Queen";"Hatchery";22;2
"Unit";"Queen";"Hatchery";22;2
"Unit";"Overlord";"Larva";34;0
"Unit";"Queen";"Hatchery";34;2
"Unit";"Zergling";"Larva";37;1
"Unit";"Zergling";"Larva";37;1
"Unit";"Zergling";"Larva";37;1
"Unit";"Zergling";"Larva";37;1
"Unit";"Zergling";"Larva";37;1
"Unit";"Zergling";"Larva";37;1
"Unit";"Queen";"Hatchery";34;2
"Unit";"Zergling";"Larva";37;1
"Unit";"Zergling";"Larva";37;1
"Building";"CreepTumorQueen";NA;37;0
"Building";"CreepTumorQueen";NA;37;0
"Unit";"Overlord";"Larva";53;0
"Building";"CreepTumor";NA;53;0
"Building";"CreepTumorQueen";NA;53;0
"Building";"CreepTumor";NA;53;0
"Building";"CreepTumorQueen";NA;53;0
"Unit";"Overlord";"Larva";54;0
"Unit";"Overlord";"Larva";54;0
"Building";"Extractor";NA;54;0
"Building";"CreepTumorQueen";NA;63;0
"Building";"CreepTumorQueen";NA;63;0
"Building";"CreepTumor";NA;63;0
"Building";"CreepTumor";NA;63;0
"Building";"CreepTumor";NA;63;0
"Building";"CreepTumor";NA;63;0
"Unit";"Overlord";"Larva";63;0
"Unit";"Overlord";"Larva";63;0
"Building";"Hatchery";NA;53;0
"Building";"RoachWarren";NA;55;0
"Unit";"Overlord";"Larva";66;0
"Unit";"Overlord";"Larva";66;0
"Unit";"Queen";"Hatchery";63;2
"Unit";"Queen";"Hatchery";66;2
"Unit";"Roach";"Larva";66;2
"Unit";"Roach";"Larva";66;2
"Unit";"Roach";"Larva";66;2
"Unit";"Roach";"Larva";66;2
"Unit";"Roach";"Larva";66;2
"Unit";"Roach";"Larva";66;2
"Unit";"Roach";"Larva";66;2
"Building";"CreepTumor";NA;66;0
"Building";"CreepTumor";NA;66;0
"Building";"CreepTumor";NA;68;0
"Building";"CreepTumor";NA;68;0
"Building";"CreepTumor";NA;68;0
"Building";"CreepTumor";NA;68;0
"Building";"Extractor";NA;66;0
"Unit";"Zergling";"Larva";68;1
"Unit";"Zergling";"Larva";68;1
"Unit";"Zergling";"Larva";68;1
"Unit";"Zergling";"Larva";68;1
"Unit";"Zergling";"Larva";68;1
"Unit";"Zergling";"Larva";68;1
"Unit";"Queen";"Hatchery";66;2
"Unit";"Zergling";"Larva";84;1
"Unit";"Zergling";"Larva";84;1
"Unit";"Zergling";"Larva";84;1
"Unit";"Zergling";"Larva";84;1
"Unit";"Zergling";"Larva";86;1
"Unit";"Zergling";"Larva";86;1
"Building";"SporeCrawler";NA;94;0
"Building";"SporeCrawler";NA;100;0
"Building";"SporeCrawler";NA;115;0
"Unit";"Queen";"Hatchery";115;2
"Unit";"Queen";"Hatchery";115;2
"Building";"EvolutionChamber";NA;115;0
"Building";"EvolutionChamber";NA;115;0
"Building";"CreepTumor";NA;119;0
"Building";"CreepTumor";NA;130;0
"Building";"CreepTumor";NA;130;0
"Building";"CreepTumor";NA;130;0
"Building";"HydraliskDen";NA;119;0
"Unit";"Queen";"Hatchery";115;2
"Unit";"Queen";"Hatchery";119;2
"Building";"CreepTumor";NA;130;0
"Building";"CreepTumor";NA;130;0
"Unit";"Queen";"Hatchery";119;2
"Unit";"Roach";"Larva";130;2
"Unit";"Roach";"Larva";130;2
"Unit";"Roach";"Larva";130;2
"Unit";"Roach";"Larva";130;2
"Unit";"Roach";"Larva";130;2
"Building";"SpineCrawler";NA;119;0
"Unit";"Roach";"Larva";130;2
"Unit";"Overlord";"Larva";130;0
"Unit";"Overlord";"Larva";130;0
"Building";"Extractor";NA;130;0
"Building";"Extractor";NA;136;0
"Building";"CreepTumor";NA;148;0
"Building";"Extractor";NA;136;0
"Unit";"Roach";"Larva";136;2
"Unit";"Roach";"Larva";136;2
"Unit";"Roach";"Larva";136;2
"Unit";"Roach";"Larva";136;2
"Unit";"Roach";"Larva";136;2
"Building";"InfestationPit";NA;130;0
"Unit";"Queen";"Hatchery";130;2
"Unit";"Zergling";"Larva";148;1
"Unit";"Zergling";"Larva";148;1
"Unit";"Zergling";"Larva";148;1
"Unit";"Zergling";"Larva";148;1
"Unit";"Zergling";"Larva";148;1
"Unit";"Zergling";"Larva";148;1
"Unit";"Zergling";"Larva";148;1
"Unit";"Zergling";"Larva";148;1
"Unit";"Zergling";"Larva";148;1
"Unit";"Zergling";"Larva";148;1
"Unit";"Zergling";"Larva";148;1
"Unit";"Zergling";"Larva";148;1
"Upgrade";"GlialReconstitution";"RoachWarren";130;0
"Unit";"Hydralisk";"Larva";158;2
"Unit";"Hydralisk";"Larva";158;2
"Unit";"Hydralisk";"Larva";160;2
"Unit";"Hydralisk";"Larva";172;2
"Unit";"Queen";"Hatchery";160;2
"Unit";"Queen";"Hatchery";160;2
"Upgrade";"EvolveGroovedSpines";"HydraliskDen";158;0
"Building";"SporeCrawler";NA;186;0
"Building";"SporeCrawler";NA;186;0
"Building";"CreepTumor";NA;194;0
"Unit";"Hydralisk";"Larva";188;2
"Unit";"Hydralisk";"Larva";188;2
"Unit";"Hydralisk";"Larva";188;2
"Upgrade";"ZergGroundArmorsLevel1";"EvolutionChamber";138;0
"Upgrade";"ZergMissileWeaponsLevel1";"EvolutionChamber";138;0
"Unit";"Overlord";"Larva";194;0
"Unit";"Overlord";"Larva";194;0
"Unit";"Queen";"Hatchery";194;2
"Unit";"Queen";"Hatchery";194;2
"Building";"SporeCrawler";NA;196;0
"Unit";"Queen";"Hatchery";194;2
"Building";"CreepTumor";NA;203;0
"Unit";"Roach";"Larva";203;2
"Unit";"Roach";"Larva";203;2
"Unit";"Roach";"Larva";213;2
"Unit";"Roach";"Larva";213;2
"Unit";"Roach";"Larva";213;2
"Unit";"Roach";"Larva";213;2
"Unit";"Roach";"Larva";213;2
"Unit";"Roach";"Larva";213;2
"Upgrade";"EvolveMuscularAugments";"HydraliskDen";203;0
"Building";"Hatchery";NA;194;0
"Unit";"Overlord";"Larva";225;0
"Unit";"Overlord";"Larva";225;0
"Unit";"Overlord";"Larva";225;0
"Unit";"Overlord";"Larva";225;0
"Unit";"Overlord";"Larva";225;0
"Building";"SpineCrawler";NA;225;0
"Building";"SpineCrawler";NA;225;0
"Unit";"Hydralisk";"Larva";234;2
"Unit";"Hydralisk";"Larva";234;2
"Unit";"Hydralisk";"Larva";234;2
"Unit";"Hydralisk";"Larva";234;2
"Unit";"Hydralisk";"Larva";234;2
"Unit";"Hydralisk";"Larva";234;2
"Unit";"Hydralisk";"Larva";234;2
"Building";"CreepTumorQueen";NA;234;0
"Building";"CreepTumorQueen";NA;234;0
"Building";"CreepTumorQueen";NA;234;0
"Unit";"Roach";"Larva";234;2
"Unit";"Hydralisk";"Larva";234;2
"Unit";"Hydralisk";"Larva";234;2
"Unit";"Hydralisk";"Larva";234;2
"Building";"Extractor";NA;234;0
"Building";"SporeCrawler";NA;234;0
"Building";"Extractor";NA;234;0
"Unit";"Hydralisk";"Larva";250;2
"Unit";"Hydralisk";"Larva";250;2
"Unit";"Hydralisk";"Larva";250;2
"Unit";"Hydralisk";"Larva";250;2
"Unit";"Hydralisk";"Larva";250;2
"Unit";"Hydralisk";"Larva";250;2
"Unit";"Hydralisk";"Larva";250;2
"Unit";"Hydralisk";"Larva";250;2
"Upgrade";"ZergMissileWeaponsLevel2";"EvolutionChamber";213;0
"Building";"Hatchery";NA;234;0
"Unit";"Roach";"Larva";256;2
"Unit";"Roach";"Larva";256;2
"Unit";"Roach";"Larva";256;2
"Unit";"Roach";"Larva";256;2
"Unit";"Roach";"Larva";256;2
"Unit";"Roach";"Larva";256;2
"Unit";"Roach";"Larva";256;2
"Unit";"Roach";"Larva";256;2
"Unit";"Roach";"Larva";256;2
"Unit";"Roach";"Larva";256;2
"Unit";"Roach";"Larva";272;2
"Unit";"Roach";"Larva";272;2
"Unit";"Roach";"Larva";272;2
"Unit";"Roach";"Larva";272;2
"Unit";"Roach";"Larva";272;2
"Unit";"Roach";"Larva";272;2
"Unit";"Roach";"Larva";272;2
"Unit";"Roach";"Larva";272;2
"Unit";"Roach";"Larva";272;2
