"type";"unit_name";"on_building";"total_supply";"supply"
"Unit";"Overlord";"Larva";12;0
"Building";"SpawningPool";NA;14;0
"Unit";"Queen";"Hatchery";18;2
"Unit";"Overlord";"Larva";19;0
"Building";"CreepTumorQueen";NA;23;0
"Building";"Hatchery";NA;18;0
"Unit";"Queen";"Hatchery";23;2
"Building";"Extractor";NA;23;0
"Building";"CreepTumorQueen";NA;25;0
"Building";"CreepTumor";NA;25;0
"Unit";"Queen";"Hatchery";25;2
"Building";"CreepTumor";NA;28;0
"Building";"CreepTumorQueen";NA;36;0
"Building";"Hatchery";NA;23;0
"Building";"CreepTumor";NA;36;0
"Unit";"Overlord";"Larva";38;0
"Building";"CreepTumorQueen";NA;38;0
"Building";"CreepTumor";NA;38;0
"Building";"CreepTumor";NA;38;0
"Building";"CreepTumor";NA;38;0
"Building";"CreepTumorQueen";NA;38;0
"Unit";"Queen";"Hatchery";38;2
"Building";"RoachWarren";NA;38;0
"Unit";"Queen";"Hatchery";38;2
"Unit";"Overlord";"Larva";46;0
"Unit";"Overlord";"Larva";47;0
"Building";"CreepTumor";NA;49;0
"Building";"CreepTumor";NA;49;0
"Building";"CreepTumor";NA;49;0
"Building";"CreepTumor";NA;53;0
"Unit";"Roach";"Larva";49;2
"Unit";"Roach";"Larva";53;2
"Unit";"Roach";"Larva";53;2
"Unit";"Roach";"Larva";53;2
"Unit";"Roach";"Larva";53;2
"Unit";"Roach";"Larva";53;2
"Unit";"Roach";"Larva";53;2
"Unit";"Roach";"Larva";53;2
"Unit";"Roach";"Larva";53;2
"Unit";"Overlord";"Larva";53;0
"Building";"CreepTumor";NA;63;0
"Building";"CreepTumor";NA;63;0
"Building";"SporeCrawler";NA;67;0
"Building";"CreepTumor";NA;71;0
"Building";"CreepTumor";NA;71;0
"Unit";"Roach";"Larva";71;2
"Unit";"Roach";"Larva";71;2
"Unit";"Roach";"Larva";71;2
"Unit";"Roach";"Larva";71;2
"Building";"CreepTumor";NA;71;0
"Unit";"Overlord";"Larva";71;0
"Unit";"Overlord";"Larva";71;0
"Unit";"Overlord";"Larva";71;0
"Building";"CreepTumorQueen";NA;83;0
"Building";"CreepTumorQueen";NA;83;0
"Building";"SporeCrawler";NA;71;0
"Building";"CreepTumorQueen";NA;83;0
"Building";"CreepTumor";NA;83;0
"Building";"Extractor";NA;83;0
"Building";"Extractor";NA;83;0
"Unit";"Roach";"Larva";91;2
"Unit";"Queen";"Hatchery";83;2
"Unit";"Roach";"Larva";91;2
"Unit";"Roach";"Larva";91;2
"Unit";"Roach";"Larva";91;2
"Building";"CreepTumor";NA;101;0
"Building";"CreepTumor";NA;101;0
"Building";"CreepTumor";NA;109;0
"Unit";"Overlord";"Larva";109;0
"Unit";"Overlord";"Larva";109;0
"Unit";"Overlord";"Larva";109;0
"Unit";"Overlord";"Larva";109;0
"Unit";"Overlord";"Larva";109;0
"Building";"CreepTumorQueen";NA;109;0
"Building";"CreepTumorQueen";NA;110;0
"Building";"CreepTumorQueen";NA;110;0
"Building";"CreepTumor";NA;110;0
"Building";"CreepTumor";NA;110;0
"Building";"CreepTumor";NA;110;0
"Building";"CreepTumor";NA;110;0
"Unit";"Overlord";"Larva";110;0
"Unit";"Roach";"Larva";110;2
"Unit";"Roach";"Larva";110;2
"Unit";"Roach";"Larva";110;2
"Unit";"Roach";"Larva";110;2
"Unit";"Roach";"Larva";110;2
"Unit";"Roach";"Larva";110;2
"Unit";"Roach";"Larva";110;2
"Building";"Extractor";NA;110;0
"Building";"EvolutionChamber";NA;110;0
"Building";"EvolutionChamber";NA;110;0
"Unit";"Roach";"Larva";117;2
"Unit";"Roach";"Larva";117;2
"Unit";"Roach";"Larva";117;2
"Building";"CreepTumor";NA;137;0
"Building";"CreepTumor";NA;137;0
"Building";"CreepTumor";NA;137;0
"Building";"CreepTumor";NA;137;0
"Building";"Extractor";NA;131;0
"Building";"Extractor";NA;137;0
"Building";"CreepTumorQueen";NA;140;0
"Building";"CreepTumorQueen";NA;140;0
"Building";"CreepTumorQueen";NA;140;0
"Unit";"Overlord";"Larva";149;0
"Unit";"Overlord";"Larva";149;0
"Unit";"Overlord";"Larva";149;0
"Building";"HydraliskDen";NA;149;0
"Building";"Hatchery";NA;131;0
"Building";"CreepTumorQueen";NA;157;0
"Building";"CreepTumorQueen";NA;157;0
"Building";"CreepTumorQueen";NA;157;0
"Building";"CreepTumor";NA;157;0
"Building";"CreepTumor";NA;157;0
"Building";"CreepTumor";NA;157;0
"Building";"CreepTumorQueen";NA;157;0
"Building";"CreepTumorQueen";NA;157;0
"Building";"Extractor";NA;157;0
"Building";"Extractor";NA;157;0
"Building";"CreepTumorQueen";NA;166;0
"Building";"CreepTumorQueen";NA;166;0
"Building";"CreepTumor";NA;166;0
"Building";"CreepTumor";NA;166;0
"Building";"CreepTumorQueen";NA;166;0
"Building";"CreepTumor";NA;166;0
"Building";"CreepTumor";NA;166;0
"Building";"CreepTumor";NA;166;0
"Building";"CreepTumor";NA;166;0
"Building";"CreepTumor";NA;166;0
"Upgrade";"GlialReconstitution";"RoachWarren";157;0
"Unit";"Overlord";"Larva";166;0
"Building";"CreepTumor";NA;166;0
"Unit";"Overlord";"Larva";166;0
"Unit";"Overlord";"Larva";166;0
"Unit";"Overlord";"Larva";166;0
"Unit";"Overlord";"Larva";166;0
"Unit";"Overlord";"Larva";166;0
"Unit";"Overlord";"Larva";166;0
"Unit";"Overlord";"Larva";166;0
"Building";"CreepTumor";NA;166;0
"Building";"CreepTumor";NA;166;0
"Building";"CreepTumor";NA;166;0
"Building";"CreepTumor";NA;166;0
"Building";"CreepTumor";NA;166;0
"Building";"CreepTumor";NA;166;0
"Building";"CreepTumor";NA;166;0
"Building";"CreepTumor";NA;166;0
"Building";"CreepTumor";NA;166;0
"Building";"CreepTumor";NA;166;0
"Building";"InfestationPit";NA;166;0
"Building";"CreepTumorQueen";NA;166;0
"Upgrade";"ZergMissileWeaponsLevel1";"EvolutionChamber";157;0
"Upgrade";"ZergGroundArmorsLevel1";"EvolutionChamber";157;0
"Building";"CreepTumorQueen";NA;166;0
"Unit";"Queen";"Hatchery";166;2
"Building";"CreepTumorQueen";NA;166;0
"Building";"CreepTumorQueen";NA;166;0
"Building";"CreepTumorQueen";NA;166;0
"Upgrade";"EvolveGroovedSpines";"HydraliskDen";166;0
"Building";"CreepTumorQueen";NA;166;0
"Building";"CreepTumorQueen";NA;168;0
"Unit";"Hydralisk";"Larva";166;2
"Unit";"Hydralisk";"Larva";166;2
"Unit";"Hydralisk";"Larva";166;2
"Unit";"Hydralisk";"Larva";166;2
"Unit";"Hydralisk";"Larva";166;2
"Unit";"Hydralisk";"Larva";166;2
"Unit";"Hydralisk";"Larva";166;2
"Unit";"Hydralisk";"Larva";166;2
"Unit";"Hydralisk";"Larva";166;2
"Unit";"Hydralisk";"Larva";166;2
"Unit";"Hydralisk";"Larva";166;2
"Unit";"Hydralisk";"Larva";166;2
"Unit";"Hydralisk";"Larva";166;2
"Unit";"Hydralisk";"Larva";166;2
"Unit";"Hydralisk";"Larva";166;2
"Unit";"Hydralisk";"Larva";166;2
"Unit";"Hydralisk";"Larva";166;2
"Unit";"Hydralisk";"Larva";166;2
"Unit";"Hydralisk";"Larva";166;2
"Unit";"Hydralisk";"Larva";166;2
"Building";"CreepTumor";NA;168;0
"Building";"CreepTumor";NA;168;0
"Building";"CreepTumor";NA;208;0
"Building";"CreepTumor";NA;208;0
"Building";"CreepTumor";NA;208;0
"Building";"CreepTumor";NA;208;0
"Building";"CreepTumor";NA;208;0
"Building";"CreepTumor";NA;208;0
"Building";"Hatchery";NA;166;0
"Building";"CreepTumor";NA;208;0
"Building";"CreepTumor";NA;208;0
"Building";"CreepTumor";NA;208;0
"Building";"CreepTumor";NA;208;0
"Building";"CreepTumor";NA;208;0
"Building";"Extractor";NA;212;0
"Building";"Extractor";NA;212;0
"Building";"Hatchery";NA;168;0
"Unit";"Hydralisk";"Larva";212;2
"Unit";"Hydralisk";"Larva";214;2
"Unit";"Hydralisk";"Larva";214;2
"Unit";"Hydralisk";"Larva";214;2
"Unit";"Hydralisk";"Larva";214;2
"Unit";"Hydralisk";"Larva";214;2
"Unit";"Hydralisk";"Larva";214;2
"Unit";"Hydralisk";"Larva";214;2
"Unit";"Hydralisk";"Larva";214;2
"Unit";"Hydralisk";"Larva";214;2
"Unit";"Hydralisk";"Larva";214;2
"Unit";"Hydralisk";"Larva";214;2
"Unit";"Hydralisk";"Larva";214;2
"Upgrade";"EvolveMuscularAugments";"HydraliskDen";212;0
"Unit";"Zergling";"Larva";214;1
"Unit";"Zergling";"Larva";214;1
"Unit";"Zergling";"Larva";214;1
"Unit";"Zergling";"Larva";214;1
"Unit";"Roach";"Larva";214;2
"Unit";"Roach";"Larva";214;2
"Unit";"Roach";"Larva";214;2
"Unit";"Roach";"Larva";214;2
"Unit";"Roach";"Larva";214;2
"Unit";"Roach";"Larva";214;2
"Unit";"Roach";"Larva";214;2
"Unit";"Roach";"Larva";214;2
"Unit";"Roach";"Larva";214;2
"Unit";"Roach";"Larva";214;2
"Unit";"Roach";"Larva";214;2
"Unit";"Hydralisk";"Larva";214;2
"Unit";"Hydralisk";"Larva";214;2
"Unit";"Hydralisk";"Larva";214;2
"Unit";"Hydralisk";"Larva";214;2
"Unit";"Hydralisk";"Larva";214;2
"Unit";"Hydralisk";"Larva";214;2
"Unit";"Hydralisk";"Larva";214;2
"Unit";"Hydralisk";"Larva";214;2
"Building";"Spire";NA;212;0
"Building";"CreepTumor";NA;280;0
"Building";"CreepTumor";NA;280;0
"Building";"CreepTumor";NA;280;0
"Building";"CreepTumor";NA;280;0
"Building";"CreepTumor";NA;280;0
"Upgrade";"ZergMissileWeaponsLevel2";"EvolutionChamber";212;0
"Upgrade";"ZergGroundArmorsLevel2";"EvolutionChamber";212;0
"Building";"CreepTumor";NA;280;0
"Building";"CreepTumor";NA;280;0
"Building";"CreepTumor";NA;280;0
"Unit";"Hydralisk";"Larva";280;2
"Building";"Extractor";NA;280;0
"Unit";"Roach";"Larva";282;2
"Unit";"Roach";"Larva";282;2
"Unit";"Roach";"Larva";282;2
"Unit";"Roach";"Larva";282;2
"Unit";"Roach";"Larva";282;2
"Unit";"Roach";"Larva";282;2
"Unit";"Hydralisk";"Larva";294;2
"Unit";"Hydralisk";"Larva";294;2
"Unit";"Hydralisk";"Larva";294;2
"Unit";"Hydralisk";"Larva";294;2
"Unit";"Hydralisk";"Larva";294;2
"Unit";"Hydralisk";"Larva";294;2
"Unit";"Hydralisk";"Larva";294;2
"Unit";"Hydralisk";"Larva";294;2
"Unit";"Hydralisk";"Larva";294;2
"Unit";"Hydralisk";"Larva";294;2
"Unit";"Hydralisk";"Larva";294;2
"Unit";"Hydralisk";"Larva";294;2
"Unit";"Hydralisk";"Larva";294;2
"Unit";"Hydralisk";"Larva";294;2
"Unit";"Hydralisk";"Larva";294;2
"Unit";"Hydralisk";"Larva";294;2
"Unit";"Hydralisk";"Larva";294;2
"Unit";"Hydralisk";"Larva";294;2
"Unit";"Hydralisk";"Larva";294;2
"Unit";"Hydralisk";"Larva";294;2
"Unit";"Hydralisk";"Larva";294;2
"Unit";"Hydralisk";"Larva";294;2
"Unit";"Hydralisk";"Larva";294;2
"Unit";"Hydralisk";"Larva";294;2
"Unit";"Hydralisk";"Larva";294;2
"Unit";"Hydralisk";"Larva";294;2
"Unit";"Hydralisk";"Larva";294;2
"Unit";"Infestor";"Larva";294;2
"Unit";"Hydralisk";"Larva";294;2
"Unit";"Hydralisk";"Larva";294;2
"Unit";"Hydralisk";"Larva";294;2
"Unit";"Hydralisk";"Larva";294;2
"Building";"Extractor";NA;348;0
"Unit";"Roach";"Larva";358;2
"Unit";"Roach";"Larva";358;2
"Unit";"Roach";"Larva";358;2
"Unit";"Roach";"Larva";358;2
"Unit";"Roach";"Larva";358;2
"Unit";"Roach";"Larva";358;2
"Unit";"Roach";"Larva";358;2
"Unit";"Roach";"Larva";358;2
"Unit";"Infestor";"Larva";358;2
"Unit";"Infestor";"Larva";358;2
"Unit";"Infestor";"Larva";358;2
"Upgrade";"ZergMissileWeaponsLevel3";"EvolutionChamber";294;0
"Upgrade";"ZergGroundArmorsLevel3";"EvolutionChamber";294;0
"Unit";"Queen";"Hatchery";358;2
"Unit";"Queen";"Hatchery";388;2
"Building";"Hatchery";NA;358;0
"Unit";"Hydralisk";"Larva";396;2
"Unit";"Hydralisk";"Larva";396;2
"Unit";"Hydralisk";"Larva";396;2
"Unit";"Hydralisk";"Larva";396;2
"Unit";"Hydralisk";"Larva";396;2
"Unit";"Hydralisk";"Larva";396;2
"Unit";"Hydralisk";"Larva";396;2
"Unit";"Hydralisk";"Larva";396;2
"Unit";"Hydralisk";"Larva";396;2
"Unit";"Hydralisk";"Larva";396;2
"Unit";"Hydralisk";"Larva";396;2
"Building";"CreepTumor";NA;398;0
"Unit";"Roach";"Larva";420;2
"Unit";"Roach";"Larva";420;2
"Unit";"Roach";"Larva";420;2
"Building";"Hatchery";NA;388;0
"Unit";"Queen";"Hatchery";420;2
"Upgrade";"Burrow";"Hatchery";420;0
"Unit";"Hydralisk";"Larva";441;2
"Unit";"Hydralisk";"Larva";441;2
"Unit";"Hydralisk";"Larva";441;2
"Unit";"Hydralisk";"Larva";441;2
"Unit";"Hydralisk";"Larva";441;2
"Unit";"Hydralisk";"Larva";441;2
"Unit";"Hydralisk";"Larva";441;2
"Unit";"Hydralisk";"Larva";441;2
"Upgrade";"TunnelingClaws";"RoachWarren";439;0
"Building";"Extractor";NA;441;0
"Building";"CreepTumor";NA;458;0
"Unit";"Corruptor";"Larva";458;2
"Unit";"Corruptor";"Larva";458;2
"Unit";"Corruptor";"Larva";458;2
"Unit";"Corruptor";"Larva";458;2
"Unit";"Corruptor";"Larva";458;2
"Unit";"Corruptor";"Larva";458;2
"Unit";"Corruptor";"Larva";458;2
"Unit";"Corruptor";"Larva";458;2
"Unit";"Corruptor";"Larva";458;2
"Unit";"Corruptor";"Larva";458;2
"Unit";"Corruptor";"Larva";458;2
"Unit";"Corruptor";"Larva";458;2
"Unit";"Corruptor";"Larva";458;2
"Unit";"Corruptor";"Larva";458;2
"Unit";"Hydralisk";"Larva";458;2
"Unit";"Hydralisk";"Larva";458;2
"Unit";"Hydralisk";"Larva";458;2
"Unit";"Hydralisk";"Larva";458;2
"Unit";"Hydralisk";"Larva";458;2
"Unit";"Hydralisk";"Larva";458;2
"Unit";"Hydralisk";"Larva";458;2
"Unit";"Hydralisk";"Larva";458;2
"Unit";"Hydralisk";"Larva";458;2
"Unit";"Hydralisk";"Larva";458;2
"Unit";"Hydralisk";"Larva";458;2
"Unit";"Hydralisk";"Larva";458;2
"Unit";"Hydralisk";"Larva";458;2
"Unit";"Hydralisk";"Larva";458;2
"Unit";"Hydralisk";"Larva";458;2
"Unit";"Hydralisk";"Larva";458;2
"Unit";"Hydralisk";"Larva";458;2
"Unit";"Hydralisk";"Larva";458;2
"Unit";"Hydralisk";"Larva";458;2
"Unit";"Hydralisk";"Larva";458;2
"Unit";"Hydralisk";"Larva";458;2
"Unit";"Hydralisk";"Larva";458;2
"Unit";"Queen";"Hatchery";458;2
"Unit";"Infestor";"Larva";458;2
"Unit";"Infestor";"Larva";458;2
"Unit";"Infestor";"Larva";458;2
"Unit";"Infestor";"Larva";458;2
"Unit";"Roach";"Larva";540;2
"Unit";"Roach";"Larva";540;2
"Unit";"Roach";"Larva";540;2
"Building";"SporeCrawler";NA;546;0
"Unit";"Roach";"Larva";546;2
"Unit";"Roach";"Larva";546;2
"Unit";"Roach";"Larva";546;2
"Unit";"Roach";"Larva";546;2
"Building";"Hatchery";NA;546;0
"Building";"Hatchery";NA;546;0
"Building";"SporeCrawler";NA;554;0
