"type";"unit_name";"on_building";"total_supply";"supply"
"Unit";"Overlord";"Larva";13;0
"Building";"Extractor";NA;19;0
"Unit";"Overlord";"Larva";21;0
"Building";"SpawningPool";NA;19;0
"Building";"Hatchery";NA;17;0
"Unit";"Zergling";"Larva";24;1
"Unit";"Zergling";"Larva";24;1
"Unit";"Zergling";"Larva";25;1
"Unit";"Zergling";"Larva";25;1
"Unit";"Queen";"Hatchery";22;2
"Unit";"Queen";"Hatchery";23;2
"Unit";"Overlord";"Larva";35;0
"Unit";"Queen";"Hatchery";35;2
"Building";"CreepTumorQueen";NA;40;0
"Unit";"Overlord";"Larva";40;0
"Unit";"Overlord";"Larva";45;0
"Unit";"Zergling";"Larva";45;1
"Unit";"Zergling";"Larva";45;1
"Building";"Hatchery";NA;33;0
"Unit";"Zergling";"Larva";45;1
"Unit";"Zergling";"Larva";45;1
"Unit";"Queen";"Hatchery";49;2
"Unit";"Zergling";"Larva";53;1
"Unit";"Zergling";"Larva";53;1
"Unit";"Zergling";"Larva";53;1
"Unit";"Zergling";"Larva";53;1
"Unit";"Zergling";"Larva";53;1
"Unit";"Zergling";"Larva";53;1
"Unit";"Zergling";"Larva";53;1
"Unit";"Zergling";"Larva";53;1
"Unit";"Zergling";"Larva";53;1
"Unit";"Zergling";"Larva";53;1
"Building";"CreepTumorQueen";NA;57;0
"Building";"EvolutionChamber";NA;53;0
"Building";"EvolutionChamber";NA;53;0
"Unit";"Queen";"Hatchery";53;2
"Building";"SporeCrawler";NA;69;0
"Building";"SporeCrawler";NA;69;0
"Building";"CreepTumorQueen";NA;78;0
"Building";"CreepTumor";NA;78;0
"Unit";"Queen";"Hatchery";69;2
"Building";"SporeCrawler";NA;78;0
"Unit";"Zergling";"Larva";84;1
"Unit";"Zergling";"Larva";84;1
"Unit";"Zergling";"Larva";84;1
"Unit";"Zergling";"Larva";84;1
"Unit";"Zergling";"Larva";84;1
"Unit";"Zergling";"Larva";84;1
"Unit";"Zergling";"Larva";84;1
"Unit";"Zergling";"Larva";84;1
"Unit";"Overlord";"Larva";84;0
"Unit";"Overlord";"Larva";84;0
"Building";"CreepTumorQueen";NA;94;0
"Building";"CreepTumor";NA;94;0
"Unit";"Zergling";"Larva";94;1
"Unit";"Zergling";"Larva";94;1
"Building";"CreepTumorQueen";NA;94;0
"Building";"Extractor";NA;86;0
"Unit";"Zergling";"Larva";94;1
"Unit";"Zergling";"Larva";94;1
"Unit";"Zergling";"Larva";94;1
"Unit";"Zergling";"Larva";94;1
"Unit";"Zergling";"Larva";94;1
"Unit";"Zergling";"Larva";94;1
"Unit";"Zergling";"Larva";94;1
"Unit";"Zergling";"Larva";94;1
"Unit";"Zergling";"Larva";94;1
"Unit";"Zergling";"Larva";94;1
"Unit";"Zergling";"Larva";94;1
"Unit";"Zergling";"Larva";94;1
"Unit";"Zergling";"Larva";94;1
"Unit";"Zergling";"Larva";94;1
"Unit";"Zergling";"Larva";94;1
"Unit";"Zergling";"Larva";94;1
"Unit";"Zergling";"Larva";94;1
"Unit";"Zergling";"Larva";94;1
"Unit";"Zergling";"Larva";94;1
"Unit";"Zergling";"Larva";94;1
"Building";"Extractor";NA;86;0
"Building";"CreepTumor";NA;116;0
"Building";"CreepTumor";NA;116;0
"Unit";"Queen";"Hatchery";94;2
"Unit";"Queen";"Hatchery";94;2
"Unit";"Overlord";"Larva";121;0
"Unit";"Overlord";"Larva";121;0
"Unit";"Overlord";"Larva";121;0
"Unit";"Overlord";"Larva";121;0
"Building";"CreepTumor";NA;124;0
"Building";"CreepTumorQueen";NA;128;0
"Unit";"Overlord";"Larva";128;0
"Unit";"Overlord";"Larva";128;0
"Unit";"Overlord";"Larva";128;0
"Upgrade";"ZergMeleeWeaponsLevel1";"EvolutionChamber";86;0
"Upgrade";"ZergGroundArmorsLevel1";"EvolutionChamber";116;0
"Building";"CreepTumor";NA;138;0
"Building";"CreepTumor";NA;138;0
"Building";"CreepTumor";NA;138;0
"Building";"Extractor";NA;138;0
"Building";"Extractor";NA;138;0
"Building";"CreepTumorQueen";NA;138;0
"Building";"CreepTumorQueen";NA;138;0
"Unit";"Zergling";"Larva";138;1
"Unit";"Zergling";"Larva";138;1
"Unit";"Zergling";"Larva";138;1
"Unit";"Zergling";"Larva";138;1
"Unit";"Zergling";"Larva";138;1
"Unit";"Zergling";"Larva";138;1
"Unit";"Zergling";"Larva";138;1
"Unit";"Zergling";"Larva";138;1
"Unit";"Zergling";"Larva";138;1
"Unit";"Zergling";"Larva";138;1
"Unit";"Zergling";"Larva";138;1
"Unit";"Zergling";"Larva";138;1
"Unit";"Zergling";"Larva";138;1
"Unit";"Zergling";"Larva";138;1
"Unit";"Zergling";"Larva";138;1
"Unit";"Zergling";"Larva";138;1
"Unit";"Zergling";"Larva";138;1
"Unit";"Zergling";"Larva";138;1
"Unit";"Zergling";"Larva";138;1
"Unit";"Zergling";"Larva";138;1
"Unit";"Zergling";"Larva";138;1
"Unit";"Zergling";"Larva";138;1
"Unit";"Zergling";"Larva";138;1
"Unit";"Zergling";"Larva";138;1
"Unit";"Zergling";"Larva";138;1
"Unit";"Zergling";"Larva";138;1
"Unit";"Zergling";"Larva";138;1
"Unit";"Zergling";"Larva";138;1
"Unit";"Zergling";"Larva";138;1
"Unit";"Zergling";"Larva";138;1
"Unit";"Zergling";"Larva";138;1
"Unit";"Zergling";"Larva";138;1
"Unit";"Zergling";"Larva";138;1
"Unit";"Zergling";"Larva";138;1
"Unit";"Zergling";"Larva";138;1
"Unit";"Zergling";"Larva";138;1
"Unit";"Overlord";"Larva";140;0
"Building";"BanelingNest";NA;138;0
"Unit";"Zergling";"Larva";178;1
"Unit";"Zergling";"Larva";178;1
"Unit";"Zergling";"Larva";178;1
"Unit";"Zergling";"Larva";178;1
"Unit";"Zergling";"Larva";178;1
"Unit";"Zergling";"Larva";178;1
"Unit";"Zergling";"Larva";178;1
"Unit";"Zergling";"Larva";178;1
"Unit";"Zergling";"Larva";178;1
"Unit";"Zergling";"Larva";178;1
"Unit";"Baneling";"Zergling";178;0
"Unit";"Baneling";"Zergling";178;0
"Unit";"Baneling";"Zergling";178;0
"Unit";"Baneling";"Zergling";178;0
"Unit";"Baneling";"Zergling";178;0
"Unit";"Baneling";"Zergling";178;0
"Building";"CreepTumorQueen";NA;188;0
"Building";"CreepTumor";NA;188;0
"Building";"CreepTumor";NA;188;0
"Building";"Extractor";NA;178;0
"Building";"CreepTumorQueen";NA;188;0
"Building";"CreepTumorQueen";NA;188;0
"Building";"CreepTumorQueen";NA;188;0
"Building";"Hatchery";NA;138;0
"Building";"CreepTumorQueen";NA;199;0
"Unit";"Overlord";"Larva";188;0
"Unit";"Overlord";"Larva";188;0
"Unit";"Zergling";"Larva";199;1
"Unit";"Zergling";"Larva";199;1
"Unit";"Zergling";"Larva";199;1
"Unit";"Zergling";"Larva";199;1
"Unit";"Zergling";"Larva";199;1
"Unit";"Zergling";"Larva";199;1
"Unit";"Zergling";"Larva";199;1
"Unit";"Zergling";"Larva";199;1
"Unit";"Zergling";"Larva";199;1
"Unit";"Zergling";"Larva";199;1
"Unit";"Zergling";"Larva";199;1
"Unit";"Zergling";"Larva";199;1
"Unit";"Zergling";"Larva";199;1
"Unit";"Zergling";"Larva";199;1
"Unit";"Zergling";"Larva";199;1
"Unit";"Zergling";"Larva";199;1
"Unit";"Zergling";"Larva";199;1
"Unit";"Zergling";"Larva";199;1
"Unit";"Baneling";"Zergling";199;0
"Unit";"Baneling";"Zergling";199;0
"Unit";"Zergling";"Larva";199;1
"Unit";"Zergling";"Larva";199;1
"Unit";"Zergling";"Larva";199;1
"Unit";"Zergling";"Larva";199;1
"Unit";"Zergling";"Larva";199;1
"Unit";"Zergling";"Larva";199;1
"Unit";"Zergling";"Larva";199;1
"Unit";"Zergling";"Larva";199;1
"Unit";"Zergling";"Larva";199;1
"Unit";"Zergling";"Larva";199;1
"Unit";"Zergling";"Larva";217;1
"Unit";"Zergling";"Larva";217;1
"Unit";"Zergling";"Larva";217;1
"Unit";"Zergling";"Larva";217;1
"Unit";"Zergling";"Larva";217;1
"Unit";"Zergling";"Larva";217;1
"Unit";"Zergling";"Larva";217;1
"Unit";"Zergling";"Larva";217;1
"Unit";"Zergling";"Larva";217;1
"Unit";"Zergling";"Larva";217;1
"Unit";"Zergling";"Larva";217;1
"Unit";"Zergling";"Larva";217;1
"Unit";"Zergling";"Larva";217;1
"Unit";"Zergling";"Larva";217;1
"Unit";"Zergling";"Larva";217;1
"Unit";"Zergling";"Larva";217;1
"Unit";"Queen";"Hatchery";199;2
"Unit";"Queen";"Hatchery";199;2
"Building";"CreepTumor";NA;245;0
"Building";"CreepTumor";NA;252;0
"Building";"CreepTumorQueen";NA;255;0
"Building";"HydraliskDen";NA;235;0
"Unit";"Zergling";"Larva";255;1
"Unit";"Zergling";"Larva";255;1
"Unit";"Zergling";"Larva";255;1
"Unit";"Zergling";"Larva";255;1
"Unit";"Zergling";"Larva";255;1
"Unit";"Zergling";"Larva";255;1
"Unit";"Zergling";"Larva";255;1
"Unit";"Zergling";"Larva";255;1
"Unit";"Zergling";"Larva";255;1
"Unit";"Zergling";"Larva";255;1
"Unit";"Zergling";"Larva";255;1
"Unit";"Zergling";"Larva";255;1
"Unit";"Zergling";"Larva";255;1
"Unit";"Zergling";"Larva";255;1
"Unit";"Zergling";"Larva";255;1
"Unit";"Zergling";"Larva";255;1
"Unit";"Zergling";"Larva";255;1
"Unit";"Zergling";"Larva";255;1
"Upgrade";"ZergMissileWeaponsLevel1";"EvolutionChamber";198;0
"Building";"CreepTumorQueen";NA;273;0
"Building";"CreepTumorQueen";NA;273;0
"Unit";"Overlord";"Larva";257;0
"Unit";"Overlord";"Larva";257;0
"Unit";"Hydralisk";"Larva";273;2
"Unit";"Hydralisk";"Larva";273;2
"Unit";"Hydralisk";"Larva";273;2
"Unit";"Hydralisk";"Larva";273;2
"Unit";"Hydralisk";"Larva";273;2
"Unit";"Baneling";"Zergling";280;0
"Unit";"Baneling";"Zergling";280;0
"Unit";"Baneling";"Zergling";280;0
"Unit";"Baneling";"Zergling";280;0
"Unit";"Baneling";"Zergling";280;0
"Building";"Extractor";NA;280;0
"Building";"SpineCrawler";NA;280;0
"Building";"Hatchery";NA;247;0
"Unit";"Zergling";"Larva";290;1
"Unit";"Zergling";"Larva";290;1
"Unit";"Zergling";"Larva";290;1
"Unit";"Zergling";"Larva";290;1
"Building";"SpineCrawler";NA;280;0
"Unit";"Zergling";"Larva";290;1
"Unit";"Zergling";"Larva";290;1
"Unit";"Zergling";"Larva";290;1
"Unit";"Zergling";"Larva";290;1
"Unit";"Zergling";"Larva";290;1
"Unit";"Zergling";"Larva";290;1
"Unit";"Zergling";"Larva";290;1
"Unit";"Zergling";"Larva";290;1
"Unit";"Zergling";"Larva";290;1
"Unit";"Zergling";"Larva";290;1
"Unit";"Zergling";"Larva";290;1
"Unit";"Zergling";"Larva";290;1
"Unit";"Zergling";"Larva";290;1
"Unit";"Zergling";"Larva";290;1
"Unit";"Zergling";"Larva";290;1
"Unit";"Zergling";"Larva";290;1
"Unit";"Zergling";"Larva";290;1
"Unit";"Zergling";"Larva";290;1
"Unit";"Zergling";"Larva";290;1
"Unit";"Zergling";"Larva";290;1
"Unit";"Zergling";"Larva";290;1
"Unit";"Zergling";"Larva";290;1
"Unit";"Zergling";"Larva";290;1
"Unit";"Zergling";"Larva";290;1
"Building";"Extractor";NA;290;0
"Unit";"Queen";"Hatchery";280;2
"Unit";"Queen";"Hatchery";280;2
"Unit";"Hydralisk";"Larva";290;2
"Building";"CreepTumor";NA;322;0
"Unit";"Hydralisk";"Larva";290;2
"Unit";"Hydralisk";"Larva";290;2
"Unit";"Hydralisk";"Larva";290;2
"Unit";"Hydralisk";"Larva";290;2
"Unit";"Hydralisk";"Larva";290;2
"Unit";"Hydralisk";"Larva";290;2
"Unit";"Hydralisk";"Larva";290;2
"Unit";"Hydralisk";"Larva";290;2
"Upgrade";"EvolveGroovedSpines";"HydraliskDen";280;0
"Unit";"Baneling";"Zergling";322;0
"Unit";"Baneling";"Zergling";322;0
"Unit";"Baneling";"Zergling";322;0
"Unit";"Baneling";"Zergling";322;0
"Unit";"Baneling";"Zergling";322;0
"Unit";"Zergling";"Larva";322;1
"Unit";"Zergling";"Larva";322;1
"Unit";"Zergling";"Larva";322;1
"Unit";"Zergling";"Larva";322;1
"Unit";"Zergling";"Larva";322;1
"Unit";"Zergling";"Larva";322;1
"Unit";"Zergling";"Larva";322;1
"Unit";"Zergling";"Larva";322;1
"Unit";"Zergling";"Larva";322;1
"Unit";"Zergling";"Larva";322;1
"Unit";"Zergling";"Larva";322;1
"Unit";"Zergling";"Larva";322;1
"Unit";"Zergling";"Larva";322;1
"Unit";"Zergling";"Larva";322;1
"Unit";"Zergling";"Larva";322;1
"Unit";"Zergling";"Larva";322;1
"Unit";"Zergling";"Larva";322;1
"Unit";"Zergling";"Larva";322;1
"Building";"CreepTumorQueen";NA;358;0
"Unit";"Baneling";"Zergling";342;0
"Unit";"Baneling";"Zergling";346;0
"Unit";"Baneling";"Zergling";354;0
"Upgrade";"ZergMeleeWeaponsLevel2";"EvolutionChamber";280;0
"Upgrade";"Burrow";"Hatchery";322;0
"Unit";"Queen";"Hatchery";340;2
"Unit";"Queen";"Hatchery";340;2
"Building";"CreepTumor";NA;358;0
"Unit";"Hydralisk";"Larva";358;2
"Unit";"Hydralisk";"Larva";358;2
"Unit";"Hydralisk";"Larva";358;2
"Unit";"Hydralisk";"Larva";358;2
"Unit";"Hydralisk";"Larva";358;2
"Unit";"Hydralisk";"Larva";358;2
"Unit";"Hydralisk";"Larva";358;2
"Unit";"Hydralisk";"Larva";358;2
"Unit";"Hydralisk";"Larva";358;2
"Unit";"Hydralisk";"Larva";358;2
"Unit";"Hydralisk";"Larva";358;2
"Unit";"Hydralisk";"Larva";358;2
"Unit";"Zergling";"Larva";365;1
"Unit";"Zergling";"Larva";365;1
"Unit";"Zergling";"Larva";365;1
"Unit";"Zergling";"Larva";365;1
"Unit";"Zergling";"Larva";365;1
"Unit";"Zergling";"Larva";365;1
"Unit";"Zergling";"Larva";365;1
"Unit";"Zergling";"Larva";365;1
"Unit";"Zergling";"Larva";365;1
"Unit";"Zergling";"Larva";365;1
"Unit";"Zergling";"Larva";365;1
"Unit";"Zergling";"Larva";365;1
"Unit";"Zergling";"Larva";365;1
"Unit";"Zergling";"Larva";365;1
"Building";"InfestationPit";NA;358;0
"Upgrade";"ZergGroundArmorsLevel2";"EvolutionChamber";290;0
"Unit";"Zergling";"Larva";403;1
"Unit";"Zergling";"Larva";403;1
"Unit";"Zergling";"Larva";403;1
"Unit";"Zergling";"Larva";403;1
"Unit";"Zergling";"Larva";403;1
"Unit";"Zergling";"Larva";403;1
"Unit";"Zergling";"Larva";403;1
"Unit";"Zergling";"Larva";403;1
"Unit";"Zergling";"Larva";403;1
"Unit";"Zergling";"Larva";403;1
"Unit";"Zergling";"Larva";403;1
"Unit";"Zergling";"Larva";403;1
"Unit";"Zergling";"Larva";403;1
"Unit";"Zergling";"Larva";403;1
"Unit";"Zergling";"Larva";403;1
"Unit";"Zergling";"Larva";403;1
"Unit";"Zergling";"Larva";403;1
"Unit";"Zergling";"Larva";403;1
"Unit";"Zergling";"Larva";403;1
"Unit";"Zergling";"Larva";403;1
"Unit";"Zergling";"Larva";403;1
"Unit";"Zergling";"Larva";403;1
"Unit";"Zergling";"Larva";403;1
"Unit";"Zergling";"Larva";403;1
"Unit";"Zergling";"Larva";403;1
"Unit";"Zergling";"Larva";403;1
"Unit";"Zergling";"Larva";403;1
"Unit";"Zergling";"Larva";403;1
"Unit";"Zergling";"Larva";403;1
"Unit";"Zergling";"Larva";403;1
"Unit";"Baneling";"Zergling";425;0
"Unit";"Baneling";"Zergling";425;0
"Unit";"Baneling";"Zergling";425;0
"Upgrade";"EvolveMuscularAugments";"HydraliskDen";365;0
"Unit";"Hydralisk";"Larva";436;2
"Unit";"Hydralisk";"Larva";436;2
"Unit";"Hydralisk";"Larva";436;2
"Unit";"Hydralisk";"Larva";436;2
"Unit";"Hydralisk";"Larva";436;2
"Unit";"Hydralisk";"Larva";436;2
"Building";"CreepTumor";NA;458;0
"Unit";"Baneling";"Zergling";458;0
"Unit";"Zergling";"Larva";458;1
"Unit";"Zergling";"Larva";458;1
"Unit";"Baneling";"Zergling";458;0
"Unit";"Baneling";"Zergling";458;0
"Unit";"Baneling";"Zergling";458;0
"Unit";"Zergling";"Larva";458;1
"Unit";"Zergling";"Larva";458;1
"Unit";"Zergling";"Larva";458;1
"Unit";"Zergling";"Larva";458;1
"Unit";"Zergling";"Larva";458;1
"Unit";"Zergling";"Larva";458;1
"Unit";"Zergling";"Larva";458;1
"Unit";"Zergling";"Larva";458;1
"Unit";"Zergling";"Larva";458;1
"Unit";"Zergling";"Larva";458;1
"Unit";"Zergling";"Larva";458;1
"Unit";"Zergling";"Larva";458;1
"Unit";"Zergling";"Larva";458;1
"Unit";"Zergling";"Larva";458;1
"Unit";"Zergling";"Larva";458;1
"Unit";"Zergling";"Larva";458;1
"Unit";"Zergling";"Larva";458;1
"Unit";"Zergling";"Larva";458;1
"Unit";"Zergling";"Larva";458;1
"Unit";"Zergling";"Larva";458;1
"Building";"SporeCrawler";NA;458;0
"Building";"SporeCrawler";NA;458;0
"Building";"SpineCrawler";NA;458;0
"Building";"Hatchery";NA;436;0
"Building";"SpineCrawler";NA;458;0
"Upgrade";"ZergMissileWeaponsLevel2";"EvolutionChamber";403;0
"Unit";"Baneling";"Zergling";480;0
"Unit";"Baneling";"Zergling";480;0
"Unit";"Zergling";"Larva";480;1
"Unit";"Zergling";"Larva";480;1
"Unit";"Zergling";"Larva";480;1
"Unit";"Zergling";"Larva";480;1
"Unit";"Zergling";"Larva";480;1
"Unit";"Zergling";"Larva";480;1
"Unit";"Zergling";"Larva";480;1
"Unit";"Zergling";"Larva";480;1
"Building";"Extractor";NA;480;0
"Building";"CreepTumorQueen";NA;480;0
"Unit";"Overlord";"Larva";480;0
"Unit";"Overlord";"Larva";480;0
"Unit";"Overlord";"Larva";480;0
"Building";"Extractor";NA;480;0
"Unit";"Overlord";"Larva";480;0
"Unit";"Overlord";"Larva";480;0
"Building";"CreepTumorQueen";NA;480;0
"Building";"CreepTumorQueen";NA;486;0
"Building";"CreepTumorQueen";NA;488;0
"Unit";"Hydralisk";"Larva";480;2
"Unit";"Hydralisk";"Larva";480;2
"Unit";"Hydralisk";"Larva";480;2
"Unit";"Hydralisk";"Larva";480;2
"Unit";"Hydralisk";"Larva";480;2
"Unit";"Hydralisk";"Larva";480;2
"Unit";"Hydralisk";"Larva";480;2
"Unit";"Hydralisk";"Larva";480;2
"Unit";"Hydralisk";"Larva";480;2
"Unit";"Hydralisk";"Larva";480;2
"Building";"CreepTumorQueen";NA;488;0
"Building";"CreepTumorQueen";NA;488;0
"Building";"CreepTumorQueen";NA;488;0
"Building";"CreepTumorQueen";NA;488;0
"Unit";"Zergling";"Larva";488;1
"Unit";"Zergling";"Larva";488;1
"Unit";"Zergling";"Larva";488;1
"Unit";"Zergling";"Larva";488;1
"Unit";"Zergling";"Larva";488;1
"Unit";"Zergling";"Larva";488;1
"Unit";"Zergling";"Larva";488;1
"Unit";"Zergling";"Larva";488;1
"Unit";"Zergling";"Larva";488;1
"Unit";"Zergling";"Larva";488;1
"Unit";"Zergling";"Larva";488;1
"Unit";"Zergling";"Larva";488;1
"Unit";"Zergling";"Larva";488;1
"Unit";"Zergling";"Larva";488;1
"Unit";"Zergling";"Larva";488;1
"Unit";"Zergling";"Larva";488;1
"Unit";"Zergling";"Larva";488;1
"Unit";"Zergling";"Larva";488;1
"Unit";"Zergling";"Larva";488;1
"Unit";"Zergling";"Larva";488;1
"Unit";"Zergling";"Larva";488;1
"Unit";"Zergling";"Larva";488;1
"Unit";"Zergling";"Larva";488;1
"Unit";"Zergling";"Larva";488;1
"Unit";"Zergling";"Larva";488;1
"Unit";"Zergling";"Larva";488;1
"Unit";"Zergling";"Larva";488;1
"Unit";"Zergling";"Larva";488;1
"Unit";"Baneling";"Zergling";488;0
"Unit";"Baneling";"Zergling";488;0
"Unit";"Baneling";"Zergling";488;0
"Unit";"Baneling";"Zergling";488;0
"Unit";"Baneling";"Zergling";488;0
"Unit";"Baneling";"Zergling";488;0
"Unit";"Baneling";"Zergling";488;0
"Unit";"Baneling";"Zergling";488;0
"Unit";"Baneling";"Zergling";488;0
"Building";"SpineCrawler";NA;488;0
"Unit";"Zergling";"Larva";536;1
"Unit";"Zergling";"Larva";536;1
"Unit";"Zergling";"Larva";536;1
"Unit";"Zergling";"Larva";536;1
"Unit";"Zergling";"Larva";536;1
"Unit";"Zergling";"Larva";536;1
"Unit";"Zergling";"Larva";536;1
"Unit";"Zergling";"Larva";536;1
"Unit";"Zergling";"Larva";536;1
"Unit";"Zergling";"Larva";536;1
"Unit";"Zergling";"Larva";536;1
"Unit";"Zergling";"Larva";536;1
"Unit";"Zergling";"Larva";536;1
"Unit";"Zergling";"Larva";536;1
"Unit";"Zergling";"Larva";536;1
"Unit";"Zergling";"Larva";536;1
"Unit";"Zergling";"Larva";536;1
"Unit";"Zergling";"Larva";536;1
"Building";"CreepTumor";NA;536;0
"Unit";"Hydralisk";"Larva";536;2
"Unit";"Hydralisk";"Larva";536;2
"Unit";"Hydralisk";"Larva";536;2
"Unit";"Hydralisk";"Larva";536;2
"Unit";"Hydralisk";"Larva";536;2
"Unit";"Hydralisk";"Larva";536;2
"Unit";"Hydralisk";"Larva";536;2
"Unit";"Hydralisk";"Larva";536;2
"Unit";"Hydralisk";"Larva";536;2
"Unit";"Hydralisk";"Larva";536;2
"Unit";"Zergling";"Larva";554;1
"Unit";"Zergling";"Larva";554;1
"Unit";"Zergling";"Larva";554;1
"Unit";"Zergling";"Larva";554;1
"Unit";"Zergling";"Larva";554;1
"Unit";"Zergling";"Larva";554;1
"Unit";"Zergling";"Larva";554;1
"Unit";"Zergling";"Larva";554;1
"Unit";"Zergling";"Larva";554;1
"Unit";"Zergling";"Larva";554;1
"Unit";"Zergling";"Larva";554;1
"Unit";"Zergling";"Larva";554;1
"Unit";"Zergling";"Larva";554;1
"Unit";"Zergling";"Larva";554;1
"Unit";"Zergling";"Larva";554;1
"Unit";"Zergling";"Larva";554;1
"Unit";"Zergling";"Larva";554;1
"Unit";"Zergling";"Larva";554;1
"Unit";"Zergling";"Larva";554;1
"Unit";"Zergling";"Larva";554;1
"Unit";"Zergling";"Larva";554;1
"Unit";"Zergling";"Larva";554;1
"Building";"CreepTumor";NA;574;0
"Building";"CreepTumor";NA;574;0
"Building";"CreepTumor";NA;574;0
"Building";"CreepTumor";NA;574;0
"Building";"CreepTumor";NA;574;0
"Building";"CreepTumor";NA;576;0
"Building";"CreepTumor";NA;574;0
"Building";"CreepTumor";NA;596;0
"Building";"CreepTumorQueen";NA;596;0
"Unit";"Baneling";"Zergling";596;0
"Unit";"Baneling";"Zergling";596;0
"Unit";"Baneling";"Zergling";596;0
"Unit";"Baneling";"Zergling";596;0
"Unit";"Baneling";"Zergling";596;0
"Unit";"Baneling";"Zergling";596;0
"Unit";"Zergling";"Larva";596;1
"Unit";"Zergling";"Larva";596;1
"Unit";"Zergling";"Larva";596;1
"Unit";"Zergling";"Larva";596;1
"Unit";"Zergling";"Larva";596;1
"Unit";"Zergling";"Larva";596;1
"Unit";"Zergling";"Larva";596;1
"Unit";"Zergling";"Larva";596;1
"Unit";"Zergling";"Larva";596;1
"Unit";"Zergling";"Larva";596;1
"Building";"CreepTumor";NA;604;0
"Building";"UltraliskCavern";NA;574;0
"Unit";"Zergling";"Larva";604;1
"Unit";"Zergling";"Larva";604;1
"Unit";"Zergling";"Larva";606;1
"Unit";"Zergling";"Larva";606;1
"Unit";"Zergling";"Larva";614;1
"Unit";"Zergling";"Larva";614;1
"Unit";"Zergling";"Larva";614;1
"Unit";"Zergling";"Larva";614;1
"Unit";"Zergling";"Larva";614;1
"Unit";"Zergling";"Larva";614;1
"Unit";"Zergling";"Larva";614;1
"Unit";"Zergling";"Larva";614;1
"Unit";"Zergling";"Larva";614;1
"Unit";"Zergling";"Larva";614;1
"Unit";"Zergling";"Larva";614;1
"Unit";"Zergling";"Larva";614;1
"Unit";"Zergling";"Larva";614;1
"Unit";"Zergling";"Larva";614;1
"Unit";"Zergling";"Larva";614;1
"Unit";"Zergling";"Larva";614;1
"Unit";"Zergling";"Larva";614;1
"Unit";"Zergling";"Larva";614;1
"Unit";"Zergling";"Larva";614;1
"Unit";"Zergling";"Larva";614;1
"Unit";"Baneling";"Zergling";614;0
"Unit";"Baneling";"Zergling";614;0
"Unit";"Baneling";"Zergling";614;0
"Unit";"Zergling";"Larva";618;1
"Unit";"Zergling";"Larva";618;1
"Unit";"Zergling";"Larva";620;1
"Unit";"Zergling";"Larva";620;1
"Unit";"Zergling";"Larva";620;1
"Unit";"Zergling";"Larva";620;1
"Unit";"Zergling";"Larva";624;1
"Unit";"Zergling";"Larva";624;1
"Unit";"Zergling";"Larva";628;1
"Unit";"Zergling";"Larva";628;1
"Unit";"Zergling";"Larva";628;1
"Unit";"Zergling";"Larva";628;1
"Unit";"Zergling";"Larva";632;1
"Unit";"Zergling";"Larva";632;1
"Unit";"Zergling";"Larva";632;1
"Unit";"Zergling";"Larva";632;1
"Unit";"Zergling";"Larva";636;1
"Unit";"Zergling";"Larva";636;1
"Unit";"Zergling";"Larva";636;1
"Unit";"Zergling";"Larva";636;1
"Unit";"Zergling";"Larva";638;1
"Unit";"Zergling";"Larva";638;1
"Unit";"Zergling";"Larva";638;1
"Unit";"Zergling";"Larva";638;1
"Building";"CreepTumor";NA;662;0
"Unit";"Hydralisk";"Larva";662;2
"Unit";"Hydralisk";"Larva";662;2
"Unit";"Hydralisk";"Larva";662;2
"Unit";"Hydralisk";"Larva";662;2
"Unit";"Hydralisk";"Larva";662;2
"Unit";"Hydralisk";"Larva";662;2
"Unit";"Hydralisk";"Larva";662;2
"Unit";"Hydralisk";"Larva";662;2
"Unit";"Hydralisk";"Larva";662;2
"Unit";"Hydralisk";"Larva";662;2
"Unit";"Hydralisk";"Larva";662;2
"Unit";"Hydralisk";"Larva";662;2
"Building";"CreepTumor";NA;662;0
"Building";"CreepTumor";NA;662;0
"Unit";"Baneling";"Zergling";686;0
"Unit";"Baneling";"Zergling";686;0
"Unit";"Baneling";"Zergling";686;0
"Unit";"Baneling";"Zergling";686;0
"Unit";"Baneling";"Zergling";686;0
"Unit";"Zergling";"Larva";686;1
"Unit";"Zergling";"Larva";686;1
"Unit";"Baneling";"Zergling";686;0
"Unit";"Zergling";"Larva";686;1
"Unit";"Zergling";"Larva";686;1
"Unit";"Zergling";"Larva";686;1
"Unit";"Zergling";"Larva";686;1
"Unit";"Zergling";"Larva";686;1
"Unit";"Zergling";"Larva";686;1
"Unit";"Zergling";"Larva";686;1
"Unit";"Zergling";"Larva";686;1
"Unit";"Zergling";"Larva";686;1
"Unit";"Zergling";"Larva";686;1
"Unit";"Zergling";"Larva";686;1
"Unit";"Zergling";"Larva";686;1
"Unit";"Zergling";"Larva";686;1
"Unit";"Zergling";"Larva";686;1
"Unit";"Zergling";"Larva";686;1
"Unit";"Zergling";"Larva";686;1
"Unit";"Ultralisk";"Larva";662;6
"Unit";"Ultralisk";"Larva";662;6
"Unit";"Zergling";"Larva";686;1
"Unit";"Zergling";"Larva";686;1
"Unit";"Zergling";"Larva";686;1
"Unit";"Zergling";"Larva";686;1
"Unit";"Zergling";"Larva";686;1
"Unit";"Zergling";"Larva";686;1
"Unit";"Infestor";"Larva";664;2
"Unit";"Infestor";"Larva";682;2
"Unit";"Infestor";"Larva";686;2
"Unit";"Zergling";"Larva";688;1
"Unit";"Zergling";"Larva";688;1
"Unit";"Zergling";"Larva";688;1
"Unit";"Zergling";"Larva";688;1
"Unit";"Zergling";"Larva";688;1
"Unit";"Zergling";"Larva";688;1
"Unit";"Zergling";"Larva";688;1
"Unit";"Zergling";"Larva";688;1
"Unit";"Zergling";"Larva";688;1
"Unit";"Zergling";"Larva";688;1
"Unit";"Zergling";"Larva";688;1
"Unit";"Zergling";"Larva";688;1
"Building";"CreepTumor";NA;702;0
"Building";"CreepTumor";NA;702;0
"Unit";"Zergling";"Larva";702;1
"Unit";"Zergling";"Larva";702;1
"Unit";"Zergling";"Larva";702;1
"Unit";"Zergling";"Larva";702;1
"Unit";"Zergling";"Larva";702;1
"Unit";"Zergling";"Larva";702;1
"Unit";"Zergling";"Larva";702;1
"Unit";"Zergling";"Larva";702;1
"Unit";"Baneling";"Zergling";702;0
"Unit";"Baneling";"Zergling";710;0
"Unit";"Baneling";"Zergling";710;0
"Unit";"Baneling";"Zergling";716;0
"Upgrade";"ZergMeleeWeaponsLevel3";"EvolutionChamber";614;0
"Upgrade";"ZergGroundArmorsLevel3";"EvolutionChamber";614;0
"Unit";"Baneling";"Zergling";748;0
"Unit";"Baneling";"Zergling";748;0
"Unit";"Baneling";"Zergling";748;0
"Building";"CreepTumor";NA;748;0
"Upgrade";"ChitinousPlating";"UltraliskCavern";686;0
"Unit";"Ultralisk";"Larva";748;6
"Unit";"Infestor";"Larva";748;2
"Unit";"Infestor";"Larva";748;2
"Unit";"Infestor";"Larva";748;2
"Unit";"Infestor";"Larva";748;2
"Unit";"Zergling";"Larva";754;1
"Unit";"Zergling";"Larva";754;1
"Unit";"Zergling";"Larva";754;1
"Unit";"Zergling";"Larva";754;1
"Unit";"Zergling";"Larva";754;1
"Unit";"Zergling";"Larva";754;1
"Unit";"Zergling";"Larva";754;1
"Unit";"Zergling";"Larva";754;1
"Unit";"Zergling";"Larva";754;1
"Unit";"Zergling";"Larva";754;1
"Unit";"Zergling";"Larva";754;1
"Unit";"Zergling";"Larva";754;1
"Unit";"Zergling";"Larva";754;1
"Unit";"Zergling";"Larva";754;1
"Unit";"Zergling";"Larva";754;1
"Unit";"Zergling";"Larva";754;1
"Unit";"Zergling";"Larva";754;1
"Unit";"Zergling";"Larva";754;1
"Building";"CreepTumor";NA;762;0
"Building";"CreepTumor";NA;762;0
"Building";"CreepTumor";NA;762;0
"Building";"CreepTumor";NA;762;0
"Building";"CreepTumor";NA;762;0
"Unit";"Hydralisk";"Larva";760;2
"Building";"Hatchery";NA;748;0
"Building";"CreepTumor";NA;782;0
"Building";"CreepTumor";NA;782;0
"Building";"Hatchery";NA;754;0
"Unit";"Ultralisk";"Larva";782;6
"Building";"CreepTumor";NA;782;0
"Unit";"Hydralisk";"Larva";782;2
"Unit";"Hydralisk";"Larva";782;2
"Unit";"Hydralisk";"Larva";782;2
"Building";"CreepTumor";NA;782;0
"Building";"Extractor";NA;782;0
"Building";"Extractor";NA;782;0
"Unit";"Baneling";"Zergling";788;0
"Unit";"Baneling";"Zergling";788;0
"Unit";"Baneling";"Zergling";788;0
"Unit";"Hydralisk";"Larva";782;2
"Unit";"Hydralisk";"Larva";782;2
"Unit";"Hydralisk";"Larva";782;2
"Unit";"Hydralisk";"Larva";782;2
"Unit";"Hydralisk";"Larva";802;2
"Unit";"Hydralisk";"Larva";802;2
"Unit";"Hydralisk";"Larva";802;2
"Unit";"Hydralisk";"Larva";802;2
"Unit";"Hydralisk";"Larva";802;2
"Unit";"Hydralisk";"Larva";802;2
"Unit";"Hydralisk";"Larva";802;2
"Unit";"Hydralisk";"Larva";802;2
"Unit";"Hydralisk";"Larva";802;2
"Unit";"Hydralisk";"Larva";802;2
"Unit";"Hydralisk";"Larva";802;2
"Unit";"Hydralisk";"Larva";802;2
"Unit";"Hydralisk";"Larva";802;2
"Unit";"Hydralisk";"Larva";802;2
"Building";"Hatchery";NA;782;0
"Building";"CreepTumor";NA;802;0
"Unit";"Zergling";"Larva";802;1
"Unit";"Zergling";"Larva";802;1
"Unit";"Zergling";"Larva";802;1
"Unit";"Zergling";"Larva";802;1
"Unit";"Zergling";"Larva";802;1
"Unit";"Zergling";"Larva";802;1
"Unit";"Zergling";"Larva";802;1
"Unit";"Zergling";"Larva";802;1
"Building";"CreepTumor";NA;830;0
"Building";"CreepTumor";NA;830;0
"Unit";"Zergling";"Larva";830;1
"Unit";"Zergling";"Larva";830;1
"Unit";"Queen";"Hatchery";802;2
"Unit";"Zergling";"Larva";830;1
"Unit";"Zergling";"Larva";830;1
"Unit";"Zergling";"Larva";830;1
"Unit";"Zergling";"Larva";830;1
"Unit";"Zergling";"Larva";830;1
"Unit";"Zergling";"Larva";830;1
"Building";"CreepTumorQueen";NA;838;0
"Building";"CreepTumor";NA;846;0
"Building";"CreepTumor";NA;848;0
"Building";"CreepTumor";NA;848;0
"Building";"CreepTumor";NA;848;0
"Unit";"Queen";"Hatchery";838;2
"Unit";"Baneling";"Zergling";848;0
"Unit";"Baneling";"Zergling";848;0
"Unit";"Infestor";"Larva";838;2
"Unit";"Infestor";"Larva";838;2
"Unit";"Ultralisk";"Larva";838;6
"Unit";"Hydralisk";"Larva";848;2
"Unit";"Hydralisk";"Larva";848;2
"Unit";"Hydralisk";"Larva";848;2
"Unit";"Hydralisk";"Larva";848;2
"Unit";"Hydralisk";"Larva";848;2
"Unit";"Hydralisk";"Larva";848;2
"Building";"CreepTumor";NA;848;0
"Unit";"Zergling";"Larva";848;1
"Unit";"Zergling";"Larva";848;1
"Unit";"Zergling";"Larva";848;1
"Unit";"Zergling";"Larva";848;1
"Unit";"Zergling";"Larva";848;1
"Unit";"Zergling";"Larva";848;1
"Unit";"Zergling";"Larva";848;1
"Unit";"Zergling";"Larva";848;1
"Building";"CreepTumor";NA;883;0
"Unit";"Hydralisk";"Larva";883;2
"Unit";"Hydralisk";"Larva";883;2
"Unit";"Hydralisk";"Larva";883;2
"Unit";"Hydralisk";"Larva";883;2
"Unit";"Hydralisk";"Larva";883;2
"Unit";"Hydralisk";"Larva";883;2
"Unit";"Hydralisk";"Larva";883;2
"Unit";"Hydralisk";"Larva";883;2
"Unit";"Zergling";"Larva";883;1
"Unit";"Zergling";"Larva";883;1
"Unit";"Zergling";"Larva";883;1
"Unit";"Zergling";"Larva";883;1
"Unit";"Zergling";"Larva";883;1
"Unit";"Zergling";"Larva";883;1
"Unit";"Zergling";"Larva";883;1
"Unit";"Zergling";"Larva";883;1
"Unit";"Zergling";"Larva";883;1
"Unit";"Zergling";"Larva";883;1
"Unit";"Zergling";"Larva";883;1
"Unit";"Zergling";"Larva";883;1
"Unit";"Zergling";"Larva";883;1
"Unit";"Zergling";"Larva";883;1
"Unit";"Zergling";"Larva";883;1
"Unit";"Zergling";"Larva";883;1
"Unit";"Zergling";"Larva";883;1
"Unit";"Zergling";"Larva";883;1
"Unit";"Zergling";"Larva";883;1
"Unit";"Zergling";"Larva";883;1
"Unit";"Zergling";"Larva";883;1
"Unit";"Zergling";"Larva";883;1
"Building";"CreepTumor";NA;899;0
"Unit";"Zergling";"Larva";883;1
"Unit";"Zergling";"Larva";883;1
"Unit";"Zergling";"Larva";883;1
"Unit";"Zergling";"Larva";883;1
"Unit";"Zergling";"Larva";883;1
"Unit";"Zergling";"Larva";883;1
"Unit";"Zergling";"Larva";883;1
"Unit";"Zergling";"Larva";883;1
"Unit";"Zergling";"Larva";883;1
"Unit";"Zergling";"Larva";883;1
"Building";"CreepTumor";NA;899;0
"Building";"Spire";NA;883;0
"Building";"CreepTumor";NA;931;0
"Building";"CreepTumor";NA;931;0
"Building";"CreepTumor";NA;931;0
"Building";"CreepTumorQueen";NA;931;0
"Unit";"Zergling";"Larva";931;1
"Unit";"Zergling";"Larva";931;1
"Unit";"Zergling";"Larva";931;1
"Unit";"Zergling";"Larva";931;1
"Unit";"Zergling";"Larva";931;1
"Unit";"Zergling";"Larva";931;1
"Unit";"Zergling";"Larva";931;1
"Unit";"Zergling";"Larva";931;1
"Unit";"Zergling";"Larva";931;1
"Unit";"Zergling";"Larva";931;1
"Unit";"Zergling";"Larva";931;1
"Unit";"Zergling";"Larva";931;1
"Unit";"Zergling";"Larva";931;1
"Unit";"Zergling";"Larva";931;1
"Unit";"Zergling";"Larva";931;1
"Unit";"Zergling";"Larva";931;1
"Building";"Hatchery";NA;931;0
"Unit";"Ultralisk";"Larva";931;6
"Unit";"Ultralisk";"Larva";931;6
"Unit";"Ultralisk";"Larva";931;6
"Building";"Hatchery";NA;931;0
"Unit";"Ultralisk";"Larva";933;6
"Unit";"Corruptor";"Larva";965;2
"Unit";"Corruptor";"Larva";965;2
"Unit";"Corruptor";"Larva";965;2
"Unit";"Hydralisk";"Larva";982;2
"Unit";"Hydralisk";"Larva";984;2
"Unit";"Hydralisk";"Larva";984;2
"Unit";"Hydralisk";"Larva";984;2
"Unit";"Zergling";"Larva";992;1
"Unit";"Zergling";"Larva";992;1
"Unit";"Zergling";"Larva";992;1
"Unit";"Zergling";"Larva";992;1
"Unit";"Zergling";"Larva";992;1
"Unit";"Zergling";"Larva";992;1
"Unit";"Zergling";"Larva";992;1
"Unit";"Zergling";"Larva";992;1
"Unit";"Zergling";"Larva";992;1
"Unit";"Zergling";"Larva";992;1
"Unit";"Zergling";"Larva";992;1
"Unit";"Zergling";"Larva";992;1
"Unit";"Zergling";"Larva";992;1
"Unit";"Zergling";"Larva";992;1
"Unit";"Zergling";"Larva";992;1
"Unit";"Zergling";"Larva";992;1
"Unit";"Ultralisk";"Larva";984;6
"Unit";"Ultralisk";"Larva";984;6
"Unit";"Ultralisk";"Larva";984;6
"Building";"CreepTumor";NA;1008;0
"Building";"Extractor";NA;992;0
"Building";"CreepTumor";NA;1008;0
"Building";"CreepTumorQueen";NA;1026;0
"Building";"Extractor";NA;1008;0
"Unit";"Infestor";"Larva";1008;2
"Unit";"Infestor";"Larva";1008;2
"Unit";"Corruptor";"Larva";1008;2
"Unit";"Corruptor";"Larva";1008;2
"Unit";"Corruptor";"Larva";1008;2
"Unit";"Corruptor";"Larva";1008;2
"Building";"CreepTumor";NA;1026;0
"Unit";"Zergling";"Larva";1026;1
"Unit";"Zergling";"Larva";1026;1
"Unit";"Zergling";"Larva";1026;1
"Unit";"Zergling";"Larva";1026;1
"Unit";"Zergling";"Larva";1026;1
"Unit";"Zergling";"Larva";1026;1
"Unit";"Zergling";"Larva";1026;1
"Unit";"Zergling";"Larva";1026;1
"Unit";"Zergling";"Larva";1026;1
"Unit";"Zergling";"Larva";1026;1
"Unit";"Zergling";"Larva";1026;1
"Unit";"Zergling";"Larva";1026;1
"Unit";"Zergling";"Larva";1026;1
"Unit";"Zergling";"Larva";1026;1
"Unit";"Zergling";"Larva";1026;1
"Unit";"Zergling";"Larva";1026;1
"Building";"CreepTumor";NA;1026;0
"Building";"CreepTumor";NA;1026;0
"Unit";"Ultralisk";"Larva";1026;6
"Building";"Extractor";NA;1030;0
"Unit";"Zergling";"Larva";1054;1
"Unit";"Zergling";"Larva";1054;1
"Unit";"Zergling";"Larva";1054;1
"Unit";"Zergling";"Larva";1054;1
"Unit";"Zergling";"Larva";1054;1
"Unit";"Zergling";"Larva";1054;1
"Unit";"Zergling";"Larva";1054;1
"Unit";"Zergling";"Larva";1054;1
"Unit";"Ultralisk";"Larva";1038;6
"Unit";"Ultralisk";"Larva";1038;6
"Building";"CreepTumor";NA;1068;0
