"type";"unit_name";"on_building";"total_supply_lag";"supply"
"Unit";"Overlord";"Larva";13;0
"Building";"Hatchery";NA;16;0
"Building";"SpawningPool";NA;18;0
"Building";"Extractor";NA;18;0
"Unit";"Overlord";"Larva";22;0
"Unit";"Queen";"Hatchery";23;2
"Unit";"Queen";"Hatchery";25;2
"Unit";"Zergling";"Larva";27;1
"Unit";"Zergling";"Larva";28;1
"Unit";"Zergling";"Larva";29;1
"Unit";"Zergling";"Larva";30;1
"Building";"Hatchery";NA;35;0
"Building";"CreepTumorQueen";NA;35;0
"Unit";"Queen";"Hatchery";35;2
"Unit";"Overlord";"Larva";37;0
"Building";"CreepTumor";NA;42;0
"Building";"CreepTumorQueen";NA;42;0
"Unit";"Zergling";"Larva";45;1
"Unit";"Zergling";"Larva";46;1
"Unit";"Zergling";"Larva";47;1
"Unit";"Zergling";"Larva";48;1
"Unit";"Queen";"Hatchery";49;2
"Unit";"Overlord";"Larva";51;0
"Unit";"Overlord";"Larva";52;0
"Building";"CreepTumor";NA;52;0
"Building";"CreepTumor";NA;52;0
"Building";"BanelingNest";NA;52;0
"Unit";"Zergling";"Larva";52;1
"Unit";"Zergling";"Larva";53;1
"Building";"CreepTumorQueen";NA;54;0
"Unit";"Overlord";"Larva";54;0
"Unit";"Zergling";"Larva";54;1
"Unit";"Zergling";"Larva";55;1
"Unit";"Zergling";"Larva";56;1
"Unit";"Zergling";"Larva";57;1
"Unit";"Queen";"Hatchery";60;2
"Unit";"Overlord";"Larva";62;0
"Building";"CreepTumor";NA;62;0
"Building";"CreepTumor";NA;62;0
"Unit";"Zergling";"Larva";64;1
"Unit";"Zergling";"Larva";65;1
"Building";"CreepTumorQueen";NA;66;0
"Unit";"Overlord";"Larva";66;0
"Unit";"Zergling";"Larva";66;1
"Unit";"Zergling";"Larva";67;1
"Unit";"Zergling";"Larva";68;1
"Unit";"Zergling";"Larva";69;1
"Unit";"Zergling";"Larva";70;1
"Unit";"Zergling";"Larva";71;1
"Unit";"Zergling";"Larva";72;1
"Unit";"Zergling";"Larva";73;1
"Unit";"Baneling";"Zergling";75;0
"Unit";"Baneling";"Zergling";75;0
"Unit";"Baneling";"Zergling";75;0
"Unit";"Overlord";"Larva";77;0
"Unit";"Baneling";"Zergling";77;0
"Unit";"Baneling";"Zergling";77;0
"Building";"SporeCrawler";NA;77;0
"Unit";"Queen";"Hatchery";77;2
"Unit";"Baneling";"Zergling";79;0
"Unit";"Baneling";"Zergling";79;0
"Unit";"Overlord";"Larva";81;0
"Unit";"Baneling";"Zergling";84;0
"Unit";"Baneling";"Zergling";84;0
"Unit";"Zergling";"Larva";84;1
"Unit";"Zergling";"Larva";85;1
"Unit";"Zergling";"Larva";86;1
"Unit";"Zergling";"Larva";87;1
"Unit";"Zergling";"Larva";88;1
"Unit";"Zergling";"Larva";89;1
"Building";"CreepTumor";NA;90;0
"Building";"CreepTumorQueen";NA;93;0
"Unit";"Zergling";"Larva";93;1
"Unit";"Zergling";"Larva";94;1
"Unit";"Overlord";"Larva";95;0
"Unit";"Zergling";"Larva";95;1
"Unit";"Zergling";"Larva";96;1
"Unit";"Zergling";"Larva";97;1
"Unit";"Zergling";"Larva";98;1
"Unit";"Zergling";"Larva";99;1
"Unit";"Zergling";"Larva";100;1
"Unit";"Zergling";"Larva";101;1
"Unit";"Zergling";"Larva";102;1
"Unit";"Zergling";"Larva";103;1
"Unit";"Zergling";"Larva";104;1
"Unit";"Baneling";"Zergling";105;0
"Unit";"Baneling";"Zergling";105;0
"Unit";"Baneling";"Zergling";105;0
"Unit";"Baneling";"Zergling";105;0
"Unit";"Zergling";"Larva";105;1
"Unit";"Zergling";"Larva";106;1
"Unit";"Zergling";"Larva";107;1
"Unit";"Zergling";"Larva";108;1
"Unit";"Zergling";"Larva";109;1
"Unit";"Zergling";"Larva";110;1
"Unit";"Queen";"Hatchery";111;2
"Unit";"Queen";"Hatchery";113;2
"Building";"CreepTumorQueen";NA;125;0
"Building";"CreepTumorQueen";NA;125;0
"Building";"Extractor";NA;125;0
"Building";"Extractor";NA;131;0
"Building";"Extractor";NA;131;0
"Building";"CreepTumor";NA;131;0
"Building";"CreepTumor";NA;131;0
"Building";"CreepTumorQueen";NA;131;0
"Unit";"Zergling";"Larva";131;1
"Unit";"Zergling";"Larva";132;1
"Building";"CreepTumor";NA;133;0
"Building";"EvolutionChamber";NA;135;0
"Building";"CreepTumor";NA;135;0
"Building";"EvolutionChamber";NA;136;0
"Building";"SporeCrawler";NA;139;0
"Building";"Extractor";NA;142;0
"Building";"CreepTumor";NA;142;0
"Building";"CreepTumor";NA;142;0
"Building";"CreepTumor";NA;142;0
"Unit";"Zergling";"Larva";142;1
"Unit";"Zergling";"Larva";143;1
"Unit";"Zergling";"Larva";144;1
"Unit";"Zergling";"Larva";145;1
"Unit";"Zergling";"Larva";146;1
"Unit";"Zergling";"Larva";147;1
"Building";"CreepTumor";NA;148;0
"Building";"CreepTumor";NA;148;0
"Building";"Hatchery";NA;148;0
"Building";"SporeCrawler";NA;149;0
"Unit";"Zergling";"Larva";149;1
"Unit";"Zergling";"Larva";150;1
"Unit";"Zergling";"Larva";151;1
"Unit";"Zergling";"Larva";152;1
"Unit";"Overlord";"Larva";159;0
"Unit";"Queen";"Hatchery";159;2
"Unit";"Overlord";"Larva";164;0
"Unit";"Baneling";"Zergling";164;0
"Unit";"Baneling";"Zergling";164;0
"Unit";"Baneling";"Zergling";164;0
"Unit";"Baneling";"Zergling";164;0
"Unit";"Baneling";"Zergling";164;0
"Unit";"Baneling";"Zergling";164;0
"Unit";"Baneling";"Zergling";164;0
"Building";"Hatchery";NA;164;0
"Unit";"Zergling";"Larva";164;1
"Unit";"Zergling";"Larva";165;1
"Unit";"Zergling";"Larva";166;1
"Unit";"Zergling";"Larva";167;1
"Unit";"Zergling";"Larva";168;1
"Unit";"Zergling";"Larva";169;1
"Unit";"Zergling";"Larva";170;1
"Unit";"Zergling";"Larva";171;1
"Unit";"Zergling";"Larva";172;1
"Unit";"Zergling";"Larva";173;1
"Unit";"Zergling";"Larva";174;1
"Unit";"Zergling";"Larva";175;1
"Building";"CreepTumor";NA;176;0
"Unit";"Queen";"Hatchery";176;2
"Building";"CreepTumor";NA;178;0
"Unit";"Baneling";"Zergling";178;0
"Unit";"Baneling";"Zergling";178;0
"Unit";"Baneling";"Zergling";178;0
"Unit";"Baneling";"Zergling";178;0
"Unit";"Baneling";"Zergling";178;0
"Unit";"Baneling";"Zergling";178;0
"Unit";"Queen";"Hatchery";179;2
"Unit";"Zergling";"Larva";183;1
"Unit";"Zergling";"Larva";184;1
"Building";"CreepTumor";NA;185;0
"Building";"CreepTumor";NA;185;0
"Building";"CreepTumor";NA;185;0
"Building";"CreepTumor";NA;185;0
"Unit";"Zergling";"Larva";185;1
"Unit";"Zergling";"Larva";186;1
"Unit";"Zergling";"Larva";187;1
"Unit";"Zergling";"Larva";188;1
"Unit";"Zergling";"Larva";189;1
"Unit";"Zergling";"Larva";190;1
"Unit";"Zergling";"Larva";191;1
"Unit";"Zergling";"Larva";192;1
"Building";"CreepTumor";NA;193;0
"Unit";"Zergling";"Larva";196;1
"Unit";"Zergling";"Larva";197;1
"Unit";"Zergling";"Larva";198;1
"Unit";"Zergling";"Larva";199;1
"Unit";"Zergling";"Larva";200;1
"Unit";"Zergling";"Larva";201;1
"Unit";"Zergling";"Larva";202;1
"Unit";"Zergling";"Larva";203;1
"Unit";"Zergling";"Larva";204;1
"Unit";"Zergling";"Larva";205;1
"Unit";"Zergling";"Larva";206;1
"Unit";"Zergling";"Larva";207;1
"Unit";"Zergling";"Larva";208;1
"Unit";"Zergling";"Larva";209;1
"Unit";"Zergling";"Larva";210;1
"Unit";"Zergling";"Larva";211;1
"Unit";"Queen";"Hatchery";212;2
"Unit";"Queen";"Hatchery";214;2
"Unit";"Overlord";"Larva";216;0
"Unit";"Queen";"Hatchery";216;2
"Unit";"Zergling";"Larva";218;1
"Unit";"Zergling";"Larva";219;1
"Unit";"Zergling";"Larva";220;1
"Unit";"Zergling";"Larva";221;1
"Unit";"Zergling";"Larva";222;1
"Unit";"Zergling";"Larva";223;1
"Unit";"Baneling";"Zergling";224;0
"Unit";"Baneling";"Zergling";224;0
"Unit";"Baneling";"Zergling";224;0
"Unit";"Baneling";"Zergling";224;0
"Unit";"Baneling";"Zergling";224;0
"Unit";"Baneling";"Zergling";224;0
"Unit";"Baneling";"Zergling";224;0
"Unit";"Baneling";"Zergling";224;0
"Unit";"Zergling";"Larva";224;1
"Unit";"Zergling";"Larva";225;1
"Unit";"Zergling";"Larva";235;1
"Unit";"Zergling";"Larva";236;1
"Building";"HydraliskDen";NA;237;0
"Unit";"Zergling";"Larva";237;1
"Unit";"Zergling";"Larva";238;1
"Unit";"Zergling";"Larva";239;1
"Unit";"Zergling";"Larva";240;1
"Unit";"Zergling";"Larva";241;1
"Unit";"Zergling";"Larva";242;1
"Unit";"Baneling";"Zergling";243;0
"Unit";"Baneling";"Zergling";243;0
"Unit";"Baneling";"Zergling";243;0
"Building";"CreepTumorQueen";NA;243;0
"Building";"CreepTumorQueen";NA;243;0
"Unit";"Overlord";"Larva";243;0
"Building";"CreepTumorQueen";NA;243;0
"Unit";"Overlord";"Larva";243;0
"Unit";"Zergling";"Larva";247;1
"Unit";"Zergling";"Larva";248;1
"Unit";"Zergling";"Larva";249;1
"Unit";"Zergling";"Larva";250;1
"Unit";"Zergling";"Larva";251;1
"Unit";"Zergling";"Larva";252;1
"Unit";"Baneling";"Zergling";253;0
"Unit";"Baneling";"Zergling";253;0
"Unit";"Baneling";"Zergling";253;0
"Unit";"Baneling";"Zergling";253;0
"Unit";"Baneling";"Zergling";253;0
"Unit";"Baneling";"Zergling";253;0
"Unit";"Baneling";"Zergling";253;0
"Unit";"Baneling";"Zergling";253;0
"Unit";"Baneling";"Zergling";253;0
"Building";"SporeCrawler";NA;254;0
"Unit";"Zergling";"Larva";254;1
"Unit";"Zergling";"Larva";255;1
"Unit";"Zergling";"Larva";256;1
"Unit";"Zergling";"Larva";257;1
"Unit";"Zergling";"Larva";258;1
"Unit";"Zergling";"Larva";259;1
"Unit";"Zergling";"Larva";260;1
"Unit";"Zergling";"Larva";261;1
"Unit";"Zergling";"Larva";262;1
"Unit";"Zergling";"Larva";263;1
"Unit";"Zergling";"Larva";264;1
"Unit";"Zergling";"Larva";265;1
"Unit";"Zergling";"Larva";266;1
"Unit";"Zergling";"Larva";267;1
"Unit";"Zergling";"Larva";268;1
"Unit";"Zergling";"Larva";269;1
"Unit";"Zergling";"Larva";270;1
"Unit";"Zergling";"Larva";271;1
"Unit";"Zergling";"Larva";272;1
"Unit";"Zergling";"Larva";273;1
"Unit";"Zergling";"Larva";274;1
"Unit";"Zergling";"Larva";275;1
"Building";"CreepTumorQueen";NA;276;0
"Unit";"Hydralisk";"Larva";276;2
"Unit";"Hydralisk";"Larva";278;2
"Unit";"Hydralisk";"Larva";280;2
"Unit";"Hydralisk";"Larva";282;2
"Building";"CreepTumorQueen";NA;284;0
"Building";"CreepTumorQueen";NA;284;0
"Building";"CreepTumor";NA;285;0
"Unit";"Overlord";"Larva";285;0
"Unit";"Overlord";"Larva";285;0
"Unit";"Overlord";"Larva";285;0
"Building";"CreepTumor";NA;285;0
"Building";"CreepTumor";NA;285;0
"Building";"InfestationPit";NA;285;0
"Unit";"Overlord";"Larva";285;0
"Unit";"Baneling";"Zergling";285;0
"Unit";"Baneling";"Zergling";285;0
"Building";"Extractor";NA;285;0
"Unit";"Overlord";"Larva";285;0
"Building";"CreepTumorQueen";NA;288;0
"Unit";"Overlord";"Larva";288;0
"Building";"CreepTumorQueen";NA;288;0
"Unit";"Zergling";"Larva";288;1
"Unit";"Zergling";"Larva";289;1
"Unit";"Zergling";"Larva";290;1
"Unit";"Zergling";"Larva";291;1
"Unit";"Zergling";"Larva";292;1
"Unit";"Zergling";"Larva";293;1
"Unit";"Zergling";"Larva";294;1
"Unit";"Zergling";"Larva";295;1
"Unit";"Zergling";"Larva";296;1
"Unit";"Zergling";"Larva";297;1
"Unit";"Zergling";"Larva";298;1
"Unit";"Zergling";"Larva";299;1
"Unit";"Zergling";"Larva";300;1
"Unit";"Zergling";"Larva";301;1
"Unit";"Zergling";"Larva";302;1
"Unit";"Zergling";"Larva";303;1
"Unit";"Zergling";"Larva";304;1
"Unit";"Zergling";"Larva";305;1
"Unit";"Zergling";"Larva";306;1
"Unit";"Zergling";"Larva";307;1
"Unit";"Zergling";"Larva";308;1
"Unit";"Zergling";"Larva";309;1
"Unit";"Zergling";"Larva";310;1
"Unit";"Zergling";"Larva";311;1
"Unit";"Zergling";"Larva";312;1
"Unit";"Zergling";"Larva";313;1
"Unit";"Hydralisk";"Larva";314;2
"Unit";"Hydralisk";"Larva";316;2
"Unit";"Zergling";"Larva";318;1
"Unit";"Zergling";"Larva";319;1
"Unit";"Zergling";"Larva";320;1
"Unit";"Zergling";"Larva";321;1
"Unit";"Zergling";"Larva";322;1
"Unit";"Zergling";"Larva";323;1
"Unit";"Zergling";"Larva";324;1
"Unit";"Zergling";"Larva";325;1
"Unit";"Zergling";"Larva";326;1
"Unit";"Zergling";"Larva";327;1
"Unit";"Zergling";"Larva";328;1
"Unit";"Zergling";"Larva";329;1
"Building";"CreepTumor";NA;330;0
"Building";"CreepTumor";NA;330;0
"Building";"CreepTumor";NA;330;0
"Building";"CreepTumor";NA;330;0
"Building";"CreepTumorQueen";NA;330;0
"Building";"CreepTumorQueen";NA;330;0
"Building";"CreepTumorQueen";NA;330;0
"Unit";"Zergling";"Larva";330;1
"Unit";"Zergling";"Larva";331;1
"Unit";"Zergling";"Larva";332;1
"Unit";"Zergling";"Larva";333;1
"Unit";"Zergling";"Larva";334;1
"Unit";"Zergling";"Larva";335;1
"Unit";"Zergling";"Larva";336;1
"Unit";"Zergling";"Larva";337;1
"Unit";"Zergling";"Larva";338;1
"Unit";"Zergling";"Larva";339;1
"Building";"CreepTumorQueen";NA;340;0
"Unit";"Zergling";"Larva";340;1
"Unit";"Zergling";"Larva";341;1
"Unit";"Zergling";"Larva";342;1
"Unit";"Zergling";"Larva";343;1
"Unit";"Zergling";"Larva";344;1
"Unit";"Zergling";"Larva";345;1
"Unit";"Zergling";"Larva";346;1
"Unit";"Zergling";"Larva";347;1
"Unit";"Zergling";"Larva";348;1
"Unit";"Zergling";"Larva";349;1
"Unit";"Zergling";"Larva";350;1
"Unit";"Zergling";"Larva";351;1
"Unit";"Zergling";"Larva";352;1
"Unit";"Zergling";"Larva";353;1
"Unit";"Zergling";"Larva";354;1
"Unit";"Zergling";"Larva";355;1
"Unit";"Zergling";"Larva";356;1
"Unit";"Zergling";"Larva";357;1
"Unit";"Zergling";"Larva";358;1
"Unit";"Zergling";"Larva";359;1
"Unit";"Zergling";"Larva";360;1
"Unit";"Zergling";"Larva";361;1
"Unit";"Zergling";"Larva";362;1
"Unit";"Zergling";"Larva";363;1
"Unit";"Zergling";"Larva";364;1
"Unit";"Zergling";"Larva";365;1
"Building";"Hatchery";NA;366;0
"Unit";"Overlord";"Larva";366;0
"Unit";"Overlord";"Larva";366;0
"Unit";"Overlord";"Larva";366;0
"Unit";"Overlord";"Larva";366;0
"Unit";"Overlord";"Larva";366;0
"Unit";"Hydralisk";"Larva";366;2
"Unit";"Hydralisk";"Larva";368;2
"Unit";"Hydralisk";"Larva";370;2
"Unit";"Hydralisk";"Larva";372;2
"Building";"CreepTumorQueen";NA;374;0
"Building";"CreepTumorQueen";NA;374;0
"Unit";"Hydralisk";"Larva";374;2
"Unit";"Hydralisk";"Larva";376;2
"Unit";"Hydralisk";"Larva";378;2
"Building";"CreepTumorQueen";NA;380;0
"Unit";"Hydralisk";"Larva";380;2
"Unit";"Zergling";"Larva";382;1
"Unit";"Zergling";"Larva";383;1
"Unit";"Zergling";"Larva";384;1
"Unit";"Zergling";"Larva";385;1
"Unit";"Zergling";"Larva";386;1
"Unit";"Zergling";"Larva";387;1
"Unit";"Zergling";"Larva";388;1
"Unit";"Zergling";"Larva";389;1
"Unit";"Zergling";"Larva";390;1
"Unit";"Zergling";"Larva";391;1
"Unit";"Zergling";"Larva";392;1
"Unit";"Zergling";"Larva";393;1
"Unit";"Zergling";"Larva";394;1
"Unit";"Zergling";"Larva";395;1
"Unit";"Zergling";"Larva";396;1
"Unit";"Zergling";"Larva";397;1
"Building";"CreepTumorQueen";NA;398;0
"Building";"CreepTumorQueen";NA;398;0
"Unit";"Zergling";"Larva";398;1
"Unit";"Zergling";"Larva";399;1
"Unit";"Zergling";"Larva";400;1
"Unit";"Zergling";"Larva";401;1
"Unit";"Zergling";"Larva";402;1
"Unit";"Zergling";"Larva";403;1
"Unit";"Zergling";"Larva";404;1
"Unit";"Zergling";"Larva";405;1
"Building";"CreepTumorQueen";NA;406;0
"Building";"Hatchery";NA;406;0
"Unit";"Zergling";"Larva";406;1
"Unit";"Zergling";"Larva";407;1
"Unit";"Zergling";"Larva";408;1
"Unit";"Zergling";"Larva";409;1
"Unit";"Zergling";"Larva";410;1
"Unit";"Zergling";"Larva";411;1
"Unit";"Zergling";"Larva";412;1
"Unit";"Zergling";"Larva";413;1
"Unit";"Zergling";"Larva";414;1
"Unit";"Zergling";"Larva";415;1
"Unit";"Zergling";"Larva";416;1
"Unit";"Zergling";"Larva";417;1
"Unit";"Zergling";"Larva";418;1
"Unit";"Zergling";"Larva";419;1
"Unit";"Zergling";"Larva";420;1
"Unit";"Zergling";"Larva";421;1
"Unit";"Zergling";"Larva";422;1
"Unit";"Zergling";"Larva";423;1
"Unit";"Zergling";"Larva";424;1
"Unit";"Zergling";"Larva";425;1
"Unit";"Zergling";"Larva";426;1
"Unit";"Zergling";"Larva";427;1
"Unit";"Zergling";"Larva";428;1
"Unit";"Zergling";"Larva";429;1
"Unit";"Zergling";"Larva";430;1
"Unit";"Zergling";"Larva";431;1
"Unit";"Zergling";"Larva";432;1
"Unit";"Zergling";"Larva";433;1
"Unit";"Zergling";"Larva";434;1
"Unit";"Zergling";"Larva";435;1
"Building";"CreepTumor";NA;436;0
"Building";"CreepTumor";NA;436;0
"Building";"CreepTumor";NA;436;0
"Building";"CreepTumor";NA;436;0
"Building";"CreepTumor";NA;436;0
"Unit";"Overlord";"Larva";436;0
"Unit";"Overlord";"Larva";436;0
"Unit";"Overlord";"Larva";436;0
"Unit";"Baneling";"Zergling";436;0
"Unit";"Baneling";"Zergling";436;0
"Unit";"Baneling";"Zergling";436;0
"Unit";"Baneling";"Zergling";436;0
"Unit";"Baneling";"Zergling";436;0
"Unit";"Baneling";"Zergling";436;0
"Unit";"Baneling";"Zergling";436;0
"Unit";"Baneling";"Zergling";436;0
"Unit";"Baneling";"Zergling";436;0
"Unit";"Baneling";"Zergling";436;0
"Unit";"Baneling";"Zergling";436;0
"Unit";"Baneling";"Zergling";436;0
"Unit";"Baneling";"Zergling";436;0
"Unit";"Baneling";"Zergling";436;0
"Unit";"Baneling";"Zergling";436;0
"Unit";"Baneling";"Zergling";436;0
"Unit";"Baneling";"Zergling";436;0
"Unit";"Baneling";"Zergling";436;0
"Unit";"Baneling";"Zergling";436;0
"Unit";"Baneling";"Zergling";436;0
"Unit";"Baneling";"Zergling";436;0
"Unit";"Zergling";"Larva";436;1
"Unit";"Zergling";"Larva";437;1
"Unit";"Zergling";"Larva";438;1
"Unit";"Zergling";"Larva";439;1
"Unit";"Zergling";"Larva";440;1
"Unit";"Zergling";"Larva";441;1
"Unit";"Zergling";"Larva";442;1
"Unit";"Zergling";"Larva";443;1
"Unit";"Zergling";"Larva";444;1
"Unit";"Zergling";"Larva";445;1
"Unit";"Zergling";"Larva";446;1
"Unit";"Zergling";"Larva";447;1
"Unit";"Zergling";"Larva";448;1
"Unit";"Zergling";"Larva";449;1
"Unit";"Zergling";"Larva";450;1
"Unit";"Zergling";"Larva";451;1
"Unit";"Zergling";"Larva";452;1
"Unit";"Zergling";"Larva";453;1
"Unit";"Overlord";"Larva";454;0
"Unit";"Overlord";"Larva";454;0
"Unit";"Overlord";"Larva";454;0
"Unit";"Zergling";"Larva";454;1
"Unit";"Zergling";"Larva";455;1
"Unit";"Zergling";"Larva";456;1
"Unit";"Zergling";"Larva";457;1
"Unit";"Zergling";"Larva";458;1
"Unit";"Zergling";"Larva";459;1
"Unit";"Zergling";"Larva";460;1
"Unit";"Zergling";"Larva";461;1
"Unit";"Zergling";"Larva";462;1
"Unit";"Zergling";"Larva";463;1
"Unit";"Zergling";"Larva";464;1
"Unit";"Zergling";"Larva";465;1
"Unit";"Zergling";"Larva";466;1
"Unit";"Zergling";"Larva";467;1
"Unit";"Zergling";"Larva";468;1
"Unit";"Zergling";"Larva";469;1
"Unit";"Zergling";"Larva";470;1
"Unit";"Zergling";"Larva";471;1
"Unit";"Zergling";"Larva";472;1
"Unit";"Zergling";"Larva";473;1
"Unit";"Zergling";"Larva";474;1
"Unit";"Zergling";"Larva";475;1
"Unit";"Zergling";"Larva";476;1
"Unit";"Zergling";"Larva";477;1
"Unit";"Zergling";"Larva";478;1
"Unit";"Zergling";"Larva";479;1
"Unit";"Zergling";"Larva";480;1
"Unit";"Zergling";"Larva";481;1
"Unit";"Zergling";"Larva";482;1
"Unit";"Zergling";"Larva";483;1
"Unit";"Zergling";"Larva";484;1
"Unit";"Zergling";"Larva";485;1
"Building";"CreepTumorQueen";NA;486;0
"Building";"CreepTumorQueen";NA;486;0
"Building";"SpawningPool";NA;486;0
"Unit";"Viper";"Larva";486;3
"Unit";"Viper";"Larva";489;3
"Unit";"Viper";"Larva";492;3
"Unit";"Baneling";"Zergling";495;0
"Unit";"Baneling";"Zergling";495;0
"Unit";"Baneling";"Zergling";495;0
"Unit";"Baneling";"Zergling";495;0
"Unit";"Baneling";"Zergling";495;0
"Unit";"Baneling";"Zergling";495;0
"Unit";"Baneling";"Zergling";495;0
"Unit";"Baneling";"Zergling";495;0
"Unit";"Baneling";"Zergling";495;0
"Unit";"Baneling";"Zergling";495;0
"Building";"CreepTumor";NA;504;0
"Unit";"Baneling";"Zergling";506;0
"Unit";"Baneling";"Zergling";506;0
"Unit";"Baneling";"Zergling";506;0
"Unit";"Baneling";"Zergling";506;0
"Unit";"Baneling";"Zergling";506;0
"Unit";"Baneling";"Zergling";506;0
"Unit";"Baneling";"Zergling";506;0
"Unit";"Baneling";"Zergling";506;0
"Unit";"Baneling";"Zergling";506;0
"Building";"CreepTumor";NA;506;0
"Unit";"Zergling";"Larva";506;1
"Unit";"Zergling";"Larva";507;1
"Unit";"Zergling";"Larva";508;1
"Unit";"Zergling";"Larva";509;1
"Unit";"Zergling";"Larva";510;1
"Unit";"Zergling";"Larva";511;1
"Unit";"Zergling";"Larva";512;1
"Unit";"Zergling";"Larva";513;1
"Unit";"Zergling";"Larva";514;1
"Unit";"Zergling";"Larva";515;1
"Unit";"Zergling";"Larva";516;1
"Unit";"Zergling";"Larva";517;1
"Unit";"Zergling";"Larva";518;1
"Unit";"Zergling";"Larva";519;1
"Unit";"Baneling";"Zergling";520;0
"Unit";"Baneling";"Zergling";520;0
"Unit";"Zergling";"Larva";520;1
"Unit";"Zergling";"Larva";521;1
"Unit";"Zergling";"Larva";522;1
"Unit";"Zergling";"Larva";523;1
"Unit";"Zergling";"Larva";524;1
"Unit";"Zergling";"Larva";525;1
"Unit";"Zergling";"Larva";526;1
"Unit";"Zergling";"Larva";527;1
"Unit";"Zergling";"Larva";528;1
"Unit";"Zergling";"Larva";529;1
"Unit";"Zergling";"Larva";530;1
"Unit";"Zergling";"Larva";531;1
"Unit";"Zergling";"Larva";532;1
"Unit";"Zergling";"Larva";533;1
"Unit";"Zergling";"Larva";534;1
"Unit";"Zergling";"Larva";535;1
"Unit";"Zergling";"Larva";536;1
"Unit";"Zergling";"Larva";537;1
"Unit";"Zergling";"Larva";538;1
"Unit";"Zergling";"Larva";539;1
"Unit";"Zergling";"Larva";540;1
"Unit";"Zergling";"Larva";541;1
"Unit";"Zergling";"Larva";542;1
"Unit";"Zergling";"Larva";543;1
"Unit";"Zergling";"Larva";544;1
"Unit";"Zergling";"Larva";545;1
"Unit";"Zergling";"Larva";546;1
"Unit";"Zergling";"Larva";547;1
"Unit";"Zergling";"Larva";548;1
"Unit";"Zergling";"Larva";549;1
"Unit";"Zergling";"Larva";550;1
"Unit";"Zergling";"Larva";551;1
"Unit";"Zergling";"Larva";552;1
"Unit";"Zergling";"Larva";553;1
"Unit";"Zergling";"Larva";554;1
"Unit";"Zergling";"Larva";555;1
"Unit";"Zergling";"Larva";556;1
"Unit";"Zergling";"Larva";557;1
"Unit";"Zergling";"Larva";558;1
"Unit";"Zergling";"Larva";559;1
"Unit";"Zergling";"Larva";560;1
"Unit";"Zergling";"Larva";561;1
"Unit";"Zergling";"Larva";562;1
"Unit";"Zergling";"Larva";563;1
"Unit";"Zergling";"Larva";564;1
"Unit";"Zergling";"Larva";565;1
"Unit";"Zergling";"Larva";566;1
"Unit";"Zergling";"Larva";567;1
"Unit";"Zergling";"Larva";568;1
"Unit";"Zergling";"Larva";569;1
"Unit";"Zergling";"Larva";570;1
"Unit";"Zergling";"Larva";571;1
"Unit";"Zergling";"Larva";572;1
"Unit";"Zergling";"Larva";573;1
"Unit";"Zergling";"Larva";574;1
"Unit";"Zergling";"Larva";575;1
"Unit";"Hydralisk";"Larva";576;2
"Unit";"Hydralisk";"Larva";578;2
"Unit";"Hydralisk";"Larva";580;2
"Building";"UltraliskCavern";NA;582;0
"Unit";"Hydralisk";"Larva";582;2
"Unit";"Hydralisk";"Larva";584;2
"Unit";"Hydralisk";"Larva";586;2
"Building";"CreepTumor";NA;588;0
"Unit";"Baneling";"Zergling";588;0
"Unit";"Baneling";"Zergling";588;0
"Unit";"Baneling";"Zergling";588;0
"Unit";"Baneling";"Zergling";588;0
"Unit";"Baneling";"Zergling";588;0
"Unit";"Baneling";"Zergling";588;0
"Unit";"Baneling";"Zergling";588;0
"Building";"CreepTumorQueen";NA;589;0
"Unit";"Zergling";"Larva";594;1
"Unit";"Zergling";"Larva";595;1
"Unit";"Zergling";"Larva";596;1
"Unit";"Zergling";"Larva";597;1
"Unit";"Zergling";"Larva";598;1
"Unit";"Zergling";"Larva";599;1
"Unit";"Zergling";"Larva";600;1
"Unit";"Zergling";"Larva";601;1
"Unit";"Queen";"Hatchery";602;2
"Unit";"Queen";"Hatchery";604;2
"Unit";"Queen";"Hatchery";606;2
"Building";"CreepTumorQueen";NA;608;0
"Unit";"Zergling";"Larva";608;1
"Unit";"Zergling";"Larva";609;1
"Building";"CreepTumorQueen";NA;610;0
"Unit";"Zergling";"Larva";610;1
"Unit";"Zergling";"Larva";611;1
"Unit";"Zergling";"Larva";612;1
"Unit";"Zergling";"Larva";613;1
"Unit";"Zergling";"Larva";614;1
"Unit";"Zergling";"Larva";615;1
"Unit";"Zergling";"Larva";616;1
"Unit";"Zergling";"Larva";617;1
"Unit";"Zergling";"Larva";618;1
"Unit";"Zergling";"Larva";619;1
"Unit";"Zergling";"Larva";620;1
"Unit";"Zergling";"Larva";621;1
"Unit";"Zergling";"Larva";622;1
"Unit";"Zergling";"Larva";623;1
"Building";"CreepTumorQueen";NA;624;0
"Building";"CreepTumor";NA;627;0
"Building";"CreepTumor";NA;627;0
"Building";"CreepTumorQueen";NA;627;0
"Unit";"Ultralisk";"Larva";627;6
"Unit";"Ultralisk";"Larva";633;6
"Building";"CreepTumor";NA;639;0
"Building";"CreepTumor";NA;639;0
"Unit";"Baneling";"Zergling";639;0
"Unit";"Baneling";"Zergling";639;0
"Unit";"Baneling";"Zergling";639;0
"Unit";"Baneling";"Zergling";639;0
"Unit";"Baneling";"Zergling";639;0
"Building";"Hatchery";NA;639;0
"Unit";"Overlord";"Larva";639;0
"Unit";"Overlord";"Larva";639;0
"Unit";"Ultralisk";"Larva";639;6
"Unit";"Zergling";"Larva";645;1
"Unit";"Zergling";"Larva";646;1
"Unit";"Zergling";"Larva";647;1
"Unit";"Zergling";"Larva";648;1
"Upgrade";"ChitinousPlating";"UltraliskCavern";649;0
"Unit";"Baneling";"Zergling";649;0
"Unit";"Baneling";"Zergling";649;0
"Unit";"Baneling";"Zergling";649;0
"Unit";"Baneling";"Zergling";649;0
"Unit";"Baneling";"Zergling";649;0
"Unit";"Baneling";"Zergling";649;0
"Unit";"Zergling";"Larva";649;1
"Unit";"Zergling";"Larva";650;1
"Unit";"Zergling";"Larva";651;1
"Unit";"Zergling";"Larva";652;1
"Unit";"Zergling";"Larva";653;1
"Unit";"Zergling";"Larva";654;1
"Unit";"Zergling";"Larva";655;1
"Unit";"Zergling";"Larva";656;1
"Unit";"Zergling";"Larva";657;1
"Unit";"Zergling";"Larva";658;1
"Unit";"Zergling";"Larva";659;1
"Unit";"Zergling";"Larva";660;1
"Unit";"Zergling";"Larva";661;1
"Unit";"Zergling";"Larva";662;1
"Unit";"Zergling";"Larva";663;1
"Unit";"Zergling";"Larva";664;1
"Unit";"Zergling";"Larva";665;1
"Unit";"Zergling";"Larva";666;1
"Unit";"Zergling";"Larva";667;1
"Unit";"Zergling";"Larva";668;1
"Unit";"Zergling";"Larva";669;1
"Unit";"Zergling";"Larva";670;1
"Unit";"Zergling";"Larva";671;1
"Unit";"Zergling";"Larva";672;1
"Unit";"Zergling";"Larva";673;1
"Unit";"Zergling";"Larva";674;1
"Unit";"Zergling";"Larva";675;1
"Unit";"Zergling";"Larva";676;1
"Unit";"Ultralisk";"Larva";677;6
"Unit";"Ultralisk";"Larva";683;6
"Unit";"Zergling";"Larva";689;1
"Unit";"Zergling";"Larva";690;1
"Unit";"Hydralisk";"Larva";691;2
"Unit";"Hydralisk";"Larva";693;2
"Unit";"Hydralisk";"Larva";695;2
"Unit";"Hydralisk";"Larva";697;2
"Unit";"Zergling";"Larva";699;1
"Unit";"Zergling";"Larva";700;1
"Unit";"Zergling";"Larva";701;1
"Unit";"Zergling";"Larva";702;1
"Unit";"Zergling";"Larva";703;1
"Unit";"Zergling";"Larva";704;1
"Building";"Hatchery";NA;705;0
"Unit";"Viper";"Larva";705;3
"Unit";"Viper";"Larva";708;3
"Unit";"Zergling";"Larva";711;1
"Unit";"Zergling";"Larva";712;1
"Unit";"Zergling";"Larva";713;1
"Unit";"Zergling";"Larva";714;1
"Unit";"Zergling";"Larva";715;1
"Unit";"Zergling";"Larva";716;1
"Unit";"Zergling";"Larva";717;1
"Unit";"Zergling";"Larva";718;1
"Unit";"Zergling";"Larva";719;1
"Unit";"Zergling";"Larva";720;1
"Unit";"Baneling";"Zergling";721;0
"Unit";"Baneling";"Zergling";721;0
"Unit";"Baneling";"Zergling";721;0
"Unit";"Baneling";"Zergling";721;0
"Unit";"Baneling";"Zergling";721;0
"Unit";"Baneling";"Zergling";721;0
"Unit";"Baneling";"Zergling";721;0
"Building";"CreepTumor";NA;721;0
"Unit";"Zergling";"Larva";721;1
"Unit";"Zergling";"Larva";722;1
"Unit";"Zergling";"Larva";723;1
"Unit";"Zergling";"Larva";724;1
"Unit";"Zergling";"Larva";725;1
"Unit";"Zergling";"Larva";726;1
"Unit";"Zergling";"Larva";727;1
"Unit";"Zergling";"Larva";728;1
"Unit";"Zergling";"Larva";729;1
"Unit";"Zergling";"Larva";730;1
"Unit";"Zergling";"Larva";731;1
"Unit";"Zergling";"Larva";732;1
"Unit";"Zergling";"Larva";733;1
"Unit";"Zergling";"Larva";734;1
"Unit";"Zergling";"Larva";735;1
"Unit";"Zergling";"Larva";736;1
"Building";"CreepTumor";NA;737;0
"Building";"CreepTumor";NA;737;0
"Building";"CreepTumor";NA;737;0
"Unit";"Hydralisk";"Larva";737;2
"Unit";"Hydralisk";"Larva";739;2
"Unit";"Hydralisk";"Larva";741;2
"Unit";"Zergling";"Larva";743;1
"Unit";"Zergling";"Larva";744;1
"Unit";"Zergling";"Larva";745;1
"Unit";"Zergling";"Larva";746;1
"Unit";"Zergling";"Larva";747;1
"Unit";"Zergling";"Larva";748;1
"Unit";"Zergling";"Larva";749;1
"Unit";"Zergling";"Larva";750;1
"Unit";"Zergling";"Larva";751;1
"Unit";"Zergling";"Larva";752;1
"Unit";"Zergling";"Larva";753;1
"Unit";"Zergling";"Larva";754;1
"Unit";"Zergling";"Larva";755;1
"Unit";"Zergling";"Larva";756;1
"Unit";"Zergling";"Larva";757;1
"Unit";"Zergling";"Larva";758;1
"Unit";"Zergling";"Larva";759;1
"Unit";"Zergling";"Larva";760;1
"Unit";"Zergling";"Larva";761;1
"Unit";"Zergling";"Larva";762;1
"Building";"Hatchery";NA;763;0
"Unit";"Zergling";"Larva";763;1
"Unit";"Zergling";"Larva";764;1
"Unit";"Zergling";"Larva";765;1
"Unit";"Zergling";"Larva";766;1
"Unit";"Zergling";"Larva";767;1
"Unit";"Zergling";"Larva";768;1
"Unit";"Zergling";"Larva";769;1
"Unit";"Zergling";"Larva";770;1
"Unit";"Zergling";"Larva";771;1
"Unit";"Zergling";"Larva";772;1
"Unit";"Zergling";"Larva";773;1
"Unit";"Zergling";"Larva";774;1
"Unit";"Zergling";"Larva";775;1
"Unit";"Zergling";"Larva";776;1
"Unit";"Zergling";"Larva";777;1
"Unit";"Zergling";"Larva";778;1
"Unit";"Zergling";"Larva";779;1
"Unit";"Zergling";"Larva";780;1
"Unit";"Zergling";"Larva";781;1
"Unit";"Zergling";"Larva";782;1
"Unit";"Zergling";"Larva";783;1
"Unit";"Zergling";"Larva";784;1
"Unit";"Zergling";"Larva";785;1
"Unit";"Zergling";"Larva";786;1
"Unit";"Zergling";"Larva";787;1
"Unit";"Zergling";"Larva";788;1
"Unit";"Zergling";"Larva";789;1
"Unit";"Zergling";"Larva";790;1
"Unit";"Zergling";"Larva";791;1
"Unit";"Zergling";"Larva";792;1
"Unit";"Zergling";"Larva";793;1
"Unit";"Zergling";"Larva";794;1
"Unit";"Hydralisk";"Larva";795;2
"Unit";"Hydralisk";"Larva";797;2
"Building";"CreepTumor";NA;799;0
"Unit";"Baneling";"Zergling";799;0
"Unit";"Baneling";"Zergling";799;0
"Unit";"Baneling";"Zergling";799;0
"Unit";"Baneling";"Zergling";799;0
"Unit";"Baneling";"Zergling";799;0
"Unit";"Baneling";"Zergling";799;0
"Unit";"Baneling";"Zergling";799;0
"Unit";"Baneling";"Zergling";799;0
"Unit";"Baneling";"Zergling";799;0
"Unit";"Baneling";"Zergling";799;0
"Unit";"Baneling";"Zergling";799;0
"Unit";"Zergling";"Larva";799;1
"Unit";"Zergling";"Larva";800;1
"Unit";"Zergling";"Larva";801;1
"Unit";"Zergling";"Larva";802;1
"Unit";"Zergling";"Larva";803;1
"Unit";"Zergling";"Larva";804;1
"Unit";"Zergling";"Larva";805;1
"Unit";"Zergling";"Larva";806;1
"Building";"CreepTumorQueen";NA;809;0
"Building";"CreepTumor";NA;811;0
"Building";"CreepTumorQueen";NA;811;0
"Unit";"Hydralisk";"Larva";811;2
"Unit";"Hydralisk";"Larva";813;2
"Unit";"Zergling";"Larva";815;1
"Unit";"Zergling";"Larva";816;1
"Unit";"Zergling";"Larva";817;1
"Unit";"Zergling";"Larva";818;1
"Unit";"Zergling";"Larva";819;1
"Unit";"Zergling";"Larva";820;1
"Unit";"Zergling";"Larva";821;1
"Unit";"Zergling";"Larva";822;1
"Unit";"Zergling";"Larva";823;1
"Unit";"Zergling";"Larva";824;1
"Unit";"Zergling";"Larva";825;1
"Unit";"Zergling";"Larva";826;1
"Unit";"Zergling";"Larva";827;1
"Unit";"Zergling";"Larva";828;1
"Unit";"Zergling";"Larva";829;1
"Unit";"Zergling";"Larva";830;1
"Unit";"Viper";"Larva";831;3
"Unit";"Viper";"Larva";834;3
"Unit";"Viper";"Larva";837;3
"Unit";"Zergling";"Larva";840;1
"Unit";"Zergling";"Larva";841;1
"Unit";"Zergling";"Larva";842;1
"Unit";"Zergling";"Larva";843;1
"Unit";"Zergling";"Larva";844;1
"Unit";"Zergling";"Larva";845;1
"Unit";"Zergling";"Larva";846;1
"Unit";"Zergling";"Larva";847;1
"Unit";"Zergling";"Larva";848;1
"Unit";"Zergling";"Larva";849;1
"Unit";"Zergling";"Larva";850;1
"Unit";"Zergling";"Larva";851;1
"Unit";"Zergling";"Larva";852;1
"Unit";"Zergling";"Larva";853;1
"Unit";"Zergling";"Larva";854;1
"Unit";"Zergling";"Larva";855;1
"Unit";"Zergling";"Larva";856;1
"Unit";"Zergling";"Larva";857;1
"Unit";"Zergling";"Larva";858;1
"Unit";"Zergling";"Larva";859;1
"Building";"Hatchery";NA;860;0
"Unit";"Baneling";"Zergling";860;0
"Unit";"Baneling";"Zergling";860;0
"Unit";"Baneling";"Zergling";860;0
"Unit";"Zergling";"Larva";860;1
"Unit";"Zergling";"Larva";861;1
"Unit";"Zergling";"Larva";862;1
"Unit";"Zergling";"Larva";863;1
"Unit";"Zergling";"Larva";864;1
"Unit";"Zergling";"Larva";865;1
"Unit";"Zergling";"Larva";866;1
"Unit";"Zergling";"Larva";867;1
"Unit";"Zergling";"Larva";868;1
"Unit";"Zergling";"Larva";869;1
"Unit";"Zergling";"Larva";870;1
"Unit";"Zergling";"Larva";871;1
"Building";"CreepTumorQueen";NA;872;0
"Building";"CreepTumorQueen";NA;872;0
"Building";"CreepTumorQueen";NA;872;0
"Building";"CreepTumor";NA;872;0
"Building";"CreepTumor";NA;872;0
"Building";"CreepTumor";NA;872;0
"Building";"CreepTumor";NA;872;0
"Unit";"Baneling";"Zergling";872;0
"Unit";"Baneling";"Zergling";872;0
"Unit";"Baneling";"Zergling";872;0
"Building";"CreepTumorQueen";NA;872;0
"Unit";"Zergling";"Larva";872;1
"Unit";"Zergling";"Larva";873;1
"Unit";"Zergling";"Larva";874;1
"Unit";"Zergling";"Larva";875;1
"Unit";"Zergling";"Larva";876;1
"Unit";"Zergling";"Larva";877;1
"Unit";"Zergling";"Larva";878;1
"Unit";"Zergling";"Larva";879;1
"Unit";"Zergling";"Larva";880;1
"Unit";"Zergling";"Larva";881;1
"Unit";"Zergling";"Larva";882;1
"Unit";"Zergling";"Larva";883;1
"Unit";"Zergling";"Larva";884;1
"Unit";"Zergling";"Larva";885;1
"Unit";"Zergling";"Larva";886;1
"Unit";"Zergling";"Larva";887;1
"Building";"CreepTumorQueen";NA;888;0
"Building";"CreepTumorQueen";NA;888;0
"Building";"CreepTumorQueen";NA;888;0
"Unit";"Baneling";"Zergling";888;0
"Unit";"Baneling";"Zergling";888;0
"Unit";"Baneling";"Zergling";888;0
"Unit";"Baneling";"Zergling";888;0
"Unit";"Baneling";"Zergling";888;0
"Unit";"Baneling";"Zergling";888;0
"Unit";"Baneling";"Zergling";888;0
"Unit";"Baneling";"Zergling";888;0
"Unit";"Baneling";"Zergling";888;0
"Unit";"Baneling";"Zergling";888;0
"Unit";"Baneling";"Zergling";888;0
"Unit";"Baneling";"Zergling";888;0
"Building";"CreepTumorQueen";NA;888;0
"Unit";"Zergling";"Larva";888;1
"Unit";"Zergling";"Larva";889;1
"Unit";"Zergling";"Larva";890;1
"Unit";"Zergling";"Larva";891;1
"Unit";"Zergling";"Larva";892;1
"Unit";"Zergling";"Larva";893;1
"Unit";"Zergling";"Larva";894;1
"Unit";"Zergling";"Larva";895;1
"Unit";"Zergling";"Larva";896;1
"Unit";"Zergling";"Larva";897;1
"Unit";"Zergling";"Larva";898;1
"Unit";"Zergling";"Larva";899;1
"Unit";"Zergling";"Larva";900;1
"Unit";"Zergling";"Larva";901;1
"Unit";"Zergling";"Larva";902;1
"Unit";"Zergling";"Larva";903;1
"Building";"CreepTumor";NA;904;0
"Unit";"Baneling";"Zergling";904;0
"Unit";"Baneling";"Zergling";904;0
"Unit";"Baneling";"Zergling";904;0
"Unit";"Baneling";"Zergling";904;0
"Unit";"Baneling";"Zergling";904;0
"Unit";"Baneling";"Zergling";904;0
"Unit";"Baneling";"Zergling";904;0
"Unit";"Baneling";"Zergling";904;0
"Unit";"Baneling";"Zergling";904;0
"Unit";"Baneling";"Zergling";904;0
"Unit";"Baneling";"Zergling";904;0
"Unit";"Baneling";"Zergling";904;0
"Unit";"Baneling";"Zergling";904;0
"Unit";"Baneling";"Zergling";904;0
"Unit";"Zergling";"Larva";904;1
"Unit";"Zergling";"Larva";905;1
"Unit";"Zergling";"Larva";906;1
"Unit";"Zergling";"Larva";907;1
"Unit";"Zergling";"Larva";908;1
"Unit";"Zergling";"Larva";909;1
"Unit";"Zergling";"Larva";910;1
"Unit";"Zergling";"Larva";911;1
"Unit";"Zergling";"Larva";912;1
"Unit";"Zergling";"Larva";913;1
"Unit";"Zergling";"Larva";914;1
"Unit";"Zergling";"Larva";915;1
"Unit";"Zergling";"Larva";916;1
"Unit";"Zergling";"Larva";917;1
"Unit";"Zergling";"Larva";918;1
"Unit";"Zergling";"Larva";919;1
"Unit";"Zergling";"Larva";920;1
"Unit";"Zergling";"Larva";921;1
"Unit";"Zergling";"Larva";922;1
"Unit";"Zergling";"Larva";923;1
"Unit";"Zergling";"Larva";924;1
"Unit";"Zergling";"Larva";925;1
"Unit";"Zergling";"Larva";926;1
"Unit";"Zergling";"Larva";927;1
"Unit";"Zergling";"Larva";928;1
"Unit";"Zergling";"Larva";929;1
"Unit";"Zergling";"Larva";930;1
"Unit";"Zergling";"Larva";931;1
"Unit";"Zergling";"Larva";932;1
"Unit";"Zergling";"Larva";933;1
"Unit";"Zergling";"Larva";934;1
"Unit";"Zergling";"Larva";935;1
"Unit";"Zergling";"Larva";936;1
"Unit";"Zergling";"Larva";937;1
"Unit";"Zergling";"Larva";938;1
"Unit";"Zergling";"Larva";939;1
"Unit";"Zergling";"Larva";940;1
"Unit";"Zergling";"Larva";941;1
"Unit";"Zergling";"Larva";942;1
"Unit";"Zergling";"Larva";943;1
"Unit";"Zergling";"Larva";944;1
"Unit";"Zergling";"Larva";945;1
"Unit";"Zergling";"Larva";946;1
"Unit";"Zergling";"Larva";947;1
"Unit";"Zergling";"Larva";948;1
"Unit";"Zergling";"Larva";949;1
"Unit";"Hydralisk";"Larva";950;2
"Unit";"Hydralisk";"Larva";952;2
"Unit";"Hydralisk";"Larva";954;2
"Unit";"Zergling";"Larva";956;1
"Unit";"Zergling";"Larva";957;1
"Unit";"Zergling";"Larva";958;1
"Unit";"Zergling";"Larva";959;1
"Unit";"Zergling";"Larva";960;1
"Unit";"Zergling";"Larva";961;1
"Unit";"Zergling";"Larva";962;1
"Unit";"Zergling";"Larva";963;1
"Unit";"Baneling";"Zergling";964;0
"Unit";"Baneling";"Zergling";964;0
"Unit";"Baneling";"Zergling";964;0
"Unit";"Baneling";"Zergling";964;0
"Unit";"Baneling";"Zergling";964;0
"Unit";"Baneling";"Zergling";964;0
"Unit";"Baneling";"Zergling";964;0
"Unit";"Baneling";"Zergling";964;0
"Unit";"Baneling";"Zergling";964;0
"Unit";"Baneling";"Zergling";964;0
"Unit";"Baneling";"Zergling";964;0
"Unit";"Baneling";"Zergling";964;0
"Building";"CreepTumor";NA;964;0
"Building";"CreepTumor";NA;964;0
"Building";"CreepTumor";NA;964;0
"Building";"CreepTumor";NA;964;0
"Building";"CreepTumor";NA;964;0
"Building";"Extractor";NA;969;0
"Unit";"Zergling";"Larva";969;1
"Unit";"Zergling";"Larva";970;1
"Unit";"Zergling";"Larva";971;1
"Unit";"Zergling";"Larva";972;1
"Unit";"Zergling";"Larva";973;1
"Unit";"Zergling";"Larva";974;1
"Unit";"Baneling";"Zergling";975;0
"Unit";"Baneling";"Zergling";975;0
"Unit";"Baneling";"Zergling";975;0
"Unit";"Baneling";"Zergling";975;0
"Unit";"Baneling";"Zergling";975;0
"Unit";"Baneling";"Zergling";975;0
"Unit";"Baneling";"Zergling";975;0
"Unit";"Baneling";"Zergling";975;0
"Unit";"Baneling";"Zergling";975;0
"Unit";"Baneling";"Zergling";975;0
"Unit";"Baneling";"Zergling";975;0
"Building";"CreepTumorQueen";NA;979;0
"Building";"CreepTumorQueen";NA;979;0
"Building";"CreepTumorQueen";NA;979;0
"Building";"CreepTumorQueen";NA;980;0
"Building";"CreepTumorQueen";NA;983;0
"Building";"CreepTumorQueen";NA;983;0
"Unit";"Zergling";"Larva";983;1
"Unit";"Zergling";"Larva";984;1
"Unit";"Zergling";"Larva";985;1
"Unit";"Zergling";"Larva";986;1
"Unit";"Zergling";"Larva";987;1
"Unit";"Zergling";"Larva";988;1
"Unit";"Zergling";"Larva";989;1
"Unit";"Zergling";"Larva";990;1
"Unit";"Zergling";"Larva";991;1
"Unit";"Zergling";"Larva";992;1
"Unit";"Zergling";"Larva";993;1
"Unit";"Zergling";"Larva";994;1
"Unit";"Zergling";"Larva";995;1
"Unit";"Zergling";"Larva";996;1
"Unit";"Zergling";"Larva";999;1
"Unit";"Zergling";"Larva";1000;1
"Unit";"Zergling";"Larva";1001;1
"Unit";"Zergling";"Larva";1002;1
"Unit";"Zergling";"Larva";1003;1
"Unit";"Zergling";"Larva";1004;1
"Unit";"Zergling";"Larva";1005;1
"Unit";"Zergling";"Larva";1006;1
"Unit";"Zergling";"Larva";1007;1
"Unit";"Zergling";"Larva";1008;1
"Building";"CreepTumor";NA;1009;0
"Building";"CreepTumor";NA;1009;0
"Building";"CreepTumor";NA;1009;0
"Building";"CreepTumor";NA;1009;0
"Building";"CreepTumor";NA;1009;0
"Building";"CreepTumor";NA;1009;0
"Unit";"Baneling";"Zergling";1009;0
"Unit";"Baneling";"Zergling";1009;0
"Unit";"Baneling";"Zergling";1009;0
"Unit";"Baneling";"Zergling";1009;0
"Unit";"Baneling";"Zergling";1009;0
"Unit";"Baneling";"Zergling";1009;0
"Unit";"Baneling";"Zergling";1009;0
"Unit";"Baneling";"Zergling";1009;0
"Unit";"Baneling";"Zergling";1009;0
"Unit";"Baneling";"Zergling";1009;0
"Unit";"Zergling";"Larva";1009;1
"Unit";"Zergling";"Larva";1010;1
"Unit";"Zergling";"Larva";1011;1
"Unit";"Zergling";"Larva";1012;1
"Unit";"Zergling";"Larva";1013;1
"Unit";"Zergling";"Larva";1014;1
"Unit";"Zergling";"Larva";1015;1
"Unit";"Zergling";"Larva";1016;1
"Unit";"Zergling";"Larva";1017;1
"Unit";"Zergling";"Larva";1018;1
"Unit";"Zergling";"Larva";1019;1
"Unit";"Zergling";"Larva";1020;1
"Building";"Extractor";NA;1021;0
"Building";"Hatchery";NA;1021;0
"Unit";"Ultralisk";"Larva";1021;6
"Unit";"Zergling";"Larva";1027;1
"Unit";"Zergling";"Larva";1028;1
"Unit";"Zergling";"Larva";1029;1
"Unit";"Zergling";"Larva";1030;1
"Unit";"Zergling";"Larva";1031;1
"Unit";"Zergling";"Larva";1032;1
"Unit";"Zergling";"Larva";1033;1
"Unit";"Zergling";"Larva";1034;1
"Unit";"Zergling";"Larva";1035;1
"Unit";"Zergling";"Larva";1036;1
"Unit";"Baneling";"Zergling";1037;0
"Unit";"Baneling";"Zergling";1037;0
"Unit";"Baneling";"Zergling";1037;0
"Unit";"Baneling";"Zergling";1037;0
"Unit";"Zergling";"Larva";1037;1
"Unit";"Zergling";"Larva";1038;1
"Unit";"Zergling";"Larva";1039;1
"Unit";"Zergling";"Larva";1040;1
"Unit";"Zergling";"Larva";1041;1
"Unit";"Zergling";"Larva";1042;1
"Unit";"Zergling";"Larva";1043;1
"Unit";"Zergling";"Larva";1044;1
"Unit";"Zergling";"Larva";1045;1
"Unit";"Zergling";"Larva";1046;1
"Unit";"Zergling";"Larva";1047;1
"Unit";"Zergling";"Larva";1048;1
"Unit";"Zergling";"Larva";1049;1
"Unit";"Zergling";"Larva";1050;1
"Unit";"Zergling";"Larva";1051;1
"Unit";"Zergling";"Larva";1052;1
"Unit";"Zergling";"Larva";1053;1
"Unit";"Zergling";"Larva";1054;1
"Unit";"Baneling";"Zergling";1055;0
"Unit";"Baneling";"Zergling";1055;0
"Unit";"Baneling";"Zergling";1055;0
"Unit";"Baneling";"Zergling";1055;0
"Unit";"Baneling";"Zergling";1055;0
"Unit";"Baneling";"Zergling";1055;0
"Unit";"Zergling";"Larva";1055;1
"Unit";"Zergling";"Larva";1056;1
"Unit";"Zergling";"Larva";1057;1
"Unit";"Zergling";"Larva";1058;1
"Unit";"Zergling";"Larva";1059;1
"Unit";"Zergling";"Larva";1060;1
"Unit";"Zergling";"Larva";1061;1
"Unit";"Zergling";"Larva";1062;1
"Unit";"Zergling";"Larva";1063;1
"Unit";"Zergling";"Larva";1064;1
"Building";"CreepTumor";NA;1065;0
"Building";"CreepTumor";NA;1065;0
"Building";"CreepTumor";NA;1065;0
"Building";"CreepTumor";NA;1065;0
"Building";"CreepTumor";NA;1065;0
"Building";"CreepTumor";NA;1065;0
"Unit";"Baneling";"Zergling";1065;0
"Unit";"Baneling";"Zergling";1065;0
"Unit";"Baneling";"Zergling";1065;0
"Unit";"Zergling";"Larva";1065;1
"Unit";"Zergling";"Larva";1066;1
"Unit";"Zergling";"Larva";1067;1
"Unit";"Zergling";"Larva";1068;1
"Unit";"Zergling";"Larva";1069;1
"Unit";"Zergling";"Larva";1070;1
"Unit";"Zergling";"Larva";1071;1
"Unit";"Zergling";"Larva";1072;1
"Unit";"Zergling";"Larva";1073;1
"Unit";"Zergling";"Larva";1074;1
"Unit";"Zergling";"Larva";1075;1
"Unit";"Zergling";"Larva";1076;1
"Unit";"Zergling";"Larva";1077;1
"Unit";"Zergling";"Larva";1078;1
"Unit";"Zergling";"Larva";1079;1
"Unit";"Zergling";"Larva";1080;1
"Unit";"Zergling";"Larva";1081;1
"Unit";"Zergling";"Larva";1082;1
"Unit";"Zergling";"Larva";1083;1
"Unit";"Zergling";"Larva";1084;1
"Unit";"Zergling";"Larva";1085;1
"Unit";"Zergling";"Larva";1086;1
"Unit";"Zergling";"Larva";1087;1
"Unit";"Zergling";"Larva";1088;1
"Unit";"Zergling";"Larva";1089;1
"Unit";"Zergling";"Larva";1090;1
"Unit";"Zergling";"Larva";1091;1
"Unit";"Zergling";"Larva";1092;1
"Unit";"Zergling";"Larva";1093;1
"Unit";"Zergling";"Larva";1094;1
"Unit";"Zergling";"Larva";1095;1
"Unit";"Zergling";"Larva";1096;1
"Unit";"Zergling";"Larva";1097;1
"Unit";"Zergling";"Larva";1098;1
"Unit";"Zergling";"Larva";1099;1
"Unit";"Zergling";"Larva";1100;1
"Unit";"Zergling";"Larva";1101;1
"Unit";"Zergling";"Larva";1102;1
"Unit";"Zergling";"Larva";1103;1
"Unit";"Zergling";"Larva";1104;1
"Unit";"Zergling";"Larva";1105;1
"Unit";"Zergling";"Larva";1106;1
"Unit";"Zergling";"Larva";1107;1
"Unit";"Zergling";"Larva";1108;1
"Unit";"Zergling";"Larva";1109;1
"Unit";"Zergling";"Larva";1110;1
"Unit";"Baneling";"Zergling";1111;0
"Unit";"Baneling";"Zergling";1111;0
"Unit";"Baneling";"Zergling";1111;0
"Unit";"Baneling";"Zergling";1111;0
"Unit";"Baneling";"Zergling";1111;0
"Unit";"Zergling";"Larva";1111;1
"Unit";"Zergling";"Larva";1112;1
"Upgrade";"SprayZerg";NA;1113;0
"Upgrade";"SprayZerg";NA;1113;0
"Upgrade";"SprayZerg";NA;1113;0
"Upgrade";"zerglingmovementspeed";NA;1113;0
"Upgrade";"SprayZerg";NA;1113;0
"Upgrade";"SprayZerg";NA;1113;0
"Upgrade";"SprayZerg";NA;1113;0
"Upgrade";"SprayZerg";NA;1113;0
"Upgrade";"SprayZerg";NA;1113;0
"Upgrade";"ZergMeleeWeaponsLevel1";NA;1113;0
"Upgrade";"ZergGroundArmorsLevel1";NA;1113;0
"Upgrade";"SprayZerg";NA;1113;0
"Upgrade";"CentrificalHooks";NA;1113;0
"Upgrade";"SprayZerg";NA;1113;0
"Upgrade";"EvolveMuscularAugments";NA;1113;0
"Upgrade";"SprayZerg";NA;1113;0
"Upgrade";"SprayZerg";NA;1113;0
"Upgrade";"ZergMeleeWeaponsLevel2";NA;1113;0
"Upgrade";"ZergGroundArmorsLevel2";NA;1113;0
"Upgrade";"SprayZerg";NA;1113;0
"Upgrade";"SprayZerg";NA;1113;0
"Upgrade";"SprayZerg";NA;1113;0
"Upgrade";"zerglingattackspeed";NA;1113;0
"Upgrade";"SprayZerg";NA;1113;0
"Upgrade";"SprayZerg";NA;1113;0
"Upgrade";"ZergMissileWeaponsLevel1";NA;1113;0
"Upgrade";"SprayZerg";NA;1113;0
"Upgrade";"SprayZerg";NA;1113;0
"Upgrade";"SprayZerg";NA;1113;0
"Upgrade";"ZergGroundArmorsLevel3";NA;1113;0
"Upgrade";"SprayZerg";NA;1113;0
"Upgrade";"SprayZerg";NA;1113;0
"Upgrade";"SprayZerg";NA;1113;0
"Upgrade";"SprayZerg";NA;1113;0
"Upgrade";"overlordspeed";NA;1113;0
"Upgrade";"SprayZerg";NA;1113;0
"Upgrade";"ZergMissileWeaponsLevel2";NA;1113;0
"Upgrade";"SprayZerg";NA;1113;0
"Upgrade";"SprayZerg";NA;1113;0
