"type";"unit_name";"on_building";"total_supply";"supply"
"Unit";"Overlord";"Larva";12;0
"Building";"Extractor";NA;19;0
"Building";"Hatchery";NA;17;0
"Unit";"Overlord";"Larva";22;0
"Building";"SpawningPool";NA;20;0
"Unit";"Zergling";"Larva";23;1
"Unit";"Zergling";"Larva";23;1
"Unit";"Zergling";"Larva";23;1
"Unit";"Zergling";"Larva";23;1
"Unit";"Queen";"Hatchery";23;2
"Unit";"Queen";"Hatchery";23;2
"Unit";"Overlord";"Larva";36;0
"Building";"CreepTumorQueen";NA;38;0
"Unit";"Overlord";"Larva";38;0
"Unit";"Queen";"Hatchery";38;2
"Building";"Hatchery";NA;28;0
"Unit";"Overlord";"Larva";46;0
"Unit";"Overlord";"Larva";46;0
"Building";"CreepTumor";NA;52;0
"Unit";"Overlord";"Larva";52;0
"Building";"CreepTumorQueen";NA;52;0
"Unit";"Queen";"Hatchery";52;2
"Unit";"Queen";"Hatchery";52;2
"Building";"CreepTumor";NA;68;0
"Unit";"Zergling";"Larva";67;1
"Unit";"Zergling";"Larva";67;1
"Building";"CreepTumorQueen";NA;70;0
"Building";"CreepTumor";NA;70;0
"Building";"CreepTumorQueen";NA;70;0
"Building";"Extractor";NA;66;0
"Unit";"Zergling";"Larva";68;1
"Unit";"Zergling";"Larva";68;1
"Unit";"Zergling";"Larva";68;1
"Unit";"Zergling";"Larva";68;1
"Unit";"Zergling";"Larva";68;1
"Unit";"Zergling";"Larva";68;1
"Unit";"Zergling";"Larva";68;1
"Unit";"Zergling";"Larva";68;1
"Unit";"Zergling";"Larva";68;1
"Unit";"Zergling";"Larva";68;1
"Unit";"Overlord";"Larva";70;0
"Unit";"Overlord";"Larva";70;0
"Unit";"Overlord";"Larva";82;0
"Building";"CreepTumorQueen";NA;82;0
"Building";"CreepTumor";NA;82;0
"Unit";"Zergling";"Larva";82;1
"Unit";"Zergling";"Larva";82;1
"Building";"CreepTumor";NA;82;0
"Unit";"Zergling";"Larva";82;1
"Unit";"Zergling";"Larva";82;1
"Unit";"Zergling";"Larva";82;1
"Unit";"Zergling";"Larva";82;1
"Unit";"Zergling";"Larva";82;1
"Unit";"Zergling";"Larva";82;1
"Unit";"Zergling";"Larva";82;1
"Unit";"Zergling";"Larva";82;1
"Unit";"Zergling";"Larva";82;1
"Unit";"Zergling";"Larva";82;1
"Unit";"Zergling";"Larva";82;1
"Unit";"Zergling";"Larva";82;1
"Unit";"Overlord";"Larva";82;0
"Building";"CreepTumor";NA;82;0
"Building";"Extractor";NA;82;0
"Unit";"Queen";"Hatchery";82;2
"Building";"BanelingNest";NA;82;0
"Building";"CreepTumorQueen";NA;98;0
"Building";"EvolutionChamber";NA;108;0
"Building";"EvolutionChamber";NA;108;0
"Building";"Hatchery";NA;82;0
"Building";"Extractor";NA;108;0
"Building";"Extractor";NA;108;0
"Unit";"Baneling";"Zergling";112;0
"Unit";"Baneling";"Zergling";112;0
"Building";"CreepTumor";NA;112;0
"Unit";"Overlord";"Larva";112;0
"Building";"CreepTumor";NA;117;0
"Unit";"Zergling";"Larva";112;1
"Unit";"Zergling";"Larva";112;1
"Unit";"Zergling";"Larva";112;1
"Unit";"Zergling";"Larva";112;1
"Unit";"Zergling";"Larva";112;1
"Unit";"Zergling";"Larva";112;1
"Unit";"Zergling";"Larva";112;1
"Unit";"Zergling";"Larva";112;1
"Building";"HydraliskDen";NA;112;0
"Unit";"Zergling";"Larva";121;1
"Unit";"Zergling";"Larva";121;1
"Unit";"Zergling";"Larva";121;1
"Unit";"Zergling";"Larva";121;1
"Unit";"Zergling";"Larva";121;1
"Unit";"Zergling";"Larva";121;1
"Unit";"Zergling";"Larva";121;1
"Unit";"Zergling";"Larva";121;1
"Unit";"Zergling";"Larva";121;1
"Unit";"Zergling";"Larva";121;1
"Unit";"Zergling";"Larva";121;1
"Unit";"Zergling";"Larva";121;1
"Unit";"Zergling";"Larva";121;1
"Unit";"Zergling";"Larva";121;1
"Unit";"Zergling";"Larva";121;1
"Unit";"Zergling";"Larva";121;1
"Unit";"Zergling";"Larva";121;1
"Unit";"Zergling";"Larva";121;1
"Unit";"Zergling";"Larva";121;1
"Unit";"Zergling";"Larva";121;1
"Unit";"Zergling";"Larva";121;1
"Unit";"Zergling";"Larva";121;1
"Unit";"Zergling";"Larva";121;1
"Unit";"Zergling";"Larva";121;1
"Unit";"Zergling";"Larva";121;1
"Unit";"Zergling";"Larva";121;1
"Building";"Extractor";NA;121;0
"Unit";"Baneling";"Zergling";129;0
"Unit";"Baneling";"Zergling";129;0
"Unit";"Baneling";"Zergling";129;0
"Unit";"Zergling";"Larva";129;1
"Unit";"Zergling";"Larva";129;1
"Unit";"Zergling";"Larva";129;1
"Unit";"Zergling";"Larva";129;1
"Unit";"Zergling";"Larva";129;1
"Unit";"Zergling";"Larva";129;1
"Unit";"Zergling";"Larva";129;1
"Unit";"Zergling";"Larva";129;1
"Unit";"Queen";"Hatchery";119;2
"Unit";"Overlord";"Larva";129;0
"Unit";"Zergling";"Larva";129;1
"Unit";"Zergling";"Larva";129;1
"Unit";"Overlord";"Larva";155;0
"Unit";"Overlord";"Larva";155;0
"Building";"CreepTumor";NA;165;0
"Building";"CreepTumor";NA;165;0
"Building";"CreepTumor";NA;165;0
"Unit";"Baneling";"Zergling";165;0
"Unit";"Baneling";"Zergling";165;0
"Unit";"Hydralisk";"Larva";165;2
"Unit";"Hydralisk";"Larva";165;2
"Unit";"Hydralisk";"Larva";165;2
"Unit";"Hydralisk";"Larva";165;2
"Unit";"Queen";"Hatchery";155;2
"Building";"CreepTumorQueen";NA;167;0
"Building";"CreepTumorQueen";NA;167;0
"Building";"CreepTumorQueen";NA;177;0
"Unit";"Hydralisk";"Larva";167;2
"Unit";"Hydralisk";"Larva";167;2
"Unit";"Hydralisk";"Larva";167;2
"Unit";"Hydralisk";"Larva";167;2
"Unit";"Hydralisk";"Larva";167;2
"Building";"CreepTumor";NA;177;0
"Unit";"Overlord";"Larva";177;0
"Unit";"Hydralisk";"Larva";177;2
"Unit";"Hydralisk";"Larva";177;2
"Unit";"Zergling";"Larva";177;1
"Unit";"Zergling";"Larva";177;1
"Unit";"Zergling";"Larva";177;1
"Unit";"Zergling";"Larva";177;1
"Unit";"Zergling";"Larva";177;1
"Unit";"Zergling";"Larva";177;1
"Unit";"Overlord";"Larva";177;0
"Unit";"Overlord";"Larva";177;0
"Unit";"Hydralisk";"Larva";177;2
"Building";"CreepTumor";NA;199;0
"Building";"CreepTumor";NA;199;0
"Building";"CreepTumor";NA;199;0
"Upgrade";"ZergGroundArmorsLevel1";"EvolutionChamber";155;0
"Building";"CreepTumor";NA;209;0
"Unit";"Zergling";"Larva";211;1
"Unit";"Zergling";"Larva";211;1
"Unit";"Zergling";"Larva";211;1
"Unit";"Zergling";"Larva";211;1
"Unit";"Zergling";"Larva";211;1
"Unit";"Zergling";"Larva";211;1
"Unit";"Zergling";"Larva";211;1
"Unit";"Zergling";"Larva";211;1
"Unit";"Zergling";"Larva";211;1
"Unit";"Zergling";"Larva";211;1
"Unit";"Zergling";"Larva";211;1
"Unit";"Zergling";"Larva";211;1
"Upgrade";"ZergMeleeWeaponsLevel1";"EvolutionChamber";165;0
"Unit";"Zergling";"Larva";211;1
"Unit";"Zergling";"Larva";211;1
"Unit";"Zergling";"Larva";211;1
"Unit";"Zergling";"Larva";211;1
"Unit";"Zergling";"Larva";211;1
"Unit";"Zergling";"Larva";211;1
"Unit";"Zergling";"Larva";211;1
"Unit";"Zergling";"Larva";211;1
"Unit";"Zergling";"Larva";211;1
"Unit";"Zergling";"Larva";211;1
"Unit";"Zergling";"Larva";211;1
"Unit";"Zergling";"Larva";211;1
"Building";"InfestationPit";NA;187;0
"Building";"CreepTumorQueen";NA;211;0
"Building";"CreepTumorQueen";NA;211;0
"Building";"CreepTumorQueen";NA;211;0
"Building";"Hatchery";NA;167;0
"Unit";"Zergling";"Larva";211;1
"Unit";"Zergling";"Larva";211;1
"Unit";"Zergling";"Larva";211;1
"Unit";"Zergling";"Larva";211;1
"Unit";"Zergling";"Larva";211;1
"Unit";"Zergling";"Larva";211;1
"Unit";"Zergling";"Larva";211;1
"Unit";"Zergling";"Larva";211;1
"Upgrade";"EvolveGroovedSpines";"HydraliskDen";187;0
"Unit";"Hydralisk";"Larva";211;2
"Unit";"Hydralisk";"Larva";211;2
"Unit";"Hydralisk";"Larva";211;2
"Unit";"Hydralisk";"Larva";211;2
"Unit";"Queen";"Hatchery";211;2
"Unit";"Zergling";"Larva";235;1
"Unit";"Zergling";"Larva";235;1
"Unit";"Zergling";"Larva";235;1
"Unit";"Zergling";"Larva";235;1
"Unit";"Zergling";"Larva";235;1
"Unit";"Zergling";"Larva";235;1
"Unit";"Zergling";"Larva";235;1
"Unit";"Zergling";"Larva";235;1
"Unit";"Overlord";"Larva";235;0
"Building";"CreepTumor";NA;251;0
"Building";"CreepTumor";NA;259;0
"Building";"CreepTumor";NA;261;0
"Unit";"Baneling";"Zergling";261;0
"Unit";"Baneling";"Zergling";261;0
"Unit";"Baneling";"Zergling";261;0
"Unit";"Baneling";"Zergling";261;0
"Unit";"Baneling";"Zergling";261;0
"Unit";"Baneling";"Zergling";261;0
"Unit";"Overlord";"Larva";261;0
"Unit";"Overlord";"Larva";261;0
"Unit";"Overlord";"Larva";261;0
"Unit";"Hydralisk";"Larva";261;2
"Unit";"Hydralisk";"Larva";261;2
"Unit";"Hydralisk";"Larva";261;2
"Unit";"Zergling";"Larva";261;1
"Unit";"Zergling";"Larva";261;1
"Unit";"Zergling";"Larva";261;1
"Unit";"Zergling";"Larva";261;1
"Unit";"Zergling";"Larva";261;1
"Unit";"Zergling";"Larva";261;1
"Unit";"Zergling";"Larva";261;1
"Unit";"Zergling";"Larva";261;1
"Unit";"Zergling";"Larva";261;1
"Unit";"Zergling";"Larva";261;1
"Unit";"Zergling";"Larva";261;1
"Unit";"Zergling";"Larva";261;1
"Unit";"Zergling";"Larva";261;1
"Unit";"Zergling";"Larva";261;1
"Unit";"Zergling";"Larva";261;1
"Unit";"Zergling";"Larva";261;1
"Unit";"Zergling";"Larva";261;1
"Unit";"Zergling";"Larva";261;1
"Unit";"Zergling";"Larva";261;1
"Unit";"Zergling";"Larva";261;1
"Unit";"Zergling";"Larva";261;1
"Unit";"Zergling";"Larva";261;1
"Unit";"Zergling";"Larva";261;1
"Unit";"Zergling";"Larva";261;1
"Unit";"Zergling";"Larva";261;1
"Unit";"Zergling";"Larva";261;1
"Unit";"Zergling";"Larva";261;1
"Unit";"Zergling";"Larva";261;1
"Unit";"Zergling";"Larva";261;1
"Unit";"Zergling";"Larva";261;1
"Building";"Extractor";NA;261;0
"Building";"Extractor";NA;261;0
"Building";"CreepTumorQueen";NA;267;0
"Building";"CreepTumorQueen";NA;269;0
"Building";"CreepTumor";NA;267;0
"Unit";"Baneling";"Zergling";297;0
"Unit";"Baneling";"Zergling";297;0
"Unit";"Baneling";"Zergling";297;0
"Unit";"Baneling";"Zergling";297;0
"Unit";"Baneling";"Zergling";297;0
"Unit";"Baneling";"Zergling";297;0
"Unit";"Baneling";"Zergling";297;0
"Unit";"Overlord";"Larva";297;0
"Unit";"Queen";"Hatchery";267;2
"Unit";"Hydralisk";"Larva";297;2
"Unit";"Hydralisk";"Larva";297;2
"Unit";"Hydralisk";"Larva";297;2
"Unit";"Hydralisk";"Larva";297;2
"Unit";"Hydralisk";"Larva";297;2
"Building";"CreepTumor";NA;297;0
"Building";"CreepTumor";NA;297;0
"Building";"CreepTumor";NA;297;0
"Building";"CreepTumor";NA;297;0
"Unit";"Zergling";"Larva";309;1
"Unit";"Zergling";"Larva";309;1
"Unit";"Overlord";"Larva";309;0
"Unit";"Overlord";"Larva";309;0
"Unit";"Zergling";"Larva";309;1
"Unit";"Zergling";"Larva";309;1
"Unit";"Zergling";"Larva";309;1
"Unit";"Zergling";"Larva";309;1
"Unit";"Zergling";"Larva";309;1
"Unit";"Zergling";"Larva";309;1
"Unit";"Zergling";"Larva";309;1
"Unit";"Zergling";"Larva";309;1
"Unit";"Zergling";"Larva";309;1
"Unit";"Zergling";"Larva";309;1
"Unit";"Zergling";"Larva";309;1
"Unit";"Zergling";"Larva";309;1
"Unit";"Zergling";"Larva";309;1
"Unit";"Zergling";"Larva";309;1
"Unit";"Zergling";"Larva";309;1
"Unit";"Zergling";"Larva";309;1
"Unit";"Zergling";"Larva";309;1
"Unit";"Zergling";"Larva";309;1
"Unit";"Zergling";"Larva";309;1
"Unit";"Zergling";"Larva";309;1
"Unit";"Zergling";"Larva";309;1
"Unit";"Zergling";"Larva";309;1
"Upgrade";"EvolveMuscularAugments";"HydraliskDen";297;0
"Upgrade";"ZergMeleeWeaponsLevel2";"EvolutionChamber";261;0
"Upgrade";"ZergGroundArmorsLevel2";"EvolutionChamber";261;0
"Building";"UltraliskCavern";NA;309;0
"Unit";"Overlord";"Larva";333;0
"Unit";"Overlord";"Larva";333;0
"Unit";"Zergling";"Larva";339;1
"Unit";"Zergling";"Larva";339;1
"Unit";"Zergling";"Larva";339;1
"Unit";"Zergling";"Larva";339;1
"Building";"CreepTumor";NA;339;0
"Building";"CreepTumor";NA;339;0
"Unit";"Ultralisk";"Larva";333;6
"Building";"CreepTumorQueen";NA;349;0
"Building";"CreepTumorQueen";NA;349;0
"Upgrade";"ChitinousPlating";"UltraliskCavern";339;0
"Building";"Hatchery";NA;343;0
"Building";"Hatchery";NA;343;0
"Building";"CreepTumorQueen";NA;349;0
"Building";"CreepTumor";NA;349;0
"Unit";"Zergling";"Larva";349;1
"Unit";"Zergling";"Larva";349;1
"Unit";"Zergling";"Larva";349;1
"Unit";"Zergling";"Larva";349;1
"Unit";"Zergling";"Larva";349;1
"Unit";"Zergling";"Larva";349;1
"Unit";"Zergling";"Larva";349;1
"Unit";"Zergling";"Larva";349;1
"Unit";"Zergling";"Larva";349;1
"Unit";"Zergling";"Larva";349;1
"Unit";"Zergling";"Larva";349;1
"Unit";"Zergling";"Larva";349;1
"Unit";"Zergling";"Larva";349;1
"Unit";"Zergling";"Larva";349;1
"Unit";"Zergling";"Larva";349;1
"Unit";"Zergling";"Larva";349;1
"Building";"CreepTumor";NA;349;0
"Building";"CreepTumorQueen";NA;349;0
"Building";"CreepTumor";NA;349;0
"Unit";"Ultralisk";"Larva";349;6
"Unit";"Ultralisk";"Larva";349;6
"Unit";"Ultralisk";"Larva";349;6
"Unit";"Hydralisk";"Larva";349;2
"Unit";"Hydralisk";"Larva";349;2
"Unit";"Hydralisk";"Larva";349;2
"Building";"CreepTumorQueen";NA;349;0
"Building";"CreepTumor";NA;349;0
"Building";"CreepTumorQueen";NA;349;0
"Building";"CreepTumorQueen";NA;349;0
"Building";"CreepTumor";NA;349;0
"Building";"CreepTumor";NA;349;0
"Building";"CreepTumorQueen";NA;351;0
"Building";"CreepTumor";NA;349;0
"Building";"CreepTumorQueen";NA;365;0
"Building";"CreepTumorQueen";NA;389;0
"Building";"CreepTumorQueen";NA;389;0
"Unit";"Ultralisk";"Larva";349;6
"Unit";"Ultralisk";"Larva";349;6
"Building";"Spire";NA;349;0
"Building";"Extractor";NA;389;0
"Building";"Extractor";NA;389;0
"Unit";"Queen";"Hatchery";389;2
"Building";"SpineCrawler";NA;389;0
"Building";"SpineCrawler";NA;389;0
"Upgrade";"ZergMeleeWeaponsLevel3";"EvolutionChamber";349;0
"Upgrade";"ZergGroundArmorsLevel3";"EvolutionChamber";349;0
"Unit";"Zergling";"Larva";403;1
"Unit";"Zergling";"Larva";403;1
"Unit";"Zergling";"Larva";403;1
"Unit";"Zergling";"Larva";403;1
"Unit";"Zergling";"Larva";403;1
"Unit";"Zergling";"Larva";403;1
"Unit";"Zergling";"Larva";403;1
"Unit";"Zergling";"Larva";403;1
"Unit";"Zergling";"Larva";403;1
"Unit";"Zergling";"Larva";403;1
"Unit";"Zergling";"Larva";403;1
"Unit";"Zergling";"Larva";403;1
"Unit";"Zergling";"Larva";403;1
"Unit";"Zergling";"Larva";403;1
"Unit";"Zergling";"Larva";403;1
"Unit";"Zergling";"Larva";403;1
"Unit";"Zergling";"Larva";403;1
"Unit";"Zergling";"Larva";403;1
"Unit";"Zergling";"Larva";403;1
"Unit";"Zergling";"Larva";403;1
"Unit";"Zergling";"Larva";403;1
"Unit";"Zergling";"Larva";403;1
"Unit";"Zergling";"Larva";403;1
"Unit";"Zergling";"Larva";403;1
"Unit";"Zergling";"Larva";403;1
"Unit";"Zergling";"Larva";403;1
"Unit";"Zergling";"Larva";403;1
"Unit";"Zergling";"Larva";403;1
"Unit";"Zergling";"Larva";403;1
"Unit";"Zergling";"Larva";403;1
"Unit";"Zergling";"Larva";403;1
"Unit";"Zergling";"Larva";403;1
"Unit";"Zergling";"Larva";403;1
"Unit";"Zergling";"Larva";403;1
"Unit";"Zergling";"Larva";403;1
"Unit";"Zergling";"Larva";403;1
"Unit";"Zergling";"Larva";403;1
"Unit";"Zergling";"Larva";403;1
"Unit";"Zergling";"Larva";403;1
"Unit";"Zergling";"Larva";403;1
"Unit";"Zergling";"Larva";403;1
"Unit";"Zergling";"Larva";403;1
"Unit";"Zergling";"Larva";403;1
"Unit";"Zergling";"Larva";403;1
"Unit";"Zergling";"Larva";403;1
"Unit";"Zergling";"Larva";403;1
"Unit";"Zergling";"Larva";403;1
"Unit";"Zergling";"Larva";403;1
"Unit";"Zergling";"Larva";403;1
"Unit";"Zergling";"Larva";403;1
"Unit";"Zergling";"Larva";403;1
"Unit";"Zergling";"Larva";403;1
"Unit";"Zergling";"Larva";403;1
"Unit";"Zergling";"Larva";403;1
"Unit";"Zergling";"Larva";403;1
"Unit";"Zergling";"Larva";403;1
"Unit";"Zergling";"Larva";403;1
"Unit";"Zergling";"Larva";403;1
"Unit";"Zergling";"Larva";403;1
"Unit";"Zergling";"Larva";403;1
"Unit";"Zergling";"Larva";403;1
"Unit";"Zergling";"Larva";403;1
"Unit";"Zergling";"Larva";403;1
"Unit";"Zergling";"Larva";403;1
"Unit";"Zergling";"Larva";403;1
"Unit";"Zergling";"Larva";403;1
"Unit";"Zergling";"Larva";403;1
"Unit";"Zergling";"Larva";403;1
"Unit";"Zergling";"Larva";403;1
"Unit";"Zergling";"Larva";403;1
"Unit";"Corruptor";"Larva";401;2
"Unit";"Corruptor";"Larva";401;2
"Unit";"Corruptor";"Larva";401;2
"Unit";"Corruptor";"Larva";401;2
"Unit";"Corruptor";"Larva";401;2
"Unit";"Corruptor";"Larva";401;2
"Unit";"Corruptor";"Larva";401;2
"Unit";"Corruptor";"Larva";401;2
"Unit";"Corruptor";"Larva";401;2
"Unit";"Baneling";"Zergling";403;0
"Unit";"Baneling";"Zergling";403;0
"Unit";"Baneling";"Zergling";403;0
"Unit";"Baneling";"Zergling";403;0
"Unit";"Zergling";"Larva";403;1
"Unit";"Zergling";"Larva";403;1
"Unit";"Zergling";"Larva";403;1
"Unit";"Zergling";"Larva";403;1
"Unit";"Zergling";"Larva";403;1
"Unit";"Zergling";"Larva";403;1
"Unit";"Zergling";"Larva";403;1
"Unit";"Zergling";"Larva";403;1
"Unit";"Corruptor";"Larva";491;2
"Unit";"Corruptor";"Larva";491;2
"Unit";"Corruptor";"Larva";491;2
"Unit";"Zergling";"Larva";499;1
"Unit";"Zergling";"Larva";499;1
"Unit";"Zergling";"Larva";499;1
"Unit";"Zergling";"Larva";499;1
"Unit";"Zergling";"Larva";499;1
"Unit";"Zergling";"Larva";499;1
"Unit";"Zergling";"Larva";499;1
"Unit";"Zergling";"Larva";499;1
"Unit";"Zergling";"Larva";499;1
"Unit";"Zergling";"Larva";499;1
"Unit";"Baneling";"Zergling";499;0
"Unit";"Ultralisk";"Larva";499;6
"Unit";"Ultralisk";"Larva";499;6
"Unit";"Ultralisk";"Larva";499;6
"Unit";"Zergling";"Larva";536;1
"Unit";"Zergling";"Larva";536;1
"Unit";"Zergling";"Larva";536;1
"Unit";"Zergling";"Larva";536;1
"Unit";"Zergling";"Larva";536;1
"Unit";"Zergling";"Larva";536;1
"Unit";"Zergling";"Larva";536;1
"Unit";"Zergling";"Larva";536;1
"Unit";"Zergling";"Larva";536;1
"Unit";"Zergling";"Larva";536;1
"Unit";"Zergling";"Larva";536;1
"Unit";"Zergling";"Larva";536;1
"Unit";"Zergling";"Larva";536;1
"Unit";"Zergling";"Larva";536;1
"Unit";"Zergling";"Larva";536;1
"Unit";"Zergling";"Larva";536;1
"Unit";"Zergling";"Larva";536;1
"Unit";"Zergling";"Larva";536;1
"Unit";"Zergling";"Larva";536;1
"Unit";"Zergling";"Larva";536;1
"Unit";"Zergling";"Larva";536;1
"Unit";"Zergling";"Larva";536;1
"Unit";"Zergling";"Larva";536;1
"Unit";"Zergling";"Larva";536;1
"Unit";"Zergling";"Larva";536;1
"Unit";"Zergling";"Larva";536;1
"Unit";"Viper";"Larva";518;3
"Unit";"Viper";"Larva";518;3
"Unit";"Viper";"Larva";518;3
"Unit";"Baneling";"Zergling";579;0
"Unit";"Baneling";"Zergling";579;0
"Unit";"Baneling";"Zergling";579;0
"Unit";"Baneling";"Zergling";579;0
"Unit";"Baneling";"Zergling";579;0
"Unit";"Baneling";"Zergling";579;0
"Unit";"Baneling";"Zergling";579;0
"Unit";"Baneling";"Zergling";579;0
"Building";"Extractor";NA;579;0
"Unit";"Baneling";"Zergling";579;0
"Building";"Extractor";NA;579;0
"Building";"CreepTumor";NA;579;0
"Building";"CreepTumor";NA;579;0
"Building";"CreepTumor";NA;579;0
"Building";"CreepTumor";NA;579;0
"Building";"CreepTumor";NA;579;0
"Building";"CreepTumor";NA;579;0
"Building";"CreepTumor";NA;585;0
"Building";"CreepTumor";NA;585;0
"Building";"CreepTumor";NA;585;0
"Building";"CreepTumor";NA;585;0
"Building";"CreepTumor";NA;585;0
"Unit";"Infestor";"Larva";585;2
"Unit";"Infestor";"Larva";585;2
"Unit";"Infestor";"Larva";585;2
"Unit";"Infestor";"Larva";585;2
"Unit";"Infestor";"Larva";585;2
"Unit";"Infestor";"Larva";585;2
"Unit";"Infestor";"Larva";585;2
"Unit";"Zergling";"Larva";585;1
"Unit";"Zergling";"Larva";585;1
"Unit";"Zergling";"Larva";585;1
"Unit";"Zergling";"Larva";585;1
"Unit";"Zergling";"Larva";585;1
"Unit";"Zergling";"Larva";585;1
"Unit";"Zergling";"Larva";585;1
"Unit";"Zergling";"Larva";585;1
"Unit";"Zergling";"Larva";585;1
"Unit";"Zergling";"Larva";585;1
"Unit";"Zergling";"Larva";585;1
"Unit";"Zergling";"Larva";585;1
"Unit";"Zergling";"Larva";585;1
"Unit";"Zergling";"Larva";585;1
"Building";"Hatchery";NA;579;0
"Building";"Hatchery";NA;579;0
"Building";"CreepTumor";NA;585;0
"Unit";"Corruptor";"Larva";585;2
"Unit";"Queen";"Hatchery";585;2
"Building";"CreepTumorQueen";NA;613;0
"Building";"CreepTumorQueen";NA;617;0
"Building";"Extractor";NA;613;0
"Building";"Extractor";NA;619;0
"Unit";"Zergling";"Larva";623;1
"Unit";"Zergling";"Larva";623;1
"Unit";"Zergling";"Larva";623;1
"Unit";"Zergling";"Larva";623;1
"Unit";"Zergling";"Larva";623;1
"Unit";"Zergling";"Larva";623;1
"Unit";"Zergling";"Larva";623;1
"Unit";"Zergling";"Larva";623;1
"Unit";"Zergling";"Larva";623;1
"Unit";"Zergling";"Larva";623;1
"Unit";"Zergling";"Larva";623;1
"Unit";"Zergling";"Larva";623;1
"Unit";"Zergling";"Larva";623;1
"Unit";"Zergling";"Larva";623;1
"Unit";"Zergling";"Larva";623;1
"Unit";"Zergling";"Larva";623;1
"Unit";"Zergling";"Larva";623;1
"Unit";"Zergling";"Larva";623;1
"Unit";"Zergling";"Larva";623;1
"Unit";"Zergling";"Larva";623;1
"Unit";"Zergling";"Larva";623;1
"Unit";"Zergling";"Larva";623;1
"Unit";"Zergling";"Larva";623;1
"Unit";"Zergling";"Larva";623;1
"Unit";"Zergling";"Larva";623;1
"Unit";"Zergling";"Larva";623;1
"Unit";"Baneling";"Zergling";649;0
"Unit";"Baneling";"Zergling";649;0
"Unit";"Baneling";"Zergling";649;0
"Unit";"Baneling";"Zergling";649;0
"Unit";"Infestor";"Larva";629;2
"Unit";"Infestor";"Larva";631;2
"Unit";"Infestor";"Larva";631;2
"Unit";"Infestor";"Larva";631;2
"Unit";"Corruptor";"Larva";649;2
"Unit";"Corruptor";"Larva";649;2
"Unit";"Corruptor";"Larva";649;2
"Unit";"Corruptor";"Larva";657;2
"Unit";"Corruptor";"Larva";657;2
"Unit";"Zergling";"Larva";663;1
"Unit";"Zergling";"Larva";663;1
"Unit";"Zergling";"Larva";663;1
"Unit";"Zergling";"Larva";663;1
"Unit";"Zergling";"Larva";663;1
"Unit";"Zergling";"Larva";663;1
"Unit";"Zergling";"Larva";663;1
"Unit";"Zergling";"Larva";663;1
"Unit";"Zergling";"Larva";663;1
"Unit";"Zergling";"Larva";663;1
"Unit";"Corruptor";"Larva";661;2
"Unit";"Corruptor";"Larva";661;2
"Unit";"Corruptor";"Larva";663;2
"Unit";"Corruptor";"Larva";663;2
"Unit";"Zergling";"Larva";681;1
"Unit";"Zergling";"Larva";681;1
"Unit";"Zergling";"Larva";681;1
"Unit";"Zergling";"Larva";681;1
"Unit";"Zergling";"Larva";681;1
"Unit";"Zergling";"Larva";681;1
"Unit";"Zergling";"Larva";681;1
"Unit";"Zergling";"Larva";681;1
"Unit";"Zergling";"Larva";681;1
"Unit";"Zergling";"Larva";681;1
"Unit";"Zergling";"Larva";681;1
"Unit";"Zergling";"Larva";681;1
"Unit";"Zergling";"Larva";681;1
"Unit";"Zergling";"Larva";681;1
"Unit";"Zergling";"Larva";681;1
"Unit";"Zergling";"Larva";681;1
"Unit";"Zergling";"Larva";681;1
"Unit";"Zergling";"Larva";681;1
"Unit";"Corruptor";"Larva";681;2
"Unit";"Corruptor";"Larva";681;2
"Building";"Hatchery";NA;657;0
"Unit";"Zergling";"Larva";685;1
"Unit";"Zergling";"Larva";685;1
"Unit";"Zergling";"Larva";709;1
"Unit";"Zergling";"Larva";709;1
"Unit";"Zergling";"Larva";709;1
"Unit";"Zergling";"Larva";709;1
"Unit";"Zergling";"Larva";709;1
"Unit";"Zergling";"Larva";709;1
"Unit";"Zergling";"Larva";709;1
"Unit";"Zergling";"Larva";709;1
"Unit";"Zergling";"Larva";709;1
"Unit";"Zergling";"Larva";709;1
"Unit";"Zergling";"Larva";709;1
"Unit";"Zergling";"Larva";709;1
"Upgrade";"Burrow";"Hatchery";681;0
"Unit";"Hydralisk";"Larva";709;2
"Unit";"Hydralisk";"Larva";709;2
"Unit";"Hydralisk";"Larva";709;2
"Unit";"Hydralisk";"Larva";709;2
"Unit";"Hydralisk";"Larva";709;2
"Unit";"Hydralisk";"Larva";709;2
"Unit";"Hydralisk";"Larva";709;2
"Unit";"Hydralisk";"Larva";709;2
"Unit";"Hydralisk";"Larva";709;2
"Unit";"Hydralisk";"Larva";709;2
"Unit";"Zergling";"Larva";709;1
"Unit";"Zergling";"Larva";709;1
"Unit";"Zergling";"Larva";709;1
"Unit";"Zergling";"Larva";709;1
"Unit";"Zergling";"Larva";709;1
"Unit";"Zergling";"Larva";709;1
"Unit";"Zergling";"Larva";709;1
"Unit";"Zergling";"Larva";709;1
"Unit";"Zergling";"Larva";709;1
"Unit";"Zergling";"Larva";709;1
"Unit";"Zergling";"Larva";709;1
"Unit";"Zergling";"Larva";709;1
"Unit";"Zergling";"Larva";709;1
"Unit";"Zergling";"Larva";709;1
"Unit";"Zergling";"Larva";709;1
"Unit";"Zergling";"Larva";709;1
"Unit";"Baneling";"Zergling";757;0
"Unit";"Baneling";"Zergling";757;0
"Unit";"Baneling";"Zergling";757;0
"Unit";"Baneling";"Zergling";757;0
"Unit";"Baneling";"Zergling";757;0
"Unit";"Baneling";"Zergling";757;0
"Unit";"Baneling";"Zergling";757;0
"Building";"Extractor";NA;757;0
"Unit";"Zergling";"Larva";757;1
"Unit";"Zergling";"Larva";757;1
"Unit";"Zergling";"Larva";757;1
"Unit";"Zergling";"Larva";757;1
"Unit";"Zergling";"Larva";757;1
"Unit";"Zergling";"Larva";757;1
"Unit";"Zergling";"Larva";757;1
"Unit";"Zergling";"Larva";757;1
"Unit";"Zergling";"Larva";757;1
"Unit";"Zergling";"Larva";757;1
"Unit";"Zergling";"Larva";757;1
"Unit";"Zergling";"Larva";757;1
"Unit";"Zergling";"Larva";757;1
"Unit";"Zergling";"Larva";757;1
"Unit";"Zergling";"Larva";757;1
"Unit";"Zergling";"Larva";757;1
"Unit";"Zergling";"Larva";757;1
"Unit";"Zergling";"Larva";757;1
"Unit";"Zergling";"Larva";757;1
"Unit";"Zergling";"Larva";757;1
"Unit";"Zergling";"Larva";757;1
"Unit";"Zergling";"Larva";757;1
"Unit";"Zergling";"Larva";757;1
"Unit";"Zergling";"Larva";757;1
"Unit";"Zergling";"Larva";757;1
"Unit";"Zergling";"Larva";757;1
"Unit";"Zergling";"Larva";757;1
"Unit";"Zergling";"Larva";757;1
"Unit";"Zergling";"Larva";757;1
"Unit";"Zergling";"Larva";757;1
"Unit";"Zergling";"Larva";757;1
"Unit";"Zergling";"Larva";757;1
"Unit";"Ultralisk";"Larva";757;6
"Unit";"Baneling";"Zergling";757;0
"Unit";"Baneling";"Zergling";757;0
"Unit";"Baneling";"Zergling";757;0
"Unit";"Baneling";"Zergling";757;0
"Unit";"Baneling";"Zergling";757;0
"Unit";"Baneling";"Zergling";757;0
"Unit";"Queen";"Hatchery";757;2
"Unit";"Queen";"Hatchery";757;2
"Unit";"Zergling";"Larva";797;1
"Unit";"Zergling";"Larva";797;1
"Unit";"Zergling";"Larva";797;1
"Unit";"Zergling";"Larva";797;1
"Unit";"Zergling";"Larva";797;1
"Unit";"Zergling";"Larva";797;1
"Unit";"Zergling";"Larva";797;1
"Unit";"Zergling";"Larva";797;1
"Unit";"Zergling";"Larva";797;1
"Unit";"Zergling";"Larva";797;1
"Unit";"Zergling";"Larva";797;1
"Unit";"Zergling";"Larva";797;1
"Unit";"Queen";"Hatchery";795;2
"Unit";"Ultralisk";"Larva";795;6
"Building";"SpineCrawler";NA;797;0
"Building";"SpineCrawler";NA;797;0
"Unit";"Baneling";"Zergling";799;0
"Unit";"Baneling";"Zergling";799;0
"Unit";"Baneling";"Zergling";799;0
"Unit";"Zergling";"Larva";799;1
"Unit";"Zergling";"Larva";799;1
"Unit";"Zergling";"Larva";799;1
"Unit";"Zergling";"Larva";799;1
"Unit";"Zergling";"Larva";799;1
"Unit";"Zergling";"Larva";799;1
"Unit";"Zergling";"Larva";799;1
"Unit";"Zergling";"Larva";799;1
"Unit";"Zergling";"Larva";799;1
"Unit";"Zergling";"Larva";799;1
"Building";"Hatchery";NA;757;0
"Unit";"Ultralisk";"Larva";797;6
"Unit";"Zergling";"Larva";844;1
"Unit";"Zergling";"Larva";844;1
"Unit";"Zergling";"Larva";844;1
"Unit";"Zergling";"Larva";844;1
"Unit";"Zergling";"Larva";844;1
"Unit";"Zergling";"Larva";844;1
"Unit";"Zergling";"Larva";844;1
"Unit";"Zergling";"Larva";844;1
"Unit";"Zergling";"Larva";844;1
"Unit";"Zergling";"Larva";844;1
"Unit";"Zergling";"Larva";844;1
"Unit";"Zergling";"Larva";844;1
"Unit";"Zergling";"Larva";844;1
"Unit";"Zergling";"Larva";844;1
"Unit";"Zergling";"Larva";844;1
"Unit";"Zergling";"Larva";844;1
"Unit";"Zergling";"Larva";844;1
"Unit";"Zergling";"Larva";844;1
"Unit";"Zergling";"Larva";844;1
"Unit";"Zergling";"Larva";844;1
"Unit";"Zergling";"Larva";844;1
"Unit";"Zergling";"Larva";844;1
"Unit";"Zergling";"Larva";844;1
"Unit";"Zergling";"Larva";844;1
"Unit";"Zergling";"Larva";844;1
"Unit";"Zergling";"Larva";844;1
"Unit";"Zergling";"Larva";844;1
"Unit";"Zergling";"Larva";844;1
"Unit";"Zergling";"Larva";844;1
"Unit";"Zergling";"Larva";844;1
"Unit";"Zergling";"Larva";844;1
"Unit";"Zergling";"Larva";844;1
"Unit";"Zergling";"Larva";844;1
"Unit";"Zergling";"Larva";844;1
"Unit";"Zergling";"Larva";844;1
"Unit";"Zergling";"Larva";844;1
"Unit";"Zergling";"Larva";844;1
"Unit";"Zergling";"Larva";844;1
"Unit";"Zergling";"Larva";844;1
"Unit";"Zergling";"Larva";844;1
"Unit";"Zergling";"Larva";844;1
"Unit";"Zergling";"Larva";844;1
"Unit";"Zergling";"Larva";844;1
"Unit";"Zergling";"Larva";844;1
"Unit";"Zergling";"Larva";844;1
"Unit";"Zergling";"Larva";844;1
"Unit";"Zergling";"Larva";890;1
"Unit";"Zergling";"Larva";890;1
"Unit";"Zergling";"Larva";890;1
"Unit";"Zergling";"Larva";890;1
"Unit";"Zergling";"Larva";890;1
"Unit";"Zergling";"Larva";890;1
"Unit";"Zergling";"Larva";890;1
"Unit";"Zergling";"Larva";890;1
"Unit";"Zergling";"Larva";890;1
"Unit";"Zergling";"Larva";890;1
"Unit";"Zergling";"Larva";890;1
"Unit";"Zergling";"Larva";890;1
"Unit";"Zergling";"Larva";890;1
"Unit";"Zergling";"Larva";890;1
"Unit";"Zergling";"Larva";890;1
"Unit";"Zergling";"Larva";890;1
"Unit";"Zergling";"Larva";890;1
"Unit";"Zergling";"Larva";890;1
"Unit";"Zergling";"Larva";890;1
"Unit";"Zergling";"Larva";890;1
"Unit";"Zergling";"Larva";890;1
"Unit";"Zergling";"Larva";890;1
"Unit";"Zergling";"Larva";890;1
"Unit";"Zergling";"Larva";890;1
"Unit";"Zergling";"Larva";890;1
"Unit";"Zergling";"Larva";890;1
"Unit";"Baneling";"Zergling";914;0
"Unit";"Baneling";"Zergling";914;0
"Unit";"Baneling";"Zergling";914;0
"Unit";"Baneling";"Zergling";914;0
"Unit";"Baneling";"Zergling";914;0
"Unit";"Baneling";"Zergling";914;0
"Unit";"Baneling";"Zergling";914;0
"Unit";"Baneling";"Zergling";914;0
"Unit";"Baneling";"Zergling";914;0
"Building";"Extractor";NA;914;0
"Unit";"Zergling";"Larva";916;1
"Unit";"Zergling";"Larva";916;1
"Unit";"Zergling";"Larva";916;1
"Unit";"Zergling";"Larva";916;1
"Unit";"Zergling";"Larva";916;1
"Unit";"Zergling";"Larva";916;1
"Unit";"Zergling";"Larva";916;1
"Unit";"Zergling";"Larva";916;1
"Unit";"Zergling";"Larva";916;1
"Unit";"Zergling";"Larva";916;1
"Unit";"Zergling";"Larva";916;1
"Unit";"Zergling";"Larva";916;1
"Unit";"Zergling";"Larva";916;1
"Unit";"Zergling";"Larva";916;1
"Unit";"Ultralisk";"Larva";890;6
"Unit";"Ultralisk";"Larva";890;6
"Unit";"Ultralisk";"Larva";890;6
"Unit";"Ultralisk";"Larva";890;6
"Unit";"Ultralisk";"Larva";890;6
"Unit";"Baneling";"Zergling";916;0
"Unit";"Baneling";"Zergling";916;0
"Unit";"Baneling";"Zergling";916;0
"Unit";"Queen";"Hatchery";916;2
"Unit";"Zergling";"Larva";960;1
"Unit";"Zergling";"Larva";960;1
"Unit";"Zergling";"Larva";960;1
"Unit";"Zergling";"Larva";960;1
"Unit";"Zergling";"Larva";960;1
"Unit";"Zergling";"Larva";960;1
"Unit";"Zergling";"Larva";960;1
"Unit";"Zergling";"Larva";960;1
"Unit";"Zergling";"Larva";960;1
"Unit";"Zergling";"Larva";960;1
"Unit";"Zergling";"Larva";960;1
"Unit";"Zergling";"Larva";960;1
"Unit";"Zergling";"Larva";960;1
"Unit";"Zergling";"Larva";960;1
"Unit";"Zergling";"Larva";960;1
"Unit";"Zergling";"Larva";960;1
"Unit";"Zergling";"Larva";960;1
"Unit";"Zergling";"Larva";960;1
"Unit";"Zergling";"Larva";960;1
"Unit";"Zergling";"Larva";960;1
"Unit";"Zergling";"Larva";960;1
"Unit";"Zergling";"Larva";960;1
"Unit";"Zergling";"Larva";960;1
"Unit";"Zergling";"Larva";960;1
"Unit";"Zergling";"Larva";960;1
"Unit";"Zergling";"Larva";960;1
"Unit";"Zergling";"Larva";960;1
"Unit";"Zergling";"Larva";960;1
"Unit";"Ultralisk";"Larva";960;6
"Unit";"Ultralisk";"Larva";960;6
"Unit";"Zergling";"Larva";990;1
"Unit";"Zergling";"Larva";990;1
"Unit";"Zergling";"Larva";990;1
"Unit";"Zergling";"Larva";990;1
"Unit";"Zergling";"Larva";990;1
"Unit";"Zergling";"Larva";990;1
"Unit";"Zergling";"Larva";990;1
"Unit";"Zergling";"Larva";990;1
"Unit";"Zergling";"Larva";990;1
"Unit";"Zergling";"Larva";990;1
"Unit";"Zergling";"Larva";990;1
"Unit";"Zergling";"Larva";990;1
"Unit";"Zergling";"Larva";990;1
"Unit";"Zergling";"Larva";990;1
"Building";"Hatchery";NA;916;0
"Unit";"Ultralisk";"Larva";990;6
"Unit";"Ultralisk";"Larva";990;6
"Unit";"Baneling";"Zergling";1016;0
"Unit";"Baneling";"Zergling";1016;0
"Unit";"Baneling";"Zergling";1016;0
"Unit";"Baneling";"Zergling";1016;0
"Unit";"Baneling";"Zergling";1016;0
"Unit";"Baneling";"Zergling";1016;0
"Unit";"Baneling";"Zergling";1016;0
"Unit";"Baneling";"Zergling";1016;0
"Unit";"Baneling";"Zergling";1016;0
"Unit";"Baneling";"Zergling";1016;0
"Unit";"Baneling";"Zergling";1016;0
"Unit";"Baneling";"Zergling";1016;0
"Unit";"Baneling";"Zergling";1016;0
"Unit";"Baneling";"Zergling";1016;0
"Unit";"Baneling";"Zergling";1016;0
"Unit";"Baneling";"Zergling";1016;0
"Unit";"Baneling";"Zergling";1016;0
"Unit";"Baneling";"Zergling";1016;0
"Unit";"Baneling";"Zergling";1016;0
"Unit";"Baneling";"Zergling";1016;0
"Unit";"Baneling";"Zergling";1016;0
"Unit";"Baneling";"Zergling";1016;0
"Unit";"Baneling";"Zergling";1016;0
"Unit";"Baneling";"Zergling";1016;0
"Unit";"Baneling";"Zergling";1016;0
"Unit";"Baneling";"Zergling";1016;0
"Unit";"Baneling";"Zergling";1016;0
"Unit";"Baneling";"Zergling";1016;0
"Unit";"Baneling";"Zergling";1016;0
"Unit";"Zergling";"Larva";1016;1
"Unit";"Zergling";"Larva";1016;1
"Unit";"Zergling";"Larva";1016;1
"Unit";"Zergling";"Larva";1016;1
"Unit";"Zergling";"Larva";1016;1
"Unit";"Zergling";"Larva";1016;1
"Unit";"Zergling";"Larva";1016;1
"Unit";"Zergling";"Larva";1016;1
"Unit";"Zergling";"Larva";1016;1
"Unit";"Zergling";"Larva";1016;1
"Unit";"Zergling";"Larva";1016;1
"Unit";"Zergling";"Larva";1016;1
"Unit";"Zergling";"Larva";1016;1
"Unit";"Zergling";"Larva";1016;1
"Unit";"Zergling";"Larva";1016;1
"Unit";"Zergling";"Larva";1016;1
"Unit";"Zergling";"Larva";1016;1
"Unit";"Zergling";"Larva";1016;1
"Unit";"Zergling";"Larva";1016;1
"Unit";"Zergling";"Larva";1016;1
"Unit";"Zergling";"Larva";1016;1
"Unit";"Zergling";"Larva";1016;1
"Unit";"Zergling";"Larva";1016;1
"Unit";"Zergling";"Larva";1016;1
"Unit";"Zergling";"Larva";1016;1
"Unit";"Zergling";"Larva";1016;1
"Unit";"Zergling";"Larva";1028;1
"Unit";"Zergling";"Larva";1028;1
"Building";"CreepTumorQueen";NA;1028;0
"Unit";"Zergling";"Larva";1059;1
"Unit";"Zergling";"Larva";1059;1
"Unit";"Zergling";"Larva";1059;1
"Unit";"Zergling";"Larva";1059;1
"Unit";"Zergling";"Larva";1059;1
"Unit";"Zergling";"Larva";1059;1
"Unit";"Zergling";"Larva";1059;1
"Unit";"Zergling";"Larva";1059;1
"Unit";"Zergling";"Larva";1059;1
"Unit";"Zergling";"Larva";1059;1
"Unit";"Queen";"Hatchery";1028;2
