"type";"unit_name";"on_building";"total_supply";"supply"
"Unit";"Overlord";"Larva";13;0
"Building";"Extractor";NA;18;0
"Building";"SpawningPool";NA;18;0
"Building";"Hatchery";NA;16;0
"Unit";"Overlord";"Larva";21;0
"Unit";"Zergling";"Larva";22;1
"Unit";"Zergling";"Larva";22;1
"Unit";"Zergling";"Larva";22;1
"Unit";"Zergling";"Larva";22;1
"Unit";"Zergling";"Larva";22;1
"Unit";"Zergling";"Larva";22;1
"Unit";"Queen";"Hatchery";22;2
"Unit";"Queen";"Hatchery";22;2
"Unit";"Overlord";"Larva";30;0
"Unit";"Queen";"Hatchery";28;2
"Building";"CreepTumorQueen";NA;38;0
"Unit";"Overlord";"Larva";42;0
"Building";"CreepTumor";NA;50;0
"Building";"CreepTumorQueen";NA;53;0
"Unit";"Zergling";"Larva";53;1
"Unit";"Zergling";"Larva";53;1
"Unit";"Zergling";"Larva";53;1
"Unit";"Zergling";"Larva";53;1
"Building";"Extractor";NA;53;0
"Unit";"Overlord";"Larva";53;0
"Unit";"Queen";"Hatchery";53;2
"Unit";"Queen";"Hatchery";53;2
"Building";"CreepTumorQueen";NA;58;0
"Building";"CreepTumor";NA;56;0
"Building";"CreepTumorQueen";NA;60;0
"Building";"CreepTumor";NA;60;0
"Building";"CreepTumorQueen";NA;60;0
"Building";"BanelingNest";NA;53;0
"Building";"Hatchery";NA;50;0
"Unit";"Zergling";"Larva";64;1
"Unit";"Zergling";"Larva";64;1
"Unit";"Overlord";"Larva";65;0
"Unit";"Baneling";"Zergling";67;0
"Unit";"Baneling";"Zergling";67;0
"Unit";"Baneling";"Zergling";67;0
"Unit";"Baneling";"Zergling";67;0
"Building";"CreepTumor";NA;67;0
"Unit";"Queen";"Hatchery";60;2
"Unit";"Queen";"Hatchery";62;2
"Building";"CreepTumorQueen";NA;69;0
"Building";"CreepTumor";NA;69;0
"Building";"CreepTumor";NA;69;0
"Building";"CreepTumor";NA;69;0
"Building";"SporeCrawler";NA;67;0
"Building";"CreepTumorQueen";NA;69;0
"Unit";"Overlord";"Larva";69;0
"Building";"SporeCrawler";NA;67;0
"Building";"CreepTumor";NA;69;0
"Unit";"Overlord";"Larva";73;0
"Building";"EvolutionChamber";NA;79;0
"Building";"EvolutionChamber";NA;79;0
"Unit";"Overlord";"Larva";79;0
"Building";"SporeCrawler";NA;86;0
"Building";"CreepTumor";NA;93;0
"Building";"CreepTumorQueen";NA;93;0
"Building";"CreepTumor";NA;93;0
"Building";"CreepTumor";NA;93;0
"Building";"CreepTumor";NA;93;0
"Building";"CreepTumor";NA;93;0
"Building";"CreepTumor";NA;93;0
"Unit";"Queen";"Hatchery";93;2
"Building";"Extractor";NA;101;0
"Building";"Extractor";NA;101;0
"Unit";"Zergling";"Larva";108;1
"Unit";"Zergling";"Larva";108;1
"Unit";"Zergling";"Larva";108;1
"Unit";"Zergling";"Larva";108;1
"Unit";"Zergling";"Larva";108;1
"Unit";"Zergling";"Larva";108;1
"Unit";"Zergling";"Larva";108;1
"Unit";"Zergling";"Larva";108;1
"Unit";"Zergling";"Larva";108;1
"Unit";"Zergling";"Larva";108;1
"Unit";"Queen";"Hatchery";101;2
"Building";"CreepTumorQueen";NA;120;0
"Building";"CreepTumorQueen";NA;120;0
"Building";"CreepTumorQueen";NA;122;0
"Building";"CreepTumor";NA;122;0
"Building";"CreepTumorQueen";NA;124;0
"Building";"CreepTumor";NA;124;0
"Building";"CreepTumor";NA;124;0
"Building";"CreepTumorQueen";NA;124;0
"Unit";"Zergling";"Larva";124;1
"Unit";"Zergling";"Larva";124;1
"Unit";"Overlord";"Larva";124;0
"Unit";"Overlord";"Larva";124;0
"Unit";"Overlord";"Larva";124;0
"Unit";"Overlord";"Larva";124;0
"Unit";"Overlord";"Larva";124;0
"Unit";"Overlord";"Larva";124;0
"Unit";"Overlord";"Larva";124;0
"Unit";"Overlord";"Larva";124;0
"Building";"SporeCrawler";NA;124;0
"Unit";"Baneling";"Zergling";124;0
"Unit";"Baneling";"Zergling";124;0
"Unit";"Baneling";"Zergling";124;0
"Unit";"Baneling";"Zergling";124;0
"Unit";"Baneling";"Zergling";124;0
"Unit";"Baneling";"Zergling";124;0
"Unit";"Baneling";"Zergling";124;0
"Unit";"Baneling";"Zergling";124;0
"Unit";"Zergling";"Larva";124;1
"Unit";"Zergling";"Larva";124;1
"Building";"SporeCrawler";NA;124;0
"Unit";"Baneling";"Zergling";124;0
"Unit";"Baneling";"Zergling";124;0
"Unit";"Baneling";"Zergling";124;0
"Unit";"Baneling";"Zergling";124;0
"Unit";"Baneling";"Zergling";124;0
"Unit";"Baneling";"Zergling";124;0
"Unit";"Baneling";"Zergling";124;0
"Unit";"Baneling";"Zergling";128;0
"Unit";"Baneling";"Zergling";128;0
"Unit";"Zergling";"Larva";126;1
"Unit";"Zergling";"Larva";126;1
"Unit";"Zergling";"Larva";126;1
"Unit";"Zergling";"Larva";126;1
"Unit";"Zergling";"Larva";126;1
"Unit";"Zergling";"Larva";126;1
"Unit";"Zergling";"Larva";126;1
"Unit";"Zergling";"Larva";126;1
"Unit";"Zergling";"Larva";126;1
"Unit";"Zergling";"Larva";126;1
"Unit";"Zergling";"Larva";126;1
"Unit";"Zergling";"Larva";126;1
"Unit";"Zergling";"Larva";126;1
"Unit";"Zergling";"Larva";126;1
"Unit";"Zergling";"Larva";126;1
"Unit";"Zergling";"Larva";126;1
"Unit";"Zergling";"Larva";126;1
"Unit";"Zergling";"Larva";126;1
"Unit";"Zergling";"Larva";126;1
"Unit";"Zergling";"Larva";126;1
"Unit";"Zergling";"Larva";126;1
"Unit";"Zergling";"Larva";126;1
"Unit";"Zergling";"Larva";126;1
"Unit";"Zergling";"Larva";126;1
"Unit";"Zergling";"Larva";126;1
"Unit";"Zergling";"Larva";126;1
"Unit";"Zergling";"Larva";126;1
"Unit";"Zergling";"Larva";126;1
"Unit";"Zergling";"Larva";128;1
"Unit";"Zergling";"Larva";128;1
"Unit";"Zergling";"Larva";128;1
"Unit";"Zergling";"Larva";128;1
"Unit";"Baneling";"Zergling";128;0
"Unit";"Baneling";"Zergling";128;0
"Unit";"Zergling";"Larva";128;1
"Unit";"Zergling";"Larva";128;1
"Unit";"Zergling";"Larva";128;1
"Unit";"Zergling";"Larva";128;1
"Unit";"Zergling";"Larva";128;1
"Unit";"Zergling";"Larva";128;1
"Unit";"Zergling";"Larva";128;1
"Unit";"Zergling";"Larva";128;1
"Unit";"Zergling";"Larva";128;1
"Unit";"Zergling";"Larva";128;1
"Unit";"Zergling";"Larva";128;1
"Unit";"Zergling";"Larva";128;1
"Unit";"Queen";"Hatchery";126;2
"Unit";"Zergling";"Larva";160;1
"Unit";"Zergling";"Larva";160;1
"Unit";"Zergling";"Larva";160;1
"Unit";"Zergling";"Larva";160;1
"Unit";"Zergling";"Larva";160;1
"Unit";"Zergling";"Larva";160;1
"Unit";"Zergling";"Larva";160;1
"Unit";"Zergling";"Larva";160;1
"Unit";"Zergling";"Larva";160;1
"Unit";"Zergling";"Larva";160;1
"Unit";"Zergling";"Larva";162;1
"Unit";"Zergling";"Larva";162;1
"Unit";"Zergling";"Larva";162;1
"Unit";"Zergling";"Larva";162;1
"Unit";"Zergling";"Larva";162;1
"Unit";"Zergling";"Larva";162;1
"Unit";"Zergling";"Larva";162;1
"Unit";"Zergling";"Larva";162;1
"Unit";"Queen";"Hatchery";128;2
"Unit";"Queen";"Hatchery";128;2
"Unit";"Zergling";"Larva";174;1
"Unit";"Zergling";"Larva";174;1
"Unit";"Zergling";"Larva";174;1
"Unit";"Zergling";"Larva";174;1
"Building";"Hatchery";NA;124;0
"Unit";"Zergling";"Larva";192;1
"Unit";"Zergling";"Larva";192;1
"Unit";"Zergling";"Larva";192;1
"Unit";"Zergling";"Larva";192;1
"Unit";"Zergling";"Larva";192;1
"Unit";"Zergling";"Larva";192;1
"Unit";"Zergling";"Larva";192;1
"Unit";"Zergling";"Larva";192;1
"Unit";"Zergling";"Larva";192;1
"Unit";"Zergling";"Larva";192;1
"Unit";"Zergling";"Larva";192;1
"Unit";"Zergling";"Larva";192;1
"Upgrade";"ZergMeleeWeaponsLevel1";"EvolutionChamber";124;0
"Upgrade";"ZergGroundArmorsLevel1";"EvolutionChamber";124;0
"Unit";"Zergling";"Larva";196;1
"Unit";"Zergling";"Larva";196;1
"Unit";"Zergling";"Larva";200;1
"Unit";"Zergling";"Larva";200;1
"Building";"Hatchery";NA;128;0
"Unit";"Zergling";"Larva";212;1
"Unit";"Zergling";"Larva";212;1
"Unit";"Zergling";"Larva";212;1
"Unit";"Zergling";"Larva";212;1
"Unit";"Zergling";"Larva";212;1
"Unit";"Zergling";"Larva";212;1
"Unit";"Zergling";"Larva";212;1
"Unit";"Zergling";"Larva";212;1
"Unit";"Zergling";"Larva";212;1
"Unit";"Zergling";"Larva";212;1
"Unit";"Baneling";"Zergling";216;0
"Unit";"Baneling";"Zergling";216;0
"Unit";"Baneling";"Zergling";216;0
"Unit";"Baneling";"Zergling";216;0
"Unit";"Baneling";"Zergling";216;0
"Unit";"Baneling";"Zergling";216;0
"Unit";"Baneling";"Zergling";216;0
"Building";"CreepTumorQueen";NA;226;0
"Building";"CreepTumorQueen";NA;226;0
"Unit";"Queen";"Hatchery";212;2
"Unit";"Baneling";"Zergling";226;0
"Building";"CreepTumorQueen";NA;226;0
"Unit";"Baneling";"Zergling";226;0
"Unit";"Baneling";"Zergling";226;0
"Unit";"Baneling";"Zergling";226;0
"Unit";"Baneling";"Zergling";226;0
"Building";"CreepTumor";NA;226;0
"Building";"CreepTumor";NA;228;0
"Building";"CreepTumor";NA;228;0
"Unit";"Queen";"Hatchery";216;2
"Building";"CreepTumorQueen";NA;228;0
"Building";"CreepTumor";NA;228;0
"Building";"CreepTumor";NA;228;0
"Building";"CreepTumor";NA;230;0
"Building";"CreepTumorQueen";NA;243;0
"Building";"CreepTumorQueen";NA;243;0
"Building";"CreepTumorQueen";NA;243;0
"Unit";"Zergling";"Larva";243;1
"Unit";"Zergling";"Larva";243;1
"Unit";"Zergling";"Larva";243;1
"Unit";"Zergling";"Larva";243;1
"Unit";"Zergling";"Larva";243;1
"Unit";"Zergling";"Larva";243;1
"Unit";"Zergling";"Larva";243;1
"Unit";"Zergling";"Larva";243;1
"Unit";"Zergling";"Larva";243;1
"Unit";"Zergling";"Larva";243;1
"Unit";"Zergling";"Larva";243;1
"Unit";"Zergling";"Larva";243;1
"Unit";"Zergling";"Larva";243;1
"Unit";"Zergling";"Larva";243;1
"Unit";"Zergling";"Larva";243;1
"Unit";"Zergling";"Larva";243;1
"Unit";"Zergling";"Larva";243;1
"Unit";"Zergling";"Larva";243;1
"Unit";"Zergling";"Larva";243;1
"Unit";"Zergling";"Larva";243;1
"Unit";"Zergling";"Larva";243;1
"Unit";"Zergling";"Larva";243;1
"Unit";"Zergling";"Larva";243;1
"Unit";"Zergling";"Larva";243;1
"Unit";"Zergling";"Larva";243;1
"Unit";"Zergling";"Larva";243;1
"Unit";"Zergling";"Larva";243;1
"Unit";"Zergling";"Larva";243;1
"Building";"InfestationPit";NA;228;0
"Building";"CreepTumor";NA;243;0
"Building";"CreepTumor";NA;243;0
"Unit";"Queen";"Hatchery";230;2
"Building";"CreepTumor";NA;243;0
"Building";"CreepTumor";NA;243;0
"Unit";"Zergling";"Larva";269;1
"Unit";"Zergling";"Larva";269;1
"Unit";"Zergling";"Larva";271;1
"Unit";"Zergling";"Larva";271;1
"Unit";"Zergling";"Larva";271;1
"Unit";"Zergling";"Larva";271;1
"Unit";"Zergling";"Larva";271;1
"Unit";"Zergling";"Larva";271;1
"Unit";"Zergling";"Larva";271;1
"Unit";"Zergling";"Larva";271;1
"Unit";"Zergling";"Larva";271;1
"Unit";"Zergling";"Larva";271;1
"Unit";"Zergling";"Larva";271;1
"Unit";"Zergling";"Larva";271;1
"Unit";"Zergling";"Larva";271;1
"Unit";"Zergling";"Larva";271;1
"Unit";"Zergling";"Larva";273;1
"Unit";"Zergling";"Larva";273;1
"Unit";"Zergling";"Larva";273;1
"Unit";"Zergling";"Larva";273;1
"Unit";"Zergling";"Larva";273;1
"Unit";"Zergling";"Larva";273;1
"Unit";"Zergling";"Larva";273;1
"Unit";"Zergling";"Larva";273;1
"Unit";"Zergling";"Larva";273;1
"Unit";"Zergling";"Larva";273;1
"Unit";"Zergling";"Larva";273;1
"Unit";"Zergling";"Larva";273;1
"Unit";"Zergling";"Larva";273;1
"Unit";"Zergling";"Larva";273;1
"Unit";"Zergling";"Larva";289;1
"Unit";"Zergling";"Larva";289;1
"Unit";"Zergling";"Larva";289;1
"Unit";"Zergling";"Larva";289;1
"Unit";"Zergling";"Larva";289;1
"Unit";"Zergling";"Larva";289;1
"Unit";"Zergling";"Larva";289;1
"Unit";"Zergling";"Larva";289;1
"Unit";"Zergling";"Larva";289;1
"Unit";"Zergling";"Larva";289;1
"Building";"CreepTumor";NA;303;0
"Unit";"Zergling";"Larva";303;1
"Unit";"Zergling";"Larva";303;1
"Unit";"Zergling";"Larva";303;1
"Unit";"Zergling";"Larva";303;1
"Unit";"Zergling";"Larva";303;1
"Unit";"Zergling";"Larva";303;1
"Unit";"Zergling";"Larva";303;1
"Unit";"Zergling";"Larva";303;1
"Unit";"Zergling";"Larva";303;1
"Unit";"Zergling";"Larva";303;1
"Building";"CreepTumor";NA;317;0
"Building";"CreepTumor";NA;317;0
"Building";"CreepTumor";NA;317;0
"Building";"CreepTumorQueen";NA;327;0
"Unit";"Overlord";"Larva";317;0
"Unit";"Overlord";"Larva";317;0
"Unit";"Baneling";"Zergling";327;0
"Unit";"Baneling";"Zergling";327;0
"Unit";"Baneling";"Zergling";327;0
"Unit";"Baneling";"Zergling";327;0
"Unit";"Baneling";"Zergling";327;0
"Unit";"Baneling";"Zergling";327;0
"Unit";"Baneling";"Zergling";327;0
"Unit";"Baneling";"Zergling";327;0
"Unit";"Baneling";"Zergling";327;0
"Unit";"Baneling";"Zergling";327;0
"Unit";"Queen";"Hatchery";303;2
"Unit";"Queen";"Hatchery";303;2
"Building";"CreepTumorQueen";NA;327;0
"Building";"CreepTumorQueen";NA;327;0
"Upgrade";"ZergMeleeWeaponsLevel2";"EvolutionChamber";239;0
"Upgrade";"ZergGroundArmorsLevel2";"EvolutionChamber";243;0
"Building";"CreepTumorQueen";NA;331;0
"Building";"CreepTumor";NA;331;0
"Building";"CreepTumor";NA;331;0
"Building";"CreepTumor";NA;331;0
"Building";"CreepTumorQueen";NA;331;0
"Building";"CreepTumorQueen";NA;331;0
"Building";"CreepTumorQueen";NA;331;0
"Unit";"Zergling";"Larva";331;1
"Unit";"Zergling";"Larva";331;1
"Unit";"Zergling";"Larva";331;1
"Unit";"Zergling";"Larva";331;1
"Unit";"Zergling";"Larva";331;1
"Unit";"Zergling";"Larva";331;1
"Unit";"Zergling";"Larva";331;1
"Unit";"Zergling";"Larva";331;1
"Unit";"Zergling";"Larva";331;1
"Unit";"Zergling";"Larva";331;1
"Unit";"Zergling";"Larva";331;1
"Unit";"Zergling";"Larva";331;1
"Unit";"Zergling";"Larva";331;1
"Unit";"Zergling";"Larva";331;1
"Unit";"Zergling";"Larva";331;1
"Unit";"Zergling";"Larva";331;1
"Unit";"Zergling";"Larva";331;1
"Unit";"Zergling";"Larva";331;1
"Unit";"Zergling";"Larva";331;1
"Unit";"Zergling";"Larva";331;1
"Unit";"Zergling";"Larva";331;1
"Unit";"Zergling";"Larva";331;1
"Unit";"Zergling";"Larva";331;1
"Unit";"Zergling";"Larva";331;1
"Unit";"Zergling";"Larva";331;1
"Unit";"Zergling";"Larva";331;1
"Unit";"Zergling";"Larva";331;1
"Unit";"Zergling";"Larva";331;1
"Unit";"Zergling";"Larva";331;1
"Unit";"Zergling";"Larva";331;1
"Unit";"Zergling";"Larva";331;1
"Unit";"Zergling";"Larva";331;1
"Unit";"Zergling";"Larva";331;1
"Unit";"Zergling";"Larva";331;1
"Unit";"Zergling";"Larva";331;1
"Unit";"Zergling";"Larva";331;1
"Unit";"Zergling";"Larva";331;1
"Unit";"Zergling";"Larva";331;1
"Unit";"Zergling";"Larva";331;1
"Unit";"Zergling";"Larva";331;1
"Building";"Extractor";NA;331;0
"Unit";"Overlord";"Larva";331;0
"Building";"CreepTumor";NA;371;0
"Building";"UltraliskCavern";NA;331;0
"Unit";"Zergling";"Larva";371;1
"Unit";"Zergling";"Larva";371;1
"Unit";"Zergling";"Larva";371;1
"Unit";"Zergling";"Larva";371;1
"Unit";"Zergling";"Larva";371;1
"Unit";"Zergling";"Larva";371;1
"Unit";"Zergling";"Larva";371;1
"Unit";"Zergling";"Larva";371;1
"Unit";"Zergling";"Larva";371;1
"Unit";"Zergling";"Larva";371;1
"Unit";"Zergling";"Larva";371;1
"Unit";"Zergling";"Larva";371;1
"Unit";"Zergling";"Larva";371;1
"Unit";"Zergling";"Larva";371;1
"Unit";"Zergling";"Larva";371;1
"Unit";"Zergling";"Larva";371;1
"Unit";"Zergling";"Larva";371;1
"Unit";"Zergling";"Larva";371;1
"Unit";"Zergling";"Larva";371;1
"Unit";"Zergling";"Larva";371;1
"Unit";"Zergling";"Larva";371;1
"Unit";"Zergling";"Larva";371;1
"Unit";"Zergling";"Larva";371;1
"Unit";"Zergling";"Larva";371;1
"Unit";"Zergling";"Larva";371;1
"Unit";"Zergling";"Larva";371;1
"Unit";"Zergling";"Larva";371;1
"Unit";"Zergling";"Larva";371;1
"Unit";"Zergling";"Larva";371;1
"Unit";"Zergling";"Larva";371;1
"Unit";"Zergling";"Larva";371;1
"Unit";"Zergling";"Larva";371;1
"Unit";"Zergling";"Larva";371;1
"Unit";"Zergling";"Larva";371;1
"Unit";"Zergling";"Larva";371;1
"Unit";"Zergling";"Larva";371;1
"Unit";"Zergling";"Larva";371;1
"Unit";"Zergling";"Larva";371;1
"Unit";"Zergling";"Larva";371;1
"Unit";"Zergling";"Larva";371;1
"Unit";"Zergling";"Larva";371;1
"Unit";"Zergling";"Larva";371;1
"Unit";"Zergling";"Larva";371;1
"Unit";"Zergling";"Larva";371;1
"Unit";"Zergling";"Larva";371;1
"Unit";"Zergling";"Larva";371;1
"Unit";"Zergling";"Larva";371;1
"Unit";"Zergling";"Larva";371;1
"Unit";"Zergling";"Larva";371;1
"Unit";"Zergling";"Larva";371;1
"Unit";"Zergling";"Larva";371;1
"Unit";"Zergling";"Larva";371;1
"Unit";"Zergling";"Larva";371;1
"Unit";"Zergling";"Larva";371;1
"Unit";"Zergling";"Larva";371;1
"Unit";"Zergling";"Larva";371;1
"Building";"CreepTumorQueen";NA;417;0
"Unit";"Zergling";"Larva";417;1
"Unit";"Zergling";"Larva";417;1
"Unit";"Zergling";"Larva";417;1
"Unit";"Zergling";"Larva";417;1
"Unit";"Zergling";"Larva";417;1
"Unit";"Zergling";"Larva";417;1
"Unit";"Zergling";"Larva";417;1
"Unit";"Zergling";"Larva";417;1
"Building";"CreepTumorQueen";NA;417;0
"Building";"CreepTumorQueen";NA;427;0
"Building";"CreepTumorQueen";NA;427;0
"Building";"CreepTumorQueen";NA;427;0
"Building";"CreepTumor";NA;427;0
"Building";"CreepTumorQueen";NA;435;0
"Building";"Extractor";NA;427;0
"Building";"Hatchery";NA;371;0
"Unit";"Ultralisk";"Larva";427;6
"Unit";"Ultralisk";"Larva";427;6
"Unit";"Ultralisk";"Larva";427;6
"Unit";"Ultralisk";"Larva";427;6
"Unit";"Zergling";"Larva";440;1
"Unit";"Zergling";"Larva";440;1
"Unit";"Zergling";"Larva";440;1
"Unit";"Zergling";"Larva";440;1
"Unit";"Zergling";"Larva";440;1
"Unit";"Zergling";"Larva";440;1
"Unit";"Zergling";"Larva";440;1
"Unit";"Zergling";"Larva";440;1
"Unit";"Zergling";"Larva";440;1
"Unit";"Zergling";"Larva";440;1
"Unit";"Ultralisk";"Larva";440;6
"Unit";"Ultralisk";"Larva";440;6
"Unit";"Ultralisk";"Larva";440;6
"Unit";"Zergling";"Larva";474;1
"Unit";"Zergling";"Larva";474;1
"Unit";"Zergling";"Larva";474;1
"Unit";"Zergling";"Larva";474;1
"Unit";"Zergling";"Larva";474;1
"Unit";"Zergling";"Larva";474;1
"Unit";"Zergling";"Larva";474;1
"Unit";"Zergling";"Larva";474;1
"Unit";"Zergling";"Larva";474;1
"Unit";"Zergling";"Larva";474;1
"Unit";"Zergling";"Larva";474;1
"Unit";"Zergling";"Larva";474;1
"Unit";"Zergling";"Larva";474;1
"Unit";"Zergling";"Larva";474;1
"Unit";"Zergling";"Larva";474;1
"Unit";"Zergling";"Larva";474;1
"Unit";"Zergling";"Larva";474;1
"Unit";"Zergling";"Larva";474;1
"Unit";"Zergling";"Larva";474;1
"Unit";"Zergling";"Larva";474;1
"Unit";"Zergling";"Larva";474;1
"Unit";"Zergling";"Larva";474;1
"Unit";"Zergling";"Larva";474;1
"Unit";"Zergling";"Larva";474;1
"Upgrade";"ChitinousPlating";"UltraliskCavern";440;0
"Building";"CreepTumor";NA;516;0
"Upgrade";"ZergMeleeWeaponsLevel3";"EvolutionChamber";371;0
"Upgrade";"ZergGroundArmorsLevel3";"EvolutionChamber";371;0
"Building";"CreepTumorQueen";NA;516;0
"Building";"CreepTumorQueen";NA;516;0
"Building";"CreepTumorQueen";NA;516;0
"Building";"CreepTumor";NA;516;0
"Building";"CreepTumor";NA;516;0
"Building";"CreepTumor";NA;516;0
"Building";"CreepTumorQueen";NA;516;0
"Building";"CreepTumor";NA;516;0
"Building";"CreepTumor";NA;516;0
"Building";"CreepTumor";NA;516;0
"Building";"CreepTumor";NA;516;0
"Building";"CreepTumor";NA;516;0
"Building";"CreepTumorQueen";NA;516;0
"Unit";"Ultralisk";"Larva";516;6
"Building";"Hatchery";NA;474;0
"Unit";"Ultralisk";"Larva";516;6
"Unit";"Infestor";"Larva";516;2
"Unit";"Infestor";"Larva";516;2
"Unit";"Ultralisk";"Larva";516;6
"Building";"CreepTumor";NA;538;0
"Building";"Hatchery";NA;516;0
"Unit";"Infestor";"Larva";544;2
"Unit";"Infestor";"Larva";544;2
"Unit";"Zergling";"Larva";557;1
"Unit";"Zergling";"Larva";557;1
"Unit";"Zergling";"Larva";557;1
"Unit";"Zergling";"Larva";557;1
"Unit";"Zergling";"Larva";557;1
"Unit";"Zergling";"Larva";557;1
"Unit";"Zergling";"Larva";557;1
"Unit";"Zergling";"Larva";557;1
"Unit";"Zergling";"Larva";557;1
"Unit";"Zergling";"Larva";557;1
"Unit";"Zergling";"Larva";557;1
"Unit";"Zergling";"Larva";557;1
"Unit";"Zergling";"Larva";557;1
"Unit";"Zergling";"Larva";557;1
"Unit";"Zergling";"Larva";557;1
"Unit";"Zergling";"Larva";557;1
"Unit";"Zergling";"Larva";557;1
"Unit";"Zergling";"Larva";557;1
"Unit";"Zergling";"Larva";557;1
"Unit";"Zergling";"Larva";557;1
"Unit";"Zergling";"Larva";557;1
"Unit";"Zergling";"Larva";557;1
"Unit";"Zergling";"Larva";557;1
"Unit";"Zergling";"Larva";557;1
"Unit";"Zergling";"Larva";557;1
"Unit";"Zergling";"Larva";557;1
"Unit";"Zergling";"Larva";557;1
"Unit";"Zergling";"Larva";557;1
"Unit";"Zergling";"Larva";557;1
"Unit";"Zergling";"Larva";557;1
"Building";"CreepTumor";NA;581;0
"Building";"Spire";NA;557;0
"Building";"CreepTumorQueen";NA;591;0
"Building";"Extractor";NA;591;0
"Building";"Extractor";NA;591;0
"Building";"Extractor";NA;591;0
"Building";"Extractor";NA;591;0
"Unit";"Infestor";"Larva";591;2
"Unit";"Infestor";"Larva";591;2
"Building";"Hatchery";NA;591;0
"Unit";"Corruptor";"Larva";591;2
"Unit";"Corruptor";"Larva";591;2
"Unit";"Corruptor";"Larva";591;2
"Unit";"Corruptor";"Larva";591;2
"Unit";"Corruptor";"Larva";591;2
"Unit";"Corruptor";"Larva";591;2
"Unit";"Corruptor";"Larva";591;2
"Unit";"Corruptor";"Larva";591;2
"Unit";"Zergling";"Larva";591;1
"Unit";"Zergling";"Larva";591;1
"Unit";"Zergling";"Larva";591;1
"Unit";"Zergling";"Larva";591;1
"Unit";"Zergling";"Larva";591;1
"Unit";"Zergling";"Larva";591;1
"Unit";"Zergling";"Larva";591;1
"Unit";"Zergling";"Larva";591;1
"Unit";"Zergling";"Larva";591;1
"Unit";"Zergling";"Larva";591;1
"Unit";"Zergling";"Larva";591;1
"Unit";"Zergling";"Larva";591;1
"Unit";"Zergling";"Larva";591;1
"Unit";"Zergling";"Larva";591;1
"Unit";"Zergling";"Larva";591;1
"Unit";"Zergling";"Larva";591;1
"Unit";"Zergling";"Larva";591;1
"Unit";"Zergling";"Larva";591;1
"Unit";"Zergling";"Larva";591;1
"Unit";"Zergling";"Larva";591;1
"Unit";"Zergling";"Larva";591;1
"Unit";"Zergling";"Larva";591;1
"Unit";"Zergling";"Larva";591;1
"Unit";"Zergling";"Larva";591;1
"Unit";"Zergling";"Larva";591;1
"Unit";"Zergling";"Larva";591;1
"Unit";"Zergling";"Larva";591;1
"Unit";"Zergling";"Larva";591;1
"Unit";"Zergling";"Larva";591;1
"Unit";"Zergling";"Larva";591;1
"Unit";"Overlord";"Larva";591;0
"Unit";"Overlord";"Larva";591;0
"Unit";"Zergling";"Larva";641;1
"Unit";"Zergling";"Larva";641;1
"Unit";"Zergling";"Larva";641;1
"Unit";"Zergling";"Larva";641;1
"Unit";"Zergling";"Larva";641;1
"Unit";"Zergling";"Larva";641;1
"Unit";"Zergling";"Larva";641;1
"Unit";"Zergling";"Larva";641;1
"Unit";"Zergling";"Larva";641;1
"Unit";"Zergling";"Larva";641;1
"Unit";"Zergling";"Larva";641;1
"Unit";"Zergling";"Larva";641;1
"Unit";"Zergling";"Larva";641;1
"Unit";"Zergling";"Larva";641;1
"Unit";"Zergling";"Larva";641;1
"Unit";"Zergling";"Larva";641;1
"Unit";"Zergling";"Larva";641;1
"Unit";"Zergling";"Larva";641;1
"Unit";"Zergling";"Larva";641;1
"Unit";"Zergling";"Larva";641;1
"Unit";"Zergling";"Larva";641;1
"Unit";"Zergling";"Larva";641;1
"Unit";"Zergling";"Larva";641;1
"Unit";"Zergling";"Larva";641;1
"Unit";"Zergling";"Larva";641;1
"Unit";"Zergling";"Larva";641;1
"Unit";"Queen";"Hatchery";595;2
"Unit";"Zergling";"Larva";669;1
"Unit";"Zergling";"Larva";669;1
"Unit";"Zergling";"Larva";669;1
"Unit";"Zergling";"Larva";669;1
"Unit";"Zergling";"Larva";669;1
"Unit";"Zergling";"Larva";669;1
"Unit";"Zergling";"Larva";669;1
"Unit";"Zergling";"Larva";669;1
"Unit";"Zergling";"Larva";669;1
"Unit";"Zergling";"Larva";669;1
"Unit";"Zergling";"Larva";669;1
"Unit";"Zergling";"Larva";669;1
"Unit";"Zergling";"Larva";669;1
"Unit";"Zergling";"Larva";669;1
"Unit";"Zergling";"Larva";669;1
"Unit";"Zergling";"Larva";669;1
"Unit";"Zergling";"Larva";669;1
"Unit";"Zergling";"Larva";669;1
"Unit";"Zergling";"Larva";669;1
"Unit";"Zergling";"Larva";669;1
"Unit";"Zergling";"Larva";669;1
"Unit";"Zergling";"Larva";669;1
"Unit";"Zergling";"Larva";669;1
"Unit";"Zergling";"Larva";669;1
"Unit";"Zergling";"Larva";669;1
"Unit";"Zergling";"Larva";669;1
"Unit";"Zergling";"Larva";669;1
"Unit";"Zergling";"Larva";669;1
"Unit";"Zergling";"Larva";669;1
"Unit";"Zergling";"Larva";669;1
"Unit";"Zergling";"Larva";669;1
"Unit";"Zergling";"Larva";669;1
"Unit";"Zergling";"Larva";669;1
"Unit";"Zergling";"Larva";669;1
"Unit";"Zergling";"Larva";669;1
"Unit";"Zergling";"Larva";669;1
"Unit";"Ultralisk";"Larva";669;6
"Unit";"Ultralisk";"Larva";669;6
"Unit";"Ultralisk";"Larva";669;6
"Unit";"Ultralisk";"Larva";669;6
"Unit";"Ultralisk";"Larva";669;6
"Unit";"Zergling";"Larva";705;1
"Unit";"Zergling";"Larva";705;1
"Unit";"Corruptor";"Larva";705;2
"Unit";"Zergling";"Larva";705;1
"Unit";"Zergling";"Larva";705;1
"Unit";"Zergling";"Larva";705;1
"Unit";"Zergling";"Larva";705;1
"Unit";"Zergling";"Larva";705;1
"Unit";"Zergling";"Larva";705;1
"Unit";"Corruptor";"Larva";705;2
"Unit";"Corruptor";"Larva";705;2
"Unit";"Zergling";"Larva";705;1
"Unit";"Zergling";"Larva";705;1
"Unit";"Zergling";"Larva";705;1
"Unit";"Zergling";"Larva";705;1
"Unit";"Zergling";"Larva";705;1
"Unit";"Zergling";"Larva";705;1
"Unit";"Corruptor";"Larva";705;2
"Unit";"Corruptor";"Larva";705;2
"Unit";"Baneling";"Zergling";755;0
"Unit";"Baneling";"Zergling";755;0
"Unit";"Baneling";"Zergling";755;0
"Unit";"Baneling";"Zergling";755;0
"Unit";"Baneling";"Zergling";755;0
"Unit";"Zergling";"Larva";755;1
"Unit";"Zergling";"Larva";755;1
"Unit";"Zergling";"Larva";755;1
"Unit";"Zergling";"Larva";755;1
"Unit";"Zergling";"Larva";755;1
"Unit";"Zergling";"Larva";755;1
"Unit";"Zergling";"Larva";755;1
"Unit";"Zergling";"Larva";755;1
"Unit";"Zergling";"Larva";755;1
"Unit";"Zergling";"Larva";755;1
"Unit";"Zergling";"Larva";755;1
"Unit";"Zergling";"Larva";755;1
"Unit";"Zergling";"Larva";755;1
"Unit";"Zergling";"Larva";755;1
"Unit";"Zergling";"Larva";755;1
"Unit";"Zergling";"Larva";755;1
"Unit";"Zergling";"Larva";755;1
"Unit";"Zergling";"Larva";755;1
"Unit";"Zergling";"Larva";755;1
"Unit";"Zergling";"Larva";755;1
"Unit";"Zergling";"Larva";755;1
"Unit";"Zergling";"Larva";755;1
"Unit";"Baneling";"Zergling";755;0
"Unit";"Zergling";"Larva";755;1
"Unit";"Zergling";"Larva";755;1
"Unit";"Zergling";"Larva";755;1
"Unit";"Zergling";"Larva";755;1
"Unit";"Baneling";"Zergling";755;0
"Unit";"Baneling";"Zergling";755;0
"Unit";"Baneling";"Zergling";755;0
"Unit";"Baneling";"Zergling";755;0
"Unit";"Baneling";"Zergling";755;0
"Building";"Extractor";NA;755;0
"Building";"Extractor";NA;755;0
"Unit";"Corruptor";"Larva";759;2
"Unit";"Zergling";"Larva";787;1
"Unit";"Zergling";"Larva";787;1
"Unit";"Zergling";"Larva";787;1
"Unit";"Zergling";"Larva";787;1
"Unit";"Zergling";"Larva";787;1
"Unit";"Zergling";"Larva";787;1
"Unit";"Zergling";"Larva";787;1
"Unit";"Zergling";"Larva";787;1
"Unit";"Zergling";"Larva";787;1
"Unit";"Zergling";"Larva";787;1
"Unit";"Zergling";"Larva";787;1
"Unit";"Zergling";"Larva";787;1
"Unit";"Zergling";"Larva";787;1
"Unit";"Zergling";"Larva";787;1
"Unit";"Zergling";"Larva";787;1
"Unit";"Zergling";"Larva";787;1
"Unit";"Zergling";"Larva";787;1
"Unit";"Zergling";"Larva";787;1
"Unit";"Zergling";"Larva";787;1
"Unit";"Zergling";"Larva";787;1
"Unit";"Zergling";"Larva";787;1
"Unit";"Zergling";"Larva";787;1
"Unit";"Corruptor";"Larva";787;2
"Unit";"Corruptor";"Larva";787;2
"Unit";"Corruptor";"Larva";787;2
"Unit";"Corruptor";"Larva";787;2
