"type";"unit_name";"on_building";"total_supply";"supply"
"Unit";"Overlord";"Larva";13;0
"Building";"Extractor";NA;17;0
"Unit";"Overlord";"Larva";21;0
"Building";"SpawningPool";NA;19;0
"Building";"Hatchery";NA;17;0
"Unit";"Zergling";"Larva";23;1
"Unit";"Zergling";"Larva";23;1
"Unit";"Zergling";"Larva";23;1
"Unit";"Zergling";"Larva";23;1
"Unit";"Queen";"Hatchery";23;2
"Unit";"Queen";"Hatchery";23;2
"Building";"CreepTumorQueen";NA;34;0
"Unit";"Overlord";"Larva";36;0
"Building";"CreepTumor";NA;38;0
"Unit";"Queen";"Hatchery";38;2
"Unit";"Overlord";"Larva";40;0
"Unit";"Zergling";"Larva";42;1
"Unit";"Zergling";"Larva";42;1
"Unit";"Zergling";"Larva";42;1
"Unit";"Zergling";"Larva";42;1
"Unit";"Zergling";"Larva";42;1
"Unit";"Zergling";"Larva";42;1
"Unit";"Zergling";"Larva";42;1
"Unit";"Zergling";"Larva";42;1
"Building";"CreepTumor";NA;44;0
"Building";"Hatchery";NA;30;0
"Unit";"Queen";"Hatchery";38;2
"Building";"CreepTumorQueen";NA;56;0
"Building";"CreepTumorQueen";NA;56;0
"Building";"Extractor";NA;56;0
"Unit";"Zergling";"Larva";62;1
"Unit";"Zergling";"Larva";62;1
"Unit";"Zergling";"Larva";62;1
"Unit";"Zergling";"Larva";62;1
"Unit";"Zergling";"Larva";62;1
"Unit";"Zergling";"Larva";62;1
"Unit";"Queen";"Hatchery";56;2
"Building";"EvolutionChamber";NA;65;0
"Building";"EvolutionChamber";NA;65;0
"Unit";"Overlord";"Larva";71;0
"Unit";"Overlord";"Larva";71;0
"Building";"CreepTumorQueen";NA;76;0
"Building";"CreepTumor";NA;76;0
"Building";"CreepTumor";NA;76;0
"Building";"CreepTumor";NA;76;0
"Unit";"Zergling";"Larva";76;1
"Unit";"Zergling";"Larva";76;1
"Unit";"Zergling";"Larva";76;1
"Unit";"Zergling";"Larva";76;1
"Unit";"Zergling";"Larva";76;1
"Unit";"Zergling";"Larva";76;1
"Unit";"Zergling";"Larva";76;1
"Unit";"Zergling";"Larva";76;1
"Unit";"Zergling";"Larva";76;1
"Unit";"Zergling";"Larva";76;1
"Unit";"Zergling";"Larva";76;1
"Unit";"Zergling";"Larva";76;1
"Unit";"Zergling";"Larva";76;1
"Unit";"Zergling";"Larva";76;1
"Unit";"Zergling";"Larva";76;1
"Unit";"Zergling";"Larva";76;1
"Unit";"Zergling";"Larva";76;1
"Unit";"Zergling";"Larva";76;1
"Building";"CreepTumorQueen";NA;94;0
"Building";"CreepTumorQueen";NA;94;0
"Building";"CreepTumor";NA;94;0
"Unit";"Overlord";"Larva";97;0
"Building";"CreepTumorQueen";NA;100;0
"Building";"CreepTumorQueen";NA;100;0
"Building";"BanelingNest";NA;76;0
"Building";"CreepTumorQueen";NA;100;0
"Building";"CreepTumor";NA;104;0
"Unit";"Baneling";"Zergling";107;0
"Unit";"Baneling";"Zergling";107;0
"Unit";"Baneling";"Zergling";107;0
"Unit";"Baneling";"Zergling";107;0
"Unit";"Baneling";"Zergling";107;0
"Unit";"Baneling";"Zergling";107;0
"Unit";"Baneling";"Zergling";107;0
"Unit";"Baneling";"Zergling";107;0
"Unit";"Zergling";"Larva";107;1
"Unit";"Zergling";"Larva";107;1
"Unit";"Queen";"Hatchery";100;2
"Unit";"Zergling";"Larva";107;1
"Unit";"Zergling";"Larva";107;1
"Unit";"Zergling";"Larva";107;1
"Unit";"Zergling";"Larva";107;1
"Unit";"Zergling";"Larva";107;1
"Unit";"Zergling";"Larva";107;1
"Unit";"Zergling";"Larva";107;1
"Unit";"Zergling";"Larva";107;1
"Unit";"Zergling";"Larva";107;1
"Unit";"Zergling";"Larva";107;1
"Unit";"Zergling";"Larva";107;1
"Unit";"Zergling";"Larva";107;1
"Unit";"Zergling";"Larva";107;1
"Unit";"Zergling";"Larva";107;1
"Unit";"Zergling";"Larva";107;1
"Unit";"Zergling";"Larva";107;1
"Unit";"Zergling";"Larva";107;1
"Unit";"Zergling";"Larva";107;1
"Unit";"Zergling";"Larva";107;1
"Unit";"Zergling";"Larva";107;1
"Building";"SporeCrawler";NA;107;0
"Building";"SporeCrawler";NA;107;0
"Unit";"Overlord";"Larva";111;0
"Unit";"Overlord";"Larva";111;0
"Building";"SporeCrawler";NA;107;0
"Building";"SporeCrawler";NA;107;0
"Building";"CreepTumor";NA;131;0
"Building";"CreepTumorQueen";NA;133;0
"Building";"Extractor";NA;131;0
"Building";"CreepTumorQueen";NA;133;0
"Building";"CreepTumorQueen";NA;133;0
"Building";"CreepTumorQueen";NA;133;0
"Upgrade";"ZergGroundArmorsLevel1";"EvolutionChamber";97;0
"Upgrade";"ZergMeleeWeaponsLevel1";"EvolutionChamber";97;0
"Unit";"Overlord";"Larva";133;0
"Unit";"Overlord";"Larva";133;0
"Unit";"Overlord";"Larva";133;0
"Unit";"Overlord";"Larva";133;0
"Building";"CreepTumor";NA;133;0
"Building";"CreepTumor";NA;133;0
"Unit";"Queen";"Hatchery";131;2
"Unit";"Zergling";"Larva";133;1
"Unit";"Zergling";"Larva";133;1
"Unit";"Zergling";"Larva";133;1
"Unit";"Zergling";"Larva";133;1
"Unit";"Zergling";"Larva";133;1
"Unit";"Zergling";"Larva";133;1
"Unit";"Zergling";"Larva";133;1
"Unit";"Zergling";"Larva";133;1
"Unit";"Zergling";"Larva";133;1
"Unit";"Zergling";"Larva";133;1
"Unit";"Zergling";"Larva";133;1
"Unit";"Zergling";"Larva";133;1
"Unit";"Zergling";"Larva";133;1
"Unit";"Zergling";"Larva";133;1
"Unit";"Zergling";"Larva";133;1
"Unit";"Zergling";"Larva";133;1
"Building";"CreepTumor";NA;139;0
"Building";"CreepTumor";NA;139;0
"Building";"CreepTumor";NA;139;0
"Building";"CreepTumor";NA;139;0
"Building";"CreepTumorQueen";NA;155;0
"Unit";"Overlord";"Larva";139;0
"Unit";"Overlord";"Larva";157;0
"Unit";"Overlord";"Larva";157;0
"Unit";"Zergling";"Larva";157;1
"Unit";"Zergling";"Larva";157;1
"Unit";"Zergling";"Larva";157;1
"Unit";"Zergling";"Larva";157;1
"Building";"Hatchery";NA;131;0
"Building";"CreepTumorQueen";NA;164;0
"Building";"CreepTumorQueen";NA;164;0
"Unit";"Zergling";"Larva";164;1
"Unit";"Zergling";"Larva";164;1
"Unit";"Zergling";"Larva";164;1
"Unit";"Zergling";"Larva";164;1
"Unit";"Zergling";"Larva";164;1
"Unit";"Zergling";"Larva";164;1
"Unit";"Zergling";"Larva";164;1
"Unit";"Zergling";"Larva";164;1
"Unit";"Zergling";"Larva";164;1
"Unit";"Zergling";"Larva";164;1
"Unit";"Zergling";"Larva";164;1
"Unit";"Zergling";"Larva";164;1
"Unit";"Zergling";"Larva";164;1
"Unit";"Zergling";"Larva";164;1
"Unit";"Zergling";"Larva";164;1
"Unit";"Zergling";"Larva";164;1
"Unit";"Zergling";"Larva";164;1
"Unit";"Zergling";"Larva";164;1
"Unit";"Zergling";"Larva";164;1
"Unit";"Zergling";"Larva";164;1
"Unit";"Zergling";"Larva";164;1
"Unit";"Zergling";"Larva";164;1
"Unit";"Zergling";"Larva";164;1
"Unit";"Zergling";"Larva";164;1
"Unit";"Zergling";"Larva";164;1
"Unit";"Zergling";"Larva";164;1
"Unit";"Zergling";"Larva";164;1
"Unit";"Zergling";"Larva";164;1
"Unit";"Zergling";"Larva";164;1
"Unit";"Zergling";"Larva";164;1
"Building";"CreepTumorQueen";NA;164;0
"Building";"CreepTumor";NA;164;0
"Building";"CreepTumorQueen";NA;164;0
"Building";"CreepTumor";NA;164;0
"Building";"CreepTumor";NA;164;0
"Building";"CreepTumor";NA;164;0
"Unit";"Zergling";"Larva";164;1
"Unit";"Zergling";"Larva";164;1
"Unit";"Zergling";"Larva";166;1
"Unit";"Zergling";"Larva";166;1
"Unit";"Zergling";"Larva";166;1
"Unit";"Zergling";"Larva";166;1
"Unit";"Zergling";"Larva";166;1
"Unit";"Zergling";"Larva";166;1
"Unit";"Baneling";"Zergling";194;0
"Unit";"Zergling";"Larva";170;1
"Unit";"Zergling";"Larva";170;1
"Unit";"Zergling";"Larva";170;1
"Unit";"Zergling";"Larva";170;1
"Unit";"Zergling";"Larva";174;1
"Unit";"Zergling";"Larva";174;1
"Unit";"Baneling";"Zergling";194;0
"Unit";"Baneling";"Zergling";194;0
"Unit";"Baneling";"Zergling";194;0
"Unit";"Baneling";"Zergling";194;0
"Building";"CreepTumor";NA;194;0
"Building";"CreepTumor";NA;194;0
"Building";"CreepTumor";NA;194;0
"Unit";"Queen";"Hatchery";164;2
"Building";"CreepTumor";NA;194;0
"Building";"CreepTumor";NA;196;0
"Building";"CreepTumor";NA;194;0
"Building";"CreepTumor";NA;208;0
"Unit";"Zergling";"Larva";208;1
"Unit";"Zergling";"Larva";208;1
"Unit";"Zergling";"Larva";209;1
"Unit";"Zergling";"Larva";209;1
"Unit";"Zergling";"Larva";209;1
"Unit";"Zergling";"Larva";209;1
"Unit";"Zergling";"Larva";210;1
"Unit";"Zergling";"Larva";210;1
"Unit";"Zergling";"Larva";210;1
"Unit";"Zergling";"Larva";210;1
"Unit";"Zergling";"Larva";210;1
"Unit";"Zergling";"Larva";210;1
"Unit";"Zergling";"Larva";210;1
"Unit";"Zergling";"Larva";210;1
"Unit";"Zergling";"Larva";211;1
"Unit";"Zergling";"Larva";211;1
"Unit";"Baneling";"Zergling";213;0
"Unit";"Baneling";"Zergling";213;0
"Unit";"Baneling";"Zergling";213;0
"Unit";"Baneling";"Zergling";213;0
"Unit";"Baneling";"Zergling";213;0
"Unit";"Baneling";"Zergling";213;0
"Building";"Extractor";NA;211;0
"Unit";"Overlord";"Larva";213;0
"Building";"CreepTumor";NA;229;0
"Building";"CreepTumor";NA;229;0
"Building";"CreepTumor";NA;229;0
"Building";"CreepTumor";NA;229;0
"Building";"CreepTumorQueen";NA;232;0
"Building";"CreepTumorQueen";NA;232;0
"Building";"CreepTumorQueen";NA;232;0
"Building";"CreepTumorQueen";NA;232;0
"Unit";"Zergling";"Larva";238;1
"Unit";"Zergling";"Larva";238;1
"Upgrade";"ZergMeleeWeaponsLevel2";"EvolutionChamber";164;0
"Unit";"Zergling";"Larva";238;1
"Unit";"Zergling";"Larva";238;1
"Unit";"Zergling";"Larva";238;1
"Unit";"Zergling";"Larva";238;1
"Unit";"Zergling";"Larva";238;1
"Unit";"Zergling";"Larva";238;1
"Unit";"Zergling";"Larva";238;1
"Unit";"Zergling";"Larva";238;1
"Unit";"Zergling";"Larva";238;1
"Unit";"Zergling";"Larva";238;1
"Unit";"Zergling";"Larva";238;1
"Unit";"Zergling";"Larva";238;1
"Unit";"Zergling";"Larva";238;1
"Unit";"Zergling";"Larva";238;1
"Unit";"Zergling";"Larva";238;1
"Unit";"Zergling";"Larva";238;1
"Unit";"Zergling";"Larva";238;1
"Unit";"Zergling";"Larva";238;1
"Unit";"Zergling";"Larva";238;1
"Unit";"Zergling";"Larva";238;1
"Building";"Hatchery";NA;194;0
"Building";"CreepTumor";NA;260;0
"Building";"CreepTumor";NA;260;0
"Building";"CreepTumor";NA;260;0
"Building";"CreepTumor";NA;260;0
"Building";"SporeCrawler";NA;238;0
"Unit";"Zergling";"Larva";238;1
"Unit";"Zergling";"Larva";238;1
"Upgrade";"ZergGroundArmorsLevel2";"EvolutionChamber";164;0
"Unit";"Zergling";"Larva";240;1
"Unit";"Zergling";"Larva";240;1
"Unit";"Zergling";"Larva";240;1
"Unit";"Zergling";"Larva";240;1
"Unit";"Zergling";"Larva";240;1
"Unit";"Zergling";"Larva";240;1
"Unit";"Zergling";"Larva";240;1
"Unit";"Zergling";"Larva";240;1
"Unit";"Zergling";"Larva";240;1
"Unit";"Zergling";"Larva";240;1
"Unit";"Zergling";"Larva";240;1
"Unit";"Zergling";"Larva";240;1
"Unit";"Zergling";"Larva";240;1
"Unit";"Zergling";"Larva";240;1
"Unit";"Zergling";"Larva";240;1
"Unit";"Zergling";"Larva";240;1
"Unit";"Zergling";"Larva";240;1
"Unit";"Zergling";"Larva";240;1
"Unit";"Baneling";"Zergling";260;0
"Unit";"Baneling";"Zergling";260;0
"Unit";"Baneling";"Zergling";260;0
"Unit";"Baneling";"Zergling";260;0
"Unit";"Baneling";"Zergling";260;0
"Building";"Extractor";NA;260;0
"Building";"Extractor";NA;260;0
"Building";"Extractor";NA;260;0
"Building";"Extractor";NA;260;0
"Building";"CreepTumor";NA;286;0
"Building";"CreepTumor";NA;286;0
"Building";"CreepTumor";NA;286;0
"Building";"CreepTumor";NA;286;0
"Building";"CreepTumor";NA;286;0
"Building";"CreepTumor";NA;286;0
"Building";"CreepTumor";NA;286;0
"Building";"CreepTumor";NA;286;0
"Unit";"Baneling";"Zergling";292;0
"Building";"InfestationPit";NA;260;0
"Unit";"Baneling";"Zergling";292;0
"Unit";"Baneling";"Zergling";292;0
"Building";"SporeCrawler";NA;283;0
"Unit";"Baneling";"Zergling";292;0
"Unit";"Baneling";"Zergling";292;0
"Unit";"Baneling";"Zergling";292;0
"Unit";"Baneling";"Zergling";292;0
"Unit";"Baneling";"Zergling";292;0
"Unit";"Baneling";"Zergling";292;0
"Unit";"Baneling";"Zergling";292;0
"Unit";"Queen";"Hatchery";260;2
"Unit";"Zergling";"Larva";292;1
"Unit";"Zergling";"Larva";292;1
"Unit";"Baneling";"Zergling";292;0
"Unit";"Zergling";"Larva";292;1
"Unit";"Zergling";"Larva";292;1
"Unit";"Zergling";"Larva";292;1
"Unit";"Zergling";"Larva";292;1
"Unit";"Zergling";"Larva";292;1
"Unit";"Zergling";"Larva";292;1
"Unit";"Zergling";"Larva";292;1
"Unit";"Zergling";"Larva";292;1
"Unit";"Zergling";"Larva";292;1
"Unit";"Zergling";"Larva";292;1
"Unit";"Baneling";"Zergling";292;0
"Unit";"Zergling";"Larva";292;1
"Unit";"Zergling";"Larva";292;1
"Unit";"Zergling";"Larva";292;1
"Unit";"Zergling";"Larva";292;1
"Unit";"Zergling";"Larva";292;1
"Unit";"Zergling";"Larva";292;1
"Unit";"Zergling";"Larva";292;1
"Unit";"Zergling";"Larva";292;1
"Unit";"Baneling";"Zergling";292;0
"Unit";"Baneling";"Zergling";292;0
"Unit";"Baneling";"Zergling";292;0
"Unit";"Baneling";"Zergling";292;0
"Unit";"Zergling";"Larva";292;1
"Unit";"Zergling";"Larva";292;1
"Unit";"Zergling";"Larva";292;1
"Unit";"Zergling";"Larva";292;1
"Unit";"Zergling";"Larva";292;1
"Unit";"Zergling";"Larva";292;1
"Unit";"Baneling";"Zergling";292;0
"Unit";"Baneling";"Zergling";292;0
"Unit";"Baneling";"Zergling";292;0
"Unit";"Baneling";"Zergling";292;0
"Unit";"Baneling";"Zergling";292;0
"Unit";"Baneling";"Zergling";292;0
"Unit";"Baneling";"Zergling";292;0
"Building";"CreepTumor";NA;292;0
"Unit";"Zergling";"Larva";292;1
"Unit";"Zergling";"Larva";292;1
"Unit";"Zergling";"Larva";292;1
"Unit";"Zergling";"Larva";292;1
"Unit";"Zergling";"Larva";294;1
"Unit";"Zergling";"Larva";294;1
"Unit";"Zergling";"Larva";294;1
"Unit";"Zergling";"Larva";294;1
"Unit";"Zergling";"Larva";294;1
"Unit";"Zergling";"Larva";294;1
"Unit";"Zergling";"Larva";294;1
"Unit";"Zergling";"Larva";294;1
"Unit";"Zergling";"Larva";294;1
"Unit";"Zergling";"Larva";294;1
"Unit";"Zergling";"Larva";294;1
"Unit";"Zergling";"Larva";294;1
"Unit";"Zergling";"Larva";294;1
"Unit";"Zergling";"Larva";294;1
"Unit";"Zergling";"Larva";294;1
"Unit";"Zergling";"Larva";294;1
"Unit";"Zergling";"Larva";320;1
"Unit";"Zergling";"Larva";320;1
"Building";"CreepTumor";NA;320;0
"Building";"CreepTumor";NA;320;0
"Building";"CreepTumor";NA;320;0
"Building";"CreepTumor";NA;320;0
"Unit";"Zergling";"Larva";320;1
"Unit";"Zergling";"Larva";320;1
"Unit";"Zergling";"Larva";320;1
"Unit";"Zergling";"Larva";320;1
"Unit";"Zergling";"Larva";320;1
"Unit";"Zergling";"Larva";320;1
"Building";"CreepTumor";NA;320;0
"Unit";"Zergling";"Larva";320;1
"Unit";"Zergling";"Larva";320;1
"Unit";"Zergling";"Larva";320;1
"Unit";"Zergling";"Larva";320;1
"Unit";"Zergling";"Larva";320;1
"Unit";"Zergling";"Larva";320;1
"Unit";"Zergling";"Larva";320;1
"Unit";"Zergling";"Larva";320;1
"Unit";"Zergling";"Larva";320;1
"Unit";"Zergling";"Larva";320;1
"Building";"CreepTumor";NA;320;0
"Building";"CreepTumor";NA;340;0
"Building";"CreepTumorQueen";NA;358;0
"Building";"CreepTumor";NA;358;0
"Unit";"Overlord";"Larva";358;0
"Unit";"Overlord";"Larva";358;0
"Unit";"Overlord";"Larva";358;0
"Unit";"Overlord";"Larva";358;0
"Unit";"Overlord";"Larva";358;0
"Unit";"Overlord";"Larva";358;0
"Unit";"Zergling";"Larva";358;1
"Unit";"Zergling";"Larva";358;1
"Unit";"Zergling";"Larva";358;1
"Unit";"Zergling";"Larva";358;1
"Unit";"Zergling";"Larva";358;1
"Unit";"Zergling";"Larva";358;1
"Unit";"Zergling";"Larva";358;1
"Unit";"Zergling";"Larva";358;1
"Unit";"Zergling";"Larva";358;1
"Unit";"Zergling";"Larva";358;1
"Unit";"Zergling";"Larva";358;1
"Unit";"Zergling";"Larva";358;1
"Unit";"Zergling";"Larva";358;1
"Unit";"Zergling";"Larva";358;1
"Unit";"Zergling";"Larva";358;1
"Unit";"Zergling";"Larva";358;1
"Unit";"Zergling";"Larva";358;1
"Unit";"Zergling";"Larva";358;1
"Unit";"Zergling";"Larva";358;1
"Unit";"Zergling";"Larva";358;1
"Unit";"Zergling";"Larva";358;1
"Unit";"Zergling";"Larva";358;1
"Unit";"Zergling";"Larva";358;1
"Unit";"Zergling";"Larva";358;1
"Unit";"Zergling";"Larva";358;1
"Unit";"Zergling";"Larva";358;1
"Unit";"Zergling";"Larva";358;1
"Unit";"Zergling";"Larva";358;1
"Unit";"Zergling";"Larva";358;1
"Unit";"Zergling";"Larva";358;1
"Unit";"Zergling";"Larva";358;1
"Unit";"Zergling";"Larva";358;1
"Unit";"Zergling";"Larva";358;1
"Unit";"Zergling";"Larva";358;1
"Building";"CreepTumorQueen";NA;370;0
"Building";"CreepTumorQueen";NA;370;0
"Building";"CreepTumorQueen";NA;370;0
"Unit";"Baneling";"Zergling";370;0
"Unit";"Baneling";"Zergling";370;0
"Unit";"Baneling";"Zergling";370;0
"Unit";"Baneling";"Zergling";370;0
"Unit";"Baneling";"Zergling";370;0
"Unit";"Baneling";"Zergling";370;0
"Unit";"Baneling";"Zergling";370;0
"Unit";"Baneling";"Zergling";370;0
"Unit";"Baneling";"Zergling";370;0
"Unit";"Baneling";"Zergling";370;0
"Unit";"Baneling";"Zergling";370;0
"Upgrade";"ZergMissileWeaponsLevel1";"EvolutionChamber";292;0
"Building";"CreepTumor";NA;392;0
"Building";"CreepTumor";NA;392;0
"Building";"CreepTumor";NA;392;0
"Building";"CreepTumor";NA;392;0
"Building";"CreepTumor";NA;392;0
"Building";"CreepTumor";NA;392;0
"Unit";"Baneling";"Zergling";392;0
"Building";"CreepTumor";NA;392;0
"Unit";"Baneling";"Zergling";392;0
"Building";"CreepTumor";NA;392;0
"Unit";"Baneling";"Zergling";392;0
"Unit";"Baneling";"Zergling";392;0
"Unit";"Baneling";"Zergling";392;0
"Unit";"Baneling";"Zergling";392;0
"Unit";"Baneling";"Zergling";392;0
"Unit";"Baneling";"Zergling";392;0
"Unit";"Baneling";"Zergling";392;0
"Unit";"Baneling";"Zergling";392;0
"Unit";"Zergling";"Larva";392;1
"Unit";"Zergling";"Larva";392;1
"Unit";"Zergling";"Larva";392;1
"Unit";"Zergling";"Larva";392;1
"Unit";"Zergling";"Larva";392;1
"Unit";"Zergling";"Larva";392;1
"Unit";"Zergling";"Larva";392;1
"Unit";"Zergling";"Larva";392;1
"Unit";"Zergling";"Larva";392;1
"Unit";"Zergling";"Larva";392;1
"Unit";"Zergling";"Larva";392;1
"Unit";"Zergling";"Larva";392;1
"Unit";"Zergling";"Larva";392;1
"Unit";"Zergling";"Larva";392;1
"Building";"UltraliskCavern";NA;392;0
"Unit";"Zergling";"Larva";406;1
"Unit";"Zergling";"Larva";406;1
"Unit";"Zergling";"Larva";406;1
"Unit";"Zergling";"Larva";406;1
"Unit";"Zergling";"Larva";406;1
"Unit";"Zergling";"Larva";406;1
"Unit";"Zergling";"Larva";406;1
"Unit";"Zergling";"Larva";406;1
"Unit";"Zergling";"Larva";406;1
"Unit";"Zergling";"Larva";406;1
"Unit";"Zergling";"Larva";406;1
"Unit";"Zergling";"Larva";406;1
"Unit";"Zergling";"Larva";406;1
"Unit";"Zergling";"Larva";406;1
"Unit";"Zergling";"Larva";406;1
"Unit";"Zergling";"Larva";406;1
"Unit";"Zergling";"Larva";406;1
"Unit";"Zergling";"Larva";406;1
"Unit";"Zergling";"Larva";406;1
"Unit";"Zergling";"Larva";406;1
"Unit";"Zergling";"Larva";406;1
"Unit";"Zergling";"Larva";406;1
"Unit";"Zergling";"Larva";406;1
"Unit";"Zergling";"Larva";406;1
"Unit";"Zergling";"Larva";406;1
"Unit";"Zergling";"Larva";406;1
"Unit";"Zergling";"Larva";406;1
"Unit";"Zergling";"Larva";406;1
"Unit";"Zergling";"Larva";406;1
"Unit";"Zergling";"Larva";406;1
"Unit";"Zergling";"Larva";406;1
"Unit";"Zergling";"Larva";406;1
"Unit";"Zergling";"Larva";406;1
"Unit";"Zergling";"Larva";406;1
"Unit";"Zergling";"Larva";406;1
"Unit";"Zergling";"Larva";406;1
"Building";"CreepTumor";NA;406;0
"Building";"CreepTumor";NA;406;0
"Building";"CreepTumor";NA;406;0
"Unit";"Overlord";"Larva";406;0
"Unit";"Overlord";"Larva";406;0
"Building";"CreepTumor";NA;442;0
"Building";"CreepTumor";NA;442;0
"Building";"CreepTumor";NA;442;0
"Building";"CreepTumor";NA;442;0
"Unit";"Zergling";"Larva";408;1
"Unit";"Zergling";"Larva";408;1
"Unit";"Zergling";"Larva";438;1
"Unit";"Zergling";"Larva";438;1
"Unit";"Zergling";"Larva";438;1
"Unit";"Zergling";"Larva";438;1
"Unit";"Zergling";"Larva";440;1
"Unit";"Zergling";"Larva";440;1
"Unit";"Zergling";"Larva";440;1
"Unit";"Zergling";"Larva";440;1
"Unit";"Zergling";"Larva";442;1
"Unit";"Zergling";"Larva";442;1
"Unit";"Zergling";"Larva";442;1
"Unit";"Zergling";"Larva";442;1
"Building";"CreepTumor";NA;442;0
"Building";"CreepTumor";NA;442;0
"Unit";"Overlord";"Larva";456;0
"Building";"Hatchery";NA;392;0
"Unit";"Zergling";"Larva";456;1
"Unit";"Zergling";"Larva";456;1
"Unit";"Zergling";"Larva";456;1
"Unit";"Zergling";"Larva";456;1
"Unit";"Zergling";"Larva";456;1
"Unit";"Zergling";"Larva";456;1
"Unit";"Zergling";"Larva";456;1
"Unit";"Zergling";"Larva";456;1
"Unit";"Zergling";"Larva";456;1
"Unit";"Zergling";"Larva";456;1
"Unit";"Zergling";"Larva";456;1
"Unit";"Zergling";"Larva";456;1
"Unit";"Zergling";"Larva";456;1
"Unit";"Zergling";"Larva";456;1
"Unit";"Zergling";"Larva";456;1
"Unit";"Zergling";"Larva";456;1
"Unit";"Viper";"Larva";456;3
"Unit";"Zergling";"Larva";456;1
"Unit";"Zergling";"Larva";456;1
"Unit";"Viper";"Larva";456;3
"Unit";"Viper";"Larva";456;3
"Unit";"Viper";"Larva";456;3
"Unit";"Ultralisk";"Larva";442;6
"Unit";"Ultralisk";"Larva";442;6
"Unit";"Baneling";"Zergling";456;0
"Unit";"Baneling";"Zergling";456;0
"Unit";"Baneling";"Zergling";456;0
"Unit";"Baneling";"Zergling";456;0
"Unit";"Baneling";"Zergling";456;0
"Unit";"Baneling";"Zergling";456;0
"Unit";"Baneling";"Zergling";456;0
"Unit";"Baneling";"Zergling";456;0
"Unit";"Baneling";"Zergling";456;0
"Unit";"Baneling";"Zergling";456;0
"Unit";"Baneling";"Zergling";456;0
"Unit";"Baneling";"Zergling";456;0
"Unit";"Baneling";"Zergling";456;0
"Unit";"Baneling";"Zergling";456;0
"Unit";"Baneling";"Zergling";456;0
"Unit";"Baneling";"Zergling";456;0
"Unit";"Baneling";"Zergling";456;0
"Building";"CreepTumor";NA;498;0
"Building";"CreepTumor";NA;498;0
"Building";"CreepTumor";NA;498;0
"Building";"CreepTumor";NA;498;0
"Unit";"Zergling";"Larva";498;1
"Unit";"Zergling";"Larva";498;1
"Upgrade";"ChitinousPlating";"UltraliskCavern";456;0
"Unit";"Zergling";"Larva";498;1
"Unit";"Zergling";"Larva";498;1
"Unit";"Zergling";"Larva";498;1
"Unit";"Zergling";"Larva";498;1
"Unit";"Zergling";"Larva";498;1
"Unit";"Zergling";"Larva";498;1
"Unit";"Zergling";"Larva";498;1
"Unit";"Zergling";"Larva";498;1
"Unit";"Zergling";"Larva";498;1
"Unit";"Zergling";"Larva";498;1
"Unit";"Zergling";"Larva";498;1
"Unit";"Zergling";"Larva";498;1
"Unit";"Zergling";"Larva";498;1
"Unit";"Zergling";"Larva";498;1
"Unit";"Zergling";"Larva";498;1
"Unit";"Zergling";"Larva";498;1
"Unit";"Zergling";"Larva";498;1
"Unit";"Zergling";"Larva";498;1
"Upgrade";"ZergGroundArmorsLevel3";"EvolutionChamber";406;0
"Building";"CreepTumor";NA;529;0
"Building";"CreepTumor";NA;529;0
"Building";"CreepTumor";NA;529;0
"Building";"CreepTumor";NA;529;0
"Upgrade";"ZergMeleeWeaponsLevel3";"EvolutionChamber";456;0
"Building";"Extractor";NA;529;0
"Unit";"Ultralisk";"Larva";529;6
"Unit";"Ultralisk";"Larva";529;6
"Unit";"Ultralisk";"Larva";529;6
"Building";"Extractor";NA;529;0
"Unit";"Zergling";"Larva";553;1
"Unit";"Zergling";"Larva";553;1
"Unit";"Ultralisk";"Larva";529;6
"Unit";"Ultralisk";"Larva";529;6
"Unit";"Ultralisk";"Larva";529;6
"Unit";"Zergling";"Larva";553;1
"Unit";"Zergling";"Larva";553;1
"Unit";"Ultralisk";"Larva";529;6
"Unit";"Zergling";"Larva";553;1
"Unit";"Zergling";"Larva";553;1
"Unit";"Zergling";"Larva";553;1
"Unit";"Zergling";"Larva";553;1
"Unit";"Zergling";"Larva";553;1
"Unit";"Zergling";"Larva";553;1
"Unit";"Zergling";"Larva";553;1
"Unit";"Zergling";"Larva";553;1
"Unit";"Zergling";"Larva";553;1
"Unit";"Zergling";"Larva";553;1
"Unit";"Zergling";"Larva";553;1
"Unit";"Zergling";"Larva";553;1
"Unit";"Zergling";"Larva";553;1
"Unit";"Zergling";"Larva";553;1
"Building";"CreepTumor";NA;553;0
"Building";"HydraliskDen";NA;529;0
"Building";"CreepTumor";NA;553;0
"Unit";"Baneling";"Zergling";553;0
"Unit";"Baneling";"Zergling";553;0
"Unit";"Baneling";"Zergling";553;0
"Unit";"Baneling";"Zergling";553;0
"Unit";"Baneling";"Zergling";553;0
"Unit";"Baneling";"Zergling";553;0
"Unit";"Baneling";"Zergling";553;0
"Unit";"Baneling";"Zergling";553;0
"Unit";"Baneling";"Zergling";553;0
"Unit";"Baneling";"Zergling";553;0
"Unit";"Queen";"Hatchery";529;2
"Unit";"Baneling";"Zergling";553;0
"Unit";"Baneling";"Zergling";553;0
"Unit";"Baneling";"Zergling";553;0
"Unit";"Baneling";"Zergling";553;0
"Unit";"Baneling";"Zergling";553;0
"Unit";"Baneling";"Zergling";553;0
"Unit";"Baneling";"Zergling";553;0
"Unit";"Baneling";"Zergling";553;0
"Unit";"Baneling";"Zergling";553;0
"Unit";"Baneling";"Zergling";553;0
"Unit";"Zergling";"Larva";595;1
"Unit";"Zergling";"Larva";595;1
"Unit";"Zergling";"Larva";595;1
"Unit";"Zergling";"Larva";595;1
"Unit";"Zergling";"Larva";595;1
"Unit";"Zergling";"Larva";595;1
"Unit";"Zergling";"Larva";595;1
"Unit";"Zergling";"Larva";595;1
"Unit";"Zergling";"Larva";595;1
"Unit";"Zergling";"Larva";595;1
"Unit";"Zergling";"Larva";595;1
"Unit";"Zergling";"Larva";595;1
"Unit";"Zergling";"Larva";595;1
"Unit";"Zergling";"Larva";595;1
"Unit";"Zergling";"Larva";595;1
"Unit";"Zergling";"Larva";595;1
"Building";"CreepTumor";NA;597;0
"Building";"CreepTumorQueen";NA;597;0
"Building";"CreepTumorQueen";NA;597;0
"Unit";"Baneling";"Zergling";597;0
"Unit";"Baneling";"Zergling";597;0
"Building";"CreepTumorQueen";NA;613;0
"Unit";"Baneling";"Zergling";597;0
"Unit";"Baneling";"Zergling";597;0
"Unit";"Baneling";"Zergling";597;0
"Unit";"Baneling";"Zergling";597;0
"Unit";"Baneling";"Zergling";597;0
"Unit";"Baneling";"Zergling";597;0
"Unit";"Baneling";"Zergling";597;0
"Unit";"Baneling";"Zergling";597;0
"Unit";"Baneling";"Zergling";597;0
"Unit";"Baneling";"Zergling";597;0
"Unit";"Baneling";"Zergling";597;0
"Unit";"Baneling";"Zergling";597;0
"Unit";"Baneling";"Zergling";597;0
"Unit";"Baneling";"Zergling";597;0
"Unit";"Baneling";"Zergling";597;0
"Unit";"Baneling";"Zergling";597;0
"Building";"CreepTumor";NA;613;0
"Building";"CreepTumor";NA;613;0
"Building";"Hatchery";NA;553;0
"Unit";"Hydralisk";"Larva";613;2
"Unit";"Hydralisk";"Larva";613;2
"Unit";"Hydralisk";"Larva";613;2
"Unit";"Hydralisk";"Larva";613;2
"Unit";"Hydralisk";"Larva";613;2
"Unit";"Hydralisk";"Larva";613;2
"Unit";"Hydralisk";"Larva";613;2
"Unit";"Hydralisk";"Larva";613;2
"Unit";"Hydralisk";"Larva";613;2
"Unit";"Hydralisk";"Larva";613;2
"Unit";"Hydralisk";"Larva";613;2
"Unit";"Hydralisk";"Larva";613;2
"Unit";"Hydralisk";"Larva";613;2
"Unit";"Zergling";"Larva";613;1
"Unit";"Zergling";"Larva";613;1
"Unit";"Zergling";"Larva";613;1
"Unit";"Zergling";"Larva";613;1
"Unit";"Zergling";"Larva";613;1
"Unit";"Zergling";"Larva";613;1
"Unit";"Zergling";"Larva";613;1
"Unit";"Zergling";"Larva";613;1
"Unit";"Zergling";"Larva";613;1
"Unit";"Zergling";"Larva";613;1
"Unit";"Zergling";"Larva";613;1
"Unit";"Zergling";"Larva";613;1
"Unit";"Zergling";"Larva";613;1
"Unit";"Zergling";"Larva";613;1
"Unit";"Zergling";"Larva";613;1
"Unit";"Zergling";"Larva";613;1
"Unit";"Zergling";"Larva";613;1
"Unit";"Zergling";"Larva";613;1
"Unit";"Zergling";"Larva";613;1
"Unit";"Zergling";"Larva";613;1
"Unit";"Zergling";"Larva";613;1
"Unit";"Zergling";"Larva";613;1
"Building";"CreepTumor";NA;639;0
"Unit";"Hydralisk";"Larva";613;2
"Unit";"Hydralisk";"Larva";613;2
"Unit";"Hydralisk";"Larva";613;2
"Unit";"Hydralisk";"Larva";613;2
"Unit";"Baneling";"Zergling";661;0
"Unit";"Baneling";"Zergling";661;0
"Unit";"Baneling";"Zergling";661;0
"Unit";"Baneling";"Zergling";661;0
"Unit";"Baneling";"Zergling";661;0
"Unit";"Baneling";"Zergling";661;0
"Unit";"Baneling";"Zergling";661;0
"Unit";"Baneling";"Zergling";661;0
"Building";"CreepTumor";NA;669;0
"Building";"CreepTumor";NA;669;0
"Building";"CreepTumor";NA;669;0
"Building";"CreepTumor";NA;669;0
"Building";"CreepTumor";NA;675;0
"Building";"SpineCrawler";NA;669;0
"Building";"SpineCrawler";NA;669;0
"Building";"SpineCrawler";NA;669;0
"Building";"Hatchery";NA;613;0
"Building";"SpineCrawler";NA;669;0
"Unit";"Hydralisk";"Larva";675;2
"Unit";"Hydralisk";"Larva";675;2
