"type";"unit_name";"on_building";"total_supply";"supply"
"Unit";"Overlord";"Larva";13;0
"Building";"Extractor";NA;18;0
"Building";"SpawningPool";NA;19;0
"Building";"Hatchery";NA;17;0
"Unit";"Overlord";"Larva";23;0
"Unit";"Zergling";"Larva";23;1
"Unit";"Zergling";"Larva";23;1
"Unit";"Zergling";"Larva";23;1
"Unit";"Zergling";"Larva";23;1
"Unit";"Queen";"Hatchery";23;2
"Unit";"Queen";"Hatchery";23;2
"Unit";"Overlord";"Larva";35;0
"Unit";"Overlord";"Larva";39;0
"Unit";"Zergling";"Larva";39;1
"Unit";"Zergling";"Larva";39;1
"Unit";"Zergling";"Larva";39;1
"Unit";"Zergling";"Larva";39;1
"Unit";"Queen";"Hatchery";36;2
"Unit";"Overlord";"Larva";39;0
"Unit";"Zergling";"Larva";39;1
"Unit";"Zergling";"Larva";39;1
"Unit";"Zergling";"Larva";39;1
"Unit";"Zergling";"Larva";39;1
"Unit";"Zergling";"Larva";39;1
"Unit";"Zergling";"Larva";39;1
"Building";"Hatchery";NA;30;0
"Unit";"Zergling";"Larva";48;1
"Unit";"Zergling";"Larva";48;1
"Unit";"Zergling";"Larva";48;1
"Unit";"Zergling";"Larva";48;1
"Building";"CreepTumorQueen";NA;54;0
"Unit";"Zergling";"Larva";54;1
"Unit";"Zergling";"Larva";54;1
"Unit";"Overlord";"Larva";54;0
"Unit";"Zergling";"Larva";54;1
"Unit";"Zergling";"Larva";54;1
"Unit";"Zergling";"Larva";54;1
"Unit";"Zergling";"Larva";54;1
"Unit";"Queen";"Hatchery";54;2
"Unit";"Queen";"Hatchery";54;2
"Building";"CreepTumorQueen";NA;85;0
"Unit";"Zergling";"Larva";77;1
"Unit";"Zergling";"Larva";77;1
"Unit";"Zergling";"Larva";77;1
"Unit";"Zergling";"Larva";77;1
"Unit";"Zergling";"Larva";77;1
"Unit";"Zergling";"Larva";77;1
"Unit";"Zergling";"Larva";77;1
"Unit";"Zergling";"Larva";77;1
"Building";"Extractor";NA;85;0
"Building";"Extractor";NA;85;0
"Unit";"Zergling";"Larva";85;1
"Unit";"Zergling";"Larva";85;1
"Unit";"Zergling";"Larva";85;1
"Unit";"Zergling";"Larva";85;1
"Unit";"Zergling";"Larva";85;1
"Unit";"Zergling";"Larva";85;1
"Building";"CreepTumorQueen";NA;93;0
"Building";"CreepTumorQueen";NA;93;0
"Unit";"Overlord";"Larva";93;0
"Unit";"Overlord";"Larva";93;0
"Building";"SpineCrawler";NA;85;0
"Unit";"Overlord";"Larva";93;0
"Building";"SpineCrawler";NA;85;0
"Building";"CreepTumor";NA;99;0
"Unit";"Overlord";"Larva";99;0
"Building";"EvolutionChamber";NA;99;0
"Building";"EvolutionChamber";NA;99;0
"Unit";"Overlord";"Larva";101;0
"Unit";"Zergling";"Larva";103;1
"Unit";"Zergling";"Larva";103;1
"Unit";"Zergling";"Larva";103;1
"Unit";"Zergling";"Larva";103;1
"Unit";"Zergling";"Larva";103;1
"Unit";"Zergling";"Larva";103;1
"Unit";"Zergling";"Larva";103;1
"Unit";"Zergling";"Larva";103;1
"Unit";"Zergling";"Larva";103;1
"Unit";"Zergling";"Larva";103;1
"Unit";"Zergling";"Larva";103;1
"Unit";"Zergling";"Larva";103;1
"Unit";"Zergling";"Larva";103;1
"Unit";"Zergling";"Larva";103;1
"Building";"CreepTumor";NA;103;0
"Building";"CreepTumor";NA;104;0
"Building";"CreepTumor";NA;118;0
"Building";"CreepTumor";NA;137;0
"Unit";"Overlord";"Larva";137;0
"Building";"Extractor";NA;137;0
"Building";"Extractor";NA;137;0
"Building";"Extractor";NA;137;0
"Building";"CreepTumor";NA;143;0
"Building";"CreepTumorQueen";NA;149;0
"Unit";"Zergling";"Larva";143;1
"Unit";"Zergling";"Larva";143;1
"Unit";"Zergling";"Larva";143;1
"Unit";"Zergling";"Larva";143;1
"Unit";"Zergling";"Larva";143;1
"Unit";"Zergling";"Larva";143;1
"Building";"CreepTumor";NA;149;0
"Building";"BanelingNest";NA;137;0
"Building";"CreepTumor";NA;155;0
"Unit";"Zergling";"Larva";149;1
"Unit";"Zergling";"Larva";149;1
"Unit";"Zergling";"Larva";149;1
"Unit";"Zergling";"Larva";149;1
"Unit";"Zergling";"Larva";149;1
"Unit";"Zergling";"Larva";149;1
"Unit";"Zergling";"Larva";149;1
"Unit";"Zergling";"Larva";149;1
"Unit";"Zergling";"Larva";149;1
"Unit";"Zergling";"Larva";149;1
"Unit";"Zergling";"Larva";149;1
"Unit";"Zergling";"Larva";149;1
"Unit";"Zergling";"Larva";149;1
"Unit";"Zergling";"Larva";149;1
"Unit";"Zergling";"Larva";149;1
"Unit";"Zergling";"Larva";149;1
"Unit";"Zergling";"Larva";149;1
"Unit";"Zergling";"Larva";149;1
"Unit";"Zergling";"Larva";149;1
"Unit";"Zergling";"Larva";149;1
"Unit";"Zergling";"Larva";149;1
"Unit";"Zergling";"Larva";149;1
"Building";"CreepTumorQueen";NA;155;0
"Building";"HydraliskDen";NA;149;0
"Building";"SporeCrawler";NA;149;0
"Building";"SporeCrawler";NA;149;0
"Unit";"Overlord";"Larva";155;0
"Unit";"Overlord";"Larva";155;0
"Unit";"Overlord";"Larva";155;0
"Building";"CreepTumor";NA;177;0
"Building";"CreepTumorQueen";NA;177;0
"Upgrade";"ZergMeleeWeaponsLevel1";"EvolutionChamber";134;0
"Building";"CreepTumor";NA;177;0
"Building";"CreepTumorQueen";NA;178;0
"Building";"CreepTumor";NA;177;0
"Building";"Hatchery";NA;137;0
"Upgrade";"ZergGroundArmorsLevel1";"EvolutionChamber";137;0
"Unit";"Overlord";"Larva";179;0
"Unit";"Queen";"Hatchery";177;2
"Building";"CreepTumor";NA;189;0
"Building";"CreepTumorQueen";NA;191;0
"Building";"CreepTumor";NA;191;0
"Building";"CreepTumor";NA;192;0
"Building";"CreepTumor";NA;204;0
"Building";"InfestationPit";NA;189;0
"Upgrade";"EvolveMuscularAugments";"HydraliskDen";179;0
"Unit";"Hydralisk";"Larva";204;2
"Unit";"Hydralisk";"Larva";204;2
"Unit";"Hydralisk";"Larva";204;2
"Unit";"Hydralisk";"Larva";204;2
"Unit";"Hydralisk";"Larva";204;2
"Unit";"Hydralisk";"Larva";204;2
"Unit";"Hydralisk";"Larva";204;2
"Building";"CreepTumorQueen";NA;204;0
"Building";"Extractor";NA;204;0
"Building";"Extractor";NA;204;0
"Building";"CreepTumor";NA;204;0
"Unit";"Overlord";"Larva";204;0
"Unit";"Overlord";"Larva";204;0
"Unit";"Hydralisk";"Larva";204;2
"Unit";"Hydralisk";"Larva";204;2
"Unit";"Hydralisk";"Larva";204;2
"Unit";"Hydralisk";"Larva";204;2
"Unit";"Hydralisk";"Larva";204;2
"Unit";"Hydralisk";"Larva";204;2
"Unit";"Overlord";"Larva";218;0
"Building";"CreepTumor";NA;218;0
"Building";"CreepTumor";NA;230;0
"Building";"CreepTumor";NA;230;0
"Building";"CreepTumorQueen";NA;230;0
"Unit";"Hydralisk";"Larva";230;2
"Unit";"Hydralisk";"Larva";230;2
"Unit";"Hydralisk";"Larva";230;2
"Unit";"Hydralisk";"Larva";230;2
"Unit";"Hydralisk";"Larva";230;2
"Unit";"Hydralisk";"Larva";230;2
"Unit";"Hydralisk";"Larva";230;2
"Unit";"Hydralisk";"Larva";230;2
"Unit";"Hydralisk";"Larva";230;2
"Unit";"Overlord";"Larva";230;0
"Unit";"Overlord";"Larva";230;0
"Unit";"Overlord";"Larva";230;0
"Building";"CreepTumor";NA;248;0
"Unit";"Overlord";"Larva";230;0
"Building";"SporeCrawler";NA;230;0
"Building";"CreepTumor";NA;248;0
"Building";"SporeCrawler";NA;230;0
"Building";"SporeCrawler";NA;230;0
"Unit";"Zergling";"Larva";248;1
"Unit";"Zergling";"Larva";248;1
"Unit";"Zergling";"Larva";248;1
"Unit";"Zergling";"Larva";248;1
"Unit";"Zergling";"Larva";248;1
"Unit";"Zergling";"Larva";248;1
"Unit";"Zergling";"Larva";248;1
"Unit";"Zergling";"Larva";248;1
"Unit";"Zergling";"Larva";248;1
"Unit";"Zergling";"Larva";248;1
"Unit";"Zergling";"Larva";248;1
"Unit";"Zergling";"Larva";248;1
"Unit";"Zergling";"Larva";248;1
"Unit";"Zergling";"Larva";248;1
"Unit";"Zergling";"Larva";248;1
"Unit";"Zergling";"Larva";248;1
"Unit";"Zergling";"Larva";248;1
"Unit";"Zergling";"Larva";248;1
"Unit";"Zergling";"Larva";248;1
"Unit";"Zergling";"Larva";248;1
"Unit";"Zergling";"Larva";248;1
"Unit";"Zergling";"Larva";248;1
"Unit";"Zergling";"Larva";248;1
"Unit";"Zergling";"Larva";248;1
"Unit";"Zergling";"Larva";248;1
"Unit";"Zergling";"Larva";248;1
"Upgrade";"ZergMeleeWeaponsLevel2";"EvolutionChamber";204;0
"Building";"SporeCrawler";NA;248;0
"Upgrade";"ZergGroundArmorsLevel2";"EvolutionChamber";204;0
"Unit";"Zergling";"Larva";274;1
"Unit";"Zergling";"Larva";274;1
"Unit";"Zergling";"Larva";274;1
"Unit";"Zergling";"Larva";274;1
"Unit";"Zergling";"Larva";274;1
"Unit";"Zergling";"Larva";274;1
"Unit";"Zergling";"Larva";274;1
"Unit";"Zergling";"Larva";274;1
"Unit";"Zergling";"Larva";274;1
"Unit";"Zergling";"Larva";274;1
"Unit";"Zergling";"Larva";274;1
"Unit";"Zergling";"Larva";274;1
"Unit";"Zergling";"Larva";274;1
"Unit";"Zergling";"Larva";274;1
"Unit";"Zergling";"Larva";274;1
"Unit";"Zergling";"Larva";274;1
"Unit";"Zergling";"Larva";274;1
"Unit";"Zergling";"Larva";274;1
"Unit";"Zergling";"Larva";274;1
"Unit";"Zergling";"Larva";274;1
"Unit";"Zergling";"Larva";274;1
"Unit";"Zergling";"Larva";274;1
"Unit";"Zergling";"Larva";274;1
"Unit";"Zergling";"Larva";274;1
"Building";"SpineCrawler";NA;248;0
"Building";"SpineCrawler";NA;248;0
"Building";"SpineCrawler";NA;248;0
"Upgrade";"EvolveGroovedSpines";"HydraliskDen";248;0
"Unit";"Zergling";"Larva";300;1
"Unit";"Zergling";"Larva";300;1
"Unit";"Zergling";"Larva";300;1
"Unit";"Zergling";"Larva";300;1
"Unit";"Zergling";"Larva";300;1
"Unit";"Zergling";"Larva";300;1
"Unit";"Zergling";"Larva";300;1
"Unit";"Zergling";"Larva";300;1
"Unit";"Zergling";"Larva";300;1
"Unit";"Zergling";"Larva";300;1
"Building";"SpineCrawler";NA;274;0
"Building";"Extractor";NA;311;0
"Unit";"Zergling";"Larva";321;1
"Unit";"Zergling";"Larva";321;1
"Unit";"Zergling";"Larva";321;1
"Unit";"Zergling";"Larva";321;1
"Unit";"Zergling";"Larva";321;1
"Unit";"Zergling";"Larva";321;1
"Unit";"Zergling";"Larva";321;1
"Unit";"Zergling";"Larva";321;1
"Unit";"Zergling";"Larva";321;1
"Unit";"Zergling";"Larva";321;1
"Unit";"Zergling";"Larva";321;1
"Unit";"Zergling";"Larva";321;1
"Unit";"Zergling";"Larva";321;1
"Unit";"Zergling";"Larva";321;1
"Unit";"Zergling";"Larva";321;1
"Unit";"Zergling";"Larva";321;1
"Unit";"Zergling";"Larva";321;1
"Unit";"Zergling";"Larva";321;1
"Unit";"Zergling";"Larva";321;1
"Unit";"Zergling";"Larva";321;1
"Building";"CreepTumor";NA;321;0
"Unit";"Baneling";"Zergling";341;0
"Unit";"Baneling";"Zergling";341;0
"Unit";"Baneling";"Zergling";341;0
"Unit";"Baneling";"Zergling";341;0
"Unit";"Baneling";"Zergling";341;0
"Unit";"Baneling";"Zergling";341;0
"Unit";"Baneling";"Zergling";341;0
"Unit";"Baneling";"Zergling";341;0
"Unit";"Baneling";"Zergling";341;0
"Unit";"Baneling";"Zergling";341;0
"Unit";"Baneling";"Zergling";341;0
"Unit";"Baneling";"Zergling";341;0
"Unit";"Baneling";"Zergling";341;0
"Unit";"Baneling";"Zergling";341;0
"Unit";"Baneling";"Zergling";341;0
"Building";"CreepTumor";NA;341;0
"Unit";"Baneling";"Zergling";341;0
"Unit";"Baneling";"Zergling";341;0
"Unit";"Baneling";"Zergling";341;0
"Unit";"Baneling";"Zergling";341;0
"Unit";"Baneling";"Zergling";341;0
"Unit";"Baneling";"Zergling";341;0
"Unit";"Baneling";"Zergling";341;0
"Unit";"Baneling";"Zergling";341;0
"Building";"SpineCrawler";NA;317;0
"Unit";"Baneling";"Zergling";341;0
"Unit";"Baneling";"Zergling";341;0
"Unit";"Baneling";"Zergling";341;0
"Unit";"Baneling";"Zergling";341;0
"Unit";"Baneling";"Zergling";341;0
"Unit";"Baneling";"Zergling";341;0
"Unit";"Baneling";"Zergling";341;0
"Unit";"Baneling";"Zergling";341;0
"Unit";"Baneling";"Zergling";341;0
"Unit";"Baneling";"Zergling";341;0
"Unit";"Baneling";"Zergling";341;0
"Unit";"Baneling";"Zergling";341;0
"Unit";"Baneling";"Zergling";341;0
"Unit";"Baneling";"Zergling";341;0
"Unit";"Baneling";"Zergling";341;0
"Unit";"Baneling";"Zergling";341;0
"Unit";"Baneling";"Zergling";341;0
"Unit";"Baneling";"Zergling";341;0
"Unit";"Baneling";"Zergling";341;0
"Building";"CreepTumor";NA;341;0
"Unit";"Baneling";"Zergling";341;0
"Unit";"Baneling";"Zergling";341;0
"Unit";"Baneling";"Zergling";341;0
"Unit";"Baneling";"Zergling";341;0
"Unit";"Baneling";"Zergling";341;0
"Unit";"Baneling";"Zergling";341;0
"Unit";"Baneling";"Zergling";341;0
"Unit";"Baneling";"Zergling";341;0
"Unit";"Baneling";"Zergling";341;0
"Building";"UltraliskCavern";NA;311;0
"Unit";"Zergling";"Larva";342;1
"Unit";"Zergling";"Larva";342;1
"Unit";"Zergling";"Larva";342;1
"Unit";"Zergling";"Larva";342;1
"Unit";"Zergling";"Larva";342;1
"Unit";"Zergling";"Larva";342;1
"Unit";"Zergling";"Larva";342;1
"Unit";"Zergling";"Larva";342;1
"Unit";"Zergling";"Larva";349;1
"Unit";"Zergling";"Larva";349;1
"Unit";"Zergling";"Larva";349;1
"Unit";"Zergling";"Larva";349;1
"Unit";"Zergling";"Larva";349;1
"Unit";"Zergling";"Larva";349;1
"Unit";"Zergling";"Larva";349;1
"Unit";"Zergling";"Larva";349;1
"Building";"Hatchery";NA;311;0
"Building";"Hatchery";NA;321;0
"Unit";"Hydralisk";"Larva";365;2
"Unit";"Hydralisk";"Larva";365;2
"Unit";"Hydralisk";"Larva";365;2
"Unit";"Hydralisk";"Larva";365;2
"Unit";"Hydralisk";"Larva";365;2
"Unit";"Hydralisk";"Larva";365;2
"Unit";"Hydralisk";"Larva";365;2
"Unit";"Hydralisk";"Larva";365;2
"Unit";"Hydralisk";"Larva";365;2
"Unit";"Hydralisk";"Larva";365;2
"Unit";"Hydralisk";"Larva";365;2
"Unit";"Hydralisk";"Larva";365;2
"Unit";"Hydralisk";"Larva";365;2
"Unit";"Hydralisk";"Larva";365;2
"Unit";"Zergling";"Larva";365;1
"Unit";"Zergling";"Larva";365;1
"Unit";"Zergling";"Larva";365;1
"Unit";"Zergling";"Larva";365;1
"Unit";"Hydralisk";"Larva";365;2
"Unit";"Hydralisk";"Larva";365;2
"Unit";"Hydralisk";"Larva";365;2
"Unit";"Hydralisk";"Larva";365;2
"Unit";"Hydralisk";"Larva";365;2
"Unit";"Hydralisk";"Larva";365;2
"Unit";"Hydralisk";"Larva";365;2
"Building";"CreepTumor";NA;393;0
"Unit";"Zergling";"Larva";373;1
"Unit";"Zergling";"Larva";373;1
"Unit";"Zergling";"Larva";387;1
"Unit";"Zergling";"Larva";387;1
"Unit";"Zergling";"Larva";387;1
"Unit";"Zergling";"Larva";387;1
"Unit";"Zergling";"Larva";391;1
"Unit";"Zergling";"Larva";391;1
"Unit";"Viper";"Larva";365;3
"Unit";"Viper";"Larva";365;3
"Unit";"Viper";"Larva";365;3
"Unit";"Viper";"Larva";365;3
"Unit";"Viper";"Larva";365;3
"Unit";"Zergling";"Larva";411;1
"Unit";"Zergling";"Larva";411;1
"Unit";"Zergling";"Larva";411;1
"Unit";"Zergling";"Larva";411;1
"Unit";"Zergling";"Larva";411;1
"Unit";"Zergling";"Larva";411;1
"Unit";"Zergling";"Larva";411;1
"Unit";"Zergling";"Larva";411;1
"Unit";"Zergling";"Larva";411;1
"Unit";"Zergling";"Larva";411;1
"Unit";"Baneling";"Zergling";411;0
"Unit";"Baneling";"Zergling";411;0
"Unit";"Baneling";"Zergling";411;0
"Building";"CreepTumor";NA;419;0
"Building";"CreepTumorQueen";NA;434;0
"Unit";"Zergling";"Larva";419;1
"Unit";"Zergling";"Larva";419;1
"Unit";"Zergling";"Larva";419;1
"Unit";"Zergling";"Larva";419;1
"Unit";"Zergling";"Larva";419;1
"Unit";"Zergling";"Larva";419;1
"Unit";"Zergling";"Larva";419;1
"Unit";"Zergling";"Larva";419;1
"Unit";"Zergling";"Larva";419;1
"Unit";"Zergling";"Larva";419;1
"Unit";"Zergling";"Larva";419;1
"Unit";"Zergling";"Larva";419;1
"Unit";"Zergling";"Larva";419;1
"Unit";"Zergling";"Larva";419;1
"Building";"CreepTumorQueen";NA;444;0
"Upgrade";"ChitinousPlating";"UltraliskCavern";365;0
"Upgrade";"ZergMeleeWeaponsLevel3";"EvolutionChamber";341;0
"Upgrade";"ZergGroundArmorsLevel3";"EvolutionChamber";341;0
"Building";"CreepTumor";NA;444;0
"Unit";"Zergling";"Larva";458;1
"Unit";"Zergling";"Larva";458;1
"Unit";"Zergling";"Larva";458;1
"Unit";"Zergling";"Larva";458;1
"Unit";"Zergling";"Larva";458;1
"Unit";"Zergling";"Larva";458;1
"Unit";"Zergling";"Larva";458;1
"Unit";"Zergling";"Larva";458;1
"Unit";"Zergling";"Larva";458;1
"Unit";"Zergling";"Larva";458;1
"Unit";"Zergling";"Larva";458;1
"Unit";"Zergling";"Larva";458;1
"Unit";"Zergling";"Larva";458;1
"Unit";"Zergling";"Larva";458;1
"Unit";"Zergling";"Larva";458;1
"Unit";"Zergling";"Larva";458;1
"Unit";"Zergling";"Larva";458;1
"Unit";"Zergling";"Larva";458;1
"Unit";"Zergling";"Larva";458;1
"Unit";"Zergling";"Larva";458;1
"Unit";"Overlord";"Larva";458;0
"Unit";"Zergling";"Larva";458;1
"Unit";"Zergling";"Larva";458;1
"Unit";"Baneling";"Zergling";458;0
"Unit";"Baneling";"Zergling";458;0
"Unit";"Baneling";"Zergling";458;0
"Unit";"Baneling";"Zergling";458;0
"Unit";"Baneling";"Zergling";458;0
"Unit";"Baneling";"Zergling";458;0
"Unit";"Baneling";"Zergling";458;0
"Unit";"Baneling";"Zergling";458;0
"Unit";"Baneling";"Zergling";458;0
"Unit";"Baneling";"Zergling";458;0
"Unit";"Baneling";"Zergling";458;0
"Unit";"Baneling";"Zergling";458;0
"Unit";"Baneling";"Zergling";458;0
"Unit";"Baneling";"Zergling";458;0
"Unit";"Baneling";"Zergling";458;0
"Unit";"Baneling";"Zergling";458;0
"Unit";"Baneling";"Zergling";458;0
"Unit";"Baneling";"Zergling";458;0
"Unit";"Baneling";"Zergling";458;0
"Unit";"Baneling";"Zergling";458;0
"Unit";"Baneling";"Zergling";458;0
"Unit";"Baneling";"Zergling";458;0
"Unit";"Baneling";"Zergling";458;0
"Unit";"Baneling";"Zergling";458;0
"Unit";"Baneling";"Zergling";458;0
"Unit";"Baneling";"Zergling";458;0
"Unit";"Overlord";"Larva";458;0
"Building";"CreepTumor";NA;478;0
"Building";"Hatchery";NA;393;0
"Building";"CreepTumorQueen";NA;478;0
"Unit";"Queen";"Hatchery";458;2
"Unit";"Zergling";"Larva";480;1
"Unit";"Zergling";"Larva";480;1
"Unit";"Zergling";"Larva";480;1
"Unit";"Zergling";"Larva";480;1
"Unit";"Zergling";"Larva";480;1
"Unit";"Zergling";"Larva";480;1
"Unit";"Zergling";"Larva";480;1
"Unit";"Zergling";"Larva";480;1
"Unit";"Zergling";"Larva";480;1
"Unit";"Zergling";"Larva";480;1
"Unit";"Zergling";"Larva";480;1
"Unit";"Zergling";"Larva";480;1
"Unit";"Zergling";"Larva";480;1
"Unit";"Zergling";"Larva";480;1
"Unit";"Zergling";"Larva";480;1
"Unit";"Zergling";"Larva";480;1
"Unit";"Zergling";"Larva";480;1
"Unit";"Zergling";"Larva";480;1
"Unit";"Queen";"Hatchery";478;2
"Unit";"Zergling";"Larva";480;1
"Unit";"Zergling";"Larva";480;1
"Unit";"Zergling";"Larva";480;1
"Unit";"Zergling";"Larva";480;1
"Unit";"Zergling";"Larva";480;1
"Unit";"Zergling";"Larva";480;1
"Unit";"Zergling";"Larva";480;1
"Unit";"Zergling";"Larva";480;1
"Unit";"Zergling";"Larva";480;1
"Unit";"Zergling";"Larva";480;1
"Unit";"Zergling";"Larva";480;1
"Unit";"Zergling";"Larva";480;1
"Unit";"Zergling";"Larva";512;1
"Unit";"Zergling";"Larva";512;1
"Unit";"Zergling";"Larva";514;1
"Unit";"Zergling";"Larva";514;1
"Unit";"Zergling";"Larva";514;1
"Unit";"Zergling";"Larva";514;1
"Unit";"Zergling";"Larva";514;1
"Unit";"Zergling";"Larva";514;1
"Unit";"Zergling";"Larva";514;1
"Unit";"Zergling";"Larva";514;1
"Unit";"Zergling";"Larva";514;1
"Unit";"Zergling";"Larva";514;1
"Unit";"Zergling";"Larva";514;1
"Unit";"Zergling";"Larva";514;1
"Unit";"Zergling";"Larva";514;1
"Unit";"Zergling";"Larva";514;1
"Unit";"Zergling";"Larva";514;1
"Unit";"Zergling";"Larva";514;1
"Unit";"Zergling";"Larva";514;1
"Unit";"Zergling";"Larva";514;1
"Unit";"Zergling";"Larva";514;1
"Unit";"Zergling";"Larva";514;1
"Unit";"Zergling";"Larva";514;1
"Unit";"Zergling";"Larva";514;1
"Unit";"Zergling";"Larva";514;1
"Unit";"Zergling";"Larva";514;1
"Unit";"Zergling";"Larva";540;1
"Unit";"Zergling";"Larva";540;1
"Unit";"Zergling";"Larva";540;1
"Unit";"Zergling";"Larva";540;1
"Unit";"Zergling";"Larva";540;1
"Unit";"Zergling";"Larva";540;1
"Unit";"Zergling";"Larva";540;1
"Unit";"Zergling";"Larva";540;1
"Unit";"Zergling";"Larva";540;1
"Unit";"Zergling";"Larva";540;1
"Unit";"Zergling";"Larva";540;1
"Unit";"Zergling";"Larva";540;1
"Unit";"Zergling";"Larva";540;1
"Unit";"Zergling";"Larva";540;1
"Unit";"Ultralisk";"Larva";532;6
"Unit";"Ultralisk";"Larva";532;6
"Unit";"Ultralisk";"Larva";532;6
"Unit";"Ultralisk";"Larva";532;6
"Building";"Extractor";NA;540;0
"Building";"Extractor";NA;540;0
"Unit";"Zergling";"Larva";554;1
"Unit";"Zergling";"Larva";554;1
"Unit";"Zergling";"Larva";554;1
"Unit";"Zergling";"Larva";554;1
"Unit";"Zergling";"Larva";554;1
"Unit";"Zergling";"Larva";554;1
"Unit";"Zergling";"Larva";554;1
"Unit";"Zergling";"Larva";554;1
"Unit";"Zergling";"Larva";578;1
"Unit";"Zergling";"Larva";578;1
"Unit";"Zergling";"Larva";578;1
"Unit";"Zergling";"Larva";578;1
"Unit";"Zergling";"Larva";578;1
"Unit";"Zergling";"Larva";578;1
"Unit";"Zergling";"Larva";578;1
"Unit";"Zergling";"Larva";578;1
"Unit";"Zergling";"Larva";578;1
"Unit";"Zergling";"Larva";578;1
"Unit";"Zergling";"Larva";578;1
"Unit";"Zergling";"Larva";578;1
"Unit";"Zergling";"Larva";578;1
"Unit";"Zergling";"Larva";578;1
"Unit";"Ultralisk";"Larva";540;6
"Unit";"Ultralisk";"Larva";540;6
"Unit";"Ultralisk";"Larva";540;6
"Unit";"Ultralisk";"Larva";540;6
"Unit";"Ultralisk";"Larva";540;6
"Unit";"Ultralisk";"Larva";540;6
"Unit";"Zergling";"Larva";636;1
"Unit";"Zergling";"Larva";636;1
"Unit";"Zergling";"Larva";636;1
"Unit";"Zergling";"Larva";636;1
"Unit";"Zergling";"Larva";636;1
"Unit";"Zergling";"Larva";636;1
"Unit";"Zergling";"Larva";636;1
"Unit";"Zergling";"Larva";636;1
"Unit";"Zergling";"Larva";636;1
"Unit";"Zergling";"Larva";636;1
"Unit";"Zergling";"Larva";636;1
"Unit";"Zergling";"Larva";636;1
"Unit";"Zergling";"Larva";636;1
"Unit";"Zergling";"Larva";636;1
"Unit";"Zergling";"Larva";636;1
"Unit";"Zergling";"Larva";636;1
"Unit";"Zergling";"Larva";636;1
"Unit";"Zergling";"Larva";636;1
"Unit";"Zergling";"Larva";636;1
"Unit";"Zergling";"Larva";636;1
"Unit";"Zergling";"Larva";636;1
"Unit";"Zergling";"Larva";636;1
"Unit";"Zergling";"Larva";636;1
"Unit";"Zergling";"Larva";636;1
"Unit";"Zergling";"Larva";636;1
"Unit";"Zergling";"Larva";636;1
"Unit";"Hydralisk";"Larva";636;2
"Unit";"Hydralisk";"Larva";636;2
"Unit";"Hydralisk";"Larva";636;2
"Unit";"Hydralisk";"Larva";636;2
"Building";"Hatchery";NA;586;0
"Unit";"Zergling";"Larva";670;1
"Unit";"Zergling";"Larva";670;1
"Unit";"Zergling";"Larva";670;1
"Unit";"Zergling";"Larva";670;1
"Unit";"Zergling";"Larva";670;1
"Unit";"Zergling";"Larva";670;1
"Unit";"Zergling";"Larva";670;1
"Unit";"Zergling";"Larva";670;1
"Unit";"Zergling";"Larva";670;1
"Unit";"Zergling";"Larva";670;1
"Unit";"Zergling";"Larva";670;1
"Unit";"Zergling";"Larva";670;1
"Unit";"Zergling";"Larva";670;1
"Unit";"Zergling";"Larva";670;1
"Unit";"Zergling";"Larva";670;1
"Unit";"Zergling";"Larva";670;1
"Unit";"Zergling";"Larva";670;1
"Unit";"Zergling";"Larva";670;1
"Unit";"Zergling";"Larva";670;1
"Unit";"Zergling";"Larva";670;1
"Building";"Hatchery";NA;636;0
"Unit";"Zergling";"Larva";690;1
"Unit";"Zergling";"Larva";690;1
"Unit";"Zergling";"Larva";690;1
"Unit";"Zergling";"Larva";690;1
"Unit";"Zergling";"Larva";690;1
"Unit";"Zergling";"Larva";690;1
"Unit";"Zergling";"Larva";690;1
"Unit";"Zergling";"Larva";690;1
"Unit";"Zergling";"Larva";690;1
"Unit";"Zergling";"Larva";690;1
"Unit";"Zergling";"Larva";690;1
"Unit";"Zergling";"Larva";690;1
"Unit";"Zergling";"Larva";690;1
"Unit";"Zergling";"Larva";690;1
"Unit";"Zergling";"Larva";690;1
"Unit";"Zergling";"Larva";690;1
"Unit";"Zergling";"Larva";690;1
"Unit";"Zergling";"Larva";690;1
"Unit";"Hydralisk";"Larva";690;2
"Unit";"Hydralisk";"Larva";690;2
"Unit";"Hydralisk";"Larva";690;2
"Unit";"Hydralisk";"Larva";690;2
"Unit";"Hydralisk";"Larva";690;2
"Unit";"Hydralisk";"Larva";690;2
"Unit";"Hydralisk";"Larva";690;2
"Unit";"Hydralisk";"Larva";690;2
"Unit";"Zergling";"Larva";708;1
"Unit";"Zergling";"Larva";708;1
"Unit";"Zergling";"Larva";708;1
"Unit";"Zergling";"Larva";708;1
"Unit";"Zergling";"Larva";708;1
"Unit";"Zergling";"Larva";708;1
"Unit";"Zergling";"Larva";708;1
"Unit";"Zergling";"Larva";708;1
"Unit";"Zergling";"Larva";708;1
"Unit";"Zergling";"Larva";708;1
"Unit";"Zergling";"Larva";708;1
"Unit";"Zergling";"Larva";708;1
"Unit";"Zergling";"Larva";708;1
"Unit";"Zergling";"Larva";708;1
"Unit";"Zergling";"Larva";708;1
"Unit";"Zergling";"Larva";708;1
"Unit";"Zergling";"Larva";708;1
"Unit";"Zergling";"Larva";708;1
"Unit";"Zergling";"Larva";708;1
"Unit";"Zergling";"Larva";708;1
"Unit";"Zergling";"Larva";708;1
"Unit";"Zergling";"Larva";708;1
"Unit";"Zergling";"Larva";708;1
"Unit";"Zergling";"Larva";708;1
