"type";"unit_name";"on_building";"total_supply_lag";"supply"
"Unit";"Overlord";"Larva";13;0
"Building";"SpawningPool";NA;17;0
"Building";"Hatchery";NA;18;0
"Building";"Extractor";NA;21;0
"Unit";"Queen";"Hatchery";21;2
"Unit";"Zergling";"Larva";23;1
"Unit";"Zergling";"Larva";24;1
"Unit";"Overlord";"Larva";25;0
"Unit";"Queen";"Hatchery";27;2
"Unit";"Queen";"Hatchery";30;2
"Unit";"Overlord";"Larva";36;0
"Building";"CreepTumorQueen";NA;42;0
"Unit";"Zergling";"Larva";42;1
"Unit";"Zergling";"Larva";43;1
"Unit";"Zergling";"Larva";44;1
"Unit";"Zergling";"Larva";45;1
"Unit";"Zergling";"Larva";46;1
"Unit";"Zergling";"Larva";47;1
"Unit";"Overlord";"Larva";48;0
"Unit";"Overlord";"Larva";51;0
"Building";"CreepTumor";NA;51;0
"Building";"CreepTumorQueen";NA;52;0
"Unit";"Overlord";"Larva";52;0
"Unit";"Queen";"Hatchery";54;2
"Unit";"Queen";"Hatchery";56;2
"Building";"Hatchery";NA;58;0
"Building";"CreepTumor";NA;67;0
"Building";"CreepTumor";NA;67;0
"Unit";"Zergling";"Larva";68;1
"Unit";"Zergling";"Larva";69;1
"Unit";"Overlord";"Larva";70;0
"Unit";"Queen";"Hatchery";70;2
"Unit";"Queen";"Hatchery";72;2
"Building";"CreepTumorQueen";NA;74;0
"Building";"Extractor";NA;74;0
"Building";"EvolutionChamber";NA;76;0
"Building";"EvolutionChamber";NA;76;0
"Unit";"Zergling";"Larva";76;1
"Unit";"Zergling";"Larva";77;1
"Unit";"Zergling";"Larva";78;1
"Unit";"Zergling";"Larva";79;1
"Unit";"Zergling";"Larva";80;1
"Unit";"Zergling";"Larva";81;1
"Unit";"Zergling";"Larva";82;1
"Unit";"Zergling";"Larva";83;1
"Unit";"Zergling";"Larva";84;1
"Unit";"Zergling";"Larva";85;1
"Unit";"Zergling";"Larva";86;1
"Unit";"Zergling";"Larva";87;1
"Building";"CreepTumorQueen";NA;88;0
"Unit";"Zergling";"Larva";88;1
"Unit";"Zergling";"Larva";89;1
"Unit";"Overlord";"Larva";90;0
"Building";"CreepTumor";NA;90;0
"Building";"CreepTumor";NA;90;0
"Unit";"Zergling";"Larva";90;1
"Unit";"Zergling";"Larva";91;1
"Building";"CreepTumorQueen";NA;92;0
"Building";"CreepTumor";NA;92;0
"Building";"CreepTumor";NA;103;0
"Building";"CreepTumor";NA;103;0
"Building";"CreepTumorQueen";NA;105;0
"Building";"CreepTumorQueen";NA;105;0
"Building";"CreepTumorQueen";NA;105;0
"Building";"CreepTumorQueen";NA;106;0
"Building";"CreepTumor";NA;106;0
"Building";"Extractor";NA;109;0
"Building";"Extractor";NA;109;0
"Building";"BanelingNest";NA;109;0
"Building";"Extractor";NA;114;0
"Building";"Extractor";NA;115;0
"Building";"CreepTumor";NA;115;0
"Unit";"Overlord";"Larva";115;0
"Building";"SporeCrawler";NA;116;0
"Building";"SporeCrawler";NA;117;0
"Building";"SporeCrawler";NA;117;0
"Building";"CreepTumor";NA;119;0
"Building";"CreepTumor";NA;119;0
"Building";"CreepTumor";NA;119;0
"Building";"CreepTumor";NA;119;0
"Unit";"Overlord";"Larva";119;0
"Building";"CreepTumorQueen";NA;119;0
"Building";"CreepTumor";NA;123;0
"Building";"InfestationPit";NA;124;0
"Building";"CreepTumorQueen";NA;124;0
"Building";"CreepTumorQueen";NA;124;0
"Building";"CreepTumor";NA;124;0
"Building";"CreepTumor";NA;124;0
"Building";"CreepTumor";NA;124;0
"Unit";"Zergling";"Larva";124;1
"Unit";"Zergling";"Larva";125;1
"Unit";"Zergling";"Larva";126;1
"Unit";"Zergling";"Larva";127;1
"Unit";"Zergling";"Larva";128;1
"Unit";"Zergling";"Larva";129;1
"Unit";"Zergling";"Larva";130;1
"Unit";"Zergling";"Larva";131;1
"Unit";"Zergling";"Larva";132;1
"Unit";"Zergling";"Larva";133;1
"Building";"CreepTumor";NA;134;0
"Building";"CreepTumorQueen";NA;134;0
"Building";"Hatchery";NA;134;0
"Unit";"Overlord";"Larva";134;0
"Building";"CreepTumor";NA;134;0
"Building";"CreepTumor";NA;134;0
"Unit";"Overlord";"Larva";134;0
"Building";"HydraliskDen";NA;134;0
"Building";"CreepTumor";NA;134;0
"Building";"CreepTumor";NA;134;0
"Building";"CreepTumor";NA;134;0
"Unit";"Overlord";"Larva";135;0
"Unit";"Overlord";"Larva";137;0
"Unit";"Overlord";"Larva";137;0
"Unit";"Overlord";"Larva";137;0
"Building";"Spire";NA;139;0
"Unit";"Queen";"Hatchery";139;2
"Unit";"Queen";"Hatchery";141;2
"Building";"CreepTumorQueen";NA;143;0
"Building";"CreepTumor";NA;150;0
"Building";"CreepTumor";NA;150;0
"Building";"CreepTumor";NA;150;0
"Unit";"Hydralisk";"Larva";150;2
"Unit";"Hydralisk";"Larva";152;2
"Unit";"Hydralisk";"Larva";154;2
"Unit";"Hydralisk";"Larva";156;2
"Building";"CreepTumor";NA;158;0
"Building";"CreepTumor";NA;158;0
"Building";"CreepTumor";NA;158;0
"Unit";"Hydralisk";"Larva";158;2
"Unit";"Hydralisk";"Larva";160;2
"Unit";"Hydralisk";"Larva";162;2
"Unit";"Hydralisk";"Larva";164;2
"Unit";"Hydralisk";"Larva";166;2
"Unit";"Hydralisk";"Larva";171;2
"Unit";"Hydralisk";"Larva";173;2
"Building";"CreepTumor";NA;175;0
"Building";"SporeCrawler";NA;175;0
"Building";"CreepTumorQueen";NA;175;0
"Building";"CreepTumorQueen";NA;175;0
"Building";"Extractor";NA;175;0
"Unit";"Hydralisk";"Larva";175;2
"Unit";"Hydralisk";"Larva";177;2
"Unit";"Hydralisk";"Larva";179;2
"Building";"Extractor";NA;181;0
"Building";"CreepTumor";NA;181;0
"Building";"CreepTumor";NA;181;0
"Building";"CreepTumor";NA;181;0
"Building";"CreepTumor";NA;181;0
"Building";"CreepTumor";NA;181;0
"Unit";"Hydralisk";"Larva";181;2
"Unit";"Hydralisk";"Larva";183;2
"Unit";"Hydralisk";"Larva";185;2
"Unit";"Hydralisk";"Larva";187;2
"Building";"CreepTumorQueen";NA;189;0
"Building";"CreepTumorQueen";NA;189;0
"Building";"CreepTumorQueen";NA;189;0
"Unit";"Hydralisk";"Larva";189;2
"Unit";"Hydralisk";"Larva";191;2
"Unit";"Hydralisk";"Larva";193;2
"Unit";"Overlord";"Larva";195;0
"Building";"CreepTumor";NA;195;0
"Building";"CreepTumor";NA;195;0
"Building";"CreepTumor";NA;195;0
"Unit";"Hydralisk";"Larva";195;2
"Unit";"Hydralisk";"Larva";197;2
"Unit";"Hydralisk";"Larva";199;2
"Unit";"Hydralisk";"Larva";201;2
"Building";"CreepTumor";NA;203;0
"Building";"CreepTumor";NA;203;0
"Building";"CreepTumor";NA;203;0
"Unit";"Overlord";"Larva";203;0
"Unit";"Overlord";"Larva";203;0
"Unit";"Overlord";"Larva";203;0
"Building";"CreepTumor";NA;203;0
"Building";"CreepTumor";NA;203;0
"Building";"CreepTumor";NA;203;0
"Building";"CreepTumor";NA;203;0
"Building";"CreepTumor";NA;203;0
"Unit";"Overlord";"Larva";203;0
"Building";"CreepTumor";NA;203;0
"Unit";"Overlord";"Larva";203;0
"Unit";"Corruptor";"Larva";203;2
"Unit";"Corruptor";"Larva";205;2
"Unit";"Corruptor";"Larva";207;2
"Unit";"Corruptor";"Larva";209;2
"Building";"CreepTumor";NA;211;0
"Unit";"Corruptor";"Larva";211;2
"Building";"CreepTumor";NA;213;0
"Building";"CreepTumor";NA;213;0
"Building";"CreepTumor";NA;213;0
"Unit";"Corruptor";"Larva";213;2
"Unit";"Corruptor";"Larva";215;2
"Building";"CreepTumor";NA;217;0
"Building";"CreepTumor";NA;217;0
"Building";"CreepTumor";NA;217;0
"Building";"CreepTumor";NA;217;0
"Building";"CreepTumor";NA;217;0
"Building";"Hatchery";NA;217;0
"Unit";"Zergling";"Larva";217;1
"Unit";"Zergling";"Larva";218;1
"Unit";"Zergling";"Larva";219;1
"Unit";"Zergling";"Larva";220;1
"Unit";"Zergling";"Larva";221;1
"Unit";"Zergling";"Larva";222;1
"Unit";"Zergling";"Larva";223;1
"Unit";"Zergling";"Larva";224;1
"Unit";"Zergling";"Larva";225;1
"Unit";"Zergling";"Larva";226;1
"Unit";"Zergling";"Larva";227;1
"Unit";"Zergling";"Larva";228;1
"Unit";"Zergling";"Larva";229;1
"Unit";"Zergling";"Larva";230;1
"Unit";"Zergling";"Larva";231;1
"Unit";"Zergling";"Larva";232;1
"Unit";"Zergling";"Larva";233;1
"Unit";"Zergling";"Larva";234;1
"Unit";"Zergling";"Larva";235;1
"Unit";"Zergling";"Larva";236;1
"Unit";"Zergling";"Larva";237;1
"Unit";"Zergling";"Larva";238;1
"Unit";"Queen";"Hatchery";239;2
"Unit";"Queen";"Hatchery";241;2
"Unit";"Queen";"Hatchery";243;2
"Building";"CreepTumor";NA;245;0
"Building";"CreepTumor";NA;245;0
"Building";"CreepTumorQueen";NA;245;0
"Building";"CreepTumorQueen";NA;245;0
"Building";"CreepTumorQueen";NA;245;0
"Building";"CreepTumorQueen";NA;245;0
"Building";"CreepTumorQueen";NA;245;0
"Upgrade";"SprayZerg";NA;245;0
"Upgrade";"SprayZerg";NA;245;0
"Upgrade";"zerglingmovementspeed";NA;245;0
"Upgrade";"SprayZerg";NA;245;0
"Upgrade";"SprayZerg";NA;245;0
"Upgrade";"SprayZerg";NA;245;0
"Upgrade";"ZergGroundArmorsLevel1";NA;245;0
"Upgrade";"ZergMeleeWeaponsLevel1";NA;245;0
"Upgrade";"CentrificalHooks";NA;245;0
"Upgrade";"SprayZerg";NA;245;0
"Upgrade";"EvolveMuscularAugments";NA;245;0
"Upgrade";"ZergGroundArmorsLevel2";NA;245;0
"Upgrade";"ZergMissileWeaponsLevel1";NA;245;0
"Upgrade";"SprayZerg";NA;245;0
"Upgrade";"overlordspeed";NA;245;0
"Upgrade";"SprayZerg";NA;245;0
