"type";"unit_name";"on_building";"total_supply";"supply"
"Unit";"Overlord";"Larva";13;0
"Building";"Extractor";NA;18;0
"Unit";"Overlord";"Larva";21;0
"Building";"SpawningPool";NA;19;0
"Building";"Hatchery";NA;17;0
"Unit";"Zergling";"Larva";23;1
"Unit";"Zergling";"Larva";23;1
"Unit";"Zergling";"Larva";23;1
"Unit";"Zergling";"Larva";23;1
"Unit";"Queen";"Hatchery";23;2
"Unit";"Queen";"Hatchery";23;2
"Building";"CreepTumorQueen";NA;32;0
"Building";"CreepTumorQueen";NA;37;0
"Building";"CreepTumor";NA;37;0
"Unit";"Overlord";"Larva";36;0
"Building";"CreepTumorQueen";NA;39;0
"Unit";"Queen";"Hatchery";32;2
"Unit";"Zergling";"Larva";39;1
"Unit";"Zergling";"Larva";39;1
"Unit";"Overlord";"Larva";39;0
"Building";"Hatchery";NA;30;0
"Unit";"Queen";"Hatchery";39;2
"Building";"CreepTumor";NA;43;0
"Building";"CreepTumor";NA;43;0
"Building";"CreepTumorQueen";NA;49;0
"Unit";"Overlord";"Larva";43;0
"Unit";"Overlord";"Larva";51;0
"Building";"CreepTumor";NA;52;0
"Unit";"Queen";"Hatchery";49;2
"Building";"CreepTumor";NA;52;0
"Building";"CreepTumor";NA;52;0
"Unit";"Queen";"Hatchery";52;2
"Building";"RoachWarren";NA;52;0
"Building";"EvolutionChamber";NA;58;0
"Unit";"Queen";"Hatchery";53;2
"Unit";"Overlord";"Larva";60;0
"Unit";"Queen";"Hatchery";56;2
"Unit";"Zergling";"Larva";60;1
"Unit";"Zergling";"Larva";60;1
"Unit";"Zergling";"Larva";60;1
"Unit";"Zergling";"Larva";60;1
"Unit";"Zergling";"Larva";60;1
"Unit";"Zergling";"Larva";60;1
"Unit";"Roach";"Larva";60;2
"Building";"EvolutionChamber";NA;60;0
"Building";"Extractor";NA;65;0
"Building";"Extractor";NA;67;0
"Building";"CreepTumor";NA;75;0
"Building";"CreepTumor";NA;77;0
"Unit";"Roach";"Larva";69;2
"Unit";"Roach";"Larva";69;2
"Unit";"Roach";"Larva";69;2
"Unit";"Roach";"Larva";69;2
"Unit";"Overlord";"Larva";75;0
"Unit";"Roach";"Larva";85;2
"Unit";"Roach";"Larva";85;2
"Unit";"Roach";"Larva";85;2
"Unit";"Roach";"Larva";85;2
"Building";"CreepTumorQueen";NA;85;0
"Unit";"Roach";"Larva";85;2
"Building";"CreepTumor";NA;103;0
"Unit";"Overlord";"Larva";103;0
"Building";"Extractor";NA;103;0
"Unit";"Overlord";"Larva";106;0
"Unit";"Overlord";"Larva";106;0
"Building";"Extractor";NA;106;0
"Unit";"Overlord";"Larva";106;0
"Building";"CreepTumor";NA;106;0
"Upgrade";"ZergMissileWeaponsLevel1";"EvolutionChamber";85;0
"Unit";"Roach";"Larva";114;2
"Unit";"Roach";"Larva";114;2
"Unit";"Roach";"Larva";114;2
"Unit";"Roach";"Larva";114;2
"Unit";"Roach";"Larva";114;2
"Unit";"Roach";"Larva";114;2
"Unit";"Roach";"Larva";114;2
"Unit";"Roach";"Larva";114;2
"Unit";"Roach";"Larva";114;2
"Unit";"Roach";"Larva";114;2
"Unit";"Roach";"Larva";130;2
"Unit";"Roach";"Larva";130;2
"Unit";"Roach";"Larva";130;2
"Unit";"Roach";"Larva";130;2
"Unit";"Roach";"Larva";130;2
"Unit";"Roach";"Larva";130;2
"Unit";"Roach";"Larva";130;2
"Unit";"Roach";"Larva";130;2
"Unit";"Roach";"Larva";130;2
"Building";"CreepTumor";NA;134;0
"Unit";"Roach";"Larva";134;2
"Unit";"Roach";"Larva";134;2
"Building";"CreepTumor";NA;134;0
"Unit";"Overlord";"Larva";134;0
"Unit";"Overlord";"Larva";134;0
"Unit";"Overlord";"Larva";134;0
"Building";"Hatchery";NA;114;0
"Unit";"Overlord";"Larva";134;0
"Unit";"Roach";"Larva";156;2
"Unit";"Roach";"Larva";156;2
"Unit";"Roach";"Larva";156;2
"Unit";"Roach";"Larva";156;2
"Unit";"Roach";"Larva";156;2
"Building";"CreepTumor";NA;156;0
"Unit";"Roach";"Larva";156;2
"Building";"Extractor";NA;156;0
"Upgrade";"GlialReconstitution";"RoachWarren";134;0
"Unit";"Roach";"Larva";171;2
"Unit";"Roach";"Larva";173;2
"Unit";"Roach";"Larva";173;2
"Unit";"Roach";"Larva";173;2
"Unit";"Roach";"Larva";173;2
"Unit";"Roach";"Larva";173;2
"Unit";"Roach";"Larva";173;2
"Unit";"Roach";"Larva";173;2
"Unit";"Roach";"Larva";173;2
"Unit";"Roach";"Larva";173;2
"Unit";"Roach";"Larva";173;2
"Unit";"Roach";"Larva";173;2
"Unit";"Roach";"Larva";173;2
"Unit";"Roach";"Larva";173;2
"Unit";"Roach";"Larva";173;2
"Unit";"Roach";"Larva";173;2
"Unit";"Roach";"Larva";173;2
"Unit";"Roach";"Larva";173;2
"Unit";"Roach";"Larva";175;2
"Unit";"Roach";"Larva";175;2
"Unit";"Roach";"Larva";175;2
"Unit";"Roach";"Larva";179;2
"Unit";"Roach";"Larva";179;2
"Building";"CreepTumor";NA;205;0
"Unit";"Roach";"Larva";201;2
"Unit";"Roach";"Larva";201;2
"Building";"CreepTumor";NA;213;0
"Unit";"Roach";"Larva";205;2
"Unit";"Roach";"Larva";205;2
"Unit";"Roach";"Larva";207;2
"Unit";"Roach";"Larva";213;2
"Unit";"Roach";"Larva";213;2
"Unit";"Overlord";"Larva";215;0
"Unit";"Roach";"Larva";219;2
"Unit";"Roach";"Larva";219;2
"Unit";"Roach";"Larva";219;2
"Upgrade";"ZergMissileWeaponsLevel2";"EvolutionChamber";156;0
"Unit";"Roach";"Larva";223;2
"Unit";"Roach";"Larva";223;2
"Unit";"Roach";"Larva";223;2
"Unit";"Roach";"Larva";229;2
"Unit";"Roach";"Larva";233;2
"Unit";"Roach";"Larva";233;2
"Unit";"Roach";"Larva";233;2
"Unit";"Roach";"Larva";233;2
"Unit";"Roach";"Larva";233;2
"Unit";"Roach";"Larva";243;2
"Unit";"Roach";"Larva";245;2
"Unit";"Roach";"Larva";245;2
"Unit";"Roach";"Larva";247;2
"Unit";"Roach";"Larva";251;2
"Unit";"Roach";"Larva";253;2
"Unit";"Roach";"Larva";255;2
"Unit";"Roach";"Larva";257;2
"Unit";"Roach";"Larva";257;2
"Unit";"Roach";"Larva";259;2
"Building";"CreepTumorQueen";NA;265;0
"Building";"CreepTumorQueen";NA;265;0
"Building";"CreepTumorQueen";NA;269;0
"Building";"CreepTumor";NA;269;0
"Unit";"Roach";"Larva";265;2
"Building";"CreepTumorQueen";NA;271;0
"Unit";"Roach";"Larva";267;2
"Unit";"Roach";"Larva";267;2
"Unit";"Roach";"Larva";267;2
"Unit";"Roach";"Larva";267;2
"Unit";"Roach";"Larva";269;2
"Unit";"Roach";"Larva";277;2
"Unit";"Roach";"Larva";279;2
"Unit";"Roach";"Larva";279;2
"Unit";"Roach";"Larva";281;2
