"type";"unit_name";"on_building";"total_supply";"supply"
"Unit";"Overlord";"Larva";13;0
"Building";"Extractor";NA;17;0
"Building";"SpawningPool";NA;19;0
"Building";"Hatchery";NA;17;0
"Unit";"Zergling";"Larva";24;1
"Unit";"Zergling";"Larva";24;1
"Unit";"Zergling";"Larva";24;1
"Unit";"Zergling";"Larva";24;1
"Unit";"Queen";"Hatchery";24;2
"Unit";"Queen";"Hatchery";24;2
"Unit";"Overlord";"Larva";32;0
"Unit";"Queen";"Hatchery";30;2
"Building";"CreepTumorQueen";NA;33;0
"Building";"Hatchery";NA;28;0
"Unit";"Queen";"Hatchery";33;2
"Unit";"Overlord";"Larva";41;0
"Unit";"Overlord";"Larva";41;0
"Building";"CreepTumor";NA;41;0
"Building";"CreepTumorQueen";NA;41;0
"Building";"CreepTumorQueen";NA;41;0
"Unit";"Queen";"Hatchery";41;2
"Building";"CreepTumorQueen";NA;47;0
"Building";"CreepTumor";NA;47;0
"Unit";"Queen";"Hatchery";43;2
"Building";"CreepTumor";NA;50;0
"Building";"CreepTumorQueen";NA;56;0
"Building";"CreepTumor";NA;51;0
"Building";"CreepTumorQueen";NA;57;0
"Building";"EvolutionChamber";NA;47;0
"Unit";"Overlord";"Larva";59;0
"Unit";"Overlord";"Larva";66;0
"Unit";"Overlord";"Larva";66;0
"Unit";"Zergling";"Larva";66;1
"Unit";"Zergling";"Larva";66;1
"Unit";"Zergling";"Larva";66;1
"Unit";"Zergling";"Larva";66;1
"Unit";"Zergling";"Larva";66;1
"Unit";"Zergling";"Larva";66;1
"Building";"CreepTumor";NA;66;0
"Building";"CreepTumor";NA;66;0
"Building";"CreepTumor";NA;66;0
"Building";"CreepTumor";NA;66;0
"Building";"CreepTumor";NA;66;0
"Building";"CreepTumor";NA;66;0
"Unit";"Zergling";"Larva";66;1
"Unit";"Zergling";"Larva";66;1
"Unit";"Zergling";"Larva";66;1
"Unit";"Zergling";"Larva";66;1
"Unit";"Zergling";"Larva";66;1
"Unit";"Zergling";"Larva";66;1
"Unit";"Zergling";"Larva";66;1
"Unit";"Zergling";"Larva";66;1
"Unit";"Zergling";"Larva";66;1
"Unit";"Zergling";"Larva";66;1
"Unit";"Zergling";"Larva";66;1
"Unit";"Zergling";"Larva";66;1
"Unit";"Zergling";"Larva";66;1
"Unit";"Zergling";"Larva";66;1
"Unit";"Zergling";"Larva";66;1
"Unit";"Zergling";"Larva";66;1
"Unit";"Zergling";"Larva";66;1
"Unit";"Zergling";"Larva";66;1
"Unit";"Queen";"Hatchery";66;2
"Unit";"Zergling";"Larva";72;1
"Unit";"Zergling";"Larva";72;1
"Unit";"Zergling";"Larva";72;1
"Unit";"Zergling";"Larva";72;1
"Unit";"Zergling";"Larva";72;1
"Unit";"Zergling";"Larva";72;1
"Unit";"Zergling";"Larva";72;1
"Unit";"Zergling";"Larva";72;1
"Unit";"Zergling";"Larva";72;1
"Unit";"Zergling";"Larva";72;1
"Unit";"Zergling";"Larva";72;1
"Unit";"Zergling";"Larva";72;1
"Unit";"Queen";"Hatchery";72;2
"Unit";"Zergling";"Larva";92;1
"Unit";"Zergling";"Larva";92;1
"Building";"CreepTumor";NA;104;0
"Unit";"Zergling";"Larva";92;1
"Unit";"Zergling";"Larva";92;1
"Building";"CreepTumor";NA;104;0
"Building";"CreepTumor";NA;104;0
"Unit";"Overlord";"Larva";92;0
"Unit";"Overlord";"Larva";94;0
"Building";"CreepTumor";NA;104;0
"Unit";"Overlord";"Larva";96;0
"Unit";"Overlord";"Larva";104;0
"Building";"Extractor";NA;104;0
"Building";"Extractor";NA;104;0
"Building";"Extractor";NA;104;0
"Building";"EvolutionChamber";NA;110;0
"Building";"CreepTumor";NA;117;0
"Unit";"Zergling";"Larva";117;1
"Unit";"Zergling";"Larva";117;1
"Unit";"Zergling";"Larva";117;1
"Unit";"Zergling";"Larva";117;1
"Unit";"Zergling";"Larva";117;1
"Unit";"Zergling";"Larva";117;1
"Unit";"Zergling";"Larva";117;1
"Unit";"Zergling";"Larva";117;1
"Unit";"Zergling";"Larva";117;1
"Unit";"Zergling";"Larva";117;1
"Unit";"Zergling";"Larva";117;1
"Unit";"Zergling";"Larva";117;1
"Unit";"Zergling";"Larva";117;1
"Unit";"Zergling";"Larva";117;1
"Building";"CreepTumorQueen";NA;117;0
"Building";"CreepTumorQueen";NA;117;0
"Building";"BanelingNest";NA;110;0
"Building";"CreepTumor";NA;117;0
"Building";"CreepTumor";NA;131;0
"Upgrade";"ZergGroundArmorsLevel1";"EvolutionChamber";72;0
"Building";"CreepTumorQueen";NA;134;0
"Building";"CreepTumor";NA;139;0
"Building";"Extractor";NA;131;0
"Building";"CreepTumor";NA;139;0
"Building";"Extractor";NA;131;0
"Building";"CreepTumorQueen";NA;139;0
"Building";"CreepTumor";NA;139;0
"Unit";"Zergling";"Larva";139;1
"Unit";"Zergling";"Larva";139;1
"Unit";"Zergling";"Larva";139;1
"Unit";"Zergling";"Larva";139;1
"Unit";"Zergling";"Larva";139;1
"Unit";"Zergling";"Larva";139;1
"Unit";"Zergling";"Larva";139;1
"Unit";"Zergling";"Larva";139;1
"Unit";"Zergling";"Larva";139;1
"Unit";"Zergling";"Larva";139;1
"Unit";"Zergling";"Larva";139;1
"Unit";"Zergling";"Larva";139;1
"Building";"Hatchery";NA;131;0
"Building";"CreepTumorQueen";NA;163;0
"Building";"CreepTumor";NA;163;0
"Building";"CreepTumor";NA;163;0
"Building";"CreepTumor";NA;163;0
"Building";"CreepTumor";NA;163;0
"Building";"CreepTumor";NA;163;0
"Building";"Hatchery";NA;139;0
"Building";"CreepTumor";NA;163;0
"Building";"HydraliskDen";NA;151;0
"Building";"InfestationPit";NA;160;0
"Unit";"Overlord";"Larva";163;0
"Unit";"Overlord";"Larva";163;0
"Unit";"Overlord";"Larva";163;0
"Unit";"Overlord";"Larva";163;0
"Unit";"Overlord";"Larva";163;0
"Upgrade";"ZergMeleeWeaponsLevel1";"EvolutionChamber";139;0
"Unit";"Hydralisk";"Larva";163;2
"Unit";"Hydralisk";"Larva";163;2
"Building";"CreepTumorQueen";NA;171;0
"Unit";"Queen";"Hatchery";163;2
"Building";"CreepTumorQueen";NA;171;0
"Building";"CreepTumor";NA;177;0
"Unit";"Zergling";"Larva";177;1
"Unit";"Zergling";"Larva";177;1
"Unit";"Zergling";"Larva";177;1
"Unit";"Zergling";"Larva";177;1
"Unit";"Zergling";"Larva";177;1
"Unit";"Zergling";"Larva";177;1
"Unit";"Zergling";"Larva";177;1
"Unit";"Zergling";"Larva";177;1
"Unit";"Zergling";"Larva";177;1
"Unit";"Zergling";"Larva";177;1
"Unit";"Zergling";"Larva";177;1
"Unit";"Zergling";"Larva";177;1
"Unit";"Zergling";"Larva";177;1
"Unit";"Zergling";"Larva";177;1
"Unit";"Zergling";"Larva";177;1
"Unit";"Zergling";"Larva";177;1
"Unit";"Zergling";"Larva";177;1
"Unit";"Zergling";"Larva";177;1
"Unit";"Zergling";"Larva";177;1
"Unit";"Zergling";"Larva";177;1
"Unit";"Zergling";"Larva";177;1
"Unit";"Zergling";"Larva";177;1
"Unit";"Zergling";"Larva";177;1
"Unit";"Zergling";"Larva";177;1
"Unit";"Zergling";"Larva";177;1
"Unit";"Zergling";"Larva";177;1
"Unit";"Zergling";"Larva";177;1
"Unit";"Zergling";"Larva";177;1
"Unit";"Zergling";"Larva";177;1
"Unit";"Zergling";"Larva";177;1
"Unit";"Queen";"Hatchery";171;2
"Unit";"Queen";"Hatchery";177;2
"Building";"Extractor";NA;207;0
"Upgrade";"EvolveGroovedSpines";"HydraliskDen";171;0
"Building";"Extractor";NA;207;0
"Unit";"Hydralisk";"Larva";207;2
"Unit";"Hydralisk";"Larva";207;2
"Unit";"Hydralisk";"Larva";207;2
"Unit";"Hydralisk";"Larva";207;2
"Unit";"Hydralisk";"Larva";207;2
"Unit";"Hydralisk";"Larva";207;2
"Unit";"Hydralisk";"Larva";207;2
"Unit";"Hydralisk";"Larva";207;2
"Unit";"Hydralisk";"Larva";207;2
"Unit";"Hydralisk";"Larva";207;2
"Unit";"Hydralisk";"Larva";207;2
"Unit";"Hydralisk";"Larva";207;2
"Unit";"Hydralisk";"Larva";207;2
"Unit";"Overlord";"Larva";211;0
"Unit";"Overlord";"Larva";211;0
"Unit";"Overlord";"Larva";211;0
"Unit";"Hydralisk";"Larva";211;2
"Unit";"Hydralisk";"Larva";211;2
"Unit";"Hydralisk";"Larva";211;2
"Unit";"Hydralisk";"Larva";211;2
"Unit";"Hydralisk";"Larva";211;2
"Building";"CreepTumor";NA;243;0
"Building";"CreepTumor";NA;243;0
"Building";"CreepTumor";NA;243;0
"Building";"CreepTumor";NA;243;0
"Building";"CreepTumorQueen";NA;253;0
"Upgrade";"ZergGroundArmorsLevel2";"EvolutionChamber";171;0
"Unit";"Baneling";"Zergling";253;0
"Unit";"Baneling";"Zergling";253;0
"Unit";"Baneling";"Zergling";253;0
"Unit";"Baneling";"Zergling";253;0
"Unit";"Baneling";"Zergling";253;0
"Unit";"Hydralisk";"Larva";253;2
"Unit";"Hydralisk";"Larva";253;2
"Unit";"Hydralisk";"Larva";253;2
"Unit";"Hydralisk";"Larva";253;2
"Unit";"Baneling";"Zergling";253;0
"Unit";"Hydralisk";"Larva";253;2
"Unit";"Hydralisk";"Larva";253;2
"Unit";"Hydralisk";"Larva";253;2
"Unit";"Hydralisk";"Larva";253;2
"Unit";"Hydralisk";"Larva";253;2
"Unit";"Hydralisk";"Larva";253;2
"Unit";"Hydralisk";"Larva";253;2
"Unit";"Hydralisk";"Larva";253;2
"Unit";"Baneling";"Zergling";253;0
"Unit";"Baneling";"Zergling";253;0
"Unit";"Baneling";"Zergling";253;0
"Unit";"Baneling";"Zergling";253;0
"Unit";"Baneling";"Zergling";253;0
"Unit";"Zergling";"Larva";253;1
"Unit";"Zergling";"Larva";253;1
"Unit";"Zergling";"Larva";253;1
"Unit";"Zergling";"Larva";253;1
"Unit";"Zergling";"Larva";253;1
"Unit";"Zergling";"Larva";253;1
"Unit";"Zergling";"Larva";253;1
"Unit";"Zergling";"Larva";253;1
"Unit";"Zergling";"Larva";253;1
"Unit";"Zergling";"Larva";253;1
"Unit";"Zergling";"Larva";253;1
"Unit";"Zergling";"Larva";253;1
"Unit";"Zergling";"Larva";253;1
"Unit";"Zergling";"Larva";253;1
"Unit";"Zergling";"Larva";253;1
"Unit";"Zergling";"Larva";253;1
"Unit";"Zergling";"Larva";253;1
"Unit";"Zergling";"Larva";253;1
"Unit";"Zergling";"Larva";253;1
"Unit";"Zergling";"Larva";253;1
"Unit";"Zergling";"Larva";253;1
"Unit";"Zergling";"Larva";253;1
"Unit";"Zergling";"Larva";253;1
"Unit";"Zergling";"Larva";253;1
"Unit";"Zergling";"Larva";253;1
"Unit";"Zergling";"Larva";253;1
"Unit";"Zergling";"Larva";253;1
"Unit";"Zergling";"Larva";253;1
"Upgrade";"EvolveMuscularAugments";"HydraliskDen";253;0
"Unit";"Zergling";"Larva";277;1
"Unit";"Zergling";"Larva";277;1
"Unit";"Zergling";"Larva";277;1
"Unit";"Zergling";"Larva";277;1
"Unit";"Zergling";"Larva";277;1
"Unit";"Zergling";"Larva";277;1
"Unit";"Zergling";"Larva";277;1
"Unit";"Zergling";"Larva";277;1
"Unit";"Zergling";"Larva";277;1
"Unit";"Zergling";"Larva";277;1
"Unit";"Zergling";"Larva";277;1
"Unit";"Zergling";"Larva";277;1
"Unit";"Zergling";"Larva";277;1
"Unit";"Zergling";"Larva";277;1
"Unit";"Zergling";"Larva";277;1
"Unit";"Zergling";"Larva";277;1
"Unit";"Zergling";"Larva";277;1
"Unit";"Zergling";"Larva";277;1
"Unit";"Zergling";"Larva";277;1
"Unit";"Zergling";"Larva";277;1
"Unit";"Zergling";"Larva";277;1
"Unit";"Zergling";"Larva";277;1
"Unit";"Zergling";"Larva";305;1
"Unit";"Zergling";"Larva";305;1
"Unit";"Zergling";"Larva";305;1
"Unit";"Zergling";"Larva";305;1
"Unit";"Zergling";"Larva";305;1
"Unit";"Zergling";"Larva";305;1
"Unit";"Zergling";"Larva";305;1
"Unit";"Zergling";"Larva";305;1
"Unit";"Zergling";"Larva";305;1
"Unit";"Zergling";"Larva";305;1
"Unit";"Zergling";"Larva";305;1
"Unit";"Zergling";"Larva";305;1
"Unit";"Zergling";"Larva";307;1
"Unit";"Zergling";"Larva";307;1
"Unit";"Hydralisk";"Larva";327;2
"Unit";"Hydralisk";"Larva";327;2
"Unit";"Hydralisk";"Larva";327;2
"Unit";"Hydralisk";"Larva";327;2
"Unit";"Hydralisk";"Larva";327;2
"Unit";"Hydralisk";"Larva";327;2
"Unit";"Hydralisk";"Larva";341;2
"Unit";"Hydralisk";"Larva";341;2
"Unit";"Hydralisk";"Larva";341;2
"Unit";"Hydralisk";"Larva";341;2
"Unit";"Hydralisk";"Larva";341;2
"Unit";"Hydralisk";"Larva";341;2
"Unit";"Hydralisk";"Larva";341;2
"Unit";"Hydralisk";"Larva";341;2
"Unit";"Zergling";"Larva";359;1
"Unit";"Zergling";"Larva";359;1
"Unit";"Zergling";"Larva";359;1
"Unit";"Zergling";"Larva";359;1
"Unit";"Zergling";"Larva";359;1
"Unit";"Zergling";"Larva";359;1
"Unit";"Zergling";"Larva";359;1
"Unit";"Zergling";"Larva";359;1
"Unit";"Zergling";"Larva";359;1
"Unit";"Zergling";"Larva";359;1
"Unit";"Zergling";"Larva";359;1
"Unit";"Zergling";"Larva";359;1
"Unit";"Zergling";"Larva";359;1
"Unit";"Zergling";"Larva";359;1
"Unit";"Zergling";"Larva";359;1
"Unit";"Zergling";"Larva";359;1
"Unit";"Zergling";"Larva";369;1
"Unit";"Zergling";"Larva";369;1
"Unit";"Zergling";"Larva";369;1
"Unit";"Zergling";"Larva";369;1
"Unit";"Zergling";"Larva";369;1
"Unit";"Zergling";"Larva";369;1
"Unit";"Zergling";"Larva";369;1
"Unit";"Zergling";"Larva";369;1
"Unit";"Zergling";"Larva";369;1
"Unit";"Zergling";"Larva";369;1
"Unit";"Zergling";"Larva";369;1
"Unit";"Zergling";"Larva";369;1
"Unit";"Zergling";"Larva";369;1
"Unit";"Zergling";"Larva";369;1
"Unit";"Zergling";"Larva";369;1
"Unit";"Zergling";"Larva";369;1
"Unit";"Zergling";"Larva";369;1
"Unit";"Zergling";"Larva";369;1
"Unit";"Zergling";"Larva";369;1
"Unit";"Zergling";"Larva";369;1
"Unit";"Zergling";"Larva";369;1
"Unit";"Zergling";"Larva";369;1
"Unit";"Baneling";"Zergling";385;0
"Unit";"Baneling";"Zergling";385;0
"Unit";"Baneling";"Zergling";385;0
"Unit";"Baneling";"Zergling";385;0
"Unit";"Baneling";"Zergling";385;0
"Unit";"Baneling";"Zergling";385;0
"Unit";"Baneling";"Zergling";385;0
"Unit";"Baneling";"Zergling";385;0
"Unit";"Baneling";"Zergling";385;0
"Unit";"Baneling";"Zergling";385;0
"Unit";"Baneling";"Zergling";385;0
"Unit";"Baneling";"Zergling";385;0
"Unit";"Baneling";"Zergling";385;0
"Unit";"Baneling";"Zergling";385;0
"Unit";"Baneling";"Zergling";385;0
"Unit";"Baneling";"Zergling";385;0
"Unit";"Hydralisk";"Larva";385;2
"Unit";"Hydralisk";"Larva";385;2
"Unit";"Hydralisk";"Larva";385;2
"Unit";"Hydralisk";"Larva";385;2
"Unit";"Hydralisk";"Larva";385;2
"Unit";"Zergling";"Larva";407;1
"Unit";"Zergling";"Larva";407;1
"Unit";"Zergling";"Larva";407;1
"Unit";"Zergling";"Larva";407;1
"Unit";"Zergling";"Larva";407;1
"Unit";"Zergling";"Larva";407;1
"Unit";"Zergling";"Larva";407;1
"Unit";"Zergling";"Larva";407;1
"Unit";"Zergling";"Larva";407;1
"Unit";"Zergling";"Larva";407;1
"Unit";"Zergling";"Larva";407;1
"Unit";"Zergling";"Larva";407;1
"Unit";"Zergling";"Larva";407;1
"Unit";"Zergling";"Larva";407;1
"Unit";"Zergling";"Larva";407;1
"Unit";"Zergling";"Larva";407;1
"Unit";"Zergling";"Larva";407;1
"Unit";"Zergling";"Larva";407;1
"Unit";"Zergling";"Larva";407;1
"Unit";"Zergling";"Larva";407;1
"Unit";"Zergling";"Larva";407;1
"Unit";"Zergling";"Larva";407;1
"Unit";"Zergling";"Larva";407;1
"Unit";"Zergling";"Larva";407;1
"Unit";"Zergling";"Larva";407;1
"Unit";"Zergling";"Larva";407;1
"Building";"UltraliskCavern";NA;385;0
"Building";"CreepTumorQueen";NA;443;0
"Upgrade";"ZergMeleeWeaponsLevel2";"EvolutionChamber";353;0
"Building";"CreepTumorQueen";NA;443;0
"Unit";"Zergling";"Larva";443;1
"Unit";"Zergling";"Larva";443;1
"Unit";"Zergling";"Larva";443;1
"Unit";"Zergling";"Larva";443;1
"Unit";"Zergling";"Larva";443;1
"Unit";"Zergling";"Larva";443;1
"Unit";"Zergling";"Larva";443;1
"Unit";"Zergling";"Larva";443;1
"Unit";"Zergling";"Larva";443;1
"Unit";"Zergling";"Larva";443;1
"Unit";"Zergling";"Larva";443;1
"Unit";"Zergling";"Larva";443;1
"Unit";"Zergling";"Larva";443;1
"Unit";"Zergling";"Larva";443;1
"Unit";"Zergling";"Larva";443;1
"Unit";"Zergling";"Larva";443;1
"Unit";"Zergling";"Larva";443;1
"Unit";"Zergling";"Larva";443;1
"Unit";"Zergling";"Larva";443;1
"Unit";"Zergling";"Larva";443;1
"Unit";"Zergling";"Larva";443;1
"Unit";"Zergling";"Larva";443;1
"Unit";"Zergling";"Larva";443;1
"Unit";"Zergling";"Larva";443;1
"Unit";"Zergling";"Larva";443;1
"Unit";"Zergling";"Larva";443;1
"Unit";"Zergling";"Larva";443;1
"Unit";"Zergling";"Larva";443;1
"Unit";"Zergling";"Larva";443;1
"Unit";"Zergling";"Larva";443;1
"Unit";"Baneling";"Zergling";443;0
"Unit";"Baneling";"Zergling";443;0
"Unit";"Baneling";"Zergling";443;0
"Unit";"Baneling";"Zergling";443;0
"Unit";"Baneling";"Zergling";443;0
"Unit";"Baneling";"Zergling";443;0
"Unit";"Baneling";"Zergling";443;0
"Unit";"Baneling";"Zergling";443;0
"Unit";"Baneling";"Zergling";443;0
"Unit";"Baneling";"Zergling";443;0
"Unit";"Baneling";"Zergling";443;0
"Unit";"Baneling";"Zergling";443;0
"Unit";"Baneling";"Zergling";443;0
"Unit";"Baneling";"Zergling";443;0
"Unit";"Baneling";"Zergling";443;0
"Unit";"Baneling";"Zergling";443;0
"Unit";"Baneling";"Zergling";443;0
"Unit";"Baneling";"Zergling";443;0
"Upgrade";"ZergGroundArmorsLevel3";"EvolutionChamber";359;0
"Unit";"Zergling";"Larva";473;1
"Unit";"Zergling";"Larva";473;1
"Unit";"Zergling";"Larva";473;1
"Unit";"Zergling";"Larva";473;1
"Unit";"Zergling";"Larva";473;1
"Unit";"Zergling";"Larva";473;1
"Unit";"Zergling";"Larva";473;1
"Unit";"Zergling";"Larva";473;1
"Unit";"Zergling";"Larva";473;1
"Unit";"Zergling";"Larva";473;1
"Unit";"Zergling";"Larva";473;1
"Unit";"Zergling";"Larva";473;1
"Unit";"Zergling";"Larva";473;1
"Unit";"Zergling";"Larva";473;1
"Unit";"Zergling";"Larva";473;1
"Unit";"Zergling";"Larva";473;1
"Unit";"Zergling";"Larva";473;1
"Unit";"Zergling";"Larva";473;1
"Unit";"Zergling";"Larva";473;1
"Unit";"Zergling";"Larva";473;1
"Unit";"Zergling";"Larva";473;1
"Unit";"Zergling";"Larva";473;1
"Unit";"Zergling";"Larva";473;1
"Unit";"Zergling";"Larva";473;1
"Unit";"Zergling";"Larva";473;1
"Unit";"Zergling";"Larva";473;1
"Building";"Hatchery";NA;417;0
"Unit";"Ultralisk";"Larva";499;6
"Unit";"Ultralisk";"Larva";499;6
"Unit";"Zergling";"Larva";499;1
"Unit";"Zergling";"Larva";499;1
"Unit";"Zergling";"Larva";499;1
"Unit";"Zergling";"Larva";499;1
"Unit";"Zergling";"Larva";499;1
"Unit";"Zergling";"Larva";499;1
"Unit";"Zergling";"Larva";499;1
"Unit";"Zergling";"Larva";499;1
"Unit";"Zergling";"Larva";499;1
"Unit";"Zergling";"Larva";499;1
"Unit";"Zergling";"Larva";499;1
"Unit";"Zergling";"Larva";499;1
"Building";"CreepTumor";NA;499;0
"Unit";"Ultralisk";"Larva";499;6
"Unit";"Zergling";"Larva";511;1
"Unit";"Zergling";"Larva";511;1
"Unit";"Ultralisk";"Larva";499;6
"Unit";"Zergling";"Larva";513;1
"Unit";"Zergling";"Larva";513;1
"Unit";"Zergling";"Larva";513;1
"Unit";"Zergling";"Larva";513;1
"Unit";"Zergling";"Larva";513;1
"Unit";"Zergling";"Larva";513;1
"Unit";"Zergling";"Larva";513;1
"Unit";"Zergling";"Larva";513;1
"Unit";"Zergling";"Larva";515;1
"Unit";"Zergling";"Larva";515;1
"Unit";"Zergling";"Larva";515;1
"Unit";"Zergling";"Larva";515;1
"Unit";"Zergling";"Larva";521;1
"Unit";"Zergling";"Larva";521;1
"Unit";"Zergling";"Larva";521;1
"Unit";"Zergling";"Larva";521;1
"Unit";"Zergling";"Larva";521;1
"Unit";"Zergling";"Larva";521;1
"Unit";"Zergling";"Larva";521;1
"Unit";"Zergling";"Larva";521;1
"Upgrade";"ChitinousPlating";"UltraliskCavern";499;0
"Upgrade";"ZergMissileWeaponsLevel1";"EvolutionChamber";473;0
"Unit";"Hydralisk";"Larva";523;2
"Unit";"Hydralisk";"Larva";523;2
"Unit";"Hydralisk";"Larva";523;2
"Unit";"Hydralisk";"Larva";523;2
"Unit";"Zergling";"Larva";565;1
"Unit";"Zergling";"Larva";565;1
"Unit";"Zergling";"Larva";565;1
"Unit";"Zergling";"Larva";565;1
"Unit";"Zergling";"Larva";565;1
"Unit";"Zergling";"Larva";565;1
"Unit";"Zergling";"Larva";565;1
"Unit";"Zergling";"Larva";565;1
"Unit";"Zergling";"Larva";565;1
"Unit";"Zergling";"Larva";565;1
"Unit";"Zergling";"Larva";565;1
"Unit";"Zergling";"Larva";565;1
"Unit";"Zergling";"Larva";565;1
"Unit";"Zergling";"Larva";565;1
"Unit";"Zergling";"Larva";565;1
"Unit";"Zergling";"Larva";565;1
"Unit";"Zergling";"Larva";565;1
"Unit";"Zergling";"Larva";565;1
"Unit";"Zergling";"Larva";565;1
"Unit";"Zergling";"Larva";565;1
"Unit";"Zergling";"Larva";565;1
"Unit";"Zergling";"Larva";565;1
"Unit";"Zergling";"Larva";565;1
"Unit";"Zergling";"Larva";565;1
"Unit";"Zergling";"Larva";565;1
"Unit";"Zergling";"Larva";565;1
"Unit";"Hydralisk";"Larva";565;2
"Unit";"Hydralisk";"Larva";567;2
"Unit";"Hydralisk";"Larva";569;2
"Unit";"Hydralisk";"Larva";569;2
"Unit";"Hydralisk";"Larva";573;2
"Unit";"Hydralisk";"Larva";577;2
"Unit";"Hydralisk";"Larva";577;2
"Unit";"Hydralisk";"Larva";577;2
"Unit";"Hydralisk";"Larva";581;2
"Unit";"Queen";"Hatchery";591;2
"Unit";"Queen";"Hatchery";591;2
"Unit";"Queen";"Hatchery";591;2
"Unit";"Zergling";"Larva";609;1
"Unit";"Zergling";"Larva";609;1
"Unit";"Zergling";"Larva";609;1
"Unit";"Zergling";"Larva";609;1
"Unit";"Zergling";"Larva";609;1
"Unit";"Zergling";"Larva";609;1
"Unit";"Zergling";"Larva";609;1
"Unit";"Zergling";"Larva";609;1
"Unit";"Zergling";"Larva";609;1
"Unit";"Zergling";"Larva";609;1
"Unit";"Zergling";"Larva";609;1
"Unit";"Zergling";"Larva";609;1
"Unit";"Zergling";"Larva";609;1
"Unit";"Zergling";"Larva";609;1
"Unit";"Zergling";"Larva";609;1
"Unit";"Zergling";"Larva";609;1
"Unit";"Zergling";"Larva";609;1
"Unit";"Zergling";"Larva";609;1
"Unit";"Zergling";"Larva";609;1
"Unit";"Zergling";"Larva";609;1
"Unit";"Zergling";"Larva";609;1
"Unit";"Zergling";"Larva";609;1
"Unit";"Zergling";"Larva";609;1
"Unit";"Zergling";"Larva";609;1
"Unit";"Zergling";"Larva";609;1
"Unit";"Zergling";"Larva";609;1
"Unit";"Zergling";"Larva";609;1
"Unit";"Zergling";"Larva";609;1
"Unit";"Zergling";"Larva";609;1
"Unit";"Zergling";"Larva";609;1
"Unit";"Zergling";"Larva";609;1
"Unit";"Zergling";"Larva";609;1
"Unit";"Zergling";"Larva";609;1
"Unit";"Zergling";"Larva";609;1
"Unit";"Zergling";"Larva";609;1
"Unit";"Zergling";"Larva";609;1
"Unit";"Zergling";"Larva";609;1
"Unit";"Zergling";"Larva";609;1
"Unit";"Zergling";"Larva";609;1
"Unit";"Zergling";"Larva";609;1
"Building";"CreepTumor";NA;655;0
"Building";"CreepTumor";NA;655;0
"Unit";"Hydralisk";"Larva";615;2
"Unit";"Hydralisk";"Larva";615;2
"Unit";"Baneling";"Zergling";655;0
"Unit";"Baneling";"Zergling";655;0
"Unit";"Hydralisk";"Larva";655;2
"Unit";"Baneling";"Zergling";655;0
"Unit";"Hydralisk";"Larva";655;2
"Unit";"Hydralisk";"Larva";655;2
"Unit";"Hydralisk";"Larva";655;2
"Unit";"Hydralisk";"Larva";655;2
"Unit";"Baneling";"Zergling";655;0
"Unit";"Baneling";"Zergling";655;0
"Unit";"Baneling";"Zergling";655;0
"Unit";"Baneling";"Zergling";655;0
"Unit";"Hydralisk";"Larva";655;2
"Unit";"Hydralisk";"Larva";655;2
"Unit";"Baneling";"Zergling";655;0
"Unit";"Baneling";"Zergling";655;0
"Unit";"Baneling";"Zergling";655;0
"Unit";"Baneling";"Zergling";655;0
"Unit";"Baneling";"Zergling";655;0
"Unit";"Baneling";"Zergling";655;0
"Unit";"Baneling";"Zergling";659;0
"Upgrade";"ZergMeleeWeaponsLevel3";"EvolutionChamber";591;0
"Unit";"Ultralisk";"Larva";673;6
"Unit";"Ultralisk";"Larva";673;6
