"type";"unit_name";"on_building";"total_supply";"supply"
"Unit";"Overlord";"Larva";13;0
"Building";"Extractor";NA;18;0
"Unit";"Overlord";"Larva";21;0
"Building";"SpawningPool";NA;19;0
"Building";"Hatchery";NA;17;0
"Unit";"Zergling";"Larva";22;1
"Unit";"Zergling";"Larva";22;1
"Unit";"Zergling";"Larva";22;1
"Unit";"Zergling";"Larva";22;1
"Unit";"Zergling";"Larva";22;1
"Unit";"Zergling";"Larva";22;1
"Unit";"Queen";"Hatchery";22;2
"Unit";"Queen";"Hatchery";22;2
"Unit";"Overlord";"Larva";37;0
"Unit";"Overlord";"Larva";39;0
"Unit";"Queen";"Hatchery";39;2
"Building";"Hatchery";NA;30;0
"Unit";"Overlord";"Larva";46;0
"Unit";"Overlord";"Larva";49;0
"Unit";"Overlord";"Larva";52;0
"Building";"EvolutionChamber";NA;52;0
"Building";"CreepTumorQueen";NA;52;0
"Unit";"Overlord";"Larva";58;0
"Unit";"Queen";"Hatchery";52;2
"Unit";"Zergling";"Larva";66;1
"Unit";"Zergling";"Larva";66;1
"Unit";"Zergling";"Larva";68;1
"Unit";"Zergling";"Larva";68;1
"Unit";"Zergling";"Larva";68;1
"Unit";"Zergling";"Larva";68;1
"Unit";"Zergling";"Larva";68;1
"Unit";"Zergling";"Larva";68;1
"Building";"CreepTumor";NA;68;0
"Building";"CreepTumorQueen";NA;68;0
"Unit";"Zergling";"Larva";68;1
"Unit";"Zergling";"Larva";68;1
"Unit";"Zergling";"Larva";68;1
"Unit";"Zergling";"Larva";68;1
"Unit";"Zergling";"Larva";68;1
"Unit";"Zergling";"Larva";68;1
"Building";"Extractor";NA;68;0
"Unit";"Queen";"Hatchery";63;2
"Unit";"Zergling";"Larva";76;1
"Unit";"Zergling";"Larva";76;1
"Unit";"Zergling";"Larva";76;1
"Unit";"Zergling";"Larva";76;1
"Unit";"Zergling";"Larva";76;1
"Unit";"Zergling";"Larva";76;1
"Unit";"Zergling";"Larva";76;1
"Unit";"Zergling";"Larva";76;1
"Unit";"Zergling";"Larva";76;1
"Unit";"Zergling";"Larva";76;1
"Building";"CreepTumorQueen";NA;84;0
"Unit";"Zergling";"Larva";82;1
"Unit";"Zergling";"Larva";82;1
"Unit";"Zergling";"Larva";82;1
"Unit";"Zergling";"Larva";82;1
"Unit";"Zergling";"Larva";82;1
"Unit";"Zergling";"Larva";82;1
"Unit";"Zergling";"Larva";82;1
"Unit";"Zergling";"Larva";82;1
"Unit";"Zergling";"Larva";82;1
"Unit";"Zergling";"Larva";82;1
"Unit";"Queen";"Hatchery";68;2
"Building";"BanelingNest";NA;68;0
"Unit";"Queen";"Hatchery";68;2
"Building";"CreepTumor";NA;94;0
"Unit";"Overlord";"Larva";84;0
"Unit";"Overlord";"Larva";84;0
"Unit";"Overlord";"Larva";94;0
"Unit";"Overlord";"Larva";94;0
"Building";"CreepTumorQueen";NA;118;0
"Building";"Extractor";NA;112;0
"Building";"Extractor";NA;112;0
"Building";"Extractor";NA;112;0
"Building";"Extractor";NA;112;0
"Unit";"Overlord";"Larva";121;0
"Unit";"Zergling";"Larva";123;1
"Unit";"Zergling";"Larva";123;1
"Building";"CreepTumorQueen";NA;127;0
"Unit";"Zergling";"Larva";127;1
"Unit";"Zergling";"Larva";127;1
"Upgrade";"ZergGroundArmorsLevel1";"EvolutionChamber";76;0
"Building";"CreepTumor";NA;129;0
"Unit";"Zergling";"Larva";127;1
"Unit";"Zergling";"Larva";127;1
"Unit";"Zergling";"Larva";127;1
"Unit";"Zergling";"Larva";127;1
"Unit";"Zergling";"Larva";127;1
"Unit";"Zergling";"Larva";127;1
"Unit";"Zergling";"Larva";127;1
"Unit";"Zergling";"Larva";127;1
"Unit";"Zergling";"Larva";129;1
"Unit";"Zergling";"Larva";129;1
"Unit";"Zergling";"Larva";129;1
"Unit";"Zergling";"Larva";129;1
"Unit";"Zergling";"Larva";129;1
"Unit";"Zergling";"Larva";129;1
"Unit";"Baneling";"Zergling";131;0
"Unit";"Zergling";"Larva";129;1
"Unit";"Zergling";"Larva";129;1
"Unit";"Zergling";"Larva";129;1
"Unit";"Zergling";"Larva";129;1
"Unit";"Baneling";"Zergling";131;0
"Unit";"Baneling";"Zergling";131;0
"Unit";"Baneling";"Zergling";131;0
"Unit";"Baneling";"Zergling";131;0
"Unit";"Baneling";"Zergling";131;0
"Unit";"Baneling";"Zergling";131;0
"Unit";"Baneling";"Zergling";131;0
"Unit";"Baneling";"Zergling";131;0
"Unit";"Zergling";"Larva";129;1
"Unit";"Zergling";"Larva";129;1
"Unit";"Zergling";"Larva";129;1
"Unit";"Zergling";"Larva";129;1
"Unit";"Zergling";"Larva";131;1
"Unit";"Zergling";"Larva";131;1
"Building";"EvolutionChamber";NA;129;0
"Unit";"Zergling";"Larva";131;1
"Unit";"Zergling";"Larva";131;1
"Unit";"Zergling";"Larva";133;1
"Unit";"Zergling";"Larva";133;1
"Building";"CreepTumor";NA;159;0
"Unit";"Overlord";"Larva";159;0
"Unit";"Overlord";"Larva";159;0
"Unit";"Zergling";"Larva";159;1
"Unit";"Zergling";"Larva";159;1
"Building";"CreepTumorQueen";NA;166;0
"Building";"CreepTumorQueen";NA;168;0
"Unit";"Zergling";"Larva";168;1
"Unit";"Zergling";"Larva";168;1
"Unit";"Zergling";"Larva";168;1
"Unit";"Zergling";"Larva";168;1
"Unit";"Zergling";"Larva";168;1
"Unit";"Zergling";"Larva";168;1
"Unit";"Zergling";"Larva";168;1
"Unit";"Zergling";"Larva";168;1
"Unit";"Zergling";"Larva";168;1
"Unit";"Zergling";"Larva";168;1
"Unit";"Zergling";"Larva";168;1
"Unit";"Zergling";"Larva";168;1
"Unit";"Zergling";"Larva";168;1
"Unit";"Zergling";"Larva";168;1
"Unit";"Zergling";"Larva";168;1
"Unit";"Zergling";"Larva";168;1
"Unit";"Zergling";"Larva";168;1
"Unit";"Zergling";"Larva";168;1
"Unit";"Zergling";"Larva";168;1
"Unit";"Zergling";"Larva";168;1
"Unit";"Zergling";"Larva";168;1
"Unit";"Zergling";"Larva";168;1
"Unit";"Zergling";"Larva";168;1
"Unit";"Zergling";"Larva";168;1
"Building";"Spire";NA;131;0
"Unit";"Overlord";"Larva";168;0
"Unit";"Overlord";"Larva";168;0
"Unit";"Overlord";"Larva";168;0
"Building";"CreepTumorQueen";NA;192;0
"Building";"CreepTumorQueen";NA;192;0
"Building";"CreepTumorQueen";NA;192;0
"Building";"CreepTumor";NA;192;0
"Unit";"Mutalisk";"Larva";192;2
"Unit";"Mutalisk";"Larva";192;2
"Unit";"Mutalisk";"Larva";192;2
"Unit";"Mutalisk";"Larva";192;2
"Unit";"Mutalisk";"Larva";192;2
"Unit";"Mutalisk";"Larva";192;2
"Unit";"Mutalisk";"Larva";192;2
"Unit";"Mutalisk";"Larva";192;2
"Unit";"Mutalisk";"Larva";192;2
"Unit";"Mutalisk";"Larva";192;2
"Unit";"Overlord";"Larva";192;0
"Unit";"Overlord";"Larva";192;0
"Building";"Hatchery";NA;168;0
"Unit";"Mutalisk";"Larva";192;2
"Unit";"Mutalisk";"Larva";192;2
"Unit";"Zergling";"Larva";192;1
"Unit";"Zergling";"Larva";192;1
"Unit";"Zergling";"Larva";192;1
"Unit";"Zergling";"Larva";192;1
"Unit";"Zergling";"Larva";192;1
"Unit";"Zergling";"Larva";192;1
"Unit";"Zergling";"Larva";192;1
"Unit";"Zergling";"Larva";192;1
"Unit";"Zergling";"Larva";192;1
"Unit";"Zergling";"Larva";192;1
"Unit";"Zergling";"Larva";192;1
"Unit";"Zergling";"Larva";192;1
"Unit";"Zergling";"Larva";192;1
"Unit";"Zergling";"Larva";192;1
"Unit";"Zergling";"Larva";192;1
"Unit";"Zergling";"Larva";192;1
"Unit";"Mutalisk";"Larva";192;2
"Unit";"Overlord";"Larva";212;0
"Unit";"Overlord";"Larva";212;0
"Unit";"Baneling";"Zergling";212;0
"Unit";"Baneling";"Zergling";212;0
"Unit";"Baneling";"Zergling";212;0
"Unit";"Baneling";"Zergling";212;0
"Unit";"Baneling";"Zergling";212;0
"Unit";"Baneling";"Zergling";212;0
"Unit";"Baneling";"Zergling";212;0
"Unit";"Zergling";"Larva";212;1
"Unit";"Zergling";"Larva";212;1
"Upgrade";"ZergMeleeWeaponsLevel1";"EvolutionChamber";168;0
"Unit";"Zergling";"Larva";212;1
"Unit";"Zergling";"Larva";212;1
"Unit";"Zergling";"Larva";232;1
"Unit";"Zergling";"Larva";232;1
"Unit";"Zergling";"Larva";232;1
"Unit";"Zergling";"Larva";232;1
"Unit";"Zergling";"Larva";232;1
"Unit";"Zergling";"Larva";232;1
"Unit";"Zergling";"Larva";232;1
"Unit";"Zergling";"Larva";232;1
"Building";"Hatchery";NA;192;0
"Upgrade";"ZergGroundArmorsLevel2";"EvolutionChamber";168;0
"Unit";"Mutalisk";"Larva";238;2
"Unit";"Mutalisk";"Larva";238;2
"Unit";"Zergling";"Larva";238;1
"Unit";"Zergling";"Larva";238;1
"Unit";"Mutalisk";"Larva";238;2
"Unit";"Zergling";"Larva";238;1
"Unit";"Zergling";"Larva";238;1
"Unit";"Zergling";"Larva";238;1
"Unit";"Zergling";"Larva";238;1
"Unit";"Zergling";"Larva";240;1
"Unit";"Zergling";"Larva";240;1
"Unit";"Zergling";"Larva";240;1
"Unit";"Zergling";"Larva";240;1
"Unit";"Zergling";"Larva";240;1
"Unit";"Zergling";"Larva";240;1
"Unit";"Zergling";"Larva";240;1
"Unit";"Zergling";"Larva";240;1
"Unit";"Mutalisk";"Larva";238;2
"Unit";"Mutalisk";"Larva";238;2
"Unit";"Zergling";"Larva";256;1
"Unit";"Zergling";"Larva";256;1
"Unit";"Zergling";"Larva";256;1
"Unit";"Zergling";"Larva";256;1
"Unit";"Zergling";"Larva";256;1
"Unit";"Zergling";"Larva";256;1
"Unit";"Zergling";"Larva";256;1
"Unit";"Zergling";"Larva";256;1
"Unit";"Zergling";"Larva";256;1
"Unit";"Zergling";"Larva";256;1
"Unit";"Zergling";"Larva";256;1
"Unit";"Zergling";"Larva";256;1
"Unit";"Baneling";"Zergling";266;0
"Unit";"Baneling";"Zergling";266;0
"Unit";"Baneling";"Zergling";266;0
"Unit";"Baneling";"Zergling";266;0
"Unit";"Baneling";"Zergling";266;0
"Unit";"Baneling";"Zergling";266;0
"Unit";"Mutalisk";"Larva";248;2
"Unit";"Zergling";"Larva";266;1
"Unit";"Zergling";"Larva";266;1
"Unit";"Zergling";"Larva";270;1
"Unit";"Zergling";"Larva";270;1
"Unit";"Zergling";"Larva";270;1
"Unit";"Zergling";"Larva";270;1
"Unit";"Zergling";"Larva";270;1
"Unit";"Zergling";"Larva";270;1
"Unit";"Zergling";"Larva";270;1
"Unit";"Zergling";"Larva";270;1
"Unit";"Baneling";"Zergling";302;0
"Unit";"Baneling";"Zergling";302;0
"Unit";"Baneling";"Zergling";302;0
"Unit";"Baneling";"Zergling";302;0
"Unit";"Baneling";"Zergling";302;0
"Unit";"Baneling";"Zergling";302;0
"Unit";"Baneling";"Zergling";302;0
"Unit";"Baneling";"Zergling";302;0
"Unit";"Baneling";"Zergling";302;0
"Unit";"Baneling";"Zergling";302;0
"Unit";"Baneling";"Zergling";302;0
"Unit";"Baneling";"Zergling";302;0
"Unit";"Baneling";"Zergling";302;0
"Unit";"Baneling";"Zergling";302;0
"Building";"CreepTumorQueen";NA;311;0
"Building";"CreepTumorQueen";NA;311;0
"Unit";"Zergling";"Larva";303;1
"Unit";"Zergling";"Larva";303;1
"Unit";"Zergling";"Larva";311;1
"Unit";"Zergling";"Larva";311;1
"Unit";"Zergling";"Larva";311;1
"Unit";"Zergling";"Larva";311;1
"Unit";"Zergling";"Larva";311;1
"Unit";"Zergling";"Larva";311;1
"Building";"CreepTumorQueen";NA;311;0
"Building";"Extractor";NA;302;0
"Building";"Extractor";NA;302;0
"Unit";"Zergling";"Larva";311;1
"Unit";"Zergling";"Larva";311;1
"Unit";"Zergling";"Larva";311;1
"Unit";"Zergling";"Larva";311;1
"Unit";"Overlord";"Larva";311;0
"Building";"InfestationPit";NA;302;0
"Unit";"Zergling";"Larva";311;1
"Unit";"Zergling";"Larva";311;1
"Unit";"Zergling";"Larva";311;1
"Unit";"Zergling";"Larva";311;1
"Unit";"Zergling";"Larva";311;1
"Unit";"Zergling";"Larva";311;1
"Unit";"Zergling";"Larva";311;1
"Unit";"Zergling";"Larva";311;1
"Building";"CreepTumorQueen";NA;319;0
"Building";"CreepTumorQueen";NA;319;0
"Building";"CreepTumorQueen";NA;319;0
"Unit";"Zergling";"Larva";311;1
"Unit";"Zergling";"Larva";311;1
"Unit";"Zergling";"Larva";311;1
"Unit";"Zergling";"Larva";311;1
"Unit";"Zergling";"Larva";323;1
"Unit";"Zergling";"Larva";323;1
"Unit";"Zergling";"Larva";323;1
"Unit";"Zergling";"Larva";323;1
"Unit";"Zergling";"Larva";323;1
"Unit";"Zergling";"Larva";323;1
"Unit";"Zergling";"Larva";323;1
"Unit";"Zergling";"Larva";323;1
"Unit";"Zergling";"Larva";323;1
"Unit";"Zergling";"Larva";323;1
"Unit";"Zergling";"Larva";323;1
"Unit";"Zergling";"Larva";323;1
"Unit";"Zergling";"Larva";323;1
"Unit";"Zergling";"Larva";323;1
"Building";"CreepTumor";NA;349;0
"Building";"CreepTumorQueen";NA;349;0
"Building";"CreepTumor";NA;349;0
"Building";"CreepTumor";NA;349;0
"Building";"CreepTumorQueen";NA;349;0
"Unit";"Baneling";"Zergling";349;0
"Unit";"Baneling";"Zergling";349;0
"Unit";"Baneling";"Zergling";349;0
"Unit";"Baneling";"Zergling";349;0
"Unit";"Baneling";"Zergling";349;0
"Unit";"Baneling";"Zergling";349;0
"Unit";"Baneling";"Zergling";349;0
"Unit";"Baneling";"Zergling";349;0
"Unit";"Baneling";"Zergling";349;0
"Unit";"Baneling";"Zergling";349;0
"Unit";"Baneling";"Zergling";349;0
"Unit";"Baneling";"Zergling";349;0
"Unit";"Baneling";"Zergling";349;0
"Unit";"Baneling";"Zergling";349;0
"Unit";"Baneling";"Zergling";349;0
"Unit";"Baneling";"Zergling";349;0
"Unit";"Baneling";"Zergling";349;0
"Unit";"Baneling";"Zergling";349;0
"Unit";"Baneling";"Zergling";349;0
"Unit";"Baneling";"Zergling";349;0
"Unit";"Baneling";"Zergling";349;0
"Unit";"Baneling";"Zergling";349;0
"Unit";"Baneling";"Zergling";349;0
"Unit";"Baneling";"Zergling";349;0
"Unit";"Baneling";"Zergling";349;0
"Unit";"Baneling";"Zergling";349;0
"Unit";"Baneling";"Zergling";349;0
"Unit";"Baneling";"Zergling";349;0
"Unit";"Baneling";"Zergling";349;0
"Unit";"Baneling";"Zergling";349;0
"Unit";"Baneling";"Zergling";349;0
"Unit";"Baneling";"Zergling";349;0
"Unit";"Baneling";"Zergling";349;0
"Unit";"Baneling";"Zergling";349;0
"Unit";"Baneling";"Zergling";349;0
"Unit";"Baneling";"Zergling";349;0
"Unit";"Baneling";"Zergling";349;0
"Unit";"Baneling";"Zergling";349;0
"Unit";"Baneling";"Zergling";349;0
"Unit";"Baneling";"Zergling";349;0
"Building";"CreepTumor";NA;349;0
"Unit";"Zergling";"Larva";349;1
"Unit";"Zergling";"Larva";349;1
"Unit";"Zergling";"Larva";349;1
"Unit";"Zergling";"Larva";349;1
"Unit";"Zergling";"Larva";349;1
"Unit";"Zergling";"Larva";349;1
"Unit";"Zergling";"Larva";349;1
"Unit";"Zergling";"Larva";349;1
"Unit";"Zergling";"Larva";349;1
"Unit";"Zergling";"Larva";349;1
"Unit";"Zergling";"Larva";349;1
"Unit";"Zergling";"Larva";349;1
"Unit";"Zergling";"Larva";349;1
"Unit";"Zergling";"Larva";349;1
"Unit";"Zergling";"Larva";349;1
"Unit";"Zergling";"Larva";349;1
"Building";"CreepTumorQueen";NA;349;0
"Building";"CreepTumorQueen";NA;349;0
"Unit";"Zergling";"Larva";349;1
"Unit";"Zergling";"Larva";349;1
"Unit";"Zergling";"Larva";349;1
"Unit";"Zergling";"Larva";349;1
"Unit";"Zergling";"Larva";349;1
"Unit";"Zergling";"Larva";349;1
"Unit";"Zergling";"Larva";349;1
"Unit";"Zergling";"Larva";349;1
"Unit";"Zergling";"Larva";353;1
"Unit";"Zergling";"Larva";353;1
"Unit";"Zergling";"Larva";353;1
"Unit";"Zergling";"Larva";353;1
"Unit";"Zergling";"Larva";353;1
"Unit";"Zergling";"Larva";353;1
"Unit";"Overlord";"Larva";353;0
"Unit";"Zergling";"Larva";353;1
"Unit";"Zergling";"Larva";353;1
"Unit";"Queen";"Hatchery";349;2
"Unit";"Corruptor";"Larva";381;2
"Unit";"Corruptor";"Larva";381;2
"Unit";"Corruptor";"Larva";381;2
"Upgrade";"ZergMeleeWeaponsLevel2";"EvolutionChamber";331;0
"Building";"Hatchery";NA;349;0
"Unit";"Corruptor";"Larva";383;2
"Unit";"Zergling";"Larva";389;1
"Unit";"Zergling";"Larva";389;1
"Unit";"Zergling";"Larva";391;1
"Unit";"Zergling";"Larva";391;1
"Unit";"Zergling";"Larva";391;1
"Unit";"Zergling";"Larva";391;1
"Unit";"Zergling";"Larva";391;1
"Unit";"Zergling";"Larva";391;1
"Unit";"Zergling";"Larva";391;1
"Unit";"Zergling";"Larva";391;1
"Unit";"Zergling";"Larva";391;1
"Unit";"Zergling";"Larva";391;1
"Unit";"Zergling";"Larva";391;1
"Unit";"Zergling";"Larva";391;1
"Unit";"Zergling";"Larva";391;1
"Unit";"Zergling";"Larva";391;1
"Unit";"Zergling";"Larva";391;1
"Unit";"Zergling";"Larva";391;1
"Unit";"Zergling";"Larva";391;1
"Unit";"Zergling";"Larva";391;1
"Unit";"Zergling";"Larva";391;1
"Unit";"Zergling";"Larva";391;1
"Unit";"Zergling";"Larva";391;1
"Unit";"Zergling";"Larva";391;1
"Unit";"Zergling";"Larva";391;1
"Unit";"Zergling";"Larva";391;1
"Unit";"Zergling";"Larva";391;1
"Unit";"Zergling";"Larva";391;1
"Unit";"Zergling";"Larva";391;1
"Unit";"Zergling";"Larva";391;1
"Unit";"Zergling";"Larva";391;1
"Unit";"Zergling";"Larva";391;1
"Unit";"Zergling";"Larva";391;1
"Unit";"Zergling";"Larva";391;1
"Unit";"Zergling";"Larva";391;1
"Unit";"Zergling";"Larva";391;1
"Unit";"Zergling";"Larva";391;1
"Unit";"Zergling";"Larva";391;1
"Unit";"Zergling";"Larva";391;1
"Unit";"Zergling";"Larva";391;1
"Unit";"Zergling";"Larva";391;1
"Unit";"Zergling";"Larva";391;1
"Unit";"Zergling";"Larva";391;1
"Unit";"Zergling";"Larva";391;1
"Unit";"Zergling";"Larva";391;1
"Unit";"Zergling";"Larva";391;1
"Unit";"Zergling";"Larva";391;1
"Unit";"Zergling";"Larva";391;1
"Unit";"Baneling";"Zergling";393;0
"Unit";"Baneling";"Zergling";405;0
"Unit";"Baneling";"Zergling";405;0
"Unit";"Baneling";"Zergling";407;0
"Unit";"Baneling";"Zergling";409;0
"Unit";"Baneling";"Zergling";409;0
"Building";"CreepTumor";NA;439;0
"Unit";"Baneling";"Zergling";439;0
"Unit";"Baneling";"Zergling";439;0
"Unit";"Corruptor";"Larva";391;2
"Unit";"Corruptor";"Larva";391;2
"Unit";"Corruptor";"Larva";391;2
"Building";"CreepTumor";NA;439;0
"Building";"CreepTumorQueen";NA;439;0
"Building";"CreepTumor";NA;439;0
"Building";"CreepTumorQueen";NA;439;0
"Building";"CreepTumor";NA;439;0
"Building";"CreepTumor";NA;439;0
"Building";"CreepTumor";NA;439;0
"Building";"CreepTumor";NA;439;0
"Unit";"Baneling";"Zergling";439;0
"Unit";"Baneling";"Zergling";441;0
"Unit";"Baneling";"Zergling";441;0
"Unit";"Baneling";"Zergling";441;0
"Unit";"Baneling";"Zergling";441;0
"Unit";"Baneling";"Zergling";441;0
"Unit";"Baneling";"Zergling";441;0
"Unit";"Baneling";"Zergling";441;0
"Unit";"Baneling";"Zergling";441;0
"Unit";"Baneling";"Zergling";441;0
"Unit";"Baneling";"Zergling";441;0
"Unit";"Baneling";"Zergling";441;0
"Building";"CreepTumor";NA;444;0
"Unit";"Zergling";"Larva";444;1
"Unit";"Zergling";"Larva";444;1
"Unit";"Zergling";"Larva";444;1
"Unit";"Zergling";"Larva";444;1
"Unit";"Zergling";"Larva";444;1
"Unit";"Zergling";"Larva";444;1
"Unit";"Zergling";"Larva";444;1
"Unit";"Zergling";"Larva";444;1
"Building";"UltraliskCavern";NA;391;0
"Unit";"Zergling";"Larva";450;1
"Unit";"Zergling";"Larva";450;1
"Building";"CreepTumor";NA;460;0
"Building";"CreepTumor";NA;460;0
"Building";"CreepTumor";NA;460;0
"Unit";"Zergling";"Larva";460;1
"Unit";"Zergling";"Larva";460;1
"Unit";"Zergling";"Larva";460;1
"Unit";"Zergling";"Larva";460;1
"Unit";"Zergling";"Larva";460;1
"Unit";"Zergling";"Larva";460;1
"Building";"CreepTumor";NA;460;0
"Unit";"Zergling";"Larva";460;1
"Unit";"Zergling";"Larva";460;1
"Building";"CreepTumor";NA;460;0
"Unit";"Zergling";"Larva";460;1
"Unit";"Zergling";"Larva";460;1
"Unit";"Ultralisk";"Larva";460;6
"Unit";"Ultralisk";"Larva";460;6
"Unit";"Ultralisk";"Larva";460;6
"Unit";"Ultralisk";"Larva";460;6
"Unit";"Zergling";"Larva";460;1
"Unit";"Zergling";"Larva";460;1
"Unit";"Zergling";"Larva";460;1
"Unit";"Zergling";"Larva";460;1
"Unit";"Zergling";"Larva";460;1
"Unit";"Zergling";"Larva";460;1
"Unit";"Zergling";"Larva";460;1
"Unit";"Zergling";"Larva";460;1
"Unit";"Zergling";"Larva";460;1
"Unit";"Zergling";"Larva";460;1
"Unit";"Baneling";"Zergling";462;0
"Unit";"Baneling";"Zergling";462;0
"Unit";"Baneling";"Zergling";462;0
"Unit";"Baneling";"Zergling";462;0
"Unit";"Baneling";"Zergling";462;0
"Unit";"Baneling";"Zergling";462;0
"Unit";"Baneling";"Zergling";462;0
"Unit";"Baneling";"Zergling";464;0
"Unit";"Baneling";"Zergling";464;0
"Building";"CreepTumor";NA;464;0
"Building";"CreepTumor";NA;464;0
"Unit";"Ultralisk";"Larva";460;6
"Building";"CreepTumor";NA;500;0
"Building";"CreepTumor";NA;500;0
"Unit";"Ultralisk";"Larva";460;6
"Building";"Hatchery";NA;458;0
"Unit";"Zergling";"Larva";510;1
"Unit";"Zergling";"Larva";510;1
"Upgrade";"ChitinousPlating";"UltraliskCavern";460;0
"Unit";"Baneling";"Zergling";516;0
"Unit";"Baneling";"Zergling";516;0
"Unit";"Baneling";"Zergling";516;0
"Unit";"Baneling";"Zergling";516;0
"Unit";"Baneling";"Zergling";516;0
"Unit";"Baneling";"Zergling";516;0
"Unit";"Baneling";"Zergling";516;0
"Unit";"Baneling";"Zergling";516;0
"Unit";"Baneling";"Zergling";516;0
"Unit";"Baneling";"Zergling";516;0
"Unit";"Baneling";"Zergling";516;0
"Unit";"Baneling";"Zergling";516;0
"Unit";"Baneling";"Zergling";516;0
"Unit";"Baneling";"Zergling";518;0
"Unit";"Baneling";"Zergling";518;0
"Unit";"Baneling";"Zergling";518;0
"Unit";"Baneling";"Zergling";518;0
"Unit";"Baneling";"Zergling";518;0
"Unit";"Baneling";"Zergling";518;0
"Unit";"Baneling";"Zergling";518;0
"Unit";"Baneling";"Zergling";518;0
"Unit";"Baneling";"Zergling";518;0
"Unit";"Baneling";"Zergling";518;0
"Unit";"Baneling";"Zergling";518;0
"Unit";"Baneling";"Zergling";518;0
"Unit";"Baneling";"Zergling";518;0
"Unit";"Baneling";"Zergling";518;0
"Unit";"Baneling";"Zergling";518;0
"Unit";"Baneling";"Zergling";518;0
"Unit";"Baneling";"Zergling";518;0
"Unit";"Baneling";"Zergling";518;0
"Unit";"Baneling";"Zergling";518;0
"Unit";"Baneling";"Zergling";518;0
"Unit";"Baneling";"Zergling";518;0
"Unit";"Baneling";"Zergling";518;0
"Unit";"Baneling";"Zergling";518;0
"Unit";"Baneling";"Zergling";518;0
"Unit";"Baneling";"Zergling";518;0
"Unit";"Baneling";"Zergling";518;0
"Unit";"Baneling";"Zergling";518;0
"Building";"CreepTumor";NA;518;0
"Building";"CreepTumor";NA;518;0
"Building";"CreepTumor";NA;518;0
"Upgrade";"ZergGroundArmorsLevel3";"EvolutionChamber";458;0
"Upgrade";"ZergMeleeWeaponsLevel3";"EvolutionChamber";458;0
"Unit";"Baneling";"Zergling";518;0
"Unit";"Baneling";"Zergling";518;0
"Unit";"Zergling";"Larva";518;1
"Unit";"Zergling";"Larva";518;1
"Unit";"Zergling";"Larva";518;1
"Unit";"Zergling";"Larva";518;1
"Unit";"Zergling";"Larva";518;1
"Unit";"Zergling";"Larva";518;1
"Unit";"Zergling";"Larva";518;1
"Unit";"Zergling";"Larva";518;1
"Unit";"Zergling";"Larva";518;1
"Unit";"Zergling";"Larva";518;1
"Unit";"Zergling";"Larva";518;1
"Unit";"Zergling";"Larva";518;1
"Unit";"Zergling";"Larva";518;1
"Unit";"Zergling";"Larva";518;1
"Unit";"Zergling";"Larva";518;1
"Unit";"Zergling";"Larva";518;1
"Unit";"Zergling";"Larva";518;1
"Unit";"Zergling";"Larva";518;1
"Unit";"Zergling";"Larva";518;1
"Unit";"Zergling";"Larva";518;1
"Unit";"Zergling";"Larva";518;1
"Unit";"Zergling";"Larva";518;1
"Unit";"Zergling";"Larva";518;1
"Unit";"Zergling";"Larva";518;1
"Unit";"Zergling";"Larva";518;1
"Unit";"Zergling";"Larva";518;1
"Unit";"Zergling";"Larva";518;1
"Unit";"Zergling";"Larva";518;1
"Unit";"Zergling";"Larva";518;1
"Unit";"Zergling";"Larva";518;1
"Unit";"Zergling";"Larva";518;1
"Unit";"Zergling";"Larva";518;1
"Unit";"Zergling";"Larva";518;1
"Unit";"Zergling";"Larva";518;1
"Unit";"Zergling";"Larva";518;1
"Unit";"Zergling";"Larva";518;1
"Unit";"Zergling";"Larva";518;1
"Unit";"Zergling";"Larva";518;1
"Unit";"Zergling";"Larva";518;1
"Unit";"Zergling";"Larva";518;1
"Unit";"Zergling";"Larva";518;1
"Unit";"Zergling";"Larva";518;1
"Unit";"Zergling";"Larva";518;1
"Unit";"Zergling";"Larva";518;1
"Unit";"Zergling";"Larva";518;1
"Unit";"Zergling";"Larva";518;1
"Unit";"Zergling";"Larva";518;1
"Unit";"Zergling";"Larva";518;1
"Unit";"Zergling";"Larva";518;1
"Unit";"Zergling";"Larva";518;1
"Unit";"Zergling";"Larva";518;1
"Unit";"Zergling";"Larva";518;1
"Unit";"Zergling";"Larva";518;1
"Unit";"Zergling";"Larva";518;1
"Unit";"Zergling";"Larva";518;1
"Unit";"Zergling";"Larva";518;1
"Unit";"Zergling";"Larva";518;1
"Unit";"Zergling";"Larva";518;1
"Unit";"Zergling";"Larva";518;1
"Unit";"Zergling";"Larva";518;1
"Unit";"Zergling";"Larva";518;1
"Unit";"Zergling";"Larva";518;1
"Unit";"Zergling";"Larva";518;1
"Unit";"Zergling";"Larva";518;1
"Unit";"Zergling";"Larva";518;1
"Unit";"Zergling";"Larva";518;1
"Unit";"Zergling";"Larva";518;1
"Unit";"Zergling";"Larva";518;1
"Unit";"Zergling";"Larva";518;1
"Unit";"Zergling";"Larva";518;1
"Unit";"Zergling";"Larva";518;1
"Unit";"Zergling";"Larva";518;1
"Unit";"Zergling";"Larva";518;1
"Unit";"Zergling";"Larva";518;1
"Unit";"Zergling";"Larva";518;1
"Unit";"Zergling";"Larva";518;1
"Unit";"Zergling";"Larva";518;1
"Unit";"Zergling";"Larva";518;1
"Unit";"Zergling";"Larva";518;1
"Unit";"Zergling";"Larva";518;1
"Unit";"Zergling";"Larva";518;1
"Unit";"Zergling";"Larva";518;1
"Unit";"Zergling";"Larva";518;1
"Unit";"Zergling";"Larva";518;1
"Unit";"Zergling";"Larva";518;1
"Unit";"Zergling";"Larva";518;1
"Unit";"Zergling";"Larva";518;1
"Unit";"Zergling";"Larva";518;1
"Unit";"Zergling";"Larva";518;1
"Unit";"Zergling";"Larva";518;1
"Unit";"Zergling";"Larva";518;1
"Unit";"Zergling";"Larva";518;1
"Unit";"Zergling";"Larva";518;1
"Unit";"Zergling";"Larva";518;1
"Unit";"Zergling";"Larva";518;1
"Unit";"Zergling";"Larva";518;1
"Unit";"Zergling";"Larva";518;1
"Unit";"Zergling";"Larva";518;1
"Unit";"Baneling";"Zergling";518;0
"Unit";"Baneling";"Zergling";518;0
"Unit";"Baneling";"Zergling";578;0
"Unit";"Baneling";"Zergling";596;0
"Unit";"Baneling";"Zergling";598;0
"Unit";"Baneling";"Zergling";598;0
"Unit";"Baneling";"Zergling";604;0
"Unit";"Baneling";"Zergling";604;0
"Unit";"Baneling";"Zergling";604;0
"Unit";"Baneling";"Zergling";604;0
"Unit";"Baneling";"Zergling";604;0
"Unit";"Baneling";"Zergling";604;0
"Unit";"Baneling";"Zergling";604;0
"Unit";"Baneling";"Zergling";604;0
"Unit";"Baneling";"Zergling";604;0
"Unit";"Baneling";"Zergling";604;0
"Unit";"Baneling";"Zergling";604;0
"Unit";"Baneling";"Zergling";604;0
"Unit";"Baneling";"Zergling";604;0
"Unit";"Baneling";"Zergling";604;0
"Unit";"Ultralisk";"Larva";518;6
"Unit";"Ultralisk";"Larva";518;6
"Unit";"Ultralisk";"Larva";518;6
"Unit";"Ultralisk";"Larva";518;6
"Unit";"Baneling";"Zergling";616;0
"Unit";"Baneling";"Zergling";616;0
"Unit";"Baneling";"Zergling";616;0
"Unit";"Baneling";"Zergling";616;0
"Unit";"Baneling";"Zergling";616;0
"Unit";"Baneling";"Zergling";616;0
"Unit";"Baneling";"Zergling";616;0
"Unit";"Baneling";"Zergling";616;0
"Unit";"Baneling";"Zergling";616;0
