"type";"unit_name";"on_building";"total_supply";"supply"
"Unit";"Overlord";"Larva";13;0
"Building";"Extractor";NA;18;0
"Building";"SpawningPool";NA;19;0
"Unit";"Overlord";"Larva";21;0
"Building";"Hatchery";NA;17;0
"Unit";"Zergling";"Larva";22;1
"Unit";"Zergling";"Larva";22;1
"Unit";"Zergling";"Larva";22;1
"Unit";"Zergling";"Larva";22;1
"Unit";"Queen";"Hatchery";22;2
"Unit";"Queen";"Hatchery";22;2
"Unit";"Queen";"Hatchery";31;2
"Unit";"Overlord";"Larva";36;0
"Building";"CreepTumorQueen";NA;42;0
"Unit";"Queen";"Hatchery";42;2
"Unit";"Queen";"Hatchery";42;2
"Unit";"Zergling";"Larva";42;1
"Unit";"Zergling";"Larva";42;1
"Unit";"Overlord";"Larva";42;0
"Unit";"Zergling";"Larva";42;1
"Unit";"Zergling";"Larva";42;1
"Unit";"Zergling";"Larva";42;1
"Unit";"Zergling";"Larva";42;1
"Unit";"Zergling";"Larva";42;1
"Unit";"Zergling";"Larva";42;1
"Building";"CreepTumorQueen";NA;42;0
"Unit";"Overlord";"Larva";42;0
"Building";"CreepTumor";NA;42;0
"Building";"Hatchery";NA;36;0
"Building";"CreepTumorQueen";NA;54;0
"Building";"CreepTumorQueen";NA;54;0
"Unit";"Overlord";"Larva";54;0
"Unit";"Overlord";"Larva";54;0
"Unit";"Overlord";"Larva";54;0
"Unit";"Overlord";"Larva";62;0
"Unit";"Overlord";"Larva";62;0
"Unit";"Queen";"Hatchery";54;2
"Building";"CreepTumorQueen";NA;62;0
"Building";"Extractor";NA;62;0
"Building";"CreepTumorQueen";NA;62;0
"Building";"CreepTumorQueen";NA;63;0
"Building";"CreepTumor";NA;63;0
"Building";"CreepTumor";NA;63;0
"Building";"CreepTumor";NA;65;0
"Building";"CreepTumor";NA;65;0
"Unit";"Zergling";"Larva";65;1
"Unit";"Zergling";"Larva";65;1
"Unit";"Zergling";"Larva";65;1
"Unit";"Zergling";"Larva";65;1
"Unit";"Zergling";"Larva";65;1
"Unit";"Zergling";"Larva";65;1
"Unit";"Zergling";"Larva";65;1
"Unit";"Zergling";"Larva";65;1
"Unit";"Zergling";"Larva";65;1
"Unit";"Zergling";"Larva";65;1
"Building";"EvolutionChamber";NA;62;0
"Building";"EvolutionChamber";NA;62;0
"Building";"CreepTumorQueen";NA;79;0
"Building";"CreepTumor";NA;79;0
"Unit";"Overlord";"Larva";69;0
"Unit";"Overlord";"Larva";69;0
"Building";"CreepTumor";NA;79;0
"Building";"CreepTumor";NA;79;0
"Building";"CreepTumor";NA;80;0
"Building";"CreepTumor";NA;80;0
"Building";"CreepTumor";NA;80;0
"Building";"BanelingNest";NA;69;0
"Building";"CreepTumor";NA;86;0
"Building";"CreepTumor";NA;86;0
"Building";"CreepTumor";NA;86;0
"Building";"CreepTumorQueen";NA;86;0
"Building";"CreepTumorQueen";NA;89;0
"Building";"CreepTumor";NA;86;0
"Building";"CreepTumor";NA;89;0
"Building";"CreepTumor";NA;89;0
"Building";"CreepTumorQueen";NA;89;0
"Building";"CreepTumorQueen";NA;89;0
"Building";"CreepTumor";NA;89;0
"Building";"CreepTumor";NA;89;0
"Building";"CreepTumor";NA;89;0
"Building";"CreepTumor";NA;89;0
"Building";"CreepTumor";NA;89;0
"Building";"CreepTumor";NA;91;0
"Unit";"Overlord";"Larva";102;0
"Building";"Extractor";NA;102;0
"Building";"Extractor";NA;102;0
"Building";"CreepTumor";NA;102;0
"Building";"CreepTumor";NA;102;0
"Building";"Extractor";NA;102;0
"Building";"Extractor";NA;102;0
"Unit";"Baneling";"Zergling";110;0
"Building";"CreepTumorQueen";NA;112;0
"Unit";"Baneling";"Zergling";110;0
"Unit";"Baneling";"Zergling";110;0
"Unit";"Baneling";"Zergling";110;0
"Unit";"Baneling";"Zergling";110;0
"Unit";"Baneling";"Zergling";110;0
"Unit";"Baneling";"Zergling";110;0
"Unit";"Baneling";"Zergling";110;0
"Unit";"Baneling";"Zergling";110;0
"Building";"CreepTumorQueen";NA;115;0
"Building";"CreepTumorQueen";NA;115;0
"Building";"CreepTumor";NA;110;0
"Building";"CreepTumor";NA;115;0
"Building";"CreepTumor";NA;115;0
"Unit";"Zergling";"Larva";115;1
"Unit";"Zergling";"Larva";115;1
"Building";"CreepTumor";NA;115;0
"Unit";"Zergling";"Larva";115;1
"Unit";"Zergling";"Larva";115;1
"Unit";"Zergling";"Larva";115;1
"Unit";"Zergling";"Larva";115;1
"Unit";"Zergling";"Larva";115;1
"Unit";"Zergling";"Larva";115;1
"Unit";"Zergling";"Larva";115;1
"Unit";"Zergling";"Larva";115;1
"Building";"CreepTumor";NA;115;0
"Unit";"Zergling";"Larva";115;1
"Unit";"Zergling";"Larva";115;1
"Building";"CreepTumor";NA;115;0
"Building";"CreepTumor";NA;115;0
"Building";"CreepTumor";NA;115;0
"Building";"CreepTumor";NA;115;0
"Upgrade";"ZergGroundArmorsLevel1";"EvolutionChamber";89;0
"Upgrade";"ZergMeleeWeaponsLevel1";"EvolutionChamber";89;0
"Unit";"Overlord";"Larva";115;0
"Unit";"Zergling";"Larva";127;1
"Unit";"Zergling";"Larva";127;1
"Building";"CreepTumor";NA;127;0
"Building";"CreepTumor";NA;127;0
"Building";"CreepTumor";NA;127;0
"Unit";"Zergling";"Larva";127;1
"Unit";"Zergling";"Larva";127;1
"Unit";"Zergling";"Larva";127;1
"Unit";"Zergling";"Larva";127;1
"Unit";"Zergling";"Larva";127;1
"Unit";"Zergling";"Larva";127;1
"Unit";"Zergling";"Larva";127;1
"Unit";"Zergling";"Larva";127;1
"Unit";"Zergling";"Larva";127;1
"Unit";"Zergling";"Larva";127;1
"Building";"CreepTumor";NA;127;0
"Building";"CreepTumor";NA;127;0
"Building";"CreepTumor";NA;128;0
"Building";"CreepTumor";NA;128;0
"Building";"Hatchery";NA;102;0
"Building";"CreepTumor";NA;128;0
"Building";"CreepTumor";NA;140;0
"Unit";"Overlord";"Larva";128;0
"Unit";"Overlord";"Larva";128;0
"Unit";"Baneling";"Zergling";140;0
"Unit";"Baneling";"Zergling";140;0
"Unit";"Baneling";"Zergling";140;0
"Building";"CreepTumor";NA;140;0
"Unit";"Baneling";"Zergling";140;0
"Building";"CreepTumor";NA;140;0
"Building";"Hatchery";NA;110;0
"Building";"CreepTumor";NA;140;0
"Building";"CreepTumor";NA;140;0
"Building";"CreepTumor";NA;140;0
"Building";"CreepTumor";NA;140;0
"Building";"CreepTumor";NA;140;0
"Unit";"Queen";"Hatchery";128;2
"Building";"CreepTumor";NA;140;0
"Building";"CreepTumor";NA;141;0
"Building";"CreepTumor";NA;141;0
"Building";"CreepTumor";NA;153;0
"Building";"Spire";NA;115;0
"Unit";"Overlord";"Larva";159;0
"Unit";"Zergling";"Larva";159;1
"Unit";"Zergling";"Larva";159;1
"Unit";"Mutalisk";"Larva";159;2
"Unit";"Zergling";"Larva";159;1
"Unit";"Zergling";"Larva";159;1
"Unit";"Zergling";"Larva";159;1
"Unit";"Zergling";"Larva";159;1
"Unit";"Zergling";"Larva";159;1
"Unit";"Zergling";"Larva";159;1
"Unit";"Zergling";"Larva";159;1
"Unit";"Zergling";"Larva";159;1
"Unit";"Zergling";"Larva";159;1
"Unit";"Zergling";"Larva";159;1
"Unit";"Mutalisk";"Larva";159;2
"Unit";"Mutalisk";"Larva";159;2
"Unit";"Mutalisk";"Larva";159;2
"Unit";"Mutalisk";"Larva";159;2
"Unit";"Mutalisk";"Larva";159;2
"Unit";"Mutalisk";"Larva";159;2
"Unit";"Mutalisk";"Larva";159;2
"Unit";"Mutalisk";"Larva";159;2
"Unit";"Mutalisk";"Larva";159;2
"Unit";"Mutalisk";"Larva";159;2
"Building";"CreepTumor";NA;159;0
"Building";"CreepTumor";NA;159;0
"Building";"CreepTumorQueen";NA;159;0
"Unit";"Overlord";"Larva";159;0
"Unit";"Overlord";"Larva";159;0
"Unit";"Overlord";"Larva";159;0
"Building";"Extractor";NA;159;0
"Building";"CreepTumor";NA;193;0
"Building";"Extractor";NA;159;0
"Building";"CreepTumor";NA;193;0
"Building";"CreepTumor";NA;193;0
"Building";"CreepTumor";NA;195;0
"Building";"CreepTumor";NA;195;0
"Unit";"Mutalisk";"Larva";193;2
"Unit";"Mutalisk";"Larva";193;2
"Unit";"Mutalisk";"Larva";193;2
"Unit";"Zergling";"Larva";195;1
"Unit";"Zergling";"Larva";195;1
"Unit";"Zergling";"Larva";195;1
"Unit";"Zergling";"Larva";195;1
"Unit";"Zergling";"Larva";195;1
"Unit";"Zergling";"Larva";195;1
"Unit";"Zergling";"Larva";195;1
"Unit";"Zergling";"Larva";195;1
"Unit";"Zergling";"Larva";195;1
"Unit";"Zergling";"Larva";195;1
"Unit";"Zergling";"Larva";195;1
"Unit";"Zergling";"Larva";195;1
"Unit";"Zergling";"Larva";195;1
"Unit";"Zergling";"Larva";195;1
"Unit";"Zergling";"Larva";195;1
"Unit";"Zergling";"Larva";195;1
"Unit";"Zergling";"Larva";195;1
"Unit";"Zergling";"Larva";195;1
"Unit";"Zergling";"Larva";195;1
"Unit";"Zergling";"Larva";195;1
"Unit";"Zergling";"Larva";195;1
"Unit";"Zergling";"Larva";195;1
"Unit";"Zergling";"Larva";195;1
"Unit";"Zergling";"Larva";195;1
"Unit";"Zergling";"Larva";195;1
"Unit";"Zergling";"Larva";195;1
"Unit";"Mutalisk";"Larva";195;2
"Building";"InfestationPit";NA;193;0
"Unit";"Zergling";"Larva";201;1
"Unit";"Zergling";"Larva";201;1
"Unit";"Overlord";"Larva";201;0
"Unit";"Zergling";"Larva";201;1
"Unit";"Zergling";"Larva";201;1
"Unit";"Zergling";"Larva";201;1
"Unit";"Zergling";"Larva";201;1
"Unit";"Zergling";"Larva";201;1
"Unit";"Zergling";"Larva";201;1
"Unit";"Zergling";"Larva";201;1
"Unit";"Zergling";"Larva";201;1
"Unit";"Zergling";"Larva";201;1
"Unit";"Zergling";"Larva";201;1
"Unit";"Zergling";"Larva";201;1
"Unit";"Zergling";"Larva";201;1
"Unit";"Zergling";"Larva";201;1
"Unit";"Zergling";"Larva";201;1
"Unit";"Zergling";"Larva";201;1
"Unit";"Zergling";"Larva";201;1
"Unit";"Zergling";"Larva";201;1
"Unit";"Zergling";"Larva";201;1
"Unit";"Mutalisk";"Larva";199;2
"Unit";"Mutalisk";"Larva";199;2
"Building";"CreepTumor";NA;229;0
"Building";"CreepTumor";NA;229;0
"Building";"CreepTumorQueen";NA;253;0
"Building";"CreepTumor";NA;253;0
"Building";"CreepTumor";NA;253;0
"Unit";"Overlord";"Larva";253;0
"Unit";"Overlord";"Larva";253;0
"Building";"CreepTumorQueen";NA;253;0
"Building";"CreepTumor";NA;253;0
"Building";"CreepTumor";NA;253;0
"Unit";"Zergling";"Larva";253;1
"Unit";"Zergling";"Larva";253;1
"Unit";"Zergling";"Larva";253;1
"Unit";"Zergling";"Larva";253;1
"Unit";"Zergling";"Larva";253;1
"Unit";"Zergling";"Larva";253;1
"Unit";"Zergling";"Larva";253;1
"Unit";"Zergling";"Larva";253;1
"Unit";"Zergling";"Larva";253;1
"Unit";"Zergling";"Larva";253;1
"Unit";"Zergling";"Larva";253;1
"Unit";"Zergling";"Larva";253;1
"Unit";"Zergling";"Larva";253;1
"Unit";"Zergling";"Larva";253;1
"Unit";"Zergling";"Larva";253;1
"Unit";"Zergling";"Larva";253;1
"Unit";"Zergling";"Larva";253;1
"Unit";"Zergling";"Larva";253;1
"Unit";"Zergling";"Larva";253;1
"Unit";"Zergling";"Larva";253;1
"Unit";"Zergling";"Larva";253;1
"Unit";"Zergling";"Larva";253;1
"Unit";"Zergling";"Larva";253;1
"Unit";"Zergling";"Larva";253;1
"Unit";"Zergling";"Larva";253;1
"Unit";"Zergling";"Larva";253;1
"Unit";"Zergling";"Larva";253;1
"Unit";"Zergling";"Larva";253;1
"Building";"Hatchery";NA;195;0
"Unit";"Zergling";"Larva";281;1
"Unit";"Zergling";"Larva";281;1
"Unit";"Zergling";"Larva";281;1
"Unit";"Zergling";"Larva";281;1
"Unit";"Zergling";"Larva";281;1
"Unit";"Zergling";"Larva";281;1
"Unit";"Zergling";"Larva";281;1
"Unit";"Zergling";"Larva";281;1
"Unit";"Zergling";"Larva";281;1
"Unit";"Zergling";"Larva";281;1
"Unit";"Zergling";"Larva";281;1
"Unit";"Zergling";"Larva";281;1
"Unit";"Zergling";"Larva";281;1
"Unit";"Zergling";"Larva";281;1
"Unit";"Zergling";"Larva";281;1
"Unit";"Zergling";"Larva";281;1
"Unit";"Zergling";"Larva";281;1
"Unit";"Zergling";"Larva";281;1
"Unit";"Zergling";"Larva";281;1
"Unit";"Zergling";"Larva";281;1
"Unit";"Zergling";"Larva";281;1
"Unit";"Zergling";"Larva";281;1
"Unit";"Zergling";"Larva";281;1
"Unit";"Zergling";"Larva";281;1
"Unit";"Zergling";"Larva";281;1
"Unit";"Zergling";"Larva";281;1
"Unit";"Zergling";"Larva";281;1
"Unit";"Zergling";"Larva";281;1
"Unit";"Zergling";"Larva";281;1
"Unit";"Zergling";"Larva";281;1
"Unit";"Zergling";"Larva";281;1
"Unit";"Zergling";"Larva";281;1
"Building";"CreepTumor";NA;281;0
"Unit";"Queen";"Hatchery";253;2
"Building";"CreepTumor";NA;281;0
"Building";"CreepTumor";NA;281;0
"Building";"CreepTumor";NA;281;0
"Building";"CreepTumor";NA;281;0
"Unit";"Zergling";"Larva";321;1
"Unit";"Zergling";"Larva";321;1
"Unit";"Zergling";"Larva";321;1
"Unit";"Zergling";"Larva";321;1
"Unit";"Zergling";"Larva";321;1
"Unit";"Zergling";"Larva";321;1
"Unit";"Zergling";"Larva";321;1
"Unit";"Zergling";"Larva";321;1
"Unit";"Zergling";"Larva";321;1
"Unit";"Zergling";"Larva";321;1
"Unit";"Zergling";"Larva";321;1
"Unit";"Zergling";"Larva";321;1
"Unit";"Zergling";"Larva";321;1
"Unit";"Zergling";"Larva";321;1
"Unit";"Zergling";"Larva";321;1
"Unit";"Zergling";"Larva";321;1
"Unit";"Zergling";"Larva";321;1
"Unit";"Zergling";"Larva";321;1
"Unit";"Zergling";"Larva";321;1
"Unit";"Zergling";"Larva";321;1
"Unit";"Zergling";"Larva";321;1
"Unit";"Zergling";"Larva";321;1
"Unit";"Zergling";"Larva";321;1
"Unit";"Zergling";"Larva";321;1
"Unit";"Zergling";"Larva";321;1
"Unit";"Zergling";"Larva";321;1
"Unit";"Zergling";"Larva";321;1
"Unit";"Zergling";"Larva";321;1
"Unit";"Zergling";"Larva";321;1
"Unit";"Zergling";"Larva";321;1
"Unit";"Zergling";"Larva";321;1
"Unit";"Zergling";"Larva";321;1
"Unit";"Zergling";"Larva";321;1
"Unit";"Zergling";"Larva";321;1
"Unit";"Zergling";"Larva";321;1
"Unit";"Zergling";"Larva";321;1
"Unit";"Zergling";"Larva";321;1
"Unit";"Zergling";"Larva";321;1
"Unit";"Zergling";"Larva";321;1
"Unit";"Zergling";"Larva";321;1
"Unit";"Zergling";"Larva";321;1
"Unit";"Zergling";"Larva";321;1
"Unit";"Zergling";"Larva";321;1
"Unit";"Zergling";"Larva";321;1
"Unit";"Zergling";"Larva";321;1
"Unit";"Zergling";"Larva";321;1
"Unit";"Zergling";"Larva";321;1
"Unit";"Zergling";"Larva";321;1
"Unit";"Zergling";"Larva";321;1
"Unit";"Zergling";"Larva";321;1
"Unit";"Zergling";"Larva";321;1
"Unit";"Zergling";"Larva";321;1
"Unit";"Zergling";"Larva";321;1
"Unit";"Zergling";"Larva";321;1
"Unit";"Zergling";"Larva";321;1
"Unit";"Zergling";"Larva";321;1
"Unit";"Zergling";"Larva";321;1
"Unit";"Zergling";"Larva";321;1
"Unit";"Zergling";"Larva";321;1
"Unit";"Zergling";"Larva";321;1
"Unit";"Zergling";"Larva";321;1
"Unit";"Zergling";"Larva";321;1
"Unit";"Zergling";"Larva";321;1
"Unit";"Zergling";"Larva";321;1
"Unit";"Zergling";"Larva";321;1
"Unit";"Zergling";"Larva";321;1
"Unit";"Zergling";"Larva";321;1
"Unit";"Zergling";"Larva";321;1
"Unit";"Zergling";"Larva";321;1
"Unit";"Zergling";"Larva";321;1
"Unit";"Baneling";"Zergling";321;0
"Unit";"Baneling";"Zergling";321;0
"Unit";"Baneling";"Zergling";321;0
"Unit";"Baneling";"Zergling";321;0
"Unit";"Baneling";"Zergling";321;0
"Unit";"Baneling";"Zergling";321;0
"Unit";"Baneling";"Zergling";321;0
"Unit";"Baneling";"Zergling";321;0
"Unit";"Baneling";"Zergling";321;0
"Unit";"Baneling";"Zergling";321;0
"Unit";"Baneling";"Zergling";321;0
"Unit";"Baneling";"Zergling";321;0
"Unit";"Baneling";"Zergling";321;0
"Unit";"Baneling";"Zergling";321;0
"Unit";"Baneling";"Zergling";321;0
"Unit";"Baneling";"Zergling";321;0
"Unit";"Baneling";"Zergling";321;0
"Unit";"Baneling";"Zergling";321;0
"Unit";"Baneling";"Zergling";321;0
"Unit";"Baneling";"Zergling";321;0
"Unit";"Baneling";"Zergling";321;0
"Unit";"Baneling";"Zergling";321;0
"Unit";"Baneling";"Zergling";321;0
"Unit";"Baneling";"Zergling";321;0
"Unit";"Baneling";"Zergling";321;0
"Unit";"Baneling";"Zergling";321;0
"Unit";"Baneling";"Zergling";321;0
"Unit";"Baneling";"Zergling";321;0
"Unit";"Baneling";"Zergling";321;0
"Unit";"Baneling";"Zergling";321;0
"Unit";"Baneling";"Zergling";321;0
"Unit";"Baneling";"Zergling";321;0
"Building";"Hatchery";NA;281;0
"Unit";"Zergling";"Larva";351;1
"Unit";"Zergling";"Larva";351;1
"Unit";"Zergling";"Larva";367;1
"Unit";"Zergling";"Larva";367;1
"Unit";"Zergling";"Larva";367;1
"Unit";"Zergling";"Larva";367;1
"Unit";"Zergling";"Larva";367;1
"Unit";"Zergling";"Larva";367;1
"Unit";"Zergling";"Larva";367;1
"Unit";"Zergling";"Larva";367;1
"Unit";"Zergling";"Larva";367;1
"Unit";"Zergling";"Larva";367;1
"Unit";"Zergling";"Larva";367;1
"Unit";"Zergling";"Larva";367;1
"Unit";"Zergling";"Larva";367;1
"Unit";"Zergling";"Larva";367;1
"Building";"CreepTumor";NA;407;0
"Building";"CreepTumor";NA;407;0
"Unit";"Viper";"Larva";367;3
"Unit";"Viper";"Larva";367;3
"Building";"UltraliskCavern";NA;321;0
"Upgrade";"ZergMeleeWeaponsLevel2";"EvolutionChamber";281;0
"Upgrade";"ZergGroundArmorsLevel2";"EvolutionChamber";281;0
"Building";"CreepTumor";NA;407;0
"Building";"CreepTumorQueen";NA;413;0
"Unit";"Overlord";"Larva";413;0
"Building";"CreepTumorQueen";NA;413;0
"Building";"CreepTumor";NA;413;0
"Building";"CreepTumor";NA;413;0
"Building";"CreepTumor";NA;413;0
"Building";"CreepTumorQueen";NA;413;0
"Building";"CreepTumor";NA;413;0
"Building";"CreepTumor";NA;413;0
"Building";"CreepTumor";NA;413;0
"Building";"CreepTumorQueen";NA;413;0
"Building";"CreepTumorQueen";NA;413;0
"Building";"CreepTumorQueen";NA;413;0
"Building";"Spire";NA;413;0
"Upgrade";"ChitinousPlating";"UltraliskCavern";413;0
"Building";"Extractor";NA;413;0
"Unit";"Zergling";"Larva";413;1
"Unit";"Zergling";"Larva";413;1
"Unit";"Zergling";"Larva";413;1
"Unit";"Zergling";"Larva";413;1
"Unit";"Ultralisk";"Larva";413;6
"Unit";"Ultralisk";"Larva";413;6
"Building";"Extractor";NA;413;0
"Building";"CreepTumor";NA;417;0
"Building";"CreepTumor";NA;417;0
"Building";"CreepTumor";NA;417;0
"Building";"CreepTumor";NA;423;0
"Building";"CreepTumor";NA;429;0
"Upgrade";"ZergMeleeWeaponsLevel3";"EvolutionChamber";413;0
"Upgrade";"ZergGroundArmorsLevel3";"EvolutionChamber";413;0
"Unit";"Zergling";"Larva";429;1
"Unit";"Zergling";"Larva";429;1
"Unit";"Zergling";"Larva";429;1
"Unit";"Zergling";"Larva";429;1
"Unit";"Zergling";"Larva";429;1
"Unit";"Zergling";"Larva";429;1
"Unit";"Zergling";"Larva";429;1
"Unit";"Zergling";"Larva";429;1
"Unit";"Zergling";"Larva";429;1
"Unit";"Zergling";"Larva";429;1
"Unit";"Zergling";"Larva";429;1
"Unit";"Zergling";"Larva";429;1
"Unit";"Zergling";"Larva";429;1
"Unit";"Zergling";"Larva";429;1
"Unit";"Zergling";"Larva";429;1
"Unit";"Zergling";"Larva";429;1
"Unit";"Zergling";"Larva";429;1
"Unit";"Zergling";"Larva";429;1
"Unit";"Zergling";"Larva";429;1
"Unit";"Zergling";"Larva";429;1
"Unit";"Zergling";"Larva";429;1
"Unit";"Zergling";"Larva";429;1
"Unit";"Zergling";"Larva";429;1
"Unit";"Zergling";"Larva";429;1
"Unit";"Zergling";"Larva";429;1
"Unit";"Zergling";"Larva";429;1
"Unit";"Zergling";"Larva";429;1
"Unit";"Zergling";"Larva";429;1
"Unit";"Zergling";"Larva";429;1
"Unit";"Zergling";"Larva";429;1
"Unit";"Zergling";"Larva";429;1
"Unit";"Zergling";"Larva";429;1
"Unit";"Zergling";"Larva";429;1
"Unit";"Zergling";"Larva";429;1
"Unit";"Baneling";"Zergling";429;0
"Unit";"Baneling";"Zergling";429;0
"Unit";"Baneling";"Zergling";429;0
"Unit";"Baneling";"Zergling";429;0
"Unit";"Baneling";"Zergling";429;0
"Unit";"Baneling";"Zergling";429;0
"Unit";"Baneling";"Zergling";429;0
"Unit";"Baneling";"Zergling";429;0
"Unit";"Baneling";"Zergling";429;0
"Unit";"Corruptor";"Larva";429;2
"Unit";"Corruptor";"Larva";429;2
"Unit";"Corruptor";"Larva";429;2
"Unit";"Corruptor";"Larva";429;2
"Unit";"Corruptor";"Larva";429;2
"Unit";"Corruptor";"Larva";429;2
"Unit";"Corruptor";"Larva";429;2
"Unit";"Corruptor";"Larva";429;2
"Unit";"Zergling";"Larva";429;1
"Unit";"Zergling";"Larva";429;1
"Unit";"Zergling";"Larva";429;1
"Unit";"Zergling";"Larva";429;1
"Unit";"Zergling";"Larva";429;1
"Unit";"Zergling";"Larva";429;1
"Unit";"Zergling";"Larva";429;1
"Unit";"Zergling";"Larva";429;1
"Unit";"Zergling";"Larva";429;1
"Unit";"Zergling";"Larva";429;1
"Unit";"Zergling";"Larva";429;1
"Unit";"Zergling";"Larva";429;1
"Unit";"Zergling";"Larva";429;1
"Unit";"Zergling";"Larva";429;1
"Unit";"Zergling";"Larva";429;1
"Unit";"Zergling";"Larva";429;1
"Unit";"Zergling";"Larva";429;1
"Unit";"Zergling";"Larva";429;1
"Unit";"Zergling";"Larva";429;1
"Unit";"Zergling";"Larva";429;1
"Unit";"Zergling";"Larva";429;1
"Unit";"Zergling";"Larva";429;1
"Unit";"Ultralisk";"Larva";429;6
"Unit";"Ultralisk";"Larva";429;6
"Unit";"Ultralisk";"Larva";429;6
"Unit";"Ultralisk";"Larva";429;6
"Unit";"Ultralisk";"Larva";429;6
"Unit";"Ultralisk";"Larva";429;6
"Unit";"Zergling";"Larva";537;1
"Unit";"Zergling";"Larva";537;1
"Unit";"Zergling";"Larva";537;1
"Unit";"Zergling";"Larva";537;1
"Unit";"Zergling";"Larva";537;1
"Unit";"Zergling";"Larva";537;1
"Unit";"Zergling";"Larva";537;1
"Unit";"Zergling";"Larva";537;1
"Building";"CreepTumor";NA;537;0
"Building";"CreepTumor";NA;537;0
"Building";"CreepTumor";NA;537;0
"Unit";"Zergling";"Larva";545;1
"Unit";"Zergling";"Larva";545;1
"Unit";"Zergling";"Larva";545;1
"Unit";"Zergling";"Larva";545;1
"Unit";"Zergling";"Larva";545;1
"Unit";"Zergling";"Larva";545;1
"Unit";"Zergling";"Larva";545;1
"Unit";"Zergling";"Larva";545;1
"Unit";"Zergling";"Larva";545;1
"Unit";"Zergling";"Larva";545;1
"Unit";"Zergling";"Larva";545;1
"Unit";"Zergling";"Larva";545;1
"Unit";"Zergling";"Larva";545;1
"Unit";"Zergling";"Larva";545;1
"Unit";"Zergling";"Larva";545;1
"Unit";"Zergling";"Larva";545;1
"Unit";"Zergling";"Larva";545;1
"Unit";"Zergling";"Larva";545;1
"Unit";"Zergling";"Larva";545;1
"Unit";"Zergling";"Larva";545;1
"Unit";"Zergling";"Larva";545;1
"Unit";"Zergling";"Larva";545;1
"Unit";"Zergling";"Larva";545;1
"Unit";"Zergling";"Larva";545;1
"Unit";"Zergling";"Larva";545;1
"Unit";"Zergling";"Larva";545;1
"Unit";"Zergling";"Larva";545;1
"Unit";"Zergling";"Larva";545;1
"Unit";"Zergling";"Larva";545;1
"Unit";"Zergling";"Larva";545;1
"Unit";"Zergling";"Larva";545;1
"Unit";"Zergling";"Larva";545;1
"Unit";"Zergling";"Larva";545;1
"Unit";"Zergling";"Larva";545;1
"Unit";"Zergling";"Larva";545;1
"Unit";"Zergling";"Larva";545;1
"Unit";"Zergling";"Larva";545;1
"Unit";"Zergling";"Larva";545;1
"Unit";"Zergling";"Larva";545;1
"Unit";"Zergling";"Larva";545;1
"Unit";"Zergling";"Larva";545;1
"Unit";"Zergling";"Larva";545;1
"Unit";"Zergling";"Larva";545;1
"Unit";"Zergling";"Larva";545;1
