"type";"unit_name";"on_building";"total_supply";"supply"
"Unit";"Overlord";"Larva";13;0
"Building";"Extractor";NA;18;0
"Unit";"Overlord";"Larva";21;0
"Building";"SpawningPool";NA;19;0
"Building";"Hatchery";NA;17;0
"Unit";"Zergling";"Larva";22;1
"Unit";"Zergling";"Larva";22;1
"Unit";"Zergling";"Larva";23;1
"Unit";"Zergling";"Larva";23;1
"Unit";"Queen";"Hatchery";22;2
"Unit";"Queen";"Hatchery";23;2
"Unit";"Overlord";"Larva";31;0
"Unit";"Overlord";"Larva";35;0
"Unit";"Queen";"Hatchery";35;2
"Building";"CreepTumorQueen";NA;41;0
"Unit";"Overlord";"Larva";39;0
"Unit";"Overlord";"Larva";46;0
"Unit";"Queen";"Hatchery";37;2
"Unit";"Zergling";"Larva";46;1
"Unit";"Zergling";"Larva";46;1
"Unit";"Zergling";"Larva";46;1
"Unit";"Zergling";"Larva";46;1
"Unit";"Overlord";"Larva";48;0
"Unit";"Overlord";"Larva";48;0
"Unit";"Zergling";"Larva";48;1
"Unit";"Zergling";"Larva";48;1
"Unit";"Zergling";"Larva";48;1
"Unit";"Zergling";"Larva";48;1
"Unit";"Zergling";"Larva";48;1
"Unit";"Zergling";"Larva";48;1
"Building";"CreepTumorQueen";NA;54;0
"Building";"CreepTumor";NA;54;0
"Building";"CreepTumorQueen";NA;54;0
"Building";"BanelingNest";NA;46;0
"Unit";"Zergling";"Larva";63;1
"Unit";"Zergling";"Larva";63;1
"Building";"Extractor";NA;66;0
"Building";"CreepTumor";NA;68;0
"Unit";"Zergling";"Larva";68;1
"Unit";"Zergling";"Larva";68;1
"Unit";"Zergling";"Larva";68;1
"Unit";"Zergling";"Larva";68;1
"Unit";"Zergling";"Larva";68;1
"Unit";"Zergling";"Larva";68;1
"Unit";"Zergling";"Larva";68;1
"Unit";"Zergling";"Larva";68;1
"Unit";"Queen";"Hatchery";63;2
"Unit";"Overlord";"Larva";68;0
"Unit";"Overlord";"Larva";68;0
"Building";"Extractor";NA;82;0
"Unit";"Zergling";"Larva";82;1
"Unit";"Zergling";"Larva";82;1
"Building";"EvolutionChamber";NA;82;0
"Building";"EvolutionChamber";NA;82;0
"Building";"Hatchery";NA;66;0
"Building";"CreepTumor";NA;93;0
"Building";"Extractor";NA;93;0
"Building";"CreepTumorQueen";NA;95;0
"Building";"CreepTumorQueen";NA;95;0
"Building";"SporeCrawler";NA;96;0
"Building";"SporeCrawler";NA;96;0
"Unit";"Zergling";"Larva";100;1
"Unit";"Zergling";"Larva";100;1
"Unit";"Zergling";"Larva";100;1
"Unit";"Zergling";"Larva";100;1
"Unit";"Zergling";"Larva";100;1
"Unit";"Zergling";"Larva";100;1
"Unit";"Baneling";"Zergling";100;0
"Unit";"Baneling";"Zergling";100;0
"Building";"SporeCrawler";NA;100;0
"Unit";"Queen";"Hatchery";100;2
"Unit";"Zergling";"Larva";109;1
"Unit";"Zergling";"Larva";109;1
"Unit";"Overlord";"Larva";103;0
"Unit";"Zergling";"Larva";109;1
"Unit";"Zergling";"Larva";109;1
"Unit";"Zergling";"Larva";109;1
"Unit";"Zergling";"Larva";109;1
"Unit";"Zergling";"Larva";109;1
"Unit";"Zergling";"Larva";109;1
"Unit";"Zergling";"Larva";109;1
"Unit";"Zergling";"Larva";109;1
"Unit";"Zergling";"Larva";109;1
"Unit";"Zergling";"Larva";109;1
"Unit";"Zergling";"Larva";109;1
"Unit";"Zergling";"Larva";109;1
"Unit";"Zergling";"Larva";109;1
"Unit";"Zergling";"Larva";109;1
"Building";"CreepTumor";NA;109;0
"Building";"CreepTumor";NA;109;0
"Building";"CreepTumor";NA;109;0
"Building";"CreepTumor";NA;109;0
"Building";"HydraliskDen";NA;103;0
"Building";"CreepTumorQueen";NA;129;0
"Unit";"Overlord";"Larva";135;0
"Unit";"Overlord";"Larva";135;0
"Building";"CreepTumor";NA;135;0
"Building";"CreepTumor";NA;135;0
"Building";"CreepTumor";NA;135;0
"Building";"Extractor";NA;135;0
"Unit";"Overlord";"Larva";135;0
"Unit";"Overlord";"Larva";135;0
"Unit";"Overlord";"Larva";135;0
"Building";"Extractor";NA;135;0
"Building";"CreepTumor";NA;135;0
"Building";"CreepTumor";NA;135;0
"Building";"CreepTumorQueen";NA;135;0
"Unit";"Overlord";"Larva";135;0
"Upgrade";"ZergMeleeWeaponsLevel1";"EvolutionChamber";100;0
"Upgrade";"ZergGroundArmorsLevel1";"EvolutionChamber";100;0
"Unit";"Baneling";"Zergling";137;0
"Unit";"Baneling";"Zergling";137;0
"Unit";"Baneling";"Zergling";137;0
"Unit";"Baneling";"Zergling";137;0
"Unit";"Baneling";"Zergling";137;0
"Unit";"Baneling";"Zergling";137;0
"Unit";"Hydralisk";"Larva";137;2
"Unit";"Hydralisk";"Larva";137;2
"Unit";"Hydralisk";"Larva";137;2
"Unit";"Hydralisk";"Larva";137;2
"Unit";"Hydralisk";"Larva";137;2
"Unit";"Hydralisk";"Larva";137;2
"Unit";"Hydralisk";"Larva";137;2
"Unit";"Hydralisk";"Larva";137;2
"Building";"CreepTumor";NA;154;0
"Building";"CreepTumor";NA;154;0
"Building";"CreepTumor";NA;154;0
"Building";"Hatchery";NA;135;0
"Upgrade";"EvolveGroovedSpines";"HydraliskDen";137;0
"Building";"CreepTumor";NA;156;0
"Building";"CreepTumor";NA;156;0
"Building";"CreepTumorQueen";NA;156;0
"Unit";"Hydralisk";"Larva";156;2
"Unit";"Hydralisk";"Larva";156;2
"Unit";"Hydralisk";"Larva";156;2
"Unit";"Zergling";"Larva";167;1
"Unit";"Zergling";"Larva";167;1
"Unit";"Zergling";"Larva";167;1
"Unit";"Zergling";"Larva";167;1
"Unit";"Zergling";"Larva";167;1
"Unit";"Zergling";"Larva";167;1
"Unit";"Zergling";"Larva";167;1
"Unit";"Zergling";"Larva";167;1
"Unit";"Zergling";"Larva";167;1
"Unit";"Zergling";"Larva";167;1
"Unit";"Zergling";"Larva";167;1
"Unit";"Zergling";"Larva";167;1
"Building";"InfestationPit";NA;156;0
"Building";"Hatchery";NA;140;0
"Building";"BanelingNest";NA;156;0
"Unit";"Hydralisk";"Larva";173;2
"Unit";"Hydralisk";"Larva";173;2
"Unit";"Hydralisk";"Larva";173;2
"Unit";"Hydralisk";"Larva";173;2
"Unit";"Zergling";"Larva";185;1
"Unit";"Zergling";"Larva";185;1
"Unit";"Zergling";"Larva";185;1
"Unit";"Zergling";"Larva";185;1
"Unit";"Zergling";"Larva";185;1
"Unit";"Zergling";"Larva";185;1
"Unit";"Zergling";"Larva";185;1
"Unit";"Zergling";"Larva";185;1
"Unit";"Zergling";"Larva";185;1
"Unit";"Zergling";"Larva";185;1
"Unit";"Zergling";"Larva";185;1
"Unit";"Zergling";"Larva";185;1
"Unit";"Zergling";"Larva";185;1
"Unit";"Zergling";"Larva";185;1
"Unit";"Zergling";"Larva";185;1
"Unit";"Zergling";"Larva";185;1
"Unit";"Zergling";"Larva";185;1
"Unit";"Zergling";"Larva";185;1
"Unit";"Zergling";"Larva";185;1
"Unit";"Zergling";"Larva";185;1
"Unit";"Zergling";"Larva";185;1
"Unit";"Zergling";"Larva";185;1
"Unit";"Zergling";"Larva";185;1
"Unit";"Zergling";"Larva";185;1
"Unit";"Baneling";"Zergling";193;0
"Unit";"Baneling";"Zergling";193;0
"Unit";"Baneling";"Zergling";193;0
"Unit";"Baneling";"Zergling";193;0
"Unit";"Overlord";"Larva";193;0
"Unit";"Overlord";"Larva";193;0
"Unit";"Overlord";"Larva";193;0
"Unit";"Overlord";"Larva";193;0
"Unit";"Baneling";"Zergling";213;0
"Unit";"Baneling";"Zergling";217;0
"Unit";"Baneling";"Zergling";217;0
"Unit";"Baneling";"Zergling";217;0
"Unit";"Baneling";"Zergling";217;0
"Unit";"Baneling";"Zergling";217;0
"Unit";"Baneling";"Zergling";217;0
"Unit";"Zergling";"Larva";217;1
"Unit";"Zergling";"Larva";217;1
"Unit";"Zergling";"Larva";217;1
"Unit";"Zergling";"Larva";217;1
"Unit";"Zergling";"Larva";217;1
"Unit";"Zergling";"Larva";217;1
"Upgrade";"ZergMeleeWeaponsLevel2";"EvolutionChamber";156;0
"Upgrade";"ZergGroundArmorsLevel2";"EvolutionChamber";167;0
"Upgrade";"EvolveMuscularAugments";"HydraliskDen";193;0
"Unit";"Zergling";"Larva";219;1
"Unit";"Zergling";"Larva";219;1
"Unit";"Zergling";"Larva";219;1
"Unit";"Zergling";"Larva";219;1
"Unit";"Zergling";"Larva";219;1
"Unit";"Zergling";"Larva";219;1
"Unit";"Zergling";"Larva";219;1
"Unit";"Zergling";"Larva";219;1
"Unit";"Zergling";"Larva";219;1
"Unit";"Zergling";"Larva";219;1
"Unit";"Zergling";"Larva";219;1
"Unit";"Zergling";"Larva";219;1
"Unit";"Zergling";"Larva";219;1
"Unit";"Zergling";"Larva";219;1
"Unit";"Zergling";"Larva";219;1
"Unit";"Zergling";"Larva";219;1
"Unit";"Zergling";"Larva";219;1
"Unit";"Zergling";"Larva";219;1
"Unit";"Zergling";"Larva";219;1
"Unit";"Zergling";"Larva";219;1
"Unit";"Zergling";"Larva";219;1
"Unit";"Zergling";"Larva";219;1
"Unit";"Zergling";"Larva";219;1
"Unit";"Zergling";"Larva";219;1
"Unit";"Zergling";"Larva";219;1
"Unit";"Zergling";"Larva";219;1
"Unit";"Zergling";"Larva";219;1
"Unit";"Zergling";"Larva";219;1
"Unit";"Zergling";"Larva";219;1
"Unit";"Zergling";"Larva";219;1
"Unit";"Zergling";"Larva";219;1
"Unit";"Zergling";"Larva";219;1
"Unit";"Zergling";"Larva";219;1
"Unit";"Zergling";"Larva";219;1
"Unit";"Zergling";"Larva";219;1
"Unit";"Zergling";"Larva";219;1
"Unit";"Baneling";"Zergling";223;0
"Building";"Hatchery";NA;185;0
"Unit";"Baneling";"Zergling";223;0
"Unit";"Baneling";"Zergling";223;0
"Unit";"Baneling";"Zergling";223;0
"Unit";"Baneling";"Zergling";223;0
"Unit";"Baneling";"Zergling";223;0
"Unit";"Baneling";"Zergling";223;0
"Unit";"Baneling";"Zergling";223;0
"Unit";"Baneling";"Zergling";223;0
"Unit";"Baneling";"Zergling";223;0
"Unit";"Baneling";"Zergling";223;0
"Unit";"Zergling";"Larva";259;1
"Unit";"Zergling";"Larva";259;1
"Unit";"Zergling";"Larva";259;1
"Unit";"Zergling";"Larva";259;1
"Unit";"Zergling";"Larva";259;1
"Unit";"Zergling";"Larva";259;1
"Unit";"Zergling";"Larva";259;1
"Unit";"Zergling";"Larva";259;1
"Unit";"Zergling";"Larva";259;1
"Unit";"Zergling";"Larva";259;1
"Unit";"Zergling";"Larva";259;1
"Unit";"Zergling";"Larva";259;1
"Unit";"Zergling";"Larva";259;1
"Unit";"Zergling";"Larva";259;1
"Unit";"Zergling";"Larva";259;1
"Unit";"Zergling";"Larva";259;1
"Unit";"Zergling";"Larva";259;1
"Unit";"Zergling";"Larva";259;1
"Unit";"Zergling";"Larva";259;1
"Unit";"Zergling";"Larva";259;1
"Unit";"Zergling";"Larva";259;1
"Unit";"Zergling";"Larva";259;1
