"type";"unit_name";"on_building";"total_supply";"supply"
"Unit";"Overlord";"Larva";12;0
"Building";"SpawningPool";NA;16;0
"Building";"Extractor";NA;19;0
"Unit";"Zergling";"Larva";21;1
"Unit";"Zergling";"Larva";21;1
"Unit";"Overlord";"Larva";21;0
"Unit";"Queen";"Hatchery";21;2
"Building";"Hatchery";NA;19;0
"Unit";"Queen";"Hatchery";24;2
"Building";"CreepTumorQueen";NA;32;0
"Unit";"Queen";"Hatchery";28;2
"Unit";"Overlord";"Larva";33;0
"Unit";"Overlord";"Larva";40;0
"Building";"CreepTumor";NA;40;0
"Building";"CreepTumorQueen";NA;41;0
"Unit";"Zergling";"Larva";43;1
"Unit";"Zergling";"Larva";43;1
"Unit";"Zergling";"Larva";43;1
"Unit";"Zergling";"Larva";43;1
"Building";"Extractor";NA;42;0
"Building";"RoachWarren";NA;41;0
"Unit";"Overlord";"Larva";46;0
"Building";"CreepTumorQueen";NA;52;0
"Building";"CreepTumor";NA;56;0
"Building";"CreepTumor";NA;56;0
"Building";"Extractor";NA;55;0
"Building";"Extractor";NA;56;0
"Unit";"Overlord";"Larva";61;0
"Building";"CreepTumor";NA;62;0
"Unit";"Overlord";"Larva";62;0
"Building";"CreepTumorQueen";NA;64;0
"Unit";"Roach";"Larva";62;2
"Unit";"Roach";"Larva";62;2
"Building";"CreepTumor";NA;64;0
"Unit";"Roach";"Larva";64;2
"Unit";"Roach";"Larva";64;2
"Unit";"Roach";"Larva";64;2
"Building";"CreepTumor";NA;64;0
"Building";"CreepTumorQueen";NA;76;0
"Unit";"Overlord";"Larva";69;0
"Building";"CreepTumor";NA;76;0
"Building";"Spire";NA;56;0
"Unit";"Roach";"Larva";69;2
"Unit";"Zergling";"Larva";76;1
"Unit";"Zergling";"Larva";76;1
"Building";"CreepTumor";NA;78;0
"Unit";"Roach";"Larva";76;2
"Unit";"Roach";"Larva";76;2
"Unit";"Roach";"Larva";76;2
"Unit";"Roach";"Larva";76;2
"Unit";"Roach";"Larva";76;2
"Unit";"Roach";"Larva";76;2
"Upgrade";"GlialReconstitution";"RoachWarren";64;0
"Unit";"Overlord";"Larva";80;0
"Unit";"Overlord";"Larva";80;0
"Building";"CreepTumor";NA;92;0
"Building";"CreepTumor";NA;92;0
"Building";"CreepTumor";NA;92;0
"Building";"CreepTumor";NA;92;0
"Unit";"Zergling";"Larva";92;1
"Unit";"Zergling";"Larva";92;1
"Building";"Hatchery";NA;76;0
"Unit";"Mutalisk";"Larva";92;2
"Unit";"Mutalisk";"Larva";92;2
"Unit";"Mutalisk";"Larva";92;2
"Unit";"Mutalisk";"Larva";92;2
"Unit";"Mutalisk";"Larva";92;2
"Unit";"Mutalisk";"Larva";92;2
"Building";"CreepTumor";NA;94;0
"Building";"CreepTumor";NA;94;0
"Building";"CreepTumor";NA;96;0
"Unit";"Mutalisk";"Larva";94;2
"Building";"CreepTumor";NA;96;0
"Building";"CreepTumor";NA;96;0
"Building";"EvolutionChamber";NA;94;0
"Building";"EvolutionChamber";NA;94;0
"Unit";"Queen";"Hatchery";94;2
"Unit";"Queen";"Hatchery";94;2
"Unit";"Queen";"Hatchery";94;2
"Building";"CreepTumor";NA;117;0
"Building";"CreepTumorQueen";NA;117;0
"Unit";"Overlord";"Larva";117;0
"Building";"CreepTumorQueen";NA;128;0
"Unit";"Overlord";"Larva";128;0
"Building";"CreepTumorQueen";NA;136;0
"Unit";"Overlord";"Larva";136;0
"Building";"CreepTumorQueen";NA;136;0
"Unit";"Zergling";"Larva";136;1
"Unit";"Zergling";"Larva";136;1
"Building";"Extractor";NA;136;0
"Building";"Extractor";NA;136;0
"Unit";"Roach";"Larva";137;2
"Unit";"Roach";"Larva";137;2
"Unit";"Overlord";"Larva";139;0
"Unit";"Roach";"Larva";137;2
"Unit";"Roach";"Larva";137;2
"Unit";"Roach";"Larva";137;2
"Unit";"Roach";"Larva";137;2
"Unit";"Roach";"Larva";137;2
"Unit";"Roach";"Larva";137;2
"Building";"CreepTumor";NA;139;0
"Building";"CreepTumor";NA;139;0
"Building";"CreepTumor";NA;139;0
"Building";"CreepTumor";NA;139;0
"Building";"CreepTumor";NA;139;0
"Building";"CreepTumor";NA;139;0
"Building";"CreepTumorQueen";NA;141;0
"Unit";"Roach";"Larva";139;2
"Building";"CreepTumor";NA;144;0
"Building";"CreepTumorQueen";NA;144;0
"Unit";"Overlord";"Larva";141;0
"Unit";"Roach";"Larva";139;2
"Unit";"Roach";"Larva";139;2
"Unit";"Roach";"Larva";139;2
"Unit";"Roach";"Larva";139;2
"Building";"CreepTumor";NA;158;0
"Building";"CreepTumor";NA;158;0
"Unit";"Overlord";"Larva";146;0
"Unit";"Overlord";"Larva";158;0
"Building";"InfestationPit";NA;139;0
"Unit";"Overlord";"Larva";162;0
"Unit";"Roach";"Larva";160;2
"Unit";"Roach";"Larva";160;2
"Unit";"Overlord";"Larva";168;0
"Unit";"Overlord";"Larva";168;0
"Unit";"Overlord";"Larva";168;0
"Unit";"Roach";"Larva";168;2
"Unit";"Roach";"Larva";168;2
"Unit";"Roach";"Larva";168;2
"Upgrade";"ZergMissileWeaponsLevel1";"EvolutionChamber";136;0
"Upgrade";"ZergGroundArmorsLevel1";"EvolutionChamber";136;0
"Unit";"Roach";"Larva";168;2
"Building";"Hatchery";NA;137;0
"Unit";"Roach";"Larva";178;2
"Unit";"Roach";"Larva";182;2
"Unit";"Roach";"Larva";182;2
"Unit";"Roach";"Larva";182;2
"Unit";"Roach";"Larva";182;2
"Unit";"Roach";"Larva";182;2
"Unit";"Roach";"Larva";182;2
"Unit";"Roach";"Larva";184;2
"Unit";"Roach";"Larva";184;2
"Unit";"Roach";"Larva";184;2
"Unit";"Roach";"Larva";184;2
"Unit";"Roach";"Larva";184;2
"Unit";"Roach";"Larva";184;2
"Unit";"Roach";"Larva";184;2
"Unit";"Roach";"Larva";184;2
"Unit";"Roach";"Larva";184;2
"Unit";"Roach";"Larva";184;2
"Unit";"Roach";"Larva";196;2
"Unit";"Roach";"Larva";196;2
"Unit";"Roach";"Larva";196;2
"Unit";"Roach";"Larva";216;2
"Unit";"Roach";"Larva";216;2
"Building";"CreepTumor";NA;227;0
"Building";"CreepTumor";NA;227;0
"Building";"CreepTumor";NA;227;0
"Building";"CreepTumor";NA;227;0
"Building";"CreepTumorQueen";NA;228;0
"Building";"CreepTumor";NA;227;0
"Building";"CreepTumor";NA;228;0
"Building";"CreepTumor";NA;228;0
"Building";"CreepTumorQueen";NA;228;0
"Building";"CreepTumor";NA;228;0
"Building";"CreepTumor";NA;228;0
"Unit";"Corruptor";"Larva";222;2
"Unit";"Corruptor";"Larva";222;2
"Unit";"Corruptor";"Larva";222;2
"Unit";"Corruptor";"Larva";222;2
"Unit";"Roach";"Larva";227;2
"Unit";"Corruptor";"Larva";222;2
"Unit";"Roach";"Larva";228;2
"Unit";"Overlord";"Larva";228;0
"Unit";"Zergling";"Larva";228;1
"Unit";"Zergling";"Larva";228;1
"Unit";"Zergling";"Larva";228;1
"Unit";"Zergling";"Larva";228;1
"Unit";"Zergling";"Larva";228;1
"Unit";"Zergling";"Larva";228;1
"Unit";"Roach";"Larva";228;2
"Unit";"Roach";"Larva";228;2
"Unit";"Roach";"Larva";243;2
"Unit";"Zergling";"Larva";251;1
"Unit";"Zergling";"Larva";251;1
"Unit";"Zergling";"Larva";251;1
"Unit";"Zergling";"Larva";251;1
"Building";"CreepTumor";NA;261;0
"Building";"CreepTumor";NA;261;0
"Building";"CreepTumor";NA;261;0
"Building";"CreepTumor";NA;261;0
"Building";"CreepTumor";NA;261;0
"Building";"CreepTumor";NA;261;0
"Building";"CreepTumor";NA;261;0
"Building";"Extractor";NA;261;0
"Building";"CreepTumor";NA;261;0
"Building";"BanelingNest";NA;255;0
"Unit";"Zergling";"Larva";261;1
"Unit";"Zergling";"Larva";261;1
"Building";"Extractor";NA;261;0
"Building";"CreepTumorQueen";NA;261;0
"Unit";"Zergling";"Larva";261;1
"Unit";"Zergling";"Larva";261;1
"Unit";"Zergling";"Larva";261;1
"Unit";"Zergling";"Larva";261;1
"Unit";"Zergling";"Larva";261;1
"Unit";"Zergling";"Larva";261;1
"Unit";"Zergling";"Larva";261;1
"Unit";"Zergling";"Larva";261;1
"Unit";"Zergling";"Larva";261;1
"Unit";"Zergling";"Larva";261;1
"Unit";"Infestor";"Larva";261;2
"Unit";"Zergling";"Larva";261;1
"Unit";"Zergling";"Larva";261;1
"Unit";"Zergling";"Larva";261;1
"Unit";"Zergling";"Larva";261;1
"Unit";"Infestor";"Larva";261;2
"Unit";"Infestor";"Larva";261;2
"Unit";"Infestor";"Larva";261;2
"Unit";"Infestor";"Larva";261;2
"Unit";"Corruptor";"Larva";261;2
"Unit";"Zergling";"Larva";290;1
"Unit";"Zergling";"Larva";290;1
"Unit";"Zergling";"Larva";290;1
"Unit";"Zergling";"Larva";290;1
"Unit";"Zergling";"Larva";290;1
"Unit";"Zergling";"Larva";290;1
"Unit";"Zergling";"Larva";290;1
"Unit";"Zergling";"Larva";290;1
"Upgrade";"ZergMissileWeaponsLevel2";"EvolutionChamber";243;0
"Upgrade";"ZergGroundArmorsLevel2";"EvolutionChamber";243;0
"Building";"CreepTumorQueen";NA;290;0
"Building";"CreepTumorQueen";NA;298;0
