"type";"unit_name";"on_building";"total_supply";"supply"
"Unit";"Overlord";"Larva";13;0
"Building";"Extractor";NA;18;0
"Unit";"Overlord";"Larva";21;0
"Building";"SpawningPool";NA;19;0
"Building";"Hatchery";NA;17;0
"Unit";"Zergling";"Larva";23;1
"Unit";"Zergling";"Larva";23;1
"Unit";"Zergling";"Larva";23;1
"Unit";"Zergling";"Larva";23;1
"Unit";"Queen";"Hatchery";22;2
"Unit";"Queen";"Hatchery";23;2
"Unit";"Overlord";"Larva";35;0
"Unit";"Overlord";"Larva";35;0
"Unit";"Queen";"Hatchery";31;2
"Building";"CreepTumorQueen";NA;37;0
"Building";"CreepTumorQueen";NA;41;0
"Unit";"Queen";"Hatchery";35;2
"Unit";"Zergling";"Larva";41;1
"Unit";"Zergling";"Larva";41;1
"Unit";"Zergling";"Larva";41;1
"Unit";"Zergling";"Larva";41;1
"Unit";"Zergling";"Larva";41;1
"Unit";"Zergling";"Larva";41;1
"Unit";"Overlord";"Larva";48;0
"Building";"CreepTumor";NA;54;0
"Unit";"Overlord";"Larva";61;0
"Unit";"Overlord";"Larva";61;0
"Unit";"Overlord";"Larva";61;0
"Unit";"Overlord";"Larva";61;0
"Building";"CreepTumor";NA;61;0
"Unit";"Queen";"Hatchery";54;2
"Building";"CreepTumorQueen";NA;61;0
"Building";"CreepTumor";NA;61;0
"Building";"CreepTumorQueen";NA;61;0
"Building";"Hatchery";NA;46;0
"Unit";"Queen";"Hatchery";61;2
"Building";"CreepTumor";NA;66;0
"Unit";"Zergling";"Larva";63;1
"Unit";"Zergling";"Larva";63;1
"Unit";"Zergling";"Larva";63;1
"Unit";"Zergling";"Larva";63;1
"Unit";"Zergling";"Larva";63;1
"Unit";"Zergling";"Larva";63;1
"Building";"CreepTumor";NA;71;0
"Building";"CreepTumor";NA;71;0
"Building";"CreepTumor";NA;71;0
"Unit";"Zergling";"Larva";71;1
"Unit";"Zergling";"Larva";71;1
"Unit";"Zergling";"Larva";71;1
"Unit";"Zergling";"Larva";71;1
"Unit";"Zergling";"Larva";71;1
"Unit";"Zergling";"Larva";71;1
"Building";"CreepTumorQueen";NA;73;0
"Building";"CreepTumorQueen";NA;73;0
"Unit";"Queen";"Hatchery";61;2
"Building";"EvolutionChamber";NA;71;0
"Unit";"Zergling";"Larva";73;1
"Unit";"Zergling";"Larva";73;1
"Building";"EvolutionChamber";NA;71;0
"Unit";"Zergling";"Larva";79;1
"Unit";"Zergling";"Larva";79;1
"Unit";"Zergling";"Larva";79;1
"Unit";"Zergling";"Larva";79;1
"Unit";"Zergling";"Larva";79;1
"Unit";"Zergling";"Larva";79;1
"Unit";"Zergling";"Larva";79;1
"Unit";"Zergling";"Larva";79;1
"Unit";"Zergling";"Larva";79;1
"Unit";"Zergling";"Larva";79;1
"Building";"CreepTumor";NA;99;0
"Building";"CreepTumor";NA;99;0
"Building";"CreepTumorQueen";NA;99;0
"Building";"CreepTumorQueen";NA;99;0
"Building";"CreepTumor";NA;99;0
"Building";"CreepTumor";NA;104;0
"Building";"CreepTumor";NA;104;0
"Building";"CreepTumorQueen";NA;104;0
"Building";"CreepTumorQueen";NA;104;0
"Building";"Extractor";NA;104;0
"Building";"Extractor";NA;104;0
"Building";"Extractor";NA;104;0
"Building";"SporeCrawler";NA;104;0
"Building";"Extractor";NA;104;0
"Building";"Extractor";NA;113;0
"Building";"SporeCrawler";NA;113;0
"Building";"CreepTumor";NA;119;0
"Building";"CreepTumor";NA;119;0
"Building";"CreepTumor";NA;119;0
"Unit";"Overlord";"Larva";119;0
"Unit";"Overlord";"Larva";119;0
"Building";"CreepTumor";NA;122;0
"Building";"CreepTumor";NA;122;0
"Building";"CreepTumor";NA;122;0
"Building";"CreepTumor";NA;122;0
"Building";"CreepTumorQueen";NA;122;0
"Building";"CreepTumorQueen";NA;122;0
"Unit";"Overlord";"Larva";122;0
"Unit";"Overlord";"Larva";122;0
"Unit";"Overlord";"Larva";122;0
"Building";"BanelingNest";NA;119;0
"Unit";"Zergling";"Larva";128;1
"Unit";"Zergling";"Larva";128;1
"Unit";"Zergling";"Larva";128;1
"Unit";"Zergling";"Larva";128;1
"Unit";"Zergling";"Larva";128;1
"Unit";"Zergling";"Larva";128;1
"Unit";"Zergling";"Larva";128;1
"Unit";"Zergling";"Larva";128;1
"Unit";"Zergling";"Larva";128;1
"Unit";"Zergling";"Larva";128;1
"Unit";"Zergling";"Larva";128;1
"Unit";"Zergling";"Larva";128;1
"Unit";"Zergling";"Larva";128;1
"Unit";"Zergling";"Larva";128;1
"Unit";"Zergling";"Larva";128;1
"Unit";"Zergling";"Larva";128;1
"Unit";"Zergling";"Larva";128;1
"Unit";"Zergling";"Larva";128;1
"Building";"CreepTumor";NA;128;0
"Building";"CreepTumor";NA;128;0
"Building";"CreepTumor";NA;146;0
"Building";"CreepTumor";NA;146;0
"Building";"CreepTumor";NA;146;0
"Building";"CreepTumor";NA;149;0
"Building";"CreepTumor";NA;149;0
"Building";"CreepTumor";NA;149;0
"Building";"CreepTumor";NA;150;0
"Building";"CreepTumorQueen";NA;150;0
"Building";"CreepTumor";NA;150;0
"Building";"CreepTumor";NA;150;0
"Building";"CreepTumorQueen";NA;150;0
"Upgrade";"ZergGroundArmorsLevel1";"EvolutionChamber";119;0
"Upgrade";"ZergMeleeWeaponsLevel1";"EvolutionChamber";119;0
"Building";"InfestationPit";NA;128;0
"Building";"Hatchery";NA;122;0
"Unit";"Queen";"Hatchery";146;2
"Unit";"Queen";"Hatchery";146;2
"Unit";"Queen";"Hatchery";146;2
"Unit";"Zergling";"Larva";152;1
"Unit";"Zergling";"Larva";152;1
"Unit";"Zergling";"Larva";152;1
"Unit";"Zergling";"Larva";152;1
"Unit";"Zergling";"Larva";152;1
"Unit";"Zergling";"Larva";152;1
"Unit";"Zergling";"Larva";152;1
"Unit";"Zergling";"Larva";152;1
"Unit";"Zergling";"Larva";152;1
"Unit";"Zergling";"Larva";152;1
"Unit";"Zergling";"Larva";152;1
"Unit";"Zergling";"Larva";152;1
"Building";"CreepTumorQueen";NA;167;0
"Building";"CreepTumor";NA;167;0
"Building";"CreepTumor";NA;167;0
"Building";"CreepTumor";NA;167;0
"Building";"CreepTumor";NA;167;0
"Building";"CreepTumor";NA;167;0
"Building";"CreepTumor";NA;167;0
"Building";"CreepTumor";NA;167;0
"Unit";"Baneling";"Zergling";179;0
"Unit";"Baneling";"Zergling";179;0
"Unit";"Baneling";"Zergling";179;0
"Unit";"Baneling";"Zergling";179;0
"Unit";"Baneling";"Zergling";179;0
"Unit";"Baneling";"Zergling";179;0
"Unit";"Baneling";"Zergling";179;0
"Unit";"Baneling";"Zergling";179;0
"Unit";"Zergling";"Larva";179;1
"Unit";"Zergling";"Larva";179;1
"Unit";"Zergling";"Larva";179;1
"Unit";"Zergling";"Larva";179;1
"Unit";"Zergling";"Larva";179;1
"Unit";"Zergling";"Larva";179;1
"Unit";"Zergling";"Larva";179;1
"Unit";"Zergling";"Larva";179;1
"Unit";"Zergling";"Larva";179;1
"Unit";"Zergling";"Larva";179;1
"Unit";"Zergling";"Larva";179;1
"Unit";"Zergling";"Larva";179;1
"Unit";"Zergling";"Larva";179;1
"Unit";"Zergling";"Larva";179;1
"Unit";"Zergling";"Larva";179;1
"Unit";"Zergling";"Larva";179;1
"Unit";"Zergling";"Larva";179;1
"Unit";"Zergling";"Larva";179;1
"Unit";"Zergling";"Larva";179;1
"Unit";"Zergling";"Larva";179;1
"Unit";"Zergling";"Larva";179;1
"Unit";"Zergling";"Larva";179;1
"Unit";"Zergling";"Larva";179;1
"Unit";"Zergling";"Larva";179;1
"Unit";"Zergling";"Larva";179;1
"Unit";"Zergling";"Larva";179;1
"Unit";"Baneling";"Zergling";179;0
"Unit";"Baneling";"Zergling";179;0
"Unit";"Baneling";"Zergling";179;0
"Unit";"Baneling";"Zergling";179;0
"Unit";"Overlord";"Larva";205;0
"Unit";"Overlord";"Larva";205;0
"Unit";"Overlord";"Larva";205;0
"Unit";"Overlord";"Larva";205;0
"Unit";"Overlord";"Larva";205;0
"Unit";"Overlord";"Larva";205;0
"Unit";"Overlord";"Larva";205;0
"Unit";"Overlord";"Larva";205;0
"Unit";"Overlord";"Larva";205;0
"Unit";"Overlord";"Larva";205;0
"Building";"CreepTumor";NA;205;0
"Building";"CreepTumor";NA;205;0
"Building";"CreepTumor";NA;205;0
"Building";"CreepTumor";NA;205;0
"Building";"CreepTumor";NA;205;0
"Building";"CreepTumor";NA;205;0
"Building";"CreepTumor";NA;205;0
"Building";"CreepTumor";NA;205;0
"Building";"CreepTumor";NA;205;0
"Upgrade";"Burrow";"Hatchery";179;0
"Building";"Extractor";NA;205;0
"Building";"Extractor";NA;205;0
"Unit";"Zergling";"Larva";209;1
"Unit";"Zergling";"Larva";209;1
"Unit";"Zergling";"Larva";209;1
"Unit";"Zergling";"Larva";209;1
"Unit";"Zergling";"Larva";209;1
"Unit";"Zergling";"Larva";209;1
"Unit";"Zergling";"Larva";209;1
"Unit";"Zergling";"Larva";209;1
"Unit";"Zergling";"Larva";209;1
"Unit";"Zergling";"Larva";209;1
"Unit";"Zergling";"Larva";209;1
"Unit";"Zergling";"Larva";209;1
"Unit";"Zergling";"Larva";209;1
"Unit";"Zergling";"Larva";209;1
"Unit";"Zergling";"Larva";209;1
"Unit";"Zergling";"Larva";209;1
"Unit";"Zergling";"Larva";209;1
"Unit";"Zergling";"Larva";209;1
"Unit";"Zergling";"Larva";209;1
"Unit";"Zergling";"Larva";209;1
"Unit";"Zergling";"Larva";209;1
"Unit";"Zergling";"Larva";209;1
"Unit";"Infestor";"Larva";205;2
"Unit";"Infestor";"Larva";205;2
"Unit";"Infestor";"Larva";205;2
"Unit";"Infestor";"Larva";205;2
"Unit";"Zergling";"Larva";209;1
"Unit";"Zergling";"Larva";209;1
"Unit";"Zergling";"Larva";209;1
"Unit";"Zergling";"Larva";209;1
"Unit";"Zergling";"Larva";209;1
"Unit";"Zergling";"Larva";209;1
"Unit";"Zergling";"Larva";209;1
"Unit";"Zergling";"Larva";209;1
"Unit";"Zergling";"Larva";209;1
"Unit";"Zergling";"Larva";209;1
"Unit";"Zergling";"Larva";209;1
"Unit";"Zergling";"Larva";209;1
"Unit";"Zergling";"Larva";209;1
"Unit";"Zergling";"Larva";209;1
"Unit";"Zergling";"Larva";209;1
"Unit";"Zergling";"Larva";209;1
"Unit";"Zergling";"Larva";209;1
"Unit";"Zergling";"Larva";209;1
"Building";"CreepTumor";NA;231;0
"Building";"CreepTumor";NA;231;0
"Building";"CreepTumorQueen";NA;257;0
"Building";"CreepTumorQueen";NA;257;0
"Building";"CreepTumorQueen";NA;257;0
"Building";"CreepTumorQueen";NA;257;0
"Building";"CreepTumorQueen";NA;257;0
"Building";"CreepTumorQueen";NA;257;0
"Building";"CreepTumorQueen";NA;257;0
"Building";"CreepTumorQueen";NA;257;0
"Building";"CreepTumorQueen";NA;257;0
"Upgrade";"NeuralParasite";"InfestationPit";209;0
"Unit";"Baneling";"Zergling";257;0
"Unit";"Baneling";"Zergling";257;0
"Unit";"Baneling";"Zergling";257;0
"Unit";"Baneling";"Zergling";257;0
"Unit";"Baneling";"Zergling";257;0
"Unit";"Baneling";"Zergling";257;0
"Upgrade";"ZergGroundArmorsLevel2";"EvolutionChamber";179;0
"Upgrade";"ZergMeleeWeaponsLevel2";"EvolutionChamber";179;0
"Unit";"Infestor";"Larva";257;2
"Unit";"Infestor";"Larva";257;2
"Unit";"Infestor";"Larva";257;2
"Unit";"Infestor";"Larva";257;2
"Building";"CreepTumorQueen";NA;265;0
"Building";"CreepTumorQueen";NA;265;0
"Building";"CreepTumor";NA;265;0
"Building";"CreepTumor";NA;265;0
"Building";"CreepTumor";NA;265;0
"Building";"CreepTumor";NA;265;0
"Building";"CreepTumor";NA;265;0
"Building";"CreepTumor";NA;265;0
"Building";"CreepTumor";NA;265;0
"Building";"CreepTumorQueen";NA;265;0
"Building";"CreepTumor";NA;265;0
"Building";"CreepTumor";NA;265;0
"Building";"SporeCrawler";NA;257;0
"Building";"CreepTumor";NA;268;0
"Building";"CreepTumorQueen";NA;268;0
"Building";"CreepTumorQueen";NA;268;0
"Building";"CreepTumorQueen";NA;268;0
"Building";"CreepTumorQueen";NA;268;0
"Unit";"Zergling";"Larva";268;1
"Unit";"Zergling";"Larva";268;1
"Unit";"Zergling";"Larva";268;1
"Unit";"Zergling";"Larva";268;1
"Unit";"Zergling";"Larva";268;1
"Unit";"Zergling";"Larva";268;1
"Unit";"Zergling";"Larva";268;1
"Unit";"Zergling";"Larva";268;1
"Unit";"Zergling";"Larva";268;1
"Unit";"Zergling";"Larva";268;1
"Unit";"Zergling";"Larva";268;1
"Unit";"Zergling";"Larva";268;1
"Unit";"Zergling";"Larva";268;1
"Unit";"Zergling";"Larva";268;1
"Unit";"Zergling";"Larva";268;1
"Unit";"Zergling";"Larva";268;1
"Unit";"Zergling";"Larva";268;1
"Unit";"Zergling";"Larva";268;1
"Unit";"Zergling";"Larva";268;1
"Unit";"Zergling";"Larva";268;1
"Unit";"Zergling";"Larva";268;1
"Unit";"Zergling";"Larva";268;1
"Unit";"Zergling";"Larva";268;1
"Unit";"Zergling";"Larva";268;1
"Unit";"Zergling";"Larva";268;1
"Unit";"Zergling";"Larva";268;1
"Unit";"Zergling";"Larva";268;1
"Unit";"Zergling";"Larva";268;1
"Unit";"Zergling";"Larva";268;1
"Unit";"Zergling";"Larva";268;1
"Unit";"Zergling";"Larva";268;1
"Unit";"Zergling";"Larva";268;1
"Unit";"Zergling";"Larva";268;1
"Unit";"Zergling";"Larva";268;1
"Unit";"Zergling";"Larva";268;1
"Unit";"Zergling";"Larva";268;1
"Unit";"Zergling";"Larva";268;1
"Unit";"Zergling";"Larva";268;1
"Unit";"Zergling";"Larva";268;1
"Unit";"Zergling";"Larva";268;1
"Unit";"Zergling";"Larva";268;1
"Unit";"Zergling";"Larva";268;1
"Unit";"Zergling";"Larva";268;1
"Unit";"Zergling";"Larva";268;1
"Unit";"Zergling";"Larva";268;1
"Unit";"Zergling";"Larva";268;1
"Building";"SpineCrawler";NA;257;0
"Unit";"Overlord";"Larva";314;0
"Unit";"Overlord";"Larva";314;0
"Unit";"Overlord";"Larva";314;0
"Unit";"Overlord";"Larva";314;0
"Unit";"Overlord";"Larva";314;0
"Building";"CreepTumorQueen";NA;314;0
"Building";"CreepTumorQueen";NA;314;0
"Building";"CreepTumorQueen";NA;314;0
"Building";"CreepTumorQueen";NA;314;0
"Building";"Hatchery";NA;257;0
"Building";"Spire";NA;257;0
"Building";"CreepTumor";NA;314;0
"Building";"CreepTumor";NA;314;0
"Building";"CreepTumor";NA;314;0
"Building";"CreepTumor";NA;314;0
"Unit";"Zergling";"Larva";314;1
"Unit";"Zergling";"Larva";314;1
"Unit";"Zergling";"Larva";314;1
"Unit";"Zergling";"Larva";314;1
"Unit";"Zergling";"Larva";314;1
"Unit";"Zergling";"Larva";314;1
"Unit";"Zergling";"Larva";314;1
"Unit";"Zergling";"Larva";314;1
"Unit";"Zergling";"Larva";314;1
"Unit";"Zergling";"Larva";314;1
"Unit";"Zergling";"Larva";314;1
"Unit";"Zergling";"Larva";314;1
"Unit";"Zergling";"Larva";314;1
"Unit";"Zergling";"Larva";314;1
"Unit";"Zergling";"Larva";314;1
"Unit";"Zergling";"Larva";314;1
"Unit";"Zergling";"Larva";314;1
"Unit";"Zergling";"Larva";314;1
"Unit";"Zergling";"Larva";314;1
"Unit";"Zergling";"Larva";314;1
"Building";"Hatchery";NA;268;0
"Unit";"Zergling";"Larva";334;1
"Unit";"Zergling";"Larva";334;1
"Unit";"Zergling";"Larva";334;1
"Unit";"Zergling";"Larva";334;1
"Unit";"Zergling";"Larva";334;1
"Unit";"Zergling";"Larva";334;1
"Unit";"Zergling";"Larva";334;1
"Unit";"Zergling";"Larva";334;1
"Unit";"Zergling";"Larva";334;1
"Unit";"Zergling";"Larva";334;1
"Unit";"Zergling";"Larva";334;1
"Unit";"Zergling";"Larva";334;1
"Unit";"Zergling";"Larva";334;1
"Unit";"Zergling";"Larva";334;1
"Unit";"Zergling";"Larva";334;1
"Unit";"Zergling";"Larva";334;1
"Unit";"Zergling";"Larva";334;1
"Unit";"Zergling";"Larva";334;1
"Unit";"Zergling";"Larva";334;1
"Unit";"Zergling";"Larva";334;1
"Unit";"Zergling";"Larva";334;1
"Unit";"Zergling";"Larva";334;1
"Unit";"Zergling";"Larva";334;1
"Unit";"Zergling";"Larva";334;1
"Unit";"Zergling";"Larva";334;1
"Unit";"Zergling";"Larva";334;1
"Unit";"Zergling";"Larva";334;1
"Unit";"Zergling";"Larva";334;1
"Unit";"Zergling";"Larva";334;1
"Unit";"Zergling";"Larva";334;1
"Unit";"Zergling";"Larva";334;1
"Unit";"Zergling";"Larva";334;1
"Unit";"Zergling";"Larva";334;1
"Unit";"Zergling";"Larva";334;1
"Unit";"Zergling";"Larva";334;1
"Unit";"Zergling";"Larva";334;1
"Building";"Extractor";NA;334;0
"Building";"Extractor";NA;334;0
"Building";"CreepTumor";NA;370;0
"Building";"CreepTumor";NA;370;0
"Building";"CreepTumor";NA;370;0
"Building";"CreepTumor";NA;370;0
"Building";"CreepTumor";NA;370;0
"Unit";"Corruptor";"Larva";370;2
"Unit";"Corruptor";"Larva";370;2
"Unit";"Corruptor";"Larva";370;2
"Unit";"Corruptor";"Larva";370;2
"Unit";"Corruptor";"Larva";370;2
"Unit";"Corruptor";"Larva";370;2
"Unit";"Corruptor";"Larva";370;2
"Unit";"Corruptor";"Larva";370;2
"Unit";"Corruptor";"Larva";370;2
"Unit";"Corruptor";"Larva";370;2
"Unit";"Corruptor";"Larva";370;2
"Building";"CreepTumor";NA;392;0
"Building";"CreepTumor";NA;392;0
"Building";"CreepTumorQueen";NA;392;0
"Building";"CreepTumorQueen";NA;392;0
"Building";"CreepTumor";NA;392;0
"Building";"CreepTumor";NA;392;0
"Building";"CreepTumor";NA;392;0
"Building";"CreepTumor";NA;392;0
"Building";"CreepTumorQueen";NA;392;0
"Unit";"Corruptor";"Larva";392;2
"Unit";"Corruptor";"Larva";392;2
"Unit";"Corruptor";"Larva";392;2
"Unit";"Corruptor";"Larva";392;2
"Unit";"Corruptor";"Larva";392;2
"Unit";"Corruptor";"Larva";392;2
"Unit";"Corruptor";"Larva";392;2
"Unit";"Zergling";"Larva";406;1
"Unit";"Zergling";"Larva";406;1
"Unit";"Zergling";"Larva";406;1
"Unit";"Zergling";"Larva";406;1
"Unit";"Zergling";"Larva";406;1
"Unit";"Zergling";"Larva";406;1
"Unit";"Zergling";"Larva";406;1
"Unit";"Zergling";"Larva";406;1
"Unit";"Zergling";"Larva";406;1
"Unit";"Zergling";"Larva";406;1
"Unit";"Zergling";"Larva";406;1
"Unit";"Zergling";"Larva";406;1
"Unit";"Zergling";"Larva";406;1
"Unit";"Zergling";"Larva";406;1
"Unit";"Zergling";"Larva";406;1
"Unit";"Zergling";"Larva";406;1
"Unit";"Zergling";"Larva";406;1
"Unit";"Zergling";"Larva";406;1
"Unit";"Zergling";"Larva";406;1
"Unit";"Zergling";"Larva";406;1
"Unit";"Zergling";"Larva";406;1
"Unit";"Zergling";"Larva";406;1
"Unit";"Zergling";"Larva";406;1
"Unit";"Zergling";"Larva";406;1
"Unit";"Zergling";"Larva";406;1
"Unit";"Zergling";"Larva";406;1
"Unit";"Zergling";"Larva";406;1
"Unit";"Zergling";"Larva";406;1
"Unit";"Zergling";"Larva";406;1
"Unit";"Zergling";"Larva";406;1
"Unit";"Zergling";"Larva";406;1
"Unit";"Zergling";"Larva";406;1
"Unit";"Zergling";"Larva";406;1
"Unit";"Zergling";"Larva";406;1
"Unit";"Zergling";"Larva";406;1
"Unit";"Zergling";"Larva";406;1
"Unit";"Zergling";"Larva";406;1
"Unit";"Zergling";"Larva";406;1
"Unit";"Zergling";"Larva";406;1
"Unit";"Zergling";"Larva";406;1
"Unit";"Zergling";"Larva";406;1
"Unit";"Zergling";"Larva";406;1
"Unit";"Zergling";"Larva";406;1
"Unit";"Zergling";"Larva";406;1
"Unit";"Zergling";"Larva";406;1
"Unit";"Zergling";"Larva";406;1
"Building";"CreepTumor";NA;406;0
"Building";"CreepTumor";NA;406;0
"Building";"CreepTumorQueen";NA;452;0
"Building";"CreepTumorQueen";NA;452;0
"Building";"CreepTumorQueen";NA;452;0
"Building";"CreepTumorQueen";NA;452;0
"Building";"CreepTumorQueen";NA;452;0
"Building";"CreepTumorQueen";NA;452;0
"Building";"Hatchery";NA;406;0
"Building";"CreepTumor";NA;452;0
"Building";"CreepTumor";NA;452;0
"Building";"CreepTumor";NA;452;0
"Building";"CreepTumor";NA;452;0
"Building";"CreepTumor";NA;452;0
"Building";"CreepTumor";NA;452;0
"Building";"SporeCrawler";NA;452;0
"Building";"SporeCrawler";NA;452;0
"Building";"SporeCrawler";NA;452;0
"Building";"SporeCrawler";NA;452;0
"Building";"SporeCrawler";NA;452;0
"Building";"SporeCrawler";NA;452;0
"Building";"SporeCrawler";NA;452;0
"Building";"SporeCrawler";NA;452;0
"Building";"SporeCrawler";NA;452;0
"Building";"CreepTumor";NA;453;0
"Building";"CreepTumorQueen";NA;453;0
"Building";"CreepTumorQueen";NA;453;0
"Building";"CreepTumor";NA;453;0
"Building";"CreepTumor";NA;453;0
"Building";"CreepTumor";NA;453;0
"Building";"CreepTumor";NA;453;0
"Unit";"Corruptor";"Larva";452;2
"Unit";"Corruptor";"Larva";452;2
"Unit";"Corruptor";"Larva";452;2
"Unit";"Corruptor";"Larva";452;2
"Building";"CreepTumor";NA;453;0
"Building";"CreepTumor";NA;461;0
"Upgrade";"ZergGroundArmorsLevel3";"EvolutionChamber";406;0
"Upgrade";"ZergMeleeWeaponsLevel3";"EvolutionChamber";406;0
"Unit";"Zergling";"Larva";461;1
"Unit";"Zergling";"Larva";461;1
"Unit";"Zergling";"Larva";461;1
"Unit";"Zergling";"Larva";461;1
"Building";"Hatchery";NA;452;0
"Building";"CreepTumor";NA;461;0
"Building";"CreepTumor";NA;461;0
"Unit";"Baneling";"Zergling";465;0
"Unit";"Baneling";"Zergling";465;0
"Unit";"Baneling";"Zergling";465;0
"Unit";"Baneling";"Zergling";465;0
"Building";"CreepTumor";NA;465;0
"Unit";"Baneling";"Zergling";465;0
"Unit";"Baneling";"Zergling";465;0
"Unit";"Baneling";"Zergling";465;0
"Unit";"Baneling";"Zergling";465;0
"Unit";"Baneling";"Zergling";465;0
"Unit";"Baneling";"Zergling";465;0
"Unit";"Baneling";"Zergling";465;0
"Unit";"Baneling";"Zergling";465;0
"Unit";"Baneling";"Zergling";465;0
"Unit";"Baneling";"Zergling";465;0
"Unit";"Baneling";"Zergling";465;0
"Unit";"Baneling";"Zergling";465;0
"Unit";"Baneling";"Zergling";465;0
"Unit";"Baneling";"Zergling";465;0
"Unit";"Baneling";"Zergling";465;0
"Unit";"Baneling";"Zergling";465;0
"Building";"CreepTumorQueen";NA;465;0
"Building";"CreepTumor";NA;465;0
"Building";"CreepTumorQueen";NA;465;0
"Building";"CreepTumor";NA;465;0
"Unit";"Baneling";"Zergling";465;0
"Unit";"Baneling";"Zergling";465;0
"Building";"CreepTumorQueen";NA;465;0
"Unit";"Baneling";"Zergling";465;0
"Unit";"Baneling";"Zergling";465;0
"Unit";"Baneling";"Zergling";465;0
"Unit";"Baneling";"Zergling";465;0
"Unit";"Baneling";"Zergling";465;0
"Unit";"Baneling";"Zergling";465;0
"Unit";"Baneling";"Zergling";465;0
"Unit";"Baneling";"Zergling";465;0
"Unit";"Baneling";"Zergling";465;0
"Unit";"Baneling";"Zergling";465;0
"Unit";"Baneling";"Zergling";465;0
"Unit";"Baneling";"Zergling";465;0
"Unit";"Baneling";"Zergling";465;0
"Unit";"Baneling";"Zergling";465;0
"Unit";"Baneling";"Zergling";465;0
"Unit";"Baneling";"Zergling";465;0
"Unit";"Baneling";"Zergling";465;0
"Unit";"Baneling";"Zergling";465;0
"Unit";"Baneling";"Zergling";465;0
"Unit";"Baneling";"Zergling";465;0
"Unit";"Baneling";"Zergling";465;0
"Unit";"Baneling";"Zergling";465;0
"Unit";"Baneling";"Zergling";465;0
"Unit";"Baneling";"Zergling";465;0
"Unit";"Baneling";"Zergling";465;0
"Unit";"Baneling";"Zergling";465;0
"Unit";"Baneling";"Zergling";465;0
"Unit";"Baneling";"Zergling";465;0
"Unit";"Baneling";"Zergling";465;0
"Unit";"Baneling";"Zergling";465;0
"Unit";"Baneling";"Zergling";465;0
"Unit";"Baneling";"Zergling";465;0
"Unit";"Baneling";"Zergling";465;0
"Unit";"Baneling";"Zergling";465;0
"Unit";"Baneling";"Zergling";465;0
"Unit";"Baneling";"Zergling";465;0
"Unit";"Baneling";"Zergling";465;0
"Unit";"Baneling";"Zergling";465;0
"Unit";"Baneling";"Zergling";465;0
"Unit";"Baneling";"Zergling";465;0
"Unit";"Baneling";"Zergling";465;0
