"type";"unit_name";"on_building";"total_supply";"supply"
"Unit";"Overlord";"Larva";13;0
"Building";"Extractor";NA;17;0
"Unit";"Overlord";"Larva";21;0
"Building";"SpawningPool";NA;19;0
"Building";"Hatchery";NA;17;0
"Unit";"Zergling";"Larva";22;1
"Unit";"Zergling";"Larva";22;1
"Unit";"Zergling";"Larva";23;1
"Unit";"Zergling";"Larva";23;1
"Unit";"Zergling";"Larva";23;1
"Unit";"Zergling";"Larva";23;1
"Unit";"Queen";"Hatchery";22;2
"Unit";"Queen";"Hatchery";23;2
"Unit";"Overlord";"Larva";33;0
"Unit";"Queen";"Hatchery";36;2
"Unit";"Queen";"Hatchery";36;2
"Building";"CreepTumorQueen";NA;40;0
"Unit";"Overlord";"Larva";38;0
"Building";"CreepTumorQueen";NA;40;0
"Building";"CreepTumor";NA;52;0
"Unit";"Overlord";"Larva";54;0
"Building";"RoachWarren";NA;50;0
"Building";"EvolutionChamber";NA;55;0
"Building";"EvolutionChamber";NA;55;0
"Building";"Extractor";NA;55;0
"Building";"Extractor";NA;55;0
"Building";"CreepTumor";NA;55;0
"Unit";"Overlord";"Larva";55;0
"Building";"CreepTumorQueen";NA;60;0
"Unit";"Overlord";"Larva";55;0
"Building";"CreepTumorQueen";NA;60;0
"Building";"Extractor";NA;60;0
"Building";"SporeCrawler";NA;60;0
"Building";"SporeCrawler";NA;63;0
"Unit";"Roach";"Larva";63;2
"Unit";"Roach";"Larva";63;2
"Building";"CreepTumor";NA;70;0
"Unit";"Roach";"Larva";70;2
"Unit";"Roach";"Larva";70;2
"Unit";"Overlord";"Larva";70;0
"Unit";"Roach";"Larva";78;2
"Building";"CreepTumor";NA;83;0
"Building";"CreepTumor";NA;83;0
"Unit";"Overlord";"Larva";78;0
"Building";"CreepTumor";NA;83;0
"Building";"CreepTumor";NA;83;0
"Building";"SpineCrawler";NA;78;0
"Unit";"Overlord";"Larva";83;0
"Unit";"Overlord";"Larva";85;0
"Building";"CreepTumor";NA;90;0
"Building";"Spire";NA;74;0
"Unit";"Mutalisk";"Larva";90;2
"Unit";"Overlord";"Larva";90;0
"Unit";"Mutalisk";"Larva";90;2
"Unit";"Mutalisk";"Larva";90;2
"Unit";"Mutalisk";"Larva";90;2
"Unit";"Mutalisk";"Larva";90;2
"Unit";"Mutalisk";"Larva";90;2
"Unit";"Mutalisk";"Larva";90;2
"Unit";"Mutalisk";"Larva";90;2
"Building";"CreepTumor";NA;90;0
"Unit";"Mutalisk";"Larva";90;2
"Building";"CreepTumor";NA;90;0
"Unit";"Overlord";"Larva";90;0
"Building";"CreepTumor";NA;108;0
"Unit";"Zergling";"Larva";106;1
"Unit";"Zergling";"Larva";106;1
"Unit";"Zergling";"Larva";106;1
"Unit";"Zergling";"Larva";106;1
"Unit";"Zergling";"Larva";106;1
"Unit";"Zergling";"Larva";106;1
"Unit";"Roach";"Larva";106;2
"Unit";"Roach";"Larva";106;2
"Building";"Hatchery";NA;85;0
"Unit";"Zergling";"Larva";108;1
"Unit";"Zergling";"Larva";108;1
"Unit";"Zergling";"Larva";108;1
"Unit";"Zergling";"Larva";108;1
"Building";"Extractor";NA;108;0
"Building";"Extractor";NA;118;0
"Unit";"Zergling";"Larva";122;1
"Unit";"Zergling";"Larva";122;1
"Unit";"Zergling";"Larva";122;1
"Unit";"Zergling";"Larva";122;1
"Unit";"Zergling";"Larva";122;1
"Unit";"Zergling";"Larva";122;1
"Unit";"Zergling";"Larva";122;1
"Unit";"Zergling";"Larva";122;1
"Unit";"Zergling";"Larva";122;1
"Unit";"Zergling";"Larva";122;1
"Unit";"Zergling";"Larva";122;1
"Unit";"Zergling";"Larva";122;1
"Unit";"Zergling";"Larva";122;1
"Unit";"Zergling";"Larva";122;1
"Unit";"Zergling";"Larva";122;1
"Unit";"Zergling";"Larva";122;1
"Upgrade";"GlialReconstitution";"RoachWarren";108;0
"Unit";"Roach";"Larva";138;2
"Unit";"Roach";"Larva";138;2
"Unit";"Queen";"Hatchery";122;2
"Unit";"Roach";"Larva";152;2
"Unit";"Roach";"Larva";155;2
"Unit";"Roach";"Larva";155;2
"Unit";"Roach";"Larva";155;2
"Unit";"Roach";"Larva";155;2
"Building";"CreepTumorQueen";NA;157;0
"Unit";"Roach";"Larva";155;2
"Unit";"Overlord";"Larva";157;0
"Unit";"Overlord";"Larva";157;0
"Upgrade";"ZergMissileWeaponsLevel1";"EvolutionChamber";118;0
"Unit";"Overlord";"Larva";157;0
"Unit";"Overlord";"Larva";157;0
"Unit";"Roach";"Larva";170;2
"Unit";"Roach";"Larva";170;2
"Unit";"Roach";"Larva";170;2
"Unit";"Roach";"Larva";170;2
"Unit";"Roach";"Larva";170;2
"Unit";"Roach";"Larva";170;2
"Unit";"Roach";"Larva";170;2
"Unit";"Roach";"Larva";170;2
"Unit";"Roach";"Larva";170;2
"Unit";"Roach";"Larva";170;2
"Building";"CreepTumor";NA;172;0
"Building";"CreepTumor";NA;173;0
"Building";"CreepTumorQueen";NA;173;0
"Building";"CreepTumor";NA;173;0
"Building";"CreepTumorQueen";NA;173;0
"Building";"CreepTumorQueen";NA;193;0
"Building";"CreepTumorQueen";NA;193;0
"Unit";"Corruptor";"Larva";173;2
"Unit";"Corruptor";"Larva";173;2
"Unit";"Corruptor";"Larva";173;2
"Unit";"Overlord";"Larva";193;0
"Unit";"Overlord";"Larva";193;0
"Unit";"Zergling";"Larva";193;1
"Unit";"Zergling";"Larva";193;1
"Unit";"Zergling";"Larva";193;1
"Unit";"Zergling";"Larva";193;1
"Building";"CreepTumor";NA;199;0
"Building";"CreepTumor";NA;199;0
"Unit";"Overlord";"Larva";193;0
"Building";"CreepTumor";NA;199;0
"Unit";"Overlord";"Larva";193;0
"Unit";"Overlord";"Larva";193;0
"Unit";"Roach";"Larva";199;2
"Unit";"Roach";"Larva";199;2
"Unit";"Roach";"Larva";199;2
"Unit";"Roach";"Larva";199;2
"Unit";"Roach";"Larva";199;2
"Unit";"Roach";"Larva";199;2
"Unit";"Roach";"Larva";199;2
"Unit";"Roach";"Larva";199;2
"Unit";"Roach";"Larva";203;2
"Unit";"Roach";"Larva";203;2
"Unit";"Roach";"Larva";203;2
"Unit";"Roach";"Larva";203;2
"Unit";"Roach";"Larva";203;2
"Unit";"Roach";"Larva";203;2
"Unit";"Roach";"Larva";203;2
"Unit";"Roach";"Larva";203;2
"Unit";"Roach";"Larva";203;2
"Upgrade";"ZergGroundArmorsLevel1";"EvolutionChamber";170;0
"Unit";"Roach";"Larva";219;2
"Unit";"Roach";"Larva";219;2
"Unit";"Roach";"Larva";219;2
"Unit";"Roach";"Larva";243;2
"Unit";"Roach";"Larva";243;2
"Unit";"Roach";"Larva";243;2
"Unit";"Roach";"Larva";243;2
"Unit";"Roach";"Larva";243;2
"Unit";"Roach";"Larva";243;2
"Unit";"Roach";"Larva";243;2
"Unit";"Roach";"Larva";243;2
"Unit";"Roach";"Larva";243;2
"Unit";"Roach";"Larva";243;2
"Unit";"Roach";"Larva";243;2
"Unit";"Roach";"Larva";243;2
"Unit";"Roach";"Larva";243;2
"Unit";"Roach";"Larva";269;2
"Unit";"Roach";"Larva";269;2
"Unit";"Roach";"Larva";269;2
"Unit";"Roach";"Larva";269;2
"Unit";"Roach";"Larva";269;2
"Unit";"Roach";"Larva";269;2
"Unit";"Roach";"Larva";269;2
"Unit";"Roach";"Larva";269;2
"Unit";"Roach";"Larva";269;2
"Unit";"Roach";"Larva";269;2
"Unit";"Roach";"Larva";269;2
"Unit";"Corruptor";"Larva";269;2
"Unit";"Corruptor";"Larva";269;2
"Unit";"Roach";"Larva";295;2
"Unit";"Roach";"Larva";295;2
"Unit";"Roach";"Larva";295;2
"Unit";"Roach";"Larva";295;2
"Unit";"Roach";"Larva";295;2
"Unit";"Roach";"Larva";295;2
"Unit";"Roach";"Larva";295;2
"Unit";"Roach";"Larva";295;2
"Unit";"Roach";"Larva";295;2
"Unit";"Roach";"Larva";295;2
"Unit";"Roach";"Larva";295;2
"Upgrade";"ZergMissileWeaponsLevel2";"EvolutionChamber";237;0
"Building";"HydraliskDen";NA;295;0
"Building";"InfestationPit";NA;295;0
"Building";"Hatchery";NA;269;0
"Unit";"Roach";"Larva";317;2
"Unit";"Roach";"Larva";317;2
"Unit";"Roach";"Larva";317;2
"Unit";"Roach";"Larva";317;2
"Unit";"Roach";"Larva";317;2
"Unit";"Roach";"Larva";317;2
"Unit";"Roach";"Larva";317;2
"Unit";"Roach";"Larva";317;2
"Unit";"Roach";"Larva";317;2
"Unit";"Roach";"Larva";317;2
"Unit";"Roach";"Larva";317;2
