"type";"unit_name";"on_building";"total_supply";"supply"
"Unit";"Overlord";"Larva";12;0
"Building";"SpawningPool";NA;19;0
"Building";"Hatchery";NA;17;0
"Unit";"Zergling";"Larva";23;1
"Unit";"Zergling";"Larva";23;1
"Unit";"Zergling";"Larva";23;1
"Unit";"Zergling";"Larva";23;1
"Unit";"Overlord";"Larva";23;0
"Unit";"Queen";"Hatchery";23;2
"Unit";"Queen";"Hatchery";23;2
"Unit";"Overlord";"Larva";29;0
"Building";"Hatchery";NA;23;0
"Unit";"Overlord";"Larva";35;0
"Building";"CreepTumorQueen";NA;39;0
"Unit";"Queen";"Hatchery";36;2
"Unit";"Queen";"Hatchery";37;2
"Building";"Extractor";NA;42;0
"Unit";"Overlord";"Larva";49;0
"Building";"Extractor";NA;45;0
"Building";"CreepTumor";NA;53;0
"Building";"CreepTumorQueen";NA;55;0
"Unit";"Zergling";"Larva";55;1
"Unit";"Zergling";"Larva";55;1
"Unit";"Zergling";"Larva";55;1
"Unit";"Zergling";"Larva";55;1
"Unit";"Zergling";"Larva";55;1
"Unit";"Zergling";"Larva";55;1
"Building";"CreepTumorQueen";NA;58;0
"Unit";"Queen";"Hatchery";51;2
"Building";"CreepTumor";NA;58;0
"Unit";"Overlord";"Larva";58;0
"Building";"CreepTumor";NA;64;0
"Building";"CreepTumorQueen";NA;66;0
"Building";"CreepTumorQueen";NA;66;0
"Unit";"Queen";"Hatchery";58;2
"Unit";"Queen";"Hatchery";58;2
"Building";"CreepTumorQueen";NA;72;0
"Unit";"Overlord";"Larva";66;0
"Building";"CreepTumor";NA;72;0
"Building";"CreepTumor";NA;72;0
"Unit";"Overlord";"Larva";77;0
"Unit";"Overlord";"Larva";77;0
"Building";"CreepTumor";NA;81;0
"Unit";"Overlord";"Larva";77;0
"Building";"CreepTumorQueen";NA;81;0
"Building";"CreepTumorQueen";NA;81;0
"Building";"CreepTumor";NA;81;0
"Unit";"Overlord";"Larva";81;0
"Building";"CreepTumorQueen";NA;88;0
"Building";"CreepTumor";NA;89;0
"Building";"SporeCrawler";NA;86;0
"Building";"EvolutionChamber";NA;81;0
"Building";"CreepTumor";NA;89;0
"Building";"CreepTumor";NA;89;0
"Building";"SporeCrawler";NA;88;0
"Building";"EvolutionChamber";NA;81;0
"Building";"CreepTumor";NA;89;0
"Building";"CreepTumorQueen";NA;89;0
"Building";"CreepTumor";NA;89;0
"Building";"CreepTumor";NA;89;0
"Building";"CreepTumor";NA;89;0
"Building";"Extractor";NA;89;0
"Unit";"Overlord";"Larva";89;0
"Unit";"Overlord";"Larva";89;0
"Unit";"Zergling";"Larva";97;1
"Unit";"Zergling";"Larva";97;1
"Unit";"Zergling";"Larva";97;1
"Unit";"Zergling";"Larva";97;1
"Unit";"Zergling";"Larva";97;1
"Unit";"Zergling";"Larva";97;1
"Unit";"Zergling";"Larva";97;1
"Unit";"Zergling";"Larva";97;1
"Unit";"Zergling";"Larva";97;1
"Unit";"Zergling";"Larva";97;1
"Building";"Extractor";NA;89;0
"Building";"Extractor";NA;89;0
"Building";"Extractor";NA;97;0
"Building";"CreepTumor";NA;107;0
"Building";"Hatchery";NA;88;0
"Building";"SporeCrawler";NA;107;0
"Building";"CreepTumor";NA;115;0
"Building";"CreepTumor";NA;115;0
"Building";"HydraliskDen";NA;107;0
"Building";"CreepTumor";NA;118;0
"Unit";"Overlord";"Larva";118;0
"Unit";"Overlord";"Larva";118;0
"Unit";"Overlord";"Larva";118;0
"Unit";"Zergling";"Larva";118;1
"Unit";"Zergling";"Larva";118;1
"Unit";"Zergling";"Larva";118;1
"Unit";"Zergling";"Larva";118;1
"Unit";"Zergling";"Larva";118;1
"Unit";"Zergling";"Larva";118;1
"Unit";"Zergling";"Larva";118;1
"Unit";"Zergling";"Larva";118;1
"Unit";"Zergling";"Larva";118;1
"Unit";"Zergling";"Larva";118;1
"Unit";"Zergling";"Larva";118;1
"Unit";"Zergling";"Larva";118;1
"Building";"BanelingNest";NA;107;0
"Building";"CreepTumor";NA;137;0
"Unit";"Queen";"Hatchery";118;2
"Building";"CreepTumor";NA;137;0
"Building";"CreepTumor";NA;137;0
"Unit";"Baneling";"Zergling";137;0
"Unit";"Baneling";"Zergling";137;0
"Unit";"Baneling";"Zergling";137;0
"Unit";"Baneling";"Zergling";137;0
"Building";"InfestationPit";NA;125;0
"Building";"CreepTumorQueen";NA;139;0
"Unit";"Hydralisk";"Larva";139;2
"Unit";"Hydralisk";"Larva";139;2
"Unit";"Hydralisk";"Larva";139;2
"Unit";"Hydralisk";"Larva";139;2
"Unit";"Hydralisk";"Larva";139;2
"Unit";"Zergling";"Larva";139;1
"Unit";"Zergling";"Larva";139;1
"Unit";"Zergling";"Larva";139;1
"Unit";"Zergling";"Larva";139;1
"Unit";"Zergling";"Larva";139;1
"Unit";"Zergling";"Larva";139;1
"Unit";"Zergling";"Larva";139;1
"Unit";"Zergling";"Larva";139;1
"Unit";"Zergling";"Larva";139;1
"Unit";"Zergling";"Larva";139;1
"Unit";"Zergling";"Larva";139;1
"Unit";"Zergling";"Larva";139;1
"Unit";"Zergling";"Larva";139;1
"Unit";"Zergling";"Larva";139;1
"Unit";"Zergling";"Larva";139;1
"Unit";"Zergling";"Larva";139;1
"Unit";"Zergling";"Larva";139;1
"Unit";"Zergling";"Larva";139;1
"Unit";"Zergling";"Larva";139;1
"Unit";"Zergling";"Larva";139;1
"Upgrade";"ZergMeleeWeaponsLevel1";"EvolutionChamber";115;0
"Upgrade";"ZergGroundArmorsLevel1";"EvolutionChamber";115;0
"Unit";"Zergling";"Larva";139;1
"Unit";"Zergling";"Larva";139;1
"Unit";"Zergling";"Larva";139;1
"Unit";"Zergling";"Larva";139;1
"Unit";"Zergling";"Larva";139;1
"Unit";"Zergling";"Larva";139;1
"Unit";"Zergling";"Larva";139;1
"Unit";"Zergling";"Larva";139;1
"Unit";"Zergling";"Larva";139;1
"Unit";"Zergling";"Larva";139;1
"Unit";"Zergling";"Larva";139;1
"Unit";"Zergling";"Larva";139;1
"Unit";"Zergling";"Larva";139;1
"Unit";"Zergling";"Larva";139;1
"Unit";"Zergling";"Larva";139;1
"Unit";"Zergling";"Larva";139;1
"Unit";"Zergling";"Larva";139;1
"Unit";"Zergling";"Larva";139;1
"Unit";"Zergling";"Larva";141;1
"Unit";"Zergling";"Larva";141;1
"Unit";"Baneling";"Zergling";169;0
"Unit";"Baneling";"Zergling";169;0
"Unit";"Baneling";"Zergling";169;0
"Unit";"Baneling";"Zergling";169;0
"Unit";"Baneling";"Zergling";169;0
"Unit";"Baneling";"Zergling";169;0
"Unit";"Baneling";"Zergling";169;0
"Unit";"Baneling";"Zergling";169;0
"Building";"CreepTumor";NA;169;0
"Unit";"Zergling";"Larva";169;1
"Unit";"Zergling";"Larva";169;1
"Unit";"Zergling";"Larva";169;1
"Unit";"Zergling";"Larva";169;1
"Unit";"Zergling";"Larva";169;1
"Unit";"Zergling";"Larva";169;1
"Unit";"Zergling";"Larva";169;1
"Unit";"Zergling";"Larva";169;1
"Unit";"Zergling";"Larva";169;1
"Unit";"Zergling";"Larva";169;1
"Building";"Hatchery";NA;131;0
"Building";"SporeCrawler";NA;169;0
"Upgrade";"EvolveGroovedSpines";"HydraliskDen";139;0
"Building";"CreepTumorQueen";NA;199;0
"Building";"CreepTumor";NA;199;0
"Building";"CreepTumorQueen";NA;199;0
"Unit";"Zergling";"Larva";199;1
"Unit";"Zergling";"Larva";199;1
"Unit";"Zergling";"Larva";199;1
"Unit";"Zergling";"Larva";199;1
"Unit";"Zergling";"Larva";199;1
"Unit";"Zergling";"Larva";199;1
"Unit";"Overlord";"Larva";199;0
"Unit";"Zergling";"Larva";199;1
"Unit";"Zergling";"Larva";199;1
"Unit";"Zergling";"Larva";199;1
"Unit";"Zergling";"Larva";199;1
"Unit";"Zergling";"Larva";199;1
"Unit";"Zergling";"Larva";199;1
"Unit";"Zergling";"Larva";199;1
"Unit";"Zergling";"Larva";199;1
"Unit";"Zergling";"Larva";199;1
"Unit";"Zergling";"Larva";199;1
"Unit";"Zergling";"Larva";199;1
"Unit";"Zergling";"Larva";199;1
"Unit";"Zergling";"Larva";199;1
"Unit";"Zergling";"Larva";199;1
"Unit";"Zergling";"Larva";199;1
"Unit";"Zergling";"Larva";199;1
"Unit";"Zergling";"Larva";199;1
"Unit";"Zergling";"Larva";199;1
"Unit";"Zergling";"Larva";199;1
"Unit";"Zergling";"Larva";199;1
"Unit";"Zergling";"Larva";199;1
"Unit";"Zergling";"Larva";199;1
"Unit";"Zergling";"Larva";199;1
"Unit";"Zergling";"Larva";199;1
"Unit";"Zergling";"Larva";199;1
"Unit";"Zergling";"Larva";199;1
"Unit";"Zergling";"Larva";199;1
"Unit";"Zergling";"Larva";199;1
"Building";"CreepTumorQueen";NA;199;0
"Building";"CreepTumorQueen";NA;199;0
"Building";"CreepTumorQueen";NA;199;0
"Unit";"Baneling";"Zergling";199;0
"Unit";"Baneling";"Zergling";199;0
"Unit";"Baneling";"Zergling";199;0
"Unit";"Baneling";"Zergling";199;0
"Unit";"Baneling";"Zergling";199;0
"Unit";"Baneling";"Zergling";199;0
"Unit";"Baneling";"Zergling";199;0
"Building";"CreepTumorQueen";NA;233;0
"Building";"CreepTumorQueen";NA;233;0
"Unit";"Queen";"Hatchery";199;2
"Building";"CreepTumorQueen";NA;233;0
"Building";"CreepTumorQueen";NA;233;0
"Building";"CreepTumorQueen";NA;233;0
"Unit";"Queen";"Hatchery";199;2
"Unit";"Zergling";"Larva";233;1
"Unit";"Zergling";"Larva";233;1
"Unit";"Zergling";"Larva";233;1
"Unit";"Zergling";"Larva";233;1
"Unit";"Zergling";"Larva";233;1
"Unit";"Zergling";"Larva";233;1
"Unit";"Zergling";"Larva";233;1
"Unit";"Zergling";"Larva";233;1
"Building";"CreepTumor";NA;246;0
"Building";"CreepTumor";NA;246;0
"Building";"Extractor";NA;233;0
"Building";"Extractor";NA;233;0
"Building";"CreepTumor";NA;246;0
"Building";"CreepTumor";NA;246;0
"Building";"CreepTumor";NA;248;0
"Building";"CreepTumor";NA;248;0
"Building";"CreepTumor";NA;248;0
"Building";"SporeCrawler";NA;246;0
"Unit";"Overlord";"Larva";256;0
"Unit";"Overlord";"Larva";256;0
"Unit";"Overlord";"Larva";256;0
"Unit";"Overlord";"Larva";256;0
"Unit";"Overlord";"Larva";256;0
"Unit";"Overlord";"Larva";256;0
"Upgrade";"EvolveMuscularAugments";"HydraliskDen";233;0
"Building";"CreepTumor";NA;256;0
"Building";"CreepTumorQueen";NA;256;0
"Unit";"Overlord";"Larva";256;0
"Building";"SporeCrawler";NA;256;0
"Unit";"Overlord";"Larva";256;0
"Unit";"Overlord";"Larva";256;0
"Building";"SporeCrawler";NA;256;0
"Building";"CreepTumor";NA;256;0
"Unit";"Overlord";"Larva";256;0
"Unit";"Overlord";"Larva";256;0
"Unit";"Zergling";"Larva";256;1
"Unit";"Zergling";"Larva";256;1
"Unit";"Zergling";"Larva";256;1
"Unit";"Zergling";"Larva";256;1
"Unit";"Zergling";"Larva";256;1
"Unit";"Zergling";"Larva";256;1
"Unit";"Zergling";"Larva";256;1
"Unit";"Zergling";"Larva";256;1
"Unit";"Zergling";"Larva";256;1
"Unit";"Zergling";"Larva";256;1
"Unit";"Zergling";"Larva";256;1
"Unit";"Zergling";"Larva";256;1
"Unit";"Zergling";"Larva";256;1
"Unit";"Zergling";"Larva";256;1
"Unit";"Zergling";"Larva";256;1
"Unit";"Zergling";"Larva";256;1
"Building";"CreepTumor";NA;256;0
"Building";"CreepTumor";NA;256;0
"Building";"CreepTumor";NA;256;0
"Building";"CreepTumor";NA;256;0
"Building";"CreepTumorQueen";NA;256;0
"Building";"CreepTumorQueen";NA;256;0
"Building";"CreepTumor";NA;256;0
"Building";"CreepTumor";NA;256;0
"Building";"CreepTumor";NA;256;0
"Building";"UltraliskCavern";NA;256;0
"Building";"CreepTumor";NA;256;0
"Unit";"Hydralisk";"Larva";256;2
"Unit";"Hydralisk";"Larva";256;2
"Unit";"Hydralisk";"Larva";256;2
"Unit";"Hydralisk";"Larva";256;2
"Unit";"Hydralisk";"Larva";256;2
"Building";"CreepTumorQueen";NA;256;0
"Building";"CreepTumorQueen";NA;256;0
"Building";"CreepTumor";NA;256;0
"Building";"CreepTumorQueen";NA;272;0
"Building";"CreepTumor";NA;272;0
"Building";"CreepTumor";NA;272;0
"Unit";"Hydralisk";"Larva";256;2
"Unit";"Hydralisk";"Larva";256;2
"Unit";"Hydralisk";"Larva";256;2
"Unit";"Hydralisk";"Larva";256;2
"Unit";"Hydralisk";"Larva";256;2
"Unit";"Hydralisk";"Larva";256;2
"Unit";"Hydralisk";"Larva";256;2
"Building";"CreepTumorQueen";NA;282;0
"Building";"CreepTumor";NA;282;0
"Building";"Spire";NA;256;0
"Unit";"Baneling";"Zergling";296;0
"Unit";"Baneling";"Zergling";296;0
"Unit";"Baneling";"Zergling";296;0
"Unit";"Baneling";"Zergling";296;0
"Unit";"Baneling";"Zergling";296;0
"Upgrade";"ZergMeleeWeaponsLevel2";"EvolutionChamber";248;0
"Upgrade";"ZergGroundArmorsLevel2";"EvolutionChamber";248;0
"Unit";"Ultralisk";"Larva";278;6
