"type";"unit_name";"on_building";"total_supply";"supply"
"Unit";"Overlord";"Larva";13;0
"Building";"SpawningPool";NA;18;0
"Building";"Hatchery";NA;17;0
"Unit";"Zergling";"Larva";21;1
"Unit";"Zergling";"Larva";21;1
"Unit";"Zergling";"Larva";21;1
"Unit";"Zergling";"Larva";21;1
"Unit";"Overlord";"Larva";21;0
"Unit";"Queen";"Hatchery";21;2
"Unit";"Queen";"Hatchery";21;2
"Building";"Hatchery";NA;21;0
"Unit";"Overlord";"Larva";31;0
"Unit";"Queen";"Hatchery";30;2
"Building";"CreepTumorQueen";NA;36;0
"Unit";"Queen";"Hatchery";33;2
"Building";"CreepTumorQueen";NA;41;0
"Unit";"Queen";"Hatchery";33;2
"Unit";"Overlord";"Larva";39;0
"Building";"Extractor";NA;46;0
"Building";"Extractor";NA;46;0
"Unit";"Queen";"Hatchery";43;2
"Building";"EvolutionChamber";NA;50;0
"Building";"EvolutionChamber";NA;52;0
"Building";"RoachWarren";NA;49;0
"Building";"CreepTumorQueen";NA;55;0
"Building";"SporeCrawler";NA;55;0
"Building";"SporeCrawler";NA;59;0
"Building";"SporeCrawler";NA;60;0
"Building";"CreepTumorQueen";NA;60;0
"Building";"CreepTumorQueen";NA;63;0
"Building";"CreepTumor";NA;63;0
"Unit";"Overlord";"Larva";60;0
"Unit";"Overlord";"Larva";60;0
"Building";"CreepTumor";NA;63;0
"Unit";"Queen";"Hatchery";60;2
"Unit";"Overlord";"Larva";63;0
"Unit";"Overlord";"Larva";63;0
"Building";"CreepTumorQueen";NA;65;0
"Building";"CreepTumorQueen";NA;65;0
"Building";"CreepTumorQueen";NA;65;0
"Building";"CreepTumorQueen";NA;69;0
"Building";"CreepTumor";NA;69;0
"Building";"CreepTumor";NA;77;0
"Building";"CreepTumorQueen";NA;77;0
"Building";"CreepTumorQueen";NA;77;0
"Unit";"Overlord";"Larva";78;0
"Unit";"Overlord";"Larva";78;0
"Building";"Extractor";NA;77;0
"Building";"Extractor";NA;78;0
"Building";"HydraliskDen";NA;77;0
"Building";"CreepTumor";NA;83;0
"Building";"InfestationPit";NA;77;0
"Building";"CreepTumor";NA;83;0
"Building";"CreepTumorQueen";NA;83;0
"Building";"CreepTumorQueen";NA;83;0
"Building";"CreepTumorQueen";NA;83;0
"Building";"CreepTumor";NA;91;0
"Building";"CreepTumor";NA;94;0
"Building";"CreepTumor";NA;96;0
"Building";"CreepTumorQueen";NA;96;0
"Building";"Extractor";NA;91;0
"Building";"Extractor";NA;96;0
"Upgrade";"ZergMissileWeaponsLevel1";"EvolutionChamber";69;0
"Building";"CreepTumorQueen";NA;97;0
"Building";"CreepTumorQueen";NA;97;0
"Unit";"Zergling";"Larva";96;1
"Unit";"Zergling";"Larva";96;1
"Unit";"Overlord";"Larva";97;0
"Unit";"Overlord";"Larva";97;0
"Building";"CreepTumorQueen";NA;99;0
"Building";"CreepTumorQueen";NA;101;0
"Building";"CreepTumor";NA;101;0
"Building";"CreepTumor";NA;101;0
"Building";"CreepTumor";NA;101;0
"Building";"CreepTumor";NA;101;0
"Building";"CreepTumor";NA;101;0
"Unit";"Roach";"Larva";104;2
"Unit";"Roach";"Larva";104;2
"Unit";"Roach";"Larva";104;2
"Unit";"Roach";"Larva";104;2
"Unit";"Roach";"Larva";104;2
"Unit";"Roach";"Larva";104;2
"Unit";"Roach";"Larva";104;2
"Unit";"Roach";"Larva";104;2
"Unit";"Roach";"Larva";104;2
"Unit";"Roach";"Larva";104;2
"Upgrade";"EvolveMuscularAugments";"HydraliskDen";97;0
"Building";"CreepTumorQueen";NA;116;0
"Building";"CreepTumorQueen";NA;116;0
"Unit";"Roach";"Larva";104;2
"Unit";"Roach";"Larva";104;2
"Unit";"Roach";"Larva";104;2
"Building";"CreepTumor";NA;122;0
"Building";"CreepTumorQueen";NA;124;0
"Building";"CreepTumorQueen";NA;124;0
"Building";"CreepTumorQueen";NA;124;0
"Unit";"Overlord";"Larva";124;0
"Unit";"Overlord";"Larva";124;0
"Unit";"Overlord";"Larva";124;0
"Unit";"Overlord";"Larva";124;0
"Unit";"Overlord";"Larva";124;0
"Unit";"Overlord";"Larva";124;0
"Building";"CreepTumor";NA;130;0
"Building";"CreepTumor";NA;130;0
"Building";"CreepTumor";NA;130;0
"Building";"CreepTumor";NA;130;0
"Building";"CreepTumor";NA;130;0
"Building";"CreepTumor";NA;130;0
"Upgrade";"GlialReconstitution";"RoachWarren";104;0
"Building";"CreepTumorQueen";NA;130;0
"Building";"CreepTumorQueen";NA;130;0
"Unit";"Hydralisk";"Larva";130;2
"Unit";"Hydralisk";"Larva";130;2
"Unit";"Hydralisk";"Larva";130;2
"Unit";"Hydralisk";"Larva";130;2
"Unit";"Hydralisk";"Larva";130;2
"Unit";"Hydralisk";"Larva";130;2
"Unit";"Hydralisk";"Larva";130;2
"Unit";"Hydralisk";"Larva";130;2
"Building";"CreepTumorQueen";NA;130;0
"Unit";"Queen";"Hatchery";130;2
"Unit";"Queen";"Hatchery";130;2
"Unit";"Queen";"Hatchery";130;2
"Building";"CreepTumorQueen";NA;146;0
"Building";"CreepTumorQueen";NA;146;0
"Building";"CreepTumorQueen";NA;146;0
"Unit";"Overlord";"Larva";146;0
"Unit";"Overlord";"Larva";146;0
"Building";"CreepTumor";NA;146;0
"Building";"CreepTumor";NA;146;0
"Building";"CreepTumor";NA;146;0
"Upgrade";"EvolveGroovedSpines";"HydraliskDen";130;0
"Building";"CreepTumor";NA;146;0
"Building";"CreepTumor";NA;146;0
"Building";"CreepTumor";NA;146;0
"Building";"CreepTumor";NA;152;0
"Building";"CreepTumor";NA;152;0
"Building";"CreepTumor";NA;152;0
"Building";"CreepTumor";NA;152;0
"Building";"CreepTumor";NA;152;0
"Building";"CreepTumorQueen";NA;152;0
"Building";"CreepTumorQueen";NA;152;0
"Unit";"Infestor";"Larva";146;2
"Unit";"Infestor";"Larva";146;2
"Unit";"Infestor";"Larva";146;2
"Building";"Extractor";NA;152;0
"Building";"Extractor";NA;152;0
"Upgrade";"ZergGroundArmorsLevel1";"EvolutionChamber";130;0
"Building";"Hatchery";NA;130;0
"Building";"CreepTumor";NA;160;0
"Building";"CreepTumor";NA;160;0
"Building";"CreepTumor";NA;160;0
"Building";"CreepTumor";NA;163;0
"Building";"SporeCrawler";NA;160;0
"Building";"Spire";NA;146;0
"Building";"CreepTumor";NA;169;0
"Building";"CreepTumor";NA;169;0
"Building";"CreepTumor";NA;169;0
"Unit";"Infestor";"Larva";160;2
"Unit";"Infestor";"Larva";160;2
"Building";"CreepTumor";NA;179;0
"Building";"CreepTumor";NA;179;0
"Building";"CreepTumor";NA;179;0
"Building";"CreepTumor";NA;179;0
"Unit";"Queen";"Hatchery";175;2
"Unit";"Corruptor";"Larva";175;2
"Unit";"Queen";"Hatchery";175;2
"Unit";"Corruptor";"Larva";175;2
"Unit";"Queen";"Hatchery";175;2
"Unit";"Corruptor";"Larva";175;2
"Unit";"Corruptor";"Larva";175;2
"Unit";"Corruptor";"Larva";175;2
"Unit";"Corruptor";"Larva";175;2
"Unit";"Queen";"Hatchery";175;2
"Unit";"Corruptor";"Larva";175;2
"Unit";"Corruptor";"Larva";175;2
"Building";"CreepTumor";NA;179;0
"Building";"CreepTumorQueen";NA;179;0
"Building";"CreepTumor";NA;179;0
"Building";"SpineCrawler";NA;175;0
"Building";"CreepTumor";NA;179;0
"Building";"CreepTumor";NA;179;0
"Building";"Hatchery";NA;175;0
"Upgrade";"ZergMissileWeaponsLevel2";"EvolutionChamber";169;0
"Unit";"Overlord";"Larva";203;0
"Unit";"Overlord";"Larva";203;0
"Unit";"Overlord";"Larva";203;0
"Unit";"Overlord";"Larva";203;0
"Unit";"Overlord";"Larva";203;0
"Unit";"Overlord";"Larva";203;0
"Unit";"Overlord";"Larva";203;0
"Unit";"Overlord";"Larva";203;0
"Unit";"Queen";"Hatchery";203;2
"Unit";"Queen";"Hatchery";203;2
"Unit";"Queen";"Hatchery";203;2
"Unit";"Queen";"Hatchery";203;2
"Unit";"Corruptor";"Larva";203;2
"Unit";"Corruptor";"Larva";203;2
"Unit";"Corruptor";"Larva";203;2
"Unit";"Corruptor";"Larva";203;2
"Upgrade";"ZergMeleeWeaponsLevel1";"EvolutionChamber";203;0
"Building";"Extractor";NA;221;0
"Building";"CreepTumorQueen";NA;221;0
"Building";"CreepTumorQueen";NA;221;0
"Unit";"Corruptor";"Larva";221;2
"Unit";"Corruptor";"Larva";221;2
"Unit";"Corruptor";"Larva";221;2
"Unit";"Corruptor";"Larva";221;2
"Unit";"Corruptor";"Larva";221;2
"Unit";"Corruptor";"Larva";221;2
"Unit";"Corruptor";"Larva";221;2
"Unit";"Corruptor";"Larva";221;2
"Building";"CreepTumorQueen";NA;221;0
"Building";"CreepTumor";NA;221;0
"Building";"CreepTumor";NA;221;0
"Building";"CreepTumorQueen";NA;221;0
"Building";"CreepTumor";NA;221;0
"Building";"CreepTumor";NA;241;0
"Building";"CreepTumor";NA;241;0
"Building";"CreepTumor";NA;241;0
"Building";"CreepTumor";NA;241;0
"Building";"Extractor";NA;241;0
"Building";"Extractor";NA;241;0
"Unit";"Overlord";"Larva";241;0
"Unit";"Overlord";"Larva";241;0
"Unit";"Corruptor";"Larva";241;2
"Unit";"Corruptor";"Larva";241;2
"Unit";"Corruptor";"Larva";241;2
"Unit";"Corruptor";"Larva";241;2
"Unit";"Corruptor";"Larva";241;2
"Unit";"Corruptor";"Larva";241;2
"Unit";"Corruptor";"Larva";241;2
"Building";"CreepTumorQueen";NA;244;0
"Building";"CreepTumorQueen";NA;244;0
"Upgrade";"Burrow";"Hatchery";241;0
"Building";"Hatchery";NA;241;0
