"type";"unit_name";"on_building";"total_supply";"supply"
"Unit";"Overlord";"Larva";13;0
"Building";"Extractor";NA;17;0
"Building";"Hatchery";NA;17;0
"Building";"SpawningPool";NA;19;0
"Unit";"Zergling";"Larva";23;1
"Unit";"Zergling";"Larva";23;1
"Unit";"Zergling";"Larva";23;1
"Unit";"Zergling";"Larva";23;1
"Unit";"Overlord";"Larva";24;0
"Unit";"Queen";"Hatchery";23;2
"Unit";"Queen";"Hatchery";23;2
"Unit";"Queen";"Hatchery";33;2
"Unit";"Overlord";"Larva";39;0
"Building";"CreepTumorQueen";NA;41;0
"Unit";"Queen";"Hatchery";41;2
"Building";"CreepTumorQueen";NA;48;0
"Building";"CreepTumor";NA;48;0
"Unit";"Overlord";"Larva";48;0
"Unit";"Overlord";"Larva";48;0
"Building";"Hatchery";NA;39;0
"Unit";"Queen";"Hatchery";48;2
"Unit";"Zergling";"Larva";50;1
"Unit";"Zergling";"Larva";50;1
"Unit";"Zergling";"Larva";50;1
"Unit";"Zergling";"Larva";50;1
"Unit";"Zergling";"Larva";50;1
"Unit";"Zergling";"Larva";50;1
"Unit";"Zergling";"Larva";50;1
"Unit";"Zergling";"Larva";50;1
"Unit";"Zergling";"Larva";50;1
"Unit";"Zergling";"Larva";50;1
"Unit";"Zergling";"Larva";50;1
"Unit";"Zergling";"Larva";50;1
"Building";"BanelingNest";NA;48;0
"Unit";"Queen";"Hatchery";50;2
"Building";"CreepTumor";NA;64;0
"Building";"CreepTumor";NA;64;0
"Unit";"Overlord";"Larva";52;0
"Unit";"Overlord";"Larva";54;0
"Unit";"Baneling";"Zergling";64;0
"Unit";"Baneling";"Zergling";64;0
"Unit";"Baneling";"Zergling";64;0
"Building";"CreepTumorQueen";NA;64;0
"Building";"Extractor";NA;64;0
"Building";"CreepTumor";NA;73;0
"Building";"CreepTumorQueen";NA;73;0
"Unit";"Overlord";"Larva";73;0
"Building";"EvolutionChamber";NA;73;0
"Building";"EvolutionChamber";NA;73;0
"Unit";"Baneling";"Zergling";81;0
"Unit";"Baneling";"Zergling";81;0
"Unit";"Baneling";"Zergling";81;0
"Unit";"Baneling";"Zergling";81;0
"Building";"CreepTumorQueen";NA;84;0
"Building";"CreepTumorQueen";NA;84;0
"Building";"CreepTumor";NA;84;0
"Unit";"Queen";"Hatchery";84;2
"Building";"Extractor";NA;89;0
"Unit";"Queen";"Hatchery";84;2
"Building";"CreepTumor";NA;95;0
"Building";"CreepTumor";NA;95;0
"Unit";"Overlord";"Larva";93;0
"Unit";"Overlord";"Larva";94;0
"Building";"CreepTumorQueen";NA;104;0
"Building";"Extractor";NA;104;0
"Building";"Extractor";NA;104;0
"Building";"Extractor";NA;104;0
"Building";"CreepTumor";NA;108;0
"Building";"CreepTumor";NA;108;0
"Building";"HydraliskDen";NA;108;0
"Building";"CreepTumorQueen";NA;114;0
"Unit";"Overlord";"Larva";114;0
"Unit";"Overlord";"Larva";114;0
"Unit";"Overlord";"Larva";114;0
"Unit";"Overlord";"Larva";114;0
"Unit";"Overlord";"Larva";114;0
"Building";"CreepTumor";NA;114;0
"Building";"CreepTumor";NA;114;0
"Unit";"Overlord";"Larva";114;0
"Unit";"Overlord";"Larva";114;0
"Upgrade";"ZergMissileWeaponsLevel1";"EvolutionChamber";104;0
"Building";"InfestationPit";NA;114;0
"Upgrade";"ZergGroundArmorsLevel1";"EvolutionChamber";104;0
"Unit";"Hydralisk";"Larva";114;2
"Unit";"Hydralisk";"Larva";114;2
"Unit";"Hydralisk";"Larva";114;2
"Unit";"Hydralisk";"Larva";114;2
"Unit";"Zergling";"Larva";116;1
"Unit";"Zergling";"Larva";116;1
"Unit";"Zergling";"Larva";116;1
"Unit";"Zergling";"Larva";116;1
"Unit";"Hydralisk";"Larva";116;2
"Unit";"Hydralisk";"Larva";116;2
"Unit";"Hydralisk";"Larva";116;2
"Unit";"Hydralisk";"Larva";116;2
"Building";"CreepTumor";NA;116;0
"Unit";"Baneling";"Zergling";116;0
"Unit";"Baneling";"Zergling";116;0
"Unit";"Baneling";"Zergling";116;0
"Unit";"Baneling";"Zergling";116;0
"Building";"CreepTumor";NA;136;0
"Unit";"Hydralisk";"Larva";124;2
"Unit";"Hydralisk";"Larva";124;2
"Unit";"Hydralisk";"Larva";124;2
"Unit";"Hydralisk";"Larva";124;2
"Unit";"Hydralisk";"Larva";124;2
"Building";"CreepTumorQueen";NA;136;0
"Building";"CreepTumorQueen";NA;136;0
"Building";"CreepTumorQueen";NA;146;0
"Unit";"Zergling";"Larva";136;1
"Unit";"Zergling";"Larva";136;1
"Unit";"Zergling";"Larva";136;1
"Unit";"Zergling";"Larva";136;1
"Unit";"Zergling";"Larva";136;1
"Unit";"Zergling";"Larva";136;1
"Unit";"Zergling";"Larva";136;1
"Unit";"Zergling";"Larva";136;1
"Unit";"Zergling";"Larva";136;1
"Unit";"Zergling";"Larva";136;1
"Unit";"Zergling";"Larva";136;1
"Unit";"Zergling";"Larva";136;1
"Unit";"Zergling";"Larva";136;1
"Unit";"Zergling";"Larva";136;1
"Unit";"Zergling";"Larva";136;1
"Unit";"Zergling";"Larva";136;1
"Unit";"Zergling";"Larva";136;1
"Unit";"Zergling";"Larva";136;1
"Unit";"Zergling";"Larva";136;1
"Unit";"Zergling";"Larva";136;1
"Unit";"Zergling";"Larva";136;1
"Unit";"Zergling";"Larva";136;1
"Unit";"Zergling";"Larva";136;1
"Unit";"Zergling";"Larva";136;1
"Unit";"Zergling";"Larva";136;1
"Unit";"Zergling";"Larva";136;1
"Unit";"Zergling";"Larva";136;1
"Unit";"Zergling";"Larva";136;1
"Upgrade";"EvolveGroovedSpines";"HydraliskDen";116;0
"Building";"Hatchery";NA;116;0
"Building";"CreepTumor";NA;174;0
"Building";"CreepTumor";NA;174;0
"Building";"CreepTumor";NA;174;0
"Unit";"Hydralisk";"Larva";174;2
"Unit";"Hydralisk";"Larva";174;2
"Unit";"Hydralisk";"Larva";174;2
"Unit";"Hydralisk";"Larva";174;2
"Building";"CreepTumor";NA;174;0
"Building";"CreepTumor";NA;174;0
"Building";"CreepTumor";NA;174;0
"Building";"CreepTumorQueen";NA;174;0
"Building";"CreepTumorQueen";NA;182;0
"Building";"CreepTumorQueen";NA;182;0
"Building";"CreepTumor";NA;182;0
"Building";"CreepTumor";NA;182;0
"Unit";"Overlord";"Larva";182;0
"Unit";"Overlord";"Larva";182;0
"Unit";"Overlord";"Larva";182;0
"Unit";"Overlord";"Larva";182;0
"Building";"CreepTumor";NA;182;0
"Unit";"Overlord";"Larva";182;0
"Unit";"Overlord";"Larva";182;0
"Unit";"Overlord";"Larva";182;0
"Building";"CreepTumor";NA;182;0
"Building";"CreepTumor";NA;182;0
"Building";"CreepTumorQueen";NA;182;0
"Building";"CreepTumorQueen";NA;182;0
"Building";"CreepTumor";NA;182;0
"Building";"CreepTumor";NA;182;0
"Building";"CreepTumor";NA;182;0
"Building";"CreepTumor";NA;182;0
"Building";"CreepTumorQueen";NA;182;0
"Upgrade";"EvolveMuscularAugments";"HydraliskDen";174;0
"Building";"CreepTumor";NA;182;0
"Building";"CreepTumor";NA;182;0
"Building";"CreepTumor";NA;182;0
"Building";"CreepTumor";NA;182;0
"Building";"CreepTumor";NA;182;0
"Building";"CreepTumor";NA;182;0
"Building";"CreepTumor";NA;182;0
"Building";"CreepTumor";NA;182;0
"Building";"Hatchery";NA;182;0
"Unit";"Hydralisk";"Larva";190;2
"Unit";"Hydralisk";"Larva";190;2
"Unit";"Hydralisk";"Larva";190;2
"Unit";"Hydralisk";"Larva";190;2
"Unit";"Hydralisk";"Larva";190;2
"Unit";"Hydralisk";"Larva";190;2
"Unit";"Hydralisk";"Larva";190;2
"Unit";"Hydralisk";"Larva";190;2
"Unit";"Hydralisk";"Larva";190;2
"Unit";"Hydralisk";"Larva";190;2
"Unit";"Hydralisk";"Larva";190;2
"Unit";"Hydralisk";"Larva";190;2
"Unit";"Hydralisk";"Larva";190;2
"Unit";"Hydralisk";"Larva";190;2
"Unit";"Zergling";"Larva";212;1
"Unit";"Zergling";"Larva";212;1
"Unit";"Zergling";"Larva";212;1
"Unit";"Zergling";"Larva";212;1
"Unit";"Zergling";"Larva";212;1
"Unit";"Zergling";"Larva";212;1
"Unit";"Zergling";"Larva";212;1
"Unit";"Zergling";"Larva";212;1
"Unit";"Zergling";"Larva";212;1
"Unit";"Zergling";"Larva";212;1
"Unit";"Zergling";"Larva";212;1
"Unit";"Zergling";"Larva";212;1
"Unit";"Zergling";"Larva";212;1
"Unit";"Zergling";"Larva";212;1
"Unit";"Hydralisk";"Larva";212;2
"Unit";"Hydralisk";"Larva";212;2
"Unit";"Hydralisk";"Larva";212;2
"Unit";"Hydralisk";"Larva";212;2
"Unit";"Hydralisk";"Larva";218;2
"Unit";"Hydralisk";"Larva";218;2
"Unit";"Hydralisk";"Larva";218;2
"Unit";"Hydralisk";"Larva";218;2
"Building";"CreepTumor";NA;240;0
"Building";"CreepTumor";NA;240;0
"Building";"CreepTumor";NA;240;0
"Building";"CreepTumor";NA;240;0
"Building";"CreepTumor";NA;240;0
"Building";"Extractor";NA;232;0
"Building";"Extractor";NA;240;0
"Unit";"Hydralisk";"Larva";240;2
"Unit";"Hydralisk";"Larva";240;2
"Upgrade";"ZergMissileWeaponsLevel2";"EvolutionChamber";182;0
"Unit";"Hydralisk";"Larva";240;2
"Unit";"Hydralisk";"Larva";240;2
"Unit";"Viper";"Larva";259;3
"Building";"Extractor";NA;262;0
"Unit";"Viper";"Larva";262;3
"Building";"Extractor";NA;262;0
"Unit";"Hydralisk";"Larva";262;2
"Unit";"Hydralisk";"Larva";262;2
"Unit";"Hydralisk";"Larva";262;2
"Unit";"Hydralisk";"Larva";262;2
"Unit";"Hydralisk";"Larva";262;2
"Unit";"Hydralisk";"Larva";262;2
"Unit";"Hydralisk";"Larva";262;2
"Building";"Spire";NA;248;0
"Unit";"Hydralisk";"Larva";268;2
"Unit";"Hydralisk";"Larva";268;2
"Unit";"Hydralisk";"Larva";268;2
"Unit";"Hydralisk";"Larva";268;2
"Unit";"Hydralisk";"Larva";268;2
"Unit";"Hydralisk";"Larva";268;2
"Unit";"Hydralisk";"Larva";268;2
"Unit";"Hydralisk";"Larva";270;2
"Unit";"Hydralisk";"Larva";270;2
"Unit";"Hydralisk";"Larva";282;2
"Unit";"Hydralisk";"Larva";282;2
"Unit";"Hydralisk";"Larva";282;2
"Unit";"Hydralisk";"Larva";282;2
"Unit";"Hydralisk";"Larva";282;2
"Unit";"Hydralisk";"Larva";282;2
"Unit";"Hydralisk";"Larva";300;2
"Unit";"Hydralisk";"Larva";300;2
"Unit";"Hydralisk";"Larva";300;2
"Unit";"Hydralisk";"Larva";300;2
"Unit";"Hydralisk";"Larva";320;2
"Unit";"Hydralisk";"Larva";320;2
"Unit";"Hydralisk";"Larva";320;2
"Unit";"Hydralisk";"Larva";320;2
"Unit";"Hydralisk";"Larva";320;2
"Unit";"Hydralisk";"Larva";320;2
"Unit";"Hydralisk";"Larva";320;2
"Unit";"Hydralisk";"Larva";320;2
"Unit";"Hydralisk";"Larva";320;2
"Unit";"Hydralisk";"Larva";338;2
"Unit";"Hydralisk";"Larva";338;2
"Unit";"Hydralisk";"Larva";338;2
"Unit";"Hydralisk";"Larva";338;2
"Unit";"Hydralisk";"Larva";338;2
"Unit";"Hydralisk";"Larva";338;2
"Unit";"Hydralisk";"Larva";338;2
"Unit";"Hydralisk";"Larva";338;2
"Unit";"Hydralisk";"Larva";342;2
"Unit";"Hydralisk";"Larva";342;2
"Unit";"Hydralisk";"Larva";344;2
"Unit";"Hydralisk";"Larva";344;2
"Unit";"Hydralisk";"Larva";344;2
"Unit";"Hydralisk";"Larva";344;2
"Unit";"Hydralisk";"Larva";344;2
"Unit";"Hydralisk";"Larva";346;2
"Unit";"Hydralisk";"Larva";346;2
"Unit";"Hydralisk";"Larva";346;2
"Building";"CreepTumorQueen";NA;352;0
"Unit";"Viper";"Larva";374;3
"Building";"CreepTumorQueen";NA;374;0
"Building";"Extractor";NA;374;0
"Building";"CreepTumorQueen";NA;378;0
"Unit";"Overlord";"Larva";374;0
"Unit";"Overlord";"Larva";374;0
"Unit";"Hydralisk";"Larva";377;2
"Unit";"Hydralisk";"Larva";377;2
"Unit";"Hydralisk";"Larva";377;2
"Building";"CreepTumorQueen";NA;378;0
"Unit";"Hydralisk";"Larva";377;2
"Unit";"Hydralisk";"Larva";377;2
"Building";"CreepTumor";NA;378;0
"Building";"CreepTumor";NA;378;0
"Building";"CreepTumorQueen";NA;378;0
"Building";"CreepTumorQueen";NA;378;0
"Building";"CreepTumor";NA;378;0
"Building";"CreepTumor";NA;378;0
"Building";"Hatchery";NA;352;0
"Building";"CreepTumor";NA;388;0
"Building";"Hatchery";NA;374;0
"Unit";"Hydralisk";"Larva";388;2
"Unit";"Hydralisk";"Larva";388;2
"Unit";"Hydralisk";"Larva";388;2
"Unit";"Hydralisk";"Larva";388;2
"Unit";"Hydralisk";"Larva";388;2
"Unit";"Hydralisk";"Larva";388;2
"Unit";"Hydralisk";"Larva";388;2
"Unit";"Hydralisk";"Larva";388;2
"Unit";"Hydralisk";"Larva";388;2
"Unit";"Hydralisk";"Larva";388;2
"Unit";"Hydralisk";"Larva";388;2
"Unit";"Hydralisk";"Larva";388;2
"Unit";"Hydralisk";"Larva";388;2
"Unit";"Hydralisk";"Larva";388;2
"Unit";"Hydralisk";"Larva";388;2
"Unit";"Hydralisk";"Larva";388;2
"Building";"CreepTumor";NA;388;0
"Unit";"Hydralisk";"Larva";388;2
"Unit";"Hydralisk";"Larva";388;2
"Unit";"Hydralisk";"Larva";388;2
"Unit";"Hydralisk";"Larva";388;2
"Building";"CreepTumor";NA;420;0
"Building";"CreepTumor";NA;420;0
"Building";"Extractor";NA;420;0
"Building";"CreepTumorQueen";NA;438;0
"Building";"CreepTumorQueen";NA;438;0
"Building";"CreepTumorQueen";NA;438;0
"Building";"CreepTumorQueen";NA;438;0
"Unit";"Viper";"Larva";438;3
"Unit";"Viper";"Larva";438;3
"Unit";"Hydralisk";"Larva";438;2
"Unit";"Hydralisk";"Larva";438;2
"Building";"CreepTumor";NA;444;0
"Building";"CreepTumorQueen";NA;444;0
"Unit";"Hydralisk";"Larva";438;2
"Unit";"Hydralisk";"Larva";438;2
"Unit";"Hydralisk";"Larva";438;2
"Unit";"Hydralisk";"Larva";438;2
"Unit";"Hydralisk";"Larva";438;2
"Unit";"Hydralisk";"Larva";438;2
"Unit";"Hydralisk";"Larva";438;2
"Building";"CreepTumor";NA;444;0
"Building";"CreepTumor";NA;444;0
"Building";"CreepTumor";NA;444;0
"Building";"CreepTumor";NA;444;0
"Building";"CreepTumor";NA;444;0
"Building";"CreepTumor";NA;467;0
"Building";"CreepTumor";NA;467;0
"Upgrade";"ZergMissileWeaponsLevel3";"EvolutionChamber";388;0
"Unit";"Hydralisk";"Larva";467;2
"Unit";"Hydralisk";"Larva";467;2
"Unit";"Hydralisk";"Larva";467;2
"Unit";"Hydralisk";"Larva";467;2
"Building";"Extractor";NA;467;0
"Building";"Extractor";NA;467;0
"Unit";"Hydralisk";"Larva";467;2
"Unit";"Zergling";"Larva";475;1
"Unit";"Zergling";"Larva";475;1
"Unit";"Hydralisk";"Larva";469;2
"Unit";"Hydralisk";"Larva";469;2
"Unit";"Hydralisk";"Larva";469;2
"Unit";"Hydralisk";"Larva";469;2
"Unit";"Hydralisk";"Larva";469;2
"Unit";"Zergling";"Larva";475;1
"Unit";"Zergling";"Larva";475;1
"Unit";"Zergling";"Larva";475;1
"Unit";"Zergling";"Larva";475;1
"Unit";"Hydralisk";"Larva";469;2
"Unit";"Hydralisk";"Larva";469;2
"Unit";"Zergling";"Larva";475;1
"Unit";"Zergling";"Larva";475;1
"Unit";"Zergling";"Larva";475;1
"Unit";"Zergling";"Larva";475;1
"Unit";"Hydralisk";"Larva";469;2
"Unit";"Hydralisk";"Larva";469;2
"Unit";"Zergling";"Larva";475;1
"Unit";"Zergling";"Larva";475;1
"Unit";"Hydralisk";"Larva";469;2
"Unit";"Zergling";"Larva";475;1
"Unit";"Zergling";"Larva";475;1
"Unit";"Zergling";"Larva";475;1
"Unit";"Zergling";"Larva";475;1
"Unit";"Zergling";"Larva";475;1
"Unit";"Zergling";"Larva";475;1
"Unit";"Zergling";"Larva";475;1
"Unit";"Zergling";"Larva";475;1
"Unit";"Zergling";"Larva";475;1
"Unit";"Zergling";"Larva";475;1
"Unit";"Zergling";"Larva";475;1
"Unit";"Zergling";"Larva";475;1
"Unit";"Zergling";"Larva";475;1
"Unit";"Zergling";"Larva";475;1
"Unit";"Zergling";"Larva";475;1
"Unit";"Zergling";"Larva";475;1
"Unit";"Zergling";"Larva";475;1
"Unit";"Zergling";"Larva";475;1
"Unit";"Zergling";"Larva";475;1
"Unit";"Zergling";"Larva";475;1
"Building";"CreepTumor";NA;529;0
"Building";"CreepTumor";NA;529;0
"Building";"CreepTumor";NA;529;0
"Building";"CreepTumor";NA;529;0
"Building";"CreepTumor";NA;529;0
"Building";"Hatchery";NA;467;0
"Unit";"Baneling";"Zergling";529;0
"Unit";"Baneling";"Zergling";529;0
"Unit";"Baneling";"Zergling";529;0
"Unit";"Baneling";"Zergling";529;0
"Unit";"Baneling";"Zergling";529;0
"Unit";"Baneling";"Zergling";529;0
"Unit";"Baneling";"Zergling";529;0
"Unit";"Hydralisk";"Larva";529;2
"Unit";"Hydralisk";"Larva";529;2
"Unit";"Hydralisk";"Larva";529;2
"Unit";"Hydralisk";"Larva";529;2
"Unit";"Hydralisk";"Larva";529;2
"Unit";"Hydralisk";"Larva";529;2
"Unit";"Hydralisk";"Larva";529;2
"Unit";"Hydralisk";"Larva";529;2
"Unit";"Hydralisk";"Larva";529;2
"Unit";"Hydralisk";"Larva";529;2
"Unit";"Hydralisk";"Larva";529;2
"Unit";"Hydralisk";"Larva";529;2
"Building";"Extractor";NA;529;0
"Building";"Extractor";NA;529;0
"Building";"CreepTumor";NA;553;0
"Building";"CreepTumor";NA;553;0
"Unit";"Viper";"Larva";553;3
"Unit";"Viper";"Larva";553;3
"Unit";"Viper";"Larva";553;3
"Building";"CreepTumor";NA;555;0
"Building";"CreepTumor";NA;556;0
"Building";"CreepTumor";NA;556;0
"Unit";"Hydralisk";"Larva";556;2
"Unit";"Hydralisk";"Larva";556;2
"Unit";"Hydralisk";"Larva";556;2
"Unit";"Hydralisk";"Larva";556;2
"Unit";"Hydralisk";"Larva";556;2
"Unit";"Hydralisk";"Larva";556;2
"Unit";"Hydralisk";"Larva";556;2
"Unit";"Hydralisk";"Larva";556;2
"Building";"CreepTumor";NA;581;0
"Building";"CreepTumorQueen";NA;581;0
"Building";"CreepTumor";NA;581;0
"Building";"CreepTumorQueen";NA;581;0
"Building";"CreepTumor";NA;581;0
"Unit";"Hydralisk";"Larva";581;2
"Unit";"Hydralisk";"Larva";581;2
"Unit";"Hydralisk";"Larva";581;2
"Unit";"Hydralisk";"Larva";581;2
"Unit";"Hydralisk";"Larva";581;2
"Unit";"Hydralisk";"Larva";581;2
"Unit";"Hydralisk";"Larva";581;2
"Unit";"Hydralisk";"Larva";581;2
"Unit";"Hydralisk";"Larva";581;2
"Building";"CreepTumorQueen";NA;581;0
"Building";"CreepTumorQueen";NA;581;0
"Unit";"Hydralisk";"Larva";599;2
"Unit";"Hydralisk";"Larva";599;2
"Unit";"Hydralisk";"Larva";599;2
"Unit";"Hydralisk";"Larva";599;2
"Unit";"Hydralisk";"Larva";599;2
"Unit";"Hydralisk";"Larva";599;2
"Unit";"Hydralisk";"Larva";599;2
"Unit";"Hydralisk";"Larva";599;2
"Unit";"Hydralisk";"Larva";599;2
"Unit";"Hydralisk";"Larva";599;2
"Unit";"Hydralisk";"Larva";599;2
"Unit";"Hydralisk";"Larva";599;2
"Unit";"Hydralisk";"Larva";623;2
"Unit";"Hydralisk";"Larva";623;2
"Unit";"Hydralisk";"Larva";623;2
"Unit";"Hydralisk";"Larva";623;2
"Unit";"Hydralisk";"Larva";623;2
"Unit";"Hydralisk";"Larva";623;2
"Unit";"Hydralisk";"Larva";623;2
"Unit";"Hydralisk";"Larva";623;2
"Unit";"Hydralisk";"Larva";623;2
"Unit";"Hydralisk";"Larva";623;2
"Unit";"Hydralisk";"Larva";623;2
"Unit";"Hydralisk";"Larva";623;2
"Unit";"Hydralisk";"Larva";623;2
"Unit";"Hydralisk";"Larva";623;2
"Unit";"Hydralisk";"Larva";623;2
"Unit";"Hydralisk";"Larva";623;2
"Unit";"Hydralisk";"Larva";623;2
"Upgrade";"ZergGroundArmorsLevel2";"EvolutionChamber";581;0
"Unit";"Viper";"Larva";623;3
"Unit";"Viper";"Larva";623;3
"Unit";"Hydralisk";"Larva";625;2
"Unit";"Viper";"Larva";623;3
"Unit";"Viper";"Larva";623;3
"Unit";"Hydralisk";"Larva";641;2
"Unit";"Hydralisk";"Larva";645;2
"Unit";"Hydralisk";"Larva";645;2
"Unit";"Hydralisk";"Larva";649;2
"Unit";"Hydralisk";"Larva";649;2
"Unit";"Hydralisk";"Larva";653;2
"Unit";"Hydralisk";"Larva";653;2
"Unit";"Hydralisk";"Larva";657;2
"Unit";"Hydralisk";"Larva";657;2
"Unit";"Hydralisk";"Larva";657;2
"Unit";"Hydralisk";"Larva";657;2
"Unit";"Hydralisk";"Larva";657;2
"Unit";"Hydralisk";"Larva";657;2
"Unit";"Hydralisk";"Larva";657;2
"Unit";"Hydralisk";"Larva";657;2
"Unit";"Hydralisk";"Larva";695;2
"Unit";"Hydralisk";"Larva";701;2
"Unit";"Hydralisk";"Larva";701;2
"Unit";"Hydralisk";"Larva";701;2
"Unit";"Hydralisk";"Larva";701;2
"Unit";"Hydralisk";"Larva";701;2
"Unit";"Hydralisk";"Larva";701;2
"Unit";"Hydralisk";"Larva";701;2
"Unit";"Hydralisk";"Larva";701;2
"Unit";"Hydralisk";"Larva";701;2
"Unit";"Hydralisk";"Larva";701;2
"Building";"CreepTumor";NA;717;0
"Unit";"Hydralisk";"Larva";701;2
"Unit";"Hydralisk";"Larva";701;2
"Unit";"Hydralisk";"Larva";701;2
"Unit";"Hydralisk";"Larva";703;2
"Building";"CreepTumor";NA;731;0
"Building";"CreepTumor";NA;731;0
"Unit";"Hydralisk";"Larva";731;2
"Unit";"Hydralisk";"Larva";731;2
"Unit";"Hydralisk";"Larva";731;2
"Unit";"Hydralisk";"Larva";731;2
"Unit";"Hydralisk";"Larva";731;2
"Unit";"Hydralisk";"Larva";731;2
"Unit";"Hydralisk";"Larva";731;2
"Unit";"Hydralisk";"Larva";731;2
"Building";"Extractor";NA;731;0
"Building";"Extractor";NA;731;0
"Building";"Extractor";NA;731;0
"Building";"Hatchery";NA;723;0
"Building";"Hatchery";NA;723;0
"Building";"CreepTumor";NA;747;0
"Building";"CreepTumor";NA;747;0
"Building";"Extractor";NA;747;0
"Building";"Extractor";NA;747;0
"Building";"CreepTumor";NA;753;0
"Building";"CreepTumor";NA;753;0
"Building";"CreepTumor";NA;753;0
"Building";"CreepTumor";NA;753;0
"Unit";"Queen";"Hatchery";753;2
"Building";"CreepTumorQueen";NA;755;0
"Building";"CreepTumor";NA;755;0
"Building";"CreepTumor";NA;755;0
"Building";"CreepTumor";NA;755;0
"Upgrade";"ZergGroundArmorsLevel3";"EvolutionChamber";753;0
