"type";"unit_name";"on_building";"total_supply";"supply"
"Building";"Pylon";NA;13;0
"Building";"Assimilator";NA;15;0
"Building";"Gateway";NA;15;0
"Building";"CyberneticsCore";NA;20;0
"Building";"Assimilator";NA;20;0
"Building";"Pylon";NA;21;0
"Unit";"Adept";"Gateway";22;2
"Building";"Nexus";NA;19;0
"Unit";"Stalker";"Gateway";26;2
"Building";"Pylon";NA;33;0
"Building";"Stargate";NA;30;0
"Unit";"Stalker";"Gateway";37;2
"Unit";"Oracle";"Stargate";38;3
"Building";"Pylon";NA;41;0
"Building";"ShieldBattery";NA;41;0
"Building";"ShieldBattery";NA;41;0
"Unit";"Stalker";"Gateway";42;2
"Building";"Assimilator";NA;47;0
"Building";"Gateway";NA;41;0
"Building";"Gateway";NA;41;0
"Unit";"Oracle";"Stargate";47;3
"Unit";"Stalker";"Gateway";57;2
"Unit";"Stalker";"Gateway";57;2
"Building";"Pylon";NA;54;0
"Unit";"Stalker";"Gateway";61;2
"Building";"TwilightCouncil";NA;50;0
"Building";"Assimilator";NA;54;0
"Unit";"Stalker";"Gateway";67;2
"Unit";"Stalker";"Gateway";67;2
"Unit";"Phoenix";"Stargate";65;2
"Building";"Nexus";NA;54;0
"Unit";"Stalker";"Gateway";74;2
"Building";"Pylon";NA;68;0
"Building";"Pylon";NA;72;0
"Unit";"Stalker";"Gateway";76;2
"Unit";"Stalker";"Gateway";76;2
"Unit";"Stalker";"Gateway";80;2
"Unit";"Phoenix";"Stargate";85;2
"Building";"Forge";NA;85;0
"Building";"Forge";NA;85;0
"Unit";"Stalker";"Gateway";97;2
"Building";"Pylon";NA;95;0
"Unit";"Zealot";"Gateway";97;2
"Unit";"Zealot";"Gateway";97;2
"Building";"Pylon";NA;95;0
"Building";"Gateway";NA;91;0
"Building";"Gateway";NA;95;0
"Building";"Assimilator";NA;105;0
"Building";"Assimilator";NA;105;0
"Unit";"Zealot";"Gateway";108;2
"Unit";"Zealot";"Gateway";108;2
"Unit";"Zealot";"Gateway";108;2
"Unit";"Zealot";"Gateway";108;2
"Unit";"Zealot";"Gateway";108;2
"Building";"TemplarArchive";NA;105;0
"Building";"Gateway";NA;105;0
"Building";"Gateway";NA;105;0
"Building";"Pylon";NA;118;0
"Building";"Pylon";NA;118;0
"Building";"Pylon";NA;120;0
"Building";"Pylon";NA;120;0
"Building";"Pylon";NA;121;0
"Building";"RoboticsFacility";NA;118;0
"Building";"Pylon";NA;121;0
"Building";"Pylon";NA;121;0
"Upgrade";"ProtossGroundWeaponsLevel1";"Forge";103;0
"Building";"Pylon";NA;121;0
"Unit";"Zealot";"Gateway";121;2
"Unit";"Zealot";"Gateway";121;2
"Unit";"Zealot";"Gateway";121;2
"Unit";"Zealot";"Gateway";121;2
"Unit";"Zealot";"Gateway";121;2
"Upgrade";"Charge";"TwilightCouncil";107;0
"Upgrade";"ProtossGroundArmorsLevel1";"Forge";105;0
"Building";"HighTemplar";NA;131;0
"Building";"HighTemplar";NA;131;0
"Unit";"Zealot";"Gateway";131;2
"Unit";"Zealot";"Gateway";131;2
"Unit";"Zealot";"Gateway";131;2
"Unit";"Zealot";"Gateway";131;2
"Unit";"Zealot";"Gateway";131;2
"Unit";"Zealot";"Gateway";141;2
"Unit";"Zealot";"Gateway";141;2
"Building";"HighTemplar";NA;145;0
"Building";"HighTemplar";NA;145;0
"Unit";"Zealot";"Gateway";145;2
"Unit";"Zealot";"Gateway";145;2
"Unit";"Zealot";"Gateway";145;2
"Unit";"Zealot";"Gateway";145;2
"Unit";"Zealot";"Gateway";145;2
"Building";"Gateway";NA;141;0
"Building";"Gateway";NA;141;0
"Building";"Gateway";NA;141;0
"Building";"Gateway";NA;141;0
"Building";"HighTemplar";NA;157;0
"Building";"HighTemplar";NA;157;0
"Building";"HighTemplar";NA;157;0
"Building";"HighTemplar";NA;157;0
"Building";"HighTemplar";NA;157;0
"Building";"HighTemplar";NA;157;0
"Building";"HighTemplar";NA;157;0
"Building";"HighTemplar";NA;157;0
"Upgrade";"ProtossGroundWeaponsLevel2";"Forge";131;0
"Building";"HighTemplar";NA;157;0
"Building";"Pylon";NA;157;0
"Building";"Pylon";NA;157;0
"Unit";"Archon";"High Templar";157;0
"Unit";"Archon";"High Templar";157;0
"Unit";"Archon";"High Templar";157;0
"Unit";"Immortal";"Robotics Facility";145;4
"Upgrade";"ProtossGroundArmorsLevel2";"Forge";131;0
"Unit";"Stalker";"Gateway";157;2
"Unit";"Stalker";"Gateway";157;2
"Unit";"Archon";"High Templar";157;0
"Building";"Pylon";NA;157;0
"Building";"RoboticsFacility";NA;155;0
"Unit";"Zealot";"Gateway";165;2
"Unit";"Zealot";"Gateway";165;2
"Unit";"Zealot";"Gateway";165;2
"Unit";"Zealot";"Gateway";165;2
"Unit";"Zealot";"Gateway";165;2
"Building";"Assimilator";NA;165;0
"Building";"HighTemplar";NA;175;0
"Building";"HighTemplar";NA;175;0
"Unit";"Zealot";"Gateway";175;2
"Building";"Pylon";NA;165;0
"Building";"Assimilator";NA;165;0
"Unit";"Observer";"Robotics Facility";165;1
"Unit";"Zealot";"Gateway";177;2
"Unit";"Zealot";"Gateway";177;2
"Unit";"Zealot";"Gateway";180;2
"Unit";"Archon";"High Templar";175;0
"Building";"Nexus";NA;155;0
"Building";"RoboticsBay";NA;165;0
"Unit";"Stalker";"Gateway";184;2
"Unit";"Stalker";"Gateway";184;2
"Unit";"Stalker";"Gateway";184;2
"Unit";"Stalker";"Gateway";184;2
"Unit";"Stalker";"Gateway";184;2
"Unit";"Stalker";"Gateway";184;2
"Unit";"Stalker";"Gateway";184;2
"Unit";"Stalker";"Gateway";198;2
"Unit";"Stalker";"Gateway";198;2
"Unit";"Stalker";"Gateway";198;2
"Unit";"Stalker";"Gateway";198;2
"Unit";"Stalker";"Gateway";198;2
"Unit";"Stalker";"Gateway";198;2
"Unit";"Zealot";"Gateway";198;2
"Unit";"Zealot";"Gateway";198;2
"Unit";"Zealot";"Gateway";198;2
"Building";"HighTemplar";NA;216;0
"Building";"HighTemplar";NA;216;0
"Building";"HighTemplar";NA;216;0
"Building";"HighTemplar";NA;216;0
"Unit";"Zealot";"Gateway";216;2
"Unit";"Zealot";"Gateway";216;2
"Unit";"Zealot";"Gateway";216;2
"Unit";"Zealot";"Gateway";216;2
"Unit";"Archon";"High Templar";224;0
"Unit";"Archon";"High Templar";224;0
"Upgrade";"ProtossGroundWeaponsLevel3";"Forge";165;0
"Upgrade";"ProtossGroundArmorsLevel3";"Forge";165;0
"Unit";"Stalker";"Gateway";224;2
"Unit";"Stalker";"Gateway";224;2
"Unit";"Stalker";"Gateway";224;2
"Unit";"Stalker";"Gateway";224;2
"Unit";"Stalker";"Gateway";224;2
"Building";"HighTemplar";NA;234;0
"Building";"HighTemplar";NA;234;0
"Unit";"Zealot";"Gateway";234;2
"Unit";"Zealot";"Gateway";234;2
"Unit";"Zealot";"Gateway";234;2
"Unit";"Zealot";"Gateway";234;2
"Unit";"Zealot";"Gateway";242;2
"Unit";"Zealot";"Gateway";242;2
"Unit";"Colossus";"Robotics Facility";224;6
"Building";"RoboticsFacility";NA;224;0
"Unit";"Archon";"High Templar";242;0
"Unit";"Observer";"Robotics Facility";242;1
"Building";"Assimilator";NA;253;0
"Unit";"Colossus";"Robotics Facility";252;6
"Building";"Pylon";NA;253;0
"Building";"Assimilator";NA;253;0
"Building";"Pylon";NA;253;0
"Upgrade";"ExtendedThermalLance";"RoboticsBay";242;0
"Upgrade";"ProtossShieldsLevel1";"Forge";242;0
"Unit";"Colossus";"Robotics Facility";253;6
"Building";"Nexus";NA;252;0
"Building";"PhotonCannon";NA;259;0
"Building";"PhotonCannon";NA;259;0
"Unit";"Zealot";"Gateway";265;2
"Unit";"Zealot";"Gateway";265;2
"Unit";"Zealot";"Gateway";265;2
"Unit";"Zealot";"Gateway";265;2
"Building";"PhotonCannon";NA;259;0
"Building";"ShieldBattery";NA;265;0
"Building";"ShieldBattery";NA;265;0
"Unit";"Zealot";"Gateway";273;2
"Unit";"Zealot";"Gateway";273;2
"Unit";"Zealot";"Gateway";273;2
"Unit";"Zealot";"Gateway";273;2
"Unit";"Zealot";"Gateway";273;2
"Unit";"Zealot";"Gateway";273;2
"Unit";"Zealot";"Gateway";273;2
"Building";"DarkShrine";NA;253;0
