"type";"unit_name";"on_building";"total_supply";"supply"
"Unit";"Overlord";"Larva";13;0
"Building";"Extractor";NA;18;0
"Unit";"Overlord";"Larva";21;0
"Building";"SpawningPool";NA;19;0
"Building";"Hatchery";NA;17;0
"Unit";"Zergling";"Larva";22;1
"Unit";"Zergling";"Larva";22;1
"Unit";"Zergling";"Larva";22;1
"Unit";"Zergling";"Larva";22;1
"Unit";"Queen";"Hatchery";22;2
"Unit";"Queen";"Hatchery";22;2
"Building";"SpineCrawler";NA;23;0
"Unit";"Zergling";"Larva";33;1
"Unit";"Zergling";"Larva";33;1
"Unit";"Zergling";"Larva";33;1
"Unit";"Zergling";"Larva";33;1
"Building";"BanelingNest";NA;23;0
"Unit";"Zergling";"Larva";33;1
"Unit";"Zergling";"Larva";33;1
"Unit";"Zergling";"Larva";33;1
"Unit";"Zergling";"Larva";33;1
"Unit";"Zergling";"Larva";33;1
"Unit";"Zergling";"Larva";33;1
"Unit";"Zergling";"Larva";33;1
"Unit";"Zergling";"Larva";33;1
"Unit";"Overlord";"Larva";51;0
"Unit";"Baneling";"Zergling";52;0
"Unit";"Baneling";"Zergling";52;0
"Unit";"Zergling";"Larva";52;1
"Unit";"Zergling";"Larva";52;1
"Unit";"Zergling";"Larva";52;1
"Unit";"Zergling";"Larva";52;1
"Unit";"Zergling";"Larva";52;1
"Unit";"Zergling";"Larva";52;1
"Unit";"Zergling";"Larva";53;1
"Unit";"Zergling";"Larva";53;1
"Unit";"Baneling";"Zergling";55;0
"Unit";"Baneling";"Zergling";55;0
"Unit";"Zergling";"Larva";58;1
"Unit";"Zergling";"Larva";58;1
"Unit";"Overlord";"Larva";70;0
"Building";"Extractor";NA;70;0
"Building";"EvolutionChamber";NA;70;0
"Building";"Extractor";NA;70;0
"Building";"Hatchery";NA;52;0
"Building";"RoachWarren";NA;70;0
"Building";"Extractor";NA;81;0
"Building";"EvolutionChamber";NA;86;0
"Building";"SporeCrawler";NA;89;0
"Building";"SporeCrawler";NA;93;0
"Building";"HydraliskDen";NA;93;0
"Unit";"Roach";"Larva";93;2
"Unit";"Roach";"Larva";93;2
"Unit";"Roach";"Larva";93;2
"Unit";"Overlord";"Larva";93;0
"Unit";"Overlord";"Larva";93;0
"Unit";"Overlord";"Larva";93;0
"Unit";"Roach";"Larva";93;2
"Unit";"Overlord";"Larva";93;0
"Unit";"Overlord";"Larva";99;0
"Unit";"Overlord";"Larva";99;0
"Unit";"Roach";"Larva";99;2
"Unit";"Roach";"Larva";99;2
"Building";"CreepTumorQueen";NA;105;0
"Upgrade";"GlialReconstitution";"RoachWarren";93;0
"Building";"SporeCrawler";NA;105;0
"Building";"CreepTumorQueen";NA;105;0
"Unit";"Hydralisk";"Larva";105;2
"Unit";"Hydralisk";"Larva";105;2
"Unit";"Hydralisk";"Larva";105;2
"Unit";"Hydralisk";"Larva";105;2
"Unit";"Hydralisk";"Larva";105;2
"Upgrade";"ZergGroundArmorsLevel1";"EvolutionChamber";93;0
"Unit";"Hydralisk";"Larva";105;2
"Unit";"Queen";"Hatchery";105;2
"Unit";"Queen";"Hatchery";105;2
"Unit";"Hydralisk";"Larva";105;2
"Unit";"Hydralisk";"Larva";105;2
"Building";"CreepTumorQueen";NA;123;0
"Building";"CreepTumor";NA;123;0
"Unit";"Hydralisk";"Larva";105;2
"Unit";"Hydralisk";"Larva";105;2
"Building";"CreepTumor";NA;125;0
"Upgrade";"EvolveGroovedSpines";"HydraliskDen";105;0
"Upgrade";"ZergMissileWeaponsLevel1";"EvolutionChamber";99;0
"Unit";"Hydralisk";"Larva";133;2
"Unit";"Hydralisk";"Larva";133;2
"Unit";"Hydralisk";"Larva";133;2
"Unit";"Hydralisk";"Larva";133;2
"Unit";"Roach";"Larva";133;2
"Unit";"Roach";"Larva";133;2
"Unit";"Overlord";"Larva";133;0
"Building";"CreepTumorQueen";NA;133;0
"Unit";"Hydralisk";"Larva";133;2
"Building";"CreepTumorQueen";NA;145;0
"Unit";"Overlord";"Larva";145;0
"Building";"Hatchery";NA;126;0
"Unit";"Hydralisk";"Larva";149;2
"Unit";"Hydralisk";"Larva";149;2
"Unit";"Hydralisk";"Larva";149;2
"Unit";"Hydralisk";"Larva";149;2
"Unit";"Hydralisk";"Larva";149;2
"Unit";"Hydralisk";"Larva";149;2
"Unit";"Hydralisk";"Larva";149;2
"Building";"CreepTumor";NA;149;0
"Upgrade";"EvolveMuscularAugments";"HydraliskDen";145;0
"Building";"CreepTumorQueen";NA;163;0
"Unit";"Hydralisk";"Larva";149;2
"Unit";"Hydralisk";"Larva";149;2
"Unit";"Hydralisk";"Larva";149;2
"Unit";"Hydralisk";"Larva";149;2
"Building";"CreepTumor";NA;174;0
"Unit";"Hydralisk";"Larva";163;2
"Unit";"Hydralisk";"Larva";163;2
"Unit";"Hydralisk";"Larva";163;2
"Upgrade";"ZergGroundArmorsLevel2";"EvolutionChamber";133;0
"Unit";"Roach";"Larva";174;2
"Unit";"Roach";"Larva";174;2
"Unit";"Roach";"Larva";174;2
"Unit";"Roach";"Larva";174;2
"Building";"CreepTumor";NA;180;0
"Unit";"Roach";"Larva";174;2
"Unit";"Roach";"Larva";174;2
"Unit";"Roach";"Larva";180;2
"Unit";"Roach";"Larva";180;2
"Unit";"Overlord";"Larva";180;0
"Building";"SporeCrawler";NA;180;0
"Unit";"Overlord";"Larva";184;0
"Unit";"Overlord";"Larva";184;0
"Unit";"Roach";"Larva";184;2
"Unit";"Roach";"Larva";184;2
"Unit";"Roach";"Larva";196;2
"Unit";"Roach";"Larva";196;2
"Unit";"Roach";"Larva";200;2
"Unit";"Roach";"Larva";200;2
"Unit";"Roach";"Larva";200;2
"Unit";"Roach";"Larva";200;2
"Unit";"Roach";"Larva";200;2
"Building";"CreepTumor";NA;200;0
"Unit";"Roach";"Larva";200;2
"Unit";"Overlord";"Larva";200;0
"Unit";"Overlord";"Larva";216;0
"Unit";"Overlord";"Larva";216;0
"Unit";"Hydralisk";"Larva";208;2
"Unit";"Hydralisk";"Larva";208;2
"Unit";"Hydralisk";"Larva";208;2
"Unit";"Hydralisk";"Larva";208;2
"Building";"Extractor";NA;218;0
"Building";"Extractor";NA;218;0
"Building";"SporeCrawler";NA;218;0
"Unit";"Hydralisk";"Larva";221;2
"Unit";"Hydralisk";"Larva";221;2
"Unit";"Hydralisk";"Larva";229;2
"Unit";"Hydralisk";"Larva";230;2
"Unit";"Hydralisk";"Larva";230;2
"Unit";"Hydralisk";"Larva";230;2
"Unit";"Hydralisk";"Larva";230;2
"Upgrade";"ZergMissileWeaponsLevel2";"EvolutionChamber";192;0
"Unit";"Hydralisk";"Larva";234;2
"Unit";"Hydralisk";"Larva";234;2
"Unit";"Hydralisk";"Larva";238;2
"Unit";"Hydralisk";"Larva";248;2
"Unit";"Hydralisk";"Larva";256;2
"Unit";"Hydralisk";"Larva";258;2
"Building";"LurkerDenMP";NA;229;0
"Unit";"Hydralisk";"Larva";258;2
"Unit";"Hydralisk";"Larva";258;2
"Unit";"Roach";"Larva";258;2
"Unit";"Hydralisk";"Larva";258;2
"Unit";"Hydralisk";"Larva";260;2
"Unit";"Hydralisk";"Larva";260;2
"Unit";"Hydralisk";"Larva";266;2
"Unit";"Hydralisk";"Larva";270;2
"Unit";"Hydralisk";"Larva";274;2
"Unit";"Hydralisk";"Larva";274;2
"Unit";"Hydralisk";"Larva";278;2
"Building";"Hatchery";NA;258;0
"Unit";"Hydralisk";"Larva";282;2
"Unit";"Hydralisk";"Larva";282;2
"Unit";"Hydralisk";"Larva";282;2
"Unit";"Hydralisk";"Larva";282;2
"Unit";"Hydralisk";"Larva";282;2
"Unit";"Hydralisk";"Larva";282;2
"Unit";"Roach";"Larva";284;2
"Unit";"Hydralisk";"Larva";282;2
"Unit";"Hydralisk";"Larva";284;2
"Unit";"Hydralisk";"Larva";300;2
"Unit";"Hydralisk";"Larva";300;2
"Unit";"Hydralisk";"Larva";300;2
"Unit";"Hydralisk";"Larva";300;2
"Unit";"Hydralisk";"Larva";300;2
"Unit";"Hydralisk";"Larva";302;2
"Unit";"Hydralisk";"Larva";302;2
