"type";"unit_name";"on_building";"total_supply";"supply"
"Unit";"Overlord";"Larva";12;0
"Building";"Extractor";NA;18;0
"Unit";"Overlord";"Larva";21;0
"Building";"SpawningPool";NA;19;0
"Building";"Hatchery";NA;17;0
"Unit";"Zergling";"Larva";23;1
"Unit";"Zergling";"Larva";23;1
"Unit";"Queen";"Hatchery";23;2
"Unit";"Queen";"Hatchery";23;2
"Unit";"Zergling";"Larva";34;1
"Unit";"Zergling";"Larva";34;1
"Unit";"Zergling";"Larva";34;1
"Unit";"Zergling";"Larva";34;1
"Unit";"Zergling";"Larva";34;1
"Unit";"Zergling";"Larva";34;1
"Unit";"Zergling";"Larva";38;1
"Unit";"Zergling";"Larva";38;1
"Unit";"Zergling";"Larva";38;1
"Unit";"Zergling";"Larva";38;1
"Building";"BanelingNest";NA;34;0
"Unit";"Overlord";"Larva";42;0
"Unit";"Zergling";"Larva";42;1
"Unit";"Zergling";"Larva";42;1
"Unit";"Zergling";"Larva";44;1
"Unit";"Zergling";"Larva";44;1
"Building";"Hatchery";NA;31;0
"Unit";"Overlord";"Larva";50;0
"Unit";"Baneling";"Zergling";53;0
"Unit";"Baneling";"Zergling";53;0
"Unit";"Queen";"Hatchery";46;2
"Building";"EvolutionChamber";NA;53;0
"Unit";"Zergling";"Larva";63;1
"Unit";"Zergling";"Larva";63;1
"Unit";"Zergling";"Larva";63;1
"Unit";"Zergling";"Larva";63;1
"Unit";"Zergling";"Larva";63;1
"Unit";"Zergling";"Larva";63;1
"Unit";"Zergling";"Larva";63;1
"Unit";"Zergling";"Larva";63;1
"Building";"Extractor";NA;63;0
"Building";"CreepTumorQueen";NA;63;0
"Unit";"Queen";"Hatchery";59;2
"Unit";"Overlord";"Larva";63;0
"Building";"RoachWarren";NA;63;0
"Unit";"Overlord";"Larva";73;0
"Unit";"Overlord";"Larva";73;0
"Unit";"Overlord";"Larva";73;0
"Building";"CreepTumor";NA;81;0
"Building";"CreepTumorQueen";NA;81;0
"Unit";"Roach";"Larva";79;2
"Unit";"Roach";"Larva";79;2
"Unit";"Roach";"Larva";79;2
"Unit";"Roach";"Larva";79;2
"Unit";"Roach";"Larva";79;2
"Building";"Extractor";NA;81;0
"Unit";"Roach";"Larva";81;2
"Unit";"Roach";"Larva";81;2
"Unit";"Roach";"Larva";81;2
"Unit";"Roach";"Larva";81;2
"Unit";"Overlord";"Larva";81;0
"Unit";"Overlord";"Larva";81;0
"Building";"Extractor";NA;91;0
"Unit";"Overlord";"Larva";91;0
"Building";"CreepTumor";NA;104;0
"Building";"CreepTumor";NA;104;0
"Unit";"Overlord";"Larva";102;0
"Upgrade";"ZergMissileWeaponsLevel1";"EvolutionChamber";73;0
"Unit";"Roach";"Larva";104;2
"Unit";"Roach";"Larva";104;2
"Unit";"Roach";"Larva";104;2
"Unit";"Roach";"Larva";104;2
"Unit";"Roach";"Larva";104;2
"Unit";"Roach";"Larva";104;2
"Building";"CreepTumorQueen";NA;108;0
"Building";"CreepTumor";NA;127;0
"Unit";"Overlord";"Larva";127;0
"Building";"Extractor";NA;127;0
"Unit";"Overlord";"Larva";134;0
"Unit";"Overlord";"Larva";134;0
"Upgrade";"GlialReconstitution";"RoachWarren";120;0
"Unit";"Roach";"Larva";134;2
"Unit";"Roach";"Larva";134;2
"Unit";"Roach";"Larva";134;2
"Unit";"Roach";"Larva";134;2
"Unit";"Roach";"Larva";134;2
"Building";"CreepTumor";NA;134;0
"Building";"CreepTumor";NA;136;0
"Building";"CreepTumor";NA;136;0
"Building";"CreepTumorQueen";NA;136;0
"Unit";"Overlord";"Larva";136;0
"Unit";"Overlord";"Larva";136;0
"Building";"Extractor";NA;146;0
"Unit";"Overlord";"Larva";146;0
"Unit";"Overlord";"Larva";146;0
"Unit";"Roach";"Larva";146;2
"Unit";"Roach";"Larva";146;2
"Unit";"Roach";"Larva";146;2
"Unit";"Roach";"Larva";146;2
"Unit";"Roach";"Larva";146;2
"Unit";"Roach";"Larva";146;2
"Unit";"Roach";"Larva";146;2
"Unit";"Roach";"Larva";146;2
"Unit";"Roach";"Larva";146;2
"Unit";"Roach";"Larva";146;2
"Unit";"Roach";"Larva";150;2
"Unit";"Roach";"Larva";150;2
"Unit";"Roach";"Larva";150;2
"Unit";"Roach";"Larva";150;2
"Unit";"Roach";"Larva";150;2
"Building";"HydraliskDen";NA;150;0
"Unit";"Roach";"Larva";170;2
"Unit";"Roach";"Larva";170;2
"Unit";"Roach";"Larva";170;2
"Unit";"Roach";"Larva";170;2
"Unit";"Roach";"Larva";170;2
"Unit";"Roach";"Larva";170;2
"Unit";"Roach";"Larva";180;2
"Unit";"Roach";"Larva";180;2
"Unit";"Roach";"Larva";180;2
"Upgrade";"ZergMissileWeaponsLevel2";"EvolutionChamber";134;0
"Unit";"Roach";"Larva";180;2
"Unit";"Roach";"Larva";180;2
"Unit";"Roach";"Larva";180;2
"Unit";"Roach";"Larva";180;2
"Unit";"Roach";"Larva";180;2
"Unit";"Roach";"Larva";180;2
"Building";"CreepTumor";NA;192;0
"Building";"CreepTumorQueen";NA;192;0
"Building";"Hatchery";NA;150;0
"Unit";"Overlord";"Larva";210;0
"Building";"Extractor";NA;210;0
"Building";"Extractor";NA;210;0
"Unit";"Overlord";"Larva";210;0
"Unit";"Overlord";"Larva";212;0
"Unit";"Hydralisk";"Larva";212;2
"Unit";"Hydralisk";"Larva";212;2
"Unit";"Hydralisk";"Larva";212;2
"Unit";"Hydralisk";"Larva";212;2
"Unit";"Hydralisk";"Larva";212;2
"Unit";"Hydralisk";"Larva";212;2
"Unit";"Hydralisk";"Larva";212;2
"Unit";"Overlord";"Larva";212;0
"Upgrade";"EvolveGroovedSpines";"HydraliskDen";212;0
"Unit";"Hydralisk";"Larva";226;2
"Unit";"Hydralisk";"Larva";226;2
"Unit";"Hydralisk";"Larva";226;2
"Unit";"Hydralisk";"Larva";226;2
"Unit";"Hydralisk";"Larva";226;2
"Unit";"Hydralisk";"Larva";226;2
"Unit";"Hydralisk";"Larva";226;2
"Unit";"Roach";"Larva";226;2
"Unit";"Roach";"Larva";226;2
"Unit";"Roach";"Larva";226;2
"Unit";"Roach";"Larva";226;2
"Unit";"Roach";"Larva";226;2
"Unit";"Roach";"Larva";226;2
"Unit";"Roach";"Larva";226;2
"Unit";"Overlord";"Larva";254;0
"Building";"CreepTumor";NA;254;0
"Unit";"Roach";"Larva";254;2
"Unit";"Roach";"Larva";254;2
"Unit";"Roach";"Larva";254;2
"Unit";"Roach";"Larva";254;2
"Unit";"Roach";"Larva";254;2
"Unit";"Roach";"Larva";254;2
"Building";"LurkerDenMP";NA;226;0
"Upgrade";"ZergGroundArmorsLevel1";"EvolutionChamber";226;0
"Unit";"Hydralisk";"Larva";266;2
"Unit";"Hydralisk";"Larva";266;2
"Unit";"Hydralisk";"Larva";266;2
"Unit";"Hydralisk";"Larva";266;2
"Unit";"Hydralisk";"Larva";266;2
"Unit";"Hydralisk";"Larva";266;2
"Unit";"Hydralisk";"Larva";266;2
"Unit";"Roach";"Larva";280;2
"Unit";"Roach";"Larva";280;2
"Unit";"Roach";"Larva";280;2
"Unit";"Roach";"Larva";280;2
"Unit";"Roach";"Larva";280;2
"Unit";"Roach";"Larva";280;2
"Unit";"Roach";"Larva";280;2
"Unit";"Roach";"Larva";280;2
"Unit";"Roach";"Larva";280;2
"Unit";"Roach";"Larva";280;2
"Unit";"Roach";"Larva";280;2
"Unit";"Roach";"Larva";302;2
"Unit";"Roach";"Larva";302;2
"Unit";"Roach";"Larva";302;2
"Unit";"Roach";"Larva";302;2
"Unit";"Roach";"Larva";302;2
"Unit";"Roach";"Larva";302;2
"Unit";"Roach";"Larva";302;2
"Building";"InfestationPit";NA;282;0
"Unit";"Roach";"Larva";302;2
"Unit";"Roach";"Larva";302;2
"Unit";"Roach";"Larva";302;2
"Unit";"Roach";"Larva";302;2
"Unit";"Roach";"Larva";302;2
"Unit";"Roach";"Larva";326;2
"Unit";"Roach";"Larva";326;2
"Unit";"Roach";"Larva";326;2
"Unit";"Roach";"Larva";326;2
"Unit";"Roach";"Larva";326;2
"Unit";"Roach";"Larva";326;2
"Unit";"Roach";"Larva";326;2
"Unit";"Roach";"Larva";326;2
"Unit";"Roach";"Larva";326;2
"Unit";"Roach";"Larva";326;2
"Unit";"Roach";"Larva";326;2
"Unit";"Roach";"Larva";326;2
"Unit";"Roach";"Larva";326;2
"Unit";"Roach";"Larva";326;2
"Unit";"Roach";"Larva";326;2
"Building";"Hatchery";NA;302;0
"Unit";"Roach";"Larva";356;2
"Unit";"Roach";"Larva";356;2
"Unit";"Roach";"Larva";356;2
"Unit";"Roach";"Larva";356;2
"Unit";"Roach";"Larva";356;2
"Unit";"Roach";"Larva";366;2
"Unit";"Roach";"Larva";366;2
"Unit";"Roach";"Larva";370;2
"Unit";"Roach";"Larva";370;2
"Unit";"Roach";"Larva";370;2
"Unit";"Roach";"Larva";370;2
"Unit";"Roach";"Larva";370;2
"Unit";"Roach";"Larva";370;2
"Unit";"Roach";"Larva";370;2
"Unit";"Roach";"Larva";370;2
"Unit";"Roach";"Larva";370;2
"Unit";"Roach";"Larva";370;2
"Unit";"Roach";"Larva";370;2
"Unit";"Roach";"Larva";370;2
"Unit";"Roach";"Larva";370;2
