"type";"unit_name";"on_building";"total_supply";"supply"
"Unit";"Overlord";"Larva";12;0
"Building";"Extractor";NA;18;0
"Building";"SpawningPool";NA;19;0
"Building";"Hatchery";NA;16;0
"Unit";"Overlord";"Larva";23;0
"Unit";"Zergling";"Larva";24;1
"Unit";"Zergling";"Larva";24;1
"Unit";"Queen";"Hatchery";24;2
"Unit";"Queen";"Hatchery";24;2
"Unit";"Overlord";"Larva";37;0
"Building";"BanelingNest";NA;34;0
"Unit";"Queen";"Hatchery";36;2
"Unit";"Overlord";"Larva";40;0
"Unit";"Zergling";"Larva";40;1
"Unit";"Zergling";"Larva";40;1
"Unit";"Zergling";"Larva";40;1
"Unit";"Zergling";"Larva";40;1
"Unit";"Zergling";"Larva";40;1
"Unit";"Zergling";"Larva";40;1
"Unit";"Zergling";"Larva";40;1
"Unit";"Zergling";"Larva";40;1
"Unit";"Zergling";"Larva";40;1
"Unit";"Zergling";"Larva";40;1
"Unit";"Zergling";"Larva";40;1
"Unit";"Zergling";"Larva";40;1
"Unit";"Zergling";"Larva";40;1
"Unit";"Zergling";"Larva";40;1
"Unit";"Zergling";"Larva";40;1
"Unit";"Zergling";"Larva";40;1
"Building";"Hatchery";NA;30;0
"Unit";"Baneling";"Zergling";54;0
"Unit";"Baneling";"Zergling";54;0
"Unit";"Zergling";"Larva";54;1
"Unit";"Zergling";"Larva";54;1
"Unit";"Zergling";"Larva";54;1
"Unit";"Zergling";"Larva";54;1
"Unit";"Overlord";"Larva";58;0
"Unit";"Overlord";"Larva";58;0
"Unit";"Zergling";"Larva";69;1
"Unit";"Zergling";"Larva";69;1
"Unit";"Zergling";"Larva";69;1
"Unit";"Zergling";"Larva";69;1
"Unit";"Zergling";"Larva";69;1
"Unit";"Zergling";"Larva";69;1
"Unit";"Zergling";"Larva";69;1
"Unit";"Zergling";"Larva";69;1
"Unit";"Zergling";"Larva";69;1
"Unit";"Zergling";"Larva";69;1
"Unit";"Zergling";"Larva";69;1
"Unit";"Zergling";"Larva";69;1
"Unit";"Zergling";"Larva";69;1
"Unit";"Zergling";"Larva";69;1
"Unit";"Zergling";"Larva";69;1
"Unit";"Zergling";"Larva";69;1
"Unit";"Zergling";"Larva";69;1
"Unit";"Zergling";"Larva";69;1
"Unit";"Zergling";"Larva";69;1
"Unit";"Zergling";"Larva";69;1
"Unit";"Zergling";"Larva";69;1
"Unit";"Zergling";"Larva";69;1
"Unit";"Zergling";"Larva";69;1
"Unit";"Zergling";"Larva";69;1
"Unit";"Zergling";"Larva";69;1
"Unit";"Zergling";"Larva";69;1
"Building";"Extractor";NA;81;0
"Unit";"Zergling";"Larva";81;1
"Unit";"Zergling";"Larva";81;1
"Unit";"Zergling";"Larva";81;1
"Unit";"Zergling";"Larva";81;1
"Unit";"Zergling";"Larva";81;1
"Unit";"Zergling";"Larva";81;1
"Unit";"Zergling";"Larva";81;1
"Unit";"Zergling";"Larva";81;1
"Building";"EvolutionChamber";NA;81;0
"Unit";"Overlord";"Larva";95;0
"Unit";"Overlord";"Larva";95;0
"Building";"RoachWarren";NA;81;0
"Unit";"Baneling";"Zergling";107;0
"Unit";"Baneling";"Zergling";107;0
"Building";"Extractor";NA;107;0
"Unit";"Overlord";"Larva";113;0
"Unit";"Zergling";"Larva";113;1
"Unit";"Zergling";"Larva";113;1
"Unit";"Zergling";"Larva";113;1
"Unit";"Zergling";"Larva";113;1
"Unit";"Zergling";"Larva";113;1
"Unit";"Zergling";"Larva";113;1
"Unit";"Zergling";"Larva";113;1
"Unit";"Zergling";"Larva";113;1
"Unit";"Roach";"Larva";113;2
"Unit";"Roach";"Larva";113;2
"Unit";"Roach";"Larva";113;2
"Unit";"Roach";"Larva";113;2
"Unit";"Roach";"Larva";113;2
"Unit";"Roach";"Larva";113;2
"Unit";"Baneling";"Zergling";113;0
"Unit";"Baneling";"Zergling";113;0
"Unit";"Baneling";"Zergling";115;0
"Unit";"Roach";"Larva";113;2
"Unit";"Roach";"Larva";135;2
"Unit";"Zergling";"Larva";143;1
"Unit";"Zergling";"Larva";143;1
"Unit";"Zergling";"Larva";143;1
"Unit";"Zergling";"Larva";143;1
"Unit";"Zergling";"Larva";143;1
"Unit";"Zergling";"Larva";143;1
"Unit";"Zergling";"Larva";143;1
"Unit";"Zergling";"Larva";143;1
"Unit";"Zergling";"Larva";143;1
"Unit";"Zergling";"Larva";143;1
"Unit";"Roach";"Larva";143;2
"Unit";"Roach";"Larva";143;2
"Unit";"Roach";"Larva";143;2
"Unit";"Roach";"Larva";143;2
"Unit";"Roach";"Larva";143;2
"Unit";"Zergling";"Larva";145;1
"Unit";"Zergling";"Larva";145;1
"Unit";"Roach";"Larva";145;2
"Unit";"Roach";"Larva";145;2
"Unit";"Zergling";"Larva";145;1
"Unit";"Zergling";"Larva";145;1
"Unit";"Baneling";"Zergling";155;0
"Unit";"Baneling";"Zergling";157;0
"Unit";"Zergling";"Larva";145;1
"Unit";"Zergling";"Larva";145;1
"Upgrade";"GlialReconstitution";"RoachWarren";113;0
"Unit";"Queen";"Hatchery";143;2
"Unit";"Zergling";"Larva";165;1
"Unit";"Zergling";"Larva";165;1
"Unit";"Zergling";"Larva";165;1
"Unit";"Zergling";"Larva";165;1
"Unit";"Zergling";"Larva";165;1
"Unit";"Zergling";"Larva";165;1
"Unit";"Zergling";"Larva";165;1
"Unit";"Zergling";"Larva";165;1
"Unit";"Zergling";"Larva";165;1
"Unit";"Zergling";"Larva";165;1
"Unit";"Roach";"Larva";188;2
"Unit";"Baneling";"Zergling";189;0
"Unit";"Baneling";"Zergling";189;0
"Upgrade";"ZergMissileWeaponsLevel1";"EvolutionChamber";141;0
"Unit";"Queen";"Hatchery";187;2
"Unit";"Zergling";"Larva";193;1
"Unit";"Zergling";"Larva";193;1
"Unit";"Zergling";"Larva";193;1
"Unit";"Zergling";"Larva";193;1
"Unit";"Roach";"Larva";193;2
"Unit";"Roach";"Larva";193;2
"Unit";"Roach";"Larva";193;2
"Unit";"Overlord";"Larva";207;0
"Unit";"Roach";"Larva";207;2
"Unit";"Roach";"Larva";207;2
"Unit";"Zergling";"Larva";207;1
"Unit";"Zergling";"Larva";207;1
"Unit";"Roach";"Larva";207;2
"Unit";"Roach";"Larva";207;2
"Unit";"Queen";"Hatchery";207;2
"Unit";"Roach";"Larva";221;2
"Unit";"Roach";"Larva";221;2
"Unit";"Roach";"Larva";241;2
"Unit";"Roach";"Larva";241;2
"Unit";"Roach";"Larva";241;2
"Unit";"Roach";"Larva";241;2
"Unit";"Roach";"Larva";241;2
"Unit";"Queen";"Hatchery";237;2
"Unit";"Roach";"Larva";241;2
"Unit";"Zergling";"Larva";241;1
"Unit";"Zergling";"Larva";241;1
"Unit";"Roach";"Larva";241;2
"Unit";"Roach";"Larva";241;2
"Unit";"Roach";"Larva";245;2
"Unit";"Overlord";"Larva";247;0
"Building";"Extractor";NA;257;0
"Unit";"Baneling";"Zergling";270;0
"Unit";"Baneling";"Zergling";270;0
"Building";"Extractor";NA;273;0
"Unit";"Roach";"Larva";274;2
"Building";"Extractor";NA;278;0
"Unit";"Roach";"Larva";278;2
"Unit";"Roach";"Larva";278;2
"Unit";"Roach";"Larva";278;2
"Unit";"Overlord";"Larva";282;0
"Unit";"Overlord";"Larva";282;0
"Unit";"Overlord";"Larva";282;0
"Building";"HydraliskDen";NA;288;0
"Unit";"Roach";"Larva";290;2
"Unit";"Roach";"Larva";290;2
"Unit";"Roach";"Larva";290;2
"Unit";"Roach";"Larva";290;2
"Unit";"Roach";"Larva";290;2
"Unit";"Roach";"Larva";290;2
"Unit";"Overlord";"Larva";290;0
"Upgrade";"ZergMissileWeaponsLevel2";"EvolutionChamber";249;0
"Upgrade";"Burrow";"Hatchery";279;0
"Unit";"Overlord";"Larva";290;0
"Upgrade";"TunnelingClaws";"RoachWarren";279;0
"Unit";"Overlord";"Larva";291;0
"Unit";"Overlord";"Larva";291;0
"Unit";"Roach";"Larva";303;2
"Unit";"Roach";"Larva";303;2
"Unit";"Roach";"Larva";303;2
"Unit";"Roach";"Larva";303;2
"Unit";"Roach";"Larva";303;2
"Unit";"Roach";"Larva";303;2
"Unit";"Roach";"Larva";303;2
"Unit";"Roach";"Larva";303;2
"Unit";"Roach";"Larva";303;2
"Unit";"Roach";"Larva";303;2
"Unit";"Roach";"Larva";303;2
"Unit";"Roach";"Larva";303;2
"Unit";"Roach";"Larva";303;2
"Unit";"Roach";"Larva";303;2
"Building";"Hatchery";NA;288;0
