"type";"unit_name";"on_building";"total_supply";"supply"
"Unit";"Overlord";"Larva";13;0
"Building";"Extractor";NA;17;0
"Unit";"Overlord";"Larva";21;0
"Building";"SpawningPool";NA;19;0
"Building";"Hatchery";NA;17;0
"Unit";"Zergling";"Larva";22;1
"Unit";"Zergling";"Larva";22;1
"Unit";"Zergling";"Larva";22;1
"Unit";"Zergling";"Larva";22;1
"Unit";"Queen";"Hatchery";22;2
"Unit";"Queen";"Hatchery";22;2
"Unit";"Overlord";"Larva";38;0
"Unit";"Overlord";"Larva";40;0
"Unit";"Zergling";"Larva";40;1
"Unit";"Zergling";"Larva";40;1
"Unit";"Zergling";"Larva";40;1
"Unit";"Zergling";"Larva";40;1
"Unit";"Zergling";"Larva";40;1
"Unit";"Zergling";"Larva";40;1
"Building";"BanelingNest";NA;35;0
"Unit";"Zergling";"Larva";40;1
"Unit";"Zergling";"Larva";40;1
"Unit";"Zergling";"Larva";41;1
"Unit";"Zergling";"Larva";41;1
"Unit";"Zergling";"Larva";41;1
"Unit";"Zergling";"Larva";41;1
"Unit";"Zergling";"Larva";41;1
"Unit";"Zergling";"Larva";41;1
"Unit";"Zergling";"Larva";47;1
"Unit";"Zergling";"Larva";47;1
"Unit";"Zergling";"Larva";47;1
"Unit";"Zergling";"Larva";47;1
"Building";"Hatchery";NA;33;0
"Unit";"Overlord";"Larva";47;0
"Unit";"Baneling";"Zergling";55;0
"Unit";"Baneling";"Zergling";55;0
"Unit";"Baneling";"Zergling";55;0
"Unit";"Baneling";"Zergling";55;0
"Unit";"Baneling";"Zergling";59;0
"Unit";"Zergling";"Larva";61;1
"Unit";"Zergling";"Larva";61;1
"Unit";"Zergling";"Larva";61;1
"Unit";"Zergling";"Larva";61;1
"Unit";"Baneling";"Zergling";69;0
"Unit";"Baneling";"Zergling";69;0
"Unit";"Baneling";"Zergling";69;0
"Unit";"Baneling";"Zergling";69;0
"Building";"Extractor";NA;69;0
"Building";"Extractor";NA;69;0
"Building";"EvolutionChamber";NA;69;0
"Unit";"Zergling";"Larva";71;1
"Unit";"Zergling";"Larva";71;1
"Unit";"Zergling";"Larva";71;1
"Unit";"Zergling";"Larva";71;1
"Unit";"Zergling";"Larva";71;1
"Unit";"Zergling";"Larva";71;1
"Unit";"Zergling";"Larva";71;1
"Unit";"Zergling";"Larva";71;1
"Unit";"Zergling";"Larva";71;1
"Unit";"Zergling";"Larva";71;1
"Building";"RoachWarren";NA;69;0
"Unit";"Overlord";"Larva";76;0
"Unit";"Queen";"Hatchery";71;2
"Unit";"Overlord";"Larva";93;0
"Unit";"Overlord";"Larva";93;0
"Unit";"Overlord";"Larva";93;0
"Unit";"Overlord";"Larva";93;0
"Unit";"Overlord";"Larva";93;0
"Unit";"Zergling";"Larva";95;1
"Unit";"Zergling";"Larva";95;1
"Unit";"Zergling";"Larva";95;1
"Unit";"Zergling";"Larva";95;1
"Unit";"Zergling";"Larva";95;1
"Unit";"Zergling";"Larva";95;1
"Unit";"Zergling";"Larva";95;1
"Unit";"Zergling";"Larva";95;1
"Unit";"Zergling";"Larva";95;1
"Unit";"Zergling";"Larva";95;1
"Unit";"Overlord";"Larva";97;0
"Unit";"Overlord";"Larva";97;0
"Unit";"Baneling";"Zergling";103;0
"Unit";"Baneling";"Zergling";103;0
"Unit";"Baneling";"Zergling";103;0
"Unit";"Zergling";"Larva";113;1
"Unit";"Zergling";"Larva";113;1
"Unit";"Zergling";"Larva";113;1
"Unit";"Zergling";"Larva";113;1
"Unit";"Zergling";"Larva";113;1
"Unit";"Zergling";"Larva";113;1
"Unit";"Zergling";"Larva";113;1
"Unit";"Zergling";"Larva";113;1
"Unit";"Baneling";"Zergling";118;0
"Unit";"Baneling";"Zergling";118;0
"Unit";"Roach";"Larva";118;2
"Unit";"Roach";"Larva";118;2
"Unit";"Roach";"Larva";118;2
"Unit";"Roach";"Larva";118;2
"Unit";"Roach";"Larva";118;2
"Unit";"Roach";"Larva";119;2
"Unit";"Roach";"Larva";123;2
"Unit";"Roach";"Larva";123;2
"Building";"Extractor";NA;119;0
"Building";"Extractor";NA;119;0
"Unit";"Roach";"Larva";145;2
"Unit";"Roach";"Larva";145;2
"Unit";"Roach";"Larva";145;2
"Unit";"Zergling";"Larva";151;1
"Unit";"Zergling";"Larva";151;1
"Unit";"Roach";"Larva";151;2
"Unit";"Roach";"Larva";151;2
"Unit";"Roach";"Larva";151;2
"Unit";"Overlord";"Larva";159;0
"Unit";"Overlord";"Larva";159;0
"Unit";"Overlord";"Larva";159;0
"Upgrade";"ZergMissileWeaponsLevel1";"EvolutionChamber";110;0
"Unit";"Overlord";"Larva";159;0
"Building";"Extractor";NA;167;0
"Building";"HydraliskDen";NA;167;0
"Unit";"Overlord";"Larva";167;0
"Unit";"Roach";"Larva";180;2
"Unit";"Roach";"Larva";182;2
"Building";"Hatchery";NA;151;0
"Unit";"Roach";"Larva";182;2
"Unit";"Roach";"Larva";182;2
"Unit";"Baneling";"Zergling";182;0
"Unit";"Baneling";"Zergling";182;0
"Unit";"Roach";"Larva";182;2
"Unit";"Roach";"Larva";182;2
"Unit";"Roach";"Larva";182;2
"Unit";"Overlord";"Larva";184;0
"Unit";"Overlord";"Larva";184;0
"Unit";"Overlord";"Larva";184;0
"Unit";"Overlord";"Larva";184;0
"Unit";"Roach";"Larva";190;2
"Unit";"Roach";"Larva";190;2
"Unit";"Roach";"Larva";197;2
"Unit";"Roach";"Larva";197;2
"Unit";"Roach";"Larva";199;2
"Unit";"Roach";"Larva";199;2
"Unit";"Roach";"Larva";199;2
"Unit";"Roach";"Larva";199;2
"Unit";"Roach";"Larva";199;2
"Unit";"Roach";"Larva";199;2
"Unit";"Roach";"Larva";199;2
"Unit";"Roach";"Larva";199;2
"Unit";"Roach";"Larva";199;2
"Unit";"Roach";"Larva";199;2
"Unit";"Roach";"Larva";199;2
"Unit";"Overlord";"Larva";223;0
"Unit";"Overlord";"Larva";223;0
"Upgrade";"EvolveGroovedSpines";"HydraliskDen";190;0
"Unit";"Roach";"Larva";223;2
"Unit";"Roach";"Larva";223;2
"Unit";"Roach";"Larva";223;2
"Unit";"Roach";"Larva";223;2
"Unit";"Roach";"Larva";223;2
"Unit";"Overlord";"Larva";229;0
"Unit";"Overlord";"Larva";229;0
"Unit";"Overlord";"Larva";229;0
"Unit";"Overlord";"Larva";229;0
"Building";"Extractor";NA;229;0
"Building";"Extractor";NA;229;0
"Building";"LurkerDenMP";NA;182;0
"Building";"SpineCrawler";NA;239;0
"Building";"SpineCrawler";NA;239;0
"Building";"SpineCrawler";NA;239;0
"Building";"SpineCrawler";NA;239;0
"Unit";"Hydralisk";"Larva";239;2
"Unit";"Hydralisk";"Larva";239;2
"Unit";"Hydralisk";"Larva";239;2
"Unit";"Hydralisk";"Larva";239;2
"Upgrade";"ZergMissileWeaponsLevel2";"EvolutionChamber";199;0
"Unit";"Hydralisk";"Larva";239;2
"Unit";"Hydralisk";"Larva";239;2
"Unit";"Hydralisk";"Larva";239;2
"Unit";"Hydralisk";"Larva";239;2
"Unit";"Hydralisk";"Larva";239;2
"Unit";"Hydralisk";"Larva";239;2
"Unit";"Hydralisk";"Larva";239;2
"Unit";"Hydralisk";"Larva";239;2
"Unit";"Roach";"Larva";239;2
"Unit";"Roach";"Larva";239;2
"Unit";"Roach";"Larva";239;2
"Unit";"Roach";"Larva";239;2
"Unit";"Roach";"Larva";239;2
"Upgrade";"EvolveMuscularAugments";"HydraliskDen";239;0
"Upgrade";"GlialReconstitution";"RoachWarren";239;0
"Building";"SpineCrawler";NA;273;0
"Building";"Hatchery";NA;247;0
"Building";"InfestationPit";NA;273;0
