"type";"unit_name";"on_building";"total_supply";"supply"
"Unit";"Overlord";"Larva";12;0
"Building";"Extractor";NA;16;0
"Building";"SpawningPool";NA;17;0
"Unit";"Overlord";"Larva";20;0
"Unit";"Zergling";"Larva";20;1
"Unit";"Zergling";"Larva";20;1
"Unit";"Zergling";"Larva";20;1
"Unit";"Zergling";"Larva";20;1
"Unit";"Queen";"Hatchery";20;2
"Unit";"Zergling";"Larva";21;1
"Unit";"Zergling";"Larva";21;1
"Building";"Hatchery";NA;19;0
"Unit";"Zergling";"Larva";29;1
"Unit";"Zergling";"Larva";29;1
"Unit";"Zergling";"Larva";29;1
"Unit";"Zergling";"Larva";29;1
"Unit";"Queen";"Hatchery";27;2
"Building";"BanelingNest";NA;23;0
"Unit";"Zergling";"Larva";29;1
"Unit";"Zergling";"Larva";29;1
"Unit";"Zergling";"Larva";31;1
"Unit";"Zergling";"Larva";31;1
"Building";"SpineCrawler";NA;31;0
"Unit";"Zergling";"Larva";39;1
"Unit";"Zergling";"Larva";39;1
"Unit";"Zergling";"Larva";39;1
"Unit";"Zergling";"Larva";39;1
"Unit";"Zergling";"Larva";39;1
"Unit";"Zergling";"Larva";39;1
"Unit";"Zergling";"Larva";39;1
"Unit";"Zergling";"Larva";39;1
"Unit";"Zergling";"Larva";39;1
"Unit";"Zergling";"Larva";39;1
"Unit";"Zergling";"Larva";39;1
"Unit";"Zergling";"Larva";39;1
"Unit";"Baneling";"Zergling";39;0
"Unit";"Baneling";"Zergling";39;0
"Unit";"Baneling";"Zergling";51;0
"Unit";"Baneling";"Zergling";51;0
"Unit";"Baneling";"Zergling";51;0
"Unit";"Baneling";"Zergling";51;0
"Unit";"Queen";"Hatchery";51;2
"Unit";"Overlord";"Larva";56;0
"Building";"Extractor";NA;62;0
"Unit";"Overlord";"Larva";66;0
"Unit";"Queen";"Hatchery";62;2
"Building";"Extractor";NA;67;0
"Unit";"Overlord";"Larva";75;0
"Unit";"Overlord";"Larva";75;0
"Unit";"Overlord";"Larva";75;0
"Building";"Extractor";NA;75;0
"Building";"CreepTumorQueen";NA;81;0
"Building";"CreepTumorQueen";NA;81;0
"Building";"SpineCrawler";NA;81;0
"Building";"Hatchery";NA;75;0
"Building";"CreepTumor";NA;92;0
"Building";"CreepTumor";NA;92;0
"Unit";"Overlord";"Larva";88;0
"Unit";"Overlord";"Larva";88;0
"Unit";"Zergling";"Larva";92;1
"Unit";"Zergling";"Larva";92;1
"Unit";"Zergling";"Larva";92;1
"Unit";"Zergling";"Larva";92;1
"Unit";"Zergling";"Larva";94;1
"Unit";"Zergling";"Larva";94;1
"Unit";"Zergling";"Larva";94;1
"Unit";"Zergling";"Larva";94;1
"Building";"Spire";NA;81;0
"Building";"SpineCrawler";NA;92;0
"Unit";"Baneling";"Zergling";102;0
"Unit";"Baneling";"Zergling";102;0
"Building";"SpineCrawler";NA;98;0
"Unit";"Mutalisk";"Larva";102;2
"Unit";"Mutalisk";"Larva";102;2
"Unit";"Mutalisk";"Larva";102;2
"Unit";"Mutalisk";"Larva";102;2
"Unit";"Mutalisk";"Larva";102;2
"Unit";"Mutalisk";"Larva";102;2
"Unit";"Mutalisk";"Larva";102;2
"Unit";"Mutalisk";"Larva";102;2
"Unit";"Mutalisk";"Larva";102;2
"Unit";"Mutalisk";"Larva";102;2
"Unit";"Mutalisk";"Larva";102;2
"Unit";"Mutalisk";"Larva";102;2
"Unit";"Overlord";"Larva";136;0
"Building";"Hatchery";NA;102;0
"Unit";"Mutalisk";"Larva";136;2
"Unit";"Mutalisk";"Larva";136;2
"Unit";"Mutalisk";"Larva";136;2
"Unit";"Mutalisk";"Larva";136;2
"Unit";"Mutalisk";"Larva";136;2
"Unit";"Zergling";"Larva";136;1
"Unit";"Zergling";"Larva";136;1
"Unit";"Zergling";"Larva";136;1
"Unit";"Zergling";"Larva";136;1
"Unit";"Zergling";"Larva";136;1
"Unit";"Zergling";"Larva";136;1
"Building";"CreepTumor";NA;146;0
"Building";"CreepTumor";NA;146;0
"Unit";"Zergling";"Larva";146;1
"Unit";"Zergling";"Larva";146;1
"Unit";"Zergling";"Larva";146;1
"Unit";"Zergling";"Larva";146;1
"Unit";"Baneling";"Zergling";152;0
"Unit";"Baneling";"Zergling";152;0
"Unit";"Baneling";"Zergling";152;0
"Unit";"Baneling";"Zergling";152;0
"Unit";"Baneling";"Zergling";152;0
"Unit";"Baneling";"Zergling";152;0
"Unit";"Baneling";"Zergling";152;0
"Unit";"Overlord";"Larva";152;0
"Unit";"Baneling";"Zergling";152;0
"Unit";"Zergling";"Larva";152;1
"Unit";"Zergling";"Larva";152;1
"Unit";"Zergling";"Larva";152;1
"Unit";"Zergling";"Larva";152;1
"Unit";"Zergling";"Larva";156;1
"Unit";"Zergling";"Larva";156;1
"Building";"CreepTumor";NA;156;0
"Building";"CreepTumor";NA;156;0
"Unit";"Zergling";"Larva";156;1
"Unit";"Zergling";"Larva";156;1
"Unit";"Zergling";"Larva";156;1
"Unit";"Zergling";"Larva";156;1
"Unit";"Zergling";"Larva";156;1
"Unit";"Zergling";"Larva";156;1
"Unit";"Zergling";"Larva";156;1
"Unit";"Zergling";"Larva";156;1
"Unit";"Zergling";"Larva";156;1
"Unit";"Zergling";"Larva";156;1
"Unit";"Zergling";"Larva";156;1
"Unit";"Zergling";"Larva";156;1
"Unit";"Zergling";"Larva";177;1
"Unit";"Zergling";"Larva";177;1
"Unit";"Zergling";"Larva";177;1
"Unit";"Zergling";"Larva";177;1
"Unit";"Zergling";"Larva";177;1
"Unit";"Zergling";"Larva";177;1
"Unit";"Zergling";"Larva";177;1
"Unit";"Zergling";"Larva";177;1
"Unit";"Overlord";"Larva";177;0
"Unit";"Overlord";"Larva";177;0
"Building";"Hatchery";NA;152;0
"Unit";"Overlord";"Larva";178;0
"Building";"CreepTumor";NA;178;0
"Building";"CreepTumor";NA;178;0
"Building";"InfestationPit";NA;164;0
"Unit";"Overlord";"Larva";178;0
"Unit";"Queen";"Hatchery";164;2
"Unit";"Overlord";"Larva";184;0
"Building";"EvolutionChamber";NA;186;0
"Building";"EvolutionChamber";NA;186;0
"Building";"Extractor";NA;188;0
"Building";"CreepTumor";NA;193;0
"Unit";"Zergling";"Larva";195;1
"Unit";"Zergling";"Larva";195;1
"Unit";"Zergling";"Larva";195;1
"Unit";"Zergling";"Larva";195;1
"Unit";"Zergling";"Larva";195;1
"Unit";"Zergling";"Larva";195;1
"Unit";"Zergling";"Larva";195;1
"Unit";"Zergling";"Larva";195;1
"Unit";"Zergling";"Larva";195;1
"Unit";"Zergling";"Larva";195;1
"Unit";"Zergling";"Larva";195;1
"Unit";"Zergling";"Larva";195;1
"Unit";"Zergling";"Larva";195;1
"Unit";"Zergling";"Larva";195;1
"Unit";"Zergling";"Larva";195;1
"Unit";"Zergling";"Larva";195;1
"Building";"CreepTumor";NA;199;0
"Unit";"Mutalisk";"Larva";199;2
"Unit";"Mutalisk";"Larva";199;2
"Unit";"Mutalisk";"Larva";199;2
"Unit";"Mutalisk";"Larva";199;2
"Unit";"Mutalisk";"Larva";215;2
"Unit";"Mutalisk";"Larva";215;2
"Unit";"Mutalisk";"Larva";215;2
"Unit";"Mutalisk";"Larva";215;2
"Unit";"Zergling";"Larva";233;1
"Unit";"Zergling";"Larva";233;1
"Unit";"Zergling";"Larva";233;1
"Unit";"Zergling";"Larva";233;1
"Unit";"Zergling";"Larva";233;1
"Unit";"Zergling";"Larva";233;1
"Unit";"Zergling";"Larva";233;1
"Unit";"Zergling";"Larva";233;1
"Unit";"Zergling";"Larva";233;1
"Unit";"Zergling";"Larva";233;1
"Unit";"Zergling";"Larva";233;1
"Unit";"Zergling";"Larva";233;1
"Unit";"Zergling";"Larva";233;1
"Unit";"Zergling";"Larva";233;1
"Unit";"Zergling";"Larva";233;1
"Unit";"Zergling";"Larva";233;1
"Unit";"Baneling";"Zergling";233;0
"Unit";"Baneling";"Zergling";233;0
"Unit";"Baneling";"Zergling";233;0
"Unit";"Baneling";"Zergling";233;0
"Unit";"Zergling";"Larva";233;1
"Unit";"Zergling";"Larva";233;1
"Unit";"Baneling";"Zergling";233;0
"Unit";"Baneling";"Zergling";233;0
"Unit";"Baneling";"Zergling";233;0
"Unit";"Baneling";"Zergling";233;0
"Unit";"Zergling";"Larva";233;1
"Unit";"Zergling";"Larva";233;1
"Unit";"Zergling";"Larva";233;1
"Unit";"Zergling";"Larva";233;1
"Unit";"Zergling";"Larva";233;1
"Unit";"Zergling";"Larva";233;1
"Unit";"Zergling";"Larva";233;1
"Unit";"Zergling";"Larva";233;1
"Unit";"Zergling";"Larva";233;1
"Unit";"Zergling";"Larva";233;1
"Building";"CreepTumor";NA;233;0
"Building";"Extractor";NA;233;0
"Building";"HydraliskDen";NA;233;0
"Unit";"Overlord";"Larva";233;0
"Unit";"Overlord";"Larva";233;0
"Unit";"Overlord";"Larva";233;0
"Unit";"Overlord";"Larva";233;0
"Unit";"Overlord";"Larva";233;0
"Upgrade";"ZergGroundArmorsLevel1";"EvolutionChamber";223;0
"Upgrade";"ZergMeleeWeaponsLevel1";"EvolutionChamber";223;0
"Unit";"Zergling";"Larva";261;1
"Unit";"Zergling";"Larva";261;1
"Unit";"Mutalisk";"Larva";261;2
"Unit";"Mutalisk";"Larva";261;2
"Unit";"Mutalisk";"Larva";261;2
"Unit";"Mutalisk";"Larva";261;2
"Unit";"Zergling";"Larva";261;1
"Unit";"Zergling";"Larva";261;1
"Unit";"Zergling";"Larva";261;1
"Unit";"Zergling";"Larva";261;1
"Unit";"Zergling";"Larva";261;1
"Unit";"Zergling";"Larva";261;1
"Unit";"Mutalisk";"Larva";261;2
"Unit";"Mutalisk";"Larva";261;2
"Unit";"Zergling";"Larva";271;1
"Unit";"Zergling";"Larva";271;1
"Unit";"Zergling";"Larva";271;1
"Unit";"Zergling";"Larva";271;1
"Unit";"Zergling";"Larva";271;1
"Unit";"Zergling";"Larva";271;1
"Unit";"Zergling";"Larva";271;1
"Unit";"Zergling";"Larva";271;1
"Unit";"Zergling";"Larva";271;1
"Unit";"Zergling";"Larva";271;1
"Unit";"Zergling";"Larva";271;1
"Unit";"Zergling";"Larva";271;1
"Unit";"Mutalisk";"Larva";271;2
"Unit";"Overlord";"Larva";293;0
"Building";"SpawningPool";NA;295;0
"Building";"Extractor";NA;295;0
"Unit";"Corruptor";"Larva";295;2
"Unit";"Corruptor";"Larva";295;2
