"type";"unit_name";"on_building";"total_supply";"supply"
"Unit";"Overlord";"Larva";13;0
"Building";"Extractor";NA;18;0
"Unit";"Overlord";"Larva";21;0
"Building";"SpawningPool";NA;19;0
"Building";"Hatchery";NA;17;0
"Unit";"Zergling";"Larva";22;1
"Unit";"Zergling";"Larva";22;1
"Unit";"Zergling";"Larva";22;1
"Unit";"Zergling";"Larva";22;1
"Unit";"Queen";"Hatchery";22;2
"Unit";"Queen";"Hatchery";22;2
"Unit";"Overlord";"Larva";38;0
"Building";"BanelingNest";NA;37;0
"Building";"EvolutionChamber";NA;41;0
"Unit";"Overlord";"Larva";44;0
"Unit";"Zergling";"Larva";44;1
"Unit";"Zergling";"Larva";44;1
"Building";"Hatchery";NA;36;0
"Unit";"Baneling";"Zergling";51;0
"Unit";"Baneling";"Zergling";51;0
"Building";"RoachWarren";NA;49;0
"Building";"Extractor";NA;53;0
"Building";"Extractor";NA;53;0
"Unit";"Overlord";"Larva";59;0
"Unit";"Overlord";"Larva";64;0
"Unit";"Overlord";"Larva";64;0
"Unit";"Overlord";"Larva";67;0
"Unit";"Roach";"Larva";69;2
"Unit";"Roach";"Larva";69;2
"Unit";"Roach";"Larva";69;2
"Unit";"Roach";"Larva";69;2
"Unit";"Roach";"Larva";69;2
"Unit";"Roach";"Larva";69;2
"Unit";"Roach";"Larva";69;2
"Unit";"Roach";"Larva";69;2
"Unit";"Roach";"Larva";69;2
"Unit";"Roach";"Larva";75;2
"Unit";"Overlord";"Larva";75;0
"Unit";"Overlord";"Larva";77;0
"Unit";"Roach";"Larva";79;2
"Unit";"Roach";"Larva";79;2
"Unit";"Roach";"Larva";81;2
"Upgrade";"ZergMissileWeaponsLevel1";"EvolutionChamber";60;0
"Unit";"Roach";"Larva";89;2
"Unit";"Roach";"Larva";91;2
"Unit";"Roach";"Larva";91;2
"Unit";"Queen";"Hatchery";85;2
"Unit";"Roach";"Larva";95;2
"Unit";"Roach";"Larva";95;2
"Building";"Extractor";NA;95;0
"Building";"Extractor";NA;95;0
"Upgrade";"GlialReconstitution";"RoachWarren";77;0
"Unit";"Overlord";"Larva";101;0
"Unit";"Overlord";"Larva";104;0
"Building";"EvolutionChamber";NA;115;0
"Building";"SporeCrawler";NA;115;0
"Unit";"Roach";"Larva";115;2
"Unit";"Roach";"Larva";115;2
"Unit";"Roach";"Larva";115;2
"Unit";"Roach";"Larva";115;2
"Unit";"Overlord";"Larva";115;0
"Unit";"Overlord";"Larva";115;0
"Unit";"Roach";"Larva";123;2
"Unit";"Roach";"Larva";123;2
"Unit";"Roach";"Larva";123;2
"Unit";"Roach";"Larva";123;2
"Unit";"Roach";"Larva";123;2
"Building";"Hatchery";NA;101;0
"Unit";"Roach";"Larva";123;2
"Unit";"Roach";"Larva";123;2
"Unit";"Roach";"Larva";123;2
"Unit";"Roach";"Larva";123;2
"Unit";"Roach";"Larva";123;2
"Unit";"Roach";"Larva";123;2
"Unit";"Roach";"Larva";123;2
"Unit";"Roach";"Larva";123;2
"Building";"Extractor";NA;149;0
"Building";"HydraliskDen";NA;133;0
"Unit";"Overlord";"Larva";157;0
"Unit";"Overlord";"Larva";157;0
"Unit";"Roach";"Larva";161;2
"Unit";"Roach";"Larva";161;2
"Unit";"Roach";"Larva";161;2
"Unit";"Roach";"Larva";161;2
"Unit";"Roach";"Larva";161;2
"Unit";"Roach";"Larva";161;2
"Unit";"Roach";"Larva";161;2
"Unit";"Roach";"Larva";161;2
"Unit";"Roach";"Larva";161;2
"Unit";"Roach";"Larva";161;2
"Unit";"Roach";"Larva";161;2
"Unit";"Roach";"Larva";161;2
"Upgrade";"ZergMissileWeaponsLevel2";"EvolutionChamber";123;0
"Upgrade";"ZergGroundArmorsLevel1";"EvolutionChamber";133;0
"Building";"Extractor";NA;185;0
"Unit";"Roach";"Larva";185;2
"Unit";"Roach";"Larva";185;2
"Unit";"Roach";"Larva";185;2
"Unit";"Roach";"Larva";185;2
"Unit";"Roach";"Larva";185;2
"Unit";"Roach";"Larva";185;2
"Unit";"Roach";"Larva";185;2
"Unit";"Queen";"Hatchery";185;2
"Building";"Extractor";NA;206;0
"Building";"Extractor";NA;206;0
"Building";"Hatchery";NA;161;0
"Unit";"Overlord";"Larva";206;0
"Unit";"Overlord";"Larva";206;0
"Unit";"Overlord";"Larva";206;0
"Unit";"Roach";"Larva";214;2
"Unit";"Roach";"Larva";214;2
"Unit";"Roach";"Larva";214;2
"Unit";"Roach";"Larva";214;2
"Unit";"Roach";"Larva";214;2
"Building";"LurkerDenMP";NA;175;0
"Unit";"Roach";"Larva";214;2
"Unit";"Roach";"Larva";214;2
"Unit";"Roach";"Larva";214;2
"Unit";"Roach";"Larva";214;2
"Unit";"Roach";"Larva";214;2
"Unit";"Roach";"Larva";214;2
"Unit";"Roach";"Larva";214;2
"Unit";"Hydralisk";"Larva";214;2
"Unit";"Hydralisk";"Larva";216;2
"Unit";"Hydralisk";"Larva";224;2
"Unit";"Hydralisk";"Larva";230;2
"Unit";"Hydralisk";"Larva";230;2
"Upgrade";"EvolveMuscularAugments";"HydraliskDen";214;0
"Unit";"Hydralisk";"Larva";238;2
"Unit";"Hydralisk";"Larva";238;2
"Unit";"Hydralisk";"Larva";238;2
"Unit";"Overlord";"Larva";254;0
"Unit";"Overlord";"Larva";254;0
"Unit";"Overlord";"Larva";254;0
"Unit";"Overlord";"Larva";254;0
"Unit";"Overlord";"Larva";254;0
"Upgrade";"ZergGroundArmorsLevel2";"EvolutionChamber";214;0
"Unit";"Roach";"Larva";254;2
"Unit";"Roach";"Larva";254;2
"Unit";"Roach";"Larva";254;2
"Unit";"Roach";"Larva";254;2
"Unit";"Roach";"Larva";254;2
"Unit";"Roach";"Larva";254;2
"Unit";"Roach";"Larva";254;2
"Unit";"Roach";"Larva";254;2
"Unit";"Roach";"Larva";254;2
"Unit";"Roach";"Larva";254;2
"Unit";"Roach";"Larva";254;2
"Unit";"Roach";"Larva";254;2
"Unit";"Roach";"Larva";254;2
"Unit";"Roach";"Larva";254;2
"Unit";"Roach";"Larva";254;2
"Unit";"Roach";"Larva";254;2
"Unit";"Roach";"Larva";254;2
"Building";"RoachWarren";NA;254;0
"Unit";"Roach";"Larva";254;2
"Unit";"Roach";"Larva";254;2
"Unit";"Roach";"Larva";254;2
"Unit";"Hydralisk";"Larva";294;2
"Unit";"Hydralisk";"Larva";294;2
"Unit";"Hydralisk";"Larva";294;2
"Unit";"Hydralisk";"Larva";294;2
"Unit";"Hydralisk";"Larva";294;2
"Unit";"Hydralisk";"Larva";294;2
"Unit";"Hydralisk";"Larva";294;2
"Unit";"Hydralisk";"Larva";294;2
"Unit";"Hydralisk";"Larva";294;2
"Building";"LurkerDenMP";NA;254;0
"Unit";"Overlord";"Larva";294;0
"Unit";"Overlord";"Larva";294;0
"Unit";"Overlord";"Larva";294;0
"Unit";"Overlord";"Larva";294;0
"Unit";"Overlord";"Larva";294;0
"Building";"Hatchery";NA;294;0
"Unit";"Hydralisk";"Larva";313;2
"Unit";"Hydralisk";"Larva";313;2
"Unit";"Hydralisk";"Larva";313;2
"Unit";"Hydralisk";"Larva";313;2
"Unit";"Hydralisk";"Larva";313;2
"Upgrade";"EvolveGroovedSpines";"HydraliskDen";296;0
"Unit";"Hydralisk";"Larva";313;2
"Unit";"Hydralisk";"Larva";313;2
"Building";"Extractor";NA;323;0
"Building";"SpawningPool";NA;327;0
