"type";"unit_name";"on_building";"total_supply";"supply"
"Unit";"Overlord";"Larva";13;0
"Building";"Extractor";NA;18;0
"Building";"Hatchery";NA;17;0
"Building";"SpawningPool";NA;18;0
"Unit";"Overlord";"Larva";22;0
"Unit";"Zergling";"Larva";25;1
"Unit";"Zergling";"Larva";25;1
"Unit";"Zergling";"Larva";25;1
"Unit";"Zergling";"Larva";25;1
"Unit";"Queen";"Hatchery";23;2
"Unit";"Queen";"Hatchery";23;2
"Building";"BanelingNest";NA;26;0
"Unit";"Overlord";"Larva";40;0
"Unit";"Overlord";"Larva";40;0
"Unit";"Zergling";"Larva";43;1
"Unit";"Zergling";"Larva";43;1
"Unit";"Zergling";"Larva";43;1
"Unit";"Zergling";"Larva";43;1
"Unit";"Zergling";"Larva";43;1
"Unit";"Zergling";"Larva";43;1
"Unit";"Zergling";"Larva";43;1
"Unit";"Zergling";"Larva";43;1
"Unit";"Zergling";"Larva";43;1
"Unit";"Zergling";"Larva";43;1
"Unit";"Zergling";"Larva";43;1
"Unit";"Zergling";"Larva";43;1
"Unit";"Zergling";"Larva";43;1
"Unit";"Zergling";"Larva";43;1
"Building";"Hatchery";NA;37;0
"Unit";"Baneling";"Zergling";55;0
"Unit";"Baneling";"Zergling";55;0
"Unit";"Baneling";"Zergling";55;0
"Unit";"Baneling";"Zergling";55;0
"Unit";"Zergling";"Larva";43;1
"Unit";"Zergling";"Larva";43;1
"Unit";"Zergling";"Larva";43;1
"Unit";"Zergling";"Larva";43;1
"Unit";"Zergling";"Larva";43;1
"Unit";"Zergling";"Larva";43;1
"Unit";"Zergling";"Larva";43;1
"Unit";"Zergling";"Larva";43;1
"Unit";"Zergling";"Larva";43;1
"Unit";"Zergling";"Larva";43;1
"Unit";"Zergling";"Larva";43;1
"Unit";"Zergling";"Larva";43;1
"Unit";"Zergling";"Larva";43;1
"Unit";"Zergling";"Larva";43;1
"Unit";"Baneling";"Zergling";71;0
"Unit";"Baneling";"Zergling";71;0
"Unit";"Zergling";"Larva";71;1
"Unit";"Zergling";"Larva";71;1
"Unit";"Zergling";"Larva";71;1
"Unit";"Zergling";"Larva";71;1
"Unit";"Zergling";"Larva";71;1
"Unit";"Zergling";"Larva";71;1
"Unit";"Zergling";"Larva";71;1
"Unit";"Zergling";"Larva";71;1
"Unit";"Zergling";"Larva";71;1
"Unit";"Zergling";"Larva";71;1
"Unit";"Zergling";"Larva";71;1
"Unit";"Zergling";"Larva";71;1
"Unit";"Zergling";"Larva";71;1
"Unit";"Zergling";"Larva";71;1
"Unit";"Overlord";"Larva";73;0
"Unit";"Baneling";"Zergling";79;0
"Unit";"Overlord";"Larva";75;0
"Unit";"Baneling";"Zergling";79;0
"Unit";"Queen";"Hatchery";71;2
"Unit";"Zergling";"Larva";79;1
"Unit";"Zergling";"Larva";79;1
"Building";"Extractor";NA;79;0
"Unit";"Zergling";"Larva";79;1
"Unit";"Zergling";"Larva";79;1
"Unit";"Zergling";"Larva";79;1
"Unit";"Zergling";"Larva";79;1
"Unit";"Zergling";"Larva";93;1
"Unit";"Zergling";"Larva";93;1
"Unit";"Zergling";"Larva";93;1
"Unit";"Zergling";"Larva";93;1
"Unit";"Zergling";"Larva";93;1
"Unit";"Zergling";"Larva";93;1
"Unit";"Zergling";"Larva";93;1
"Unit";"Zergling";"Larva";93;1
"Unit";"Zergling";"Larva";93;1
"Unit";"Zergling";"Larva";93;1
"Unit";"Zergling";"Larva";93;1
"Unit";"Zergling";"Larva";93;1
"Unit";"Zergling";"Larva";93;1
"Unit";"Zergling";"Larva";93;1
"Unit";"Zergling";"Larva";93;1
"Unit";"Zergling";"Larva";93;1
"Unit";"Zergling";"Larva";93;1
"Unit";"Zergling";"Larva";93;1
"Unit";"Zergling";"Larva";93;1
"Unit";"Zergling";"Larva";93;1
"Unit";"Zergling";"Larva";93;1
"Unit";"Zergling";"Larva";93;1
"Unit";"Baneling";"Zergling";93;0
"Unit";"Baneling";"Zergling";93;0
"Unit";"Baneling";"Zergling";93;0
"Unit";"Zergling";"Larva";115;1
"Unit";"Zergling";"Larva";115;1
"Unit";"Zergling";"Larva";115;1
"Unit";"Zergling";"Larva";115;1
"Unit";"Zergling";"Larva";115;1
"Unit";"Zergling";"Larva";115;1
"Unit";"Zergling";"Larva";115;1
"Unit";"Zergling";"Larva";115;1
"Unit";"Zergling";"Larva";115;1
"Unit";"Zergling";"Larva";115;1
"Unit";"Zergling";"Larva";115;1
"Unit";"Zergling";"Larva";115;1
"Unit";"Zergling";"Larva";115;1
"Unit";"Zergling";"Larva";115;1
"Unit";"Zergling";"Larva";115;1
"Unit";"Zergling";"Larva";115;1
"Unit";"Zergling";"Larva";115;1
"Unit";"Zergling";"Larva";115;1
"Unit";"Baneling";"Zergling";115;0
"Unit";"Baneling";"Zergling";115;0
"Unit";"Baneling";"Zergling";115;0
"Unit";"Baneling";"Zergling";115;0
"Unit";"Baneling";"Zergling";115;0
"Unit";"Baneling";"Zergling";115;0
"Unit";"Baneling";"Zergling";136;0
"Unit";"Zergling";"Larva";136;1
"Unit";"Zergling";"Larva";136;1
"Unit";"Zergling";"Larva";136;1
"Unit";"Zergling";"Larva";136;1
"Unit";"Zergling";"Larva";136;1
"Unit";"Zergling";"Larva";136;1
"Unit";"Zergling";"Larva";136;1
"Unit";"Zergling";"Larva";136;1
"Unit";"Zergling";"Larva";136;1
"Unit";"Zergling";"Larva";136;1
"Unit";"Zergling";"Larva";136;1
"Unit";"Zergling";"Larva";136;1
"Building";"Extractor";NA;136;0
"Unit";"Baneling";"Zergling";155;0
"Unit";"Baneling";"Zergling";155;0
"Unit";"Baneling";"Zergling";155;0
"Unit";"Baneling";"Zergling";155;0
"Unit";"Baneling";"Zergling";155;0
"Unit";"Zergling";"Larva";155;1
"Unit";"Zergling";"Larva";155;1
"Unit";"Zergling";"Larva";155;1
"Unit";"Zergling";"Larva";155;1
"Unit";"Zergling";"Larva";155;1
"Unit";"Zergling";"Larva";155;1
"Unit";"Zergling";"Larva";155;1
"Unit";"Zergling";"Larva";155;1
"Unit";"Zergling";"Larva";155;1
"Unit";"Zergling";"Larva";155;1
"Unit";"Zergling";"Larva";155;1
"Unit";"Zergling";"Larva";155;1
"Unit";"Zergling";"Larva";155;1
"Unit";"Zergling";"Larva";155;1
"Unit";"Zergling";"Larva";155;1
"Unit";"Zergling";"Larva";155;1
"Unit";"Zergling";"Larva";155;1
"Unit";"Zergling";"Larva";155;1
"Unit";"Zergling";"Larva";155;1
"Unit";"Zergling";"Larva";155;1
"Unit";"Zergling";"Larva";155;1
"Unit";"Zergling";"Larva";155;1
"Unit";"Zergling";"Larva";157;1
"Unit";"Zergling";"Larva";157;1
"Unit";"Zergling";"Larva";157;1
"Unit";"Zergling";"Larva";157;1
"Unit";"Zergling";"Larva";157;1
"Unit";"Zergling";"Larva";157;1
"Unit";"Zergling";"Larva";157;1
"Unit";"Zergling";"Larva";157;1
"Unit";"Zergling";"Larva";157;1
"Unit";"Zergling";"Larva";157;1
"Building";"CreepTumorQueen";NA;171;0
"Unit";"Zergling";"Larva";171;1
"Unit";"Zergling";"Larva";171;1
"Building";"SporeCrawler";NA;171;0
"Building";"HydraliskDen";NA;171;0
"Unit";"Zergling";"Larva";189;1
"Unit";"Zergling";"Larva";189;1
"Unit";"Zergling";"Larva";189;1
"Unit";"Zergling";"Larva";189;1
"Unit";"Zergling";"Larva";189;1
"Unit";"Zergling";"Larva";189;1
"Unit";"Zergling";"Larva";189;1
"Unit";"Zergling";"Larva";189;1
"Unit";"Zergling";"Larva";189;1
"Unit";"Zergling";"Larva";189;1
"Unit";"Zergling";"Larva";189;1
"Unit";"Zergling";"Larva";189;1
"Unit";"Zergling";"Larva";189;1
"Unit";"Zergling";"Larva";189;1
"Unit";"Queen";"Hatchery";171;2
"Unit";"Queen";"Hatchery";171;2
"Unit";"Queen";"Hatchery";171;2
"Unit";"Zergling";"Larva";189;1
"Unit";"Zergling";"Larva";189;1
"Unit";"Zergling";"Larva";189;1
"Unit";"Zergling";"Larva";189;1
"Unit";"Zergling";"Larva";189;1
"Unit";"Zergling";"Larva";189;1
"Building";"CreepTumorQueen";NA;209;0
"Building";"CreepTumorQueen";NA;215;0
"Building";"CreepTumorQueen";NA;215;0
"Unit";"Hydralisk";"Larva";209;2
"Unit";"Hydralisk";"Larva";209;2
"Unit";"Hydralisk";"Larva";209;2
"Unit";"Hydralisk";"Larva";209;2
"Unit";"Hydralisk";"Larva";209;2
"Unit";"Hydralisk";"Larva";209;2
"Unit";"Overlord";"Larva";215;0
"Unit";"Overlord";"Larva";215;0
"Unit";"Overlord";"Larva";215;0
"Unit";"Overlord";"Larva";215;0
"Unit";"Overlord";"Larva";215;0
"Unit";"Overlord";"Larva";215;0
"Building";"CreepTumorQueen";NA;227;0
"Building";"CreepTumor";NA;227;0
"Building";"CreepTumor";NA;227;0
"Building";"SporeCrawler";NA;227;0
"Building";"RoachWarren";NA;227;0
"Building";"SporeCrawler";NA;233;0
"Building";"CreepTumor";NA;239;0
"Building";"CreepTumor";NA;239;0
"Building";"Extractor";NA;239;0
"Building";"Extractor";NA;239;0
"Unit";"Hydralisk";"Larva";247;2
"Unit";"Hydralisk";"Larva";248;2
"Unit";"Hydralisk";"Larva";249;2
"Building";"CreepTumor";NA;250;0
"Building";"SporeCrawler";NA;250;0
"Unit";"Queen";"Hatchery";247;2
"Unit";"Queen";"Hatchery";247;2
"Upgrade";"EvolveGroovedSpines";"HydraliskDen";239;0
"Building";"Extractor";NA;250;0
"Unit";"Zergling";"Larva";264;1
"Unit";"Zergling";"Larva";264;1
"Unit";"Zergling";"Larva";264;1
"Unit";"Zergling";"Larva";264;1
"Unit";"Zergling";"Larva";264;1
"Unit";"Zergling";"Larva";264;1
"Unit";"Hydralisk";"Larva";264;2
"Unit";"Hydralisk";"Larva";264;2
"Unit";"Hydralisk";"Larva";264;2
"Unit";"Hydralisk";"Larva";264;2
"Unit";"Hydralisk";"Larva";264;2
"Building";"CreepTumorQueen";NA;268;0
"Building";"CreepTumorQueen";NA;268;0
"Building";"CreepTumor";NA;268;0
"Unit";"Overlord";"Larva";268;0
"Unit";"Overlord";"Larva";268;0
"Unit";"Baneling";"Zergling";274;0
"Unit";"Baneling";"Zergling";276;0
"Unit";"Baneling";"Zergling";276;0
"Unit";"Baneling";"Zergling";276;0
"Unit";"Baneling";"Zergling";278;0
"Unit";"Baneling";"Zergling";278;0
"Unit";"Baneling";"Zergling";284;0
"Unit";"Baneling";"Zergling";284;0
"Unit";"Baneling";"Zergling";284;0
"Unit";"Roach";"Larva";284;2
"Unit";"Roach";"Larva";284;2
"Building";"EvolutionChamber";NA;284;0
"Unit";"Roach";"Larva";284;2
"Unit";"Roach";"Larva";284;2
"Unit";"Roach";"Larva";284;2
"Unit";"Roach";"Larva";284;2
"Building";"EvolutionChamber";NA;284;0
"Unit";"Overlord";"Larva";287;0
"Unit";"Overlord";"Larva";287;0
"Upgrade";"EvolveMuscularAugments";"HydraliskDen";284;0
"Unit";"Baneling";"Zergling";299;0
"Unit";"Baneling";"Zergling";299;0
"Unit";"Baneling";"Zergling";299;0
"Unit";"Hydralisk";"Larva";299;2
"Upgrade";"GlialReconstitution";"RoachWarren";284;0
"Unit";"Hydralisk";"Larva";299;2
"Unit";"Hydralisk";"Larva";299;2
"Unit";"Hydralisk";"Larva";299;2
"Unit";"Hydralisk";"Larva";299;2
"Unit";"Overlord";"Larva";302;0
"Unit";"Overlord";"Larva";302;0
"Unit";"Hydralisk";"Larva";302;2
"Unit";"Hydralisk";"Larva";314;2
"Unit";"Hydralisk";"Larva";314;2
"Unit";"Hydralisk";"Larva";314;2
"Unit";"Hydralisk";"Larva";314;2
"Unit";"Hydralisk";"Larva";314;2
"Unit";"Hydralisk";"Larva";314;2
"Unit";"Hydralisk";"Larva";314;2
"Unit";"Hydralisk";"Larva";314;2
"Unit";"Hydralisk";"Larva";314;2
"Unit";"Hydralisk";"Larva";314;2
"Building";"SporeCrawler";NA;314;0
"Building";"InfestationPit";NA;314;0
"Unit";"Hydralisk";"Larva";314;2
"Unit";"Queen";"Hatchery";314;2
"Unit";"Hydralisk";"Larva";314;2
"Unit";"Hydralisk";"Larva";314;2
"Unit";"Hydralisk";"Larva";314;2
"Unit";"Queen";"Hatchery";314;2
"Unit";"Hydralisk";"Larva";314;2
"Unit";"Hydralisk";"Larva";314;2
"Unit";"Queen";"Hatchery";314;2
"Upgrade";"ZergMissileWeaponsLevel1";"EvolutionChamber";312;0
"Unit";"Hydralisk";"Larva";336;2
"Unit";"Hydralisk";"Larva";352;2
"Unit";"Hydralisk";"Larva";352;2
"Unit";"Hydralisk";"Larva";352;2
"Unit";"Hydralisk";"Larva";352;2
"Unit";"Hydralisk";"Larva";352;2
"Unit";"Hydralisk";"Larva";352;2
"Unit";"Hydralisk";"Larva";352;2
"Upgrade";"ZergGroundArmorsLevel1";"EvolutionChamber";314;0
"Building";"CreepTumorQueen";NA;368;0
"Building";"CreepTumorQueen";NA;368;0
"Building";"CreepTumorQueen";NA;368;0
"Building";"CreepTumor";NA;375;0
"Building";"CreepTumor";NA;375;0
"Unit";"Infestor";"Larva";375;2
"Unit";"Infestor";"Larva";375;2
"Building";"CreepTumor";NA;375;0
"Unit";"Zergling";"Larva";375;1
"Unit";"Zergling";"Larva";375;1
"Unit";"Zergling";"Larva";375;1
"Unit";"Zergling";"Larva";375;1
"Unit";"Zergling";"Larva";375;1
"Unit";"Zergling";"Larva";375;1
"Unit";"Zergling";"Larva";375;1
"Unit";"Zergling";"Larva";375;1
"Unit";"Zergling";"Larva";375;1
"Unit";"Zergling";"Larva";375;1
"Unit";"Zergling";"Larva";375;1
"Unit";"Zergling";"Larva";375;1
"Unit";"Zergling";"Larva";375;1
"Unit";"Zergling";"Larva";375;1
"Unit";"Zergling";"Larva";375;1
"Unit";"Zergling";"Larva";375;1
"Unit";"Zergling";"Larva";375;1
"Unit";"Zergling";"Larva";375;1
"Unit";"Zergling";"Larva";375;1
"Unit";"Zergling";"Larva";375;1
"Unit";"Zergling";"Larva";375;1
"Unit";"Zergling";"Larva";375;1
"Unit";"Zergling";"Larva";375;1
"Unit";"Zergling";"Larva";375;1
"Unit";"Infestor";"Larva";375;2
"Building";"CreepTumor";NA;403;0
"Building";"CreepTumor";NA;403;0
"Unit";"Overlord";"Larva";375;0
"Unit";"Overlord";"Larva";375;0
"Building";"Extractor";NA;405;0
"Building";"Extractor";NA;405;0
"Unit";"Zergling";"Larva";405;1
"Unit";"Zergling";"Larva";405;1
"Unit";"Zergling";"Larva";405;1
"Unit";"Zergling";"Larva";405;1
"Unit";"Zergling";"Larva";405;1
"Unit";"Zergling";"Larva";405;1
"Unit";"Zergling";"Larva";405;1
"Unit";"Zergling";"Larva";405;1
"Unit";"Zergling";"Larva";405;1
"Unit";"Zergling";"Larva";405;1
"Unit";"Zergling";"Larva";405;1
"Unit";"Zergling";"Larva";405;1
"Unit";"Zergling";"Larva";405;1
"Unit";"Zergling";"Larva";405;1
"Unit";"Zergling";"Larva";405;1
"Unit";"Zergling";"Larva";405;1
"Building";"Hatchery";NA;375;0
"Unit";"Infestor";"Larva";405;2
"Unit";"Infestor";"Larva";405;2
"Unit";"Infestor";"Larva";405;2
"Unit";"Infestor";"Larva";405;2
"Unit";"Baneling";"Zergling";421;0
"Unit";"Baneling";"Zergling";421;0
"Unit";"Baneling";"Zergling";421;0
"Unit";"Baneling";"Zergling";421;0
"Unit";"Baneling";"Zergling";421;0
"Unit";"Baneling";"Zergling";421;0
"Unit";"Baneling";"Zergling";421;0
"Unit";"Baneling";"Zergling";421;0
"Unit";"Baneling";"Zergling";421;0
"Unit";"Baneling";"Zergling";421;0
"Unit";"Baneling";"Zergling";421;0
"Unit";"Baneling";"Zergling";421;0
"Unit";"Baneling";"Zergling";421;0
"Unit";"Baneling";"Zergling";421;0
"Unit";"Hydralisk";"Larva";432;2
"Unit";"Hydralisk";"Larva";432;2
"Unit";"Hydralisk";"Larva";432;2
"Unit";"Hydralisk";"Larva";432;2
"Unit";"Hydralisk";"Larva";432;2
"Unit";"Hydralisk";"Larva";432;2
"Unit";"Hydralisk";"Larva";432;2
"Unit";"Hydralisk";"Larva";432;2
"Unit";"Hydralisk";"Larva";432;2
"Unit";"Hydralisk";"Larva";432;2
"Unit";"Hydralisk";"Larva";432;2
"Unit";"Hydralisk";"Larva";432;2
"Unit";"Hydralisk";"Larva";432;2
"Unit";"Baneling";"Zergling";432;0
"Unit";"Baneling";"Zergling";432;0
"Unit";"Baneling";"Zergling";432;0
"Unit";"Roach";"Larva";432;2
"Upgrade";"ZergMissileWeaponsLevel2";"EvolutionChamber";405;0
"Unit";"Roach";"Larva";432;2
"Unit";"Roach";"Larva";432;2
"Unit";"Roach";"Larva";432;2
"Unit";"Roach";"Larva";432;2
"Unit";"Roach";"Larva";432;2
"Unit";"Roach";"Larva";470;2
"Unit";"Roach";"Larva";470;2
"Unit";"Roach";"Larva";470;2
"Unit";"Roach";"Larva";470;2
"Unit";"Roach";"Larva";470;2
"Unit";"Roach";"Larva";470;2
"Unit";"Roach";"Larva";470;2
"Unit";"Roach";"Larva";470;2
"Unit";"Roach";"Larva";470;2
"Unit";"Roach";"Larva";470;2
"Unit";"Roach";"Larva";470;2
"Unit";"Zergling";"Larva";470;1
"Unit";"Zergling";"Larva";470;1
"Unit";"Zergling";"Larva";470;1
"Unit";"Zergling";"Larva";470;1
"Unit";"Zergling";"Larva";470;1
"Unit";"Zergling";"Larva";470;1
"Unit";"Zergling";"Larva";470;1
"Unit";"Zergling";"Larva";470;1
"Unit";"Zergling";"Larva";470;1
"Unit";"Zergling";"Larva";470;1
"Unit";"Zergling";"Larva";470;1
"Unit";"Zergling";"Larva";470;1
"Unit";"Zergling";"Larva";470;1
"Unit";"Zergling";"Larva";470;1
"Unit";"Zergling";"Larva";470;1
"Unit";"Zergling";"Larva";470;1
"Unit";"Hydralisk";"Larva";508;2
"Unit";"Hydralisk";"Larva";508;2
"Unit";"Hydralisk";"Larva";508;2
"Unit";"Hydralisk";"Larva";508;2
"Unit";"Hydralisk";"Larva";508;2
"Unit";"Hydralisk";"Larva";508;2
"Unit";"Hydralisk";"Larva";508;2
"Unit";"Overlord";"Larva";522;0
"Unit";"Overlord";"Larva";522;0
"Unit";"Overlord";"Larva";522;0
"Unit";"Overlord";"Larva";522;0
"Unit";"Hydralisk";"Larva";522;2
"Unit";"Hydralisk";"Larva";522;2
"Unit";"Hydralisk";"Larva";522;2
"Unit";"Hydralisk";"Larva";522;2
"Unit";"Hydralisk";"Larva";522;2
"Unit";"Hydralisk";"Larva";522;2
"Unit";"Hydralisk";"Larva";522;2
"Unit";"Hydralisk";"Larva";522;2
"Unit";"Hydralisk";"Larva";522;2
"Unit";"Hydralisk";"Larva";522;2
"Unit";"Hydralisk";"Larva";522;2
"Unit";"Hydralisk";"Larva";522;2
"Unit";"Hydralisk";"Larva";522;2
"Unit";"Hydralisk";"Larva";522;2
"Unit";"Hydralisk";"Larva";522;2
"Building";"CreepTumor";NA;552;0
"Building";"CreepTumor";NA;552;0
"Unit";"Overlord";"Larva";552;0
"Unit";"Overlord";"Larva";552;0
"Unit";"Overlord";"Larva";552;0
"Unit";"Overlord";"Larva";552;0
"Unit";"Overlord";"Larva";552;0
"Building";"CreepTumor";NA;552;0
"Building";"CreepTumor";NA;552;0
"Building";"CreepTumor";NA;552;0
"Unit";"Baneling";"Zergling";552;0
"Unit";"Baneling";"Zergling";552;0
"Unit";"Baneling";"Zergling";552;0
"Unit";"Baneling";"Zergling";552;0
"Unit";"Baneling";"Zergling";552;0
"Unit";"Baneling";"Zergling";552;0
"Unit";"Baneling";"Zergling";552;0
"Unit";"Baneling";"Zergling";552;0
"Unit";"Baneling";"Zergling";552;0
"Unit";"Baneling";"Zergling";552;0
"Unit";"Baneling";"Zergling";552;0
"Unit";"Baneling";"Zergling";552;0
"Unit";"Baneling";"Zergling";552;0
"Unit";"Baneling";"Zergling";552;0
"Unit";"Baneling";"Zergling";552;0
"Unit";"Baneling";"Zergling";552;0
"Unit";"Baneling";"Zergling";552;0
"Unit";"Baneling";"Zergling";552;0
"Unit";"Baneling";"Zergling";552;0
"Unit";"Baneling";"Zergling";552;0
"Unit";"Baneling";"Zergling";552;0
"Unit";"Baneling";"Zergling";552;0
"Unit";"Baneling";"Zergling";552;0
"Unit";"Baneling";"Zergling";552;0
"Unit";"Baneling";"Zergling";552;0
"Unit";"Baneling";"Zergling";552;0
"Unit";"Baneling";"Zergling";552;0
"Unit";"Baneling";"Zergling";552;0
"Unit";"Baneling";"Zergling";552;0
"Unit";"Baneling";"Zergling";552;0
"Building";"Extractor";NA;552;0
"Building";"Extractor";NA;552;0
"Building";"Hatchery";NA;552;0
"Unit";"Roach";"Larva";552;2
"Unit";"Roach";"Larva";552;2
"Unit";"Baneling";"Zergling";570;0
