"type";"unit_name";"on_building";"total_supply";"supply"
"Unit";"Overlord";"Larva";13;0
"Building";"Extractor";NA;16;0
"Building";"SpawningPool";NA;16;0
"Unit";"Zergling";"Larva";20;1
"Unit";"Zergling";"Larva";20;1
"Unit";"Queen";"Hatchery";20;2
"Unit";"Overlord";"Larva";24;0
"Building";"Hatchery";NA;19;0
"Unit";"Zergling";"Larva";26;1
"Unit";"Zergling";"Larva";26;1
"Unit";"Zergling";"Larva";26;1
"Unit";"Zergling";"Larva";26;1
"Unit";"Zergling";"Larva";26;1
"Unit";"Zergling";"Larva";26;1
"Building";"SpineCrawler";NA;24;0
"Unit";"Zergling";"Larva";28;1
"Unit";"Zergling";"Larva";28;1
"Unit";"Queen";"Hatchery";26;2
"Unit";"Zergling";"Larva";36;1
"Unit";"Zergling";"Larva";36;1
"Unit";"Zergling";"Larva";36;1
"Unit";"Zergling";"Larva";36;1
"Unit";"Zergling";"Larva";36;1
"Unit";"Zergling";"Larva";36;1
"Building";"CreepTumorQueen";NA;36;0
"Building";"BanelingNest";NA;32;0
"Unit";"Queen";"Hatchery";36;2
"Building";"CreepTumorQueen";NA;42;0
"Building";"CreepTumor";NA;42;0
"Unit";"Baneling";"Zergling";48;0
"Unit";"Baneling";"Zergling";48;0
"Unit";"Baneling";"Zergling";48;0
"Unit";"Baneling";"Zergling";48;0
"Unit";"Baneling";"Zergling";54;0
"Unit";"Baneling";"Zergling";54;0
"Unit";"Overlord";"Larva";54;0
"Building";"CreepTumor";NA;59;0
"Building";"CreepTumor";NA;59;0
"Building";"CreepTumorQueen";NA;64;0
"Building";"CreepTumorQueen";NA;65;0
"Building";"Extractor";NA;59;0
"Building";"Extractor";NA;60;0
"Building";"CreepTumor";NA;65;0
"Building";"CreepTumor";NA;71;0
"Building";"Extractor";NA;65;0
"Unit";"Overlord";"Larva";72;0
"Unit";"Overlord";"Larva";72;0
"Building";"RoachWarren";NA;65;0
"Unit";"Overlord";"Larva";72;0
"Unit";"Overlord";"Larva";72;0
"Building";"CreepTumor";NA;72;0
"Building";"CreepTumor";NA;72;0
"Building";"CreepTumor";NA;73;0
"Building";"CreepTumor";NA;74;0
"Unit";"Roach";"Larva";72;2
"Unit";"Roach";"Larva";72;2
"Unit";"Zergling";"Larva";74;1
"Unit";"Zergling";"Larva";74;1
"Unit";"Zergling";"Larva";74;1
"Unit";"Zergling";"Larva";74;1
"Unit";"Roach";"Larva";77;2
"Unit";"Roach";"Larva";77;2
"Unit";"Roach";"Larva";77;2
"Unit";"Roach";"Larva";77;2
"Unit";"Roach";"Larva";77;2
"Unit";"Roach";"Larva";77;2
"Building";"CreepTumor";NA;85;0
"Building";"CreepTumor";NA;85;0
"Building";"CreepTumor";NA;87;0
"Building";"CreepTumor";NA;97;0
"Building";"CreepTumorQueen";NA;97;0
"Unit";"Roach";"Larva";85;2
"Unit";"Roach";"Larva";85;2
"Unit";"Roach";"Larva";85;2
"Building";"CreepTumorQueen";NA;97;0
"Unit";"Baneling";"Zergling";97;0
"Unit";"Baneling";"Zergling";97;0
"Unit";"Baneling";"Zergling";97;0
"Unit";"Baneling";"Zergling";97;0
"Unit";"Overlord";"Larva";97;0
"Unit";"Overlord";"Larva";97;0
"Unit";"Overlord";"Larva";97;0
"Building";"CreepTumor";NA;103;0
"Building";"CreepTumor";NA;103;0
"Unit";"Roach";"Larva";103;2
"Building";"CreepTumor";NA;103;0
"Building";"CreepTumor";NA;103;0
"Building";"CreepTumor";NA;103;0
"Building";"CreepTumor";NA;103;0
"Upgrade";"GlialReconstitution";"RoachWarren";85;0
"Unit";"Roach";"Larva";108;2
"Unit";"Roach";"Larva";108;2
"Unit";"Roach";"Larva";108;2
"Unit";"Roach";"Larva";108;2
"Unit";"Roach";"Larva";108;2
"Unit";"Roach";"Larva";108;2
"Unit";"Roach";"Larva";108;2
"Building";"CreepTumor";NA;108;0
"Building";"CreepTumor";NA;108;0
"Building";"CreepTumor";NA;108;0
"Building";"CreepTumor";NA;122;0
"Building";"CreepTumor";NA;124;0
"Building";"CreepTumor";NA;125;0
"Building";"CreepTumor";NA;125;0
"Building";"CreepTumor";NA;125;0
"Building";"CreepTumor";NA;125;0
"Building";"Hatchery";NA;103;0
"Building";"EvolutionChamber";NA;125;0
"Building";"CreepTumor";NA;130;0
"Building";"CreepTumor";NA;131;0
"Building";"EvolutionChamber";NA;125;0
"Building";"CreepTumor";NA;131;0
"Unit";"Overlord";"Larva";131;0
"Building";"CreepTumor";NA;137;0
"Unit";"Overlord";"Larva";137;0
"Unit";"Overlord";"Larva";137;0
"Unit";"Overlord";"Larva";137;0
"Building";"CreepTumor";NA;137;0
"Building";"CreepTumor";NA;137;0
"Unit";"Roach";"Larva";137;2
"Unit";"Roach";"Larva";137;2
"Building";"CreepTumor";NA;137;0
"Unit";"Roach";"Larva";137;2
"Building";"CreepTumor";NA;137;0
"Building";"CreepTumor";NA;137;0
"Building";"Extractor";NA;137;0
"Building";"SporeCrawler";NA;137;0
"Building";"Extractor";NA;137;0
"Unit";"Roach";"Larva";143;2
"Unit";"Roach";"Larva";143;2
"Unit";"Roach";"Larva";143;2
"Unit";"Roach";"Larva";143;2
"Unit";"Roach";"Larva";143;2
"Building";"CreepTumor";NA;147;0
"Building";"CreepTumor";NA;147;0
"Building";"CreepTumor";NA;147;0
"Building";"CreepTumor";NA;147;0
"Building";"CreepTumor";NA;147;0
"Building";"CreepTumor";NA;155;0
"Unit";"Overlord";"Larva";157;0
"Unit";"Overlord";"Larva";157;0
"Unit";"Overlord";"Larva";157;0
"Unit";"Overlord";"Larva";157;0
"Building";"SporeCrawler";NA;157;0
"Building";"CreepTumor";NA;163;0
"Building";"SporeCrawler";NA;157;0
"Building";"CreepTumor";NA;163;0
"Building";"CreepTumor";NA;163;0
"Building";"HydraliskDen";NA;157;0
"Unit";"Roach";"Larva";163;2
"Unit";"Roach";"Larva";163;2
"Unit";"Roach";"Larva";163;2
"Unit";"Roach";"Larva";163;2
"Unit";"Roach";"Larva";163;2
"Unit";"Roach";"Larva";163;2
"Unit";"Roach";"Larva";163;2
"Unit";"Roach";"Larva";163;2
"Unit";"Roach";"Larva";163;2
"Unit";"Roach";"Larva";163;2
"Unit";"Roach";"Larva";163;2
"Unit";"Roach";"Larva";163;2
"Upgrade";"ZergMissileWeaponsLevel1";"EvolutionChamber";143;0
"Upgrade";"ZergGroundArmorsLevel1";"EvolutionChamber";143;0
"Unit";"Overlord";"Larva";187;0
"Unit";"Overlord";"Larva";187;0
"Building";"CreepTumor";NA;187;0
"Building";"CreepTumor";NA;187;0
"Building";"CreepTumor";NA;187;0
"Unit";"Hydralisk";"Larva";187;2
"Unit";"Hydralisk";"Larva";187;2
"Unit";"Hydralisk";"Larva";187;2
"Unit";"Hydralisk";"Larva";187;2
"Unit";"Hydralisk";"Larva";187;2
"Unit";"Hydralisk";"Larva";187;2
"Unit";"Overlord";"Larva";199;0
"Unit";"Overlord";"Larva";199;0
"Unit";"Overlord";"Larva";199;0
"Unit";"Roach";"Larva";199;2
"Unit";"Roach";"Larva";199;2
"Unit";"Roach";"Larva";199;2
"Unit";"Roach";"Larva";199;2
"Unit";"Roach";"Larva";199;2
"Unit";"Roach";"Larva";199;2
"Unit";"Roach";"Larva";199;2
"Unit";"Roach";"Larva";199;2
"Unit";"Roach";"Larva";199;2
"Unit";"Roach";"Larva";199;2
"Building";"InfestationPit";NA;199;0
"Upgrade";"EvolveGroovedSpines";"HydraliskDen";187;0
"Building";"Extractor";NA;199;0
"Building";"SpineCrawler";NA;199;0
"Building";"SpineCrawler";NA;199;0
"Building";"SpineCrawler";NA;199;0
"Upgrade";"Burrow";"Hatchery";199;0
"Building";"Spire";NA;199;0
"Unit";"Zergling";"Larva";219;1
"Unit";"Zergling";"Larva";219;1
"Unit";"Zergling";"Larva";219;1
"Unit";"Zergling";"Larva";219;1
"Unit";"Zergling";"Larva";219;1
"Unit";"Zergling";"Larva";219;1
"Unit";"Zergling";"Larva";219;1
"Unit";"Zergling";"Larva";219;1
"Unit";"Zergling";"Larva";219;1
"Unit";"Zergling";"Larva";219;1
"Unit";"Zergling";"Larva";219;1
"Unit";"Zergling";"Larva";219;1
"Unit";"Zergling";"Larva";219;1
"Unit";"Zergling";"Larva";219;1
"Unit";"Zergling";"Larva";219;1
"Unit";"Zergling";"Larva";219;1
"Unit";"Zergling";"Larva";219;1
"Unit";"Zergling";"Larva";219;1
"Unit";"Zergling";"Larva";219;1
"Unit";"Zergling";"Larva";219;1
"Unit";"Zergling";"Larva";219;1
"Unit";"Zergling";"Larva";219;1
"Unit";"Zergling";"Larva";219;1
"Unit";"Zergling";"Larva";219;1
"Unit";"Zergling";"Larva";219;1
"Unit";"Zergling";"Larva";219;1
"Unit";"Zergling";"Larva";219;1
"Unit";"Zergling";"Larva";219;1
"Unit";"Zergling";"Larva";219;1
"Unit";"Zergling";"Larva";219;1
"Building";"LurkerDenMP";NA;199;0
"Building";"Hatchery";NA;199;0
