"type";"unit_name";"on_building";"total_supply";"supply"
"Unit";"Overlord";"Larva";12;0
"Building";"Extractor";NA;17;0
"Unit";"Overlord";"Larva";21;0
"Building";"SpawningPool";NA;19;0
"Building";"Hatchery";NA;17;0
"Unit";"Zergling";"Larva";22;1
"Unit";"Zergling";"Larva";22;1
"Unit";"Zergling";"Larva";22;1
"Unit";"Zergling";"Larva";22;1
"Unit";"Queen";"Hatchery";22;2
"Unit";"Queen";"Hatchery";22;2
"Building";"CreepTumorQueen";NA;38;0
"Building";"BanelingNest";NA;35;0
"Unit";"Overlord";"Larva";38;0
"Unit";"Baneling";"Zergling";41;0
"Unit";"Baneling";"Zergling";41;0
"Unit";"Queen";"Hatchery";38;2
"Unit";"Baneling";"Zergling";41;0
"Unit";"Zergling";"Larva";41;1
"Unit";"Zergling";"Larva";41;1
"Unit";"Zergling";"Larva";41;1
"Unit";"Zergling";"Larva";41;1
"Unit";"Zergling";"Larva";41;1
"Unit";"Zergling";"Larva";41;1
"Unit";"Zergling";"Larva";41;1
"Unit";"Zergling";"Larva";41;1
"Building";"Hatchery";NA;33;0
"Building";"CreepTumor";NA;41;0
"Building";"CreepTumor";NA;57;0
"Unit";"Queen";"Hatchery";54;2
"Unit";"Queen";"Hatchery";54;2
"Unit";"Overlord";"Larva";57;0
"Unit";"Overlord";"Larva";57;0
"Building";"Extractor";NA;57;0
"Building";"RoachWarren";NA;55;0
"Building";"EvolutionChamber";NA;57;0
"Unit";"Zergling";"Larva";64;1
"Unit";"Zergling";"Larva";64;1
"Unit";"Zergling";"Larva";64;1
"Unit";"Zergling";"Larva";64;1
"Unit";"Zergling";"Larva";66;1
"Unit";"Zergling";"Larva";66;1
"Unit";"Zergling";"Larva";66;1
"Unit";"Zergling";"Larva";66;1
"Unit";"Zergling";"Larva";66;1
"Unit";"Zergling";"Larva";66;1
"Unit";"Zergling";"Larva";66;1
"Unit";"Zergling";"Larva";66;1
"Unit";"Zergling";"Larva";66;1
"Unit";"Zergling";"Larva";66;1
"Building";"CreepTumor";NA;69;0
"Building";"Extractor";NA;69;0
"Unit";"Roach";"Larva";77;2
"Unit";"Roach";"Larva";77;2
"Unit";"Roach";"Larva";77;2
"Unit";"Baneling";"Zergling";83;0
"Unit";"Overlord";"Larva";83;0
"Unit";"Overlord";"Larva";83;0
"Unit";"Baneling";"Zergling";83;0
"Unit";"Overlord";"Larva";83;0
"Unit";"Overlord";"Larva";89;0
"Unit";"Overlord";"Larva";89;0
"Building";"CreepTumorQueen";NA;113;0
"Unit";"Overlord";"Larva";112;0
"Building";"CreepTumorQueen";NA;119;0
"Building";"Extractor";NA;112;0
"Building";"Extractor";NA;112;0
"Upgrade";"ZergMissileWeaponsLevel1";"EvolutionChamber";89;0
"Building";"CreepTumor";NA;119;0
"Upgrade";"GlialReconstitution";"RoachWarren";97;0
"Building";"Extractor";NA;119;0
"Unit";"Roach";"Larva";119;2
"Unit";"Roach";"Larva";119;2
"Unit";"Roach";"Larva";119;2
"Unit";"Roach";"Larva";119;2
"Unit";"Roach";"Larva";119;2
"Unit";"Roach";"Larva";119;2
"Unit";"Overlord";"Larva";119;0
"Unit";"Roach";"Larva";119;2
"Unit";"Roach";"Larva";119;2
"Building";"EvolutionChamber";NA;119;0
"Unit";"Roach";"Larva";123;2
"Unit";"Roach";"Larva";123;2
"Unit";"Roach";"Larva";123;2
"Unit";"Overlord";"Larva";135;0
"Unit";"Overlord";"Larva";135;0
"Unit";"Roach";"Larva";139;2
"Unit";"Roach";"Larva";139;2
"Unit";"Roach";"Larva";139;2
"Building";"CreepTumor";NA;145;0
"Building";"CreepTumor";NA;145;0
"Building";"CreepTumor";NA;145;0
"Unit";"Overlord";"Larva";145;0
"Unit";"Overlord";"Larva";145;0
"Unit";"Overlord";"Larva";145;0
"Building";"CreepTumorQueen";NA;151;0
"Unit";"Roach";"Larva";145;2
"Unit";"Roach";"Larva";145;2
"Unit";"Roach";"Larva";145;2
"Unit";"Roach";"Larva";145;2
"Unit";"Roach";"Larva";151;2
"Building";"CreepTumorQueen";NA;151;0
"Building";"CreepTumorQueen";NA;151;0
"Unit";"Roach";"Larva";151;2
"Unit";"Roach";"Larva";151;2
"Unit";"Roach";"Larva";151;2
"Unit";"Overlord";"Larva";151;0
"Unit";"Overlord";"Larva";151;0
"Building";"Hatchery";NA;119;0
"Unit";"Roach";"Larva";151;2
"Unit";"Roach";"Larva";151;2
"Unit";"Roach";"Larva";151;2
"Unit";"Roach";"Larva";151;2
"Unit";"Roach";"Larva";161;2
"Unit";"Roach";"Larva";161;2
"Unit";"Roach";"Larva";163;2
"Unit";"Roach";"Larva";163;2
"Unit";"Roach";"Larva";167;2
"Unit";"Roach";"Larva";167;2
"Unit";"Roach";"Larva";167;2
"Unit";"Roach";"Larva";167;2
"Unit";"Roach";"Larva";169;2
"Unit";"Roach";"Larva";171;2
"Unit";"Roach";"Larva";173;2
"Unit";"Roach";"Larva";183;2
"Unit";"Roach";"Larva";183;2
"Unit";"Roach";"Larva";183;2
"Unit";"Roach";"Larva";183;2
"Unit";"Roach";"Larva";187;2
"Unit";"Roach";"Larva";187;2
"Unit";"Roach";"Larva";187;2
"Unit";"Roach";"Larva";197;2
"Unit";"Roach";"Larva";197;2
"Unit";"Roach";"Larva";197;2
"Unit";"Roach";"Larva";197;2
"Unit";"Roach";"Larva";197;2
"Unit";"Roach";"Larva";197;2
"Unit";"Roach";"Larva";197;2
"Unit";"Roach";"Larva";199;2
"Unit";"Overlord";"Larva";211;0
"Unit";"Roach";"Larva";211;2
"Unit";"Roach";"Larva";211;2
"Building";"Extractor";NA;211;0
"Upgrade";"ZergGroundArmorsLevel1";"EvolutionChamber";159;0
"Unit";"Roach";"Larva";225;2
"Unit";"Roach";"Larva";227;2
"Unit";"Roach";"Larva";229;2
"Unit";"Roach";"Larva";229;2
"Unit";"Roach";"Larva";229;2
"Unit";"Roach";"Larva";231;2
"Unit";"Roach";"Larva";233;2
"Unit";"Roach";"Larva";233;2
"Unit";"Roach";"Larva";233;2
"Unit";"Overlord";"Larva";233;0
"Upgrade";"ZergMissileWeaponsLevel2";"EvolutionChamber";161;0
"Unit";"Overlord";"Larva";237;0
"Unit";"Roach";"Larva";251;2
"Unit";"Roach";"Larva";251;2
"Unit";"Roach";"Larva";251;2
"Unit";"Roach";"Larva";251;2
"Upgrade";"Burrow";"Hatchery";229;0
"Unit";"Roach";"Larva";251;2
"Unit";"Roach";"Larva";251;2
"Unit";"Roach";"Larva";251;2
"Unit";"Roach";"Larva";251;2
"Upgrade";"TunnelingClaws";"RoachWarren";229;0
"Unit";"Roach";"Larva";251;2
"Unit";"Roach";"Larva";251;2
"Unit";"Roach";"Larva";251;2
"Unit";"Roach";"Larva";251;2
"Unit";"Roach";"Larva";251;2
"Unit";"Roach";"Larva";251;2
"Unit";"Roach";"Larva";251;2
"Unit";"Roach";"Larva";259;2
"Unit";"Roach";"Larva";259;2
"Unit";"Roach";"Larva";259;2
"Unit";"Roach";"Larva";259;2
"Unit";"Roach";"Larva";259;2
"Unit";"Roach";"Larva";281;2
"Unit";"Roach";"Larva";281;2
"Unit";"Roach";"Larva";281;2
"Unit";"Roach";"Larva";281;2
"Unit";"Roach";"Larva";281;2
"Unit";"Roach";"Larva";301;2
"Unit";"Roach";"Larva";301;2
"Unit";"Roach";"Larva";301;2
"Unit";"Roach";"Larva";301;2
"Unit";"Roach";"Larva";301;2
"Unit";"Roach";"Larva";301;2
"Unit";"Roach";"Larva";301;2
"Unit";"Roach";"Larva";301;2
"Unit";"Roach";"Larva";301;2
"Unit";"Roach";"Larva";319;2
"Unit";"Roach";"Larva";319;2
"Unit";"Roach";"Larva";319;2
"Unit";"Roach";"Larva";319;2
"Unit";"Roach";"Larva";319;2
"Unit";"Roach";"Larva";319;2
"Unit";"Roach";"Larva";319;2
"Unit";"Roach";"Larva";319;2
"Unit";"Roach";"Larva";319;2
"Unit";"Roach";"Larva";319;2
"Unit";"Roach";"Larva";319;2
"Unit";"Roach";"Larva";319;2
"Unit";"Roach";"Larva";319;2
"Unit";"Roach";"Larva";319;2
"Unit";"Roach";"Larva";319;2
"Unit";"Roach";"Larva";319;2
"Unit";"Roach";"Larva";319;2
"Unit";"Roach";"Larva";319;2
"Unit";"Roach";"Larva";323;2
"Unit";"Roach";"Larva";333;2
"Unit";"Roach";"Larva";341;2
"Unit";"Roach";"Larva";349;2
"Building";"CreepTumor";NA;355;0
"Building";"CreepTumor";NA;355;0
"Unit";"Roach";"Larva";349;2
"Unit";"Roach";"Larva";349;2
"Unit";"Roach";"Larva";349;2
"Unit";"Roach";"Larva";349;2
"Unit";"Roach";"Larva";355;2
"Unit";"Roach";"Larva";355;2
"Unit";"Roach";"Larva";355;2
"Unit";"Queen";"Hatchery";339;2
"Unit";"Roach";"Larva";359;2
"Unit";"Roach";"Larva";359;2
"Unit";"Roach";"Larva";359;2
"Unit";"Roach";"Larva";359;2
"Unit";"Roach";"Larva";371;2
"Unit";"Roach";"Larva";377;2
"Unit";"Roach";"Larva";377;2
"Unit";"Roach";"Larva";377;2
"Unit";"Roach";"Larva";377;2
"Unit";"Roach";"Larva";377;2
"Unit";"Roach";"Larva";377;2
