"type";"unit_name";"on_building";"total_supply";"supply"
"Unit";"Overlord";"Larva";12;0
"Building";"Extractor";NA;16;0
"Unit";"Overlord";"Larva";20;0
"Building";"SpawningPool";NA;18;0
"Building";"Hatchery";NA;16;0
"Unit";"Zergling";"Larva";21;1
"Unit";"Zergling";"Larva";21;1
"Unit";"Queen";"Hatchery";21;2
"Unit";"Queen";"Hatchery";23;2
"Unit";"Overlord";"Larva";36;0
"Building";"CreepTumorQueen";NA;36;0
"Unit";"Zergling";"Larva";36;1
"Unit";"Zergling";"Larva";36;1
"Unit";"Zergling";"Larva";36;1
"Unit";"Zergling";"Larva";36;1
"Unit";"Queen";"Hatchery";36;2
"Building";"BanelingNest";NA;36;0
"Unit";"Zergling";"Larva";39;1
"Unit";"Zergling";"Larva";39;1
"Unit";"Zergling";"Larva";39;1
"Unit";"Zergling";"Larva";39;1
"Unit";"Zergling";"Larva";39;1
"Unit";"Zergling";"Larva";39;1
"Unit";"Zergling";"Larva";39;1
"Unit";"Zergling";"Larva";39;1
"Unit";"Zergling";"Larva";39;1
"Unit";"Zergling";"Larva";39;1
"Unit";"Zergling";"Larva";39;1
"Unit";"Zergling";"Larva";39;1
"Building";"Hatchery";NA;32;0
"Unit";"Zergling";"Larva";45;1
"Unit";"Zergling";"Larva";45;1
"Unit";"Zergling";"Larva";45;1
"Unit";"Zergling";"Larva";45;1
"Unit";"Baneling";"Zergling";57;0
"Unit";"Baneling";"Zergling";57;0
"Unit";"Overlord";"Larva";45;0
"Unit";"Zergling";"Larva";61;1
"Unit";"Zergling";"Larva";61;1
"Unit";"Zergling";"Larva";61;1
"Unit";"Zergling";"Larva";61;1
"Unit";"Zergling";"Larva";61;1
"Unit";"Zergling";"Larva";61;1
"Unit";"Zergling";"Larva";61;1
"Unit";"Zergling";"Larva";61;1
"Unit";"Zergling";"Larva";61;1
"Unit";"Zergling";"Larva";61;1
"Unit";"Zergling";"Larva";61;1
"Unit";"Zergling";"Larva";61;1
"Unit";"Zergling";"Larva";61;1
"Unit";"Zergling";"Larva";61;1
"Unit";"Zergling";"Larva";61;1
"Unit";"Zergling";"Larva";61;1
"Unit";"Zergling";"Larva";61;1
"Unit";"Zergling";"Larva";61;1
"Unit";"Zergling";"Larva";61;1
"Unit";"Zergling";"Larva";61;1
"Unit";"Zergling";"Larva";61;1
"Unit";"Zergling";"Larva";61;1
"Unit";"Zergling";"Larva";61;1
"Unit";"Zergling";"Larva";61;1
"Unit";"Zergling";"Larva";61;1
"Unit";"Zergling";"Larva";61;1
"Unit";"Zergling";"Larva";61;1
"Unit";"Zergling";"Larva";61;1
"Unit";"Baneling";"Zergling";75;0
"Unit";"Baneling";"Zergling";75;0
"Unit";"Baneling";"Zergling";75;0
"Unit";"Overlord";"Larva";89;0
"Building";"CreepTumor";NA;89;0
"Unit";"Queen";"Hatchery";75;2
"Unit";"Baneling";"Zergling";89;0
"Unit";"Baneling";"Zergling";89;0
"Unit";"Queen";"Hatchery";75;2
"Building";"Extractor";NA;89;0
"Building";"CreepTumorQueen";NA;95;0
"Unit";"Overlord";"Larva";89;0
"Building";"EvolutionChamber";NA;89;0
"Unit";"Zergling";"Larva";95;1
"Unit";"Zergling";"Larva";95;1
"Unit";"Zergling";"Larva";95;1
"Unit";"Zergling";"Larva";95;1
"Unit";"Baneling";"Zergling";100;0
"Unit";"Baneling";"Zergling";100;0
"Building";"RoachWarren";NA;99;0
"Building";"CreepTumorQueen";NA;108;0
"Building";"Extractor";NA;108;0
"Unit";"Baneling";"Zergling";108;0
"Building";"CreepTumorQueen";NA;123;0
"Building";"CreepTumor";NA;123;0
"Building";"CreepTumor";NA;123;0
"Unit";"Overlord";"Larva";123;0
"Unit";"Overlord";"Larva";123;0
"Unit";"Overlord";"Larva";123;0
"Unit";"Roach";"Larva";131;2
"Unit";"Roach";"Larva";131;2
"Unit";"Roach";"Larva";131;2
"Unit";"Roach";"Larva";131;2
"Unit";"Roach";"Larva";131;2
"Unit";"Roach";"Larva";131;2
"Unit";"Roach";"Larva";131;2
"Unit";"Roach";"Larva";131;2
"Unit";"Roach";"Larva";131;2
"Unit";"Roach";"Larva";131;2
"Building";"CreepTumor";NA;132;0
"Building";"CreepTumor";NA;132;0
"Building";"CreepTumor";NA;132;0
"Building";"CreepTumor";NA;132;0
"Building";"Extractor";NA;132;0
"Unit";"Roach";"Larva";132;2
"Unit";"Roach";"Larva";132;2
"Unit";"Roach";"Larva";132;2
"Upgrade";"ZergMissileWeaponsLevel1";"EvolutionChamber";114;0
"Unit";"Overlord";"Larva";152;0
"Unit";"Overlord";"Larva";152;0
"Unit";"Zergling";"Larva";152;1
"Unit";"Zergling";"Larva";152;1
"Building";"Extractor";NA;152;0
"Unit";"Roach";"Larva";158;2
"Unit";"Roach";"Larva";158;2
"Unit";"Roach";"Larva";158;2
"Building";"CreepTumor";NA;166;0
"Building";"CreepTumor";NA;166;0
"Building";"SpineCrawler";NA;152;0
"Unit";"Overlord";"Larva";160;0
"Unit";"Overlord";"Larva";160;0
"Unit";"Overlord";"Larva";160;0
"Unit";"Overlord";"Larva";160;0
"Unit";"Overlord";"Larva";160;0
"Building";"CreepTumor";NA;171;0
"Building";"CreepTumorQueen";NA;171;0
"Unit";"Overlord";"Larva";166;0
"Unit";"Overlord";"Larva";166;0
"Building";"Extractor";NA;166;0
"Unit";"Baneling";"Zergling";171;0
"Unit";"Roach";"Larva";171;2
"Unit";"Baneling";"Zergling";171;0
"Unit";"Roach";"Larva";171;2
"Unit";"Roach";"Larva";171;2
"Unit";"Roach";"Larva";171;2
"Unit";"Roach";"Larva";171;2
"Unit";"Overlord";"Larva";171;0
"Unit";"Overlord";"Larva";171;0
"Unit";"Roach";"Larva";171;2
"Unit";"Roach";"Larva";171;2
"Upgrade";"GlialReconstitution";"RoachWarren";160;0
"Building";"CreepTumor";NA;184;0
"Unit";"Roach";"Larva";184;2
"Unit";"Roach";"Larva";184;2
"Unit";"Roach";"Larva";184;2
"Unit";"Roach";"Larva";184;2
"Unit";"Roach";"Larva";184;2
"Unit";"Roach";"Larva";184;2
"Unit";"Roach";"Larva";188;2
"Unit";"Roach";"Larva";188;2
"Unit";"Roach";"Larva";188;2
"Unit";"Roach";"Larva";188;2
"Unit";"Roach";"Larva";188;2
"Unit";"Roach";"Larva";188;2
"Unit";"Roach";"Larva";190;2
"Unit";"Roach";"Larva";190;2
"Unit";"Roach";"Larva";190;2
"Unit";"Roach";"Larva";190;2
"Unit";"Roach";"Larva";190;2
"Building";"CreepTumor";NA;210;0
"Building";"CreepTumor";NA;210;0
"Building";"CreepTumor";NA;210;0
"Unit";"Overlord";"Larva";210;0
"Unit";"Overlord";"Larva";210;0
"Unit";"Overlord";"Larva";210;0
"Building";"Hatchery";NA;171;0
"Unit";"Roach";"Larva";222;2
"Unit";"Roach";"Larva";222;2
"Unit";"Roach";"Larva";222;2
"Building";"CreepTumor";NA;222;0
"Unit";"Roach";"Larva";222;2
"Unit";"Roach";"Larva";222;2
"Unit";"Roach";"Larva";222;2
"Unit";"Roach";"Larva";222;2
"Unit";"Roach";"Larva";222;2
"Unit";"Roach";"Larva";222;2
"Unit";"Roach";"Larva";222;2
"Unit";"Queen";"Hatchery";222;2
"Unit";"Roach";"Larva";228;2
"Unit";"Roach";"Larva";228;2
"Unit";"Roach";"Larva";228;2
"Unit";"Roach";"Larva";228;2
"Unit";"Roach";"Larva";228;2
"Unit";"Roach";"Larva";228;2
"Unit";"Roach";"Larva";228;2
"Unit";"Roach";"Larva";228;2
"Unit";"Roach";"Larva";238;2
"Unit";"Roach";"Larva";238;2
"Unit";"Roach";"Larva";238;2
"Unit";"Overlord";"Larva";242;0
"Unit";"Roach";"Larva";260;2
"Building";"HydraliskDen";NA;244;0
"Unit";"Roach";"Larva";266;2
"Unit";"Roach";"Larva";266;2
"Unit";"Roach";"Larva";266;2
"Unit";"Roach";"Larva";266;2
