"type";"unit_name";"on_building";"total_supply";"supply"
"Unit";"Overlord";"Larva";12;0
"Building";"Extractor";NA;18;0
"Unit";"Overlord";"Larva";21;0
"Building";"SpawningPool";NA;19;0
"Building";"Hatchery";NA;17;0
"Unit";"Queen";"Hatchery";22;2
"Unit";"Queen";"Hatchery";23;2
"Unit";"Zergling";"Larva";27;1
"Unit";"Zergling";"Larva";27;1
"Building";"CreepTumorQueen";NA;33;0
"Unit";"Overlord";"Larva";35;0
"Unit";"Queen";"Hatchery";33;2
"Unit";"Overlord";"Larva";36;0
"Building";"CreepTumor";NA;36;0
"Building";"BanelingNest";NA;35;0
"Unit";"Overlord";"Larva";38;0
"Unit";"Overlord";"Larva";38;0
"Building";"Hatchery";NA;33;0
"Unit";"Zergling";"Larva";42;1
"Unit";"Zergling";"Larva";42;1
"Unit";"Zergling";"Larva";42;1
"Unit";"Zergling";"Larva";42;1
"Unit";"Zergling";"Larva";42;1
"Unit";"Zergling";"Larva";42;1
"Unit";"Zergling";"Larva";42;1
"Unit";"Zergling";"Larva";42;1
"Building";"CreepTumor";NA;42;0
"Unit";"Zergling";"Larva";42;1
"Unit";"Zergling";"Larva";42;1
"Unit";"Zergling";"Larva";43;1
"Unit";"Zergling";"Larva";43;1
"Unit";"Zergling";"Larva";43;1
"Unit";"Zergling";"Larva";43;1
"Unit";"Zergling";"Larva";43;1
"Unit";"Zergling";"Larva";43;1
"Unit";"Zergling";"Larva";43;1
"Unit";"Zergling";"Larva";43;1
"Unit";"Zergling";"Larva";43;1
"Unit";"Zergling";"Larva";43;1
"Unit";"Zergling";"Larva";43;1
"Unit";"Zergling";"Larva";43;1
"Unit";"Baneling";"Zergling";51;0
"Unit";"Baneling";"Zergling";51;0
"Unit";"Baneling";"Zergling";51;0
"Unit";"Baneling";"Zergling";51;0
"Unit";"Zergling";"Larva";49;1
"Unit";"Zergling";"Larva";49;1
"Unit";"Overlord";"Larva";65;0
"Unit";"Queen";"Hatchery";55;2
"Unit";"Overlord";"Larva";72;0
"Unit";"Zergling";"Larva";83;1
"Unit";"Zergling";"Larva";83;1
"Unit";"Zergling";"Larva";83;1
"Unit";"Zergling";"Larva";83;1
"Unit";"Zergling";"Larva";83;1
"Unit";"Zergling";"Larva";83;1
"Unit";"Zergling";"Larva";83;1
"Unit";"Zergling";"Larva";83;1
"Unit";"Zergling";"Larva";83;1
"Unit";"Zergling";"Larva";83;1
"Unit";"Zergling";"Larva";83;1
"Unit";"Zergling";"Larva";83;1
"Building";"CreepTumor";NA;99;0
"Unit";"Zergling";"Larva";99;1
"Unit";"Zergling";"Larva";99;1
"Unit";"Zergling";"Larva";99;1
"Unit";"Zergling";"Larva";99;1
"Unit";"Zergling";"Larva";99;1
"Unit";"Zergling";"Larva";99;1
"Unit";"Zergling";"Larva";99;1
"Unit";"Zergling";"Larva";99;1
"Building";"EvolutionChamber";NA;84;0
"Unit";"Overlord";"Larva";99;0
"Building";"Extractor";NA;99;0
"Building";"Extractor";NA;99;0
"Building";"RoachWarren";NA;84;0
"Unit";"Overlord";"Larva";107;0
"Unit";"Roach";"Larva";107;2
"Unit";"Roach";"Larva";107;2
"Unit";"Roach";"Larva";107;2
"Unit";"Roach";"Larva";107;2
"Unit";"Roach";"Larva";107;2
"Unit";"Roach";"Larva";107;2
"Unit";"Roach";"Larva";107;2
"Unit";"Roach";"Larva";107;2
"Unit";"Roach";"Larva";107;2
"Unit";"Roach";"Larva";107;2
"Unit";"Overlord";"Larva";107;0
"Unit";"Overlord";"Larva";107;0
"Unit";"Overlord";"Larva";107;0
"Unit";"Roach";"Larva";107;2
"Unit";"Roach";"Larva";107;2
"Unit";"Overlord";"Larva";128;0
"Building";"Extractor";NA;128;0
"Unit";"Overlord";"Larva";139;0
"Building";"CreepTumor";NA;139;0
"Unit";"Roach";"Larva";139;2
"Unit";"Roach";"Larva";139;2
"Unit";"Roach";"Larva";139;2
"Unit";"Roach";"Larva";139;2
"Unit";"Roach";"Larva";139;2
"Unit";"Roach";"Larva";139;2
"Unit";"Roach";"Larva";139;2
"Unit";"Roach";"Larva";139;2
"Unit";"Roach";"Larva";142;2
"Unit";"Roach";"Larva";142;2
"Unit";"Overlord";"Larva";144;0
"Unit";"Overlord";"Larva";146;0
"Unit";"Roach";"Larva";164;2
"Unit";"Roach";"Larva";164;2
"Unit";"Roach";"Larva";164;2
"Unit";"Roach";"Larva";164;2
"Unit";"Roach";"Larva";164;2
"Unit";"Roach";"Larva";166;2
"Unit";"Overlord";"Larva";166;0
"Upgrade";"ZergMissileWeaponsLevel1";"EvolutionChamber";128;0
"Unit";"Roach";"Larva";166;2
"Unit";"Roach";"Larva";166;2
"Building";"Extractor";NA;166;0
"Unit";"Roach";"Larva";166;2
"Unit";"Roach";"Larva";166;2
"Unit";"Roach";"Larva";166;2
"Unit";"Roach";"Larva";176;2
"Unit";"Roach";"Larva";176;2
"Unit";"Roach";"Larva";176;2
"Unit";"Roach";"Larva";178;2
"Unit";"Roach";"Larva";178;2
"Unit";"Roach";"Larva";180;2
"Unit";"Roach";"Larva";180;2
"Unit";"Roach";"Larva";188;2
"Unit";"Roach";"Larva";192;2
"Unit";"Roach";"Larva";192;2
"Unit";"Roach";"Larva";192;2
"Unit";"Roach";"Larva";192;2
"Unit";"Overlord";"Larva";196;0
"Unit";"Roach";"Larva";202;2
"Unit";"Overlord";"Larva";202;0
"Unit";"Roach";"Larva";202;2
"Unit";"Roach";"Larva";202;2
"Unit";"Overlord";"Larva";202;0
"Unit";"Overlord";"Larva";212;0
"Upgrade";"GlialReconstitution";"RoachWarren";178;0
"Unit";"Zergling";"Larva";212;1
"Unit";"Zergling";"Larva";212;1
"Unit";"Overlord";"Larva";212;0
"Unit";"Roach";"Larva";218;2
"Unit";"Roach";"Larva";218;2
"Unit";"Roach";"Larva";218;2
"Unit";"Roach";"Larva";218;2
"Unit";"Roach";"Larva";218;2
"Unit";"Roach";"Larva";218;2
"Unit";"Roach";"Larva";218;2
"Unit";"Roach";"Larva";218;2
