"type";"unit_name";"on_building";"total_supply";"supply"
"Unit";"Overlord";"Larva";12;0
"Building";"SpawningPool";NA;16;0
"Unit";"Overlord";"Larva";18;0
"Unit";"Zergling";"Larva";20;1
"Unit";"Zergling";"Larva";20;1
"Unit";"Zergling";"Larva";20;1
"Unit";"Zergling";"Larva";20;1
"Unit";"Queen";"Hatchery";18;2
"Building";"Hatchery";NA;18;0
"Unit";"Queen";"Hatchery";25;2
"Unit";"Queen";"Hatchery";28;2
"Unit";"Queen";"Hatchery";34;2
"Unit";"Overlord";"Larva";40;0
"Building";"EvolutionChamber";NA;40;0
"Building";"CreepTumorQueen";NA;42;0
"Building";"CreepTumorQueen";NA;42;0
"Building";"CreepTumorQueen";NA;42;0
"Building";"CreepTumorQueen";NA;42;0
"Building";"Extractor";NA;40;0
"Building";"EvolutionChamber";NA;40;0
"Building";"Extractor";NA;42;0
"Unit";"Queen";"Hatchery";40;2
"Building";"Hatchery";NA;30;0
"Unit";"Overlord";"Larva";42;0
"Building";"CreepTumor";NA;44;0
"Building";"CreepTumor";NA;54;0
"Building";"CreepTumorQueen";NA;54;0
"Building";"CreepTumor";NA;54;0
"Building";"CreepTumorQueen";NA;54;0
"Building";"Extractor";NA;60;0
"Building";"RoachWarren";NA;54;0
"Building";"Extractor";NA;60;0
"Unit";"Roach";"Larva";63;2
"Unit";"Roach";"Larva";63;2
"Unit";"Overlord";"Larva";66;0
"Unit";"Overlord";"Larva";66;0
"Unit";"Overlord";"Larva";66;0
"Unit";"Overlord";"Larva";66;0
"Building";"CreepTumor";NA;70;0
"Unit";"Roach";"Larva";70;2
"Unit";"Roach";"Larva";70;2
"Unit";"Roach";"Larva";70;2
"Unit";"Roach";"Larva";70;2
"Unit";"Roach";"Larva";70;2
"Unit";"Roach";"Larva";70;2
"Unit";"Roach";"Larva";70;2
"Unit";"Roach";"Larva";70;2
"Unit";"Roach";"Larva";70;2
"Unit";"Roach";"Larva";70;2
"Unit";"Roach";"Larva";90;2
"Unit";"Roach";"Larva";90;2
"Unit";"Roach";"Larva";90;2
"Unit";"Overlord";"Larva";92;0
"Upgrade";"ZergMissileWeaponsLevel1";"EvolutionChamber";70;0
"Building";"CreepTumor";NA;98;0
"Unit";"Roach";"Larva";98;2
"Unit";"Roach";"Larva";98;2
"Unit";"Roach";"Larva";98;2
"Unit";"Roach";"Larva";98;2
"Unit";"Roach";"Larva";98;2
"Unit";"Overlord";"Larva";98;0
"Unit";"Overlord";"Larva";98;0
"Unit";"Overlord";"Larva";98;0
"Unit";"Overlord";"Larva";98;0
"Building";"CreepTumorQueen";NA;98;0
"Building";"CreepTumorQueen";NA;108;0
"Building";"CreepTumorQueen";NA;108;0
"Building";"Hatchery";NA;92;0
"Upgrade";"ZergGroundArmorsLevel1";"EvolutionChamber";92;0
"Building";"Hatchery";NA;98;0
"Building";"CreepTumorQueen";NA;117;0
"Building";"CreepTumor";NA;115;0
"Building";"CreepTumor";NA;115;0
"Building";"CreepTumor";NA;117;0
"Building";"CreepTumorQueen";NA;117;0
"Building";"HydraliskDen";NA;115;0
"Building";"SporeCrawler";NA;118;0
"Building";"SporeCrawler";NA;118;0
"Building";"SporeCrawler";NA;118;0
"Building";"SporeCrawler";NA;118;0
"Building";"CreepTumor";NA;122;0
"Unit";"Roach";"Larva";118;2
"Unit";"Roach";"Larva";118;2
"Unit";"Roach";"Larva";118;2
"Unit";"Roach";"Larva";118;2
"Unit";"Roach";"Larva";118;2
"Building";"CreepTumor";NA;122;0
"Building";"CreepTumor";NA;122;0
"Building";"CreepTumorQueen";NA;124;0
"Building";"CreepTumorQueen";NA;124;0
"Unit";"Roach";"Larva";122;2
"Unit";"Roach";"Larva";122;2
"Unit";"Roach";"Larva";122;2
"Upgrade";"GlialReconstitution";"RoachWarren";115;0
"Unit";"Overlord";"Larva";134;0
"Unit";"Overlord";"Larva";134;0
"Unit";"Overlord";"Larva";134;0
"Unit";"Overlord";"Larva";134;0
"Unit";"Overlord";"Larva";140;0
"Unit";"Overlord";"Larva";140;0
"Unit";"Overlord";"Larva";140;0
"Unit";"Overlord";"Larva";140;0
"Building";"CreepTumorQueen";NA;145;0
"Building";"CreepTumor";NA;145;0
"Building";"CreepTumor";NA;145;0
"Building";"CreepTumorQueen";NA;145;0
"Building";"CreepTumor";NA;145;0
"Building";"CreepTumorQueen";NA;145;0
"Building";"CreepTumor";NA;145;0
"Building";"CreepTumor";NA;145;0
"Unit";"Overlord";"Larva";145;0
"Unit";"Roach";"Larva";145;2
"Unit";"Roach";"Larva";145;2
"Unit";"Roach";"Larva";145;2
"Unit";"Roach";"Larva";145;2
"Unit";"Roach";"Larva";145;2
"Unit";"Roach";"Larva";145;2
"Unit";"Roach";"Larva";145;2
"Unit";"Roach";"Larva";145;2
"Unit";"Roach";"Larva";145;2
"Unit";"Roach";"Larva";145;2
"Unit";"Roach";"Larva";145;2
"Upgrade";"EvolveGroovedSpines";"HydraliskDen";145;0
"Building";"CreepTumor";NA;163;0
"Building";"CreepTumor";NA;163;0
"Building";"CreepTumor";NA;163;0
"Building";"CreepTumor";NA;163;0
"Building";"CreepTumor";NA;167;0
"Building";"CreepTumor";NA;167;0
"Building";"CreepTumor";NA;167;0
"Building";"CreepTumor";NA;167;0
"Building";"CreepTumor";NA;184;0
"Building";"CreepTumor";NA;184;0
"Building";"Extractor";NA;184;0
"Building";"CreepTumor";NA;184;0
"Building";"Extractor";NA;184;0
"Building";"CreepTumor";NA;184;0
"Building";"Extractor";NA;184;0
"Building";"Extractor";NA;184;0
"Building";"CreepTumor";NA;184;0
"Building";"CreepTumor";NA;184;0
"Building";"CreepTumor";NA;184;0
"Building";"CreepTumor";NA;184;0
"Upgrade";"EvolveMuscularAugments";"HydraliskDen";184;0
"Building";"CreepTumor";NA;193;0
"Building";"CreepTumor";NA;193;0
"Building";"CreepTumor";NA;193;0
"Building";"CreepTumor";NA;193;0
"Building";"CreepTumor";NA;193;0
"Building";"CreepTumor";NA;193;0
"Unit";"Hydralisk";"Larva";193;2
"Unit";"Hydralisk";"Larva";193;2
"Unit";"Hydralisk";"Larva";193;2
"Unit";"Hydralisk";"Larva";193;2
"Unit";"Hydralisk";"Larva";193;2
"Unit";"Hydralisk";"Larva";193;2
"Unit";"Hydralisk";"Larva";193;2
"Unit";"Hydralisk";"Larva";193;2
"Unit";"Overlord";"Larva";193;0
"Unit";"Overlord";"Larva";193;0
"Unit";"Overlord";"Larva";193;0
"Unit";"Overlord";"Larva";193;0
"Building";"CreepTumor";NA;210;0
"Building";"CreepTumor";NA;210;0
"Building";"CreepTumor";NA;210;0
"Building";"Extractor";NA;210;0
"Building";"CreepTumor";NA;210;0
"Building";"CreepTumor";NA;210;0
"Building";"CreepTumor";NA;210;0
"Building";"Extractor";NA;210;0
"Building";"CreepTumor";NA;210;0
"Building";"CreepTumor";NA;212;0
"Building";"CreepTumor";NA;212;0
"Building";"CreepTumor";NA;212;0
"Building";"InfestationPit";NA;210;0
"Upgrade";"ZergGroundArmorsLevel2";"EvolutionChamber";193;0
"Building";"CreepTumor";NA;212;0
"Building";"CreepTumor";NA;212;0
"Building";"CreepTumor";NA;212;0
"Building";"LurkerDenMP";NA;193;0
"Building";"CreepTumor";NA;212;0
"Building";"CreepTumor";NA;212;0
"Building";"CreepTumor";NA;212;0
"Unit";"Overlord";"Larva";212;0
"Building";"Hatchery";NA;210;0
"Building";"CreepTumor";NA;212;0
"Unit";"Hydralisk";"Larva";212;2
"Unit";"Hydralisk";"Larva";212;2
"Unit";"Hydralisk";"Larva";212;2
"Unit";"Hydralisk";"Larva";212;2
"Unit";"Hydralisk";"Larva";212;2
"Unit";"Hydralisk";"Larva";212;2
"Unit";"Hydralisk";"Larva";212;2
"Building";"Spire";NA;210;0
"Building";"CreepTumor";NA;212;0
"Building";"CreepTumor";NA;212;0
"Building";"CreepTumor";NA;212;0
"Unit";"Hydralisk";"Larva";226;2
"Unit";"Hydralisk";"Larva";226;2
"Upgrade";"ZergMissileWeaponsLevel2";"EvolutionChamber";212;0
"Unit";"Hydralisk";"Larva";230;2
"Unit";"Roach";"Larva";230;2
"Unit";"Roach";"Larva";230;2
"Unit";"Roach";"Larva";230;2
"Unit";"Hydralisk";"Larva";230;2
"Unit";"Hydralisk";"Larva";240;2
"Unit";"Hydralisk";"Larva";240;2
"Unit";"Hydralisk";"Larva";240;2
"Unit";"Hydralisk";"Larva";240;2
"Unit";"Hydralisk";"Larva";240;2
"Unit";"Hydralisk";"Larva";240;2
"Unit";"Mutalisk";"Larva";240;2
"Unit";"Mutalisk";"Larva";240;2
"Unit";"Mutalisk";"Larva";240;2
"Unit";"Mutalisk";"Larva";240;2
"Unit";"Mutalisk";"Larva";240;2
"Unit";"Mutalisk";"Larva";240;2
"Unit";"Mutalisk";"Larva";240;2
"Unit";"Mutalisk";"Larva";240;2
"Unit";"Mutalisk";"Larva";240;2
"Unit";"Mutalisk";"Larva";240;2
"Unit";"Mutalisk";"Larva";240;2
"Unit";"Mutalisk";"Larva";240;2
"Unit";"Mutalisk";"Larva";240;2
"Unit";"Mutalisk";"Larva";240;2
"Unit";"Mutalisk";"Larva";240;2
"Unit";"Mutalisk";"Larva";240;2
"Unit";"Mutalisk";"Larva";240;2
"Unit";"Mutalisk";"Larva";240;2
"Unit";"Mutalisk";"Larva";258;2
"Unit";"Mutalisk";"Larva";258;2
"Unit";"Mutalisk";"Larva";258;2
"Unit";"Mutalisk";"Larva";258;2
"Unit";"Mutalisk";"Larva";258;2
"Unit";"Mutalisk";"Larva";258;2
"Unit";"Mutalisk";"Larva";258;2
"Unit";"Mutalisk";"Larva";258;2
"Unit";"Mutalisk";"Larva";259;2
"Unit";"Mutalisk";"Larva";259;2
"Unit";"Mutalisk";"Larva";259;2
"Unit";"Mutalisk";"Larva";259;2
"Unit";"Mutalisk";"Larva";259;2
"Building";"CreepTumorQueen";NA;291;0
"Building";"CreepTumorQueen";NA;317;0
"Building";"CreepTumorQueen";NA;317;0
