"type";"unit_name";"on_building";"total_supply";"supply"
"Unit";"Overlord";"Larva";12;0
"Building";"Extractor";NA;16;0
"Building";"SpawningPool";NA;17;0
"Unit";"Overlord";"Larva";21;0
"Unit";"Zergling";"Larva";21;1
"Unit";"Zergling";"Larva";21;1
"Unit";"Zergling";"Larva";21;1
"Unit";"Zergling";"Larva";21;1
"Unit";"Queen";"Hatchery";21;2
"Unit";"Zergling";"Larva";21;1
"Unit";"Zergling";"Larva";21;1
"Building";"Hatchery";NA;20;0
"Unit";"Zergling";"Larva";29;1
"Unit";"Zergling";"Larva";29;1
"Unit";"Queen";"Hatchery";25;2
"Unit";"Zergling";"Larva";29;1
"Unit";"Zergling";"Larva";29;1
"Building";"BanelingNest";NA;23;0
"Building";"SpineCrawler";NA;29;0
"Unit";"Zergling";"Larva";35;1
"Unit";"Zergling";"Larva";35;1
"Unit";"Zergling";"Larva";35;1
"Unit";"Zergling";"Larva";35;1
"Unit";"Zergling";"Larva";35;1
"Unit";"Zergling";"Larva";35;1
"Unit";"Baneling";"Zergling";35;0
"Unit";"Baneling";"Zergling";35;0
"Unit";"Queen";"Hatchery";31;2
"Unit";"Baneling";"Zergling";44;0
"Unit";"Baneling";"Zergling";44;0
"Unit";"Zergling";"Larva";45;1
"Unit";"Zergling";"Larva";45;1
"Unit";"Zergling";"Larva";45;1
"Unit";"Zergling";"Larva";45;1
"Unit";"Queen";"Hatchery";44;2
"Building";"CreepTumorQueen";NA;54;0
"Unit";"Zergling";"Larva";52;1
"Unit";"Zergling";"Larva";52;1
"Unit";"Baneling";"Zergling";59;0
"Unit";"Overlord";"Larva";56;0
"Building";"CreepTumor";NA;63;0
"Unit";"Zergling";"Larva";63;1
"Unit";"Zergling";"Larva";63;1
"Unit";"Zergling";"Larva";63;1
"Unit";"Zergling";"Larva";63;1
"Building";"Extractor";NA;63;0
"Unit";"Overlord";"Larva";64;0
"Building";"CreepTumor";NA;75;0
"Building";"Extractor";NA;75;0
"Building";"Extractor";NA;75;0
"Unit";"Overlord";"Larva";79;0
"Unit";"Overlord";"Larva";79;0
"Unit";"Queen";"Hatchery";75;2
"Unit";"Zergling";"Larva";83;1
"Unit";"Zergling";"Larva";83;1
"Unit";"Zergling";"Larva";83;1
"Unit";"Zergling";"Larva";83;1
"Unit";"Overlord";"Larva";83;0
"Building";"CreepTumorQueen";NA;92;0
"Building";"CreepTumor";NA;92;0
"Unit";"Baneling";"Zergling";94;0
"Unit";"Zergling";"Larva";92;1
"Unit";"Zergling";"Larva";92;1
"Unit";"Queen";"Hatchery";85;2
"Building";"Hatchery";NA;83;0
"Unit";"Overlord";"Larva";101;0
"Unit";"Overlord";"Larva";101;0
"Building";"Extractor";NA;104;0
"Building";"Spire";NA;94;0
"Building";"Extractor";NA;104;0
"Unit";"Baneling";"Zergling";115;0
"Unit";"Baneling";"Zergling";115;0
"Unit";"Baneling";"Zergling";115;0
"Unit";"Baneling";"Zergling";115;0
"Unit";"Zergling";"Larva";115;1
"Unit";"Zergling";"Larva";115;1
"Unit";"Mutalisk";"Larva";113;2
"Unit";"Mutalisk";"Larva";113;2
"Unit";"Mutalisk";"Larva";113;2
"Unit";"Zergling";"Larva";115;1
"Unit";"Zergling";"Larva";115;1
"Unit";"Mutalisk";"Larva";113;2
"Unit";"Zergling";"Larva";115;1
"Unit";"Zergling";"Larva";115;1
"Unit";"Zergling";"Larva";115;1
"Unit";"Zergling";"Larva";115;1
"Unit";"Mutalisk";"Larva";113;2
"Unit";"Mutalisk";"Larva";113;2
"Unit";"Mutalisk";"Larva";113;2
"Unit";"Mutalisk";"Larva";113;2
"Building";"EvolutionChamber";NA;113;0
"Unit";"Overlord";"Larva";115;0
"Unit";"Overlord";"Larva";115;0
"Unit";"Overlord";"Larva";115;0
"Unit";"Overlord";"Larva";115;0
"Unit";"Mutalisk";"Larva";139;2
"Unit";"Mutalisk";"Larva";139;2
"Unit";"Mutalisk";"Larva";139;2
"Unit";"Mutalisk";"Larva";139;2
"Unit";"Mutalisk";"Larva";139;2
"Unit";"Mutalisk";"Larva";139;2
"Unit";"Mutalisk";"Larva";149;2
"Unit";"Mutalisk";"Larva";149;2
"Building";"SporeCrawler";NA;151;0
"Unit";"Mutalisk";"Larva";151;2
"Unit";"Mutalisk";"Larva";153;2
"Unit";"Mutalisk";"Larva";161;2
"Building";"SporeCrawler";NA;161;0
"Unit";"Mutalisk";"Larva";167;2
"Unit";"Mutalisk";"Larva";170;2
"Unit";"Mutalisk";"Larva";171;2
"Unit";"Mutalisk";"Larva";173;2
"Unit";"Mutalisk";"Larva";173;2
"Unit";"Overlord";"Larva";181;0
"Unit";"Zergling";"Larva";181;1
"Unit";"Zergling";"Larva";181;1
"Unit";"Zergling";"Larva";181;1
"Unit";"Zergling";"Larva";181;1
"Unit";"Zergling";"Larva";188;1
"Unit";"Zergling";"Larva";188;1
"Unit";"Zergling";"Larva";188;1
"Unit";"Zergling";"Larva";188;1
"Unit";"Zergling";"Larva";188;1
"Unit";"Zergling";"Larva";188;1
"Unit";"Zergling";"Larva";188;1
"Unit";"Zergling";"Larva";188;1
"Unit";"Zergling";"Larva";188;1
"Unit";"Zergling";"Larva";188;1
"Unit";"Zergling";"Larva";190;1
"Unit";"Zergling";"Larva";190;1
"Unit";"Queen";"Hatchery";188;2
"Unit";"Overlord";"Larva";206;0
"Unit";"Overlord";"Larva";206;0
"Unit";"Overlord";"Larva";206;0
"Unit";"Overlord";"Larva";206;0
"Unit";"Overlord";"Larva";206;0
"Unit";"Overlord";"Larva";206;0
"Building";"SporeCrawler";NA;206;0
"Building";"SporeCrawler";NA;208;0
"Unit";"Mutalisk";"Larva";208;2
"Unit";"Mutalisk";"Larva";208;2
"Unit";"Mutalisk";"Larva";208;2
"Unit";"Mutalisk";"Larva";208;2
"Unit";"Mutalisk";"Larva";208;2
"Unit";"Mutalisk";"Larva";208;2
"Unit";"Mutalisk";"Larva";208;2
"Unit";"Mutalisk";"Larva";208;2
"Unit";"Zergling";"Larva";214;1
"Unit";"Zergling";"Larva";214;1
"Unit";"Zergling";"Larva";214;1
"Unit";"Zergling";"Larva";214;1
"Unit";"Mutalisk";"Larva";214;2
"Unit";"Mutalisk";"Larva";214;2
"Unit";"Mutalisk";"Larva";214;2
"Unit";"Mutalisk";"Larva";214;2
"Unit";"Mutalisk";"Larva";214;2
"Unit";"Mutalisk";"Larva";214;2
"Unit";"Mutalisk";"Larva";214;2
"Unit";"Mutalisk";"Larva";224;2
"Unit";"Overlord";"Larva";226;0
"Building";"SporeCrawler";NA;238;0
"Unit";"Mutalisk";"Larva";240;2
"Unit";"Mutalisk";"Larva";240;2
"Unit";"Mutalisk";"Larva";247;2
"Unit";"Zergling";"Larva";247;1
"Unit";"Zergling";"Larva";247;1
"Unit";"Mutalisk";"Larva";247;2
"Unit";"Mutalisk";"Larva";251;2
"Unit";"Mutalisk";"Larva";251;2
"Building";"CreepTumor";NA;255;0
"Unit";"Zergling";"Larva";257;1
"Unit";"Zergling";"Larva";257;1
"Unit";"Zergling";"Larva";257;1
"Unit";"Zergling";"Larva";257;1
"Unit";"Zergling";"Larva";257;1
"Unit";"Zergling";"Larva";257;1
"Unit";"Zergling";"Larva";257;1
"Unit";"Zergling";"Larva";257;1
"Unit";"Zergling";"Larva";257;1
"Unit";"Zergling";"Larva";257;1
"Unit";"Zergling";"Larva";257;1
"Unit";"Zergling";"Larva";257;1
"Unit";"Mutalisk";"Larva";257;2
"Unit";"Mutalisk";"Larva";257;2
"Unit";"Overlord";"Larva";257;0
"Unit";"Baneling";"Zergling";264;0
"Unit";"Baneling";"Zergling";264;0
"Unit";"Baneling";"Zergling";266;0
"Unit";"Zergling";"Larva";270;1
"Unit";"Zergling";"Larva";270;1
"Unit";"Zergling";"Larva";272;1
"Unit";"Zergling";"Larva";272;1
"Unit";"Zergling";"Larva";282;1
"Unit";"Zergling";"Larva";282;1
"Unit";"Mutalisk";"Larva";282;2
"Unit";"Mutalisk";"Larva";282;2
"Unit";"Mutalisk";"Larva";286;2
"Unit";"Mutalisk";"Larva";286;2
"Unit";"Zergling";"Larva";292;1
"Unit";"Zergling";"Larva";292;1
"Building";"Hatchery";NA;261;0
"Unit";"Mutalisk";"Larva";292;2
"Unit";"Mutalisk";"Larva";292;2
"Unit";"Mutalisk";"Larva";298;2
"Unit";"Mutalisk";"Larva";298;2
"Unit";"Overlord";"Larva";306;0
"Unit";"Overlord";"Larva";306;0
"Unit";"Baneling";"Zergling";306;0
"Unit";"Baneling";"Zergling";306;0
"Unit";"Baneling";"Zergling";306;0
"Building";"SporeCrawler";NA;306;0
"Building";"Extractor";NA;306;0
"Building";"SporeCrawler";NA;306;0
"Building";"Extractor";NA;307;0
"Unit";"Mutalisk";"Larva";306;2
"Unit";"Mutalisk";"Larva";306;2
"Unit";"Queen";"Hatchery";302;2
"Building";"SpineCrawler";NA;306;0
"Unit";"Mutalisk";"Larva";325;2
"Unit";"Mutalisk";"Larva";325;2
"Unit";"Zergling";"Larva";325;1
"Unit";"Zergling";"Larva";325;1
"Unit";"Zergling";"Larva";325;1
"Unit";"Zergling";"Larva";325;1
"Unit";"Zergling";"Larva";325;1
"Unit";"Zergling";"Larva";325;1
"Building";"InfestationPit";NA;321;0
"Unit";"Mutalisk";"Larva";325;2
"Unit";"Mutalisk";"Larva";325;2
"Building";"SporeCrawler";NA;329;0
"Unit";"Queen";"Hatchery";329;2
