"type";"unit_name";"on_building";"total_supply";"supply"
"Unit";"Overlord";"Larva";12;0
"Building";"SpawningPool";NA;16;0
"Building";"Extractor";NA;20;0
"Unit";"Queen";"Hatchery";21;2
"Unit";"Overlord";"Larva";23;0
"Building";"Hatchery";NA;18;0
"Building";"RoachWarren";NA;21;0
"Unit";"Roach";"Larva";26;2
"Unit";"Roach";"Larva";26;2
"Unit";"Roach";"Larva";26;2
"Unit";"Roach";"Larva";26;2
"Unit";"Queen";"Hatchery";26;2
"Unit";"Overlord";"Larva";27;0
"Unit";"Overlord";"Larva";40;0
"Building";"EvolutionChamber";NA;40;0
"Building";"Extractor";NA;47;0
"Building";"Extractor";NA;47;0
"Unit";"Overlord";"Larva";53;0
"Unit";"Overlord";"Larva";53;0
"Unit";"Roach";"Larva";53;2
"Unit";"Roach";"Larva";53;2
"Unit";"Roach";"Larva";53;2
"Unit";"Roach";"Larva";53;2
"Unit";"Roach";"Larva";53;2
"Unit";"Overlord";"Larva";53;0
"Unit";"Zergling";"Larva";53;1
"Unit";"Zergling";"Larva";53;1
"Unit";"Zergling";"Larva";53;1
"Unit";"Zergling";"Larva";53;1
"Unit";"Zergling";"Larva";53;1
"Unit";"Zergling";"Larva";53;1
"Unit";"Zergling";"Larva";53;1
"Unit";"Zergling";"Larva";53;1
"Unit";"Zergling";"Larva";53;1
"Unit";"Zergling";"Larva";53;1
"Unit";"Zergling";"Larva";53;1
"Unit";"Zergling";"Larva";53;1
"Unit";"Roach";"Larva";53;2
"Building";"Extractor";NA;53;0
"Unit";"Roach";"Larva";61;2
"Unit";"Roach";"Larva";63;2
"Unit";"Roach";"Larva";77;2
"Unit";"Roach";"Larva";77;2
"Upgrade";"ZergMissileWeaponsLevel1";"EvolutionChamber";53;0
"Unit";"Roach";"Larva";79;2
"Unit";"Roach";"Larva";79;2
"Unit";"Roach";"Larva";81;2
"Unit";"Zergling";"Larva";81;1
"Unit";"Zergling";"Larva";81;1
"Unit";"Roach";"Larva";81;2
"Unit";"Roach";"Larva";95;2
"Unit";"Roach";"Larva";95;2
"Unit";"Roach";"Larva";95;2
"Unit";"Roach";"Larva";95;2
"Unit";"Roach";"Larva";95;2
"Unit";"Roach";"Larva";95;2
"Unit";"Overlord";"Larva";95;0
"Unit";"Overlord";"Larva";95;0
"Unit";"Overlord";"Larva";97;0
"Unit";"Overlord";"Larva";107;0
"Unit";"Overlord";"Larva";107;0
"Building";"EvolutionChamber";NA;107;0
"Building";"EvolutionChamber";NA;107;0
"Upgrade";"GlialReconstitution";"RoachWarren";107;0
"Building";"HydraliskDen";NA;118;0
"Building";"Hatchery";NA;107;0
"Unit";"Queen";"Hatchery";118;2
"Unit";"Hydralisk";"Larva";126;2
"Unit";"Hydralisk";"Larva";126;2
"Unit";"Hydralisk";"Larva";126;2
"Unit";"Hydralisk";"Larva";126;2
"Unit";"Hydralisk";"Larva";126;2
"Unit";"Hydralisk";"Larva";126;2
"Unit";"Hydralisk";"Larva";126;2
"Unit";"Hydralisk";"Larva";128;2
"Upgrade";"EvolveGroovedSpines";"HydraliskDen";128;0
"Unit";"Hydralisk";"Larva";144;2
"Unit";"Hydralisk";"Larva";144;2
"Unit";"Hydralisk";"Larva";144;2
"Unit";"Hydralisk";"Larva";144;2
"Unit";"Hydralisk";"Larva";144;2
"Unit";"Hydralisk";"Larva";144;2
"Unit";"Hydralisk";"Larva";144;2
"Upgrade";"ZergGroundArmorsLevel1";"EvolutionChamber";126;0
"Unit";"Overlord";"Larva";144;0
"Unit";"Overlord";"Larva";144;0
"Unit";"Overlord";"Larva";144;0
"Unit";"Overlord";"Larva";144;0
"Unit";"Overlord";"Larva";158;0
"Unit";"Overlord";"Larva";158;0
"Upgrade";"ZergMissileWeaponsLevel2";"EvolutionChamber";126;0
"Unit";"Roach";"Larva";158;2
"Unit";"Roach";"Larva";158;2
"Unit";"Roach";"Larva";158;2
"Unit";"Roach";"Larva";158;2
"Unit";"Roach";"Larva";158;2
"Unit";"Roach";"Larva";158;2
"Unit";"Roach";"Larva";158;2
"Unit";"Roach";"Larva";158;2
"Unit";"Roach";"Larva";158;2
"Unit";"Roach";"Larva";158;2
"Unit";"Roach";"Larva";158;2
"Unit";"Roach";"Larva";158;2
"Unit";"Roach";"Larva";158;2
"Unit";"Roach";"Larva";158;2
"Unit";"Roach";"Larva";158;2
"Unit";"Roach";"Larva";158;2
"Unit";"Roach";"Larva";158;2
"Unit";"Roach";"Larva";158;2
"Unit";"Roach";"Larva";158;2
"Unit";"Roach";"Larva";184;2
"Unit";"Roach";"Larva";184;2
"Unit";"Roach";"Larva";184;2
"Unit";"Roach";"Larva";184;2
"Upgrade";"EvolveMuscularAugments";"HydraliskDen";158;0
"Unit";"Roach";"Larva";204;2
"Unit";"Roach";"Larva";204;2
"Unit";"Roach";"Larva";204;2
"Unit";"Roach";"Larva";204;2
"Unit";"Roach";"Larva";204;2
"Unit";"Roach";"Larva";204;2
"Unit";"Roach";"Larva";204;2
"Unit";"Roach";"Larva";204;2
"Unit";"Roach";"Larva";204;2
"Unit";"Roach";"Larva";204;2
"Unit";"Roach";"Larva";204;2
"Unit";"Overlord";"Larva";204;0
"Unit";"Overlord";"Larva";204;0
"Unit";"Overlord";"Larva";204;0
"Unit";"Queen";"Hatchery";226;2
"Building";"Hatchery";NA;226;0
"Building";"Extractor";NA;245;0
"Building";"Extractor";NA;245;0
"Building";"InfestationPit";NA;245;0
"Unit";"Hydralisk";"Larva";245;2
"Unit";"Hydralisk";"Larva";245;2
"Unit";"Hydralisk";"Larva";245;2
"Unit";"Hydralisk";"Larva";245;2
"Unit";"Hydralisk";"Larva";245;2
"Unit";"Hydralisk";"Larva";245;2
"Unit";"Hydralisk";"Larva";245;2
"Unit";"Hydralisk";"Larva";245;2
