"type";"unit_name";"on_building";"total_supply";"supply"
"Unit";"Overlord";"Larva";13;0
"Building";"Extractor";NA;18;0
"Unit";"Overlord";"Larva";21;0
"Building";"SpawningPool";NA;19;0
"Building";"Hatchery";NA;17;0
"Unit";"Zergling";"Larva";22;1
"Unit";"Zergling";"Larva";22;1
"Unit";"Zergling";"Larva";22;1
"Unit";"Zergling";"Larva";22;1
"Unit";"Queen";"Hatchery";22;2
"Unit";"Queen";"Hatchery";22;2
"Unit";"Zergling";"Larva";38;1
"Unit";"Zergling";"Larva";38;1
"Unit";"Zergling";"Larva";38;1
"Unit";"Zergling";"Larva";38;1
"Unit";"Zergling";"Larva";38;1
"Unit";"Zergling";"Larva";38;1
"Unit";"Overlord";"Larva";38;0
"Unit";"Zergling";"Larva";42;1
"Unit";"Zergling";"Larva";42;1
"Unit";"Zergling";"Larva";42;1
"Unit";"Zergling";"Larva";42;1
"Unit";"Zergling";"Larva";42;1
"Unit";"Zergling";"Larva";42;1
"Building";"BanelingNest";NA;38;0
"Unit";"Baneling";"Zergling";56;0
"Building";"Hatchery";NA;35;0
"Unit";"Overlord";"Larva";56;0
"Unit";"Overlord";"Larva";56;0
"Building";"EvolutionChamber";NA;58;0
"Building";"Extractor";NA;58;0
"Unit";"Baneling";"Zergling";65;0
"Unit";"Baneling";"Zergling";65;0
"Unit";"Baneling";"Zergling";65;0
"Unit";"Baneling";"Zergling";65;0
"Unit";"Queen";"Hatchery";58;2
"Building";"Extractor";NA;65;0
"Unit";"Zergling";"Larva";68;1
"Unit";"Zergling";"Larva";68;1
"Unit";"Zergling";"Larva";68;1
"Unit";"Zergling";"Larva";68;1
"Unit";"Zergling";"Larva";70;1
"Unit";"Zergling";"Larva";70;1
"Unit";"Zergling";"Larva";70;1
"Unit";"Zergling";"Larva";70;1
"Unit";"Zergling";"Larva";70;1
"Unit";"Zergling";"Larva";70;1
"Unit";"Zergling";"Larva";70;1
"Unit";"Zergling";"Larva";70;1
"Building";"RoachWarren";NA;65;0
"Unit";"Baneling";"Zergling";93;0
"Unit";"Zergling";"Larva";84;1
"Unit";"Zergling";"Larva";84;1
"Unit";"Zergling";"Larva";84;1
"Unit";"Zergling";"Larva";84;1
"Unit";"Zergling";"Larva";84;1
"Unit";"Zergling";"Larva";84;1
"Unit";"Zergling";"Larva";84;1
"Unit";"Zergling";"Larva";84;1
"Unit";"Zergling";"Larva";85;1
"Unit";"Zergling";"Larva";85;1
"Unit";"Overlord";"Larva";93;0
"Unit";"Overlord";"Larva";103;0
"Unit";"Overlord";"Larva";103;0
"Unit";"Overlord";"Larva";107;0
"Unit";"Queen";"Hatchery";93;2
"Unit";"Roach";"Larva";107;2
"Unit";"Roach";"Larva";107;2
"Unit";"Roach";"Larva";107;2
"Unit";"Roach";"Larva";107;2
"Unit";"Roach";"Larva";107;2
"Building";"Extractor";NA;107;0
"Unit";"Roach";"Larva";109;2
"Unit";"Roach";"Larva";109;2
"Unit";"Roach";"Larva";109;2
"Building";"CreepTumorQueen";NA;117;0
"Upgrade";"ZergMissileWeaponsLevel1";"EvolutionChamber";84;0
"Unit";"Baneling";"Zergling";117;0
"Unit";"Baneling";"Zergling";117;0
"Unit";"Overlord";"Larva";117;0
"Unit";"Roach";"Larva";117;2
"Unit";"Roach";"Larva";117;2
"Unit";"Roach";"Larva";117;2
"Unit";"Roach";"Larva";117;2
"Unit";"Roach";"Larva";127;2
"Unit";"Roach";"Larva";133;2
"Unit";"Roach";"Larva";133;2
"Unit";"Overlord";"Larva";133;0
"Unit";"Overlord";"Larva";133;0
"Unit";"Overlord";"Larva";133;0
"Unit";"Overlord";"Larva";141;0
"Unit";"Overlord";"Larva";147;0
"Building";"CreepTumor";NA;147;0
"Upgrade";"GlialReconstitution";"RoachWarren";117;0
"Building";"Extractor";NA;147;0
"Unit";"Roach";"Larva";155;2
"Unit";"Roach";"Larva";155;2
"Building";"CreepTumor";NA;156;0
"Unit";"Roach";"Larva";155;2
"Unit";"Roach";"Larva";156;2
"Unit";"Roach";"Larva";156;2
"Unit";"Roach";"Larva";160;2
"Unit";"Roach";"Larva";160;2
"Unit";"Roach";"Larva";160;2
"Unit";"Roach";"Larva";160;2
"Unit";"Roach";"Larva";160;2
"Unit";"Roach";"Larva";160;2
"Building";"CreepTumorQueen";NA;166;0
"Unit";"Roach";"Larva";162;2
"Unit";"Roach";"Larva";162;2
"Unit";"Roach";"Larva";162;2
"Unit";"Overlord";"Larva";166;0
"Unit";"Roach";"Larva";166;2
"Unit";"Roach";"Larva";166;2
"Unit";"Roach";"Larva";166;2
"Unit";"Roach";"Larva";166;2
"Unit";"Roach";"Larva";166;2
"Unit";"Overlord";"Larva";178;0
"Unit";"Overlord";"Larva";178;0
"Unit";"Overlord";"Larva";180;0
"Building";"CreepTumor";NA;186;0
"Unit";"Overlord";"Larva";194;0
"Unit";"Overlord";"Larva";194;0
"Unit";"Roach";"Larva";194;2
"Unit";"Roach";"Larva";194;2
"Unit";"Roach";"Larva";194;2
"Unit";"Roach";"Larva";194;2
"Unit";"Roach";"Larva";194;2
"Building";"Hatchery";NA;155;0
"Unit";"Roach";"Larva";194;2
"Unit";"Roach";"Larva";194;2
"Unit";"Roach";"Larva";194;2
"Unit";"Roach";"Larva";194;2
"Unit";"Roach";"Larva";194;2
"Unit";"Roach";"Larva";194;2
"Unit";"Roach";"Larva";194;2
"Unit";"Roach";"Larva";204;2
"Unit";"Roach";"Larva";204;2
"Unit";"Roach";"Larva";204;2
"Unit";"Roach";"Larva";204;2
"Unit";"Roach";"Larva";204;2
"Unit";"Roach";"Larva";204;2
"Building";"HydraliskDen";NA;204;0
"Unit";"Roach";"Larva";218;2
"Unit";"Roach";"Larva";218;2
"Unit";"Roach";"Larva";218;2
"Unit";"Roach";"Larva";218;2
"Unit";"Roach";"Larva";218;2
"Unit";"Roach";"Larva";218;2
"Unit";"Roach";"Larva";218;2
"Unit";"Roach";"Larva";218;2
"Unit";"Roach";"Larva";218;2
"Unit";"Roach";"Larva";218;2
"Upgrade";"ZergMissileWeaponsLevel2";"EvolutionChamber";160;0
"Unit";"Roach";"Larva";230;2
"Unit";"Roach";"Larva";230;2
"Unit";"Roach";"Larva";230;2
"Unit";"Hydralisk";"Larva";250;2
"Unit";"Hydralisk";"Larva";250;2
"Unit";"Hydralisk";"Larva";250;2
"Unit";"Hydralisk";"Larva";250;2
"Unit";"Hydralisk";"Larva";250;2
"Unit";"Hydralisk";"Larva";250;2
"Building";"CreepTumorQueen";NA;256;0
"Unit";"Hydralisk";"Larva";256;2
"Unit";"Hydralisk";"Larva";256;2
"Building";"CreepTumor";NA;256;0
"Building";"CreepTumor";NA;272;0
"Unit";"Hydralisk";"Larva";268;2
"Unit";"Hydralisk";"Larva";268;2
"Unit";"Hydralisk";"Larva";268;2
"Unit";"Hydralisk";"Larva";268;2
"Unit";"Hydralisk";"Larva";268;2
"Unit";"Hydralisk";"Larva";268;2
"Building";"CreepTumorQueen";NA;272;0
"Unit";"Hydralisk";"Larva";272;2
"Unit";"Hydralisk";"Larva";282;2
"Unit";"Hydralisk";"Larva";282;2
"Unit";"Hydralisk";"Larva";282;2
"Building";"CreepTumor";NA;286;0
"Building";"SporeCrawler";NA;286;0
"Upgrade";"EvolveMuscularAugments";"HydraliskDen";284;0
"Unit";"Roach";"Larva";292;2
"Unit";"Roach";"Larva";292;2
"Unit";"Roach";"Larva";292;2
"Unit";"Roach";"Larva";292;2
"Unit";"Roach";"Larva";292;2
"Unit";"Roach";"Larva";292;2
"Unit";"Roach";"Larva";292;2
"Unit";"Roach";"Larva";292;2
"Unit";"Roach";"Larva";292;2
"Unit";"Roach";"Larva";292;2
"Unit";"Roach";"Larva";292;2
"Unit";"Roach";"Larva";292;2
"Building";"CreepTumor";NA;310;0
"Building";"SporeCrawler";NA;310;0
"Unit";"Hydralisk";"Larva";310;2
"Unit";"Hydralisk";"Larva";310;2
"Unit";"Hydralisk";"Larva";310;2
"Unit";"Roach";"Larva";316;2
"Unit";"Hydralisk";"Larva";316;2
"Unit";"Roach";"Larva";324;2
"Unit";"Roach";"Larva";324;2
"Unit";"Roach";"Larva";330;2
"Unit";"Overlord";"Larva";330;0
"Unit";"Overlord";"Larva";330;0
"Unit";"Overlord";"Larva";330;0
"Unit";"Overlord";"Larva";330;0
"Unit";"Roach";"Larva";332;2
"Unit";"Roach";"Larva";332;2
"Unit";"Roach";"Larva";332;2
"Unit";"Roach";"Larva";332;2
"Unit";"Roach";"Larva";332;2
"Unit";"Roach";"Larva";332;2
"Unit";"Roach";"Larva";332;2
"Unit";"Roach";"Larva";332;2
"Unit";"Roach";"Larva";332;2
"Building";"CreepTumor";NA;334;0
"Unit";"Roach";"Larva";332;2
"Unit";"Roach";"Larva";332;2
"Unit";"Roach";"Larva";332;2
"Unit";"Roach";"Larva";332;2
"Unit";"Roach";"Larva";350;2
"Unit";"Roach";"Larva";350;2
"Unit";"Roach";"Larva";350;2
"Unit";"Roach";"Larva";358;2
"Unit";"Roach";"Larva";358;2
"Unit";"Roach";"Larva";360;2
"Unit";"Roach";"Larva";360;2
"Unit";"Roach";"Larva";364;2
