"type";"unit_name";"on_building";"total_supply";"supply"
"Unit";"Overlord";"Larva";13;0
"Building";"Extractor";NA;18;0
"Building";"Hatchery";NA;16;0
"Unit";"Overlord";"Larva";22;0
"Building";"SpawningPool";NA;19;0
"Unit";"Queen";"Hatchery";22;2
"Unit";"Queen";"Hatchery";22;2
"Unit";"Zergling";"Larva";27;1
"Unit";"Zergling";"Larva";27;1
"Unit";"Zergling";"Larva";27;1
"Unit";"Zergling";"Larva";27;1
"Unit";"Zergling";"Larva";27;1
"Unit";"Zergling";"Larva";27;1
"Unit";"Zergling";"Larva";32;1
"Unit";"Zergling";"Larva";32;1
"Unit";"Zergling";"Larva";32;1
"Unit";"Zergling";"Larva";32;1
"Building";"EvolutionChamber";NA;32;0
"Building";"BanelingNest";NA;27;0
"Unit";"Zergling";"Larva";42;1
"Unit";"Zergling";"Larva";42;1
"Unit";"Baneling";"Zergling";47;0
"Unit";"Overlord";"Larva";48;0
"Unit";"Overlord";"Larva";48;0
"Unit";"Overlord";"Larva";48;0
"Unit";"Zergling";"Larva";48;1
"Unit";"Zergling";"Larva";48;1
"Unit";"Overlord";"Larva";48;0
"Unit";"Overlord";"Larva";48;0
"Unit";"Zergling";"Larva";48;1
"Unit";"Zergling";"Larva";48;1
"Unit";"Zergling";"Larva";48;1
"Unit";"Zergling";"Larva";48;1
"Unit";"Zergling";"Larva";48;1
"Unit";"Zergling";"Larva";48;1
"Unit";"Zergling";"Larva";48;1
"Unit";"Zergling";"Larva";48;1
"Unit";"Zergling";"Larva";48;1
"Unit";"Zergling";"Larva";48;1
"Unit";"Zergling";"Larva";48;1
"Unit";"Zergling";"Larva";48;1
"Building";"Hatchery";NA;42;0
"Unit";"Zergling";"Larva";48;1
"Unit";"Zergling";"Larva";48;1
"Unit";"Zergling";"Larva";48;1
"Unit";"Zergling";"Larva";48;1
"Unit";"Baneling";"Zergling";48;0
"Unit";"Baneling";"Zergling";48;0
"Unit";"Baneling";"Zergling";62;0
"Unit";"Baneling";"Zergling";62;0
"Unit";"Zergling";"Larva";66;1
"Unit";"Zergling";"Larva";66;1
"Unit";"Zergling";"Larva";66;1
"Unit";"Zergling";"Larva";66;1
"Unit";"Zergling";"Larva";66;1
"Unit";"Zergling";"Larva";66;1
"Unit";"Baneling";"Zergling";72;0
"Unit";"Baneling";"Zergling";72;0
"Upgrade";"ZergMeleeWeaponsLevel1";"EvolutionChamber";48;0
"Unit";"Queen";"Hatchery";72;2
"Unit";"Zergling";"Larva";80;1
"Unit";"Zergling";"Larva";80;1
"Unit";"Zergling";"Larva";80;1
"Unit";"Zergling";"Larva";80;1
"Unit";"Zergling";"Larva";80;1
"Unit";"Zergling";"Larva";80;1
"Unit";"Zergling";"Larva";86;1
"Unit";"Zergling";"Larva";86;1
"Unit";"Zergling";"Larva";86;1
"Unit";"Zergling";"Larva";86;1
"Unit";"Zergling";"Larva";86;1
"Unit";"Zergling";"Larva";86;1
"Unit";"Zergling";"Larva";86;1
"Unit";"Zergling";"Larva";86;1
"Unit";"Zergling";"Larva";86;1
"Unit";"Zergling";"Larva";86;1
"Unit";"Zergling";"Larva";86;1
"Unit";"Zergling";"Larva";86;1
"Unit";"Zergling";"Larva";86;1
"Unit";"Zergling";"Larva";86;1
"Unit";"Zergling";"Larva";94;1
"Unit";"Zergling";"Larva";94;1
"Unit";"Baneling";"Zergling";94;0
"Unit";"Zergling";"Larva";94;1
"Unit";"Zergling";"Larva";94;1
"Unit";"Zergling";"Larva";94;1
"Unit";"Zergling";"Larva";94;1
"Unit";"Zergling";"Larva";94;1
"Unit";"Zergling";"Larva";94;1
"Building";"CreepTumorQueen";NA;108;0
"Unit";"Baneling";"Zergling";108;0
"Unit";"Baneling";"Zergling";108;0
"Unit";"Baneling";"Zergling";108;0
"Unit";"Zergling";"Larva";108;1
"Unit";"Zergling";"Larva";108;1
"Building";"Extractor";NA;108;0
"Building";"Extractor";NA;108;0
"Unit";"Zergling";"Larva";116;1
"Unit";"Zergling";"Larva";116;1
"Unit";"Zergling";"Larva";116;1
"Unit";"Zergling";"Larva";116;1
"Unit";"Zergling";"Larva";116;1
"Unit";"Zergling";"Larva";116;1
"Unit";"Baneling";"Zergling";119;0
"Unit";"Baneling";"Zergling";119;0
"Building";"Extractor";NA;108;0
"Unit";"Overlord";"Larva";119;0
"Unit";"Overlord";"Larva";119;0
"Unit";"Baneling";"Zergling";127;0
"Unit";"Baneling";"Zergling";127;0
"Unit";"Zergling";"Larva";127;1
"Unit";"Zergling";"Larva";127;1
"Unit";"Zergling";"Larva";127;1
"Unit";"Zergling";"Larva";127;1
"Unit";"Zergling";"Larva";127;1
"Unit";"Zergling";"Larva";127;1
"Unit";"Zergling";"Larva";127;1
"Unit";"Zergling";"Larva";127;1
"Unit";"Zergling";"Larva";127;1
"Unit";"Zergling";"Larva";127;1
"Unit";"Zergling";"Larva";127;1
"Unit";"Zergling";"Larva";127;1
"Unit";"Zergling";"Larva";127;1
"Unit";"Zergling";"Larva";127;1
"Unit";"Zergling";"Larva";127;1
"Unit";"Zergling";"Larva";127;1
"Unit";"Zergling";"Larva";127;1
"Unit";"Zergling";"Larva";127;1
"Unit";"Zergling";"Larva";127;1
"Unit";"Zergling";"Larva";127;1
"Unit";"Zergling";"Larva";127;1
"Unit";"Zergling";"Larva";127;1
"Unit";"Zergling";"Larva";127;1
"Unit";"Zergling";"Larva";127;1
"Unit";"Zergling";"Larva";127;1
"Unit";"Zergling";"Larva";127;1
"Unit";"Zergling";"Larva";153;1
"Unit";"Zergling";"Larva";153;1
"Unit";"Zergling";"Larva";153;1
"Unit";"Zergling";"Larva";153;1
"Unit";"Zergling";"Larva";153;1
"Unit";"Zergling";"Larva";153;1
"Unit";"Zergling";"Larva";153;1
"Unit";"Zergling";"Larva";153;1
"Unit";"Zergling";"Larva";153;1
"Unit";"Zergling";"Larva";153;1
"Unit";"Zergling";"Larva";153;1
"Unit";"Zergling";"Larva";153;1
"Unit";"Zergling";"Larva";153;1
"Unit";"Zergling";"Larva";153;1
"Unit";"Baneling";"Zergling";153;0
"Unit";"Baneling";"Zergling";153;0
"Unit";"Baneling";"Zergling";153;0
"Unit";"Baneling";"Zergling";153;0
"Unit";"Baneling";"Zergling";153;0
"Unit";"Baneling";"Zergling";153;0
"Building";"Hatchery";NA;121;0
"Unit";"Zergling";"Larva";153;1
"Unit";"Zergling";"Larva";153;1
"Unit";"Zergling";"Larva";153;1
"Unit";"Zergling";"Larva";153;1
"Unit";"Zergling";"Larva";153;1
"Unit";"Zergling";"Larva";153;1
"Unit";"Zergling";"Larva";153;1
"Unit";"Zergling";"Larva";153;1
"Unit";"Zergling";"Larva";153;1
"Unit";"Zergling";"Larva";153;1
"Unit";"Zergling";"Larva";153;1
"Unit";"Zergling";"Larva";153;1
"Unit";"Zergling";"Larva";167;1
"Unit";"Zergling";"Larva";167;1
"Unit";"Zergling";"Larva";167;1
"Unit";"Zergling";"Larva";167;1
"Unit";"Zergling";"Larva";167;1
"Unit";"Zergling";"Larva";167;1
"Unit";"Zergling";"Larva";167;1
"Unit";"Zergling";"Larva";167;1
"Unit";"Zergling";"Larva";167;1
"Unit";"Zergling";"Larva";167;1
"Unit";"Zergling";"Larva";179;1
"Unit";"Zergling";"Larva";179;1
"Unit";"Zergling";"Larva";179;1
"Unit";"Zergling";"Larva";179;1
"Unit";"Zergling";"Larva";179;1
"Unit";"Zergling";"Larva";179;1
"Unit";"Zergling";"Larva";179;1
"Unit";"Zergling";"Larva";179;1
"Unit";"Zergling";"Larva";179;1
"Unit";"Zergling";"Larva";179;1
"Unit";"Zergling";"Larva";179;1
"Unit";"Zergling";"Larva";179;1
"Unit";"Zergling";"Larva";179;1
"Unit";"Zergling";"Larva";179;1
"Unit";"Zergling";"Larva";179;1
"Unit";"Zergling";"Larva";179;1
"Building";"CreepTumorQueen";NA;179;0
"Unit";"Baneling";"Zergling";179;0
"Unit";"Baneling";"Zergling";179;0
"Unit";"Baneling";"Zergling";179;0
"Unit";"Baneling";"Zergling";179;0
"Unit";"Baneling";"Zergling";179;0
"Unit";"Baneling";"Zergling";179;0
"Unit";"Baneling";"Zergling";179;0
"Unit";"Baneling";"Zergling";179;0
"Unit";"Baneling";"Zergling";179;0
"Unit";"Baneling";"Zergling";179;0
"Unit";"Baneling";"Zergling";179;0
"Unit";"Baneling";"Zergling";179;0
"Unit";"Zergling";"Larva";179;1
"Unit";"Zergling";"Larva";179;1
"Unit";"Zergling";"Larva";179;1
"Unit";"Zergling";"Larva";179;1
"Building";"CreepTumorQueen";NA;189;0
"Building";"CreepTumor";NA;201;0
"Unit";"Zergling";"Larva";189;1
"Unit";"Zergling";"Larva";189;1
"Unit";"Zergling";"Larva";205;1
"Unit";"Zergling";"Larva";205;1
"Unit";"Zergling";"Larva";205;1
"Unit";"Zergling";"Larva";205;1
"Building";"RoachWarren";NA;179;0
"Unit";"Zergling";"Larva";209;1
"Unit";"Zergling";"Larva";209;1
"Unit";"Zergling";"Larva";211;1
"Unit";"Zergling";"Larva";211;1
"Unit";"Zergling";"Larva";211;1
"Unit";"Zergling";"Larva";211;1
"Unit";"Zergling";"Larva";211;1
"Unit";"Zergling";"Larva";211;1
"Unit";"Zergling";"Larva";211;1
"Unit";"Zergling";"Larva";211;1
"Unit";"Zergling";"Larva";215;1
"Unit";"Zergling";"Larva";215;1
"Unit";"Zergling";"Larva";215;1
"Unit";"Zergling";"Larva";215;1
"Unit";"Zergling";"Larva";215;1
"Unit";"Zergling";"Larva";215;1
"Unit";"Zergling";"Larva";215;1
"Unit";"Zergling";"Larva";215;1
"Unit";"Zergling";"Larva";215;1
"Unit";"Zergling";"Larva";215;1
"Unit";"Zergling";"Larva";215;1
"Unit";"Zergling";"Larva";215;1
"Unit";"Zergling";"Larva";215;1
"Unit";"Zergling";"Larva";215;1
"Unit";"Zergling";"Larva";215;1
"Unit";"Zergling";"Larva";215;1
"Unit";"Zergling";"Larva";215;1
"Unit";"Zergling";"Larva";215;1
"Unit";"Zergling";"Larva";215;1
"Unit";"Zergling";"Larva";215;1
"Unit";"Zergling";"Larva";215;1
"Unit";"Zergling";"Larva";215;1
"Unit";"Zergling";"Larva";247;1
"Unit";"Zergling";"Larva";247;1
"Unit";"Zergling";"Larva";247;1
"Unit";"Zergling";"Larva";247;1
"Unit";"Zergling";"Larva";247;1
"Unit";"Zergling";"Larva";247;1
"Unit";"Zergling";"Larva";251;1
"Unit";"Zergling";"Larva";251;1
"Unit";"Zergling";"Larva";251;1
"Unit";"Zergling";"Larva";251;1
"Unit";"Zergling";"Larva";251;1
"Unit";"Zergling";"Larva";251;1
"Unit";"Zergling";"Larva";251;1
"Unit";"Zergling";"Larva";251;1
"Unit";"Zergling";"Larva";251;1
"Unit";"Zergling";"Larva";251;1
"Unit";"Zergling";"Larva";251;1
"Unit";"Zergling";"Larva";251;1
"Unit";"Zergling";"Larva";251;1
"Unit";"Zergling";"Larva";251;1
"Building";"CreepTumor";NA;251;0
"Unit";"Zergling";"Larva";257;1
"Unit";"Zergling";"Larva";257;1
"Unit";"Zergling";"Larva";257;1
"Unit";"Zergling";"Larva";257;1
"Unit";"Zergling";"Larva";257;1
"Unit";"Zergling";"Larva";257;1
"Unit";"Zergling";"Larva";257;1
"Unit";"Zergling";"Larva";257;1
"Unit";"Zergling";"Larva";273;1
"Unit";"Zergling";"Larva";273;1
"Unit";"Zergling";"Larva";273;1
"Unit";"Zergling";"Larva";273;1
"Unit";"Zergling";"Larva";273;1
"Unit";"Zergling";"Larva";273;1
"Unit";"Zergling";"Larva";281;1
"Unit";"Zergling";"Larva";281;1
"Unit";"Zergling";"Larva";281;1
"Unit";"Zergling";"Larva";281;1
"Unit";"Zergling";"Larva";281;1
"Unit";"Zergling";"Larva";281;1
"Unit";"Zergling";"Larva";281;1
"Unit";"Zergling";"Larva";281;1
"Unit";"Zergling";"Larva";281;1
"Unit";"Zergling";"Larva";281;1
"Unit";"Zergling";"Larva";283;1
"Unit";"Zergling";"Larva";283;1
"Unit";"Zergling";"Larva";283;1
"Unit";"Zergling";"Larva";283;1
"Unit";"Zergling";"Larva";283;1
"Unit";"Zergling";"Larva";283;1
"Unit";"Zergling";"Larva";301;1
"Unit";"Zergling";"Larva";301;1
"Unit";"Zergling";"Larva";301;1
"Unit";"Zergling";"Larva";301;1
"Unit";"Zergling";"Larva";301;1
"Unit";"Zergling";"Larva";301;1
"Unit";"Zergling";"Larva";301;1
"Unit";"Zergling";"Larva";301;1
"Unit";"Zergling";"Larva";301;1
"Unit";"Zergling";"Larva";301;1
"Unit";"Zergling";"Larva";301;1
"Unit";"Zergling";"Larva";301;1
"Unit";"Baneling";"Zergling";307;0
"Unit";"Overlord";"Larva";307;0
"Unit";"Baneling";"Zergling";307;0
"Unit";"Baneling";"Zergling";307;0
"Unit";"Baneling";"Zergling";307;0
"Unit";"Overlord";"Larva";307;0
"Unit";"Baneling";"Zergling";307;0
"Building";"CreepTumor";NA;319;0
"Unit";"Baneling";"Zergling";307;0
"Building";"CreepTumorQueen";NA;319;0
"Unit";"Baneling";"Zergling";307;0
"Unit";"Roach";"Larva";307;2
"Building";"CreepTumor";NA;319;0
"Building";"CreepTumor";NA;319;0
"Building";"CreepTumorQueen";NA;319;0
"Unit";"Baneling";"Zergling";319;0
"Unit";"Baneling";"Zergling";319;0
"Unit";"Baneling";"Zergling";319;0
"Unit";"Baneling";"Zergling";319;0
"Unit";"Baneling";"Zergling";319;0
"Unit";"Baneling";"Zergling";319;0
"Building";"CreepTumorQueen";NA;319;0
"Unit";"Baneling";"Zergling";319;0
"Unit";"Baneling";"Zergling";319;0
"Unit";"Zergling";"Larva";319;1
"Unit";"Zergling";"Larva";319;1
"Unit";"Zergling";"Larva";319;1
"Unit";"Zergling";"Larva";319;1
"Unit";"Roach";"Larva";319;2
"Unit";"Roach";"Larva";319;2
"Unit";"Zergling";"Larva";321;1
"Unit";"Zergling";"Larva";321;1
"Unit";"Zergling";"Larva";321;1
"Unit";"Zergling";"Larva";321;1
"Unit";"Zergling";"Larva";321;1
"Unit";"Zergling";"Larva";321;1
"Unit";"Zergling";"Larva";321;1
"Unit";"Zergling";"Larva";321;1
"Unit";"Zergling";"Larva";321;1
"Unit";"Zergling";"Larva";321;1
"Unit";"Zergling";"Larva";321;1
"Unit";"Zergling";"Larva";321;1
"Unit";"Zergling";"Larva";321;1
"Unit";"Zergling";"Larva";321;1
"Unit";"Zergling";"Larva";321;1
"Unit";"Zergling";"Larva";321;1
"Unit";"Roach";"Larva";323;2
"Unit";"Roach";"Larva";323;2
"Unit";"Roach";"Larva";329;2
"Unit";"Roach";"Larva";329;2
"Unit";"Roach";"Larva";329;2
"Unit";"Baneling";"Zergling";349;0
"Unit";"Baneling";"Zergling";349;0
"Unit";"Baneling";"Zergling";349;0
"Unit";"Baneling";"Zergling";349;0
"Unit";"Baneling";"Zergling";349;0
"Unit";"Baneling";"Zergling";349;0
"Unit";"Roach";"Larva";345;2
"Unit";"Roach";"Larva";345;2
"Unit";"Roach";"Larva";345;2
"Unit";"Roach";"Larva";355;2
"Unit";"Roach";"Larva";355;2
"Unit";"Roach";"Larva";355;2
"Unit";"Zergling";"Larva";361;1
"Unit";"Zergling";"Larva";361;1
"Unit";"Roach";"Larva";361;2
"Unit";"Roach";"Larva";361;2
"Unit";"Roach";"Larva";361;2
"Unit";"Roach";"Larva";361;2
"Building";"CreepTumor";NA;367;0
"Building";"CreepTumor";NA;367;0
"Unit";"Zergling";"Larva";367;1
"Unit";"Zergling";"Larva";367;1
"Unit";"Roach";"Larva";367;2
"Unit";"Roach";"Larva";367;2
"Unit";"Roach";"Larva";367;2
"Unit";"Roach";"Larva";367;2
"Upgrade";"ZergMissileWeaponsLevel1";"EvolutionChamber";321;0
"Upgrade";"GlialReconstitution";"RoachWarren";355;0
"Unit";"Zergling";"Larva";387;1
"Unit";"Zergling";"Larva";387;1
"Unit";"Zergling";"Larva";387;1
"Unit";"Zergling";"Larva";387;1
"Unit";"Zergling";"Larva";387;1
"Unit";"Zergling";"Larva";387;1
"Unit";"Zergling";"Larva";392;1
"Unit";"Zergling";"Larva";392;1
"Unit";"Roach";"Larva";392;2
"Unit";"Zergling";"Larva";392;1
"Unit";"Zergling";"Larva";392;1
"Unit";"Roach";"Larva";392;2
