"type";"unit_name";"on_building";"total_supply";"supply"
"Unit";"Overlord";"Larva";13;0
"Building";"Extractor";NA;18;0
"Unit";"Overlord";"Larva";21;0
"Building";"SpawningPool";NA;19;0
"Building";"Hatchery";NA;17;0
"Unit";"Zergling";"Larva";22;1
"Unit";"Zergling";"Larva";22;1
"Unit";"Zergling";"Larva";22;1
"Unit";"Zergling";"Larva";22;1
"Unit";"Zergling";"Larva";22;1
"Unit";"Zergling";"Larva";22;1
"Unit";"Queen";"Hatchery";22;2
"Unit";"Queen";"Hatchery";22;2
"Unit";"Overlord";"Larva";37;0
"Building";"BanelingNest";NA;36;0
"Unit";"Zergling";"Larva";41;1
"Unit";"Zergling";"Larva";41;1
"Unit";"Zergling";"Larva";41;1
"Unit";"Zergling";"Larva";41;1
"Unit";"Zergling";"Larva";41;1
"Unit";"Zergling";"Larva";41;1
"Unit";"Zergling";"Larva";41;1
"Unit";"Zergling";"Larva";41;1
"Unit";"Zergling";"Larva";41;1
"Unit";"Zergling";"Larva";41;1
"Unit";"Zergling";"Larva";42;1
"Unit";"Zergling";"Larva";42;1
"Unit";"Baneling";"Zergling";55;0
"Unit";"Baneling";"Zergling";55;0
"Building";"Hatchery";NA;34;0
"Unit";"Overlord";"Larva";57;0
"Unit";"Baneling";"Zergling";59;0
"Unit";"Baneling";"Zergling";59;0
"Unit";"Baneling";"Zergling";59;0
"Unit";"Baneling";"Zergling";59;0
"Unit";"Queen";"Hatchery";55;2
"Unit";"Baneling";"Zergling";59;0
"Unit";"Baneling";"Zergling";64;0
"Building";"Extractor";NA;63;0
"Unit";"Baneling";"Zergling";67;0
"Unit";"Overlord";"Larva";67;0
"Unit";"Overlord";"Larva";67;0
"Unit";"Zergling";"Larva";67;1
"Unit";"Zergling";"Larva";67;1
"Unit";"Zergling";"Larva";67;1
"Unit";"Zergling";"Larva";67;1
"Unit";"Zergling";"Larva";67;1
"Unit";"Zergling";"Larva";67;1
"Unit";"Zergling";"Larva";67;1
"Unit";"Zergling";"Larva";67;1
"Unit";"Zergling";"Larva";67;1
"Unit";"Zergling";"Larva";67;1
"Unit";"Zergling";"Larva";67;1
"Unit";"Zergling";"Larva";67;1
"Building";"CreepTumorQueen";NA;67;0
"Unit";"Zergling";"Larva";67;1
"Unit";"Zergling";"Larva";67;1
"Unit";"Zergling";"Larva";67;1
"Unit";"Zergling";"Larva";67;1
"Building";"RoachWarren";NA;64;0
"Unit";"Zergling";"Larva";67;1
"Unit";"Zergling";"Larva";67;1
"Unit";"Overlord";"Larva";67;0
"Unit";"Roach";"Larva";87;2
"Unit";"Roach";"Larva";87;2
"Unit";"Roach";"Larva";87;2
"Unit";"Roach";"Larva";87;2
"Unit";"Roach";"Larva";88;2
"Unit";"Roach";"Larva";88;2
"Unit";"Roach";"Larva";88;2
"Unit";"Roach";"Larva";88;2
"Unit";"Roach";"Larva";88;2
"Unit";"Roach";"Larva";88;2
"Unit";"Overlord";"Larva";88;0
"Unit";"Roach";"Larva";88;2
"Unit";"Roach";"Larva";104;2
"Unit";"Overlord";"Larva";108;0
"Unit";"Roach";"Larva";106;2
"Unit";"Roach";"Larva";106;2
"Unit";"Overlord";"Larva";110;0
"Building";"CreepTumor";NA;110;0
"Building";"Extractor";NA;110;0
"Unit";"Roach";"Larva";112;2
"Unit";"Baneling";"Zergling";119;0
"Unit";"Baneling";"Zergling";119;0
"Unit";"Baneling";"Zergling";119;0
"Unit";"Roach";"Larva";118;2
"Unit";"Overlord";"Larva";126;0
"Building";"EvolutionChamber";NA;126;0
"Unit";"Roach";"Larva";137;2
"Unit";"Roach";"Larva";137;2
"Unit";"Roach";"Larva";137;2
"Unit";"Overlord";"Larva";140;0
"Unit";"Overlord";"Larva";140;0
"Unit";"Overlord";"Larva";140;0
"Building";"Extractor";NA;140;0
"Unit";"Overlord";"Larva";140;0
"Unit";"Roach";"Larva";146;2
"Unit";"Roach";"Larva";146;2
"Unit";"Overlord";"Larva";146;0
"Building";"CreepTumor";NA;148;0
"Unit";"Overlord";"Larva";148;0
"Unit";"Overlord";"Larva";148;0
"Unit";"Overlord";"Larva";148;0
"Building";"Extractor";NA;148;0
"Unit";"Roach";"Larva";152;2
"Unit";"Roach";"Larva";159;2
"Unit";"Roach";"Larva";160;2
"Unit";"Roach";"Larva";160;2
"Unit";"Roach";"Larva";160;2
"Unit";"Roach";"Larva";160;2
"Building";"Extractor";NA;162;0
"Unit";"Roach";"Larva";162;2
"Unit";"Roach";"Larva";162;2
"Unit";"Roach";"Larva";162;2
"Unit";"Roach";"Larva";162;2
"Unit";"Roach";"Larva";162;2
"Unit";"Roach";"Larva";168;2
"Unit";"Roach";"Larva";168;2
"Building";"CreepTumor";NA;176;0
"Unit";"Roach";"Larva";176;2
"Unit";"Roach";"Larva";176;2
"Building";"HydraliskDen";NA;168;0
"Unit";"Overlord";"Larva";186;0
"Unit";"Overlord";"Larva";190;0
"Unit";"Roach";"Larva";191;2
"Unit";"Roach";"Larva";191;2
"Unit";"Roach";"Larva";191;2
"Unit";"Roach";"Larva";191;2
"Unit";"Roach";"Larva";191;2
"Unit";"Roach";"Larva";191;2
"Unit";"Roach";"Larva";191;2
"Unit";"Roach";"Larva";191;2
"Unit";"Roach";"Larva";191;2
"Unit";"Roach";"Larva";191;2
"Upgrade";"ZergMissileWeaponsLevel1";"EvolutionChamber";152;0
"Building";"CreepTumor";NA;207;0
"Unit";"Roach";"Larva";195;2
"Unit";"Roach";"Larva";211;2
"Unit";"Roach";"Larva";211;2
"Upgrade";"GlialReconstitution";"RoachWarren";186;0
"Unit";"Roach";"Larva";219;2
"Unit";"Overlord";"Larva";219;0
"Unit";"Overlord";"Larva";219;0
"Unit";"Roach";"Larva";219;2
"Unit";"Roach";"Larva";219;2
"Unit";"Roach";"Larva";229;2
"Unit";"Roach";"Larva";229;2
"Unit";"Roach";"Larva";229;2
"Unit";"Roach";"Larva";229;2
"Unit";"Roach";"Larva";229;2
"Unit";"Roach";"Larva";229;2
"Unit";"Roach";"Larva";229;2
"Unit";"Roach";"Larva";229;2
