"type";"unit_name";"on_building";"total_supply";"supply"
"Building";"Pylon";NA;13;0
"Building";"Assimilator";NA;16;0
"Building";"Assimilator";NA;17;0
"Building";"Pylon";NA;18;0
"Building";"Forge";NA;18;0
"Building";"Pylon";NA;20;0
"Building";"PhotonCannon";NA;23;0
"Building";"Pylon";NA;24;0
"Building";"PhotonCannon";NA;23;0
"Building";"PhotonCannon";NA;23;0
"Building";"Pylon";NA;25;0
"Building";"PhotonCannon";NA;28;0
"Building";"Gateway";NA;27;0
"Building";"Nexus";NA;26;0
"Building";"Pylon";NA;31;0
"Building";"CyberneticsCore";NA;32;0
"Unit";"Zealot";"Gateway";32;2
"Building";"Assimilator";NA;35;0
"Building";"Assimilator";NA;37;0
"Building";"Pylon";NA;42;0
"Building";"Pylon";NA;42;0
"Building";"Stargate";NA;41;0
"Building";"Stargate";NA;41;0
"Building";"ShieldBattery";NA;47;0
"Building";"PhotonCannon";NA;47;0
"Building";"Nexus";NA;45;0
"Upgrade";"ProtossAirWeaponsLevel1";"CyberneticsCore";47;0
"Building";"Assimilator";NA;61;0
"Building";"Assimilator";NA;64;0
"Building";"Pylon";NA;67;0
"Building";"Pylon";NA;67;0
"Building";"Pylon";NA;67;0
"Building";"Forge";NA;73;0
"Building";"Forge";NA;73;0
"Building";"Forge";NA;73;0
"Building";"Pylon";NA;73;0
"Building";"TwilightCouncil";NA;73;0
"Building";"Pylon";NA;73;0
"Upgrade";"ProtossAirArmorsLevel1";"CyberneticsCore";64;0
"Building";"Pylon";NA;73;0
"Building";"FleetBeacon";NA;73;0
"Building";"RoboticsFacility";NA;73;0
"Building";"TemplarArchive";NA;73;0
"Unit";"Observer";"Robotics Facility";73;1
"Building";"Pylon";NA;73;0
"Building";"Pylon";NA;73;0
"Building";"Assimilator";NA;73;0
"Unit";"Observer";"Robotics Facility";73;1
"Building";"Assimilator";NA;73;0
"Building";"PhotonCannon";NA;73;0
"Building";"PhotonCannon";NA;74;0
"Unit";"Observer";"Robotics Facility";74;1
"Building";"PhotonCannon";NA;74;0
"Building";"Pylon";NA;75;0
"Building";"RoboticsBay";NA;74;0
"Unit";"Observer";"Robotics Facility";75;1
"Building";"Nexus";NA;73;0
"Upgrade";"ProtossGroundWeaponsLevel1";"Forge";73;0
"Upgrade";"ProtossGroundArmorsLevel1";"Forge";73;0
"Upgrade";"ProtossShieldsLevel1";"Forge";73;0
"Building";"Gateway";NA;74;0
"Upgrade";"Charge";"TwilightCouncil";73;0
"Unit";"Carrier";"Stargate";73;6
"Unit";"Carrier";"Stargate";73;6
"Building";"Gateway";NA;75;0
"Building";"ShieldBattery";NA;76;0
"Building";"PhotonCannon";NA;76;0
"Building";"PhotonCannon";NA;76;0
"Building";"PhotonCannon";NA;76;0
"Building";"Gateway";NA;95;0
"Building";"Gateway";NA;95;0
"Building";"Gateway";NA;95;0
"Unit";"Observer";"Robotics Facility";95;1
"Building";"Gateway";NA;95;0
"Building";"Pylon";NA;95;0
"Unit";"Carrier";"Stargate";95;6
"Unit";"Carrier";"Stargate";95;6
"Unit";"Observer";"Robotics Facility";95;1
"Upgrade";"GraviticDrive";"RoboticsBay";95;0
"Building";"Pylon";NA;96;0
"Building";"PhotonCannon";NA;96;0
"Upgrade";"ProtossAirWeaponsLevel2";"CyberneticsCore";95;0
"Building";"PhotonCannon";NA;96;0
"Building";"PhotonCannon";NA;96;0
"Building";"PhotonCannon";NA;96;0
"Building";"PhotonCannon";NA;96;0
"Building";"PhotonCannon";NA;96;0
"Unit";"Observer";"Robotics Facility";108;1
"Building";"HighTemplar";NA;110;0
"Building";"HighTemplar";NA;110;0
"Building";"HighTemplar";NA;110;0
"Building";"HighTemplar";NA;110;0
"Building";"HighTemplar";NA;110;0
"Unit";"Observer";"Robotics Facility";109;1
"Upgrade";"ProtossGroundWeaponsLevel2";"Forge";95;0
"Upgrade";"ProtossGroundArmorsLevel2";"Forge";95;0
"Upgrade";"ProtossShieldsLevel2";"Forge";95;0
"Unit";"Observer";"Robotics Facility";110;1
"Building";"Gateway";NA;110;0
"Building";"Gateway";NA;110;0
"Building";"Gateway";NA;110;0
"Unit";"Carrier";"Stargate";109;6
"Unit";"Carrier";"Stargate";109;6
"Building";"Gateway";NA;111;0
"Building";"Gateway";NA;111;0
"Building";"Gateway";NA;111;0
"Upgrade";"ProtossAirArmorsLevel2";"CyberneticsCore";110;0
"Upgrade";"ProtossGroundWeaponsLevel3";"Forge";124;0
"Upgrade";"ProtossGroundArmorsLevel3";"Forge";124;0
"Upgrade";"ProtossShieldsLevel3";"Forge";124;0
"Unit";"Carrier";"Stargate";124;6
"Unit";"Carrier";"Stargate";124;6
"Building";"HighTemplar";NA;136;0
"Building";"HighTemplar";NA;136;0
"Building";"HighTemplar";NA;136;0
"Building";"HighTemplar";NA;136;0
"Building";"HighTemplar";NA;136;0
"Building";"HighTemplar";NA;136;0
"Building";"HighTemplar";NA;136;0
"Building";"HighTemplar";NA;136;0
"Building";"HighTemplar";NA;136;0
"Building";"HighTemplar";NA;136;0
"Upgrade";"ProtossAirWeaponsLevel3";"CyberneticsCore";124;0
"Unit";"Observer";"Robotics Facility";136;1
"Unit";"Zealot";"Gateway";137;2
"Unit";"Zealot";"Gateway";137;2
"Unit";"Zealot";"Gateway";137;2
"Unit";"Zealot";"Gateway";137;2
"Unit";"Zealot";"Gateway";137;2
"Unit";"Zealot";"Gateway";137;2
"Unit";"Zealot";"Gateway";137;2
"Unit";"Zealot";"Gateway";137;2
"Unit";"Zealot";"Gateway";137;2
"Unit";"Zealot";"Gateway";137;2
"Unit";"Zealot";"Gateway";137;2
"Unit";"Zealot";"Gateway";137;2
"Unit";"Zealot";"Gateway";137;2
"Building";"Pylon";NA;163;0
"Building";"Pylon";NA;163;0
"Upgrade";"ProtossAirArmorsLevel3";"CyberneticsCore";163;0
"Building";"Pylon";NA;163;0
"Unit";"Zealot";"Gateway";163;2
"Unit";"Zealot";"Gateway";163;2
"Unit";"Zealot";"Gateway";163;2
"Unit";"Zealot";"Gateway";163;2
"Unit";"Zealot";"Gateway";163;2
"Unit";"Zealot";"Gateway";163;2
"Unit";"Zealot";"Gateway";163;2
"Unit";"Zealot";"Gateway";163;2
"Unit";"Zealot";"Gateway";163;2
"Unit";"Zealot";"Gateway";163;2
"Unit";"Zealot";"Gateway";163;2
"Unit";"Zealot";"Gateway";163;2
"Unit";"Zealot";"Gateway";163;2
"Building";"ShieldBattery";NA;163;0
"Building";"ShieldBattery";NA;163;0
"Building";"PhotonCannon";NA;163;0
"Building";"Gateway";NA;163;0
"Building";"Gateway";NA;163;0
"Building";"Gateway";NA;163;0
"Building";"Assimilator";NA;163;0
"Building";"Assimilator";NA;163;0
"Unit";"Zealot";"Gateway";189;2
"Unit";"Zealot";"Gateway";189;2
"Unit";"Zealot";"Gateway";189;2
"Unit";"Zealot";"Gateway";189;2
"Unit";"Zealot";"Gateway";189;2
"Unit";"Zealot";"Gateway";189;2
"Unit";"Zealot";"Gateway";189;2
"Unit";"Zealot";"Gateway";189;2
"Unit";"Zealot";"Gateway";189;2
"Unit";"Zealot";"Gateway";189;2
"Unit";"Zealot";"Gateway";189;2
"Unit";"Zealot";"Gateway";189;2
"Unit";"Zealot";"Gateway";189;2
"Building";"Nexus";NA;163;0
"Building";"PhotonCannon";NA;189;0
"Upgrade";"ExtendedThermalLance";"RoboticsBay";163;0
"Building";"Pylon";NA;215;0
"Building";"Pylon";NA;215;0
"Building";"ShieldBattery";NA;215;0
"Building";"ShieldBattery";NA;215;0
"Building";"PhotonCannon";NA;215;0
"Building";"PhotonCannon";NA;215;0
"Building";"PhotonCannon";NA;215;0
"Building";"PhotonCannon";NA;215;0
"Building";"PhotonCannon";NA;215;0
"Building";"PhotonCannon";NA;215;0
"Building";"PhotonCannon";NA;215;0
"Building";"PhotonCannon";NA;215;0
"Building";"PhotonCannon";NA;215;0
"Building";"Pylon";NA;215;0
"Building";"PhotonCannon";NA;215;0
"Building";"Nexus";NA;215;0
"Building";"PhotonCannon";NA;215;0
"Building";"PhotonCannon";NA;215;0
"Building";"PhotonCannon";NA;215;0
"Building";"PhotonCannon";NA;215;0
"Unit";"Observer";"Robotics Facility";215;1
"Building";"Assimilator";NA;215;0
"Unit";"Observer";"Robotics Facility";215;1
"Unit";"Observer";"Robotics Facility";216;1
"Unit";"Observer";"Robotics Facility";217;1
"Building";"Pylon";NA;218;0
"Building";"Pylon";NA;218;0
"Unit";"Observer";"Robotics Facility";218;1
"Building";"ShieldBattery";NA;220;0
"Building";"PhotonCannon";NA;220;0
"Building";"PhotonCannon";NA;220;0
"Building";"PhotonCannon";NA;220;0
"Building";"PhotonCannon";NA;220;0
"Building";"Nexus";NA;218;0
"Building";"PhotonCannon";NA;220;0
"Building";"PhotonCannon";NA;220;0
"Building";"PhotonCannon";NA;220;0
"Building";"Assimilator";NA;220;0
"Building";"PhotonCannon";NA;220;0
"Building";"PhotonCannon";NA;220;0
"Building";"PhotonCannon";NA;220;0
"Building";"PhotonCannon";NA;220;0
"Building";"Assimilator";NA;220;0
"Building";"PhotonCannon";NA;220;0
"Building";"Nexus";NA;220;0
"Unit";"Zealot";"Gateway";220;2
"Unit";"Zealot";"Gateway";220;2
"Unit";"Zealot";"Gateway";220;2
"Unit";"Zealot";"Gateway";220;2
"Unit";"Zealot";"Gateway";220;2
"Unit";"Zealot";"Gateway";220;2
"Unit";"Zealot";"Gateway";220;2
"Unit";"Zealot";"Gateway";220;2
"Unit";"Zealot";"Gateway";220;2
"Unit";"Zealot";"Gateway";220;2
"Unit";"Zealot";"Gateway";220;2
"Unit";"Zealot";"Gateway";220;2
"Unit";"Zealot";"Gateway";220;2
"Unit";"Zealot";"Gateway";220;2
"Unit";"Zealot";"Gateway";220;2
"Unit";"Zealot";"Gateway";220;2
"Building";"Pylon";NA;220;0
"Building";"Pylon";NA;220;0
"Unit";"Zealot";"Gateway";252;2
"Unit";"Zealot";"Gateway";252;2
"Unit";"Zealot";"Gateway";252;2
"Unit";"Zealot";"Gateway";252;2
"Unit";"Zealot";"Gateway";252;2
"Unit";"Zealot";"Gateway";252;2
"Unit";"Zealot";"Gateway";252;2
"Unit";"Zealot";"Gateway";252;2
"Unit";"Zealot";"Gateway";252;2
"Unit";"Zealot";"Gateway";252;2
"Unit";"Zealot";"Gateway";252;2
"Unit";"Zealot";"Gateway";252;2
"Unit";"Zealot";"Gateway";252;2
"Unit";"Zealot";"Gateway";252;2
"Unit";"Zealot";"Gateway";252;2
"Unit";"Zealot";"Gateway";252;2
"Building";"Pylon";NA;252;0
"Building";"ShieldBattery";NA;284;0
"Building";"Gateway";NA;252;0
"Building";"PhotonCannon";NA;284;0
"Building";"PhotonCannon";NA;284;0
"Building";"Gateway";NA;252;0
"Building";"PhotonCannon";NA;284;0
"Building";"Gateway";NA;252;0
"Building";"Gateway";NA;252;0
"Building";"PhotonCannon";NA;284;0
"Building";"PhotonCannon";NA;284;0
"Building";"PhotonCannon";NA;284;0
"Building";"PhotonCannon";NA;284;0
"Building";"PhotonCannon";NA;284;0
"Building";"PhotonCannon";NA;284;0
"Unit";"Zealot";"Gateway";284;2
"Unit";"Zealot";"Gateway";284;2
"Unit";"Zealot";"Gateway";284;2
"Unit";"Zealot";"Gateway";284;2
"Unit";"Zealot";"Gateway";284;2
"Unit";"Zealot";"Gateway";284;2
"Unit";"Zealot";"Gateway";284;2
"Unit";"Zealot";"Gateway";284;2
"Unit";"Zealot";"Gateway";284;2
"Unit";"Zealot";"Gateway";284;2
"Building";"PhotonCannon";NA;284;0
"Building";"PhotonCannon";NA;284;0
"Building";"PhotonCannon";NA;284;0
"Building";"PhotonCannon";NA;284;0
"Building";"Assimilator";NA;284;0
"Building";"PhotonCannon";NA;284;0
"Building";"PhotonCannon";NA;284;0
"Building";"Assimilator";NA;284;0
