"type";"unit_name";"on_building";"total_supply";"supply"
"Building";"Pylon";NA;13;0
"Building";"Assimilator";NA;16;0
"Building";"Gateway";NA;15;0
"Building";"Pylon";NA;21;0
"Building";"Assimilator";NA;20;0
"Building";"CyberneticsCore";NA;19;0
"Unit";"Adept";"Gateway";21;2
"Building";"Nexus";NA;19;0
"Unit";"Adept";"Gateway";26;2
"Building";"Pylon";NA;29;0
"Building";"Stargate";NA;23;0
"Unit";"Oracle";"Stargate";34;3
"Building";"Assimilator";NA;38;0
"Building";"Assimilator";NA;39;0
"Unit";"Oracle";"Stargate";39;3
"Building";"Gateway";NA;37;0
"Building";"Pylon";NA;46;0
"Building";"Forge";NA;46;0
"Building";"TwilightCouncil";NA;46;0
"Unit";"Phoenix";"Stargate";53;2
"Building";"Pylon";NA;62;0
"Building";"TemplarArchive";NA;61;0
"Building";"Pylon";NA;62;0
"Building";"RoboticsFacility";NA;60;0
"Building";"Nexus";NA;54;0
"Building";"Assimilator";NA;62;0
"Building";"HighTemplar";NA;66;0
"Building";"HighTemplar";NA;66;0
"Building";"Assimilator";NA;64;0
"Building";"Pylon";NA;64;0
"Building";"Pylon";NA;64;0
"Unit";"Archon";"High Templar";68;0
"Building";"Gateway";NA;62;0
"Building";"Gateway";NA;64;0
"Building";"HighTemplar";NA;73;0
"Building";"HighTemplar";NA;73;0
"Unit";"Archon";"High Templar";73;0
"Unit";"Observer";"Robotics Facility";73;1
"Upgrade";"Charge";"TwilightCouncil";64;0
"Building";"Gateway";NA;68;0
"Building";"Gateway";NA;68;0
"Building";"Gateway";NA;68;0
"Building";"OracleStasisTrap";NA;78;0
"Building";"Gateway";NA;71;0
"Upgrade";"ProtossGroundWeaponsLevel1";"Forge";64;0
"Building";"Pylon";NA;75;0
"Unit";"Zealot";"Gateway";79;2
"Unit";"Zealot";"Gateway";79;2
"Unit";"Zealot";"Gateway";79;2
"Unit";"Zealot";"Gateway";79;2
"Unit";"Zealot";"Gateway";88;2
"Unit";"Zealot";"Gateway";88;2
"Unit";"Zealot";"Gateway";88;2
"Unit";"Zealot";"Gateway";88;2
"Building";"ShieldBattery";NA;78;0
"Unit";"Immortal";"Robotics Facility";75;4
"Unit";"Zealot";"Gateway";100;2
"Unit";"Zealot";"Gateway";100;2
"Unit";"Zealot";"Gateway";100;2
"Unit";"Zealot";"Gateway";100;2
"Unit";"Immortal";"Robotics Facility";96;4
"Building";"HighTemplar";NA;112;0
"Building";"HighTemplar";NA;112;0
"Building";"HighTemplar";NA;112;0
"Building";"HighTemplar";NA;112;0
"Building";"HighTemplar";NA;112;0
"Building";"HighTemplar";NA;112;0
"Building";"Pylon";NA;112;0
"Building";"RoboticsFacility";NA;108;0
"Unit";"Zealot";"Gateway";112;2
"Unit";"Zealot";"Gateway";114;2
"Building";"Assimilator";NA;112;0
"Building";"Pylon";NA;112;0
"Unit";"Immortal";"Robotics Facility";112;4
"Unit";"Zealot";"Gateway";120;2
"Unit";"Zealot";"Gateway";120;2
"Unit";"Zealot";"Gateway";120;2
"Unit";"Zealot";"Gateway";120;2
"Unit";"Zealot";"Gateway";120;2
"Unit";"Zealot";"Gateway";120;2
"Unit";"Zealot";"Gateway";120;2
"Unit";"Observer";"Robotics Facility";114;1
"Building";"OracleStasisTrap";NA;134;0
"Building";"Pylon";NA;116;0
"Unit";"Immortal";"Robotics Facility";112;4
"Building";"Pylon";NA;120;0
"Building";"Pylon";NA;120;0
"Building";"Nexus";NA;112;0
"Building";"ShieldBattery";NA;134;0
"Building";"ShieldBattery";NA;134;0
"Unit";"Immortal";"Robotics Facility";134;4
"Unit";"Immortal";"Robotics Facility";134;4
"Building";"Assimilator";NA;142;0
"Building";"PhotonCannon";NA;142;0
"Unit";"Zealot";"Gateway";152;2
"Unit";"Zealot";"Gateway";152;2
"Unit";"Zealot";"Gateway";152;2
"Unit";"Zealot";"Gateway";152;2
"Unit";"Zealot";"Gateway";152;2
"Unit";"Zealot";"Gateway";152;2
"Unit";"Zealot";"Gateway";152;2
"Unit";"Zealot";"Gateway";152;2
"Building";"FleetBeacon";NA;139;0
"Unit";"Immortal";"Robotics Facility";142;4
"Unit";"Immortal";"Robotics Facility";142;4
"Upgrade";"ProtossGroundWeaponsLevel2";"Forge";112;0
"Building";"Pylon";NA;150;0
"Building";"PhotonCannon";NA;150;0
"Building";"PhotonCannon";NA;150;0
"Building";"ShieldBattery";NA;150;0
"Building";"Stargate";NA;150;0
"Unit";"Immortal";"Robotics Facility";154;4
"Unit";"Immortal";"Robotics Facility";170;4
"Unit";"Oracle";"Stargate";178;3
"Unit";"Immortal";"Robotics Facility";178;4
"Unit";"Immortal";"Robotics Facility";182;4
"Unit";"Zealot";"Gateway";193;2
"Unit";"Zealot";"Gateway";197;2
"Unit";"Zealot";"Gateway";197;2
"Unit";"Zealot";"Gateway";197;2
"Unit";"Zealot";"Gateway";197;2
"Unit";"Zealot";"Gateway";197;2
"Unit";"Zealot";"Gateway";197;2
"Unit";"Zealot";"Gateway";197;2
"Unit";"Observer";"Robotics Facility";189;1
"Unit";"Archon";"High Templar";213;0
"Unit";"Archon";"High Templar";213;0
"Building";"HighTemplar";NA;214;0
"Building";"HighTemplar";NA;214;0
"Building";"HighTemplar";NA;214;0
"Building";"HighTemplar";NA;214;0
"Building";"HighTemplar";NA;214;0
"Building";"Stargate";NA;193;0
"Building";"Nexus";NA;189;0
"Building";"Pylon";NA;214;0
"Building";"Assimilator";NA;214;0
"Unit";"Carrier";"Stargate";189;6
"Building";"Pylon";NA;214;0
"Unit";"Carrier";"Stargate";189;6
"Building";"Assimilator";NA;214;0
"Building";"PhotonCannon";NA;214;0
"Building";"PhotonCannon";NA;214;0
"Building";"HighTemplar";NA;226;0
"Building";"HighTemplar";NA;226;0
"Building";"HighTemplar";NA;226;0
"Building";"HighTemplar";NA;226;0
"Building";"Stargate";NA;214;0
"Unit";"Archon";"High Templar";226;0
"Unit";"Archon";"High Templar";226;0
"Building";"PhotonCannon";NA;226;0
"Building";"PhotonCannon";NA;226;0
"Building";"PhotonCannon";NA;226;0
"Building";"PhotonCannon";NA;226;0
"Building";"PhotonCannon";NA;226;0
"Building";"PhotonCannon";NA;226;0
"Unit";"Zealot";"Gateway";226;2
"Unit";"Zealot";"Gateway";226;2
"Unit";"Zealot";"Gateway";226;2
"Unit";"Zealot";"Gateway";226;2
"Building";"PhotonCannon";NA;226;0
"Building";"PhotonCannon";NA;226;0
"Building";"ShieldBattery";NA;226;0
"Unit";"Carrier";"Stargate";214;6
"Building";"ShieldBattery";NA;226;0
"Unit";"Mothership";"Mothership Core";214;6
"Upgrade";"ProtossAirWeaponsLevel1";"CyberneticsCore";214;0
"Building";"HighTemplar";NA;246;0
"Building";"HighTemplar";NA;246;0
"Building";"HighTemplar";NA;246;0
"Building";"HighTemplar";NA;246;0
"Unit";"Carrier";"Stargate";226;6
"Unit";"Carrier";"Stargate";226;6
"Building";"Nexus";NA;226;0
"Unit";"Observer";"Robotics Facility";246;1
"Unit";"Observer";"Robotics Facility";246;1
"Building";"Pylon";NA;246;0
"Building";"Assimilator";NA;246;0
"Building";"HighTemplar";NA;260;0
"Building";"HighTemplar";NA;260;0
"Building";"HighTemplar";NA;260;0
"Unit";"Carrier";"Stargate";226;6
"Building";"HighTemplar";NA;260;0
"Building";"Pylon";NA;260;0
"Building";"Assimilator";NA;258;0
"Upgrade";"ProtossGroundWeaponsLevel3";"Forge";226;0
"Unit";"Archon";"High Templar";260;0
"Unit";"Archon";"High Templar";266;0
"Unit";"Observer";"Robotics Facility";260;1
"Unit";"Carrier";"Stargate";240;6
"Building";"PhotonCannon";NA;267;0
"Building";"PhotonCannon";NA;267;0
"Building";"PhotonCannon";NA;273;0
"Building";"PhotonCannon";NA;273;0
"Building";"PhotonCannon";NA;273;0
"Building";"PhotonCannon";NA;273;0
"Building";"PhotonCannon";NA;273;0
"Building";"PhotonCannon";NA;273;0
"Building";"ShieldBattery";NA;273;0
"Building";"ShieldBattery";NA;273;0
"Building";"ShieldBattery";NA;273;0
"Building";"ShieldBattery";NA;273;0
