"type";"unit_name";"on_building";"total_supply";"supply"
"Building";"Pylon";NA;13;0
"Building";"Assimilator";NA;15;0
"Building";"Gateway";NA;15;0
"Building";"Assimilator";NA;20;0
"Building";"CyberneticsCore";NA;19;0
"Building";"Pylon";NA;21;0
"Unit";"Adept";"Gateway";21;2
"Building";"Nexus";NA;19;0
"Unit";"Stalker";"Gateway";23;2
"Building";"TwilightCouncil";NA;23;0
"Building";"ShieldBattery";NA;34;0
"Building";"RoboticsFacility";NA;33;0
"Building";"Gateway";NA;33;0
"Building";"Gateway";NA;34;0
"Building";"Assimilator";NA;36;0
"Building";"Assimilator";NA;37;0
"Building";"Pylon";NA;39;0
"Unit";"Sentry";"Gateway";44;2
"Building";"Pylon";NA;42;0
"Building";"DarkShrine";NA;34;0
"Building";"Gateway";NA;39;0
"Building";"DarkTemplar";NA;50;0
"Building";"DarkTemplar";NA;50;0
"Building";"DarkTemplar";NA;50;0
"Building";"DarkTemplar";NA;50;0
"Unit";"Archon";"High Templar";51;0
"Unit";"Archon";"High Templar";51;0
"Building";"Pylon";NA;51;0
"Building";"Forge";NA;51;0
"Building";"Nexus";NA;49;0
"Building";"Gateway";NA;52;0
"Building";"Gateway";NA;52;0
"Building";"Gateway";NA;52;0
"Building";"Gateway";NA;52;0
"Building";"DarkTemplar";NA;57;0
"Building";"DarkTemplar";NA;57;0
"Building";"DarkTemplar";NA;57;0
"Building";"DarkTemplar";NA;57;0
"Building";"Pylon";NA;57;0
"Building";"Pylon";NA;57;0
"Upgrade";"Charge";"TwilightCouncil";52;0
"Building";"Pylon";NA;59;0
"Unit";"Immortal";"Robotics Facility";56;4
"Building";"ShieldBattery";NA;59;0
"Unit";"Sentry";"Gateway";68;2
"Unit";"Sentry";"Gateway";68;2
"Unit";"Sentry";"Gateway";68;2
"Unit";"Sentry";"Gateway";68;2
"Building";"Pylon";NA;67;0
"Building";"Pylon";NA;67;0
"Unit";"Zealot";"Gateway";80;2
"Building";"Assimilator";NA;67;0
"Building";"Assimilator";NA;67;0
"Building";"Pylon";NA;67;0
"Building";"Pylon";NA;68;0
"Building";"Pylon";NA;73;0
"Building";"Pylon";NA;77;0
"Upgrade";"ProtossGroundWeaponsLevel1";"Forge";57;0
"Unit";"Immortal";"Robotics Facility";67;4
"Building";"TemplarArchive";NA;67;0
"Building";"Pylon";NA;83;0
"Unit";"Zealot";"Gateway";91;2
"Unit";"Zealot";"Gateway";91;2
"Unit";"Zealot";"Gateway";91;2
"Unit";"Zealot";"Gateway";91;2
"Unit";"Zealot";"Gateway";91;2
"Unit";"Zealot";"Gateway";91;2
"Unit";"Zealot";"Gateway";91;2
"Unit";"Zealot";"Gateway";91;2
"Unit";"Immortal";"Robotics Facility";84;4
"Building";"Pylon";NA;107;0
"Building";"Pylon";NA;107;0
"Building";"HighTemplar";NA;114;0
"Building";"HighTemplar";NA;114;0
"Building";"HighTemplar";NA;114;0
"Building";"HighTemplar";NA;114;0
"Building";"Pylon";NA;114;0
"Building";"HighTemplar";NA;115;0
"Building";"HighTemplar";NA;115;0
"Building";"HighTemplar";NA;115;0
"Building";"PhotonCannon";NA;114;0
"Building";"PhotonCannon";NA;114;0
"Unit";"Archon";"High Templar";115;0
"Building";"PhotonCannon";NA;115;0
"Unit";"Zealot";"Gateway";115;2
"Building";"Pylon";NA;115;0
"Building";"DarkTemplar";NA;117;0
"Building";"DarkTemplar";NA;117;0
"Building";"DarkTemplar";NA;117;0
"Unit";"Zealot";"Gateway";117;2
"Building";"Pylon";NA;115;0
"Building";"Pylon";NA;115;0
"Upgrade";"ProtossGroundWeaponsLevel2";"Forge";107;0
"Building";"ShieldBattery";NA;115;0
"Building";"ShieldBattery";NA;115;0
"Unit";"Immortal";"Robotics Facility";115;4
"Unit";"Zealot";"Gateway";123;2
"Unit";"Zealot";"Gateway";123;2
"Unit";"Zealot";"Gateway";123;2
"Unit";"Zealot";"Gateway";123;2
"Unit";"Zealot";"Gateway";131;2
"Unit";"Zealot";"Gateway";131;2
"Unit";"Zealot";"Gateway";131;2
"Unit";"Zealot";"Gateway";131;2
"Unit";"Immortal";"Robotics Facility";119;4
"Building";"Pylon";NA;131;0
"Building";"PhotonCannon";NA;131;0
"Building";"PhotonCannon";NA;131;0
"Building";"ShieldBattery";NA;131;0
"Building";"PhotonCannon";NA;131;0
"Building";"Nexus";NA;115;0
"Building";"ShieldBattery";NA;131;0
"Building";"PhotonCannon";NA;131;0
"Unit";"Zealot";"Gateway";146;2
"Unit";"Zealot";"Gateway";146;2
"Unit";"Zealot";"Gateway";146;2
"Unit";"Zealot";"Gateway";146;2
"Unit";"Zealot";"Gateway";146;2
"Unit";"Zealot";"Gateway";146;2
"Unit";"Zealot";"Gateway";146;2
"Unit";"Zealot";"Gateway";146;2
"Building";"Assimilator";NA;162;0
"Building";"Assimilator";NA;162;0
"Unit";"Observer";"Robotics Facility";162;1
"Building";"Stargate";NA;146;0
"Building";"PhotonCannon";NA;162;0
"Building";"PhotonCannon";NA;162;0
"Building";"PhotonCannon";NA;162;0
"Building";"Pylon";NA;163;0
"Building";"Pylon";NA;163;0
"Building";"Pylon";NA;163;0
"Building";"Pylon";NA;163;0
"Building";"PhotonCannon";NA;164;0
"Building";"PhotonCannon";NA;164;0
"Building";"FleetBeacon";NA;163;0
"Unit";"Zealot";"Gateway";164;2
"Unit";"Zealot";"Gateway";164;2
"Unit";"Zealot";"Gateway";164;2
"Unit";"Zealot";"Gateway";164;2
"Unit";"Zealot";"Gateway";164;2
"Unit";"Zealot";"Gateway";164;2
"Unit";"Zealot";"Gateway";164;2
"Unit";"Zealot";"Gateway";164;2
"Unit";"Immortal";"Robotics Facility";164;4
"Building";"Stargate";NA;164;0
"Building";"Stargate";NA;164;0
"Upgrade";"ProtossGroundWeaponsLevel3";"Forge";162;0
"Unit";"Zealot";"Gateway";184;2
"Building";"Gateway";NA;164;0
"Building";"Gateway";NA;164;0
"Building";"Gateway";NA;164;0
"Building";"Gateway";NA;180;0
"Building";"Pylon";NA;186;0
"Building";"Pylon";NA;186;0
"Building";"Pylon";NA;186;0
"Building";"DarkTemplar";NA;186;0
"Building";"DarkTemplar";NA;186;0
"Building";"DarkTemplar";NA;186;0
"Building";"DarkTemplar";NA;186;0
"Building";"DarkTemplar";NA;186;0
"Unit";"Zealot";"Gateway";186;2
"Unit";"Zealot";"Gateway";186;2
"Upgrade";"ProtossAirWeaponsLevel1";"CyberneticsCore";180;0
"Building";"Nexus";NA;184;0
"Unit";"Mothership";"Mothership Core";186;6
"Unit";"Carrier";"Stargate";186;6
"Unit";"Carrier";"Stargate";186;6
"Building";"HighTemplar";NA;201;0
"Building";"HighTemplar";NA;203;0
"Building";"HighTemplar";NA;203;0
"Building";"HighTemplar";NA;203;0
"Building";"HighTemplar";NA;203;0
"Building";"HighTemplar";NA;204;0
"Building";"HighTemplar";NA;204;0
"Building";"HighTemplar";NA;204;0
"Building";"HighTemplar";NA;204;0
"Building";"HighTemplar";NA;204;0
"Building";"HighTemplar";NA;204;0
"Building";"PhotonCannon";NA;192;0
"Unit";"Carrier";"Stargate";186;6
"Building";"PhotonCannon";NA;192;0
"Unit";"Archon";"High Templar";216;0
"Unit";"Archon";"High Templar";216;0
"Unit";"Archon";"High Templar";216;0
"Unit";"Archon";"High Templar";216;0
"Unit";"Archon";"High Templar";216;0
"Building";"PhotonCannon";NA;192;0
"Upgrade";"ProtossShieldsLevel1";"Forge";186;0
"Building";"PhotonCannon";NA;222;0
"Building";"PhotonCannon";NA;222;0
"Building";"PhotonCannon";NA;222;0
"Building";"ShieldBattery";NA;222;0
"Building";"ShieldBattery";NA;222;0
"Building";"ShieldBattery";NA;222;0
"Unit";"Zealot";"Gateway";222;2
"Unit";"Zealot";"Gateway";222;2
"Unit";"Zealot";"Gateway";222;2
"Unit";"Zealot";"Gateway";222;2
"Unit";"Zealot";"Gateway";222;2
"Building";"Assimilator";NA;222;0
"Unit";"Zealot";"Gateway";222;2
"Building";"Assimilator";NA;222;0
"Unit";"Carrier";"Stargate";192;6
"Unit";"Zealot";"Gateway";222;2
"Unit";"Carrier";"Stargate";192;6
"Building";"PhotonCannon";NA;240;0
"Building";"PhotonCannon";NA;242;0
"Building";"HighTemplar";NA;248;0
"Building";"HighTemplar";NA;248;0
"Building";"HighTemplar";NA;248;0
"Building";"HighTemplar";NA;248;0
"Building";"HighTemplar";NA;248;0
"Building";"HighTemplar";NA;248;0
"Building";"HighTemplar";NA;248;0
"Unit";"Zealot";"Gateway";248;2
"Unit";"Zealot";"Gateway";248;2
"Unit";"Zealot";"Gateway";248;2
"Unit";"Stalker";"Gateway";254;2
"Unit";"Stalker";"Gateway";254;2
"Upgrade";"ProtossAirWeaponsLevel2";"CyberneticsCore";222;0
"Unit";"Stalker";"Gateway";258;2
"Unit";"Stalker";"Gateway";258;2
"Unit";"Stalker";"Gateway";258;2
"Building";"Nexus";NA;254;0
"Building";"Nexus";NA;258;0
"Unit";"Observer";"Robotics Facility";264;1
"Building";"TemplarArchive";NA;267;0
"Building";"Nexus";NA;264;0
"Building";"DarkTemplar";NA;267;0
"Building";"DarkTemplar";NA;267;0
"Building";"DarkTemplar";NA;267;0
"Unit";"Zealot";"Gateway";267;2
"Unit";"Zealot";"Gateway";267;2
"Unit";"Zealot";"Gateway";267;2
"Unit";"Zealot";"Gateway";267;2
"Unit";"Oracle";"Stargate";267;3
"Unit";"Zealot";"Gateway";267;2
"Unit";"Zealot";"Gateway";267;2
"Unit";"Zealot";"Gateway";267;2
"Unit";"Zealot";"Gateway";267;2
"Unit";"Tempest";"Stargate";267;4
"Unit";"Tempest";"Stargate";267;4
"Unit";"Zealot";"Gateway";294;2
"Unit";"Zealot";"Gateway";294;2
"Unit";"Zealot";"Gateway";294;2
"Unit";"Zealot";"Gateway";294;2
"Unit";"Zealot";"Gateway";294;2
"Unit";"Zealot";"Gateway";294;2
"Unit";"Zealot";"Gateway";294;2
"Unit";"Zealot";"Gateway";294;2
"Building";"Pylon";NA;294;0
"Building";"Pylon";NA;294;0
"Building";"DarkTemplar";NA;310;0
"Building";"DarkTemplar";NA;310;0
"Building";"DarkTemplar";NA;310;0
"Building";"DarkTemplar";NA;310;0
"Building";"Nexus";NA;294;0
"Unit";"Zealot";"Gateway";310;2
"Unit";"Zealot";"Gateway";310;2
"Unit";"Zealot";"Gateway";310;2
"Unit";"Zealot";"Gateway";310;2
"Unit";"Zealot";"Gateway";310;2
"Unit";"Zealot";"Gateway";310;2
"Unit";"Zealot";"Gateway";310;2
"Upgrade";"ProtossAirWeaponsLevel3";"CyberneticsCore";294;0
"Unit";"Mothership";"Mothership Core";310;6
"Unit";"Archon";"High Templar";324;0
"Building";"DarkTemplar";NA;330;0
"Building";"DarkTemplar";NA;330;0
"Building";"DarkTemplar";NA;330;0
"Building";"DarkTemplar";NA;330;0
"Building";"DarkTemplar";NA;330;0
"Unit";"Archon";"High Templar";330;0
"Unit";"Archon";"High Templar";330;0
"Building";"HighTemplar";NA;330;0
"Building";"HighTemplar";NA;330;0
"Building";"HighTemplar";NA;330;0
"Unit";"Zealot";"Gateway";330;2
"Unit";"Zealot";"Gateway";330;2
"Unit";"Zealot";"Gateway";334;2
"Unit";"Zealot";"Gateway";334;2
"Unit";"Zealot";"Gateway";334;2
"Unit";"Zealot";"Gateway";334;2
"Unit";"Zealot";"Gateway";334;2
"Unit";"Zealot";"Gateway";334;2
"Unit";"Zealot";"Gateway";334;2
"Unit";"Zealot";"Gateway";334;2
"Unit";"Zealot";"Gateway";334;2
"Unit";"Zealot";"Gateway";334;2
"Building";"Assimilator";NA;334;0
"Building";"Nexus";NA;334;0
