"type";"unit_name";"on_building";"total_supply";"supply"
"Building";"Pylon";NA;13;0
"Building";"Assimilator";NA;16;0
"Building";"Gateway";NA;15;0
"Building";"Assimilator";NA;20;0
"Building";"CyberneticsCore";NA;20;0
"Building";"Pylon";NA;21;0
"Building";"Nexus";NA;19;0
"Unit";"Adept";"Gateway";22;2
"Unit";"Adept";"Gateway";24;2
"Building";"Stargate";NA;24;0
"Unit";"Adept";"Gateway";31;2
"Unit";"Oracle";"Stargate";31;3
"Building";"Pylon";NA;35;0
"Building";"Gateway";NA;31;0
"Unit";"Phoenix";"Stargate";39;2
"Building";"Pylon";NA;48;0
"Building";"TwilightCouncil";NA;44;0
"Building";"Gateway";NA;44;0
"Building";"Assimilator";NA;53;0
"Building";"Assimilator";NA;54;0
"Building";"OracleStasisTrap";NA;55;0
"Building";"Forge";NA;53;0
"Building";"Pylon";NA;55;0
"Building";"Gateway";NA;52;0
"Building";"RoboticsFacility";NA;53;0
"Unit";"Zealot";"Gateway";60;2
"Unit";"Zealot";"Gateway";60;2
"Building";"Nexus";NA;52;0
"Unit";"Sentry";"Gateway";68;2
"Unit";"Sentry";"Gateway";68;2
"Unit";"Zealot";"Gateway";69;2
"Unit";"Zealot";"Gateway";69;2
"Building";"RoboticsFacility";NA;57;0
"Building";"Assimilator";NA;65;0
"Building";"Assimilator";NA;66;0
"Unit";"Immortal";"Robotics Facility";59;4
"Building";"RoboticsBay";NA;59;0
"Building";"Pylon";NA;80;0
"Building";"Pylon";NA;80;0
"Upgrade";"Charge";"TwilightCouncil";57;0
"Unit";"Zealot";"Gateway";85;2
"Upgrade";"ProtossGroundWeaponsLevel1";"Forge";57;0
"Building";"Pylon";NA;88;0
"Unit";"Immortal";"Robotics Facility";85;4
"Building";"Pylon";NA;88;0
"Unit";"Zealot";"Gateway";95;2
"Unit";"Zealot";"Gateway";95;2
"Unit";"Zealot";"Gateway";95;2
"Unit";"Zealot";"Gateway";95;2
"Unit";"Colossus";"Robotics Facility";81;6
"Unit";"Immortal";"Robotics Facility";90;4
"Unit";"Sentry";"Gateway";115;2
"Unit";"Sentry";"Gateway";115;2
"Unit";"Sentry";"Gateway";115;2
"Building";"Gateway";NA;111;0
"Building";"Gateway";NA;111;0
"Upgrade";"ExtendedThermalLance";"RoboticsBay";90;0
"Unit";"Zealot";"Gateway";121;2
"Unit";"Zealot";"Gateway";121;2
"Unit";"Zealot";"Gateway";121;2
"Unit";"Zealot";"Gateway";121;2
"Unit";"Colossus";"Robotics Facility";111;6
"Unit";"Immortal";"Robotics Facility";121;4
"Unit";"Zealot";"Gateway";135;2
"Unit";"Zealot";"Gateway";135;2
"Unit";"Zealot";"Gateway";135;2
"Unit";"Zealot";"Gateway";135;2
"Unit";"Zealot";"Gateway";135;2
"Unit";"Zealot";"Gateway";135;2
"Building";"CyberneticsCore";NA;121;0
"Unit";"Sentry";"Gateway";151;2
"Unit";"Sentry";"Gateway";151;2
"Unit";"Sentry";"Gateway";151;2
"Unit";"Zealot";"Gateway";151;2
"Unit";"Zealot";"Gateway";151;2
"Unit";"Zealot";"Gateway";151;2
"Building";"Gateway";NA;121;0
"Building";"Gateway";NA;121;0
"Unit";"Immortal";"Robotics Facility";129;4
"Unit";"Immortal";"Robotics Facility";135;4
"Upgrade";"ProtossGroundWeaponsLevel2";"Forge";111;0
"Unit";"Sentry";"Gateway";171;2
"Unit";"Sentry";"Gateway";171;2
"Unit";"Sentry";"Gateway";171;2
"Unit";"Sentry";"Gateway";171;2
"Unit";"Sentry";"Gateway";171;2
"Unit";"Sentry";"Gateway";171;2
"Unit";"Sentry";"Gateway";171;2
"Building";"Pylon";NA;171;0
"Unit";"Immortal";"Robotics Facility";171;4
"Building";"Pylon";NA;185;0
"Unit";"Zealot";"Gateway";185;2
"Unit";"Zealot";"Gateway";185;2
"Unit";"Zealot";"Gateway";185;2
"Unit";"Zealot";"Gateway";195;2
"Unit";"Zealot";"Gateway";195;2
"Unit";"Zealot";"Gateway";195;2
"Unit";"Zealot";"Gateway";195;2
"Building";"Pylon";NA;195;0
"Building";"Pylon";NA;195;0
"Unit";"Sentry";"Gateway";203;2
"Unit";"Sentry";"Gateway";203;2
"Unit";"Zealot";"Gateway";203;2
"Unit";"Zealot";"Gateway";203;2
"Unit";"Zealot";"Gateway";203;2
"Unit";"Zealot";"Gateway";203;2
"Unit";"Zealot";"Gateway";203;2
"Unit";"Immortal";"Robotics Facility";185;4
"Unit";"Observer";"Robotics Facility";217;1
"Unit";"Observer";"Robotics Facility";217;1
"Building";"Pylon";NA;223;0
"Building";"Pylon";NA;223;0
"Building";"Pylon";NA;223;0
"Building";"Pylon";NA;223;0
"Building";"Pylon";NA;223;0
"Unit";"Zealot";"Gateway";223;2
"Unit";"Zealot";"Gateway";223;2
"Unit";"Zealot";"Gateway";223;2
"Unit";"Zealot";"Gateway";223;2
"Unit";"Zealot";"Gateway";223;2
"Unit";"Zealot";"Gateway";223;2
"Unit";"Zealot";"Gateway";223;2
"Unit";"Zealot";"Gateway";237;2
"Unit";"Zealot";"Gateway";237;2
"Unit";"Zealot";"Gateway";237;2
"Unit";"Zealot";"Gateway";237;2
"Unit";"Zealot";"Gateway";237;2
"Unit";"Zealot";"Gateway";237;2
"Unit";"Zealot";"Gateway";237;2
"Unit";"Zealot";"Gateway";237;2
"Building";"Pylon";NA;237;0
"Building";"TemplarArchive";NA;237;0
"Unit";"Zealot";"Gateway";253;2
"Unit";"Zealot";"Gateway";253;2
"Unit";"Zealot";"Gateway";253;2
"Unit";"Zealot";"Gateway";253;2
"Unit";"Zealot";"Gateway";253;2
"Building";"HighTemplar";NA;263;0
"Building";"HighTemplar";NA;263;0
"Building";"HighTemplar";NA;263;0
"Building";"HighTemplar";NA;263;0
"Building";"HighTemplar";NA;263;0
"Unit";"Zealot";"Gateway";263;2
"Unit";"Zealot";"Gateway";265;2
"Unit";"Zealot";"Gateway";265;2
"Unit";"Colossus";"Robotics Facility";253;6
"Unit";"Colossus";"Robotics Facility";253;6
"Unit";"Sentry";"Gateway";281;2
"Unit";"Sentry";"Gateway";281;2
"Unit";"Zealot";"Gateway";281;2
"Unit";"Zealot";"Gateway";281;2
"Unit";"Immortal";"Robotics Facility";269;4
"Unit";"Immortal";"Robotics Facility";269;4
"Building";"HighTemplar";NA;297;0
"Building";"HighTemplar";NA;297;0
"Building";"HighTemplar";NA;297;0
"Unit";"Zealot";"Gateway";297;2
"Unit";"Zealot";"Gateway";297;2
"Unit";"Zealot";"Gateway";297;2
"Unit";"Zealot";"Gateway";297;2
"Unit";"Zealot";"Gateway";297;2
"Unit";"Observer";"Robotics Facility";289;1
"Unit";"Observer";"Robotics Facility";289;1
"Unit";"Archon";"High Templar";297;0
"Building";"HighTemplar";NA;309;0
"Building";"HighTemplar";NA;309;0
"Unit";"Zealot";"Gateway";309;2
"Unit";"Zealot";"Gateway";309;2
"Unit";"Zealot";"Gateway";309;2
"Unit";"Zealot";"Gateway";309;2
"Unit";"Zealot";"Gateway";309;2
"Unit";"Sentry";"Gateway";319;2
"Unit";"Immortal";"Robotics Facility";309;4
"Unit";"Immortal";"Robotics Facility";309;4
"Upgrade";"ProtossGroundWeaponsLevel3";"Forge";269;0
"Building";"HighTemplar";NA;329;0
"Building";"HighTemplar";NA;329;0
"Unit";"Zealot";"Gateway";329;2
"Unit";"Zealot";"Gateway";329;2
"Unit";"Zealot";"Gateway";329;2
"Unit";"Observer";"Robotics Facility";321;1
"Unit";"Observer";"Robotics Facility";321;1
"Unit";"Archon";"High Templar";329;0
"Unit";"Zealot";"Gateway";337;2
"Unit";"Zealot";"Gateway";337;2
"Unit";"Zealot";"Gateway";337;2
"Unit";"Zealot";"Gateway";337;2
"Unit";"Zealot";"Gateway";337;2
"Building";"HighTemplar";NA;337;0
"Building";"HighTemplar";NA;337;0
"Unit";"Zealot";"Gateway";337;2
"Unit";"Archon";"High Templar";347;0
"Unit";"Archon";"High Templar";347;0
"Unit";"Archon";"High Templar";349;0
"Unit";"Observer";"Robotics Facility";337;1
"Unit";"Observer";"Robotics Facility";337;1
"Unit";"Zealot";"Gateway";351;2
"Unit";"Zealot";"Gateway";351;2
"Unit";"Zealot";"Gateway";355;2
"Unit";"Zealot";"Gateway";355;2
"Unit";"Zealot";"Gateway";355;2
