"type";"unit_name";"on_building";"total_supply";"supply"
"Building";"Pylon";NA;13;0
"Building";"Assimilator";NA;16;0
"Building";"Gateway";NA;14;0
"Building";"Pylon";NA;18;0
"Building";"CyberneticsCore";NA;18;0
"Building";"Assimilator";NA;19;0
"Unit";"Adept";"Gateway";20;2
"Building";"Nexus";NA;18;0
"Unit";"Adept";"Gateway";22;2
"Building";"Stargate";NA;28;0
"Building";"Gateway";NA;28;0
"Building";"Pylon";NA;35;0
"Building";"Gateway";NA;32;0
"Building";"Assimilator";NA;35;0
"Building";"Assimilator";NA;35;0
"Unit";"Oracle";"Stargate";34;3
"Unit";"Phoenix";"Stargate";39;2
"Building";"Stargate";NA;38;0
"Building";"Pylon";NA;47;0
"Unit";"Phoenix";"Stargate";50;2
"Unit";"Phoenix";"Stargate";51;2
"Unit";"Phoenix";"Stargate";54;2
"Building";"Pylon";NA;58;0
"Unit";"Phoenix";"Stargate";58;2
"Unit";"Sentry";"Gateway";63;2
"Unit";"Sentry";"Gateway";63;2
"Building";"TwilightCouncil";NA;59;0
"Building";"ShieldBattery";NA;63;0
"Building";"Nexus";NA;53;0
"Building";"RoboticsFacility";NA;59;0
"Building";"Pylon";NA;71;0
"Building";"Pylon";NA;71;0
"Building";"Pylon";NA;71;0
"Building";"Pylon";NA;71;0
"Unit";"Phoenix";"Stargate";71;2
"Unit";"Phoenix";"Stargate";71;2
"Unit";"Sentry";"Gateway";73;2
"Unit";"Sentry";"Gateway";73;2
"Building";"Gateway";NA;71;0
"Building";"Gateway";NA;71;0
"Unit";"Adept";"Gateway";88;2
"Unit";"Adept";"Gateway";88;2
"Unit";"Adept";"Gateway";88;2
"Building";"Gateway";NA;73;0
"Building";"Gateway";NA;73;0
"Unit";"Phoenix";"Stargate";85;2
"Building";"Assimilator";NA;85;0
"Upgrade";"Charge";"TwilightCouncil";71;0
"Building";"TemplarArchive";NA;85;0
"Unit";"Immortal";"Robotics Facility";85;4
"Unit";"Zealot";"Gateway";100;2
"Unit";"Zealot";"Gateway";100;2
"Unit";"Zealot";"Gateway";100;2
"Unit";"Zealot";"Gateway";106;2
"Unit";"Zealot";"Gateway";106;2
"Building";"ShieldBattery";NA;94;0
"Building";"ShieldBattery";NA;96;0
"Unit";"Zealot";"Gateway";110;2
"Unit";"Zealot";"Gateway";110;2
"Unit";"Zealot";"Gateway";110;2
"Unit";"Zealot";"Gateway";110;2
"Unit";"Zealot";"Gateway";110;2
"Unit";"Zealot";"Gateway";110;2
"Unit";"Immortal";"Robotics Facility";100;4
"Unit";"Phoenix";"Stargate";110;2
"Building";"Pylon";NA;126;0
"Building";"Assimilator";NA;126;0
"Building";"Pylon";NA;127;0
"Building";"HighTemplar";NA;131;0
"Building";"HighTemplar";NA;131;0
"Building";"Pylon";NA;127;0
"Building";"Pylon";NA;129;0
"Building";"Forge";NA;126;0
"Building";"HighTemplar";NA;131;0
"Building";"HighTemplar";NA;131;0
"Building";"HighTemplar";NA;131;0
"Building";"Pylon";NA;131;0
"Building";"Pylon";NA;131;0
"Building";"Gateway";NA;127;0
"Building";"Pylon";NA;131;0
"Building";"Pylon";NA;131;0
"Building";"Gateway";NA;127;0
"Unit";"Immortal";"Robotics Facility";131;4
"Building";"HighTemplar";NA;139;0
"Building";"HighTemplar";NA;139;0
"Building";"Pylon";NA;139;0
"Unit";"Zealot";"Gateway";139;2
"Unit";"Zealot";"Gateway";139;2
"Unit";"Zealot";"Gateway";139;2
"Unit";"Zealot";"Gateway";139;2
"Building";"Pylon";NA;139;0
"Unit";"Immortal";"Robotics Facility";139;4
"Building";"Pylon";NA;147;0
"Building";"Pylon";NA;147;0
"Building";"HighTemplar";NA;152;0
"Unit";"Zealot";"Gateway";152;2
"Unit";"Zealot";"Gateway";152;2
"Unit";"Zealot";"Gateway";152;2
"Building";"PhotonCannon";NA;147;0
"Building";"PhotonCannon";NA;147;0
"Building";"PhotonCannon";NA;147;0
"Building";"PhotonCannon";NA;147;0
"Building";"Assimilator";NA;148;0
"Building";"Nexus";NA;135;0
"Upgrade";"ProtossGroundWeaponsLevel1";"Forge";134;0
"Building";"Assimilator";NA;152;0
"Building";"HighTemplar";NA;158;0
"Building";"HighTemplar";NA;158;0
"Unit";"Zealot";"Gateway";158;2
"Unit";"Zealot";"Gateway";158;2
"Unit";"Zealot";"Gateway";158;2
"Unit";"Zealot";"Gateway";158;2
"Unit";"Zealot";"Gateway";158;2
"Building";"FleetBeacon";NA;148;0
"Unit";"Archon";"High Templar";158;0
"Unit";"Zealot";"Gateway";168;2
"Unit";"Zealot";"Gateway";168;2
"Unit";"Zealot";"Gateway";168;2
"Unit";"Zealot";"Gateway";168;2
"Unit";"Zealot";"Gateway";168;2
"Unit";"Zealot";"Gateway";168;2
"Unit";"Observer";"Robotics Facility";168;1
"Unit";"Zealot";"Gateway";181;2
"Unit";"Zealot";"Gateway";181;2
"Unit";"Zealot";"Gateway";181;2
"Unit";"Zealot";"Gateway";181;2
"Unit";"Zealot";"Gateway";181;2
"Unit";"Zealot";"Gateway";181;2
"Unit";"Zealot";"Gateway";181;2
"Unit";"Zealot";"Gateway";181;2
"Unit";"Zealot";"Gateway";197;2
"Unit";"Zealot";"Gateway";197;2
"Unit";"Zealot";"Gateway";197;2
"Unit";"Zealot";"Gateway";197;2
"Unit";"Zealot";"Gateway";197;2
"Unit";"Zealot";"Gateway";197;2
"Unit";"Zealot";"Gateway";197;2
"Unit";"Zealot";"Gateway";197;2
"Unit";"Zealot";"Gateway";213;2
"Unit";"Zealot";"Gateway";213;2
"Unit";"Zealot";"Gateway";213;2
"Unit";"Zealot";"Gateway";213;2
"Unit";"Zealot";"Gateway";213;2
"Unit";"Zealot";"Gateway";213;2
"Unit";"Zealot";"Gateway";213;2
"Unit";"Zealot";"Gateway";213;2
"Unit";"Immortal";"Robotics Facility";197;4
"Upgrade";"ProtossGroundWeaponsLevel2";"Forge";181;0
"Unit";"Zealot";"Gateway";233;2
"Unit";"Zealot";"Gateway";233;2
"Unit";"Zealot";"Gateway";233;2
"Unit";"Zealot";"Gateway";233;2
"Unit";"Zealot";"Gateway";233;2
"Unit";"Zealot";"Gateway";233;2
"Unit";"Zealot";"Gateway";233;2
"Unit";"Zealot";"Gateway";233;2
"Building";"PhotonCannon";NA;229;0
"Building";"PhotonCannon";NA;229;0
"Building";"Stargate";NA;229;0
"Building";"Stargate";NA;229;0
"Unit";"Carrier";"Stargate";197;6
"Unit";"Immortal";"Robotics Facility";233;4
"Building";"Pylon";NA;249;0
"Unit";"Zealot";"Gateway";259;2
"Unit";"Zealot";"Gateway";259;2
"Unit";"Zealot";"Gateway";259;2
"Unit";"Zealot";"Gateway";259;2
"Unit";"Zealot";"Gateway";259;2
"Unit";"Zealot";"Gateway";259;2
"Unit";"Zealot";"Gateway";259;2
"Unit";"Zealot";"Gateway";259;2
"Building";"HighTemplar";NA;275;0
"Building";"HighTemplar";NA;275;0
"Building";"HighTemplar";NA;275;0
"Building";"HighTemplar";NA;275;0
"Building";"HighTemplar";NA;275;0
"Building";"HighTemplar";NA;275;0
"Building";"HighTemplar";NA;275;0
"Building";"HighTemplar";NA;275;0
"Building";"Nexus";NA;249;0
"Unit";"Mothership";"Mothership Core";259;6
"Building";"HighTemplar";NA;275;0
"Building";"HighTemplar";NA;275;0
"Building";"HighTemplar";NA;275;0
"Building";"HighTemplar";NA;275;0
"Building";"HighTemplar";NA;275;0
"Building";"HighTemplar";NA;275;0
"Building";"HighTemplar";NA;275;0
"Unit";"Archon";"High Templar";281;0
"Unit";"Archon";"High Templar";281;0
"Unit";"Archon";"High Templar";281;0
"Unit";"Carrier";"Stargate";259;6
"Unit";"Carrier";"Stargate";259;6
"Unit";"Zealot";"Gateway";293;2
"Unit";"Zealot";"Gateway";293;2
"Unit";"Zealot";"Gateway";293;2
"Unit";"Zealot";"Gateway";293;2
"Unit";"Zealot";"Gateway";293;2
"Unit";"Zealot";"Gateway";293;2
"Unit";"Zealot";"Gateway";293;2
"Unit";"Zealot";"Gateway";293;2
"Upgrade";"ProtossGroundWeaponsLevel3";"Forge";275;0
"Unit";"Zealot";"Gateway";309;2
"Unit";"Zealot";"Gateway";309;2
"Unit";"Zealot";"Gateway";309;2
"Unit";"Zealot";"Gateway";309;2
"Unit";"Zealot";"Gateway";309;2
"Unit";"Zealot";"Gateway";309;2
"Unit";"Zealot";"Gateway";309;2
"Unit";"Carrier";"Stargate";293;6
"Unit";"Carrier";"Stargate";293;6
"Unit";"Zealot";"Gateway";323;2
"Unit";"Zealot";"Gateway";323;2
