"type";"unit_name";"on_building";"total_supply";"supply"
"Building";"Pylon";NA;13;0
"Building";"Assimilator";NA;14;0
"Building";"Gateway";NA;16;0
"Building";"Assimilator";NA;21;0
"Building";"Pylon";NA;21;0
"Building";"CyberneticsCore";NA;20;0
"Unit";"Adept";"Gateway";22;2
"Building";"Nexus";NA;20;0
"Unit";"Adept";"Gateway";24;2
"Building";"Stargate";NA;23;0
"Unit";"Oracle";"Stargate";30;3
"Building";"Pylon";NA;36;0
"Unit";"Phoenix";"Stargate";37;2
"Building";"Assimilator";NA;41;0
"Building";"Assimilator";NA;41;0
"Building";"Pylon";NA;47;0
"Unit";"Oracle";"Stargate";47;3
"Building";"Gateway";NA;43;0
"Building";"Pylon";NA;51;0
"Building";"Pylon";NA;58;0
"Building";"FleetBeacon";NA;52;0
"Building";"Pylon";NA;58;0
"Building";"Stargate";NA;56;0
"Building";"OracleStasisTrap";NA;62;0
"Building";"Pylon";NA;62;0
"Building";"Pylon";NA;62;0
"Building";"Nexus";NA;58;0
"Building";"OracleStasisTrap";NA;65;0
"Building";"Assimilator";NA;64;0
"Building";"Assimilator";NA;64;0
"Unit";"Zealot";"Gateway";66;2
"Building";"Pylon";NA;65;0
"Upgrade";"ProtossAirWeaponsLevel1";"CyberneticsCore";59;0
"Unit";"Zealot";"Gateway";70;2
"Unit";"Carrier";"Stargate";60;6
"Unit";"Carrier";"Stargate";60;6
"Building";"Pylon";NA;70;0
"Building";"ShieldBattery";NA;70;0
"Building";"Pylon";NA;86;0
"Unit";"Sentry";"Gateway";88;2
"Building";"Pylon";NA;88;0
"Unit";"Mothership";"Mothership Core";66;6
"Building";"Pylon";NA;95;0
"Building";"Stargate";NA;92;0
"Building";"Pylon";NA;103;0
"Building";"Forge";NA;95;0
"Unit";"Carrier";"Stargate";73;6
"Unit";"Phoenix";"Stargate";104;2
"Unit";"Carrier";"Stargate";86;6
"Building";"Nexus";NA;102;0
"Building";"Pylon";NA;121;0
"Building";"PhotonCannon";NA;121;0
"Building";"PhotonCannon";NA;121;0
"Building";"PhotonCannon";NA;121;0
"Building";"Pylon";NA;121;0
"Building";"PhotonCannon";NA;121;0
"Building";"PhotonCannon";NA;121;0
"Building";"Assimilator";NA;121;0
"Building";"PhotonCannon";NA;121;0
"Building";"PhotonCannon";NA;121;0
"Building";"Assimilator";NA;121;0
"Building";"Pylon";NA;121;0
"Unit";"Carrier";"Stargate";104;6
"Unit";"Carrier";"Stargate";104;6
"Building";"Stargate";NA;121;0
"Unit";"Carrier";"Stargate";112;6
"Upgrade";"ProtossAirWeaponsLevel2";"CyberneticsCore";118;0
"Unit";"Oracle";"Stargate";127;3
"Unit";"Oracle";"Stargate";127;3
"Building";"Pylon";NA;139;0
"Building";"Pylon";NA;139;0
"Building";"ShieldBattery";NA;139;0
"Building";"PhotonCannon";NA;139;0
"Building";"Pylon";NA;139;0
"Upgrade";"ProtossShieldsLevel1";"Forge";121;0
"Building";"TwilightCouncil";NA;139;0
"Building";"Gateway";NA;145;0
"Building";"Gateway";NA;145;0
"Building";"Gateway";NA;145;0
"Building";"Gateway";NA;145;0
"Building";"Gateway";NA;145;0
"Building";"Gateway";NA;145;0
"Building";"Gateway";NA;145;0
"Unit";"Carrier";"Stargate";133;6
"Building";"OracleStasisTrap";NA;145;0
"Unit";"Carrier";"Stargate";139;6
"Building";"OracleStasisTrap";NA;157;0
"Building";"RoboticsFacility";NA;145;0
"Building";"TemplarArchive";NA;145;0
"Building";"Gateway";NA;145;0
"Building";"Pylon";NA;157;0
"Building";"HighTemplar";NA;157;0
"Building";"HighTemplar";NA;157;0
"Building";"HighTemplar";NA;157;0
"Building";"HighTemplar";NA;157;0
"Building";"HighTemplar";NA;157;0
"Building";"HighTemplar";NA;157;0
"Building";"HighTemplar";NA;157;0
"Building";"PhotonCannon";NA;157;0
"Unit";"Archon";"High Templar";157;0
"Building";"PhotonCannon";NA;157;0
"Building";"PhotonCannon";NA;157;0
"Building";"DarkShrine";NA;145;0
"Building";"PhotonCannon";NA;157;0
"Building";"ShieldBattery";NA;157;0
"Upgrade";"ProtossShieldsLevel2";"Forge";145;0
"Unit";"Observer";"Robotics Facility";157;1
"Building";"DarkTemplar";NA;157;0
"Building";"DarkTemplar";NA;157;0
"Upgrade";"Charge";"TwilightCouncil";157;0
"Building";"DarkTemplar";NA;157;0
"Building";"Nexus";NA;157;0
"Building";"PhotonCannon";NA;157;0
"Building";"PhotonCannon";NA;157;0
"Building";"PhotonCannon";NA;157;0
"Building";"PhotonCannon";NA;157;0
"Building";"PhotonCannon";NA;157;0
"Building";"OracleStasisTrap";NA;158;0
"Upgrade";"ProtossAirWeaponsLevel3";"CyberneticsCore";145;0
"Unit";"Observer";"Robotics Facility";157;1
"Building";"ShieldBattery";NA;157;0
"Building";"PhotonCannon";NA;159;0
"Building";"PhotonCannon";NA;159;0
"Building";"Assimilator";NA;159;0
"Building";"Assimilator";NA;159;0
"Building";"OracleStasisTrap";NA;159;0
"Building";"OracleStasisTrap";NA;159;0
"Building";"DarkTemplar";NA;159;0
"Unit";"Zealot";"Gateway";159;2
"Unit";"Zealot";"Gateway";159;2
"Unit";"Zealot";"Gateway";159;2
"Unit";"Zealot";"Gateway";159;2
"Unit";"Zealot";"Gateway";159;2
"Building";"Pylon";NA;159;0
"Upgrade";"ProtossAirArmorsLevel1";"CyberneticsCore";159;0
"Building";"Pylon";NA;169;0
"Building";"PhotonCannon";NA;169;0
"Building";"PhotonCannon";NA;169;0
"Building";"PhotonCannon";NA;169;0
"Building";"PhotonCannon";NA;169;0
"Building";"Pylon";NA;169;0
"Upgrade";"ProtossShieldsLevel3";"Forge";159;0
"Building";"OracleStasisTrap";NA;169;0
"Building";"Nexus";NA;169;0
"Building";"DarkTemplar";NA;169;0
"Unit";"Zealot";"Gateway";169;2
"Unit";"Zealot";"Gateway";169;2
"Unit";"Zealot";"Gateway";169;2
"Unit";"Zealot";"Gateway";169;2
"Unit";"Zealot";"Gateway";169;2
"Building";"Pylon";NA;169;0
"Unit";"Zealot";"Gateway";169;2
"Unit";"Zealot";"Gateway";169;2
"Building";"PhotonCannon";NA;169;0
"Building";"PhotonCannon";NA;169;0
"Building";"PhotonCannon";NA;169;0
"Building";"PhotonCannon";NA;169;0
"Building";"PhotonCannon";NA;169;0
"Building";"Pylon";NA;183;0
"Building";"PhotonCannon";NA;169;0
"Building";"RoboticsBay";NA;169;0
"Building";"PhotonCannon";NA;169;0
"Building";"PhotonCannon";NA;169;0
"Upgrade";"ProtossAirArmorsLevel2";"CyberneticsCore";169;0
"Building";"Nexus";NA;169;0
"Upgrade";"ProtossGroundWeaponsLevel1";"Forge";169;0
"Building";"HighTemplar";NA;183;0
"Building";"HighTemplar";NA;183;0
"Building";"DarkTemplar";NA;183;0
"Unit";"Zealot";"Gateway";183;2
"Unit";"Zealot";"Gateway";183;2
"Unit";"Zealot";"Gateway";183;2
"Unit";"Zealot";"Gateway";183;2
"Unit";"Zealot";"Gateway";183;2
"Unit";"Zealot";"Gateway";183;2
"Unit";"Zealot";"Gateway";183;2
"Building";"OracleStasisTrap";NA;197;0
"Building";"Nexus";NA;183;0
"Building";"PhotonCannon";NA;183;0
"Building";"PhotonCannon";NA;183;0
"Building";"Pylon";NA;197;0
"Building";"PhotonCannon";NA;183;0
"Building";"PhotonCannon";NA;183;0
"Building";"PhotonCannon";NA;183;0
"Building";"PhotonCannon";NA;185;0
"Building";"DarkTemplar";NA;197;0
"Building";"OracleStasisTrap";NA;197;0
"Building";"PhotonCannon";NA;197;0
"Building";"PhotonCannon";NA;197;0
"Building";"PhotonCannon";NA;197;0
"Building";"Assimilator";NA;197;0
"Building";"PhotonCannon";NA;197;0
"Building";"PhotonCannon";NA;197;0
"Building";"Assimilator";NA;197;0
"Building";"PhotonCannon";NA;197;0
"Building";"OracleStasisTrap";NA;197;0
"Building";"PhotonCannon";NA;197;0
"Unit";"Observer";"Robotics Facility";197;1
"Building";"OracleStasisTrap";NA;198;0
"Upgrade";"ProtossGroundWeaponsLevel2";"Forge";197;0
"Building";"OracleStasisTrap";NA;198;0
"Building";"DarkTemplar";NA;198;0
"Unit";"Zealot";"Gateway";198;2
"Unit";"Zealot";"Gateway";198;2
"Unit";"Zealot";"Gateway";198;2
"Unit";"Zealot";"Gateway";198;2
"Unit";"Zealot";"Gateway";198;2
"Unit";"Zealot";"Gateway";198;2
"Building";"DarkTemplar";NA;210;0
"Upgrade";"ProtossAirArmorsLevel3";"CyberneticsCore";197;0
"Building";"DarkTemplar";NA;210;0
"Upgrade";"GraviticDrive";"RoboticsBay";198;0
"Building";"OracleStasisTrap";NA;210;0
"Building";"DarkTemplar";NA;210;0
"Unit";"Zealot";"Gateway";210;2
"Unit";"Zealot";"Gateway";210;2
"Unit";"Zealot";"Gateway";210;2
"Unit";"Zealot";"Gateway";210;2
"Building";"Assimilator";NA;210;0
"Building";"Assimilator";NA;210;0
"Building";"OracleStasisTrap";NA;218;0
"Building";"DarkTemplar";NA;218;0
"Unit";"Zealot";"Gateway";218;2
"Unit";"Zealot";"Gateway";218;2
"Unit";"Zealot";"Gateway";218;2
"Unit";"Zealot";"Gateway";218;2
"Unit";"Zealot";"Gateway";218;2
"Building";"OracleStasisTrap";NA;228;0
"Building";"DarkTemplar";NA;228;0
"Unit";"Zealot";"Gateway";228;2
"Unit";"Zealot";"Gateway";230;2
"Unit";"Zealot";"Gateway";230;2
"Building";"DarkTemplar";NA;234;0
"Unit";"Zealot";"Gateway";234;2
"Unit";"Zealot";"Gateway";234;2
"Upgrade";"ProtossGroundWeaponsLevel3";"Forge";218;0
"Unit";"Oracle";"Stargate";238;3
"Unit";"Oracle";"Stargate";238;3
"Building";"OracleStasisTrap";NA;244;0
"Building";"OracleStasisTrap";NA;244;0
"Upgrade";"ProtossGroundArmorsLevel1";"Forge";238;0
"Building";"PhotonCannon";NA;244;0
"Building";"PhotonCannon";NA;244;0
"Building";"PhotonCannon";NA;244;0
"Building";"PhotonCannon";NA;244;0
"Building";"PhotonCannon";NA;244;0
"Building";"PhotonCannon";NA;244;0
"Building";"PhotonCannon";NA;244;0
"Building";"PhotonCannon";NA;244;0
"Building";"DarkTemplar";NA;244;0
"Unit";"Zealot";"Gateway";244;2
"Unit";"Zealot";"Gateway";244;2
"Unit";"Zealot";"Gateway";244;2
"Unit";"Zealot";"Gateway";244;2
"Unit";"Zealot";"Gateway";244;2
"Unit";"Zealot";"Gateway";244;2
"Unit";"Zealot";"Gateway";244;2
"Unit";"Zealot";"Gateway";258;2
"Unit";"Zealot";"Gateway";258;2
"Unit";"Zealot";"Gateway";258;2
"Unit";"Zealot";"Gateway";258;2
"Unit";"Zealot";"Gateway";258;2
"Unit";"Zealot";"Gateway";258;2
"Unit";"Zealot";"Gateway";258;2
"Unit";"Zealot";"Gateway";258;2
"Unit";"Zealot";"Gateway";258;2
"Unit";"Zealot";"Gateway";258;2
"Upgrade";"ProtossGroundArmorsLevel2";"Forge";244;0
"Building";"HighTemplar";NA;278;0
"Building";"HighTemplar";NA;278;0
"Building";"HighTemplar";NA;278;0
"Building";"HighTemplar";NA;278;0
"Building";"HighTemplar";NA;278;0
"Building";"HighTemplar";NA;278;0
"Unit";"Oracle";"Stargate";278;3
"Unit";"Oracle";"Stargate";278;3
"Unit";"Observer";"Robotics Facility";284;1
"Building";"DarkTemplar";NA;284;0
"Unit";"Zealot";"Gateway";284;2
"Unit";"Zealot";"Gateway";284;2
"Unit";"Zealot";"Gateway";284;2
"Unit";"Zealot";"Gateway";291;2
"Unit";"Zealot";"Gateway";291;2
"Unit";"Zealot";"Gateway";291;2
"Unit";"Zealot";"Gateway";291;2
"Unit";"Zealot";"Gateway";291;2
"Unit";"Zealot";"Gateway";291;2
"Building";"Pylon";NA;285;0
"Unit";"Mothership";"Mothership Core";278;6
"Building";"HighTemplar";NA;309;0
"Building";"HighTemplar";NA;309;0
"Building";"Nexus";NA;284;0
"Building";"DarkTemplar";NA;309;0
"Unit";"Zealot";"Gateway";309;2
"Unit";"Zealot";"Gateway";309;2
"Unit";"Zealot";"Gateway";309;2
"Unit";"Zealot";"Gateway";309;2
"Unit";"Zealot";"Gateway";309;2
"Unit";"Zealot";"Gateway";309;2
"Unit";"Zealot";"Gateway";309;2
"Unit";"Zealot";"Gateway";309;2
"Unit";"Zealot";"Gateway";309;2
"Building";"PhotonCannon";NA;309;0
"Upgrade";"ProtossGroundArmorsLevel3";"Forge";284;0
"Building";"HighTemplar";NA;327;0
"Building";"HighTemplar";NA;327;0
"Building";"HighTemplar";NA;327;0
"Building";"HighTemplar";NA;327;0
"Building";"HighTemplar";NA;327;0
"Building";"HighTemplar";NA;327;0
"Building";"HighTemplar";NA;327;0
"Building";"HighTemplar";NA;327;0
"Building";"HighTemplar";NA;327;0
"Building";"HighTemplar";NA;327;0
"Unit";"Archon";"High Templar";327;0
"Unit";"Archon";"High Templar";327;0
"Unit";"Archon";"High Templar";327;0
"Unit";"Archon";"High Templar";327;0
"Unit";"Archon";"High Templar";327;0
"Building";"PhotonCannon";NA;327;0
"Building";"PhotonCannon";NA;327;0
"Building";"PhotonCannon";NA;327;0
"Building";"PhotonCannon";NA;327;0
"Building";"OracleStasisTrap";NA;327;0
"Building";"DarkTemplar";NA;327;0
"Unit";"Zealot";"Gateway";327;2
"Unit";"Zealot";"Gateway";327;2
"Unit";"Zealot";"Gateway";327;2
"Unit";"Zealot";"Gateway";327;2
"Unit";"Zealot";"Gateway";327;2
"Unit";"Zealot";"Gateway";327;2
"Unit";"Zealot";"Gateway";327;2
"Unit";"Zealot";"Gateway";327;2
"Unit";"Zealot";"Gateway";327;2
"Building";"Pylon";NA;327;0
"Building";"Pylon";NA;327;0
"Building";"Pylon";NA;327;0
"Building";"Assimilator";NA;327;0
"Building";"Assimilator";NA;327;0
"Building";"HighTemplar";NA;345;0
"Building";"HighTemplar";NA;345;0
"Building";"HighTemplar";NA;345;0
"Building";"HighTemplar";NA;345;0
"Building";"HighTemplar";NA;345;0
"Building";"HighTemplar";NA;345;0
"Building";"HighTemplar";NA;345;0
"Building";"HighTemplar";NA;345;0
"Building";"HighTemplar";NA;345;0
"Building";"Nexus";NA;327;0
"Unit";"Archon";"High Templar";345;0
"Unit";"Archon";"High Templar";345;0
"Building";"Nexus";NA;327;0
"Unit";"Archon";"High Templar";345;0
