"type";"unit_name";"on_building";"total_supply";"supply"
"Building";"Pylon";NA;13;0
"Building";"Assimilator";NA;15;0
"Building";"Gateway";NA;15;0
"Building";"Assimilator";NA;21;0
"Building";"Pylon";NA;21;0
"Building";"CyberneticsCore";NA;20;0
"Unit";"Adept";"Gateway";22;2
"Building";"Nexus";NA;19;0
"Unit";"Adept";"Gateway";27;2
"Building";"Stargate";NA;23;0
"Building";"Pylon";NA;36;0
"Unit";"Oracle";"Stargate";31;3
"Unit";"Adept";"Gateway";37;2
"Unit";"Phoenix";"Stargate";38;2
"Building";"ShieldBattery";NA;42;0
"Building";"Gateway";NA;36;0
"Building";"Assimilator";NA;44;0
"Building";"Assimilator";NA;44;0
"Building";"Pylon";NA;50;0
"Building";"RoboticsFacility";NA;47;0
"Building";"Pylon";NA;54;0
"Building";"TwilightCouncil";NA;51;0
"Building";"Pylon";NA;55;0
"Building";"Gateway";NA;53;0
"Building";"Gateway";NA;53;0
"Building";"Pylon";NA;57;0
"Building";"TemplarArchive";NA;57;0
"Building";"Forge";NA;57;0
"Building";"HighTemplar";NA;58;0
"Building";"HighTemplar";NA;58;0
"Building";"HighTemplar";NA;58;0
"Building";"HighTemplar";NA;58;0
"Unit";"Observer";"Robotics Facility";57;1
"Unit";"Archon";"High Templar";60;0
"Unit";"Archon";"High Templar";60;0
"Building";"Pylon";NA;60;0
"Building";"Gateway";NA;57;0
"Building";"OracleStasisTrap";NA;62;0
"Building";"Gateway";NA;57;0
"Building";"Nexus";NA;57;0
"Building";"OracleStasisTrap";NA;63;0
"Building";"Pylon";NA;61;0
"Upgrade";"Charge";"TwilightCouncil";57;0
"Unit";"Immortal";"Robotics Facility";58;4
"Unit";"Zealot";"Gateway";75;2
"Unit";"Zealot";"Gateway";75;2
"Unit";"Zealot";"Gateway";75;2
"Unit";"Zealot";"Gateway";75;2
"Unit";"Zealot";"Gateway";75;2
"Unit";"Zealot";"Gateway";75;2
"Unit";"Immortal";"Robotics Facility";63;4
"Building";"Assimilator";NA;72;0
"Building";"Assimilator";NA;72;0
"Building";"RoboticsFacility";NA;70;0
"Building";"ShieldBattery";NA;92;0
"Unit";"Zealot";"Gateway";92;2
"Unit";"Zealot";"Gateway";92;2
"Unit";"Zealot";"Gateway";92;2
"Unit";"Zealot";"Gateway";92;2
"Unit";"Immortal";"Robotics Facility";74;4
"Unit";"Zealot";"Gateway";92;2
"Unit";"Zealot";"Gateway";92;2
"Building";"ShieldBattery";NA;92;0
"Upgrade";"ProtossGroundWeaponsLevel1";"Forge";62;0
"Building";"OracleStasisTrap";NA;109;0
"Unit";"Immortal";"Robotics Facility";92;4
"Building";"Pylon";NA;109;0
"Building";"Pylon";NA;109;0
"Unit";"Immortal";"Robotics Facility";108;4
"Building";"Pylon";NA;109;0
"Unit";"Zealot";"Gateway";115;2
"Unit";"Zealot";"Gateway";115;2
"Unit";"Zealot";"Gateway";115;2
"Unit";"Zealot";"Gateway";115;2
"Unit";"Zealot";"Gateway";119;2
"Building";"Pylon";NA;111;0
"Building";"Pylon";NA;111;0
"Building";"HighTemplar";NA;130;0
"Building";"HighTemplar";NA;130;0
"Building";"HighTemplar";NA;130;0
"Building";"HighTemplar";NA;130;0
"Building";"HighTemplar";NA;130;0
"Building";"HighTemplar";NA;130;0
"Unit";"Immortal";"Robotics Facility";115;4
"Building";"CyberneticsCore";NA;130;0
"Building";"Pylon";NA;134;0
"Unit";"Zealot";"Gateway";135;2
"Unit";"Zealot";"Gateway";135;2
"Unit";"Zealot";"Gateway";135;2
"Unit";"Zealot";"Gateway";135;2
"Unit";"Zealot";"Gateway";135;2
"Unit";"Zealot";"Gateway";135;2
"Unit";"Immortal";"Robotics Facility";134;4
"Unit";"Immortal";"Robotics Facility";134;4
"Upgrade";"ProtossGroundWeaponsLevel2";"Forge";111;0
"Building";"Pylon";NA;147;0
"Building";"Pylon";NA;147;0
"Unit";"Zealot";"Gateway";155;2
"Unit";"Zealot";"Gateway";155;2
"Unit";"Zealot";"Gateway";155;2
"Unit";"Zealot";"Gateway";155;2
"Unit";"Zealot";"Gateway";155;2
"Building";"Nexus";NA;134;0
"Building";"Gateway";NA;135;0
"Building";"Gateway";NA;135;0
"Building";"PhotonCannon";NA;155;0
"Building";"PhotonCannon";NA;155;0
"Building";"FleetBeacon";NA;155;0
"Unit";"Zealot";"Gateway";167;2
"Unit";"Archon";"High Templar";167;0
"Unit";"Archon";"High Templar";167;0
"Unit";"Zealot";"Gateway";167;2
"Unit";"Archon";"High Templar";167;0
"Unit";"Zealot";"Gateway";167;2
"Unit";"Zealot";"Gateway";167;2
"Unit";"Zealot";"Gateway";167;2
"Unit";"Zealot";"Gateway";167;2
"Building";"HighTemplar";NA;179;0
"Building";"HighTemplar";NA;179;0
"Building";"HighTemplar";NA;179;0
"Building";"HighTemplar";NA;179;0
"Building";"HighTemplar";NA;179;0
"Building";"HighTemplar";NA;179;0
"Unit";"Immortal";"Robotics Facility";167;4
"Unit";"Immortal";"Robotics Facility";167;4
"Building";"Assimilator";NA;179;0
"Building";"Assimilator";NA;179;0
"Unit";"Sentry";"Gateway";187;2
"Unit";"Sentry";"Gateway";187;2
"Unit";"Zealot";"Gateway";191;2
"Unit";"Zealot";"Gateway";191;2
"Unit";"Zealot";"Gateway";192;2
"Unit";"Zealot";"Gateway";193;2
"Unit";"Zealot";"Gateway";193;2
"Unit";"Zealot";"Gateway";193;2
"Unit";"Immortal";"Robotics Facility";179;4
"Building";"Pylon";NA;191;0
"Unit";"Immortal";"Robotics Facility";179;4
"Building";"Gateway";NA;187;0
"Unit";"Zealot";"Gateway";216;2
"Building";"Gateway";NA;187;0
"Unit";"Zealot";"Gateway";216;2
"Unit";"Zealot";"Gateway";216;2
"Unit";"Oracle";"Stargate";191;3
"Upgrade";"ProtossGroundWeaponsLevel3";"Forge";167;0
"Unit";"Immortal";"Robotics Facility";191;4
"Building";"ShieldBattery";NA;216;0
"Unit";"Immortal";"Robotics Facility";210;4
"Building";"ShieldBattery";NA;216;0
"Unit";"Archon";"High Templar";229;0
"Unit";"Archon";"High Templar";229;0
"Unit";"Zealot";"Gateway";233;2
"Unit";"Zealot";"Gateway";233;2
"Unit";"Zealot";"Gateway";233;2
"Unit";"Zealot";"Gateway";233;2
"Unit";"Zealot";"Gateway";233;2
"Unit";"Zealot";"Gateway";233;2
"Unit";"Zealot";"Gateway";233;2
"Unit";"Zealot";"Gateway";233;2
"Unit";"Zealot";"Gateway";233;2
"Unit";"Zealot";"Gateway";233;2
