"type";"unit_name";"on_building";"total_supply";"supply"
"Building";"Pylon";NA;13;0
"Building";"Assimilator";NA;17;0
"Building";"Assimilator";NA;17;0
"Building";"Gateway";NA;15;0
"Building";"Pylon";NA;21;0
"Building";"CyberneticsCore";NA;20;0
"Unit";"Stalker";"Gateway";24;2
"Building";"Pylon";NA;25;0
"Building";"Stargate";NA;24;0
"Building";"Nexus";NA;23;0
"Building";"Forge";NA;26;0
"Unit";"Sentry";"Gateway";26;2
"Unit";"Oracle";"Stargate";29;3
"Building";"Assimilator";NA;39;0
"Building";"Assimilator";NA;40;0
"Building";"ShieldBattery";NA;42;0
"Building";"PhotonCannon";NA;42;0
"Building";"PhotonCannon";NA;42;0
"Building";"FleetBeacon";NA;44;0
"Building";"Stargate";NA;46;0
"Building";"Pylon";NA;50;0
"Building";"Pylon";NA;50;0
"Building";"Pylon";NA;50;0
"Unit";"Phoenix";"Stargate";53;2
"Building";"Pylon";NA;55;0
"Building";"Nexus";NA;50;0
"Building";"Pylon";NA;61;0
"Building";"OracleStasisTrap";NA;63;0
"Building";"TwilightCouncil";NA;61;0
"Unit";"Carrier";"Stargate";51;6
"Unit";"Carrier";"Stargate";51;6
"Building";"Gateway";NA;61;0
"Building";"Gateway";NA;62;0
"Building";"Gateway";NA;62;0
"Building";"Assimilator";NA;81;0
"Building";"Assimilator";NA;81;0
"Building";"Gateway";NA;63;0
"Building";"Gateway";NA;63;0
"Building";"Gateway";NA;63;0
"Upgrade";"ProtossAirWeaponsLevel1";"CyberneticsCore";62;0
"Building";"PhotonCannon";NA;81;0
"Building";"PhotonCannon";NA;82;0
"Building";"TemplarArchive";NA;82;0
"Building";"Pylon";NA;82;0
"Building";"Gateway";NA;81;0
"Building";"Pylon";NA;82;0
"Building";"Gateway";NA;81;0
"Building";"Pylon";NA;82;0
"Upgrade";"Charge";"TwilightCouncil";82;0
"Unit";"Mothership";"Mothership Core";82;6
"Building";"Pylon";NA;95;0
"Building";"HighTemplar";NA;95;0
"Building";"HighTemplar";NA;95;0
"Building";"HighTemplar";NA;95;0
"Building";"HighTemplar";NA;95;0
"Building";"PhotonCannon";NA;95;0
"Building";"Pylon";NA;95;0
"Building";"Pylon";NA;95;0
"Building";"RoboticsFacility";NA;95;0
"Unit";"Zealot";"Gateway";95;2
"Building";"PhotonCannon";NA;95;0
"Building";"PhotonCannon";NA;95;0
"Building";"ShieldBattery";NA;95;0
"Building";"HighTemplar";NA;97;0
"Building";"HighTemplar";NA;97;0
"Unit";"Phoenix";"Stargate";95;2
"Building";"HighTemplar";NA;97;0
"Building";"PhotonCannon";NA;95;0
"Unit";"Zealot";"Gateway";97;2
"Building";"PhotonCannon";NA;95;0
"Building";"Pylon";NA;97;0
"Building";"PhotonCannon";NA;97;0
"Building";"PhotonCannon";NA;97;0
"Building";"Assimilator";NA;97;0
"Building";"ShieldBattery";NA;97;0
"Building";"ShieldBattery";NA;97;0
"Building";"Assimilator";NA;99;0
"Unit";"Zealot";"Gateway";101;2
"Unit";"Zealot";"Gateway";101;2
"Unit";"Zealot";"Gateway";101;2
"Unit";"Zealot";"Gateway";101;2
"Unit";"Zealot";"Gateway";101;2
"Unit";"Zealot";"Gateway";101;2
"Building";"PhotonCannon";NA;97;0
"Building";"PhotonCannon";NA;97;0
"Upgrade";"ProtossGroundWeaponsLevel1";"Forge";95;0
"Building";"Nexus";NA;95;0
"Unit";"Observer";"Robotics Facility";101;1
"Upgrade";"ProtossAirWeaponsLevel2";"CyberneticsCore";95;0
"Building";"Pylon";NA;113;0
"Building";"PhotonCannon";NA;113;0
"Building";"Stargate";NA;101;0
"Building";"PhotonCannon";NA;113;0
"Building";"ShieldBattery";NA;113;0
"Building";"ShieldBattery";NA;113;0
"Building";"Stargate";NA;113;0
"Unit";"Zealot";"Gateway";114;2
"Building";"Pylon";NA;114;0
"Building";"Pylon";NA;114;0
"Unit";"Zealot";"Gateway";116;2
"Unit";"Zealot";"Gateway";116;2
"Unit";"Zealot";"Gateway";116;2
"Unit";"Zealot";"Gateway";116;2
"Unit";"Zealot";"Gateway";116;2
"Unit";"Zealot";"Gateway";116;2
"Unit";"Zealot";"Gateway";116;2
"Unit";"Zealot";"Gateway";116;2
"Unit";"Zealot";"Gateway";116;2
"Unit";"Carrier";"Stargate";114;6
"Unit";"Zealot";"Gateway";140;2
"Unit";"Zealot";"Gateway";140;2
"Unit";"Zealot";"Gateway";140;2
"Unit";"Zealot";"Gateway";140;2
"Unit";"Zealot";"Gateway";148;2
"Unit";"Zealot";"Gateway";148;2
"Unit";"Zealot";"Gateway";148;2
"Unit";"Observer";"Robotics Facility";140;1
"Unit";"Carrier";"Stargate";114;6
"Upgrade";"ProtossGroundWeaponsLevel2";"Forge";114;0
"Unit";"Zealot";"Gateway";154;2
"Unit";"Carrier";"Stargate";114;6
"Unit";"Carrier";"Stargate";116;6
"Upgrade";"ProtossAirWeaponsLevel3";"CyberneticsCore";114;0
"Unit";"Zealot";"Gateway";175;2
"Unit";"Zealot";"Gateway";177;2
"Unit";"Zealot";"Gateway";177;2
"Unit";"Zealot";"Gateway";177;2
"Unit";"Zealot";"Gateway";177;2
"Unit";"Zealot";"Gateway";177;2
"Unit";"Zealot";"Gateway";177;2
"Building";"Pylon";NA;177;0
"Unit";"Zealot";"Gateway";189;2
"Unit";"Zealot";"Gateway";189;2
"Unit";"Zealot";"Gateway";189;2
"Unit";"Zealot";"Gateway";189;2
"Unit";"Zealot";"Gateway";189;2
"Unit";"Zealot";"Gateway";189;2
"Building";"HighTemplar";NA;201;0
"Building";"HighTemplar";NA;201;0
"Building";"HighTemplar";NA;201;0
"Unit";"Carrier";"Stargate";175;6
"Unit";"Carrier";"Stargate";175;6
"Building";"DarkShrine";NA;177;0
"Unit";"Carrier";"Stargate";175;6
"Unit";"Carrier";"Stargate";175;6
"Building";"Nexus";NA;177;0
"Upgrade";"ProtossAirArmorsLevel1";"CyberneticsCore";177;0
"Unit";"Zealot";"Gateway";225;2
"Unit";"Zealot";"Gateway";225;2
"Unit";"Zealot";"Gateway";225;2
"Unit";"Zealot";"Gateway";225;2
"Unit";"Zealot";"Gateway";225;2
"Unit";"Zealot";"Gateway";225;2
"Unit";"Zealot";"Gateway";237;2
"Unit";"Zealot";"Gateway";237;2
"Unit";"Zealot";"Gateway";237;2
"Unit";"Zealot";"Gateway";237;2
"Unit";"Zealot";"Gateway";237;2
"Unit";"Zealot";"Gateway";237;2
"Unit";"Zealot";"Gateway";237;2
"Unit";"Zealot";"Gateway";237;2
"Unit";"Zealot";"Gateway";237;2
"Upgrade";"ProtossGroundWeaponsLevel3";"Forge";189;0
"Building";"Assimilator";NA;237;0
"Building";"Assimilator";NA;237;0
"Building";"PhotonCannon";NA;237;0
"Building";"PhotonCannon";NA;237;0
"Building";"ShieldBattery";NA;237;0
"Building";"PhotonCannon";NA;255;0
"Unit";"Zealot";"Gateway";255;2
"Unit";"Zealot";"Gateway";255;2
"Unit";"Zealot";"Gateway";255;2
"Unit";"Zealot";"Gateway";255;2
"Unit";"Zealot";"Gateway";255;2
"Unit";"Zealot";"Gateway";255;2
"Unit";"Zealot";"Gateway";255;2
"Unit";"Zealot";"Gateway";255;2
"Unit";"Zealot";"Gateway";255;2
