"type";"unit_name";"on_building";"total_supply";"supply"
"Building";"Pylon";NA;13;0
"Building";"Pylon";NA;16;0
"Building";"Assimilator";NA;17;0
"Building";"Gateway";NA;15;0
"Building";"Assimilator";NA;22;0
"Building";"CyberneticsCore";NA;21;0
"Building";"Pylon";NA;23;0
"Unit";"Adept";"Gateway";24;2
"Building";"Nexus";NA;20;0
"Unit";"Adept";"Gateway";26;2
"Unit";"Adept";"Gateway";29;2
"Building";"Stargate";NA;28;0
"Building";"Gateway";NA;33;0
"Unit";"Oracle";"Stargate";37;3
"Building";"Assimilator";NA;43;0
"Building";"Assimilator";NA;43;0
"Building";"Pylon";NA;48;0
"Unit";"Phoenix";"Stargate";46;2
"Building";"TwilightCouncil";NA;43;0
"Building";"Pylon";NA;48;0
"Building";"Pylon";NA;51;0
"Building";"RoboticsFacility";NA;48;0
"Building";"OracleStasisTrap";NA;56;0
"Building";"TemplarArchive";NA;53;0
"Building";"Pylon";NA;56;0
"Building";"Gateway";NA;53;0
"Building";"Gateway";NA;56;0
"Building";"Pylon";NA;56;0
"Building";"Gateway";NA;56;0
"Building";"Gateway";NA;56;0
"Building";"Gateway";NA;56;0
"Unit";"Observer";"Robotics Facility";56;1
"Building";"OracleStasisTrap";NA;58;0
"Building";"HighTemplar";NA;60;0
"Building";"HighTemplar";NA;61;0
"Building";"HighTemplar";NA;61;0
"Building";"HighTemplar";NA;61;0
"Unit";"Archon";"High Templar";61;0
"Unit";"Archon";"High Templar";61;0
"Building";"Pylon";NA;60;0
"Building";"Forge";NA;59;0
"Building";"Pylon";NA;63;0
"Unit";"Zealot";"Gateway";65;2
"Unit";"Zealot";"Gateway";65;2
"Unit";"Zealot";"Gateway";65;2
"Unit";"Zealot";"Gateway";65;2
"Unit";"Zealot";"Gateway";65;2
"Unit";"Zealot";"Gateway";65;2
"Building";"Nexus";NA;56;0
"Unit";"Zealot";"Gateway";79;2
"Unit";"Immortal";"Robotics Facility";61;4
"Upgrade";"Charge";"TwilightCouncil";56;0
"Unit";"Zealot";"Gateway";88;2
"Unit";"Zealot";"Gateway";88;2
"Unit";"Zealot";"Gateway";88;2
"Unit";"Zealot";"Gateway";89;2
"Building";"HighTemplar";NA;99;0
"Building";"HighTemplar";NA;100;0
"Building";"HighTemplar";NA;100;0
"Building";"HighTemplar";NA;102;0
"Building";"Assimilator";NA;98;0
"Building";"Assimilator";NA;99;0
"Unit";"Archon";"High Templar";102;0
"Unit";"Zealot";"Gateway";102;2
"Unit";"Zealot";"Gateway";102;2
"Unit";"Zealot";"Gateway";102;2
"Building";"Pylon";NA;101;0
"Unit";"Archon";"High Templar";102;0
"Building";"Pylon";NA;102;0
"Building";"Pylon";NA;108;0
"Building";"HighTemplar";NA;111;0
"Building";"HighTemplar";NA;111;0
"Building";"Pylon";NA;108;0
"Building";"OracleStasisTrap";NA;112;0
"Unit";"Immortal";"Robotics Facility";102;4
"Building";"HighTemplar";NA;116;0
"Unit";"Observer";"Robotics Facility";112;1
"Unit";"Zealot";"Gateway";116;2
"Unit";"Zealot";"Gateway";116;2
"Unit";"Zealot";"Gateway";116;2
"Building";"OracleStasisTrap";NA;123;0
"Building";"RoboticsFacility";NA;112;0
"Unit";"Zealot";"Gateway";123;2
"Unit";"Zealot";"Gateway";123;2
"Unit";"Zealot";"Gateway";123;2
"Building";"Pylon";NA;123;0
"Building";"HighTemplar";NA;129;0
"Building";"HighTemplar";NA;129;0
"Building";"HighTemplar";NA;129;0
"Building";"HighTemplar";NA;129;0
"Unit";"Immortal";"Robotics Facility";123;4
"Building";"Pylon";NA;123;0
"Upgrade";"ProtossGroundWeaponsLevel1";"Forge";111;0
"Building";"Pylon";NA;123;0
"Unit";"Archon";"High Templar";133;0
"Unit";"Archon";"High Templar";133;0
"Unit";"Observer";"Robotics Facility";129;1
"Building";"Pylon";NA;133;0
"Unit";"Immortal";"Robotics Facility";129;4
"Building";"HighTemplar";NA;140;0
"Building";"HighTemplar";NA;140;0
"Building";"OracleStasisTrap";NA;140;0
"Building";"PhotonCannon";NA;133;0
"Building";"ShieldBattery";NA;133;0
"Unit";"Archon";"High Templar";140;0
"Unit";"Zealot";"Gateway";140;2
"Unit";"Zealot";"Gateway";140;2
"Unit";"Zealot";"Gateway";140;2
"Unit";"Zealot";"Gateway";140;2
"Unit";"Zealot";"Gateway";140;2
"Building";"PhotonCannon";NA;133;0
"Building";"PhotonCannon";NA;133;0
"Building";"PhotonCannon";NA;136;0
"Building";"Nexus";NA;123;0
"Building";"PhotonCannon";NA;136;0
"Building";"PhotonCannon";NA;136;0
"Building";"Gateway";NA;133;0
"Building";"Gateway";NA;133;0
"Building";"Gateway";NA;133;0
"Building";"DarkShrine";NA;129;0
"Unit";"Immortal";"Robotics Facility";140;4
"Unit";"Immortal";"Robotics Facility";140;4
"Building";"OracleStasisTrap";NA;154;0
"Building";"DarkTemplar";NA;158;0
"Building";"DarkTemplar";NA;158;0
"Building";"DarkTemplar";NA;158;0
"Unit";"Zealot";"Gateway";158;2
"Unit";"Zealot";"Gateway";158;2
"Unit";"Zealot";"Gateway";158;2
"Unit";"Zealot";"Gateway";158;2
"Unit";"Zealot";"Gateway";158;2
"Unit";"Zealot";"Gateway";158;2
"Unit";"Immortal";"Robotics Facility";150;4
"Building";"FleetBeacon";NA;150;0
"Building";"Pylon";NA;158;0
"Unit";"Immortal";"Robotics Facility";158;4
"Building";"Assimilator";NA;174;0
"Unit";"Immortal";"Robotics Facility";158;4
"Building";"Assimilator";NA;174;0
"Building";"HighTemplar";NA;178;0
"Building";"HighTemplar";NA;178;0
"Building";"HighTemplar";NA;178;0
"Upgrade";"ProtossGroundWeaponsLevel2";"Forge";150;0
"Unit";"Zealot";"Gateway";182;2
"Unit";"Zealot";"Gateway";182;2
"Unit";"Zealot";"Gateway";182;2
"Unit";"Zealot";"Gateway";182;2
"Unit";"Zealot";"Gateway";182;2
"Unit";"Zealot";"Gateway";182;2
"Unit";"Zealot";"Gateway";182;2
"Unit";"Zealot";"Gateway";196;2
"Unit";"Zealot";"Gateway";196;2
"Unit";"Zealot";"Gateway";196;2
"Unit";"Zealot";"Gateway";196;2
"Unit";"Zealot";"Gateway";196;2
"Unit";"Zealot";"Gateway";196;2
"Unit";"Zealot";"Gateway";196;2
"Unit";"Zealot";"Gateway";196;2
"Unit";"Archon";"High Templar";196;0
