"type";"unit_name";"on_building";"total_supply";"supply"
"Building";"Pylon";NA;13;0
"Building";"Assimilator";NA;16;0
"Building";"Gateway";NA;15;0
"Unit";"Zealot";"Gateway";18;2
"Building";"CyberneticsCore";NA;18;0
"Building";"Pylon";NA;18;0
"Unit";"Stalker";"Gateway";18;2
"Building";"Nexus";NA;18;0
"Unit";"Sentry";"Gateway";20;2
"Building";"ShieldBattery";NA;22;0
"Unit";"Adept";"Gateway";24;2
