"type";"unit_name";"on_building";"total_supply";"supply"
"Building";"Pylon";NA;13;0
"Building";"Assimilator";NA;16;0
"Building";"Gateway";NA;15;0
"Building";"Assimilator";NA;20;0
"Building";"Pylon";NA;20;0
"Building";"CyberneticsCore";NA;20;0
"Unit";"Adept";"Gateway";21;2
"Building";"Nexus";NA;19;0
"Unit";"Adept";"Gateway";26;2
"Building";"Stargate";NA;23;0
"Unit";"Adept";"Gateway";28;2
"Unit";"Phoenix";"Stargate";31;2
"Building";"Gateway";NA;28;0
"Unit";"Adept";"Gateway";34;2
"Unit";"Phoenix";"Stargate";37;2
"Building";"Assimilator";NA;42;0
"Building";"Assimilator";NA;42;0
"Building";"Pylon";NA;46;0
"Building";"ShieldBattery";NA;44;0
"Building";"ShieldBattery";NA;46;0
"Unit";"Phoenix";"Stargate";46;2
"Unit";"Phoenix";"Stargate";46;2
"Building";"Pylon";NA;51;0
"Building";"TwilightCouncil";NA;46;0
"Unit";"Adept";"Gateway";54;2
"Building";"Pylon";NA;54;0
"Unit";"Sentry";"Gateway";56;2
"Unit";"Phoenix";"Stargate";54;2
"Building";"Nexus";NA;46;0
"Building";"Gateway";NA;50;0
"Building";"Pylon";NA;60;0
"Unit";"Adept";"Gateway";64;2
"Unit";"Adept";"Gateway";66;2
"Building";"Pylon";NA;64;0
"Unit";"Adept";"Gateway";68;2
"Unit";"Phoenix";"Stargate";62;2
"Unit";"Phoenix";"Stargate";78;2
"Unit";"Adept";"Gateway";92;2
"Unit";"Adept";"Gateway";92;2
"Unit";"Adept";"Gateway";92;2
"Unit";"Phoenix";"Stargate";89;2
"Unit";"Adept";"Gateway";105;2
"Unit";"Adept";"Gateway";105;2
"Unit";"Adept";"Gateway";105;2
"Building";"Pylon";NA;100;0
"Building";"Pylon";NA;105;0
"Building";"Assimilator";NA;105;0
"Building";"Assimilator";NA;105;0
"Building";"RoboticsFacility";NA;92;0
"Building";"RoboticsFacility";NA;92;0
"Building";"Pylon";NA;111;0
"Building";"Gateway";NA;93;0
"Building";"Gateway";NA;100;0
"Building";"Gateway";NA;100;0
"Building";"ShieldBattery";NA;105;0
"Building";"ShieldBattery";NA;111;0
"Unit";"Adept";"Gateway";111;2
"Unit";"Adept";"Gateway";111;2
"Unit";"Adept";"Gateway";111;2
"Building";"Forge";NA;111;0
"Building";"Forge";NA;111;0
"Building";"TemplarArchive";NA;111;0
"Unit";"Immortal";"Robotics Facility";111;4
"Unit";"Immortal";"Robotics Facility";111;4
"Building";"HighTemplar";NA;118;0
"Building";"HighTemplar";NA;118;0
"Building";"HighTemplar";NA;118;0
"Building";"Pylon";NA;117;0
"Building";"Pylon";NA;117;0
"Building";"Pylon";NA;117;0
"Unit";"Zealot";"Gateway";127;2
"Unit";"Zealot";"Gateway";127;2
"Building";"HighTemplar";NA;131;0
"Unit";"Immortal";"Robotics Facility";118;4
"Unit";"Immortal";"Robotics Facility";122;4
"Building";"Assimilator";NA;127;0
"Building";"PhotonCannon";NA;127;0
"Building";"ShieldBattery";NA;127;0
"Unit";"Zealot";"Gateway";141;2
"Building";"Assimilator";NA;131;0
"Unit";"Zealot";"Gateway";141;2
"Unit";"Zealot";"Gateway";141;2
"Unit";"Immortal";"Robotics Facility";132;4
"Unit";"Immortal";"Robotics Facility";132;4
"Building";"Nexus";NA;127;0
"Unit";"Zealot";"Gateway";159;2
"Unit";"Zealot";"Gateway";159;2
"Unit";"Zealot";"Gateway";159;2
"Unit";"Zealot";"Gateway";159;2
"Unit";"Zealot";"Gateway";167;2
"Unit";"Zealot";"Gateway";167;2
"Upgrade";"ProtossGroundArmorsLevel1";"Forge";133;0
"Upgrade";"ProtossGroundWeaponsLevel1";"Forge";133;0
"Unit";"Immortal";"Robotics Facility";158;4
"Unit";"Immortal";"Robotics Facility";158;4
"Building";"Pylon";NA;171;0
"Building";"HighTemplar";NA;181;0
"Building";"HighTemplar";NA;181;0
"Building";"HighTemplar";NA;181;0
"Building";"Pylon";NA;172;0
"Building";"Pylon";NA;172;0
"Unit";"Zealot";"Gateway";181;2
"Unit";"Zealot";"Gateway";181;2
"Building";"HighTemplar";NA;181;0
"Unit";"Adept";"Gateway";185;2
"Unit";"Adept";"Gateway";185;2
"Unit";"Observer";"Robotics Facility";185;1
"Unit";"Observer";"Robotics Facility";185;1
"Unit";"Adept";"Gateway";193;2
"Building";"Gateway";NA;172;0
"Unit";"Adept";"Gateway";193;2
"Unit";"Adept";"Gateway";193;2
"Unit";"Adept";"Gateway";193;2
"Building";"Gateway";NA;172;0
"Building";"Gateway";NA;173;0
"Building";"Gateway";NA;181;0
"Unit";"Observer";"Robotics Facility";202;1
"Unit";"Observer";"Robotics Facility";202;1
"Unit";"Zealot";"Gateway";207;2
"Unit";"Zealot";"Gateway";207;2
"Unit";"Zealot";"Gateway";207;2
"Building";"Pylon";NA;202;0
"Building";"Pylon";NA;205;0
"Building";"Pylon";NA;205;0
"Building";"Pylon";NA;205;0
"Building";"PhotonCannon";NA;203;0
"Building";"PhotonCannon";NA;203;0
"Building";"PhotonCannon";NA;203;0
"Building";"PhotonCannon";NA;203;0
"Building";"Pylon";NA;207;0
"Upgrade";"Charge";"TwilightCouncil";185;0
"Unit";"Immortal";"Robotics Facility";203;4
"Building";"HighTemplar";NA;214;0
"Building";"HighTemplar";NA;214;0
"Building";"HighTemplar";NA;214;0
"Building";"HighTemplar";NA;214;0
"Building";"HighTemplar";NA;218;0
"Building";"HighTemplar";NA;218;0
"Building";"HighTemplar";NA;218;0
"Building";"HighTemplar";NA;218;0
"Unit";"Zealot";"Gateway";218;2
"Unit";"Immortal";"Robotics Facility";206;4
"Building";"PhotonCannon";NA;214;0
"Building";"PhotonCannon";NA;214;0
"Building";"PhotonCannon";NA;214;0
"Upgrade";"ProtossGroundWeaponsLevel2";"Forge";185;0
"Upgrade";"ProtossGroundArmorsLevel2";"Forge";185;0
"Building";"PhotonCannon";NA;214;0
"Building";"Pylon";NA;214;0
"Building";"ShieldBattery";NA;214;0
"Building";"ShieldBattery";NA;214;0
"Building";"Pylon";NA;218;0
"Building";"PhotonCannon";NA;214;0
"Building";"Assimilator";NA;214;0
"Unit";"Archon";"High Templar";225;0
"Unit";"Archon";"High Templar";225;0
"Unit";"Archon";"High Templar";225;0
"Building";"Pylon";NA;219;0
"Unit";"Observer";"Robotics Facility";214;1
"Unit";"Archon";"High Templar";225;0
"Building";"Pylon";NA;219;0
"Building";"Pylon";NA;219;0
"Building";"Assimilator";NA;218;0
"Unit";"Observer";"Robotics Facility";221;1
"Building";"PhotonCannon";NA;225;0
"Building";"PhotonCannon";NA;226;0
"Building";"PhotonCannon";NA;226;0
"Building";"PhotonCannon";NA;226;0
"Building";"PhotonCannon";NA;227;0
"Building";"PhotonCannon";NA;227;0
"Building";"Nexus";NA;214;0
"Building";"Stargate";NA;226;0
"Building";"Stargate";NA;227;0
"Building";"PhotonCannon";NA;227;0
"Building";"PhotonCannon";NA;227;0
"Building";"PhotonCannon";NA;227;0
"Building";"PhotonCannon";NA;227;0
"Building";"FleetBeacon";NA;227;0
"Unit";"Zealot";"Gateway";228;2
"Unit";"Zealot";"Gateway";228;2
"Building";"ShieldBattery";NA;228;0
"Building";"ShieldBattery";NA;228;0
"Building";"ShieldBattery";NA;228;0
"Building";"PhotonCannon";NA;228;0
"Building";"Pylon";NA;232;0
"Building";"Pylon";NA;232;0
"Unit";"Phoenix";"Stargate";232;2
"Unit";"Phoenix";"Stargate";232;2
"Building";"Pylon";NA;232;0
"Building";"Pylon";NA;232;0
"Upgrade";"ProtossGroundWeaponsLevel3";"Forge";227;0
"Building";"PhotonCannon";NA;232;0
"Building";"PhotonCannon";NA;232;0
"Building";"PhotonCannon";NA;232;0
"Building";"PhotonCannon";NA;232;0
"Upgrade";"ProtossShieldsLevel1";"Forge";228;0
"Building";"PhotonCannon";NA;232;0
"Building";"PhotonCannon";NA;232;0
"Upgrade";"ProtossAirWeaponsLevel1";"CyberneticsCore";228;0
"Building";"ShieldBattery";NA;232;0
"Unit";"Carrier";"Stargate";228;6
"Building";"PhotonCannon";NA;236;0
"Unit";"Carrier";"Stargate";228;6
"Building";"PhotonCannon";NA;236;0
"Building";"PhotonCannon";NA;236;0
"Building";"PhotonCannon";NA;236;0
"Unit";"Mothership";"Mothership Core";232;6
"Building";"PhotonCannon";NA;236;0
"Building";"PhotonCannon";NA;236;0
"Building";"PhotonCannon";NA;236;0
"Building";"PhotonCannon";NA;236;0
"Building";"ShieldBattery";NA;236;0
"Building";"ShieldBattery";NA;236;0
"Building";"ShieldBattery";NA;236;0
"Building";"ShieldBattery";NA;236;0
"Building";"Pylon";NA;254;0
"Building";"Pylon";NA;254;0
"Building";"Pylon";NA;254;0
"Unit";"Carrier";"Stargate";236;6
"Building";"Pylon";NA;254;0
"Building";"Pylon";NA;254;0
"Building";"PhotonCannon";NA;254;0
"Building";"PhotonCannon";NA;254;0
"Building";"PhotonCannon";NA;254;0
"Building";"PhotonCannon";NA;254;0
"Building";"PhotonCannon";NA;254;0
"Building";"Pylon";NA;260;0
"Building";"ShieldBattery";NA;254;0
"Building";"ShieldBattery";NA;254;0
"Unit";"Carrier";"Stargate";236;6
"Building";"ShieldBattery";NA;254;0
"Building";"ShieldBattery";NA;254;0
"Building";"ShieldBattery";NA;254;0
"Unit";"Observer";"Robotics Facility";260;1
"Unit";"Observer";"Robotics Facility";260;1
"Upgrade";"ProtossShieldsLevel2";"Forge";254;0
"Unit";"Observer";"Robotics Facility";268;1
"Upgrade";"ProtossGroundArmorsLevel3";"Forge";254;0
"Unit";"Zealot";"Gateway";269;2
"Unit";"Carrier";"Stargate";260;6
"Building";"PhotonCannon";NA;269;0
"Building";"PhotonCannon";NA;269;0
"Building";"PhotonCannon";NA;269;0
"Building";"ShieldBattery";NA;269;0
"Building";"ShieldBattery";NA;269;0
"Unit";"Observer";"Robotics Facility";271;1
"Unit";"Observer";"Robotics Facility";271;1
"Unit";"Carrier";"Stargate";266;6
"Upgrade";"ProtossAirWeaponsLevel2";"CyberneticsCore";268;0
"Building";"Pylon";NA;285;0
