"type";"unit_name";"on_building";"total_supply";"supply"
"Building";"Pylon";NA;13;0
"Building";"Assimilator";NA;15;0
"Building";"Gateway";NA;15;0
"Building";"Assimilator";NA;20;0
"Building";"CyberneticsCore";NA;20;0
"Building";"Pylon";NA;21;0
"Building";"Nexus";NA;19;0
"Unit";"Adept";"Gateway";23;2
"Building";"TwilightCouncil";NA;24;0
"Unit";"Adept";"Gateway";30;2
"Building";"RoboticsFacility";NA;29;0
"Building";"Pylon";NA;38;0
"Building";"Gateway";NA;38;0
"Building";"Gateway";NA;38;0
"Building";"Assimilator";NA;41;0
"Building";"DarkShrine";NA;34;0
"Building";"Assimilator";NA;43;0
"Building";"DarkTemplar";NA;46;0
"Building";"DarkTemplar";NA;46;0
"Building";"DarkTemplar";NA;46;0
"Building";"Pylon";NA;49;0
"Building";"Pylon";NA;49;0
"Building";"Gateway";NA;47;0
"Building";"Gateway";NA;47;0
"Building";"Gateway";NA;47;0
"Building";"DarkTemplar";NA;49;0
"Building";"Gateway";NA;48;0
"Unit";"Archon";"High Templar";49;0
"Unit";"Zealot";"Gateway";49;2
"Unit";"Zealot";"Gateway";49;2
"Unit";"Zealot";"Gateway";49;2
"Unit";"Zealot";"Gateway";49;2
"Building";"Gateway";NA;48;0
"Unit";"Archon";"High Templar";49;0
"Building";"Pylon";NA;49;0
"Building";"Pylon";NA;49;0
"Building";"DarkTemplar";NA;57;0
"Building";"DarkTemplar";NA;57;0
"Upgrade";"Charge";"TwilightCouncil";48;0
"Unit";"Archon";"High Templar";57;0
"Building";"Gateway";NA;49;0
"Building";"Gateway";NA;49;0
"Unit";"Zealot";"Gateway";57;2
"Unit";"Zealot";"Gateway";57;2
"Unit";"Zealot";"Gateway";57;2
"Unit";"Zealot";"Gateway";57;2
"Unit";"Zealot";"Gateway";57;2
"Unit";"Zealot";"Gateway";57;2
"Unit";"Zealot";"Gateway";69;2
"Unit";"Zealot";"Gateway";69;2
"Unit";"Zealot";"Gateway";73;2
"Unit";"Zealot";"Gateway";73;2
"Unit";"Zealot";"Gateway";73;2
"Unit";"Zealot";"Gateway";73;2
"Unit";"Zealot";"Gateway";73;2
"Unit";"Zealot";"Gateway";73;2
"Building";"DarkTemplar";NA;85;0
"Building";"DarkTemplar";NA;85;0
"Building";"DarkTemplar";NA;85;0
"Building";"DarkTemplar";NA;85;0
"Building";"DarkTemplar";NA;85;0
"Building";"DarkTemplar";NA;85;0
"Building";"DarkTemplar";NA;85;0
"Building";"DarkTemplar";NA;85;0
"Building";"DarkTemplar";NA;85;0
"Building";"DarkTemplar";NA;85;0
"Unit";"Archon";"High Templar";85;0
"Unit";"Archon";"High Templar";85;0
"Unit";"Archon";"High Templar";85;0
"Unit";"Archon";"High Templar";85;0
"Unit";"Archon";"High Templar";85;0
"Unit";"Immortal";"Robotics Facility";85;4
"Building";"Pylon";NA;89;0
"Unit";"Zealot";"Gateway";89;2
"Unit";"Zealot";"Gateway";89;2
"Unit";"Zealot";"Gateway";89;2
"Unit";"Zealot";"Gateway";89;2
"Unit";"Zealot";"Gateway";89;2
"Unit";"Zealot";"Gateway";89;2
"Building";"DarkTemplar";NA;102;0
"Building";"DarkTemplar";NA;102;0
"Unit";"Archon";"High Templar";102;0
"Unit";"Immortal";"Robotics Facility";89;4
"Building";"DarkTemplar";NA;107;0
"Building";"DarkTemplar";NA;107;0
"Building";"TemplarArchive";NA;102;0
"Unit";"Archon";"High Templar";107;0
"Unit";"Immortal";"Robotics Facility";102;4
"Building";"Nexus";NA;89;0
"Building";"Assimilator";NA;107;0
"Building";"HighTemplar";NA;112;0
"Unit";"Observer";"Robotics Facility";107;1
"Building";"HighTemplar";NA;112;0
"Building";"Assimilator";NA;107;0
"Unit";"Archon";"High Templar";113;0
"Building";"Pylon";NA;112;0
"Building";"Pylon";NA;112;0
"Building";"Pylon";NA;112;0
"Unit";"Zealot";"Gateway";117;2
"Unit";"Zealot";"Gateway";117;2
"Unit";"Zealot";"Gateway";117;2
"Unit";"Zealot";"Gateway";117;2
"Building";"HighTemplar";NA;128;0
"Building";"HighTemplar";NA;128;0
"Building";"HighTemplar";NA;128;0
"Building";"HighTemplar";NA;128;0
"Unit";"Zealot";"Gateway";128;2
"Unit";"Zealot";"Gateway";128;2
"Unit";"Zealot";"Gateway";128;2
"Unit";"Zealot";"Gateway";128;2
"Unit";"Immortal";"Robotics Facility";115;4
"Unit";"Archon";"High Templar";137;0
"Unit";"Archon";"High Templar";137;0
"Building";"Pylon";NA;137;0
"Building";"Pylon";NA;137;0
"Unit";"Zealot";"Gateway";142;2
"Unit";"Zealot";"Gateway";142;2
"Unit";"Zealot";"Gateway";142;2
"Unit";"Zealot";"Gateway";142;2
"Unit";"Zealot";"Gateway";142;2
"Unit";"Zealot";"Gateway";142;2
"Unit";"Zealot";"Gateway";142;2
"Unit";"Zealot";"Gateway";142;2
"Unit";"Zealot";"Gateway";144;2
"Unit";"Zealot";"Gateway";146;2
"Building";"HighTemplar";NA;163;0
"Building";"HighTemplar";NA;163;0
"Building";"HighTemplar";NA;163;0
"Building";"HighTemplar";NA;163;0
"Building";"HighTemplar";NA;163;0
"Building";"HighTemplar";NA;163;0
"Unit";"Zealot";"Gateway";163;2
"Unit";"Zealot";"Gateway";163;2
"Unit";"Zealot";"Gateway";163;2
"Unit";"Zealot";"Gateway";163;2
"Unit";"Archon";"High Templar";165;0
"Unit";"Archon";"High Templar";167;0
"Unit";"Archon";"High Templar";169;0
"Building";"DarkTemplar";NA;171;0
"Building";"DarkTemplar";NA;171;0
"Unit";"Zealot";"Gateway";171;2
"Unit";"Zealot";"Gateway";171;2
"Unit";"Zealot";"Gateway";175;2
"Unit";"Zealot";"Gateway";175;2
"Unit";"Zealot";"Gateway";175;2
"Unit";"Zealot";"Gateway";175;2
"Unit";"Zealot";"Gateway";175;2
"Unit";"Zealot";"Gateway";175;2
