"type";"unit_name";"on_building";"total_supply_lag";"supply"
"Building";"Pylon";NA;14;0
"Building";"Gateway";NA;16;0
"Building";"Assimilator";NA;17;0
"Building";"Nexus";NA;20;0
"Building";"CyberneticsCore";NA;20;0
"Building";"Pylon";NA;22;0
"Building";"Assimilator";NA;22;0
"Unit";"Adept";"Gateway";23;2
"Unit";"Adept";"Gateway";27;2
"Building";"Pylon";NA;29;0
"Building";"Pylon";NA;29;0
"Building";"Pylon";NA;29;0
"Building";"Stargate";NA;30;0
"Unit";"Adept";"Gateway";31;2
"Building";"Gateway";NA;34;0
"Building";"Gateway";NA;35;0
"Unit";"Oracle";"Stargate";35;3
"Building";"Pylon";NA;42;0
"Unit";"Phoenix";"Stargate";42;2
"Unit";"Adept";"Gateway";45;2
"Building";"Pylon";NA;51;0
"Unit";"Phoenix";"Stargate";51;2
"Building";"TwilightCouncil";NA;58;0
"Building";"Forge";NA;59;0
"Building";"Pylon";NA;59;0
"Building";"Pylon";NA;59;0
"Building";"Assimilator";NA;59;0
"Unit";"Adept";"Gateway";59;2
"Unit";"Adept";"Gateway";61;2
"Unit";"Adept";"Gateway";63;2
"Building";"Assimilator";NA;65;0
"Building";"Pylon";NA;66;0
"Unit";"Phoenix";"Stargate";66;2
"Building";"Pylon";NA;68;0
"Building";"Pylon";NA;68;0
"Unit";"Phoenix";"Stargate";68;2
"Building";"Nexus";NA;70;0
"Building";"Pylon";NA;70;0
"Building";"Pylon";NA;70;0
"Upgrade";"ProtossGroundWeaponsLevel1";"Forge";70;0
"Building";"Gateway";NA;72;0
"Building";"Gateway";NA;72;0
"Unit";"Adept";"Gateway";73;2
"Unit";"Adept";"Gateway";75;2
"Unit";"Adept";"Gateway";77;2
"Building";"Pylon";NA;81;0
"Building";"Gateway";NA;81;0
"Building";"RoboticsFacility";NA;81;0
"Building";"Gateway";NA;81;0
"Unit";"Sentry";"Gateway";81;2
"Unit";"Sentry";"Gateway";83;2
"Unit";"Adept";"Gateway";87;2
"Building";"Pylon";NA;95;0
"Unit";"Adept";"Gateway";95;2
"Unit";"Adept";"Gateway";97;2
"Unit";"Adept";"Gateway";99;2
"Unit";"Adept";"Gateway";101;2
"Unit";"Adept";"Gateway";103;2
"Building";"Pylon";NA;108;0
"Unit";"Adept";"Gateway";108;2
"Unit";"Adept";"Gateway";110;2
"Unit";"Adept";"Gateway";112;2
"Unit";"Adept";"Gateway";114;2
"Unit";"Adept";"Gateway";116;2
"Unit";"Adept";"Gateway";121;2
"Unit";"Adept";"Gateway";123;2
"Unit";"Sentry";"Gateway";125;2
"Unit";"Sentry";"Gateway";127;2
"Unit";"Adept";"Gateway";129;2
"Unit";"Adept";"Gateway";131;2
"Unit";"Adept";"Gateway";133;2
"Unit";"Adept";"Gateway";136;2
"Unit";"Adept";"Gateway";138;2
"Unit";"Adept";"Gateway";140;2
"Unit";"Adept";"Gateway";142;2
"Unit";"Adept";"Gateway";144;2
"Unit";"Adept";"Gateway";146;2
"Unit";"Adept";"Gateway";148;2
"Building";"Nexus";NA;151;0
"Building";"Pylon";NA;151;0
"Building";"Assimilator";NA;152;0
"Building";"Pylon";NA;152;0
"Building";"Assimilator";NA;152;0
"Building";"RoboticsBay";NA;153;0
"Building";"RoboticsFacility";NA;153;0
"Unit";"Adept";"Gateway";153;2
"Unit";"Adept";"Gateway";155;2
"Unit";"Adept";"Gateway";157;2
"Unit";"Adept";"Gateway";159;2
"Unit";"Adept";"Gateway";161;2
"Unit";"Adept";"Gateway";163;2
"Unit";"Adept";"Gateway";165;2
"Building";"Pylon";NA;167;0
"Building";"Pylon";NA;167;0
"Unit";"Adept";"Gateway";167;2
"Unit";"Adept";"Gateway";169;2
"Unit";"Adept";"Gateway";171;2
"Unit";"Stalker";"Gateway";176;2
"Unit";"Stalker";"Gateway";178;2
"Unit";"Stalker";"Gateway";180;2
"Unit";"Stalker";"Gateway";182;2
"Unit";"Stalker";"Gateway";184;2
"Unit";"Stalker";"Gateway";186;2
"Unit";"Stalker";"Gateway";188;2
"Upgrade";"SprayProtoss";NA;190;0
"Upgrade";"SprayProtoss";NA;190;0
"Upgrade";"WarpGateResearch";NA;190;0
"Upgrade";"SprayProtoss";NA;190;0
"Upgrade";"SprayProtoss";NA;190;0
"Upgrade";"AdeptPiercingAttack";NA;190;0
"Upgrade";"SprayProtoss";NA;190;0
"Upgrade";"ProtossGroundArmorsLevel1";NA;190;0
"Upgrade";"SprayProtoss";NA;190;0
