"type";"unit_name";"on_building";"total_supply_lag";"supply"
"Building";"Pylon";NA;14;0
"Building";"Gateway";NA;16;0
"Building";"Assimilator";NA;17;0
"Building";"Nexus";NA;20;0
"Building";"CyberneticsCore";NA;21;0
"Building";"Assimilator";NA;22;0
"Building";"Pylon";NA;23;0
"Unit";"Adept";"Gateway";23;2
"Building";"RoboticsFacility";NA;30;0
"Unit";"Stalker";"Gateway";33;2
"Building";"Gateway";NA;39;0
"Building";"Gateway";NA;39;0
"Building";"Pylon";NA;41;0
"Building";"TwilightCouncil";NA;42;0
"Building";"Assimilator";NA;42;0
"Building";"Assimilator";NA;42;0
"Unit";"Observer";"Robotics Facility";46;1
"Building";"Pylon";NA;48;0
"Unit";"Stalker";"Gateway";49;2
"Building";"Pylon";NA;51;0
"Building";"DarkShrine";NA;51;0
"Unit";"Adept";"Gateway";53;2
"Unit";"Adept";"Gateway";55;2
"Unit";"Adept";"Gateway";57;2
"Building";"Gateway";NA;59;0
"Building";"Gateway";NA;59;0
"Building";"Pylon";NA;59;0
"Unit";"Immortal";"Robotics Facility";59;4
"Unit";"Stalker";"Gateway";63;2
"Unit";"Stalker";"Gateway";65;2
"Unit";"Stalker";"Gateway";67;2
"Building";"Pylon";NA;69;0
"Building";"Forge";NA;69;0
"Building";"Pylon";NA;69;0
"Building";"Pylon";NA;69;0
"Upgrade";"Charge";"TwilightCouncil";69;0
"Building";"Pylon";NA;69;0
"Building";"DarkTemplar";NA;69;0
"Building";"DarkTemplar";NA;69;0
"Building";"DarkTemplar";NA;69;0
"Unit";"Immortal";"Robotics Facility";71;4
"Building";"DarkTemplar";NA;75;0
"Building";"DarkTemplar";NA;75;0
"Unit";"Stalker";"Gateway";77;2
"Unit";"Stalker";"Gateway";79;2
"Upgrade";"ProtossGroundWeaponsLevel1";"Forge";81;0
"Unit";"Stalker";"Gateway";81;2
"Unit";"Immortal";"Robotics Facility";83;4
"Building";"TemplarArchive";NA;87;0
"Unit";"Zealot";"Gateway";87;2
"Unit";"Zealot";"Gateway";89;2
"Unit";"Zealot";"Gateway";91;2
"Unit";"Zealot";"Gateway";93;2
"Building";"Nexus";NA;95;0
"Unit";"Zealot";"Gateway";95;2
"Building";"Gateway";NA;99;0
"Building";"Gateway";NA;99;0
"Building";"DarkTemplar";NA;99;0
"Unit";"Zealot";"Gateway";99;2
"Unit";"Zealot";"Gateway";101;2
"Unit";"Zealot";"Gateway";103;2
"Unit";"Zealot";"Gateway";106;2
"Building";"HighTemplar";NA;108;0
"Building";"HighTemplar";NA;108;0
"Building";"Pylon";NA;108;0
"Unit";"Zealot";"Gateway";108;2
"Unit";"Zealot";"Gateway";110;2
"Building";"Pylon";NA;112;0
"Unit";"Stalker";"Gateway";114;2
"Unit";"Stalker";"Gateway";116;2
"Unit";"Stalker";"Gateway";118;2
"Unit";"Stalker";"Gateway";120;2
"Unit";"Stalker";"Gateway";122;2
"Building";"Pylon";NA;126;0
"Building";"HighTemplar";NA;126;0
"Building";"HighTemplar";NA;126;0
"Building";"Pylon";NA;129;0
"Building";"Pylon";NA;129;0
"Building";"Pylon";NA;129;0
"Building";"DarkTemplar";NA;129;0
"Unit";"Zealot";"Gateway";131;2
"Unit";"Zealot";"Gateway";133;2
"Unit";"Zealot";"Gateway";135;2
"Unit";"Zealot";"Gateway";137;2
"Unit";"Zealot";"Gateway";139;2
"Unit";"Zealot";"Gateway";141;2
"Building";"Pylon";NA;146;0
"Building";"DarkTemplar";NA;146;0
"Building";"HighTemplar";NA;146;0
"Building";"HighTemplar";NA;146;0
"Unit";"Zealot";"Gateway";146;2
"Unit";"Zealot";"Gateway";148;2
"Unit";"Archon";"High Templar";152;0
"Building";"Assimilator";NA;153;0
"Building";"Assimilator";NA;153;0
"Building";"RoboticsBay";NA;153;0
"Building";"Forge";NA;156;0
"Building";"DarkTemplar";NA;156;0
"Building";"DarkTemplar";NA;157;0
"Building";"Pylon";NA;159;0
"Unit";"Stalker";"Gateway";159;2
"Building";"HighTemplar";NA;161;0
"Building";"PhotonCannon";NA;161;0
"Building";"HighTemplar";NA;161;0
"Unit";"Archon";"High Templar";164;0
"Unit";"Zealot";"Gateway";164;2
"Unit";"Zealot";"Gateway";166;2
"Building";"DarkTemplar";NA;168;0
"Building";"DarkTemplar";NA;168;0
"Building";"DarkTemplar";NA;168;0
"Unit";"Zealot";"Gateway";170;2
"Unit";"Zealot";"Gateway";172;2
"Unit";"Zealot";"Gateway";174;2
"Unit";"Zealot";"Gateway";176;2
"Unit";"Colossus";"Robotics Facility";179;6
"Upgrade";"ProtossGroundWeaponsLevel2";"Forge";185;0
"Building";"PhotonCannon";NA;185;0
"Unit";"Stalker";"Gateway";185;2
"Unit";"Stalker";"Gateway";187;2
"Unit";"Stalker";"Gateway";189;2
"Upgrade";"ExtendedThermalLance";"RoboticsBay";191;0
"Building";"HighTemplar";NA;191;0
"Unit";"Colossus";"Robotics Facility";191;6
"Unit";"Stalker";"Gateway";197;2
"Unit";"Stalker";"Gateway";199;2
"Unit";"Stalker";"Gateway";201;2
"Unit";"Stalker";"Gateway";203;2
"Building";"Nexus";NA;205;0
"Unit";"Stalker";"Gateway";205;2
"Unit";"Stalker";"Gateway";207;2
"Unit";"Stalker";"Gateway";209;2
"Unit";"Stalker";"Gateway";211;2
"Unit";"Stalker";"Gateway";213;2
"Unit";"Stalker";"Gateway";215;2
"Building";"HighTemplar";NA;220;0
"Building";"HighTemplar";NA;220;0
"Building";"HighTemplar";NA;220;0
"Building";"Pylon";NA;220;0
"Unit";"Archon";"High Templar";220;0
"Unit";"Archon";"High Templar";220;0
"Unit";"Zealot";"Gateway";220;2
"Unit";"Zealot";"Gateway";222;2
"Unit";"Zealot";"Gateway";224;2
"Unit";"Zealot";"Gateway";226;2
"Unit";"Colossus";"Robotics Facility";228;6
"Building";"HighTemplar";NA;234;0
"Building";"HighTemplar";NA;234;0
"Building";"HighTemplar";NA;234;0
"Building";"Assimilator";NA;234;0
"Building";"Assimilator";NA;234;0
"Building";"HighTemplar";NA;234;0
"Building";"HighTemplar";NA;234;0
"Building";"Pylon";NA;234;0
"Unit";"Zealot";"Gateway";234;2
"Unit";"Zealot";"Gateway";236;2
"Unit";"Zealot";"Gateway";238;2
"Unit";"Zealot";"Gateway";240;2
"Unit";"Zealot";"Gateway";242;2
"Building";"PhotonCannon";NA;244;0
"Building";"PhotonCannon";NA;244;0
"Building";"PhotonCannon";NA;244;0
"Building";"Pylon";NA;244;0
"Unit";"Zealot";"Gateway";244;2
"Unit";"Zealot";"Gateway";246;2
"Unit";"Zealot";"Gateway";248;2
"Building";"HighTemplar";NA;250;0
"Building";"HighTemplar";NA;250;0
"Upgrade";"ProtossGroundWeaponsLevel3";"Forge";250;0
"Building";"Pylon";NA;250;0
"Unit";"Colossus";"Robotics Facility";250;6
"Unit";"Zealot";"Gateway";256;2
"Unit";"Zealot";"Gateway";258;2
"Unit";"Zealot";"Gateway";260;2
"Unit";"Zealot";"Gateway";262;2
"Unit";"Zealot";"Gateway";264;2
"Unit";"Zealot";"Gateway";266;2
"Unit";"Zealot";"Gateway";268;2
"Unit";"Stalker";"Gateway";270;2
"Unit";"Stalker";"Gateway";272;2
"Unit";"Stalker";"Gateway";274;2
"Unit";"Stalker";"Gateway";276;2
"Unit";"Stalker";"Gateway";278;2
"Unit";"Stalker";"Gateway";280;2
"Building";"HighTemplar";NA;282;0
"Building";"Nexus";NA;282;0
"Building";"HighTemplar";NA;282;0
"Building";"HighTemplar";NA;282;0
"Building";"HighTemplar";NA;282;0
"Building";"HighTemplar";NA;282;0
"Building";"Pylon";NA;282;0
"Unit";"Stalker";"Gateway";282;2
"Unit";"Stalker";"Gateway";284;2
"Unit";"Colossus";"Robotics Facility";286;6
"Unit";"Zealot";"Gateway";292;2
"Unit";"Zealot";"Gateway";294;2
"Unit";"Zealot";"Gateway";296;2
"Unit";"Zealot";"Gateway";298;2
"Unit";"Zealot";"Gateway";300;2
"Unit";"Zealot";"Gateway";302;2
"Unit";"Zealot";"Gateway";304;2
"Building";"RoboticsFacility";NA;306;0
"Unit";"Stalker";"Gateway";306;2
"Unit";"Stalker";"Gateway";308;2
"Unit";"Stalker";"Gateway";310;2
"Unit";"Stalker";"Gateway";312;2
"Unit";"Stalker";"Gateway";314;2
"Unit";"Stalker";"Gateway";316;2
"Building";"HighTemplar";NA;318;0
"Unit";"Stalker";"Gateway";319;2
"Unit";"Stalker";"Gateway";321;2
"Unit";"Stalker";"Gateway";323;2
"Unit";"Stalker";"Gateway";325;2
"Unit";"Stalker";"Gateway";327;2
"Unit";"Stalker";"Gateway";329;2
"Unit";"Disruptor";"Robotics Facility";335;3
"Building";"Assimilator";NA;338;0
"Building";"Assimilator";NA;338;0
"Building";"PhotonCannon";NA;338;0
"Unit";"Stalker";"Gateway";338;2
"Unit";"Stalker";"Gateway";340;2
"Unit";"Stalker";"Gateway";342;2
"Unit";"Stalker";"Gateway";344;2
"Building";"Pylon";NA;349;0
"Unit";"Colossus";"Robotics Facility";349;6
"Building";"HighTemplar";NA;355;0
"Building";"HighTemplar";NA;355;0
"Unit";"Zealot";"Gateway";355;2
"Unit";"Zealot";"Gateway";357;2
"Unit";"Zealot";"Gateway";359;2
"Unit";"Zealot";"Gateway";361;2
"Unit";"Zealot";"Gateway";363;2
"Building";"Pylon";NA;365;0
"Unit";"Stalker";"Gateway";365;2
"Unit";"Stalker";"Gateway";367;2
"Unit";"Stalker";"Gateway";369;2
"Unit";"Stalker";"Gateway";371;2
"Unit";"Stalker";"Gateway";373;2
"Unit";"Stalker";"Gateway";375;2
"Unit";"Stalker";"Gateway";377;2
"Unit";"Colossus";"Robotics Facility";379;6
"Unit";"Colossus";"Robotics Facility";385;6
"Unit";"Stalker";"Gateway";391;2
"Unit";"Stalker";"Gateway";393;2
"Unit";"Stalker";"Gateway";395;2
"Unit";"Stalker";"Gateway";397;2
"Unit";"Stalker";"Gateway";399;2
"Unit";"Colossus";"Robotics Facility";401;6
"Unit";"Stalker";"Gateway";407;2
"Unit";"Stalker";"Gateway";409;2
"Unit";"Stalker";"Gateway";411;2
"Unit";"Stalker";"Gateway";413;2
"Unit";"Stalker";"Gateway";415;2
"Unit";"Stalker";"Gateway";417;2
"Unit";"Stalker";"Gateway";419;2
"Unit";"Stalker";"Gateway";421;2
"Unit";"Stalker";"Gateway";423;2
"Unit";"Stalker";"Gateway";425;2
"Unit";"Stalker";"Gateway";427;2
"Unit";"Stalker";"Gateway";429;2
"Unit";"Stalker";"Gateway";431;2
"Unit";"Stalker";"Gateway";433;2
"Unit";"Stalker";"Gateway";435;2
"Unit";"Stalker";"Gateway";437;2
"Unit";"Stalker";"Gateway";439;2
"Unit";"Stalker";"Gateway";441;2
"Unit";"Stalker";"Gateway";443;2
"Unit";"Stalker";"Gateway";445;2
"Unit";"Stalker";"Gateway";447;2
"Unit";"Stalker";"Gateway";449;2
"Upgrade";"SprayProtoss";NA;451;0
"Upgrade";"SprayProtoss";NA;451;0
"Upgrade";"WarpGateResearch";NA;451;0
"Upgrade";"SprayProtoss";NA;451;0
"Upgrade";"SprayProtoss";NA;451;0
"Upgrade";"PsiStormTech";NA;451;0
"Upgrade";"ProtossGroundArmorsLevel1";NA;451;0
"Upgrade";"SprayProtoss";NA;451;0
"Upgrade";"SprayProtoss";NA;451;0
"Upgrade";"ProtossGroundArmorsLevel2";NA;451;0
"Upgrade";"SprayProtoss";NA;451;0
"Upgrade";"BlinkTech";NA;451;0
"Upgrade";"SprayProtoss";NA;451;0
"Upgrade";"ProtossGroundArmorsLevel3";NA;451;0
"Upgrade";"SprayProtoss";NA;451;0
"Upgrade";"SprayProtoss";NA;451;0
