"type";"unit_name";"on_building";"total_supply_lag";"supply"
"Unit";"Overlord";"Larva";13;0
"Building";"Hatchery";NA;16;0
"Building";"Extractor";NA;19;0
"Building";"SpawningPool";NA;19;0
"Building";"Hatchery";NA;23;0
"Unit";"Queen";"Hatchery";24;2
"Unit";"Zergling";"Larva";26;1
"Unit";"Zergling";"Larva";27;1
"Unit";"Queen";"Hatchery";30;2
"Unit";"Overlord";"Larva";33;0
"Unit";"Zergling";"Larva";33;1
"Unit";"Zergling";"Larva";34;1
"Unit";"Zergling";"Larva";35;1
"Unit";"Zergling";"Larva";36;1
"Unit";"Queen";"Hatchery";37;2
"Unit";"Queen";"Hatchery";43;2
"Building";"CreepTumorQueen";NA;47;0
"Unit";"Overlord";"Larva";47;0
"Unit";"Overlord";"Larva";49;0
"Building";"SporeCrawler";NA;49;0
"Unit";"Overlord";"Larva";51;0
"Building";"SporeCrawler";NA;51;0
"Building";"CreepTumor";NA;52;0
"Building";"CreepTumorQueen";NA;53;0
"Building";"EvolutionChamber";NA;63;0
"Building";"SporeCrawler";NA;67;0
"Building";"CreepTumor";NA;68;0
"Building";"CreepTumorQueen";NA;71;0
"Building";"Extractor";NA;71;0
"Building";"Extractor";NA;71;0
"Building";"CreepTumor";NA;71;0
"Unit";"Zergling";"Larva";72;1
"Unit";"Zergling";"Larva";73;1
"Unit";"Overlord";"Larva";74;0
"Unit";"Overlord";"Larva";74;0
"Building";"CreepTumor";NA;74;0
"Unit";"Overlord";"Larva";74;0
"Building";"CreepTumor";NA;74;0
"Building";"BanelingNest";NA;74;0
"Unit";"Zergling";"Larva";74;1
"Unit";"Zergling";"Larva";75;1
"Unit";"Zergling";"Larva";76;1
"Unit";"Zergling";"Larva";77;1
"Unit";"Zergling";"Larva";78;1
"Unit";"Zergling";"Larva";79;1
"Unit";"Zergling";"Larva";80;1
"Unit";"Zergling";"Larva";81;1
"Unit";"Zergling";"Larva";82;1
"Unit";"Zergling";"Larva";83;1
"Unit";"Zergling";"Larva";84;1
"Unit";"Zergling";"Larva";85;1
"Unit";"Zergling";"Larva";86;1
"Unit";"Zergling";"Larva";87;1
"Unit";"Zergling";"Larva";88;1
"Unit";"Zergling";"Larva";89;1
"Unit";"Overlord";"Larva";96;0
"Unit";"Overlord";"Larva";100;0
"Building";"HydraliskDen";NA;100;0
"Unit";"Zergling";"Larva";100;1
"Unit";"Zergling";"Larva";101;1
"Unit";"Zergling";"Larva";102;1
"Unit";"Zergling";"Larva";103;1
"Unit";"Zergling";"Larva";104;1
"Unit";"Zergling";"Larva";105;1
"Unit";"Zergling";"Larva";106;1
"Unit";"Zergling";"Larva";107;1
"Building";"Extractor";NA;109;0
"Building";"Extractor";NA;109;0
"Building";"CreepTumor";NA;109;0
"Building";"CreepTumor";NA;112;0
"Building";"CreepTumor";NA;112;0
"Building";"Extractor";NA;123;0
"Unit";"Overlord";"Larva";123;0
"Building";"CreepTumor";NA;123;0
"Building";"CreepTumor";NA;123;0
"Unit";"Zergling";"Larva";123;1
"Unit";"Zergling";"Larva";124;1
"Unit";"Zergling";"Larva";125;1
"Unit";"Zergling";"Larva";126;1
"Unit";"Overlord";"Larva";127;0
"Unit";"Overlord";"Larva";127;0
"Unit";"Overlord";"Larva";127;0
"Unit";"Hydralisk";"Larva";127;2
"Unit";"Hydralisk";"Larva";129;2
"Unit";"Hydralisk";"Larva";131;2
"Unit";"Hydralisk";"Larva";133;2
"Unit";"Hydralisk";"Larva";135;2
"Unit";"Hydralisk";"Larva";137;2
"Building";"CreepTumor";NA;139;0
"Unit";"Queen";"Hatchery";139;2
"Unit";"Hydralisk";"Larva";141;2
"Unit";"Hydralisk";"Larva";143;2
"Building";"CreepTumor";NA;145;0
"Unit";"Hydralisk";"Larva";145;2
"Unit";"Hydralisk";"Larva";147;2
"Unit";"Hydralisk";"Larva";149;2
"Unit";"Hydralisk";"Larva";154;2
"Unit";"Hydralisk";"Larva";156;2
"Unit";"Overlord";"Larva";158;0
"Building";"CreepTumor";NA;158;0
"Unit";"Hydralisk";"Larva";158;2
"Unit";"Overlord";"Larva";160;0
"Unit";"Overlord";"Larva";160;0
"Building";"CreepTumor";NA;160;0
"Unit";"Overlord";"Larva";160;0
"Unit";"Hydralisk";"Larva";161;2
"Unit";"Baneling";"Zergling";163;0
"Unit";"Baneling";"Zergling";163;0
"Unit";"Baneling";"Zergling";163;0
"Unit";"Baneling";"Zergling";163;0
"Unit";"Baneling";"Zergling";163;0
"Unit";"Baneling";"Zergling";163;0
"Building";"Hatchery";NA;163;0
"Unit";"Baneling";"Zergling";163;0
"Unit";"Baneling";"Zergling";163;0
"Unit";"Baneling";"Zergling";163;0
"Unit";"Baneling";"Zergling";163;0
"Unit";"Baneling";"Zergling";163;0
"Unit";"Baneling";"Zergling";163;0
"Unit";"Baneling";"Zergling";163;0
"Unit";"Hydralisk";"Larva";163;2
"Building";"CreepTumor";NA;165;0
"Unit";"Hydralisk";"Larva";165;2
"Unit";"Hydralisk";"Larva";167;2
"Unit";"Hydralisk";"Larva";169;2
"Unit";"Hydralisk";"Larva";171;2
"Unit";"Hydralisk";"Larva";173;2
"Unit";"Zergling";"Larva";175;1
"Unit";"Zergling";"Larva";176;1
"Unit";"Zergling";"Larva";177;1
"Unit";"Zergling";"Larva";178;1
"Unit";"Zergling";"Larva";179;1
"Unit";"Zergling";"Larva";180;1
"Unit";"Zergling";"Larva";181;1
"Unit";"Zergling";"Larva";182;1
"Unit";"Zergling";"Larva";183;1
"Unit";"Zergling";"Larva";184;1
"Unit";"Baneling";"Zergling";185;0
"Unit";"Baneling";"Zergling";185;0
"Unit";"Baneling";"Zergling";185;0
"Unit";"Baneling";"Zergling";185;0
"Unit";"Baneling";"Zergling";185;0
"Unit";"Baneling";"Zergling";185;0
"Unit";"Hydralisk";"Larva";185;2
"Unit";"Hydralisk";"Larva";187;2
"Unit";"Hydralisk";"Larva";189;2
"Unit";"Zergling";"Larva";191;1
"Unit";"Zergling";"Larva";192;1
"Unit";"Zergling";"Larva";193;1
"Unit";"Zergling";"Larva";194;1
"Unit";"Zergling";"Larva";195;1
"Unit";"Zergling";"Larva";196;1
"Unit";"Zergling";"Larva";197;1
"Unit";"Zergling";"Larva";198;1
"Unit";"Zergling";"Larva";199;1
"Unit";"Zergling";"Larva";200;1
"Unit";"Zergling";"Larva";201;1
"Unit";"Zergling";"Larva";202;1
"Unit";"Hydralisk";"Larva";203;2
"Unit";"Hydralisk";"Larva";205;2
"Unit";"Hydralisk";"Larva";207;2
"Unit";"Hydralisk";"Larva";209;2
"Unit";"Zergling";"Larva";211;1
"Unit";"Zergling";"Larva";212;1
"Unit";"Zergling";"Larva";213;1
"Unit";"Zergling";"Larva";214;1
"Unit";"Zergling";"Larva";215;1
"Unit";"Zergling";"Larva";216;1
"Unit";"Zergling";"Larva";217;1
"Unit";"Zergling";"Larva";218;1
"Unit";"Hydralisk";"Larva";219;2
"Unit";"Hydralisk";"Larva";221;2
"Unit";"Hydralisk";"Larva";223;2
"Unit";"Zergling";"Larva";225;1
"Unit";"Zergling";"Larva";226;1
"Unit";"Zergling";"Larva";227;1
"Unit";"Zergling";"Larva";228;1
"Unit";"Zergling";"Larva";229;1
"Unit";"Zergling";"Larva";230;1
"Unit";"Zergling";"Larva";231;1
"Unit";"Zergling";"Larva";232;1
"Unit";"Baneling";"Zergling";233;0
"Unit";"Baneling";"Zergling";233;0
"Unit";"Baneling";"Zergling";233;0
"Unit";"Baneling";"Zergling";233;0
"Unit";"Baneling";"Zergling";233;0
"Unit";"Baneling";"Zergling";233;0
"Unit";"Hydralisk";"Larva";233;2
"Unit";"Hydralisk";"Larva";235;2
"Unit";"Zergling";"Larva";237;1
"Unit";"Zergling";"Larva";238;1
"Unit";"Zergling";"Larva";239;1
"Unit";"Zergling";"Larva";240;1
"Unit";"Zergling";"Larva";241;1
"Unit";"Zergling";"Larva";242;1
"Unit";"Zergling";"Larva";243;1
"Unit";"Zergling";"Larva";244;1
"Unit";"Zergling";"Larva";245;1
"Unit";"Zergling";"Larva";246;1
"Unit";"Zergling";"Larva";247;1
"Unit";"Zergling";"Larva";248;1
"Unit";"Zergling";"Larva";249;1
"Unit";"Zergling";"Larva";250;1
"Unit";"Hydralisk";"Larva";251;2
"Unit";"Hydralisk";"Larva";253;2
"Unit";"Hydralisk";"Larva";255;2
"Unit";"Hydralisk";"Larva";257;2
"Unit";"Hydralisk";"Larva";259;2
"Unit";"Zergling";"Larva";261;1
"Unit";"Zergling";"Larva";262;1
"Unit";"Zergling";"Larva";263;1
"Unit";"Zergling";"Larva";264;1
"Unit";"Zergling";"Larva";265;1
"Unit";"Zergling";"Larva";266;1
"Unit";"Zergling";"Larva";267;1
"Unit";"Zergling";"Larva";268;1
"Upgrade";"SprayZerg";NA;269;0
"Upgrade";"SprayZerg";NA;269;0
"Upgrade";"SprayZerg";NA;269;0
"Upgrade";"SprayZerg";NA;269;0
"Upgrade";"zerglingmovementspeed";NA;269;0
"Upgrade";"ZergMeleeWeaponsLevel1";NA;269;0
"Upgrade";"CentrificalHooks";NA;269;0
"Upgrade";"SprayZerg";NA;269;0
"Upgrade";"EvolveMuscularAugments";NA;269;0
"Upgrade";"SprayZerg";NA;269;0
"Upgrade";"ZergMeleeWeaponsLevel2";NA;269;0
