"type";"unit_name";"on_building";"total_supply_lag";"supply"
"Unit";"Overlord";"Larva";13;0
"Building";"Hatchery";NA;17;0
"Building";"Extractor";NA;20;0
"Building";"SpawningPool";NA;20;0
"Unit";"Overlord";"Larva";24;0
"Unit";"Queen";"Hatchery";28;2
"Unit";"Queen";"Hatchery";30;2
"Unit";"Overlord";"Larva";37;0
"Unit";"Overlord";"Larva";39;0
"Unit";"Queen";"Hatchery";39;2
"Unit";"Overlord";"Larva";41;0
"Building";"Extractor";NA;41;0
"Unit";"Zergling";"Larva";41;1
"Unit";"Zergling";"Larva";42;1
"Unit";"Zergling";"Larva";43;1
"Unit";"Zergling";"Larva";44;1
"Unit";"Zergling";"Larva";45;1
"Unit";"Zergling";"Larva";46;1
"Unit";"Zergling";"Larva";47;1
"Unit";"Zergling";"Larva";48;1
"Unit";"Zergling";"Larva";49;1
"Unit";"Zergling";"Larva";50;1
"Unit";"Zergling";"Larva";51;1
"Unit";"Zergling";"Larva";52;1
"Building";"EvolutionChamber";NA;58;0
"Building";"CreepTumorQueen";NA;60;0
"Building";"BanelingNest";NA;60;0
"Building";"Extractor";NA;61;0
"Building";"SpineCrawler";NA;61;0
"Unit";"Zergling";"Larva";63;1
"Unit";"Zergling";"Larva";64;1
"Unit";"Zergling";"Larva";65;1
"Unit";"Zergling";"Larva";66;1
"Unit";"Zergling";"Larva";67;1
"Unit";"Zergling";"Larva";68;1
"Unit";"Zergling";"Larva";69;1
"Unit";"Zergling";"Larva";70;1
"Unit";"Zergling";"Larva";71;1
"Unit";"Zergling";"Larva";72;1
"Unit";"Queen";"Hatchery";74;2
"Unit";"Zergling";"Larva";76;1
"Unit";"Zergling";"Larva";77;1
"Unit";"Zergling";"Larva";78;1
"Unit";"Zergling";"Larva";79;1
"Unit";"Zergling";"Larva";80;1
"Unit";"Zergling";"Larva";81;1
"Unit";"Zergling";"Larva";82;1
"Unit";"Zergling";"Larva";83;1
"Unit";"Zergling";"Larva";84;1
"Unit";"Zergling";"Larva";85;1
"Unit";"Baneling";"Zergling";86;0
"Unit";"Baneling";"Zergling";86;0
"Unit";"Baneling";"Zergling";86;0
"Unit";"Baneling";"Zergling";86;0
"Unit";"Baneling";"Zergling";86;0
"Unit";"Zergling";"Larva";86;1
"Unit";"Zergling";"Larva";87;1
"Unit";"Overlord";"Larva";88;0
"Unit";"Baneling";"Zergling";88;0
"Unit";"Baneling";"Zergling";88;0
"Unit";"Overlord";"Larva";90;0
"Building";"Hatchery";NA;94;0
"Unit";"Overlord";"Larva";94;0
"Unit";"Overlord";"Larva";98;0
"Building";"HydraliskDen";NA;98;0
"Unit";"Baneling";"Zergling";98;0
"Unit";"Baneling";"Zergling";98;0
"Unit";"Baneling";"Zergling";98;0
"Unit";"Zergling";"Larva";98;1
"Unit";"Zergling";"Larva";99;1
"Unit";"Zergling";"Larva";100;1
"Unit";"Zergling";"Larva";101;1
"Unit";"Zergling";"Larva";102;1
"Unit";"Zergling";"Larva";103;1
"Unit";"Zergling";"Larva";104;1
"Unit";"Zergling";"Larva";105;1
"Unit";"Zergling";"Larva";106;1
"Unit";"Zergling";"Larva";107;1
"Unit";"Zergling";"Larva";108;1
"Unit";"Zergling";"Larva";109;1
"Unit";"Zergling";"Larva";110;1
"Unit";"Zergling";"Larva";111;1
"Unit";"Hydralisk";"Larva";115;2
"Unit";"Hydralisk";"Larva";117;2
"Unit";"Hydralisk";"Larva";119;2
"Unit";"Hydralisk";"Larva";121;2
"Unit";"Hydralisk";"Larva";123;2
"Unit";"Hydralisk";"Larva";125;2
"Unit";"Overlord";"Larva";127;0
"Unit";"Overlord";"Larva";127;0
"Unit";"Hydralisk";"Larva";127;2
"Unit";"Hydralisk";"Larva";129;2
"Unit";"Baneling";"Zergling";131;0
"Unit";"Baneling";"Zergling";131;0
"Unit";"Baneling";"Zergling";131;0
"Unit";"Baneling";"Zergling";131;0
"Unit";"Baneling";"Zergling";131;0
"Unit";"Baneling";"Zergling";131;0
"Unit";"Overlord";"Larva";131;0
"Unit";"Overlord";"Larva";131;0
"Unit";"Overlord";"Larva";131;0
"Unit";"Hydralisk";"Larva";138;2
"Unit";"Hydralisk";"Larva";140;2
"Unit";"Hydralisk";"Larva";142;2
"Unit";"Queen";"Hatchery";145;2
"Unit";"Hydralisk";"Larva";148;2
"Unit";"Hydralisk";"Larva";150;2
"Unit";"Hydralisk";"Larva";152;2
"Unit";"Hydralisk";"Larva";154;2
"Unit";"Hydralisk";"Larva";156;2
"Unit";"Hydralisk";"Larva";158;2
"Unit";"Hydralisk";"Larva";160;2
"Unit";"Overlord";"Larva";162;0
"Building";"SpineCrawler";NA;162;0
"Building";"SpineCrawler";NA;162;0
"Building";"SpineCrawler";NA;162;0
"Building";"SpineCrawler";NA;162;0
"Unit";"Hydralisk";"Larva";162;2
"Unit";"Hydralisk";"Larva";164;2
"Unit";"Hydralisk";"Larva";166;2
"Unit";"Overlord";"Larva";168;0
"Unit";"Hydralisk";"Larva";168;2
"Unit";"Overlord";"Larva";170;0
"Building";"CreepTumor";NA;170;0
"Unit";"Zergling";"Larva";170;1
"Unit";"Zergling";"Larva";171;1
"Unit";"Zergling";"Larva";172;1
"Unit";"Zergling";"Larva";173;1
"Unit";"Overlord";"Larva";174;0
"Unit";"Overlord";"Larva";174;0
"Unit";"Overlord";"Larva";174;0
"Unit";"Zergling";"Larva";174;1
"Unit";"Zergling";"Larva";175;1
"Unit";"Zergling";"Larva";176;1
"Unit";"Zergling";"Larva";177;1
"Unit";"Hydralisk";"Larva";178;2
"Unit";"Hydralisk";"Larva";180;2
"Unit";"Hydralisk";"Larva";182;2
"Unit";"Zergling";"Larva";184;1
"Unit";"Zergling";"Larva";185;1
"Unit";"Zergling";"Larva";186;1
"Unit";"Zergling";"Larva";187;1
"Unit";"Zergling";"Larva";188;1
"Unit";"Zergling";"Larva";189;1
"Unit";"Zergling";"Larva";190;1
"Unit";"Zergling";"Larva";191;1
"Unit";"Zergling";"Larva";192;1
"Unit";"Zergling";"Larva";193;1
"Unit";"Zergling";"Larva";194;1
"Unit";"Zergling";"Larva";195;1
"Unit";"Zergling";"Larva";196;1
"Unit";"Zergling";"Larva";197;1
"Unit";"Zergling";"Larva";198;1
"Unit";"Zergling";"Larva";199;1
"Unit";"Zergling";"Larva";200;1
"Unit";"Zergling";"Larva";201;1
"Unit";"Zergling";"Larva";202;1
"Unit";"Zergling";"Larva";203;1
"Unit";"Zergling";"Larva";206;1
"Unit";"Zergling";"Larva";207;1
"Unit";"Zergling";"Larva";208;1
"Unit";"Zergling";"Larva";209;1
"Unit";"Zergling";"Larva";210;1
"Unit";"Zergling";"Larva";211;1
"Unit";"Zergling";"Larva";212;1
"Unit";"Zergling";"Larva";213;1
"Unit";"Baneling";"Zergling";216;0
"Building";"Extractor";NA;216;0
"Unit";"Hydralisk";"Larva";216;2
"Building";"Extractor";NA;218;0
"Unit";"Zergling";"Larva";218;1
"Unit";"Zergling";"Larva";219;1
"Unit";"Zergling";"Larva";220;1
"Unit";"Zergling";"Larva";221;1
"Unit";"Zergling";"Larva";222;1
"Unit";"Zergling";"Larva";223;1
"Building";"SporeCrawler";NA;224;0
"Building";"SporeCrawler";NA;224;0
"Building";"SporeCrawler";NA;224;0
"Building";"SpineCrawler";NA;225;0
"Unit";"Zergling";"Larva";225;1
"Unit";"Zergling";"Larva";226;1
"Unit";"Zergling";"Larva";227;1
"Unit";"Zergling";"Larva";228;1
"Unit";"Zergling";"Larva";229;1
"Unit";"Zergling";"Larva";230;1
"Unit";"Zergling";"Larva";231;1
"Unit";"Zergling";"Larva";232;1
"Unit";"Zergling";"Larva";233;1
"Unit";"Zergling";"Larva";234;1
"Unit";"Zergling";"Larva";235;1
"Unit";"Zergling";"Larva";236;1
"Unit";"Zergling";"Larva";241;1
"Unit";"Zergling";"Larva";242;1
"Unit";"Overlord";"Larva";243;0
"Unit";"Overlord";"Larva";246;0
"Unit";"Overlord";"Larva";248;0
"Unit";"Zergling";"Larva";248;1
"Unit";"Zergling";"Larva";249;1
"Unit";"Zergling";"Larva";250;1
"Unit";"Zergling";"Larva";251;1
"Unit";"Zergling";"Larva";252;1
"Unit";"Zergling";"Larva";253;1
"Unit";"Zergling";"Larva";254;1
"Unit";"Zergling";"Larva";255;1
"Unit";"Zergling";"Larva";256;1
"Unit";"Zergling";"Larva";257;1
"Unit";"Zergling";"Larva";258;1
"Unit";"Zergling";"Larva";259;1
"Unit";"Zergling";"Larva";260;1
"Unit";"Zergling";"Larva";261;1
"Unit";"Zergling";"Larva";262;1
"Unit";"Zergling";"Larva";263;1
"Unit";"Zergling";"Larva";264;1
"Unit";"Zergling";"Larva";265;1
"Unit";"Zergling";"Larva";266;1
"Unit";"Zergling";"Larva";267;1
"Unit";"Zergling";"Larva";268;1
"Unit";"Zergling";"Larva";269;1
"Unit";"Hydralisk";"Larva";274;2
"Unit";"Hydralisk";"Larva";276;2
"Unit";"Hydralisk";"Larva";278;2
"Unit";"Hydralisk";"Larva";280;2
"Unit";"Hydralisk";"Larva";282;2
"Unit";"Hydralisk";"Larva";284;2
"Unit";"Hydralisk";"Larva";286;2
"Unit";"Hydralisk";"Larva";288;2
"Unit";"Hydralisk";"Larva";290;2
"Unit";"Hydralisk";"Larva";292;2
"Unit";"Hydralisk";"Larva";294;2
"Unit";"Overlord";"Larva";297;0
"Unit";"Zergling";"Larva";298;1
"Unit";"Zergling";"Larva";299;1
"Unit";"Zergling";"Larva";300;1
"Unit";"Zergling";"Larva";301;1
"Unit";"Zergling";"Larva";302;1
"Unit";"Zergling";"Larva";303;1
"Building";"CreepTumorQueen";NA;304;0
"Unit";"Overlord";"Larva";304;0
"Unit";"Zergling";"Larva";304;1
"Unit";"Zergling";"Larva";305;1
"Unit";"Zergling";"Larva";306;1
"Unit";"Zergling";"Larva";307;1
"Unit";"Zergling";"Larva";308;1
"Unit";"Zergling";"Larva";309;1
"Unit";"Zergling";"Larva";310;1
"Unit";"Zergling";"Larva";311;1
"Building";"Hatchery";NA;312;0
"Building";"Extractor";NA;312;0
"Unit";"Overlord";"Larva";314;0
"Building";"CreepTumor";NA;314;0
"Building";"CreepTumorQueen";NA;314;0
"Unit";"Zergling";"Larva";314;1
"Unit";"Zergling";"Larva";315;1
"Building";"CreepTumorQueen";NA;316;0
"Unit";"Zergling";"Larva";316;1
"Unit";"Zergling";"Larva";317;1
"Unit";"Zergling";"Larva";318;1
"Unit";"Zergling";"Larva";319;1
"Unit";"Zergling";"Larva";320;1
"Unit";"Zergling";"Larva";321;1
"Unit";"Baneling";"Zergling";323;0
"Unit";"Baneling";"Zergling";323;0
"Unit";"Baneling";"Zergling";323;0
"Unit";"Baneling";"Zergling";323;0
"Unit";"Baneling";"Zergling";323;0
"Unit";"Baneling";"Zergling";323;0
"Unit";"Baneling";"Zergling";323;0
"Unit";"Baneling";"Zergling";323;0
"Unit";"Baneling";"Zergling";323;0
"Unit";"Baneling";"Zergling";323;0
"Unit";"Baneling";"Zergling";323;0
"Unit";"Baneling";"Zergling";323;0
"Unit";"Baneling";"Zergling";323;0
"Unit";"Baneling";"Zergling";323;0
"Unit";"Baneling";"Zergling";323;0
"Unit";"Baneling";"Zergling";323;0
"Unit";"Zergling";"Larva";323;1
"Unit";"Zergling";"Larva";324;1
"Unit";"Zergling";"Larva";325;1
"Unit";"Zergling";"Larva";326;1
"Unit";"Zergling";"Larva";327;1
"Unit";"Zergling";"Larva";328;1
"Unit";"Zergling";"Larva";329;1
"Unit";"Zergling";"Larva";330;1
"Unit";"Zergling";"Larva";331;1
"Unit";"Zergling";"Larva";332;1
"Unit";"Zergling";"Larva";333;1
"Unit";"Zergling";"Larva";334;1
"Unit";"Hydralisk";"Larva";338;2
"Unit";"Hydralisk";"Larva";340;2
"Unit";"Hydralisk";"Larva";342;2
"Unit";"Hydralisk";"Larva";344;2
"Unit";"Hydralisk";"Larva";346;2
"Unit";"Hydralisk";"Larva";348;2
"Unit";"Hydralisk";"Larva";350;2
"Unit";"Hydralisk";"Larva";352;2
"Unit";"Hydralisk";"Larva";354;2
"Unit";"Hydralisk";"Larva";356;2
"Unit";"Hydralisk";"Larva";358;2
"Unit";"Hydralisk";"Larva";360;2
"Unit";"Hydralisk";"Larva";362;2
"Unit";"Zergling";"Larva";364;1
"Unit";"Zergling";"Larva";365;1
"Unit";"Zergling";"Larva";366;1
"Unit";"Zergling";"Larva";367;1
"Unit";"Overlord";"Larva";368;0
"Unit";"Overlord";"Larva";371;0
"Unit";"Overlord";"Larva";372;0
"Unit";"Zergling";"Larva";376;1
"Unit";"Zergling";"Larva";377;1
"Unit";"Zergling";"Larva";378;1
"Unit";"Zergling";"Larva";379;1
"Unit";"Zergling";"Larva";380;1
"Unit";"Zergling";"Larva";381;1
"Unit";"Zergling";"Larva";382;1
"Unit";"Zergling";"Larva";383;1
"Unit";"Zergling";"Larva";386;1
"Unit";"Zergling";"Larva";387;1
"Unit";"Zergling";"Larva";388;1
"Unit";"Zergling";"Larva";389;1
"Unit";"Hydralisk";"Larva";390;2
"Unit";"Hydralisk";"Larva";392;2
"Unit";"Hydralisk";"Larva";394;2
"Unit";"Overlord";"Larva";396;0
"Building";"CreepTumor";NA;396;0
"Unit";"Hydralisk";"Larva";396;2
"Unit";"Hydralisk";"Larva";398;2
"Unit";"Hydralisk";"Larva";400;2
"Unit";"Baneling";"Zergling";402;0
"Unit";"Baneling";"Zergling";402;0
"Unit";"Baneling";"Zergling";402;0
"Unit";"Baneling";"Zergling";402;0
"Unit";"Hydralisk";"Larva";402;2
"Unit";"Hydralisk";"Larva";404;2
"Unit";"Hydralisk";"Larva";406;2
"Unit";"Hydralisk";"Larva";408;2
"Unit";"Hydralisk";"Larva";410;2
"Unit";"Hydralisk";"Larva";412;2
"Unit";"Hydralisk";"Larva";414;2
"Unit";"Hydralisk";"Larva";416;2
"Unit";"Hydralisk";"Larva";418;2
"Unit";"Zergling";"Larva";420;1
"Unit";"Zergling";"Larva";421;1
"Unit";"Zergling";"Larva";422;1
"Unit";"Zergling";"Larva";423;1
"Unit";"Baneling";"Zergling";424;0
"Unit";"Baneling";"Zergling";424;0
"Unit";"Baneling";"Zergling";424;0
"Unit";"Baneling";"Zergling";424;0
"Unit";"Baneling";"Zergling";424;0
"Unit";"Baneling";"Zergling";424;0
"Unit";"Baneling";"Zergling";424;0
"Unit";"Baneling";"Zergling";424;0
"Unit";"Hydralisk";"Larva";424;2
"Unit";"Hydralisk";"Larva";426;2
"Unit";"Hydralisk";"Larva";428;2
"Unit";"Hydralisk";"Larva";430;2
"Unit";"Zergling";"Larva";433;1
"Unit";"Zergling";"Larva";434;1
"Unit";"Zergling";"Larva";435;1
"Unit";"Zergling";"Larva";436;1
"Unit";"Zergling";"Larva";437;1
"Unit";"Zergling";"Larva";438;1
"Unit";"Zergling";"Larva";439;1
"Unit";"Zergling";"Larva";440;1
"Unit";"Overlord";"Larva";441;0
"Unit";"Hydralisk";"Larva";441;2
"Unit";"Hydralisk";"Larva";443;2
"Unit";"Zergling";"Larva";445;1
"Unit";"Zergling";"Larva";446;1
"Unit";"Zergling";"Larva";447;1
"Unit";"Zergling";"Larva";448;1
"Unit";"Zergling";"Larva";449;1
"Unit";"Zergling";"Larva";450;1
"Unit";"Zergling";"Larva";451;1
"Unit";"Zergling";"Larva";452;1
"Unit";"Zergling";"Larva";453;1
"Unit";"Zergling";"Larva";454;1
"Unit";"Zergling";"Larva";455;1
"Unit";"Zergling";"Larva";456;1
"Unit";"Zergling";"Larva";457;1
"Unit";"Zergling";"Larva";458;1
"Building";"Extractor";NA;460;0
"Building";"Extractor";NA;460;0
"Building";"SporeCrawler";NA;460;0
"Unit";"Zergling";"Larva";460;1
"Unit";"Zergling";"Larva";461;1
"Unit";"Zergling";"Larva";462;1
"Unit";"Zergling";"Larva";463;1
"Building";"SpineCrawler";NA;464;0
"Building";"SpineCrawler";NA;464;0
"Unit";"Zergling";"Larva";464;1
"Unit";"Zergling";"Larva";465;1
"Unit";"Zergling";"Larva";466;1
"Unit";"Zergling";"Larva";467;1
"Unit";"Baneling";"Zergling";468;0
"Unit";"Baneling";"Zergling";468;0
"Unit";"Baneling";"Zergling";468;0
"Unit";"Baneling";"Zergling";468;0
"Unit";"Baneling";"Zergling";468;0
"Unit";"Baneling";"Zergling";468;0
"Unit";"Baneling";"Zergling";468;0
"Unit";"Baneling";"Zergling";468;0
"Unit";"Baneling";"Zergling";468;0
"Unit";"Baneling";"Zergling";468;0
"Unit";"Baneling";"Zergling";468;0
"Unit";"Baneling";"Zergling";468;0
"Unit";"Baneling";"Zergling";468;0
"Unit";"Baneling";"Zergling";468;0
"Unit";"Baneling";"Zergling";468;0
"Unit";"Baneling";"Zergling";468;0
"Unit";"Baneling";"Zergling";468;0
"Unit";"Baneling";"Zergling";468;0
"Unit";"Baneling";"Zergling";468;0
"Unit";"Baneling";"Zergling";468;0
"Unit";"Baneling";"Zergling";468;0
"Unit";"Baneling";"Zergling";468;0
"Unit";"Baneling";"Zergling";468;0
"Unit";"Baneling";"Zergling";468;0
"Unit";"Baneling";"Zergling";468;0
"Unit";"Baneling";"Zergling";468;0
"Upgrade";"SprayZerg";NA;477;0
"Upgrade";"SprayZerg";NA;477;0
"Upgrade";"SprayZerg";NA;477;0
"Upgrade";"zerglingmovementspeed";NA;477;0
"Upgrade";"overlordspeed";NA;477;0
"Upgrade";"SprayZerg";NA;477;0
"Upgrade";"SprayZerg";NA;477;0
"Upgrade";"EvolveMuscularAugments";NA;477;0
"Upgrade";"ZergMissileWeaponsLevel1";NA;477;0
"Upgrade";"CentrificalHooks";NA;477;0
"Upgrade";"SprayZerg";NA;477;0
"Upgrade";"ZergMissileWeaponsLevel2";NA;477;0
"Upgrade";"SprayZerg";NA;477;0
"Upgrade";"ZergGroundArmorsLevel1";NA;477;0
