"type";"unit_name";"on_building";"total_supply_lag";"supply"
"Unit";"Overlord";"Larva";13;0
"Building";"Hatchery";NA;16;0
"Building";"Extractor";NA;19;0
"Building";"SpawningPool";NA;19;0
"Building";"Hatchery";NA;23;0
"Unit";"Zergling";"Larva";24;1
"Unit";"Zergling";"Larva";25;1
"Unit";"Queen";"Hatchery";26;2
"Unit";"Queen";"Hatchery";29;2
"Unit";"Overlord";"Larva";31;0
"Unit";"Zergling";"Larva";33;1
"Unit";"Zergling";"Larva";34;1
"Unit";"Zergling";"Larva";35;1
"Unit";"Zergling";"Larva";36;1
"Unit";"Queen";"Hatchery";40;2
"Unit";"Overlord";"Larva";42;0
"Unit";"Queen";"Hatchery";43;2
"Building";"CreepTumorQueen";NA;47;0
"Unit";"Overlord";"Larva";51;0
"Building";"CreepTumor";NA;55;0
"Unit";"Overlord";"Larva";57;0
"Building";"RoachWarren";NA;58;0
"Building";"Extractor";NA;58;0
"Building";"Extractor";NA;58;0
"Building";"CreepTumorQueen";NA;60;0
"Building";"CreepTumor";NA;65;0
"Unit";"Overlord";"Larva";70;0
"Building";"SporeCrawler";NA;73;0
"Building";"CreepTumor";NA;73;0
"Unit";"Overlord";"Larva";73;0
"Building";"CreepTumor";NA;73;0
"Unit";"Roach";"Larva";73;2
"Unit";"Roach";"Larva";75;2
"Unit";"Roach";"Larva";77;2
"Unit";"Roach";"Larva";79;2
"Building";"SporeCrawler";NA;81;0
"Unit";"Roach";"Larva";81;2
"Unit";"Roach";"Larva";83;2
"Unit";"Roach";"Larva";85;2
"Unit";"Roach";"Larva";87;2
"Unit";"Roach";"Larva";89;2
"Building";"SporeCrawler";NA;91;0
"Unit";"Roach";"Larva";91;2
"Unit";"Roach";"Larva";93;2
"Unit";"Overlord";"Larva";96;0
"Unit";"Overlord";"Larva";96;0
"Building";"CreepTumorQueen";NA;96;0
"Unit";"Overlord";"Larva";96;0
"Building";"EvolutionChamber";NA;96;0
"Building";"CreepTumor";NA;96;0
"Building";"CreepTumor";NA;96;0
"Unit";"Overlord";"Larva";96;0
"Building";"CreepTumorQueen";NA;96;0
"Building";"CreepTumorQueen";NA;103;0
"Building";"Extractor";NA;105;0
"Upgrade";"GlialReconstitution";"RoachWarren";108;0
"Building";"Extractor";NA;112;0
"Unit";"Roach";"Larva";112;2
"Unit";"Roach";"Larva";114;2
"Unit";"Roach";"Larva";116;2
"Unit";"Roach";"Larva";118;2
"Unit";"Roach";"Larva";120;2
"Unit";"Roach";"Larva";122;2
"Unit";"Roach";"Larva";124;2
"Unit";"Roach";"Larva";126;2
"Unit";"Overlord";"Larva";128;0
"Building";"CreepTumor";NA;128;0
"Building";"CreepTumor";NA;128;0
"Building";"CreepTumor";NA;128;0
"Building";"CreepTumorQueen";NA;128;0
"Building";"CreepTumor";NA;128;0
"Unit";"Roach";"Larva";128;2
"Unit";"Roach";"Larva";130;2
"Unit";"Overlord";"Larva";132;0
"Unit";"Queen";"Hatchery";132;2
"Building";"Hatchery";NA;134;0
"Unit";"Roach";"Larva";134;2
"Unit";"Roach";"Larva";136;2
"Unit";"Roach";"Larva";138;2
"Unit";"Roach";"Larva";140;2
"Unit";"Overlord";"Larva";142;0
"Building";"CreepTumor";NA;142;0
"Building";"CreepTumorQueen";NA;142;0
"Unit";"Overlord";"Larva";142;0
"Unit";"Overlord";"Larva";142;0
"Unit";"Zergling";"Larva";142;1
"Unit";"Zergling";"Larva";143;1
"Unit";"Zergling";"Larva";144;1
"Unit";"Zergling";"Larva";145;1
"Unit";"Zergling";"Larva";146;1
"Unit";"Zergling";"Larva";147;1
"Unit";"Zergling";"Larva";148;1
"Unit";"Zergling";"Larva";149;1
"Unit";"Zergling";"Larva";150;1
"Unit";"Zergling";"Larva";151;1
"Unit";"Zergling";"Larva";152;1
"Unit";"Zergling";"Larva";153;1
"Unit";"Overlord";"Larva";154;0
"Unit";"Zergling";"Larva";154;1
"Unit";"Zergling";"Larva";155;1
"Unit";"Zergling";"Larva";156;1
"Unit";"Zergling";"Larva";157;1
"Unit";"Zergling";"Larva";158;1
"Unit";"Zergling";"Larva";159;1
"Unit";"Zergling";"Larva";160;1
"Unit";"Zergling";"Larva";161;1
"Unit";"Zergling";"Larva";162;1
"Unit";"Zergling";"Larva";163;1
"Unit";"Zergling";"Larva";164;1
"Unit";"Zergling";"Larva";165;1
"Unit";"Zergling";"Larva";166;1
"Unit";"Zergling";"Larva";167;1
"Unit";"Zergling";"Larva";168;1
"Unit";"Zergling";"Larva";169;1
"Unit";"Zergling";"Larva";170;1
"Unit";"Zergling";"Larva";171;1
"Building";"CreepTumor";NA;172;0
"Building";"CreepTumor";NA;172;0
"Building";"CreepTumor";NA;172;0
"Unit";"Zergling";"Larva";172;1
"Unit";"Zergling";"Larva";173;1
"Unit";"Zergling";"Larva";174;1
"Unit";"Zergling";"Larva";175;1
"Unit";"Zergling";"Larva";176;1
"Unit";"Zergling";"Larva";177;1
"Unit";"Zergling";"Larva";178;1
"Unit";"Zergling";"Larva";179;1
"Unit";"Zergling";"Larva";180;1
"Unit";"Zergling";"Larva";181;1
"Unit";"Zergling";"Larva";182;1
"Unit";"Zergling";"Larva";183;1
"Building";"BanelingNest";NA;184;0
"Unit";"Zergling";"Larva";184;1
"Unit";"Zergling";"Larva";185;1
"Unit";"Zergling";"Larva";186;1
"Unit";"Zergling";"Larva";187;1
"Unit";"Zergling";"Larva";188;1
"Unit";"Zergling";"Larva";189;1
"Unit";"Zergling";"Larva";190;1
"Unit";"Zergling";"Larva";191;1
"Unit";"Zergling";"Larva";192;1
"Unit";"Zergling";"Larva";193;1
"Unit";"Zergling";"Larva";194;1
"Unit";"Zergling";"Larva";195;1
"Unit";"Zergling";"Larva";196;1
"Unit";"Zergling";"Larva";197;1
"Unit";"Zergling";"Larva";198;1
"Unit";"Zergling";"Larva";199;1
"Building";"CreepTumor";NA;200;0
"Unit";"Zergling";"Larva";200;1
"Unit";"Zergling";"Larva";201;1
"Unit";"Zergling";"Larva";202;1
"Unit";"Zergling";"Larva";203;1
"Unit";"Zergling";"Larva";204;1
"Unit";"Zergling";"Larva";205;1
"Unit";"Zergling";"Larva";206;1
"Unit";"Zergling";"Larva";207;1
"Unit";"Zergling";"Larva";208;1
"Unit";"Zergling";"Larva";209;1
"Unit";"Zergling";"Larva";210;1
"Unit";"Zergling";"Larva";211;1
"Unit";"Zergling";"Larva";212;1
"Unit";"Zergling";"Larva";213;1
"Unit";"Zergling";"Larva";214;1
"Unit";"Zergling";"Larva";215;1
"Unit";"Zergling";"Larva";216;1
"Unit";"Zergling";"Larva";217;1
"Unit";"Zergling";"Larva";218;1
"Unit";"Zergling";"Larva";219;1
"Unit";"Zergling";"Larva";220;1
"Unit";"Zergling";"Larva";221;1
"Unit";"Zergling";"Larva";222;1
"Unit";"Zergling";"Larva";223;1
"Unit";"Zergling";"Larva";224;1
"Unit";"Zergling";"Larva";225;1
"Unit";"Zergling";"Larva";226;1
"Unit";"Zergling";"Larva";227;1
"Unit";"Zergling";"Larva";228;1
"Unit";"Zergling";"Larva";229;1
"Unit";"Zergling";"Larva";230;1
"Unit";"Zergling";"Larva";231;1
"Unit";"Zergling";"Larva";232;1
"Unit";"Zergling";"Larva";233;1
"Unit";"Zergling";"Larva";234;1
"Unit";"Zergling";"Larva";235;1
"Unit";"Zergling";"Larva";236;1
"Unit";"Zergling";"Larva";237;1
"Unit";"Zergling";"Larva";238;1
"Unit";"Zergling";"Larva";239;1
"Unit";"Zergling";"Larva";240;1
"Unit";"Zergling";"Larva";241;1
"Unit";"Zergling";"Larva";242;1
"Unit";"Zergling";"Larva";243;1
"Unit";"Zergling";"Larva";244;1
"Unit";"Zergling";"Larva";245;1
"Unit";"Zergling";"Larva";246;1
"Unit";"Zergling";"Larva";247;1
"Unit";"Zergling";"Larva";248;1
"Unit";"Zergling";"Larva";249;1
"Unit";"Zergling";"Larva";250;1
"Unit";"Zergling";"Larva";251;1
"Unit";"Zergling";"Larva";252;1
"Unit";"Zergling";"Larva";253;1
"Unit";"Zergling";"Larva";254;1
"Unit";"Zergling";"Larva";255;1
"Unit";"Zergling";"Larva";256;1
"Unit";"Zergling";"Larva";257;1
"Unit";"Zergling";"Larva";258;1
"Unit";"Zergling";"Larva";259;1
"Unit";"Zergling";"Larva";260;1
"Unit";"Zergling";"Larva";261;1
"Unit";"Zergling";"Larva";262;1
"Unit";"Zergling";"Larva";263;1
"Unit";"Zergling";"Larva";264;1
"Unit";"Zergling";"Larva";265;1
"Building";"CreepTumor";NA;266;0
"Unit";"Queen";"Hatchery";266;2
"Unit";"Zergling";"Larva";268;1
"Unit";"Zergling";"Larva";269;1
"Unit";"Zergling";"Larva";270;1
"Unit";"Zergling";"Larva";271;1
"Unit";"Zergling";"Larva";272;1
"Unit";"Zergling";"Larva";273;1
"Unit";"Zergling";"Larva";274;1
"Unit";"Zergling";"Larva";275;1
"Unit";"Baneling";"Zergling";276;0
"Unit";"Baneling";"Zergling";276;0
"Unit";"Baneling";"Zergling";276;0
"Unit";"Baneling";"Zergling";276;0
"Unit";"Baneling";"Zergling";276;0
"Unit";"Baneling";"Zergling";276;0
"Unit";"Baneling";"Zergling";276;0
"Unit";"Baneling";"Zergling";276;0
"Unit";"Baneling";"Zergling";276;0
"Unit";"Baneling";"Zergling";276;0
"Unit";"Baneling";"Zergling";276;0
"Unit";"Baneling";"Zergling";276;0
"Unit";"Roach";"Larva";276;2
"Unit";"Roach";"Larva";278;2
"Unit";"Roach";"Larva";280;2
"Unit";"Zergling";"Larva";282;1
"Unit";"Zergling";"Larva";283;1
"Unit";"Zergling";"Larva";284;1
"Unit";"Zergling";"Larva";285;1
"Unit";"Zergling";"Larva";286;1
"Unit";"Zergling";"Larva";287;1
"Unit";"Zergling";"Larva";288;1
"Unit";"Zergling";"Larva";289;1
"Unit";"Zergling";"Larva";290;1
"Unit";"Zergling";"Larva";291;1
"Unit";"Zergling";"Larva";292;1
"Unit";"Zergling";"Larva";293;1
"Unit";"Zergling";"Larva";294;1
"Unit";"Zergling";"Larva";295;1
"Unit";"Zergling";"Larva";296;1
"Unit";"Zergling";"Larva";297;1
"Unit";"Zergling";"Larva";298;1
"Unit";"Zergling";"Larva";299;1
"Unit";"Zergling";"Larva";300;1
"Unit";"Zergling";"Larva";301;1
"Unit";"Zergling";"Larva";302;1
"Unit";"Zergling";"Larva";303;1
"Unit";"Zergling";"Larva";304;1
"Unit";"Zergling";"Larva";305;1
"Unit";"Zergling";"Larva";306;1
"Unit";"Zergling";"Larva";307;1
"Unit";"Zergling";"Larva";308;1
"Unit";"Zergling";"Larva";309;1
"Unit";"Zergling";"Larva";310;1
"Unit";"Zergling";"Larva";311;1
"Unit";"Zergling";"Larva";312;1
"Unit";"Zergling";"Larva";313;1
"Unit";"Zergling";"Larva";314;1
"Unit";"Zergling";"Larva";315;1
"Unit";"Zergling";"Larva";316;1
"Unit";"Zergling";"Larva";317;1
"Unit";"Zergling";"Larva";318;1
"Unit";"Zergling";"Larva";319;1
"Unit";"Zergling";"Larva";320;1
"Unit";"Zergling";"Larva";321;1
"Unit";"Zergling";"Larva";322;1
"Unit";"Zergling";"Larva";323;1
"Unit";"Zergling";"Larva";324;1
"Unit";"Zergling";"Larva";325;1
"Unit";"Zergling";"Larva";326;1
"Unit";"Zergling";"Larva";327;1
"Unit";"Zergling";"Larva";328;1
"Unit";"Zergling";"Larva";329;1
"Unit";"Roach";"Larva";330;2
"Unit";"Roach";"Larva";332;2
"Unit";"Roach";"Larva";334;2
"Unit";"Zergling";"Larva";336;1
"Unit";"Zergling";"Larva";337;1
"Unit";"Zergling";"Larva";338;1
"Unit";"Zergling";"Larva";339;1
"Unit";"Zergling";"Larva";340;1
"Unit";"Zergling";"Larva";341;1
"Unit";"Zergling";"Larva";342;1
"Unit";"Zergling";"Larva";343;1
"Unit";"Zergling";"Larva";344;1
"Unit";"Zergling";"Larva";345;1
"Unit";"Zergling";"Larva";346;1
"Unit";"Zergling";"Larva";347;1
"Unit";"Zergling";"Larva";348;1
"Unit";"Zergling";"Larva";349;1
"Unit";"Zergling";"Larva";350;1
"Unit";"Zergling";"Larva";351;1
"Unit";"Zergling";"Larva";352;1
"Unit";"Zergling";"Larva";353;1
"Unit";"Zergling";"Larva";354;1
"Unit";"Zergling";"Larva";355;1
"Unit";"Baneling";"Zergling";356;0
"Unit";"Baneling";"Zergling";356;0
"Unit";"Baneling";"Zergling";356;0
"Unit";"Baneling";"Zergling";356;0
"Unit";"Baneling";"Zergling";356;0
"Unit";"Baneling";"Zergling";356;0
"Unit";"Baneling";"Zergling";356;0
"Unit";"Baneling";"Zergling";356;0
"Unit";"Baneling";"Zergling";356;0
"Unit";"Zergling";"Larva";356;1
"Unit";"Zergling";"Larva";357;1
"Unit";"Zergling";"Larva";358;1
"Unit";"Zergling";"Larva";359;1
"Unit";"Zergling";"Larva";360;1
"Unit";"Zergling";"Larva";361;1
"Upgrade";"SprayZerg";NA;362;0
"Upgrade";"SprayZerg";NA;362;0
"Upgrade";"SprayZerg";NA;362;0
"Upgrade";"SprayZerg";NA;362;0
"Upgrade";"zerglingmovementspeed";NA;362;0
"Upgrade";"SprayZerg";NA;362;0
"Upgrade";"SprayZerg";NA;362;0
"Upgrade";"ZergMissileWeaponsLevel1";NA;362;0
"Upgrade";"CentrificalHooks";NA;362;0
"Upgrade";"ZergMeleeWeaponsLevel1";NA;362;0
