"type";"unit_name";"on_building";"total_supply_lag";"supply"
"Unit";"Overlord";"Larva";13;0
"Building";"Hatchery";NA;17;0
"Building";"SpawningPool";NA;18;0
"Building";"Extractor";NA;18;0
"Unit";"Overlord";"Larva";22;0
"Unit";"Queen";"Hatchery";22;2
"Unit";"Zergling";"Larva";24;1
"Unit";"Zergling";"Larva";25;1
"Unit";"Zergling";"Larva";26;1
"Unit";"Zergling";"Larva";27;1
"Unit";"Queen";"Hatchery";28;2
"Unit";"Zergling";"Larva";30;1
"Unit";"Zergling";"Larva";31;1
"Unit";"Queen";"Hatchery";36;2
"Unit";"Overlord";"Larva";40;0
"Building";"CreepTumorQueen";NA;42;0
"Building";"Hatchery";NA;50;0
"Unit";"Overlord";"Larva";51;0
"Unit";"Overlord";"Larva";51;0
"Building";"EvolutionChamber";NA;51;0
"Building";"CreepTumorQueen";NA;52;0
"Unit";"Overlord";"Larva";52;0
"Unit";"Queen";"Hatchery";52;2
"Unit";"Queen";"Hatchery";54;2
"Unit";"Overlord";"Larva";66;0
"Building";"RoachWarren";NA;68;0
"Unit";"Overlord";"Larva";69;0
"Unit";"Zergling";"Larva";69;1
"Unit";"Zergling";"Larva";70;1
"Unit";"Zergling";"Larva";71;1
"Unit";"Zergling";"Larva";72;1
"Unit";"Zergling";"Larva";73;1
"Unit";"Zergling";"Larva";74;1
"Unit";"Zergling";"Larva";75;1
"Unit";"Zergling";"Larva";76;1
"Unit";"Zergling";"Larva";77;1
"Unit";"Zergling";"Larva";78;1
"Unit";"Zergling";"Larva";79;1
"Unit";"Zergling";"Larva";80;1
"Unit";"Zergling";"Larva";81;1
"Unit";"Zergling";"Larva";82;1
"Unit";"Zergling";"Larva";83;1
"Unit";"Zergling";"Larva";84;1
"Building";"SporeCrawler";NA;94;0
"Building";"SporeCrawler";NA;94;0
"Building";"CreepTumor";NA;95;0
"Building";"SporeCrawler";NA;102;0
"Unit";"Zergling";"Larva";102;1
"Unit";"Zergling";"Larva";103;1
"Unit";"Zergling";"Larva";104;1
"Unit";"Zergling";"Larva";105;1
"Unit";"Zergling";"Larva";106;1
"Unit";"Zergling";"Larva";107;1
"Unit";"Zergling";"Larva";108;1
"Unit";"Zergling";"Larva";109;1
"Unit";"Zergling";"Larva";110;1
"Unit";"Zergling";"Larva";111;1
"Unit";"Zergling";"Larva";112;1
"Unit";"Zergling";"Larva";113;1
"Unit";"Zergling";"Larva";114;1
"Unit";"Zergling";"Larva";115;1
"Unit";"Zergling";"Larva";116;1
"Unit";"Zergling";"Larva";117;1
"Unit";"Zergling";"Larva";118;1
"Unit";"Zergling";"Larva";119;1
"Unit";"Zergling";"Larva";120;1
"Unit";"Zergling";"Larva";121;1
"Unit";"Zergling";"Larva";122;1
"Unit";"Zergling";"Larva";123;1
"Unit";"Zergling";"Larva";124;1
"Unit";"Zergling";"Larva";125;1
"Unit";"Zergling";"Larva";126;1
"Unit";"Zergling";"Larva";127;1
"Unit";"Zergling";"Larva";128;1
"Unit";"Zergling";"Larva";129;1
"Unit";"Zergling";"Larva";140;1
"Unit";"Zergling";"Larva";141;1
"Unit";"Zergling";"Larva";142;1
"Unit";"Zergling";"Larva";143;1
"Unit";"Zergling";"Larva";144;1
"Unit";"Zergling";"Larva";145;1
"Unit";"Zergling";"Larva";146;1
"Unit";"Zergling";"Larva";147;1
"Unit";"Zergling";"Larva";148;1
"Unit";"Zergling";"Larva";149;1
"Unit";"Zergling";"Larva";150;1
"Unit";"Zergling";"Larva";151;1
"Unit";"Zergling";"Larva";152;1
"Unit";"Zergling";"Larva";153;1
"Unit";"Zergling";"Larva";154;1
"Unit";"Zergling";"Larva";155;1
"Unit";"Zergling";"Larva";156;1
"Unit";"Zergling";"Larva";157;1
"Building";"Extractor";NA;170;0
"Building";"Extractor";NA;171;0
"Building";"Extractor";NA;173;0
"Building";"Extractor";NA;173;0
"Building";"Extractor";NA;181;0
"Building";"Hatchery";NA;188;0
"Unit";"Zergling";"Larva";193;1
"Unit";"Zergling";"Larva";194;1
"Unit";"Zergling";"Larva";195;1
"Unit";"Zergling";"Larva";196;1
"Unit";"Zergling";"Larva";197;1
"Unit";"Zergling";"Larva";198;1
"Building";"BanelingNest";NA;199;0
"Unit";"Zergling";"Larva";199;1
"Unit";"Zergling";"Larva";200;1
"Unit";"Zergling";"Larva";201;1
"Unit";"Zergling";"Larva";202;1
"Building";"Hatchery";NA;203;0
"Unit";"Zergling";"Larva";203;1
"Unit";"Zergling";"Larva";204;1
"Unit";"Zergling";"Larva";205;1
"Unit";"Zergling";"Larva";206;1
"Building";"CreepTumor";NA;207;0
"Building";"CreepTumorQueen";NA;207;0
"Building";"CreepTumorQueen";NA;207;0
"Building";"CreepTumorQueen";NA;207;0
"Unit";"Overlord";"Larva";207;0
"Unit";"Overlord";"Larva";207;0
"Unit";"Overlord";"Larva";207;0
"Unit";"Overlord";"Larva";207;0
"Unit";"Overlord";"Larva";207;0
"Unit";"Overlord";"Larva";207;0
"Unit";"Overlord";"Larva";207;0
"Unit";"Overlord";"Larva";207;0
"Building";"Spire";NA;207;0
"Building";"CreepTumorQueen";NA;207;0
"Unit";"Zergling";"Larva";207;1
"Unit";"Zergling";"Larva";208;1
"Unit";"Zergling";"Larva";209;1
"Unit";"Zergling";"Larva";210;1
"Unit";"Baneling";"Zergling";211;0
"Unit";"Baneling";"Zergling";211;0
"Unit";"Baneling";"Zergling";211;0
"Unit";"Baneling";"Zergling";211;0
"Unit";"Baneling";"Zergling";211;0
"Unit";"Baneling";"Zergling";211;0
"Unit";"Zergling";"Larva";211;1
"Unit";"Zergling";"Larva";212;1
"Unit";"Zergling";"Larva";213;1
"Unit";"Zergling";"Larva";214;1
"Unit";"Zergling";"Larva";215;1
"Unit";"Zergling";"Larva";216;1
"Unit";"Zergling";"Larva";217;1
"Unit";"Zergling";"Larva";218;1
"Unit";"Zergling";"Larva";219;1
"Unit";"Zergling";"Larva";220;1
"Unit";"Zergling";"Larva";221;1
"Unit";"Zergling";"Larva";222;1
"Building";"CreepTumor";NA;223;0
"Building";"CreepTumor";NA;223;0
"Building";"CreepTumor";NA;223;0
"Unit";"Zergling";"Larva";223;1
"Unit";"Zergling";"Larva";224;1
"Unit";"Zergling";"Larva";225;1
"Unit";"Zergling";"Larva";226;1
"Unit";"Zergling";"Larva";227;1
"Unit";"Zergling";"Larva";228;1
"Unit";"Zergling";"Larva";229;1
"Unit";"Zergling";"Larva";230;1
"Unit";"Baneling";"Zergling";231;0
"Unit";"Baneling";"Zergling";231;0
"Unit";"Baneling";"Zergling";231;0
"Unit";"Baneling";"Zergling";231;0
"Unit";"Zergling";"Larva";231;1
"Unit";"Zergling";"Larva";232;1
"Unit";"Queen";"Hatchery";233;2
"Unit";"Zergling";"Larva";235;1
"Unit";"Zergling";"Larva";236;1
"Unit";"Zergling";"Larva";237;1
"Unit";"Zergling";"Larva";238;1
"Unit";"Zergling";"Larva";239;1
"Unit";"Zergling";"Larva";240;1
"Unit";"Zergling";"Larva";241;1
"Unit";"Zergling";"Larva";242;1
"Unit";"Zergling";"Larva";243;1
"Unit";"Zergling";"Larva";244;1
"Unit";"Zergling";"Larva";245;1
"Unit";"Zergling";"Larva";246;1
"Unit";"Zergling";"Larva";247;1
"Unit";"Zergling";"Larva";248;1
"Building";"CreepTumorQueen";NA;249;0
"Unit";"Zergling";"Larva";249;1
"Unit";"Zergling";"Larva";250;1
"Unit";"Zergling";"Larva";251;1
"Unit";"Zergling";"Larva";252;1
"Unit";"Zergling";"Larva";253;1
"Unit";"Zergling";"Larva";254;1
"Unit";"Zergling";"Larva";255;1
"Unit";"Zergling";"Larva";256;1
"Unit";"Zergling";"Larva";257;1
"Unit";"Zergling";"Larva";258;1
"Unit";"Zergling";"Larva";259;1
"Unit";"Zergling";"Larva";260;1
"Unit";"Zergling";"Larva";261;1
"Unit";"Zergling";"Larva";262;1
"Unit";"Zergling";"Larva";263;1
"Unit";"Zergling";"Larva";264;1
"Unit";"Zergling";"Larva";265;1
"Unit";"Zergling";"Larva";266;1
"Unit";"Zergling";"Larva";267;1
"Unit";"Zergling";"Larva";268;1
"Unit";"Zergling";"Larva";269;1
"Unit";"Zergling";"Larva";270;1
"Unit";"Zergling";"Larva";271;1
"Unit";"Zergling";"Larva";272;1
"Unit";"Zergling";"Larva";273;1
"Unit";"Zergling";"Larva";274;1
"Unit";"Zergling";"Larva";275;1
"Unit";"Zergling";"Larva";276;1
"Unit";"Zergling";"Larva";277;1
"Unit";"Zergling";"Larva";278;1
"Unit";"Zergling";"Larva";279;1
"Unit";"Zergling";"Larva";280;1
"Unit";"Baneling";"Zergling";287;0
"Unit";"Baneling";"Zergling";287;0
"Unit";"Baneling";"Zergling";287;0
"Unit";"Baneling";"Zergling";287;0
"Unit";"Baneling";"Zergling";287;0
"Unit";"Baneling";"Zergling";287;0
"Unit";"Baneling";"Zergling";287;0
"Unit";"Baneling";"Zergling";287;0
"Unit";"Baneling";"Zergling";287;0
"Unit";"Baneling";"Zergling";287;0
"Unit";"Baneling";"Zergling";287;0
"Unit";"Baneling";"Zergling";287;0
"Unit";"Baneling";"Zergling";287;0
"Unit";"Baneling";"Zergling";287;0
"Unit";"Baneling";"Zergling";287;0
"Unit";"Zergling";"Larva";287;1
"Unit";"Zergling";"Larva";288;1
"Unit";"Zergling";"Larva";289;1
"Unit";"Zergling";"Larva";290;1
"Building";"CreepTumorQueen";NA;291;0
"Unit";"Zergling";"Larva";291;1
"Unit";"Zergling";"Larva";292;1
"Unit";"Zergling";"Larva";293;1
"Unit";"Zergling";"Larva";294;1
"Building";"CreepTumor";NA;295;0
"Unit";"Overlord";"Larva";296;0
"Building";"Extractor";NA;296;0
"Unit";"Zergling";"Larva";296;1
"Unit";"Zergling";"Larva";297;1
"Unit";"Zergling";"Larva";298;1
"Unit";"Zergling";"Larva";299;1
"Unit";"Overlord";"Larva";300;0
"Unit";"Mutalisk";"Larva";300;2
"Unit";"Mutalisk";"Larva";302;2
"Unit";"Mutalisk";"Larva";304;2
"Unit";"Mutalisk";"Larva";306;2
"Unit";"Mutalisk";"Larva";308;2
"Unit";"Mutalisk";"Larva";310;2
"Unit";"Mutalisk";"Larva";312;2
"Building";"SporeCrawler";NA;314;0
"Unit";"Queen";"Hatchery";314;2
"Unit";"Mutalisk";"Larva";322;2
"Unit";"Mutalisk";"Larva";324;2
"Unit";"Mutalisk";"Larva";326;2
"Unit";"Mutalisk";"Larva";328;2
"Unit";"Zergling";"Larva";330;1
"Unit";"Zergling";"Larva";331;1
"Unit";"Zergling";"Larva";332;1
"Unit";"Zergling";"Larva";333;1
"Unit";"Zergling";"Larva";334;1
"Unit";"Zergling";"Larva";335;1
"Unit";"Zergling";"Larva";336;1
"Unit";"Zergling";"Larva";337;1
"Unit";"Zergling";"Larva";338;1
"Unit";"Zergling";"Larva";339;1
"Unit";"Zergling";"Larva";340;1
"Unit";"Zergling";"Larva";341;1
"Unit";"Zergling";"Larva";342;1
"Unit";"Zergling";"Larva";343;1
"Unit";"Zergling";"Larva";344;1
"Unit";"Zergling";"Larva";345;1
"Unit";"Zergling";"Larva";346;1
"Unit";"Zergling";"Larva";347;1
"Unit";"Zergling";"Larva";348;1
"Unit";"Zergling";"Larva";349;1
"Unit";"Zergling";"Larva";350;1
"Unit";"Zergling";"Larva";351;1
"Unit";"Zergling";"Larva";352;1
"Unit";"Zergling";"Larva";353;1
"Unit";"Zergling";"Larva";354;1
"Unit";"Zergling";"Larva";355;1
"Unit";"Zergling";"Larva";356;1
"Unit";"Zergling";"Larva";357;1
"Unit";"Zergling";"Larva";358;1
"Unit";"Zergling";"Larva";359;1
"Unit";"Zergling";"Larva";360;1
"Unit";"Zergling";"Larva";361;1
"Unit";"Zergling";"Larva";362;1
"Unit";"Zergling";"Larva";363;1
"Unit";"Zergling";"Larva";364;1
"Unit";"Zergling";"Larva";365;1
"Unit";"Zergling";"Larva";366;1
"Unit";"Zergling";"Larva";367;1
"Unit";"Zergling";"Larva";368;1
"Unit";"Zergling";"Larva";369;1
"Building";"CreepTumor";NA;370;0
"Unit";"Zergling";"Larva";370;1
"Unit";"Zergling";"Larva";371;1
"Unit";"Zergling";"Larva";372;1
"Unit";"Zergling";"Larva";373;1
"Unit";"Zergling";"Larva";374;1
"Unit";"Zergling";"Larva";375;1
"Building";"Extractor";NA;376;0
"Unit";"Baneling";"Zergling";376;0
"Unit";"Baneling";"Zergling";376;0
"Unit";"Baneling";"Zergling";376;0
"Unit";"Baneling";"Zergling";376;0
"Unit";"Baneling";"Zergling";376;0
"Unit";"Baneling";"Zergling";376;0
"Unit";"Baneling";"Zergling";376;0
"Unit";"Baneling";"Zergling";376;0
"Unit";"Baneling";"Zergling";376;0
"Unit";"Baneling";"Zergling";376;0
"Unit";"Baneling";"Zergling";376;0
"Building";"CreepTumorQueen";NA;376;0
"Building";"CreepTumor";NA;376;0
"Building";"CreepTumor";NA;376;0
"Building";"Hatchery";NA;376;0
"Building";"CreepTumorQueen";NA;376;0
"Building";"CreepTumorQueen";NA;376;0
"Building";"CreepTumorQueen";NA;376;0
"Unit";"Zergling";"Larva";376;1
"Unit";"Zergling";"Larva";377;1
"Unit";"Zergling";"Larva";378;1
"Unit";"Zergling";"Larva";379;1
"Unit";"Overlord";"Larva";380;0
"Unit";"Baneling";"Zergling";380;0
"Unit";"Baneling";"Zergling";380;0
"Unit";"Baneling";"Zergling";380;0
"Unit";"Baneling";"Zergling";380;0
"Unit";"Baneling";"Zergling";380;0
"Unit";"Baneling";"Zergling";380;0
"Unit";"Baneling";"Zergling";380;0
"Unit";"Baneling";"Zergling";380;0
"Unit";"Baneling";"Zergling";380;0
"Unit";"Baneling";"Zergling";380;0
"Unit";"Overlord";"Larva";380;0
"Building";"CreepTumor";NA;380;0
"Unit";"Overlord";"Larva";380;0
"Building";"InfestationPit";NA;380;0
"Unit";"Zergling";"Larva";380;1
"Unit";"Zergling";"Larva";381;1
"Unit";"Overlord";"Larva";382;0
"Unit";"Overlord";"Larva";382;0
"Unit";"Zergling";"Larva";382;1
"Unit";"Zergling";"Larva";383;1
"Unit";"Zergling";"Larva";384;1
"Unit";"Zergling";"Larva";385;1
"Unit";"Zergling";"Larva";386;1
"Unit";"Zergling";"Larva";387;1
"Unit";"Overlord";"Larva";388;0
"Unit";"Mutalisk";"Larva";388;2
"Unit";"Mutalisk";"Larva";390;2
"Unit";"Mutalisk";"Larva";392;2
"Unit";"Overlord";"Larva";394;0
"Unit";"Mutalisk";"Larva";394;2
"Unit";"Mutalisk";"Larva";396;2
"Unit";"Mutalisk";"Larva";398;2
"Unit";"Mutalisk";"Larva";400;2
"Unit";"Mutalisk";"Larva";402;2
"Unit";"Zergling";"Larva";404;1
"Unit";"Zergling";"Larva";405;1
"Unit";"Zergling";"Larva";406;1
"Unit";"Zergling";"Larva";407;1
"Unit";"Zergling";"Larva";408;1
"Unit";"Zergling";"Larva";409;1
"Unit";"Zergling";"Larva";410;1
"Unit";"Zergling";"Larva";411;1
"Building";"CreepTumor";NA;412;0
"Unit";"Zergling";"Larva";412;1
"Unit";"Zergling";"Larva";413;1
"Unit";"Queen";"Hatchery";414;2
"Unit";"Zergling";"Larva";416;1
"Unit";"Zergling";"Larva";417;1
"Unit";"Zergling";"Larva";418;1
"Unit";"Zergling";"Larva";419;1
"Unit";"Overlord";"Larva";420;0
"Unit";"Baneling";"Zergling";420;0
"Unit";"Baneling";"Zergling";420;0
"Unit";"Baneling";"Zergling";420;0
"Unit";"Baneling";"Zergling";420;0
"Unit";"Baneling";"Zergling";420;0
"Unit";"Baneling";"Zergling";420;0
"Unit";"Baneling";"Zergling";420;0
"Unit";"Baneling";"Zergling";420;0
"Unit";"Baneling";"Zergling";420;0
"Unit";"Baneling";"Zergling";420;0
"Unit";"Baneling";"Zergling";420;0
"Unit";"Baneling";"Zergling";420;0
"Unit";"Baneling";"Zergling";420;0
"Unit";"Overlord";"Larva";420;0
"Building";"CreepTumor";NA;420;0
"Building";"CreepTumor";NA;420;0
"Building";"CreepTumor";NA;420;0
"Building";"CreepTumor";NA;420;0
"Unit";"Baneling";"Zergling";420;0
"Unit";"Baneling";"Zergling";420;0
"Unit";"Baneling";"Zergling";420;0
"Unit";"Baneling";"Zergling";420;0
"Unit";"Baneling";"Zergling";420;0
"Unit";"Baneling";"Zergling";420;0
"Unit";"Baneling";"Zergling";420;0
"Unit";"Baneling";"Zergling";420;0
"Unit";"Baneling";"Zergling";420;0
"Unit";"Baneling";"Zergling";420;0
"Unit";"Baneling";"Zergling";420;0
"Unit";"Baneling";"Zergling";420;0
"Unit";"Baneling";"Zergling";420;0
"Unit";"Baneling";"Zergling";420;0
"Unit";"Baneling";"Zergling";420;0
"Unit";"Baneling";"Zergling";420;0
"Unit";"Baneling";"Zergling";420;0
"Unit";"Baneling";"Zergling";420;0
"Unit";"Baneling";"Zergling";420;0
"Unit";"Baneling";"Zergling";420;0
"Unit";"Baneling";"Zergling";420;0
"Unit";"Baneling";"Zergling";420;0
"Unit";"Baneling";"Zergling";420;0
"Unit";"Baneling";"Zergling";420;0
"Unit";"Baneling";"Zergling";420;0
"Unit";"Baneling";"Zergling";420;0
"Unit";"Baneling";"Zergling";420;0
"Building";"CreepTumor";NA;420;0
"Building";"CreepTumor";NA;420;0
"Building";"CreepTumor";NA;420;0
"Building";"CreepTumor";NA;420;0
"Unit";"Overlord";"Larva";420;0
"Building";"CreepTumor";NA;420;0
"Building";"CreepTumorQueen";NA;420;0
"Building";"CreepTumorQueen";NA;420;0
"Unit";"Zergling";"Larva";420;1
"Unit";"Zergling";"Larva";421;1
"Unit";"Zergling";"Larva";422;1
"Unit";"Zergling";"Larva";423;1
"Unit";"Zergling";"Larva";424;1
"Unit";"Zergling";"Larva";425;1
"Unit";"Zergling";"Larva";426;1
"Unit";"Zergling";"Larva";427;1
"Unit";"Zergling";"Larva";428;1
"Unit";"Zergling";"Larva";429;1
"Unit";"Zergling";"Larva";430;1
"Unit";"Zergling";"Larva";431;1
"Unit";"Zergling";"Larva";432;1
"Unit";"Zergling";"Larva";433;1
"Unit";"Zergling";"Larva";434;1
"Unit";"Zergling";"Larva";435;1
"Unit";"Zergling";"Larva";436;1
"Unit";"Zergling";"Larva";437;1
"Unit";"Zergling";"Larva";438;1
"Unit";"Zergling";"Larva";439;1
"Unit";"Zergling";"Larva";440;1
"Unit";"Zergling";"Larva";441;1
"Unit";"Zergling";"Larva";442;1
"Unit";"Zergling";"Larva";443;1
"Unit";"Zergling";"Larva";444;1
"Unit";"Zergling";"Larva";445;1
"Unit";"Zergling";"Larva";446;1
"Unit";"Zergling";"Larva";447;1
"Unit";"Zergling";"Larva";448;1
"Unit";"Zergling";"Larva";449;1
"Unit";"Zergling";"Larva";450;1
"Unit";"Zergling";"Larva";451;1
"Building";"CreepTumor";NA;455;0
"Building";"CreepTumor";NA;456;0
"Building";"CreepTumor";NA;456;0
"Building";"CreepTumor";NA;456;0
"Unit";"Mutalisk";"Larva";456;2
"Unit";"Mutalisk";"Larva";458;2
"Unit";"Mutalisk";"Larva";460;2
"Unit";"Infestor";"Larva";462;2
"Building";"Hatchery";NA;464;0
"Unit";"Mutalisk";"Larva";464;2
"Unit";"Mutalisk";"Larva";466;2
"Unit";"Mutalisk";"Larva";468;2
"Unit";"Mutalisk";"Larva";470;2
"Unit";"Mutalisk";"Larva";472;2
"Unit";"Mutalisk";"Larva";474;2
"Unit";"Mutalisk";"Larva";476;2
"Unit";"Mutalisk";"Larva";478;2
"Unit";"Zergling";"Larva";480;1
"Unit";"Zergling";"Larva";481;1
"Building";"Hatchery";NA;482;0
"Building";"CreepTumor";NA;482;0
"Building";"CreepTumor";NA;482;0
"Building";"CreepTumor";NA;482;0
"Building";"CreepTumor";NA;482;0
"Unit";"Zergling";"Larva";482;1
"Unit";"Zergling";"Larva";483;1
"Unit";"Zergling";"Larva";484;1
"Unit";"Zergling";"Larva";485;1
"Unit";"Zergling";"Larva";486;1
"Unit";"Zergling";"Larva";487;1
"Unit";"Zergling";"Larva";488;1
"Unit";"Zergling";"Larva";489;1
"Unit";"Zergling";"Larva";490;1
"Unit";"Zergling";"Larva";491;1
"Unit";"Zergling";"Larva";492;1
"Unit";"Zergling";"Larva";493;1
"Unit";"Zergling";"Larva";494;1
"Unit";"Zergling";"Larva";495;1
"Unit";"Zergling";"Larva";496;1
"Unit";"Zergling";"Larva";497;1
"Unit";"Zergling";"Larva";498;1
"Unit";"Zergling";"Larva";499;1
"Unit";"Zergling";"Larva";500;1
"Unit";"Zergling";"Larva";501;1
"Unit";"Zergling";"Larva";502;1
"Unit";"Zergling";"Larva";503;1
"Unit";"Zergling";"Larva";504;1
"Unit";"Zergling";"Larva";505;1
"Unit";"Zergling";"Larva";506;1
"Unit";"Zergling";"Larva";507;1
"Unit";"Zergling";"Larva";508;1
"Unit";"Zergling";"Larva";509;1
"Unit";"Zergling";"Larva";510;1
"Unit";"Zergling";"Larva";511;1
"Unit";"Zergling";"Larva";512;1
"Unit";"Zergling";"Larva";513;1
"Unit";"Zergling";"Larva";514;1
"Unit";"Zergling";"Larva";515;1
"Unit";"Zergling";"Larva";516;1
"Unit";"Zergling";"Larva";517;1
"Unit";"Zergling";"Larva";518;1
"Unit";"Zergling";"Larva";519;1
"Unit";"Zergling";"Larva";520;1
"Unit";"Zergling";"Larva";521;1
"Unit";"Zergling";"Larva";522;1
"Unit";"Zergling";"Larva";523;1
"Unit";"Zergling";"Larva";524;1
"Unit";"Zergling";"Larva";525;1
"Unit";"Zergling";"Larva";526;1
"Unit";"Zergling";"Larva";527;1
"Unit";"Zergling";"Larva";528;1
"Unit";"Zergling";"Larva";529;1
"Building";"CreepTumor";NA;530;0
"Building";"CreepTumor";NA;530;0
"Unit";"Zergling";"Larva";530;1
"Unit";"Zergling";"Larva";531;1
"Unit";"Baneling";"Zergling";532;0
"Unit";"Baneling";"Zergling";532;0
"Unit";"Baneling";"Zergling";532;0
"Unit";"Baneling";"Zergling";532;0
"Unit";"Baneling";"Zergling";532;0
"Unit";"Baneling";"Zergling";532;0
"Unit";"Baneling";"Zergling";532;0
"Unit";"Baneling";"Zergling";532;0
"Unit";"Baneling";"Zergling";532;0
"Unit";"Baneling";"Zergling";532;0
"Unit";"Baneling";"Zergling";532;0
"Unit";"Baneling";"Zergling";532;0
"Unit";"Baneling";"Zergling";532;0
"Unit";"Baneling";"Zergling";532;0
"Unit";"Zergling";"Larva";532;1
"Unit";"Zergling";"Larva";533;1
"Unit";"Zergling";"Larva";534;1
"Unit";"Zergling";"Larva";535;1
"Unit";"Zergling";"Larva";536;1
"Unit";"Zergling";"Larva";537;1
"Unit";"Zergling";"Larva";538;1
"Unit";"Zergling";"Larva";539;1
"Unit";"Zergling";"Larva";540;1
"Unit";"Zergling";"Larva";541;1
"Building";"CreepTumor";NA;542;0
"Building";"CreepTumor";NA;542;0
"Building";"CreepTumor";NA;542;0
"Building";"CreepTumor";NA;542;0
"Unit";"Baneling";"Zergling";542;0
"Unit";"Baneling";"Zergling";542;0
"Unit";"Baneling";"Zergling";542;0
"Unit";"Baneling";"Zergling";542;0
"Unit";"Baneling";"Zergling";542;0
"Unit";"Baneling";"Zergling";542;0
"Unit";"Baneling";"Zergling";542;0
"Unit";"Baneling";"Zergling";542;0
"Unit";"Baneling";"Zergling";542;0
"Unit";"Baneling";"Zergling";542;0
"Unit";"Baneling";"Zergling";542;0
"Unit";"Baneling";"Zergling";542;0
"Unit";"Baneling";"Zergling";542;0
"Unit";"Baneling";"Zergling";542;0
"Unit";"Baneling";"Zergling";542;0
"Unit";"Baneling";"Zergling";542;0
"Unit";"Baneling";"Zergling";542;0
"Unit";"Baneling";"Zergling";542;0
"Unit";"Zergling";"Larva";542;1
"Unit";"Zergling";"Larva";543;1
"Unit";"Zergling";"Larva";544;1
"Unit";"Zergling";"Larva";545;1
"Unit";"Zergling";"Larva";546;1
"Unit";"Zergling";"Larva";547;1
"Unit";"Zergling";"Larva";548;1
"Unit";"Zergling";"Larva";549;1
"Unit";"Zergling";"Larva";550;1
"Unit";"Zergling";"Larva";551;1
"Unit";"Zergling";"Larva";552;1
"Unit";"Zergling";"Larva";553;1
"Unit";"Zergling";"Larva";554;1
"Unit";"Zergling";"Larva";555;1
"Unit";"Zergling";"Larva";556;1
"Unit";"Zergling";"Larva";557;1
"Unit";"Zergling";"Larva";558;1
"Unit";"Zergling";"Larva";559;1
"Unit";"Zergling";"Larva";560;1
"Unit";"Zergling";"Larva";561;1
"Unit";"Zergling";"Larva";562;1
"Unit";"Zergling";"Larva";563;1
"Unit";"Zergling";"Larva";564;1
"Unit";"Zergling";"Larva";565;1
"Unit";"Zergling";"Larva";566;1
"Unit";"Zergling";"Larva";567;1
"Unit";"Zergling";"Larva";568;1
"Unit";"Zergling";"Larva";569;1
"Unit";"Zergling";"Larva";570;1
"Unit";"Zergling";"Larva";571;1
"Unit";"Zergling";"Larva";572;1
"Unit";"Zergling";"Larva";573;1
"Unit";"Zergling";"Larva";574;1
"Unit";"Zergling";"Larva";575;1
"Unit";"Zergling";"Larva";576;1
"Unit";"Zergling";"Larva";577;1
"Unit";"Zergling";"Larva";578;1
"Unit";"Zergling";"Larva";579;1
"Unit";"Zergling";"Larva";580;1
"Unit";"Zergling";"Larva";581;1
"Unit";"Zergling";"Larva";582;1
"Unit";"Zergling";"Larva";583;1
"Unit";"Zergling";"Larva";584;1
"Unit";"Zergling";"Larva";585;1
"Unit";"Zergling";"Larva";586;1
"Unit";"Zergling";"Larva";587;1
"Unit";"Zergling";"Larva";588;1
"Unit";"Zergling";"Larva";589;1
"Unit";"Zergling";"Larva";590;1
"Unit";"Zergling";"Larva";591;1
"Unit";"Zergling";"Larva";592;1
"Unit";"Zergling";"Larva";593;1
"Unit";"Zergling";"Larva";594;1
"Unit";"Zergling";"Larva";595;1
"Unit";"Zergling";"Larva";596;1
"Unit";"Zergling";"Larva";597;1
"Unit";"Zergling";"Larva";598;1
"Unit";"Zergling";"Larva";599;1
"Unit";"Zergling";"Larva";600;1
"Unit";"Zergling";"Larva";601;1
"Unit";"Zergling";"Larva";602;1
"Unit";"Zergling";"Larva";603;1
"Unit";"Zergling";"Larva";604;1
"Unit";"Zergling";"Larva";605;1
"Unit";"Zergling";"Larva";606;1
"Unit";"Zergling";"Larva";607;1
"Unit";"Zergling";"Larva";608;1
"Unit";"Zergling";"Larva";609;1
"Building";"UltraliskCavern";NA;610;0
"Building";"CreepTumor";NA;610;0
"Building";"CreepTumor";NA;610;0
"Building";"CreepTumor";NA;610;0
"Unit";"Baneling";"Zergling";610;0
"Unit";"Baneling";"Zergling";610;0
"Unit";"Baneling";"Zergling";610;0
"Unit";"Baneling";"Zergling";610;0
"Unit";"Baneling";"Zergling";610;0
"Unit";"Baneling";"Zergling";610;0
"Unit";"Baneling";"Zergling";610;0
"Unit";"Baneling";"Zergling";610;0
"Unit";"Baneling";"Zergling";610;0
"Unit";"Baneling";"Zergling";610;0
"Unit";"Baneling";"Zergling";610;0
"Unit";"Baneling";"Zergling";610;0
"Unit";"Baneling";"Zergling";610;0
"Unit";"Baneling";"Zergling";610;0
"Unit";"Baneling";"Zergling";610;0
"Unit";"Baneling";"Zergling";610;0
"Unit";"Baneling";"Zergling";610;0
"Unit";"Baneling";"Zergling";610;0
"Unit";"Baneling";"Zergling";610;0
"Unit";"Baneling";"Zergling";610;0
"Unit";"Baneling";"Zergling";610;0
"Unit";"Baneling";"Zergling";610;0
"Unit";"Zergling";"Larva";610;1
"Unit";"Zergling";"Larva";611;1
"Building";"CreepTumor";NA;612;0
"Unit";"Zergling";"Larva";612;1
"Unit";"Zergling";"Larva";613;1
"Unit";"Zergling";"Larva";614;1
"Unit";"Zergling";"Larva";615;1
"Unit";"Zergling";"Larva";616;1
"Unit";"Zergling";"Larva";617;1
"Unit";"Baneling";"Zergling";618;0
"Unit";"Baneling";"Zergling";618;0
"Unit";"Baneling";"Zergling";618;0
"Unit";"Baneling";"Zergling";618;0
"Unit";"Baneling";"Zergling";618;0
"Unit";"Baneling";"Zergling";618;0
"Unit";"Baneling";"Zergling";618;0
"Unit";"Baneling";"Zergling";618;0
"Unit";"Baneling";"Zergling";618;0
"Unit";"Baneling";"Zergling";618;0
"Unit";"Baneling";"Zergling";618;0
"Unit";"Baneling";"Zergling";618;0
"Unit";"Baneling";"Zergling";618;0
"Unit";"Baneling";"Zergling";618;0
"Unit";"Baneling";"Zergling";618;0
"Unit";"Baneling";"Zergling";618;0
"Unit";"Baneling";"Zergling";618;0
"Unit";"Baneling";"Zergling";618;0
"Unit";"Baneling";"Zergling";618;0
"Unit";"Baneling";"Zergling";618;0
"Unit";"Baneling";"Zergling";618;0
"Unit";"Zergling";"Larva";618;1
"Unit";"Zergling";"Larva";619;1
"Unit";"Zergling";"Larva";620;1
"Unit";"Zergling";"Larva";621;1
"Unit";"Zergling";"Larva";622;1
"Unit";"Zergling";"Larva";623;1
"Unit";"Zergling";"Larva";624;1
"Unit";"Zergling";"Larva";625;1
"Unit";"Zergling";"Larva";626;1
"Unit";"Zergling";"Larva";627;1
"Unit";"Zergling";"Larva";628;1
"Unit";"Zergling";"Larva";629;1
"Unit";"Zergling";"Larva";630;1
"Unit";"Zergling";"Larva";631;1
"Unit";"Zergling";"Larva";632;1
"Unit";"Zergling";"Larva";633;1
"Unit";"Zergling";"Larva";634;1
"Unit";"Zergling";"Larva";635;1
"Unit";"Zergling";"Larva";636;1
"Unit";"Zergling";"Larva";637;1
"Unit";"Zergling";"Larva";638;1
"Unit";"Zergling";"Larva";639;1
"Unit";"Zergling";"Larva";640;1
"Unit";"Zergling";"Larva";641;1
"Unit";"Zergling";"Larva";642;1
"Unit";"Zergling";"Larva";643;1
"Unit";"Zergling";"Larva";644;1
"Unit";"Zergling";"Larva";645;1
"Unit";"Zergling";"Larva";646;1
"Unit";"Zergling";"Larva";647;1
"Unit";"Zergling";"Larva";648;1
"Unit";"Zergling";"Larva";649;1
"Unit";"Zergling";"Larva";650;1
"Unit";"Zergling";"Larva";651;1
"Unit";"Zergling";"Larva";652;1
"Unit";"Zergling";"Larva";653;1
"Unit";"Zergling";"Larva";654;1
"Unit";"Zergling";"Larva";655;1
"Unit";"Zergling";"Larva";656;1
"Unit";"Zergling";"Larva";657;1
"Unit";"Zergling";"Larva";658;1
"Unit";"Zergling";"Larva";659;1
"Unit";"Zergling";"Larva";660;1
"Unit";"Zergling";"Larva";661;1
"Unit";"Zergling";"Larva";662;1
"Unit";"Zergling";"Larva";663;1
"Building";"Hatchery";NA;664;0
"Upgrade";"ChitinousPlating";"UltraliskCavern";664;0
"Building";"CreepTumor";NA;664;0
"Building";"CreepTumor";NA;664;0
"Building";"CreepTumor";NA;664;0
"Building";"CreepTumor";NA;664;0
"Building";"Hatchery";NA;664;0
"Unit";"Zergling";"Larva";664;1
"Unit";"Zergling";"Larva";665;1
"Unit";"Zergling";"Larva";666;1
"Unit";"Zergling";"Larva";667;1
"Unit";"Zergling";"Larva";668;1
"Unit";"Zergling";"Larva";669;1
"Unit";"Zergling";"Larva";670;1
"Unit";"Zergling";"Larva";671;1
"Unit";"Zergling";"Larva";672;1
"Unit";"Zergling";"Larva";673;1
"Unit";"Zergling";"Larva";674;1
"Unit";"Zergling";"Larva";675;1
"Unit";"Zergling";"Larva";676;1
"Unit";"Zergling";"Larva";677;1
"Unit";"Zergling";"Larva";678;1
"Unit";"Zergling";"Larva";679;1
"Unit";"Zergling";"Larva";680;1
"Unit";"Zergling";"Larva";681;1
"Unit";"Zergling";"Larva";682;1
"Unit";"Zergling";"Larva";683;1
"Unit";"Zergling";"Larva";684;1
"Unit";"Zergling";"Larva";685;1
"Unit";"Zergling";"Larva";686;1
"Unit";"Zergling";"Larva";687;1
"Unit";"Zergling";"Larva";688;1
"Unit";"Zergling";"Larva";689;1
"Unit";"Zergling";"Larva";690;1
"Unit";"Zergling";"Larva";691;1
"Unit";"Zergling";"Larva";692;1
"Unit";"Zergling";"Larva";693;1
"Unit";"Zergling";"Larva";694;1
"Unit";"Zergling";"Larva";695;1
"Unit";"Zergling";"Larva";696;1
"Unit";"Zergling";"Larva";697;1
"Unit";"Zergling";"Larva";698;1
"Unit";"Zergling";"Larva";699;1
"Unit";"Zergling";"Larva";700;1
"Unit";"Zergling";"Larva";701;1
"Unit";"Zergling";"Larva";702;1
"Unit";"Zergling";"Larva";703;1
"Unit";"Zergling";"Larva";704;1
"Unit";"Zergling";"Larva";705;1
"Unit";"Zergling";"Larva";706;1
"Unit";"Zergling";"Larva";707;1
"Unit";"Zergling";"Larva";708;1
"Unit";"Zergling";"Larva";709;1
"Unit";"Zergling";"Larva";710;1
"Unit";"Zergling";"Larva";711;1
"Unit";"Zergling";"Larva";712;1
"Unit";"Zergling";"Larva";713;1
"Unit";"Baneling";"Zergling";714;0
"Unit";"Baneling";"Zergling";714;0
"Unit";"Baneling";"Zergling";714;0
"Unit";"Baneling";"Zergling";714;0
"Unit";"Baneling";"Zergling";714;0
"Unit";"Baneling";"Zergling";714;0
"Unit";"Baneling";"Zergling";714;0
"Unit";"Baneling";"Zergling";714;0
"Unit";"Baneling";"Zergling";714;0
"Unit";"Baneling";"Zergling";714;0
"Unit";"Baneling";"Zergling";714;0
"Unit";"Baneling";"Zergling";714;0
"Unit";"Baneling";"Zergling";714;0
"Unit";"Baneling";"Zergling";714;0
"Unit";"Baneling";"Zergling";714;0
"Unit";"Baneling";"Zergling";714;0
"Unit";"Baneling";"Zergling";714;0
"Unit";"Baneling";"Zergling";714;0
"Unit";"Baneling";"Zergling";714;0
"Unit";"Baneling";"Zergling";714;0
"Unit";"Baneling";"Zergling";714;0
"Unit";"Baneling";"Zergling";714;0
"Unit";"Baneling";"Zergling";714;0
"Unit";"Baneling";"Zergling";714;0
"Unit";"Baneling";"Zergling";714;0
"Unit";"Baneling";"Zergling";714;0
"Unit";"Baneling";"Zergling";714;0
"Unit";"Baneling";"Zergling";714;0
"Unit";"Baneling";"Zergling";714;0
"Unit";"Baneling";"Zergling";714;0
"Unit";"Baneling";"Zergling";714;0
"Unit";"Baneling";"Zergling";714;0
"Unit";"Zergling";"Larva";714;1
"Unit";"Zergling";"Larva";715;1
"Unit";"Zergling";"Larva";716;1
"Unit";"Zergling";"Larva";717;1
"Unit";"Zergling";"Larva";718;1
"Unit";"Zergling";"Larva";719;1
"Unit";"Zergling";"Larva";720;1
"Unit";"Zergling";"Larva";721;1
"Unit";"Zergling";"Larva";722;1
"Unit";"Zergling";"Larva";723;1
"Unit";"Zergling";"Larva";724;1
"Unit";"Zergling";"Larva";725;1
"Unit";"Zergling";"Larva";726;1
"Unit";"Zergling";"Larva";727;1
"Unit";"Zergling";"Larva";728;1
"Unit";"Zergling";"Larva";729;1
"Unit";"Zergling";"Larva";730;1
"Unit";"Zergling";"Larva";731;1
"Unit";"Zergling";"Larva";732;1
"Unit";"Zergling";"Larva";733;1
"Unit";"Zergling";"Larva";734;1
"Unit";"Zergling";"Larva";735;1
"Unit";"Baneling";"Zergling";736;0
"Unit";"Baneling";"Zergling";736;0
"Unit";"Baneling";"Zergling";736;0
"Unit";"Baneling";"Zergling";736;0
"Unit";"Baneling";"Zergling";736;0
"Unit";"Baneling";"Zergling";736;0
"Unit";"Baneling";"Zergling";736;0
"Unit";"Zergling";"Larva";736;1
"Unit";"Zergling";"Larva";737;1
"Unit";"Zergling";"Larva";738;1
"Unit";"Zergling";"Larva";739;1
"Unit";"Zergling";"Larva";740;1
"Unit";"Zergling";"Larva";741;1
"Unit";"Zergling";"Larva";742;1
"Unit";"Zergling";"Larva";743;1
"Unit";"Zergling";"Larva";744;1
"Unit";"Zergling";"Larva";745;1
"Unit";"Infestor";"Larva";746;2
"Unit";"Infestor";"Larva";748;2
"Unit";"Infestor";"Larva";751;2
"Unit";"Infestor";"Larva";753;2
"Unit";"Infestor";"Larva";755;2
"Unit";"Infestor";"Larva";757;2
"Unit";"Infestor";"Larva";759;2
"Building";"Hatchery";NA;761;0
"Unit";"Ultralisk";"Larva";761;6
"Unit";"Ultralisk";"Larva";767;6
"Unit";"Ultralisk";"Larva";773;6
"Building";"CreepTumorQueen";NA;779;0
"Building";"CreepTumorQueen";NA;779;0
"Building";"CreepTumorQueen";NA;779;0
"Building";"CreepTumorQueen";NA;779;0
"Unit";"Ultralisk";"Larva";779;6
"Unit";"Ultralisk";"Larva";785;6
"Building";"CreepTumorQueen";NA;791;0
"Building";"CreepTumorQueen";NA;791;0
"Upgrade";"Burrow";"Hatchery";791;0
"Building";"CreepTumor";NA;791;0
"Building";"CreepTumor";NA;791;0
"Building";"CreepTumor";NA;791;0
"Unit";"Ultralisk";"Larva";791;6
"Unit";"Ultralisk";"Larva";797;6
"Unit";"Ultralisk";"Larva";803;6
"Unit";"Ultralisk";"Larva";809;6
"Unit";"Ultralisk";"Larva";815;6
"Building";"CreepTumor";NA;821;0
"Building";"CreepTumor";NA;821;0
"Building";"CreepTumor";NA;821;0
"Building";"CreepTumor";NA;821;0
"Building";"CreepTumor";NA;821;0
"Unit";"Ultralisk";"Larva";821;6
"Building";"CreepTumor";NA;827;0
"Building";"CreepTumor";NA;827;0
"Building";"CreepTumor";NA;827;0
"Building";"CreepTumor";NA;827;0
"Unit";"Zergling";"Larva";827;1
"Unit";"Zergling";"Larva";828;1
"Unit";"Zergling";"Larva";829;1
"Unit";"Zergling";"Larva";830;1
"Building";"Extractor";NA;831;0
"Building";"Extractor";NA;831;0
"Unit";"Zergling";"Larva";831;1
"Unit";"Zergling";"Larva";832;1
"Unit";"Zergling";"Larva";833;1
"Unit";"Zergling";"Larva";834;1
"Unit";"Zergling";"Larva";835;1
"Unit";"Zergling";"Larva";836;1
"Unit";"Zergling";"Larva";837;1
"Unit";"Zergling";"Larva";838;1
"Unit";"Zergling";"Larva";839;1
"Unit";"Zergling";"Larva";840;1
"Unit";"Zergling";"Larva";841;1
"Unit";"Zergling";"Larva";842;1
"Unit";"Zergling";"Larva";843;1
"Unit";"Zergling";"Larva";844;1
"Unit";"Zergling";"Larva";845;1
"Unit";"Zergling";"Larva";846;1
"Unit";"Zergling";"Larva";847;1
"Unit";"Zergling";"Larva";848;1
"Unit";"Zergling";"Larva";849;1
"Unit";"Zergling";"Larva";850;1
"Unit";"Zergling";"Larva";851;1
"Unit";"Zergling";"Larva";852;1
"Unit";"Zergling";"Larva";853;1
"Unit";"Zergling";"Larva";854;1
"Unit";"Zergling";"Larva";855;1
"Unit";"Zergling";"Larva";856;1
"Upgrade";"SprayZerg";NA;857;0
"Upgrade";"SprayZerg";NA;857;0
"Upgrade";"zerglingmovementspeed";NA;857;0
"Upgrade";"SprayZerg";NA;857;0
"Upgrade";"overlordspeed";NA;857;0
"Upgrade";"SprayZerg";NA;857;0
"Upgrade";"ZergGroundArmorsLevel1";NA;857;0
"Upgrade";"SprayZerg";NA;857;0
"Upgrade";"SprayZerg";NA;857;0
"Upgrade";"SprayZerg";NA;857;0
"Upgrade";"ZergMeleeWeaponsLevel1";NA;857;0
"Upgrade";"SprayZerg";NA;857;0
"Upgrade";"CentrificalHooks";NA;857;0
"Upgrade";"SprayZerg";NA;857;0
"Upgrade";"ZergGroundArmorsLevel2";NA;857;0
"Upgrade";"ZergFlyerWeaponsLevel1";NA;857;0
"Upgrade";"SprayZerg";NA;857;0
"Upgrade";"SprayZerg";NA;857;0
"Upgrade";"SprayZerg";NA;857;0
"Upgrade";"ZergMeleeWeaponsLevel2";NA;857;0
"Upgrade";"zerglingattackspeed";NA;857;0
"Upgrade";"SprayZerg";NA;857;0
"Upgrade";"SprayZerg";NA;857;0
"Upgrade";"ZergFlyerWeaponsLevel2";NA;857;0
"Upgrade";"SprayZerg";NA;857;0
"Upgrade";"ZergGroundArmorsLevel3";NA;857;0
"Upgrade";"SprayZerg";NA;857;0
"Upgrade";"SprayZerg";NA;857;0
"Upgrade";"SprayZerg";NA;857;0
"Upgrade";"SprayZerg";NA;857;0
"Upgrade";"ZergMeleeWeaponsLevel3";NA;857;0
"Upgrade";"InfestorEnergyUpgrade";NA;857;0
"Upgrade";"SprayZerg";NA;857;0
"Upgrade";"SprayZerg";NA;857;0
