"type";"unit_name";"on_building";"total_supply_lag";"supply"
"Building";"Pylon";NA;14;0
"Building";"Gateway";NA;16;0
"Building";"Assimilator";NA;16;0
"Building";"Nexus";NA;19;0
"Building";"CyberneticsCore";NA;20;0
"Building";"Assimilator";NA;21;0
"Building";"Pylon";NA;22;0
"Unit";"Stalker";"Gateway";23;2
"Unit";"Adept";"Gateway";28;2
"Building";"TwilightCouncil";NA;32;0
"Building";"RoboticsFacility";NA;36;0
"Building";"Pylon";NA;37;0
"Building";"DarkShrine";NA;41;0
"Building";"Gateway";NA;43;0
"Building";"Gateway";NA;43;0
"Building";"Gateway";NA;43;0
"Building";"Assimilator";NA;43;0
"Building";"Assimilator";NA;43;0
"Building";"Pylon";NA;44;0
"Building";"Pylon";NA;46;0
"Unit";"Adept";"Gateway";47;2
"Building";"DarkTemplar";NA;54;0
"Building";"DarkTemplar";NA;54;0
"Building";"DarkTemplar";NA;54;0
"Building";"DarkTemplar";NA;54;0
"Building";"Nexus";NA;60;0
"Building";"Pylon";NA;61;0
"Unit";"Archon";"High Templar";61;0
"Unit";"Archon";"High Templar";61;0
"Building";"DarkTemplar";NA;61;0
"Building";"Pylon";NA;61;0
"Building";"Pylon";NA;61;0
"Building";"DarkTemplar";NA;61;0
"Building";"DarkTemplar";NA;61;0
"Building";"DarkTemplar";NA;61;0
"Unit";"Archon";"High Templar";63;0
"Unit";"Archon";"High Templar";63;0
"Building";"Pylon";NA;65;0
"Unit";"Adept";"Gateway";65;2
"Unit";"Observer";"Robotics Facility";69;1
"Unit";"Zealot";"Gateway";72;2
"Unit";"Zealot";"Gateway";74;2
"Unit";"Zealot";"Gateway";76;2
"Unit";"Zealot";"Gateway";83;2
"Unit";"Zealot";"Gateway";85;2
"Unit";"Zealot";"Gateway";88;2
"Unit";"Zealot";"Gateway";90;2
"Unit";"Zealot";"Gateway";96;2
"Unit";"Zealot";"Gateway";98;2
"Unit";"Zealot";"Gateway";100;2
"Unit";"Zealot";"Gateway";102;2
"Upgrade";"SprayProtoss";NA;104;0
"Upgrade";"SprayProtoss";NA;104;0
"Upgrade";"WarpGateResearch";NA;104;0
"Upgrade";"SprayProtoss";NA;104;0
"Upgrade";"SprayProtoss";NA;104;0
