"type";"unit_name";"on_building";"total_supply_lag";"supply"
"Building";"Pylon";NA;14;0
"Building";"Gateway";NA;16;0
"Building";"Assimilator";NA;17;0
"Building";"Nexus";NA;20;0
"Building";"CyberneticsCore";NA;20;0
"Building";"Assimilator";NA;21;0
"Building";"Pylon";NA;22;0
"Unit";"Adept";"Gateway";23;2
"Building";"Stargate";NA;26;0
"Unit";"Adept";"Gateway";29;2
"Unit";"Oracle";"Stargate";35;3
"Building";"Pylon";NA;40;0
"Unit";"Adept";"Gateway";41;2
"Building";"Gateway";NA;45;0
"Unit";"Phoenix";"Stargate";45;2
"Building";"Assimilator";NA;49;0
"Building";"Assimilator";NA;50;0
"Building";"Pylon";NA;51;0
"Building";"Pylon";NA;52;0
"Unit";"Oracle";"Stargate";55;3
"Building";"Nexus";NA;59;0
"Building";"Stargate";NA;60;0
"Unit";"Adept";"Gateway";60;2
"Unit";"Adept";"Gateway";62;2
"Building";"Pylon";NA;65;0
"Unit";"Oracle";"Stargate";67;3
"Building";"Pylon";NA;70;0
"Unit";"Oracle";"Stargate";74;3
"Building";"TwilightCouncil";NA;78;0
"Building";"Forge";NA;78;0
"Unit";"Oracle";"Stargate";79;3
"Building";"Pylon";NA;83;0
"Building";"Pylon";NA;84;0
"Unit";"Zealot";"Gateway";84;2
"Unit";"Zealot";"Gateway";86;2
"Building";"Assimilator";NA;92;0
"Unit";"Oracle";"Stargate";92;3
"Building";"Assimilator";NA;96;0
"Unit";"Oracle";"Stargate";98;3
"Building";"Pylon";NA;101;0
"Upgrade";"Charge";"TwilightCouncil";105;0
"Upgrade";"ProtossGroundWeaponsLevel1";"Forge";105;0
"Building";"Gateway";NA;105;0
"Building";"Gateway";NA;105;0
"Unit";"Oracle";"Stargate";105;3
"Building";"Gateway";NA;108;0
"Building";"Gateway";NA;108;0
"Unit";"Oracle";"Stargate";108;3
"Building";"Nexus";NA;112;0
"Building";"Pylon";NA;112;0
"Unit";"Zealot";"Gateway";112;2
"Unit";"Zealot";"Gateway";114;2
"Unit";"Oracle";"Stargate";116;3
"Building";"Gateway";NA;119;0
"Building";"Gateway";NA;119;0
"Building";"TemplarArchive";NA;119;0
"Building";"Pylon";NA;119;0
"Building";"Pylon";NA;119;0
"Building";"OracleStasisTrap";NA;119;0
"Building";"OracleStasisTrap";NA;119;0
"Building";"OracleStasisTrap";NA;119;0
"Building";"PhotonCannon";NA;119;0
"Building";"PhotonCannon";NA;119;0
"Building";"OracleStasisTrap";NA;119;0
"Building";"PhotonCannon";NA;119;0
"Unit";"Sentry";"Gateway";119;2
"Unit";"Oracle";"Stargate";121;3
"Building";"OracleStasisTrap";NA;124;0
"Building";"OracleStasisTrap";NA;124;0
"Building";"Pylon";NA;124;0
"Building";"Pylon";NA;124;0
"Building";"Pylon";NA;124;0
"Unit";"Oracle";"Stargate";124;3
"Building";"Pylon";NA;127;0
"Building";"Pylon";NA;127;0
"Building";"Pylon";NA;127;0
"Building";"Pylon";NA;127;0
"Building";"HighTemplar";NA;127;0
"Building";"HighTemplar";NA;127;0
"Unit";"Archon";"High Templar";127;0
"Unit";"Oracle";"Stargate";127;3
"Building";"Pylon";NA;130;0
"Unit";"Zealot";"Gateway";130;2
"Unit";"Zealot";"Gateway";132;2
"Unit";"Zealot";"Gateway";134;2
"Unit";"Zealot";"Gateway";136;2
"Building";"OracleStasisTrap";NA;138;0
"Building";"OracleStasisTrap";NA;138;0
"Building";"OracleStasisTrap";NA;138;0
"Building";"OracleStasisTrap";NA;138;0
"Building";"OracleStasisTrap";NA;138;0
"Building";"HighTemplar";NA;138;0
"Building";"HighTemplar";NA;138;0
"Unit";"Archon";"High Templar";138;0
"Unit";"Zealot";"Gateway";138;2
"Unit";"Zealot";"Gateway";140;2
"Unit";"Zealot";"Gateway";142;2
"Unit";"Zealot";"Gateway";144;2
"Unit";"Zealot";"Gateway";146;2
"Unit";"Zealot";"Gateway";148;2
"Building";"OracleStasisTrap";NA;150;0
"Building";"OracleStasisTrap";NA;150;0
"Building";"OracleStasisTrap";NA;150;0
"Building";"OracleStasisTrap";NA;152;0
"Building";"HighTemplar";NA;152;0
"Building";"HighTemplar";NA;152;0
"Building";"HighTemplar";NA;152;0
"Building";"HighTemplar";NA;152;0
"Unit";"Archon";"High Templar";152;0
"Unit";"Archon";"High Templar";152;0
"Unit";"Zealot";"Gateway";152;2
"Unit";"Zealot";"Gateway";154;2
"Unit";"Zealot";"Gateway";156;2
"Unit";"Oracle";"Stargate";158;3
"Unit";"Zealot";"Gateway";161;2
"Unit";"Oracle";"Stargate";164;3
"Building";"Assimilator";NA;169;0
"Building";"Assimilator";NA;169;0
"Unit";"Zealot";"Gateway";169;2
"Unit";"Zealot";"Gateway";171;2
"Unit";"Zealot";"Gateway";173;2
"Unit";"Zealot";"Gateway";175;2
"Unit";"Zealot";"Gateway";177;2
"Unit";"Zealot";"Gateway";179;2
"Unit";"Zealot";"Gateway";181;2
"Building";"Nexus";NA;183;0
"Building";"Pylon";NA;183;0
"Building";"OracleStasisTrap";NA;183;0
"Building";"OracleStasisTrap";NA;183;0
"Unit";"Oracle";"Stargate";183;3
"Building";"Pylon";NA;186;0
"Unit";"Zealot";"Gateway";186;2
"Unit";"Oracle";"Stargate";188;3
"Building";"HighTemplar";NA;191;0
"Building";"HighTemplar";NA;191;0
"Unit";"Zealot";"Gateway";191;2
"Unit";"Zealot";"Gateway";193;2
"Unit";"Zealot";"Gateway";195;2
"Building";"PhotonCannon";NA;197;0
"Building";"PhotonCannon";NA;197;0
"Building";"PhotonCannon";NA;197;0
"Building";"PhotonCannon";NA;197;0
"Building";"HighTemplar";NA;197;0
"Building";"HighTemplar";NA;197;0
"Building";"Assimilator";NA;197;0
"Unit";"Oracle";"Stargate";197;3
"Unit";"Zealot";"Gateway";200;2
"Unit";"Zealot";"Gateway";202;2
"Unit";"Zealot";"Gateway";204;2
"Unit";"Oracle";"Stargate";206;3
"Building";"Assimilator";NA;209;0
"Unit";"Zealot";"Gateway";209;2
"Unit";"Zealot";"Gateway";211;2
"Upgrade";"ProtossGroundWeaponsLevel2";"Forge";213;0
"Building";"FleetBeacon";NA;213;0
"Unit";"Zealot";"Gateway";213;2
"Building";"PhotonCannon";NA;215;0
"Building";"PhotonCannon";NA;215;0
"Unit";"Zealot";"Gateway";215;2
"Unit";"Zealot";"Gateway";217;2
"Unit";"Zealot";"Gateway";219;2
"Unit";"Zealot";"Gateway";221;2
"Unit";"Zealot";"Gateway";223;2
"Unit";"Zealot";"Gateway";225;2
"Unit";"Zealot";"Gateway";227;2
"Unit";"Zealot";"Gateway";229;2
"Building";"HighTemplar";NA;231;0
"Building";"HighTemplar";NA;231;0
"Building";"Stargate";NA;231;0
"Building";"OracleStasisTrap";NA;231;0
"Building";"OracleStasisTrap";NA;231;0
"Building";"OracleStasisTrap";NA;231;0
"Unit";"Zealot";"Gateway";231;2
"Unit";"Zealot";"Gateway";233;2
"Unit";"Zealot";"Gateway";235;2
"Unit";"Zealot";"Gateway";237;2
"Unit";"Zealot";"Gateway";239;2
"Building";"OracleStasisTrap";NA;241;0
"Building";"OracleStasisTrap";NA;241;0
"Building";"OracleStasisTrap";NA;241;0
"Building";"OracleStasisTrap";NA;241;0
"Building";"HighTemplar";NA;241;0
"Building";"HighTemplar";NA;241;0
"Building";"OracleStasisTrap";NA;241;0
"Building";"OracleStasisTrap";NA;241;0
"Building";"OracleStasisTrap";NA;241;0
"Building";"OracleStasisTrap";NA;241;0
"Building";"OracleStasisTrap";NA;241;0
"Building";"OracleStasisTrap";NA;241;0
"Building";"OracleStasisTrap";NA;241;0
"Unit";"Zealot";"Gateway";241;2
"Unit";"Zealot";"Gateway";243;2
"Unit";"Zealot";"Gateway";245;2
"Unit";"Zealot";"Gateway";247;2
"Unit";"Zealot";"Gateway";249;2
"Unit";"Zealot";"Gateway";251;2
"Unit";"Carrier";"Stargate";253;6
"Building";"OracleStasisTrap";NA;259;0
"Building";"OracleStasisTrap";NA;259;0
"Building";"OracleStasisTrap";NA;259;0
"Building";"OracleStasisTrap";NA;259;0
"Building";"OracleStasisTrap";NA;259;0
"Building";"OracleStasisTrap";NA;259;0
"Unit";"Carrier";"Stargate";259;6
"Unit";"Carrier";"Stargate";265;6
"Building";"OracleStasisTrap";NA;271;0
"Building";"OracleStasisTrap";NA;271;0
"Building";"OracleStasisTrap";NA;271;0
"Building";"OracleStasisTrap";NA;271;0
"Building";"OracleStasisTrap";NA;271;0
"Building";"CyberneticsCore";NA;271;0
"Unit";"Zealot";"Gateway";271;2
"Unit";"Zealot";"Gateway";273;2
"Unit";"Zealot";"Gateway";275;2
"Unit";"Zealot";"Gateway";277;2
"Unit";"Zealot";"Gateway";279;2
"Building";"Forge";NA;281;0
"Building";"HighTemplar";NA;281;0
"Building";"HighTemplar";NA;281;0
"Building";"HighTemplar";NA;281;0
"Building";"OracleStasisTrap";NA;281;0
"Building";"OracleStasisTrap";NA;281;0
"Upgrade";"ProtossAirWeaponsLevel1";"CyberneticsCore";281;0
"Building";"OracleStasisTrap";NA;281;0
"Unit";"Archon";"High Templar";281;0
"Upgrade";"ProtossGroundWeaponsLevel3";"Forge";281;0
"Building";"RoboticsFacility";NA;281;0
"Building";"Stargate";NA;281;0
"Building";"Stargate";NA;281;0
"Building";"Stargate";NA;281;0
"Unit";"Carrier";"Stargate";281;6
"Building";"HighTemplar";NA;287;0
"Building";"HighTemplar";NA;287;0
"Upgrade";"ProtossShieldsLevel1";"Forge";287;0
"Unit";"Observer";"Robotics Facility";287;1
"Building";"OracleStasisTrap";NA;288;0
"Building";"OracleStasisTrap";NA;288;0
"Building";"HighTemplar";NA;288;0
"Building";"HighTemplar";NA;288;0
"Building";"Nexus";NA;288;0
"Building";"Pylon";NA;288;0
"Building";"OracleStasisTrap";NA;288;0
"Building";"OracleStasisTrap";NA;288;0
"Building";"OracleStasisTrap";NA;288;0
"Building";"OracleStasisTrap";NA;288;0
"Building";"OracleStasisTrap";NA;288;0
"Building";"OracleStasisTrap";NA;288;0
"Building";"PhotonCannon";NA;288;0
"Building";"HighTemplar";NA;288;0
"Building";"HighTemplar";NA;288;0
"Building";"PhotonCannon";NA;288;0
"Unit";"Archon";"High Templar";288;0
"Building";"PhotonCannon";NA;288;0
"Unit";"Archon";"High Templar";288;0
"Unit";"Zealot";"Gateway";288;2
"Unit";"Zealot";"Gateway";290;2
"Building";"PhotonCannon";NA;292;0
"Unit";"Zealot";"Gateway";292;2
"Unit";"Zealot";"Gateway";294;2
"Unit";"Zealot";"Gateway";296;2
"Unit";"Zealot";"Gateway";298;2
"Building";"PhotonCannon";NA;300;0
"Building";"Assimilator";NA;300;0
"Building";"Assimilator";NA;300;0
"Upgrade";"ProtossAirWeaponsLevel2";"CyberneticsCore";300;0
"Upgrade";"ProtossShieldsLevel2";"Forge";300;0
"Building";"OracleStasisTrap";NA;300;0
"Building";"OracleStasisTrap";NA;300;0
"Building";"OracleStasisTrap";NA;300;0
"Building";"OracleStasisTrap";NA;300;0
"Building";"HighTemplar";NA;300;0
"Building";"OracleStasisTrap";NA;300;0
"Building";"HighTemplar";NA;300;0
"Unit";"Zealot";"Gateway";300;2
"Unit";"Zealot";"Gateway";302;2
"Unit";"Zealot";"Gateway";304;2
"Unit";"Zealot";"Gateway";306;2
"Building";"HighTemplar";NA;308;0
"Building";"OracleStasisTrap";NA;308;0
"Building";"OracleStasisTrap";NA;308;0
"Building";"HighTemplar";NA;308;0
"Unit";"Archon";"High Templar";308;0
"Building";"OracleStasisTrap";NA;308;0
"Building";"OracleStasisTrap";NA;308;0
"Unit";"Archon";"High Templar";308;0
"Building";"OracleStasisTrap";NA;308;0
"Building";"OracleStasisTrap";NA;308;0
"Building";"Nexus";NA;308;0
"Building";"Pylon";NA;308;0
"Building";"OracleStasisTrap";NA;308;0
"Building";"OracleStasisTrap";NA;308;0
"Building";"OracleStasisTrap";NA;308;0
"Building";"OracleStasisTrap";NA;308;0
"Building";"PhotonCannon";NA;308;0
"Building";"PhotonCannon";NA;308;0
"Unit";"Observer";"Robotics Facility";308;1
"Building";"PhotonCannon";NA;309;0
"Building";"PhotonCannon";NA;309;0
"Building";"Assimilator";NA;309;0
"Building";"HighTemplar";NA;309;0
"Building";"HighTemplar";NA;309;0
"Building";"HighTemplar";NA;309;0
"Building";"HighTemplar";NA;309;0
"Building";"Assimilator";NA;309;0
"Unit";"Archon";"High Templar";309;0
"Unit";"Archon";"High Templar";309;0
"Unit";"Zealot";"Gateway";309;2
"Unit";"Zealot";"Gateway";311;2
"Unit";"Zealot";"Gateway";313;2
"Unit";"Zealot";"Gateway";315;2
"Building";"OracleStasisTrap";NA;317;0
"Building";"OracleStasisTrap";NA;317;0
"Building";"OracleStasisTrap";NA;317;0
"Building";"OracleStasisTrap";NA;317;0
"Unit";"Observer";"Robotics Facility";317;1
"Building";"OracleStasisTrap";NA;318;0
"Upgrade";"ProtossAirWeaponsLevel3";"CyberneticsCore";318;0
"Upgrade";"ProtossShieldsLevel3";"Forge";318;0
"Building";"OracleStasisTrap";NA;318;0
"Building";"HighTemplar";NA;318;0
"Building";"HighTemplar";NA;318;0
"Building";"HighTemplar";NA;318;0
"Building";"HighTemplar";NA;318;0
"Unit";"Archon";"High Templar";318;0
"Unit";"Archon";"High Templar";318;0
"Unit";"Zealot";"Gateway";318;2
"Unit";"Zealot";"Gateway";320;2
"Unit";"Zealot";"Gateway";322;2
"Unit";"Zealot";"Gateway";324;2
"Building";"Nexus";NA;326;0
"Building";"Nexus";NA;326;0
"Unit";"Carrier";"Stargate";326;6
"Unit";"Carrier";"Stargate";332;6
"Building";"Pylon";NA;338;0
"Building";"HighTemplar";NA;338;0
"Building";"HighTemplar";NA;338;0
"Building";"HighTemplar";NA;338;0
"Building";"HighTemplar";NA;338;0
"Unit";"Zealot";"Gateway";338;2
"Unit";"Zealot";"Gateway";340;2
"Unit";"Zealot";"Gateway";342;2
"Unit";"Zealot";"Gateway";344;2
"Unit";"Archon";"High Templar";346;0
"Unit";"Archon";"High Templar";346;0
"Building";"Pylon";NA;346;0
"Building";"PhotonCannon";NA;346;0
"Building";"PhotonCannon";NA;346;0
"Building";"PhotonCannon";NA;346;0
"Building";"PhotonCannon";NA;346;0
"Building";"PhotonCannon";NA;346;0
"Building";"PhotonCannon";NA;346;0
"Building";"PhotonCannon";NA;346;0
"Building";"PhotonCannon";NA;346;0
"Building";"PhotonCannon";NA;346;0
"Building";"Pylon";NA;346;0
"Building";"HighTemplar";NA;346;0
"Building";"HighTemplar";NA;346;0
"Building";"HighTemplar";NA;346;0
"Building";"HighTemplar";NA;346;0
"Unit";"Zealot";"Gateway";346;2
"Unit";"Zealot";"Gateway";348;2
"Unit";"Zealot";"Gateway";350;2
"Unit";"Zealot";"Gateway";352;2
"Unit";"Archon";"High Templar";354;0
"Unit";"Archon";"High Templar";354;0
"Building";"HighTemplar";NA;354;0
"Building";"HighTemplar";NA;354;0
"Building";"HighTemplar";NA;354;0
"Building";"HighTemplar";NA;354;0
"Building";"HighTemplar";NA;354;0
"Building";"HighTemplar";NA;354;0
"Building";"HighTemplar";NA;354;0
"Building";"HighTemplar";NA;354;0
"Unit";"Zealot";"Gateway";354;2
"Unit";"Zealot";"Gateway";356;2
"Unit";"Zealot";"Gateway";358;2
"Unit";"Zealot";"Gateway";360;2
"Unit";"Archon";"High Templar";362;0
"Unit";"Archon";"High Templar";362;0
"Building";"PhotonCannon";NA;362;0
"Unit";"Zealot";"Gateway";362;2
"Unit";"Zealot";"Gateway";364;2
"Unit";"Archon";"High Templar";366;0
"Building";"PhotonCannon";NA;366;0
"Unit";"Archon";"High Templar";366;0
"Building";"PhotonCannon";NA;366;0
"Building";"Assimilator";NA;366;0
"Building";"Assimilator";NA;366;0
"Unit";"Zealot";"Gateway";366;2
"Unit";"Zealot";"Gateway";368;2
"Unit";"Zealot";"Gateway";370;2
"Unit";"Zealot";"Gateway";372;2
"Unit";"Zealot";"Gateway";374;2
"Unit";"Zealot";"Gateway";376;2
"Unit";"Zealot";"Gateway";378;2
"Unit";"Zealot";"Gateway";380;2
"Unit";"Zealot";"Gateway";382;2
"Unit";"Zealot";"Gateway";384;2
"Unit";"Zealot";"Gateway";386;2
"Unit";"Carrier";"Stargate";388;6
"Unit";"Carrier";"Stargate";394;6
"Unit";"Carrier";"Stargate";400;6
"Unit";"Carrier";"Stargate";406;6
"Unit";"Zealot";"Gateway";413;2
"Unit";"Zealot";"Gateway";415;2
"Unit";"Zealot";"Gateway";417;2
"Unit";"Zealot";"Gateway";419;2
"Unit";"Zealot";"Gateway";421;2
"Unit";"Zealot";"Gateway";423;2
"Unit";"Zealot";"Gateway";425;2
"Unit";"Zealot";"Gateway";427;2
"Unit";"Carrier";"Stargate";432;6
"Unit";"Carrier";"Stargate";438;6
"Building";"Pylon";NA;445;0
"Building";"Assimilator";NA;445;0
"Building";"Assimilator";NA;445;0
"Unit";"Carrier";"Stargate";445;6
"Building";"PhotonCannon";NA;451;0
"Building";"PhotonCannon";NA;451;0
"Building";"PhotonCannon";NA;451;0
"Building";"PhotonCannon";NA;451;0
"Building";"Nexus";NA;451;0
"Building";"HighTemplar";NA;451;0
"Building";"HighTemplar";NA;451;0
"Building";"Pylon";NA;451;0
"Unit";"Archon";"High Templar";451;0
"Building";"Nexus";NA;451;0
"Building";"Nexus";NA;451;0
"Building";"Pylon";NA;451;0
"Building";"Pylon";NA;451;0
"Unit";"Zealot";"Gateway";451;2
"Unit";"Zealot";"Gateway";453;2
"Unit";"Zealot";"Gateway";455;2
"Unit";"Zealot";"Gateway";457;2
"Unit";"Zealot";"Gateway";459;2
"Unit";"Zealot";"Gateway";461;2
"Unit";"Zealot";"Gateway";463;2
"Unit";"Zealot";"Gateway";465;2
"Unit";"Zealot";"Gateway";467;2
"Building";"HighTemplar";NA;469;0
"Building";"HighTemplar";NA;469;0
"Unit";"Tempest";"Stargate";472;4
"Unit";"Tempest";"Stargate";476;4
"Building";"Pylon";NA;480;0
"Unit";"Observer";"Robotics Facility";480;1
"Building";"PhotonCannon";NA;481;0
"Building";"Assimilator";NA;481;0
"Unit";"Observer";"Robotics Facility";481;1
"Unit";"Zealot";"Gateway";482;2
"Unit";"Zealot";"Gateway";484;2
"Unit";"Zealot";"Gateway";486;2
"Unit";"Zealot";"Gateway";488;2
"Unit";"Observer";"Robotics Facility";490;1
"Unit";"Observer";"Robotics Facility";491;1
"Building";"Pylon";NA;492;0
"Building";"Pylon";NA;492;0
"Building";"Nexus";NA;492;0
"Building";"PhotonCannon";NA;492;0
"Building";"HighTemplar";NA;492;0
"Building";"HighTemplar";NA;492;0
"Building";"HighTemplar";NA;492;0
"Building";"HighTemplar";NA;492;0
"Unit";"Archon";"High Templar";492;0
"Unit";"Archon";"High Templar";492;0
"Building";"PhotonCannon";NA;492;0
"Unit";"Zealot";"Gateway";492;2
"Building";"HighTemplar";NA;494;0
"Building";"HighTemplar";NA;494;0
"Building";"HighTemplar";NA;494;0
"Building";"HighTemplar";NA;494;0
"Building";"HighTemplar";NA;494;0
"Building";"HighTemplar";NA;494;0
"Unit";"Zealot";"Gateway";494;2
"Unit";"Zealot";"Gateway";496;2
"Unit";"Archon";"High Templar";498;0
"Unit";"Archon";"High Templar";498;0
"Unit";"Archon";"High Templar";498;0
"Unit";"Zealot";"Gateway";498;2
"Unit";"Zealot";"Gateway";500;2
"Unit";"Zealot";"Gateway";502;2
"Unit";"Zealot";"Gateway";504;2
"Unit";"Zealot";"Gateway";506;2
"Unit";"Zealot";"Gateway";508;2
"Upgrade";"SprayProtoss";NA;510;0
"Upgrade";"SprayProtoss";NA;510;0
"Upgrade";"WarpGateResearch";NA;510;0
"Upgrade";"SprayProtoss";NA;510;0
"Upgrade";"SprayProtoss";NA;510;0
"Upgrade";"SprayProtoss";NA;510;0
"Upgrade";"SprayProtoss";NA;510;0
"Upgrade";"SprayProtoss";NA;510;0
"Upgrade";"SprayProtoss";NA;510;0
"Upgrade";"PsiStormTech";NA;510;0
"Upgrade";"CarrierLaunchSpeedUpgrade";NA;510;0
"Upgrade";"SprayProtoss";NA;510;0
"Upgrade";"ProtossAirArmorsLevel1";NA;510;0
"Upgrade";"SprayProtoss";NA;510;0
"Upgrade";"SprayProtoss";NA;510;0
"Upgrade";"ProtossGroundArmorsLevel1";NA;510;0
"Upgrade";"ProtossAirArmorsLevel2";NA;510;0
"Upgrade";"SprayProtoss";NA;510;0
"Upgrade";"SprayProtoss";NA;510;0
"Upgrade";"SprayProtoss";NA;510;0
"Upgrade";"SprayProtoss";NA;510;0
"Upgrade";"SprayProtoss";NA;510;0
"Upgrade";"ProtossAirArmorsLevel3";NA;510;0
"Upgrade";"ProtossGroundArmorsLevel2";NA;510;0
"Upgrade";"SprayProtoss";NA;510;0
"Upgrade";"SprayProtoss";NA;510;0
"Upgrade";"SprayProtoss";NA;510;0
"Upgrade";"SprayProtoss";NA;510;0
"Upgrade";"SprayProtoss";NA;510;0
"Upgrade";"SprayProtoss";NA;510;0
"Upgrade";"ProtossGroundArmorsLevel3";NA;510;0
"Upgrade";"SprayProtoss";NA;510;0
"Upgrade";"SprayProtoss";NA;510;0
