"type";"unit_name";"on_building";"total_supply";"supply"
"Unit";"Overlord";"Larva";13;0
"Building";"Extractor";NA;17;0
"Building";"SpawningPool";NA;19;0
"Building";"Hatchery";NA;17;0
"Unit";"Zergling";"Larva";24;1
"Unit";"Zergling";"Larva";24;1
"Unit";"Zergling";"Larva";24;1
"Unit";"Zergling";"Larva";24;1
"Unit";"Overlord";"Larva";24;0
"Unit";"Queen";"Hatchery";24;2
"Unit";"Queen";"Hatchery";24;2
"Unit";"Overlord";"Larva";28;0
"Unit";"Queen";"Hatchery";33;2
"Unit";"Queen";"Hatchery";33;2
"Building";"CreepTumorQueen";NA;37;0
"Building";"CreepTumorQueen";NA;44;0
"Unit";"Overlord";"Larva";45;0
"Unit";"Overlord";"Larva";45;0
"Building";"CreepTumor";NA;45;0
"Unit";"Queen";"Hatchery";45;2
"Building";"Hatchery";NA;33;0
"Building";"CreepTumor";NA;48;0
"Building";"CreepTumorQueen";NA;50;0
"Building";"CreepTumorQueen";NA;50;0
"Building";"CreepTumorQueen";NA;50;0
"Building";"Extractor";NA;48;0
"Building";"CreepTumor";NA;54;0
"Unit";"Queen";"Hatchery";48;2
"Unit";"Zergling";"Larva";56;1
"Unit";"Zergling";"Larva";56;1
"Unit";"Zergling";"Larva";57;1
"Unit";"Zergling";"Larva";57;1
"Unit";"Zergling";"Larva";57;1
"Unit";"Zergling";"Larva";57;1
"Unit";"Queen";"Hatchery";54;2
"Unit";"Zergling";"Larva";61;1
"Unit";"Zergling";"Larva";61;1
"Unit";"Zergling";"Larva";63;1
"Unit";"Zergling";"Larva";63;1
"Unit";"Zergling";"Larva";63;1
"Unit";"Zergling";"Larva";63;1
"Unit";"Zergling";"Larva";63;1
"Unit";"Zergling";"Larva";63;1
"Unit";"Zergling";"Larva";63;1
"Unit";"Zergling";"Larva";63;1
"Unit";"Queen";"Hatchery";61;2
"Building";"CreepTumorQueen";NA;81;0
"Building";"CreepTumorQueen";NA;81;0
"Unit";"Overlord";"Larva";81;0
"Unit";"Overlord";"Larva";81;0
"Unit";"Overlord";"Larva";81;0
"Unit";"Overlord";"Larva";81;0
"Building";"CreepTumor";NA;83;0
"Unit";"Overlord";"Larva";83;0
"Unit";"Overlord";"Larva";83;0
"Unit";"Overlord";"Larva";83;0
"Building";"Hatchery";NA;61;0
"Unit";"Queen";"Hatchery";83;2
"Unit";"Queen";"Hatchery";83;2
"Building";"CreepTumor";NA;83;0
"Building";"CreepTumor";NA;83;0
"Building";"EvolutionChamber";NA;83;0
"Building";"EvolutionChamber";NA;83;0
"Building";"CreepTumorQueen";NA;93;0
"Building";"CreepTumorQueen";NA;93;0
"Building";"CreepTumor";NA;93;0
"Building";"Extractor";NA;83;0
"Building";"Extractor";NA;83;0
"Building";"CreepTumorQueen";NA;93;0
"Building";"CreepTumorQueen";NA;93;0
"Building";"CreepTumor";NA;105;0
"Building";"CreepTumor";NA;105;0
"Building";"CreepTumor";NA;105;0
"Building";"BanelingNest";NA;83;0
"Building";"CreepTumor";NA;105;0
"Building";"CreepTumor";NA;108;0
"Building";"CreepTumor";NA;108;0
"Building";"CreepTumor";NA;108;0
"Building";"SporeCrawler";NA;108;0
"Building";"SporeCrawler";NA;108;0
"Building";"CreepTumor";NA;128;0
"Building";"SporeCrawler";NA;120;0
"Building";"CreepTumor";NA;128;0
"Building";"CreepTumor";NA;128;0
"Building";"CreepTumor";NA;128;0
"Building";"HydraliskDen";NA;128;0
"Building";"CreepTumor";NA;143;0
"Building";"CreepTumor";NA;143;0
"Building";"CreepTumor";NA;143;0
"Building";"Extractor";NA;128;0
"Building";"CreepTumorQueen";NA;143;0
"Building";"Extractor";NA;128;0
"Building";"InfestationPit";NA;128;0
"Building";"SporeCrawler";NA;129;0
"Building";"CreepTumor";NA;143;0
"Building";"SporeCrawler";NA;134;0
"Building";"CreepTumor";NA;143;0
"Building";"SporeCrawler";NA;143;0
"Building";"CreepTumorQueen";NA;143;0
"Upgrade";"ZergMeleeWeaponsLevel1";"EvolutionChamber";109;0
"Building";"CreepTumor";NA;143;0
"Building";"CreepTumor";NA;143;0
"Building";"CreepTumorQueen";NA;143;0
"Upgrade";"ZergGroundArmorsLevel1";"EvolutionChamber";109;0
"Building";"CreepTumorQueen";NA;143;0
"Building";"CreepTumorQueen";NA;143;0
"Unit";"Zergling";"Larva";143;1
"Unit";"Zergling";"Larva";143;1
"Unit";"Zergling";"Larva";143;1
"Unit";"Zergling";"Larva";143;1
"Unit";"Zergling";"Larva";143;1
"Unit";"Zergling";"Larva";143;1
"Unit";"Zergling";"Larva";143;1
"Unit";"Zergling";"Larva";143;1
"Unit";"Zergling";"Larva";143;1
"Unit";"Zergling";"Larva";143;1
"Unit";"Zergling";"Larva";143;1
"Unit";"Zergling";"Larva";143;1
"Unit";"Zergling";"Larva";143;1
"Unit";"Zergling";"Larva";143;1
"Unit";"Zergling";"Larva";143;1
"Unit";"Zergling";"Larva";143;1
"Unit";"Zergling";"Larva";143;1
"Unit";"Zergling";"Larva";143;1
"Unit";"Zergling";"Larva";143;1
"Unit";"Zergling";"Larva";143;1
"Unit";"Zergling";"Larva";143;1
"Unit";"Zergling";"Larva";143;1
"Unit";"Zergling";"Larva";143;1
"Unit";"Zergling";"Larva";143;1
"Unit";"Zergling";"Larva";143;1
"Unit";"Zergling";"Larva";143;1
"Building";"CreepTumorQueen";NA;143;0
"Unit";"Overlord";"Larva";143;0
"Unit";"Overlord";"Larva";143;0
"Unit";"Zergling";"Larva";143;1
"Unit";"Zergling";"Larva";143;1
"Unit";"Zergling";"Larva";143;1
"Unit";"Zergling";"Larva";143;1
"Unit";"Zergling";"Larva";143;1
"Unit";"Zergling";"Larva";143;1
"Unit";"Zergling";"Larva";143;1
"Unit";"Zergling";"Larva";143;1
"Unit";"Zergling";"Larva";143;1
"Unit";"Zergling";"Larva";143;1
"Unit";"Baneling";"Zergling";145;0
"Unit";"Baneling";"Zergling";151;0
"Unit";"Baneling";"Zergling";155;0
"Unit";"Baneling";"Zergling";155;0
"Unit";"Baneling";"Zergling";159;0
"Unit";"Baneling";"Zergling";159;0
"Unit";"Baneling";"Zergling";163;0
"Unit";"Baneling";"Zergling";163;0
"Unit";"Zergling";"Larva";169;1
"Unit";"Zergling";"Larva";169;1
"Unit";"Zergling";"Larva";169;1
"Unit";"Zergling";"Larva";169;1
"Unit";"Zergling";"Larva";169;1
"Unit";"Zergling";"Larva";169;1
"Unit";"Zergling";"Larva";169;1
"Unit";"Zergling";"Larva";169;1
"Unit";"Zergling";"Larva";169;1
"Unit";"Zergling";"Larva";169;1
"Unit";"Zergling";"Larva";169;1
"Unit";"Zergling";"Larva";169;1
"Unit";"Baneling";"Zergling";179;0
"Unit";"Baneling";"Zergling";179;0
"Unit";"Baneling";"Zergling";179;0
"Unit";"Baneling";"Zergling";179;0
"Unit";"Baneling";"Zergling";179;0
"Unit";"Baneling";"Zergling";179;0
"Unit";"Baneling";"Zergling";179;0
"Unit";"Baneling";"Zergling";179;0
"Unit";"Baneling";"Zergling";179;0
"Unit";"Baneling";"Zergling";179;0
"Unit";"Baneling";"Zergling";179;0
"Unit";"Baneling";"Zergling";179;0
"Unit";"Baneling";"Zergling";179;0
"Unit";"Zergling";"Larva";179;1
"Unit";"Zergling";"Larva";179;1
"Unit";"Baneling";"Zergling";179;0
"Unit";"Baneling";"Zergling";179;0
"Unit";"Baneling";"Zergling";179;0
"Unit";"Baneling";"Zergling";179;0
"Unit";"Baneling";"Zergling";179;0
"Unit";"Baneling";"Zergling";179;0
"Unit";"Zergling";"Larva";179;1
"Unit";"Zergling";"Larva";179;1
"Unit";"Zergling";"Larva";179;1
"Unit";"Zergling";"Larva";179;1
"Unit";"Zergling";"Larva";179;1
"Unit";"Zergling";"Larva";179;1
"Unit";"Zergling";"Larva";179;1
"Unit";"Zergling";"Larva";179;1
"Unit";"Zergling";"Larva";179;1
"Unit";"Zergling";"Larva";179;1
"Unit";"Overlord";"Larva";179;0
"Unit";"Zergling";"Larva";191;1
"Unit";"Zergling";"Larva";191;1
"Unit";"Zergling";"Larva";191;1
"Unit";"Zergling";"Larva";191;1
"Unit";"Zergling";"Larva";191;1
"Unit";"Zergling";"Larva";191;1
"Unit";"Zergling";"Larva";191;1
"Unit";"Zergling";"Larva";191;1
"Unit";"Zergling";"Larva";191;1
"Unit";"Zergling";"Larva";191;1
"Unit";"Queen";"Hatchery";169;2
"Building";"CreepTumorQueen";NA;205;0
"Building";"CreepTumorQueen";NA;213;0
"Building";"CreepTumorQueen";NA;213;0
"Building";"CreepTumorQueen";NA;213;0
"Building";"CreepTumor";NA;220;0
"Building";"CreepTumor";NA;222;0
"Building";"CreepTumor";NA;222;0
"Building";"CreepTumor";NA;222;0
"Building";"CreepTumor";NA;222;0
"Building";"CreepTumor";NA;222;0
"Building";"CreepTumor";NA;222;0
"Building";"CreepTumor";NA;222;0
"Unit";"Overlord";"Larva";222;0
"Unit";"Zergling";"Larva";222;1
"Unit";"Zergling";"Larva";222;1
"Unit";"Overlord";"Larva";222;0
"Unit";"Overlord";"Larva";222;0
"Unit";"Zergling";"Larva";222;1
"Unit";"Zergling";"Larva";222;1
"Unit";"Zergling";"Larva";222;1
"Unit";"Zergling";"Larva";222;1
"Unit";"Zergling";"Larva";222;1
"Unit";"Zergling";"Larva";222;1
"Unit";"Zergling";"Larva";222;1
"Unit";"Zergling";"Larva";222;1
"Unit";"Zergling";"Larva";222;1
"Unit";"Zergling";"Larva";222;1
"Unit";"Zergling";"Larva";222;1
"Unit";"Zergling";"Larva";222;1
"Unit";"Zergling";"Larva";222;1
"Unit";"Zergling";"Larva";222;1
"Building";"CreepTumor";NA;238;0
"Building";"CreepTumor";NA;238;0
"Building";"Extractor";NA;222;0
"Building";"CreepTumor";NA;238;0
"Unit";"Overlord";"Larva";238;0
"Unit";"Overlord";"Larva";238;0
"Unit";"Zergling";"Larva";238;1
"Unit";"Zergling";"Larva";238;1
"Unit";"Zergling";"Larva";238;1
"Unit";"Zergling";"Larva";238;1
"Unit";"Zergling";"Larva";238;1
"Unit";"Zergling";"Larva";238;1
"Unit";"Zergling";"Larva";238;1
"Unit";"Zergling";"Larva";238;1
"Building";"CreepTumor";NA;241;0
"Building";"CreepTumor";NA;241;0
"Building";"CreepTumor";NA;241;0
"Building";"CreepTumor";NA;241;0
"Building";"Extractor";NA;249;0
"Building";"Extractor";NA;249;0
"Unit";"Baneling";"Zergling";249;0
"Unit";"Baneling";"Zergling";249;0
"Unit";"Baneling";"Zergling";249;0
"Unit";"Baneling";"Zergling";249;0
"Unit";"Baneling";"Zergling";249;0
"Unit";"Baneling";"Zergling";249;0
"Unit";"Hydralisk";"Larva";249;2
"Unit";"Hydralisk";"Larva";249;2
"Unit";"Hydralisk";"Larva";249;2
"Unit";"Hydralisk";"Larva";249;2
"Unit";"Hydralisk";"Larva";249;2
"Unit";"Hydralisk";"Larva";249;2
"Unit";"Hydralisk";"Larva";249;2
"Unit";"Hydralisk";"Larva";249;2
"Unit";"Hydralisk";"Larva";249;2
"Unit";"Hydralisk";"Larva";249;2
"Unit";"Hydralisk";"Larva";249;2
"Unit";"Hydralisk";"Larva";249;2
"Unit";"Hydralisk";"Larva";249;2
"Unit";"Hydralisk";"Larva";249;2
"Building";"CreepTumor";NA;249;0
"Building";"CreepTumor";NA;249;0
"Building";"CreepTumor";NA;249;0
"Building";"CreepTumor";NA;249;0
"Unit";"Zergling";"Larva";249;1
"Unit";"Zergling";"Larva";249;1
"Unit";"Zergling";"Larva";249;1
"Unit";"Zergling";"Larva";249;1
"Unit";"Zergling";"Larva";249;1
"Unit";"Zergling";"Larva";249;1
"Unit";"Zergling";"Larva";249;1
"Unit";"Zergling";"Larva";249;1
"Upgrade";"EvolveMuscularAugments";"HydraliskDen";238;0
"Unit";"Zergling";"Larva";277;1
"Unit";"Zergling";"Larva";277;1
"Unit";"Baneling";"Zergling";285;0
"Unit";"Zergling";"Larva";277;1
"Unit";"Zergling";"Larva";277;1
"Unit";"Zergling";"Larva";277;1
"Unit";"Zergling";"Larva";277;1
"Unit";"Zergling";"Larva";277;1
"Unit";"Zergling";"Larva";277;1
"Unit";"Baneling";"Zergling";285;0
"Unit";"Baneling";"Zergling";285;0
"Unit";"Zergling";"Larva";277;1
"Unit";"Zergling";"Larva";277;1
"Unit";"Zergling";"Larva";277;1
"Unit";"Zergling";"Larva";277;1
"Unit";"Zergling";"Larva";277;1
"Unit";"Zergling";"Larva";277;1
"Unit";"Baneling";"Zergling";285;0
"Unit";"Baneling";"Zergling";285;0
"Unit";"Baneling";"Zergling";285;0
"Unit";"Zergling";"Larva";277;1
"Unit";"Zergling";"Larva";277;1
"Unit";"Baneling";"Zergling";285;0
"Unit";"Baneling";"Zergling";285;0
"Unit";"Zergling";"Larva";277;1
"Unit";"Zergling";"Larva";277;1
"Unit";"Zergling";"Larva";277;1
"Unit";"Zergling";"Larva";277;1
"Unit";"Zergling";"Larva";277;1
"Unit";"Zergling";"Larva";277;1
"Unit";"Baneling";"Zergling";285;0
"Unit";"Zergling";"Larva";277;1
"Unit";"Zergling";"Larva";277;1
"Unit";"Baneling";"Zergling";285;0
"Unit";"Baneling";"Zergling";285;0
"Unit";"Baneling";"Zergling";285;0
"Unit";"Baneling";"Zergling";285;0
"Unit";"Baneling";"Zergling";285;0
"Unit";"Zergling";"Larva";309;1
"Unit";"Zergling";"Larva";309;1
"Unit";"Zergling";"Larva";309;1
"Unit";"Zergling";"Larva";309;1
"Unit";"Zergling";"Larva";309;1
"Unit";"Zergling";"Larva";309;1
"Unit";"Zergling";"Larva";309;1
"Unit";"Zergling";"Larva";309;1
"Unit";"Zergling";"Larva";309;1
"Unit";"Zergling";"Larva";309;1
"Unit";"Zergling";"Larva";309;1
"Unit";"Zergling";"Larva";309;1
"Unit";"Zergling";"Larva";309;1
"Unit";"Zergling";"Larva";309;1
"Unit";"Zergling";"Larva";309;1
"Unit";"Zergling";"Larva";309;1
"Unit";"Zergling";"Larva";309;1
"Unit";"Zergling";"Larva";309;1
"Building";"CreepTumor";NA;338;0
"Building";"CreepTumor";NA;338;0
"Building";"CreepTumor";NA;338;0
"Building";"CreepTumor";NA;338;0
"Unit";"Queen";"Hatchery";309;2
"Upgrade";"EvolveGroovedSpines";"HydraliskDen";309;0
"Building";"CreepTumorQueen";NA;340;0
"Building";"CreepTumorQueen";NA;340;0
"Building";"CreepTumorQueen";NA;340;0
"Unit";"Zergling";"Larva";340;1
"Unit";"Zergling";"Larva";340;1
"Unit";"Zergling";"Larva";340;1
"Unit";"Zergling";"Larva";340;1
"Unit";"Zergling";"Larva";340;1
"Unit";"Zergling";"Larva";340;1
"Unit";"Zergling";"Larva";340;1
"Unit";"Zergling";"Larva";340;1
"Unit";"Zergling";"Larva";340;1
"Unit";"Zergling";"Larva";340;1
"Unit";"Zergling";"Larva";340;1
"Unit";"Zergling";"Larva";340;1
"Unit";"Zergling";"Larva";340;1
"Unit";"Zergling";"Larva";340;1
"Building";"CreepTumorQueen";NA;340;0
"Unit";"Zergling";"Larva";340;1
"Unit";"Zergling";"Larva";340;1
"Unit";"Zergling";"Larva";340;1
"Unit";"Zergling";"Larva";340;1
"Unit";"Zergling";"Larva";340;1
"Unit";"Zergling";"Larva";340;1
"Unit";"Zergling";"Larva";340;1
"Unit";"Zergling";"Larva";340;1
"Unit";"Zergling";"Larva";340;1
"Unit";"Zergling";"Larva";340;1
"Unit";"Zergling";"Larva";340;1
"Unit";"Zergling";"Larva";340;1
"Unit";"Zergling";"Larva";340;1
"Unit";"Zergling";"Larva";340;1
"Building";"CreepTumorQueen";NA;340;0
"Unit";"Zergling";"Larva";368;1
"Unit";"Zergling";"Larva";368;1
"Unit";"Baneling";"Zergling";368;0
"Unit";"Zergling";"Larva";368;1
"Unit";"Zergling";"Larva";368;1
"Unit";"Zergling";"Larva";368;1
"Unit";"Zergling";"Larva";368;1
"Unit";"Zergling";"Larva";368;1
"Unit";"Zergling";"Larva";368;1
"Unit";"Zergling";"Larva";368;1
"Unit";"Zergling";"Larva";368;1
"Unit";"Zergling";"Larva";368;1
"Unit";"Zergling";"Larva";368;1
"Unit";"Zergling";"Larva";368;1
"Unit";"Zergling";"Larva";368;1
"Unit";"Zergling";"Larva";368;1
"Unit";"Zergling";"Larva";368;1
"Unit";"Baneling";"Zergling";368;0
"Unit";"Baneling";"Zergling";368;0
"Unit";"Baneling";"Zergling";368;0
"Unit";"Zergling";"Larva";368;1
"Unit";"Zergling";"Larva";368;1
"Unit";"Baneling";"Zergling";368;0
"Unit";"Baneling";"Zergling";368;0
"Building";"CreepTumor";NA;386;0
"Building";"CreepTumor";NA;386;0
"Building";"CreepTumor";NA;386;0
"Building";"CreepTumor";NA;386;0
"Building";"CreepTumor";NA;386;0
"Building";"CreepTumor";NA;386;0
"Building";"CreepTumor";NA;386;0
"Building";"CreepTumor";NA;386;0
"Building";"CreepTumor";NA;386;0
"Unit";"Hydralisk";"Larva";368;2
"Unit";"Hydralisk";"Larva";368;2
"Unit";"Hydralisk";"Larva";368;2
"Unit";"Hydralisk";"Larva";368;2
"Unit";"Hydralisk";"Larva";368;2
"Unit";"Hydralisk";"Larva";368;2
"Unit";"Hydralisk";"Larva";368;2
"Unit";"Hydralisk";"Larva";368;2
"Unit";"Baneling";"Zergling";402;0
"Upgrade";"ZergMeleeWeaponsLevel2";"EvolutionChamber";328;0
"Unit";"Baneling";"Zergling";402;0
"Unit";"Baneling";"Zergling";402;0
"Unit";"Baneling";"Zergling";402;0
"Unit";"Baneling";"Zergling";402;0
"Unit";"Baneling";"Zergling";402;0
"Unit";"Baneling";"Zergling";402;0
"Unit";"Baneling";"Zergling";402;0
"Unit";"Baneling";"Zergling";402;0
"Unit";"Baneling";"Zergling";402;0
"Unit";"Baneling";"Zergling";402;0
"Unit";"Baneling";"Zergling";402;0
"Unit";"Baneling";"Zergling";402;0
"Unit";"Baneling";"Zergling";402;0
"Unit";"Baneling";"Zergling";402;0
"Unit";"Baneling";"Zergling";402;0
"Building";"UltraliskCavern";NA;368;0
"Unit";"Hydralisk";"Larva";386;2
"Unit";"Hydralisk";"Larva";386;2
"Unit";"Hydralisk";"Larva";386;2
"Unit";"Hydralisk";"Larva";386;2
"Unit";"Hydralisk";"Larva";386;2
"Unit";"Hydralisk";"Larva";386;2
"Unit";"Hydralisk";"Larva";386;2
"Unit";"Hydralisk";"Larva";386;2
"Unit";"Hydralisk";"Larva";386;2
"Unit";"Zergling";"Larva";420;1
"Unit";"Zergling";"Larva";420;1
"Unit";"Zergling";"Larva";420;1
"Unit";"Zergling";"Larva";420;1
"Unit";"Zergling";"Larva";420;1
"Unit";"Zergling";"Larva";420;1
"Unit";"Zergling";"Larva";420;1
"Unit";"Zergling";"Larva";420;1
"Unit";"Zergling";"Larva";420;1
"Unit";"Zergling";"Larva";420;1
"Unit";"Zergling";"Larva";420;1
"Unit";"Zergling";"Larva";420;1
"Unit";"Zergling";"Larva";420;1
"Unit";"Zergling";"Larva";420;1
"Unit";"Zergling";"Larva";420;1
"Unit";"Zergling";"Larva";420;1
"Unit";"Zergling";"Larva";420;1
"Unit";"Zergling";"Larva";420;1
"Unit";"Zergling";"Larva";420;1
"Unit";"Zergling";"Larva";420;1
"Unit";"Zergling";"Larva";420;1
"Unit";"Zergling";"Larva";420;1
"Unit";"Zergling";"Larva";420;1
"Unit";"Zergling";"Larva";420;1
"Building";"Hatchery";NA;370;0
"Unit";"Zergling";"Larva";420;1
"Unit";"Zergling";"Larva";420;1
"Unit";"Zergling";"Larva";420;1
"Unit";"Zergling";"Larva";420;1
"Unit";"Zergling";"Larva";420;1
"Unit";"Zergling";"Larva";420;1
"Unit";"Zergling";"Larva";420;1
"Unit";"Zergling";"Larva";420;1
"Unit";"Zergling";"Larva";420;1
"Unit";"Zergling";"Larva";420;1
"Unit";"Zergling";"Larva";420;1
"Unit";"Zergling";"Larva";420;1
"Unit";"Zergling";"Larva";420;1
"Unit";"Zergling";"Larva";420;1
"Unit";"Zergling";"Larva";420;1
"Unit";"Zergling";"Larva";420;1
"Unit";"Baneling";"Zergling";464;0
"Unit";"Baneling";"Zergling";464;0
"Unit";"Baneling";"Zergling";464;0
"Unit";"Baneling";"Zergling";464;0
"Unit";"Baneling";"Zergling";464;0
"Unit";"Baneling";"Zergling";464;0
"Unit";"Baneling";"Zergling";464;0
"Unit";"Baneling";"Zergling";464;0
"Unit";"Baneling";"Zergling";464;0
"Unit";"Baneling";"Zergling";464;0
"Unit";"Baneling";"Zergling";464;0
"Unit";"Baneling";"Zergling";464;0
"Unit";"Baneling";"Zergling";464;0
"Unit";"Baneling";"Zergling";464;0
"Unit";"Baneling";"Zergling";464;0
"Unit";"Overlord";"Larva";464;0
"Unit";"Overlord";"Larva";464;0
"Unit";"Overlord";"Larva";464;0
"Unit";"Overlord";"Larva";464;0
"Unit";"Overlord";"Larva";464;0
"Unit";"Overlord";"Larva";464;0
"Upgrade";"ZergGroundArmorsLevel2";"EvolutionChamber";402;0
"Unit";"Ultralisk";"Larva";464;6
"Unit";"Ultralisk";"Larva";464;6
"Unit";"Ultralisk";"Larva";464;6
"Unit";"Ultralisk";"Larva";464;6
"Unit";"Ultralisk";"Larva";464;6
"Unit";"Ultralisk";"Larva";464;6
"Unit";"Ultralisk";"Larva";464;6
"Unit";"Zergling";"Larva";464;1
"Unit";"Zergling";"Larva";464;1
"Unit";"Zergling";"Larva";464;1
"Unit";"Zergling";"Larva";464;1
"Unit";"Zergling";"Larva";464;1
"Unit";"Zergling";"Larva";464;1
"Unit";"Zergling";"Larva";464;1
"Unit";"Zergling";"Larva";464;1
"Unit";"Zergling";"Larva";464;1
"Unit";"Zergling";"Larva";464;1
"Unit";"Zergling";"Larva";464;1
"Unit";"Zergling";"Larva";464;1
"Unit";"Zergling";"Larva";464;1
"Unit";"Zergling";"Larva";464;1
"Unit";"Zergling";"Larva";464;1
"Unit";"Zergling";"Larva";464;1
"Unit";"Zergling";"Larva";464;1
"Unit";"Zergling";"Larva";464;1
"Building";"CreepTumor";NA;524;0
"Building";"CreepTumor";NA;524;0
"Building";"CreepTumor";NA;524;0
"Building";"CreepTumor";NA;524;0
"Building";"CreepTumor";NA;524;0
"Building";"CreepTumor";NA;524;0
"Unit";"Hydralisk";"Larva";524;2
"Unit";"Hydralisk";"Larva";524;2
"Unit";"Hydralisk";"Larva";524;2
"Unit";"Hydralisk";"Larva";524;2
"Unit";"Hydralisk";"Larva";524;2
"Unit";"Hydralisk";"Larva";524;2
"Unit";"Hydralisk";"Larva";524;2
"Unit";"Hydralisk";"Larva";524;2
"Unit";"Hydralisk";"Larva";524;2
"Unit";"Hydralisk";"Larva";524;2
"Unit";"Hydralisk";"Larva";524;2
"Unit";"Hydralisk";"Larva";524;2
"Unit";"Hydralisk";"Larva";524;2
"Unit";"Hydralisk";"Larva";524;2
"Unit";"Hydralisk";"Larva";524;2
"Unit";"Hydralisk";"Larva";524;2
"Unit";"Hydralisk";"Larva";524;2
"Upgrade";"ChitinousPlating";"UltraliskCavern";464;0
"Building";"SporeCrawler";NA;524;0
"Unit";"Hydralisk";"Larva";524;2
"Unit";"Hydralisk";"Larva";524;2
"Unit";"Hydralisk";"Larva";524;2
"Unit";"Hydralisk";"Larva";524;2
"Unit";"Hydralisk";"Larva";524;2
"Unit";"Hydralisk";"Larva";524;2
"Unit";"Hydralisk";"Larva";524;2
"Unit";"Hydralisk";"Larva";524;2
"Building";"SporeCrawler";NA;558;0
"Building";"SporeCrawler";NA;558;0
"Building";"CreepTumor";NA;574;0
"Building";"CreepTumor";NA;574;0
"Building";"CreepTumor";NA;584;0
"Building";"CreepTumor";NA;584;0
"Building";"CreepTumor";NA;584;0
"Building";"CreepTumor";NA;584;0
"Building";"CreepTumor";NA;584;0
"Building";"CreepTumor";NA;584;0
"Unit";"Hydralisk";"Larva";584;2
"Unit";"Hydralisk";"Larva";584;2
"Unit";"Hydralisk";"Larva";584;2
"Unit";"Hydralisk";"Larva";584;2
"Unit";"Hydralisk";"Larva";584;2
"Unit";"Hydralisk";"Larva";584;2
"Unit";"Hydralisk";"Larva";584;2
"Unit";"Hydralisk";"Larva";584;2
"Unit";"Hydralisk";"Larva";584;2
"Unit";"Baneling";"Zergling";584;0
"Unit";"Baneling";"Zergling";584;0
"Unit";"Baneling";"Zergling";584;0
"Unit";"Baneling";"Zergling";584;0
"Unit";"Baneling";"Zergling";584;0
"Unit";"Baneling";"Zergling";584;0
"Unit";"Baneling";"Zergling";584;0
"Unit";"Baneling";"Zergling";584;0
"Upgrade";"ZergMeleeWeaponsLevel3";"EvolutionChamber";524;0
"Unit";"Zergling";"Larva";602;1
"Unit";"Zergling";"Larva";602;1
"Unit";"Zergling";"Larva";604;1
"Unit";"Zergling";"Larva";604;1
"Unit";"Zergling";"Larva";604;1
"Unit";"Zergling";"Larva";604;1
"Unit";"Zergling";"Larva";604;1
"Unit";"Zergling";"Larva";604;1
"Unit";"Zergling";"Larva";604;1
"Unit";"Zergling";"Larva";604;1
"Unit";"Zergling";"Larva";604;1
"Unit";"Zergling";"Larva";604;1
"Unit";"Zergling";"Larva";604;1
"Unit";"Zergling";"Larva";604;1
"Unit";"Zergling";"Larva";604;1
"Unit";"Zergling";"Larva";604;1
"Unit";"Zergling";"Larva";604;1
"Unit";"Zergling";"Larva";604;1
"Unit";"Zergling";"Larva";604;1
"Unit";"Zergling";"Larva";604;1
"Unit";"Zergling";"Larva";604;1
"Unit";"Zergling";"Larva";604;1
"Unit";"Zergling";"Larva";604;1
"Unit";"Zergling";"Larva";604;1
"Unit";"Zergling";"Larva";604;1
"Unit";"Zergling";"Larva";604;1
"Unit";"Zergling";"Larva";604;1
"Unit";"Zergling";"Larva";604;1
"Unit";"Zergling";"Larva";604;1
"Unit";"Zergling";"Larva";604;1
"Unit";"Zergling";"Larva";604;1
"Unit";"Zergling";"Larva";604;1
"Unit";"Zergling";"Larva";604;1
"Unit";"Zergling";"Larva";604;1
"Unit";"Zergling";"Larva";604;1
"Unit";"Zergling";"Larva";604;1
"Unit";"Zergling";"Larva";604;1
"Unit";"Zergling";"Larva";604;1
"Unit";"Zergling";"Larva";604;1
"Unit";"Zergling";"Larva";604;1
"Unit";"Zergling";"Larva";604;1
"Unit";"Zergling";"Larva";604;1
"Unit";"Zergling";"Larva";604;1
"Unit";"Zergling";"Larva";604;1
"Unit";"Zergling";"Larva";604;1
"Unit";"Zergling";"Larva";604;1
"Unit";"Zergling";"Larva";604;1
"Unit";"Zergling";"Larva";604;1
"Unit";"Zergling";"Larva";604;1
"Unit";"Zergling";"Larva";604;1
"Building";"Extractor";NA;652;0
"Building";"Extractor";NA;652;0
"Unit";"Baneling";"Zergling";652;0
"Unit";"Baneling";"Zergling";652;0
"Unit";"Baneling";"Zergling";652;0
"Unit";"Baneling";"Zergling";652;0
"Unit";"Baneling";"Zergling";652;0
"Unit";"Baneling";"Zergling";652;0
"Unit";"Baneling";"Zergling";652;0
"Building";"Spire";NA;584;0
"Unit";"Baneling";"Zergling";652;0
"Unit";"Baneling";"Zergling";652;0
"Unit";"Baneling";"Zergling";652;0
"Unit";"Baneling";"Zergling";652;0
"Unit";"Baneling";"Zergling";652;0
"Unit";"Baneling";"Zergling";652;0
"Unit";"Baneling";"Zergling";652;0
"Unit";"Baneling";"Zergling";652;0
"Unit";"Queen";"Hatchery";604;2
"Unit";"Baneling";"Zergling";652;0
"Unit";"Baneling";"Zergling";652;0
"Building";"CreepTumor";NA;652;0
"Building";"CreepTumor";NA;652;0
"Unit";"Zergling";"Larva";652;1
"Unit";"Zergling";"Larva";652;1
"Unit";"Zergling";"Larva";652;1
"Unit";"Zergling";"Larva";652;1
"Unit";"Zergling";"Larva";652;1
"Unit";"Zergling";"Larva";652;1
"Unit";"Zergling";"Larva";652;1
"Unit";"Zergling";"Larva";652;1
"Unit";"Zergling";"Larva";652;1
"Unit";"Zergling";"Larva";652;1
"Unit";"Zergling";"Larva";652;1
"Unit";"Zergling";"Larva";652;1
"Unit";"Zergling";"Larva";652;1
"Unit";"Zergling";"Larva";652;1
"Unit";"Zergling";"Larva";652;1
"Unit";"Zergling";"Larva";652;1
"Unit";"Zergling";"Larva";652;1
"Unit";"Zergling";"Larva";652;1
"Unit";"Zergling";"Larva";652;1
"Unit";"Zergling";"Larva";652;1
"Unit";"Ultralisk";"Larva";652;6
"Unit";"Ultralisk";"Larva";652;6
"Unit";"Ultralisk";"Larva";652;6
"Unit";"Ultralisk";"Larva";652;6
"Upgrade";"ZergGroundArmorsLevel3";"EvolutionChamber";584;0
"Unit";"Zergling";"Larva";698;1
"Unit";"Zergling";"Larva";698;1
"Unit";"Zergling";"Larva";698;1
"Unit";"Zergling";"Larva";698;1
"Unit";"Zergling";"Larva";698;1
"Unit";"Zergling";"Larva";698;1
"Unit";"Zergling";"Larva";698;1
"Unit";"Zergling";"Larva";698;1
"Unit";"Zergling";"Larva";698;1
"Unit";"Zergling";"Larva";698;1
"Unit";"Zergling";"Larva";698;1
"Unit";"Zergling";"Larva";698;1
"Unit";"Zergling";"Larva";698;1
"Unit";"Zergling";"Larva";698;1
"Unit";"Zergling";"Larva";698;1
"Unit";"Zergling";"Larva";698;1
"Unit";"Zergling";"Larva";698;1
"Unit";"Zergling";"Larva";698;1
"Unit";"Zergling";"Larva";698;1
"Unit";"Zergling";"Larva";698;1
"Unit";"Zergling";"Larva";698;1
"Unit";"Zergling";"Larva";698;1
"Unit";"Zergling";"Larva";698;1
"Unit";"Zergling";"Larva";698;1
"Unit";"Zergling";"Larva";698;1
"Unit";"Zergling";"Larva";698;1
"Unit";"Zergling";"Larva";698;1
"Unit";"Zergling";"Larva";698;1
"Unit";"Zergling";"Larva";698;1
"Unit";"Zergling";"Larva";698;1
"Unit";"Zergling";"Larva";698;1
"Unit";"Zergling";"Larva";698;1
"Unit";"Zergling";"Larva";698;1
"Unit";"Zergling";"Larva";698;1
"Unit";"Zergling";"Larva";698;1
"Unit";"Zergling";"Larva";698;1
"Unit";"Zergling";"Larva";698;1
"Unit";"Zergling";"Larva";698;1
"Unit";"Zergling";"Larva";698;1
"Unit";"Zergling";"Larva";698;1
