"type";"unit_name";"on_building";"total_supply";"supply"
"Unit";"Overlord";"Larva";12;0
"Building";"SpawningPool";NA;19;0
"Building";"Hatchery";NA;17;0
"Unit";"Overlord";"Larva";23;0
"Unit";"Zergling";"Larva";23;1
"Unit";"Zergling";"Larva";23;1
"Unit";"Zergling";"Larva";23;1
"Unit";"Zergling";"Larva";23;1
"Unit";"Queen";"Hatchery";23;2
"Unit";"Queen";"Hatchery";23;2
"Building";"Hatchery";NA;22;0
"Unit";"Overlord";"Larva";34;0
"Building";"Extractor";NA;38;0
"Unit";"Queen";"Hatchery";34;2
"Unit";"Queen";"Hatchery";38;2
"Building";"Extractor";NA;42;0
"Building";"CreepTumorQueen";NA;52;0
"Unit";"Overlord";"Larva";54;0
"Unit";"Overlord";"Larva";54;0
"Unit";"Overlord";"Larva";57;0
"Building";"CreepTumorQueen";NA;57;0
"Building";"CreepTumor";NA;57;0
"Building";"EvolutionChamber";NA;57;0
"Building";"EvolutionChamber";NA;57;0
"Unit";"Queen";"Hatchery";57;2
"Building";"RoachWarren";NA;57;0
"Building";"SporeCrawler";NA;67;0
"Building";"SporeCrawler";NA;68;0
"Building";"SpineCrawler";NA;65;0
"Unit";"Roach";"Larva";80;2
"Unit";"Roach";"Larva";80;2
"Unit";"Overlord";"Larva";83;0
"Unit";"Overlord";"Larva";83;0
"Building";"Extractor";NA;83;0
"Building";"SporeCrawler";NA;83;0
"Building";"Extractor";NA;87;0
"Unit";"Overlord";"Larva";87;0
"Unit";"Overlord";"Larva";87;0
"Building";"CreepTumorQueen";NA;87;0
"Building";"Extractor";NA;87;0
"Unit";"Overlord";"Larva";93;0
"Unit";"Overlord";"Larva";93;0
"Unit";"Overlord";"Larva";93;0
"Building";"Extractor";NA;93;0
"Unit";"Roach";"Larva";93;2
"Unit";"Roach";"Larva";93;2
"Unit";"Roach";"Larva";93;2
"Unit";"Zergling";"Larva";99;1
"Unit";"Zergling";"Larva";99;1
"Unit";"Zergling";"Larva";99;1
"Unit";"Zergling";"Larva";99;1
"Unit";"Zergling";"Larva";99;1
"Unit";"Zergling";"Larva";99;1
"Unit";"Zergling";"Larva";99;1
"Unit";"Zergling";"Larva";99;1
"Unit";"Overlord";"Larva";99;0
"Unit";"Overlord";"Larva";99;0
"Building";"CreepTumor";NA;113;0
"Building";"CreepTumorQueen";NA;114;0
"Upgrade";"ZergGroundArmorsLevel1";"EvolutionChamber";87;0
"Upgrade";"ZergMeleeWeaponsLevel1";"EvolutionChamber";87;0
"Building";"CreepTumorQueen";NA;121;0
"Building";"CreepTumorQueen";NA;121;0
"Unit";"Zergling";"Larva";119;1
"Unit";"Zergling";"Larva";119;1
"Unit";"Zergling";"Larva";119;1
"Unit";"Zergling";"Larva";119;1
"Building";"HydraliskDen";NA;113;0
"Building";"CreepTumorQueen";NA;121;0
"Unit";"Zergling";"Larva";121;1
"Unit";"Zergling";"Larva";121;1
"Unit";"Zergling";"Larva";121;1
"Unit";"Zergling";"Larva";121;1
"Unit";"Zergling";"Larva";121;1
"Unit";"Zergling";"Larva";121;1
"Unit";"Zergling";"Larva";121;1
"Unit";"Zergling";"Larva";121;1
"Unit";"Zergling";"Larva";121;1
"Unit";"Zergling";"Larva";121;1
"Building";"CreepTumorQueen";NA;121;0
"Unit";"Overlord";"Larva";121;0
"Building";"BanelingNest";NA;113;0
"Building";"Hatchery";NA;99;0
"Building";"CreepTumorQueen";NA;146;0
"Unit";"Zergling";"Larva";146;1
"Unit";"Zergling";"Larva";146;1
"Unit";"Zergling";"Larva";146;1
"Unit";"Zergling";"Larva";146;1
"Unit";"Zergling";"Larva";146;1
"Unit";"Zergling";"Larva";146;1
"Unit";"Zergling";"Larva";146;1
"Unit";"Zergling";"Larva";146;1
"Unit";"Zergling";"Larva";146;1
"Unit";"Zergling";"Larva";146;1
"Unit";"Zergling";"Larva";146;1
"Unit";"Zergling";"Larva";146;1
"Unit";"Zergling";"Larva";146;1
"Unit";"Zergling";"Larva";146;1
"Unit";"Zergling";"Larva";146;1
"Unit";"Zergling";"Larva";146;1
"Unit";"Zergling";"Larva";146;1
"Unit";"Zergling";"Larva";146;1
"Unit";"Zergling";"Larva";146;1
"Unit";"Zergling";"Larva";146;1
"Unit";"Baneling";"Zergling";146;0
"Unit";"Zergling";"Larva";146;1
"Unit";"Zergling";"Larva";146;1
"Building";"CreepTumor";NA;146;0
"Unit";"Baneling";"Zergling";146;0
"Building";"CreepTumor";NA;146;0
"Building";"CreepTumor";NA;146;0
"Unit";"Baneling";"Zergling";146;0
"Unit";"Baneling";"Zergling";146;0
"Unit";"Baneling";"Zergling";146;0
"Unit";"Baneling";"Zergling";146;0
"Building";"CreepTumor";NA;146;0
"Unit";"Hydralisk";"Larva";146;2
"Unit";"Hydralisk";"Larva";146;2
"Unit";"Hydralisk";"Larva";146;2
"Unit";"Hydralisk";"Larva";146;2
"Unit";"Hydralisk";"Larva";146;2
"Unit";"Hydralisk";"Larva";146;2
"Unit";"Hydralisk";"Larva";146;2
"Unit";"Hydralisk";"Larva";146;2
"Unit";"Hydralisk";"Larva";146;2
"Unit";"Overlord";"Larva";168;0
"Upgrade";"EvolveGroovedSpines";"HydraliskDen";146;0
"Unit";"Overlord";"Larva";168;0
"Unit";"Overlord";"Larva";168;0
"Unit";"Overlord";"Larva";168;0
"Unit";"Overlord";"Larva";168;0
"Unit";"Baneling";"Zergling";186;0
"Unit";"Baneling";"Zergling";186;0
"Unit";"Baneling";"Zergling";186;0
"Unit";"Baneling";"Zergling";186;0
"Unit";"Baneling";"Zergling";186;0
"Unit";"Baneling";"Zergling";186;0
"Unit";"Baneling";"Zergling";186;0
"Unit";"Baneling";"Zergling";186;0
"Unit";"Baneling";"Zergling";186;0
"Unit";"Baneling";"Zergling";186;0
"Unit";"Baneling";"Zergling";186;0
"Unit";"Baneling";"Zergling";186;0
"Unit";"Zergling";"Larva";186;1
"Unit";"Zergling";"Larva";186;1
"Building";"InfestationPit";NA;168;0
"Unit";"Zergling";"Larva";186;1
"Unit";"Zergling";"Larva";186;1
"Unit";"Zergling";"Larva";186;1
"Unit";"Zergling";"Larva";186;1
"Unit";"Zergling";"Larva";186;1
"Unit";"Zergling";"Larva";186;1
"Building";"CreepTumor";NA;186;0
"Building";"CreepTumor";NA;186;0
"Unit";"Zergling";"Larva";186;1
"Unit";"Zergling";"Larva";186;1
"Building";"CreepTumor";NA;186;0
"Unit";"Zergling";"Larva";186;1
"Unit";"Zergling";"Larva";186;1
"Unit";"Zergling";"Larva";186;1
"Unit";"Zergling";"Larva";186;1
"Unit";"Zergling";"Larva";186;1
"Unit";"Zergling";"Larva";186;1
"Unit";"Zergling";"Larva";186;1
"Unit";"Zergling";"Larva";186;1
"Unit";"Zergling";"Larva";186;1
"Unit";"Zergling";"Larva";186;1
"Unit";"Zergling";"Larva";186;1
"Unit";"Zergling";"Larva";186;1
"Unit";"Zergling";"Larva";186;1
"Unit";"Zergling";"Larva";186;1
"Building";"CreepTumor";NA;188;0
"Unit";"Zergling";"Larva";186;1
"Unit";"Zergling";"Larva";186;1
"Unit";"Zergling";"Larva";186;1
"Unit";"Zergling";"Larva";186;1
"Unit";"Zergling";"Larva";186;1
"Unit";"Zergling";"Larva";186;1
"Unit";"Zergling";"Larva";186;1
"Unit";"Zergling";"Larva";186;1
"Unit";"Zergling";"Larva";186;1
"Unit";"Zergling";"Larva";186;1
"Unit";"Zergling";"Larva";186;1
"Unit";"Zergling";"Larva";186;1
"Building";"Extractor";NA;186;0
"Building";"Extractor";NA;186;0
"Building";"CreepTumor";NA;197;0
"Building";"CreepTumorQueen";NA;197;0
"Building";"CreepTumorQueen";NA;197;0
"Building";"CreepTumorQueen";NA;197;0
"Unit";"Overlord";"Larva";195;0
"Building";"CreepTumorQueen";NA;197;0
"Unit";"Zergling";"Larva";197;1
"Unit";"Zergling";"Larva";197;1
"Unit";"Zergling";"Larva";197;1
"Unit";"Zergling";"Larva";197;1
"Unit";"Zergling";"Larva";197;1
"Unit";"Zergling";"Larva";197;1
"Unit";"Zergling";"Larva";197;1
"Unit";"Zergling";"Larva";197;1
"Unit";"Zergling";"Larva";197;1
"Unit";"Zergling";"Larva";197;1
"Unit";"Zergling";"Larva";197;1
"Unit";"Zergling";"Larva";197;1
"Unit";"Zergling";"Larva";197;1
"Unit";"Zergling";"Larva";197;1
"Unit";"Zergling";"Larva";197;1
"Unit";"Zergling";"Larva";197;1
"Unit";"Zergling";"Larva";197;1
"Unit";"Zergling";"Larva";197;1
"Unit";"Zergling";"Larva";225;1
"Unit";"Zergling";"Larva";225;1
"Upgrade";"ZergGroundArmorsLevel2";"EvolutionChamber";146;0
"Upgrade";"ZergMeleeWeaponsLevel2";"EvolutionChamber";146;0
"Unit";"Baneling";"Zergling";225;0
"Unit";"Baneling";"Zergling";225;0
"Unit";"Baneling";"Zergling";225;0
"Unit";"Baneling";"Zergling";225;0
"Unit";"Baneling";"Zergling";225;0
"Unit";"Baneling";"Zergling";225;0
"Unit";"Baneling";"Zergling";225;0
"Unit";"Baneling";"Zergling";225;0
"Unit";"Zergling";"Larva";225;1
"Unit";"Zergling";"Larva";225;1
"Unit";"Zergling";"Larva";225;1
"Unit";"Zergling";"Larva";225;1
"Unit";"Zergling";"Larva";225;1
"Unit";"Zergling";"Larva";225;1
"Unit";"Zergling";"Larva";225;1
"Unit";"Zergling";"Larva";225;1
"Building";"Hatchery";NA;168;0
"Building";"CreepTumorQueen";NA;245;0
"Unit";"Hydralisk";"Larva";225;2
"Unit";"Hydralisk";"Larva";225;2
"Building";"Hatchery";NA;170;0
"Building";"CreepTumor";NA;245;0
"Building";"CreepTumor";NA;245;0
"Building";"CreepTumor";NA;245;0
"Building";"CreepTumor";NA;245;0
"Upgrade";"EvolveMuscularAugments";"HydraliskDen";186;0
"Unit";"Hydralisk";"Larva";243;2
"Unit";"Hydralisk";"Larva";243;2
"Unit";"Hydralisk";"Larva";243;2
"Unit";"Hydralisk";"Larva";243;2
"Unit";"Hydralisk";"Larva";243;2
"Unit";"Hydralisk";"Larva";243;2
"Unit";"Hydralisk";"Larva";243;2
"Unit";"Zergling";"Larva";253;1
"Unit";"Zergling";"Larva";253;1
"Unit";"Zergling";"Larva";253;1
"Unit";"Zergling";"Larva";253;1
"Unit";"Zergling";"Larva";253;1
"Unit";"Zergling";"Larva";253;1
"Unit";"Zergling";"Larva";253;1
"Unit";"Zergling";"Larva";253;1
"Unit";"Zergling";"Larva";253;1
"Unit";"Zergling";"Larva";253;1
"Unit";"Zergling";"Larva";253;1
"Unit";"Zergling";"Larva";253;1
"Unit";"Hydralisk";"Larva";271;2
"Unit";"Hydralisk";"Larva";271;2
"Unit";"Hydralisk";"Larva";271;2
"Unit";"Hydralisk";"Larva";271;2
"Unit";"Hydralisk";"Larva";271;2
"Unit";"Hydralisk";"Larva";271;2
"Unit";"Zergling";"Larva";283;1
"Unit";"Zergling";"Larva";283;1
"Unit";"Zergling";"Larva";283;1
"Unit";"Zergling";"Larva";283;1
"Unit";"Baneling";"Zergling";283;0
"Unit";"Baneling";"Zergling";283;0
"Unit";"Baneling";"Zergling";283;0
"Unit";"Baneling";"Zergling";283;0
"Unit";"Baneling";"Zergling";283;0
"Unit";"Hydralisk";"Larva";283;2
"Unit";"Zergling";"Larva";283;1
"Unit";"Zergling";"Larva";283;1
"Unit";"Hydralisk";"Larva";283;2
"Unit";"Zergling";"Larva";283;1
"Unit";"Zergling";"Larva";283;1
"Unit";"Zergling";"Larva";283;1
"Unit";"Zergling";"Larva";283;1
"Unit";"Zergling";"Larva";283;1
"Unit";"Zergling";"Larva";283;1
"Unit";"Zergling";"Larva";283;1
"Unit";"Zergling";"Larva";283;1
"Unit";"Zergling";"Larva";283;1
"Unit";"Zergling";"Larva";283;1
"Unit";"Zergling";"Larva";283;1
"Unit";"Zergling";"Larva";283;1
"Unit";"Zergling";"Larva";283;1
"Unit";"Zergling";"Larva";283;1
"Unit";"Zergling";"Larva";283;1
"Unit";"Zergling";"Larva";283;1
"Unit";"Zergling";"Larva";283;1
"Unit";"Zergling";"Larva";283;1
"Unit";"Zergling";"Larva";283;1
"Unit";"Zergling";"Larva";283;1
"Unit";"Zergling";"Larva";283;1
"Unit";"Zergling";"Larva";283;1
"Unit";"Zergling";"Larva";283;1
"Unit";"Zergling";"Larva";283;1
"Unit";"Zergling";"Larva";283;1
"Unit";"Zergling";"Larva";283;1
"Building";"CreepTumor";NA;299;0
"Building";"CreepTumor";NA;299;0
"Unit";"Zergling";"Larva";299;1
"Unit";"Zergling";"Larva";299;1
"Building";"CreepTumorQueen";NA;305;0
"Unit";"Zergling";"Larva";299;1
"Unit";"Zergling";"Larva";299;1
"Unit";"Zergling";"Larva";299;1
"Unit";"Zergling";"Larva";299;1
"Building";"CreepTumorQueen";NA;329;0
"Unit";"Zergling";"Larva";329;1
"Unit";"Zergling";"Larva";329;1
"Unit";"Zergling";"Larva";331;1
"Unit";"Zergling";"Larva";331;1
"Unit";"Overlord";"Larva";339;0
"Unit";"Overlord";"Larva";339;0
"Unit";"Overlord";"Larva";339;0
"Building";"SporeCrawler";NA;341;0
"Building";"SporeCrawler";NA;341;0
"Unit";"Zergling";"Larva";341;1
"Unit";"Zergling";"Larva";341;1
"Unit";"Zergling";"Larva";341;1
"Unit";"Zergling";"Larva";341;1
"Unit";"Zergling";"Larva";341;1
"Unit";"Zergling";"Larva";341;1
"Unit";"Zergling";"Larva";341;1
"Unit";"Zergling";"Larva";341;1
"Unit";"Zergling";"Larva";341;1
"Unit";"Zergling";"Larva";341;1
"Building";"CreepTumor";NA;341;0
"Building";"CreepTumor";NA;341;0
"Unit";"Baneling";"Zergling";341;0
"Unit";"Baneling";"Zergling";341;0
"Unit";"Baneling";"Zergling";341;0
"Unit";"Baneling";"Zergling";341;0
"Unit";"Baneling";"Zergling";341;0
"Unit";"Baneling";"Zergling";341;0
"Unit";"Baneling";"Zergling";341;0
"Unit";"Baneling";"Zergling";341;0
"Unit";"Baneling";"Zergling";341;0
"Unit";"Baneling";"Zergling";341;0
"Building";"CreepTumor";NA;346;0
"Building";"CreepTumor";NA;356;0
"Building";"CreepTumor";NA;356;0
"Building";"CreepTumor";NA;356;0
"Unit";"Overlord";"Larva";346;0
"Building";"UltraliskCavern";NA;341;0
"Unit";"Overlord";"Larva";356;0
"Unit";"Overlord";"Larva";356;0
"Unit";"Zergling";"Larva";356;1
"Unit";"Zergling";"Larva";356;1
"Unit";"Zergling";"Larva";357;1
"Unit";"Zergling";"Larva";357;1
"Unit";"Queen";"Hatchery";356;2
"Building";"Hatchery";NA;346;0
"Unit";"Overlord";"Larva";367;0
"Building";"CreepTumor";NA;367;0
"Building";"CreepTumor";NA;367;0
"Unit";"Overlord";"Larva";367;0
"Unit";"Overlord";"Larva";367;0
"Building";"Extractor";NA;367;0
"Building";"Extractor";NA;367;0
"Unit";"Zergling";"Larva";367;1
"Unit";"Zergling";"Larva";367;1
"Unit";"Zergling";"Larva";367;1
"Unit";"Zergling";"Larva";367;1
"Unit";"Zergling";"Larva";367;1
"Unit";"Zergling";"Larva";367;1
"Upgrade";"ChitinousPlating";"UltraliskCavern";361;0
"Unit";"Overlord";"Larva";367;0
"Upgrade";"Burrow";"Hatchery";367;0
"Building";"Spire";NA;361;0
"Upgrade";"ZergGroundArmorsLevel3";"EvolutionChamber";356;0
"Upgrade";"ZergMeleeWeaponsLevel3";"EvolutionChamber";356;0
"Unit";"Ultralisk";"Larva";367;6
"Unit";"Ultralisk";"Larva";367;6
"Unit";"Hydralisk";"Larva";381;2
"Unit";"Hydralisk";"Larva";381;2
"Unit";"Hydralisk";"Larva";381;2
"Unit";"Hydralisk";"Larva";381;2
"Unit";"Hydralisk";"Larva";381;2
"Unit";"Hydralisk";"Larva";381;2
"Unit";"Zergling";"Larva";393;1
"Unit";"Zergling";"Larva";393;1
"Unit";"Zergling";"Larva";393;1
"Unit";"Zergling";"Larva";393;1
"Unit";"Zergling";"Larva";393;1
"Unit";"Zergling";"Larva";393;1
"Unit";"Zergling";"Larva";393;1
"Unit";"Zergling";"Larva";393;1
"Unit";"Zergling";"Larva";393;1
"Unit";"Zergling";"Larva";393;1
"Unit";"Zergling";"Larva";393;1
"Unit";"Zergling";"Larva";393;1
"Unit";"Zergling";"Larva";393;1
"Unit";"Zergling";"Larva";393;1
"Unit";"Zergling";"Larva";393;1
"Unit";"Zergling";"Larva";393;1
"Unit";"Zergling";"Larva";395;1
"Unit";"Zergling";"Larva";395;1
"Unit";"Zergling";"Larva";395;1
"Unit";"Zergling";"Larva";395;1
"Unit";"Zergling";"Larva";395;1
"Unit";"Zergling";"Larva";395;1
"Unit";"Zergling";"Larva";395;1
"Unit";"Zergling";"Larva";395;1
"Unit";"Zergling";"Larva";397;1
"Unit";"Zergling";"Larva";397;1
"Unit";"Zergling";"Larva";397;1
"Unit";"Zergling";"Larva";397;1
"Unit";"Zergling";"Larva";397;1
"Unit";"Zergling";"Larva";397;1
"Unit";"Zergling";"Larva";397;1
"Unit";"Zergling";"Larva";397;1
"Unit";"Zergling";"Larva";397;1
"Unit";"Zergling";"Larva";397;1
"Unit";"Zergling";"Larva";397;1
"Unit";"Zergling";"Larva";397;1
"Unit";"Zergling";"Larva";397;1
"Unit";"Zergling";"Larva";397;1
"Unit";"Zergling";"Larva";397;1
"Unit";"Zergling";"Larva";397;1
"Unit";"Zergling";"Larva";399;1
"Unit";"Zergling";"Larva";399;1
"Unit";"Zergling";"Larva";399;1
"Unit";"Zergling";"Larva";399;1
"Unit";"Zergling";"Larva";399;1
"Unit";"Zergling";"Larva";399;1
"Unit";"Zergling";"Larva";399;1
"Unit";"Zergling";"Larva";399;1
"Unit";"Zergling";"Larva";399;1
"Unit";"Zergling";"Larva";399;1
"Unit";"Zergling";"Larva";399;1
"Unit";"Zergling";"Larva";399;1
"Unit";"Zergling";"Larva";399;1
"Unit";"Zergling";"Larva";399;1
"Unit";"Zergling";"Larva";399;1
"Unit";"Zergling";"Larva";399;1
"Unit";"Hydralisk";"Larva";393;2
"Unit";"Hydralisk";"Larva";393;2
"Unit";"Hydralisk";"Larva";393;2
"Unit";"Hydralisk";"Larva";393;2
"Unit";"Hydralisk";"Larva";393;2
"Unit";"Hydralisk";"Larva";405;2
"Unit";"Ultralisk";"Larva";393;6
"Unit";"Ultralisk";"Larva";393;6
"Unit";"Hydralisk";"Larva";405;2
"Unit";"Ultralisk";"Larva";393;6
"Unit";"Ultralisk";"Larva";393;6
"Unit";"Ultralisk";"Larva";393;6
"Building";"CreepTumor";NA;471;0
"Building";"CreepTumor";NA;471;0
"Unit";"Baneling";"Zergling";471;0
"Unit";"Baneling";"Zergling";471;0
"Unit";"Baneling";"Zergling";471;0
"Unit";"Baneling";"Zergling";471;0
"Unit";"Baneling";"Zergling";471;0
"Unit";"Baneling";"Zergling";471;0
"Unit";"Baneling";"Zergling";471;0
"Unit";"Baneling";"Zergling";471;0
"Unit";"Baneling";"Zergling";471;0
"Unit";"Baneling";"Zergling";471;0
"Unit";"Baneling";"Zergling";471;0
"Unit";"Baneling";"Zergling";471;0
"Unit";"Baneling";"Zergling";471;0
"Unit";"Baneling";"Zergling";471;0
"Unit";"Baneling";"Zergling";471;0
"Building";"CreepTumor";NA;471;0
"Building";"CreepTumor";NA;471;0
"Unit";"Baneling";"Zergling";471;0
"Unit";"Baneling";"Zergling";471;0
"Unit";"Baneling";"Zergling";471;0
"Unit";"Baneling";"Zergling";471;0
"Building";"CreepTumor";NA;471;0
"Unit";"Baneling";"Zergling";471;0
"Unit";"Baneling";"Zergling";471;0
"Unit";"Baneling";"Zergling";471;0
"Building";"CreepTumor";NA;471;0
"Building";"CreepTumor";NA;471;0
