"type";"unit_name";"on_building";"total_supply";"supply"
"Unit";"Overlord";"Larva";13;0
"Building";"Extractor";NA;19;0
"Unit";"Overlord";"Larva";21;0
"Building";"SpawningPool";NA;19;0
"Building";"Hatchery";NA;17;0
"Unit";"Zergling";"Larva";22;1
"Unit";"Zergling";"Larva";22;1
"Unit";"Queen";"Hatchery";22;2
"Unit";"Queen";"Hatchery";22;2
"Unit";"Zergling";"Larva";26;1
"Unit";"Zergling";"Larva";26;1
"Building";"CreepTumorQueen";NA;34;0
"Unit";"Overlord";"Larva";35;0
"Unit";"Queen";"Hatchery";31;2
"Building";"CreepTumor";NA;37;0
"Building";"Hatchery";NA;26;0
"Unit";"Overlord";"Larva";43;0
"Building";"CreepTumor";NA;48;0
"Building";"CreepTumorQueen";NA;50;0
"Unit";"Zergling";"Larva";50;1
"Unit";"Zergling";"Larva";50;1
"Unit";"Zergling";"Larva";50;1
"Unit";"Zergling";"Larva";50;1
"Unit";"Zergling";"Larva";50;1
"Unit";"Zergling";"Larva";50;1
"Unit";"Zergling";"Larva";50;1
"Unit";"Zergling";"Larva";50;1
"Unit";"Queen";"Hatchery";48;2
"Unit";"Queen";"Hatchery";48;2
"Unit";"Queen";"Hatchery";48;2
"Unit";"Overlord";"Larva";50;0
"Unit";"Overlord";"Larva";51;0
"Unit";"Overlord";"Larva";61;0
"Building";"CreepTumorQueen";NA;67;0
"Unit";"Overlord";"Larva";69;0
"Building";"EvolutionChamber";NA;67;0
"Building";"EvolutionChamber";NA;67;0
"Building";"CreepTumorQueen";NA;69;0
"Unit";"Queen";"Hatchery";69;2
"Building";"CreepTumor";NA;73;0
"Unit";"Queen";"Hatchery";69;2
"Unit";"Queen";"Hatchery";69;2
"Building";"CreepTumor";NA;83;0
"Building";"CreepTumor";NA;90;0
"Building";"Extractor";NA;81;0
"Building";"Extractor";NA;83;0
"Unit";"Overlord";"Larva";96;0
"Building";"Extractor";NA;98;0
"Building";"Extractor";NA;99;0
"Building";"Extractor";NA;99;0
"Building";"BanelingNest";NA;90;0
"Building";"CreepTumor";NA;100;0
"Building";"CreepTumor";NA;100;0
"Unit";"Zergling";"Larva";100;1
"Unit";"Zergling";"Larva";100;1
"Unit";"Zergling";"Larva";100;1
"Unit";"Zergling";"Larva";100;1
"Unit";"Zergling";"Larva";100;1
"Unit";"Zergling";"Larva";100;1
"Unit";"Zergling";"Larva";100;1
"Unit";"Zergling";"Larva";100;1
"Unit";"Zergling";"Larva";100;1
"Unit";"Zergling";"Larva";100;1
"Unit";"Zergling";"Larva";100;1
"Unit";"Zergling";"Larva";100;1
"Unit";"Zergling";"Larva";100;1
"Unit";"Zergling";"Larva";100;1
"Building";"CreepTumorQueen";NA;118;0
"Building";"CreepTumor";NA;120;0
"Unit";"Zergling";"Larva";118;1
"Unit";"Zergling";"Larva";118;1
"Unit";"Zergling";"Larva";118;1
"Unit";"Zergling";"Larva";118;1
"Unit";"Zergling";"Larva";118;1
"Unit";"Zergling";"Larva";118;1
"Building";"CreepTumor";NA;120;0
"Unit";"Overlord";"Larva";120;0
"Unit";"Overlord";"Larva";120;0
"Unit";"Overlord";"Larva";120;0
"Upgrade";"ZergGroundArmorsLevel1";"EvolutionChamber";90;0
"Unit";"Overlord";"Larva";122;0
"Unit";"Baneling";"Zergling";128;0
"Unit";"Baneling";"Zergling";128;0
"Unit";"Baneling";"Zergling";128;0
"Unit";"Baneling";"Zergling";128;0
"Upgrade";"ZergMeleeWeaponsLevel1";"EvolutionChamber";99;0
"Unit";"Zergling";"Larva";128;1
"Unit";"Zergling";"Larva";128;1
"Unit";"Zergling";"Larva";128;1
"Unit";"Zergling";"Larva";128;1
"Unit";"Zergling";"Larva";128;1
"Unit";"Zergling";"Larva";128;1
"Unit";"Zergling";"Larva";128;1
"Unit";"Zergling";"Larva";128;1
"Unit";"Zergling";"Larva";128;1
"Unit";"Zergling";"Larva";128;1
"Building";"CreepTumor";NA;128;0
"Building";"CreepTumor";NA;128;0
"Unit";"Zergling";"Larva";128;1
"Unit";"Zergling";"Larva";128;1
"Building";"HydraliskDen";NA;128;0
"Building";"CreepTumor";NA;128;0
"Building";"CreepTumorQueen";NA;128;0
"Building";"CreepTumorQueen";NA;128;0
"Building";"CreepTumorQueen";NA;128;0
"Unit";"Overlord";"Larva";128;0
"Building";"CreepTumor";NA;142;0
"Unit";"Zergling";"Larva";129;1
"Unit";"Zergling";"Larva";129;1
"Unit";"Zergling";"Larva";130;1
"Unit";"Zergling";"Larva";130;1
"Unit";"Zergling";"Larva";131;1
"Unit";"Zergling";"Larva";131;1
"Unit";"Zergling";"Larva";131;1
"Unit";"Zergling";"Larva";131;1
"Unit";"Baneling";"Zergling";142;0
"Unit";"Baneling";"Zergling";142;0
"Building";"Hatchery";NA;106;0
"Unit";"Overlord";"Larva";142;0
"Unit";"Overlord";"Larva";142;0
"Building";"CreepTumor";NA;152;0
"Building";"CreepTumor";NA;152;0
"Building";"CreepTumor";NA;152;0
"Building";"CreepTumor";NA;152;0
"Unit";"Hydralisk";"Larva";144;2
"Unit";"Hydralisk";"Larva";144;2
"Unit";"Hydralisk";"Larva";144;2
"Unit";"Hydralisk";"Larva";144;2
"Building";"Hatchery";NA;122;0
"Unit";"Hydralisk";"Larva";152;2
"Unit";"Hydralisk";"Larva";152;2
"Building";"CreepTumor";NA;152;0
"Unit";"Hydralisk";"Larva";152;2
"Unit";"Hydralisk";"Larva";152;2
"Unit";"Hydralisk";"Larva";152;2
"Unit";"Hydralisk";"Larva";152;2
"Building";"CreepTumor";NA;160;0
"Unit";"Hydralisk";"Larva";152;2
"Unit";"Overlord";"Larva";160;0
"Unit";"Hydralisk";"Larva";152;2
"Unit";"Overlord";"Larva";164;0
"Building";"CreepTumorQueen";NA;176;0
"Building";"CreepTumorQueen";NA;176;0
"Upgrade";"EvolveMuscularAugments";"HydraliskDen";152;0
"Unit";"Hydralisk";"Larva";176;2
"Unit";"Hydralisk";"Larva";176;2
"Building";"CreepTumor";NA;184;0
"Building";"InfestationPit";NA;174;0
"Building";"CreepTumor";NA;184;0
"Building";"CreepTumor";NA;184;0
"Building";"CreepTumor";NA;184;0
"Unit";"Zergling";"Larva";184;1
"Unit";"Zergling";"Larva";184;1
"Unit";"Zergling";"Larva";184;1
"Unit";"Zergling";"Larva";184;1
"Unit";"Zergling";"Larva";184;1
"Unit";"Zergling";"Larva";184;1
"Unit";"Zergling";"Larva";184;1
"Unit";"Zergling";"Larva";184;1
"Unit";"Zergling";"Larva";184;1
"Unit";"Zergling";"Larva";184;1
"Unit";"Zergling";"Larva";184;1
"Unit";"Zergling";"Larva";184;1
"Unit";"Zergling";"Larva";184;1
"Unit";"Zergling";"Larva";184;1
"Unit";"Zergling";"Larva";184;1
"Unit";"Zergling";"Larva";184;1
"Unit";"Hydralisk";"Larva";188;2
"Unit";"Hydralisk";"Larva";188;2
"Building";"CreepTumor";NA;204;0
"Unit";"Baneling";"Zergling";204;0
"Building";"CreepTumor";NA;204;0
"Unit";"Baneling";"Zergling";204;0
"Unit";"Baneling";"Zergling";204;0
"Unit";"Baneling";"Zergling";204;0
"Unit";"Baneling";"Zergling";204;0
"Unit";"Baneling";"Zergling";204;0
"Unit";"Baneling";"Zergling";204;0
"Unit";"Baneling";"Zergling";204;0
"Unit";"Baneling";"Zergling";204;0
"Unit";"Zergling";"Larva";204;1
"Unit";"Zergling";"Larva";204;1
"Unit";"Zergling";"Larva";204;1
"Unit";"Zergling";"Larva";204;1
"Unit";"Zergling";"Larva";204;1
"Unit";"Zergling";"Larva";204;1
"Unit";"Zergling";"Larva";204;1
"Unit";"Zergling";"Larva";204;1
"Unit";"Zergling";"Larva";204;1
"Unit";"Zergling";"Larva";204;1
"Unit";"Zergling";"Larva";204;1
"Unit";"Zergling";"Larva";204;1
"Unit";"Zergling";"Larva";204;1
"Unit";"Zergling";"Larva";204;1
"Unit";"Zergling";"Larva";204;1
"Unit";"Zergling";"Larva";204;1
"Building";"CreepTumor";NA;204;0
"Building";"CreepTumor";NA;208;0
"Building";"CreepTumor";NA;208;0
"Building";"Extractor";NA;210;0
"Unit";"Zergling";"Larva";224;1
"Unit";"Zergling";"Larva";224;1
"Unit";"Zergling";"Larva";224;1
"Unit";"Zergling";"Larva";224;1
"Unit";"Zergling";"Larva";224;1
"Unit";"Zergling";"Larva";224;1
"Unit";"Zergling";"Larva";224;1
"Unit";"Zergling";"Larva";224;1
"Unit";"Zergling";"Larva";224;1
"Unit";"Zergling";"Larva";224;1
"Unit";"Zergling";"Larva";224;1
"Unit";"Zergling";"Larva";224;1
"Unit";"Zergling";"Larva";224;1
"Unit";"Zergling";"Larva";224;1
"Unit";"Zergling";"Larva";224;1
"Unit";"Zergling";"Larva";224;1
"Unit";"Zergling";"Larva";224;1
"Unit";"Zergling";"Larva";224;1
"Unit";"Zergling";"Larva";224;1
"Unit";"Zergling";"Larva";224;1
"Unit";"Zergling";"Larva";224;1
"Unit";"Zergling";"Larva";224;1
"Unit";"Zergling";"Larva";224;1
"Unit";"Zergling";"Larva";224;1
"Unit";"Zergling";"Larva";224;1
"Unit";"Zergling";"Larva";224;1
"Unit";"Zergling";"Larva";224;1
"Unit";"Zergling";"Larva";224;1
"Unit";"Zergling";"Larva";224;1
"Unit";"Zergling";"Larva";224;1
"Unit";"Zergling";"Larva";224;1
"Unit";"Zergling";"Larva";224;1
"Building";"Hatchery";NA;184;0
"Building";"Extractor";NA;224;0
"Upgrade";"EvolveGroovedSpines";"HydraliskDen";204;0
"Unit";"Baneling";"Zergling";259;0
"Unit";"Baneling";"Zergling";259;0
"Building";"Hatchery";NA;204;0
"Unit";"Hydralisk";"Larva";259;2
"Unit";"Hydralisk";"Larva";259;2
"Unit";"Hydralisk";"Larva";259;2
"Unit";"Hydralisk";"Larva";259;2
"Unit";"Hydralisk";"Larva";259;2
"Unit";"Hydralisk";"Larva";259;2
"Unit";"Hydralisk";"Larva";259;2
"Upgrade";"ZergGroundArmorsLevel2";"EvolutionChamber";184;0
"Upgrade";"ZergMeleeWeaponsLevel2";"EvolutionChamber";184;0
"Unit";"Hydralisk";"Larva";259;2
"Unit";"Hydralisk";"Larva";259;2
"Unit";"Hydralisk";"Larva";259;2
"Unit";"Hydralisk";"Larva";259;2
"Unit";"Baneling";"Zergling";273;0
"Unit";"Baneling";"Zergling";273;0
"Unit";"Baneling";"Zergling";273;0
"Unit";"Baneling";"Zergling";273;0
"Unit";"Baneling";"Zergling";273;0
"Unit";"Baneling";"Zergling";273;0
"Unit";"Hydralisk";"Larva";259;2
"Unit";"Hydralisk";"Larva";259;2
"Building";"CreepTumor";NA;273;0
"Building";"CreepTumor";NA;273;0
"Unit";"Viper";"Larva";259;3
"Unit";"Viper";"Larva";259;3
"Unit";"Zergling";"Larva";281;1
"Unit";"Zergling";"Larva";281;1
"Unit";"Zergling";"Larva";281;1
"Unit";"Zergling";"Larva";281;1
"Unit";"Hydralisk";"Larva";273;2
"Unit";"Hydralisk";"Larva";273;2
"Unit";"Zergling";"Larva";281;1
"Unit";"Zergling";"Larva";281;1
"Unit";"Zergling";"Larva";281;1
"Unit";"Zergling";"Larva";281;1
"Unit";"Zergling";"Larva";281;1
"Unit";"Zergling";"Larva";281;1
"Unit";"Zergling";"Larva";281;1
"Unit";"Zergling";"Larva";281;1
"Unit";"Zergling";"Larva";281;1
"Unit";"Zergling";"Larva";281;1
"Unit";"Zergling";"Larva";281;1
"Unit";"Zergling";"Larva";281;1
"Unit";"Zergling";"Larva";285;1
"Unit";"Zergling";"Larva";285;1
"Unit";"Zergling";"Larva";285;1
"Unit";"Zergling";"Larva";285;1
"Unit";"Zergling";"Larva";285;1
"Unit";"Zergling";"Larva";285;1
"Unit";"Zergling";"Larva";285;1
"Unit";"Zergling";"Larva";285;1
"Building";"CreepTumor";NA;288;0
"Building";"CreepTumor";NA;291;0
"Unit";"Zergling";"Larva";285;1
"Unit";"Zergling";"Larva";285;1
"Unit";"Zergling";"Larva";285;1
"Unit";"Zergling";"Larva";285;1
"Unit";"Zergling";"Larva";285;1
"Unit";"Zergling";"Larva";285;1
"Building";"CreepTumorQueen";NA;299;0
"Building";"CreepTumorQueen";NA;311;0
"Building";"CreepTumorQueen";NA;311;0
"Unit";"Zergling";"Larva";325;1
"Unit";"Zergling";"Larva";325;1
"Unit";"Zergling";"Larva";325;1
"Unit";"Zergling";"Larva";325;1
"Unit";"Baneling";"Zergling";325;0
"Unit";"Zergling";"Larva";325;1
"Unit";"Zergling";"Larva";325;1
"Unit";"Zergling";"Larva";325;1
"Unit";"Zergling";"Larva";325;1
"Unit";"Baneling";"Zergling";325;0
"Unit";"Baneling";"Zergling";325;0
"Unit";"Baneling";"Zergling";325;0
"Unit";"Baneling";"Zergling";325;0
"Unit";"Baneling";"Zergling";325;0
"Building";"CreepTumor";NA;325;0
"Building";"CreepTumor";NA;325;0
"Building";"CreepTumor";NA;325;0
"Building";"CreepTumor";NA;325;0
"Building";"CreepTumor";NA;325;0
"Building";"CreepTumor";NA;325;0
"Building";"CreepTumorQueen";NA;325;0
"Building";"CreepTumor";NA;325;0
"Unit";"Overlord";"Larva";325;0
"Unit";"Overlord";"Larva";325;0
"Unit";"Overlord";"Larva";325;0
"Building";"CreepTumorQueen";NA;333;0
"Building";"CreepTumorQueen";NA;333;0
"Unit";"Zergling";"Larva";333;1
"Unit";"Zergling";"Larva";333;1
"Unit";"Zergling";"Larva";333;1
"Unit";"Zergling";"Larva";333;1
"Unit";"Zergling";"Larva";333;1
"Unit";"Zergling";"Larva";333;1
"Unit";"Zergling";"Larva";333;1
"Unit";"Zergling";"Larva";333;1
"Unit";"Zergling";"Larva";333;1
"Unit";"Zergling";"Larva";333;1
"Unit";"Zergling";"Larva";333;1
"Unit";"Zergling";"Larva";333;1
"Unit";"Zergling";"Larva";333;1
"Unit";"Zergling";"Larva";333;1
"Building";"CreepTumorQueen";NA;333;0
"Unit";"Overlord";"Larva";333;0
"Unit";"Overlord";"Larva";333;0
"Unit";"Zergling";"Larva";333;1
"Unit";"Zergling";"Larva";333;1
"Unit";"Zergling";"Larva";333;1
"Unit";"Zergling";"Larva";333;1
"Unit";"Zergling";"Larva";347;1
"Unit";"Zergling";"Larva";347;1
"Building";"CreepTumor";NA;355;0
"Building";"CreepTumor";NA;355;0
"Unit";"Zergling";"Larva";347;1
"Unit";"Zergling";"Larva";347;1
"Unit";"Zergling";"Larva";347;1
"Unit";"Zergling";"Larva";347;1
"Unit";"Baneling";"Zergling";355;0
"Unit";"Baneling";"Zergling";355;0
"Unit";"Baneling";"Zergling";355;0
"Unit";"Baneling";"Zergling";355;0
"Unit";"Baneling";"Zergling";355;0
"Unit";"Baneling";"Zergling";355;0
"Unit";"Baneling";"Zergling";355;0
"Unit";"Baneling";"Zergling";355;0
"Building";"Hatchery";NA;325;0
"Building";"CreepTumor";NA;361;0
"Building";"CreepTumor";NA;361;0
"Unit";"Baneling";"Zergling";361;0
"Unit";"Baneling";"Zergling";361;0
"Unit";"Baneling";"Zergling";361;0
"Unit";"Zergling";"Larva";355;1
"Unit";"Zergling";"Larva";355;1
"Unit";"Baneling";"Zergling";361;0
"Unit";"Zergling";"Larva";355;1
"Unit";"Zergling";"Larva";355;1
"Unit";"Zergling";"Larva";355;1
"Unit";"Zergling";"Larva";355;1
"Unit";"Zergling";"Larva";355;1
"Unit";"Zergling";"Larva";355;1
"Unit";"Zergling";"Larva";355;1
"Unit";"Zergling";"Larva";355;1
"Unit";"Baneling";"Zergling";361;0
"Building";"CreepTumor";NA;365;0
"Unit";"Zergling";"Larva";361;1
"Unit";"Zergling";"Larva";361;1
"Unit";"Zergling";"Larva";361;1
"Unit";"Zergling";"Larva";361;1
"Unit";"Zergling";"Larva";361;1
"Unit";"Zergling";"Larva";361;1
"Building";"CreepTumor";NA;365;0
"Unit";"Zergling";"Larva";365;1
"Unit";"Zergling";"Larva";365;1
"Unit";"Zergling";"Larva";365;1
"Unit";"Zergling";"Larva";365;1
"Unit";"Zergling";"Larva";365;1
"Unit";"Zergling";"Larva";365;1
"Building";"UltraliskCavern";NA;335;0
"Unit";"Zergling";"Larva";365;1
"Unit";"Zergling";"Larva";365;1
"Unit";"Zergling";"Larva";365;1
"Unit";"Zergling";"Larva";365;1
"Unit";"Zergling";"Larva";365;1
"Unit";"Zergling";"Larva";365;1
"Unit";"Zergling";"Larva";365;1
"Unit";"Zergling";"Larva";365;1
"Unit";"Zergling";"Larva";365;1
"Unit";"Zergling";"Larva";365;1
"Unit";"Zergling";"Larva";365;1
"Unit";"Zergling";"Larva";365;1
"Building";"SporeCrawler";NA;375;0
"Unit";"Zergling";"Larva";399;1
"Unit";"Zergling";"Larva";399;1
"Unit";"Zergling";"Larva";399;1
"Unit";"Zergling";"Larva";399;1
"Unit";"Zergling";"Larva";399;1
"Unit";"Zergling";"Larva";399;1
"Unit";"Zergling";"Larva";399;1
"Unit";"Zergling";"Larva";399;1
"Unit";"Zergling";"Larva";399;1
"Unit";"Zergling";"Larva";399;1
"Unit";"Zergling";"Larva";399;1
"Unit";"Zergling";"Larva";399;1
"Unit";"Zergling";"Larva";399;1
"Unit";"Zergling";"Larva";399;1
"Unit";"Zergling";"Larva";399;1
"Unit";"Zergling";"Larva";399;1
"Unit";"Zergling";"Larva";399;1
"Unit";"Zergling";"Larva";399;1
"Unit";"Zergling";"Larva";399;1
"Unit";"Zergling";"Larva";399;1
"Unit";"Zergling";"Larva";399;1
"Unit";"Zergling";"Larva";399;1
"Unit";"Zergling";"Larva";399;1
"Unit";"Zergling";"Larva";399;1
"Unit";"Zergling";"Larva";399;1
"Unit";"Zergling";"Larva";399;1
"Unit";"Zergling";"Larva";399;1
"Unit";"Zergling";"Larva";399;1
"Unit";"Zergling";"Larva";399;1
"Unit";"Zergling";"Larva";399;1
"Unit";"Zergling";"Larva";399;1
"Unit";"Zergling";"Larva";399;1
"Unit";"Zergling";"Larva";399;1
"Unit";"Zergling";"Larva";399;1
"Unit";"Zergling";"Larva";399;1
"Unit";"Zergling";"Larva";399;1
"Unit";"Zergling";"Larva";399;1
"Unit";"Zergling";"Larva";399;1
"Unit";"Zergling";"Larva";399;1
"Unit";"Zergling";"Larva";399;1
"Unit";"Zergling";"Larva";399;1
"Unit";"Zergling";"Larva";399;1
"Unit";"Baneling";"Zergling";399;0
"Unit";"Baneling";"Zergling";399;0
"Unit";"Baneling";"Zergling";399;0
"Unit";"Baneling";"Zergling";399;0
"Unit";"Baneling";"Zergling";399;0
"Unit";"Baneling";"Zergling";399;0
"Unit";"Baneling";"Zergling";399;0
"Unit";"Baneling";"Zergling";399;0
"Unit";"Baneling";"Zergling";399;0
"Unit";"Zergling";"Larva";399;1
"Unit";"Zergling";"Larva";399;1
"Unit";"Zergling";"Larva";399;1
"Unit";"Zergling";"Larva";399;1
"Unit";"Zergling";"Larva";399;1
"Unit";"Zergling";"Larva";399;1
"Unit";"Zergling";"Larva";399;1
"Unit";"Zergling";"Larva";399;1
"Unit";"Zergling";"Larva";399;1
"Unit";"Zergling";"Larva";399;1
"Unit";"Zergling";"Larva";399;1
"Unit";"Zergling";"Larva";399;1
"Unit";"Zergling";"Larva";399;1
"Unit";"Zergling";"Larva";399;1
"Unit";"Zergling";"Larva";399;1
"Unit";"Zergling";"Larva";399;1
"Unit";"Zergling";"Larva";399;1
"Unit";"Zergling";"Larva";399;1
"Unit";"Zergling";"Larva";441;1
"Unit";"Zergling";"Larva";441;1
"Unit";"Zergling";"Larva";441;1
"Unit";"Zergling";"Larva";441;1
"Unit";"Zergling";"Larva";441;1
"Unit";"Zergling";"Larva";441;1
"Unit";"Zergling";"Larva";441;1
"Unit";"Zergling";"Larva";441;1
"Unit";"Zergling";"Larva";441;1
"Unit";"Zergling";"Larva";441;1
"Unit";"Zergling";"Larva";441;1
"Unit";"Zergling";"Larva";441;1
"Unit";"Zergling";"Larva";441;1
"Unit";"Zergling";"Larva";441;1
"Unit";"Zergling";"Larva";441;1
"Unit";"Zergling";"Larva";441;1
"Building";"CreepTumor";NA;475;0
"Building";"CreepTumor";NA;475;0
"Upgrade";"ZergMeleeWeaponsLevel3";"EvolutionChamber";333;0
"Building";"CreepTumor";NA;475;0
"Upgrade";"ZergGroundArmorsLevel3";"EvolutionChamber";347;0
"Unit";"Baneling";"Zergling";475;0
"Unit";"Baneling";"Zergling";475;0
"Unit";"Baneling";"Zergling";475;0
"Unit";"Baneling";"Zergling";475;0
"Building";"CreepTumor";NA;475;0
"Building";"CreepTumor";NA;475;0
"Unit";"Hydralisk";"Larva";475;2
"Unit";"Hydralisk";"Larva";475;2
"Unit";"Hydralisk";"Larva";475;2
"Unit";"Ultralisk";"Larva";475;6
"Unit";"Ultralisk";"Larva";475;6
"Unit";"Ultralisk";"Larva";475;6
"Building";"CreepTumor";NA;475;0
"Unit";"Baneling";"Zergling";475;0
"Unit";"Baneling";"Zergling";475;0
"Unit";"Baneling";"Zergling";475;0
"Unit";"Baneling";"Zergling";475;0
"Unit";"Baneling";"Zergling";475;0
"Unit";"Baneling";"Zergling";475;0
"Unit";"Zergling";"Larva";481;1
"Unit";"Zergling";"Larva";481;1
"Unit";"Zergling";"Larva";481;1
"Unit";"Zergling";"Larva";481;1
"Unit";"Zergling";"Larva";481;1
"Unit";"Zergling";"Larva";481;1
"Unit";"Zergling";"Larva";481;1
"Unit";"Zergling";"Larva";481;1
"Unit";"Zergling";"Larva";481;1
"Unit";"Zergling";"Larva";481;1
"Unit";"Zergling";"Larva";481;1
"Unit";"Zergling";"Larva";481;1
"Building";"CreepTumor";NA;499;0
"Building";"CreepTumor";NA;499;0
"Unit";"Zergling";"Larva";499;1
"Unit";"Zergling";"Larva";499;1
"Unit";"Zergling";"Larva";499;1
"Unit";"Zergling";"Larva";499;1
"Unit";"Zergling";"Larva";499;1
"Unit";"Zergling";"Larva";499;1
"Unit";"Zergling";"Larva";499;1
"Unit";"Zergling";"Larva";499;1
"Unit";"Zergling";"Larva";499;1
"Unit";"Zergling";"Larva";499;1
"Unit";"Ultralisk";"Larva";475;6
"Unit";"Ultralisk";"Larva";475;6
"Building";"Extractor";NA;499;0
"Building";"CreepTumor";NA;527;0
"Building";"CreepTumor";NA;533;0
"Building";"CreepTumor";NA;533;0
"Upgrade";"ChitinousPlating";"UltraliskCavern";475;0
"Building";"CreepTumor";NA;533;0
"Building";"CreepTumorQueen";NA;533;0
"Building";"CreepTumor";NA;533;0
"Building";"CreepTumorQueen";NA;533;0
"Building";"CreepTumor";NA;533;0
"Unit";"Ultralisk";"Larva";499;6
"Building";"CreepTumor";NA;533;0
"Unit";"Ultralisk";"Larva";511;6
"Unit";"Baneling";"Zergling";533;0
"Unit";"Baneling";"Zergling";533;0
"Building";"CreepTumor";NA;545;0
"Unit";"Zergling";"Larva";545;1
"Unit";"Zergling";"Larva";545;1
"Unit";"Zergling";"Larva";545;1
"Unit";"Zergling";"Larva";545;1
"Unit";"Zergling";"Larva";545;1
"Unit";"Zergling";"Larva";545;1
"Unit";"Zergling";"Larva";545;1
"Unit";"Zergling";"Larva";545;1
"Building";"CreepTumor";NA;545;0
"Building";"CreepTumor";NA;553;0
"Building";"CreepTumor";NA;553;0
"Building";"CreepTumor";NA;553;0
"Building";"CreepTumor";NA;553;0
"Building";"CreepTumor";NA;553;0
"Building";"Spire";NA;533;0
"Building";"CreepTumorQueen";NA;553;0
"Building";"CreepTumorQueen";NA;553;0
"Building";"CreepTumor";NA;553;0
"Building";"CreepTumor";NA;553;0
"Building";"CreepTumor";NA;553;0
"Building";"CreepTumor";NA;553;0
"Building";"CreepTumor";NA;553;0
"Building";"CreepTumor";NA;553;0
"Building";"CreepTumor";NA;553;0
"Upgrade";"ZergMissileWeaponsLevel1";"EvolutionChamber";539;0
"Building";"Hatchery";NA;545;0
"Unit";"Corruptor";"Larva";553;2
"Unit";"Corruptor";"Larva";553;2
"Unit";"Corruptor";"Larva";553;2
"Unit";"Corruptor";"Larva";553;2
"Building";"CreepTumorQueen";NA;561;0
"Building";"CreepTumorQueen";NA;561;0
"Unit";"Zergling";"Larva";561;1
"Unit";"Zergling";"Larva";561;1
"Unit";"Zergling";"Larva";561;1
"Unit";"Zergling";"Larva";561;1
"Unit";"Zergling";"Larva";561;1
"Unit";"Zergling";"Larva";561;1
"Unit";"Zergling";"Larva";561;1
"Unit";"Zergling";"Larva";561;1
"Unit";"Zergling";"Larva";561;1
"Unit";"Zergling";"Larva";561;1
"Unit";"Zergling";"Larva";561;1
"Unit";"Zergling";"Larva";561;1
"Unit";"Zergling";"Larva";561;1
"Unit";"Zergling";"Larva";561;1
"Unit";"Zergling";"Larva";561;1
"Unit";"Zergling";"Larva";561;1
"Unit";"Zergling";"Larva";561;1
"Unit";"Zergling";"Larva";561;1
"Unit";"Zergling";"Larva";561;1
"Unit";"Zergling";"Larva";561;1
"Unit";"Zergling";"Larva";561;1
"Unit";"Zergling";"Larva";561;1
"Unit";"Ultralisk";"Larva";561;6
"Unit";"Ultralisk";"Larva";561;6
"Unit";"Zergling";"Larva";561;1
"Unit";"Zergling";"Larva";561;1
"Unit";"Zergling";"Larva";561;1
"Unit";"Zergling";"Larva";561;1
"Unit";"Ultralisk";"Larva";561;6
"Unit";"Ultralisk";"Larva";561;6
"Unit";"Ultralisk";"Larva";561;6
"Building";"CreepTumor";NA;561;0
"Unit";"Corruptor";"Larva";561;2
"Unit";"Corruptor";"Larva";561;2
"Unit";"Corruptor";"Larva";561;2
"Unit";"Corruptor";"Larva";561;2
"Unit";"Corruptor";"Larva";561;2
"Building";"CreepTumor";NA;561;0
"Unit";"Corruptor";"Larva";561;2
"Unit";"Corruptor";"Larva";561;2
"Building";"CreepTumor";NA;561;0
"Building";"CreepTumor";NA;561;0
"Building";"CreepTumor";NA;561;0
"Building";"CreepTumor";NA;561;0
"Building";"CreepTumor";NA;561;0
"Building";"CreepTumor";NA;561;0
"Building";"CreepTumor";NA;561;0
"Building";"CreepTumor";NA;561;0
"Building";"CreepTumor";NA;605;0
"Unit";"Ultralisk";"Larva";561;6
"Unit";"Ultralisk";"Larva";561;6
"Unit";"Ultralisk";"Larva";561;6
"Unit";"Baneling";"Zergling";631;0
"Unit";"Baneling";"Zergling";631;0
"Unit";"Baneling";"Zergling";631;0
"Unit";"Baneling";"Zergling";631;0
"Unit";"Baneling";"Zergling";631;0
"Unit";"Baneling";"Zergling";631;0
"Unit";"Baneling";"Zergling";631;0
"Unit";"Baneling";"Zergling";631;0
"Unit";"Baneling";"Zergling";631;0
"Unit";"Baneling";"Zergling";631;0
"Unit";"Baneling";"Zergling";631;0
"Unit";"Baneling";"Zergling";631;0
"Building";"Extractor";NA;631;0
"Building";"Extractor";NA;631;0
"Unit";"Zergling";"Larva";649;1
"Unit";"Zergling";"Larva";649;1
"Unit";"Zergling";"Larva";649;1
"Unit";"Zergling";"Larva";649;1
"Building";"CreepTumor";NA;649;0
"Unit";"Zergling";"Larva";649;1
"Unit";"Zergling";"Larva";649;1
"Unit";"Zergling";"Larva";649;1
"Unit";"Zergling";"Larva";649;1
"Unit";"Zergling";"Larva";649;1
"Unit";"Zergling";"Larva";649;1
"Unit";"Zergling";"Larva";649;1
"Unit";"Zergling";"Larva";649;1
"Unit";"Zergling";"Larva";649;1
"Unit";"Zergling";"Larva";649;1
"Unit";"Zergling";"Larva";649;1
"Unit";"Zergling";"Larva";649;1
"Unit";"Zergling";"Larva";649;1
"Unit";"Zergling";"Larva";649;1
"Unit";"Zergling";"Larva";649;1
"Unit";"Zergling";"Larva";649;1
"Unit";"Viper";"Larva";649;3
