"type";"unit_name";"on_building";"total_supply";"supply"
"Unit";"Overlord";"Larva";12;0
"Building";"Extractor";NA;19;0
"Building";"SpawningPool";NA;19;0
"Unit";"Overlord";"Larva";22;0
"Building";"Hatchery";NA;17;0
"Unit";"Zergling";"Larva";22;1
"Unit";"Zergling";"Larva";22;1
"Unit";"Zergling";"Larva";22;1
"Unit";"Zergling";"Larva";22;1
"Unit";"Queen";"Hatchery";22;2
"Unit";"Queen";"Hatchery";22;2
"Unit";"Overlord";"Larva";33;0
"Unit";"Queen";"Hatchery";33;2
"Building";"CreepTumorQueen";NA;40;0
"Unit";"Overlord";"Larva";42;0
"Building";"Hatchery";NA;33;0
"Building";"CreepTumor";NA;50;0
"Building";"Extractor";NA;50;0
"Building";"Extractor";NA;50;0
"Unit";"Overlord";"Larva";50;0
"Unit";"Overlord";"Larva";50;0
"Unit";"Zergling";"Larva";50;1
"Unit";"Zergling";"Larva";50;1
"Unit";"Zergling";"Larva";50;1
"Unit";"Zergling";"Larva";50;1
"Unit";"Queen";"Hatchery";50;2
"Building";"RoachWarren";NA;50;0
"Unit";"Overlord";"Larva";56;0
"Unit";"Overlord";"Larva";56;0
"Building";"CreepTumor";NA;63;0
"Building";"CreepTumorQueen";NA;63;0
"Unit";"Roach";"Larva";63;2
"Unit";"Roach";"Larva";63;2
"Unit";"Roach";"Larva";63;2
"Unit";"Roach";"Larva";63;2
"Unit";"Roach";"Larva";63;2
"Unit";"Roach";"Larva";63;2
"Unit";"Roach";"Larva";63;2
"Unit";"Roach";"Larva";63;2
"Building";"SporeCrawler";NA;88;0
"Building";"CreepTumorQueen";NA;92;0
"Building";"CreepTumor";NA;92;0
"Building";"CreepTumor";NA;92;0
"Building";"SporeCrawler";NA;88;0
"Unit";"Overlord";"Larva";92;0
"Building";"CreepTumorQueen";NA;92;0
"Unit";"Overlord";"Larva";92;0
"Unit";"Zergling";"Larva";100;1
"Unit";"Zergling";"Larva";100;1
"Unit";"Zergling";"Larva";100;1
"Unit";"Zergling";"Larva";100;1
"Unit";"Zergling";"Larva";100;1
"Unit";"Zergling";"Larva";100;1
"Unit";"Zergling";"Larva";100;1
"Unit";"Zergling";"Larva";100;1
"Unit";"Zergling";"Larva";100;1
"Unit";"Zergling";"Larva";100;1
"Unit";"Zergling";"Larva";100;1
"Unit";"Zergling";"Larva";100;1
"Unit";"Zergling";"Larva";100;1
"Unit";"Zergling";"Larva";100;1
"Unit";"Zergling";"Larva";100;1
"Unit";"Zergling";"Larva";100;1
"Unit";"Zergling";"Larva";100;1
"Unit";"Zergling";"Larva";100;1
"Building";"CreepTumor";NA;100;0
"Building";"EvolutionChamber";NA;100;0
"Building";"EvolutionChamber";NA;102;0
"Unit";"Queen";"Hatchery";118;2
"Building";"Hatchery";NA;100;0
"Unit";"Overlord";"Larva";138;0
"Unit";"Overlord";"Larva";138;0
"Unit";"Zergling";"Larva";138;1
"Unit";"Zergling";"Larva";138;1
"Unit";"Zergling";"Larva";138;1
"Unit";"Zergling";"Larva";138;1
"Unit";"Zergling";"Larva";138;1
"Unit";"Zergling";"Larva";138;1
"Unit";"Zergling";"Larva";138;1
"Unit";"Zergling";"Larva";138;1
"Unit";"Zergling";"Larva";138;1
"Unit";"Zergling";"Larva";138;1
"Unit";"Zergling";"Larva";138;1
"Unit";"Zergling";"Larva";138;1
"Unit";"Zergling";"Larva";138;1
"Unit";"Zergling";"Larva";138;1
"Unit";"Zergling";"Larva";138;1
"Unit";"Zergling";"Larva";138;1
"Unit";"Zergling";"Larva";138;1
"Unit";"Zergling";"Larva";138;1
"Unit";"Zergling";"Larva";138;1
"Unit";"Zergling";"Larva";138;1
"Unit";"Zergling";"Larva";138;1
"Unit";"Zergling";"Larva";138;1
"Unit";"Zergling";"Larva";138;1
"Unit";"Zergling";"Larva";138;1
"Unit";"Zergling";"Larva";138;1
"Unit";"Zergling";"Larva";138;1
"Building";"Extractor";NA;138;0
"Building";"Extractor";NA;138;0
"Building";"SporeCrawler";NA;138;0
"Unit";"Queen";"Hatchery";138;2
"Unit";"Queen";"Hatchery";138;2
"Unit";"Queen";"Hatchery";138;2
"Unit";"Queen";"Hatchery";138;2
"Building";"BanelingNest";NA;138;0
"Building";"Extractor";NA;170;0
"Unit";"Overlord";"Larva";185;0
"Unit";"Overlord";"Larva";185;0
"Building";"Extractor";NA;185;0
"Building";"Extractor";NA;185;0
"Building";"CreepTumorQueen";NA;189;0
"Building";"CreepTumor";NA;189;0
"Building";"Hatchery";NA;138;0
"Building";"CreepTumorQueen";NA;189;0
"Building";"CreepTumorQueen";NA;190;0
"Building";"CreepTumorQueen";NA;201;0
"Unit";"Queen";"Hatchery";185;2
"Unit";"Queen";"Hatchery";185;2
"Unit";"Queen";"Hatchery";185;2
"Building";"CreepTumorQueen";NA;201;0
"Unit";"Zergling";"Larva";201;1
"Unit";"Zergling";"Larva";201;1
"Unit";"Zergling";"Larva";201;1
"Unit";"Zergling";"Larva";201;1
"Unit";"Zergling";"Larva";201;1
"Unit";"Zergling";"Larva";201;1
"Unit";"Zergling";"Larva";201;1
"Unit";"Zergling";"Larva";201;1
"Unit";"Overlord";"Larva";201;0
"Unit";"Overlord";"Larva";201;0
"Unit";"Overlord";"Larva";201;0
"Unit";"Zergling";"Larva";203;1
"Unit";"Zergling";"Larva";203;1
"Unit";"Zergling";"Larva";203;1
"Unit";"Zergling";"Larva";203;1
"Unit";"Zergling";"Larva";205;1
"Unit";"Zergling";"Larva";205;1
"Unit";"Zergling";"Larva";205;1
"Unit";"Zergling";"Larva";205;1
"Unit";"Zergling";"Larva";205;1
"Unit";"Zergling";"Larva";205;1
"Building";"InfestationPit";NA;189;0
"Unit";"Zergling";"Larva";207;1
"Unit";"Zergling";"Larva";207;1
"Unit";"Zergling";"Larva";207;1
"Unit";"Zergling";"Larva";207;1
"Unit";"Zergling";"Larva";207;1
"Unit";"Zergling";"Larva";207;1
"Unit";"Zergling";"Larva";207;1
"Unit";"Zergling";"Larva";207;1
"Unit";"Zergling";"Larva";207;1
"Unit";"Zergling";"Larva";207;1
"Unit";"Zergling";"Larva";207;1
"Unit";"Zergling";"Larva";207;1
"Building";"Hatchery";NA;176;0
"Upgrade";"ZergGroundArmorsLevel1";"EvolutionChamber";170;0
"Upgrade";"ZergMeleeWeaponsLevel1";"EvolutionChamber";170;0
"Unit";"Zergling";"Larva";246;1
"Unit";"Zergling";"Larva";246;1
"Building";"HydraliskDen";NA;237;0
"Unit";"Zergling";"Larva";246;1
"Unit";"Zergling";"Larva";246;1
"Unit";"Zergling";"Larva";246;1
"Unit";"Zergling";"Larva";246;1
"Unit";"Zergling";"Larva";246;1
"Unit";"Zergling";"Larva";246;1
"Unit";"Zergling";"Larva";246;1
"Unit";"Zergling";"Larva";246;1
"Unit";"Zergling";"Larva";246;1
"Unit";"Zergling";"Larva";246;1
"Unit";"Zergling";"Larva";246;1
"Unit";"Zergling";"Larva";246;1
"Unit";"Zergling";"Larva";246;1
"Unit";"Zergling";"Larva";246;1
"Unit";"Baneling";"Zergling";249;0
"Unit";"Baneling";"Zergling";249;0
"Unit";"Baneling";"Zergling";249;0
"Unit";"Baneling";"Zergling";249;0
"Unit";"Baneling";"Zergling";249;0
"Unit";"Baneling";"Zergling";263;0
"Unit";"Baneling";"Zergling";265;0
"Unit";"Baneling";"Zergling";265;0
"Unit";"Baneling";"Zergling";265;0
"Unit";"Baneling";"Zergling";265;0
"Unit";"Queen";"Hatchery";246;2
"Unit";"Baneling";"Zergling";265;0
"Unit";"Baneling";"Zergling";265;0
"Unit";"Baneling";"Zergling";265;0
"Unit";"Baneling";"Zergling";265;0
"Unit";"Baneling";"Zergling";265;0
"Unit";"Queen";"Hatchery";246;2
"Unit";"Queen";"Hatchery";246;2
"Unit";"Queen";"Hatchery";246;2
"Unit";"Zergling";"Larva";259;1
"Unit";"Zergling";"Larva";259;1
"Unit";"Zergling";"Larva";259;1
"Unit";"Zergling";"Larva";259;1
"Unit";"Zergling";"Larva";259;1
"Unit";"Zergling";"Larva";259;1
"Unit";"Zergling";"Larva";259;1
"Unit";"Zergling";"Larva";259;1
"Unit";"Zergling";"Larva";259;1
"Unit";"Zergling";"Larva";259;1
"Unit";"Zergling";"Larva";259;1
"Unit";"Zergling";"Larva";259;1
"Unit";"Zergling";"Larva";259;1
"Unit";"Zergling";"Larva";259;1
"Unit";"Zergling";"Larva";259;1
"Unit";"Zergling";"Larva";259;1
"Unit";"Zergling";"Larva";259;1
"Unit";"Zergling";"Larva";259;1
"Unit";"Zergling";"Larva";259;1
"Unit";"Zergling";"Larva";259;1
"Unit";"Zergling";"Larva";259;1
"Unit";"Zergling";"Larva";259;1
"Building";"SporeCrawler";NA;249;0
"Unit";"Zergling";"Larva";265;1
"Unit";"Zergling";"Larva";265;1
"Unit";"Zergling";"Larva";265;1
"Unit";"Zergling";"Larva";265;1
"Unit";"Zergling";"Larva";265;1
"Unit";"Zergling";"Larva";265;1
"Unit";"Zergling";"Larva";265;1
"Unit";"Zergling";"Larva";265;1
"Unit";"Zergling";"Larva";265;1
"Unit";"Zergling";"Larva";265;1
"Unit";"Zergling";"Larva";265;1
"Unit";"Zergling";"Larva";265;1
"Unit";"Zergling";"Larva";265;1
"Unit";"Zergling";"Larva";265;1
"Unit";"Zergling";"Larva";265;1
"Unit";"Zergling";"Larva";265;1
"Unit";"Zergling";"Larva";265;1
"Unit";"Zergling";"Larva";265;1
"Unit";"Zergling";"Larva";265;1
"Unit";"Zergling";"Larva";265;1
"Unit";"Zergling";"Larva";267;1
"Unit";"Zergling";"Larva";267;1
"Unit";"Zergling";"Larva";267;1
"Unit";"Zergling";"Larva";267;1
"Unit";"Zergling";"Larva";267;1
"Unit";"Zergling";"Larva";267;1
"Building";"SpineCrawler";NA;249;0
"Unit";"Zergling";"Larva";311;1
"Unit";"Zergling";"Larva";311;1
"Unit";"Zergling";"Larva";311;1
"Unit";"Zergling";"Larva";311;1
"Unit";"Zergling";"Larva";311;1
"Unit";"Zergling";"Larva";311;1
"Unit";"Zergling";"Larva";311;1
"Unit";"Zergling";"Larva";311;1
"Unit";"Zergling";"Larva";311;1
"Unit";"Zergling";"Larva";311;1
"Unit";"Zergling";"Larva";311;1
"Unit";"Zergling";"Larva";311;1
"Unit";"Zergling";"Larva";311;1
"Unit";"Zergling";"Larva";311;1
"Unit";"Zergling";"Larva";311;1
"Unit";"Zergling";"Larva";311;1
"Unit";"Zergling";"Larva";311;1
"Unit";"Zergling";"Larva";311;1
"Unit";"Zergling";"Larva";311;1
"Unit";"Zergling";"Larva";311;1
"Unit";"Zergling";"Larva";311;1
"Unit";"Zergling";"Larva";311;1
"Unit";"Zergling";"Larva";311;1
"Unit";"Zergling";"Larva";311;1
"Unit";"Zergling";"Larva";321;1
"Unit";"Zergling";"Larva";321;1
"Unit";"Zergling";"Larva";321;1
"Unit";"Zergling";"Larva";321;1
"Unit";"Zergling";"Larva";321;1
"Unit";"Zergling";"Larva";321;1
"Unit";"Zergling";"Larva";321;1
"Unit";"Zergling";"Larva";321;1
"Unit";"Zergling";"Larva";321;1
"Unit";"Zergling";"Larva";321;1
"Unit";"Zergling";"Larva";321;1
"Unit";"Zergling";"Larva";321;1
"Building";"CreepTumorQueen";NA;341;0
"Building";"CreepTumorQueen";NA;341;0
"Building";"CreepTumorQueen";NA;345;0
"Building";"CreepTumorQueen";NA;361;0
"Building";"CreepTumorQueen";NA;361;0
"Building";"Extractor";NA;361;0
"Building";"Extractor";NA;361;0
"Unit";"Baneling";"Zergling";371;0
"Unit";"Baneling";"Zergling";371;0
"Unit";"Baneling";"Zergling";371;0
"Unit";"Baneling";"Zergling";371;0
"Unit";"Baneling";"Zergling";371;0
"Unit";"Baneling";"Zergling";371;0
"Building";"CreepTumorQueen";NA;371;0
"Unit";"Zergling";"Larva";371;1
"Unit";"Zergling";"Larva";371;1
"Unit";"Zergling";"Larva";371;1
"Unit";"Zergling";"Larva";371;1
"Unit";"Zergling";"Larva";371;1
"Unit";"Zergling";"Larva";371;1
"Unit";"Zergling";"Larva";371;1
"Unit";"Zergling";"Larva";371;1
"Unit";"Zergling";"Larva";371;1
"Unit";"Zergling";"Larva";371;1
"Unit";"Zergling";"Larva";371;1
"Unit";"Zergling";"Larva";371;1
"Unit";"Zergling";"Larva";371;1
"Unit";"Zergling";"Larva";371;1
"Building";"SporeCrawler";NA;371;0
"Unit";"Zergling";"Larva";371;1
"Unit";"Zergling";"Larva";371;1
"Unit";"Zergling";"Larva";371;1
"Unit";"Zergling";"Larva";371;1
"Unit";"Zergling";"Larva";371;1
"Unit";"Zergling";"Larva";371;1
"Building";"CreepTumorQueen";NA;371;0
"Building";"CreepTumor";NA;371;0
"Building";"CreepTumor";NA;371;0
"Building";"SporeCrawler";NA;371;0
"Unit";"Overlord";"Larva";371;0
"Unit";"Overlord";"Larva";371;0
"Unit";"Overlord";"Larva";371;0
"Unit";"Overlord";"Larva";371;0
"Building";"CreepTumor";NA;371;0
"Building";"CreepTumor";NA;371;0
"Building";"CreepTumorQueen";NA;371;0
"Building";"CreepTumor";NA;371;0
"Building";"CreepTumor";NA;371;0
"Building";"CreepTumor";NA;371;0
"Building";"UltraliskCavern";NA;371;0
"Building";"SpineCrawler";NA;371;0
"Upgrade";"ZergGroundArmorsLevel2";"EvolutionChamber";309;0
"Upgrade";"ZergMeleeWeaponsLevel2";"EvolutionChamber";309;0
"Unit";"Baneling";"Zergling";391;0
"Unit";"Baneling";"Zergling";391;0
"Unit";"Baneling";"Zergling";391;0
"Unit";"Baneling";"Zergling";391;0
"Unit";"Baneling";"Zergling";391;0
"Unit";"Baneling";"Zergling";391;0
"Unit";"Baneling";"Zergling";391;0
"Unit";"Baneling";"Zergling";391;0
"Unit";"Baneling";"Zergling";391;0
"Unit";"Baneling";"Zergling";391;0
"Unit";"Hydralisk";"Larva";391;2
"Unit";"Hydralisk";"Larva";391;2
"Unit";"Hydralisk";"Larva";391;2
"Unit";"Hydralisk";"Larva";391;2
"Unit";"Hydralisk";"Larva";391;2
"Unit";"Hydralisk";"Larva";391;2
"Unit";"Hydralisk";"Larva";391;2
"Unit";"Hydralisk";"Larva";391;2
"Unit";"Hydralisk";"Larva";391;2
"Unit";"Hydralisk";"Larva";391;2
"Unit";"Hydralisk";"Larva";391;2
"Unit";"Hydralisk";"Larva";391;2
"Unit";"Hydralisk";"Larva";391;2
"Unit";"Hydralisk";"Larva";391;2
"Unit";"Hydralisk";"Larva";391;2
"Unit";"Hydralisk";"Larva";391;2
"Building";"Spire";NA;371;0
"Unit";"Zergling";"Larva";417;1
"Unit";"Zergling";"Larva";417;1
"Unit";"Overlord";"Larva";423;0
"Unit";"Overlord";"Larva";423;0
"Unit";"Overlord";"Larva";423;0
"Unit";"Baneling";"Zergling";423;0
"Unit";"Baneling";"Zergling";423;0
"Unit";"Baneling";"Zergling";423;0
"Unit";"Baneling";"Zergling";423;0
"Unit";"Baneling";"Zergling";423;0
"Unit";"Baneling";"Zergling";423;0
"Unit";"Baneling";"Zergling";423;0
"Unit";"Baneling";"Zergling";423;0
"Unit";"Zergling";"Larva";423;1
"Unit";"Zergling";"Larva";423;1
"Unit";"Zergling";"Larva";423;1
"Unit";"Zergling";"Larva";423;1
"Unit";"Zergling";"Larva";423;1
"Unit";"Zergling";"Larva";423;1
"Unit";"Zergling";"Larva";423;1
"Unit";"Zergling";"Larva";423;1
"Unit";"Zergling";"Larva";423;1
"Unit";"Zergling";"Larva";423;1
"Unit";"Zergling";"Larva";425;1
"Unit";"Zergling";"Larva";425;1
"Upgrade";"EvolveGroovedSpines";"HydraliskDen";391;0
"Unit";"Hydralisk";"Larva";425;2
"Unit";"Hydralisk";"Larva";425;2
"Unit";"Hydralisk";"Larva";425;2
"Unit";"Hydralisk";"Larva";425;2
"Unit";"Hydralisk";"Larva";425;2
"Unit";"Hydralisk";"Larva";425;2
"Unit";"Hydralisk";"Larva";425;2
"Unit";"Hydralisk";"Larva";425;2
"Unit";"Hydralisk";"Larva";425;2
"Unit";"Hydralisk";"Larva";425;2
"Unit";"Hydralisk";"Larva";425;2
"Unit";"Hydralisk";"Larva";425;2
"Unit";"Zergling";"Larva";435;1
"Unit";"Zergling";"Larva";435;1
"Upgrade";"ChitinousPlating";"UltraliskCavern";423;0
"Unit";"Zergling";"Larva";463;1
"Unit";"Zergling";"Larva";463;1
"Unit";"Zergling";"Larva";463;1
"Unit";"Zergling";"Larva";463;1
"Unit";"Zergling";"Larva";463;1
"Unit";"Zergling";"Larva";463;1
"Unit";"Zergling";"Larva";463;1
"Unit";"Zergling";"Larva";463;1
"Unit";"Zergling";"Larva";463;1
"Unit";"Zergling";"Larva";463;1
"Unit";"Zergling";"Larva";463;1
"Unit";"Zergling";"Larva";463;1
"Unit";"Zergling";"Larva";463;1
"Unit";"Zergling";"Larva";463;1
"Unit";"Zergling";"Larva";463;1
"Unit";"Zergling";"Larva";463;1
"Unit";"Zergling";"Larva";463;1
"Unit";"Zergling";"Larva";463;1
"Unit";"Zergling";"Larva";463;1
"Unit";"Zergling";"Larva";463;1
"Unit";"Zergling";"Larva";463;1
"Unit";"Zergling";"Larva";463;1
"Unit";"Zergling";"Larva";463;1
"Unit";"Zergling";"Larva";463;1
"Unit";"Zergling";"Larva";463;1
"Unit";"Zergling";"Larva";463;1
"Unit";"Zergling";"Larva";463;1
"Unit";"Zergling";"Larva";463;1
"Unit";"Zergling";"Larva";463;1
"Unit";"Zergling";"Larva";463;1
"Unit";"Zergling";"Larva";463;1
"Unit";"Zergling";"Larva";463;1
"Unit";"Zergling";"Larva";463;1
"Unit";"Zergling";"Larva";463;1
"Unit";"Zergling";"Larva";463;1
"Unit";"Zergling";"Larva";463;1
"Unit";"Zergling";"Larva";463;1
"Unit";"Zergling";"Larva";463;1
"Unit";"Zergling";"Larva";463;1
"Unit";"Zergling";"Larva";463;1
"Unit";"Zergling";"Larva";463;1
"Unit";"Zergling";"Larva";463;1
"Unit";"Zergling";"Larva";463;1
"Unit";"Zergling";"Larva";463;1
"Unit";"Hydralisk";"Larva";463;2
"Unit";"Hydralisk";"Larva";463;2
"Unit";"Hydralisk";"Larva";463;2
"Unit";"Hydralisk";"Larva";463;2
"Unit";"Hydralisk";"Larva";463;2
"Unit";"Ultralisk";"Larva";463;6
"Unit";"Ultralisk";"Larva";463;6
"Unit";"Ultralisk";"Larva";463;6
"Unit";"Zergling";"Larva";517;1
"Unit";"Zergling";"Larva";517;1
"Unit";"Zergling";"Larva";517;1
"Unit";"Zergling";"Larva";517;1
"Unit";"Zergling";"Larva";517;1
"Unit";"Zergling";"Larva";517;1
"Unit";"Zergling";"Larva";517;1
"Unit";"Zergling";"Larva";517;1
"Unit";"Zergling";"Larva";517;1
"Unit";"Zergling";"Larva";517;1
"Unit";"Zergling";"Larva";517;1
"Unit";"Zergling";"Larva";517;1
"Unit";"Zergling";"Larva";517;1
"Unit";"Zergling";"Larva";517;1
"Unit";"Zergling";"Larva";517;1
"Unit";"Zergling";"Larva";517;1
"Unit";"Zergling";"Larva";517;1
"Unit";"Zergling";"Larva";517;1
"Unit";"Zergling";"Larva";517;1
"Unit";"Zergling";"Larva";517;1
"Unit";"Zergling";"Larva";517;1
"Unit";"Zergling";"Larva";517;1
"Unit";"Zergling";"Larva";517;1
"Unit";"Zergling";"Larva";517;1
"Unit";"Zergling";"Larva";517;1
"Unit";"Zergling";"Larva";517;1
"Unit";"Zergling";"Larva";517;1
"Unit";"Zergling";"Larva";517;1
"Unit";"Zergling";"Larva";517;1
"Unit";"Zergling";"Larva";517;1
"Unit";"Zergling";"Larva";517;1
"Unit";"Zergling";"Larva";517;1
"Unit";"Zergling";"Larva";517;1
"Unit";"Zergling";"Larva";517;1
"Unit";"Zergling";"Larva";517;1
"Unit";"Zergling";"Larva";517;1
"Unit";"Queen";"Hatchery";517;2
"Unit";"Queen";"Hatchery";517;2
"Unit";"Queen";"Hatchery";517;2
"Unit";"Queen";"Hatchery";517;2
"Unit";"Queen";"Hatchery";517;2
"Unit";"Queen";"Hatchery";517;2
"Unit";"Baneling";"Zergling";571;0
"Unit";"Baneling";"Zergling";571;0
"Unit";"Baneling";"Zergling";571;0
"Unit";"Baneling";"Zergling";571;0
"Unit";"Baneling";"Zergling";571;0
"Unit";"Baneling";"Zergling";571;0
"Unit";"Baneling";"Zergling";571;0
"Unit";"Baneling";"Zergling";571;0
"Unit";"Baneling";"Zergling";571;0
"Unit";"Baneling";"Zergling";571;0
"Unit";"Baneling";"Zergling";571;0
"Building";"CreepTumor";NA;571;0
"Building";"CreepTumor";NA;571;0
"Building";"CreepTumorQueen";NA;583;0
"Building";"CreepTumorQueen";NA;583;0
"Building";"CreepTumorQueen";NA;583;0
"Unit";"Hydralisk";"Larva";583;2
"Unit";"Hydralisk";"Larva";583;2
"Unit";"Hydralisk";"Larva";583;2
"Unit";"Hydralisk";"Larva";583;2
"Unit";"Hydralisk";"Larva";583;2
"Unit";"Hydralisk";"Larva";583;2
"Unit";"Zergling";"Larva";583;1
"Unit";"Zergling";"Larva";583;1
"Unit";"Zergling";"Larva";583;1
"Unit";"Zergling";"Larva";583;1
"Unit";"Ultralisk";"Larva";583;6
"Unit";"Ultralisk";"Larva";583;6
"Unit";"Ultralisk";"Larva";583;6
"Unit";"Zergling";"Larva";599;1
"Unit";"Zergling";"Larva";599;1
"Unit";"Zergling";"Larva";599;1
"Unit";"Zergling";"Larva";599;1
"Unit";"Zergling";"Larva";599;1
"Unit";"Zergling";"Larva";599;1
"Unit";"Zergling";"Larva";599;1
"Unit";"Zergling";"Larva";599;1
"Unit";"Zergling";"Larva";599;1
"Unit";"Zergling";"Larva";599;1
"Unit";"Zergling";"Larva";599;1
"Unit";"Zergling";"Larva";599;1
"Unit";"Zergling";"Larva";599;1
"Unit";"Zergling";"Larva";599;1
"Unit";"Zergling";"Larva";599;1
"Unit";"Zergling";"Larva";599;1
"Unit";"Zergling";"Larva";599;1
"Unit";"Zergling";"Larva";599;1
"Building";"Hatchery";NA;581;0
"Building";"CreepTumorQueen";NA;629;0
"Building";"CreepTumorQueen";NA;633;0
"Building";"CreepTumorQueen";NA;635;0
"Building";"CreepTumor";NA;633;0
"Unit";"Baneling";"Zergling";635;0
"Unit";"Baneling";"Zergling";635;0
"Unit";"Baneling";"Zergling";635;0
"Unit";"Baneling";"Zergling";635;0
"Unit";"Baneling";"Zergling";635;0
"Unit";"Baneling";"Zergling";635;0
"Unit";"Baneling";"Zergling";635;0
"Unit";"Baneling";"Zergling";635;0
"Unit";"Baneling";"Zergling";635;0
"Unit";"Ultralisk";"Larva";599;6
"Unit";"Ultralisk";"Larva";599;6
"Building";"CreepTumorQueen";NA;647;0
"Building";"CreepTumor";NA;647;0
"Building";"CreepTumorQueen";NA;647;0
"Building";"CreepTumor";NA;647;0
"Building";"CreepTumor";NA;647;0
"Building";"CreepTumorQueen";NA;647;0
"Building";"CreepTumor";NA;647;0
"Unit";"Hydralisk";"Larva";635;2
"Unit";"Hydralisk";"Larva";635;2
"Unit";"Hydralisk";"Larva";635;2
"Unit";"Hydralisk";"Larva";635;2
"Unit";"Hydralisk";"Larva";635;2
"Unit";"Hydralisk";"Larva";635;2
"Unit";"Hydralisk";"Larva";635;2
"Unit";"Hydralisk";"Larva";635;2
"Building";"Extractor";NA;647;0
"Building";"Extractor";NA;647;0
"Upgrade";"ZergGroundArmorsLevel3";"EvolutionChamber";583;0
"Upgrade";"ZergMeleeWeaponsLevel3";"EvolutionChamber";583;0
"Unit";"Hydralisk";"Larva";670;2
"Unit";"Hydralisk";"Larva";670;2
"Unit";"Hydralisk";"Larva";670;2
"Unit";"Hydralisk";"Larva";670;2
"Unit";"Ultralisk";"Larva";663;6
"Upgrade";"EvolveMuscularAugments";"HydraliskDen";647;0
"Building";"SporeCrawler";NA;670;0
"Building";"SporeCrawler";NA;670;0
"Unit";"Hydralisk";"Larva";670;2
"Unit";"Hydralisk";"Larva";670;2
"Unit";"Hydralisk";"Larva";670;2
"Building";"SpineCrawler";NA;670;0
"Unit";"Baneling";"Zergling";690;0
"Unit";"Baneling";"Zergling";692;0
"Unit";"Baneling";"Zergling";694;0
"Unit";"Baneling";"Zergling";694;0
"Unit";"Ultralisk";"Larva";670;6
"Building";"CreepTumorQueen";NA;696;0
"Building";"CreepTumorQueen";NA;696;0
"Building";"CreepTumorQueen";NA;696;0
"Building";"CreepTumorQueen";NA;696;0
"Building";"CreepTumorQueen";NA;696;0
"Building";"Hatchery";NA;670;0
"Building";"CreepTumorQueen";NA;702;0
"Building";"CreepTumorQueen";NA;702;0
"Unit";"Corruptor";"Larva";702;2
"Building";"CreepTumorQueen";NA;704;0
"Building";"CreepTumorQueen";NA;704;0
"Building";"CreepTumor";NA;704;0
"Building";"CreepTumor";NA;704;0
"Building";"CreepTumor";NA;704;0
"Building";"CreepTumor";NA;704;0
"Building";"CreepTumor";NA;704;0
"Building";"CreepTumorQueen";NA;704;0
"Unit";"Corruptor";"Larva";704;2
"Unit";"Corruptor";"Larva";704;2
"Unit";"Corruptor";"Larva";704;2
"Unit";"Corruptor";"Larva";704;2
"Unit";"Corruptor";"Larva";704;2
"Unit";"Corruptor";"Larva";704;2
"Unit";"Corruptor";"Larva";704;2
"Unit";"Corruptor";"Larva";704;2
"Building";"CreepTumor";NA;704;0
"Building";"CreepTumor";NA;704;0
"Unit";"Overlord";"Larva";704;0
"Unit";"Overlord";"Larva";704;0
"Unit";"Overlord";"Larva";704;0
"Building";"CreepTumorQueen";NA;722;0
"Building";"CreepTumorQueen";NA;722;0
"Building";"CreepTumorQueen";NA;722;0
"Building";"CreepTumorQueen";NA;722;0
"Building";"CreepTumorQueen";NA;722;0
"Building";"CreepTumorQueen";NA;722;0
"Building";"CreepTumor";NA;722;0
"Building";"CreepTumor";NA;722;0
"Building";"CreepTumor";NA;722;0
"Building";"CreepTumor";NA;722;0
"Building";"Extractor";NA;722;0
"Building";"Extractor";NA;722;0
"Unit";"Corruptor";"Larva";728;2
"Unit";"Corruptor";"Larva";728;2
"Unit";"Corruptor";"Larva";728;2
"Unit";"Corruptor";"Larva";728;2
"Unit";"Corruptor";"Larva";728;2
"Unit";"Corruptor";"Larva";728;2
"Unit";"Corruptor";"Larva";728;2
"Unit";"Corruptor";"Larva";728;2
"Unit";"Corruptor";"Larva";728;2
"Unit";"Corruptor";"Larva";728;2
"Unit";"Corruptor";"Larva";728;2
"Unit";"Corruptor";"Larva";728;2
"Unit";"Corruptor";"Larva";728;2
"Unit";"Corruptor";"Larva";730;2
"Unit";"Corruptor";"Larva";736;2
"Upgrade";"ZergMissileWeaponsLevel1";"EvolutionChamber";728;0
"Building";"CreepTumorQueen";NA;758;0
"Building";"CreepTumorQueen";NA;758;0
"Building";"CreepTumorQueen";NA;758;0
"Unit";"Ultralisk";"Larva";758;6
"Unit";"Zergling";"Larva";764;1
"Unit";"Zergling";"Larva";764;1
"Unit";"Zergling";"Larva";764;1
"Unit";"Zergling";"Larva";764;1
"Unit";"Zergling";"Larva";764;1
"Unit";"Zergling";"Larva";764;1
"Unit";"Zergling";"Larva";764;1
"Unit";"Zergling";"Larva";764;1
"Unit";"Zergling";"Larva";764;1
"Unit";"Zergling";"Larva";764;1
"Unit";"Zergling";"Larva";764;1
"Unit";"Zergling";"Larva";764;1
"Unit";"Zergling";"Larva";764;1
"Unit";"Zergling";"Larva";764;1
