"type";"unit_name";"on_building";"total_supply";"supply"
"Unit";"Overlord";"Larva";12;0
"Building";"Extractor";NA;21;0
"Building";"Hatchery";NA;16;0
"Building";"SpawningPool";NA;19;0
"Unit";"Zergling";"Larva";23;1
"Unit";"Zergling";"Larva";23;1
"Unit";"Zergling";"Larva";23;1
"Unit";"Zergling";"Larva";23;1
"Unit";"Overlord";"Larva";23;0
"Unit";"Queen";"Hatchery";23;2
"Unit";"Queen";"Hatchery";23;2
"Building";"Hatchery";NA;21;0
"Unit";"Overlord";"Larva";41;0
"Unit";"Overlord";"Larva";41;0
"Unit";"Queen";"Hatchery";40;2
"Unit";"Overlord";"Larva";41;0
"Building";"CreepTumorQueen";NA;47;0
"Unit";"Queen";"Hatchery";42;2
"Unit";"Zergling";"Larva";49;1
"Unit";"Zergling";"Larva";49;1
"Unit";"Zergling";"Larva";49;1
"Unit";"Zergling";"Larva";49;1
"Unit";"Zergling";"Larva";49;1
"Unit";"Zergling";"Larva";49;1
"Building";"CreepTumor";NA;54;0
"Building";"CreepTumorQueen";NA;66;0
"Building";"CreepTumorQueen";NA;66;0
"Unit";"Queen";"Hatchery";49;2
"Building";"BanelingNest";NA;49;0
"Building";"CreepTumor";NA;71;0
"Unit";"Queen";"Hatchery";61;2
"Building";"CreepTumor";NA;72;0
"Building";"CreepTumorQueen";NA;72;0
"Unit";"Baneling";"Zergling";72;0
"Unit";"Baneling";"Zergling";72;0
"Unit";"Queen";"Hatchery";66;2
"Unit";"Baneling";"Zergling";72;0
"Unit";"Baneling";"Zergling";72;0
"Building";"CreepTumorQueen";NA;74;0
"Building";"CreepTumor";NA;74;0
"Unit";"Overlord";"Larva";72;0
"Unit";"Overlord";"Larva";72;0
"Unit";"Overlord";"Larva";72;0
"Unit";"Overlord";"Larva";72;0
"Building";"CreepTumorQueen";NA;74;0
"Unit";"Overlord";"Larva";74;0
"Building";"CreepTumor";NA;76;0
"Building";"CreepTumor";NA;76;0
"Building";"SporeCrawler";NA;76;0
"Unit";"Overlord";"Larva";76;0
"Building";"SporeCrawler";NA;76;0
"Building";"SporeCrawler";NA;76;0
"Unit";"Zergling";"Larva";80;1
"Unit";"Zergling";"Larva";80;1
"Unit";"Zergling";"Larva";81;1
"Unit";"Zergling";"Larva";81;1
"Unit";"Zergling";"Larva";81;1
"Unit";"Zergling";"Larva";81;1
"Building";"CreepTumor";NA;81;0
"Building";"CreepTumor";NA;81;0
"Building";"CreepTumor";NA;84;0
"Building";"CreepTumorQueen";NA;94;0
"Building";"Extractor";NA;81;0
"Building";"CreepTumorQueen";NA;94;0
"Building";"CreepTumorQueen";NA;94;0
"Unit";"Queen";"Hatchery";81;2
"Unit";"Queen";"Hatchery";81;2
"Building";"CreepTumorQueen";NA;94;0
"Building";"CreepTumor";NA;94;0
"Building";"Extractor";NA;94;0
"Building";"EvolutionChamber";NA;94;0
"Building";"EvolutionChamber";NA;94;0
"Building";"CreepTumorQueen";NA;108;0
"Building";"CreepTumor";NA;108;0
"Building";"Hatchery";NA;76;0
"Building";"CreepTumor";NA;108;0
"Building";"CreepTumor";NA;108;0
"Building";"CreepTumor";NA;108;0
"Unit";"Overlord";"Larva";108;0
"Building";"HydraliskDen";NA;102;0
"Building";"Extractor";NA;108;0
"Building";"CreepTumor";NA;117;0
"Building";"CreepTumor";NA;117;0
"Building";"CreepTumorQueen";NA;117;0
"Building";"CreepTumorQueen";NA;117;0
"Building";"Extractor";NA;117;0
"Building";"Extractor";NA;117;0
"Unit";"Zergling";"Larva";121;1
"Unit";"Zergling";"Larva";121;1
"Unit";"Zergling";"Larva";121;1
"Unit";"Zergling";"Larva";121;1
"Unit";"Zergling";"Larva";121;1
"Unit";"Zergling";"Larva";121;1
"Unit";"Zergling";"Larva";121;1
"Unit";"Zergling";"Larva";121;1
"Unit";"Zergling";"Larva";121;1
"Unit";"Zergling";"Larva";121;1
"Unit";"Zergling";"Larva";121;1
"Unit";"Zergling";"Larva";121;1
"Unit";"Zergling";"Larva";121;1
"Unit";"Zergling";"Larva";121;1
"Building";"CreepTumor";NA;141;0
"Building";"CreepTumor";NA;141;0
"Unit";"Overlord";"Larva";141;0
"Building";"CreepTumor";NA;144;0
"Building";"CreepTumor";NA;144;0
"Building";"CreepTumor";NA;144;0
"Building";"CreepTumor";NA;144;0
"Unit";"Zergling";"Larva";144;1
"Unit";"Zergling";"Larva";144;1
"Unit";"Overlord";"Larva";144;0
"Unit";"Zergling";"Larva";144;1
"Unit";"Zergling";"Larva";144;1
"Unit";"Zergling";"Larva";144;1
"Unit";"Zergling";"Larva";144;1
"Unit";"Zergling";"Larva";144;1
"Unit";"Zergling";"Larva";144;1
"Unit";"Zergling";"Larva";144;1
"Unit";"Zergling";"Larva";144;1
"Unit";"Zergling";"Larva";144;1
"Unit";"Zergling";"Larva";144;1
"Building";"Extractor";NA;141;0
"Unit";"Zergling";"Larva";144;1
"Unit";"Zergling";"Larva";144;1
"Unit";"Zergling";"Larva";144;1
"Unit";"Zergling";"Larva";144;1
"Building";"CreepTumor";NA;144;0
"Unit";"Zergling";"Larva";144;1
"Unit";"Zergling";"Larva";144;1
"Unit";"Zergling";"Larva";144;1
"Unit";"Zergling";"Larva";144;1
"Unit";"Zergling";"Larva";144;1
"Unit";"Zergling";"Larva";144;1
"Building";"CreepTumor";NA;144;0
"Building";"CreepTumor";NA;144;0
"Building";"CreepTumor";NA;144;0
"Building";"CreepTumorQueen";NA;144;0
"Building";"Hatchery";NA;108;0
"Building";"CreepTumorQueen";NA;144;0
"Building";"CreepTumorQueen";NA;144;0
"Unit";"Queen";"Hatchery";142;2
"Building";"CreepTumorQueen";NA;166;0
"Upgrade";"EvolveGroovedSpines";"HydraliskDen";127;0
"Unit";"Hydralisk";"Larva";166;2
"Unit";"Hydralisk";"Larva";166;2
"Unit";"Hydralisk";"Larva";166;2
"Building";"Extractor";NA;174;0
"Building";"CreepTumor";NA;180;0
"Building";"CreepTumor";NA;180;0
"Building";"CreepTumor";NA;180;0
"Building";"CreepTumor";NA;180;0
"Building";"CreepTumor";NA;180;0
"Building";"CreepTumor";NA;180;0
"Building";"CreepTumor";NA;180;0
"Building";"CreepTumor";NA;180;0
"Upgrade";"ZergGroundArmorsLevel1";"EvolutionChamber";127;0
"Unit";"Overlord";"Larva";180;0
"Unit";"Overlord";"Larva";180;0
"Unit";"Overlord";"Larva";180;0
"Unit";"Queen";"Hatchery";172;2
"Building";"SporeCrawler";NA;180;0
"Unit";"Hydralisk";"Larva";180;2
"Unit";"Hydralisk";"Larva";180;2
"Unit";"Hydralisk";"Larva";180;2
"Unit";"Hydralisk";"Larva";180;2
"Unit";"Hydralisk";"Larva";180;2
"Unit";"Hydralisk";"Larva";180;2
"Unit";"Hydralisk";"Larva";180;2
"Unit";"Hydralisk";"Larva";180;2
"Unit";"Hydralisk";"Larva";180;2
"Building";"CreepTumor";NA;180;0
"Building";"CreepTumor";NA;180;0
"Building";"SporeCrawler";NA;180;0
"Building";"CreepTumor";NA;180;0
"Building";"CreepTumor";NA;180;0
"Building";"CreepTumorQueen";NA;180;0
"Building";"CreepTumorQueen";NA;180;0
"Building";"CreepTumor";NA;180;0
"Building";"CreepTumor";NA;180;0
"Building";"InfestationPit";NA;180;0
"Unit";"Zergling";"Larva";182;1
"Unit";"Zergling";"Larva";182;1
"Unit";"Overlord";"Larva";180;0
"Unit";"Overlord";"Larva";180;0
"Unit";"Zergling";"Larva";182;1
"Unit";"Zergling";"Larva";182;1
"Unit";"Zergling";"Larva";182;1
"Unit";"Zergling";"Larva";182;1
"Unit";"Zergling";"Larva";182;1
"Unit";"Zergling";"Larva";182;1
"Unit";"Zergling";"Larva";182;1
"Unit";"Zergling";"Larva";182;1
"Unit";"Zergling";"Larva";182;1
"Unit";"Zergling";"Larva";182;1
"Unit";"Zergling";"Larva";182;1
"Unit";"Zergling";"Larva";182;1
"Unit";"Zergling";"Larva";182;1
"Unit";"Zergling";"Larva";182;1
"Unit";"Zergling";"Larva";182;1
"Unit";"Zergling";"Larva";182;1
"Unit";"Zergling";"Larva";182;1
"Unit";"Zergling";"Larva";182;1
"Unit";"Zergling";"Larva";182;1
"Unit";"Zergling";"Larva";182;1
"Unit";"Zergling";"Larva";182;1
"Unit";"Zergling";"Larva";182;1
"Unit";"Zergling";"Larva";182;1
"Unit";"Zergling";"Larva";182;1
"Unit";"Baneling";"Zergling";200;0
"Unit";"Baneling";"Zergling";200;0
"Unit";"Baneling";"Zergling";200;0
"Unit";"Baneling";"Zergling";200;0
"Unit";"Baneling";"Zergling";200;0
"Unit";"Baneling";"Zergling";200;0
"Unit";"Baneling";"Zergling";200;0
"Unit";"Baneling";"Zergling";200;0
"Unit";"Baneling";"Zergling";200;0
"Unit";"Baneling";"Zergling";200;0
"Unit";"Baneling";"Zergling";200;0
"Unit";"Baneling";"Zergling";200;0
"Unit";"Baneling";"Zergling";200;0
"Unit";"Baneling";"Zergling";200;0
"Building";"CreepTumor";NA;200;0
"Building";"CreepTumor";NA;200;0
"Building";"CreepTumor";NA;200;0
"Unit";"Zergling";"Larva";200;1
"Unit";"Zergling";"Larva";200;1
"Unit";"Zergling";"Larva";200;1
"Unit";"Zergling";"Larva";200;1
"Unit";"Baneling";"Zergling";226;0
"Unit";"Baneling";"Zergling";226;0
"Unit";"Baneling";"Zergling";226;0
"Unit";"Baneling";"Zergling";226;0
"Unit";"Baneling";"Zergling";226;0
"Unit";"Baneling";"Zergling";226;0
"Unit";"Baneling";"Zergling";226;0
"Upgrade";"ZergMeleeWeaponsLevel1";"EvolutionChamber";166;0
"Upgrade";"EvolveMuscularAugments";"HydraliskDen";180;0
"Building";"CreepTumorQueen";NA;230;0
"Building";"CreepTumorQueen";NA;230;0
"Unit";"Zergling";"Larva";230;1
"Unit";"Zergling";"Larva";230;1
"Unit";"Zergling";"Larva";230;1
"Unit";"Zergling";"Larva";230;1
"Unit";"Zergling";"Larva";230;1
"Unit";"Zergling";"Larva";230;1
"Unit";"Zergling";"Larva";230;1
"Unit";"Zergling";"Larva";230;1
"Unit";"Zergling";"Larva";230;1
"Unit";"Zergling";"Larva";230;1
"Unit";"Zergling";"Larva";230;1
"Unit";"Zergling";"Larva";230;1
"Unit";"Zergling";"Larva";230;1
"Unit";"Zergling";"Larva";230;1
"Unit";"Zergling";"Larva";230;1
"Unit";"Zergling";"Larva";230;1
"Unit";"Zergling";"Larva";230;1
"Unit";"Zergling";"Larva";230;1
"Unit";"Zergling";"Larva";230;1
"Unit";"Zergling";"Larva";230;1
"Unit";"Zergling";"Larva";230;1
"Unit";"Zergling";"Larva";230;1
"Unit";"Zergling";"Larva";230;1
"Unit";"Zergling";"Larva";230;1
"Unit";"Zergling";"Larva";230;1
"Unit";"Zergling";"Larva";230;1
"Unit";"Zergling";"Larva";230;1
"Unit";"Zergling";"Larva";230;1
"Unit";"Zergling";"Larva";230;1
"Unit";"Zergling";"Larva";230;1
"Unit";"Zergling";"Larva";230;1
"Unit";"Zergling";"Larva";230;1
"Unit";"Zergling";"Larva";230;1
"Unit";"Zergling";"Larva";230;1
"Unit";"Zergling";"Larva";230;1
"Unit";"Zergling";"Larva";230;1
"Unit";"Zergling";"Larva";230;1
"Unit";"Zergling";"Larva";230;1
"Unit";"Zergling";"Larva";230;1
"Unit";"Zergling";"Larva";230;1
"Unit";"Zergling";"Larva";230;1
"Unit";"Zergling";"Larva";230;1
"Unit";"Zergling";"Larva";230;1
"Unit";"Zergling";"Larva";230;1
"Unit";"Zergling";"Larva";230;1
"Unit";"Zergling";"Larva";230;1
"Unit";"Zergling";"Larva";230;1
"Unit";"Zergling";"Larva";230;1
"Building";"CreepTumor";NA;278;0
"Building";"CreepTumor";NA;278;0
"Building";"CreepTumor";NA;278;0
"Building";"CreepTumor";NA;278;0
"Building";"CreepTumor";NA;278;0
"Building";"CreepTumor";NA;285;0
"Building";"CreepTumorQueen";NA;285;0
"Unit";"Queen";"Hatchery";230;2
"Building";"CreepTumor";NA;285;0
"Building";"CreepTumor";NA;285;0
"Building";"CreepTumor";NA;285;0
"Building";"CreepTumor";NA;285;0
"Unit";"Zergling";"Larva";285;1
"Unit";"Zergling";"Larva";285;1
"Unit";"Zergling";"Larva";285;1
"Unit";"Zergling";"Larva";285;1
"Unit";"Zergling";"Larva";285;1
"Unit";"Zergling";"Larva";285;1
"Unit";"Zergling";"Larva";285;1
"Unit";"Zergling";"Larva";285;1
"Unit";"Zergling";"Larva";285;1
"Unit";"Zergling";"Larva";285;1
"Unit";"Zergling";"Larva";285;1
"Unit";"Zergling";"Larva";285;1
"Unit";"Zergling";"Larva";285;1
"Unit";"Zergling";"Larva";285;1
"Unit";"Zergling";"Larva";285;1
"Unit";"Zergling";"Larva";285;1
"Unit";"Zergling";"Larva";285;1
"Unit";"Zergling";"Larva";285;1
"Unit";"Zergling";"Larva";285;1
"Unit";"Zergling";"Larva";285;1
"Unit";"Zergling";"Larva";285;1
"Unit";"Zergling";"Larva";285;1
"Unit";"Zergling";"Larva";285;1
"Unit";"Zergling";"Larva";285;1
"Unit";"Zergling";"Larva";285;1
"Unit";"Zergling";"Larva";285;1
"Unit";"Zergling";"Larva";285;1
"Unit";"Zergling";"Larva";285;1
"Unit";"Zergling";"Larva";285;1
"Unit";"Zergling";"Larva";285;1
"Unit";"Zergling";"Larva";285;1
"Unit";"Zergling";"Larva";285;1
"Unit";"Zergling";"Larva";285;1
"Unit";"Zergling";"Larva";285;1
"Unit";"Zergling";"Larva";285;1
"Unit";"Zergling";"Larva";285;1
"Building";"CreepTumor";NA;287;0
"Building";"CreepTumor";NA;287;0
"Building";"CreepTumor";NA;287;0
"Building";"CreepTumor";NA;287;0
"Building";"CreepTumor";NA;287;0
"Building";"CreepTumor";NA;287;0
"Building";"SporeCrawler";NA;287;0
"Building";"CreepTumor";NA;323;0
"Building";"CreepTumor";NA;323;0
"Unit";"Zergling";"Larva";323;1
"Unit";"Zergling";"Larva";323;1
"Upgrade";"ZergGroundArmorsLevel2";"EvolutionChamber";230;0
"Unit";"Overlord";"Larva";323;0
"Unit";"Zergling";"Larva";323;1
"Unit";"Zergling";"Larva";323;1
"Unit";"Zergling";"Larva";323;1
"Unit";"Zergling";"Larva";323;1
"Unit";"Zergling";"Larva";323;1
"Unit";"Zergling";"Larva";323;1
"Unit";"Overlord";"Larva";323;0
"Unit";"Zergling";"Larva";323;1
"Unit";"Zergling";"Larva";323;1
"Unit";"Zergling";"Larva";323;1
"Unit";"Zergling";"Larva";323;1
"Unit";"Zergling";"Larva";323;1
"Unit";"Zergling";"Larva";323;1
"Unit";"Zergling";"Larva";323;1
"Unit";"Zergling";"Larva";323;1
"Unit";"Zergling";"Larva";323;1
"Unit";"Zergling";"Larva";323;1
"Unit";"Zergling";"Larva";323;1
"Unit";"Zergling";"Larva";323;1
"Unit";"Zergling";"Larva";323;1
"Unit";"Zergling";"Larva";323;1
"Unit";"Zergling";"Larva";323;1
"Unit";"Zergling";"Larva";323;1
"Unit";"Zergling";"Larva";323;1
"Unit";"Zergling";"Larva";323;1
"Unit";"Zergling";"Larva";323;1
"Unit";"Zergling";"Larva";323;1
"Unit";"Zergling";"Larva";323;1
"Unit";"Zergling";"Larva";323;1
"Unit";"Zergling";"Larva";323;1
"Unit";"Zergling";"Larva";323;1
"Unit";"Zergling";"Larva";323;1
"Unit";"Zergling";"Larva";323;1
"Unit";"Zergling";"Larva";323;1
"Unit";"Zergling";"Larva";323;1
"Unit";"Zergling";"Larva";323;1
"Unit";"Zergling";"Larva";323;1
"Unit";"Zergling";"Larva";323;1
"Unit";"Zergling";"Larva";323;1
"Unit";"Zergling";"Larva";323;1
"Unit";"Zergling";"Larva";323;1
"Building";"Spire";NA;278;0
"Unit";"Baneling";"Zergling";323;0
"Unit";"Baneling";"Zergling";323;0
"Unit";"Baneling";"Zergling";323;0
"Unit";"Baneling";"Zergling";323;0
"Unit";"Baneling";"Zergling";323;0
"Unit";"Baneling";"Zergling";323;0
"Unit";"Baneling";"Zergling";323;0
"Unit";"Baneling";"Zergling";323;0
"Unit";"Baneling";"Zergling";323;0
"Unit";"Baneling";"Zergling";323;0
"Unit";"Baneling";"Zergling";323;0
"Unit";"Baneling";"Zergling";323;0
"Unit";"Baneling";"Zergling";323;0
"Unit";"Baneling";"Zergling";323;0
"Unit";"Baneling";"Zergling";323;0
"Unit";"Baneling";"Zergling";323;0
"Unit";"Baneling";"Zergling";323;0
"Unit";"Baneling";"Zergling";323;0
"Building";"CreepTumor";NA;323;0
"Building";"CreepTumor";NA;323;0
"Building";"CreepTumor";NA;323;0
"Building";"CreepTumor";NA;323;0
"Building";"CreepTumor";NA;367;0
"Building";"CreepTumor";NA;367;0
"Building";"Hatchery";NA;285;0
"Building";"CreepTumor";NA;367;0
"Building";"CreepTumor";NA;367;0
"Unit";"Viper";"Larva";365;3
"Unit";"Viper";"Larva";365;3
"Unit";"Viper";"Larva";365;3
"Unit";"Viper";"Larva";365;3
"Unit";"Baneling";"Zergling";367;0
"Unit";"Baneling";"Zergling";367;0
"Unit";"Baneling";"Zergling";367;0
"Unit";"Baneling";"Zergling";367;0
"Unit";"Baneling";"Zergling";367;0
"Unit";"Baneling";"Zergling";367;0
"Unit";"Baneling";"Zergling";367;0
"Unit";"Baneling";"Zergling";367;0
"Unit";"Baneling";"Zergling";367;0
"Unit";"Baneling";"Zergling";367;0
"Upgrade";"ZergMeleeWeaponsLevel2";"EvolutionChamber";287;0
"Unit";"Corruptor";"Larva";379;2
"Unit";"Corruptor";"Larva";381;2
"Unit";"Corruptor";"Larva";381;2
"Unit";"Corruptor";"Larva";381;2
"Unit";"Corruptor";"Larva";381;2
"Unit";"Corruptor";"Larva";381;2
"Unit";"Corruptor";"Larva";381;2
"Unit";"Corruptor";"Larva";381;2
"Unit";"Corruptor";"Larva";381;2
"Unit";"Overlord";"Larva";381;0
"Unit";"Overlord";"Larva";381;0
"Unit";"Overlord";"Larva";381;0
"Unit";"Overlord";"Larva";381;0
"Unit";"Zergling";"Larva";397;1
"Unit";"Zergling";"Larva";397;1
"Unit";"Zergling";"Larva";397;1
"Unit";"Zergling";"Larva";397;1
"Unit";"Zergling";"Larva";397;1
"Unit";"Zergling";"Larva";397;1
"Unit";"Zergling";"Larva";397;1
"Unit";"Zergling";"Larva";397;1
"Unit";"Zergling";"Larva";397;1
"Unit";"Zergling";"Larva";397;1
"Unit";"Zergling";"Larva";397;1
"Unit";"Zergling";"Larva";397;1
"Unit";"Zergling";"Larva";397;1
"Unit";"Zergling";"Larva";397;1
"Unit";"Zergling";"Larva";397;1
"Unit";"Zergling";"Larva";397;1
"Unit";"Zergling";"Larva";397;1
"Unit";"Zergling";"Larva";397;1
"Unit";"Zergling";"Larva";397;1
"Unit";"Zergling";"Larva";397;1
"Unit";"Zergling";"Larva";397;1
"Unit";"Zergling";"Larva";397;1
"Unit";"Zergling";"Larva";397;1
"Unit";"Zergling";"Larva";397;1
"Unit";"Zergling";"Larva";397;1
"Unit";"Zergling";"Larva";397;1
"Unit";"Zergling";"Larva";397;1
"Unit";"Zergling";"Larva";397;1
"Unit";"Zergling";"Larva";397;1
"Unit";"Zergling";"Larva";397;1
"Unit";"Zergling";"Larva";397;1
"Unit";"Zergling";"Larva";397;1
"Unit";"Zergling";"Larva";397;1
"Unit";"Zergling";"Larva";397;1
"Unit";"Zergling";"Larva";397;1
"Unit";"Zergling";"Larva";397;1
"Building";"CreepTumorQueen";NA;433;0
"Unit";"Zergling";"Larva";433;1
"Unit";"Zergling";"Larva";433;1
"Unit";"Zergling";"Larva";433;1
"Unit";"Zergling";"Larva";433;1
"Unit";"Zergling";"Larva";433;1
"Unit";"Zergling";"Larva";433;1
"Unit";"Zergling";"Larva";433;1
"Unit";"Zergling";"Larva";433;1
"Unit";"Zergling";"Larva";433;1
"Unit";"Zergling";"Larva";433;1
"Unit";"Zergling";"Larva";433;1
"Unit";"Zergling";"Larva";433;1
"Unit";"Zergling";"Larva";433;1
"Unit";"Zergling";"Larva";433;1
"Unit";"Zergling";"Larva";433;1
"Unit";"Zergling";"Larva";433;1
"Unit";"Zergling";"Larva";433;1
"Unit";"Zergling";"Larva";433;1
"Unit";"Zergling";"Larva";433;1
"Unit";"Zergling";"Larva";433;1
"Unit";"Zergling";"Larva";433;1
"Unit";"Zergling";"Larva";433;1
"Unit";"Zergling";"Larva";433;1
"Unit";"Zergling";"Larva";433;1
"Unit";"Zergling";"Larva";433;1
"Unit";"Zergling";"Larva";433;1
"Unit";"Zergling";"Larva";433;1
"Unit";"Zergling";"Larva";433;1
"Unit";"Zergling";"Larva";433;1
"Unit";"Zergling";"Larva";433;1
"Unit";"Zergling";"Larva";433;1
"Unit";"Zergling";"Larva";433;1
"Unit";"Zergling";"Larva";433;1
"Unit";"Zergling";"Larva";433;1
"Unit";"Zergling";"Larva";433;1
"Unit";"Zergling";"Larva";433;1
"Unit";"Zergling";"Larva";433;1
"Unit";"Zergling";"Larva";433;1
"Unit";"Zergling";"Larva";433;1
"Unit";"Zergling";"Larva";433;1
"Unit";"Zergling";"Larva";433;1
"Unit";"Zergling";"Larva";433;1
"Unit";"Zergling";"Larva";433;1
"Unit";"Zergling";"Larva";433;1
"Unit";"Zergling";"Larva";433;1
"Unit";"Zergling";"Larva";433;1
"Upgrade";"ZergGroundArmorsLevel3";"EvolutionChamber";381;0
"Unit";"Corruptor";"Larva";433;2
"Unit";"Corruptor";"Larva";433;2
"Unit";"Corruptor";"Larva";433;2
"Unit";"Corruptor";"Larva";433;2
"Unit";"Corruptor";"Larva";433;2
"Unit";"Corruptor";"Larva";433;2
"Unit";"Corruptor";"Larva";433;2
"Unit";"Corruptor";"Larva";433;2
"Building";"CreepTumorQueen";NA;479;0
"Building";"CreepTumor";NA;495;0
"Building";"CreepTumor";NA;495;0
"Building";"CreepTumor";NA;495;0
"Building";"CreepTumor";NA;495;0
"Unit";"Queen";"Hatchery";433;2
"Unit";"Queen";"Hatchery";433;2
"Unit";"Corruptor";"Larva";433;2
"Building";"CreepTumorQueen";NA;495;0
"Unit";"Corruptor";"Larva";433;2
"Unit";"Corruptor";"Larva";433;2
"Building";"Extractor";NA;505;0
"Building";"Extractor";NA;505;0
"Building";"CreepTumor";NA;505;0
"Unit";"Baneling";"Zergling";505;0
"Unit";"Baneling";"Zergling";505;0
"Unit";"Baneling";"Zergling";505;0
"Unit";"Baneling";"Zergling";505;0
"Unit";"Baneling";"Zergling";505;0
"Unit";"Baneling";"Zergling";505;0
"Unit";"Baneling";"Zergling";505;0
"Unit";"Baneling";"Zergling";505;0
"Unit";"Baneling";"Zergling";505;0
"Unit";"Baneling";"Zergling";505;0
"Unit";"Baneling";"Zergling";505;0
"Unit";"Baneling";"Zergling";505;0
"Unit";"Baneling";"Zergling";505;0
"Unit";"Baneling";"Zergling";505;0
"Unit";"Baneling";"Zergling";505;0
"Unit";"Baneling";"Zergling";505;0
"Unit";"Baneling";"Zergling";505;0
"Unit";"Baneling";"Zergling";505;0
"Building";"CreepTumorQueen";NA;505;0
"Building";"CreepTumor";NA;505;0
"Building";"CreepTumor";NA;505;0
"Building";"CreepTumor";NA;505;0
"Building";"CreepTumorQueen";NA;505;0
"Building";"CreepTumorQueen";NA;505;0
"Building";"CreepTumorQueen";NA;505;0
"Building";"CreepTumor";NA;505;0
"Building";"CreepTumorQueen";NA;505;0
"Building";"CreepTumorQueen";NA;505;0
"Building";"CreepTumorQueen";NA;505;0
"Building";"CreepTumorQueen";NA;505;0
"Building";"CreepTumorQueen";NA;505;0
"Building";"Spire";NA;495;0
"Unit";"Zergling";"Larva";505;1
"Unit";"Zergling";"Larva";505;1
"Unit";"Zergling";"Larva";505;1
"Unit";"Zergling";"Larva";505;1
"Unit";"Zergling";"Larva";505;1
"Unit";"Zergling";"Larva";505;1
"Unit";"Zergling";"Larva";505;1
"Unit";"Zergling";"Larva";505;1
"Unit";"Zergling";"Larva";505;1
"Unit";"Zergling";"Larva";505;1
"Unit";"Zergling";"Larva";505;1
"Unit";"Zergling";"Larva";505;1
"Unit";"Zergling";"Larva";505;1
"Unit";"Zergling";"Larva";505;1
"Unit";"Zergling";"Larva";505;1
"Unit";"Zergling";"Larva";505;1
"Unit";"Zergling";"Larva";505;1
"Unit";"Zergling";"Larva";505;1
"Unit";"Zergling";"Larva";505;1
"Unit";"Zergling";"Larva";505;1
"Unit";"Zergling";"Larva";505;1
"Unit";"Zergling";"Larva";505;1
"Unit";"Zergling";"Larva";505;1
"Unit";"Zergling";"Larva";505;1
"Unit";"Zergling";"Larva";505;1
"Unit";"Zergling";"Larva";505;1
"Unit";"Zergling";"Larva";505;1
"Unit";"Zergling";"Larva";505;1
"Unit";"Zergling";"Larva";505;1
"Unit";"Zergling";"Larva";505;1
"Unit";"Zergling";"Larva";505;1
"Unit";"Zergling";"Larva";505;1
"Unit";"Zergling";"Larva";505;1
"Unit";"Zergling";"Larva";505;1
"Unit";"Zergling";"Larva";505;1
"Unit";"Zergling";"Larva";505;1
"Unit";"Zergling";"Larva";505;1
"Unit";"Zergling";"Larva";505;1
"Unit";"Zergling";"Larva";505;1
"Unit";"Zergling";"Larva";505;1
"Unit";"Zergling";"Larva";505;1
"Unit";"Zergling";"Larva";505;1
"Unit";"Zergling";"Larva";505;1
"Unit";"Zergling";"Larva";505;1
"Unit";"Zergling";"Larva";505;1
"Unit";"Zergling";"Larva";505;1
"Unit";"Zergling";"Larva";505;1
"Unit";"Zergling";"Larva";505;1
"Unit";"Zergling";"Larva";505;1
"Unit";"Zergling";"Larva";505;1
"Unit";"Zergling";"Larva";505;1
"Unit";"Zergling";"Larva";505;1
"Unit";"Zergling";"Larva";505;1
"Unit";"Zergling";"Larva";505;1
"Unit";"Zergling";"Larva";505;1
"Unit";"Zergling";"Larva";505;1
"Unit";"Zergling";"Larva";505;1
"Unit";"Zergling";"Larva";505;1
"Unit";"Zergling";"Larva";505;1
"Unit";"Zergling";"Larva";505;1
"Unit";"Zergling";"Larva";505;1
"Unit";"Zergling";"Larva";505;1
"Unit";"Zergling";"Larva";505;1
"Unit";"Zergling";"Larva";505;1
"Unit";"Zergling";"Larva";505;1
"Unit";"Zergling";"Larva";505;1
"Unit";"Zergling";"Larva";505;1
"Unit";"Zergling";"Larva";505;1
"Unit";"Zergling";"Larva";505;1
"Unit";"Zergling";"Larva";505;1
"Unit";"Zergling";"Larva";525;1
"Unit";"Zergling";"Larva";525;1
"Unit";"Zergling";"Larva";525;1
"Unit";"Zergling";"Larva";525;1
"Unit";"Zergling";"Larva";525;1
"Unit";"Zergling";"Larva";525;1
"Unit";"Zergling";"Larva";525;1
"Unit";"Zergling";"Larva";525;1
"Unit";"Zergling";"Larva";525;1
"Unit";"Zergling";"Larva";525;1
"Unit";"Zergling";"Larva";525;1
"Unit";"Zergling";"Larva";525;1
"Unit";"Zergling";"Larva";525;1
"Unit";"Zergling";"Larva";525;1
"Unit";"Zergling";"Larva";525;1
"Unit";"Zergling";"Larva";525;1
"Unit";"Zergling";"Larva";525;1
"Unit";"Zergling";"Larva";525;1
"Unit";"Zergling";"Larva";525;1
"Unit";"Zergling";"Larva";525;1
"Unit";"Zergling";"Larva";525;1
"Unit";"Zergling";"Larva";525;1
"Unit";"Zergling";"Larva";525;1
"Unit";"Zergling";"Larva";525;1
"Unit";"Zergling";"Larva";525;1
"Unit";"Zergling";"Larva";525;1
"Unit";"Baneling";"Zergling";575;0
"Unit";"Baneling";"Zergling";575;0
"Unit";"Baneling";"Zergling";575;0
"Unit";"Baneling";"Zergling";575;0
"Unit";"Baneling";"Zergling";575;0
"Unit";"Baneling";"Zergling";575;0
"Unit";"Baneling";"Zergling";575;0
"Unit";"Baneling";"Zergling";575;0
"Building";"CreepTumor";NA;601;0
"Building";"CreepTumor";NA;601;0
"Building";"CreepTumor";NA;601;0
"Upgrade";"ZergMissileWeaponsLevel1";"EvolutionChamber";505;0
"Building";"CreepTumor";NA;601;0
"Building";"CreepTumor";NA;601;0
"Building";"CreepTumor";NA;601;0
"Building";"CreepTumorQueen";NA;601;0
"Building";"CreepTumorQueen";NA;601;0
"Building";"CreepTumorQueen";NA;601;0
"Building";"CreepTumor";NA;601;0
"Building";"CreepTumor";NA;601;0
"Building";"CreepTumor";NA;601;0
"Building";"CreepTumor";NA;601;0
"Building";"CreepTumor";NA;601;0
"Building";"CreepTumor";NA;601;0
"Building";"CreepTumor";NA;601;0
"Upgrade";"ZergMeleeWeaponsLevel3";"EvolutionChamber";505;0
"Building";"CreepTumorQueen";NA;601;0
"Building";"CreepTumorQueen";NA;601;0
"Unit";"Baneling";"Zergling";601;0
"Unit";"Baneling";"Zergling";601;0
"Unit";"Baneling";"Zergling";601;0
"Unit";"Baneling";"Zergling";601;0
"Unit";"Baneling";"Zergling";601;0
"Unit";"Baneling";"Zergling";601;0
"Unit";"Baneling";"Zergling";601;0
"Unit";"Baneling";"Zergling";601;0
"Unit";"Baneling";"Zergling";601;0
"Unit";"Baneling";"Zergling";601;0
"Unit";"Baneling";"Zergling";601;0
"Unit";"Baneling";"Zergling";601;0
"Unit";"Baneling";"Zergling";601;0
"Unit";"Baneling";"Zergling";601;0
"Unit";"Baneling";"Zergling";601;0
"Unit";"Baneling";"Zergling";601;0
