"type";"unit_name";"on_building";"total_supply";"supply"
"Unit";"Overlord";"Larva";12;0
"Building";"Extractor";NA;18;0
"Building";"SpawningPool";NA;18;0
"Unit";"Overlord";"Larva";21;0
"Building";"Hatchery";NA;17;0
"Unit";"Zergling";"Larva";23;1
"Unit";"Zergling";"Larva";23;1
"Unit";"Zergling";"Larva";23;1
"Unit";"Zergling";"Larva";23;1
"Unit";"Queen";"Hatchery";22;2
"Unit";"Queen";"Hatchery";23;2
"Unit";"Zergling";"Larva";36;1
"Unit";"Zergling";"Larva";36;1
"Unit";"Overlord";"Larva";36;0
"Unit";"Overlord";"Larva";38;0
"Building";"CreepTumorQueen";NA;40;0
"Unit";"Queen";"Hatchery";36;2
"Unit";"Overlord";"Larva";40;0
"Building";"CreepTumor";NA;47;0
"Building";"Hatchery";NA;35;0
"Unit";"Overlord";"Larva";51;0
"Unit";"Queen";"Hatchery";47;2
"Building";"Extractor";NA;51;0
"Building";"EvolutionChamber";NA;55;0
"Building";"CreepTumor";NA;58;0
"Building";"CreepTumorQueen";NA;62;0
"Unit";"Overlord";"Larva";62;0
"Unit";"Zergling";"Larva";64;1
"Unit";"Zergling";"Larva";64;1
"Unit";"Zergling";"Larva";64;1
"Unit";"Zergling";"Larva";64;1
"Building";"EvolutionChamber";NA;64;0
"Building";"BanelingNest";NA;55;0
"Unit";"Zergling";"Larva";66;1
"Unit";"Zergling";"Larva";66;1
"Building";"CreepTumor";NA;70;0
"Unit";"Zergling";"Larva";68;1
"Unit";"Zergling";"Larva";68;1
"Unit";"Zergling";"Larva";68;1
"Unit";"Zergling";"Larva";68;1
"Unit";"Zergling";"Larva";68;1
"Unit";"Zergling";"Larva";68;1
"Unit";"Zergling";"Larva";68;1
"Unit";"Zergling";"Larva";68;1
"Building";"CreepTumorQueen";NA;72;0
"Unit";"Overlord";"Larva";70;0
"Unit";"Overlord";"Larva";72;0
"Unit";"Zergling";"Larva";82;1
"Unit";"Zergling";"Larva";82;1
"Unit";"Overlord";"Larva";82;0
"Unit";"Overlord";"Larva";82;0
"Unit";"Baneling";"Zergling";82;0
"Unit";"Baneling";"Zergling";82;0
"Unit";"Baneling";"Zergling";82;0
"Unit";"Baneling";"Zergling";82;0
"Unit";"Overlord";"Larva";82;0
"Unit";"Overlord";"Larva";82;0
"Unit";"Zergling";"Larva";83;1
"Unit";"Zergling";"Larva";83;1
"Building";"CreepTumor";NA;83;0
"Unit";"Zergling";"Larva";83;1
"Unit";"Zergling";"Larva";83;1
"Unit";"Zergling";"Larva";83;1
"Unit";"Zergling";"Larva";83;1
"Unit";"Zergling";"Larva";83;1
"Unit";"Zergling";"Larva";83;1
"Unit";"Zergling";"Larva";83;1
"Unit";"Zergling";"Larva";83;1
"Unit";"Zergling";"Larva";85;1
"Unit";"Zergling";"Larva";85;1
"Unit";"Zergling";"Larva";85;1
"Unit";"Zergling";"Larva";85;1
"Unit";"Zergling";"Larva";85;1
"Unit";"Zergling";"Larva";85;1
"Unit";"Zergling";"Larva";85;1
"Unit";"Zergling";"Larva";85;1
"Building";"CreepTumorQueen";NA;96;0
"Unit";"Zergling";"Larva";104;1
"Unit";"Zergling";"Larva";104;1
"Unit";"Zergling";"Larva";104;1
"Unit";"Zergling";"Larva";104;1
"Unit";"Zergling";"Larva";104;1
"Unit";"Zergling";"Larva";104;1
"Unit";"Zergling";"Larva";104;1
"Unit";"Zergling";"Larva";104;1
"Unit";"Zergling";"Larva";104;1
"Unit";"Zergling";"Larva";104;1
"Unit";"Zergling";"Larva";104;1
"Unit";"Zergling";"Larva";104;1
"Unit";"Zergling";"Larva";104;1
"Unit";"Zergling";"Larva";104;1
"Unit";"Zergling";"Larva";104;1
"Unit";"Zergling";"Larva";104;1
"Unit";"Zergling";"Larva";104;1
"Unit";"Zergling";"Larva";104;1
"Unit";"Zergling";"Larva";104;1
"Unit";"Zergling";"Larva";104;1
"Unit";"Zergling";"Larva";104;1
"Unit";"Zergling";"Larva";104;1
"Unit";"Zergling";"Larva";104;1
"Unit";"Zergling";"Larva";104;1
"Unit";"Zergling";"Larva";104;1
"Unit";"Zergling";"Larva";104;1
"Unit";"Zergling";"Larva";104;1
"Unit";"Zergling";"Larva";104;1
"Unit";"Zergling";"Larva";104;1
"Unit";"Zergling";"Larva";104;1
"Building";"CreepTumorQueen";NA;104;0
"Building";"CreepTumor";NA;104;0
"Unit";"Zergling";"Larva";104;1
"Unit";"Zergling";"Larva";104;1
"Unit";"Zergling";"Larva";104;1
"Unit";"Zergling";"Larva";104;1
"Unit";"Zergling";"Larva";104;1
"Unit";"Zergling";"Larva";104;1
"Unit";"Zergling";"Larva";104;1
"Unit";"Zergling";"Larva";104;1
"Unit";"Baneling";"Zergling";104;0
"Unit";"Baneling";"Zergling";104;0
"Unit";"Baneling";"Zergling";104;0
"Unit";"Baneling";"Zergling";104;0
"Unit";"Baneling";"Zergling";104;0
"Unit";"Baneling";"Zergling";104;0
"Unit";"Baneling";"Zergling";104;0
"Unit";"Baneling";"Zergling";104;0
"Unit";"Baneling";"Zergling";104;0
"Unit";"Baneling";"Zergling";104;0
"Unit";"Baneling";"Zergling";104;0
"Unit";"Zergling";"Larva";104;1
"Unit";"Zergling";"Larva";104;1
"Unit";"Zergling";"Larva";104;1
"Unit";"Zergling";"Larva";104;1
"Building";"CreepTumor";NA;134;0
"Upgrade";"ZergGroundArmorsLevel1";"EvolutionChamber";82;0
"Unit";"Zergling";"Larva";134;1
"Unit";"Zergling";"Larva";134;1
"Unit";"Zergling";"Larva";134;1
"Unit";"Zergling";"Larva";134;1
"Building";"CreepTumor";NA;142;0
"Unit";"Overlord";"Larva";142;0
"Upgrade";"ZergMeleeWeaponsLevel1";"EvolutionChamber";88;0
"Unit";"Zergling";"Larva";150;1
"Unit";"Zergling";"Larva";150;1
"Unit";"Zergling";"Larva";150;1
"Unit";"Zergling";"Larva";150;1
"Unit";"Zergling";"Larva";150;1
"Unit";"Zergling";"Larva";150;1
"Unit";"Zergling";"Larva";150;1
"Unit";"Zergling";"Larva";150;1
"Unit";"Zergling";"Larva";150;1
"Unit";"Zergling";"Larva";150;1
"Unit";"Zergling";"Larva";150;1
"Unit";"Zergling";"Larva";150;1
"Unit";"Zergling";"Larva";150;1
"Unit";"Zergling";"Larva";150;1
"Unit";"Zergling";"Larva";150;1
"Unit";"Zergling";"Larva";150;1
"Unit";"Zergling";"Larva";150;1
"Unit";"Zergling";"Larva";150;1
"Unit";"Zergling";"Larva";150;1
"Unit";"Zergling";"Larva";150;1
"Unit";"Zergling";"Larva";150;1
"Unit";"Zergling";"Larva";150;1
"Unit";"Zergling";"Larva";150;1
"Unit";"Zergling";"Larva";150;1
"Building";"CreepTumor";NA;150;0
"Building";"CreepTumor";NA;150;0
"Unit";"Baneling";"Zergling";150;0
"Unit";"Baneling";"Zergling";150;0
"Unit";"Baneling";"Zergling";150;0
"Unit";"Baneling";"Zergling";150;0
"Unit";"Baneling";"Zergling";150;0
"Unit";"Baneling";"Zergling";150;0
"Building";"Extractor";NA;150;0
"Building";"Hatchery";NA;134;0
"Unit";"Overlord";"Larva";177;0
"Unit";"Overlord";"Larva";177;0
"Unit";"Baneling";"Zergling";177;0
"Unit";"Baneling";"Zergling";177;0
"Unit";"Baneling";"Zergling";177;0
"Building";"CreepTumor";NA;177;0
"Unit";"Zergling";"Larva";177;1
"Unit";"Zergling";"Larva";177;1
"Unit";"Baneling";"Zergling";178;0
"Unit";"Baneling";"Zergling";178;0
"Unit";"Baneling";"Zergling";178;0
"Unit";"Zergling";"Larva";177;1
"Unit";"Zergling";"Larva";177;1
"Unit";"Zergling";"Larva";177;1
"Unit";"Zergling";"Larva";177;1
"Unit";"Zergling";"Larva";177;1
"Unit";"Zergling";"Larva";177;1
"Unit";"Zergling";"Larva";177;1
"Unit";"Zergling";"Larva";177;1
"Unit";"Zergling";"Larva";177;1
"Unit";"Zergling";"Larva";177;1
"Unit";"Zergling";"Larva";177;1
"Unit";"Zergling";"Larva";177;1
"Unit";"Zergling";"Larva";178;1
"Unit";"Zergling";"Larva";178;1
"Unit";"Baneling";"Zergling";180;0
"Unit";"Baneling";"Zergling";181;0
"Unit";"Baneling";"Zergling";182;0
"Unit";"Baneling";"Zergling";182;0
"Unit";"Baneling";"Zergling";182;0
"Building";"Extractor";NA;178;0
"Building";"CreepTumor";NA;196;0
"Building";"Extractor";NA;196;0
"Building";"Extractor";NA;196;0
"Building";"Hatchery";NA;177;0
"Building";"CreepTumor";NA;218;0
"Unit";"Zergling";"Larva";207;1
"Unit";"Zergling";"Larva";207;1
"Unit";"Zergling";"Larva";209;1
"Unit";"Zergling";"Larva";209;1
"Unit";"Zergling";"Larva";214;1
"Unit";"Zergling";"Larva";214;1
"Unit";"Zergling";"Larva";217;1
"Unit";"Zergling";"Larva";217;1
"Building";"CreepTumor";NA;218;0
"Unit";"Overlord";"Larva";226;0
"Unit";"Overlord";"Larva";226;0
"Building";"Extractor";NA;226;0
"Building";"Extractor";NA;226;0
"Building";"CreepTumor";NA;230;0
"Unit";"Baneling";"Zergling";230;0
"Unit";"Baneling";"Zergling";230;0
"Unit";"Baneling";"Zergling";230;0
"Unit";"Baneling";"Zergling";230;0
"Unit";"Baneling";"Zergling";230;0
"Unit";"Zergling";"Larva";230;1
"Unit";"Zergling";"Larva";230;1
"Unit";"Zergling";"Larva";230;1
"Unit";"Zergling";"Larva";230;1
"Unit";"Zergling";"Larva";230;1
"Unit";"Zergling";"Larva";230;1
"Unit";"Zergling";"Larva";230;1
"Unit";"Zergling";"Larva";230;1
"Building";"Spire";NA;196;0
"Unit";"Zergling";"Larva";241;1
"Unit";"Zergling";"Larva";241;1
"Unit";"Zergling";"Larva";241;1
"Unit";"Zergling";"Larva";241;1
"Unit";"Zergling";"Larva";241;1
"Unit";"Zergling";"Larva";241;1
"Unit";"Zergling";"Larva";241;1
"Unit";"Zergling";"Larva";241;1
"Unit";"Zergling";"Larva";241;1
"Unit";"Zergling";"Larva";241;1
"Unit";"Zergling";"Larva";241;1
"Unit";"Zergling";"Larva";241;1
"Unit";"Zergling";"Larva";241;1
"Unit";"Zergling";"Larva";241;1
"Unit";"Zergling";"Larva";241;1
"Unit";"Zergling";"Larva";241;1
"Unit";"Zergling";"Larva";241;1
"Unit";"Zergling";"Larva";241;1
"Unit";"Zergling";"Larva";241;1
"Unit";"Zergling";"Larva";241;1
"Unit";"Zergling";"Larva";241;1
"Unit";"Zergling";"Larva";241;1
"Unit";"Zergling";"Larva";241;1
"Unit";"Zergling";"Larva";241;1
"Unit";"Zergling";"Larva";249;1
"Unit";"Zergling";"Larva";249;1
"Unit";"Zergling";"Larva";249;1
"Unit";"Zergling";"Larva";249;1
"Unit";"Zergling";"Larva";249;1
"Unit";"Zergling";"Larva";249;1
"Unit";"Zergling";"Larva";249;1
"Unit";"Zergling";"Larva";249;1
"Unit";"Zergling";"Larva";249;1
"Unit";"Zergling";"Larva";249;1
"Unit";"Zergling";"Larva";249;1
"Unit";"Zergling";"Larva";249;1
"Unit";"Baneling";"Zergling";273;0
"Unit";"Baneling";"Zergling";273;0
"Unit";"Baneling";"Zergling";273;0
"Unit";"Baneling";"Zergling";273;0
"Unit";"Baneling";"Zergling";273;0
"Unit";"Zergling";"Larva";273;1
"Unit";"Zergling";"Larva";273;1
"Unit";"Zergling";"Larva";273;1
"Unit";"Zergling";"Larva";273;1
"Unit";"Zergling";"Larva";273;1
"Unit";"Zergling";"Larva";273;1
"Unit";"Zergling";"Larva";273;1
"Unit";"Zergling";"Larva";273;1
"Unit";"Zergling";"Larva";273;1
"Unit";"Zergling";"Larva";273;1
"Unit";"Zergling";"Larva";273;1
"Unit";"Zergling";"Larva";273;1
"Unit";"Baneling";"Zergling";285;0
"Unit";"Baneling";"Zergling";285;0
"Unit";"Baneling";"Zergling";285;0
"Unit";"Zergling";"Larva";285;1
"Unit";"Zergling";"Larva";285;1
"Unit";"Zergling";"Larva";285;1
"Unit";"Zergling";"Larva";285;1
"Unit";"Zergling";"Larva";285;1
"Unit";"Zergling";"Larva";285;1
"Unit";"Zergling";"Larva";285;1
"Unit";"Zergling";"Larva";285;1
"Unit";"Zergling";"Larva";285;1
"Unit";"Zergling";"Larva";285;1
"Unit";"Zergling";"Larva";285;1
"Unit";"Zergling";"Larva";285;1
"Building";"Hatchery";NA;236;0
"Unit";"Zergling";"Larva";298;1
"Unit";"Zergling";"Larva";298;1
"Unit";"Zergling";"Larva";298;1
"Unit";"Zergling";"Larva";298;1
"Unit";"Zergling";"Larva";298;1
"Unit";"Zergling";"Larva";298;1
"Unit";"Zergling";"Larva";298;1
"Unit";"Zergling";"Larva";298;1
"Unit";"Zergling";"Larva";298;1
"Unit";"Zergling";"Larva";298;1
"Unit";"Zergling";"Larva";298;1
"Unit";"Zergling";"Larva";298;1
"Unit";"Zergling";"Larva";298;1
"Unit";"Zergling";"Larva";298;1
"Unit";"Zergling";"Larva";298;1
"Unit";"Zergling";"Larva";298;1
"Unit";"Zergling";"Larva";298;1
"Unit";"Zergling";"Larva";298;1
"Unit";"Zergling";"Larva";298;1
"Unit";"Zergling";"Larva";298;1
"Unit";"Zergling";"Larva";298;1
"Unit";"Zergling";"Larva";298;1
"Unit";"Zergling";"Larva";298;1
"Unit";"Zergling";"Larva";298;1
"Unit";"Zergling";"Larva";298;1
"Unit";"Zergling";"Larva";298;1
"Unit";"Zergling";"Larva";298;1
"Unit";"Zergling";"Larva";298;1
"Unit";"Zergling";"Larva";298;1
"Unit";"Zergling";"Larva";298;1
"Unit";"Zergling";"Larva";298;1
"Unit";"Zergling";"Larva";298;1
"Unit";"Zergling";"Larva";298;1
"Unit";"Zergling";"Larva";298;1
"Unit";"Mutalisk";"Larva";298;2
"Unit";"Overlord";"Larva";310;0
"Unit";"Overlord";"Larva";310;0
"Building";"CreepTumor";NA;338;0
"Unit";"Mutalisk";"Larva";310;2
"Unit";"Mutalisk";"Larva";310;2
"Unit";"Mutalisk";"Larva";310;2
"Unit";"Mutalisk";"Larva";310;2
"Unit";"Mutalisk";"Larva";310;2
"Unit";"Mutalisk";"Larva";310;2
"Unit";"Mutalisk";"Larva";312;2
"Unit";"Mutalisk";"Larva";312;2
"Unit";"Mutalisk";"Larva";324;2
"Unit";"Mutalisk";"Larva";344;2
"Upgrade";"ZergGroundArmorsLevel2";"EvolutionChamber";241;0
"Unit";"Zergling";"Larva";364;1
"Unit";"Zergling";"Larva";364;1
"Unit";"Zergling";"Larva";364;1
"Unit";"Zergling";"Larva";364;1
"Unit";"Zergling";"Larva";364;1
"Unit";"Zergling";"Larva";364;1
"Unit";"Zergling";"Larva";364;1
"Unit";"Zergling";"Larva";364;1
"Unit";"Zergling";"Larva";364;1
"Unit";"Zergling";"Larva";364;1
"Unit";"Zergling";"Larva";364;1
"Unit";"Zergling";"Larva";364;1
"Unit";"Zergling";"Larva";364;1
"Unit";"Zergling";"Larva";364;1
"Unit";"Zergling";"Larva";364;1
"Unit";"Zergling";"Larva";364;1
"Unit";"Zergling";"Larva";364;1
"Unit";"Zergling";"Larva";364;1
"Unit";"Zergling";"Larva";364;1
"Unit";"Zergling";"Larva";364;1
"Unit";"Mutalisk";"Larva";356;2
"Unit";"Mutalisk";"Larva";356;2
"Unit";"Mutalisk";"Larva";356;2
"Unit";"Mutalisk";"Larva";356;2
"Unit";"Mutalisk";"Larva";356;2
"Unit";"Mutalisk";"Larva";364;2
"Unit";"Mutalisk";"Larva";364;2
"Upgrade";"ZergMeleeWeaponsLevel2";"EvolutionChamber";273;0
"Unit";"Zergling";"Larva";366;1
"Unit";"Zergling";"Larva";366;1
"Unit";"Zergling";"Larva";366;1
"Unit";"Zergling";"Larva";366;1
"Unit";"Zergling";"Larva";366;1
"Unit";"Zergling";"Larva";366;1
"Unit";"Zergling";"Larva";366;1
"Unit";"Zergling";"Larva";366;1
"Unit";"Zergling";"Larva";366;1
"Unit";"Zergling";"Larva";366;1
"Unit";"Zergling";"Larva";366;1
"Unit";"Zergling";"Larva";366;1
"Unit";"Zergling";"Larva";366;1
"Unit";"Zergling";"Larva";366;1
"Unit";"Zergling";"Larva";366;1
"Unit";"Zergling";"Larva";366;1
"Unit";"Zergling";"Larva";366;1
"Unit";"Zergling";"Larva";366;1
"Unit";"Zergling";"Larva";366;1
"Unit";"Zergling";"Larva";366;1
"Unit";"Zergling";"Larva";366;1
"Unit";"Zergling";"Larva";366;1
"Unit";"Baneling";"Zergling";400;0
"Unit";"Baneling";"Zergling";400;0
"Unit";"Baneling";"Zergling";400;0
"Unit";"Baneling";"Zergling";400;0
"Unit";"Baneling";"Zergling";400;0
"Unit";"Baneling";"Zergling";400;0
"Unit";"Baneling";"Zergling";400;0
"Unit";"Baneling";"Zergling";400;0
"Unit";"Baneling";"Zergling";400;0
"Unit";"Baneling";"Zergling";400;0
"Unit";"Baneling";"Zergling";400;0
"Unit";"Baneling";"Zergling";400;0
"Unit";"Baneling";"Zergling";400;0
"Unit";"Baneling";"Zergling";400;0
"Unit";"Baneling";"Zergling";400;0
"Unit";"Baneling";"Zergling";400;0
"Unit";"Baneling";"Zergling";400;0
"Unit";"Baneling";"Zergling";400;0
"Unit";"Baneling";"Zergling";400;0
"Unit";"Baneling";"Zergling";400;0
"Building";"CreepTumor";NA;422;0
"Building";"Extractor";NA;422;0
"Building";"Extractor";NA;422;0
"Unit";"Zergling";"Larva";425;1
"Unit";"Zergling";"Larva";425;1
"Unit";"Zergling";"Larva";426;1
"Unit";"Zergling";"Larva";426;1
"Unit";"Zergling";"Larva";426;1
"Unit";"Zergling";"Larva";426;1
"Unit";"Zergling";"Larva";426;1
"Unit";"Zergling";"Larva";426;1
"Unit";"Zergling";"Larva";426;1
"Unit";"Zergling";"Larva";426;1
"Unit";"Zergling";"Larva";426;1
"Unit";"Zergling";"Larva";426;1
"Unit";"Zergling";"Larva";426;1
"Unit";"Zergling";"Larva";426;1
"Unit";"Zergling";"Larva";426;1
"Unit";"Zergling";"Larva";426;1
"Unit";"Zergling";"Larva";426;1
"Unit";"Zergling";"Larva";426;1
"Unit";"Baneling";"Zergling";427;0
"Unit";"Baneling";"Zergling";427;0
"Unit";"Baneling";"Zergling";427;0
"Unit";"Baneling";"Zergling";427;0
"Unit";"Overlord";"Larva";427;0
"Unit";"Overlord";"Larva";427;0
"Unit";"Zergling";"Larva";430;1
"Unit";"Zergling";"Larva";430;1
"Unit";"Baneling";"Zergling";430;0
"Unit";"Baneling";"Zergling";430;0
"Unit";"Zergling";"Larva";430;1
"Unit";"Zergling";"Larva";430;1
"Unit";"Zergling";"Larva";430;1
"Unit";"Zergling";"Larva";430;1
"Unit";"Zergling";"Larva";430;1
"Unit";"Zergling";"Larva";430;1
"Unit";"Zergling";"Larva";430;1
"Unit";"Zergling";"Larva";430;1
"Unit";"Zergling";"Larva";430;1
"Unit";"Zergling";"Larva";430;1
"Unit";"Baneling";"Zergling";430;0
"Unit";"Baneling";"Zergling";430;0
"Unit";"Zergling";"Larva";430;1
"Unit";"Zergling";"Larva";430;1
"Unit";"Zergling";"Larva";448;1
"Unit";"Zergling";"Larva";448;1
"Unit";"Zergling";"Larva";448;1
"Unit";"Zergling";"Larva";448;1
"Unit";"Zergling";"Larva";448;1
"Unit";"Zergling";"Larva";448;1
"Unit";"Zergling";"Larva";448;1
"Unit";"Zergling";"Larva";448;1
"Unit";"Zergling";"Larva";448;1
"Unit";"Zergling";"Larva";448;1
"Unit";"Zergling";"Larva";448;1
"Unit";"Zergling";"Larva";448;1
"Unit";"Zergling";"Larva";448;1
"Unit";"Zergling";"Larva";448;1
"Unit";"Zergling";"Larva";448;1
"Unit";"Zergling";"Larva";448;1
"Unit";"Zergling";"Larva";448;1
"Unit";"Zergling";"Larva";448;1
"Unit";"Zergling";"Larva";448;1
"Unit";"Zergling";"Larva";448;1
"Building";"Extractor";NA;448;0
"Building";"Extractor";NA;448;0
"Unit";"Mutalisk";"Larva";448;2
"Unit";"Mutalisk";"Larva";462;2
"Unit";"Mutalisk";"Larva";462;2
"Unit";"Mutalisk";"Larva";462;2
"Unit";"Mutalisk";"Larva";462;2
"Unit";"Mutalisk";"Larva";462;2
"Unit";"Baneling";"Zergling";484;0
"Unit";"Baneling";"Zergling";484;0
"Unit";"Baneling";"Zergling";484;0
"Unit";"Baneling";"Zergling";484;0
"Unit";"Baneling";"Zergling";484;0
"Unit";"Baneling";"Zergling";484;0
"Unit";"Baneling";"Zergling";484;0
"Unit";"Baneling";"Zergling";484;0
"Unit";"Baneling";"Zergling";484;0
"Unit";"Zergling";"Larva";484;1
"Unit";"Zergling";"Larva";484;1
"Unit";"Zergling";"Larva";484;1
"Unit";"Zergling";"Larva";484;1
"Unit";"Zergling";"Larva";484;1
"Unit";"Zergling";"Larva";484;1
"Unit";"Overlord";"Larva";489;0
"Unit";"Overlord";"Larva";490;0
"Building";"InfestationPit";NA;484;0
"Building";"CreepTumorQueen";NA;506;0
"Building";"Hatchery";NA;448;0
"Building";"CreepTumorQueen";NA;506;0
"Unit";"Overlord";"Larva";506;0
"Unit";"Overlord";"Larva";506;0
"Unit";"Overlord";"Larva";506;0
"Unit";"Zergling";"Larva";509;1
"Unit";"Zergling";"Larva";509;1
"Unit";"Zergling";"Larva";509;1
"Unit";"Zergling";"Larva";509;1
"Unit";"Zergling";"Larva";509;1
"Unit";"Zergling";"Larva";509;1
"Unit";"Zergling";"Larva";509;1
"Unit";"Zergling";"Larva";509;1
"Unit";"Zergling";"Larva";509;1
"Unit";"Zergling";"Larva";509;1
"Unit";"Zergling";"Larva";509;1
"Unit";"Zergling";"Larva";509;1
"Unit";"Zergling";"Larva";509;1
"Unit";"Zergling";"Larva";509;1
"Unit";"Zergling";"Larva";509;1
"Unit";"Zergling";"Larva";509;1
"Building";"CreepTumor";NA;509;0
"Building";"CreepTumor";NA;509;0
"Building";"CreepTumorQueen";NA;525;0
"Unit";"Zergling";"Larva";525;1
"Unit";"Zergling";"Larva";525;1
"Unit";"Zergling";"Larva";525;1
"Unit";"Zergling";"Larva";525;1
"Unit";"Zergling";"Larva";525;1
"Unit";"Zergling";"Larva";525;1
"Unit";"Zergling";"Larva";525;1
"Unit";"Zergling";"Larva";525;1
"Unit";"Zergling";"Larva";525;1
"Unit";"Zergling";"Larva";525;1
"Unit";"Zergling";"Larva";525;1
"Unit";"Zergling";"Larva";525;1
"Unit";"Zergling";"Larva";525;1
"Unit";"Zergling";"Larva";525;1
"Unit";"Zergling";"Larva";525;1
"Unit";"Zergling";"Larva";525;1
"Unit";"Zergling";"Larva";525;1
"Unit";"Zergling";"Larva";525;1
"Unit";"Zergling";"Larva";525;1
"Unit";"Zergling";"Larva";525;1
"Unit";"Zergling";"Larva";525;1
"Unit";"Zergling";"Larva";525;1
"Unit";"Zergling";"Larva";525;1
"Unit";"Zergling";"Larva";525;1
"Unit";"Baneling";"Zergling";525;0
"Unit";"Baneling";"Zergling";525;0
"Unit";"Baneling";"Zergling";525;0
"Unit";"Baneling";"Zergling";525;0
"Unit";"Baneling";"Zergling";525;0
"Unit";"Zergling";"Larva";549;1
"Unit";"Zergling";"Larva";549;1
"Unit";"Zergling";"Larva";549;1
"Unit";"Zergling";"Larva";549;1
"Unit";"Zergling";"Larva";549;1
"Unit";"Zergling";"Larva";549;1
"Unit";"Zergling";"Larva";549;1
"Unit";"Zergling";"Larva";549;1
"Unit";"Zergling";"Larva";549;1
"Unit";"Zergling";"Larva";549;1
"Unit";"Zergling";"Larva";549;1
"Unit";"Zergling";"Larva";549;1
"Unit";"Zergling";"Larva";549;1
"Unit";"Zergling";"Larva";549;1
"Unit";"Zergling";"Larva";549;1
"Unit";"Zergling";"Larva";549;1
"Unit";"Zergling";"Larva";549;1
"Unit";"Zergling";"Larva";549;1
"Unit";"Zergling";"Larva";549;1
"Unit";"Zergling";"Larva";549;1
"Unit";"Zergling";"Larva";549;1
"Unit";"Zergling";"Larva";549;1
"Unit";"Zergling";"Larva";549;1
"Unit";"Zergling";"Larva";549;1
"Unit";"Zergling";"Larva";549;1
"Unit";"Zergling";"Larva";549;1
"Unit";"Zergling";"Larva";549;1
"Unit";"Zergling";"Larva";549;1
"Unit";"Zergling";"Larva";549;1
"Unit";"Zergling";"Larva";549;1
"Unit";"Zergling";"Larva";549;1
"Unit";"Zergling";"Larva";549;1
"Unit";"Zergling";"Larva";549;1
"Unit";"Zergling";"Larva";549;1
"Unit";"Zergling";"Larva";549;1
"Unit";"Zergling";"Larva";549;1
"Unit";"Zergling";"Larva";549;1
"Unit";"Zergling";"Larva";549;1
"Unit";"Zergling";"Larva";549;1
"Unit";"Zergling";"Larva";549;1
"Unit";"Zergling";"Larva";549;1
"Unit";"Zergling";"Larva";549;1
"Unit";"Zergling";"Larva";549;1
"Unit";"Zergling";"Larva";549;1
"Unit";"Zergling";"Larva";549;1
"Unit";"Zergling";"Larva";549;1
"Unit";"Zergling";"Larva";549;1
"Unit";"Zergling";"Larva";549;1
"Unit";"Zergling";"Larva";549;1
"Unit";"Zergling";"Larva";549;1
"Unit";"Zergling";"Larva";549;1
"Unit";"Zergling";"Larva";549;1
"Unit";"Zergling";"Larva";549;1
"Unit";"Zergling";"Larva";549;1
"Unit";"Zergling";"Larva";549;1
"Unit";"Zergling";"Larva";549;1
"Unit";"Zergling";"Larva";549;1
"Unit";"Zergling";"Larva";549;1
"Unit";"Zergling";"Larva";549;1
"Unit";"Zergling";"Larva";549;1
"Unit";"Zergling";"Larva";549;1
"Unit";"Zergling";"Larva";549;1
"Unit";"Zergling";"Larva";549;1
"Unit";"Zergling";"Larva";549;1
"Unit";"Zergling";"Larva";549;1
"Unit";"Zergling";"Larva";549;1
"Unit";"Zergling";"Larva";549;1
"Unit";"Zergling";"Larva";549;1
"Unit";"Zergling";"Larva";549;1
"Unit";"Zergling";"Larva";549;1
"Unit";"Zergling";"Larva";549;1
"Unit";"Zergling";"Larva";549;1
"Unit";"Zergling";"Larva";549;1
"Unit";"Zergling";"Larva";549;1
"Unit";"Zergling";"Larva";549;1
"Unit";"Zergling";"Larva";549;1
"Unit";"Baneling";"Zergling";549;0
"Unit";"Baneling";"Zergling";549;0
"Unit";"Baneling";"Zergling";549;0
"Unit";"Baneling";"Zergling";549;0
"Unit";"Baneling";"Zergling";549;0
"Unit";"Baneling";"Zergling";549;0
"Unit";"Baneling";"Zergling";549;0
"Unit";"Baneling";"Zergling";549;0
"Unit";"Baneling";"Zergling";549;0
"Unit";"Baneling";"Zergling";549;0
"Unit";"Baneling";"Zergling";549;0
"Unit";"Baneling";"Zergling";549;0
"Unit";"Baneling";"Zergling";549;0
"Unit";"Baneling";"Zergling";549;0
"Unit";"Baneling";"Zergling";549;0
"Unit";"Baneling";"Zergling";549;0
"Unit";"Baneling";"Zergling";549;0
"Unit";"Baneling";"Zergling";549;0
"Unit";"Baneling";"Zergling";549;0
"Unit";"Baneling";"Zergling";549;0
"Unit";"Baneling";"Zergling";549;0
"Unit";"Baneling";"Zergling";549;0
"Unit";"Baneling";"Zergling";549;0
"Unit";"Baneling";"Zergling";549;0
"Unit";"Baneling";"Zergling";625;0
"Unit";"Baneling";"Zergling";625;0
"Unit";"Baneling";"Zergling";625;0
"Unit";"Baneling";"Zergling";625;0
"Unit";"Baneling";"Zergling";625;0
"Unit";"Baneling";"Zergling";625;0
"Unit";"Baneling";"Zergling";625;0
"Unit";"Baneling";"Zergling";625;0
"Unit";"Baneling";"Zergling";625;0
"Unit";"Baneling";"Zergling";625;0
"Unit";"Baneling";"Zergling";625;0
"Unit";"Baneling";"Zergling";625;0
"Unit";"Zergling";"Larva";625;1
"Unit";"Zergling";"Larva";625;1
"Unit";"Zergling";"Larva";625;1
"Unit";"Zergling";"Larva";625;1
"Unit";"Zergling";"Larva";625;1
"Unit";"Zergling";"Larva";625;1
"Unit";"Zergling";"Larva";625;1
"Unit";"Zergling";"Larva";625;1
"Unit";"Zergling";"Larva";625;1
"Unit";"Zergling";"Larva";625;1
"Unit";"Zergling";"Larva";625;1
"Unit";"Zergling";"Larva";625;1
"Unit";"Zergling";"Larva";625;1
"Unit";"Zergling";"Larva";625;1
"Unit";"Zergling";"Larva";625;1
"Unit";"Zergling";"Larva";625;1
"Unit";"Zergling";"Larva";625;1
"Unit";"Zergling";"Larva";625;1
"Unit";"Zergling";"Larva";625;1
"Unit";"Zergling";"Larva";625;1
"Unit";"Zergling";"Larva";625;1
"Unit";"Zergling";"Larva";625;1
"Unit";"Zergling";"Larva";625;1
"Unit";"Zergling";"Larva";625;1
"Unit";"Zergling";"Larva";625;1
"Unit";"Zergling";"Larva";625;1
"Unit";"Zergling";"Larva";625;1
"Unit";"Zergling";"Larva";625;1
"Unit";"Zergling";"Larva";625;1
"Unit";"Zergling";"Larva";625;1
"Unit";"Zergling";"Larva";625;1
"Unit";"Zergling";"Larva";625;1
"Unit";"Zergling";"Larva";625;1
"Unit";"Zergling";"Larva";625;1
"Building";"CreepTumor";NA;625;0
"Building";"CreepTumor";NA;625;0
"Unit";"Zergling";"Larva";659;1
"Unit";"Zergling";"Larva";659;1
"Unit";"Zergling";"Larva";659;1
"Unit";"Zergling";"Larva";659;1
"Unit";"Zergling";"Larva";659;1
"Unit";"Zergling";"Larva";659;1
"Unit";"Zergling";"Larva";659;1
"Unit";"Zergling";"Larva";659;1
"Unit";"Zergling";"Larva";659;1
"Unit";"Zergling";"Larva";659;1
"Unit";"Zergling";"Larva";659;1
"Unit";"Zergling";"Larva";659;1
"Unit";"Zergling";"Larva";659;1
"Unit";"Zergling";"Larva";659;1
"Building";"UltraliskCavern";NA;625;0
"Building";"Extractor";NA;678;0
"Building";"CreepTumor";NA;678;0
"Building";"Extractor";NA;678;0
"Unit";"Ultralisk";"Larva";673;6
"Unit";"Ultralisk";"Larva";673;6
"Unit";"Ultralisk";"Larva";673;6
"Unit";"Ultralisk";"Larva";673;6
"Unit";"Ultralisk";"Larva";673;6
"Unit";"Ultralisk";"Larva";673;6
"Unit";"Baneling";"Zergling";678;0
"Unit";"Baneling";"Zergling";678;0
"Unit";"Baneling";"Zergling";678;0
"Unit";"Baneling";"Zergling";678;0
"Unit";"Baneling";"Zergling";678;0
"Unit";"Baneling";"Zergling";678;0
"Unit";"Baneling";"Zergling";678;0
"Unit";"Baneling";"Zergling";678;0
"Unit";"Baneling";"Zergling";678;0
"Unit";"Infestor";"Larva";678;2
"Unit";"Infestor";"Larva";678;2
"Building";"CreepTumorQueen";NA;678;0
"Unit";"Ultralisk";"Larva";678;6
"Building";"CreepTumorQueen";NA;678;0
