"type";"unit_name";"on_building";"total_supply";"supply"
"Unit";"Overlord";"Larva";12;0
"Building";"SpawningPool";NA;19;0
"Building";"Extractor";NA;21;0
"Building";"Hatchery";NA;17;0
"Unit";"Zergling";"Larva";24;1
"Unit";"Zergling";"Larva";24;1
"Unit";"Zergling";"Larva";24;1
"Unit";"Zergling";"Larva";24;1
"Unit";"Queen";"Hatchery";24;2
"Unit";"Overlord";"Larva";28;0
"Building";"Hatchery";NA;21;0
"Unit";"Overlord";"Larva";28;0
"Unit";"Queen";"Hatchery";24;2
"Building";"CreepTumorQueen";NA;41;0
"Unit";"Zergling";"Larva";42;1
"Unit";"Zergling";"Larva";42;1
"Unit";"Zergling";"Larva";43;1
"Unit";"Zergling";"Larva";43;1
"Unit";"Zergling";"Larva";44;1
"Unit";"Zergling";"Larva";44;1
"Unit";"Queen";"Hatchery";41;2
"Building";"CreepTumor";NA;51;0
"Unit";"Queen";"Hatchery";45;2
"Unit";"Overlord";"Larva";51;0
"Unit";"Overlord";"Larva";51;0
"Unit";"Queen";"Hatchery";45;2
"Unit";"Overlord";"Larva";55;0
"Unit";"Overlord";"Larva";57;0
"Building";"CreepTumor";NA;62;0
"Unit";"Overlord";"Larva";62;0
"Unit";"Queen";"Hatchery";57;2
"Unit";"Queen";"Hatchery";57;2
"Building";"SporeCrawler";NA;65;0
"Building";"SporeCrawler";NA;65;0
"Building";"SporeCrawler";NA;65;0
"Building";"SporeCrawler";NA;69;0
"Building";"CreepTumor";NA;78;0
"Building";"CreepTumorQueen";NA;78;0
"Building";"CreepTumorQueen";NA;78;0
"Building";"Extractor";NA;73;0
"Building";"CreepTumorQueen";NA;84;0
"Building";"CreepTumorQueen";NA;84;0
"Building";"BanelingNest";NA;65;0
"Building";"CreepTumorQueen";NA;84;0
"Building";"CreepTumorQueen";NA;84;0
"Building";"CreepTumorQueen";NA;84;0
"Building";"CreepTumorQueen";NA;87;0
"Building";"CreepTumorQueen";NA;87;0
"Building";"CreepTumorQueen";NA;87;0
"Building";"CreepTumorQueen";NA;87;0
"Building";"CreepTumor";NA;88;0
"Building";"CreepTumor";NA;88;0
"Building";"CreepTumor";NA;89;0
"Building";"CreepTumor";NA;90;0
"Building";"CreepTumor";NA;90;0
"Building";"CreepTumor";NA;93;0
"Building";"CreepTumor";NA;93;0
"Building";"CreepTumor";NA;94;0
"Building";"CreepTumor";NA;96;0
"Building";"Extractor";NA;87;0
"Building";"CreepTumorQueen";NA;99;0
"Building";"CreepTumorQueen";NA;101;0
"Building";"CreepTumorQueen";NA;103;0
"Building";"CreepTumorQueen";NA;103;0
"Unit";"Overlord";"Larva";103;0
"Unit";"Overlord";"Larva";103;0
"Building";"CreepTumor";NA;103;0
"Building";"CreepTumor";NA;103;0
"Building";"CreepTumor";NA;103;0
"Building";"CreepTumor";NA;103;0
"Building";"CreepTumor";NA;103;0
"Building";"CreepTumor";NA;103;0
"Unit";"Zergling";"Larva";103;1
"Unit";"Zergling";"Larva";103;1
"Unit";"Zergling";"Larva";103;1
"Unit";"Zergling";"Larva";103;1
"Unit";"Zergling";"Larva";103;1
"Unit";"Zergling";"Larva";103;1
"Unit";"Zergling";"Larva";103;1
"Unit";"Zergling";"Larva";103;1
"Unit";"Zergling";"Larva";103;1
"Unit";"Zergling";"Larva";103;1
"Unit";"Zergling";"Larva";103;1
"Unit";"Zergling";"Larva";103;1
"Unit";"Zergling";"Larva";103;1
"Unit";"Zergling";"Larva";103;1
"Building";"Extractor";NA;103;0
"Building";"Extractor";NA;103;0
"Building";"EvolutionChamber";NA;103;0
"Building";"EvolutionChamber";NA;103;0
"Unit";"Overlord";"Larva";109;0
"Unit";"Overlord";"Larva";109;0
"Building";"Hatchery";NA;87;0
"Unit";"Baneling";"Zergling";123;0
"Unit";"Baneling";"Zergling";123;0
"Unit";"Baneling";"Zergling";123;0
"Unit";"Baneling";"Zergling";123;0
"Unit";"Baneling";"Zergling";123;0
"Unit";"Baneling";"Zergling";123;0
"Unit";"Baneling";"Zergling";123;0
"Unit";"Zergling";"Larva";123;1
"Unit";"Zergling";"Larva";123;1
"Unit";"Zergling";"Larva";123;1
"Unit";"Zergling";"Larva";123;1
"Building";"Extractor";NA;111;0
"Building";"CreepTumor";NA;123;0
"Building";"CreepTumor";NA;123;0
"Building";"CreepTumor";NA;123;0
"Building";"CreepTumor";NA;123;0
"Building";"CreepTumor";NA;123;0
"Building";"CreepTumor";NA;123;0
"Building";"CreepTumor";NA;123;0
"Building";"CreepTumor";NA;123;0
"Building";"CreepTumor";NA;123;0
"Building";"SporeCrawler";NA;127;0
"Building";"CreepTumor";NA;127;0
"Building";"CreepTumor";NA;127;0
"Building";"CreepTumor";NA;127;0
"Building";"CreepTumor";NA;127;0
"Building";"CreepTumor";NA;127;0
"Unit";"Queen";"Hatchery";127;2
"Building";"SporeCrawler";NA;127;0
"Unit";"Overlord";"Larva";127;0
"Unit";"Overlord";"Larva";127;0
"Unit";"Overlord";"Larva";127;0
"Unit";"Overlord";"Larva";127;0
"Unit";"Zergling";"Larva";133;1
"Unit";"Zergling";"Larva";133;1
"Unit";"Zergling";"Larva";135;1
"Unit";"Zergling";"Larva";135;1
"Unit";"Zergling";"Larva";135;1
"Unit";"Zergling";"Larva";135;1
"Unit";"Zergling";"Larva";135;1
"Unit";"Zergling";"Larva";135;1
"Unit";"Zergling";"Larva";135;1
"Unit";"Zergling";"Larva";135;1
"Unit";"Zergling";"Larva";135;1
"Unit";"Zergling";"Larva";135;1
"Unit";"Zergling";"Larva";135;1
"Unit";"Zergling";"Larva";135;1
"Unit";"Zergling";"Larva";135;1
"Unit";"Zergling";"Larva";135;1
"Unit";"Zergling";"Larva";135;1
"Unit";"Zergling";"Larva";135;1
"Unit";"Zergling";"Larva";135;1
"Unit";"Zergling";"Larva";135;1
"Unit";"Zergling";"Larva";135;1
"Unit";"Zergling";"Larva";135;1
"Unit";"Zergling";"Larva";135;1
"Unit";"Zergling";"Larva";135;1
"Building";"CreepTumor";NA;135;0
"Building";"CreepTumor";NA;135;0
"Building";"CreepTumor";NA;135;0
"Building";"CreepTumor";NA;135;0
"Building";"CreepTumor";NA;135;0
"Building";"CreepTumor";NA;135;0
"Building";"CreepTumor";NA;135;0
"Building";"CreepTumor";NA;135;0
"Building";"CreepTumorQueen";NA;137;0
"Building";"CreepTumorQueen";NA;137;0
"Building";"CreepTumorQueen";NA;137;0
"Building";"CreepTumorQueen";NA;137;0
"Building";"CreepTumor";NA;161;0
"Building";"HydraliskDen";NA;135;0
"Building";"CreepTumor";NA;161;0
"Building";"CreepTumor";NA;161;0
"Building";"CreepTumor";NA;161;0
"Building";"CreepTumor";NA;161;0
"Unit";"Overlord";"Larva";161;0
"Unit";"Baneling";"Zergling";161;0
"Building";"CreepTumor";NA;161;0
"Building";"InfestationPit";NA;135;0
"Building";"CreepTumor";NA;163;0
"Building";"CreepTumor";NA;163;0
"Building";"CreepTumor";NA;163;0
"Building";"CreepTumor";NA;163;0
"Building";"CreepTumor";NA;163;0
"Building";"CreepTumor";NA;163;0
"Building";"CreepTumor";NA;163;0
"Building";"CreepTumor";NA;163;0
"Building";"CreepTumor";NA;163;0
"Building";"CreepTumor";NA;163;0
"Building";"CreepTumor";NA;163;0
"Building";"CreepTumor";NA;163;0
"Unit";"Hydralisk";"Larva";163;2
"Unit";"Hydralisk";"Larva";163;2
"Unit";"Hydralisk";"Larva";163;2
"Unit";"Hydralisk";"Larva";163;2
"Unit";"Hydralisk";"Larva";163;2
"Unit";"Hydralisk";"Larva";163;2
"Unit";"Hydralisk";"Larva";163;2
"Unit";"Hydralisk";"Larva";163;2
"Building";"CreepTumor";NA;163;0
"Building";"Hatchery";NA;135;0
"Building";"CreepTumor";NA;166;0
"Building";"CreepTumor";NA;165;0
"Building";"CreepTumor";NA;163;0
"Building";"CreepTumor";NA;168;0
"Building";"CreepTumor";NA;172;0
"Building";"CreepTumor";NA;177;0
"Upgrade";"ZergGroundArmorsLevel1";"EvolutionChamber";135;0
"Unit";"Overlord";"Larva";193;0
"Unit";"Overlord";"Larva";193;0
"Building";"CreepTumorQueen";NA;193;0
"Unit";"Zergling";"Larva";193;1
"Unit";"Zergling";"Larva";193;1
"Unit";"Overlord";"Larva";193;0
"Unit";"Zergling";"Larva";193;1
"Unit";"Zergling";"Larva";193;1
"Unit";"Zergling";"Larva";193;1
"Unit";"Zergling";"Larva";193;1
"Unit";"Zergling";"Larva";193;1
"Unit";"Zergling";"Larva";193;1
"Unit";"Zergling";"Larva";193;1
"Unit";"Zergling";"Larva";193;1
"Unit";"Zergling";"Larva";193;1
"Unit";"Zergling";"Larva";193;1
"Unit";"Zergling";"Larva";193;1
"Unit";"Zergling";"Larva";193;1
"Unit";"Zergling";"Larva";193;1
"Unit";"Zergling";"Larva";193;1
"Unit";"Zergling";"Larva";193;1
"Unit";"Zergling";"Larva";193;1
"Unit";"Zergling";"Larva";193;1
"Unit";"Zergling";"Larva";193;1
"Unit";"Zergling";"Larva";193;1
"Unit";"Zergling";"Larva";193;1
"Unit";"Zergling";"Larva";193;1
"Unit";"Zergling";"Larva";193;1
"Unit";"Zergling";"Larva";193;1
"Unit";"Zergling";"Larva";193;1
"Unit";"Zergling";"Larva";193;1
"Unit";"Zergling";"Larva";193;1
"Unit";"Zergling";"Larva";193;1
"Unit";"Zergling";"Larva";193;1
"Unit";"Zergling";"Larva";193;1
"Unit";"Zergling";"Larva";193;1
"Building";"CreepTumor";NA;193;0
"Building";"CreepTumor";NA;193;0
"Building";"CreepTumor";NA;193;0
"Building";"CreepTumor";NA;193;0
"Building";"CreepTumor";NA;193;0
"Building";"CreepTumor";NA;193;0
"Building";"CreepTumor";NA;193;0
"Building";"CreepTumor";NA;193;0
"Building";"CreepTumor";NA;193;0
"Building";"CreepTumor";NA;193;0
"Building";"CreepTumor";NA;193;0
"Building";"CreepTumor";NA;193;0
"Building";"CreepTumor";NA;193;0
"Unit";"Baneling";"Zergling";193;0
"Unit";"Baneling";"Zergling";193;0
"Unit";"Baneling";"Zergling";193;0
"Unit";"Baneling";"Zergling";193;0
"Unit";"Baneling";"Zergling";193;0
"Unit";"Baneling";"Zergling";193;0
"Unit";"Baneling";"Zergling";193;0
"Unit";"Baneling";"Zergling";193;0
"Unit";"Baneling";"Zergling";193;0
"Unit";"Baneling";"Zergling";193;0
"Unit";"Baneling";"Zergling";193;0
"Unit";"Baneling";"Zergling";193;0
"Unit";"Baneling";"Zergling";193;0
"Unit";"Baneling";"Zergling";193;0
"Unit";"Baneling";"Zergling";193;0
"Unit";"Baneling";"Zergling";193;0
"Unit";"Baneling";"Zergling";193;0
"Unit";"Baneling";"Zergling";193;0
"Unit";"Baneling";"Zergling";193;0
"Unit";"Baneling";"Zergling";193;0
"Unit";"Baneling";"Zergling";193;0
"Unit";"Queen";"Hatchery";193;2
"Upgrade";"ZergMeleeWeaponsLevel1";"EvolutionChamber";163;0
"Building";"CreepTumor";NA;225;0
"Building";"CreepTumor";NA;225;0
"Upgrade";"EvolveGroovedSpines";"HydraliskDen";163;0
"Unit";"Zergling";"Larva";195;1
"Unit";"Zergling";"Larva";195;1
"Unit";"Zergling";"Larva";197;1
"Unit";"Zergling";"Larva";197;1
"Unit";"Zergling";"Larva";201;1
"Unit";"Zergling";"Larva";201;1
"Unit";"Zergling";"Larva";201;1
"Unit";"Zergling";"Larva";201;1
"Unit";"Zergling";"Larva";205;1
"Unit";"Zergling";"Larva";205;1
"Unit";"Zergling";"Larva";209;1
"Unit";"Zergling";"Larva";209;1
"Unit";"Zergling";"Larva";209;1
"Unit";"Zergling";"Larva";209;1
"Unit";"Zergling";"Larva";213;1
"Unit";"Zergling";"Larva";213;1
"Building";"CreepTumor";NA;225;0
"Building";"CreepTumor";NA;225;0
"Building";"CreepTumor";NA;225;0
"Building";"CreepTumor";NA;243;0
"Building";"CreepTumor";NA;243;0
"Building";"CreepTumor";NA;243;0
"Building";"CreepTumorQueen";NA;243;0
"Building";"CreepTumor";NA;243;0
"Building";"CreepTumor";NA;243;0
"Unit";"Overlord";"Larva";243;0
"Unit";"Overlord";"Larva";243;0
"Unit";"Overlord";"Larva";243;0
"Unit";"Zergling";"Larva";243;1
"Unit";"Zergling";"Larva";243;1
"Unit";"Overlord";"Larva";243;0
"Building";"CreepTumor";NA;243;0
"Unit";"Overlord";"Larva";243;0
"Unit";"Zergling";"Larva";243;1
"Unit";"Zergling";"Larva";243;1
"Unit";"Zergling";"Larva";243;1
"Unit";"Zergling";"Larva";243;1
"Unit";"Zergling";"Larva";243;1
"Unit";"Zergling";"Larva";243;1
"Unit";"Zergling";"Larva";243;1
"Unit";"Zergling";"Larva";243;1
"Unit";"Zergling";"Larva";243;1
"Unit";"Zergling";"Larva";243;1
"Unit";"Zergling";"Larva";243;1
"Unit";"Zergling";"Larva";243;1
"Unit";"Zergling";"Larva";243;1
"Unit";"Zergling";"Larva";243;1
"Unit";"Zergling";"Larva";243;1
"Unit";"Zergling";"Larva";243;1
"Building";"CreepTumor";NA;243;0
"Building";"CreepTumor";NA;243;0
"Building";"Extractor";NA;243;0
"Building";"Extractor";NA;243;0
"Building";"CreepTumor";NA;268;0
"Building";"CreepTumor";NA;268;0
"Building";"CreepTumor";NA;268;0
"Building";"CreepTumor";NA;268;0
"Building";"CreepTumor";NA;268;0
"Unit";"Viper";"Larva";243;3
"Unit";"Viper";"Larva";243;3
"Building";"CreepTumor";NA;268;0
"Building";"CreepTumor";NA;268;0
"Unit";"Viper";"Larva";261;3
"Building";"CreepTumor";NA;268;0
"Building";"CreepTumorQueen";NA;268;0
"Building";"EvolutionChamber";NA;268;0
"Building";"EvolutionChamber";NA;268;0
"Building";"EvolutionChamber";NA;268;0
"Upgrade";"EvolveMuscularAugments";"HydraliskDen";243;0
"Unit";"Viper";"Larva";268;3
"Unit";"Zergling";"Larva";277;1
"Unit";"Zergling";"Larva";277;1
"Unit";"Zergling";"Larva";277;1
"Unit";"Zergling";"Larva";277;1
"Unit";"Zergling";"Larva";277;1
"Unit";"Zergling";"Larva";277;1
"Unit";"Zergling";"Larva";277;1
"Unit";"Zergling";"Larva";277;1
"Unit";"Zergling";"Larva";277;1
"Unit";"Zergling";"Larva";277;1
"Unit";"Zergling";"Larva";277;1
"Unit";"Zergling";"Larva";277;1
"Unit";"Zergling";"Larva";277;1
"Unit";"Zergling";"Larva";277;1
"Unit";"Zergling";"Larva";277;1
"Unit";"Zergling";"Larva";277;1
"Unit";"Zergling";"Larva";277;1
"Unit";"Zergling";"Larva";277;1
"Unit";"Zergling";"Larva";277;1
"Unit";"Zergling";"Larva";277;1
"Unit";"Zergling";"Larva";277;1
"Unit";"Zergling";"Larva";277;1
"Unit";"Zergling";"Larva";277;1
"Unit";"Zergling";"Larva";277;1
"Unit";"Zergling";"Larva";277;1
"Unit";"Zergling";"Larva";277;1
"Unit";"Zergling";"Larva";277;1
"Unit";"Zergling";"Larva";277;1
"Unit";"Zergling";"Larva";277;1
"Unit";"Zergling";"Larva";277;1
"Unit";"Zergling";"Larva";277;1
"Unit";"Zergling";"Larva";277;1
"Unit";"Zergling";"Larva";277;1
"Unit";"Zergling";"Larva";277;1
"Unit";"Zergling";"Larva";277;1
"Unit";"Zergling";"Larva";277;1
"Unit";"Zergling";"Larva";277;1
"Unit";"Zergling";"Larva";277;1
"Unit";"Zergling";"Larva";277;1
"Unit";"Zergling";"Larva";277;1
"Unit";"Zergling";"Larva";277;1
"Unit";"Zergling";"Larva";277;1
"Unit";"Zergling";"Larva";277;1
"Unit";"Zergling";"Larva";277;1
"Unit";"Zergling";"Larva";277;1
"Unit";"Zergling";"Larva";277;1
"Unit";"Zergling";"Larva";277;1
"Unit";"Zergling";"Larva";277;1
"Unit";"Zergling";"Larva";277;1
"Unit";"Zergling";"Larva";277;1
"Unit";"Zergling";"Larva";277;1
"Unit";"Zergling";"Larva";277;1
"Building";"CreepTumor";NA;320;0
"Unit";"Zergling";"Larva";322;1
"Unit";"Zergling";"Larva";322;1
"Unit";"Zergling";"Larva";322;1
"Unit";"Zergling";"Larva";322;1
"Unit";"Zergling";"Larva";322;1
"Unit";"Zergling";"Larva";322;1
"Unit";"Zergling";"Larva";322;1
"Unit";"Zergling";"Larva";322;1
"Unit";"Zergling";"Larva";322;1
"Unit";"Zergling";"Larva";322;1
"Unit";"Zergling";"Larva";322;1
"Unit";"Zergling";"Larva";322;1
"Unit";"Zergling";"Larva";322;1
"Unit";"Zergling";"Larva";322;1
"Unit";"Zergling";"Larva";322;1
"Unit";"Zergling";"Larva";322;1
"Unit";"Hydralisk";"Larva";322;2
"Unit";"Hydralisk";"Larva";322;2
"Unit";"Baneling";"Zergling";348;0
"Unit";"Baneling";"Zergling";348;0
"Unit";"Baneling";"Zergling";348;0
"Unit";"Baneling";"Zergling";348;0
"Unit";"Baneling";"Zergling";348;0
"Unit";"Baneling";"Zergling";348;0
"Unit";"Baneling";"Zergling";348;0
"Unit";"Baneling";"Zergling";348;0
"Unit";"Baneling";"Zergling";348;0
"Unit";"Baneling";"Zergling";348;0
"Unit";"Baneling";"Zergling";348;0
"Building";"CreepTumor";NA;352;0
"Unit";"Zergling";"Larva";352;1
"Unit";"Zergling";"Larva";352;1
"Unit";"Zergling";"Larva";352;1
"Unit";"Zergling";"Larva";352;1
"Unit";"Zergling";"Larva";352;1
"Unit";"Zergling";"Larva";352;1
"Unit";"Zergling";"Larva";352;1
"Unit";"Zergling";"Larva";352;1
"Unit";"Zergling";"Larva";352;1
"Unit";"Zergling";"Larva";352;1
"Unit";"Zergling";"Larva";352;1
"Unit";"Zergling";"Larva";352;1
"Unit";"Zergling";"Larva";352;1
"Unit";"Zergling";"Larva";352;1
"Unit";"Zergling";"Larva";352;1
"Unit";"Zergling";"Larva";352;1
"Unit";"Zergling";"Larva";352;1
"Unit";"Zergling";"Larva";352;1
"Unit";"Zergling";"Larva";352;1
"Unit";"Zergling";"Larva";352;1
"Unit";"Zergling";"Larva";352;1
"Unit";"Zergling";"Larva";352;1
"Unit";"Zergling";"Larva";352;1
"Unit";"Zergling";"Larva";352;1
"Unit";"Zergling";"Larva";352;1
"Unit";"Zergling";"Larva";352;1
"Unit";"Zergling";"Larva";352;1
"Unit";"Zergling";"Larva";352;1
"Upgrade";"ZergMeleeWeaponsLevel2";"EvolutionChamber";268;0
"Upgrade";"ZergGroundArmorsLevel2";"EvolutionChamber";268;0
"Unit";"Zergling";"Larva";380;1
"Unit";"Zergling";"Larva";380;1
"Unit";"Zergling";"Larva";380;1
"Unit";"Zergling";"Larva";380;1
"Unit";"Zergling";"Larva";380;1
"Unit";"Zergling";"Larva";380;1
"Unit";"Zergling";"Larva";380;1
"Unit";"Zergling";"Larva";380;1
"Unit";"Zergling";"Larva";380;1
"Unit";"Zergling";"Larva";380;1
"Unit";"Zergling";"Larva";380;1
"Unit";"Zergling";"Larva";380;1
"Unit";"Zergling";"Larva";380;1
"Unit";"Zergling";"Larva";380;1
"Unit";"Zergling";"Larva";380;1
"Unit";"Zergling";"Larva";380;1
"Unit";"Zergling";"Larva";380;1
"Unit";"Zergling";"Larva";380;1
"Unit";"Hydralisk";"Larva";352;2
"Unit";"Hydralisk";"Larva";352;2
"Unit";"Hydralisk";"Larva";352;2
"Unit";"Hydralisk";"Larva";352;2
"Unit";"Hydralisk";"Larva";352;2
"Unit";"Hydralisk";"Larva";352;2
"Unit";"Hydralisk";"Larva";352;2
"Unit";"Hydralisk";"Larva";352;2
"Unit";"Zergling";"Larva";400;1
"Unit";"Zergling";"Larva";400;1
"Unit";"Zergling";"Larva";412;1
"Unit";"Zergling";"Larva";412;1
"Unit";"Zergling";"Larva";412;1
"Unit";"Zergling";"Larva";412;1
"Unit";"Zergling";"Larva";412;1
"Unit";"Zergling";"Larva";412;1
"Unit";"Zergling";"Larva";414;1
"Unit";"Zergling";"Larva";414;1
"Unit";"Zergling";"Larva";414;1
"Unit";"Zergling";"Larva";414;1
"Unit";"Zergling";"Larva";414;1
"Unit";"Zergling";"Larva";414;1
"Unit";"Zergling";"Larva";414;1
"Unit";"Zergling";"Larva";414;1
"Unit";"Zergling";"Larva";414;1
"Unit";"Zergling";"Larva";414;1
"Unit";"Zergling";"Larva";414;1
"Unit";"Zergling";"Larva";414;1
"Unit";"Zergling";"Larva";414;1
"Unit";"Zergling";"Larva";414;1
"Building";"UltraliskCavern";NA;352;0
"Building";"CreepTumor";NA;414;0
"Building";"CreepTumor";NA;426;0
"Building";"CreepTumor";NA;436;0
"Building";"CreepTumor";NA;436;0
"Building";"CreepTumorQueen";NA;436;0
"Building";"CreepTumorQueen";NA;436;0
"Building";"CreepTumorQueen";NA;436;0
"Building";"CreepTumorQueen";NA;436;0
"Unit";"Zergling";"Larva";436;1
"Unit";"Zergling";"Larva";436;1
"Unit";"Zergling";"Larva";436;1
"Unit";"Zergling";"Larva";436;1
"Unit";"Zergling";"Larva";436;1
"Unit";"Zergling";"Larva";436;1
"Unit";"Zergling";"Larva";436;1
"Unit";"Zergling";"Larva";436;1
"Unit";"Zergling";"Larva";436;1
"Unit";"Zergling";"Larva";436;1
"Unit";"Zergling";"Larva";436;1
"Unit";"Zergling";"Larva";436;1
"Unit";"Zergling";"Larva";436;1
"Unit";"Zergling";"Larva";436;1
"Building";"Spire";NA;352;0
"Building";"CreepTumor";NA;436;0
"Building";"CreepTumorQueen";NA;436;0
"Building";"CreepTumorQueen";NA;436;0
"Building";"CreepTumor";NA;436;0
"Building";"CreepTumor";NA;436;0
"Building";"CreepTumor";NA;436;0
"Building";"CreepTumor";NA;436;0
"Building";"CreepTumorQueen";NA;436;0
"Building";"CreepTumorQueen";NA;436;0
"Building";"CreepTumor";NA;436;0
"Building";"CreepTumor";NA;436;0
"Building";"CreepTumor";NA;436;0
"Building";"CreepTumor";NA;436;0
"Building";"CreepTumor";NA;436;0
"Building";"CreepTumor";NA;436;0
"Building";"CreepTumorQueen";NA;450;0
"Building";"CreepTumor";NA;450;0
"Building";"CreepTumor";NA;450;0
"Building";"CreepTumor";NA;450;0
"Building";"CreepTumor";NA;450;0
"Building";"CreepTumor";NA;450;0
"Building";"CreepTumor";NA;450;0
"Building";"CreepTumor";NA;450;0
"Building";"CreepTumor";NA;450;0
"Building";"CreepTumor";NA;450;0
"Building";"CreepTumor";NA;450;0
"Building";"CreepTumor";NA;450;0
"Building";"CreepTumor";NA;450;0
"Building";"CreepTumor";NA;450;0
"Building";"CreepTumor";NA;450;0
"Building";"Extractor";NA;450;0
"Building";"Extractor";NA;450;0
"Building";"CreepTumor";NA;450;0
"Building";"Hatchery";NA;450;0
"Building";"EvolutionChamber";NA;450;0
"Building";"EvolutionChamber";NA;450;0
"Building";"EvolutionChamber";NA;450;0
"Building";"EvolutionChamber";NA;450;0
"Building";"CreepTumor";NA;450;0
"Building";"EvolutionChamber";NA;450;0
"Building";"SporeCrawler";NA;450;0
"Upgrade";"ChitinousPlating";"UltraliskCavern";450;0
"Upgrade";"ZergGroundArmorsLevel3";"EvolutionChamber";450;0
"Upgrade";"ZergMeleeWeaponsLevel3";"EvolutionChamber";450;0
"Building";"CreepTumor";NA;450;0
"Building";"CreepTumorQueen";NA;450;0
"Building";"CreepTumorQueen";NA;450;0
"Building";"CreepTumor";NA;450;0
"Building";"CreepTumor";NA;450;0
"Building";"CreepTumor";NA;450;0
"Building";"CreepTumor";NA;450;0
"Building";"CreepTumor";NA;450;0
"Building";"CreepTumor";NA;450;0
"Building";"CreepTumor";NA;450;0
"Building";"CreepTumor";NA;450;0
"Building";"SpineCrawler";NA;450;0
"Unit";"Ultralisk";"Larva";450;6
"Building";"CreepTumor";NA;450;0
"Building";"CreepTumor";NA;450;0
"Building";"CreepTumor";NA;456;0
"Building";"CreepTumor";NA;456;0
"Building";"CreepTumor";NA;456;0
"Building";"CreepTumor";NA;456;0
"Building";"CreepTumor";NA;456;0
"Building";"CreepTumor";NA;456;0
"Building";"CreepTumor";NA;456;0
"Building";"CreepTumor";NA;456;0
"Building";"CreepTumor";NA;456;0
"Building";"CreepTumor";NA;456;0
"Building";"CreepTumor";NA;456;0
"Unit";"Ultralisk";"Larva";450;6
"Building";"CreepTumor";NA;456;0
"Building";"CreepTumor";NA;456;0
"Building";"CreepTumor";NA;456;0
"Building";"CreepTumor";NA;456;0
"Building";"Spire";NA;450;0
"Building";"CreepTumor";NA;456;0
"Building";"CreepTumor";NA;462;0
"Building";"CreepTumor";NA;462;0
"Building";"CreepTumorQueen";NA;462;0
"Building";"CreepTumorQueen";NA;462;0
"Building";"CreepTumorQueen";NA;462;0
"Building";"SporeCrawler";NA;462;0
"Building";"CreepTumorQueen";NA;462;0
"Building";"CreepTumorQueen";NA;462;0
"Building";"CreepTumorQueen";NA;462;0
"Building";"CreepTumor";NA;462;0
"Building";"CreepTumor";NA;462;0
"Unit";"Corruptor";"Larva";462;2
"Unit";"Corruptor";"Larva";462;2
"Unit";"Corruptor";"Larva";462;2
"Building";"CreepTumor";NA;462;0
"Building";"CreepTumor";NA;462;0
"Building";"CreepTumor";NA;462;0
"Building";"CreepTumor";NA;462;0
"Upgrade";"ZergMissileWeaponsLevel1";"EvolutionChamber";456;0
"Building";"CreepTumor";NA;468;0
"Unit";"Corruptor";"Larva";468;2
"Unit";"Corruptor";"Larva";468;2
"Unit";"Corruptor";"Larva";468;2
"Unit";"Corruptor";"Larva";468;2
"Unit";"Corruptor";"Larva";468;2
"Unit";"Corruptor";"Larva";468;2
"Unit";"Corruptor";"Larva";468;2
"Building";"CreepTumor";NA;468;0
"Building";"CreepTumorQueen";NA;468;0
"Unit";"Viper";"Larva";468;3
"Unit";"Viper";"Larva";468;3
"Unit";"Viper";"Larva";468;3
"Unit";"Viper";"Larva";468;3
"Building";"CreepTumorQueen";NA;468;0
"Building";"CreepTumorQueen";NA;468;0
"Building";"CreepTumorQueen";NA;468;0
"Building";"CreepTumorQueen";NA;482;0
"Building";"CreepTumor";NA;494;0
"Building";"CreepTumorQueen";NA;494;0
"Building";"CreepTumorQueen";NA;494;0
"Building";"CreepTumor";NA;494;0
"Building";"CreepTumor";NA;494;0
"Building";"CreepTumor";NA;494;0
"Building";"CreepTumor";NA;494;0
"Building";"CreepTumor";NA;494;0
"Building";"CreepTumor";NA;494;0
"Building";"CreepTumor";NA;494;0
"Building";"CreepTumor";NA;494;0
"Building";"CreepTumor";NA;494;0
"Unit";"Corruptor";"Larva";494;2
"Building";"CreepTumorQueen";NA;494;0
"Building";"CreepTumorQueen";NA;494;0
"Building";"CreepTumorQueen";NA;494;0
"Building";"CreepTumor";NA;496;0
"Building";"SporeCrawler";NA;494;0
"Building";"SporeCrawler";NA;494;0
"Building";"SporeCrawler";NA;494;0
"Building";"SporeCrawler";NA;494;0
"Building";"SporeCrawler";NA;494;0
"Building";"SporeCrawler";NA;494;0
"Building";"SporeCrawler";NA;494;0
"Building";"SporeCrawler";NA;494;0
"Building";"SporeCrawler";NA;494;0
"Building";"SporeCrawler";NA;494;0
"Building";"SporeCrawler";NA;496;0
"Building";"SporeCrawler";NA;496;0
"Building";"SporeCrawler";NA;496;0
"Building";"CreepTumor";NA;496;0
"Building";"CreepTumor";NA;496;0
"Building";"CreepTumor";NA;496;0
"Building";"CreepTumor";NA;496;0
"Unit";"Corruptor";"Larva";496;2
"Unit";"Corruptor";"Larva";496;2
"Unit";"Corruptor";"Larva";496;2
"Unit";"Corruptor";"Larva";496;2
"Unit";"Corruptor";"Larva";496;2
"Upgrade";"ZergMissileWeaponsLevel2";"EvolutionChamber";494;0
"Unit";"Corruptor";"Larva";496;2
"Unit";"Corruptor";"Larva";496;2
"Unit";"Corruptor";"Larva";496;2
"Unit";"Corruptor";"Larva";496;2
"Building";"CreepTumorQueen";NA;514;0
"Building";"CreepTumor";NA;514;0
"Unit";"Corruptor";"Larva";514;2
"Unit";"Corruptor";"Larva";514;2
"Unit";"Corruptor";"Larva";514;2
"Unit";"Corruptor";"Larva";514;2
"Unit";"Corruptor";"Larva";514;2
"Building";"SporeCrawler";NA;514;0
"Building";"SporeCrawler";NA;514;0
"Building";"SporeCrawler";NA;514;0
"Building";"SporeCrawler";NA;524;0
"Building";"SporeCrawler";NA;524;0
"Building";"SporeCrawler";NA;524;0
"Building";"CreepTumor";NA;524;0
"Building";"CreepTumor";NA;524;0
"Building";"CreepTumor";NA;524;0
"Building";"CreepTumor";NA;524;0
"Building";"CreepTumor";NA;524;0
"Building";"CreepTumor";NA;524;0
"Unit";"Overlord";"Larva";524;0
"Unit";"Overlord";"Larva";524;0
"Building";"CreepTumor";NA;524;0
"Building";"SporeCrawler";NA;524;0
"Building";"SporeCrawler";NA;524;0
"Building";"SporeCrawler";NA;524;0
"Building";"Extractor";NA;524;0
"Building";"CreepTumor";NA;524;0
"Building";"Extractor";NA;524;0
"Building";"CreepTumor";NA;524;0
"Building";"CreepTumor";NA;524;0
"Building";"CreepTumor";NA;524;0
"Building";"CreepTumor";NA;524;0
"Building";"CreepTumor";NA;524;0
"Unit";"Zergling";"Larva";524;1
"Unit";"Zergling";"Larva";524;1
"Unit";"Zergling";"Larva";524;1
"Unit";"Zergling";"Larva";524;1
"Unit";"Zergling";"Larva";524;1
"Unit";"Zergling";"Larva";524;1
"Unit";"Zergling";"Larva";524;1
"Unit";"Zergling";"Larva";524;1
"Unit";"Zergling";"Larva";524;1
"Unit";"Zergling";"Larva";524;1
"Unit";"Zergling";"Larva";524;1
"Unit";"Zergling";"Larva";524;1
"Unit";"Zergling";"Larva";524;1
"Unit";"Zergling";"Larva";524;1
"Unit";"Zergling";"Larva";524;1
"Unit";"Zergling";"Larva";524;1
"Unit";"Zergling";"Larva";524;1
"Unit";"Zergling";"Larva";524;1
"Unit";"Zergling";"Larva";524;1
"Unit";"Zergling";"Larva";524;1
"Unit";"Zergling";"Larva";524;1
"Unit";"Zergling";"Larva";524;1
"Unit";"Zergling";"Larva";524;1
"Unit";"Zergling";"Larva";524;1
"Unit";"Zergling";"Larva";524;1
"Unit";"Zergling";"Larva";524;1
"Unit";"Zergling";"Larva";524;1
"Unit";"Zergling";"Larva";524;1
"Unit";"Zergling";"Larva";524;1
"Unit";"Zergling";"Larva";524;1
"Unit";"Zergling";"Larva";524;1
"Unit";"Zergling";"Larva";524;1
"Unit";"Zergling";"Larva";524;1
"Unit";"Zergling";"Larva";524;1
"Building";"CreepTumor";NA;524;0
"Building";"CreepTumor";NA;524;0
"Building";"CreepTumor";NA;524;0
"Building";"CreepTumor";NA;524;0
"Building";"CreepTumor";NA;524;0
"Building";"CreepTumor";NA;524;0
"Building";"CreepTumor";NA;524;0
"Building";"CreepTumor";NA;524;0
"Building";"Hatchery";NA;524;0
"Building";"CreepTumor";NA;558;0
"Building";"CreepTumor";NA;558;0
"Unit";"Zergling";"Larva";558;1
"Unit";"Zergling";"Larva";558;1
"Unit";"Zergling";"Larva";558;1
"Unit";"Zergling";"Larva";558;1
"Unit";"Zergling";"Larva";558;1
"Unit";"Zergling";"Larva";558;1
"Unit";"Zergling";"Larva";558;1
"Unit";"Zergling";"Larva";558;1
"Unit";"Zergling";"Larva";558;1
"Unit";"Zergling";"Larva";558;1
"Unit";"Zergling";"Larva";558;1
"Unit";"Zergling";"Larva";558;1
"Unit";"Zergling";"Larva";558;1
"Unit";"Zergling";"Larva";558;1
"Unit";"Zergling";"Larva";558;1
"Unit";"Zergling";"Larva";558;1
"Unit";"Baneling";"Zergling";574;0
"Unit";"Baneling";"Zergling";574;0
"Unit";"Baneling";"Zergling";574;0
"Unit";"Baneling";"Zergling";574;0
"Unit";"Baneling";"Zergling";574;0
"Unit";"Baneling";"Zergling";574;0
"Unit";"Baneling";"Zergling";574;0
"Unit";"Baneling";"Zergling";574;0
"Unit";"Baneling";"Zergling";574;0
"Unit";"Baneling";"Zergling";574;0
"Unit";"Baneling";"Zergling";574;0
"Unit";"Baneling";"Zergling";574;0
"Unit";"Baneling";"Zergling";574;0
"Unit";"Zergling";"Larva";574;1
"Unit";"Zergling";"Larva";574;1
"Unit";"Baneling";"Zergling";574;0
"Unit";"Baneling";"Zergling";574;0
"Unit";"Baneling";"Zergling";574;0
"Unit";"Zergling";"Larva";574;1
"Unit";"Zergling";"Larva";574;1
"Unit";"Zergling";"Larva";574;1
"Unit";"Zergling";"Larva";574;1
"Unit";"Zergling";"Larva";574;1
"Unit";"Zergling";"Larva";574;1
"Unit";"Zergling";"Larva";574;1
"Unit";"Zergling";"Larva";574;1
"Unit";"Zergling";"Larva";574;1
"Unit";"Zergling";"Larva";574;1
"Unit";"Zergling";"Larva";574;1
"Unit";"Zergling";"Larva";574;1
"Unit";"Zergling";"Larva";574;1
"Unit";"Zergling";"Larva";574;1
"Unit";"Zergling";"Larva";574;1
"Unit";"Zergling";"Larva";574;1
"Unit";"Zergling";"Larva";574;1
"Unit";"Zergling";"Larva";574;1
"Unit";"Zergling";"Larva";574;1
"Unit";"Zergling";"Larva";574;1
"Building";"CreepTumor";NA;574;0
"Upgrade";"ZergMissileWeaponsLevel3";"EvolutionChamber";524;0
"Building";"CreepTumor";NA;596;0
"Building";"CreepTumor";NA;596;0
"Building";"CreepTumor";NA;596;0
"Building";"CreepTumor";NA;596;0
"Building";"CreepTumor";NA;596;0
"Building";"CreepTumor";NA;596;0
"Building";"CreepTumor";NA;596;0
"Building";"CreepTumor";NA;596;0
"Building";"CreepTumor";NA;596;0
"Unit";"Zergling";"Larva";596;1
"Unit";"Zergling";"Larva";596;1
"Unit";"Zergling";"Larva";596;1
"Unit";"Zergling";"Larva";596;1
"Unit";"Zergling";"Larva";596;1
"Unit";"Zergling";"Larva";596;1
"Unit";"Zergling";"Larva";596;1
"Unit";"Zergling";"Larva";596;1
"Unit";"Zergling";"Larva";596;1
"Unit";"Zergling";"Larva";596;1
"Building";"SporeCrawler";NA;596;0
"Unit";"Overlord";"Larva";606;0
"Unit";"Overlord";"Larva";606;0
"Unit";"Overlord";"Larva";606;0
"Unit";"Overlord";"Larva";606;0
"Unit";"Overlord";"Larva";606;0
"Unit";"Overlord";"Larva";606;0
"Unit";"Overlord";"Larva";606;0
"Unit";"Corruptor";"Larva";606;2
"Unit";"Corruptor";"Larva";606;2
"Building";"CreepTumor";NA;606;0
"Unit";"Baneling";"Zergling";606;0
"Unit";"Baneling";"Zergling";606;0
"Unit";"Baneling";"Zergling";606;0
"Unit";"Baneling";"Zergling";606;0
"Unit";"Baneling";"Zergling";606;0
"Unit";"Baneling";"Zergling";606;0
"Unit";"Baneling";"Zergling";606;0
"Unit";"Baneling";"Zergling";606;0
"Unit";"Baneling";"Zergling";606;0
"Unit";"Baneling";"Zergling";606;0
"Unit";"Baneling";"Zergling";606;0
"Unit";"Baneling";"Zergling";606;0
"Unit";"Baneling";"Zergling";606;0
"Unit";"Baneling";"Zergling";606;0
"Unit";"Baneling";"Zergling";606;0
"Unit";"Baneling";"Zergling";606;0
"Unit";"Hydralisk";"Larva";610;2
"Unit";"Hydralisk";"Larva";610;2
"Unit";"Hydralisk";"Larva";610;2
"Unit";"Hydralisk";"Larva";610;2
"Unit";"Hydralisk";"Larva";610;2
"Unit";"Hydralisk";"Larva";610;2
"Unit";"Hydralisk";"Larva";610;2
"Unit";"Hydralisk";"Larva";610;2
"Unit";"Hydralisk";"Larva";610;2
"Unit";"Hydralisk";"Larva";610;2
"Unit";"Hydralisk";"Larva";610;2
"Unit";"Hydralisk";"Larva";610;2
"Building";"CreepTumor";NA;610;0
"Building";"CreepTumor";NA;610;0
"Building";"CreepTumor";NA;610;0
"Building";"CreepTumor";NA;610;0
"Building";"CreepTumor";NA;610;0
"Building";"CreepTumorQueen";NA;610;0
"Building";"CreepTumor";NA;610;0
"Building";"CreepTumor";NA;610;0
"Building";"CreepTumor";NA;634;0
"Building";"CreepTumor";NA;634;0
"Building";"CreepTumor";NA;634;0
"Unit";"Corruptor";"Larva";634;2
"Unit";"Corruptor";"Larva";634;2
"Unit";"Corruptor";"Larva";634;2
"Building";"SporeCrawler";NA;640;0
"Building";"SporeCrawler";NA;640;0
"Building";"Hatchery";NA;634;0
"Building";"SporeCrawler";NA;640;0
"Unit";"Zergling";"Larva";640;1
"Unit";"Zergling";"Larva";640;1
"Unit";"Zergling";"Larva";640;1
"Unit";"Zergling";"Larva";640;1
"Unit";"Zergling";"Larva";640;1
"Unit";"Zergling";"Larva";640;1
"Unit";"Zergling";"Larva";640;1
"Unit";"Zergling";"Larva";640;1
"Unit";"Zergling";"Larva";640;1
"Unit";"Zergling";"Larva";640;1
"Unit";"Zergling";"Larva";640;1
"Unit";"Zergling";"Larva";640;1
"Unit";"Zergling";"Larva";640;1
"Unit";"Zergling";"Larva";640;1
"Unit";"Zergling";"Larva";640;1
"Unit";"Zergling";"Larva";640;1
"Unit";"Zergling";"Larva";640;1
"Unit";"Zergling";"Larva";640;1
"Unit";"Zergling";"Larva";640;1
"Unit";"Zergling";"Larva";640;1
"Unit";"Zergling";"Larva";640;1
"Unit";"Zergling";"Larva";640;1
"Unit";"Zergling";"Larva";640;1
"Unit";"Zergling";"Larva";640;1
"Unit";"Zergling";"Larva";640;1
"Unit";"Zergling";"Larva";640;1
"Building";"CreepTumor";NA;642;0
"Building";"CreepTumorQueen";NA;666;0
"Unit";"Corruptor";"Larva";666;2
"Unit";"Corruptor";"Larva";666;2
"Unit";"Corruptor";"Larva";666;2
"Unit";"Corruptor";"Larva";666;2
"Unit";"Corruptor";"Larva";666;2
"Unit";"Hydralisk";"Larva";676;2
"Unit";"Hydralisk";"Larva";676;2
"Unit";"Hydralisk";"Larva";676;2
"Unit";"Hydralisk";"Larva";676;2
"Unit";"Hydralisk";"Larva";676;2
"Unit";"Hydralisk";"Larva";676;2
"Unit";"Hydralisk";"Larva";676;2
"Unit";"Hydralisk";"Larva";676;2
"Unit";"Hydralisk";"Larva";676;2
"Unit";"Hydralisk";"Larva";676;2
"Unit";"Zergling";"Larva";676;1
"Unit";"Zergling";"Larva";676;1
"Unit";"Zergling";"Larva";676;1
"Unit";"Zergling";"Larva";676;1
"Unit";"Zergling";"Larva";676;1
"Unit";"Zergling";"Larva";676;1
"Unit";"Zergling";"Larva";676;1
"Unit";"Zergling";"Larva";676;1
"Unit";"Zergling";"Larva";676;1
"Unit";"Zergling";"Larva";676;1
"Unit";"Zergling";"Larva";676;1
"Unit";"Zergling";"Larva";676;1
"Unit";"Zergling";"Larva";676;1
"Unit";"Zergling";"Larva";676;1
"Unit";"Zergling";"Larva";676;1
"Unit";"Zergling";"Larva";676;1
"Unit";"Zergling";"Larva";676;1
"Unit";"Zergling";"Larva";676;1
"Unit";"Zergling";"Larva";676;1
"Unit";"Zergling";"Larva";676;1
"Unit";"Zergling";"Larva";676;1
"Unit";"Zergling";"Larva";676;1
"Unit";"Zergling";"Larva";676;1
"Unit";"Zergling";"Larva";676;1
"Building";"CreepTumor";NA;676;0
"Building";"CreepTumor";NA;676;0
"Unit";"Queen";"Hatchery";676;2
"Unit";"Queen";"Hatchery";676;2
"Unit";"Queen";"Hatchery";676;2
"Unit";"Queen";"Hatchery";676;2
"Building";"CreepTumor";NA;676;0
"Building";"CreepTumor";NA;720;0
"Unit";"Queen";"Hatchery";676;2
"Unit";"Queen";"Hatchery";676;2
"Unit";"Queen";"Hatchery";676;2
"Unit";"Baneling";"Zergling";728;0
"Unit";"Baneling";"Zergling";728;0
"Unit";"Baneling";"Zergling";728;0
"Unit";"Baneling";"Zergling";728;0
"Unit";"Baneling";"Zergling";728;0
"Unit";"Baneling";"Zergling";728;0
"Unit";"Baneling";"Zergling";728;0
"Unit";"Baneling";"Zergling";728;0
"Unit";"Baneling";"Zergling";728;0
"Unit";"Baneling";"Zergling";728;0
"Unit";"Baneling";"Zergling";728;0
"Building";"Extractor";NA;728;0
"Building";"Extractor";NA;728;0
"Unit";"Hydralisk";"Larva";728;2
"Unit";"Hydralisk";"Larva";728;2
"Unit";"Hydralisk";"Larva";728;2
"Unit";"Hydralisk";"Larva";728;2
"Unit";"Hydralisk";"Larva";728;2
"Unit";"Hydralisk";"Larva";728;2
"Building";"Hatchery";NA;728;0
"Unit";"Corruptor";"Larva";746;2
"Unit";"Corruptor";"Larva";746;2
"Unit";"Corruptor";"Larva";746;2
"Unit";"Corruptor";"Larva";746;2
"Unit";"Corruptor";"Larva";746;2
"Unit";"Corruptor";"Larva";746;2
"Unit";"Corruptor";"Larva";746;2
"Unit";"Corruptor";"Larva";746;2
"Unit";"Corruptor";"Larva";746;2
"Unit";"Queen";"Hatchery";746;2
"Building";"CreepTumor";NA;783;0
"Building";"CreepTumor";NA;783;0
"Building";"CreepTumor";NA;783;0
"Unit";"Hydralisk";"Larva";783;2
"Unit";"Hydralisk";"Larva";783;2
"Unit";"Hydralisk";"Larva";783;2
"Unit";"Hydralisk";"Larva";783;2
"Unit";"Hydralisk";"Larva";783;2
"Unit";"Hydralisk";"Larva";783;2
"Unit";"Hydralisk";"Larva";783;2
"Unit";"Hydralisk";"Larva";783;2
"Unit";"Zergling";"Larva";783;1
"Unit";"Zergling";"Larva";783;1
"Unit";"Zergling";"Larva";783;1
"Unit";"Zergling";"Larva";783;1
"Unit";"Zergling";"Larva";783;1
"Unit";"Zergling";"Larva";783;1
"Unit";"Zergling";"Larva";783;1
"Unit";"Zergling";"Larva";783;1
"Unit";"Zergling";"Larva";783;1
"Unit";"Zergling";"Larva";783;1
"Unit";"Zergling";"Larva";783;1
"Unit";"Zergling";"Larva";783;1
"Unit";"Zergling";"Larva";783;1
"Unit";"Zergling";"Larva";783;1
"Unit";"Zergling";"Larva";783;1
"Unit";"Zergling";"Larva";783;1
"Unit";"Zergling";"Larva";783;1
"Unit";"Zergling";"Larva";783;1
"Unit";"Zergling";"Larva";783;1
"Unit";"Zergling";"Larva";783;1
"Unit";"Zergling";"Larva";783;1
"Unit";"Zergling";"Larva";783;1
"Building";"CreepTumorQueen";NA;783;0
"Building";"CreepTumorQueen";NA;799;0
"Building";"CreepTumorQueen";NA;799;0
"Building";"Hatchery";NA;783;0
"Unit";"Zergling";"Larva";821;1
"Unit";"Zergling";"Larva";821;1
"Unit";"Zergling";"Larva";821;1
"Unit";"Zergling";"Larva";821;1
"Unit";"Zergling";"Larva";821;1
"Unit";"Zergling";"Larva";821;1
"Unit";"Zergling";"Larva";821;1
"Unit";"Zergling";"Larva";821;1
"Unit";"Zergling";"Larva";821;1
"Unit";"Zergling";"Larva";821;1
"Unit";"Zergling";"Larva";821;1
"Unit";"Zergling";"Larva";821;1
"Unit";"Hydralisk";"Larva";821;2
"Unit";"Hydralisk";"Larva";821;2
"Unit";"Hydralisk";"Larva";821;2
"Unit";"Hydralisk";"Larva";821;2
"Unit";"Hydralisk";"Larva";821;2
"Unit";"Hydralisk";"Larva";821;2
"Unit";"Hydralisk";"Larva";821;2
"Building";"CreepTumor";NA;821;0
"Building";"CreepTumor";NA;821;0
"Unit";"Baneling";"Zergling";833;0
"Unit";"Baneling";"Zergling";833;0
"Unit";"Baneling";"Zergling";833;0
"Unit";"Baneling";"Zergling";833;0
"Unit";"Baneling";"Zergling";833;0
"Unit";"Baneling";"Zergling";833;0
"Unit";"Baneling";"Zergling";833;0
"Unit";"Baneling";"Zergling";833;0
"Unit";"Baneling";"Zergling";833;0
"Unit";"Baneling";"Zergling";833;0
"Building";"CreepTumor";NA;847;0
"Building";"CreepTumor";NA;847;0
"Building";"CreepTumor";NA;847;0
"Unit";"Zergling";"Larva";869;1
"Unit";"Zergling";"Larva";869;1
"Unit";"Zergling";"Larva";869;1
"Unit";"Zergling";"Larva";869;1
"Unit";"Zergling";"Larva";869;1
"Unit";"Zergling";"Larva";869;1
"Unit";"Zergling";"Larva";869;1
"Unit";"Zergling";"Larva";869;1
"Unit";"Zergling";"Larva";869;1
"Unit";"Zergling";"Larva";869;1
"Unit";"Zergling";"Larva";869;1
"Unit";"Zergling";"Larva";869;1
"Unit";"Zergling";"Larva";869;1
"Unit";"Zergling";"Larva";869;1
"Unit";"Zergling";"Larva";869;1
"Unit";"Zergling";"Larva";869;1
"Unit";"Zergling";"Larva";869;1
"Unit";"Zergling";"Larva";869;1
"Unit";"Zergling";"Larva";869;1
"Unit";"Zergling";"Larva";869;1
"Unit";"Zergling";"Larva";869;1
"Unit";"Zergling";"Larva";869;1
"Unit";"Zergling";"Larva";869;1
"Unit";"Zergling";"Larva";869;1
"Building";"CreepTumor";NA;900;0
"Unit";"Baneling";"Zergling";900;0
"Unit";"Baneling";"Zergling";900;0
"Unit";"Baneling";"Zergling";900;0
"Unit";"Baneling";"Zergling";900;0
"Unit";"Baneling";"Zergling";900;0
"Unit";"Baneling";"Zergling";900;0
"Unit";"Baneling";"Zergling";900;0
"Unit";"Baneling";"Zergling";900;0
"Unit";"Baneling";"Zergling";900;0
"Unit";"Hydralisk";"Larva";900;2
"Unit";"Hydralisk";"Larva";900;2
"Unit";"Hydralisk";"Larva";900;2
"Unit";"Hydralisk";"Larva";900;2
"Unit";"Hydralisk";"Larva";900;2
"Unit";"Hydralisk";"Larva";900;2
"Building";"Extractor";NA;900;0
"Building";"Extractor";NA;900;0
"Unit";"Zergling";"Larva";912;1
"Unit";"Zergling";"Larva";912;1
"Unit";"Zergling";"Larva";912;1
"Unit";"Zergling";"Larva";912;1
"Unit";"Zergling";"Larva";912;1
"Unit";"Zergling";"Larva";912;1
"Unit";"Zergling";"Larva";912;1
"Unit";"Zergling";"Larva";912;1
"Unit";"Zergling";"Larva";912;1
"Unit";"Zergling";"Larva";912;1
"Unit";"Zergling";"Larva";912;1
"Unit";"Zergling";"Larva";912;1
"Unit";"Zergling";"Larva";912;1
"Unit";"Zergling";"Larva";912;1
"Unit";"Zergling";"Larva";912;1
"Unit";"Zergling";"Larva";912;1
"Unit";"Zergling";"Larva";912;1
"Unit";"Zergling";"Larva";912;1
"Unit";"Zergling";"Larva";912;1
"Unit";"Zergling";"Larva";912;1
"Unit";"Zergling";"Larva";912;1
"Unit";"Zergling";"Larva";912;1
"Unit";"Zergling";"Larva";912;1
"Unit";"Zergling";"Larva";912;1
"Unit";"Zergling";"Larva";912;1
"Unit";"Zergling";"Larva";912;1
"Unit";"Zergling";"Larva";912;1
"Unit";"Zergling";"Larva";912;1
"Unit";"Zergling";"Larva";912;1
"Unit";"Zergling";"Larva";912;1
"Unit";"Zergling";"Larva";912;1
"Unit";"Zergling";"Larva";912;1
"Unit";"Zergling";"Larva";912;1
"Unit";"Zergling";"Larva";912;1
"Unit";"Zergling";"Larva";912;1
"Unit";"Zergling";"Larva";912;1
"Unit";"Zergling";"Larva";912;1
"Unit";"Zergling";"Larva";912;1
"Building";"Extractor";NA;912;0
"Building";"SporeCrawler";NA;912;0
"Building";"Extractor";NA;912;0
"Unit";"Baneling";"Zergling";964;0
"Unit";"Baneling";"Zergling";964;0
"Unit";"Baneling";"Zergling";964;0
"Unit";"Baneling";"Zergling";964;0
"Unit";"Baneling";"Zergling";964;0
"Unit";"Zergling";"Larva";964;1
"Unit";"Zergling";"Larva";964;1
"Unit";"Zergling";"Larva";964;1
"Unit";"Zergling";"Larva";964;1
"Unit";"Zergling";"Larva";964;1
"Unit";"Zergling";"Larva";964;1
"Unit";"Zergling";"Larva";964;1
"Unit";"Zergling";"Larva";964;1
"Unit";"Zergling";"Larva";964;1
"Unit";"Zergling";"Larva";964;1
"Unit";"Zergling";"Larva";964;1
"Unit";"Zergling";"Larva";964;1
"Unit";"Zergling";"Larva";964;1
"Unit";"Zergling";"Larva";964;1
"Unit";"Zergling";"Larva";964;1
"Unit";"Zergling";"Larva";964;1
"Unit";"Zergling";"Larva";964;1
"Unit";"Zergling";"Larva";964;1
"Unit";"Zergling";"Larva";964;1
"Unit";"Zergling";"Larva";964;1
"Unit";"Zergling";"Larva";964;1
"Unit";"Zergling";"Larva";964;1
"Unit";"Zergling";"Larva";964;1
"Unit";"Zergling";"Larva";964;1
"Unit";"Zergling";"Larva";964;1
"Unit";"Zergling";"Larva";964;1
"Unit";"Zergling";"Larva";964;1
"Unit";"Zergling";"Larva";964;1
"Unit";"Zergling";"Larva";964;1
"Unit";"Zergling";"Larva";964;1
"Building";"SporeCrawler";NA;964;0
"Unit";"Queen";"Hatchery";964;2
"Unit";"Queen";"Hatchery";964;2
"Unit";"Queen";"Hatchery";964;2
"Unit";"Queen";"Hatchery";964;2
"Unit";"Queen";"Hatchery";964;2
"Unit";"Queen";"Hatchery";964;2
"Unit";"Baneling";"Zergling";994;0
"Unit";"Zergling";"Larva";994;1
"Unit";"Zergling";"Larva";994;1
"Unit";"Baneling";"Zergling";994;0
"Unit";"Baneling";"Zergling";994;0
"Unit";"Baneling";"Zergling";994;0
"Unit";"Zergling";"Larva";994;1
"Unit";"Zergling";"Larva";994;1
"Unit";"Zergling";"Larva";994;1
"Unit";"Zergling";"Larva";994;1
"Unit";"Zergling";"Larva";994;1
"Unit";"Zergling";"Larva";994;1
"Unit";"Baneling";"Zergling";994;0
"Unit";"Baneling";"Zergling";994;0
"Building";"CreepTumor";NA;994;0
"Unit";"Baneling";"Zergling";994;0
"Unit";"Baneling";"Zergling";994;0
"Unit";"Zergling";"Larva";994;1
"Unit";"Zergling";"Larva";994;1
"Unit";"Zergling";"Larva";994;1
"Unit";"Zergling";"Larva";994;1
"Unit";"Zergling";"Larva";994;1
"Unit";"Zergling";"Larva";994;1
"Unit";"Zergling";"Larva";994;1
"Unit";"Zergling";"Larva";994;1
"Unit";"Baneling";"Zergling";994;0
"Unit";"Baneling";"Zergling";994;0
"Unit";"Baneling";"Zergling";994;0
"Unit";"Zergling";"Larva";994;1
"Unit";"Zergling";"Larva";994;1
"Unit";"Zergling";"Larva";994;1
"Unit";"Zergling";"Larva";994;1
"Unit";"Zergling";"Larva";994;1
"Unit";"Zergling";"Larva";994;1
"Unit";"Zergling";"Larva";994;1
"Unit";"Zergling";"Larva";994;1
"Unit";"Baneling";"Zergling";994;0
"Unit";"Baneling";"Zergling";994;0
"Unit";"Zergling";"Larva";994;1
"Unit";"Zergling";"Larva";994;1
"Unit";"Zergling";"Larva";994;1
"Unit";"Zergling";"Larva";994;1
"Unit";"Zergling";"Larva";994;1
"Unit";"Zergling";"Larva";994;1
"Unit";"Zergling";"Larva";994;1
"Unit";"Zergling";"Larva";994;1
"Unit";"Zergling";"Larva";994;1
"Unit";"Zergling";"Larva";994;1
"Building";"CreepTumor";NA;994;0
"Building";"CreepTumor";NA;994;0
"Building";"CreepTumor";NA;994;0
"Building";"CreepTumor";NA;1040;0
"Unit";"Baneling";"Zergling";1040;0
"Unit";"Baneling";"Zergling";1040;0
"Unit";"Baneling";"Zergling";1040;0
"Unit";"Baneling";"Zergling";1040;0
"Unit";"Baneling";"Zergling";1040;0
"Unit";"Baneling";"Zergling";1040;0
"Unit";"Baneling";"Zergling";1040;0
"Unit";"Baneling";"Zergling";1040;0
"Unit";"Baneling";"Zergling";1040;0
"Unit";"Baneling";"Zergling";1040;0
"Unit";"Baneling";"Zergling";1040;0
"Unit";"Baneling";"Zergling";1040;0
"Unit";"Baneling";"Zergling";1040;0
"Unit";"Zergling";"Larva";1040;1
"Unit";"Zergling";"Larva";1040;1
"Unit";"Zergling";"Larva";1040;1
"Unit";"Zergling";"Larva";1040;1
"Unit";"Zergling";"Larva";1040;1
"Unit";"Zergling";"Larva";1040;1
"Unit";"Zergling";"Larva";1040;1
"Unit";"Zergling";"Larva";1040;1
"Unit";"Zergling";"Larva";1040;1
"Unit";"Zergling";"Larva";1040;1
"Unit";"Zergling";"Larva";1040;1
"Unit";"Zergling";"Larva";1040;1
"Unit";"Zergling";"Larva";1040;1
"Unit";"Zergling";"Larva";1040;1
"Unit";"Zergling";"Larva";1040;1
"Unit";"Zergling";"Larva";1040;1
"Unit";"Zergling";"Larva";1040;1
"Unit";"Zergling";"Larva";1040;1
"Unit";"Zergling";"Larva";1040;1
"Unit";"Zergling";"Larva";1040;1
"Unit";"Zergling";"Larva";1060;1
"Unit";"Zergling";"Larva";1060;1
"Unit";"Zergling";"Larva";1060;1
"Unit";"Zergling";"Larva";1060;1
"Unit";"Zergling";"Larva";1060;1
"Unit";"Zergling";"Larva";1060;1
"Unit";"Zergling";"Larva";1060;1
"Unit";"Zergling";"Larva";1060;1
"Unit";"Zergling";"Larva";1060;1
"Unit";"Zergling";"Larva";1060;1
"Unit";"Zergling";"Larva";1060;1
"Unit";"Zergling";"Larva";1060;1
"Unit";"Zergling";"Larva";1060;1
"Unit";"Zergling";"Larva";1060;1
"Building";"CreepTumor";NA;1074;0
"Unit";"Zergling";"Larva";1060;1
"Unit";"Zergling";"Larva";1060;1
"Unit";"Zergling";"Larva";1060;1
"Unit";"Zergling";"Larva";1060;1
"Unit";"Zergling";"Larva";1060;1
"Unit";"Zergling";"Larva";1060;1
"Unit";"Zergling";"Larva";1060;1
"Unit";"Zergling";"Larva";1060;1
"Unit";"Zergling";"Larva";1060;1
"Unit";"Zergling";"Larva";1060;1
"Unit";"Zergling";"Larva";1060;1
"Unit";"Zergling";"Larva";1060;1
"Unit";"Zergling";"Larva";1060;1
"Unit";"Zergling";"Larva";1060;1
"Unit";"Zergling";"Larva";1060;1
"Unit";"Zergling";"Larva";1060;1
"Unit";"Zergling";"Larva";1060;1
"Unit";"Zergling";"Larva";1060;1
"Unit";"Zergling";"Larva";1060;1
"Unit";"Zergling";"Larva";1060;1
"Unit";"Zergling";"Larva";1060;1
"Unit";"Zergling";"Larva";1060;1
"Unit";"Zergling";"Larva";1060;1
"Unit";"Zergling";"Larva";1060;1
"Unit";"Zergling";"Larva";1060;1
"Unit";"Zergling";"Larva";1060;1
"Unit";"Zergling";"Larva";1060;1
"Unit";"Zergling";"Larva";1060;1
"Unit";"Zergling";"Larva";1060;1
"Unit";"Zergling";"Larva";1060;1
"Unit";"Zergling";"Larva";1060;1
"Unit";"Zergling";"Larva";1060;1
"Unit";"Zergling";"Larva";1074;1
"Unit";"Zergling";"Larva";1074;1
"Unit";"Zergling";"Larva";1074;1
"Unit";"Zergling";"Larva";1074;1
"Unit";"Zergling";"Larva";1074;1
"Unit";"Zergling";"Larva";1074;1
"Unit";"Zergling";"Larva";1074;1
"Unit";"Zergling";"Larva";1074;1
"Unit";"Zergling";"Larva";1074;1
"Unit";"Zergling";"Larva";1074;1
"Unit";"Zergling";"Larva";1074;1
"Unit";"Zergling";"Larva";1074;1
"Unit";"Zergling";"Larva";1074;1
"Unit";"Zergling";"Larva";1074;1
"Unit";"Zergling";"Larva";1074;1
"Unit";"Zergling";"Larva";1074;1
"Unit";"Queen";"Hatchery";1074;2
"Unit";"Baneling";"Zergling";1122;0
"Unit";"Baneling";"Zergling";1122;0
"Unit";"Baneling";"Zergling";1122;0
"Unit";"Baneling";"Zergling";1122;0
"Unit";"Baneling";"Zergling";1122;0
"Unit";"Baneling";"Zergling";1122;0
"Unit";"Baneling";"Zergling";1122;0
"Unit";"Baneling";"Zergling";1122;0
"Unit";"Baneling";"Zergling";1122;0
"Unit";"Baneling";"Zergling";1122;0
"Unit";"Baneling";"Zergling";1122;0
"Unit";"Baneling";"Zergling";1122;0
"Unit";"Baneling";"Zergling";1122;0
"Unit";"Hydralisk";"Larva";1106;2
"Unit";"Hydralisk";"Larva";1106;2
"Unit";"Hydralisk";"Larva";1106;2
"Unit";"Hydralisk";"Larva";1106;2
"Unit";"Hydralisk";"Larva";1106;2
"Unit";"Hydralisk";"Larva";1106;2
"Unit";"Hydralisk";"Larva";1106;2
"Unit";"Hydralisk";"Larva";1106;2
"Unit";"Hydralisk";"Larva";1106;2
"Unit";"Hydralisk";"Larva";1106;2
"Unit";"Hydralisk";"Larva";1106;2
"Unit";"Hydralisk";"Larva";1106;2
