"type";"unit_name";"on_building";"total_supply";"supply"
"Unit";"Overlord";"Larva";13;0
"Building";"Extractor";NA;18;0
"Unit";"Overlord";"Larva";21;0
"Building";"SpawningPool";NA;19;0
"Building";"Hatchery";NA;17;0
"Unit";"Zergling";"Larva";22;1
"Unit";"Zergling";"Larva";22;1
"Unit";"Zergling";"Larva";23;1
"Unit";"Zergling";"Larva";23;1
"Unit";"Queen";"Hatchery";22;2
"Unit";"Queen";"Hatchery";23;2
"Unit";"Overlord";"Larva";33;0
"Unit";"Overlord";"Larva";35;0
"Unit";"Overlord";"Larva";38;0
"Building";"CreepTumorQueen";NA;39;0
"Unit";"Queen";"Hatchery";37;2
"Building";"Hatchery";NA;29;0
"Building";"CreepTumorQueen";NA;50;0
"Building";"CreepTumor";NA;50;0
"Unit";"Queen";"Hatchery";44;2
"Unit";"Overlord";"Larva";51;0
"Building";"Extractor";NA;54;0
"Unit";"Queen";"Hatchery";50;2
"Building";"Extractor";NA;54;0
"Unit";"Zergling";"Larva";54;1
"Unit";"Zergling";"Larva";54;1
"Unit";"Overlord";"Larva";54;0
"Unit";"Zergling";"Larva";54;1
"Unit";"Zergling";"Larva";54;1
"Unit";"Zergling";"Larva";54;1
"Unit";"Zergling";"Larva";54;1
"Unit";"Zergling";"Larva";54;1
"Unit";"Zergling";"Larva";54;1
"Building";"CreepTumorQueen";NA;57;0
"Unit";"Queen";"Hatchery";51;2
"Unit";"Zergling";"Larva";59;1
"Unit";"Zergling";"Larva";59;1
"Unit";"Zergling";"Larva";61;1
"Unit";"Zergling";"Larva";61;1
"Unit";"Overlord";"Larva";75;0
"Unit";"Overlord";"Larva";75;0
"Building";"CreepTumor";NA;79;0
"Building";"CreepTumor";NA;79;0
"Building";"CreepTumorQueen";NA;79;0
"Building";"CreepTumorQueen";NA;79;0
"Unit";"Overlord";"Larva";79;0
"Building";"EvolutionChamber";NA;79;0
"Building";"CreepTumor";NA;83;0
"Building";"EvolutionChamber";NA;79;0
"Building";"CreepTumorQueen";NA;88;0
"Unit";"Queen";"Hatchery";79;2
"Building";"CreepTumorQueen";NA;88;0
"Building";"CreepTumor";NA;91;0
"Building";"CreepTumor";NA;91;0
"Building";"CreepTumor";NA;93;0
"Building";"CreepTumor";NA;93;0
"Building";"CreepTumor";NA;93;0
"Unit";"Overlord";"Larva";96;0
"Unit";"Overlord";"Larva";102;0
"Unit";"Overlord";"Larva";106;0
"Building";"CreepTumor";NA;107;0
"Building";"CreepTumor";NA;107;0
"Building";"CreepTumor";NA;107;0
"Building";"Extractor";NA;107;0
"Building";"CreepTumor";NA;107;0
"Building";"Extractor";NA;107;0
"Building";"CreepTumorQueen";NA;107;0
"Building";"CreepTumor";NA;107;0
"Building";"CreepTumor";NA;107;0
"Building";"CreepTumorQueen";NA;107;0
"Building";"Extractor";NA;107;0
"Unit";"Zergling";"Larva";107;1
"Unit";"Zergling";"Larva";107;1
"Unit";"Zergling";"Larva";107;1
"Unit";"Zergling";"Larva";107;1
"Unit";"Zergling";"Larva";107;1
"Unit";"Zergling";"Larva";107;1
"Building";"HydraliskDen";NA;107;0
"Building";"CreepTumor";NA;113;0
"Building";"CreepTumor";NA;113;0
"Building";"CreepTumor";NA;113;0
"Building";"CreepTumor";NA;113;0
"Building";"CreepTumor";NA;113;0
"Building";"CreepTumorQueen";NA;125;0
"Building";"CreepTumor";NA;125;0
"Building";"CreepTumor";NA;125;0
"Building";"CreepTumorQueen";NA;126;0
"Building";"CreepTumor";NA;126;0
"Building";"BanelingNest";NA;107;0
"Unit";"Queen";"Hatchery";113;2
"Building";"Hatchery";NA;107;0
"Upgrade";"ZergMeleeWeaponsLevel1";"EvolutionChamber";107;0
"Upgrade";"ZergGroundArmorsLevel1";"EvolutionChamber";107;0
"Building";"SporeCrawler";NA;142;0
"Building";"SporeCrawler";NA;142;0
"Building";"InfestationPit";NA;133;0
"Building";"CreepTumor";NA;143;0
"Unit";"Overlord";"Larva";142;0
"Building";"CreepTumor";NA;143;0
"Building";"CreepTumor";NA;143;0
"Building";"CreepTumor";NA;143;0
"Building";"CreepTumor";NA;143;0
"Building";"CreepTumor";NA;143;0
"Building";"CreepTumor";NA;143;0
"Building";"CreepTumor";NA;143;0
"Building";"Hatchery";NA;126;0
"Upgrade";"EvolveGroovedSpines";"HydraliskDen";130;0
"Building";"Hatchery";NA;126;0
"Unit";"Hydralisk";"Larva";142;2
"Unit";"Hydralisk";"Larva";142;2
"Unit";"Hydralisk";"Larva";142;2
"Unit";"Hydralisk";"Larva";142;2
"Unit";"Hydralisk";"Larva";142;2
"Unit";"Hydralisk";"Larva";142;2
"Unit";"Hydralisk";"Larva";142;2
"Unit";"Hydralisk";"Larva";142;2
"Unit";"Queen";"Hatchery";142;2
"Building";"SporeCrawler";NA;143;0
"Unit";"Overlord";"Larva";143;0
"Unit";"Hydralisk";"Larva";143;2
"Unit";"Hydralisk";"Larva";143;2
"Unit";"Hydralisk";"Larva";143;2
"Unit";"Hydralisk";"Larva";143;2
"Unit";"Hydralisk";"Larva";143;2
"Building";"CreepTumor";NA;159;0
"Building";"CreepTumor";NA;159;0
"Building";"CreepTumor";NA;159;0
"Building";"CreepTumor";NA;161;0
"Building";"CreepTumor";NA;161;0
"Building";"CreepTumor";NA;161;0
"Building";"CreepTumor";NA;161;0
"Building";"CreepTumor";NA;168;0
"Unit";"Zergling";"Larva";178;1
"Unit";"Zergling";"Larva";178;1
"Unit";"Zergling";"Larva";178;1
"Unit";"Zergling";"Larva";178;1
"Unit";"Zergling";"Larva";178;1
"Unit";"Zergling";"Larva";178;1
"Unit";"Zergling";"Larva";178;1
"Unit";"Zergling";"Larva";178;1
"Unit";"Zergling";"Larva";178;1
"Unit";"Zergling";"Larva";178;1
"Unit";"Zergling";"Larva";178;1
"Unit";"Zergling";"Larva";178;1
"Unit";"Zergling";"Larva";178;1
"Unit";"Zergling";"Larva";178;1
"Unit";"Zergling";"Larva";178;1
"Unit";"Zergling";"Larva";178;1
"Unit";"Zergling";"Larva";178;1
"Unit";"Zergling";"Larva";178;1
"Unit";"Zergling";"Larva";178;1
"Unit";"Zergling";"Larva";178;1
"Unit";"Zergling";"Larva";178;1
"Unit";"Zergling";"Larva";178;1
"Unit";"Zergling";"Larva";178;1
"Unit";"Zergling";"Larva";178;1
"Unit";"Zergling";"Larva";178;1
"Unit";"Zergling";"Larva";178;1
"Unit";"Zergling";"Larva";178;1
"Unit";"Zergling";"Larva";178;1
"Building";"CreepTumor";NA;211;0
"Upgrade";"EvolveMuscularAugments";"HydraliskDen";178;0
"Unit";"Overlord";"Larva";211;0
"Unit";"Overlord";"Larva";211;0
"Unit";"Overlord";"Larva";211;0
"Unit";"Overlord";"Larva";211;0
"Unit";"Hydralisk";"Larva";211;2
"Upgrade";"ZergMeleeWeaponsLevel2";"EvolutionChamber";143;0
"Upgrade";"ZergGroundArmorsLevel2";"EvolutionChamber";143;0
"Unit";"Overlord";"Larva";213;0
"Unit";"Overlord";"Larva";213;0
"Building";"UltraliskCavern";NA;211;0
"Unit";"Zergling";"Larva";213;1
"Unit";"Zergling";"Larva";213;1
"Unit";"Zergling";"Larva";213;1
"Unit";"Zergling";"Larva";213;1
"Unit";"Zergling";"Larva";213;1
"Unit";"Zergling";"Larva";213;1
"Unit";"Zergling";"Larva";213;1
"Unit";"Zergling";"Larva";213;1
"Unit";"Zergling";"Larva";213;1
"Unit";"Zergling";"Larva";213;1
"Unit";"Zergling";"Larva";213;1
"Unit";"Zergling";"Larva";213;1
"Unit";"Hydralisk";"Larva";213;2
"Unit";"Hydralisk";"Larva";213;2
"Unit";"Hydralisk";"Larva";213;2
"Unit";"Hydralisk";"Larva";213;2
"Unit";"Hydralisk";"Larva";213;2
"Unit";"Hydralisk";"Larva";213;2
"Unit";"Hydralisk";"Larva";213;2
"Building";"Hatchery";NA;211;0
"Building";"Spire";NA;211;0
"Unit";"Overlord";"Larva";239;0
"Unit";"Overlord";"Larva";239;0
"Unit";"Overlord";"Larva";239;0
"Building";"Extractor";NA;239;0
"Unit";"Overlord";"Larva";239;0
"Building";"CreepTumor";NA;251;0
"Building";"CreepTumor";NA;251;0
"Unit";"Baneling";"Zergling";251;0
"Unit";"Baneling";"Zergling";251;0
"Unit";"Baneling";"Zergling";251;0
"Unit";"Baneling";"Zergling";251;0
"Unit";"Baneling";"Zergling";251;0
"Unit";"Baneling";"Zergling";251;0
"Unit";"Baneling";"Zergling";251;0
"Unit";"Baneling";"Zergling";251;0
"Unit";"Baneling";"Zergling";251;0
"Unit";"Baneling";"Zergling";251;0
"Unit";"Baneling";"Zergling";251;0
"Unit";"Baneling";"Zergling";251;0
"Unit";"Baneling";"Zergling";251;0
"Unit";"Baneling";"Zergling";251;0
"Unit";"Baneling";"Zergling";251;0
"Unit";"Baneling";"Zergling";251;0
"Unit";"Baneling";"Zergling";251;0
"Unit";"Baneling";"Zergling";251;0
"Unit";"Baneling";"Zergling";251;0
"Unit";"Baneling";"Zergling";251;0
"Unit";"Baneling";"Zergling";251;0
"Unit";"Baneling";"Zergling";251;0
"Unit";"Zergling";"Larva";251;1
"Unit";"Zergling";"Larva";251;1
"Unit";"Zergling";"Larva";251;1
"Unit";"Zergling";"Larva";251;1
"Unit";"Zergling";"Larva";251;1
"Unit";"Zergling";"Larva";251;1
"Unit";"Zergling";"Larva";251;1
"Unit";"Zergling";"Larva";251;1
"Unit";"Zergling";"Larva";251;1
"Unit";"Zergling";"Larva";251;1
"Unit";"Zergling";"Larva";251;1
"Unit";"Zergling";"Larva";251;1
"Unit";"Zergling";"Larva";251;1
"Unit";"Zergling";"Larva";251;1
"Unit";"Zergling";"Larva";251;1
"Unit";"Zergling";"Larva";251;1
"Unit";"Zergling";"Larva";251;1
"Unit";"Zergling";"Larva";251;1
"Unit";"Zergling";"Larva";251;1
"Unit";"Zergling";"Larva";251;1
"Unit";"Zergling";"Larva";251;1
"Unit";"Zergling";"Larva";251;1
"Unit";"Zergling";"Larva";251;1
"Unit";"Zergling";"Larva";251;1
"Unit";"Zergling";"Larva";251;1
"Unit";"Zergling";"Larva";251;1
"Unit";"Zergling";"Larva";251;1
"Unit";"Zergling";"Larva";251;1
"Unit";"Baneling";"Zergling";251;0
"Building";"SporeCrawler";NA;251;0
"Building";"SporeCrawler";NA;251;0
"Unit";"Zergling";"Larva";251;1
"Unit";"Zergling";"Larva";251;1
"Unit";"Zergling";"Larva";251;1
"Unit";"Zergling";"Larva";251;1
"Unit";"Zergling";"Larva";251;1
"Unit";"Zergling";"Larva";251;1
"Unit";"Zergling";"Larva";251;1
"Unit";"Zergling";"Larva";251;1
"Unit";"Zergling";"Larva";251;1
"Unit";"Zergling";"Larva";251;1
"Unit";"Zergling";"Larva";251;1
"Unit";"Zergling";"Larva";251;1
"Unit";"Zergling";"Larva";251;1
"Unit";"Zergling";"Larva";251;1
"Unit";"Zergling";"Larva";251;1
"Unit";"Zergling";"Larva";251;1
"Unit";"Zergling";"Larva";251;1
"Unit";"Zergling";"Larva";251;1
"Unit";"Zergling";"Larva";251;1
"Unit";"Zergling";"Larva";251;1
"Unit";"Zergling";"Larva";251;1
"Unit";"Zergling";"Larva";251;1
"Unit";"Zergling";"Larva";251;1
"Unit";"Zergling";"Larva";251;1
"Unit";"Zergling";"Larva";251;1
"Unit";"Zergling";"Larva";251;1
"Unit";"Zergling";"Larva";305;1
"Unit";"Zergling";"Larva";305;1
"Unit";"Zergling";"Larva";305;1
"Unit";"Zergling";"Larva";305;1
"Unit";"Zergling";"Larva";305;1
"Unit";"Zergling";"Larva";305;1
"Unit";"Zergling";"Larva";305;1
"Unit";"Zergling";"Larva";305;1
"Unit";"Zergling";"Larva";305;1
"Unit";"Zergling";"Larva";305;1
"Unit";"Zergling";"Larva";305;1
"Unit";"Zergling";"Larva";305;1
"Unit";"Zergling";"Larva";305;1
"Unit";"Zergling";"Larva";305;1
"Unit";"Zergling";"Larva";305;1
"Unit";"Zergling";"Larva";305;1
"Unit";"Zergling";"Larva";305;1
"Unit";"Zergling";"Larva";305;1
"Unit";"Zergling";"Larva";305;1
"Unit";"Zergling";"Larva";305;1
"Upgrade";"ChitinousPlating";"UltraliskCavern";251;0
"Unit";"Zergling";"Larva";305;1
"Unit";"Zergling";"Larva";305;1
"Unit";"Zergling";"Larva";305;1
"Unit";"Zergling";"Larva";305;1
"Unit";"Zergling";"Larva";305;1
"Unit";"Zergling";"Larva";305;1
"Unit";"Zergling";"Larva";305;1
"Unit";"Zergling";"Larva";305;1
"Unit";"Zergling";"Larva";305;1
"Unit";"Zergling";"Larva";305;1
"Unit";"Zergling";"Larva";305;1
"Unit";"Zergling";"Larva";305;1
"Unit";"Baneling";"Zergling";325;0
"Unit";"Baneling";"Zergling";325;0
"Unit";"Baneling";"Zergling";325;0
"Unit";"Baneling";"Zergling";325;0
"Unit";"Baneling";"Zergling";325;0
"Unit";"Baneling";"Zergling";325;0
"Unit";"Baneling";"Zergling";325;0
"Unit";"Hydralisk";"Larva";305;2
"Unit";"Hydralisk";"Larva";305;2
"Unit";"Hydralisk";"Larva";305;2
"Unit";"Hydralisk";"Larva";305;2
"Unit";"Hydralisk";"Larva";305;2
"Building";"CreepTumorQueen";NA;347;0
"Building";"CreepTumorQueen";NA;347;0
"Building";"CreepTumorQueen";NA;351;0
"Building";"CreepTumorQueen";NA;351;0
"Building";"CreepTumorQueen";NA;351;0
"Unit";"Ultralisk";"Larva";327;6
"Unit";"Ultralisk";"Larva";327;6
"Unit";"Ultralisk";"Larva";331;6
"Unit";"Ultralisk";"Larva";331;6
"Building";"CreepTumorQueen";NA;351;0
"Unit";"Baneling";"Zergling";351;0
"Unit";"Baneling";"Zergling";351;0
"Unit";"Baneling";"Zergling";351;0
"Unit";"Baneling";"Zergling";351;0
"Unit";"Baneling";"Zergling";351;0
"Building";"CreepTumor";NA;351;0
"Building";"CreepTumor";NA;351;0
"Building";"CreepTumor";NA;375;0
"Building";"Extractor";NA;351;0
"Unit";"Ultralisk";"Larva";351;6
"Unit";"Zergling";"Larva";375;1
"Unit";"Zergling";"Larva";375;1
"Unit";"Zergling";"Larva";375;1
"Unit";"Zergling";"Larva";375;1
"Unit";"Zergling";"Larva";375;1
"Unit";"Zergling";"Larva";375;1
"Unit";"Zergling";"Larva";375;1
"Unit";"Zergling";"Larva";375;1
"Unit";"Zergling";"Larva";375;1
"Unit";"Zergling";"Larva";375;1
"Unit";"Zergling";"Larva";375;1
"Unit";"Zergling";"Larva";375;1
"Unit";"Zergling";"Larva";375;1
"Unit";"Zergling";"Larva";375;1
"Unit";"Zergling";"Larva";375;1
"Unit";"Zergling";"Larva";375;1
"Unit";"Zergling";"Larva";375;1
"Unit";"Zergling";"Larva";375;1
"Unit";"Zergling";"Larva";375;1
"Unit";"Zergling";"Larva";375;1
"Unit";"Zergling";"Larva";375;1
"Unit";"Zergling";"Larva";375;1
"Unit";"Zergling";"Larva";375;1
"Unit";"Zergling";"Larva";375;1
"Unit";"Zergling";"Larva";375;1
"Unit";"Zergling";"Larva";375;1
"Unit";"Zergling";"Larva";375;1
"Unit";"Zergling";"Larva";375;1
"Unit";"Zergling";"Larva";375;1
"Unit";"Zergling";"Larva";375;1
"Unit";"Zergling";"Larva";375;1
"Unit";"Zergling";"Larva";375;1
"Unit";"Zergling";"Larva";375;1
"Unit";"Zergling";"Larva";375;1
"Unit";"Zergling";"Larva";375;1
"Unit";"Zergling";"Larva";375;1
"Upgrade";"ZergMeleeWeaponsLevel3";"EvolutionChamber";279;0
"Upgrade";"ZergGroundArmorsLevel3";"EvolutionChamber";279;0
"Unit";"Queen";"Hatchery";375;2
"Building";"CreepTumor";NA;417;0
"Building";"CreepTumor";NA;417;0
"Building";"CreepTumor";NA;417;0
"Building";"CreepTumor";NA;417;0
"Building";"CreepTumor";NA;417;0
"Building";"CreepTumor";NA;417;0
"Building";"CreepTumor";NA;417;0
"Building";"CreepTumor";NA;417;0
"Unit";"Queen";"Hatchery";375;2
"Unit";"Queen";"Hatchery";375;2
"Unit";"Corruptor";"Larva";417;2
"Unit";"Corruptor";"Larva";417;2
"Unit";"Corruptor";"Larva";417;2
"Unit";"Corruptor";"Larva";417;2
"Unit";"Corruptor";"Larva";417;2
"Unit";"Corruptor";"Larva";417;2
"Unit";"Corruptor";"Larva";417;2
"Unit";"Corruptor";"Larva";417;2
"Unit";"Corruptor";"Larva";417;2
"Unit";"Corruptor";"Larva";417;2
"Building";"CreepTumor";NA;419;0
"Building";"CreepTumor";NA;419;0
"Building";"CreepTumor";NA;421;0
"Building";"CreepTumor";NA;421;0
"Building";"CreepTumor";NA;423;0
"Building";"CreepTumor";NA;423;0
"Building";"CreepTumor";NA;423;0
"Building";"Hatchery";NA;375;0
"Building";"CreepTumor";NA;423;0
"Upgrade";"Burrow";"Hatchery";375;0
"Unit";"Baneling";"Zergling";443;0
"Unit";"Baneling";"Zergling";443;0
"Unit";"Baneling";"Zergling";443;0
"Unit";"Baneling";"Zergling";443;0
"Unit";"Baneling";"Zergling";443;0
"Unit";"Baneling";"Zergling";443;0
"Unit";"Baneling";"Zergling";443;0
"Unit";"Baneling";"Zergling";443;0
"Unit";"Baneling";"Zergling";443;0
"Unit";"Baneling";"Zergling";443;0
"Unit";"Baneling";"Zergling";443;0
"Unit";"Baneling";"Zergling";443;0
"Unit";"Baneling";"Zergling";443;0
"Building";"CreepTumor";NA;443;0
"Building";"Extractor";NA;443;0
"Building";"CreepTumor";NA;443;0
"Building";"CreepTumor";NA;443;0
"Building";"SporeCrawler";NA;443;0
"Unit";"Zergling";"Larva";443;1
"Unit";"Zergling";"Larva";443;1
"Unit";"Zergling";"Larva";443;1
"Unit";"Zergling";"Larva";443;1
"Unit";"Zergling";"Larva";443;1
"Unit";"Zergling";"Larva";443;1
"Unit";"Zergling";"Larva";443;1
"Unit";"Zergling";"Larva";443;1
"Unit";"Zergling";"Larva";443;1
"Unit";"Zergling";"Larva";443;1
"Unit";"Zergling";"Larva";443;1
"Unit";"Zergling";"Larva";443;1
"Unit";"Zergling";"Larva";443;1
"Unit";"Zergling";"Larva";443;1
"Unit";"Zergling";"Larva";443;1
"Unit";"Zergling";"Larva";443;1
"Unit";"Zergling";"Larva";443;1
"Unit";"Zergling";"Larva";443;1
"Unit";"Zergling";"Larva";443;1
"Unit";"Zergling";"Larva";443;1
"Unit";"Zergling";"Larva";443;1
"Unit";"Zergling";"Larva";443;1
"Unit";"Zergling";"Larva";443;1
"Unit";"Zergling";"Larva";443;1
"Unit";"Zergling";"Larva";443;1
"Unit";"Zergling";"Larva";443;1
"Unit";"Zergling";"Larva";443;1
"Unit";"Zergling";"Larva";443;1
"Unit";"Zergling";"Larva";443;1
"Unit";"Zergling";"Larva";443;1
"Unit";"Zergling";"Larva";443;1
"Unit";"Zergling";"Larva";443;1
"Unit";"Zergling";"Larva";443;1
"Unit";"Zergling";"Larva";443;1
"Unit";"Zergling";"Larva";443;1
"Unit";"Zergling";"Larva";443;1
"Unit";"Zergling";"Larva";443;1
"Unit";"Zergling";"Larva";443;1
"Upgrade";"ZergMissileWeaponsLevel1";"EvolutionChamber";443;0
"Unit";"Corruptor";"Larva";484;2
"Unit";"Corruptor";"Larva";484;2
"Unit";"Corruptor";"Larva";484;2
"Unit";"Baneling";"Zergling";484;0
"Building";"CreepTumor";NA;484;0
"Unit";"Baneling";"Zergling";484;0
"Unit";"Baneling";"Zergling";484;0
"Unit";"Baneling";"Zergling";484;0
"Unit";"Baneling";"Zergling";484;0
"Unit";"Baneling";"Zergling";484;0
"Unit";"Baneling";"Zergling";484;0
"Unit";"Baneling";"Zergling";484;0
"Unit";"Baneling";"Zergling";484;0
"Building";"CreepTumor";NA;484;0
"Building";"CreepTumor";NA;484;0
"Building";"CreepTumor";NA;484;0
"Building";"CreepTumor";NA;484;0
"Building";"CreepTumor";NA;484;0
"Building";"CreepTumor";NA;484;0
"Building";"CreepTumor";NA;484;0
"Building";"CreepTumorQueen";NA;490;0
"Building";"Extractor";NA;484;0
"Building";"CreepTumorQueen";NA;490;0
"Building";"CreepTumorQueen";NA;490;0
"Unit";"Baneling";"Zergling";490;0
"Unit";"Baneling";"Zergling";490;0
"Unit";"Baneling";"Zergling";490;0
"Unit";"Baneling";"Zergling";490;0
"Unit";"Baneling";"Zergling";490;0
"Unit";"Baneling";"Zergling";490;0
"Unit";"Baneling";"Zergling";490;0
"Unit";"Baneling";"Zergling";490;0
"Unit";"Baneling";"Zergling";490;0
"Unit";"Baneling";"Zergling";490;0
"Unit";"Baneling";"Zergling";490;0
"Unit";"Baneling";"Zergling";490;0
"Unit";"Baneling";"Zergling";490;0
"Building";"CreepTumor";NA;490;0
"Building";"Extractor";NA;490;0
"Unit";"Baneling";"Zergling";490;0
"Unit";"Baneling";"Zergling";490;0
"Unit";"Baneling";"Zergling";490;0
"Unit";"Baneling";"Zergling";490;0
"Unit";"Baneling";"Zergling";490;0
"Unit";"Baneling";"Zergling";490;0
"Unit";"Baneling";"Zergling";490;0
"Unit";"Baneling";"Zergling";490;0
"Unit";"Baneling";"Zergling";490;0
"Building";"CreepTumorQueen";NA;490;0
"Building";"CreepTumorQueen";NA;490;0
"Building";"CreepTumorQueen";NA;490;0
"Building";"SporeCrawler";NA;490;0
"Unit";"Zergling";"Larva";490;1
"Unit";"Zergling";"Larva";490;1
"Unit";"Zergling";"Larva";490;1
"Unit";"Zergling";"Larva";490;1
"Unit";"Zergling";"Larva";490;1
"Unit";"Zergling";"Larva";490;1
"Unit";"Zergling";"Larva";490;1
"Unit";"Zergling";"Larva";490;1
"Unit";"Zergling";"Larva";490;1
"Unit";"Zergling";"Larva";490;1
"Unit";"Zergling";"Larva";490;1
"Unit";"Zergling";"Larva";490;1
"Unit";"Zergling";"Larva";490;1
"Unit";"Zergling";"Larva";490;1
"Unit";"Zergling";"Larva";490;1
"Unit";"Zergling";"Larva";490;1
"Unit";"Zergling";"Larva";490;1
"Unit";"Zergling";"Larva";490;1
"Unit";"Zergling";"Larva";490;1
"Unit";"Zergling";"Larva";490;1
"Unit";"Zergling";"Larva";490;1
"Unit";"Zergling";"Larva";490;1
"Unit";"Zergling";"Larva";490;1
"Unit";"Zergling";"Larva";490;1
"Unit";"Zergling";"Larva";490;1
"Unit";"Zergling";"Larva";490;1
"Unit";"Zergling";"Larva";490;1
"Unit";"Zergling";"Larva";490;1
"Unit";"Zergling";"Larva";490;1
"Unit";"Zergling";"Larva";490;1
"Unit";"Zergling";"Larva";490;1
"Unit";"Zergling";"Larva";490;1
"Unit";"Zergling";"Larva";490;1
"Unit";"Zergling";"Larva";490;1
"Unit";"Zergling";"Larva";490;1
"Unit";"Zergling";"Larva";490;1
"Unit";"Zergling";"Larva";490;1
"Unit";"Zergling";"Larva";490;1
"Unit";"Ultralisk";"Larva";490;6
"Unit";"Ultralisk";"Larva";490;6
"Unit";"Ultralisk";"Larva";490;6
"Unit";"Ultralisk";"Larva";490;6
"Unit";"Ultralisk";"Larva";490;6
"Unit";"Ultralisk";"Larva";490;6
"Unit";"Ultralisk";"Larva";490;6
"Unit";"Hydralisk";"Larva";490;2
"Unit";"Hydralisk";"Larva";490;2
"Unit";"Hydralisk";"Larva";490;2
"Unit";"Hydralisk";"Larva";490;2
"Unit";"Hydralisk";"Larva";490;2
"Unit";"Hydralisk";"Larva";490;2
"Unit";"Hydralisk";"Larva";490;2
"Unit";"Hydralisk";"Larva";490;2
"Unit";"Hydralisk";"Larva";490;2
"Unit";"Hydralisk";"Larva";490;2
"Unit";"Hydralisk";"Larva";490;2
"Unit";"Hydralisk";"Larva";490;2
"Building";"CreepTumor";NA;570;0
"Building";"CreepTumor";NA;594;0
"Unit";"Baneling";"Zergling";594;0
"Unit";"Baneling";"Zergling";594;0
"Unit";"Baneling";"Zergling";594;0
"Unit";"Baneling";"Zergling";594;0
"Unit";"Baneling";"Zergling";594;0
"Unit";"Baneling";"Zergling";594;0
"Unit";"Baneling";"Zergling";594;0
"Unit";"Baneling";"Zergling";594;0
"Unit";"Baneling";"Zergling";594;0
"Unit";"Baneling";"Zergling";594;0
"Unit";"Baneling";"Zergling";594;0
"Unit";"Baneling";"Zergling";594;0
"Unit";"Baneling";"Zergling";594;0
"Unit";"Baneling";"Zergling";595;0
"Unit";"Baneling";"Zergling";595;0
"Unit";"Baneling";"Zergling";595;0
"Unit";"Baneling";"Zergling";595;0
"Unit";"Baneling";"Zergling";595;0
"Unit";"Baneling";"Zergling";595;0
"Unit";"Ultralisk";"Larva";528;6
"Unit";"Zergling";"Larva";599;1
"Unit";"Zergling";"Larva";599;1
"Upgrade";"ZergMissileWeaponsLevel2";"EvolutionChamber";490;0
"Building";"CreepTumor";NA;607;0
"Building";"CreepTumor";NA;607;0
"Building";"CreepTumor";NA;607;0
"Building";"Hatchery";NA;599;0
"Unit";"Zergling";"Larva";607;1
"Unit";"Zergling";"Larva";607;1
"Unit";"Zergling";"Larva";607;1
"Unit";"Zergling";"Larva";607;1
"Unit";"Zergling";"Larva";607;1
"Unit";"Zergling";"Larva";607;1
"Unit";"Zergling";"Larva";607;1
"Unit";"Zergling";"Larva";607;1
"Building";"CreepTumorQueen";NA;607;0
"Building";"CreepTumorQueen";NA;607;0
"Unit";"Corruptor";"Larva";607;2
"Unit";"Corruptor";"Larva";607;2
"Unit";"Corruptor";"Larva";607;2
"Unit";"Corruptor";"Larva";607;2
"Unit";"Corruptor";"Larva";607;2
"Building";"CreepTumor";NA;615;0
"Building";"CreepTumor";NA;615;0
"Building";"CreepTumor";NA;615;0
"Building";"CreepTumor";NA;615;0
"Unit";"Overlord";"Larva";625;0
"Unit";"Overlord";"Larva";625;0
"Unit";"Overlord";"Larva";625;0
"Unit";"Overlord";"Larva";625;0
"Unit";"Overlord";"Larva";625;0
"Building";"CreepTumor";NA;625;0
"Building";"CreepTumor";NA;625;0
"Unit";"Zergling";"Larva";625;1
"Unit";"Zergling";"Larva";625;1
"Unit";"Zergling";"Larva";625;1
"Unit";"Zergling";"Larva";625;1
"Unit";"Zergling";"Larva";625;1
"Unit";"Zergling";"Larva";625;1
"Unit";"Zergling";"Larva";625;1
"Unit";"Zergling";"Larva";625;1
"Unit";"Zergling";"Larva";625;1
"Unit";"Zergling";"Larva";625;1
"Unit";"Zergling";"Larva";625;1
"Unit";"Zergling";"Larva";625;1
"Building";"CreepTumor";NA;625;0
"Building";"CreepTumor";NA;625;0
"Unit";"Zergling";"Larva";637;1
"Unit";"Zergling";"Larva";637;1
"Unit";"Zergling";"Larva";637;1
"Unit";"Zergling";"Larva";637;1
"Unit";"Zergling";"Larva";637;1
"Unit";"Zergling";"Larva";637;1
"Unit";"Zergling";"Larva";637;1
"Unit";"Zergling";"Larva";637;1
"Building";"CreepTumor";NA;645;0
"Building";"Hatchery";NA;637;0
"Unit";"Baneling";"Zergling";645;0
"Unit";"Baneling";"Zergling";645;0
"Unit";"Baneling";"Zergling";645;0
"Unit";"Baneling";"Zergling";645;0
"Unit";"Baneling";"Zergling";645;0
"Unit";"Baneling";"Zergling";645;0
"Unit";"Baneling";"Zergling";645;0
"Unit";"Baneling";"Zergling";645;0
"Unit";"Baneling";"Zergling";645;0
"Unit";"Baneling";"Zergling";645;0
"Unit";"Baneling";"Zergling";645;0
"Unit";"Baneling";"Zergling";645;0
"Unit";"Baneling";"Zergling";645;0
"Unit";"Baneling";"Zergling";645;0
"Unit";"Baneling";"Zergling";645;0
"Unit";"Baneling";"Zergling";645;0
"Unit";"Baneling";"Zergling";645;0
"Unit";"Baneling";"Zergling";645;0
"Unit";"Baneling";"Zergling";645;0
"Unit";"Baneling";"Zergling";645;0
"Unit";"Baneling";"Zergling";645;0
"Unit";"Baneling";"Zergling";645;0
"Unit";"Baneling";"Zergling";645;0
"Unit";"Baneling";"Zergling";645;0
"Unit";"Baneling";"Zergling";645;0
"Unit";"Baneling";"Zergling";645;0
"Unit";"Baneling";"Zergling";645;0
"Building";"CreepTumor";NA;645;0
"Building";"CreepTumor";NA;645;0
"Building";"CreepTumor";NA;645;0
"Upgrade";"ZergMissileWeaponsLevel3";"EvolutionChamber";625;0
"Building";"SporeCrawler";NA;645;0
"Building";"Extractor";NA;645;0
"Building";"Extractor";NA;645;0
"Unit";"Corruptor";"Larva";645;2
"Unit";"Zergling";"Larva";645;1
"Unit";"Zergling";"Larva";645;1
"Unit";"Zergling";"Larva";647;1
"Unit";"Zergling";"Larva";647;1
"Unit";"Zergling";"Larva";647;1
"Unit";"Zergling";"Larva";647;1
"Unit";"Zergling";"Larva";647;1
"Unit";"Zergling";"Larva";647;1
"Unit";"Zergling";"Larva";647;1
"Unit";"Zergling";"Larva";647;1
"Unit";"Zergling";"Larva";647;1
"Unit";"Zergling";"Larva";647;1
"Unit";"Zergling";"Larva";647;1
"Unit";"Zergling";"Larva";647;1
"Unit";"Zergling";"Larva";647;1
"Unit";"Zergling";"Larva";647;1
"Unit";"Zergling";"Larva";647;1
"Unit";"Zergling";"Larva";647;1
"Unit";"Zergling";"Larva";647;1
"Unit";"Zergling";"Larva";647;1
"Unit";"Zergling";"Larva";647;1
"Unit";"Zergling";"Larva";647;1
"Unit";"Zergling";"Larva";647;1
"Unit";"Zergling";"Larva";647;1
"Unit";"Zergling";"Larva";647;1
"Unit";"Zergling";"Larva";647;1
"Unit";"Zergling";"Larva";647;1
"Unit";"Zergling";"Larva";647;1
"Unit";"Zergling";"Larva";647;1
"Unit";"Zergling";"Larva";647;1
"Unit";"Zergling";"Larva";647;1
"Unit";"Zergling";"Larva";647;1
"Unit";"Zergling";"Larva";647;1
"Unit";"Zergling";"Larva";647;1
"Unit";"Zergling";"Larva";647;1
"Unit";"Zergling";"Larva";647;1
"Unit";"Zergling";"Larva";647;1
"Unit";"Zergling";"Larva";647;1
"Unit";"Zergling";"Larva";647;1
"Unit";"Zergling";"Larva";647;1
"Unit";"Zergling";"Larva";647;1
"Unit";"Zergling";"Larva";647;1
"Unit";"Zergling";"Larva";647;1
"Unit";"Zergling";"Larva";647;1
"Unit";"Zergling";"Larva";647;1
"Unit";"Zergling";"Larva";647;1
"Unit";"Zergling";"Larva";647;1
"Unit";"Zergling";"Larva";647;1
"Unit";"Zergling";"Larva";647;1
"Unit";"Zergling";"Larva";647;1
"Unit";"Zergling";"Larva";647;1
"Unit";"Zergling";"Larva";647;1
"Unit";"Zergling";"Larva";647;1
"Unit";"Zergling";"Larva";647;1
"Unit";"Zergling";"Larva";647;1
"Unit";"Zergling";"Larva";647;1
"Unit";"Overlord";"Larva";647;0
"Unit";"Overlord";"Larva";647;0
"Unit";"Overlord";"Larva";647;0
"Unit";"Zergling";"Larva";647;1
"Unit";"Zergling";"Larva";647;1
"Unit";"Zergling";"Larva";647;1
"Unit";"Zergling";"Larva";647;1
"Unit";"Zergling";"Larva";647;1
"Unit";"Zergling";"Larva";647;1
"Unit";"Zergling";"Larva";647;1
"Unit";"Zergling";"Larva";647;1
"Unit";"Zergling";"Larva";647;1
"Unit";"Zergling";"Larva";647;1
"Unit";"Zergling";"Larva";647;1
"Unit";"Zergling";"Larva";647;1
"Unit";"Zergling";"Larva";647;1
"Unit";"Zergling";"Larva";647;1
"Unit";"Overlord";"Larva";659;0
"Unit";"Overlord";"Larva";667;0
"Unit";"Overlord";"Larva";673;0
"Unit";"Overlord";"Larva";681;0
"Unit";"Overlord";"Larva";689;0
"Unit";"Ultralisk";"Larva";647;6
"Unit";"Ultralisk";"Larva";647;6
"Unit";"Ultralisk";"Larva";647;6
"Unit";"Ultralisk";"Larva";647;6
"Unit";"Ultralisk";"Larva";647;6
"Unit";"Ultralisk";"Larva";647;6
"Unit";"Ultralisk";"Larva";647;6
"Unit";"Corruptor";"Larva";735;2
"Unit";"Corruptor";"Larva";735;2
"Unit";"Corruptor";"Larva";735;2
"Unit";"Corruptor";"Larva";735;2
"Unit";"Corruptor";"Larva";735;2
"Unit";"Corruptor";"Larva";735;2
"Unit";"Baneling";"Zergling";759;0
"Unit";"Baneling";"Zergling";759;0
"Unit";"Baneling";"Zergling";759;0
"Unit";"Baneling";"Zergling";759;0
"Unit";"Baneling";"Zergling";759;0
"Unit";"Baneling";"Zergling";759;0
"Unit";"Baneling";"Zergling";759;0
"Unit";"Baneling";"Zergling";759;0
"Unit";"Baneling";"Zergling";759;0
"Unit";"Baneling";"Zergling";759;0
"Unit";"Baneling";"Zergling";759;0
"Unit";"Baneling";"Zergling";759;0
"Unit";"Baneling";"Zergling";759;0
"Unit";"Baneling";"Zergling";759;0
"Unit";"Hydralisk";"Larva";759;2
"Unit";"Hydralisk";"Larva";759;2
"Unit";"Hydralisk";"Larva";759;2
"Unit";"Hydralisk";"Larva";759;2
"Unit";"Hydralisk";"Larva";759;2
"Unit";"Hydralisk";"Larva";759;2
"Unit";"Hydralisk";"Larva";759;2
"Unit";"Hydralisk";"Larva";759;2
"Unit";"Hydralisk";"Larva";759;2
"Unit";"Hydralisk";"Larva";759;2
"Unit";"Hydralisk";"Larva";759;2
"Unit";"Ultralisk";"Larva";735;6
"Unit";"Ultralisk";"Larva";735;6
"Unit";"Zergling";"Larva";759;1
"Unit";"Zergling";"Larva";759;1
"Unit";"Zergling";"Larva";759;1
"Unit";"Zergling";"Larva";759;1
"Unit";"Zergling";"Larva";759;1
"Unit";"Zergling";"Larva";759;1
"Unit";"Zergling";"Larva";759;1
"Unit";"Zergling";"Larva";759;1
"Unit";"Zergling";"Larva";805;1
"Unit";"Zergling";"Larva";805;1
"Unit";"Zergling";"Larva";815;1
"Unit";"Zergling";"Larva";815;1
"Unit";"Zergling";"Larva";815;1
"Unit";"Zergling";"Larva";815;1
"Unit";"Zergling";"Larva";815;1
"Unit";"Zergling";"Larva";815;1
"Unit";"Zergling";"Larva";815;1
"Unit";"Zergling";"Larva";815;1
"Unit";"Zergling";"Larva";815;1
"Unit";"Zergling";"Larva";815;1
"Unit";"Zergling";"Larva";815;1
"Unit";"Zergling";"Larva";815;1
"Unit";"Zergling";"Larva";815;1
"Unit";"Zergling";"Larva";815;1
"Unit";"Zergling";"Larva";815;1
"Unit";"Zergling";"Larva";815;1
"Unit";"Zergling";"Larva";815;1
"Unit";"Zergling";"Larva";815;1
"Unit";"Zergling";"Larva";815;1
"Unit";"Zergling";"Larva";815;1
"Unit";"Zergling";"Larva";815;1
"Unit";"Zergling";"Larva";815;1
"Unit";"Zergling";"Larva";815;1
"Unit";"Zergling";"Larva";815;1
"Unit";"Zergling";"Larva";815;1
"Unit";"Zergling";"Larva";815;1
"Unit";"Zergling";"Larva";815;1
"Unit";"Zergling";"Larva";815;1
"Unit";"Zergling";"Larva";815;1
"Unit";"Zergling";"Larva";815;1
"Unit";"Zergling";"Larva";815;1
"Unit";"Zergling";"Larva";815;1
"Unit";"Zergling";"Larva";815;1
"Unit";"Zergling";"Larva";815;1
"Unit";"Ultralisk";"Larva";849;6
"Unit";"Ultralisk";"Larva";849;6
"Unit";"Ultralisk";"Larva";849;6
