"type";"unit_name";"on_building";"total_supply";"supply"
"Unit";"Overlord";"Larva";12;0
"Building";"Extractor";NA;18;0
"Building";"SpawningPool";NA;16;0
"Unit";"Zergling";"Larva";21;1
"Unit";"Zergling";"Larva";21;1
"Unit";"Overlord";"Larva";21;0
"Unit";"Queen";"Hatchery";20;2
"Building";"Hatchery";NA;20;0
"Unit";"Overlord";"Larva";27;0
"Building";"RoachWarren";NA;24;0
"Unit";"Queen";"Hatchery";26;2
"Unit";"Roach";"Larva";27;2
"Unit";"Roach";"Larva";27;2
"Unit";"Roach";"Larva";27;2
"Unit";"Roach";"Larva";27;2
"Unit";"Roach";"Larva";29;2
"Unit";"Roach";"Larva";29;2
"Unit";"Overlord";"Larva";44;0
"Building";"Extractor";NA;47;0
"Unit";"Overlord";"Larva";49;0
"Building";"Extractor";NA;62;0
"Building";"SporeCrawler";NA;65;0
"Building";"Extractor";NA;65;0
"Building";"SporeCrawler";NA;65;0
"Unit";"Roach";"Larva";69;2
"Unit";"Overlord";"Larva";69;0
"Unit";"Overlord";"Larva";69;0
"Unit";"Overlord";"Larva";69;0
"Building";"EvolutionChamber";NA;72;0
"Unit";"Roach";"Larva";74;2
"Building";"EvolutionChamber";NA;72;0
"Unit";"Roach";"Larva";76;2
"Unit";"Roach";"Larva";76;2
"Unit";"Roach";"Larva";76;2
"Unit";"Roach";"Larva";76;2
"Unit";"Roach";"Larva";76;2
"Unit";"Roach";"Larva";76;2
"Building";"CreepTumorQueen";NA;90;0
"Building";"SporeCrawler";NA;90;0
"Upgrade";"GlialReconstitution";"RoachWarren";76;0
"Unit";"Roach";"Larva";92;2
"Unit";"Roach";"Larva";92;2
"Unit";"Roach";"Larva";92;2
"Unit";"Roach";"Larva";92;2
"Unit";"Roach";"Larva";92;2
"Unit";"Roach";"Larva";92;2
"Unit";"Roach";"Larva";92;2
"Unit";"Roach";"Larva";92;2
"Unit";"Roach";"Larva";92;2
"Unit";"Overlord";"Larva";92;0
"Unit";"Overlord";"Larva";92;0
"Unit";"Overlord";"Larva";92;0
"Unit";"Overlord";"Larva";92;0
"Unit";"Overlord";"Larva";92;0
"Unit";"Overlord";"Larva";108;0
"Building";"Hatchery";NA;92;0
"Unit";"Roach";"Larva";110;2
"Unit";"Roach";"Larva";110;2
"Unit";"Roach";"Larva";110;2
"Unit";"Roach";"Larva";110;2
"Upgrade";"ZergMissileWeaponsLevel1";"EvolutionChamber";92;0
"Unit";"Queen";"Hatchery";110;2
"Upgrade";"ZergGroundArmorsLevel1";"EvolutionChamber";92;0
"Unit";"Roach";"Larva";116;2
"Unit";"Roach";"Larva";116;2
"Unit";"Roach";"Larva";116;2
"Unit";"Roach";"Larva";116;2
"Unit";"Roach";"Larva";116;2
"Unit";"Roach";"Larva";116;2
"Unit";"Roach";"Larva";116;2
"Building";"HydraliskDen";NA;134;0
"Building";"SporeCrawler";NA;138;0
"Unit";"Roach";"Larva";142;2
"Unit";"Roach";"Larva";142;2
"Unit";"Roach";"Larva";142;2
"Unit";"Roach";"Larva";142;2
"Unit";"Queen";"Hatchery";138;2
"Building";"Extractor";NA;146;0
"Building";"CreepTumorQueen";NA;159;0
"Unit";"Hydralisk";"Larva";154;2
"Unit";"Hydralisk";"Larva";154;2
"Unit";"Hydralisk";"Larva";154;2
"Building";"CreepTumor";NA;159;0
"Unit";"Hydralisk";"Larva";156;2
"Unit";"Roach";"Larva";165;2
"Unit";"Roach";"Larva";165;2
"Unit";"Roach";"Larva";165;2
"Unit";"Roach";"Larva";165;2
"Unit";"Roach";"Larva";165;2
"Unit";"Roach";"Larva";165;2
"Unit";"Roach";"Larva";165;2
"Unit";"Roach";"Larva";165;2
"Unit";"Roach";"Larva";165;2
"Unit";"Roach";"Larva";165;2
"Unit";"Roach";"Larva";165;2
"Unit";"Roach";"Larva";167;2
"Unit";"Roach";"Larva";167;2
"Unit";"Roach";"Larva";167;2
"Unit";"Overlord";"Larva";167;0
"Unit";"Overlord";"Larva";167;0
"Unit";"Overlord";"Larva";167;0
"Unit";"Overlord";"Larva";167;0
"Unit";"Overlord";"Larva";167;0
"Unit";"Overlord";"Larva";169;0
"Upgrade";"EvolveMuscularAugments";"HydraliskDen";159;0
"Building";"Extractor";NA;191;0
"Unit";"Overlord";"Larva";195;0
"Unit";"Roach";"Larva";195;2
"Unit";"Roach";"Larva";195;2
"Unit";"Roach";"Larva";195;2
"Upgrade";"ZergMissileWeaponsLevel2";"EvolutionChamber";146;0
"Upgrade";"ZergGroundArmorsLevel2";"EvolutionChamber";146;0
"Unit";"Roach";"Larva";204;2
"Unit";"Roach";"Larva";204;2
"Unit";"Roach";"Larva";204;2
"Unit";"Roach";"Larva";204;2
"Unit";"Roach";"Larva";204;2
"Unit";"Roach";"Larva";204;2
"Unit";"Roach";"Larva";204;2
"Unit";"Roach";"Larva";204;2
"Unit";"Roach";"Larva";204;2
"Unit";"Roach";"Larva";204;2
"Unit";"Roach";"Larva";204;2
"Unit";"Hydralisk";"Larva";204;2
"Unit";"Hydralisk";"Larva";204;2
"Unit";"Hydralisk";"Larva";204;2
"Unit";"Hydralisk";"Larva";204;2
"Unit";"Hydralisk";"Larva";204;2
"Unit";"Hydralisk";"Larva";204;2
"Unit";"Hydralisk";"Larva";226;2
"Unit";"Hydralisk";"Larva";226;2
"Unit";"Hydralisk";"Larva";226;2
"Unit";"Hydralisk";"Larva";226;2
"Building";"CreepTumor";NA;239;0
"Unit";"Roach";"Larva";237;2
"Unit";"Roach";"Larva";237;2
"Building";"CreepTumorQueen";NA;245;0
"Unit";"Roach";"Larva";239;2
"Unit";"Roach";"Larva";239;2
"Unit";"Roach";"Larva";239;2
"Unit";"Roach";"Larva";239;2
"Unit";"Roach";"Larva";239;2
"Unit";"Roach";"Larva";239;2
"Building";"CreepTumorQueen";NA;247;0
"Unit";"Roach";"Larva";245;2
"Unit";"Roach";"Larva";245;2
"Unit";"Roach";"Larva";245;2
"Unit";"Roach";"Larva";245;2
"Unit";"Roach";"Larva";247;2
"Unit";"Roach";"Larva";261;2
"Unit";"Roach";"Larva";261;2
"Unit";"Roach";"Larva";261;2
"Unit";"Roach";"Larva";273;2
"Unit";"Roach";"Larva";273;2
"Unit";"Roach";"Larva";273;2
"Unit";"Roach";"Larva";273;2
"Unit";"Roach";"Larva";273;2
"Unit";"Roach";"Larva";273;2
"Unit";"Roach";"Larva";273;2
"Unit";"Roach";"Larva";273;2
"Unit";"Roach";"Larva";273;2
"Unit";"Roach";"Larva";273;2
"Building";"Hatchery";NA;226;0
