"type";"unit_name";"on_building";"total_supply";"supply"
"Unit";"Overlord";"Larva";13;0
"Building";"Extractor";NA;18;0
"Unit";"Overlord";"Larva";22;0
"Building";"SpawningPool";NA;19;0
"Building";"Hatchery";NA;17;0
"Unit";"Zergling";"Larva";22;1
"Unit";"Zergling";"Larva";22;1
"Unit";"Zergling";"Larva";22;1
"Unit";"Zergling";"Larva";22;1
"Unit";"Queen";"Hatchery";22;2
"Unit";"Queen";"Hatchery";22;2
"Building";"CreepTumorQueen";NA;34;0
"Unit";"Overlord";"Larva";36;0
"Unit";"Queen";"Hatchery";34;2
"Unit";"Overlord";"Larva";36;0
"Building";"CreepTumor";NA;39;0
"Building";"Hatchery";NA;27;0
"Unit";"Overlord";"Larva";40;0
"Unit";"Zergling";"Larva";40;1
"Unit";"Zergling";"Larva";40;1
"Building";"CreepTumorQueen";NA;46;0
"Unit";"Overlord";"Larva";46;0
"Building";"CreepTumor";NA;48;0
"Building";"CreepTumor";NA;48;0
"Unit";"Queen";"Hatchery";46;2
"Unit";"Queen";"Hatchery";46;2
"Building";"CreepTumorQueen";NA;66;0
"Unit";"Zergling";"Larva";65;1
"Unit";"Zergling";"Larva";65;1
"Building";"CreepTumor";NA;66;0
"Building";"EvolutionChamber";NA;60;0
"Unit";"Zergling";"Larva";66;1
"Unit";"Zergling";"Larva";66;1
"Building";"EvolutionChamber";NA;62;0
"Unit";"Zergling";"Larva";67;1
"Unit";"Zergling";"Larva";67;1
"Unit";"Zergling";"Larva";67;1
"Unit";"Zergling";"Larva";67;1
"Unit";"Zergling";"Larva";67;1
"Unit";"Zergling";"Larva";67;1
"Unit";"Zergling";"Larva";67;1
"Unit";"Zergling";"Larva";67;1
"Unit";"Overlord";"Larva";69;0
"Unit";"Overlord";"Larva";69;0
"Building";"CreepTumorQueen";NA;85;0
"Building";"CreepTumor";NA;85;0
"Building";"CreepTumor";NA;85;0
"Building";"CreepTumor";NA;85;0
"Building";"Extractor";NA;85;0
"Building";"Extractor";NA;85;0
"Unit";"Queen";"Hatchery";81;2
"Unit";"Queen";"Hatchery";81;2
"Unit";"Queen";"Hatchery";81;2
"Unit";"Overlord";"Larva";91;0
"Unit";"Zergling";"Larva";91;1
"Unit";"Zergling";"Larva";91;1
"Unit";"Zergling";"Larva";91;1
"Unit";"Zergling";"Larva";91;1
"Building";"SporeCrawler";NA;103;0
"Unit";"Zergling";"Larva";104;1
"Unit";"Zergling";"Larva";104;1
"Unit";"Zergling";"Larva";104;1
"Unit";"Zergling";"Larva";104;1
"Unit";"Zergling";"Larva";104;1
"Unit";"Zergling";"Larva";104;1
"Unit";"Zergling";"Larva";109;1
"Unit";"Zergling";"Larva";109;1
"Unit";"Zergling";"Larva";109;1
"Unit";"Zergling";"Larva";109;1
"Building";"BanelingNest";NA;91;0
"Unit";"Zergling";"Larva";109;1
"Unit";"Zergling";"Larva";109;1
"Building";"SporeCrawler";NA;115;0
"Building";"SporeCrawler";NA;115;0
"Building";"Extractor";NA;115;0
"Building";"Extractor";NA;115;0
"Unit";"Queen";"Hatchery";109;2
"Unit";"Queen";"Hatchery";109;2
"Unit";"Queen";"Hatchery";109;2
"Building";"CreepTumor";NA;121;0
"Building";"CreepTumor";NA;123;0
"Building";"CreepTumor";NA;132;0
"Building";"CreepTumor";NA;132;0
"Building";"Extractor";NA;121;0
"Building";"CreepTumorQueen";NA;132;0
"Building";"CreepTumorQueen";NA;132;0
"Unit";"Zergling";"Larva";138;1
"Unit";"Zergling";"Larva";138;1
"Unit";"Zergling";"Larva";138;1
"Unit";"Zergling";"Larva";138;1
"Unit";"Zergling";"Larva";138;1
"Unit";"Zergling";"Larva";138;1
"Unit";"Zergling";"Larva";138;1
"Unit";"Zergling";"Larva";138;1
"Unit";"Zergling";"Larva";138;1
"Unit";"Zergling";"Larva";138;1
"Unit";"Zergling";"Larva";138;1
"Unit";"Zergling";"Larva";138;1
"Upgrade";"ZergMeleeWeaponsLevel1";"EvolutionChamber";104;0
"Upgrade";"ZergGroundArmorsLevel1";"EvolutionChamber";104;0
"Building";"CreepTumorQueen";NA;140;0
"Unit";"Overlord";"Larva";138;0
"Unit";"Zergling";"Larva";138;1
"Unit";"Zergling";"Larva";138;1
"Building";"CreepTumorQueen";NA;140;0
"Unit";"Overlord";"Larva";140;0
"Building";"CreepTumor";NA;150;0
"Building";"CreepTumor";NA;152;0
"Building";"CreepTumor";NA;152;0
"Unit";"Overlord";"Larva";140;0
"Building";"CreepTumor";NA;152;0
"Building";"CreepTumor";NA;152;0
"Building";"CreepTumor";NA;154;0
"Unit";"Overlord";"Larva";154;0
"Unit";"Overlord";"Larva";154;0
"Unit";"Baneling";"Zergling";154;0
"Unit";"Baneling";"Zergling";154;0
"Unit";"Zergling";"Larva";154;1
"Unit";"Zergling";"Larva";154;1
"Unit";"Baneling";"Zergling";154;0
"Unit";"Zergling";"Larva";154;1
"Unit";"Zergling";"Larva";154;1
"Unit";"Zergling";"Larva";154;1
"Unit";"Zergling";"Larva";154;1
"Unit";"Zergling";"Larva";154;1
"Unit";"Zergling";"Larva";154;1
"Unit";"Zergling";"Larva";154;1
"Unit";"Zergling";"Larva";154;1
"Unit";"Baneling";"Zergling";154;0
"Unit";"Baneling";"Zergling";154;0
"Building";"CreepTumor";NA;154;0
"Building";"CreepTumor";NA;154;0
"Unit";"Zergling";"Larva";154;1
"Unit";"Zergling";"Larva";154;1
"Unit";"Zergling";"Larva";154;1
"Unit";"Zergling";"Larva";154;1
"Unit";"Zergling";"Larva";154;1
"Unit";"Zergling";"Larva";154;1
"Unit";"Zergling";"Larva";154;1
"Unit";"Zergling";"Larva";154;1
"Unit";"Zergling";"Larva";154;1
"Unit";"Zergling";"Larva";154;1
"Unit";"Zergling";"Larva";154;1
"Unit";"Zergling";"Larva";154;1
"Building";"CreepTumorQueen";NA;154;0
"Building";"CreepTumorQueen";NA;156;0
"Building";"CreepTumor";NA;156;0
"Unit";"Queen";"Hatchery";152;2
"Unit";"Queen";"Hatchery";152;2
"Building";"Hatchery";NA;132;0
"Building";"CreepTumor";NA;164;0
"Building";"CreepTumor";NA;164;0
"Unit";"Overlord";"Larva";154;0
"Building";"CreepTumor";NA;164;0
"Building";"Hatchery";NA;138;0
"Building";"CreepTumor";NA;182;0
"Building";"CreepTumor";NA;182;0
"Building";"CreepTumor";NA;182;0
"Unit";"Overlord";"Larva";180;0
"Unit";"Overlord";"Larva";180;0
"Building";"CreepTumor";NA;182;0
"Building";"HydraliskDen";NA;180;0
"Building";"CreepTumor";NA;192;0
"Building";"CreepTumor";NA;192;0
"Unit";"Overlord";"Larva";182;0
"Building";"CreepTumor";NA;192;0
"Building";"InfestationPit";NA;180;0
"Unit";"Overlord";"Larva";192;0
"Unit";"Hydralisk";"Larva";192;2
"Unit";"Hydralisk";"Larva";192;2
"Unit";"Hydralisk";"Larva";192;2
"Unit";"Hydralisk";"Larva";192;2
"Unit";"Hydralisk";"Larva";192;2
"Unit";"Hydralisk";"Larva";192;2
"Unit";"Hydralisk";"Larva";192;2
"Unit";"Hydralisk";"Larva";192;2
"Unit";"Hydralisk";"Larva";192;2
"Unit";"Hydralisk";"Larva";192;2
"Unit";"Hydralisk";"Larva";192;2
"Unit";"Hydralisk";"Larva";192;2
"Unit";"Hydralisk";"Larva";192;2
"Unit";"Hydralisk";"Larva";192;2
"Unit";"Hydralisk";"Larva";192;2
"Unit";"Hydralisk";"Larva";192;2
"Building";"Extractor";NA;206;0
"Building";"Extractor";NA;206;0
"Unit";"Hydralisk";"Larva";210;2
"Unit";"Hydralisk";"Larva";210;2
"Unit";"Hydralisk";"Larva";210;2
"Unit";"Hydralisk";"Larva";210;2
"Upgrade";"ZergMissileWeaponsLevel1";"EvolutionChamber";182;0
"Unit";"Overlord";"Larva";224;0
"Building";"CreepTumor";NA;224;0
"Unit";"Overlord";"Larva";224;0
"Building";"CreepTumor";NA;224;0
"Building";"CreepTumor";NA;224;0
"Unit";"Hydralisk";"Larva";224;2
"Unit";"Hydralisk";"Larva";224;2
"Unit";"Overlord";"Larva";224;0
"Building";"CreepTumorQueen";NA;232;0
"Building";"CreepTumor";NA;232;0
"Unit";"Baneling";"Zergling";230;0
"Unit";"Baneling";"Zergling";232;0
"Unit";"Baneling";"Zergling";232;0
"Unit";"Baneling";"Zergling";232;0
"Unit";"Baneling";"Zergling";232;0
"Building";"CreepTumorQueen";NA;232;0
"Unit";"Baneling";"Zergling";232;0
"Unit";"Baneling";"Zergling";232;0
"Upgrade";"EvolveGroovedSpines";"HydraliskDen";192;0
"Building";"CreepTumor";NA;232;0
"Building";"CreepTumorQueen";NA;232;0
"Building";"CreepTumorQueen";NA;236;0
"Upgrade";"ZergGroundArmorsLevel2";"EvolutionChamber";192;0
"Building";"Hatchery";NA;224;0
"Building";"CreepTumor";NA;236;0
"Building";"Extractor";NA;236;0
"Unit";"Overlord";"Larva";236;0
"Unit";"Overlord";"Larva";236;0
"Unit";"Overlord";"Larva";236;0
"Building";"CreepTumor";NA;236;0
"Building";"CreepTumor";NA;236;0
"Building";"CreepTumor";NA;236;0
"Building";"CreepTumor";NA;236;0
"Building";"CreepTumor";NA;236;0
"Building";"CreepTumor";NA;236;0
"Building";"CreepTumor";NA;236;0
"Building";"CreepTumorQueen";NA;236;0
"Building";"CreepTumorQueen";NA;236;0
"Upgrade";"EvolveMuscularAugments";"HydraliskDen";236;0
"Building";"CreepTumor";NA;236;0
"Building";"CreepTumor";NA;236;0
"Building";"Extractor";NA;236;0
"Building";"Extractor";NA;236;0
"Building";"CreepTumor";NA;236;0
"Building";"CreepTumor";NA;236;0
"Building";"CreepTumor";NA;236;0
"Building";"CreepTumor";NA;236;0
"Building";"CreepTumor";NA;236;0
"Unit";"Viper";"Larva";236;3
"Building";"CreepTumor";NA;236;0
"Unit";"Viper";"Larva";236;3
"Building";"CreepTumorQueen";NA;236;0
"Building";"CreepTumorQueen";NA;236;0
"Building";"CreepTumorQueen";NA;236;0
"Unit";"Viper";"Larva";236;3
"Unit";"Baneling";"Zergling";243;0
"Unit";"Baneling";"Zergling";243;0
"Unit";"Baneling";"Zergling";243;0
"Unit";"Baneling";"Zergling";243;0
"Unit";"Baneling";"Zergling";243;0
"Unit";"Baneling";"Zergling";243;0
"Unit";"Baneling";"Zergling";243;0
"Unit";"Baneling";"Zergling";243;0
"Unit";"Baneling";"Zergling";243;0
"Unit";"Baneling";"Zergling";243;0
"Unit";"Zergling";"Larva";239;1
"Unit";"Zergling";"Larva";239;1
"Unit";"Zergling";"Larva";239;1
"Unit";"Zergling";"Larva";239;1
"Unit";"Zergling";"Larva";239;1
"Unit";"Zergling";"Larva";239;1
"Unit";"Zergling";"Larva";239;1
"Unit";"Zergling";"Larva";239;1
"Unit";"Zergling";"Larva";239;1
"Unit";"Zergling";"Larva";239;1
"Unit";"Baneling";"Zergling";243;0
"Building";"CreepTumorQueen";NA;243;0
"Building";"CreepTumor";NA;243;0
"Building";"CreepTumor";NA;243;0
"Building";"CreepTumor";NA;243;0
"Building";"CreepTumor";NA;243;0
"Building";"CreepTumor";NA;243;0
"Upgrade";"ZergMissileWeaponsLevel2";"EvolutionChamber";236;0
"Building";"CreepTumor";NA;256;0
"Building";"CreepTumor";NA;256;0
"Unit";"Baneling";"Zergling";256;0
"Unit";"Baneling";"Zergling";256;0
"Unit";"Baneling";"Zergling";256;0
"Unit";"Baneling";"Zergling";256;0
"Unit";"Baneling";"Zergling";256;0
"Unit";"Baneling";"Zergling";256;0
"Unit";"Baneling";"Zergling";256;0
"Unit";"Baneling";"Zergling";256;0
"Unit";"Zergling";"Larva";256;1
"Unit";"Zergling";"Larva";256;1
"Building";"CreepTumor";NA;256;0
"Building";"Spire";NA;239;0
"Unit";"Hydralisk";"Larva";258;2
"Unit";"Hydralisk";"Larva";258;2
"Unit";"Hydralisk";"Larva";258;2
"Unit";"Hydralisk";"Larva";258;2
"Unit";"Hydralisk";"Larva";258;2
"Unit";"Hydralisk";"Larva";258;2
"Unit";"Hydralisk";"Larva";258;2
"Unit";"Hydralisk";"Larva";258;2
"Unit";"Hydralisk";"Larva";258;2
"Unit";"Hydralisk";"Larva";258;2
"Unit";"Hydralisk";"Larva";258;2
"Unit";"Hydralisk";"Larva";258;2
"Unit";"Hydralisk";"Larva";258;2
"Unit";"Hydralisk";"Larva";258;2
"Unit";"Zergling";"Larva";258;1
"Unit";"Zergling";"Larva";258;1
"Unit";"Zergling";"Larva";258;1
"Unit";"Zergling";"Larva";258;1
"Unit";"Zergling";"Larva";258;1
"Unit";"Zergling";"Larva";258;1
"Unit";"Zergling";"Larva";258;1
"Unit";"Zergling";"Larva";258;1
"Unit";"Zergling";"Larva";258;1
"Unit";"Zergling";"Larva";258;1
"Unit";"Zergling";"Larva";258;1
"Unit";"Zergling";"Larva";258;1
"Unit";"Zergling";"Larva";258;1
"Unit";"Zergling";"Larva";258;1
"Unit";"Zergling";"Larva";258;1
"Unit";"Zergling";"Larva";258;1
"Unit";"Zergling";"Larva";258;1
"Unit";"Zergling";"Larva";258;1
"Unit";"Zergling";"Larva";258;1
"Unit";"Zergling";"Larva";258;1
"Unit";"Zergling";"Larva";258;1
"Unit";"Zergling";"Larva";258;1
"Unit";"Zergling";"Larva";258;1
"Unit";"Zergling";"Larva";258;1
"Unit";"Zergling";"Larva";258;1
"Unit";"Zergling";"Larva";258;1
"Unit";"Zergling";"Larva";258;1
"Unit";"Zergling";"Larva";258;1
"Unit";"Zergling";"Larva";258;1
"Unit";"Zergling";"Larva";258;1
"Unit";"Zergling";"Larva";258;1
"Unit";"Zergling";"Larva";258;1
"Unit";"Zergling";"Larva";258;1
"Unit";"Zergling";"Larva";258;1
"Unit";"Zergling";"Larva";258;1
"Unit";"Zergling";"Larva";258;1
"Unit";"Hydralisk";"Larva";258;2
"Unit";"Hydralisk";"Larva";258;2
"Unit";"Hydralisk";"Larva";258;2
"Unit";"Hydralisk";"Larva";258;2
"Unit";"Hydralisk";"Larva";258;2
"Unit";"Hydralisk";"Larva";258;2
"Unit";"Hydralisk";"Larva";258;2
"Unit";"Hydralisk";"Larva";258;2
"Upgrade";"ZergGroundArmorsLevel3";"EvolutionChamber";236;0
"Building";"CreepTumor";NA;338;0
"Building";"CreepTumor";NA;338;0
"Unit";"Hydralisk";"Larva";330;2
"Building";"CreepTumor";NA;338;0
"Unit";"Hydralisk";"Larva";332;2
"Unit";"Hydralisk";"Larva";332;2
"Unit";"Hydralisk";"Larva";332;2
"Unit";"Hydralisk";"Larva";336;2
"Building";"CreepTumor";NA;338;0
"Building";"CreepTumor";NA;338;0
"Building";"CreepTumor";NA;338;0
"Building";"CreepTumor";NA;338;0
"Building";"CreepTumor";NA;338;0
"Unit";"Baneling";"Zergling";348;0
"Unit";"Baneling";"Zergling";348;0
"Unit";"Baneling";"Zergling";348;0
"Unit";"Baneling";"Zergling";348;0
"Unit";"Baneling";"Zergling";348;0
"Unit";"Baneling";"Zergling";348;0
"Unit";"Baneling";"Zergling";348;0
"Unit";"Baneling";"Zergling";348;0
"Unit";"Baneling";"Zergling";348;0
"Unit";"Baneling";"Zergling";348;0
"Unit";"Baneling";"Zergling";348;0
"Unit";"Baneling";"Zergling";348;0
"Unit";"Baneling";"Zergling";348;0
"Building";"CreepTumor";NA;348;0
"Building";"CreepTumor";NA;348;0
"Building";"CreepTumor";NA;348;0
"Unit";"Zergling";"Larva";348;1
"Unit";"Zergling";"Larva";348;1
"Unit";"Zergling";"Larva";348;1
"Unit";"Zergling";"Larva";348;1
"Unit";"Zergling";"Larva";348;1
"Unit";"Zergling";"Larva";348;1
"Unit";"Zergling";"Larva";348;1
"Unit";"Zergling";"Larva";348;1
"Unit";"Zergling";"Larva";348;1
"Unit";"Zergling";"Larva";348;1
"Unit";"Zergling";"Larva";348;1
"Unit";"Zergling";"Larva";348;1
"Building";"CreepTumorQueen";NA;348;0
"Building";"CreepTumorQueen";NA;348;0
"Building";"CreepTumorQueen";NA;348;0
"Building";"Hatchery";NA;330;0
"Building";"UltraliskCavern";NA;338;0
"Unit";"Zergling";"Larva";360;1
"Unit";"Zergling";"Larva";360;1
"Unit";"Zergling";"Larva";360;1
"Unit";"Zergling";"Larva";360;1
"Unit";"Zergling";"Larva";360;1
"Unit";"Zergling";"Larva";360;1
"Unit";"Zergling";"Larva";360;1
"Unit";"Zergling";"Larva";360;1
"Unit";"Zergling";"Larva";360;1
"Unit";"Zergling";"Larva";360;1
"Unit";"Zergling";"Larva";360;1
"Unit";"Zergling";"Larva";360;1
"Unit";"Zergling";"Larva";360;1
"Unit";"Zergling";"Larva";360;1
"Unit";"Zergling";"Larva";360;1
"Unit";"Zergling";"Larva";360;1
"Unit";"Zergling";"Larva";360;1
"Unit";"Zergling";"Larva";360;1
"Unit";"Zergling";"Larva";360;1
"Unit";"Zergling";"Larva";360;1
"Unit";"Zergling";"Larva";360;1
"Unit";"Zergling";"Larva";360;1
"Unit";"Zergling";"Larva";360;1
"Unit";"Zergling";"Larva";360;1
"Unit";"Zergling";"Larva";360;1
"Unit";"Zergling";"Larva";360;1
"Unit";"Zergling";"Larva";360;1
"Unit";"Zergling";"Larva";360;1
"Unit";"Zergling";"Larva";360;1
"Unit";"Zergling";"Larva";360;1
"Unit";"Zergling";"Larva";360;1
"Unit";"Zergling";"Larva";360;1
"Unit";"Zergling";"Larva";360;1
"Unit";"Zergling";"Larva";360;1
"Building";"CreepTumor";NA;360;0
"Unit";"Viper";"Larva";360;3
"Building";"CreepTumor";NA;360;0
"Unit";"Viper";"Larva";360;3
"Unit";"Viper";"Larva";360;3
"Building";"CreepTumor";NA;360;0
"Building";"CreepTumor";NA;360;0
"Building";"CreepTumor";NA;360;0
"Building";"CreepTumor";NA;360;0
"Building";"CreepTumor";NA;360;0
"Building";"CreepTumor";NA;360;0
"Building";"CreepTumorQueen";NA;394;0
"Building";"CreepTumorQueen";NA;400;0
"Building";"Hatchery";NA;348;0
"Unit";"Hydralisk";"Larva";408;2
"Unit";"Hydralisk";"Larva";408;2
"Unit";"Hydralisk";"Larva";408;2
"Unit";"Hydralisk";"Larva";408;2
"Unit";"Hydralisk";"Larva";408;2
"Unit";"Hydralisk";"Larva";408;2
"Unit";"Zergling";"Larva";408;1
"Unit";"Zergling";"Larva";408;1
"Unit";"Zergling";"Larva";408;1
"Unit";"Zergling";"Larva";408;1
"Unit";"Zergling";"Larva";408;1
"Unit";"Zergling";"Larva";408;1
"Unit";"Zergling";"Larva";408;1
"Unit";"Zergling";"Larva";408;1
"Unit";"Zergling";"Larva";408;1
"Unit";"Zergling";"Larva";408;1
"Unit";"Zergling";"Larva";408;1
"Unit";"Zergling";"Larva";408;1
"Unit";"Zergling";"Larva";408;1
"Unit";"Zergling";"Larva";408;1
"Unit";"Zergling";"Larva";408;1
"Unit";"Zergling";"Larva";408;1
"Unit";"Zergling";"Larva";408;1
"Unit";"Zergling";"Larva";408;1
"Unit";"Hydralisk";"Larva";408;2
"Unit";"Hydralisk";"Larva";408;2
"Unit";"Hydralisk";"Larva";408;2
"Unit";"Hydralisk";"Larva";408;2
"Unit";"Hydralisk";"Larva";408;2
"Unit";"Hydralisk";"Larva";408;2
"Upgrade";"ZergMeleeWeaponsLevel2";"EvolutionChamber";348;0
"Building";"CreepTumor";NA;420;0
"Building";"CreepTumor";NA;420;0
"Building";"CreepTumor";NA;420;0
"Building";"CreepTumor";NA;420;0
"Unit";"Baneling";"Zergling";450;0
"Unit";"Baneling";"Zergling";450;0
"Unit";"Baneling";"Zergling";450;0
"Unit";"Baneling";"Zergling";450;0
"Unit";"Baneling";"Zergling";450;0
"Unit";"Baneling";"Zergling";450;0
"Unit";"Baneling";"Zergling";450;0
"Unit";"Baneling";"Zergling";450;0
"Unit";"Baneling";"Zergling";450;0
"Unit";"Baneling";"Zergling";450;0
"Unit";"Baneling";"Zergling";450;0
"Unit";"Baneling";"Zergling";450;0
"Unit";"Baneling";"Zergling";450;0
"Unit";"Baneling";"Zergling";450;0
"Unit";"Baneling";"Zergling";450;0
"Unit";"Baneling";"Zergling";450;0
"Unit";"Baneling";"Zergling";450;0
"Unit";"Baneling";"Zergling";450;0
"Unit";"Baneling";"Zergling";450;0
"Upgrade";"ZergMissileWeaponsLevel3";"EvolutionChamber";348;0
"Unit";"Hydralisk";"Larva";450;2
"Unit";"Hydralisk";"Larva";450;2
"Unit";"Hydralisk";"Larva";450;2
"Building";"CreepTumor";NA;450;0
"Building";"CreepTumor";NA;450;0
"Building";"CreepTumor";NA;450;0
"Building";"CreepTumorQueen";NA;457;0
"Building";"CreepTumorQueen";NA;457;0
"Upgrade";"ChitinousPlating";"UltraliskCavern";457;0
"Unit";"Zergling";"Larva";470;1
"Unit";"Zergling";"Larva";470;1
"Unit";"Zergling";"Larva";470;1
"Unit";"Zergling";"Larva";470;1
"Unit";"Zergling";"Larva";470;1
"Unit";"Zergling";"Larva";470;1
"Unit";"Hydralisk";"Larva";470;2
"Unit";"Hydralisk";"Larva";470;2
"Unit";"Hydralisk";"Larva";470;2
"Unit";"Hydralisk";"Larva";470;2
"Unit";"Hydralisk";"Larva";470;2
"Unit";"Hydralisk";"Larva";470;2
"Unit";"Hydralisk";"Larva";470;2
"Unit";"Hydralisk";"Larva";470;2
"Unit";"Hydralisk";"Larva";470;2
"Unit";"Hydralisk";"Larva";470;2
"Unit";"Hydralisk";"Larva";496;2
"Unit";"Queen";"Hatchery";508;2
"Unit";"Queen";"Hatchery";508;2
"Building";"CreepTumor";NA;514;0
"Building";"CreepTumor";NA;515;0
"Unit";"Hydralisk";"Larva";510;2
"Unit";"Hydralisk";"Larva";510;2
"Unit";"Hydralisk";"Larva";510;2
"Unit";"Ultralisk";"Larva";518;6
"Building";"CreepTumor";NA;534;0
"Unit";"Zergling";"Larva";528;1
"Unit";"Zergling";"Larva";528;1
"Unit";"Zergling";"Larva";528;1
"Unit";"Zergling";"Larva";528;1
"Building";"CreepTumor";NA;534;0
"Unit";"Zergling";"Larva";528;1
"Unit";"Zergling";"Larva";528;1
"Unit";"Zergling";"Larva";528;1
"Unit";"Zergling";"Larva";528;1
"Building";"CreepTumor";NA;534;0
"Unit";"Zergling";"Larva";528;1
"Unit";"Zergling";"Larva";528;1
"Unit";"Zergling";"Larva";528;1
"Unit";"Zergling";"Larva";528;1
"Building";"Hatchery";NA;510;0
"Building";"CreepTumorQueen";NA;546;0
"Building";"CreepTumorQueen";NA;546;0
"Unit";"Ultralisk";"Larva";528;6
"Unit";"Ultralisk";"Larva";528;6
"Unit";"Ultralisk";"Larva";528;6
"Unit";"Zergling";"Larva";546;1
"Unit";"Zergling";"Larva";546;1
"Building";"CreepTumor";NA;564;0
"Building";"CreepTumorQueen";NA;564;0
"Building";"CreepTumor";NA;596;0
"Building";"Hatchery";NA;546;0
"Building";"CreepTumor";NA;596;0
"Building";"CreepTumor";NA;596;0
"Unit";"Zergling";"Larva";596;1
"Unit";"Zergling";"Larva";596;1
"Building";"CreepTumor";NA;596;0
"Building";"CreepTumor";NA;598;0
"Building";"CreepTumor";NA;598;0
"Building";"CreepTumorQueen";NA;601;0
"Unit";"Zergling";"Larva";601;1
"Unit";"Zergling";"Larva";601;1
"Unit";"Zergling";"Larva";601;1
"Unit";"Zergling";"Larva";601;1
"Unit";"Zergling";"Larva";601;1
"Unit";"Zergling";"Larva";601;1
"Unit";"Zergling";"Larva";601;1
"Unit";"Zergling";"Larva";601;1
"Unit";"Zergling";"Larva";601;1
"Unit";"Zergling";"Larva";601;1
"Unit";"Zergling";"Larva";601;1
"Unit";"Zergling";"Larva";601;1
"Unit";"Zergling";"Larva";601;1
"Unit";"Zergling";"Larva";601;1
"Unit";"Zergling";"Larva";601;1
"Unit";"Zergling";"Larva";601;1
"Unit";"Zergling";"Larva";601;1
"Unit";"Zergling";"Larva";601;1
"Unit";"Zergling";"Larva";601;1
"Unit";"Zergling";"Larva";601;1
"Unit";"Zergling";"Larva";601;1
"Unit";"Zergling";"Larva";601;1
"Building";"CreepTumorQueen";NA;601;0
"Building";"CreepTumorQueen";NA;601;0
"Upgrade";"ZergMeleeWeaponsLevel3";"EvolutionChamber";546;0
"Building";"Hatchery";NA;596;0
"Building";"Hatchery";NA;596;0
"Building";"SpineCrawler";NA;601;0
"Building";"SpineCrawler";NA;601;0
"Building";"CreepTumorQueen";NA;631;0
"Building";"CreepTumorQueen";NA;635;0
"Unit";"Baneling";"Zergling";635;0
"Unit";"Baneling";"Zergling";635;0
"Unit";"Baneling";"Zergling";635;0
"Unit";"Baneling";"Zergling";635;0
"Unit";"Baneling";"Zergling";635;0
"Unit";"Baneling";"Zergling";635;0
"Unit";"Baneling";"Zergling";635;0
"Unit";"Baneling";"Zergling";635;0
"Unit";"Baneling";"Zergling";635;0
"Unit";"Baneling";"Zergling";635;0
"Unit";"Baneling";"Zergling";635;0
"Building";"Hatchery";NA;601;0
"Building";"SpineCrawler";NA;623;0
"Building";"SpineCrawler";NA;623;0
"Building";"SpineCrawler";NA;624;0
"Building";"SpineCrawler";NA;635;0
"Unit";"Zergling";"Larva";643;1
"Unit";"Zergling";"Larva";643;1
"Unit";"Zergling";"Larva";643;1
"Unit";"Zergling";"Larva";643;1
"Unit";"Zergling";"Larva";643;1
"Unit";"Zergling";"Larva";643;1
"Unit";"Zergling";"Larva";643;1
"Unit";"Zergling";"Larva";643;1
"Unit";"Zergling";"Larva";643;1
"Unit";"Zergling";"Larva";643;1
"Unit";"Zergling";"Larva";643;1
"Unit";"Zergling";"Larva";643;1
"Unit";"Zergling";"Larva";643;1
"Unit";"Zergling";"Larva";643;1
"Unit";"Zergling";"Larva";643;1
"Unit";"Zergling";"Larva";643;1
"Unit";"Zergling";"Larva";643;1
"Unit";"Zergling";"Larva";643;1
"Unit";"Zergling";"Larva";643;1
"Unit";"Zergling";"Larva";643;1
"Unit";"Zergling";"Larva";643;1
"Unit";"Zergling";"Larva";643;1
"Unit";"Zergling";"Larva";643;1
"Unit";"Zergling";"Larva";643;1
"Unit";"Zergling";"Larva";643;1
"Unit";"Zergling";"Larva";643;1
"Unit";"Zergling";"Larva";643;1
"Unit";"Zergling";"Larva";643;1
"Building";"CreepTumor";NA;643;0
"Building";"CreepTumor";NA;671;0
"Building";"CreepTumor";NA;671;0
"Unit";"Baneling";"Zergling";671;0
"Unit";"Baneling";"Zergling";671;0
"Unit";"Baneling";"Zergling";671;0
"Unit";"Baneling";"Zergling";671;0
"Unit";"Baneling";"Zergling";671;0
"Unit";"Baneling";"Zergling";671;0
"Unit";"Baneling";"Zergling";671;0
"Unit";"Baneling";"Zergling";671;0
"Unit";"Baneling";"Zergling";671;0
"Unit";"Baneling";"Zergling";671;0
"Unit";"Baneling";"Zergling";671;0
"Unit";"Baneling";"Zergling";671;0
"Unit";"Baneling";"Zergling";671;0
"Unit";"Baneling";"Zergling";671;0
"Unit";"Baneling";"Zergling";671;0
"Unit";"Baneling";"Zergling";671;0
"Unit";"Baneling";"Zergling";671;0
"Unit";"Baneling";"Zergling";671;0
"Unit";"Baneling";"Zergling";671;0
"Unit";"Baneling";"Zergling";671;0
"Unit";"Baneling";"Zergling";671;0
"Unit";"Baneling";"Zergling";671;0
"Unit";"Baneling";"Zergling";671;0
"Unit";"Baneling";"Zergling";671;0
"Unit";"Baneling";"Zergling";671;0
"Unit";"Baneling";"Zergling";671;0
"Unit";"Baneling";"Zergling";671;0
"Unit";"Baneling";"Zergling";671;0
"Building";"CreepTumor";NA;671;0
"Building";"CreepTumor";NA;671;0
"Unit";"Zergling";"Larva";671;1
"Unit";"Zergling";"Larva";671;1
"Unit";"Zergling";"Larva";671;1
"Unit";"Zergling";"Larva";671;1
"Unit";"Zergling";"Larva";671;1
"Unit";"Zergling";"Larva";671;1
"Unit";"Zergling";"Larva";671;1
"Unit";"Zergling";"Larva";671;1
"Unit";"Zergling";"Larva";671;1
"Unit";"Zergling";"Larva";671;1
"Unit";"Zergling";"Larva";671;1
"Unit";"Zergling";"Larva";671;1
"Unit";"Zergling";"Larva";671;1
"Unit";"Zergling";"Larva";671;1
"Unit";"Zergling";"Larva";671;1
"Unit";"Zergling";"Larva";671;1
"Unit";"Zergling";"Larva";671;1
"Unit";"Zergling";"Larva";671;1
"Unit";"Zergling";"Larva";671;1
"Unit";"Zergling";"Larva";671;1
"Unit";"Zergling";"Larva";671;1
"Unit";"Zergling";"Larva";671;1
"Unit";"Zergling";"Larva";671;1
"Unit";"Zergling";"Larva";671;1
"Unit";"Zergling";"Larva";671;1
"Unit";"Zergling";"Larva";671;1
"Unit";"Zergling";"Larva";671;1
"Unit";"Zergling";"Larva";671;1
"Unit";"Zergling";"Larva";671;1
"Unit";"Zergling";"Larva";671;1
"Unit";"Zergling";"Larva";671;1
"Unit";"Zergling";"Larva";671;1
"Unit";"Zergling";"Larva";671;1
"Unit";"Zergling";"Larva";671;1
"Building";"Hatchery";NA;671;0
"Unit";"Baneling";"Zergling";705;0
"Unit";"Baneling";"Zergling";705;0
"Unit";"Baneling";"Zergling";705;0
"Unit";"Baneling";"Zergling";705;0
"Unit";"Ultralisk";"Larva";705;6
"Unit";"Zergling";"Larva";705;1
"Unit";"Zergling";"Larva";705;1
"Unit";"Zergling";"Larva";705;1
"Unit";"Zergling";"Larva";705;1
"Unit";"Zergling";"Larva";705;1
"Unit";"Zergling";"Larva";705;1
"Unit";"Zergling";"Larva";705;1
"Unit";"Zergling";"Larva";705;1
"Unit";"Zergling";"Larva";705;1
"Unit";"Zergling";"Larva";705;1
"Unit";"Zergling";"Larva";705;1
"Unit";"Zergling";"Larva";705;1
"Unit";"Zergling";"Larva";705;1
"Unit";"Zergling";"Larva";705;1
"Unit";"Zergling";"Larva";705;1
"Unit";"Zergling";"Larva";705;1
"Unit";"Zergling";"Larva";705;1
"Unit";"Zergling";"Larva";705;1
"Unit";"Zergling";"Larva";705;1
"Unit";"Zergling";"Larva";705;1
"Unit";"Zergling";"Larva";705;1
"Unit";"Zergling";"Larva";705;1
"Unit";"Zergling";"Larva";705;1
"Unit";"Zergling";"Larva";705;1
"Unit";"Zergling";"Larva";705;1
"Unit";"Zergling";"Larva";705;1
"Unit";"Zergling";"Larva";705;1
"Unit";"Zergling";"Larva";705;1
"Building";"CreepTumorQueen";NA;739;0
"Unit";"Ultralisk";"Larva";705;6
"Unit";"Ultralisk";"Larva";705;6
"Unit";"Ultralisk";"Larva";705;6
"Unit";"Ultralisk";"Larva";705;6
"Unit";"Ultralisk";"Larva";705;6
"Unit";"Ultralisk";"Larva";705;6
"Unit";"Baneling";"Zergling";739;0
"Unit";"Baneling";"Zergling";739;0
"Unit";"Baneling";"Zergling";739;0
"Unit";"Baneling";"Zergling";739;0
"Unit";"Baneling";"Zergling";739;0
"Unit";"Baneling";"Zergling";739;0
"Unit";"Baneling";"Zergling";739;0
"Unit";"Baneling";"Zergling";739;0
"Unit";"Baneling";"Zergling";739;0
"Unit";"Baneling";"Zergling";739;0
"Unit";"Baneling";"Zergling";739;0
"Unit";"Baneling";"Zergling";739;0
"Unit";"Baneling";"Zergling";739;0
"Unit";"Baneling";"Zergling";739;0
"Unit";"Baneling";"Zergling";739;0
"Unit";"Baneling";"Zergling";739;0
"Unit";"Baneling";"Zergling";739;0
"Unit";"Baneling";"Zergling";739;0
"Unit";"Baneling";"Zergling";739;0
"Unit";"Baneling";"Zergling";739;0
"Unit";"Baneling";"Zergling";739;0
"Unit";"Baneling";"Zergling";739;0
"Unit";"Baneling";"Zergling";739;0
"Unit";"Baneling";"Zergling";739;0
"Unit";"Baneling";"Zergling";739;0
"Unit";"Baneling";"Zergling";739;0
"Unit";"Baneling";"Zergling";739;0
"Unit";"Baneling";"Zergling";739;0
"Building";"CreepTumorQueen";NA;739;0
"Building";"Extractor";NA;739;0
"Building";"Extractor";NA;739;0
"Building";"Extractor";NA;739;0
"Building";"Extractor";NA;739;0
"Unit";"Infestor";"Larva";775;2
"Unit";"Infestor";"Larva";775;2
"Unit";"Zergling";"Larva";779;1
"Unit";"Zergling";"Larva";779;1
"Unit";"Zergling";"Larva";779;1
"Unit";"Zergling";"Larva";779;1
"Unit";"Zergling";"Larva";779;1
"Unit";"Zergling";"Larva";779;1
"Unit";"Zergling";"Larva";779;1
"Unit";"Zergling";"Larva";779;1
"Upgrade";"Burrow";"Hatchery";775;0
"Unit";"Overlord";"Larva";779;0
"Building";"Extractor";NA;779;0
"Unit";"Ultralisk";"Larva";779;6
"Unit";"Ultralisk";"Larva";779;6
"Unit";"Ultralisk";"Larva";779;6
"Unit";"Ultralisk";"Larva";779;6
"Unit";"Ultralisk";"Larva";779;6
"Unit";"Baneling";"Zergling";787;0
"Unit";"Baneling";"Zergling";787;0
"Unit";"Baneling";"Zergling";787;0
"Unit";"Baneling";"Zergling";787;0
"Unit";"Baneling";"Zergling";787;0
"Unit";"Baneling";"Zergling";787;0
"Unit";"Baneling";"Zergling";787;0
"Unit";"Baneling";"Zergling";787;0
"Unit";"Baneling";"Zergling";787;0
"Unit";"Baneling";"Zergling";787;0
"Unit";"Overlord";"Larva";787;0
"Unit";"Overlord";"Larva";787;0
"Building";"CreepTumor";NA;817;0
"Unit";"Zergling";"Larva";817;1
"Unit";"Zergling";"Larva";817;1
"Unit";"Zergling";"Larva";817;1
"Unit";"Zergling";"Larva";817;1
"Unit";"Zergling";"Larva";817;1
"Unit";"Zergling";"Larva";817;1
"Unit";"Zergling";"Larva";817;1
"Unit";"Zergling";"Larva";817;1
"Unit";"Zergling";"Larva";817;1
"Unit";"Zergling";"Larva";817;1
"Unit";"Zergling";"Larva";817;1
"Unit";"Zergling";"Larva";817;1
"Unit";"Zergling";"Larva";817;1
"Unit";"Zergling";"Larva";817;1
"Unit";"Zergling";"Larva";817;1
"Unit";"Zergling";"Larva";817;1
"Unit";"Zergling";"Larva";817;1
"Unit";"Zergling";"Larva";817;1
"Unit";"Zergling";"Larva";817;1
"Unit";"Zergling";"Larva";817;1
"Unit";"Zergling";"Larva";817;1
"Unit";"Zergling";"Larva";817;1
"Unit";"Zergling";"Larva";817;1
"Unit";"Zergling";"Larva";817;1
"Building";"CreepTumor";NA;817;0
"Building";"CreepTumor";NA;817;0
"Building";"CreepTumorQueen";NA;841;0
"Building";"CreepTumorQueen";NA;841;0
"Unit";"Baneling";"Zergling";841;0
"Unit";"Baneling";"Zergling";841;0
"Unit";"Baneling";"Zergling";841;0
"Unit";"Baneling";"Zergling";841;0
"Unit";"Baneling";"Zergling";841;0
"Unit";"Baneling";"Zergling";841;0
"Unit";"Baneling";"Zergling";841;0
"Unit";"Baneling";"Zergling";841;0
"Unit";"Baneling";"Zergling";841;0
"Unit";"Baneling";"Zergling";841;0
"Unit";"Baneling";"Zergling";841;0
"Unit";"Baneling";"Zergling";841;0
"Unit";"Baneling";"Zergling";841;0
"Unit";"Baneling";"Zergling";841;0
"Unit";"Baneling";"Zergling";841;0
"Unit";"Baneling";"Zergling";841;0
"Unit";"Baneling";"Zergling";841;0
"Unit";"Baneling";"Zergling";841;0
"Unit";"Baneling";"Zergling";841;0
"Unit";"Baneling";"Zergling";841;0
"Unit";"Baneling";"Zergling";841;0
"Unit";"Baneling";"Zergling";841;0
"Unit";"Baneling";"Zergling";841;0
"Unit";"Baneling";"Zergling";841;0
"Unit";"Overlord";"Larva";841;0
"Unit";"Overlord";"Larva";841;0
"Unit";"Overlord";"Larva";841;0
"Building";"SporeCrawler";NA;841;0
"Building";"CreepTumor";NA;841;0
"Unit";"Hydralisk";"Larva";841;2
"Unit";"Hydralisk";"Larva";841;2
"Unit";"Zergling";"Larva";841;1
"Unit";"Zergling";"Larva";841;1
"Unit";"Hydralisk";"Larva";841;2
"Unit";"Zergling";"Larva";841;1
"Unit";"Zergling";"Larva";841;1
"Unit";"Zergling";"Larva";841;1
"Unit";"Zergling";"Larva";841;1
"Unit";"Zergling";"Larva";841;1
"Unit";"Zergling";"Larva";841;1
"Unit";"Hydralisk";"Larva";841;2
"Unit";"Zergling";"Larva";841;1
"Unit";"Zergling";"Larva";841;1
"Unit";"Zergling";"Larva";841;1
"Unit";"Zergling";"Larva";841;1
"Unit";"Zergling";"Larva";841;1
"Unit";"Zergling";"Larva";841;1
"Unit";"Zergling";"Larva";841;1
"Unit";"Zergling";"Larva";841;1
"Unit";"Zergling";"Larva";841;1
"Unit";"Zergling";"Larva";841;1
"Unit";"Zergling";"Larva";841;1
"Unit";"Zergling";"Larva";841;1
"Unit";"Zergling";"Larva";841;1
"Unit";"Zergling";"Larva";841;1
"Unit";"Zergling";"Larva";841;1
"Unit";"Zergling";"Larva";841;1
"Unit";"Zergling";"Larva";841;1
"Unit";"Zergling";"Larva";841;1
"Unit";"Zergling";"Larva";841;1
"Unit";"Zergling";"Larva";841;1
"Unit";"Zergling";"Larva";841;1
"Unit";"Zergling";"Larva";841;1
"Unit";"Zergling";"Larva";841;1
"Unit";"Zergling";"Larva";841;1
"Unit";"Zergling";"Larva";841;1
"Unit";"Zergling";"Larva";841;1
"Unit";"Zergling";"Larva";841;1
"Unit";"Zergling";"Larva";841;1
"Unit";"Zergling";"Larva";841;1
"Unit";"Zergling";"Larva";841;1
"Unit";"Zergling";"Larva";841;1
"Unit";"Zergling";"Larva";841;1
"Unit";"Zergling";"Larva";841;1
"Unit";"Zergling";"Larva";841;1
"Unit";"Zergling";"Larva";841;1
"Unit";"Zergling";"Larva";841;1
"Unit";"Infestor";"Larva";841;2
"Unit";"Infestor";"Larva";841;2
"Unit";"Infestor";"Larva";841;2
"Unit";"Infestor";"Larva";841;2
"Unit";"Infestor";"Larva";841;2
"Unit";"Zergling";"Larva";841;1
"Unit";"Zergling";"Larva";841;1
"Unit";"Ultralisk";"Larva";841;6
"Unit";"Ultralisk";"Larva";841;6
"Unit";"Ultralisk";"Larva";841;6
"Unit";"Ultralisk";"Larva";841;6
"Unit";"Ultralisk";"Larva";841;6
"Unit";"Ultralisk";"Larva";841;6
"Unit";"Zergling";"Larva";857;1
"Unit";"Zergling";"Larva";857;1
"Building";"Extractor";NA;841;0
"Building";"Extractor";NA;845;0
"Unit";"Baneling";"Zergling";905;0
"Unit";"Baneling";"Zergling";905;0
"Unit";"Baneling";"Zergling";905;0
"Unit";"Baneling";"Zergling";905;0
"Unit";"Baneling";"Zergling";905;0
"Unit";"Baneling";"Zergling";905;0
"Unit";"Baneling";"Zergling";905;0
"Unit";"Baneling";"Zergling";905;0
"Unit";"Baneling";"Zergling";905;0
"Unit";"Baneling";"Zergling";905;0
"Unit";"Baneling";"Zergling";905;0
"Unit";"Baneling";"Zergling";905;0
"Unit";"Baneling";"Zergling";905;0
"Unit";"Baneling";"Zergling";905;0
"Unit";"Baneling";"Zergling";905;0
"Unit";"Baneling";"Zergling";905;0
"Unit";"Baneling";"Zergling";905;0
"Unit";"Baneling";"Zergling";905;0
"Building";"CreepTumor";NA;951;0
"Unit";"Baneling";"Zergling";951;0
"Unit";"Baneling";"Zergling";951;0
"Unit";"Baneling";"Zergling";951;0
"Unit";"Baneling";"Zergling";951;0
"Unit";"Baneling";"Zergling";951;0
"Unit";"Baneling";"Zergling";951;0
"Unit";"Baneling";"Zergling";951;0
"Unit";"Baneling";"Zergling";951;0
"Unit";"Baneling";"Zergling";951;0
"Unit";"Baneling";"Zergling";951;0
"Building";"CreepTumor";NA;951;0
"Unit";"Zergling";"Larva";951;1
"Unit";"Zergling";"Larva";951;1
"Unit";"Zergling";"Larva";951;1
"Unit";"Zergling";"Larva";951;1
"Unit";"Zergling";"Larva";951;1
"Unit";"Zergling";"Larva";951;1
"Unit";"Zergling";"Larva";951;1
"Unit";"Zergling";"Larva";951;1
"Unit";"Zergling";"Larva";951;1
"Unit";"Zergling";"Larva";951;1
"Unit";"Zergling";"Larva";951;1
"Unit";"Zergling";"Larva";951;1
"Unit";"Zergling";"Larva";963;1
"Unit";"Zergling";"Larva";963;1
"Unit";"Zergling";"Larva";963;1
"Unit";"Zergling";"Larva";963;1
"Unit";"Zergling";"Larva";963;1
"Unit";"Zergling";"Larva";963;1
"Unit";"Zergling";"Larva";963;1
"Unit";"Zergling";"Larva";963;1
"Unit";"Zergling";"Larva";963;1
"Unit";"Zergling";"Larva";963;1
"Unit";"Zergling";"Larva";963;1
"Unit";"Zergling";"Larva";963;1
"Unit";"Zergling";"Larva";963;1
"Unit";"Zergling";"Larva";963;1
"Unit";"Zergling";"Larva";963;1
"Unit";"Zergling";"Larva";963;1
"Unit";"Zergling";"Larva";963;1
"Unit";"Zergling";"Larva";963;1
"Unit";"Hydralisk";"Larva";963;2
"Unit";"Hydralisk";"Larva";963;2
"Unit";"Hydralisk";"Larva";963;2
"Unit";"Hydralisk";"Larva";963;2
"Unit";"Hydralisk";"Larva";963;2
"Unit";"Hydralisk";"Larva";963;2
"Unit";"Hydralisk";"Larva";963;2
"Unit";"Hydralisk";"Larva";963;2
"Unit";"Hydralisk";"Larva";963;2
"Unit";"Hydralisk";"Larva";963;2
"Unit";"Hydralisk";"Larva";963;2
"Unit";"Hydralisk";"Larva";963;2
"Unit";"Hydralisk";"Larva";963;2
"Unit";"Hydralisk";"Larva";963;2
"Unit";"Baneling";"Zergling";963;0
"Unit";"Baneling";"Zergling";963;0
"Unit";"Baneling";"Zergling";963;0
"Unit";"Baneling";"Zergling";963;0
"Unit";"Baneling";"Zergling";963;0
"Building";"CreepTumor";NA;963;0
"Building";"CreepTumor";NA;963;0
"Building";"CreepTumor";NA;963;0
"Unit";"Zergling";"Larva";989;1
"Unit";"Zergling";"Larva";989;1
"Unit";"Zergling";"Larva";1007;1
"Unit";"Zergling";"Larva";1007;1
"Unit";"Zergling";"Larva";1009;1
"Unit";"Zergling";"Larva";1009;1
"Unit";"Zergling";"Larva";1009;1
"Unit";"Zergling";"Larva";1009;1
"Unit";"Zergling";"Larva";1009;1
"Unit";"Zergling";"Larva";1009;1
"Unit";"Zergling";"Larva";1009;1
"Unit";"Zergling";"Larva";1009;1
"Building";"CreepTumor";NA;1021;0
"Building";"CreepTumorQueen";NA;1021;0
"Building";"CreepTumorQueen";NA;1021;0
"Building";"CreepTumorQueen";NA;1021;0
"Building";"CreepTumorQueen";NA;1021;0
"Building";"Extractor";NA;1021;0
"Building";"CreepTumor";NA;1021;0
"Unit";"Overlord";"Larva";1021;0
"Unit";"Overlord";"Larva";1021;0
"Unit";"Overlord";"Larva";1021;0
"Unit";"Overlord";"Larva";1021;0
"Unit";"Zergling";"Larva";1021;1
"Unit";"Zergling";"Larva";1021;1
"Unit";"Zergling";"Larva";1021;1
"Unit";"Zergling";"Larva";1021;1
"Unit";"Zergling";"Larva";1021;1
"Unit";"Zergling";"Larva";1021;1
"Unit";"Zergling";"Larva";1021;1
"Unit";"Zergling";"Larva";1021;1
"Unit";"Zergling";"Larva";1021;1
"Unit";"Zergling";"Larva";1021;1
"Unit";"Zergling";"Larva";1021;1
"Unit";"Zergling";"Larva";1021;1
"Unit";"Zergling";"Larva";1021;1
"Unit";"Zergling";"Larva";1021;1
"Unit";"Zergling";"Larva";1021;1
"Unit";"Zergling";"Larva";1021;1
"Unit";"Baneling";"Zergling";1023;0
"Unit";"Baneling";"Zergling";1023;0
"Unit";"Baneling";"Zergling";1023;0
"Unit";"Baneling";"Zergling";1023;0
"Building";"CreepTumor";NA;1023;0
"Building";"Hatchery";NA;1021;0
"Unit";"Infestor";"Larva";1023;2
"Building";"CreepTumor";NA;1039;0
"Building";"CreepTumor";NA;1039;0
"Building";"CreepTumor";NA;1039;0
"Building";"Extractor";NA;1039;0
"Building";"CreepTumor";NA;1041;0
"Unit";"Corruptor";"Larva";1041;2
"Unit";"Corruptor";"Larva";1041;2
"Unit";"Corruptor";"Larva";1041;2
"Unit";"Corruptor";"Larva";1041;2
"Unit";"Corruptor";"Larva";1041;2
"Unit";"Corruptor";"Larva";1041;2
"Unit";"Corruptor";"Larva";1041;2
"Unit";"Baneling";"Zergling";1041;0
"Unit";"Baneling";"Zergling";1041;0
"Unit";"Baneling";"Zergling";1041;0
"Unit";"Baneling";"Zergling";1041;0
"Unit";"Baneling";"Zergling";1041;0
"Unit";"Baneling";"Zergling";1041;0
"Unit";"Corruptor";"Larva";1041;2
"Unit";"Corruptor";"Larva";1041;2
"Unit";"Corruptor";"Larva";1041;2
"Unit";"Corruptor";"Larva";1041;2
"Unit";"Corruptor";"Larva";1041;2
"Unit";"Corruptor";"Larva";1041;2
"Unit";"Corruptor";"Larva";1041;2
"Unit";"Zergling";"Larva";1055;1
"Unit";"Zergling";"Larva";1055;1
"Unit";"Zergling";"Larva";1055;1
"Unit";"Zergling";"Larva";1055;1
"Unit";"Zergling";"Larva";1055;1
"Unit";"Zergling";"Larva";1055;1
"Unit";"Zergling";"Larva";1055;1
"Unit";"Zergling";"Larva";1055;1
"Unit";"Baneling";"Zergling";1055;0
"Unit";"Baneling";"Zergling";1055;0
"Unit";"Baneling";"Zergling";1055;0
"Unit";"Infestor";"Larva";1041;2
"Unit";"Infestor";"Larva";1041;2
"Unit";"Infestor";"Larva";1043;2
"Unit";"Zergling";"Larva";1083;1
"Unit";"Zergling";"Larva";1083;1
"Unit";"Zergling";"Larva";1083;1
"Unit";"Zergling";"Larva";1083;1
"Unit";"Zergling";"Larva";1083;1
"Unit";"Zergling";"Larva";1083;1
"Unit";"Zergling";"Larva";1083;1
"Unit";"Zergling";"Larva";1083;1
"Unit";"Zergling";"Larva";1083;1
"Unit";"Zergling";"Larva";1083;1
"Unit";"Zergling";"Larva";1083;1
"Unit";"Zergling";"Larva";1083;1
"Unit";"Zergling";"Larva";1083;1
"Unit";"Zergling";"Larva";1083;1
"Unit";"Zergling";"Larva";1083;1
"Unit";"Zergling";"Larva";1083;1
"Unit";"Zergling";"Larva";1083;1
"Unit";"Zergling";"Larva";1083;1
"Unit";"Zergling";"Larva";1083;1
"Unit";"Zergling";"Larva";1083;1
"Unit";"Zergling";"Larva";1083;1
"Unit";"Zergling";"Larva";1083;1
"Unit";"Zergling";"Larva";1083;1
"Unit";"Zergling";"Larva";1083;1
"Unit";"Zergling";"Larva";1083;1
"Unit";"Zergling";"Larva";1083;1
"Unit";"Zergling";"Larva";1083;1
"Unit";"Zergling";"Larva";1083;1
"Unit";"Zergling";"Larva";1083;1
"Unit";"Zergling";"Larva";1083;1
"Unit";"Zergling";"Larva";1083;1
"Unit";"Zergling";"Larva";1083;1
"Unit";"Zergling";"Larva";1083;1
"Unit";"Zergling";"Larva";1083;1
"Unit";"Zergling";"Larva";1083;1
"Unit";"Zergling";"Larva";1083;1
"Unit";"Zergling";"Larva";1083;1
"Unit";"Zergling";"Larva";1083;1
"Unit";"Zergling";"Larva";1083;1
"Unit";"Zergling";"Larva";1083;1
"Unit";"Zergling";"Larva";1083;1
"Unit";"Zergling";"Larva";1083;1
"Unit";"Baneling";"Zergling";1083;0
"Unit";"Baneling";"Zergling";1083;0
"Unit";"Baneling";"Zergling";1083;0
"Unit";"Zergling";"Larva";1083;1
"Unit";"Zergling";"Larva";1083;1
"Building";"CreepTumor";NA;1083;0
"Unit";"Zergling";"Larva";1083;1
"Unit";"Zergling";"Larva";1083;1
"Unit";"Zergling";"Larva";1083;1
"Unit";"Zergling";"Larva";1083;1
"Unit";"Zergling";"Larva";1083;1
"Unit";"Zergling";"Larva";1083;1
"Unit";"Zergling";"Larva";1083;1
"Unit";"Zergling";"Larva";1083;1
"Unit";"Zergling";"Larva";1083;1
"Unit";"Zergling";"Larva";1083;1
"Unit";"Zergling";"Larva";1083;1
"Unit";"Zergling";"Larva";1083;1
"Unit";"Zergling";"Larva";1083;1
"Unit";"Zergling";"Larva";1083;1
"Unit";"Zergling";"Larva";1083;1
"Unit";"Zergling";"Larva";1083;1
"Unit";"Zergling";"Larva";1083;1
"Unit";"Zergling";"Larva";1083;1
"Unit";"Zergling";"Larva";1083;1
"Unit";"Zergling";"Larva";1083;1
"Unit";"Zergling";"Larva";1083;1
"Unit";"Zergling";"Larva";1083;1
"Unit";"Zergling";"Larva";1083;1
"Unit";"Zergling";"Larva";1083;1
"Unit";"Zergling";"Larva";1083;1
"Unit";"Zergling";"Larva";1083;1
"Unit";"Zergling";"Larva";1083;1
"Unit";"Zergling";"Larva";1083;1
"Unit";"Zergling";"Larva";1083;1
"Unit";"Zergling";"Larva";1083;1
"Unit";"Zergling";"Larva";1083;1
"Unit";"Zergling";"Larva";1083;1
"Unit";"Zergling";"Larva";1083;1
"Unit";"Zergling";"Larva";1083;1
"Unit";"Zergling";"Larva";1083;1
"Unit";"Zergling";"Larva";1083;1
"Unit";"Zergling";"Larva";1083;1
"Unit";"Zergling";"Larva";1083;1
"Unit";"Zergling";"Larva";1083;1
"Unit";"Zergling";"Larva";1083;1
"Unit";"Zergling";"Larva";1083;1
"Unit";"Zergling";"Larva";1083;1
"Unit";"Zergling";"Larva";1083;1
"Unit";"Zergling";"Larva";1083;1
"Unit";"Zergling";"Larva";1083;1
"Unit";"Zergling";"Larva";1083;1
"Unit";"Zergling";"Larva";1083;1
"Unit";"Zergling";"Larva";1083;1
"Unit";"Zergling";"Larva";1083;1
"Unit";"Zergling";"Larva";1083;1
"Unit";"Ultralisk";"Larva";1077;6
"Unit";"Ultralisk";"Larva";1077;6
"Unit";"Overlord";"Larva";1177;0
"Unit";"Overlord";"Larva";1177;0
"Unit";"Zergling";"Larva";1189;1
"Unit";"Zergling";"Larva";1189;1
"Unit";"Zergling";"Larva";1189;1
"Unit";"Zergling";"Larva";1189;1
"Unit";"Zergling";"Larva";1189;1
"Unit";"Zergling";"Larva";1189;1
"Unit";"Zergling";"Larva";1189;1
"Unit";"Zergling";"Larva";1189;1
"Unit";"Zergling";"Larva";1189;1
"Unit";"Zergling";"Larva";1189;1
"Unit";"Zergling";"Larva";1189;1
"Unit";"Zergling";"Larva";1189;1
"Unit";"Zergling";"Larva";1189;1
"Unit";"Zergling";"Larva";1189;1
"Unit";"Zergling";"Larva";1189;1
"Unit";"Zergling";"Larva";1189;1
"Unit";"Zergling";"Larva";1189;1
"Unit";"Zergling";"Larva";1189;1
"Unit";"Zergling";"Larva";1189;1
"Unit";"Zergling";"Larva";1189;1
"Unit";"Zergling";"Larva";1189;1
"Unit";"Zergling";"Larva";1189;1
"Unit";"Zergling";"Larva";1189;1
"Unit";"Zergling";"Larva";1189;1
"Unit";"Zergling";"Larva";1189;1
"Unit";"Zergling";"Larva";1189;1
"Unit";"Zergling";"Larva";1189;1
"Unit";"Zergling";"Larva";1189;1
"Unit";"Zergling";"Larva";1189;1
"Unit";"Zergling";"Larva";1189;1
"Unit";"Zergling";"Larva";1189;1
"Unit";"Zergling";"Larva";1189;1
"Unit";"Zergling";"Larva";1189;1
"Unit";"Zergling";"Larva";1189;1
"Unit";"Zergling";"Larva";1189;1
"Unit";"Zergling";"Larva";1189;1
"Building";"Extractor";NA;1189;0
"Building";"Extractor";NA;1189;0
"Unit";"Infestor";"Larva";1189;2
"Unit";"Ultralisk";"Larva";1225;6
"Unit";"Ultralisk";"Larva";1225;6
"Unit";"Infestor";"Larva";1225;2
"Unit";"Zergling";"Larva";1233;1
"Unit";"Zergling";"Larva";1233;1
"Unit";"Zergling";"Larva";1233;1
"Unit";"Zergling";"Larva";1233;1
"Unit";"Zergling";"Larva";1233;1
"Unit";"Zergling";"Larva";1233;1
"Unit";"Zergling";"Larva";1233;1
"Unit";"Zergling";"Larva";1233;1
"Unit";"Zergling";"Larva";1233;1
"Unit";"Zergling";"Larva";1233;1
