"type";"unit_name";"on_building";"total_supply";"supply"
"Unit";"Overlord";"Larva";13;0
"Building";"Extractor";NA;17;0
"Building";"SpawningPool";NA;19;0
"Building";"Hatchery";NA;17;0
"Unit";"Overlord";"Larva";22;0
"Unit";"Zergling";"Larva";23;1
"Unit";"Zergling";"Larva";23;1
"Unit";"Queen";"Hatchery";23;2
"Unit";"Queen";"Hatchery";23;2
"Building";"CreepTumorQueen";NA;33;0
"Building";"CreepTumorQueen";NA;33;0
"Unit";"Overlord";"Larva";32;0
"Building";"CreepTumor";NA;35;0
"Building";"CreepTumorQueen";NA;35;0
"Unit";"Queen";"Hatchery";33;2
"Building";"CreepTumor";NA;37;0
"Unit";"Queen";"Hatchery";35;2
"Unit";"Overlord";"Larva";37;0
"Building";"Hatchery";NA;28;0
"Building";"CreepTumor";NA;46;0
"Building";"CreepTumor";NA;46;0
"Building";"CreepTumorQueen";NA;46;0
"Unit";"Overlord";"Larva";47;0
"Building";"Extractor";NA;50;0
"Building";"CreepTumor";NA;52;0
"Unit";"Queen";"Hatchery";46;2
"Unit";"Queen";"Hatchery";46;2
"Unit";"Overlord";"Larva";52;0
"Building";"CreepTumor";NA;52;0
"Building";"CreepTumor";NA;54;0
"Building";"CreepTumorQueen";NA;54;0
"Unit";"Queen";"Hatchery";46;2
"Building";"CreepTumorQueen";NA;54;0
"Unit";"Zergling";"Larva";54;1
"Unit";"Zergling";"Larva";54;1
"Unit";"Zergling";"Larva";54;1
"Unit";"Zergling";"Larva";54;1
"Unit";"Zergling";"Larva";54;1
"Unit";"Zergling";"Larva";54;1
"Unit";"Zergling";"Larva";54;1
"Unit";"Zergling";"Larva";54;1
"Unit";"Zergling";"Larva";60;1
"Unit";"Zergling";"Larva";60;1
"Unit";"Zergling";"Larva";60;1
"Unit";"Zergling";"Larva";60;1
"Building";"CreepTumor";NA;65;0
"Building";"EvolutionChamber";NA;60;0
"Building";"EvolutionChamber";NA;63;0
"Building";"SporeCrawler";NA;73;0
"Building";"SporeCrawler";NA;73;0
"Unit";"Queen";"Hatchery";58;2
"Building";"CreepTumor";NA;78;0
"Building";"SporeCrawler";NA;73;0
"Unit";"Overlord";"Larva";78;0
"Building";"CreepTumor";NA;81;0
"Unit";"Overlord";"Larva";78;0
"Building";"CreepTumor";NA;81;0
"Building";"CreepTumor";NA;97;0
"Building";"Extractor";NA;85;0
"Building";"CreepTumorQueen";NA;97;0
"Building";"CreepTumorQueen";NA;98;0
"Building";"Extractor";NA;97;0
"Building";"Extractor";NA;97;0
"Building";"Extractor";NA;97;0
"Unit";"Overlord";"Larva";102;0
"Unit";"Overlord";"Larva";102;0
"Building";"RoachWarren";NA;97;0
"Building";"CreepTumor";NA;104;0
"Unit";"Overlord";"Larva";106;0
"Unit";"Overlord";"Larva";107;0
"Building";"BanelingNest";NA;102;0
"Building";"CreepTumorQueen";NA;111;0
"Unit";"Overlord";"Larva";111;0
"Upgrade";"ZergMeleeWeaponsLevel1";"EvolutionChamber";85;0
"Upgrade";"ZergGroundArmorsLevel1";"EvolutionChamber";85;0
"Building";"CreepTumorQueen";NA;113;0
"Unit";"Overlord";"Larva";111;0
"Unit";"Overlord";"Larva";111;0
"Building";"Hatchery";NA;92;0
"Unit";"Overlord";"Larva";113;0
"Building";"CreepTumorQueen";NA;122;0
"Unit";"Roach";"Larva";122;2
"Unit";"Roach";"Larva";122;2
"Unit";"Roach";"Larva";122;2
"Unit";"Roach";"Larva";122;2
"Unit";"Roach";"Larva";122;2
"Building";"CreepTumorQueen";NA;122;0
"Unit";"Overlord";"Larva";122;0
"Building";"CreepTumorQueen";NA;122;0
"Building";"CreepTumor";NA;122;0
"Unit";"Roach";"Larva";122;2
"Unit";"Roach";"Larva";122;2
"Unit";"Baneling";"Zergling";122;0
"Unit";"Baneling";"Zergling";122;0
"Unit";"Baneling";"Zergling";122;0
"Unit";"Baneling";"Zergling";122;0
"Unit";"Baneling";"Zergling";122;0
"Unit";"Baneling";"Zergling";122;0
"Unit";"Roach";"Larva";122;2
"Unit";"Roach";"Larva";122;2
"Unit";"Roach";"Larva";122;2
"Unit";"Roach";"Larva";122;2
"Unit";"Queen";"Hatchery";122;2
"Unit";"Roach";"Larva";136;2
"Unit";"Roach";"Larva";136;2
"Unit";"Roach";"Larva";136;2
"Unit";"Roach";"Larva";136;2
"Unit";"Roach";"Larva";136;2
"Unit";"Roach";"Larva";136;2
"Building";"HydraliskDen";NA;136;0
"Unit";"Roach";"Larva";144;2
"Unit";"Overlord";"Larva";144;0
"Unit";"Roach";"Larva";144;2
"Unit";"Overlord";"Larva";144;0
"Unit";"Roach";"Larva";144;2
"Unit";"Zergling";"Larva";158;1
"Unit";"Zergling";"Larva";158;1
"Unit";"Zergling";"Larva";158;1
"Unit";"Zergling";"Larva";158;1
"Unit";"Zergling";"Larva";158;1
"Unit";"Zergling";"Larva";158;1
"Unit";"Zergling";"Larva";158;1
"Unit";"Zergling";"Larva";158;1
"Unit";"Zergling";"Larva";158;1
"Unit";"Zergling";"Larva";158;1
"Unit";"Zergling";"Larva";158;1
"Unit";"Zergling";"Larva";158;1
"Unit";"Overlord";"Larva";164;0
"Unit";"Overlord";"Larva";164;0
"Unit";"Overlord";"Larva";164;0
"Building";"CreepTumorQueen";NA;176;0
"Building";"CreepTumorQueen";NA;176;0
"Unit";"Hydralisk";"Larva";176;2
"Unit";"Hydralisk";"Larva";176;2
"Unit";"Hydralisk";"Larva";176;2
"Unit";"Hydralisk";"Larva";176;2
"Unit";"Hydralisk";"Larva";176;2
"Unit";"Hydralisk";"Larva";176;2
"Unit";"Hydralisk";"Larva";176;2
"Building";"CreepTumorQueen";NA;176;0
"Unit";"Overlord";"Larva";176;0
"Unit";"Overlord";"Larva";176;0
"Unit";"Overlord";"Larva";176;0
"Upgrade";"ZergMissileWeaponsLevel1";"EvolutionChamber";140;0
"Building";"InfestationPit";NA;176;0
"Upgrade";"GlialReconstitution";"RoachWarren";176;0
"Unit";"Hydralisk";"Larva";176;2
"Unit";"Hydralisk";"Larva";176;2
"Unit";"Hydralisk";"Larva";176;2
"Unit";"Hydralisk";"Larva";176;2
"Unit";"Hydralisk";"Larva";176;2
"Unit";"Hydralisk";"Larva";176;2
"Unit";"Overlord";"Larva";190;0
"Unit";"Overlord";"Larva";190;0
"Building";"CreepTumorQueen";NA;190;0
"Building";"CreepTumorQueen";NA;190;0
"Building";"CreepTumor";NA;190;0
"Building";"CreepTumorQueen";NA;190;0
"Building";"CreepTumor";NA;190;0
"Building";"CreepTumor";NA;190;0
"Building";"Hatchery";NA;176;0
"Unit";"Overlord";"Larva";202;0
"Unit";"Zergling";"Larva";202;1
"Unit";"Zergling";"Larva";202;1
"Building";"CreepTumorQueen";NA;209;0
"Building";"CreepTumorQueen";NA;211;0
"Unit";"Hydralisk";"Larva";207;2
"Unit";"Hydralisk";"Larva";207;2
"Unit";"Overlord";"Larva";211;0
"Unit";"Overlord";"Larva";211;0
"Unit";"Zergling";"Larva";211;1
"Unit";"Zergling";"Larva";211;1
"Unit";"Zergling";"Larva";211;1
"Unit";"Zergling";"Larva";211;1
"Unit";"Zergling";"Larva";211;1
"Unit";"Zergling";"Larva";211;1
"Unit";"Zergling";"Larva";211;1
"Unit";"Zergling";"Larva";211;1
"Unit";"Zergling";"Larva";211;1
"Unit";"Zergling";"Larva";211;1
"Building";"Extractor";NA;211;0
"Building";"CreepTumor";NA;211;0
"Upgrade";"ZergGroundArmorsLevel2";"EvolutionChamber";176;0
"Building";"CreepTumor";NA;211;0
"Unit";"Zergling";"Larva";211;1
"Unit";"Zergling";"Larva";211;1
"Unit";"Zergling";"Larva";211;1
"Unit";"Zergling";"Larva";211;1
"Unit";"Zergling";"Larva";211;1
"Unit";"Zergling";"Larva";211;1
"Unit";"Zergling";"Larva";211;1
"Unit";"Zergling";"Larva";211;1
"Unit";"Zergling";"Larva";211;1
"Unit";"Zergling";"Larva";211;1
"Unit";"Zergling";"Larva";211;1
"Unit";"Zergling";"Larva";211;1
"Unit";"Zergling";"Larva";211;1
"Unit";"Zergling";"Larva";211;1
"Unit";"Zergling";"Larva";211;1
"Unit";"Zergling";"Larva";211;1
"Building";"CreepTumor";NA;215;0
"Upgrade";"EvolveMuscularAugments";"HydraliskDen";202;0
"Building";"CreepTumorQueen";NA;225;0
"Building";"Spire";NA;190;0
"Building";"Extractor";NA;241;0
"Unit";"Overlord";"Larva";241;0
"Unit";"Overlord";"Larva";241;0
"Unit";"Overlord";"Larva";241;0
"Unit";"Overlord";"Larva";241;0
"Unit";"Corruptor";"Larva";241;2
"Unit";"Corruptor";"Larva";241;2
"Unit";"Corruptor";"Larva";241;2
"Unit";"Corruptor";"Larva";241;2
"Unit";"Corruptor";"Larva";241;2
"Unit";"Corruptor";"Larva";241;2
"Unit";"Corruptor";"Larva";241;2
"Upgrade";"EvolveGroovedSpines";"HydraliskDen";241;0
"Unit";"Corruptor";"Larva";241;2
"Unit";"Corruptor";"Larva";241;2
"Unit";"Zergling";"Larva";249;1
"Unit";"Zergling";"Larva";249;1
"Unit";"Zergling";"Larva";249;1
"Unit";"Zergling";"Larva";249;1
"Unit";"Zergling";"Larva";249;1
"Unit";"Zergling";"Larva";249;1
"Unit";"Zergling";"Larva";249;1
"Unit";"Zergling";"Larva";249;1
"Unit";"Zergling";"Larva";249;1
"Unit";"Zergling";"Larva";249;1
"Unit";"Corruptor";"Larva";241;2
"Unit";"Zergling";"Larva";249;1
"Unit";"Zergling";"Larva";249;1
"Unit";"Zergling";"Larva";249;1
"Unit";"Zergling";"Larva";249;1
"Unit";"Zergling";"Larva";249;1
"Unit";"Zergling";"Larva";249;1
"Unit";"Zergling";"Larva";249;1
"Unit";"Zergling";"Larva";249;1
"Unit";"Corruptor";"Larva";241;2
"Unit";"Zergling";"Larva";249;1
"Unit";"Zergling";"Larva";249;1
"Unit";"Corruptor";"Larva";241;2
"Unit";"Corruptor";"Larva";249;2
"Unit";"Corruptor";"Larva";249;2
"Unit";"Corruptor";"Larva";249;2
"Unit";"Zergling";"Larva";259;1
"Unit";"Zergling";"Larva";259;1
"Unit";"Zergling";"Larva";259;1
"Unit";"Zergling";"Larva";259;1
"Unit";"Zergling";"Larva";259;1
"Unit";"Zergling";"Larva";259;1
"Unit";"Zergling";"Larva";259;1
"Unit";"Zergling";"Larva";259;1
"Unit";"Zergling";"Larva";259;1
"Unit";"Zergling";"Larva";259;1
"Unit";"Zergling";"Larva";285;1
"Unit";"Zergling";"Larva";285;1
"Building";"CreepTumor";NA;303;0
"Building";"CreepTumor";NA;303;0
"Building";"CreepTumor";NA;303;0
"Building";"CreepTumor";NA;303;0
"Building";"CreepTumorQueen";NA;303;0
"Unit";"Hydralisk";"Larva";303;2
"Unit";"Hydralisk";"Larva";303;2
"Unit";"Hydralisk";"Larva";303;2
"Unit";"Hydralisk";"Larva";303;2
"Unit";"Hydralisk";"Larva";303;2
"Unit";"Hydralisk";"Larva";303;2
"Building";"Hatchery";NA;303;0
"Unit";"Hydralisk";"Larva";315;2
"Unit";"Hydralisk";"Larva";315;2
"Unit";"Hydralisk";"Larva";315;2
"Unit";"Hydralisk";"Larva";315;2
"Unit";"Hydralisk";"Larva";315;2
"Unit";"Hydralisk";"Larva";315;2
"Unit";"Hydralisk";"Larva";315;2
"Unit";"Hydralisk";"Larva";315;2
"Unit";"Hydralisk";"Larva";315;2
"Unit";"Hydralisk";"Larva";315;2
"Unit";"Hydralisk";"Larva";315;2
"Unit";"Hydralisk";"Larva";315;2
"Unit";"Zergling";"Larva";315;1
"Unit";"Zergling";"Larva";315;1
"Unit";"Zergling";"Larva";315;1
"Unit";"Zergling";"Larva";315;1
"Unit";"Zergling";"Larva";315;1
"Unit";"Zergling";"Larva";315;1
"Unit";"Zergling";"Larva";315;1
"Unit";"Zergling";"Larva";315;1
"Upgrade";"ZergMissileWeaponsLevel2";"EvolutionChamber";303;0
"Unit";"Corruptor";"Larva";339;2
"Unit";"Corruptor";"Larva";339;2
"Unit";"Hydralisk";"Larva";347;2
"Unit";"Hydralisk";"Larva";347;2
"Unit";"Hydralisk";"Larva";347;2
"Unit";"Hydralisk";"Larva";347;2
"Unit";"Hydralisk";"Larva";347;2
