"type";"unit_name";"on_building";"total_supply";"supply"
"Unit";"Overlord";"Larva";12;0
"Building";"Extractor";NA;18;0
"Building";"SpawningPool";NA;18;0
"Building";"Hatchery";NA;17;0
"Unit";"Overlord";"Larva";22;0
"Unit";"Zergling";"Larva";23;1
"Unit";"Zergling";"Larva";23;1
"Unit";"Zergling";"Larva";23;1
"Unit";"Zergling";"Larva";23;1
"Unit";"Queen";"Hatchery";22;2
"Unit";"Queen";"Hatchery";23;2
"Unit";"Overlord";"Larva";37;0
"Unit";"Queen";"Hatchery";34;2
"Building";"CreepTumorQueen";NA;41;0
"Unit";"Overlord";"Larva";41;0
"Unit";"Queen";"Hatchery";39;2
"Building";"CreepTumor";NA;46;0
"Building";"CreepTumorQueen";NA;48;0
"Unit";"Overlord";"Larva";46;0
"Unit";"Overlord";"Larva";46;0
"Building";"Extractor";NA;48;0
"Building";"Hatchery";NA;39;0
"Building";"CreepTumor";NA;54;0
"Building";"CreepTumor";NA;54;0
"Building";"BanelingNest";NA;46;0
"Unit";"Queen";"Hatchery";48;2
"Unit";"Zergling";"Larva";57;1
"Unit";"Zergling";"Larva";57;1
"Unit";"Zergling";"Larva";57;1
"Unit";"Zergling";"Larva";57;1
"Unit";"Zergling";"Larva";57;1
"Unit";"Zergling";"Larva";57;1
"Building";"EvolutionChamber";NA;57;0
"Unit";"Zergling";"Larva";57;1
"Unit";"Zergling";"Larva";57;1
"Building";"EvolutionChamber";NA;57;0
"Unit";"Zergling";"Larva";57;1
"Unit";"Zergling";"Larva";57;1
"Unit";"Zergling";"Larva";57;1
"Unit";"Zergling";"Larva";57;1
"Unit";"Zergling";"Larva";57;1
"Unit";"Zergling";"Larva";57;1
"Unit";"Zergling";"Larva";58;1
"Unit";"Zergling";"Larva";58;1
"Unit";"Baneling";"Zergling";62;0
"Unit";"Baneling";"Zergling";62;0
"Unit";"Baneling";"Zergling";62;0
"Unit";"Baneling";"Zergling";62;0
"Building";"CreepTumor";NA;68;0
"Building";"CreepTumorQueen";NA;68;0
"Unit";"Queen";"Hatchery";57;2
"Building";"CreepTumor";NA;80;0
"Unit";"Baneling";"Zergling";80;0
"Unit";"Baneling";"Zergling";80;0
"Unit";"Baneling";"Zergling";80;0
"Unit";"Baneling";"Zergling";80;0
"Building";"CreepTumor";NA;80;0
"Building";"CreepTumor";NA;80;0
"Building";"Extractor";NA;78;0
"Unit";"Overlord";"Larva";80;0
"Unit";"Overlord";"Larva";81;0
"Unit";"Queen";"Hatchery";78;2
"Unit";"Overlord";"Larva";87;0
"Unit";"Overlord";"Larva";87;0
"Unit";"Overlord";"Larva";87;0
"Unit";"Overlord";"Larva";87;0
"Unit";"Overlord";"Larva";87;0
"Unit";"Overlord";"Larva";87;0
"Unit";"Overlord";"Larva";87;0
"Building";"CreepTumor";NA;87;0
"Building";"CreepTumor";NA;87;0
"Building";"CreepTumorQueen";NA;88;0
"Building";"CreepTumor";NA;93;0
"Building";"CreepTumorQueen";NA;93;0
"Building";"CreepTumorQueen";NA;93;0
"Building";"CreepTumorQueen";NA;93;0
"Building";"HydraliskDen";NA;87;0
"Building";"CreepTumorQueen";NA;102;0
"Building";"CreepTumorQueen";NA;102;0
"Building";"CreepTumor";NA;102;0
"Building";"CreepTumor";NA;102;0
"Upgrade";"ZergMeleeWeaponsLevel1";"EvolutionChamber";85;0
"Building";"CreepTumor";NA;102;0
"Building";"CreepTumor";NA;103;0
"Building";"CreepTumor";NA;106;0
"Building";"Extractor";NA;102;0
"Building";"CreepTumor";NA;106;0
"Building";"CreepTumor";NA;106;0
"Unit";"Hydralisk";"Larva";102;2
"Unit";"Hydralisk";"Larva";102;2
"Building";"Extractor";NA;106;0
"Building";"Extractor";NA;106;0
"Building";"CreepTumor";NA;118;0
"Building";"CreepTumor";NA;119;0
"Unit";"Baneling";"Zergling";119;0
"Unit";"Baneling";"Zergling";119;0
"Unit";"Baneling";"Zergling";119;0
"Unit";"Hydralisk";"Larva";119;2
"Unit";"Hydralisk";"Larva";119;2
"Unit";"Hydralisk";"Larva";119;2
"Building";"CreepTumor";NA;121;0
"Building";"CreepTumor";NA;121;0
"Building";"CreepTumor";NA;121;0
"Building";"InfestationPit";NA;118;0
"Unit";"Overlord";"Larva";121;0
"Unit";"Overlord";"Larva";121;0
"Unit";"Overlord";"Larva";121;0
"Building";"CreepTumorQueen";NA;127;0
"Upgrade";"EvolveGroovedSpines";"HydraliskDen";106;0
"Building";"CreepTumorQueen";NA;127;0
"Upgrade";"ZergMissileWeaponsLevel1";"EvolutionChamber";102;0
"Unit";"Zergling";"Larva";127;1
"Unit";"Zergling";"Larva";127;1
"Unit";"Zergling";"Larva";127;1
"Unit";"Zergling";"Larva";127;1
"Unit";"Zergling";"Larva";127;1
"Unit";"Zergling";"Larva";127;1
"Unit";"Zergling";"Larva";127;1
"Unit";"Zergling";"Larva";127;1
"Unit";"Zergling";"Larva";127;1
"Unit";"Zergling";"Larva";127;1
"Unit";"Zergling";"Larva";127;1
"Unit";"Zergling";"Larva";127;1
"Unit";"Hydralisk";"Larva";127;2
"Unit";"Hydralisk";"Larva";127;2
"Unit";"Hydralisk";"Larva";127;2
"Unit";"Hydralisk";"Larva";127;2
"Unit";"Hydralisk";"Larva";127;2
"Unit";"Hydralisk";"Larva";127;2
"Unit";"Hydralisk";"Larva";127;2
"Building";"CreepTumor";NA;127;0
"Building";"CreepTumorQueen";NA;127;0
"Building";"CreepTumorQueen";NA;127;0
"Building";"CreepTumor";NA;139;0
"Building";"CreepTumorQueen";NA;145;0
"Building";"CreepTumor";NA;139;0
"Building";"CreepTumor";NA;153;0
"Building";"CreepTumor";NA;153;0
"Building";"CreepTumorQueen";NA;153;0
"Building";"Hatchery";NA;119;0
"Unit";"Overlord";"Larva";153;0
"Unit";"Overlord";"Larva";153;0
"Unit";"Hydralisk";"Larva";153;2
"Unit";"Overlord";"Larva";153;0
"Unit";"Hydralisk";"Larva";153;2
"Unit";"Hydralisk";"Larva";153;2
"Unit";"Hydralisk";"Larva";153;2
"Unit";"Hydralisk";"Larva";153;2
"Unit";"Hydralisk";"Larva";153;2
"Unit";"Hydralisk";"Larva";153;2
"Unit";"Overlord";"Larva";153;0
"Unit";"Overlord";"Larva";153;0
"Unit";"Overlord";"Larva";153;0
"Building";"CreepTumor";NA;153;0
"Building";"CreepTumor";NA;153;0
"Upgrade";"ZergGroundArmorsLevel1";"EvolutionChamber";121;0
"Building";"CreepTumor";NA;170;0
"Building";"CreepTumorQueen";NA;170;0
"Building";"CreepTumorQueen";NA;170;0
"Unit";"Zergling";"Larva";170;1
"Unit";"Zergling";"Larva";170;1
"Unit";"Zergling";"Larva";170;1
"Unit";"Zergling";"Larva";170;1
"Unit";"Zergling";"Larva";170;1
"Unit";"Zergling";"Larva";170;1
"Unit";"Zergling";"Larva";170;1
"Unit";"Zergling";"Larva";170;1
"Unit";"Zergling";"Larva";170;1
"Unit";"Zergling";"Larva";170;1
"Unit";"Zergling";"Larva";170;1
"Unit";"Zergling";"Larva";170;1
"Unit";"Zergling";"Larva";170;1
"Unit";"Zergling";"Larva";170;1
"Building";"CreepTumor";NA;170;0
"Building";"CreepTumor";NA;170;0
"Building";"Hatchery";NA;127;0
"Building";"CreepTumor";NA;184;0
"Building";"CreepTumorQueen";NA;184;0
"Building";"CreepTumorQueen";NA;184;0
"Building";"CreepTumor";NA;184;0
"Unit";"Baneling";"Zergling";184;0
"Building";"CreepTumorQueen";NA;184;0
"Unit";"Baneling";"Zergling";184;0
"Upgrade";"EvolveMuscularAugments";"HydraliskDen";170;0
"Building";"Extractor";NA;184;0
"Building";"Extractor";NA;184;0
"Building";"CreepTumor";NA;184;0
"Building";"CreepTumor";NA;184;0
"Building";"CreepTumor";NA;184;0
"Building";"CreepTumor";NA;184;0
"Building";"CreepTumor";NA;184;0
"Building";"Hatchery";NA;170;0
"Building";"CreepTumor";NA;198;0
"Building";"CreepTumorQueen";NA;198;0
"Building";"Extractor";NA;184;0
"Building";"Extractor";NA;184;0
"Building";"CreepTumorQueen";NA;198;0
"Building";"CreepTumor";NA;198;0
"Building";"CreepTumorQueen";NA;198;0
"Building";"CreepTumorQueen";NA;198;0
"Building";"CreepTumorQueen";NA;198;0
"Building";"CreepTumorQueen";NA;198;0
"Building";"CreepTumorQueen";NA;198;0
"Building";"CreepTumor";NA;198;0
"Unit";"Hydralisk";"Larva";198;2
"Unit";"Hydralisk";"Larva";198;2
"Unit";"Hydralisk";"Larva";198;2
"Unit";"Hydralisk";"Larva";198;2
"Unit";"Hydralisk";"Larva";198;2
"Unit";"Hydralisk";"Larva";198;2
"Unit";"Hydralisk";"Larva";198;2
"Unit";"Hydralisk";"Larva";198;2
"Unit";"Hydralisk";"Larva";198;2
"Unit";"Hydralisk";"Larva";198;2
"Unit";"Hydralisk";"Larva";198;2
"Unit";"Baneling";"Zergling";200;0
"Building";"CreepTumor";NA;220;0
"Unit";"Baneling";"Zergling";220;0
"Building";"CreepTumor";NA;220;0
"Unit";"Baneling";"Zergling";220;0
"Building";"CreepTumor";NA;220;0
"Unit";"Baneling";"Zergling";220;0
"Unit";"Baneling";"Zergling";220;0
"Unit";"Baneling";"Zergling";220;0
"Building";"CreepTumor";NA;220;0
"Unit";"Baneling";"Zergling";220;0
"Unit";"Baneling";"Zergling";220;0
"Building";"CreepTumor";NA;220;0
"Building";"CreepTumorQueen";NA;220;0
"Building";"CreepTumor";NA;220;0
"Building";"CreepTumor";NA;220;0
"Building";"Spire";NA;198;0
"Building";"CreepTumorQueen";NA;220;0
"Building";"Spire";NA;198;0
"Building";"CreepTumor";NA;220;0
"Building";"CreepTumor";NA;220;0
"Building";"CreepTumor";NA;220;0
"Building";"CreepTumor";NA;220;0
"Building";"CreepTumor";NA;220;0
"Building";"CreepTumor";NA;220;0
"Unit";"Overlord";"Larva";220;0
"Unit";"Viper";"Larva";220;3
"Unit";"Viper";"Larva";220;3
"Unit";"Viper";"Larva";220;3
"Upgrade";"ZergMissileWeaponsLevel2";"EvolutionChamber";198;0
"Unit";"Hydralisk";"Larva";220;2
"Upgrade";"ZergGroundArmorsLevel2";"EvolutionChamber";198;0
"Unit";"Hydralisk";"Larva";220;2
"Unit";"Hydralisk";"Larva";220;2
"Unit";"Hydralisk";"Larva";220;2
"Unit";"Hydralisk";"Larva";220;2
"Unit";"Hydralisk";"Larva";220;2
"Unit";"Hydralisk";"Larva";220;2
"Unit";"Hydralisk";"Larva";220;2
"Unit";"Hydralisk";"Larva";220;2
"Unit";"Hydralisk";"Larva";220;2
"Unit";"Hydralisk";"Larva";220;2
"Unit";"Hydralisk";"Larva";220;2
"Unit";"Hydralisk";"Larva";220;2
"Unit";"Hydralisk";"Larva";220;2
"Unit";"Hydralisk";"Larva";223;2
"Unit";"Hydralisk";"Larva";223;2
"Unit";"Hydralisk";"Larva";226;2
"Unit";"Hydralisk";"Larva";226;2
"Unit";"Hydralisk";"Larva";226;2
"Unit";"Hydralisk";"Larva";226;2
"Unit";"Hydralisk";"Larva";226;2
"Unit";"Hydralisk";"Larva";229;2
"Unit";"Hydralisk";"Larva";229;2
"Unit";"Hydralisk";"Larva";229;2
"Unit";"Hydralisk";"Larva";229;2
"Unit";"Hydralisk";"Larva";229;2
"Unit";"Hydralisk";"Larva";229;2
"Unit";"Hydralisk";"Larva";229;2
"Unit";"Hydralisk";"Larva";229;2
"Unit";"Hydralisk";"Larva";255;2
"Unit";"Hydralisk";"Larva";255;2
"Building";"CreepTumor";NA;287;0
"Building";"CreepTumor";NA;287;0
"Building";"CreepTumor";NA;287;0
"Building";"CreepTumor";NA;287;0
"Building";"CreepTumor";NA;287;0
"Building";"CreepTumor";NA;287;0
"Building";"CreepTumor";NA;287;0
"Building";"CreepTumor";NA;287;0
"Building";"CreepTumor";NA;287;0
"Building";"CreepTumor";NA;287;0
"Unit";"Hydralisk";"Larva";291;2
"Unit";"Hydralisk";"Larva";291;2
"Unit";"Hydralisk";"Larva";291;2
"Unit";"Hydralisk";"Larva";291;2
"Unit";"Hydralisk";"Larva";291;2
"Unit";"Hydralisk";"Larva";291;2
"Unit";"Hydralisk";"Larva";291;2
"Unit";"Hydralisk";"Larva";291;2
"Unit";"Hydralisk";"Larva";291;2
"Unit";"Hydralisk";"Larva";291;2
"Unit";"Hydralisk";"Larva";291;2
"Unit";"Hydralisk";"Larva";291;2
"Unit";"Hydralisk";"Larva";291;2
"Unit";"Hydralisk";"Larva";291;2
"Unit";"Hydralisk";"Larva";291;2
"Unit";"Hydralisk";"Larva";291;2
"Unit";"Hydralisk";"Larva";291;2
"Unit";"Hydralisk";"Larva";291;2
"Unit";"Hydralisk";"Larva";291;2
"Unit";"Hydralisk";"Larva";291;2
"Unit";"Hydralisk";"Larva";291;2
"Unit";"Hydralisk";"Larva";291;2
"Unit";"Hydralisk";"Larva";291;2
"Unit";"Hydralisk";"Larva";291;2
"Unit";"Hydralisk";"Larva";323;2
"Unit";"Hydralisk";"Larva";323;2
"Unit";"Hydralisk";"Larva";323;2
"Unit";"Hydralisk";"Larva";323;2
"Unit";"Hydralisk";"Larva";323;2
"Building";"CreepTumor";NA;339;0
"Building";"CreepTumor";NA;339;0
"Building";"CreepTumor";NA;339;0
"Building";"CreepTumor";NA;339;0
"Building";"CreepTumorQueen";NA;339;0
"Building";"CreepTumorQueen";NA;349;0
"Unit";"Hydralisk";"Larva";339;2
"Unit";"Hydralisk";"Larva";341;2
"Unit";"Hydralisk";"Larva";341;2
"Unit";"Hydralisk";"Larva";341;2
"Unit";"Hydralisk";"Larva";349;2
"Unit";"Hydralisk";"Larva";349;2
"Unit";"Hydralisk";"Larva";349;2
"Unit";"Hydralisk";"Larva";349;2
"Unit";"Hydralisk";"Larva";349;2
"Unit";"Hydralisk";"Larva";349;2
"Unit";"Hydralisk";"Larva";349;2
"Unit";"Hydralisk";"Larva";349;2
"Unit";"Hydralisk";"Larva";349;2
"Unit";"Hydralisk";"Larva";349;2
"Unit";"Hydralisk";"Larva";349;2
"Unit";"Hydralisk";"Larva";349;2
"Unit";"Hydralisk";"Larva";349;2
"Unit";"Hydralisk";"Larva";349;2
"Unit";"Hydralisk";"Larva";349;2
"Unit";"Hydralisk";"Larva";349;2
"Unit";"Hydralisk";"Larva";349;2
"Unit";"Hydralisk";"Larva";349;2
"Unit";"Hydralisk";"Larva";349;2
"Building";"CreepTumor";NA;395;0
"Upgrade";"ZergMissileWeaponsLevel3";"EvolutionChamber";291;0
"Upgrade";"ZergGroundArmorsLevel3";"EvolutionChamber";291;0
"Unit";"Zergling";"Larva";395;1
"Unit";"Zergling";"Larva";395;1
"Unit";"Zergling";"Larva";395;1
"Unit";"Zergling";"Larva";395;1
"Unit";"Zergling";"Larva";395;1
"Unit";"Zergling";"Larva";395;1
"Unit";"Zergling";"Larva";395;1
"Unit";"Zergling";"Larva";395;1
"Unit";"Zergling";"Larva";395;1
"Unit";"Zergling";"Larva";395;1
"Unit";"Zergling";"Larva";395;1
"Unit";"Zergling";"Larva";395;1
"Unit";"Zergling";"Larva";395;1
"Unit";"Zergling";"Larva";395;1
"Unit";"Zergling";"Larva";395;1
"Unit";"Zergling";"Larva";395;1
"Unit";"Zergling";"Larva";395;1
"Unit";"Zergling";"Larva";395;1
"Unit";"Zergling";"Larva";395;1
"Unit";"Zergling";"Larva";395;1
"Unit";"Zergling";"Larva";395;1
"Unit";"Zergling";"Larva";395;1
"Unit";"Zergling";"Larva";395;1
"Unit";"Zergling";"Larva";395;1
"Unit";"Viper";"Larva";357;3
"Unit";"Viper";"Larva";357;3
"Unit";"Viper";"Larva";357;3
"Building";"Hatchery";NA;349;0
"Building";"Hatchery";NA;349;0
"Unit";"Baneling";"Zergling";428;0
"Unit";"Baneling";"Zergling";428;0
"Unit";"Baneling";"Zergling";428;0
"Unit";"Baneling";"Zergling";428;0
"Unit";"Baneling";"Zergling";428;0
"Unit";"Baneling";"Zergling";428;0
"Unit";"Baneling";"Zergling";428;0
"Unit";"Baneling";"Zergling";428;0
"Unit";"Baneling";"Zergling";428;0
"Unit";"Baneling";"Zergling";428;0
"Unit";"Baneling";"Zergling";428;0
"Unit";"Baneling";"Zergling";428;0
"Unit";"Baneling";"Zergling";428;0
"Unit";"Baneling";"Zergling";428;0
"Unit";"Baneling";"Zergling";428;0
"Unit";"Baneling";"Zergling";428;0
"Unit";"Baneling";"Zergling";428;0
"Unit";"Baneling";"Zergling";428;0
"Unit";"Baneling";"Zergling";428;0
"Unit";"Baneling";"Zergling";428;0
"Unit";"Baneling";"Zergling";428;0
"Unit";"Baneling";"Zergling";428;0
"Unit";"Baneling";"Zergling";428;0
"Unit";"Baneling";"Zergling";428;0
"Building";"Extractor";NA;428;0
"Building";"Extractor";NA;428;0
"Unit";"Zergling";"Larva";428;1
"Unit";"Zergling";"Larva";428;1
"Unit";"Zergling";"Larva";428;1
"Unit";"Zergling";"Larva";428;1
"Unit";"Hydralisk";"Larva";428;2
"Unit";"Hydralisk";"Larva";428;2
"Unit";"Hydralisk";"Larva";428;2
"Unit";"Hydralisk";"Larva";428;2
"Unit";"Hydralisk";"Larva";428;2
"Unit";"Hydralisk";"Larva";428;2
"Unit";"Hydralisk";"Larva";428;2
"Unit";"Hydralisk";"Larva";428;2
"Unit";"Hydralisk";"Larva";428;2
"Unit";"Hydralisk";"Larva";428;2
"Unit";"Hydralisk";"Larva";428;2
"Unit";"Hydralisk";"Larva";428;2
"Unit";"Hydralisk";"Larva";428;2
"Unit";"Hydralisk";"Larva";428;2
"Unit";"Hydralisk";"Larva";428;2
"Unit";"Hydralisk";"Larva";428;2
"Unit";"Hydralisk";"Larva";428;2
"Unit";"Hydralisk";"Larva";428;2
"Unit";"Hydralisk";"Larva";428;2
"Unit";"Hydralisk";"Larva";428;2
"Unit";"Hydralisk";"Larva";428;2
"Unit";"Hydralisk";"Larva";428;2
"Unit";"Hydralisk";"Larva";428;2
"Building";"CreepTumor";NA;432;0
"Building";"CreepTumor";NA;432;0
"Unit";"Hydralisk";"Larva";478;2
"Unit";"Hydralisk";"Larva";478;2
"Unit";"Hydralisk";"Larva";478;2
"Unit";"Hydralisk";"Larva";478;2
"Unit";"Hydralisk";"Larva";478;2
"Unit";"Hydralisk";"Larva";478;2
"Unit";"Hydralisk";"Larva";478;2
"Unit";"Hydralisk";"Larva";478;2
"Unit";"Hydralisk";"Larva";478;2
"Unit";"Hydralisk";"Larva";478;2
"Unit";"Hydralisk";"Larva";478;2
"Unit";"Hydralisk";"Larva";478;2
"Unit";"Hydralisk";"Larva";478;2
"Unit";"Hydralisk";"Larva";490;2
"Unit";"Hydralisk";"Larva";490;2
"Building";"CreepTumor";NA;504;0
"Unit";"Hydralisk";"Larva";508;2
"Unit";"Hydralisk";"Larva";508;2
"Unit";"Hydralisk";"Larva";508;2
"Unit";"Hydralisk";"Larva";508;2
"Unit";"Hydralisk";"Larva";508;2
"Unit";"Hydralisk";"Larva";508;2
"Unit";"Hydralisk";"Larva";508;2
"Unit";"Hydralisk";"Larva";508;2
"Unit";"Hydralisk";"Larva";508;2
"Unit";"Hydralisk";"Larva";508;2
"Unit";"Hydralisk";"Larva";508;2
"Unit";"Hydralisk";"Larva";508;2
"Unit";"Hydralisk";"Larva";508;2
"Unit";"Hydralisk";"Larva";508;2
"Unit";"Hydralisk";"Larva";508;2
"Unit";"Hydralisk";"Larva";508;2
"Unit";"Hydralisk";"Larva";508;2
"Unit";"Hydralisk";"Larva";508;2
"Unit";"Hydralisk";"Larva";508;2
"Unit";"Hydralisk";"Larva";508;2
"Unit";"Hydralisk";"Larva";508;2
"Unit";"Hydralisk";"Larva";508;2
"Unit";"Hydralisk";"Larva";508;2
"Unit";"Hydralisk";"Larva";508;2
"Unit";"Hydralisk";"Larva";508;2
"Unit";"Hydralisk";"Larva";508;2
"Unit";"Hydralisk";"Larva";508;2
"Unit";"Hydralisk";"Larva";508;2
"Unit";"Hydralisk";"Larva";508;2
"Unit";"Hydralisk";"Larva";508;2
"Unit";"Hydralisk";"Larva";508;2
"Unit";"Zergling";"Larva";508;1
"Unit";"Zergling";"Larva";508;1
"Unit";"Zergling";"Larva";508;1
"Unit";"Zergling";"Larva";508;1
"Unit";"Zergling";"Larva";508;1
"Unit";"Zergling";"Larva";508;1
"Unit";"Zergling";"Larva";508;1
"Unit";"Zergling";"Larva";508;1
"Unit";"Zergling";"Larva";508;1
"Unit";"Zergling";"Larva";508;1
"Unit";"Zergling";"Larva";508;1
"Unit";"Zergling";"Larva";508;1
"Unit";"Zergling";"Larva";508;1
"Unit";"Zergling";"Larva";508;1
"Unit";"Zergling";"Larva";508;1
"Unit";"Zergling";"Larva";508;1
"Unit";"Zergling";"Larva";508;1
"Unit";"Zergling";"Larva";508;1
"Unit";"Zergling";"Larva";508;1
"Unit";"Zergling";"Larva";508;1
"Unit";"Zergling";"Larva";508;1
"Unit";"Zergling";"Larva";508;1
"Unit";"Zergling";"Larva";508;1
"Unit";"Zergling";"Larva";508;1
"Unit";"Zergling";"Larva";508;1
"Unit";"Zergling";"Larva";508;1
"Unit";"Zergling";"Larva";508;1
"Unit";"Zergling";"Larva";508;1
"Unit";"Zergling";"Larva";508;1
"Unit";"Zergling";"Larva";508;1
"Upgrade";"ZergMeleeWeaponsLevel2";"EvolutionChamber";478;0
"Building";"CreepTumor";NA;508;0
"Building";"CreepTumor";NA;508;0
"Building";"CreepTumor";NA;508;0
"Building";"CreepTumor";NA;508;0
"Unit";"Corruptor";"Larva";508;2
"Unit";"Corruptor";"Larva";508;2
"Unit";"Corruptor";"Larva";508;2
"Unit";"Corruptor";"Larva";508;2
"Unit";"Corruptor";"Larva";508;2
"Unit";"Hydralisk";"Larva";614;2
"Unit";"Hydralisk";"Larva";614;2
"Unit";"Hydralisk";"Larva";614;2
"Unit";"Hydralisk";"Larva";614;2
"Unit";"Hydralisk";"Larva";614;2
"Unit";"Hydralisk";"Larva";614;2
"Unit";"Hydralisk";"Larva";614;2
"Unit";"Hydralisk";"Larva";614;2
"Unit";"Hydralisk";"Larva";614;2
"Unit";"Hydralisk";"Larva";614;2
"Unit";"Hydralisk";"Larva";614;2
"Unit";"Hydralisk";"Larva";614;2
"Unit";"Hydralisk";"Larva";614;2
"Unit";"Hydralisk";"Larva";614;2
"Unit";"Hydralisk";"Larva";614;2
"Unit";"Hydralisk";"Larva";614;2
"Unit";"Hydralisk";"Larva";614;2
"Unit";"Hydralisk";"Larva";614;2
"Unit";"Hydralisk";"Larva";614;2
"Unit";"Zergling";"Larva";614;1
"Unit";"Zergling";"Larva";614;1
"Unit";"Zergling";"Larva";614;1
"Unit";"Zergling";"Larva";614;1
"Unit";"Zergling";"Larva";614;1
"Unit";"Zergling";"Larva";614;1
"Unit";"Zergling";"Larva";614;1
"Unit";"Zergling";"Larva";614;1
"Unit";"Zergling";"Larva";614;1
"Unit";"Zergling";"Larva";614;1
"Unit";"Zergling";"Larva";614;1
"Unit";"Zergling";"Larva";614;1
"Building";"CreepTumor";NA;671;0
"Building";"CreepTumor";NA;671;0
"Building";"Hatchery";NA;614;0
"Building";"CreepTumorQueen";NA;671;0
"Unit";"Baneling";"Zergling";671;0
"Unit";"Baneling";"Zergling";671;0
"Unit";"Baneling";"Zergling";671;0
"Unit";"Baneling";"Zergling";671;0
"Unit";"Baneling";"Zergling";671;0
"Unit";"Baneling";"Zergling";671;0
"Unit";"Baneling";"Zergling";671;0
"Unit";"Baneling";"Zergling";671;0
"Building";"CreepTumorQueen";NA;671;0
"Building";"CreepTumorQueen";NA;683;0
"Building";"CreepTumorQueen";NA;683;0
"Building";"CreepTumorQueen";NA;683;0
"Building";"CreepTumorQueen";NA;683;0
"Building";"CreepTumor";NA;683;0
"Building";"CreepTumor";NA;683;0
"Unit";"Baneling";"Zergling";683;0
"Unit";"Baneling";"Zergling";683;0
"Building";"CreepTumor";NA;683;0
"Unit";"Hydralisk";"Larva";683;2
"Unit";"Hydralisk";"Larva";683;2
"Unit";"Hydralisk";"Larva";683;2
"Unit";"Hydralisk";"Larva";683;2
"Unit";"Hydralisk";"Larva";683;2
"Unit";"Hydralisk";"Larva";683;2
"Unit";"Hydralisk";"Larva";683;2
"Unit";"Hydralisk";"Larva";683;2
"Unit";"Hydralisk";"Larva";683;2
"Unit";"Hydralisk";"Larva";683;2
"Unit";"Hydralisk";"Larva";683;2
"Unit";"Hydralisk";"Larva";683;2
"Unit";"Hydralisk";"Larva";683;2
"Building";"CreepTumor";NA;709;0
"Building";"CreepTumor";NA;709;0
"Building";"CreepTumor";NA;709;0
"Building";"CreepTumor";NA;709;0
"Building";"CreepTumor";NA;709;0
"Building";"CreepTumorQueen";NA;709;0
"Building";"CreepTumorQueen";NA;709;0
"Building";"CreepTumorQueen";NA;709;0
"Unit";"Viper";"Larva";709;3
"Unit";"Viper";"Larva";709;3
"Unit";"Hydralisk";"Larva";709;2
"Unit";"Hydralisk";"Larva";709;2
"Unit";"Hydralisk";"Larva";709;2
"Unit";"Hydralisk";"Larva";709;2
"Unit";"Hydralisk";"Larva";709;2
"Unit";"Hydralisk";"Larva";709;2
"Unit";"Hydralisk";"Larva";709;2
"Unit";"Hydralisk";"Larva";709;2
"Unit";"Hydralisk";"Larva";709;2
"Unit";"Hydralisk";"Larva";709;2
"Unit";"Hydralisk";"Larva";709;2
"Unit";"Hydralisk";"Larva";709;2
"Building";"CreepTumor";NA;739;0
"Building";"CreepTumor";NA;739;0
"Building";"SpineCrawler";NA;715;0
"Building";"SpineCrawler";NA;715;0
"Building";"SpineCrawler";NA;715;0
"Unit";"Corruptor";"Larva";715;2
"Unit";"Corruptor";"Larva";715;2
"Unit";"Corruptor";"Larva";715;2
"Unit";"Corruptor";"Larva";715;2
"Unit";"Corruptor";"Larva";715;2
"Building";"Extractor";NA;739;0
"Building";"Extractor";NA;739;0
"Unit";"Hydralisk";"Larva";739;2
"Unit";"Hydralisk";"Larva";739;2
"Unit";"Hydralisk";"Larva";739;2
"Unit";"Hydralisk";"Larva";739;2
"Unit";"Hydralisk";"Larva";739;2
"Unit";"Hydralisk";"Larva";739;2
"Unit";"Hydralisk";"Larva";739;2
"Unit";"Hydralisk";"Larva";739;2
"Unit";"Hydralisk";"Larva";739;2
"Unit";"Hydralisk";"Larva";739;2
"Unit";"Hydralisk";"Larva";739;2
"Unit";"Hydralisk";"Larva";739;2
"Unit";"Hydralisk";"Larva";739;2
"Unit";"Hydralisk";"Larva";739;2
"Unit";"Hydralisk";"Larva";739;2
"Unit";"Hydralisk";"Larva";739;2
"Unit";"Hydralisk";"Larva";739;2
"Unit";"Hydralisk";"Larva";739;2
"Unit";"Hydralisk";"Larva";739;2
"Unit";"Hydralisk";"Larva";739;2
"Unit";"Hydralisk";"Larva";739;2
"Building";"UltraliskCavern";NA;715;0
"Building";"CreepTumor";NA;791;0
"Unit";"Hydralisk";"Larva";749;2
"Unit";"Hydralisk";"Larva";751;2
"Unit";"Hydralisk";"Larva";751;2
"Unit";"Hydralisk";"Larva";751;2
"Unit";"Hydralisk";"Larva";791;2
"Unit";"Hydralisk";"Larva";791;2
"Unit";"Hydralisk";"Larva";791;2
"Unit";"Hydralisk";"Larva";791;2
"Unit";"Hydralisk";"Larva";791;2
"Unit";"Hydralisk";"Larva";791;2
"Unit";"Hydralisk";"Larva";791;2
"Unit";"Hydralisk";"Larva";791;2
"Unit";"Hydralisk";"Larva";791;2
"Unit";"Hydralisk";"Larva";791;2
"Unit";"Hydralisk";"Larva";819;2
"Unit";"Hydralisk";"Larva";819;2
"Unit";"Hydralisk";"Larva";819;2
"Unit";"Hydralisk";"Larva";819;2
"Unit";"Hydralisk";"Larva";819;2
"Unit";"Hydralisk";"Larva";819;2
"Unit";"Hydralisk";"Larva";819;2
"Unit";"Hydralisk";"Larva";819;2
"Unit";"Hydralisk";"Larva";819;2
"Unit";"Hydralisk";"Larva";837;2
"Unit";"Hydralisk";"Larva";837;2
"Unit";"Hydralisk";"Larva";837;2
"Unit";"Hydralisk";"Larva";837;2
"Unit";"Hydralisk";"Larva";837;2
"Unit";"Hydralisk";"Larva";837;2
"Unit";"Hydralisk";"Larva";837;2
"Unit";"Hydralisk";"Larva";837;2
"Unit";"Hydralisk";"Larva";837;2
"Unit";"Hydralisk";"Larva";837;2
"Unit";"Hydralisk";"Larva";837;2
"Unit";"Hydralisk";"Larva";837;2
"Unit";"Hydralisk";"Larva";837;2
"Unit";"Hydralisk";"Larva";837;2
"Unit";"Hydralisk";"Larva";837;2
"Unit";"Hydralisk";"Larva";867;2
"Unit";"Hydralisk";"Larva";867;2
"Unit";"Hydralisk";"Larva";867;2
"Unit";"Hydralisk";"Larva";867;2
"Building";"CreepTumor";NA;882;0
"Unit";"Viper";"Larva";882;3
"Unit";"Viper";"Larva";882;3
"Unit";"Viper";"Larva";882;3
"Unit";"Hydralisk";"Larva";882;2
"Unit";"Hydralisk";"Larva";882;2
"Unit";"Hydralisk";"Larva";882;2
"Unit";"Hydralisk";"Larva";882;2
"Unit";"Hydralisk";"Larva";882;2
"Unit";"Hydralisk";"Larva";882;2
"Unit";"Hydralisk";"Larva";882;2
"Unit";"Hydralisk";"Larva";882;2
"Unit";"Hydralisk";"Larva";882;2
"Unit";"Hydralisk";"Larva";882;2
"Unit";"Hydralisk";"Larva";882;2
"Unit";"Hydralisk";"Larva";882;2
"Unit";"Hydralisk";"Larva";882;2
"Unit";"Hydralisk";"Larva";882;2
"Building";"Extractor";NA;891;0
"Building";"Hatchery";NA;882;0
"Unit";"Hydralisk";"Larva";919;2
"Unit";"Hydralisk";"Larva";919;2
"Unit";"Hydralisk";"Larva";919;2
"Unit";"Hydralisk";"Larva";919;2
"Unit";"Hydralisk";"Larva";919;2
"Unit";"Hydralisk";"Larva";919;2
"Unit";"Zergling";"Larva";934;1
"Unit";"Zergling";"Larva";934;1
"Unit";"Zergling";"Larva";934;1
"Unit";"Zergling";"Larva";934;1
"Unit";"Zergling";"Larva";934;1
"Unit";"Zergling";"Larva";934;1
"Unit";"Zergling";"Larva";934;1
"Unit";"Zergling";"Larva";934;1
"Unit";"Zergling";"Larva";934;1
"Unit";"Zergling";"Larva";934;1
"Unit";"Zergling";"Larva";934;1
"Unit";"Zergling";"Larva";934;1
"Unit";"Zergling";"Larva";934;1
"Unit";"Zergling";"Larva";934;1
"Unit";"Zergling";"Larva";934;1
"Unit";"Zergling";"Larva";934;1
"Unit";"Zergling";"Larva";934;1
"Unit";"Zergling";"Larva";934;1
"Unit";"Zergling";"Larva";934;1
"Unit";"Zergling";"Larva";934;1
"Unit";"Zergling";"Larva";934;1
"Unit";"Zergling";"Larva";934;1
"Unit";"Zergling";"Larva";934;1
"Unit";"Zergling";"Larva";934;1
"Unit";"Zergling";"Larva";934;1
"Unit";"Zergling";"Larva";934;1
"Unit";"Zergling";"Larva";934;1
"Unit";"Zergling";"Larva";934;1
"Unit";"Zergling";"Larva";934;1
"Unit";"Zergling";"Larva";934;1
"Unit";"Zergling";"Larva";934;1
"Unit";"Zergling";"Larva";934;1
"Unit";"Zergling";"Larva";934;1
"Unit";"Zergling";"Larva";934;1
"Unit";"Zergling";"Larva";934;1
"Unit";"Zergling";"Larva";934;1
"Unit";"Zergling";"Larva";934;1
"Unit";"Zergling";"Larva";934;1
"Unit";"Zergling";"Larva";934;1
"Unit";"Zergling";"Larva";934;1
"Unit";"Zergling";"Larva";934;1
"Unit";"Zergling";"Larva";934;1
"Unit";"Zergling";"Larva";934;1
"Unit";"Zergling";"Larva";934;1
"Unit";"Zergling";"Larva";934;1
"Unit";"Zergling";"Larva";934;1
"Unit";"Baneling";"Zergling";980;0
"Unit";"Baneling";"Zergling";980;0
"Unit";"Baneling";"Zergling";980;0
"Unit";"Baneling";"Zergling";980;0
"Unit";"Baneling";"Zergling";980;0
"Unit";"Baneling";"Zergling";980;0
"Unit";"Baneling";"Zergling";980;0
"Unit";"Baneling";"Zergling";980;0
"Unit";"Hydralisk";"Larva";980;2
"Unit";"Hydralisk";"Larva";980;2
"Unit";"Hydralisk";"Larva";980;2
"Unit";"Hydralisk";"Larva";980;2
"Unit";"Hydralisk";"Larva";980;2
"Unit";"Hydralisk";"Larva";980;2
"Unit";"Hydralisk";"Larva";980;2
"Unit";"Hydralisk";"Larva";980;2
"Unit";"Hydralisk";"Larva";980;2
"Unit";"Zergling";"Larva";998;1
"Unit";"Zergling";"Larva";998;1
"Unit";"Zergling";"Larva";998;1
"Unit";"Zergling";"Larva";998;1
"Unit";"Zergling";"Larva";998;1
"Unit";"Zergling";"Larva";998;1
"Unit";"Zergling";"Larva";998;1
"Unit";"Zergling";"Larva";998;1
"Unit";"Zergling";"Larva";998;1
"Unit";"Zergling";"Larva";998;1
"Unit";"Zergling";"Larva";998;1
"Unit";"Zergling";"Larva";998;1
"Unit";"Zergling";"Larva";998;1
"Unit";"Zergling";"Larva";998;1
"Unit";"Zergling";"Larva";998;1
"Unit";"Zergling";"Larva";998;1
"Unit";"Zergling";"Larva";998;1
"Unit";"Zergling";"Larva";998;1
"Unit";"Zergling";"Larva";998;1
"Unit";"Zergling";"Larva";998;1
"Unit";"Zergling";"Larva";998;1
"Unit";"Zergling";"Larva";998;1
"Unit";"Zergling";"Larva";998;1
"Unit";"Zergling";"Larva";998;1
"Unit";"Zergling";"Larva";998;1
"Unit";"Zergling";"Larva";998;1
"Unit";"Zergling";"Larva";998;1
"Unit";"Zergling";"Larva";998;1
"Unit";"Zergling";"Larva";998;1
"Unit";"Zergling";"Larva";998;1
"Unit";"Zergling";"Larva";998;1
"Unit";"Zergling";"Larva";998;1
"Unit";"Zergling";"Larva";998;1
"Unit";"Zergling";"Larva";998;1
"Unit";"Hydralisk";"Larva";998;2
"Unit";"Hydralisk";"Larva";998;2
"Unit";"Hydralisk";"Larva";998;2
"Unit";"Hydralisk";"Larva";998;2
"Unit";"Hydralisk";"Larva";998;2
"Unit";"Hydralisk";"Larva";998;2
"Unit";"Hydralisk";"Larva";998;2
"Building";"SporeCrawler";NA;1046;0
"Building";"SporeCrawler";NA;1046;0
"Building";"SporeCrawler";NA;1046;0
"Building";"CreepTumor";NA;1046;0
"Unit";"Zergling";"Larva";1046;1
"Unit";"Zergling";"Larva";1046;1
"Unit";"Zergling";"Larva";1046;1
"Unit";"Zergling";"Larva";1046;1
"Unit";"Zergling";"Larva";1046;1
"Unit";"Zergling";"Larva";1046;1
"Unit";"Zergling";"Larva";1046;1
"Unit";"Zergling";"Larva";1046;1
"Unit";"Zergling";"Larva";1046;1
"Unit";"Zergling";"Larva";1046;1
"Unit";"Zergling";"Larva";1046;1
"Unit";"Zergling";"Larva";1046;1
"Unit";"Zergling";"Larva";1046;1
"Unit";"Zergling";"Larva";1046;1
"Unit";"Zergling";"Larva";1046;1
"Unit";"Zergling";"Larva";1046;1
"Unit";"Zergling";"Larva";1046;1
"Unit";"Zergling";"Larva";1046;1
"Unit";"Zergling";"Larva";1046;1
"Unit";"Zergling";"Larva";1046;1
"Unit";"Zergling";"Larva";1046;1
"Unit";"Zergling";"Larva";1046;1
"Unit";"Zergling";"Larva";1046;1
"Unit";"Zergling";"Larva";1046;1
"Unit";"Zergling";"Larva";1046;1
"Unit";"Zergling";"Larva";1046;1
"Unit";"Zergling";"Larva";1046;1
"Unit";"Zergling";"Larva";1046;1
"Unit";"Zergling";"Larva";1046;1
"Unit";"Zergling";"Larva";1046;1
"Unit";"Zergling";"Larva";1046;1
"Unit";"Zergling";"Larva";1046;1
"Unit";"Zergling";"Larva";1046;1
"Unit";"Zergling";"Larva";1046;1
"Unit";"Zergling";"Larva";1046;1
"Unit";"Zergling";"Larva";1046;1
"Unit";"Zergling";"Larva";1046;1
"Unit";"Zergling";"Larva";1046;1
"Unit";"Zergling";"Larva";1046;1
"Unit";"Zergling";"Larva";1046;1
"Unit";"Zergling";"Larva";1046;1
"Unit";"Zergling";"Larva";1046;1
"Unit";"Hydralisk";"Larva";1088;2
"Unit";"Hydralisk";"Larva";1088;2
"Unit";"Hydralisk";"Larva";1088;2
"Unit";"Hydralisk";"Larva";1088;2
"Unit";"Hydralisk";"Larva";1088;2
"Building";"Hatchery";NA;1046;0
"Building";"Hatchery";NA;1046;0
"Unit";"Zergling";"Larva";1088;1
"Unit";"Zergling";"Larva";1088;1
"Unit";"Zergling";"Larva";1088;1
"Unit";"Zergling";"Larva";1088;1
"Unit";"Zergling";"Larva";1088;1
"Unit";"Zergling";"Larva";1088;1
"Unit";"Zergling";"Larva";1088;1
"Unit";"Zergling";"Larva";1088;1
"Unit";"Zergling";"Larva";1088;1
"Unit";"Zergling";"Larva";1088;1
"Unit";"Zergling";"Larva";1088;1
"Unit";"Zergling";"Larva";1088;1
"Unit";"Zergling";"Larva";1088;1
"Unit";"Zergling";"Larva";1088;1
"Unit";"Zergling";"Larva";1088;1
"Unit";"Zergling";"Larva";1088;1
"Unit";"Zergling";"Larva";1088;1
"Unit";"Zergling";"Larva";1088;1
"Unit";"Zergling";"Larva";1088;1
"Unit";"Zergling";"Larva";1088;1
"Unit";"Zergling";"Larva";1088;1
"Unit";"Zergling";"Larva";1088;1
"Unit";"Zergling";"Larva";1088;1
"Unit";"Zergling";"Larva";1088;1
"Unit";"Zergling";"Larva";1088;1
"Unit";"Zergling";"Larva";1088;1
"Unit";"Zergling";"Larva";1088;1
"Unit";"Zergling";"Larva";1088;1
"Unit";"Zergling";"Larva";1088;1
"Unit";"Zergling";"Larva";1088;1
"Unit";"Zergling";"Larva";1088;1
"Unit";"Zergling";"Larva";1088;1
"Unit";"Zergling";"Larva";1088;1
"Unit";"Zergling";"Larva";1088;1
"Unit";"Zergling";"Larva";1088;1
"Unit";"Zergling";"Larva";1088;1
"Unit";"Zergling";"Larva";1088;1
"Unit";"Zergling";"Larva";1088;1
"Unit";"Zergling";"Larva";1088;1
"Unit";"Zergling";"Larva";1088;1
"Unit";"Hydralisk";"Larva";1138;2
"Building";"Extractor";NA;1138;0
"Building";"Extractor";NA;1141;0
"Building";"Extractor";NA;1145;0
"Unit";"Zergling";"Larva";1145;1
"Unit";"Zergling";"Larva";1145;1
"Unit";"Zergling";"Larva";1145;1
"Unit";"Zergling";"Larva";1145;1
"Unit";"Zergling";"Larva";1145;1
"Unit";"Zergling";"Larva";1145;1
"Unit";"Zergling";"Larva";1145;1
"Unit";"Zergling";"Larva";1145;1
"Unit";"Zergling";"Larva";1145;1
"Unit";"Zergling";"Larva";1145;1
"Unit";"Zergling";"Larva";1145;1
"Unit";"Zergling";"Larva";1145;1
"Unit";"Zergling";"Larva";1145;1
"Unit";"Zergling";"Larva";1145;1
"Unit";"Zergling";"Larva";1145;1
"Unit";"Zergling";"Larva";1145;1
"Building";"Extractor";NA;1145;0
"Unit";"Zergling";"Larva";1145;1
"Unit";"Zergling";"Larva";1145;1
"Unit";"Zergling";"Larva";1145;1
"Unit";"Zergling";"Larva";1145;1
"Unit";"Zergling";"Larva";1145;1
"Unit";"Zergling";"Larva";1145;1
"Unit";"Zergling";"Larva";1145;1
"Unit";"Zergling";"Larva";1145;1
"Unit";"Zergling";"Larva";1145;1
"Unit";"Zergling";"Larva";1145;1
"Unit";"Zergling";"Larva";1145;1
"Unit";"Zergling";"Larva";1145;1
"Unit";"Zergling";"Larva";1145;1
"Unit";"Zergling";"Larva";1145;1
"Unit";"Zergling";"Larva";1145;1
"Unit";"Zergling";"Larva";1145;1
"Unit";"Zergling";"Larva";1145;1
"Unit";"Zergling";"Larva";1145;1
"Unit";"Zergling";"Larva";1145;1
"Unit";"Zergling";"Larva";1145;1
"Unit";"Zergling";"Larva";1145;1
"Unit";"Zergling";"Larva";1145;1
"Unit";"Zergling";"Larva";1145;1
"Unit";"Zergling";"Larva";1145;1
"Unit";"Zergling";"Larva";1145;1
"Unit";"Zergling";"Larva";1145;1
"Unit";"Zergling";"Larva";1145;1
"Unit";"Zergling";"Larva";1145;1
"Unit";"Zergling";"Larva";1145;1
"Unit";"Zergling";"Larva";1145;1
"Unit";"Zergling";"Larva";1145;1
"Unit";"Zergling";"Larva";1145;1
"Unit";"Zergling";"Larva";1145;1
"Unit";"Zergling";"Larva";1145;1
"Unit";"Zergling";"Larva";1145;1
"Unit";"Zergling";"Larva";1145;1
"Unit";"Hydralisk";"Larva";1145;2
"Unit";"Hydralisk";"Larva";1199;2
"Unit";"Hydralisk";"Larva";1199;2
"Building";"SporeCrawler";NA;1204;0
"Building";"SporeCrawler";NA;1204;0
"Building";"SporeCrawler";NA;1204;0
"Unit";"Hydralisk";"Larva";1204;2
"Unit";"Hydralisk";"Larva";1204;2
"Unit";"Hydralisk";"Larva";1204;2
"Unit";"Hydralisk";"Larva";1204;2
"Unit";"Hydralisk";"Larva";1204;2
"Unit";"Hydralisk";"Larva";1210;2
"Unit";"Hydralisk";"Larva";1214;2
"Unit";"Hydralisk";"Larva";1214;2
"Unit";"Hydralisk";"Larva";1216;2
"Unit";"Corruptor";"Larva";1216;2
"Unit";"Hydralisk";"Larva";1225;2
"Unit";"Hydralisk";"Larva";1231;2
"Unit";"Hydralisk";"Larva";1231;2
"Building";"SpineCrawler";NA;1237;0
"Building";"SpineCrawler";NA;1237;0
"Unit";"Hydralisk";"Larva";1239;2
"Unit";"Hydralisk";"Larva";1239;2
"Building";"CreepTumor";NA;1249;0
"Building";"CreepTumor";NA;1252;0
"Building";"CreepTumor";NA;1258;0
"Building";"Hatchery";NA;1258;0
"Building";"CreepTumor";NA;1276;0
"Building";"Extractor";NA;1282;0
"Building";"Extractor";NA;1282;0
"Unit";"Hydralisk";"Larva";1291;2
"Unit";"Hydralisk";"Larva";1291;2
"Unit";"Hydralisk";"Larva";1291;2
"Unit";"Hydralisk";"Larva";1299;2
"Unit";"Hydralisk";"Larva";1299;2
"Unit";"Hydralisk";"Larva";1299;2
"Unit";"Hydralisk";"Larva";1299;2
"Unit";"Hydralisk";"Larva";1299;2
"Unit";"Hydralisk";"Larva";1299;2
"Unit";"Hydralisk";"Larva";1299;2
"Unit";"Hydralisk";"Larva";1299;2
"Unit";"Hydralisk";"Larva";1299;2
"Unit";"Hydralisk";"Larva";1299;2
"Unit";"Hydralisk";"Larva";1299;2
"Unit";"Hydralisk";"Larva";1311;2
"Unit";"Hydralisk";"Larva";1311;2
