"type";"unit_name";"on_building";"total_supply_lag";"supply"
"Unit";"Overlord";"Larva";13;0
"Building";"Hatchery";NA;17;0
"Building";"SpawningPool";NA;19;0
"Building";"Hatchery";NA;21;0
"Unit";"Queen";"Hatchery";23;2
"Unit";"Queen";"Hatchery";25;2
"Unit";"Zergling";"Larva";27;1
"Unit";"Zergling";"Larva";28;1
"Unit";"Zergling";"Larva";29;1
"Unit";"Zergling";"Larva";30;1
"Unit";"Overlord";"Larva";31;0
"Unit";"Queen";"Hatchery";37;2
"Building";"CreepTumorQueen";NA;39;0
"Unit";"Queen";"Hatchery";41;2
"Unit";"Overlord";"Larva";44;0
"Unit";"Overlord";"Larva";47;0
"Building";"Extractor";NA;51;0
"Building";"Extractor";NA;53;0
"Unit";"Queen";"Hatchery";54;2
"Building";"CreepTumor";NA;56;0
"Unit";"Overlord";"Larva";56;0
"Building";"CreepTumorQueen";NA;61;0
"Unit";"Overlord";"Larva";64;0
"Building";"CreepTumorQueen";NA;64;0
"Unit";"Overlord";"Larva";66;0
"Unit";"Overlord";"Larva";68;0
"Building";"EvolutionChamber";NA;68;0
"Unit";"Queen";"Hatchery";68;2
"Building";"EvolutionChamber";NA;70;0
"Building";"CreepTumor";NA;72;0
"Building";"CreepTumor";NA;74;0
"Building";"CreepTumorQueen";NA;76;0
"Building";"SporeCrawler";NA;76;0
"Unit";"Zergling";"Larva";76;1
"Unit";"Zergling";"Larva";77;1
"Unit";"Zergling";"Larva";78;1
"Unit";"Zergling";"Larva";79;1
"Unit";"Zergling";"Larva";80;1
"Unit";"Zergling";"Larva";81;1
"Building";"SporeCrawler";NA;82;0
"Unit";"Zergling";"Larva";82;1
"Unit";"Zergling";"Larva";83;1
"Unit";"Zergling";"Larva";84;1
"Unit";"Zergling";"Larva";85;1
"Unit";"Zergling";"Larva";86;1
"Unit";"Zergling";"Larva";87;1
"Building";"CreepTumor";NA;101;0
"Building";"CreepTumor";NA;101;0
"Building";"CreepTumor";NA;101;0
"Building";"CreepTumorQueen";NA;104;0
"Building";"CreepTumorQueen";NA;104;0
"Building";"CreepTumorQueen";NA;104;0
"Building";"Extractor";NA;106;0
"Building";"Extractor";NA;106;0
"Unit";"Overlord";"Larva";108;0
"Building";"BanelingNest";NA;110;0
"Building";"CreepTumor";NA;113;0
"Building";"CreepTumor";NA;114;0
"Building";"CreepTumor";NA;114;0
"Building";"CreepTumor";NA;114;0
"Building";"CreepTumor";NA;115;0
"Building";"CreepTumor";NA;115;0
"Building";"Hatchery";NA;115;0
"Building";"Extractor";NA;120;0
"Building";"Extractor";NA;120;0
"Unit";"Overlord";"Larva";122;0
"Unit";"Overlord";"Larva";122;0
"Unit";"Zergling";"Larva";122;1
"Unit";"Zergling";"Larva";123;1
"Unit";"Zergling";"Larva";124;1
"Unit";"Zergling";"Larva";125;1
"Unit";"Zergling";"Larva";126;1
"Unit";"Zergling";"Larva";127;1
"Unit";"Zergling";"Larva";128;1
"Unit";"Zergling";"Larva";129;1
"Unit";"Overlord";"Larva";130;0
"Unit";"Overlord";"Larva";130;0
"Unit";"Overlord";"Larva";130;0
"Building";"CreepTumor";NA;130;0
"Building";"CreepTumor";NA;130;0
"Building";"CreepTumor";NA;130;0
"Unit";"Zergling";"Larva";130;1
"Unit";"Zergling";"Larva";131;1
"Unit";"Zergling";"Larva";132;1
"Unit";"Zergling";"Larva";133;1
"Unit";"Zergling";"Larva";134;1
"Unit";"Zergling";"Larva";135;1
"Unit";"Zergling";"Larva";136;1
"Unit";"Zergling";"Larva";137;1
"Unit";"Zergling";"Larva";138;1
"Unit";"Zergling";"Larva";139;1
"Building";"CreepTumor";NA;140;0
"Building";"CreepTumor";NA;140;0
"Building";"CreepTumor";NA;140;0
"Unit";"Zergling";"Larva";141;1
"Unit";"Zergling";"Larva";142;1
"Unit";"Zergling";"Larva";143;1
"Unit";"Zergling";"Larva";144;1
"Building";"Spire";NA;145;0
"Unit";"Baneling";"Zergling";145;0
"Unit";"Baneling";"Zergling";145;0
"Unit";"Baneling";"Zergling";145;0
"Unit";"Baneling";"Zergling";145;0
"Unit";"Baneling";"Zergling";145;0
"Unit";"Baneling";"Zergling";145;0
"Unit";"Baneling";"Zergling";145;0
"Unit";"Baneling";"Zergling";145;0
"Unit";"Baneling";"Zergling";145;0
"Unit";"Zergling";"Larva";147;1
"Unit";"Zergling";"Larva";148;1
"Unit";"Zergling";"Larva";149;1
"Unit";"Zergling";"Larva";150;1
"Unit";"Zergling";"Larva";151;1
"Unit";"Zergling";"Larva";152;1
"Unit";"Zergling";"Larva";153;1
"Unit";"Zergling";"Larva";154;1
"Unit";"Zergling";"Larva";155;1
"Unit";"Zergling";"Larva";156;1
"Unit";"Zergling";"Larva";157;1
"Unit";"Zergling";"Larva";158;1
"Unit";"Zergling";"Larva";159;1
"Unit";"Zergling";"Larva";160;1
"Unit";"Zergling";"Larva";161;1
"Unit";"Zergling";"Larva";162;1
"Building";"CreepTumor";NA;163;0
"Unit";"Zergling";"Larva";163;1
"Unit";"Zergling";"Larva";164;1
"Unit";"Zergling";"Larva";165;1
"Unit";"Zergling";"Larva";166;1
"Building";"CreepTumor";NA;167;0
"Unit";"Zergling";"Larva";167;1
"Unit";"Zergling";"Larva";168;1
"Building";"CreepTumor";NA;169;0
"Building";"CreepTumor";NA;169;0
"Building";"CreepTumor";NA;169;0
"Building";"CreepTumor";NA;169;0
"Unit";"Baneling";"Zergling";169;0
"Unit";"Queen";"Hatchery";169;2
"Unit";"Zergling";"Larva";171;1
"Unit";"Zergling";"Larva";172;1
"Unit";"Zergling";"Larva";173;1
"Unit";"Zergling";"Larva";174;1
"Unit";"Zergling";"Larva";175;1
"Unit";"Zergling";"Larva";176;1
"Unit";"Overlord";"Larva";177;0
"Unit";"Zergling";"Larva";179;1
"Unit";"Zergling";"Larva";180;1
"Unit";"Zergling";"Larva";181;1
"Unit";"Zergling";"Larva";182;1
"Unit";"Zergling";"Larva";183;1
"Unit";"Zergling";"Larva";184;1
"Unit";"Zergling";"Larva";185;1
"Unit";"Zergling";"Larva";186;1
"Unit";"Zergling";"Larva";187;1
"Unit";"Zergling";"Larva";188;1
"Unit";"Zergling";"Larva";189;1
"Unit";"Zergling";"Larva";190;1
"Unit";"Zergling";"Larva";191;1
"Unit";"Zergling";"Larva";192;1
"Building";"CreepTumor";NA;196;0
"Building";"CreepTumor";NA;196;0
"Building";"CreepTumorQueen";NA;196;0
"Building";"CreepTumorQueen";NA;196;0
"Building";"CreepTumor";NA;196;0
"Unit";"Overlord";"Larva";196;0
"Building";"CreepTumor";NA;199;0
"Building";"Extractor";NA;199;0
"Building";"CreepTumor";NA;199;0
"Unit";"Baneling";"Zergling";201;0
"Unit";"Baneling";"Zergling";201;0
"Unit";"Baneling";"Zergling";201;0
"Unit";"Baneling";"Zergling";201;0
"Unit";"Zergling";"Larva";201;1
"Unit";"Zergling";"Larva";202;1
"Unit";"Zergling";"Larva";203;1
"Unit";"Zergling";"Larva";204;1
"Unit";"Zergling";"Larva";205;1
"Unit";"Zergling";"Larva";206;1
"Unit";"Zergling";"Larva";207;1
"Unit";"Zergling";"Larva";208;1
"Unit";"Zergling";"Larva";209;1
"Unit";"Zergling";"Larva";210;1
"Unit";"Zergling";"Larva";211;1
"Unit";"Zergling";"Larva";212;1
"Unit";"Zergling";"Larva";213;1
"Unit";"Zergling";"Larva";214;1
"Unit";"Zergling";"Larva";215;1
"Unit";"Zergling";"Larva";216;1
"Unit";"Zergling";"Larva";217;1
"Unit";"Zergling";"Larva";218;1
"Unit";"Zergling";"Larva";219;1
"Unit";"Zergling";"Larva";220;1
"Unit";"Overlord";"Larva";221;0
"Building";"CreepTumor";NA;221;0
"Building";"CreepTumor";NA;221;0
"Unit";"Overlord";"Larva";221;0
"Building";"CreepTumor";NA;221;0
"Building";"CreepTumor";NA;221;0
"Unit";"Mutalisk";"Larva";221;2
"Unit";"Mutalisk";"Larva";223;2
"Unit";"Mutalisk";"Larva";225;2
"Unit";"Mutalisk";"Larva";227;2
"Unit";"Mutalisk";"Larva";229;2
"Unit";"Mutalisk";"Larva";231;2
"Unit";"Mutalisk";"Larva";233;2
"Unit";"Mutalisk";"Larva";235;2
"Unit";"Mutalisk";"Larva";237;2
"Unit";"Mutalisk";"Larva";239;2
"Building";"CreepTumor";NA;241;0
"Unit";"Mutalisk";"Larva";241;2
"Building";"SporeCrawler";NA;246;0
"Unit";"Zergling";"Larva";247;1
"Unit";"Zergling";"Larva";248;1
"Unit";"Zergling";"Larva";249;1
"Unit";"Zergling";"Larva";250;1
"Unit";"Zergling";"Larva";251;1
"Unit";"Zergling";"Larva";252;1
"Unit";"Zergling";"Larva";253;1
"Unit";"Zergling";"Larva";254;1
"Unit";"Zergling";"Larva";255;1
"Unit";"Zergling";"Larva";256;1
"Unit";"Mutalisk";"Larva";257;2
"Unit";"Overlord";"Larva";259;0
"Unit";"Baneling";"Zergling";259;0
"Unit";"Baneling";"Zergling";259;0
"Unit";"Baneling";"Zergling";259;0
"Unit";"Overlord";"Larva";259;0
"Unit";"Mutalisk";"Larva";259;2
"Building";"CreepTumorQueen";NA;262;0
"Building";"CreepTumorQueen";NA;262;0
"Unit";"Zergling";"Larva";262;1
"Unit";"Zergling";"Larva";263;1
"Unit";"Zergling";"Larva";264;1
"Unit";"Zergling";"Larva";265;1
"Unit";"Zergling";"Larva";266;1
"Unit";"Zergling";"Larva";267;1
"Unit";"Zergling";"Larva";268;1
"Unit";"Zergling";"Larva";269;1
"Unit";"Zergling";"Larva";270;1
"Unit";"Zergling";"Larva";271;1
"Unit";"Zergling";"Larva";272;1
"Unit";"Zergling";"Larva";273;1
"Unit";"Zergling";"Larva";274;1
"Unit";"Zergling";"Larva";275;1
"Unit";"Overlord";"Larva";276;0
"Building";"InfestationPit";NA;276;0
"Building";"Hatchery";NA;276;0
"Building";"CreepTumorQueen";NA;276;0
"Building";"CreepTumorQueen";NA;276;0
"Unit";"Baneling";"Zergling";276;0
"Unit";"Baneling";"Zergling";276;0
"Unit";"Baneling";"Zergling";276;0
"Unit";"Baneling";"Zergling";276;0
"Unit";"Baneling";"Zergling";276;0
"Unit";"Baneling";"Zergling";276;0
"Unit";"Baneling";"Zergling";276;0
"Unit";"Baneling";"Zergling";276;0
"Unit";"Baneling";"Zergling";276;0
"Unit";"Baneling";"Zergling";276;0
"Unit";"Overlord";"Larva";276;0
"Building";"CreepTumorQueen";NA;276;0
"Unit";"Zergling";"Larva";276;1
"Unit";"Zergling";"Larva";277;1
"Unit";"Zergling";"Larva";278;1
"Unit";"Zergling";"Larva";279;1
"Building";"CreepTumorQueen";NA;280;0
"Building";"CreepTumor";NA;280;0
"Building";"CreepTumor";NA;280;0
"Building";"CreepTumor";NA;280;0
"Building";"CreepTumor";NA;280;0
"Building";"CreepTumor";NA;280;0
"Building";"CreepTumor";NA;280;0
"Unit";"Zergling";"Larva";280;1
"Unit";"Zergling";"Larva";281;1
"Unit";"Zergling";"Larva";282;1
"Unit";"Zergling";"Larva";283;1
"Unit";"Zergling";"Larva";284;1
"Unit";"Zergling";"Larva";285;1
"Unit";"Zergling";"Larva";286;1
"Unit";"Zergling";"Larva";287;1
"Unit";"Zergling";"Larva";288;1
"Unit";"Zergling";"Larva";289;1
"Unit";"Zergling";"Larva";290;1
"Unit";"Zergling";"Larva";291;1
"Unit";"Zergling";"Larva";292;1
"Unit";"Zergling";"Larva";293;1
"Unit";"Zergling";"Larva";294;1
"Unit";"Zergling";"Larva";295;1
"Unit";"Zergling";"Larva";296;1
"Unit";"Zergling";"Larva";297;1
"Unit";"Zergling";"Larva";298;1
"Unit";"Zergling";"Larva";299;1
"Building";"CreepTumorQueen";NA;300;0
"Building";"CreepTumor";NA;300;0
"Building";"CreepTumorQueen";NA;302;0
"Unit";"Zergling";"Larva";302;1
"Unit";"Zergling";"Larva";303;1
"Unit";"Zergling";"Larva";304;1
"Unit";"Zergling";"Larva";305;1
"Unit";"Zergling";"Larva";306;1
"Unit";"Zergling";"Larva";307;1
"Unit";"Zergling";"Larva";308;1
"Unit";"Zergling";"Larva";309;1
"Unit";"Zergling";"Larva";310;1
"Unit";"Zergling";"Larva";311;1
"Unit";"Zergling";"Larva";312;1
"Unit";"Zergling";"Larva";313;1
"Unit";"Zergling";"Larva";314;1
"Unit";"Zergling";"Larva";315;1
"Unit";"Zergling";"Larva";316;1
"Unit";"Zergling";"Larva";317;1
"Unit";"Zergling";"Larva";318;1
"Unit";"Zergling";"Larva";319;1
"Unit";"Zergling";"Larva";320;1
"Unit";"Zergling";"Larva";321;1
"Unit";"Zergling";"Larva";322;1
"Unit";"Zergling";"Larva";323;1
"Unit";"Zergling";"Larva";324;1
"Unit";"Zergling";"Larva";325;1
"Unit";"Zergling";"Larva";326;1
"Unit";"Zergling";"Larva";327;1
"Unit";"Zergling";"Larva";328;1
"Unit";"Zergling";"Larva";329;1
"Unit";"Zergling";"Larva";330;1
"Unit";"Zergling";"Larva";331;1
"Unit";"Zergling";"Larva";332;1
"Unit";"Zergling";"Larva";333;1
"Unit";"Zergling";"Larva";334;1
"Unit";"Zergling";"Larva";335;1
"Unit";"Baneling";"Zergling";336;0
"Unit";"Baneling";"Zergling";336;0
"Unit";"Baneling";"Zergling";336;0
"Unit";"Baneling";"Zergling";336;0
"Unit";"Baneling";"Zergling";336;0
"Unit";"Baneling";"Zergling";336;0
"Unit";"Baneling";"Zergling";336;0
"Unit";"Baneling";"Zergling";336;0
"Unit";"Baneling";"Zergling";336;0
"Unit";"Baneling";"Zergling";336;0
"Unit";"Baneling";"Zergling";336;0
"Unit";"Baneling";"Zergling";336;0
"Unit";"Baneling";"Zergling";336;0
"Unit";"Baneling";"Zergling";336;0
"Unit";"Baneling";"Zergling";336;0
"Unit";"Baneling";"Zergling";336;0
"Unit";"Baneling";"Zergling";336;0
"Building";"CreepTumor";NA;336;0
"Building";"CreepTumor";NA;336;0
"Building";"CreepTumor";NA;336;0
"Building";"CreepTumor";NA;336;0
"Building";"CreepTumor";NA;336;0
"Unit";"Baneling";"Zergling";336;0
"Building";"CreepTumor";NA;336;0
"Building";"CreepTumor";NA;336;0
"Building";"CreepTumor";NA;336;0
"Unit";"Baneling";"Zergling";336;0
"Unit";"Baneling";"Zergling";336;0
"Unit";"Baneling";"Zergling";336;0
"Unit";"Baneling";"Zergling";336;0
"Unit";"Baneling";"Zergling";336;0
"Unit";"Baneling";"Zergling";336;0
"Unit";"Baneling";"Zergling";336;0
"Unit";"Baneling";"Zergling";336;0
"Unit";"Baneling";"Zergling";336;0
"Unit";"Baneling";"Zergling";336;0
"Unit";"Baneling";"Zergling";336;0
"Unit";"Baneling";"Zergling";336;0
"Unit";"Zergling";"Larva";336;1
"Unit";"Zergling";"Larva";337;1
"Unit";"Zergling";"Larva";338;1
"Unit";"Zergling";"Larva";339;1
"Unit";"Zergling";"Larva";340;1
"Unit";"Zergling";"Larva";341;1
"Unit";"Zergling";"Larva";342;1
"Unit";"Zergling";"Larva";343;1
"Unit";"Zergling";"Larva";344;1
"Unit";"Zergling";"Larva";345;1
"Unit";"Zergling";"Larva";346;1
"Unit";"Zergling";"Larva";347;1
"Unit";"Zergling";"Larva";348;1
"Unit";"Zergling";"Larva";349;1
"Unit";"Zergling";"Larva";350;1
"Unit";"Zergling";"Larva";351;1
"Building";"Extractor";NA;352;0
"Building";"CreepTumor";NA;353;0
"Building";"CreepTumor";NA;353;0
"Building";"CreepTumor";NA;353;0
"Building";"CreepTumor";NA;353;0
"Unit";"Baneling";"Zergling";353;0
"Unit";"Baneling";"Zergling";353;0
"Unit";"Baneling";"Zergling";353;0
"Unit";"Baneling";"Zergling";353;0
"Unit";"Baneling";"Zergling";353;0
"Unit";"Baneling";"Zergling";353;0
"Unit";"Baneling";"Zergling";353;0
"Unit";"Baneling";"Zergling";353;0
"Unit";"Baneling";"Zergling";353;0
"Unit";"Baneling";"Zergling";353;0
"Unit";"Baneling";"Zergling";353;0
"Unit";"Baneling";"Zergling";353;0
"Unit";"Baneling";"Zergling";353;0
"Unit";"Baneling";"Zergling";353;0
"Unit";"Baneling";"Zergling";353;0
"Unit";"Baneling";"Zergling";353;0
"Building";"CreepTumor";NA;353;0
"Building";"CreepTumor";NA;353;0
"Building";"CreepTumor";NA;353;0
"Unit";"Baneling";"Zergling";353;0
"Unit";"Baneling";"Zergling";353;0
"Unit";"Baneling";"Zergling";353;0
"Unit";"Baneling";"Zergling";353;0
"Unit";"Baneling";"Zergling";353;0
"Unit";"Baneling";"Zergling";353;0
"Unit";"Baneling";"Zergling";353;0
"Unit";"Baneling";"Zergling";353;0
"Unit";"Baneling";"Zergling";353;0
"Unit";"Baneling";"Zergling";353;0
"Building";"CreepTumorQueen";NA;353;0
"Building";"CreepTumorQueen";NA;353;0
"Unit";"Zergling";"Larva";353;1
"Unit";"Zergling";"Larva";354;1
"Unit";"Zergling";"Larva";355;1
"Unit";"Zergling";"Larva";356;1
"Unit";"Zergling";"Larva";357;1
"Unit";"Zergling";"Larva";358;1
"Unit";"Zergling";"Larva";359;1
"Unit";"Zergling";"Larva";360;1
"Unit";"Zergling";"Larva";361;1
"Unit";"Zergling";"Larva";362;1
"Unit";"Zergling";"Larva";363;1
"Unit";"Zergling";"Larva";364;1
"Unit";"Zergling";"Larva";365;1
"Unit";"Zergling";"Larva";366;1
"Unit";"Zergling";"Larva";367;1
"Unit";"Zergling";"Larva";368;1
"Unit";"Zergling";"Larva";369;1
"Unit";"Zergling";"Larva";370;1
"Unit";"Zergling";"Larva";371;1
"Unit";"Zergling";"Larva";372;1
"Unit";"Zergling";"Larva";373;1
"Unit";"Zergling";"Larva";374;1
"Unit";"Zergling";"Larva";375;1
"Unit";"Zergling";"Larva";376;1
"Unit";"Zergling";"Larva";377;1
"Unit";"Zergling";"Larva";378;1
"Unit";"Zergling";"Larva";379;1
"Unit";"Zergling";"Larva";380;1
"Unit";"Zergling";"Larva";381;1
"Unit";"Zergling";"Larva";382;1
"Unit";"Zergling";"Larva";383;1
"Unit";"Zergling";"Larva";384;1
"Unit";"Zergling";"Larva";385;1
"Unit";"Zergling";"Larva";386;1
"Unit";"Zergling";"Larva";387;1
"Unit";"Zergling";"Larva";388;1
"Unit";"Zergling";"Larva";389;1
"Unit";"Zergling";"Larva";390;1
"Unit";"Zergling";"Larva";391;1
"Unit";"Zergling";"Larva";392;1
"Unit";"Zergling";"Larva";393;1
"Unit";"Zergling";"Larva";394;1
"Unit";"Zergling";"Larva";395;1
"Unit";"Zergling";"Larva";396;1
"Unit";"Zergling";"Larva";397;1
"Unit";"Zergling";"Larva";398;1
"Unit";"Zergling";"Larva";399;1
"Unit";"Zergling";"Larva";400;1
"Unit";"Zergling";"Larva";401;1
"Unit";"Zergling";"Larva";402;1
"Unit";"Zergling";"Larva";403;1
"Unit";"Zergling";"Larva";404;1
"Unit";"Zergling";"Larva";405;1
"Unit";"Zergling";"Larva";406;1
"Unit";"Zergling";"Larva";407;1
"Unit";"Zergling";"Larva";408;1
"Unit";"Zergling";"Larva";409;1
"Unit";"Zergling";"Larva";410;1
"Unit";"Zergling";"Larva";411;1
"Unit";"Zergling";"Larva";412;1
"Unit";"Zergling";"Larva";413;1
"Unit";"Zergling";"Larva";414;1
"Unit";"Zergling";"Larva";415;1
"Unit";"Zergling";"Larva";416;1
"Unit";"Zergling";"Larva";417;1
"Unit";"Zergling";"Larva";418;1
"Unit";"Baneling";"Zergling";419;0
"Unit";"Baneling";"Zergling";419;0
"Unit";"Baneling";"Zergling";419;0
"Unit";"Baneling";"Zergling";419;0
"Unit";"Baneling";"Zergling";419;0
"Unit";"Baneling";"Zergling";419;0
"Unit";"Baneling";"Zergling";419;0
"Unit";"Zergling";"Larva";419;1
"Unit";"Zergling";"Larva";420;1
"Unit";"Zergling";"Larva";421;1
"Unit";"Zergling";"Larva";422;1
"Unit";"Zergling";"Larva";423;1
"Unit";"Zergling";"Larva";424;1
"Unit";"Zergling";"Larva";425;1
"Unit";"Zergling";"Larva";426;1
"Unit";"Zergling";"Larva";427;1
"Unit";"Zergling";"Larva";428;1
"Unit";"Zergling";"Larva";429;1
"Unit";"Zergling";"Larva";430;1
"Unit";"Zergling";"Larva";431;1
"Unit";"Zergling";"Larva";432;1
"Unit";"Zergling";"Larva";433;1
"Unit";"Zergling";"Larva";434;1
"Unit";"Zergling";"Larva";435;1
"Unit";"Zergling";"Larva";436;1
"Unit";"Zergling";"Larva";437;1
"Unit";"Zergling";"Larva";438;1
"Unit";"Zergling";"Larva";439;1
"Unit";"Zergling";"Larva";440;1
"Unit";"Zergling";"Larva";441;1
"Unit";"Zergling";"Larva";442;1
"Unit";"Zergling";"Larva";443;1
"Unit";"Zergling";"Larva";444;1
"Unit";"Zergling";"Larva";445;1
"Unit";"Zergling";"Larva";446;1
"Building";"Hatchery";NA;447;0
"Unit";"Corruptor";"Larva";447;2
"Unit";"Corruptor";"Larva";449;2
"Unit";"Corruptor";"Larva";451;2
"Unit";"Corruptor";"Larva";453;2
"Unit";"Corruptor";"Larva";455;2
"Unit";"Corruptor";"Larva";457;2
"Unit";"Corruptor";"Larva";459;2
"Building";"CreepTumor";NA;461;0
"Building";"CreepTumor";NA;461;0
"Building";"CreepTumor";NA;461;0
"Building";"CreepTumor";NA;461;0
"Unit";"Corruptor";"Larva";461;2
"Building";"Extractor";NA;467;0
"Building";"CreepTumor";NA;467;0
"Building";"CreepTumor";NA;467;0
"Building";"CreepTumor";NA;467;0
"Building";"CreepTumorQueen";NA;467;0
"Building";"CreepTumorQueen";NA;467;0
"Building";"CreepTumorQueen";NA;467;0
"Building";"CreepTumorQueen";NA;467;0
"Building";"CreepTumorQueen";NA;467;0
"Building";"CreepTumorQueen";NA;467;0
"Building";"CreepTumorQueen";NA;467;0
"Building";"Extractor";NA;471;0
"Building";"CreepTumor";NA;471;0
"Building";"CreepTumor";NA;471;0
"Building";"CreepTumor";NA;471;0
"Building";"CreepTumorQueen";NA;471;0
"Building";"CreepTumorQueen";NA;471;0
"Building";"CreepTumorQueen";NA;471;0
"Building";"CreepTumorQueen";NA;471;0
"Building";"CreepTumorQueen";NA;471;0
"Building";"SporeCrawler";NA;471;0
"Building";"CreepTumorQueen";NA;471;0
"Building";"Hatchery";NA;471;0
"Building";"CreepTumorQueen";NA;471;0
"Building";"SporeCrawler";NA;471;0
"Building";"CreepTumorQueen";NA;471;0
"Building";"CreepTumorQueen";NA;471;0
"Building";"CreepTumorQueen";NA;471;0
"Building";"CreepTumorQueen";NA;471;0
"Building";"CreepTumorQueen";NA;471;0
"Building";"CreepTumorQueen";NA;471;0
"Building";"CreepTumorQueen";NA;471;0
"Unit";"Baneling";"Zergling";471;0
"Unit";"Baneling";"Zergling";471;0
"Unit";"Baneling";"Zergling";471;0
"Unit";"Baneling";"Zergling";471;0
"Unit";"Zergling";"Larva";471;1
"Unit";"Zergling";"Larva";472;1
"Unit";"Zergling";"Larva";473;1
"Unit";"Zergling";"Larva";474;1
"Unit";"Zergling";"Larva";475;1
"Unit";"Zergling";"Larva";476;1
"Unit";"Zergling";"Larva";477;1
"Unit";"Zergling";"Larva";478;1
"Unit";"Zergling";"Larva";479;1
"Unit";"Zergling";"Larva";480;1
"Unit";"Zergling";"Larva";481;1
"Unit";"Zergling";"Larva";482;1
"Unit";"Zergling";"Larva";483;1
"Unit";"Zergling";"Larva";484;1
"Unit";"Zergling";"Larva";485;1
"Unit";"Zergling";"Larva";486;1
"Unit";"Zergling";"Larva";487;1
"Unit";"Zergling";"Larva";488;1
"Unit";"Baneling";"Zergling";489;0
"Unit";"Baneling";"Zergling";489;0
"Unit";"Baneling";"Zergling";489;0
"Building";"CreepTumorQueen";NA;489;0
"Unit";"Baneling";"Zergling";489;0
"Unit";"Baneling";"Zergling";489;0
"Unit";"Baneling";"Zergling";489;0
"Unit";"Baneling";"Zergling";489;0
"Unit";"Baneling";"Zergling";489;0
"Unit";"Baneling";"Zergling";489;0
"Unit";"Baneling";"Zergling";489;0
"Building";"CreepTumor";NA;489;0
"Building";"CreepTumorQueen";NA;489;0
"Building";"CreepTumor";NA;489;0
"Building";"CreepTumor";NA;489;0
"Building";"CreepTumor";NA;489;0
"Unit";"Baneling";"Zergling";489;0
"Unit";"Baneling";"Zergling";489;0
"Unit";"Baneling";"Zergling";489;0
"Unit";"Baneling";"Zergling";489;0
"Unit";"Baneling";"Zergling";489;0
"Unit";"Baneling";"Zergling";489;0
"Unit";"Baneling";"Zergling";489;0
"Building";"CreepTumorQueen";NA;489;0
"Unit";"Baneling";"Zergling";489;0
"Unit";"Baneling";"Zergling";489;0
"Unit";"Baneling";"Zergling";489;0
"Unit";"Baneling";"Zergling";489;0
"Unit";"Baneling";"Zergling";489;0
"Unit";"Baneling";"Zergling";489;0
"Unit";"Baneling";"Zergling";489;0
"Building";"CreepTumorQueen";NA;489;0
"Unit";"Baneling";"Zergling";489;0
"Unit";"Baneling";"Zergling";489;0
"Unit";"Baneling";"Zergling";489;0
"Unit";"Baneling";"Zergling";489;0
"Unit";"Baneling";"Zergling";489;0
"Unit";"Baneling";"Zergling";489;0
"Unit";"Baneling";"Zergling";489;0
"Unit";"Baneling";"Zergling";489;0
"Unit";"Baneling";"Zergling";489;0
"Unit";"Zergling";"Larva";489;1
"Unit";"Zergling";"Larva";490;1
"Unit";"Zergling";"Larva";491;1
"Unit";"Zergling";"Larva";492;1
"Unit";"Zergling";"Larva";493;1
"Unit";"Zergling";"Larva";494;1
"Unit";"Zergling";"Larva";495;1
"Unit";"Zergling";"Larva";496;1
"Unit";"Zergling";"Larva";497;1
"Unit";"Zergling";"Larva";498;1
"Unit";"Zergling";"Larva";499;1
"Unit";"Zergling";"Larva";500;1
"Unit";"Zergling";"Larva";501;1
"Unit";"Zergling";"Larva";502;1
"Unit";"Zergling";"Larva";503;1
"Unit";"Zergling";"Larva";504;1
"Unit";"Zergling";"Larva";505;1
"Unit";"Zergling";"Larva";506;1
"Unit";"Zergling";"Larva";507;1
"Unit";"Zergling";"Larva";508;1
"Unit";"Zergling";"Larva";509;1
"Unit";"Zergling";"Larva";510;1
"Unit";"Zergling";"Larva";511;1
"Unit";"Zergling";"Larva";512;1
"Unit";"Zergling";"Larva";513;1
"Unit";"Zergling";"Larva";514;1
"Unit";"Zergling";"Larva";515;1
"Unit";"Zergling";"Larva";516;1
"Unit";"Zergling";"Larva";517;1
"Unit";"Zergling";"Larva";518;1
"Unit";"Zergling";"Larva";519;1
"Unit";"Zergling";"Larva";520;1
"Unit";"Zergling";"Larva";521;1
"Unit";"Zergling";"Larva";522;1
"Unit";"Zergling";"Larva";523;1
"Unit";"Zergling";"Larva";524;1
"Unit";"Zergling";"Larva";525;1
"Unit";"Zergling";"Larva";526;1
"Unit";"Zergling";"Larva";527;1
"Unit";"Zergling";"Larva";528;1
"Unit";"Zergling";"Larva";529;1
"Unit";"Zergling";"Larva";530;1
"Unit";"Zergling";"Larva";531;1
"Unit";"Zergling";"Larva";532;1
"Unit";"Zergling";"Larva";533;1
"Unit";"Zergling";"Larva";534;1
"Unit";"Zergling";"Larva";535;1
"Unit";"Zergling";"Larva";536;1
"Unit";"Zergling";"Larva";537;1
"Unit";"Zergling";"Larva";538;1
"Unit";"Zergling";"Larva";539;1
"Unit";"Zergling";"Larva";540;1
"Unit";"Zergling";"Larva";541;1
"Unit";"Zergling";"Larva";542;1
"Unit";"Zergling";"Larva";543;1
"Unit";"Zergling";"Larva";544;1
"Unit";"Zergling";"Larva";545;1
"Unit";"Zergling";"Larva";546;1
"Unit";"Zergling";"Larva";547;1
"Unit";"Zergling";"Larva";548;1
"Unit";"Zergling";"Larva";549;1
"Unit";"Zergling";"Larva";550;1
"Unit";"Zergling";"Larva";551;1
"Unit";"Zergling";"Larva";552;1
"Unit";"Zergling";"Larva";553;1
"Unit";"Zergling";"Larva";554;1
"Unit";"Zergling";"Larva";555;1
"Unit";"Zergling";"Larva";556;1
"Unit";"Zergling";"Larva";557;1
"Unit";"Zergling";"Larva";558;1
"Unit";"Zergling";"Larva";559;1
"Unit";"Zergling";"Larva";560;1
"Unit";"Zergling";"Larva";561;1
"Unit";"Zergling";"Larva";562;1
"Unit";"Zergling";"Larva";563;1
"Unit";"Zergling";"Larva";564;1
"Unit";"Zergling";"Larva";565;1
"Unit";"Zergling";"Larva";566;1
"Unit";"Zergling";"Larva";567;1
"Unit";"Zergling";"Larva";568;1
"Unit";"Zergling";"Larva";569;1
"Unit";"Zergling";"Larva";570;1
"Unit";"Zergling";"Larva";571;1
"Unit";"Zergling";"Larva";572;1
"Unit";"Zergling";"Larva";573;1
"Unit";"Zergling";"Larva";574;1
"Unit";"Zergling";"Larva";575;1
"Unit";"Zergling";"Larva";576;1
"Unit";"Zergling";"Larva";577;1
"Unit";"Zergling";"Larva";578;1
"Unit";"Zergling";"Larva";579;1
"Unit";"Zergling";"Larva";580;1
"Unit";"Zergling";"Larva";581;1
"Unit";"Zergling";"Larva";582;1
"Unit";"Zergling";"Larva";583;1
"Unit";"Zergling";"Larva";584;1
"Unit";"Zergling";"Larva";585;1
"Unit";"Zergling";"Larva";586;1
"Unit";"Zergling";"Larva";587;1
"Unit";"Zergling";"Larva";588;1
"Unit";"Zergling";"Larva";589;1
"Unit";"Zergling";"Larva";590;1
"Unit";"Baneling";"Zergling";591;0
"Unit";"Baneling";"Zergling";591;0
"Unit";"Baneling";"Zergling";591;0
"Unit";"Baneling";"Zergling";591;0
"Unit";"Baneling";"Zergling";591;0
"Unit";"Baneling";"Zergling";591;0
"Unit";"Baneling";"Zergling";591;0
"Unit";"Baneling";"Zergling";591;0
"Unit";"Baneling";"Zergling";591;0
"Unit";"Baneling";"Zergling";591;0
"Unit";"Baneling";"Zergling";591;0
"Unit";"Baneling";"Zergling";591;0
"Unit";"Baneling";"Zergling";591;0
"Unit";"Baneling";"Zergling";591;0
"Unit";"Baneling";"Zergling";591;0
"Unit";"Baneling";"Zergling";591;0
"Unit";"Baneling";"Zergling";591;0
"Unit";"Baneling";"Zergling";591;0
"Unit";"Baneling";"Zergling";591;0
"Unit";"Baneling";"Zergling";591;0
"Unit";"Baneling";"Zergling";591;0
"Unit";"Baneling";"Zergling";591;0
"Unit";"Baneling";"Zergling";591;0
"Unit";"Baneling";"Zergling";591;0
"Unit";"Baneling";"Zergling";591;0
"Unit";"Zergling";"Larva";591;1
"Unit";"Zergling";"Larva";592;1
"Unit";"Zergling";"Larva";593;1
"Unit";"Zergling";"Larva";594;1
"Unit";"Zergling";"Larva";595;1
"Unit";"Zergling";"Larva";596;1
"Unit";"Zergling";"Larva";597;1
"Unit";"Zergling";"Larva";598;1
"Unit";"Zergling";"Larva";599;1
"Unit";"Zergling";"Larva";600;1
"Unit";"Baneling";"Zergling";601;0
"Unit";"Baneling";"Zergling";601;0
"Unit";"Baneling";"Zergling";601;0
"Unit";"Baneling";"Zergling";601;0
"Unit";"Baneling";"Zergling";601;0
"Unit";"Baneling";"Zergling";601;0
"Unit";"Baneling";"Zergling";601;0
"Unit";"Baneling";"Zergling";601;0
"Unit";"Baneling";"Zergling";601;0
"Unit";"Baneling";"Zergling";601;0
"Unit";"Zergling";"Larva";601;1
"Unit";"Zergling";"Larva";602;1
"Unit";"Zergling";"Larva";603;1
"Unit";"Zergling";"Larva";604;1
"Unit";"Zergling";"Larva";605;1
"Unit";"Zergling";"Larva";606;1
"Unit";"Zergling";"Larva";607;1
"Unit";"Zergling";"Larva";608;1
"Unit";"Overlord";"Larva";609;0
"Unit";"Overlord";"Larva";609;0
"Unit";"Baneling";"Zergling";609;0
"Unit";"Baneling";"Zergling";609;0
"Unit";"Baneling";"Zergling";609;0
"Unit";"Baneling";"Zergling";609;0
"Unit";"Zergling";"Larva";609;1
"Unit";"Zergling";"Larva";610;1
"Unit";"Zergling";"Larva";611;1
"Unit";"Zergling";"Larva";612;1
"Unit";"Zergling";"Larva";613;1
"Unit";"Zergling";"Larva";614;1
"Unit";"Zergling";"Larva";615;1
"Unit";"Zergling";"Larva";616;1
"Unit";"Zergling";"Larva";617;1
"Unit";"Zergling";"Larva";618;1
"Upgrade";"SprayZerg";NA;619;0
"Upgrade";"SprayZerg";NA;619;0
"Upgrade";"SprayZerg";NA;619;0
"Upgrade";"SprayZerg";NA;619;0
"Upgrade";"zerglingmovementspeed";NA;619;0
"Upgrade";"SprayZerg";NA;619;0
"Upgrade";"SprayZerg";NA;619;0
"Upgrade";"ZergGroundArmorsLevel1";NA;619;0
"Upgrade";"ZergMeleeWeaponsLevel1";NA;619;0
"Upgrade";"overlordspeed";NA;619;0
"Upgrade";"CentrificalHooks";NA;619;0
"Upgrade";"SprayZerg";NA;619;0
"Upgrade";"ZergGroundArmorsLevel2";NA;619;0
"Upgrade";"ZergMeleeWeaponsLevel2";NA;619;0
"Upgrade";"SprayZerg";NA;619;0
"Upgrade";"ZergFlyerWeaponsLevel1";NA;619;0
"Upgrade";"SprayZerg";NA;619;0
"Upgrade";"zerglingattackspeed";NA;619;0
"Upgrade";"SprayZerg";NA;619;0
"Upgrade";"SprayZerg";NA;619;0
"Upgrade";"ZergGroundArmorsLevel3";NA;619;0
"Upgrade";"ZergMeleeWeaponsLevel3";NA;619;0
"Upgrade";"SprayZerg";NA;619;0
"Upgrade";"ZergFlyerWeaponsLevel2";NA;619;0
