"type";"unit_name";"on_building";"total_supply";"supply"
"Unit";"Overlord";"Larva";12;0
"Building";"Extractor";NA;21;0
"Building";"SpawningPool";NA;19;0
"Building";"Hatchery";NA;17;0
"Unit";"Zergling";"Larva";24;1
"Unit";"Zergling";"Larva";24;1
"Unit";"Zergling";"Larva";24;1
"Unit";"Zergling";"Larva";24;1
"Unit";"Overlord";"Larva";24;0
"Unit";"Queen";"Hatchery";24;2
"Unit";"Overlord";"Larva";28;0
"Unit";"Queen";"Hatchery";24;2
"Building";"Hatchery";NA;22;0
"Building";"CreepTumorQueen";NA;41;0
"Building";"CreepTumor";NA;48;0
"Unit";"Overlord";"Larva";48;0
"Unit";"Queen";"Hatchery";47;2
"Building";"CreepTumorQueen";NA;53;0
"Building";"CreepTumor";NA;55;0
"Unit";"Queen";"Hatchery";49;2
"Building";"SporeCrawler";NA;53;0
"Unit";"Overlord";"Larva";59;0
"Unit";"Overlord";"Larva";59;0
"Building";"SporeCrawler";NA;55;0
"Building";"BanelingNest";NA;49;0
"Unit";"Overlord";"Larva";63;0
"Unit";"Overlord";"Larva";63;0
"Unit";"Zergling";"Larva";63;1
"Unit";"Zergling";"Larva";63;1
"Unit";"Zergling";"Larva";63;1
"Unit";"Zergling";"Larva";63;1
"Unit";"Zergling";"Larva";63;1
"Unit";"Zergling";"Larva";63;1
"Unit";"Zergling";"Larva";63;1
"Unit";"Zergling";"Larva";63;1
"Unit";"Zergling";"Larva";63;1
"Unit";"Zergling";"Larva";63;1
"Unit";"Zergling";"Larva";63;1
"Unit";"Zergling";"Larva";63;1
"Unit";"Baneling";"Zergling";63;0
"Unit";"Baneling";"Zergling";63;0
"Unit";"Baneling";"Zergling";63;0
"Unit";"Baneling";"Zergling";63;0
"Building";"CreepTumor";NA;63;0
"Building";"CreepTumor";NA;63;0
"Unit";"Overlord";"Larva";63;0
"Building";"SporeCrawler";NA;63;0
"Unit";"Queen";"Hatchery";63;2
"Unit";"Queen";"Hatchery";63;2
"Building";"SporeCrawler";NA;75;0
"Building";"CreepTumorQueen";NA;88;0
"Building";"CreepTumorQueen";NA;88;0
"Unit";"Overlord";"Larva";85;0
"Building";"CreepTumorQueen";NA;88;0
"Building";"CreepTumor";NA;88;0
"Building";"CreepTumorQueen";NA;89;0
"Building";"CreepTumorQueen";NA;89;0
"Building";"CreepTumorQueen";NA;91;0
"Unit";"Queen";"Hatchery";81;2
"Unit";"Overlord";"Larva";91;0
"Building";"CreepTumorQueen";NA;91;0
"Building";"CreepTumorQueen";NA;91;0
"Unit";"Queen";"Hatchery";91;2
"Building";"CreepTumorQueen";NA;99;0
"Building";"CreepTumorQueen";NA;99;0
"Building";"CreepTumorQueen";NA;99;0
"Building";"CreepTumorQueen";NA;101;0
"Building";"CreepTumorQueen";NA;106;0
"Building";"Extractor";NA;99;0
"Building";"Extractor";NA;99;0
"Unit";"Queen";"Hatchery";99;2
"Building";"CreepTumor";NA;111;0
"Building";"CreepTumor";NA;111;0
"Building";"CreepTumor";NA;111;0
"Building";"CreepTumor";NA;111;0
"Building";"Extractor";NA;111;0
"Building";"CreepTumor";NA;111;0
"Building";"Extractor";NA;111;0
"Building";"Extractor";NA;111;0
"Building";"HydraliskDen";NA;111;0
"Building";"CreepTumorQueen";NA;117;0
"Building";"CreepTumorQueen";NA;117;0
"Unit";"Overlord";"Larva";117;0
"Unit";"Overlord";"Larva";117;0
"Unit";"Zergling";"Larva";117;1
"Unit";"Zergling";"Larva";117;1
"Unit";"Zergling";"Larva";117;1
"Unit";"Zergling";"Larva";117;1
"Unit";"Zergling";"Larva";117;1
"Unit";"Zergling";"Larva";117;1
"Unit";"Zergling";"Larva";117;1
"Unit";"Zergling";"Larva";117;1
"Unit";"Zergling";"Larva";117;1
"Unit";"Zergling";"Larva";117;1
"Unit";"Zergling";"Larva";117;1
"Unit";"Zergling";"Larva";117;1
"Unit";"Zergling";"Larva";117;1
"Unit";"Zergling";"Larva";117;1
"Unit";"Zergling";"Larva";117;1
"Unit";"Zergling";"Larva";117;1
"Building";"Hatchery";NA;99;0
"Building";"CreepTumorQueen";NA;133;0
"Building";"CreepTumorQueen";NA;133;0
"Unit";"Zergling";"Larva";133;1
"Unit";"Zergling";"Larva";133;1
"Unit";"Zergling";"Larva";133;1
"Unit";"Zergling";"Larva";133;1
"Unit";"Zergling";"Larva";133;1
"Unit";"Zergling";"Larva";133;1
"Unit";"Zergling";"Larva";133;1
"Unit";"Zergling";"Larva";133;1
"Building";"CreepTumorQueen";NA;138;0
"Building";"CreepTumorQueen";NA;138;0
"Building";"CreepTumorQueen";NA;139;0
"Building";"CreepTumorQueen";NA;139;0
"Building";"CreepTumor";NA;139;0
"Building";"CreepTumor";NA;151;0
"Building";"CreepTumor";NA;151;0
"Building";"CreepTumor";NA;151;0
"Building";"Hatchery";NA;115;0
"Building";"CreepTumorQueen";NA;155;0
"Building";"CreepTumorQueen";NA;155;0
"Unit";"Zergling";"Larva";151;1
"Unit";"Zergling";"Larva";151;1
"Unit";"Zergling";"Larva";151;1
"Unit";"Zergling";"Larva";151;1
"Building";"EvolutionChamber";NA;139;0
"Building";"EvolutionChamber";NA;139;0
"Unit";"Zergling";"Larva";155;1
"Unit";"Zergling";"Larva";155;1
"Unit";"Zergling";"Larva";155;1
"Unit";"Zergling";"Larva";155;1
"Unit";"Zergling";"Larva";155;1
"Unit";"Zergling";"Larva";155;1
"Unit";"Zergling";"Larva";155;1
"Unit";"Zergling";"Larva";155;1
"Unit";"Zergling";"Larva";155;1
"Unit";"Zergling";"Larva";155;1
"Building";"SporeCrawler";NA;151;0
"Unit";"Queen";"Hatchery";139;2
"Unit";"Overlord";"Larva";155;0
"Building";"CreepTumor";NA;155;0
"Building";"CreepTumor";NA;155;0
"Building";"CreepTumor";NA;155;0
"Unit";"Overlord";"Larva";155;0
"Unit";"Overlord";"Larva";155;0
"Unit";"Overlord";"Larva";155;0
"Upgrade";"EvolveGroovedSpines";"HydraliskDen";133;0
"Unit";"Overlord";"Larva";155;0
"Unit";"Overlord";"Larva";155;0
"Unit";"Overlord";"Larva";155;0
"Building";"InfestationPit";NA;151;0
"Unit";"Hydralisk";"Larva";155;2
"Unit";"Hydralisk";"Larva";155;2
"Unit";"Hydralisk";"Larva";155;2
"Building";"CreepTumor";NA;171;0
"Building";"CreepTumor";NA;171;0
"Building";"CreepTumor";NA;171;0
"Building";"CreepTumor";NA;171;0
"Building";"CreepTumor";NA;171;0
"Building";"CreepTumor";NA;171;0
"Building";"CreepTumor";NA;171;0
"Building";"CreepTumorQueen";NA;173;0
"Building";"EvolutionChamber";NA;171;0
"Unit";"Hydralisk";"Larva";171;2
"Building";"CreepTumorQueen";NA;177;0
"Unit";"Hydralisk";"Larva";171;2
"Unit";"Hydralisk";"Larva";171;2
"Unit";"Hydralisk";"Larva";171;2
"Unit";"Hydralisk";"Larva";171;2
"Building";"CreepTumorQueen";NA;177;0
"Building";"CreepTumorQueen";NA;177;0
"Unit";"Hydralisk";"Larva";173;2
"Unit";"Hydralisk";"Larva";173;2
"Unit";"Hydralisk";"Larva";173;2
"Unit";"Hydralisk";"Larva";173;2
"Unit";"Hydralisk";"Larva";173;2
"Unit";"Baneling";"Zergling";187;0
"Unit";"Baneling";"Zergling";187;0
"Unit";"Baneling";"Zergling";187;0
"Unit";"Baneling";"Zergling";187;0
"Unit";"Zergling";"Larva";197;1
"Unit";"Zergling";"Larva";197;1
"Unit";"Zergling";"Larva";197;1
"Unit";"Zergling";"Larva";197;1
"Unit";"Zergling";"Larva";197;1
"Unit";"Zergling";"Larva";197;1
"Unit";"Zergling";"Larva";197;1
"Unit";"Zergling";"Larva";197;1
"Unit";"Zergling";"Larva";197;1
"Unit";"Zergling";"Larva";197;1
"Unit";"Zergling";"Larva";197;1
"Unit";"Zergling";"Larva";197;1
"Unit";"Zergling";"Larva";197;1
"Unit";"Zergling";"Larva";197;1
"Unit";"Zergling";"Larva";197;1
"Unit";"Zergling";"Larva";197;1
"Unit";"Zergling";"Larva";197;1
"Unit";"Zergling";"Larva";197;1
"Unit";"Zergling";"Larva";197;1
"Unit";"Zergling";"Larva";197;1
"Unit";"Zergling";"Larva";197;1
"Unit";"Zergling";"Larva";197;1
"Unit";"Zergling";"Larva";197;1
"Unit";"Zergling";"Larva";197;1
"Unit";"Zergling";"Larva";197;1
"Unit";"Zergling";"Larva";197;1
"Unit";"Zergling";"Larva";197;1
"Unit";"Zergling";"Larva";197;1
"Unit";"Zergling";"Larva";197;1
"Unit";"Zergling";"Larva";197;1
"Unit";"Zergling";"Larva";197;1
"Unit";"Zergling";"Larva";197;1
"Unit";"Zergling";"Larva";197;1
"Unit";"Zergling";"Larva";197;1
"Unit";"Zergling";"Larva";197;1
"Unit";"Zergling";"Larva";197;1
"Unit";"Zergling";"Larva";197;1
"Unit";"Zergling";"Larva";197;1
"Unit";"Zergling";"Larva";197;1
"Unit";"Zergling";"Larva";197;1
"Unit";"Zergling";"Larva";197;1
"Unit";"Zergling";"Larva";197;1
"Building";"CreepTumorQueen";NA;197;0
"Building";"CreepTumor";NA;197;0
"Building";"CreepTumor";NA;197;0
"Building";"CreepTumor";NA;197;0
"Building";"CreepTumor";NA;197;0
"Building";"CreepTumor";NA;197;0
"Building";"CreepTumor";NA;197;0
"Building";"CreepTumor";NA;197;0
"Building";"CreepTumor";NA;197;0
"Building";"CreepTumor";NA;197;0
"Building";"CreepTumor";NA;197;0
"Building";"CreepTumor";NA;197;0
"Building";"CreepTumor";NA;197;0
"Unit";"Baneling";"Zergling";239;0
"Unit";"Baneling";"Zergling";239;0
"Unit";"Baneling";"Zergling";239;0
"Unit";"Baneling";"Zergling";239;0
"Unit";"Baneling";"Zergling";239;0
"Unit";"Baneling";"Zergling";239;0
"Unit";"Baneling";"Zergling";239;0
"Unit";"Baneling";"Zergling";239;0
"Unit";"Baneling";"Zergling";239;0
"Unit";"Baneling";"Zergling";239;0
"Unit";"Baneling";"Zergling";239;0
"Unit";"Baneling";"Zergling";239;0
"Unit";"Baneling";"Zergling";239;0
"Unit";"Baneling";"Zergling";239;0
"Unit";"Zergling";"Larva";239;1
"Unit";"Zergling";"Larva";239;1
"Unit";"Zergling";"Larva";239;1
"Unit";"Zergling";"Larva";239;1
"Unit";"Zergling";"Larva";239;1
"Unit";"Zergling";"Larva";239;1
"Unit";"Zergling";"Larva";239;1
"Unit";"Zergling";"Larva";239;1
"Unit";"Zergling";"Larva";239;1
"Unit";"Zergling";"Larva";239;1
"Unit";"Zergling";"Larva";239;1
"Unit";"Zergling";"Larva";239;1
"Unit";"Zergling";"Larva";239;1
"Unit";"Zergling";"Larva";239;1
"Unit";"Zergling";"Larva";239;1
"Unit";"Zergling";"Larva";239;1
"Unit";"Zergling";"Larva";239;1
"Unit";"Zergling";"Larva";239;1
"Unit";"Zergling";"Larva";239;1
"Unit";"Zergling";"Larva";239;1
"Unit";"Zergling";"Larva";239;1
"Unit";"Zergling";"Larva";239;1
"Unit";"Zergling";"Larva";239;1
"Unit";"Zergling";"Larva";239;1
"Building";"CreepTumor";NA;239;0
"Building";"Spire";NA;177;0
"Building";"CreepTumor";NA;263;0
"Unit";"Queen";"Hatchery";239;2
"Building";"CreepTumor";NA;263;0
"Building";"CreepTumor";NA;263;0
"Building";"CreepTumor";NA;263;0
"Building";"CreepTumor";NA;263;0
"Building";"CreepTumor";NA;263;0
"Building";"CreepTumor";NA;263;0
"Building";"CreepTumor";NA;263;0
"Building";"CreepTumor";NA;263;0
"Building";"CreepTumor";NA;268;0
"Building";"CreepTumor";NA;268;0
"Building";"CreepTumor";NA;268;0
"Upgrade";"ZergGroundArmorsLevel1";"EvolutionChamber";187;0
"Building";"CreepTumor";NA;268;0
"Building";"CreepTumor";NA;268;0
"Upgrade";"ZergMeleeWeaponsLevel1";"EvolutionChamber";187;0
"Unit";"Zergling";"Larva";272;1
"Unit";"Zergling";"Larva";272;1
"Unit";"Zergling";"Larva";272;1
"Unit";"Zergling";"Larva";272;1
"Unit";"Zergling";"Larva";272;1
"Unit";"Zergling";"Larva";272;1
"Unit";"Zergling";"Larva";272;1
"Unit";"Zergling";"Larva";272;1
"Unit";"Zergling";"Larva";272;1
"Unit";"Zergling";"Larva";272;1
"Unit";"Zergling";"Larva";272;1
"Unit";"Zergling";"Larva";272;1
"Unit";"Zergling";"Larva";272;1
"Unit";"Zergling";"Larva";272;1
"Unit";"Zergling";"Larva";272;1
"Unit";"Zergling";"Larva";272;1
"Unit";"Zergling";"Larva";272;1
"Unit";"Zergling";"Larva";272;1
"Unit";"Zergling";"Larva";272;1
"Unit";"Zergling";"Larva";272;1
"Unit";"Zergling";"Larva";272;1
"Unit";"Zergling";"Larva";272;1
"Unit";"Baneling";"Zergling";272;0
"Unit";"Baneling";"Zergling";272;0
"Unit";"Baneling";"Zergling";272;0
"Unit";"Baneling";"Zergling";272;0
"Unit";"Baneling";"Zergling";272;0
"Unit";"Baneling";"Zergling";272;0
"Unit";"Baneling";"Zergling";272;0
"Unit";"Baneling";"Zergling";272;0
"Unit";"Baneling";"Zergling";272;0
"Unit";"Baneling";"Zergling";272;0
"Building";"CreepTumorQueen";NA;272;0
"Building";"Extractor";NA;294;0
"Unit";"Overlord";"Larva";294;0
"Building";"Extractor";NA;294;0
"Unit";"Overlord";"Larva";294;0
"Unit";"Overlord";"Larva";294;0
"Unit";"Overlord";"Larva";294;0
"Unit";"Overlord";"Larva";294;0
"Unit";"Overlord";"Larva";294;0
"Unit";"Overlord";"Larva";294;0
"Unit";"Overlord";"Larva";294;0
"Unit";"Overlord";"Larva";294;0
"Unit";"Overlord";"Larva";294;0
"Building";"CreepTumor";NA;294;0
"Building";"CreepTumor";NA;294;0
"Building";"CreepTumor";NA;294;0
"Building";"CreepTumor";NA;294;0
"Building";"CreepTumor";NA;294;0
"Building";"CreepTumor";NA;294;0
"Building";"CreepTumor";NA;294;0
"Building";"UltraliskCavern";NA;294;0
"Building";"CreepTumorQueen";NA;300;0
"Unit";"Corruptor";"Larva";294;2
"Unit";"Corruptor";"Larva";294;2
"Unit";"Corruptor";"Larva";294;2
"Unit";"Corruptor";"Larva";294;2
"Unit";"Corruptor";"Larva";294;2
"Building";"CreepTumorQueen";NA;300;0
"Building";"CreepTumorQueen";NA;300;0
"Upgrade";"ZergMissileWeaponsLevel1";"EvolutionChamber";272;0
"Unit";"Corruptor";"Larva";294;2
"Unit";"Corruptor";"Larva";300;2
"Unit";"Corruptor";"Larva";300;2
"Unit";"Corruptor";"Larva";300;2
"Unit";"Zergling";"Larva";310;1
"Unit";"Zergling";"Larva";310;1
"Unit";"Zergling";"Larva";310;1
"Unit";"Zergling";"Larva";310;1
"Unit";"Zergling";"Larva";310;1
"Unit";"Zergling";"Larva";310;1
"Unit";"Zergling";"Larva";310;1
"Unit";"Zergling";"Larva";310;1
"Unit";"Zergling";"Larva";310;1
"Unit";"Zergling";"Larva";310;1
"Unit";"Zergling";"Larva";310;1
"Unit";"Zergling";"Larva";310;1
"Unit";"Zergling";"Larva";310;1
"Unit";"Zergling";"Larva";310;1
"Unit";"Zergling";"Larva";310;1
"Unit";"Zergling";"Larva";310;1
"Unit";"Zergling";"Larva";310;1
"Unit";"Zergling";"Larva";310;1
"Unit";"Zergling";"Larva";312;1
"Unit";"Zergling";"Larva";312;1
"Unit";"Zergling";"Larva";312;1
"Unit";"Zergling";"Larva";312;1
"Building";"CreepTumor";NA;312;0
"Building";"CreepTumor";NA;312;0
"Building";"CreepTumor";NA;318;0
"Building";"CreepTumor";NA;318;0
"Building";"CreepTumor";NA;318;0
"Building";"Hatchery";NA;294;0
"Building";"CreepTumor";NA;318;0
"Building";"CreepTumor";NA;340;0
"Upgrade";"ZergGroundArmorsLevel2";"EvolutionChamber";294;0
"Upgrade";"ZergMeleeWeaponsLevel2";"EvolutionChamber";294;0
"Upgrade";"ChitinousPlating";"UltraliskCavern";322;0
"Unit";"Zergling";"Larva";346;1
"Unit";"Zergling";"Larva";346;1
"Unit";"Zergling";"Larva";346;1
"Unit";"Zergling";"Larva";346;1
"Unit";"Zergling";"Larva";346;1
"Unit";"Zergling";"Larva";346;1
"Unit";"Zergling";"Larva";346;1
"Unit";"Zergling";"Larva";346;1
"Unit";"Zergling";"Larva";346;1
"Unit";"Zergling";"Larva";346;1
"Unit";"Zergling";"Larva";346;1
"Unit";"Zergling";"Larva";346;1
"Unit";"Zergling";"Larva";346;1
"Unit";"Zergling";"Larva";346;1
"Unit";"Zergling";"Larva";346;1
"Unit";"Zergling";"Larva";346;1
"Unit";"Zergling";"Larva";346;1
"Unit";"Zergling";"Larva";346;1
"Unit";"Zergling";"Larva";346;1
"Unit";"Zergling";"Larva";346;1
"Unit";"Zergling";"Larva";346;1
"Unit";"Zergling";"Larva";346;1
"Unit";"Zergling";"Larva";346;1
"Unit";"Zergling";"Larva";346;1
"Unit";"Zergling";"Larva";346;1
"Unit";"Zergling";"Larva";346;1
"Unit";"Zergling";"Larva";346;1
"Unit";"Zergling";"Larva";346;1
"Unit";"Zergling";"Larva";346;1
"Unit";"Zergling";"Larva";346;1
"Unit";"Zergling";"Larva";346;1
"Unit";"Zergling";"Larva";346;1
"Unit";"Zergling";"Larva";346;1
"Unit";"Zergling";"Larva";346;1
"Unit";"Zergling";"Larva";346;1
"Unit";"Zergling";"Larva";346;1
"Unit";"Zergling";"Larva";346;1
"Unit";"Zergling";"Larva";346;1
"Unit";"Zergling";"Larva";346;1
"Unit";"Zergling";"Larva";346;1
"Unit";"Zergling";"Larva";346;1
"Unit";"Zergling";"Larva";346;1
"Unit";"Zergling";"Larva";346;1
"Unit";"Zergling";"Larva";346;1
"Unit";"Zergling";"Larva";346;1
"Unit";"Zergling";"Larva";346;1
"Unit";"Zergling";"Larva";346;1
"Unit";"Zergling";"Larva";346;1
"Unit";"Zergling";"Larva";394;1
"Unit";"Zergling";"Larva";394;1
"Unit";"Zergling";"Larva";394;1
"Unit";"Zergling";"Larva";394;1
"Building";"CreepTumor";NA;398;0
"Unit";"Corruptor";"Larva";398;2
"Unit";"Corruptor";"Larva";398;2
"Unit";"Corruptor";"Larva";398;2
"Unit";"Corruptor";"Larva";398;2
"Unit";"Corruptor";"Larva";398;2
"Building";"CreepTumorQueen";NA;398;0
"Unit";"Corruptor";"Larva";398;2
"Unit";"Corruptor";"Larva";398;2
"Unit";"Corruptor";"Larva";398;2
"Unit";"Corruptor";"Larva";398;2
"Building";"Extractor";NA;398;0
"Building";"Extractor";NA;398;0
"Building";"CreepTumor";NA;402;0
"Building";"CreepTumor";NA;424;0
"Building";"CreepTumor";NA;424;0
"Building";"CreepTumorQueen";NA;424;0
"Building";"Hatchery";NA;398;0
"Building";"Spire";NA;398;0
"Unit";"Zergling";"Larva";424;1
"Unit";"Zergling";"Larva";424;1
"Unit";"Zergling";"Larva";424;1
"Unit";"Zergling";"Larva";424;1
"Unit";"Zergling";"Larva";424;1
"Unit";"Zergling";"Larva";424;1
"Unit";"Zergling";"Larva";424;1
"Unit";"Zergling";"Larva";424;1
"Unit";"Zergling";"Larva";424;1
"Unit";"Zergling";"Larva";424;1
"Unit";"Zergling";"Larva";424;1
"Unit";"Zergling";"Larva";424;1
"Unit";"Zergling";"Larva";424;1
"Unit";"Zergling";"Larva";424;1
"Unit";"Zergling";"Larva";424;1
"Unit";"Zergling";"Larva";424;1
"Unit";"Zergling";"Larva";424;1
"Unit";"Zergling";"Larva";424;1
"Unit";"Zergling";"Larva";424;1
"Unit";"Zergling";"Larva";424;1
"Unit";"Zergling";"Larva";424;1
"Unit";"Zergling";"Larva";424;1
"Unit";"Zergling";"Larva";424;1
"Unit";"Zergling";"Larva";424;1
"Upgrade";"ZergGroundArmorsLevel3";"EvolutionChamber";398;0
"Upgrade";"ZergMeleeWeaponsLevel3";"EvolutionChamber";398;0
"Building";"CreepTumor";NA;448;0
"Unit";"Corruptor";"Larva";424;2
"Unit";"Corruptor";"Larva";424;2
"Unit";"Corruptor";"Larva";424;2
"Unit";"Corruptor";"Larva";424;2
"Unit";"Corruptor";"Larva";424;2
"Unit";"Corruptor";"Larva";424;2
"Unit";"Corruptor";"Larva";424;2
"Building";"CreepTumor";NA;462;0
"Unit";"Viper";"Larva";462;3
"Upgrade";"ZergMissileWeaponsLevel2";"EvolutionChamber";424;0
"Building";"Hatchery";NA;462;0
"Building";"CreepTumor";NA;465;0
"Unit";"Zergling";"Larva";465;1
"Unit";"Zergling";"Larva";465;1
"Unit";"Zergling";"Larva";465;1
"Unit";"Zergling";"Larva";465;1
"Unit";"Zergling";"Larva";465;1
"Unit";"Zergling";"Larva";465;1
"Unit";"Zergling";"Larva";465;1
"Unit";"Zergling";"Larva";465;1
"Unit";"Zergling";"Larva";465;1
"Unit";"Zergling";"Larva";465;1
"Unit";"Zergling";"Larva";465;1
"Unit";"Zergling";"Larva";465;1
"Unit";"Zergling";"Larva";465;1
"Unit";"Zergling";"Larva";465;1
"Unit";"Zergling";"Larva";465;1
"Unit";"Zergling";"Larva";465;1
"Unit";"Zergling";"Larva";465;1
"Unit";"Zergling";"Larva";465;1
"Unit";"Zergling";"Larva";465;1
"Unit";"Zergling";"Larva";465;1
"Unit";"Zergling";"Larva";465;1
"Unit";"Zergling";"Larva";465;1
"Unit";"Viper";"Larva";465;3
"Unit";"Viper";"Larva";465;3
"Unit";"Viper";"Larva";465;3
"Unit";"Zergling";"Larva";487;1
"Unit";"Zergling";"Larva";487;1
"Unit";"Zergling";"Larva";487;1
"Unit";"Zergling";"Larva";487;1
"Unit";"Zergling";"Larva";487;1
"Unit";"Zergling";"Larva";487;1
"Unit";"Zergling";"Larva";487;1
"Unit";"Zergling";"Larva";487;1
"Unit";"Zergling";"Larva";487;1
"Unit";"Zergling";"Larva";487;1
"Unit";"Zergling";"Larva";487;1
"Unit";"Zergling";"Larva";487;1
"Unit";"Zergling";"Larva";487;1
"Unit";"Zergling";"Larva";487;1
"Unit";"Zergling";"Larva";496;1
"Unit";"Zergling";"Larva";496;1
"Unit";"Zergling";"Larva";496;1
"Unit";"Zergling";"Larva";496;1
"Unit";"Zergling";"Larva";496;1
"Unit";"Zergling";"Larva";496;1
"Unit";"Zergling";"Larva";496;1
"Unit";"Zergling";"Larva";496;1
"Unit";"Zergling";"Larva";496;1
"Unit";"Zergling";"Larva";496;1
"Unit";"Zergling";"Larva";496;1
"Unit";"Zergling";"Larva";496;1
"Building";"CreepTumor";NA;510;0
"Unit";"Corruptor";"Larva";522;2
"Unit";"Corruptor";"Larva";522;2
"Unit";"Corruptor";"Larva";522;2
"Unit";"Corruptor";"Larva";522;2
"Unit";"Corruptor";"Larva";522;2
"Unit";"Corruptor";"Larva";522;2
"Unit";"Corruptor";"Larva";522;2
"Unit";"Corruptor";"Larva";522;2
"Unit";"Corruptor";"Larva";522;2
"Building";"CreepTumor";NA;524;0
"Unit";"Corruptor";"Larva";524;2
"Unit";"Corruptor";"Larva";524;2
"Unit";"Corruptor";"Larva";524;2
"Unit";"Corruptor";"Larva";524;2
"Unit";"Corruptor";"Larva";524;2
"Unit";"Corruptor";"Larva";524;2
"Unit";"Corruptor";"Larva";524;2
"Unit";"Corruptor";"Larva";524;2
"Unit";"Hydralisk";"Larva";540;2
"Unit";"Hydralisk";"Larva";540;2
"Unit";"Hydralisk";"Larva";540;2
"Unit";"Hydralisk";"Larva";540;2
"Unit";"Hydralisk";"Larva";540;2
"Unit";"Hydralisk";"Larva";540;2
"Unit";"Hydralisk";"Larva";540;2
"Unit";"Hydralisk";"Larva";540;2
"Unit";"Queen";"Hatchery";540;2
"Unit";"Queen";"Hatchery";540;2
