"type";"unit_name";"on_building";"total_supply";"supply"
"Unit";"Overlord";"Larva";12;0
"Building";"Extractor";NA;19;0
"Building";"Hatchery";NA;17;0
"Building";"SpawningPool";NA;20;0
"Unit";"Queen";"Hatchery";24;2
"Unit";"Queen";"Hatchery";24;2
"Unit";"Overlord";"Larva";26;0
"Unit";"Overlord";"Larva";29;0
"Unit";"Overlord";"Larva";32;0
"Building";"Hatchery";NA;23;0
"Unit";"Overlord";"Larva";37;0
"Unit";"Queen";"Hatchery";37;2
"Unit";"Zergling";"Larva";42;1
"Unit";"Zergling";"Larva";42;1
"Unit";"Zergling";"Larva";42;1
"Unit";"Zergling";"Larva";42;1
"Unit";"Zergling";"Larva";42;1
"Unit";"Zergling";"Larva";42;1
"Unit";"Zergling";"Larva";42;1
"Unit";"Zergling";"Larva";42;1
"Unit";"Zergling";"Larva";42;1
"Unit";"Zergling";"Larva";42;1
"Unit";"Queen";"Hatchery";39;2
"Unit";"Queen";"Hatchery";39;2
"Building";"CreepTumorQueen";NA;54;0
"Building";"CreepTumorQueen";NA;54;0
"Unit";"Overlord";"Larva";54;0
"Unit";"Queen";"Hatchery";46;2
"Unit";"Overlord";"Larva";60;0
"Unit";"Overlord";"Larva";63;0
"Building";"BanelingNest";NA;54;0
"Building";"CreepTumorQueen";NA;68;0
"Building";"CreepTumorQueen";NA;68;0
"Building";"CreepTumor";NA;68;0
"Unit";"Overlord";"Larva";68;0
"Unit";"Overlord";"Larva";68;0
"Building";"CreepTumor";NA;70;0
"Unit";"Queen";"Hatchery";68;2
"Building";"CreepTumorQueen";NA;84;0
"Building";"CreepTumor";NA;84;0
"Building";"CreepTumor";NA;84;0
"Unit";"Baneling";"Zergling";84;0
"Unit";"Baneling";"Zergling";84;0
"Unit";"Zergling";"Larva";84;1
"Unit";"Zergling";"Larva";84;1
"Unit";"Zergling";"Larva";84;1
"Unit";"Zergling";"Larva";84;1
"Unit";"Zergling";"Larva";84;1
"Unit";"Zergling";"Larva";84;1
"Unit";"Queen";"Hatchery";74;2
"Building";"Extractor";NA;84;0
"Building";"Extractor";NA;84;0
"Building";"SporeCrawler";NA;84;0
"Building";"CreepTumor";NA;97;0
"Building";"CreepTumorQueen";NA;97;0
"Building";"CreepTumorQueen";NA;97;0
"Building";"CreepTumor";NA;97;0
"Building";"SporeCrawler";NA;86;0
"Building";"CreepTumor";NA;97;0
"Unit";"Overlord";"Larva";103;0
"Building";"CreepTumorQueen";NA;103;0
"Unit";"Overlord";"Larva";103;0
"Building";"CreepTumorQueen";NA;103;0
"Unit";"Overlord";"Larva";103;0
"Building";"CreepTumorQueen";NA;105;0
"Building";"CreepTumorQueen";NA;105;0
"Unit";"Overlord";"Larva";103;0
"Building";"CreepTumorQueen";NA;105;0
"Building";"CreepTumor";NA;105;0
"Building";"CreepTumor";NA;105;0
"Building";"CreepTumor";NA;105;0
"Unit";"Zergling";"Larva";105;1
"Unit";"Zergling";"Larva";105;1
"Unit";"Zergling";"Larva";105;1
"Unit";"Zergling";"Larva";105;1
"Unit";"Zergling";"Larva";105;1
"Unit";"Zergling";"Larva";105;1
"Unit";"Zergling";"Larva";105;1
"Unit";"Zergling";"Larva";105;1
"Unit";"Zergling";"Larva";105;1
"Unit";"Zergling";"Larva";105;1
"Unit";"Zergling";"Larva";105;1
"Unit";"Zergling";"Larva";105;1
"Unit";"Zergling";"Larva";105;1
"Unit";"Zergling";"Larva";105;1
"Unit";"Zergling";"Larva";105;1
"Unit";"Zergling";"Larva";105;1
"Unit";"Zergling";"Larva";105;1
"Unit";"Zergling";"Larva";105;1
"Unit";"Zergling";"Larva";105;1
"Unit";"Zergling";"Larva";105;1
"Unit";"Zergling";"Larva";105;1
"Unit";"Zergling";"Larva";105;1
"Unit";"Zergling";"Larva";105;1
"Unit";"Zergling";"Larva";105;1
"Unit";"Zergling";"Larva";105;1
"Unit";"Zergling";"Larva";105;1
"Unit";"Zergling";"Larva";105;1
"Unit";"Zergling";"Larva";105;1
"Unit";"Zergling";"Larva";105;1
"Unit";"Zergling";"Larva";105;1
"Unit";"Zergling";"Larva";129;1
"Unit";"Zergling";"Larva";129;1
"Building";"CreepTumor";NA;129;0
"Unit";"Zergling";"Larva";129;1
"Unit";"Zergling";"Larva";129;1
"Unit";"Zergling";"Larva";129;1
"Unit";"Zergling";"Larva";129;1
"Unit";"Zergling";"Larva";129;1
"Unit";"Zergling";"Larva";129;1
"Building";"CreepTumorQueen";NA;129;0
"Building";"CreepTumorQueen";NA;129;0
"Building";"CreepTumorQueen";NA;129;0
"Building";"CreepTumorQueen";NA;135;0
"Building";"CreepTumor";NA;135;0
"Building";"CreepTumor";NA;135;0
"Building";"CreepTumor";NA;135;0
"Building";"CreepTumor";NA;135;0
"Building";"CreepTumor";NA;135;0
"Building";"CreepTumor";NA;135;0
"Building";"SporeCrawler";NA;143;0
"Building";"Hatchery";NA;105;0
"Unit";"Overlord";"Larva";143;0
"Unit";"Overlord";"Larva";143;0
"Unit";"Zergling";"Larva";143;1
"Unit";"Zergling";"Larva";143;1
"Unit";"Zergling";"Larva";143;1
"Unit";"Zergling";"Larva";143;1
"Unit";"Zergling";"Larva";143;1
"Unit";"Zergling";"Larva";143;1
"Unit";"Zergling";"Larva";143;1
"Unit";"Zergling";"Larva";143;1
"Unit";"Zergling";"Larva";143;1
"Unit";"Zergling";"Larva";143;1
"Unit";"Zergling";"Larva";143;1
"Unit";"Zergling";"Larva";143;1
"Unit";"Zergling";"Larva";143;1
"Unit";"Zergling";"Larva";143;1
"Unit";"Zergling";"Larva";143;1
"Unit";"Zergling";"Larva";143;1
"Unit";"Zergling";"Larva";143;1
"Unit";"Zergling";"Larva";143;1
"Building";"Extractor";NA;143;0
"Building";"SporeCrawler";NA;143;0
"Building";"EvolutionChamber";NA;143;0
"Building";"EvolutionChamber";NA;143;0
"Building";"HydraliskDen";NA;143;0
"Building";"Extractor";NA;166;0
"Building";"Extractor";NA;166;0
"Building";"CreepTumor";NA;183;0
"Building";"CreepTumor";NA;183;0
"Unit";"Queen";"Hatchery";166;2
"Building";"CreepTumor";NA;183;0
"Building";"CreepTumor";NA;183;0
"Building";"CreepTumor";NA;183;0
"Unit";"Baneling";"Zergling";183;0
"Unit";"Baneling";"Zergling";183;0
"Unit";"Baneling";"Zergling";183;0
"Unit";"Baneling";"Zergling";183;0
"Unit";"Overlord";"Larva";183;0
"Unit";"Overlord";"Larva";183;0
"Unit";"Hydralisk";"Larva";183;2
"Unit";"Hydralisk";"Larva";183;2
"Unit";"Hydralisk";"Larva";183;2
"Unit";"Hydralisk";"Larva";183;2
"Unit";"Hydralisk";"Larva";183;2
"Unit";"Hydralisk";"Larva";183;2
"Unit";"Hydralisk";"Larva";183;2
"Unit";"Hydralisk";"Larva";183;2
"Unit";"Hydralisk";"Larva";183;2
"Building";"CreepTumor";NA;203;0
"Building";"CreepTumorQueen";NA;203;0
"Building";"CreepTumorQueen";NA;203;0
"Building";"CreepTumorQueen";NA;203;0
"Building";"CreepTumorQueen";NA;203;0
"Building";"CreepTumor";NA;203;0
"Building";"CreepTumor";NA;203;0
"Building";"CreepTumorQueen";NA;203;0
"Building";"CreepTumor";NA;203;0
"Upgrade";"EvolveGroovedSpines";"HydraliskDen";183;0
"Building";"CreepTumor";NA;203;0
"Building";"CreepTumor";NA;203;0
"Unit";"Overlord";"Larva";203;0
"Unit";"Overlord";"Larva";203;0
"Unit";"Overlord";"Larva";203;0
"Unit";"Overlord";"Larva";203;0
"Building";"CreepTumorQueen";NA;203;0
"Building";"InfestationPit";NA;199;0
"Building";"CreepTumorQueen";NA;213;0
"Building";"CreepTumorQueen";NA;213;0
"Building";"CreepTumorQueen";NA;213;0
"Building";"CreepTumor";NA;213;0
"Building";"CreepTumor";NA;213;0
"Building";"CreepTumor";NA;213;0
"Building";"CreepTumor";NA;213;0
"Building";"CreepTumor";NA;213;0
"Building";"CreepTumor";NA;213;0
"Building";"Hatchery";NA;183;0
"Unit";"Overlord";"Larva";213;0
"Unit";"Hydralisk";"Larva";209;2
"Unit";"Hydralisk";"Larva";213;2
"Unit";"Hydralisk";"Larva";213;2
"Unit";"Hydralisk";"Larva";213;2
"Unit";"Hydralisk";"Larva";213;2
"Unit";"Hydralisk";"Larva";213;2
"Unit";"Hydralisk";"Larva";213;2
"Unit";"Hydralisk";"Larva";213;2
"Unit";"Hydralisk";"Larva";213;2
"Unit";"Hydralisk";"Larva";213;2
"Building";"Extractor";NA;213;0
"Upgrade";"ZergGroundArmorsLevel1";"EvolutionChamber";183;0
"Upgrade";"ZergMeleeWeaponsLevel1";"EvolutionChamber";185;0
"Unit";"Overlord";"Larva";213;0
"Building";"CreepTumor";NA;233;0
"Building";"CreepTumor";NA;233;0
"Building";"CreepTumor";NA;233;0
"Building";"CreepTumor";NA;233;0
"Building";"SporeCrawler";NA;233;0
"Building";"CreepTumor";NA;233;0
"Building";"CreepTumor";NA;233;0
"Building";"CreepTumor";NA;233;0
"Building";"CreepTumor";NA;233;0
"Building";"Extractor";NA;233;0
"Unit";"Hydralisk";"Larva";233;2
"Unit";"Hydralisk";"Larva";233;2
"Unit";"Hydralisk";"Larva";233;2
"Unit";"Hydralisk";"Larva";233;2
"Unit";"Hydralisk";"Larva";233;2
"Unit";"Hydralisk";"Larva";233;2
"Upgrade";"EvolveMuscularAugments";"HydraliskDen";213;0
"Building";"CreepTumor";NA;233;0
"Building";"CreepTumor";NA;233;0
"Building";"CreepTumor";NA;233;0
"Building";"CreepTumor";NA;233;0
"Building";"CreepTumorQueen";NA;245;0
"Building";"CreepTumorQueen";NA;245;0
"Building";"CreepTumorQueen";NA;245;0
"Unit";"Zergling";"Larva";245;1
"Unit";"Zergling";"Larva";245;1
"Unit";"Zergling";"Larva";245;1
"Unit";"Zergling";"Larva";245;1
"Unit";"Zergling";"Larva";245;1
"Unit";"Zergling";"Larva";245;1
"Unit";"Zergling";"Larva";245;1
"Unit";"Zergling";"Larva";245;1
"Unit";"Zergling";"Larva";245;1
"Unit";"Zergling";"Larva";245;1
"Unit";"Zergling";"Larva";245;1
"Unit";"Zergling";"Larva";245;1
"Unit";"Zergling";"Larva";245;1
"Unit";"Zergling";"Larva";245;1
"Unit";"Zergling";"Larva";245;1
"Unit";"Zergling";"Larva";245;1
"Unit";"Zergling";"Larva";245;1
"Unit";"Zergling";"Larva";245;1
"Unit";"Zergling";"Larva";245;1
"Unit";"Zergling";"Larva";245;1
"Unit";"Zergling";"Larva";245;1
"Unit";"Zergling";"Larva";245;1
"Unit";"Zergling";"Larva";245;1
"Unit";"Zergling";"Larva";245;1
"Unit";"Zergling";"Larva";245;1
"Unit";"Zergling";"Larva";245;1
"Unit";"Zergling";"Larva";245;1
"Unit";"Zergling";"Larva";245;1
"Unit";"Zergling";"Larva";245;1
"Unit";"Zergling";"Larva";245;1
"Unit";"Zergling";"Larva";245;1
"Unit";"Zergling";"Larva";245;1
"Unit";"Hydralisk";"Larva";245;2
"Unit";"Hydralisk";"Larva";245;2
"Unit";"Hydralisk";"Larva";245;2
"Unit";"Zergling";"Larva";245;1
"Unit";"Zergling";"Larva";245;1
"Unit";"Zergling";"Larva";245;1
"Unit";"Zergling";"Larva";245;1
"Unit";"Zergling";"Larva";245;1
"Unit";"Zergling";"Larva";245;1
"Unit";"Zergling";"Larva";245;1
"Unit";"Zergling";"Larva";245;1
"Unit";"Zergling";"Larva";245;1
"Unit";"Zergling";"Larva";245;1
"Unit";"Zergling";"Larva";245;1
"Unit";"Zergling";"Larva";245;1
"Unit";"Zergling";"Larva";245;1
"Unit";"Zergling";"Larva";245;1
"Unit";"Queen";"Hatchery";245;2
"Unit";"Zergling";"Larva";245;1
"Unit";"Zergling";"Larva";245;1
"Unit";"Zergling";"Larva";245;1
"Unit";"Zergling";"Larva";245;1
"Unit";"Zergling";"Larva";245;1
"Unit";"Zergling";"Larva";245;1
"Unit";"Zergling";"Larva";245;1
"Unit";"Zergling";"Larva";245;1
"Building";"CreepTumor";NA;283;0
"Building";"CreepTumor";NA;283;0
"Building";"CreepTumor";NA;283;0
"Building";"CreepTumor";NA;283;0
"Building";"CreepTumor";NA;283;0
"Building";"Hatchery";NA;233;0
"Unit";"Zergling";"Larva";307;1
"Unit";"Zergling";"Larva";307;1
"Unit";"Zergling";"Larva";307;1
"Unit";"Zergling";"Larva";307;1
"Unit";"Zergling";"Larva";307;1
"Unit";"Zergling";"Larva";307;1
"Unit";"Zergling";"Larva";307;1
"Unit";"Zergling";"Larva";307;1
"Unit";"Zergling";"Larva";307;1
"Unit";"Zergling";"Larva";307;1
"Unit";"Zergling";"Larva";307;1
"Unit";"Zergling";"Larva";307;1
"Unit";"Zergling";"Larva";307;1
"Unit";"Zergling";"Larva";307;1
"Unit";"Zergling";"Larva";307;1
"Unit";"Zergling";"Larva";307;1
"Unit";"Zergling";"Larva";307;1
"Unit";"Zergling";"Larva";307;1
"Building";"CreepTumor";NA;307;0
"Building";"CreepTumor";NA;307;0
"Building";"CreepTumor";NA;307;0
"Building";"CreepTumor";NA;307;0
"Building";"CreepTumor";NA;307;0
"Building";"CreepTumor";NA;307;0
"Building";"CreepTumor";NA;307;0
"Unit";"Hydralisk";"Larva";307;2
"Unit";"Hydralisk";"Larva";307;2
"Unit";"Hydralisk";"Larva";307;2
"Unit";"Hydralisk";"Larva";307;2
"Unit";"Hydralisk";"Larva";307;2
"Unit";"Hydralisk";"Larva";307;2
"Unit";"Hydralisk";"Larva";307;2
"Building";"CreepTumor";NA;325;0
"Building";"CreepTumorQueen";NA;325;0
"Building";"SpineCrawler";NA;325;0
"Building";"SpineCrawler";NA;325;0
"Building";"SpineCrawler";NA;325;0
"Building";"SpineCrawler";NA;325;0
"Unit";"Baneling";"Zergling";339;0
"Unit";"Baneling";"Zergling";339;0
"Unit";"Baneling";"Zergling";339;0
"Unit";"Baneling";"Zergling";339;0
"Unit";"Baneling";"Zergling";339;0
"Unit";"Baneling";"Zergling";339;0
"Unit";"Baneling";"Zergling";339;0
"Unit";"Baneling";"Zergling";339;0
"Unit";"Baneling";"Zergling";339;0
"Unit";"Baneling";"Zergling";339;0
"Unit";"Baneling";"Zergling";339;0
"Unit";"Baneling";"Zergling";339;0
"Unit";"Baneling";"Zergling";339;0
"Unit";"Baneling";"Zergling";339;0
"Unit";"Baneling";"Zergling";339;0
"Unit";"Baneling";"Zergling";339;0
"Unit";"Baneling";"Zergling";339;0
"Unit";"Baneling";"Zergling";339;0
"Unit";"Baneling";"Zergling";339;0
"Unit";"Baneling";"Zergling";339;0
"Unit";"Baneling";"Zergling";339;0
"Unit";"Overlord";"Larva";339;0
"Unit";"Baneling";"Zergling";339;0
"Unit";"Baneling";"Zergling";339;0
"Unit";"Overlord";"Larva";339;0
"Unit";"Baneling";"Zergling";339;0
"Unit";"Baneling";"Zergling";339;0
"Unit";"Baneling";"Zergling";339;0
"Unit";"Baneling";"Zergling";339;0
"Unit";"Baneling";"Zergling";339;0
"Unit";"Baneling";"Zergling";339;0
"Unit";"Baneling";"Zergling";339;0
"Unit";"Baneling";"Zergling";339;0
"Unit";"Baneling";"Zergling";339;0
"Unit";"Baneling";"Zergling";339;0
"Unit";"Baneling";"Zergling";339;0
"Unit";"Baneling";"Zergling";339;0
"Unit";"Baneling";"Zergling";339;0
"Unit";"Baneling";"Zergling";339;0
"Unit";"Baneling";"Zergling";339;0
"Unit";"Baneling";"Zergling";339;0
"Unit";"Baneling";"Zergling";339;0
"Upgrade";"ZergMissileWeaponsLevel1";"EvolutionChamber";283;0
"Unit";"Overlord";"Larva";339;0
"Unit";"Overlord";"Larva";339;0
"Unit";"Hydralisk";"Larva";339;2
"Unit";"Hydralisk";"Larva";339;2
"Unit";"Hydralisk";"Larva";339;2
"Unit";"Hydralisk";"Larva";339;2
"Unit";"Hydralisk";"Larva";339;2
"Unit";"Hydralisk";"Larva";339;2
"Unit";"Hydralisk";"Larva";339;2
"Unit";"Hydralisk";"Larva";339;2
"Upgrade";"ZergGroundArmorsLevel2";"EvolutionChamber";283;0
"Building";"CreepTumor";NA;355;0
"Building";"CreepTumor";NA;355;0
"Building";"CreepTumor";NA;355;0
"Building";"CreepTumor";NA;355;0
"Unit";"Hydralisk";"Larva";339;2
"Unit";"Hydralisk";"Larva";339;2
"Unit";"Hydralisk";"Larva";339;2
"Unit";"Hydralisk";"Larva";339;2
"Unit";"Hydralisk";"Larva";339;2
"Unit";"Hydralisk";"Larva";339;2
"Unit";"Hydralisk";"Larva";339;2
"Unit";"Hydralisk";"Larva";339;2
"Unit";"Hydralisk";"Larva";339;2
"Unit";"Hydralisk";"Larva";339;2
"Unit";"Hydralisk";"Larva";339;2
"Building";"CreepTumor";NA;355;0
"Building";"CreepTumor";NA;377;0
"Unit";"Hydralisk";"Larva";355;2
"Unit";"Hydralisk";"Larva";355;2
"Unit";"Zergling";"Larva";377;1
"Unit";"Zergling";"Larva";377;1
"Unit";"Zergling";"Larva";377;1
"Unit";"Zergling";"Larva";377;1
"Unit";"Zergling";"Larva";377;1
"Unit";"Zergling";"Larva";377;1
"Unit";"Zergling";"Larva";377;1
"Unit";"Zergling";"Larva";377;1
"Unit";"Zergling";"Larva";377;1
"Unit";"Zergling";"Larva";377;1
"Unit";"Zergling";"Larva";377;1
"Unit";"Zergling";"Larva";377;1
"Unit";"Zergling";"Larva";377;1
"Unit";"Zergling";"Larva";377;1
"Unit";"Zergling";"Larva";377;1
"Unit";"Zergling";"Larva";377;1
"Unit";"Zergling";"Larva";377;1
"Unit";"Zergling";"Larva";377;1
"Unit";"Zergling";"Larva";377;1
"Unit";"Zergling";"Larva";377;1
"Unit";"Zergling";"Larva";377;1
"Unit";"Zergling";"Larva";377;1
"Unit";"Zergling";"Larva";377;1
"Unit";"Zergling";"Larva";377;1
"Unit";"Zergling";"Larva";377;1
"Unit";"Zergling";"Larva";377;1
"Unit";"Zergling";"Larva";377;1
"Unit";"Zergling";"Larva";377;1
"Unit";"Zergling";"Larva";422;1
"Unit";"Zergling";"Larva";422;1
"Unit";"Zergling";"Larva";422;1
"Unit";"Zergling";"Larva";422;1
"Unit";"Zergling";"Larva";422;1
"Unit";"Zergling";"Larva";422;1
"Unit";"Zergling";"Larva";422;1
"Unit";"Zergling";"Larva";422;1
"Unit";"Zergling";"Larva";422;1
"Unit";"Zergling";"Larva";422;1
"Unit";"Viper";"Larva";422;3
"Unit";"Viper";"Larva";422;3
"Unit";"Viper";"Larva";422;3
"Unit";"Viper";"Larva";422;3
"Building";"CreepTumor";NA;432;0
"Building";"CreepTumor";NA;432;0
"Building";"CreepTumorQueen";NA;432;0
"Building";"CreepTumor";NA;432;0
"Building";"CreepTumorQueen";NA;432;0
"Building";"CreepTumor";NA;432;0
"Building";"CreepTumor";NA;432;0
"Building";"CreepTumor";NA;432;0
"Building";"CreepTumor";NA;432;0
"Building";"CreepTumor";NA;432;0
"Building";"CreepTumor";NA;432;0
"Building";"CreepTumor";NA;444;0
"Building";"CreepTumor";NA;444;0
"Building";"CreepTumor";NA;444;0
"Building";"CreepTumor";NA;444;0
"Building";"CreepTumor";NA;444;0
"Building";"CreepTumor";NA;444;0
"Building";"Extractor";NA;444;0
"Unit";"Zergling";"Larva";444;1
"Unit";"Zergling";"Larva";444;1
"Unit";"Zergling";"Larva";444;1
"Unit";"Zergling";"Larva";444;1
"Unit";"Zergling";"Larva";444;1
"Unit";"Zergling";"Larva";444;1
"Unit";"Zergling";"Larva";444;1
"Unit";"Zergling";"Larva";444;1
"Building";"Extractor";NA;444;0
"Unit";"Zergling";"Larva";452;1
"Unit";"Zergling";"Larva";452;1
"Unit";"Zergling";"Larva";452;1
"Unit";"Zergling";"Larva";452;1
"Unit";"Zergling";"Larva";452;1
"Unit";"Zergling";"Larva";452;1
"Building";"CreepTumor";NA;479;0
"Building";"CreepTumor";NA;479;0
"Building";"CreepTumorQueen";NA;479;0
"Building";"CreepTumorQueen";NA;479;0
"Unit";"Baneling";"Zergling";479;0
"Unit";"Baneling";"Zergling";479;0
"Unit";"Baneling";"Zergling";479;0
"Unit";"Baneling";"Zergling";479;0
"Unit";"Baneling";"Zergling";479;0
"Unit";"Baneling";"Zergling";479;0
"Unit";"Baneling";"Zergling";479;0
"Unit";"Baneling";"Zergling";479;0
"Unit";"Baneling";"Zergling";479;0
"Unit";"Baneling";"Zergling";479;0
"Unit";"Baneling";"Zergling";479;0
"Unit";"Baneling";"Zergling";479;0
"Unit";"Baneling";"Zergling";479;0
"Building";"CreepTumor";NA;479;0
"Building";"CreepTumor";NA;479;0
"Building";"CreepTumor";NA;479;0
"Upgrade";"ZergGroundArmorsLevel3";"EvolutionChamber";422;0
"Unit";"Zergling";"Larva";479;1
"Unit";"Zergling";"Larva";479;1
"Unit";"Zergling";"Larva";479;1
"Unit";"Zergling";"Larva";479;1
"Unit";"Zergling";"Larva";479;1
"Unit";"Zergling";"Larva";479;1
"Unit";"Zergling";"Larva";479;1
"Unit";"Zergling";"Larva";479;1
"Unit";"Zergling";"Larva";479;1
"Unit";"Zergling";"Larva";479;1
"Unit";"Zergling";"Larva";479;1
"Unit";"Zergling";"Larva";479;1
"Unit";"Zergling";"Larva";479;1
"Unit";"Zergling";"Larva";479;1
"Unit";"Zergling";"Larva";479;1
"Unit";"Zergling";"Larva";479;1
"Unit";"Zergling";"Larva";479;1
"Unit";"Zergling";"Larva";479;1
"Unit";"Overlord";"Larva";485;0
"Building";"CreepTumor";NA;503;0
"Building";"CreepTumor";NA;503;0
"Building";"CreepTumor";NA;503;0
"Unit";"Overlord";"Larva";485;0
"Unit";"Overlord";"Larva";485;0
"Unit";"Overlord";"Larva";485;0
"Unit";"Overlord";"Larva";485;0
"Unit";"Overlord";"Larva";485;0
"Unit";"Overlord";"Larva";485;0
"Unit";"Overlord";"Larva";485;0
"Building";"CreepTumor";NA;503;0
"Building";"CreepTumor";NA;503;0
"Building";"CreepTumor";NA;503;0
"Building";"CreepTumor";NA;503;0
"Building";"CreepTumor";NA;503;0
"Building";"CreepTumor";NA;503;0
"Building";"CreepTumor";NA;503;0
"Building";"CreepTumor";NA;503;0
"Building";"SporeCrawler";NA;503;0
"Building";"CreepTumorQueen";NA;503;0
"Building";"CreepTumor";NA;503;0
"Building";"CreepTumorQueen";NA;503;0
"Building";"CreepTumorQueen";NA;503;0
"Building";"SpineCrawler";NA;503;0
"Building";"SpineCrawler";NA;503;0
"Unit";"Zergling";"Larva";503;1
"Unit";"Zergling";"Larva";503;1
"Unit";"Zergling";"Larva";503;1
"Unit";"Zergling";"Larva";503;1
"Unit";"Zergling";"Larva";503;1
"Unit";"Zergling";"Larva";503;1
"Unit";"Zergling";"Larva";503;1
"Unit";"Zergling";"Larva";503;1
"Unit";"Zergling";"Larva";503;1
"Unit";"Zergling";"Larva";503;1
"Unit";"Zergling";"Larva";503;1
"Unit";"Zergling";"Larva";503;1
"Unit";"Zergling";"Larva";503;1
"Unit";"Zergling";"Larva";503;1
"Unit";"Zergling";"Larva";503;1
"Unit";"Zergling";"Larva";503;1
"Unit";"Zergling";"Larva";503;1
"Unit";"Zergling";"Larva";503;1
"Unit";"Zergling";"Larva";503;1
"Unit";"Zergling";"Larva";503;1
"Unit";"Zergling";"Larva";503;1
"Unit";"Zergling";"Larva";503;1
"Unit";"Zergling";"Larva";503;1
"Unit";"Zergling";"Larva";503;1
"Unit";"Zergling";"Larva";503;1
"Unit";"Zergling";"Larva";503;1
"Unit";"Zergling";"Larva";503;1
"Unit";"Zergling";"Larva";503;1
"Unit";"Zergling";"Larva";503;1
"Unit";"Zergling";"Larva";503;1
"Unit";"Zergling";"Larva";503;1
"Unit";"Zergling";"Larva";503;1
"Unit";"Hydralisk";"Larva";503;2
"Unit";"Hydralisk";"Larva";503;2
"Unit";"Hydralisk";"Larva";503;2
"Unit";"Hydralisk";"Larva";503;2
"Unit";"Hydralisk";"Larva";503;2
"Unit";"Hydralisk";"Larva";503;2
"Unit";"Hydralisk";"Larva";503;2
"Unit";"Hydralisk";"Larva";503;2
"Unit";"Hydralisk";"Larva";503;2
"Unit";"Hydralisk";"Larva";503;2
"Unit";"Hydralisk";"Larva";503;2
"Unit";"Hydralisk";"Larva";503;2
"Unit";"Hydralisk";"Larva";503;2
"Unit";"Hydralisk";"Larva";503;2
"Unit";"Hydralisk";"Larva";503;2
"Unit";"Hydralisk";"Larva";503;2
"Unit";"Hydralisk";"Larva";503;2
"Building";"Spire";NA;503;0
"Unit";"Overlord";"Larva";503;0
"Unit";"Hydralisk";"Larva";503;2
"Unit";"Overlord";"Larva";531;0
"Upgrade";"ZergMissileWeaponsLevel2";"EvolutionChamber";485;0
"Building";"Hatchery";NA;503;0
"Unit";"Hydralisk";"Larva";571;2
"Unit";"Hydralisk";"Larva";571;2
"Unit";"Hydralisk";"Larva";571;2
"Unit";"Hydralisk";"Larva";571;2
"Unit";"Hydralisk";"Larva";571;2
"Unit";"Hydralisk";"Larva";571;2
"Unit";"Hydralisk";"Larva";571;2
"Unit";"Hydralisk";"Larva";571;2
"Unit";"Hydralisk";"Larva";571;2
"Unit";"Hydralisk";"Larva";571;2
"Unit";"Hydralisk";"Larva";571;2
"Unit";"Hydralisk";"Larva";571;2
"Unit";"Hydralisk";"Larva";571;2
"Unit";"Hydralisk";"Larva";571;2
"Unit";"Hydralisk";"Larva";571;2
"Unit";"Hydralisk";"Larva";571;2
"Unit";"Hydralisk";"Larva";571;2
"Unit";"Hydralisk";"Larva";571;2
"Unit";"Hydralisk";"Larva";571;2
"Unit";"Hydralisk";"Larva";571;2
"Unit";"Hydralisk";"Larva";571;2
"Unit";"Hydralisk";"Larva";571;2
"Unit";"Hydralisk";"Larva";571;2
"Unit";"Hydralisk";"Larva";571;2
"Unit";"Hydralisk";"Larva";571;2
"Unit";"Hydralisk";"Larva";571;2
"Unit";"Hydralisk";"Larva";605;2
"Unit";"Hydralisk";"Larva";605;2
"Unit";"Hydralisk";"Larva";605;2
"Unit";"Hydralisk";"Larva";605;2
"Unit";"Hydralisk";"Larva";605;2
"Unit";"Hydralisk";"Larva";605;2
"Unit";"Hydralisk";"Larva";605;2
"Unit";"Zergling";"Larva";607;1
"Unit";"Zergling";"Larva";607;1
"Unit";"Zergling";"Larva";607;1
"Unit";"Zergling";"Larva";607;1
"Unit";"Zergling";"Larva";607;1
"Unit";"Zergling";"Larva";607;1
"Unit";"Zergling";"Larva";607;1
"Unit";"Zergling";"Larva";607;1
"Unit";"Zergling";"Larva";607;1
"Unit";"Zergling";"Larva";607;1
"Unit";"Zergling";"Larva";607;1
"Unit";"Zergling";"Larva";607;1
"Unit";"Zergling";"Larva";607;1
"Unit";"Zergling";"Larva";607;1
"Building";"CreepTumor";NA;623;0
"Building";"CreepTumor";NA;623;0
"Building";"CreepTumor";NA;623;0
"Unit";"Hydralisk";"Larva";623;2
"Unit";"Hydralisk";"Larva";623;2
"Unit";"Hydralisk";"Larva";623;2
"Unit";"Hydralisk";"Larva";623;2
"Unit";"Hydralisk";"Larva";623;2
"Unit";"Hydralisk";"Larva";623;2
"Unit";"Hydralisk";"Larva";623;2
"Unit";"Hydralisk";"Larva";651;2
"Unit";"Zergling";"Larva";651;1
"Unit";"Zergling";"Larva";651;1
"Unit";"Zergling";"Larva";651;1
"Unit";"Zergling";"Larva";651;1
"Unit";"Zergling";"Larva";651;1
"Unit";"Zergling";"Larva";651;1
"Unit";"Zergling";"Larva";651;1
"Unit";"Zergling";"Larva";651;1
"Unit";"Zergling";"Larva";651;1
"Unit";"Zergling";"Larva";651;1
"Unit";"Zergling";"Larva";651;1
"Unit";"Zergling";"Larva";651;1
"Unit";"Zergling";"Larva";651;1
"Unit";"Zergling";"Larva";651;1
"Unit";"Zergling";"Larva";651;1
"Unit";"Zergling";"Larva";651;1
"Unit";"Zergling";"Larva";651;1
"Unit";"Zergling";"Larva";651;1
"Unit";"Zergling";"Larva";651;1
"Unit";"Zergling";"Larva";651;1
"Unit";"Zergling";"Larva";651;1
"Unit";"Zergling";"Larva";651;1
"Unit";"Zergling";"Larva";651;1
"Unit";"Zergling";"Larva";651;1
"Unit";"Zergling";"Larva";651;1
"Unit";"Zergling";"Larva";651;1
"Unit";"Zergling";"Larva";651;1
"Unit";"Zergling";"Larva";651;1
"Unit";"Zergling";"Larva";651;1
"Unit";"Zergling";"Larva";651;1
"Unit";"Zergling";"Larva";651;1
"Unit";"Zergling";"Larva";651;1
"Unit";"Zergling";"Larva";651;1
"Unit";"Zergling";"Larva";651;1
"Unit";"Zergling";"Larva";651;1
"Unit";"Zergling";"Larva";651;1
"Building";"CreepTumor";NA;665;0
"Building";"CreepTumor";NA;665;0
"Building";"CreepTumor";NA;665;0
"Unit";"Zergling";"Larva";665;1
"Unit";"Zergling";"Larva";665;1
"Unit";"Zergling";"Larva";665;1
"Unit";"Zergling";"Larva";665;1
"Unit";"Zergling";"Larva";665;1
"Unit";"Zergling";"Larva";665;1
"Unit";"Zergling";"Larva";665;1
"Unit";"Zergling";"Larva";665;1
"Unit";"Zergling";"Larva";665;1
"Unit";"Zergling";"Larva";665;1
"Unit";"Zergling";"Larva";665;1
"Unit";"Zergling";"Larva";665;1
"Unit";"Zergling";"Larva";665;1
"Unit";"Zergling";"Larva";665;1
"Unit";"Zergling";"Larva";667;1
"Unit";"Zergling";"Larva";667;1
"Building";"CreepTumor";NA;703;0
"Unit";"Zergling";"Larva";667;1
"Unit";"Zergling";"Larva";667;1
"Unit";"Zergling";"Larva";667;1
"Unit";"Zergling";"Larva";667;1
"Unit";"Zergling";"Larva";667;1
"Unit";"Zergling";"Larva";667;1
"Building";"CreepTumor";NA;703;0
"Building";"CreepTumor";NA;703;0
"Upgrade";"Burrow";"Hatchery";651;0
"Unit";"Hydralisk";"Larva";703;2
"Unit";"Hydralisk";"Larva";703;2
"Unit";"Hydralisk";"Larva";703;2
"Unit";"Hydralisk";"Larva";703;2
"Unit";"Baneling";"Zergling";725;0
"Unit";"Baneling";"Zergling";725;0
"Unit";"Baneling";"Zergling";725;0
"Unit";"Baneling";"Zergling";725;0
"Unit";"Baneling";"Zergling";725;0
"Unit";"Baneling";"Zergling";725;0
"Unit";"Baneling";"Zergling";725;0
"Unit";"Baneling";"Zergling";725;0
"Unit";"Baneling";"Zergling";725;0
"Unit";"Baneling";"Zergling";725;0
"Unit";"Baneling";"Zergling";725;0
"Unit";"Baneling";"Zergling";725;0
"Unit";"Baneling";"Zergling";725;0
"Unit";"Baneling";"Zergling";725;0
"Unit";"Baneling";"Zergling";725;0
"Unit";"Baneling";"Zergling";725;0
"Unit";"Baneling";"Zergling";725;0
"Unit";"Baneling";"Zergling";725;0
"Unit";"Baneling";"Zergling";725;0
"Unit";"Baneling";"Zergling";725;0
"Unit";"Baneling";"Zergling";725;0
"Building";"CreepTumor";NA;725;0
"Building";"CreepTumor";NA;725;0
"Unit";"Corruptor";"Larva";717;2
"Unit";"Corruptor";"Larva";717;2
"Unit";"Corruptor";"Larva";717;2
"Unit";"Corruptor";"Larva";717;2
"Unit";"Corruptor";"Larva";717;2
"Unit";"Corruptor";"Larva";717;2
"Unit";"Corruptor";"Larva";717;2
"Unit";"Corruptor";"Larva";717;2
"Building";"CreepTumor";NA;733;0
"Unit";"Hydralisk";"Larva";725;2
"Unit";"Hydralisk";"Larva";725;2
"Unit";"Hydralisk";"Larva";725;2
"Unit";"Hydralisk";"Larva";725;2
"Building";"CreepTumor";NA;733;0
"Unit";"Overlord";"Larva";733;0
"Unit";"Overlord";"Larva";733;0
"Unit";"Overlord";"Larva";733;0
"Unit";"Overlord";"Larva";733;0
"Unit";"Overlord";"Larva";733;0
"Unit";"Overlord";"Larva";733;0
"Unit";"Baneling";"Zergling";737;0
"Unit";"Baneling";"Zergling";749;0
"Unit";"Baneling";"Zergling";749;0
"Unit";"Baneling";"Zergling";749;0
"Unit";"Baneling";"Zergling";749;0
"Unit";"Baneling";"Zergling";749;0
"Unit";"Baneling";"Zergling";749;0
"Building";"Extractor";NA;733;0
"Building";"Extractor";NA;733;0
"Building";"CreepTumor";NA;757;0
"Building";"CreepTumor";NA;757;0
"Building";"CreepTumor";NA;757;0
"Building";"CreepTumor";NA;757;0
"Unit";"Overlord";"Larva";757;0
"Unit";"Overlord";"Larva";757;0
"Unit";"Overlord";"Larva";757;0
"Unit";"Overlord";"Larva";757;0
"Unit";"Overlord";"Larva";757;0
"Unit";"Overlord";"Larva";757;0
"Building";"CreepTumor";NA;757;0
"Building";"CreepTumor";NA;757;0
"Building";"CreepTumor";NA;757;0
"Building";"CreepTumor";NA;757;0
"Building";"CreepTumor";NA;757;0
"Building";"CreepTumor";NA;757;0
"Building";"SporeCrawler";NA;757;0
"Building";"CreepTumor";NA;757;0
"Building";"CreepTumor";NA;757;0
"Upgrade";"ZergMissileWeaponsLevel3";"EvolutionChamber";665;0
"Building";"SpineCrawler";NA;757;0
"Building";"CreepTumor";NA;757;0
"Building";"CreepTumor";NA;757;0
"Building";"CreepTumor";NA;757;0
"Building";"CreepTumor";NA;757;0
"Unit";"Corruptor";"Larva";757;2
"Unit";"Corruptor";"Larva";757;2
"Unit";"Corruptor";"Larva";757;2
"Unit";"Corruptor";"Larva";757;2
"Unit";"Corruptor";"Larva";757;2
"Building";"CreepTumor";NA;757;0
"Building";"CreepTumor";NA;767;0
"Building";"CreepTumor";NA;767;0
"Building";"CreepTumor";NA;767;0
"Building";"CreepTumor";NA;767;0
"Building";"CreepTumor";NA;767;0
"Building";"CreepTumor";NA;767;0
"Building";"CreepTumor";NA;767;0
"Building";"CreepTumor";NA;767;0
"Building";"CreepTumor";NA;767;0
"Building";"CreepTumor";NA;767;0
"Building";"CreepTumor";NA;767;0
"Building";"CreepTumor";NA;767;0
"Unit";"Corruptor";"Larva";767;2
"Unit";"Corruptor";"Larva";767;2
"Unit";"Corruptor";"Larva";767;2
"Unit";"Corruptor";"Larva";767;2
"Unit";"Corruptor";"Larva";767;2
"Building";"CreepTumor";NA;767;0
"Building";"CreepTumor";NA;767;0
"Building";"Extractor";NA;767;0
"Building";"Extractor";NA;767;0
"Unit";"Baneling";"Zergling";777;0
"Unit";"Baneling";"Zergling";777;0
"Unit";"Baneling";"Zergling";777;0
"Unit";"Baneling";"Zergling";777;0
"Unit";"Baneling";"Zergling";777;0
"Unit";"Baneling";"Zergling";777;0
"Unit";"Baneling";"Zergling";777;0
"Unit";"Baneling";"Zergling";777;0
"Unit";"Baneling";"Zergling";777;0
"Unit";"Baneling";"Zergling";777;0
"Unit";"Baneling";"Zergling";777;0
"Unit";"Baneling";"Zergling";777;0
"Unit";"Baneling";"Zergling";777;0
"Unit";"Baneling";"Zergling";777;0
"Unit";"Viper";"Larva";767;3
"Unit";"Viper";"Larva";767;3
"Upgrade";"ZergMeleeWeaponsLevel2";"EvolutionChamber";757;0
"Building";"CreepTumor";NA;777;0
"Building";"CreepTumorQueen";NA;783;0
"Building";"CreepTumor";NA;783;0
"Building";"CreepTumorQueen";NA;783;0
"Building";"CreepTumorQueen";NA;783;0
"Building";"SporeCrawler";NA;783;0
"Building";"CreepTumorQueen";NA;783;0
"Building";"SporeCrawler";NA;783;0
"Building";"Hatchery";NA;767;0
"Unit";"Zergling";"Larva";783;1
"Unit";"Zergling";"Larva";783;1
"Unit";"Zergling";"Larva";783;1
"Unit";"Zergling";"Larva";783;1
"Building";"SporeCrawler";NA;783;0
"Unit";"Zergling";"Larva";783;1
"Unit";"Zergling";"Larva";783;1
"Unit";"Zergling";"Larva";783;1
"Unit";"Zergling";"Larva";783;1
"Unit";"Zergling";"Larva";783;1
"Unit";"Zergling";"Larva";783;1
"Unit";"Zergling";"Larva";783;1
"Unit";"Zergling";"Larva";783;1
"Unit";"Zergling";"Larva";783;1
"Unit";"Zergling";"Larva";783;1
"Unit";"Zergling";"Larva";783;1
"Unit";"Zergling";"Larva";783;1
"Building";"SporeCrawler";NA;783;0
"Unit";"Viper";"Larva";783;3
"Unit";"Viper";"Larva";783;3
"Unit";"Viper";"Larva";783;3
"Unit";"Viper";"Larva";783;3
"Building";"CreepTumor";NA;811;0
"Building";"CreepTumor";NA;811;0
"Building";"CreepTumor";NA;811;0
"Building";"CreepTumor";NA;811;0
"Building";"CreepTumor";NA;811;0
"Building";"SporeCrawler";NA;811;0
"Building";"SporeCrawler";NA;811;0
"Building";"CreepTumor";NA;811;0
"Building";"CreepTumor";NA;811;0
"Unit";"Corruptor";"Larva";811;2
"Unit";"Corruptor";"Larva";811;2
"Unit";"Corruptor";"Larva";811;2
"Unit";"Corruptor";"Larva";811;2
"Unit";"Corruptor";"Larva";811;2
"Unit";"Corruptor";"Larva";811;2
"Unit";"Corruptor";"Larva";811;2
"Building";"CreepTumorQueen";NA;811;0
"Building";"CreepTumorQueen";NA;811;0
"Building";"SpineCrawler";NA;811;0
"Building";"CreepTumorQueen";NA;811;0
"Building";"CreepTumorQueen";NA;811;0
"Building";"CreepTumor";NA;811;0
"Building";"CreepTumor";NA;811;0
"Building";"CreepTumor";NA;825;0
"Building";"SpineCrawler";NA;811;0
"Unit";"Hydralisk";"Larva";825;2
"Unit";"Hydralisk";"Larva";825;2
"Unit";"Hydralisk";"Larva";825;2
"Unit";"Hydralisk";"Larva";825;2
"Unit";"Hydralisk";"Larva";825;2
"Unit";"Hydralisk";"Larva";825;2
"Unit";"Hydralisk";"Larva";825;2
"Unit";"Hydralisk";"Larva";825;2
"Unit";"Corruptor";"Larva";825;2
"Unit";"Corruptor";"Larva";825;2
"Unit";"Corruptor";"Larva";825;2
"Unit";"Corruptor";"Larva";825;2
"Building";"CreepTumor";NA;849;0
"Building";"CreepTumor";NA;849;0
"Building";"CreepTumor";NA;849;0
"Building";"CreepTumor";NA;849;0
"Unit";"Zergling";"Larva";849;1
"Unit";"Zergling";"Larva";849;1
"Unit";"Zergling";"Larva";849;1
"Unit";"Zergling";"Larva";849;1
"Unit";"Zergling";"Larva";849;1
"Unit";"Zergling";"Larva";849;1
"Unit";"Zergling";"Larva";849;1
"Unit";"Zergling";"Larva";849;1
"Unit";"Zergling";"Larva";849;1
"Unit";"Zergling";"Larva";849;1
"Unit";"Zergling";"Larva";849;1
"Unit";"Zergling";"Larva";849;1
"Unit";"Zergling";"Larva";849;1
"Unit";"Zergling";"Larva";849;1
"Unit";"Zergling";"Larva";849;1
"Unit";"Zergling";"Larva";849;1
"Unit";"Zergling";"Larva";849;1
"Unit";"Zergling";"Larva";849;1
"Unit";"Zergling";"Larva";849;1
"Unit";"Zergling";"Larva";849;1
"Building";"CreepTumor";NA;849;0
"Building";"CreepTumorQueen";NA;849;0
"Unit";"Viper";"Larva";869;3
"Unit";"Viper";"Larva";869;3
"Unit";"Viper";"Larva";869;3
"Unit";"Viper";"Larva";869;3
"Unit";"Viper";"Larva";869;3
"Unit";"Baneling";"Zergling";869;0
"Unit";"Baneling";"Zergling";869;0
"Building";"CreepTumor";NA;884;0
"Building";"CreepTumor";NA;884;0
"Unit";"Hydralisk";"Larva";869;2
"Unit";"Hydralisk";"Larva";869;2
"Unit";"Hydralisk";"Larva";869;2
"Unit";"Hydralisk";"Larva";869;2
"Unit";"Hydralisk";"Larva";869;2
"Unit";"Hydralisk";"Larva";869;2
"Unit";"Hydralisk";"Larva";869;2
"Unit";"Baneling";"Zergling";884;0
"Unit";"Baneling";"Zergling";884;0
"Unit";"Baneling";"Zergling";884;0
"Building";"SporeCrawler";NA;898;0
"Building";"SporeCrawler";NA;898;0
"Building";"SporeCrawler";NA;898;0
"Building";"SporeCrawler";NA;898;0
"Building";"SporeCrawler";NA;898;0
"Building";"SporeCrawler";NA;898;0
"Building";"CreepTumorQueen";NA;898;0
"Building";"CreepTumorQueen";NA;898;0
"Building";"CreepTumor";NA;898;0
"Building";"CreepTumor";NA;898;0
"Building";"SporeCrawler";NA;898;0
"Building";"SporeCrawler";NA;898;0
"Building";"SporeCrawler";NA;898;0
"Building";"SporeCrawler";NA;898;0
"Building";"CreepTumor";NA;898;0
"Building";"CreepTumor";NA;898;0
"Building";"CreepTumor";NA;898;0
"Building";"CreepTumor";NA;898;0
"Building";"CreepTumor";NA;898;0
"Upgrade";"ZergMeleeWeaponsLevel3";"EvolutionChamber";869;0
"Building";"SporeCrawler";NA;898;0
"Building";"SporeCrawler";NA;898;0
"Building";"SporeCrawler";NA;898;0
"Building";"Hatchery";NA;898;0
"Unit";"Zergling";"Larva";898;1
"Unit";"Zergling";"Larva";898;1
"Unit";"Zergling";"Larva";898;1
"Unit";"Zergling";"Larva";898;1
"Unit";"Zergling";"Larva";898;1
"Unit";"Zergling";"Larva";898;1
"Unit";"Zergling";"Larva";898;1
"Unit";"Zergling";"Larva";898;1
"Unit";"Zergling";"Larva";898;1
"Unit";"Zergling";"Larva";898;1
"Unit";"Zergling";"Larva";898;1
"Unit";"Zergling";"Larva";898;1
"Unit";"Zergling";"Larva";898;1
"Unit";"Zergling";"Larva";898;1
"Unit";"Baneling";"Zergling";898;0
"Unit";"Baneling";"Zergling";898;0
"Unit";"Baneling";"Zergling";898;0
"Unit";"Baneling";"Zergling";898;0
"Unit";"Baneling";"Zergling";898;0
"Unit";"Baneling";"Zergling";898;0
"Unit";"Baneling";"Zergling";898;0
"Unit";"Baneling";"Zergling";898;0
"Unit";"Baneling";"Zergling";898;0
"Unit";"Baneling";"Zergling";898;0
"Unit";"Baneling";"Zergling";898;0
"Unit";"Baneling";"Zergling";898;0
"Unit";"Baneling";"Zergling";898;0
"Unit";"Baneling";"Zergling";898;0
"Unit";"Baneling";"Zergling";898;0
"Unit";"Zergling";"Larva";912;1
"Unit";"Zergling";"Larva";912;1
"Unit";"Zergling";"Larva";912;1
"Unit";"Zergling";"Larva";912;1
"Unit";"Zergling";"Larva";912;1
"Unit";"Zergling";"Larva";912;1
"Unit";"Zergling";"Larva";912;1
"Unit";"Zergling";"Larva";912;1
"Unit";"Zergling";"Larva";912;1
"Unit";"Zergling";"Larva";912;1
"Unit";"Zergling";"Larva";912;1
"Unit";"Zergling";"Larva";912;1
"Unit";"Zergling";"Larva";912;1
"Unit";"Zergling";"Larva";912;1
"Unit";"Zergling";"Larva";912;1
"Unit";"Zergling";"Larva";912;1
"Unit";"Queen";"Hatchery";912;2
"Unit";"Queen";"Hatchery";912;2
"Unit";"Queen";"Hatchery";932;2
"Unit";"Queen";"Hatchery";932;2
"Unit";"Queen";"Hatchery";932;2
"Unit";"Queen";"Hatchery";932;2
"Unit";"Zergling";"Larva";932;1
"Unit";"Zergling";"Larva";932;1
"Unit";"Zergling";"Larva";932;1
"Unit";"Zergling";"Larva";932;1
"Unit";"Zergling";"Larva";932;1
"Unit";"Zergling";"Larva";932;1
"Unit";"Zergling";"Larva";932;1
"Unit";"Zergling";"Larva";932;1
"Unit";"Zergling";"Larva";932;1
"Unit";"Zergling";"Larva";932;1
"Unit";"Zergling";"Larva";932;1
"Unit";"Zergling";"Larva";932;1
"Building";"SporeCrawler";NA;952;0
"Building";"SporeCrawler";NA;952;0
"Building";"SporeCrawler";NA;952;0
"Building";"SporeCrawler";NA;952;0
"Building";"SporeCrawler";NA;952;0
"Building";"SporeCrawler";NA;952;0
"Building";"SporeCrawler";NA;952;0
"Building";"SporeCrawler";NA;952;0
"Building";"SporeCrawler";NA;952;0
"Building";"SporeCrawler";NA;952;0
"Building";"SporeCrawler";NA;952;0
"Building";"SporeCrawler";NA;952;0
"Building";"SporeCrawler";NA;952;0
"Building";"SporeCrawler";NA;952;0
"Building";"SporeCrawler";NA;952;0
"Unit";"Queen";"Hatchery";952;2
"Unit";"Queen";"Hatchery";952;2
"Unit";"Queen";"Hatchery";952;2
"Building";"Hatchery";NA;952;0
"Unit";"Hydralisk";"Larva";958;2
"Unit";"Hydralisk";"Larva";958;2
"Unit";"Hydralisk";"Larva";958;2
"Unit";"Hydralisk";"Larva";958;2
"Unit";"Hydralisk";"Larva";958;2
"Unit";"Hydralisk";"Larva";958;2
"Unit";"Hydralisk";"Larva";958;2
"Unit";"Hydralisk";"Larva";958;2
"Unit";"Hydralisk";"Larva";958;2
"Unit";"Hydralisk";"Larva";958;2
"Unit";"Corruptor";"Larva";958;2
"Unit";"Corruptor";"Larva";958;2
"Unit";"Corruptor";"Larva";958;2
"Unit";"Corruptor";"Larva";958;2
"Unit";"Corruptor";"Larva";958;2
"Unit";"Corruptor";"Larva";958;2
"Unit";"Overlord";"Larva";990;0
"Unit";"Overlord";"Larva";990;0
"Unit";"Overlord";"Larva";990;0
"Unit";"Hydralisk";"Larva";990;2
"Unit";"Hydralisk";"Larva";990;2
"Unit";"Hydralisk";"Larva";990;2
"Unit";"Hydralisk";"Larva";990;2
"Unit";"Hydralisk";"Larva";990;2
"Unit";"Hydralisk";"Larva";990;2
"Unit";"Hydralisk";"Larva";990;2
"Unit";"Hydralisk";"Larva";990;2
"Unit";"Hydralisk";"Larva";990;2
"Unit";"Hydralisk";"Larva";990;2
"Unit";"Hydralisk";"Larva";990;2
"Unit";"Hydralisk";"Larva";990;2
"Unit";"Hydralisk";"Larva";990;2
"Unit";"Hydralisk";"Larva";990;2
"Unit";"Hydralisk";"Larva";990;2
"Unit";"Hydralisk";"Larva";990;2
"Unit";"Hydralisk";"Larva";1022;2
"Unit";"Hydralisk";"Larva";1022;2
"Unit";"Hydralisk";"Larva";1022;2
"Unit";"Hydralisk";"Larva";1022;2
"Unit";"Hydralisk";"Larva";1022;2
"Unit";"Hydralisk";"Larva";1022;2
"Unit";"Hydralisk";"Larva";1022;2
"Unit";"Hydralisk";"Larva";1022;2
"Unit";"Hydralisk";"Larva";1022;2
"Unit";"Hydralisk";"Larva";1022;2
"Unit";"Hydralisk";"Larva";1022;2
"Unit";"Queen";"Hatchery";1022;2
"Unit";"Queen";"Hatchery";1022;2
"Unit";"Queen";"Hatchery";1022;2
"Unit";"Zergling";"Larva";1044;1
"Unit";"Zergling";"Larva";1044;1
"Unit";"Zergling";"Larva";1044;1
"Unit";"Zergling";"Larva";1044;1
"Unit";"Zergling";"Larva";1044;1
"Unit";"Zergling";"Larva";1044;1
"Unit";"Zergling";"Larva";1044;1
"Unit";"Zergling";"Larva";1044;1
"Unit";"Zergling";"Larva";1044;1
"Unit";"Zergling";"Larva";1044;1
"Unit";"Zergling";"Larva";1044;1
"Unit";"Zergling";"Larva";1044;1
"Unit";"Corruptor";"Larva";1062;2
"Unit";"Corruptor";"Larva";1062;2
"Unit";"Corruptor";"Larva";1062;2
"Unit";"Corruptor";"Larva";1062;2
"Building";"CreepTumor";NA;1070;0
"Unit";"Hydralisk";"Larva";1070;2
"Unit";"Hydralisk";"Larva";1070;2
"Unit";"Hydralisk";"Larva";1070;2
"Unit";"Hydralisk";"Larva";1070;2
"Unit";"Hydralisk";"Larva";1070;2
"Unit";"Hydralisk";"Larva";1070;2
"Unit";"Hydralisk";"Larva";1070;2
"Unit";"Queen";"Hatchery";1070;2
"Unit";"Queen";"Hatchery";1070;2
"Unit";"Queen";"Hatchery";1070;2
"Unit";"Queen";"Hatchery";1070;2
"Unit";"Queen";"Hatchery";1070;2
"Building";"CreepTumor";NA;1094;0
"Building";"CreepTumor";NA;1094;0
"Building";"CreepTumor";NA;1094;0
"Building";"CreepTumor";NA;1094;0
"Building";"CreepTumor";NA;1094;0
"Building";"CreepTumor";NA;1094;0
