"type";"unit_name";"on_building";"total_supply";"supply"
"Unit";"Overlord";"Larva";13;0
"Building";"Extractor";NA;17;0
"Building";"SpawningPool";NA;19;0
"Building";"Hatchery";NA;17;0
"Unit";"Overlord";"Larva";22;0
"Unit";"Zergling";"Larva";23;1
"Unit";"Zergling";"Larva";23;1
"Unit";"Zergling";"Larva";23;1
"Unit";"Zergling";"Larva";23;1
"Unit";"Queen";"Hatchery";23;2
"Unit";"Queen";"Hatchery";23;2
"Unit";"Overlord";"Larva";35;0
"Unit";"Queen";"Hatchery";35;2
"Building";"CreepTumorQueen";NA;44;0
"Unit";"Overlord";"Larva";44;0
"Unit";"Overlord";"Larva";44;0
"Unit";"Queen";"Hatchery";39;2
"Building";"CreepTumorQueen";NA;51;0
"Building";"CreepTumorQueen";NA;51;0
"Building";"Hatchery";NA;39;0
"Building";"Extractor";NA;50;0
"Building";"CreepTumor";NA;58;0
"Unit";"Overlord";"Larva";58;0
"Building";"BanelingNest";NA;50;0
"Unit";"Queen";"Hatchery";58;2
"Unit";"Queen";"Hatchery";58;2
"Building";"EvolutionChamber";NA;58;0
"Building";"EvolutionChamber";NA;58;0
"Unit";"Zergling";"Larva";69;1
"Unit";"Zergling";"Larva";69;1
"Unit";"Baneling";"Zergling";69;0
"Unit";"Baneling";"Zergling";69;0
"Building";"CreepTumor";NA;69;0
"Building";"CreepTumor";NA;69;0
"Unit";"Baneling";"Zergling";69;0
"Unit";"Zergling";"Larva";69;1
"Unit";"Zergling";"Larva";69;1
"Unit";"Zergling";"Larva";69;1
"Unit";"Zergling";"Larva";69;1
"Unit";"Zergling";"Larva";69;1
"Unit";"Zergling";"Larva";69;1
"Unit";"Zergling";"Larva";69;1
"Unit";"Zergling";"Larva";69;1
"Building";"CreepTumor";NA;69;0
"Unit";"Overlord";"Larva";69;0
"Building";"CreepTumorQueen";NA;69;0
"Unit";"Queen";"Hatchery";65;2
"Unit";"Queen";"Hatchery";67;2
"Unit";"Zergling";"Larva";71;1
"Unit";"Zergling";"Larva";71;1
"Unit";"Zergling";"Larva";71;1
"Unit";"Zergling";"Larva";71;1
"Unit";"Zergling";"Larva";71;1
"Unit";"Zergling";"Larva";71;1
"Unit";"Zergling";"Larva";73;1
"Unit";"Zergling";"Larva";73;1
"Unit";"Baneling";"Zergling";79;0
"Unit";"Baneling";"Zergling";79;0
"Unit";"Zergling";"Larva";77;1
"Unit";"Zergling";"Larva";77;1
"Unit";"Baneling";"Zergling";79;0
"Building";"CreepTumor";NA;79;0
"Building";"CreepTumor";NA;79;0
"Unit";"Overlord";"Larva";79;0
"Building";"CreepTumor";NA;93;0
"Building";"CreepTumor";NA;93;0
"Building";"Extractor";NA;93;0
"Building";"CreepTumorQueen";NA;108;0
"Unit";"Overlord";"Larva";108;0
"Unit";"Overlord";"Larva";108;0
"Unit";"Overlord";"Larva";108;0
"Building";"CreepTumorQueen";NA;108;0
"Building";"CreepTumorQueen";NA;108;0
"Unit";"Zergling";"Larva";108;1
"Unit";"Zergling";"Larva";108;1
"Unit";"Zergling";"Larva";108;1
"Unit";"Zergling";"Larva";108;1
"Unit";"Zergling";"Larva";108;1
"Unit";"Zergling";"Larva";108;1
"Building";"CreepTumor";NA;108;0
"Building";"CreepTumor";NA;114;0
"Unit";"Baneling";"Zergling";114;0
"Unit";"Baneling";"Zergling";114;0
"Unit";"Baneling";"Zergling";114;0
"Building";"Extractor";NA;114;0
"Building";"Extractor";NA;114;0
"Building";"Extractor";NA;114;0
"Building";"CreepTumor";NA;124;0
"Upgrade";"ZergMeleeWeaponsLevel1";"EvolutionChamber";93;0
"Unit";"Overlord";"Larva";124;0
"Unit";"Overlord";"Larva";124;0
"Upgrade";"ZergGroundArmorsLevel1";"EvolutionChamber";93;0
"Building";"SporeCrawler";NA;124;0
"Building";"SporeCrawler";NA;124;0
"Building";"SporeCrawler";NA;124;0
"Building";"CreepTumor";NA;133;0
"Unit";"Zergling";"Larva";133;1
"Unit";"Zergling";"Larva";133;1
"Unit";"Zergling";"Larva";133;1
"Unit";"Zergling";"Larva";133;1
"Unit";"Zergling";"Larva";133;1
"Unit";"Zergling";"Larva";133;1
"Unit";"Zergling";"Larva";133;1
"Unit";"Zergling";"Larva";133;1
"Unit";"Zergling";"Larva";133;1
"Unit";"Zergling";"Larva";133;1
"Unit";"Zergling";"Larva";133;1
"Unit";"Zergling";"Larva";133;1
"Unit";"Zergling";"Larva";133;1
"Unit";"Zergling";"Larva";133;1
"Unit";"Zergling";"Larva";133;1
"Unit";"Zergling";"Larva";133;1
"Unit";"Zergling";"Larva";133;1
"Unit";"Zergling";"Larva";133;1
"Building";"CreepTumor";NA;134;0
"Building";"CreepTumor";NA;134;0
"Building";"Hatchery";NA;114;0
"Unit";"Baneling";"Zergling";134;0
"Unit";"Baneling";"Zergling";134;0
"Unit";"Baneling";"Zergling";134;0
"Unit";"Baneling";"Zergling";134;0
"Unit";"Baneling";"Zergling";134;0
"Unit";"Baneling";"Zergling";134;0
"Building";"CreepTumor";NA;152;0
"Unit";"Overlord";"Larva";152;0
"Unit";"Overlord";"Larva";152;0
"Building";"Hatchery";NA;119;0
"Building";"CreepTumorQueen";NA;152;0
"Building";"CreepTumorQueen";NA;152;0
"Building";"CreepTumor";NA;152;0
"Unit";"Zergling";"Larva";152;1
"Unit";"Zergling";"Larva";152;1
"Unit";"Zergling";"Larva";152;1
"Unit";"Zergling";"Larva";152;1
"Unit";"Zergling";"Larva";152;1
"Unit";"Zergling";"Larva";152;1
"Unit";"Zergling";"Larva";152;1
"Unit";"Zergling";"Larva";152;1
"Unit";"Zergling";"Larva";152;1
"Unit";"Zergling";"Larva";152;1
"Unit";"Zergling";"Larva";152;1
"Unit";"Zergling";"Larva";152;1
"Unit";"Zergling";"Larva";152;1
"Unit";"Zergling";"Larva";152;1
"Building";"CreepTumorQueen";NA;152;0
"Building";"CreepTumorQueen";NA;152;0
"Unit";"Zergling";"Larva";152;1
"Unit";"Zergling";"Larva";152;1
"Unit";"Zergling";"Larva";152;1
"Unit";"Zergling";"Larva";152;1
"Unit";"Zergling";"Larva";152;1
"Unit";"Zergling";"Larva";152;1
"Unit";"Zergling";"Larva";152;1
"Unit";"Zergling";"Larva";152;1
"Unit";"Zergling";"Larva";152;1
"Unit";"Zergling";"Larva";152;1
"Unit";"Zergling";"Larva";152;1
"Unit";"Zergling";"Larva";152;1
"Unit";"Zergling";"Larva";152;1
"Unit";"Zergling";"Larva";152;1
"Unit";"Zergling";"Larva";152;1
"Unit";"Zergling";"Larva";152;1
"Building";"CreepTumorQueen";NA;154;0
"Building";"CreepTumorQueen";NA;166;0
"Unit";"Baneling";"Zergling";166;0
"Unit";"Baneling";"Zergling";166;0
"Unit";"Zergling";"Larva";166;1
"Unit";"Zergling";"Larva";166;1
"Unit";"Baneling";"Zergling";166;0
"Unit";"Baneling";"Zergling";166;0
"Unit";"Baneling";"Zergling";166;0
"Unit";"Baneling";"Zergling";166;0
"Unit";"Baneling";"Zergling";166;0
"Unit";"Baneling";"Zergling";166;0
"Unit";"Baneling";"Zergling";166;0
"Unit";"Baneling";"Zergling";166;0
"Unit";"Baneling";"Zergling";166;0
"Unit";"Baneling";"Zergling";166;0
"Unit";"Baneling";"Zergling";166;0
"Unit";"Baneling";"Zergling";166;0
"Unit";"Baneling";"Zergling";166;0
"Unit";"Baneling";"Zergling";166;0
"Unit";"Baneling";"Zergling";166;0
"Unit";"Zergling";"Larva";166;1
"Unit";"Zergling";"Larva";166;1
"Unit";"Baneling";"Zergling";166;0
"Unit";"Baneling";"Zergling";166;0
"Unit";"Zergling";"Larva";166;1
"Unit";"Zergling";"Larva";166;1
"Unit";"Zergling";"Larva";166;1
"Unit";"Zergling";"Larva";166;1
"Unit";"Baneling";"Zergling";166;0
"Unit";"Zergling";"Larva";166;1
"Unit";"Zergling";"Larva";166;1
"Unit";"Zergling";"Larva";166;1
"Unit";"Zergling";"Larva";166;1
"Unit";"Baneling";"Zergling";166;0
"Unit";"Baneling";"Zergling";166;0
"Unit";"Baneling";"Zergling";166;0
"Unit";"Baneling";"Zergling";166;0
"Unit";"Baneling";"Zergling";166;0
"Unit";"Baneling";"Zergling";166;0
"Unit";"Baneling";"Zergling";166;0
"Unit";"Baneling";"Zergling";166;0
"Unit";"Baneling";"Zergling";166;0
"Unit";"Baneling";"Zergling";166;0
"Unit";"Baneling";"Zergling";166;0
"Unit";"Baneling";"Zergling";166;0
"Unit";"Zergling";"Larva";182;1
"Unit";"Zergling";"Larva";182;1
"Unit";"Zergling";"Larva";182;1
"Unit";"Zergling";"Larva";182;1
"Unit";"Zergling";"Larva";182;1
"Unit";"Zergling";"Larva";182;1
"Unit";"Zergling";"Larva";182;1
"Unit";"Zergling";"Larva";182;1
"Unit";"Zergling";"Larva";182;1
"Unit";"Zergling";"Larva";182;1
"Unit";"Zergling";"Larva";182;1
"Unit";"Zergling";"Larva";182;1
"Unit";"Zergling";"Larva";182;1
"Unit";"Zergling";"Larva";182;1
"Unit";"Zergling";"Larva";182;1
"Unit";"Zergling";"Larva";182;1
"Unit";"Zergling";"Larva";182;1
"Unit";"Zergling";"Larva";182;1
"Unit";"Zergling";"Larva";182;1
"Unit";"Zergling";"Larva";182;1
"Unit";"Zergling";"Larva";182;1
"Unit";"Zergling";"Larva";182;1
"Unit";"Zergling";"Larva";194;1
"Unit";"Zergling";"Larva";194;1
"Unit";"Zergling";"Larva";194;1
"Unit";"Zergling";"Larva";194;1
"Unit";"Zergling";"Larva";194;1
"Unit";"Zergling";"Larva";194;1
"Unit";"Zergling";"Larva";194;1
"Unit";"Zergling";"Larva";194;1
"Unit";"Zergling";"Larva";194;1
"Unit";"Zergling";"Larva";194;1
"Unit";"Zergling";"Larva";194;1
"Unit";"Zergling";"Larva";194;1
"Unit";"Zergling";"Larva";194;1
"Unit";"Zergling";"Larva";194;1
"Building";"CreepTumor";NA;194;0
"Building";"CreepTumorQueen";NA;216;0
"Building";"CreepTumorQueen";NA;216;0
"Building";"CreepTumorQueen";NA;216;0
"Unit";"Zergling";"Larva";216;1
"Unit";"Zergling";"Larva";216;1
"Unit";"Zergling";"Larva";216;1
"Unit";"Zergling";"Larva";216;1
"Unit";"Zergling";"Larva";216;1
"Unit";"Zergling";"Larva";216;1
"Unit";"Zergling";"Larva";216;1
"Unit";"Zergling";"Larva";216;1
"Unit";"Zergling";"Larva";216;1
"Unit";"Zergling";"Larva";216;1
"Unit";"Zergling";"Larva";216;1
"Unit";"Zergling";"Larva";216;1
"Unit";"Zergling";"Larva";216;1
"Unit";"Zergling";"Larva";216;1
"Unit";"Zergling";"Larva";216;1
"Unit";"Zergling";"Larva";216;1
"Unit";"Zergling";"Larva";216;1
"Unit";"Zergling";"Larva";216;1
"Unit";"Zergling";"Larva";216;1
"Unit";"Zergling";"Larva";216;1
"Unit";"Baneling";"Zergling";230;0
"Unit";"Baneling";"Zergling";230;0
"Unit";"Baneling";"Zergling";230;0
"Unit";"Baneling";"Zergling";230;0
"Unit";"Baneling";"Zergling";230;0
"Unit";"Baneling";"Zergling";230;0
"Unit";"Baneling";"Zergling";230;0
"Unit";"Baneling";"Zergling";230;0
"Unit";"Baneling";"Zergling";230;0
"Unit";"Baneling";"Zergling";230;0
"Unit";"Baneling";"Zergling";230;0
"Unit";"Baneling";"Zergling";230;0
"Unit";"Baneling";"Zergling";230;0
"Unit";"Baneling";"Zergling";230;0
"Unit";"Baneling";"Zergling";230;0
"Unit";"Baneling";"Zergling";230;0
"Unit";"Baneling";"Zergling";230;0
"Building";"HydraliskDen";NA;216;0
"Unit";"Zergling";"Larva";230;1
"Unit";"Zergling";"Larva";230;1
"Unit";"Zergling";"Larva";230;1
"Unit";"Zergling";"Larva";230;1
"Unit";"Zergling";"Larva";230;1
"Unit";"Zergling";"Larva";230;1
"Unit";"Zergling";"Larva";230;1
"Unit";"Zergling";"Larva";230;1
"Unit";"Zergling";"Larva";230;1
"Unit";"Zergling";"Larva";230;1
"Unit";"Zergling";"Larva";230;1
"Unit";"Zergling";"Larva";230;1
"Unit";"Zergling";"Larva";230;1
"Unit";"Zergling";"Larva";230;1
"Unit";"Zergling";"Larva";230;1
"Unit";"Zergling";"Larva";230;1
"Unit";"Zergling";"Larva";230;1
"Unit";"Zergling";"Larva";230;1
"Unit";"Zergling";"Larva";230;1
"Unit";"Zergling";"Larva";230;1
"Unit";"Zergling";"Larva";230;1
"Unit";"Zergling";"Larva";230;1
"Unit";"Baneling";"Zergling";250;0
"Unit";"Baneling";"Zergling";250;0
"Unit";"Baneling";"Zergling";250;0
"Unit";"Baneling";"Zergling";250;0
"Unit";"Baneling";"Zergling";250;0
"Unit";"Baneling";"Zergling";250;0
"Unit";"Baneling";"Zergling";250;0
"Unit";"Baneling";"Zergling";250;0
"Unit";"Baneling";"Zergling";250;0
"Unit";"Baneling";"Zergling";250;0
"Unit";"Baneling";"Zergling";250;0
"Unit";"Baneling";"Zergling";250;0
"Unit";"Baneling";"Zergling";250;0
"Unit";"Baneling";"Zergling";250;0
"Unit";"Baneling";"Zergling";250;0
"Unit";"Baneling";"Zergling";250;0
"Unit";"Zergling";"Larva";250;1
"Unit";"Zergling";"Larva";250;1
"Unit";"Zergling";"Larva";250;1
"Unit";"Zergling";"Larva";250;1
"Unit";"Zergling";"Larva";250;1
"Unit";"Zergling";"Larva";250;1
"Unit";"Zergling";"Larva";250;1
"Unit";"Zergling";"Larva";250;1
"Unit";"Zergling";"Larva";250;1
"Unit";"Zergling";"Larva";250;1
"Unit";"Zergling";"Larva";250;1
"Unit";"Zergling";"Larva";250;1
"Upgrade";"ZergMeleeWeaponsLevel2";"EvolutionChamber";166;0
"Upgrade";"ZergGroundArmorsLevel2";"EvolutionChamber";166;0
"Unit";"Hydralisk";"Larva";272;2
"Unit";"Hydralisk";"Larva";272;2
"Unit";"Hydralisk";"Larva";272;2
"Unit";"Hydralisk";"Larva";272;2
"Unit";"Hydralisk";"Larva";272;2
"Building";"CreepTumorQueen";NA;284;0
"Building";"CreepTumor";NA;284;0
"Building";"CreepTumorQueen";NA;284;0
"Building";"CreepTumor";NA;284;0
"Building";"CreepTumor";NA;284;0
"Building";"CreepTumor";NA;284;0
"Building";"CreepTumor";NA;284;0
"Building";"CreepTumor";NA;284;0
"Building";"CreepTumor";NA;284;0
"Building";"CreepTumorQueen";NA;294;0
"Building";"CreepTumorQueen";NA;294;0
"Building";"CreepTumor";NA;294;0
"Building";"CreepTumorQueen";NA;294;0
"Building";"CreepTumorQueen";NA;294;0
"Unit";"Overlord";"Larva";294;0
"Unit";"Overlord";"Larva";294;0
"Unit";"Overlord";"Larva";294;0
"Unit";"Overlord";"Larva";294;0
"Building";"Extractor";NA;294;0
"Building";"Extractor";NA;294;0
"Building";"CreepTumor";NA;300;0
"Building";"CreepTumor";NA;304;0
"Building";"CreepTumor";NA;304;0
"Unit";"Hydralisk";"Larva";294;2
"Unit";"Hydralisk";"Larva";294;2
"Unit";"Hydralisk";"Larva";294;2
"Unit";"Hydralisk";"Larva";294;2
"Unit";"Hydralisk";"Larva";294;2
"Building";"CreepTumor";NA;304;0
"Building";"CreepTumor";NA;304;0
"Building";"CreepTumor";NA;304;0
"Building";"CreepTumor";NA;304;0
"Building";"InfestationPit";NA;294;0
"Upgrade";"EvolveGroovedSpines";"HydraliskDen";286;0
"Building";"CreepTumor";NA;314;0
"Building";"CreepTumor";NA;314;0
"Building";"CreepTumor";NA;314;0
"Unit";"Hydralisk";"Larva";314;2
"Unit";"Hydralisk";"Larva";314;2
"Unit";"Hydralisk";"Larva";314;2
"Unit";"Hydralisk";"Larva";314;2
"Unit";"Hydralisk";"Larva";314;2
"Unit";"Hydralisk";"Larva";314;2
"Unit";"Hydralisk";"Larva";314;2
"Unit";"Hydralisk";"Larva";314;2
"Unit";"Hydralisk";"Larva";314;2
"Unit";"Hydralisk";"Larva";314;2
"Unit";"Hydralisk";"Larva";314;2
"Unit";"Hydralisk";"Larva";314;2
"Unit";"Hydralisk";"Larva";314;2
"Unit";"Hydralisk";"Larva";314;2
"Unit";"Hydralisk";"Larva";314;2
"Unit";"Hydralisk";"Larva";314;2
"Unit";"Hydralisk";"Larva";314;2
"Unit";"Zergling";"Larva";314;1
"Unit";"Zergling";"Larva";314;1
"Unit";"Zergling";"Larva";314;1
"Unit";"Zergling";"Larva";314;1
"Unit";"Zergling";"Larva";314;1
"Unit";"Zergling";"Larva";314;1
"Unit";"Zergling";"Larva";314;1
"Unit";"Zergling";"Larva";314;1
"Unit";"Zergling";"Larva";314;1
"Unit";"Zergling";"Larva";314;1
"Unit";"Zergling";"Larva";314;1
"Unit";"Zergling";"Larva";314;1
"Unit";"Zergling";"Larva";314;1
"Unit";"Zergling";"Larva";314;1
"Unit";"Zergling";"Larva";314;1
"Unit";"Zergling";"Larva";314;1
"Unit";"Zergling";"Larva";314;1
"Unit";"Zergling";"Larva";314;1
"Unit";"Zergling";"Larva";314;1
"Unit";"Zergling";"Larva";314;1
"Unit";"Zergling";"Larva";314;1
"Unit";"Zergling";"Larva";314;1
"Unit";"Zergling";"Larva";314;1
"Unit";"Zergling";"Larva";314;1
"Unit";"Zergling";"Larva";314;1
"Unit";"Zergling";"Larva";314;1
"Unit";"Zergling";"Larva";314;1
"Unit";"Zergling";"Larva";314;1
"Building";"CreepTumor";NA;314;0
"Building";"CreepTumor";NA;314;0
"Building";"CreepTumor";NA;314;0
"Building";"CreepTumor";NA;314;0
"Building";"CreepTumor";NA;314;0
"Building";"CreepTumor";NA;314;0
"Building";"CreepTumor";NA;320;0
"Building";"CreepTumor";NA;332;0
"Building";"CreepTumor";NA;376;0
"Building";"CreepTumor";NA;376;0
"Building";"CreepTumor";NA;376;0
"Building";"CreepTumor";NA;376;0
"Unit";"Baneling";"Zergling";376;0
"Unit";"Baneling";"Zergling";376;0
"Unit";"Baneling";"Zergling";376;0
"Unit";"Baneling";"Zergling";376;0
"Unit";"Baneling";"Zergling";376;0
"Unit";"Baneling";"Zergling";376;0
"Unit";"Baneling";"Zergling";376;0
"Unit";"Baneling";"Zergling";376;0
"Unit";"Baneling";"Zergling";376;0
"Unit";"Baneling";"Zergling";376;0
"Unit";"Baneling";"Zergling";376;0
"Unit";"Baneling";"Zergling";376;0
"Unit";"Baneling";"Zergling";376;0
"Unit";"Baneling";"Zergling";376;0
"Unit";"Baneling";"Zergling";376;0
"Unit";"Baneling";"Zergling";376;0
"Unit";"Baneling";"Zergling";376;0
"Unit";"Baneling";"Zergling";376;0
"Unit";"Zergling";"Larva";376;1
"Unit";"Zergling";"Larva";376;1
"Unit";"Zergling";"Larva";376;1
"Unit";"Zergling";"Larva";376;1
"Unit";"Zergling";"Larva";376;1
"Unit";"Zergling";"Larva";376;1
"Unit";"Zergling";"Larva";376;1
"Unit";"Zergling";"Larva";376;1
"Unit";"Zergling";"Larva";376;1
"Unit";"Zergling";"Larva";376;1
"Unit";"Zergling";"Larva";376;1
"Unit";"Zergling";"Larva";376;1
"Unit";"Zergling";"Larva";376;1
"Unit";"Zergling";"Larva";376;1
"Unit";"Zergling";"Larva";376;1
"Unit";"Zergling";"Larva";376;1
"Unit";"Zergling";"Larva";376;1
"Unit";"Zergling";"Larva";376;1
"Unit";"Zergling";"Larva";376;1
"Unit";"Zergling";"Larva";376;1
"Unit";"Zergling";"Larva";376;1
"Unit";"Zergling";"Larva";376;1
"Unit";"Zergling";"Larva";376;1
"Unit";"Zergling";"Larva";376;1
"Unit";"Zergling";"Larva";376;1
"Unit";"Zergling";"Larva";376;1
"Unit";"Zergling";"Larva";376;1
"Unit";"Zergling";"Larva";376;1
"Unit";"Zergling";"Larva";376;1
"Unit";"Zergling";"Larva";376;1
"Upgrade";"ZergMissileWeaponsLevel1";"EvolutionChamber";314;0
"Unit";"Zergling";"Larva";406;1
"Unit";"Zergling";"Larva";406;1
"Unit";"Zergling";"Larva";406;1
"Unit";"Zergling";"Larva";406;1
"Unit";"Zergling";"Larva";406;1
"Unit";"Zergling";"Larva";406;1
"Unit";"Zergling";"Larva";406;1
"Unit";"Zergling";"Larva";406;1
"Unit";"Zergling";"Larva";406;1
"Unit";"Zergling";"Larva";406;1
"Unit";"Zergling";"Larva";406;1
"Unit";"Zergling";"Larva";406;1
"Unit";"Zergling";"Larva";406;1
"Unit";"Zergling";"Larva";406;1
"Unit";"Zergling";"Larva";406;1
"Unit";"Zergling";"Larva";406;1
"Unit";"Zergling";"Larva";406;1
"Unit";"Zergling";"Larva";406;1
"Unit";"Zergling";"Larva";406;1
"Unit";"Zergling";"Larva";406;1
"Unit";"Zergling";"Larva";406;1
"Unit";"Zergling";"Larva";406;1
"Unit";"Zergling";"Larva";406;1
"Unit";"Zergling";"Larva";406;1
"Unit";"Zergling";"Larva";406;1
"Unit";"Zergling";"Larva";406;1
"Building";"CreepTumor";NA;406;0
"Unit";"Baneling";"Zergling";406;0
"Unit";"Baneling";"Zergling";406;0
"Unit";"Baneling";"Zergling";406;0
"Unit";"Baneling";"Zergling";406;0
"Unit";"Baneling";"Zergling";406;0
"Building";"CreepTumor";NA;406;0
"Unit";"Zergling";"Larva";406;1
"Unit";"Zergling";"Larva";406;1
"Unit";"Zergling";"Larva";406;1
"Unit";"Zergling";"Larva";406;1
"Unit";"Zergling";"Larva";406;1
"Unit";"Zergling";"Larva";406;1
"Unit";"Zergling";"Larva";406;1
"Unit";"Zergling";"Larva";406;1
"Unit";"Zergling";"Larva";406;1
"Unit";"Zergling";"Larva";406;1
"Unit";"Zergling";"Larva";406;1
"Unit";"Zergling";"Larva";406;1
"Unit";"Zergling";"Larva";406;1
"Unit";"Zergling";"Larva";406;1
"Unit";"Zergling";"Larva";406;1
"Unit";"Zergling";"Larva";406;1
"Unit";"Zergling";"Larva";406;1
"Unit";"Zergling";"Larva";406;1
"Unit";"Zergling";"Larva";406;1
"Unit";"Zergling";"Larva";406;1
"Unit";"Zergling";"Larva";406;1
"Unit";"Zergling";"Larva";406;1
"Unit";"Zergling";"Larva";406;1
"Unit";"Zergling";"Larva";406;1
"Unit";"Zergling";"Larva";406;1
"Unit";"Zergling";"Larva";406;1
"Unit";"Zergling";"Larva";406;1
"Unit";"Zergling";"Larva";406;1
"Unit";"Zergling";"Larva";406;1
"Unit";"Zergling";"Larva";406;1
"Unit";"Zergling";"Larva";406;1
"Unit";"Zergling";"Larva";406;1
"Building";"Hatchery";NA;348;0
"Unit";"Hydralisk";"Larva";464;2
"Unit";"Hydralisk";"Larva";464;2
"Unit";"Hydralisk";"Larva";464;2
"Unit";"Hydralisk";"Larva";464;2
"Unit";"Hydralisk";"Larva";464;2
"Unit";"Hydralisk";"Larva";464;2
"Unit";"Hydralisk";"Larva";464;2
"Unit";"Baneling";"Zergling";464;0
"Unit";"Baneling";"Zergling";464;0
"Unit";"Baneling";"Zergling";464;0
"Unit";"Baneling";"Zergling";464;0
"Unit";"Baneling";"Zergling";464;0
"Unit";"Baneling";"Zergling";464;0
"Unit";"Baneling";"Zergling";464;0
"Unit";"Baneling";"Zergling";464;0
"Unit";"Baneling";"Zergling";464;0
"Unit";"Baneling";"Zergling";464;0
"Unit";"Baneling";"Zergling";464;0
"Unit";"Hydralisk";"Larva";464;2
"Unit";"Hydralisk";"Larva";464;2
"Unit";"Hydralisk";"Larva";464;2
"Unit";"Hydralisk";"Larva";464;2
"Unit";"Hydralisk";"Larva";464;2
"Building";"CreepTumor";NA;478;0
"Unit";"Hydralisk";"Larva";478;2
"Unit";"Hydralisk";"Larva";478;2
"Unit";"Hydralisk";"Larva";478;2
"Unit";"Hydralisk";"Larva";478;2
"Unit";"Hydralisk";"Larva";478;2
"Unit";"Hydralisk";"Larva";478;2
"Building";"CreepTumor";NA;488;0
"Unit";"Overlord";"Larva";488;0
"Unit";"Overlord";"Larva";488;0
"Building";"CreepTumor";NA;488;0
"Building";"CreepTumor";NA;488;0
"Building";"CreepTumor";NA;488;0
"Building";"CreepTumor";NA;491;0
"Unit";"Baneling";"Zergling";504;0
"Unit";"Baneling";"Zergling";504;0
"Unit";"Baneling";"Zergling";504;0
"Unit";"Baneling";"Zergling";504;0
"Unit";"Baneling";"Zergling";504;0
"Building";"CreepTumorQueen";NA;504;0
"Building";"CreepTumorQueen";NA;504;0
"Building";"CreepTumorQueen";NA;504;0
"Building";"CreepTumorQueen";NA;504;0
"Building";"CreepTumorQueen";NA;504;0
"Building";"CreepTumorQueen";NA;504;0
"Unit";"Zergling";"Larva";504;1
"Unit";"Zergling";"Larva";504;1
"Unit";"Zergling";"Larva";504;1
"Unit";"Zergling";"Larva";504;1
"Unit";"Zergling";"Larva";504;1
"Unit";"Zergling";"Larva";504;1
"Unit";"Zergling";"Larva";504;1
"Unit";"Zergling";"Larva";504;1
"Unit";"Zergling";"Larva";504;1
"Unit";"Zergling";"Larva";504;1
"Unit";"Zergling";"Larva";504;1
"Unit";"Zergling";"Larva";504;1
"Unit";"Zergling";"Larva";504;1
"Unit";"Zergling";"Larva";504;1
"Unit";"Zergling";"Larva";504;1
"Unit";"Zergling";"Larva";504;1
"Unit";"Zergling";"Larva";504;1
"Unit";"Zergling";"Larva";504;1
"Unit";"Zergling";"Larva";504;1
"Unit";"Zergling";"Larva";504;1
"Unit";"Zergling";"Larva";504;1
"Unit";"Zergling";"Larva";504;1
"Unit";"Zergling";"Larva";504;1
"Unit";"Zergling";"Larva";504;1
"Unit";"Zergling";"Larva";504;1
"Unit";"Zergling";"Larva";504;1
"Unit";"Zergling";"Larva";504;1
"Unit";"Zergling";"Larva";504;1
"Unit";"Zergling";"Larva";504;1
"Unit";"Zergling";"Larva";504;1
"Unit";"Zergling";"Larva";504;1
"Unit";"Zergling";"Larva";504;1
"Unit";"Zergling";"Larva";504;1
"Unit";"Zergling";"Larva";504;1
"Unit";"Zergling";"Larva";504;1
"Unit";"Zergling";"Larva";504;1
"Unit";"Zergling";"Larva";504;1
"Unit";"Zergling";"Larva";504;1
"Unit";"Zergling";"Larva";504;1
"Unit";"Zergling";"Larva";504;1
"Unit";"Zergling";"Larva";504;1
"Unit";"Zergling";"Larva";504;1
"Unit";"Zergling";"Larva";504;1
"Unit";"Zergling";"Larva";504;1
"Unit";"Zergling";"Larva";504;1
"Unit";"Zergling";"Larva";504;1
"Unit";"Zergling";"Larva";504;1
"Unit";"Zergling";"Larva";504;1
"Unit";"Zergling";"Larva";504;1
"Unit";"Zergling";"Larva";504;1
"Unit";"Zergling";"Larva";504;1
"Unit";"Zergling";"Larva";504;1
"Unit";"Baneling";"Zergling";556;0
"Unit";"Baneling";"Zergling";556;0
"Unit";"Baneling";"Zergling";556;0
"Unit";"Baneling";"Zergling";556;0
"Unit";"Baneling";"Zergling";556;0
"Unit";"Baneling";"Zergling";556;0
"Unit";"Baneling";"Zergling";556;0
"Unit";"Baneling";"Zergling";556;0
"Unit";"Baneling";"Zergling";556;0
"Unit";"Baneling";"Zergling";556;0
"Building";"CreepTumor";NA;556;0
"Building";"CreepTumorQueen";NA;556;0
"Unit";"Hydralisk";"Larva";556;2
"Building";"CreepTumor";NA;556;0
"Unit";"Hydralisk";"Larva";556;2
"Unit";"Hydralisk";"Larva";556;2
"Building";"CreepTumor";NA;556;0
"Unit";"Hydralisk";"Larva";556;2
"Unit";"Hydralisk";"Larva";556;2
"Unit";"Hydralisk";"Larva";556;2
"Unit";"Hydralisk";"Larva";556;2
"Unit";"Hydralisk";"Larva";556;2
"Unit";"Hydralisk";"Larva";556;2
"Unit";"Hydralisk";"Larva";556;2
"Building";"CreepTumor";NA;556;0
"Building";"CreepTumor";NA;556;0
"Building";"CreepTumorQueen";NA;556;0
"Upgrade";"EvolveMuscularAugments";"HydraliskDen";504;0
"Building";"CreepTumor";NA;576;0
"Building";"CreepTumor";NA;576;0
"Building";"CreepTumor";NA;576;0
"Building";"CreepTumor";NA;576;0
"Building";"CreepTumor";NA;576;0
"Building";"CreepTumor";NA;576;0
"Building";"CreepTumorQueen";NA;576;0
"Building";"CreepTumor";NA;576;0
"Building";"CreepTumor";NA;576;0
"Unit";"Hydralisk";"Larva";576;2
"Unit";"Hydralisk";"Larva";576;2
"Unit";"Hydralisk";"Larva";576;2
"Unit";"Hydralisk";"Larva";576;2
"Unit";"Hydralisk";"Larva";576;2
"Unit";"Hydralisk";"Larva";576;2
"Unit";"Hydralisk";"Larva";576;2
"Unit";"Hydralisk";"Larva";576;2
"Unit";"Hydralisk";"Larva";576;2
"Unit";"Hydralisk";"Larva";576;2
"Unit";"Hydralisk";"Larva";576;2
"Unit";"Hydralisk";"Larva";576;2
"Unit";"Hydralisk";"Larva";576;2
"Unit";"Hydralisk";"Larva";576;2
"Building";"CreepTumor";NA;576;0
"Building";"CreepTumor";NA;576;0
"Unit";"Baneling";"Zergling";576;0
"Unit";"Baneling";"Zergling";576;0
"Unit";"Baneling";"Zergling";576;0
"Unit";"Baneling";"Zergling";576;0
"Unit";"Baneling";"Zergling";576;0
"Unit";"Baneling";"Zergling";576;0
"Unit";"Baneling";"Zergling";576;0
"Unit";"Baneling";"Zergling";576;0
"Unit";"Baneling";"Zergling";576;0
"Unit";"Baneling";"Zergling";576;0
"Unit";"Baneling";"Zergling";576;0
"Unit";"Baneling";"Zergling";576;0
"Unit";"Baneling";"Zergling";576;0
"Unit";"Baneling";"Zergling";576;0
"Unit";"Baneling";"Zergling";576;0
"Unit";"Baneling";"Zergling";576;0
"Unit";"Baneling";"Zergling";576;0
"Unit";"Baneling";"Zergling";576;0
"Unit";"Baneling";"Zergling";576;0
"Unit";"Baneling";"Zergling";576;0
"Unit";"Baneling";"Zergling";576;0
"Unit";"Baneling";"Zergling";576;0
"Unit";"Baneling";"Zergling";576;0
"Unit";"Baneling";"Zergling";576;0
"Unit";"Baneling";"Zergling";576;0
"Unit";"Baneling";"Zergling";576;0
"Unit";"Baneling";"Zergling";576;0
"Unit";"Baneling";"Zergling";576;0
"Unit";"Baneling";"Zergling";576;0
"Unit";"Baneling";"Zergling";576;0
"Unit";"Baneling";"Zergling";576;0
"Upgrade";"ZergMissileWeaponsLevel2";"EvolutionChamber";504;0
"Building";"UltraliskCavern";NA;576;0
"Unit";"Zergling";"Larva";604;1
"Unit";"Zergling";"Larva";604;1
"Unit";"Zergling";"Larva";604;1
"Unit";"Zergling";"Larva";604;1
"Unit";"Zergling";"Larva";604;1
"Unit";"Zergling";"Larva";604;1
"Unit";"Zergling";"Larva";604;1
"Unit";"Zergling";"Larva";604;1
"Unit";"Zergling";"Larva";604;1
"Unit";"Zergling";"Larva";604;1
"Unit";"Zergling";"Larva";604;1
"Unit";"Zergling";"Larva";604;1
"Unit";"Zergling";"Larva";604;1
"Unit";"Zergling";"Larva";604;1
"Unit";"Zergling";"Larva";604;1
"Unit";"Zergling";"Larva";604;1
"Unit";"Zergling";"Larva";604;1
"Unit";"Zergling";"Larva";604;1
"Unit";"Zergling";"Larva";604;1
"Unit";"Zergling";"Larva";604;1
"Unit";"Zergling";"Larva";604;1
"Unit";"Zergling";"Larva";604;1
"Unit";"Zergling";"Larva";604;1
"Unit";"Zergling";"Larva";604;1
"Building";"CreepTumor";NA;604;0
"Building";"CreepTumor";NA;628;0
"Unit";"Zergling";"Larva";604;1
"Unit";"Zergling";"Larva";604;1
"Unit";"Zergling";"Larva";604;1
"Unit";"Zergling";"Larva";604;1
"Unit";"Zergling";"Larva";604;1
"Unit";"Zergling";"Larva";604;1
"Unit";"Zergling";"Larva";604;1
"Unit";"Zergling";"Larva";604;1
"Unit";"Zergling";"Larva";604;1
"Unit";"Zergling";"Larva";604;1
"Unit";"Zergling";"Larva";604;1
"Unit";"Zergling";"Larva";604;1
"Unit";"Zergling";"Larva";604;1
"Unit";"Zergling";"Larva";604;1
"Unit";"Zergling";"Larva";604;1
"Unit";"Zergling";"Larva";604;1
"Unit";"Zergling";"Larva";604;1
"Unit";"Zergling";"Larva";604;1
"Unit";"Zergling";"Larva";604;1
"Unit";"Zergling";"Larva";604;1
"Unit";"Zergling";"Larva";604;1
"Unit";"Zergling";"Larva";604;1
"Unit";"Zergling";"Larva";604;1
"Unit";"Zergling";"Larva";604;1
"Unit";"Zergling";"Larva";604;1
"Unit";"Zergling";"Larva";604;1
"Unit";"Zergling";"Larva";604;1
"Unit";"Zergling";"Larva";604;1
"Unit";"Zergling";"Larva";604;1
"Unit";"Zergling";"Larva";604;1
"Unit";"Zergling";"Larva";604;1
"Unit";"Zergling";"Larva";604;1
"Upgrade";"ZergMeleeWeaponsLevel3";"EvolutionChamber";576;0
