"type";"unit_name";"on_building";"total_supply";"supply"
"Unit";"Overlord";"Larva";12;0
"Building";"Extractor";NA;18;0
"Building";"SpawningPool";NA;19;0
"Building";"Hatchery";NA;17;0
"Unit";"Overlord";"Larva";22;0
"Unit";"Zergling";"Larva";23;1
"Unit";"Zergling";"Larva";23;1
"Unit";"Zergling";"Larva";23;1
"Unit";"Zergling";"Larva";23;1
"Unit";"Queen";"Hatchery";23;2
"Unit";"Queen";"Hatchery";23;2
"Unit";"Overlord";"Larva";36;0
"Unit";"Queen";"Hatchery";36;2
"Building";"Extractor";NA;37;0
"Building";"CreepTumorQueen";NA;40;0
"Unit";"Overlord";"Larva";39;0
"Unit";"Zergling";"Larva";50;1
"Unit";"Zergling";"Larva";50;1
"Building";"CreepTumor";NA;50;0
"Unit";"Zergling";"Larva";50;1
"Unit";"Zergling";"Larva";50;1
"Unit";"Zergling";"Larva";50;1
"Unit";"Zergling";"Larva";50;1
"Building";"CreepTumorQueen";NA;50;0
"Unit";"Zergling";"Larva";50;1
"Unit";"Zergling";"Larva";50;1
"Building";"Extractor";NA;50;0
"Building";"Extractor";NA;50;0
"Unit";"Overlord";"Larva";50;0
"Building";"CreepTumor";NA;63;0
"Building";"CreepTumor";NA;64;0
"Unit";"Overlord";"Larva";64;0
"Unit";"Overlord";"Larva";66;0
"Building";"CreepTumorQueen";NA;71;0
"Building";"Spire";NA;50;0
"Building";"SporeCrawler";NA;71;0
"Unit";"Overlord";"Larva";71;0
"Building";"SporeCrawler";NA;71;0
"Building";"Hatchery";NA;50;0
"Unit";"Zergling";"Larva";72;1
"Unit";"Zergling";"Larva";72;1
"Unit";"Zergling";"Larva";72;1
"Unit";"Zergling";"Larva";72;1
"Unit";"Zergling";"Larva";72;1
"Unit";"Zergling";"Larva";72;1
"Unit";"Mutalisk";"Larva";72;2
"Unit";"Mutalisk";"Larva";72;2
"Unit";"Mutalisk";"Larva";72;2
"Unit";"Mutalisk";"Larva";72;2
"Unit";"Mutalisk";"Larva";72;2
"Unit";"Mutalisk";"Larva";91;2
"Unit";"Mutalisk";"Larva";92;2
"Unit";"Mutalisk";"Larva";94;2
"Unit";"Mutalisk";"Larva";94;2
"Building";"CreepTumor";NA;103;0
"Building";"SporeCrawler";NA;114;0
"Building";"EvolutionChamber";NA;117;0
"Building";"EvolutionChamber";NA;117;0
"Building";"BanelingNest";NA;117;0
"Unit";"Overlord";"Larva";136;0
"Building";"Extractor";NA;136;0
"Building";"Extractor";NA;136;0
"Unit";"Overlord";"Larva";137;0
"Unit";"Overlord";"Larva";142;0
"Unit";"Overlord";"Larva";142;0
"Building";"InfestationPit";NA;136;0
"Unit";"Zergling";"Larva";146;1
"Unit";"Zergling";"Larva";146;1
"Unit";"Zergling";"Larva";146;1
"Unit";"Zergling";"Larva";146;1
"Unit";"Zergling";"Larva";146;1
"Unit";"Zergling";"Larva";146;1
"Unit";"Zergling";"Larva";146;1
"Unit";"Zergling";"Larva";146;1
"Unit";"Zergling";"Larva";146;1
"Unit";"Zergling";"Larva";146;1
"Unit";"Zergling";"Larva";146;1
"Unit";"Zergling";"Larva";146;1
"Unit";"Zergling";"Larva";146;1
"Unit";"Zergling";"Larva";146;1
"Unit";"Zergling";"Larva";146;1
"Unit";"Zergling";"Larva";146;1
"Unit";"Zergling";"Larva";146;1
"Unit";"Zergling";"Larva";146;1
"Unit";"Zergling";"Larva";146;1
"Unit";"Zergling";"Larva";146;1
"Unit";"Zergling";"Larva";146;1
"Unit";"Zergling";"Larva";146;1
"Unit";"Zergling";"Larva";146;1
"Unit";"Zergling";"Larva";146;1
"Unit";"Zergling";"Larva";146;1
"Unit";"Zergling";"Larva";146;1
"Building";"CreepTumor";NA;167;0
"Building";"CreepTumor";NA;167;0
"Unit";"Zergling";"Larva";167;1
"Unit";"Zergling";"Larva";167;1
"Unit";"Zergling";"Larva";167;1
"Unit";"Zergling";"Larva";167;1
"Unit";"Zergling";"Larva";167;1
"Unit";"Zergling";"Larva";167;1
"Unit";"Zergling";"Larva";167;1
"Unit";"Zergling";"Larva";167;1
"Unit";"Zergling";"Larva";167;1
"Unit";"Zergling";"Larva";167;1
"Unit";"Zergling";"Larva";167;1
"Unit";"Zergling";"Larva";167;1
"Unit";"Zergling";"Larva";173;1
"Unit";"Zergling";"Larva";173;1
"Unit";"Zergling";"Larva";173;1
"Unit";"Zergling";"Larva";173;1
"Unit";"Zergling";"Larva";173;1
"Unit";"Zergling";"Larva";173;1
"Unit";"Zergling";"Larva";173;1
"Unit";"Zergling";"Larva";173;1
"Building";"Hatchery";NA;136;0
"Unit";"Overlord";"Larva";179;0
"Unit";"Zergling";"Larva";193;1
"Unit";"Zergling";"Larva";193;1
"Unit";"Zergling";"Larva";193;1
"Unit";"Zergling";"Larva";193;1
"Unit";"Zergling";"Larva";193;1
"Unit";"Zergling";"Larva";193;1
"Unit";"Zergling";"Larva";193;1
"Unit";"Zergling";"Larva";193;1
"Unit";"Infestor";"Larva";173;2
"Unit";"Baneling";"Zergling";193;0
"Unit";"Infestor";"Larva";173;2
"Unit";"Baneling";"Zergling";193;0
"Unit";"Baneling";"Zergling";193;0
"Unit";"Baneling";"Zergling";193;0
"Unit";"Baneling";"Zergling";193;0
"Unit";"Baneling";"Zergling";193;0
"Unit";"Baneling";"Zergling";193;0
"Unit";"Baneling";"Zergling";193;0
"Unit";"Baneling";"Zergling";193;0
"Unit";"Baneling";"Zergling";193;0
"Unit";"Baneling";"Zergling";193;0
"Unit";"Baneling";"Zergling";193;0
"Unit";"Baneling";"Zergling";193;0
"Unit";"Baneling";"Zergling";193;0
"Unit";"Zergling";"Larva";193;1
"Unit";"Zergling";"Larva";193;1
"Unit";"Zergling";"Larva";193;1
"Unit";"Zergling";"Larva";193;1
"Unit";"Zergling";"Larva";193;1
"Unit";"Zergling";"Larva";193;1
"Unit";"Zergling";"Larva";193;1
"Unit";"Zergling";"Larva";193;1
"Unit";"Zergling";"Larva";193;1
"Unit";"Zergling";"Larva";193;1
"Unit";"Zergling";"Larva";193;1
"Unit";"Zergling";"Larva";193;1
"Unit";"Overlord";"Larva";193;0
"Unit";"Zergling";"Larva";193;1
"Unit";"Zergling";"Larva";193;1
"Unit";"Baneling";"Zergling";201;0
"Unit";"Zergling";"Larva";193;1
"Unit";"Zergling";"Larva";193;1
"Unit";"Zergling";"Larva";193;1
"Unit";"Zergling";"Larva";193;1
"Unit";"Zergling";"Larva";193;1
"Unit";"Zergling";"Larva";193;1
"Unit";"Zergling";"Larva";193;1
"Unit";"Zergling";"Larva";193;1
"Unit";"Baneling";"Zergling";201;0
"Unit";"Baneling";"Zergling";201;0
"Unit";"Baneling";"Zergling";201;0
"Unit";"Baneling";"Zergling";201;0
"Unit";"Baneling";"Zergling";201;0
"Unit";"Baneling";"Zergling";201;0
"Unit";"Baneling";"Zergling";201;0
"Unit";"Zergling";"Larva";201;1
"Unit";"Zergling";"Larva";201;1
"Upgrade";"ZergGroundArmorsLevel1";"EvolutionChamber";146;0
"Upgrade";"ZergMeleeWeaponsLevel1";"EvolutionChamber";146;0
"Unit";"Queen";"Hatchery";201;2
"Unit";"Zergling";"Larva";229;1
"Unit";"Zergling";"Larva";229;1
"Unit";"Zergling";"Larva";229;1
"Unit";"Zergling";"Larva";229;1
"Unit";"Zergling";"Larva";229;1
"Unit";"Zergling";"Larva";229;1
"Unit";"Zergling";"Larva";229;1
"Unit";"Zergling";"Larva";229;1
"Unit";"Zergling";"Larva";229;1
"Unit";"Zergling";"Larva";229;1
"Unit";"Zergling";"Larva";229;1
"Unit";"Zergling";"Larva";229;1
"Unit";"Zergling";"Larva";229;1
"Unit";"Zergling";"Larva";229;1
"Unit";"Zergling";"Larva";229;1
"Unit";"Zergling";"Larva";229;1
"Unit";"Zergling";"Larva";229;1
"Unit";"Zergling";"Larva";229;1
"Unit";"Zergling";"Larva";229;1
"Unit";"Zergling";"Larva";229;1
"Building";"Extractor";NA;231;0
"Building";"Extractor";NA;231;0
"Unit";"Zergling";"Larva";231;1
"Unit";"Zergling";"Larva";231;1
"Unit";"Zergling";"Larva";239;1
"Unit";"Zergling";"Larva";239;1
"Unit";"Zergling";"Larva";239;1
"Unit";"Zergling";"Larva";239;1
"Unit";"Zergling";"Larva";239;1
"Unit";"Zergling";"Larva";239;1
"Unit";"Zergling";"Larva";239;1
"Unit";"Zergling";"Larva";239;1
"Unit";"Zergling";"Larva";239;1
"Unit";"Zergling";"Larva";239;1
"Unit";"Zergling";"Larva";239;1
"Unit";"Zergling";"Larva";239;1
"Unit";"Zergling";"Larva";259;1
"Unit";"Zergling";"Larva";259;1
"Unit";"Zergling";"Larva";259;1
"Unit";"Zergling";"Larva";259;1
"Unit";"Zergling";"Larva";259;1
"Unit";"Zergling";"Larva";259;1
"Unit";"Zergling";"Larva";259;1
"Unit";"Zergling";"Larva";259;1
"Unit";"Zergling";"Larva";259;1
"Unit";"Zergling";"Larva";259;1
"Unit";"Zergling";"Larva";259;1
"Unit";"Zergling";"Larva";259;1
"Building";"UltraliskCavern";NA;229;0
"Unit";"Overlord";"Larva";261;0
"Unit";"Baneling";"Zergling";273;0
"Unit";"Baneling";"Zergling";273;0
"Unit";"Baneling";"Zergling";273;0
"Unit";"Baneling";"Zergling";273;0
"Unit";"Baneling";"Zergling";273;0
"Unit";"Baneling";"Zergling";273;0
"Unit";"Baneling";"Zergling";273;0
"Unit";"Baneling";"Zergling";273;0
"Unit";"Baneling";"Zergling";273;0
"Unit";"Baneling";"Zergling";273;0
"Unit";"Baneling";"Zergling";273;0
"Unit";"Baneling";"Zergling";273;0
"Unit";"Baneling";"Zergling";273;0
"Unit";"Baneling";"Zergling";273;0
"Unit";"Baneling";"Zergling";273;0
"Unit";"Baneling";"Zergling";273;0
"Unit";"Baneling";"Zergling";273;0
"Unit";"Zergling";"Larva";273;1
"Unit";"Zergling";"Larva";273;1
"Unit";"Overlord";"Larva";273;0
"Unit";"Zergling";"Larva";273;1
"Unit";"Zergling";"Larva";273;1
"Unit";"Zergling";"Larva";273;1
"Unit";"Zergling";"Larva";273;1
"Unit";"Zergling";"Larva";273;1
"Unit";"Zergling";"Larva";273;1
"Unit";"Zergling";"Larva";273;1
"Unit";"Zergling";"Larva";273;1
"Unit";"Viper";"Larva";261;3
"Unit";"Queen";"Hatchery";261;2
"Building";"Hatchery";NA;231;0
"Unit";"Zergling";"Larva";300;1
"Unit";"Zergling";"Larva";300;1
"Unit";"Zergling";"Larva";300;1
"Unit";"Zergling";"Larva";300;1
"Unit";"Zergling";"Larva";300;1
"Unit";"Zergling";"Larva";300;1
"Unit";"Zergling";"Larva";300;1
"Unit";"Zergling";"Larva";300;1
"Unit";"Zergling";"Larva";300;1
"Unit";"Zergling";"Larva";300;1
"Unit";"Zergling";"Larva";300;1
"Unit";"Zergling";"Larva";300;1
"Unit";"Overlord";"Larva";312;0
"Unit";"Overlord";"Larva";312;0
"Unit";"Overlord";"Larva";312;0
"Unit";"Overlord";"Larva";312;0
"Unit";"Overlord";"Larva";312;0
"Building";"CreepTumor";NA;312;0
"Unit";"Overlord";"Larva";312;0
"Unit";"Overlord";"Larva";312;0
"Unit";"Ultralisk";"Larva";298;6
"Unit";"Overlord";"Larva";312;0
"Unit";"Ultralisk";"Larva";300;6
"Upgrade";"ZergGroundArmorsLevel2";"EvolutionChamber";273;0
"Unit";"Queen";"Hatchery";312;2
"Unit";"Queen";"Hatchery";312;2
"Unit";"Queen";"Hatchery";312;2
"Unit";"Queen";"Hatchery";312;2
"Upgrade";"ChitinousPlating";"UltraliskCavern";312;0
"Unit";"Ultralisk";"Larva";318;6
"Unit";"Ultralisk";"Larva";318;6
"Building";"CreepTumor";NA;344;0
"Unit";"Viper";"Larva";324;3
"Upgrade";"ZergMeleeWeaponsLevel2";"EvolutionChamber";300;0
"Unit";"Baneling";"Zergling";350;0
"Unit";"Baneling";"Zergling";350;0
"Unit";"Baneling";"Zergling";350;0
"Unit";"Baneling";"Zergling";350;0
"Unit";"Baneling";"Zergling";350;0
"Unit";"Baneling";"Zergling";350;0
"Unit";"Baneling";"Zergling";350;0
"Unit";"Baneling";"Zergling";350;0
"Unit";"Baneling";"Zergling";350;0
"Unit";"Baneling";"Zergling";350;0
"Unit";"Ultralisk";"Larva";332;6
"Unit";"Ultralisk";"Larva";332;6
"Unit";"Baneling";"Zergling";350;0
"Unit";"Ultralisk";"Larva";332;6
"Unit";"Zergling";"Larva";350;1
"Unit";"Zergling";"Larva";350;1
"Unit";"Zergling";"Larva";350;1
"Unit";"Zergling";"Larva";350;1
"Unit";"Zergling";"Larva";350;1
"Unit";"Zergling";"Larva";350;1
"Unit";"Ultralisk";"Larva";347;6
"Unit";"Corruptor";"Larva";353;2
"Unit";"Corruptor";"Larva";353;2
"Unit";"Corruptor";"Larva";387;2
"Unit";"Ultralisk";"Larva";387;6
"Unit";"Ultralisk";"Larva";387;6
"Unit";"Ultralisk";"Larva";387;6
"Unit";"Corruptor";"Larva";387;2
"Unit";"Corruptor";"Larva";387;2
"Unit";"Corruptor";"Larva";387;2
"Unit";"Corruptor";"Larva";387;2
"Unit";"Ultralisk";"Larva";387;6
"Unit";"Ultralisk";"Larva";407;6
"Unit";"Ultralisk";"Larva";415;6
"Unit";"Ultralisk";"Larva";415;6
"Unit";"Ultralisk";"Larva";427;6
"Unit";"Ultralisk";"Larva";427;6
"Unit";"Ultralisk";"Larva";439;6
"Unit";"Ultralisk";"Larva";439;6
