"type";"unit_name";"on_building";"total_supply";"supply"
"Unit";"Overlord";"Larva";13;0
"Building";"Extractor";NA;18;0
"Building";"SpawningPool";NA;18;0
"Building";"Hatchery";NA;16;0
"Unit";"Overlord";"Larva";21;0
"Unit";"Zergling";"Larva";22;1
"Unit";"Zergling";"Larva";22;1
"Unit";"Zergling";"Larva";22;1
"Unit";"Zergling";"Larva";22;1
"Unit";"Queen";"Hatchery";22;2
"Unit";"Queen";"Hatchery";22;2
"Unit";"Overlord";"Larva";37;0
"Unit";"Queen";"Hatchery";37;2
"Building";"CreepTumorQueen";NA;39;0
"Unit";"Zergling";"Larva";39;1
"Unit";"Zergling";"Larva";39;1
"Unit";"Zergling";"Larva";39;1
"Unit";"Zergling";"Larva";39;1
"Unit";"Zergling";"Larva";39;1
"Unit";"Zergling";"Larva";39;1
"Building";"Hatchery";NA;36;0
"Unit";"Overlord";"Larva";53;0
"Unit";"Overlord";"Larva";53;0
"Building";"Extractor";NA;55;0
"Unit";"Overlord";"Larva";60;0
"Building";"EvolutionChamber";NA;55;0
"Unit";"Queen";"Hatchery";55;2
"Unit";"Queen";"Hatchery";55;2
"Building";"Extractor";NA;60;0
"Building";"CreepTumorQueen";NA;63;0
"Building";"CreepTumor";NA;62;0
"Building";"CreepTumorQueen";NA;71;0
"Unit";"Queen";"Hatchery";60;2
"Unit";"Overlord";"Larva";79;0
"Unit";"Overlord";"Larva";80;0
"Unit";"Overlord";"Larva";80;0
"Unit";"Queen";"Hatchery";75;2
"Building";"BanelingNest";NA;75;0
"Building";"Extractor";NA;80;0
"Building";"CreepTumor";NA;82;0
"Building";"CreepTumorQueen";NA;83;0
"Building";"CreepTumorQueen";NA;83;0
"Building";"CreepTumor";NA;83;0
"Building";"CreepTumorQueen";NA;83;0
"Building";"CreepTumorQueen";NA;83;0
"Unit";"Zergling";"Larva";96;1
"Unit";"Zergling";"Larva";96;1
"Unit";"Zergling";"Larva";96;1
"Unit";"Zergling";"Larva";96;1
"Unit";"Zergling";"Larva";96;1
"Unit";"Zergling";"Larva";96;1
"Unit";"Zergling";"Larva";96;1
"Unit";"Zergling";"Larva";96;1
"Unit";"Zergling";"Larva";96;1
"Unit";"Zergling";"Larva";96;1
"Unit";"Zergling";"Larva";96;1
"Unit";"Zergling";"Larva";96;1
"Unit";"Zergling";"Larva";96;1
"Unit";"Zergling";"Larva";96;1
"Unit";"Zergling";"Larva";96;1
"Unit";"Zergling";"Larva";96;1
"Unit";"Zergling";"Larva";96;1
"Unit";"Zergling";"Larva";96;1
"Unit";"Zergling";"Larva";96;1
"Unit";"Zergling";"Larva";96;1
"Unit";"Overlord";"Larva";96;0
"Unit";"Overlord";"Larva";96;0
"Unit";"Overlord";"Larva";96;0
"Unit";"Baneling";"Zergling";110;0
"Unit";"Baneling";"Zergling";110;0
"Unit";"Baneling";"Zergling";110;0
"Unit";"Baneling";"Zergling";110;0
"Unit";"Overlord";"Larva";110;0
"Building";"EvolutionChamber";NA;96;0
"Unit";"Zergling";"Larva";116;1
"Unit";"Zergling";"Larva";116;1
"Unit";"Zergling";"Larva";116;1
"Unit";"Zergling";"Larva";116;1
"Unit";"Zergling";"Larva";116;1
"Unit";"Zergling";"Larva";116;1
"Unit";"Zergling";"Larva";116;1
"Unit";"Zergling";"Larva";116;1
"Unit";"Zergling";"Larva";116;1
"Unit";"Zergling";"Larva";116;1
"Unit";"Zergling";"Larva";116;1
"Unit";"Zergling";"Larva";116;1
"Unit";"Zergling";"Larva";116;1
"Unit";"Zergling";"Larva";116;1
"Unit";"Zergling";"Larva";116;1
"Unit";"Zergling";"Larva";116;1
"Unit";"Zergling";"Larva";116;1
"Unit";"Zergling";"Larva";116;1
"Unit";"Zergling";"Larva";116;1
"Unit";"Zergling";"Larva";116;1
"Unit";"Zergling";"Larva";116;1
"Unit";"Zergling";"Larva";116;1
"Unit";"Zergling";"Larva";116;1
"Unit";"Zergling";"Larva";116;1
"Unit";"Zergling";"Larva";116;1
"Unit";"Zergling";"Larva";116;1
"Unit";"Zergling";"Larva";116;1
"Unit";"Zergling";"Larva";116;1
"Upgrade";"ZergGroundArmorsLevel1";"EvolutionChamber";80;0
"Unit";"Zergling";"Larva";116;1
"Unit";"Zergling";"Larva";116;1
"Unit";"Zergling";"Larva";116;1
"Unit";"Zergling";"Larva";116;1
"Unit";"Queen";"Hatchery";116;2
"Unit";"Zergling";"Larva";116;1
"Unit";"Zergling";"Larva";116;1
"Unit";"Zergling";"Larva";116;1
"Unit";"Zergling";"Larva";116;1
"Unit";"Zergling";"Larva";116;1
"Unit";"Zergling";"Larva";116;1
"Building";"CreepTumor";NA;150;0
"Building";"CreepTumor";NA;150;0
"Building";"CreepTumor";NA;150;0
"Building";"CreepTumor";NA;150;0
"Building";"CreepTumor";NA;150;0
"Building";"CreepTumor";NA;150;0
"Building";"CreepTumorQueen";NA;156;0
"Building";"CreepTumorQueen";NA;161;0
"Unit";"Overlord";"Larva";161;0
"Building";"CreepTumor";NA;161;0
"Building";"CreepTumor";NA;161;0
"Building";"CreepTumor";NA;161;0
"Building";"CreepTumor";NA;161;0
"Building";"CreepTumor";NA;161;0
"Building";"CreepTumor";NA;161;0
"Building";"CreepTumor";NA;161;0
"Unit";"Baneling";"Zergling";168;0
"Unit";"Baneling";"Zergling";168;0
"Unit";"Baneling";"Zergling";169;0
"Unit";"Baneling";"Zergling";169;0
"Unit";"Baneling";"Zergling";171;0
"Unit";"Baneling";"Zergling";171;0
"Unit";"Baneling";"Zergling";173;0
"Unit";"Baneling";"Zergling";175;0
"Unit";"Baneling";"Zergling";175;0
"Unit";"Baneling";"Zergling";175;0
"Unit";"Baneling";"Zergling";177;0
"Unit";"Baneling";"Zergling";177;0
"Unit";"Baneling";"Zergling";177;0
"Unit";"Baneling";"Zergling";177;0
"Building";"SporeCrawler";NA;168;0
"Unit";"Zergling";"Larva";177;1
"Unit";"Zergling";"Larva";177;1
"Unit";"Zergling";"Larva";177;1
"Unit";"Zergling";"Larva";177;1
"Unit";"Zergling";"Larva";177;1
"Unit";"Zergling";"Larva";177;1
"Building";"Hatchery";NA;148;0
"Unit";"Zergling";"Larva";177;1
"Unit";"Zergling";"Larva";177;1
"Unit";"Zergling";"Larva";177;1
"Unit";"Zergling";"Larva";177;1
"Unit";"Zergling";"Larva";177;1
"Unit";"Zergling";"Larva";177;1
"Unit";"Zergling";"Larva";177;1
"Unit";"Zergling";"Larva";177;1
"Unit";"Zergling";"Larva";177;1
"Unit";"Zergling";"Larva";177;1
"Unit";"Zergling";"Larva";177;1
"Unit";"Zergling";"Larva";177;1
"Unit";"Zergling";"Larva";177;1
"Unit";"Zergling";"Larva";177;1
"Unit";"Zergling";"Larva";177;1
"Unit";"Zergling";"Larva";177;1
"Unit";"Zergling";"Larva";177;1
"Unit";"Zergling";"Larva";177;1
"Unit";"Zergling";"Larva";183;1
"Unit";"Zergling";"Larva";183;1
"Unit";"Zergling";"Larva";183;1
"Unit";"Zergling";"Larva";183;1
"Unit";"Zergling";"Larva";183;1
"Unit";"Zergling";"Larva";183;1
"Unit";"Zergling";"Larva";183;1
"Unit";"Zergling";"Larva";183;1
"Unit";"Zergling";"Larva";183;1
"Unit";"Zergling";"Larva";183;1
"Unit";"Zergling";"Larva";183;1
"Unit";"Zergling";"Larva";183;1
"Unit";"Zergling";"Larva";183;1
"Unit";"Zergling";"Larva";183;1
"Unit";"Baneling";"Zergling";201;0
"Unit";"Baneling";"Zergling";201;0
"Unit";"Zergling";"Larva";215;1
"Unit";"Zergling";"Larva";215;1
"Unit";"Zergling";"Larva";215;1
"Unit";"Zergling";"Larva";215;1
"Unit";"Zergling";"Larva";215;1
"Unit";"Zergling";"Larva";215;1
"Unit";"Zergling";"Larva";215;1
"Unit";"Zergling";"Larva";215;1
"Unit";"Zergling";"Larva";215;1
"Unit";"Zergling";"Larva";215;1
"Unit";"Zergling";"Larva";215;1
"Unit";"Zergling";"Larva";215;1
"Unit";"Zergling";"Larva";215;1
"Unit";"Zergling";"Larva";215;1
"Unit";"Zergling";"Larva";215;1
"Unit";"Zergling";"Larva";215;1
"Unit";"Zergling";"Larva";215;1
"Unit";"Zergling";"Larva";215;1
"Unit";"Zergling";"Larva";215;1
"Unit";"Zergling";"Larva";215;1
"Upgrade";"ZergMeleeWeaponsLevel1";"EvolutionChamber";168;0
"Building";"CreepTumor";NA;236;0
"Building";"CreepTumor";NA;236;0
"Building";"CreepTumor";NA;236;0
"Building";"HydraliskDen";NA;215;0
"Upgrade";"ZergGroundArmorsLevel2";"EvolutionChamber";168;0
"Building";"CreepTumorQueen";NA;236;0
"Unit";"Overlord";"Larva";236;0
"Unit";"Overlord";"Larva";236;0
"Unit";"Overlord";"Larva";236;0
"Building";"CreepTumorQueen";NA;236;0
"Unit";"Queen";"Hatchery";236;2
"Building";"CreepTumor";NA;236;0
"Building";"CreepTumor";NA;236;0
"Building";"CreepTumor";NA;236;0
"Building";"CreepTumor";NA;236;0
"Building";"CreepTumorQueen";NA;236;0
"Building";"CreepTumor";NA;236;0
"Building";"CreepTumor";NA;236;0
"Unit";"Queen";"Hatchery";236;2
"Building";"CreepTumor";NA;236;0
"Building";"CreepTumorQueen";NA;236;0
"Unit";"Baneling";"Zergling";236;0
"Unit";"Baneling";"Zergling";236;0
"Unit";"Baneling";"Zergling";236;0
"Unit";"Baneling";"Zergling";236;0
"Unit";"Baneling";"Zergling";236;0
"Unit";"Baneling";"Zergling";236;0
"Unit";"Baneling";"Zergling";236;0
"Unit";"Baneling";"Zergling";236;0
"Unit";"Baneling";"Zergling";236;0
"Unit";"Zergling";"Larva";236;1
"Unit";"Zergling";"Larva";236;1
"Unit";"Zergling";"Larva";236;1
"Unit";"Zergling";"Larva";236;1
"Unit";"Zergling";"Larva";236;1
"Unit";"Zergling";"Larva";236;1
"Unit";"Zergling";"Larva";236;1
"Unit";"Zergling";"Larva";236;1
"Unit";"Zergling";"Larva";236;1
"Unit";"Zergling";"Larva";236;1
"Unit";"Zergling";"Larva";236;1
"Unit";"Zergling";"Larva";236;1
"Unit";"Zergling";"Larva";236;1
"Unit";"Zergling";"Larva";236;1
"Unit";"Zergling";"Larva";236;1
"Unit";"Zergling";"Larva";236;1
"Unit";"Zergling";"Larva";236;1
"Unit";"Zergling";"Larva";236;1
"Unit";"Zergling";"Larva";236;1
"Unit";"Zergling";"Larva";236;1
"Unit";"Zergling";"Larva";236;1
"Unit";"Zergling";"Larva";236;1
"Unit";"Zergling";"Larva";236;1
"Unit";"Zergling";"Larva";236;1
"Unit";"Zergling";"Larva";236;1
"Unit";"Zergling";"Larva";236;1
"Unit";"Zergling";"Larva";236;1
"Unit";"Zergling";"Larva";236;1
"Unit";"Zergling";"Larva";236;1
"Unit";"Zergling";"Larva";236;1
"Unit";"Zergling";"Larva";236;1
"Unit";"Zergling";"Larva";236;1
"Building";"CreepTumorQueen";NA;238;0
"Unit";"Zergling";"Larva";236;1
"Unit";"Zergling";"Larva";236;1
"Unit";"Zergling";"Larva";236;1
"Unit";"Zergling";"Larva";236;1
"Building";"Hatchery";NA;215;0
"Unit";"Queen";"Hatchery";236;2
"Building";"InfestationPit";NA;236;0
"Unit";"Zergling";"Larva";238;1
"Unit";"Zergling";"Larva";238;1
"Unit";"Zergling";"Larva";238;1
"Unit";"Zergling";"Larva";238;1
"Unit";"Zergling";"Larva";238;1
"Unit";"Zergling";"Larva";238;1
"Unit";"Zergling";"Larva";238;1
"Unit";"Zergling";"Larva";238;1
"Unit";"Zergling";"Larva";240;1
"Unit";"Zergling";"Larva";240;1
"Unit";"Zergling";"Larva";240;1
"Unit";"Zergling";"Larva";240;1
"Unit";"Overlord";"Larva";240;0
"Unit";"Overlord";"Larva";240;0
"Building";"Hatchery";NA;236;0
"Unit";"Overlord";"Larva";240;0
"Unit";"Overlord";"Larva";240;0
"Unit";"Overlord";"Larva";240;0
"Building";"Hatchery";NA;236;0
"Unit";"Zergling";"Larva";290;1
"Unit";"Zergling";"Larva";290;1
"Unit";"Zergling";"Larva";290;1
"Unit";"Zergling";"Larva";290;1
"Unit";"Zergling";"Larva";290;1
"Unit";"Zergling";"Larva";290;1
"Unit";"Zergling";"Larva";290;1
"Unit";"Zergling";"Larva";290;1
"Unit";"Zergling";"Larva";290;1
"Unit";"Zergling";"Larva";290;1
"Unit";"Zergling";"Larva";290;1
"Unit";"Zergling";"Larva";290;1
"Unit";"Zergling";"Larva";290;1
"Unit";"Zergling";"Larva";290;1
"Unit";"Zergling";"Larva";290;1
"Unit";"Zergling";"Larva";290;1
"Unit";"Zergling";"Larva";290;1
"Unit";"Zergling";"Larva";290;1
"Unit";"Zergling";"Larva";290;1
"Unit";"Zergling";"Larva";290;1
"Upgrade";"EvolveGroovedSpines";"HydraliskDen";238;0
"Unit";"Zergling";"Larva";290;1
"Unit";"Zergling";"Larva";290;1
"Unit";"Zergling";"Larva";290;1
"Unit";"Zergling";"Larva";290;1
"Unit";"Zergling";"Larva";290;1
"Unit";"Zergling";"Larva";290;1
"Unit";"Queen";"Hatchery";276;2
"Unit";"Zergling";"Larva";290;1
"Unit";"Zergling";"Larva";290;1
"Unit";"Zergling";"Larva";290;1
"Unit";"Zergling";"Larva";290;1
"Unit";"Zergling";"Larva";290;1
"Unit";"Zergling";"Larva";290;1
"Unit";"Zergling";"Larva";290;1
"Unit";"Zergling";"Larva";290;1
"Unit";"Zergling";"Larva";290;1
"Unit";"Zergling";"Larva";290;1
"Unit";"Zergling";"Larva";290;1
"Unit";"Zergling";"Larva";290;1
"Unit";"Zergling";"Larva";290;1
"Unit";"Zergling";"Larva";290;1
"Building";"Extractor";NA;326;0
"Building";"Extractor";NA;330;0
"Building";"CreepTumor";NA;341;0
"Building";"CreepTumor";NA;344;0
"Building";"CreepTumor";NA;344;0
"Building";"CreepTumor";NA;344;0
"Building";"CreepTumorQueen";NA;344;0
"Unit";"Hydralisk";"Larva";344;2
"Unit";"Hydralisk";"Larva";344;2
"Unit";"Hydralisk";"Larva";344;2
"Unit";"Hydralisk";"Larva";344;2
"Unit";"Hydralisk";"Larva";344;2
"Unit";"Hydralisk";"Larva";344;2
"Unit";"Hydralisk";"Larva";344;2
"Unit";"Hydralisk";"Larva";344;2
"Unit";"Hydralisk";"Larva";344;2
"Unit";"Hydralisk";"Larva";344;2
"Upgrade";"ZergMissileWeaponsLevel1";"EvolutionChamber";240;0
"Upgrade";"ZergMeleeWeaponsLevel2";"EvolutionChamber";238;0
"Building";"CreepTumor";NA;344;0
"Building";"CreepTumor";NA;344;0
"Building";"CreepTumor";NA;344;0
"Building";"CreepTumor";NA;364;0
"Building";"CreepTumor";NA;364;0
"Building";"CreepTumorQueen";NA;364;0
"Unit";"Hydralisk";"Larva";344;2
"Unit";"Hydralisk";"Larva";344;2
"Unit";"Hydralisk";"Larva";344;2
"Unit";"Hydralisk";"Larva";344;2
"Unit";"Hydralisk";"Larva";344;2
"Unit";"Hydralisk";"Larva";344;2
"Unit";"Hydralisk";"Larva";364;2
"Unit";"Hydralisk";"Larva";364;2
"Unit";"Hydralisk";"Larva";364;2
"Unit";"Hydralisk";"Larva";364;2
"Unit";"Baneling";"Zergling";365;0
"Unit";"Baneling";"Zergling";365;0
"Unit";"Baneling";"Zergling";365;0
"Unit";"Baneling";"Zergling";365;0
"Unit";"Baneling";"Zergling";365;0
"Unit";"Baneling";"Zergling";365;0
"Unit";"Baneling";"Zergling";365;0
"Unit";"Baneling";"Zergling";365;0
"Unit";"Baneling";"Zergling";365;0
"Upgrade";"EvolveMuscularAugments";"HydraliskDen";344;0
"Unit";"Baneling";"Zergling";365;0
"Unit";"Baneling";"Zergling";365;0
"Unit";"Baneling";"Zergling";365;0
"Unit";"Baneling";"Zergling";365;0
"Unit";"Baneling";"Zergling";365;0
"Unit";"Baneling";"Zergling";365;0
"Building";"CreepTumor";NA;365;0
"Building";"CreepTumor";NA;365;0
"Building";"CreepTumor";NA;365;0
"Building";"CreepTumor";NA;365;0
"Building";"CreepTumor";NA;365;0
"Unit";"Zergling";"Larva";365;1
"Unit";"Zergling";"Larva";365;1
"Building";"CreepTumorQueen";NA;385;0
"Unit";"Overlord";"Larva";385;0
"Unit";"Overlord";"Larva";385;0
"Building";"Extractor";NA;387;0
"Building";"Extractor";NA;387;0
"Unit";"Hydralisk";"Larva";387;2
"Unit";"Hydralisk";"Larva";387;2
"Unit";"Hydralisk";"Larva";387;2
"Unit";"Hydralisk";"Larva";387;2
"Unit";"Hydralisk";"Larva";387;2
"Unit";"Hydralisk";"Larva";387;2
"Unit";"Hydralisk";"Larva";387;2
"Unit";"Hydralisk";"Larva";387;2
"Unit";"Hydralisk";"Larva";387;2
"Building";"CreepTumor";NA;387;0
"Building";"CreepTumor";NA;387;0
"Building";"CreepTumor";NA;387;0
"Building";"CreepTumor";NA;387;0
"Building";"CreepTumorQueen";NA;405;0
"Building";"CreepTumor";NA;405;0
"Building";"CreepTumor";NA;405;0
"Building";"CreepTumor";NA;405;0
"Building";"CreepTumor";NA;405;0
"Building";"CreepTumorQueen";NA;411;0
"Building";"CreepTumorQueen";NA;411;0
"Building";"Extractor";NA;387;0
"Building";"Extractor";NA;393;0
"Building";"CreepTumorQueen";NA;411;0
"Building";"CreepTumor";NA;411;0
"Building";"CreepTumor";NA;411;0
"Building";"CreepTumorQueen";NA;411;0
"Building";"CreepTumor";NA;411;0
"Unit";"Viper";"Larva";411;3
"Building";"CreepTumorQueen";NA;411;0
"Building";"CreepTumor";NA;411;0
"Building";"Spire";NA;387;0
"Unit";"Overlord";"Larva";414;0
"Unit";"Overlord";"Larva";414;0
"Unit";"Overlord";"Larva";414;0
"Unit";"Baneling";"Zergling";414;0
"Unit";"Baneling";"Zergling";414;0
"Unit";"Baneling";"Zergling";414;0
"Unit";"Baneling";"Zergling";414;0
"Unit";"Baneling";"Zergling";414;0
"Unit";"Baneling";"Zergling";414;0
"Unit";"Baneling";"Zergling";414;0
"Unit";"Baneling";"Zergling";414;0
"Building";"CreepTumor";NA;414;0
"Building";"CreepTumor";NA;414;0
"Unit";"Zergling";"Larva";414;1
"Unit";"Zergling";"Larva";414;1
"Unit";"Zergling";"Larva";414;1
"Unit";"Zergling";"Larva";414;1
"Unit";"Zergling";"Larva";414;1
"Unit";"Zergling";"Larva";414;1
"Unit";"Zergling";"Larva";414;1
"Unit";"Zergling";"Larva";414;1
"Unit";"Zergling";"Larva";414;1
"Unit";"Zergling";"Larva";414;1
"Unit";"Zergling";"Larva";414;1
"Unit";"Zergling";"Larva";414;1
"Unit";"Zergling";"Larva";414;1
"Unit";"Zergling";"Larva";414;1
"Unit";"Baneling";"Zergling";414;0
"Unit";"Zergling";"Larva";414;1
"Unit";"Zergling";"Larva";414;1
"Unit";"Zergling";"Larva";414;1
"Unit";"Zergling";"Larva";414;1
"Unit";"Zergling";"Larva";414;1
"Unit";"Zergling";"Larva";414;1
"Unit";"Zergling";"Larva";414;1
"Unit";"Zergling";"Larva";414;1
"Unit";"Zergling";"Larva";414;1
"Unit";"Zergling";"Larva";414;1
"Unit";"Baneling";"Zergling";414;0
"Unit";"Zergling";"Larva";414;1
"Unit";"Zergling";"Larva";414;1
"Unit";"Zergling";"Larva";414;1
"Unit";"Zergling";"Larva";414;1
"Unit";"Zergling";"Larva";414;1
"Unit";"Zergling";"Larva";414;1
"Unit";"Zergling";"Larva";414;1
"Unit";"Zergling";"Larva";414;1
"Unit";"Baneling";"Zergling";414;0
"Unit";"Baneling";"Zergling";414;0
"Unit";"Baneling";"Zergling";414;0
"Unit";"Baneling";"Zergling";414;0
"Unit";"Zergling";"Larva";414;1
"Unit";"Zergling";"Larva";414;1
"Unit";"Zergling";"Larva";414;1
"Unit";"Zergling";"Larva";414;1
"Unit";"Zergling";"Larva";414;1
"Unit";"Zergling";"Larva";414;1
"Unit";"Zergling";"Larva";414;1
"Unit";"Zergling";"Larva";414;1
"Unit";"Baneling";"Zergling";414;0
"Unit";"Baneling";"Zergling";414;0
"Unit";"Baneling";"Zergling";414;0
"Unit";"Baneling";"Zergling";414;0
"Unit";"Zergling";"Larva";414;1
"Unit";"Zergling";"Larva";414;1
"Unit";"Zergling";"Larva";414;1
"Unit";"Zergling";"Larva";414;1
"Unit";"Zergling";"Larva";414;1
"Unit";"Zergling";"Larva";414;1
"Unit";"Zergling";"Larva";414;1
"Unit";"Zergling";"Larva";414;1
"Building";"CreepTumor";NA;414;0
"Upgrade";"ZergGroundArmorsLevel3";"EvolutionChamber";387;0
"Unit";"Zergling";"Larva";414;1
"Unit";"Zergling";"Larva";414;1
"Unit";"Zergling";"Larva";414;1
"Unit";"Zergling";"Larva";414;1
"Unit";"Zergling";"Larva";414;1
"Unit";"Zergling";"Larva";414;1
"Unit";"Zergling";"Larva";414;1
"Unit";"Zergling";"Larva";414;1
"Unit";"Zergling";"Larva";414;1
"Unit";"Zergling";"Larva";414;1
"Unit";"Zergling";"Larva";414;1
"Unit";"Zergling";"Larva";414;1
"Unit";"Zergling";"Larva";414;1
"Unit";"Zergling";"Larva";414;1
"Unit";"Zergling";"Larva";414;1
"Unit";"Zergling";"Larva";414;1
"Unit";"Zergling";"Larva";414;1
"Unit";"Zergling";"Larva";414;1
"Unit";"Zergling";"Larva";414;1
"Unit";"Zergling";"Larva";414;1
"Unit";"Zergling";"Larva";414;1
"Unit";"Zergling";"Larva";414;1
"Unit";"Zergling";"Larva";414;1
"Unit";"Zergling";"Larva";414;1
"Unit";"Zergling";"Larva";414;1
"Unit";"Zergling";"Larva";414;1
"Unit";"Zergling";"Larva";414;1
"Unit";"Zergling";"Larva";414;1
"Unit";"Baneling";"Zergling";462;0
"Unit";"Baneling";"Zergling";462;0
"Unit";"Baneling";"Zergling";462;0
"Unit";"Baneling";"Zergling";462;0
"Unit";"Baneling";"Zergling";462;0
"Unit";"Baneling";"Zergling";462;0
"Unit";"Baneling";"Zergling";462;0
"Unit";"Baneling";"Zergling";462;0
"Unit";"Zergling";"Larva";436;1
"Unit";"Zergling";"Larva";436;1
"Unit";"Baneling";"Zergling";462;0
"Unit";"Baneling";"Zergling";462;0
"Unit";"Baneling";"Zergling";462;0
"Unit";"Baneling";"Zergling";462;0
"Unit";"Baneling";"Zergling";462;0
"Unit";"Baneling";"Zergling";462;0
"Unit";"Baneling";"Zergling";462;0
"Unit";"Zergling";"Larva";450;1
"Unit";"Zergling";"Larva";450;1
"Unit";"Zergling";"Larva";450;1
"Unit";"Zergling";"Larva";450;1
"Unit";"Baneling";"Zergling";462;0
"Unit";"Zergling";"Larva";454;1
"Unit";"Zergling";"Larva";454;1
"Unit";"Zergling";"Larva";454;1
"Unit";"Zergling";"Larva";454;1
"Unit";"Zergling";"Larva";458;1
"Unit";"Zergling";"Larva";458;1
"Unit";"Zergling";"Larva";462;1
"Unit";"Zergling";"Larva";462;1
"Unit";"Zergling";"Larva";462;1
"Unit";"Zergling";"Larva";462;1
"Unit";"Zergling";"Larva";462;1
"Unit";"Zergling";"Larva";462;1
"Unit";"Baneling";"Zergling";462;0
"Unit";"Baneling";"Zergling";462;0
"Unit";"Baneling";"Zergling";462;0
"Unit";"Baneling";"Zergling";462;0
"Unit";"Baneling";"Zergling";462;0
"Unit";"Baneling";"Zergling";462;0
"Unit";"Baneling";"Zergling";462;0
"Unit";"Baneling";"Zergling";462;0
"Unit";"Baneling";"Zergling";462;0
"Unit";"Baneling";"Zergling";462;0
"Unit";"Baneling";"Zergling";462;0
"Unit";"Baneling";"Zergling";462;0
"Unit";"Baneling";"Zergling";462;0
"Unit";"Baneling";"Zergling";462;0
"Unit";"Baneling";"Zergling";462;0
"Upgrade";"ZergMeleeWeaponsLevel3";"EvolutionChamber";387;0
"Unit";"Baneling";"Zergling";464;0
"Unit";"Zergling";"Larva";508;1
"Unit";"Zergling";"Larva";508;1
"Unit";"Zergling";"Larva";508;1
"Unit";"Zergling";"Larva";508;1
"Unit";"Zergling";"Larva";508;1
"Unit";"Zergling";"Larva";508;1
"Unit";"Zergling";"Larva";508;1
"Unit";"Zergling";"Larva";508;1
"Unit";"Zergling";"Larva";508;1
"Unit";"Zergling";"Larva";508;1
"Unit";"Zergling";"Larva";508;1
"Unit";"Zergling";"Larva";508;1
"Unit";"Zergling";"Larva";508;1
"Unit";"Zergling";"Larva";508;1
"Unit";"Zergling";"Larva";508;1
"Unit";"Zergling";"Larva";508;1
"Unit";"Zergling";"Larva";508;1
"Unit";"Zergling";"Larva";508;1
"Unit";"Zergling";"Larva";508;1
"Unit";"Zergling";"Larva";508;1
"Unit";"Zergling";"Larva";508;1
"Unit";"Zergling";"Larva";508;1
"Unit";"Zergling";"Larva";508;1
"Unit";"Zergling";"Larva";508;1
"Unit";"Zergling";"Larva";508;1
"Unit";"Zergling";"Larva";508;1
"Unit";"Zergling";"Larva";508;1
"Unit";"Zergling";"Larva";508;1
"Unit";"Zergling";"Larva";508;1
"Unit";"Zergling";"Larva";508;1
"Unit";"Zergling";"Larva";508;1
"Unit";"Zergling";"Larva";508;1
"Unit";"Zergling";"Larva";508;1
"Unit";"Zergling";"Larva";508;1
"Unit";"Zergling";"Larva";508;1
"Unit";"Zergling";"Larva";508;1
"Unit";"Zergling";"Larva";508;1
"Unit";"Zergling";"Larva";508;1
"Unit";"Zergling";"Larva";508;1
"Unit";"Zergling";"Larva";508;1
"Unit";"Zergling";"Larva";508;1
"Unit";"Zergling";"Larva";508;1
"Unit";"Zergling";"Larva";508;1
"Unit";"Zergling";"Larva";508;1
"Unit";"Zergling";"Larva";508;1
"Unit";"Zergling";"Larva";508;1
"Unit";"Zergling";"Larva";508;1
"Unit";"Zergling";"Larva";508;1
"Unit";"Baneling";"Zergling";556;0
"Unit";"Baneling";"Zergling";556;0
"Unit";"Baneling";"Zergling";556;0
"Unit";"Baneling";"Zergling";556;0
"Unit";"Baneling";"Zergling";556;0
"Unit";"Baneling";"Zergling";556;0
"Unit";"Baneling";"Zergling";556;0
"Unit";"Baneling";"Zergling";556;0
"Unit";"Baneling";"Zergling";556;0
"Unit";"Baneling";"Zergling";556;0
"Unit";"Baneling";"Zergling";556;0
"Unit";"Baneling";"Zergling";556;0
"Unit";"Baneling";"Zergling";556;0
"Unit";"Baneling";"Zergling";556;0
"Unit";"Baneling";"Zergling";556;0
"Unit";"Baneling";"Zergling";556;0
"Unit";"Baneling";"Zergling";556;0
"Unit";"Baneling";"Zergling";556;0
"Building";"CreepTumorQueen";NA;556;0
"Unit";"Zergling";"Larva";556;1
"Unit";"Zergling";"Larva";556;1
"Unit";"Zergling";"Larva";556;1
"Unit";"Zergling";"Larva";556;1
"Unit";"Zergling";"Larva";556;1
"Unit";"Zergling";"Larva";556;1
"Unit";"Zergling";"Larva";556;1
"Unit";"Zergling";"Larva";556;1
"Unit";"Zergling";"Larva";556;1
"Unit";"Zergling";"Larva";556;1
"Unit";"Zergling";"Larva";556;1
"Unit";"Zergling";"Larva";556;1
"Unit";"Zergling";"Larva";556;1
"Unit";"Zergling";"Larva";556;1
"Unit";"Zergling";"Larva";556;1
"Unit";"Zergling";"Larva";556;1
"Unit";"Zergling";"Larva";556;1
"Unit";"Zergling";"Larva";556;1
"Unit";"Zergling";"Larva";556;1
"Unit";"Zergling";"Larva";556;1
"Unit";"Zergling";"Larva";556;1
"Unit";"Zergling";"Larva";556;1
"Unit";"Zergling";"Larva";556;1
"Unit";"Zergling";"Larva";556;1
"Unit";"Zergling";"Larva";556;1
"Unit";"Zergling";"Larva";556;1
"Unit";"Zergling";"Larva";556;1
"Unit";"Zergling";"Larva";556;1
"Unit";"Zergling";"Larva";556;1
"Unit";"Zergling";"Larva";556;1
"Unit";"Baneling";"Zergling";556;0
"Unit";"Baneling";"Zergling";556;0
"Unit";"Baneling";"Zergling";556;0
"Unit";"Baneling";"Zergling";556;0
"Unit";"Baneling";"Zergling";556;0
"Unit";"Baneling";"Zergling";556;0
"Unit";"Baneling";"Zergling";556;0
"Unit";"Baneling";"Zergling";556;0
"Unit";"Baneling";"Zergling";556;0
"Unit";"Baneling";"Zergling";556;0
"Unit";"Baneling";"Zergling";556;0
"Building";"CreepTumorQueen";NA;556;0
"Unit";"Zergling";"Larva";556;1
"Unit";"Zergling";"Larva";556;1
"Unit";"Zergling";"Larva";556;1
"Unit";"Zergling";"Larva";556;1
"Unit";"Zergling";"Larva";556;1
"Unit";"Zergling";"Larva";556;1
"Unit";"Zergling";"Larva";556;1
"Unit";"Zergling";"Larva";556;1
"Unit";"Zergling";"Larva";556;1
"Unit";"Zergling";"Larva";556;1
"Building";"CreepTumor";NA;584;0
"Building";"CreepTumor";NA;584;0
"Unit";"Baneling";"Zergling";586;0
"Unit";"Baneling";"Zergling";586;0
"Unit";"Baneling";"Zergling";586;0
"Unit";"Baneling";"Zergling";586;0
"Unit";"Baneling";"Zergling";586;0
"Unit";"Viper";"Larva";596;3
"Unit";"Viper";"Larva";596;3
"Unit";"Viper";"Larva";596;3
"Unit";"Viper";"Larva";596;3
"Unit";"Viper";"Larva";596;3
"Unit";"Viper";"Larva";596;3
"Unit";"Baneling";"Zergling";596;0
"Unit";"Baneling";"Zergling";596;0
"Unit";"Baneling";"Zergling";596;0
"Unit";"Baneling";"Zergling";596;0
"Unit";"Baneling";"Zergling";596;0
"Unit";"Baneling";"Zergling";596;0
"Unit";"Baneling";"Zergling";596;0
"Unit";"Baneling";"Zergling";596;0
"Building";"UltraliskCavern";NA;596;0
"Building";"Hatchery";NA;596;0
"Unit";"Zergling";"Larva";614;1
"Unit";"Zergling";"Larva";614;1
"Unit";"Zergling";"Larva";614;1
"Unit";"Zergling";"Larva";614;1
"Unit";"Zergling";"Larva";614;1
"Unit";"Zergling";"Larva";614;1
"Unit";"Zergling";"Larva";614;1
"Unit";"Zergling";"Larva";614;1
"Building";"Hatchery";NA;614;0
"Unit";"Ultralisk";"Larva";614;6
"Unit";"Ultralisk";"Larva";614;6
"Unit";"Baneling";"Zergling";622;0
"Unit";"Baneling";"Zergling";622;0
"Unit";"Baneling";"Zergling";622;0
"Unit";"Baneling";"Zergling";622;0
"Unit";"Baneling";"Zergling";622;0
"Unit";"Baneling";"Zergling";622;0
"Unit";"Baneling";"Zergling";622;0
"Unit";"Baneling";"Zergling";622;0
"Unit";"Baneling";"Zergling";622;0
"Unit";"Baneling";"Zergling";622;0
"Building";"CreepTumorQueen";NA;634;0
"Unit";"Ultralisk";"Larva";622;6
"Unit";"Ultralisk";"Larva";622;6
"Unit";"Zergling";"Larva";634;1
"Unit";"Zergling";"Larva";634;1
"Upgrade";"ChitinousPlating";"UltraliskCavern";622;0
"Unit";"Zergling";"Larva";634;1
"Unit";"Zergling";"Larva";634;1
"Unit";"Zergling";"Larva";634;1
"Unit";"Zergling";"Larva";634;1
"Unit";"Zergling";"Larva";634;1
"Unit";"Zergling";"Larva";634;1
"Unit";"Zergling";"Larva";634;1
"Unit";"Zergling";"Larva";634;1
"Unit";"Zergling";"Larva";634;1
"Unit";"Zergling";"Larva";634;1
"Unit";"Zergling";"Larva";634;1
"Unit";"Zergling";"Larva";634;1
"Unit";"Zergling";"Larva";634;1
"Unit";"Zergling";"Larva";634;1
"Unit";"Zergling";"Larva";634;1
"Unit";"Zergling";"Larva";634;1
"Unit";"Ultralisk";"Larva";634;6
"Unit";"Ultralisk";"Larva";634;6
"Unit";"Ultralisk";"Larva";634;6
"Unit";"Ultralisk";"Larva";634;6
"Unit";"Ultralisk";"Larva";634;6
"Unit";"Ultralisk";"Larva";634;6
"Building";"CreepTumorQueen";NA;664;0
"Building";"CreepTumorQueen";NA;664;0
"Unit";"Overlord";"Larva";664;0
"Unit";"Overlord";"Larva";664;0
"Unit";"Overlord";"Larva";664;0
"Unit";"Overlord";"Larva";664;0
"Unit";"Overlord";"Larva";664;0
"Unit";"Overlord";"Larva";664;0
"Building";"CreepTumor";NA;700;0
"Building";"CreepTumor";NA;700;0
"Building";"CreepTumorQueen";NA;700;0
"Building";"CreepTumor";NA;700;0
"Building";"CreepTumorQueen";NA;700;0
"Unit";"Corruptor";"Larva";700;2
"Building";"CreepTumorQueen";NA;700;0
"Unit";"Baneling";"Zergling";700;0
"Unit";"Baneling";"Zergling";700;0
"Unit";"Baneling";"Zergling";700;0
"Unit";"Baneling";"Zergling";700;0
"Unit";"Zergling";"Larva";700;1
"Unit";"Zergling";"Larva";700;1
"Building";"CreepTumorQueen";NA;700;0
"Unit";"Corruptor";"Larva";700;2
"Unit";"Corruptor";"Larva";700;2
"Unit";"Corruptor";"Larva";700;2
"Unit";"Corruptor";"Larva";700;2
"Unit";"Corruptor";"Larva";700;2
"Unit";"Corruptor";"Larva";700;2
"Unit";"Corruptor";"Larva";700;2
"Unit";"Corruptor";"Larva";700;2
"Unit";"Corruptor";"Larva";700;2
"Unit";"Corruptor";"Larva";700;2
"Building";"SporeCrawler";NA;700;0
"Building";"SporeCrawler";NA;704;0
"Building";"Hatchery";NA;700;0
"Unit";"Zergling";"Larva";724;1
"Unit";"Zergling";"Larva";724;1
"Unit";"Zergling";"Larva";724;1
"Unit";"Zergling";"Larva";724;1
"Unit";"Zergling";"Larva";724;1
"Unit";"Zergling";"Larva";724;1
"Unit";"Zergling";"Larva";724;1
"Unit";"Zergling";"Larva";724;1
"Unit";"Zergling";"Larva";724;1
"Unit";"Zergling";"Larva";724;1
"Unit";"Zergling";"Larva";724;1
"Unit";"Zergling";"Larva";724;1
"Unit";"Zergling";"Larva";724;1
"Unit";"Zergling";"Larva";724;1
"Unit";"Zergling";"Larva";724;1
"Unit";"Zergling";"Larva";724;1
"Unit";"Zergling";"Larva";724;1
"Unit";"Zergling";"Larva";724;1
"Unit";"Zergling";"Larva";724;1
"Unit";"Zergling";"Larva";724;1
"Unit";"Zergling";"Larva";724;1
"Unit";"Zergling";"Larva";724;1
"Unit";"Zergling";"Larva";724;1
"Unit";"Zergling";"Larva";724;1
"Unit";"Zergling";"Larva";724;1
"Unit";"Zergling";"Larva";724;1
"Building";"CreepTumor";NA;750;0
"Unit";"Zergling";"Larva";728;1
"Unit";"Zergling";"Larva";728;1
"Unit";"Zergling";"Larva";732;1
"Unit";"Zergling";"Larva";732;1
"Unit";"Zergling";"Larva";732;1
"Unit";"Zergling";"Larva";732;1
"Unit";"Zergling";"Larva";732;1
"Unit";"Zergling";"Larva";732;1
"Unit";"Zergling";"Larva";732;1
"Unit";"Zergling";"Larva";732;1
"Unit";"Zergling";"Larva";732;1
"Unit";"Zergling";"Larva";732;1
"Unit";"Zergling";"Larva";732;1
"Unit";"Zergling";"Larva";732;1
"Unit";"Zergling";"Larva";732;1
"Unit";"Zergling";"Larva";732;1
"Unit";"Zergling";"Larva";734;1
"Unit";"Zergling";"Larva";734;1
"Unit";"Zergling";"Larva";734;1
"Unit";"Zergling";"Larva";734;1
"Building";"CreepTumorQueen";NA;750;0
"Unit";"Ultralisk";"Larva";724;6
"Unit";"Ultralisk";"Larva";724;6
"Unit";"Ultralisk";"Larva";724;6
"Unit";"Ultralisk";"Larva";724;6
"Unit";"Ultralisk";"Larva";724;6
"Building";"CreepTumorQueen";NA;750;0
"Unit";"Zergling";"Larva";750;1
"Unit";"Zergling";"Larva";750;1
"Unit";"Zergling";"Larva";750;1
"Unit";"Zergling";"Larva";750;1
"Unit";"Zergling";"Larva";750;1
"Unit";"Zergling";"Larva";750;1
"Unit";"Zergling";"Larva";750;1
"Unit";"Zergling";"Larva";750;1
"Unit";"Zergling";"Larva";750;1
"Unit";"Zergling";"Larva";750;1
"Unit";"Zergling";"Larva";750;1
"Unit";"Zergling";"Larva";750;1
"Unit";"Zergling";"Larva";750;1
"Unit";"Zergling";"Larva";750;1
"Unit";"Zergling";"Larva";750;1
"Unit";"Zergling";"Larva";750;1
"Unit";"Zergling";"Larva";770;1
"Unit";"Zergling";"Larva";770;1
"Unit";"Baneling";"Zergling";800;0
"Unit";"Zergling";"Larva";770;1
"Unit";"Zergling";"Larva";770;1
"Unit";"Zergling";"Larva";770;1
"Unit";"Zergling";"Larva";770;1
"Unit";"Baneling";"Zergling";800;0
"Unit";"Baneling";"Zergling";800;0
"Unit";"Baneling";"Zergling";800;0
"Unit";"Zergling";"Larva";770;1
"Unit";"Zergling";"Larva";770;1
"Unit";"Zergling";"Larva";770;1
"Unit";"Zergling";"Larva";770;1
"Unit";"Baneling";"Zergling";800;0
"Unit";"Baneling";"Zergling";800;0
"Unit";"Baneling";"Zergling";800;0
"Unit";"Zergling";"Larva";814;1
"Unit";"Zergling";"Larva";814;1
"Unit";"Zergling";"Larva";816;1
"Unit";"Zergling";"Larva";816;1
"Unit";"Zergling";"Larva";816;1
"Unit";"Zergling";"Larva";816;1
"Unit";"Zergling";"Larva";816;1
"Unit";"Zergling";"Larva";816;1
"Unit";"Zergling";"Larva";816;1
"Unit";"Zergling";"Larva";816;1
"Unit";"Zergling";"Larva";816;1
"Unit";"Zergling";"Larva";816;1
"Unit";"Zergling";"Larva";816;1
"Unit";"Zergling";"Larva";816;1
"Unit";"Zergling";"Larva";816;1
"Unit";"Zergling";"Larva";816;1
"Unit";"Zergling";"Larva";826;1
"Unit";"Zergling";"Larva";826;1
"Unit";"Zergling";"Larva";826;1
"Unit";"Zergling";"Larva";826;1
"Unit";"Zergling";"Larva";826;1
"Unit";"Zergling";"Larva";826;1
"Unit";"Zergling";"Larva";826;1
"Unit";"Zergling";"Larva";826;1
"Unit";"Zergling";"Larva";826;1
"Unit";"Zergling";"Larva";826;1
"Unit";"Zergling";"Larva";826;1
"Unit";"Zergling";"Larva";826;1
"Unit";"Zergling";"Larva";826;1
"Unit";"Zergling";"Larva";826;1
"Unit";"Zergling";"Larva";826;1
"Unit";"Zergling";"Larva";826;1
"Unit";"Zergling";"Larva";828;1
"Unit";"Zergling";"Larva";828;1
"Unit";"Baneling";"Zergling";842;0
"Unit";"Baneling";"Zergling";842;0
"Unit";"Baneling";"Zergling";844;0
"Unit";"Zergling";"Larva";842;1
"Unit";"Zergling";"Larva";842;1
"Unit";"Zergling";"Larva";842;1
"Unit";"Zergling";"Larva";842;1
"Unit";"Zergling";"Larva";842;1
"Unit";"Zergling";"Larva";842;1
"Unit";"Zergling";"Larva";842;1
"Unit";"Zergling";"Larva";842;1
"Unit";"Zergling";"Larva";848;1
"Unit";"Zergling";"Larva";848;1
"Unit";"Zergling";"Larva";848;1
"Unit";"Zergling";"Larva";848;1
"Unit";"Zergling";"Larva";848;1
"Unit";"Zergling";"Larva";848;1
"Unit";"Zergling";"Larva";860;1
"Unit";"Zergling";"Larva";860;1
"Unit";"Zergling";"Larva";860;1
"Unit";"Zergling";"Larva";860;1
"Unit";"Zergling";"Larva";860;1
"Unit";"Zergling";"Larva";860;1
"Unit";"Zergling";"Larva";860;1
"Unit";"Zergling";"Larva";860;1
"Unit";"Zergling";"Larva";862;1
"Unit";"Zergling";"Larva";862;1
"Unit";"Zergling";"Larva";862;1
"Unit";"Zergling";"Larva";862;1
"Unit";"Zergling";"Larva";864;1
"Unit";"Zergling";"Larva";864;1
"Unit";"Zergling";"Larva";864;1
"Unit";"Zergling";"Larva";864;1
"Unit";"Zergling";"Larva";864;1
"Unit";"Zergling";"Larva";864;1
"Unit";"Zergling";"Larva";868;1
"Unit";"Zergling";"Larva";868;1
"Unit";"Zergling";"Larva";868;1
"Unit";"Zergling";"Larva";868;1
"Building";"CreepTumor";NA;874;0
"Unit";"Zergling";"Larva";874;1
"Unit";"Zergling";"Larva";874;1
"Building";"CreepTumor";NA;874;0
"Unit";"Zergling";"Larva";874;1
"Unit";"Zergling";"Larva";874;1
"Building";"CreepTumorQueen";NA;874;0
"Unit";"Zergling";"Larva";874;1
"Unit";"Zergling";"Larva";874;1
"Unit";"Zergling";"Larva";874;1
"Unit";"Zergling";"Larva";874;1
"Unit";"Zergling";"Larva";874;1
"Unit";"Zergling";"Larva";874;1
"Unit";"Zergling";"Larva";874;1
"Unit";"Zergling";"Larva";874;1
"Unit";"Zergling";"Larva";874;1
"Unit";"Zergling";"Larva";874;1
"Unit";"Zergling";"Larva";874;1
"Unit";"Zergling";"Larva";874;1
"Unit";"Zergling";"Larva";874;1
"Unit";"Zergling";"Larva";874;1
"Unit";"Zergling";"Larva";874;1
"Unit";"Zergling";"Larva";874;1
"Unit";"Baneling";"Zergling";896;0
"Unit";"Baneling";"Zergling";896;0
"Unit";"Zergling";"Larva";896;1
"Unit";"Zergling";"Larva";896;1
"Unit";"Zergling";"Larva";896;1
"Unit";"Zergling";"Larva";896;1
"Unit";"Zergling";"Larva";896;1
"Unit";"Zergling";"Larva";896;1
"Unit";"Zergling";"Larva";896;1
"Unit";"Zergling";"Larva";896;1
"Unit";"Baneling";"Zergling";916;0
"Unit";"Zergling";"Larva";912;1
"Unit";"Zergling";"Larva";912;1
"Unit";"Zergling";"Larva";912;1
"Unit";"Zergling";"Larva";912;1
"Unit";"Zergling";"Larva";912;1
"Unit";"Zergling";"Larva";912;1
"Unit";"Zergling";"Larva";912;1
"Unit";"Zergling";"Larva";912;1
"Unit";"Zergling";"Larva";912;1
"Unit";"Zergling";"Larva";912;1
"Unit";"Zergling";"Larva";912;1
"Unit";"Zergling";"Larva";912;1
"Unit";"Zergling";"Larva";912;1
"Unit";"Zergling";"Larva";912;1
"Unit";"Zergling";"Larva";924;1
"Unit";"Zergling";"Larva";924;1
"Unit";"Zergling";"Larva";924;1
"Unit";"Zergling";"Larva";924;1
"Unit";"Zergling";"Larva";924;1
"Unit";"Zergling";"Larva";924;1
"Unit";"Zergling";"Larva";924;1
"Unit";"Zergling";"Larva";924;1
"Unit";"Zergling";"Larva";924;1
"Unit";"Zergling";"Larva";924;1
"Unit";"Zergling";"Larva";924;1
"Unit";"Zergling";"Larva";924;1
"Unit";"Zergling";"Larva";924;1
"Unit";"Zergling";"Larva";924;1
"Unit";"Zergling";"Larva";924;1
"Unit";"Zergling";"Larva";924;1
"Unit";"Zergling";"Larva";924;1
"Unit";"Zergling";"Larva";924;1
"Unit";"Zergling";"Larva";924;1
"Unit";"Zergling";"Larva";924;1
"Unit";"Zergling";"Larva";924;1
"Unit";"Zergling";"Larva";924;1
"Unit";"Zergling";"Larva";938;1
"Unit";"Zergling";"Larva";938;1
"Unit";"Zergling";"Larva";938;1
"Unit";"Zergling";"Larva";938;1
"Unit";"Zergling";"Larva";938;1
"Unit";"Zergling";"Larva";938;1
"Unit";"Zergling";"Larva";938;1
"Unit";"Zergling";"Larva";938;1
"Unit";"Zergling";"Larva";960;1
"Unit";"Zergling";"Larva";960;1
"Unit";"Zergling";"Larva";960;1
"Unit";"Zergling";"Larva";960;1
"Unit";"Zergling";"Larva";960;1
"Unit";"Zergling";"Larva";960;1
"Unit";"Zergling";"Larva";960;1
"Unit";"Zergling";"Larva";960;1
"Unit";"Zergling";"Larva";960;1
"Unit";"Zergling";"Larva";960;1
"Unit";"Zergling";"Larva";960;1
"Unit";"Zergling";"Larva";960;1
"Unit";"Zergling";"Larva";960;1
"Unit";"Zergling";"Larva";960;1
"Unit";"Ultralisk";"Larva";938;6
"Unit";"Zergling";"Larva";968;1
"Unit";"Zergling";"Larva";968;1
"Unit";"Zergling";"Larva";968;1
"Unit";"Zergling";"Larva";968;1
"Unit";"Zergling";"Larva";968;1
"Unit";"Zergling";"Larva";968;1
"Unit";"Zergling";"Larva";968;1
"Unit";"Zergling";"Larva";968;1
"Unit";"Zergling";"Larva";968;1
"Unit";"Zergling";"Larva";968;1
"Unit";"Zergling";"Larva";968;1
"Unit";"Zergling";"Larva";968;1
"Unit";"Baneling";"Zergling";982;0
"Unit";"Baneling";"Zergling";982;0
"Unit";"Baneling";"Zergling";982;0
"Unit";"Baneling";"Zergling";982;0
"Unit";"Baneling";"Zergling";982;0
"Unit";"Baneling";"Zergling";982;0
"Unit";"Baneling";"Zergling";982;0
"Unit";"Baneling";"Zergling";982;0
"Unit";"Baneling";"Zergling";982;0
"Unit";"Baneling";"Zergling";982;0
"Unit";"Baneling";"Zergling";982;0
"Unit";"Baneling";"Zergling";982;0
"Unit";"Baneling";"Zergling";1000;0
"Unit";"Baneling";"Zergling";1000;0
"Unit";"Baneling";"Zergling";1000;0
"Unit";"Baneling";"Zergling";1000;0
"Unit";"Baneling";"Zergling";1000;0
"Unit";"Zergling";"Larva";1000;1
"Unit";"Zergling";"Larva";1000;1
"Unit";"Zergling";"Larva";1000;1
"Unit";"Zergling";"Larva";1000;1
"Unit";"Zergling";"Larva";1000;1
"Unit";"Zergling";"Larva";1000;1
"Unit";"Zergling";"Larva";1000;1
"Unit";"Zergling";"Larva";1000;1
"Unit";"Zergling";"Larva";1000;1
"Unit";"Zergling";"Larva";1000;1
"Unit";"Zergling";"Larva";1000;1
"Unit";"Zergling";"Larva";1000;1
"Unit";"Zergling";"Larva";1000;1
"Unit";"Zergling";"Larva";1000;1
"Unit";"Zergling";"Larva";1000;1
"Unit";"Zergling";"Larva";1000;1
"Unit";"Baneling";"Zergling";1016;0
"Unit";"Baneling";"Zergling";1016;0
"Unit";"Baneling";"Zergling";1016;0
"Unit";"Baneling";"Zergling";1016;0
"Unit";"Baneling";"Zergling";1016;0
"Unit";"Baneling";"Zergling";1016;0
"Building";"CreepTumorQueen";NA;1016;0
"Unit";"Baneling";"Zergling";1016;0
"Unit";"Zergling";"Larva";1016;1
"Unit";"Zergling";"Larva";1016;1
"Unit";"Zergling";"Larva";1016;1
"Unit";"Zergling";"Larva";1016;1
"Building";"CreepTumorQueen";NA;1016;0
"Building";"Hatchery";NA;982;0
"Unit";"Baneling";"Zergling";1016;0
"Unit";"Baneling";"Zergling";1016;0
"Unit";"Zergling";"Larva";1020;1
"Unit";"Zergling";"Larva";1020;1
"Unit";"Zergling";"Larva";1020;1
"Unit";"Zergling";"Larva";1020;1
"Unit";"Zergling";"Larva";1020;1
"Unit";"Zergling";"Larva";1020;1
"Unit";"Zergling";"Larva";1020;1
"Unit";"Zergling";"Larva";1020;1
"Unit";"Zergling";"Larva";1020;1
"Unit";"Zergling";"Larva";1020;1
"Unit";"Zergling";"Larva";1020;1
"Unit";"Zergling";"Larva";1020;1
"Unit";"Zergling";"Larva";1020;1
"Unit";"Zergling";"Larva";1020;1
"Unit";"Zergling";"Larva";1020;1
"Unit";"Zergling";"Larva";1020;1
"Unit";"Zergling";"Larva";1020;1
"Unit";"Zergling";"Larva";1020;1
"Unit";"Zergling";"Larva";1020;1
"Unit";"Zergling";"Larva";1020;1
"Unit";"Zergling";"Larva";1020;1
"Unit";"Zergling";"Larva";1020;1
"Unit";"Baneling";"Zergling";1042;0
"Unit";"Baneling";"Zergling";1042;0
"Unit";"Baneling";"Zergling";1042;0
"Building";"CreepTumor";NA;1042;0
"Unit";"Baneling";"Zergling";1042;0
"Building";"CreepTumor";NA;1042;0
"Unit";"Baneling";"Zergling";1042;0
"Building";"CreepTumor";NA;1042;0
"Building";"CreepTumor";NA;1042;0
"Building";"CreepTumor";NA;1042;0
"Unit";"Zergling";"Larva";1042;1
"Unit";"Zergling";"Larva";1042;1
"Unit";"Zergling";"Larva";1042;1
"Unit";"Zergling";"Larva";1042;1
"Unit";"Zergling";"Larva";1042;1
"Unit";"Zergling";"Larva";1042;1
"Unit";"Zergling";"Larva";1042;1
"Unit";"Zergling";"Larva";1042;1
"Unit";"Zergling";"Larva";1042;1
"Unit";"Zergling";"Larva";1042;1
"Unit";"Zergling";"Larva";1042;1
"Unit";"Zergling";"Larva";1042;1
"Unit";"Zergling";"Larva";1042;1
"Unit";"Zergling";"Larva";1042;1
"Unit";"Infestor";"Larva";1020;2
"Unit";"Infestor";"Larva";1020;2
"Unit";"Zergling";"Larva";1042;1
"Unit";"Zergling";"Larva";1042;1
"Building";"Hatchery";NA;1016;0
"Unit";"Zergling";"Larva";1062;1
"Unit";"Zergling";"Larva";1062;1
"Unit";"Zergling";"Larva";1062;1
"Unit";"Zergling";"Larva";1062;1
"Unit";"Zergling";"Larva";1062;1
"Unit";"Zergling";"Larva";1062;1
"Unit";"Zergling";"Larva";1062;1
"Unit";"Zergling";"Larva";1062;1
"Unit";"Zergling";"Larva";1062;1
"Unit";"Zergling";"Larva";1062;1
"Unit";"Zergling";"Larva";1062;1
"Unit";"Zergling";"Larva";1062;1
"Unit";"Zergling";"Larva";1062;1
"Unit";"Zergling";"Larva";1062;1
"Unit";"Zergling";"Larva";1062;1
"Unit";"Zergling";"Larva";1062;1
"Unit";"Zergling";"Larva";1062;1
"Unit";"Zergling";"Larva";1062;1
"Unit";"Zergling";"Larva";1062;1
"Unit";"Zergling";"Larva";1062;1
"Unit";"Zergling";"Larva";1062;1
"Unit";"Zergling";"Larva";1062;1
"Unit";"Baneling";"Zergling";1062;0
"Unit";"Baneling";"Zergling";1062;0
"Unit";"Baneling";"Zergling";1062;0
"Unit";"Baneling";"Zergling";1062;0
"Unit";"Baneling";"Zergling";1062;0
"Unit";"Baneling";"Zergling";1062;0
"Unit";"Baneling";"Zergling";1062;0
"Unit";"Zergling";"Larva";1062;1
"Unit";"Zergling";"Larva";1062;1
"Unit";"Zergling";"Larva";1062;1
"Unit";"Zergling";"Larva";1062;1
"Unit";"Infestor";"Larva";1062;2
"Unit";"Infestor";"Larva";1062;2
"Unit";"Overlord";"Larva";1084;0
"Unit";"Baneling";"Zergling";1084;0
"Unit";"Baneling";"Zergling";1084;0
"Unit";"Zergling";"Larva";1084;1
"Unit";"Zergling";"Larva";1084;1
"Unit";"Zergling";"Larva";1084;1
"Unit";"Zergling";"Larva";1084;1
"Unit";"Zergling";"Larva";1084;1
"Unit";"Zergling";"Larva";1084;1
"Unit";"Zergling";"Larva";1084;1
"Unit";"Zergling";"Larva";1084;1
"Unit";"Baneling";"Zergling";1100;0
"Unit";"Baneling";"Zergling";1100;0
"Unit";"Baneling";"Zergling";1100;0
"Unit";"Baneling";"Zergling";1100;0
"Unit";"Baneling";"Zergling";1100;0
"Unit";"Baneling";"Zergling";1100;0
"Unit";"Baneling";"Zergling";1100;0
"Unit";"Baneling";"Zergling";1100;0
"Unit";"Baneling";"Zergling";1100;0
"Unit";"Baneling";"Zergling";1100;0
"Unit";"Baneling";"Zergling";1100;0
"Unit";"Zergling";"Larva";1100;1
"Unit";"Zergling";"Larva";1100;1
"Unit";"Zergling";"Larva";1100;1
"Unit";"Zergling";"Larva";1100;1
"Unit";"Zergling";"Larva";1100;1
"Unit";"Zergling";"Larva";1100;1
"Unit";"Zergling";"Larva";1100;1
"Unit";"Zergling";"Larva";1100;1
"Unit";"Zergling";"Larva";1100;1
"Unit";"Zergling";"Larva";1100;1
"Unit";"Zergling";"Larva";1100;1
"Unit";"Zergling";"Larva";1100;1
"Unit";"Zergling";"Larva";1100;1
"Unit";"Zergling";"Larva";1100;1
"Unit";"Infestor";"Larva";1092;2
"Unit";"Infestor";"Larva";1092;2
"Unit";"Infestor";"Larva";1092;2
"Unit";"Zergling";"Larva";1100;1
"Unit";"Zergling";"Larva";1100;1
"Unit";"Zergling";"Larva";1100;1
"Unit";"Zergling";"Larva";1100;1
"Unit";"Zergling";"Larva";1100;1
"Unit";"Zergling";"Larva";1100;1
"Unit";"Zergling";"Larva";1100;1
"Unit";"Zergling";"Larva";1100;1
"Unit";"Baneling";"Zergling";1128;0
"Unit";"Baneling";"Zergling";1128;0
"Unit";"Baneling";"Zergling";1128;0
"Unit";"Baneling";"Zergling";1128;0
"Unit";"Baneling";"Zergling";1128;0
"Unit";"Baneling";"Zergling";1128;0
"Unit";"Baneling";"Zergling";1128;0
"Unit";"Baneling";"Zergling";1128;0
"Unit";"Baneling";"Zergling";1128;0
"Unit";"Baneling";"Zergling";1128;0
"Unit";"Zergling";"Larva";1128;1
"Unit";"Zergling";"Larva";1128;1
"Unit";"Zergling";"Larva";1128;1
"Unit";"Zergling";"Larva";1128;1
"Unit";"Zergling";"Larva";1128;1
"Unit";"Zergling";"Larva";1128;1
"Unit";"Zergling";"Larva";1128;1
"Unit";"Zergling";"Larva";1128;1
"Unit";"Zergling";"Larva";1128;1
"Unit";"Zergling";"Larva";1128;1
"Unit";"Zergling";"Larva";1128;1
"Unit";"Zergling";"Larva";1128;1
"Unit";"Zergling";"Larva";1128;1
"Unit";"Zergling";"Larva";1128;1
"Unit";"Zergling";"Larva";1128;1
"Unit";"Zergling";"Larva";1128;1
"Unit";"Zergling";"Larva";1128;1
"Unit";"Zergling";"Larva";1128;1
"Unit";"Zergling";"Larva";1128;1
"Unit";"Zergling";"Larva";1128;1
"Unit";"Zergling";"Larva";1128;1
"Unit";"Zergling";"Larva";1128;1
"Unit";"Zergling";"Larva";1128;1
"Unit";"Zergling";"Larva";1128;1
"Unit";"Zergling";"Larva";1128;1
"Unit";"Zergling";"Larva";1128;1
"Unit";"Zergling";"Larva";1128;1
"Unit";"Zergling";"Larva";1128;1
"Unit";"Zergling";"Larva";1128;1
"Unit";"Zergling";"Larva";1128;1
"Unit";"Zergling";"Larva";1128;1
"Unit";"Zergling";"Larva";1128;1
"Unit";"Zergling";"Larva";1128;1
"Unit";"Zergling";"Larva";1128;1
"Unit";"Zergling";"Larva";1128;1
"Unit";"Zergling";"Larva";1128;1
"Unit";"Zergling";"Larva";1128;1
"Unit";"Zergling";"Larva";1128;1
"Unit";"Baneling";"Zergling";1128;0
"Unit";"Baneling";"Zergling";1128;0
"Unit";"Baneling";"Zergling";1128;0
"Unit";"Baneling";"Zergling";1128;0
"Unit";"Baneling";"Zergling";1128;0
"Unit";"Baneling";"Zergling";1128;0
"Unit";"Zergling";"Larva";1128;1
"Unit";"Zergling";"Larva";1128;1
"Unit";"Zergling";"Larva";1128;1
"Unit";"Zergling";"Larva";1128;1
"Unit";"Zergling";"Larva";1128;1
"Unit";"Zergling";"Larva";1128;1
"Unit";"Zergling";"Larva";1128;1
"Unit";"Zergling";"Larva";1128;1
"Unit";"Zergling";"Larva";1150;1
"Unit";"Zergling";"Larva";1150;1
"Unit";"Zergling";"Larva";1150;1
"Unit";"Zergling";"Larva";1150;1
"Unit";"Zergling";"Larva";1150;1
"Unit";"Zergling";"Larva";1150;1
"Unit";"Zergling";"Larva";1152;1
"Unit";"Zergling";"Larva";1152;1
"Unit";"Zergling";"Larva";1152;1
"Unit";"Zergling";"Larva";1152;1
"Unit";"Zergling";"Larva";1166;1
"Unit";"Zergling";"Larva";1166;1
"Unit";"Zergling";"Larva";1166;1
"Unit";"Zergling";"Larva";1166;1
"Unit";"Zergling";"Larva";1166;1
"Unit";"Zergling";"Larva";1166;1
"Unit";"Zergling";"Larva";1166;1
"Unit";"Zergling";"Larva";1166;1
"Unit";"Baneling";"Zergling";1174;0
"Unit";"Zergling";"Larva";1174;1
"Unit";"Zergling";"Larva";1174;1
"Unit";"Zergling";"Larva";1174;1
"Unit";"Zergling";"Larva";1174;1
"Unit";"Zergling";"Larva";1174;1
"Unit";"Zergling";"Larva";1174;1
"Unit";"Zergling";"Larva";1174;1
"Unit";"Zergling";"Larva";1174;1
"Unit";"Zergling";"Larva";1174;1
"Unit";"Zergling";"Larva";1174;1
"Unit";"Zergling";"Larva";1192;1
"Unit";"Zergling";"Larva";1192;1
"Unit";"Zergling";"Larva";1192;1
"Unit";"Zergling";"Larva";1192;1
"Unit";"Zergling";"Larva";1192;1
"Unit";"Zergling";"Larva";1192;1
"Unit";"Zergling";"Larva";1192;1
"Unit";"Zergling";"Larva";1192;1
"Unit";"Zergling";"Larva";1192;1
"Unit";"Zergling";"Larva";1192;1
"Unit";"Zergling";"Larva";1192;1
"Unit";"Zergling";"Larva";1192;1
"Unit";"Baneling";"Zergling";1202;0
"Unit";"Baneling";"Zergling";1202;0
"Unit";"Baneling";"Zergling";1202;0
