"type";"unit_name";"on_building";"total_supply";"supply"
"Building";"Extractor";NA;13;0
"Unit";"Overlord";"Larva";15;0
"Building";"SpawningPool";NA;15;0
"Unit";"Zergling";"Larva";18;1
"Unit";"Zergling";"Larva";18;1
"Unit";"Zergling";"Larva";18;1
"Unit";"Zergling";"Larva";18;1
"Unit";"Zergling";"Larva";18;1
"Unit";"Zergling";"Larva";18;1
"Unit";"Overlord";"Larva";25;0
"Unit";"Zergling";"Larva";25;1
"Unit";"Zergling";"Larva";25;1
"Unit";"Queen";"Hatchery";25;2
"Unit";"Zergling";"Larva";25;1
"Unit";"Zergling";"Larva";25;1
"Unit";"Zergling";"Larva";25;1
"Unit";"Zergling";"Larva";25;1
"Unit";"Zergling";"Larva";27;1
"Unit";"Zergling";"Larva";27;1
"Building";"Hatchery";NA;25;0
"Unit";"Queen";"Hatchery";27;2
"Building";"CreepTumorQueen";NA;37;0
"Unit";"Queen";"Hatchery";37;2
"Building";"CreepTumor";NA;45;0
"Unit";"Overlord";"Larva";45;0
"Unit";"Overlord";"Larva";45;0
"Building";"CreepTumorQueen";NA;47;0
"Building";"Hatchery";NA;39;0
"Unit";"Overlord";"Larva";47;0
"Building";"CreepTumorQueen";NA;54;0
"Building";"CreepTumor";NA;54;0
"Building";"CreepTumor";NA;54;0
"Unit";"Queen";"Hatchery";47;2
"Building";"CreepTumorQueen";NA;56;0
"Unit";"Queen";"Hatchery";60;2
"Building";"SporeCrawler";NA;66;0
"Building";"SporeCrawler";NA;66;0
"Unit";"Zergling";"Larva";71;1
"Unit";"Zergling";"Larva";71;1
"Unit";"Zergling";"Larva";71;1
"Unit";"Zergling";"Larva";71;1
"Building";"SporeCrawler";NA;67;0
"Unit";"Zergling";"Larva";71;1
"Unit";"Zergling";"Larva";71;1
"Unit";"Zergling";"Larva";71;1
"Unit";"Zergling";"Larva";71;1
"Unit";"Zergling";"Larva";73;1
"Unit";"Zergling";"Larva";73;1
"Unit";"Zergling";"Larva";80;1
"Unit";"Zergling";"Larva";80;1
"Unit";"Zergling";"Larva";80;1
"Unit";"Zergling";"Larva";80;1
"Unit";"Zergling";"Larva";80;1
"Unit";"Zergling";"Larva";80;1
"Unit";"Zergling";"Larva";82;1
"Unit";"Zergling";"Larva";82;1
"Unit";"Zergling";"Larva";82;1
"Unit";"Zergling";"Larva";82;1
"Unit";"Zergling";"Larva";82;1
"Unit";"Zergling";"Larva";82;1
"Unit";"Zergling";"Larva";82;1
"Unit";"Zergling";"Larva";82;1
"Building";"CreepTumor";NA;86;0
"Building";"CreepTumor";NA;100;0
"Building";"CreepTumor";NA;102;0
"Building";"CreepTumor";NA;102;0
"Building";"CreepTumorQueen";NA;104;0
"Building";"CreepTumorQueen";NA;104;0
"Unit";"Overlord";"Larva";104;0
"Unit";"Overlord";"Larva";104;0
"Unit";"Overlord";"Larva";104;0
"Building";"Extractor";NA;104;0
"Building";"Extractor";NA;104;0
"Building";"Extractor";NA;104;0
"Building";"Extractor";NA;104;0
"Building";"Extractor";NA;107;0
"Building";"SporeCrawler";NA;124;0
"Unit";"Overlord";"Larva";126;0
"Building";"CreepTumor";NA;132;0
"Building";"CreepTumor";NA;132;0
"Building";"CreepTumor";NA;132;0
"Building";"CreepTumor";NA;132;0
"Building";"CreepTumorQueen";NA;132;0
"Building";"CreepTumor";NA;132;0
"Building";"CreepTumorQueen";NA;132;0
"Unit";"Overlord";"Larva";132;0
"Unit";"Overlord";"Larva";132;0
"Building";"CreepTumor";NA;132;0
"Building";"CreepTumorQueen";NA;135;0
"Building";"EvolutionChamber";NA;131;0
"Building";"CreepTumorQueen";NA;135;0
"Building";"EvolutionChamber";NA;131;0
"Unit";"Overlord";"Larva";132;0
"Unit";"Overlord";"Larva";132;0
"Building";"Spire";NA;108;0
"Building";"BanelingNest";NA;131;0
"Building";"CreepTumor";NA;141;0
"Building";"CreepTumor";NA;141;0
"Building";"CreepTumor";NA;141;0
"Building";"CreepTumor";NA;141;0
"Building";"CreepTumor";NA;141;0
"Unit";"Mutalisk";"Larva";137;2
"Unit";"Mutalisk";"Larva";137;2
"Unit";"Mutalisk";"Larva";137;2
"Unit";"Mutalisk";"Larva";137;2
"Unit";"Mutalisk";"Larva";137;2
"Unit";"Mutalisk";"Larva";137;2
"Unit";"Mutalisk";"Larva";137;2
"Unit";"Mutalisk";"Larva";139;2
"Unit";"Mutalisk";"Larva";141;2
"Unit";"Mutalisk";"Larva";141;2
"Building";"CreepTumor";NA;141;0
"Building";"CreepTumor";NA;141;0
"Building";"CreepTumor";NA;141;0
"Building";"CreepTumor";NA;141;0
"Unit";"Zergling";"Larva";162;1
"Unit";"Zergling";"Larva";162;1
"Unit";"Zergling";"Larva";162;1
"Unit";"Zergling";"Larva";162;1
"Unit";"Zergling";"Larva";162;1
"Unit";"Zergling";"Larva";162;1
"Unit";"Zergling";"Larva";162;1
"Unit";"Zergling";"Larva";162;1
"Unit";"Zergling";"Larva";162;1
"Unit";"Zergling";"Larva";162;1
"Unit";"Zergling";"Larva";162;1
"Unit";"Zergling";"Larva";162;1
"Unit";"Zergling";"Larva";162;1
"Unit";"Zergling";"Larva";162;1
"Unit";"Zergling";"Larva";162;1
"Unit";"Zergling";"Larva";162;1
"Unit";"Zergling";"Larva";162;1
"Unit";"Zergling";"Larva";162;1
"Unit";"Zergling";"Larva";162;1
"Unit";"Zergling";"Larva";162;1
"Unit";"Zergling";"Larva";162;1
"Unit";"Zergling";"Larva";162;1
"Unit";"Zergling";"Larva";162;1
"Unit";"Zergling";"Larva";162;1
"Building";"Hatchery";NA;135;0
"Building";"CreepTumor";NA;187;0
"Building";"CreepTumor";NA;187;0
"Building";"CreepTumor";NA;187;0
"Building";"CreepTumor";NA;187;0
"Building";"SporeCrawler";NA;187;0
"Building";"InfestationPit";NA;162;0
"Unit";"Queen";"Hatchery";162;2
"Unit";"Zergling";"Larva";189;1
"Unit";"Zergling";"Larva";189;1
"Unit";"Zergling";"Larva";190;1
"Unit";"Zergling";"Larva";190;1
"Unit";"Zergling";"Larva";190;1
"Unit";"Zergling";"Larva";190;1
"Unit";"Zergling";"Larva";190;1
"Unit";"Zergling";"Larva";190;1
"Building";"CreepTumor";NA;196;0
"Building";"CreepTumor";NA;198;0
"Building";"SpineCrawler";NA;187;0
"Building";"CreepTumor";NA;198;0
"Building";"CreepTumor";NA;198;0
"Building";"Hatchery";NA;155;0
"Building";"CreepTumor";NA;198;0
"Unit";"Zergling";"Larva";196;1
"Unit";"Zergling";"Larva";196;1
"Unit";"Zergling";"Larva";196;1
"Unit";"Zergling";"Larva";196;1
"Unit";"Zergling";"Larva";196;1
"Unit";"Zergling";"Larva";196;1
"Unit";"Zergling";"Larva";196;1
"Unit";"Zergling";"Larva";196;1
"Unit";"Zergling";"Larva";196;1
"Unit";"Zergling";"Larva";196;1
"Unit";"Zergling";"Larva";196;1
"Unit";"Zergling";"Larva";196;1
"Unit";"Overlord";"Larva";206;0
"Unit";"Overlord";"Larva";206;0
"Unit";"Queen";"Hatchery";196;2
"Unit";"Mutalisk";"Larva";210;2
"Unit";"Mutalisk";"Larva";210;2
"Unit";"Mutalisk";"Larva";210;2
"Unit";"Mutalisk";"Larva";210;2
"Unit";"Overlord";"Larva";222;0
"Unit";"Overlord";"Larva";222;0
"Building";"Extractor";NA;232;0
"Building";"Extractor";NA;232;0
"Unit";"Baneling";"Zergling";232;0
"Unit";"Baneling";"Zergling";232;0
"Unit";"Baneling";"Zergling";232;0
"Unit";"Zergling";"Larva";232;1
"Unit";"Zergling";"Larva";232;1
"Unit";"Baneling";"Zergling";232;0
"Unit";"Zergling";"Larva";232;1
"Unit";"Zergling";"Larva";232;1
"Unit";"Zergling";"Larva";232;1
"Unit";"Zergling";"Larva";232;1
"Unit";"Zergling";"Larva";232;1
"Unit";"Zergling";"Larva";232;1
"Unit";"Mutalisk";"Larva";232;2
"Unit";"Mutalisk";"Larva";232;2
"Unit";"Mutalisk";"Larva";232;2
"Unit";"Mutalisk";"Larva";232;2
"Unit";"Mutalisk";"Larva";232;2
"Unit";"Mutalisk";"Larva";232;2
"Upgrade";"ZergMeleeWeaponsLevel1";"EvolutionChamber";187;0
"Upgrade";"ZergGroundArmorsLevel1";"EvolutionChamber";189;0
"Unit";"Zergling";"Larva";256;1
"Unit";"Zergling";"Larva";256;1
"Unit";"Overlord";"Larva";256;0
"Unit";"Overlord";"Larva";256;0
"Unit";"Overlord";"Larva";256;0
"Unit";"Overlord";"Larva";256;0
"Unit";"Overlord";"Larva";256;0
"Unit";"Overlord";"Larva";256;0
"Unit";"Overlord";"Larva";256;0
"Unit";"Overlord";"Larva";256;0
"Unit";"Overlord";"Larva";256;0
"Unit";"Overlord";"Larva";256;0
"Unit";"Overlord";"Larva";258;0
"Building";"CreepTumor";NA;258;0
"Building";"CreepTumor";NA;258;0
"Building";"CreepTumor";NA;258;0
"Building";"CreepTumor";NA;258;0
"Building";"CreepTumor";NA;258;0
"Building";"SporeCrawler";NA;258;0
"Unit";"Baneling";"Zergling";258;0
"Unit";"Baneling";"Zergling";258;0
"Unit";"Baneling";"Zergling";258;0
"Unit";"Baneling";"Zergling";258;0
"Unit";"Baneling";"Zergling";258;0
"Unit";"Baneling";"Zergling";258;0
"Unit";"Baneling";"Zergling";258;0
"Unit";"Baneling";"Zergling";258;0
"Unit";"Baneling";"Zergling";258;0
"Unit";"Baneling";"Zergling";258;0
"Unit";"Baneling";"Zergling";258;0
"Unit";"Baneling";"Zergling";258;0
"Unit";"Baneling";"Zergling";258;0
"Unit";"Baneling";"Zergling";258;0
"Unit";"Baneling";"Zergling";258;0
"Unit";"Baneling";"Zergling";258;0
"Unit";"Baneling";"Zergling";258;0
"Building";"Hatchery";NA;232;0
"Unit";"Zergling";"Larva";258;1
"Unit";"Zergling";"Larva";258;1
"Unit";"Zergling";"Larva";258;1
"Unit";"Zergling";"Larva";258;1
"Unit";"Zergling";"Larva";258;1
"Unit";"Zergling";"Larva";258;1
"Unit";"Zergling";"Larva";258;1
"Unit";"Zergling";"Larva";258;1
"Unit";"Zergling";"Larva";258;1
"Unit";"Zergling";"Larva";258;1
"Building";"SpineCrawler";NA;258;0
"Upgrade";"Burrow";"Hatchery";258;0
"Unit";"Zergling";"Larva";273;1
"Unit";"Zergling";"Larva";273;1
"Unit";"Zergling";"Larva";273;1
"Unit";"Zergling";"Larva";273;1
"Unit";"Zergling";"Larva";273;1
"Unit";"Zergling";"Larva";273;1
"Unit";"Zergling";"Larva";273;1
"Unit";"Zergling";"Larva";273;1
"Unit";"Zergling";"Larva";273;1
"Unit";"Zergling";"Larva";273;1
"Unit";"Zergling";"Larva";273;1
"Unit";"Zergling";"Larva";273;1
"Unit";"Zergling";"Larva";273;1
"Unit";"Zergling";"Larva";273;1
"Unit";"Zergling";"Larva";273;1
"Unit";"Zergling";"Larva";273;1
"Unit";"Zergling";"Larva";273;1
"Unit";"Zergling";"Larva";273;1
"Unit";"Zergling";"Larva";273;1
"Unit";"Zergling";"Larva";273;1
"Unit";"Baneling";"Zergling";273;0
"Unit";"Zergling";"Larva";273;1
"Unit";"Zergling";"Larva";273;1
"Unit";"Zergling";"Larva";273;1
"Unit";"Zergling";"Larva";273;1
"Unit";"Zergling";"Larva";273;1
"Unit";"Zergling";"Larva";273;1
"Unit";"Zergling";"Larva";273;1
"Unit";"Zergling";"Larva";273;1
"Unit";"Baneling";"Zergling";273;0
"Unit";"Baneling";"Zergling";273;0
"Unit";"Baneling";"Zergling";273;0
"Unit";"Baneling";"Zergling";273;0
"Unit";"Baneling";"Zergling";273;0
"Building";"CreepTumor";NA;273;0
"Unit";"Zergling";"Larva";301;1
"Unit";"Zergling";"Larva";301;1
"Unit";"Zergling";"Larva";301;1
"Unit";"Zergling";"Larva";301;1
"Unit";"Zergling";"Larva";301;1
"Unit";"Zergling";"Larva";301;1
"Unit";"Zergling";"Larva";301;1
"Unit";"Zergling";"Larva";301;1
"Unit";"Zergling";"Larva";301;1
"Unit";"Zergling";"Larva";301;1
"Unit";"Zergling";"Larva";301;1
"Unit";"Zergling";"Larva";301;1
"Unit";"Zergling";"Larva";301;1
"Unit";"Zergling";"Larva";301;1
"Unit";"Zergling";"Larva";301;1
"Unit";"Zergling";"Larva";301;1
"Unit";"Zergling";"Larva";301;1
"Unit";"Zergling";"Larva";301;1
"Unit";"Zergling";"Larva";301;1
"Unit";"Zergling";"Larva";301;1
"Unit";"Zergling";"Larva";301;1
"Unit";"Zergling";"Larva";301;1
"Unit";"Zergling";"Larva";301;1
"Unit";"Zergling";"Larva";301;1
"Unit";"Zergling";"Larva";301;1
"Unit";"Zergling";"Larva";301;1
"Unit";"Zergling";"Larva";301;1
"Unit";"Zergling";"Larva";301;1
"Unit";"Zergling";"Larva";301;1
"Unit";"Zergling";"Larva";301;1
"Unit";"Zergling";"Larva";301;1
"Unit";"Zergling";"Larva";301;1
"Unit";"Zergling";"Larva";301;1
"Unit";"Zergling";"Larva";301;1
"Building";"UltraliskCavern";NA;268;0
