"type";"unit_name";"on_building";"total_supply";"supply"
"Unit";"Overlord";"Larva";12;0
"Building";"Extractor";NA;17;0
"Building";"SpawningPool";NA;17;0
"Unit";"Zergling";"Larva";21;1
"Unit";"Zergling";"Larva";21;1
"Unit";"Overlord";"Larva";21;0
"Unit";"Queen";"Hatchery";21;2
"Unit";"Zergling";"Larva";23;1
"Unit";"Zergling";"Larva";23;1
"Building";"Hatchery";NA;19;0
"Unit";"Queen";"Hatchery";24;2
"Unit";"Overlord";"Larva";36;0
"Building";"CreepTumorQueen";NA;40;0
"Unit";"Zergling";"Larva";40;1
"Unit";"Zergling";"Larva";40;1
"Unit";"Zergling";"Larva";40;1
"Unit";"Zergling";"Larva";40;1
"Unit";"Overlord";"Larva";40;0
"Unit";"Queen";"Hatchery";39;2
"Unit";"Overlord";"Larva";40;0
"Unit";"Overlord";"Larva";42;0
"Building";"Extractor";NA;46;0
"Building";"CreepTumor";NA;52;0
"Building";"Hatchery";NA;35;0
"Building";"CreepTumorQueen";NA;54;0
"Unit";"Overlord";"Larva";56;0
"Building";"SporeCrawler";NA;56;0
"Building";"SporeCrawler";NA;56;0
"Building";"CreepTumor";NA;62;0
"Building";"CreepTumor";NA;62;0
"Building";"SporeCrawler";NA;61;0
"Unit";"Queen";"Hatchery";60;2
"Unit";"Zergling";"Larva";62;1
"Unit";"Zergling";"Larva";62;1
"Unit";"Zergling";"Larva";62;1
"Unit";"Zergling";"Larva";62;1
"Unit";"Queen";"Hatchery";60;2
"Unit";"Zergling";"Larva";62;1
"Unit";"Zergling";"Larva";62;1
"Unit";"Zergling";"Larva";62;1
"Unit";"Zergling";"Larva";62;1
"Building";"EvolutionChamber";NA;62;0
"Building";"BanelingNest";NA;62;0
"Building";"CreepTumorQueen";NA;83;0
"Building";"CreepTumorQueen";NA;83;0
"Unit";"Queen";"Hatchery";68;2
"Unit";"Overlord";"Larva";80;0
"Unit";"Queen";"Hatchery";80;2
"Unit";"Overlord";"Larva";87;0
"Unit";"Overlord";"Larva";87;0
"Unit";"Baneling";"Zergling";94;0
"Unit";"Baneling";"Zergling";94;0
"Building";"Extractor";NA;87;0
"Unit";"Baneling";"Zergling";94;0
"Unit";"Baneling";"Zergling";94;0
"Unit";"Baneling";"Zergling";95;0
"Unit";"Baneling";"Zergling";95;0
"Building";"Extractor";NA;87;0
"Building";"CreepTumor";NA;97;0
"Building";"CreepTumor";NA;97;0
"Unit";"Overlord";"Larva";97;0
"Building";"Extractor";NA;97;0
"Building";"Extractor";NA;97;0
"Building";"CreepTumorQueen";NA;103;0
"Building";"CreepTumorQueen";NA;103;0
"Building";"CreepTumorQueen";NA;103;0
"Building";"CreepTumorQueen";NA;103;0
"Building";"HydraliskDen";NA;103;0
"Unit";"Zergling";"Larva";108;1
"Unit";"Zergling";"Larva";108;1
"Unit";"Zergling";"Larva";110;1
"Unit";"Zergling";"Larva";110;1
"Unit";"Zergling";"Larva";110;1
"Unit";"Zergling";"Larva";110;1
"Unit";"Zergling";"Larva";110;1
"Unit";"Zergling";"Larva";110;1
"Unit";"Zergling";"Larva";110;1
"Unit";"Zergling";"Larva";110;1
"Unit";"Zergling";"Larva";110;1
"Unit";"Zergling";"Larva";110;1
"Building";"EvolutionChamber";NA;106;0
"Unit";"Baneling";"Zergling";110;0
"Unit";"Baneling";"Zergling";110;0
"Unit";"Baneling";"Zergling";110;0
"Unit";"Baneling";"Zergling";110;0
"Unit";"Baneling";"Zergling";110;0
"Unit";"Baneling";"Zergling";110;0
"Unit";"Baneling";"Zergling";110;0
"Unit";"Baneling";"Zergling";110;0
"Unit";"Zergling";"Larva";110;1
"Unit";"Zergling";"Larva";110;1
"Unit";"Zergling";"Larva";110;1
"Unit";"Zergling";"Larva";110;1
"Unit";"Zergling";"Larva";110;1
"Unit";"Zergling";"Larva";110;1
"Unit";"Zergling";"Larva";110;1
"Unit";"Zergling";"Larva";110;1
"Unit";"Zergling";"Larva";110;1
"Unit";"Zergling";"Larva";110;1
"Unit";"Hydralisk";"Larva";110;2
"Upgrade";"ZergGroundArmorsLevel1";"EvolutionChamber";97;0
"Building";"CreepTumorQueen";NA;141;0
"Unit";"Overlord";"Larva";136;0
"Unit";"Hydralisk";"Larva";136;2
"Unit";"Hydralisk";"Larva";136;2
"Building";"Hatchery";NA;106;0
"Building";"CreepTumorQueen";NA;145;0
"Building";"CreepTumorQueen";NA;145;0
"Unit";"Hydralisk";"Larva";141;2
"Unit";"Hydralisk";"Larva";141;2
"Unit";"Hydralisk";"Larva";141;2
"Unit";"Hydralisk";"Larva";141;2
"Unit";"Hydralisk";"Larva";141;2
"Building";"CreepTumorQueen";NA;145;0
"Building";"CreepTumorQueen";NA;145;0
"Building";"CreepTumorQueen";NA;145;0
"Upgrade";"EvolveGroovedSpines";"HydraliskDen";138;0
"Unit";"Hydralisk";"Larva";145;2
"Unit";"Hydralisk";"Larva";145;2
"Unit";"Hydralisk";"Larva";145;2
"Building";"InfestationPit";NA;143;0
"Unit";"Overlord";"Larva";155;0
"Unit";"Overlord";"Larva";155;0
"Unit";"Overlord";"Larva";155;0
"Building";"CreepTumor";NA;161;0
"Building";"CreepTumor";NA;161;0
"Building";"CreepTumor";NA;161;0
"Building";"CreepTumor";NA;161;0
"Building";"CreepTumor";NA;161;0
"Unit";"Baneling";"Zergling";161;0
"Unit";"Baneling";"Zergling";161;0
"Unit";"Baneling";"Zergling";161;0
"Unit";"Baneling";"Zergling";161;0
"Unit";"Baneling";"Zergling";161;0
"Unit";"Hydralisk";"Larva";155;2
"Unit";"Hydralisk";"Larva";155;2
"Unit";"Hydralisk";"Larva";161;2
"Unit";"Hydralisk";"Larva";161;2
"Unit";"Hydralisk";"Larva";161;2
"Unit";"Hydralisk";"Larva";161;2
"Unit";"Hydralisk";"Larva";161;2
"Building";"CreepTumor";NA;172;0
"Building";"CreepTumor";NA;172;0
"Building";"CreepTumor";NA;172;0
"Building";"CreepTumor";NA;172;0
"Building";"CreepTumor";NA;172;0
"Unit";"Overlord";"Larva";172;0
"Unit";"Overlord";"Larva";172;0
"Unit";"Overlord";"Larva";172;0
"Upgrade";"ZergMissileWeaponsLevel1";"EvolutionChamber";145;0
"Building";"Hatchery";NA;145;0
"Unit";"Overlord";"Larva";175;0
"Unit";"Overlord";"Larva";175;0
"Unit";"Overlord";"Larva";175;0
"Building";"Extractor";NA;173;0
"Building";"Extractor";NA;175;0
"Upgrade";"EvolveMuscularAugments";"HydraliskDen";161;0
"Building";"SporeCrawler";NA;185;0
"Building";"SporeCrawler";NA;185;0
"Building";"CreepTumorQueen";NA;187;0
"Building";"CreepTumorQueen";NA;187;0
"Building";"CreepTumorQueen";NA;187;0
"Unit";"Hydralisk";"Larva";185;2
"Unit";"Hydralisk";"Larva";185;2
"Unit";"Hydralisk";"Larva";185;2
"Building";"SpineCrawler";NA;185;0
"Building";"RoachWarren";NA;187;0
"Building";"CreepTumor";NA;200;0
"Building";"CreepTumor";NA;200;0
"Building";"CreepTumor";NA;200;0
"Building";"CreepTumor";NA;200;0
"Unit";"Overlord";"Larva";200;0
"Unit";"Overlord";"Larva";200;0
"Unit";"Viper";"Larva";200;3
"Unit";"Viper";"Larva";200;3
"Unit";"Viper";"Larva";200;3
"Building";"UltraliskCavern";NA;193;0
"Unit";"Roach";"Larva";200;2
"Unit";"Roach";"Larva";200;2
"Unit";"Roach";"Larva";200;2
"Unit";"Roach";"Larva";200;2
"Unit";"Roach";"Larva";200;2
"Unit";"Roach";"Larva";200;2
"Unit";"Roach";"Larva";200;2
"Unit";"Roach";"Larva";200;2
"Unit";"Roach";"Larva";200;2
"Unit";"Roach";"Larva";201;2
"Unit";"Roach";"Larva";201;2
"Unit";"Roach";"Larva";201;2
"Unit";"Roach";"Larva";201;2
"Unit";"Roach";"Larva";201;2
"Building";"Spire";NA;189;0
"Unit";"Viper";"Larva";228;3
"Unit";"Viper";"Larva";228;3
"Unit";"Zergling";"Larva";238;1
"Unit";"Zergling";"Larva";238;1
"Unit";"Zergling";"Larva";238;1
"Unit";"Zergling";"Larva";238;1
"Unit";"Zergling";"Larva";238;1
"Unit";"Zergling";"Larva";238;1
"Unit";"Zergling";"Larva";238;1
"Unit";"Zergling";"Larva";238;1
"Unit";"Zergling";"Larva";238;1
"Unit";"Zergling";"Larva";238;1
"Unit";"Zergling";"Larva";238;1
"Unit";"Zergling";"Larva";238;1
"Unit";"Zergling";"Larva";238;1
"Unit";"Zergling";"Larva";238;1
"Unit";"Zergling";"Larva";238;1
"Unit";"Zergling";"Larva";238;1
"Unit";"Zergling";"Larva";238;1
"Unit";"Zergling";"Larva";238;1
"Unit";"Zergling";"Larva";238;1
"Unit";"Zergling";"Larva";238;1
"Unit";"Zergling";"Larva";238;1
"Unit";"Zergling";"Larva";238;1
"Unit";"Zergling";"Larva";238;1
"Unit";"Zergling";"Larva";238;1
"Unit";"Hydralisk";"Larva";238;2
"Unit";"Hydralisk";"Larva";238;2
"Unit";"Hydralisk";"Larva";238;2
"Unit";"Hydralisk";"Larva";238;2
"Unit";"Hydralisk";"Larva";238;2
"Upgrade";"ZergGroundArmorsLevel2";"EvolutionChamber";193;0
"Upgrade";"GlialReconstitution";"RoachWarren";228;0
"Upgrade";"ZergMissileWeaponsLevel2";"EvolutionChamber";200;0
"Unit";"Hydralisk";"Larva";268;2
"Unit";"Hydralisk";"Larva";268;2
"Unit";"Hydralisk";"Larva";268;2
"Unit";"Hydralisk";"Larva";268;2
"Unit";"Hydralisk";"Larva";268;2
"Unit";"Hydralisk";"Larva";268;2
"Unit";"Hydralisk";"Larva";268;2
"Unit";"Hydralisk";"Larva";284;2
"Unit";"Hydralisk";"Larva";292;2
"Unit";"Hydralisk";"Larva";292;2
"Unit";"Hydralisk";"Larva";292;2
"Unit";"Hydralisk";"Larva";292;2
"Unit";"Hydralisk";"Larva";292;2
"Unit";"Hydralisk";"Larva";292;2
"Upgrade";"ChitinousPlating";"UltraliskCavern";278;0
"Building";"CreepTumor";NA;323;0
"Building";"CreepTumor";NA;323;0
"Building";"CreepTumor";NA;323;0
"Unit";"Hydralisk";"Larva";323;2
"Unit";"Hydralisk";"Larva";323;2
"Unit";"Hydralisk";"Larva";323;2
"Unit";"Hydralisk";"Larva";323;2
"Unit";"Hydralisk";"Larva";323;2
"Unit";"Hydralisk";"Larva";323;2
"Building";"Hatchery";NA;292;0
"Unit";"Roach";"Larva";323;2
"Unit";"Roach";"Larva";323;2
"Unit";"Roach";"Larva";323;2
"Unit";"Roach";"Larva";323;2
"Unit";"Roach";"Larva";323;2
"Unit";"Roach";"Larva";335;2
"Unit";"Roach";"Larva";335;2
"Unit";"Roach";"Larva";335;2
"Unit";"Roach";"Larva";335;2
"Unit";"Roach";"Larva";335;2
"Unit";"Roach";"Larva";335;2
"Unit";"Roach";"Larva";357;2
"Unit";"Roach";"Larva";357;2
"Unit";"Roach";"Larva";357;2
"Unit";"Roach";"Larva";357;2
"Unit";"Roach";"Larva";357;2
"Unit";"Roach";"Larva";357;2
"Unit";"Roach";"Larva";357;2
"Unit";"Roach";"Larva";357;2
"Unit";"Roach";"Larva";357;2
"Unit";"Roach";"Larva";357;2
"Unit";"Roach";"Larva";357;2
"Unit";"Roach";"Larva";357;2
"Unit";"Roach";"Larva";357;2
"Unit";"Roach";"Larva";383;2
"Unit";"Roach";"Larva";383;2
"Unit";"Roach";"Larva";383;2
"Unit";"Roach";"Larva";383;2
"Unit";"Roach";"Larva";383;2
"Unit";"Roach";"Larva";383;2
"Unit";"Roach";"Larva";383;2
"Unit";"Roach";"Larva";383;2
"Unit";"Roach";"Larva";383;2
"Building";"CreepTumor";NA;383;0
"Building";"CreepTumor";NA;383;0
"Building";"CreepTumor";NA;383;0
"Unit";"Corruptor";"Larva";383;2
"Unit";"Corruptor";"Larva";383;2
"Unit";"Corruptor";"Larva";383;2
"Unit";"Corruptor";"Larva";383;2
"Unit";"Corruptor";"Larva";383;2
"Upgrade";"ZergMissileWeaponsLevel3";"EvolutionChamber";323;0
"Unit";"Corruptor";"Larva";411;2
"Unit";"Corruptor";"Larva";411;2
"Unit";"Corruptor";"Larva";411;2
"Unit";"Corruptor";"Larva";411;2
"Unit";"Corruptor";"Larva";411;2
"Unit";"Corruptor";"Larva";411;2
"Unit";"Corruptor";"Larva";411;2
"Unit";"Corruptor";"Larva";411;2
"Unit";"Corruptor";"Larva";411;2
"Unit";"Corruptor";"Larva";411;2
"Building";"Hatchery";NA;401;0
"Upgrade";"ZergGroundArmorsLevel3";"EvolutionChamber";357;0
"Unit";"Viper";"Larva";431;3
"Unit";"Viper";"Larva";431;3
"Unit";"Zergling";"Larva";438;1
"Unit";"Zergling";"Larva";438;1
"Unit";"Zergling";"Larva";438;1
"Unit";"Zergling";"Larva";438;1
"Unit";"Zergling";"Larva";438;1
"Unit";"Zergling";"Larva";438;1
"Unit";"Zergling";"Larva";438;1
"Unit";"Zergling";"Larva";438;1
"Unit";"Zergling";"Larva";438;1
"Unit";"Zergling";"Larva";438;1
"Unit";"Zergling";"Larva";438;1
"Unit";"Zergling";"Larva";438;1
"Unit";"Zergling";"Larva";438;1
"Unit";"Zergling";"Larva";438;1
"Unit";"Zergling";"Larva";438;1
"Unit";"Zergling";"Larva";438;1
"Unit";"Zergling";"Larva";438;1
"Unit";"Zergling";"Larva";438;1
"Unit";"Zergling";"Larva";438;1
"Unit";"Zergling";"Larva";438;1
"Unit";"Zergling";"Larva";438;1
"Unit";"Zergling";"Larva";438;1
"Unit";"Zergling";"Larva";438;1
"Unit";"Zergling";"Larva";438;1
"Unit";"Zergling";"Larva";438;1
"Unit";"Zergling";"Larva";438;1
"Unit";"Zergling";"Larva";438;1
"Unit";"Zergling";"Larva";438;1
"Building";"CreepTumor";NA;444;0
"Building";"CreepTumor";NA;444;0
"Building";"CreepTumor";NA;444;0
"Building";"SpineCrawler";NA;438;0
"Building";"SporeCrawler";NA;450;0
"Building";"Spire";NA;411;0
"Unit";"Roach";"Larva";474;2
"Unit";"Roach";"Larva";474;2
"Unit";"Roach";"Larva";474;2
"Building";"SpineCrawler";NA;472;0
"Building";"SpineCrawler";NA;472;0
"Unit";"Corruptor";"Larva";472;2
"Unit";"Corruptor";"Larva";480;2
"Unit";"Corruptor";"Larva";480;2
"Unit";"Corruptor";"Larva";480;2
"Upgrade";"ZergMeleeWeaponsLevel1";"EvolutionChamber";438;0
"Unit";"Zergling";"Larva";482;1
"Unit";"Zergling";"Larva";482;1
"Unit";"Hydralisk";"Larva";482;2
"Unit";"Hydralisk";"Larva";482;2
"Unit";"Hydralisk";"Larva";482;2
"Unit";"Hydralisk";"Larva";482;2
"Unit";"Hydralisk";"Larva";498;2
"Unit";"Hydralisk";"Larva";498;2
"Unit";"Hydralisk";"Larva";498;2
"Unit";"Hydralisk";"Larva";504;2
"Unit";"Hydralisk";"Larva";504;2
"Unit";"Hydralisk";"Larva";504;2
"Unit";"Hydralisk";"Larva";504;2
"Unit";"Hydralisk";"Larva";504;2
"Building";"CreepTumor";NA;519;0
"Building";"CreepTumor";NA;519;0
"Building";"CreepTumor";NA;519;0
"Unit";"Hydralisk";"Larva";519;2
"Unit";"Hydralisk";"Larva";519;2
"Building";"CreepTumor";NA;519;0
"Building";"CreepTumor";NA;519;0
"Building";"CreepTumor";NA;519;0
"Building";"Extractor";NA;519;0
"Unit";"Hydralisk";"Larva";523;2
"Unit";"Hydralisk";"Larva";523;2
"Unit";"Hydralisk";"Larva";523;2
"Unit";"Viper";"Larva";519;3
"Unit";"Viper";"Larva";519;3
"Unit";"Viper";"Larva";519;3
"Unit";"Zergling";"Larva";523;1
"Unit";"Zergling";"Larva";523;1
"Building";"Extractor";NA;523;0
"Unit";"Roach";"Larva";523;2
"Unit";"Roach";"Larva";523;2
"Unit";"Roach";"Larva";523;2
"Unit";"Roach";"Larva";523;2
"Unit";"Roach";"Larva";523;2
"Unit";"Hydralisk";"Larva";523;2
"Unit";"Hydralisk";"Larva";523;2
"Unit";"Zergling";"Larva";557;1
"Unit";"Zergling";"Larva";557;1
"Building";"Hatchery";NA;523;0
"Unit";"Zergling";"Larva";557;1
"Unit";"Zergling";"Larva";557;1
"Unit";"Zergling";"Larva";557;1
"Unit";"Zergling";"Larva";557;1
"Unit";"Zergling";"Larva";557;1
"Unit";"Zergling";"Larva";557;1
"Unit";"Zergling";"Larva";557;1
"Unit";"Zergling";"Larva";557;1
"Unit";"Zergling";"Larva";557;1
"Unit";"Zergling";"Larva";557;1
"Unit";"Zergling";"Larva";557;1
"Unit";"Zergling";"Larva";557;1
"Unit";"Zergling";"Larva";557;1
"Unit";"Zergling";"Larva";557;1
"Unit";"Zergling";"Larva";557;1
"Unit";"Zergling";"Larva";557;1
"Unit";"Zergling";"Larva";557;1
"Unit";"Zergling";"Larva";557;1
"Unit";"Zergling";"Larva";557;1
"Unit";"Zergling";"Larva";557;1
"Unit";"Zergling";"Larva";557;1
"Unit";"Zergling";"Larva";557;1
"Unit";"Roach";"Larva";557;2
"Unit";"Zergling";"Larva";557;1
"Unit";"Zergling";"Larva";557;1
"Unit";"Roach";"Larva";557;2
"Unit";"Roach";"Larva";557;2
"Building";"CreepTumor";NA;557;0
"Unit";"Viper";"Larva";557;3
"Building";"CreepTumor";NA;557;0
"Unit";"Viper";"Larva";557;3
"Unit";"Hydralisk";"Larva";557;2
"Unit";"Hydralisk";"Larva";557;2
"Unit";"Hydralisk";"Larva";557;2
