"type";"unit_name";"on_building";"total_supply";"supply"
"Unit";"Overlord";"Larva";13;0
"Building";"SpawningPool";NA;14;0
"Unit";"Zergling";"Larva";19;1
"Unit";"Zergling";"Larva";19;1
"Unit";"Zergling";"Larva";19;1
"Unit";"Zergling";"Larva";19;1
"Unit";"Zergling";"Larva";19;1
"Unit";"Zergling";"Larva";19;1
"Unit";"Overlord";"Larva";19;0
"Unit";"Queen";"Hatchery";19;2
"Building";"Hatchery";NA;18;0
"Unit";"Queen";"Hatchery";25;2
"Building";"CreepTumorQueen";NA;34;0
"Unit";"Queen";"Hatchery";30;2
"Unit";"Overlord";"Larva";33;0
"Building";"Hatchery";NA;25;0
"Unit";"Zergling";"Larva";39;1
"Unit";"Zergling";"Larva";39;1
"Unit";"Zergling";"Larva";39;1
"Unit";"Zergling";"Larva";39;1
"Building";"CreepTumorQueen";NA;42;0
"Building";"CreepTumor";NA;42;0
"Unit";"Queen";"Hatchery";37;2
"Unit";"Queen";"Hatchery";42;2
"Unit";"Overlord";"Larva";48;0
"Building";"CreepTumorQueen";NA;60;0
"Building";"CreepTumor";NA;60;0
"Unit";"Overlord";"Larva";56;0
"Building";"CreepTumor";NA;60;0
"Building";"CreepTumorQueen";NA;60;0
"Building";"CreepTumorQueen";NA;60;0
"Building";"Extractor";NA;60;0
"Building";"Extractor";NA;60;0
"Unit";"Overlord";"Larva";60;0
"Unit";"Queen";"Hatchery";60;2
"Unit";"Queen";"Hatchery";60;2
"Unit";"Zergling";"Larva";65;1
"Unit";"Zergling";"Larva";65;1
"Unit";"Zergling";"Larva";65;1
"Unit";"Zergling";"Larva";65;1
"Unit";"Zergling";"Larva";65;1
"Unit";"Zergling";"Larva";65;1
"Building";"CreepTumor";NA;69;0
"Building";"CreepTumor";NA;69;0
"Building";"CreepTumor";NA;69;0
"Building";"CreepTumor";NA;69;0
"Unit";"Overlord";"Larva";69;0
"Building";"EvolutionChamber";NA;69;0
"Building";"EvolutionChamber";NA;69;0
"Building";"CreepTumor";NA;79;0
"Unit";"Overlord";"Larva";79;0
"Building";"CreepTumor";NA;79;0
"Building";"CreepTumor";NA;79;0
"Unit";"Overlord";"Larva";79;0
"Unit";"Overlord";"Larva";79;0
"Building";"RoachWarren";NA;79;0
"Unit";"Overlord";"Larva";87;0
"Unit";"Overlord";"Larva";87;0
"Building";"CreepTumor";NA;91;0
"Building";"CreepTumorQueen";NA;94;0
"Building";"CreepTumorQueen";NA;94;0
"Building";"CreepTumor";NA;94;0
"Building";"CreepTumor";NA;94;0
"Building";"Extractor";NA;94;0
"Building";"Extractor";NA;94;0
"Unit";"Zergling";"Larva";94;1
"Unit";"Zergling";"Larva";94;1
"Unit";"Zergling";"Larva";94;1
"Unit";"Zergling";"Larva";94;1
"Unit";"Zergling";"Larva";94;1
"Unit";"Zergling";"Larva";94;1
"Unit";"Zergling";"Larva";94;1
"Unit";"Zergling";"Larva";94;1
"Unit";"Zergling";"Larva";94;1
"Unit";"Zergling";"Larva";94;1
"Unit";"Zergling";"Larva";94;1
"Unit";"Zergling";"Larva";94;1
"Unit";"Roach";"Larva";98;2
"Unit";"Roach";"Larva";98;2
"Unit";"Roach";"Larva";98;2
"Building";"BanelingNest";NA;94;0
"Building";"SporeCrawler";NA;119;0
"Unit";"Overlord";"Larva";119;0
"Building";"Hatchery";NA;98;0
"Building";"CreepTumor";NA;131;0
"Building";"CreepTumor";NA;131;0
"Building";"CreepTumor";NA;131;0
"Building";"CreepTumor";NA;131;0
"Building";"Extractor";NA;131;0
"Building";"CreepTumor";NA;131;0
"Building";"Extractor";NA;131;0
"Unit";"Baneling";"Zergling";139;0
"Unit";"Baneling";"Zergling";139;0
"Unit";"Baneling";"Zergling";139;0
"Unit";"Baneling";"Zergling";139;0
"Building";"CreepTumor";NA;149;0
"Building";"CreepTumor";NA;149;0
"Unit";"Zergling";"Larva";149;1
"Unit";"Zergling";"Larva";149;1
"Unit";"Zergling";"Larva";149;1
"Unit";"Zergling";"Larva";149;1
"Unit";"Zergling";"Larva";149;1
"Unit";"Zergling";"Larva";149;1
"Building";"Extractor";NA;149;0
"Building";"CreepTumor";NA;160;0
"Building";"CreepTumor";NA;160;0
"Unit";"Baneling";"Zergling";151;0
"Unit";"Baneling";"Zergling";160;0
"Unit";"Baneling";"Zergling";160;0
"Unit";"Baneling";"Zergling";160;0
"Unit";"Baneling";"Zergling";160;0
"Unit";"Baneling";"Zergling";160;0
"Unit";"Baneling";"Zergling";160;0
"Unit";"Baneling";"Zergling";160;0
"Building";"Extractor";NA;149;0
"Building";"CreepTumor";NA;160;0
"Unit";"Zergling";"Larva";160;1
"Unit";"Zergling";"Larva";160;1
"Unit";"Zergling";"Larva";160;1
"Unit";"Zergling";"Larva";160;1
"Unit";"Zergling";"Larva";160;1
"Unit";"Zergling";"Larva";160;1
"Unit";"Zergling";"Larva";160;1
"Unit";"Zergling";"Larva";160;1
"Unit";"Zergling";"Larva";160;1
"Unit";"Zergling";"Larva";160;1
"Building";"CreepTumorQueen";NA;160;0
"Building";"Spire";NA;131;0
"Building";"CreepTumorQueen";NA;162;0
"Building";"CreepTumorQueen";NA;166;0
"Building";"CreepTumorQueen";NA;166;0
"Unit";"Zergling";"Larva";160;1
"Unit";"Zergling";"Larva";160;1
"Unit";"Zergling";"Larva";160;1
"Unit";"Zergling";"Larva";160;1
"Unit";"Zergling";"Larva";160;1
"Unit";"Zergling";"Larva";160;1
"Unit";"Zergling";"Larva";160;1
"Unit";"Zergling";"Larva";160;1
"Unit";"Zergling";"Larva";160;1
"Unit";"Zergling";"Larva";160;1
"Unit";"Zergling";"Larva";160;1
"Unit";"Zergling";"Larva";160;1
"Unit";"Zergling";"Larva";160;1
"Unit";"Zergling";"Larva";160;1
"Unit";"Overlord";"Larva";166;0
"Unit";"Overlord";"Larva";166;0
"Unit";"Overlord";"Larva";166;0
"Unit";"Overlord";"Larva";166;0
"Upgrade";"ZergMeleeWeaponsLevel1";"EvolutionChamber";131;0
"Upgrade";"ZergGroundArmorsLevel1";"EvolutionChamber";131;0
"Building";"CreepTumor";NA;190;0
"Unit";"Overlord";"Larva";176;0
"Unit";"Overlord";"Larva";176;0
"Building";"CreepTumor";NA;190;0
"Building";"CreepTumor";NA;190;0
"Building";"CreepTumor";NA;190;0
"Building";"CreepTumor";NA;190;0
"Building";"CreepTumor";NA;190;0
"Building";"CreepTumorQueen";NA;190;0
"Building";"CreepTumorQueen";NA;190;0
"Building";"CreepTumorQueen";NA;190;0
"Building";"CreepTumorQueen";NA;190;0
"Building";"CreepTumorQueen";NA;190;0
"Unit";"Baneling";"Zergling";190;0
"Unit";"Baneling";"Zergling";190;0
"Unit";"Baneling";"Zergling";190;0
"Unit";"Baneling";"Zergling";190;0
"Unit";"Baneling";"Zergling";190;0
"Unit";"Baneling";"Zergling";190;0
"Unit";"Baneling";"Zergling";190;0
"Unit";"Baneling";"Zergling";190;0
"Unit";"Mutalisk";"Larva";190;2
"Unit";"Mutalisk";"Larva";190;2
"Unit";"Mutalisk";"Larva";190;2
"Unit";"Mutalisk";"Larva";190;2
"Unit";"Mutalisk";"Larva";190;2
"Unit";"Mutalisk";"Larva";190;2
"Unit";"Mutalisk";"Larva";190;2
"Unit";"Mutalisk";"Larva";190;2
"Unit";"Mutalisk";"Larva";190;2
"Unit";"Zergling";"Larva";190;1
"Unit";"Zergling";"Larva";190;1
"Unit";"Zergling";"Larva";190;1
"Unit";"Zergling";"Larva";190;1
"Unit";"Zergling";"Larva";190;1
"Unit";"Zergling";"Larva";190;1
"Unit";"Zergling";"Larva";190;1
"Unit";"Zergling";"Larva";190;1
"Unit";"Zergling";"Larva";190;1
"Unit";"Zergling";"Larva";190;1
"Unit";"Zergling";"Larva";190;1
"Unit";"Zergling";"Larva";190;1
"Unit";"Zergling";"Larva";190;1
"Unit";"Zergling";"Larva";190;1
"Unit";"Zergling";"Larva";190;1
"Unit";"Zergling";"Larva";190;1
"Unit";"Zergling";"Larva";190;1
"Unit";"Zergling";"Larva";190;1
"Unit";"Zergling";"Larva";190;1
"Unit";"Zergling";"Larva";190;1
"Unit";"Zergling";"Larva";190;1
"Unit";"Zergling";"Larva";190;1
"Unit";"Zergling";"Larva";190;1
"Unit";"Zergling";"Larva";190;1
"Unit";"Zergling";"Larva";190;1
"Unit";"Zergling";"Larva";190;1
"Unit";"Zergling";"Larva";190;1
"Unit";"Zergling";"Larva";190;1
"Unit";"Zergling";"Larva";190;1
"Unit";"Zergling";"Larva";190;1
"Building";"Hatchery";NA;166;0
"Building";"CreepTumorQueen";NA;238;0
"Building";"CreepTumorQueen";NA;238;0
"Building";"CreepTumorQueen";NA;238;0
"Building";"CreepTumorQueen";NA;238;0
"Building";"CreepTumor";NA;238;0
"Building";"CreepTumor";NA;238;0
"Building";"CreepTumor";NA;238;0
"Unit";"Overlord";"Larva";238;0
"Unit";"Overlord";"Larva";238;0
"Unit";"Overlord";"Larva";238;0
"Building";"CreepTumor";NA;238;0
"Building";"CreepTumor";NA;238;0
"Building";"CreepTumor";NA;238;0
"Unit";"Roach";"Larva";238;2
"Unit";"Roach";"Larva";238;2
"Unit";"Roach";"Larva";238;2
"Unit";"Roach";"Larva";238;2
"Unit";"Roach";"Larva";238;2
"Unit";"Roach";"Larva";238;2
"Unit";"Roach";"Larva";238;2
"Unit";"Roach";"Larva";238;2
"Unit";"Overlord";"Larva";247;0
"Unit";"Overlord";"Larva";247;0
"Building";"InfestationPit";NA;238;0
"Upgrade";"GlialReconstitution";"RoachWarren";224;0
"Unit";"Roach";"Larva";247;2
"Unit";"Roach";"Larva";249;2
"Unit";"Roach";"Larva";249;2
"Unit";"Roach";"Larva";249;2
"Unit";"Roach";"Larva";249;2
"Unit";"Roach";"Larva";249;2
"Unit";"Roach";"Larva";249;2
"Unit";"Roach";"Larva";249;2
"Unit";"Roach";"Larva";249;2
"Unit";"Roach";"Larva";263;2
"Unit";"Roach";"Larva";263;2
"Unit";"Roach";"Larva";263;2
"Unit";"Roach";"Larva";263;2
"Unit";"Roach";"Larva";263;2
"Unit";"Roach";"Larva";263;2
"Unit";"Roach";"Larva";263;2
"Unit";"Roach";"Larva";263;2
"Unit";"Roach";"Larva";263;2
"Unit";"Roach";"Larva";263;2
"Unit";"Roach";"Larva";263;2
"Building";"Hatchery";NA;238;0
"Building";"CreepTumor";NA;307;0
"Building";"CreepTumor";NA;308;0
"Building";"CreepTumor";NA;309;0
"Building";"CreepTumor";NA;317;0
"Building";"CreepTumor";NA;317;0
"Building";"CreepTumor";NA;317;0
"Building";"CreepTumor";NA;317;0
"Building";"CreepTumor";NA;317;0
"Building";"CreepTumor";NA;317;0
"Building";"CreepTumor";NA;317;0
"Building";"CreepTumor";NA;317;0
"Building";"HydraliskDen";NA;306;0
"Unit";"Roach";"Larva";317;2
"Unit";"Roach";"Larva";317;2
"Unit";"Roach";"Larva";317;2
"Unit";"Roach";"Larva";317;2
"Unit";"Roach";"Larva";317;2
"Unit";"Roach";"Larva";317;2
"Unit";"Roach";"Larva";317;2
"Unit";"Roach";"Larva";317;2
"Unit";"Roach";"Larva";317;2
"Building";"CreepTumor";NA;317;0
"Building";"CreepTumor";NA;317;0
"Building";"CreepTumor";NA;317;0
"Building";"CreepTumor";NA;317;0
"Upgrade";"ZergMissileWeaponsLevel1";"EvolutionChamber";263;0
"Building";"Extractor";NA;317;0
"Building";"Extractor";NA;317;0
"Building";"CreepTumor";NA;335;0
"Building";"CreepTumor";NA;335;0
"Building";"CreepTumor";NA;335;0
"Building";"CreepTumor";NA;335;0
"Unit";"Queen";"Hatchery";317;2
"Building";"CreepTumor";NA;337;0
"Building";"CreepTumor";NA;337;0
"Building";"CreepTumor";NA;337;0
"Unit";"Viper";"Larva";337;3
"Unit";"Viper";"Larva";337;3
"Unit";"Viper";"Larva";337;3
"Building";"CreepTumor";NA;346;0
"Upgrade";"ZergGroundArmorsLevel2";"EvolutionChamber";335;0
"Unit";"Hydralisk";"Larva";346;2
"Unit";"Hydralisk";"Larva";346;2
"Unit";"Hydralisk";"Larva";346;2
"Unit";"Hydralisk";"Larva";346;2
"Unit";"Hydralisk";"Larva";346;2
"Unit";"Hydralisk";"Larva";346;2
"Unit";"Hydralisk";"Larva";346;2
"Unit";"Hydralisk";"Larva";346;2
"Building";"CreepTumor";NA;362;0
"Building";"CreepTumor";NA;362;0
"Building";"CreepTumor";NA;362;0
"Building";"CreepTumor";NA;362;0
"Building";"SpineCrawler";NA;346;0
"Unit";"Roach";"Larva";346;2
"Building";"CreepTumor";NA;362;0
"Building";"CreepTumor";NA;362;0
"Unit";"Roach";"Larva";346;2
"Unit";"Roach";"Larva";346;2
"Unit";"Roach";"Larva";346;2
"Unit";"Roach";"Larva";346;2
"Unit";"Roach";"Larva";346;2
"Building";"SpineCrawler";NA;346;0
"Building";"SpineCrawler";NA;346;0
"Building";"CreepTumor";NA;362;0
"Building";"CreepTumor";NA;362;0
"Building";"CreepTumor";NA;362;0
"Upgrade";"ZergMissileWeaponsLevel2";"EvolutionChamber";337;0
"Building";"SpineCrawler";NA;346;0
"Upgrade";"EvolveMuscularAugments";"HydraliskDen";346;0
"Building";"Spire";NA;346;0
"Building";"CreepTumorQueen";NA;374;0
"Unit";"Roach";"Larva";374;2
"Unit";"Roach";"Larva";374;2
"Unit";"Roach";"Larva";374;2
"Building";"CreepTumorQueen";NA;374;0
"Unit";"Roach";"Larva";374;2
"Unit";"Roach";"Larva";374;2
"Unit";"Roach";"Larva";374;2
"Unit";"Roach";"Larva";374;2
"Unit";"Roach";"Larva";374;2
"Unit";"Roach";"Larva";374;2
"Unit";"Roach";"Larva";374;2
"Unit";"Roach";"Larva";374;2
"Building";"CreepTumorQueen";NA;374;0
"Building";"CreepTumorQueen";NA;374;0
"Unit";"Roach";"Larva";374;2
"Building";"Hatchery";NA;346;0
"Unit";"Roach";"Larva";374;2
"Unit";"Roach";"Larva";374;2
"Unit";"Roach";"Larva";374;2
"Unit";"Roach";"Larva";374;2
"Unit";"Roach";"Larva";374;2
"Building";"CreepTumorQueen";NA;374;0
"Building";"CreepTumorQueen";NA;374;0
"Building";"CreepTumorQueen";NA;376;0
"Building";"CreepTumorQueen";NA;396;0
"Building";"Hatchery";NA;346;0
"Building";"CreepTumor";NA;408;0
"Building";"CreepTumor";NA;408;0
"Building";"CreepTumor";NA;408;0
"Building";"CreepTumor";NA;408;0
"Building";"CreepTumor";NA;408;0
"Building";"CreepTumor";NA;408;0
"Building";"CreepTumor";NA;408;0
"Building";"CreepTumor";NA;408;0
"Building";"CreepTumor";NA;408;0
"Building";"CreepTumor";NA;408;0
"Building";"CreepTumor";NA;408;0
"Building";"CreepTumor";NA;408;0
"Unit";"Roach";"Larva";408;2
"Unit";"Roach";"Larva";408;2
"Unit";"Roach";"Larva";408;2
"Unit";"Roach";"Larva";408;2
"Unit";"Roach";"Larva";408;2
"Unit";"Hydralisk";"Larva";408;2
"Building";"CreepTumor";NA;408;0
"Unit";"Hydralisk";"Larva";408;2
"Unit";"Hydralisk";"Larva";408;2
"Unit";"Hydralisk";"Larva";408;2
"Unit";"Hydralisk";"Larva";408;2
"Unit";"Hydralisk";"Larva";408;2
"Unit";"Hydralisk";"Larva";408;2
"Unit";"Hydralisk";"Larva";408;2
"Unit";"Hydralisk";"Larva";408;2
"Building";"CreepTumor";NA;408;0
"Unit";"Viper";"Larva";408;3
"Unit";"Viper";"Larva";408;3
"Unit";"Viper";"Larva";408;3
"Unit";"Viper";"Larva";408;3
"Building";"CreepTumor";NA;448;0
"Building";"CreepTumor";NA;448;0
"Building";"CreepTumor";NA;448;0
"Building";"CreepTumorQueen";NA;448;0
"Building";"CreepTumorQueen";NA;448;0
"Building";"CreepTumor";NA;448;0
"Building";"CreepTumor";NA;448;0
"Building";"CreepTumor";NA;448;0
"Building";"CreepTumorQueen";NA;448;0
"Building";"CreepTumorQueen";NA;448;0
"Building";"CreepTumorQueen";NA;448;0
"Building";"CreepTumorQueen";NA;448;0
"Building";"CreepTumorQueen";NA;448;0
"Building";"CreepTumorQueen";NA;448;0
"Building";"CreepTumorQueen";NA;448;0
"Building";"CreepTumorQueen";NA;448;0
"Upgrade";"ZergGroundArmorsLevel3";"EvolutionChamber";374;0
"Building";"CreepTumor";NA;448;0
"Building";"CreepTumor";NA;448;0
"Building";"CreepTumor";NA;448;0
"Building";"CreepTumor";NA;448;0
"Building";"CreepTumor";NA;448;0
"Building";"CreepTumor";NA;448;0
"Building";"CreepTumor";NA;448;0
"Building";"CreepTumor";NA;448;0
"Unit";"Corruptor";"Larva";448;2
"Building";"CreepTumor";NA;448;0
"Building";"CreepTumor";NA;448;0
"Building";"CreepTumor";NA;448;0
"Building";"CreepTumor";NA;448;0
"Building";"CreepTumor";NA;448;0
"Building";"CreepTumor";NA;448;0
"Unit";"Corruptor";"Larva";448;2
"Unit";"Corruptor";"Larva";448;2
"Unit";"Corruptor";"Larva";448;2
"Unit";"Corruptor";"Larva";448;2
"Building";"CreepTumor";NA;448;0
"Upgrade";"EvolveGroovedSpines";"HydraliskDen";448;0
"Unit";"Corruptor";"Larva";458;2
"Unit";"Corruptor";"Larva";458;2
"Unit";"Corruptor";"Larva";458;2
"Unit";"Corruptor";"Larva";458;2
"Unit";"Corruptor";"Larva";458;2
"Unit";"Corruptor";"Larva";458;2
"Unit";"Hydralisk";"Larva";458;2
"Unit";"Viper";"Larva";458;3
"Unit";"Viper";"Larva";458;3
"Unit";"Viper";"Larva";458;3
"Unit";"Viper";"Larva";458;3
"Unit";"Queen";"Hatchery";458;2
"Unit";"Queen";"Hatchery";458;2
"Unit";"Queen";"Hatchery";458;2
"Unit";"Queen";"Hatchery";458;2
"Unit";"Queen";"Hatchery";458;2
"Unit";"Queen";"Hatchery";458;2
"Unit";"Queen";"Hatchery";458;2
"Unit";"Queen";"Hatchery";458;2
"Building";"CreepTumor";NA;500;0
"Building";"CreepTumor";NA;500;0
"Building";"CreepTumor";NA;500;0
"Building";"CreepTumor";NA;501;0
"Building";"CreepTumor";NA;510;0
"Building";"CreepTumor";NA;510;0
"Building";"CreepTumor";NA;510;0
"Building";"CreepTumor";NA;510;0
"Building";"CreepTumor";NA;510;0
"Building";"CreepTumor";NA;510;0
"Building";"CreepTumor";NA;510;0
"Building";"CreepTumor";NA;510;0
"Building";"CreepTumor";NA;510;0
"Building";"CreepTumor";NA;510;0
"Unit";"Hydralisk";"Larva";484;2
"Building";"CreepTumor";NA;510;0
"Building";"CreepTumor";NA;510;0
"Unit";"Hydralisk";"Larva";484;2
"Unit";"Hydralisk";"Larva";484;2
"Unit";"Hydralisk";"Larva";484;2
"Unit";"Hydralisk";"Larva";486;2
"Upgrade";"ZergMissileWeaponsLevel3";"EvolutionChamber";448;0
"Building";"CreepTumor";NA;510;0
"Building";"CreepTumor";NA;510;0
"Building";"CreepTumor";NA;510;0
"Building";"CreepTumor";NA;510;0
"Unit";"Queen";"Hatchery";484;2
"Unit";"Queen";"Hatchery";486;2
"Unit";"Queen";"Hatchery";488;2
"Unit";"Hydralisk";"Larva";510;2
"Unit";"Hydralisk";"Larva";510;2
"Building";"Extractor";NA;510;0
"Building";"Extractor";NA;510;0
"Building";"CreepTumor";NA;530;0
"Unit";"Corruptor";"Larva";530;2
"Unit";"Corruptor";"Larva";530;2
"Unit";"Corruptor";"Larva";530;2
"Unit";"Corruptor";"Larva";530;2
"Building";"CreepTumor";NA;530;0
