"type";"unit_name";"on_building";"total_supply";"supply"
"Unit";"Overlord";"Larva";12;0
"Building";"Extractor";NA;18;0
"Unit";"Overlord";"Larva";21;0
"Building";"SpawningPool";NA;19;0
"Building";"Hatchery";NA;17;0
"Unit";"Zergling";"Larva";22;1
"Unit";"Zergling";"Larva";22;1
"Unit";"Zergling";"Larva";22;1
"Unit";"Zergling";"Larva";22;1
"Unit";"Zergling";"Larva";22;1
"Unit";"Zergling";"Larva";22;1
"Unit";"Queen";"Hatchery";22;2
"Unit";"Queen";"Hatchery";22;2
"Building";"CreepTumorQueen";NA;36;0
"Unit";"Overlord";"Larva";36;0
"Unit";"Queen";"Hatchery";36;2
"Building";"CreepTumor";NA;40;0
"Unit";"Overlord";"Larva";42;0
"Unit";"Queen";"Hatchery";42;2
"Building";"CreepTumorQueen";NA;51;0
"Building";"Hatchery";NA;40;0
"Building";"Extractor";NA;51;0
"Building";"CreepTumor";NA;59;0
"Unit";"Overlord";"Larva";59;0
"Unit";"Overlord";"Larva";59;0
"Unit";"Overlord";"Larva";59;0
"Building";"CreepTumor";NA;59;0
"Building";"CreepTumorQueen";NA;59;0
"Unit";"Zergling";"Larva";62;1
"Unit";"Zergling";"Larva";62;1
"Unit";"Zergling";"Larva";62;1
"Unit";"Zergling";"Larva";62;1
"Unit";"Zergling";"Larva";62;1
"Unit";"Zergling";"Larva";62;1
"Unit";"Zergling";"Larva";62;1
"Unit";"Zergling";"Larva";62;1
"Unit";"Zergling";"Larva";62;1
"Unit";"Zergling";"Larva";62;1
"Unit";"Zergling";"Larva";64;1
"Unit";"Zergling";"Larva";64;1
"Unit";"Zergling";"Larva";64;1
"Unit";"Zergling";"Larva";64;1
"Unit";"Zergling";"Larva";64;1
"Unit";"Zergling";"Larva";64;1
"Unit";"Zergling";"Larva";64;1
"Unit";"Zergling";"Larva";64;1
"Building";"BanelingNest";NA;59;0
"Unit";"Queen";"Hatchery";59;2
"Building";"CreepTumor";NA;74;0
"Building";"CreepTumor";NA;74;0
"Building";"CreepTumor";NA;74;0
"Unit";"Zergling";"Larva";64;1
"Unit";"Zergling";"Larva";64;1
"Unit";"Zergling";"Larva";64;1
"Unit";"Zergling";"Larva";64;1
"Unit";"Zergling";"Larva";64;1
"Unit";"Zergling";"Larva";64;1
"Unit";"Overlord";"Larva";74;0
"Unit";"Baneling";"Zergling";84;0
"Unit";"Baneling";"Zergling";84;0
"Unit";"Baneling";"Zergling";84;0
"Unit";"Baneling";"Zergling";84;0
"Unit";"Baneling";"Zergling";84;0
"Unit";"Baneling";"Zergling";84;0
"Unit";"Baneling";"Zergling";84;0
"Unit";"Baneling";"Zergling";84;0
"Unit";"Baneling";"Zergling";84;0
"Unit";"Baneling";"Zergling";84;0
"Building";"EvolutionChamber";NA;82;0
"Unit";"Overlord";"Larva";90;0
"Building";"EvolutionChamber";NA;84;0
"Building";"Hatchery";NA;59;0
"Building";"CreepTumorQueen";NA;96;0
"Unit";"Overlord";"Larva";96;0
"Building";"Extractor";NA;96;0
"Building";"Extractor";NA;96;0
"Unit";"Overlord";"Larva";110;0
"Building";"CreepTumor";NA;110;0
"Unit";"Overlord";"Larva";110;0
"Building";"SporeCrawler";NA;110;0
"Unit";"Baneling";"Zergling";110;0
"Unit";"Baneling";"Zergling";110;0
"Unit";"Zergling";"Larva";110;1
"Unit";"Zergling";"Larva";110;1
"Unit";"Zergling";"Larva";110;1
"Unit";"Zergling";"Larva";110;1
"Unit";"Zergling";"Larva";110;1
"Unit";"Zergling";"Larva";110;1
"Unit";"Zergling";"Larva";110;1
"Unit";"Zergling";"Larva";110;1
"Unit";"Zergling";"Larva";110;1
"Unit";"Zergling";"Larva";110;1
"Unit";"Zergling";"Larva";110;1
"Unit";"Zergling";"Larva";110;1
"Building";"Extractor";NA;110;0
"Unit";"Zergling";"Larva";110;1
"Unit";"Zergling";"Larva";110;1
"Unit";"Zergling";"Larva";110;1
"Unit";"Zergling";"Larva";110;1
"Unit";"Zergling";"Larva";110;1
"Unit";"Zergling";"Larva";110;1
"Building";"SpineCrawler";NA;110;0
"Building";"CreepTumor";NA;135;0
"Unit";"Queen";"Hatchery";110;2
"Unit";"Overlord";"Larva";135;0
"Unit";"Zergling";"Larva";135;1
"Unit";"Zergling";"Larva";135;1
"Unit";"Zergling";"Larva";135;1
"Unit";"Zergling";"Larva";135;1
"Unit";"Zergling";"Larva";135;1
"Unit";"Zergling";"Larva";135;1
"Unit";"Zergling";"Larva";135;1
"Unit";"Zergling";"Larva";135;1
"Unit";"Zergling";"Larva";135;1
"Unit";"Zergling";"Larva";135;1
"Unit";"Zergling";"Larva";135;1
"Unit";"Zergling";"Larva";135;1
"Unit";"Zergling";"Larva";135;1
"Unit";"Zergling";"Larva";135;1
"Unit";"Zergling";"Larva";135;1
"Unit";"Zergling";"Larva";135;1
"Unit";"Zergling";"Larva";135;1
"Unit";"Zergling";"Larva";135;1
"Unit";"Zergling";"Larva";135;1
"Unit";"Zergling";"Larva";135;1
"Unit";"Zergling";"Larva";135;1
"Unit";"Zergling";"Larva";135;1
"Unit";"Zergling";"Larva";135;1
"Unit";"Zergling";"Larva";135;1
"Unit";"Zergling";"Larva";135;1
"Unit";"Zergling";"Larva";135;1
"Unit";"Zergling";"Larva";135;1
"Unit";"Zergling";"Larva";135;1
"Unit";"Zergling";"Larva";135;1
"Unit";"Zergling";"Larva";135;1
"Building";"CreepTumorQueen";NA;167;0
"Building";"Extractor";NA;137;0
"Upgrade";"ZergMeleeWeaponsLevel1";"EvolutionChamber";110;0
"Unit";"Overlord";"Larva";170;0
"Unit";"Queen";"Hatchery";139;2
"Unit";"Zergling";"Larva";171;1
"Unit";"Zergling";"Larva";171;1
"Unit";"Zergling";"Larva";171;1
"Unit";"Zergling";"Larva";171;1
"Unit";"Zergling";"Larva";171;1
"Unit";"Zergling";"Larva";171;1
"Unit";"Zergling";"Larva";171;1
"Unit";"Zergling";"Larva";171;1
"Unit";"Zergling";"Larva";171;1
"Unit";"Zergling";"Larva";171;1
"Unit";"Zergling";"Larva";171;1
"Unit";"Zergling";"Larva";171;1
"Unit";"Zergling";"Larva";171;1
"Unit";"Zergling";"Larva";171;1
"Unit";"Zergling";"Larva";171;1
"Unit";"Zergling";"Larva";171;1
"Unit";"Zergling";"Larva";171;1
"Unit";"Zergling";"Larva";171;1
"Unit";"Zergling";"Larva";171;1
"Unit";"Zergling";"Larva";171;1
"Unit";"Zergling";"Larva";171;1
"Unit";"Zergling";"Larva";171;1
"Unit";"Zergling";"Larva";171;1
"Unit";"Zergling";"Larva";171;1
"Unit";"Zergling";"Larva";171;1
"Unit";"Zergling";"Larva";171;1
"Unit";"Zergling";"Larva";171;1
"Unit";"Zergling";"Larva";171;1
"Unit";"Zergling";"Larva";171;1
"Unit";"Zergling";"Larva";171;1
"Upgrade";"ZergGroundArmorsLevel1";"EvolutionChamber";110;0
"Unit";"Baneling";"Zergling";171;0
"Unit";"Baneling";"Zergling";171;0
"Unit";"Baneling";"Zergling";171;0
"Unit";"Baneling";"Zergling";171;0
"Unit";"Baneling";"Zergling";171;0
"Unit";"Baneling";"Zergling";171;0
"Unit";"Baneling";"Zergling";171;0
"Unit";"Baneling";"Zergling";171;0
"Unit";"Baneling";"Zergling";171;0
"Unit";"Baneling";"Zergling";171;0
"Unit";"Baneling";"Zergling";171;0
"Unit";"Baneling";"Zergling";171;0
"Unit";"Baneling";"Zergling";171;0
"Unit";"Baneling";"Zergling";171;0
"Unit";"Baneling";"Zergling";171;0
"Unit";"Zergling";"Larva";171;1
"Unit";"Zergling";"Larva";171;1
"Unit";"Zergling";"Larva";171;1
"Unit";"Zergling";"Larva";171;1
"Building";"SporeCrawler";NA;171;0
"Unit";"Baneling";"Zergling";203;0
"Building";"Hatchery";NA;135;0
"Building";"Spire";NA;171;0
"Unit";"Queen";"Hatchery";207;2
"Unit";"Queen";"Hatchery";207;2
"Unit";"Mutalisk";"Larva";224;2
"Unit";"Mutalisk";"Larva";224;2
"Unit";"Mutalisk";"Larva";224;2
"Unit";"Mutalisk";"Larva";224;2
"Unit";"Mutalisk";"Larva";224;2
"Unit";"Mutalisk";"Larva";224;2
"Unit";"Mutalisk";"Larva";224;2
"Unit";"Mutalisk";"Larva";224;2
"Unit";"Mutalisk";"Larva";224;2
"Building";"CreepTumorQueen";NA;228;0
"Unit";"Overlord";"Larva";228;0
"Unit";"Overlord";"Larva";228;0
"Unit";"Overlord";"Larva";228;0
"Unit";"Overlord";"Larva";228;0
"Unit";"Overlord";"Larva";228;0
"Building";"Extractor";NA;228;0
"Building";"Extractor";NA;228;0
"Building";"CreepTumor";NA;228;0
"Unit";"Queen";"Hatchery";228;2
"Unit";"Mutalisk";"Larva";246;2
"Unit";"Mutalisk";"Larva";246;2
"Unit";"Mutalisk";"Larva";246;2
"Unit";"Mutalisk";"Larva";246;2
"Unit";"Mutalisk";"Larva";246;2
"Unit";"Overlord";"Larva";246;0
"Building";"CreepTumorQueen";NA;248;0
"Upgrade";"ZergMeleeWeaponsLevel2";"EvolutionChamber";207;0
"Unit";"Mutalisk";"Larva";248;2
"Unit";"Mutalisk";"Larva";248;2
"Unit";"Mutalisk";"Larva";248;2
"Unit";"Mutalisk";"Larva";248;2
"Building";"CreepTumorQueen";NA;258;0
"Unit";"Mutalisk";"Larva";258;2
"Unit";"Zergling";"Larva";266;1
"Unit";"Zergling";"Larva";266;1
"Unit";"Zergling";"Larva";266;1
"Unit";"Zergling";"Larva";266;1
"Unit";"Zergling";"Larva";266;1
"Unit";"Zergling";"Larva";266;1
"Unit";"Zergling";"Larva";266;1
"Unit";"Zergling";"Larva";266;1
"Unit";"Zergling";"Larva";266;1
"Unit";"Zergling";"Larva";266;1
"Unit";"Zergling";"Larva";266;1
"Unit";"Zergling";"Larva";266;1
"Unit";"Zergling";"Larva";266;1
"Unit";"Zergling";"Larva";266;1
"Unit";"Zergling";"Larva";266;1
"Unit";"Zergling";"Larva";266;1
"Unit";"Zergling";"Larva";266;1
"Unit";"Zergling";"Larva";266;1
"Unit";"Zergling";"Larva";266;1
"Unit";"Zergling";"Larva";266;1
"Unit";"Zergling";"Larva";266;1
"Unit";"Zergling";"Larva";266;1
"Unit";"Zergling";"Larva";266;1
"Unit";"Zergling";"Larva";266;1
"Unit";"Zergling";"Larva";266;1
"Unit";"Zergling";"Larva";266;1
"Unit";"Zergling";"Larva";266;1
"Unit";"Zergling";"Larva";266;1
"Unit";"Zergling";"Larva";266;1
"Unit";"Zergling";"Larva";266;1
"Unit";"Zergling";"Larva";266;1
"Unit";"Zergling";"Larva";266;1
"Unit";"Zergling";"Larva";266;1
"Unit";"Zergling";"Larva";266;1
"Unit";"Zergling";"Larva";266;1
"Unit";"Zergling";"Larva";266;1
"Unit";"Zergling";"Larva";266;1
"Unit";"Zergling";"Larva";266;1
"Unit";"Zergling";"Larva";266;1
"Unit";"Zergling";"Larva";266;1
"Unit";"Zergling";"Larva";266;1
"Unit";"Zergling";"Larva";266;1
"Unit";"Zergling";"Larva";266;1
"Unit";"Zergling";"Larva";266;1
"Unit";"Zergling";"Larva";266;1
"Unit";"Zergling";"Larva";266;1
"Unit";"Zergling";"Larva";266;1
"Unit";"Zergling";"Larva";266;1
"Unit";"Zergling";"Larva";266;1
"Unit";"Zergling";"Larva";266;1
"Unit";"Zergling";"Larva";266;1
"Unit";"Zergling";"Larva";266;1
"Unit";"Zergling";"Larva";266;1
"Unit";"Zergling";"Larva";266;1
"Unit";"Zergling";"Larva";266;1
"Unit";"Zergling";"Larva";266;1
"Unit";"Zergling";"Larva";266;1
"Unit";"Zergling";"Larva";266;1
"Unit";"Zergling";"Larva";266;1
"Unit";"Zergling";"Larva";266;1
"Unit";"Zergling";"Larva";266;1
"Unit";"Zergling";"Larva";266;1
"Building";"InfestationPit";NA;266;0
"Building";"CreepTumorQueen";NA;330;0
"Building";"CreepTumor";NA;330;0
"Building";"CreepTumor";NA;330;0
"Building";"CreepTumor";NA;330;0
"Unit";"Mutalisk";"Larva";268;2
"Unit";"Mutalisk";"Larva";268;2
"Unit";"Mutalisk";"Larva";268;2
"Unit";"Mutalisk";"Larva";268;2
"Unit";"Baneling";"Zergling";330;0
"Unit";"Baneling";"Zergling";330;0
"Unit";"Baneling";"Zergling";330;0
"Unit";"Baneling";"Zergling";330;0
"Unit";"Baneling";"Zergling";330;0
"Unit";"Baneling";"Zergling";330;0
"Unit";"Baneling";"Zergling";330;0
"Unit";"Baneling";"Zergling";330;0
"Unit";"Baneling";"Zergling";330;0
"Unit";"Baneling";"Zergling";330;0
"Unit";"Baneling";"Zergling";330;0
"Unit";"Baneling";"Zergling";330;0
"Unit";"Baneling";"Zergling";330;0
"Unit";"Baneling";"Zergling";330;0
"Unit";"Baneling";"Zergling";330;0
"Unit";"Baneling";"Zergling";330;0
"Unit";"Baneling";"Zergling";330;0
"Unit";"Baneling";"Zergling";330;0
"Unit";"Overlord";"Larva";338;0
"Upgrade";"ZergGroundArmorsLevel2";"EvolutionChamber";248;0
"Building";"Hatchery";NA;266;0
"Unit";"Zergling";"Larva";338;1
"Unit";"Zergling";"Larva";338;1
"Unit";"Zergling";"Larva";338;1
"Unit";"Zergling";"Larva";338;1
"Unit";"Zergling";"Larva";338;1
"Unit";"Zergling";"Larva";338;1
"Unit";"Zergling";"Larva";338;1
"Unit";"Zergling";"Larva";338;1
"Unit";"Zergling";"Larva";338;1
"Unit";"Zergling";"Larva";338;1
"Unit";"Zergling";"Larva";338;1
"Unit";"Zergling";"Larva";338;1
"Unit";"Zergling";"Larva";338;1
"Unit";"Zergling";"Larva";338;1
"Unit";"Zergling";"Larva";338;1
"Unit";"Zergling";"Larva";338;1
"Unit";"Zergling";"Larva";338;1
"Unit";"Zergling";"Larva";338;1
"Unit";"Zergling";"Larva";338;1
"Unit";"Zergling";"Larva";338;1
"Unit";"Zergling";"Larva";338;1
"Unit";"Zergling";"Larva";338;1
"Unit";"Zergling";"Larva";338;1
"Unit";"Zergling";"Larva";338;1
"Unit";"Zergling";"Larva";338;1
"Unit";"Zergling";"Larva";338;1
"Unit";"Zergling";"Larva";338;1
"Unit";"Zergling";"Larva";338;1
"Unit";"Zergling";"Larva";338;1
"Unit";"Zergling";"Larva";338;1
"Unit";"Zergling";"Larva";338;1
"Unit";"Zergling";"Larva";338;1
"Unit";"Zergling";"Larva";338;1
"Unit";"Zergling";"Larva";338;1
"Unit";"Zergling";"Larva";338;1
"Unit";"Zergling";"Larva";338;1
"Unit";"Zergling";"Larva";338;1
"Unit";"Zergling";"Larva";338;1
"Unit";"Mutalisk";"Larva";338;2
"Unit";"Mutalisk";"Larva";338;2
"Unit";"Mutalisk";"Larva";338;2
"Unit";"Mutalisk";"Larva";338;2
"Unit";"Mutalisk";"Larva";338;2
"Unit";"Mutalisk";"Larva";338;2
"Unit";"Mutalisk";"Larva";338;2
"Unit";"Mutalisk";"Larva";338;2
"Building";"CreepTumor";NA;392;0
"Unit";"Zergling";"Larva";392;1
"Unit";"Zergling";"Larva";392;1
"Unit";"Zergling";"Larva";392;1
"Unit";"Zergling";"Larva";392;1
"Unit";"Zergling";"Larva";392;1
"Unit";"Zergling";"Larva";392;1
"Unit";"Zergling";"Larva";392;1
"Unit";"Zergling";"Larva";392;1
"Unit";"Zergling";"Larva";392;1
"Unit";"Zergling";"Larva";392;1
"Unit";"Zergling";"Larva";392;1
"Unit";"Zergling";"Larva";392;1
"Unit";"Zergling";"Larva";392;1
"Unit";"Zergling";"Larva";392;1
"Unit";"Zergling";"Larva";392;1
"Unit";"Zergling";"Larva";392;1
"Unit";"Zergling";"Larva";392;1
"Unit";"Zergling";"Larva";392;1
"Unit";"Zergling";"Larva";392;1
"Unit";"Zergling";"Larva";392;1
"Unit";"Zergling";"Larva";392;1
"Unit";"Zergling";"Larva";392;1
"Unit";"Zergling";"Larva";392;1
"Unit";"Zergling";"Larva";392;1
"Unit";"Zergling";"Larva";392;1
"Unit";"Zergling";"Larva";392;1
"Unit";"Zergling";"Larva";392;1
"Unit";"Zergling";"Larva";392;1
"Unit";"Zergling";"Larva";392;1
"Unit";"Zergling";"Larva";392;1
"Unit";"Zergling";"Larva";392;1
"Unit";"Zergling";"Larva";392;1
"Unit";"Zergling";"Larva";392;1
"Unit";"Zergling";"Larva";392;1
"Unit";"Zergling";"Larva";392;1
"Unit";"Zergling";"Larva";392;1
"Unit";"Zergling";"Larva";392;1
"Unit";"Zergling";"Larva";392;1
"Building";"Extractor";NA;392;0
"Building";"Extractor";NA;392;0
"Unit";"Baneling";"Zergling";430;0
"Unit";"Baneling";"Zergling";430;0
"Unit";"Baneling";"Zergling";430;0
"Unit";"Baneling";"Zergling";430;0
"Unit";"Baneling";"Zergling";430;0
"Unit";"Baneling";"Zergling";430;0
"Unit";"Baneling";"Zergling";430;0
"Unit";"Baneling";"Zergling";430;0
"Unit";"Zergling";"Larva";430;1
"Unit";"Zergling";"Larva";430;1
"Unit";"Zergling";"Larva";430;1
"Unit";"Zergling";"Larva";430;1
"Unit";"Zergling";"Larva";430;1
"Unit";"Zergling";"Larva";430;1
"Unit";"Zergling";"Larva";430;1
"Unit";"Zergling";"Larva";430;1
"Unit";"Zergling";"Larva";430;1
"Unit";"Zergling";"Larva";430;1
"Unit";"Zergling";"Larva";430;1
"Unit";"Zergling";"Larva";430;1
"Unit";"Zergling";"Larva";430;1
"Unit";"Zergling";"Larva";430;1
"Unit";"Zergling";"Larva";430;1
"Unit";"Zergling";"Larva";430;1
"Unit";"Zergling";"Larva";430;1
"Unit";"Zergling";"Larva";430;1
"Unit";"Zergling";"Larva";430;1
"Unit";"Zergling";"Larva";430;1
"Unit";"Zergling";"Larva";430;1
"Unit";"Zergling";"Larva";430;1
"Unit";"Zergling";"Larva";430;1
"Unit";"Zergling";"Larva";430;1
"Unit";"Zergling";"Larva";430;1
"Unit";"Zergling";"Larva";430;1
"Unit";"Baneling";"Zergling";430;0
"Unit";"Baneling";"Zergling";430;0
"Unit";"Baneling";"Zergling";430;0
"Unit";"Baneling";"Zergling";430;0
"Unit";"Baneling";"Zergling";430;0
"Unit";"Baneling";"Zergling";430;0
"Unit";"Baneling";"Zergling";430;0
"Unit";"Zergling";"Larva";430;1
"Unit";"Zergling";"Larva";430;1
"Unit";"Zergling";"Larva";430;1
"Unit";"Zergling";"Larva";430;1
"Unit";"Zergling";"Larva";430;1
"Unit";"Zergling";"Larva";430;1
"Unit";"Zergling";"Larva";430;1
"Unit";"Zergling";"Larva";430;1
"Unit";"Zergling";"Larva";430;1
"Unit";"Zergling";"Larva";430;1
"Unit";"Zergling";"Larva";430;1
"Unit";"Zergling";"Larva";430;1
"Unit";"Zergling";"Larva";430;1
"Unit";"Zergling";"Larva";430;1
"Unit";"Zergling";"Larva";430;1
"Unit";"Zergling";"Larva";430;1
"Unit";"Overlord";"Larva";456;0
"Unit";"Overlord";"Larva";456;0
"Unit";"Overlord";"Larva";456;0
"Building";"CreepTumor";NA;481;0
"Building";"UltraliskCavern";NA;481;0
"Unit";"Baneling";"Zergling";483;0
"Unit";"Baneling";"Zergling";483;0
"Unit";"Baneling";"Zergling";483;0
"Unit";"Baneling";"Zergling";483;0
"Unit";"Baneling";"Zergling";483;0
"Unit";"Baneling";"Zergling";483;0
"Building";"Extractor";NA;483;0
"Building";"CreepTumor";NA;483;0
"Building";"CreepTumor";NA;483;0
"Upgrade";"ZergMeleeWeaponsLevel3";"EvolutionChamber";481;0
"Upgrade";"ZergGroundArmorsLevel3";"EvolutionChamber";481;0
"Unit";"Ultralisk";"Larva";483;6
"Unit";"Ultralisk";"Larva";483;6
"Unit";"Ultralisk";"Larva";483;6
"Unit";"Ultralisk";"Larva";483;6
"Unit";"Ultralisk";"Larva";483;6
"Unit";"Ultralisk";"Larva";483;6
"Unit";"Ultralisk";"Larva";483;6
"Unit";"Ultralisk";"Larva";483;6
"Unit";"Ultralisk";"Larva";483;6
"Unit";"Ultralisk";"Larva";483;6
"Building";"CreepTumor";NA;483;0
"Building";"Hatchery";NA;481;0
"Unit";"Zergling";"Larva";483;1
"Unit";"Zergling";"Larva";483;1
"Unit";"Zergling";"Larva";483;1
"Unit";"Zergling";"Larva";483;1
"Unit";"Zergling";"Larva";483;1
"Unit";"Zergling";"Larva";483;1
"Unit";"Zergling";"Larva";483;1
"Unit";"Zergling";"Larva";483;1
"Unit";"Zergling";"Larva";483;1
"Unit";"Zergling";"Larva";483;1
"Unit";"Zergling";"Larva";483;1
"Unit";"Zergling";"Larva";483;1
"Unit";"Zergling";"Larva";483;1
"Unit";"Zergling";"Larva";483;1
"Unit";"Zergling";"Larva";483;1
"Unit";"Zergling";"Larva";483;1
"Unit";"Zergling";"Larva";483;1
"Unit";"Zergling";"Larva";483;1
"Unit";"Zergling";"Larva";483;1
"Unit";"Zergling";"Larva";483;1
"Unit";"Zergling";"Larva";483;1
"Unit";"Zergling";"Larva";483;1
"Unit";"Zergling";"Larva";483;1
"Unit";"Zergling";"Larva";483;1
"Unit";"Zergling";"Larva";483;1
"Unit";"Zergling";"Larva";483;1
"Unit";"Zergling";"Larva";483;1
"Unit";"Zergling";"Larva";483;1
"Unit";"Zergling";"Larva";483;1
"Unit";"Zergling";"Larva";483;1
"Unit";"Zergling";"Larva";483;1
"Unit";"Zergling";"Larva";483;1
"Unit";"Zergling";"Larva";483;1
"Unit";"Zergling";"Larva";483;1
"Unit";"Zergling";"Larva";483;1
"Unit";"Zergling";"Larva";483;1
"Unit";"Zergling";"Larva";483;1
"Unit";"Zergling";"Larva";483;1
"Unit";"Zergling";"Larva";483;1
"Unit";"Zergling";"Larva";483;1
"Unit";"Zergling";"Larva";483;1
"Unit";"Zergling";"Larva";483;1
"Building";"Hatchery";NA;483;0
"Unit";"Zergling";"Larva";585;1
"Unit";"Zergling";"Larva";585;1
"Upgrade";"ChitinousPlating";"UltraliskCavern";483;0
"Unit";"Zergling";"Larva";587;1
"Unit";"Zergling";"Larva";587;1
"Unit";"Zergling";"Larva";587;1
"Unit";"Zergling";"Larva";587;1
"Unit";"Zergling";"Larva";587;1
"Unit";"Zergling";"Larva";587;1
"Unit";"Zergling";"Larva";587;1
"Unit";"Zergling";"Larva";587;1
"Unit";"Zergling";"Larva";587;1
"Unit";"Zergling";"Larva";587;1
"Unit";"Zergling";"Larva";587;1
"Unit";"Zergling";"Larva";587;1
"Unit";"Zergling";"Larva";587;1
"Unit";"Zergling";"Larva";587;1
"Unit";"Zergling";"Larva";587;1
"Unit";"Zergling";"Larva";587;1
"Unit";"Zergling";"Larva";587;1
"Unit";"Zergling";"Larva";587;1
"Unit";"Zergling";"Larva";587;1
"Unit";"Zergling";"Larva";587;1
"Unit";"Zergling";"Larva";587;1
"Unit";"Zergling";"Larva";587;1
"Unit";"Zergling";"Larva";587;1
"Unit";"Zergling";"Larva";587;1
"Unit";"Zergling";"Larva";587;1
"Unit";"Zergling";"Larva";587;1
"Unit";"Zergling";"Larva";587;1
"Unit";"Zergling";"Larva";587;1
"Unit";"Ultralisk";"Larva";587;6
"Unit";"Ultralisk";"Larva";587;6
"Unit";"Ultralisk";"Larva";587;6
"Unit";"Ultralisk";"Larva";587;6
"Unit";"Ultralisk";"Larva";587;6
"Unit";"Ultralisk";"Larva";587;6
"Unit";"Ultralisk";"Larva";587;6
"Unit";"Ultralisk";"Larva";587;6
"Building";"SporeCrawler";NA;587;0
"Unit";"Baneling";"Zergling";615;0
"Unit";"Baneling";"Zergling";615;0
"Unit";"Baneling";"Zergling";615;0
"Unit";"Baneling";"Zergling";615;0
"Unit";"Baneling";"Zergling";615;0
"Unit";"Baneling";"Zergling";615;0
"Unit";"Zergling";"Larva";615;1
"Unit";"Zergling";"Larva";615;1
"Unit";"Zergling";"Larva";615;1
"Unit";"Zergling";"Larva";615;1
"Unit";"Zergling";"Larva";615;1
"Unit";"Zergling";"Larva";615;1
"Unit";"Zergling";"Larva";615;1
"Unit";"Zergling";"Larva";615;1
"Unit";"Zergling";"Larva";615;1
"Unit";"Zergling";"Larva";615;1
"Unit";"Zergling";"Larva";615;1
"Unit";"Zergling";"Larva";615;1
"Unit";"Zergling";"Larva";615;1
"Unit";"Zergling";"Larva";615;1
"Unit";"Zergling";"Larva";615;1
"Unit";"Zergling";"Larva";615;1
"Unit";"Zergling";"Larva";615;1
"Unit";"Zergling";"Larva";615;1
"Unit";"Zergling";"Larva";615;1
"Unit";"Zergling";"Larva";615;1
"Unit";"Zergling";"Larva";615;1
"Unit";"Zergling";"Larva";615;1
"Unit";"Infestor";"Larva";587;2
"Unit";"Infestor";"Larva";587;2
"Unit";"Infestor";"Larva";587;2
"Unit";"Infestor";"Larva";587;2
"Unit";"Infestor";"Larva";587;2
"Building";"SpineCrawler";NA;587;0
"Building";"SpineCrawler";NA;587;0
"Unit";"Zergling";"Larva";695;1
"Unit";"Zergling";"Larva";695;1
"Unit";"Zergling";"Larva";695;1
"Unit";"Zergling";"Larva";695;1
"Unit";"Zergling";"Larva";695;1
"Unit";"Zergling";"Larva";695;1
"Unit";"Zergling";"Larva";695;1
"Unit";"Zergling";"Larva";695;1
"Unit";"Zergling";"Larva";695;1
"Unit";"Zergling";"Larva";695;1
"Unit";"Zergling";"Larva";695;1
"Unit";"Zergling";"Larva";695;1
"Unit";"Zergling";"Larva";695;1
"Unit";"Zergling";"Larva";695;1
"Unit";"Zergling";"Larva";695;1
"Unit";"Zergling";"Larva";695;1
"Unit";"Zergling";"Larva";695;1
"Unit";"Zergling";"Larva";695;1
"Unit";"Zergling";"Larva";695;1
"Unit";"Zergling";"Larva";695;1
"Unit";"Zergling";"Larva";695;1
"Unit";"Zergling";"Larva";695;1
"Unit";"Zergling";"Larva";695;1
"Unit";"Zergling";"Larva";695;1
"Unit";"Zergling";"Larva";695;1
"Unit";"Zergling";"Larva";695;1
"Unit";"Zergling";"Larva";695;1
"Unit";"Zergling";"Larva";695;1
"Unit";"Zergling";"Larva";695;1
"Unit";"Zergling";"Larva";695;1
"Unit";"Zergling";"Larva";695;1
"Unit";"Zergling";"Larva";695;1
"Unit";"Zergling";"Larva";695;1
"Unit";"Zergling";"Larva";695;1
"Unit";"Zergling";"Larva";695;1
"Unit";"Zergling";"Larva";695;1
"Unit";"Zergling";"Larva";695;1
"Unit";"Zergling";"Larva";695;1
"Unit";"Zergling";"Larva";695;1
"Unit";"Zergling";"Larva";695;1
"Unit";"Zergling";"Larva";695;1
"Unit";"Zergling";"Larva";695;1
"Unit";"Zergling";"Larva";695;1
"Unit";"Zergling";"Larva";695;1
"Building";"Extractor";NA;695;0
"Building";"Extractor";NA;695;0
"Unit";"Ultralisk";"Larva";695;6
"Unit";"Ultralisk";"Larva";695;6
"Unit";"Ultralisk";"Larva";695;6
"Building";"SporeCrawler";NA;757;0
"Building";"SporeCrawler";NA;757;0
"Unit";"Zergling";"Larva";766;1
"Unit";"Zergling";"Larva";766;1
"Unit";"Zergling";"Larva";766;1
"Unit";"Zergling";"Larva";766;1
"Unit";"Zergling";"Larva";766;1
"Unit";"Zergling";"Larva";766;1
"Unit";"Zergling";"Larva";766;1
"Unit";"Zergling";"Larva";766;1
"Unit";"Zergling";"Larva";766;1
"Unit";"Zergling";"Larva";766;1
"Unit";"Zergling";"Larva";766;1
"Unit";"Zergling";"Larva";766;1
"Unit";"Zergling";"Larva";766;1
"Unit";"Zergling";"Larva";766;1
"Unit";"Zergling";"Larva";766;1
"Unit";"Zergling";"Larva";766;1
"Building";"CreepTumorQueen";NA;782;0
"Unit";"Infestor";"Larva";782;2
"Unit";"Infestor";"Larva";782;2
"Unit";"Infestor";"Larva";782;2
"Unit";"Infestor";"Larva";782;2
"Unit";"Infestor";"Larva";782;2
"Unit";"Ultralisk";"Larva";782;6
"Unit";"Ultralisk";"Larva";782;6
"Unit";"Ultralisk";"Larva";782;6
"Unit";"Ultralisk";"Larva";782;6
"Building";"Hatchery";NA;782;0
"Unit";"Zergling";"Larva";816;1
"Unit";"Zergling";"Larva";816;1
"Unit";"Zergling";"Larva";816;1
"Unit";"Zergling";"Larva";816;1
"Unit";"Zergling";"Larva";816;1
"Unit";"Zergling";"Larva";816;1
"Unit";"Zergling";"Larva";816;1
"Unit";"Zergling";"Larva";816;1
"Unit";"Zergling";"Larva";816;1
"Unit";"Zergling";"Larva";816;1
"Unit";"Zergling";"Larva";816;1
"Unit";"Zergling";"Larva";816;1
"Unit";"Zergling";"Larva";816;1
"Unit";"Zergling";"Larva";816;1
"Unit";"Zergling";"Larva";816;1
"Unit";"Zergling";"Larva";816;1
"Unit";"Zergling";"Larva";816;1
"Unit";"Zergling";"Larva";816;1
"Unit";"Zergling";"Larva";816;1
"Unit";"Zergling";"Larva";816;1
"Unit";"Zergling";"Larva";816;1
"Unit";"Zergling";"Larva";816;1
"Unit";"Zergling";"Larva";816;1
"Unit";"Zergling";"Larva";816;1
"Unit";"Zergling";"Larva";840;1
"Unit";"Zergling";"Larva";840;1
"Unit";"Zergling";"Larva";840;1
"Unit";"Zergling";"Larva";840;1
"Unit";"Zergling";"Larva";840;1
"Unit";"Zergling";"Larva";840;1
"Unit";"Zergling";"Larva";840;1
"Unit";"Zergling";"Larva";840;1
"Unit";"Zergling";"Larva";840;1
"Unit";"Zergling";"Larva";840;1
"Unit";"Zergling";"Larva";840;1
"Unit";"Zergling";"Larva";840;1
"Unit";"Zergling";"Larva";840;1
"Unit";"Zergling";"Larva";840;1
"Unit";"Zergling";"Larva";840;1
"Unit";"Zergling";"Larva";840;1
"Unit";"Zergling";"Larva";840;1
"Unit";"Zergling";"Larva";840;1
"Unit";"Zergling";"Larva";840;1
"Unit";"Zergling";"Larva";840;1
"Unit";"Zergling";"Larva";840;1
"Unit";"Zergling";"Larva";840;1
"Unit";"Zergling";"Larva";840;1
"Unit";"Zergling";"Larva";840;1
"Unit";"Zergling";"Larva";840;1
"Unit";"Zergling";"Larva";840;1
"Unit";"Zergling";"Larva";840;1
"Unit";"Zergling";"Larva";840;1
"Unit";"Baneling";"Zergling";840;0
"Unit";"Baneling";"Zergling";840;0
"Unit";"Baneling";"Zergling";840;0
"Unit";"Baneling";"Zergling";840;0
"Unit";"Baneling";"Zergling";840;0
"Unit";"Baneling";"Zergling";840;0
"Unit";"Baneling";"Zergling";840;0
"Unit";"Baneling";"Zergling";840;0
"Building";"CreepTumorQueen";NA;840;0
"Building";"Extractor";NA;840;0
"Building";"Extractor";NA;840;0
"Unit";"Queen";"Hatchery";816;2
"Unit";"Queen";"Hatchery";816;2
"Unit";"Infestor";"Larva";840;2
"Unit";"Infestor";"Larva";840;2
"Unit";"Infestor";"Larva";840;2
"Unit";"Infestor";"Larva";840;2
"Unit";"Infestor";"Larva";840;2
"Unit";"Infestor";"Larva";840;2
"Unit";"Ultralisk";"Larva";876;6
"Unit";"Ultralisk";"Larva";876;6
"Unit";"Ultralisk";"Larva";876;6
"Unit";"Ultralisk";"Larva";876;6
"Unit";"Zergling";"Larva";912;1
"Unit";"Zergling";"Larva";912;1
"Unit";"Ultralisk";"Larva";888;6
"Unit";"Ultralisk";"Larva";888;6
"Unit";"Ultralisk";"Larva";888;6
"Unit";"Ultralisk";"Larva";888;6
"Building";"CreepTumor";NA;938;0
"Unit";"Ultralisk";"Larva";938;6
"Unit";"Ultralisk";"Larva";938;6
"Unit";"Zergling";"Larva";938;1
"Unit";"Zergling";"Larva";938;1
"Unit";"Ultralisk";"Larva";938;6
"Unit";"Zergling";"Larva";938;1
"Unit";"Zergling";"Larva";938;1
"Unit";"Zergling";"Larva";938;1
"Unit";"Zergling";"Larva";938;1
"Unit";"Zergling";"Larva";938;1
"Unit";"Zergling";"Larva";938;1
"Unit";"Zergling";"Larva";938;1
"Unit";"Zergling";"Larva";938;1
"Unit";"Zergling";"Larva";938;1
"Unit";"Zergling";"Larva";938;1
"Unit";"Zergling";"Larva";938;1
"Unit";"Zergling";"Larva";938;1
"Unit";"Zergling";"Larva";938;1
"Unit";"Zergling";"Larva";938;1
"Unit";"Zergling";"Larva";938;1
"Unit";"Zergling";"Larva";938;1
"Unit";"Zergling";"Larva";938;1
"Unit";"Zergling";"Larva";938;1
"Unit";"Zergling";"Larva";938;1
"Unit";"Zergling";"Larva";938;1
"Unit";"Zergling";"Larva";938;1
"Unit";"Zergling";"Larva";938;1
"Unit";"Zergling";"Larva";938;1
"Unit";"Zergling";"Larva";938;1
"Unit";"Zergling";"Larva";938;1
"Unit";"Zergling";"Larva";938;1
"Unit";"Zergling";"Larva";938;1
"Unit";"Zergling";"Larva";938;1
"Building";"Extractor";NA;986;0
"Building";"Hatchery";NA;938;0
"Unit";"Ultralisk";"Larva";986;6
"Unit";"Ultralisk";"Larva";986;6
"Unit";"Ultralisk";"Larva";986;6
"Unit";"Ultralisk";"Larva";986;6
"Unit";"Zergling";"Larva";1010;1
"Unit";"Zergling";"Larva";1010;1
"Unit";"Zergling";"Larva";1010;1
"Unit";"Zergling";"Larva";1010;1
"Unit";"Zergling";"Larva";1010;1
"Unit";"Zergling";"Larva";1010;1
"Unit";"Zergling";"Larva";1010;1
"Unit";"Zergling";"Larva";1010;1
"Unit";"Zergling";"Larva";1010;1
"Unit";"Zergling";"Larva";1010;1
"Unit";"Zergling";"Larva";1010;1
"Unit";"Zergling";"Larva";1010;1
"Unit";"Zergling";"Larva";1010;1
"Unit";"Zergling";"Larva";1010;1
"Unit";"Zergling";"Larva";1010;1
"Unit";"Zergling";"Larva";1010;1
"Unit";"Zergling";"Larva";1010;1
"Unit";"Zergling";"Larva";1010;1
"Unit";"Zergling";"Larva";1010;1
"Unit";"Zergling";"Larva";1010;1
"Unit";"Zergling";"Larva";1014;1
"Unit";"Zergling";"Larva";1014;1
"Unit";"Zergling";"Larva";1014;1
"Unit";"Zergling";"Larva";1014;1
"Unit";"Zergling";"Larva";1014;1
"Unit";"Zergling";"Larva";1014;1
"Unit";"Zergling";"Larva";1014;1
"Unit";"Zergling";"Larva";1014;1
"Unit";"Zergling";"Larva";1014;1
"Unit";"Zergling";"Larva";1014;1
"Unit";"Zergling";"Larva";1014;1
"Unit";"Zergling";"Larva";1014;1
"Unit";"Zergling";"Larva";1014;1
"Unit";"Zergling";"Larva";1014;1
"Unit";"Zergling";"Larva";1030;1
"Unit";"Zergling";"Larva";1030;1
"Unit";"Zergling";"Larva";1030;1
"Unit";"Zergling";"Larva";1030;1
"Unit";"Zergling";"Larva";1030;1
"Unit";"Zergling";"Larva";1030;1
"Unit";"Zergling";"Larva";1030;1
"Unit";"Zergling";"Larva";1030;1
"Unit";"Zergling";"Larva";1030;1
"Unit";"Zergling";"Larva";1030;1
"Building";"Extractor";NA;1054;0
"Building";"CreepTumor";NA;1054;0
"Unit";"Queen";"Hatchery";1054;2
"Unit";"Queen";"Hatchery";1054;2
"Unit";"Queen";"Hatchery";1054;2
"Unit";"Queen";"Hatchery";1054;2
"Unit";"Queen";"Hatchery";1054;2
"Building";"Hatchery";NA;1054;0
"Unit";"Ultralisk";"Larva";1054;6
"Unit";"Ultralisk";"Larva";1054;6
