"type";"unit_name";"on_building";"total_supply";"supply"
"Unit";"Overlord";"Larva";13;0
"Building";"Extractor";NA;17;0
"Building";"SpawningPool";NA;18;0
"Building";"Hatchery";NA;17;0
"Unit";"Overlord";"Larva";23;0
"Unit";"Zergling";"Larva";23;1
"Unit";"Zergling";"Larva";23;1
"Unit";"Zergling";"Larva";23;1
"Unit";"Zergling";"Larva";23;1
"Unit";"Queen";"Hatchery";23;2
"Unit";"Queen";"Hatchery";23;2
"Unit";"Zergling";"Larva";27;1
"Unit";"Zergling";"Larva";27;1
"Unit";"Zergling";"Larva";27;1
"Unit";"Zergling";"Larva";27;1
"Building";"CreepTumorQueen";NA;37;0
"Unit";"Overlord";"Larva";37;0
"Unit";"Overlord";"Larva";37;0
"Unit";"Queen";"Hatchery";37;2
"Building";"CreepTumor";NA;38;0
"Building";"BanelingNest";NA;37;0
"Building";"CreepTumorQueen";NA;46;0
"Building";"Extractor";NA;48;0
"Unit";"Overlord";"Larva";50;0
"Unit";"Overlord";"Larva";50;0
"Building";"CreepTumor";NA;54;0
"Building";"CreepTumorQueen";NA;54;0
"Building";"CreepTumor";NA;54;0
"Building";"Extractor";NA;54;0
"Unit";"Overlord";"Larva";57;0
"Unit";"Overlord";"Larva";57;0
"Unit";"Zergling";"Larva";59;1
"Unit";"Zergling";"Larva";59;1
"Unit";"Zergling";"Larva";59;1
"Unit";"Zergling";"Larva";59;1
"Unit";"Zergling";"Larva";59;1
"Unit";"Zergling";"Larva";59;1
"Unit";"Zergling";"Larva";59;1
"Unit";"Zergling";"Larva";59;1
"Unit";"Zergling";"Larva";59;1
"Unit";"Zergling";"Larva";59;1
"Building";"Extractor";NA;59;0
"Building";"CreepTumorQueen";NA;75;0
"Building";"CreepTumor";NA;75;0
"Building";"CreepTumor";NA;75;0
"Unit";"Overlord";"Larva";72;0
"Unit";"Overlord";"Larva";72;0
"Unit";"Overlord";"Larva";72;0
"Unit";"Zergling";"Larva";72;1
"Unit";"Zergling";"Larva";72;1
"Unit";"Zergling";"Larva";72;1
"Unit";"Zergling";"Larva";72;1
"Unit";"Zergling";"Larva";72;1
"Unit";"Zergling";"Larva";72;1
"Building";"EvolutionChamber";NA;75;0
"Building";"CreepTumor";NA;82;0
"Building";"CreepTumor";NA;82;0
"Building";"CreepTumorQueen";NA;84;0
"Building";"CreepTumor";NA;82;0
"Building";"CreepTumor";NA;84;0
"Building";"Spire";NA;59;0
"Unit";"Zergling";"Larva";84;1
"Unit";"Zergling";"Larva";84;1
"Unit";"Zergling";"Larva";84;1
"Unit";"Zergling";"Larva";84;1
"Unit";"Zergling";"Larva";84;1
"Unit";"Zergling";"Larva";84;1
"Unit";"Zergling";"Larva";84;1
"Unit";"Zergling";"Larva";84;1
"Unit";"Zergling";"Larva";84;1
"Unit";"Zergling";"Larva";84;1
"Unit";"Zergling";"Larva";84;1
"Unit";"Zergling";"Larva";84;1
"Unit";"Zergling";"Larva";84;1
"Unit";"Zergling";"Larva";84;1
"Unit";"Zergling";"Larva";84;1
"Unit";"Zergling";"Larva";84;1
"Unit";"Baneling";"Zergling";100;0
"Building";"CreepTumor";NA;100;0
"Unit";"Baneling";"Zergling";100;0
"Unit";"Baneling";"Zergling";100;0
"Unit";"Baneling";"Zergling";100;0
"Unit";"Baneling";"Zergling";100;0
"Unit";"Baneling";"Zergling";100;0
"Unit";"Baneling";"Zergling";100;0
"Unit";"Zergling";"Larva";100;1
"Unit";"Zergling";"Larva";100;1
"Building";"CreepTumor";NA;100;0
"Unit";"Zergling";"Larva";100;1
"Unit";"Zergling";"Larva";100;1
"Unit";"Zergling";"Larva";100;1
"Unit";"Zergling";"Larva";100;1
"Unit";"Baneling";"Zergling";100;0
"Unit";"Zergling";"Larva";100;1
"Unit";"Zergling";"Larva";100;1
"Unit";"Zergling";"Larva";100;1
"Unit";"Zergling";"Larva";100;1
"Unit";"Baneling";"Zergling";100;0
"Unit";"Baneling";"Zergling";100;0
"Building";"CreepTumor";NA;100;0
"Building";"CreepTumor";NA;100;0
"Building";"CreepTumor";NA;100;0
"Building";"CreepTumorQueen";NA;100;0
"Building";"Hatchery";NA;75;0
"Unit";"Zergling";"Larva";100;1
"Unit";"Zergling";"Larva";100;1
"Unit";"Zergling";"Larva";100;1
"Unit";"Zergling";"Larva";100;1
"Unit";"Zergling";"Larva";100;1
"Unit";"Zergling";"Larva";100;1
"Unit";"Zergling";"Larva";100;1
"Unit";"Zergling";"Larva";100;1
"Unit";"Zergling";"Larva";118;1
"Unit";"Zergling";"Larva";118;1
"Unit";"Zergling";"Larva";118;1
"Unit";"Zergling";"Larva";118;1
"Unit";"Zergling";"Larva";118;1
"Unit";"Zergling";"Larva";118;1
"Unit";"Zergling";"Larva";118;1
"Unit";"Zergling";"Larva";118;1
"Unit";"Zergling";"Larva";118;1
"Unit";"Zergling";"Larva";118;1
"Unit";"Zergling";"Larva";118;1
"Unit";"Zergling";"Larva";118;1
"Unit";"Zergling";"Larva";118;1
"Unit";"Zergling";"Larva";118;1
"Unit";"Zergling";"Larva";118;1
"Unit";"Zergling";"Larva";118;1
"Unit";"Zergling";"Larva";118;1
"Unit";"Zergling";"Larva";118;1
"Unit";"Zergling";"Larva";118;1
"Unit";"Zergling";"Larva";118;1
"Building";"CreepTumor";NA;139;0
"Building";"CreepTumor";NA;139;0
"Building";"CreepTumor";NA;139;0
"Building";"CreepTumor";NA;139;0
"Building";"CreepTumor";NA;139;0
"Building";"CreepTumor";NA;141;0
"Unit";"Queen";"Hatchery";118;2
"Unit";"Queen";"Hatchery";118;2
"Building";"SporeCrawler";NA;141;0
"Upgrade";"ZergMeleeWeaponsLevel1";"EvolutionChamber";100;0
"Building";"EvolutionChamber";NA;153;0
"Unit";"Overlord";"Larva";157;0
"Unit";"Overlord";"Larva";157;0
"Unit";"Overlord";"Larva";157;0
"Unit";"Overlord";"Larva";157;0
"Unit";"Baneling";"Zergling";164;0
"Unit";"Baneling";"Zergling";164;0
"Unit";"Baneling";"Zergling";164;0
"Unit";"Baneling";"Zergling";164;0
"Unit";"Baneling";"Zergling";164;0
"Unit";"Baneling";"Zergling";164;0
"Unit";"Baneling";"Zergling";164;0
"Unit";"Baneling";"Zergling";164;0
"Unit";"Baneling";"Zergling";164;0
"Unit";"Baneling";"Zergling";164;0
"Unit";"Baneling";"Zergling";164;0
"Unit";"Mutalisk";"Larva";163;2
"Unit";"Mutalisk";"Larva";163;2
"Unit";"Mutalisk";"Larva";164;2
"Unit";"Mutalisk";"Larva";164;2
"Unit";"Mutalisk";"Larva";164;2
"Unit";"Mutalisk";"Larva";164;2
"Unit";"Mutalisk";"Larva";164;2
"Unit";"Zergling";"Larva";164;1
"Unit";"Zergling";"Larva";164;1
"Unit";"Zergling";"Larva";164;1
"Unit";"Zergling";"Larva";164;1
"Unit";"Zergling";"Larva";164;1
"Unit";"Zergling";"Larva";164;1
"Unit";"Zergling";"Larva";164;1
"Unit";"Zergling";"Larva";164;1
"Unit";"Zergling";"Larva";164;1
"Unit";"Zergling";"Larva";164;1
"Unit";"Zergling";"Larva";164;1
"Unit";"Zergling";"Larva";164;1
"Unit";"Zergling";"Larva";164;1
"Unit";"Zergling";"Larva";164;1
"Unit";"Zergling";"Larva";164;1
"Unit";"Zergling";"Larva";164;1
"Unit";"Zergling";"Larva";164;1
"Unit";"Zergling";"Larva";164;1
"Unit";"Zergling";"Larva";164;1
"Unit";"Zergling";"Larva";164;1
"Unit";"Zergling";"Larva";182;1
"Unit";"Zergling";"Larva";182;1
"Unit";"Zergling";"Larva";192;1
"Unit";"Zergling";"Larva";192;1
"Building";"Extractor";NA;196;0
"Unit";"Overlord";"Larva";198;0
"Building";"Hatchery";NA;163;0
"Unit";"Overlord";"Larva";200;0
"Building";"Extractor";NA;198;0
"Unit";"Mutalisk";"Larva";208;2
"Unit";"Mutalisk";"Larva";208;2
"Unit";"Mutalisk";"Larva";208;2
"Unit";"Mutalisk";"Larva";208;2
"Unit";"Mutalisk";"Larva";208;2
"Unit";"Mutalisk";"Larva";208;2
"Unit";"Mutalisk";"Larva";208;2
"Unit";"Mutalisk";"Larva";208;2
"Unit";"Mutalisk";"Larva";208;2
"Unit";"Zergling";"Larva";226;1
"Unit";"Zergling";"Larva";226;1
"Unit";"Queen";"Hatchery";208;2
"Unit";"Zergling";"Larva";226;1
"Unit";"Zergling";"Larva";226;1
"Unit";"Zergling";"Larva";226;1
"Unit";"Zergling";"Larva";226;1
"Unit";"Zergling";"Larva";226;1
"Unit";"Zergling";"Larva";226;1
"Unit";"Zergling";"Larva";226;1
"Unit";"Zergling";"Larva";226;1
"Unit";"Zergling";"Larva";226;1
"Unit";"Zergling";"Larva";226;1
"Unit";"Zergling";"Larva";226;1
"Unit";"Zergling";"Larva";226;1
"Unit";"Zergling";"Larva";226;1
"Unit";"Zergling";"Larva";226;1
"Unit";"Zergling";"Larva";226;1
"Unit";"Zergling";"Larva";226;1
"Unit";"Zergling";"Larva";226;1
"Unit";"Zergling";"Larva";226;1
"Unit";"Zergling";"Larva";226;1
"Unit";"Zergling";"Larva";226;1
"Building";"InfestationPit";NA;208;0
"Unit";"Overlord";"Larva";226;0
"Unit";"Overlord";"Larva";226;0
"Unit";"Overlord";"Larva";226;0
"Unit";"Overlord";"Larva";226;0
"Upgrade";"ZergMeleeWeaponsLevel2";"EvolutionChamber";164;0
"Unit";"Zergling";"Larva";230;1
"Unit";"Zergling";"Larva";230;1
"Unit";"Zergling";"Larva";244;1
"Unit";"Zergling";"Larva";244;1
"Unit";"Zergling";"Larva";244;1
"Unit";"Zergling";"Larva";244;1
"Unit";"Zergling";"Larva";248;1
"Unit";"Zergling";"Larva";248;1
"Unit";"Zergling";"Larva";248;1
"Unit";"Zergling";"Larva";248;1
"Unit";"Zergling";"Larva";248;1
"Unit";"Zergling";"Larva";248;1
"Building";"CreepTumor";NA;262;0
"Building";"CreepTumor";NA;262;0
"Building";"CreepTumor";NA;262;0
"Building";"CreepTumor";NA;262;0
"Unit";"Baneling";"Zergling";262;0
"Unit";"Baneling";"Zergling";262;0
"Unit";"Baneling";"Zergling";262;0
"Unit";"Baneling";"Zergling";262;0
"Unit";"Baneling";"Zergling";262;0
"Unit";"Baneling";"Zergling";262;0
"Unit";"Baneling";"Zergling";262;0
"Unit";"Baneling";"Zergling";262;0
"Unit";"Baneling";"Zergling";262;0
"Unit";"Zergling";"Larva";262;1
"Unit";"Zergling";"Larva";262;1
"Unit";"Baneling";"Zergling";262;0
"Unit";"Baneling";"Zergling";262;0
"Unit";"Baneling";"Zergling";262;0
"Unit";"Baneling";"Zergling";262;0
"Unit";"Zergling";"Larva";262;1
"Unit";"Zergling";"Larva";262;1
"Unit";"Zergling";"Larva";262;1
"Unit";"Zergling";"Larva";262;1
"Unit";"Zergling";"Larva";262;1
"Unit";"Zergling";"Larva";262;1
"Unit";"Zergling";"Larva";262;1
"Unit";"Zergling";"Larva";262;1
"Unit";"Zergling";"Larva";262;1
"Unit";"Zergling";"Larva";262;1
"Unit";"Zergling";"Larva";262;1
"Unit";"Zergling";"Larva";262;1
"Building";"CreepTumorQueen";NA;262;0
"Building";"CreepTumorQueen";NA;262;0
"Building";"CreepTumorQueen";NA;276;0
"Building";"Hatchery";NA;226;0
