"type";"unit_name";"on_building";"total_supply";"supply"
"Unit";"Overlord";"Larva";13;0
"Building";"Extractor";NA;18;0
"Building";"Hatchery";NA;17;0
"Building";"SpawningPool";NA;18;0
"Unit";"Zergling";"Larva";24;1
"Unit";"Zergling";"Larva";24;1
"Unit";"Zergling";"Larva";24;1
"Unit";"Zergling";"Larva";24;1
"Unit";"Overlord";"Larva";25;0
"Unit";"Queen";"Hatchery";24;2
"Unit";"Queen";"Hatchery";24;2
"Unit";"Overlord";"Larva";39;0
"Unit";"Queen";"Hatchery";34;2
"Building";"CreepTumorQueen";NA;43;0
"Unit";"Overlord";"Larva";43;0
"Unit";"Overlord";"Larva";43;0
"Unit";"Queen";"Hatchery";43;2
"Unit";"Overlord";"Larva";49;0
"Building";"Hatchery";NA;34;0
"Building";"CreepTumorQueen";NA;53;0
"Building";"CreepTumorQueen";NA;53;0
"Unit";"Queen";"Hatchery";51;2
"Unit";"Zergling";"Larva";60;1
"Unit";"Zergling";"Larva";60;1
"Unit";"Zergling";"Larva";60;1
"Unit";"Zergling";"Larva";60;1
"Unit";"Zergling";"Larva";60;1
"Unit";"Zergling";"Larva";60;1
"Unit";"Zergling";"Larva";60;1
"Unit";"Zergling";"Larva";60;1
"Unit";"Zergling";"Larva";60;1
"Unit";"Zergling";"Larva";60;1
"Building";"CreepTumorQueen";NA;60;0
"Unit";"Queen";"Hatchery";51;2
"Building";"Extractor";NA;60;0
"Building";"Extractor";NA;60;0
"Building";"EvolutionChamber";NA;62;0
"Building";"EvolutionChamber";NA;62;0
"Building";"CreepTumor";NA;74;0
"Building";"CreepTumor";NA;74;0
"Building";"CreepTumor";NA;74;0
"Building";"CreepTumor";NA;87;0
"Building";"CreepTumor";NA;87;0
"Building";"HydraliskDen";NA;87;0
"Building";"CreepTumor";NA;87;0
"Building";"Extractor";NA;87;0
"Building";"CreepTumorQueen";NA;87;0
"Unit";"Overlord";"Larva";87;0
"Unit";"Overlord";"Larva";87;0
"Unit";"Overlord";"Larva";87;0
"Unit";"Overlord";"Larva";87;0
"Unit";"Overlord";"Larva";87;0
"Unit";"Zergling";"Larva";92;1
"Unit";"Zergling";"Larva";92;1
"Unit";"Zergling";"Larva";92;1
"Unit";"Zergling";"Larva";92;1
"Unit";"Zergling";"Larva";92;1
"Unit";"Zergling";"Larva";92;1
"Unit";"Zergling";"Larva";92;1
"Unit";"Zergling";"Larva";92;1
"Unit";"Queen";"Hatchery";87;2
"Building";"BanelingNest";NA;87;0
"Building";"Hatchery";NA;87;0
"Building";"CreepTumor";NA;102;0
"Building";"CreepTumor";NA;102;0
"Building";"CreepTumorQueen";NA;102;0
"Building";"CreepTumorQueen";NA;103;0
"Building";"CreepTumorQueen";NA;103;0
"Building";"CreepTumorQueen";NA;105;0
"Building";"Extractor";NA;102;0
"Building";"Extractor";NA;102;0
"Unit";"Zergling";"Larva";102;1
"Unit";"Zergling";"Larva";102;1
"Unit";"Zergling";"Larva";102;1
"Unit";"Zergling";"Larva";102;1
"Unit";"Zergling";"Larva";102;1
"Unit";"Zergling";"Larva";102;1
"Unit";"Zergling";"Larva";102;1
"Unit";"Zergling";"Larva";102;1
"Unit";"Zergling";"Larva";102;1
"Unit";"Zergling";"Larva";102;1
"Unit";"Zergling";"Larva";102;1
"Unit";"Zergling";"Larva";102;1
"Unit";"Zergling";"Larva";102;1
"Unit";"Zergling";"Larva";102;1
"Unit";"Zergling";"Larva";102;1
"Unit";"Zergling";"Larva";102;1
"Unit";"Zergling";"Larva";102;1
"Unit";"Zergling";"Larva";102;1
"Unit";"Zergling";"Larva";102;1
"Unit";"Zergling";"Larva";102;1
"Unit";"Zergling";"Larva";102;1
"Unit";"Zergling";"Larva";102;1
"Unit";"Zergling";"Larva";102;1
"Unit";"Zergling";"Larva";102;1
"Unit";"Zergling";"Larva";102;1
"Unit";"Zergling";"Larva";102;1
"Building";"Hatchery";NA;87;0
"Upgrade";"EvolveGroovedSpines";"HydraliskDen";92;0
"Upgrade";"ZergMeleeWeaponsLevel1";"EvolutionChamber";87;0
"Unit";"Hydralisk";"Larva";106;2
"Building";"CreepTumor";NA;132;0
"Building";"CreepTumorQueen";NA;132;0
"Building";"CreepTumorQueen";NA;132;0
"Building";"CreepTumor";NA;132;0
"Building";"CreepTumor";NA;132;0
"Building";"CreepTumor";NA;132;0
"Unit";"Queen";"Hatchery";106;2
"Unit";"Queen";"Hatchery";132;2
"Building";"CreepTumor";NA;147;0
"Building";"CreepTumor";NA;149;0
"Building";"CreepTumor";NA;149;0
"Building";"CreepTumor";NA;149;0
"Building";"CreepTumor";NA;149;0
"Unit";"Hydralisk";"Larva";147;2
"Unit";"Hydralisk";"Larva";147;2
"Unit";"Hydralisk";"Larva";147;2
"Unit";"Hydralisk";"Larva";147;2
"Unit";"Hydralisk";"Larva";147;2
"Unit";"Overlord";"Larva";147;0
"Unit";"Overlord";"Larva";147;0
"Building";"CreepTumorQueen";NA;149;0
"Building";"CreepTumorQueen";NA;159;0
"Unit";"Baneling";"Zergling";149;0
"Building";"CreepTumorQueen";NA;159;0
"Unit";"Baneling";"Zergling";149;0
"Unit";"Baneling";"Zergling";149;0
"Unit";"Baneling";"Zergling";149;0
"Unit";"Baneling";"Zergling";151;0
"Unit";"Baneling";"Zergling";151;0
"Unit";"Baneling";"Zergling";151;0
"Unit";"Baneling";"Zergling";151;0
"Unit";"Baneling";"Zergling";151;0
"Unit";"Baneling";"Zergling";151;0
"Unit";"Baneling";"Zergling";155;0
"Unit";"Baneling";"Zergling";155;0
"Unit";"Baneling";"Zergling";159;0
"Unit";"Baneling";"Zergling";159;0
"Unit";"Baneling";"Zergling";159;0
"Unit";"Baneling";"Zergling";159;0
"Unit";"Baneling";"Zergling";159;0
"Unit";"Baneling";"Zergling";159;0
"Unit";"Baneling";"Zergling";159;0
"Unit";"Zergling";"Larva";159;1
"Unit";"Zergling";"Larva";159;1
"Unit";"Zergling";"Larva";159;1
"Unit";"Zergling";"Larva";159;1
"Unit";"Zergling";"Larva";159;1
"Unit";"Zergling";"Larva";159;1
"Unit";"Hydralisk";"Larva";159;2
"Unit";"Hydralisk";"Larva";159;2
"Unit";"Hydralisk";"Larva";159;2
"Building";"CreepTumor";NA;159;0
"Unit";"Zergling";"Larva";165;1
"Unit";"Zergling";"Larva";165;1
"Unit";"Zergling";"Larva";165;1
"Unit";"Zergling";"Larva";165;1
"Unit";"Zergling";"Larva";165;1
"Unit";"Zergling";"Larva";165;1
"Unit";"Zergling";"Larva";165;1
"Unit";"Zergling";"Larva";165;1
"Unit";"Zergling";"Larva";165;1
"Unit";"Zergling";"Larva";165;1
"Unit";"Zergling";"Larva";165;1
"Unit";"Zergling";"Larva";165;1
"Unit";"Zergling";"Larva";165;1
"Unit";"Zergling";"Larva";165;1
"Unit";"Zergling";"Larva";165;1
"Unit";"Zergling";"Larva";165;1
"Unit";"Zergling";"Larva";165;1
"Unit";"Zergling";"Larva";165;1
"Unit";"Zergling";"Larva";165;1
"Unit";"Zergling";"Larva";165;1
"Unit";"Zergling";"Larva";165;1
"Unit";"Zergling";"Larva";165;1
"Unit";"Zergling";"Larva";165;1
"Unit";"Zergling";"Larva";165;1
"Unit";"Queen";"Hatchery";159;2
"Upgrade";"ZergGroundArmorsLevel1";"EvolutionChamber";147;0
"Building";"CreepTumorQueen";NA;197;0
"Building";"CreepTumor";NA;197;0
"Building";"CreepTumor";NA;197;0
"Building";"CreepTumor";NA;197;0
"Building";"CreepTumor";NA;198;0
"Building";"CreepTumor";NA;217;0
"Building";"CreepTumor";NA;217;0
"Building";"CreepTumor";NA;217;0
"Unit";"Overlord";"Larva";217;0
"Unit";"Overlord";"Larva";217;0
"Unit";"Overlord";"Larva";217;0
"Unit";"Overlord";"Larva";217;0
"Building";"CreepTumorQueen";NA;222;0
"Building";"CreepTumorQueen";NA;222;0
"Building";"CreepTumorQueen";NA;222;0
"Building";"CreepTumorQueen";NA;222;0
"Upgrade";"ZergMeleeWeaponsLevel2";"EvolutionChamber";159;0
"Building";"CreepTumor";NA;222;0
"Unit";"Hydralisk";"Larva";222;2
"Unit";"Hydralisk";"Larva";222;2
"Unit";"Hydralisk";"Larva";222;2
"Unit";"Hydralisk";"Larva";222;2
"Unit";"Hydralisk";"Larva";222;2
"Unit";"Hydralisk";"Larva";222;2
"Unit";"Baneling";"Zergling";222;0
"Building";"Extractor";NA;222;0
"Unit";"Baneling";"Zergling";222;0
"Unit";"Baneling";"Zergling";222;0
"Unit";"Baneling";"Zergling";222;0
"Unit";"Baneling";"Zergling";222;0
"Unit";"Baneling";"Zergling";222;0
"Unit";"Baneling";"Zergling";222;0
"Unit";"Baneling";"Zergling";222;0
"Unit";"Baneling";"Zergling";222;0
"Unit";"Baneling";"Zergling";222;0
"Unit";"Baneling";"Zergling";222;0
"Unit";"Baneling";"Zergling";222;0
"Unit";"Baneling";"Zergling";222;0
"Unit";"Baneling";"Zergling";222;0
"Unit";"Baneling";"Zergling";222;0
"Unit";"Baneling";"Zergling";222;0
"Unit";"Baneling";"Zergling";222;0
"Unit";"Baneling";"Zergling";222;0
"Upgrade";"EvolveMuscularAugments";"HydraliskDen";217;0
"Unit";"Zergling";"Larva";222;1
"Unit";"Zergling";"Larva";222;1
"Unit";"Zergling";"Larva";222;1
"Unit";"Zergling";"Larva";222;1
"Unit";"Zergling";"Larva";222;1
"Unit";"Zergling";"Larva";222;1
"Unit";"Zergling";"Larva";222;1
"Unit";"Zergling";"Larva";222;1
"Unit";"Zergling";"Larva";222;1
"Unit";"Zergling";"Larva";222;1
"Unit";"Zergling";"Larva";222;1
"Unit";"Zergling";"Larva";222;1
"Unit";"Zergling";"Larva";222;1
"Unit";"Zergling";"Larva";222;1
"Unit";"Zergling";"Larva";222;1
"Unit";"Zergling";"Larva";222;1
"Unit";"Zergling";"Larva";222;1
"Unit";"Zergling";"Larva";222;1
"Unit";"Zergling";"Larva";222;1
"Unit";"Zergling";"Larva";222;1
"Unit";"Zergling";"Larva";222;1
"Unit";"Zergling";"Larva";222;1
"Unit";"Zergling";"Larva";234;1
"Unit";"Zergling";"Larva";234;1
"Unit";"Zergling";"Larva";234;1
"Unit";"Zergling";"Larva";234;1
"Unit";"Zergling";"Larva";234;1
"Unit";"Zergling";"Larva";234;1
"Unit";"Zergling";"Larva";234;1
"Unit";"Zergling";"Larva";234;1
"Building";"CreepTumor";NA;234;0
"Building";"CreepTumor";NA;234;0
"Building";"CreepTumor";NA;234;0
"Building";"CreepTumor";NA;234;0
"Building";"CreepTumor";NA;234;0
"Building";"CreepTumor";NA;234;0
"Unit";"Zergling";"Larva";256;1
"Unit";"Zergling";"Larva";256;1
"Unit";"Zergling";"Larva";256;1
"Unit";"Zergling";"Larva";256;1
"Unit";"Zergling";"Larva";256;1
"Unit";"Zergling";"Larva";256;1
"Unit";"Zergling";"Larva";256;1
"Unit";"Zergling";"Larva";256;1
"Unit";"Zergling";"Larva";256;1
"Unit";"Zergling";"Larva";256;1
"Unit";"Zergling";"Larva";256;1
"Unit";"Zergling";"Larva";256;1
"Unit";"Zergling";"Larva";256;1
"Unit";"Zergling";"Larva";256;1
"Unit";"Zergling";"Larva";256;1
"Unit";"Zergling";"Larva";256;1
"Unit";"Zergling";"Larva";256;1
"Unit";"Zergling";"Larva";256;1
"Unit";"Zergling";"Larva";256;1
"Unit";"Zergling";"Larva";256;1
"Unit";"Zergling";"Larva";256;1
"Unit";"Zergling";"Larva";256;1
"Unit";"Zergling";"Larva";256;1
"Unit";"Zergling";"Larva";256;1
"Unit";"Zergling";"Larva";256;1
"Unit";"Zergling";"Larva";256;1
"Unit";"Zergling";"Larva";256;1
"Unit";"Zergling";"Larva";256;1
"Building";"Hatchery";NA;217;0
"Building";"SporeCrawler";NA;264;0
"Building";"SporeCrawler";NA;264;0
"Building";"InfestationPit";NA;264;0
"Unit";"Overlord";"Larva";292;0
"Unit";"Overlord";"Larva";292;0
"Unit";"Overlord";"Larva";292;0
"Unit";"Overlord";"Larva";292;0
"Unit";"Overlord";"Larva";292;0
"Unit";"Baneling";"Zergling";292;0
"Unit";"Baneling";"Zergling";292;0
"Unit";"Baneling";"Zergling";292;0
"Unit";"Baneling";"Zergling";292;0
"Unit";"Baneling";"Zergling";292;0
"Unit";"Baneling";"Zergling";292;0
"Unit";"Baneling";"Zergling";292;0
"Unit";"Baneling";"Zergling";292;0
"Unit";"Zergling";"Larva";292;1
"Unit";"Zergling";"Larva";292;1
"Unit";"Hydralisk";"Larva";292;2
"Unit";"Hydralisk";"Larva";292;2
"Unit";"Hydralisk";"Larva";292;2
"Unit";"Zergling";"Larva";303;1
"Unit";"Zergling";"Larva";303;1
"Unit";"Zergling";"Larva";308;1
"Unit";"Zergling";"Larva";308;1
"Unit";"Zergling";"Larva";310;1
"Unit";"Zergling";"Larva";310;1
"Unit";"Zergling";"Larva";310;1
"Unit";"Zergling";"Larva";310;1
"Unit";"Zergling";"Larva";311;1
"Unit";"Zergling";"Larva";311;1
"Unit";"Zergling";"Larva";311;1
"Unit";"Zergling";"Larva";311;1
"Unit";"Zergling";"Larva";312;1
"Unit";"Zergling";"Larva";312;1
"Unit";"Zergling";"Larva";312;1
"Unit";"Zergling";"Larva";312;1
"Unit";"Zergling";"Larva";314;1
"Unit";"Zergling";"Larva";314;1
"Unit";"Baneling";"Zergling";339;0
"Unit";"Baneling";"Zergling";339;0
"Unit";"Baneling";"Zergling";339;0
"Unit";"Baneling";"Zergling";339;0
"Unit";"Baneling";"Zergling";339;0
"Unit";"Hydralisk";"Larva";321;2
"Unit";"Hydralisk";"Larva";321;2
"Unit";"Hydralisk";"Larva";321;2
"Unit";"Hydralisk";"Larva";321;2
"Unit";"Hydralisk";"Larva";321;2
"Unit";"Hydralisk";"Larva";321;2
"Unit";"Hydralisk";"Larva";321;2
"Upgrade";"ZergGroundArmorsLevel2";"EvolutionChamber";264;0
"Building";"SporeCrawler";NA;339;0
"Upgrade";"ZergMissileWeaponsLevel1";"EvolutionChamber";292;0
"Unit";"Zergling";"Larva";353;1
"Unit";"Zergling";"Larva";353;1
"Building";"CreepTumorQueen";NA;353;0
"Building";"CreepTumorQueen";NA;353;0
"Unit";"Zergling";"Larva";353;1
"Unit";"Zergling";"Larva";353;1
"Unit";"Zergling";"Larva";353;1
"Unit";"Zergling";"Larva";353;1
"Unit";"Zergling";"Larva";353;1
"Unit";"Zergling";"Larva";353;1
"Unit";"Zergling";"Larva";353;1
"Unit";"Zergling";"Larva";353;1
"Unit";"Zergling";"Larva";353;1
"Unit";"Zergling";"Larva";353;1
"Unit";"Zergling";"Larva";353;1
"Unit";"Zergling";"Larva";353;1
"Unit";"Zergling";"Larva";353;1
"Unit";"Zergling";"Larva";353;1
"Unit";"Zergling";"Larva";353;1
"Unit";"Zergling";"Larva";353;1
"Unit";"Zergling";"Larva";353;1
"Unit";"Zergling";"Larva";353;1
"Unit";"Zergling";"Larva";353;1
"Unit";"Zergling";"Larva";353;1
"Unit";"Zergling";"Larva";353;1
"Unit";"Zergling";"Larva";353;1
"Unit";"Zergling";"Larva";353;1
"Unit";"Zergling";"Larva";353;1
"Unit";"Zergling";"Larva";353;1
"Unit";"Zergling";"Larva";353;1
"Unit";"Zergling";"Larva";353;1
"Unit";"Zergling";"Larva";353;1
"Unit";"Zergling";"Larva";353;1
"Unit";"Zergling";"Larva";353;1
"Building";"CreepTumorQueen";NA;353;0
"Building";"CreepTumorQueen";NA;353;0
"Building";"CreepTumorQueen";NA;353;0
"Building";"SpineCrawler";NA;339;0
"Unit";"Queen";"Hatchery";339;2
"Building";"CreepTumor";NA;353;0
"Building";"CreepTumorQueen";NA;353;0
"Building";"CreepTumorQueen";NA;385;0
"Building";"CreepTumor";NA;385;0
"Building";"CreepTumor";NA;385;0
"Building";"CreepTumor";NA;385;0
"Building";"CreepTumorQueen";NA;385;0
"Unit";"Baneling";"Zergling";385;0
"Unit";"Baneling";"Zergling";385;0
"Unit";"Baneling";"Zergling";385;0
"Unit";"Baneling";"Zergling";385;0
"Unit";"Baneling";"Zergling";385;0
"Unit";"Baneling";"Zergling";385;0
"Unit";"Baneling";"Zergling";385;0
"Unit";"Baneling";"Zergling";385;0
"Unit";"Baneling";"Zergling";385;0
"Unit";"Baneling";"Zergling";385;0
"Unit";"Baneling";"Zergling";385;0
"Unit";"Baneling";"Zergling";385;0
"Unit";"Baneling";"Zergling";385;0
"Unit";"Baneling";"Zergling";385;0
"Unit";"Baneling";"Zergling";385;0
"Unit";"Baneling";"Zergling";385;0
"Unit";"Baneling";"Zergling";385;0
"Unit";"Baneling";"Zergling";385;0
"Unit";"Baneling";"Zergling";385;0
"Unit";"Baneling";"Zergling";385;0
"Unit";"Baneling";"Zergling";385;0
"Unit";"Baneling";"Zergling";385;0
"Unit";"Baneling";"Zergling";385;0
"Unit";"Zergling";"Larva";387;1
"Unit";"Zergling";"Larva";387;1
"Unit";"Zergling";"Larva";387;1
"Unit";"Zergling";"Larva";387;1
"Unit";"Zergling";"Larva";387;1
"Unit";"Zergling";"Larva";387;1
"Unit";"Zergling";"Larva";387;1
"Unit";"Zergling";"Larva";387;1
"Unit";"Zergling";"Larva";387;1
"Unit";"Zergling";"Larva";387;1
"Unit";"Zergling";"Larva";387;1
"Unit";"Zergling";"Larva";387;1
"Unit";"Zergling";"Larva";387;1
"Unit";"Zergling";"Larva";387;1
"Unit";"Zergling";"Larva";387;1
"Unit";"Zergling";"Larva";387;1
"Unit";"Zergling";"Larva";387;1
"Unit";"Zergling";"Larva";387;1
"Unit";"Zergling";"Larva";387;1
"Unit";"Zergling";"Larva";387;1
"Unit";"Zergling";"Larva";387;1
"Unit";"Zergling";"Larva";387;1
"Unit";"Zergling";"Larva";387;1
"Unit";"Zergling";"Larva";387;1
"Unit";"Zergling";"Larva";387;1
"Unit";"Zergling";"Larva";387;1
"Unit";"Zergling";"Larva";387;1
"Unit";"Zergling";"Larva";387;1
"Unit";"Zergling";"Larva";387;1
"Unit";"Zergling";"Larva";387;1
"Unit";"Zergling";"Larva";387;1
"Unit";"Zergling";"Larva";387;1
"Unit";"Zergling";"Larva";387;1
"Unit";"Zergling";"Larva";387;1
"Unit";"Zergling";"Larva";387;1
"Unit";"Zergling";"Larva";387;1
"Unit";"Zergling";"Larva";387;1
"Unit";"Zergling";"Larva";387;1
"Unit";"Zergling";"Larva";387;1
"Unit";"Zergling";"Larva";387;1
"Unit";"Zergling";"Larva";387;1
"Unit";"Zergling";"Larva";387;1
"Unit";"Zergling";"Larva";387;1
"Unit";"Zergling";"Larva";387;1
"Unit";"Zergling";"Larva";387;1
"Unit";"Zergling";"Larva";387;1
"Unit";"Zergling";"Larva";387;1
"Unit";"Zergling";"Larva";387;1
"Unit";"Zergling";"Larva";435;1
"Unit";"Zergling";"Larva";435;1
"Unit";"Zergling";"Larva";435;1
"Unit";"Zergling";"Larva";435;1
"Unit";"Zergling";"Larva";435;1
"Unit";"Zergling";"Larva";435;1
"Unit";"Zergling";"Larva";435;1
"Unit";"Zergling";"Larva";435;1
"Unit";"Zergling";"Larva";435;1
"Unit";"Zergling";"Larva";435;1
"Unit";"Zergling";"Larva";435;1
"Unit";"Zergling";"Larva";435;1
"Unit";"Zergling";"Larva";435;1
"Unit";"Zergling";"Larva";435;1
"Unit";"Zergling";"Larva";435;1
"Unit";"Zergling";"Larva";435;1
"Unit";"Zergling";"Larva";435;1
"Unit";"Zergling";"Larva";435;1
"Unit";"Zergling";"Larva";435;1
"Unit";"Zergling";"Larva";435;1
"Unit";"Zergling";"Larva";435;1
"Unit";"Zergling";"Larva";435;1
"Unit";"Zergling";"Larva";435;1
"Unit";"Zergling";"Larva";435;1
"Unit";"Zergling";"Larva";435;1
"Unit";"Zergling";"Larva";435;1
"Unit";"Zergling";"Larva";435;1
"Unit";"Zergling";"Larva";435;1
"Building";"CreepTumorQueen";NA;435;0
"Unit";"Baneling";"Zergling";463;0
"Unit";"Baneling";"Zergling";463;0
"Unit";"Baneling";"Zergling";463;0
"Unit";"Baneling";"Zergling";463;0
"Unit";"Baneling";"Zergling";463;0
"Unit";"Baneling";"Zergling";463;0
"Unit";"Baneling";"Zergling";463;0
"Unit";"Baneling";"Zergling";463;0
"Unit";"Baneling";"Zergling";463;0
"Unit";"Baneling";"Zergling";463;0
"Unit";"Baneling";"Zergling";463;0
"Unit";"Baneling";"Zergling";463;0
"Unit";"Baneling";"Zergling";463;0
"Unit";"Queen";"Hatchery";435;2
"Unit";"Baneling";"Zergling";463;0
"Unit";"Queen";"Hatchery";435;2
"Unit";"Queen";"Hatchery";435;2
"Unit";"Queen";"Hatchery";435;2
"Unit";"Queen";"Hatchery";435;2
"Unit";"Baneling";"Zergling";463;0
"Unit";"Baneling";"Zergling";463;0
"Building";"Extractor";NA;463;0
"Building";"CreepTumor";NA;463;0
"Building";"CreepTumorQueen";NA;463;0
"Building";"CreepTumor";NA;463;0
"Unit";"Hydralisk";"Larva";463;2
"Building";"CreepTumor";NA;463;0
"Unit";"Hydralisk";"Larva";463;2
"Building";"CreepTumorQueen";NA;463;0
"Unit";"Hydralisk";"Larva";463;2
"Unit";"Hydralisk";"Larva";463;2
"Unit";"Hydralisk";"Larva";463;2
"Unit";"Hydralisk";"Larva";463;2
"Unit";"Hydralisk";"Larva";463;2
"Unit";"Hydralisk";"Larva";463;2
"Unit";"Hydralisk";"Larva";463;2
"Unit";"Hydralisk";"Larva";463;2
"Unit";"Hydralisk";"Larva";463;2
"Unit";"Hydralisk";"Larva";463;2
"Unit";"Hydralisk";"Larva";463;2
"Unit";"Hydralisk";"Larva";463;2
"Unit";"Hydralisk";"Larva";463;2
"Building";"CreepTumorQueen";NA;463;0
"Building";"UltraliskCavern";NA;463;0
"Building";"Extractor";NA;463;0
"Building";"Extractor";NA;463;0
"Building";"CreepTumor";NA;475;0
"Unit";"Hydralisk";"Larva";473;2
"Unit";"Hydralisk";"Larva";473;2
"Unit";"Hydralisk";"Larva";473;2
"Unit";"Hydralisk";"Larva";473;2
"Unit";"Hydralisk";"Larva";473;2
"Unit";"Hydralisk";"Larva";473;2
"Unit";"Hydralisk";"Larva";473;2
"Unit";"Hydralisk";"Larva";473;2
"Unit";"Zergling";"Larva";503;1
"Unit";"Zergling";"Larva";503;1
"Unit";"Zergling";"Larva";503;1
"Unit";"Zergling";"Larva";503;1
"Unit";"Zergling";"Larva";503;1
"Unit";"Zergling";"Larva";503;1
"Unit";"Zergling";"Larva";503;1
"Unit";"Zergling";"Larva";503;1
"Unit";"Zergling";"Larva";503;1
"Unit";"Zergling";"Larva";503;1
"Unit";"Zergling";"Larva";503;1
"Unit";"Zergling";"Larva";503;1
"Building";"CreepTumor";NA;503;0
"Building";"CreepTumor";NA;503;0
"Building";"CreepTumor";NA;505;0
"Building";"CreepTumor";NA;519;0
"Unit";"Zergling";"Larva";531;1
"Unit";"Zergling";"Larva";531;1
"Unit";"Zergling";"Larva";531;1
"Unit";"Zergling";"Larva";531;1
"Unit";"Zergling";"Larva";531;1
"Unit";"Zergling";"Larva";531;1
"Unit";"Zergling";"Larva";531;1
"Unit";"Zergling";"Larva";531;1
"Unit";"Zergling";"Larva";531;1
"Unit";"Zergling";"Larva";531;1
"Unit";"Zergling";"Larva";531;1
"Unit";"Zergling";"Larva";531;1
"Unit";"Zergling";"Larva";531;1
"Unit";"Zergling";"Larva";531;1
"Unit";"Zergling";"Larva";531;1
"Unit";"Zergling";"Larva";531;1
"Unit";"Zergling";"Larva";531;1
"Unit";"Zergling";"Larva";531;1
"Unit";"Zergling";"Larva";531;1
"Unit";"Zergling";"Larva";531;1
"Unit";"Zergling";"Larva";531;1
"Unit";"Zergling";"Larva";531;1
"Unit";"Zergling";"Larva";531;1
"Unit";"Zergling";"Larva";531;1
"Unit";"Zergling";"Larva";531;1
"Unit";"Zergling";"Larva";531;1
"Building";"CreepTumor";NA;557;0
"Building";"CreepTumor";NA;557;0
"Building";"CreepTumor";NA;557;0
"Building";"CreepTumor";NA;557;0
"Building";"CreepTumorQueen";NA;557;0
"Building";"CreepTumorQueen";NA;557;0
"Unit";"Zergling";"Larva";557;1
"Unit";"Zergling";"Larva";557;1
"Unit";"Zergling";"Larva";557;1
"Unit";"Zergling";"Larva";557;1
"Unit";"Zergling";"Larva";557;1
"Unit";"Zergling";"Larva";557;1
"Unit";"Zergling";"Larva";557;1
"Unit";"Zergling";"Larva";557;1
"Unit";"Zergling";"Larva";557;1
"Unit";"Zergling";"Larva";557;1
"Unit";"Zergling";"Larva";557;1
"Unit";"Zergling";"Larva";557;1
"Unit";"Zergling";"Larva";557;1
"Unit";"Zergling";"Larva";557;1
"Unit";"Zergling";"Larva";557;1
"Unit";"Zergling";"Larva";557;1
"Unit";"Zergling";"Larva";557;1
"Unit";"Zergling";"Larva";557;1
"Unit";"Zergling";"Larva";557;1
"Unit";"Zergling";"Larva";557;1
"Building";"CreepTumorQueen";NA;557;0
"Building";"CreepTumorQueen";NA;557;0
"Unit";"Baneling";"Zergling";577;0
"Unit";"Baneling";"Zergling";577;0
"Unit";"Baneling";"Zergling";577;0
"Unit";"Baneling";"Zergling";577;0
"Unit";"Baneling";"Zergling";577;0
"Unit";"Baneling";"Zergling";577;0
"Unit";"Baneling";"Zergling";577;0
"Unit";"Baneling";"Zergling";577;0
"Unit";"Baneling";"Zergling";577;0
"Unit";"Baneling";"Zergling";577;0
"Unit";"Baneling";"Zergling";577;0
"Unit";"Baneling";"Zergling";577;0
"Unit";"Baneling";"Zergling";577;0
"Unit";"Baneling";"Zergling";577;0
"Unit";"Baneling";"Zergling";577;0
"Unit";"Baneling";"Zergling";577;0
"Unit";"Baneling";"Zergling";577;0
"Unit";"Baneling";"Zergling";577;0
"Unit";"Baneling";"Zergling";577;0
"Unit";"Baneling";"Zergling";577;0
"Unit";"Baneling";"Zergling";577;0
"Unit";"Baneling";"Zergling";577;0
"Unit";"Baneling";"Zergling";577;0
"Unit";"Baneling";"Zergling";577;0
"Unit";"Baneling";"Zergling";577;0
"Unit";"Baneling";"Zergling";577;0
"Unit";"Baneling";"Zergling";577;0
"Unit";"Baneling";"Zergling";577;0
"Unit";"Baneling";"Zergling";577;0
"Unit";"Baneling";"Zergling";577;0
"Unit";"Baneling";"Zergling";577;0
"Unit";"Baneling";"Zergling";577;0
"Unit";"Baneling";"Zergling";577;0
"Unit";"Baneling";"Zergling";577;0
"Unit";"Baneling";"Zergling";577;0
"Unit";"Baneling";"Zergling";577;0
"Unit";"Baneling";"Zergling";577;0
"Unit";"Baneling";"Zergling";577;0
"Unit";"Baneling";"Zergling";577;0
"Unit";"Baneling";"Zergling";577;0
"Unit";"Baneling";"Zergling";577;0
"Unit";"Baneling";"Zergling";577;0
"Unit";"Baneling";"Zergling";577;0
"Unit";"Baneling";"Zergling";577;0
"Unit";"Baneling";"Zergling";577;0
"Unit";"Baneling";"Zergling";577;0
"Upgrade";"ZergMeleeWeaponsLevel3";"EvolutionChamber";503;0
"Upgrade";"ZergGroundArmorsLevel3";"EvolutionChamber";503;0
"Building";"CreepTumor";NA;577;0
"Building";"CreepTumor";NA;577;0
"Building";"Spire";NA;557;0
"Upgrade";"ChitinousPlating";"UltraliskCavern";557;0
"Unit";"Zergling";"Larva";577;1
"Unit";"Zergling";"Larva";577;1
"Unit";"Zergling";"Larva";577;1
"Unit";"Zergling";"Larva";577;1
"Unit";"Zergling";"Larva";577;1
"Unit";"Zergling";"Larva";577;1
"Unit";"Zergling";"Larva";577;1
"Unit";"Zergling";"Larva";577;1
"Unit";"Zergling";"Larva";577;1
"Unit";"Zergling";"Larva";577;1
"Unit";"Zergling";"Larva";577;1
"Unit";"Zergling";"Larva";577;1
"Unit";"Zergling";"Larva";577;1
"Unit";"Zergling";"Larva";577;1
"Building";"Spire";NA;557;0
"Unit";"Zergling";"Larva";577;1
"Unit";"Zergling";"Larva";577;1
"Unit";"Zergling";"Larva";577;1
"Unit";"Zergling";"Larva";577;1
"Unit";"Zergling";"Larva";577;1
"Unit";"Zergling";"Larva";577;1
"Unit";"Zergling";"Larva";577;1
"Unit";"Zergling";"Larva";577;1
"Unit";"Zergling";"Larva";577;1
"Unit";"Zergling";"Larva";577;1
"Unit";"Zergling";"Larva";577;1
"Unit";"Zergling";"Larva";577;1
"Unit";"Zergling";"Larva";577;1
"Unit";"Zergling";"Larva";577;1
"Unit";"Zergling";"Larva";577;1
"Unit";"Zergling";"Larva";577;1
"Unit";"Zergling";"Larva";577;1
"Unit";"Zergling";"Larva";577;1
"Unit";"Zergling";"Larva";577;1
"Unit";"Zergling";"Larva";577;1
"Unit";"Zergling";"Larva";577;1
"Unit";"Zergling";"Larva";577;1
"Unit";"Zergling";"Larva";577;1
"Unit";"Zergling";"Larva";577;1
"Unit";"Zergling";"Larva";577;1
"Unit";"Zergling";"Larva";577;1
"Unit";"Zergling";"Larva";577;1
"Unit";"Zergling";"Larva";577;1
"Unit";"Hydralisk";"Larva";577;2
"Unit";"Hydralisk";"Larva";577;2
"Unit";"Hydralisk";"Larva";577;2
"Unit";"Hydralisk";"Larva";577;2
"Unit";"Hydralisk";"Larva";577;2
"Unit";"Hydralisk";"Larva";577;2
"Unit";"Hydralisk";"Larva";577;2
"Unit";"Hydralisk";"Larva";577;2
"Unit";"Hydralisk";"Larva";577;2
"Unit";"Hydralisk";"Larva";577;2
"Unit";"Hydralisk";"Larva";577;2
"Unit";"Hydralisk";"Larva";577;2
"Building";"Hatchery";NA;577;0
"Unit";"Ultralisk";"Larva";577;6
"Unit";"Ultralisk";"Larva";577;6
"Unit";"Ultralisk";"Larva";577;6
"Unit";"Ultralisk";"Larva";577;6
"Unit";"Ultralisk";"Larva";577;6
"Unit";"Ultralisk";"Larva";577;6
"Building";"CreepTumor";NA;643;0
"Building";"CreepTumor";NA;643;0
"Building";"CreepTumor";NA;643;0
"Building";"CreepTumor";NA;643;0
"Unit";"Corruptor";"Larva";643;2
"Building";"CreepTumorQueen";NA;643;0
"Building";"CreepTumorQueen";NA;643;0
"Unit";"Baneling";"Zergling";681;0
"Unit";"Baneling";"Zergling";681;0
"Unit";"Baneling";"Zergling";681;0
"Unit";"Baneling";"Zergling";681;0
"Unit";"Baneling";"Zergling";681;0
"Unit";"Baneling";"Zergling";681;0
"Unit";"Baneling";"Zergling";681;0
"Unit";"Baneling";"Zergling";681;0
"Unit";"Baneling";"Zergling";681;0
"Unit";"Baneling";"Zergling";681;0
"Unit";"Baneling";"Zergling";681;0
"Unit";"Baneling";"Zergling";681;0
"Unit";"Baneling";"Zergling";681;0
"Unit";"Baneling";"Zergling";681;0
"Unit";"Baneling";"Zergling";681;0
"Unit";"Baneling";"Zergling";681;0
"Unit";"Baneling";"Zergling";681;0
"Unit";"Baneling";"Zergling";681;0
"Unit";"Baneling";"Zergling";681;0
"Unit";"Baneling";"Zergling";681;0
"Unit";"Baneling";"Zergling";681;0
"Unit";"Baneling";"Zergling";681;0
"Unit";"Baneling";"Zergling";681;0
"Unit";"Baneling";"Zergling";681;0
"Unit";"Baneling";"Zergling";681;0
"Unit";"Baneling";"Zergling";681;0
"Unit";"Baneling";"Zergling";681;0
"Unit";"Baneling";"Zergling";681;0
"Unit";"Baneling";"Zergling";681;0
"Building";"CreepTumor";NA;681;0
"Unit";"Baneling";"Zergling";681;0
"Unit";"Baneling";"Zergling";681;0
"Unit";"Baneling";"Zergling";681;0
"Unit";"Baneling";"Zergling";681;0
"Unit";"Baneling";"Zergling";681;0
"Unit";"Baneling";"Zergling";681;0
"Unit";"Baneling";"Zergling";681;0
"Unit";"Baneling";"Zergling";681;0
"Building";"CreepTumor";NA;681;0
"Unit";"Baneling";"Zergling";681;0
"Building";"CreepTumorQueen";NA;681;0
"Building";"CreepTumorQueen";NA;681;0
"Building";"CreepTumorQueen";NA;681;0
"Unit";"Zergling";"Larva";681;1
"Unit";"Zergling";"Larva";681;1
"Building";"CreepTumor";NA;681;0
"Unit";"Zergling";"Larva";681;1
"Unit";"Zergling";"Larva";681;1
"Unit";"Zergling";"Larva";681;1
"Unit";"Zergling";"Larva";681;1
"Unit";"Zergling";"Larva";681;1
"Unit";"Zergling";"Larva";681;1
"Unit";"Zergling";"Larva";681;1
"Unit";"Zergling";"Larva";681;1
"Building";"CreepTumor";NA;681;0
"Unit";"Zergling";"Larva";681;1
"Unit";"Zergling";"Larva";681;1
"Unit";"Zergling";"Larva";681;1
"Unit";"Zergling";"Larva";681;1
"Unit";"Zergling";"Larva";681;1
"Unit";"Zergling";"Larva";681;1
"Unit";"Zergling";"Larva";681;1
"Unit";"Zergling";"Larva";681;1
"Unit";"Zergling";"Larva";681;1
"Unit";"Zergling";"Larva";681;1
