"type";"unit_name";"on_building";"total_supply";"supply"
"Unit";"Overlord";"Larva";13;0
"Building";"Extractor";NA;18;0
"Unit";"Overlord";"Larva";21;0
"Building";"SpawningPool";NA;19;0
"Building";"Hatchery";NA;17;0
"Unit";"Zergling";"Larva";22;1
"Unit";"Zergling";"Larva";22;1
"Unit";"Zergling";"Larva";23;1
"Unit";"Zergling";"Larva";23;1
"Unit";"Queen";"Hatchery";22;2
"Unit";"Queen";"Hatchery";23;2
"Unit";"Overlord";"Larva";36;0
"Unit";"Overlord";"Larva";39;0
"Building";"CreepTumorQueen";NA;41;0
"Unit";"Queen";"Hatchery";36;2
"Building";"CreepTumor";NA;50;0
"Unit";"Zergling";"Larva";52;1
"Unit";"Zergling";"Larva";52;1
"Unit";"Zergling";"Larva";52;1
"Unit";"Zergling";"Larva";52;1
"Unit";"Zergling";"Larva";52;1
"Unit";"Zergling";"Larva";52;1
"Unit";"Zergling";"Larva";52;1
"Unit";"Zergling";"Larva";52;1
"Unit";"Zergling";"Larva";52;1
"Unit";"Zergling";"Larva";52;1
"Building";"Hatchery";NA;36;0
"Unit";"Queen";"Hatchery";42;2
"Building";"Extractor";NA;52;0
"Building";"Extractor";NA;52;0
"Building";"CreepTumor";NA;66;0
"Building";"CreepTumorQueen";NA;70;0
"Building";"RoachWarren";NA;52;0
"Building";"CreepTumorQueen";NA;72;0
"Unit";"Overlord";"Larva";66;0
"Unit";"Overlord";"Larva";73;0
"Unit";"Queen";"Hatchery";66;2
"Building";"CreepTumorQueen";NA;73;0
"Building";"CreepTumor";NA;73;0
"Building";"CreepTumor";NA;73;0
"Building";"CreepTumor";NA;73;0
"Unit";"Roach";"Larva";73;2
"Unit";"Overlord";"Larva";75;0
"Unit";"Overlord";"Larva";75;0
"Unit";"Overlord";"Larva";81;0
"Unit";"Overlord";"Larva";83;0
"Unit";"Overlord";"Larva";83;0
"Unit";"Roach";"Larva";83;2
"Unit";"Roach";"Larva";83;2
"Unit";"Roach";"Larva";83;2
"Unit";"Roach";"Larva";83;2
"Unit";"Roach";"Larva";83;2
"Unit";"Roach";"Larva";83;2
"Unit";"Roach";"Larva";83;2
"Unit";"Roach";"Larva";83;2
"Building";"EvolutionChamber";NA;81;0
"Building";"EvolutionChamber";NA;83;0
"Unit";"Queen";"Hatchery";83;2
"Unit";"Overlord";"Larva";99;0
"Building";"CreepTumor";NA;99;0
"Building";"CreepTumor";NA;99;0
"Unit";"Queen";"Hatchery";83;2
"Building";"SporeCrawler";NA;107;0
"Building";"CreepTumorQueen";NA;116;0
"Unit";"Overlord";"Larva";116;0
"Building";"CreepTumorQueen";NA;116;0
"Building";"Extractor";NA;116;0
"Building";"CreepTumorQueen";NA;116;0
"Unit";"Overlord";"Larva";116;0
"Building";"Extractor";NA;116;0
"Building";"CreepTumor";NA;121;0
"Building";"CreepTumor";NA;121;0
"Unit";"Overlord";"Larva";116;0
"Building";"Extractor";NA;116;0
"Upgrade";"GlialReconstitution";"RoachWarren";107;0
"Unit";"Overlord";"Larva";121;0
"Unit";"Overlord";"Larva";121;0
"Unit";"Roach";"Larva";121;2
"Unit";"Roach";"Larva";121;2
"Unit";"Roach";"Larva";121;2
"Unit";"Roach";"Larva";121;2
"Unit";"Roach";"Larva";121;2
"Unit";"Roach";"Larva";121;2
"Unit";"Roach";"Larva";121;2
"Unit";"Roach";"Larva";121;2
"Unit";"Roach";"Larva";121;2
"Unit";"Roach";"Larva";121;2
"Unit";"Roach";"Larva";121;2
"Building";"CreepTumor";NA;121;0
"Building";"CreepTumor";NA;121;0
"Building";"CreepTumor";NA;121;0
"Unit";"Overlord";"Larva";121;0
"Building";"CreepTumorQueen";NA;121;0
"Building";"CreepTumor";NA;121;0
"Building";"HydraliskDen";NA;121;0
"Unit";"Overlord";"Larva";143;0
"Unit";"Overlord";"Larva";143;0
"Building";"InfestationPit";NA;121;0
"Upgrade";"ZergMissileWeaponsLevel1";"EvolutionChamber";116;0
"Upgrade";"ZergGroundArmorsLevel1";"EvolutionChamber";116;0
"Building";"CreepTumor";NA;159;0
"Building";"CreepTumor";NA;159;0
"Building";"CreepTumor";NA;159;0
"Building";"CreepTumor";NA;159;0
"Building";"CreepTumorQueen";NA;159;0
"Building";"Hatchery";NA;121;0
"Building";"CreepTumorQueen";NA;161;0
"Building";"CreepTumorQueen";NA;161;0
"Unit";"Overlord";"Larva";161;0
"Building";"Extractor";NA;161;0
"Building";"Extractor";NA;161;0
"Building";"CreepTumorQueen";NA;170;0
"Unit";"Hydralisk";"Larva";170;2
"Unit";"Hydralisk";"Larva";170;2
"Unit";"Hydralisk";"Larva";170;2
"Unit";"Hydralisk";"Larva";170;2
"Unit";"Hydralisk";"Larva";170;2
"Unit";"Hydralisk";"Larva";170;2
"Unit";"Hydralisk";"Larva";170;2
"Unit";"Hydralisk";"Larva";170;2
"Unit";"Hydralisk";"Larva";170;2
"Building";"CreepTumorQueen";NA;170;0
"Building";"CreepTumor";NA;170;0
"Building";"CreepTumor";NA;170;0
"Building";"CreepTumor";NA;170;0
"Building";"CreepTumor";NA;170;0
"Upgrade";"EvolveGroovedSpines";"HydraliskDen";170;0
"Building";"SpineCrawler";NA;170;0
"Building";"SpineCrawler";NA;170;0
"Building";"CreepTumor";NA;194;0
"Building";"CreepTumorQueen";NA;194;0
"Building";"CreepTumor";NA;194;0
"Unit";"Overlord";"Larva";194;0
"Building";"CreepTumor";NA;199;0
"Building";"CreepTumor";NA;199;0
"Building";"CreepTumor";NA;199;0
"Building";"Hatchery";NA;170;0
"Unit";"Overlord";"Larva";199;0
"Unit";"Viper";"Larva";194;3
"Unit";"Viper";"Larva";194;3
"Building";"CreepTumor";NA;199;0
"Unit";"Viper";"Larva";194;3
"Building";"EvolutionChamber";NA;199;0
"Building";"EvolutionChamber";NA;199;0
"Building";"CreepTumor";NA;199;0
"Building";"CreepTumor";NA;199;0
"Building";"CreepTumorQueen";NA;199;0
"Building";"CreepTumor";NA;199;0
"Building";"CreepTumor";NA;199;0
"Building";"CreepTumor";NA;199;0
"Upgrade";"ZergMissileWeaponsLevel2";"EvolutionChamber";170;0
"Upgrade";"ZergGroundArmorsLevel2";"EvolutionChamber";170;0
"Unit";"Viper";"Larva";199;3
"Unit";"Hydralisk";"Larva";199;2
"Unit";"Hydralisk";"Larva";199;2
"Unit";"Hydralisk";"Larva";199;2
"Unit";"Hydralisk";"Larva";199;2
"Unit";"Hydralisk";"Larva";199;2
"Unit";"Hydralisk";"Larva";199;2
"Building";"CreepTumor";NA;211;0
"Building";"Spire";NA;194;0
"Building";"CreepTumor";NA;211;0
"Building";"CreepTumor";NA;219;0
"Building";"CreepTumorQueen";NA;231;0
"Building";"CreepTumor";NA;231;0
"Building";"CreepTumor";NA;231;0
"Building";"CreepTumor";NA;231;0
"Building";"CreepTumor";NA;231;0
"Building";"CreepTumor";NA;231;0
"Building";"CreepTumor";NA;231;0
"Building";"CreepTumor";NA;231;0
"Unit";"Viper";"Larva";208;3
"Unit";"Hydralisk";"Larva";208;2
"Unit";"Hydralisk";"Larva";208;2
"Building";"CreepTumorQueen";NA;231;0
"Building";"Extractor";NA;231;0
"Building";"Extractor";NA;231;0
"Building";"CreepTumor";NA;238;0
"Unit";"Hydralisk";"Larva";238;2
"Unit";"Hydralisk";"Larva";238;2
"Unit";"Hydralisk";"Larva";238;2
"Unit";"Hydralisk";"Larva";238;2
"Unit";"Hydralisk";"Larva";238;2
"Unit";"Hydralisk";"Larva";238;2
"Unit";"Hydralisk";"Larva";238;2
"Unit";"Hydralisk";"Larva";238;2
"Building";"SpineCrawler";NA;231;0
"Building";"SpineCrawler";NA;231;0
"Building";"CreepTumor";NA;261;0
"Building";"CreepTumor";NA;262;0
"Building";"CreepTumor";NA;262;0
"Building";"CreepTumor";NA;262;0
"Building";"CreepTumor";NA;262;0
"Building";"CreepTumor";NA;262;0
"Building";"CreepTumor";NA;262;0
"Building";"CreepTumor";NA;268;0
"Building";"CreepTumor";NA;268;0
"Building";"CreepTumor";NA;268;0
"Building";"CreepTumorQueen";NA;268;0
"Building";"CreepTumor";NA;268;0
"Building";"CreepTumor";NA;268;0
"Building";"SpineCrawler";NA;268;0
"Unit";"Corruptor";"Larva";268;2
"Unit";"Corruptor";"Larva";268;2
"Unit";"Corruptor";"Larva";268;2
"Unit";"Corruptor";"Larva";268;2
"Unit";"Corruptor";"Larva";268;2
"Unit";"Corruptor";"Larva";268;2
"Unit";"Corruptor";"Larva";268;2
"Unit";"Corruptor";"Larva";268;2
"Unit";"Viper";"Larva";268;3
"Unit";"Viper";"Larva";268;3
"Unit";"Corruptor";"Larva";284;2
"Unit";"Corruptor";"Larva";284;2
"Unit";"Corruptor";"Larva";284;2
"Unit";"Hydralisk";"Larva";284;2
"Unit";"Hydralisk";"Larva";284;2
"Building";"CreepTumor";NA;290;0
"Building";"CreepTumor";NA;290;0
"Unit";"Hydralisk";"Larva";284;2
"Building";"CreepTumor";NA;290;0
"Building";"CreepTumor";NA;290;0
"Building";"CreepTumor";NA;290;0
"Building";"CreepTumor";NA;290;0
"Unit";"Corruptor";"Larva";296;2
"Unit";"Corruptor";"Larva";296;2
"Unit";"Corruptor";"Larva";296;2
"Building";"CreepTumor";NA;305;0
"Building";"CreepTumor";NA;305;0
"Building";"CreepTumor";NA;305;0
"Building";"CreepTumor";NA;305;0
"Building";"CreepTumor";NA;305;0
"Unit";"Hydralisk";"Larva";305;2
"Unit";"Hydralisk";"Larva";305;2
"Unit";"Hydralisk";"Larva";305;2
"Unit";"Hydralisk";"Larva";305;2
"Unit";"Hydralisk";"Larva";305;2
"Unit";"Hydralisk";"Larva";321;2
"Unit";"Hydralisk";"Larva";321;2
"Unit";"Hydralisk";"Larva";321;2
"Unit";"Hydralisk";"Larva";321;2
"Unit";"Hydralisk";"Larva";321;2
"Unit";"Hydralisk";"Larva";321;2
"Unit";"Hydralisk";"Larva";321;2
"Unit";"Hydralisk";"Larva";321;2
"Unit";"Hydralisk";"Larva";321;2
"Unit";"Hydralisk";"Larva";321;2
"Unit";"Hydralisk";"Larva";321;2
"Building";"Hatchery";NA;296;0
"Unit";"Roach";"Larva";321;2
"Unit";"Roach";"Larva";321;2
"Unit";"Roach";"Larva";321;2
"Unit";"Roach";"Larva";321;2
"Unit";"Roach";"Larva";321;2
"Unit";"Roach";"Larva";321;2
"Unit";"Corruptor";"Larva";321;2
"Unit";"Corruptor";"Larva";321;2
"Unit";"Corruptor";"Larva";321;2
"Unit";"Corruptor";"Larva";321;2
"Unit";"Corruptor";"Larva";321;2
"Unit";"Corruptor";"Larva";321;2
"Building";"CreepTumor";NA;349;0
"Building";"CreepTumor";NA;353;0
"Building";"CreepTumor";NA;351;0
"Building";"CreepTumor";NA;353;0
"Building";"CreepTumor";NA;372;0
"Building";"CreepTumor";NA;372;0
"Unit";"Hydralisk";"Larva";339;2
"Unit";"Hydralisk";"Larva";343;2
"Unit";"Hydralisk";"Larva";343;2
"Unit";"Hydralisk";"Larva";343;2
"Unit";"Hydralisk";"Larva";343;2
"Building";"Extractor";NA;343;0
"Building";"Extractor";NA;358;0
"Upgrade";"ZergMeleeWeaponsLevel1";"EvolutionChamber";305;0
"Unit";"Roach";"Larva";382;2
"Unit";"Roach";"Larva";382;2
"Unit";"Roach";"Larva";382;2
"Unit";"Hydralisk";"Larva";382;2
"Building";"SpineCrawler";NA;372;0
"Building";"SpineCrawler";NA;372;0
"Building";"SpineCrawler";NA;372;0
"Unit";"Hydralisk";"Larva";382;2
"Unit";"Hydralisk";"Larva";382;2
"Unit";"Hydralisk";"Larva";382;2
"Unit";"Hydralisk";"Larva";382;2
"Unit";"Hydralisk";"Larva";382;2
"Unit";"Hydralisk";"Larva";382;2
"Unit";"Hydralisk";"Larva";382;2
"Unit";"Hydralisk";"Larva";382;2
"Unit";"Hydralisk";"Larva";382;2
"Unit";"Roach";"Larva";390;2
"Unit";"Roach";"Larva";390;2
"Unit";"Roach";"Larva";390;2
"Unit";"Roach";"Larva";390;2
"Unit";"Roach";"Larva";390;2
"Unit";"Roach";"Larva";390;2
"Unit";"Roach";"Larva";390;2
"Unit";"Overlord";"Larva";400;0
