"type";"unit_name";"on_building";"total_supply";"supply"
"Unit";"Overlord";"Larva";12;0
"Building";"Extractor";NA;17;0
"Building";"Hatchery";NA;17;0
"Unit";"Overlord";"Larva";22;0
"Building";"SpawningPool";NA;19;0
"Unit";"Zergling";"Larva";22;1
"Unit";"Zergling";"Larva";22;1
"Unit";"Zergling";"Larva";22;1
"Unit";"Zergling";"Larva";22;1
"Unit";"Queen";"Hatchery";22;2
"Unit";"Queen";"Hatchery";22;2
"Unit";"Overlord";"Larva";34;0
"Unit";"Queen";"Hatchery";34;2
"Building";"CreepTumorQueen";NA;41;0
"Building";"CreepTumorQueen";NA;41;0
"Unit";"Overlord";"Larva";41;0
"Unit";"Queen";"Hatchery";41;2
"Unit";"Zergling";"Larva";49;1
"Unit";"Zergling";"Larva";49;1
"Unit";"Zergling";"Larva";49;1
"Unit";"Zergling";"Larva";49;1
"Unit";"Zergling";"Larva";49;1
"Unit";"Zergling";"Larva";49;1
"Building";"CreepTumorQueen";NA;51;0
"Unit";"Zergling";"Larva";49;1
"Unit";"Zergling";"Larva";49;1
"Building";"CreepTumorQueen";NA;51;0
"Building";"Extractor";NA;51;0
"Building";"Hatchery";NA;39;0
"Building";"CreepTumor";NA;61;0
"Unit";"Overlord";"Larva";59;0
"Unit";"Overlord";"Larva";61;0
"Unit";"Overlord";"Larva";61;0
"Building";"CreepTumor";NA;61;0
"Unit";"Queen";"Hatchery";51;2
"Unit";"Queen";"Hatchery";51;2
"Building";"BanelingNest";NA;51;0
"Building";"SporeCrawler";NA;61;0
"Building";"SporeCrawler";NA;61;0
"Unit";"Zergling";"Larva";65;1
"Unit";"Zergling";"Larva";65;1
"Unit";"Zergling";"Larva";65;1
"Unit";"Zergling";"Larva";65;1
"Building";"SporeCrawler";NA;65;0
"Unit";"Queen";"Hatchery";61;2
"Unit";"Zergling";"Larva";73;1
"Unit";"Zergling";"Larva";73;1
"Unit";"Zergling";"Larva";73;1
"Unit";"Zergling";"Larva";73;1
"Unit";"Zergling";"Larva";73;1
"Unit";"Zergling";"Larva";73;1
"Unit";"Zergling";"Larva";73;1
"Unit";"Zergling";"Larva";73;1
"Unit";"Zergling";"Larva";73;1
"Unit";"Zergling";"Larva";73;1
"Unit";"Zergling";"Larva";73;1
"Unit";"Zergling";"Larva";73;1
"Building";"CreepTumor";NA;77;0
"Building";"CreepTumorQueen";NA;79;0
"Building";"CreepTumor";NA;79;0
"Building";"CreepTumor";NA;79;0
"Unit";"Overlord";"Larva";100;0
"Unit";"Overlord";"Larva";100;0
"Building";"Extractor";NA;105;0
"Building";"Extractor";NA;105;0
"Building";"Extractor";NA;105;0
"Building";"CreepTumor";NA;117;0
"Building";"CreepTumorQueen";NA;117;0
"Building";"CreepTumorQueen";NA;117;0
"Building";"CreepTumorQueen";NA;127;0
"Building";"CreepTumorQueen";NA;130;0
"Building";"CreepTumorQueen";NA;130;0
"Building";"Extractor";NA;117;0
"Building";"HydraliskDen";NA;127;0
"Building";"EvolutionChamber";NA;130;0
"Building";"EvolutionChamber";NA;130;0
"Building";"CreepTumor";NA;130;0
"Building";"CreepTumor";NA;130;0
"Building";"CreepTumor";NA;130;0
"Building";"CreepTumor";NA;130;0
"Building";"CreepTumor";NA;130;0
"Building";"CreepTumor";NA;130;0
"Building";"CreepTumor";NA;130;0
"Building";"CreepTumor";NA;130;0
"Building";"CreepTumorQueen";NA;132;0
"Building";"CreepTumorQueen";NA;132;0
"Building";"CreepTumorQueen";NA;132;0
"Building";"CreepTumorQueen";NA;133;0
"Building";"CreepTumorQueen";NA;143;0
"Building";"Hatchery";NA;120;0
"Building";"InfestationPit";NA;130;0
"Building";"Extractor";NA;143;0
"Unit";"Overlord";"Larva";143;0
"Unit";"Overlord";"Larva";143;0
"Unit";"Overlord";"Larva";143;0
"Unit";"Overlord";"Larva";143;0
"Unit";"Overlord";"Larva";143;0
"Building";"SporeCrawler";NA;143;0
"Unit";"Baneling";"Zergling";143;0
"Unit";"Baneling";"Zergling";143;0
"Unit";"Baneling";"Zergling";143;0
"Unit";"Baneling";"Zergling";143;0
"Unit";"Hydralisk";"Larva";143;2
"Unit";"Baneling";"Zergling";143;0
"Building";"Hatchery";NA;130;0
"Unit";"Baneling";"Zergling";143;0
"Unit";"Baneling";"Zergling";143;0
"Unit";"Baneling";"Zergling";143;0
"Unit";"Baneling";"Zergling";143;0
"Building";"Extractor";NA;143;0
"Building";"CreepTumor";NA;143;0
"Building";"CreepTumor";NA;143;0
"Building";"CreepTumor";NA;143;0
"Building";"CreepTumor";NA;143;0
"Building";"CreepTumor";NA;143;0
"Building";"CreepTumor";NA;143;0
"Building";"CreepTumor";NA;143;0
"Building";"CreepTumor";NA;143;0
"Building";"CreepTumor";NA;143;0
"Building";"CreepTumor";NA;143;0
"Building";"CreepTumorQueen";NA;143;0
"Building";"CreepTumor";NA;143;0
"Building";"CreepTumorQueen";NA;145;0
"Building";"CreepTumorQueen";NA;145;0
"Upgrade";"EvolveGroovedSpines";"HydraliskDen";143;0
"Unit";"Hydralisk";"Larva";145;2
"Unit";"Hydralisk";"Larva";145;2
"Unit";"Hydralisk";"Larva";145;2
"Unit";"Hydralisk";"Larva";145;2
"Unit";"Hydralisk";"Larva";145;2
"Unit";"Hydralisk";"Larva";145;2
"Unit";"Hydralisk";"Larva";145;2
"Unit";"Hydralisk";"Larva";145;2
"Unit";"Hydralisk";"Larva";145;2
"Unit";"Hydralisk";"Larva";145;2
"Unit";"Hydralisk";"Larva";145;2
"Unit";"Hydralisk";"Larva";145;2
"Unit";"Hydralisk";"Larva";145;2
"Unit";"Hydralisk";"Larva";145;2
"Unit";"Hydralisk";"Larva";145;2
"Unit";"Hydralisk";"Larva";145;2
"Unit";"Hydralisk";"Larva";145;2
"Building";"CreepTumorQueen";NA;145;0
"Building";"CreepTumorQueen";NA;145;0
"Unit";"Zergling";"Larva";145;1
"Unit";"Zergling";"Larva";145;1
"Unit";"Zergling";"Larva";145;1
"Unit";"Zergling";"Larva";145;1
"Building";"CreepTumor";NA;183;0
"Building";"CreepTumor";NA;183;0
"Building";"CreepTumor";NA;183;0
"Building";"CreepTumor";NA;183;0
"Building";"CreepTumor";NA;183;0
"Building";"CreepTumor";NA;183;0
"Building";"CreepTumor";NA;183;0
"Building";"CreepTumor";NA;183;0
"Building";"CreepTumor";NA;183;0
"Building";"CreepTumor";NA;183;0
"Building";"CreepTumor";NA;183;0
"Upgrade";"ZergMissileWeaponsLevel1";"EvolutionChamber";145;0
"Upgrade";"ZergGroundArmorsLevel1";"EvolutionChamber";145;0
"Building";"CreepTumor";NA;183;0
"Building";"CreepTumor";NA;183;0
"Building";"CreepTumor";NA;183;0
"Unit";"Overlord";"Larva";183;0
"Unit";"Overlord";"Larva";183;0
"Building";"CreepTumor";NA;183;0
"Unit";"Overlord";"Larva";183;0
"Unit";"Overlord";"Larva";183;0
"Unit";"Overlord";"Larva";183;0
"Unit";"Overlord";"Larva";183;0
"Unit";"Overlord";"Larva";183;0
"Unit";"Overlord";"Larva";183;0
"Building";"CreepTumor";NA;183;0
"Upgrade";"EvolveMuscularAugments";"HydraliskDen";183;0
"Building";"CreepTumor";NA;183;0
"Building";"CreepTumor";NA;183;0
"Building";"CreepTumorQueen";NA;183;0
"Building";"CreepTumor";NA;183;0
"Building";"CreepTumor";NA;183;0
"Building";"CreepTumor";NA;183;0
"Building";"CreepTumor";NA;183;0
"Building";"CreepTumor";NA;183;0
"Building";"CreepTumor";NA;183;0
"Building";"CreepTumor";NA;183;0
"Building";"CreepTumor";NA;183;0
"Building";"CreepTumor";NA;183;0
"Building";"CreepTumor";NA;183;0
"Building";"CreepTumor";NA;183;0
"Building";"Spire";NA;183;0
"Building";"CreepTumor";NA;183;0
"Building";"CreepTumor";NA;183;0
"Unit";"Hydralisk";"Larva";183;2
"Building";"CreepTumor";NA;183;0
"Unit";"Hydralisk";"Larva";183;2
"Unit";"Hydralisk";"Larva";183;2
"Unit";"Hydralisk";"Larva";183;2
"Unit";"Hydralisk";"Larva";183;2
"Unit";"Hydralisk";"Larva";183;2
"Building";"Hatchery";NA;183;0
"Unit";"Hydralisk";"Larva";183;2
"Unit";"Hydralisk";"Larva";183;2
"Unit";"Hydralisk";"Larva";183;2
"Unit";"Hydralisk";"Larva";183;2
"Unit";"Baneling";"Zergling";195;0
"Unit";"Hydralisk";"Larva";183;2
"Unit";"Hydralisk";"Larva";183;2
"Unit";"Baneling";"Zergling";195;0
"Unit";"Baneling";"Zergling";195;0
"Building";"Hatchery";NA;183;0
"Building";"CreepTumor";NA;207;0
"Building";"CreepTumor";NA;207;0
"Building";"CreepTumor";NA;207;0
"Building";"CreepTumor";NA;207;0
"Building";"CreepTumor";NA;207;0
"Upgrade";"ZergMissileWeaponsLevel2";"EvolutionChamber";183;0
"Upgrade";"ZergGroundArmorsLevel2";"EvolutionChamber";183;0
"Unit";"Hydralisk";"Larva";207;2
"Unit";"Hydralisk";"Larva";207;2
"Unit";"Hydralisk";"Larva";207;2
"Unit";"Hydralisk";"Larva";207;2
"Unit";"Hydralisk";"Larva";207;2
"Unit";"Hydralisk";"Larva";207;2
"Unit";"Hydralisk";"Larva";207;2
"Unit";"Hydralisk";"Larva";209;2
"Unit";"Hydralisk";"Larva";219;2
"Unit";"Hydralisk";"Larva";221;2
"Unit";"Hydralisk";"Larva";221;2
"Unit";"Hydralisk";"Larva";221;2
"Unit";"Hydralisk";"Larva";221;2
"Building";"CreepTumor";NA;221;0
"Building";"CreepTumor";NA;233;0
"Building";"CreepTumor";NA;233;0
"Building";"CreepTumor";NA;233;0
"Building";"CreepTumor";NA;233;0
"Building";"CreepTumor";NA;233;0
"Building";"Spire";NA;207;0
"Building";"SpineCrawler";NA;221;0
"Building";"SpineCrawler";NA;221;0
"Building";"SpineCrawler";NA;233;0
"Building";"SpineCrawler";NA;233;0
"Building";"SpineCrawler";NA;233;0
"Building";"CreepTumor";NA;233;0
"Unit";"Hydralisk";"Larva";233;2
"Unit";"Hydralisk";"Larva";233;2
"Building";"CreepTumor";NA;233;0
"Building";"CreepTumor";NA;233;0
"Building";"CreepTumor";NA;233;0
"Building";"SporeCrawler";NA;233;0
"Building";"SporeCrawler";NA;237;0
"Building";"SporeCrawler";NA;237;0
"Building";"SporeCrawler";NA;237;0
"Building";"SporeCrawler";NA;237;0
"Building";"SporeCrawler";NA;237;0
"Building";"SporeCrawler";NA;237;0
"Building";"SporeCrawler";NA;237;0
"Building";"CreepTumor";NA;246;0
"Building";"CreepTumor";NA;246;0
"Building";"CreepTumor";NA;246;0
"Building";"CreepTumor";NA;246;0
"Building";"CreepTumor";NA;246;0
"Building";"SporeCrawler";NA;246;0
"Building";"SporeCrawler";NA;246;0
"Building";"SporeCrawler";NA;246;0
"Building";"SporeCrawler";NA;246;0
"Building";"SporeCrawler";NA;246;0
"Unit";"Mutalisk";"Larva";246;2
"Unit";"Mutalisk";"Larva";246;2
"Unit";"Mutalisk";"Larva";246;2
"Unit";"Mutalisk";"Larva";246;2
"Building";"CreepTumor";NA;254;0
"Building";"CreepTumor";NA;254;0
"Unit";"Hydralisk";"Larva";254;2
"Unit";"Hydralisk";"Larva";254;2
"Unit";"Hydralisk";"Larva";254;2
"Unit";"Hydralisk";"Larva";254;2
"Unit";"Hydralisk";"Larva";254;2
"Unit";"Hydralisk";"Larva";254;2
"Unit";"Hydralisk";"Larva";254;2
"Unit";"Hydralisk";"Larva";254;2
"Unit";"Hydralisk";"Larva";254;2
"Unit";"Hydralisk";"Larva";254;2
"Unit";"Hydralisk";"Larva";254;2
"Unit";"Hydralisk";"Larva";254;2
"Unit";"Hydralisk";"Larva";254;2
"Unit";"Hydralisk";"Larva";254;2
"Unit";"Hydralisk";"Larva";254;2
"Unit";"Hydralisk";"Larva";254;2
"Unit";"Hydralisk";"Larva";254;2
"Unit";"Hydralisk";"Larva";254;2
"Unit";"Hydralisk";"Larva";254;2
"Unit";"Hydralisk";"Larva";254;2
"Unit";"Hydralisk";"Larva";254;2
"Unit";"Hydralisk";"Larva";254;2
"Unit";"Hydralisk";"Larva";254;2
"Unit";"Hydralisk";"Larva";254;2
"Unit";"Hydralisk";"Larva";254;2
"Building";"CreepTumor";NA;254;0
"Unit";"Mutalisk";"Larva";254;2
"Unit";"Mutalisk";"Larva";254;2
"Building";"CreepTumor";NA;308;0
"Building";"CreepTumor";NA;308;0
"Building";"CreepTumor";NA;308;0
"Building";"Hatchery";NA;308;0
"Building";"Hatchery";NA;308;0
"Building";"Hatchery";NA;308;0
"Building";"Hatchery";NA;308;0
"Building";"Hatchery";NA;308;0
"Building";"Extractor";NA;308;0
"Building";"Extractor";NA;308;0
"Unit";"Hydralisk";"Larva";328;2
"Unit";"Hydralisk";"Larva";328;2
"Unit";"Hydralisk";"Larva";328;2
"Unit";"Hydralisk";"Larva";328;2
"Unit";"Hydralisk";"Larva";328;2
"Unit";"Hydralisk";"Larva";328;2
"Unit";"Hydralisk";"Larva";328;2
"Unit";"Hydralisk";"Larva";328;2
"Unit";"Hydralisk";"Larva";328;2
"Building";"Hatchery";NA;308;0
"Unit";"Hydralisk";"Larva";328;2
"Unit";"Hydralisk";"Larva";328;2
"Unit";"Hydralisk";"Larva";328;2
"Unit";"Hydralisk";"Larva";328;2
"Unit";"Hydralisk";"Larva";328;2
"Unit";"Hydralisk";"Larva";328;2
"Unit";"Hydralisk";"Larva";328;2
"Unit";"Hydralisk";"Larva";328;2
"Unit";"Hydralisk";"Larva";328;2
"Unit";"Hydralisk";"Larva";328;2
"Unit";"Hydralisk";"Larva";328;2
"Unit";"Hydralisk";"Larva";328;2
"Unit";"Hydralisk";"Larva";328;2
"Unit";"Hydralisk";"Larva";328;2
"Unit";"Hydralisk";"Larva";328;2
"Unit";"Hydralisk";"Larva";328;2
"Unit";"Hydralisk";"Larva";328;2
"Unit";"Hydralisk";"Larva";328;2
"Unit";"Hydralisk";"Larva";328;2
"Unit";"Hydralisk";"Larva";328;2
"Unit";"Hydralisk";"Larva";328;2
"Unit";"Hydralisk";"Larva";328;2
"Unit";"Hydralisk";"Larva";328;2
"Unit";"Hydralisk";"Larva";328;2
"Unit";"Hydralisk";"Larva";328;2
"Building";"SporeCrawler";NA;346;0
"Building";"SporeCrawler";NA;346;0
"Building";"SpineCrawler";NA;346;0
"Building";"SpineCrawler";NA;346;0
"Building";"SpineCrawler";NA;346;0
"Building";"SpineCrawler";NA;346;0
"Building";"SpineCrawler";NA;346;0
"Unit";"Hydralisk";"Larva";396;2
"Unit";"Hydralisk";"Larva";396;2
"Unit";"Hydralisk";"Larva";396;2
"Unit";"Hydralisk";"Larva";396;2
"Unit";"Hydralisk";"Larva";396;2
"Unit";"Hydralisk";"Larva";396;2
"Unit";"Hydralisk";"Larva";396;2
"Unit";"Hydralisk";"Larva";396;2
"Unit";"Hydralisk";"Larva";396;2
"Unit";"Hydralisk";"Larva";396;2
"Unit";"Hydralisk";"Larva";396;2
"Unit";"Hydralisk";"Larva";396;2
"Unit";"Hydralisk";"Larva";396;2
"Unit";"Hydralisk";"Larva";396;2
"Unit";"Hydralisk";"Larva";396;2
"Unit";"Hydralisk";"Larva";396;2
"Unit";"Hydralisk";"Larva";396;2
"Unit";"Hydralisk";"Larva";396;2
"Unit";"Hydralisk";"Larva";396;2
"Unit";"Hydralisk";"Larva";396;2
"Unit";"Hydralisk";"Larva";396;2
"Unit";"Hydralisk";"Larva";396;2
"Unit";"Hydralisk";"Larva";396;2
"Unit";"Hydralisk";"Larva";396;2
"Unit";"Hydralisk";"Larva";396;2
"Unit";"Hydralisk";"Larva";396;2
"Unit";"Hydralisk";"Larva";396;2
"Unit";"Hydralisk";"Larva";396;2
"Unit";"Hydralisk";"Larva";396;2
"Building";"SporeCrawler";NA;454;0
"Unit";"Hydralisk";"Larva";454;2
"Building";"SporeCrawler";NA;454;0
"Unit";"Hydralisk";"Larva";454;2
"Unit";"Hydralisk";"Larva";454;2
"Unit";"Hydralisk";"Larva";454;2
"Unit";"Hydralisk";"Larva";454;2
"Unit";"Hydralisk";"Larva";454;2
"Unit";"Hydralisk";"Larva";454;2
"Unit";"Hydralisk";"Larva";454;2
"Unit";"Hydralisk";"Larva";454;2
"Unit";"Hydralisk";"Larva";454;2
"Unit";"Hydralisk";"Larva";454;2
"Unit";"Hydralisk";"Larva";454;2
"Unit";"Hydralisk";"Larva";454;2
"Unit";"Hydralisk";"Larva";454;2
"Unit";"Hydralisk";"Larva";454;2
"Unit";"Hydralisk";"Larva";454;2
