"type";"unit_name";"on_building";"total_supply_lag";"supply"
"Unit";"Overlord";"Larva";13;0
"Building";"SpawningPool";NA;16;0
"Building";"Hatchery";NA;18;0
"Unit";"Zergling";"Larva";19;1
"Unit";"Zergling";"Larva";20;1
"Unit";"Zergling";"Larva";21;1
"Unit";"Zergling";"Larva";22;1
"Unit";"Zergling";"Larva";23;1
"Unit";"Zergling";"Larva";24;1
"Unit";"Queen";"Hatchery";25;2
"Unit";"Overlord";"Larva";27;0
"Building";"Hatchery";NA;27;0
"Unit";"Queen";"Hatchery";29;2
"Unit";"Queen";"Hatchery";34;2
"Unit";"Overlord";"Larva";42;0
"Unit";"Queen";"Hatchery";45;2
"Building";"CreepTumorQueen";NA;48;0
"Building";"Extractor";NA;48;0
"Building";"Extractor";NA;48;0
"Unit";"Queen";"Hatchery";52;2
"Unit";"Overlord";"Larva";54;0
"Building";"CreepTumor";NA;57;0
"Building";"CreepTumorQueen";NA;59;0
"Unit";"Zergling";"Larva";59;1
"Unit";"Zergling";"Larva";60;1
"Unit";"Zergling";"Larva";61;1
"Unit";"Zergling";"Larva";62;1
"Unit";"Zergling";"Larva";63;1
"Unit";"Zergling";"Larva";64;1
"Unit";"Zergling";"Larva";65;1
"Unit";"Zergling";"Larva";66;1
"Building";"EvolutionChamber";NA;67;0
"Unit";"Overlord";"Larva";67;0
"Building";"EvolutionChamber";NA;67;0
"Unit";"Queen";"Hatchery";70;2
"Building";"SporeCrawler";NA;74;0
"Building";"CreepTumor";NA;74;0
"Unit";"Zergling";"Larva";74;1
"Unit";"Zergling";"Larva";75;1
"Unit";"Zergling";"Larva";76;1
"Unit";"Zergling";"Larva";77;1
"Unit";"Zergling";"Larva";78;1
"Unit";"Zergling";"Larva";79;1
"Unit";"Overlord";"Larva";82;0
"Building";"SporeCrawler";NA;85;0
"Unit";"Overlord";"Larva";87;0
"Building";"CreepTumor";NA;91;0
"Building";"CreepTumor";NA;91;0
"Building";"CreepTumorQueen";NA;94;0
"Building";"SporeCrawler";NA;95;0
"Unit";"Overlord";"Larva";95;0
"Unit";"Zergling";"Larva";101;1
"Unit";"Zergling";"Larva";102;1
"Unit";"Zergling";"Larva";103;1
"Unit";"Zergling";"Larva";104;1
"Unit";"Zergling";"Larva";105;1
"Unit";"Zergling";"Larva";106;1
"Unit";"Zergling";"Larva";107;1
"Unit";"Zergling";"Larva";108;1
"Building";"CreepTumor";NA;117;0
"Building";"Extractor";NA;118;0
"Building";"CreepTumor";NA;120;0
"Unit";"Overlord";"Larva";122;0
"Building";"CreepTumorQueen";NA;122;0
"Building";"CreepTumorQueen";NA;122;0
"Unit";"Overlord";"Larva";122;0
"Building";"Hatchery";NA;122;0
"Building";"CreepTumorQueen";NA;122;0
"Building";"Extractor";NA;122;0
"Building";"Extractor";NA;122;0
"Building";"BanelingNest";NA;122;0
"Unit";"Overlord";"Larva";122;0
"Building";"CreepTumorQueen";NA;122;0
"Unit";"Overlord";"Larva";126;0
"Building";"CreepTumor";NA;126;0
"Unit";"Overlord";"Larva";126;0
"Building";"Hatchery";NA;131;0
"Building";"Extractor";NA;131;0
"Unit";"Zergling";"Larva";131;1
"Unit";"Zergling";"Larva";132;1
"Unit";"Zergling";"Larva";133;1
"Unit";"Zergling";"Larva";134;1
"Building";"CreepTumorQueen";NA;135;0
"Unit";"Zergling";"Larva";135;1
"Unit";"Zergling";"Larva";136;1
"Unit";"Zergling";"Larva";137;1
"Unit";"Zergling";"Larva";138;1
"Unit";"Zergling";"Larva";139;1
"Unit";"Zergling";"Larva";140;1
"Building";"CreepTumorQueen";NA;141;0
"Building";"CreepTumor";NA;141;0
"Building";"CreepTumor";NA;141;0
"Building";"CreepTumor";NA;141;0
"Building";"CreepTumor";NA;141;0
"Building";"CreepTumor";NA;141;0
"Unit";"Zergling";"Larva";141;1
"Unit";"Zergling";"Larva";142;1
"Unit";"Zergling";"Larva";143;1
"Unit";"Zergling";"Larva";144;1
"Unit";"Zergling";"Larva";145;1
"Unit";"Zergling";"Larva";146;1
"Unit";"Zergling";"Larva";147;1
"Unit";"Zergling";"Larva";148;1
"Unit";"Zergling";"Larva";149;1
"Unit";"Zergling";"Larva";150;1
"Unit";"Zergling";"Larva";151;1
"Unit";"Zergling";"Larva";152;1
"Unit";"Zergling";"Larva";153;1
"Unit";"Zergling";"Larva";154;1
"Unit";"Zergling";"Larva";155;1
"Unit";"Zergling";"Larva";156;1
"Building";"Spire";NA;157;0
"Unit";"Baneling";"Zergling";159;0
"Unit";"Baneling";"Zergling";159;0
"Unit";"Baneling";"Zergling";159;0
"Unit";"Baneling";"Zergling";159;0
"Unit";"Baneling";"Zergling";159;0
"Unit";"Baneling";"Zergling";159;0
"Unit";"Baneling";"Zergling";159;0
"Unit";"Baneling";"Zergling";159;0
"Unit";"Baneling";"Zergling";159;0
"Unit";"Baneling";"Zergling";159;0
"Building";"CreepTumor";NA;159;0
"Building";"CreepTumor";NA;159;0
"Unit";"Overlord";"Larva";162;0
"Building";"CreepTumorQueen";NA;162;0
"Building";"CreepTumorQueen";NA;162;0
"Building";"CreepTumorQueen";NA;162;0
"Building";"CreepTumor";NA;162;0
"Building";"CreepTumorQueen";NA;162;0
"Building";"CreepTumorQueen";NA;162;0
"Unit";"Overlord";"Larva";171;0
"Unit";"Queen";"Hatchery";172;2
"Building";"CreepTumor";NA;174;0
"Building";"CreepTumor";NA;174;0
"Building";"CreepTumor";NA;174;0
"Building";"CreepTumor";NA;174;0
"Building";"CreepTumor";NA;174;0
"Building";"CreepTumor";NA;174;0
"Building";"Extractor";NA;178;0
"Unit";"Overlord";"Larva";178;0
"Building";"CreepTumorQueen";NA;178;0
"Unit";"Zergling";"Larva";178;1
"Unit";"Zergling";"Larva";179;1
"Unit";"Zergling";"Larva";180;1
"Unit";"Zergling";"Larva";181;1
"Unit";"Zergling";"Larva";182;1
"Unit";"Zergling";"Larva";183;1
"Unit";"Zergling";"Larva";184;1
"Unit";"Zergling";"Larva";185;1
"Unit";"Zergling";"Larva";186;1
"Unit";"Zergling";"Larva";187;1
"Unit";"Zergling";"Larva";188;1
"Unit";"Zergling";"Larva";189;1
"Unit";"Zergling";"Larva";190;1
"Unit";"Zergling";"Larva";191;1
"Unit";"Zergling";"Larva";192;1
"Unit";"Zergling";"Larva";193;1
"Unit";"Zergling";"Larva";194;1
"Unit";"Zergling";"Larva";195;1
"Unit";"Queen";"Hatchery";196;2
"Building";"CreepTumor";NA;198;0
"Building";"CreepTumor";NA;198;0
"Building";"CreepTumor";NA;198;0
"Building";"CreepTumor";NA;198;0
"Building";"CreepTumor";NA;198;0
"Building";"Hatchery";NA;198;0
"Building";"CreepTumor";NA;198;0
"Building";"CreepTumorQueen";NA;198;0
"Unit";"Mutalisk";"Larva";198;2
"Unit";"Mutalisk";"Larva";200;2
"Unit";"Mutalisk";"Larva";202;2
"Unit";"Mutalisk";"Larva";204;2
"Unit";"Mutalisk";"Larva";206;2
"Unit";"Mutalisk";"Larva";208;2
"Unit";"Mutalisk";"Larva";210;2
"Building";"CreepTumorQueen";NA;212;0
"Unit";"Mutalisk";"Larva";212;2
"Building";"CreepTumorQueen";NA;214;0
"Unit";"Zergling";"Larva";214;1
"Unit";"Zergling";"Larva";215;1
"Unit";"Zergling";"Larva";216;1
"Unit";"Zergling";"Larva";217;1
"Unit";"Zergling";"Larva";218;1
"Unit";"Zergling";"Larva";219;1
"Unit";"Zergling";"Larva";220;1
"Unit";"Zergling";"Larva";221;1
"Unit";"Zergling";"Larva";222;1
"Unit";"Zergling";"Larva";223;1
"Unit";"Zergling";"Larva";224;1
"Unit";"Zergling";"Larva";225;1
"Unit";"Zergling";"Larva";226;1
"Unit";"Zergling";"Larva";227;1
"Building";"InfestationPit";NA;228;0
"Unit";"Zergling";"Larva";228;1
"Unit";"Zergling";"Larva";229;1
"Unit";"Overlord";"Larva";230;0
"Unit";"Overlord";"Larva";230;0
"Building";"CreepTumorQueen";NA;230;0
"Building";"CreepTumor";NA;230;0
"Unit";"Mutalisk";"Larva";230;2
"Unit";"Mutalisk";"Larva";232;2
"Building";"CreepTumorQueen";NA;234;0
"Building";"CreepTumor";NA;234;0
"Unit";"Overlord";"Larva";234;0
"Unit";"Overlord";"Larva";234;0
"Unit";"Zergling";"Larva";239;1
"Unit";"Zergling";"Larva";240;1
"Unit";"Zergling";"Larva";241;1
"Unit";"Zergling";"Larva";242;1
"Unit";"Zergling";"Larva";243;1
"Unit";"Zergling";"Larva";244;1
"Unit";"Zergling";"Larva";245;1
"Unit";"Zergling";"Larva";246;1
"Unit";"Zergling";"Larva";247;1
"Unit";"Zergling";"Larva";248;1
"Unit";"Zergling";"Larva";249;1
"Unit";"Zergling";"Larva";250;1
"Unit";"Zergling";"Larva";251;1
"Unit";"Zergling";"Larva";252;1
"Unit";"Zergling";"Larva";253;1
"Unit";"Zergling";"Larva";254;1
"Unit";"Zergling";"Larva";255;1
"Unit";"Zergling";"Larva";256;1
"Unit";"Zergling";"Larva";257;1
"Unit";"Zergling";"Larva";258;1
"Unit";"Zergling";"Larva";259;1
"Unit";"Zergling";"Larva";260;1
"Building";"CreepTumor";NA;261;0
"Unit";"Baneling";"Zergling";261;0
"Unit";"Baneling";"Zergling";261;0
"Building";"CreepTumor";NA;261;0
"Building";"CreepTumor";NA;261;0
"Building";"CreepTumor";NA;261;0
"Building";"CreepTumor";NA;261;0
"Building";"CreepTumor";NA;261;0
"Building";"CreepTumor";NA;261;0
"Building";"Extractor";NA;261;0
"Upgrade";"Burrow";"Hatchery";261;0
"Unit";"Queen";"Hatchery";268;2
"Building";"SporeCrawler";NA;270;0
"Building";"SpineCrawler";NA;273;0
"Building";"SporeCrawler";NA;273;0
"Building";"SpineCrawler";NA;273;0
"Unit";"Overlord";"Larva";273;0
"Unit";"Overlord";"Larva";273;0
"Building";"CreepTumor";NA;273;0
"Building";"CreepTumor";NA;273;0
"Building";"CreepTumor";NA;273;0
"Unit";"Overlord";"Larva";273;0
"Unit";"Overlord";"Larva";273;0
"Building";"Extractor";NA;273;0
"Building";"CreepTumor";NA;273;0
"Building";"CreepTumor";NA;273;0
"Building";"CreepTumor";NA;273;0
"Building";"CreepTumor";NA;273;0
"Building";"CreepTumor";NA;273;0
"Building";"CreepTumor";NA;273;0
"Building";"CreepTumorQueen";NA;273;0
"Building";"CreepTumorQueen";NA;273;0
"Building";"CreepTumorQueen";NA;273;0
"Unit";"Zergling";"Larva";273;1
"Unit";"Zergling";"Larva";274;1
"Unit";"Zergling";"Larva";275;1
"Unit";"Zergling";"Larva";276;1
"Unit";"Zergling";"Larva";277;1
"Unit";"Zergling";"Larva";278;1
"Unit";"Zergling";"Larva";279;1
"Unit";"Zergling";"Larva";280;1
"Unit";"Zergling";"Larva";281;1
"Unit";"Zergling";"Larva";282;1
"Unit";"Zergling";"Larva";283;1
"Unit";"Zergling";"Larva";284;1
"Unit";"Zergling";"Larva";285;1
"Unit";"Zergling";"Larva";286;1
"Unit";"Zergling";"Larva";287;1
"Unit";"Zergling";"Larva";288;1
"Unit";"Zergling";"Larva";289;1
"Unit";"Zergling";"Larva";290;1
"Unit";"Zergling";"Larva";291;1
"Unit";"Zergling";"Larva";292;1
"Unit";"Zergling";"Larva";293;1
"Unit";"Zergling";"Larva";294;1
"Unit";"Zergling";"Larva";295;1
"Unit";"Zergling";"Larva";296;1
"Unit";"Zergling";"Larva";297;1
"Unit";"Zergling";"Larva";298;1
"Unit";"Zergling";"Larva";299;1
"Unit";"Zergling";"Larva";300;1
"Unit";"Zergling";"Larva";301;1
"Unit";"Zergling";"Larva";302;1
"Building";"CreepTumorQueen";NA;303;0
"Unit";"Zergling";"Larva";303;1
"Unit";"Zergling";"Larva";304;1
"Unit";"Zergling";"Larva";305;1
"Unit";"Zergling";"Larva";306;1
"Unit";"Zergling";"Larva";307;1
"Unit";"Zergling";"Larva";308;1
"Unit";"Zergling";"Larva";309;1
"Unit";"Zergling";"Larva";310;1
"Unit";"Zergling";"Larva";311;1
"Unit";"Zergling";"Larva";312;1
"Unit";"Zergling";"Larva";313;1
"Unit";"Zergling";"Larva";314;1
"Unit";"Zergling";"Larva";315;1
"Unit";"Zergling";"Larva";316;1
"Unit";"Zergling";"Larva";317;1
"Unit";"Zergling";"Larva";318;1
"Unit";"Zergling";"Larva";319;1
"Unit";"Zergling";"Larva";320;1
"Unit";"Zergling";"Larva";321;1
"Unit";"Zergling";"Larva";322;1
"Unit";"Zergling";"Larva";323;1
"Unit";"Zergling";"Larva";324;1
"Unit";"Zergling";"Larva";325;1
"Unit";"Zergling";"Larva";326;1
"Unit";"Zergling";"Larva";327;1
"Unit";"Zergling";"Larva";328;1
"Unit";"Zergling";"Larva";329;1
"Unit";"Zergling";"Larva";330;1
"Unit";"Zergling";"Larva";331;1
"Unit";"Zergling";"Larva";332;1
"Unit";"Zergling";"Larva";333;1
"Unit";"Zergling";"Larva";334;1
"Unit";"Zergling";"Larva";335;1
"Unit";"Zergling";"Larva";336;1
"Unit";"Zergling";"Larva";337;1
"Unit";"Zergling";"Larva";338;1
"Unit";"Zergling";"Larva";339;1
"Unit";"Zergling";"Larva";340;1
"Unit";"Zergling";"Larva";341;1
"Unit";"Zergling";"Larva";342;1
"Unit";"Zergling";"Larva";343;1
"Unit";"Zergling";"Larva";344;1
"Unit";"Zergling";"Larva";345;1
"Unit";"Zergling";"Larva";346;1
"Building";"CreepTumor";NA;347;0
"Unit";"Baneling";"Zergling";347;0
"Unit";"Baneling";"Zergling";347;0
"Unit";"Baneling";"Zergling";347;0
"Unit";"Baneling";"Zergling";347;0
"Unit";"Baneling";"Zergling";347;0
"Unit";"Baneling";"Zergling";347;0
"Unit";"Baneling";"Zergling";347;0
"Unit";"Baneling";"Zergling";347;0
"Unit";"Baneling";"Zergling";347;0
"Unit";"Baneling";"Zergling";347;0
"Unit";"Baneling";"Zergling";347;0
"Unit";"Baneling";"Zergling";347;0
"Unit";"Baneling";"Zergling";347;0
"Unit";"Baneling";"Zergling";347;0
"Unit";"Baneling";"Zergling";347;0
"Unit";"Baneling";"Zergling";347;0
"Unit";"Baneling";"Zergling";347;0
"Unit";"Baneling";"Zergling";347;0
"Unit";"Baneling";"Zergling";347;0
"Unit";"Baneling";"Zergling";347;0
"Unit";"Baneling";"Zergling";347;0
"Unit";"Baneling";"Zergling";347;0
"Unit";"Baneling";"Zergling";347;0
"Unit";"Baneling";"Zergling";347;0
"Unit";"Baneling";"Zergling";347;0
"Unit";"Baneling";"Zergling";347;0
"Unit";"Baneling";"Zergling";347;0
"Unit";"Baneling";"Zergling";347;0
"Unit";"Baneling";"Zergling";347;0
"Unit";"Baneling";"Zergling";347;0
"Unit";"Baneling";"Zergling";347;0
"Unit";"Baneling";"Zergling";347;0
"Unit";"Baneling";"Zergling";347;0
"Unit";"Baneling";"Zergling";347;0
"Unit";"Baneling";"Zergling";347;0
"Unit";"Baneling";"Zergling";347;0
"Unit";"Baneling";"Zergling";347;0
"Unit";"Baneling";"Zergling";347;0
"Unit";"Baneling";"Zergling";347;0
"Unit";"Baneling";"Zergling";347;0
"Unit";"Baneling";"Zergling";347;0
"Unit";"Baneling";"Zergling";347;0
"Unit";"Baneling";"Zergling";347;0
"Unit";"Baneling";"Zergling";347;0
"Unit";"Baneling";"Zergling";347;0
"Unit";"Baneling";"Zergling";347;0
"Unit";"Baneling";"Zergling";347;0
"Unit";"Baneling";"Zergling";347;0
"Unit";"Baneling";"Zergling";347;0
"Unit";"Zergling";"Larva";347;1
"Unit";"Zergling";"Larva";348;1
"Unit";"Zergling";"Larva";349;1
"Unit";"Zergling";"Larva";350;1
"Unit";"Zergling";"Larva";351;1
"Unit";"Zergling";"Larva";352;1
"Unit";"Zergling";"Larva";353;1
"Unit";"Zergling";"Larva";354;1
"Building";"Hatchery";NA;355;0
"Building";"CreepTumor";NA;355;0
"Unit";"Baneling";"Zergling";355;0
"Unit";"Baneling";"Zergling";355;0
"Unit";"Baneling";"Zergling";355;0
"Unit";"Baneling";"Zergling";355;0
"Unit";"Baneling";"Zergling";355;0
"Unit";"Baneling";"Zergling";355;0
"Unit";"Baneling";"Zergling";355;0
"Unit";"Baneling";"Zergling";355;0
"Unit";"Baneling";"Zergling";355;0
"Unit";"Baneling";"Zergling";355;0
"Unit";"Baneling";"Zergling";355;0
"Unit";"Baneling";"Zergling";355;0
"Unit";"Baneling";"Zergling";355;0
"Unit";"Baneling";"Zergling";355;0
"Unit";"Baneling";"Zergling";355;0
"Unit";"Baneling";"Zergling";355;0
"Unit";"Baneling";"Zergling";355;0
"Unit";"Baneling";"Zergling";355;0
"Unit";"Baneling";"Zergling";355;0
"Unit";"Baneling";"Zergling";355;0
"Unit";"Baneling";"Zergling";355;0
"Unit";"Baneling";"Zergling";355;0
"Unit";"Baneling";"Zergling";355;0
"Unit";"Baneling";"Zergling";355;0
"Unit";"Zergling";"Larva";355;1
"Unit";"Zergling";"Larva";356;1
"Unit";"Zergling";"Larva";357;1
"Unit";"Zergling";"Larva";358;1
"Unit";"Zergling";"Larva";359;1
"Unit";"Zergling";"Larva";360;1
"Unit";"Zergling";"Larva";361;1
"Unit";"Zergling";"Larva";362;1
"Unit";"Zergling";"Larva";363;1
"Unit";"Zergling";"Larva";364;1
"Unit";"Zergling";"Larva";365;1
"Unit";"Zergling";"Larva";366;1
"Unit";"Zergling";"Larva";367;1
"Unit";"Zergling";"Larva";368;1
"Unit";"Zergling";"Larva";369;1
"Unit";"Zergling";"Larva";370;1
"Building";"CreepTumorQueen";NA;371;0
"Building";"CreepTumorQueen";NA;371;0
"Building";"CreepTumorQueen";NA;371;0
"Building";"CreepTumorQueen";NA;371;0
"Unit";"Zergling";"Larva";371;1
"Unit";"Zergling";"Larva";372;1
"Unit";"Zergling";"Larva";373;1
"Unit";"Zergling";"Larva";374;1
"Unit";"Zergling";"Larva";375;1
"Unit";"Zergling";"Larva";376;1
"Unit";"Zergling";"Larva";377;1
"Unit";"Zergling";"Larva";378;1
"Unit";"Zergling";"Larva";379;1
"Unit";"Zergling";"Larva";380;1
"Unit";"Zergling";"Larva";381;1
"Unit";"Zergling";"Larva";382;1
"Unit";"Zergling";"Larva";383;1
"Unit";"Zergling";"Larva";384;1
"Unit";"Zergling";"Larva";385;1
"Unit";"Zergling";"Larva";386;1
"Unit";"Zergling";"Larva";387;1
"Unit";"Zergling";"Larva";388;1
"Unit";"Zergling";"Larva";389;1
"Unit";"Zergling";"Larva";390;1
"Unit";"Zergling";"Larva";391;1
"Unit";"Zergling";"Larva";392;1
"Unit";"Zergling";"Larva";393;1
"Unit";"Zergling";"Larva";394;1
"Unit";"Zergling";"Larva";395;1
"Unit";"Zergling";"Larva";396;1
"Unit";"Zergling";"Larva";397;1
"Unit";"Zergling";"Larva";398;1
"Unit";"Zergling";"Larva";399;1
"Unit";"Zergling";"Larva";400;1
"Unit";"Zergling";"Larva";401;1
"Unit";"Zergling";"Larva";402;1
"Unit";"Zergling";"Larva";403;1
"Unit";"Zergling";"Larva";404;1
"Unit";"Zergling";"Larva";405;1
"Unit";"Zergling";"Larva";406;1
"Unit";"Zergling";"Larva";407;1
"Unit";"Zergling";"Larva";408;1
"Unit";"Zergling";"Larva";409;1
"Unit";"Zergling";"Larva";410;1
"Unit";"Zergling";"Larva";411;1
"Unit";"Zergling";"Larva";412;1
"Unit";"Zergling";"Larva";413;1
"Unit";"Zergling";"Larva";414;1
"Unit";"Zergling";"Larva";415;1
"Unit";"Zergling";"Larva";416;1
"Unit";"Zergling";"Larva";417;1
"Unit";"Zergling";"Larva";418;1
"Unit";"Zergling";"Larva";419;1
"Unit";"Zergling";"Larva";420;1
"Unit";"Zergling";"Larva";421;1
"Unit";"Zergling";"Larva";422;1
"Unit";"Corruptor";"Larva";423;2
"Unit";"Corruptor";"Larva";425;2
"Unit";"Corruptor";"Larva";427;2
"Unit";"Corruptor";"Larva";429;2
"Unit";"Corruptor";"Larva";431;2
"Unit";"Corruptor";"Larva";433;2
"Building";"CreepTumor";NA;435;0
"Building";"CreepTumor";NA;435;0
"Building";"CreepTumor";NA;435;0
"Building";"CreepTumor";NA;435;0
"Building";"CreepTumor";NA;435;0
"Building";"CreepTumorQueen";NA;435;0
"Building";"CreepTumorQueen";NA;435;0
"Unit";"Corruptor";"Larva";435;2
"Unit";"Corruptor";"Larva";437;2
"Unit";"Corruptor";"Larva";439;2
"Unit";"Corruptor";"Larva";441;2
"Unit";"Corruptor";"Larva";443;2
"Unit";"Zergling";"Larva";445;1
"Unit";"Zergling";"Larva";446;1
"Unit";"Zergling";"Larva";447;1
"Unit";"Zergling";"Larva";448;1
"Unit";"Zergling";"Larva";449;1
"Unit";"Zergling";"Larva";450;1
"Unit";"Zergling";"Larva";451;1
"Unit";"Zergling";"Larva";452;1
"Unit";"Zergling";"Larva";453;1
"Unit";"Zergling";"Larva";454;1
"Unit";"Zergling";"Larva";455;1
"Unit";"Zergling";"Larva";456;1
"Unit";"Zergling";"Larva";457;1
"Unit";"Zergling";"Larva";458;1
"Unit";"Zergling";"Larva";459;1
"Unit";"Zergling";"Larva";460;1
"Unit";"Zergling";"Larva";461;1
"Unit";"Zergling";"Larva";462;1
"Unit";"Zergling";"Larva";463;1
"Unit";"Zergling";"Larva";464;1
"Unit";"Zergling";"Larva";465;1
"Unit";"Zergling";"Larva";466;1
"Unit";"Zergling";"Larva";467;1
"Unit";"Zergling";"Larva";468;1
"Unit";"Zergling";"Larva";469;1
"Unit";"Zergling";"Larva";470;1
"Unit";"Zergling";"Larva";471;1
"Unit";"Zergling";"Larva";472;1
"Unit";"Zergling";"Larva";473;1
"Unit";"Zergling";"Larva";474;1
"Unit";"Zergling";"Larva";475;1
"Unit";"Zergling";"Larva";476;1
"Unit";"Zergling";"Larva";477;1
"Unit";"Zergling";"Larva";478;1
"Unit";"Zergling";"Larva";479;1
"Unit";"Zergling";"Larva";480;1
"Unit";"Zergling";"Larva";481;1
"Unit";"Zergling";"Larva";482;1
"Unit";"Zergling";"Larva";483;1
"Unit";"Zergling";"Larva";484;1
"Unit";"Zergling";"Larva";485;1
"Unit";"Zergling";"Larva";486;1
"Unit";"Zergling";"Larva";487;1
"Unit";"Zergling";"Larva";488;1
"Unit";"Zergling";"Larva";489;1
"Unit";"Zergling";"Larva";490;1
"Unit";"Zergling";"Larva";491;1
"Unit";"Zergling";"Larva";492;1
"Unit";"Zergling";"Larva";493;1
"Unit";"Zergling";"Larva";494;1
"Unit";"Zergling";"Larva";495;1
"Unit";"Zergling";"Larva";496;1
"Unit";"Zergling";"Larva";497;1
"Unit";"Zergling";"Larva";498;1
"Unit";"Zergling";"Larva";499;1
"Unit";"Zergling";"Larva";500;1
"Unit";"Zergling";"Larva";501;1
"Unit";"Zergling";"Larva";502;1
"Unit";"Zergling";"Larva";503;1
"Unit";"Zergling";"Larva";504;1
"Unit";"Zergling";"Larva";505;1
"Unit";"Zergling";"Larva";506;1
"Unit";"Zergling";"Larva";507;1
"Unit";"Zergling";"Larva";508;1
"Unit";"Zergling";"Larva";509;1
"Unit";"Zergling";"Larva";510;1
"Unit";"Zergling";"Larva";511;1
"Unit";"Zergling";"Larva";512;1
"Unit";"Zergling";"Larva";513;1
"Unit";"Zergling";"Larva";514;1
"Unit";"Zergling";"Larva";515;1
"Unit";"Zergling";"Larva";516;1
"Unit";"Zergling";"Larva";517;1
"Unit";"Zergling";"Larva";518;1
"Unit";"Zergling";"Larva";519;1
"Unit";"Zergling";"Larva";520;1
"Unit";"Zergling";"Larva";521;1
"Unit";"Zergling";"Larva";522;1
"Unit";"Zergling";"Larva";523;1
"Unit";"Zergling";"Larva";524;1
"Unit";"Zergling";"Larva";525;1
"Unit";"Zergling";"Larva";526;1
"Unit";"Zergling";"Larva";527;1
"Unit";"Zergling";"Larva";528;1
"Unit";"Zergling";"Larva";529;1
"Unit";"Zergling";"Larva";530;1
"Unit";"Zergling";"Larva";531;1
"Unit";"Zergling";"Larva";532;1
"Unit";"Zergling";"Larva";533;1
"Unit";"Zergling";"Larva";534;1
"Unit";"Zergling";"Larva";535;1
"Unit";"Zergling";"Larva";536;1
"Unit";"Zergling";"Larva";537;1
"Unit";"Zergling";"Larva";538;1
"Unit";"Zergling";"Larva";539;1
"Unit";"Zergling";"Larva";540;1
"Unit";"Zergling";"Larva";541;1
"Unit";"Zergling";"Larva";542;1
"Unit";"Zergling";"Larva";543;1
"Unit";"Zergling";"Larva";544;1
"Unit";"Zergling";"Larva";545;1
"Unit";"Zergling";"Larva";546;1
"Unit";"Zergling";"Larva";547;1
"Unit";"Zergling";"Larva";548;1
"Unit";"Zergling";"Larva";549;1
"Unit";"Zergling";"Larva";550;1
"Unit";"Baneling";"Zergling";551;0
"Unit";"Baneling";"Zergling";551;0
"Unit";"Baneling";"Zergling";551;0
"Unit";"Baneling";"Zergling";551;0
"Unit";"Baneling";"Zergling";551;0
"Unit";"Baneling";"Zergling";551;0
"Unit";"Baneling";"Zergling";551;0
"Unit";"Baneling";"Zergling";551;0
"Unit";"Baneling";"Zergling";551;0
"Unit";"Baneling";"Zergling";551;0
"Unit";"Baneling";"Zergling";551;0
"Unit";"Baneling";"Zergling";551;0
"Unit";"Baneling";"Zergling";551;0
"Unit";"Baneling";"Zergling";551;0
"Building";"CreepTumor";NA;551;0
"Building";"CreepTumor";NA;551;0
"Building";"CreepTumor";NA;551;0
"Unit";"Baneling";"Zergling";551;0
"Unit";"Baneling";"Zergling";551;0
"Unit";"Baneling";"Zergling";551;0
"Unit";"Baneling";"Zergling";551;0
"Unit";"Baneling";"Zergling";551;0
"Unit";"Baneling";"Zergling";551;0
"Unit";"Baneling";"Zergling";551;0
"Unit";"Baneling";"Zergling";551;0
"Unit";"Baneling";"Zergling";551;0
"Unit";"Baneling";"Zergling";551;0
"Building";"CreepTumor";NA;551;0
"Unit";"Baneling";"Zergling";551;0
"Unit";"Baneling";"Zergling";551;0
"Unit";"Baneling";"Zergling";551;0
"Unit";"Baneling";"Zergling";551;0
"Building";"CreepTumorQueen";NA;551;0
"Upgrade";"SprayZerg";NA;551;0
"Upgrade";"SprayZerg";NA;551;0
"Upgrade";"SprayZerg";NA;551;0
"Upgrade";"SprayZerg";NA;551;0
"Upgrade";"zerglingmovementspeed";NA;551;0
"Upgrade";"SprayZerg";NA;551;0
"Upgrade";"SprayZerg";NA;551;0
"Upgrade";"ZergGroundArmorsLevel1";NA;551;0
"Upgrade";"ZergMeleeWeaponsLevel1";NA;551;0
"Upgrade";"SprayZerg";NA;551;0
"Upgrade";"SprayZerg";NA;551;0
"Upgrade";"SprayZerg";NA;551;0
"Upgrade";"CentrificalHooks";NA;551;0
"Upgrade";"overlordspeed";NA;551;0
"Upgrade";"SprayZerg";NA;551;0
"Upgrade";"ZergGroundArmorsLevel2";NA;551;0
"Upgrade";"ZergMeleeWeaponsLevel2";NA;551;0
"Upgrade";"SprayZerg";NA;551;0
"Upgrade";"ZergFlyerWeaponsLevel1";NA;551;0
"Upgrade";"SprayZerg";NA;551;0
"Upgrade";"zerglingattackspeed";NA;551;0
