"type";"unit_name";"on_building";"total_supply";"supply"
"Unit";"Overlord";"Larva";13;0
"Building";"Extractor";NA;18;0
"Unit";"Overlord";"Larva";21;0
"Building";"SpawningPool";NA;19;0
"Building";"Hatchery";NA;17;0
"Unit";"Zergling";"Larva";22;1
"Unit";"Zergling";"Larva";22;1
"Unit";"Queen";"Hatchery";22;2
"Unit";"Queen";"Hatchery";22;2
"Building";"CreepTumorQueen";NA;35;0
"Unit";"Overlord";"Larva";35;0
"Unit";"Queen";"Hatchery";34;2
"Building";"CreepTumor";NA;35;0
"Building";"CreepTumorQueen";NA;38;0
"Unit";"Overlord";"Larva";35;0
"Building";"CreepTumorQueen";NA;44;0
"Unit";"Overlord";"Larva";40;0
"Building";"CreepTumor";NA;44;0
"Building";"CreepTumor";NA;44;0
"Unit";"Zergling";"Larva";44;1
"Unit";"Zergling";"Larva";44;1
"Unit";"Queen";"Hatchery";40;2
"Building";"Hatchery";NA;35;0
"Building";"CreepTumor";NA;55;0
"Building";"CreepTumor";NA;55;0
"Building";"CreepTumorQueen";NA;55;0
"Building";"Extractor";NA;53;0
"Building";"EvolutionChamber";NA;60;0
"Unit";"Queen";"Hatchery";55;2
"Building";"EvolutionChamber";NA;60;0
"Building";"CreepTumor";NA;65;0
"Building";"CreepTumor";NA;65;0
"Unit";"Zergling";"Larva";60;1
"Unit";"Zergling";"Larva";60;1
"Unit";"Zergling";"Larva";60;1
"Unit";"Zergling";"Larva";60;1
"Unit";"Zergling";"Larva";60;1
"Unit";"Zergling";"Larva";60;1
"Building";"CreepTumor";NA;77;0
"Unit";"Overlord";"Larva";67;0
"Building";"CreepTumor";NA;77;0
"Unit";"Overlord";"Larva";77;0
"Building";"CreepTumor";NA;77;0
"Building";"CreepTumorQueen";NA;77;0
"Unit";"Overlord";"Larva";77;0
"Building";"Hatchery";NA;57;0
"Building";"SporeCrawler";NA;77;0
"Building";"BanelingNest";NA;65;0
"Unit";"Overlord";"Larva";82;0
"Unit";"Zergling";"Larva";82;1
"Unit";"Zergling";"Larva";82;1
"Unit";"Zergling";"Larva";82;1
"Unit";"Zergling";"Larva";82;1
"Unit";"Zergling";"Larva";82;1
"Unit";"Zergling";"Larva";82;1
"Unit";"Zergling";"Larva";82;1
"Unit";"Zergling";"Larva";82;1
"Unit";"Zergling";"Larva";82;1
"Unit";"Zergling";"Larva";82;1
"Unit";"Zergling";"Larva";82;1
"Unit";"Zergling";"Larva";82;1
"Unit";"Zergling";"Larva";82;1
"Unit";"Zergling";"Larva";82;1
"Unit";"Zergling";"Larva";82;1
"Unit";"Zergling";"Larva";82;1
"Unit";"Zergling";"Larva";82;1
"Unit";"Zergling";"Larva";82;1
"Unit";"Zergling";"Larva";82;1
"Unit";"Zergling";"Larva";82;1
"Unit";"Zergling";"Larva";82;1
"Unit";"Zergling";"Larva";82;1
"Unit";"Zergling";"Larva";82;1
"Unit";"Zergling";"Larva";82;1
"Unit";"Zergling";"Larva";82;1
"Unit";"Zergling";"Larva";82;1
"Unit";"Zergling";"Larva";82;1
"Unit";"Zergling";"Larva";82;1
"Unit";"Zergling";"Larva";82;1
"Unit";"Zergling";"Larva";82;1
"Unit";"Zergling";"Larva";82;1
"Unit";"Zergling";"Larva";82;1
"Unit";"Baneling";"Zergling";86;0
"Unit";"Baneling";"Zergling";98;0
"Unit";"Baneling";"Zergling";98;0
"Unit";"Baneling";"Zergling";98;0
"Unit";"Baneling";"Zergling";98;0
"Unit";"Baneling";"Zergling";98;0
"Building";"Hatchery";NA;65;0
"Building";"CreepTumor";NA;98;0
"Unit";"Baneling";"Zergling";98;0
"Building";"CreepTumor";NA;98;0
"Unit";"Baneling";"Zergling";98;0
"Unit";"Zergling";"Larva";98;1
"Unit";"Zergling";"Larva";98;1
"Unit";"Zergling";"Larva";98;1
"Unit";"Zergling";"Larva";98;1
"Unit";"Zergling";"Larva";98;1
"Unit";"Zergling";"Larva";98;1
"Unit";"Zergling";"Larva";98;1
"Unit";"Zergling";"Larva";98;1
"Unit";"Zergling";"Larva";114;1
"Unit";"Zergling";"Larva";114;1
"Unit";"Zergling";"Larva";114;1
"Unit";"Zergling";"Larva";114;1
"Unit";"Zergling";"Larva";114;1
"Unit";"Zergling";"Larva";114;1
"Unit";"Zergling";"Larva";114;1
"Unit";"Zergling";"Larva";114;1
"Unit";"Baneling";"Zergling";114;0
"Unit";"Baneling";"Zergling";114;0
"Unit";"Baneling";"Zergling";114;0
"Unit";"Zergling";"Larva";122;1
"Unit";"Zergling";"Larva";122;1
"Unit";"Zergling";"Larva";122;1
"Unit";"Zergling";"Larva";122;1
"Unit";"Zergling";"Larva";122;1
"Unit";"Zergling";"Larva";122;1
"Unit";"Zergling";"Larva";122;1
"Unit";"Zergling";"Larva";122;1
"Unit";"Zergling";"Larva";122;1
"Unit";"Zergling";"Larva";122;1
"Unit";"Zergling";"Larva";122;1
"Unit";"Zergling";"Larva";122;1
"Unit";"Zergling";"Larva";122;1
"Unit";"Zergling";"Larva";122;1
"Unit";"Zergling";"Larva";122;1
"Unit";"Zergling";"Larva";122;1
"Unit";"Zergling";"Larva";122;1
"Unit";"Zergling";"Larva";122;1
"Unit";"Zergling";"Larva";122;1
"Unit";"Zergling";"Larva";122;1
"Unit";"Zergling";"Larva";122;1
"Unit";"Zergling";"Larva";122;1
"Unit";"Zergling";"Larva";130;1
"Unit";"Zergling";"Larva";130;1
"Unit";"Zergling";"Larva";130;1
"Unit";"Zergling";"Larva";130;1
"Building";"CreepTumor";NA;130;0
"Unit";"Zergling";"Larva";130;1
"Unit";"Zergling";"Larva";130;1
"Unit";"Zergling";"Larva";130;1
"Unit";"Zergling";"Larva";130;1
"Building";"CreepTumor";NA;130;0
"Building";"CreepTumor";NA;130;0
"Building";"Extractor";NA;152;0
"Unit";"Overlord";"Larva";152;0
"Building";"Extractor";NA;152;0
"Upgrade";"ZergMeleeWeaponsLevel1";"EvolutionChamber";82;0
"Unit";"Overlord";"Larva";172;0
"Unit";"Overlord";"Larva";172;0
"Unit";"Queen";"Hatchery";152;2
"Building";"Extractor";NA;172;0
"Building";"CreepTumor";NA;175;0
"Building";"Extractor";NA;172;0
"Building";"CreepTumor";NA;177;0
"Unit";"Overlord";"Larva";177;0
"Building";"EvolutionChamber";NA;180;0
"Unit";"Zergling";"Larva";180;1
"Unit";"Zergling";"Larva";180;1
"Unit";"Zergling";"Larva";180;1
"Unit";"Zergling";"Larva";180;1
"Unit";"Zergling";"Larva";180;1
"Unit";"Zergling";"Larva";180;1
"Unit";"Zergling";"Larva";180;1
"Unit";"Zergling";"Larva";180;1
"Unit";"Zergling";"Larva";180;1
"Unit";"Zergling";"Larva";180;1
"Unit";"Zergling";"Larva";180;1
"Unit";"Zergling";"Larva";180;1
"Unit";"Zergling";"Larva";180;1
"Unit";"Zergling";"Larva";180;1
"Unit";"Zergling";"Larva";180;1
"Unit";"Zergling";"Larva";180;1
"Unit";"Zergling";"Larva";180;1
"Unit";"Zergling";"Larva";180;1
"Unit";"Zergling";"Larva";180;1
"Unit";"Zergling";"Larva";180;1
"Unit";"Zergling";"Larva";180;1
"Unit";"Zergling";"Larva";180;1
"Unit";"Zergling";"Larva";180;1
"Unit";"Zergling";"Larva";180;1
"Unit";"Zergling";"Larva";180;1
"Unit";"Zergling";"Larva";180;1
"Unit";"Zergling";"Larva";180;1
"Unit";"Zergling";"Larva";180;1
"Unit";"Zergling";"Larva";180;1
"Unit";"Zergling";"Larva";180;1
"Unit";"Zergling";"Larva";180;1
"Unit";"Zergling";"Larva";180;1
"Unit";"Zergling";"Larva";180;1
"Unit";"Zergling";"Larva";180;1
"Unit";"Overlord";"Larva";180;0
"Unit";"Overlord";"Larva";180;0
"Unit";"Overlord";"Larva";180;0
"Building";"SporeCrawler";NA;180;0
"Unit";"Zergling";"Larva";214;1
"Unit";"Zergling";"Larva";214;1
"Building";"SporeCrawler";NA;180;0
"Unit";"Zergling";"Larva";214;1
"Unit";"Zergling";"Larva";214;1
"Unit";"Zergling";"Larva";214;1
"Unit";"Zergling";"Larva";214;1
"Unit";"Zergling";"Larva";214;1
"Unit";"Zergling";"Larva";214;1
"Unit";"Zergling";"Larva";214;1
"Unit";"Zergling";"Larva";214;1
"Unit";"Zergling";"Larva";214;1
"Unit";"Zergling";"Larva";214;1
"Unit";"Zergling";"Larva";214;1
"Unit";"Zergling";"Larva";214;1
"Unit";"Zergling";"Larva";214;1
"Unit";"Zergling";"Larva";214;1
"Unit";"Queen";"Hatchery";180;2
"Building";"CreepTumor";NA;214;0
"Unit";"Baneling";"Zergling";214;0
"Unit";"Baneling";"Zergling";214;0
"Unit";"Baneling";"Zergling";214;0
"Unit";"Baneling";"Zergling";214;0
"Unit";"Baneling";"Zergling";214;0
"Unit";"Baneling";"Zergling";214;0
"Unit";"Baneling";"Zergling";214;0
"Unit";"Baneling";"Zergling";214;0
"Unit";"Baneling";"Zergling";214;0
"Unit";"Baneling";"Zergling";214;0
"Unit";"Baneling";"Zergling";214;0
"Unit";"Baneling";"Zergling";214;0
"Unit";"Baneling";"Zergling";214;0
"Unit";"Baneling";"Zergling";214;0
"Unit";"Baneling";"Zergling";214;0
"Unit";"Baneling";"Zergling";214;0
"Unit";"Baneling";"Zergling";214;0
"Unit";"Baneling";"Zergling";214;0
"Unit";"Baneling";"Zergling";214;0
"Unit";"Baneling";"Zergling";214;0
"Unit";"Baneling";"Zergling";214;0
"Unit";"Baneling";"Zergling";214;0
"Unit";"Baneling";"Zergling";214;0
"Unit";"Baneling";"Zergling";214;0
"Unit";"Baneling";"Zergling";214;0
"Unit";"Baneling";"Zergling";214;0
"Unit";"Baneling";"Zergling";214;0
"Unit";"Baneling";"Zergling";214;0
"Unit";"Baneling";"Zergling";214;0
"Unit";"Overlord";"Larva";214;0
"Unit";"Zergling";"Larva";232;1
"Unit";"Zergling";"Larva";232;1
"Unit";"Zergling";"Larva";232;1
"Unit";"Zergling";"Larva";232;1
"Unit";"Zergling";"Larva";232;1
"Unit";"Zergling";"Larva";232;1
"Unit";"Zergling";"Larva";232;1
"Unit";"Zergling";"Larva";232;1
"Unit";"Zergling";"Larva";232;1
"Unit";"Zergling";"Larva";232;1
"Unit";"Zergling";"Larva";232;1
"Unit";"Zergling";"Larva";232;1
"Unit";"Zergling";"Larva";232;1
"Unit";"Zergling";"Larva";232;1
"Unit";"Zergling";"Larva";232;1
"Unit";"Zergling";"Larva";232;1
"Unit";"Zergling";"Larva";232;1
"Unit";"Zergling";"Larva";232;1
"Unit";"Zergling";"Larva";232;1
"Unit";"Zergling";"Larva";232;1
"Unit";"Zergling";"Larva";232;1
"Unit";"Zergling";"Larva";232;1
"Unit";"Zergling";"Larva";232;1
"Unit";"Zergling";"Larva";232;1
"Unit";"Zergling";"Larva";232;1
"Unit";"Zergling";"Larva";232;1
"Unit";"Zergling";"Larva";232;1
"Unit";"Zergling";"Larva";232;1
"Unit";"Zergling";"Larva";232;1
"Unit";"Zergling";"Larva";232;1
"Unit";"Zergling";"Larva";232;1
"Unit";"Zergling";"Larva";232;1
"Unit";"Zergling";"Larva";232;1
"Unit";"Zergling";"Larva";232;1
"Unit";"Zergling";"Larva";232;1
"Unit";"Zergling";"Larva";232;1
"Unit";"Zergling";"Larva";232;1
"Unit";"Zergling";"Larva";232;1
"Unit";"Zergling";"Larva";232;1
"Unit";"Zergling";"Larva";232;1
"Unit";"Baneling";"Zergling";232;0
"Unit";"Baneling";"Zergling";232;0
"Unit";"Baneling";"Zergling";232;0
"Unit";"Baneling";"Zergling";232;0
"Unit";"Baneling";"Zergling";232;0
"Unit";"Baneling";"Zergling";242;0
"Unit";"Overlord";"Larva";232;0
"Unit";"Baneling";"Zergling";256;0
"Unit";"Baneling";"Zergling";258;0
"Unit";"Baneling";"Zergling";258;0
"Unit";"Baneling";"Zergling";258;0
"Unit";"Baneling";"Zergling";258;0
"Unit";"Baneling";"Zergling";260;0
"Unit";"Baneling";"Zergling";260;0
"Unit";"Baneling";"Zergling";262;0
"Unit";"Baneling";"Zergling";266;0
"Unit";"Baneling";"Zergling";272;0
"Unit";"Baneling";"Zergling";272;0
"Unit";"Baneling";"Zergling";272;0
"Unit";"Baneling";"Zergling";276;0
"Unit";"Baneling";"Zergling";276;0
"Unit";"Baneling";"Zergling";276;0
"Unit";"Baneling";"Zergling";276;0
"Unit";"Baneling";"Zergling";276;0
"Unit";"Baneling";"Zergling";276;0
"Upgrade";"ZergGroundArmorsLevel1";"EvolutionChamber";214;0
"Unit";"Zergling";"Larva";276;1
"Unit";"Zergling";"Larva";276;1
"Unit";"Zergling";"Larva";276;1
"Unit";"Zergling";"Larva";276;1
"Unit";"Zergling";"Larva";276;1
"Unit";"Zergling";"Larva";276;1
"Unit";"Zergling";"Larva";276;1
"Unit";"Zergling";"Larva";276;1
"Unit";"Zergling";"Larva";276;1
"Unit";"Zergling";"Larva";276;1
"Unit";"Zergling";"Larva";276;1
"Unit";"Zergling";"Larva";276;1
"Unit";"Zergling";"Larva";276;1
"Unit";"Zergling";"Larva";276;1
