"type";"unit_name";"on_building";"total_supply";"supply"
"Unit";"Overlord";"Larva";13;0
"Building";"Extractor";NA;15;0
"Building";"SpawningPool";NA;17;0
"Unit";"Zergling";"Larva";21;1
"Unit";"Zergling";"Larva";21;1
"Unit";"Overlord";"Larva";21;0
"Unit";"Queen";"Hatchery";21;2
"Building";"Hatchery";NA;20;0
"Unit";"Queen";"Hatchery";24;2
"Unit";"Overlord";"Larva";29;0
"Unit";"Queen";"Hatchery";28;2
"Building";"CreepTumorQueen";NA;41;0
"Unit";"Overlord";"Larva";42;0
"Unit";"Zergling";"Larva";44;1
"Unit";"Zergling";"Larva";44;1
"Unit";"Zergling";"Larva";45;1
"Unit";"Zergling";"Larva";45;1
"Building";"CreepTumorQueen";NA;49;0
"Unit";"Overlord";"Larva";49;0
"Unit";"Overlord";"Larva";49;0
"Building";"CreepTumor";NA;53;0
"Building";"CreepTumor";NA;53;0
"Unit";"Zergling";"Larva";53;1
"Unit";"Zergling";"Larva";53;1
"Unit";"Zergling";"Larva";53;1
"Unit";"Zergling";"Larva";53;1
"Unit";"Zergling";"Larva";53;1
"Unit";"Zergling";"Larva";53;1
"Unit";"Zergling";"Larva";53;1
"Unit";"Zergling";"Larva";53;1
"Unit";"Zergling";"Larva";53;1
"Unit";"Zergling";"Larva";53;1
"Unit";"Zergling";"Larva";53;1
"Unit";"Zergling";"Larva";53;1
"Unit";"Zergling";"Larva";53;1
"Unit";"Zergling";"Larva";53;1
"Unit";"Overlord";"Larva";53;0
"Building";"Hatchery";NA;42;0
"Building";"SporeCrawler";NA;53;0
"Unit";"Zergling";"Larva";53;1
"Unit";"Zergling";"Larva";53;1
"Unit";"Queen";"Hatchery";53;2
"Unit";"Zergling";"Larva";53;1
"Unit";"Zergling";"Larva";53;1
"Unit";"Overlord";"Larva";53;0
"Building";"BanelingNest";NA;53;0
"Unit";"Zergling";"Larva";73;1
"Unit";"Zergling";"Larva";73;1
"Unit";"Zergling";"Larva";73;1
"Unit";"Zergling";"Larva";73;1
"Unit";"Zergling";"Larva";73;1
"Unit";"Zergling";"Larva";73;1
"Unit";"Zergling";"Larva";73;1
"Unit";"Zergling";"Larva";73;1
"Unit";"Zergling";"Larva";73;1
"Unit";"Zergling";"Larva";73;1
"Unit";"Zergling";"Larva";73;1
"Unit";"Zergling";"Larva";73;1
"Unit";"Zergling";"Larva";73;1
"Unit";"Zergling";"Larva";73;1
"Unit";"Zergling";"Larva";73;1
"Unit";"Zergling";"Larva";73;1
"Building";"CreepTumor";NA;73;0
"Unit";"Queen";"Hatchery";69;2
"Building";"CreepTumor";NA;96;0
"Unit";"Queen";"Hatchery";73;2
"Building";"Extractor";NA;101;0
"Building";"Extractor";NA;101;0
"Building";"CreepTumorQueen";NA;108;0
"Building";"EvolutionChamber";NA;103;0
"Building";"EvolutionChamber";NA;104;0
"Building";"CreepTumor";NA;111;0
"Unit";"Queen";"Hatchery";108;2
"Unit";"Overlord";"Larva";113;0
"Unit";"Overlord";"Larva";122;0
"Building";"CreepTumor";NA;124;0
"Building";"CreepTumorQueen";NA;124;0
"Building";"CreepTumorQueen";NA;124;0
"Building";"Extractor";NA;122;0
"Building";"Extractor";NA;122;0
"Building";"Extractor";NA;122;0
"Building";"CreepTumor";NA;129;0
"Building";"CreepTumor";NA;129;0
"Building";"CreepTumor";NA;131;0
"Building";"CreepTumor";NA;132;0
"Building";"HydraliskDen";NA;129;0
"Unit";"Overlord";"Larva";137;0
"Building";"CreepTumorQueen";NA;139;0
"Building";"RoachWarren";NA;129;0
"Unit";"Overlord";"Larva";139;0
"Unit";"Overlord";"Larva";139;0
"Unit";"Overlord";"Larva";139;0
"Unit";"Overlord";"Larva";139;0
"Building";"CreepTumorQueen";NA;139;0
"Building";"CreepTumor";NA;139;0
"Building";"CreepTumor";NA;139;0
"Unit";"Hydralisk";"Larva";139;2
"Unit";"Hydralisk";"Larva";139;2
"Building";"CreepTumor";NA;139;0
"Building";"CreepTumor";NA;139;0
"Unit";"Hydralisk";"Larva";139;2
"Unit";"Hydralisk";"Larva";139;2
"Unit";"Hydralisk";"Larva";139;2
"Unit";"Hydralisk";"Larva";139;2
"Unit";"Hydralisk";"Larva";139;2
"Unit";"Hydralisk";"Larva";139;2
"Unit";"Hydralisk";"Larva";139;2
"Unit";"Hydralisk";"Larva";139;2
"Unit";"Hydralisk";"Larva";145;2
"Unit";"Hydralisk";"Larva";145;2
"Unit";"Hydralisk";"Larva";145;2
"Building";"CreepTumor";NA;153;0
"Unit";"Hydralisk";"Larva";145;2
"Building";"CreepTumor";NA;157;0
"Unit";"Hydralisk";"Larva";149;2
"Unit";"Hydralisk";"Larva";149;2
"Building";"CreepTumor";NA;159;0
"Unit";"Hydralisk";"Larva";153;2
"Building";"Hatchery";NA;139;0
"Building";"CreepTumorQueen";NA;161;0
"Building";"CreepTumorQueen";NA;167;0
"Building";"CreepTumor";NA;165;0
"Upgrade";"EvolveGroovedSpines";"HydraliskDen";139;0
"Upgrade";"ZergGroundArmorsLevel1";"EvolutionChamber";139;0
"Upgrade";"ZergMissileWeaponsLevel1";"EvolutionChamber";139;0
"Unit";"Overlord";"Larva";173;0
"Building";"Extractor";NA;181;0
"Building";"Extractor";NA;181;0
"Upgrade";"GlialReconstitution";"RoachWarren";153;0
"Building";"InfestationPit";NA;181;0
"Unit";"Overlord";"Larva";190;0
"Unit";"Overlord";"Larva";190;0
"Building";"CreepTumor";NA;190;0
"Building";"CreepTumor";NA;190;0
"Building";"CreepTumor";NA;190;0
"Unit";"Hydralisk";"Larva";190;2
"Unit";"Hydralisk";"Larva";190;2
"Unit";"Hydralisk";"Larva";190;2
"Unit";"Roach";"Larva";190;2
"Unit";"Roach";"Larva";190;2
"Unit";"Roach";"Larva";190;2
"Unit";"Roach";"Larva";190;2
"Building";"CreepTumorQueen";NA;190;0
"Building";"SpineCrawler";NA;190;0
"Building";"CreepTumorQueen";NA;190;0
"Building";"SpineCrawler";NA;190;0
"Building";"SpineCrawler";NA;190;0
"Unit";"Overlord";"Larva";204;0
"Unit";"Overlord";"Larva";204;0
"Unit";"Overlord";"Larva";204;0
"Unit";"Overlord";"Larva";204;0
"Upgrade";"EvolveMuscularAugments";"HydraliskDen";190;0
"Building";"CreepTumorQueen";NA;204;0
"Building";"CreepTumorQueen";NA;204;0
"Building";"CreepTumor";NA;204;0
"Building";"CreepTumor";NA;204;0
"Building";"CreepTumorQueen";NA;204;0
"Building";"CreepTumorQueen";NA;204;0
"Building";"CreepTumor";NA;204;0
"Building";"CreepTumor";NA;204;0
"Building";"CreepTumorQueen";NA;204;0
"Building";"CreepTumorQueen";NA;204;0
"Unit";"Roach";"Larva";204;2
"Building";"CreepTumor";NA;204;0
"Building";"CreepTumor";NA;204;0
"Unit";"Overlord";"Larva";204;0
"Building";"Hatchery";NA;204;0
"Building";"CreepTumor";NA;207;0
"Building";"CreepTumor";NA;207;0
"Building";"CreepTumor";NA;207;0
"Building";"CreepTumor";NA;207;0
"Building";"CreepTumor";NA;207;0
"Building";"CreepTumor";NA;207;0
"Building";"CreepTumorQueen";NA;207;0
"Building";"CreepTumorQueen";NA;207;0
"Unit";"Overlord";"Larva";207;0
"Upgrade";"ZergMissileWeaponsLevel2";"EvolutionChamber";204;0
"Upgrade";"ZergGroundArmorsLevel2";"EvolutionChamber";204;0
"Unit";"Viper";"Larva";207;3
"Unit";"Viper";"Larva";207;3
"Unit";"Viper";"Larva";207;3
"Unit";"Zergling";"Larva";207;1
"Unit";"Zergling";"Larva";207;1
"Unit";"Zergling";"Larva";207;1
"Unit";"Zergling";"Larva";207;1
"Unit";"Zergling";"Larva";207;1
"Unit";"Zergling";"Larva";207;1
"Unit";"Zergling";"Larva";207;1
"Unit";"Zergling";"Larva";207;1
"Unit";"Zergling";"Larva";207;1
"Unit";"Zergling";"Larva";207;1
"Unit";"Zergling";"Larva";207;1
"Unit";"Zergling";"Larva";207;1
"Unit";"Overlord";"Larva";207;0
"Unit";"Overlord";"Larva";207;0
"Unit";"Hydralisk";"Larva";207;2
"Unit";"Hydralisk";"Larva";207;2
"Unit";"Hydralisk";"Larva";207;2
"Unit";"Hydralisk";"Larva";207;2
"Unit";"Hydralisk";"Larva";207;2
"Unit";"Hydralisk";"Larva";207;2
"Unit";"Hydralisk";"Larva";207;2
"Unit";"Hydralisk";"Larva";207;2
"Unit";"Hydralisk";"Larva";207;2
"Unit";"Hydralisk";"Larva";207;2
"Unit";"Hydralisk";"Larva";207;2
"Unit";"Hydralisk";"Larva";207;2
"Unit";"Hydralisk";"Larva";207;2
"Unit";"Hydralisk";"Larva";207;2
"Building";"Spire";NA;207;0
"Unit";"Roach";"Larva";256;2
"Unit";"Roach";"Larva";256;2
"Unit";"Roach";"Larva";256;2
"Unit";"Roach";"Larva";256;2
"Unit";"Roach";"Larva";256;2
"Unit";"Roach";"Larva";256;2
"Unit";"Roach";"Larva";256;2
"Unit";"Roach";"Larva";256;2
"Unit";"Roach";"Larva";256;2
"Unit";"Hydralisk";"Larva";256;2
"Unit";"Hydralisk";"Larva";256;2
"Unit";"Hydralisk";"Larva";256;2
"Unit";"Hydralisk";"Larva";256;2
"Unit";"Hydralisk";"Larva";256;2
"Unit";"Hydralisk";"Larva";256;2
"Unit";"Hydralisk";"Larva";256;2
"Unit";"Hydralisk";"Larva";256;2
"Unit";"Hydralisk";"Larva";256;2
"Unit";"Roach";"Larva";274;2
"Unit";"Roach";"Larva";274;2
"Unit";"Roach";"Larva";274;2
"Unit";"Roach";"Larva";274;2
"Unit";"Roach";"Larva";274;2
"Unit";"Roach";"Larva";274;2
"Unit";"Roach";"Larva";274;2
"Unit";"Roach";"Larva";274;2
"Unit";"Hydralisk";"Larva";292;2
"Unit";"Hydralisk";"Larva";292;2
"Unit";"Hydralisk";"Larva";292;2
"Unit";"Hydralisk";"Larva";292;2
"Unit";"Hydralisk";"Larva";292;2
"Unit";"Hydralisk";"Larva";292;2
"Unit";"Hydralisk";"Larva";292;2
"Unit";"Hydralisk";"Larva";292;2
"Unit";"Hydralisk";"Larva";292;2
"Building";"CreepTumor";NA;308;0
"Building";"CreepTumor";NA;308;0
"Unit";"Zergling";"Larva";308;1
"Unit";"Zergling";"Larva";308;1
"Unit";"Zergling";"Larva";308;1
"Unit";"Zergling";"Larva";308;1
"Unit";"Zergling";"Larva";308;1
"Unit";"Zergling";"Larva";308;1
"Unit";"Zergling";"Larva";308;1
"Unit";"Zergling";"Larva";308;1
"Unit";"Zergling";"Larva";308;1
"Unit";"Zergling";"Larva";308;1
"Unit";"Zergling";"Larva";308;1
"Unit";"Zergling";"Larva";308;1
"Unit";"Zergling";"Larva";308;1
"Unit";"Zergling";"Larva";308;1
"Unit";"Zergling";"Larva";308;1
"Unit";"Zergling";"Larva";308;1
"Unit";"Hydralisk";"Larva";294;2
"Unit";"Hydralisk";"Larva";294;2
"Unit";"Hydralisk";"Larva";294;2
"Unit";"Zergling";"Larva";308;1
"Unit";"Zergling";"Larva";308;1
"Unit";"Zergling";"Larva";308;1
"Unit";"Zergling";"Larva";308;1
"Unit";"Zergling";"Larva";308;1
"Unit";"Zergling";"Larva";308;1
"Building";"CreepTumor";NA;326;0
"Building";"CreepTumor";NA;320;0
"Building";"CreepTumor";NA;326;0
"Building";"CreepTumor";NA;326;0
"Building";"CreepTumor";NA;326;0
"Building";"CreepTumorQueen";NA;348;0
"Building";"CreepTumorQueen";NA;348;0
"Building";"CreepTumor";NA;354;0
"Building";"CreepTumor";NA;354;0
"Building";"CreepTumorQueen";NA;354;0
"Building";"CreepTumor";NA;354;0
"Building";"EvolutionChamber";NA;354;0
"Building";"EvolutionChamber";NA;354;0
"Unit";"Queen";"Hatchery";342;2
"Unit";"Queen";"Hatchery";342;2
"Building";"CreepTumor";NA;354;0
"Building";"CreepTumor";NA;354;0
"Building";"CreepTumor";NA;354;0
"Building";"Extractor";NA;354;0
"Building";"CreepTumor";NA;354;0
"Building";"CreepTumor";NA;354;0
"Building";"RoachWarren";NA;354;0
"Unit";"Viper";"Larva";361;3
"Building";"CreepTumor";NA;361;0
"Unit";"Viper";"Larva";361;3
"Building";"CreepTumor";NA;361;0
"Building";"CreepTumor";NA;361;0
"Building";"CreepTumor";NA;361;0
"Building";"CreepTumor";NA;361;0
"Building";"Extractor";NA;361;0
"Building";"Extractor";NA;361;0
"Unit";"Roach";"Larva";373;2
"Unit";"Roach";"Larva";373;2
"Unit";"Roach";"Larva";373;2
"Unit";"Roach";"Larva";373;2
"Unit";"Roach";"Larva";373;2
"Unit";"Roach";"Larva";373;2
"Unit";"Roach";"Larva";373;2
"Unit";"Roach";"Larva";373;2
"Unit";"Roach";"Larva";373;2
"Unit";"Roach";"Larva";373;2
"Unit";"Roach";"Larva";373;2
"Unit";"Roach";"Larva";373;2
"Unit";"Roach";"Larva";373;2
"Unit";"Roach";"Larva";373;2
"Building";"Hatchery";NA;361;0
"Building";"CreepTumor";NA;401;0
"Building";"Hatchery";NA;361;0
"Unit";"Hydralisk";"Larva";401;2
"Unit";"Hydralisk";"Larva";401;2
"Unit";"Hydralisk";"Larva";401;2
"Unit";"Hydralisk";"Larva";401;2
"Unit";"Hydralisk";"Larva";401;2
"Building";"CreepTumor";NA;411;0
