"type";"unit_name";"on_building";"total_supply";"supply"
"Unit";"Overlord";"Larva";13;0
"Building";"Extractor";NA;17;0
"Building";"SpawningPool";NA;17;0
"Building";"Hatchery";NA;16;0
"Unit";"Zergling";"Larva";23;1
"Unit";"Zergling";"Larva";23;1
"Unit";"Queen";"Hatchery";22;2
"Unit";"Zergling";"Larva";23;1
"Unit";"Zergling";"Larva";23;1
"Unit";"Queen";"Hatchery";23;2
"Unit";"Overlord";"Larva";25;0
"Unit";"Overlord";"Larva";33;0
"Unit";"Queen";"Hatchery";33;2
"Building";"CreepTumorQueen";NA;41;0
"Unit";"Overlord";"Larva";49;0
"Unit";"Overlord";"Larva";49;0
"Unit";"Queen";"Hatchery";49;2
"Unit";"Zergling";"Larva";49;1
"Unit";"Zergling";"Larva";49;1
"Unit";"Zergling";"Larva";49;1
"Unit";"Zergling";"Larva";49;1
"Unit";"Zergling";"Larva";49;1
"Unit";"Zergling";"Larva";49;1
"Unit";"Zergling";"Larva";49;1
"Unit";"Zergling";"Larva";49;1
"Building";"CreepTumor";NA;49;0
"Unit";"Zergling";"Larva";49;1
"Unit";"Zergling";"Larva";49;1
"Unit";"Zergling";"Larva";49;1
"Unit";"Zergling";"Larva";49;1
"Building";"BanelingNest";NA;49;0
"Building";"CreepTumorQueen";NA;49;0
"Building";"Hatchery";NA;39;0
"Unit";"Overlord";"Larva";49;0
"Unit";"Overlord";"Larva";49;0
"Unit";"Queen";"Hatchery";49;2
"Building";"Extractor";NA;49;0
"Building";"CreepTumorQueen";NA;63;0
"Unit";"Baneling";"Zergling";65;0
"Unit";"Baneling";"Zergling";65;0
"Unit";"Baneling";"Zergling";65;0
"Unit";"Baneling";"Zergling";65;0
"Unit";"Baneling";"Zergling";65;0
"Unit";"Baneling";"Zergling";65;0
"Unit";"Queen";"Hatchery";63;2
"Building";"CreepTumorQueen";NA;77;0
"Building";"CreepTumor";NA;77;0
"Building";"CreepTumor";NA;77;0
"Building";"CreepTumorQueen";NA;79;0
"Building";"CreepTumorQueen";NA;79;0
"Building";"Extractor";NA;77;0
"Unit";"Queen";"Hatchery";71;2
"Building";"EvolutionChamber";NA;77;0
"Building";"EvolutionChamber";NA;79;0
"Building";"SporeCrawler";NA;79;0
"Building";"SporeCrawler";NA;79;0
"Building";"SporeCrawler";NA;79;0
"Building";"CreepTumor";NA;89;0
"Building";"CreepTumor";NA;89;0
"Building";"CreepTumor";NA;92;0
"Unit";"Overlord";"Larva";92;0
"Unit";"Overlord";"Larva";92;0
"Building";"Extractor";NA;92;0
"Building";"CreepTumor";NA;97;0
"Building";"CreepTumor";NA;97;0
"Unit";"Baneling";"Zergling";97;0
"Unit";"Baneling";"Zergling";97;0
"Unit";"Baneling";"Zergling";97;0
"Unit";"Baneling";"Zergling";97;0
"Unit";"Baneling";"Zergling";97;0
"Building";"HydraliskDen";NA;93;0
"Building";"Extractor";NA;97;0
"Building";"Extractor";NA;97;0
"Building";"CreepTumor";NA;110;0
"Building";"CreepTumor";NA;110;0
"Unit";"Overlord";"Larva";114;0
"Unit";"Overlord";"Larva";114;0
"Unit";"Overlord";"Larva";114;0
"Unit";"Overlord";"Larva";114;0
"Building";"CreepTumorQueen";NA;114;0
"Unit";"Hydralisk";"Larva";114;2
"Unit";"Hydralisk";"Larva";114;2
"Building";"CreepTumorQueen";NA;114;0
"Building";"CreepTumorQueen";NA;114;0
"Unit";"Overlord";"Larva";114;0
"Unit";"Overlord";"Larva";114;0
"Unit";"Hydralisk";"Larva";114;2
"Building";"CreepTumor";NA;118;0
"Building";"CreepTumor";NA;118;0
"Building";"InfestationPit";NA;114;0
"Building";"Hatchery";NA;97;0
"Unit";"Hydralisk";"Larva";118;2
"Unit";"Hydralisk";"Larva";118;2
"Unit";"Hydralisk";"Larva";118;2
"Unit";"Hydralisk";"Larva";118;2
"Unit";"Hydralisk";"Larva";118;2
"Unit";"Hydralisk";"Larva";118;2
"Unit";"Hydralisk";"Larva";118;2
"Building";"Hatchery";NA;98;0
"Unit";"Overlord";"Larva";118;0
"Unit";"Overlord";"Larva";118;0
"Unit";"Overlord";"Larva";118;0
"Unit";"Baneling";"Zergling";118;0
"Unit";"Baneling";"Zergling";118;0
"Unit";"Baneling";"Zergling";118;0
"Unit";"Baneling";"Zergling";120;0
"Building";"CreepTumorQueen";NA;120;0
"Building";"CreepTumorQueen";NA;120;0
"Unit";"Hydralisk";"Larva";118;2
"Unit";"Hydralisk";"Larva";118;2
"Unit";"Hydralisk";"Larva";118;2
"Building";"CreepTumorQueen";NA;120;0
"Upgrade";"ZergMissileWeaponsLevel1";"EvolutionChamber";112;0
"Upgrade";"ZergGroundArmorsLevel1";"EvolutionChamber";112;0
"Building";"CreepTumor";NA;148;0
"Unit";"Overlord";"Larva";144;0
"Unit";"Overlord";"Larva";145;0
"Building";"CreepTumor";NA;148;0
"Building";"Extractor";NA;148;0
"Unit";"Hydralisk";"Larva";148;2
"Building";"Extractor";NA;152;0
"Unit";"Hydralisk";"Larva";149;2
"Unit";"Hydralisk";"Larva";150;2
"Unit";"Hydralisk";"Larva";150;2
"Unit";"Hydralisk";"Larva";150;2
"Unit";"Hydralisk";"Larva";150;2
"Unit";"Zergling";"Larva";152;1
"Unit";"Zergling";"Larva";152;1
"Unit";"Zergling";"Larva";152;1
"Unit";"Zergling";"Larva";152;1
"Unit";"Zergling";"Larva";152;1
"Unit";"Zergling";"Larva";152;1
"Unit";"Zergling";"Larva";152;1
"Unit";"Zergling";"Larva";152;1
"Unit";"Zergling";"Larva";152;1
"Unit";"Zergling";"Larva";152;1
"Unit";"Zergling";"Larva";152;1
"Unit";"Zergling";"Larva";152;1
"Unit";"Zergling";"Larva";152;1
"Unit";"Zergling";"Larva";152;1
"Unit";"Zergling";"Larva";152;1
"Unit";"Zergling";"Larva";152;1
"Unit";"Zergling";"Larva";152;1
"Unit";"Zergling";"Larva";152;1
"Unit";"Zergling";"Larva";152;1
"Unit";"Zergling";"Larva";152;1
"Unit";"Zergling";"Larva";152;1
"Unit";"Zergling";"Larva";152;1
"Unit";"Zergling";"Larva";152;1
"Unit";"Zergling";"Larva";152;1
"Unit";"Zergling";"Larva";152;1
"Unit";"Zergling";"Larva";152;1
"Unit";"Zergling";"Larva";152;1
"Unit";"Zergling";"Larva";152;1
"Unit";"Zergling";"Larva";152;1
"Unit";"Zergling";"Larva";152;1
"Unit";"Queen";"Hatchery";152;2
"Unit";"Overlord";"Larva";179;0
"Building";"CreepTumor";NA;211;0
"Building";"CreepTumor";NA;211;0
"Building";"CreepTumor";NA;211;0
"Building";"CreepTumor";NA;212;0
"Building";"CreepTumorQueen";NA;219;0
"Building";"CreepTumorQueen";NA;219;0
"Upgrade";"EvolveGroovedSpines";"HydraliskDen";211;0
"Building";"CreepTumor";NA;219;0
"Unit";"Hydralisk";"Larva";219;2
"Unit";"Hydralisk";"Larva";219;2
"Unit";"Hydralisk";"Larva";219;2
"Unit";"Hydralisk";"Larva";219;2
"Building";"CreepTumor";NA;220;0
"Unit";"Baneling";"Zergling";220;0
"Unit";"Baneling";"Zergling";220;0
"Building";"CreepTumor";NA;228;0
"Building";"CreepTumor";NA;228;0
"Building";"CreepTumorQueen";NA;228;0
"Unit";"Hydralisk";"Larva";228;2
"Unit";"Hydralisk";"Larva";228;2
"Unit";"Hydralisk";"Larva";228;2
"Unit";"Hydralisk";"Larva";228;2
"Unit";"Hydralisk";"Larva";228;2
"Building";"CreepTumor";NA;228;0
"Building";"CreepTumor";NA;228;0
"Building";"CreepTumorQueen";NA;238;0
"Building";"CreepTumorQueen";NA;238;0
"Unit";"Hydralisk";"Larva";238;2
"Unit";"Hydralisk";"Larva";238;2
"Unit";"Hydralisk";"Larva";238;2
"Unit";"Hydralisk";"Larva";238;2
"Unit";"Hydralisk";"Larva";238;2
"Unit";"Hydralisk";"Larva";238;2
"Unit";"Hydralisk";"Larva";238;2
"Building";"CreepTumor";NA;252;0
"Upgrade";"ZergMissileWeaponsLevel2";"EvolutionChamber";219;0
"Building";"CreepTumor";NA;252;0
"Building";"CreepTumorQueen";NA;252;0
"Building";"CreepTumor";NA;252;0
"Building";"CreepTumor";NA;252;0
"Building";"CreepTumorQueen";NA;252;0
"Building";"CreepTumor";NA;252;0
"Building";"CreepTumor";NA;252;0
"Unit";"Overlord";"Larva";252;0
"Unit";"Overlord";"Larva";252;0
"Unit";"Overlord";"Larva";252;0
"Building";"CreepTumorQueen";NA;252;0
"Unit";"Hydralisk";"Larva";252;2
"Unit";"Hydralisk";"Larva";252;2
"Upgrade";"EvolveMuscularAugments";"HydraliskDen";238;0
"Building";"Hatchery";NA;238;0
"Upgrade";"ZergGroundArmorsLevel2";"EvolutionChamber";228;0
"Unit";"Hydralisk";"Larva";268;2
"Unit";"Hydralisk";"Larva";268;2
"Unit";"Hydralisk";"Larva";268;2
"Unit";"Hydralisk";"Larva";268;2
"Building";"CreepTumor";NA;268;0
"Building";"CreepTumor";NA;268;0
"Building";"CreepTumor";NA;276;0
"Unit";"Hydralisk";"Larva";276;2
"Unit";"Hydralisk";"Larva";276;2
"Unit";"Hydralisk";"Larva";276;2
"Unit";"Hydralisk";"Larva";276;2
"Unit";"Hydralisk";"Larva";276;2
"Unit";"Hydralisk";"Larva";276;2
"Unit";"Hydralisk";"Larva";276;2
"Unit";"Hydralisk";"Larva";276;2
"Unit";"Hydralisk";"Larva";276;2
"Unit";"Hydralisk";"Larva";276;2
"Unit";"Hydralisk";"Larva";276;2
"Unit";"Hydralisk";"Larva";276;2
"Building";"CreepTumor";NA;276;0
"Building";"CreepTumor";NA;276;0
"Unit";"Hydralisk";"Larva";276;2
"Unit";"Hydralisk";"Larva";276;2
"Unit";"Hydralisk";"Larva";276;2
"Unit";"Hydralisk";"Larva";276;2
"Unit";"Hydralisk";"Larva";276;2
"Unit";"Hydralisk";"Larva";276;2
"Unit";"Hydralisk";"Larva";276;2
"Unit";"Hydralisk";"Larva";276;2
"Unit";"Hydralisk";"Larva";276;2
"Unit";"Hydralisk";"Larva";276;2
"Unit";"Hydralisk";"Larva";276;2
"Unit";"Hydralisk";"Larva";276;2
"Unit";"Hydralisk";"Larva";276;2
"Unit";"Hydralisk";"Larva";276;2
"Unit";"Hydralisk";"Larva";276;2
"Building";"CreepTumorQueen";NA;300;0
"Building";"CreepTumorQueen";NA;301;0
"Building";"CreepTumor";NA;337;0
"Building";"CreepTumor";NA;337;0
"Building";"CreepTumorQueen";NA;337;0
"Building";"CreepTumorQueen";NA;337;0
"Building";"CreepTumorQueen";NA;337;0
"Building";"CreepTumorQueen";NA;337;0
"Unit";"Viper";"Larva";337;3
"Building";"CreepTumorQueen";NA;337;0
"Building";"CreepTumor";NA;337;0
"Building";"CreepTumor";NA;337;0
"Building";"CreepTumorQueen";NA;337;0
"Unit";"Hydralisk";"Larva";340;2
"Building";"CreepTumor";NA;340;0
"Unit";"Hydralisk";"Larva";340;2
"Unit";"Hydralisk";"Larva";340;2
"Unit";"Hydralisk";"Larva";340;2
"Unit";"Hydralisk";"Larva";340;2
"Unit";"Hydralisk";"Larva";340;2
"Unit";"Hydralisk";"Larva";340;2
"Unit";"Hydralisk";"Larva";340;2
"Unit";"Hydralisk";"Larva";340;2
"Unit";"Hydralisk";"Larva";340;2
"Unit";"Hydralisk";"Larva";340;2
"Unit";"Hydralisk";"Larva";340;2
"Unit";"Hydralisk";"Larva";340;2
"Unit";"Hydralisk";"Larva";340;2
"Unit";"Hydralisk";"Larva";340;2
"Unit";"Hydralisk";"Larva";340;2
"Unit";"Hydralisk";"Larva";340;2
"Unit";"Hydralisk";"Larva";340;2
"Unit";"Hydralisk";"Larva";340;2
"Unit";"Hydralisk";"Larva";340;2
"Unit";"Hydralisk";"Larva";340;2
"Unit";"Hydralisk";"Larva";340;2
"Unit";"Hydralisk";"Larva";340;2
"Unit";"Hydralisk";"Larva";340;2
"Upgrade";"ZergMissileWeaponsLevel3";"EvolutionChamber";276;0
"Upgrade";"ZergGroundArmorsLevel3";"EvolutionChamber";276;0
"Building";"CreepTumor";NA;388;0
"Building";"CreepTumor";NA;388;0
"Building";"CreepTumor";NA;388;0
"Unit";"Hydralisk";"Larva";388;2
"Unit";"Hydralisk";"Larva";388;2
"Unit";"Hydralisk";"Larva";388;2
"Unit";"Hydralisk";"Larva";388;2
"Unit";"Hydralisk";"Larva";388;2
"Unit";"Hydralisk";"Larva";388;2
"Unit";"Overlord";"Larva";388;0
"Unit";"Hydralisk";"Larva";388;2
"Unit";"Hydralisk";"Larva";388;2
"Unit";"Hydralisk";"Larva";388;2
"Unit";"Hydralisk";"Larva";388;2
"Unit";"Hydralisk";"Larva";388;2
"Unit";"Hydralisk";"Larva";388;2
"Unit";"Overlord";"Larva";388;0
"Unit";"Hydralisk";"Larva";388;2
"Unit";"Overlord";"Larva";388;0
"Unit";"Overlord";"Larva";388;0
"Building";"CreepTumor";NA;388;0
"Building";"CreepTumor";NA;414;0
"Building";"Extractor";NA;414;0
"Building";"Extractor";NA;414;0
"Unit";"Hydralisk";"Larva";414;2
"Unit";"Hydralisk";"Larva";414;2
"Unit";"Hydralisk";"Larva";414;2
"Unit";"Hydralisk";"Larva";414;2
"Unit";"Hydralisk";"Larva";414;2
"Building";"CreepTumor";NA;414;0
"Building";"CreepTumor";NA;424;0
"Building";"Hatchery";NA;414;0
"Building";"CreepTumor";NA;424;0
"Building";"CreepTumor";NA;424;0
"Unit";"Hydralisk";"Larva";424;2
"Unit";"Hydralisk";"Larva";424;2
"Building";"CreepTumor";NA;428;0
"Unit";"Hydralisk";"Larva";428;2
"Unit";"Hydralisk";"Larva";428;2
"Unit";"Hydralisk";"Larva";432;2
"Unit";"Hydralisk";"Larva";432;2
"Unit";"Hydralisk";"Larva";432;2
"Unit";"Hydralisk";"Larva";432;2
"Unit";"Hydralisk";"Larva";432;2
"Unit";"Hydralisk";"Larva";432;2
"Unit";"Hydralisk";"Larva";432;2
"Unit";"Hydralisk";"Larva";432;2
"Unit";"Hydralisk";"Larva";432;2
"Unit";"Hydralisk";"Larva";432;2
"Unit";"Hydralisk";"Larva";432;2
"Unit";"Hydralisk";"Larva";432;2
"Unit";"Hydralisk";"Larva";432;2
"Unit";"Hydralisk";"Larva";432;2
"Unit";"Hydralisk";"Larva";432;2
"Unit";"Hydralisk";"Larva";432;2
"Unit";"Hydralisk";"Larva";432;2
"Unit";"Hydralisk";"Larva";432;2
"Building";"SporeCrawler";NA;460;0
"Building";"SporeCrawler";NA;460;0
"Building";"SporeCrawler";NA;460;0
"Building";"SporeCrawler";NA;460;0
"Building";"CreepTumor";NA;468;0
"Building";"CreepTumor";NA;468;0
"Building";"CreepTumorQueen";NA;468;0
"Building";"CreepTumorQueen";NA;468;0
"Building";"CreepTumorQueen";NA;468;0
"Building";"CreepTumorQueen";NA;468;0
