"type";"unit_name";"on_building";"total_supply";"supply"
"Unit";"Overlord";"Larva";13;0
"Building";"Extractor";NA;18;0
"Unit";"Overlord";"Larva";21;0
"Building";"SpawningPool";NA;19;0
"Building";"Hatchery";NA;17;0
"Unit";"Zergling";"Larva";22;1
"Unit";"Zergling";"Larva";22;1
"Unit";"Zergling";"Larva";22;1
"Unit";"Zergling";"Larva";22;1
"Unit";"Zergling";"Larva";22;1
"Unit";"Zergling";"Larva";22;1
"Unit";"Queen";"Hatchery";22;2
"Unit";"Queen";"Hatchery";22;2
"Building";"CreepTumorQueen";NA;37;0
"Building";"CreepTumor";NA;38;0
"Unit";"Overlord";"Larva";37;0
"Unit";"Overlord";"Larva";37;0
"Unit";"Queen";"Hatchery";37;2
"Building";"CreepTumorQueen";NA;41;0
"Unit";"Overlord";"Larva";43;0
"Building";"Hatchery";NA;33;0
"Unit";"Overlord";"Larva";47;0
"Building";"Extractor";NA;47;0
"Building";"CreepTumorQueen";NA;48;0
"Building";"CreepTumor";NA;48;0
"Building";"CreepTumor";NA;48;0
"Unit";"Queen";"Hatchery";47;2
"Building";"CreepTumorQueen";NA;55;0
"Unit";"Overlord";"Larva";55;0
"Building";"CreepTumor";NA;63;0
"Building";"CreepTumor";NA;63;0
"Unit";"Overlord";"Larva";63;0
"Unit";"Overlord";"Larva";63;0
"Unit";"Queen";"Hatchery";55;2
"Building";"CreepTumor";NA;63;0
"Building";"CreepTumorQueen";NA;63;0
"Unit";"Overlord";"Larva";63;0
"Unit";"Overlord";"Larva";63;0
"Building";"BanelingNest";NA;57;0
"Building";"EvolutionChamber";NA;63;0
"Building";"EvolutionChamber";NA;63;0
"Unit";"Queen";"Hatchery";63;2
"Unit";"Zergling";"Larva";67;1
"Unit";"Zergling";"Larva";67;1
"Unit";"Zergling";"Larva";67;1
"Unit";"Zergling";"Larva";67;1
"Unit";"Zergling";"Larva";67;1
"Unit";"Zergling";"Larva";67;1
"Unit";"Zergling";"Larva";67;1
"Unit";"Zergling";"Larva";67;1
"Unit";"Zergling";"Larva";67;1
"Unit";"Zergling";"Larva";67;1
"Unit";"Zergling";"Larva";67;1
"Unit";"Zergling";"Larva";67;1
"Unit";"Zergling";"Larva";67;1
"Unit";"Zergling";"Larva";67;1
"Building";"CreepTumor";NA;71;0
"Building";"CreepTumor";NA;71;0
"Building";"CreepTumor";NA;71;0
"Building";"CreepTumor";NA;71;0
"Building";"CreepTumorQueen";NA;90;0
"Unit";"Zergling";"Larva";79;1
"Unit";"Zergling";"Larva";79;1
"Unit";"Zergling";"Larva";87;1
"Unit";"Zergling";"Larva";87;1
"Unit";"Zergling";"Larva";87;1
"Unit";"Zergling";"Larva";87;1
"Unit";"Zergling";"Larva";90;1
"Unit";"Zergling";"Larva";90;1
"Unit";"Zergling";"Larva";90;1
"Unit";"Zergling";"Larva";90;1
"Unit";"Zergling";"Larva";90;1
"Unit";"Zergling";"Larva";90;1
"Unit";"Zergling";"Larva";90;1
"Unit";"Zergling";"Larva";90;1
"Unit";"Zergling";"Larva";90;1
"Unit";"Zergling";"Larva";90;1
"Unit";"Zergling";"Larva";90;1
"Unit";"Zergling";"Larva";90;1
"Unit";"Zergling";"Larva";90;1
"Unit";"Zergling";"Larva";90;1
"Unit";"Zergling";"Larva";90;1
"Unit";"Zergling";"Larva";90;1
"Unit";"Baneling";"Zergling";96;0
"Unit";"Baneling";"Zergling";96;0
"Unit";"Zergling";"Larva";96;1
"Unit";"Zergling";"Larva";96;1
"Building";"CreepTumorQueen";NA;112;0
"Building";"CreepTumorQueen";NA;112;0
"Building";"CreepTumorQueen";NA;112;0
"Building";"SporeCrawler";NA;96;0
"Building";"CreepTumor";NA;112;0
"Unit";"Overlord";"Larva";114;0
"Building";"CreepTumorQueen";NA;114;0
"Unit";"Overlord";"Larva";114;0
"Unit";"Overlord";"Larva";124;0
"Unit";"Zergling";"Larva";124;1
"Unit";"Zergling";"Larva";124;1
"Unit";"Zergling";"Larva";124;1
"Unit";"Zergling";"Larva";124;1
"Unit";"Zergling";"Larva";124;1
"Unit";"Zergling";"Larva";124;1
"Unit";"Zergling";"Larva";124;1
"Unit";"Zergling";"Larva";124;1
"Unit";"Zergling";"Larva";124;1
"Unit";"Zergling";"Larva";124;1
"Unit";"Zergling";"Larva";124;1
"Unit";"Zergling";"Larva";124;1
"Unit";"Zergling";"Larva";124;1
"Unit";"Zergling";"Larva";124;1
"Unit";"Zergling";"Larva";124;1
"Unit";"Zergling";"Larva";124;1
"Unit";"Zergling";"Larva";124;1
"Unit";"Zergling";"Larva";124;1
"Unit";"Zergling";"Larva";124;1
"Unit";"Zergling";"Larva";124;1
"Unit";"Zergling";"Larva";124;1
"Unit";"Zergling";"Larva";124;1
"Unit";"Zergling";"Larva";124;1
"Unit";"Zergling";"Larva";124;1
"Building";"SpineCrawler";NA;124;0
"Building";"SpineCrawler";NA;124;0
"Building";"CreepTumor";NA;124;0
"Building";"CreepTumor";NA;124;0
"Building";"CreepTumorQueen";NA;124;0
"Building";"CreepTumor";NA;124;0
"Building";"CreepTumor";NA;124;0
"Building";"Extractor";NA;124;0
"Upgrade";"ZergMeleeWeaponsLevel1";"EvolutionChamber";114;0
"Building";"InfestationPit";NA;124;0
"Building";"CreepTumorQueen";NA;148;0
"Unit";"Zergling";"Larva";148;1
"Unit";"Zergling";"Larva";148;1
"Unit";"Zergling";"Larva";148;1
"Unit";"Zergling";"Larva";148;1
"Unit";"Zergling";"Larva";148;1
"Unit";"Zergling";"Larva";148;1
"Unit";"Zergling";"Larva";148;1
"Unit";"Zergling";"Larva";148;1
"Unit";"Zergling";"Larva";148;1
"Unit";"Zergling";"Larva";148;1
"Unit";"Zergling";"Larva";148;1
"Unit";"Zergling";"Larva";148;1
"Unit";"Zergling";"Larva";148;1
"Unit";"Zergling";"Larva";148;1
"Unit";"Zergling";"Larva";148;1
"Unit";"Zergling";"Larva";148;1
"Unit";"Zergling";"Larva";148;1
"Unit";"Zergling";"Larva";148;1
"Unit";"Zergling";"Larva";148;1
"Unit";"Zergling";"Larva";148;1
"Unit";"Overlord";"Larva";148;0
"Unit";"Overlord";"Larva";148;0
"Unit";"Baneling";"Zergling";148;0
"Unit";"Overlord";"Larva";148;0
"Unit";"Overlord";"Larva";148;0
"Unit";"Baneling";"Zergling";148;0
"Unit";"Baneling";"Zergling";148;0
"Unit";"Baneling";"Zergling";148;0
"Unit";"Baneling";"Zergling";148;0
"Building";"Hatchery";NA;124;0
"Building";"CreepTumor";NA;148;0
"Upgrade";"ZergGroundArmorsLevel1";"EvolutionChamber";124;0
"Unit";"Baneling";"Zergling";168;0
"Unit";"Baneling";"Zergling";168;0
"Unit";"Baneling";"Zergling";168;0
"Unit";"Baneling";"Zergling";168;0
"Unit";"Baneling";"Zergling";168;0
"Unit";"Baneling";"Zergling";168;0
"Unit";"Baneling";"Zergling";168;0
"Unit";"Baneling";"Zergling";168;0
"Unit";"Baneling";"Zergling";168;0
"Unit";"Baneling";"Zergling";168;0
"Unit";"Baneling";"Zergling";168;0
"Unit";"Baneling";"Zergling";168;0
"Unit";"Baneling";"Zergling";168;0
"Unit";"Baneling";"Zergling";168;0
"Unit";"Zergling";"Larva";168;1
"Unit";"Zergling";"Larva";168;1
"Unit";"Zergling";"Larva";168;1
"Unit";"Zergling";"Larva";168;1
"Unit";"Zergling";"Larva";168;1
"Unit";"Zergling";"Larva";168;1
"Unit";"Zergling";"Larva";168;1
"Unit";"Zergling";"Larva";168;1
"Unit";"Zergling";"Larva";168;1
"Unit";"Zergling";"Larva";168;1
"Unit";"Zergling";"Larva";168;1
"Unit";"Zergling";"Larva";168;1
"Unit";"Zergling";"Larva";168;1
"Unit";"Zergling";"Larva";168;1
"Building";"Hatchery";NA;124;0
"Building";"CreepTumorQueen";NA;168;0
"Building";"CreepTumor";NA;182;0
"Building";"CreepTumor";NA;182;0
"Building";"CreepTumor";NA;182;0
"Building";"CreepTumor";NA;182;0
"Unit";"Overlord";"Larva";168;0
"Building";"Hatchery";NA;124;0
"Building";"CreepTumor";NA;182;0
"Unit";"Overlord";"Larva";182;0
"Unit";"Overlord";"Larva";182;0
"Unit";"Overlord";"Larva";182;0
"Building";"CreepTumor";NA;182;0
"Building";"CreepTumor";NA;182;0
"Building";"CreepTumor";NA;182;0
"Building";"CreepTumor";NA;182;0
"Building";"CreepTumor";NA;182;0
"Building";"CreepTumorQueen";NA;182;0
"Building";"CreepTumorQueen";NA;182;0
"Unit";"Zergling";"Larva";182;1
"Unit";"Zergling";"Larva";182;1
"Unit";"Overlord";"Larva";182;0
"Unit";"Zergling";"Larva";182;1
"Unit";"Zergling";"Larva";182;1
"Unit";"Zergling";"Larva";182;1
"Unit";"Zergling";"Larva";182;1
"Unit";"Zergling";"Larva";182;1
"Unit";"Zergling";"Larva";182;1
"Unit";"Zergling";"Larva";182;1
"Unit";"Zergling";"Larva";182;1
"Unit";"Zergling";"Larva";182;1
"Unit";"Zergling";"Larva";182;1
"Unit";"Zergling";"Larva";182;1
"Unit";"Zergling";"Larva";182;1
"Unit";"Zergling";"Larva";182;1
"Unit";"Zergling";"Larva";182;1
"Unit";"Zergling";"Larva";182;1
"Unit";"Zergling";"Larva";182;1
"Unit";"Zergling";"Larva";182;1
"Unit";"Zergling";"Larva";182;1
"Unit";"Zergling";"Larva";182;1
"Unit";"Zergling";"Larva";182;1
"Unit";"Zergling";"Larva";182;1
"Unit";"Zergling";"Larva";182;1
"Unit";"Zergling";"Larva";182;1
"Unit";"Zergling";"Larva";182;1
"Unit";"Zergling";"Larva";182;1
"Unit";"Zergling";"Larva";182;1
"Unit";"Zergling";"Larva";182;1
"Unit";"Zergling";"Larva";182;1
"Unit";"Zergling";"Larva";182;1
"Unit";"Zergling";"Larva";182;1
"Unit";"Zergling";"Larva";182;1
"Unit";"Zergling";"Larva";182;1
"Unit";"Zergling";"Larva";182;1
"Unit";"Zergling";"Larva";182;1
"Unit";"Zergling";"Larva";182;1
"Unit";"Zergling";"Larva";182;1
"Unit";"Zergling";"Larva";182;1
"Unit";"Zergling";"Larva";182;1
"Unit";"Zergling";"Larva";182;1
"Unit";"Zergling";"Larva";182;1
"Unit";"Zergling";"Larva";182;1
"Unit";"Zergling";"Larva";182;1
"Building";"CreepTumor";NA;186;0
"Building";"CreepTumor";NA;186;0
"Building";"Hatchery";NA;182;0
