"type";"unit_name";"on_building";"total_supply";"supply"
"Unit";"Overlord";"Larva";12;0
"Building";"Extractor";NA;18;0
"Unit";"Overlord";"Larva";21;0
"Building";"SpawningPool";NA;19;0
"Building";"Hatchery";NA;17;0
"Unit";"Zergling";"Larva";22;1
"Unit";"Zergling";"Larva";22;1
"Unit";"Zergling";"Larva";23;1
"Unit";"Zergling";"Larva";23;1
"Unit";"Queen";"Hatchery";23;2
"Unit";"Queen";"Hatchery";23;2
"Unit";"Overlord";"Larva";35;0
"Unit";"Queen";"Hatchery";35;2
"Building";"CreepTumorQueen";NA;40;0
"Building";"CreepTumorQueen";NA;43;0
"Unit";"Queen";"Hatchery";38;2
"Unit";"Overlord";"Larva";43;0
"Building";"Hatchery";NA;30;0
"Unit";"Queen";"Hatchery";40;2
"Building";"Extractor";NA;49;0
"Building";"RoachWarren";NA;46;0
"Unit";"Zergling";"Larva";55;1
"Unit";"Zergling";"Larva";55;1
"Unit";"Zergling";"Larva";55;1
"Unit";"Zergling";"Larva";55;1
"Unit";"Zergling";"Larva";55;1
"Unit";"Zergling";"Larva";55;1
"Unit";"Zergling";"Larva";55;1
"Unit";"Zergling";"Larva";55;1
"Unit";"Queen";"Hatchery";49;2
"Building";"CreepTumor";NA;60;0
"Building";"CreepTumorQueen";NA;60;0
"Building";"CreepTumorQueen";NA;60;0
"Building";"EvolutionChamber";NA;60;0
"Unit";"Overlord";"Larva";68;0
"Unit";"Overlord";"Larva";68;0
"Unit";"Overlord";"Larva";70;0
"Building";"CreepTumor";NA;83;0
"Building";"CreepTumor";NA;83;0
"Building";"CreepTumorQueen";NA;83;0
"Building";"CreepTumorQueen";NA;84;0
"Building";"BanelingNest";NA;80;0
"Building";"Extractor";NA;84;0
"Building";"Extractor";NA;84;0
"Unit";"Overlord";"Larva";92;0
"Building";"Extractor";NA;87;0
"Building";"HydraliskDen";NA;84;0
"Building";"EvolutionChamber";NA;90;0
"Building";"CreepTumor";NA;99;0
"Building";"CreepTumor";NA;99;0
"Building";"CreepTumor";NA;99;0
"Unit";"Overlord";"Larva";99;0
"Unit";"Overlord";"Larva";99;0
"Unit";"Overlord";"Larva";99;0
"Unit";"Overlord";"Larva";99;0
"Unit";"Overlord";"Larva";99;0
"Building";"Hatchery";NA;84;0
"Upgrade";"ZergMeleeWeaponsLevel1";"EvolutionChamber";84;0
"Building";"Extractor";NA;103;0
"Unit";"Hydralisk";"Larva";103;2
"Unit";"Hydralisk";"Larva";103;2
"Unit";"Hydralisk";"Larva";103;2
"Unit";"Hydralisk";"Larva";103;2
"Building";"CreepTumorQueen";NA;114;0
"Unit";"Zergling";"Larva";113;1
"Unit";"Zergling";"Larva";113;1
"Unit";"Zergling";"Larva";113;1
"Unit";"Zergling";"Larva";113;1
"Unit";"Zergling";"Larva";113;1
"Unit";"Zergling";"Larva";113;1
"Unit";"Zergling";"Larva";113;1
"Unit";"Zergling";"Larva";113;1
"Building";"CreepTumor";NA;114;0
"Building";"CreepTumor";NA;114;0
"Unit";"Zergling";"Larva";113;1
"Unit";"Zergling";"Larva";113;1
"Building";"CreepTumor";NA;114;0
"Building";"CreepTumorQueen";NA;114;0
"Unit";"Zergling";"Larva";113;1
"Unit";"Zergling";"Larva";113;1
"Building";"CreepTumorQueen";NA;114;0
"Unit";"Zergling";"Larva";113;1
"Unit";"Zergling";"Larva";113;1
"Building";"CreepTumorQueen";NA;122;0
"Unit";"Zergling";"Larva";114;1
"Unit";"Zergling";"Larva";114;1
"Unit";"Zergling";"Larva";114;1
"Unit";"Zergling";"Larva";114;1
"Unit";"Zergling";"Larva";114;1
"Unit";"Zergling";"Larva";114;1
"Building";"CreepTumorQueen";NA;122;0
"Unit";"Zergling";"Larva";114;1
"Unit";"Zergling";"Larva";114;1
"Unit";"Zergling";"Larva";114;1
"Unit";"Zergling";"Larva";114;1
"Unit";"Zergling";"Larva";114;1
"Unit";"Zergling";"Larva";114;1
"Building";"CreepTumorQueen";NA;122;0
"Building";"CreepTumorQueen";NA;136;0
"Unit";"Overlord";"Larva";122;0
"Building";"Hatchery";NA;99;0
"Upgrade";"EvolveGroovedSpines";"HydraliskDen";103;0
"Unit";"Overlord";"Larva";152;0
"Unit";"Overlord";"Larva";152;0
"Building";"Extractor";NA;152;0
"Unit";"Baneling";"Zergling";152;0
"Building";"Extractor";NA;152;0
"Building";"CreepTumor";NA;152;0
"Building";"CreepTumor";NA;152;0
"Unit";"Baneling";"Zergling";152;0
"Building";"CreepTumor";NA;152;0
"Unit";"Baneling";"Zergling";152;0
"Unit";"Baneling";"Zergling";152;0
"Unit";"Baneling";"Zergling";152;0
"Unit";"Baneling";"Zergling";152;0
"Unit";"Baneling";"Zergling";152;0
"Unit";"Baneling";"Zergling";152;0
"Building";"CreepTumor";NA;153;0
"Unit";"Zergling";"Larva";152;1
"Unit";"Zergling";"Larva";152;1
"Unit";"Zergling";"Larva";152;1
"Unit";"Zergling";"Larva";152;1
"Unit";"Zergling";"Larva";152;1
"Unit";"Zergling";"Larva";152;1
"Unit";"Zergling";"Larva";152;1
"Unit";"Zergling";"Larva";152;1
"Unit";"Zergling";"Larva";152;1
"Unit";"Zergling";"Larva";152;1
"Unit";"Zergling";"Larva";152;1
"Unit";"Zergling";"Larva";152;1
"Unit";"Zergling";"Larva";152;1
"Unit";"Zergling";"Larva";152;1
"Unit";"Zergling";"Larva";152;1
"Unit";"Zergling";"Larva";152;1
"Unit";"Zergling";"Larva";152;1
"Unit";"Zergling";"Larva";152;1
"Unit";"Zergling";"Larva";152;1
"Unit";"Zergling";"Larva";152;1
"Unit";"Zergling";"Larva";152;1
"Unit";"Zergling";"Larva";152;1
"Unit";"Zergling";"Larva";152;1
"Unit";"Zergling";"Larva";152;1
"Unit";"Zergling";"Larva";152;1
"Unit";"Zergling";"Larva";152;1
"Unit";"Zergling";"Larva";152;1
"Unit";"Zergling";"Larva";152;1
"Unit";"Zergling";"Larva";152;1
"Unit";"Zergling";"Larva";152;1
"Building";"CreepTumor";NA;157;0
"Building";"CreepTumor";NA;157;0
"Building";"CreepTumor";NA;157;0
"Building";"CreepTumor";NA;157;0
"Building";"CreepTumor";NA;157;0
"Building";"CreepTumor";NA;157;0
"Unit";"Zergling";"Larva";157;1
"Unit";"Zergling";"Larva";157;1
"Unit";"Zergling";"Larva";157;1
"Unit";"Zergling";"Larva";157;1
"Unit";"Zergling";"Larva";157;1
"Unit";"Zergling";"Larva";157;1
"Building";"InfestationPit";NA;152;0
"Unit";"Hydralisk";"Larva";187;2
"Unit";"Hydralisk";"Larva";187;2
"Unit";"Hydralisk";"Larva";187;2
"Unit";"Hydralisk";"Larva";187;2
"Unit";"Hydralisk";"Larva";187;2
"Unit";"Hydralisk";"Larva";187;2
"Unit";"Hydralisk";"Larva";187;2
"Unit";"Hydralisk";"Larva";187;2
"Building";"Hatchery";NA;146;0
"Unit";"Overlord";"Larva";193;0
"Unit";"Overlord";"Larva";193;0
"Unit";"Zergling";"Larva";205;1
"Unit";"Zergling";"Larva";205;1
"Unit";"Zergling";"Larva";207;1
"Unit";"Zergling";"Larva";207;1
"Upgrade";"EvolveMuscularAugments";"HydraliskDen";157;0
"Unit";"Zergling";"Larva";223;1
"Unit";"Zergling";"Larva";223;1
"Unit";"Zergling";"Larva";223;1
"Unit";"Zergling";"Larva";223;1
"Unit";"Zergling";"Larva";223;1
"Unit";"Zergling";"Larva";223;1
"Unit";"Zergling";"Larva";223;1
"Unit";"Zergling";"Larva";223;1
"Unit";"Zergling";"Larva";223;1
"Unit";"Zergling";"Larva";223;1
"Unit";"Zergling";"Larva";223;1
"Unit";"Zergling";"Larva";223;1
"Unit";"Zergling";"Larva";223;1
"Unit";"Zergling";"Larva";223;1
"Unit";"Zergling";"Larva";223;1
"Unit";"Zergling";"Larva";223;1
"Unit";"Zergling";"Larva";223;1
"Unit";"Zergling";"Larva";223;1
"Unit";"Zergling";"Larva";223;1
"Unit";"Zergling";"Larva";223;1
"Unit";"Zergling";"Larva";223;1
"Unit";"Zergling";"Larva";223;1
"Unit";"Zergling";"Larva";223;1
"Unit";"Zergling";"Larva";223;1
"Unit";"Zergling";"Larva";223;1
"Unit";"Zergling";"Larva";223;1
"Unit";"Zergling";"Larva";227;1
"Unit";"Zergling";"Larva";227;1
"Unit";"Zergling";"Larva";227;1
"Unit";"Zergling";"Larva";227;1
"Upgrade";"ZergGroundArmorsLevel1";"EvolutionChamber";157;0
"Unit";"Zergling";"Larva";237;1
"Unit";"Zergling";"Larva";237;1
"Unit";"Zergling";"Larva";237;1
"Unit";"Zergling";"Larva";237;1
"Unit";"Zergling";"Larva";237;1
"Unit";"Zergling";"Larva";237;1
"Unit";"Zergling";"Larva";237;1
"Unit";"Zergling";"Larva";237;1
"Unit";"Zergling";"Larva";237;1
"Unit";"Zergling";"Larva";237;1
"Unit";"Zergling";"Larva";237;1
"Unit";"Zergling";"Larva";237;1
"Unit";"Zergling";"Larva";237;1
"Unit";"Zergling";"Larva";237;1
"Unit";"Zergling";"Larva";237;1
"Unit";"Zergling";"Larva";237;1
"Unit";"Zergling";"Larva";253;1
"Unit";"Zergling";"Larva";253;1
"Unit";"Zergling";"Larva";253;1
"Unit";"Zergling";"Larva";253;1
"Unit";"Zergling";"Larva";253;1
"Unit";"Zergling";"Larva";253;1
"Building";"Extractor";NA;237;0
"Building";"Extractor";NA;237;0
"Upgrade";"ZergMeleeWeaponsLevel2";"EvolutionChamber";157;0
"Building";"SporeCrawler";NA;280;0
"Building";"SporeCrawler";NA;284;0
"Building";"SporeCrawler";NA;286;0
"Unit";"Zergling";"Larva";289;1
"Unit";"Zergling";"Larva";289;1
"Unit";"Zergling";"Larva";290;1
"Unit";"Zergling";"Larva";290;1
"Unit";"Zergling";"Larva";290;1
"Unit";"Zergling";"Larva";290;1
"Unit";"Zergling";"Larva";290;1
"Unit";"Zergling";"Larva";290;1
"Unit";"Zergling";"Larva";290;1
"Unit";"Zergling";"Larva";290;1
"Unit";"Zergling";"Larva";290;1
"Unit";"Zergling";"Larva";290;1
"Unit";"Overlord";"Larva";290;0
"Unit";"Overlord";"Larva";290;0
"Unit";"Overlord";"Larva";290;0
"Unit";"Overlord";"Larva";290;0
"Unit";"Overlord";"Larva";290;0
"Unit";"Baneling";"Zergling";305;0
"Unit";"Zergling";"Larva";305;1
"Unit";"Zergling";"Larva";305;1
"Unit";"Baneling";"Zergling";305;0
"Unit";"Baneling";"Zergling";305;0
"Unit";"Baneling";"Zergling";305;0
"Unit";"Zergling";"Larva";305;1
"Unit";"Zergling";"Larva";305;1
"Unit";"Baneling";"Zergling";305;0
"Unit";"Baneling";"Zergling";305;0
"Unit";"Zergling";"Larva";305;1
"Unit";"Zergling";"Larva";305;1
"Unit";"Zergling";"Larva";305;1
"Unit";"Zergling";"Larva";305;1
"Unit";"Baneling";"Zergling";305;0
"Unit";"Baneling";"Zergling";305;0
"Unit";"Zergling";"Larva";305;1
"Unit";"Zergling";"Larva";305;1
"Unit";"Zergling";"Larva";305;1
"Unit";"Zergling";"Larva";305;1
"Unit";"Baneling";"Zergling";305;0
"Unit";"Zergling";"Larva";305;1
"Unit";"Zergling";"Larva";305;1
"Unit";"Zergling";"Larva";305;1
"Unit";"Zergling";"Larva";305;1
"Unit";"Zergling";"Larva";305;1
"Unit";"Zergling";"Larva";305;1
"Unit";"Zergling";"Larva";305;1
"Unit";"Zergling";"Larva";305;1
"Unit";"Zergling";"Larva";305;1
"Unit";"Zergling";"Larva";305;1
"Unit";"Zergling";"Larva";305;1
"Unit";"Zergling";"Larva";305;1
"Unit";"Zergling";"Larva";305;1
"Unit";"Zergling";"Larva";305;1
"Unit";"Zergling";"Larva";305;1
"Unit";"Zergling";"Larva";305;1
"Unit";"Zergling";"Larva";305;1
"Unit";"Zergling";"Larva";305;1
"Unit";"Zergling";"Larva";305;1
"Unit";"Zergling";"Larva";305;1
"Unit";"Zergling";"Larva";305;1
"Unit";"Zergling";"Larva";305;1
"Unit";"Zergling";"Larva";305;1
"Unit";"Zergling";"Larva";305;1
"Unit";"Zergling";"Larva";305;1
"Unit";"Zergling";"Larva";305;1
"Unit";"Zergling";"Larva";305;1
"Unit";"Zergling";"Larva";305;1
"Unit";"Zergling";"Larva";305;1
"Unit";"Zergling";"Larva";305;1
"Unit";"Baneling";"Zergling";305;0
"Unit";"Baneling";"Zergling";305;0
"Unit";"Baneling";"Zergling";305;0
"Unit";"Baneling";"Zergling";305;0
"Unit";"Baneling";"Zergling";305;0
"Unit";"Baneling";"Zergling";305;0
"Unit";"Baneling";"Zergling";305;0
"Unit";"Baneling";"Zergling";305;0
"Unit";"Baneling";"Zergling";305;0
"Unit";"Baneling";"Zergling";305;0
"Unit";"Baneling";"Zergling";305;0
"Unit";"Baneling";"Zergling";305;0
"Unit";"Baneling";"Zergling";305;0
"Unit";"Baneling";"Zergling";305;0
"Unit";"Baneling";"Zergling";305;0
"Unit";"Baneling";"Zergling";305;0
"Unit";"Baneling";"Zergling";305;0
"Unit";"Baneling";"Zergling";305;0
"Unit";"Baneling";"Zergling";305;0
"Unit";"Baneling";"Zergling";305;0
"Unit";"Baneling";"Zergling";305;0
"Unit";"Baneling";"Zergling";305;0
"Unit";"Baneling";"Zergling";305;0
"Unit";"Baneling";"Zergling";305;0
"Unit";"Zergling";"Larva";305;1
"Unit";"Zergling";"Larva";305;1
"Unit";"Zergling";"Larva";305;1
"Unit";"Zergling";"Larva";305;1
"Unit";"Zergling";"Larva";305;1
"Unit";"Zergling";"Larva";305;1
"Unit";"Zergling";"Larva";305;1
"Unit";"Zergling";"Larva";305;1
"Building";"CreepTumorQueen";NA;347;0
"Building";"CreepTumorQueen";NA;347;0
"Building";"CreepTumorQueen";NA;347;0
"Building";"CreepTumorQueen";NA;347;0
"Building";"CreepTumorQueen";NA;355;0
"Building";"CreepTumorQueen";NA;355;0
"Building";"CreepTumorQueen";NA;355;0
"Building";"CreepTumorQueen";NA;355;0
"Building";"CreepTumorQueen";NA;355;0
"Building";"CreepTumorQueen";NA;355;0
"Building";"CreepTumorQueen";NA;355;0
"Building";"CreepTumorQueen";NA;355;0
"Building";"CreepTumorQueen";NA;355;0
"Unit";"Zergling";"Larva";355;1
"Unit";"Zergling";"Larva";355;1
"Unit";"Zergling";"Larva";355;1
"Unit";"Zergling";"Larva";355;1
"Unit";"Zergling";"Larva";355;1
"Unit";"Zergling";"Larva";355;1
"Unit";"Zergling";"Larva";355;1
"Unit";"Zergling";"Larva";355;1
"Unit";"Zergling";"Larva";355;1
"Unit";"Zergling";"Larva";355;1
"Unit";"Zergling";"Larva";355;1
"Unit";"Zergling";"Larva";355;1
"Unit";"Zergling";"Larva";355;1
"Unit";"Zergling";"Larva";355;1
"Unit";"Zergling";"Larva";355;1
"Unit";"Zergling";"Larva";355;1
"Unit";"Zergling";"Larva";355;1
"Unit";"Zergling";"Larva";355;1
"Unit";"Zergling";"Larva";355;1
"Unit";"Zergling";"Larva";355;1
"Unit";"Zergling";"Larva";355;1
"Unit";"Zergling";"Larva";355;1
"Unit";"Zergling";"Larva";355;1
"Unit";"Zergling";"Larva";355;1
"Unit";"Zergling";"Larva";355;1
"Unit";"Zergling";"Larva";355;1
"Unit";"Zergling";"Larva";355;1
"Unit";"Zergling";"Larva";355;1
"Unit";"Zergling";"Larva";355;1
"Unit";"Zergling";"Larva";355;1
"Unit";"Zergling";"Larva";355;1
"Unit";"Zergling";"Larva";355;1
"Unit";"Zergling";"Larva";355;1
"Unit";"Zergling";"Larva";355;1
"Unit";"Zergling";"Larva";355;1
"Unit";"Zergling";"Larva";355;1
"Unit";"Zergling";"Larva";355;1
"Unit";"Zergling";"Larva";355;1
"Unit";"Zergling";"Larva";355;1
"Unit";"Zergling";"Larva";355;1
"Unit";"Zergling";"Larva";355;1
"Unit";"Zergling";"Larva";355;1
"Unit";"Zergling";"Larva";355;1
"Unit";"Zergling";"Larva";355;1
"Unit";"Zergling";"Larva";355;1
"Unit";"Zergling";"Larva";355;1
"Unit";"Zergling";"Larva";355;1
"Unit";"Zergling";"Larva";355;1
"Unit";"Zergling";"Larva";355;1
"Unit";"Zergling";"Larva";355;1
"Unit";"Zergling";"Larva";355;1
"Unit";"Zergling";"Larva";355;1
"Unit";"Zergling";"Larva";355;1
"Unit";"Zergling";"Larva";355;1
"Unit";"Zergling";"Larva";355;1
"Unit";"Zergling";"Larva";355;1
"Unit";"Zergling";"Larva";355;1
"Unit";"Zergling";"Larva";355;1
"Unit";"Zergling";"Larva";355;1
"Unit";"Zergling";"Larva";355;1
"Unit";"Zergling";"Larva";355;1
"Unit";"Zergling";"Larva";355;1
"Unit";"Zergling";"Larva";355;1
"Unit";"Zergling";"Larva";355;1
"Building";"CreepTumor";NA;355;0
"Building";"CreepTumor";NA;355;0
"Building";"CreepTumor";NA;355;0
"Building";"CreepTumor";NA;355;0
"Building";"CreepTumor";NA;355;0
"Building";"CreepTumor";NA;355;0
"Unit";"Zergling";"Larva";355;1
"Unit";"Zergling";"Larva";355;1
"Unit";"Zergling";"Larva";355;1
"Unit";"Zergling";"Larva";355;1
"Unit";"Zergling";"Larva";355;1
"Unit";"Zergling";"Larva";355;1
"Unit";"Zergling";"Larva";355;1
"Unit";"Zergling";"Larva";355;1
"Unit";"Zergling";"Larva";355;1
"Unit";"Zergling";"Larva";355;1
"Unit";"Zergling";"Larva";355;1
"Unit";"Zergling";"Larva";355;1
"Unit";"Zergling";"Larva";413;1
"Unit";"Zergling";"Larva";413;1
"Unit";"Zergling";"Larva";413;1
"Unit";"Zergling";"Larva";413;1
"Unit";"Zergling";"Larva";413;1
"Unit";"Zergling";"Larva";413;1
"Unit";"Zergling";"Larva";419;1
"Unit";"Zergling";"Larva";419;1
"Unit";"Zergling";"Larva";419;1
"Unit";"Zergling";"Larva";419;1
"Unit";"Hydralisk";"Larva";413;2
"Unit";"Hydralisk";"Larva";413;2
"Unit";"Hydralisk";"Larva";445;2
"Unit";"Hydralisk";"Larva";445;2
"Unit";"Hydralisk";"Larva";445;2
"Unit";"Hydralisk";"Larva";445;2
"Unit";"Hydralisk";"Larva";445;2
"Unit";"Hydralisk";"Larva";445;2
"Unit";"Hydralisk";"Larva";445;2
"Unit";"Hydralisk";"Larva";445;2
"Unit";"Hydralisk";"Larva";445;2
"Unit";"Hydralisk";"Larva";445;2
"Unit";"Hydralisk";"Larva";445;2
"Unit";"Viper";"Larva";441;3
"Unit";"Viper";"Larva";441;3
"Unit";"Viper";"Larva";441;3
"Unit";"Viper";"Larva";441;3
"Unit";"Viper";"Larva";441;3
"Upgrade";"ZergMissileWeaponsLevel1";"EvolutionChamber";355;0
"Building";"CreepTumorQueen";NA;445;0
"Building";"CreepTumorQueen";NA;445;0
"Building";"CreepTumorQueen";NA;445;0
"Building";"UltraliskCavern";NA;437;0
"Building";"SporeCrawler";NA;445;0
"Building";"SporeCrawler";NA;445;0
"Unit";"Overlord";"Larva";479;0
"Building";"CreepTumor";NA;482;0
"Building";"CreepTumor";NA;482;0
"Building";"CreepTumor";NA;482;0
"Upgrade";"ZergGroundArmorsLevel2";"EvolutionChamber";355;0
"Building";"CreepTumor";NA;482;0
"Building";"CreepTumor";NA;482;0
"Building";"CreepTumor";NA;482;0
"Unit";"Baneling";"Zergling";482;0
"Unit";"Baneling";"Zergling";482;0
"Unit";"Baneling";"Zergling";482;0
"Unit";"Baneling";"Zergling";482;0
"Unit";"Baneling";"Zergling";482;0
"Unit";"Baneling";"Zergling";482;0
"Unit";"Baneling";"Zergling";482;0
"Unit";"Baneling";"Zergling";482;0
"Unit";"Baneling";"Zergling";482;0
"Building";"Hatchery";NA;435;0
"Building";"Hatchery";NA;441;0
"Unit";"Ultralisk";"Larva";482;6
"Unit";"Ultralisk";"Larva";482;6
"Unit";"Ultralisk";"Larva";482;6
"Unit";"Ultralisk";"Larva";482;6
"Unit";"Ultralisk";"Larva";482;6
"Building";"CreepTumor";NA;506;0
"Building";"CreepTumor";NA;506;0
"Building";"CreepTumor";NA;506;0
"Unit";"Baneling";"Zergling";506;0
"Unit";"Baneling";"Zergling";506;0
"Unit";"Baneling";"Zergling";506;0
"Unit";"Baneling";"Zergling";506;0
"Unit";"Baneling";"Zergling";506;0
"Unit";"Baneling";"Zergling";506;0
"Unit";"Baneling";"Zergling";506;0
"Unit";"Baneling";"Zergling";506;0
"Unit";"Baneling";"Zergling";506;0
"Unit";"Baneling";"Zergling";506;0
"Unit";"Baneling";"Zergling";506;0
"Unit";"Baneling";"Zergling";506;0
"Unit";"Baneling";"Zergling";506;0
"Unit";"Baneling";"Zergling";506;0
"Unit";"Baneling";"Zergling";506;0
"Unit";"Baneling";"Zergling";506;0
"Unit";"Baneling";"Zergling";506;0
"Unit";"Baneling";"Zergling";506;0
"Unit";"Baneling";"Zergling";506;0
"Unit";"Baneling";"Zergling";506;0
"Unit";"Baneling";"Zergling";506;0
"Unit";"Baneling";"Zergling";506;0
"Building";"CreepTumor";NA;506;0
"Building";"CreepTumor";NA;506;0
"Building";"CreepTumor";NA;506;0
"Upgrade";"ChitinousPlating";"UltraliskCavern";482;0
"Unit";"Zergling";"Larva";512;1
"Unit";"Zergling";"Larva";512;1
"Unit";"Zergling";"Larva";512;1
"Unit";"Zergling";"Larva";512;1
"Unit";"Zergling";"Larva";512;1
"Unit";"Zergling";"Larva";512;1
"Unit";"Zergling";"Larva";512;1
"Unit";"Zergling";"Larva";512;1
"Unit";"Zergling";"Larva";512;1
"Unit";"Zergling";"Larva";512;1
"Unit";"Zergling";"Larva";512;1
"Unit";"Zergling";"Larva";512;1
"Unit";"Zergling";"Larva";512;1
"Unit";"Zergling";"Larva";512;1
"Unit";"Zergling";"Larva";512;1
"Unit";"Zergling";"Larva";512;1
"Unit";"Zergling";"Larva";512;1
"Unit";"Zergling";"Larva";512;1
"Unit";"Zergling";"Larva";512;1
"Unit";"Zergling";"Larva";512;1
"Unit";"Zergling";"Larva";512;1
"Unit";"Zergling";"Larva";512;1
"Unit";"Zergling";"Larva";512;1
"Unit";"Zergling";"Larva";512;1
"Unit";"Zergling";"Larva";512;1
"Unit";"Zergling";"Larva";512;1
"Unit";"Zergling";"Larva";512;1
"Unit";"Zergling";"Larva";512;1
"Unit";"Zergling";"Larva";512;1
"Unit";"Zergling";"Larva";512;1
"Unit";"Zergling";"Larva";512;1
"Unit";"Zergling";"Larva";512;1
"Unit";"Zergling";"Larva";512;1
"Unit";"Zergling";"Larva";512;1
"Unit";"Zergling";"Larva";512;1
"Unit";"Zergling";"Larva";512;1
"Unit";"Zergling";"Larva";512;1
"Unit";"Zergling";"Larva";512;1
"Unit";"Zergling";"Larva";512;1
"Unit";"Zergling";"Larva";512;1
"Unit";"Zergling";"Larva";512;1
"Unit";"Zergling";"Larva";512;1
"Unit";"Zergling";"Larva";512;1
"Unit";"Zergling";"Larva";512;1
"Unit";"Zergling";"Larva";512;1
"Unit";"Zergling";"Larva";512;1
"Unit";"Zergling";"Larva";512;1
"Unit";"Zergling";"Larva";512;1
"Unit";"Zergling";"Larva";512;1
"Unit";"Zergling";"Larva";512;1
"Unit";"Zergling";"Larva";512;1
"Unit";"Zergling";"Larva";512;1
"Unit";"Zergling";"Larva";512;1
"Unit";"Zergling";"Larva";512;1
"Unit";"Zergling";"Larva";512;1
"Unit";"Zergling";"Larva";512;1
"Unit";"Zergling";"Larva";512;1
"Unit";"Zergling";"Larva";512;1
"Unit";"Zergling";"Larva";520;1
"Unit";"Zergling";"Larva";520;1
"Unit";"Zergling";"Larva";522;1
"Unit";"Zergling";"Larva";522;1
"Unit";"Zergling";"Larva";522;1
"Unit";"Zergling";"Larva";522;1
"Unit";"Zergling";"Larva";522;1
"Unit";"Zergling";"Larva";522;1
"Unit";"Zergling";"Larva";522;1
"Unit";"Zergling";"Larva";522;1
"Unit";"Zergling";"Larva";522;1
"Unit";"Zergling";"Larva";522;1
"Unit";"Zergling";"Larva";522;1
"Unit";"Zergling";"Larva";522;1
"Unit";"Zergling";"Larva";522;1
"Unit";"Zergling";"Larva";522;1
"Unit";"Zergling";"Larva";522;1
"Unit";"Zergling";"Larva";522;1
"Unit";"Zergling";"Larva";522;1
"Unit";"Zergling";"Larva";522;1
"Unit";"Zergling";"Larva";522;1
"Unit";"Zergling";"Larva";522;1
"Unit";"Zergling";"Larva";522;1
"Unit";"Zergling";"Larva";522;1
"Unit";"Zergling";"Larva";522;1
"Unit";"Zergling";"Larva";522;1
"Unit";"Zergling";"Larva";522;1
"Unit";"Zergling";"Larva";522;1
"Unit";"Zergling";"Larva";522;1
"Unit";"Zergling";"Larva";522;1
"Unit";"Zergling";"Larva";522;1
"Unit";"Zergling";"Larva";522;1
"Unit";"Zergling";"Larva";522;1
"Unit";"Zergling";"Larva";522;1
"Unit";"Zergling";"Larva";522;1
"Unit";"Zergling";"Larva";522;1
"Unit";"Zergling";"Larva";522;1
"Unit";"Zergling";"Larva";522;1
"Unit";"Zergling";"Larva";522;1
"Unit";"Zergling";"Larva";522;1
"Unit";"Zergling";"Larva";522;1
"Unit";"Zergling";"Larva";522;1
"Unit";"Zergling";"Larva";522;1
"Unit";"Zergling";"Larva";522;1
"Unit";"Zergling";"Larva";522;1
"Unit";"Zergling";"Larva";522;1
"Unit";"Zergling";"Larva";522;1
"Unit";"Zergling";"Larva";522;1
"Unit";"Zergling";"Larva";522;1
"Unit";"Zergling";"Larva";522;1
"Unit";"Zergling";"Larva";522;1
"Unit";"Zergling";"Larva";522;1
"Unit";"Zergling";"Larva";522;1
"Unit";"Zergling";"Larva";522;1
"Unit";"Zergling";"Larva";522;1
"Unit";"Zergling";"Larva";522;1
"Unit";"Zergling";"Larva";522;1
"Unit";"Zergling";"Larva";522;1
"Unit";"Zergling";"Larva";522;1
"Unit";"Zergling";"Larva";522;1
"Unit";"Zergling";"Larva";522;1
"Unit";"Zergling";"Larva";522;1
"Unit";"Zergling";"Larva";522;1
"Unit";"Zergling";"Larva";522;1
"Unit";"Zergling";"Larva";522;1
"Unit";"Zergling";"Larva";522;1
"Upgrade";"ZergMeleeWeaponsLevel3";"EvolutionChamber";482;0
"Unit";"Baneling";"Zergling";650;0
"Unit";"Baneling";"Zergling";650;0
"Unit";"Baneling";"Zergling";650;0
"Unit";"Baneling";"Zergling";650;0
"Unit";"Baneling";"Zergling";650;0
"Unit";"Baneling";"Zergling";650;0
"Unit";"Baneling";"Zergling";650;0
"Unit";"Baneling";"Zergling";650;0
"Unit";"Baneling";"Zergling";650;0
"Unit";"Baneling";"Zergling";650;0
"Unit";"Baneling";"Zergling";650;0
"Unit";"Baneling";"Zergling";650;0
"Unit";"Baneling";"Zergling";650;0
"Unit";"Baneling";"Zergling";650;0
"Unit";"Ultralisk";"Larva";546;6
"Unit";"Ultralisk";"Larva";610;6
"Unit";"Ultralisk";"Larva";610;6
"Unit";"Ultralisk";"Larva";610;6
"Unit";"Baneling";"Zergling";656;0
"Unit";"Baneling";"Zergling";656;0
"Unit";"Baneling";"Zergling";656;0
"Unit";"Baneling";"Zergling";656;0
"Unit";"Baneling";"Zergling";656;0
"Unit";"Baneling";"Zergling";656;0
"Unit";"Baneling";"Zergling";656;0
"Unit";"Baneling";"Zergling";656;0
"Unit";"Baneling";"Zergling";656;0
"Unit";"Baneling";"Zergling";656;0
"Unit";"Baneling";"Zergling";656;0
"Unit";"Baneling";"Zergling";656;0
"Unit";"Baneling";"Zergling";668;0
"Unit";"Baneling";"Zergling";668;0
"Unit";"Baneling";"Zergling";674;0
"Unit";"Baneling";"Zergling";674;0
"Unit";"Baneling";"Zergling";674;0
"Upgrade";"ZergGroundArmorsLevel3";"EvolutionChamber";512;0
"Unit";"Ultralisk";"Larva";650;6
"Unit";"Viper";"Larva";674;3
"Unit";"Viper";"Larva";674;3
"Building";"Hatchery";NA;650;0
"Unit";"Baneling";"Zergling";686;0
"Unit";"Baneling";"Zergling";686;0
"Unit";"Baneling";"Zergling";686;0
"Unit";"Baneling";"Zergling";686;0
"Unit";"Baneling";"Zergling";686;0
"Unit";"Baneling";"Zergling";686;0
"Unit";"Baneling";"Zergling";686;0
"Unit";"Baneling";"Zergling";686;0
"Unit";"Baneling";"Zergling";686;0
"Unit";"Baneling";"Zergling";686;0
"Unit";"Baneling";"Zergling";686;0
"Unit";"Baneling";"Zergling";686;0
"Unit";"Baneling";"Zergling";686;0
"Unit";"Baneling";"Zergling";686;0
"Unit";"Baneling";"Zergling";686;0
"Unit";"Baneling";"Zergling";686;0
"Unit";"Baneling";"Zergling";686;0
"Unit";"Baneling";"Zergling";686;0
"Unit";"Baneling";"Zergling";686;0
"Unit";"Baneling";"Zergling";686;0
"Unit";"Baneling";"Zergling";686;0
"Unit";"Baneling";"Zergling";686;0
"Unit";"Baneling";"Zergling";686;0
"Unit";"Baneling";"Zergling";686;0
"Unit";"Baneling";"Zergling";686;0
"Unit";"Baneling";"Zergling";686;0
"Building";"Hatchery";NA;674;0
"Unit";"Zergling";"Larva";688;1
"Unit";"Zergling";"Larva";688;1
"Unit";"Zergling";"Larva";688;1
"Unit";"Zergling";"Larva";688;1
"Unit";"Zergling";"Larva";688;1
"Unit";"Zergling";"Larva";688;1
"Unit";"Zergling";"Larva";688;1
"Unit";"Zergling";"Larva";688;1
"Unit";"Zergling";"Larva";688;1
"Unit";"Zergling";"Larva";688;1
"Unit";"Zergling";"Larva";688;1
"Unit";"Zergling";"Larva";688;1
"Unit";"Zergling";"Larva";688;1
"Unit";"Zergling";"Larva";688;1
"Unit";"Zergling";"Larva";688;1
"Unit";"Zergling";"Larva";688;1
"Unit";"Zergling";"Larva";688;1
"Unit";"Zergling";"Larva";688;1
"Unit";"Zergling";"Larva";688;1
"Unit";"Zergling";"Larva";688;1
"Unit";"Zergling";"Larva";688;1
"Unit";"Zergling";"Larva";688;1
"Unit";"Zergling";"Larva";688;1
"Unit";"Zergling";"Larva";688;1
"Unit";"Zergling";"Larva";688;1
"Unit";"Zergling";"Larva";688;1
"Unit";"Zergling";"Larva";688;1
"Unit";"Zergling";"Larva";688;1
"Unit";"Zergling";"Larva";688;1
"Unit";"Zergling";"Larva";688;1
"Unit";"Zergling";"Larva";688;1
"Unit";"Zergling";"Larva";688;1
"Unit";"Zergling";"Larva";688;1
"Unit";"Zergling";"Larva";688;1
"Unit";"Zergling";"Larva";688;1
"Unit";"Zergling";"Larva";688;1
"Unit";"Zergling";"Larva";688;1
"Unit";"Zergling";"Larva";688;1
"Unit";"Zergling";"Larva";688;1
"Unit";"Zergling";"Larva";688;1
"Unit";"Zergling";"Larva";688;1
"Unit";"Zergling";"Larva";688;1
"Unit";"Zergling";"Larva";688;1
"Unit";"Zergling";"Larva";688;1
"Unit";"Zergling";"Larva";688;1
"Unit";"Zergling";"Larva";688;1
"Unit";"Zergling";"Larva";688;1
"Unit";"Zergling";"Larva";688;1
"Unit";"Zergling";"Larva";688;1
"Unit";"Zergling";"Larva";688;1
"Unit";"Zergling";"Larva";688;1
"Unit";"Zergling";"Larva";688;1
"Unit";"Zergling";"Larva";688;1
"Unit";"Zergling";"Larva";688;1
"Unit";"Zergling";"Larva";688;1
"Unit";"Zergling";"Larva";688;1
"Unit";"Zergling";"Larva";688;1
"Unit";"Zergling";"Larva";688;1
"Unit";"Zergling";"Larva";688;1
"Unit";"Zergling";"Larva";688;1
"Unit";"Zergling";"Larva";716;1
"Unit";"Zergling";"Larva";716;1
"Unit";"Zergling";"Larva";716;1
"Unit";"Zergling";"Larva";716;1
"Unit";"Ultralisk";"Larva";688;6
"Unit";"Ultralisk";"Larva";688;6
"Unit";"Ultralisk";"Larva";688;6
"Unit";"Zergling";"Larva";716;1
"Unit";"Zergling";"Larva";716;1
"Unit";"Ultralisk";"Larva";688;6
"Unit";"Ultralisk";"Larva";688;6
"Unit";"Ultralisk";"Larva";688;6
"Unit";"Ultralisk";"Larva";688;6
"Unit";"Zergling";"Larva";736;1
"Unit";"Zergling";"Larva";736;1
"Unit";"Zergling";"Larva";738;1
"Unit";"Zergling";"Larva";738;1
"Unit";"Zergling";"Larva";738;1
"Unit";"Zergling";"Larva";738;1
"Unit";"Ultralisk";"Larva";748;6
"Upgrade";"ZergMissileWeaponsLevel2";"EvolutionChamber";688;0
"Unit";"Zergling";"Larva";823;1
"Unit";"Zergling";"Larva";823;1
"Unit";"Zergling";"Larva";823;1
"Unit";"Zergling";"Larva";823;1
"Unit";"Zergling";"Larva";823;1
"Unit";"Zergling";"Larva";823;1
"Unit";"Zergling";"Larva";823;1
"Unit";"Zergling";"Larva";823;1
"Unit";"Zergling";"Larva";823;1
"Unit";"Zergling";"Larva";823;1
"Unit";"Zergling";"Larva";823;1
"Unit";"Zergling";"Larva";823;1
"Unit";"Zergling";"Larva";823;1
"Unit";"Zergling";"Larva";823;1
"Unit";"Zergling";"Larva";823;1
"Unit";"Zergling";"Larva";823;1
"Unit";"Zergling";"Larva";823;1
"Unit";"Zergling";"Larva";823;1
"Unit";"Zergling";"Larva";823;1
"Unit";"Zergling";"Larva";823;1
"Unit";"Zergling";"Larva";823;1
"Unit";"Zergling";"Larva";823;1
"Unit";"Zergling";"Larva";823;1
"Unit";"Zergling";"Larva";823;1
"Unit";"Zergling";"Larva";823;1
"Unit";"Zergling";"Larva";823;1
"Unit";"Zergling";"Larva";823;1
"Unit";"Zergling";"Larva";823;1
"Unit";"Zergling";"Larva";823;1
"Unit";"Zergling";"Larva";823;1
"Unit";"Zergling";"Larva";823;1
"Unit";"Zergling";"Larva";823;1
"Unit";"Zergling";"Larva";823;1
"Unit";"Zergling";"Larva";823;1
"Building";"CreepTumorQueen";NA;823;0
