"type";"unit_name";"on_building";"total_supply";"supply"
"Unit";"Overlord";"Larva";12;0
"Building";"Extractor";NA;18;0
"Unit";"Overlord";"Larva";21;0
"Building";"SpawningPool";NA;19;0
"Building";"Hatchery";NA;16;0
"Unit";"Zergling";"Larva";22;1
"Unit";"Zergling";"Larva";22;1
"Unit";"Zergling";"Larva";22;1
"Unit";"Zergling";"Larva";22;1
"Unit";"Zergling";"Larva";22;1
"Unit";"Zergling";"Larva";22;1
"Unit";"Queen";"Hatchery";22;2
"Unit";"Queen";"Hatchery";22;2
"Unit";"Overlord";"Larva";36;0
"Unit";"Queen";"Hatchery";33;2
"Building";"CreepTumorQueen";NA;40;0
"Unit";"Overlord";"Larva";44;0
"Building";"CreepTumor";NA;50;0
"Building";"CreepTumorQueen";NA;50;0
"Unit";"Queen";"Hatchery";50;2
"Unit";"Overlord";"Larva";50;0
"Unit";"Queen";"Hatchery";50;2
"Building";"Extractor";NA;50;0
"Unit";"Overlord";"Larva";55;0
"Building";"CreepTumorQueen";NA;59;0
"Building";"CreepTumorQueen";NA;61;0
"Building";"CreepTumor";NA;61;0
"Building";"CreepTumor";NA;61;0
"Building";"CreepTumorQueen";NA;61;0
"Building";"BanelingNest";NA;50;0
"Unit";"Zergling";"Larva";61;1
"Unit";"Zergling";"Larva";61;1
"Unit";"Zergling";"Larva";61;1
"Unit";"Zergling";"Larva";61;1
"Building";"Hatchery";NA;50;0
"Unit";"Zergling";"Larva";61;1
"Unit";"Zergling";"Larva";61;1
"Unit";"Zergling";"Larva";61;1
"Unit";"Zergling";"Larva";61;1
"Unit";"Queen";"Hatchery";59;2
"Unit";"Queen";"Hatchery";59;2
"Building";"SporeCrawler";NA;61;0
"Building";"SporeCrawler";NA;61;0
"Unit";"Baneling";"Zergling";69;0
"Building";"CreepTumor";NA;71;0
"Unit";"Baneling";"Zergling";70;0
"Unit";"Baneling";"Zergling";70;0
"Unit";"Baneling";"Zergling";70;0
"Building";"SporeCrawler";NA;61;0
"Building";"CreepTumorQueen";NA;73;0
"Building";"CreepTumor";NA;73;0
"Building";"CreepTumor";NA;75;0
"Building";"CreepTumorQueen";NA;75;0
"Unit";"Queen";"Hatchery";71;2
"Building";"CreepTumor";NA;86;0
"Building";"CreepTumorQueen";NA;86;0
"Building";"CreepTumor";NA;86;0
"Building";"EvolutionChamber";NA;85;0
"Building";"CreepTumorQueen";NA;88;0
"Building";"EvolutionChamber";NA;85;0
"Building";"CreepTumor";NA;88;0
"Unit";"Overlord";"Larva";90;0
"Building";"CreepTumorQueen";NA;94;0
"Unit";"Overlord";"Larva";90;0
"Unit";"Overlord";"Larva";90;0
"Building";"CreepTumorQueen";NA;95;0
"Building";"Extractor";NA;90;0
"Building";"Extractor";NA;90;0
"Building";"CreepTumorQueen";NA;95;0
"Building";"CreepTumorQueen";NA;95;0
"Building";"CreepTumorQueen";NA;95;0
"Building";"CreepTumor";NA;95;0
"Unit";"Overlord";"Larva";95;0
"Unit";"Overlord";"Larva";95;0
"Building";"CreepTumorQueen";NA;95;0
"Building";"CreepTumorQueen";NA;97;0
"Building";"CreepTumor";NA;97;0
"Building";"CreepTumor";NA;97;0
"Building";"CreepTumor";NA;97;0
"Building";"CreepTumor";NA;97;0
"Building";"CreepTumorQueen";NA;104;0
"Unit";"Overlord";"Larva";104;0
"Unit";"Zergling";"Larva";115;1
"Unit";"Zergling";"Larva";115;1
"Unit";"Zergling";"Larva";115;1
"Unit";"Zergling";"Larva";115;1
"Unit";"Zergling";"Larva";115;1
"Unit";"Zergling";"Larva";115;1
"Unit";"Zergling";"Larva";116;1
"Unit";"Zergling";"Larva";116;1
"Unit";"Zergling";"Larva";116;1
"Unit";"Zergling";"Larva";116;1
"Building";"SporeCrawler";NA;116;0
"Building";"SporeCrawler";NA;116;0
"Building";"CreepTumor";NA;122;0
"Building";"CreepTumor";NA;122;0
"Building";"CreepTumor";NA;122;0
"Unit";"Overlord";"Larva";122;0
"Building";"CreepTumor";NA;122;0
"Building";"CreepTumor";NA;122;0
"Building";"CreepTumor";NA;126;0
"Unit";"Zergling";"Larva";122;1
"Unit";"Zergling";"Larva";122;1
"Unit";"Zergling";"Larva";122;1
"Unit";"Zergling";"Larva";122;1
"Unit";"Zergling";"Larva";122;1
"Unit";"Zergling";"Larva";122;1
"Unit";"Zergling";"Larva";122;1
"Unit";"Zergling";"Larva";122;1
"Unit";"Zergling";"Larva";122;1
"Unit";"Zergling";"Larva";122;1
"Building";"CreepTumor";NA;126;0
"Building";"CreepTumor";NA;126;0
"Unit";"Zergling";"Larva";122;1
"Unit";"Zergling";"Larva";122;1
"Building";"SporeCrawler";NA;122;0
"Building";"InfestationPit";NA;116;0
"Building";"CreepTumorQueen";NA;126;0
"Building";"CreepTumorQueen";NA;126;0
"Building";"CreepTumorQueen";NA;126;0
"Upgrade";"ZergMeleeWeaponsLevel1";"EvolutionChamber";104;0
"Upgrade";"ZergGroundArmorsLevel1";"EvolutionChamber";104;0
"Building";"Hatchery";NA;104;0
"Building";"SporeCrawler";NA;129;0
"Building";"SporeCrawler";NA;141;0
"Building";"CreepTumor";NA;144;0
"Building";"CreepTumor";NA;144;0
"Building";"CreepTumor";NA;144;0
"Building";"CreepTumor";NA;144;0
"Building";"CreepTumor";NA;144;0
"Unit";"Zergling";"Larva";145;1
"Unit";"Zergling";"Larva";145;1
"Unit";"Zergling";"Larva";152;1
"Unit";"Zergling";"Larva";152;1
"Unit";"Zergling";"Larva";152;1
"Unit";"Zergling";"Larva";152;1
"Unit";"Zergling";"Larva";154;1
"Unit";"Zergling";"Larva";154;1
"Unit";"Zergling";"Larva";154;1
"Unit";"Zergling";"Larva";154;1
"Unit";"Zergling";"Larva";156;1
"Unit";"Zergling";"Larva";156;1
"Unit";"Baneling";"Zergling";158;0
"Unit";"Baneling";"Zergling";158;0
"Unit";"Baneling";"Zergling";158;0
"Unit";"Baneling";"Zergling";158;0
"Unit";"Baneling";"Zergling";158;0
"Unit";"Baneling";"Zergling";158;0
"Unit";"Baneling";"Zergling";158;0
"Unit";"Baneling";"Zergling";158;0
"Unit";"Baneling";"Zergling";158;0
"Unit";"Baneling";"Zergling";158;0
"Unit";"Baneling";"Zergling";158;0
"Unit";"Baneling";"Zergling";158;0
"Unit";"Baneling";"Zergling";158;0
"Unit";"Baneling";"Zergling";158;0
"Unit";"Baneling";"Zergling";158;0
"Unit";"Baneling";"Zergling";158;0
"Unit";"Baneling";"Zergling";158;0
"Unit";"Baneling";"Zergling";158;0
"Unit";"Baneling";"Zergling";158;0
"Unit";"Baneling";"Zergling";158;0
"Unit";"Zergling";"Larva";158;1
"Unit";"Zergling";"Larva";158;1
"Unit";"Zergling";"Larva";158;1
"Unit";"Zergling";"Larva";158;1
"Unit";"Zergling";"Larva";158;1
"Unit";"Zergling";"Larva";158;1
"Unit";"Zergling";"Larva";158;1
"Unit";"Zergling";"Larva";158;1
"Unit";"Zergling";"Larva";158;1
"Unit";"Zergling";"Larva";158;1
"Unit";"Zergling";"Larva";158;1
"Unit";"Zergling";"Larva";158;1
"Unit";"Zergling";"Larva";158;1
"Unit";"Zergling";"Larva";158;1
"Unit";"Zergling";"Larva";158;1
"Unit";"Zergling";"Larva";158;1
"Unit";"Zergling";"Larva";158;1
"Unit";"Zergling";"Larva";158;1
"Unit";"Zergling";"Larva";158;1
"Unit";"Zergling";"Larva";158;1
"Building";"Extractor";NA;158;0
"Unit";"Zergling";"Larva";170;1
"Unit";"Zergling";"Larva";170;1
"Unit";"Zergling";"Larva";170;1
"Unit";"Zergling";"Larva";170;1
"Unit";"Zergling";"Larva";170;1
"Unit";"Zergling";"Larva";170;1
"Unit";"Zergling";"Larva";170;1
"Unit";"Zergling";"Larva";170;1
"Unit";"Zergling";"Larva";170;1
"Unit";"Zergling";"Larva";170;1
"Unit";"Zergling";"Larva";170;1
"Unit";"Zergling";"Larva";170;1
"Unit";"Baneling";"Zergling";186;0
"Unit";"Baneling";"Zergling";190;0
"Unit";"Zergling";"Larva";184;1
"Unit";"Zergling";"Larva";184;1
"Unit";"Baneling";"Zergling";190;0
"Unit";"Baneling";"Zergling";190;0
"Unit";"Baneling";"Zergling";190;0
"Unit";"Baneling";"Zergling";190;0
"Unit";"Baneling";"Zergling";190;0
"Unit";"Baneling";"Zergling";190;0
"Unit";"Baneling";"Zergling";190;0
"Unit";"Zergling";"Larva";184;1
"Unit";"Zergling";"Larva";184;1
"Unit";"Zergling";"Larva";184;1
"Unit";"Zergling";"Larva";184;1
"Unit";"Baneling";"Zergling";190;0
"Unit";"Baneling";"Zergling";190;0
"Unit";"Queen";"Hatchery";158;2
"Unit";"Zergling";"Larva";190;1
"Unit";"Zergling";"Larva";190;1
"Unit";"Queen";"Hatchery";184;2
"Unit";"Queen";"Hatchery";184;2
"Building";"CreepTumorQueen";NA;212;0
"Building";"CreepTumorQueen";NA;212;0
"Building";"CreepTumorQueen";NA;212;0
"Unit";"Overlord";"Larva";212;0
"Unit";"Queen";"Hatchery";208;2
"Unit";"Zergling";"Larva";223;1
"Unit";"Zergling";"Larva";223;1
"Unit";"Overlord";"Larva";223;0
"Unit";"Overlord";"Larva";223;0
"Unit";"Zergling";"Larva";223;1
"Unit";"Zergling";"Larva";223;1
"Unit";"Zergling";"Larva";223;1
"Unit";"Zergling";"Larva";223;1
"Unit";"Zergling";"Larva";223;1
"Unit";"Zergling";"Larva";223;1
"Unit";"Zergling";"Larva";223;1
"Unit";"Zergling";"Larva";223;1
"Unit";"Zergling";"Larva";223;1
"Unit";"Zergling";"Larva";223;1
"Unit";"Zergling";"Larva";223;1
"Unit";"Zergling";"Larva";223;1
"Unit";"Zergling";"Larva";223;1
"Unit";"Zergling";"Larva";223;1
"Unit";"Zergling";"Larva";223;1
"Unit";"Zergling";"Larva";223;1
"Unit";"Zergling";"Larva";223;1
"Unit";"Zergling";"Larva";223;1
"Unit";"Zergling";"Larva";223;1
"Unit";"Zergling";"Larva";223;1
"Unit";"Zergling";"Larva";223;1
"Unit";"Zergling";"Larva";223;1
"Unit";"Zergling";"Larva";223;1
"Unit";"Zergling";"Larva";223;1
"Building";"Extractor";NA;223;0
"Building";"CreepTumorQueen";NA;228;0
"Building";"CreepTumorQueen";NA;228;0
"Building";"CreepTumor";NA;228;0
"Building";"CreepTumor";NA;228;0
"Building";"CreepTumor";NA;228;0
"Building";"CreepTumor";NA;228;0
"Building";"CreepTumorQueen";NA;254;0
"Building";"CreepTumorQueen";NA;254;0
"Building";"CreepTumorQueen";NA;254;0
"Unit";"Overlord";"Larva";228;0
"Unit";"Overlord";"Larva";228;0
"Unit";"Overlord";"Larva";228;0
"Unit";"Overlord";"Larva";228;0
"Unit";"Overlord";"Larva";228;0
"Unit";"Overlord";"Larva";228;0
"Unit";"Overlord";"Larva";228;0
"Building";"UltraliskCavern";NA;223;0
"Unit";"Zergling";"Larva";254;1
"Unit";"Zergling";"Larva";254;1
"Unit";"Zergling";"Larva";254;1
"Unit";"Zergling";"Larva";254;1
"Unit";"Zergling";"Larva";254;1
"Unit";"Zergling";"Larva";254;1
"Unit";"Zergling";"Larva";254;1
"Unit";"Zergling";"Larva";254;1
"Unit";"Zergling";"Larva";254;1
"Unit";"Zergling";"Larva";254;1
"Unit";"Zergling";"Larva";254;1
"Unit";"Zergling";"Larva";254;1
"Unit";"Zergling";"Larva";254;1
"Unit";"Zergling";"Larva";254;1
"Unit";"Zergling";"Larva";254;1
"Unit";"Zergling";"Larva";254;1
"Unit";"Zergling";"Larva";254;1
"Unit";"Zergling";"Larva";254;1
"Building";"SporeCrawler";NA;254;0
"Upgrade";"ZergMeleeWeaponsLevel2";"EvolutionChamber";208;0
"Upgrade";"ZergGroundArmorsLevel2";"EvolutionChamber";208;0
"Building";"CreepTumorQueen";NA;272;0
"Building";"CreepTumorQueen";NA;272;0
"Building";"CreepTumorQueen";NA;272;0
"Building";"CreepTumorQueen";NA;272;0
"Building";"CreepTumorQueen";NA;272;0
"Building";"CreepTumorQueen";NA;272;0
"Building";"Spire";NA;223;0
"Building";"SporeCrawler";NA;272;0
"Building";"CreepTumor";NA;272;0
"Building";"CreepTumor";NA;272;0
"Building";"Extractor";NA;272;0
"Building";"CreepTumor";NA;272;0
"Unit";"Zergling";"Larva";272;1
"Unit";"Zergling";"Larva";272;1
"Unit";"Zergling";"Larva";272;1
"Unit";"Zergling";"Larva";272;1
"Unit";"Zergling";"Larva";272;1
"Unit";"Zergling";"Larva";272;1
"Unit";"Zergling";"Larva";272;1
"Unit";"Zergling";"Larva";272;1
"Unit";"Zergling";"Larva";272;1
"Unit";"Zergling";"Larva";272;1
"Unit";"Zergling";"Larva";272;1
"Unit";"Zergling";"Larva";272;1
"Unit";"Zergling";"Larva";272;1
"Unit";"Zergling";"Larva";272;1
"Unit";"Zergling";"Larva";272;1
"Unit";"Zergling";"Larva";272;1
"Unit";"Zergling";"Larva";272;1
"Unit";"Zergling";"Larva";272;1
"Unit";"Zergling";"Larva";272;1
"Unit";"Zergling";"Larva";272;1
"Unit";"Zergling";"Larva";272;1
"Unit";"Zergling";"Larva";272;1
"Unit";"Zergling";"Larva";272;1
"Unit";"Zergling";"Larva";272;1
"Unit";"Zergling";"Larva";272;1
"Unit";"Zergling";"Larva";272;1
"Unit";"Zergling";"Larva";272;1
"Unit";"Zergling";"Larva";272;1
"Unit";"Zergling";"Larva";272;1
"Unit";"Zergling";"Larva";272;1
"Unit";"Zergling";"Larva";272;1
"Unit";"Zergling";"Larva";272;1
"Unit";"Ultralisk";"Larva";272;6
"Unit";"Ultralisk";"Larva";272;6
"Unit";"Ultralisk";"Larva";272;6
"Unit";"Ultralisk";"Larva";272;6
"Unit";"Ultralisk";"Larva";272;6
"Unit";"Ultralisk";"Larva";272;6
"Building";"CreepTumor";NA;340;0
"Building";"Hatchery";NA;272;0
"Building";"CreepTumor";NA;340;0
"Building";"CreepTumor";NA;340;0
"Building";"CreepTumor";NA;340;0
"Building";"CreepTumor";NA;340;0
"Building";"CreepTumorQueen";NA;340;0
"Building";"CreepTumorQueen";NA;340;0
"Unit";"Corruptor";"Larva";340;2
"Unit";"Corruptor";"Larva";340;2
"Unit";"Corruptor";"Larva";340;2
"Unit";"Corruptor";"Larva";340;2
"Unit";"Corruptor";"Larva";340;2
"Unit";"Corruptor";"Larva";340;2
"Upgrade";"ChitinousPlating";"UltraliskCavern";272;0
"Building";"CreepTumor";NA;340;0
"Building";"CreepTumor";NA;340;0
"Building";"CreepTumor";NA;340;0
"Building";"CreepTumor";NA;340;0
"Building";"CreepTumor";NA;340;0
"Building";"CreepTumor";NA;352;0
"Unit";"Queen";"Hatchery";340;2
"Unit";"Overlord";"Larva";340;0
"Unit";"Zergling";"Larva";340;1
"Unit";"Zergling";"Larva";340;1
"Unit";"Overlord";"Larva";340;0
"Unit";"Corruptor";"Larva";340;2
"Unit";"Zergling";"Larva";340;1
"Unit";"Zergling";"Larva";340;1
"Unit";"Zergling";"Larva";340;1
"Unit";"Zergling";"Larva";340;1
"Unit";"Zergling";"Larva";340;1
"Unit";"Zergling";"Larva";340;1
"Unit";"Zergling";"Larva";340;1
"Unit";"Zergling";"Larva";340;1
"Unit";"Zergling";"Larva";340;1
"Unit";"Zergling";"Larva";340;1
"Unit";"Corruptor";"Larva";340;2
"Unit";"Zergling";"Larva";340;1
"Unit";"Zergling";"Larva";340;1
"Unit";"Zergling";"Larva";340;1
"Unit";"Zergling";"Larva";340;1
"Unit";"Zergling";"Larva";340;1
"Unit";"Zergling";"Larva";340;1
"Unit";"Zergling";"Larva";340;1
"Unit";"Zergling";"Larva";340;1
"Building";"CreepTumor";NA;352;0
"Building";"CreepTumor";NA;352;0
"Unit";"Overlord";"Larva";352;0
"Unit";"Overlord";"Larva";352;0
"Building";"CreepTumor";NA;378;0
"Building";"Extractor";NA;354;0
"Unit";"Zergling";"Larva";378;1
"Unit";"Zergling";"Larva";378;1
"Unit";"Zergling";"Larva";378;1
"Unit";"Zergling";"Larva";378;1
"Unit";"Baneling";"Zergling";382;0
"Unit";"Baneling";"Zergling";382;0
"Unit";"Baneling";"Zergling";382;0
"Unit";"Baneling";"Zergling";382;0
"Unit";"Baneling";"Zergling";382;0
"Unit";"Baneling";"Zergling";382;0
"Unit";"Baneling";"Zergling";382;0
"Unit";"Baneling";"Zergling";382;0
"Unit";"Baneling";"Zergling";382;0
"Unit";"Baneling";"Zergling";382;0
"Unit";"Baneling";"Zergling";382;0
"Unit";"Baneling";"Zergling";382;0
"Unit";"Baneling";"Zergling";382;0
"Unit";"Baneling";"Zergling";382;0
"Unit";"Baneling";"Zergling";382;0
"Unit";"Baneling";"Zergling";382;0
"Unit";"Baneling";"Zergling";382;0
"Unit";"Baneling";"Zergling";382;0
"Unit";"Baneling";"Zergling";382;0
"Unit";"Baneling";"Zergling";382;0
"Unit";"Baneling";"Zergling";382;0
"Unit";"Baneling";"Zergling";382;0
"Unit";"Baneling";"Zergling";382;0
"Unit";"Baneling";"Zergling";382;0
"Unit";"Baneling";"Zergling";382;0
"Unit";"Baneling";"Zergling";382;0
"Building";"CreepTumorQueen";NA;382;0
"Unit";"Queen";"Hatchery";378;2
"Unit";"Baneling";"Zergling";382;0
"Unit";"Baneling";"Zergling";382;0
"Unit";"Baneling";"Zergling";382;0
"Unit";"Baneling";"Zergling";382;0
"Unit";"Baneling";"Zergling";382;0
"Unit";"Baneling";"Zergling";382;0
"Unit";"Baneling";"Zergling";382;0
"Unit";"Zergling";"Larva";382;1
"Unit";"Zergling";"Larva";382;1
"Unit";"Zergling";"Larva";382;1
"Unit";"Zergling";"Larva";382;1
"Unit";"Zergling";"Larva";382;1
"Unit";"Zergling";"Larva";382;1
"Unit";"Queen";"Hatchery";382;2
"Upgrade";"ZergMeleeWeaponsLevel3";"EvolutionChamber";340;0
"Unit";"Zergling";"Larva";390;1
"Unit";"Zergling";"Larva";390;1
"Unit";"Zergling";"Larva";390;1
"Unit";"Zergling";"Larva";390;1
"Unit";"Zergling";"Larva";390;1
"Unit";"Zergling";"Larva";390;1
"Unit";"Zergling";"Larva";390;1
"Unit";"Zergling";"Larva";390;1
"Unit";"Zergling";"Larva";390;1
"Unit";"Zergling";"Larva";390;1
"Unit";"Zergling";"Larva";390;1
"Unit";"Zergling";"Larva";390;1
"Unit";"Zergling";"Larva";390;1
"Unit";"Zergling";"Larva";390;1
"Unit";"Zergling";"Larva";390;1
"Unit";"Zergling";"Larva";390;1
"Unit";"Zergling";"Larva";392;1
"Unit";"Zergling";"Larva";392;1
"Unit";"Zergling";"Larva";392;1
"Unit";"Zergling";"Larva";392;1
"Unit";"Zergling";"Larva";392;1
"Unit";"Zergling";"Larva";392;1
"Unit";"Zergling";"Larva";392;1
"Unit";"Zergling";"Larva";392;1
"Unit";"Zergling";"Larva";392;1
"Unit";"Zergling";"Larva";392;1
"Unit";"Zergling";"Larva";392;1
"Unit";"Zergling";"Larva";392;1
"Unit";"Zergling";"Larva";392;1
"Unit";"Zergling";"Larva";392;1
"Unit";"Zergling";"Larva";392;1
"Unit";"Zergling";"Larva";392;1
"Unit";"Zergling";"Larva";392;1
"Unit";"Zergling";"Larva";392;1
"Unit";"Zergling";"Larva";392;1
"Unit";"Zergling";"Larva";392;1
"Unit";"Zergling";"Larva";392;1
"Unit";"Zergling";"Larva";392;1
"Unit";"Zergling";"Larva";392;1
"Unit";"Zergling";"Larva";392;1
"Unit";"Zergling";"Larva";392;1
"Unit";"Zergling";"Larva";392;1
"Unit";"Zergling";"Larva";392;1
"Unit";"Zergling";"Larva";392;1
"Unit";"Zergling";"Larva";392;1
"Unit";"Zergling";"Larva";392;1
"Unit";"Zergling";"Larva";392;1
"Unit";"Zergling";"Larva";392;1
"Unit";"Zergling";"Larva";392;1
"Unit";"Zergling";"Larva";392;1
"Unit";"Zergling";"Larva";392;1
"Unit";"Zergling";"Larva";392;1
"Unit";"Zergling";"Larva";392;1
"Unit";"Zergling";"Larva";392;1
"Unit";"Zergling";"Larva";392;1
"Unit";"Zergling";"Larva";392;1
