"type";"unit_name";"on_building";"total_supply";"supply"
"Unit";"Overlord";"Larva";12;0
"Building";"Extractor";NA;14;0
"Building";"SpawningPool";NA;17;0
"Unit";"Overlord";"Larva";19;0
"Building";"Extractor";NA;20;0
"Unit";"Overlord";"Larva";20;0
"Unit";"Queen";"Hatchery";20;2
"Building";"RoachWarren";NA;20;0
"Unit";"Zergling";"Larva";24;1
"Unit";"Zergling";"Larva";24;1
"Unit";"Zergling";"Larva";24;1
"Unit";"Zergling";"Larva";24;1
"Unit";"Roach";"Larva";24;2
"Unit";"Roach";"Larva";24;2
"Unit";"Overlord";"Larva";30;0
"Unit";"Roach";"Larva";30;2
"Unit";"Roach";"Larva";30;2
"Unit";"Roach";"Larva";32;2
"Unit";"Roach";"Larva";32;2
"Unit";"Roach";"Larva";32;2
"Unit";"Overlord";"Larva";40;0
"Unit";"Roach";"Larva";42;2
"Unit";"Roach";"Larva";42;2
"Unit";"Overlord";"Larva";42;0
"Unit";"Roach";"Larva";42;2
"Unit";"Roach";"Larva";42;2
"Unit";"Roach";"Larva";50;2
"Unit";"Roach";"Larva";50;2
"Unit";"Roach";"Larva";50;2
"Unit";"Roach";"Larva";56;2
"Unit";"Roach";"Larva";56;2
"Unit";"Roach";"Larva";56;2
"Unit";"Roach";"Larva";56;2
"Unit";"Roach";"Larva";70;2
"Unit";"Roach";"Larva";70;2
"Building";"Hatchery";NA;64;0
"Unit";"Roach";"Larva";72;2
"Unit";"Roach";"Larva";74;2
"Unit";"Roach";"Larva";74;2
"Unit";"Roach";"Larva";76;2
"Unit";"Roach";"Larva";76;2
"Unit";"Roach";"Larva";76;2
"Unit";"Zergling";"Larva";80;1
"Unit";"Zergling";"Larva";80;1
"Unit";"Zergling";"Larva";80;1
"Unit";"Zergling";"Larva";80;1
"Unit";"Zergling";"Larva";80;1
"Unit";"Zergling";"Larva";80;1
"Unit";"Zergling";"Larva";80;1
"Unit";"Zergling";"Larva";80;1
"Building";"Extractor";NA;80;0
"Building";"Extractor";NA;80;0
"Unit";"Roach";"Larva";84;2
"Unit";"Roach";"Larva";84;2
"Unit";"Overlord";"Larva";88;0
"Unit";"Overlord";"Larva";90;0
"Unit";"Overlord";"Larva";94;0
"Unit";"Overlord";"Larva";98;0
"Unit";"Roach";"Larva";98;2
"Unit";"Roach";"Larva";98;2
"Unit";"Roach";"Larva";98;2
"Unit";"Roach";"Larva";98;2
"Unit";"Roach";"Larva";98;2
"Unit";"Roach";"Larva";98;2
"Unit";"Roach";"Larva";113;2
"Unit";"Roach";"Larva";113;2
"Unit";"Roach";"Larva";113;2
"Unit";"Roach";"Larva";113;2
"Unit";"Roach";"Larva";113;2
"Unit";"Roach";"Larva";113;2
"Unit";"Overlord";"Larva";123;0
"Unit";"Roach";"Larva";125;2
"Unit";"Roach";"Larva";125;2
"Unit";"Roach";"Larva";125;2
"Unit";"Roach";"Larva";125;2
"Unit";"Overlord";"Larva";135;0
"Unit";"Overlord";"Larva";135;0
"Building";"EvolutionChamber";NA;135;0
"Unit";"Overlord";"Larva";137;0
"Unit";"Roach";"Larva";149;2
"Unit";"Roach";"Larva";149;2
"Unit";"Roach";"Larva";149;2
"Unit";"Roach";"Larva";149;2
"Unit";"Roach";"Larva";149;2
"Unit";"Roach";"Larva";149;2
"Upgrade";"ZergGroundArmorsLevel1";"EvolutionChamber";144;0
"Unit";"Zergling";"Larva";166;1
"Unit";"Zergling";"Larva";166;1
"Unit";"Zergling";"Larva";166;1
"Unit";"Zergling";"Larva";166;1
"Unit";"Zergling";"Larva";166;1
"Unit";"Zergling";"Larva";166;1
"Unit";"Zergling";"Larva";166;1
"Unit";"Zergling";"Larva";166;1
"Building";"EvolutionChamber";NA;166;0
"Unit";"Zergling";"Larva";166;1
"Unit";"Zergling";"Larva";166;1
"Unit";"Overlord";"Larva";166;0
"Unit";"Zergling";"Larva";166;1
"Unit";"Zergling";"Larva";166;1
"Building";"Hatchery";NA;165;0
"Unit";"Zergling";"Larva";174;1
"Unit";"Zergling";"Larva";174;1
"Unit";"Zergling";"Larva";174;1
"Unit";"Zergling";"Larva";174;1
"Unit";"Zergling";"Larva";174;1
"Unit";"Zergling";"Larva";174;1
"Unit";"Zergling";"Larva";174;1
"Unit";"Zergling";"Larva";174;1
"Unit";"Zergling";"Larva";174;1
"Unit";"Zergling";"Larva";174;1
"Unit";"Queen";"Hatchery";166;2
"Unit";"Zergling";"Larva";178;1
"Unit";"Zergling";"Larva";178;1
"Unit";"Zergling";"Larva";178;1
"Unit";"Zergling";"Larva";178;1
"Unit";"Zergling";"Larva";178;1
"Unit";"Zergling";"Larva";178;1
"Unit";"Zergling";"Larva";178;1
"Unit";"Zergling";"Larva";178;1
"Unit";"Zergling";"Larva";178;1
"Unit";"Zergling";"Larva";178;1
"Unit";"Queen";"Hatchery";190;2
"Unit";"Overlord";"Larva";202;0
"Unit";"Overlord";"Larva";206;0
"Building";"BanelingNest";NA;200;0
"Unit";"Overlord";"Larva";211;0
"Unit";"Zergling";"Larva";211;1
"Unit";"Zergling";"Larva";211;1
"Unit";"Zergling";"Larva";211;1
"Unit";"Zergling";"Larva";211;1
"Unit";"Zergling";"Larva";211;1
"Unit";"Zergling";"Larva";211;1
"Unit";"Zergling";"Larva";211;1
"Unit";"Zergling";"Larva";211;1
"Building";"InfestationPit";NA;211;0
"Building";"Extractor";NA;213;0
"Building";"Extractor";NA;215;0
"Upgrade";"ZergMeleeWeaponsLevel1";"EvolutionChamber";200;0
"Unit";"Zergling";"Larva";234;1
"Unit";"Zergling";"Larva";234;1
"Unit";"Zergling";"Larva";236;1
"Unit";"Zergling";"Larva";236;1
"Unit";"Zergling";"Larva";236;1
"Unit";"Zergling";"Larva";236;1
"Unit";"Zergling";"Larva";236;1
"Unit";"Zergling";"Larva";236;1
"Unit";"Queen";"Hatchery";230;2
"Building";"SporeCrawler";NA;241;0
"Building";"HydraliskDen";NA;241;0
"Upgrade";"ZergGroundArmorsLevel2";"EvolutionChamber";211;0
"Unit";"Overlord";"Larva";251;0
"Unit";"Overlord";"Larva";251;0
"Unit";"Hydralisk";"Larva";255;2
"Unit";"Hydralisk";"Larva";255;2
"Unit";"Hydralisk";"Larva";255;2
"Building";"Hatchery";NA;241;0
"Unit";"Hydralisk";"Larva";255;2
"Unit";"Queen";"Hatchery";255;2
"Unit";"Overlord";"Larva";265;0
"Building";"CreepTumorQueen";NA;269;0
"Unit";"Hydralisk";"Larva";265;2
"Unit";"Hydralisk";"Larva";265;2
"Unit";"Hydralisk";"Larva";265;2
"Unit";"Hydralisk";"Larva";265;2
"Unit";"Hydralisk";"Larva";265;2
"Unit";"Hydralisk";"Larva";265;2
"Unit";"Hydralisk";"Larva";265;2
"Unit";"Queen";"Hatchery";261;2
"Building";"SporeCrawler";NA;265;0
"Unit";"Overlord";"Larva";269;0
"Building";"CreepTumorQueen";NA;269;0
"Upgrade";"EvolveGroovedSpines";"HydraliskDen";255;0
"Building";"CreepTumorQueen";NA;269;0
"Building";"CreepTumorQueen";NA;285;0
"Unit";"Hydralisk";"Larva";269;2
"Unit";"Hydralisk";"Larva";269;2
"Building";"CreepTumorQueen";NA;285;0
"Unit";"Baneling";"Zergling";285;0
"Unit";"Baneling";"Zergling";285;0
"Unit";"Baneling";"Zergling";285;0
"Unit";"Baneling";"Zergling";285;0
"Unit";"Baneling";"Zergling";285;0
"Unit";"Baneling";"Zergling";285;0
"Unit";"Baneling";"Zergling";285;0
"Unit";"Hydralisk";"Larva";269;2
"Unit";"Hydralisk";"Larva";269;2
"Unit";"Hydralisk";"Larva";269;2
"Unit";"Hydralisk";"Larva";269;2
"Unit";"Viper";"Larva";285;3
"Unit";"Viper";"Larva";285;3
"Building";"CreepTumorQueen";NA;297;0
"Building";"CreepTumor";NA;297;0
"Unit";"Hydralisk";"Larva";297;2
"Unit";"Hydralisk";"Larva";297;2
"Unit";"Hydralisk";"Larva";297;2
"Unit";"Hydralisk";"Larva";297;2
"Upgrade";"ZergMissileWeaponsLevel1";"EvolutionChamber";261;0
"Building";"CreepTumorQueen";NA;303;0
"Unit";"Zergling";"Larva";300;1
"Unit";"Zergling";"Larva";300;1
"Unit";"Zergling";"Larva";303;1
"Unit";"Zergling";"Larva";303;1
"Unit";"Zergling";"Larva";303;1
"Unit";"Zergling";"Larva";303;1
"Unit";"Zergling";"Larva";303;1
"Unit";"Zergling";"Larva";303;1
"Unit";"Zergling";"Larva";303;1
"Unit";"Zergling";"Larva";303;1
"Unit";"Zergling";"Larva";303;1
"Unit";"Zergling";"Larva";303;1
"Unit";"Zergling";"Larva";303;1
"Unit";"Zergling";"Larva";303;1
"Building";"Spire";NA;269;0
"Building";"CreepTumorQueen";NA;325;0
"Building";"CreepTumor";NA;325;0
"Upgrade";"ZergMeleeWeaponsLevel2";"EvolutionChamber";265;0
"Building";"CreepTumorQueen";NA;325;0
"Upgrade";"EvolveMuscularAugments";"HydraliskDen";297;0
"Unit";"Overlord";"Larva";325;0
"Unit";"Overlord";"Larva";325;0
"Unit";"Overlord";"Larva";325;0
"Unit";"Overlord";"Larva";325;0
"Unit";"Zergling";"Larva";325;1
"Unit";"Zergling";"Larva";325;1
"Unit";"Zergling";"Larva";325;1
"Unit";"Zergling";"Larva";325;1
"Unit";"Zergling";"Larva";325;1
"Unit";"Zergling";"Larva";325;1
"Unit";"Zergling";"Larva";325;1
"Unit";"Zergling";"Larva";325;1
"Unit";"Overlord";"Larva";325;0
"Unit";"Overlord";"Larva";325;0
"Unit";"Overlord";"Larva";325;0
"Unit";"Zergling";"Larva";325;1
"Unit";"Zergling";"Larva";325;1
"Unit";"Zergling";"Larva";325;1
"Unit";"Zergling";"Larva";325;1
"Unit";"Zergling";"Larva";325;1
"Unit";"Zergling";"Larva";325;1
"Unit";"Zergling";"Larva";325;1
"Unit";"Zergling";"Larva";325;1
"Unit";"Zergling";"Larva";325;1
"Unit";"Zergling";"Larva";325;1
"Unit";"Zergling";"Larva";325;1
"Unit";"Zergling";"Larva";325;1
"Unit";"Zergling";"Larva";325;1
"Unit";"Zergling";"Larva";325;1
"Unit";"Zergling";"Larva";325;1
"Unit";"Zergling";"Larva";325;1
"Unit";"Zergling";"Larva";325;1
"Unit";"Zergling";"Larva";325;1
"Unit";"Zergling";"Larva";325;1
"Unit";"Zergling";"Larva";325;1
"Unit";"Overlord";"Larva";353;0
"Unit";"Overlord";"Larva";353;0
"Unit";"Viper";"Larva";353;3
"Unit";"Viper";"Larva";353;3
"Unit";"Zergling";"Larva";353;1
"Unit";"Zergling";"Larva";353;1
"Unit";"Zergling";"Larva";353;1
"Unit";"Zergling";"Larva";353;1
"Unit";"Zergling";"Larva";353;1
"Unit";"Zergling";"Larva";353;1
"Unit";"Zergling";"Larva";353;1
"Unit";"Zergling";"Larva";353;1
"Unit";"Zergling";"Larva";353;1
"Unit";"Zergling";"Larva";353;1
"Unit";"Zergling";"Larva";353;1
"Unit";"Zergling";"Larva";353;1
"Unit";"Zergling";"Larva";353;1
"Unit";"Zergling";"Larva";353;1
"Unit";"Zergling";"Larva";353;1
"Unit";"Zergling";"Larva";353;1
"Unit";"Zergling";"Larva";353;1
"Unit";"Zergling";"Larva";353;1
"Unit";"Zergling";"Larva";353;1
"Unit";"Zergling";"Larva";353;1
"Unit";"Zergling";"Larva";353;1
"Unit";"Zergling";"Larva";353;1
"Unit";"Zergling";"Larva";353;1
"Unit";"Zergling";"Larva";353;1
"Unit";"Zergling";"Larva";353;1
"Unit";"Zergling";"Larva";353;1
"Unit";"Zergling";"Larva";353;1
"Unit";"Zergling";"Larva";353;1
"Building";"Extractor";NA;353;0
"Unit";"Baneling";"Zergling";387;0
"Unit";"Baneling";"Zergling";387;0
"Unit";"Baneling";"Zergling";387;0
"Unit";"Baneling";"Zergling";387;0
"Unit";"Baneling";"Zergling";387;0
"Unit";"Baneling";"Zergling";387;0
"Unit";"Baneling";"Zergling";387;0
"Unit";"Baneling";"Zergling";387;0
"Unit";"Baneling";"Zergling";387;0
"Unit";"Baneling";"Zergling";387;0
"Building";"CreepTumor";NA;387;0
"Building";"CreepTumor";NA;387;0
"Building";"CreepTumor";NA;387;0
"Building";"CreepTumor";NA;387;0
"Building";"CreepTumor";NA;387;0
"Building";"CreepTumorQueen";NA;387;0
"Building";"CreepTumor";NA;387;0
"Building";"Extractor";NA;387;0
"Unit";"Corruptor";"Larva";387;2
"Unit";"Corruptor";"Larva";387;2
"Unit";"Corruptor";"Larva";387;2
"Unit";"Corruptor";"Larva";387;2
"Unit";"Corruptor";"Larva";387;2
"Unit";"Corruptor";"Larva";387;2
"Unit";"Corruptor";"Larva";387;2
"Unit";"Baneling";"Zergling";387;0
"Unit";"Baneling";"Zergling";387;0
"Unit";"Baneling";"Zergling";387;0
"Unit";"Baneling";"Zergling";387;0
"Unit";"Baneling";"Zergling";387;0
"Unit";"Zergling";"Larva";387;1
"Unit";"Zergling";"Larva";387;1
"Unit";"Zergling";"Larva";387;1
"Unit";"Zergling";"Larva";387;1
"Unit";"Zergling";"Larva";387;1
"Unit";"Zergling";"Larva";387;1
"Unit";"Zergling";"Larva";387;1
"Unit";"Zergling";"Larva";387;1
"Building";"Spire";NA;387;0
"Building";"SporeCrawler";NA;409;0
"Building";"SpineCrawler";NA;409;0
"Unit";"Corruptor";"Larva";409;2
"Unit";"Corruptor";"Larva";409;2
"Unit";"Corruptor";"Larva";409;2
"Unit";"Corruptor";"Larva";409;2
"Unit";"Zergling";"Larva";409;1
"Unit";"Zergling";"Larva";409;1
"Unit";"Zergling";"Larva";409;1
"Unit";"Zergling";"Larva";409;1
"Unit";"Zergling";"Larva";409;1
"Unit";"Zergling";"Larva";409;1
"Unit";"Zergling";"Larva";409;1
"Unit";"Zergling";"Larva";409;1
"Unit";"Zergling";"Larva";409;1
"Unit";"Zergling";"Larva";409;1
"Unit";"Zergling";"Larva";417;1
"Unit";"Zergling";"Larva";417;1
"Unit";"Zergling";"Larva";417;1
"Unit";"Zergling";"Larva";417;1
"Unit";"Zergling";"Larva";417;1
"Unit";"Zergling";"Larva";417;1
"Unit";"Zergling";"Larva";417;1
"Unit";"Zergling";"Larva";417;1
"Unit";"Zergling";"Larva";417;1
"Unit";"Zergling";"Larva";417;1
"Unit";"Zergling";"Larva";417;1
"Unit";"Zergling";"Larva";417;1
"Unit";"Zergling";"Larva";417;1
"Unit";"Zergling";"Larva";417;1
"Unit";"Zergling";"Larva";417;1
"Unit";"Zergling";"Larva";417;1
"Unit";"Zergling";"Larva";417;1
"Unit";"Zergling";"Larva";417;1
"Unit";"Zergling";"Larva";417;1
"Unit";"Zergling";"Larva";417;1
"Unit";"Zergling";"Larva";417;1
"Unit";"Zergling";"Larva";417;1
"Unit";"Zergling";"Larva";417;1
"Unit";"Zergling";"Larva";417;1
"Unit";"Zergling";"Larva";417;1
"Unit";"Zergling";"Larva";417;1
"Unit";"Zergling";"Larva";417;1
"Unit";"Zergling";"Larva";417;1
"Unit";"Zergling";"Larva";417;1
"Unit";"Zergling";"Larva";417;1
"Unit";"Zergling";"Larva";417;1
"Unit";"Zergling";"Larva";417;1
"Unit";"Zergling";"Larva";417;1
"Unit";"Zergling";"Larva";417;1
"Unit";"Zergling";"Larva";417;1
"Unit";"Zergling";"Larva";417;1
"Unit";"Zergling";"Larva";417;1
"Unit";"Zergling";"Larva";417;1
"Building";"CreepTumor";NA;427;0
"Building";"CreepTumor";NA;427;0
"Building";"CreepTumor";NA;427;0
"Building";"CreepTumor";NA;427;0
"Building";"CreepTumor";NA;465;0
"Building";"Extractor";NA;417;0
"Building";"Extractor";NA;425;0
"Building";"CreepTumor";NA;465;0
"Building";"CreepTumor";NA;465;0
"Building";"CreepTumor";NA;465;0
"Building";"CreepTumor";NA;465;0
"Building";"Hatchery";NA;417;0
"Unit";"Zergling";"Larva";465;1
"Unit";"Zergling";"Larva";465;1
"Unit";"Zergling";"Larva";465;1
"Unit";"Zergling";"Larva";465;1
"Unit";"Zergling";"Larva";465;1
"Unit";"Zergling";"Larva";465;1
"Unit";"Zergling";"Larva";465;1
"Unit";"Zergling";"Larva";465;1
"Unit";"Zergling";"Larva";465;1
"Unit";"Zergling";"Larva";465;1
"Unit";"Zergling";"Larva";465;1
"Unit";"Zergling";"Larva";465;1
"Unit";"Zergling";"Larva";465;1
"Unit";"Zergling";"Larva";465;1
"Unit";"Zergling";"Larva";465;1
"Unit";"Zergling";"Larva";465;1
"Unit";"Zergling";"Larva";465;1
"Unit";"Zergling";"Larva";465;1
"Unit";"Zergling";"Larva";465;1
"Unit";"Zergling";"Larva";465;1
"Unit";"Zergling";"Larva";465;1
"Unit";"Zergling";"Larva";465;1
"Unit";"Zergling";"Larva";465;1
"Unit";"Zergling";"Larva";465;1
"Unit";"Zergling";"Larva";465;1
"Unit";"Zergling";"Larva";465;1
"Unit";"Zergling";"Larva";465;1
"Unit";"Zergling";"Larva";465;1
"Unit";"Zergling";"Larva";465;1
"Unit";"Zergling";"Larva";465;1
"Unit";"Zergling";"Larva";465;1
"Unit";"Zergling";"Larva";465;1
"Unit";"Zergling";"Larva";465;1
"Unit";"Zergling";"Larva";465;1
"Unit";"Zergling";"Larva";465;1
"Unit";"Zergling";"Larva";465;1
"Unit";"Zergling";"Larva";465;1
"Unit";"Zergling";"Larva";465;1
"Unit";"Zergling";"Larva";465;1
"Unit";"Zergling";"Larva";465;1
"Unit";"Zergling";"Larva";465;1
"Unit";"Zergling";"Larva";465;1
"Unit";"Zergling";"Larva";465;1
"Unit";"Zergling";"Larva";465;1
"Unit";"Zergling";"Larva";465;1
"Unit";"Zergling";"Larva";465;1
"Unit";"Zergling";"Larva";465;1
"Unit";"Zergling";"Larva";465;1
"Unit";"Zergling";"Larva";465;1
"Unit";"Zergling";"Larva";465;1
"Upgrade";"Burrow";"Hatchery";465;0
"Upgrade";"ZergMeleeWeaponsLevel3";"EvolutionChamber";465;0
"Unit";"Zergling";"Larva";515;1
"Unit";"Zergling";"Larva";515;1
"Unit";"Zergling";"Larva";515;1
"Unit";"Zergling";"Larva";515;1
"Unit";"Zergling";"Larva";515;1
"Unit";"Zergling";"Larva";515;1
"Unit";"Zergling";"Larva";515;1
"Unit";"Zergling";"Larva";515;1
"Unit";"Zergling";"Larva";515;1
"Unit";"Zergling";"Larva";515;1
"Unit";"Zergling";"Larva";515;1
"Unit";"Zergling";"Larva";515;1
"Unit";"Zergling";"Larva";515;1
"Unit";"Zergling";"Larva";515;1
"Unit";"Zergling";"Larva";515;1
"Unit";"Zergling";"Larva";515;1
"Unit";"Zergling";"Larva";515;1
"Unit";"Zergling";"Larva";515;1
"Unit";"Zergling";"Larva";515;1
"Unit";"Zergling";"Larva";515;1
"Unit";"Zergling";"Larva";515;1
"Unit";"Zergling";"Larva";515;1
"Unit";"Zergling";"Larva";515;1
"Unit";"Zergling";"Larva";515;1
"Unit";"Zergling";"Larva";515;1
"Unit";"Zergling";"Larva";515;1
"Unit";"Zergling";"Larva";515;1
"Unit";"Zergling";"Larva";515;1
"Unit";"Baneling";"Zergling";515;0
"Unit";"Baneling";"Zergling";515;0
"Unit";"Baneling";"Zergling";515;0
"Unit";"Baneling";"Zergling";515;0
"Unit";"Baneling";"Zergling";515;0
"Unit";"Baneling";"Zergling";515;0
"Unit";"Baneling";"Zergling";515;0
"Unit";"Baneling";"Zergling";515;0
"Unit";"Baneling";"Zergling";515;0
"Unit";"Baneling";"Zergling";515;0
"Upgrade";"ZergGroundArmorsLevel3";"EvolutionChamber";465;0
"Unit";"Zergling";"Larva";543;1
"Unit";"Zergling";"Larva";543;1
"Unit";"Zergling";"Larva";543;1
"Unit";"Zergling";"Larva";543;1
"Unit";"Zergling";"Larva";543;1
"Unit";"Zergling";"Larva";543;1
"Unit";"Zergling";"Larva";543;1
"Unit";"Zergling";"Larva";543;1
"Unit";"Zergling";"Larva";543;1
"Unit";"Zergling";"Larva";543;1
"Unit";"Zergling";"Larva";543;1
"Unit";"Zergling";"Larva";543;1
"Unit";"Zergling";"Larva";543;1
"Unit";"Zergling";"Larva";543;1
"Unit";"Zergling";"Larva";543;1
"Unit";"Zergling";"Larva";543;1
"Unit";"Zergling";"Larva";543;1
"Unit";"Zergling";"Larva";543;1
"Unit";"Corruptor";"Larva";543;2
"Unit";"Corruptor";"Larva";543;2
"Unit";"Zergling";"Larva";565;1
"Unit";"Zergling";"Larva";565;1
"Unit";"Zergling";"Larva";565;1
"Unit";"Zergling";"Larva";565;1
"Unit";"Zergling";"Larva";565;1
"Unit";"Zergling";"Larva";565;1
"Unit";"Zergling";"Larva";565;1
"Unit";"Zergling";"Larva";565;1
"Unit";"Zergling";"Larva";565;1
"Unit";"Zergling";"Larva";565;1
"Unit";"Zergling";"Larva";565;1
"Unit";"Zergling";"Larva";565;1
"Unit";"Zergling";"Larva";565;1
"Unit";"Zergling";"Larva";565;1
"Unit";"Zergling";"Larva";565;1
"Unit";"Zergling";"Larva";565;1
"Unit";"Zergling";"Larva";565;1
"Unit";"Zergling";"Larva";565;1
"Unit";"Zergling";"Larva";565;1
"Unit";"Zergling";"Larva";565;1
"Unit";"Zergling";"Larva";565;1
"Unit";"Zergling";"Larva";565;1
"Unit";"Zergling";"Larva";565;1
"Unit";"Zergling";"Larva";565;1
"Unit";"Zergling";"Larva";565;1
"Unit";"Zergling";"Larva";565;1
"Unit";"Zergling";"Larva";565;1
"Unit";"Zergling";"Larva";565;1
"Unit";"Zergling";"Larva";565;1
"Unit";"Zergling";"Larva";565;1
"Unit";"Zergling";"Larva";565;1
"Unit";"Zergling";"Larva";565;1
"Unit";"Zergling";"Larva";565;1
"Unit";"Zergling";"Larva";565;1
"Unit";"Zergling";"Larva";565;1
"Unit";"Zergling";"Larva";565;1
"Unit";"Zergling";"Larva";565;1
"Unit";"Zergling";"Larva";565;1
"Unit";"Zergling";"Larva";565;1
"Unit";"Zergling";"Larva";565;1
"Unit";"Zergling";"Larva";565;1
"Unit";"Zergling";"Larva";565;1
"Unit";"Zergling";"Larva";587;1
"Unit";"Zergling";"Larva";587;1
"Unit";"Zergling";"Larva";587;1
"Unit";"Zergling";"Larva";587;1
"Unit";"Zergling";"Larva";587;1
"Unit";"Zergling";"Larva";587;1
"Unit";"Zergling";"Larva";587;1
"Unit";"Zergling";"Larva";587;1
"Unit";"Zergling";"Larva";587;1
"Unit";"Zergling";"Larva";587;1
"Unit";"Zergling";"Larva";607;1
"Unit";"Zergling";"Larva";607;1
"Unit";"Zergling";"Larva";607;1
"Unit";"Zergling";"Larva";607;1
"Unit";"Zergling";"Larva";607;1
"Unit";"Zergling";"Larva";607;1
"Unit";"Zergling";"Larva";607;1
"Unit";"Zergling";"Larva";607;1
"Building";"CreepTumor";NA;625;0
"Building";"CreepTumor";NA;625;0
"Building";"CreepTumor";NA;625;0
"Building";"CreepTumor";NA;625;0
"Building";"CreepTumor";NA;625;0
"Unit";"Zergling";"Larva";625;1
"Unit";"Zergling";"Larva";625;1
"Unit";"Zergling";"Larva";625;1
"Unit";"Zergling";"Larva";625;1
"Unit";"Corruptor";"Larva";625;2
"Unit";"Corruptor";"Larva";625;2
"Unit";"Corruptor";"Larva";625;2
"Unit";"Corruptor";"Larva";625;2
"Unit";"Corruptor";"Larva";625;2
"Unit";"Corruptor";"Larva";625;2
"Unit";"Corruptor";"Larva";625;2
"Unit";"Corruptor";"Larva";625;2
"Unit";"Corruptor";"Larva";625;2
"Unit";"Corruptor";"Larva";625;2
"Unit";"Baneling";"Zergling";626;0
"Unit";"Baneling";"Zergling";626;0
"Unit";"Baneling";"Zergling";626;0
"Unit";"Baneling";"Zergling";626;0
"Unit";"Baneling";"Zergling";626;0
"Unit";"Baneling";"Zergling";626;0
"Unit";"Baneling";"Zergling";626;0
"Unit";"Baneling";"Zergling";626;0
"Unit";"Baneling";"Zergling";626;0
"Unit";"Baneling";"Zergling";626;0
"Unit";"Zergling";"Larva";626;1
"Unit";"Zergling";"Larva";626;1
"Unit";"Zergling";"Larva";626;1
"Unit";"Zergling";"Larva";626;1
"Unit";"Zergling";"Larva";626;1
"Unit";"Zergling";"Larva";626;1
"Building";"CreepTumor";NA;656;0
"Building";"CreepTumor";NA;656;0
"Unit";"Zergling";"Larva";656;1
"Unit";"Zergling";"Larva";656;1
"Unit";"Zergling";"Larva";656;1
"Unit";"Zergling";"Larva";656;1
"Unit";"Zergling";"Larva";656;1
"Unit";"Zergling";"Larva";656;1
"Unit";"Zergling";"Larva";656;1
"Unit";"Zergling";"Larva";656;1
"Unit";"Zergling";"Larva";656;1
"Unit";"Zergling";"Larva";656;1
"Unit";"Zergling";"Larva";656;1
"Unit";"Zergling";"Larva";656;1
"Unit";"Zergling";"Larva";656;1
"Unit";"Zergling";"Larva";656;1
"Unit";"Zergling";"Larva";656;1
"Unit";"Zergling";"Larva";656;1
"Unit";"Corruptor";"Larva";650;2
"Unit";"Corruptor";"Larva";650;2
"Unit";"Corruptor";"Larva";650;2
"Unit";"Corruptor";"Larva";656;2
"Unit";"Zergling";"Larva";680;1
"Unit";"Zergling";"Larva";680;1
"Unit";"Zergling";"Larva";680;1
"Unit";"Zergling";"Larva";680;1
"Unit";"Zergling";"Larva";680;1
"Unit";"Zergling";"Larva";680;1
"Unit";"Zergling";"Larva";680;1
"Unit";"Zergling";"Larva";680;1
"Unit";"Zergling";"Larva";680;1
"Unit";"Zergling";"Larva";680;1
"Unit";"Zergling";"Larva";680;1
"Unit";"Zergling";"Larva";680;1
"Unit";"Zergling";"Larva";680;1
"Unit";"Zergling";"Larva";680;1
"Unit";"Zergling";"Larva";680;1
"Unit";"Zergling";"Larva";680;1
"Unit";"Zergling";"Larva";680;1
"Unit";"Zergling";"Larva";680;1
"Unit";"Zergling";"Larva";680;1
"Unit";"Zergling";"Larva";680;1
"Unit";"Zergling";"Larva";680;1
"Unit";"Zergling";"Larva";680;1
"Unit";"Zergling";"Larva";680;1
"Unit";"Zergling";"Larva";680;1
"Unit";"Zergling";"Larva";680;1
"Unit";"Zergling";"Larva";680;1
"Building";"CreepTumorQueen";NA;680;0
"Building";"CreepTumor";NA;680;0
"Building";"CreepTumor";NA;680;0
"Building";"CreepTumor";NA;680;0
"Upgrade";"ZergMissileWeaponsLevel2";"EvolutionChamber";678;0
"Unit";"Zergling";"Larva";706;1
"Unit";"Zergling";"Larva";706;1
"Unit";"Zergling";"Larva";706;1
"Unit";"Zergling";"Larva";706;1
"Unit";"Zergling";"Larva";706;1
"Unit";"Zergling";"Larva";706;1
"Unit";"Zergling";"Larva";706;1
"Unit";"Zergling";"Larva";706;1
"Unit";"Zergling";"Larva";706;1
"Unit";"Zergling";"Larva";706;1
"Unit";"Zergling";"Larva";706;1
"Unit";"Zergling";"Larva";706;1
"Building";"Hatchery";NA;680;0
"Building";"Hatchery";NA;706;0
"Unit";"Zergling";"Larva";718;1
"Unit";"Zergling";"Larva";718;1
"Unit";"Zergling";"Larva";718;1
"Unit";"Zergling";"Larva";718;1
"Unit";"Zergling";"Larva";718;1
"Unit";"Zergling";"Larva";718;1
"Unit";"Zergling";"Larva";718;1
"Unit";"Zergling";"Larva";718;1
"Unit";"Zergling";"Larva";718;1
"Unit";"Zergling";"Larva";718;1
"Unit";"Zergling";"Larva";718;1
"Unit";"Zergling";"Larva";718;1
"Unit";"Zergling";"Larva";718;1
"Unit";"Zergling";"Larva";718;1
"Building";"Hatchery";NA;706;0
"Unit";"Zergling";"Larva";718;1
"Unit";"Zergling";"Larva";718;1
